{
  "type": "Feature",
  "properties": {
    "iso:country":"CH",
    "sg:address":"Menznauerstrasse 73 6110 Wolhusen. Postfach 62",
    "sg:city":"Wolhusen",
    "sg:orig_category":"Herstellung von M\u00f6beln",
    "sg:phone":"+41 41 490 17 55",
    "sg:postcode":"6110",
    "sg:province":"Luzern",
    "wof:name":"Dreisternm\u00f6bel-m\u00f6belfabrik Ag Wolhusen",
    "wof:placetype":"venue"
},
  "geometry": {"coordinates":[8.0702590942,47.0650749207],"type":"Point"}
}