{
  "type": "Feature",
  "properties": {
    "iso:country":"CH",
    "sg:address":"Transversale De L'autoroute 5 1926 Fully. Postfach",
    "sg:city":"Fully",
    "sg:orig_category":"Instandhaltung U Reparatur von Automobilen",
    "sg:postcode":"1926",
    "sg:province":"Valais",
    "wof:name":"Sam Automobiles S\u00e0rl Garage Etc",
    "wof:placetype":"venue"
},
  "geometry": {"coordinates":[7.1268391609,46.1316184998],"type":"Point"}
}