{
  "type": "Feature",
  "properties": {
    "addr:full":"Glattalstrasse 505 R\u00fcmlang Z\u00fcrich 8153",
    "addr:housenumber":"505",
    "addr:postcode":"8153",
    "addr:street":"Glattalstrasse;Zuerich",
    "iso:country":"CH",
    "sg:address":"Glattalstrasse 505",
    "sg:city":"R\u00fcmlang",
    "sg:orig_category":"Betrieb U technische Hilfsdienste des Kultur U Unterhaltungswesens",
    "sg:phone":"+41 18181133",
    "sg:postcode":"8153",
    "sg:province":"Z\u00fcrich",
    "wof:name":"Disciple Music, Galfano D.",
    "wof:placetype":"venue"
},
  "geometry": {"coordinates":[8.542779,47.433594],"type":"Point"}
}