{
  "type": "Feature",
  "properties": {
    "iso:country":"CH",
    "sg:address":"Hauptstrasse 100c",
    "sg:city":"Churwalden",
    "sg:orig_category":"Handel mit Automobilen",
    "sg:postcode":"7075",
    "sg:province":"Graubunden",
    "wof:name":"J\u00e4ger Automobile",
    "wof:placetype":"venue"
},
  "geometry": {"coordinates":[9.5423164368,46.7822494507],"type":"Point"}
}