{
  "type": "Feature",
  "properties": {
    "addr:full":"Bleikenstrasse 56 Wattwil St. Gallen 9630",
    "addr:housenumber":"56",
    "addr:postcode":"9630",
    "addr:street":"Bleikenstrasse",
    "iso:country":"CH",
    "sg:address":"Bleikenstrasse 56",
    "sg:city":"Wattwil",
    "sg:classifiers":[
        {
            "category":"Structure",
            "subcategory":"Bridge",
            "type":"Public Place"
        }
    ],
    "sg:phone":"+41 71 987 30 40",
    "sg:postcode":"9630",
    "sg:province":"St. Gallen",
    "sg:tags":[
        "construction"
    ],
    "wof:name":"Pozzi Ag",
    "wof:placetype":"venue"
},
  "geometry": {"coordinates":[9.08957,47.290321],"type":"Point"}
}