{
  "type": "Feature",
  "properties": {
    "iso:country":"CH",
    "sg:address":"Via Zandone",
    "sg:city":"Losone",
    "sg:classifiers":[
        {
            "category":"Retail",
            "subcategory":"Auto Repair",
            "type":"Services"
        }
    ],
    "sg:phone":"+41 91 791 89 41",
    "sg:postcode":"6616",
    "sg:province":"Ticino",
    "sg:tags":[
        "machine",
        "abrasive",
        "cut-off"
    ],
    "wof:name":"F. Boccadoro Sa",
    "wof:placetype":"venue"
},
  "geometry": {"coordinates":[8.737174,46.179207],"type":"Point"}
}