{
  "type": "Feature",
  "properties": {
    "iso:country":"CH",
    "sg:address":"Avenue Gustave-coindet 6",
    "sg:city":"Vevey",
    "sg:orig_category":"Maurerarbeiten",
    "sg:phone":"+41 21 921 37 19",
    "sg:postcode":"1800",
    "sg:province":"Vaud",
    "wof:name":"Eug\u00e8ne Th\u00e9raulaz Entreprise De Ma\u00e7onnerie",
    "wof:placetype":"venue"
},
  "geometry": {"coordinates":[6.8390421867,46.4624710083],"type":"Point"}
}