{
  "type": "Feature",
  "properties": {
    "iso:country":"CH",
    "sg:address":"Rue St-pierre 10",
    "sg:city":"Fribourg",
    "sg:orig_category":"Arztpraxen",
    "sg:phone":"+41 26 322 20 22",
    "sg:postcode":"1700",
    "sg:province":"Fribourg",
    "wof:name":"Dr M\u00e9d. Paul Rwakabayiza M\u00e9decin Sp\u00e9cialiste Fmh",
    "wof:placetype":"venue"
},
  "geometry": {"coordinates":[7.155527,46.80397],"type":"Point"}
}