{
  "type": "Feature",
  "properties": {
    "iso:country":"CH",
    "sg:address":"Industriestrasse 12 8212 Neuhausen. Postfach 708",
    "sg:city":"Neuhausen",
    "sg:orig_category":"Wirtschaftspr\u00fcfung, Steuerberatung U Treuhand",
    "sg:phone":"+41 52 672 77 20",
    "sg:postcode":"8212",
    "sg:province":"Schaffhausen",
    "wof:name":"Inter Treuhand Marino Gmbh",
    "wof:placetype":"venue"
},
  "geometry": {"coordinates":[8.6183223724,47.6800231934],"type":"Point"}
}