{
  "type": "Feature",
  "properties": {
    "iso:country":"CH",
    "sg:address":"Place Vingt-deux-cantons 3",
    "sg:city":"Gen\u00e8ve",
    "sg:orig_category":"Detailhandel mit B\u00fcchern, Zeitungen, Schreib U Papeteriewaren Detailhandel mit Spielwaren",
    "sg:phone":"+41 55 644 12 57",
    "sg:postcode":"1201",
    "sg:province":"Gen\u00e8ve",
    "wof:name":"Wild Ag, Schwanden",
    "wof:placetype":"venue"
},
  "geometry": {"coordinates":[9.074473,46.994251],"type":"Point"}
}