{
  "type": "Feature",
  "properties": {
    "iso:country":"CH",
    "sg:address":"Br\u00fcckenweg 15",
    "sg:city":"Oberwichtrach",
    "sg:orig_category":"Blumen U Zierpflanzenbau",
    "sg:phone":"+41 31 781 10 08",
    "sg:postcode":"3114",
    "sg:province":"Bern",
    "wof:name":"Werner Liebi G\u00e4rtnerei",
    "wof:placetype":"venue"
},
  "geometry": {"coordinates":[7.576506,46.843365],"type":"Point"}
}