{
  "type": "Feature",
  "properties": {
    "iso:country":"CH",
    "sg:address":"Schulstrasse 5",
    "sg:city":"Schlieren",
    "sg:orig_category":"Detailhandel mit Blumen U Pflanzen",
    "sg:phone":"+41 17309184",
    "sg:postcode":"8952",
    "sg:province":"Z\u00fcrich",
    "wof:name":"Gabi Langmeier Blumenhaus Keusch",
    "wof:placetype":"venue"
},
  "geometry": {"coordinates":[8.449813,47.396702],"type":"Point"}
}