{
  "type": "Feature",
  "properties": {
    "addr:full":"Route De Begnins 1 Gland Vaud 1196",
    "addr:housenumber":"1",
    "addr:postcode":"1196",
    "addr:street":"Route De Begnins",
    "iso:country":"CH",
    "sg:address":"Route De Begnins 1",
    "sg:city":"Gland",
    "sg:orig_category":"Bars Verwaltung von Immobilien",
    "sg:phone":"+41 22 364 10 48",
    "sg:postcode":"1196",
    "sg:province":"Vaud",
    "wof:name":"Pub 1340, Joubert Thierry",
    "wof:placetype":"venue"
},
  "geometry": {"coordinates":[6.268883,46.420235],"type":"Point"}
}