{
  "type": "Feature",
  "properties": {
    "iso:country":"CH",
    "sg:address":"An Der Halde 5",
    "sg:city":"Triesen",
    "sg:orig_category":"Innendekorationsateliers",
    "sg:phone":"+423 392 21 44",
    "sg:postcode":"9495",
    "wof:name":"Ren\u00e9 H\u00e4nni Tapezierer-dekorateur",
    "wof:placetype":"venue"
},
  "geometry": {"coordinates":[9.5263433456,47.1096611023],"type":"Point"}
}