{
  "type": "Feature",
  "properties": {
    "iso:country":"CH",
    "sg:address":"Grenzacherstrasse 210",
    "sg:city":"Basel",
    "sg:orig_category":"Museen",
    "sg:phone":"+41 61 681 93 20",
    "sg:postcode":"4058",
    "sg:province":"Basel-Stadt",
    "wof:name":"Museum Jean Tinguely",
    "wof:placetype":"venue"
},
  "geometry": {"coordinates":[7.6106410027,47.5592193604],"type":"Point"}
}