{
  "type": "Feature",
  "properties": {
    "addr:full":"Wartstrasse 21 Winterthur Z\u00fcrich 8400",
    "addr:housenumber":"21",
    "addr:postcode":"8400",
    "addr:street":"Wartstrasse",
    "iso:country":"CH",
    "sg:address":"Wartstrasse 21",
    "sg:city":"Winterthur",
    "sg:orig_category":"Detailhandel mit Bekleidung",
    "sg:postcode":"8400",
    "sg:province":"Z\u00fcrich",
    "wof:name":"Dolcevita, Wohlwend Eva Textil Boutique",
    "wof:placetype":"venue"
},
  "geometry": {"coordinates":[9.462694,47.16938],"type":"Point"}
}