{
  "type": "Feature",
  "properties": {
    "iso:country":"CH",
    "sg:address":"Glattalstrasse 212",
    "sg:city":"R\u00fcmlang",
    "sg:orig_category":"Detailhandel mit Haustieren U zoologischem Bedarf Fachdetailhandel in Verkaufsr\u00e4umen",
    "sg:phone":"+41 71 311 84 15",
    "sg:postcode":"8153",
    "sg:province":"Z\u00fcrich",
    "wof:name":"Qualipet Ag Haustierbedarfs-center",
    "wof:placetype":"venue"
},
  "geometry": {"coordinates":[9.3136148453,47.4147872925],"type":"Point"}
}