{
  "type": "Feature",
  "properties": {
    "iso:country":"CH",
    "sg:address":"Via Mondasc 1 6514 Sementina. Postfach",
    "sg:city":"Sementina",
    "sg:orig_category":"Sonstiger spezialisierter Hoch U Tiefbau",
    "sg:postcode":"6514",
    "sg:province":"Ticino",
    "wof:name":"Scialpi Sagl",
    "wof:placetype":"venue"
},
  "geometry": {"coordinates":[8.9948472977,46.1798286438],"type":"Point"}
}