{
  "type": "Feature",
  "properties": {
    "iso:country":"CH",
    "sg:address":"Sonnenh\u00fcgel 5",
    "sg:city":"T\u00e4gerschen",
    "sg:orig_category":"Sportvereine Turnen Vereine Damen",
    "sg:phone":"+41 71 917 17 14",
    "sg:postcode":"9554",
    "sg:province":"Thurgau",
    "wof:name":"Frauenturnverein Tobel",
    "wof:placetype":"venue"
},
  "geometry": {"coordinates":[9.0315618515,47.5101318359],"type":"Point"}
}