{
  "type": "Feature",
  "properties": {
    "iso:country":"CH",
    "sg:address":"Limmatstrasse 217",
    "sg:city":"Z\u00fcrich",
    "sg:orig_category":"Softwareentwicklung U beratung Sonstige mit der Informatik verbundene T\u00e4tigkeiten",
    "sg:phone":"+41 12737121",
    "sg:postcode":"8005",
    "sg:province":"Z\u00fcrich",
    "wof:name":"Adet Projekt Management Gmbh",
    "wof:placetype":"venue"
},
  "geometry": {"coordinates":[8.5272464752,47.3876075745],"type":"Point"}
}