{
  "type": "Feature",
  "properties": {
    "iso:country":"CH",
    "sg:address":"Geissberg",
    "sg:city":"Wolfhausen",
    "sg:orig_category":"Grosshandel mit lebenden Tieren",
    "sg:phone":"+41 55 243 12 28",
    "sg:postcode":"8633",
    "sg:province":"Z\u00fcrich",
    "wof:name":"Franz Thoma Viehhandel",
    "wof:placetype":"venue"
},
  "geometry": {"coordinates":[8.8075647354,47.2540931702],"type":"Point"}
}