{
  "type": "Feature",
  "properties": {
    "addr:full":"Winkelhalde 1 Grosswangen Luzern 6022",
    "addr:housenumber":"1",
    "addr:postcode":"6022",
    "addr:street":"Winkelhalde",
    "iso:country":"CH",
    "sg:address":"Winkelhalde 1",
    "sg:city":"Grosswangen",
    "sg:classifiers":[
        {
            "category":"Banks & Credit Unions",
            "subcategory":"Bank",
            "type":"Services"
        }
    ],
    "sg:phone":"+41 4145712883",
    "sg:postcode":"6022",
    "sg:province":"Luzern",
    "wof:name":"Schweiz. Mobiliar",
    "wof:placetype":"venue"
},
  "geometry": {"coordinates":[8.046995,47.129498],"type":"Point"}
}