{
  "type": "Feature",
  "properties": {
    "iso:country":"CH",
    "sg:address":"4323",
    "sg:city":"Wallbach",
    "sg:orig_category":"Politische Parteien SVP",
    "sg:postcode":"4323",
    "sg:province":"Aargau",
    "wof:name":"Svp Ortsparteipr\u00e4sident",
    "wof:placetype":"venue"
},
  "geometry": {"coordinates":[7.8947701454,47.5680618286],"type":"Point"}
}