{
  "type": "Feature",
  "properties": {
    "iso:country":"CH",
    "sg:address":"Hochfelderstrasse 3 8180 B\u00fclach. Postfach",
    "sg:city":"B\u00fclach",
    "sg:orig_category":"RESTAURANTS: TEA-ROOMS",
    "sg:postcode":"8180",
    "sg:province":"Z\u00fcrich",
    "wof:name":"Vinsa Gmbh Gastronomiebetriebe. Waren; Im, Export, Handel",
    "wof:placetype":"venue"
},
  "geometry": {"coordinates":[8.537484169,47.5191307068],"type":"Point"}
}