{
  "type": "Feature",
  "properties": {
    "iso:country":"CH",
    "sg:address":"7559",
    "sg:city":"Tschlin",
    "sg:orig_category":"Primarschulen",
    "sg:phone":"+41 81 866 34 92",
    "sg:postcode":"7559",
    "sg:province":"Graubunden",
    "wof:name":"Primarschule",
    "wof:placetype":"venue"
},
  "geometry": {"coordinates":[10.4146795273,46.9042701721],"type":"Point"}
}