{
  "type": "Feature",
  "properties": {
    "iso:country":"CH",
    "sg:address":"Luzernerstrasse 20 6330 Cham. Postfach 357",
    "sg:city":"Cham",
    "sg:classifiers":[
        {
            "category":"Restaurant",
            "type":"Food & Drink"
        }
    ],
    "sg:phone":"+41 79 667 88 08",
    "sg:postcode":"6330",
    "sg:province":"Zug",
    "wof:name":"Restaurant Raben",
    "wof:placetype":"venue"
},
  "geometry": {"coordinates":[8.4577074051,47.1795463562],"type":"Point"}
}