{
  "type": "Feature",
  "properties": {
    "iso:country":"CH",
    "sg:address":"Gen\u00e8ve Rue De 84 1004 Lausanne. Postfach",
    "sg:city":"Lausanne",
    "sg:orig_category":"Pensionskassen",
    "sg:postcode":"1003",
    "sg:province":"Vaud",
    "wof:name":"Fondation De Pr\u00e9voyance En Faveur Du Personnel De Durafourg Sa",
    "wof:placetype":"venue"
},
  "geometry": {"coordinates":[6.614648819,46.5248641968],"type":"Point"}
}