{
  "type": "Feature",
  "properties": {
    "iso:country":"CH",
    "sg:address":"Dorfstrasse 12",
    "sg:city":"Feusisberg",
    "sg:orig_category":"Bau von Strassen, Sportanlagen U Bahnverkehrsstrecken Gartenbau",
    "sg:phone":"+41 17863933",
    "sg:postcode":"8835",
    "sg:province":"Schwyz",
    "wof:name":"Vonplon R. Ag",
    "wof:placetype":"venue"
},
  "geometry": {"coordinates":[8.743295,47.18494],"type":"Point"}
}