{
  "type": "Feature",
  "properties": {
    "iso:country":"CH",
    "sg:address":"Glaserbergstrasse 21",
    "sg:city":"Basel",
    "sg:orig_category":"Werbung",
    "sg:phone":"+41 61 322 81 38",
    "sg:postcode":"4056",
    "sg:province":"Basel-Stadt",
    "wof:name":"Art Et Technique, Franco Rainoni",
    "wof:placetype":"venue"
},
  "geometry": {"coordinates":[7.5695757866,47.56690979],"type":"Point"}
}