{
  "type": "Feature",
  "properties": {
    "iso:country":"CH",
    "sg:address":"Centralstrasse 9",
    "sg:city":"Sursee",
    "sg:classifiers":[
        {
            "category":"Government",
            "subcategory":"Post Office",
            "type":"Public Place"
        }
    ],
    "sg:phone":"+41 41 926 60 00",
    "sg:postcode":"6210",
    "sg:province":"Luzern",
    "sg:tags":[
        "die",
        "poststellen"
    ],
    "wof:name":"Die Schweizerische Post",
    "wof:placetype":"venue"
},
  "geometry": {"coordinates":[8.1068134308,47.1716346741],"type":"Point"}
}