{
  "type": "Feature",
  "properties": {
    "iso:country":"CH",
    "sg:address":"Winkelstrasse 3",
    "sg:city":"Oftringen",
    "sg:orig_category":"Allgemeiner Gartenbau Dienstleistungen im Gartenbau",
    "sg:phone":"+41 32 351 61 38",
    "sg:postcode":"4665",
    "sg:province":"Aargau",
    "wof:name":"Fahrni's G\u00e4rten",
    "wof:placetype":"venue"
},
  "geometry": {"coordinates":[7.363203,47.140095],"type":"Point"}
}