{
  "type": "Feature",
  "properties": {
    "iso:country":"CH",
    "sg:address":"Grossfeldstrasse 3",
    "sg:city":"Kriens",
    "sg:orig_category":"Kauf U Verkauf von Immobilien auf eigene Rechnung",
    "sg:postcode":"6010",
    "sg:province":"Luzern",
    "wof:name":"Sanatio Ag",
    "wof:placetype":"venue"
},
  "geometry": {"coordinates":[8.2835140228,47.0335769653],"type":"Point"}
}