{
  "type": "Feature",
  "properties": {
    "iso:country":"CH",
    "sg:address":"Geisshaldenalp",
    "sg:city":"Eggiwil",
    "sg:orig_category":"Wohnheime",
    "sg:phone":"+41 34 491 16 37",
    "sg:postcode":"3537",
    "sg:province":"Bern",
    "wof:name":"Ferienheim Erika",
    "wof:placetype":"venue"
},
  "geometry": {"coordinates":[7.795882225,46.8750648499],"type":"Point"}
}