{
  "type": "Feature",
  "properties": {
    "iso:country":"CH",
    "sg:address":"Raihaltenstrasse 41 8912 Obfelden. Postfach 104",
    "sg:city":"Obfelden",
    "sg:orig_category":"Sonstige mit der Informatik verbundene T\u00e4tigkeiten",
    "sg:phone":"+41 32 969 26 15",
    "sg:postcode":"8912",
    "sg:province":"Z\u00fcrich",
    "wof:name":"Novisoft Wahli C.",
    "wof:placetype":"venue"
},
  "geometry": {"coordinates":[6.8299050331,47.102809906],"type":"Point"}
}