{
  "type": "Feature",
  "properties": {
    "iso:country":"CH",
    "sg:address":"Grabenstrasse 52",
    "sg:city":"Frauenfeld",
    "sg:orig_category":"Unclassifiable Establishments",
    "sg:phone":"+41 52 720 10 34",
    "sg:postcode":"8500",
    "sg:province":"Thurgau",
    "wof:name":"Hanf Und Teeladen Eggmann",
    "wof:placetype":"venue"
},
  "geometry": {"coordinates":[8.899389267,47.5583076477],"type":"Point"}
}