{
  "type": "Feature",
  "properties": {
    "iso:country":"CH",
    "sg:address":"Steinengasse 12",
    "sg:city":"Bettingen",
    "sg:orig_category":"Herstellung von sonstigen elektrischen Ausr\u00fcstungen",
    "sg:phone":"+41 61 601 06 86",
    "sg:postcode":"4126",
    "sg:province":"Basel-Stadt",
    "wof:name":"Telecomp Team Leuenberger B.",
    "wof:placetype":"venue"
},
  "geometry": {"coordinates":[7.6674609184,47.5719490051],"type":"Point"}
}