{
  "type": "Feature",
  "properties": {
    "iso:country":"CH",
    "sg:address":"Chemin Des Bossons 21",
    "sg:city":"Lausanne",
    "sg:orig_category":"Gartenbau Landschaftsplanungsb\u00fcros U Gartenarchitekturb\u00fcros",
    "sg:phone":"+41 21 646 70 15",
    "sg:postcode":"1018",
    "sg:province":"Vaud",
    "wof:name":"Tavernese Bruno",
    "wof:placetype":"venue"
},
  "geometry": {"coordinates":[6.6205019951,46.5374412537],"type":"Point"}
}