{
  "type": "Feature",
  "properties": {
    "iso:country":"CH",
    "sg:address":"Blegistrasse 11 6340 Baar. Postfach",
    "sg:city":"Cham",
    "sg:orig_category":"Markt U Meinungsforschung",
    "sg:phone":"+41 41 748 01 80",
    "sg:postcode":"6330",
    "sg:province":"Zug",
    "wof:name":"Adtcom Network Computing Ms Ag Marketing-organisation Zur Unterst\u00fctzung Des Verkaufs Und",
    "wof:placetype":"venue"
},
  "geometry": {"coordinates":[8.5704059601,47.2158355713],"type":"Point"}
}