{
  "type": "Feature",
  "properties": {
    "iso:country":"CH",
    "sg:address":"1906",
    "sg:city":"Charrat",
    "sg:orig_category":"Herstellung von k\u00e4lte U lufttechnischen Erzeugnissen f\u00fcr gewerbliche Zwecke Lagerung",
    "sg:phone":"+41 27 746 17 02",
    "sg:postcode":"1906",
    "sg:province":"Valais",
    "wof:name":"Entrep\u00f4ts Frigorifiques De Charrat-fully & Environs Sa",
    "wof:placetype":"venue"
},
  "geometry": {"coordinates":[7.1296892166,46.1249885559],"type":"Point"}
}