{
  "type": "Feature",
  "properties": {
    "iso:country":"CH",
    "sg:address":"L\u00e4ttenwiesenstrasse 8 Glattbrugg 8152 Opfikon. Postfach",
    "sg:city":"Glattbrugg",
    "sg:orig_category":"Betrieb U technische Hilfsdienste des Kultur U Unterhaltungswesens",
    "sg:postcode":"8152",
    "sg:province":"Z\u00fcrich",
    "wof:name":"Sabor Latino Marketing, Media & Publicity, Winkler Maria",
    "wof:placetype":"venue"
},
  "geometry": {"coordinates":[8.57401,47.429298],"type":"Point"}
}