{
  "type": "Feature",
  "properties": {
    "iso:country":"CH",
    "sg:address":"Hauptstrasse 52",
    "sg:city":"H\u00fcttlingen",
    "sg:classifiers":[
        {
            "category":"Banks & Credit Unions",
            "subcategory":"Bank",
            "type":"Services"
        }
    ],
    "sg:phone":"+41 4154652222",
    "sg:postcode":"8553",
    "sg:province":"Thurgau",
    "wof:name":"Raiffeisenbank, H\u00fcttlingen-felben",
    "wof:placetype":"venue"
},
  "geometry": {"coordinates":[8.977632,47.577904],"type":"Point"}
}