{
  "type": "Feature",
  "properties": {
    "iso:country":"CH",
    "sg:address":"Klosbachstrasse 112",
    "sg:city":"Z\u00fcrich",
    "sg:orig_category":"Fussreflexzonenmassage",
    "sg:phone":"+41 12627053",
    "sg:postcode":"8032",
    "sg:province":"Z\u00fcrich",
    "wof:name":"Gisela Gensetter Fussreflexzonentherapie",
    "wof:placetype":"venue"
},
  "geometry": {"coordinates":[8.5617198944,47.3682670593],"type":"Point"}
}