{
  "type": "Feature",
  "properties": {
    "addr:full":"P\u00fcntstrasse 4 Niederhasli Z\u00fcrich 8155",
    "addr:housenumber":"4",
    "addr:postcode":"8155",
    "addr:street":"Puentstrasse",
    "iso:country":"CH",
    "sg:address":"P\u00fcntstrasse 4",
    "sg:city":"Niederhasli",
    "sg:orig_category":"Berufliche Weiterbildung, Erwachsenenbildung",
    "sg:phone":"+41 41 874 16 05",
    "sg:postcode":"8155",
    "sg:province":"Z\u00fcrich",
    "wof:name":"'webtech Seminare",
    "wof:placetype":"venue"
},
  "geometry": {"coordinates":[8.644188,46.880489],"type":"Point"}
}