{
  "type": "Feature",
  "properties": {
    "iso:country":"CH",
    "sg:address":"Industriestr. 35",
    "sg:city":"Otelfingen",
    "sg:classifiers":[
        {
            "category":"Manufacturing",
            "subcategory":"Chemicals & Compounds",
            "type":"Manufacturing & Wholesale Goods"
        }
    ],
    "sg:phone":"+41 4118445422",
    "sg:postcode":"8112",
    "sg:province":"Z\u00fcrich",
    "sg:tags":[
        "pharmaceutical",
        "chemistry",
        "-",
        "by-product"
    ],
    "wof:name":"Bostik Findley Ag",
    "wof:placetype":"venue"
},
  "geometry": {"coordinates":[8.401212,47.457188],"type":"Point"}
}