{
  "type": "Feature",
  "properties": {
    "iso:country":"CH",
    "sg:address":"Berggasse 4",
    "sg:city":"K\u00f6lliken",
    "sg:orig_category":"Bezirks, Sekundar, Realschulen, Oberstufe der Primarschulen",
    "sg:phone":"+41 62 723 38 20",
    "sg:postcode":"5742",
    "sg:province":"Aargau",
    "wof:name":"Sekundarschule",
    "wof:placetype":"venue"
},
  "geometry": {"coordinates":[8.021566,47.3354],"type":"Point"}
}