{
  "type": "Feature",
  "properties": {
    "addr:full":"Ch. De La Vo\u00ebte 33 Vallorbe Vaud 1337",
    "addr:housenumber":"33",
    "addr:postcode":"1337",
    "addr:street":"Ch. De La Voe\u0308Te",
    "iso:country":"CH",
    "sg:address":"Ch. De La Vo\u00ebte 33",
    "sg:city":"Vallorbe",
    "sg:orig_category":"Allgemeiner Hoch U Tiefbau",
    "sg:postcode":"1337",
    "sg:province":"Vaud",
    "wof:name":"Jadon Ltd, \u00e0 Londres, Succursale De Vallorbe",
    "wof:placetype":"venue"
},
  "geometry": {"coordinates":[6.382047,46.712646],"type":"Point"}
}