{
  "type": "Feature",
  "properties": {
    "iso:country":"CH",
    "sg:address":"R\u00fctiweg 8",
    "sg:city":"Unterkulm",
    "sg:orig_category":"Sportvereine Turnen",
    "sg:phone":"+41 62 776 28 67",
    "sg:postcode":"5726",
    "sg:province":"Aargau",
    "wof:name":"Turnverein Etv",
    "wof:placetype":"venue"
},
  "geometry": {"coordinates":[8.104929924,47.3146896362],"type":"Point"}
}