{
  "type": "Feature",
  "properties": {
    "iso:country":"CH",
    "sg:address":"Heinrichsgasse 18 4055 Basel. Postfach",
    "sg:city":"Basel",
    "sg:orig_category":"Ingenieurb\u00fcros Elektro Planer f\u00fcr Alternativenergie and Solararchitektur",
    "sg:phone":"+41 61 273 36 36",
    "sg:postcode":"4009",
    "sg:province":"Basel-Stadt",
    "wof:name":"W & S Ingenieurb\u00fcro F\u00fcr Elektroplanung Ag",
    "wof:placetype":"venue"
},
  "geometry": {"coordinates":[7.575920105,47.5564651489],"type":"Point"}
}