{
  "type": "Feature",
  "properties": {
    "iso:country":"CH",
    "sg:address":"Dettighoferstrasse 50",
    "sg:city":"Lengwil-oberhofen",
    "sg:orig_category":"Herstellung von Konstruktionsteilen, Fertigbauteilen U Ausbauelementen aus Holz",
    "sg:postcode":"8574",
    "sg:province":"Thurgau",
    "wof:name":"Bucher Franz",
    "wof:placetype":"venue"
},
  "geometry": {"coordinates":[9.1993503571,47.6224403381],"type":"Point"}
}