{
  "type": "Feature",
  "properties": {
    "iso:country":"CH",
    "sg:address":"Seestrasse 69",
    "sg:city":"Gunten",
    "sg:orig_category":"Fachdetailhandel in Verkaufsr\u00e4umen",
    "sg:postcode":"3654",
    "sg:province":"Bern",
    "wof:name":"Windsurfing-shop, Berhard J\u00fcrg",
    "wof:placetype":"venue"
},
  "geometry": {"coordinates":[8.7822036743,47.373626709],"type":"Point"}
}