{
  "type": "Feature",
  "properties": {
    "iso:country":"CH",
    "sg:address":"Wehntalerstrasse 23",
    "sg:city":"Oberweningen",
    "sg:orig_category":"Herstellung von Bekleidung U Pelzwaren Textilgewerbe",
    "sg:phone":"+41 79 285 28 89",
    "sg:postcode":"8165",
    "sg:province":"Z\u00fcrich",
    "wof:name":"Performance Cr\u00e9ations, B\u00e9doui B. Et N.",
    "wof:placetype":"venue"
},
  "geometry": {"coordinates":[6.8386092186,46.4851760864],"type":"Point"}
}