{
  "type": "Feature",
  "properties": {
    "iso:country":"CH",
    "sg:address":"Heinrichstrasse 125",
    "sg:city":"Z\u00fcrich",
    "sg:orig_category":"Detailhandel mit elektrischen Haushalts-,Radio U Fernsehger\u00e4ten sowie Musikinstrumenten Vervielf\u00e4lti",
    "sg:phone":"+41 14402575",
    "sg:postcode":"8005",
    "sg:province":"Z\u00fcrich",
    "wof:name":"Audio Partner Kommunikations- & Studio-technik Gmbh",
    "wof:placetype":"venue"
},
  "geometry": {"coordinates":[8.5278396606,47.386138916],"type":"Point"}
}