{
  "type": "Feature",
  "properties": {
    "iso:country":"CH",
    "sg:address":"Sagiweg 21",
    "sg:city":"Schnottwil",
    "sg:orig_category":"S\u00e4gewerke",
    "sg:phone":"+41 32 351 14 21",
    "sg:postcode":"3253",
    "sg:province":"Solothurn",
    "wof:name":"Hans-ueli Dick S\u00e4gewerk",
    "wof:placetype":"venue"
},
  "geometry": {"coordinates":[7.3940329552,47.1068191528],"type":"Point"}
}