{
  "type": "Feature",
  "properties": {
    "iso:country":"CH",
    "sg:address":"Hausenstrasse 60 3860 Meiringen. Postfach 691",
    "sg:city":"Meiringen",
    "sg:orig_category":"Betrieb von Taxis Einzelhandel mit Automobilteilen U Zubeh\u00f6r",
    "sg:phone":"+41 79 310 26 34",
    "sg:postcode":"3860",
    "sg:province":"Bern",
    "wof:name":"Selfors Fredrik Taxi, Carunternehmung, Personentransporte, Pneuservice",
    "wof:placetype":"venue"
},
  "geometry": {"coordinates":[8.169805,46.730148],"type":"Point"}
}