{
  "type": "Feature",
  "properties": {
    "iso:country":"CH",
    "sg:address":"Feldlistrasse 14 9413 Oberegg. Postfach",
    "sg:city":"Oberegg",
    "sg:orig_category":"Abbruch U Sprenggewerbe, Erdbewegungsarbeiten",
    "sg:postcode":"9413",
    "sg:province":"Appenzell Innerhoden",
    "wof:name":"Uso-handel Sonderegger Gebrauchtwaren Aus Abbruch Und Liquidationen; Handel. Planung, Durchf\u00fchrung Von Industrieabbruch-arbeiten",
    "wof:placetype":"venue"
},
  "geometry": {"coordinates":[9.553037,47.423901],"type":"Point"}
}