{
  "type": "Feature",
  "properties": {
    "iso:country":"CH",
    "sg:address":"8767 Elm. Postfach",
    "sg:city":"Elm",
    "sg:orig_category":"Zimmerei, Dachdeckerei, Bauspenglerei U Abdichtung",
    "sg:phone":"+41 55 642 12 85",
    "sg:postcode":"8767",
    "sg:province":"Glarus",
    "wof:name":"Zentner Peter, Dipl. Dachdeckermeister",
    "wof:placetype":"venue"
},
  "geometry": {"coordinates":[9.1728467941,46.9213943481],"type":"Point"}
}