{
  "type": "Feature",
  "properties": {
    "iso:country":"CH",
    "sg:address":"Friesstrasse 8 8050 Z\u00fcrich",
    "sg:city":"Zust",
    "sg:orig_category":"Detailhandel mit B\u00fcchern, Zeitungen, Schreib U Papeteriewaren",
    "sg:postcode":"50",
    "wof:name":"Swiss Chalet Line Food P.a. Lambelet Kiosque Etc",
    "wof:placetype":"venue"
},
  "geometry": {"coordinates":[6.943916,46.522507],"type":"Point"}
}