{
  "type": "Feature",
  "properties": {
    "iso:country":"CH",
    "sg:address":"Gaishausstrasse 41",
    "sg:city":"Appenzell",
    "sg:orig_category":"Sportvereine Turnen",
    "sg:phone":"+41 71 787 45 89",
    "sg:postcode":"9050",
    "sg:province":"Appenzell Innerhoden",
    "wof:name":"Turnverein Stv Appezell",
    "wof:placetype":"venue"
},
  "geometry": {"coordinates":[9.403626442,47.3305206299],"type":"Point"}
}