{
  "type": "Feature",
  "properties": {
    "iso:country":"CH",
    "sg:address":"3976",
    "sg:city":"No\u00ebs",
    "sg:orig_category":"Detailhandel mit Radio U Fernsehger\u00e4ten Detailhandel mit fotografischen Artikeln",
    "sg:phone":"+41 27 456 85 11",
    "sg:postcode":"3976",
    "sg:province":"Valais",
    "wof:name":"Interdiscount Ag Hi-fi Video Photo Radio",
    "wof:placetype":"venue"
},
  "geometry": {"coordinates":[7.5055451393,46.2809448242],"type":"Point"}
}