{
  "type": "Feature",
  "properties": {
    "iso:country":"CH",
    "sg:address":"Route De Vallaire 149",
    "sg:city":"Ecublens",
    "sg:classifiers":[
        {
            "category":"Professional",
            "subcategory":"Art Services",
            "type":"Services"
        }
    ],
    "sg:phone":"+41 21 691 08 18",
    "sg:postcode":"1024",
    "sg:province":"Vaud",
    "sg:tags":[
        "artistic",
        "glazings"
    ],
    "wof:name":"Simonetti Fr\u00e8res S.a.r.l.",
    "wof:placetype":"venue"
},
  "geometry": {"coordinates":[6.547383,46.514698],"type":"Point"}
}