{
  "type": "Feature",
  "properties": {
    "addr:full":"Riedstrasse 4 Ermatingen Thurgau 8272",
    "addr:housenumber":"4",
    "addr:postcode":"8272",
    "addr:street":"Riedstrasse",
    "iso:country":"CH",
    "sg:address":"Riedstrasse 4",
    "sg:city":"Ermatingen",
    "sg:orig_category":"Allgemeiner Hoch U Tiefbau",
    "sg:postcode":"8272",
    "sg:province":"Thurgau",
    "wof:name":"Stutz Hermann Ag",
    "wof:placetype":"venue"
},
  "geometry": {"coordinates":[9.088705,47.670788],"type":"Point"}
}