{
  "type": "Feature",
  "properties": {
    "iso:country":"CH",
    "sg:address":"Passage Du Cardinal 2 A",
    "sg:city":"Fribourg",
    "sg:orig_category":"Herstellung von Metallkonstruktionen",
    "sg:phone":"+41 26 402 81 11",
    "sg:postcode":"1700",
    "sg:province":"Fribourg",
    "wof:name":"Guterres Joaquim - Metallfassaden",
    "wof:placetype":"venue"
},
  "geometry": {"coordinates":[7.1472411156,46.79870224],"type":"Point"}
}