{
  "type": "Feature",
  "properties": {
    "iso:country":"CH",
    "sg:address":"Uetlibergstrasse 30 8045 Z\u00fcrich",
    "sg:city":"Zust",
    "sg:orig_category":"RESTAURANTS: TEA-ROOMS",
    "sg:postcode":"45",
    "wof:name":"Ristorante Pi\u00e9 Sa",
    "wof:placetype":"venue"
},
  "geometry": {"coordinates":[8.7924995422,46.2998199463],"type":"Point"}
}