{
  "type": "Feature",
  "properties": {
    "iso:country":"CH",
    "sg:address":"Sonnhalde 2",
    "sg:city":"Edlibach",
    "sg:orig_category":"Sportvereine Sch\u00fctzen Armbrust",
    "sg:phone":"+41 41 755 03 34",
    "sg:postcode":"6313",
    "sg:province":"Zug",
    "wof:name":"Armbrustsch\u00fctzenverein Zug",
    "wof:placetype":"venue"
},
  "geometry": {"coordinates":[8.5740156174,47.1813392639],"type":"Point"}
}