{
  "type": "Feature",
  "properties": {
    "iso:country":"CH",
    "sg:address":"Rue Du Mauborget 1",
    "sg:city":"Yverdon-les-bains",
    "sg:orig_category":"Detailhandel mit Milcherzeugnissen U Eiern Sonstiger Fachdetailhandel mit Nahrungsmitteln, Getr\u00e4nken",
    "sg:phone":"+41 26 917 81 13",
    "sg:postcode":"1400",
    "sg:province":"Vaud",
    "wof:name":"Benoit & Evelyne D\u00e9forel Laiterie De Sales",
    "wof:placetype":"venue"
},
  "geometry": {"coordinates":[6.9744057655,46.6355400085],"type":"Point"}
}