{
  "type": "Feature",
  "properties": {
    "iso:country":"CH",
    "sg:address":"Giacomettistrasse 110 7000 Chur. Postfach 40",
    "sg:city":"Chur",
    "sg:orig_category":"Technische, physikalische U chemische Untersuchung",
    "sg:phone":"+41 81 353 15 01",
    "sg:postcode":"7006",
    "sg:province":"Graubunden",
    "wof:name":"Griso-baucontrol Ag.",
    "wof:placetype":"venue"
},
  "geometry": {"coordinates":[9.5288534164,46.863483429],"type":"Point"}
}