{
  "type": "Feature",
  "properties": {
    "addr:full":"Auwiesenstrasse 1 Winterthur Z\u00fcrich 8406",
    "addr:housenumber":"1",
    "addr:postcode":"8406",
    "addr:street":"Auwiesenstrasse",
    "iso:country":"CH",
    "sg:address":"Auwiesenstrasse 1",
    "sg:city":"Winterthur",
    "sg:orig_category":"Card Gluers",
    "sg:phone":"+41 52 269 28 80",
    "sg:postcode":"8406",
    "sg:province":"Z\u00fcrich",
    "wof:name":"Weber Ag Druckverarbeitung Und Versand",
    "wof:placetype":"venue"
},
  "geometry": {"coordinates":[8.7101,47.484673],"type":"Point"}
}