{
  "type": "Feature",
  "properties": {
    "iso:country":"CH",
    "sg:address":"Hennimoostrasse 40",
    "sg:city":"Diepoldsau",
    "sg:orig_category":"Maschinen-Fabrikation",
    "sg:postcode":"9444",
    "sg:province":"St. Gallen",
    "wof:name":"Besserer Konstruktionen Gmbh",
    "wof:placetype":"venue"
},
  "geometry": {"coordinates":[9.6485919952,47.3877067566],"type":"Point"}
}