{
  "type": "Feature",
  "properties": {
    "iso:country":"CH",
    "sg:address":"L\u00e4ngackerstrasse 25",
    "sg:city":"Aarburg",
    "sg:orig_category":"Vereine Frauen Vereine Gemeinn\u00fctzige",
    "sg:phone":"+41 62 791 48 72",
    "sg:postcode":"4663",
    "sg:province":"Aargau",
    "wof:name":"Gemeinn\u00fctziger Frauenverein",
    "wof:placetype":"venue"
},
  "geometry": {"coordinates":[7.9093251228,47.3355178833],"type":"Point"}
}