{
  "type": "Feature",
  "properties": {
    "iso:country":"CH",
    "sg:address":"2887 Soubey. Postfach",
    "sg:city":"Soubey",
    "sg:classifiers":[
        {
            "category":"Travel",
            "subcategory":"Hotels & Motels",
            "type":"Entertainment"
        }
    ],
    "sg:postcode":"2887",
    "sg:province":"Jura",
    "sg:tags":[
        "hotels",
        "mit",
        "restaurant"
    ],
    "wof:name":"Jossi Hanspeter",
    "wof:placetype":"venue"
},
  "geometry": {"coordinates":[8.2095518112,46.7326622009],"type":"Point"}
}