{
  "type": "Feature",
  "properties": {
    "iso:country":"CH",
    "sg:address":"Menzbergstrasse 46",
    "sg:city":"Willisau",
    "sg:classifiers":[
        {
            "category":"Manufacturing",
            "subcategory":"Wood Products",
            "type":"Manufacturing & Wholesale Goods"
        }
    ],
    "sg:phone":"+41 41 970 14 38",
    "sg:postcode":"6130",
    "sg:province":"Luzern",
    "sg:tags":[
        "gate",
        "made",
        "door"
    ],
    "wof:name":"E. Zimmermann Ag",
    "wof:placetype":"venue"
},
  "geometry": {"coordinates":[7.9972801208,47.1098823547],"type":"Point"}
}