{
  "type": "Feature",
  "properties": {
    "iso:country":"CH",
    "sg:address":"Schulstrasse 6",
    "sg:city":"Turbenthal",
    "sg:orig_category":"Verwaltung der Rechtspflege, Gerichte",
    "sg:phone":"+41 52 385 11 11",
    "sg:postcode":"8488",
    "sg:province":"Z\u00fcrich",
    "wof:name":"Notariat Grundbuch-& Konkursamt Turbenthal",
    "wof:placetype":"venue"
},
  "geometry": {"coordinates":[8.8468618393,47.4386520386],"type":"Point"}
}