{
  "type": "Feature",
  "properties": {
    "iso:country":"CH",
    "sg:address":"Dorfstrasse 77",
    "sg:city":"Adelboden",
    "sg:orig_category":"Unclassifiable Establishments",
    "sg:postcode":"3715",
    "sg:province":"Bern",
    "wof:name":"Hotel Waldhaus-huldi Ag",
    "wof:placetype":"venue"
},
  "geometry": {"coordinates":[7.5540480614,46.4888153076],"type":"Point"}
}