{
  "type": "Feature",
  "properties": {
    "iso:country":"CH",
    "sg:address":"Gen\u00e8ve Rue De 21 1003 Lausanne. Postfach",
    "sg:city":"Lausanne",
    "sg:orig_category":"Grosshandel mit Getr\u00e4nken",
    "sg:postcode":"1003",
    "sg:province":"Vaud",
    "wof:name":"Guilde Du Vin",
    "wof:placetype":"venue"
},
  "geometry": {"coordinates":[6.627412796,46.5220565796],"type":"Point"}
}