{
  "type": "Feature",
  "properties": {
    "iso:country":"CH",
    "sg:address":"Murtenstrasse 1 3008 Bern. Postfach",
    "sg:city":"Bern",
    "sg:orig_category":"Grosshandel mit Nahrungsmitteln, Getr\u00e4nken U Tabakwaren ohne ausgepr\u00e4gten Schwerpunkt",
    "sg:phone":"+41 31 381 09 18",
    "sg:postcode":"3005",
    "sg:province":"Bern",
    "wof:name":"Maletti A. Lebensmittelhandel.",
    "wof:placetype":"venue"
},
  "geometry": {"coordinates":[7.4275259972,46.9482498169],"type":"Point"}
}