{
  "type": "Feature",
  "properties": {
    "iso:country":"CH",
    "sg:address":"T\u00f6distrasse 8",
    "sg:city":"B\u00e4retswil",
    "sg:orig_category":"Architektur U Ingenieurb\u00fcros Wirtschaftspr\u00fcfung, Steuerberatung U Treuhand",
    "sg:phone":"+41 878 880 102",
    "sg:postcode":"8344",
    "sg:province":"Z\u00fcrich",
    "wof:name":"Gubser Treuhand Gmbh",
    "wof:placetype":"venue"
},
  "geometry": {"coordinates":[8.85108,47.342087],"type":"Point"}
}