{
  "type": "Feature",
  "properties": {
    "iso:country":"CH",
    "sg:address":"Route De B\u00e2le 185",
    "sg:city":"Del\u00e9mont",
    "sg:orig_category":"Jugendherbergen U H\u00fctten",
    "sg:phone":"+41 32 422 20 18",
    "sg:postcode":"2800",
    "sg:province":"Jura",
    "wof:name":"Auberge De Jeunesse Asj",
    "wof:placetype":"venue"
},
  "geometry": {"coordinates":[7.3597841263,47.3714103699],"type":"Point"}
}