{
  "type": "Feature",
  "properties": {
    "iso:country":"CH",
    "sg:address":"Rue Du Scex 21",
    "sg:city":"Sion",
    "sg:orig_category":"Vermietung U Verpachtung von eigenen Immobilien",
    "sg:postcode":"1950",
    "sg:province":"Valais",
    "wof:name":"Eden-scex Sa",
    "wof:placetype":"venue"
},
  "geometry": {"coordinates":[7.365085125,46.2326393127],"type":"Point"}
}