{
  "type": "Feature",
  "properties": {
    "iso:country":"CH",
    "sg:address":"Kronengasse 6362 Stansstad. Postfach",
    "sg:city":"Stansstad",
    "sg:orig_category":"Non-Classified Establishments",
    "sg:postcode":"6362",
    "sg:province":"Nidwalden",
    "wof:name":"Degustationabc, Ren\u00e9 Smienk",
    "wof:placetype":"venue"
},
  "geometry": {"coordinates":[5.1808700562,45.8973388672],"type":"Point"}
}