{
  "type": "Feature",
  "properties": {
    "iso:country":"CH",
    "sg:address":"Baumg\u00e4rtliring 27",
    "sg:city":"Gelterkinden",
    "sg:orig_category":"Unclassifiable Establishments",
    "sg:postcode":"4460",
    "sg:province":"Basel-Landschaft",
    "wof:name":"Concordia Krankenkasse",
    "wof:placetype":"venue"
},
  "geometry": {"coordinates":[7.8572211266,47.4685020447],"type":"Point"}
}