{
  "type": "Feature",
  "properties": {
    "iso:country":"CH",
    "sg:address":"Les Vernasses",
    "sg:city":"Icogne",
    "sg:orig_category":"Landesverteidigung, Sozialversicherung \u00d6ffentliche Verwaltung",
    "sg:phone":"+41 27 483 20 00",
    "sg:postcode":"1977",
    "sg:province":"Valais",
    "wof:name":"Centre De Protection Civile",
    "wof:placetype":"venue"
},
  "geometry": {"coordinates":[7.4397788048,46.2945365906],"type":"Point"}
}