{
  "type": "Feature",
  "properties": {
    "iso:country":"CH",
    "sg:address":"Wisen 9612 Dreien. Postfach",
    "sg:city":"Dreien",
    "sg:orig_category":"RESTAURANTS: TEA-ROOMS",
    "sg:postcode":"9612",
    "sg:province":"St. Gallen",
    "wof:name":"Rest. Sch\u00e4lli Loser Hanspeter",
    "wof:placetype":"venue"
},
  "geometry": {"coordinates":[9.0176811218,47.3729324341],"type":"Point"}
}