{
  "type": "Feature",
  "properties": {
    "addr:full":"Lindenstrasse 24 8307 Effretikon. Postfach Tagelswangen Z\u00fcrich 8317",
    "addr:housenumber":"24",
    "addr:postcode":"8307 effretikon. postfach;8317",
    "addr:street":"Lindenstrasse",
    "iso:country":"CH",
    "sg:address":"Lindenstrasse 24 8307 Effretikon. Postfach",
    "sg:city":"Tagelswangen",
    "sg:orig_category":"Architektur U Ingenieurb\u00fcros Sonstige technische Beratung U Planung",
    "sg:phone":"+41 52 343 55 56",
    "sg:postcode":"8317",
    "sg:province":"Z\u00fcrich",
    "wof:name":"Moba-z Gmbh Anlagebau, Industriemontage, Bauleitung; Planung, Beratung, Montage",
    "wof:placetype":"venue"
},
  "geometry": {"coordinates":[8.698213,47.427097],"type":"Point"}
}