{
  "type": "Feature",
  "properties": {
    "iso:country":"CH",
    "sg:address":"4562",
    "sg:city":"Biberist",
    "sg:orig_category":"Verwertung von Milch",
    "sg:postcode":"4562",
    "sg:province":"Solothurn",
    "wof:name":"Milchgenossenschaft Birmenstorf-m\u00fcnzlishausen",
    "wof:placetype":"venue"
},
  "geometry": {"coordinates":[8.2616596222,47.4556159973],"type":"Point"}
}