{
  "type": "Feature",
  "properties": {
    "iso:country":"CH",
    "sg:address":"Buchelirain 6 9400 Rorschach. Postfach",
    "sg:city":"Rorschach",
    "sg:orig_category":"Unclassifiable Establishments",
    "sg:postcode":"9400",
    "sg:province":"St. Gallen",
    "wof:name":"Steponline Gmbh",
    "wof:placetype":"venue"
},
  "geometry": {"coordinates":[9.5004024506,47.4718971252],"type":"Point"}
}