{
  "type": "Feature",
  "properties": {
    "iso:country":"CH",
    "sg:address":"1588",
    "sg:city":"Cudrefin",
    "sg:orig_category":"Primarschulen",
    "sg:phone":"+41 26 677 40 44",
    "sg:postcode":"1588",
    "sg:province":"Vaud",
    "wof:name":"Ecole Primaire",
    "wof:placetype":"venue"
},
  "geometry": {"coordinates":[7.0185198784,46.9558601379],"type":"Point"}
}