{
  "type": "Feature",
  "properties": {
    "addr:full":"Worblaufenstrasse 161 3048 Worblaufen. Postfach 73 Worblaufen Bern 3048",
    "addr:housenumber":"161;73",
    "addr:postcode":"3048;3048",
    "addr:street":"Worblaufenstrasse;Postfach",
    "iso:country":"CH",
    "sg:address":"Worblaufenstrasse 161 3048 Worblaufen. Postfach 73",
    "sg:city":"Worblaufen",
    "sg:classifiers":[
        {
            "category":"Bars & Pubs",
            "type":"Food & Drink"
        }
    ],
    "sg:phone":"+41 32 841 26 10",
    "sg:postcode":"3048",
    "sg:province":"Bern",
    "wof:name":"Drakkar S\u00e0rl",
    "wof:placetype":"venue"
},
  "geometry": {"coordinates":[6.857987,46.965614],"type":"Point"}
}