{
  "type": "Feature",
  "properties": {
    "iso:country":"CH",
    "sg:address":"1528",
    "sg:city":"Surpierre",
    "sg:orig_category":"Detailhandel mit Antiquit\u00e4ten U Gebrauchtwaren in Verkaufsr\u00e4umen",
    "sg:postcode":"1528",
    "sg:province":"Fribourg",
    "wof:name":"Ch\u00e2teau De Surpierre-antiquit\u00e9s",
    "wof:placetype":"venue"
},
  "geometry": {"coordinates":[6.85046,46.74324],"type":"Point"}
}