{
  "type": "Feature",
  "properties": {
    "iso:country":"CH",
    "sg:address":"Lehnstrasse 35 9014 St. Gallen. Postfach 9014 St. Gallen",
    "sg:city":"Zust",
    "sg:orig_category":"Handelsvermittlung von Textilien, Bekleidung, Schuhen U Lederwaren",
    "sg:phone":"+41 71 277 03 45",
    "sg:postcode":"14",
    "wof:name":"K\u00f6nig Textiles",
    "wof:placetype":"venue"
},
  "geometry": {"coordinates":[9.3299999237,47.405960083],"type":"Point"}
}