{
  "type": "Feature",
  "properties": {
    "iso:country":"CH",
    "sg:address":"Surseestrasse 34",
    "sg:city":"Neuenkirch",
    "sg:orig_category":"Instandhaltung U Reparatur von Automobilen Tankstellen",
    "sg:phone":"+41 22 343 00 20",
    "sg:postcode":"6206",
    "sg:province":"Luzern",
    "wof:name":"Auto Erb Carouge Sa",
    "wof:placetype":"venue"
},
  "geometry": {"coordinates":[6.1358709335,46.1789360046],"type":"Point"}
}