{
  "type": "Feature",
  "properties": {
    "iso:country":"CH",
    "sg:address":"Schulstrasse 2 7302 Landquart. Postfach",
    "sg:city":"Landquart",
    "sg:orig_category":"RESTAURANTS: TEA-ROOMS",
    "sg:phone":"+41 81 322 16 92",
    "sg:postcode":"7302",
    "sg:province":"Graubunden",
    "wof:name":"Pizzeria Pinocchio, Pirrera Francesco",
    "wof:placetype":"venue"
},
  "geometry": {"coordinates":[9.5576810837,46.9675292969],"type":"Point"}
}