{
  "type": "Feature",
  "properties": {
    "addr:full":"Route De Lossy 1 Belfaux Fribourg 1782",
    "addr:housenumber":"1",
    "addr:postcode":"1782",
    "addr:street":"Route De Lossy",
    "iso:country":"CH",
    "sg:address":"Route De Lossy 1",
    "sg:city":"Belfaux",
    "sg:classifiers":[
        {
            "category":"Banks & Credit Unions",
            "subcategory":"Bank",
            "type":"Services"
        }
    ],
    "sg:phone":"+41 37451419",
    "sg:postcode":"1782",
    "sg:province":"Fribourg",
    "wof:name":"Banque Raiffeisen De Belfaux",
    "wof:placetype":"venue"
},
  "geometry": {"coordinates":[7.10764,46.82225],"type":"Point"}
}