{
  "type": "Feature",
  "properties": {
    "iso:country":"CH",
    "sg:address":"Freiburgerstrasse 9",
    "sg:city":"Basel",
    "sg:orig_category":"Sonstige Kurierdienste",
    "sg:postcode":"4000",
    "sg:province":"Basel-Stadt",
    "wof:name":"Genossenschaft Davoser Revue",
    "wof:placetype":"venue"
},
  "geometry": {"coordinates":[9.8360099792,46.8027687073],"type":"Point"}
}