{
  "type": "Feature",
  "properties": {
    "iso:country":"CH",
    "sg:address":"Steinbruchstrasse 4",
    "sg:city":"M\u00e4genwil",
    "sg:orig_category":"Sanit\u00e4r, Heizungs U L\u00fcftungsinstallation Sanit\u00e4rinstallation",
    "sg:phone":"+41 62 896 22 06",
    "sg:postcode":"5506",
    "sg:province":"Aargau",
    "wof:name":"Glatthard Ag",
    "wof:placetype":"venue"
},
  "geometry": {"coordinates":[8.2425642014,47.410358429],"type":"Point"}
}