{
  "type": "Feature",
  "properties": {
    "iso:country":"CH",
    "sg:address":"Hinterbergstrasse 9",
    "sg:city":"Cham",
    "sg:orig_category":"Detailhandel mit Boden U Wandbel\u00e4gen ohne Teppiche Detailhandel mit Teppichen",
    "sg:phone":"+41 41 711 86 21",
    "sg:postcode":"6330",
    "sg:province":"Zug",
    "wof:name":"Hans Hassler Ag Teppiche Bodenbel\u00e4ge Vorh\u00e4nge",
    "wof:placetype":"venue"
},
  "geometry": {"coordinates":[8.476729,47.18734],"type":"Point"}
}