{
  "type": "Feature",
  "properties": {
    "addr:full":"Hatswil Hefenhofen Thurgau 8580",
    "addr:postcode":"8580",
    "iso:country":"CH",
    "sg:address":"Hatswil",
    "sg:city":"Hefenhofen",
    "sg:orig_category":"Detailhandel mit Brot, Back U S\u00fcsswaren",
    "sg:phone":"+41 71 411 12 36",
    "sg:postcode":"8580",
    "sg:province":"Thurgau",
    "wof:name":"Hanspeter M\u00e4chler B\u00e4ckerei-konditorei",
    "wof:placetype":"venue"
},
  "geometry": {"coordinates":[9.32418,47.555679],"type":"Point"}
}