{
  "type": "Feature",
  "properties": {
    "iso:country":"CH",
    "sg:address":"G\u00f6ldistrasse 1",
    "sg:city":"Richterswil",
    "sg:orig_category":"Werbung",
    "sg:phone":"+41 17848308",
    "sg:postcode":"8805",
    "sg:province":"Z\u00fcrich",
    "wof:name":"Gerster Consulting",
    "wof:placetype":"venue"
},
  "geometry": {"coordinates":[8.6990003586,47.20652771],"type":"Point"}
}