{
  "type": "Feature",
  "properties": {
    "iso:country":"CH",
    "sg:address":"Steinlerweg 13",
    "sg:city":"Niederlenz",
    "sg:orig_category":"Vorschulen, Kinderg\u00e4rten",
    "sg:phone":"+41 55 243 21 35",
    "sg:postcode":"5702",
    "sg:province":"Aargau",
    "wof:name":"Kindergarten",
    "wof:placetype":"venue"
},
  "geometry": {"coordinates":[7.4697628021,47.3869476318],"type":"Point"}
}