{
  "type": "Feature",
  "properties": {
    "iso:country":"CH",
    "sg:address":"Bollenhofstrasse 4",
    "sg:city":"Dietikon",
    "sg:orig_category":"Malerei Tapeziererei",
    "sg:phone":"+41 17415257",
    "sg:postcode":"8953",
    "sg:province":"Z\u00fcrich",
    "wof:name":"Urs Heimoz Allrounding",
    "wof:placetype":"venue"
},
  "geometry": {"coordinates":[8.3938121796,47.4041557312],"type":"Point"}
}