{
  "type": "Feature",
  "properties": {
    "iso:country":"CH",
    "sg:address":"Langenmooserstrasse 22",
    "sg:city":"Truttikon",
    "sg:orig_category":"Organisationen des Gesundheitswesen",
    "sg:phone":"+41 52 319 31 88",
    "sg:postcode":"8467",
    "sg:province":"Z\u00fcrich",
    "wof:name":"Samariterv.tr\u00fcllikon & Umg.",
    "wof:placetype":"venue"
},
  "geometry": {"coordinates":[8.7239360809,47.6307601929],"type":"Point"}
}