{
  "type": "Feature",
  "properties": {
    "iso:country":"CH",
    "sg:address":"D\u00f6rflistrasse 45",
    "sg:city":"Z\u00fcrich",
    "sg:classifiers":[
        {
            "category":"Military Area",
            "subcategory":"Air Force Base",
            "type":"Public Place"
        }
    ],
    "sg:phone":"+41 13199030",
    "sg:postcode":"8050",
    "sg:province":"Z\u00fcrich",
    "sg:tags":[
        "fire",
        "restoration",
        "damage"
    ],
    "wof:name":"Nettag Ag",
    "wof:placetype":"venue"
},
  "geometry": {"coordinates":[8.5501060486,47.4063453674],"type":"Point"}
}