{
  "type": "Feature",
  "properties": {
    "iso:country":"CH",
    "sg:address":"Schachenstrasse 7",
    "sg:city":"Hedingen",
    "sg:orig_category":"Vorschulen, Kinderg\u00e4rten",
    "sg:phone":"+41 17600690",
    "sg:postcode":"8908",
    "sg:province":"Z\u00fcrich",
    "wof:name":"Kindergarten Schachen I & Ii",
    "wof:placetype":"venue"
},
  "geometry": {"coordinates":[8.4448518753,47.2972488403],"type":"Point"}
}