{
  "type": "Feature",
  "properties": {
    "iso:country":"CH",
    "sg:address":"Bahnhofstrasse 7 7000 Chur. Postfach 270",
    "sg:city":"Chur",
    "sg:orig_category":"Detailhandel mit Uhren U Schmuck Reparatur von Uhren U Schmuck",
    "sg:phone":"+41 81 252 14 50",
    "sg:postcode":"7001",
    "sg:province":"Graubunden",
    "wof:name":"Guido Decurtins Uhren & Bijouterie",
    "wof:placetype":"venue"
},
  "geometry": {"coordinates":[9.5306978226,46.8528327942],"type":"Point"}
}