{
  "type": "Feature",
  "properties": {
    "iso:country":"CH",
    "sg:address":"Artherstrasse 28",
    "sg:city":"Zug",
    "sg:orig_category":"Architekturb\u00fcros",
    "sg:phone":"+41 41 711 57 89",
    "sg:postcode":"6300",
    "sg:province":"Zug",
    "wof:name":"Arthur Keiser Architekturb\u00fcro",
    "wof:placetype":"venue"
},
  "geometry": {"coordinates":[8.512641,47.160412],"type":"Point"}
}