{
  "type": "Feature",
  "properties": {
    "iso:country":"CH",
    "sg:address":"Rue Haldimand 10",
    "sg:city":"Lausanne",
    "sg:orig_category":"Architektur U Ingenieurb\u00fcros Arztpraxen",
    "sg:phone":"+41 32 914 30 07",
    "sg:postcode":"1003",
    "sg:province":"Vaud",
    "wof:name":"Willemin Fran\u00e7ois",
    "wof:placetype":"venue"
},
  "geometry": {"coordinates":[6.830084,47.103977],"type":"Point"}
}