{
  "type": "Feature",
  "properties": {
    "addr:full":"Eschikerstrasse 15 8307 Effretikon. Postfach Effretikon Z\u00fcrich 8307",
    "addr:housenumber":"15",
    "addr:postcode":"8307 effretikon. postfach;8307",
    "addr:street":"Eschikerstrasse",
    "iso:country":"CH",
    "sg:address":"Eschikerstrasse 15 8307 Effretikon. Postfach",
    "sg:city":"Effretikon",
    "sg:orig_category":"Aktivit\u00e4ten der Generalunternehmen im Baugewerbe Vermittlung von Immobilien",
    "sg:phone":"+41 52 355 17 15",
    "sg:postcode":"8307",
    "sg:province":"Z\u00fcrich",
    "wof:name":"Bol Management Gmbh",
    "wof:placetype":"venue"
},
  "geometry": {"coordinates":[8.688959,47.434525],"type":"Point"}
}