{
  "type": "Feature",
  "properties": {
    "iso:country":"CH",
    "sg:address":"Buechegg 9",
    "sg:city":"Herbligen",
    "sg:orig_category":"Vermittlung von Immobilien Verwaltung von Immobilien",
    "sg:phone":"+41 31 771 16 25",
    "sg:postcode":"3671",
    "sg:province":"Bern",
    "wof:name":"Treuhand Burkhardt-sauerteig",
    "wof:placetype":"venue"
},
  "geometry": {"coordinates":[7.616440773,46.8249855042],"type":"Point"}
}