{
  "type": "Feature",
  "properties": {
    "iso:country":"CH",
    "sg:address":"Boulevard Georges-favon 2 1200 Genf. Postfach",
    "sg:city":"Gen\u00e8ve",
    "sg:orig_category":"Unclassifiable Establishments",
    "sg:phone":"+41 31 872 00 31",
    "sg:postcode":"1204",
    "sg:province":"Gen\u00e8ve",
    "wof:name":"Comsat Balli",
    "wof:placetype":"venue"
},
  "geometry": {"coordinates":[7.4153399467,47.0588417053],"type":"Point"}
}