{
  "type": "Feature",
  "properties": {
    "iso:country":"CH",
    "sg:address":"Avenue Georgette 2",
    "sg:city":"Lausanne",
    "sg:orig_category":"Detailhandel mit Waren verschiedener Art, Hauptrichtung Nahrungsmittel Fachdetailhandel mit Nahrungs",
    "sg:phone":"+41 21 312 56 31",
    "sg:postcode":"1003",
    "sg:province":"Vaud",
    "wof:name":"Mulhaupt & Cie",
    "wof:placetype":"venue"
},
  "geometry": {"coordinates":[6.6378087997,46.5177574158],"type":"Point"}
}