{
  "type": "Feature",
  "properties": {
    "iso:country":"CH",
    "sg:address":"Cure Chemin De La 3 1092 Belmont-lausanne. Postfach",
    "sg:city":"Belmont-lausanne",
    "sg:orig_category":"Grosshandel mit Getr\u00e4nken",
    "sg:phone":"+41 21 841 19 04",
    "sg:postcode":"1092",
    "sg:province":"Vaud",
    "wof:name":"M\u00fcller Bernard",
    "wof:placetype":"venue"
},
  "geometry": {"coordinates":[6.3260798454,46.6681747437],"type":"Point"}
}