{
  "type": "Feature",
  "properties": {
    "iso:country":"CH",
    "sg:address":"K\u00e4giswilerstrasse 6060 Sarnen. Postfach 531",
    "sg:city":"Sarnen",
    "sg:orig_category":"Herstellung von Ger\u00e4ten der Elektrizit\u00e4tserzeugung, -verteilung u.\u00e4. -Herstellung von sonstigen elek",
    "sg:phone":"+41 41 660 29 66",
    "sg:postcode":"6060",
    "sg:province":"Obwalden",
    "wof:name":"Disa Elektro Ag",
    "wof:placetype":"venue"
},
  "geometry": {"coordinates":[8.2587308884,46.9083213806],"type":"Point"}
}