{
  "type": "Feature",
  "properties": {
    "iso:country":"CH",
    "sg:address":"Schulhausstrasse 7",
    "sg:city":"Maur",
    "sg:orig_category":"Fachdetailhandel in Verkaufsr\u00e4umen",
    "sg:postcode":"8124",
    "sg:province":"Z\u00fcrich",
    "wof:name":"Famo Ag",
    "wof:placetype":"venue"
},
  "geometry": {"coordinates":[8.6538238525,47.3274345398],"type":"Point"}
}