{
  "type": "Feature",
  "properties": {
    "iso:country":"CH",
    "sg:address":"En Reutet",
    "sg:city":"Collombey",
    "sg:orig_category":"Abwasserreinigung",
    "sg:phone":"+41 21 967 09 47",
    "sg:postcode":"1868",
    "sg:province":"Valais",
    "wof:name":"Station D'\u00e9puration",
    "wof:placetype":"venue"
},
  "geometry": {"coordinates":[6.926135,46.398186],"type":"Point"}
}