{
  "type": "Feature",
  "properties": {
    "iso:country":"CH",
    "sg:address":"Els\u00e4sserstrasse 8 4056 Basel. Postfach",
    "sg:city":"Basel",
    "sg:orig_category":"Detailhandel mit Textilien Herstellung von N\u00e4hgarn",
    "sg:phone":"+41 81 832 29 00",
    "sg:postcode":"4004",
    "sg:province":"Basel-Stadt",
    "wof:name":"Loro Piana Suisse Sa Attivit\u00e0 Industriale E Commerciale Nel Settore Delle Lane Ecc",
    "wof:placetype":"venue"
},
  "geometry": {"coordinates":[9.8402519226,46.497379303],"type":"Point"}
}