{
  "type": "Feature",
  "properties": {
    "iso:country":"CH",
    "sg:address":"Boisy Chemin Du 15 1004 Lausanne Case Postale",
    "sg:city":"Lausanne",
    "sg:orig_category":"Grosshandel mit Eisenwaren sowie Installationsbedarf f\u00fcr Gas, Wasser U Heizung",
    "sg:phone":"+41 55 256 20 46",
    "sg:postcode":"1003",
    "sg:province":"Vaud",
    "wof:name":"Grass Thomas, Fachgesch\u00e4ft F\u00fcr Eisenwaren U. Haushalt",
    "wof:placetype":"venue"
},
  "geometry": {"coordinates":[8.9413003922,47.2884101868],"type":"Point"}
}