{
  "type": "Feature",
  "properties": {
    "iso:country":"CH",
    "sg:address":"Rorschacher Strasse 176",
    "sg:city":"St.gallen",
    "sg:orig_category":"Herstellung von Teilen U Zubeh\u00f6r f\u00fcr Automobile",
    "sg:phone":"+41 71 244 09 77",
    "sg:postcode":"9000",
    "sg:province":"St. Gallen",
    "wof:name":"K\u00fchler-r\u00fcesch.",
    "wof:placetype":"venue"
},
  "geometry": {"coordinates":[9.3982477188,47.4324798584],"type":"Point"}
}