{
  "type": "Feature",
  "properties": {
    "iso:country":"CH",
    "sg:address":"St. Gallerstrasse 80",
    "sg:city":"Arbon",
    "sg:orig_category":"Grosshandel mit festen Brennstoffen U Mineral\u00f6lerzeugnissen",
    "sg:phone":"+41 71 446 15 14",
    "sg:postcode":"9320",
    "sg:province":"Thurgau",
    "wof:name":"Brennstoff Ag Arbon",
    "wof:placetype":"venue"
},
  "geometry": {"coordinates":[9.4215288162,47.5094680786],"type":"Point"}
}