{
  "type": "Feature",
  "properties": {
    "iso:country":"CH",
    "sg:address":"Erde 1976 Erde. Postfach",
    "sg:city":"Erde",
    "sg:orig_category":"Reinigungsgewerbe",
    "sg:postcode":"1976",
    "sg:province":"Valais",
    "wof:name":"Rudaz-chapuis Viviane, Home-cleaner",
    "wof:placetype":"venue"
},
  "geometry": {"coordinates":[7.2959799767,46.2425804138],"type":"Point"}
}