{
  "type": "Feature",
  "properties": {
    "iso:country":"CH",
    "sg:address":"Lehnenweingarten 8 8592 Uttwil. Postfach",
    "sg:city":"Uttwil",
    "sg:orig_category":"Unclassifiable Establishments",
    "sg:postcode":"8592",
    "sg:province":"Thurgau",
    "wof:name":"Lanz Trans Uttwil Transporte",
    "wof:placetype":"venue"
},
  "geometry": {"coordinates":[9.335234642,47.5844192505],"type":"Point"}
}