{
  "type": "Feature",
  "properties": {
    "iso:country":"CH",
    "sg:address":"Arrennys Chemin Des 1",
    "sg:city":"Founex",
    "sg:orig_category":"Non-Classified Establishments",
    "sg:postcode":"1297",
    "sg:province":"Vaud",
    "wof:name":"Allcomp Roz\u00e9 F.",
    "wof:placetype":"venue"
},
  "geometry": {"coordinates":[6.1926550865,46.3329696655],"type":"Point"}
}