{
  "type": "Feature",
  "properties": {
    "iso:country":"CH",
    "sg:address":"8488",
    "sg:city":"Turbenthal",
    "sg:orig_category":"Vereine Frauen Vereine Gemeinn\u00fctzige",
    "sg:phone":"+41 1654060",
    "sg:postcode":"8488",
    "sg:province":"Z\u00fcrich",
    "wof:name":"Gemeinn\u00fctziger Frauenverein",
    "wof:placetype":"venue"
},
  "geometry": {"coordinates":[8.847366333,47.4357910156],"type":"Point"}
}