{
  "type": "Feature",
  "properties": {
    "iso:country":"CH",
    "sg:address":"M\u00fcllheimerstrasse 58",
    "sg:city":"Basel",
    "sg:orig_category":"Herstellung von Teppichen Verlegen von Fussboden",
    "sg:phone":"+41 61 691 05 00",
    "sg:postcode":"4057",
    "sg:province":"Basel-Stadt",
    "wof:name":"C. Hepp Ag",
    "wof:placetype":"venue"
},
  "geometry": {"coordinates":[7.5929408073,47.5663757324],"type":"Point"}
}