{
  "type": "Feature",
  "properties": {
    "addr:full":"Industriestrasse W\u00e4denswil Z\u00fcrich 8820",
    "addr:postcode":"8820",
    "addr:street":"Industriestrasse Waedenswil Zuerich",
    "iso:country":"CH",
    "sg:address":"Industriestrasse",
    "sg:city":"W\u00e4denswil",
    "sg:classifiers":[
        {
            "category":"Organizations",
            "subcategory":"Labor Organization",
            "type":"Services"
        }
    ],
    "sg:phone":"+41 17820070",
    "sg:postcode":"8820",
    "sg:province":"Z\u00fcrich",
    "sg:tags":[
        "work",
        "assembling",
        "assembly",
        "contract"
    ],
    "wof:name":"Arnold Ehrat Ag",
    "wof:placetype":"venue"
},
  "geometry": {"coordinates":[8.637937,47.235432],"type":"Point"}
}