{
  "type": "Feature",
  "properties": {
    "iso:country":"CH",
    "sg:address":"Kantonsstrasse",
    "sg:city":"Neuheim",
    "sg:orig_category":"Instandhaltung U Reparatur von Automobilen",
    "sg:postcode":"6345",
    "sg:province":"Zug",
    "wof:name":"L\u00f6tscher S. Ag",
    "wof:placetype":"venue"
},
  "geometry": {"coordinates":[8.5765800476,47.2029075623],"type":"Point"}
}