{
  "type": "Feature",
  "properties": {
    "iso:country":"CH",
    "sg:address":"Hauptstrasse 13",
    "sg:city":"Lommiswil",
    "sg:orig_category":"Verwertung von Milch",
    "sg:postcode":"4514",
    "sg:province":"Solothurn",
    "wof:name":"Milchgenossenschaft Lommiswil",
    "wof:placetype":"venue"
},
  "geometry": {"coordinates":[7.4713659286,47.2231369019],"type":"Point"}
}