{
  "type": "Feature",
  "properties": {
    "iso:country":"CH",
    "sg:address":"Les Ages",
    "sg:city":"Avenches",
    "sg:orig_category":"Abfallbeseitigung R\u00fcckgewinnung U Vorbereitung f\u00fcr die Wiederverwertung Recycling von nichtmetallisc",
    "sg:phone":"+41 26 675 21 22",
    "sg:postcode":"1580",
    "sg:province":"Vaud",
    "wof:name":"Vegetech Compost Sa",
    "wof:placetype":"venue"
},
  "geometry": {"coordinates":[7.040785,46.880058],"type":"Point"}
}