{
  "type": "Feature",
  "properties": {
    "iso:country":"CH",
    "sg:address":"Rue Des Cr\u00eats 3",
    "sg:city":"Dombresson",
    "sg:orig_category":"Softwareentwicklung U beratung",
    "sg:postcode":"2056",
    "sg:province":"Neuch\u00e2tel",
    "wof:name":"Uranie Consulting Sa",
    "wof:placetype":"venue"
},
  "geometry": {"coordinates":[6.9545311928,47.0717010498],"type":"Point"}
}