{
  "type": "Feature",
  "properties": {
    "iso:country":"CH",
    "sg:address":"Waagtalstrasse 25",
    "sg:city":"Unteriberg",
    "sg:orig_category":"Kaminfeger",
    "sg:phone":"+41 55 414 17 34",
    "sg:postcode":"8842",
    "sg:province":"Schwyz",
    "wof:name":"Josef Marty Kaminfegermeister",
    "wof:placetype":"venue"
},
  "geometry": {"coordinates":[8.8021993637,47.0569000244],"type":"Point"}
}