{
  "type": "Feature",
  "properties": {
    "addr:full":"Stadthausstrasse 53 Winterthur Z\u00fcrich 8400",
    "addr:housenumber":"53",
    "addr:postcode":"8400",
    "addr:street":"Stadthausstrasse",
    "iso:country":"CH",
    "sg:address":"Stadthausstrasse 53",
    "sg:city":"Winterthur",
    "sg:orig_category":"Allgemeiner Hoch U Tiefbau",
    "sg:phone":"+41 52 212 91 41",
    "sg:postcode":"8400",
    "sg:province":"Z\u00fcrich",
    "wof:name":"Amsel-werk Winterthur, Vrendli Amsler & Partner",
    "wof:placetype":"venue"
},
  "geometry": {"coordinates":[8.730002,47.500206],"type":"Point"}
}