{
  "type": "Feature",
  "properties": {
    "iso:country":"CH",
    "sg:address":"Freiestrasse 37",
    "sg:city":"Biel/bienne",
    "sg:orig_category":"Markt U Meinungsforschung",
    "sg:postcode":"2500",
    "sg:province":"Bern",
    "wof:name":"Kelag Marketing Ag Biel",
    "wof:placetype":"venue"
},
  "geometry": {"coordinates":[7.2506217957,47.1428489685],"type":"Point"}
}