{
  "type": "Feature",
  "properties": {
    "iso:country":"CH",
    "sg:address":"Gourgas Rue 1 1205 Gen\u00e8ve. Postfach",
    "sg:city":"Gen\u00e8ve",
    "sg:orig_category":"RESTAURANTS: TEA-ROOMS",
    "sg:postcode":"1205",
    "sg:province":"Gen\u00e8ve",
    "wof:name":"Pugin Roger",
    "wof:placetype":"venue"
},
  "geometry": {"coordinates":[6.1390881538,46.1990852356],"type":"Point"}
}