{
  "type": "Feature",
  "properties": {
    "iso:country":"CH",
    "sg:address":"St\u00fcdliackerstrasse 11",
    "sg:city":"Schaffhausen",
    "sg:orig_category":"Unclassifiable Establishments",
    "sg:postcode":"8207",
    "sg:province":"Schaffhausen",
    "wof:name":"Restaurant Herbilo Fasswald",
    "wof:placetype":"venue"
},
  "geometry": {"coordinates":[8.6642913818,47.7210998535],"type":"Point"}
}