{
  "type": "Feature",
  "properties": {
    "iso:country":"CH",
    "sg:address":"Hittnauerstrasse 2",
    "sg:city":"Saland",
    "sg:classifiers":[
        {
            "category":"Restaurant",
            "type":"Food & Drink"
        }
    ],
    "sg:phone":"+41 52 386 12 14",
    "sg:postcode":"8493",
    "sg:province":"Z\u00fcrich",
    "wof:name":"Restaurant Krone",
    "wof:placetype":"venue"
},
  "geometry": {"coordinates":[8.8541097641,47.3906326294],"type":"Point"}
}