{
  "type": "Feature",
  "properties": {
    "iso:country":"CH",
    "sg:address":"Obere Kirchstrasse 30",
    "sg:city":"Wallisellen",
    "sg:orig_category":"Detailhandel mit Damenbekleidung",
    "sg:phone":"+41 18302939",
    "sg:postcode":"8304",
    "sg:province":"Z\u00fcrich",
    "wof:name":"Margot Oberholzer Reviva Mode",
    "wof:placetype":"venue"
},
  "geometry": {"coordinates":[8.596963,47.416904],"type":"Point"}
}