{
  "type": "Feature",
  "properties": {
    "addr:full":"Rue Des Grottes 20 Gen\u00e8ve Gen\u00e8ve 1201",
    "addr:housenumber":"20",
    "addr:postcode":"1201",
    "addr:street":"Rue Des Grottes",
    "iso:country":"CH",
    "sg:address":"Rue Des Grottes 20",
    "sg:city":"Gen\u00e8ve",
    "sg:orig_category":"Detailhandel mit B\u00fcchern",
    "sg:phone":"+41 22 733 49 14",
    "sg:postcode":"1201",
    "sg:province":"Gen\u00e8ve",
    "wof:name":"Bouquinerie La Grotte Aux F\u00e9es Librairie",
    "wof:placetype":"venue"
},
  "geometry": {"coordinates":[6.1392,46.210754],"type":"Point"}
}