{
  "type": "Feature",
  "properties": {
    "addr:full":"5745 Safenwil Aargau 5745",
    "addr:postcode":"5745;5745",
    "iso:country":"CH",
    "sg:address":"5745",
    "sg:city":"Safenwil",
    "sg:classifiers":[
        {
            "category":"Education",
            "subcategory":"Library",
            "type":"Public Place"
        }
    ],
    "sg:postcode":"5745",
    "sg:province":"Aargau",
    "sg:tags":[
        "u",
        "bibliotheken",
        "archive"
    ],
    "wof:name":"Volksbibliothek",
    "wof:placetype":"venue"
},
  "geometry": {"coordinates":[7.983643,47.318893],"type":"Point"}
}