{
  "type": "Feature",
  "properties": {
    "iso:country":"CH",
    "sg:address":"Beaulieustrasse 55",
    "sg:city":"Bern",
    "sg:orig_category":"Vereine Gesang",
    "sg:phone":"+41 31 301 34 12",
    "sg:postcode":"3012",
    "sg:province":"Bern",
    "wof:name":"M\u00e4nnerchor Der Eisenbahner Bern C/o Freies Gymnasium",
    "wof:placetype":"venue"
},
  "geometry": {"coordinates":[7.4342489243,46.9598960876],"type":"Point"}
}