{
  "type": "Feature",
  "properties": {
    "iso:country":"CH",
    "sg:address":"Neug\u00fcterstrasse 3",
    "sg:city":"Felsberg",
    "sg:orig_category":"Ger\u00fcstbau",
    "sg:phone":"+41 81 252 05 03",
    "sg:postcode":"7012",
    "sg:province":"Graubunden",
    "wof:name":"Marcel Broger Ger\u00fcstbau",
    "wof:placetype":"venue"
},
  "geometry": {"coordinates":[9.4806661606,46.8475608826],"type":"Point"}
}