{
  "type": "Feature",
  "properties": {
    "iso:country":"CH",
    "sg:address":"Dornacherstrasse 161",
    "sg:city":"Basel",
    "sg:orig_category":"Unclassifiable Establishments",
    "sg:postcode":"4053",
    "sg:province":"Basel-Stadt",
    "wof:name":"Continue Ag Multimedia, Internet, Print",
    "wof:placetype":"venue"
},
  "geometry": {"coordinates":[7.5922322273,47.5424194336],"type":"Point"}
}