{
  "type": "Feature",
  "properties": {
    "iso:country":"CH",
    "sg:address":"Bahnhofstrasse 6",
    "sg:city":"Thun",
    "sg:orig_category":"Non-Classified Establishments",
    "sg:postcode":"3600",
    "sg:province":"Bern",
    "wof:name":"Krebsstiftung Thun-berner Oberland",
    "wof:placetype":"venue"
},
  "geometry": {"coordinates":[7.6296210289,46.7560157776],"type":"Point"}
}