{
  "type": "Feature",
  "properties": {
    "iso:country":"CH",
    "sg:address":"Chemin Des Vignes 10a",
    "sg:city":"Chavornay",
    "sg:orig_category":"Elektroinstallation Fernmeldedienste",
    "sg:phone":"+41 24 442 24 22",
    "sg:postcode":"1373",
    "sg:province":"Vaud",
    "wof:name":"Rapin Telecom T\u00e9lecommunication-electricite",
    "wof:placetype":"venue"
},
  "geometry": {"coordinates":[6.5711312294,46.6997718811],"type":"Point"}
}