{
  "type": "Feature",
  "properties": {
    "iso:country":"CH",
    "sg:address":"K\u00e4sershausgasse St\u00f6ckli",
    "sg:city":"Leimiswil",
    "sg:orig_category":"Herstellung von sonstigen landwirtschaftlichen Maschinen",
    "sg:phone":"+41 79 340 95 42",
    "sg:postcode":"4935",
    "sg:province":"Bern",
    "wof:name":"Daniel K\u00e4ser Alfa-laval Servicedienst",
    "wof:placetype":"venue"
},
  "geometry": {"coordinates":[7.7640829086,47.149520874],"type":"Point"}
}