{
  "type": "Feature",
  "properties": {
    "addr:full":"Talackerstrasse 17 Glattbrugg Z\u00fcrich 8152",
    "addr:housenumber":"17",
    "addr:postcode":"8152",
    "addr:street":"Talackerstrasse",
    "iso:country":"CH",
    "sg:address":"Talackerstrasse 17",
    "sg:city":"Glattbrugg",
    "sg:orig_category":"Allgemeiner Hoch U Tiefbau",
    "sg:postcode":"8152",
    "sg:province":"Z\u00fcrich",
    "wof:name":"Baucolor 2000 Gmbh",
    "wof:placetype":"venue"
},
  "geometry": {"coordinates":[9.368124,47.408566],"type":"Point"}
}