{
  "type": "Feature",
  "properties": {
    "iso:country":"CH",
    "sg:address":"1902",
    "sg:city":"Evionnaz",
    "sg:orig_category":"Betrieb von Sportanlagen",
    "sg:postcode":"1902",
    "sg:province":"Valais",
    "wof:name":"Crazygolf Sa",
    "wof:placetype":"venue"
},
  "geometry": {"coordinates":[7.023276,46.177052],"type":"Point"}
}