{
  "type": "Feature",
  "properties": {
    "iso:country":"CH",
    "sg:address":"Buchserstrasse 15",
    "sg:city":"Niederhasli",
    "sg:orig_category":"Instandhaltung U Reparatur von Automobilen",
    "sg:phone":"+41 79 310 25 45",
    "sg:postcode":"8155",
    "sg:province":"Z\u00fcrich",
    "wof:name":"Jutzeler Andreas, Stockhorngarage.",
    "wof:placetype":"venue"
},
  "geometry": {"coordinates":[7.8617801666,49.1125106812],"type":"Point"}
}