{
  "type": "Feature",
  "properties": {
    "addr:full":"Av. Pictet-de-rochemont 33ter Gen\u00e8ve Gen\u00e8ve 1207",
    "addr:housenumber":"33ter",
    "addr:postcode":"1207",
    "addr:street":"Av. Pictet-De-Rochemont",
    "iso:country":"CH",
    "sg:address":"Av. Pictet-de-rochemont 33ter",
    "sg:city":"Gen\u00e8ve",
    "sg:classifiers":[
        {
            "category":"Professional",
            "subcategory":"Accounting & Tax Preparation",
            "type":"Services"
        }
    ],
    "sg:phone":"+41 22 731 73 39",
    "sg:postcode":"1207",
    "sg:province":"Gen\u00e8ve",
    "sg:tags":[
        "lamp",
        "design"
    ],
    "wof:name":"Metalo\u00efd S\u00e0rl",
    "wof:placetype":"venue"
},
  "geometry": {"coordinates":[6.162697,46.200382],"type":"Point"}
}