{
  "type": "Feature",
  "properties": {
    "iso:country":"CH",
    "sg:address":"Route De L'ecole 95",
    "sg:city":"Posieux",
    "sg:orig_category":"Elektroinstallation",
    "sg:phone":"+41 26 411 16 23",
    "sg:postcode":"1725",
    "sg:province":"Fribourg",
    "wof:name":"Electricit\u00e9 Galley Sa",
    "wof:placetype":"venue"
},
  "geometry": {"coordinates":[7.0917220116,46.7594337463],"type":"Point"}
}