{
  "type": "Feature",
  "properties": {
    "iso:country":"CH",
    "sg:address":"Schwerzenbachstrasse",
    "sg:city":"Giswil",
    "sg:orig_category":"Unclassifiable Establishments",
    "sg:postcode":"6074",
    "sg:province":"Obwalden",
    "wof:name":"Thomas Frauenknecht Organisationsentwicklung",
    "wof:placetype":"venue"
},
  "geometry": {"coordinates":[8.1803102493,46.84608078],"type":"Point"}
}