{
  "type": "Feature",
  "properties": {
    "iso:country":"CH",
    "sg:address":"Grundstrasse 21",
    "sg:city":"D\u00fcbendorf",
    "sg:orig_category":"Hardwareberatung",
    "sg:phone":"+41 18202270",
    "sg:postcode":"8600",
    "sg:province":"Z\u00fcrich",
    "wof:name":"Vcs Visual Computing Services Ag Informationsverarbeitende Ger\u00e4te U. Software; Handel, Im, Export. Computeranimationen Usw",
    "wof:placetype":"venue"
},
  "geometry": {"coordinates":[8.6189546585,47.4004516602],"type":"Point"}
}