{
  "type": "Feature",
  "properties": {
    "iso:country":"CH",
    "sg:address":"Loomattenweg 11",
    "sg:city":"Spreitenbach",
    "sg:orig_category":"Non-Classified Establishments",
    "sg:postcode":"8957",
    "sg:province":"Aargau",
    "wof:name":"Portmann R. Berorganizer",
    "wof:placetype":"venue"
},
  "geometry": {"coordinates":[8.3599891663,47.4219589233],"type":"Point"}
}