{
  "type": "Feature",
  "properties": {
    "iso:country":"CH",
    "sg:address":"Bohnackerstrasse 1-3",
    "sg:city":"Dielsdorf",
    "sg:orig_category":"Saunas, Solarien, Fitnesszentren U \u00e4hnliches",
    "sg:phone":"+41 52 246 08 09",
    "sg:postcode":"8157",
    "sg:province":"Z\u00fcrich",
    "wof:name":"Hydrowell Gmbh",
    "wof:placetype":"venue"
},
  "geometry": {"coordinates":[8.7716197968,47.5080108643],"type":"Point"}
}