{
  "type": "Feature",
  "properties": {
    "iso:country":"CH",
    "sg:address":"Holeestrasse 149",
    "sg:city":"Basel",
    "sg:orig_category":"Wirtschaftspr\u00fcfung, Steuerberatung U Treuhand",
    "sg:phone":"+41 61 302 78 77",
    "sg:postcode":"4054",
    "sg:province":"Basel-Stadt",
    "wof:name":"Comtex Revisions Ag",
    "wof:placetype":"venue"
},
  "geometry": {"coordinates":[7.5658888817,47.5462226868],"type":"Point"}
}