{
  "type": "Feature",
  "properties": {
    "iso:country":"CH",
    "sg:address":"Rue Grand-ch\u00e2telain 3",
    "sg:city":"Vouvry",
    "sg:orig_category":"Vermittlung von Immobilien",
    "sg:phone":"+41 24 481 12 12",
    "sg:postcode":"1896",
    "sg:province":"Valais",
    "wof:name":"Vuadens C\u00e9cile",
    "wof:placetype":"venue"
},
  "geometry": {"coordinates":[6.8913798332,46.3356590271],"type":"Point"}
}