{
  "type": "Feature",
  "properties": {
    "iso:country":"CH",
    "sg:address":"Rheinstrasse 51",
    "sg:city":"Frauenfeld",
    "sg:classifiers":[
        {
            "category":"Restaurant",
            "type":"Food & Drink"
        }
    ],
    "sg:phone":"+41 17371152",
    "sg:postcode":"8500",
    "sg:province":"Thurgau",
    "wof:name":"Restaurant Metzgerst\u00fcbli",
    "wof:placetype":"venue"
},
  "geometry": {"coordinates":[8.4618701935,47.3522262573],"type":"Point"}
}