{
  "type": "Feature",
  "properties": {
    "iso:country":"CH",
    "sg:address":"Unterdorf 6b",
    "sg:city":"Nieder\u00f6sch",
    "sg:orig_category":"Fussboden, Fliesen U Plattenlegerei, Tapeziererei",
    "sg:phone":"+41 34 413 02 92",
    "sg:postcode":"3424",
    "sg:province":"Bern",
    "wof:name":"Schipo Schiegg R.",
    "wof:placetype":"venue"
},
  "geometry": {"coordinates":[7.6148099899,47.119884491],"type":"Point"}
}