{
  "type": "Feature",
  "properties": {
    "iso:country":"CH",
    "sg:address":"Malagnou Route De 52 1208 Gen\u00e8ve. Postfach",
    "sg:city":"Gen\u00e8ve",
    "sg:orig_category":"Fachdetailhandel in Verkaufsr\u00e4umen",
    "sg:postcode":"1208",
    "sg:province":"Gen\u00e8ve",
    "wof:name":"Girod Florence",
    "wof:placetype":"venue"
},
  "geometry": {"coordinates":[6.1634287834,46.1965026855],"type":"Point"}
}