{
  "type": "Feature",
  "properties": {
    "iso:country":"CH",
    "sg:address":"St. Gallerstrasse 28",
    "sg:city":"Rehetobel",
    "sg:classifiers":[
        {
            "category":"Restaurant",
            "type":"Food & Drink"
        }
    ],
    "sg:phone":"+41 71 877 12 90",
    "sg:postcode":"9038",
    "sg:province":"Appenzell Ausserrhoden",
    "wof:name":"Restaurant Weinburg",
    "wof:placetype":"venue"
},
  "geometry": {"coordinates":[9.4804363251,47.4283065796],"type":"Point"}
}