{
  "type": "Feature",
  "properties": {
    "iso:country":"CH",
    "sg:address":"Trockenloostrasse 1",
    "sg:city":"Regensdorf",
    "sg:orig_category":"Architektur U Ingenieurb\u00fcros",
    "sg:phone":"+41 27 322 60 76",
    "sg:postcode":"8105",
    "sg:province":"Z\u00fcrich",
    "wof:name":"Csd Ing\u00e9nieurs Conseils Sa",
    "wof:placetype":"venue"
},
  "geometry": {"coordinates":[7.357139,46.230961],"type":"Point"}
}