{
  "type": "Feature",
  "properties": {
    "iso:country":"CH",
    "sg:address":"Viale Carlo Stoppa 1",
    "sg:city":"Chiasso",
    "sg:orig_category":"RESTAURANTS: TEA-ROOMS",
    "sg:postcode":"6830",
    "sg:province":"Ticino",
    "wof:name":"Balsamini Renata",
    "wof:placetype":"venue"
},
  "geometry": {"coordinates":[9.0327882767,45.8365936279],"type":"Point"}
}