{
  "type": "Feature",
  "properties": {
    "iso:country":"CH",
    "sg:address":"Ruchweg 3",
    "sg:city":"Tuggen",
    "sg:orig_category":"Herstellung von Drahtwaren Herstellung von keramischen Haushaltswaren U Ziergegenst\u00e4nden",
    "sg:phone":"+41 79 404 49 79",
    "sg:postcode":"8856",
    "sg:province":"Schwyz",
    "wof:name":"E. Boppart Ag",
    "wof:placetype":"venue"
},
  "geometry": {"coordinates":[8.2945404053,47.3471717834],"type":"Point"}
}