{
  "type": "Feature",
  "properties": {
    "iso:country":"CH",
    "sg:address":"Poststrasse 14b 8805 Richterswil. Postfach",
    "sg:city":"Richterswil",
    "sg:orig_category":"Polizei",
    "sg:phone":"+41 17840100",
    "sg:postcode":"8805",
    "sg:province":"Z\u00fcrich",
    "wof:name":"Kantonspolizei",
    "wof:placetype":"venue"
},
  "geometry": {"coordinates":[8.7058153152,47.2083435059],"type":"Point"}
}