{
  "type": "Feature",
  "properties": {
    "iso:country":"CH",
    "sg:address":"Via Luigi Lavizzari 19",
    "sg:city":"Mendrisio",
    "sg:classifiers":[
        {
            "category":"Insurance",
            "subcategory":"Insurance Agent",
            "type":"Services"
        }
    ],
    "sg:phone":"+41 91 640 45 40",
    "sg:postcode":"6850",
    "sg:province":"Ticino",
    "sg:tags":[
        "versicherungsagenturen",
        "-broker"
    ],
    "wof:name":"Basilese Assicurazioni Agenzia Gian Paolo Tommasini",
    "wof:placetype":"venue"
},
  "geometry": {"coordinates":[8.9866161346,45.8704681396],"type":"Point"}
}