{
  "type": "Feature",
  "properties": {
    "iso:country":"CH",
    "sg:address":"Schulhausstrasse 2a",
    "sg:city":"Lommiswil",
    "sg:orig_category":"Sonstige mit der Informatik verbundene T\u00e4tigkeiten",
    "sg:phone":"+41 32 641 30 10",
    "sg:postcode":"4514",
    "sg:province":"Solothurn",
    "wof:name":"Andragogics Gmbh",
    "wof:placetype":"venue"
},
  "geometry": {"coordinates":[7.4727988243,47.2251777649],"type":"Point"}
}