{
  "type": "Feature",
  "properties": {
    "iso:country":"CH",
    "sg:address":"Aegeristrasse 17",
    "sg:city":"Zug",
    "sg:orig_category":"Werbegrafikateliers",
    "sg:phone":"+41 41 711 51 13",
    "sg:postcode":"6300",
    "sg:province":"Zug",
    "wof:name":"Daniel Bamert Kunstmaler Grafiker Kreakurs",
    "wof:placetype":"venue"
},
  "geometry": {"coordinates":[8.5178146362,47.166431427],"type":"Point"}
}