{
  "type": "Feature",
  "properties": {
    "iso:country":"CH",
    "sg:address":"Kapellenweg 3 5600 Lenzburg. Postfach",
    "sg:city":"Lenzburg",
    "sg:classifiers":[
        {
            "category":"Professional",
            "subcategory":"Employment Agencies",
            "type":"Services"
        }
    ],
    "sg:postcode":"5600",
    "sg:province":"Aargau",
    "sg:tags":[
        "personal",
        "u",
        "stellenvermittlung"
    ],
    "wof:name":"Perspektiva-entwicklungsberatung, Inh. Mani A.",
    "wof:placetype":"venue"
},
  "geometry": {"coordinates":[8.1866674423,47.3906898499],"type":"Point"}
}