{
  "type": "Feature",
  "properties": {
    "iso:country":"CH",
    "sg:address":"Tanneurs Rue Des 2",
    "sg:city":"Pruntrut",
    "sg:orig_category":"Detailhandel mit Bekleidung",
    "sg:postcode":"2900",
    "sg:province":"Jura",
    "wof:name":"Babey Rachel",
    "wof:placetype":"venue"
},
  "geometry": {"coordinates":[7.076585,47.41774],"type":"Point"}
}