{
  "type": "Feature",
  "properties": {
    "iso:country":"CH",
    "sg:address":"Rte De Pr\u00e9-bois 20",
    "sg:city":"Meyrin",
    "sg:orig_category":"Vermietung von Luftfahrzeugen",
    "sg:postcode":"1217",
    "sg:province":"Gen\u00e8ve",
    "wof:name":"Cordaz Mauro",
    "wof:placetype":"venue"
},
  "geometry": {"coordinates":[7.0641651154,47.0518341064],"type":"Point"}
}