{
  "type": "Feature",
  "properties": {
    "iso:country":"CH",
    "sg:address":"Usteristrasse 17",
    "sg:city":"Z\u00fcrich",
    "sg:orig_category":"Arztpraxen",
    "sg:phone":"+41 12117388",
    "sg:postcode":"8001",
    "sg:province":"Z\u00fcrich",
    "wof:name":"Dr.med.anne-marie Benz Spezial\u00e4rztin Fmh",
    "wof:placetype":"venue"
},
  "geometry": {"coordinates":[8.536716,47.375687],"type":"Point"}
}