{
  "type": "Feature",
  "properties": {
    "iso:country":"CH",
    "sg:address":"Bleicherweg 11 4102 Binningen. Postfach 393",
    "sg:city":"Binningen",
    "sg:orig_category":"Non-Classified Establishments",
    "sg:phone":"+41 61 302 73 75",
    "sg:postcode":"4102",
    "sg:province":"Basel-Landschaft",
    "wof:name":"B\u00fcchner Ag",
    "wof:placetype":"venue"
},
  "geometry": {"coordinates":[7.5667910576,47.5421066284],"type":"Point"}
}