{
  "type": "Feature",
  "properties": {
    "iso:country":"CH",
    "sg:address":"Furtrainstrasse 11",
    "sg:city":"B\u00fclach",
    "sg:orig_category":"Unclassifiable Establishments",
    "sg:postcode":"8180",
    "sg:province":"Z\u00fcrich",
    "wof:name":"Weisser Ring",
    "wof:placetype":"venue"
},
  "geometry": {"coordinates":[8.5297031403,47.5205841064],"type":"Point"}
}