{
  "type": "Feature",
  "properties": {
    "iso:country":"CH",
    "sg:address":"Niederhaslistrasse 12",
    "sg:city":"Dielsdorf",
    "sg:orig_category":"Herstellung von sonstigen Erzeugnissen",
    "sg:postcode":"8157",
    "sg:province":"Z\u00fcrich",
    "wof:name":"Fuji Ballon Team Club",
    "wof:placetype":"venue"
},
  "geometry": {"coordinates":[8.4641675949,47.4829292297],"type":"Point"}
}