{
  "type": "Feature",
  "properties": {
    "iso:country":"CH",
    "sg:address":"Freiburgstrasse 370",
    "sg:city":"Bern",
    "sg:orig_category":"Forschung U Entwicklung",
    "sg:phone":"+41 71 274 74 74",
    "sg:postcode":"3018",
    "sg:province":"Bern",
    "wof:name":"Empa Eidg. Materialpr\u00fcfungs-& Forschungsanstalt",
    "wof:placetype":"venue"
},
  "geometry": {"coordinates":[9.3405218124,47.4129104614],"type":"Point"}
}