{
  "type": "Feature",
  "properties": {
    "iso:country":"CH",
    "sg:address":"Gerlafingenstrasse 4",
    "sg:city":"Kriegstetten",
    "sg:classifiers":[
        {
            "category":"Social Services",
            "subcategory":"Retirement Home",
            "type":"Services"
        }
    ],
    "sg:phone":"+41 32 675 26 84",
    "sg:postcode":"4566",
    "sg:province":"Solothurn",
    "sg:tags":[
        "pflegeheime",
        "u",
        "alters"
    ],
    "wof:name":"Seniorenheim Kriegstetten",
    "wof:placetype":"venue"
},
  "geometry": {"coordinates":[7.589244,47.173618],"type":"Point"}
}