{
  "type": "Feature",
  "properties": {
    "iso:country":"CH",
    "sg:address":"Allmigstrasse 4 8841 Gross. Postfach",
    "sg:city":"Gross",
    "sg:orig_category":"Herstellung von sonstigen elektrischen Ausr\u00fcstungen",
    "sg:postcode":"8841",
    "sg:province":"Schwyz",
    "wof:name":"Sinani, Ochsner-f\u00e4h Daniel",
    "wof:placetype":"venue"
},
  "geometry": {"coordinates":[8.7816553116,47.11302948],"type":"Point"}
}