{
  "type": "Feature",
  "properties": {
    "iso:country":"CH",
    "sg:address":"Hermandingen 72",
    "sg:city":"Auswil",
    "sg:classifiers":[
        {
            "category":"Insurance",
            "subcategory":"Insurance Agent",
            "type":"Services"
        }
    ],
    "sg:phone":"+41 800 808 080",
    "sg:postcode":"4944",
    "sg:province":"Bern",
    "sg:tags":[
        "versicherungsagenturen",
        "-broker"
    ],
    "wof:name":"Z\u00fcrich Versicherungen Agentur Heinz Jordi",
    "wof:placetype":"venue"
},
  "geometry": {"coordinates":[7.8433761597,47.1374740601],"type":"Point"}
}