{
  "type": "Feature",
  "properties": {
    "iso:country":"CH",
    "sg:address":"Hofh\u00f6lzliweg 6",
    "sg:city":"Z\u00fcrich",
    "sg:orig_category":"Sportvereine Unihockey",
    "sg:phone":"+41 13710923",
    "sg:postcode":"8046",
    "sg:province":"Z\u00fcrich",
    "wof:name":"Unihockey Team Z\u00fcrich- Affoltern",
    "wof:placetype":"venue"
},
  "geometry": {"coordinates":[8.526432991,47.4102249146],"type":"Point"}
}