{
  "type": "Feature",
  "properties": {
    "iso:country":"CH",
    "sg:address":"Rennweg 20 4052 Basel. Postfach 174",
    "sg:city":"Riehen",
    "sg:orig_category":"Geb\u00e4ude, Wohnungsreinigung Reinigungsgewerbe",
    "sg:phone":"+41 61 603 23 15",
    "sg:postcode":"4125",
    "sg:province":"Basel-Stadt",
    "wof:name":"Abac-reinigung M. Campinari",
    "wof:placetype":"venue"
},
  "geometry": {"coordinates":[7.6047129631,47.5510749817],"type":"Point"}
}