{
  "type": "Feature",
  "properties": {
    "iso:country":"CH",
    "sg:address":"Baumgartenstr. 15 8200 Schaffhausen. Postfach 692",
    "sg:city":"Schaffhausen",
    "sg:orig_category":"Interessenvertretungen",
    "sg:postcode":"8201",
    "sg:province":"Schaffhausen",
    "wof:name":"Homberger Stipendienstiftung",
    "wof:placetype":"venue"
},
  "geometry": {"coordinates":[8.6368761063,47.6945114136],"type":"Point"}
}