{
  "type": "Feature",
  "properties": {
    "iso:country":"CH",
    "sg:address":"Bucheggstrasse 141 8057 Z\u00fcrich. Postfach 292",
    "sg:city":"Z\u00fcrich",
    "sg:orig_category":"Grosshandel mit B\u00fcromaschinen Grosshandel mit Datenverarbeitungsger\u00e4ten",
    "sg:phone":"+41 13638050",
    "sg:postcode":"8057",
    "sg:province":"Z\u00fcrich",
    "wof:name":"Gn\u00e4dinger & Davoli Ag",
    "wof:placetype":"venue"
},
  "geometry": {"coordinates":[8.5393104553,47.3987541199],"type":"Point"}
}