{
  "type": "Feature",
  "properties": {
    "iso:country":"CH",
    "sg:address":"Batailles Chemin Des 22",
    "sg:city":"Vernier",
    "sg:orig_category":"Unclassifiable Establishments",
    "sg:phone":"+41 34 431 26 19",
    "sg:postcode":"1214",
    "sg:province":"Gen\u00e8ve",
    "wof:name":"Cas Scheidegger Holding Ag",
    "wof:placetype":"venue"
},
  "geometry": {"coordinates":[7.7966070175,47.0409126282],"type":"Point"}
}