{
  "type": "Feature",
  "properties": {
    "iso:country":"CH",
    "sg:address":"Rue Des Remparts 5",
    "sg:city":"Sitten",
    "sg:orig_category":"Detailhandel mit B\u00fcchern Detailhandel mit B\u00fcchern, Zeitungen, Schreib U Papeteriewaren",
    "sg:phone":"+41 27 323 64 50",
    "sg:postcode":"1950",
    "sg:province":"Valais",
    "wof:name":"Michellod Elsa",
    "wof:placetype":"venue"
},
  "geometry": {"coordinates":[7.359161,46.232521],"type":"Point"}
}