{
  "type": "Feature",
  "properties": {
    "iso:country":"CH",
    "sg:address":"Ankerweg 5",
    "sg:city":"Ipsach",
    "sg:classifiers":[
        {
            "category":"Personal",
            "subcategory":"Nail Salon",
            "type":"Services"
        }
    ],
    "sg:phone":"+41 32 331 31 21",
    "sg:postcode":"2563",
    "sg:province":"Bern",
    "sg:tags":[
        "manicure"
    ],
    "wof:name":"Nail Creations Maurer Daniela",
    "wof:placetype":"venue"
},
  "geometry": {"coordinates":[7.2319989204,47.1147270203],"type":"Point"}
}