{
  "type": "Feature",
  "properties": {
    "iso:country":"CH",
    "sg:address":"1127",
    "sg:city":"Clarmont",
    "sg:orig_category":"Gemeindeverwaltungen",
    "sg:phone":"+41 21 800 37 95",
    "sg:postcode":"1127",
    "sg:province":"Vaud",
    "wof:name":"Administration Communale De Clarmont",
    "wof:placetype":"venue"
},
  "geometry": {"coordinates":[6.4504499435,46.5495109558],"type":"Point"}
}