{
  "type": "Feature",
  "properties": {
    "iso:country":"CH",
    "sg:address":"Brunnmattstrasse 4a 3414 Oberburg. Postfach",
    "sg:city":"Oberburg",
    "sg:orig_category":"Detailhandel mit Brot, Back U S\u00fcsswaren Herstellung von Dauerbackwaren",
    "sg:phone":"+41 34 423 39 30",
    "sg:postcode":"3414",
    "sg:province":"Bern",
    "wof:name":"Robe-backwaren Ag",
    "wof:placetype":"venue"
},
  "geometry": {"coordinates":[7.630063,47.041035],"type":"Point"}
}