{
  "type": "Feature",
  "properties": {
    "iso:country":"CH",
    "sg:address":"Place Du Porte 17-19",
    "sg:city":"Lausanne",
    "sg:orig_category":"Detailhandel mit Uhren U Schmuck Reparatur von Uhren U Schmuck",
    "sg:phone":"+41 71 222 11 55",
    "sg:postcode":"1006",
    "sg:province":"Vaud",
    "wof:name":"Gut & Co Goldschmiede Uhrmacher",
    "wof:placetype":"venue"
},
  "geometry": {"coordinates":[9.3763990402,47.4258041382],"type":"Point"}
}