{
  "type": "Feature",
  "properties": {
    "iso:country":"CH",
    "sg:address":"Hauptstrasse 272 5053 Staffelbach. Postfach",
    "sg:city":"Staffelbach",
    "sg:orig_category":"Detailhandel mit Bekleidung",
    "sg:postcode":"5053",
    "sg:province":"Aargau",
    "wof:name":"Ro-ma Jeans & Wear, Wilhelm + D\u00e4twyler",
    "wof:placetype":"venue"
},
  "geometry": {"coordinates":[8.041622,47.286911],"type":"Point"}
}