{
  "type": "Feature",
  "properties": {
    "iso:country":"CH",
    "sg:address":"Bleichestrasse 27 4058 Basel. Postfach 327",
    "sg:city":"Basel",
    "sg:orig_category":"Sonstige Verkehrsvermittlung",
    "sg:phone":"+41 61 691 13 13",
    "sg:postcode":"4021",
    "wof:name":"Mts Messe Service Ag",
    "wof:placetype":"venue"
},
  "geometry": {"coordinates":[7.6015381813,47.5662727356],"type":"Point"}
}