{
  "type": "Feature",
  "properties": {
    "iso:country":"CH",
    "sg:address":"Rue De La Constituante 4",
    "sg:city":"Del\u00e9mont",
    "sg:orig_category":"Tanzschulen, Tanzlehrer",
    "sg:phone":"+41 32 422 95 09",
    "sg:postcode":"2800",
    "sg:province":"Jura",
    "wof:name":"In\u00e8s Meury Bertaiola Ecole De Danse Classique",
    "wof:placetype":"venue"
},
  "geometry": {"coordinates":[7.3423571587,47.3648529053],"type":"Point"}
}