{
  "type": "Feature",
  "properties": {
    "iso:country":"CH",
    "sg:address":"Bahnhofstrasse 16 3400 Burgdorf. Postfach",
    "sg:city":"Burgdorf",
    "sg:orig_category":"Innenarchitekturb\u00fcros Verwaltung von Immobilien",
    "sg:phone":"+41 34 422 40 05",
    "sg:postcode":"3401",
    "sg:province":"Bern",
    "wof:name":"Raum-ideen Gmbh",
    "wof:placetype":"venue"
},
  "geometry": {"coordinates":[7.6236820221,47.0595664978],"type":"Point"}
}