{
  "type": "Feature",
  "properties": {
    "iso:country":"CH",
    "sg:address":"Gotthardstrasse 33d",
    "sg:city":"Oberarth",
    "sg:orig_category":"Alters U Pflegeheime Institutionen f\u00fcr Behinderte",
    "sg:phone":"+41 55 256 78 78",
    "sg:postcode":"6414",
    "sg:province":"Schwyz",
    "wof:name":"Alters-& Pflegeheim Gr\u00fcnegg Karl Meerstetter",
    "wof:placetype":"venue"
},
  "geometry": {"coordinates":[8.9413,47.28841],"type":"Point"}
}