{
  "type": "Feature",
  "properties": {
    "iso:country":"CH",
    "sg:address":"Route De Cl\u00e9menty 60",
    "sg:city":"Nyon",
    "sg:orig_category":"Architektur U Ingenieurb\u00fcros Geometerb\u00fcros",
    "sg:phone":"+41 22 361 88 40",
    "sg:postcode":"1260",
    "sg:province":"Vaud",
    "wof:name":"Schenk Bernard Sa",
    "wof:placetype":"venue"
},
  "geometry": {"coordinates":[6.229004,46.381302],"type":"Point"}
}