{
  "type": "Feature",
  "properties": {
    "iso:country":"CH",
    "sg:address":"Gewerbestrasse 7",
    "sg:city":"Allschwil",
    "sg:orig_category":"Zahntechnische Laboratorien",
    "sg:phone":"+41 27 322 64 36",
    "sg:postcode":"4123",
    "sg:province":"Basel-Landschaft",
    "wof:name":"Raphy Knupfer Laboratoire Dentaire Permadent",
    "wof:placetype":"venue"
},
  "geometry": {"coordinates":[7.3605527878,46.2346343994],"type":"Point"}
}