{
  "type": "Feature",
  "properties": {
    "iso:country":"CH",
    "sg:address":"Via Giovan Battist Pioda 12",
    "sg:city":"Lugano",
    "sg:orig_category":"Wirtschaftspr\u00fcfung, Steuerberatung U Treuhand",
    "sg:phone":"+41 91 921 07 41",
    "sg:postcode":"6900",
    "sg:province":"Ticino",
    "wof:name":"Studio Fiduciario Botta Cristiano",
    "wof:placetype":"venue"
},
  "geometry": {"coordinates":[8.9544038773,46.0073471069],"type":"Point"}
}