{
  "type": "Feature",
  "properties": {
    "iso:country":"CH",
    "sg:address":"6516",
    "sg:city":"Cugnasco",
    "sg:orig_category":"Campingpl\u00e4tze Detailhandel mit Zeitungen U Zeitschriften Kioske",
    "sg:phone":"+41 91 859 16 88",
    "sg:postcode":"6516",
    "sg:province":"Ticino",
    "wof:name":"Campeggio Riarena",
    "wof:placetype":"venue"
},
  "geometry": {"coordinates":[8.91774,46.175251],"type":"Point"}
}