{
  "type": "Feature",
  "properties": {
    "iso:country":"CH",
    "sg:address":"Metzggasse 8 8400 Winterthur. Postfach",
    "sg:city":"Winterthur",
    "sg:orig_category":"Non-Classified Establishments",
    "sg:postcode":"8400",
    "sg:province":"Z\u00fcrich",
    "wof:name":"K\u00fcng Alex, Second Electronics",
    "wof:placetype":"venue"
},
  "geometry": {"coordinates":[8.8971567154,47.1867675781],"type":"Point"}
}