{
  "type": "Feature",
  "properties": {
    "iso:country":"CH",
    "sg:address":"Loostrasse 13 8803 R\u00fcschlikon. Postfach",
    "sg:city":"R\u00fcschlikon",
    "sg:orig_category":"Oberfl\u00e4chenveredlung U W\u00e4rmebehandlung",
    "sg:postcode":"8803",
    "sg:province":"Z\u00fcrich",
    "wof:name":"Gr Technologie Ag Produkte Und Dienstleistungen F\u00fcr Die Oberfl\u00e4chenbehandlung Und Den Anlage Und Maschinenbau; Herstellung Und Handel Usw",
    "wof:placetype":"venue"
},
  "geometry": {"coordinates":[8.5447683334,47.3055648804],"type":"Point"}
}