{
  "type": "Feature",
  "properties": {
    "iso:country":"CH",
    "sg:address":"Riedstrasse 7",
    "sg:city":"Cham",
    "sg:orig_category":"Herstellung von elektronischen Bauelementen",
    "sg:phone":"+41 41 743 07 71",
    "sg:postcode":"6330",
    "sg:province":"Zug",
    "wof:name":"Fierz K",
    "wof:placetype":"venue"
},
  "geometry": {"coordinates":[8.4766769409,47.1891326904],"type":"Point"}
}