{
  "type": "Feature",
  "properties": {
    "iso:country":"CH",
    "sg:address":"Sternengasse 6 4051 Basel. Postfach",
    "sg:city":"Basel",
    "sg:orig_category":"Pensionskassen",
    "sg:phone":"+41 61 271 01 55",
    "sg:postcode":"4051",
    "sg:province":"Basel-Stadt",
    "wof:name":"Personalf\u00fcrsorgestiftung Der Baum Ag",
    "wof:placetype":"venue"
},
  "geometry": {"coordinates":[7.5931110382,47.5522346497],"type":"Point"}
}