{
  "type": "Feature",
  "properties": {
    "iso:country":"CH",
    "sg:address":"4115",
    "sg:city":"Mariastein",
    "sg:orig_category":"Wohnheime",
    "sg:phone":"+41 61 735 11 41",
    "sg:postcode":"4115",
    "sg:province":"Solothurn",
    "wof:name":"Kloster Mariastein",
    "wof:placetype":"venue"
},
  "geometry": {"coordinates":[7.4898700714,47.4764099121],"type":"Point"}
}