{
  "type": "Feature",
  "properties": {
    "iso:country":"CH",
    "sg:address":"Neuhofstr. 9 6032 Emmen. Postfach",
    "sg:city":"Emmenbr\u00fccke",
    "sg:orig_category":"Maler U Glasergewerbe",
    "sg:phone":"+41 41 281 14 17",
    "sg:postcode":"6020",
    "sg:province":"Luzern",
    "wof:name":"Birrer Heinz",
    "wof:placetype":"venue"
},
  "geometry": {"coordinates":[8.2575540543,47.0716438293],"type":"Point"}
}