{
  "type": "Feature",
  "properties": {
    "iso:country":"CH",
    "sg:address":"Brunnmatt Lindencham",
    "sg:city":"Cham",
    "sg:orig_category":"Grosshandel mit Maschinen U Ausr\u00fcstungen Grosshandel mit sonstigen Nahrungsmitteln",
    "sg:phone":"+41 41 780 83 72",
    "sg:postcode":"6330",
    "sg:province":"Zug",
    "wof:name":"Josef Nietlispach B\u00e4ckereimaschinen",
    "wof:placetype":"venue"
},
  "geometry": {"coordinates":[8.4589233398,47.1807899475],"type":"Point"}
}