{
  "type": "Feature",
  "properties": {
    "iso:country":"CH",
    "sg:address":"1623",
    "sg:city":"Semsales",
    "sg:orig_category":"Verwertung von Milch",
    "sg:postcode":"1623",
    "sg:province":"Fribourg",
    "wof:name":"Soci\u00e9t\u00e9 De Laiterie De Sen\u00e8des",
    "wof:placetype":"venue"
},
  "geometry": {"coordinates":[7.1783599854,46.7523612976],"type":"Point"}
}