{
  "type": "Feature",
  "properties": {
    "iso:country":"CH",
    "sg:address":"Rebbergstrasse 48",
    "sg:city":"Ennetbaden",
    "sg:orig_category":"Blumen U Zierpflanzenbau",
    "sg:phone":"+41 56 222 78 59",
    "sg:postcode":"5408",
    "sg:province":"Aargau",
    "wof:name":"Otto Wetzel Blumeng\u00e4rtnerei",
    "wof:placetype":"venue"
},
  "geometry": {"coordinates":[8.321455,47.482151],"type":"Point"}
}