{
  "type": "Feature",
  "properties": {
    "iso:country":"CH",
    "sg:address":"Emil Frey-strasse 85",
    "sg:city":"M\u00fcnchenstein",
    "sg:orig_category":"Grosshandel mit Datenverarbeitungsger\u00e4ten Softwareentwicklung U beratung",
    "sg:phone":"+41 61 401 09 44",
    "sg:postcode":"4142",
    "sg:province":"Basel-Landschaft",
    "wof:name":"Webland Internet Service, Leu Fredy",
    "wof:placetype":"venue"
},
  "geometry": {"coordinates":[7.6120471954,47.5284194946],"type":"Point"}
}