{
  "type": "Feature",
  "properties": {
    "iso:country":"CH",
    "sg:address":"Rinaustrasse 286",
    "sg:city":"Kaiseraugst",
    "sg:orig_category":"Grosshandel mit Werkzeugmaschinen Herstellung von Werkzeugmaschinen",
    "sg:phone":"+41 61 811 55 45",
    "sg:postcode":"4303",
    "sg:province":"Aargau",
    "wof:name":"Ridem Ag Profiltechnik",
    "wof:placetype":"venue"
},
  "geometry": {"coordinates":[7.7323122025,47.5407867432],"type":"Point"}
}