{
  "type": "Feature",
  "properties": {
    "iso:country":"CH",
    "sg:address":"La Tena 1997 Haute-nendaz. Postfach",
    "sg:city":"Haute-nendaz",
    "sg:orig_category":"Handelsvermittlung U Grosshandel Unternehmensberatung",
    "sg:phone":"+41 27 288 23 35",
    "sg:postcode":"1997",
    "sg:province":"Valais",
    "wof:name":"Mawico Sa",
    "wof:placetype":"venue"
},
  "geometry": {"coordinates":[7.2981119156,46.1841583252],"type":"Point"}
}