{
  "type": "Feature",
  "properties": {
    "addr:full":"R\u00e4llikon 787 Hinteregg Z\u00fcrich 8132",
    "addr:housenumber":"787",
    "addr:postcode":"8132",
    "iso:country":"CH",
    "sg:address":"R\u00e4llikon 787",
    "sg:city":"Hinteregg",
    "sg:orig_category":"Ausbaugewerbe",
    "sg:phone":"+41 19841641",
    "sg:postcode":"8132",
    "sg:province":"Z\u00fcrich",
    "wof:name":"Peter Hardmeier Ag",
    "wof:placetype":"venue"
},
  "geometry": {"coordinates":[8.690055,47.300556],"type":"Point"}
}