{
  "type": "Feature",
  "properties": {
    "iso:country":"CH",
    "sg:address":"Laubstrasse 10",
    "sg:city":"Schwyz",
    "sg:orig_category":"Interessenvertretungen Wasserversorgung",
    "sg:phone":"+41 41 811 54 04",
    "sg:postcode":"6430",
    "sg:province":"Schwyz",
    "wof:name":"Dorfgenossenschaft Schwyz",
    "wof:placetype":"venue"
},
  "geometry": {"coordinates":[8.65995121,47.0209236145],"type":"Point"}
}