{
  "type": "Feature",
  "properties": {
    "iso:country":"CH",
    "sg:address":"Bl\u00e4siring 150",
    "sg:city":"Basel",
    "sg:orig_category":"Detailhandel mit Radio U Fernsehger\u00e4ten Detailhandel mit Schreib U Papeteriewaren",
    "sg:phone":"+41 41 460 23 10",
    "sg:postcode":"4057",
    "sg:province":"Basel-Stadt",
    "wof:name":"Alfons & Pia Aregger Papeterie Lautsprecher",
    "wof:placetype":"venue"
},
  "geometry": {"coordinates":[8.2235832214,47.131149292],"type":"Point"}
}