{
  "type": "Feature",
  "properties": {
    "iso:country":"CH",
    "sg:address":"Dorf",
    "sg:city":"Roggliswil",
    "sg:orig_category":"Vereine Vogel-& Naturschutz",
    "sg:postcode":"6265",
    "sg:province":"Luzern",
    "wof:name":"Ornithol.verein Sursee/umg.",
    "wof:placetype":"venue"
},
  "geometry": {"coordinates":[8.0744695663,47.1829185486],"type":"Point"}
}