{
  "type": "Feature",
  "properties": {
    "iso:country":"CH",
    "sg:address":"Regensdorferstrasse 18",
    "sg:city":"D\u00e4llikon",
    "sg:classifiers":[
        {
            "category":"Community Center",
            "subcategory":"Youth",
            "type":"Public Place"
        }
    ],
    "sg:phone":"+41 18441688",
    "sg:postcode":"8108",
    "sg:province":"Z\u00fcrich",
    "sg:tags":[
        "filter",
        "liquid"
    ],
    "wof:name":"Osmota Oskar Kern Filtertechnik U. -systeme",
    "wof:placetype":"venue"
},
  "geometry": {"coordinates":[8.440328598,47.4395484924],"type":"Point"}
}