{
  "type": "Feature",
  "properties": {
    "iso:country":"CH",
    "sg:address":"Eugen Huber-strasse 21",
    "sg:city":"Z\u00fcrich",
    "sg:orig_category":"Reiseb\u00fcros U Reiseveranstalter",
    "sg:phone":"+41 14300606",
    "sg:postcode":"8048",
    "sg:province":"Z\u00fcrich",
    "wof:name":"Tuarek Fahsi Ouriaghli Mix-tour's",
    "wof:placetype":"venue"
},
  "geometry": {"coordinates":[8.4836874008,47.3852653503],"type":"Point"}
}