{
  "type": "Feature",
  "properties": {
    "iso:country":"CH",
    "sg:address":"Unterer Aareweg 8",
    "sg:city":"Lyss",
    "sg:orig_category":"Detailhandel mit B\u00fcromaschinen U einrichtungen Grosshandel mit B\u00fcromaschinen U einrichtungen",
    "sg:phone":"+41 81 420 15 55",
    "sg:postcode":"3250",
    "sg:province":"Bern",
    "wof:name":"Escher B\u00fcrocenter Ag",
    "wof:placetype":"venue"
},
  "geometry": {"coordinates":[9.85375,46.832729],"type":"Point"}
}