{
  "type": "Feature",
  "properties": {
    "iso:country":"CH",
    "sg:address":"Hertiweg 22",
    "sg:city":"B\u00fclach",
    "sg:orig_category":"Gymnastik U Fitnesszentren",
    "sg:phone":"+41 18622120",
    "sg:postcode":"8180",
    "sg:province":"Z\u00fcrich",
    "wof:name":"Estetica Donna Fitness-center",
    "wof:placetype":"venue"
},
  "geometry": {"coordinates":[8.5384969711,47.5223846436],"type":"Point"}
}