{
  "type": "Feature",
  "properties": {
    "iso:country":"CH",
    "sg:address":"M\u00e4deracher 2",
    "sg:city":"D\u00f6ttingen",
    "sg:orig_category":"Maler U Glasergewerbe Malerei",
    "sg:phone":"+41 79 418 10 88",
    "sg:postcode":"5312",
    "sg:province":"Aargau",
    "wof:name":"R. Voehringer Ag",
    "wof:placetype":"venue"
},
  "geometry": {"coordinates":[8.2567110062,47.5721817017],"type":"Point"}
}