{
  "type": "Feature",
  "properties": {
    "iso:country":"CH",
    "sg:address":"Hauptstrasse 67 2575 T\u00e4uffelen. Postfach 192",
    "sg:city":"T\u00e4uffelen",
    "sg:orig_category":"Herstellung von sonstigen Metallwaren Satzherstellung U Reproduktion",
    "sg:phone":"+41 32 396 25 25",
    "sg:postcode":"2575",
    "sg:province":"Bern",
    "wof:name":"Inter-gravure Gerlach A. & Co",
    "wof:placetype":"venue"
},
  "geometry": {"coordinates":[7.2005181313,47.0697555542],"type":"Point"}
}