{
  "type": "Feature",
  "properties": {
    "iso:country":"CH",
    "sg:address":"Hauptstrasse 44",
    "sg:city":"Hemmental",
    "sg:orig_category":"Bauschreinerei Herstellung von Fenstern U T\u00fcren aus Holz",
    "sg:phone":"+41 52 685 40 53",
    "sg:postcode":"8231",
    "sg:province":"Schaffhausen",
    "wof:name":"Stefan Leu Schreinerei & Fensterbau",
    "wof:placetype":"venue"
},
  "geometry": {"coordinates":[8.5865468979,47.7333374023],"type":"Point"}
}