{
  "type": "Feature",
  "properties": {
    "addr:full":"Metzgergasse 22 Aarau Aargau 5000",
    "addr:housenumber":"22",
    "addr:postcode":"5000",
    "addr:street":"Metzgergasse",
    "iso:country":"CH",
    "sg:address":"Metzgergasse 22",
    "sg:city":"Aarau",
    "sg:orig_category":"Detailhandel mit Brot, Back U S\u00fcsswaren",
    "sg:phone":"+41 62 822 22 41",
    "sg:postcode":"5000",
    "sg:province":"Aargau",
    "wof:name":"Aare B\u00e4ckerei Gmbh",
    "wof:placetype":"venue"
},
  "geometry": {"coordinates":[8.0438,47.393639],"type":"Point"}
}