{
  "type": "Feature",
  "properties": {
    "addr:full":"Landstrasse 49 Oberehrendingen 5422",
    "addr:housenumber":"49",
    "addr:postcode":"5422",
    "addr:street":"Landstrasse;Oberehrendingen",
    "iso:country":"CH",
    "sg:address":"Landstrasse 49",
    "sg:city":"Oberehrendingen",
    "sg:orig_category":"Industrie, Elektronik U Elektrik",
    "sg:phone":"+41 56 203 40 40",
    "sg:postcode":"5422",
    "wof:name":"Deltadrive - Die Digitale Antriebsl\u00f6sung",
    "wof:placetype":"venue"
},
  "geometry": {"coordinates":[8.340626,47.495789],"type":"Point"}
}