{
  "type": "Feature",
  "properties": {
    "iso:country":"CH",
    "sg:address":"St.galler-strasse 39",
    "sg:city":"Winterthur",
    "sg:classifiers":[
        {
            "category":"Government",
            "subcategory":"Post Office",
            "type":"Public Place"
        }
    ],
    "sg:phone":"+41 52 242 83 38",
    "sg:postcode":"8400",
    "sg:province":"Z\u00fcrich",
    "sg:tags":[
        "caf\u00e9s",
        "tea-rooms"
    ],
    "wof:name":"Caf\u00e9 Gabriel",
    "wof:placetype":"venue"
},
  "geometry": {"coordinates":[8.7380962372,47.4984588623],"type":"Point"}
}