{
  "type": "Feature",
  "properties": {
    "addr:full":"Lavaux Route De 29 1802 Corseaux. Postfach Corseaux Vaud 1802",
    "addr:housenumber":"lavaux;29",
    "addr:postcode":"1802 corseaux. postfach corseaux;1802",
    "addr:street":"Route De",
    "iso:country":"CH",
    "sg:address":"Lavaux Route De 29 1802 Corseaux. Postfach",
    "sg:city":"Corseaux",
    "sg:orig_category":"Grosshandel mit Erzen U Metallen",
    "sg:phone":"+41 21 923 00 00",
    "sg:postcode":"1802",
    "sg:province":"Vaud",
    "wof:name":"Uldry Eric Sa",
    "wof:placetype":"venue"
},
  "geometry": {"coordinates":[6.833991,46.471809],"type":"Point"}
}