{
  "type": "Feature",
  "properties": {
    "iso:country":"CH",
    "sg:address":"Rotterdam-strasse 21",
    "sg:city":"Basel",
    "sg:orig_category":"Unclassifiable Establishments",
    "sg:postcode":"4053",
    "sg:province":"Basel-Stadt",
    "wof:name":"Gantex S.a.",
    "wof:placetype":"venue"
},
  "geometry": {"coordinates":[6.8612399101,46.98828125],"type":"Point"}
}