{
  "type": "Feature",
  "properties": {
    "iso:country":"CH",
    "sg:address":"Case Tostale",
    "sg:city":"Vessy",
    "sg:classifiers":[
        {
            "category":"Manufacturing",
            "subcategory":"Printing",
            "type":"Manufacturing & Wholesale Goods"
        }
    ],
    "sg:phone":"+41 22 890 01 30",
    "sg:postcode":"1234",
    "sg:province":"Gen\u00e8ve",
    "sg:tags":[
        "publishing"
    ],
    "wof:name":"Imsynex Sarl",
    "wof:placetype":"venue"
},
  "geometry": {"coordinates":[6.1582798958,46.1719741821],"type":"Point"}
}