{
  "type": "Feature",
  "properties": {
    "iso:country":"CH",
    "sg:address":"Bahnstr. 18",
    "sg:city":"Rupperswil",
    "sg:classifiers":[
        {
            "category":"Wholesale",
            "subcategory":"Machinery & Supplies",
            "type":"Manufacturing & Wholesale Goods"
        }
    ],
    "sg:phone":"+41 71 288 10 35",
    "sg:postcode":"5102",
    "sg:province":"Aargau",
    "sg:tags":[
        "food",
        "processing",
        "-",
        "machine",
        "equipment",
        "engineering",
        "mechanical"
    ],
    "wof:name":"Germann & Frei Ag",
    "wof:placetype":"venue"
},
  "geometry": {"coordinates":[9.4243459702,47.4420318604],"type":"Point"}
}