{
  "type": "Feature",
  "properties": {
    "iso:country":"CH",
    "sg:address":"Birchweg 7",
    "sg:city":"Schaffhausen",
    "sg:orig_category":"Maler U Glasergewerbe",
    "sg:postcode":"8200",
    "sg:province":"Schaffhausen",
    "wof:name":"Maler Und Parkettarbeiten Serifi",
    "wof:placetype":"venue"
},
  "geometry": {"coordinates":[8.6301412582,47.714012146],"type":"Point"}
}