{
  "type": "Feature",
  "properties": {
    "addr:full":"Winzerstrasse 6 Z\u00fcrich Z\u00fcrich 8049",
    "addr:housenumber":"6",
    "addr:postcode":"8049",
    "addr:street":"Winzerstrasse",
    "iso:country":"CH",
    "sg:address":"Winzerstrasse 6",
    "sg:city":"Z\u00fcrich",
    "sg:orig_category":"Architektur U Ingenieurb\u00fcros",
    "sg:phone":"+41 13419001",
    "sg:postcode":"8049",
    "sg:province":"Z\u00fcrich",
    "wof:name":"Albert Josuran Bauten & Sanierungen",
    "wof:placetype":"venue"
},
  "geometry": {"coordinates":[8.493818,47.400478],"type":"Point"}
}