{
  "type": "Feature",
  "properties": {
    "iso:country":"CH",
    "sg:address":"Lausenerstrasse 16",
    "sg:city":"Liestal",
    "sg:orig_category":"Detailhandel mit elektrischen Haushalts-,Radio U Fernsehger\u00e4ten sowie Musikinstrumenten Elektroinsta",
    "sg:phone":"+41 61 927 91 91",
    "sg:postcode":"4410",
    "sg:province":"Basel-Landschaft",
    "wof:name":"Willy Gysin Ag",
    "wof:placetype":"venue"
},
  "geometry": {"coordinates":[7.7485499382,47.4756774902],"type":"Point"}
}