{
  "type": "Feature",
  "properties": {
    "iso:country":"CH",
    "sg:address":"Chalet La Collina 3962 Montana. Postfach",
    "sg:city":"Montana",
    "sg:orig_category":"Elektrizit\u00e4tsversorgung",
    "sg:postcode":"3962",
    "wof:name":"Aqua-tech, Patrick Galley",
    "wof:placetype":"venue"
},
  "geometry": {"coordinates":[6.2354798317,46.4775047302],"type":"Point"}
}