{
  "type": "Feature",
  "properties": {
    "iso:country":"CH",
    "sg:address":"Alpsteinstrasse 6",
    "sg:city":"Appenzell",
    "sg:orig_category":"Maler U Glasergewerbe",
    "sg:phone":"+41 71 787 34 24",
    "sg:postcode":"9050",
    "sg:province":"Appenzell Innerhoden",
    "wof:name":"Peter Sparr",
    "wof:placetype":"venue"
},
  "geometry": {"coordinates":[9.4076833725,47.3314361572],"type":"Point"}
}