{
  "type": "Feature",
  "properties": {
    "iso:country":"CH",
    "sg:address":"Hauptstrasse 111",
    "sg:city":"Frick",
    "sg:orig_category":"Detailhandel mit Textilien Verlegen von Fussboden",
    "sg:phone":"+41 55 240 16 87",
    "sg:postcode":"5070",
    "sg:province":"Aargau",
    "wof:name":"Niederdorfer Robert",
    "wof:placetype":"venue"
},
  "geometry": {"coordinates":[8.8491601944,47.2588844299],"type":"Point"}
}