{
  "type": "Feature",
  "properties": {
    "iso:country":"CH",
    "sg:address":"Reigoldswilerstrasse 12",
    "sg:city":"Bretzwil",
    "sg:orig_category":"Sonstige pers\u00f6nliche Dienstleistungen Unternehmensberatung",
    "sg:phone":"+41 61 941 10 12",
    "sg:postcode":"4207",
    "sg:province":"Basel-Landschaft",
    "wof:name":"Bruggmann Guido Qualit\u00e4tsentwicklung In Bildungsinstitutionen",
    "wof:placetype":"venue"
},
  "geometry": {"coordinates":[7.6537241936,47.3976898193],"type":"Point"}
}