{
  "type": "Feature",
  "properties": {
    "iso:country":"CH",
    "sg:address":"7250 Klosters. Postfach",
    "sg:city":"Klosters",
    "sg:orig_category":"Fachdetailhandel in Verkaufsr\u00e4umen",
    "sg:postcode":"7250",
    "sg:province":"Graubunden",
    "wof:name":"Boner Jakob",
    "wof:placetype":"venue"
},
  "geometry": {"coordinates":[9.8801698685,46.8800468445],"type":"Point"}
}