{
  "type": "Feature",
  "properties": {
    "iso:country":"CH",
    "sg:address":"Route Des Ateliers 1950 Sion Case Postale 487",
    "sg:city":"Sion",
    "sg:orig_category":"G\u00fcterbef\u00f6rderung im Strassenverkehr",
    "sg:phone":"+41 27 203 33 65",
    "sg:postcode":"1951",
    "sg:province":"Valais",
    "wof:name":"Sion-transports S.t. Sa",
    "wof:placetype":"venue"
},
  "geometry": {"coordinates":[7.3697719574,46.2272453308],"type":"Point"}
}