{
  "type": "Feature",
  "properties": {
    "iso:country":"CH",
    "sg:address":"Alte Landstrasse 106 9445 Rebstein. Postfach",
    "sg:city":"Rebstein",
    "sg:orig_category":"Sonstige mit der Informatik verbundene T\u00e4tigkeiten",
    "sg:postcode":"9445",
    "sg:province":"St. Gallen",
    "wof:name":"Hilogix Consulting Ag Management- U. It-beratung. It-bezogene Produkte; Entwicklung, Produktion, Implementation U. Handel Usw",
    "wof:placetype":"venue"
},
  "geometry": {"coordinates":[9.5792655945,47.3969841003],"type":"Point"}
}