{
  "type": "Feature",
  "properties": {
    "iso:country":"CH",
    "sg:address":"Fabrikstrasse 52",
    "sg:city":"Z\u00fcrich",
    "sg:orig_category":"Maler U Glasergewerbe",
    "sg:phone":"+41 12717163",
    "sg:postcode":"8003",
    "sg:province":"Z\u00fcrich",
    "wof:name":"Bodmer Robert Malergesch\u00e4ft",
    "wof:placetype":"venue"
},
  "geometry": {"coordinates":[8.5256299973,47.3843612671],"type":"Point"}
}