{
  "type": "Feature",
  "properties": {
    "iso:country":"CH",
    "sg:address":"B\u00e4ndlistrasse 31",
    "sg:city":"Z\u00fcrich",
    "sg:classifiers":[
        {
            "category":"Food & Beverages",
            "subcategory":"Specialty",
            "type":"Retail Goods"
        }
    ],
    "sg:phone":"+41 14305656",
    "sg:postcode":"8064",
    "sg:province":"Z\u00fcrich",
    "sg:tags":[
        "caterer"
    ],
    "wof:name":"Royal Gourmet Express San H. Speisekurier Mit Produktion U. Hauslieferdienst",
    "wof:placetype":"venue"
},
  "geometry": {"coordinates":[8.486271,47.395779],"type":"Point"}
}