{
  "type": "Feature",
  "properties": {
    "iso:country":"CH",
    "sg:address":"Augartenstrasse 29",
    "sg:city":"M\u00f6rschwil",
    "sg:orig_category":"Unternehmensberatung",
    "sg:postcode":"9402",
    "sg:province":"St. Gallen",
    "wof:name":"Kgm Consulting Gmbh",
    "wof:placetype":"venue"
},
  "geometry": {"coordinates":[8.5877161026,47.3184204102],"type":"Point"}
}