{
  "type": "Feature",
  "properties": {
    "iso:country":"CH",
    "sg:address":"Altschulhaus",
    "sg:city":"Buchrain",
    "sg:orig_category":"Vorschulen, Kinderg\u00e4rten",
    "sg:phone":"+41 41 712 01 58",
    "sg:postcode":"6033",
    "sg:province":"Luzern",
    "wof:name":"Kindergarten",
    "wof:placetype":"venue"
},
  "geometry": {"coordinates":[8.5085449219,47.1477661133],"type":"Point"}
}