{
  "type": "Feature",
  "properties": {
    "iso:country":"CH",
    "sg:address":"Carona Via Marco Da 1",
    "sg:city":"Lugano",
    "sg:orig_category":"Allgemeiner Hoch U Tiefbau",
    "sg:postcode":"6900",
    "sg:province":"Ticino",
    "wof:name":"Andreoli Dante",
    "wof:placetype":"venue"
},
  "geometry": {"coordinates":[8.95823,46.011639],"type":"Point"}
}