{
  "type": "Feature",
  "properties": {
    "iso:country":"CH",
    "sg:address":"Bernstrasse 5",
    "sg:city":"Kehrsatz",
    "sg:orig_category":"Nationale Postdienste",
    "sg:phone":"+41 31 961 31 01",
    "sg:postcode":"3122",
    "sg:province":"Bern",
    "wof:name":"Die Schweizerische Post",
    "wof:placetype":"venue"
},
  "geometry": {"coordinates":[7.4708900452,46.9101295471],"type":"Point"}
}