{
  "type": "Feature",
  "properties": {
    "iso:country":"CH",
    "sg:address":"Chiesa Via Alla 6808 Torricella. Postfach",
    "sg:city":"Torricella",
    "sg:orig_category":"Grosshandel mit Erzen U Metallen",
    "sg:phone":"+41 91 945 51 17",
    "sg:postcode":"6808",
    "sg:province":"Ticino",
    "wof:name":"Aura Di Gianni Pezzali & Maurizio Rossi",
    "wof:placetype":"venue"
},
  "geometry": {"coordinates":[8.9221410751,46.0651702881],"type":"Point"}
}