{
  "type": "Feature",
  "properties": {
    "iso:country":"CH",
    "sg:address":"4497",
    "sg:city":"R\u00fcnenberg",
    "sg:orig_category":"Handelsvermittlung von Textilien, Bekleidung, Schuhen U Lederwaren",
    "sg:phone":"+41 61 981 59 25",
    "sg:postcode":"4497",
    "sg:province":"Basel-Landschaft",
    "wof:name":"Malitex Modeagentur Rolli-lombriser Laura",
    "wof:placetype":"venue"
},
  "geometry": {"coordinates":[7.8806300163,47.4319610596],"type":"Point"}
}