{
  "type": "Feature",
  "properties": {
    "addr:full":"Limmatstrasse 34 8005 Z\u00fcrich. Postfach Z\u00fcrich Z\u00fcrich 8005",
    "addr:housenumber":"34",
    "addr:postcode":"8005 zuerich. postfach;8005",
    "addr:street":"Limmatstrasse",
    "iso:country":"CH",
    "sg:address":"Limmatstrasse 34 8005 Z\u00fcrich. Postfach",
    "sg:city":"Z\u00fcrich",
    "sg:orig_category":"Allgemeiner Hoch U Tiefbau",
    "sg:postcode":"8005",
    "sg:province":"Z\u00fcrich",
    "wof:name":"Ok Bau Ag",
    "wof:placetype":"venue"
},
  "geometry": {"coordinates":[8.536722,47.380997],"type":"Point"}
}