{
  "type": "Feature",
  "properties": {
    "iso:country":"CH",
    "sg:address":"Zunzgerstrasse 1 4450 Sissach. Postfach",
    "sg:city":"Sissach",
    "sg:orig_category":"Detailhandel mit Geschenkartikeln U Souvenirs Fachdetailhandel in Verkaufsr\u00e4umen",
    "sg:phone":"+41 61 973 22 88",
    "sg:postcode":"4450",
    "sg:province":"Basel-Landschaft",
    "wof:name":"Gecko Trendshop De Weerdt Theo Geschenkartikel, Hanfprodukte, Kunsthandwerk, Esoterik",
    "wof:placetype":"venue"
},
  "geometry": {"coordinates":[7.8102831841,47.4636688232],"type":"Point"}
}