{
  "type": "Feature",
  "properties": {
    "addr:full":"Contrada Maggiore 21 Ascona Ticino 6612",
    "addr:housenumber":"21",
    "addr:postcode":"6612",
    "addr:street":"Contrada Maggiore",
    "iso:country":"CH",
    "sg:address":"Contrada Maggiore 21",
    "sg:city":"Ascona",
    "sg:classifiers":[
        {
            "category":"Bars & Pubs",
            "type":"Food & Drink"
        }
    ],
    "sg:phone":"+41 91 827 14 28",
    "sg:postcode":"6612",
    "sg:province":"Ticino",
    "sg:tags":[
        "restaurant"
    ],
    "wof:name":"Ristorante & Bar Molera",
    "wof:placetype":"venue"
},
  "geometry": {"coordinates":[9.14456,46.2631],"type":"Point"}
}