{
  "type": "Feature",
  "properties": {
    "iso:country":"CH",
    "sg:address":"Gerechtigkeitsgasse 3",
    "sg:city":"Bern",
    "sg:orig_category":"HOTELS: MIT RESTAURANT Sonstiger Fachdetailhandel in Verkaufsr\u00e4umen",
    "sg:phone":"+41 31 311 10 40",
    "sg:postcode":"3011",
    "sg:province":"Bern",
    "wof:name":"Boutique Nelli, J\u00fcrg Friedrich",
    "wof:placetype":"venue"
},
  "geometry": {"coordinates":[7.4556078911,46.9484939575],"type":"Point"}
}