{
  "type": "Feature",
  "properties": {
    "iso:country":"CH",
    "sg:address":"St\u00e4mpfelweg 15",
    "sg:city":"Dagmersellen",
    "sg:orig_category":"Bauschreinerei",
    "sg:phone":"+41 79 647 15 54",
    "sg:postcode":"6252",
    "sg:province":"Luzern",
    "wof:name":"Walter Steiger Schreinerei",
    "wof:placetype":"venue"
},
  "geometry": {"coordinates":[7.98551,47.212391],"type":"Point"}
}