{
  "type": "Feature",
  "properties": {
    "iso:country":"CH",
    "sg:address":"K\u00fcrbergsteig 8",
    "sg:city":"Z\u00fcrich",
    "sg:orig_category":"Tanzschulen, Tanzlehrer",
    "sg:phone":"+41 91 682 28 57",
    "sg:postcode":"8049",
    "sg:province":"Z\u00fcrich",
    "wof:name":"Happy Dancing",
    "wof:placetype":"venue"
},
  "geometry": {"coordinates":[9.0216236115,45.8420829773],"type":"Point"}
}