{
  "type": "Feature",
  "properties": {
    "iso:country":"CH",
    "sg:address":"Gr\u00fctstrasse 9",
    "sg:city":"Jona",
    "sg:orig_category":"Grosshandel mit sonstigen Konsumg\u00fctern Vermietung U Verpachtung von eigenen Immobilien",
    "sg:phone":"+41 79 416 87 54",
    "sg:postcode":"8645",
    "sg:province":"St. Gallen",
    "wof:name":"Cool Sa",
    "wof:placetype":"venue"
},
  "geometry": {"coordinates":[8.8392696381,47.2350006104],"type":"Point"}
}