{
  "type": "Feature",
  "properties": {
    "iso:country":"CH",
    "sg:address":"3115",
    "sg:city":"Gerzensee",
    "sg:classifiers":[
        {
            "category":"Government",
            "subcategory":"Post Office",
            "type":"Public Place"
        }
    ],
    "sg:phone":"+41 31 781 01 04",
    "sg:postcode":"3115",
    "sg:province":"Bern",
    "sg:tags":[
        "die",
        "poststellen"
    ],
    "wof:name":"Die Post",
    "wof:placetype":"venue"
},
  "geometry": {"coordinates":[7.5467591286,46.8397903442],"type":"Point"}
}