{
  "type": "Feature",
  "properties": {
    "iso:country":"CH",
    "sg:address":"Route De France 6",
    "sg:city":"Boncourt",
    "sg:orig_category":"Non-Classified Establishments",
    "sg:postcode":"2926",
    "sg:province":"Jura",
    "wof:name":"Alain Gatherat Boucherie",
    "wof:placetype":"venue"
},
  "geometry": {"coordinates":[7.0157327652,47.4967422485],"type":"Point"}
}