{
  "type": "Feature",
  "properties": {
    "iso:country":"CH",
    "sg:address":"Q. Du Mont-blanc 1",
    "sg:city":"Gen\u00e8ve",
    "sg:classifiers":[
        {
            "category":"Banks & Credit Unions",
            "subcategory":"Bank",
            "type":"Services"
        }
    ],
    "sg:phone":"+41 22 908 16 11",
    "sg:postcode":"1201",
    "sg:province":"Gen\u00e8ve",
    "wof:name":"Banque Clariden",
    "wof:placetype":"venue"
},
  "geometry": {"coordinates":[6.147694,46.207092],"type":"Point"}
}