{
  "type": "Feature",
  "properties": {
    "iso:country":"CH",
    "sg:address":"Industriering 38",
    "sg:city":"Lyss",
    "sg:orig_category":"Einzelhandel mit Automobilen Instandhaltung U Reparatur von Automobilen",
    "sg:phone":"+41 32 384 27 62",
    "sg:postcode":"3250",
    "sg:province":"Bern",
    "wof:name":"J\u00f6rg Glauser Transgar Transporte & Garage",
    "wof:placetype":"venue"
},
  "geometry": {"coordinates":[7.3056759834,47.0893554688],"type":"Point"}
}