{
  "type": "Feature",
  "properties": {
    "iso:country":"CH",
    "sg:address":"H\u00e4rdlistrasse 14",
    "sg:city":"Spreitenbach",
    "sg:orig_category":"Erbringung von Dienstleistungen f\u00fcr Unternehmen",
    "sg:phone":"+41 61 403 97 77",
    "sg:postcode":"8957",
    "sg:province":"Aargau",
    "wof:name":"Professional Security Design A. Gr\u00fcninger",
    "wof:placetype":"venue"
},
  "geometry": {"coordinates":[7.5626268387,47.5098991394],"type":"Point"}
}