{
  "type": "Feature",
  "properties": {
    "addr:full":"Lohwisstrasse 16 Ebmatingen Z\u00fcrich 8123",
    "addr:housenumber":"16",
    "addr:postcode":"8123",
    "addr:street":"Lohwisstrasse;Ebmatingen Zuerich",
    "iso:country":"CH",
    "sg:address":"Lohwisstrasse 16",
    "sg:city":"Ebmatingen",
    "sg:classifiers":[
        {
            "category":"Retail",
            "subcategory":"Car Wash",
            "type":"Services"
        }
    ],
    "sg:phone":"+41 19802536",
    "sg:postcode":"8123",
    "sg:province":"Z\u00fcrich",
    "sg:tags":[
        "oil",
        "essential"
    ],
    "wof:name":"Bonsana Ag",
    "wof:placetype":"venue"
},
  "geometry": {"coordinates":[8.643955,47.355698],"type":"Point"}
}