{
  "type": "Feature",
  "properties": {
    "iso:country":"CH",
    "sg:address":"Altgraben 188",
    "sg:city":"Egerkingen",
    "sg:orig_category":"G\u00fcterbef\u00f6rderung im Strassenverkehr",
    "sg:postcode":"4622",
    "sg:province":"Solothurn",
    "wof:name":"F\u00fcrst Transporte",
    "wof:placetype":"venue"
},
  "geometry": {"coordinates":[7.8007221222,47.3134422302],"type":"Point"}
}