{
  "type": "Feature",
  "properties": {
    "iso:country":"CH",
    "sg:address":"Rue Des Coll\u00e8ges 2",
    "sg:city":"Bussigny-lausanne",
    "sg:orig_category":"Primarschulen",
    "sg:phone":"+41 32 968 10 28",
    "sg:postcode":"1030",
    "sg:province":"Vaud",
    "wof:name":"Ecole Primaire Coll\u00e8ge Du Valanvron",
    "wof:placetype":"venue"
},
  "geometry": {"coordinates":[6.8603920937,47.1431312561],"type":"Point"}
}