{
  "type": "Feature",
  "properties": {
    "iso:country":"CH",
    "sg:address":"Dorfstrasse 7",
    "sg:city":"Allenwinden",
    "sg:classifiers":[
        {
            "category":"Restaurant",
            "type":"Food & Drink"
        }
    ],
    "sg:phone":"+41 41 710 15 35",
    "sg:postcode":"6319",
    "sg:province":"Zug",
    "wof:name":"Restaurant D\u00f6rfli",
    "wof:placetype":"venue"
},
  "geometry": {"coordinates":[8.5557365417,47.1642341614],"type":"Point"}
}