{
  "type": "Feature",
  "properties": {
    "iso:country":"CH",
    "sg:address":"Englischviertelstrasse 7",
    "sg:city":"Z\u00fcrich",
    "sg:orig_category":"Handelsvermittlung U Grosshandel",
    "sg:phone":"+41 12520665",
    "sg:postcode":"8032",
    "sg:province":"Z\u00fcrich",
    "wof:name":"Abc Trading Establishment M.solovev Valerii",
    "wof:placetype":"venue"
},
  "geometry": {"coordinates":[8.5552835464,47.3689613342],"type":"Point"}
}