{
  "type": "Feature",
  "properties": {
    "addr:full":"World Trade Center-blocco 3 Agno Ticino 6982",
    "addr:housenumber":"3",
    "addr:postcode":"6982",
    "iso:country":"CH",
    "sg:address":"World Trade Center-blocco 3",
    "sg:city":"Agno",
    "sg:orig_category":"Arztpraxen",
    "sg:phone":"+41 91 610 20 30",
    "sg:postcode":"6982",
    "sg:province":"Ticino",
    "wof:name":"Dottori M. & C. Emmenegger Specialisti Fmh",
    "wof:placetype":"venue"
},
  "geometry": {"coordinates":[8.89933,45.996754],"type":"Point"}
}