{
  "type": "Feature",
  "properties": {
    "iso:country":"CH",
    "sg:address":"Frohburgstrasse 3",
    "sg:city":"Luzern",
    "sg:orig_category":"Nationale Postdienste",
    "sg:phone":"+41 61 411 04 18",
    "sg:postcode":"6002",
    "sg:province":"Luzern",
    "wof:name":"Die Schweizerische Post M\u00fcnchenstein 2 Dorf",
    "wof:placetype":"venue"
},
  "geometry": {"coordinates":[7.619207859,47.5140380859],"type":"Point"}
}