{
  "type": "Feature",
  "properties": {
    "iso:country":"CH",
    "sg:address":"R\u00fcckimattweg 10",
    "sg:city":"Fraubrunnen",
    "sg:orig_category":"D\u00e4mmung gegen K\u00e4lte, W\u00e4rme, Schall U Ersch\u00fctterung",
    "sg:phone":"+41 31 767 86 45",
    "sg:postcode":"3312",
    "sg:province":"Bern",
    "wof:name":"Beat Rychener Fugendichtungen",
    "wof:placetype":"venue"
},
  "geometry": {"coordinates":[7.525261879,47.0864677429],"type":"Point"}
}