{
  "type": "Feature",
  "properties": {
    "iso:country":"CH",
    "sg:address":"Ausserdorf 9",
    "sg:city":"Hallwil",
    "sg:orig_category":"Non-Classified Establishments",
    "sg:postcode":"5705",
    "sg:province":"Aargau",
    "wof:name":"Frymag Gmbh",
    "wof:placetype":"venue"
},
  "geometry": {"coordinates":[8.1797466278,47.3249015808],"type":"Point"}
}