{
  "type": "Feature",
  "properties": {
    "iso:country":"CH",
    "sg:address":"6674 Someo. Postfach",
    "sg:city":"Someo",
    "sg:orig_category":"Allgemeiner Hoch U Tiefbau",
    "sg:phone":"+41 41 632 40 20",
    "sg:postcode":"6674",
    "sg:province":"Ticino",
    "wof:name":"Poli A. Ag, Hergiswil",
    "wof:placetype":"venue"
},
  "geometry": {"coordinates":[8.312144,46.987637],"type":"Point"}
}