{
  "type": "Feature",
  "properties": {
    "iso:country":"CH",
    "sg:address":"Stadelhoferstrasse 42",
    "sg:city":"Z\u00fcrich",
    "sg:orig_category":"Werbegrafikateliers",
    "sg:phone":"+41 12510821",
    "sg:postcode":"8001",
    "sg:province":"Z\u00fcrich",
    "wof:name":"Wolf-werner L\u00fcthy Grafisches Atelier",
    "wof:placetype":"venue"
},
  "geometry": {"coordinates":[8.5464906693,47.3678359985],"type":"Point"}
}