{
  "type": "Feature",
  "properties": {
    "iso:country":"CH",
    "sg:address":"Alberich Zwyssigstrasse 33",
    "sg:city":"Wettingen",
    "sg:orig_category":"Planer f\u00fcr Alternativenergie and Solararchitektur Planer f\u00fcr Energiekonzepte",
    "sg:phone":"+41 56 426 01 62",
    "sg:postcode":"5430",
    "sg:province":"Aargau",
    "wof:name":"Urs W\u00fcrmli Ingenieurb\u00fcro",
    "wof:placetype":"venue"
},
  "geometry": {"coordinates":[8.3210630417,47.4619407654],"type":"Point"}
}