{
  "type": "Feature",
  "properties": {
    "iso:country":"CH",
    "sg:address":"Franklinstrasse 24",
    "sg:city":"Rorschach",
    "sg:orig_category":"Detailhandel mit Brennstoffen U Heizmaterial",
    "sg:phone":"+41 71 841 23 86",
    "sg:postcode":"9400",
    "sg:province":"St. Gallen",
    "wof:name":"Osterwalder St.gallen Ag Avia Mineral\u00f6lprodukte",
    "wof:placetype":"venue"
},
  "geometry": {"coordinates":[9.489338,47.472637],"type":"Point"}
}