{
  "type": "Feature",
  "properties": {
    "iso:country":"CH",
    "sg:address":"Vordere Hauptgasse 65",
    "sg:city":"Zofingen",
    "sg:orig_category":"Detailhandel mit Herrenbekleidung",
    "sg:phone":"+41 62 751 12 78",
    "sg:postcode":"4800",
    "sg:province":"Aargau",
    "wof:name":"Rosmarie Thoenen Thoenen Herrenmode",
    "wof:placetype":"venue"
},
  "geometry": {"coordinates":[7.9456958771,47.2875976562],"type":"Point"}
}