{
  "type": "Feature",
  "properties": {
    "iso:country":"CH",
    "sg:address":"Pflugstrasse 7",
    "sg:city":"Vaduz",
    "sg:orig_category":"Installation von Heizungs, L\u00fcftungs U Klimaanlagen",
    "sg:phone":"+41 31 765 61 40",
    "sg:postcode":"9490",
    "wof:name":"K\u00e4lte K & H K\u00e4lte-klima-w\u00e4rmepumpen",
    "wof:placetype":"venue"
},
  "geometry": {"coordinates":[-82.59181976319999,33.4613304138],"type":"Point"}
}