{
  "type": "Feature",
  "properties": {
    "iso:country":"CH",
    "sg:address":"Rue Des Vollandes 26 1200 Genf. Postfach",
    "sg:city":"Gen\u00e8ve",
    "sg:orig_category":"Herstellung von elektronischen Bauelementen",
    "sg:postcode":"1207",
    "sg:province":"Gen\u00e8ve",
    "wof:name":"Info Au Galop, M\u00fcller",
    "wof:placetype":"venue"
},
  "geometry": {"coordinates":[6.1606712341,46.2046585083],"type":"Point"}
}