{
  "type": "Feature",
  "properties": {
    "iso:country":"CH",
    "sg:address":"1400 Cheseaux-nor\u00e9az. Postfach",
    "sg:city":"Cheseaux-nor\u00e9az",
    "sg:orig_category":"Sonstige pers\u00f6nliche Dienstleistungen",
    "sg:postcode":"1400",
    "sg:province":"Vaud",
    "wof:name":"Rhumamed S\u00e0rl, \u00e0 Yverdon-les-bains, Centre Thermal",
    "wof:placetype":"venue"
},
  "geometry": {"coordinates":[6.670759201,46.7817420959],"type":"Point"}
}