{
  "type": "Feature",
  "properties": {
    "iso:country":"CH",
    "sg:address":"Chemin Des M\u00e9sanges 6 1032 Romanel-s-lausanne Case Postale 94",
    "sg:city":"Romanel-s-lausanne",
    "sg:orig_category":"Handel mit Automobilen",
    "sg:phone":"+41 26 921 38 59",
    "sg:postcode":"1032",
    "sg:province":"Vaud",
    "wof:name":"Rona Automobiles S\u00e0rl",
    "wof:placetype":"venue"
},
  "geometry": {"coordinates":[7.0663948059,46.6079711914],"type":"Point"}
}