{
  "type": "Feature",
  "properties": {
    "iso:country":"CH",
    "sg:address":"Rheinstrasse 23",
    "sg:city":"Frauenfeld",
    "sg:orig_category":"Detailhandel mit elektrischen Haushalts-,Radio U Fernsehger\u00e4ten sowie Musikinstrumenten",
    "sg:phone":"+41 52 730 10 61",
    "sg:postcode":"8500",
    "sg:province":"Thurgau",
    "wof:name":"Video Zone Gmbh",
    "wof:placetype":"venue"
},
  "geometry": {"coordinates":[8.8941106796,47.5573501587],"type":"Point"}
}