{
  "type": "Feature",
  "properties": {
    "iso:country":"CH",
    "sg:address":"Niederlindach",
    "sg:city":"Kirchlindach",
    "sg:orig_category":"Landwirtschaft, Jagd U damit verbundene Dienstleistungen",
    "sg:phone":"+41 31 829 03 74",
    "sg:postcode":"3038",
    "sg:province":"Bern",
    "wof:name":"Dr.ing.h.u. Winzenried Landw.gutsbetriebe",
    "wof:placetype":"venue"
},
  "geometry": {"coordinates":[7.4236397743,46.9945907593],"type":"Point"}
}