{
  "type": "Feature",
  "properties": {
    "iso:country":"CH",
    "sg:address":"Greifengasse 7 4058 Basel. Postfach",
    "sg:city":"Basel",
    "sg:orig_category":"Softwareentwicklung U beratung",
    "sg:phone":"+41 61 683 34 40",
    "sg:postcode":"4058",
    "sg:province":"Basel-Stadt",
    "wof:name":"316 Tn Interaktive Und Klassische Medien Gmbh",
    "wof:placetype":"venue"
},
  "geometry": {"coordinates":[7.5915532112,47.5611038208],"type":"Point"}
}