{
  "type": "Feature",
  "properties": {
    "iso:country":"CH",
    "sg:address":"Grellingen 4202 Duggingen. Postfach",
    "sg:city":"Duggingen",
    "sg:orig_category":"Herstellung von sonstigen organischen Grundstoffen U Chemikalien",
    "sg:phone":"+41 61 741 14 00",
    "sg:postcode":"4202",
    "sg:province":"Basel-Landschaft",
    "wof:name":"Dr. W. Baumann Ag",
    "wof:placetype":"venue"
},
  "geometry": {"coordinates":[7.6079897881,47.4483108521],"type":"Point"}
}