{
  "type": "Feature",
  "properties": {
    "iso:country":"CH",
    "sg:address":"Rue Des Grottes 7",
    "sg:city":"Gen\u00e8ve",
    "sg:orig_category":"Detailhandel mit Metallwaren, Anstrichmitteln, Glaswaren, Bau U Heimwerkerbedarf Glaserei",
    "sg:phone":"+41 22 733 81 77",
    "sg:postcode":"1201",
    "sg:province":"Gen\u00e8ve",
    "wof:name":"Pasqual-stefano Sa",
    "wof:placetype":"venue"
},
  "geometry": {"coordinates":[6.1393899918,46.210269928],"type":"Point"}
}