{
  "type": "Feature",
  "properties": {
    "iso:country":"CH",
    "sg:address":"Unterdorf",
    "sg:city":"Ursenbach",
    "sg:orig_category":"Grosshandel mit Nahrungsmitteln, Getr\u00e4nken U Tabakwaren ohne ausgepr\u00e4gten Schwerpunkt",
    "sg:postcode":"4937",
    "sg:province":"Bern",
    "wof:name":"Th. Seiler-fuhrer",
    "wof:placetype":"venue"
},
  "geometry": {"coordinates":[7.779897213,47.1448059082],"type":"Point"}
}