{
  "type": "Feature",
  "properties": {
    "iso:country":"CH",
    "sg:address":"Chemin De Pontenet 4",
    "sg:city":"Malleray-b\u00e9vilard",
    "sg:orig_category":"Interessenvertretungen U sonstige Vereinigungen",
    "sg:postcode":"2735",
    "sg:province":"Bern",
    "wof:name":"Groupement Des Ski-clubs Jura",
    "wof:placetype":"venue"
},
  "geometry": {"coordinates":[6.8929100037,47.1429443359],"type":"Point"}
}