{
  "type": "Feature",
  "properties": {
    "iso:country":"CH",
    "sg:address":"Wilstrasse 6",
    "sg:city":"Schafisheim",
    "sg:orig_category":"Unclassifiable Establishments",
    "sg:phone":"+41 62 891 92 02",
    "sg:postcode":"5503",
    "sg:province":"Aargau",
    "wof:name":"Joventa Handels Ag",
    "wof:placetype":"venue"
},
  "geometry": {"coordinates":[8.1406831741,47.3713340759],"type":"Point"}
}