{
  "type": "Feature",
  "properties": {
    "iso:country":"CH",
    "sg:address":"Alte S\u00e4gerei",
    "sg:city":"Rona",
    "sg:orig_category":"Grosshandel mit Milch, Milcherzeugnissen, Eiern, Speise\u00f6len U Nahrungsfetten",
    "sg:phone":"+41 71 944 13 44",
    "sg:postcode":"7454",
    "sg:province":"Graubunden",
    "wof:name":"Emmi Interfrais Sa Depot Wil",
    "wof:placetype":"venue"
},
  "geometry": {"coordinates":[9.1234006882,47.4656410217],"type":"Point"}
}