{
  "type": "Feature",
  "properties": {
    "iso:country":"CH",
    "sg:address":"H\u00f6lzliwiesenstrasse 4 8604 Volketswil. Postfach",
    "sg:city":"Volketswil",
    "sg:orig_category":"Herstellung von Werkzeugmaschinen",
    "sg:postcode":"8604",
    "sg:province":"Z\u00fcrich",
    "wof:name":"Haug Oskar Ag",
    "wof:placetype":"venue"
},
  "geometry": {"coordinates":[8.6793756485,47.3786811829],"type":"Point"}
}