{
  "type": "Feature",
  "properties": {
    "iso:country":"CH",
    "sg:address":"Route Grand-st-bernard 11",
    "sg:city":"Bex",
    "sg:orig_category":"G\u00fcterbef\u00f6rderung im Strassenverkehr",
    "sg:phone":"+41 24 463 36 77",
    "sg:postcode":"1880",
    "sg:province":"Vaud",
    "wof:name":"Andr\u00e9 Corboz Transports Internationaux",
    "wof:placetype":"venue"
},
  "geometry": {"coordinates":[7.002699852,46.249835968],"type":"Point"}
}