{
  "type": "Feature",
  "properties": {
    "iso:country":"CH",
    "sg:address":"Oltenstrasse 18",
    "sg:city":"Oberbipp",
    "sg:orig_category":"Sonstige mit der Informatik verbundene T\u00e4tigkeiten",
    "sg:postcode":"4538",
    "sg:province":"Bern",
    "wof:name":"Compusult Kempf Willi F.",
    "wof:placetype":"venue"
},
  "geometry": {"coordinates":[7.6754789352,47.2634010315],"type":"Point"}
}