{
  "type": "Feature",
  "properties": {
    "iso:country":"CH",
    "sg:address":"Haldenstrasse 36",
    "sg:city":"Watt",
    "sg:orig_category":"Wirtschaftsverb\u00e4nde Gewerbeverb\u00e4nde/-vereine",
    "sg:phone":"+41 17500928",
    "sg:postcode":"8105",
    "sg:province":"Z\u00fcrich",
    "wof:name":"Gewerbeverein Bezirk Limmattal",
    "wof:placetype":"venue"
},
  "geometry": {"coordinates":[8.4409542084,47.4158477783],"type":"Point"}
}