{
  "type": "Feature",
  "properties": {
    "iso:country":"CH",
    "sg:address":"9565",
    "sg:city":"Bussnang",
    "sg:orig_category":"Vereine Gesang",
    "sg:postcode":"9565",
    "sg:province":"Thurgau",
    "wof:name":"M\u00e4nnerchor Busswil",
    "wof:placetype":"venue"
},
  "geometry": {"coordinates":[9.0140800476,47.4496917725],"type":"Point"}
}