{
  "type": "Feature",
  "properties": {
    "iso:country":"CH",
    "sg:address":"Niederfeldstrasse 5",
    "sg:city":"B\u00fcsserach",
    "sg:orig_category":"D\u00e4mmung gegen K\u00e4lte, W\u00e4rme, Schall U Ersch\u00fctterung Verlegen von Fliesen U Platten",
    "sg:phone":"+41 61 781 11 21",
    "sg:postcode":"4227",
    "sg:province":"Solothurn",
    "wof:name":"Borer Severin Ag",
    "wof:placetype":"venue"
},
  "geometry": {"coordinates":[7.5447058678,47.3962631226],"type":"Point"}
}