{
  "type": "Feature",
  "properties": {
    "iso:country":"CH",
    "sg:address":"Via Pietro Peri 2",
    "sg:city":"Lugano",
    "sg:classifiers":[
        {
            "category":"Travel",
            "subcategory":"Hotels & Motels",
            "type":"Entertainment"
        }
    ],
    "sg:postcode":"6900",
    "sg:province":"Ticino",
    "sg:tags":[
        "hotels",
        "mit",
        "restaurant"
    ],
    "wof:name":"Soleado Sa",
    "wof:placetype":"venue"
},
  "geometry": {"coordinates":[8.9508810043,46.0053215027],"type":"Point"}
}