{
  "type": "Feature",
  "properties": {
    "iso:country":"CH",
    "sg:address":"5444",
    "sg:city":"K\u00fcnten",
    "sg:orig_category":"Schulpflegen",
    "sg:postcode":"5444",
    "sg:province":"Aargau",
    "wof:name":"Schulpflege Der Gemeinde K\u00fcsnacht",
    "wof:placetype":"venue"
},
  "geometry": {"coordinates":[8.5801401138,47.3188896179],"type":"Point"}
}