{
  "type": "Feature",
  "properties": {
    "iso:country":"CH",
    "sg:address":"6982",
    "sg:city":"Agno",
    "sg:orig_category":"Stukkateurgewerbe, Gipserei U Verputzerei",
    "sg:postcode":"6982",
    "sg:province":"Ticino",
    "wof:name":"Moser Gipser Gmbh Gipserarbeiten Usw",
    "wof:placetype":"venue"
},
  "geometry": {"coordinates":[9.2412977219,47.4210929871],"type":"Point"}
}