{
  "type": "Feature",
  "properties": {
    "iso:country":"CH",
    "sg:address":"6952",
    "sg:city":"Canobbio",
    "sg:orig_category":"Sonstige pers\u00f6nliche Dienstleistungen",
    "sg:postcode":"6952",
    "sg:province":"Ticino",
    "wof:name":"Zuntini Luca",
    "wof:placetype":"venue"
},
  "geometry": {"coordinates":[8.9687299728,46.0362205505],"type":"Point"}
}