{
  "type": "Feature",
  "properties": {
    "iso:country":"CH",
    "sg:address":"Schwandenholzstrasse 228",
    "sg:city":"Z\u00fcrich",
    "sg:orig_category":"Elektroinstallation",
    "sg:postcode":"8046",
    "sg:province":"Z\u00fcrich",
    "wof:name":"Huber J\u00fcrg, Elektrik Elektroprojekte, Elektr. Ger\u00e4tehandel Usw",
    "wof:placetype":"venue"
},
  "geometry": {"coordinates":[8.5209636688,47.4239845276],"type":"Point"}
}