{
  "type": "Feature",
  "properties": {
    "iso:country":"CH",
    "sg:address":"Florastrasse 12 2500 Biel/bienne. Postfach",
    "sg:city":"Biel/bienne",
    "sg:orig_category":"RESTAURANTS: TEA-ROOMS",
    "sg:postcode":"2502",
    "sg:province":"Bern",
    "wof:name":"Restaurant Milady Gmbh",
    "wof:placetype":"venue"
},
  "geometry": {"coordinates":[7.2464799881,47.1381149292],"type":"Point"}
}