{
  "type": "Feature",
  "properties": {
    "iso:country":"CH",
    "sg:address":"Via Girella 2",
    "sg:city":"Lamone",
    "sg:orig_category":"Grosshandel mit pharmazeutischen Erzeugnissen, medizinischen U orthop\u00e4dischen Artikeln",
    "sg:phone":"+41 91 972 54 37",
    "sg:postcode":"6814",
    "sg:province":"Ticino",
    "wof:name":"Sanicar Sa",
    "wof:placetype":"venue"
},
  "geometry": {"coordinates":[8.9315128326,46.0430145264],"type":"Point"}
}