{
  "type": "Feature",
  "properties": {
    "iso:country":"CH",
    "sg:address":"Quellenstrasse 5",
    "sg:city":"Goldach",
    "sg:orig_category":"Detailhandel mit Boden U Wandbel\u00e4gen ohne Teppiche Verlegen von Fussboden",
    "sg:phone":"+41 71 841 45 22",
    "sg:postcode":"9403",
    "sg:province":"St. Gallen",
    "wof:name":"Emil Wirth Bodenbel\u00e4ge",
    "wof:placetype":"venue"
},
  "geometry": {"coordinates":[9.470935,47.472927],"type":"Point"}
}