{
  "type": "Feature",
  "properties": {
    "iso:country":"CH",
    "sg:address":"Bahnhofstrasse 5 3900 Brig. Postfach",
    "sg:city":"Brig",
    "sg:orig_category":"Zahnarztpraxen Zahntechnische Laboratorien",
    "sg:phone":"+41 27 923 23 80",
    "sg:postcode":"3900",
    "sg:province":"Valais",
    "wof:name":"Sarbach Alwin, Zahntechnisches Labor",
    "wof:placetype":"venue"
},
  "geometry": {"coordinates":[7.9883990288,46.3182258606],"type":"Point"}
}