{
  "type": "Feature",
  "properties": {
    "iso:country":"CH",
    "sg:address":"Rampa Via",
    "sg:city":"Chiasso",
    "sg:orig_category":"Sonstige mit Sport verbundene T\u00e4tigkeiten",
    "sg:postcode":"6830",
    "sg:province":"Ticino",
    "wof:name":"E Group",
    "wof:placetype":"venue"
},
  "geometry": {"coordinates":[9.0234966278,45.8351211548],"type":"Point"}
}