{
  "type": "Feature",
  "properties": {
    "iso:country":"CH",
    "sg:address":"1899",
    "sg:city":"Torgon",
    "sg:orig_category":"G\u00fcterbef\u00f6rderung im Strassenverkehr",
    "sg:phone":"+41 24 481 11 73",
    "sg:postcode":"1899",
    "sg:province":"Valais",
    "wof:name":"Pierre Gu\u00e9rin Transports",
    "wof:placetype":"venue"
},
  "geometry": {"coordinates":[6.8765802383,46.3203010559],"type":"Point"}
}