{
  "type": "Feature",
  "properties": {
    "iso:country":"CH",
    "sg:address":"Via Giuseppe Corti 5",
    "sg:city":"Balerna",
    "sg:orig_category":"Schiffsbau ohne Boots U Yachtbau",
    "sg:postcode":"6828",
    "sg:province":"Ticino",
    "wof:name":"Plot Yacht Concept, Dipl.-ing. Rainer Niessner",
    "wof:placetype":"venue"
},
  "geometry": {"coordinates":[9.012172699,45.8415718079],"type":"Point"}
}