{
  "type": "Feature",
  "properties": {
    "addr:full":"Staldenstrasse 5 3400 Burgdorf. Postfach Burgdorf Bern 3401",
    "addr:housenumber":"5",
    "addr:postcode":"3400 burgdorf. postfach;3401",
    "addr:street":"Staldenstrasse;Bern",
    "iso:country":"CH",
    "sg:address":"Staldenstrasse 5 3400 Burgdorf. Postfach",
    "sg:city":"Burgdorf",
    "sg:orig_category":"Architektur U Ingenieurb\u00fcros Architekturb\u00fcros",
    "sg:phone":"+41 34 423 13 73",
    "sg:postcode":"3401",
    "sg:province":"Bern",
    "wof:name":"Atelier G + S Architekten Und Planer Ag",
    "wof:placetype":"venue"
},
  "geometry": {"coordinates":[7.625966,47.057079],"type":"Point"}
}