{
  "type": "Feature",
  "properties": {
    "iso:country":"CH",
    "sg:address":"Sandackerstrasse 4",
    "sg:city":"H\u00f6ri",
    "sg:classifiers":[
        {
            "category":"Education",
            "subcategory":"Library",
            "type":"Public Place"
        }
    ],
    "sg:phone":"+41 18621763",
    "sg:postcode":"8181",
    "sg:province":"Z\u00fcrich",
    "sg:tags":[
        "u",
        "bibliotheken",
        "archive"
    ],
    "wof:name":"Schul-& Gemeindebibliothek",
    "wof:placetype":"venue"
},
  "geometry": {"coordinates":[8.514539,47.51009],"type":"Point"}
}