{
  "type": "Feature",
  "properties": {
    "iso:country":"CH",
    "sg:address":"Voa Sporz 7082 Vaz/obervaz. Postfach",
    "sg:city":"Vaz/obervaz",
    "sg:orig_category":"RESTAURANTS: TEA-ROOMS",
    "sg:postcode":"7082",
    "sg:province":"Graubunden",
    "wof:name":"Grotto Pojana Sagl Esercizio Pubblico, Acquisto E Vendita Di Inventari Ecc",
    "wof:placetype":"venue"
},
  "geometry": {"coordinates":[8.9712247849,45.9057006836],"type":"Point"}
}