{
  "type": "Feature",
  "properties": {
    "iso:country":"CH",
    "sg:address":"Turmgasse 29b",
    "sg:city":"K\u00fcblis",
    "sg:orig_category":"Herstellung von sonstigen Fahrzeugen",
    "sg:phone":"+41 81 332 13 20",
    "sg:postcode":"7240",
    "sg:province":"Graubunden",
    "wof:name":"Caprez Sport Ag",
    "wof:placetype":"venue"
},
  "geometry": {"coordinates":[9.776386261,46.9143257141],"type":"Point"}
}