{
  "type": "Feature",
  "properties": {
    "iso:country":"CH",
    "sg:address":"Soodring 13a",
    "sg:city":"Adliswil",
    "sg:orig_category":"Herstellung von k\u00e4lte U lufttechnischen Erzeugnissen f\u00fcr gewerbliche Zwecke Sanit\u00e4r U Heizungsinstal",
    "sg:phone":"+41 41 630 17 02",
    "sg:postcode":"8134",
    "sg:province":"Z\u00fcrich",
    "wof:name":"Alessandri Walter, Heizungen.",
    "wof:placetype":"venue"
},
  "geometry": {"coordinates":[8.3081331253,46.9900360107],"type":"Point"}
}