{
  "type": "Feature",
  "properties": {
    "iso:country":"CH",
    "sg:address":"Dorfstrasse 24",
    "sg:city":"Birr-lupfig",
    "sg:orig_category":"Sanit\u00e4r, Heizungs U L\u00fcftungsinstallation",
    "sg:phone":"+41 56 450 01 81",
    "sg:postcode":"5242",
    "sg:province":"Aargau",
    "wof:name":"Saniburki Gmbh",
    "wof:placetype":"venue"
},
  "geometry": {"coordinates":[8.2027254105,47.4361724854],"type":"Point"}
}