{
  "type": "Feature",
  "properties": {
    "iso:country":"CH",
    "sg:address":"Rue St-georges 18 2800 Del\u00e9mont Case Postale",
    "sg:city":"Delsberg",
    "sg:orig_category":"Herstellung von Schrauben, Nieten, Ketten U Federn",
    "sg:phone":"+41 32 422 24 30",
    "sg:postcode":"2800",
    "sg:province":"Jura",
    "wof:name":"Vardeco Sa",
    "wof:placetype":"venue"
},
  "geometry": {"coordinates":[7.3443021774,47.3535041809],"type":"Point"}
}