{
  "type": "Feature",
  "properties": {
    "iso:country":"CH",
    "sg:address":"Avenue De La Gare 51",
    "sg:city":"Charrat",
    "sg:orig_category":"Nationale Postdienste",
    "sg:phone":"+41 27 746 11 92",
    "sg:postcode":"1906",
    "sg:province":"Valais",
    "wof:name":"La Poste Suisse",
    "wof:placetype":"venue"
},
  "geometry": {"coordinates":[7.1269049644,46.1265716553],"type":"Point"}
}