{
  "type": "Feature",
  "properties": {
    "iso:country":"CH",
    "sg:address":"Bruggerstrasse 37",
    "sg:city":"Baden",
    "sg:orig_category":"Erbringung von Dienstleistungen f\u00fcr Unternehmen",
    "sg:phone":"+41 56 221 66 22",
    "sg:postcode":"5400",
    "sg:province":"Aargau",
    "wof:name":"B\u00fcrki & Moser Gmbh Beschriftungen + Siebdruck",
    "wof:placetype":"venue"
},
  "geometry": {"coordinates":[8.3047838211,47.4764022827],"type":"Point"}
}