{
  "type": "Feature",
  "properties": {
    "addr:full":"Vaglio Vaglio Ticino 6947",
    "addr:postcode":"6947",
    "addr:street":"Vaglio Vaglio Ticino",
    "iso:country":"CH",
    "sg:address":"Vaglio",
    "sg:city":"Vaglio",
    "sg:classifiers":[
        {
            "category":"Home & Garden",
            "subcategory":"Building Materials",
            "type":"Retail Goods"
        }
    ],
    "sg:phone":"+41 91 943 59 78",
    "sg:postcode":"6947",
    "sg:province":"Ticino",
    "sg:tags":[
        "maintenance",
        "de-icing",
        "winter"
    ],
    "wof:name":"Gresol Sagl",
    "wof:placetype":"venue"
},
  "geometry": {"coordinates":[8.95931,46.055851],"type":"Point"}
}