{
  "type": "Feature",
  "properties": {
    "iso:country":"CH",
    "sg:address":"P\u00e2quier Aux Oies",
    "sg:city":"Faoug",
    "sg:orig_category":"Herstellung von sonstigen elektrischen Ausr\u00fcstungen",
    "sg:postcode":"1595",
    "sg:province":"Bern",
    "wof:name":"Protakta-norm M\u00fcnger Eveline",
    "wof:placetype":"venue"
},
  "geometry": {"coordinates":[7.0660347939,46.9041252136],"type":"Point"}
}