{
  "type": "Feature",
  "properties": {
    "iso:country":"CH",
    "sg:address":"Rue Des Parcs 2a",
    "sg:city":"Neuch\u00e2tel",
    "sg:orig_category":"P\u00e9dicure",
    "sg:phone":"+41 61 701 72 36",
    "sg:postcode":"2000",
    "sg:province":"Neuch\u00e2tel",
    "wof:name":"Catherine V\u00f6gtli P\u00e9dicure",
    "wof:placetype":"venue"
},
  "geometry": {"coordinates":[7.6181578636,47.476890564],"type":"Point"}
}