{
  "type": "Feature",
  "properties": {
    "iso:country":"CH",
    "sg:address":"Rue Du Village",
    "sg:city":"Vullierens",
    "sg:orig_category":"Verlagsgewerbe",
    "sg:phone":"+41 21 869 72 51",
    "sg:postcode":"1115",
    "sg:province":"Vaud",
    "wof:name":"Anne W\u00e4lti S-cool Editions",
    "wof:placetype":"venue"
},
  "geometry": {"coordinates":[6.4832239151,46.5741119385],"type":"Point"}
}