{
  "type": "Feature",
  "properties": {
    "iso:country":"CH",
    "sg:address":"Hofweg 21",
    "sg:city":"Grenchen",
    "sg:orig_category":"Herstellung von \u00d6fen U Brennern",
    "sg:postcode":"2540",
    "sg:province":"Solothurn",
    "wof:name":"Ofen, Chemin\u00e9ebau Und Plattenbel\u00e4ge, Abegglen Hans-peter",
    "wof:placetype":"venue"
},
  "geometry": {"coordinates":[7.6346597672,46.3163299561],"type":"Point"}
}