{
  "type": "Feature",
  "properties": {
    "iso:country":"CH",
    "sg:address":"Grand-rue 16",
    "sg:city":"Corg\u00e9mont",
    "sg:orig_category":"Detailhandel mit Fleisch U Fleischwaren",
    "sg:phone":"+41 32 489 17 61",
    "sg:postcode":"2606",
    "sg:province":"Bern",
    "wof:name":"Michel Junod Boucherie-charcuterie",
    "wof:placetype":"venue"
},
  "geometry": {"coordinates":[7.1437749863,47.1942825317],"type":"Point"}
}