{
  "type": "Feature",
  "properties": {
    "iso:country":"CH",
    "sg:address":"Avenue Tronchet 2",
    "sg:city":"Th\u00f4nex",
    "sg:orig_category":"Fachdetailhandel mit pharmazeutischen Produkten",
    "sg:phone":"+41 22 348 06 32",
    "sg:postcode":"1226",
    "sg:province":"Gen\u00e8ve",
    "wof:name":"Pharmacies Tronchet",
    "wof:placetype":"venue"
},
  "geometry": {"coordinates":[6.2032718658,46.1932144165],"type":"Point"}
}