{
  "type": "Feature",
  "properties": {
    "iso:country":"CH",
    "sg:address":"Kiener Avenue 17",
    "sg:city":"Yverdon-les-bains",
    "sg:orig_category":"Instandhaltung U Reparatur von Automobilen",
    "sg:phone":"+41 79 425 86 69",
    "sg:postcode":"1400",
    "sg:province":"Vaud",
    "wof:name":"D\u00e9pannage Automobile, Ballestraz Christian",
    "wof:placetype":"venue"
},
  "geometry": {"coordinates":[6.6277470589,46.7777290344],"type":"Point"}
}