{
  "type": "Feature",
  "properties": {
    "iso:country":"CH",
    "sg:address":"Aargauerstrasse 180",
    "sg:city":"Z\u00fcrich",
    "sg:orig_category":"Erbringung von Dienstleistungen f\u00fcr Unternehmen Offsetdruck",
    "sg:phone":"+41 14327790",
    "sg:postcode":"8048",
    "sg:province":"Z\u00fcrich",
    "wof:name":"Freytag Ag",
    "wof:placetype":"venue"
},
  "geometry": {"coordinates":[8.4936380386,47.3922996521],"type":"Point"}
}