{
  "type": "Feature",
  "properties": {
    "addr:full":"Dossenstrasse 3 Aarau Aargau 5000",
    "addr:housenumber":"3",
    "addr:postcode":"5000",
    "addr:street":"Dossenstrasse",
    "iso:country":"CH",
    "sg:address":"Dossenstrasse 3",
    "sg:city":"Aarau",
    "sg:orig_category":"Arztpraxen",
    "sg:phone":"+41 62 825 13 33",
    "sg:postcode":"5000",
    "sg:province":"Aargau",
    "wof:name":"Dr.med. Yolanda Vieli Spezial\u00e4rztin",
    "wof:placetype":"venue"
},
  "geometry": {"coordinates":[8.045811,47.383514],"type":"Point"}
}