{
  "type": "Feature",
  "properties": {
    "iso:country":"CH",
    "sg:address":"Via Stazione 6780 Airolo. Postfach",
    "sg:city":"Airolo",
    "sg:classifiers":[
        {
            "category":"Restaurant",
            "type":"Food & Drink"
        }
    ],
    "sg:phone":"+41 79 681 01 18",
    "sg:postcode":"6780",
    "sg:province":"Ticino",
    "wof:name":"Ristorante Cristallina",
    "wof:placetype":"venue"
},
  "geometry": {"coordinates":[8.6040563583,46.5281944275],"type":"Point"}
}