{
  "type": "Feature",
  "properties": {
    "iso:country":"CH",
    "sg:address":"Avenue Mon-loisir 7",
    "sg:city":"Lausanne",
    "sg:orig_category":"Detailhandel mit Waren verschiedener Art, Hauptrichtung Nahrungsmittel Fachdetailhandel mit Nahrungs",
    "sg:phone":"+41 21 616 37 77",
    "sg:postcode":"1006",
    "sg:province":"Vaud",
    "wof:name":"P. Puce & C. Lacarbonara Aux Saveurs D'italie",
    "wof:placetype":"venue"
},
  "geometry": {"coordinates":[6.6330089569,46.5120124817],"type":"Point"}
}