{
  "type": "Feature",
  "properties": {
    "iso:country":"CH",
    "sg:address":"Lausanne Rue De 36",
    "sg:city":"Fribourg",
    "sg:orig_category":"Finanzierungsinstitutionen",
    "sg:postcode":"1700",
    "sg:province":"Fribourg",
    "wof:name":"Bausch & Lomb Fribourg Sa",
    "wof:placetype":"venue"
},
  "geometry": {"coordinates":[7.1592769623,46.8056602478],"type":"Point"}
}