{
  "type": "Feature",
  "properties": {
    "iso:country":"CH",
    "sg:address":"Hauptstrasse 4",
    "sg:city":"Laufen",
    "sg:orig_category":"Gymnastik U Fitnesszentren Saunas, Solarien, Fitnesszentren U \u00e4hnliches",
    "sg:phone":"+41 61 761 33 10",
    "sg:postcode":"4242",
    "sg:province":"Basel-Landschaft",
    "wof:name":"Move And Sun, Aerobic Und Solarium, Muheim Und Kienberger",
    "wof:placetype":"venue"
},
  "geometry": {"coordinates":[7.5007429123,47.4210853577],"type":"Point"}
}