{
  "type": "Feature",
  "properties": {
    "iso:country":"CH",
    "sg:address":"Oberes B\u00fcel 10",
    "sg:city":"Humlikon",
    "sg:orig_category":"Erbringung von Dienstleistungen f\u00fcr Unternehmen Grafikateliers, Design",
    "sg:phone":"+41 24 471 74 20",
    "sg:postcode":"8457",
    "sg:province":"Z\u00fcrich",
    "wof:name":"Pilloud Christian",
    "wof:placetype":"venue"
},
  "geometry": {"coordinates":[6.9522790909,46.2524147034],"type":"Point"}
}