{
  "type": "Feature",
  "properties": {
    "iso:country":"CH",
    "sg:address":"Rue Haute 10",
    "sg:city":"Grandson",
    "sg:orig_category":"Verwaltung von Immobilien",
    "sg:phone":"+41 71 222 60 01",
    "sg:postcode":"1422",
    "sg:province":"Vaud",
    "wof:name":"Jean Bollhalter Liegenschaftsverwaltung Verwa",
    "wof:placetype":"venue"
},
  "geometry": {"coordinates":[9.3741111755,47.4217948914],"type":"Point"}
}