{
  "type": "Feature",
  "properties": {
    "iso:country":"CH",
    "sg:address":"Oberh\u00f6rstetten",
    "sg:city":"Unterh\u00f6rstetten",
    "sg:orig_category":"Autogaragen",
    "sg:phone":"+41 52 763 24 63",
    "sg:postcode":"8508",
    "sg:province":"Thurgau",
    "wof:name":"Fernando Frei Toyota-& Leyland-garage",
    "wof:placetype":"venue"
},
  "geometry": {"coordinates":[9.00956,47.634415],"type":"Point"}
}