{
  "type": "Feature",
  "properties": {
    "iso:country":"CH",
    "sg:address":"Route De La Gemmi",
    "sg:city":"Sierre",
    "sg:orig_category":"Herstellung von sonstigen Metallwaren",
    "sg:phone":"+41 27 455 44 95",
    "sg:postcode":"3960",
    "sg:province":"Valais",
    "wof:name":"Metafa, Metallwarenfabrik Ag",
    "wof:placetype":"venue"
},
  "geometry": {"coordinates":[7.5557169914,46.2986793518],"type":"Point"}
}