{
  "type": "Feature",
  "properties": {
    "iso:country":"CH",
    "sg:address":"Route D'englisberg 11",
    "sg:city":"Granges-paccot",
    "sg:orig_category":"Allgemeiner Hoch U Tiefbau",
    "sg:phone":"+41 34 437 17 13",
    "sg:postcode":"1763",
    "sg:province":"Fribourg",
    "wof:name":"Waber Christian.",
    "wof:placetype":"venue"
},
  "geometry": {"coordinates":[7.737956,47.035275],"type":"Point"}
}