{
  "type": "Feature",
  "properties": {
    "iso:country":"CH",
    "sg:address":"Burgstrasse 175",
    "sg:city":"Riehen",
    "sg:orig_category":"Reiseb\u00fcros U Reiseveranstalter",
    "sg:postcode":"4125",
    "sg:province":"Basel-Stadt",
    "wof:name":"J. Buhl",
    "wof:placetype":"venue"
},
  "geometry": {"coordinates":[7.6394982338,47.5776023865],"type":"Point"}
}