{
  "type": "Feature",
  "properties": {
    "iso:country":"CH",
    "sg:address":"Babylonstrasse 615",
    "sg:city":"Neuendorf",
    "sg:orig_category":"Elektroinstallation",
    "sg:phone":"+41 79 209 10 40",
    "sg:postcode":"4623",
    "sg:province":"Solothurn",
    "wof:name":"Wyss Elektro Ag, Elektrische Unternehmung",
    "wof:placetype":"venue"
},
  "geometry": {"coordinates":[7.8017001152,47.2964286804],"type":"Point"}
}