{
  "type": "Feature",
  "properties": {
    "iso:country":"CH",
    "sg:address":"Route De Lausanne 16",
    "sg:city":"Yverdon-les-bains",
    "sg:orig_category":"Mechanische Werkst\u00e4tten",
    "sg:phone":"+41 31 882 15 15",
    "sg:postcode":"1400",
    "sg:province":"Vaud",
    "wof:name":"Bernhard B\u00fctikofer Mechanik",
    "wof:placetype":"venue"
},
  "geometry": {"coordinates":[7.3602480888,46.9157333374],"type":"Point"}
}