{
  "type": "Feature",
  "properties": {
    "iso:country":"CH",
    "sg:address":"Rue De La Terrassi\u00e8re 13 1200 Genf. Postfach",
    "sg:city":"Gen\u00e8ve",
    "sg:orig_category":"Vermietung U Verpachtung von eigenen Immobilien",
    "sg:postcode":"1207",
    "sg:province":"Gen\u00e8ve",
    "wof:name":"Myrko Ag",
    "wof:placetype":"venue"
},
  "geometry": {"coordinates":[9.560918808,47.4253234863],"type":"Point"}
}