{
  "type": "Feature",
  "properties": {
    "iso:country":"CH",
    "sg:address":"Gurtenareal 1",
    "sg:city":"Wabern",
    "sg:orig_category":"Werbeagenturen Werbegrafikateliers",
    "sg:phone":"+41 31 960 43 33",
    "sg:postcode":"3084",
    "sg:province":"Bern",
    "wof:name":"B & B Blunier & Bossard Werbeberatung & Grafik",
    "wof:placetype":"venue"
},
  "geometry": {"coordinates":[7.4394087791,46.9296913147],"type":"Point"}
}