{
  "type": "Feature",
  "properties": {
    "iso:country":"CH",
    "sg:address":"Auf Dem Graben 26 3800 Unterseen. Postfach 159",
    "sg:city":"Unterseen",
    "sg:orig_category":"Grosshandel mit Textilien Herstellung von Teppichen",
    "sg:phone":"+41 79 656 69 17",
    "sg:postcode":"3800",
    "sg:province":"Bern",
    "wof:name":"Chaubert Ag",
    "wof:placetype":"venue"
},
  "geometry": {"coordinates":[7.8485770226,46.6865463257],"type":"Point"}
}