{
  "type": "Feature",
  "properties": {
    "addr:full":"Hermikonstr. 39a 8600 D\u00fcbendorf. Postfach D\u00fcbendorf Z\u00fcrich 8600",
    "addr:housenumber":"39a",
    "addr:postcode":"8600;8600",
    "addr:street":"Hermikonstr.;Postfach",
    "iso:country":"CH",
    "sg:address":"Hermikonstr. 39a 8600 D\u00fcbendorf. Postfach",
    "sg:city":"D\u00fcbendorf",
    "sg:orig_category":"Detailhandel mit Bekleidung",
    "sg:postcode":"8600",
    "sg:province":"Z\u00fcrich",
    "wof:name":"Damenmode Kurth B. C.",
    "wof:placetype":"venue"
},
  "geometry": {"coordinates":[8.626163,47.394138],"type":"Point"}
}