{
  "type": "Feature",
  "properties": {
    "addr:full":"Unterdorfstrasse 26 Wigoltingen Thurgau 8556",
    "addr:housenumber":"26",
    "addr:postcode":"8556",
    "addr:street":"Unterdorfstrasse",
    "iso:country":"CH",
    "sg:address":"Unterdorfstrasse 26",
    "sg:city":"Wigoltingen",
    "sg:orig_category":"Allgemeiner Hoch U Tiefbau Hobel U Holzimpr\u00e4gnierwerke",
    "sg:phone":"+41 79 631 80 11",
    "sg:postcode":"8556",
    "sg:province":"Thurgau",
    "wof:name":"Engeli Walter & Co Holz Und Bautenschutz",
    "wof:placetype":"venue"
},
  "geometry": {"coordinates":[9.0295,47.601749],"type":"Point"}
}