{
  "type": "Feature",
  "properties": {
    "iso:country":"CH",
    "sg:address":"Route Des Lacs 1 3960 Sierre Case Postale 319",
    "sg:city":"Sierre",
    "sg:orig_category":"Handel mit Motorr\u00e4dern, Teilen U Zubeh\u00f6r Instandhaltung U Reparatur von Motorr\u00e4dern",
    "sg:postcode":"3960",
    "sg:province":"Valais",
    "wof:name":"Corona P.",
    "wof:placetype":"venue"
},
  "geometry": {"coordinates":[9.8209161758,46.7938766479],"type":"Point"}
}