{
  "type": "Feature",
  "properties": {
    "iso:country":"CH",
    "sg:address":"Zimmertalstrasse 2",
    "sg:city":"Sarnen",
    "sg:classifiers":[
        {
            "category":"Education",
            "subcategory":"Library",
            "type":"Public Place"
        }
    ],
    "sg:postcode":"6060",
    "sg:province":"Obwalden",
    "sg:tags":[
        "u",
        "bibliotheken",
        "archive"
    ],
    "wof:name":"Bibliothek Des Kath.volksvereins",
    "wof:placetype":"venue"
},
  "geometry": {"coordinates":[9.02664,47.41993],"type":"Point"}
}