{
  "type": "Feature",
  "properties": {
    "iso:country":"CH",
    "sg:address":"Rue De Champr\u00e9veyres 2",
    "sg:city":"Neuch\u00e2tel",
    "sg:orig_category":"Fachdetailhandel in Verkaufsr\u00e4umen Herstellung von elektronischen Bauelementen",
    "sg:phone":"+41 87803041",
    "sg:postcode":"2000",
    "sg:province":"Neuch\u00e2tel",
    "wof:name":"Alpes Lasers",
    "wof:placetype":"venue"
},
  "geometry": {"coordinates":[6.9624547958,47.005317688],"type":"Point"}
}