{
  "type": "Feature",
  "properties": {
    "iso:country":"CH",
    "sg:address":"Repos Chemin Du 2 1213 Petit-lancy. Postfach",
    "sg:city":"Petit-lancy",
    "sg:orig_category":"Detailhandel mit Bekleidung",
    "sg:phone":"+41 22 793 74 47",
    "sg:postcode":"1213",
    "sg:province":"Gen\u00e8ve",
    "wof:name":"Az Distribution, Olaniyi Edward",
    "wof:placetype":"venue"
},
  "geometry": {"coordinates":[6.100106,46.183716],"type":"Point"}
}