{
  "type": "Feature",
  "properties": {
    "iso:country":"CH",
    "sg:address":"Buchholzweg 38",
    "sg:city":"K\u00f6niz",
    "sg:orig_category":"Sportvereine Ballsport Volleyball",
    "sg:postcode":"3098",
    "sg:province":"Bern",
    "wof:name":"Volleyball-club K\u00f6niz",
    "wof:placetype":"venue"
},
  "geometry": {"coordinates":[7.4212021828,46.913734436],"type":"Point"}
}