{
  "type": "Feature",
  "properties": {
    "iso:country":"CH",
    "sg:address":"St. Johanns-ring 43 4056 Basel. Postfach",
    "sg:city":"Basel",
    "sg:orig_category":"Vermietung U Verpachtung von eigenen Immobilien",
    "sg:postcode":"4051",
    "sg:province":"Basel-Stadt",
    "wof:name":"Peter Str\u00fcbin, Immobilien Immobilien; Erwerb, Verwaltung, Ver\u00e4usserung",
    "wof:placetype":"venue"
},
  "geometry": {"coordinates":[7.5775179863,47.5642471313],"type":"Point"}
}