{
  "type": "Feature",
  "properties": {
    "iso:country":"CH",
    "sg:address":"Untermattweg 8 3027 Bern. Postfach 382",
    "sg:city":"Bern",
    "sg:orig_category":"Grosshandel mit elektrischen Haushaltsger\u00e4ten, Radio U Fernsehger\u00e4ten Herstellung von sonstigen elek",
    "sg:phone":"+41 31 990 71 11",
    "sg:postcode":"3027",
    "sg:province":"Bern",
    "wof:name":"S\u00e9cheron Sa, Succursale De Berne",
    "wof:placetype":"venue"
},
  "geometry": {"coordinates":[7.40020895,46.9491577148],"type":"Point"}
}