{
  "type": "Feature",
  "properties": {
    "iso:country":"CH",
    "sg:address":"Sur La Rive 116",
    "sg:city":"Corban",
    "sg:orig_category":"Mechanische Werkst\u00e4tten",
    "sg:phone":"+41 32 438 88 60",
    "sg:postcode":"2826",
    "sg:province":"Jura",
    "wof:name":"Jacques Erismann Travaux De M\u00e9canique",
    "wof:placetype":"venue"
},
  "geometry": {"coordinates":[7.4711060524,47.3462295532],"type":"Point"}
}