{
  "type": "Feature",
  "properties": {
    "addr:full":"Rue De La Plaine 14 / Cp 575 Yverdon Vaud 1400",
    "addr:housenumber":"14 / cp",
    "addr:postcode":"575;1400",
    "addr:street":"Rue De La Plaine",
    "iso:country":"CH",
    "sg:address":"Rue De La Plaine 14 / Cp 575",
    "sg:city":"Yverdon",
    "sg:classifiers":[
        {
            "category":"Banks & Credit Unions",
            "subcategory":"Bank",
            "type":"Services"
        }
    ],
    "sg:phone":"+41 24 423 43 00",
    "sg:postcode":"1400",
    "sg:province":"Vaud",
    "wof:name":"Banque Piguet & Cie Sa, Gestion De Fortunes",
    "wof:placetype":"venue"
},
  "geometry": {"coordinates":[6.670759,46.781742],"type":"Point"}
}