{
  "type": "Feature",
  "properties": {
    "iso:country":"CH",
    "sg:address":"Rue Des Moulins 39",
    "sg:city":"Versoix",
    "sg:orig_category":"Innendekorationsateliers Maler U Glasergewerbe",
    "sg:phone":"+41 32 751 34 59",
    "sg:postcode":"1290",
    "sg:province":"Gen\u00e8ve",
    "wof:name":"Seigneur Jean-marc, Succursale De La Neuveville",
    "wof:placetype":"venue"
},
  "geometry": {"coordinates":[7.097671032,47.0666847229],"type":"Point"}
}