{
  "type": "Feature",
  "properties": {
    "iso:country":"CH",
    "sg:address":"1837",
    "sg:city":"Ch\u00e2teau-d'oex",
    "sg:classifiers":[
        {
            "category":"Travel",
            "subcategory":"Hotels & Motels",
            "type":"Entertainment"
        }
    ],
    "sg:phone":"+41 26 924 57 04",
    "sg:postcode":"1837",
    "sg:tags":[
        "hotels",
        "mit",
        "restaurant"
    ],
    "wof:name":"Hotel Des Bouquetins",
    "wof:placetype":"venue"
},
  "geometry": {"coordinates":[0.6858400106,45.2460517883],"type":"Point"}
}