{
  "type": "Feature",
  "properties": {
    "iso:country":"CH",
    "sg:address":"Bullenbergstrasse 31c 5612 Villmergen. Postfach",
    "sg:city":"Villmergen",
    "sg:orig_category":"Sonstige mit der Informatik verbundene T\u00e4tigkeiten",
    "sg:postcode":"5612",
    "sg:province":"Aargau",
    "wof:name":"Adabis Engineering Gmbh",
    "wof:placetype":"venue"
},
  "geometry": {"coordinates":[8.2550153732,47.3464546204],"type":"Point"}
}