{
  "type": "Feature",
  "properties": {
    "iso:country":"CH",
    "sg:address":"Hofstatt 15",
    "sg:city":"Erstfeld",
    "sg:orig_category":"Bau U Wohngenossenschaften",
    "sg:postcode":"6472",
    "sg:province":"Uri",
    "wof:name":"Baugenossenschaft Birtschen",
    "wof:placetype":"venue"
},
  "geometry": {"coordinates":[8.646785,46.824047],"type":"Point"}
}