{
  "type": "Feature",
  "properties": {
    "iso:country":"CH",
    "sg:address":"Avenue De La Riollaz 5",
    "sg:city":"Payerne",
    "sg:orig_category":"Internationale Organisationen mit Beh\u00f6rdecharakter",
    "sg:phone":"+41 26 660 11 52",
    "sg:postcode":"1530",
    "sg:province":"Vaud",
    "wof:name":"Assoc.europ\u00e9enne Des Enseignants,m.jean-p.thi\u00e9baud",
    "wof:placetype":"venue"
},
  "geometry": {"coordinates":[6.9417190552,46.818611145],"type":"Point"}
}