{
  "type": "Feature",
  "properties": {
    "iso:country":"CH",
    "sg:address":"3322",
    "sg:city":"Mattstetten",
    "sg:orig_category":"Gemeindeverwaltungen",
    "sg:phone":"+41 31 859 19 41",
    "sg:postcode":"3322",
    "sg:province":"Bern",
    "wof:name":"Gemeindeverwaltung Mattstetten",
    "wof:placetype":"venue"
},
  "geometry": {"coordinates":[7.5029997826,47.0181694031],"type":"Point"}
}