{
  "type": "Feature",
  "properties": {
    "addr:full":"Rietstrasse 3 Tagelswangen Z\u00fcrich 8317",
    "addr:housenumber":"3",
    "addr:postcode":"8317",
    "addr:street":"Rietstrasse",
    "iso:country":"CH",
    "sg:address":"Rietstrasse 3",
    "sg:city":"Tagelswangen",
    "sg:orig_category":"Detailhandel mit Antiquit\u00e4ten Detailhandel mit B\u00fcchern",
    "sg:phone":"+41 52 343 53 31",
    "sg:postcode":"8317",
    "sg:province":"Z\u00fcrich",
    "wof:name":"Hansj\u00f6rg Struchen Antiquit\u00e4ten & B\u00fccher",
    "wof:placetype":"venue"
},
  "geometry": {"coordinates":[8.672168,47.43383],"type":"Point"}
}