{
  "type": "Feature",
  "properties": {
    "iso:country":"CH",
    "sg:address":"Dorfweg 9",
    "sg:city":"Uster",
    "sg:orig_category":"Non-Classified Establishments",
    "sg:postcode":"8610",
    "sg:province":"Z\u00fcrich",
    "wof:name":"Walitec Rohrsysteme Walter Meier",
    "wof:placetype":"venue"
},
  "geometry": {"coordinates":[8.7314434052,47.3443527222],"type":"Point"}
}