{
  "type": "Feature",
  "properties": {
    "iso:country":"CH",
    "sg:address":"Hauptstr. 69",
    "sg:city":"Gossliwil",
    "sg:orig_category":"Reinigungsgewerbe",
    "sg:phone":"+41 32 661 01 05",
    "sg:postcode":"4579",
    "sg:province":"Solothurn",
    "wof:name":"Amigo Reinigungen",
    "wof:placetype":"venue"
},
  "geometry": {"coordinates":[7.4350762367,47.1370277405],"type":"Point"}
}