{
  "type": "Feature",
  "properties": {
    "iso:country":"CH",
    "sg:address":"Kehrweg 374",
    "sg:city":"Wittnau",
    "sg:orig_category":"Unclassifiable Establishments",
    "sg:phone":"+41 62 871 09 77",
    "sg:postcode":"5064",
    "sg:province":"Aargau",
    "wof:name":"Webideen",
    "wof:placetype":"venue"
},
  "geometry": {"coordinates":[7.9797701836,47.4831504822],"type":"Point"}
}