{
  "type": "Feature",
  "properties": {
    "addr:full":"Fellenbergstrasse 289 Z\u00fcrich Z\u00fcrich 8047",
    "addr:housenumber":"289",
    "addr:postcode":"8047",
    "addr:street":"Fellenbergstrasse",
    "iso:country":"CH",
    "sg:address":"Fellenbergstrasse 289",
    "sg:city":"Z\u00fcrich",
    "sg:orig_category":"Aktivit\u00e4ten der Generalunternehmen im Baugewerbe Architekturb\u00fcros",
    "sg:phone":"+41 14974097",
    "sg:postcode":"8047",
    "sg:province":"Z\u00fcrich",
    "wof:name":"Max Sch\u00f6nenberg & Partner Ag",
    "wof:placetype":"venue"
},
  "geometry": {"coordinates":[8.490612,47.375187],"type":"Point"}
}