{
  "type": "Feature",
  "properties": {
    "iso:country":"CH",
    "sg:address":"Amriswilerstrasse 3",
    "sg:city":"Bischofszell",
    "sg:orig_category":"Wirtschaftspr\u00fcfung, Steuerberatung U Treuhand",
    "sg:phone":"+41 71 422 60 77",
    "sg:postcode":"9220",
    "sg:province":"Thurgau",
    "wof:name":"Iic - Kirmizi",
    "wof:placetype":"venue"
},
  "geometry": {"coordinates":[9.2408180237,47.498134613],"type":"Point"}
}