{
  "type": "Feature",
  "properties": {
    "iso:country":"CH",
    "sg:address":"Avenue Kiener 17",
    "sg:city":"Yverdon-les-bains",
    "sg:orig_category":"R\u00fcckgewinnung U Vorbereitung f\u00fcr die Wiederverwertung Recycling von Schrott",
    "sg:phone":"+41 41 988 19 87",
    "sg:postcode":"1400",
    "sg:province":"Vaud",
    "wof:name":"M\u00fcller Leo Autoverwertung",
    "wof:placetype":"venue"
},
  "geometry": {"coordinates":[7.9368600845,47.1366004944],"type":"Point"}
}