{
  "type": "Feature",
  "properties": {
    "iso:country":"CH",
    "sg:city":"St. German",
    "sg:classifiers":[
        {
            "category":"Banks & Credit Unions",
            "subcategory":"Bank",
            "type":"Services"
        }
    ],
    "sg:phone":"+41 4128442044",
    "sg:postcode":"3936",
    "wof:name":"Raiffeisenbank",
    "wof:placetype":"venue"
},
  "geometry": {"coordinates":[7.822692,46.312092],"type":"Point"}
}