{
  "type": "Feature",
  "properties": {
    "iso:country":"CH",
    "sg:address":"Brandisstrasse 8",
    "sg:city":"Chur",
    "sg:orig_category":"Politische Parteien SVP",
    "sg:phone":"+41 81 252 60 53",
    "sg:postcode":"7000",
    "sg:province":"Graubunden",
    "wof:name":"Schweiz.volkspartei Svp Graub\u00fcnden",
    "wof:placetype":"venue"
},
  "geometry": {"coordinates":[9.5340461731,46.854221344],"type":"Point"}
}