{
  "type": "Feature",
  "properties": {
    "iso:country":"CH",
    "sg:address":"H\u00e4rd\u00f6pfuhoger 17 4812 M\u00fchlethal. Postfach",
    "sg:city":"M\u00fchlethal",
    "sg:orig_category":"Allgemeiner Hoch U Tiefbau",
    "sg:phone":"+41 27 785 24 12",
    "sg:postcode":"4812",
    "sg:province":"Aargau",
    "wof:name":"Besse Et Baillifard Sa",
    "wof:placetype":"venue"
},
  "geometry": {"coordinates":[7.212448,46.08046],"type":"Point"}
}