{
  "type": "Feature",
  "properties": {
    "iso:country":"CH",
    "sg:address":"1063",
    "sg:city":"Chapelle-s-moudon",
    "sg:orig_category":"Verwertung von Milch",
    "sg:postcode":"1063",
    "sg:province":"Vaud",
    "wof:name":"Soci\u00e9t\u00e9 De Laiterie De Charmey",
    "wof:placetype":"venue"
},
  "geometry": {"coordinates":[7.1641640663,46.6192207336],"type":"Point"}
}