{
  "type": "Feature",
  "properties": {
    "iso:country":"CH",
    "sg:address":"Z\u00fcrcher Strasse 267 9014 St. Gallen",
    "sg:city":"Zust",
    "sg:orig_category":"Herstellung von k\u00e4lte U lufttechnischen Erzeugnissen f\u00fcr gewerbliche Zwecke",
    "sg:phone":"+41 41 497 35 35",
    "sg:postcode":"14",
    "wof:name":"Burri Josef Ag",
    "wof:placetype":"venue"
},
  "geometry": {"coordinates":[8.1827249527,47.0368156433],"type":"Point"}
}