{
  "type": "Feature",
  "properties": {
    "iso:country":"CH",
    "sg:address":"Chesa Crasta",
    "sg:city":"Pontresina",
    "sg:orig_category":"Elektroinstallation",
    "sg:phone":"+41 81 837 32 32",
    "sg:postcode":"7504",
    "sg:province":"Graubunden",
    "wof:name":"Pomatti Ag",
    "wof:placetype":"venue"
},
  "geometry": {"coordinates":[9.9050941467,46.4886283875],"type":"Point"}
}