{
  "type": "Feature",
  "properties": {
    "iso:country":"CH",
    "sg:address":"7422",
    "sg:city":"Tartar",
    "sg:orig_category":"G\u00fcterbef\u00f6rderung im Strassenverkehr",
    "sg:postcode":"7422",
    "sg:province":"Graubunden",
    "wof:name":"Tiri Chr.",
    "wof:placetype":"venue"
},
  "geometry": {"coordinates":[9.4193201065,46.7181587219],"type":"Point"}
}