{
  "type": "Feature",
  "properties": {
    "iso:country":"CH",
    "sg:address":"Route De Ch\u00e2telard 52",
    "sg:city":"Lausanne",
    "sg:orig_category":"Architektur U Ingenieurb\u00fcros",
    "sg:phone":"+41 21 646 17 74",
    "sg:postcode":"1018",
    "sg:province":"Vaud",
    "wof:name":"Pierre Chuard Bureau D'ing\u00e9nieur",
    "wof:placetype":"venue"
},
  "geometry": {"coordinates":[6.624012,46.543434],"type":"Point"}
}