{
  "type": "Feature",
  "properties": {
    "iso:country":"CH",
    "sg:address":"Gesellschaftsstrasse 21",
    "sg:city":"Bern",
    "sg:orig_category":"Elektroinstallation Finanzierungsinstitutionen",
    "sg:phone":"+41 31 302 10 70",
    "sg:postcode":"3012",
    "sg:province":"Bern",
    "wof:name":"Bernelektro Ag",
    "wof:placetype":"venue"
},
  "geometry": {"coordinates":[7.4363808632,46.952507019],"type":"Point"}
}