{
  "type": "Feature",
  "properties": {
    "iso:country":"CH",
    "sg:address":"Altgasse 13",
    "sg:city":"Baar",
    "sg:classifiers":[
        {
            "category":"Travel",
            "subcategory":"Hotels & Motels",
            "type":"Entertainment"
        }
    ],
    "sg:postcode":"6340",
    "sg:province":"Zug",
    "sg:tags":[
        "hotels",
        "mit",
        "restaurant"
    ],
    "wof:name":"J. M\u00fcrner-kernen",
    "wof:placetype":"venue"
},
  "geometry": {"coordinates":[7.7210421562,46.5906181335],"type":"Point"}
}