{
  "type": "Feature",
  "properties": {
    "iso:country":"CH",
    "sg:address":"Schaffhauserstrasse 85",
    "sg:city":"Glattbrugg",
    "sg:orig_category":"Detailhandel mit Bekleidung Detailhandel mit Textilien",
    "sg:phone":"+41 18104157",
    "sg:postcode":"8152",
    "sg:province":"Z\u00fcrich",
    "wof:name":"Guglielmo Ferretto Mercerie & Textilien",
    "wof:placetype":"venue"
},
  "geometry": {"coordinates":[8.563137,47.431995],"type":"Point"}
}