{
  "type": "Feature",
  "properties": {
    "iso:country":"CH",
    "sg:address":"R\u00fcegsaustrasse 5",
    "sg:city":"Hasle-r\u00fcegsau",
    "sg:orig_category":"Detailhandel mit Schuhen",
    "sg:phone":"+41 34 461 17 79",
    "sg:postcode":"3415",
    "sg:province":"Bern",
    "wof:name":"Werner Burkhalter Schuhhaus",
    "wof:placetype":"venue"
},
  "geometry": {"coordinates":[7.6563792229,47.0166625977],"type":"Point"}
}