{
  "type": "Feature",
  "properties": {
    "iso:country":"CH",
    "sg:address":"2822",
    "sg:city":"Courroux",
    "sg:orig_category":"Detailhandel mit Milcherzeugnissen U Eiern Verarbeitung von Milch",
    "sg:postcode":"2822",
    "sg:province":"Jura",
    "wof:name":"Soci\u00e9t\u00e9 De Laiterie De Puidoux-village",
    "wof:placetype":"venue"
},
  "geometry": {"coordinates":[9.6746397018,56.4246482849],"type":"Point"}
}