{
  "type": "Feature",
  "properties": {
    "iso:country":"CH",
    "sg:address":"Talgut-zentrum 34",
    "sg:city":"Ittigen",
    "sg:orig_category":"Arztpraxen",
    "sg:phone":"+41 31 921 00 71",
    "sg:postcode":"3063",
    "sg:province":"Bern",
    "wof:name":"Dr.med.emil Dreyer Arzt F.allgemeine Medizin Fmh",
    "wof:placetype":"venue"
},
  "geometry": {"coordinates":[7.481509,46.974644],"type":"Point"}
}