{
  "type": "Feature",
  "properties": {
    "iso:country":"CH",
    "sg:address":"Grossteilerstrasse 50",
    "sg:city":"Giswil",
    "sg:orig_category":"Detailhandel mit Brot, Back U S\u00fcsswaren Detailhandel mit Waren verschiedener Art, Hauptrichtung Nahr",
    "sg:phone":"+41 41 675 10 24",
    "sg:postcode":"6074",
    "sg:province":"Obwalden",
    "wof:name":"Hans Vogler Sunnis B\u00e4ckerei-konditorei",
    "wof:placetype":"venue"
},
  "geometry": {"coordinates":[8.17088,46.847988],"type":"Point"}
}