{
  "type": "Feature",
  "properties": {
    "iso:country":"CH",
    "sg:address":"Hauptstr. 8",
    "sg:city":"Lostorf",
    "sg:classifiers":[
        {
            "category":"Shopping",
            "subcategory":"Computers & Home Electronics",
            "type":"Retail Goods"
        }
    ],
    "sg:phone":"+41 62 298 15 70",
    "sg:postcode":"4654",
    "sg:province":"Solothurn",
    "sg:tags":[
        "electronic",
        "electrical",
        "equipment"
    ],
    "wof:name":"Ernst K\u00c4ser",
    "wof:placetype":"venue"
},
  "geometry": {"coordinates":[7.9490919113,47.3780059814],"type":"Point"}
}