{
  "type": "Feature",
  "properties": {
    "iso:country":"CH",
    "sg:address":"Piazza Stazione 4",
    "sg:city":"Muralto",
    "sg:orig_category":"Detailhandel mit Damenbekleidung",
    "sg:phone":"+41 91 743 85 55",
    "sg:postcode":"6600",
    "sg:province":"Ticino",
    "wof:name":"Beldona Ag",
    "wof:placetype":"venue"
},
  "geometry": {"coordinates":[8.800718,46.172012],"type":"Point"}
}