{
  "type": "Feature",
  "properties": {
    "iso:country":"CH",
    "sg:address":"Laret 38",
    "sg:city":"Pontresina",
    "sg:orig_category":"Interessenvertretungen",
    "sg:postcode":"7504",
    "sg:province":"Graubunden",
    "wof:name":"Pro Lutra",
    "wof:placetype":"venue"
},
  "geometry": {"coordinates":[9.9024705887,46.4937591553],"type":"Point"}
}