{
  "type": "Feature",
  "properties": {
    "iso:country":"CH",
    "sg:address":"Bantigerstrasse 35 3006 Bern. Postfach",
    "sg:city":"Bern",
    "sg:orig_category":"Detailhandel mit Fleisch U Fleischwaren",
    "sg:postcode":"3005",
    "sg:province":"Bern",
    "wof:name":"R\u00fcegg-f\u00e4ssler Frau",
    "wof:placetype":"venue"
},
  "geometry": {"coordinates":[8.9215288162,47.2395362854],"type":"Point"}
}