{
  "type": "Feature",
  "properties": {
    "iso:country":"CH",
    "sg:address":"F\u00fcrstensteinerstrasse 48",
    "sg:city":"Basel",
    "sg:orig_category":"Allgemeiner Gartenbau Dienstleistungen im Gartenbau",
    "sg:postcode":"4053",
    "sg:province":"Basel-Stadt",
    "wof:name":"Cederus Ag Gartenpflege & Unterhalt",
    "wof:placetype":"venue"
},
  "geometry": {"coordinates":[7.559219,47.506977],"type":"Point"}
}