{
  "type": "Feature",
  "properties": {
    "iso:country":"CH",
    "sg:address":"Pilatusstrasse 1",
    "sg:city":"Aarburg",
    "sg:classifiers":[
        {
            "category":"Restaurant",
            "type":"Food & Drink"
        }
    ],
    "sg:phone":"+41 62 791 58 18",
    "sg:postcode":"4663",
    "sg:province":"Aargau",
    "wof:name":"Restaurant Central",
    "wof:placetype":"venue"
},
  "geometry": {"coordinates":[7.9001531601,47.3198471069],"type":"Point"}
}