{
  "type": "Feature",
  "properties": {
    "addr:full":"Rue De La Thiolleyres 20 Estavayer-le-lac Fribourg 1470",
    "addr:housenumber":"20",
    "addr:postcode":"1470",
    "addr:street":"Rue De La Thiolleyres;Fribourg",
    "iso:country":"CH",
    "sg:address":"Rue De La Thiolleyres 20",
    "sg:city":"Estavayer-le-lac",
    "sg:orig_category":"Detailhandel mit Brot, Back U S\u00fcsswaren",
    "sg:phone":"+41 26 663 41 73",
    "sg:postcode":"1470",
    "sg:province":"Fribourg",
    "wof:name":"Roland Horisberger Boulangerie & P\u00e2tisserie",
    "wof:placetype":"venue"
},
  "geometry": {"coordinates":[6.844299,46.849018],"type":"Point"}
}