{
  "type": "Feature",
  "properties": {
    "addr:full":"Solothurnstrasse 47 Luterbach Solothurn 4542",
    "addr:housenumber":"47",
    "addr:postcode":"4542",
    "addr:street":"Solothurnstrasse",
    "iso:country":"CH",
    "sg:address":"Solothurnstrasse 47",
    "sg:city":"Luterbach",
    "sg:orig_category":"Architekturb\u00fcros",
    "sg:phone":"+41 19322444",
    "sg:postcode":"4542",
    "sg:province":"Solothurn",
    "wof:name":"Markus Dieterle Architekturb\u00fcro",
    "wof:placetype":"venue"
},
  "geometry": {"coordinates":[8.789124,47.306644],"type":"Point"}
}