{
  "type": "Feature",
  "properties": {
    "iso:country":"CH",
    "sg:address":"Kantonsstrasse 3930 Visp. Postfach",
    "sg:city":"Visp",
    "sg:orig_category":"RESTAURANTS: TEA-ROOMS",
    "sg:postcode":"3930",
    "sg:province":"Valais",
    "wof:name":"Pizzeria-restaurant Le Bristol, Blatter Liselotte",
    "wof:placetype":"venue"
},
  "geometry": {"coordinates":[7.877933979,46.2925758362],"type":"Point"}
}