{
  "type": "Feature",
  "properties": {
    "iso:country":"CH",
    "sg:address":"Hauptstrasse 131 6182 Escholzmatt. Postfach 82",
    "sg:city":"Escholzmatt",
    "sg:orig_category":"S\u00e4ge, Hobel U Holzimpr\u00e4gnierwerke S\u00e4gewerke",
    "sg:phone":"+41 41 486 12 40",
    "sg:postcode":"6182",
    "sg:province":"Luzern",
    "wof:name":"Bucher Jos. Ag, S\u00e4ge Und Hobelwerk",
    "wof:placetype":"venue"
},
  "geometry": {"coordinates":[7.9330430031,46.9113807678],"type":"Point"}
}