{
  "type": "Feature",
  "properties": {
    "iso:country":"CH",
    "sg:address":"Route De Compois 6 1245 Collonge-bellerive Case Postale 212",
    "sg:city":"Collonge-bellerive",
    "sg:orig_category":"Herstellung von Mess U Kontrollinstrumenten U vorrichtungen",
    "sg:phone":"+41 22 855 91 00",
    "sg:postcode":"1245",
    "sg:province":"Gen\u00e8ve",
    "wof:name":"Orbisph\u00e8re Gve Sa",
    "wof:placetype":"venue"
},
  "geometry": {"coordinates":[6.2174291611,46.2472648621],"type":"Point"}
}