{
  "type": "Feature",
  "properties": {
    "iso:country":"CH",
    "sg:address":"Marktgasse 31",
    "sg:city":"Interlaken",
    "sg:orig_category":"Detailhandel mit Schuhen",
    "sg:phone":"+41 33 823 33 25",
    "sg:postcode":"3800",
    "sg:province":"Bern",
    "wof:name":"Scarpino Schuhhaus",
    "wof:placetype":"venue"
},
  "geometry": {"coordinates":[7.8532891273,46.6855697632],"type":"Point"}
}