{
  "type": "Feature",
  "properties": {
    "iso:country":"CH",
    "sg:address":"Schmiedgasse 1 6370 Stans. Postfach 994",
    "sg:city":"Stans",
    "sg:orig_category":"Fachdetailhandel in Verkaufsr\u00e4umen Grosshandel mit Foto U Kinoger\u00e4ten, feinmechanischen U optischen ",
    "sg:phone":"+41 41 610 66 44",
    "sg:postcode":"6370",
    "sg:province":"Nidwalden",
    "wof:name":"Schmiedgass Optik Ag",
    "wof:placetype":"venue"
},
  "geometry": {"coordinates":[8.3672122955,46.9563293457],"type":"Point"}
}