{
  "type": "Feature",
  "properties": {
    "iso:country":"CH",
    "sg:address":"D\u00fcrsenen Samstagern",
    "sg:city":"Richterswil",
    "sg:orig_category":"Allgemeiner Hoch U Tiefbau",
    "sg:postcode":"8805",
    "sg:province":"Z\u00fcrich",
    "wof:name":"Baugesellschaft Arta Ag",
    "wof:placetype":"venue"
},
  "geometry": {"coordinates":[9.007776,47.598274],"type":"Point"}
}