{
  "type": "Feature",
  "properties": {
    "iso:country":"CH",
    "sg:address":"Riedgrabenstrasse 16",
    "sg:city":"R\u00fcmlang",
    "sg:orig_category":"Herstellung von Kunststoffwaren Mechanik",
    "sg:phone":"+41 62 390 13 10",
    "sg:postcode":"8153",
    "sg:province":"Z\u00fcrich",
    "wof:name":"Dreno Gmbh",
    "wof:placetype":"venue"
},
  "geometry": {"coordinates":[7.7445139885,47.3313903809],"type":"Point"}
}