{
  "type": "Feature",
  "properties": {
    "iso:country":"CH",
    "sg:address":"Piazza Cioccaro 8",
    "sg:city":"Lugano",
    "sg:orig_category":"Wirtschaftspr\u00fcfung, Steuerberatung U Treuhand",
    "sg:phone":"+41 55 410 64 05",
    "sg:postcode":"6900",
    "sg:province":"Ticino",
    "wof:name":"Inglin Hermann",
    "wof:placetype":"venue"
},
  "geometry": {"coordinates":[8.7845592499,47.1978416443],"type":"Point"}
}