{
  "type": "Feature",
  "properties": {
    "iso:country":"CH",
    "sg:address":"R\u00fcfenacherstrasse 97",
    "sg:city":"Riniken",
    "sg:orig_category":"Herstellung von K\u00fcchenm\u00f6beln",
    "sg:phone":"+41 32 953 35 00",
    "sg:postcode":"5223",
    "sg:province":"Aargau",
    "wof:name":"Haefeli Joseph Sa",
    "wof:placetype":"venue"
},
  "geometry": {"coordinates":[6.9572901726,47.2244682312],"type":"Point"}
}