{
  "type": "Feature",
  "properties": {
    "iso:country":"CH",
    "sg:address":"Beauregard Avenue 1",
    "sg:city":"Freiburg",
    "sg:orig_category":"Grosshandel mit Getr\u00e4nken",
    "sg:phone":"+41 26 425 40 90",
    "sg:postcode":"1700",
    "sg:province":"Fribourg",
    "wof:name":"Evian-volvic Suisse Sa",
    "wof:placetype":"venue"
},
  "geometry": {"coordinates":[7.1489992142,46.8023338318],"type":"Point"}
}