{
  "type": "Feature",
  "properties": {
    "iso:country":"CH",
    "sg:address":"Hauptgasse 2",
    "sg:city":"Olten",
    "sg:orig_category":"Drogerien Parf\u00fcmerien U sonstiger Detailhandel mit kosmetischen Artikeln U K\u00f6rperpflegemitteln",
    "sg:phone":"+41 55 442 14 14",
    "sg:postcode":"4600",
    "sg:province":"Solothurn",
    "wof:name":"Urs Kr\u00e4henmann Drogerie Parf\u00fcmerie",
    "wof:placetype":"venue"
},
  "geometry": {"coordinates":[8.8518838882,47.1923904419],"type":"Point"}
}