{
  "type": "Feature",
  "properties": {
    "iso:country":"CH",
    "sg:address":"Pierre-\u00e0-bochet Ch.de La 16",
    "sg:city":"Th\u00f4nex",
    "sg:orig_category":"Non-Classified Establishments",
    "sg:postcode":"1226",
    "sg:province":"Gen\u00e8ve",
    "wof:name":"Sofimmo S\u00e0rl",
    "wof:placetype":"venue"
},
  "geometry": {"coordinates":[6.2149162292,46.1991157532],"type":"Point"}
}