{
  "type": "Feature",
  "properties": {
    "iso:country":"CH",
    "sg:address":"Giacomettistrasse 31",
    "sg:city":"Bern",
    "sg:orig_category":"Betrieb von Taxis G\u00fcterbef\u00f6rderung im Strassenverkehr",
    "sg:phone":"+41 31 351 70 70",
    "sg:postcode":"3006",
    "sg:province":"Bern",
    "wof:name":"Orlando Galiffa Transporte & Taxi Service",
    "wof:placetype":"venue"
},
  "geometry": {"coordinates":[7.473097,46.946613],"type":"Point"}
}