{
  "type": "Feature",
  "properties": {
    "addr:full":"Ackersteinstrasse 178 Z\u00fcrich Z\u00fcrich 8049",
    "addr:housenumber":"178",
    "addr:postcode":"8049",
    "addr:street":"Ackersteinstrasse",
    "iso:country":"CH",
    "sg:address":"Ackersteinstrasse 178",
    "sg:city":"Z\u00fcrich",
    "sg:orig_category":"Arztpraxen",
    "sg:phone":"+41 13415672",
    "sg:postcode":"8049",
    "sg:province":"Z\u00fcrich",
    "wof:name":"Dr.med.corinna Palla Spezial\u00e4rztin Fmh",
    "wof:placetype":"venue"
},
  "geometry": {"coordinates":[8.500832,47.400555],"type":"Point"}
}