{
  "type": "Feature",
  "properties": {
    "iso:country":"CH",
    "sg:address":"Moosweg 18",
    "sg:city":"Riehen",
    "sg:orig_category":"Schreib U \u00dcbersetzungsb\u00fcros",
    "sg:phone":"+41 18029020",
    "sg:postcode":"4125",
    "sg:province":"Basel-Stadt",
    "wof:name":"Herakles B\u00fcrodienste Und Buchhaltungen Scheidegger Kurt",
    "wof:placetype":"venue"
},
  "geometry": {"coordinates":[8.7584342957,47.3066902161],"type":"Point"}
}