{
  "type": "Feature",
  "properties": {
    "iso:country":"CH",
    "sg:address":"Lee 1",
    "sg:city":"Sch\u00f6nb\u00fchl-urtenen",
    "sg:orig_category":"Primarschulen",
    "sg:phone":"+41 31 859 05 00",
    "sg:postcode":"3322",
    "sg:province":"Bern",
    "wof:name":"Primarschule",
    "wof:placetype":"venue"
},
  "geometry": {"coordinates":[7.4995298386,47.0204238892],"type":"Point"}
}