{
  "type": "Feature",
  "properties": {
    "iso:country":"CH",
    "sg:address":"7434",
    "sg:city":"Sufers",
    "sg:orig_category":"Sportvereine Sch\u00fctzen",
    "sg:postcode":"7434",
    "sg:province":"Graubunden",
    "wof:name":"Schiessverein",
    "wof:placetype":"venue"
},
  "geometry": {"coordinates":[9.3665018082,46.5704421997],"type":"Point"}
}