{
  "type": "Feature",
  "properties": {
    "iso:country":"CH",
    "sg:address":"Kirchstrasse 24",
    "sg:city":"Glarus",
    "sg:orig_category":"Detailhandel mit Musikinstrumenten K\u00fcnstlerische Schulen",
    "sg:phone":"+41 79 420 36 92",
    "sg:postcode":"8750",
    "sg:province":"Glarus",
    "wof:name":"Luigi-gino Russo",
    "wof:placetype":"venue"
},
  "geometry": {"coordinates":[8.9300136566,47.2654914856],"type":"Point"}
}