{
  "type": "Feature",
  "properties": {
    "iso:country":"CH",
    "sg:address":"Feldstrasse 23",
    "sg:city":"Zizers",
    "sg:orig_category":"Hoch U Tiefbau",
    "sg:phone":"+41 81 322 59 62",
    "sg:postcode":"7205",
    "sg:province":"Graubunden",
    "wof:name":"J\u00fcrg Schlegel Umbauten & Renovationen",
    "wof:placetype":"venue"
},
  "geometry": {"coordinates":[9.5638599396,46.928691864],"type":"Point"}
}