{
  "type": "Feature",
  "properties": {
    "iso:country":"CH",
    "sg:address":"Route De Cossonay 100",
    "sg:city":"Prilly",
    "sg:classifiers":[
        {
            "category":"Professional",
            "subcategory":"Printing & Photocopies",
            "type":"Services"
        }
    ],
    "sg:phone":"+41 21 634 58 23",
    "sg:postcode":"1008",
    "sg:province":"Vaud",
    "sg:tags":[
        "presses",
        "digital"
    ],
    "wof:name":"Heidelberg Suisse Sa",
    "wof:placetype":"venue"
},
  "geometry": {"coordinates":[6.596807003,46.5397033691],"type":"Point"}
}