{
  "type": "Feature",
  "properties": {
    "iso:country":"CH",
    "sg:address":"Viaduktstrasse 5",
    "sg:city":"Grenchen",
    "sg:orig_category":"Gartenbau",
    "sg:phone":"+41 32 653 95 21",
    "sg:postcode":"2540",
    "sg:province":"Solothurn",
    "wof:name":"Hans Wilp Gartenbau & -pflege",
    "wof:placetype":"venue"
},
  "geometry": {"coordinates":[7.3935670853,47.1959533691],"type":"Point"}
}