{
  "type": "Feature",
  "properties": {
    "iso:country":"CH",
    "sg:address":"B\u00e4reggstrasse 2",
    "sg:city":"Langenthal",
    "sg:orig_category":"Sonstiger Fachdetailhandel mit Nahrungsmitteln, Getr\u00e4nken U Tabak in Verkaufsr\u00e4umen",
    "sg:postcode":"4900",
    "sg:province":"Bern",
    "wof:name":"Graf Hans Rudolf",
    "wof:placetype":"venue"
},
  "geometry": {"coordinates":[7.7827038765,47.2210426331],"type":"Point"}
}