{
  "type": "Feature",
  "properties": {
    "iso:country":"CH",
    "sg:address":"B\u00fcgl Da La Nina",
    "sg:city":"Samedan",
    "sg:classifiers":[
        {
            "category":"Education",
            "subcategory":"Library",
            "type":"Public Place"
        }
    ],
    "sg:phone":"+41 81 852 36 73",
    "sg:postcode":"7503",
    "sg:province":"Graubunden",
    "sg:tags":[
        "u",
        "bibliotheken",
        "archive"
    ],
    "wof:name":"Ludothek Arlekin",
    "wof:placetype":"venue"
},
  "geometry": {"coordinates":[9.869104,46.533527],"type":"Point"}
}