{
  "type": "Feature",
  "properties": {
    "iso:country":"CH",
    "sg:address":"Loostrasse 1",
    "sg:city":"R\u00fcschlikon",
    "sg:orig_category":"Instandhaltung U Reparatur von Automobilen",
    "sg:phone":"+41 55 240 50 00",
    "sg:postcode":"8803",
    "sg:province":"Z\u00fcrich",
    "wof:name":"Fischer Waldau Garage Gmbh, R\u00fcti",
    "wof:placetype":"venue"
},
  "geometry": {"coordinates":[8.8393688202,47.2607383728],"type":"Point"}
}