{
  "type": "Feature",
  "properties": {
    "addr:full":"Lyon Rue De 85 1203 Gen\u00e8ve Case Postale Gen\u00e8ve Gen\u00e8ve 1203",
    "addr:housenumber":"85",
    "addr:postcode":"1203;postale;1203",
    "addr:street":"Rue De",
    "iso:country":"CH",
    "sg:address":"Lyon Rue De 85 1203 Gen\u00e8ve Case Postale",
    "sg:city":"Gen\u00e8ve",
    "sg:orig_category":"Allgemeiner Hoch U Tiefbau",
    "sg:phone":"+41 41 850 14 22",
    "sg:postcode":"1203",
    "sg:province":"Gen\u00e8ve",
    "wof:name":"Gr\u00e4tzer Bautrans Gmbh, Baumaschinen Und Transportarbeiten",
    "wof:placetype":"venue"
},
  "geometry": {"coordinates":[8.441075,47.089996],"type":"Point"}
}