{
  "type": "Feature",
  "properties": {
    "iso:country":"CH",
    "sg:address":"H\u00f6flistrasse 1",
    "sg:city":"Reichenburg",
    "sg:orig_category":"Detailhandel mit Radio U Fernsehger\u00e4ten",
    "sg:phone":"+41 79 420 24 56",
    "sg:postcode":"8864",
    "sg:province":"Schwyz",
    "wof:name":"Guido Graf Radio-tv Video",
    "wof:placetype":"venue"
},
  "geometry": {"coordinates":[8.9831829071,47.1668167114],"type":"Point"}
}