{
  "type": "Feature",
  "properties": {
    "addr:full":"Gartematt 9 B\u00fclach Z\u00fcrich 8180",
    "addr:housenumber":"9",
    "addr:postcode":"8180",
    "addr:street":"Gartematt;Zuerich",
    "iso:country":"CH",
    "sg:address":"Gartematt 9",
    "sg:city":"B\u00fclach",
    "sg:orig_category":"Arztpraxen",
    "sg:phone":"+41 18605757",
    "sg:postcode":"8180",
    "sg:province":"Z\u00fcrich",
    "wof:name":"Dres Med. P. & C. Nagel Aerzte F\u00fcr Allg.medizin Fmh",
    "wof:placetype":"venue"
},
  "geometry": {"coordinates":[8.54282,47.518669],"type":"Point"}
}