{
  "type": "Feature",
  "properties": {
    "iso:country":"CH",
    "sg:address":"Alte Landstrasse 55 8702 Zollikon. Postfach 183",
    "sg:city":"Zollikon",
    "sg:orig_category":"Unternehmensberatung",
    "sg:phone":"+41 13913022",
    "sg:postcode":"8702",
    "sg:province":"Z\u00fcrich",
    "wof:name":"Mayer Matthias C. Beratung Von Unternehmen Im In Und Ausland.",
    "wof:placetype":"venue"
},
  "geometry": {"coordinates":[8.5737752914,47.3400878906],"type":"Point"}
}