{
  "type": "Feature",
  "properties": {
    "iso:country":"CH",
    "sg:address":"Route Cantonale 144",
    "sg:city":"V\u00e9troz",
    "sg:orig_category":"Grosshandel mit Wein U Spirituosen",
    "sg:phone":"+41 22 343 49 96",
    "sg:postcode":"1963",
    "sg:province":"Valais",
    "wof:name":"Dupasquier Et Cie Sa",
    "wof:placetype":"venue"
},
  "geometry": {"coordinates":[6.1414251328,46.1833114624],"type":"Point"}
}