{
  "type": "Feature",
  "properties": {
    "addr:full":"Lugnorre Lugnorre Fribourg 1789",
    "addr:postcode":"1789",
    "iso:country":"CH",
    "sg:address":"Lugnorre",
    "sg:city":"Lugnorre",
    "sg:orig_category":"Architektur U Ingenieurb\u00fcros",
    "sg:phone":"+41 26 673 36 17",
    "sg:postcode":"1789",
    "sg:province":"Fribourg",
    "wof:name":"Hikol Ag",
    "wof:placetype":"venue"
},
  "geometry": {"coordinates":[7.082371,46.947933],"type":"Point"}
}