{
  "type": "Feature",
  "properties": {
    "iso:country":"CH",
    "sg:address":"Bahnhofstrasse 9 6233 B\u00fcron. Postfach 3",
    "sg:city":"B\u00fcron",
    "sg:orig_category":"Sanit\u00e4r, Heizungs U L\u00fcftungsinstallation Sanit\u00e4rinstallation",
    "sg:phone":"+41 41 933 11 25",
    "sg:postcode":"6233",
    "sg:province":"Luzern",
    "wof:name":"Wyss Daniel",
    "wof:placetype":"venue"
},
  "geometry": {"coordinates":[8.0929460526,47.2126121521],"type":"Point"}
}