{
  "type": "Feature",
  "properties": {
    "iso:country":"CH",
    "sg:address":"Via Circonvallazione 22",
    "sg:city":"Ascona",
    "sg:orig_category":"Arztpraxen",
    "sg:phone":"+41 91 791 61 40",
    "sg:postcode":"6612",
    "sg:province":"Ticino",
    "wof:name":"Dott.med.joseph Stephan Bisig Specialista Fmh",
    "wof:placetype":"venue"
},
  "geometry": {"coordinates":[8.772311,46.152813],"type":"Point"}
}