{
  "type": "Feature",
  "properties": {
    "iso:country":"CH",
    "sg:address":"T\u00f6berstrasse 16",
    "sg:city":"Rheineck",
    "sg:orig_category":"RESTAURANTS: TEA-ROOMS",
    "sg:phone":"+41 71 888 48 98",
    "sg:postcode":"9424",
    "sg:province":"St. Gallen",
    "wof:name":"Rest. Buhof, A. Cavallaro",
    "wof:placetype":"venue"
},
  "geometry": {"coordinates":[9.5755367279,47.4700393677],"type":"Point"}
}