{
  "type": "Feature",
  "properties": {
    "iso:country":"CH",
    "sg:address":"Stadlerstrasse 2",
    "sg:city":"Hochfelden",
    "sg:orig_category":"Nationale Postdienste",
    "sg:phone":"+41 18601405",
    "sg:postcode":"8182",
    "sg:province":"Z\u00fcrich",
    "wof:name":"Die Schweizerische Post",
    "wof:placetype":"venue"
},
  "geometry": {"coordinates":[8.5166959763,47.5234298706],"type":"Point"}
}