{
  "type": "Feature",
  "properties": {
    "iso:country":"CH",
    "sg:address":"Aumattweg 59",
    "sg:city":"Steffisburg",
    "sg:orig_category":"Sonstiger spezialisierter Hoch U Tiefbau",
    "sg:phone":"+41 33 437 72 10",
    "sg:postcode":"3613",
    "sg:province":"Bern",
    "wof:name":"Grimm Dieter",
    "wof:placetype":"venue"
},
  "geometry": {"coordinates":[7.619562149,46.7752838135],"type":"Point"}
}