{
  "type": "Feature",
  "properties": {
    "iso:country":"CH",
    "sg:address":"Neuhofstrasse 20",
    "sg:city":"Lindau",
    "sg:orig_category":"Non-Classified Establishments",
    "sg:postcode":"8315",
    "sg:province":"Z\u00fcrich",
    "wof:name":"U. Widmer Gartenpflege & Gartengestaltung Gmbh",
    "wof:placetype":"venue"
},
  "geometry": {"coordinates":[8.6735458374,47.4409866333],"type":"Point"}
}