{
  "type": "Feature",
  "properties": {
    "iso:country":"CH",
    "sg:address":"Eichmattweg 23",
    "sg:city":"Kaisten",
    "sg:orig_category":"Fahrschulen, Flugschulen",
    "sg:phone":"+41 62 874 15 65",
    "sg:postcode":"5082",
    "sg:province":"Aargau",
    "wof:name":"Franz Schmid Autofahrschule",
    "wof:placetype":"venue"
},
  "geometry": {"coordinates":[8.0412359238,47.5453300476],"type":"Point"}
}