{
  "type": "Feature",
  "properties": {
    "iso:country":"CH",
    "sg:address":"Steinentorstrasse 20",
    "sg:city":"Basel",
    "sg:orig_category":"Unternehmensberatung",
    "sg:postcode":"4010",
    "sg:province":"Basel-Stadt",
    "wof:name":"Vitanova Consulting Ag",
    "wof:placetype":"venue"
},
  "geometry": {"coordinates":[7.5885639191,47.5516853333],"type":"Point"}
}