{
  "type": "Feature",
  "properties": {
    "iso:country":"CH",
    "sg:address":"Schlachthausstrasse 1 2540 Grenchen. Postfach",
    "sg:city":"Grenchen",
    "sg:orig_category":"Detailhandel mit elektrischen Haushalts-,Radio U Fernsehger\u00e4ten sowie Musikinstrumenten",
    "sg:postcode":"2540",
    "sg:province":"Solothurn",
    "wof:name":"Rm Di Malpangotti Roberto",
    "wof:placetype":"venue"
},
  "geometry": {"coordinates":[8.993519783,46.1875801086],"type":"Point"}
}