{
  "type": "Feature",
  "properties": {
    "iso:country":"CH",
    "sg:address":"Kanzleistrasse 1",
    "sg:city":"Berneck",
    "sg:orig_category":"Fahrschulen, Flugschulen",
    "sg:phone":"+41 71 744 17 67",
    "sg:postcode":"9442",
    "sg:province":"St. Gallen",
    "wof:name":"Walter Wolfsberger Autofahrschule",
    "wof:placetype":"venue"
},
  "geometry": {"coordinates":[9.6101112366,47.4250946045],"type":"Point"}
}