{
  "type": "Feature",
  "properties": {
    "iso:country":"CH",
    "sg:address":"Rieterstrasse 7 8406 Winterthur. Postfach",
    "sg:city":"Winterthur",
    "sg:orig_category":"Grosshandel mit Getr\u00e4nken",
    "sg:phone":"+41 52 202 27 62",
    "sg:postcode":"8406",
    "sg:province":"Z\u00fcrich",
    "wof:name":"Schiller F.",
    "wof:placetype":"venue"
},
  "geometry": {"coordinates":[8.7075080872,47.4930152893],"type":"Point"}
}