{
  "type": "Feature",
  "properties": {
    "iso:country":"CH",
    "sg:address":"St. Galler Strasse 17",
    "sg:city":"Arbon",
    "sg:orig_category":"Parf\u00fcmerien U sonstiger Detailhandel mit kosmetischen Artikeln U K\u00f6rperpflegemitteln",
    "sg:phone":"+41 71 440 04 90",
    "sg:postcode":"9320",
    "sg:province":"Thurgau",
    "wof:name":"Impo Import Parf\u00fcmerien Ag",
    "wof:placetype":"venue"
},
  "geometry": {"coordinates":[9.4302091599,47.5114860535],"type":"Point"}
}