{
  "type": "Feature",
  "properties": {
    "iso:country":"CH",
    "sg:address":"Place Des Halles 13",
    "sg:city":"Neuch\u00e2tel",
    "sg:orig_category":"Herstellung von Brot U Backwaren Herstellung von Dauerbackwaren",
    "sg:phone":"+41 32 725 48 25",
    "sg:postcode":"2000",
    "sg:province":"Neuch\u00e2tel",
    "wof:name":"Biscuiterie Neuch\u00e2teloise",
    "wof:placetype":"venue"
},
  "geometry": {"coordinates":[6.9285531044,46.9904060364],"type":"Point"}
}