{
  "type": "Feature",
  "properties": {
    "iso:country":"CH",
    "sg:address":"P\u00e9lisserie Rue De La 22 1204 Gen\u00e8ve. Postfach",
    "sg:city":"Gen\u00e8ve",
    "sg:orig_category":"RESTAURANTS: TEA-ROOMS",
    "sg:postcode":"1204",
    "sg:province":"Gen\u00e8ve",
    "wof:name":"Muccio Nicola & Cie",
    "wof:placetype":"venue"
},
  "geometry": {"coordinates":[6.1456551552,46.2020492554],"type":"Point"}
}