{
  "type": "Feature",
  "properties": {
    "iso:country":"CH",
    "sg:address":"Landstrasse 29",
    "sg:city":"Netstal",
    "sg:orig_category":"Herstellung von k\u00e4lte U lufttechnischen Erzeugnissen f\u00fcr gewerbliche Zwecke",
    "sg:postcode":"8754",
    "sg:province":"Glarus",
    "wof:name":"Gubser R., Montagebau",
    "wof:placetype":"venue"
},
  "geometry": {"coordinates":[9.0537281036,47.0612945557],"type":"Point"}
}