{
  "type": "Feature",
  "properties": {
    "iso:country":"CH",
    "sg:address":"En Levremont 25",
    "sg:city":"Apples",
    "sg:orig_category":"Grosshandel mit B\u00fcromaschinen Grosshandel mit Datenverarbeitungsger\u00e4ten",
    "sg:phone":"+41 21 800 51 30",
    "sg:postcode":"1143",
    "sg:province":"Vaud",
    "wof:name":"Computer Service F.sonnrein",
    "wof:placetype":"venue"
},
  "geometry": {"coordinates":[6.4433121681,46.5579833984],"type":"Point"}
}