{
  "type": "Feature",
  "properties": {
    "iso:country":"CH",
    "sg:address":"1950",
    "sg:city":"Sion",
    "sg:orig_category":"Interessenvertretungen",
    "sg:postcode":"1950",
    "sg:province":"Valais",
    "wof:name":"Fondation De L'eglise Evang\u00e9lique Libre",
    "wof:placetype":"venue"
},
  "geometry": {"coordinates":[6.9093837738,46.9873085022],"type":"Point"}
}