{
  "type": "Feature",
  "properties": {
    "iso:country":"CH",
    "sg:address":"Xxxi-d\u00e9cembre Rue Du 42 1207 Gen\u00e8ve. Postfach",
    "sg:city":"Gen\u00e8ve",
    "sg:orig_category":"Herstellung von Elektromotoren, Generatoren U Transformatoren",
    "sg:postcode":"1207",
    "sg:province":"Gen\u00e8ve",
    "wof:name":"Rtm-plast Sa Produits Et Articles, Notamm. De Mat\u00e9riel Dans Le Domaine \u00e9nerg\u00e9tique; Commerce, Repr\u00e9sentation",
    "wof:placetype":"venue"
},
  "geometry": {"coordinates":[6.1617798805,46.2005882263],"type":"Point"}
}