{
  "type": "Feature",
  "properties": {
    "iso:country":"CH",
    "sg:address":"Rue Marcello 7",
    "sg:city":"Fribourg",
    "sg:classifiers":[
        {
            "category":"Travel",
            "subcategory":"Hotels & Motels",
            "type":"Entertainment"
        }
    ],
    "sg:postcode":"1700",
    "sg:province":"Fribourg",
    "sg:tags":[
        "hotels",
        "mit",
        "restaurant"
    ],
    "wof:name":"Fleuti-gerber Jean",
    "wof:placetype":"venue"
},
  "geometry": {"coordinates":[7.1544771194,46.8081703186],"type":"Point"}
}