{
  "type": "Feature",
  "properties": {
    "iso:country":"CH",
    "sg:address":"Chasa Villa Alpina",
    "sg:city":"Tschierv",
    "sg:classifiers":[
        {
            "category":"Travel",
            "subcategory":"Hotels & Motels",
            "type":"Entertainment"
        }
    ],
    "sg:phone":"+41 81 858 56 07",
    "sg:postcode":"7532",
    "sg:province":"Graubunden",
    "sg:tags":[
        "hotels",
        "mit",
        "restaurant"
    ],
    "wof:name":"Zimmermann Lutz Hans",
    "wof:placetype":"venue"
},
  "geometry": {"coordinates":[10.3364992142,46.6264190674],"type":"Point"}
}