{
  "type": "Feature",
  "properties": {
    "iso:country":"CH",
    "sg:address":"Scheuchzerstrasse 27",
    "sg:city":"Z\u00fcrich",
    "sg:orig_category":"Wohnheime f\u00fcr Kinder U Jugendliche",
    "sg:phone":"+41 13624351",
    "sg:postcode":"8006",
    "sg:province":"Z\u00fcrich",
    "wof:name":"Studentinnenheim Sonnegg",
    "wof:placetype":"venue"
},
  "geometry": {"coordinates":[8.5448236465,47.3843574524],"type":"Point"}
}