{
  "type": "Feature",
  "properties": {
    "iso:country":"CH",
    "sg:address":"Industriestrasse 13",
    "sg:city":"Rotkreuz",
    "sg:orig_category":"Fotografische Ateliers Werbevermittlung",
    "sg:phone":"+41 41 711 97 47",
    "sg:postcode":"6343",
    "sg:province":"Zug",
    "wof:name":"Harry Burst Fotografie & Grafik",
    "wof:placetype":"venue"
},
  "geometry": {"coordinates":[8.4306592941,47.1515541077],"type":"Point"}
}