{
  "type": "Feature",
  "properties": {
    "addr:full":"Jungstrasse 15 8050 Z\u00fcrich Zust 50",
    "addr:housenumber":"15;50",
    "addr:postcode":"8050",
    "addr:street":"Jungstrasse;Zust",
    "iso:country":"CH",
    "sg:address":"Jungstrasse 15 8050 Z\u00fcrich",
    "sg:city":"Zust",
    "sg:orig_category":"Detailhandel mit Bekleidung",
    "sg:phone":"+41 13001474",
    "sg:postcode":"50",
    "wof:name":"Trends, Stucki Christoph",
    "wof:placetype":"venue"
},
  "geometry": {"coordinates":[8.54944,47.413521],"type":"Point"}
}