{
  "type": "Feature",
  "properties": {
    "iso:country":"CH",
    "sg:address":"7608",
    "sg:city":"Castasegna",
    "sg:orig_category":"Primarschulen",
    "sg:phone":"+41 81 822 10 40",
    "sg:postcode":"7608",
    "sg:province":"Graubunden",
    "wof:name":"Scuola Elementare",
    "wof:placetype":"venue"
},
  "geometry": {"coordinates":[9.516998291,46.3341445923],"type":"Point"}
}