{
  "type": "Feature",
  "properties": {
    "iso:country":"CH",
    "sg:address":"Nidaugasse 41",
    "sg:city":"Biel/bienne",
    "sg:orig_category":"Detailhandel mit Uhren U Schmuck Herstellung von Schmuck, Gold U Silberschmiedwaren",
    "sg:phone":"+41 32 323 50 51",
    "sg:postcode":"2502",
    "sg:province":"Bern",
    "wof:name":"Icmen & Cie",
    "wof:placetype":"venue"
},
  "geometry": {"coordinates":[7.2468490601,47.1379966736],"type":"Point"}
}