{
  "type": "Feature",
  "properties": {
    "iso:country":"CH",
    "sg:address":"Route De L'etraz 164",
    "sg:city":"Aubonne",
    "sg:orig_category":"Bauingenieurb\u00fcros allgemein",
    "sg:phone":"+41 21 808 58 66",
    "sg:postcode":"1170",
    "sg:province":"Vaud",
    "wof:name":"L\u00e9onard Gabella Bureau D'ing\u00e9nieur",
    "wof:placetype":"venue"
},
  "geometry": {"coordinates":[6.405173,46.501472],"type":"Point"}
}