{
  "type": "Feature",
  "properties": {
    "iso:country":"CH",
    "sg:address":"Waaghausgasse 1 3000 Bern 7. Postfach",
    "sg:city":"Bern",
    "sg:orig_category":"Verwaltung von Immobilien",
    "sg:postcode":"3005",
    "sg:province":"Bern",
    "wof:name":"Ekz Avry Ag In Bern Einkaufszentrum Usw; Erwerb, Vermietung, Verwaltung",
    "wof:placetype":"venue"
},
  "geometry": {"coordinates":[7.4443302155,46.9482955933],"type":"Point"}
}