{
  "type": "Feature",
  "properties": {
    "iso:country":"CH",
    "sg:address":"Industriestrasse 26",
    "sg:city":"Wittenbach",
    "sg:orig_category":"Instandhaltung U Reparatur von Automobilen",
    "sg:phone":"+41 71 298 11 22",
    "sg:postcode":"9303",
    "wof:name":"Gerster Carrosserie Ag",
    "wof:placetype":"venue"
},
  "geometry": {"coordinates":[9.3926954269,47.4627227783],"type":"Point"}
}