{
  "type": "Feature",
  "properties": {
    "iso:country":"CH",
    "sg:address":"Schw\u00e4ndi",
    "sg:city":"Filzbach",
    "sg:orig_category":"Detailhandel mit Milcherzeugnissen U Eiern Verarbeitung von Milch",
    "sg:phone":"+41 55 614 16 40",
    "sg:postcode":"8757",
    "sg:province":"Glarus",
    "wof:name":"Milchzentrale",
    "wof:placetype":"venue"
},
  "geometry": {"coordinates":[9.1325349808,47.1195755005],"type":"Point"}
}