{
  "type": "Feature",
  "properties": {
    "iso:country":"CH",
    "sg:address":"Rue De Vevey 110",
    "sg:city":"Bulle",
    "sg:orig_category":"Architektur U Ingenieurb\u00fcros",
    "sg:postcode":"1630",
    "sg:province":"Fribourg",
    "wof:name":"Alpha Sa Bulle",
    "wof:placetype":"venue"
},
  "geometry": {"coordinates":[7.05082,46.615208],"type":"Point"}
}