{
  "type": "Feature",
  "properties": {
    "iso:country":"CH",
    "sg:address":"Hauptstrasse",
    "sg:city":"Dreien",
    "sg:orig_category":"Bauschreinerei Zimmerei, Ingenieurholzbau",
    "sg:phone":"+41 71 983 13 52",
    "sg:postcode":"9612",
    "sg:province":"St. Gallen",
    "wof:name":"Josef Fust Holzbau",
    "wof:placetype":"venue"
},
  "geometry": {"coordinates":[9.013435,47.370907],"type":"Point"}
}