{
  "type": "Feature",
  "properties": {
    "iso:country":"CH",
    "sg:address":"Chemin De Praz-lau 3",
    "sg:city":"Cheseaux-lausanne",
    "sg:orig_category":"Schlossereien Stahl U Leichtmetallbau",
    "sg:phone":"+41 26 496 22 19",
    "sg:postcode":"1033",
    "sg:province":"Vaud",
    "wof:name":"J\u00f6rg & Co Metallbau Ag",
    "wof:placetype":"venue"
},
  "geometry": {"coordinates":[7.2485480309,46.8556518555],"type":"Point"}
}