{
  "type": "Feature",
  "properties": {
    "iso:country":"CH",
    "sg:address":"Rebrainstrasse 23 8632 Tann. Postfach 12",
    "sg:city":"Tann",
    "sg:orig_category":"Vereine Gesang",
    "sg:phone":"+41 55 240 32 30",
    "sg:postcode":"8632",
    "sg:province":"Z\u00fcrich",
    "wof:name":"M\u00e4nnerchor Oberd\u00fcrnten",
    "wof:placetype":"venue"
},
  "geometry": {"coordinates":[8.8483972549,47.2684593201],"type":"Point"}
}