{
  "type": "Feature",
  "properties": {
    "iso:country":"CH",
    "sg:address":"Poststrasse 9",
    "sg:city":"St.gallen",
    "sg:orig_category":"Bau U Wohngenossenschaften",
    "sg:phone":"+41 71 222 34 33",
    "sg:postcode":"9000",
    "sg:province":"St. Gallen",
    "wof:name":"Wohnbaugen.lerchenfeld",
    "wof:placetype":"venue"
},
  "geometry": {"coordinates":[9.373483,47.424759],"type":"Point"}
}