{
  "type": "Feature",
  "properties": {
    "iso:country":"CH",
    "sg:address":"Chemin Frank-thomas 34 1200 Genf Case Postale 416",
    "sg:city":"Gen\u00e8ve",
    "sg:orig_category":"Unclassifiable Establishments",
    "sg:phone":"+41 79 224 23 00",
    "sg:postcode":"1206",
    "sg:province":"Gen\u00e8ve",
    "wof:name":"Madvideo, Denis Maurer Vid\u00e9aste Ind\u00e9pendant",
    "wof:placetype":"venue"
},
  "geometry": {"coordinates":[6.8571648598,46.9701118469],"type":"Point"}
}