{
  "type": "Feature",
  "properties": {
    "iso:country":"CH",
    "sg:address":"Thurtalstrasse 235",
    "sg:city":"Thalheim",
    "sg:orig_category":"Sportvereine Turnen Vereine Damen",
    "sg:phone":"+41 52 336 12 16",
    "sg:postcode":"8478",
    "sg:province":"Z\u00fcrich",
    "wof:name":"Damenriege Thalheim Der Zkb",
    "wof:placetype":"venue"
},
  "geometry": {"coordinates":[8.7467899323,47.581325531],"type":"Point"}
}