{
  "type": "Feature",
  "properties": {
    "iso:country":"CH",
    "sg:address":"Alte Post",
    "sg:city":"Pfaffnau",
    "sg:orig_category":"Grosshandel mit Holz U Bauelementen aus Holz Grosshandel mit Holz U Baustoffen",
    "sg:phone":"+41 62 754 14 88",
    "sg:postcode":"6264",
    "sg:province":"Luzern",
    "wof:name":"Vonesch Stephan",
    "wof:placetype":"venue"
},
  "geometry": {"coordinates":[7.8960399628,47.227016449],"type":"Point"}
}