{
  "type": "Feature",
  "properties": {
    "iso:country":"CH",
    "sg:address":"Brisgistrasse 2 5400 Baden. Postfach",
    "sg:city":"Baden",
    "sg:orig_category":"Vermietung U Verpachtung von eigenen Immobilien",
    "sg:postcode":"5400",
    "sg:province":"Aargau",
    "wof:name":"Baumann Immobilien Ag, Baden",
    "wof:placetype":"venue"
},
  "geometry": {"coordinates":[8.2857542038,47.4840583801],"type":"Point"}
}