{
  "type": "Feature",
  "properties": {
    "iso:country":"CH",
    "sg:address":"Gartenstrasse 19 8002 Z\u00fcrich. Postfach",
    "sg:city":"Z\u00fcrich",
    "sg:orig_category":"Reiseb\u00fcros U Reiseveranstalter",
    "sg:postcode":"8001",
    "sg:province":"Z\u00fcrich",
    "wof:name":"Schmid Osterinsel Reisen Reisen; Organisation, Verkauf. Tourismusf\u00f6rderung Auf Osterinseln",
    "wof:placetype":"venue"
},
  "geometry": {"coordinates":[8.5334501266,47.3681793213],"type":"Point"}
}