{
  "type": "Feature",
  "properties": {
    "addr:full":"Monbijoustrasse 33 3011 Bern. Postfach 6336 Bern Bern 3001",
    "addr:housenumber":"33",
    "addr:postcode":"3011;postfach 6336 bern;3001",
    "addr:street":"Monbijoustrasse",
    "iso:country":"CH",
    "sg:address":"Monbijoustrasse 33 3011 Bern. Postfach 6336",
    "sg:city":"Bern",
    "sg:orig_category":"Arbeitnehmerverb\u00e4nde",
    "sg:phone":"+41 22 748 20 80",
    "sg:postcode":"3001",
    "sg:province":"Bern",
    "wof:name":"Conf\u00e9d\u00e9ration Mondiale Du Travail",
    "wof:placetype":"venue"
},
  "geometry": {"coordinates":[6.139525,46.221081],"type":"Point"}
}