{
  "type": "Feature",
  "properties": {
    "iso:country":"CH",
    "sg:address":"Via Boscioredo 9a",
    "sg:city":"Ascona",
    "sg:orig_category":"Verwaltung von Immobilien",
    "sg:postcode":"6612",
    "sg:province":"Ticino",
    "wof:name":"Soldica S\u00e0rl",
    "wof:placetype":"venue"
},
  "geometry": {"coordinates":[5.1808700562,45.8973388672],"type":"Point"}
}