{
  "type": "Feature",
  "properties": {
    "iso:country":"CH",
    "sg:address":"Orpundstrasse 78",
    "sg:city":"Biel/bienne",
    "sg:orig_category":"Interessenvertretungen U sonstige Vereinigungen",
    "sg:phone":"+41 32 342 22 43",
    "sg:postcode":"2504",
    "sg:province":"Bern",
    "wof:name":"Seel\u00e4nd.kunstturnervereinig.",
    "wof:placetype":"venue"
},
  "geometry": {"coordinates":[7.2806301117,47.1423492432],"type":"Point"}
}