{
  "type": "Feature",
  "properties": {
    "iso:country":"CH",
    "sg:address":"Talackerstrasse 11",
    "sg:city":"Glattbrugg",
    "sg:orig_category":"Handelsvermittlung von Textilien, Bekleidung, Schuhen U Lederwaren",
    "sg:postcode":"8152",
    "sg:province":"Z\u00fcrich",
    "wof:name":"Maildex Versand Ag",
    "wof:placetype":"venue"
},
  "geometry": {"coordinates":[9.2549495697,47.4144134521],"type":"Point"}
}