{
  "type": "Feature",
  "properties": {
    "iso:country":"CH",
    "sg:address":"Bahnhofstrasse 13",
    "sg:city":"Emmen",
    "sg:classifiers":[
        {
            "category":"Banks & Credit Unions",
            "subcategory":"Bank",
            "type":"Services"
        }
    ],
    "sg:phone":"+41 4141555533",
    "sg:postcode":"6020",
    "sg:province":"Luzern",
    "wof:name":"Landw. Kreditkasse, Des Kts. Luzern",
    "wof:placetype":"venue"
},
  "geometry": {"coordinates":[8.281296,47.071033],"type":"Point"}
}