{
  "type": "Feature",
  "properties": {
    "iso:country":"CH",
    "sg:address":"M\u00fchlegasse 8 8302 Kloten. Postfach",
    "sg:city":"Kloten",
    "sg:orig_category":"Sonstiger Grosshandel",
    "sg:postcode":"8302",
    "sg:province":"Z\u00fcrich",
    "wof:name":"I E M Marinkovic R Geschenk, Werbeartikel, Waren; Im, Export",
    "wof:placetype":"venue"
},
  "geometry": {"coordinates":[8.5894603729,47.4508552551],"type":"Point"}
}