{
  "type": "Feature",
  "properties": {
    "addr:full":"Avenue Du Ch\u00e2teau 8 Prilly Vaud 1008",
    "addr:housenumber":"8",
    "addr:postcode":"1008",
    "addr:street":"Avenue Du Cha\u0302Teau",
    "iso:country":"CH",
    "sg:address":"Avenue Du Ch\u00e2teau 8",
    "sg:city":"Prilly",
    "sg:orig_category":"Allgemeiner Hoch U Tiefbau",
    "sg:phone":"+41 21 624 74 65",
    "sg:postcode":"1008",
    "sg:province":"Vaud",
    "wof:name":"Entreprise De Services Et De Travaux Publics, Liselotte Kouninef",
    "wof:placetype":"venue"
},
  "geometry": {"coordinates":[6.604916,46.535484],"type":"Point"}
}