{
  "type": "Feature",
  "properties": {
    "iso:country":"CH",
    "sg:address":"Parkterrasse 16",
    "sg:city":"Bern",
    "sg:orig_category":"Lichtpause U Reprografiebetriebe Offsetdruck",
    "sg:phone":"+41 21 637 30 50",
    "sg:postcode":"3012",
    "sg:province":"Bern",
    "wof:name":"Pierre-alain Mouttet Copyquick",
    "wof:placetype":"venue"
},
  "geometry": {"coordinates":[6.5804958344,46.5382461548],"type":"Point"}
}