{
  "type": "Feature",
  "properties": {
    "iso:country":"CH",
    "sg:address":"Chemin De Pr\u00e9-marin 28",
    "sg:city":"Mont-sur-lausanne",
    "sg:orig_category":"Erwachsenenbildung U Unterricht",
    "sg:phone":"+41 21 653 99 47",
    "sg:postcode":"1052",
    "sg:province":"Vaud",
    "wof:name":"Declic Sa",
    "wof:placetype":"venue"
},
  "geometry": {"coordinates":[6.6308131218,46.5527420044],"type":"Point"}
}