{
  "type": "Feature",
  "properties": {
    "iso:country":"CH",
    "sg:city":"Engwang",
    "sg:orig_category":"Shopping U Fachgesch\u00e4fte, Bekleidung",
    "sg:phone":"+41 71 657 20 63",
    "sg:postcode":"8556",
    "sg:province":"Thurgau",
    "wof:name":"Topmedia",
    "wof:placetype":"venue"
},
  "geometry": {"coordinates":[9.050276,47.599289],"type":"Point"}
}