{
  "type": "Feature",
  "properties": {
    "iso:country":"CH",
    "sg:address":"Ernst-sch\u00fcler-strasse 62 2500 Biel/bienne. Postfach",
    "sg:city":"Biel/bienne",
    "sg:orig_category":"Sonstiger spezialisierter Hoch U Tiefbau",
    "sg:postcode":"2502",
    "sg:province":"Bern",
    "wof:name":"Henkel Bruno, Nachfolger B\u00e4der & Zotti",
    "wof:placetype":"venue"
},
  "geometry": {"coordinates":[7.2517719269,47.1409339905],"type":"Point"}
}