{
  "type": "Feature",
  "properties": {
    "iso:country":"CH",
    "sg:address":"Zelgstrasse 9",
    "sg:city":"Uster",
    "sg:orig_category":"Vereine Geselligkeit",
    "sg:phone":"+41 71 477 12 41",
    "sg:postcode":"8610",
    "sg:province":"Z\u00fcrich",
    "wof:name":"Appenzeller-verein Arbon",
    "wof:placetype":"venue"
},
  "geometry": {"coordinates":[9.3692731857,47.5288887024],"type":"Point"}
}