{
  "type": "Feature",
  "properties": {
    "iso:country":"CH",
    "sg:address":"Grafenauweg 7",
    "sg:city":"Zug",
    "sg:orig_category":"Sonstige pers\u00f6nliche Dienstleistungen Sonstiger Grosshandel",
    "sg:phone":"+41 41 711 44 55",
    "sg:postcode":"6300",
    "sg:province":"Zug",
    "wof:name":"Etc Services Gmbh",
    "wof:placetype":"venue"
},
  "geometry": {"coordinates":[8.5125427246,47.1739501953],"type":"Point"}
}