{
  "type": "Feature",
  "properties": {
    "iso:country":"CH",
    "sg:address":"Gr\u00fcntalstrasse 28",
    "sg:city":"Arbon",
    "sg:orig_category":"Zimmerei, Dachdeckerei, Bauspenglerei U Abdichtung",
    "sg:phone":"+41 71 446 90 20",
    "sg:postcode":"9320",
    "sg:province":"Thurgau",
    "wof:name":"Ndb-dach - Fassaden Und Fensterbau Gmbh",
    "wof:placetype":"venue"
},
  "geometry": {"coordinates":[9.4154872894,47.506565094],"type":"Point"}
}