{
  "type": "Feature",
  "properties": {
    "iso:country":"CH",
    "sg:address":"P\u00e2ques Rue Des 12",
    "sg:city":"Geneveys-coffrane",
    "sg:orig_category":"Forstwirtschaft ohne Dienstleistungen in der Forstwirtschaft",
    "sg:phone":"+41 79 240 55 32",
    "sg:postcode":"2206",
    "sg:province":"Neuch\u00e2tel",
    "wof:name":"Oppliger Fr\u00e8res",
    "wof:placetype":"venue"
},
  "geometry": {"coordinates":[6.8518447876,47.0164413452],"type":"Point"}
}