{
  "type": "Feature",
  "properties": {
    "addr:full":"Hebelstrasse 75 Basel Basel-Stadt 4056",
    "addr:housenumber":"75",
    "addr:postcode":"4056",
    "addr:street":"Hebelstrasse",
    "iso:country":"CH",
    "sg:address":"Hebelstrasse 75",
    "sg:city":"Basel",
    "sg:orig_category":"Bau U Wohngenossenschaften",
    "sg:postcode":"4056",
    "sg:province":"Basel-Stadt",
    "wof:name":"Wohnbaugen.der Stadtmusik Bs C/o O.h\u00e4ring Immobilien",
    "wof:placetype":"venue"
},
  "geometry": {"coordinates":[7.578755,47.562054],"type":"Point"}
}