{
  "type": "Feature",
  "properties": {
    "iso:country":"CH",
    "sg:address":"Kehrsitenstrasse 23",
    "sg:city":"Stansstad",
    "sg:orig_category":"Unclassifiable Establishments",
    "sg:postcode":"6362",
    "sg:province":"Nidwalden",
    "wof:name":"Thommen F. Holding Ag",
    "wof:placetype":"venue"
},
  "geometry": {"coordinates":[8.3416986465,46.9808349609],"type":"Point"}
}