{
  "type": "Feature",
  "properties": {
    "iso:country":"CH",
    "sg:address":"Rue Du 23-juin 2",
    "sg:city":"Courrendlin",
    "sg:orig_category":"Erbringung von sonstigen Dienstleistungen f\u00fcr Unterhaltung, Erholung U Freizeit",
    "sg:phone":"+41 66336977",
    "sg:postcode":"2830",
    "sg:province":"Jura",
    "wof:name":"Arti Services Grillon Bertrand",
    "wof:placetype":"venue"
},
  "geometry": {"coordinates":[7.3725252151,47.3403053284],"type":"Point"}
}