{
  "type": "Feature",
  "properties": {
    "addr:full":"Gurtengasse 6 3011 Bern. Postfach Bern Bern 3001",
    "addr:housenumber":"6",
    "addr:postcode":"3011;postfach;3001",
    "addr:street":"Gurtengasse",
    "iso:country":"CH",
    "sg:address":"Gurtengasse 6 3011 Bern. Postfach",
    "sg:city":"Bern",
    "sg:orig_category":"Arbeitnehmerverb\u00e4nde",
    "sg:phone":"+41 31 311 31 81",
    "sg:postcode":"3001",
    "sg:province":"Bern",
    "wof:name":"Schweiz.verband Milchwirt- Schaftlicher Betriebsleiter",
    "wof:placetype":"venue"
},
  "geometry": {"coordinates":[7.441645,46.946754],"type":"Point"}
}