{
  "type": "Feature",
  "properties": {
    "iso:country":"CH",
    "sg:address":"Bahnhofstrasse 48",
    "sg:city":"Muttenz",
    "sg:orig_category":"Grosshandel mit Software Softwareentwicklung U beratung",
    "sg:phone":"+41 55 214 13 71",
    "sg:postcode":"4132",
    "sg:province":"Basel-Landschaft",
    "wof:name":"Beltrame Informatik Gmbh",
    "wof:placetype":"venue"
},
  "geometry": {"coordinates":[8.822473526,47.2313041687],"type":"Point"}
}