{
  "type": "Feature",
  "properties": {
    "addr:full":"Seuzachstrasse 28 8413 Neftenbach. Postfach 122 Neftenbach Z\u00fcrich 8413",
    "addr:housenumber":"28;122",
    "addr:postcode":"8413;8413",
    "addr:street":"Seuzachstrasse;Postfach",
    "iso:country":"CH",
    "sg:address":"Seuzachstrasse 28 8413 Neftenbach. Postfach 122",
    "sg:city":"Neftenbach",
    "sg:orig_category":"Chemische Industrie Herstellung von Seifen, Wasch U Reinigungsmitteln",
    "sg:phone":"+41 52 315 19 78",
    "sg:postcode":"8413",
    "sg:province":"Z\u00fcrich",
    "wof:name":"Tavernaro Ag Reinigungsmaschinen, Reinigungsger\u00e4te Und Reinigungsprodukte",
    "wof:placetype":"venue"
},
  "geometry": {"coordinates":[8.674004,47.531227],"type":"Point"}
}