{
  "type": "Feature",
  "properties": {
    "iso:country":"CH",
    "sg:address":"Rue Abb\u00e9-g.-joliat 2",
    "sg:city":"Court\u00e9telle",
    "sg:orig_category":"Herstellung von Uhren",
    "sg:phone":"+41 32 422 18 24",
    "sg:postcode":"2852",
    "sg:province":"Jura",
    "wof:name":"Joliat Sa.",
    "wof:placetype":"venue"
},
  "geometry": {"coordinates":[7.3182291985,47.3396034241],"type":"Point"}
}