{
  "type": "Feature",
  "properties": {
    "iso:country":"CH",
    "sg:address":"Belpbergstrasse 46c",
    "sg:city":"M\u00fcnsingen",
    "sg:orig_category":"Wirtschaftspr\u00fcfung, Steuerberatung U Treuhand",
    "sg:phone":"+41 31 721 30 12",
    "sg:postcode":"3110",
    "sg:province":"Bern",
    "wof:name":"Sch\u00e4deli Treuhand Ag M\u00fcnsingen",
    "wof:placetype":"venue"
},
  "geometry": {"coordinates":[7.5509300232,46.8678703308],"type":"Point"}
}