{
  "type": "Feature",
  "properties": {
    "iso:country":"CH",
    "sg:address":"Ch. Du Nant-d'aisy 31",
    "sg:city":"Ani\u00e8res",
    "sg:orig_category":"Herstellung von optischen U fotografischen Ger\u00e4ten",
    "sg:phone":"+41 79 219 05 25",
    "sg:postcode":"1247",
    "sg:province":"Gen\u00e8ve",
    "wof:name":"Multilasers, Neracher A.",
    "wof:placetype":"venue"
},
  "geometry": {"coordinates":[6.2244901657,46.2759819031],"type":"Point"}
}