{
  "type": "Feature",
  "properties": {
    "iso:country":"CH",
    "sg:address":"Marktgasse 19",
    "sg:city":"Bern",
    "sg:orig_category":"Fachdetailhandel in Verkaufsr\u00e4umen",
    "sg:postcode":"3011",
    "sg:province":"Bern",
    "wof:name":"Blackmoon Designs Gmbh",
    "wof:placetype":"venue"
},
  "geometry": {"coordinates":[7.4464249611,46.9477882385],"type":"Point"}
}