{
  "type": "Feature",
  "properties": {
    "iso:country":"CH",
    "sg:address":"Stationsstrasse 66a",
    "sg:city":"Wettswil",
    "sg:orig_category":"Sportvereine Ski",
    "sg:phone":"+41 635154",
    "sg:postcode":"8907",
    "sg:province":"Z\u00fcrich",
    "wof:name":"Skiclub Z\u00fcrich Oberland",
    "wof:placetype":"venue"
},
  "geometry": {"coordinates":[8.809969902,47.3327064514],"type":"Point"}
}