{
  "type": "Feature",
  "properties": {
    "iso:country":"CH",
    "sg:address":"Kirchgasse 5 4416 Bubendorf. Postfach",
    "sg:city":"Bubendorf",
    "sg:orig_category":"Sanit\u00e4r, Heizungs U L\u00fcftungsinstallation",
    "sg:postcode":"4416",
    "sg:province":"Basel-Landschaft",
    "wof:name":"Kurt Meyer",
    "wof:placetype":"venue"
},
  "geometry": {"coordinates":[7.7354898453,47.4489936829],"type":"Point"}
}