{
  "type": "Feature",
  "properties": {
    "iso:country":"CH",
    "sg:address":"Rue De La Chapelle 11",
    "sg:city":"Ponts-de-martel",
    "sg:orig_category":"Vereine Abstinenten",
    "sg:phone":"+41 32 937 16 77",
    "sg:postcode":"2316",
    "sg:province":"Neuch\u00e2tel",
    "wof:name":"Croix-bleue Neuch\u00e2teloise",
    "wof:placetype":"venue"
},
  "geometry": {"coordinates":[6.7335882187,47.0004997253],"type":"Point"}
}