{
  "type": "Feature",
  "properties": {
    "iso:country":"CH",
    "sg:address":"1937",
    "sg:city":"Orsi\u00e8res",
    "sg:orig_category":"Allgemeiner Hoch U Tiefbau",
    "sg:phone":"+41 27 783 14 67",
    "sg:postcode":"1937",
    "sg:province":"Valais",
    "wof:name":"Lovey Ulysse",
    "wof:placetype":"venue"
},
  "geometry": {"coordinates":[7.14629,46.030697],"type":"Point"}
}