{
  "type": "Feature",
  "properties": {
    "iso:country":"CH",
    "sg:address":"Via Bossi 6",
    "sg:city":"Lugano",
    "sg:classifiers":[
        {
            "category":"Banks & Credit Unions",
            "subcategory":"Bank",
            "type":"Services"
        }
    ],
    "sg:phone":"+41 91 870 13 49",
    "sg:postcode":"6900",
    "sg:province":"Ticino",
    "wof:name":"Banca Raiffeisen Media E Bassa Blenio",
    "wof:placetype":"venue"
},
  "geometry": {"coordinates":[8.981,46.411419],"type":"Point"}
}