{
  "type": "Feature",
  "properties": {
    "iso:country":"CH",
    "sg:address":"Grabenstrasse 57 8500 Frauenfeld. Postfach",
    "sg:city":"Frauenfeld",
    "sg:orig_category":"RESTAURANTS: TEA-ROOMS",
    "sg:phone":"+41 52 722 13 19",
    "sg:postcode":"8500",
    "sg:province":"Thurgau",
    "wof:name":"Ck-gastro Gmbh Gastronomiebetrieb",
    "wof:placetype":"venue"
},
  "geometry": {"coordinates":[8.8995800018,47.5583992004],"type":"Point"}
}