{
  "type": "Feature",
  "properties": {
    "iso:country":"CH",
    "sg:address":"Tilleuls Rue Des 1",
    "sg:city":"Geneveys-coffrane",
    "sg:orig_category":"Handel mit Automobilteilen U Zubeh\u00f6r",
    "sg:phone":"+41 79 206 61 22",
    "sg:postcode":"2206",
    "sg:province":"Neuch\u00e2tel",
    "wof:name":"M\u00e9capi\u00e8ces Jean-marie Stubi",
    "wof:placetype":"venue"
},
  "geometry": {"coordinates":[6.8518447876,47.0164413452],"type":"Point"}
}