{
  "type": "Feature",
  "properties": {
    "iso:country":"CH",
    "sg:address":"Via Al Gaggio 27",
    "sg:city":"Pazzallo",
    "sg:orig_category":"Non-Classified Establishments",
    "sg:postcode":"6912",
    "sg:province":"Ticino",
    "wof:name":"Cantoni Meccanica Sagl",
    "wof:placetype":"venue"
},
  "geometry": {"coordinates":[8.9400396347,45.9830589294],"type":"Point"}
}