{
  "type": "Feature",
  "properties": {
    "iso:country":"CH",
    "sg:address":"Promenadenstrasse 21 8200 Schaffhausen. Postfach 1118",
    "sg:city":"Schaffhausen",
    "sg:orig_category":"Fotografische Ateliers",
    "sg:phone":"+41 52 624 60 66",
    "sg:postcode":"8201",
    "sg:province":"Schaffhausen",
    "wof:name":"Pb & R Marketing & Werbeberatung",
    "wof:placetype":"venue"
},
  "geometry": {"coordinates":[8.6284179688,47.694934845],"type":"Point"}
}