{
  "type": "Feature",
  "properties": {
    "iso:country":"CH",
    "sg:address":"1580",
    "sg:city":"Avenches",
    "sg:orig_category":"Bezirks, Sekundar, Realschulen, Oberstufe der Primarschulen",
    "sg:postcode":"1580",
    "sg:province":"Vaud",
    "wof:name":"Ecole Secondaire Coll\u00e8ge Sous-ville",
    "wof:placetype":"venue"
},
  "geometry": {"coordinates":[7.040785,46.880058],"type":"Point"}
}