{
  "type": "Feature",
  "properties": {
    "iso:country":"CH",
    "sg:address":"Sonnhaldenstrasse 12",
    "sg:city":"Menznau",
    "sg:orig_category":"Detailhandel mit Boden U Wandbel\u00e4gen ohne Teppiche Detailhandel mit Teppichen",
    "sg:phone":"+41 79 335 27 54",
    "sg:postcode":"6122",
    "sg:province":"Luzern",
    "wof:name":"Christof Rohrer Bodenbel\u00e4ge",
    "wof:placetype":"venue"
},
  "geometry": {"coordinates":[8.042977,47.083912],"type":"Point"}
}