{
  "type": "Feature",
  "properties": {
    "iso:country":"CH",
    "sg:address":"Via Carlo Frasca 4",
    "sg:city":"Lugano",
    "sg:orig_category":"W\u00e4scherei U chemische Reinigung",
    "sg:phone":"+41 91 923 33 53",
    "sg:postcode":"6900",
    "sg:province":"Ticino",
    "wof:name":"Riedi Giacomo Sa Per L'esercizio Dei Negozi Silca",
    "wof:placetype":"venue"
},
  "geometry": {"coordinates":[8.9553508759,46.0064048767],"type":"Point"}
}