{
  "type": "Feature",
  "properties": {
    "iso:country":"CH",
    "sg:address":"Gerbstrasse 3",
    "sg:city":"W\u00e4denswil",
    "sg:orig_category":"Sonstige Aktivit\u00e4ten der nicht-\u00e4rztlichen Medizinalberufe",
    "sg:phone":"+41 17802644",
    "sg:postcode":"8820",
    "sg:province":"Z\u00fcrich",
    "wof:name":"Maria Gisler Atemtherapie",
    "wof:placetype":"venue"
},
  "geometry": {"coordinates":[8.6728792191,47.229259491],"type":"Point"}
}