{
  "type": "Feature",
  "properties": {
    "iso:country":"CH",
    "sg:address":"Chemin De La Bruy\u00e8re 2",
    "sg:city":"Pully",
    "sg:orig_category":"Sportvereine Ballsport Basketball",
    "sg:postcode":"1009",
    "sg:province":"Vaud",
    "wof:name":"Union Armenienne Sportive",
    "wof:placetype":"venue"
},
  "geometry": {"coordinates":[6.662170887,46.5219535828],"type":"Point"}
}