{
  "type": "Feature",
  "properties": {
    "iso:country":"CH",
    "sg:address":"1428",
    "sg:city":"Provence",
    "sg:orig_category":"Instandhaltung U Reparatur von Automobilen",
    "sg:phone":"+41 24 434 18 16",
    "sg:postcode":"1428",
    "sg:province":"Vaud",
    "wof:name":"Lombardot Pierre.",
    "wof:placetype":"venue"
},
  "geometry": {"coordinates":[6.7277708054,46.8915061951],"type":"Point"}
}