{
  "type": "Feature",
  "properties": {
    "iso:country":"CH",
    "sg:address":"Campagna Via 10 6900 Lugano. Postfach",
    "sg:city":"Lugano",
    "sg:orig_category":"Non-Classified Establishments",
    "sg:postcode":"6900",
    "sg:province":"Ticino",
    "wof:name":"Agrisystems Finance Sa",
    "wof:placetype":"venue"
},
  "geometry": {"coordinates":[6.9919700623,46.8852348328],"type":"Point"}
}