{
  "type": "Feature",
  "properties": {
    "iso:country":"CH",
    "sg:address":"Luzernstrasse 41 6280 Hochdorf. Postfach",
    "sg:city":"Hochdorf",
    "sg:orig_category":"Unclassifiable Establishments",
    "sg:postcode":"6280",
    "sg:province":"Luzern",
    "wof:name":"Arnold Franz Gmbh",
    "wof:placetype":"venue"
},
  "geometry": {"coordinates":[8.3025979996,47.1637382507],"type":"Point"}
}