{
  "type": "Feature",
  "properties": {
    "iso:country":"CH",
    "sg:address":"Rue Des Lacs 12",
    "sg:city":"Sierre",
    "sg:classifiers":[
        {
            "category":"Restaurant",
            "type":"Food & Drink"
        }
    ],
    "sg:phone":"+41 27 455 13 98",
    "sg:postcode":"3960",
    "sg:province":"Valais",
    "wof:name":"Steakhouse Pizzeria Des Amis",
    "wof:placetype":"venue"
},
  "geometry": {"coordinates":[7.5373659134,46.2930831909],"type":"Point"}
}