{
  "type": "Feature",
  "properties": {
    "iso:country":"CH",
    "sg:address":"Chemin Des Fraisiers 7",
    "sg:city":"Grand-lancy",
    "sg:orig_category":"Physiotherapie",
    "sg:phone":"+41 22 794 86 16",
    "sg:postcode":"1212",
    "sg:province":"Gen\u00e8ve",
    "wof:name":"Jean-luc Pellet Physioth\u00e9rapie",
    "wof:placetype":"venue"
},
  "geometry": {"coordinates":[6.1148691177,46.1754798889],"type":"Point"}
}