{
  "type": "Feature",
  "properties": {
    "iso:country":"CH",
    "sg:address":"Rebackerstrasse 5",
    "sg:city":"Kerzers",
    "sg:orig_category":"G\u00fcterbef\u00f6rderung im Strassenverkehr",
    "sg:phone":"+41 31 755 74 02",
    "sg:postcode":"3210",
    "sg:province":"Fribourg",
    "wof:name":"Dufr\u00e8not H. Transporte",
    "wof:placetype":"venue"
},
  "geometry": {"coordinates":[7.2148442268,46.9747085571],"type":"Point"}
}