{
  "type": "Feature",
  "properties": {
    "iso:country":"CH",
    "sg:address":"Hauptstrasse 96",
    "sg:city":"Nidau",
    "sg:orig_category":"Grosshandel mit Holz U Baustoffen",
    "sg:phone":"+41 62 771 38 19",
    "sg:postcode":"2560",
    "sg:province":"Bern",
    "wof:name":"Gautschi & Merz Ag",
    "wof:placetype":"venue"
},
  "geometry": {"coordinates":[8.2094697952,47.2582511902],"type":"Point"}
}