{
  "type": "Feature",
  "properties": {
    "iso:country":"CH",
    "sg:address":"Avenue De La Praille 55",
    "sg:city":"Carouge",
    "sg:classifiers":[
        {
            "category":"Park",
            "subcategory":"Provincial",
            "type":"Public Place"
        }
    ],
    "sg:phone":"+41 22 343 75 60",
    "sg:postcode":"1227",
    "sg:province":"Gen\u00e8ve",
    "sg:tags":[
        "birthday",
        "card"
    ],
    "wof:name":"Imprimerie Steiner S.a.",
    "wof:placetype":"venue"
},
  "geometry": {"coordinates":[6.129614,46.186745],"type":"Point"}
}