{
  "type": "Feature",
  "properties": {
    "iso:country":"CH",
    "sg:address":"Z\u00fcrichstrasse 23c",
    "sg:city":"Biel/bienne",
    "sg:orig_category":"Installation von Heizungs, L\u00fcftungs U Klimaanlagen Sanit\u00e4r U Heizungsinstallation",
    "sg:phone":"+41 32 384 89 85",
    "sg:postcode":"2504",
    "sg:province":"Bern",
    "wof:name":"Wagner Installations Ag",
    "wof:placetype":"venue"
},
  "geometry": {"coordinates":[7.291864872,47.16173172],"type":"Point"}
}