{
  "type": "Feature",
  "properties": {
    "iso:country":"CH",
    "sg:address":"Niederdorfstrasse 5",
    "sg:city":"Z\u00fcrich",
    "sg:classifiers":[
        {
            "category":"Restaurant",
            "type":"Food & Drink"
        }
    ],
    "sg:phone":"+41 12519400",
    "sg:postcode":"8001",
    "sg:province":"Z\u00fcrich",
    "wof:name":"Restaurant Spaghetti Factory",
    "wof:placetype":"venue"
},
  "geometry": {"coordinates":[8.5436897278,47.3728904724],"type":"Point"}
}