{
  "type": "Feature",
  "properties": {
    "iso:country":"CH",
    "sg:address":"Untere Br\u00fchlstrasse 4",
    "sg:city":"Zofingen",
    "sg:orig_category":"Unclassifiable Establishments",
    "sg:postcode":"4800",
    "sg:province":"Aargau",
    "wof:name":"Siegfried Dienste Ag",
    "wof:placetype":"venue"
},
  "geometry": {"coordinates":[7.9391918182,47.2885551453],"type":"Point"}
}