{
  "type": "Feature",
  "properties": {
    "iso:country":"CH",
    "sg:address":"Seeackerstrasse 3",
    "sg:city":"Horn",
    "sg:orig_category":"Grosshandel mit Eisenwaren sowie Installationsbedarf f\u00fcr Gas, Wasser U Heizung Grosshandel mit chemi",
    "sg:phone":"+41 71 841 82 87",
    "sg:postcode":"9326",
    "sg:province":"Thurgau",
    "wof:name":"Powertec Gmbh",
    "wof:placetype":"venue"
},
  "geometry": {"coordinates":[9.458776474,47.4965858459],"type":"Point"}
}