{
  "type": "Feature",
  "properties": {
    "iso:country":"CH",
    "sg:address":"R\u00fcmlangerstrasse 9 8105 Watt. Postfach 1094",
    "sg:city":"Watt",
    "sg:orig_category":"Personal U Stellenvermittlung Unternehmensberatung",
    "sg:phone":"+41 18702244",
    "sg:postcode":"8105",
    "sg:province":"Z\u00fcrich",
    "wof:name":"Oprandi & Partner Ag Personal-& Unternehmensber.",
    "wof:placetype":"venue"
},
  "geometry": {"coordinates":[8.4821243286,47.4428863525],"type":"Point"}
}