{
  "type": "Feature",
  "properties": {
    "addr:full":"R\u00e4mistrasse 38 Z\u00fcrich Z\u00fcrich 8001",
    "addr:housenumber":"38",
    "addr:postcode":"8001",
    "addr:street":"Raemistrasse",
    "iso:country":"CH",
    "sg:address":"R\u00e4mistrasse 38",
    "sg:city":"Z\u00fcrich",
    "sg:orig_category":"Arztpraxen",
    "sg:phone":"+41 12510124",
    "sg:postcode":"8001",
    "sg:province":"Z\u00fcrich",
    "wof:name":"Dr.med.ivan Vesel Spezialarzt Fmh",
    "wof:placetype":"venue"
},
  "geometry": {"coordinates":[8.549571,47.370605],"type":"Point"}
}