{
  "type": "Feature",
  "properties": {
    "iso:country":"CH",
    "sg:address":"Lindenstrasse 30",
    "sg:city":"Ettiswil",
    "sg:orig_category":"Sportvereine Ballsport Badminton",
    "sg:phone":"+41 41 980 44 39",
    "sg:postcode":"6218",
    "sg:province":"Luzern",
    "wof:name":"Badminton-club Sursee",
    "wof:placetype":"venue"
},
  "geometry": {"coordinates":[8.0131826401,47.1467094421],"type":"Point"}
}