{
  "type": "Feature",
  "properties": {
    "iso:country":"CH",
    "sg:address":"Lerchenweg 5",
    "sg:city":"Steffisburg",
    "sg:orig_category":"Architektur U Ingenieurb\u00fcros Architekturb\u00fcros",
    "sg:phone":"+41 33 437 37 83",
    "sg:postcode":"3613",
    "sg:province":"Bern",
    "wof:name":"Aebi Urs Architekten Ag",
    "wof:placetype":"venue"
},
  "geometry": {"coordinates":[7.608279,46.772297],"type":"Point"}
}