{
  "type": "Feature",
  "properties": {
    "iso:country":"CH",
    "sg:address":"Promenadenstrasse 20",
    "sg:city":"Eglisau",
    "sg:orig_category":"Softwareentwicklung U beratung Unternehmensberatung",
    "sg:phone":"+41 79 660 27 77",
    "sg:postcode":"8193",
    "sg:province":"Z\u00fcrich",
    "wof:name":"Ki Trade Manser Erwin J.",
    "wof:placetype":"venue"
},
  "geometry": {"coordinates":[7.9733982086,47.3254928589],"type":"Point"}
}