{
  "type": "Feature",
  "properties": {
    "iso:country":"CH",
    "sg:address":"Poststrasse 3 6340 Baar. Postfach 440",
    "sg:city":"Baar",
    "sg:orig_category":"Handelsvermittlung U Grosshandel Sonstiger Grosshandel",
    "sg:phone":"+41 79 336 11 10",
    "sg:postcode":"6341",
    "sg:province":"Zug",
    "wof:name":"Reflex Systems Ag",
    "wof:placetype":"venue"
},
  "geometry": {"coordinates":[8.8874874115,47.2009735107],"type":"Point"}
}