{
  "type": "Feature",
  "properties": {
    "iso:country":"CH",
    "sg:address":"Steinlerweg 5",
    "sg:city":"Frenkendorf",
    "sg:orig_category":"Vereine Frauen Vereine Gemeinn\u00fctzige",
    "sg:postcode":"4402",
    "sg:province":"Basel-Landschaft",
    "wof:name":"Coop Frauenbund Frenkendorf",
    "wof:placetype":"venue"
},
  "geometry": {"coordinates":[7.7203440666,47.5061035156],"type":"Point"}
}