{
  "type": "Feature",
  "properties": {
    "iso:country":"CH",
    "sg:address":"B\u00fcmplizstrasse 12",
    "sg:city":"Bern",
    "sg:orig_category":"Architekturb\u00fcros Detailhandel mit Bekleidung",
    "sg:phone":"+41 31 991 24 06",
    "sg:postcode":"3027",
    "sg:province":"Bern",
    "wof:name":"Arco Mode-accessoires Cervinka + Bohonek",
    "wof:placetype":"venue"
},
  "geometry": {"coordinates":[7.396571,46.948692],"type":"Point"}
}