{
  "type": "Feature",
  "properties": {
    "iso:country":"CH",
    "sg:address":"Rue De Cord\u00e9",
    "sg:city":"Ardon",
    "sg:classifiers":[
        {
            "category":"Insurance",
            "subcategory":"Insurance Agent",
            "type":"Services"
        }
    ],
    "sg:phone":"+41 27 306 47 25",
    "sg:postcode":"1957",
    "sg:province":"Valais",
    "sg:tags":[
        "versicherungsagenturen",
        "-broker"
    ],
    "wof:name":"Jacques-louis Delaloye Agence Winterthur-assurances",
    "wof:placetype":"venue"
},
  "geometry": {"coordinates":[7.2568349838,46.2064590454],"type":"Point"}
}