{
  "type": "Feature",
  "properties": {
    "iso:country":"CH",
    "sg:address":"Kreuzgasse 81",
    "sg:city":"Kerzers",
    "sg:orig_category":"Haltung von Rindern",
    "sg:postcode":"3210",
    "sg:province":"Fribourg",
    "wof:name":"Viehuchtgenossenschaft Winklen.",
    "wof:placetype":"venue"
},
  "geometry": {"coordinates":[7.6804499626,46.6164894104],"type":"Point"}
}