{
  "type": "Feature",
  "properties": {
    "iso:country":"CH",
    "sg:address":"Im Tobelacker 9 8044 Gockhausen. Postfach",
    "sg:city":"Gockhausen",
    "sg:orig_category":"Unternehmensberatung",
    "sg:postcode":"8044",
    "sg:province":"Z\u00fcrich",
    "wof:name":"Sittacon Gmbh Unternehmensberatung Im Dienstleistungs Und Produktionsbereich",
    "wof:placetype":"venue"
},
  "geometry": {"coordinates":[8.6067371368,47.3779640198],"type":"Point"}
}