{
  "type": "Feature",
  "properties": {
    "iso:country":"CH",
    "sg:address":"Wilerweg 60",
    "sg:city":"Olten",
    "sg:orig_category":"Erschliessung von Grundst\u00fccken",
    "sg:postcode":"4600",
    "sg:province":"Solothurn",
    "wof:name":"Soziale Wohnbauaktion Olten",
    "wof:placetype":"venue"
},
  "geometry": {"coordinates":[7.9180197716,47.346786499],"type":"Point"}
}