{
  "type": "Feature",
  "properties": {
    "iso:country":"CH",
    "sg:address":"Gewerbestrasse 4",
    "sg:city":"W\u00e4ngi",
    "sg:orig_category":"Autolackierereien Autospenglereien",
    "sg:phone":"+41 52 378 18 36",
    "sg:postcode":"9545",
    "sg:province":"Thurgau",
    "wof:name":"Walter Herren Carrosserie & Spritzwerk",
    "wof:placetype":"venue"
},
  "geometry": {"coordinates":[8.939539,47.502949],"type":"Point"}
}