{
  "type": "Feature",
  "properties": {
    "iso:country":"CH",
    "sg:address":"Centro Lugano-sud Centro Ikea",
    "sg:city":"Grancia",
    "sg:orig_category":"Detailhandel mit Beleuchtungs U Haushaltsgegenst\u00e4nden Detailhandel mit Radio U Fernsehger\u00e4ten",
    "sg:phone":"+41 91 965 32 32",
    "sg:postcode":"6916",
    "sg:province":"Ticino",
    "wof:name":"Media Markt Sa",
    "wof:placetype":"venue"
},
  "geometry": {"coordinates":[8.928205,45.97361],"type":"Point"}
}