{
  "type": "Feature",
  "properties": {
    "iso:country":"CH",
    "sg:address":"Limmattalstrasse 228 8000 Z\u00fcrich. Postfach",
    "sg:city":"Z\u00fcrich",
    "sg:orig_category":"Elektroinstallation",
    "sg:postcode":"8049",
    "sg:province":"Z\u00fcrich",
    "wof:name":"Lovcen Pavicevic",
    "wof:placetype":"venue"
},
  "geometry": {"coordinates":[8.4955148697,47.4022865295],"type":"Point"}
}