{
  "type": "Feature",
  "properties": {
    "iso:country":"CH",
    "sg:address":"2900",
    "sg:city":"Porrentruy",
    "sg:orig_category":"Wirtschafts- and Arbeitgeberverb\u00e4nde",
    "sg:postcode":"2900",
    "sg:province":"Jura",
    "wof:name":"Assoc.des Maitres-bouchers Du District De Porrentruy",
    "wof:placetype":"venue"
},
  "geometry": {"coordinates":[7.0782270432,47.4170303345],"type":"Point"}
}