{
  "type": "Feature",
  "properties": {
    "iso:country":"CH",
    "sg:address":"Melchnaustrasse 66",
    "sg:city":"Langenthal",
    "sg:orig_category":"Tankstellen",
    "sg:phone":"+41 32 968 39 78",
    "sg:postcode":"4900",
    "sg:province":"Bern",
    "wof:name":"Michel Bridel Station Service Bp",
    "wof:placetype":"venue"
},
  "geometry": {"coordinates":[6.8340368271,47.1021614075],"type":"Point"}
}