{
  "type": "Feature",
  "properties": {
    "iso:country":"CH",
    "sg:address":"General Guisanstrasse 37",
    "sg:city":"Interlaken",
    "sg:orig_category":"Detailhandel mit Gebrauchtwaren in Verkaufsr\u00e4umen",
    "sg:phone":"+41 33 823 30 67",
    "sg:postcode":"3800",
    "sg:province":"Bern",
    "wof:name":"Brockenstube Des Gemeinn\u00fctzigen Frauenvereins",
    "wof:placetype":"venue"
},
  "geometry": {"coordinates":[7.8532748222,46.6814804077],"type":"Point"}
}