{
  "type": "Feature",
  "properties": {
    "iso:country":"CH",
    "sg:address":"Niklaus-konrad-strasse 12",
    "sg:city":"Solothurn",
    "sg:orig_category":"Advokaturb\u00fcros Notariate",
    "sg:phone":"+41 32 622 47 40",
    "sg:postcode":"4500",
    "sg:province":"Solothurn",
    "wof:name":"Zwygart & Ryser",
    "wof:placetype":"venue"
},
  "geometry": {"coordinates":[7.540833,47.204632],"type":"Point"}
}