{
  "type": "Feature",
  "properties": {
    "iso:country":"CH",
    "sg:address":"Avenue Adrien-jeandin 37",
    "sg:city":"Th\u00f4nex",
    "sg:classifiers":[
        {
            "category":"Restaurant",
            "type":"Food & Drink"
        }
    ],
    "sg:phone":"+41 32 968 48 47",
    "sg:postcode":"1226",
    "sg:province":"Gen\u00e8ve",
    "wof:name":"Brasserie Le Chauxois",
    "wof:placetype":"venue"
},
  "geometry": {"coordinates":[6.8442430496,47.1053657532],"type":"Point"}
}