{
  "type": "Feature",
  "properties": {
    "iso:country":"CH",
    "sg:address":"G\u00e4ssli 19",
    "sg:city":"Mastrils",
    "sg:orig_category":"Herstellung von Automobilen",
    "sg:postcode":"7303",
    "sg:province":"Graubunden",
    "wof:name":"Zai Rudolf Ag",
    "wof:placetype":"venue"
},
  "geometry": {"coordinates":[9.5490598679,46.9704017639],"type":"Point"}
}