{
  "type": "Feature",
  "properties": {
    "iso:country":"CH",
    "sg:address":"Staadackerstr. 61",
    "sg:city":"B\u00e4rschwil",
    "sg:orig_category":"G\u00fcterbef\u00f6rderung im Strassenverkehr",
    "sg:postcode":"4252",
    "sg:province":"Solothurn",
    "wof:name":"Iten Andreas",
    "wof:placetype":"venue"
},
  "geometry": {"coordinates":[7.4719281197,47.3968772888],"type":"Point"}
}