{
  "type": "Feature",
  "properties": {
    "iso:country":"CH",
    "sg:address":"Alfred Escher-strasse 26",
    "sg:city":"Z\u00fcrich",
    "sg:orig_category":"Personal U Stellenvermittlung Unternehmensberatung",
    "sg:phone":"+41 21 925 80 10",
    "sg:postcode":"8002",
    "sg:province":"Z\u00fcrich",
    "wof:name":"Coperman Sa",
    "wof:placetype":"venue"
},
  "geometry": {"coordinates":[5.1808700562,45.8973388672],"type":"Point"}
}