{
  "type": "Feature",
  "properties": {
    "iso:country":"CH",
    "sg:address":"Feldstrasse 2a",
    "sg:city":"Turbenthal",
    "sg:orig_category":"Bezirks, Sekundar, Realschulen, Oberstufe der Primarschulen",
    "sg:phone":"+41 52 397 22 70",
    "sg:postcode":"8488",
    "sg:province":"Z\u00fcrich",
    "wof:name":"Oberstufenschule Breiti",
    "wof:placetype":"venue"
},
  "geometry": {"coordinates":[8.850044,47.43631],"type":"Point"}
}