{
  "type": "Feature",
  "properties": {
    "iso:country":"CH",
    "sg:address":"Obere Grabenmattstrasse 11b",
    "sg:city":"Oberrohrdorf",
    "sg:orig_category":"Geb\u00e4ude, Wohnungsreinigung",
    "sg:phone":"+41 56 496 61 44",
    "sg:postcode":"5452",
    "sg:province":"Aargau",
    "wof:name":"Alba Reinigung",
    "wof:placetype":"venue"
},
  "geometry": {"coordinates":[8.3128700256,47.4202613831],"type":"Point"}
}