{
  "type": "Feature",
  "properties": {
    "iso:country":"CH",
    "sg:address":"Stedtligass 16 8627 Gr\u00fcningen. Postfach",
    "sg:city":"Yverdon-les-bains",
    "sg:orig_category":"Non-Classified Establishments",
    "sg:postcode":"1400",
    "sg:province":"Vaud",
    "wof:name":"Castrum Ag",
    "wof:placetype":"venue"
},
  "geometry": {"coordinates":[8.7637252808,47.2843933105],"type":"Point"}
}