{
  "type": "Feature",
  "properties": {
    "iso:country":"CH",
    "sg:address":"Siewerdtstrasse 69 8050 Z\u00fcrich. Postfach 8050 Z\u00fcrich",
    "sg:city":"Zust",
    "sg:orig_category":"Vermietung von Automobilen",
    "sg:phone":"+41 13167080",
    "sg:postcode":"50",
    "wof:name":"Excellence Luxury Services Ag Fahrzeuge, Liegenschaften Im Gehob. Preissegment; Dienstl., Bes. Vermietung",
    "wof:placetype":"venue"
},
  "geometry": {"coordinates":[8.5534200668,47.4123191833],"type":"Point"}
}