{
  "type": "Feature",
  "properties": {
    "addr:full":"6288 Schongau Luzern 6288",
    "addr:housenumber":"6288",
    "addr:postcode":"6288",
    "addr:street":"Schongau Luzern",
    "iso:country":"CH",
    "sg:address":"6288",
    "sg:city":"Schongau",
    "sg:orig_category":"Bezirks, Sekundar, Realschulen, Oberstufe der Primarschulen",
    "sg:postcode":"6288",
    "sg:province":"Luzern",
    "wof:name":"Realschule Mettmen",
    "wof:placetype":"venue"
},
  "geometry": {"coordinates":[8.263608,47.267738],"type":"Point"}
}