{
  "type": "Feature",
  "properties": {
    "iso:country":"CH",
    "sg:address":"Petit-schoenberg 56",
    "sg:city":"Fribourg",
    "sg:classifiers":[
        {
            "category":"Building & Trades",
            "subcategory":"Construction",
            "type":"Services"
        }
    ],
    "sg:phone":"+41 26 488 06 06",
    "sg:postcode":"1700",
    "sg:province":"Fribourg",
    "sg:tags":[
        "heating"
    ],
    "wof:name":"Innoservice Ag",
    "wof:placetype":"venue"
},
  "geometry": {"coordinates":[7.1444897652,46.8025093079],"type":"Point"}
}