{
  "type": "Feature",
  "properties": {
    "iso:country":"CH",
    "sg:address":"Fahrweidstrasse 46",
    "sg:city":"Fahrweid",
    "sg:orig_category":"Druck ohne Zeitungsdruck Offsetdruck",
    "sg:phone":"+41 17484260",
    "sg:postcode":"8951",
    "sg:province":"Z\u00fcrich",
    "wof:name":"Druckerei Fahrweid, Peyer J.",
    "wof:placetype":"venue"
},
  "geometry": {"coordinates":[8.414478302,47.4119262695],"type":"Point"}
}