{
  "type": "Feature",
  "properties": {
    "iso:country":"CH",
    "sg:address":"Boulevard Carl-vogt 87",
    "sg:city":"Gen\u00e8ve",
    "sg:orig_category":"Naturheil\u00e4rzte and Heilpraktiker",
    "sg:phone":"+41 22 800 22 50",
    "sg:postcode":"1205",
    "sg:province":"Gen\u00e8ve",
    "wof:name":"Luc Defago Naturopathe",
    "wof:placetype":"venue"
},
  "geometry": {"coordinates":[6.1395192146,46.1961097717],"type":"Point"}
}