{
  "type": "Feature",
  "properties": {
    "iso:country":"CH",
    "sg:address":"Rainsiedlung 16",
    "sg:city":"St\u00e4fa",
    "sg:orig_category":"Tanzschulen, Tanzlehrer",
    "sg:phone":"+41 19261756",
    "sg:postcode":"8712",
    "sg:province":"Z\u00fcrich",
    "wof:name":"Ida Schiltknecht Ballettp\u00e4dagogin",
    "wof:placetype":"venue"
},
  "geometry": {"coordinates":[8.7179908752,47.245803833],"type":"Point"}
}