{
  "type": "Feature",
  "properties": {
    "iso:country":"CH",
    "sg:address":"Cloche Rue De La 8 1201 Gen\u00e8ve. Postfach",
    "sg:city":"Gen\u00e8ve",
    "sg:orig_category":"Herstellung von Hebezeugen U F\u00f6rdermitteln",
    "sg:postcode":"1201",
    "sg:province":"Gen\u00e8ve",
    "wof:name":"M. Trulli Aufz\u00fcge-service",
    "wof:placetype":"venue"
},
  "geometry": {"coordinates":[8.7789669037,47.3110771179],"type":"Point"}
}