{
  "type": "Feature",
  "properties": {
    "iso:country":"CH",
    "sg:address":"Rue De La Poste 5",
    "sg:city":"Perroy",
    "sg:orig_category":"Fachdetailhandel in Verkaufsr\u00e4umen",
    "sg:postcode":"1166",
    "sg:province":"Vaud",
    "wof:name":"Look In Sport Diffusion, Giller Et Favre",
    "wof:placetype":"venue"
},
  "geometry": {"coordinates":[6.3646011353,46.4683876038],"type":"Point"}
}