{
  "type": "Feature",
  "properties": {
    "iso:country":"CH",
    "sg:address":"Berglistrasse 7",
    "sg:city":"Luzern",
    "sg:orig_category":"Shiatsu-Therapie",
    "sg:phone":"+41 41 310 20 61",
    "sg:postcode":"6005",
    "sg:province":"Luzern",
    "wof:name":"Rita Reichmuth Shiatsu",
    "wof:placetype":"venue"
},
  "geometry": {"coordinates":[8.2989673615,47.0428199768],"type":"Point"}
}