{
  "type": "Feature",
  "properties": {
    "iso:country":"CH",
    "sg:address":"Boden",
    "sg:city":"Engelberg",
    "sg:classifiers":[
        {
            "category":"Restaurant",
            "type":"Food & Drink"
        }
    ],
    "sg:phone":"+41 41 637 13 94",
    "sg:postcode":"6390",
    "sg:province":"Obwalden",
    "wof:name":"Restaurant Boden",
    "wof:placetype":"venue"
},
  "geometry": {"coordinates":[8.3862457275,46.823764801],"type":"Point"}
}