{
  "type": "Feature",
  "properties": {
    "iso:country":"CH",
    "sg:address":"Via Emilio Bossi 30b",
    "sg:city":"Chiasso",
    "sg:orig_category":"Grosshandel mit Tabakwaren",
    "sg:phone":"+41 91 682 48 56",
    "sg:postcode":"6830",
    "sg:province":"Ticino",
    "wof:name":"Fumaria Sa Tabacchi All'ingrosso",
    "wof:placetype":"venue"
},
  "geometry": {"coordinates":[9.0318174362,45.8355979919],"type":"Point"}
}