{
  "type": "Feature",
  "properties": {
    "iso:country":"CH",
    "sg:address":"Kornhausgasse 1",
    "sg:city":"Burgdorf",
    "sg:orig_category":"Geb\u00e4ude, Wohnungsreinigung Reinigungsgewerbe",
    "sg:phone":"+41 79 652 33 19",
    "sg:postcode":"3400",
    "sg:province":"Bern",
    "wof:name":"Jupiter-reinigungsdienst Ag",
    "wof:placetype":"venue"
},
  "geometry": {"coordinates":[7.4805440903,46.9389457703],"type":"Point"}
}