{
  "type": "Feature",
  "properties": {
    "iso:country":"CH",
    "sg:address":"Mont-blanc Quai Du 29",
    "sg:city":"Gen\u00e8ve",
    "sg:orig_category":"Non-Classified Establishments",
    "sg:postcode":"1201",
    "sg:province":"Gen\u00e8ve",
    "wof:name":"Vidal Olimpio Augusto Costruzione E Manutenzione Giardini",
    "wof:placetype":"venue"
},
  "geometry": {"coordinates":[9.0142173767,45.8494758606],"type":"Point"}
}