{
  "type": "Feature",
  "properties": {
    "iso:country":"CH",
    "sg:address":"Rue De La Poste 27",
    "sg:city":"Fully",
    "sg:orig_category":"Grosshandel mit Obst U Gem\u00fcse",
    "sg:phone":"+41 79 628 41 59",
    "sg:postcode":"1926",
    "sg:province":"Valais",
    "wof:name":"Georgy Carron Courtier En Fruits",
    "wof:placetype":"venue"
},
  "geometry": {"coordinates":[7.1149568558,46.1376533508],"type":"Point"}
}