{
  "type": "Feature",
  "properties": {
    "iso:country":"CH",
    "sg:address":"Rebgasse 17",
    "sg:city":"Liestal",
    "sg:orig_category":"Sonstiger Detailhandel mit Waren verschiedener Art, Hauptrichtung Nichtnahrungsmittel",
    "sg:phone":"+41 61 922 24 25",
    "sg:postcode":"4410",
    "sg:province":"Basel-Landschaft",
    "wof:name":"Stephan Hunsperger Hanf Paradies",
    "wof:placetype":"venue"
},
  "geometry": {"coordinates":[7.7338380814,47.4861488342],"type":"Point"}
}