{
  "type": "Feature",
  "properties": {
    "iso:country":"CH",
    "sg:address":"Neugr\u00fct 35",
    "sg:city":"Balzers",
    "sg:orig_category":"Herstellung von Ger\u00e4ten der Elektrizit\u00e4tserzeugung, -verteilung u.\u00e4. -Herstellung von elektronischen",
    "sg:phone":"+423 388 48 44",
    "sg:postcode":"9496",
    "wof:name":"Merck Balzers Ag",
    "wof:placetype":"venue"
},
  "geometry": {"coordinates":[9.5088729858,47.0773086548],"type":"Point"}
}