{
  "type": "Feature",
  "properties": {
    "addr:full":"Route De Salavaux Faoug Bern 1595",
    "addr:postcode":"1595",
    "addr:street":"Route De Salavaux",
    "iso:country":"CH",
    "sg:address":"Route De Salavaux",
    "sg:city":"Faoug",
    "sg:orig_category":"Bauschreinerei Einbau von Schreinerwaren",
    "sg:phone":"+41 26 670 57 12",
    "sg:postcode":"1595",
    "sg:province":"Bern",
    "wof:name":"Guillaume Trisconi Menuiserie Agencement Cuisines",
    "wof:placetype":"venue"
},
  "geometry": {"coordinates":[7.06976,46.905685],"type":"Point"}
}