{
  "type": "Feature",
  "properties": {
    "iso:country":"CH",
    "sg:address":"Neuhaltenstrasse 1",
    "sg:city":"Ebikon",
    "sg:orig_category":"Grosshandel mit medizinischen U orthop\u00e4dischen Artikeln Herstellung von medizinischen U chirurgische",
    "sg:phone":"+41 41 440 58 66",
    "sg:postcode":"6030",
    "sg:province":"Luzern",
    "wof:name":"Hermap Ag Ortop\u00e4die-technik Gesundheits-center",
    "wof:placetype":"venue"
},
  "geometry": {"coordinates":[8.3435697556,47.0879020691],"type":"Point"}
}