{
  "type": "Feature",
  "properties": {
    "iso:country":"CH",
    "sg:address":"Geissbergstrasse 22",
    "sg:city":"Kloten",
    "sg:orig_category":"Erwachsenenbildung U Unterricht K\u00fcnstlerische Schulen",
    "sg:phone":"+41 18134275",
    "sg:postcode":"8302",
    "sg:province":"Z\u00fcrich",
    "wof:name":"Bruno Brandenberger Musikschule",
    "wof:placetype":"venue"
},
  "geometry": {"coordinates":[8.5915880203,47.4549865723],"type":"Point"}
}