{
  "type": "Feature",
  "properties": {
    "iso:country":"CH",
    "sg:address":"Centrale Rue 47 2740 Montagne-moutier. Postfach",
    "sg:city":"Montagne-moutier",
    "sg:orig_category":"Herstellung von sonstigen elektrischen Ausr\u00fcstungen",
    "sg:postcode":"2740",
    "sg:province":"Bern",
    "wof:name":"Return S\u00e0rl",
    "wof:placetype":"venue"
},
  "geometry": {"coordinates":[7.3724632263,47.2787246704],"type":"Point"}
}