{
  "type": "Feature",
  "properties": {
    "iso:country":"CH",
    "sg:address":"Joran Chemin Du 1 1260 Nyon. Postfach",
    "sg:city":"Nyon",
    "sg:orig_category":"Veterin\u00e4rwesen",
    "sg:postcode":"1260",
    "sg:province":"Vaud",
    "wof:name":"Cabinet V\u00e9t\u00e9rinaire R\u00e8 Roberto S\u00e0rl",
    "wof:placetype":"venue"
},
  "geometry": {"coordinates":[6.9953799248,46.2966117859],"type":"Point"}
}