{
  "type": "Feature",
  "properties": {
    "iso:country":"CH",
    "sg:address":"Brunnenstrasse 10 8610 Uster. Postfach",
    "sg:city":"Uster",
    "sg:orig_category":"Sonstige mit der Informatik verbundene T\u00e4tigkeiten",
    "sg:phone":"+41 18510264",
    "sg:postcode":"8610",
    "sg:province":"Z\u00fcrich",
    "wof:name":"Business Innovation Lothal",
    "wof:placetype":"venue"
},
  "geometry": {"coordinates":[8.506980896,47.480178833],"type":"Point"}
}