{
  "type": "Feature",
  "properties": {
    "iso:country":"CH",
    "sg:address":"Via S.stefano 7",
    "sg:city":"Pedrinate",
    "sg:orig_category":"G\u00fcterbef\u00f6rderung im Strassenverkehr",
    "sg:phone":"+41 91 683 63 15",
    "sg:postcode":"6832",
    "sg:province":"Ticino",
    "wof:name":"Rosato Trasporti & Co Sa",
    "wof:placetype":"venue"
},
  "geometry": {"coordinates":[9.0116605759,45.827003479],"type":"Point"}
}