{
  "type": "Feature",
  "properties": {
    "iso:country":"CH",
    "sg:address":"Langackerstrasse",
    "sg:city":"D\u00fcrnten",
    "sg:orig_category":"Vorschulen, Kinderg\u00e4rten",
    "sg:phone":"+41 55 241 01 07",
    "sg:postcode":"8635",
    "sg:province":"Z\u00fcrich",
    "wof:name":"Kindergarten Langacker 1 & 2",
    "wof:placetype":"venue"
},
  "geometry": {"coordinates":[8.8665161133,47.2783546448],"type":"Point"}
}