{
  "type": "Feature",
  "properties": {
    "iso:country":"CH",
    "sg:address":"Sch\u00fctzengasse 1",
    "sg:city":"Z\u00fcrich",
    "sg:orig_category":"Reparatur von Uhren U Schmuck",
    "sg:phone":"+41 12110344",
    "sg:postcode":"8001",
    "sg:province":"Z\u00fcrich",
    "wof:name":"Hermann Zimmermann Uhrenfachgesch\u00e4ft",
    "wof:placetype":"venue"
},
  "geometry": {"coordinates":[8.5407247543,47.3760414124],"type":"Point"}
}