{
  "type": "Feature",
  "properties": {
    "iso:country":"CH",
    "sg:address":"Juraweide 9",
    "sg:city":"Biberstein",
    "sg:classifiers":[
        {
            "category":"Restaurant",
            "type":"Food & Drink"
        }
    ],
    "sg:phone":"+41 62 827 45 45",
    "sg:postcode":"5023",
    "sg:province":"Aargau",
    "wof:name":"Restaurant Juraweid",
    "wof:placetype":"venue"
},
  "geometry": {"coordinates":[8.0727109909,47.4153175354],"type":"Point"}
}