{
  "type": "Feature",
  "properties": {
    "iso:country":"CH",
    "sg:address":"Choller Str. 38",
    "sg:city":"Zug",
    "sg:classifiers":[
        {
            "category":"Wholesale",
            "subcategory":"Medical Equipment & Supplies",
            "type":"Manufacturing & Wholesale Goods"
        }
    ],
    "sg:phone":"+41 41 749 88 44",
    "sg:postcode":"6300",
    "sg:province":"Zug",
    "sg:tags":[
        "instrument",
        "health",
        "-",
        "precision"
    ],
    "wof:name":"Varian Medical System International Ag",
    "wof:placetype":"venue"
},
  "geometry": {"coordinates":[8.4930562973,47.1862182617],"type":"Point"}
}