{
  "type": "Feature",
  "properties": {
    "iso:country":"CH",
    "sg:address":"Laufenstrasse 13",
    "sg:city":"Breitenbach",
    "sg:classifiers":[
        {
            "category":"Home & Garden",
            "subcategory":"Building Materials",
            "type":"Retail Goods"
        }
    ],
    "sg:phone":"+41 61 791 19 66",
    "sg:postcode":"4226",
    "sg:province":"Solothurn",
    "sg:tags":[
        "window",
        "cellar"
    ],
    "wof:name":"Daniel M\u00e4der Glaserei",
    "wof:placetype":"venue"
},
  "geometry": {"coordinates":[7.542444,47.407475],"type":"Point"}
}