{
  "type": "Feature",
  "properties": {
    "iso:country":"CH",
    "sg:address":"Aarm\u00fchlestrasse 14",
    "sg:city":"Interlaken",
    "sg:classifiers":[
        {
            "category":"Commercial Area",
            "type":"Public Place"
        }
    ],
    "sg:phone":"+41 33 826 64 80",
    "sg:postcode":"3800",
    "sg:province":"Bern",
    "sg:tags":[
        "equipping",
        "kitchen"
    ],
    "wof:name":"Hotelbedarf Interlaken Ag",
    "wof:placetype":"venue"
},
  "geometry": {"coordinates":[7.8533978462,46.6837539673],"type":"Point"}
}