{
  "type": "Feature",
  "properties": {
    "iso:country":"CH",
    "sg:address":"Konstanzerstrasse 18",
    "sg:city":"Kreuzlingen",
    "sg:orig_category":"Kauf U Verkauf von Immobilien auf eigene Rechnung",
    "sg:phone":"+41 71 672 48 35",
    "sg:postcode":"8280",
    "sg:province":"Thurgau",
    "wof:name":"Terrenus Ag",
    "wof:placetype":"venue"
},
  "geometry": {"coordinates":[9.1679916382,47.6545715332],"type":"Point"}
}