{
  "type": "Feature",
  "properties": {
    "addr:full":"Pfarreiheim Weesen St. Gallen 8872",
    "addr:postcode":"8872",
    "iso:country":"CH",
    "sg:address":"Pfarreiheim",
    "sg:city":"Weesen",
    "sg:classifiers":[
        {
            "category":"Education",
            "subcategory":"Library",
            "type":"Public Place"
        }
    ],
    "sg:phone":"+41 55 283 11 26",
    "sg:postcode":"8872",
    "sg:province":"St. Gallen",
    "sg:tags":[
        "u",
        "bibliotheken",
        "archive"
    ],
    "wof:name":"Gemeindebibliothek",
    "wof:placetype":"venue"
},
  "geometry": {"coordinates":[9.101615,47.136185],"type":"Point"}
}