{
  "type": "Feature",
  "properties": {
    "iso:country":"CH",
    "sg:address":"Dozwilerstrasse 18",
    "sg:city":"Kesswil",
    "sg:orig_category":"Sportvereine Turnen",
    "sg:phone":"+41 71 463 49 29",
    "sg:postcode":"8593",
    "sg:province":"Thurgau",
    "wof:name":"M\u00e4nnerriege Kesswil",
    "wof:placetype":"venue"
},
  "geometry": {"coordinates":[9.3154220581,47.5912322998],"type":"Point"}
}