{
  "type": "Feature",
  "properties": {
    "iso:country":"CH",
    "sg:address":"Promenade De L'europe 11",
    "sg:city":"Gen\u00e8ve",
    "sg:orig_category":"Warenh\u00e4user",
    "sg:postcode":"1203",
    "sg:province":"Gen\u00e8ve",
    "wof:name":"Abm Au Bon March\u00e9 Coopark",
    "wof:placetype":"venue"
},
  "geometry": {"coordinates":[8.4468126297,47.2741775513],"type":"Point"}
}