{
  "type": "Feature",
  "properties": {
    "iso:country":"CH",
    "sg:address":"Via Soldino 24",
    "sg:city":"Paradiso",
    "sg:classifiers":[
        {
            "category":"Wholesale",
            "subcategory":"Books, Periodicals, & Newspapers",
            "type":"Manufacturing & Wholesale Goods"
        }
    ],
    "sg:phone":"+41 32 953 16 49",
    "sg:postcode":"6900",
    "sg:province":"Ticino",
    "sg:tags":[
        "directory",
        "publisher"
    ],
    "wof:name":"G\u00eetes De Suisse S\u00e0rl",
    "wof:placetype":"venue"
},
  "geometry": {"coordinates":[6.9508051872,47.2299575806],"type":"Point"}
}