{
  "type": "Feature",
  "properties": {
    "iso:country":"CH",
    "sg:address":"Steinbockstr. 2",
    "sg:city":"Chur",
    "sg:classifiers":[
        {
            "category":"Banks & Credit Unions",
            "subcategory":"Bank",
            "type":"Services"
        }
    ],
    "sg:phone":"+41 81 252 41 24",
    "sg:postcode":"7000",
    "sg:province":"Graubunden",
    "wof:name":"Aufina",
    "wof:placetype":"venue"
},
  "geometry": {"coordinates":[9.529252,46.852367],"type":"Point"}
}