{
  "type": "Feature",
  "properties": {
    "iso:country":"CH",
    "sg:address":"Althardstrasse 300",
    "sg:city":"Regensdorf",
    "sg:orig_category":"Handel mit Automobilen Instandhaltung U Reparatur von Automobilen",
    "sg:phone":"+41 79 642 72 37",
    "sg:postcode":"8105",
    "sg:province":"Z\u00fcrich",
    "wof:name":"Shami Autoland Gmbh",
    "wof:placetype":"venue"
},
  "geometry": {"coordinates":[8.462228775,47.4446525574],"type":"Point"}
}