{
  "type": "Feature",
  "properties": {
    "iso:country":"CH",
    "sg:address":"Taminserstrasse 42",
    "sg:city":"Felsberg",
    "sg:orig_category":"Zimmerei, Dachdeckerei, Bauspenglerei U Abdichtung",
    "sg:phone":"+41 81 252 47 89",
    "sg:postcode":"7012",
    "sg:province":"Graubunden",
    "wof:name":"Cavelti Charles",
    "wof:placetype":"venue"
},
  "geometry": {"coordinates":[9.4724283218,46.8452796936],"type":"Point"}
}