{
  "type": "Feature",
  "properties": {
    "iso:country":"CH",
    "sg:address":"Rue Du Commerce",
    "sg:city":"Leysin",
    "sg:orig_category":"Handelsvermittlung U Grosshandel",
    "sg:phone":"+41 24 494 38 00",
    "sg:postcode":"1854",
    "sg:province":"Vaud",
    "wof:name":"Merlin Titanium S\u00e0rl",
    "wof:placetype":"venue"
},
  "geometry": {"coordinates":[7.0113239288,46.3460617065],"type":"Point"}
}