{
  "type": "Feature",
  "properties": {
    "iso:country":"CH",
    "sg:address":"Rue De La Dent-blanche 14",
    "sg:city":"Sion",
    "sg:classifiers":[
        {
            "category":"Government",
            "subcategory":"Post Office",
            "type":"Public Place"
        }
    ],
    "sg:phone":"+41 27 322 63 98",
    "sg:postcode":"1950",
    "sg:province":"Valais",
    "sg:tags":[
        "caf\u00e9s",
        "tea-rooms"
    ],
    "wof:name":"Bar \u00e0 Caf\u00e9 Lido",
    "wof:placetype":"venue"
},
  "geometry": {"coordinates":[7.3594999313,46.2309494019],"type":"Point"}
}