{
  "type": "Feature",
  "properties": {
    "iso:country":"CH",
    "sg:address":"Untere Allmendstrasse 3a",
    "sg:city":"Steinhausen",
    "sg:orig_category":"Instandhaltung U Reparatur von Automobilen",
    "sg:phone":"+41 41 740 29 40",
    "sg:postcode":"6312",
    "sg:province":"Zug",
    "wof:name":"Blau-weiss Garage Ag",
    "wof:placetype":"venue"
},
  "geometry": {"coordinates":[8.4956245422,47.1924285889],"type":"Point"}
}