{
  "type": "Feature",
  "properties": {
    "iso:country":"CH",
    "sg:address":"Am Tych 4b 4665 Oftringen. Postfach",
    "sg:city":"Oftringen",
    "sg:orig_category":"Non-Classified Establishments",
    "sg:postcode":"4665",
    "sg:province":"Aargau",
    "wof:name":"Tripkovic International Transports",
    "wof:placetype":"venue"
},
  "geometry": {"coordinates":[7.9162788391,47.3131904602],"type":"Point"}
}