{
  "type": "Feature",
  "properties": {
    "iso:country":"CH",
    "sg:address":"D\u00fcbendorfstrasse 111",
    "sg:city":"Z\u00fcrich",
    "sg:orig_category":"Sonstige Kurierdienste",
    "sg:postcode":"8051",
    "sg:province":"Z\u00fcrich",
    "wof:name":"Kurierdienst A. Vespe",
    "wof:placetype":"venue"
},
  "geometry": {"coordinates":[8.578086853,47.4029045105],"type":"Point"}
}