{
  "type": "Feature",
  "properties": {
    "iso:country":"CH",
    "sg:address":"Z\u00fcrich Rue De 23c 2500 Biel/bienne. Postfach",
    "sg:city":"Biel/bienne",
    "sg:orig_category":"Herstellung von Elektromotoren, Generatoren U Transformatoren",
    "sg:phone":"+41 71 634 80 20",
    "sg:postcode":"2500",
    "sg:province":"Bern",
    "wof:name":"Ecowatt Ag",
    "wof:placetype":"venue"
},
  "geometry": {"coordinates":[9.1520795822,47.550567627],"type":"Point"}
}