{
  "type": "Feature",
  "properties": {
    "iso:country":"CH",
    "sg:address":"Oberdorfstrasse 30",
    "sg:city":"Weiach",
    "sg:orig_category":"Grosshandel mit Baumaschinen Grosshandel mit Holz U Baustoffen",
    "sg:phone":"+41 79 605 11 22",
    "sg:postcode":"8187",
    "sg:province":"Z\u00fcrich",
    "wof:name":"Maxit Ag Moderne Baustofftechnik",
    "wof:placetype":"venue"
},
  "geometry": {"coordinates":[8.4404211044,47.5546073914],"type":"Point"}
}