{
  "type": "Feature",
  "properties": {
    "iso:country":"CH",
    "sg:address":"Lerchenweg 10",
    "sg:city":"D\u00fcbendorf",
    "sg:orig_category":"Sonstiger Grosshandel",
    "sg:phone":"+41 17155435",
    "sg:postcode":"8600",
    "sg:province":"Z\u00fcrich",
    "wof:name":"A. Welti & Co",
    "wof:placetype":"venue"
},
  "geometry": {"coordinates":[8.5525827408,47.3153915405],"type":"Point"}
}