{
  "type": "Feature",
  "properties": {
    "iso:country":"CH",
    "sg:address":"Tassonnaire",
    "sg:city":"Troistorrents",
    "sg:orig_category":"Softwareentwicklung U beratung",
    "sg:postcode":"1872",
    "sg:province":"Valais",
    "wof:name":"Boissard Christian",
    "wof:placetype":"venue"
},
  "geometry": {"coordinates":[6.9101648331,46.2270851135],"type":"Point"}
}