{
  "type": "Feature",
  "properties": {
    "addr:full":"Z\u00fcrcherstrasse 15 Frauenfeld Thurgau 8500",
    "addr:housenumber":"15",
    "addr:postcode":"8500",
    "addr:street":"Zuercherstrasse",
    "iso:country":"CH",
    "sg:address":"Z\u00fcrcherstrasse 15",
    "sg:city":"Frauenfeld",
    "sg:classifiers":[
        {
            "category":"Professional",
            "subcategory":"Advertising",
            "type":"Services"
        }
    ],
    "sg:phone":"+41 52 721 11 57",
    "sg:postcode":"8500",
    "sg:province":"Thurgau",
    "sg:tags":[
        "agency"
    ],
    "wof:name":"H\u00e9! Ag F\u00fcr Kommunikation",
    "wof:placetype":"venue"
},
  "geometry": {"coordinates":[8.875241,47.552372],"type":"Point"}
}