{
  "type": "Feature",
  "properties": {
    "iso:country":"CH",
    "sg:address":"2562 Port. Postfach 75",
    "sg:city":"Port",
    "sg:orig_category":"Vereine Musik/Blasmusik",
    "sg:phone":"+41 32 331 31 35",
    "sg:postcode":"2562",
    "sg:province":"Bern",
    "wof:name":"Musikgesellschaft Port",
    "wof:placetype":"venue"
},
  "geometry": {"coordinates":[7.2550401688,47.1164245605],"type":"Point"}
}