{
  "type": "Feature",
  "properties": {
    "iso:country":"CH",
    "sg:address":"Stazione Via Della 11",
    "sg:city":"Muralto",
    "sg:orig_category":"Erbringung von Dienstleistungen f\u00fcr Unternehmen",
    "sg:postcode":"6600",
    "sg:province":"Ticino",
    "wof:name":"New Way Of Research Sa",
    "wof:placetype":"venue"
},
  "geometry": {"coordinates":[8.8015155792,46.1734085083],"type":"Point"}
}