{
  "type": "Feature",
  "properties": {
    "iso:country":"CH",
    "sg:address":"Siviriez",
    "sg:city":"Siviriez",
    "sg:classifiers":[
        {
            "category":"Banks & Credit Unions",
            "subcategory":"Bank",
            "type":"Services"
        }
    ],
    "sg:phone":"+41 26 656 13 40",
    "sg:postcode":"1678",
    "sg:province":"Fribourg",
    "wof:name":"Caisse D'epargne, De Siviriez",
    "wof:placetype":"venue"
},
  "geometry": {"coordinates":[6.874525,46.656879],"type":"Point"}
}