{
  "type": "Feature",
  "properties": {
    "iso:country":"CH",
    "sg:address":"Pr\u00e9s De La Ruatte 56a",
    "sg:city":"Montignez",
    "sg:classifiers":[
        {
            "category":"Banks & Credit Unions",
            "subcategory":"Bank",
            "type":"Services"
        }
    ],
    "sg:phone":"+41 32 475 54 67",
    "sg:postcode":"2924",
    "sg:province":"Jura",
    "wof:name":"Raiffeisen, Martin Claude",
    "wof:placetype":"venue"
},
  "geometry": {"coordinates":[7.059067,47.487106],"type":"Point"}
}