{
  "type": "Feature",
  "properties": {
    "iso:country":"CH",
    "sg:address":"Hardstrasse 67",
    "sg:city":"Z\u00fcrich",
    "sg:orig_category":"Dachdeckerei D\u00e4mmung gegen K\u00e4lte, W\u00e4rme, Schall U Ersch\u00fctterung",
    "sg:phone":"+41 27 458 20 88",
    "sg:postcode":"8004",
    "sg:province":"Z\u00fcrich",
    "wof:name":"Maison Bornet Sa Inst.sanitaires & Couverture",
    "wof:placetype":"venue"
},
  "geometry": {"coordinates":[7.46364,46.258438],"type":"Point"}
}