{
  "type": "Feature",
  "properties": {
    "iso:country":"CH",
    "sg:address":"Weiherstrasse 41",
    "sg:city":"Kreuzlingen",
    "sg:classifiers":[
        {
            "category":"Manufacturing",
            "subcategory":"Rubber & Plastics",
            "type":"Manufacturing & Wholesale Goods"
        }
    ],
    "sg:phone":"+41 32 926 72 72",
    "sg:postcode":"8280",
    "sg:province":"Thurgau",
    "sg:tags":[
        "box"
    ],
    "wof:name":"Inca Plastic Sa",
    "wof:placetype":"venue"
},
  "geometry": {"coordinates":[6.8104639053,47.0943984985],"type":"Point"}
}