{
  "type": "Feature",
  "properties": {
    "iso:country":"CH",
    "sg:address":"Boujean Rue De 60",
    "sg:city":"Biel/bienne",
    "sg:orig_category":"Non-Classified Establishments",
    "sg:postcode":"2502",
    "sg:province":"Bern",
    "wof:name":"R\u00e9sidence Les Mimosas S\u00e0rl",
    "wof:placetype":"venue"
},
  "geometry": {"coordinates":[7.2576961517,47.1476516724],"type":"Point"}
}