{
  "type": "Feature",
  "properties": {
    "addr:full":"Baarerstrasse 57 Zug Zug 6300",
    "addr:housenumber":"57",
    "addr:postcode":"6300",
    "addr:street":"Baarerstrasse;Zug",
    "iso:country":"CH",
    "sg:address":"Baarerstrasse 57",
    "sg:city":"Zug",
    "sg:orig_category":"Datenverarbeitungsdienste Logistikberatung",
    "sg:phone":"+41 79 312 51 07",
    "sg:postcode":"6300",
    "sg:province":"Zug",
    "wof:name":"Planzer Consulting",
    "wof:placetype":"venue"
},
  "geometry": {"coordinates":[8.43903,47.15395],"type":"Point"}
}