{
  "type": "Feature",
  "properties": {
    "iso:country":"CH",
    "sg:address":"Postgasse 5",
    "sg:city":"G\u00fcmmenen",
    "sg:orig_category":"Detailhandel mit Milcherzeugnissen U Eiern Verarbeitung von Milch",
    "sg:phone":"+41 31 751 15 36",
    "sg:postcode":"3205",
    "sg:province":"Bern",
    "wof:name":"Otto Kiener K\u00e4serei",
    "wof:placetype":"venue"
},
  "geometry": {"coordinates":[7.2423100471,46.9475212097],"type":"Point"}
}