{
  "type": "Feature",
  "properties": {
    "iso:country":"CH",
    "sg:address":"Bremgartenstrasse 18",
    "sg:city":"Zollikofen",
    "sg:orig_category":"Handelsvermittlung U Grosshandel Herstellung von Bergwerks U Baumaschinen",
    "sg:phone":"+41 31 911 48 49",
    "sg:postcode":"3052",
    "sg:province":"Bern",
    "wof:name":"Wittwer Handels Gmbh",
    "wof:placetype":"venue"
},
  "geometry": {"coordinates":[7.4458599091,46.9897117615],"type":"Point"}
}