{
  "type": "Feature",
  "properties": {
    "iso:country":"CH",
    "sg:address":"Aemtlerstrasse 28",
    "sg:city":"Z\u00fcrich",
    "sg:orig_category":"Detailhandel mit Fahrr\u00e4dern Handel mit Motorr\u00e4dern, Teilen U Zubeh\u00f6r Instandhaltung U Reparatur von ",
    "sg:phone":"+41 14333005",
    "sg:postcode":"8003",
    "sg:province":"Z\u00fcrich",
    "wof:name":"Rolf Theiler Velos & Mofas",
    "wof:placetype":"venue"
},
  "geometry": {"coordinates":[8.5158576965,47.3718605042],"type":"Point"}
}