{
  "type": "Feature",
  "properties": {
    "iso:country":"CH",
    "sg:address":"Allmendstrasse 37",
    "sg:city":"Grenchen",
    "sg:orig_category":"Stukkateurgewerbe, Gipserei U Verputzerei",
    "sg:postcode":"2540",
    "sg:province":"Solothurn",
    "wof:name":"Gipserei Zingg",
    "wof:placetype":"venue"
},
  "geometry": {"coordinates":[7.3897848129,47.2026634216],"type":"Point"}
}