{
  "type": "Feature",
  "properties": {
    "iso:country":"CH",
    "sg:address":"Pelikanstrasse 19",
    "sg:city":"Z\u00fcrich",
    "sg:orig_category":"Architektur U Ingenieurb\u00fcros",
    "sg:postcode":"8001",
    "sg:province":"Z\u00fcrich",
    "wof:name":"Oberholzer Adolphe",
    "wof:placetype":"venue"
},
  "geometry": {"coordinates":[8.536692,47.371548],"type":"Point"}
}