{
  "type": "Feature",
  "properties": {
    "iso:country":"CH",
    "sg:address":"Hasenb\u00fchlstrasse 11",
    "sg:city":"Heiden",
    "sg:orig_category":"Herstellung von medizinischen U chirurgischen Ger\u00e4ten sowie orthop\u00e4dischen Vorrichtungen",
    "sg:phone":"+41 71 243 52 60",
    "sg:postcode":"9410",
    "sg:province":"Appenzell Ausserrhoden",
    "wof:name":"Orthop\u00e4die Am Rosenberg Heiden",
    "wof:placetype":"venue"
},
  "geometry": {"coordinates":[9.5266914368,47.4467353821],"type":"Point"}
}