{
  "type": "Feature",
  "properties": {
    "iso:country":"CH",
    "sg:address":"Floraweg 1 8580 Amriswil. Postfach",
    "sg:city":"Amriswil",
    "sg:orig_category":"Werbung",
    "sg:postcode":"8580",
    "sg:province":"Thurgau",
    "wof:name":"Panta Rhei Pr Gmbh",
    "wof:placetype":"venue"
},
  "geometry": {"coordinates":[9.3046607971,47.5482521057],"type":"Point"}
}