{
  "type": "Feature",
  "properties": {
    "iso:country":"CH",
    "sg:address":"Soullier Rue Benjamin- 12 1202 Gen\u00e8ve. Postfach",
    "sg:city":"Gen\u00e8ve",
    "sg:orig_category":"Instandhaltung U Reparatur von Automobilen",
    "sg:phone":"+41 34 491 17 69",
    "sg:postcode":"1202",
    "sg:province":"Gen\u00e8ve",
    "wof:name":"B. Steiner",
    "wof:placetype":"venue"
},
  "geometry": {"coordinates":[7.7421040535,46.854801178],"type":"Point"}
}