{
  "type": "Feature",
  "properties": {
    "addr:full":"Rue Du Jura 7 Gen\u00e8ve Gen\u00e8ve 1201",
    "addr:housenumber":"7",
    "addr:postcode":"1201",
    "addr:street":"Rue Du Jura",
    "iso:country":"CH",
    "sg:address":"Rue Du Jura 7",
    "sg:city":"Gen\u00e8ve",
    "sg:orig_category":"Aktivit\u00e4ten der Generalunternehmen im Baugewerbe Allgemeiner Hoch U Tiefbau",
    "sg:phone":"+41 22 344 27 40",
    "sg:postcode":"1201",
    "sg:province":"Gen\u00e8ve",
    "wof:name":"Toso, Les Fils De Louis, P.-l. Et M. Toso Succ.",
    "wof:placetype":"venue"
},
  "geometry": {"coordinates":[6.138186,46.208752],"type":"Point"}
}