{
  "type": "Feature",
  "properties": {
    "iso:country":"CH",
    "sg:address":"Inzlingerstrasse 70",
    "sg:city":"Riehen",
    "sg:orig_category":"Filmverleih U Videoprogrammanbieter",
    "sg:phone":"+41 61 643 01 75",
    "sg:postcode":"4125",
    "sg:province":"Basel-Stadt",
    "wof:name":"Power Shop Versand, May",
    "wof:placetype":"venue"
},
  "geometry": {"coordinates":[7.6559457779,47.5870895386],"type":"Point"}
}