{
  "type": "Feature",
  "properties": {
    "iso:country":"CH",
    "sg:address":"Kaistenbergstrasse 10",
    "sg:city":"Frick",
    "sg:orig_category":"Bauschreinerei Herstellung von Konstruktionsteilen, Fertigbauteilen U Ausbauelementen aus Holz",
    "sg:phone":"+41 41 870 62 82",
    "sg:postcode":"5070",
    "sg:province":"Aargau",
    "wof:name":"Schilter Ag",
    "wof:placetype":"venue"
},
  "geometry": {"coordinates":[8.630829,46.879951],"type":"Point"}
}