{
  "type": "Feature",
  "properties": {
    "iso:country":"CH",
    "sg:address":"Talgut-zentrum 22",
    "sg:city":"Ittigen",
    "sg:orig_category":"Vereine Mandolinen and Gitarren",
    "sg:postcode":"3063",
    "sg:province":"Bern",
    "wof:name":"Berner Mandolinenorchester",
    "wof:placetype":"venue"
},
  "geometry": {"coordinates":[7.4803729057,46.9746589661],"type":"Point"}
}