{
  "type": "Feature",
  "properties": {
    "iso:country":"CH",
    "sg:address":"L\u00e4ngenbergstrasse 2",
    "sg:city":"Schaffhausen",
    "sg:orig_category":"RESTAURANTS: TEA-ROOMS",
    "sg:postcode":"8200",
    "sg:province":"Schaffhausen",
    "wof:name":"Michael Siegwarth",
    "wof:placetype":"venue"
},
  "geometry": {"coordinates":[8.6301612854,47.7266120911],"type":"Point"}
}