{
  "type": "Feature",
  "properties": {
    "addr:full":"Ziegelbr\u00fcckstrasse 19 Niederurnen Glarus 8867",
    "addr:housenumber":"19",
    "addr:postcode":"8867",
    "addr:street":"Ziegelbrueckstrasse",
    "iso:country":"CH",
    "sg:address":"Ziegelbr\u00fcckstrasse 19",
    "sg:city":"Niederurnen",
    "sg:orig_category":"Detailhandel mit Brot, Back U S\u00fcsswaren",
    "sg:phone":"+41 55 610 16 36",
    "sg:postcode":"8867",
    "sg:province":"Glarus",
    "wof:name":"Jacques Gabriel Ag B\u00e4ckerei-konditorei",
    "wof:placetype":"venue"
},
  "geometry": {"coordinates":[9.056097,47.128448],"type":"Point"}
}