{
  "type": "Feature",
  "properties": {
    "iso:country":"CH",
    "sg:address":"Entfelderstrasse 7",
    "sg:city":"Sch\u00f6nenwerd",
    "sg:orig_category":"Informatikdienste",
    "sg:phone":"+41 62 858 70 33",
    "sg:postcode":"5012",
    "sg:province":"Solothurn",
    "wof:name":"Kraan & Richards",
    "wof:placetype":"venue"
},
  "geometry": {"coordinates":[8.0116043091,47.3719482422],"type":"Point"}
}