{
  "type": "Feature",
  "properties": {
    "iso:country":"CH",
    "sg:address":"Heissgl\u00e4ndstr. 20",
    "sg:city":"Pratteln",
    "sg:classifiers":[
        {
            "category":"Home & Garden",
            "subcategory":"Furniture",
            "type":"Retail Goods"
        }
    ],
    "sg:phone":"+41 61 811 31 31",
    "sg:postcode":"4133",
    "sg:province":"Basel-Landschaft",
    "sg:tags":[
        "professional",
        "household",
        "wood"
    ],
    "wof:name":"Inter-lundia Ag",
    "wof:placetype":"venue"
},
  "geometry": {"coordinates":[7.7092618942,47.5305671692],"type":"Point"}
}