{
  "type": "Feature",
  "properties": {
    "iso:country":"CH",
    "sg:address":"Ch\u00e2teau Rue Du 4",
    "sg:city":"Gen\u00e8ve",
    "sg:orig_category":"Non-Classified Establishments",
    "sg:postcode":"1203",
    "sg:province":"Gen\u00e8ve",
    "wof:name":"Profil Gestion S\u00e0rl",
    "wof:placetype":"venue"
},
  "geometry": {"coordinates":[6.1306858063,46.2047653198],"type":"Point"}
}