{
  "type": "Feature",
  "properties": {
    "iso:country":"CH",
    "sg:address":"K\u00f6chlistrasse 15 8004 Z\u00fcrich. Postfach",
    "sg:city":"Z\u00fcrich",
    "sg:orig_category":"Werbung",
    "sg:phone":"+41 32 730 20 88",
    "sg:postcode":"8004",
    "sg:province":"Z\u00fcrich",
    "wof:name":"Heubi Pierre-alain, Conseils En Communication Et M\u00e9dias",
    "wof:placetype":"venue"
},
  "geometry": {"coordinates":[6.8612399101,46.98828125],"type":"Point"}
}