{
  "type": "Feature",
  "properties": {
    "iso:country":"CH",
    "sg:address":"Hof",
    "sg:city":"Seelisberg",
    "sg:orig_category":"Tapeziererei",
    "sg:phone":"+41 41 820 46 15",
    "sg:postcode":"6377",
    "sg:province":"Uri",
    "wof:name":"Hansruedy Flury Maler-& Tapezierergesch\u00e4ft",
    "wof:placetype":"venue"
},
  "geometry": {"coordinates":[8.57771492,46.96534729],"type":"Point"}
}