{
  "type": "Feature",
  "properties": {
    "iso:country":"CH",
    "sg:address":"Leiernstrasse 3",
    "sg:city":"Sch\u00fcpfen",
    "sg:orig_category":"Detailhandel mit B\u00fcchern, Zeitungen, Schreib U Papeteriewaren",
    "sg:phone":"+41 22 827 48 48",
    "sg:postcode":"3054",
    "sg:province":"Bern",
    "wof:name":"Pws Syst\u00e8mes S\u00e0rl",
    "wof:placetype":"venue"
},
  "geometry": {"coordinates":[6.13,46.183323],"type":"Point"}
}