{
  "type": "Feature",
  "properties": {
    "iso:country":"CH",
    "sg:address":"Zimberh\u00fcbel 597 5728 Gontenschwil. Postfach 13",
    "sg:city":"Gontenschwil",
    "sg:orig_category":"Technische B\u00fcros Heizung, L\u00fcftung, Klima Technische B\u00fcros Sanit\u00e4r",
    "sg:postcode":"5728",
    "sg:province":"Aargau",
    "wof:name":"H.u. Brand Planungsb\u00fcro Haustechnik",
    "wof:placetype":"venue"
},
  "geometry": {"coordinates":[8.7716197968,47.5080108643],"type":"Point"}
}