{
  "type": "Feature",
  "properties": {
    "iso:country":"CH",
    "sg:address":"Rochers Les",
    "sg:city":"Chandolin-savi\u00e8se",
    "sg:orig_category":"Elektroinstallation",
    "sg:phone":"+41 21 807 32 59",
    "sg:postcode":"1965",
    "sg:province":"Valais",
    "wof:name":"Groupe 5, Nicoulaz J.-p.",
    "wof:placetype":"venue"
},
  "geometry": {"coordinates":[7.3385391235,46.2504730225],"type":"Point"}
}