{
  "type": "Feature",
  "properties": {
    "iso:country":"CH",
    "sg:address":"Route De Berne 6",
    "sg:city":"Lausanne",
    "sg:classifiers":[
        {
            "category":"Shopping",
            "subcategory":"Computers & Home Electronics",
            "type":"Retail Goods"
        }
    ],
    "sg:phone":"+41 21 652 13 53",
    "sg:postcode":"1010",
    "sg:province":"Vaud",
    "sg:tags":[
        "blanket"
    ],
    "wof:name":"Borio Sa",
    "wof:placetype":"venue"
},
  "geometry": {"coordinates":[6.6474318504,46.5341796875],"type":"Point"}
}