{
  "type": "Feature",
  "properties": {
    "iso:country":"CH",
    "sg:address":"Schitterstrasse 11",
    "sg:city":"Oberegg",
    "sg:orig_category":"Erwachsenenbildung U Unterricht",
    "sg:phone":"+41 71 891 62 19",
    "sg:postcode":"9413",
    "sg:province":"Appenzell Innerhoden",
    "wof:name":"Heico, Heinimann U.",
    "wof:placetype":"venue"
},
  "geometry": {"coordinates":[9.5524635315,47.4260292053],"type":"Point"}
}