{
  "type": "Feature",
  "properties": {
    "iso:country":"CH",
    "sg:address":"Hauptstrasse 31",
    "sg:city":"Densb\u00fcren",
    "sg:orig_category":"Sonstiger Grosshandel",
    "sg:phone":"+41 55 260 17 77",
    "sg:postcode":"5026",
    "sg:province":"Aargau",
    "wof:name":"Unitone Gmbh",
    "wof:placetype":"venue"
},
  "geometry": {"coordinates":[8.853556633,47.2501564026],"type":"Point"}
}