{
  "type": "Feature",
  "properties": {
    "iso:country":"CH",
    "sg:address":"Freiburgstrasse 69",
    "sg:city":"Murten",
    "sg:classifiers":[
        {
            "category":"Building & Trades",
            "subcategory":"Plumbing",
            "type":"Services"
        }
    ],
    "sg:phone":"+41 32 931 63 33",
    "sg:postcode":"3280",
    "sg:province":"Fribourg",
    "sg:tags":[
        "cropping",
        "tool"
    ],
    "wof:name":"Orth & Cie Successeur E. Hahn Et J.-l. Schnegg",
    "wof:placetype":"venue"
},
  "geometry": {"coordinates":[6.752808,47.060703],"type":"Point"}
}