{
  "type": "Feature",
  "properties": {
    "iso:country":"CH",
    "sg:address":"H\u00f6henstrasse Ost 87",
    "sg:city":"Olten",
    "sg:orig_category":"Praxis f\u00fcr Atlaslogie",
    "sg:phone":"+41 62 296 09 29",
    "sg:postcode":"4600",
    "sg:province":"Solothurn",
    "wof:name":"Marianne Amport Atlaslogie",
    "wof:placetype":"venue"
},
  "geometry": {"coordinates":[7.9211602211,47.3461265564],"type":"Point"}
}