{
  "type": "Feature",
  "properties": {
    "iso:country":"CH",
    "sg:address":"Oberlandstrasse 27 3700 Spiez. Postfach 272",
    "sg:city":"Spiez",
    "sg:orig_category":"Detailhandel mit Tabakwaren Detailhandel mit Zeitungen U Zeitschriften Kioske",
    "sg:phone":"+41 27 322 78 35",
    "sg:postcode":"3700",
    "sg:province":"Bern",
    "wof:name":"B\u00e9atrice Dubuis Kiosque Tabacs Ritz",
    "wof:placetype":"venue"
},
  "geometry": {"coordinates":[7.3585538864,46.2353820801],"type":"Point"}
}