{
  "type": "Feature",
  "properties": {
    "iso:country":"CH",
    "sg:address":"Grindelstrasse 6 8303 Bassersdorf. Postfach 451",
    "sg:city":"Bassersdorf",
    "sg:orig_category":"Herstellung von Ger\u00e4ten der Elektrizit\u00e4tserzeugung, -verteilung u.\u00e4. -Herstellung von sonstigen elek",
    "sg:phone":"+41 18381111",
    "sg:postcode":"8303",
    "sg:province":"Z\u00fcrich",
    "wof:name":"Rotronic Ag",
    "wof:placetype":"venue"
},
  "geometry": {"coordinates":[8.6074132919,47.4466171265],"type":"Point"}
}