{
  "type": "Feature",
  "properties": {
    "iso:country":"CH",
    "sg:address":"Rue Beausite 3",
    "sg:city":"Moutier",
    "sg:classifiers":[
        {
            "category":"Manufacturing",
            "subcategory":"Metals",
            "type":"Manufacturing & Wholesale Goods"
        }
    ],
    "sg:phone":"+41 56 485 81 81",
    "sg:postcode":"2740",
    "sg:province":"Bern",
    "sg:tags":[
        "metallurgy",
        "metalworking",
        "processing"
    ],
    "wof:name":"Birchmeier Spr\u00dchtechnik Ag",
    "wof:placetype":"venue"
},
  "geometry": {"coordinates":[8.313249588,47.4063491821],"type":"Point"}
}