{
  "type": "Feature",
  "properties": {
    "iso:country":"CH",
    "sg:address":"Berstelstr. 25",
    "sg:city":"Arisdorf",
    "sg:classifiers":[
        {
            "category":"Professional",
            "subcategory":"Computer Services",
            "type":"Services"
        }
    ],
    "sg:phone":"+41 61 811 95 55",
    "sg:postcode":"4422",
    "sg:province":"Basel-Landschaft",
    "sg:tags":[
        "information",
        "technology",
        "software"
    ],
    "wof:name":"Urech & Harr Ag",
    "wof:placetype":"venue"
},
  "geometry": {"coordinates":[7.7672848701,47.4979171753],"type":"Point"}
}