{
  "type": "Feature",
  "properties": {
    "iso:country":"CH",
    "sg:address":"R\u00fctistrasse 6",
    "sg:city":"Baden",
    "sg:orig_category":"Personal U Stellenvermittlung Unternehmensberatung",
    "sg:postcode":"5400",
    "sg:province":"Aargau",
    "wof:name":"Bc - Boll Consulting Unternehmensberatung",
    "wof:placetype":"venue"
},
  "geometry": {"coordinates":[8.3048095703,47.474822998],"type":"Point"}
}