{
  "type": "Feature",
  "properties": {
    "iso:country":"CH",
    "sg:address":"Walchestrasse 33 8006 Z\u00fcrich. Postfach",
    "sg:city":"Z\u00fcrich",
    "sg:orig_category":"Organisationen des Gesundheitswesen",
    "sg:phone":"+41 12165111",
    "sg:postcode":"8035",
    "sg:province":"Z\u00fcrich",
    "wof:name":"F\u00fcrsorgestelle Stadt\u00e4rztlicher Dienst",
    "wof:placetype":"venue"
},
  "geometry": {"coordinates":[8.5408916473,47.3819541931],"type":"Point"}
}