{
  "type": "Feature",
  "properties": {
    "iso:country":"CH",
    "sg:address":"Hofmatt",
    "sg:city":"Zimmerwald",
    "sg:orig_category":"Sportvereine Turnen",
    "sg:phone":"+41 31 819 20 13",
    "sg:postcode":"3086",
    "sg:province":"Bern",
    "wof:name":"Turnverein Stv Zimmerwald",
    "wof:placetype":"venue"
},
  "geometry": {"coordinates":[7.4716010094,46.8815917969],"type":"Point"}
}