{
  "type": "Feature",
  "properties": {
    "addr:full":"Waldst\u00e4tterstrasse 17 Luzern Luzern 6003",
    "addr:housenumber":"17",
    "addr:postcode":"6003",
    "addr:street":"Waldstaetterstrasse",
    "iso:country":"CH",
    "sg:address":"Waldst\u00e4tterstrasse 17",
    "sg:city":"Luzern",
    "sg:orig_category":"Detailhandel mit Bekleidung",
    "sg:phone":"+41 41 220 02 55",
    "sg:postcode":"6003",
    "sg:province":"Luzern",
    "wof:name":"Jaccar\u00e9 Woman & Design Maya Brechb\u00fchler",
    "wof:placetype":"venue"
},
  "geometry": {"coordinates":[8.307678,47.04636],"type":"Point"}
}