{
  "type": "Feature",
  "properties": {
    "iso:country":"CH",
    "sg:address":"Route De Villars-vert 21 1752 Villars-sur-gl\u00e2ne. Postfach",
    "sg:city":"Villars-sur-gl\u00e2ne",
    "sg:orig_category":"Sonstiger Grosshandel",
    "sg:postcode":"1752",
    "sg:province":"Fribourg",
    "wof:name":"Entreprise M'buli J.c. Co Ltd, \u00e0 Londres, Succursale De Villars-sur-gl\u00e2ne",
    "wof:placetype":"venue"
},
  "geometry": {"coordinates":[7.1281261444,46.8003501892],"type":"Point"}
}