{
  "type": "Feature",
  "properties": {
    "addr:full":"Seevorstadt 29 2502 Biel/bienne. Postfach Biel/bienne Bern 2501",
    "addr:housenumber":"29;2501",
    "addr:postcode":"2502;postfach",
    "addr:street":"Seevorstadt",
    "iso:country":"CH",
    "sg:address":"Seevorstadt 29 2502 Biel/bienne. Postfach",
    "sg:city":"Biel/bienne",
    "sg:orig_category":"Aktivit\u00e4ten der Generalunternehmen im Baugewerbe Vermittlung von Immobilien",
    "sg:phone":"+41 32 323 51 41",
    "sg:postcode":"2501",
    "sg:province":"Bern",
    "wof:name":"Cobat Bienne Sa",
    "wof:placetype":"venue"
},
  "geometry": {"coordinates":[7.236018,47.136326],"type":"Point"}
}