{
  "type": "Feature",
  "properties": {
    "iso:country":"CH",
    "sg:address":"Birkenweg 8",
    "sg:city":"Rheinfelden",
    "sg:orig_category":"Unternehmensberatung",
    "sg:phone":"+41 61 833 16 25",
    "sg:postcode":"4310",
    "sg:province":"Aargau",
    "wof:name":"Juan Peromingo Peba Wirtschaftsberatung",
    "wof:placetype":"venue"
},
  "geometry": {"coordinates":[7.7951087952,47.5487709045],"type":"Point"}
}