{
  "type": "Feature",
  "properties": {
    "iso:country":"CH",
    "sg:address":"3473",
    "sg:city":"Alchenstorf",
    "sg:orig_category":"Haltung von Rindern",
    "sg:postcode":"3473",
    "sg:province":"Bern",
    "wof:name":"Viehzuchtgenossenschaft Alchenstorf",
    "wof:placetype":"venue"
},
  "geometry": {"coordinates":[7.6403398514,47.1247901917],"type":"Point"}
}