{
  "type": "Feature",
  "properties": {
    "iso:country":"CH",
    "sg:address":"7312",
    "sg:city":"Pf\u00e4fers",
    "sg:classifiers":[
        {
            "category":"Education",
            "subcategory":"Library",
            "type":"Public Place"
        }
    ],
    "sg:postcode":"7312",
    "sg:province":"St. Gallen",
    "sg:tags":[
        "u",
        "bibliotheken",
        "archive"
    ],
    "wof:name":"Katholische Pfarrbibliothek",
    "wof:placetype":"venue"
},
  "geometry": {"coordinates":[9.51001,46.986591],"type":"Point"}
}