{
  "type": "Feature",
  "properties": {
    "iso:country":"CH",
    "sg:address":"5522",
    "sg:city":"T\u00e4gerig",
    "sg:classifiers":[
        {
            "category":"Education",
            "subcategory":"Library",
            "type":"Public Place"
        }
    ],
    "sg:postcode":"5522",
    "sg:province":"Aargau",
    "sg:tags":[
        "u",
        "bibliotheken",
        "archive"
    ],
    "wof:name":"Katholische Pfarrbibliothek",
    "wof:placetype":"venue"
},
  "geometry": {"coordinates":[8.27898,47.39827],"type":"Point"}
}