{
  "type": "Feature",
  "properties": {
    "iso:country":"CH",
    "sg:address":"Les Fontaines 10",
    "sg:city":"Mont-tramelan",
    "sg:orig_category":"Vereine Gesang",
    "sg:postcode":"2723",
    "sg:province":"Bern",
    "wof:name":"Choeur Mixte Mennon.tramelan",
    "wof:placetype":"venue"
},
  "geometry": {"coordinates":[7.0674757957,47.2072563171],"type":"Point"}
}