{
  "type": "Feature",
  "properties": {
    "iso:country":"CH",
    "sg:address":"Alle Gerre",
    "sg:city":"Losone",
    "sg:orig_category":"Malerei",
    "sg:phone":"+41 91 791 17 38",
    "sg:postcode":"6616",
    "sg:province":"Ticino",
    "wof:name":"Olindo Vittori Impresa Di Pittura",
    "wof:placetype":"venue"
},
  "geometry": {"coordinates":[8.7507324219,46.1770553589],"type":"Point"}
}