{
  "type": "Feature",
  "properties": {
    "iso:country":"CH",
    "sg:address":"Bernstrasse 283",
    "sg:city":"Rothrist",
    "sg:orig_category":"G\u00fcterbef\u00f6rderung im Strassenverkehr",
    "sg:phone":"+41 79 211 57 88",
    "sg:postcode":"4852",
    "sg:province":"Aargau",
    "wof:name":"Habegger-transporte Ag",
    "wof:placetype":"venue"
},
  "geometry": {"coordinates":[7.8562941551,47.2933654785],"type":"Point"}
}