{
  "type": "Feature",
  "properties": {
    "addr:full":"Reverdil Avenue 14 1260 Nyon Case Postale 2622 Mont-sur-lausanne Vaud 1052",
    "addr:postcode":"1260;2622 mont-sur-lausanne;1052",
    "addr:street":"Avenue 14;Postale",
    "iso:country":"CH",
    "sg:address":"Reverdil Avenue 14 1260 Nyon Case Postale 2622",
    "sg:city":"Mont-sur-lausanne",
    "sg:orig_category":"Datenverarbeitungsdienste Herstellung von Radio U Fernsehger\u00e4ten sowie phono U videotechnischen Ger\u00e4",
    "sg:phone":"+41 22 362 26 26",
    "sg:postcode":"1052",
    "sg:province":"Vaud",
    "wof:name":"Telindus Networks Sa, Succursale De Le Mont-sur-lausanne",
    "wof:placetype":"venue"
},
  "geometry": {"coordinates":[6.232134,46.380848],"type":"Point"}
}