{
  "type": "Feature",
  "properties": {
    "iso:country":"CH",
    "sg:address":"Mi\u00e8ge Route De 1",
    "sg:city":"Sierre",
    "sg:orig_category":"Elektroinstallation",
    "sg:phone":"+41 27 455 16 53",
    "sg:postcode":"3960",
    "sg:province":"Valais",
    "wof:name":"Electrosa-rossier-vocat Sa, Sierre Entreprise G\u00e9n\u00e9rale D'\u00e9lectricit\u00e9",
    "wof:placetype":"venue"
},
  "geometry": {"coordinates":[7.5306549072,46.2924041748],"type":"Point"}
}