{
  "type": "Feature",
  "properties": {
    "iso:country":"CH",
    "sg:address":"Wilerstrasse 71",
    "sg:city":"Flawil",
    "sg:orig_category":"Bau U Wohngenossenschaften",
    "sg:phone":"+41 79 350 22 04",
    "sg:postcode":"9230",
    "sg:province":"St. Gallen",
    "wof:name":"Casa Libera Sg,lib.baugen. C/o Seiz Haus-& Industrietech.",
    "wof:placetype":"venue"
},
  "geometry": {"coordinates":[9.183526,47.415276],"type":"Point"}
}