{
  "type": "Feature",
  "properties": {
    "iso:country":"CH",
    "sg:address":"Ringstrasse 7",
    "sg:city":"Ermatingen",
    "sg:orig_category":"Druck ohne Zeitungsdruck Offsetdruck",
    "sg:phone":"+41 71 664 21 82",
    "sg:postcode":"8272",
    "sg:province":"Thurgau",
    "wof:name":"Couvert Druck Zurlinden Ag",
    "wof:placetype":"venue"
},
  "geometry": {"coordinates":[9.0771417618,47.6667518616],"type":"Point"}
}