{
  "type": "Feature",
  "properties": {
    "iso:country":"CH",
    "sg:address":"H\u00fcnenbergerstrasse 49c",
    "sg:city":"Cham",
    "sg:orig_category":"Handelsvermittlung U Grosshandel Herstellung von elektrischen Lampen U Leuchten",
    "sg:phone":"+41 41 780 74 83",
    "sg:postcode":"6330",
    "sg:province":"Zug",
    "wof:name":"Colux H\u00fcbscher",
    "wof:placetype":"venue"
},
  "geometry": {"coordinates":[8.4476242065,47.1799545288],"type":"Point"}
}