{
  "type": "Feature",
  "properties": {
    "iso:country":"CH",
    "sg:address":"Oberdorf 50",
    "sg:city":"Hellikon",
    "sg:orig_category":"Herstellung von Karosserien U Anh\u00e4ngern",
    "sg:phone":"+41 61 871 06 61",
    "sg:postcode":"4316",
    "sg:province":"Aargau",
    "wof:name":"Willi Waldmeier",
    "wof:placetype":"venue"
},
  "geometry": {"coordinates":[7.918202877,47.5086975098],"type":"Point"}
}