{
  "type": "Feature",
  "properties": {
    "iso:country":"CH",
    "sg:address":"P\u00e9rolles Boulevard De 34",
    "sg:city":"Fribourg",
    "sg:orig_category":"Unclassifiable Establishments",
    "sg:phone":"+41 26 322 10 24",
    "sg:postcode":"1700",
    "sg:province":"Fribourg",
    "wof:name":"Nyctis Holding S.a.",
    "wof:placetype":"venue"
},
  "geometry": {"coordinates":[7.1536831856,46.8037452698],"type":"Point"}
}