{
  "type": "Feature",
  "properties": {
    "iso:country":"CH",
    "sg:address":"Grand-st-bernard Avenue 74",
    "sg:city":"Martigny",
    "sg:orig_category":"Detailhandel mit Textilien",
    "sg:phone":"+41 27 722 26 50",
    "sg:postcode":"1920",
    "sg:province":"Valais",
    "wof:name":"Collection Alchi, Ducrey Rhoona",
    "wof:placetype":"venue"
},
  "geometry": {"coordinates":[7.0688090324,46.0969924927],"type":"Point"}
}