{
  "type": "Feature",
  "properties": {
    "addr:full":"Hintergasse 38 Elgg Z\u00fcrich 8353",
    "addr:housenumber":"38",
    "addr:postcode":"8353",
    "addr:street":"Hintergasse",
    "iso:country":"CH",
    "sg:address":"Hintergasse 38",
    "sg:city":"Elgg",
    "sg:orig_category":"Bauschreinerei Herstellung von Konstruktionsteilen, Fertigbauteilen U Ausbauelementen aus Holz",
    "sg:phone":"+41 52 364 20 41",
    "sg:postcode":"8353",
    "sg:province":"Z\u00fcrich",
    "wof:name":"Bruggmann Ag",
    "wof:placetype":"venue"
},
  "geometry": {"coordinates":[8.868834,47.488766],"type":"Point"}
}