{
  "type": "Feature",
  "properties": {
    "iso:country":"CH",
    "sg:address":"Herrenweg 995",
    "sg:city":"Meilen",
    "sg:classifiers":[
        {
            "category":"Real Estate",
            "subcategory":"Architect",
            "type":"Services"
        }
    ],
    "sg:phone":"+41 19237925",
    "sg:postcode":"8706",
    "sg:province":"Z\u00fcrich",
    "sg:tags":[
        "work",
        "developing"
    ],
    "wof:name":"Bv-control Ag",
    "wof:placetype":"venue"
},
  "geometry": {"coordinates":[8.6796751022,47.2857780457],"type":"Point"}
}