{
  "type": "Feature",
  "properties": {
    "iso:country":"CH",
    "sg:address":"Vogelbuckstrasse 37 8307 Effretikon. Postfach",
    "sg:city":"Effretikon",
    "sg:orig_category":"Reinigungsgewerbe",
    "sg:postcode":"8307",
    "sg:province":"Z\u00fcrich",
    "wof:name":"Mirka Reinigungen Di Grazia",
    "wof:placetype":"venue"
},
  "geometry": {"coordinates":[8.6843767166,47.4346351624],"type":"Point"}
}