{
  "type": "Feature",
  "properties": {
    "iso:country":"CH",
    "sg:address":"Rathausgasse 5",
    "sg:city":"Baden",
    "sg:classifiers":[
        {
            "category":"Restaurant",
            "type":"Food & Drink"
        }
    ],
    "sg:phone":"+41 56 222 85 25",
    "sg:postcode":"5400",
    "sg:province":"Aargau",
    "wof:name":"Restaurant Roter Turm",
    "wof:placetype":"venue"
},
  "geometry": {"coordinates":[8.3085441589,47.4727210999],"type":"Point"}
}