{
  "type": "Feature",
  "properties": {
    "iso:country":"CH",
    "sg:address":"Kirchstrasse 3792 Saanen. Postfach",
    "sg:city":"Gstaad",
    "sg:orig_category":"Allgemeiner Hoch U Tiefbau",
    "sg:postcode":"3780",
    "sg:province":"Bern",
    "wof:name":"B\u00fcro F\u00fcr Bauleitungen, Robert Stutz",
    "wof:placetype":"venue"
},
  "geometry": {"coordinates":[7.259283,46.490665],"type":"Point"}
}