{
  "type": "Feature",
  "properties": {
    "iso:country":"CH",
    "sg:address":"6873",
    "sg:city":"Corteglia",
    "sg:orig_category":"Datenbanken Softwareentwicklung U beratung",
    "sg:phone":"+41 91 646 86 45",
    "sg:postcode":"6873",
    "sg:province":"Ticino",
    "wof:name":"Sistec Informatica Sagl",
    "wof:placetype":"venue"
},
  "geometry": {"coordinates":[8.99469,45.861839],"type":"Point"}
}