{
  "type": "Feature",
  "properties": {
    "iso:country":"CH",
    "sg:address":"B\u00e4umlihofstrasse 146",
    "sg:city":"Basel",
    "sg:orig_category":"Fachdetailhandel mit pharmazeutischen Produkten Grosshandel mit sonstigen Nahrungsmitteln",
    "sg:phone":"+41 61 601 14 28",
    "sg:postcode":"4058",
    "sg:province":"Basel-Stadt",
    "wof:name":"B\u00e4umlihof Apotheke Ag",
    "wof:placetype":"venue"
},
  "geometry": {"coordinates":[7.6189651489,47.565662384],"type":"Point"}
}