{
  "type": "Feature",
  "properties": {
    "iso:country":"CH",
    "sg:address":"7064",
    "sg:city":"Tschiertschen",
    "sg:classifiers":[
        {
            "category":"Travel",
            "subcategory":"Hotels & Motels",
            "type":"Entertainment"
        }
    ],
    "sg:postcode":"7064",
    "sg:province":"Graubunden",
    "sg:tags":[
        "hotels",
        "mit",
        "restaurant"
    ],
    "wof:name":"Caviezel Reto",
    "wof:placetype":"venue"
},
  "geometry": {"coordinates":[9.8055782318,46.9113388062],"type":"Point"}
}