{
  "type": "Feature",
  "properties": {
    "iso:country":"CH",
    "sg:address":"Zugerstrasse 127",
    "sg:city":"W\u00e4denswil",
    "sg:orig_category":"Sportvereine Turnen",
    "sg:postcode":"8820",
    "sg:province":"Z\u00fcrich",
    "wof:name":"Turnverein Satus",
    "wof:placetype":"venue"
},
  "geometry": {"coordinates":[8.6538562775,47.2338371277],"type":"Point"}
}