{
  "type": "Feature",
  "properties": {
    "addr:full":"Montezillon Montmollin 2205",
    "addr:postcode":"2205",
    "addr:street":"Montmollin",
    "iso:country":"CH",
    "sg:address":"Montezillon",
    "sg:city":"Montmollin",
    "sg:orig_category":"Bauingenieurb\u00fcros allgemein Ingenieurb\u00fcros Umwelttechnik and \u00d6kologie",
    "sg:phone":"+41 32 731 53 53",
    "sg:postcode":"2205",
    "wof:name":"Bernard Matthey Ing\u00e9nieurs-conseils Sa",
    "wof:placetype":"venue"
},
  "geometry": {"coordinates":[6.798516,46.988811],"type":"Point"}
}