{
  "type": "Feature",
  "properties": {
    "iso:country":"CH",
    "sg:address":"M\u00fcnsterberg 14",
    "sg:city":"Basel",
    "sg:orig_category":"Detailhandel mit Schuhen Herstellung von Schuhen",
    "sg:phone":"+41 61 271 24 36",
    "sg:postcode":"4051",
    "sg:province":"Basel-Stadt",
    "wof:name":"M\u00fcki Chaussures D' Enfants K\u00fchner Fischer Gabriele",
    "wof:placetype":"venue"
},
  "geometry": {"coordinates":[7.5913448334,47.5555496216],"type":"Point"}
}