{
  "type": "Feature",
  "properties": {
    "iso:country":"CH",
    "sg:address":"St. Alban-vorstadt 90 4052 Basel. Postfach",
    "sg:city":"Basel",
    "sg:orig_category":"Grosshandel mit chemischen Erzeugnissen",
    "sg:phone":"+41 32 351 32 32",
    "sg:postcode":"4002",
    "sg:province":"Basel-Stadt",
    "wof:name":"Morena Foam Ag",
    "wof:placetype":"venue"
},
  "geometry": {"coordinates":[7.3590488434,47.1430397034],"type":"Point"}
}