{
  "type": "Feature",
  "properties": {
    "addr:full":"V\u00f6geliacher 4 B\u00fclach Z\u00fcrich 8180",
    "addr:housenumber":"4",
    "addr:postcode":"8180",
    "addr:street":"Voegeliacher;Zuerich",
    "iso:country":"CH",
    "sg:address":"V\u00f6geliacher 4",
    "sg:city":"B\u00fclach",
    "sg:orig_category":"Bau U Wohngenossenschaften",
    "sg:postcode":"8180",
    "sg:province":"Z\u00fcrich",
    "wof:name":"Gen.alterswohnungen B\u00fclach",
    "wof:placetype":"venue"
},
  "geometry": {"coordinates":[8.546985,47.521511],"type":"Point"}
}