{
  "type": "Feature",
  "properties": {
    "addr:full":"Str\u00fcpfistrasse 3 Lungern Obwalden 6078",
    "addr:housenumber":"3",
    "addr:postcode":"6078",
    "addr:street":"Struepfistrasse",
    "iso:country":"CH",
    "sg:address":"Str\u00fcpfistrasse 3",
    "sg:city":"Lungern",
    "sg:orig_category":"Dachdeckerei",
    "sg:phone":"+41 71 244 87 27",
    "sg:postcode":"6078",
    "sg:province":"Obwalden",
    "wof:name":"Jakob Stark Bedachungsgesch\u00e4ft",
    "wof:placetype":"venue"
},
  "geometry": {"coordinates":[9.383168,47.430584],"type":"Point"}
}