{
  "type": "Feature",
  "properties": {
    "iso:country":"CH",
    "sg:address":"3360",
    "sg:city":"Herzogenbuchsee",
    "sg:orig_category":"Wirtschafts- and Arbeitgeberverb\u00e4nde",
    "sg:phone":"+41 52 233 42 44",
    "sg:postcode":"3360",
    "sg:province":"Bern",
    "wof:name":"Verkauf Schweiz Sektion Winterthur",
    "wof:placetype":"venue"
},
  "geometry": {"coordinates":[8.7607221603,47.4835586548],"type":"Point"}
}