{
  "type": "Feature",
  "properties": {
    "iso:country":"CH",
    "sg:address":"Spisergasse 6",
    "sg:city":"St.gallen",
    "sg:orig_category":"RESTAURANTS: TEA-ROOMS",
    "sg:phone":"+41 71 223 73 03",
    "sg:postcode":"9000",
    "sg:province":"St. Gallen",
    "wof:name":"Picstop Kubli",
    "wof:placetype":"venue"
},
  "geometry": {"coordinates":[9.3768939972,47.4247283936],"type":"Point"}
}