{
  "type": "Feature",
  "properties": {
    "iso:country":"CH",
    "sg:address":"Egglistrasse Chalet Erika 3780 Gruben B. Gstaad. Postfach",
    "sg:city":"Gstaad",
    "sg:orig_category":"Satzherstellung U Reproduktion",
    "sg:phone":"+41 2385036",
    "sg:postcode":"3780",
    "sg:province":"Bern",
    "wof:name":"Typo Graf",
    "wof:placetype":"venue"
},
  "geometry": {"coordinates":[8.7834348679,47.3666038513],"type":"Point"}
}