{
  "type": "Feature",
  "properties": {
    "iso:country":"CH",
    "sg:address":"Weststrasse 133",
    "sg:city":"Winterthur",
    "sg:orig_category":"Sportvereine Sch\u00fctzen",
    "sg:phone":"+41 52 222 49 99",
    "sg:postcode":"8408",
    "sg:province":"Z\u00fcrich",
    "wof:name":"Feldsch\u00fctzen.veltheim",
    "wof:placetype":"venue"
},
  "geometry": {"coordinates":[8.704829216,47.5098762512],"type":"Point"}
}