{
  "type": "Feature",
  "properties": {
    "addr:full":"Haslifeldweg 15 Oberdiessbach Bern 3672",
    "addr:housenumber":"15",
    "addr:postcode":"3672",
    "addr:street":"Haslifeldweg",
    "iso:country":"CH",
    "sg:address":"Haslifeldweg 15",
    "sg:city":"Oberdiessbach",
    "sg:orig_category":"Blumen U Zierpflanzenbau",
    "sg:phone":"+41 31 771 05 38",
    "sg:postcode":"3672",
    "sg:province":"Bern",
    "wof:name":"G\u00e4rtnerei Mathys & Co",
    "wof:placetype":"venue"
},
  "geometry": {"coordinates":[7.625836,46.847439],"type":"Point"}
}