{
  "type": "Feature",
  "properties": {
    "iso:country":"CH",
    "sg:address":"Burgfelderstrasse 16",
    "sg:city":"Burgdorf",
    "sg:orig_category":"Erschliessung von Grundst\u00fccken",
    "sg:postcode":"3400",
    "sg:province":"Bern",
    "wof:name":"Genossenschaft Eigenheim Gesang-verbindung Technikum Burgdorf",
    "wof:placetype":"venue"
},
  "geometry": {"coordinates":[7.6270961761,47.0519294739],"type":"Point"}
}