{
  "type": "Feature",
  "properties": {
    "iso:country":"CH",
    "sg:address":"Fliederweg 6",
    "sg:city":"Sutz",
    "sg:orig_category":"Architektur U Ingenieurb\u00fcros",
    "sg:phone":"+41 32 397 10 76",
    "sg:postcode":"2572",
    "sg:province":"Bern",
    "wof:name":"M\u00f6pa, Bartoli Leonardo",
    "wof:placetype":"venue"
},
  "geometry": {"coordinates":[7.214371,47.096558],"type":"Point"}
}