{
  "type": "Feature",
  "properties": {
    "iso:country":"CH",
    "sg:address":"Z\u00fcrcherstrasse 44",
    "sg:city":"Windisch",
    "sg:classifiers":[
        {
            "category":"Restaurant",
            "type":"Food & Drink"
        }
    ],
    "sg:phone":"+41 56 441 10 42",
    "sg:postcode":"5210",
    "sg:province":"Aargau",
    "wof:name":"Restaurant Zur Sonne",
    "wof:placetype":"venue"
},
  "geometry": {"coordinates":[8.2205667496,47.47838974],"type":"Point"}
}