{
  "type": "Feature",
  "properties": {
    "iso:country":"CH",
    "sg:address":"Triststrasse 15",
    "sg:city":"Chur",
    "sg:orig_category":"Handel mit Automobilen",
    "sg:phone":"+41 81237723",
    "sg:postcode":"7000",
    "sg:province":"Graubunden",
    "wof:name":"Ftc Exclusiv - Auto, Th\u00f6ni Franz",
    "wof:placetype":"venue"
},
  "geometry": {"coordinates":[9.5073690414,46.8453178406],"type":"Point"}
}