{
  "type": "Feature",
  "properties": {
    "iso:country":"CH",
    "sg:address":"Schlossstrasse 21",
    "sg:city":"Pratteln",
    "sg:orig_category":"Detailhandel mit Bekleidung Detailhandel mit Damenbekleidung",
    "sg:phone":"+41 55 240 16 06",
    "sg:postcode":"4133",
    "sg:province":"Basel-Landschaft",
    "wof:name":"W\u00f6rner Mode R\u00fcti Ag Modehaus & Papillon-boutique",
    "wof:placetype":"venue"
},
  "geometry": {"coordinates":[8.799845,47.326904],"type":"Point"}
}