{
  "type": "Feature",
  "properties": {
    "iso:country":"CH",
    "sg:address":"Angensteinerstrasse 28",
    "sg:city":"Basel",
    "sg:orig_category":"Fachdetailhandel in Verkaufsr\u00e4umen",
    "sg:postcode":"4052",
    "sg:province":"Basel-Stadt",
    "wof:name":"Einhorn Kunst & Video Ag",
    "wof:placetype":"venue"
},
  "geometry": {"coordinates":[7.6040158272,47.5492782593],"type":"Point"}
}