{
  "type": "Feature",
  "properties": {
    "iso:country":"CH",
    "sg:address":"G\u00fcterstrasse 21",
    "sg:city":"Sissach",
    "sg:orig_category":"Grosshandel mit sonstigen Gebrauchs U Verbrauchsg\u00fctern Grosshandel mit sonstigen Halbwaren",
    "sg:phone":"+41 61 971 77 00",
    "sg:postcode":"4450",
    "sg:province":"Basel-Landschaft",
    "wof:name":"Walter Bucherer Inter Papier Agentur Ipa",
    "wof:placetype":"venue"
},
  "geometry": {"coordinates":[7.8182878494,47.4616279602],"type":"Point"}
}