{
  "type": "Feature",
  "properties": {
    "iso:country":"CH",
    "sg:address":"Via Lambertenghi 8",
    "sg:city":"Lugano",
    "sg:orig_category":"Detailhandel mit B\u00fcchern, Zeitungen, Schreib U Papeteriewaren",
    "sg:phone":"+41 91 922 65 27",
    "sg:postcode":"6900",
    "sg:province":"Ticino",
    "wof:name":"Roll-matic Di Paltenghi Prisca",
    "wof:placetype":"venue"
},
  "geometry": {"coordinates":[8.958104,46.009804],"type":"Point"}
}