{
  "type": "Feature",
  "properties": {
    "iso:country":"CH",
    "sg:address":"Scherrat 20 7013 Domat/ems. Postfach",
    "sg:city":"Domat/ems",
    "sg:orig_category":"Berufsberatungen",
    "sg:phone":"+41 17615820",
    "sg:postcode":"7013",
    "sg:province":"Graubunden",
    "wof:name":"Berufsberatung F\u00fcr Jugendliche & Erwachsene",
    "wof:placetype":"venue"
},
  "geometry": {"coordinates":[8.454478,47.276993],"type":"Point"}
}