{
  "type": "Feature",
  "properties": {
    "iso:country":"CH",
    "sg:address":"Piazza Giuseppe Motta 15",
    "sg:city":"Ascona",
    "sg:classifiers":[
        {
            "category":"Travel",
            "subcategory":"Hotels & Motels",
            "type":"Entertainment"
        }
    ],
    "sg:phone":"+41 91 791 15 14",
    "sg:postcode":"6612",
    "sg:province":"Ticino",
    "sg:tags":[
        "hotels",
        "mit",
        "restaurant"
    ],
    "wof:name":"Albergo Elvezia",
    "wof:placetype":"venue"
},
  "geometry": {"coordinates":[8.7676534653,46.1545181274],"type":"Point"}
}