{
  "type": "Feature",
  "properties": {
    "iso:country":"CH",
    "sg:address":"Lorzenweidstr. 40 6330 Cham. Postfach",
    "sg:city":"Hagendorn",
    "sg:orig_category":"Detektivb\u00fcros U \u00dcberwachung",
    "sg:postcode":"6332",
    "sg:province":"Zug",
    "wof:name":"S.c.o. Levi",
    "wof:placetype":"venue"
},
  "geometry": {"coordinates":[9.0378389359,47.4079704285],"type":"Point"}
}