{
  "type": "Feature",
  "properties": {
    "iso:country":"CH",
    "sg:address":"Rue De La Promenande 21 Et Gra",
    "sg:city":"Bulle",
    "sg:orig_category":"Fachdetailhandel in Verkaufsr\u00e4umen",
    "sg:postcode":"1630",
    "sg:province":"Fribourg",
    "wof:name":"Fleur Andr\u00e9, Roulin Pascal",
    "wof:placetype":"venue"
},
  "geometry": {"coordinates":[7.0573811531,46.6186027527],"type":"Point"}
}