{
  "type": "Feature",
  "properties": {
    "iso:country":"CH",
    "sg:address":"Bachtobelstrasse 17",
    "sg:city":"Ebmatingen",
    "sg:orig_category":"Innendekorationsateliers",
    "sg:phone":"+41 19801543",
    "sg:postcode":"8123",
    "sg:province":"Z\u00fcrich",
    "wof:name":"Regula Widmer B\u00e4ttig Vorhang-atelier",
    "wof:placetype":"venue"
},
  "geometry": {"coordinates":[8.6396760941,47.3539924622],"type":"Point"}
}