{
  "type": "Feature",
  "properties": {
    "addr:full":"Dorfstrasse 1 Flumenthal Solothurn 4534",
    "addr:housenumber":"1",
    "addr:postcode":"4534",
    "addr:street":"Dorfstrasse",
    "iso:country":"CH",
    "sg:address":"Dorfstrasse 1",
    "sg:city":"Flumenthal",
    "sg:orig_category":"Allgemeiner Hoch U Tiefbau Maurerarbeiten",
    "sg:phone":"+41 32 637 11 93",
    "sg:postcode":"4534",
    "sg:province":"Solothurn",
    "wof:name":"Schlup-bau & Keramik Gmbh",
    "wof:placetype":"venue"
},
  "geometry": {"coordinates":[7.598516,47.235146],"type":"Point"}
}