{
  "type": "Feature",
  "properties": {
    "iso:country":"CH",
    "sg:address":"Stockenstrasse 19 9249 Algetshausen. Postfach",
    "sg:city":"Algetshausen",
    "sg:orig_category":"Herstellung von industriellen Prozesssteuerungsanlagen",
    "sg:phone":"+41 71 310 11 07",
    "sg:postcode":"9249",
    "sg:province":"St. Gallen",
    "wof:name":"Linzberger Elektronik",
    "wof:placetype":"venue"
},
  "geometry": {"coordinates":[9.3183517456,47.4242935181],"type":"Point"}
}