{
  "type": "Feature",
  "properties": {
    "iso:country":"CH",
    "sg:address":"Schulgasse 15",
    "sg:city":"Giebenach",
    "sg:orig_category":"Softwareentwicklung U beratung",
    "sg:phone":"+41 61 363 27 60",
    "sg:postcode":"4304",
    "sg:province":"Basel-Landschaft",
    "wof:name":"Visar Visual Arts Watzl",
    "wof:placetype":"venue"
},
  "geometry": {"coordinates":[7.7465848923,47.5237236023],"type":"Point"}
}