{
  "type": "Feature",
  "properties": {
    "iso:country":"CH",
    "sg:address":"Bahnhofstrasse 8 6260 Reiden. Postfach",
    "sg:city":"Reiden",
    "sg:orig_category":"Handelsvermittlung U Grosshandel Sonstiger Grosshandel",
    "sg:phone":"+41 21 847 11 00",
    "sg:postcode":"6260",
    "sg:province":"Luzern",
    "wof:name":"Furrer Toni Sa",
    "wof:placetype":"venue"
},
  "geometry": {"coordinates":[6.6639499664,46.5902061462],"type":"Point"}
}