{
  "type": "Feature",
  "properties": {
    "iso:country":"CH",
    "sg:address":"Eichtalstrasse 8634 Hombrechtikon. Postfach 500",
    "sg:city":"Hombrechtikon",
    "sg:orig_category":"Herstellung von Ger\u00e4ten der Elektrizit\u00e4tserzeugung, -verteilung u.\u00e4. -Herstellung von elektronischen",
    "sg:phone":"+41 55 264 20 20",
    "sg:postcode":"8634",
    "sg:province":"Z\u00fcrich",
    "wof:name":"Remsig Ag",
    "wof:placetype":"venue"
},
  "geometry": {"coordinates":[8.7739601135,47.2492866516],"type":"Point"}
}