{
  "type": "Feature",
  "properties": {
    "iso:country":"CH",
    "sg:address":"Via Cantonale 22",
    "sg:city":"Lugano",
    "sg:classifiers":[
        {
            "category":"Building & Trades",
            "subcategory":"Construction",
            "type":"Services"
        }
    ],
    "sg:phone":"+41 91 911 98 00",
    "sg:postcode":"6900",
    "sg:province":"Ticino",
    "sg:tags":[
        "installation",
        "air-conditioning",
        "system"
    ],
    "wof:name":"Climatic Di Lugano Sa",
    "wof:placetype":"venue"
},
  "geometry": {"coordinates":[8.950659,46.009251],"type":"Point"}
}