{
  "type": "Feature",
  "properties": {
    "iso:country":"CH",
    "sg:address":"Rotwandstrasse 68",
    "sg:city":"Z\u00fcrich",
    "sg:classifiers":[
        {
            "category":"Professional",
            "subcategory":"Employment Agencies",
            "type":"Services"
        }
    ],
    "sg:phone":"+41 55 410 61 71",
    "sg:postcode":"8004",
    "sg:province":"Z\u00fcrich",
    "sg:tags":[
        "personal",
        "u",
        "stellenvermittlung"
    ],
    "wof:name":"Mc Beratung",
    "wof:placetype":"venue"
},
  "geometry": {"coordinates":[8.778427124,47.2024307251],"type":"Point"}
}