{
  "type": "Feature",
  "properties": {
    "iso:country":"CH",
    "sg:address":"Jetzikofen",
    "sg:city":"Kirchlindach",
    "sg:orig_category":"Non-Classified Establishments",
    "sg:postcode":"3038",
    "sg:province":"Bern",
    "wof:name":"Reitbetrieb S. Winterberger",
    "wof:placetype":"venue"
},
  "geometry": {"coordinates":[7.3958101273,47.0016899109],"type":"Point"}
}