{
  "type": "Feature",
  "properties": {
    "iso:country":"CH",
    "sg:address":"1974",
    "sg:city":"Arbaz",
    "sg:orig_category":"Vermietung U Verpachtung von eigenen Immobilien",
    "sg:phone":"+41 27 398 30 50",
    "sg:postcode":"1974",
    "sg:province":"Valais",
    "wof:name":"Francey Roland, Immobilier",
    "wof:placetype":"venue"
},
  "geometry": {"coordinates":[7.3841748238,46.273109436],"type":"Point"}
}