{
  "type": "Feature",
  "properties": {
    "iso:country":"CH",
    "sg:address":"J\u00e4gerweg 4",
    "sg:city":"Grabs",
    "sg:orig_category":"Mechanische Werkst\u00e4tten",
    "sg:phone":"+41 81 771 29 30",
    "sg:postcode":"9472",
    "sg:province":"St. Gallen",
    "wof:name":"Ferdinand Gabathuler Mechanische Werkst\u00e4tte",
    "wof:placetype":"venue"
},
  "geometry": {"coordinates":[9.4498786926,47.1800079346],"type":"Point"}
}