{
  "type": "Feature",
  "properties": {
    "iso:country":"CH",
    "sg:address":"Unterfeldstrasse 19",
    "sg:city":"Oberkulm",
    "sg:orig_category":"Werbeagenturen",
    "sg:phone":"+41 62 776 34 32",
    "sg:postcode":"5727",
    "sg:province":"Aargau",
    "wof:name":"Ako",
    "wof:placetype":"venue"
},
  "geometry": {"coordinates":[8.1164541245,47.3016319275],"type":"Point"}
}