{
  "type": "Feature",
  "properties": {
    "iso:country":"CH",
    "sg:address":"Im Letten 1",
    "sg:city":"Oberhasli",
    "sg:orig_category":"Geb\u00e4ude, Wohnungsreinigung",
    "sg:phone":"+41 18500608",
    "sg:postcode":"8156",
    "sg:province":"Z\u00fcrich",
    "wof:name":"Vittorio & Daniela Tamburiello Reinigungsinstitut",
    "wof:placetype":"venue"
},
  "geometry": {"coordinates":[8.504360199,47.466129303],"type":"Point"}
}