{
  "type": "Feature",
  "properties": {
    "iso:country":"CH",
    "sg:address":"Bruggweg 18",
    "sg:city":"Dornach",
    "sg:orig_category":"Wirtschaftsverb\u00e4nde Industrie, Handel and Gewerbe",
    "sg:phone":"+41 61 701 37 84",
    "sg:postcode":"4143",
    "sg:province":"Solothurn",
    "wof:name":"Vereinigung Schweizerischer Textilfachlehrer",
    "wof:placetype":"venue"
},
  "geometry": {"coordinates":[7.609773159,47.4874839783],"type":"Point"}
}