{
  "type": "Feature",
  "properties": {
    "iso:country":"CH",
    "sg:address":"G\u00fcrtelstrasse 24",
    "sg:city":"Chur",
    "sg:orig_category":"Diskotheken, Dancings, Night Clubs",
    "sg:phone":"+41 81 284 45 89",
    "sg:postcode":"7000",
    "sg:province":"Graubunden",
    "wof:name":"Night Club Golden Life",
    "wof:placetype":"venue"
},
  "geometry": {"coordinates":[9.5271730423,46.8534240723],"type":"Point"}
}