{
  "type": "Feature",
  "properties": {
    "iso:country":"CH",
    "sg:address":"Rabius",
    "sg:city":"Sumvitg",
    "sg:orig_category":"Bau von Strassen, Sportanlagen U Bahnverkehrsstrecken",
    "sg:phone":"+41 81 936 35 00",
    "sg:postcode":"7175",
    "sg:province":"Graubunden",
    "wof:name":"Candinas Sa",
    "wof:placetype":"venue"
},
  "geometry": {"coordinates":[8.935793,46.72736],"type":"Point"}
}