{
  "type": "Feature",
  "properties": {
    "iso:country":"CH",
    "sg:address":"Stettbachstrasse 34",
    "sg:city":"D\u00fcbendorf",
    "sg:orig_category":"Allgemeiner Hoch U Tiefbau Allgemeiner Hochbau",
    "sg:phone":"+41 18211256",
    "sg:postcode":"8600",
    "sg:province":"Z\u00fcrich",
    "wof:name":"Piai L. Ag, Bauunternehmung",
    "wof:placetype":"venue"
},
  "geometry": {"coordinates":[8.59708,47.394058],"type":"Point"}
}