{
  "type": "Feature",
  "properties": {
    "iso:country":"CH",
    "sg:address":"Bankstrasse 17",
    "sg:city":"Uster",
    "sg:orig_category":"Zahntechnische Laboratorien",
    "sg:phone":"+41 19416330",
    "sg:postcode":"8610",
    "sg:province":"Z\u00fcrich",
    "wof:name":"J\u00fcrg Gass Praxis F\u00fcr Zahnprothetik",
    "wof:placetype":"venue"
},
  "geometry": {"coordinates":[8.716427803,47.3511238098],"type":"Point"}
}