{
  "type": "Feature",
  "properties": {
    "iso:country":"CH",
    "sg:address":"Dorf",
    "sg:city":"Buttisholz",
    "sg:orig_category":"RESTAURANTS: TEA-ROOMS",
    "sg:phone":"+41 55 210 21 25",
    "sg:postcode":"6018",
    "sg:province":"Luzern",
    "wof:name":"Rest. Zeughaus, Engelmann C.",
    "wof:placetype":"venue"
},
  "geometry": {"coordinates":[8.8253526688,47.2279243469],"type":"Point"}
}