{
  "type": "Feature",
  "properties": {
    "addr:full":"Prarreyer Verseg\u00e8res Valais 1947",
    "addr:postcode":"1947",
    "iso:country":"CH",
    "sg:address":"Prarreyer",
    "sg:city":"Verseg\u00e8res",
    "sg:orig_category":"Bauschreinerei Herstellung von Konstruktionsteilen, Fertigbauteilen U Ausbauelementen aus Holz",
    "sg:phone":"+41 27 776 11 80",
    "sg:postcode":"1947",
    "sg:province":"Valais",
    "wof:name":"Baillifard Maurice & Fils Sa",
    "wof:placetype":"venue"
},
  "geometry": {"coordinates":[7.22683,46.067379],"type":"Point"}
}