{
  "type": "Feature",
  "properties": {
    "iso:country":"CH",
    "sg:address":"Seefeldstrasse 25 8008 Z\u00fcrich. Postfach",
    "sg:city":"Z\u00fcrich",
    "sg:orig_category":"Interessenvertretungen",
    "sg:postcode":"8001",
    "sg:province":"Z\u00fcrich",
    "wof:name":"Stiftung F\u00fcr Wissenschaftliche, Systematische Forschungen Auf Dem Gebiete Des Stahlbaus",
    "wof:placetype":"venue"
},
  "geometry": {"coordinates":[8.549323082,47.3638381958],"type":"Point"}
}