{
  "type": "Feature",
  "properties": {
    "iso:country":"CH",
    "sg:address":"Sandhofstrasse 7",
    "sg:city":"W\u00e4denswil",
    "sg:orig_category":"Advokaturb\u00fcros",
    "sg:phone":"+41 17808110",
    "sg:postcode":"8820",
    "sg:province":"Z\u00fcrich",
    "wof:name":"Dr.franz Breitenmoser Advokaturb\u00fcro",
    "wof:placetype":"venue"
},
  "geometry": {"coordinates":[8.671408,47.220039],"type":"Point"}
}