{
  "type": "Feature",
  "properties": {
    "iso:country":"CH",
    "sg:address":"Rue Du Rh\u00f4ne 114",
    "sg:city":"Gen\u00e8ve",
    "sg:orig_category":"Herstellung von Metallerzeugnissen ohne Maschinenbau Herstellung von Schmuck, Gold U Silberschmiedwa",
    "sg:phone":"+41 32 341 66 67",
    "sg:postcode":"1204",
    "sg:province":"Gen\u00e8ve",
    "wof:name":"Bambi Bracelets Romerio Alin",
    "wof:placetype":"venue"
},
  "geometry": {"coordinates":[7.2764248848,47.1472702026],"type":"Point"}
}