{
  "type": "Feature",
  "properties": {
    "iso:country":"CH",
    "sg:address":"Bielstrasse 1",
    "sg:city":"Worben",
    "sg:orig_category":"Detailhandel mit Waren verschiedener Art, Hauptrichtung Nahrungsmittel Grosshandel mit Nahrungsmitte",
    "sg:phone":"+41 32 384 55 55",
    "sg:postcode":"3252",
    "sg:province":"Bern",
    "wof:name":"Gafner & Van Vrijaldenhoven",
    "wof:placetype":"venue"
},
  "geometry": {"coordinates":[7.2952208519,47.102935791],"type":"Point"}
}