{
  "type": "Feature",
  "properties": {
    "iso:country":"CH",
    "sg:address":"Bleicherweg 10 8022 Z\u00fcrich. Postfach",
    "sg:city":"Z\u00fcrich",
    "sg:orig_category":"Interessenvertretungen",
    "sg:postcode":"8022",
    "sg:province":"Z\u00fcrich",
    "wof:name":"Vereinigung Von Forfaitierenden Instituten In Der Schweiz",
    "wof:placetype":"venue"
},
  "geometry": {"coordinates":[8.5368833542,47.3685417175],"type":"Point"}
}