{
  "type": "Feature",
  "properties": {
    "iso:country":"CH",
    "sg:address":"Rue Du Bourg 30 3960 Sierre Case Postale 239",
    "sg:city":"Sierre",
    "sg:orig_category":"Interessenvertretungen Museen",
    "sg:phone":"+41 27 455 16 03",
    "sg:postcode":"3960",
    "sg:province":"Valais",
    "wof:name":"Fondation Rilke Rainer-maria",
    "wof:placetype":"venue"
},
  "geometry": {"coordinates":[7.5369467735,46.2941017151],"type":"Point"}
}