{
  "type": "Feature",
  "properties": {
    "iso:country":"CH",
    "sg:address":"Aarburgerstrasse 29",
    "sg:city":"Zofingen",
    "sg:orig_category":"G\u00fcterbef\u00f6rderung im Strassenverkehr",
    "sg:phone":"+41 21 968 31 01",
    "sg:postcode":"4800",
    "sg:province":"Aargau",
    "wof:name":"Glur Transports Sa",
    "wof:placetype":"venue"
},
  "geometry": {"coordinates":[6.9333348274,46.3521118164],"type":"Point"}
}