{
  "type": "Feature",
  "properties": {
    "iso:country":"CH",
    "sg:address":"Allmendstrasse 32",
    "sg:city":"Gunzgen",
    "sg:orig_category":"Non-Classified Establishments",
    "sg:postcode":"4617",
    "sg:province":"Solothurn",
    "wof:name":"Turmgarage Studer Gmbh",
    "wof:placetype":"venue"
},
  "geometry": {"coordinates":[7.8385639191,47.3074684143],"type":"Point"}
}