{
  "type": "Feature",
  "properties": {
    "iso:country":"CH",
    "sg:address":"Route Du Jorat 146 Vers-chez",
    "sg:city":"Lausanne",
    "sg:orig_category":"Gesundheitswesen",
    "sg:phone":"+41 21 784 35 50",
    "sg:postcode":"1000",
    "sg:province":"Vaud",
    "wof:name":"Plan Bien-\u00eatre, Egger Cosette",
    "wof:placetype":"venue"
},
  "geometry": {"coordinates":[6.6947751045,46.5545883179],"type":"Point"}
}