{
  "type": "Feature",
  "properties": {
    "iso:country":"CH",
    "sg:address":"Quellenweg 1",
    "sg:city":"Wabern",
    "sg:orig_category":"Detailhandel mit Damenbekleidung",
    "sg:phone":"+41 31 964 06 60",
    "sg:postcode":"3084",
    "sg:province":"Bern",
    "wof:name":"Love Brautmode Bern",
    "wof:placetype":"venue"
},
  "geometry": {"coordinates":[7.453195,46.927734],"type":"Point"}
}