{
  "type": "Feature",
  "properties": {
    "iso:country":"CH",
    "sg:address":"Z\u00fcrichstrasse 37",
    "sg:city":"Luzern",
    "sg:orig_category":"Einbau von Schreinerwaren Herstellung von K\u00fcchenm\u00f6beln",
    "sg:phone":"+41 41 410 56 56",
    "sg:postcode":"6004",
    "sg:province":"Luzern",
    "wof:name":"Estermann K\u00fcchenatelier Ag",
    "wof:placetype":"venue"
},
  "geometry": {"coordinates":[8.309469223,47.0581283569],"type":"Point"}
}