{
  "type": "Feature",
  "properties": {
    "iso:country":"CH",
    "sg:address":"Altenburgstrasse 22",
    "sg:city":"Wettingen",
    "sg:orig_category":"Interessenvertretungen",
    "sg:postcode":"5430",
    "sg:province":"Aargau",
    "wof:name":"Schweiz. Berufsverband Der Juwelenfasser (sbvj)",
    "wof:placetype":"venue"
},
  "geometry": {"coordinates":[8.3145341873,47.4661178589],"type":"Point"}
}