{
  "type": "Feature",
  "properties": {
    "iso:country":"CH",
    "sg:address":"Jolissaint Rue Pierre- 37",
    "sg:city":"St-imier",
    "sg:orig_category":"Gesundheitswesen",
    "sg:postcode":"2610",
    "sg:province":"Bern",
    "wof:name":"P.p. Physio-ost\u00e9o S\u00e0rl",
    "wof:placetype":"venue"
},
  "geometry": {"coordinates":[6.9944829941,47.1521987915],"type":"Point"}
}