{
  "type": "Feature",
  "properties": {
    "iso:country":"CH",
    "sg:address":"Bern-z\u00fcrich Strasse 40",
    "sg:city":"Langenthal",
    "sg:orig_category":"Herstellung von Ger\u00e4ten der Elektrizit\u00e4tserzeugung, -verteilung u.\u00e4. -Herstellung von elektrischen L",
    "sg:phone":"+41 62 916 70 50",
    "sg:postcode":"4900",
    "sg:province":"Bern",
    "wof:name":"Fluora Leuchten Ag",
    "wof:placetype":"venue"
},
  "geometry": {"coordinates":[7.7700800896,47.2221908569],"type":"Point"}
}