{
  "type": "Feature",
  "properties": {
    "iso:country":"CH",
    "sg:address":"B\u00e9guelin Place Roland 5",
    "sg:city":"Delsberg",
    "sg:orig_category":"Herstellung von sonstigen elektrischen Ausr\u00fcstungen",
    "sg:phone":"+41 79 474 25 60",
    "sg:postcode":"2800",
    "sg:province":"Jura",
    "wof:name":"Bussnes Line, Moleka Bofengene",
    "wof:placetype":"venue"
},
  "geometry": {"coordinates":[7.3430409431,47.3659248352],"type":"Point"}
}