{
  "type": "Feature",
  "properties": {
    "iso:country":"CH",
    "sg:address":"T\u00f6sstalstrasse 253",
    "sg:city":"Winterthur",
    "sg:orig_category":"Detailhandel mit Fahrr\u00e4dern Handel mit Motorr\u00e4dern, Teilen U Zubeh\u00f6r Instandhaltung U Reparatur von ",
    "sg:phone":"+41 52 242 31 76",
    "sg:postcode":"8405",
    "sg:province":"Z\u00fcrich",
    "wof:name":"Walter Wild 2 Rad-center",
    "wof:placetype":"venue"
},
  "geometry": {"coordinates":[8.7610740662,47.4834747314],"type":"Point"}
}