{
  "type": "Feature",
  "properties": {
    "iso:country":"CH",
    "sg:address":"Derri\u00e8re-chez-chappuis",
    "sg:city":"Corcelles-payerne",
    "sg:orig_category":"Herstellung von Mess U Kontrollinstrumenten U vorrichtungen Mechanische Werkst\u00e4tten",
    "sg:phone":"+41 21 845 68 02",
    "sg:postcode":"1562",
    "sg:province":"Vaud",
    "wof:name":"Rochat Jean-marc, M\u00e9canique De Pr\u00e9cision",
    "wof:placetype":"venue"
},
  "geometry": {"coordinates":[6.2358779907,46.6058235168],"type":"Point"}
}