{
  "type": "Feature",
  "properties": {
    "iso:country":"CH",
    "sg:address":"Wylerringstrasse 9 3014 Bern. Postfach 661",
    "sg:city":"Bern",
    "sg:orig_category":"Sanit\u00e4rinstallation U Spenglerei",
    "sg:phone":"+41 62 771 70 57",
    "sg:postcode":"3014",
    "sg:province":"Bern",
    "wof:name":"Spenglerei Zimmermann",
    "wof:placetype":"venue"
},
  "geometry": {"coordinates":[8.19231987,47.2619247437],"type":"Point"}
}