{
  "type": "Feature",
  "properties": {
    "iso:country":"CH",
    "sg:address":"Pau Champ Du 5",
    "sg:city":"Cort\u00e9bert",
    "sg:orig_category":"Handel mit Automobilteilen U Zubeh\u00f6r",
    "sg:phone":"+41 32 489 22 56",
    "sg:postcode":"2607",
    "sg:province":"Bern",
    "wof:name":"Loesch Daniel",
    "wof:placetype":"venue"
},
  "geometry": {"coordinates":[7.1067647934,47.1905899048],"type":"Point"}
}