{
  "type": "Feature",
  "properties": {
    "iso:country":"CH",
    "sg:address":"Kirchg\u00e4ssli 9",
    "sg:city":"Biel/bienne",
    "sg:orig_category":"Detailhandel mit Fleisch U Fleischwaren",
    "sg:phone":"+41 19401323",
    "sg:postcode":"2502",
    "sg:province":"Bern",
    "wof:name":"Ryffel, Rudolf.",
    "wof:placetype":"venue"
},
  "geometry": {"coordinates":[8.7090778351,47.3452835083],"type":"Point"}
}