{
  "type": "Feature",
  "properties": {
    "iso:country":"CH",
    "sg:address":"Rue De Lausanne 43",
    "sg:city":"Payerne",
    "sg:orig_category":"Massagestudios",
    "sg:phone":"+41 79 404 02 43",
    "sg:postcode":"1530",
    "sg:province":"Vaud",
    "wof:name":"Daniela Frei Sunshine-massagen",
    "wof:placetype":"venue"
},
  "geometry": {"coordinates":[8.7834758759,47.3680038452],"type":"Point"}
}