{
  "type": "Feature",
  "properties": {
    "iso:country":"CH",
    "sg:address":"5732",
    "sg:city":"Zetzwil",
    "sg:orig_category":"Landw. Genossenschaften Viehzucht",
    "sg:postcode":"5732",
    "sg:province":"Aargau",
    "wof:name":"Viehzuchtgenossenschaft",
    "wof:placetype":"venue"
},
  "geometry": {"coordinates":[8.1829795837,47.2510986328],"type":"Point"}
}