{
  "type": "Feature",
  "properties": {
    "iso:country":"CH",
    "sg:address":"Industriestrasse 3",
    "sg:city":"R\u00fcdtligen",
    "sg:orig_category":"Gewinnung von Kies U Sand",
    "sg:phone":"+41 34 413 13 76",
    "sg:postcode":"3422",
    "sg:province":"Bern",
    "wof:name":"Kiesindustrie Ag R\u00fcdtligen",
    "wof:placetype":"venue"
},
  "geometry": {"coordinates":[7.5636191368,47.0950775146],"type":"Point"}
}