{
  "type": "Feature",
  "properties": {
    "iso:country":"CH",
    "sg:address":"Via Marconi 2 6900 Lugano. Postfach Caselle Postale 2805",
    "sg:city":"Lugano",
    "sg:orig_category":"Aktivit\u00e4t der Bankinstitute Kreditinstitute ohne Spezialkreditinstitute",
    "sg:phone":"+41 91 912 58 58",
    "sg:postcode":"6901",
    "sg:province":"Ticino",
    "wof:name":"Barclays Bank (svizzera) Sa, Succursale Di Lugano",
    "wof:placetype":"venue"
},
  "geometry": {"coordinates":[8.95429,46.003887],"type":"Point"}
}