{
  "type": "Feature",
  "properties": {
    "iso:country":"CH",
    "sg:address":"Via Guisan 6",
    "sg:city":"Paradiso",
    "sg:orig_category":"Herstellung von sonstigen chemischen Erzeugnissen Pharmazeutische Industrie",
    "sg:phone":"+41 91 980 90 13",
    "sg:postcode":"6900",
    "sg:province":"Ticino",
    "wof:name":"Crosschem Intercontinental Company, Derbesi & Co.",
    "wof:placetype":"venue"
},
  "geometry": {"coordinates":[8.9463977814,45.9922637939],"type":"Point"}
}