{
  "type": "Feature",
  "properties": {
    "iso:country":"CH",
    "sg:address":"W\u00fclflingerstrasse 53 8400 Winterthur. Postfach 215",
    "sg:city":"Winterthur",
    "sg:classifiers":[
        {
            "category":"Restaurant",
            "type":"Food & Drink"
        }
    ],
    "sg:phone":"+41 62 893 12 66",
    "sg:postcode":"8407",
    "wof:name":"Restaurant Central",
    "wof:placetype":"venue"
},
  "geometry": {"coordinates":[8.1822299957,47.4161148071],"type":"Point"}
}