{
  "type": "Feature",
  "properties": {
    "iso:country":"CH",
    "sg:address":"Geiselfeldstrasse 3",
    "sg:city":"Gerlafingen",
    "sg:orig_category":"Herstellung von konfektionierten Textilwaren ohne Bekleidung",
    "sg:postcode":"4563",
    "sg:province":"Solothurn",
    "wof:name":"Alija Storen Gmbh",
    "wof:placetype":"venue"
},
  "geometry": {"coordinates":[7.5765018463,47.1703262329],"type":"Point"}
}