{
  "type": "Feature",
  "properties": {
    "iso:country":"CH",
    "sg:address":"Bahnhofstrasse 13",
    "sg:city":"Baar",
    "sg:orig_category":"Sonstiger Detailhandel nicht in Verkaufsr\u00e4umen",
    "sg:phone":"+41 41 769 33 33",
    "sg:postcode":"6340",
    "sg:province":"Zug",
    "wof:name":"Ricardo.ch Ag E-commerce, Auktionen, Shop",
    "wof:placetype":"venue"
},
  "geometry": {"coordinates":[8.5235738754,47.1951293945],"type":"Point"}
}