{
  "type": "Feature",
  "properties": {
    "iso:country":"CH",
    "sg:address":"Marktgasse 33",
    "sg:city":"Rheinfelden",
    "sg:orig_category":"Detailhandel mit Schuhen",
    "sg:phone":"+41 61 831 53 27",
    "sg:postcode":"4310",
    "sg:province":"Aargau",
    "wof:name":"Bata Schuh Ag",
    "wof:placetype":"venue"
},
  "geometry": {"coordinates":[7.7921509743,47.554977417],"type":"Point"}
}