{
  "type": "Feature",
  "properties": {
    "iso:country":"CH",
    "sg:address":"Lausanne Rue De 68",
    "sg:city":"Morges",
    "sg:orig_category":"Unternehmensberatung",
    "sg:phone":"+41 21 802 36 35",
    "sg:postcode":"1110",
    "sg:province":"Vaud",
    "wof:name":"Sycomore S\u00e0rl",
    "wof:placetype":"venue"
},
  "geometry": {"coordinates":[6.5080127716,46.5164146423],"type":"Point"}
}