{
  "type": "Feature",
  "properties": {
    "iso:country":"CH",
    "sg:address":"Lauchefeld 33",
    "sg:city":"Matzingen",
    "sg:orig_category":"Herstellung von Metallkonstruktionen Schlossereien",
    "sg:phone":"+41 52 376 30 90",
    "sg:postcode":"9548",
    "sg:province":"Thurgau",
    "wof:name":"Gasser Metallbau",
    "wof:placetype":"venue"
},
  "geometry": {"coordinates":[8.9333047867,47.5170936584],"type":"Point"}
}