{
  "type": "Feature",
  "properties": {
    "iso:country":"CH",
    "sg:address":"Blignoud",
    "sg:city":"Ayent",
    "sg:orig_category":"Instandhaltung U Reparatur von Automobilen",
    "sg:phone":"+41 27 398 37 47",
    "sg:postcode":"1966",
    "sg:province":"Valais",
    "wof:name":"Blanc Gino.",
    "wof:placetype":"venue"
},
  "geometry": {"coordinates":[7.3983302116,46.272190094],"type":"Point"}
}