{
  "type": "Feature",
  "properties": {
    "iso:country":"CH",
    "sg:address":"Rue Du Couchant 15",
    "sg:city":"Hermance",
    "sg:orig_category":"Interessenvertretungen Wohnheime",
    "sg:phone":"+41 22 751 13 31",
    "sg:postcode":"1248",
    "sg:province":"Gen\u00e8ve",
    "wof:name":"Maison De Convalescence De La Tour Regrouper Les Efforts B\u00e9n\u00e9voles En Vue L'exploit., L'animation Et L'entretien D'un \u00e9tablissement M\u00e9dical Priv\u00e9 Etc",
    "wof:placetype":"venue"
},
  "geometry": {"coordinates":[6.2457299232,46.3010253906],"type":"Point"}
}