{
  "type": "Feature",
  "properties": {
    "iso:country":"CH",
    "sg:address":"Gerbehof 115e",
    "sg:city":"D\u00fcrrenroth",
    "sg:orig_category":"Bauschreinerei Herstellung von M\u00f6beln verschiedener Art",
    "sg:phone":"+41 34 435 16 06",
    "sg:postcode":"3465",
    "sg:province":"Bern",
    "wof:name":"Bill & Schmid Gmbh",
    "wof:placetype":"venue"
},
  "geometry": {"coordinates":[7.782937,47.089497],"type":"Point"}
}