{
  "type": "Feature",
  "properties": {
    "iso:country":"CH",
    "sg:address":"Zelg",
    "sg:city":"Mamishaus",
    "sg:orig_category":"Detailhandel mit Radio U Fernsehger\u00e4ten Herstellung von Radio U Fernsehger\u00e4ten sowie phono U videote",
    "sg:phone":"+41 31 731 05 04",
    "sg:postcode":"3152",
    "sg:province":"Bern",
    "wof:name":"Toni Zahnd",
    "wof:placetype":"venue"
},
  "geometry": {"coordinates":[7.3641462326,46.8205718994],"type":"Point"}
}