{
  "type": "Feature",
  "properties": {
    "iso:country":"CH",
    "sg:address":"Falknisstrasse 11b",
    "sg:city":"Sargans",
    "sg:orig_category":"Fahrr\u00e4der and Zubeh\u00f6r Grosshandel Handel mit Motorr\u00e4dern, Teilen U Zubeh\u00f6r Instandhaltung U Reparatu",
    "sg:phone":"+41 32 843 04 04",
    "sg:postcode":"7320",
    "sg:province":"St. Gallen",
    "wof:name":"Motana Sa Motos & Scooters",
    "wof:placetype":"venue"
},
  "geometry": {"coordinates":[6.8632078171,46.9605751038],"type":"Point"}
}