{
  "type": "Feature",
  "properties": {
    "iso:country":"CH",
    "sg:address":"Menznauerstrasse 13 6110 Wolhusen. Postfach",
    "sg:city":"Wolhusen",
    "sg:orig_category":"Primarschulen",
    "sg:phone":"+41 41 492 66 39",
    "sg:postcode":"6110",
    "sg:province":"Luzern",
    "wof:name":"Primarschule",
    "wof:placetype":"venue"
},
  "geometry": {"coordinates":[8.073182106,47.0596656799],"type":"Point"}
}