{
  "type": "Feature",
  "properties": {
    "iso:country":"CH",
    "sg:address":"Madetswilerstrasse 18 8332 Russikon. Postfach 31",
    "sg:city":"Russikon",
    "sg:orig_category":"Detailhandel mit Metallwaren, Anstrichmitteln, Glaswaren, Bau U Heimwerkerbedarf G\u00fcterbef\u00f6rderung im",
    "sg:phone":"+41 21 625 34 45",
    "sg:postcode":"8332",
    "sg:province":"Z\u00fcrich",
    "wof:name":"Rollin Sa",
    "wof:placetype":"venue"
},
  "geometry": {"coordinates":[6.5837430954,46.5450897217],"type":"Point"}
}