{
  "type": "Feature",
  "properties": {
    "iso:country":"CH",
    "sg:address":"Seefeld 13",
    "sg:city":"Nottwil",
    "sg:orig_category":"Druckgewerbe Radio U Fernsehanstalten",
    "sg:phone":"+41 19296200",
    "sg:postcode":"6207",
    "sg:province":"Luzern",
    "wof:name":"Pmc Print Media Corporation",
    "wof:placetype":"venue"
},
  "geometry": {"coordinates":[8.7256679535,47.2735481262],"type":"Point"}
}