{
  "type": "Feature",
  "properties": {
    "iso:country":"CH",
    "sg:address":"Route De Berne 285",
    "sg:city":"Epalinges",
    "sg:classifiers":[
        {
            "category":"Travel",
            "subcategory":"Hotels & Motels",
            "type":"Entertainment"
        }
    ],
    "sg:phone":"+41 21 784 19 03",
    "sg:postcode":"1066",
    "sg:province":"Vaud",
    "sg:tags":[
        "hotels",
        "mit",
        "restaurant"
    ],
    "wof:name":"H\u00f4tel La Marmite",
    "wof:placetype":"venue"
},
  "geometry": {"coordinates":[6.6833248138,46.5551757812],"type":"Point"}
}