{
  "type": "Feature",
  "properties": {
    "iso:country":"CH",
    "sg:address":"Felixenweid 1",
    "sg:city":"M\u00fchlau",
    "sg:orig_category":"Mit Sport verbundene T\u00e4tigkeiten",
    "sg:phone":"+41 78 749 63 13",
    "sg:postcode":"5642",
    "sg:province":"Aargau",
    "wof:name":"Karat\u00e9 Club La Chaux-de-fonds Shintaikan",
    "wof:placetype":"venue"
},
  "geometry": {"coordinates":[6.8214797974,47.0974884033],"type":"Point"}
}