{
  "type": "Feature",
  "properties": {
    "iso:country":"CH",
    "sg:address":"Route De Payerne 16",
    "sg:city":"Villars-sur-gl\u00e2ne",
    "sg:orig_category":"Grosshandel mit Getreide, Saatgut U Futtermitteln",
    "sg:postcode":"1752",
    "sg:province":"Fribourg",
    "wof:name":"Agricem Sa",
    "wof:placetype":"venue"
},
  "geometry": {"coordinates":[7.109336853,46.7958450317],"type":"Point"}
}