{
  "type": "Feature",
  "properties": {
    "iso:country":"CH",
    "sg:address":"Oberg\u00fctschrain 3a",
    "sg:city":"Luzern",
    "sg:classifiers":[
        {
            "category":"Restaurant",
            "type":"Food & Drink"
        }
    ],
    "sg:phone":"+41 41 310 18 94",
    "sg:postcode":"6003",
    "sg:province":"Luzern",
    "wof:name":"Restaurant Treff-oberg\u00fctsch",
    "wof:placetype":"venue"
},
  "geometry": {"coordinates":[8.287437439,47.0457992554],"type":"Point"}
}