{
  "type": "Feature",
  "properties": {
    "iso:country":"CH",
    "sg:address":"8454",
    "sg:city":"Buchberg",
    "sg:orig_category":"Sportvereine Sch\u00fctzen",
    "sg:phone":"+41 27 927 27 62",
    "sg:postcode":"8454",
    "sg:province":"Schaffhausen",
    "wof:name":"Schiessverein",
    "wof:placetype":"venue"
},
  "geometry": {"coordinates":[8.5517597198,47.5684814453],"type":"Point"}
}