{
  "type": "Feature",
  "properties": {
    "addr:full":"Seestrasse 125 W\u00e4denswil Z\u00fcrich 8820",
    "addr:housenumber":"125",
    "addr:postcode":"8820",
    "addr:street":"Seestrasse;Zuerich",
    "iso:country":"CH",
    "sg:address":"Seestrasse 125",
    "sg:city":"W\u00e4denswil",
    "sg:classifiers":[
        {
            "category":"Structure",
            "subcategory":"Office Building",
            "type":"Public Place"
        }
    ],
    "sg:phone":"+41 17805628",
    "sg:postcode":"8820",
    "sg:province":"Z\u00fcrich",
    "sg:tags":[
        "equipment",
        "alarm",
        "installation",
        "system"
    ],
    "wof:name":"Linnekogel Sicherheitstechnik",
    "wof:placetype":"venue"
},
  "geometry": {"coordinates":[8.673255,47.230576],"type":"Point"}
}