{
  "type": "Feature",
  "properties": {
    "iso:country":"CH",
    "sg:address":"Route Des Terreaux 17",
    "sg:city":"Corsier-sur-vevey",
    "sg:orig_category":"Erbringung von Dienstleistungen f\u00fcr Unternehmen",
    "sg:postcode":"1804",
    "sg:province":"Vaud",
    "wof:name":"Photo P. Deb\u00e9taz Jacqueline.",
    "wof:placetype":"venue"
},
  "geometry": {"coordinates":[6.8477478027,46.4720191956],"type":"Point"}
}