{
  "type": "Feature",
  "properties": {
    "iso:country":"CH",
    "sg:address":"Talackerstrasse 14",
    "sg:city":"T\u00e4gerwilen",
    "sg:orig_category":"Herstellung von medizinischen U chirurgischen Ger\u00e4ten sowie orthop\u00e4dischen Vorrichtungen Herstellung",
    "sg:phone":"+41 71 272 30 00",
    "sg:postcode":"8274",
    "sg:province":"Thurgau",
    "wof:name":"Galifa Ag Kontaktlinsen, Mikrooptik, Usw; Herstellung, Vertrieb",
    "wof:placetype":"venue"
},
  "geometry": {"coordinates":[8.1297502518,47.4778671265],"type":"Point"}
}