{
  "type": "Feature",
  "properties": {
    "iso:country":"CH",
    "sg:address":"B\u00f6sch 37 6331 H\u00fcnenberg. Postfach",
    "sg:city":"H\u00fcnenberg",
    "sg:orig_category":"Elektro- and elektronische Maschinen Grosshandel Herstellung von elektronischen Bauelementen",
    "sg:phone":"+41 41 784 41 84",
    "sg:postcode":"6331",
    "sg:province":"Zug",
    "wof:name":"Wintec Technology Gmbh Produkte, Bes. Elektronische Bauteile F\u00fcr Die Computer-industrie Und Edv; Import Und Export-handel",
    "wof:placetype":"venue"
},
  "geometry": {"coordinates":[8.4402618408,47.1603851318],"type":"Point"}
}