{
  "type": "Feature",
  "properties": {
    "iso:country":"CH",
    "sg:address":"Schwand 300",
    "sg:city":"Bleiken",
    "sg:orig_category":"Bauspenglerei Zimmerei, Dachdeckerei, Bauspenglerei U Abdichtung",
    "sg:phone":"+41 31 771 18 84",
    "sg:postcode":"3674",
    "sg:province":"Bern",
    "wof:name":"Martin Haldimann Bauspenglerei",
    "wof:placetype":"venue"
},
  "geometry": {"coordinates":[7.636838,46.823761],"type":"Point"}
}