{
  "type": "Feature",
  "properties": {
    "iso:country":"CH",
    "sg:address":"Krummeneichstrasse 34",
    "sg:city":"Pratteln",
    "sg:orig_category":"Pensionskassen",
    "sg:postcode":"4133",
    "sg:province":"Basel-Landschaft",
    "wof:name":"Rta-sammelstiftung",
    "wof:placetype":"venue"
},
  "geometry": {"coordinates":[7.705177784,47.5235137939],"type":"Point"}
}