{
  "type": "Feature",
  "properties": {
    "iso:country":"CH",
    "sg:address":"Logengasse 29 2502 Biel/bienne. Postfach",
    "sg:city":"Biel/bienne",
    "sg:orig_category":"Elektroinstallation",
    "sg:postcode":"2502",
    "sg:province":"Bern",
    "wof:name":"Theo Schmutz Elektromontagen",
    "wof:placetype":"venue"
},
  "geometry": {"coordinates":[8.8011131287,47.3285675049],"type":"Point"}
}