{
  "type": "Feature",
  "properties": {
    "iso:country":"CH",
    "sg:address":"In Der Gandstrasse 15",
    "sg:city":"Zumikon",
    "sg:orig_category":"Non-Classified Establishments",
    "sg:postcode":"8126",
    "sg:province":"Z\u00fcrich",
    "wof:name":"Leo Wildhaber's Koch Event",
    "wof:placetype":"venue"
},
  "geometry": {"coordinates":[8.6151580811,47.3364944458],"type":"Point"}
}