{
  "type": "Feature",
  "properties": {
    "iso:country":"CH",
    "sg:address":"Baarerstrasse 43",
    "sg:city":"Zug",
    "sg:orig_category":"Binnenschiffahrt",
    "sg:postcode":"6300",
    "sg:province":"Zug",
    "wof:name":"Lygren Atle",
    "wof:placetype":"venue"
},
  "geometry": {"coordinates":[7.212448,46.08046],"type":"Point"}
}