{
  "type": "Feature",
  "properties": {
    "iso:country":"CH",
    "sg:address":"Sallenbachstrasse 14 8055 Z\u00fcrich. Postfach",
    "sg:city":"Z\u00fcrich",
    "sg:orig_category":"Sonstiger Grosshandel",
    "sg:postcode":"8055",
    "sg:province":"Z\u00fcrich",
    "wof:name":"Sie Trust Scepanovic",
    "wof:placetype":"venue"
},
  "geometry": {"coordinates":[8.499997139,47.3696746826],"type":"Point"}
}