{
  "type": "Feature",
  "properties": {
    "iso:country":"CH",
    "sg:address":"Hauptstrasse 19",
    "sg:city":"Flaach",
    "sg:orig_category":"Detailhandel mit M\u00f6beln Verlegen von Fussboden",
    "sg:phone":"+41 52 318 16 21",
    "sg:postcode":"8416",
    "sg:province":"Z\u00fcrich",
    "wof:name":"Frauenfelder M\u00f6bel Ag Innenausstattungen",
    "wof:placetype":"venue"
},
  "geometry": {"coordinates":[8.6042976379,47.5744552612],"type":"Point"}
}