{
  "type": "Feature",
  "properties": {
    "iso:country":"CH",
    "sg:address":"Sch\u00fctzeng\u00fctlistrasse 21",
    "sg:city":"Bischofszell",
    "sg:orig_category":"Non-Classified Establishments",
    "sg:postcode":"9220",
    "sg:province":"Thurgau",
    "wof:name":"Massiv-holz-m\u00f6belbauer Von Bischofszell, Christoph Lerch",
    "wof:placetype":"venue"
},
  "geometry": {"coordinates":[9.2386894226,47.4900512695],"type":"Point"}
}