{
  "type": "Feature",
  "properties": {
    "iso:country":"CH",
    "sg:address":"Burstwiesenstrasse 69 8606 Greifensee. Postfach",
    "sg:city":"Greifensee",
    "sg:orig_category":"Maler U Glasergewerbe",
    "sg:postcode":"8606",
    "sg:province":"Z\u00fcrich",
    "wof:name":"Brunner Rolf",
    "wof:placetype":"venue"
},
  "geometry": {"coordinates":[8.6758871078,47.3745422363],"type":"Point"}
}