{
  "type": "Feature",
  "properties": {
    "iso:country":"CH",
    "sg:address":"Basadingerstrasse 14",
    "sg:city":"Diessenhofen",
    "sg:orig_category":"Zahnkliniken",
    "sg:phone":"+41 18403388",
    "sg:postcode":"8253",
    "sg:province":"Thurgau",
    "wof:name":"Schulzahnklinik",
    "wof:placetype":"venue"
},
  "geometry": {"coordinates":[8.4654397964,47.4354667664],"type":"Point"}
}