{
  "type": "Feature",
  "properties": {
    "addr:full":"Chemin Malombr\u00e9 5 Gen\u00e8ve Gen\u00e8ve 1206",
    "addr:housenumber":"5",
    "addr:postcode":"1206",
    "addr:street":"Chemin Malombre\u0301",
    "iso:country":"CH",
    "sg:address":"Chemin Malombr\u00e9 5",
    "sg:city":"Gen\u00e8ve",
    "sg:orig_category":"Arztpraxen",
    "sg:phone":"+41 22 346 02 25",
    "sg:postcode":"1206",
    "sg:province":"Gen\u00e8ve",
    "wof:name":"Dr M\u00e9d. Fran\u00e7oise Riedlinger M\u00e9decin G\u00e9n\u00e9raliste",
    "wof:placetype":"venue"
},
  "geometry": {"coordinates":[6.152568,46.195911],"type":"Point"}
}