{
  "type": "Feature",
  "properties": {
    "iso:country":"CH",
    "sg:address":"Via Al Nido 7",
    "sg:city":"Lugano",
    "sg:orig_category":"Herstellung von k\u00e4lte U lufttechnischen Erzeugnissen f\u00fcr gewerbliche Zwecke",
    "sg:phone":"+41 91 966 57 32",
    "sg:postcode":"6900",
    "sg:province":"Ticino",
    "wof:name":"Flavio Valsangiacomo Studio D'ingegneria",
    "wof:placetype":"venue"
},
  "geometry": {"coordinates":[8.9429826736,46.0072250366],"type":"Point"}
}