{
  "type": "Feature",
  "properties": {
    "iso:country":"CH",
    "sg:address":"Z\u00fcrichstrasse 38 8840 Einsiedeln. Postfach 548",
    "sg:city":"Einsiedeln",
    "sg:orig_category":"Herstellung von Zement Herstellung von Ziegeln U sonstiger Baukeramik",
    "sg:phone":"+41 24 472 72 00",
    "sg:postcode":"8840",
    "sg:province":"Schwyz",
    "wof:name":"Procim Sa",
    "wof:placetype":"venue"
},
  "geometry": {"coordinates":[6.9584798813,46.2775840759],"type":"Point"}
}