{
  "type": "Feature",
  "properties": {
    "iso:country":"CH",
    "sg:address":"Rive Rue De 20",
    "sg:city":"Nyon",
    "sg:orig_category":"Instandhaltung U Reparatur von Automobilen",
    "sg:postcode":"1260",
    "sg:province":"Vaud",
    "wof:name":"Electra S.\u00e0 R.l.",
    "wof:placetype":"venue"
},
  "geometry": {"coordinates":[6.2390799522,46.3823661804],"type":"Point"}
}