{
  "type": "Feature",
  "properties": {
    "iso:country":"CH",
    "sg:address":"Schwadernaustrasse 29",
    "sg:city":"Aegerten",
    "sg:orig_category":"Oberfl\u00e4chenveredlung U W\u00e4rmebehandlung",
    "sg:phone":"+41 32 373 53 38",
    "sg:postcode":"2558",
    "sg:province":"Bern",
    "wof:name":"H\u00e4nni W.",
    "wof:placetype":"venue"
},
  "geometry": {"coordinates":[7.290722847,47.1227455139],"type":"Point"}
}