{
  "type": "Feature",
  "properties": {
    "iso:country":"CH",
    "sg:address":"Postgasse 2",
    "sg:city":"Arbon",
    "sg:orig_category":"Non-Classified Establishments",
    "sg:postcode":"9320",
    "sg:province":"Thurgau",
    "wof:name":"Held Mode Gmbh",
    "wof:placetype":"venue"
},
  "geometry": {"coordinates":[9.4359407425,47.5157470703],"type":"Point"}
}