{
  "type": "Feature",
  "properties": {
    "iso:country":"CH",
    "sg:address":"Alpenstrasse 9",
    "sg:city":"Zug",
    "sg:orig_category":"Unclassifiable Establishments",
    "sg:phone":"+41 41 710 04 28",
    "sg:postcode":"6300",
    "sg:province":"Zug",
    "wof:name":"Sichem Holding Ag",
    "wof:placetype":"venue"
},
  "geometry": {"coordinates":[8.5144662857,47.1723403931],"type":"Point"}
}