{
  "type": "Feature",
  "properties": {
    "iso:country":"CH",
    "sg:address":"Chileholzstrasse 7",
    "sg:city":"Sulzbach",
    "sg:orig_category":"Sportvereine Behindertensport",
    "sg:postcode":"8614",
    "sg:province":"Z\u00fcrich",
    "wof:name":"Svbs Wetzikon-gbzo",
    "wof:placetype":"venue"
},
  "geometry": {"coordinates":[8.752412796,47.3619689941],"type":"Point"}
}