{
  "type": "Feature",
  "properties": {
    "iso:country":"CH",
    "sg:address":"Waldh\u00e4usernstrasse 5",
    "sg:city":"Waltenschwil",
    "sg:orig_category":"Gemischte Landwirtschaft",
    "sg:postcode":"5622",
    "sg:province":"Aargau",
    "wof:name":"Stiftung Garden, Natural Ecologycal Farming In South India",
    "wof:placetype":"venue"
},
  "geometry": {"coordinates":[8.3100061417,47.3335914612],"type":"Point"}
}