{
  "type": "Feature",
  "properties": {
    "iso:country":"CH",
    "sg:address":"Jungfraustrasse 19a",
    "sg:city":"Uetendorf",
    "sg:orig_category":"Autospenglereien",
    "sg:phone":"+41 33 345 85 85",
    "sg:postcode":"3661",
    "sg:province":"Bern",
    "wof:name":"Urs Kr\u00e4henb\u00fchl Carrosserie",
    "wof:placetype":"venue"
},
  "geometry": {"coordinates":[7.594071,46.778976],"type":"Point"}
}