{
  "type": "Feature",
  "properties": {
    "iso:country":"CH",
    "sg:address":"Seestrasse 14",
    "sg:city":"Willerzell",
    "sg:orig_category":"Sonstiger spezialisierter Hoch U Tiefbau",
    "sg:phone":"+41 55 412 45 12",
    "sg:postcode":"8846",
    "sg:province":"Schwyz",
    "wof:name":"F\u00e4ssler Betonbohr & -fr\u00e4s Ag",
    "wof:placetype":"venue"
},
  "geometry": {"coordinates":[8.7941923141,47.1278762817],"type":"Point"}
}