{
  "type": "Feature",
  "properties": {
    "iso:country":"CH",
    "sg:address":"5612 Villmergen. Postfach 84",
    "sg:city":"Villmergen",
    "sg:orig_category":"Sportvereine Ballsport Badminton",
    "sg:phone":"+41 56 441 51 61",
    "sg:postcode":"5612",
    "sg:province":"Aargau",
    "wof:name":"Badminton-club Vindonissa",
    "wof:placetype":"venue"
},
  "geometry": {"coordinates":[8.2269802094,47.4968261719],"type":"Point"}
}