{
  "type": "Feature",
  "properties": {
    "iso:country":"CH",
    "sg:address":"B\u00fcndte 12",
    "sg:city":"Tamins",
    "sg:orig_category":"Fahrschulen, Flugschulen",
    "sg:phone":"+41 81 641 28 78",
    "sg:postcode":"7015",
    "sg:province":"Graubunden",
    "wof:name":"Heimi Joos Autofahrschule",
    "wof:placetype":"venue"
},
  "geometry": {"coordinates":[9.4056510925,46.8297119141],"type":"Point"}
}