{
  "type": "Feature",
  "properties": {
    "iso:country":"CH",
    "sg:address":"St\u00f6ckackerstrasse 9",
    "sg:city":"Bern",
    "sg:orig_category":"Eisbahnen and Eissportpl\u00e4tze Tennis- and Squash-Centers Hallen",
    "sg:phone":"+41 31 381 10 76",
    "sg:postcode":"3027",
    "sg:province":"Bern",
    "wof:name":"Eisbahn Weyermannshaus",
    "wof:placetype":"venue"
},
  "geometry": {"coordinates":[7.403637886,46.9483413696],"type":"Point"}
}