{
  "type": "Feature",
  "properties": {
    "iso:country":"CH",
    "sg:address":"Eggwilstrasse 4",
    "sg:city":"Bronschhofen",
    "sg:orig_category":"Architektur U Ingenieurb\u00fcros Herstellung von Metallkonstruktionen",
    "sg:phone":"+41 71 911 10 90",
    "sg:postcode":"9552",
    "sg:province":"St. Gallen",
    "wof:name":"Neff Josef.",
    "wof:placetype":"venue"
},
  "geometry": {"coordinates":[9.033677,47.484196],"type":"Point"}
}