{
  "type": "Feature",
  "properties": {
    "iso:country":"CH",
    "sg:address":"Rue De Pommey 15",
    "sg:city":"Chamoson",
    "sg:orig_category":"Grosshandel mit Getr\u00e4nken Grosshandel mit Wein U Spirituosen",
    "sg:phone":"+41 27 306 27 49",
    "sg:postcode":"1955",
    "sg:province":"Valais",
    "wof:name":"Daniel Putallaz Vins Engros",
    "wof:placetype":"venue"
},
  "geometry": {"coordinates":[7.2264709473,46.2021865845],"type":"Point"}
}