{
  "type": "Feature",
  "properties": {
    "iso:country":"CH",
    "sg:address":"Herolfingen 277",
    "sg:city":"Gysenstein",
    "sg:orig_category":"Haltung von Schweinen",
    "sg:phone":"+41 81 844 06 69",
    "sg:postcode":"3503",
    "sg:province":"Bern",
    "wof:name":"Maurizio Crameri Allevamento Suini",
    "wof:placetype":"venue"
},
  "geometry": {"coordinates":[10.0753107071,46.3597335815],"type":"Point"}
}