{
  "type": "Feature",
  "properties": {
    "iso:country":"CH",
    "sg:address":"H\u00f6henstrasse 43",
    "sg:city":"Fl\u00fcelen",
    "sg:orig_category":"Handel mit Motorr\u00e4dern, Teilen U Zubeh\u00f6r Instandhaltung U Reparatur von Motorr\u00e4dern",
    "sg:phone":"+41 41 870 99 68",
    "sg:postcode":"6454",
    "sg:province":"Uri",
    "wof:name":"Gisler Bike & Hike",
    "wof:placetype":"venue"
},
  "geometry": {"coordinates":[8.623916626,46.9130897522],"type":"Point"}
}