{
  "type": "Feature",
  "properties": {
    "iso:country":"CH",
    "sg:address":"Dorfch\u00e4rn 1",
    "sg:city":"Sch\u00f6tz",
    "sg:orig_category":"Herstellung von medizinischen U chirurgischen Ger\u00e4ten sowie orthop\u00e4dischen Vorrichtungen",
    "sg:phone":"+41 41 980 56 17",
    "sg:postcode":"6247",
    "sg:province":"Luzern",
    "wof:name":"Dental Labor Plamida Plazinic Dr. Milovan",
    "wof:placetype":"venue"
},
  "geometry": {"coordinates":[7.988699913,47.1694869995],"type":"Point"}
}