{
  "type": "Feature",
  "properties": {
    "iso:country":"CH",
    "sg:address":"Kirchweg 1",
    "sg:city":"Konolfingen",
    "sg:orig_category":"Detailhandel mit Damenbekleidung",
    "sg:phone":"+41 31 791 31 00",
    "sg:postcode":"3510",
    "sg:province":"Bern",
    "wof:name":"Annedore Andrey First-& Secondhand-boutique",
    "wof:placetype":"venue"
},
  "geometry": {"coordinates":[7.62017,46.878284],"type":"Point"}
}