{
  "type": "Feature",
  "properties": {
    "iso:country":"CH",
    "sg:address":"Bordacherstrasse 20",
    "sg:city":"D\u00e4llikon",
    "sg:orig_category":"Unternehmensberatung",
    "sg:postcode":"8108",
    "sg:province":"Z\u00fcrich",
    "wof:name":"Storni A., Industrieberatung",
    "wof:placetype":"venue"
},
  "geometry": {"coordinates":[8.4442176819,47.4375495911],"type":"Point"}
}