{
  "type": "Feature",
  "properties": {
    "iso:country":"CH",
    "sg:address":"Route De Bertigny 12",
    "sg:city":"Fribourg",
    "sg:orig_category":"Religi\u00f6se Vereinigungen",
    "sg:postcode":"1700",
    "sg:province":"Fribourg",
    "wof:name":"Eglise Du Christ (culte Africain)",
    "wof:placetype":"venue"
},
  "geometry": {"coordinates":[7.1424889565,46.802532196],"type":"Point"}
}