{
  "type": "Feature",
  "properties": {
    "iso:country":"CH",
    "sg:address":"Piz Linard",
    "sg:city":"Lantsch/lenz",
    "sg:orig_category":"Geb\u00e4ude, Wohnungsreinigung",
    "sg:phone":"+41 81 681 22 83",
    "sg:postcode":"7083",
    "sg:province":"Graubunden",
    "wof:name":"Anton Noth Geb\u00e4udereinigung Toni",
    "wof:placetype":"venue"
},
  "geometry": {"coordinates":[9.5632972717,46.6852493286],"type":"Point"}
}