{
  "type": "Feature",
  "properties": {
    "iso:country":"CH",
    "sg:address":"Neuwisstrasse 5",
    "sg:city":"Oberembrach",
    "sg:orig_category":"Reiseb\u00fcros U Reiseveranstalter",
    "sg:postcode":"8425",
    "sg:province":"Z\u00fcrich",
    "wof:name":"Iza Travel, Luternauer Jzabela, Kunst Und Kulturreisen Polen",
    "wof:placetype":"venue"
},
  "geometry": {"coordinates":[8.6205377579,47.4863128662],"type":"Point"}
}