{
  "type": "Feature",
  "properties": {
    "iso:country":"CH",
    "sg:address":"Wettsteinallee 17",
    "sg:city":"Basel",
    "sg:orig_category":"Detailhandel mit Radio U Fernsehger\u00e4ten",
    "sg:phone":"+41 61 681 43 43",
    "sg:postcode":"4058",
    "sg:province":"Basel-Stadt",
    "wof:name":"Peter Zeller Multimedia Und Av-technik",
    "wof:placetype":"venue"
},
  "geometry": {"coordinates":[7.5997219086,47.5599899292],"type":"Point"}
}