{
  "type": "Feature",
  "properties": {
    "iso:country":"CH",
    "sg:address":"Holtweg 3",
    "sg:city":"Buus",
    "sg:orig_category":"Herstellung von sonstigen elektrischen Ausr\u00fcstungen",
    "sg:phone":"+41 61 761 32 79",
    "sg:postcode":"4463",
    "sg:province":"Basel-Landschaft",
    "wof:name":"Elektroniklabor K\u00f6nig",
    "wof:placetype":"venue"
},
  "geometry": {"coordinates":[7.8639030457,47.5074577332],"type":"Point"}
}