{
  "type": "Feature",
  "properties": {
    "iso:country":"CH",
    "sg:address":"Hemberger Strasse T\u00fcetlisberg",
    "sg:city":"Wattwil",
    "sg:orig_category":"Sportvereine Ski",
    "sg:phone":"+41 71 988 22 48",
    "sg:postcode":"9630",
    "sg:province":"St. Gallen",
    "wof:name":"Skiclub Akro-team W'berg-togg.",
    "wof:placetype":"venue"
},
  "geometry": {"coordinates":[9.0868349075,47.2996559143],"type":"Point"}
}