{
  "type": "Feature",
  "properties": {
    "iso:country":"CH",
    "sg:address":"Haldenweg 4",
    "sg:city":"Arisdorf",
    "sg:orig_category":"Vereine Wissenschaftliche",
    "sg:phone":"+41 61 811 14 73",
    "sg:postcode":"4422",
    "sg:province":"Basel-Landschaft",
    "wof:name":"Entomologische Gesellschaft Bs",
    "wof:placetype":"venue"
},
  "geometry": {"coordinates":[7.7636761665,47.5084190369],"type":"Point"}
}