{
  "type": "Feature",
  "properties": {
    "addr:full":"P\u00e2quiers Avenue Des 22 St-blaise Neuch\u00e2tel 2072",
    "addr:postcode":"2072",
    "addr:street":"Pa\u0302Quiers Avenue Des 22;Neucha\u0302Tel",
    "iso:country":"CH",
    "sg:address":"P\u00e2quiers Avenue Des 22",
    "sg:city":"St-blaise",
    "sg:orig_category":"Detailhandel mit B\u00fcchern, Zeitungen, Schreib U Papeteriewaren",
    "sg:phone":"+41 32 754 32 32",
    "sg:postcode":"2072",
    "sg:province":"Neuch\u00e2tel",
    "wof:name":"Red'x Sa",
    "wof:placetype":"venue"
},
  "geometry": {"coordinates":[6.990164,47.014908],"type":"Point"}
}