{
  "type": "Feature",
  "properties": {
    "iso:country":"CH",
    "sg:address":"Rue Du Milieu 45",
    "sg:city":"Coeuve",
    "sg:orig_category":"Vorschulen, Kinderg\u00e4rten",
    "sg:phone":"+41 32 967 61 70",
    "sg:postcode":"2932",
    "sg:province":"Jura",
    "wof:name":"Ecole Enfantine",
    "wof:placetype":"venue"
},
  "geometry": {"coordinates":[6.8258938789,47.104221344],"type":"Point"}
}