{
  "type": "Feature",
  "properties": {
    "iso:country":"CH",
    "sg:address":"Sous-les-sentiers",
    "sg:city":"Tr\u00e9lex",
    "sg:orig_category":"Fischzucht, Teichwirtschaft",
    "sg:phone":"+41 22 369 19 22",
    "sg:postcode":"1270",
    "sg:province":"Vaud",
    "wof:name":"Philippe Magnenat Pisciculture",
    "wof:placetype":"venue"
},
  "geometry": {"coordinates":[6.2048749924,46.4152450562],"type":"Point"}
}