{
  "type": "Feature",
  "properties": {
    "iso:country":"CH",
    "sg:address":"Route De La Gl\u00e2ne 128a",
    "sg:city":"Villars-sur-gl\u00e2ne",
    "sg:orig_category":"Detailhandel mit Milcherzeugnissen U Eiern Detailhandel mit Waren verschiedener Art, Hauptrichtung N",
    "sg:phone":"+41 26 402 56 78",
    "sg:postcode":"1752",
    "sg:province":"Fribourg",
    "wof:name":"Pascal Oberson Laiterie & Alimentation",
    "wof:placetype":"venue"
},
  "geometry": {"coordinates":[7.1384720802,46.7906608582],"type":"Point"}
}