{
  "type": "Feature",
  "properties": {
    "iso:country":"CH",
    "sg:address":"Sonnmattstrasse 15",
    "sg:city":"M\u00fcnchenstein",
    "sg:orig_category":"Kosmetikinstitute",
    "sg:phone":"+41 61 411 74 68",
    "sg:postcode":"4142",
    "sg:province":"Basel-Landschaft",
    "wof:name":"Ilona Ryser Kosmetikinstitut",
    "wof:placetype":"venue"
},
  "geometry": {"coordinates":[7.6110129356,47.5202407837],"type":"Point"}
}