{
  "type": "Feature",
  "properties": {
    "iso:country":"CH",
    "sg:address":"Flurlingerweg 9",
    "sg:city":"Neuhausen",
    "sg:orig_category":"Vermietung U Verpachtung von eigenen Immobilien Vermittlung von Immobilien",
    "sg:phone":"+41 52 672 84 44",
    "sg:postcode":"8212",
    "sg:province":"Schaffhausen",
    "wof:name":"Immopax Ag",
    "wof:placetype":"venue"
},
  "geometry": {"coordinates":[8.6259908676,47.6802368164],"type":"Point"}
}