{
  "type": "Feature",
  "properties": {
    "iso:country":"CH",
    "sg:address":"Via Del Sole 8",
    "sg:city":"Pregassona",
    "sg:orig_category":"Fleischverarbeitung",
    "sg:postcode":"6963",
    "sg:province":"Ticino",
    "wof:name":"Della Santa Giovanni",
    "wof:placetype":"venue"
},
  "geometry": {"coordinates":[8.9686031342,46.0182304382],"type":"Point"}
}