{
  "type": "Feature",
  "properties": {
    "iso:country":"CH",
    "sg:address":"L\u00e4uferplatz 9",
    "sg:city":"Bern",
    "sg:orig_category":"Kunsthandel",
    "sg:phone":"+41 31 311 63 01",
    "sg:postcode":"3011",
    "sg:province":"Bern",
    "wof:name":"Werkgalerie Am L\u00e4uferplatz",
    "wof:placetype":"venue"
},
  "geometry": {"coordinates":[7.457420826,46.9495162964],"type":"Point"}
}