{
  "type": "Feature",
  "properties": {
    "iso:country":"CH",
    "sg:address":"1630",
    "sg:city":"Bulle",
    "sg:orig_category":"Vereine Musik/Blasmusik",
    "sg:phone":"+41 26 912 20 00",
    "sg:postcode":"1630",
    "sg:province":"Fribourg",
    "wof:name":"Jeunesses Musicales De La Gruy\u00e8re",
    "wof:placetype":"venue"
},
  "geometry": {"coordinates":[7.0232000351,46.6070785522],"type":"Point"}
}