{
  "type": "Feature",
  "properties": {
    "addr:full":"Buechwaldstrasse 13 Heimberg Bern 3627",
    "addr:housenumber":"13",
    "addr:postcode":"3627",
    "addr:street":"Buechwaldstrasse",
    "iso:country":"CH",
    "sg:address":"Buechwaldstrasse 13",
    "sg:city":"Heimberg",
    "sg:orig_category":"Allgemeiner Hoch U Tiefbau",
    "sg:phone":"+41 79 220 49 46",
    "sg:postcode":"3627",
    "sg:province":"Bern",
    "wof:name":"Kuonen Raphael Baugesch\u00e4ft",
    "wof:placetype":"venue"
},
  "geometry": {"coordinates":[7.63466,46.31633],"type":"Point"}
}