{
  "type": "Feature",
  "properties": {
    "addr:full":"Ulrichstrasse 14 Z\u00fcrich Z\u00fcrich 8032",
    "addr:housenumber":"14",
    "addr:postcode":"8032",
    "addr:street":"Ulrichstrasse",
    "iso:country":"CH",
    "sg:address":"Ulrichstrasse 14",
    "sg:city":"Z\u00fcrich",
    "sg:orig_category":"Advokaturb\u00fcros",
    "sg:phone":"+41 13885757",
    "sg:postcode":"8032",
    "sg:province":"Z\u00fcrich",
    "wof:name":"Hans Schmidt Advokaturb\u00fcro",
    "wof:placetype":"venue"
},
  "geometry": {"coordinates":[8.56351,47.361481],"type":"Point"}
}