{
  "type": "Feature",
  "properties": {
    "iso:country":"CH",
    "sg:address":"Lettenstrasse 8",
    "sg:city":"Rotkreuz",
    "sg:orig_category":"Sonstige mit der Informatik verbundene T\u00e4tigkeiten",
    "sg:postcode":"6343",
    "sg:province":"Zug",
    "wof:name":"Lanz Consulting Ag",
    "wof:placetype":"venue"
},
  "geometry": {"coordinates":[8.431429863,47.1476821899],"type":"Point"}
}