{
  "type": "Feature",
  "properties": {
    "iso:country":"CH",
    "sg:address":"Niederlenzerstrasse 21",
    "sg:city":"Lenzburg",
    "sg:orig_category":"Arbeitnehmerverb\u00e4nde",
    "sg:phone":"+41 62 885 37 40",
    "sg:postcode":"5600",
    "sg:province":"Aargau",
    "wof:name":"Gewerkschaft Bau & Industrie Gbi - Sektion Lenzburg-freiamt",
    "wof:placetype":"venue"
},
  "geometry": {"coordinates":[8.180212,47.389019],"type":"Point"}
}