{
  "type": "Feature",
  "properties": {
    "iso:country":"CH",
    "sg:address":"5612",
    "sg:city":"Villmergen",
    "sg:orig_category":"Sportvereine Turnen Vereine Damen",
    "sg:phone":"+41 62 212 30 40",
    "sg:postcode":"5612",
    "sg:province":"Aargau",
    "wof:name":"Damenturnverein Wangen",
    "wof:placetype":"venue"
},
  "geometry": {"coordinates":[7.8684778214,47.3468666077],"type":"Point"}
}