{
  "type": "Feature",
  "properties": {
    "addr:full":"Emmenspitz Zuchwil Solothurn 4528",
    "addr:postcode":"4528",
    "iso:country":"CH",
    "sg:address":"Emmenspitz",
    "sg:city":"Zuchwil",
    "sg:orig_category":"Allgemeiner Hoch U Tiefbau",
    "sg:phone":"+41 62 685 07 80",
    "sg:postcode":"4528",
    "sg:province":"Solothurn",
    "wof:name":"Rescosol Ag",
    "wof:placetype":"venue"
},
  "geometry": {"coordinates":[7.569855,47.21492],"type":"Point"}
}