{
  "type": "Feature",
  "properties": {
    "iso:country":"CH",
    "sg:address":"Badstrasse 17",
    "sg:city":"Niederurnen",
    "sg:orig_category":"Detailhandel mit Damenbekleidung",
    "sg:phone":"+41 55 610 30 68",
    "sg:postcode":"8867",
    "sg:province":"Glarus",
    "wof:name":"Couture-atelier Lydia Bissig",
    "wof:placetype":"venue"
},
  "geometry": {"coordinates":[9.053778,47.126698],"type":"Point"}
}