{
  "type": "Feature",
  "properties": {
    "iso:country":"CH",
    "sg:address":"Jurastrasse 26",
    "sg:city":"Seltisberg",
    "sg:orig_category":"Innenarchitekturb\u00fcros",
    "sg:phone":"+41 71 311 49 49",
    "sg:postcode":"4411",
    "sg:province":"Basel-Landschaft",
    "wof:name":"Andreas Schaffner Innenarchitektur",
    "wof:placetype":"venue"
},
  "geometry": {"coordinates":[9.3103294373,47.4059524536],"type":"Point"}
}