{
  "type": "Feature",
  "properties": {
    "addr:full":"Welsikerstrasse 4 Dinhard Z\u00fcrich 8474",
    "addr:housenumber":"4",
    "addr:postcode":"8474",
    "addr:street":"Welsikerstrasse",
    "iso:country":"CH",
    "sg:address":"Welsikerstrasse 4",
    "sg:city":"Dinhard",
    "sg:classifiers":[
        {
            "category":"Education",
            "subcategory":"Library",
            "type":"Public Place"
        }
    ],
    "sg:phone":"+41 52 320 80 90",
    "sg:postcode":"8474",
    "sg:province":"Z\u00fcrich",
    "sg:tags":[
        "u",
        "bibliotheken",
        "archive"
    ],
    "wof:name":"Gemeindebibliothek",
    "wof:placetype":"venue"
},
  "geometry": {"coordinates":[8.768416,47.555313],"type":"Point"}
}