{
  "type": "Feature",
  "properties": {
    "iso:country":"CH",
    "sg:address":"Vonwilstrasse 51",
    "sg:city":"St.gallen",
    "sg:orig_category":"Maler U Glasergewerbe",
    "sg:phone":"+41 71 278 57 74",
    "sg:postcode":"9000",
    "sg:province":"St. Gallen",
    "wof:name":"Allemann H.",
    "wof:placetype":"venue"
},
  "geometry": {"coordinates":[9.3555135727,47.419670105],"type":"Point"}
}