{
  "type": "Feature",
  "properties": {
    "iso:country":"CH",
    "sg:address":"Schulstrasse 19",
    "sg:city":"Islikon",
    "sg:orig_category":"Detailhandel mit Geschenkartikeln U Souvenirs Modeschmuck Detailhandel",
    "sg:phone":"+41 52 375 23 60",
    "sg:postcode":"8546",
    "sg:province":"Thurgau",
    "wof:name":"It's M Marcella H\u00f6gger",
    "wof:placetype":"venue"
},
  "geometry": {"coordinates":[8.8418302536,47.5454711914],"type":"Point"}
}