{
  "type": "Feature",
  "properties": {
    "iso:country":"CH",
    "sg:address":"Bahnhofstrasse 47",
    "sg:city":"Biel/bienne",
    "sg:orig_category":"Unclassifiable Establishments",
    "sg:postcode":"2502",
    "sg:province":"Bern",
    "wof:name":"G&s Elements Sa",
    "wof:placetype":"venue"
},
  "geometry": {"coordinates":[7.2458219528,47.1362228394],"type":"Point"}
}