{
  "type": "Feature",
  "properties": {
    "iso:country":"CH",
    "sg:address":"Uttins Rue Des 36",
    "sg:city":"Yverdon-les-bains",
    "sg:orig_category":"Grosshandel mit lebenden Tieren",
    "sg:postcode":"1400",
    "sg:province":"Vaud",
    "wof:name":"Coq Ogiz S\u00e0rl",
    "wof:placetype":"venue"
},
  "geometry": {"coordinates":[6.6414198875,46.7786331177],"type":"Point"}
}