{
  "type": "Feature",
  "properties": {
    "iso:country":"CH",
    "sg:address":"Industriestrasse 5 Effretikon 8308 Horben B. Illnau. Postfach",
    "sg:city":"Effretikon",
    "sg:orig_category":"Herstellung von Metallkonstruktionen",
    "sg:phone":"+41 57222577",
    "sg:postcode":"8307",
    "sg:province":"Z\u00fcrich",
    "wof:name":"Ferrowohlen Ag",
    "wof:placetype":"venue"
},
  "geometry": {"coordinates":[8.260881424,47.3507728577],"type":"Point"}
}