{
  "type": "Feature",
  "properties": {
    "iso:country":"CH",
    "sg:address":"Hohlenbaumstrasse 201",
    "sg:city":"Schaffhausen",
    "sg:orig_category":"Sonderschulen Wohnheime f\u00fcr Kinder U Jugendliche",
    "sg:phone":"+41 52 624 62 45",
    "sg:postcode":"8200",
    "sg:province":"Schaffhausen",
    "wof:name":"Morgenstern Schule F\u00fcr Entwicklungsbehinderte Kinder",
    "wof:placetype":"venue"
},
  "geometry": {"coordinates":[8.6250247955,47.7084922791],"type":"Point"}
}