{
  "type": "Feature",
  "properties": {
    "iso:country":"CH",
    "sg:address":"Via Regina 21",
    "sg:city":"Vezia",
    "sg:orig_category":"Non-Classified Establishments",
    "sg:postcode":"6943",
    "sg:province":"Ticino",
    "wof:name":"Psa Finance (suisse) Sa",
    "wof:placetype":"venue"
},
  "geometry": {"coordinates":[8.9384832382,46.0204963684],"type":"Point"}
}