{
  "type": "Feature",
  "properties": {
    "iso:country":"CH",
    "sg:address":"Chemin Des Osches 67",
    "sg:city":"Pully",
    "sg:orig_category":"Gartenbau Sonstiges Textilgewerbe",
    "sg:phone":"+41 79 200 55 90",
    "sg:postcode":"1009",
    "sg:province":"Vaud",
    "wof:name":"Bruhin Garten Ag",
    "wof:placetype":"venue"
},
  "geometry": {"coordinates":[8.8888187408,47.2022094727],"type":"Point"}
}