{
  "type": "Feature",
  "properties": {
    "iso:country":"CH",
    "sg:address":"Via Della Stazione 4",
    "sg:city":"Muralto",
    "sg:orig_category":"Detailhandel mit Bekleidung",
    "sg:phone":"+41 91 743 62 70",
    "sg:postcode":"6600",
    "sg:province":"Ticino",
    "wof:name":"Les Griffes Sa",
    "wof:placetype":"venue"
},
  "geometry": {"coordinates":[8.80141,46.173119],"type":"Point"}
}