{
  "type": "Feature",
  "properties": {
    "iso:country":"CH",
    "sg:address":"Schellenrainstrasse 14",
    "sg:city":"Sursee",
    "sg:orig_category":"Datenverarbeitungsdienste",
    "sg:phone":"+41 41 921 57 20",
    "sg:postcode":"6210",
    "sg:province":"Luzern",
    "wof:name":"Yvan Jeanmonod Creanet",
    "wof:placetype":"venue"
},
  "geometry": {"coordinates":[8.10346,47.167168],"type":"Point"}
}