{
  "type": "Feature",
  "properties": {
    "iso:country":"CH",
    "sg:address":"Engadinstrasse 27 7000 Chur. Postfach",
    "sg:city":"Chur",
    "sg:orig_category":"Reiseb\u00fcros U Reiseveranstalter",
    "sg:phone":"+41 81 252 59 61",
    "sg:postcode":"7002",
    "sg:province":"Graubunden",
    "wof:name":"Luis Torneiro Reiseb\u00fcro",
    "wof:placetype":"venue"
},
  "geometry": {"coordinates":[9.529091835,46.8505058289],"type":"Point"}
}