{
  "type": "Feature",
  "properties": {
    "iso:country":"CH",
    "sg:address":"Hauptstrasse 29",
    "sg:city":"Herznach",
    "sg:orig_category":"Erdbewegungsarbeiten",
    "sg:phone":"+41 62 867 80 67",
    "sg:postcode":"5027",
    "sg:province":"Aargau",
    "wof:name":"Deiss Ag Natursteine",
    "wof:placetype":"venue"
},
  "geometry": {"coordinates":[8.0505609512,47.4755859375],"type":"Point"}
}