{
  "type": "Feature",
  "properties": {
    "iso:country":"CH",
    "sg:address":"L\u00fcssiweg 43",
    "sg:city":"Zug",
    "sg:orig_category":"Architektur U Ingenieurb\u00fcros Architekturb\u00fcros",
    "sg:phone":"+41 71 845 55 66",
    "sg:postcode":"6300",
    "sg:province":"Zug",
    "wof:name":"Archtech Partner Gmbh",
    "wof:placetype":"venue"
},
  "geometry": {"coordinates":[8.525546,47.175117],"type":"Point"}
}