{
  "type": "Feature",
  "properties": {
    "iso:country":"CH",
    "sg:address":"Diamantstrasse 7",
    "sg:city":"Biel/bienne",
    "sg:orig_category":"Erbringung von Dienstleistungen f\u00fcr Unternehmen",
    "sg:phone":"+41 32 322 39 89",
    "sg:postcode":"2503",
    "sg:province":"Bern",
    "wof:name":"Ardec Piazzoni A.",
    "wof:placetype":"venue"
},
  "geometry": {"coordinates":[7.2509579659,47.1384925842],"type":"Point"}
}