{
  "type": "Feature",
  "properties": {
    "iso:country":"CH",
    "sg:address":"Via Robiana 1",
    "sg:city":"Besazio",
    "sg:orig_category":"Non-Classified Establishments",
    "sg:postcode":"6863",
    "sg:province":"Ticino",
    "wof:name":"Vittorio Borlini Studio D'ingegneria",
    "wof:placetype":"venue"
},
  "geometry": {"coordinates":[8.9495582581,45.8700294495],"type":"Point"}
}