{
  "type": "Feature",
  "properties": {
    "addr:full":"Rebbergstrasse 18 Untersiggenthal Aargau 5417",
    "addr:housenumber":"18",
    "addr:postcode":"5417",
    "addr:street":"Rebbergstrasse",
    "iso:country":"CH",
    "sg:address":"Rebbergstrasse 18",
    "sg:city":"Untersiggenthal",
    "sg:classifiers":[
        {
            "category":"Social Services",
            "subcategory":"Retirement Home",
            "type":"Services"
        }
    ],
    "sg:phone":"+41 56 288 38 25",
    "sg:postcode":"5417",
    "sg:province":"Aargau",
    "sg:tags":[
        "pflegeheime",
        "u",
        "alters"
    ],
    "wof:name":"Sunnhalde Altersheim",
    "wof:placetype":"venue"
},
  "geometry": {"coordinates":[8.250419,47.503395],"type":"Point"}
}