{
  "type": "Feature",
  "properties": {
    "iso:country":"CH",
    "sg:address":"4618",
    "sg:city":"Boningen",
    "sg:orig_category":"Gewinnung von Kies U Sand Herstellung von sonstigen Produkten aus nichtmetallischen Mineralien",
    "sg:phone":"+41 62 216 23 82",
    "sg:postcode":"4618",
    "sg:province":"Solothurn",
    "wof:name":"Aeschlimann Ag Strassenbau & Asphaltierungen",
    "wof:placetype":"venue"
},
  "geometry": {"coordinates":[7.8518800735,47.3009414673],"type":"Point"}
}