{
  "type": "Feature",
  "properties": {
    "iso:country":"CH",
    "sg:address":"Obere Plessurstrasse 36",
    "sg:city":"Chur",
    "sg:orig_category":"Non-Classified Establishments",
    "sg:postcode":"7000",
    "sg:province":"Graubunden",
    "wof:name":"Sanpro Holding Ag",
    "wof:placetype":"venue"
},
  "geometry": {"coordinates":[9.5269432068,46.8498497009],"type":"Point"}
}