{
  "type": "Feature",
  "properties": {
    "addr:full":"Plancemont Couvet Neuch\u00e2tel 2108",
    "addr:postcode":"2108",
    "addr:street":"Neucha\u0302Tel",
    "iso:country":"CH",
    "sg:address":"Plancemont",
    "sg:city":"Couvet",
    "sg:orig_category":"Advokaturb\u00fcros",
    "sg:phone":"+41 32 863 17 27",
    "sg:postcode":"2108",
    "sg:province":"Neuch\u00e2tel",
    "wof:name":"Cath\u00e9rine Leu Etude D'avocat",
    "wof:placetype":"venue"
},
  "geometry": {"coordinates":[6.62127,46.928169],"type":"Point"}
}