{
  "type": "Feature",
  "properties": {
    "iso:country":"CH",
    "sg:address":"Avenue Du L\u00e9man 31",
    "sg:city":"Lausanne",
    "sg:orig_category":"Hardwareberatung Softwareentwicklung U beratung",
    "sg:phone":"+41 21 324 20 15",
    "sg:postcode":"1005",
    "sg:province":"Vaud",
    "wof:name":"Infor (schweiz) Ag Logistik",
    "wof:placetype":"venue"
},
  "geometry": {"coordinates":[6.6461567879,46.5160942078],"type":"Point"}
}