{
  "type": "Feature",
  "properties": {
    "iso:country":"CH",
    "sg:address":"Rosengartenstrasse 6 8037 Z\u00fcrich. Postfach",
    "sg:city":"Z\u00fcrich",
    "sg:orig_category":"Unclassifiable Establishments",
    "sg:phone":"+41 21 944 31 25",
    "sg:postcode":"8037",
    "sg:province":"Z\u00fcrich",
    "wof:name":"Pvs Afigest, Paul Van Saanen",
    "wof:placetype":"venue"
},
  "geometry": {"coordinates":[6.8557391167,46.4531402588],"type":"Point"}
}