{
  "type": "Feature",
  "properties": {
    "iso:country":"CH",
    "sg:address":"Mont-de-sion Rue Du 3 1206 Gen\u00e8ve. Postfach",
    "sg:city":"Gen\u00e8ve",
    "sg:orig_category":"Detailhandel mit Waren verschiedener Art, Hauptrichtung Nahrungsmittel",
    "sg:postcode":"1206",
    "sg:province":"Gen\u00e8ve",
    "wof:name":"Boukal Cheikh M. Et Mme.",
    "wof:placetype":"venue"
},
  "geometry": {"coordinates":[6.1530580521,46.1972923279],"type":"Point"}
}