{
  "type": "Feature",
  "properties": {
    "iso:country":"CH",
    "sg:address":"Fin Doie 8 2854 Bassecourt. Postfach",
    "sg:city":"Bassecourt",
    "sg:orig_category":"W\u00e4scherei U chemische Reinigung",
    "sg:postcode":"2854",
    "sg:province":"Jura",
    "wof:name":"Bourquard Maryse Lavage Chimique, Pressing",
    "wof:placetype":"venue"
},
  "geometry": {"coordinates":[7.2434229851,47.3354721069],"type":"Point"}
}