{
  "type": "Feature",
  "properties": {
    "iso:country":"CH",
    "sg:address":"Attikerstrasse 35 Attikon 8132 Hinteregg. Postfach",
    "sg:city":"Hinteregg",
    "sg:orig_category":"Bausteine Fabrikation, Handel",
    "sg:postcode":"8132",
    "sg:province":"Z\u00fcrich",
    "wof:name":"Enzler Ag",
    "wof:placetype":"venue"
},
  "geometry": {"coordinates":[8.690055,47.300556],"type":"Point"}
}