{
  "type": "Feature",
  "properties": {
    "iso:country":"CH",
    "sg:address":"Moosstrasse 46-48",
    "sg:city":"Kaufdorf",
    "sg:orig_category":"Autoabbruch",
    "sg:phone":"+41 31 809 06 16",
    "sg:postcode":"3126",
    "sg:province":"Bern",
    "wof:name":"Franz-walter Messerli Autoabbruch",
    "wof:placetype":"venue"
},
  "geometry": {"coordinates":[7.501629,46.836704],"type":"Point"}
}