{
  "type": "Feature",
  "properties": {
    "iso:country":"CH",
    "sg:address":"Industrie Rue De L'",
    "sg:city":"Nyon",
    "sg:orig_category":"Herstellung von Sportger\u00e4ten",
    "sg:postcode":"1260",
    "sg:province":"Vaud",
    "wof:name":"Vioget Eric Fabrication Et Vente D'articles De P\u00eache",
    "wof:placetype":"venue"
},
  "geometry": {"coordinates":[6.2389202118,46.3830718994],"type":"Point"}
}