{
  "type": "Feature",
  "properties": {
    "iso:country":"CH",
    "sg:address":"Blumenrain 23",
    "sg:city":"Basel",
    "sg:orig_category":"Unternehmensberatung",
    "sg:phone":"+41 79 421 40 57",
    "sg:postcode":"4051",
    "sg:province":"Basel-Stadt",
    "wof:name":"Junker Unternehmensberatung",
    "wof:placetype":"venue"
},
  "geometry": {"coordinates":[8.600684166,47.3294639587],"type":"Point"}
}