{
  "type": "Feature",
  "properties": {
    "iso:country":"CH",
    "sg:address":"Kugelgasse 7",
    "sg:city":"M\u00e4nnedorf",
    "sg:orig_category":"Versicherungen Hauptagenturen",
    "sg:phone":"+41 19205056",
    "sg:postcode":"8708",
    "sg:province":"Z\u00fcrich",
    "wof:name":"Winterthur-versicherungen Hauptagentur",
    "wof:placetype":"venue"
},
  "geometry": {"coordinates":[8.6898889542,47.2535667419],"type":"Point"}
}