{
  "type": "Feature",
  "properties": {
    "iso:country":"CH",
    "sg:address":"Friedhofstrasse 7 4127 Birsfelden. Postfach",
    "sg:city":"Birsfelden",
    "sg:orig_category":"Herstellung von k\u00e4lte U lufttechnischen Erzeugnissen f\u00fcr gewerbliche Zwecke",
    "sg:phone":"+41 79 434 53 06",
    "sg:postcode":"4127",
    "sg:province":"Basel-Landschaft",
    "wof:name":"L\u00dcftungsbau Bolzern H. L\u00fcftungsanlagen; Montage Usw",
    "wof:placetype":"venue"
},
  "geometry": {"coordinates":[7.6254200935,47.5553894043],"type":"Point"}
}