{
  "type": "Feature",
  "properties": {
    "iso:country":"CH",
    "sg:address":"Forchstrasse 175",
    "sg:city":"Z\u00fcrich",
    "sg:orig_category":"Grosshandel mit Flachglas, Sanit\u00e4rkeramik U Anstrichmitteln Grosshandel mit M\u00f6beln, Wohnbedarf, Tepp",
    "sg:phone":"+41 14225775",
    "sg:postcode":"8032",
    "sg:province":"Z\u00fcrich",
    "wof:name":"Avantino Ag",
    "wof:placetype":"venue"
},
  "geometry": {"coordinates":[8.5658550262,47.3603401184],"type":"Point"}
}