{
  "type": "Feature",
  "properties": {
    "iso:country":"CH",
    "sg:address":"Wipkingerplatz 7",
    "sg:city":"Z\u00fcrich",
    "sg:orig_category":"Nationale Postdienste",
    "sg:phone":"+41 12724390",
    "sg:postcode":"8037",
    "sg:province":"Z\u00fcrich",
    "wof:name":"Die Schweizerische Post Z\u00fcrich 37 Wipkingen",
    "wof:placetype":"venue"
},
  "geometry": {"coordinates":[8.5236415863,47.3928184509],"type":"Point"}
}