{
  "type": "Feature",
  "properties": {
    "iso:country":"CH",
    "sg:address":"Avenue De La Gare 6 1880 Bex Case Postale 186",
    "sg:city":"Bex",
    "sg:classifiers":[
        {
            "category":"Bars & Pubs",
            "type":"Food & Drink"
        }
    ],
    "sg:phone":"+41 32 913 94 33",
    "sg:postcode":"1880",
    "sg:province":"Vaud",
    "wof:name":"Pub Le Pacha",
    "wof:placetype":"venue"
},
  "geometry": {"coordinates":[6.826113,47.101372],"type":"Point"}
}