{
  "type": "Feature",
  "properties": {
    "iso:country":"CH",
    "sg:address":"Landoltstrasse 43",
    "sg:city":"Bern",
    "sg:orig_category":"Sonstige technische Beratung U Planung",
    "sg:phone":"+41 41 660 22 13",
    "sg:postcode":"3007",
    "sg:province":"Bern",
    "wof:name":"Josef Ettlin B\u00fcro F\u00fcr Umweltfragen",
    "wof:placetype":"venue"
},
  "geometry": {"coordinates":[7.4403848648,46.9359931946],"type":"Point"}
}