{
  "type": "Feature",
  "properties": {
    "iso:country":"CH",
    "sg:address":"La Vieille Forge",
    "sg:city":"Poliez-le-grand",
    "sg:orig_category":"Detailhandel mit Fahrr\u00e4dern Handel mit Motorr\u00e4dern, Teilen U Zubeh\u00f6r Instandhaltung U Reparatur von ",
    "sg:phone":"+41 21 881 21 93",
    "sg:postcode":"1041",
    "sg:province":"Vaud",
    "wof:name":"Harley-davidson Peter & Ingrid Wirz",
    "wof:placetype":"venue"
},
  "geometry": {"coordinates":[6.6604199409,46.6171188354],"type":"Point"}
}