{
  "type": "Feature",
  "properties": {
    "iso:country":"CH",
    "sg:address":"3941",
    "sg:classifiers":[
        {
            "category":"Travel",
            "subcategory":"Hotels & Motels",
            "type":"Entertainment"
        }
    ],
    "sg:phone":"+41 27 473 15 89",
    "sg:postcode":"3941",
    "sg:tags":[
        "hotels",
        "mit",
        "restaurant"
    ],
    "wof:name":"Hotel Rhodania, Roland Kammacher",
    "wof:placetype":"venue"
},
  "geometry": {"coordinates":[144.8237915039,-38.3983001709],"type":"Point"}
}