{
  "type": "Feature",
  "properties": {
    "iso:country":"CH",
    "sg:address":"Chemin De Bois-genoud 16",
    "sg:city":"Romanel-s-lausanne",
    "sg:orig_category":"Vereine Abstinenten",
    "sg:phone":"+41 22 329 11 69",
    "sg:postcode":"1032",
    "sg:province":"Vaud",
    "wof:name":"F\u00e9d.genevoise P.la Pr\u00e9vention De L'alcoolisme Fegpa",
    "wof:placetype":"venue"
},
  "geometry": {"coordinates":[6.1428852081,46.1942558289],"type":"Point"}
}