{
  "type": "Feature",
  "properties": {
    "iso:country":"CH",
    "sg:address":"Roc Rue Du 8",
    "sg:city":"Neuch\u00e2tel",
    "sg:orig_category":"Softwareentwicklung U beratung",
    "sg:phone":"+41 79 225 44 18",
    "sg:postcode":"2000",
    "sg:province":"Neuch\u00e2tel",
    "wof:name":"Object Way S\u00e0rl",
    "wof:placetype":"venue"
},
  "geometry": {"coordinates":[6.9310851097,46.9903335571],"type":"Point"}
}