{
  "type": "Feature",
  "properties": {
    "iso:country":"CH",
    "sg:address":"Wylerstrasse 19",
    "sg:city":"Bern",
    "sg:classifiers":[
        {
            "category":"Bus Stop",
            "subcategory":"None",
            "type":"Transportation"
        }
    ],
    "sg:phone":"+41 31 332 32 68",
    "sg:postcode":"3014",
    "sg:province":"Bern",
    "sg:tags":[
        "engraving",
        "workshop"
    ],
    "wof:name":"Franco Sisti",
    "wof:placetype":"venue"
},
  "geometry": {"coordinates":[7.4493541718,46.9590301514],"type":"Point"}
}