{
  "type": "Feature",
  "properties": {
    "iso:country":"CH",
    "sg:address":"Oberneuhofstrasse 5",
    "sg:city":"Baar",
    "sg:orig_category":"Unternehmensberatung",
    "sg:phone":"+41 79 427 14 55",
    "sg:postcode":"6340",
    "sg:province":"Zug",
    "wof:name":"Hofer Unternehmensberatung",
    "wof:placetype":"venue"
},
  "geometry": {"coordinates":[8.5164089203,47.1889839172],"type":"Point"}
}