{
  "type": "Feature",
  "properties": {
    "iso:country":"CH",
    "sg:address":"Ausserdorfstrasse 33",
    "sg:city":"Maschwanden",
    "sg:orig_category":"Non-Classified Establishments",
    "sg:postcode":"8933",
    "sg:province":"Z\u00fcrich",
    "wof:name":"Rovor Services Gmbh",
    "wof:placetype":"venue"
},
  "geometry": {"coordinates":[8.4268732071,47.2333335876],"type":"Point"}
}