{
  "type": "Feature",
  "properties": {
    "iso:country":"CH",
    "sg:address":"Eichenstrasse 3",
    "sg:city":"Basel",
    "sg:orig_category":"Vereine Fasnacht",
    "sg:phone":"+41 61 301 20 47",
    "sg:postcode":"4054",
    "sg:province":"Basel-Stadt",
    "wof:name":"D'aigebreedler",
    "wof:placetype":"venue"
},
  "geometry": {"coordinates":[7.5704169273,47.5567092896],"type":"Point"}
}