{
  "type": "Feature",
  "properties": {
    "iso:country":"CH",
    "sg:address":"Hutins Chemin Des 5 1232 Confignon. Postfach",
    "sg:city":"Confignon",
    "sg:classifiers":[
        {
            "category":"Travel",
            "subcategory":"Hotels & Motels",
            "type":"Entertainment"
        }
    ],
    "sg:postcode":"1232",
    "sg:province":"Gen\u00e8ve",
    "sg:tags":[
        "hotels",
        "mit",
        "restaurant"
    ],
    "wof:name":"Salamin Solange",
    "wof:placetype":"venue"
},
  "geometry": {"coordinates":[5.1808700562,45.8973388672],"type":"Point"}
}