{
  "type": "Feature",
  "properties": {
    "iso:country":"CH",
    "sg:address":"Chemin Pr\u00e9-olivier",
    "sg:city":"Chavannes-des-bois",
    "sg:orig_category":"Massagestudios Naturheil\u00e4rzte and Heilpraktiker",
    "sg:phone":"+41 22 755 37 24",
    "sg:postcode":"1290",
    "sg:province":"Gen\u00e8ve",
    "wof:name":"Ruth Comminot Naturopathe & Massage",
    "wof:placetype":"venue"
},
  "geometry": {"coordinates":[6.1313419342,46.313369751],"type":"Point"}
}