{
  "type": "Feature",
  "properties": {
    "iso:country":"CH",
    "sg:address":"8426",
    "sg:city":"Lufingen",
    "sg:orig_category":"Elektrizit\u00e4tsversorgung",
    "sg:postcode":"8426",
    "sg:province":"Z\u00fcrich",
    "wof:name":"Elektrizit\u00e4tsgenossenschaft Lufingen",
    "wof:placetype":"venue"
},
  "geometry": {"coordinates":[8.5896100998,47.4827308655],"type":"Point"}
}