{
  "type": "Feature",
  "properties": {
    "iso:country":"CH",
    "sg:address":"Dorfstrasse 15",
    "sg:city":"Selzach",
    "sg:orig_category":"Detailhandel mit fotografischen Artikeln Fotografische Ateliers",
    "sg:phone":"+41 32 641 22 09",
    "sg:postcode":"2545",
    "sg:province":"Solothurn",
    "wof:name":"Fsh Foto Studio",
    "wof:placetype":"venue"
},
  "geometry": {"coordinates":[7.4555649757,47.2042655945],"type":"Point"}
}