{
  "type": "Feature",
  "properties": {
    "iso:country":"CH",
    "sg:address":"-reunies 86",
    "sg:city":"Grand Lancy",
    "sg:classifiers":[
        {
            "category":"Banks & Credit Unions",
            "subcategory":"Bank",
            "type":"Services"
        }
    ],
    "sg:phone":"+41 22 884 09 11",
    "sg:postcode":"1212",
    "sg:province":"Gen\u00e8ve",
    "wof:name":"Swiss Bank Corp., Palettes, Avenue Des Communes",
    "wof:placetype":"venue"
},
  "geometry": {"coordinates":[6.123265,46.172298],"type":"Point"}
}