{
  "type": "Feature",
  "properties": {
    "iso:country":"CH",
    "sg:address":"Bollwerk-promenade 5",
    "sg:city":"Basel",
    "sg:orig_category":"Dialysis Software",
    "sg:phone":"+41 61 286 30 00",
    "sg:postcode":"4051",
    "sg:province":"Basel-Stadt",
    "wof:name":"Eds Information Business Gmbh",
    "wof:placetype":"venue"
},
  "geometry": {"coordinates":[7.5880298615,47.5508155823],"type":"Point"}
}