{
  "type": "Feature",
  "properties": {
    "iso:country":"CH",
    "sg:address":"Rue Du Parc 3",
    "sg:city":"Sion",
    "sg:orig_category":"Unclassifiable Establishments",
    "sg:postcode":"1950",
    "sg:province":"Valais",
    "wof:name":"Nicole Savioz Kin\u00e9siologie & Massages",
    "wof:placetype":"venue"
},
  "geometry": {"coordinates":[7.3713321686,46.2323493958],"type":"Point"}
}