{
  "type": "Feature",
  "properties": {
    "iso:country":"CH",
    "sg:address":"Chemin Des Avettes 10",
    "sg:city":"Meyrin",
    "sg:orig_category":"Erdbewegungsarbeiten",
    "sg:phone":"+41 22 782 70 79",
    "sg:postcode":"1217",
    "sg:province":"Gen\u00e8ve",
    "wof:name":"Constant Furrer Entreprise De Terrassement",
    "wof:placetype":"venue"
},
  "geometry": {"coordinates":[6.0922827721,46.2359542847],"type":"Point"}
}