{
  "type": "Feature",
  "properties": {
    "iso:country":"CH",
    "sg:address":"Chapelle Rue De La 32",
    "sg:city":"Peseux",
    "sg:orig_category":"Softwareentwicklung U beratung",
    "sg:phone":"+41 32 740 18 40",
    "sg:postcode":"2034",
    "sg:province":"Neuch\u00e2tel",
    "wof:name":"G-r Informatique, Raad & Gfeller",
    "wof:placetype":"venue"
},
  "geometry": {"coordinates":[6.8898267746,46.9876365662],"type":"Point"}
}