{
  "type": "Feature",
  "properties": {
    "iso:country":"CH",
    "sg:address":"Schwarztorstrasse 47",
    "sg:city":"Bern",
    "sg:orig_category":"Reparatur von Schuhen U Lederwaren",
    "sg:phone":"+41 31 381 45 13",
    "sg:postcode":"3007",
    "sg:province":"Bern",
    "wof:name":"Sezer Schuh Und Schl\u00fcsselservice Gmbh",
    "wof:placetype":"venue"
},
  "geometry": {"coordinates":[7.4326648712,46.9441146851],"type":"Point"}
}