{
  "type": "Feature",
  "properties": {
    "iso:country":"CH",
    "sg:address":"Rue Cornavin 7",
    "sg:city":"Gen\u00e8ve",
    "sg:orig_category":"Detailhandel mit Radio U Fernsehger\u00e4ten Detailhandel mit elektrischen Haushalts-,Radio U Fernsehger\u00e4",
    "sg:phone":"+41 22 731 85 30",
    "sg:postcode":"1201",
    "sg:province":"Gen\u00e8ve",
    "wof:name":"Stambac, Modern-music Sa",
    "wof:placetype":"venue"
},
  "geometry": {"coordinates":[6.1421232224,46.2076187134],"type":"Point"}
}