{
  "type": "Feature",
  "properties": {
    "iso:country":"CH",
    "sg:address":"Rue De L'encyclop\u00e9die 6",
    "sg:city":"Gen\u00e8ve",
    "sg:orig_category":"Instandhaltung U Reparatur von Automobilen",
    "sg:phone":"+41 22 344 68 42",
    "sg:postcode":"1201",
    "sg:province":"Gen\u00e8ve",
    "wof:name":"Garage De L'encyclop\u00e9die, Denis Cl\u00e9ment",
    "wof:placetype":"venue"
},
  "geometry": {"coordinates":[6.1352319717,46.206817627],"type":"Point"}
}