{
  "type": "Feature",
  "properties": {
    "addr:full":"R\u00fcmikerstrasse 16 8409 Hegi (winterthur). Postfach Winterthur Z\u00fcrich 8406",
    "addr:housenumber":"16",
    "addr:postcode":"8409;8406",
    "addr:street":"Ruemikerstrasse;Hegi;Postfach",
    "iso:country":"CH",
    "sg:address":"R\u00fcmikerstrasse 16 8409 Hegi (winterthur). Postfach",
    "sg:city":"Winterthur",
    "sg:orig_category":"Allgemeiner Hoch U Tiefbau",
    "sg:postcode":"8406",
    "sg:province":"Z\u00fcrich",
    "wof:name":"Winbau Gmbh Dienstleistungen Im Bausektor",
    "wof:placetype":"venue"
},
  "geometry": {"coordinates":[8.77162,47.508011],"type":"Point"}
}