{
  "type": "Feature",
  "properties": {
    "iso:country":"CH",
    "sg:address":"Burggasse 3",
    "sg:city":"Weisslingen",
    "sg:orig_category":"Wirtschaftsverb\u00e4nde Gewerbeverb\u00e4nde/-vereine",
    "sg:phone":"+41 52 384 12 79",
    "sg:postcode":"8484",
    "sg:province":"Z\u00fcrich",
    "wof:name":"Gewerbeverein Weisslingen Pr\u00e4s.herrn Rolf Keller",
    "wof:placetype":"venue"
},
  "geometry": {"coordinates":[8.7626638412,47.4328460693],"type":"Point"}
}