{
  "type": "Feature",
  "properties": {
    "iso:country":"CH",
    "sg:address":"Geissacher 7",
    "sg:city":"Zumikon",
    "sg:orig_category":"Unternehmensberatung",
    "sg:phone":"+41 19190022",
    "sg:postcode":"8126",
    "sg:province":"Z\u00fcrich",
    "wof:name":"S.s.o. Staub Special Operation",
    "wof:placetype":"venue"
},
  "geometry": {"coordinates":[8.6276092529,47.3299751282],"type":"Point"}
}