{
  "type": "Feature",
  "properties": {
    "iso:country":"CH",
    "sg:address":"Pflugg\u00e4sslein 3",
    "sg:city":"Basel",
    "sg:orig_category":"Detailhandel mit B\u00fcchern",
    "sg:phone":"+41 61 262 04 90",
    "sg:postcode":"4001",
    "sg:province":"Basel-Stadt",
    "wof:name":"Domus-haus Buchhandlung F\u00fcr Architektur Und Design Limacher Rita M. B\u00fccher, Zeitschriften, Ton- U. Bildtr\u00e4ger Bes. A. D. Gebiet Architektur, Kunst U. Design",
    "wof:placetype":"venue"
},
  "geometry": {"coordinates":[7.589363,47.555946],"type":"Point"}
}