{
  "type": "Feature",
  "properties": {
    "iso:country":"CH",
    "sg:address":"4450 Sissach. Postfach 237",
    "sg:city":"Sissach",
    "sg:classifiers":[
        {
            "category":"Autos & Motor Vehicles",
            "subcategory":"Recreational Vehicle Sales",
            "type":"Retail Goods"
        }
    ],
    "sg:postcode":"4450",
    "sg:province":"Basel-Landschaft",
    "sg:tags":[
        "sportvereine",
        "go-kart",
        "kart"
    ],
    "wof:name":"Karting-club Baselland",
    "wof:placetype":"venue"
},
  "geometry": {"coordinates":[7.8127641678,47.4675979614],"type":"Point"}
}