{
  "type": "Feature",
  "properties": {
    "iso:country":"CH",
    "sg:address":"Bernstrasse 5",
    "sg:city":"Kiesen",
    "sg:orig_category":"Non-Classified Establishments",
    "sg:postcode":"3629",
    "sg:province":"Bern",
    "wof:name":"Resab Apparatebau Gmbh Recyclingapparatebau",
    "wof:placetype":"venue"
},
  "geometry": {"coordinates":[7.5871510506,46.8194007874],"type":"Point"}
}