{
  "type": "Feature",
  "properties": {
    "iso:country":"CH",
    "sg:address":"Radelfingenstrasse 24-26 3270 Aarberg. Postfach",
    "sg:city":"Aarberg",
    "sg:orig_category":"Herstellung von D\u00fcngemitteln U Stickstoffverbindungen Herstellung von sonstigen Produkten aus nichtm",
    "sg:phone":"+41 32 391 63 00",
    "sg:postcode":"3270",
    "sg:province":"Bern",
    "wof:name":"Ricoter Erdaufbereitung Ag",
    "wof:placetype":"venue"
},
  "geometry": {"coordinates":[7.2782621384,47.0419464111],"type":"Point"}
}