{
  "type": "Feature",
  "properties": {
    "iso:country":"CH",
    "sg:address":"B\u00e4lliz 62",
    "sg:city":"Thun",
    "sg:classifiers":[
        {
            "category":"Restaurant",
            "type":"Food & Drink"
        }
    ],
    "sg:postcode":"3600",
    "sg:province":"Bern",
    "sg:tags":[
        "tea-rooms",
        "restaurants"
    ],
    "wof:name":"Caf\u00e9 Le Passage Interdit",
    "wof:placetype":"venue"
},
  "geometry": {"coordinates":[-63.2513618469,-24.1957702637],"type":"Point"}
}