{
  "type": "Feature",
  "properties": {
    "addr:full":"Ath\u00e9n\u00e9e Rue De L' 31 1206 Gen\u00e8ve. Postfach Gen\u00e8ve Gen\u00e8ve 1206",
    "addr:housenumber":"31",
    "addr:postcode":"1206;postfach;1206",
    "addr:street":"Rue De L '",
    "iso:country":"CH",
    "sg:address":"Ath\u00e9n\u00e9e Rue De L' 31 1206 Gen\u00e8ve. Postfach",
    "sg:city":"Gen\u00e8ve",
    "sg:orig_category":"Architektur U Ingenieurb\u00fcros",
    "sg:phone":"+41 26 401 11 22",
    "sg:postcode":"1206",
    "sg:province":"Gen\u00e8ve",
    "wof:name":"Atelier D'architecture Et Design Gamboni Peter Architecte Dipl. Epf/sia Sa",
    "wof:placetype":"venue"
},
  "geometry": {"coordinates":[2.407909,44.16367],"type":"Point"}
}