{
  "type": "Feature",
  "properties": {
    "iso:country":"CH",
    "sg:address":"Rue De La Porcelaine 5",
    "sg:city":"Nyon",
    "sg:orig_category":"Autoreiseunternehmen Reiseb\u00fcros",
    "sg:phone":"+41 22 361 20 25",
    "sg:postcode":"1260",
    "sg:province":"Vaud",
    "wof:name":"Pierre Louis",
    "wof:placetype":"venue"
},
  "geometry": {"coordinates":[6.242866,46.38353],"type":"Point"}
}