{
  "type": "Feature",
  "properties": {
    "iso:country":"CH",
    "sg:address":"Grabenstrasse 32 6300 Zug. Postfach",
    "sg:city":"Zug",
    "sg:orig_category":"Unternehmensberatung",
    "sg:phone":"+41 41 728 63 32",
    "sg:postcode":"6301",
    "sg:province":"Zug",
    "wof:name":"Iw Management Gmbh",
    "wof:placetype":"venue"
},
  "geometry": {"coordinates":[8.5146417618,47.1651420593],"type":"Point"}
}