{
  "type": "Feature",
  "properties": {
    "iso:country":"CH",
    "sg:address":"Route De Divonne 48-centre Articom",
    "sg:city":"Nyon",
    "sg:classifiers":[
        {
            "category":"Manufacturing",
            "subcategory":"Motor Vehicles & Parts",
            "type":"Manufacturing & Wholesale Goods"
        }
    ],
    "sg:phone":"+41 22 361 56 02",
    "sg:postcode":"1260",
    "sg:province":"Vaud",
    "sg:tags":[
        "electronic",
        "assembling",
        "component"
    ],
    "wof:name":"Teutschmann Electronic",
    "wof:placetype":"venue"
},
  "geometry": {"coordinates":[6.23908,46.382366],"type":"Point"}
}