{
  "type": "Feature",
  "properties": {
    "iso:country":"CH",
    "sg:address":"Rebbergstrasse 15",
    "sg:city":"Adlikon",
    "sg:orig_category":"Wirtschaftspr\u00fcfung, Steuerberatung U Treuhand",
    "sg:phone":"+41 52 317 33 36",
    "sg:postcode":"8452",
    "sg:province":"Z\u00fcrich",
    "wof:name":"Froehlich Treuhand",
    "wof:placetype":"venue"
},
  "geometry": {"coordinates":[8.6899614334,47.5815582275],"type":"Point"}
}