{
  "type": "Feature",
  "properties": {
    "iso:country":"CH",
    "sg:address":"Heinzenbergstrasse 430",
    "sg:city":"Thusis",
    "sg:orig_category":"Kaminfeger",
    "sg:phone":"+41 81 651 43 39",
    "sg:postcode":"7430",
    "sg:province":"Graubunden",
    "wof:name":"Dario Cortesi Kaminfegermeister",
    "wof:placetype":"venue"
},
  "geometry": {"coordinates":[9.4354162216,46.6999130249],"type":"Point"}
}