{
  "type": "Feature",
  "properties": {
    "addr:full":"Missionsstrasse 36 4055 Basel. Postfach Basel Basel-Stadt 4012",
    "addr:housenumber":"36",
    "addr:postcode":"4055;4012",
    "addr:street":"Missionsstrasse;Postfach",
    "iso:country":"CH",
    "sg:address":"Missionsstrasse 36 4055 Basel. Postfach",
    "sg:city":"Basel",
    "sg:orig_category":"Detailhandel mit B\u00fcchern",
    "sg:phone":"+41 61 261 64 64",
    "sg:postcode":"4012",
    "sg:province":"Basel-Stadt",
    "wof:name":"Reinhardt-media-service Friedrich Reinhardt Ag",
    "wof:placetype":"venue"
},
  "geometry": {"coordinates":[7.57726,47.560219],"type":"Point"}
}