{
  "type": "Feature",
  "properties": {
    "iso:country":"CH",
    "sg:address":"Gr\u00fcnheinrichweg 2",
    "sg:city":"Glattfelden",
    "sg:orig_category":"Markt U Meinungsforschung",
    "sg:phone":"+41 18672432",
    "sg:postcode":"8192",
    "sg:province":"Z\u00fcrich",
    "wof:name":"D\u00fcrr Dr. A. M.",
    "wof:placetype":"venue"
},
  "geometry": {"coordinates":[8.5001792908,47.5590286255],"type":"Point"}
}