{
  "type": "Feature",
  "properties": {
    "iso:country":"CH",
    "sg:address":"Via Cortivallo 22c",
    "sg:city":"Lugano",
    "sg:orig_category":"Architektur U Ingenieurb\u00fcros",
    "sg:postcode":"6900",
    "sg:province":"Ticino",
    "wof:name":"Bba B\u00fcro F\u00fcr Bautechnologie Und Bauausr\u00fcstungen Gmbh",
    "wof:placetype":"venue"
},
  "geometry": {"coordinates":[8.938128,46.005898],"type":"Point"}
}