{
  "type": "Feature",
  "properties": {
    "iso:country":"CH",
    "sg:address":"Stehrenberg",
    "sg:city":"Bussnang",
    "sg:orig_category":"Detailhandel mit Brot, Back U S\u00fcsswaren",
    "sg:postcode":"9565",
    "sg:province":"Thurgau",
    "wof:name":"Lehmann A.",
    "wof:placetype":"venue"
},
  "geometry": {"coordinates":[9.07873,47.557739],"type":"Point"}
}