{
  "type": "Feature",
  "properties": {
    "iso:country":"CH",
    "sg:address":"Morgartenring 24",
    "sg:city":"Basel",
    "sg:orig_category":"Grosshandel mit B\u00fcromaschinen Grosshandel mit sonstigen Halbwaren",
    "sg:phone":"+41 61 302 55 73",
    "sg:postcode":"4054",
    "sg:province":"Basel-Stadt",
    "wof:name":"Charles Kipfer B\u00fcrobedarf",
    "wof:placetype":"venue"
},
  "geometry": {"coordinates":[7.5649008751,47.5560264587],"type":"Point"}
}