{
  "type": "Feature",
  "properties": {
    "iso:country":"CH",
    "sg:address":"Tour-haldimand Av. De La 5",
    "sg:city":"Pully",
    "sg:orig_category":"Fernmeldedienste",
    "sg:postcode":"1009",
    "sg:province":"Vaud",
    "wof:name":"Cdpt Compagnie De Developpement Pour Programmes De Television Sa",
    "wof:placetype":"venue"
},
  "geometry": {"coordinates":[6.6544079781,46.5139274597],"type":"Point"}
}