{
  "type": "Feature",
  "properties": {
    "iso:country":"CH",
    "sg:address":"Av. Gambach 9",
    "sg:city":"Fribourg",
    "sg:orig_category":"Fachdetailhandel in Verkaufsr\u00e4umen",
    "sg:postcode":"1700",
    "sg:province":"Fribourg",
    "wof:name":"Chusa Art Developement Sa.",
    "wof:placetype":"venue"
},
  "geometry": {"coordinates":[7.1494522095,46.8060646057],"type":"Point"}
}