{
  "type": "Feature",
  "properties": {
    "iso:country":"CH",
    "sg:address":"Lentulusstrasse 65",
    "sg:city":"Bern",
    "sg:orig_category":"Allgemeiner Hoch U Tiefbau",
    "sg:phone":"+41 31 371 91 80",
    "sg:postcode":"3007",
    "sg:province":"Bern",
    "wof:name":"Gemi Baumanagement Gmbh",
    "wof:placetype":"venue"
},
  "geometry": {"coordinates":[7.428148,46.939594],"type":"Point"}
}