{
  "type": "Feature",
  "properties": {
    "iso:country":"CH",
    "sg:address":"Grundstrasse 12",
    "sg:city":"Rotkreuz",
    "sg:orig_category":"Betrieb von Sportanlagen Sonstige mit Sport verbundene T\u00e4tigkeiten",
    "sg:phone":"+41 41 799 30 20",
    "sg:postcode":"6343",
    "sg:province":"Zug",
    "wof:name":"Gest\u00fct Gnadenthal Ag",
    "wof:placetype":"venue"
},
  "geometry": {"coordinates":[8.430276,47.145691],"type":"Point"}
}