{
  "type": "Feature",
  "properties": {
    "iso:country":"CH",
    "sg:address":"Ey 13 3063 Ittigen. Postfach",
    "sg:city":"Ittigen",
    "sg:orig_category":"Herstellung von Ger\u00e4ten der Elektrizit\u00e4tserzeugung, -verteilung u.\u00e4. -Herstellung von sonstigen elek",
    "sg:phone":"+41 31 924 24 24",
    "sg:postcode":"3063",
    "sg:province":"Bern",
    "wof:name":"Comlab Ag",
    "wof:placetype":"venue"
},
  "geometry": {"coordinates":[7.4714679718,46.9739189148],"type":"Point"}
}