{
  "type": "Feature",
  "properties": {
    "iso:country":"CH",
    "sg:address":"Via Al Molino",
    "sg:city":"Grancia",
    "sg:orig_category":"Grosshandel mit Holz U Baustoffen",
    "sg:phone":"+41 91 960 50 10",
    "sg:postcode":"6916",
    "sg:province":"Ticino",
    "wof:name":"Bum Building Materials Sa",
    "wof:placetype":"venue"
},
  "geometry": {"coordinates":[8.9250659943,45.9669761658],"type":"Point"}
}