{
  "type": "Feature",
  "properties": {
    "iso:country":"CH",
    "sg:address":"Grand Rue 100",
    "sg:city":"Montreux",
    "sg:orig_category":"Detailhandel mit Geschenkartikeln U Souvenirs Grosshandel mit Textilien",
    "sg:phone":"+41 21 963 70 91",
    "sg:postcode":"1820",
    "sg:province":"Vaud",
    "wof:name":"Modisar Sa Boutique Raphael",
    "wof:placetype":"venue"
},
  "geometry": {"coordinates":[6.9069590569,46.4383010864],"type":"Point"}
}