{
  "type": "Feature",
  "properties": {
    "addr:full":"Zelgstrasse 72 Uetendorf Bern 3661",
    "addr:housenumber":"72",
    "addr:postcode":"3661",
    "addr:street":"Zelgstrasse",
    "iso:country":"CH",
    "sg:address":"Zelgstrasse 72",
    "sg:city":"Uetendorf",
    "sg:orig_category":"Autolackierereien",
    "sg:phone":"+41 33 223 66 15",
    "sg:postcode":"3661",
    "sg:province":"Bern",
    "wof:name":"Thomas Dermond Carrosserie & Autolackierungen",
    "wof:placetype":"venue"
},
  "geometry": {"coordinates":[7.576693,46.776901],"type":"Point"}
}