{
  "type": "Feature",
  "properties": {
    "iso:country":"CH",
    "sg:address":"2207",
    "sg:city":"Coffrane",
    "sg:orig_category":"Forstwirtschaft ohne Dienstleistungen in der Forstwirtschaft",
    "sg:postcode":"2207",
    "sg:province":"Neuch\u00e2tel",
    "wof:name":"Entreprise Foresti\u00e8re Magnin E. & Fils",
    "wof:placetype":"venue"
},
  "geometry": {"coordinates":[6.8666000366,47.0085411072],"type":"Point"}
}