{
  "type": "Feature",
  "properties": {
    "iso:country":"CH",
    "sg:address":"Rebenweg 33",
    "sg:city":"Gampelen",
    "sg:orig_category":"Unclassifiable Establishments",
    "sg:postcode":"3236",
    "sg:province":"Bern",
    "wof:name":"Info Prime Pbz Co Ltd, London, Zweigniederlassung Gampelen",
    "wof:placetype":"venue"
},
  "geometry": {"coordinates":[7.0475049019,47.0182342529],"type":"Point"}
}