{
  "type": "Feature",
  "properties": {
    "iso:country":"CH",
    "sg:address":"1372",
    "sg:city":"Bavois",
    "sg:orig_category":"Verwertung von Milch",
    "sg:postcode":"1372",
    "sg:province":"Vaud",
    "wof:name":"Soci\u00e9t\u00e9 De Fromagerie Et De Laiterie De Progens",
    "wof:placetype":"venue"
},
  "geometry": {"coordinates":[6.9213700294,46.5899467468],"type":"Point"}
}