{
  "type": "Feature",
  "properties": {
    "iso:country":"CH",
    "sg:address":"Vadianstrasse 39",
    "sg:city":"St.gallen",
    "sg:orig_category":"Dienstleistungen von Beteiligungsgesellschaften",
    "sg:postcode":"9000",
    "sg:province":"St. Gallen",
    "wof:name":"Vahekeni Joao, Africaconsultant",
    "wof:placetype":"venue"
},
  "geometry": {"coordinates":[6.8638272285,46.4492607117],"type":"Point"}
}