{
  "type": "Feature",
  "properties": {
    "iso:country":"CH",
    "sg:address":"Steigstr. 20",
    "sg:city":"Turgi",
    "sg:classifiers":[
        {
            "category":"Building & Trades",
            "subcategory":"Construction",
            "type":"Services"
        }
    ],
    "sg:phone":"+41 56 298 18 18",
    "sg:postcode":"5300",
    "sg:province":"Aargau",
    "sg:tags":[
        "work",
        "public"
    ],
    "wof:name":"Umbricht Ag",
    "wof:placetype":"venue"
},
  "geometry": {"coordinates":[8.25203,47.495525],"type":"Point"}
}