{
  "type": "Feature",
  "properties": {
    "iso:country":"CH",
    "sg:address":"4950",
    "sg:city":"Huttwil",
    "sg:orig_category":"Erschliessung von Grundst\u00fccken",
    "sg:postcode":"4950",
    "sg:province":"Bern",
    "wof:name":"Wohnbaugenossenschaft Huttwil",
    "wof:placetype":"venue"
},
  "geometry": {"coordinates":[7.8472599983,47.1139984131],"type":"Point"}
}