{
  "type": "Feature",
  "properties": {
    "iso:country":"CH",
    "sg:address":"Blegistr. 17b",
    "sg:city":"Baar",
    "sg:classifiers":[
        {
            "category":"Manufacturing",
            "subcategory":"Textiles",
            "type":"Manufacturing & Wholesale Goods"
        }
    ],
    "sg:phone":"+41 4119431111",
    "sg:postcode":"6340",
    "sg:province":"Zug",
    "sg:tags":[
        "linen",
        "clothing",
        "fabric"
    ],
    "wof:name":"Lenzlinger S\u00d6hne Ag",
    "wof:placetype":"venue"
},
  "geometry": {"coordinates":[9.2822599411,53.6873283386],"type":"Point"}
}