{
  "type": "Feature",
  "properties": {
    "iso:country":"CH",
    "sg:address":"Riedweg 1",
    "sg:city":"Dietikon",
    "sg:orig_category":"Kauf U Verkauf von Immobilien auf eigene Rechnung",
    "sg:postcode":"8953",
    "sg:province":"Z\u00fcrich",
    "wof:name":"Peter Frei, Immobilien-beratungen",
    "wof:placetype":"venue"
},
  "geometry": {"coordinates":[8.3926830292,47.4191055298],"type":"Point"}
}