{
  "type": "Feature",
  "properties": {
    "addr:full":"Bachweg 17 Oberr\u00fcti Aargau 5647",
    "addr:housenumber":"17",
    "addr:postcode":"5647",
    "addr:street":"Bachweg",
    "iso:country":"CH",
    "sg:address":"Bachweg 17",
    "sg:city":"Oberr\u00fcti",
    "sg:classifiers":[
        {
            "category":"Organizations",
            "subcategory":"Labor Organization",
            "type":"Services"
        }
    ],
    "sg:phone":"+41 41 787 19 72",
    "sg:postcode":"5647",
    "sg:province":"Aargau",
    "sg:tags":[
        "work",
        "assembling",
        "assembly",
        "contract"
    ],
    "wof:name":"Inox-montagen Meier & St\u00f6ckli Gmbh",
    "wof:placetype":"venue"
},
  "geometry": {"coordinates":[8.396401,47.167995],"type":"Point"}
}