{
  "type": "Feature",
  "properties": {
    "iso:country":"CH",
    "sg:address":"Lenzhardstrasse 24b",
    "sg:city":"Rupperswil",
    "sg:orig_category":"Innenarchitekturb\u00fcros",
    "sg:phone":"+41 62 897 00 71",
    "sg:postcode":"5102",
    "sg:province":"Aargau",
    "wof:name":"Hans-ruedi Amsler Innenarchitektur",
    "wof:placetype":"venue"
},
  "geometry": {"coordinates":[8.1321487427,47.3991508484],"type":"Point"}
}