{
  "type": "Feature",
  "properties": {
    "iso:country":"CH",
    "sg:address":"2014 B\u00f4le Case Postale 90",
    "sg:city":"B\u00f4le",
    "sg:orig_category":"Sportvereine P\u00e9tanque",
    "sg:postcode":"2014",
    "sg:province":"Neuch\u00e2tel",
    "wof:name":"P\u00e9tanque-cl.la Sportive Neuch.",
    "wof:placetype":"venue"
},
  "geometry": {"coordinates":[6.8359699249,46.9682388306],"type":"Point"}
}