{
  "type": "Feature",
  "properties": {
    "iso:country":"CH",
    "sg:address":"Baumgartenstrasse 2",
    "sg:city":"Spreitenbach",
    "sg:orig_category":"Sonstiger Grosshandel",
    "sg:phone":"+41 56 401 38 61",
    "sg:postcode":"8957",
    "sg:province":"Aargau",
    "wof:name":"Gravo-import-export, Branko Gostovic",
    "wof:placetype":"venue"
},
  "geometry": {"coordinates":[8.3662185669,47.422908783],"type":"Point"}
}