{
  "type": "Feature",
  "properties": {
    "iso:country":"CH",
    "sg:address":"Schachen Spiezwiler",
    "sg:city":"Spiez",
    "sg:orig_category":"Grosshandel mit lebenden Tieren",
    "sg:postcode":"3700",
    "sg:province":"Bern",
    "wof:name":"Schafzuchtgenossenschaft Spiez Ii",
    "wof:placetype":"venue"
},
  "geometry": {"coordinates":[7.6656889915,46.6787452698],"type":"Point"}
}