{
  "type": "Feature",
  "properties": {
    "iso:country":"CH",
    "sg:address":"Morgartenstrasse 16",
    "sg:city":"Luzern",
    "sg:classifiers":[
        {
            "category":"Education",
            "subcategory":"Library",
            "type":"Public Place"
        }
    ],
    "sg:postcode":"6003",
    "sg:province":"Luzern",
    "sg:tags":[
        "u",
        "bibliotheken",
        "archive"
    ],
    "wof:name":"Bibliothek Der Evang.-ref.kirchgemeinde",
    "wof:placetype":"venue"
},
  "geometry": {"coordinates":[8.30817,47.049061],"type":"Point"}
}