{
  "type": "Feature",
  "properties": {
    "iso:country":"CH",
    "sg:address":"Poststrasse 5",
    "sg:city":"Sarnen",
    "sg:orig_category":"Rechtsberatung",
    "sg:postcode":"6060",
    "sg:province":"Obwalden",
    "wof:name":"Eschfina Ag",
    "wof:placetype":"venue"
},
  "geometry": {"coordinates":[8.2470731735,46.8957595825],"type":"Point"}
}