{
  "type": "Feature",
  "properties": {
    "iso:country":"CH",
    "sg:address":"Chemin Des Chaucheys 5",
    "sg:city":"Founex",
    "sg:orig_category":"Handelsvermittlung U Grosshandel",
    "sg:phone":"+41 22 776 03 40",
    "sg:postcode":"1297",
    "sg:province":"Vaud",
    "wof:name":"Skyway Technology Sa",
    "wof:placetype":"venue"
},
  "geometry": {"coordinates":[6.1982488632,46.3344078064],"type":"Point"}
}