{
  "type": "Feature",
  "properties": {
    "iso:country":"CH",
    "sg:address":"Coq-d'inde Rue Du 1",
    "sg:city":"Neuch\u00e2tel",
    "sg:orig_category":"Grosshandel mit Getreide, Saatgut U Futtermitteln",
    "sg:postcode":"2000",
    "sg:province":"Neuch\u00e2tel",
    "wof:name":"El Hout S\u00e0rl",
    "wof:placetype":"venue"
},
  "geometry": {"coordinates":[6.928314209,46.990737915],"type":"Point"}
}