{
  "type": "Feature",
  "properties": {
    "addr:full":"Bahnhofplatz 9 Winterthur Z\u00fcrich 8400",
    "addr:housenumber":"9",
    "addr:postcode":"8400",
    "addr:street":"Bahnhofplatz",
    "iso:country":"CH",
    "sg:address":"Bahnhofplatz 9",
    "sg:city":"Winterthur",
    "sg:orig_category":"Detailhandel mit Blumen U Pflanzen Detailhandel mit Geschenkartikeln U Souvenirs",
    "sg:postcode":"8400",
    "sg:province":"Z\u00fcrich",
    "wof:name":"Beatrice Steffen Blumengesch\u00e4ft Gate One",
    "wof:placetype":"venue"
},
  "geometry": {"coordinates":[8.724494,47.500824],"type":"Point"}
}