{
  "type": "Feature",
  "properties": {
    "iso:country":"CH",
    "sg:address":"Dufour Rue Du G\u00e9n\u00e9ral- 15 1204 Gen\u00e8ve. Postfach",
    "sg:city":"Gen\u00e8ve",
    "sg:orig_category":"Wirtschaftspr\u00fcfung, Steuerberatung U Treuhand",
    "sg:phone":"+41 58 286 51 11",
    "sg:postcode":"1204",
    "sg:province":"Gen\u00e8ve",
    "wof:name":"Soci\u00e9t\u00e9 Fiduciaire Lemano",
    "wof:placetype":"venue"
},
  "geometry": {"coordinates":[6.6256132126,46.5237007141],"type":"Point"}
}