{
  "type": "Feature",
  "properties": {
    "iso:country":"CH",
    "sg:address":"Ebnetrain 11",
    "sg:city":"Meggen",
    "sg:orig_category":"Erschliessung Kauf U Verkauf von Immobilien Unternehmensberatung",
    "sg:phone":"+41 41 378 04 10",
    "sg:postcode":"6045",
    "sg:province":"Luzern",
    "wof:name":"Halene Blankenagel Management Ag",
    "wof:placetype":"venue"
},
  "geometry": {"coordinates":[8.3664827347,47.0474700928],"type":"Point"}
}