{
  "type": "Feature",
  "properties": {
    "iso:country":"CH",
    "sg:address":"B\u00fcrenstrasse 257",
    "sg:city":"Nennigkofen",
    "sg:orig_category":"Nationale Postdienste",
    "sg:phone":"+41 32 622 22 05",
    "sg:postcode":"4574",
    "sg:province":"Solothurn",
    "wof:name":"Die Schweizerische Post",
    "wof:placetype":"venue"
},
  "geometry": {"coordinates":[7.4966330528,47.1880187988],"type":"Point"}
}