{
  "type": "Feature",
  "properties": {
    "iso:country":"CH",
    "sg:address":"Wynaweg 8",
    "sg:city":"Oberkulm",
    "sg:orig_category":"Bauschreinerei",
    "sg:phone":"+41 62 776 25 09",
    "sg:postcode":"5727",
    "sg:province":"Aargau",
    "wof:name":"Willy Barfuss Schreinerei",
    "wof:placetype":"venue"
},
  "geometry": {"coordinates":[8.118559,47.298626],"type":"Point"}
}