{
  "type": "Feature",
  "properties": {
    "iso:country":"CH",
    "sg:address":"Lenzhardstrasse 17",
    "sg:city":"Lenzburg",
    "sg:orig_category":"Grosshandel mit Eisenwaren sowie Installationsbedarf f\u00fcr Gas, Wasser U Heizung Grosshandel mit sonst",
    "sg:phone":"+41 62 891 81 51",
    "sg:postcode":"5600",
    "sg:province":"Aargau",
    "wof:name":"Jakob Hug Ag Maschinen Und Werkzeuge",
    "wof:placetype":"venue"
},
  "geometry": {"coordinates":[8.1621656418,47.3951835632],"type":"Point"}
}