{
  "type": "Feature",
  "properties": {
    "iso:country":"CH",
    "sg:address":"3988",
    "sg:city":"Ulrichen",
    "sg:orig_category":"Schulpflegen",
    "sg:postcode":"3988",
    "sg:province":"Valais",
    "wof:name":"Schulkommission Der Gemeinde Ulrichen",
    "wof:placetype":"venue"
},
  "geometry": {"coordinates":[8.3043403625,46.5064048767],"type":"Point"}
}