{
  "type": "Feature",
  "properties": {
    "iso:country":"CH",
    "sg:address":"Levant Rue Du 91",
    "sg:city":"Martigny",
    "sg:orig_category":"Allgemeiner Hoch U Tiefbau",
    "sg:phone":"+41 27 722 00 34",
    "sg:postcode":"1920",
    "sg:province":"Valais",
    "wof:name":"Cerm",
    "wof:placetype":"venue"
},
  "geometry": {"coordinates":[7.077048,46.09779],"type":"Point"}
}