{
  "type": "Feature",
  "properties": {
    "iso:country":"CH",
    "sg:address":"Bahnhofplatz 3900 Brig. Postfach 91",
    "sg:city":"Brig",
    "sg:orig_category":"Bahnhofbuffets",
    "sg:phone":"+41 27 923 13 98",
    "sg:postcode":"3900",
    "sg:province":"Valais",
    "wof:name":"Bahnhofbuffet",
    "wof:placetype":"venue"
},
  "geometry": {"coordinates":[7.987549,46.319118],"type":"Point"}
}