{
  "type": "Feature",
  "properties": {
    "iso:country":"CH",
    "sg:address":"Scheuchzerstrasse 69",
    "sg:city":"Z\u00fcrich",
    "sg:orig_category":"Sonstiger Grosshandel",
    "sg:postcode":"8006",
    "sg:province":"Z\u00fcrich",
    "wof:name":"Emkatech Ryser Marc",
    "wof:placetype":"venue"
},
  "geometry": {"coordinates":[8.296620369,47.3763389587],"type":"Point"}
}