{
  "type": "Feature",
  "properties": {
    "iso:country":"CH",
    "sg:address":"Bergstrasse 120 8708 M\u00e4nnedorf. Postfach",
    "sg:city":"M\u00e4nnedorf",
    "sg:orig_category":"Sonderschulen Wohnheime f\u00fcr Kinder U Jugendliche",
    "sg:phone":"+41 19200358",
    "sg:postcode":"8708",
    "sg:province":"Z\u00fcrich",
    "wof:name":"Kant.kinderheim Br\u00fcschhalde",
    "wof:placetype":"venue"
},
  "geometry": {"coordinates":[8.7015800476,47.2533798218],"type":"Point"}
}