{
  "type": "Feature",
  "properties": {
    "iso:country":"CH",
    "sg:address":"Obstgarten 1",
    "sg:city":"Niederhelfenschwil",
    "sg:orig_category":"Mechanik Werkzeugschleifereien",
    "sg:phone":"+41 71 744 04 24",
    "sg:postcode":"9527",
    "sg:province":"St. Gallen",
    "wof:name":"Pfaffstaller / Kr\u00f6ss Gmbh Dienstleistungen Auf Den Gebieten Nachschleifservice Von Werkzeugen Usw",
    "wof:placetype":"venue"
},
  "geometry": {"coordinates":[9.6350574493,47.4486122131],"type":"Point"}
}