{
  "type": "Feature",
  "properties": {
    "iso:country":"CH",
    "sg:address":"1595",
    "sg:city":"Clavaleyres",
    "sg:orig_category":"Landesverteidigung, Sozialversicherung \u00d6ffentliche Verwaltung",
    "sg:phone":"+41 31 747 89 75",
    "sg:postcode":"1595",
    "sg:province":"Bern",
    "wof:name":"Centre De Protection Civile",
    "wof:placetype":"venue"
},
  "geometry": {"coordinates":[7.0906162262,46.8994026184],"type":"Point"}
}