{
  "type": "Feature",
  "properties": {
    "iso:country":"CH",
    "sg:address":"Dorfstrasse 2a",
    "sg:city":"Muolen",
    "sg:orig_category":"Erschliessung von Grundst\u00fccken",
    "sg:phone":"+41 62 758 35 39",
    "sg:postcode":"9313",
    "sg:province":"St. Gallen",
    "wof:name":"Wohnbaugen.langnau Wl",
    "wof:placetype":"venue"
},
  "geometry": {"coordinates":[7.9593119621,47.2305374146],"type":"Point"}
}