{
  "type": "Feature",
  "properties": {
    "iso:country":"CH",
    "sg:address":"Schlosshaldenstrasse 25",
    "sg:city":"Wittenbach",
    "sg:orig_category":"HERSTELLUNG VON GER\u00c4TEN DER ELEKTRIZIT\u00c4TSERZEUGUNG, -VERTEILUNG U.\u00c4 Herstellung von Hebezeugen U F\u00f6r",
    "sg:phone":"+41 71 298 09 09",
    "sg:postcode":"9303",
    "wof:name":"Marotec Ag Zerst\u00e4ubungstechnik",
    "wof:placetype":"venue"
},
  "geometry": {"coordinates":[9.3831806183,47.4638786316],"type":"Point"}
}