{
  "type": "Feature",
  "properties": {
    "iso:country":"CH",
    "sg:address":"Avenue Vinet 16",
    "sg:city":"Lausanne",
    "sg:orig_category":"P\u00e9dicure",
    "sg:phone":"+41 21 648 18 88",
    "sg:postcode":"1004",
    "sg:province":"Vaud",
    "wof:name":"Fran\u00e7oise Guignard P\u00e9dicure",
    "wof:placetype":"venue"
},
  "geometry": {"coordinates":[6.6299471855,46.5256767273],"type":"Point"}
}