{
  "type": "Feature",
  "properties": {
    "iso:country":"CH",
    "sg:address":"7417",
    "sg:city":"Trans",
    "sg:orig_category":"Landesverteidigung, Sozialversicherung \u00d6ffentliche Verwaltung",
    "sg:phone":"+41 81 655 19 66",
    "sg:postcode":"7417",
    "sg:province":"Graubunden",
    "wof:name":"Zivilschutzstelle Trans",
    "wof:placetype":"venue"
},
  "geometry": {"coordinates":[9.4602603912,46.7651596069],"type":"Point"}
}