{
  "type": "Feature",
  "properties": {
    "iso:country":"CH",
    "sg:address":"8585",
    "sg:city":"Herrenhof",
    "sg:orig_category":"Obstbau",
    "sg:phone":"+41 61 401 31 43",
    "sg:postcode":"8585",
    "sg:province":"Thurgau",
    "wof:name":"Hanspeter & Renate Ryser Obstbau",
    "wof:placetype":"venue"
},
  "geometry": {"coordinates":[7.554901123,47.515045166],"type":"Point"}
}