{
  "type": "Feature",
  "properties": {
    "iso:country":"CH",
    "sg:address":"Kreuzmatte 3",
    "sg:city":"Ennetb\u00fcrgen",
    "sg:orig_category":"Mit dem Versicherungsgewerbe verbundene T\u00e4tigkeiten",
    "sg:postcode":"6373",
    "sg:province":"Nidwalden",
    "wof:name":"Riva Bruno",
    "wof:placetype":"venue"
},
  "geometry": {"coordinates":[8.4120550156,46.9855728149],"type":"Point"}
}