{
  "type": "Feature",
  "properties": {
    "iso:country":"CH",
    "sg:address":"R\u00f6tzmattweg 66 4600 Olten. Postfach",
    "sg:city":"Olten",
    "sg:orig_category":"Herstellung von Metallkonstruktionen",
    "sg:postcode":"4600",
    "sg:province":"Solothurn",
    "wof:name":"Schibli Josef",
    "wof:placetype":"venue"
},
  "geometry": {"coordinates":[7.8974580765,47.3463554382],"type":"Point"}
}