{
  "type": "Feature",
  "properties": {
    "iso:country":"CH",
    "sg:address":"Hauptstrasse 21",
    "sg:city":"Derendingen",
    "sg:orig_category":"Detailhandel mit M\u00f6beln U Haushaltsgegenst\u00e4nden Grosshandel mit M\u00f6beln, Wohnbedarf, Teppichen U Bode",
    "sg:phone":"+41 32 682 32 80",
    "sg:postcode":"4552",
    "sg:province":"Solothurn",
    "wof:name":"Budo Gmbh",
    "wof:placetype":"venue"
},
  "geometry": {"coordinates":[7.5841112137,47.1976318359],"type":"Point"}
}