{
  "type": "Feature",
  "properties": {
    "iso:country":"CH",
    "sg:address":"Bodenackerstrasse 51",
    "sg:city":"Dulliken",
    "sg:orig_category":"Unclassifiable Establishments",
    "sg:postcode":"4657",
    "sg:province":"Solothurn",
    "wof:name":"Buchversand Gloggner",
    "wof:placetype":"venue"
},
  "geometry": {"coordinates":[8.6847753525,47.2698974609],"type":"Point"}
}