{
  "type": "Feature",
  "properties": {
    "iso:country":"CH",
    "sg:address":"6864",
    "sg:city":"Arzo",
    "sg:orig_category":"S\u00e4ge, Hobel U Holzimpr\u00e4gnierwerke",
    "sg:phone":"+41 91 647 27 65",
    "sg:postcode":"6864",
    "sg:province":"Ticino",
    "wof:name":"Broggi Alberto",
    "wof:placetype":"venue"
},
  "geometry": {"coordinates":[8.9395303726,45.8800201416],"type":"Point"}
}