{
  "type": "Feature",
  "properties": {
    "iso:country":"CH",
    "sg:address":"Rheinstrasse 10",
    "sg:city":"Frauenfeld",
    "sg:orig_category":"Unclassifiable Establishments",
    "sg:postcode":"8500",
    "sg:province":"Thurgau",
    "wof:name":"Partex Holding Ag Frauenfeld",
    "wof:placetype":"venue"
},
  "geometry": {"coordinates":[8.8959579468,47.5562744141],"type":"Point"}
}