{
  "type": "Feature",
  "properties": {
    "iso:country":"CH",
    "sg:address":"Rosengasse 1",
    "sg:city":"Glarus",
    "sg:classifiers":[
        {
            "category":"Professional",
            "subcategory":"Employment Agencies",
            "type":"Services"
        }
    ],
    "sg:phone":"+41 55 640 15 25",
    "sg:postcode":"8750",
    "sg:province":"Glarus",
    "sg:tags":[
        "personal",
        "u",
        "stellenvermittlung"
    ],
    "wof:name":"T.m. Kreis Ag",
    "wof:placetype":"venue"
},
  "geometry": {"coordinates":[9.0705013275,47.0379676819],"type":"Point"}
}