{
  "type": "Feature",
  "properties": {
    "iso:country":"CH",
    "sg:address":"H\u00fcttnerstr. 42 8835 Feusisberg. Postfach",
    "sg:city":"Schindellegi",
    "sg:orig_category":"Herstellung von Konstruktionsteilen, Fertigbauteilen U Ausbauelementen aus Holz",
    "sg:postcode":"8834",
    "sg:province":"Schwyz",
    "wof:name":"Gadmer-ineichen Hans",
    "wof:placetype":"venue"
},
  "geometry": {"coordinates":[9.8209104538,46.7938690186],"type":"Point"}
}