{
  "type": "Feature",
  "properties": {
    "addr:full":"Helvetiastrasse 47 St.gallen St. Gallen 9000",
    "addr:housenumber":"47",
    "addr:postcode":"9000",
    "addr:street":"Helvetiastrasse",
    "iso:country":"CH",
    "sg:address":"Helvetiastrasse 47",
    "sg:city":"St.gallen",
    "sg:orig_category":"Detailhandel mit Bekleidung Kleiderboutiquen",
    "sg:phone":"+41 71 245 04 75",
    "sg:postcode":"9000",
    "sg:province":"St. Gallen",
    "wof:name":"Boutique H, Hungerb\u00fchler Heidi",
    "wof:placetype":"venue"
},
  "geometry": {"coordinates":[9.3954,47.43359],"type":"Point"}
}