{
  "type": "Feature",
  "properties": {
    "addr:full":"Rue Saint-honor\u00e9 1 Neuch\u00e2tel Neuch\u00e2tel 2000",
    "addr:housenumber":"1",
    "addr:postcode":"2000",
    "addr:street":"Rue Saint-Honore\u0301",
    "iso:country":"CH",
    "sg:address":"Rue Saint-honor\u00e9 1",
    "sg:city":"Neuch\u00e2tel",
    "sg:orig_category":"Arztpraxen",
    "sg:phone":"+41 32 724 58 15",
    "sg:postcode":"2000",
    "sg:province":"Neuch\u00e2tel",
    "wof:name":"Dr M\u00e9d. Vlado Simunovic M\u00e9decin Sp\u00e9cialiste Fmh",
    "wof:placetype":"venue"
},
  "geometry": {"coordinates":[6.931357,46.990891],"type":"Point"}
}