{
  "type": "Feature",
  "properties": {
    "iso:country":"CH",
    "sg:address":"Hauptstr. 24",
    "sg:city":"B\u00f6ckten",
    "sg:orig_category":"Handel mit Automobilen",
    "sg:postcode":"4461",
    "sg:province":"Basel-Landschaft",
    "wof:name":"Rohrmatt-automobile, B\u00fcrgin Elisabeth",
    "wof:placetype":"venue"
},
  "geometry": {"coordinates":[7.839263916,47.4631881714],"type":"Point"}
}