{
  "type": "Feature",
  "properties": {
    "iso:country":"CH",
    "sg:address":"Dorfstrasse 7b",
    "sg:city":"B\u00fcnzen",
    "sg:orig_category":"Grosshandel mit Datenverarbeitungsger\u00e4ten",
    "sg:phone":"+41 56 666 31 10",
    "sg:postcode":"5624",
    "sg:province":"Aargau",
    "wof:name":"Information Projects & Services Gmbh",
    "wof:placetype":"venue"
},
  "geometry": {"coordinates":[8.322640419,47.3099098206],"type":"Point"}
}