{
  "type": "Feature",
  "properties": {
    "iso:country":"CH",
    "sg:address":"3949",
    "sg:city":"Hohtenn",
    "sg:orig_category":"RESTAURANTS: TEA-ROOMS",
    "sg:postcode":"3949",
    "sg:province":"Valais",
    "wof:name":"Restaurant Bergholz, Maurer & Kohler",
    "wof:placetype":"venue"
},
  "geometry": {"coordinates":[9.0382299423,47.4578742981],"type":"Point"}
}