{
  "type": "Feature",
  "properties": {
    "iso:country":"CH",
    "sg:address":"Scheunerweg 26",
    "sg:city":"Ittigen",
    "sg:orig_category":"Fachdetailhandel in Verkaufsr\u00e4umen Herstellung von Futtermitteln f\u00fcr Nutztiere",
    "sg:phone":"+41 31 921 02 71",
    "sg:postcode":"3063",
    "sg:province":"Bern",
    "wof:name":"Peter Bracher Hunden\u00e4hrmittel",
    "wof:placetype":"venue"
},
  "geometry": {"coordinates":[7.4763240814,46.9718780518],"type":"Point"}
}