{
  "type": "Feature",
  "properties": {
    "iso:country":"CH",
    "sg:address":"Amriswiler Strasse 46",
    "sg:city":"Weinfelden",
    "sg:orig_category":"Betrieb von Taxis",
    "sg:phone":"+41 71 622 22 55",
    "sg:postcode":"8570",
    "sg:province":"Thurgau",
    "wof:name":"Taxizentrale A.schmid",
    "wof:placetype":"venue"
},
  "geometry": {"coordinates":[9.116036,47.566868],"type":"Point"}
}