{
  "type": "Feature",
  "properties": {
    "addr:full":"Forrenbergstrasse 50 Seuzach Z\u00fcrich 8472",
    "addr:housenumber":"50",
    "addr:postcode":"8472",
    "addr:street":"Forrenbergstrasse",
    "iso:country":"CH",
    "sg:address":"Forrenbergstrasse 50",
    "sg:city":"Seuzach",
    "sg:orig_category":"Architektur U Ingenieurb\u00fcros",
    "sg:phone":"+41 52 243 03 30",
    "sg:postcode":"8472",
    "sg:province":"Z\u00fcrich",
    "wof:name":"Rootec Gmbh",
    "wof:placetype":"venue"
},
  "geometry": {"coordinates":[8.73018,47.527294],"type":"Point"}
}