{
  "type": "Feature",
  "properties": {
    "iso:country":"CH",
    "sg:address":"Buchsistrasse 25",
    "sg:city":"Th\u00f6rigen",
    "sg:orig_category":"Haltung von Schweinen",
    "sg:phone":"+41 62 961 41 35",
    "sg:postcode":"3367",
    "sg:province":"Bern",
    "wof:name":"Josef Burri Schweinezucht",
    "wof:placetype":"venue"
},
  "geometry": {"coordinates":[7.7272548676,47.1747016907],"type":"Point"}
}