{
  "type": "Feature",
  "properties": {
    "iso:country":"CH",
    "sg:address":"Gotthardstrasse 27",
    "sg:city":"Zug",
    "sg:orig_category":"Akupunktur Massagestudios",
    "sg:phone":"+41 41 710 89 89",
    "sg:postcode":"6300",
    "sg:province":"Zug",
    "wof:name":"Rita Diener Akupunktur & Massagen",
    "wof:placetype":"venue"
},
  "geometry": {"coordinates":[8.513626,47.172619],"type":"Point"}
}