{
  "type": "Feature",
  "properties": {
    "iso:country":"CH",
    "sg:address":"Watterstrasse 59",
    "sg:city":"Regensdorf",
    "sg:orig_category":"Grosshandel mit Textilien",
    "sg:phone":"+41 12115148",
    "sg:postcode":"8105",
    "sg:province":"Z\u00fcrich",
    "wof:name":"Toa Ag",
    "wof:placetype":"venue"
},
  "geometry": {"coordinates":[8.4668006897,47.4322471619],"type":"Point"}
}