{
  "type": "Feature",
  "properties": {
    "iso:country":"CH",
    "sg:address":"Route Principale 222",
    "sg:city":"Sugiez",
    "sg:orig_category":"Nationale Postdienste",
    "sg:phone":"+41 26 673 15 06",
    "sg:postcode":"1786",
    "sg:province":"Fribourg",
    "wof:name":"La Poste Suisse",
    "wof:placetype":"venue"
},
  "geometry": {"coordinates":[7.1074199677,46.9571495056],"type":"Point"}
}