{
  "type": "Feature",
  "properties": {
    "iso:country":"CH",
    "sg:address":"Lindhofstrasse 13",
    "sg:city":"M\u00f6nchaltorf",
    "sg:orig_category":"Sonstiger Detailhandel mit Metallwaren, Anstrichmitteln, Glaswaren, Bau U Heimwerkerbedarf",
    "sg:phone":"+41 19481430",
    "sg:postcode":"8617",
    "sg:province":"Z\u00fcrich",
    "wof:name":"Rolf Hollenstein Gartengestaltung Mit Holz",
    "wof:placetype":"venue"
},
  "geometry": {"coordinates":[8.7228603363,47.3123893738],"type":"Point"}
}