{
  "type": "Feature",
  "properties": {
    "iso:country":"CH",
    "sg:address":"Tafletenstrasse 11",
    "sg:city":"Bubikon",
    "sg:orig_category":"Herstellung von Fenstern U T\u00fcren aus Holz Herstellung von Konstruktionsteilen, Fertigbauteilen U Aus",
    "sg:phone":"+41 81 302 16 03",
    "sg:postcode":"8608",
    "sg:province":"Z\u00fcrich",
    "wof:name":"Ferdinand Triet Schreinerei M\u00f6bel Fenster",
    "wof:placetype":"venue"
},
  "geometry": {"coordinates":[9.5063829422,47.0107116699],"type":"Point"}
}