{
  "type": "Feature",
  "properties": {
    "iso:country":"CH",
    "sg:address":"Burggrabenstrasse 18b",
    "sg:city":"Kreuzlingen",
    "sg:orig_category":"Fahrschulen, Flugschulen",
    "sg:phone":"+41 79 351 54 54",
    "sg:postcode":"8280",
    "sg:province":"Thurgau",
    "wof:name":"Peter Treuthardt Autofahrschule",
    "wof:placetype":"venue"
},
  "geometry": {"coordinates":[9.186665535,47.6394538879],"type":"Point"}
}