{
  "type": "Feature",
  "properties": {
    "iso:country":"CH",
    "sg:address":"Frauenfelderstrasse 31",
    "sg:city":"W\u00e4ngi",
    "sg:orig_category":"Herstellung von Konstruktionsteilen, Fertigbauteilen U Ausbauelementen aus Holz Hoch U Tiefbau",
    "sg:phone":"+41 19381700",
    "sg:postcode":"9545",
    "sg:province":"Thurgau",
    "wof:name":"Br\u00fctsch E. Ag",
    "wof:placetype":"venue"
},
  "geometry": {"coordinates":[8.8321075439,47.3028717041],"type":"Point"}
}