{
  "type": "Feature",
  "properties": {
    "iso:country":"CH",
    "sg:address":"Champ Du Pl\u00e2ne 5 2533 Evilard. Postfach",
    "sg:city":"Magglingen/macolin",
    "sg:orig_category":"Erbringung von Dienstleistungen f\u00fcr Unternehmen",
    "sg:postcode":"2532",
    "sg:province":"Bern",
    "wof:name":"Tanner Andr\u00e9",
    "wof:placetype":"venue"
},
  "geometry": {"coordinates":[7.2173628807,47.144153595],"type":"Point"}
}