{
  "type": "Feature",
  "properties": {
    "iso:country":"CH",
    "sg:address":"Nationalquai 1000 Lausanne. Postfach",
    "sg:city":"Lausanne",
    "sg:orig_category":"Instandhaltung U Reparatur von Automobilen",
    "sg:phone":"+41 21 616 07 75",
    "sg:postcode":"1006",
    "sg:province":"Vaud",
    "wof:name":"Gret James.",
    "wof:placetype":"venue"
},
  "geometry": {"coordinates":[6.6947751045,46.5545883179],"type":"Point"}
}