{
  "type": "Feature",
  "properties": {
    "iso:country":"CH",
    "sg:address":"Via De Coisson 13 1214 Vernier. Postfach",
    "sg:city":"Vernier",
    "sg:orig_category":"Markt U Meinungsforschung Sonstige pers\u00f6nliche Dienstleistungen",
    "sg:phone":"+41 22 341 04 02",
    "sg:postcode":"1214",
    "sg:province":"Gen\u00e8ve",
    "wof:name":"Cvm Services Sarl Concept, Vente Etc. De Services Et Produits",
    "wof:placetype":"venue"
},
  "geometry": {"coordinates":[6.0804309845,46.2137985229],"type":"Point"}
}