{
  "type": "Feature",
  "properties": {
    "iso:country":"CH",
    "sg:address":"Erlimattstrasse 4 5035 Unterentfelden. Postfach",
    "sg:city":"Unterentfelden",
    "sg:orig_category":"Unclassifiable Establishments",
    "sg:postcode":"5035",
    "sg:province":"Aargau",
    "wof:name":"Gomo Holding Ag",
    "wof:placetype":"venue"
},
  "geometry": {"coordinates":[8.0418834686,47.3715858459],"type":"Point"}
}