{
  "type": "Feature",
  "properties": {
    "iso:country":"CH",
    "sg:address":"Hohfuhren 222 A 3123 Belp. Postfach",
    "sg:city":"Belp",
    "sg:orig_category":"Sanit\u00e4r U Heizungsinstallation Sanit\u00e4rinstallation U Spenglerei",
    "sg:postcode":"3123",
    "sg:province":"Bern",
    "wof:name":"Ramseier Walter Nachfolger Ramseier J\u00fcrg Sanit\u00e4r-heizung-spenglerei",
    "wof:placetype":"venue"
},
  "geometry": {"coordinates":[7.5148029327,46.8897705078],"type":"Point"}
}