{
  "type": "Feature",
  "properties": {
    "iso:country":"CH",
    "sg:address":"M\u00fchlestrasse 4 3123 Belp. Postfach 76",
    "sg:city":"Belp",
    "sg:orig_category":"Herstellung von Teppichen",
    "sg:phone":"+41 79 819 24 12",
    "sg:postcode":"3123",
    "sg:province":"Bern",
    "wof:name":"Gebr\u00fcder Liechti Gmbh",
    "wof:placetype":"venue"
},
  "geometry": {"coordinates":[7.5015029907,46.8891944885],"type":"Point"}
}