{
  "type": "Feature",
  "properties": {
    "iso:country":"CH",
    "sg:address":"Via Al Ci\u00f2s",
    "sg:city":"Torricella",
    "sg:orig_category":"Vereine Musik/Blasmusik",
    "sg:phone":"+41 91 945 19 08",
    "sg:postcode":"6808",
    "sg:province":"Ticino",
    "wof:name":"St\u00e0 Filarm.torricella-taverne",
    "wof:placetype":"venue"
},
  "geometry": {"coordinates":[8.9221410751,46.0651702881],"type":"Point"}
}