{
  "type": "Feature",
  "properties": {
    "addr:full":"Schulstr. 23 Scheuren Bern 2556",
    "addr:housenumber":"23",
    "addr:postcode":"2556",
    "addr:street":"Schulstr.",
    "iso:country":"CH",
    "sg:address":"Schulstr. 23",
    "sg:city":"Scheuren",
    "sg:orig_category":"Allgemeiner Hoch U Tiefbau",
    "sg:phone":"+41 79 356 59 59",
    "sg:postcode":"2556",
    "sg:province":"Bern",
    "wof:name":"Jakob Kappeler Ag",
    "wof:placetype":"venue"
},
  "geometry": {"coordinates":[7.31777,47.132439],"type":"Point"}
}