{
  "type": "Feature",
  "properties": {
    "iso:country":"CH",
    "sg:address":"Thalberg Rue Sigismond- 2 1201 Gen\u00e8ve. Postfach",
    "sg:city":"Gen\u00e8ve",
    "sg:orig_category":"Fachdetailhandel in Verkaufsr\u00e4umen",
    "sg:phone":"+41 41 630 33 43",
    "sg:postcode":"1201",
    "sg:province":"Gen\u00e8ve",
    "wof:name":"Heco Fleurs Ag",
    "wof:placetype":"venue"
},
  "geometry": {"coordinates":[8.305688858,46.9952163696],"type":"Point"}
}