{
  "type": "Feature",
  "properties": {
    "iso:country":"CH",
    "sg:address":"Alpenstrasse 1 6300 Zug. Postfach",
    "sg:city":"Zug",
    "sg:orig_category":"Unclassifiable Establishments",
    "sg:phone":"+41 41 712 25 25",
    "sg:postcode":"6300",
    "sg:province":"Zug",
    "wof:name":"Mayer & Cie Holding Ag",
    "wof:placetype":"venue"
},
  "geometry": {"coordinates":[8.5137405396,47.1711502075],"type":"Point"}
}