{
  "type": "Feature",
  "properties": {
    "iso:country":"CH",
    "sg:address":"Bachstrasse 35",
    "sg:city":"Th\u00f6rigen",
    "sg:orig_category":"Herstellung von Verpackungsmitteln aus Holz",
    "sg:phone":"+41 62 961 14 74",
    "sg:postcode":"3367",
    "sg:province":"Bern",
    "wof:name":"Hans K\u00e4ser Mechanische K\u00fcferei",
    "wof:placetype":"venue"
},
  "geometry": {"coordinates":[7.7300457954,47.168132782],"type":"Point"}
}