{
  "type": "Feature",
  "properties": {
    "iso:country":"CH",
    "sg:address":"Dorfstrasse 44a",
    "sg:city":"Mirchel",
    "sg:orig_category":"Detailhandel Einzelhandel mit Automobilteilen U Zubeh\u00f6r Reparatur von Gebrauchsg\u00fctern",
    "sg:phone":"+41 22 342 23 78",
    "sg:postcode":"3532",
    "sg:province":"Bern",
    "wof:name":"Edouard Hostettler",
    "wof:placetype":"venue"
},
  "geometry": {"coordinates":[6.1478619576,46.1764793396],"type":"Point"}
}