{
  "type": "Feature",
  "properties": {
    "iso:country":"CH",
    "sg:address":"Reutenenstrasse 8",
    "sg:city":"Windisch",
    "sg:orig_category":"Detailhandel mit Fleisch U Fleischwaren",
    "sg:phone":"+41 56 441 23 08",
    "sg:postcode":"5210",
    "sg:province":"Aargau",
    "wof:name":"Meier Hansruedi",
    "wof:placetype":"venue"
},
  "geometry": {"coordinates":[8.2080259323,47.4759864807],"type":"Point"}
}