{
  "type": "Feature",
  "properties": {
    "iso:country":"CH",
    "sg:address":"Glarnerstrasse 7",
    "sg:city":"Siebnen",
    "sg:orig_category":"Allgemeiner Hoch U Tiefbau Vermittlung von Immobilien",
    "sg:phone":"+41 55 440 45 03",
    "sg:postcode":"8854",
    "sg:province":"Schwyz",
    "wof:name":"Weibel G. Ag, Planung, Beratung, Verkauf",
    "wof:placetype":"venue"
},
  "geometry": {"coordinates":[8.898065,47.174755],"type":"Point"}
}