{
  "type": "Feature",
  "properties": {
    "iso:country":"CH",
    "sg:address":"Gustackerstrasse 15",
    "sg:city":"Bottmingen",
    "sg:orig_category":"Vereine Gesang",
    "sg:phone":"+41 61 701 62 92",
    "sg:postcode":"4103",
    "sg:province":"Basel-Landschaft",
    "wof:name":"Regio-chor Binningen/basel",
    "wof:placetype":"venue"
},
  "geometry": {"coordinates":[7.5674071312,47.5235519409],"type":"Point"}
}