{
  "type": "Feature",
  "properties": {
    "addr:full":"Hauptstrasse 27 Reiden Luzern 6260",
    "addr:housenumber":"27",
    "addr:postcode":"6260",
    "addr:street":"Hauptstrasse",
    "iso:country":"CH",
    "sg:address":"Hauptstrasse 27",
    "sg:city":"Reiden",
    "sg:orig_category":"Detailhandel mit Brot, Back U S\u00fcsswaren",
    "sg:phone":"+41 62 758 22 33",
    "sg:postcode":"6260",
    "sg:province":"Luzern",
    "wof:name":"B\u00e4ckerei-konditorei Nyffenegger",
    "wof:placetype":"venue"
},
  "geometry": {"coordinates":[7.971223,47.243732],"type":"Point"}
}