{
  "type": "Feature",
  "properties": {
    "iso:country":"CH",
    "sg:address":"B\u00e4chtoldstrasse 4",
    "sg:city":"Z\u00fcrich",
    "sg:orig_category":"Datenverarbeitungsdienste",
    "sg:phone":"+41 17370485",
    "sg:postcode":"8044",
    "sg:province":"Z\u00fcrich",
    "wof:name":"Ernst Brand Edv-beratung",
    "wof:placetype":"venue"
},
  "geometry": {"coordinates":[8.444825,47.359364],"type":"Point"}
}