{
  "type": "Feature",
  "properties": {
    "iso:country":"CH",
    "sg:address":"Plaine Route De La 20 1026 Denges. Postfach",
    "sg:city":"Denges",
    "sg:orig_category":"Instandhaltung U Reparatur von Automobilen",
    "sg:phone":"+41 71 333 34 35",
    "sg:postcode":"1026",
    "sg:province":"Vaud",
    "wof:name":"Rotbach-garage Drexel Ag",
    "wof:placetype":"venue"
},
  "geometry": {"coordinates":[9.3923788071,47.3891868591],"type":"Point"}
}