{
  "type": "Feature",
  "properties": {
    "iso:country":"CH",
    "sg:address":"Himmelrichstrasse 24",
    "sg:city":"Baldegg",
    "sg:orig_category":"Detailhandel mit Antiquit\u00e4ten",
    "sg:phone":"+41 41 910 33 63",
    "sg:postcode":"6283",
    "sg:province":"Luzern",
    "wof:name":"Beat Giger Antiquit\u00e4ten",
    "wof:placetype":"venue"
},
  "geometry": {"coordinates":[8.281954,47.184326],"type":"Point"}
}