{
  "type": "Feature",
  "properties": {
    "iso:country":"CH",
    "sg:address":"Via Bossi 6a",
    "sg:city":"Chiasso",
    "sg:orig_category":"Autogaragen Handel mit Automobilen",
    "sg:phone":"+41 33 438 15 74",
    "sg:postcode":"6830",
    "sg:province":"Ticino",
    "wof:name":"Dummermuth + Kr\u00c4henb\u00dchl",
    "wof:placetype":"venue"
},
  "geometry": {"coordinates":[7.658954,46.794609],"type":"Point"}
}