{
  "type": "Feature",
  "properties": {
    "iso:country":"CH",
    "sg:address":"Fr\u00f6belstrasse 11 8032 Z\u00fcrich. Postfach",
    "sg:city":"Z\u00fcrich",
    "sg:orig_category":"Verlagsgewerbe",
    "sg:phone":"+41 13812367",
    "sg:postcode":"8029",
    "wof:name":"Edition R & F Ruth Mayer",
    "wof:placetype":"venue"
},
  "geometry": {"coordinates":[8.5664825439,47.3617515564],"type":"Point"}
}