{
  "type": "Feature",
  "properties": {
    "iso:country":"CH",
    "sg:address":"Seftigenstrasse 205",
    "sg:city":"Wabern",
    "sg:orig_category":"Detailhandel mit Blumen U Pflanzen",
    "sg:phone":"+41 31 961 44 04",
    "sg:postcode":"3084",
    "sg:province":"Bern",
    "wof:name":"Sonja Muster Blumengesch\u00e4ft Sonfleur",
    "wof:placetype":"venue"
},
  "geometry": {"coordinates":[7.448346,46.930244],"type":"Point"}
}