{
  "type": "Feature",
  "properties": {
    "iso:country":"CH",
    "sg:address":"S\u00e4gegasse 51",
    "sg:city":"M\u00fcnsingen",
    "sg:orig_category":"Allgemeiner Hoch U Tiefbau",
    "sg:postcode":"3110",
    "sg:province":"Bern",
    "wof:name":"Mosimann/m\u00e4chler Gmbh",
    "wof:placetype":"venue"
},
  "geometry": {"coordinates":[8.734148,47.197395],"type":"Point"}
}