{
  "type": "Feature",
  "properties": {
    "iso:country":"CH",
    "sg:address":"Rue Du Bugnon 19",
    "sg:city":"Lausanne",
    "sg:orig_category":"Informatikschulen",
    "sg:phone":"+41 21 314 46 80",
    "sg:postcode":"1005",
    "sg:province":"Vaud",
    "wof:name":"Ecole Cant.vaud.de Techniciens En Radiologie M\u00e9dicale",
    "wof:placetype":"venue"
},
  "geometry": {"coordinates":[6.6405267715,46.5246238708],"type":"Point"}
}