{
  "type": "Feature",
  "properties": {
    "iso:country":"CH",
    "sg:address":"H\u00fcbeliweg 9",
    "sg:city":"M\u00fcnchenbuchsee",
    "sg:orig_category":"Geb\u00e4ude, Wohnungsreinigung Reinigungsgewerbe",
    "sg:phone":"+41 31 869 40 40",
    "sg:postcode":"3053",
    "sg:province":"Bern",
    "wof:name":"Up-reinigungsdienst, Utz Andreas",
    "wof:placetype":"venue"
},
  "geometry": {"coordinates":[7.438560009,47.0203285217],"type":"Point"}
}