{
  "type": "Feature",
  "properties": {
    "iso:country":"CH",
    "sg:address":"Ochsengasse 20",
    "sg:city":"Allschwil",
    "sg:orig_category":"Erschliessung von Grundst\u00fccken",
    "sg:postcode":"4123",
    "sg:province":"Basel-Landschaft",
    "wof:name":"Bbg Basler Baugesellschaft Ag",
    "wof:placetype":"venue"
},
  "geometry": {"coordinates":[7.5395298004,47.5492095947],"type":"Point"}
}