{
  "type": "Feature",
  "properties": {
    "iso:country":"CH",
    "sg:address":"St. Alban-rheinweg 144 4052 Basel. Postfach",
    "sg:city":"Basel",
    "sg:orig_category":"Herstellung von elektrischen Lampen U Leuchten",
    "sg:phone":"+41 61 312 44 22",
    "sg:postcode":"4052",
    "sg:province":"Basel-Stadt",
    "wof:name":"Urs Siegenthaler Ag Beleuchtungsanlagen; Optimierung, Einrichtung Usw",
    "wof:placetype":"venue"
},
  "geometry": {"coordinates":[7.60623312,47.5550727844],"type":"Point"}
}