{
  "type": "Feature",
  "properties": {
    "iso:country":"CH",
    "sg:address":"Via Maggio 1 6900 Lugano. Postfach 6906 Lugano",
    "sg:city":"Caselle",
    "sg:orig_category":"Vermietung U Verpachtung von eigenen Immobilien",
    "sg:postcode":"6",
    "wof:name":"Al Rosaio Sa",
    "wof:placetype":"venue"
},
  "geometry": {"coordinates":[8.961098671,46.0080337524],"type":"Point"}
}