{
  "type": "Feature",
  "properties": {
    "iso:country":"CH",
    "sg:address":"4716",
    "sg:city":"G\u00e4nsbrunnen",
    "sg:classifiers":[
        {
            "category":"Restaurant",
            "type":"Food & Drink"
        }
    ],
    "sg:phone":"+41 32 639 13 13",
    "sg:postcode":"4716",
    "sg:province":"Solothurn",
    "wof:name":"Restaurant Binzberg",
    "wof:placetype":"venue"
},
  "geometry": {"coordinates":[7.4681038857,47.2623519897],"type":"Point"}
}