{
  "type": "Feature",
  "properties": {
    "iso:country":"CH",
    "sg:address":"Neumattstrasse 1",
    "sg:city":"Aarau",
    "sg:orig_category":"Non-Classified Establishments",
    "sg:postcode":"5000",
    "sg:province":"Aargau",
    "wof:name":"Az Vertriebs Ag",
    "wof:placetype":"venue"
},
  "geometry": {"coordinates":[8.0664024353,47.3979911804],"type":"Point"}
}