{
  "type": "Feature",
  "properties": {
    "iso:country":"CH",
    "sg:address":"Nidfeldstrasse 5",
    "sg:city":"Kriens",
    "sg:orig_category":"Erwachsenenbildung U Unterricht",
    "sg:phone":"+41 41 320 70 08",
    "sg:postcode":"6010",
    "sg:province":"Luzern",
    "wof:name":"Odysseus Siegrist Ren\u00e9",
    "wof:placetype":"venue"
},
  "geometry": {"coordinates":[8.2958450317,47.0304374695],"type":"Point"}
}