{
  "type": "Feature",
  "properties": {
    "iso:country":"CH",
    "sg:address":"Rue Centrale 16",
    "sg:city":"St-l\u00e9onard",
    "sg:orig_category":"Nationale Postdienste",
    "sg:phone":"+41 27 203 22 91",
    "sg:postcode":"1958",
    "sg:province":"Valais",
    "wof:name":"La Poste Suisse",
    "wof:placetype":"venue"
},
  "geometry": {"coordinates":[7.4176311493,46.2540588379],"type":"Point"}
}