{
  "type": "Feature",
  "properties": {
    "iso:country":"CH",
    "sg:address":"Wihaldenstrasse 27b",
    "sg:city":"Bubikon",
    "sg:orig_category":"Unclassifiable Establishments",
    "sg:phone":"+41 55 243 49 00",
    "sg:postcode":"8608",
    "sg:province":"Z\u00fcrich",
    "wof:name":"Bachmann Bau Ag",
    "wof:placetype":"venue"
},
  "geometry": {"coordinates":[8.8172187805,47.2639312744],"type":"Point"}
}