{
  "type": "Feature",
  "properties": {
    "iso:country":"CH",
    "sg:address":"Im Chl\u00f6sterli 6",
    "sg:city":"Urdorf",
    "sg:orig_category":"Detailhandel mit Antiquit\u00e4ten U Gebrauchtwaren in Verkaufsr\u00e4umen Detailhandel mit Bekleidung",
    "sg:phone":"+41 17351991",
    "sg:postcode":"8902",
    "sg:province":"Z\u00fcrich",
    "wof:name":"Joker Mode Daniel Marty",
    "wof:placetype":"venue"
},
  "geometry": {"coordinates":[8.420795,47.381748],"type":"Point"}
}