{
  "type": "Feature",
  "properties": {
    "iso:country":"CH",
    "sg:address":"Sternenstrasse 35",
    "sg:city":"Herzogenbuchsee",
    "sg:orig_category":"Herstellung von Konstruktionsteilen, Fertigbauteilen U Ausbauelementen aus Holz",
    "sg:phone":"+41 62 398 48 48",
    "sg:postcode":"3360",
    "sg:province":"Bern",
    "wof:name":"Hoch Fenstertechnik Ag",
    "wof:placetype":"venue"
},
  "geometry": {"coordinates":[7.7078590393,47.191986084],"type":"Point"}
}