{
  "type": "Feature",
  "properties": {
    "iso:country":"CH",
    "sg:address":"3317",
    "sg:city":"M\u00fclchi",
    "sg:orig_category":"Herstellung von sonstigen landwirtschaftlichen Maschinen Mechanische Werkst\u00e4tten",
    "sg:phone":"+41 71 755 30 49",
    "sg:postcode":"3317",
    "sg:province":"Bern",
    "wof:name":"Andreas Heeb Mech.werkstatt & Landmaschinen",
    "wof:placetype":"venue"
},
  "geometry": {"coordinates":[9.5155897141,47.3734283447],"type":"Point"}
}