{
  "type": "Feature",
  "properties": {
    "iso:country":"CH",
    "sg:address":"Worbstrasse 170 3073 G\u00fcmligen. Postfach 264",
    "sg:city":"G\u00fcmligen",
    "sg:orig_category":"Detailhandel mit Computern U Software",
    "sg:phone":"+41 31 958 55 55",
    "sg:postcode":"3073",
    "sg:province":"Bern",
    "wof:name":"Delec Ag",
    "wof:placetype":"venue"
},
  "geometry": {"coordinates":[7.500334,46.934555],"type":"Point"}
}