{
  "type": "Feature",
  "properties": {
    "iso:country":"CH",
    "sg:address":"Dorfstrasse 25",
    "sg:city":"Brunnadern",
    "sg:classifiers":[
        {
            "category":"Travel",
            "subcategory":"Hotels & Motels",
            "type":"Entertainment"
        }
    ],
    "sg:phone":"+41 71 374 12 59",
    "sg:postcode":"9125",
    "sg:province":"St. Gallen",
    "sg:tags":[
        "hotels",
        "mit",
        "restaurant"
    ],
    "wof:name":"Gasthaus Krone, Gerster Natalie Restaurationsbetrieb, Bes. Spezialit\u00e4tenbeiz",
    "wof:placetype":"venue"
},
  "geometry": {"coordinates":[9.1315755844,47.3350105286],"type":"Point"}
}