{
  "type": "Feature",
  "properties": {
    "iso:country":"CH",
    "sg:address":"Hauptgasse 49 9050 Appenzell. Postfach",
    "sg:city":"Appenzell",
    "sg:orig_category":"Knee And Ankle Protective Coverings",
    "sg:phone":"+41 17763436",
    "sg:postcode":"9050",
    "sg:province":"Appenzell Innerhoden",
    "wof:name":"Power-bike Gmbh",
    "wof:placetype":"venue"
},
  "geometry": {"coordinates":[8.4508714676,47.2806625366],"type":"Point"}
}