{
  "type": "Feature",
  "properties": {
    "iso:country":"CH",
    "sg:address":"Riedwiesenstrasse 20",
    "sg:city":"Dietlikon",
    "sg:orig_category":"Instandhaltung U Reparatur von Automobilen Mechanische Werkst\u00e4tten",
    "sg:phone":"+41 18337377",
    "sg:postcode":"8305",
    "sg:province":"Z\u00fcrich",
    "wof:name":"Mech Point Gmbh",
    "wof:placetype":"venue"
},
  "geometry": {"coordinates":[8.6268825531,47.4133682251],"type":"Point"}
}