{
  "type": "Feature",
  "properties": {
    "iso:country":"CH",
    "sg:address":"Zimmertalstrasse 2",
    "sg:city":"Sarnen",
    "sg:orig_category":"Erschliessung von Grundst\u00fccken",
    "sg:postcode":"6060",
    "sg:province":"Obwalden",
    "wof:name":"Gewo Genossenschaft F\u00fcr Gemeinn\u00fctzigen Wohnungsbau, Sarnen",
    "wof:placetype":"venue"
},
  "geometry": {"coordinates":[8.2457742691,46.9052085876],"type":"Point"}
}