{
  "type": "Feature",
  "properties": {
    "iso:country":"CH",
    "sg:address":"Mitteldorf 2",
    "sg:city":"Kallnach",
    "sg:orig_category":"RESTAURANTS: TEA-ROOMS",
    "sg:phone":"+41 32 392 14 22",
    "sg:postcode":"3283",
    "sg:province":"Bern",
    "wof:name":"Restaurant Sternen, R\u00f6thlisberger K.",
    "wof:placetype":"venue"
},
  "geometry": {"coordinates":[7.2361588478,47.0215950012],"type":"Point"}
}