{
  "type": "Feature",
  "properties": {
    "iso:country":"CH",
    "sg:address":"La Mauguettaz",
    "sg:city":"Yvonand",
    "sg:orig_category":"Herstellung von Fenstern U T\u00fcren aus Holz",
    "sg:phone":"+41 24 430 12 59",
    "sg:postcode":"1462",
    "sg:province":"Vaud",
    "wof:name":"Ego Kiefer Ag Fenster & T\u00fcren",
    "wof:placetype":"venue"
},
  "geometry": {"coordinates":[6.7211999893,46.7800292969],"type":"Point"}
}