{
  "type": "Feature",
  "properties": {
    "iso:country":"CH",
    "sg:address":"Hohlstrasse 457",
    "sg:city":"Z\u00fcrich",
    "sg:orig_category":"Bars Erbringung von sonstigen Dienstleistungen f\u00fcr Unterhaltung, Erholung U Freizeit",
    "sg:phone":"+41 56 621 08 80",
    "sg:postcode":"8048",
    "sg:province":"Z\u00fcrich",
    "wof:name":"Billard G & Internet Wohlen",
    "wof:placetype":"venue"
},
  "geometry": {"coordinates":[8.274656,47.344856],"type":"Point"}
}