{
  "type": "Feature",
  "properties": {
    "iso:country":"CH",
    "sg:address":"6197",
    "sg:city":"Schangnau",
    "sg:orig_category":"Sportvereine Sch\u00fctzen Pistolen-& Gewehr",
    "sg:postcode":"6197",
    "sg:province":"Bern",
    "wof:name":"Pistolensch\u00fctzen",
    "wof:placetype":"venue"
},
  "geometry": {"coordinates":[7.8605628014,46.8275260925],"type":"Point"}
}