{
  "type": "Feature",
  "properties": {
    "iso:country":"CH",
    "sg:address":"Meienbergstrasse 59",
    "sg:city":"Jona",
    "sg:orig_category":"Finanzierungsinstitutionen",
    "sg:phone":"+41 55 210 75 86",
    "sg:postcode":"8645",
    "sg:province":"St. Gallen",
    "wof:name":"Walter Weber Finanz, Immobilien Und Wirtschaftsberatung",
    "wof:placetype":"venue"
},
  "geometry": {"coordinates":[8.8277759552,47.2382965088],"type":"Point"}
}