{
  "type": "Feature",
  "properties": {
    "iso:country":"CH",
    "sg:address":"Avenue De La Gare 2",
    "sg:city":"Ch\u00e2tel St Denis",
    "sg:classifiers":[
        {
            "category":"Banks & Credit Unions",
            "subcategory":"Bank",
            "type":"Services"
        }
    ],
    "sg:phone":"+41 21 948 71 51",
    "sg:postcode":"1618",
    "sg:province":"Fribourg",
    "wof:name":"Union De Banques Suisses",
    "wof:placetype":"venue"
},
  "geometry": {"coordinates":[6.900182,46.52589],"type":"Point"}
}