{
  "type": "Feature",
  "properties": {
    "iso:country":"CH",
    "sg:address":"Fabrikstrasse 8 3360 Herzogenbuchsee. Postfach",
    "sg:city":"Herzogenbuchsee",
    "sg:orig_category":"Elektrizit\u00e4tsversorgung Gasversorgung",
    "sg:phone":"+41 55 240 16 51",
    "sg:postcode":"3360",
    "sg:province":"Bern",
    "wof:name":"Gemeindewerke R\u00fcti Elektrizit\u00e4t-gas-wasser",
    "wof:placetype":"venue"
},
  "geometry": {"coordinates":[8.8517770767,47.2560043335],"type":"Point"}
}