{
  "type": "Feature",
  "properties": {
    "iso:country":"CH",
    "sg:address":"Rue De La Borde 31",
    "sg:city":"Lausanne",
    "sg:classifiers":[
        {
            "category":"Restaurant",
            "type":"Food & Drink"
        }
    ],
    "sg:phone":"+41 21 646 03 18",
    "sg:postcode":"1018",
    "sg:province":"Vaud",
    "wof:name":"Caf\u00e9 La Toja",
    "wof:placetype":"venue"
},
  "geometry": {"coordinates":[6.6320309639,46.529296875],"type":"Point"}
}