{
  "type": "Feature",
  "properties": {
    "iso:country":"CH",
    "sg:address":"Via Lische 14 Casella Postale 71",
    "sg:city":"Stabio",
    "sg:classifiers":[
        {
            "category":"Wholesale",
            "subcategory":"Medical Equipment & Supplies",
            "type":"Manufacturing & Wholesale Goods"
        }
    ],
    "sg:phone":"+41 91 647 21 45",
    "sg:postcode":"6855",
    "sg:province":"Ticino",
    "sg:tags":[
        "instrument",
        "health",
        "-",
        "precision"
    ],
    "wof:name":"Rubis Outils Sa",
    "wof:placetype":"venue"
},
  "geometry": {"coordinates":[8.9393825531,45.8523521423],"type":"Point"}
}