{
  "type": "Feature",
  "properties": {
    "iso:country":"CH",
    "sg:address":"Mattenstrasse 84 2503 Biel/bienne Case Postale 51",
    "sg:city":"Biel/bienne",
    "sg:orig_category":"Grosshandel mit Erzen U Metallen Grosshandel mit sonstigen Maschinen U Ausr\u00fcstungen f\u00fcr Industrie, H",
    "sg:phone":"+41 32 323 83 75",
    "sg:postcode":"2501",
    "sg:province":"Bern",
    "wof:name":"Gs Kinetic Systems Ag",
    "wof:placetype":"venue"
},
  "geometry": {"coordinates":[7.2521910667,47.1351165771],"type":"Point"}
}