{
  "type": "Feature",
  "properties": {
    "iso:country":"CH",
    "sg:address":"Ferdinand-gonseth 9",
    "sg:city":"Montagne-sonvilier",
    "sg:orig_category":"RESTAURANTS: TEA-ROOMS",
    "sg:postcode":"2615",
    "sg:province":"Bern",
    "wof:name":"B\u00fctikofer Urs, Rest. Schwert",
    "wof:placetype":"venue"
},
  "geometry": {"coordinates":[8.9413003922,47.2884101868],"type":"Point"}
}