{
  "type": "Feature",
  "properties": {
    "iso:country":"CH",
    "sg:address":"Campestro",
    "sg:city":"Tesserete",
    "sg:orig_category":"Bestattungswesen",
    "sg:phone":"+41 91 943 10 23",
    "sg:postcode":"6950",
    "sg:province":"Ticino",
    "wof:name":"Edo Molteni Funeraria Sa",
    "wof:placetype":"venue"
},
  "geometry": {"coordinates":[8.96756,46.067341],"type":"Point"}
}