{
  "type": "Feature",
  "properties": {
    "iso:country":"CH",
    "sg:address":"Sch\u00fcracherstrasse 29",
    "sg:city":"Br\u00fcttisellen",
    "sg:orig_category":"Malerei-Gipserei Stukkateurgewerbe, Gipserei U Verputzerei",
    "sg:phone":"+41 18331666",
    "sg:postcode":"8306",
    "sg:province":"Z\u00fcrich",
    "wof:name":"Willi St\u00e4deli Gipser-& Stukkaturgesch\u00e4ft",
    "wof:placetype":"venue"
},
  "geometry": {"coordinates":[8.6334648132,47.4190101624],"type":"Point"}
}