{
  "type": "Feature",
  "properties": {
    "iso:country":"CH",
    "sg:address":"Curaglia",
    "sg:city":"Curaglia",
    "sg:classifiers":[
        {
            "category":"Banks & Credit Unions",
            "subcategory":"Bank",
            "type":"Services"
        }
    ],
    "sg:phone":"+41 4191568346",
    "sg:postcode":"6944",
    "sg:province":"Ticino",
    "wof:name":"Societ\u00e0 Di Banca Svizzera",
    "wof:placetype":"venue"
},
  "geometry": {"coordinates":[8.945352,46.036991],"type":"Point"}
}