{
  "type": "Feature",
  "properties": {
    "addr:full":"Dorfpl. Arosa Graubunden 7050",
    "addr:postcode":"7050",
    "iso:country":"CH",
    "sg:address":"Dorfpl.",
    "sg:city":"Arosa",
    "sg:classifiers":[
        {
            "category":"Banks & Credit Unions",
            "subcategory":"Bank",
            "type":"Services"
        }
    ],
    "sg:phone":"+41 81 378 62 62",
    "sg:postcode":"7050",
    "sg:province":"Graubunden",
    "wof:name":"Credit Suisse",
    "wof:placetype":"venue"
},
  "geometry": {"coordinates":[9.677415,46.778339],"type":"Point"}
}