{
  "type": "Feature",
  "properties": {
    "iso:country":"CH",
    "sg:address":"Postgasshalde 41",
    "sg:city":"Bern",
    "sg:classifiers":[
        {
            "category":"Restaurant",
            "type":"Food & Drink"
        }
    ],
    "sg:phone":"+41 31 311 76 85",
    "sg:postcode":"3011",
    "sg:province":"Bern",
    "wof:name":"Club-restaurant Sch\u00fctti",
    "wof:placetype":"venue"
},
  "geometry": {"coordinates":[7.453163147,46.9488983154],"type":"Point"}
}