{
  "type": "Feature",
  "properties": {
    "iso:country":"CH",
    "sg:address":"Strada Regina 1",
    "sg:city":"Lugano",
    "sg:orig_category":"Detailhandel mit Bekleidung Grosshandel mit Bekleidung",
    "sg:phone":"+41 91 993 03 72",
    "sg:postcode":"6900",
    "sg:province":"Ticino",
    "wof:name":"Jack Stone Sa Importaz.-esportaz.",
    "wof:placetype":"venue"
},
  "geometry": {"coordinates":[8.945635,45.997334],"type":"Point"}
}