{
  "type": "Feature",
  "properties": {
    "iso:country":"CH",
    "sg:address":"Corso Elvezia 10",
    "sg:city":"Lugano",
    "sg:orig_category":"Softwareentwicklung U beratung Unternehmensberatung",
    "sg:phone":"+41 91 921 25 65",
    "sg:postcode":"6900",
    "sg:province":"Ticino",
    "wof:name":"Targetmedia Consulting Sa",
    "wof:placetype":"venue"
},
  "geometry": {"coordinates":[8.9557857513,46.006980896],"type":"Point"}
}