{
  "type": "Feature",
  "properties": {
    "iso:country":"CH",
    "sg:address":"Oltenstr. 5",
    "sg:city":"Attiswil",
    "sg:orig_category":"Stukkateurgewerbe, Gipserei U Verputzerei",
    "sg:phone":"+41 32 637 27 47",
    "sg:postcode":"4536",
    "sg:province":"Bern",
    "wof:name":"Leisi Hans, Gipsergesch\u00e4ft",
    "wof:placetype":"venue"
},
  "geometry": {"coordinates":[7.6144361496,47.2473144531],"type":"Point"}
}