{
  "type": "Feature",
  "properties": {
    "iso:country":"CH",
    "sg:address":"Hasenwiese 6",
    "sg:city":"Mollis",
    "sg:orig_category":"Sportvereine Ballsport Tennis",
    "sg:phone":"+41 55 612 34 64",
    "sg:postcode":"8753",
    "sg:province":"Glarus",
    "wof:name":"Glarner Tc",
    "wof:placetype":"venue"
},
  "geometry": {"coordinates":[9.074508667,47.0953140259],"type":"Point"}
}