{
  "type": "Feature",
  "properties": {
    "iso:country":"CH",
    "sg:address":"Solothurnerstr. 6 4632 Trimbach. Postfach",
    "sg:city":"Olten",
    "sg:orig_category":"RESTAURANTS: TEA-ROOMS",
    "sg:phone":"+41 62 293 30 32",
    "sg:postcode":"4603",
    "sg:province":"Solothurn",
    "wof:name":"Restaurant Zur Kapelle, Studer Urs",
    "wof:placetype":"venue"
},
  "geometry": {"coordinates":[7.8993601799,47.3614349365],"type":"Point"}
}