{
  "type": "Feature",
  "properties": {
    "iso:country":"CH",
    "sg:address":"Baldeggstrasse 32 6280 Hochdorf. Postfach 835",
    "sg:city":"Hochdorf",
    "sg:orig_category":"Detailhandel mit Musikinstrumenten",
    "sg:phone":"+41 41 910 18 68",
    "sg:postcode":"6281",
    "sg:province":"Luzern",
    "wof:name":"Heinz Gasser Blas-& Schlaginstrumente",
    "wof:placetype":"venue"
},
  "geometry": {"coordinates":[8.2853574753,47.1732788086],"type":"Point"}
}