{
  "type": "Feature",
  "properties": {
    "iso:country":"CH",
    "sg:address":"Zentralplatz",
    "sg:city":"Biel",
    "sg:classifiers":[
        {
            "category":"Banks & Credit Unions",
            "subcategory":"Bank",
            "type":"Services"
        }
    ],
    "sg:phone":"+41 32274747",
    "sg:postcode":"2501",
    "sg:province":"Bern",
    "wof:name":"Kantonalbank Von Bern",
    "wof:placetype":"venue"
},
  "geometry": {"coordinates":[7.24868,47.14381],"type":"Point"}
}