{
  "type": "Feature",
  "properties": {
    "iso:country":"CH",
    "sg:address":"Oberlandstrasse 21",
    "sg:city":"Spiez",
    "sg:orig_category":"Detailhandel mit Sportartikeln Fachdetailhandel in Verkaufsr\u00e4umen",
    "sg:phone":"+41 33 654 02 75",
    "sg:postcode":"3700",
    "sg:province":"Bern",
    "wof:name":"Fit-line Sports Cornelia Schluchter",
    "wof:placetype":"venue"
},
  "geometry": {"coordinates":[7.6777739525,46.6890068054],"type":"Point"}
}