{
  "type": "Feature",
  "properties": {
    "iso:country":"CH",
    "sg:address":"Bilstenstrasse 62",
    "sg:city":"Altendorf",
    "sg:orig_category":"Grosshandel mit lebenden Tieren",
    "sg:phone":"+41 55 284 16 24",
    "sg:postcode":"8852",
    "sg:province":"Schwyz",
    "wof:name":"Ziegler Hermann",
    "wof:placetype":"venue"
},
  "geometry": {"coordinates":[8.9501724243,47.2425689697],"type":"Point"}
}