{
  "type": "Feature",
  "properties": {
    "iso:country":"CH",
    "sg:address":"Albisstrasse 74",
    "sg:city":"Z\u00fcrich",
    "sg:orig_category":"Kosmetikinstitute",
    "sg:phone":"+41 81 416 75 05",
    "sg:postcode":"8038",
    "sg:province":"Z\u00fcrich",
    "wof:name":"Maja Barandun Kosmetikinstitut",
    "wof:placetype":"venue"
},
  "geometry": {"coordinates":[9.8325433731,46.800743103],"type":"Point"}
}