{
  "type": "Feature",
  "properties": {
    "iso:country":"CH",
    "sg:address":"Pr\u00e9 Cuendoz",
    "sg:city":"Ch\u00e2teau-d'oex",
    "sg:orig_category":"Detailhandel mit Waren verschiedener Art, Hauptrichtung Nahrungsmittel Fachdetailhandel mit Nahrungs",
    "sg:phone":"+41 26 924 48 17",
    "sg:postcode":"1837",
    "wof:name":"A. Transmontana Sp\u00e9cialit\u00e9s Portugaises",
    "wof:placetype":"venue"
},
  "geometry": {"coordinates":[5.9581398964,46.5957260132],"type":"Point"}
}