{
  "type": "Feature",
  "properties": {
    "iso:country":"CH",
    "sg:address":"Rue Mauverney 18b 1196 Gland Case Postale Case Postale 750",
    "sg:city":"Gland",
    "sg:orig_category":"Erschliessung von Grundst\u00fccken Kauf U Verkauf von Immobilien auf eigene Rechnung",
    "sg:phone":"+41 22 995 10 10",
    "sg:postcode":"1196",
    "sg:province":"Vaud",
    "wof:name":"Immo-sales S\u00e0rl Agence Immobili\u00e8re",
    "wof:placetype":"venue"
},
  "geometry": {"coordinates":[6.2755608559,46.417427063],"type":"Point"}
}