{
  "type": "Feature",
  "properties": {
    "iso:country":"CH",
    "sg:address":"Kreuzweidstrasse 22",
    "sg:city":"Widen",
    "sg:orig_category":"Wirtschafts- and Arbeitgeberverb\u00e4nde",
    "sg:phone":"+41 56 633 51 37",
    "sg:postcode":"8967",
    "sg:province":"Aargau",
    "wof:name":"Verband Aargauer Volkstheater Herrn Peter Beck",
    "wof:placetype":"venue"
},
  "geometry": {"coordinates":[8.3568201065,47.3740272522],"type":"Point"}
}