{
  "type": "Feature",
  "properties": {
    "iso:country":"CH",
    "sg:address":"Sur Le Beau Chemin De 29",
    "sg:city":"Confignon",
    "sg:orig_category":"Sonstige mit der Informatik verbundene T\u00e4tigkeiten",
    "sg:postcode":"1232",
    "sg:province":"Gen\u00e8ve",
    "wof:name":"Infinet Technologies S\u00e0rl",
    "wof:placetype":"venue"
},
  "geometry": {"coordinates":[6.0925278664,46.1771774292],"type":"Point"}
}