{
  "type": "Feature",
  "properties": {
    "addr:full":"Rue Du Contrat-social 5 Gen\u00e8ve Gen\u00e8ve 1203",
    "addr:housenumber":"5",
    "addr:postcode":"1203",
    "addr:street":"Rue Du Contrat-Social",
    "iso:country":"CH",
    "sg:address":"Rue Du Contrat-social 5",
    "sg:city":"Gen\u00e8ve",
    "sg:classifiers":[
        {
            "category":"Education",
            "subcategory":"Library",
            "type":"Public Place"
        }
    ],
    "sg:phone":"+41 22 344 50 60",
    "sg:postcode":"1203",
    "sg:province":"Gen\u00e8ve",
    "sg:tags":[
        "u",
        "bibliotheken",
        "archive"
    ],
    "wof:name":"Biblioth\u00e8que St-jean Biblioth\u00e8que Des Jeunes",
    "wof:placetype":"venue"
},
  "geometry": {"coordinates":[6.123694,46.204338],"type":"Point"}
}