{
  "type": "Feature",
  "properties": {
    "addr:full":"Bahnhofstrasse 15 6430 Schwyz. Postfach 321 Schwyz Schwyz 6431",
    "addr:housenumber":"15;321",
    "addr:postcode":"6430;6431",
    "addr:street":"Bahnhofstrasse;Postfach",
    "iso:country":"CH",
    "sg:address":"Bahnhofstrasse 15 6430 Schwyz. Postfach 321",
    "sg:city":"Schwyz",
    "sg:orig_category":"Alters U Hinterlassenenversicherung AHV, Invalidenversicherung IV, Arbeitslosenversicherung ALV",
    "sg:phone":"+41 41 819 11 24",
    "sg:postcode":"6431",
    "sg:province":"Schwyz",
    "wof:name":"Kant. Arbeitslosenkasse Schwyz",
    "wof:placetype":"venue"
},
  "geometry": {"coordinates":[8.649298,47.021427],"type":"Point"}
}