{
  "type": "Feature",
  "properties": {
    "iso:country":"CH",
    "sg:address":"Langr\u00fctistrasse 94",
    "sg:city":"D\u00fcrnten",
    "sg:orig_category":"Allgemeiner Hoch U Tiefbau",
    "sg:phone":"+41 77931709",
    "sg:postcode":"8635",
    "sg:province":"Z\u00fcrich",
    "wof:name":"Rabag D\u00fcrnten Ag",
    "wof:placetype":"venue"
},
  "geometry": {"coordinates":[8.877037,47.275234],"type":"Point"}
}