{
  "type": "Feature",
  "properties": {
    "addr:full":"Riedstr. 50a 3600 Thun. Postfach H\u00fcnibach Bern 3626",
    "addr:housenumber":"50a",
    "addr:postcode":"3600 thun. postfach huenibach;3626",
    "addr:street":"Riedstr.",
    "iso:country":"CH",
    "sg:address":"Riedstr. 50a 3600 Thun. Postfach",
    "sg:city":"H\u00fcnibach",
    "sg:orig_category":"Architektur U Ingenieurb\u00fcros",
    "sg:postcode":"3626",
    "sg:province":"Bern",
    "wof:name":"Ingenieurb\u00fcro F\u00fcr Maschinenbau, Rikli Christian",
    "wof:placetype":"venue"
},
  "geometry": {"coordinates":[7.646814,46.748875],"type":"Point"}
}