{
  "type": "Feature",
  "properties": {
    "iso:country":"CH",
    "sg:address":"Brunnenweg 1",
    "sg:city":"Meinisberg",
    "sg:classifiers":[
        {
            "category":"Insurance",
            "subcategory":"Insurance Agent",
            "type":"Services"
        }
    ],
    "sg:phone":"+41 32 377 41 31",
    "sg:postcode":"2554",
    "sg:province":"Bern",
    "sg:tags":[
        "versicherungsagenturen",
        "-broker"
    ],
    "wof:name":"Z\u00fcrich Versicherungen Agentur Hansruedi Baumann",
    "wof:placetype":"venue"
},
  "geometry": {"coordinates":[7.3426880836,47.1588973999],"type":"Point"}
}