{
  "type": "Feature",
  "properties": {
    "iso:country":"CH",
    "sg:address":"Bahnhofplatz 8 7000 Chur. Postfach",
    "sg:city":"Chur",
    "sg:orig_category":"Wirtschafts- and Arbeitgeberverb\u00e4nde",
    "sg:phone":"+41 81 250 19 40",
    "sg:postcode":"7001",
    "sg:province":"Graubunden",
    "wof:name":"Selva B\u00fcndner Wald- Wirtschaftsverband",
    "wof:placetype":"venue"
},
  "geometry": {"coordinates":[9.5298366547,46.8529434204],"type":"Point"}
}