{
  "type": "Feature",
  "properties": {
    "iso:country":"CH",
    "sg:address":"Hegiweg 29",
    "sg:city":"Diegten",
    "sg:orig_category":"Zahntechnische Laboratorien",
    "sg:phone":"+41 61 971 63 37",
    "sg:postcode":"4457",
    "sg:province":"Basel-Landschaft",
    "wof:name":"Lukas H\u00e4felfinger Zahntechnisches Labor",
    "wof:placetype":"venue"
},
  "geometry": {"coordinates":[7.8150000572,47.4124603271],"type":"Point"}
}