{
  "type": "Feature",
  "properties": {
    "iso:country":"CH",
    "sg:address":"Gontenstrasse 35",
    "sg:city":"Appenzell",
    "sg:classifiers":[
        {
            "category":"Restaurant",
            "type":"Food & Drink"
        }
    ],
    "sg:phone":"+41 55 444 12 08",
    "sg:postcode":"9050",
    "sg:province":"Appenzell Innerhoden",
    "wof:name":"Restaurant Rose",
    "wof:placetype":"venue"
},
  "geometry": {"coordinates":[8.9527902603,47.1751785278],"type":"Point"}
}