{
  "type": "Feature",
  "properties": {
    "iso:country":"CH",
    "sg:address":"Garage Du Faubourg",
    "sg:city":"Avenches",
    "sg:orig_category":"Instandhaltung U Reparatur von Automobilen",
    "sg:phone":"+41 26 675 14 23",
    "sg:postcode":"1580",
    "sg:province":"Vaud",
    "wof:name":"Ibach Ch.",
    "wof:placetype":"venue"
},
  "geometry": {"coordinates":[7.0407848358,46.8800582886],"type":"Point"}
}