{
  "type": "Feature",
  "properties": {
    "iso:country":"CH",
    "sg:address":"3932",
    "sg:city":"Visperterminen",
    "sg:orig_category":"Verkehrs- and Tourismusb\u00fcros",
    "sg:phone":"+41 27 946 80 60",
    "sg:postcode":"3932",
    "sg:province":"Valais",
    "wof:name":"Verkehrsverein Visperterminen- Staldbach",
    "wof:placetype":"venue"
},
  "geometry": {"coordinates":[7.9026641846,46.2593460083],"type":"Point"}
}