{
  "type": "Feature",
  "properties": {
    "iso:country":"CH",
    "sg:address":"Waaggasse 5",
    "sg:city":"Othmarsingen",
    "sg:orig_category":"Softwareentwicklung U beratung Sonstiger Grosshandel",
    "sg:phone":"+41 62 896 34 12",
    "sg:postcode":"5504",
    "sg:province":"Aargau",
    "wof:name":"Itb Inco Trading & Broking Ag",
    "wof:placetype":"venue"
},
  "geometry": {"coordinates":[8.2170085907,47.4000205994],"type":"Point"}
}