{
  "type": "Feature",
  "properties": {
    "iso:country":"CH",
    "sg:address":"Weststrasse 24 7000 Chur. Postfach 60",
    "sg:city":"Chur",
    "sg:orig_category":"Sanit\u00e4r U Heizungsinstallation Sanit\u00e4r, Heizungs U L\u00fcftungsinstallation",
    "sg:phone":"+41 81 252 77 18",
    "sg:postcode":"7007",
    "sg:province":"Graubunden",
    "wof:name":"Giger Jakob Ag",
    "wof:placetype":"venue"
},
  "geometry": {"coordinates":[9.5233201981,46.8463401794],"type":"Point"}
}