{
  "type": "Feature",
  "properties": {
    "iso:country":"CH",
    "sg:address":"Industrie Werrikon 2",
    "sg:city":"N\u00e4nikon",
    "sg:classifiers":[
        {
            "category":"Manufacturing",
            "subcategory":"Motor Vehicles & Parts",
            "type":"Manufacturing & Wholesale Goods"
        }
    ],
    "sg:phone":"+41 19059911",
    "sg:postcode":"8606",
    "sg:province":"Z\u00fcrich",
    "sg:tags":[
        "aluminium",
        "processing",
        "sheet"
    ],
    "wof:name":"Wolfermann Stahl- Und Metallbau Ag",
    "wof:placetype":"venue"
},
  "geometry": {"coordinates":[8.677529,47.365234],"type":"Point"}
}