{
  "type": "Feature",
  "properties": {
    "iso:country":"CH",
    "sg:address":"Wolfbodenstrasse 15",
    "sg:city":"M\u00e4genwil",
    "sg:orig_category":"Galvanische Betriebe",
    "sg:phone":"+41 62 896 28 50",
    "sg:postcode":"5506",
    "sg:province":"Aargau",
    "wof:name":"Tecga Techn.galvanoservice Ag",
    "wof:placetype":"venue"
},
  "geometry": {"coordinates":[8.2386350632,47.4155082703],"type":"Point"}
}