{
  "type": "Feature",
  "properties": {
    "iso:country":"CH",
    "sg:address":"Kl\u00f6sterlistrasse 11a 6010 Kriens. Postfach 296",
    "sg:city":"Kriens",
    "sg:orig_category":"Sportvereine Turnen Vereine Damen",
    "sg:phone":"+41 71 311 50 66",
    "sg:postcode":"6011",
    "sg:province":"Luzern",
    "wof:name":"Turnver.stv Abtwil-st.josefen",
    "wof:placetype":"venue"
},
  "geometry": {"coordinates":[9.3130655289,47.4202346802],"type":"Point"}
}