{
  "type": "Feature",
  "properties": {
    "iso:country":"CH",
    "sg:address":"1329",
    "sg:city":"Bretonni\u00e8res",
    "sg:orig_category":"Landesverteidigung, Sozialversicherung \u00d6ffentliche Verwaltung",
    "sg:phone":"+41 21 845 60 59",
    "sg:postcode":"1329",
    "sg:province":"Vaud",
    "wof:name":"Centre De Protection Civile",
    "wof:placetype":"venue"
},
  "geometry": {"coordinates":[6.282310009,46.6478347778],"type":"Point"}
}