{
  "type": "Feature",
  "properties": {
    "iso:country":"CH",
    "sg:address":"Seehofstrasse 6",
    "sg:city":"Uttwil",
    "sg:orig_category":"RESTAURANTS: TEA-ROOMS",
    "sg:phone":"+41 71 463 19 94",
    "sg:postcode":"8592",
    "sg:province":"Thurgau",
    "wof:name":"Restaurant Pier 7462",
    "wof:placetype":"venue"
},
  "geometry": {"coordinates":[9.3427639008,47.5857162476],"type":"Point"}
}