{
  "type": "Feature",
  "properties": {
    "iso:country":"CH",
    "sg:address":"Rheinstrasse 36",
    "sg:city":"Embrach",
    "sg:orig_category":"Zahnarztpraxen",
    "sg:phone":"+41 18654653",
    "sg:postcode":"8424",
    "sg:province":"Z\u00fcrich",
    "wof:name":"Dr. Med. Dent. Wenzel Dufek Zahnarzt",
    "wof:placetype":"venue"
},
  "geometry": {"coordinates":[8.5867414474,47.5193138123],"type":"Point"}
}