{
  "type": "Feature",
  "properties": {
    "iso:country":"CH",
    "sg:address":"Maison-forte Rue De La 12 1287 Laconnex. Postfach",
    "sg:city":"Laconnex",
    "sg:orig_category":"Markt U Meinungsforschung",
    "sg:phone":"+41 22 756 24 97",
    "sg:postcode":"1287",
    "sg:province":"Gen\u00e8ve",
    "wof:name":"Banbery Alan Consultant De Marketing",
    "wof:placetype":"venue"
},
  "geometry": {"coordinates":[6.0363259315,46.1576728821],"type":"Point"}
}