{
  "type": "Feature",
  "properties": {
    "iso:country":"CH",
    "sg:address":"Chemin De Beau-val 3",
    "sg:city":"Lausanne",
    "sg:orig_category":"Architekturb\u00fcros",
    "sg:phone":"+41 21 624 03 23",
    "sg:postcode":"1012",
    "sg:province":"Vaud",
    "wof:name":"Jacques Pessina Bureau D'architecture",
    "wof:placetype":"venue"
},
  "geometry": {"coordinates":[6.617792,46.527691],"type":"Point"}
}