{
  "type": "Feature",
  "properties": {
    "iso:country":"CH",
    "sg:address":"Glis 3902 Glis. Postfach",
    "sg:city":"Glis",
    "sg:orig_category":"Wohnheime",
    "sg:phone":"+41 27 924 14 20",
    "sg:postcode":"3902",
    "sg:province":"Valais",
    "wof:name":"Oberwalliser Verein Zur F\u00f6rderung Geistig Behinderter",
    "wof:placetype":"venue"
},
  "geometry": {"coordinates":[7.9785251617,46.311164856],"type":"Point"}
}