{
  "type": "Feature",
  "properties": {
    "addr:full":"G\u00fctli 159 9428 Walzenhausen. Postfach Walzenhausen Appenzell Ausserrhoden 9428",
    "addr:housenumber":"159",
    "addr:postcode":"9428 walzenhausen. postfach;9428",
    "addr:street":"Guetli;Ausserrhoden",
    "iso:country":"CH",
    "sg:address":"G\u00fctli 159 9428 Walzenhausen. Postfach",
    "sg:city":"Walzenhausen",
    "sg:orig_category":"Detailhandel mit Beleuchtungs U Haushaltsgegenst\u00e4nden Detailhandel mit M\u00f6beln U Haushaltsgegenst\u00e4nde",
    "sg:postcode":"9428",
    "sg:province":"Appenzell Ausserrhoden",
    "wof:name":"Kurt Keller",
    "wof:placetype":"venue"
},
  "geometry": {"coordinates":[9.606639,47.449066],"type":"Point"}
}