{
  "type": "Feature",
  "properties": {
    "iso:country":"CH",
    "sg:address":"Erlen 8",
    "sg:city":"Speicher",
    "sg:orig_category":"Interessenvertretungen U sonstige Vereinigungen",
    "sg:phone":"+41 55 243 25 60",
    "sg:postcode":"9042",
    "sg:province":"Appenzell Ausserrhoden",
    "wof:name":"Hilaria Bubikon",
    "wof:placetype":"venue"
},
  "geometry": {"coordinates":[8.8516378403,47.2586097717],"type":"Point"}
}