{
  "type": "Feature",
  "properties": {
    "iso:country":"CH",
    "sg:address":"Via Losanna 6",
    "sg:city":"Biasca",
    "sg:orig_category":"Sanit\u00e4r U Heizungsinstallation",
    "sg:phone":"+41 91 862 18 29",
    "sg:postcode":"6710",
    "sg:province":"Ticino",
    "wof:name":"Oertli Service Ag",
    "wof:placetype":"venue"
},
  "geometry": {"coordinates":[8.9700450897,46.3555335999],"type":"Point"}
}