{
  "type": "Feature",
  "properties": {
    "iso:country":"CH",
    "sg:address":"Zimberh\u00fcbel 597 5728 Gontenschwil. Postfach 13",
    "sg:city":"Gontenschwil",
    "sg:orig_category":"Technische B\u00fcros Heizung, L\u00fcftung, Klima Technische B\u00fcros Sanit\u00e4r",
    "sg:phone":"+41 62 773 24 09",
    "sg:postcode":"5728",
    "sg:province":"Aargau",
    "wof:name":"Gloor & Sehringer Gmbh",
    "wof:placetype":"venue"
},
  "geometry": {"coordinates":[8.1554021835,47.2606506348],"type":"Point"}
}