{
  "type": "Feature",
  "properties": {
    "iso:country":"CH",
    "sg:address":"Sonnenbergstrasse 3",
    "sg:city":"Heiden",
    "sg:orig_category":"Allgemeiner Hoch U Tiefbau Verwaltung von Immobilien",
    "sg:phone":"+41 71 891 26 39",
    "sg:postcode":"9410",
    "sg:province":"Appenzell Ausserrhoden",
    "wof:name":"Bau- U. Verwaltungs Ag., Heiden",
    "wof:placetype":"venue"
},
  "geometry": {"coordinates":[9.542016,47.439014],"type":"Point"}
}