{
  "type": "Feature",
  "properties": {
    "iso:country":"CH",
    "sg:address":"Grossmatte 7",
    "sg:city":"Littau",
    "sg:orig_category":"Herstellung von Elektromotoren, Generatoren U Transformatoren Herstellung von sonstigen elektrischen",
    "sg:phone":"+41 41 250 41 59",
    "sg:postcode":"6014",
    "sg:province":"Luzern",
    "wof:name":"Fema Ag Littau",
    "wof:placetype":"venue"
},
  "geometry": {"coordinates":[8.2635555267,47.0477638245],"type":"Point"}
}