{
  "type": "Feature",
  "properties": {
    "iso:country":"CH",
    "sg:address":"Langenbruckstrasse 2",
    "sg:city":"H\u00e4gendorf",
    "sg:orig_category":"G\u00fcterbef\u00f6rderung im Strassenverkehr",
    "sg:phone":"+41 62 216 32 30",
    "sg:postcode":"4614",
    "sg:province":"Solothurn",
    "wof:name":"Kamber Kurt Transporte",
    "wof:placetype":"venue"
},
  "geometry": {"coordinates":[7.8412108421,47.3433189392],"type":"Point"}
}