{
  "type": "Feature",
  "properties": {
    "iso:country":"CH",
    "sg:address":"Hauptstrasse 22",
    "sg:city":"Bronschhofen",
    "sg:orig_category":"Landesverteidigung, Sozialversicherung \u00d6ffentliche Verwaltung",
    "sg:phone":"+41 71 911 12 30",
    "sg:postcode":"9552",
    "sg:province":"St. Gallen",
    "wof:name":"Zivilschutzstelle Bronschhofen",
    "wof:placetype":"venue"
},
  "geometry": {"coordinates":[9.0363721848,47.4758758545],"type":"Point"}
}