{
  "type": "Feature",
  "properties": {
    "iso:country":"CH",
    "sg:address":"Wetzikerstrasse 35 8344 B\u00e4retswil. Postfach 125",
    "sg:city":"B\u00e4retswil",
    "sg:orig_category":"D\u00e4mmung gegen K\u00e4lte, W\u00e4rme, Schall U Ersch\u00fctterung Hoch U Tiefbau",
    "sg:phone":"+41 19392484",
    "sg:postcode":"8344",
    "sg:province":"Z\u00fcrich",
    "wof:name":"Brelon Verputz Ag",
    "wof:placetype":"venue"
},
  "geometry": {"coordinates":[8.8500709534,47.3314857483],"type":"Point"}
}