{
  "type": "Feature",
  "properties": {
    "iso:country":"CH",
    "sg:address":"Rue Des Terreaux 13",
    "sg:city":"Orbe",
    "sg:orig_category":"Sportvereine Sch\u00fctzen",
    "sg:phone":"+41 24 441 34 50",
    "sg:postcode":"1350",
    "sg:province":"Vaud",
    "wof:name":"St\u00e9 De Tir Armes De Guerre",
    "wof:placetype":"venue"
},
  "geometry": {"coordinates":[6.5306959152,46.7244949341],"type":"Point"}
}