{
  "type": "Feature",
  "properties": {
    "iso:country":"CH",
    "sg:address":"Route D'arconciel 3",
    "sg:city":"Treyvaux",
    "sg:orig_category":"Unclassifiable Establishments",
    "sg:postcode":"1733",
    "sg:province":"Fribourg",
    "wof:name":"Dr M\u00e9d. Monique Savopol M\u00e9decin Sp\u00e9cialiste Fmh",
    "wof:placetype":"venue"
},
  "geometry": {"coordinates":[7.1329197884,46.7332344055],"type":"Point"}
}