{
  "type": "Feature",
  "properties": {
    "iso:country":"CH",
    "sg:address":"Bibersteinerstrasse 2",
    "sg:city":"Rombach",
    "sg:orig_category":"Druck ohne Zeitungsdruck Papier U Kartongewerbe",
    "sg:phone":"+41 62 827 25 52",
    "sg:postcode":"5022",
    "sg:province":"Aargau",
    "wof:name":"Gesch\u00e4ftsb\u00fccherfabrik Rombach Ag",
    "wof:placetype":"venue"
},
  "geometry": {"coordinates":[8.0439910889,47.401473999],"type":"Point"}
}