{
  "type": "Feature",
  "properties": {
    "iso:country":"CH",
    "sg:address":"Industriestrasse 24",
    "sg:city":"Luterbach",
    "sg:orig_category":"Herstellung von Radio U Fernsehger\u00e4ten sowie phono U videotechnischen Ger\u00e4ten",
    "sg:phone":"+41 32 682 70 70",
    "sg:postcode":"4542",
    "sg:province":"Solothurn",
    "wof:name":"Powerhouse Ag Beschallungs Und Beleuchtungstechnik",
    "wof:placetype":"venue"
},
  "geometry": {"coordinates":[7.5826702118,47.210018158],"type":"Point"}
}