{
  "type": "Feature",
  "properties": {
    "iso:country":"CH",
    "sg:address":"Randweg 19",
    "sg:city":"Bern",
    "sg:orig_category":"Unclassifiable Establishments",
    "sg:postcode":"3013",
    "sg:province":"Bern",
    "wof:name":"Kader-schulung K\u00dcnzi",
    "wof:placetype":"venue"
},
  "geometry": {"coordinates":[7.4432749748,46.9578056335],"type":"Point"}
}