{
  "type": "Feature",
  "properties": {
    "iso:country":"CH",
    "sg:address":"Lambergstrasse 4",
    "sg:city":"Uster",
    "sg:orig_category":"Sonstiger spezialisierter Hoch U Tiefbau",
    "sg:postcode":"8610",
    "sg:province":"Z\u00fcrich",
    "wof:name":"Masto, Maganuco + Stoop",
    "wof:placetype":"venue"
},
  "geometry": {"coordinates":[8.7353830338,47.3419265747],"type":"Point"}
}