{
  "type": "Feature",
  "properties": {
    "iso:country":"CH",
    "sg:address":"Luzernerstrasse 11",
    "sg:city":"Rotkreuz",
    "sg:orig_category":"Non-Classified Establishments",
    "sg:postcode":"6343",
    "sg:province":"Zug",
    "wof:name":"W\u00fcthrich Haushaltger\u00e4te",
    "wof:placetype":"venue"
},
  "geometry": {"coordinates":[8.426735878,47.1398773193],"type":"Point"}
}