{
  "type": "Feature",
  "properties": {
    "iso:country":"CH",
    "sg:address":"1307",
    "sg:city":"Lussery-villars",
    "sg:orig_category":"Malerei Stukkateurgewerbe, Gipserei U Verputzerei",
    "sg:phone":"+41 21 861 06 86",
    "sg:postcode":"1307",
    "sg:province":"Vaud",
    "wof:name":"Fran\u00e7ois Invernizzi Gypserie & Peinture",
    "wof:placetype":"venue"
},
  "geometry": {"coordinates":[6.5258197784,46.6319198608],"type":"Point"}
}