{
  "type": "Feature",
  "properties": {
    "iso:country":"CH",
    "sg:address":"Giesserstrasse 1",
    "sg:city":"Othmarsingen",
    "sg:orig_category":"Herstellung von Automobilen",
    "sg:phone":"+41 56 496 11 88",
    "sg:postcode":"5504",
    "sg:province":"Aargau",
    "wof:name":"Imbax Ag",
    "wof:placetype":"venue"
},
  "geometry": {"coordinates":[8.3136329651,47.4043045044],"type":"Point"}
}