{
  "type": "Feature",
  "properties": {
    "addr:full":"Schachenallee 29 Aarau Aargau 5000",
    "addr:housenumber":"29",
    "addr:postcode":"5000",
    "addr:street":"Schachenallee",
    "iso:country":"CH",
    "sg:address":"Schachenallee 29",
    "sg:city":"Aarau",
    "sg:orig_category":"Berufliche Weiterbildung, Erwachsenenbildung Berufsbildende weiterf\u00fchrende Schulen",
    "sg:phone":"+41 26 670 31 91",
    "sg:postcode":"5000",
    "sg:province":"Aargau",
    "wof:name":"Ausbildungszentrum Der Sbb",
    "wof:placetype":"venue"
},
  "geometry": {"coordinates":[7.108453,46.925232],"type":"Point"}
}