{
  "type": "Feature",
  "properties": {
    "iso:country":"CH",
    "sg:address":"Via Moree 11",
    "sg:city":"Mendrisio",
    "sg:orig_category":"Mechanische Werkst\u00e4tten Stahl U Leichtmetallbau",
    "sg:phone":"+41 91 646 20 01",
    "sg:postcode":"6850",
    "sg:province":"Ticino",
    "wof:name":"Alfredo Finke Sa Metalcostruzioni & Meccanica",
    "wof:placetype":"venue"
},
  "geometry": {"coordinates":[8.9802703857,45.8728103638],"type":"Point"}
}