{
  "type": "Feature",
  "properties": {
    "iso:country":"CH",
    "sg:address":"Ochsengasse 8",
    "sg:city":"Rheinau",
    "sg:orig_category":"Non-Classified Establishments",
    "sg:phone":"+41 52 319 12 53",
    "sg:postcode":"8462",
    "sg:province":"Z\u00fcrich",
    "wof:name":"Gasthaus L\u00f6wen",
    "wof:placetype":"venue"
},
  "geometry": {"coordinates":[8.6038866043,47.6454849243],"type":"Point"}
}