{
  "type": "Feature",
  "properties": {
    "iso:country":"CH",
    "sg:address":"Rompeda Via 10",
    "sg:city":"Giubiasco",
    "sg:orig_category":"Allgemeiner Hoch U Tiefbau",
    "sg:postcode":"6512",
    "sg:province":"Ticino",
    "wof:name":"Aemme Impresa Di Costruzioni Marrazzo Antonio & Co",
    "wof:placetype":"venue"
},
  "geometry": {"coordinates":[9.014726,46.172943],"type":"Point"}
}