{
  "type": "Feature",
  "properties": {
    "iso:country":"CH",
    "sg:address":"Staatsstrasse 22",
    "sg:city":"Hilterfingen",
    "sg:orig_category":"Fussreflexzonenmassage P\u00e9dicure",
    "sg:phone":"+41 33 243 13 33",
    "sg:postcode":"3652",
    "sg:province":"Bern",
    "wof:name":"Praxis F\u00fcr Fusspflege",
    "wof:placetype":"venue"
},
  "geometry": {"coordinates":[7.6579051018,46.7359237671],"type":"Point"}
}