{
  "type": "Feature",
  "properties": {
    "iso:country":"CH",
    "sg:address":"Axenstrasse 9",
    "sg:city":"Brunnen",
    "sg:orig_category":"Vermietung U Verpachtung von eigenen Immobilien",
    "sg:postcode":"6440",
    "sg:province":"Schwyz",
    "wof:name":"Ergan Gmbh",
    "wof:placetype":"venue"
},
  "geometry": {"coordinates":[8.6072063446,46.9934921265],"type":"Point"}
}