{
  "type": "Feature",
  "properties": {
    "iso:country":"CH",
    "sg:address":"Zinnengasse 5 8001 Z\u00fcrich. Postfach",
    "sg:city":"Z\u00fcrich",
    "sg:orig_category":"Reiseb\u00fcros U Reiseveranstalter",
    "sg:phone":"+41 12421430",
    "sg:postcode":"8022",
    "sg:province":"Z\u00fcrich",
    "wof:name":"Senator Travel Ag",
    "wof:placetype":"venue"
},
  "geometry": {"coordinates":[8.5415725708,47.3704452515],"type":"Point"}
}