{
  "type": "Feature",
  "properties": {
    "iso:country":"CH",
    "sg:address":"Lehnenweingarten 6",
    "sg:city":"Uttwil",
    "sg:orig_category":"Unternehmensberatung",
    "sg:postcode":"8592",
    "sg:province":"Thurgau",
    "wof:name":"Ibc International Business Consulting Gmbh",
    "wof:placetype":"venue"
},
  "geometry": {"coordinates":[9.3354988098,47.5846748352],"type":"Point"}
}