{
  "type": "Feature",
  "properties": {
    "iso:country":"CH",
    "sg:address":"Piazza F. Borromini",
    "sg:city":"Bissone",
    "sg:orig_category":"Wirtschaftspr\u00fcfung, Steuerberatung U Treuhand",
    "sg:phone":"+41 91 683 34 66",
    "sg:postcode":"6816",
    "sg:province":"Ticino",
    "wof:name":"Sarima Sa",
    "wof:placetype":"venue"
},
  "geometry": {"coordinates":[8.9645547867,45.9506759644],"type":"Point"}
}