{
  "type": "Feature",
  "properties": {
    "iso:country":"CH",
    "sg:address":"Via Dei Canova 13",
    "sg:city":"Chiasso",
    "sg:orig_category":"Detailhandel mit Schuhen U Lederwaren Herstellung von Reiseartikeln, Leder U Sattlerwaren",
    "sg:phone":"+41 91 683 09 10",
    "sg:postcode":"6830",
    "sg:province":"Ticino",
    "wof:name":"Canal Luciano",
    "wof:placetype":"venue"
},
  "geometry": {"coordinates":[9.019613266,45.8327178955],"type":"Point"}
}