{
  "type": "Feature",
  "properties": {
    "iso:country":"CH",
    "sg:address":"Industriestrasse 13c",
    "sg:city":"Zug",
    "sg:orig_category":"Technische, physikalische U chemische Untersuchung",
    "sg:postcode":"6300",
    "sg:province":"Zug",
    "wof:name":"Testdraft Ag",
    "wof:placetype":"venue"
},
  "geometry": {"coordinates":[8.7637605667,47.1964530945],"type":"Point"}
}