{
  "type": "Feature",
  "properties": {
    "iso:country":"CH",
    "sg:address":"Hochdorferstrasse 20",
    "sg:city":"Hildisrieden",
    "sg:orig_category":"Herstellung von Elektrizit\u00e4tsverteilungs U schalteinrichtungen",
    "sg:phone":"+41 41 467 33 11",
    "sg:postcode":"6024",
    "sg:province":"Luzern",
    "wof:name":"Norfolk Elektronik Stalder",
    "wof:placetype":"venue"
},
  "geometry": {"coordinates":[8.2329797745,47.1512947083],"type":"Point"}
}