{
  "type": "Feature",
  "properties": {
    "iso:country":"CH",
    "sg:address":"Riva Antonio Caccia 1a",
    "sg:city":"Lugano",
    "sg:orig_category":"Dienstleistungen von Beteiligungsgesellschaften",
    "sg:phone":"+41 91 994 43 32",
    "sg:postcode":"6900",
    "sg:province":"Ticino",
    "wof:name":"Maximat",
    "wof:placetype":"venue"
},
  "geometry": {"coordinates":[8.9475860596,45.9980354309],"type":"Point"}
}