{
  "type": "Feature",
  "properties": {
    "iso:country":"CH",
    "sg:address":"Florastrasse 1",
    "sg:city":"Cham",
    "sg:orig_category":"Sonstige mit der Informatik verbundene T\u00e4tigkeiten",
    "sg:postcode":"6330",
    "sg:province":"Zug",
    "wof:name":"B\u00fcro Pellanda.",
    "wof:placetype":"venue"
},
  "geometry": {"coordinates":[8.468501091,47.1851081848],"type":"Point"}
}