{
  "type": "Feature",
  "properties": {
    "iso:country":"CH",
    "sg:address":"Rebstockrain 18",
    "sg:city":"Luzern",
    "sg:orig_category":"Bauingenieurb\u00fcros allgemein",
    "sg:phone":"+41 41 370 72 25",
    "sg:postcode":"6006",
    "sg:province":"Luzern",
    "wof:name":"Christian Brunner Ingenieurb\u00fcro",
    "wof:placetype":"venue"
},
  "geometry": {"coordinates":[8.349218,47.045094],"type":"Point"}
}