{
  "type": "Feature",
  "properties": {
    "iso:country":"CH",
    "sg:address":"Industriestrasse 21",
    "sg:city":"Mellingen",
    "sg:classifiers":[
        {
            "category":"Wholesale",
            "subcategory":"Books, Periodicals, & Newspapers",
            "type":"Manufacturing & Wholesale Goods"
        }
    ],
    "sg:phone":"+41 56 491 02 91",
    "sg:postcode":"5507",
    "sg:province":"Aargau",
    "sg:tags":[
        "professional",
        "journal",
        "journals",
        "publisher"
    ],
    "wof:name":"Diagonal Verlags Ag",
    "wof:placetype":"venue"
},
  "geometry": {"coordinates":[8.275718689,47.4102859497],"type":"Point"}
}