{
  "type": "Feature",
  "properties": {
    "iso:country":"CH",
    "sg:address":"Hochstrasse 99",
    "sg:city":"Basel",
    "sg:orig_category":"Abwasserreinigung, Abfallbeseitigung U sonstige Entsorgung",
    "sg:phone":"+41 61 331 08 28",
    "sg:postcode":"4053",
    "sg:province":"Basel-Stadt",
    "wof:name":"Abbruch-service Basel Haizmann A.",
    "wof:placetype":"venue"
},
  "geometry": {"coordinates":[7.598047,47.543812],"type":"Point"}
}