{
  "type": "Feature",
  "properties": {
    "iso:country":"CH",
    "sg:address":"Schachenm\u00fchle 13a",
    "sg:city":"Hubersdorf",
    "sg:orig_category":"Herstellung von Schrauben, Nieten, Ketten U Federn",
    "sg:phone":"+41 32 637 19 14",
    "sg:postcode":"4535",
    "sg:province":"Solothurn",
    "wof:name":"Schw\u00e4gli Lucien",
    "wof:placetype":"venue"
},
  "geometry": {"coordinates":[7.5904250145,47.2463302612],"type":"Point"}
}