{
  "type": "Feature",
  "properties": {
    "iso:country":"CH",
    "sg:address":"Rue De Veraye 2 1820 Montreux Case Postale 34",
    "sg:city":"Territet-veytaux",
    "sg:orig_category":"Berufsbildende weiterf\u00fchrende Schulen",
    "sg:phone":"+41 21 963 83 83",
    "sg:postcode":"1820",
    "sg:province":"Vaud",
    "wof:name":"Phyo Formation En Ost\u00e9opathie",
    "wof:placetype":"venue"
},
  "geometry": {"coordinates":[6.928286,46.422729],"type":"Point"}
}