{
  "type": "Feature",
  "properties": {
    "iso:country":"CH",
    "sg:address":"Einsiedlerstrasse 31",
    "sg:city":"W\u00e4denswil",
    "sg:orig_category":"Herstellung von Ger\u00e4ten der Elektrizit\u00e4tserzeugung, -verteilung u.\u00e4. -Herstellung von elektronischen",
    "sg:phone":"+41 17802535",
    "sg:postcode":"8820",
    "sg:province":"Z\u00fcrich",
    "wof:name":"Mineltec Hoffmann E.",
    "wof:placetype":"venue"
},
  "geometry": {"coordinates":[8.6873531342,47.218914032],"type":"Point"}
}