{
  "type": "Feature",
  "properties": {
    "iso:country":"CH",
    "sg:address":"Kalofen 1",
    "sg:city":"Grosswangen",
    "sg:orig_category":"Fernmeldedienste",
    "sg:postcode":"6022",
    "sg:province":"Luzern",
    "wof:name":"Gemeinschafts-antennenanlage Grosswangen Ag",
    "wof:placetype":"venue"
},
  "geometry": {"coordinates":[8.0496912003,47.1313362122],"type":"Point"}
}