{
  "type": "Feature",
  "properties": {
    "iso:country":"CH",
    "sg:address":"L\u00f6berenstrasse 19 6300 Zug. Postfach",
    "sg:city":"Zug",
    "sg:orig_category":"Kauf U Verkauf von Immobilien auf eigene Rechnung",
    "sg:phone":"+41 71 877 20 35",
    "sg:postcode":"6300",
    "sg:province":"Zug",
    "wof:name":"Synkope Immobilien, Paul Camenzind",
    "wof:placetype":"venue"
},
  "geometry": {"coordinates":[9.4735059738,47.436706543],"type":"Point"}
}