{
  "type": "Feature",
  "properties": {
    "iso:country":"CH",
    "sg:address":"Eggenstrasse 15 5616 Meisterschwanden. Postfach",
    "sg:city":"Meisterschwanden",
    "sg:orig_category":"Softwareentwicklung U beratung",
    "sg:phone":"+41 56 667 27 81",
    "sg:postcode":"5616",
    "sg:province":"Aargau",
    "wof:name":"Voggi-lernprogramme L\u00fcscher Andreas Software F\u00fcr Den Bildungsbereich; Entwicklung, Vertrieb",
    "wof:placetype":"venue"
},
  "geometry": {"coordinates":[8.2257318497,47.2953872681],"type":"Point"}
}