{
  "type": "Feature",
  "properties": {
    "iso:country":"CH",
    "sg:address":"Fluhmattstrasse 4",
    "sg:city":"Buchrain",
    "sg:orig_category":"Vereine Musik/Blasmusik",
    "sg:postcode":"6033",
    "sg:province":"Luzern",
    "wof:name":"Feldmusik Eschenbach",
    "wof:placetype":"venue"
},
  "geometry": {"coordinates":[8.3200368881,47.13256073],"type":"Point"}
}