{
  "type": "Feature",
  "properties": {
    "iso:country":"CH",
    "sg:address":"V. Industria 12 Casella Postale 1239",
    "sg:city":"Biasca",
    "sg:classifiers":[
        {
            "category":"Professional",
            "subcategory":"Engineering",
            "type":"Services"
        }
    ],
    "sg:phone":"+41 91 873 01 01",
    "sg:postcode":"6710",
    "sg:province":"Ticino",
    "sg:tags":[
        "machine",
        "-",
        "mechanical"
    ],
    "wof:name":"Nickelmesh Sa",
    "wof:placetype":"venue"
},
  "geometry": {"coordinates":[8.9698448181,46.3577651978],"type":"Point"}
}