{
  "type": "Feature",
  "properties": {
    "addr:full":"Place De L'universit\u00e9 3 Gen\u00e8ve Gen\u00e8ve 1205",
    "addr:housenumber":"3",
    "addr:postcode":"1205",
    "addr:street":"Place De L'Universite \u0301",
    "iso:country":"CH",
    "sg:address":"Place De L'universit\u00e9 3",
    "sg:city":"Gen\u00e8ve",
    "sg:classifiers":[
        {
            "category":"Education",
            "subcategory":"Library",
            "type":"Public Place"
        }
    ],
    "sg:phone":"+41 22 705 73 14",
    "sg:postcode":"1205",
    "sg:province":"Gen\u00e8ve",
    "sg:tags":[
        "u",
        "bibliotheken",
        "archive"
    ],
    "wof:name":"Facult\u00e9 Des Lettres Biblioth\u00e8que",
    "wof:placetype":"venue"
},
  "geometry": {"coordinates":[6.143565,46.198299],"type":"Point"}
}