{
  "type": "Feature",
  "properties": {
    "iso:country":"CH",
    "sg:address":"Wachtmeistergasse 2",
    "sg:city":"Frutigen",
    "sg:orig_category":"D\u00e9colletagen and Schrauben Herstellung Pulvermetallurgie Schmieden, Pressen, Stanzen U Profilwalzen ",
    "sg:phone":"+41 32 968 64 51",
    "sg:postcode":"3714",
    "sg:province":"Bern",
    "wof:name":"Raoul Guyot Sa Etampage & D\u00e9colletage",
    "wof:placetype":"venue"
},
  "geometry": {"coordinates":[6.8296809196,47.1061592102],"type":"Point"}
}