{
  "type": "Feature",
  "properties": {
    "iso:country":"CH",
    "sg:address":"Uferweg 1 3400 Burgdorf. Postfach",
    "sg:city":"Burgdorf",
    "sg:orig_category":"Elektroinstallation",
    "sg:phone":"+41 19315010",
    "sg:postcode":"3400",
    "sg:province":"Bern",
    "wof:name":"Elektro Frauchiger Ag",
    "wof:placetype":"venue"
},
  "geometry": {"coordinates":[8.7950897217,47.32629776],"type":"Point"}
}