{
  "type": "Feature",
  "properties": {
    "iso:country":"CH",
    "sg:address":"Avenue Maurice-troillet 95",
    "sg:city":"Sion",
    "sg:classifiers":[
        {
            "category":"Wholesale",
            "subcategory":"Construction Materials",
            "type":"Manufacturing & Wholesale Goods"
        }
    ],
    "sg:phone":"+41 27 322 27 82",
    "sg:postcode":"1950",
    "sg:province":"Valais",
    "sg:tags":[
        "concrete",
        "additive"
    ],
    "wof:name":"Difutec Sa",
    "wof:placetype":"venue"
},
  "geometry": {"coordinates":[7.33623,46.225948],"type":"Point"}
}