{
  "type": "Feature",
  "properties": {
    "iso:country":"CH",
    "sg:address":"Chemin Du Vert-pr\u00e9 3",
    "sg:city":"Petit-lancy",
    "sg:orig_category":"Malerei Tapeziererei",
    "sg:phone":"+41 22 792 95 92",
    "sg:postcode":"1213",
    "sg:province":"Gen\u00e8ve",
    "wof:name":"Ren\u00e9 Steiner Peinture & Papiers-peints",
    "wof:placetype":"venue"
},
  "geometry": {"coordinates":[6.1181201935,46.1918258667],"type":"Point"}
}