{
  "type": "Feature",
  "properties": {
    "iso:country":"CH",
    "sg:address":"St\u00fctzli",
    "sg:city":"Doppleschwand",
    "sg:orig_category":"Grosshandel mit lebenden Tieren",
    "sg:phone":"+41 41 480 16 88",
    "sg:postcode":"6112",
    "sg:province":"Luzern",
    "wof:name":"Viehhandel Untern\u00e4hrer Gmbh",
    "wof:placetype":"venue"
},
  "geometry": {"coordinates":[8.0531072617,47.0187835693],"type":"Point"}
}