{
  "type": "Feature",
  "properties": {
    "iso:country":"CH",
    "sg:address":"Marter Via 10",
    "sg:city":"Porza",
    "sg:orig_category":"Abbruch U Sprenggewerbe, Erdbewegungsarbeiten",
    "sg:phone":"+41 91 940 65 83",
    "sg:postcode":"6948",
    "sg:province":"Ticino",
    "wof:name":"Migliarese Angelo",
    "wof:placetype":"venue"
},
  "geometry": {"coordinates":[8.954516,46.029469],"type":"Point"}
}