{
  "type": "Feature",
  "properties": {
    "iso:country":"CH",
    "sg:address":"3363",
    "sg:city":"Ober\u00f6nz",
    "sg:orig_category":"Verkehrs- and Tourismusb\u00fcros",
    "sg:phone":"+41 27 932 10 00",
    "sg:postcode":"3363",
    "sg:province":"Bern",
    "wof:name":"Verkehrsverein",
    "wof:placetype":"venue"
},
  "geometry": {"coordinates":[7.6887397766,47.1736412048],"type":"Point"}
}