{
  "type": "Feature",
  "properties": {
    "iso:country":"CH",
    "sg:address":"Albisriederstrasse 252",
    "sg:city":"Z\u00fcrich",
    "sg:orig_category":"G\u00fcterbef\u00f6rderung im Strassenverkehr",
    "sg:phone":"+41 79 603 65 27",
    "sg:postcode":"8047",
    "sg:province":"Z\u00fcrich",
    "wof:name":"K\u00e4ser Transport Transportfirma",
    "wof:placetype":"venue"
},
  "geometry": {"coordinates":[-77.13302612299999,40.4769287109],"type":"Point"}
}