{
  "type": "Feature",
  "properties": {
    "iso:country":"CH",
    "sg:address":"Chevrens Route De 47",
    "sg:city":"Ani\u00e8res",
    "sg:orig_category":"Finanzierungsinstitutionen",
    "sg:phone":"+41 22 751 25 44",
    "sg:postcode":"1247",
    "sg:province":"Gen\u00e8ve",
    "wof:name":"Maini Thomann",
    "wof:placetype":"venue"
},
  "geometry": {"coordinates":[6.2301588058,46.2790222168],"type":"Point"}
}