{
  "type": "Feature",
  "properties": {
    "iso:country":"CH",
    "sg:address":"Gewerbestrasse 7 3661 Uetendorf. Postfach 34",
    "sg:city":"Uetendorf",
    "sg:orig_category":"Herstellung von Betonerzeugnissen f\u00fcr den Bau",
    "sg:phone":"+41 33 346 55 00",
    "sg:postcode":"3661",
    "sg:province":"Bern",
    "wof:name":"Rauh-betonschalungen Ag",
    "wof:placetype":"venue"
},
  "geometry": {"coordinates":[7.57587,46.776253],"type":"Point"}
}