{
  "type": "Feature",
  "properties": {
    "iso:country":"CH",
    "sg:address":"Rainacker 177",
    "sg:city":"Niederbuchsiten",
    "sg:orig_category":"Ingenieurb\u00fcros Maschinenbau Patentverwertung",
    "sg:phone":"+41 22 771 29 33",
    "sg:postcode":"4626",
    "sg:province":"Solothurn",
    "wof:name":"Jean S. Robert Bureau D'ing\u00e9nieur",
    "wof:placetype":"venue"
},
  "geometry": {"coordinates":[6.1042528152,46.1490287781],"type":"Point"}
}