{
  "type": "Feature",
  "properties": {
    "iso:country":"CH",
    "sg:address":"Baarerstrasse 75 6300 Zug. Postfach 2551",
    "sg:city":"Zug",
    "sg:orig_category":"Markt U Meinungsforschung Unternehmensberatung",
    "sg:phone":"+41 41 728 75 75",
    "sg:postcode":"6302",
    "sg:province":"Zug",
    "wof:name":"Sigma Promotion Ag",
    "wof:placetype":"venue"
},
  "geometry": {"coordinates":[8.517616272,47.1769981384],"type":"Point"}
}