{
  "type": "Feature",
  "properties": {
    "iso:country":"CH",
    "sg:address":"Hardstrasse 30",
    "sg:city":"Safenwil",
    "sg:orig_category":"Politische Parteien SVP",
    "sg:phone":"+41 62 797 91 23",
    "sg:postcode":"5745",
    "sg:province":"Aargau",
    "wof:name":"Svp Ortspartei Safenwil",
    "wof:placetype":"venue"
},
  "geometry": {"coordinates":[7.9886269569,47.3249855042],"type":"Point"}
}