{
  "type": "Feature",
  "properties": {
    "iso:country":"CH",
    "sg:address":"Neue Winterthurerstrasse 75 8304 Wallisellen. Postfach",
    "sg:city":"Glattzentrum",
    "sg:orig_category":"Werbevermittlung Werbung",
    "sg:phone":"+41 18305050",
    "sg:postcode":"8301",
    "sg:province":"Z\u00fcrich",
    "wof:name":"Plakatron Ag",
    "wof:placetype":"venue"
},
  "geometry": {"coordinates":[8.6003408432,47.4092330933],"type":"Point"}
}