{
  "type": "Feature",
  "properties": {
    "iso:country":"CH",
    "sg:address":"Ch. De La Vuarpilli\u00e8re 1",
    "sg:city":"Nyon",
    "sg:classifiers":[
        {
            "category":"Manufacturing",
            "subcategory":"Metals",
            "type":"Manufacturing & Wholesale Goods"
        }
    ],
    "sg:phone":"+41 22 361 06 23",
    "sg:postcode":"1260",
    "sg:province":"Vaud",
    "sg:tags":[
        "alloy",
        "construction",
        "lightweight"
    ],
    "wof:name":"Ouvrages M\u00e9talliques Sa",
    "wof:placetype":"venue"
},
  "geometry": {"coordinates":[6.218711853,46.400177002],"type":"Point"}
}