{
  "type": "Feature",
  "properties": {
    "iso:country":"CH",
    "sg:address":"Hof 3862 Innertkirchen. Postfach 61",
    "sg:city":"Innertkirchen",
    "sg:orig_category":"Grosshandel mit Eisenwaren sowie Installationsbedarf f\u00fcr Gas, Wasser U Heizung Sanit\u00e4rinstallation",
    "sg:postcode":"3862",
    "sg:province":"Bern",
    "wof:name":"Schild, Hans.",
    "wof:placetype":"venue"
},
  "geometry": {"coordinates":[8.2295875549,46.7051315308],"type":"Point"}
}