{
  "type": "Feature",
  "properties": {
    "iso:country":"CH",
    "sg:address":"Bernfeldweg 17",
    "sg:city":"Jegenstorf",
    "sg:orig_category":"Sportvereine Sch\u00fctzen",
    "sg:phone":"+41 31 761 04 10",
    "sg:postcode":"3303",
    "sg:province":"Bern",
    "wof:name":"Artilleriesch\u00fctzengesell.",
    "wof:placetype":"venue"
},
  "geometry": {"coordinates":[7.5026760101,47.043636322],"type":"Point"}
}