{
  "type": "Feature",
  "properties": {
    "iso:country":"CH",
    "sg:address":"Morgentalstrasse 34",
    "sg:city":"Aadorf",
    "sg:orig_category":"Handel mit Automobilteilen U Zubeh\u00f6r",
    "sg:phone":"+41 71 642 73 22",
    "sg:postcode":"8355",
    "sg:province":"Thurgau",
    "wof:name":"Stabil Autogep\u00e4cktr\u00e4ger",
    "wof:placetype":"venue"
},
  "geometry": {"coordinates":[8.8960943222,47.4940986633],"type":"Point"}
}