{
  "type": "Feature",
  "properties": {
    "iso:country":"CH",
    "sg:address":"Rue De L'ondine 19 1636 Broc. Postfach",
    "sg:city":"Broc",
    "sg:orig_category":"Sonstige mit Sport verbundene T\u00e4tigkeiten",
    "sg:postcode":"1636",
    "sg:province":"Fribourg",
    "wof:name":"Moto-club De La Gruy\u00e8re",
    "wof:placetype":"venue"
},
  "geometry": {"coordinates":[7.1003499031,46.6031417847],"type":"Point"}
}