{
  "type": "Feature",
  "properties": {
    "iso:country":"CH",
    "sg:address":"1783",
    "sg:city":"Pensier",
    "sg:orig_category":"Werbung",
    "sg:phone":"+41 56 442 14 40",
    "sg:postcode":"1783",
    "sg:province":"Fribourg",
    "wof:name":"Mediall, Bachmann R.",
    "wof:placetype":"venue"
},
  "geometry": {"coordinates":[8.2035999298,47.4864692688],"type":"Point"}
}