{
  "type": "Feature",
  "properties": {
    "iso:country":"CH",
    "sg:address":"Schmitterstrasse 28",
    "sg:city":"Diepoldsau",
    "sg:orig_category":"Detailhandel mit Sportartikeln Herstellung von Sportger\u00e4ten",
    "sg:phone":"+41 19326682",
    "sg:postcode":"9444",
    "sg:province":"St. Gallen",
    "wof:name":"Iten Sport",
    "wof:placetype":"venue"
},
  "geometry": {"coordinates":[8.794383049,47.3206520081],"type":"Point"}
}