{
  "type": "Feature",
  "properties": {
    "iso:country":"CH",
    "sg:address":"Gartenstrasse 10",
    "sg:city":"Amriswil",
    "sg:orig_category":"Softwareentwicklung U beratung",
    "sg:postcode":"8580",
    "sg:province":"Thurgau",
    "wof:name":"Nutronic Edv Nufer Erich",
    "wof:placetype":"venue"
},
  "geometry": {"coordinates":[9.3046646118,47.5533256531],"type":"Point"}
}