{
  "type": "Feature",
  "properties": {
    "iso:country":"CH",
    "sg:address":"Langgr\u00fctstrasse 103 8000 Z\u00fcrich. Postfach",
    "sg:city":"Z\u00fcrich",
    "sg:orig_category":"Sonstige pers\u00f6nliche Dienstleistungen",
    "sg:postcode":"8047",
    "sg:province":"Z\u00fcrich",
    "wof:name":"Crysec Gmbh",
    "wof:placetype":"venue"
},
  "geometry": {"coordinates":[8.4955825806,47.372959137],"type":"Point"}
}