{
  "type": "Feature",
  "properties": {
    "iso:country":"CH",
    "sg:address":"Romanshornerstrasse 21",
    "sg:city":"Arbon",
    "sg:orig_category":"Handel mit Motorr\u00e4dern, Teilen U Zubeh\u00f6r Instandhaltung U Reparatur von Motorr\u00e4dern",
    "sg:postcode":"9320",
    "sg:province":"Thurgau",
    "wof:name":"Zweirad-center Walser",
    "wof:placetype":"venue"
},
  "geometry": {"coordinates":[9.4290962219,47.5174751282],"type":"Point"}
}