{
  "type": "Feature",
  "properties": {
    "iso:country":"CH",
    "sg:address":"Route De St-julien 77bis",
    "sg:city":"Grand-lancy",
    "sg:orig_category":"Autogaragen Grosshandel mit Wasch U Reinigungsmitteln",
    "sg:phone":"+41 22 343 29 20",
    "sg:postcode":"1212",
    "sg:province":"Gen\u00e8ve",
    "wof:name":"Gleam Car Di Diego Giacomantonio",
    "wof:placetype":"venue"
},
  "geometry": {"coordinates":[6.126332,46.172459],"type":"Point"}
}