{
  "type": "Feature",
  "properties": {
    "iso:country":"CH",
    "sg:address":"Rue Des Rois 13 1200 Gen\u00e8ve. Postfach",
    "sg:city":"Gen\u00e8ve",
    "sg:orig_category":"Religi\u00f6se Vereinigungen",
    "sg:phone":"+41 22 329 37 22",
    "sg:postcode":"1204",
    "sg:province":"Gen\u00e8ve",
    "wof:name":"Groupement Genevois De La Vie Protestante",
    "wof:placetype":"venue"
},
  "geometry": {"coordinates":[6.137983799,46.202457428],"type":"Point"}
}