{
  "type": "Feature",
  "properties": {
    "iso:country":"CH",
    "sg:address":"Altenbergstrasse 8",
    "sg:city":"Bern",
    "sg:orig_category":"Fotografische Ateliers",
    "sg:phone":"+41 56 443 32 09",
    "sg:postcode":"3013",
    "sg:province":"Bern",
    "wof:name":"Werner Wegm\u00fcller Fotografisches Atelier",
    "wof:placetype":"venue"
},
  "geometry": {"coordinates":[8.169210434,47.4446563721],"type":"Point"}
}