{
  "type": "Feature",
  "properties": {
    "iso:country":"CH",
    "sg:address":"Riedmattenstrasse 56",
    "sg:city":"Port",
    "sg:orig_category":"Bauschreinerei",
    "sg:phone":"+41 79 407 08 63",
    "sg:postcode":"2562",
    "sg:province":"Bern",
    "wof:name":"Franco Curcuruto Schreinerei",
    "wof:placetype":"venue"
},
  "geometry": {"coordinates":[8.79835,47.333172],"type":"Point"}
}