{
  "type": "Feature",
  "properties": {
    "iso:country":"CH",
    "sg:address":"Huber Avenue Max 10",
    "sg:city":"Sierre",
    "sg:orig_category":"Detailhandel mit Metallwaren, Anstrichmitteln, Glaswaren, Bau U Heimwerkerbedarf",
    "sg:phone":"+41 27 456 29 52",
    "sg:postcode":"3960",
    "sg:province":"Valais",
    "wof:name":"Borer Sandra",
    "wof:placetype":"venue"
},
  "geometry": {"coordinates":[7.5306549072,46.2924041748],"type":"Point"}
}