{
  "type": "Feature",
  "properties": {
    "iso:country":"CH",
    "sg:address":"Birkenweg 19",
    "sg:city":"Laufen",
    "sg:orig_category":"Herstellung von sonstigen Metallwaren",
    "sg:phone":"+41 61 761 19 91",
    "sg:postcode":"4242",
    "sg:province":"Basel-Landschaft",
    "wof:name":"Gisa H\u00e4nggi Guido + Potenza Salvatore",
    "wof:placetype":"venue"
},
  "geometry": {"coordinates":[7.4956851006,47.4237976074],"type":"Point"}
}