{
  "type": "Feature",
  "properties": {
    "iso:country":"CH",
    "sg:address":"Hauptstrasse 296",
    "sg:city":"Bottenwil",
    "sg:orig_category":"Druckweiterverarbeitung",
    "sg:phone":"+41 19405914",
    "sg:postcode":"4814",
    "sg:province":"Aargau",
    "wof:name":"E. Keller Ag Handbuchbinderei",
    "wof:placetype":"venue"
},
  "geometry": {"coordinates":[8.8062210083,47.3302688599],"type":"Point"}
}