{
  "type": "Feature",
  "properties": {
    "iso:country":"CH",
    "sg:address":"Sous-raimeux 7",
    "sg:city":"Montagne-moutier",
    "sg:orig_category":"Grosshandel mit Nahrungsmitteln, Getr\u00e4nken U Tabakwaren ohne ausgepr\u00e4gten Schwerpunkt",
    "sg:phone":"+41 32 493 73 87",
    "sg:postcode":"2740",
    "sg:province":"Bern",
    "wof:name":"Pellaton Diffusion",
    "wof:placetype":"venue"
},
  "geometry": {"coordinates":[7.3848361969,47.282207489],"type":"Point"}
}