{
  "type": "Feature",
  "properties": {
    "iso:country":"CH",
    "sg:address":"Hauptstrasse 70",
    "sg:city":"Tecknau",
    "sg:orig_category":"Fachdetailhandel in Verkaufsr\u00e4umen Reparatur von Uhren U Schmuck",
    "sg:phone":"+41 61 981 10 16",
    "sg:postcode":"4492",
    "sg:province":"Basel-Landschaft",
    "wof:name":"Eugen Fiechter, Ergo-watch",
    "wof:placetype":"venue"
},
  "geometry": {"coordinates":[7.8854842186,47.4486274719],"type":"Point"}
}