{
  "type": "Feature",
  "properties": {
    "iso:country":"CH",
    "sg:address":"Molard Place Du 5 1204 Gen\u00e8ve. Postfach",
    "sg:city":"Gen\u00e8ve",
    "sg:orig_category":"Sonstige mit der Informatik verbundene T\u00e4tigkeiten",
    "sg:postcode":"1204",
    "sg:province":"Gen\u00e8ve",
    "wof:name":"Rdr Regency Data Research Sa",
    "wof:placetype":"venue"
},
  "geometry": {"coordinates":[6.1484470367,46.2035598755],"type":"Point"}
}