{
  "type": "Feature",
  "properties": {
    "iso:country":"CH",
    "sg:address":"Junkholzweg 3 4303 Kaiseraugst. Postfach 98",
    "sg:city":"Kaiseraugst",
    "sg:orig_category":"Grosshandel mit Eisenwaren sowie Installationsbedarf f\u00fcr Gas, Wasser U Heizung",
    "sg:phone":"+41 61 811 62 60",
    "sg:postcode":"4303",
    "sg:province":"Aargau",
    "wof:name":"Allco-allenspach Gmbh",
    "wof:placetype":"venue"
},
  "geometry": {"coordinates":[7.7308330536,47.5379562378],"type":"Point"}
}