{
  "type": "Feature",
  "properties": {
    "iso:country":"CH",
    "sg:address":"Dietlikerstrasse 22",
    "sg:city":"Kloten",
    "sg:orig_category":"Herstellung von medizinischen U chirurgischen Ger\u00e4ten sowie orthop\u00e4dischen Vorrichtungen",
    "sg:postcode":"8302",
    "sg:province":"Z\u00fcrich",
    "wof:name":"Meddex, Dr. Z. Simonovoc",
    "wof:placetype":"venue"
},
  "geometry": {"coordinates":[8.5861158371,47.4472694397],"type":"Point"}
}