{
  "type": "Feature",
  "properties": {
    "addr:full":"L\u00f6wenplatz 9 6004 Luzern. Postfach Luzern Luzern 6003",
    "addr:housenumber":"9",
    "addr:postcode":"6004;postfach;6003",
    "addr:street":"Loewenplatz",
    "iso:country":"CH",
    "sg:address":"L\u00f6wenplatz 9 6004 Luzern. Postfach",
    "sg:city":"Luzern",
    "sg:orig_category":"Allgemeiner Hoch U Tiefbau",
    "sg:postcode":"6003",
    "sg:province":"Luzern",
    "wof:name":"Gerig Ulrich Baugesch\u00e4ft",
    "wof:placetype":"venue"
},
  "geometry": {"coordinates":[8.305341,47.052784],"type":"Point"}
}