{
  "type": "Feature",
  "properties": {
    "iso:country":"CH",
    "sg:address":"Chemin De Ch\u00eanaie 127",
    "sg:city":"Bellevue",
    "sg:orig_category":"Architektur U Ingenieurb\u00fcros",
    "sg:phone":"+41 22 774 14 33",
    "sg:postcode":"1293",
    "sg:province":"Gen\u00e8ve",
    "wof:name":"Erem, Mulet Ricard",
    "wof:placetype":"venue"
},
  "geometry": {"coordinates":[6.147988,46.25795],"type":"Point"}
}