{
  "type": "Feature",
  "properties": {
    "iso:country":"CH",
    "sg:address":"Buchholzstrasse 55",
    "sg:city":"Glarus",
    "sg:orig_category":"Sonstige Institutionen des Sozialwesens ohne Beherbergung",
    "sg:postcode":"8750",
    "sg:province":"Glarus",
    "wof:name":"Elternvereinigung Daj Region Gl'land",
    "wof:placetype":"venue"
},
  "geometry": {"coordinates":[9.0639781952,47.04895401],"type":"Point"}
}