{
  "type": "Feature",
  "properties": {
    "iso:country":"CH",
    "sg:address":"Willishalten 266",
    "sg:city":"Zimmerwald",
    "sg:orig_category":"Finanzierungsinstitutionen",
    "sg:phone":"+41 31 819 33 38",
    "sg:postcode":"3086",
    "sg:province":"Bern",
    "wof:name":"Priscus Finanztreuhand Gesellschaft F\u00fcr Aktive Finanzplanung Und Verm\u00f6gensverwaltung Mbh",
    "wof:placetype":"venue"
},
  "geometry": {"coordinates":[7.4716010094,46.8815917969],"type":"Point"}
}