{
  "type": "Feature",
  "properties": {
    "iso:country":"CH",
    "sg:address":"Sandgruebestrasse 4",
    "sg:city":"Sursee",
    "sg:orig_category":"Grosshandel mit Software Softwareentwicklung U beratung",
    "sg:phone":"+41 41 921 08 73",
    "sg:postcode":"6210",
    "sg:province":"Luzern",
    "wof:name":"Pro-c (international) Sa",
    "wof:placetype":"venue"
},
  "geometry": {"coordinates":[8.1100902557,47.1765480042],"type":"Point"}
}