{
  "type": "Feature",
  "properties": {
    "iso:country":"CH",
    "sg:address":"Heckenweg 1",
    "sg:city":"Herrliberg",
    "sg:orig_category":"Unternehmensberatung Wirtschaftspr\u00fcfung, Steuerberatung U Treuhand",
    "sg:phone":"+41 19153462",
    "sg:postcode":"8704",
    "sg:province":"Z\u00fcrich",
    "wof:name":"Jw Treuhand & Beratungs Gmbh",
    "wof:placetype":"venue"
},
  "geometry": {"coordinates":[8.6251115799,47.2855262756],"type":"Point"}
}