{
  "type": "Feature",
  "properties": {
    "iso:country":"CH",
    "sg:address":"Zum Rauacker 19",
    "sg:city":"Arlesheim",
    "sg:orig_category":"Vereine Fasnacht",
    "sg:phone":"+41 61 701 80 03",
    "sg:postcode":"4144",
    "sg:province":"Basel-Landschaft",
    "wof:name":"D Gaiferl\u00e4tz",
    "wof:placetype":"venue"
},
  "geometry": {"coordinates":[7.615940094,47.4902153015],"type":"Point"}
}