{
  "type": "Feature",
  "properties": {
    "addr:full":"Chellenstrasse 16e Walchwil Zug 6318",
    "addr:housenumber":"16e",
    "addr:postcode":"6318",
    "addr:street":"Chellenstrasse;Zug",
    "iso:country":"CH",
    "sg:address":"Chellenstrasse 16e",
    "sg:city":"Walchwil",
    "sg:orig_category":"Datenverarbeitungsdienste Softwareentwicklung U beratung",
    "sg:phone":"+41 18851111",
    "sg:postcode":"6318",
    "sg:province":"Zug",
    "wof:name":"Dao Informatik Ag",
    "wof:placetype":"venue"
},
  "geometry": {"coordinates":[8.502083,47.487999],"type":"Point"}
}