{
  "type": "Feature",
  "properties": {
    "iso:country":"CH",
    "sg:address":"Waldeckstrasse 1",
    "sg:city":"B\u00e4tterkinden",
    "sg:orig_category":"Detailhandel mit Getr\u00e4nken",
    "sg:phone":"+41 32 665 37 28",
    "sg:postcode":"3315",
    "sg:province":"Bern",
    "wof:name":"Markus Begert Getr\u00e4nke",
    "wof:placetype":"venue"
},
  "geometry": {"coordinates":[7.5331339836,47.1288223267],"type":"Point"}
}