{
  "type": "Feature",
  "properties": {
    "iso:country":"CH",
    "sg:address":"Florastrasse 5",
    "sg:city":"Z\u00fcrich",
    "sg:orig_category":"Non-Classified Establishments",
    "sg:postcode":"8008",
    "sg:province":"Z\u00fcrich",
    "wof:name":"Screen Space Gmbh",
    "wof:placetype":"venue"
},
  "geometry": {"coordinates":[8.5487642288,47.3609848022],"type":"Point"}
}