{
  "type": "Feature",
  "properties": {
    "iso:country":"CH",
    "sg:address":"Schlossbergstrasse 8",
    "sg:city":"Zollikon",
    "sg:orig_category":"Sportvereine Ballsport Tennis",
    "sg:phone":"+41 13915217",
    "sg:postcode":"8702",
    "sg:province":"Z\u00fcrich",
    "wof:name":"Tc Z\u00fcrich",
    "wof:placetype":"venue"
},
  "geometry": {"coordinates":[8.5798788071,47.3457641602],"type":"Point"}
}