{
  "type": "Feature",
  "properties": {
    "iso:country":"CH",
    "sg:address":"Viale Stefano Franscini 23",
    "sg:city":"Lugano",
    "sg:orig_category":"Detailhandel mit Waren verschiedener Art, Hauptrichtung Nahrungsmittel",
    "sg:postcode":"6900",
    "sg:province":"Ticino",
    "wof:name":"Alisana Sa",
    "wof:placetype":"venue"
},
  "geometry": {"coordinates":[8.9541187286,46.0107040405],"type":"Point"}
}