{
  "type": "Feature",
  "properties": {
    "iso:country":"CH",
    "sg:address":"Pilatusstrasse 13",
    "sg:city":"Sarnen",
    "sg:orig_category":"G\u00fcterbef\u00f6rderung im Strassenverkehr",
    "sg:phone":"+41 41 660 40 66",
    "sg:postcode":"6060",
    "sg:province":"Obwalden",
    "wof:name":"Ab\u00e4cherli Transport Ag",
    "wof:placetype":"venue"
},
  "geometry": {"coordinates":[8.2477207184,46.9005088806],"type":"Point"}
}