{
  "type": "Feature",
  "properties": {
    "iso:country":"CH",
    "sg:address":"Avenue De La Gare 9",
    "sg:city":"Conthey",
    "sg:orig_category":"Elektroinstallation",
    "sg:phone":"+41 27 346 65 05",
    "sg:postcode":"1964",
    "sg:province":"Valais",
    "wof:name":"Balet & Rey \u00e9lectricit\u00e9 Sa",
    "wof:placetype":"venue"
},
  "geometry": {"coordinates":[7.3035731316,46.2187576294],"type":"Point"}
}