{
  "type": "Feature",
  "properties": {
    "iso:country":"CH",
    "sg:address":"Place De La Gare 9",
    "sg:city":"Nyon",
    "sg:orig_category":"Sonstiges Versicherungsgewerbe",
    "sg:postcode":"1260",
    "sg:province":"Vaud",
    "wof:name":"Mobili\u00e8re Suisse Soci\u00e9t\u00e9 D'assurances, Agence G\u00e9n\u00e9rale De Nyon, Desarzens Etienne",
    "wof:placetype":"venue"
},
  "geometry": {"coordinates":[6.2364168167,46.3842086792],"type":"Point"}
}