{
  "type": "Feature",
  "properties": {
    "iso:country":"CH",
    "sg:address":"Chemin Pontverre 15",
    "sg:city":"Confignon",
    "sg:orig_category":"Architekturb\u00fcros",
    "sg:phone":"+41 22 757 27 09",
    "sg:postcode":"1232",
    "sg:province":"Gen\u00e8ve",
    "wof:name":"Paul Marti Bureau D'architecture",
    "wof:placetype":"venue"
},
  "geometry": {"coordinates":[6.081943,46.173351],"type":"Point"}
}