{
  "type": "Feature",
  "properties": {
    "iso:country":"CH",
    "sg:address":"Zentralstrasse 121",
    "sg:city":"Neuhausen",
    "sg:orig_category":"Instandhaltung U Reparatur von Automobilen",
    "sg:phone":"+41 41 852 11 11",
    "sg:postcode":"8212",
    "sg:province":"Schaffhausen",
    "wof:name":"Schmid Max Ag",
    "wof:placetype":"venue"
},
  "geometry": {"coordinates":[8.6221208572,47.6859474182],"type":"Point"}
}