{
  "type": "Feature",
  "properties": {
    "iso:country":"CH",
    "sg:address":"Tivoli 8957 Spreitenbach. Postfach 1541",
    "sg:city":"Spreitenbach",
    "sg:orig_category":"Grosshandel mit B\u00fcromaschinen Grosshandel mit M\u00f6beln, Wohnbedarf, Teppichen U Bodenbel\u00e4gen",
    "sg:phone":"+41 56 402 14 14",
    "sg:postcode":"8957",
    "sg:province":"Aargau",
    "wof:name":"Lexus Data Systems, Nagihan Karaer",
    "wof:placetype":"venue"
},
  "geometry": {"coordinates":[8.3656835556,47.4180450439],"type":"Point"}
}