{
  "type": "Feature",
  "properties": {
    "iso:country":"CH",
    "sg:address":"Thurgauerstrasse 56",
    "sg:city":"Z\u00fcrich",
    "sg:orig_category":"Zivilschutz",
    "sg:phone":"+41 41 666 64 44",
    "sg:postcode":"8050",
    "sg:province":"Z\u00fcrich",
    "wof:name":"Kant. Bev\u00f6lkerungsschutzamt",
    "wof:placetype":"venue"
},
  "geometry": {"coordinates":[8.2487850189,46.8949966431],"type":"Point"}
}