{
  "type": "Feature",
  "properties": {
    "iso:country":"CH",
    "sg:address":"Chemin Des Vignettes 18",
    "sg:city":"Crans-pr\u00e8s-c\u00e9ligny",
    "sg:orig_category":"Handelsvermittlung U Grosshandel",
    "sg:phone":"+41 22 776 65 65",
    "sg:postcode":"1299",
    "sg:province":"Vaud",
    "wof:name":"Amp Trading Sa",
    "wof:placetype":"venue"
},
  "geometry": {"coordinates":[6.1997981071,46.358001709],"type":"Point"}
}