{
  "type": "Feature",
  "properties": {
    "iso:country":"CH",
    "sg:address":"Kirschgartenstrasse 4",
    "sg:city":"Pratteln",
    "sg:orig_category":"Maschinen and Apparate divers Grosshandel",
    "sg:phone":"+41 61 823 87 20",
    "sg:postcode":"4133",
    "sg:province":"Basel-Landschaft",
    "wof:name":"Elisabeth L\u00f6liger L\u00f6pre Vibrator",
    "wof:placetype":"venue"
},
  "geometry": {"coordinates":[7.6917610168,47.5180015564],"type":"Point"}
}