{
  "type": "Feature",
  "properties": {
    "iso:country":"CH",
    "sg:address":"Corso Elvezia 24",
    "sg:city":"Lugano",
    "sg:orig_category":"Kosmetikinstitute",
    "sg:phone":"+41 91 923 24 84",
    "sg:postcode":"6900",
    "sg:province":"Ticino",
    "wof:name":"Karin Steffen Istituto Di Bellezza Regina",
    "wof:placetype":"venue"
},
  "geometry": {"coordinates":[8.9561777115,46.0089530945],"type":"Point"}
}