{
  "type": "Feature",
  "properties": {
    "iso:country":"CH",
    "sg:address":"6717",
    "sg:city":"Dangio-torre",
    "sg:orig_category":"Sonstige mit Sport verbundene T\u00e4tigkeiten",
    "sg:postcode":"6717",
    "sg:province":"Ticino",
    "wof:name":"Scl-tigers Ag",
    "wof:placetype":"venue"
},
  "geometry": {"coordinates":[7.757589817,46.9491271973],"type":"Point"}
}