{
  "type": "Feature",
  "properties": {
    "iso:country":"CH",
    "sg:address":"Hauptstrasse 16",
    "sg:city":"Muotathal",
    "sg:orig_category":"Hoch U Tiefbau",
    "sg:phone":"+41 41 830 10 33",
    "sg:postcode":"6436",
    "sg:province":"Schwyz",
    "wof:name":"Franz Renggli Baugesch\u00e4ft",
    "wof:placetype":"venue"
},
  "geometry": {"coordinates":[8.7545251846,46.975151062],"type":"Point"}
}