{
  "type": "Feature",
  "properties": {
    "iso:country":"CH",
    "sg:address":"Chemin Des Hutins 9",
    "sg:city":"Ani\u00e8res",
    "sg:orig_category":"Unclassifiable Establishments",
    "sg:postcode":"1247",
    "sg:province":"Gen\u00e8ve",
    "wof:name":"Latl.ch Sa",
    "wof:placetype":"venue"
},
  "geometry": {"coordinates":[6.2295060158,46.2813873291],"type":"Point"}
}