{
  "type": "Feature",
  "properties": {
    "iso:country":"CH",
    "sg:address":"Route Des Dailles 40 1700 Fribourg Case Postale 864",
    "sg:city":"Fribourg",
    "sg:orig_category":"Kauf U Verkauf von Immobilien auf eigene Rechnung Verwaltung von Immobilien",
    "sg:phone":"+41 26 401 25 64",
    "sg:postcode":"1701",
    "sg:province":"Fribourg",
    "wof:name":"Sefig, Jordan & Cie",
    "wof:placetype":"venue"
},
  "geometry": {"coordinates":[7.1536831856,46.8037452698],"type":"Point"}
}