{
  "type": "Feature",
  "properties": {
    "iso:country":"CH",
    "sg:address":"Route De Cit\u00e9-ouest 2",
    "sg:city":"Gland",
    "sg:orig_category":"Herstellung von Behindertenfahrzeugen Herstellung von orthop\u00e4dischen Vorrichtungen",
    "sg:phone":"+41 22 354 60 10",
    "sg:postcode":"1196",
    "sg:province":"Vaud",
    "wof:name":"Invacare Sa",
    "wof:placetype":"venue"
},
  "geometry": {"coordinates":[6.2583179474,46.4233665466],"type":"Point"}
}