{
  "type": "Feature",
  "properties": {
    "iso:country":"CH",
    "sg:address":"Glennerstrasse 7130 Ilanz. Postfach",
    "sg:city":"Ilanz",
    "sg:classifiers":[
        {
            "category":"Restaurant",
            "type":"Food & Drink"
        }
    ],
    "sg:phone":"+41 81 925 19 93",
    "sg:postcode":"7130",
    "sg:province":"Graubunden",
    "wof:name":"Ustria Sursilvana",
    "wof:placetype":"venue"
},
  "geometry": {"coordinates":[9.2053203583,46.774181366],"type":"Point"}
}