{
  "type": "Feature",
  "properties": {
    "iso:country":"CH",
    "sg:address":"Lohwisstrasse 46 8123 Ebmatingen. Postfach 258",
    "sg:city":"Ebmatingen",
    "sg:orig_category":"Architekturb\u00fcros Technische B\u00fcros Hoch-& Tiefbau",
    "sg:phone":"+41 19821030",
    "sg:postcode":"8123",
    "sg:province":"Z\u00fcrich",
    "wof:name":"Ecas Ag Bauberatungen",
    "wof:placetype":"venue"
},
  "geometry": {"coordinates":[8.6434,47.35635],"type":"Point"}
}