{
  "type": "Feature",
  "properties": {
    "iso:country":"CH",
    "sg:address":"Bernstrasse 59",
    "sg:city":"B\u00e4tterkinden",
    "sg:orig_category":"Grosshandel mit sonstigen Halbwaren",
    "sg:phone":"+41 32 665 43 71",
    "sg:postcode":"3315",
    "sg:province":"Bern",
    "wof:name":"Instech, Installationstechnik, E. M\u00fchlethaler",
    "wof:placetype":"venue"
},
  "geometry": {"coordinates":[7.5347700119,47.1210594177],"type":"Point"}
}