{
  "type": "Feature",
  "properties": {
    "iso:country":"CH",
    "sg:address":"Quaistrasse 5",
    "sg:city":"Steinach",
    "sg:orig_category":"Grosshandel mit B\u00fcromaschinen Grosshandel mit Datenverarbeitungsger\u00e4ten",
    "sg:phone":"+41 71 440 09 40",
    "sg:postcode":"9323",
    "sg:province":"St. Gallen",
    "wof:name":"Incotech Engineering",
    "wof:placetype":"venue"
},
  "geometry": {"coordinates":[9.4378738403,47.5042572021],"type":"Point"}
}