{
  "type": "Feature",
  "properties": {
    "iso:country":"CH",
    "sg:address":"Bernstrasse 269",
    "sg:city":"Heimberg",
    "sg:orig_category":"Instandhaltung U Reparatur von Automobilen Tankstellen",
    "sg:phone":"+41 33 437 13 33",
    "sg:postcode":"3627",
    "sg:province":"Bern",
    "wof:name":"Walter Gerber",
    "wof:placetype":"venue"
},
  "geometry": {"coordinates":[7.6087532043,46.7851867676],"type":"Point"}
}