{
  "type": "Feature",
  "properties": {
    "iso:country":"CH",
    "sg:address":"Avenue Des Pins 3",
    "sg:city":"Yvonand",
    "sg:orig_category":"Reiseb\u00fcros U Reiseveranstalter",
    "sg:phone":"+41 55 420 11 85",
    "sg:postcode":"1462",
    "sg:province":"Vaud",
    "wof:name":"V\u00f6gele Reisen International Ag",
    "wof:placetype":"venue"
},
  "geometry": {"coordinates":[8.7886457443,47.2017974854],"type":"Point"}
}