{
  "type": "Feature",
  "properties": {
    "iso:country":"CH",
    "sg:address":"Voa Principala 49",
    "sg:city":"Lenzerheide/lai",
    "sg:orig_category":"Detailhandel mit Brillen U anderen Sehhilfen",
    "sg:phone":"+41 55 210 16 49",
    "sg:postcode":"7078",
    "sg:province":"Graubunden",
    "wof:name":"Nicole Diem Optik",
    "wof:placetype":"venue"
},
  "geometry": {"coordinates":[8.818351,47.226505],"type":"Point"}
}