{
  "type": "Feature",
  "properties": {
    "iso:country":"CH",
    "sg:address":"La Platta",
    "sg:city":"Breil/brigels",
    "sg:classifiers":[
        {
            "category":"Travel",
            "subcategory":"Hotels & Motels",
            "type":"Entertainment"
        }
    ],
    "sg:phone":"+41 81 941 11 43",
    "sg:postcode":"7165",
    "sg:province":"Graubunden",
    "sg:tags":[
        "hotels",
        "mit",
        "restaurant"
    ],
    "wof:name":"Hotel Kistenpass Ag",
    "wof:placetype":"venue"
},
  "geometry": {"coordinates":[9.0638198853,46.7651901245],"type":"Point"}
}