{
  "type": "Feature",
  "properties": {
    "iso:country":"CH",
    "sg:address":"R\u00fcmikerstrasse 23",
    "sg:city":"R\u00e4terschen",
    "sg:orig_category":"Detailhandel mit B\u00fcromaschinen U einrichtungen Detailhandel mit Schreib U Papeteriewaren",
    "sg:phone":"+41 56 441 98 66",
    "sg:postcode":"8352",
    "sg:province":"Z\u00fcrich",
    "wof:name":"Neum\u00e4rt Papeterie B\u00fcrobedarf",
    "wof:placetype":"venue"
},
  "geometry": {"coordinates":[8.207595,47.483032],"type":"Point"}
}