{
  "type": "Feature",
  "properties": {
    "iso:country":"CH",
    "sg:address":"Neugasse 29",
    "sg:city":"Zug",
    "sg:orig_category":"Unclassifiable Establishments",
    "sg:postcode":"6300",
    "sg:province":"Zug",
    "wof:name":"B - Tal Holding Ag",
    "wof:placetype":"venue"
},
  "geometry": {"coordinates":[8.5155334473,47.1661834717],"type":"Point"}
}