{
  "type": "Feature",
  "properties": {
    "iso:country":"CH",
    "sg:address":"Bahnhofstrasse 21",
    "sg:city":"D\u00fcbendorf",
    "sg:orig_category":"Bauschreinerei Herstellung von M\u00f6beln verschiedener Art",
    "sg:phone":"+41 18218489",
    "sg:postcode":"8600",
    "sg:province":"Z\u00fcrich",
    "wof:name":"Ludwig B\u00fcki Bau-& M\u00f6belschreinerei",
    "wof:placetype":"venue"
},
  "geometry": {"coordinates":[8.618741,47.397667],"type":"Point"}
}