{
  "type": "Feature",
  "properties": {
    "iso:country":"CH",
    "sg:address":"Hohlstrasse 176 8000 Z\u00fcrich. Postfach",
    "sg:city":"Z\u00fcrich",
    "sg:orig_category":"Herstellung von sonstigen elektrischen Ausr\u00fcstungen",
    "sg:phone":"+41 71 288 15 55",
    "sg:postcode":"8000",
    "sg:province":"Z\u00fcrich",
    "wof:name":"Kummler + Matter Ag",
    "wof:placetype":"venue"
},
  "geometry": {"coordinates":[9.4206314087,47.4403038025],"type":"Point"}
}