{
  "type": "Feature",
  "properties": {
    "iso:country":"CH",
    "sg:address":"Loonstrasse 31",
    "sg:city":"Oberrohrdorf",
    "sg:orig_category":"Vermietung U Verpachtung von eigenen Immobilien",
    "sg:phone":"+41 18580942",
    "sg:postcode":"5452",
    "sg:province":"Aargau",
    "wof:name":"Steig Immobilien Ag Oberrohrdorf",
    "wof:placetype":"venue"
},
  "geometry": {"coordinates":[8.3097229004,47.4247779846],"type":"Point"}
}