{
  "type": "Feature",
  "properties": {
    "iso:country":"CH",
    "sg:address":"R\u00e9servoir Chemin Du 4b 1012 Lausanne. Postfach",
    "sg:city":"Lausanne",
    "sg:orig_category":"Pensionskassen",
    "sg:postcode":"1003",
    "sg:province":"Vaud",
    "wof:name":"Fonds De Pr\u00e9voyance Du Personnel D'ipro Lausanne Sa",
    "wof:placetype":"venue"
},
  "geometry": {"coordinates":[6.6569061279,46.5252304077],"type":"Point"}
}