{
  "type": "Feature",
  "properties": {
    "iso:country":"CH",
    "sg:address":"Rue Haldimand 51",
    "sg:city":"Yverdon-les-bains",
    "sg:orig_category":"Sonstiger spezialisierter Hoch U Tiefbau",
    "sg:postcode":"1400",
    "sg:province":"Vaud",
    "wof:name":"Neno, Vukanovic Nenad",
    "wof:placetype":"venue"
},
  "geometry": {"coordinates":[6.6469960213,46.7789001465],"type":"Point"}
}