{
  "type": "Feature",
  "properties": {
    "iso:country":"CH",
    "sg:address":"Turnerstrasse 6 8006 Z\u00fcrich. Postfach",
    "sg:city":"Z\u00fcrich",
    "sg:orig_category":"Forschung U Entwicklung im Bereich der Naturwissenschaften",
    "sg:postcode":"8001",
    "sg:province":"Z\u00fcrich",
    "wof:name":"Philosophisches Institut Parakletunser Mittelalterl. Philosophie, Religionsphilosophie Usw; Studium, Erforschung",
    "wof:placetype":"venue"
},
  "geometry": {"coordinates":[8.5445194244,47.3838615417],"type":"Point"}
}