{
  "type": "Feature",
  "properties": {
    "iso:country":"CH",
    "sg:address":"Bienenweg 10",
    "sg:city":"M\u00f6hlin",
    "sg:orig_category":"Mechanik Mechanische Werkst\u00e4tten",
    "sg:phone":"+41 61 851 11 96",
    "sg:postcode":"4313",
    "sg:province":"Aargau",
    "wof:name":"Vasellari Ag",
    "wof:placetype":"venue"
},
  "geometry": {"coordinates":[7.8444871902,47.5581817627],"type":"Point"}
}