{
  "type": "Feature",
  "properties": {
    "iso:country":"CH",
    "sg:address":"Chamerstrasse 15",
    "sg:city":"H\u00fcnenberg",
    "sg:orig_category":"Grosshandel mit Nahrungsmitteln, Getr\u00e4nken U Tabakwaren ohne ausgepr\u00e4gten Schwerpunkt",
    "sg:postcode":"6331",
    "sg:province":"Zug",
    "wof:name":"Via Emilia Sa",
    "wof:placetype":"venue"
},
  "geometry": {"coordinates":[8.4270572662,47.1775817871],"type":"Point"}
}