{
  "type": "Feature",
  "properties": {
    "iso:country":"CH",
    "sg:address":"Via Genzana 2",
    "sg:city":"Massagno",
    "sg:orig_category":"Gartenbau Landschaftsplanungsb\u00fcros U Gartenarchitekturb\u00fcros",
    "sg:phone":"+41 91 966 11 26",
    "sg:postcode":"6900",
    "sg:province":"Ticino",
    "wof:name":"Heiner Rodel Architetto Paesaggista",
    "wof:placetype":"venue"
},
  "geometry": {"coordinates":[8.9463281631,46.0087623596],"type":"Point"}
}