{
  "type": "Feature",
  "properties": {
    "iso:country":"CH",
    "sg:address":"Blegistrasse 13 6340 Baar. Postfach",
    "sg:city":"Baar",
    "sg:orig_category":"Sonstiger Grosshandel",
    "sg:postcode":"6340",
    "sg:province":"Zug",
    "wof:name":"Intercare Ltd Warenhandel. Finanzierung V. Handelgesch\u00e4ften. Forschung Usw. In Der Gesundheitsf\u00f6rderung",
    "wof:placetype":"venue"
},
  "geometry": {"coordinates":[8.5692443848,47.2156867981],"type":"Point"}
}