{
  "type": "Feature",
  "properties": {
    "iso:country":"CH",
    "sg:address":"Schweighofstrasse 206 8045 Z\u00fcrich",
    "sg:city":"Zust",
    "sg:orig_category":"Detailhandel mit elektrischen Haushalts-,Radio U Fernsehger\u00e4ten sowie Musikinstrumenten",
    "sg:postcode":"45",
    "wof:name":"Musikinstrumentenbau Weyeneth",
    "wof:placetype":"venue"
},
  "geometry": {"coordinates":[7.4359478951,46.6566886902],"type":"Point"}
}