{
  "type": "Feature",
  "properties": {
    "iso:country":"CH",
    "sg:address":"Stockhornstrasse 25",
    "sg:city":"Zollikofen",
    "sg:orig_category":"Unclassifiable Establishments",
    "sg:postcode":"3052",
    "sg:province":"Bern",
    "wof:name":"Meyer-k\u00fcng Heidi Hmk Strategie Und Kommunikationsberatung",
    "wof:placetype":"venue"
},
  "geometry": {"coordinates":[7.447455883,46.9999084473],"type":"Point"}
}