{
  "type": "Feature",
  "properties": {
    "iso:country":"CH",
    "sg:address":"Staatsstrasse 171",
    "sg:city":"H\u00fcnibach",
    "sg:orig_category":"Detailhandel mit Geschenkartikeln U Souvenirs",
    "sg:phone":"+41 32 373 55 84",
    "sg:postcode":"3626",
    "sg:province":"Bern",
    "wof:name":"Gygax & Co Bijou Les Boutiques",
    "wof:placetype":"venue"
},
  "geometry": {"coordinates":[7.2666568756,47.1203079224],"type":"Point"}
}