{
  "type": "Feature",
  "properties": {
    "iso:country":"CH",
    "sg:address":"6968",
    "sg:city":"Sonvico",
    "sg:orig_category":"Bestattungswesen",
    "sg:phone":"+41 91 943 13 49",
    "sg:postcode":"6968",
    "sg:province":"Ticino",
    "wof:name":"Meneghelli & Co",
    "wof:placetype":"venue"
},
  "geometry": {"coordinates":[8.989252,46.057045],"type":"Point"}
}