{
  "type": "Feature",
  "properties": {
    "addr:full":"Moosackerstrasse 15 Diepoldsau St. Gallen 9444",
    "addr:housenumber":"15",
    "addr:postcode":"9444",
    "addr:street":"Moosackerstrasse",
    "iso:country":"CH",
    "sg:address":"Moosackerstrasse 15",
    "sg:city":"Diepoldsau",
    "sg:orig_category":"Bauschreinerei Herstellung von Konstruktionsteilen, Fertigbauteilen U Ausbauelementen aus Holz",
    "sg:phone":"+41 79 409 77 02",
    "sg:postcode":"9444",
    "sg:province":"St. Gallen",
    "wof:name":"Urban Dietsche & S\u00f6hne Ag",
    "wof:placetype":"venue"
},
  "geometry": {"coordinates":[9.653373,47.386772],"type":"Point"}
}