{
  "type": "Feature",
  "properties": {
    "iso:country":"CH",
    "sg:address":"Viale Giovanni Motta 28",
    "sg:city":"Bellinzona",
    "sg:orig_category":"Herstellung von elektrischen Lampen U Leuchten",
    "sg:phone":"+41 91 826 47 47",
    "sg:postcode":"6500",
    "sg:province":"Ticino",
    "wof:name":"Modaluce Sagl Atelier Dell'illuminazione",
    "wof:placetype":"venue"
},
  "geometry": {"coordinates":[9.0241193771,46.1944618225],"type":"Point"}
}