{
  "type": "Feature",
  "properties": {
    "iso:country":"CH",
    "sg:address":"1405",
    "sg:city":"Pomy",
    "sg:orig_category":"Herstellung von sonstigen landwirtschaftlichen Maschinen Mechanische Werkst\u00e4tten",
    "sg:phone":"+41 24 425 88 23",
    "sg:postcode":"1405",
    "sg:province":"Vaud",
    "wof:name":"Pierre-alain Helfer Atelier M\u00e9canique & Agricole",
    "wof:placetype":"venue"
},
  "geometry": {"coordinates":[6.6688499451,46.7578010559],"type":"Point"}
}