{
  "type": "Feature",
  "properties": {
    "iso:country":"CH",
    "sg:address":"Badistrasse 31",
    "sg:city":"Ebnat",
    "sg:orig_category":"Primarschulen",
    "sg:phone":"+41 71 993 29 80",
    "sg:postcode":"9642",
    "sg:province":"St. Gallen",
    "wof:name":"Primarschule Gill",
    "wof:placetype":"venue"
},
  "geometry": {"coordinates":[9.1210670471,47.2665061951],"type":"Point"}
}