{
  "type": "Feature",
  "properties": {
    "iso:country":"CH",
    "sg:address":"Alter Aargauerstalden 2",
    "sg:city":"Bern",
    "sg:classifiers":[
        {
            "category":"Government",
            "subcategory":"Post Office",
            "type":"Public Place"
        }
    ],
    "sg:phone":"+41 31 368 09 60",
    "sg:postcode":"3006",
    "sg:province":"Bern",
    "sg:tags":[
        "caf\u00e9s",
        "tea-rooms"
    ],
    "wof:name":"Caf\u00e9-bar Sous-sol",
    "wof:placetype":"venue"
},
  "geometry": {"coordinates":[7.4601211548,46.9483947754],"type":"Point"}
}