{
  "type": "Feature",
  "properties": {
    "iso:country":"CH",
    "sg:address":"Industriering 19 3250 Lyss. Postfach 156",
    "sg:city":"Lyss",
    "sg:orig_category":"G\u00fcterbef\u00f6rderung im Strassenverkehr",
    "sg:phone":"+41 32 387 32 32",
    "sg:postcode":"3250",
    "sg:province":"Bern",
    "wof:name":"Panalpina Ag, Bern-lyss",
    "wof:placetype":"venue"
},
  "geometry": {"coordinates":[7.3094501495,47.0887641907],"type":"Point"}
}