{
  "type": "Feature",
  "properties": {
    "iso:country":"CH",
    "sg:address":"Kapplerstrasse 113",
    "sg:city":"Ebnat",
    "sg:orig_category":"Instandhaltung U Reparatur von Automobilen",
    "sg:phone":"+41 71 993 33 55",
    "sg:postcode":"9642",
    "sg:province":"St. Gallen",
    "wof:name":"Garage Hermann Ag",
    "wof:placetype":"venue"
},
  "geometry": {"coordinates":[9.1094083786,47.2734069824],"type":"Point"}
}