{
  "type": "Feature",
  "properties": {
    "iso:country":"CH",
    "sg:address":"6742",
    "sg:city":"Pollegio",
    "sg:orig_category":"Schulpflegen",
    "sg:postcode":"6742",
    "sg:province":"Ticino",
    "wof:name":"Delegazione Scolastica Del Comune Di Pollegio",
    "wof:placetype":"venue"
},
  "geometry": {"coordinates":[8.9466400146,46.3723182678],"type":"Point"}
}