{
  "type": "Feature",
  "properties": {
    "iso:country":"CH",
    "sg:address":"M\u00fchlauerstrasse",
    "sg:city":"Auw",
    "sg:orig_category":"Sportvereine Sch\u00fctzen",
    "sg:phone":"+41 56 668 10 73",
    "sg:postcode":"5644",
    "sg:province":"Aargau",
    "wof:name":"Feldsch\u00fctzengesellschaft Auw",
    "wof:placetype":"venue"
},
  "geometry": {"coordinates":[8.3688840866,47.2101516724],"type":"Point"}
}