{
  "type": "Feature",
  "properties": {
    "iso:country":"CH",
    "sg:address":"Kirchgasse 17",
    "sg:city":"Niederbipp",
    "sg:orig_category":"Reiseb\u00fcros U Reiseveranstalter",
    "sg:phone":"+41 79 341 10 60",
    "sg:postcode":"4704",
    "sg:province":"Bern",
    "wof:name":"Stoyns Ag",
    "wof:placetype":"venue"
},
  "geometry": {"coordinates":[7.6938390732,47.265335083],"type":"Point"}
}