{
  "type": "Feature",
  "properties": {
    "iso:country":"CH",
    "sg:address":"Opfikonerstrasse 32",
    "sg:city":"Wallisellen",
    "sg:orig_category":"Non-Classified Establishments",
    "sg:postcode":"8304",
    "sg:province":"Z\u00fcrich",
    "wof:name":"Wanner Jakob",
    "wof:placetype":"venue"
},
  "geometry": {"coordinates":[8.5861253738,47.4167938232],"type":"Point"}
}