{
  "type": "Feature",
  "properties": {
    "iso:country":"CH",
    "sg:address":"Postgasse 40 3011 Bern. Postfach",
    "sg:city":"Bern",
    "sg:orig_category":"Herstellung von industriellen Prozesssteuerungsanlagen",
    "sg:phone":"+41 31 312 47 85",
    "sg:postcode":"3005",
    "sg:province":"Bern",
    "wof:name":"Solarte Ing. B\u00fcro Stucki Photovoltaik Anlagen U. Elektronische Steuerungen; Planung",
    "wof:placetype":"venue"
},
  "geometry": {"coordinates":[7.4545621872,46.9490280151],"type":"Point"}
}