{
  "type": "Feature",
  "properties": {
    "addr:full":"Pelikanplatz 5 8001 Z\u00fcrich. Postfach 4739 Z\u00fcrich Z\u00fcrich 8022",
    "addr:housenumber":"5",
    "addr:postcode":"8001 zuerich. postfach 4739;8022",
    "addr:street":"Pelikanplatz",
    "iso:country":"CH",
    "sg:address":"Pelikanplatz 5 8001 Z\u00fcrich. Postfach 4739",
    "sg:city":"Z\u00fcrich",
    "sg:orig_category":"Allgemeiner Hochbau Bauschreinerei",
    "sg:phone":"+41 12189292",
    "sg:postcode":"8022",
    "sg:province":"Z\u00fcrich",
    "wof:name":"Locher Ag Z\u00fcrich Bauingenieure & Bauunternehmer",
    "wof:placetype":"venue"
},
  "geometry": {"coordinates":[8.53608,47.370922],"type":"Point"}
}