{
  "type": "Feature",
  "properties": {
    "iso:country":"CH",
    "sg:address":"Bahnhofstrasse 1",
    "sg:city":"Klosters",
    "sg:orig_category":"Massagestudios",
    "sg:phone":"+41 81 410 24 24",
    "sg:postcode":"7250",
    "sg:province":"Graubunden",
    "wof:name":"Maria Landolt Massagen",
    "wof:placetype":"venue"
},
  "geometry": {"coordinates":[9.8814077377,46.8691940308],"type":"Point"}
}