{
  "type": "Feature",
  "properties": {
    "iso:country":"CH",
    "sg:address":"Sonnmatt",
    "sg:city":"Bowil",
    "sg:orig_category":"Vermietung U Verpachtung von eigenen Immobilien",
    "sg:postcode":"3533",
    "sg:province":"Bern",
    "wof:name":"Ferd. Steck Immobilien Ag",
    "wof:placetype":"venue"
},
  "geometry": {"coordinates":[7.694881916,46.8934135437],"type":"Point"}
}