{
  "type": "Feature",
  "properties": {
    "iso:country":"CH",
    "sg:address":"Rue F.-marchand 18",
    "sg:city":"Montagne-sonvilier",
    "sg:classifiers":[
        {
            "category":"Travel",
            "subcategory":"Hotels & Motels",
            "type":"Entertainment"
        }
    ],
    "sg:postcode":"2615",
    "sg:province":"Bern",
    "sg:tags":[
        "hotels",
        "mit",
        "restaurant"
    ],
    "wof:name":"Iluminada Gmbh",
    "wof:placetype":"venue"
},
  "geometry": {"coordinates":[9.8248758316,46.7995834351],"type":"Point"}
}