{
  "type": "Feature",
  "properties": {
    "iso:country":"CH",
    "sg:address":"Gare Avenue De La 42 2800 Del\u00e9mont. Postfach",
    "sg:city":"Delsberg",
    "sg:orig_category":"Herstellung von Teppichen",
    "sg:phone":"+41 32 423 30 59",
    "sg:postcode":"2800",
    "sg:province":"Jura",
    "wof:name":"Banq Gilles Entrepr. De Carrelage",
    "wof:placetype":"venue"
},
  "geometry": {"coordinates":[7.3439698219,47.3653564453],"type":"Point"}
}