{
  "type": "Feature",
  "properties": {
    "iso:country":"CH",
    "sg:address":"Hauptstrasse 28",
    "sg:city":"H\u00f6lstein",
    "sg:orig_category":"Handel mit Automobilen",
    "sg:postcode":"4434",
    "sg:province":"Basel-Landschaft",
    "wof:name":"Hess R. & M. Automobile",
    "wof:placetype":"venue"
},
  "geometry": {"coordinates":[7.7693910599,47.4259719849],"type":"Point"}
}