{
  "type": "Feature",
  "properties": {
    "addr:full":"Kasinostrasse 15 Aarau Aargau 5000",
    "addr:housenumber":"15",
    "addr:postcode":"5000",
    "addr:street":"Kasinostrasse",
    "iso:country":"CH",
    "sg:address":"Kasinostrasse 15",
    "sg:city":"Aarau",
    "sg:orig_category":"Detailhandel mit Bekleidung Detailhandel mit Herrenbekleidung",
    "sg:phone":"+41 17363333",
    "sg:postcode":"5000",
    "sg:province":"Aargau",
    "wof:name":"Pkz Burger-kehl & Co Ag",
    "wof:placetype":"venue"
},
  "geometry": {"coordinates":[8.04673,47.392925],"type":"Point"}
}