{
  "type": "Feature",
  "properties": {
    "iso:country":"CH",
    "sg:address":"Giebeleichstrasse 48",
    "sg:city":"Opfikon",
    "sg:orig_category":"Vereine Damen Vereine Gesang",
    "sg:phone":"+41 76 376 75 80",
    "sg:postcode":"8152",
    "sg:province":"Z\u00fcrich",
    "wof:name":"Frauenchor",
    "wof:placetype":"venue"
},
  "geometry": {"coordinates":[8.5645227432,47.4283180237],"type":"Point"}
}