{
  "type": "Feature",
  "properties": {
    "iso:country":"CH",
    "sg:address":"Gimel",
    "sg:city":"Gimel",
    "sg:classifiers":[
        {
            "category":"Banks & Credit Unions",
            "subcategory":"Bank",
            "type":"Services"
        }
    ],
    "sg:phone":"+41 21 828 31 12",
    "sg:postcode":"1188",
    "sg:province":"Vaud",
    "wof:name":"Caisse De Credit Mutuel",
    "wof:placetype":"venue"
},
  "geometry": {"coordinates":[6.307616,46.50872],"type":"Point"}
}