{
  "type": "Feature",
  "properties": {
    "iso:country":"CH",
    "sg:address":"Grand-rue 161",
    "sg:city":"Tramelan",
    "sg:orig_category":"Fachdetailhandel mit pharmazeutischen Produkten",
    "sg:phone":"+41 32 487 42 48",
    "sg:postcode":"2720",
    "sg:province":"Bern",
    "wof:name":"Pharmacie Schneeberger.",
    "wof:placetype":"venue"
},
  "geometry": {"coordinates":[7.0986962318,47.2228507996],"type":"Point"}
}