{
  "type": "Feature",
  "properties": {
    "iso:country":"CH",
    "sg:address":"3923",
    "sg:city":"T\u00f6rbel",
    "sg:orig_category":"RESTAURANTS: TEA-ROOMS",
    "sg:postcode":"3923",
    "sg:province":"Valais",
    "wof:name":"Restaurant Moosalpe, Kalbermatten Amad\u00e9",
    "wof:placetype":"venue"
},
  "geometry": {"coordinates":[7.8499798775,46.2373695374],"type":"Point"}
}