{
  "type": "Feature",
  "properties": {
    "iso:country":"CH",
    "sg:address":"Haldenmattstr. 3",
    "sg:city":"Sursee",
    "sg:classifiers":[
        {
            "category":"Autos & Motor Vehicles",
            "subcategory":"Automobile Sales",
            "type":"Retail Goods"
        }
    ],
    "sg:phone":"+41 41 926 65 11",
    "sg:postcode":"6210",
    "sg:province":"Luzern",
    "sg:tags":[
        "equipment",
        "transport"
    ],
    "wof:name":"Intercycle Sa",
    "wof:placetype":"venue"
},
  "geometry": {"coordinates":[8.0978546143,47.1763153076],"type":"Point"}
}