{
  "type": "Feature",
  "properties": {
    "iso:country":"CH",
    "sg:address":"Arnold B\u00f6cklin-strasse 35 4051 Basel. Postfach 513",
    "sg:city":"Basel",
    "sg:orig_category":"Detailhandel mit Metallwaren, Anstrichmitteln, Glaswaren, Bau U Heimwerkerbedarf Sanit\u00e4rinstallation",
    "sg:phone":"+41 61 206 11 99",
    "sg:postcode":"4016",
    "sg:province":"Basel-Stadt",
    "wof:name":"Swiss Rain Ag",
    "wof:placetype":"venue"
},
  "geometry": {"coordinates":[7.5765771866,47.5512886047],"type":"Point"}
}