{
  "type": "Feature",
  "properties": {
    "iso:country":"CH",
    "sg:address":"Rosenweg 35",
    "sg:city":"Bern",
    "sg:orig_category":"Sonstige pers\u00f6nliche Dienstleistungen Unternehmensberatung",
    "sg:phone":"+41 31 371 33 63",
    "sg:postcode":"3007",
    "sg:province":"Bern",
    "wof:name":"Ks, Kaspar+steiner Gmbh",
    "wof:placetype":"venue"
},
  "geometry": {"coordinates":[7.4344711304,46.9359931946],"type":"Point"}
}