{
  "type": "Feature",
  "properties": {
    "iso:country":"CH",
    "sg:address":"Schibeweidstrasse 13",
    "sg:city":"B\u00fcnzen",
    "sg:orig_category":"Herstellung von Metallkonstruktionen Spezieller Tiefbau",
    "sg:phone":"+41 56 666 16 02",
    "sg:postcode":"5624",
    "sg:province":"Aargau",
    "wof:name":"Scoppa Montagen - Service Gmbh",
    "wof:placetype":"venue"
},
  "geometry": {"coordinates":[8.3284425735,47.3123397827],"type":"Point"}
}