{
  "type": "Feature",
  "properties": {
    "iso:country":"CH",
    "sg:address":"J\u00f6chlerweg 7",
    "sg:city":"Baar",
    "sg:orig_category":"Non-Classified Establishments",
    "sg:phone":"+41 41 760 18 05",
    "sg:postcode":"6340",
    "sg:province":"Zug",
    "wof:name":"Huber & Suhner Ag Energie-& Nachrichten\u00fcbertr.",
    "wof:placetype":"venue"
},
  "geometry": {"coordinates":[8.5252132416,47.2007102966],"type":"Point"}
}