{
  "type": "Feature",
  "properties": {
    "iso:country":"CH",
    "sg:city":"Spreitenbach",
    "sg:classifiers":[
        {
            "category":"Shopping",
            "subcategory":"Computers & Home Electronics",
            "type":"Retail Goods"
        }
    ],
    "sg:phone":"+41 4113822323",
    "sg:postcode":"8957",
    "sg:province":"Aargau",
    "sg:tags":[
        "chamber",
        "commerce"
    ],
    "wof:name":"Chamber Of Commerce Switzerland - Ukraine",
    "wof:placetype":"venue"
},
  "geometry": {"coordinates":[8.53955,47.37706],"type":"Point"}
}