{
  "type": "Feature",
  "properties": {
    "iso:country":"CH",
    "sg:address":"Hintere Blumenstrasse 1",
    "sg:city":"Rheineck",
    "sg:orig_category":"Detailhandel mit Sportartikeln",
    "sg:phone":"+41 71 888 55 22",
    "sg:postcode":"9424",
    "sg:province":"St. Gallen",
    "wof:name":"Elanautic Bernet",
    "wof:placetype":"venue"
},
  "geometry": {"coordinates":[9.5819282532,47.4677581787],"type":"Point"}
}