{
  "type": "Feature",
  "properties": {
    "iso:country":"CH",
    "sg:address":"In Der Specki 13 9494 Schaan. Postfach 147",
    "sg:city":"Schaan",
    "sg:classifiers":[
        {
            "category":"Manufacturing",
            "subcategory":"Metals",
            "type":"Manufacturing & Wholesale Goods"
        }
    ],
    "sg:phone":"+423 232 19 21",
    "sg:postcode":"9494",
    "sg:tags":[
        "u",
        "leichtmetallbau",
        "stahl"
    ],
    "wof:name":"A. Walser & E. Wohlwend Ag Metallbau",
    "wof:placetype":"venue"
},
  "geometry": {"coordinates":[9.5108890533,47.1694641113],"type":"Point"}
}