{
  "type": "Feature",
  "properties": {
    "iso:country":"CH",
    "sg:address":"Obere Fenchernstrasse 12 4552 Derendingen. Postfach",
    "sg:city":"Derendingen",
    "sg:orig_category":"Polizei",
    "sg:phone":"+41 32 681 53 11",
    "sg:postcode":"4552",
    "sg:province":"Solothurn",
    "wof:name":"Kantonaler Polizeiposten",
    "wof:placetype":"venue"
},
  "geometry": {"coordinates":[7.58893013,47.1994056702],"type":"Point"}
}