{
  "type": "Feature",
  "properties": {
    "iso:country":"CH",
    "sg:address":"Wyd\u00e4ckerring 73",
    "sg:city":"Z\u00fcrich",
    "sg:orig_category":"Softwareentwicklung U beratung",
    "sg:phone":"+41 61 715 73 00",
    "sg:postcode":"8047",
    "sg:province":"Z\u00fcrich",
    "wof:name":"Metso Endress + Hauser Technology Ag Automatisierungshard- U. Software; Forschung, Entwicklung, Konstruktion Usw",
    "wof:placetype":"venue"
},
  "geometry": {"coordinates":[7.6003937721,47.4883308411],"type":"Point"}
}