{
  "type": "Feature",
  "properties": {
    "iso:country":"CH",
    "sg:address":"Rautistrasse 71 8048 Z\u00fcrich. Postfach",
    "sg:city":"Z\u00fcrich",
    "sg:orig_category":"Autotransporte international Lagerh\u00e4user",
    "sg:phone":"+41 14052727",
    "sg:postcode":"8043",
    "sg:province":"Z\u00fcrich",
    "wof:name":"Schneider & Cie Ag Internationale Transporte",
    "wof:placetype":"venue"
},
  "geometry": {"coordinates":[8.486701,47.382496],"type":"Point"}
}