{
  "type": "Feature",
  "properties": {
    "iso:country":"CH",
    "sg:address":"Chemin Des Chentres 2",
    "sg:city":"Etoy",
    "sg:orig_category":"Herstellung von konfektionierten Textilwaren ohne Bekleidung",
    "sg:postcode":"1163",
    "sg:province":"Vaud",
    "wof:name":"Storesax S\u00e0rl",
    "wof:placetype":"venue"
},
  "geometry": {"coordinates":[6.4226708412,46.4889755249],"type":"Point"}
}