{
  "type": "Feature",
  "properties": {
    "iso:country":"CH",
    "sg:address":"K\u00e4sereistr. 4",
    "sg:city":"Tobel",
    "sg:orig_category":"Zimmerei, Dachdeckerei, Bauspenglerei U Abdichtung",
    "sg:phone":"+41 71 917 12 20",
    "sg:postcode":"9555",
    "sg:province":"Thurgau",
    "wof:name":"R\u00fctsche",
    "wof:placetype":"venue"
},
  "geometry": {"coordinates":[9.0331878662,47.5172271729],"type":"Point"}
}