{
  "type": "Feature",
  "properties": {
    "iso:country":"CH",
    "sg:address":"Oberdorfstrasse 3",
    "sg:city":"R\u00fcmlang",
    "sg:orig_category":"Herstellung von Metallkonstruktionen",
    "sg:phone":"+41 18170385",
    "sg:postcode":"8153",
    "sg:province":"Z\u00fcrich",
    "wof:name":"Thom O.",
    "wof:placetype":"venue"
},
  "geometry": {"coordinates":[8.5299873352,47.4524345398],"type":"Point"}
}