{
  "type": "Feature",
  "properties": {
    "iso:country":"CH",
    "sg:address":"Froschaugasse 15",
    "sg:city":"Z\u00fcrich",
    "sg:classifiers":[
        {
            "category":"Restaurant",
            "type":"Food & Drink"
        }
    ],
    "sg:phone":"+41 81 332 22 47",
    "sg:postcode":"8001",
    "sg:province":"Z\u00fcrich",
    "wof:name":"Restaurant Madrisa",
    "wof:placetype":"venue"
},
  "geometry": {"coordinates":[9.8064022064,46.9110946655],"type":"Point"}
}