{
  "type": "Feature",
  "properties": {
    "iso:country":"CH",
    "sg:address":"Bernstrasse 8",
    "sg:city":"B\u00fctzberg",
    "sg:orig_category":"Detailhandel mit Milcherzeugnissen U Eiern Verarbeitung von Milch",
    "sg:phone":"+41 62 963 11 70",
    "sg:postcode":"4922",
    "sg:province":"Bern",
    "wof:name":"Simon Jenzer K\u00e4serei",
    "wof:placetype":"venue"
},
  "geometry": {"coordinates":[7.7475328445,47.2163009644],"type":"Point"}
}