{
  "type": "Feature",
  "properties": {
    "iso:country":"CH",
    "sg:address":"Burgenzielrain 5",
    "sg:city":"Bern",
    "sg:orig_category":"Sonstige Aktivit\u00e4ten der nicht-\u00e4rztlichen Medizinalberufe",
    "sg:phone":"+41 71 222 51 48",
    "sg:postcode":"3006",
    "sg:province":"Bern",
    "wof:name":"Marianne Signer Atemtherapie",
    "wof:placetype":"venue"
},
  "geometry": {"coordinates":[9.3695478439,47.4252967834],"type":"Point"}
}