{
  "type": "Feature",
  "properties": {
    "addr:full":"Bodmerstr 14 Z\u00fcrich Z\u00fcrich 8002",
    "addr:housenumber":"14",
    "addr:postcode":"8002",
    "addr:street":"Bodmerstr",
    "iso:country":"CH",
    "sg:address":"Bodmerstr 14",
    "sg:city":"Z\u00fcrich",
    "sg:classifiers":[
        {
            "category":"Banks & Credit Unions",
            "subcategory":"Financial Services",
            "type":"Services"
        }
    ],
    "sg:phone":"+41 4112836633",
    "sg:postcode":"8002",
    "sg:province":"Z\u00fcrich",
    "sg:tags":[
        "banking",
        "finance",
        "insurance"
    ],
    "wof:name":"Lengen Finanz Ag",
    "wof:placetype":"venue"
},
  "geometry": {"coordinates":[8.532774,47.365398],"type":"Point"}
}