{
  "type": "Feature",
  "properties": {
    "iso:country":"CH",
    "sg:address":"Grabenstrasse 15",
    "sg:city":"Chur",
    "sg:orig_category":"Grosshandel mit sonstigen Maschinen U Ausr\u00fcstungen f\u00fcr Industrie, Handel U Schiffahrt",
    "sg:phone":"+41 81 252 48 41",
    "sg:postcode":"7000",
    "sg:province":"Graubunden",
    "wof:name":"Golbiness Ag",
    "wof:placetype":"venue"
},
  "geometry": {"coordinates":[9.5321493149,46.8507995605],"type":"Point"}
}