{
  "type": "Feature",
  "properties": {
    "iso:country":"CH",
    "sg:address":"Aussermatt 24h",
    "sg:city":"R\u00fceggisberg",
    "sg:orig_category":"Herstellung von K\u00e4se",
    "sg:phone":"+41 41 670 37 37",
    "sg:postcode":"3088",
    "sg:province":"Bern",
    "wof:name":"Guido & Monika Wolfisberg Dorfk\u00e4serei",
    "wof:placetype":"venue"
},
  "geometry": {"coordinates":[8.272310257,46.941608429],"type":"Point"}
}