{
  "type": "Feature",
  "properties": {
    "iso:country":"CH",
    "sg:address":"Niederb\u00fcrerstrasse 13",
    "sg:city":"Bischofszell",
    "sg:orig_category":"Gewinnung von Kies U Sand G\u00fcterbef\u00f6rderung im Strassenverkehr",
    "sg:phone":"+41 71 422 19 59",
    "sg:postcode":"9220",
    "sg:province":"Thurgau",
    "wof:name":"Meyer Kieswerk Ag",
    "wof:placetype":"venue"
},
  "geometry": {"coordinates":[9.2368278503,47.4900550842],"type":"Point"}
}