{
  "type": "Feature",
  "properties": {
    "iso:country":"CH",
    "sg:address":"Bahnhofstrasse 14",
    "sg:city":"Lyss",
    "sg:orig_category":"Detailhandel mit Brillen U anderen Sehhilfen Fachdetailhandel in Verkaufsr\u00e4umen",
    "sg:phone":"+41 32 385 33 13",
    "sg:postcode":"3250",
    "sg:province":"Bern",
    "wof:name":"Mc Optik Lyss Gmbh",
    "wof:placetype":"venue"
},
  "geometry": {"coordinates":[7.305968,47.076874],"type":"Point"}
}