{
  "type": "Feature",
  "properties": {
    "iso:country":"CH",
    "sg:address":"Hauptstrasse",
    "sg:city":"Mettschlatt",
    "sg:classifiers":[
        {
            "category":"Restaurant",
            "type":"Food & Drink"
        }
    ],
    "sg:phone":"+41 52 657 13 07",
    "sg:postcode":"8252",
    "sg:province":"Thurgau",
    "wof:name":"Gasthaus Baumgarten",
    "wof:placetype":"venue"
},
  "geometry": {"coordinates":[8.6988162994,47.6564865112],"type":"Point"}
}