{
  "type": "Feature",
  "properties": {
    "iso:country":"CH",
    "sg:address":"V\u00e9lodrome Rue Du 8 1205 Gen\u00e8ve. Postfach",
    "sg:city":"Gen\u00e8ve",
    "sg:orig_category":"Detailhandel mit Metallwaren, Anstrichmitteln, Glaswaren, Bau U Heimwerkerbedarf",
    "sg:postcode":"1205",
    "sg:province":"Gen\u00e8ve",
    "wof:name":"Romagnoli, Micro-technique",
    "wof:placetype":"venue"
},
  "geometry": {"coordinates":[6.1306672096,46.1999511719],"type":"Point"}
}