{
  "type": "Feature",
  "properties": {
    "iso:country":"CH",
    "sg:address":"Chlus 6h 7241 Conters. Postfach",
    "sg:city":"Landquart",
    "sg:orig_category":"Krankenkassen Zentralverwaltungen Sonstiges Versicherungsgewerbe",
    "sg:phone":"+41 81 307 31 61",
    "sg:postcode":"7302",
    "sg:province":"Graubunden",
    "wof:name":"\u00d6kk Kranken Und Unfallversicherungen Ag",
    "wof:placetype":"venue"
},
  "geometry": {"coordinates":[9.7985095978,46.9016914368],"type":"Point"}
}