{
  "type": "Feature",
  "properties": {
    "iso:country":"CH",
    "sg:address":"Staadstrasse 80",
    "sg:city":"Grenchen",
    "sg:orig_category":"Grosshandel mit Erzen U Metallen Grosshandel mit Nahrungsmitteln, Getr\u00e4nken U Tabakwaren",
    "sg:phone":"+41 21 944 02 22",
    "sg:postcode":"2540",
    "sg:province":"Solothurn",
    "wof:name":"Alton Sa",
    "wof:placetype":"venue"
},
  "geometry": {"coordinates":[6.8591117859,46.4586791992],"type":"Point"}
}