{
  "type": "Feature",
  "properties": {
    "iso:country":"CH",
    "sg:address":"Claraplatz 2 4058 Basel. Postfach",
    "sg:city":"Basel",
    "sg:orig_category":"Arztpraxen",
    "sg:phone":"+41 61 692 90 09",
    "sg:postcode":"4005",
    "sg:province":"Basel-Stadt",
    "wof:name":"Dr.med.pietro Gallacchi Spezialarzt Fmh",
    "wof:placetype":"venue"
},
  "geometry": {"coordinates":[7.594885,47.561951],"type":"Point"}
}