{
  "type": "Feature",
  "properties": {
    "iso:country":"CH",
    "sg:address":"Claragraben 55 4051 Basel. Postfach",
    "sg:city":"Basel",
    "sg:orig_category":"Personenbef\u00f6rderung im Nahverkehr",
    "sg:phone":"+41 26 652 24 18",
    "sg:postcode":"4005",
    "sg:province":"Basel-Stadt",
    "wof:name":"Chemins De Fer Fribourgeois Gfm",
    "wof:placetype":"venue"
},
  "geometry": {"coordinates":[6.9089260101,46.688785553],"type":"Point"}
}