{
  "type": "Feature",
  "properties": {
    "iso:country":"CH",
    "sg:address":"Tschuppen 167f",
    "sg:city":"Krattigen",
    "sg:orig_category":"Herstellung von sonstigen elektrischen Ausr\u00fcstungen",
    "sg:phone":"+41 33 655 02 31",
    "sg:postcode":"3704",
    "sg:province":"Bern",
    "wof:name":"Compart Engineering Ag",
    "wof:placetype":"venue"
},
  "geometry": {"coordinates":[7.7323050499,46.6604614258],"type":"Point"}
}