{
  "type": "Feature",
  "properties": {
    "iso:country":"CH",
    "sg:address":"Kempttalstrasse 61",
    "sg:city":"Fehraltorf",
    "sg:classifiers":[
        {
            "category":"Restaurant",
            "type":"Food & Drink"
        }
    ],
    "sg:phone":"+41 19541737",
    "sg:postcode":"8320",
    "sg:province":"Z\u00fcrich",
    "wof:name":"Restaurant Scharfeck",
    "wof:placetype":"venue"
},
  "geometry": {"coordinates":[8.7521257401,47.3880958557],"type":"Point"}
}