{
  "type": "Feature",
  "properties": {
    "iso:country":"CH",
    "sg:address":"Fabrikstrasse 6",
    "sg:city":"Biberist",
    "sg:orig_category":"Sportvereine Ballsport Tennis",
    "sg:phone":"+41 32 671 32 11",
    "sg:postcode":"4562",
    "sg:province":"Solothurn",
    "wof:name":"Tc Biber",
    "wof:placetype":"venue"
},
  "geometry": {"coordinates":[7.5678830147,47.1814422607],"type":"Point"}
}