{
  "type": "Feature",
  "properties": {
    "iso:country":"CH",
    "sg:address":"Chemin Du Vaugueny 6",
    "sg:city":"Epalinges",
    "sg:orig_category":"Mechanik Mechanische Werkst\u00e4tten",
    "sg:phone":"+41 21 652 58 63",
    "sg:postcode":"1066",
    "sg:province":"Vaud",
    "wof:name":"Jonathan Geiser Atelier M\u00e9canique",
    "wof:placetype":"venue"
},
  "geometry": {"coordinates":[6.6589097977,46.5461997986],"type":"Point"}
}