{
  "type": "Feature",
  "properties": {
    "addr:full":"M\u00e4dersforst 108 Rossh\u00e4usern Bern 3204",
    "addr:housenumber":"108",
    "addr:postcode":"3204",
    "addr:street":"Rosshaeusern Bern",
    "iso:country":"CH",
    "sg:address":"M\u00e4dersforst 108",
    "sg:city":"Rossh\u00e4usern",
    "sg:orig_category":"Bauschreinerei Innenausbau",
    "sg:phone":"+41 31 751 21 78",
    "sg:postcode":"3204",
    "sg:province":"Bern",
    "wof:name":"Wirth Innenausbau Ag",
    "wof:placetype":"venue"
},
  "geometry": {"coordinates":[7.268981,46.919567],"type":"Point"}
}