{
  "type": "Feature",
  "properties": {
    "iso:country":"CH",
    "sg:address":"Rue Du Xxxi-d\u00e9cembre 60 1200 Gen\u00e8ve. Postfach",
    "sg:city":"Gen\u00e8ve",
    "sg:classifiers":[
        {
            "category":"Communications",
            "subcategory":"Radio Station",
            "type":"Services"
        }
    ],
    "sg:phone":"+41 22 700 01 16",
    "sg:postcode":"1207",
    "sg:province":"Gen\u00e8ve",
    "sg:tags":[
        "fernsehanstalten",
        "u"
    ],
    "wof:name":"Vivid Video, Patricia Vargas, German Vargas Et Christophe Polese",
    "wof:placetype":"venue"
},
  "geometry": {"coordinates":[6.1616091728,46.2010955811],"type":"Point"}
}