{
  "type": "Feature",
  "properties": {
    "iso:country":"CH",
    "sg:address":"Manessestrasse 72",
    "sg:city":"Z\u00fcrich",
    "sg:orig_category":"Werbeagenturen",
    "sg:phone":"+41 14510229",
    "sg:postcode":"8003",
    "sg:province":"Z\u00fcrich",
    "wof:name":"Texterei Alfred Preisig",
    "wof:placetype":"venue"
},
  "geometry": {"coordinates":[8.5219449997,47.3661270142],"type":"Point"}
}