{
  "type": "Feature",
  "properties": {
    "iso:country":"CH",
    "sg:address":"Ulmenstrasse 3 4127 Birsfelden. Postfach 509",
    "sg:city":"Birsfelden",
    "sg:orig_category":"Strassenbau",
    "sg:phone":"+41 61 313 05 55",
    "sg:postcode":"4127",
    "sg:province":"Basel-Landschaft",
    "wof:name":"Armin H. L\u00fcthi Spezial Tiefbau",
    "wof:placetype":"venue"
},
  "geometry": {"coordinates":[7.628841877,47.5488243103],"type":"Point"}
}