{
  "type": "Feature",
  "properties": {
    "iso:country":"CH",
    "sg:address":"Titlisstrasse 29",
    "sg:city":"Emmenbr\u00fccke",
    "sg:classifiers":[
        {
            "category":"Manufacturing",
            "subcategory":"Chemicals & Compounds",
            "type":"Manufacturing & Wholesale Goods"
        }
    ],
    "sg:phone":"+41 41 260 58 75",
    "sg:postcode":"6020",
    "sg:province":"Luzern",
    "sg:tags":[
        "biochemicals"
    ],
    "wof:name":"Bio-science Products Ag",
    "wof:placetype":"venue"
},
  "geometry": {"coordinates":[8.281716,47.074795],"type":"Point"}
}