{
  "type": "Feature",
  "properties": {
    "iso:country":"CH",
    "sg:address":"Gottardo Via San 146",
    "sg:city":"Savosa",
    "sg:orig_category":"Detailhandel mit Waren verschiedener Art, Hauptrichtung Nahrungsmittel",
    "sg:phone":"+41 21 802 10 57",
    "sg:postcode":"6942",
    "sg:province":"Ticino",
    "wof:name":"Altevogt C. Sa",
    "wof:placetype":"venue"
},
  "geometry": {"coordinates":[6.4661898613,46.508731842],"type":"Point"}
}