{
  "type": "Feature",
  "properties": {
    "iso:country":"CH",
    "sg:address":"Kurfirstensteig 4 8002 Z\u00fcrich. Postfach",
    "sg:city":"Z\u00fcrich",
    "sg:orig_category":"Herstellung von sonstigen elektrischen Ausr\u00fcstungen",
    "sg:postcode":"8001",
    "sg:province":"Z\u00fcrich",
    "wof:name":"H\u00e4usler-elektro-apparatebau Ag, Richard Elektroapparate Usw; Herst., Montage",
    "wof:placetype":"venue"
},
  "geometry": {"coordinates":[8.5276861191,47.3570861816],"type":"Point"}
}