{
  "type": "Feature",
  "properties": {
    "iso:country":"CH",
    "sg:address":"Campingstrasse 9",
    "sg:city":"B\u00f6nigen",
    "sg:orig_category":"Politische Vereinigungen",
    "sg:phone":"+41 79 656 69 10",
    "sg:postcode":"3806",
    "sg:province":"Bern",
    "wof:name":"Fbp Freie B\u00fcrger-partei",
    "wof:placetype":"venue"
},
  "geometry": {"coordinates":[7.8931488991,46.6904563904],"type":"Point"}
}