{
  "type": "Feature",
  "properties": {
    "iso:country":"CH",
    "sg:address":"Hittnauerstrasse",
    "sg:city":"Saland",
    "sg:classifiers":[
        {
            "category":"Manufacturing",
            "subcategory":"Wood Products",
            "type":"Manufacturing & Wholesale Goods"
        }
    ],
    "sg:phone":"+41 52 386 21 21",
    "sg:postcode":"8493",
    "sg:province":"Z\u00fcrich",
    "sg:tags":[
        "made",
        "balcony"
    ],
    "wof:name":"Wittwer Ag",
    "wof:placetype":"venue"
},
  "geometry": {"coordinates":[8.853045,47.390804],"type":"Point"}
}