{
  "type": "Feature",
  "properties": {
    "iso:country":"CH",
    "sg:address":"Conti Vicolo Dei 4 6932 Breganzona. Postfach",
    "sg:city":"Breganzona",
    "sg:orig_category":"RESTAURANTS: TEA-ROOMS",
    "sg:postcode":"6932",
    "sg:province":"Ticino",
    "wof:name":"Rocchi Sa",
    "wof:placetype":"venue"
},
  "geometry": {"coordinates":[8.9248876572,46.0064048767],"type":"Point"}
}