{
  "type": "Feature",
  "properties": {
    "iso:country":"CH",
    "sg:address":"Furlenstrasse 88",
    "sg:city":"Lausen",
    "sg:orig_category":"G\u00fcterbef\u00f6rderung im Strassenverkehr",
    "sg:phone":"+41 61 921 64 27",
    "sg:postcode":"4415",
    "sg:province":"Basel-Landschaft",
    "wof:name":"Daniel Pitsch, Transporte",
    "wof:placetype":"venue"
},
  "geometry": {"coordinates":[7.758122921,47.4642219543],"type":"Point"}
}