{
  "type": "Feature",
  "properties": {
    "iso:country":"CH",
    "sg:address":"Unterm\u00fcli 6",
    "sg:city":"Zug",
    "sg:orig_category":"Wirtschaftspr\u00fcfung, Steuerberatung U Treuhand",
    "sg:postcode":"6300",
    "sg:province":"Zug",
    "wof:name":"Jzb Buchhaltung Und Administration Zurm\u00fchle J.",
    "wof:placetype":"venue"
},
  "geometry": {"coordinates":[7.9829950333,47.3561477661],"type":"Point"}
}