{
  "type": "Feature",
  "properties": {
    "iso:country":"CH",
    "sg:address":"Buzibachstrasse 15 6023 Rothenburg. Postfach",
    "sg:city":"Rothenburg",
    "sg:orig_category":"Grosshandel mit Obst U Gem\u00fcse",
    "sg:phone":"+41 61 337 80 82",
    "sg:postcode":"6023",
    "sg:province":"Luzern",
    "wof:name":"M\u00fcller & Dietrich Fruchthof Ag",
    "wof:placetype":"venue"
},
  "geometry": {"coordinates":[7.6076350212,47.5314674377],"type":"Point"}
}