{
  "type": "Feature",
  "properties": {
    "iso:country":"CH",
    "sg:address":"Rue Mercerie 12",
    "sg:city":"Lausanne",
    "sg:orig_category":"Betrieb von Sportanlagen",
    "sg:phone":"+41 21 310 47 70",
    "sg:postcode":"1003",
    "sg:province":"Vaud",
    "wof:name":"Holmes Place Sports & Health Club",
    "wof:placetype":"venue"
},
  "geometry": {"coordinates":[6.633938,46.521633],"type":"Point"}
}