{
  "type": "Feature",
  "properties": {
    "iso:country":"CH",
    "sg:address":"Ebenaustrasse 10 6048 Horw. Postfach 3255",
    "sg:city":"Luzern",
    "sg:orig_category":"Grosshandel mit keramischen Erzeugnissen,Glaswaren U Tapeten Herstellung von keramischen Haushaltswa",
    "sg:phone":"+41 41 340 31 77",
    "sg:postcode":"6005",
    "sg:province":"Luzern",
    "wof:name":"Hurni Ferdinand, Inh. Conrad Schwaninger",
    "wof:placetype":"venue"
},
  "geometry": {"coordinates":[8.3079395294,47.0138587952],"type":"Point"}
}