{
  "type": "Feature",
  "properties": {
    "iso:country":"CH",
    "sg:address":"Hauptstrasse 27",
    "sg:city":"Einsiedeln",
    "sg:orig_category":"Detailhandel mit Fleisch U Fleischwaren",
    "sg:phone":"+41 55 422 11 15",
    "sg:postcode":"8840",
    "sg:province":"Schwyz",
    "wof:name":"Metzgerei Schnidrig Gmbh",
    "wof:placetype":"venue"
},
  "geometry": {"coordinates":[8.7461223602,47.1274452209],"type":"Point"}
}