{
  "type": "Feature",
  "properties": {
    "addr:full":"Kantonsstrasse 68b Horw Luzern 6048",
    "addr:housenumber":"68b",
    "addr:postcode":"6048",
    "addr:street":"Kantonsstrasse",
    "iso:country":"CH",
    "sg:address":"Kantonsstrasse 68b",
    "sg:city":"Horw",
    "sg:orig_category":"Allgemeiner Hoch U Tiefbau",
    "sg:phone":"+41 41 340 07 07",
    "sg:postcode":"6048",
    "sg:province":"Luzern",
    "wof:name":"Staub Louis Ag",
    "wof:placetype":"venue"
},
  "geometry": {"coordinates":[8.310532,47.02108],"type":"Point"}
}