{
  "type": "Feature",
  "properties": {
    "iso:country":"CH",
    "sg:address":"Arbachstrasse 4",
    "sg:city":"Baar",
    "sg:orig_category":"Finanzierungsinstitutionen Institutionen f\u00fcr Finanzierungsleasing",
    "sg:phone":"+41 41 761 20 10",
    "sg:postcode":"6340",
    "sg:province":"Zug",
    "wof:name":"Joshua Finanz & Leasing Ag",
    "wof:placetype":"venue"
},
  "geometry": {"coordinates":[8.5326147079,47.1820068359],"type":"Point"}
}