{
  "type": "Feature",
  "properties": {
    "iso:country":"CH",
    "sg:address":"Wasserwerkstrasse 11 8006 Z\u00fcrich. Postfach",
    "sg:city":"Z\u00fcrich",
    "sg:orig_category":"Handelsvermittlung von Maschinen, technischem Bedarf, Wasser U Luftfahrzeugen",
    "sg:postcode":"8001",
    "sg:province":"Z\u00fcrich",
    "wof:name":"Oukhtomsky, Dr. Jur Ivan. Industrievertretungen. Vertrieb Von Metallurgischen Erzeugnissen Im In Und Ausland",
    "wof:placetype":"venue"
},
  "geometry": {"coordinates":[8.5405416489,47.3825912476],"type":"Point"}
}