{
  "type": "Feature",
  "properties": {
    "addr:full":"Durisolstrasse 1b Villmergen Aargau 5612",
    "addr:housenumber":"1b",
    "addr:postcode":"5612",
    "addr:street":"Durisolstrasse",
    "iso:country":"CH",
    "sg:address":"Durisolstrasse 1b",
    "sg:city":"Villmergen",
    "sg:orig_category":"Architektur U Ingenieurb\u00fcros Grosshandel mit Eisenwaren sowie Installationsbedarf f\u00fcr Gas, Wasser U ",
    "sg:phone":"+41 56 622 49 22",
    "sg:postcode":"5612",
    "sg:province":"Aargau",
    "wof:name":"Torex Handels Ag",
    "wof:placetype":"venue"
},
  "geometry": {"coordinates":[8.250877,47.354221],"type":"Point"}
}