{
  "type": "Feature",
  "properties": {
    "iso:country":"CH",
    "sg:address":"Murgstrasse 1",
    "sg:city":"Fischingen",
    "sg:orig_category":"Detailhandel mit Uhren U Schmuck Herstellung von Schmuck, Gold U Silberschmiedwaren",
    "sg:phone":"+41 71 977 18 55",
    "sg:postcode":"8376",
    "sg:province":"Thurgau",
    "wof:name":"B\u00fcchi Annette",
    "wof:placetype":"venue"
},
  "geometry": {"coordinates":[8.9678144455,47.4107437134],"type":"Point"}
}