{
  "type": "Feature",
  "properties": {
    "iso:country":"CH",
    "sg:address":"Gersauerstrasse 78 6440 Brunnen. Postfach 127",
    "sg:city":"Brunnen",
    "sg:orig_category":"Zahnkliniken",
    "sg:phone":"+41 87802310",
    "sg:postcode":"6440",
    "sg:province":"Schwyz",
    "wof:name":"Dentesana",
    "wof:placetype":"venue"
},
  "geometry": {"coordinates":[8.5954198837,46.9993286133],"type":"Point"}
}