{
  "type": "Feature",
  "properties": {
    "iso:country":"CH",
    "sg:address":"Tannenstrasse 57 L",
    "sg:city":"Embrach",
    "sg:orig_category":"Non-Classified Establishments",
    "sg:postcode":"8424",
    "sg:province":"Z\u00fcrich",
    "wof:name":"Unistore, C. Truchet",
    "wof:placetype":"venue"
},
  "geometry": {"coordinates":[8.5935716629,47.506690979],"type":"Point"}
}