{
  "type": "Feature",
  "properties": {
    "iso:country":"CH",
    "sg:address":"Alkerenweg 23",
    "sg:city":"Worben",
    "sg:orig_category":"Hoch U Tiefbau",
    "sg:phone":"+41 41 790 51 14",
    "sg:postcode":"3252",
    "sg:province":"Bern",
    "wof:name":"Edi Haas Baugesch\u00e4ft",
    "wof:placetype":"venue"
},
  "geometry": {"coordinates":[8.4382047653,47.1558494568],"type":"Point"}
}