{
  "type": "Feature",
  "properties": {
    "iso:country":"CH",
    "sg:address":"Reinacherstr. 129",
    "sg:city":"Basel",
    "sg:classifiers":[
        {
            "category":"Shopping",
            "subcategory":"Crafts & Fabrics",
            "type":"Retail Goods"
        }
    ],
    "sg:phone":"+41 55 440 35 22",
    "sg:postcode":"4053",
    "sg:province":"Basel-Stadt",
    "sg:tags":[
        "rubber",
        "textile",
        "linen",
        "clothing",
        "plastic"
    ],
    "wof:name":"Balz Vogt Ag",
    "wof:placetype":"venue"
},
  "geometry": {"coordinates":[8.8978376389,47.1882667542],"type":"Point"}
}