{
  "type": "Feature",
  "properties": {
    "iso:country":"CH",
    "sg:address":"Chemin De Beaupr\u00e9 55",
    "sg:city":"Gy",
    "sg:orig_category":"Abbruch U Sprenggewerbe, Erdbewegungsarbeiten Erdbewegungsarbeiten",
    "sg:phone":"+41 22 759 10 00",
    "sg:postcode":"1251",
    "sg:province":"Gen\u00e8ve",
    "wof:name":"Aymon Burgdorfer Terrassement",
    "wof:placetype":"venue"
},
  "geometry": {"coordinates":[6.253242,46.258144],"type":"Point"}
}