{
  "type": "Feature",
  "properties": {
    "iso:country":"CH",
    "sg:address":"Seilerstrasse 1",
    "sg:city":"Arbon",
    "sg:orig_category":"Maler U Glasergewerbe Malerei",
    "sg:phone":"+41 71 446 32 30",
    "sg:postcode":"9320",
    "sg:province":"Thurgau",
    "wof:name":"Ernst Schlappritzi Atelier 15",
    "wof:placetype":"venue"
},
  "geometry": {"coordinates":[9.4281721115,47.5133666992],"type":"Point"}
}