{
  "type": "Feature",
  "properties": {
    "iso:country":"CH",
    "sg:address":"Kreuzgasse 3454 Sumiswald. Postfach",
    "sg:city":"Gr\u00fcnen",
    "sg:orig_category":"Architektur U Ingenieurb\u00fcros",
    "sg:phone":"+41 34 432 32 32",
    "sg:postcode":"3455",
    "sg:province":"Bern",
    "wof:name":"Kramer, Haller Und Partner Architekten Und Planer",
    "wof:placetype":"venue"
},
  "geometry": {"coordinates":[7.746918,47.028164],"type":"Point"}
}