{
  "type": "Feature",
  "properties": {
    "iso:country":"CH",
    "sg:address":"Unter Altstadt 12",
    "sg:city":"Zug",
    "sg:orig_category":"Unclassifiable Establishments",
    "sg:postcode":"6300",
    "sg:province":"Zug",
    "wof:name":"Jian Cheng Hu, Golden Dragon China Restaurant",
    "wof:placetype":"venue"
},
  "geometry": {"coordinates":[8.514465332,47.1659507751],"type":"Point"}
}