{
  "type": "Feature",
  "properties": {
    "iso:country":"CH",
    "sg:address":"Seeackerstrasse 21",
    "sg:city":"Horn",
    "sg:orig_category":"Non-Classified Establishments",
    "sg:postcode":"9326",
    "sg:province":"Thurgau",
    "wof:name":"Cfs Biotech-lab-supplies Gmbh",
    "wof:placetype":"venue"
},
  "geometry": {"coordinates":[9.456445694,47.4962158203],"type":"Point"}
}