{
  "type": "Feature",
  "properties": {
    "iso:country":"CH",
    "sg:address":"Landes Chemin Des 9 2503 Biel/bienne. Postfach",
    "sg:city":"Biel/bienne",
    "sg:orig_category":"Erschliessung von Grundst\u00fccken",
    "sg:postcode":"2503",
    "sg:province":"Bern",
    "wof:name":"Soci\u00e9t\u00e9 Coop\u00e9rative De Construction Mon Home",
    "wof:placetype":"venue"
},
  "geometry": {"coordinates":[7.2472572327,47.1408882141],"type":"Point"}
}