{
  "type": "Feature",
  "properties": {
    "addr:full":"L\u00e4nggasse 33 Courgevaux Fribourg 1796",
    "addr:housenumber":"33",
    "addr:postcode":"1796",
    "addr:street":"Laenggasse",
    "iso:country":"CH",
    "sg:address":"L\u00e4nggasse 33",
    "sg:city":"Courgevaux",
    "sg:orig_category":"Autogaragen Autospenglereien",
    "sg:phone":"+41 79 634 40 04",
    "sg:postcode":"1796",
    "sg:province":"Fribourg",
    "wof:name":"Hermann Gerger Garage Carrosserie",
    "wof:placetype":"venue"
},
  "geometry": {"coordinates":[7.107539,46.918201],"type":"Point"}
}