{
  "type": "Feature",
  "properties": {
    "iso:country":"CH",
    "sg:address":"Altgasse 80 E",
    "sg:city":"Baar",
    "sg:orig_category":"Herstellung von Mess U Kontrollinstrumenten U vorrichtungen",
    "sg:postcode":"6340",
    "sg:province":"Zug",
    "wof:name":"Obrolabor Ag",
    "wof:placetype":"venue"
},
  "geometry": {"coordinates":[8.5262966156,47.1947250366],"type":"Point"}
}