{
  "type": "Feature",
  "properties": {
    "iso:country":"CH",
    "sg:address":"B\u00e9thusy Avenue De 70",
    "sg:city":"Lausanne",
    "sg:orig_category":"Softwareentwicklung U beratung",
    "sg:phone":"+41 17130585",
    "sg:postcode":"1012",
    "sg:province":"Vaud",
    "wof:name":"Gsd Gaschen Schmid Data Gmbh",
    "wof:placetype":"venue"
},
  "geometry": {"coordinates":[8.5402450562,47.285484314],"type":"Point"}
}