{
  "type": "Feature",
  "properties": {
    "iso:country":"CH",
    "sg:address":"Langgartenweg 2",
    "sg:city":"Kreuzlingen",
    "sg:orig_category":"Sportvereine Turnen Vereine Damen",
    "sg:phone":"+41 71 672 35 18",
    "sg:postcode":"8280",
    "sg:province":"Thurgau",
    "wof:name":"Frauenturngruppe",
    "wof:placetype":"venue"
},
  "geometry": {"coordinates":[9.1703958511,47.643371582],"type":"Point"}
}