{
  "type": "Feature",
  "properties": {
    "iso:country":"CH",
    "sg:address":"3925 Gr\u00e4chen. Postfach 33",
    "sg:city":"Gr\u00e4chen",
    "sg:orig_category":"Campingpl\u00e4tze",
    "sg:phone":"+41 55 284 14 57",
    "sg:postcode":"3925",
    "sg:province":"Valais",
    "wof:name":"Camping H\u00fcttenberg Ag",
    "wof:placetype":"venue"
},
  "geometry": {"coordinates":[9.01256,47.27047],"type":"Point"}
}