{
  "type": "Feature",
  "properties": {
    "iso:country":"CH",
    "sg:address":"Zentralstrasse 6",
    "sg:city":"Boswil",
    "sg:orig_category":"Instandhaltung U Reparatur von Automobilen Tankstellen",
    "sg:phone":"+41 56 666 12 41",
    "sg:postcode":"5623",
    "sg:province":"Aargau",
    "wof:name":"Garage Jean Keusch Ag",
    "wof:placetype":"venue"
},
  "geometry": {"coordinates":[8.3118438721,47.3031654358],"type":"Point"}
}