{
  "type": "Feature",
  "properties": {
    "addr:full":"Chemin Du Vieux-v\u00e9senaz 41 V\u00e9senaz Gen\u00e8ve 1222",
    "addr:housenumber":"41",
    "addr:postcode":"1222",
    "addr:street":"Chemin Du Vieux-Ve\u0301Senaz",
    "iso:country":"CH",
    "sg:address":"Chemin Du Vieux-v\u00e9senaz 41",
    "sg:city":"V\u00e9senaz",
    "sg:orig_category":"Arztpraxen",
    "sg:phone":"+41 22 752 46 51",
    "sg:postcode":"1222",
    "sg:province":"Gen\u00e8ve",
    "wof:name":"Dr M\u00e9d. Martine Blanc M\u00e9decin G\u00e9n\u00e9raliste",
    "wof:placetype":"venue"
},
  "geometry": {"coordinates":[6.197967,46.239521],"type":"Point"}
}