{
  "type": "Feature",
  "properties": {
    "iso:country":"CH",
    "sg:address":"Ruffinistrasse 5",
    "sg:city":"Grenchen",
    "sg:orig_category":"Kinderkrippen U horte",
    "sg:phone":"+41 32 652 64 91",
    "sg:postcode":"2540",
    "sg:province":"Solothurn",
    "wof:name":"Kinderkrippe Der Stadt Grenchen",
    "wof:placetype":"venue"
},
  "geometry": {"coordinates":[7.3829779625,47.1867752075],"type":"Point"}
}