{
  "type": "Feature",
  "properties": {
    "addr:full":"Chemin Des Italies 13 Vernier Gen\u00e8ve 1214",
    "addr:housenumber":"13",
    "addr:postcode":"1214",
    "addr:street":"Chemin Des Italies",
    "iso:country":"CH",
    "sg:address":"Chemin Des Italies 13",
    "sg:city":"Vernier",
    "sg:classifiers":[
        {
            "category":"Manufacturing",
            "subcategory":"Printing",
            "type":"Manufacturing & Wholesale Goods"
        }
    ],
    "sg:phone":"+41 22 719 13 13",
    "sg:postcode":"1214",
    "sg:province":"Gen\u00e8ve",
    "sg:tags":[
        "house",
        "book"
    ],
    "wof:name":"Atar Roto Presse Sa",
    "wof:placetype":"venue"
},
  "geometry": {"coordinates":[6.080475,46.212345],"type":"Point"}
}