{
  "type": "Feature",
  "properties": {
    "iso:country":"CH",
    "sg:address":"Limmatstrasse 20",
    "sg:city":"Neuenhof",
    "sg:orig_category":"Mechanische Werkst\u00e4tten Pulvermetallurgie Schmieden, Pressen, Stanzen U Profilwalzen von Metallen",
    "sg:phone":"+41 32 653 19 87",
    "sg:postcode":"5432",
    "sg:province":"Aargau",
    "wof:name":"Gogniat Roger Ag",
    "wof:placetype":"venue"
},
  "geometry": {"coordinates":[7.3897662163,47.1987380981],"type":"Point"}
}