{
  "type": "Feature",
  "properties": {
    "iso:country":"CH",
    "sg:address":"Kirchgasse 2",
    "sg:city":"Ettingen",
    "sg:orig_category":"RESTAURANTS: TEA-ROOMS",
    "sg:phone":"+41 61 721 10 17",
    "sg:postcode":"4107",
    "sg:province":"Basel-Landschaft",
    "wof:name":"Th\u00fcring-m\u00f6schlin Romy",
    "wof:placetype":"venue"
},
  "geometry": {"coordinates":[7.5436768532,47.4802360535],"type":"Point"}
}