{
  "type": "Feature",
  "properties": {
    "iso:country":"CH",
    "sg:address":"Seestrasse 66",
    "sg:city":"Horn",
    "sg:classifiers":[
        {
            "category":"Restaurant",
            "type":"Food & Drink"
        }
    ],
    "sg:phone":"+41 71 841 21 06",
    "sg:postcode":"9326",
    "sg:province":"Thurgau",
    "wof:name":"Restaurant Traube",
    "wof:placetype":"venue"
},
  "geometry": {"coordinates":[9.4638090134,47.4957885742],"type":"Point"}
}