{
  "type": "Feature",
  "properties": {
    "iso:country":"CH",
    "sg:address":"Hafnerstrasse 60 8005 Z\u00fcrich. Postfach",
    "sg:city":"Z\u00fcrich",
    "sg:classifiers":[
        {
            "category":"Communications",
            "subcategory":"Film & Video Production",
            "type":"Services"
        }
    ],
    "sg:phone":"+41 12710004",
    "sg:postcode":"8001",
    "sg:province":"Z\u00fcrich",
    "sg:tags":[
        "videofilmherstellung",
        "u"
    ],
    "wof:name":"F Project Bartos Trickfilmarbeiten Bes. F. Werbung",
    "wof:placetype":"venue"
},
  "geometry": {"coordinates":[8.5375080109,47.3822784424],"type":"Point"}
}