{
  "type": "Feature",
  "properties": {
    "iso:country":"CH",
    "sg:address":"Buechstrasse 26",
    "sg:city":"Ganterschwil",
    "sg:orig_category":"Herstellung von Reiseartikeln, Leder U Sattlerwaren Innendekorationsateliers",
    "sg:phone":"+41 71 983 33 48",
    "sg:postcode":"9608",
    "sg:province":"St. Gallen",
    "wof:name":"Hugo R\u00fcegg Sattlerei & Polsterei",
    "wof:placetype":"venue"
},
  "geometry": {"coordinates":[9.0935716629,47.3831481934],"type":"Point"}
}