{
  "type": "Feature",
  "properties": {
    "iso:country":"CH",
    "sg:address":"Regina Via 54",
    "sg:city":"Agno",
    "sg:orig_category":"Unternehmensberatung",
    "sg:phone":"+41 71 288 05 05",
    "sg:postcode":"6982",
    "sg:province":"Ticino",
    "wof:name":"Mip Management Informationspartner Ag",
    "wof:placetype":"venue"
},
  "geometry": {"coordinates":[9.418217659,47.4458961487],"type":"Point"}
}