{
  "type": "Feature",
  "properties": {
    "iso:country":"CH",
    "sg:address":"Schafisweg 15",
    "sg:city":"Ligerz",
    "sg:orig_category":"Organisationen des Gesundheitswesen",
    "sg:phone":"+41 32 315 13 50",
    "sg:postcode":"2514",
    "sg:province":"Bern",
    "wof:name":"Samariterverein Am See",
    "wof:placetype":"venue"
},
  "geometry": {"coordinates":[7.1352510452,47.0840110779],"type":"Point"}
}