{
  "type": "Feature",
  "properties": {
    "iso:country":"CH",
    "sg:address":"Via Oldelli 1",
    "sg:city":"Mendrisio",
    "sg:orig_category":"Benzin, Heiz\u00f6l and Mineral\u00f6lprodukte Grosshandel Mineral\u00f6lverarbeitung",
    "sg:phone":"+41 91 640 30 00",
    "sg:postcode":"6850",
    "sg:province":"Ticino",
    "wof:name":"Grassi Oil Sa",
    "wof:placetype":"venue"
},
  "geometry": {"coordinates":[8.974789,45.867317],"type":"Point"}
}