{
  "type": "Feature",
  "properties": {
    "iso:country":"CH",
    "sg:address":"Waldeggstrasse 2",
    "sg:city":"Rotkreuz",
    "sg:orig_category":"Herstellung von Metallerzeugnissen ohne Maschinenbau Herstellung von elektrischen Haushaltsger\u00e4ten",
    "sg:phone":"+41 17616336",
    "sg:postcode":"6343",
    "sg:province":"Zug",
    "wof:name":"Wibis Ag",
    "wof:placetype":"venue"
},
  "geometry": {"coordinates":[8.4410018921,47.2730064392],"type":"Point"}
}