{
  "type": "Feature",
  "properties": {
    "iso:country":"CH",
    "sg:address":"F\u00e4rchstrasse 8 4629 Fulenbach. Postfach 29",
    "sg:city":"Fulenbach",
    "sg:orig_category":"Herstellung von isolierten Elektrokabeln, -leitungen U dr\u00e4hten",
    "sg:phone":"+41 62 917 30 30",
    "sg:postcode":"4629",
    "sg:province":"Solothurn",
    "wof:name":"Abotron Ag Kabelkonfektion",
    "wof:placetype":"venue"
},
  "geometry": {"coordinates":[7.832442,47.283825],"type":"Point"}
}