{
  "type": "Feature",
  "properties": {
    "iso:country":"CH",
    "sg:address":"3926",
    "sg:city":"Embd",
    "sg:orig_category":"Sportvereine Sch\u00fctzen",
    "sg:postcode":"3926",
    "sg:province":"Valais",
    "wof:name":"Milit\u00e4rschiessverein",
    "wof:placetype":"venue"
},
  "geometry": {"coordinates":[7.8282060623,46.2169151306],"type":"Point"}
}