{
  "type": "Feature",
  "properties": {
    "iso:country":"CH",
    "sg:address":"L\u00e4tth\u00fcbelstrasse 12",
    "sg:city":"Lostorf",
    "sg:orig_category":"Fachdetailhandel in Verkaufsr\u00e4umen",
    "sg:phone":"+41 62 298 33 15",
    "sg:postcode":"4654",
    "sg:province":"Solothurn",
    "wof:name":"Wallo Sports Marc W. Walker",
    "wof:placetype":"venue"
},
  "geometry": {"coordinates":[7.9425029755,47.3817939758],"type":"Point"}
}