{
  "type": "Feature",
  "properties": {
    "iso:country":"CH",
    "sg:address":"Muzy Rue 8 1207 Gen\u00e8ve. Postfach",
    "sg:city":"Gen\u00e8ve",
    "sg:orig_category":"Finanzierungsinstitutionen",
    "sg:postcode":"1201",
    "sg:province":"Gen\u00e8ve",
    "wof:name":"Tech Style Concept Ag, Schaan (liechtenstein), Succursale Di Castel San Pietro Affari Finanziari E Commerciali, Partecipazione Ecc",
    "wof:placetype":"venue"
},
  "geometry": {"coordinates":[9.0076999664,45.8654785156],"type":"Point"}
}