{
  "type": "Feature",
  "properties": {
    "iso:country":"CH",
    "sg:address":"Unterer Graben 21",
    "sg:city":"St.gallen",
    "sg:orig_category":"RESTAURANTS: TEA-ROOMS",
    "sg:postcode":"9000",
    "sg:province":"St. Gallen",
    "wof:name":"Casablanca Caf\u00e9-restaurant L. Sulzer",
    "wof:placetype":"venue"
},
  "geometry": {"coordinates":[8.6235713959,47.2005004883],"type":"Point"}
}