{
  "type": "Feature",
  "properties": {
    "iso:country":"CH",
    "sg:address":"Moosstrasse 7",
    "sg:city":"R\u00fcschlikon",
    "sg:orig_category":"Grosshandel mit Fleisch U Fleischwaren Grosshandel mit Obst U Gem\u00fcse",
    "sg:phone":"+41 17046510",
    "sg:postcode":"8803",
    "sg:province":"Z\u00fcrich",
    "wof:name":"Prodega Ag Cash & Carry",
    "wof:placetype":"venue"
},
  "geometry": {"coordinates":[8.5459842682,47.3030929565],"type":"Point"}
}