{
  "type": "Feature",
  "properties": {
    "iso:country":"CH",
    "sg:address":"Stazione Piazza",
    "sg:city":"Muralto",
    "sg:orig_category":"RESTAURANTS: TEA-ROOMS",
    "sg:phone":"+41 91 743 32 62",
    "sg:postcode":"6600",
    "sg:province":"Ticino",
    "wof:name":"Ristorante Bar Stazione Sa",
    "wof:placetype":"venue"
},
  "geometry": {"coordinates":[8.8009147644,46.1721305847],"type":"Point"}
}