{
  "type": "Feature",
  "properties": {
    "iso:country":"CH",
    "sg:address":"Wolfgalgenstrasse 1",
    "sg:city":"Oberkulm",
    "sg:orig_category":"Verarbeitung von Milch Verwertung von Milch",
    "sg:postcode":"5727",
    "sg:province":"Aargau",
    "wof:name":"K\u00e4sereigenossenschaft Oberkulm",
    "wof:placetype":"venue"
},
  "geometry": {"coordinates":[8.1245260239,47.3002967834],"type":"Point"}
}