{
  "type": "Feature",
  "properties": {
    "iso:country":"CH",
    "sg:address":"Mattenweg",
    "sg:city":"Sch\u00f6nb\u00fchl-urtenen",
    "sg:classifiers":[
        {
            "category":"Government",
            "subcategory":"Post Office",
            "type":"Public Place"
        }
    ],
    "sg:phone":"+41 31 859 34 38",
    "sg:postcode":"3322",
    "sg:province":"Bern",
    "sg:tags":[
        "caf\u00e9s",
        "tea-rooms"
    ],
    "wof:name":"Caf\u00e9 Solbad",
    "wof:placetype":"venue"
},
  "geometry": {"coordinates":[7.4953417778,47.0212440491],"type":"Point"}
}