{
  "type": "Feature",
  "properties": {
    "iso:country":"CH",
    "sg:address":"Route De La Goeille 6",
    "sg:city":"Savigny",
    "sg:orig_category":"Non-Classified Establishments",
    "sg:phone":"+41 21 781 28 51",
    "sg:postcode":"1073",
    "sg:province":"Vaud",
    "wof:name":"Fromecs Sa",
    "wof:placetype":"venue"
},
  "geometry": {"coordinates":[6.7272047997,46.5466651917],"type":"Point"}
}