{
  "type": "Feature",
  "properties": {
    "iso:country":"CH",
    "sg:address":"Bildweg 6",
    "sg:city":"Bronschhofen",
    "sg:orig_category":"Sonstige mit der Informatik verbundene T\u00e4tigkeiten",
    "sg:phone":"+41 71 910 04 31",
    "sg:postcode":"9552",
    "sg:province":"St. Gallen",
    "wof:name":"Coradi-service, Jossi Peter",
    "wof:placetype":"venue"
},
  "geometry": {"coordinates":[9.0363349915,47.4721298218],"type":"Point"}
}