{
  "type": "Feature",
  "properties": {
    "addr:full":"Grundstrasse 15 Baar Zug 6340",
    "addr:housenumber":"15",
    "addr:postcode":"6340",
    "addr:street":"Grundstrasse;Zug",
    "iso:country":"CH",
    "sg:address":"Grundstrasse 15",
    "sg:city":"Baar",
    "sg:orig_category":"Architektur U Ingenieurb\u00fcros",
    "sg:phone":"+41 21 791 13 56",
    "sg:postcode":"6340",
    "sg:province":"Zug",
    "wof:name":"E-teach S\u00e0rl",
    "wof:placetype":"venue"
},
  "geometry": {"coordinates":[6.677415,46.513313],"type":"Point"}
}