{
  "type": "Feature",
  "properties": {
    "iso:country":"CH",
    "sg:address":"4242 Laufen. Postfach 218",
    "sg:city":"Laufen",
    "sg:orig_category":"Sportvereine Eissport Curling",
    "sg:phone":"+41 61 761 28 10",
    "sg:postcode":"4242",
    "sg:province":"Basel-Landschaft",
    "wof:name":"Curling Club Laufen-first",
    "wof:placetype":"venue"
},
  "geometry": {"coordinates":[7.5014591217,47.420375824],"type":"Point"}
}