{
  "type": "Feature",
  "properties": {
    "addr:full":"Route De La Scie 2 1753 Matran Case Postale 26 Matran Fribourg 1753",
    "addr:housenumber":"2",
    "addr:postcode":"1753;26;1753",
    "addr:street":"Route De La Scie;Postale",
    "iso:country":"CH",
    "sg:address":"Route De La Scie 2 1753 Matran Case Postale 26",
    "sg:city":"Matran",
    "sg:orig_category":"Architektur U Ingenieurb\u00fcros Bauingenieurb\u00fcros",
    "sg:phone":"+41 26 401 14 61",
    "sg:postcode":"1753",
    "sg:province":"Fribourg",
    "wof:name":"Hd Consultant S\u00e0rl Consultant Technique Dans Les Domaines De La Construction Etc",
    "wof:placetype":"venue"
},
  "geometry": {"coordinates":[7.09966,46.784588],"type":"Point"}
}