{
  "type": "Feature",
  "properties": {
    "iso:country":"CH",
    "sg:address":"Haldenstrasse 1",
    "sg:city":"Aesch",
    "sg:orig_category":"Grosshandel mit Nahrungsmitteln, Getr\u00e4nken U Tabakwaren ohne ausgepr\u00e4gten Schwerpunkt",
    "sg:postcode":"8904",
    "sg:province":"Z\u00fcrich",
    "wof:name":"Dorf-laden L\u00e4uchli Martin",
    "wof:placetype":"venue"
},
  "geometry": {"coordinates":[7.4413700104,46.4569587708],"type":"Point"}
}