{
  "type": "Feature",
  "properties": {
    "iso:country":"CH",
    "sg:address":"Weberg\u00e4sschen 4",
    "sg:city":"Riehen",
    "sg:orig_category":"Detailhandel mit Sportartikeln",
    "sg:phone":"+41 61 641 46 49",
    "sg:postcode":"4125",
    "sg:province":"Basel-Stadt",
    "wof:name":"Cenci Ag Sport & Mode",
    "wof:placetype":"venue"
},
  "geometry": {"coordinates":[7.6516089439,47.5849761963],"type":"Point"}
}