{
  "type": "Feature",
  "properties": {
    "iso:country":"CH",
    "sg:address":"Levratte La 32d",
    "sg:city":"Nyon",
    "sg:orig_category":"Sonstiger Grosshandel",
    "sg:postcode":"1260",
    "sg:province":"Vaud",
    "wof:name":"Ceo Cultural Exchange Organization S\u00e0rl",
    "wof:placetype":"venue"
},
  "geometry": {"coordinates":[6.2297940254,46.3884925842],"type":"Point"}
}