{
  "type": "Feature",
  "properties": {
    "iso:country":"CH",
    "sg:address":"Hinterm\u00e4ttlistrasse 4",
    "sg:city":"M\u00e4genwil",
    "sg:orig_category":"Grosshandel mit sonstigen Gebrauchs U Verbrauchsg\u00fctern Sonstiger Fachdetailhandel in Verkaufsr\u00e4umen",
    "sg:phone":"+41 62 896 07 07",
    "sg:postcode":"5506",
    "sg:province":"Aargau",
    "wof:name":"Richner Waffen Gmbh",
    "wof:placetype":"venue"
},
  "geometry": {"coordinates":[8.2244081497,47.4107704163],"type":"Point"}
}