{
  "type": "Feature",
  "properties": {
    "addr:full":"Marktplatz 16 Lyss Bern 3250",
    "addr:housenumber":"16",
    "addr:postcode":"3250",
    "addr:street":"Marktplatz;Bern",
    "iso:country":"CH",
    "sg:address":"Marktplatz 16",
    "sg:city":"Lyss",
    "sg:classifiers":[
        {
            "category":"Manufacturing",
            "subcategory":"Paper Products",
            "type":"Manufacturing & Wholesale Goods"
        }
    ],
    "sg:phone":"+41 32 385 10 83",
    "sg:postcode":"3250",
    "sg:province":"Bern",
    "sg:tags":[
        "brochure",
        "production"
    ],
    "wof:name":"Ursula Loosli Print-egge",
    "wof:placetype":"venue"
},
  "geometry": {"coordinates":[7.304858,47.073357],"type":"Point"}
}