{
  "type": "Feature",
  "properties": {
    "addr:full":"Promenade 56 Davos Graubunden 7270",
    "addr:housenumber":"56",
    "addr:postcode":"7270",
    "addr:street":"Promenade",
    "iso:country":"CH",
    "sg:address":"Promenade 56",
    "sg:city":"Davos",
    "sg:classifiers":[
        {
            "category":"Banks & Credit Unions",
            "subcategory":"Bank",
            "type":"Services"
        }
    ],
    "sg:phone":"+41 81 414 14 14",
    "sg:postcode":"7270",
    "sg:province":"Graubunden",
    "wof:name":"Graub\u00fcndner Kantonalbank",
    "wof:placetype":"venue"
},
  "geometry": {"coordinates":[9.822363,46.796329],"type":"Point"}
}