{
  "type": "Feature",
  "properties": {
    "iso:country":"CH",
    "sg:address":"Saint-laurent Rue 32 1003 Lausanne. Postfach",
    "sg:city":"Lausanne",
    "sg:orig_category":"Pensionskassen",
    "sg:phone":"+41 21 311 25 27",
    "sg:postcode":"1003",
    "sg:province":"Vaud",
    "wof:name":"Fonds De Pr\u00e9voyance En Faveur Du Personnel De La Maison Fonjallaz, Oetiker Sa",
    "wof:placetype":"venue"
},
  "geometry": {"coordinates":[6.6306900978,46.5223999023],"type":"Point"}
}