{
  "type": "Feature",
  "properties": {
    "addr:full":"Paradeplatz / Tiefenh\u00f6fe 6 Z\u00fcrich Z\u00fcrich 8022",
    "addr:housenumber":"6",
    "addr:postcode":"8022",
    "addr:street":"Paradeplatz",
    "iso:country":"CH",
    "sg:address":"Paradeplatz / Tiefenh\u00f6fe 6",
    "sg:city":"Z\u00fcrich",
    "sg:classifiers":[
        {
            "category":"Banks & Credit Unions",
            "subcategory":"Bank",
            "type":"Services"
        }
    ],
    "sg:phone":"+41 12113313",
    "sg:postcode":"8022",
    "sg:province":"Z\u00fcrich",
    "wof:name":"Fuji Bank (schweiz) Ag",
    "wof:placetype":"venue"
},
  "geometry": {"coordinates":[8.53801,47.369091],"type":"Point"}
}