{
  "type": "Feature",
  "properties": {
    "iso:country":"CH",
    "sg:address":"Sch\u00fcrstr. 44 6032 Emmen. Postfach",
    "sg:city":"Emmenbr\u00fccke",
    "sg:orig_category":"Herstellung von Radio U Fernsehger\u00e4ten sowie phono U videotechnischen Ger\u00e4ten",
    "sg:postcode":"6020",
    "sg:province":"Luzern",
    "wof:name":"Video + Tontr\u00e4ger-vertrieb Boog K.",
    "wof:placetype":"venue"
},
  "geometry": {"coordinates":[8.2702980042,47.0877418518],"type":"Point"}
}