{
  "type": "Feature",
  "properties": {
    "iso:country":"CH",
    "sg:address":"Kulmackerweg 16",
    "sg:city":"Sissach",
    "sg:orig_category":"Zahntechnische Laboratorien",
    "sg:phone":"+41 61 971 23 48",
    "sg:postcode":"4450",
    "sg:province":"Basel-Landschaft",
    "wof:name":"Schaub Ludwig, Zahntech. Labor K\u00fcnstlicher Zahnersatz; Anfertigung, Reparatur, \u00c4nderung",
    "wof:placetype":"venue"
},
  "geometry": {"coordinates":[7.8066082001,47.4611167908],"type":"Point"}
}