{
  "type": "Feature",
  "properties": {
    "iso:country":"CH",
    "sg:address":"Marktstrasse 3",
    "sg:city":"Niederuzwil",
    "sg:orig_category":"Nationale Postdienste",
    "sg:phone":"+41 32 637 11 05",
    "sg:postcode":"9244",
    "sg:province":"St. Gallen",
    "wof:name":"Die Schweizerische Post",
    "wof:placetype":"venue"
},
  "geometry": {"coordinates":[9.1425943375,47.4459571838],"type":"Point"}
}