{
  "type": "Feature",
  "properties": {
    "iso:country":"CH",
    "sg:address":"Rue Du Lavoir 8",
    "sg:city":"Avenches",
    "sg:orig_category":"Sonstiges Textilgewerbe",
    "sg:phone":"+41 79 255 49 48",
    "sg:postcode":"1580",
    "sg:province":"Vaud",
    "wof:name":"La Grange Aux Tissus S\u00e0rl",
    "wof:placetype":"venue"
},
  "geometry": {"coordinates":[7.040664196,46.8770904541],"type":"Point"}
}