{
  "type": "Feature",
  "properties": {
    "iso:country":"CH",
    "sg:address":"R\u00e9gie Rue De La 6",
    "sg:city":"Delsberg",
    "sg:orig_category":"Fussboden, Fliesen U Plattenlegerei, Tapeziererei",
    "sg:phone":"+41 79 631 75 85",
    "sg:postcode":"2800",
    "sg:province":"Jura",
    "wof:name":"Zopp\u00e9 Parquets S\u00e0rl",
    "wof:placetype":"venue"
},
  "geometry": {"coordinates":[7.3439698219,47.3653564453],"type":"Point"}
}