{
  "type": "Feature",
  "properties": {
    "iso:country":"CH",
    "sg:address":"Dorf",
    "sg:city":"Heitenried",
    "sg:orig_category":"Herstellung von \u00d6fen U Brennern",
    "sg:phone":"+41 26 495 13 89",
    "sg:postcode":"1714",
    "sg:province":"Fribourg",
    "wof:name":"Aebischer Thomas & Co",
    "wof:placetype":"venue"
},
  "geometry": {"coordinates":[7.2986240387,46.8276405334],"type":"Point"}
}