{
  "type": "Feature",
  "properties": {
    "iso:country":"CH",
    "sg:address":"Forst",
    "sg:city":"Grabs",
    "sg:orig_category":"Fahrschulen, Flugschulen",
    "sg:phone":"+41 79 608 59 53",
    "sg:postcode":"9472",
    "sg:province":"St. Gallen",
    "wof:name":"Hansueli Vetsch Autofahrschule",
    "wof:placetype":"venue"
},
  "geometry": {"coordinates":[9.4314899445,47.1847381592],"type":"Point"}
}