{
  "type": "Feature",
  "properties": {
    "iso:country":"CH",
    "sg:address":"Rue Du Cardinal-journet 9",
    "sg:city":"Meyrin",
    "sg:orig_category":"Herstellung von Karosserien U Anh\u00e4ngern",
    "sg:phone":"+41 22 782 40 45",
    "sg:postcode":"1217",
    "sg:province":"Gen\u00e8ve",
    "wof:name":"Carrosserie-express, Di Berardino D. Et Leoni G.",
    "wof:placetype":"venue"
},
  "geometry": {"coordinates":[6.0837898254,46.2238121033],"type":"Point"}
}