{
  "type": "Feature",
  "properties": {
    "iso:country":"CH",
    "sg:address":"Viehmarktgasse 57",
    "sg:city":"Laufen",
    "sg:orig_category":"Herstellung von medizinischen U chirurgischen Ger\u00e4ten sowie orthop\u00e4dischen Vorrichtungen Zahntechnis",
    "sg:phone":"+41 61 761 29 29",
    "sg:postcode":"4242",
    "sg:province":"Basel-Landschaft",
    "wof:name":"Gerold Nussbaumer, Zahntechnisches Labor",
    "wof:placetype":"venue"
},
  "geometry": {"coordinates":[7.4998140335,47.4226837158],"type":"Point"}
}