{
  "type": "Feature",
  "properties": {
    "iso:country":"CH",
    "sg:address":"Gotthardstrasse 5 8002 Z\u00fcrich. Postfach 4779",
    "sg:city":"Z\u00fcrich",
    "sg:orig_category":"Diskotheken, Dancings, Night Clubs",
    "sg:phone":"+41 32 931 81 05",
    "sg:postcode":"8022",
    "sg:province":"Z\u00fcrich",
    "wof:name":"La Canasta Sa",
    "wof:placetype":"venue"
},
  "geometry": {"coordinates":[6.7485117912,47.0584869385],"type":"Point"}
}