{
  "type": "Feature",
  "properties": {
    "iso:country":"CH",
    "sg:address":"Lehngasse",
    "sg:city":"Wilderswil",
    "sg:classifiers":[
        {
            "category":"Banks & Credit Unions",
            "subcategory":"Bank",
            "type":"Services"
        }
    ],
    "sg:phone":"+41 36229229",
    "sg:postcode":"3812",
    "sg:province":"Bern",
    "wof:name":"Raiffeisenbank",
    "wof:placetype":"venue"
},
  "geometry": {"coordinates":[7.86328,46.66082],"type":"Point"}
}