{
  "type": "Feature",
  "properties": {
    "iso:country":"CH",
    "sg:address":"Karl Jaspers-allee 5 4052 Basel. Postfach",
    "sg:city":"Basel",
    "sg:orig_category":"Non-Classified Establishments",
    "sg:postcode":"4051",
    "sg:province":"Basel-Stadt",
    "wof:name":"Rawal Ag Beteiligungen, Treuhandgesch\u00e4fte Usw",
    "wof:placetype":"venue"
},
  "geometry": {"coordinates":[7.6108617783,47.5478248596],"type":"Point"}
}