{
  "type": "Feature",
  "properties": {
    "iso:country":"CH",
    "sg:address":"Flurstrasse 16",
    "sg:city":"Bern",
    "sg:orig_category":"Malerei",
    "sg:phone":"+41 71 966 57 76",
    "sg:postcode":"3014",
    "sg:province":"Bern",
    "wof:name":"Helmut Br\u00fcgger Malergesch\u00e4ft",
    "wof:placetype":"venue"
},
  "geometry": {"coordinates":[8.9860811234,47.4507369995],"type":"Point"}
}