{
  "type": "Feature",
  "properties": {
    "iso:country":"CH",
    "sg:address":"Chemin De Relion 1e",
    "sg:city":"Collonge-bellerive",
    "sg:classifiers":[
        {
            "category":"Professional",
            "subcategory":"Employment Agencies",
            "type":"Services"
        }
    ],
    "sg:phone":"+41 22 752 38 23",
    "sg:postcode":"1245",
    "sg:province":"Gen\u00e8ve",
    "sg:tags":[
        "personal",
        "u",
        "stellenvermittlung"
    ],
    "wof:name":"Grandjean Heli",
    "wof:placetype":"venue"
},
  "geometry": {"coordinates":[6.1986107826,46.2521858215],"type":"Point"}
}