{
  "type": "Feature",
  "properties": {
    "iso:country":"CH",
    "sg:address":"Aarburgerstrasse 5",
    "sg:city":"Zofingen",
    "sg:orig_category":"Detailhandel mit Waren verschiedener Art, Hauptrichtung Nahrungsmittel",
    "sg:phone":"+41 62 745 35 50",
    "sg:postcode":"4800",
    "sg:province":"Aargau",
    "wof:name":"Migros-markt",
    "wof:placetype":"venue"
},
  "geometry": {"coordinates":[7.9424362183,47.2916908264],"type":"Point"}
}