{
  "type": "Feature",
  "properties": {
    "iso:country":"CH",
    "sg:address":"Margarethenstrasse 17 4053 Basel. Postfach",
    "sg:city":"Basel",
    "sg:orig_category":"Zoll- and Grenzb\u00fcros",
    "sg:phone":"+41 61 271 77 30",
    "sg:postcode":"4017",
    "sg:province":"Basel-Stadt",
    "wof:name":"Ptt Postzollamt",
    "wof:placetype":"venue"
},
  "geometry": {"coordinates":[7.5855689049,47.5471076965],"type":"Point"}
}