{
  "type": "Feature",
  "properties": {
    "iso:country":"CH",
    "sg:address":"Birsigstrasse 80 4054 Basel. Postfach",
    "sg:city":"Basel",
    "sg:orig_category":"Mit dem Versicherungsgewerbe verbundene T\u00e4tigkeiten Pensionskassen",
    "sg:phone":"+41 61 283 23 21",
    "sg:postcode":"4054",
    "sg:province":"Basel-Stadt",
    "wof:name":"Pekad Gmbh Technische Verwaltungen U. Allgemeine Beratung Von Pensionskassen Usw",
    "wof:placetype":"venue"
},
  "geometry": {"coordinates":[7.5805478096,47.5498428345],"type":"Point"}
}