{
  "type": "Feature",
  "properties": {
    "iso:country":"CH",
    "sg:address":"Hauptstrasse 76",
    "sg:city":"Homburg",
    "sg:orig_category":"Erdbewegungsarbeiten G\u00fcterbef\u00f6rderung im Strassenverkehr",
    "sg:postcode":"8508",
    "sg:province":"Thurgau",
    "wof:name":"Daniel Herzog Transporte",
    "wof:placetype":"venue"
},
  "geometry": {"coordinates":[8.9997024536,47.6348304749],"type":"Point"}
}