{
  "type": "Feature",
  "properties": {
    "iso:country":"CH",
    "sg:address":"Speerstrasse 32",
    "sg:city":"Z\u00fcrich",
    "sg:orig_category":"Detailhandel mit Textilien Herstellung von konfektionierten Textilwaren ohne Bekleidung",
    "sg:phone":"+41 79 436 05 32",
    "sg:postcode":"8038",
    "sg:province":"Z\u00fcrich",
    "wof:name":"Simply S Saurer Thomas",
    "wof:placetype":"venue"
},
  "geometry": {"coordinates":[8.5266475677,47.3417778015],"type":"Point"}
}