{
  "type": "Feature",
  "properties": {
    "iso:country":"CH",
    "sg:address":"Arisd\u00f6rferstrasse 4",
    "sg:city":"Liestal",
    "sg:orig_category":"Wirtschaftspr\u00fcfung, Steuerberatung U Treuhand",
    "sg:phone":"+41 61 921 91 00",
    "sg:postcode":"4410",
    "sg:province":"Basel-Landschaft",
    "wof:name":"Dr. Leupin",
    "wof:placetype":"venue"
},
  "geometry": {"coordinates":[7.7395467758,47.4864387512],"type":"Point"}
}