{
  "type": "Feature",
  "properties": {
    "iso:country":"CH",
    "sg:address":"Rathausg\u00e4ssli 6 2500 Biel/bienne. Postfach",
    "sg:city":"Biel/bienne",
    "sg:orig_category":"RESTAURANTS: TEA-ROOMS",
    "sg:postcode":"2502",
    "sg:province":"Bern",
    "wof:name":"Stirnimann Peter",
    "wof:placetype":"venue"
},
  "geometry": {"coordinates":[9.1225099564,46.7561416626],"type":"Point"}
}