{
  "type": "Feature",
  "properties": {
    "iso:country":"CH",
    "sg:address":"Dorfstrasse 14",
    "sg:city":"Kloten",
    "sg:orig_category":"Unclassifiable Establishments",
    "sg:postcode":"8302",
    "sg:province":"Z\u00fcrich",
    "wof:name":"Adecco Humain Resources Ag",
    "wof:placetype":"venue"
},
  "geometry": {"coordinates":[8.5822172165,47.4531593323],"type":"Point"}
}