{
  "type": "Feature",
  "properties": {
    "iso:country":"CH",
    "sg:address":"Regensbergstrasse 242b",
    "sg:city":"Z\u00fcrich",
    "sg:orig_category":"Digital Subscriber Line Dsl Routers Hdsl, Sdsl, Adsl, Vdsl",
    "sg:phone":"+41 13154400",
    "sg:postcode":"8050",
    "sg:province":"Z\u00fcrich",
    "wof:name":"Init Seven Ag",
    "wof:placetype":"venue"
},
  "geometry": {"coordinates":[8.530459404,47.4109725952],"type":"Point"}
}