{
  "type": "Feature",
  "properties": {
    "iso:country":"CH",
    "sg:address":"Alexanderstrasse 8 7000 Chur. Postfach 311",
    "sg:city":"Chur",
    "sg:orig_category":"Fahrschulen, Flugschulen",
    "sg:postcode":"7001",
    "sg:province":"Graubunden",
    "wof:name":"Marco Codiferro Autofahrschule",
    "wof:placetype":"venue"
},
  "geometry": {"coordinates":[9.5315208435,46.8525695801],"type":"Point"}
}