{
  "type": "Feature",
  "properties": {
    "iso:country":"CH",
    "sg:address":"Bremgarterstrasse 12",
    "sg:city":"Widen",
    "sg:orig_category":"Nationale Postdienste",
    "sg:phone":"+41 56 633 14 79",
    "sg:postcode":"8967",
    "sg:province":"Aargau",
    "wof:name":"Die Schweizerische Post",
    "wof:placetype":"venue"
},
  "geometry": {"coordinates":[8.3615560532,47.3672790527],"type":"Point"}
}