{
  "type": "Feature",
  "properties": {
    "iso:country":"CH",
    "sg:address":"Dorfstrasse 66 3715 Adelboden. Postfach",
    "sg:city":"Adelboden",
    "sg:orig_category":"Detailhandel mit Sportartikeln Fachdetailhandel in Verkaufsr\u00e4umen",
    "sg:phone":"+41 33 673 20 72",
    "sg:postcode":"3715",
    "sg:province":"Bern",
    "wof:name":"Sport Shop Den Hartog Frans.",
    "wof:placetype":"venue"
},
  "geometry": {"coordinates":[7.5557150841,46.4904136658],"type":"Point"}
}