{
  "type": "Feature",
  "properties": {
    "iso:country":"CH",
    "sg:address":"Schickmattweg 8 8332 Russikon. Postfach",
    "sg:city":"Russikon",
    "sg:orig_category":"Grosshandel mit elektrischen Haushaltsger\u00e4ten",
    "sg:phone":"+41 19550608",
    "sg:postcode":"8332",
    "sg:province":"Z\u00fcrich",
    "wof:name":"Stephan & S\u00f6hne Gmbh & Co",
    "wof:placetype":"venue"
},
  "geometry": {"coordinates":[8.7740049362,47.3910179138],"type":"Point"}
}