{
  "type": "Feature",
  "properties": {
    "iso:country":"CH",
    "sg:address":"En Ogoz",
    "sg:city":"St-saphorin-lavaux",
    "sg:orig_category":"Detailhandel mit Metallwaren, Anstrichmitteln, Glaswaren, Bau U Heimwerkerbedarf Maschinenbau",
    "sg:phone":"+41 21 946 53 03",
    "sg:postcode":"1813",
    "wof:name":"Nt Services S\u00e0rl",
    "wof:placetype":"venue"
},
  "geometry": {"coordinates":[6.7959570885,46.4733009338],"type":"Point"}
}