{
  "type": "Feature",
  "properties": {
    "iso:country":"CH",
    "sg:address":"Sch\u00f6nenwerderstrasse 26",
    "sg:city":"Aarau",
    "sg:orig_category":"Vermietung von Automobilen",
    "sg:phone":"+41 62 824 16 69",
    "sg:postcode":"5000",
    "sg:province":"Aargau",
    "wof:name":"Georges Kohler Garage & Autovermietung",
    "wof:placetype":"venue"
},
  "geometry": {"coordinates":[8.0394220352,47.3870773315],"type":"Point"}
}