{
  "type": "Feature",
  "properties": {
    "iso:country":"CH",
    "sg:address":"Muesmattstrasse 38",
    "sg:city":"Bern",
    "sg:orig_category":"Institutionen f\u00fcr Finanzierungsleasing",
    "sg:phone":"+41 31 301 87 07",
    "sg:postcode":"3012",
    "sg:province":"Bern",
    "wof:name":"Wenger F. & Co Autoleasing.",
    "wof:placetype":"venue"
},
  "geometry": {"coordinates":[7.4289488792,46.9541473389],"type":"Point"}
}