{
  "type": "Feature",
  "properties": {
    "iso:country":"CH",
    "sg:address":"Avenue De Sainte-clotilde 5",
    "sg:city":"Gen\u00e8ve",
    "sg:orig_category":"Film U Videofilmherstellung Sonstige Hilfsdienste des Kultur U Unterhaltungswesens",
    "sg:phone":"+41 22 328 69 91",
    "sg:postcode":"1205",
    "sg:province":"Gen\u00e8ve",
    "wof:name":"Kal\u00e9idoscope R\u00e9alisations Audio-visuelles",
    "wof:placetype":"venue"
},
  "geometry": {"coordinates":[6.1346750259,46.2006416321],"type":"Point"}
}