{
  "type": "Feature",
  "properties": {
    "iso:country":"CH",
    "sg:address":"B\u00fcndtestrasse 5",
    "sg:city":"Chur",
    "sg:orig_category":"Werbung",
    "sg:postcode":"7000",
    "sg:province":"Graubunden",
    "wof:name":"Creatrend A. Malgaroli",
    "wof:placetype":"venue"
},
  "geometry": {"coordinates":[9.5197982788,46.8500595093],"type":"Point"}
}