{
  "type": "Feature",
  "properties": {
    "addr:full":"Terbinerstrasse 10 Visp Valais 3930",
    "addr:housenumber":"10",
    "addr:postcode":"3930",
    "addr:street":"Terbinerstrasse",
    "iso:country":"CH",
    "sg:address":"Terbinerstrasse 10",
    "sg:city":"Visp",
    "sg:orig_category":"Bauschreinerei Herstellung von Konstruktionsteilen, Fertigbauteilen U Ausbauelementen aus Holz",
    "sg:phone":"+41 27 946 11 81",
    "sg:postcode":"3930",
    "sg:province":"Valais",
    "wof:name":"Schreinerei Kreuzer & Studer Ag",
    "wof:placetype":"venue"
},
  "geometry": {"coordinates":[7.885162,46.290474],"type":"Point"}
}