{
  "type": "Feature",
  "properties": {
    "iso:country":"CH",
    "sg:address":"Hauptstrasse 30",
    "sg:city":"Pfeffingen",
    "sg:orig_category":"Detailhandel mit Waren verschiedener Art, Hauptrichtung Nahrungsmittel Grosshandel mit Nahrungsmitte",
    "sg:phone":"+41 61 751 55 22",
    "sg:postcode":"4148",
    "sg:province":"Basel-Landschaft",
    "wof:name":"Reinhold Finger Denner-satellit",
    "wof:placetype":"venue"
},
  "geometry": {"coordinates":[7.5900139809,47.4602279663],"type":"Point"}
}