{
  "type": "Feature",
  "properties": {
    "iso:country":"CH",
    "sg:address":"Montana-vermala",
    "sg:city":"Montana-vermala",
    "sg:orig_category":"Pensionskassen",
    "sg:postcode":"3962",
    "wof:name":"Fondation G. Barras Sa",
    "wof:placetype":"venue"
},
  "geometry": {"coordinates":[7.4924340248,46.3144187927],"type":"Point"}
}