{
  "type": "Feature",
  "properties": {
    "iso:country":"CH",
    "sg:address":"Alte Dorfstrasse 173",
    "sg:city":"Tennwil",
    "sg:orig_category":"Handelsvermittlung U Grosshandel",
    "sg:phone":"+41 56 667 30 00",
    "sg:postcode":"5617",
    "sg:province":"Aargau",
    "wof:name":"Bucofin Ag",
    "wof:placetype":"venue"
},
  "geometry": {"coordinates":[8.2208747864,47.3071289062],"type":"Point"}
}