{
  "type": "Feature",
  "properties": {
    "iso:country":"CH",
    "sg:address":"Dorfstrasse 16",
    "sg:city":"Belp",
    "sg:orig_category":"Detailhandel mit B\u00fcromaschinen U einrichtungen",
    "sg:phone":"+41 31 819 06 02",
    "sg:postcode":"3123",
    "sg:province":"Bern",
    "wof:name":"B\u00fcrki B\u00fcrobedarf Ag Papeterie",
    "wof:placetype":"venue"
},
  "geometry": {"coordinates":[7.498322,46.892464],"type":"Point"}
}