{
  "type": "Feature",
  "properties": {
    "iso:country":"CH",
    "sg:address":"Arbonerstrasse 17",
    "sg:city":"Amriswil",
    "sg:orig_category":"Institutionen f\u00fcr Behinderte Wohnheime",
    "sg:phone":"+41 71 414 13 13",
    "sg:postcode":"8580",
    "sg:province":"Thurgau",
    "wof:name":"Genossenschaft Arbeitsheim F\u00fcr Behinderte, Amriswil",
    "wof:placetype":"venue"
},
  "geometry": {"coordinates":[9.302028656,47.5448493958],"type":"Point"}
}