{
  "type": "Feature",
  "properties": {
    "iso:country":"CH",
    "sg:address":"Dufourstrasse 52",
    "sg:city":"Zollikon",
    "sg:orig_category":"Werbung",
    "sg:phone":"+41 13902320",
    "sg:postcode":"8702",
    "sg:province":"Z\u00fcrich",
    "wof:name":"Jbw, Werbeagentur, J\u00fcrg Bachmann",
    "wof:placetype":"venue"
},
  "geometry": {"coordinates":[8.5707521439,47.3417015076],"type":"Point"}
}