{
  "type": "Feature",
  "properties": {
    "addr:full":"3903 Mund Valais 3903",
    "addr:housenumber":"3903",
    "addr:postcode":"3903",
    "addr:street":"Mund Valais",
    "iso:country":"CH",
    "sg:address":"3903",
    "sg:city":"Mund",
    "sg:orig_category":"Allgemeiner Hoch U Tiefbau Maurerarbeiten",
    "sg:phone":"+41 24 499 12 20",
    "sg:postcode":"3903",
    "sg:province":"Valais",
    "wof:name":"Veillard & Crausaz Sa",
    "wof:placetype":"venue"
},
  "geometry": {"coordinates":[6.99538,46.296612],"type":"Point"}
}