{
  "type": "Feature",
  "properties": {
    "iso:country":"CH",
    "sg:address":"Industriestrasse 5 6005 Luzern. Postfach",
    "sg:city":"Luzern",
    "sg:orig_category":"Non-Classified Establishments",
    "sg:phone":"+41 41 360 49 49",
    "sg:postcode":"6003",
    "sg:province":"Luzern",
    "wof:name":"Peter B\u00fcrki Ag Immobilien Und Beteiligungen Beteiligungen Usw",
    "wof:placetype":"venue"
},
  "geometry": {"coordinates":[8.3109703064,47.0418701172],"type":"Point"}
}