{
  "type": "Feature",
  "properties": {
    "iso:country":"CH",
    "sg:address":"Stegmattgasse 7 3506 Grossh\u00f6chstetten. Postfach",
    "sg:city":"Grossh\u00f6chstetten",
    "sg:orig_category":"Tierarztpraxis",
    "sg:phone":"+41 41 610 41 44",
    "sg:postcode":"3506",
    "sg:province":"Bern",
    "wof:name":"Dr. Med. Vet. Anton W\u00fcrsch Tierarzt",
    "wof:placetype":"venue"
},
  "geometry": {"coordinates":[8.3801145554,46.9620323181],"type":"Point"}
}