{
  "type": "Feature",
  "properties": {
    "iso:country":"CH",
    "sg:address":"Tschalunstrasse 4",
    "sg:city":"Oberiberg",
    "sg:orig_category":"Detailhandel mit Schuhen Fachdetailhandel in Verkaufsr\u00e4umen",
    "sg:phone":"+41 55 414 12 12",
    "sg:postcode":"8843",
    "sg:province":"Schwyz",
    "wof:name":"Holdener Sport",
    "wof:placetype":"venue"
},
  "geometry": {"coordinates":[8.7814178467,47.0395317078],"type":"Point"}
}