{
  "type": "Feature",
  "properties": {
    "iso:country":"CH",
    "sg:address":"Via San Francesco 2",
    "sg:city":"Locarno",
    "sg:orig_category":"Fachdetailhandel mit pharmazeutischen Produkten",
    "sg:phone":"+41 91 646 12 28",
    "sg:postcode":"6600",
    "sg:province":"Ticino",
    "wof:name":"Farmacia Luciano Ronchi & Figlio",
    "wof:placetype":"venue"
},
  "geometry": {"coordinates":[9.0076999664,45.8654785156],"type":"Point"}
}