{
  "type": "Feature",
  "properties": {
    "iso:country":"CH",
    "sg:address":"Amsler-laffon-strasse 3",
    "sg:city":"Schaffhausen",
    "sg:orig_category":"Softwareentwicklung U beratung",
    "sg:phone":"+41 52252731",
    "sg:postcode":"8200",
    "sg:province":"Schaffhausen",
    "wof:name":"Eichhorn Informatik",
    "wof:placetype":"venue"
},
  "geometry": {"coordinates":[8.6425094604,47.707698822],"type":"Point"}
}