{
  "type": "Feature",
  "properties": {
    "iso:country":"CH",
    "sg:address":"R\u00fctihofstrasse 27",
    "sg:city":"Z\u00fcrich",
    "sg:orig_category":"Geb\u00e4ude, Wohnungsreinigung Reinigungsgewerbe",
    "sg:phone":"+41 13411623",
    "sg:postcode":"8049",
    "sg:province":"Z\u00fcrich",
    "wof:name":"Rauscher Reinigungen",
    "wof:placetype":"venue"
},
  "geometry": {"coordinates":[8.4783859253,47.4141578674],"type":"Point"}
}