{
  "type": "Feature",
  "properties": {
    "iso:country":"CH",
    "sg:address":"Friedensgasse 52 4056 Basel. Postfach",
    "sg:city":"Basel",
    "sg:orig_category":"Druckgewerbe Offsetdruck",
    "sg:phone":"+41 61 381 50 06",
    "sg:postcode":"4012",
    "sg:province":"Basel-Stadt",
    "wof:name":"Kurt Fankhauser Ag Buch Und Offsetdruckerei",
    "wof:placetype":"venue"
},
  "geometry": {"coordinates":[7.5767908096,47.5617866516],"type":"Point"}
}