{
  "type": "Feature",
  "properties": {
    "iso:country":"CH",
    "sg:address":"Lindenstrasse 34",
    "sg:city":"Buttwil",
    "sg:classifiers":[
        {
            "category":"Tea Room",
            "subcategory":"None",
            "type":"Food & Drink"
        }
    ],
    "sg:phone":"+41 56 664 42 03",
    "sg:postcode":"5632",
    "sg:province":"Aargau",
    "sg:tags":[
        "plaster"
    ],
    "wof:name":"E. L\u00fcthi Gmbh Gipsergesch\u00e4ft",
    "wof:placetype":"venue"
},
  "geometry": {"coordinates":[8.3112125397,47.2652282715],"type":"Point"}
}