{
  "type": "Feature",
  "properties": {
    "iso:country":"CH",
    "sg:address":"Platte 18 8755 Ennenda. Postfach",
    "sg:city":"Ennenda",
    "sg:orig_category":"Reiseb\u00fcros U Reiseveranstalter",
    "sg:postcode":"8755",
    "sg:province":"Glarus",
    "wof:name":"Rossini Andrea Weinreisen Weinreisen Usw.; Planung, Organisation",
    "wof:placetype":"venue"
},
  "geometry": {"coordinates":[9.0827188492,47.0316467285],"type":"Point"}
}