{
  "type": "Feature",
  "properties": {
    "iso:country":"CH",
    "sg:address":"Hauptstrasse 37",
    "sg:city":"F\u00fcllinsdorf",
    "sg:orig_category":"Kosmetikinstitute",
    "sg:phone":"+41 61 751 58 82",
    "sg:postcode":"4414",
    "sg:province":"Basel-Landschaft",
    "wof:name":"Monika Hasler Kosmetik-k\u00e4mmerli",
    "wof:placetype":"venue"
},
  "geometry": {"coordinates":[7.5952339172,47.470451355],"type":"Point"}
}