{
  "type": "Feature",
  "properties": {
    "iso:country":"CH",
    "sg:address":"Alte L\u00fctzelfl\u00fchstrasse 20",
    "sg:city":"Hasle-r\u00fcegsau",
    "sg:orig_category":"Autogaragen",
    "sg:phone":"+41 32 968 25 28",
    "sg:postcode":"3415",
    "sg:province":"Bern",
    "wof:name":"Daniel Tarditi Garage",
    "wof:placetype":"venue"
},
  "geometry": {"coordinates":[6.84126,47.10899],"type":"Point"}
}