{
  "type": "Feature",
  "properties": {
    "iso:country":"CH",
    "sg:address":"6563",
    "sg:city":"Mesocco",
    "sg:orig_category":"Vorschulen, Kinderg\u00e4rten",
    "sg:phone":"+41 91 831 11 18",
    "sg:postcode":"6563",
    "sg:province":"Graubunden",
    "wof:name":"Scuola Materna",
    "wof:placetype":"venue"
},
  "geometry": {"coordinates":[9.2328996658,46.3916320801],"type":"Point"}
}