{
  "type": "Feature",
  "properties": {
    "iso:country":"CH",
    "sg:address":"Unterm\u00fcli 6 6300 Zug. Postfach",
    "sg:city":"Walchwil",
    "sg:orig_category":"Pensionskassen",
    "sg:postcode":"6318",
    "sg:province":"Zug",
    "wof:name":"Personalf\u00fcrsorgestiftung F\u00fcr Handel Und Gewerbe Zug",
    "wof:placetype":"venue"
},
  "geometry": {"coordinates":[8.5216379166,47.167224884],"type":"Point"}
}