{
  "type": "Feature",
  "properties": {
    "iso:country":"CH",
    "sg:address":"Barboleusaz La",
    "sg:city":"Gryon",
    "sg:orig_category":"Vermietung U Verpachtung von eigenen Immobilien",
    "sg:phone":"+41 79 212 77 14",
    "sg:postcode":"1882",
    "sg:province":"Vaud",
    "wof:name":"Paysages Services Sa Immeubles. Jardinage, Paysagistes Etc.; Travaux",
    "wof:placetype":"venue"
},
  "geometry": {"coordinates":[7.0722770691,46.2830963135],"type":"Point"}
}