{
  "type": "Feature",
  "properties": {
    "iso:country":"CH",
    "sg:address":"Saint-fran\u00e7ois Place 1 1003 Lausanne. Postfach",
    "sg:city":"Lausanne",
    "sg:orig_category":"Vermietung U Verpachtung von eigenen Immobilien",
    "sg:postcode":"1003",
    "sg:province":"Vaud",
    "wof:name":"Le Cottage C Sa",
    "wof:placetype":"venue"
},
  "geometry": {"coordinates":[5.1808700562,45.8973388672],"type":"Point"}
}