{
  "type": "Feature",
  "properties": {
    "iso:country":"CH",
    "sg:address":"R\u00fcbibachstrasse 4",
    "sg:city":"Ennetmoos",
    "sg:orig_category":"G\u00fcterbef\u00f6rderung im Strassenverkehr",
    "sg:postcode":"6372",
    "sg:province":"Nidwalden",
    "wof:name":"Menzi Paketlogistik",
    "wof:placetype":"venue"
},
  "geometry": {"coordinates":[8.3080463409,46.9342880249],"type":"Point"}
}