{
  "type": "Feature",
  "properties": {
    "iso:country":"CH",
    "sg:address":"Flurstrasse 14",
    "sg:city":"Kloten",
    "sg:orig_category":"Softwareentwicklung U beratung",
    "sg:phone":"+41 18811575",
    "sg:postcode":"8302",
    "sg:province":"Z\u00fcrich",
    "wof:name":"Ask Milo Milesevic Nikola",
    "wof:placetype":"venue"
},
  "geometry": {"coordinates":[8.5915336609,47.4539260864],"type":"Point"}
}