{
  "type": "Feature",
  "properties": {
    "iso:country":"CH",
    "sg:address":"M\u00e4rit 1",
    "sg:city":"Erlach",
    "sg:orig_category":"Sportvereine Eissport Curling",
    "sg:phone":"+41 32 338 51 80",
    "sg:postcode":"3235",
    "sg:province":"Bern",
    "wof:name":"J & S Fachleiter",
    "wof:placetype":"venue"
},
  "geometry": {"coordinates":[7.0960650444,47.0438957214],"type":"Point"}
}