{
  "type": "Feature",
  "properties": {
    "iso:country":"CH",
    "sg:address":"Seewiesenstrasse 10 8597 Landschlacht. Postfach 18",
    "sg:city":"Landschlacht",
    "sg:orig_category":"Unternehmensberatung",
    "sg:phone":"+41 71 695 12 22",
    "sg:postcode":"8597",
    "sg:province":"Thurgau",
    "wof:name":"Dietrich Consulting",
    "wof:placetype":"venue"
},
  "geometry": {"coordinates":[9.2515354156,47.626991272],"type":"Point"}
}