{
  "type": "Feature",
  "properties": {
    "addr:full":"Hausmatt 6 Steinen Schwyz 6422",
    "addr:housenumber":"6",
    "addr:postcode":"6422",
    "addr:street":"Hausmatt;Schwyz",
    "iso:country":"CH",
    "sg:address":"Hausmatt 6",
    "sg:city":"Steinen",
    "sg:orig_category":"Architektur U Ingenieurb\u00fcros",
    "sg:phone":"+41 55 240 62 13",
    "sg:postcode":"6422",
    "sg:province":"Schwyz",
    "wof:name":"Architekturb\u00fcro Baumgartner H. Ag",
    "wof:placetype":"venue"
},
  "geometry": {"coordinates":[8.866158,47.26619],"type":"Point"}
}