{
  "type": "Feature",
  "properties": {
    "iso:country":"CH",
    "sg:address":"Zelgstrasse 3 3715 Adelboden. Postfach",
    "sg:city":"Adelboden",
    "sg:orig_category":"Polizei",
    "sg:phone":"+41 33 671 81 41",
    "sg:postcode":"3715",
    "sg:province":"Bern",
    "wof:name":"Kantonale Polizei",
    "wof:placetype":"venue"
},
  "geometry": {"coordinates":[7.5604357719,46.4922218323],"type":"Point"}
}