{
  "type": "Feature",
  "properties": {
    "iso:country":"CH",
    "sg:address":"Glutz-blotzheimstr. 3 4500 Solothurn. Postfach",
    "sg:city":"Solothurn",
    "sg:orig_category":"Unternehmensberatung",
    "sg:phone":"+41 32 625 99 70",
    "sg:postcode":"4502",
    "sg:province":"Solothurn",
    "wof:name":"Awd Allgemeiner Wirtschaftsdienst, Agentur Buchmeier R.",
    "wof:placetype":"venue"
},
  "geometry": {"coordinates":[7.5287308693,47.2020111084],"type":"Point"}
}