{
  "type": "Feature",
  "properties": {
    "iso:country":"CH",
    "sg:address":"Thunstrasse 4",
    "sg:city":"Bern",
    "sg:orig_category":"Versicherungen Hauptagenturen",
    "sg:phone":"+41 31 302 11 44",
    "sg:postcode":"3005",
    "sg:province":"Bern",
    "wof:name":"Winterthur-versicherungen Hauptagentur Bern-l\u00e4nggasse",
    "wof:placetype":"venue"
},
  "geometry": {"coordinates":[7.4340791702,46.9522705078],"type":"Point"}
}