{
  "type": "Feature",
  "properties": {
    "iso:country":"CH",
    "sg:address":"Cadogno 6614 Brissago. Postfach Caselle Postale 626",
    "sg:city":"Brissago",
    "sg:orig_category":"Betrieb von Taxis G\u00fcterbef\u00f6rderung im Strassenverkehr",
    "sg:phone":"+41 91 793 03 03",
    "sg:postcode":"6614",
    "sg:province":"Ticino",
    "wof:name":"Franceschino Prato Autotrasporti & Tassi",
    "wof:placetype":"venue"
},
  "geometry": {"coordinates":[8.705838,46.119301],"type":"Point"}
}