{
  "type": "Feature",
  "properties": {
    "iso:country":"CH",
    "sg:address":"St. Anna-schloss-strasse 6",
    "sg:city":"Rorschacherberg",
    "sg:orig_category":"G\u00fcterbef\u00f6rderung im Strassenverkehr Vermietung U Verpachtung von eigenen Immobilien",
    "sg:phone":"+41 71 855 53 33",
    "sg:postcode":"9404",
    "sg:province":"St. Gallen",
    "wof:name":"Willy Dornbierer Ag",
    "wof:placetype":"venue"
},
  "geometry": {"coordinates":[9.4858942032,47.4682922363],"type":"Point"}
}