{
  "type": "Feature",
  "properties": {
    "iso:country":"CH",
    "sg:address":"L\u00e9cheretta Rue De La 9",
    "sg:city":"Bulle",
    "sg:orig_category":"Sonstige pers\u00f6nliche Dienstleistungen",
    "sg:phone":"+41 26 919 59 49",
    "sg:postcode":"1630",
    "sg:province":"Fribourg",
    "wof:name":"Optigestion Sa",
    "wof:placetype":"venue"
},
  "geometry": {"coordinates":[7.0555028915,46.6190223694],"type":"Point"}
}