{
  "type": "Feature",
  "properties": {
    "iso:country":"CH",
    "sg:address":"Zeughausgasse 35/37",
    "sg:city":"Bern",
    "sg:orig_category":"Detailhandel mit B\u00fcchern, Zeitungen, Schreib U Papeteriewaren",
    "sg:postcode":"3005",
    "sg:province":"Bern",
    "wof:name":"Vivace - Buchhandlung Feg Bern",
    "wof:placetype":"venue"
},
  "geometry": {"coordinates":[7.444756,46.94891],"type":"Point"}
}