{
  "type": "Feature",
  "properties": {
    "iso:country":"CH",
    "sg:address":"Schitterstrasse 2",
    "sg:city":"Oberegg",
    "sg:classifiers":[
        {
            "category":"Insurance",
            "subcategory":"Insurance Agent",
            "type":"Services"
        }
    ],
    "sg:phone":"+41 71 891 23 55",
    "sg:postcode":"9413",
    "sg:province":"Appenzell Innerhoden",
    "sg:tags":[
        "versicherungsagenturen",
        "-broker"
    ],
    "wof:name":"Helvetia Patria Versicherungen Agentur",
    "wof:placetype":"venue"
},
  "geometry": {"coordinates":[9.5523891449,47.4250564575],"type":"Point"}
}