{
  "type": "Feature",
  "properties": {
    "iso:country":"CH",
    "sg:address":"Winterthurerstrasse 661",
    "sg:city":"Z\u00fcrich",
    "sg:orig_category":"Herstellung von sonstigen Maschinen f\u00fcr unspezifische Verwendung",
    "sg:postcode":"8051",
    "sg:province":"Z\u00fcrich",
    "wof:name":"Geibel Werner Apparatebau",
    "wof:placetype":"venue"
},
  "geometry": {"coordinates":[8.3153133392,46.9894943237],"type":"Point"}
}