{
  "type": "Feature",
  "properties": {
    "iso:country":"CH",
    "sg:address":"Avenue Agassiz 2 1003 Lausanne. Postfach",
    "sg:city":"Lausanne",
    "sg:orig_category":"Wirtschaftsverb\u00e4nde Industrie, Handel and Gewerbe",
    "sg:phone":"+41 21 319 71 11",
    "sg:postcode":"1001",
    "sg:province":"Vaud",
    "wof:name":"Assoc.vaudoise Des D\u00e9taillants En Textiles Avdt",
    "wof:placetype":"venue"
},
  "geometry": {"coordinates":[6.631734848,46.518119812],"type":"Point"}
}