{
  "type": "Feature",
  "properties": {
    "iso:country":"CH",
    "sg:address":"1913",
    "sg:city":"Saillon",
    "sg:orig_category":"Blumen U Zierpflanzenbau Gem\u00fcsebau",
    "sg:phone":"+41 27 744 13 97",
    "sg:postcode":"1913",
    "sg:province":"Valais",
    "wof:name":"Louis & Edith Cheseaux Etablissement Horticole",
    "wof:placetype":"venue"
},
  "geometry": {"coordinates":[7.1853,46.171909],"type":"Point"}
}