{
  "type": "Feature",
  "properties": {
    "iso:country":"CH",
    "sg:address":"Villette Rue De La 15",
    "sg:city":"Yverdon-les-bains",
    "sg:classifiers":[
        {
            "category":"Professional",
            "subcategory":"Employment Agencies",
            "type":"Services"
        }
    ],
    "sg:postcode":"1400",
    "sg:province":"Vaud",
    "sg:tags":[
        "personal",
        "u",
        "stellenvermittlung"
    ],
    "wof:name":"Boy And Girl, Mathey Alain",
    "wof:placetype":"venue"
},
  "geometry": {"coordinates":[6.6414198875,46.7786331177],"type":"Point"}
}