{
  "type": "Feature",
  "properties": {
    "iso:country":"CH",
    "sg:address":"Hauptstrasse 143",
    "sg:city":"Aesch",
    "sg:classifiers":[
        {
            "category":"Shopping",
            "subcategory":"Department Store",
            "type":"Retail Goods"
        }
    ],
    "sg:phone":"+41 41 917 33 18",
    "sg:postcode":"6287",
    "sg:province":"Luzern",
    "sg:tags":[
        "linen",
        "bed"
    ],
    "wof:name":"Land And Sky Wasserbetten Ag",
    "wof:placetype":"venue"
},
  "geometry": {"coordinates":[8.239444,47.260876],"type":"Point"}
}