{
  "type": "Feature",
  "properties": {
    "iso:country":"CH",
    "sg:address":"Vicolo Nassetta 2",
    "sg:city":"Lugano",
    "sg:orig_category":"Handels-H\u00e4user U Gesellschaften",
    "sg:phone":"+41 71 766 22 44",
    "sg:postcode":"6900",
    "sg:province":"Ticino",
    "wof:name":"Klant - Peperoni - Design",
    "wof:placetype":"venue"
},
  "geometry": {"coordinates":[9.5413999557,47.2958374023],"type":"Point"}
}