{
  "type": "Feature",
  "properties": {
    "iso:country":"CH",
    "sg:address":"Mattweg 177",
    "sg:city":"Arlesheim",
    "sg:orig_category":"Sonstige mit der Informatik verbundene T\u00e4tigkeiten",
    "sg:postcode":"4144",
    "sg:province":"Basel-Landschaft",
    "wof:name":"Bitech, Miluska Ivan Dipl. Ing.",
    "wof:placetype":"venue"
},
  "geometry": {"coordinates":[7.6173329353,47.5060043335],"type":"Point"}
}