{
  "type": "Feature",
  "properties": {
    "iso:country":"CH",
    "sg:address":"Fabrikstrasse 15 8000 Z\u00fcrich. Postfach",
    "sg:city":"Z\u00fcrich",
    "sg:orig_category":"Softwareentwicklung U beratung",
    "sg:phone":"+41 12727740",
    "sg:postcode":"8001",
    "sg:province":"Z\u00fcrich",
    "wof:name":"Interlogics Gmbh",
    "wof:placetype":"venue"
},
  "geometry": {"coordinates":[8.5283088684,47.3866424561],"type":"Point"}
}