{
  "type": "Feature",
  "properties": {
    "iso:country":"CH",
    "sg:address":"Kalchb\u00fchlstrasse 163",
    "sg:city":"Z\u00fcrich",
    "sg:orig_category":"Detailhandel mit Damenbekleidung",
    "sg:phone":"+41 71 220 30 15",
    "sg:postcode":"8038",
    "sg:province":"Z\u00fcrich",
    "wof:name":"Weber Bekleidung Ag",
    "wof:placetype":"venue"
},
  "geometry": {"coordinates":[-90.405624,42.392254],"type":"Point"}
}