{
  "type": "Feature",
  "properties": {
    "iso:country":"CH",
    "sg:address":"Hallwylstrasse 54",
    "sg:city":"Z\u00fcrich",
    "sg:orig_category":"Gesundheitswesen",
    "sg:phone":"+41 12427574",
    "sg:postcode":"8004",
    "sg:province":"Z\u00fcrich",
    "wof:name":"Massagepraxis Blaser Andrea Dienstleistungen Im Bereich Gesundheitsf\u00f6rderung Und Pr\u00e4vention",
    "wof:placetype":"venue"
},
  "geometry": {"coordinates":[8.5279035568,47.3708686829],"type":"Point"}
}