{
  "type": "Feature",
  "properties": {
    "iso:country":"CH",
    "sg:address":"Flughofstrasse",
    "sg:city":"Kloten",
    "sg:orig_category":"Unclassifiable Establishments",
    "sg:phone":"+41 18126908",
    "sg:postcode":"8302",
    "sg:province":"Z\u00fcrich",
    "wof:name":"Sr Technics Group Bau Und Werkplanung Tfw",
    "wof:placetype":"venue"
},
  "geometry": {"coordinates":[8.5671606064,47.4411010742],"type":"Point"}
}