{
  "type": "Feature",
  "properties": {
    "iso:country":"CH",
    "sg:address":"Z\u00fcrcherstrasse 308",
    "sg:city":"Frauenfeld",
    "sg:orig_category":"Grosshandel mit Eisenwaren sowie Installationsbedarf f\u00fcr Gas, Wasser U Heizung Grosshandel mit Masch",
    "sg:phone":"+41 52 723 26 26",
    "sg:postcode":"8500",
    "sg:province":"Thurgau",
    "wof:name":"Wasu Suter Walter Ag",
    "wof:placetype":"venue"
},
  "geometry": {"coordinates":[8.9108076096,47.5646781921],"type":"Point"}
}