{
  "type": "Feature",
  "properties": {
    "iso:country":"CH",
    "sg:address":"Ruezenwil",
    "sg:city":"Bernhardzell",
    "sg:orig_category":"Haltung von Schweinen",
    "sg:phone":"+41 71 298 51 06",
    "sg:postcode":"9304",
    "sg:province":"St. Gallen",
    "wof:name":"Bartholet Peter, Schweinez\u00fcchter.",
    "wof:placetype":"venue"
},
  "geometry": {"coordinates":[9.3354454041,47.4729347229],"type":"Point"}
}