{
  "type": "Feature",
  "properties": {
    "iso:country":"CH",
    "sg:address":"Rue Du Casino 53",
    "sg:city":"Montreux",
    "sg:orig_category":"Non-Classified Establishments",
    "sg:postcode":"1820",
    "sg:province":"Vaud",
    "wof:name":"Acl Diffusion S\u00e0rl",
    "wof:placetype":"venue"
},
  "geometry": {"coordinates":[6.9106731415,46.4308738708],"type":"Point"}
}