{
  "type": "Feature",
  "properties": {
    "iso:country":"CH",
    "sg:address":"Bettlachstrasse 23",
    "sg:city":"Grenchen",
    "sg:orig_category":"Versicherungen Hauptagenturen",
    "sg:phone":"+41 32 653 19 14",
    "sg:postcode":"2540",
    "sg:province":"Solothurn",
    "wof:name":"Rentenanstalt/swiss Life Bezirksagentur",
    "wof:placetype":"venue"
},
  "geometry": {"coordinates":[7.3976249695,47.1932182312],"type":"Point"}
}