{
  "type": "Feature",
  "properties": {
    "iso:country":"CH",
    "sg:address":"Bahnhofstrasse 47",
    "sg:city":"Otelfingen",
    "sg:orig_category":"RESTAURANTS: TEA-ROOMS",
    "sg:phone":"+41 41 870 28 66",
    "sg:postcode":"8112",
    "sg:province":"Z\u00fcrich",
    "wof:name":"Furrer H. Restaurant Eggberge",
    "wof:placetype":"venue"
},
  "geometry": {"coordinates":[8.639749527,46.8880310059],"type":"Point"}
}