{
  "type": "Feature",
  "properties": {
    "iso:country":"CH",
    "sg:address":"Grande-rue 84",
    "sg:city":"Ponts-de-martel",
    "sg:classifiers":[
        {
            "category":"Insurance",
            "subcategory":"Insurance Agent",
            "type":"Services"
        }
    ],
    "sg:phone":"+41 32 937 19 00",
    "sg:postcode":"2316",
    "sg:province":"Neuch\u00e2tel",
    "sg:tags":[
        "versicherungsagenturen",
        "-broker"
    ],
    "wof:name":"Luc Geiser Conseils En Assurances",
    "wof:placetype":"venue"
},
  "geometry": {"coordinates":[6.7226371765,46.9956436157],"type":"Point"}
}