{
  "type": "Feature",
  "properties": {
    "iso:country":"CH",
    "sg:address":"1735",
    "sg:city":"Giffers",
    "sg:orig_category":"RESTAURANTS: TEA-ROOMS",
    "sg:postcode":"1735",
    "sg:province":"Fribourg",
    "wof:name":"Rumpf Christian & Evelyne, La Cord\u00e9e",
    "wof:placetype":"venue"
},
  "geometry": {"coordinates":[7.508395195,46.0821838379],"type":"Point"}
}