{
  "type": "Feature",
  "properties": {
    "iso:country":"CH",
    "sg:address":"Grand'rue 18",
    "sg:city":"Founex",
    "sg:orig_category":"Rebbau",
    "sg:phone":"+41 22 776 11 80",
    "sg:postcode":"1297",
    "sg:province":"Vaud",
    "wof:name":"Domaine De La Treille & De La Doye",
    "wof:placetype":"venue"
},
  "geometry": {"coordinates":[6.1922469139,46.3314247131],"type":"Point"}
}