{
  "type": "Feature",
  "properties": {
    "iso:country":"CH",
    "sg:address":"Rue De Gibraltar 20",
    "sg:city":"Neuch\u00e2tel",
    "sg:orig_category":"Sonstiger Fachdetailhandel mit Nahrungsmitteln, Getr\u00e4nken U Tabak in Verkaufsr\u00e4umen",
    "sg:phone":"+41 32 725 14 13",
    "sg:postcode":"2000",
    "sg:province":"Neuch\u00e2tel",
    "wof:name":"Bio-source, Martin Kr\u00e4henb\u00fchl",
    "wof:placetype":"venue"
},
  "geometry": {"coordinates":[6.9441900253,46.9979362488],"type":"Point"}
}