{
  "type": "Feature",
  "properties": {
    "iso:country":"CH",
    "sg:address":"Ch.de La Petite-boissi\u00e8re 1200 Gen\u00e8ve. Postfach",
    "sg:city":"Gen\u00e8ve",
    "sg:orig_category":"Fotografisches Gewerbe U fotografische Laboratorien",
    "sg:postcode":"1208",
    "sg:province":"Gen\u00e8ve",
    "wof:name":"Jordan Didier",
    "wof:placetype":"venue"
},
  "geometry": {"coordinates":[6.1703248024,46.1990585327],"type":"Point"}
}