{
  "type": "Feature",
  "properties": {
    "iso:country":"CH",
    "sg:address":"Schulhausstrasse 1",
    "sg:city":"Horw",
    "sg:orig_category":"Non-Classified Establishments",
    "sg:phone":"+41 62 929 19 80",
    "sg:postcode":"6048",
    "sg:province":"Luzern",
    "wof:name":"E. Rosner",
    "wof:placetype":"venue"
},
  "geometry": {"coordinates":[7.8011798859,47.2409095764],"type":"Point"}
}