{
  "type": "Feature",
  "properties": {
    "iso:country":"CH",
    "sg:address":"Rest. Adler",
    "sg:city":"Glarus",
    "sg:orig_category":"Bau von Strassen, Sportanlagen U Bahnverkehrsstrecken",
    "sg:phone":"+41 55 640 18 28",
    "sg:postcode":"8750",
    "sg:province":"Glarus",
    "wof:name":"Wirth Paul",
    "wof:placetype":"venue"
},
  "geometry": {"coordinates":[9.06809,47.03997],"type":"Point"}
}