{
  "type": "Feature",
  "properties": {
    "iso:country":"CH",
    "sg:address":"Rautistrasse 77",
    "sg:city":"Z\u00fcrich",
    "sg:orig_category":"Softwareentwicklung U beratung",
    "sg:phone":"+41 14051940633423",
    "sg:postcode":"8048",
    "sg:province":"Z\u00fcrich",
    "wof:name":"Blue Chips Informatik Ag",
    "wof:placetype":"venue"
},
  "geometry": {"coordinates":[8.4867010117,47.3824958801],"type":"Point"}
}