{
  "type": "Feature",
  "properties": {
    "iso:country":"CH",
    "sg:address":"Florastrasse 40",
    "sg:city":"Basel",
    "sg:orig_category":"Finanzierungsinstitutionen Unternehmensberatung",
    "sg:phone":"+41 61 692 57 23",
    "sg:postcode":"4057",
    "sg:province":"Basel-Stadt",
    "wof:name":"Hudson-rhine Consulting, R. Koppay",
    "wof:placetype":"venue"
},
  "geometry": {"coordinates":[7.5885128975,47.5641403198],"type":"Point"}
}