{
  "type": "Feature",
  "properties": {
    "iso:country":"CH",
    "sg:address":"Holz 780",
    "sg:city":"Wolfhalden",
    "sg:orig_category":"Grosshandel mit Holz U Baustoffen Hoch U Tiefbau",
    "sg:phone":"+41 52 383 29 08",
    "sg:postcode":"9427",
    "sg:province":"Appenzell Ausserrhoden",
    "wof:name":"Schwyter Leo Ag",
    "wof:placetype":"venue"
},
  "geometry": {"coordinates":[8.8003911972,47.4425888062],"type":"Point"}
}