{
  "type": "Feature",
  "properties": {
    "iso:country":"CH",
    "sg:address":"Avenue Adrien-jeandin 7",
    "sg:city":"Th\u00f4nex",
    "sg:orig_category":"Zahnkliniken",
    "sg:phone":"+41 22 796 44 45",
    "sg:postcode":"1226",
    "sg:province":"Gen\u00e8ve",
    "wof:name":"Clinique Dentaire Ecole Avanchet-sal\u00e8ve",
    "wof:placetype":"venue"
},
  "geometry": {"coordinates":[6.1095972061,46.2202796936],"type":"Point"}
}