{
  "type": "Feature",
  "properties": {
    "iso:country":"CH",
    "sg:address":"B\u00fchlstrasse 49",
    "sg:city":"Egerkingen",
    "sg:orig_category":"Offsetdruck Satzherstellung U Reproduktion",
    "sg:phone":"+41 71 227 18 40",
    "sg:postcode":"4622",
    "sg:province":"Solothurn",
    "wof:name":"Indicolor Ag",
    "wof:placetype":"venue"
},
  "geometry": {"coordinates":[9.2937202454,47.4073410034],"type":"Point"}
}