{
  "type": "Feature",
  "properties": {
    "iso:country":"CH",
    "sg:address":"Torackerstrasse 3",
    "sg:city":"Herisau",
    "sg:orig_category":"Naturheil\u00e4rzte and Heilpraktiker",
    "sg:phone":"+41 71 351 14 63",
    "sg:postcode":"9100",
    "sg:province":"Appenzell Ausserrhoden",
    "wof:name":"Nicola Liebich Naturheilpraxis",
    "wof:placetype":"venue"
},
  "geometry": {"coordinates":[9.2809324265,47.3847846985],"type":"Point"}
}