{
  "type": "Feature",
  "properties": {
    "iso:country":"CH",
    "sg:address":"Roseng\u00e4ssli 12 6003 Luzern. Postfach",
    "sg:city":"Luzern",
    "sg:orig_category":"Grosshandel mit sonstigen Gebrauchs U Verbrauchsg\u00fctern",
    "sg:phone":"+41 41 210 90 03",
    "sg:postcode":"6003",
    "sg:province":"Luzern",
    "wof:name":"R. Ruckli + Co Ag Edelsteinhandel, Schmuck Usw; Handel",
    "wof:placetype":"venue"
},
  "geometry": {"coordinates":[8.3033943176,47.0506095886],"type":"Point"}
}