{
  "type": "Feature",
  "properties": {
    "iso:country":"CH",
    "sg:address":"M\u00fchlebr\u00fccke",
    "sg:city":"Biel/bienne",
    "sg:orig_category":"Architektur U Ingenieurb\u00fcros Informatikdienste",
    "sg:phone":"+41 31 333 44 40",
    "sg:postcode":"2502",
    "sg:province":"Bern",
    "wof:name":"Alras Gmbh",
    "wof:placetype":"venue"
},
  "geometry": {"coordinates":[7.4546580315,46.9572143555],"type":"Point"}
}