{
  "type": "Feature",
  "properties": {
    "iso:country":"CH",
    "sg:address":"Bellinzona Via 19",
    "sg:city":"Biasca",
    "sg:orig_category":"Sonstiger Grosshandel",
    "sg:phone":"+41 71 288 62 44",
    "sg:postcode":"6710",
    "sg:province":"Ticino",
    "wof:name":"Santschi Esther Waren; Handel",
    "wof:placetype":"venue"
},
  "geometry": {"coordinates":[9.4186496735,47.4378471375],"type":"Point"}
}