{
  "type": "Feature",
  "properties": {
    "iso:country":"CH",
    "sg:address":"Neubergweg 28",
    "sg:city":"Therwil",
    "sg:orig_category":"G\u00fcterbef\u00f6rderung im Strassenverkehr",
    "sg:phone":"+41 61 721 49 38",
    "sg:postcode":"4106",
    "sg:province":"Basel-Landschaft",
    "wof:name":"United Forwarders Ltd",
    "wof:placetype":"venue"
},
  "geometry": {"coordinates":[7.5660710335,47.5029792786],"type":"Point"}
}