{
  "type": "Feature",
  "properties": {
    "iso:country":"CH",
    "sg:address":"Hauptstrasse 61",
    "sg:city":"Kriegstetten",
    "sg:orig_category":"Wirtschafts- and Arbeitgeberverb\u00e4nde",
    "sg:postcode":"4566",
    "sg:province":"Solothurn",
    "wof:name":"Hotelier-verein St.moritz Herrn Andrea Badrutt",
    "wof:placetype":"venue"
},
  "geometry": {"coordinates":[9.8381910324,46.4970664978],"type":"Point"}
}