{
  "type": "Feature",
  "properties": {
    "iso:country":"CH",
    "sg:address":"Macconnens",
    "sg:city":"Villarimboud",
    "sg:orig_category":"Herstellung von sonstigen landwirtschaftlichen Maschinen Instandhaltung U Reparatur von Automobilen",
    "sg:phone":"+41 79 427 04 26",
    "sg:postcode":"1691",
    "sg:province":"Fribourg",
    "wof:name":"Georges Moullet Garage & Machines Agricoles",
    "wof:placetype":"venue"
},
  "geometry": {"coordinates":[6.9633450508,46.7408638],"type":"Point"}
}