{
  "type": "Feature",
  "properties": {
    "iso:country":"CH",
    "sg:address":"Z\u00f6llistrasse 23",
    "sg:city":"Uhwiesen",
    "sg:orig_category":"Berufliche Weiterbildung, Erwachsenenbildung",
    "sg:phone":"+41 52 659 11 10",
    "sg:postcode":"8248",
    "sg:province":"Z\u00fcrich",
    "wof:name":"Volkshochschule",
    "wof:placetype":"venue"
},
  "geometry": {"coordinates":[8.627899,47.673653],"type":"Point"}
}