{
  "type": "Feature",
  "properties": {
    "iso:country":"CH",
    "sg:address":"6982",
    "sg:city":"Agno",
    "sg:orig_category":"Grosshandel mit B\u00fcromaschinen Herstellung von sonstigen Waren aus Papier, Karton U Pappe",
    "sg:phone":"+41 61 482 12 12",
    "sg:postcode":"6982",
    "sg:province":"Ticino",
    "wof:name":"Schoba Handel, Schoch Peter",
    "wof:placetype":"venue"
},
  "geometry": {"coordinates":[7.5463089943,47.5586013794],"type":"Point"}
}