{
  "type": "Feature",
  "properties": {
    "iso:country":"CH",
    "sg:address":"Hauptstrasse 23",
    "sg:city":"Sch\u00fcpbach",
    "sg:orig_category":"Herstellung von sonstigen landwirtschaftlichen Maschinen Mechanische Werkst\u00e4tten",
    "sg:phone":"+41 34 497 21 00",
    "sg:postcode":"3535",
    "sg:province":"Bern",
    "wof:name":"Hans L\u00fcthi Landmaschinen",
    "wof:placetype":"venue"
},
  "geometry": {"coordinates":[7.7346858978,46.9285049438],"type":"Point"}
}