{
  "type": "Feature",
  "properties": {
    "iso:country":"CH",
    "sg:address":"Rue D'oche 17",
    "sg:city":"Martigny",
    "sg:orig_category":"RESTAURANTS: TEA-ROOMS",
    "sg:postcode":"1920",
    "sg:province":"Valais",
    "wof:name":"Moret, Berthold",
    "wof:placetype":"venue"
},
  "geometry": {"coordinates":[6.8572998047,46.6518135071],"type":"Point"}
}