{
  "type": "Feature",
  "properties": {
    "iso:country":"CH",
    "sg:address":"Hinterhofstrasse 5",
    "sg:city":"Kleinandelfingen",
    "sg:orig_category":"Vereine Damen Vereine Gesang",
    "sg:phone":"+41 52 317 29 56",
    "sg:postcode":"8451",
    "sg:province":"Z\u00fcrich",
    "wof:name":"Frauen-& T\u00f6chterchor",
    "wof:placetype":"venue"
},
  "geometry": {"coordinates":[8.6834354401,47.5986557007],"type":"Point"}
}