{
  "type": "Feature",
  "properties": {
    "iso:country":"CH",
    "sg:address":"Utengasse 16 4058 Basel. Postfach",
    "sg:city":"Basel",
    "sg:orig_category":"Pensionskassen",
    "sg:phone":"+41 61 681 51 51",
    "sg:postcode":"4051",
    "sg:province":"Basel-Stadt",
    "wof:name":"Vorsorgestiftung Der Willy A. Bachofen Ag (bvg)",
    "wof:placetype":"venue"
},
  "geometry": {"coordinates":[7.5923838615,47.5606155396],"type":"Point"}
}