{
  "type": "Feature",
  "properties": {
    "iso:country":"CH",
    "sg:address":"Schl\u00fcssbergstrasse 1160",
    "sg:city":"Gr\u00fcningen",
    "sg:orig_category":"Detailhandel mit Fahrr\u00e4dern Handel mit Motorr\u00e4dern, Teilen U Zubeh\u00f6r Instandhaltung U Reparatur von ",
    "sg:phone":"+41 19352037",
    "sg:postcode":"8627",
    "sg:province":"Z\u00fcrich",
    "wof:name":"Peter Fr\u00f6hlich Velos Motos",
    "wof:placetype":"venue"
},
  "geometry": {"coordinates":[8.7556877136,47.2779197693],"type":"Point"}
}