{
  "type": "Feature",
  "properties": {
    "iso:country":"CH",
    "sg:address":"Chamerstrasse 30",
    "sg:city":"Zug",
    "sg:orig_category":"Unclassifiable Establishments",
    "sg:postcode":"6300",
    "sg:province":"Zug",
    "wof:name":"Romag Holding Ag",
    "wof:placetype":"venue"
},
  "geometry": {"coordinates":[8.5089349747,47.1728401184],"type":"Point"}
}