{
  "type": "Feature",
  "properties": {
    "iso:country":"CH",
    "sg:address":"Via Ai Molini 5",
    "sg:city":"Losone",
    "sg:orig_category":"Herstellung von k\u00e4lte U lufttechnischen Erzeugnissen f\u00fcr gewerbliche Zwecke Maschinen and Apparate d",
    "sg:phone":"+41 91 780 56 00",
    "sg:postcode":"6616",
    "sg:province":"Ticino",
    "wof:name":"Fresco Sa",
    "wof:placetype":"venue"
},
  "geometry": {"coordinates":[8.7597789764,46.1645050049],"type":"Point"}
}