{
  "type": "Feature",
  "properties": {
    "iso:country":"CH",
    "sg:address":"Via Alla Chiesa 3",
    "sg:city":"Viganello",
    "sg:orig_category":"Architekturb\u00fcros",
    "sg:phone":"+41 91 971 49 94",
    "sg:postcode":"6962",
    "sg:province":"Ticino",
    "wof:name":"Mauro Galfetti Studio D'architettura",
    "wof:placetype":"venue"
},
  "geometry": {"coordinates":[8.966539,46.011517],"type":"Point"}
}