{
  "type": "Feature",
  "properties": {
    "iso:country":"CH",
    "sg:address":"Grenzstr. (post Lyss).",
    "sg:city":"Kappelen",
    "sg:orig_category":"Kantinen",
    "sg:phone":"+41 32 384 57 34",
    "sg:postcode":"3273",
    "sg:province":"Bern",
    "wof:name":"Gafner Peter.",
    "wof:placetype":"venue"
},
  "geometry": {"coordinates":[7.2932348251,47.0710906982],"type":"Point"}
}