{
  "type": "Feature",
  "properties": {
    "iso:country":"CH",
    "sg:address":"Nelkenweg 8 6330 Cham. Postfach 5109 6305 Zug",
    "sg:city":"Annahme",
    "sg:orig_category":"Sonstige Kurierdienste",
    "sg:phone":"+41 41 781 05 60",
    "sg:postcode":"5",
    "wof:name":"K-p-s Kurier, K\u00fcng M.",
    "wof:placetype":"venue"
},
  "geometry": {"coordinates":[8.4708518982,47.1854438782],"type":"Point"}
}