{
  "type": "Feature",
  "properties": {
    "iso:country":"CH",
    "sg:address":"6962 Viganello. Postfach",
    "sg:city":"Viganello",
    "sg:orig_category":"Detektivb\u00fcros U \u00dcberwachung",
    "sg:phone":"+41 91 972 23 45",
    "sg:postcode":"6962",
    "sg:province":"Ticino",
    "wof:name":"La Traccia Sagl Investigazioni E Sicurezza",
    "wof:placetype":"venue"
},
  "geometry": {"coordinates":[8.9713602066,46.0117912292],"type":"Point"}
}