{
  "type": "Feature",
  "properties": {
    "iso:country":"CH",
    "sg:address":"Schipfe 57",
    "sg:city":"Z\u00fcrich",
    "sg:orig_category":"Vorschulen, Kinderg\u00e4rten",
    "sg:postcode":"8001",
    "sg:province":"Z\u00fcrich",
    "wof:name":"St\u00e4dtischer Kindergarten",
    "wof:placetype":"venue"
},
  "geometry": {"coordinates":[8.5415897369,47.3741073608],"type":"Point"}
}