{
  "type": "Feature",
  "properties": {
    "iso:country":"CH",
    "sg:address":"Sevogelstrasse 51 4052 Basel. Postfach",
    "sg:city":"Basel",
    "sg:orig_category":"Non-Classified Establishments",
    "sg:postcode":"4051",
    "sg:province":"Basel-Stadt",
    "wof:name":"St. Darnutzer Maschinen + Ger\u00e4te",
    "wof:placetype":"venue"
},
  "geometry": {"coordinates":[9.4502401352,46.7011146545],"type":"Point"}
}