{
  "type": "Feature",
  "properties": {
    "iso:country":"CH",
    "sg:address":"Dornacherstrasse 286",
    "sg:city":"Basel",
    "sg:orig_category":"Sportvereine Flug Aero-Club",
    "sg:phone":"+41 61 636 64 55",
    "sg:postcode":"4053",
    "sg:province":"Basel-Stadt",
    "wof:name":"Ae.c.s.modellfluggr.basilisk",
    "wof:placetype":"venue"
},
  "geometry": {"coordinates":[7.5997757912,47.5397796631],"type":"Point"}
}