{
  "type": "Feature",
  "properties": {
    "iso:country":"CH",
    "sg:address":"Im Rybeli 3",
    "sg:city":"Willisau",
    "sg:orig_category":"Vereine Musik/Blasmusik",
    "sg:postcode":"6130",
    "sg:province":"Luzern",
    "wof:name":"Stadtmusik Willisau",
    "wof:placetype":"venue"
},
  "geometry": {"coordinates":[7.9775052071,47.1189727783],"type":"Point"}
}