{
  "type": "Feature",
  "properties": {
    "iso:country":"CH",
    "sg:address":"Torstrasse 25",
    "sg:city":"St.gallen",
    "sg:orig_category":"Herstellung von medizinischen U chirurgischen Ger\u00e4ten sowie orthop\u00e4dischen Vorrichtungen Zahntechnis",
    "sg:phone":"+41 19107218",
    "sg:postcode":"9000",
    "sg:province":"St. Gallen",
    "wof:name":"Zweig Gabriele Dental-labor",
    "wof:placetype":"venue"
},
  "geometry": {"coordinates":[8.5992002487,47.3078765869],"type":"Point"}
}