{
  "type": "Feature",
  "properties": {
    "iso:country":"CH",
    "sg:address":"Sentier Du Lyc\u00e9e 1",
    "sg:city":"Pully",
    "sg:orig_category":"Arztpraxen",
    "sg:phone":"+41 21 728 32 19",
    "sg:postcode":"1009",
    "sg:province":"Vaud",
    "wof:name":"Dr M\u00e9d. Alain Mayor M\u00e9decin Sp\u00e9cialiste Fmh",
    "wof:placetype":"venue"
},
  "geometry": {"coordinates":[6.659136,46.508774],"type":"Point"}
}