{
  "type": "Feature",
  "properties": {
    "iso:country":"CH",
    "sg:address":"Grabenweg 3 3612 Steffisburg. Postfach",
    "sg:city":"Steffisburg",
    "sg:orig_category":"Vermittlung von Immobilien Verwaltung von Immobilien",
    "sg:phone":"+41 33 437 81 39",
    "sg:postcode":"3612",
    "sg:province":"Bern",
    "wof:name":"Werner Aeschbacher Immobilien",
    "wof:placetype":"venue"
},
  "geometry": {"coordinates":[7.6339950562,46.7820625305],"type":"Point"}
}