{
  "type": "Feature",
  "properties": {
    "iso:country":"CH",
    "sg:address":"Schosshaldenstrasse 31",
    "sg:city":"Bern",
    "sg:orig_category":"Bauspenglerei Zimmerei, Dachdeckerei, Bauspenglerei U Abdichtung",
    "sg:phone":"+41 31 351 20 50",
    "sg:postcode":"3006",
    "sg:province":"Bern",
    "wof:name":"Kyburz + Co, Nachfolger Selg-kyburz Ren\u00e9",
    "wof:placetype":"venue"
},
  "geometry": {"coordinates":[7.46522,46.946945],"type":"Point"}
}