{
  "type": "Feature",
  "properties": {
    "iso:country":"CH",
    "sg:address":"Talstrasse 3930 Visp. Postfach",
    "sg:city":"Baltschieder",
    "sg:orig_category":"Grosshandel mit Nahrungsmitteln, Getr\u00e4nken U Tabakwaren ohne ausgepr\u00e4gten Schwerpunkt",
    "sg:postcode":"3937",
    "sg:province":"Valais",
    "wof:name":"Hermann Marceline",
    "wof:placetype":"venue"
},
  "geometry": {"coordinates":[7.8810448647,46.285823822],"type":"Point"}
}