{
  "type": "Feature",
  "properties": {
    "iso:country":"CH",
    "sg:address":"Frauholzstrasse 9a 6422 Steinen. Postfach",
    "sg:city":"Steinen",
    "sg:orig_category":"Softwareentwicklung U beratung",
    "sg:postcode":"6422",
    "sg:province":"Schwyz",
    "wof:name":"Actronic Suter & Merz",
    "wof:placetype":"venue"
},
  "geometry": {"coordinates":[8.6063766479,47.0474052429],"type":"Point"}
}