{
  "type": "Feature",
  "properties": {
    "iso:country":"CH",
    "sg:address":"3226",
    "sg:city":"Treiten",
    "sg:orig_category":"Dienstleistungen im landwirtschaftlichen Pflanzen U Gartenbau",
    "sg:postcode":"3226",
    "sg:province":"Bern",
    "wof:name":"Dreschgenossenschaft Wangen",
    "wof:placetype":"venue"
},
  "geometry": {"coordinates":[8.6456403732,47.4106483459],"type":"Point"}
}