{
  "type": "Feature",
  "properties": {
    "iso:country":"CH",
    "sg:address":"Avenue De Rhodanie 48 1007 Lausanne Case Postale 3720",
    "sg:city":"Lausanne",
    "sg:orig_category":"Finanzierungsinstitutionen",
    "sg:phone":"+41 21 612 06 00",
    "sg:postcode":"1002",
    "sg:province":"Vaud",
    "wof:name":"Renault Finance Sa",
    "wof:placetype":"venue"
},
  "geometry": {"coordinates":[6.6107797623,46.5148582458],"type":"Point"}
}