{
  "type": "Feature",
  "properties": {
    "iso:country":"CH",
    "sg:address":"Oberdorf",
    "sg:city":"Wilderswil",
    "sg:orig_category":"G\u00fcterbef\u00f6rderung im Strassenverkehr",
    "sg:phone":"+41 33 822 21 02",
    "sg:postcode":"3812",
    "sg:province":"Bern",
    "wof:name":"Adolf Eschler Autotransporte",
    "wof:placetype":"venue"
},
  "geometry": {"coordinates":[7.857626915,46.6645393372],"type":"Point"}
}