{
  "type": "Feature",
  "properties": {
    "iso:country":"CH",
    "sg:address":"Rue De L'envers 29a",
    "sg:city":"Sonceboz-sombeval",
    "sg:orig_category":"Sportvereine Ballsport Volleyball",
    "sg:phone":"+41 32 489 21 54",
    "sg:postcode":"2605",
    "sg:province":"Bern",
    "wof:name":"Volleyball-club De Sonceboz",
    "wof:placetype":"venue"
},
  "geometry": {"coordinates":[7.1722898483,47.1978988647],"type":"Point"}
}