{
  "type": "Feature",
  "properties": {
    "iso:country":"CH",
    "sg:address":"Auwiesenstrasse 13 8406 Winterthur. Postfach",
    "sg:city":"Winterthur",
    "sg:orig_category":"Herstellung von sonstigen Nahrungsmitteln",
    "sg:postcode":"8406",
    "sg:province":"Z\u00fcrich",
    "wof:name":"Kr\u00e4mer-badoni Sagl",
    "wof:placetype":"venue"
},
  "geometry": {"coordinates":[9.8381910324,46.4970664978],"type":"Point"}
}