{
  "type": "Feature",
  "properties": {
    "iso:country":"CH",
    "sg:address":"Chemin Des Bourdons 9",
    "sg:city":"Evilard",
    "sg:orig_category":"Reinigungsgewerbe",
    "sg:phone":"+41 32 322 35 92",
    "sg:postcode":"2533",
    "sg:province":"Bern",
    "wof:name":"La Poutzerie Rossier Marthe",
    "wof:placetype":"venue"
},
  "geometry": {"coordinates":[7.2386088371,47.1526451111],"type":"Point"}
}