{
  "type": "Feature",
  "properties": {
    "iso:country":"CH",
    "sg:address":"Hafencenter/hafenstr. 50",
    "sg:city":"Kreuzlingen",
    "sg:orig_category":"Instandhaltung U Reparatur von Automobilen",
    "sg:phone":"+41 71 288 54 44",
    "sg:postcode":"8280",
    "sg:province":"Thurgau",
    "wof:name":"Garage Raic T.",
    "wof:placetype":"venue"
},
  "geometry": {"coordinates":[9.4193458557,47.4391212463],"type":"Point"}
}