{
  "type": "Feature",
  "properties": {
    "iso:country":"CH",
    "sg:address":"Rue De Zaehringen 2 1700 Fribourg Case Postale 93",
    "sg:city":"Fribourg",
    "sg:orig_category":"Detailhandel mit Uhren U Schmuck Fachdetailhandel in Verkaufsr\u00e4umen",
    "sg:phone":"+41 26 322 62 28",
    "sg:postcode":"1702",
    "sg:province":"Fribourg",
    "wof:name":"M\u00f6schler Robert.",
    "wof:placetype":"venue"
},
  "geometry": {"coordinates":[7.1650881767,46.8055458069],"type":"Point"}
}