{
  "type": "Feature",
  "properties": {
    "iso:country":"CH",
    "sg:address":"Claragraben 131",
    "sg:city":"Basel",
    "sg:orig_category":"Autogaragen",
    "sg:phone":"+41 61 691 32 13",
    "sg:postcode":"4057",
    "sg:province":"Basel-Stadt",
    "wof:name":"Paul B\u00fchler Garage",
    "wof:placetype":"venue"
},
  "geometry": {"coordinates":[7.592979,47.564342],"type":"Point"}
}