{
  "type": "Feature",
  "properties": {
    "iso:country":"CH",
    "sg:address":"Lang\u00e4cherstrasse 12",
    "sg:city":"Wettswil",
    "sg:orig_category":"Politische Parteien SVP",
    "sg:phone":"+41 17002203",
    "sg:postcode":"8907",
    "sg:province":"Z\u00fcrich",
    "wof:name":"Svp Ortspartei Wettswil",
    "wof:placetype":"venue"
},
  "geometry": {"coordinates":[8.4722938538,47.3422431946],"type":"Point"}
}