{
  "type": "Feature",
  "properties": {
    "iso:country":"CH",
    "sg:address":"Schwanengasse 1",
    "sg:city":"Solothurn",
    "sg:orig_category":"Unix\u00ae-Networks",
    "sg:phone":"+41 32 621 30 41",
    "sg:postcode":"4500",
    "sg:province":"Solothurn",
    "wof:name":"Ixpert Ag",
    "wof:placetype":"venue"
},
  "geometry": {"coordinates":[7.5366129875,47.2049026489],"type":"Point"}
}