{
  "type": "Feature",
  "properties": {
    "iso:country":"CH",
    "sg:address":"Weier 6a 3616 Schwarzenegg. Postfach",
    "sg:city":"Schwarzenegg",
    "sg:orig_category":"Darlehenskassen U Raiffeisenbanken",
    "sg:phone":"+41 33 453 12 21",
    "sg:postcode":"3616",
    "sg:province":"Bern",
    "wof:name":"Raiffeisenbank Schwarzenegg",
    "wof:placetype":"venue"
},
  "geometry": {"coordinates":[7.720293,46.794529],"type":"Point"}
}