{
  "type": "Feature",
  "properties": {
    "iso:country":"CH",
    "sg:address":"4463",
    "sg:city":"Buus",
    "sg:orig_category":"Wasserversorgung",
    "sg:postcode":"4463",
    "sg:province":"Basel-Landschaft",
    "wof:name":"Wasserversorgung Der Gemeinde B\u00e4rschwil",
    "wof:placetype":"venue"
},
  "geometry": {"coordinates":[8.6473550797,47.5728683472],"type":"Point"}
}