{
  "type": "Feature",
  "properties": {
    "iso:country":"CH",
    "sg:address":"Piazza San Stefano",
    "sg:city":"Rancate",
    "sg:orig_category":"Gemeindeverwaltungen",
    "sg:phone":"+41 91 646 13 80",
    "sg:postcode":"6862",
    "sg:province":"Ticino",
    "wof:name":"Amministrazione Comunale Di Rancate",
    "wof:placetype":"venue"
},
  "geometry": {"coordinates":[8.9681348801,45.8714981079],"type":"Point"}
}