{
  "type": "Feature",
  "properties": {
    "iso:country":"CH",
    "sg:address":"Rue Du Vuache 1",
    "sg:city":"Gen\u00e8ve",
    "sg:classifiers":[
        {
            "category":"Restaurant",
            "type":"Food & Drink"
        }
    ],
    "sg:phone":"+41 81 416 25 21",
    "sg:postcode":"1201",
    "sg:province":"Gen\u00e8ve",
    "wof:name":"Restaurant-pizzeria Touring",
    "wof:placetype":"venue"
},
  "geometry": {"coordinates":[9.8417234421,46.8094520569],"type":"Point"}
}