{
  "type": "Feature",
  "properties": {
    "iso:country":"CH",
    "sg:address":"Marktgasse 36",
    "sg:city":"Langenthal",
    "sg:orig_category":"Interessenvertretungen",
    "sg:postcode":"4900",
    "sg:province":"Bern",
    "wof:name":"Schweizerischer Verband Medizinischer Masseure Wahrung U. F\u00f6rderung Der Beruflichen Interessen Der Mitglieder Usw",
    "wof:placetype":"venue"
},
  "geometry": {"coordinates":[9.8304243088,46.7945747375],"type":"Point"}
}