{
  "type": "Feature",
  "properties": {
    "iso:country":"CH",
    "sg:address":"Rebenh\u00f6he 3 5612 Villmergen. Postfach 126",
    "sg:city":"Villmergen",
    "sg:orig_category":"Grosshandel mit Getreide, Saatgut U Futtermitteln",
    "sg:phone":"+41 56 622 29 05",
    "sg:postcode":"5612",
    "sg:province":"Aargau",
    "wof:name":"Bruno Zumsteg Ag",
    "wof:placetype":"venue"
},
  "geometry": {"coordinates":[8.2535009384,47.3476409912],"type":"Point"}
}