{
  "type": "Feature",
  "properties": {
    "iso:country":"CH",
    "sg:address":"Ziegelbr\u00fcckstrasse 22a",
    "sg:city":"Niederurnen",
    "sg:orig_category":"Unclassifiable Establishments",
    "sg:postcode":"8867",
    "sg:province":"Glarus",
    "wof:name":"Linsi Immobilien Ag Zug",
    "wof:placetype":"venue"
},
  "geometry": {"coordinates":[8.5090923309,47.1435928345],"type":"Point"}
}