{
  "type": "Feature",
  "properties": {
    "iso:country":"CH",
    "sg:address":"Westbahnhofstrasse 1",
    "sg:city":"Solothurn",
    "sg:orig_category":"Physiotherapie",
    "sg:phone":"+41 76 390 42 51",
    "sg:postcode":"4500",
    "sg:province":"Solothurn",
    "wof:name":"Physiotherapie Westbahnhof",
    "wof:placetype":"venue"
},
  "geometry": {"coordinates":[7.5323982239,47.2072525024],"type":"Point"}
}