{
  "type": "Feature",
  "properties": {
    "iso:country":"CH",
    "sg:address":"Chemin Des Vernaz",
    "sg:city":"Aire-la-ville",
    "sg:orig_category":"Detailhandel mit Uhren U Schmuck",
    "sg:phone":"+41 22 342 67 34",
    "sg:postcode":"1288",
    "sg:province":"Gen\u00e8ve",
    "wof:name":"Jacques Vorpe Atelier Bijouterie Joaillerie",
    "wof:placetype":"venue"
},
  "geometry": {"coordinates":[6.1415681839,46.1860389709],"type":"Point"}
}