{
  "type": "Feature",
  "properties": {
    "iso:country":"CH",
    "sg:address":"Streitgasse 20",
    "sg:city":"Basel",
    "sg:classifiers":[
        {
            "category":"Restaurant",
            "type":"Food & Drink"
        }
    ],
    "sg:phone":"+41 61 262 11 30",
    "sg:postcode":"4051",
    "sg:province":"Basel-Stadt",
    "wof:name":"Ristorante/pizzeria Centro Am Barfi",
    "wof:placetype":"venue"
},
  "geometry": {"coordinates":[7.5899977684,47.5552062988],"type":"Point"}
}