{
  "type": "Feature",
  "properties": {
    "iso:country":"CH",
    "sg:address":"Ristenb\u00fchl-matzingen.",
    "sg:city":"Matzingen",
    "sg:orig_category":"Kalb U Schweine-M\u00e4sterei U Zucht",
    "sg:phone":"+41 52 376 12 95",
    "sg:postcode":"9548",
    "sg:province":"Thurgau",
    "wof:name":"Ammann Heinrich",
    "wof:placetype":"venue"
},
  "geometry": {"coordinates":[8.9112997055,47.5244560242],"type":"Point"}
}