{
  "type": "Feature",
  "properties": {
    "iso:country":"CH",
    "sg:address":"Nordstrasse 172",
    "sg:city":"Z\u00fcrich",
    "sg:orig_category":"Fachdetailhandel in Verkaufsr\u00e4umen",
    "sg:postcode":"8037",
    "sg:province":"Z\u00fcrich",
    "wof:name":"Aquarium Nord, Vera Muzak Aquaristik, Aquarien; Handel Usw.",
    "wof:placetype":"venue"
},
  "geometry": {"coordinates":[8.531870842,47.3920707703],"type":"Point"}
}