{
  "type": "Feature",
  "properties": {
    "iso:country":"CH",
    "sg:address":"Spiegelgasse 29",
    "sg:city":"Z\u00fcrich",
    "sg:orig_category":"Innendekorationsateliers",
    "sg:phone":"+41 12512719",
    "sg:postcode":"8001",
    "sg:province":"Z\u00fcrich",
    "wof:name":"Leo Sailer Innenausstattung",
    "wof:placetype":"venue"
},
  "geometry": {"coordinates":[8.5453653336,47.3723144531],"type":"Point"}
}