{
  "type": "Feature",
  "properties": {
    "iso:country":"CH",
    "sg:address":"Bahnh\u00f6heweg 82 3018 Bern. Postfach",
    "sg:city":"Bern",
    "sg:orig_category":"Sonstiges Verlagsgewerbe",
    "sg:phone":"+41 31 998 92 22",
    "sg:postcode":"3018",
    "sg:province":"Bern",
    "wof:name":"Plakatgesellschaft Apg/sga Filiale Bern",
    "wof:placetype":"venue"
},
  "geometry": {"coordinates":[7.3976898193,46.9391746521],"type":"Point"}
}