{
  "type": "Feature",
  "properties": {
    "iso:country":"CH",
    "sg:address":"Baslerstrasse 79",
    "sg:city":"Olten",
    "sg:orig_category":"Handel mit Automobilen",
    "sg:phone":"+41 62 212 01 66",
    "sg:postcode":"4600",
    "sg:province":"Solothurn",
    "wof:name":"Peltier Louis Ag",
    "wof:placetype":"venue"
},
  "geometry": {"coordinates":[7.9016470909,47.3551521301],"type":"Point"}
}