{
  "type": "Feature",
  "properties": {
    "iso:country":"CH",
    "sg:address":"Grauensteinstrasse 7c",
    "sg:city":"G\u00fcttingen",
    "sg:orig_category":"Sportvereine Ballsport Squash",
    "sg:phone":"+41 71 690 06 35",
    "sg:postcode":"8594",
    "sg:province":"Thurgau",
    "wof:name":"Squash Club Amriswil",
    "wof:placetype":"venue"
},
  "geometry": {"coordinates":[9.2883682251,47.6064224243],"type":"Point"}
}