{
  "type": "Feature",
  "properties": {
    "iso:country":"CH",
    "sg:address":"4528",
    "sg:city":"Zuchwil",
    "sg:orig_category":"Grosshandel mit Getreide, Saatgut U Futtermitteln",
    "sg:phone":"+41 14931500",
    "sg:postcode":"4528",
    "sg:province":"Solothurn",
    "wof:name":"W\u00e4lchli Frank, Getreide-futtermittel",
    "wof:placetype":"venue"
},
  "geometry": {"coordinates":[8.4728136063,47.3586730957],"type":"Point"}
}