{
  "type": "Feature",
  "properties": {
    "addr:full":"K\u00fcchengasse 16 4051 Basel. Postfach Basel Basel-Stadt 4002",
    "addr:housenumber":"16",
    "addr:postcode":"4051;4002",
    "addr:street":"Kuechengasse;Postfach",
    "iso:country":"CH",
    "sg:address":"K\u00fcchengasse 16 4051 Basel. Postfach",
    "sg:city":"Basel",
    "sg:orig_category":"Architektur U Ingenieurb\u00fcros",
    "sg:phone":"+41 61 271 67 60",
    "sg:postcode":"4002",
    "sg:province":"Basel-Stadt",
    "wof:name":"Eglin Ristic Ingenieurb\u00fcro Ag",
    "wof:placetype":"venue"
},
  "geometry": {"coordinates":[7.589151,47.548775],"type":"Point"}
}