{
  "type": "Feature",
  "properties": {
    "iso:country":"CH",
    "sg:address":"Wegastrasse 28",
    "sg:city":"Allschwil",
    "sg:orig_category":"Physiotherapie Sonstige Aktivit\u00e4ten der nicht-\u00e4rztlichen Medizinalberufe",
    "sg:phone":"+41 61 302 62 02",
    "sg:postcode":"4123",
    "sg:province":"Basel-Landschaft",
    "wof:name":"Dominik Schenker Physiotherapie & Kinesiologie",
    "wof:placetype":"venue"
},
  "geometry": {"coordinates":[7.5611982346,47.555557251],"type":"Point"}
}