{
  "type": "Feature",
  "properties": {
    "iso:country":"CH",
    "sg:address":"Dammstrasse 64",
    "sg:city":"Biberist",
    "sg:orig_category":"Detektivb\u00fcros U \u00dcberwachung",
    "sg:postcode":"4562",
    "sg:province":"Solothurn",
    "wof:name":"Buggle N.",
    "wof:placetype":"venue"
},
  "geometry": {"coordinates":[7.5607790947,47.1742515564],"type":"Point"}
}