{
  "type": "Feature",
  "properties": {
    "iso:country":"CH",
    "sg:address":"Ch. Du Champ-des-filles 7",
    "sg:city":"Plan-les-ouates",
    "sg:classifiers":[
        {
            "category":"Professional",
            "subcategory":"Engineering",
            "type":"Services"
        }
    ],
    "sg:phone":"+41 22 794 35 10",
    "sg:postcode":"1228",
    "sg:province":"Gen\u00e8ve",
    "wof:name":"Derendinger & Cie S.a.",
    "wof:placetype":"venue"
},
  "geometry": {"coordinates":[6.108641,46.166779],"type":"Point"}
}