{
  "type": "Feature",
  "properties": {
    "iso:country":"CH",
    "sg:address":"Avenue Du Pont-de-la- Roua",
    "sg:city":"Ardon",
    "sg:orig_category":"Grosshandel mit Wein U Spirituosen Mineralquellen, Herstellung von alkoholfreien Getr\u00e4nken",
    "sg:phone":"+41 27 306 28 87",
    "sg:postcode":"1957",
    "sg:province":"Valais",
    "wof:name":"Ap\u00e9ricot S\u00e0rl",
    "wof:placetype":"venue"
},
  "geometry": {"coordinates":[7.2588601112,46.208190918],"type":"Point"}
}