{
  "type": "Feature",
  "properties": {
    "iso:country":"CH",
    "sg:address":"Hauptstrasse 39",
    "sg:city":"B\u00e4ttwil",
    "sg:orig_category":"Detailhandel mit Radio U Fernsehger\u00e4ten Detailhandel mit elektrischen Haushalts-,Radio U Fernsehger\u00e4",
    "sg:phone":"+41 61 731 37 70",
    "sg:postcode":"4112",
    "sg:province":"Solothurn",
    "wof:name":"Tes Technik Elektronik Service Stefan Hilber",
    "wof:placetype":"venue"
},
  "geometry": {"coordinates":[7.5074501038,47.4900169373],"type":"Point"}
}