{
  "type": "Feature",
  "properties": {
    "iso:country":"CH",
    "sg:address":"Brunnmattstrasse 456",
    "sg:city":"Remigen",
    "sg:orig_category":"Herstellung von Pumpen U Kompressoren",
    "sg:phone":"+41 56 284 01 01",
    "sg:postcode":"5236",
    "sg:province":"Aargau",
    "wof:name":"3s Systemtechnik Ag",
    "wof:placetype":"venue"
},
  "geometry": {"coordinates":[8.1856460571,47.5138969421],"type":"Point"}
}