{
  "type": "Feature",
  "properties": {
    "iso:country":"CH",
    "sg:address":"Ribibachstrasse 1",
    "sg:city":"Wiler",
    "sg:classifiers":[
        {
            "category":"Manufacturing",
            "subcategory":"Rubber & Plastics",
            "type":"Manufacturing & Wholesale Goods"
        }
    ],
    "sg:phone":"+41 32 666 30 70",
    "sg:postcode":"3428",
    "sg:province":"Bern",
    "sg:tags":[
        "injection",
        "part",
        "moulded"
    ],
    "wof:name":"Max Allemann Werkzeugbau Ag",
    "wof:placetype":"venue"
},
  "geometry": {"coordinates":[7.5546650887,47.1511878967],"type":"Point"}
}