{
  "type": "Feature",
  "properties": {
    "iso:country":"CH",
    "sg:address":"R\u00f6slistrasse 2 8006 Z\u00fcrich. Postfach",
    "sg:city":"Z\u00fcrich",
    "sg:orig_category":"Interessenvertretungen",
    "sg:phone":"+41 13617620",
    "sg:postcode":"8001",
    "sg:province":"Z\u00fcrich",
    "wof:name":"Kramer Anna Maria Und Karl-stiftung F\u00f6rderung Humanit\u00e4rer Ideen, Aktivit\u00e4ten F\u00fcr Die Menschliche Wohlfahrt Usw",
    "wof:placetype":"venue"
},
  "geometry": {"coordinates":[8.5397987366,47.3876991272],"type":"Point"}
}