{
  "type": "Feature",
  "properties": {
    "iso:country":"CH",
    "sg:address":"M\u00fchlethalstrasse 83",
    "sg:city":"Zofingen",
    "sg:orig_category":"Herstellung von Spielwaren",
    "sg:postcode":"4800",
    "sg:province":"Aargau",
    "wof:name":"Gerber Tauch Technik",
    "wof:placetype":"venue"
},
  "geometry": {"coordinates":[9.1234006882,47.4656410217],"type":"Point"}
}