{
  "type": "Feature",
  "properties": {
    "iso:country":"CH",
    "sg:address":"Avenue Des Morgines 21",
    "sg:city":"Petit-lancy",
    "sg:orig_category":"Stukkateurgewerbe, Gipserei U Verputzerei",
    "sg:phone":"+41 22 792 23 27",
    "sg:postcode":"1213",
    "sg:province":"Gen\u00e8ve",
    "wof:name":"Entreprise Du B\u00e2timent Fortis C.",
    "wof:placetype":"venue"
},
  "geometry": {"coordinates":[6.1110620499,46.1902046204],"type":"Point"}
}