{
  "type": "Feature",
  "properties": {
    "iso:country":"CH",
    "sg:address":"Z\u00fcrichstrasse 66-68 6004 Luzern. Postfach",
    "sg:city":"Luzern",
    "sg:orig_category":"Detailhandel mit elektrischen Haushalts-,Radio U Fernsehger\u00e4ten sowie Musikinstrumenten",
    "sg:phone":"+41 41 422 02 02",
    "sg:postcode":"6004",
    "sg:province":"Luzern",
    "wof:name":"Music & Drummer Shop Luzern, Albert Bossert",
    "wof:placetype":"venue"
},
  "geometry": {"coordinates":[8.3091230392,47.060760498],"type":"Point"}
}