{
  "type": "Feature",
  "properties": {
    "addr:full":"Rebhaldenweg 8 Niederrohrdorf Aargau 5443",
    "addr:housenumber":"8",
    "addr:postcode":"5443",
    "addr:street":"Rebhaldenweg",
    "iso:country":"CH",
    "sg:address":"Rebhaldenweg 8",
    "sg:city":"Niederrohrdorf",
    "sg:orig_category":"Architektur U Ingenieurb\u00fcros",
    "sg:phone":"+41 56 496 43 18",
    "sg:postcode":"5443",
    "sg:province":"Aargau",
    "wof:name":"Blaser Bau-management",
    "wof:placetype":"venue"
},
  "geometry": {"coordinates":[8.306328,47.420845],"type":"Point"}
}