{
  "type": "Feature",
  "properties": {
    "iso:country":"CH",
    "sg:address":"Lohrenwiese 7",
    "sg:city":"Kaltbrunn",
    "sg:orig_category":"Wirtschaftspr\u00fcfung, Steuerberatung U Treuhand",
    "sg:postcode":"8722",
    "sg:province":"St. Gallen",
    "wof:name":"Jbes Gmbh",
    "wof:placetype":"venue"
},
  "geometry": {"coordinates":[9.0233402252,47.2162055969],"type":"Point"}
}