{
  "type": "Feature",
  "properties": {
    "iso:country":"CH",
    "sg:address":"Muotastrasse 6 6438 Ibach. Postfach 259",
    "sg:city":"Ibach",
    "sg:orig_category":"Architektur U Ingenieurb\u00fcros Architekturb\u00fcros",
    "sg:phone":"+41 41 811 21 47",
    "sg:postcode":"6438",
    "sg:province":"Schwyz",
    "wof:name":"J. Pfyl's S\u00f6hne Gmbh Architekturb\u00fcro",
    "wof:placetype":"venue"
},
  "geometry": {"coordinates":[8.643721,47.011703],"type":"Point"}
}