{
  "type": "Feature",
  "properties": {
    "iso:country":"CH",
    "sg:address":"Dorfstrasse 49",
    "sg:city":"R\u00fcdlingen",
    "sg:orig_category":"Kunsthandel",
    "sg:phone":"+41 18673890",
    "sg:postcode":"8455",
    "sg:province":"Schaffhausen",
    "wof:name":"Iris C. Steinegger Galerie",
    "wof:placetype":"venue"
},
  "geometry": {"coordinates":[8.571439743,47.5809822083],"type":"Point"}
}