{
  "type": "Feature",
  "properties": {
    "iso:country":"CH",
    "sg:address":"Saint-mathieu Chemin De 18",
    "sg:city":"Bernex",
    "sg:orig_category":"M\u00f6belschreinereien",
    "sg:postcode":"1233",
    "sg:province":"Gen\u00e8ve",
    "wof:name":"Delaspre Francis",
    "wof:placetype":"venue"
},
  "geometry": {"coordinates":[6.0815868378,46.1809692383],"type":"Point"}
}