{
  "type": "Feature",
  "properties": {
    "iso:country":"CH",
    "sg:address":"Geissbergstrasse 2",
    "sg:city":"Kloten",
    "sg:orig_category":"Geb\u00e4ude, Wohnungsreinigung",
    "sg:phone":"+41 18137904",
    "sg:postcode":"8302",
    "sg:province":"Z\u00fcrich",
    "wof:name":"Josef Marty Fenster-& Baureinigung",
    "wof:placetype":"venue"
},
  "geometry": {"coordinates":[8.5931301117,47.4538841248],"type":"Point"}
}