{
  "type": "Feature",
  "properties": {
    "iso:country":"CH",
    "sg:address":"Sommerstrasse 12",
    "sg:city":"Gr\u00e4nichen",
    "sg:orig_category":"Kaminfeger",
    "sg:phone":"+41 62 842 29 69",
    "sg:postcode":"5722",
    "sg:province":"Aargau",
    "wof:name":"Werner Hunziker Kaminfegermeister",
    "wof:placetype":"venue"
},
  "geometry": {"coordinates":[8.095281601,47.3627891541],"type":"Point"}
}