{
  "type": "Feature",
  "properties": {
    "addr:full":"Feldstrasse 15 Rietheim Aargau 5323",
    "addr:housenumber":"15",
    "addr:postcode":"5323",
    "addr:street":"Feldstrasse",
    "iso:country":"CH",
    "sg:address":"Feldstrasse 15",
    "sg:city":"Rietheim",
    "sg:classifiers":[
        {
            "category":"Professional",
            "subcategory":"Advertising",
            "type":"Services"
        }
    ],
    "sg:phone":"+41 56 249 22 20",
    "sg:postcode":"5323",
    "sg:province":"Aargau",
    "sg:tags":[
        "imprint"
    ],
    "wof:name":"Fischer Druck",
    "wof:placetype":"venue"
},
  "geometry": {"coordinates":[8.278997,47.601326],"type":"Point"}
}