{
  "type": "Feature",
  "properties": {
    "iso:country":"CH",
    "sg:address":"Bahnhofstrasse 22",
    "sg:city":"Meilen",
    "sg:orig_category":"Sonstiger Grosshandel",
    "sg:postcode":"8706",
    "sg:province":"Z\u00fcrich",
    "wof:name":"Adagio Ag",
    "wof:placetype":"venue"
},
  "geometry": {"coordinates":[8.6440467834,47.2686576843],"type":"Point"}
}