{
  "type": "Feature",
  "properties": {
    "iso:country":"CH",
    "sg:address":"Chemin De L'union 1",
    "sg:city":"Jongny",
    "sg:orig_category":"Herstellung von sonstigen elektrischen Ausr\u00fcstungen",
    "sg:phone":"+41 21 781 25 48",
    "sg:postcode":"1805",
    "sg:province":"Vaud",
    "wof:name":"Soudomatic H\u00fcni & Co",
    "wof:placetype":"venue"
},
  "geometry": {"coordinates":[6.8394041061,46.4782180786],"type":"Point"}
}