{
  "type": "Feature",
  "properties": {
    "iso:country":"CH",
    "sg:address":"Patriotenweg 1",
    "sg:city":"Solothurn",
    "sg:orig_category":"Interessenvertretungen",
    "sg:postcode":"4500",
    "sg:province":"Solothurn",
    "wof:name":"Stiftung Lebensr\u00e4ume Des Asjv",
    "wof:placetype":"venue"
},
  "geometry": {"coordinates":[7.5370988846,47.2049407959],"type":"Point"}
}