{
  "type": "Feature",
  "properties": {
    "iso:country":"CH",
    "sg:address":"Route De La Rasse",
    "sg:city":"Evionnaz",
    "sg:orig_category":"Sportvereine Ballsport Tischtennis",
    "sg:phone":"+41 22 344 61 47",
    "sg:postcode":"1902",
    "sg:province":"Valais",
    "wof:name":"Ctt Meyrin",
    "wof:placetype":"venue"
},
  "geometry": {"coordinates":[6.079791069,46.2343292236],"type":"Point"}
}