{
  "type": "Feature",
  "properties": {
    "iso:country":"CH",
    "sg:address":"Route De France 36",
    "sg:city":"Boncourt",
    "sg:orig_category":"Dachdeckerei Zimmerei, Dachdeckerei, Bauspenglerei U Abdichtung",
    "sg:phone":"+41 32 475 50 01",
    "sg:postcode":"2926",
    "sg:province":"Jura",
    "wof:name":"Dobler Denis.",
    "wof:placetype":"venue"
},
  "geometry": {"coordinates":[7.014731,47.501396],"type":"Point"}
}