{
  "type": "Feature",
  "properties": {
    "iso:country":"CH",
    "sg:address":"Kastanienbaumstrasse 66",
    "sg:city":"Horw",
    "sg:orig_category":"Erschliessung von Grundst\u00fccken",
    "sg:postcode":"6048",
    "sg:province":"Luzern",
    "wof:name":"Soziale Wohnbaugen.horw",
    "wof:placetype":"venue"
},
  "geometry": {"coordinates":[8.3108234406,47.0241699219],"type":"Point"}
}