{
  "type": "Feature",
  "properties": {
    "iso:country":"CH",
    "sg:address":"Unterwilrain 44",
    "sg:city":"Littau",
    "sg:orig_category":"Sonstiger spezialisierter Hoch U Tiefbau",
    "sg:phone":"+41 41 250 44 94",
    "sg:postcode":"6014",
    "sg:province":"Luzern",
    "wof:name":"Cook Trockenbau Gmbh",
    "wof:placetype":"venue"
},
  "geometry": {"coordinates":[8.2767715454,47.0500564575],"type":"Point"}
}