{
  "type": "Feature",
  "properties": {
    "iso:country":"CH",
    "sg:address":"Giltstein",
    "sg:city":"M\u00f6rel",
    "sg:orig_category":"Vermittlung von Immobilien Wirtschaftspr\u00fcfung, Steuerberatung U Treuhand",
    "sg:phone":"+41 41 670 26 26",
    "sg:postcode":"3983",
    "sg:province":"Valais",
    "wof:name":"Treuhandb\u00fcro Langensand",
    "wof:placetype":"venue"
},
  "geometry": {"coordinates":[8.270655632,46.9403305054],"type":"Point"}
}