{
  "type": "Feature",
  "properties": {
    "iso:country":"CH",
    "sg:address":"All\u00e9e Des Soupirs 1 2900 Pruntrut. Postfach",
    "sg:city":"Pruntrut",
    "sg:orig_category":"Druck ohne Zeitungsdruck",
    "sg:postcode":"2900",
    "sg:province":"Jura",
    "wof:name":"Centre D'impression Le Pays Sa",
    "wof:placetype":"venue"
},
  "geometry": {"coordinates":[7.0758571625,47.4175415039],"type":"Point"}
}