{
  "type": "Feature",
  "properties": {
    "iso:country":"CH",
    "sg:address":"Hans-haller-gasse 4 8180 B\u00fclach. Postfach",
    "sg:city":"B\u00fclach",
    "sg:orig_category":"Interessenvertretungen",
    "sg:phone":"+41 18607959",
    "sg:postcode":"8180",
    "sg:province":"Z\u00fcrich",
    "wof:name":"Stiftung Sigristenkeller B\u00fclach",
    "wof:placetype":"venue"
},
  "geometry": {"coordinates":[8.5407409668,47.5167617798],"type":"Point"}
}