{
  "type": "Feature",
  "properties": {
    "iso:country":"CH",
    "sg:address":"Kronenstrasse 8",
    "sg:city":"St\u00e4fa",
    "sg:orig_category":"Erbringung von Dienstleistungen f\u00fcr Unternehmen",
    "sg:postcode":"8712",
    "sg:province":"Z\u00fcrich",
    "wof:name":"Innerlight Gmbh",
    "wof:placetype":"venue"
},
  "geometry": {"coordinates":[8.7246990204,47.2416687012],"type":"Point"}
}