{
  "type": "Feature",
  "properties": {
    "iso:country":"CH",
    "sg:address":"Margelackerstrasse 7",
    "sg:city":"Muttenz",
    "sg:orig_category":"Stukkateurgewerbe, Gipserei U Verputzerei",
    "sg:phone":"+41 61 462 15 15",
    "sg:postcode":"4132",
    "sg:province":"Basel-Landschaft",
    "wof:name":"Putrino Gipsergesch\u00e4ft",
    "wof:placetype":"venue"
},
  "geometry": {"coordinates":[7.6340618134,47.5309333801],"type":"Point"}
}