{
  "type": "Feature",
  "properties": {
    "iso:country":"CH",
    "sg:address":"Plazza Aviatica 4",
    "sg:city":"Samedan",
    "sg:classifiers":[
        {
            "category":"Professional",
            "subcategory":"Business Services",
            "type":"Services"
        }
    ],
    "sg:phone":"+41 81 851 18 18",
    "sg:postcode":"7503",
    "sg:province":"Graubunden",
    "sg:tags":[
        "travel",
        "-",
        "transport",
        "air"
    ],
    "wof:name":"Heli Bernina Ag",
    "wof:placetype":"venue"
},
  "geometry": {"coordinates":[9.87816,46.529995],"type":"Point"}
}