{
  "type": "Feature",
  "properties": {
    "iso:country":"CH",
    "sg:address":"Wegmattes\u00e4ge",
    "sg:city":"Sch\u00fcpfheim",
    "sg:orig_category":"Hobelwerke S\u00e4gewerke",
    "sg:phone":"+41 41 484 16 15",
    "sg:postcode":"6170",
    "sg:province":"Luzern",
    "wof:name":"Wickiholz Daniel Wicki S\u00e4ge-& Hobelwerk",
    "wof:placetype":"venue"
},
  "geometry": {"coordinates":[8.0121335983,46.9343109131],"type":"Point"}
}