{
  "type": "Feature",
  "properties": {
    "iso:country":"CH",
    "sg:address":"7403",
    "sg:city":"Rh\u00e4z\u00fcns",
    "sg:orig_category":"Schulpflegen",
    "sg:postcode":"7403",
    "sg:province":"Graubunden",
    "wof:name":"Schulrat Der Primarschule Sils Im Domleschg",
    "wof:placetype":"venue"
},
  "geometry": {"coordinates":[9.4555253983,46.7018165588],"type":"Point"}
}