{
  "type": "Feature",
  "properties": {
    "iso:country":"CH",
    "sg:address":"Via Dogana 2",
    "sg:city":"Bellinzona",
    "sg:orig_category":"Detailhandel mit Bekleidung Detailhandel mit Textilien",
    "sg:phone":"+41 62 390 12 14",
    "sg:postcode":"6500",
    "sg:province":"Ticino",
    "wof:name":"Lydia Hafner Restenstube & Textilien",
    "wof:placetype":"venue"
},
  "geometry": {"coordinates":[7.750949,47.333328],"type":"Point"}
}