{
  "type": "Feature",
  "properties": {
    "iso:country":"CH",
    "sg:address":"6718",
    "sg:city":"Olivone",
    "sg:orig_category":"Verwertung von Milch",
    "sg:postcode":"6718",
    "sg:province":"Ticino",
    "wof:name":"Latteria-caseificio Sociale San Vittore",
    "wof:placetype":"venue"
},
  "geometry": {"coordinates":[9.1073904037,46.2385597229],"type":"Point"}
}