{
  "type": "Feature",
  "properties": {
    "iso:country":"CH",
    "sg:address":"8302",
    "sg:city":"Kloten",
    "sg:orig_category":"Politische Parteien Evangelische Volkspartei",
    "sg:phone":"+41 19120537",
    "sg:postcode":"8302",
    "sg:province":"Z\u00fcrich",
    "wof:name":"Evp Ortspartei K\u00fcsnacht",
    "wof:placetype":"venue"
},
  "geometry": {"coordinates":[8.6057138443,47.3267478943],"type":"Point"}
}