{
  "type": "Feature",
  "properties": {
    "iso:country":"CH",
    "sg:address":"Wasserg. 12",
    "sg:city":"Lohn",
    "sg:classifiers":[
        {
            "category":"Shopping",
            "subcategory":"Computers & Home Electronics",
            "type":"Retail Goods"
        }
    ],
    "sg:phone":"+41 32 677 50 60",
    "sg:postcode":"4573",
    "sg:province":"Solothurn",
    "sg:tags":[
        "equipment",
        "electrical",
        "component",
        "electric",
        "electronic"
    ],
    "wof:name":"Zaugg Elektronik Ag",
    "wof:placetype":"venue"
},
  "geometry": {"coordinates":[7.524810791,47.1698150635],"type":"Point"}
}