{
  "type": "Feature",
  "properties": {
    "iso:country":"CH",
    "sg:address":"Ottoplatz 19 7000 Chur. Postfach",
    "sg:city":"Chur",
    "sg:orig_category":"Wirtschaftspr\u00fcfung, Steuerberatung U Treuhand",
    "sg:postcode":"7000",
    "sg:province":"Graubunden",
    "wof:name":"Real-boden Ag",
    "wof:placetype":"venue"
},
  "geometry": {"coordinates":[9.5318384171,46.85364151],"type":"Point"}
}