{
  "type": "Feature",
  "properties": {
    "iso:country":"CH",
    "sg:address":"Vogelsangstrasse 13 Effretikon 8308 Agasul. Postfach",
    "sg:city":"Effretikon",
    "sg:orig_category":"Herstellung von \u00d6fen U Brennern",
    "sg:postcode":"8307",
    "sg:province":"Z\u00fcrich",
    "wof:name":"Alpinofen Import Ag",
    "wof:placetype":"venue"
},
  "geometry": {"coordinates":[8.7239246368,47.4074707031],"type":"Point"}
}