{
  "type": "Feature",
  "properties": {
    "iso:country":"CH",
    "sg:address":"Limmatstrasse 73 8005 Z\u00fcrich. Postfach",
    "sg:city":"Z\u00fcrich",
    "sg:orig_category":"Grosshandel mit Holz U Baustoffen",
    "sg:phone":"+41 34 448 23 23",
    "sg:postcode":"8005",
    "sg:province":"Z\u00fcrich",
    "wof:name":"Basys Ag",
    "wof:placetype":"venue"
},
  "geometry": {"coordinates":[7.5677270889,47.0958404541],"type":"Point"}
}