{
  "type": "Feature",
  "properties": {
    "iso:country":"CH",
    "sg:address":"Seestrasse 17",
    "sg:city":"Uttwil",
    "sg:classifiers":[
        {
            "category":"Travel",
            "subcategory":"Hotels & Motels",
            "type":"Entertainment"
        }
    ],
    "sg:phone":"+41 71 463 17 03",
    "sg:postcode":"8592",
    "sg:province":"Thurgau",
    "sg:tags":[
        "hotels",
        "mit",
        "restaurant"
    ],
    "wof:name":"Hotel Bad Uttwil",
    "wof:placetype":"venue"
},
  "geometry": {"coordinates":[9.3442487717,47.5855827332],"type":"Point"}
}