{
  "type": "Feature",
  "properties": {
    "iso:country":"CH",
    "sg:address":"K\u00fcttigerstrasse 1 5022 Rombach. Postfach",
    "sg:city":"Rombach",
    "sg:orig_category":"RESTAURANTS: TEA-ROOMS",
    "sg:postcode":"5022",
    "sg:province":"Aargau",
    "wof:name":"Cw-chinese Gmbh Gastronomielokal Usw",
    "wof:placetype":"venue"
},
  "geometry": {"coordinates":[8.0421648026,47.4008522034],"type":"Point"}
}