{
  "type": "Feature",
  "properties": {
    "iso:country":"CH",
    "sg:address":"Hauptstrasse 8",
    "sg:city":"Balgach",
    "sg:orig_category":"Sportvereine Turnen Vereine Damen",
    "sg:phone":"+41 71 722 29 81",
    "sg:postcode":"9436",
    "sg:province":"St. Gallen",
    "wof:name":"Damenriege Balgach",
    "wof:placetype":"venue"
},
  "geometry": {"coordinates":[9.6123447418,47.4087753296],"type":"Point"}
}