{
  "type": "Feature",
  "properties": {
    "iso:country":"CH",
    "sg:address":"Gare Rue De La 19",
    "sg:city":"St-imier",
    "sg:orig_category":"Herstellung von Teppichen",
    "sg:postcode":"2610",
    "sg:province":"Bern",
    "wof:name":"Fresta Carrelages S. \u00e0 R.l.",
    "wof:placetype":"venue"
},
  "geometry": {"coordinates":[6.9958171844,47.1520423889],"type":"Point"}
}