{
  "type": "Feature",
  "properties": {
    "iso:country":"CH",
    "sg:address":"Enkh\u00fcseren",
    "sg:city":"Niederhelfenschwil",
    "sg:orig_category":"Wirtschaftspr\u00fcfung, Steuerberatung U Treuhand",
    "sg:phone":"+41 71 947 10 78",
    "sg:postcode":"9527",
    "sg:province":"St. Gallen",
    "wof:name":"Juen Treuhand Gmbh",
    "wof:placetype":"venue"
},
  "geometry": {"coordinates":[9.1876983643,47.4777603149],"type":"Point"}
}