{
  "type": "Feature",
  "properties": {
    "iso:country":"CH",
    "sg:address":"Mittelh\u00e4usern",
    "sg:city":"Mittelh\u00e4usern",
    "sg:classifiers":[
        {
            "category":"Banks & Credit Unions",
            "subcategory":"Bank",
            "type":"Services"
        }
    ],
    "sg:phone":"+41 81 330 54 50",
    "sg:postcode":"3147",
    "sg:province":"Bern",
    "wof:name":"Raiffeisenbank Mittelpr\u00e4ttig\u00e4u",
    "wof:placetype":"venue"
},
  "geometry": {"coordinates":[9.742712,46.915298],"type":"Point"}
}