{
  "type": "Feature",
  "properties": {
    "iso:country":"CH",
    "sg:address":"Avenue Ruchonnet 30",
    "sg:city":"Lausanne",
    "sg:orig_category":"P\u00e9dicure",
    "sg:phone":"+41 21 343 01 43",
    "sg:postcode":"1003",
    "sg:province":"Vaud",
    "wof:name":"M. Christophe Paoli",
    "wof:placetype":"venue"
},
  "geometry": {"coordinates":[6.6238780022,46.5195999146],"type":"Point"}
}