{
  "type": "Feature",
  "properties": {
    "iso:country":"CH",
    "sg:address":"Robert-durrerstrasse 6",
    "sg:city":"Stans",
    "sg:orig_category":"Sonstige Hilfs U Nebent\u00e4tigkeiten f\u00fcr den Landverkehr",
    "sg:phone":"+41 41 610 65 14",
    "sg:postcode":"6370",
    "sg:province":"Nidwalden",
    "wof:name":"Bahnhofparking Stans Ag",
    "wof:placetype":"venue"
},
  "geometry": {"coordinates":[8.3677387238,46.9588356018],"type":"Point"}
}