{
  "type": "Feature",
  "properties": {
    "iso:country":"CH",
    "sg:address":"In Der Breiti 10",
    "sg:city":"Urdorf",
    "sg:orig_category":"Softwareentwicklung U beratung",
    "sg:phone":"+41 17389999",
    "sg:postcode":"8902",
    "sg:province":"Z\u00fcrich",
    "wof:name":"Pansoft Ag",
    "wof:placetype":"venue"
},
  "geometry": {"coordinates":[8.431429863,47.3788566589],"type":"Point"}
}