{
  "type": "Feature",
  "properties": {
    "iso:country":"CH",
    "sg:address":"Langgr\u00fctstrasse 102",
    "sg:city":"Z\u00fcrich",
    "sg:orig_category":"Sonstige Hilfsdienste des Kultur U Unterhaltungswesens Vervielf\u00e4ltigung von bespielten Tontr\u00e4gern",
    "sg:phone":"+41 14923586",
    "sg:postcode":"8047",
    "sg:province":"Z\u00fcrich",
    "wof:name":"Bacteria Records Friedlhuemer Musikwerke Usw; Produktion, Phonograph. Auswertung. Tontr\u00e4gerherstellung",
    "wof:placetype":"venue"
},
  "geometry": {"coordinates":[8.4961862564,47.3731498718],"type":"Point"}
}