{
  "type": "Feature",
  "properties": {
    "iso:country":"CH",
    "sg:address":"Rue De La Gare 8 2350 Saignel\u00e9gier. Postfach",
    "sg:city":"Saignel\u00e9gier",
    "sg:orig_category":"Detailhandel mit B\u00fcchern, Zeitungen, Schreib U Papeteriewaren Detailhandel mit Zeitungen U Zeitschri",
    "sg:phone":"+41 32 951 12 34",
    "sg:postcode":"2350",
    "sg:province":"Jura",
    "wof:name":"Pelletier",
    "wof:placetype":"venue"
},
  "geometry": {"coordinates":[6.995882,47.255394],"type":"Point"}
}