{
  "type": "Feature",
  "properties": {
    "iso:country":"CH",
    "sg:address":"Museumstrasse 1",
    "sg:city":"Aesch",
    "sg:orig_category":"RESTAURANTS: TEA-ROOMS",
    "sg:postcode":"8904",
    "sg:province":"Z\u00fcrich",
    "wof:name":"Ren\u00e9 Brunner Gastro-betriebe Gmbh",
    "wof:placetype":"venue"
},
  "geometry": {"coordinates":[8.4376192093,47.3364181519],"type":"Point"}
}