{
  "type": "Feature",
  "properties": {
    "iso:country":"CH",
    "sg:address":"Gaiser Strasse 19 9050 Appenzell. Postfach 64",
    "sg:city":"Appenzell",
    "sg:orig_category":"Herstellung von Haushalts, Hygiene U Toilettenartikeln aus Zellstoff U Papier Textilgewerbe",
    "sg:phone":"+41 71 277 84 84",
    "sg:postcode":"9050",
    "sg:province":"Appenzell Innerhoden",
    "wof:name":"Doerig & Kreier Ag Taschent\u00fccher Heimtextilien",
    "wof:placetype":"venue"
},
  "geometry": {"coordinates":[9.4109363556,47.3310012817],"type":"Point"}
}