{
  "type": "Feature",
  "properties": {
    "iso:country":"CH",
    "sg:address":"Baselstrasse 38",
    "sg:city":"Luzern",
    "sg:orig_category":"Druck ohne Zeitungsdruck Offsetdruck",
    "sg:phone":"+41 41 240 95 44",
    "sg:postcode":"6003",
    "sg:province":"Luzern",
    "wof:name":"Dahinden Jos.",
    "wof:placetype":"venue"
},
  "geometry": {"coordinates":[8.29551,47.05323],"type":"Point"}
}