{
  "type": "Feature",
  "properties": {
    "iso:country":"CH",
    "sg:address":"Dorfstrasse 26",
    "sg:city":"Jona",
    "sg:orig_category":"Forstwirtschaft ohne Dienstleistungen in der Forstwirtschaft",
    "sg:postcode":"8645",
    "sg:province":"St. Gallen",
    "wof:name":"N\u00fcesch & Ammann Forstunternehmung Ag",
    "wof:placetype":"venue"
},
  "geometry": {"coordinates":[8.8376483917,47.2301635742],"type":"Point"}
}