{
  "type": "Feature",
  "properties": {
    "iso:country":"CH",
    "sg:address":"Kappelenring 52c",
    "sg:city":"Hinterkappelen",
    "sg:orig_category":"Unternehmensberatung",
    "sg:phone":"+41 79 411 68 94",
    "sg:postcode":"3032",
    "sg:province":"Bern",
    "wof:name":"Christian Zahnd Organisationsberatung",
    "wof:placetype":"venue"
},
  "geometry": {"coordinates":[7.375685215,46.9668998718],"type":"Point"}
}