{
  "type": "Feature",
  "properties": {
    "iso:country":"CH",
    "sg:address":"Zugerstrasse 77",
    "sg:city":"Baar",
    "sg:orig_category":"Finanzierungsinstitutionen",
    "sg:postcode":"6340",
    "sg:province":"Zug",
    "wof:name":"Rueda Ag",
    "wof:placetype":"venue"
},
  "geometry": {"coordinates":[8.5199966431,47.1830482483],"type":"Point"}
}