{
  "type": "Feature",
  "properties": {
    "iso:country":"CH",
    "sg:address":"Weissbadstrasse 14 9057 Schwende. Postfach",
    "sg:city":"Schwende",
    "sg:orig_category":"Fachdetailhandel in Verkaufsr\u00e4umen",
    "sg:postcode":"9057",
    "sg:province":"Appenzell Innerhoden",
    "wof:name":"Anifit Ag",
    "wof:placetype":"venue"
},
  "geometry": {"coordinates":[9.4171199799,47.326461792],"type":"Point"}
}