{
  "type": "Feature",
  "properties": {
    "iso:country":"CH",
    "sg:address":"Route De Divonne 48",
    "sg:city":"Nyon",
    "sg:orig_category":"Herstellung von Teppichen Verlegen von Fussboden",
    "sg:phone":"+41 79 206 49 19",
    "sg:postcode":"1260",
    "sg:province":"Vaud",
    "wof:name":"Allaman Sa",
    "wof:placetype":"venue"
},
  "geometry": {"coordinates":[6.2227759361,46.3829574585],"type":"Point"}
}