{
  "type": "Feature",
  "properties": {
    "iso:country":"CH",
    "sg:address":"Vy Des Cr\u00eats 15",
    "sg:city":"Mies",
    "sg:orig_category":"Sonstige pers\u00f6nliche Dienstleistungen",
    "sg:phone":"+41 22 755 52 34",
    "sg:postcode":"1295",
    "sg:province":"Vaud",
    "wof:name":"Zainzinger Walter",
    "wof:placetype":"venue"
},
  "geometry": {"coordinates":[6.1665129662,46.3031311035],"type":"Point"}
}