{
  "type": "Feature",
  "properties": {
    "iso:country":"CH",
    "sg:address":"Rue De Lausanne 65",
    "sg:city":"Pr\u00e9verenges",
    "sg:orig_category":"Arztpraxen",
    "sg:phone":"+41 21 804 70 55",
    "sg:postcode":"1028",
    "sg:province":"Vaud",
    "wof:name":"Dr M\u00e9d. Marc-andr\u00e9 Perrin M\u00e9decin Sp\u00e9cialiste Fmh",
    "wof:placetype":"venue"
},
  "geometry": {"coordinates":[6.530507,46.517124],"type":"Point"}
}