{
  "type": "Feature",
  "properties": {
    "addr:full":"Avenue De Frontenex 32 Gen\u00e8ve Gen\u00e8ve 1207",
    "addr:housenumber":"32",
    "addr:postcode":"1207",
    "addr:street":"Avenue De Frontenex",
    "iso:country":"CH",
    "sg:address":"Avenue De Frontenex 32",
    "sg:city":"Gen\u00e8ve",
    "sg:orig_category":"Aktivit\u00e4ten der Generalunternehmen im Baugewerbe Sonstiger spezialisierter Hoch U Tiefbau",
    "sg:phone":"+41 22 735 05 48",
    "sg:postcode":"1207",
    "sg:province":"Gen\u00e8ve",
    "wof:name":"Cavecchia Sa",
    "wof:placetype":"venue"
},
  "geometry": {"coordinates":[6.158845,46.201469],"type":"Point"}
}