{
  "type": "Feature",
  "properties": {
    "iso:country":"CH",
    "sg:address":"Schulhausstrasse 65 5618 Bettwil. Postfach",
    "sg:city":"Bettwil",
    "sg:orig_category":"K\u00fcnstlerische U schriftstellerische T\u00e4tigkeiten U Darbietungen",
    "sg:postcode":"5618",
    "sg:province":"Aargau",
    "wof:name":"Sonic Playground Gmbh Dienstleistungen In Den Bereichen Musik U. Multimedia, Bes. Soundengineering Usw",
    "wof:placetype":"venue"
},
  "geometry": {"coordinates":[8.266579628,47.2910614014],"type":"Point"}
}