{
  "type": "Feature",
  "properties": {
    "addr:full":"Bliggenswil Bauma Z\u00fcrich 8494",
    "addr:postcode":"8494",
    "addr:street":"Bliggenswil",
    "iso:country":"CH",
    "sg:address":"Bliggenswil",
    "sg:city":"Bauma",
    "sg:orig_category":"Betrieb von Sportanlagen",
    "sg:postcode":"8494",
    "sg:province":"Z\u00fcrich",
    "wof:name":"Gespa, Genossenschaft Spiel Und Sportanlagen Bergholz Wil",
    "wof:placetype":"venue"
},
  "geometry": {"coordinates":[9.057597,47.469204],"type":"Point"}
}