{
  "type": "Feature",
  "properties": {
    "iso:country":"CH",
    "sg:address":"Albisriederstrasse 399",
    "sg:city":"Z\u00fcrich",
    "sg:orig_category":"Pensionskassen",
    "sg:phone":"+41 14912555",
    "sg:postcode":"8047",
    "sg:province":"Z\u00fcrich",
    "wof:name":"Personalf\u00fcrsorgestiftung Des Vereins Schweizerische Bibliothek F\u00fcr Blinde Und Sehbehinderte Sbs, 8047 Z\u00fcrich",
    "wof:placetype":"venue"
},
  "geometry": {"coordinates":[8.4824743271,47.3740196228],"type":"Point"}
}