{
  "type": "Feature",
  "properties": {
    "iso:country":"CH",
    "sg:address":"1418",
    "sg:city":"Vuarrens",
    "sg:orig_category":"Haltung von Schweinen Verarbeitung von Milch",
    "sg:phone":"+41 21 887 76 42",
    "sg:postcode":"1418",
    "sg:province":"Vaud",
    "wof:name":"Kurt Burkhard",
    "wof:placetype":"venue"
},
  "geometry": {"coordinates":[6.6476688385,46.6862792969],"type":"Point"}
}