{
  "type": "Feature",
  "properties": {
    "iso:country":"CH",
    "sg:address":"Elisabeth-frei-strasse 12 2540 Grenchen. Postfach",
    "sg:city":"Grenchen",
    "sg:orig_category":"Zimmerei, Dachdeckerei, Bauspenglerei U Abdichtung",
    "sg:postcode":"2540",
    "sg:province":"Solothurn",
    "wof:name":"Dafatech Gmbh, Dach, Fassaden Und Spenglertechnik",
    "wof:placetype":"venue"
},
  "geometry": {"coordinates":[7.757589817,46.9491271973],"type":"Point"}
}