{
  "type": "Feature",
  "properties": {
    "iso:country":"CH",
    "sg:address":"Sarmenstorferstrasse 4-8",
    "sg:city":"Fahrwangen",
    "sg:orig_category":"Lamps, Rustic",
    "sg:phone":"+41 56 676 60 50",
    "sg:postcode":"5615",
    "sg:province":"Aargau",
    "wof:name":"Rupp Metalltrend Ag Schmiedeisen Und Leuchten",
    "wof:placetype":"venue"
},
  "geometry": {"coordinates":[8.2427034378,47.2952766418],"type":"Point"}
}