{
  "type": "Feature",
  "properties": {
    "iso:country":"CH",
    "sg:address":"Grand-rue 58",
    "sg:city":"Payerne",
    "sg:orig_category":"Fotografisches Gewerbe U fotografische Laboratorien",
    "sg:phone":"+41 79 213 67 23",
    "sg:postcode":"1530",
    "sg:province":"Vaud",
    "wof:name":"Corminboeuf Patrick",
    "wof:placetype":"venue"
},
  "geometry": {"coordinates":[6.9371051788,46.8212776184],"type":"Point"}
}