{
  "type": "Feature",
  "properties": {
    "iso:country":"CH",
    "sg:address":"Beim Neumarkt",
    "sg:city":"Brugg",
    "sg:classifiers":[
        {
            "category":"Banks & Credit Unions",
            "subcategory":"Bank",
            "type":"Services"
        }
    ],
    "sg:phone":"+41 4156429111",
    "sg:postcode":"5200",
    "sg:province":"Aargau",
    "wof:name":"Union Bank Of Switzerland",
    "wof:placetype":"venue"
},
  "geometry": {"coordinates":[8.206764,47.48418],"type":"Point"}
}