{
  "type": "Feature",
  "properties": {
    "iso:country":"CH",
    "sg:address":"Restaurant Obermatt",
    "sg:city":"Ennetb\u00fcrgen",
    "sg:classifiers":[
        {
            "category":"Travel",
            "subcategory":"Hotels & Motels",
            "type":"Entertainment"
        }
    ],
    "sg:postcode":"6373",
    "sg:province":"Nidwalden",
    "sg:tags":[
        "hotels",
        "mit",
        "restaurant"
    ],
    "wof:name":"Murer, Peter",
    "wof:placetype":"venue"
},
  "geometry": {"coordinates":[8.4138898849,46.9846916199],"type":"Point"}
}