{
  "type": "Feature",
  "properties": {
    "iso:country":"CH",
    "sg:address":"Jakobstrasse 1 5430 Wettingen. Postfach 3100",
    "sg:city":"Wettingen",
    "sg:orig_category":"Handel mit Automobilen",
    "sg:phone":"+41 56 427 02 13",
    "sg:postcode":"5430",
    "sg:province":"Aargau",
    "wof:name":"Ih Automobile Ag Automobile, Liegenschaften; Handel",
    "wof:placetype":"venue"
},
  "geometry": {"coordinates":[8.3173923492,47.4696273804],"type":"Point"}
}