{
  "type": "Feature",
  "properties": {
    "addr:full":"Oberer Deutweg 59 Winterthur Z\u00fcrich 8400",
    "addr:housenumber":"59",
    "addr:postcode":"8400",
    "addr:street":"Oberer Deutweg",
    "iso:country":"CH",
    "sg:address":"Oberer Deutweg 59",
    "sg:city":"Winterthur",
    "sg:orig_category":"Detailhandel mit Computern U Software",
    "sg:phone":"+41 52 233 23 20",
    "sg:postcode":"8400",
    "sg:province":"Z\u00fcrich",
    "wof:name":"Luigi Rotondaro Digital Store",
    "wof:placetype":"venue"
},
  "geometry": {"coordinates":[8.741925,47.493958],"type":"Point"}
}