{
  "type": "Feature",
  "properties": {
    "iso:country":"CH",
    "sg:address":"Burgmatt 22b",
    "sg:city":"Baar",
    "sg:classifiers":[
        {
            "category":"Professional",
            "subcategory":"Engineering",
            "type":"Services"
        }
    ],
    "sg:phone":"+41 41 761 47 87",
    "sg:postcode":"6340",
    "sg:province":"Zug",
    "wof:name":"Ceft Engineering & Trading Ag",
    "wof:placetype":"venue"
},
  "geometry": {"coordinates":[8.5380268097,47.1923866272],"type":"Point"}
}