{
  "type": "Feature",
  "properties": {
    "iso:country":"CH",
    "sg:address":"Aeschengraben 21",
    "sg:city":"Basel",
    "sg:classifiers":[
        {
            "category":"Banks & Credit Unions",
            "subcategory":"Financial Services",
            "type":"Services"
        }
    ],
    "sg:phone":"+41 61 285 85 85",
    "sg:postcode":"4002",
    "sg:province":"Basel-Stadt",
    "sg:tags":[
        "banking",
        "finance",
        "insurance"
    ],
    "wof:name":"Baloise Holding Ag",
    "wof:placetype":"venue"
},
  "geometry": {"coordinates":[7.592657,47.549576],"type":"Point"}
}