{
  "type": "Feature",
  "properties": {
    "iso:country":"CH",
    "sg:address":"Hauptstrasse 73",
    "sg:city":"Hornussen",
    "sg:classifiers":[
        {
            "category":"Restaurant",
            "type":"Food & Drink"
        }
    ],
    "sg:phone":"+41 62 871 44 60",
    "sg:postcode":"5075",
    "sg:province":"Aargau",
    "wof:name":"Restaurant Feldschl\u00f6ssli",
    "wof:placetype":"venue"
},
  "geometry": {"coordinates":[8.0642442703,47.4997634888],"type":"Point"}
}