{
  "type": "Feature",
  "properties": {
    "iso:country":"CH",
    "sg:address":"Hirschengraben 42 8001 Z\u00fcrich. Postfach",
    "sg:city":"Z\u00fcrich",
    "sg:orig_category":"Schulpflegen",
    "sg:phone":"+41 12511296",
    "sg:postcode":"8025",
    "wof:name":"Kreisschulpflege Z\u00fcrichberg",
    "wof:placetype":"venue"
},
  "geometry": {"coordinates":[8.5474557877,47.3733634949],"type":"Point"}
}