{
  "type": "Feature",
  "properties": {
    "iso:country":"CH",
    "sg:address":"Village Rue Du 40",
    "sg:city":"Corseaux",
    "sg:orig_category":"Sonstige mit der Informatik verbundene T\u00e4tigkeiten",
    "sg:postcode":"1802",
    "sg:province":"Vaud",
    "wof:name":"Allorg Ag",
    "wof:placetype":"venue"
},
  "geometry": {"coordinates":[8.5452337265,47.321598053],"type":"Point"}
}