{
  "type": "Feature",
  "properties": {
    "iso:country":"CH",
    "sg:address":"Bleicherweg 66",
    "sg:city":"Z\u00fcrich",
    "sg:orig_category":"Verm\u00f6gensverwaltung",
    "sg:phone":"+41 12212002",
    "sg:postcode":"8002",
    "sg:province":"Z\u00fcrich",
    "wof:name":"Scherrer & Partner Investment Management Ag",
    "wof:placetype":"venue"
},
  "geometry": {"coordinates":[8.533197403,47.3668823242],"type":"Point"}
}