{
  "type": "Feature",
  "properties": {
    "iso:country":"CH",
    "sg:address":"Bundtels",
    "sg:city":"D\u00fcdingen",
    "sg:orig_category":"Non-Classified Establishments",
    "sg:phone":"+41 26 493 22 43",
    "sg:postcode":"3186",
    "sg:province":"Fribourg",
    "wof:name":"Andrey Josef, Gartenbau",
    "wof:placetype":"venue"
},
  "geometry": {"coordinates":[7.2050280571,46.8657493591],"type":"Point"}
}