{
  "type": "Feature",
  "properties": {
    "iso:country":"CH",
    "sg:address":"Ahornweg 27",
    "sg:city":"K\u00fcttigen",
    "sg:orig_category":"Vermietung U Verpachtung von eigenen Immobilien",
    "sg:phone":"+41 62 827 33 66",
    "sg:postcode":"5024",
    "sg:province":"Aargau",
    "wof:name":"Brogle Immobilien",
    "wof:placetype":"venue"
},
  "geometry": {"coordinates":[8.0480461121,47.4093894958],"type":"Point"}
}