{
  "type": "Feature",
  "properties": {
    "iso:country":"CH",
    "sg:address":"Le Petit-bourg B",
    "sg:city":"Ch\u00e2tel-st-denis",
    "sg:orig_category":"Organisationen des Gesundheitswesen",
    "sg:phone":"+41 21 948 84 54",
    "sg:postcode":"1618",
    "sg:province":"Fribourg",
    "wof:name":"Centre De Sant\u00e9 De La Veveyse Soins \u00e0 Domicile",
    "wof:placetype":"venue"
},
  "geometry": {"coordinates":[6.9015398026,46.5275344849],"type":"Point"}
}