{
  "type": "Feature",
  "properties": {
    "iso:country":"CH",
    "sg:address":"Jaquet-droz Rue 2",
    "sg:city":"Neuch\u00e2tel",
    "sg:orig_category":"Unclassifiable Establishments",
    "sg:postcode":"2000",
    "sg:province":"Neuch\u00e2tel",
    "wof:name":"Boulangerie-p\u00e2tisserie Et Tea-room Du Mail, Yves Keller",
    "wof:placetype":"venue"
},
  "geometry": {"coordinates":[6.9478878975,46.9978752136],"type":"Point"}
}