{
  "type": "Feature",
  "properties": {
    "iso:country":"CH",
    "sg:address":"Bahnhofstrasse 3920 Zermatt. Postfach 9",
    "sg:city":"Zermatt",
    "sg:orig_category":"RESTAURANTS: TEA-ROOMS",
    "sg:phone":"+41 71 277 10 52",
    "sg:postcode":"3920",
    "sg:province":"Valais",
    "wof:name":"Restaurant Zeughaus Grenzstr.",
    "wof:placetype":"venue"
},
  "geometry": {"coordinates":[9.3595075607,47.4177894592],"type":"Point"}
}