{
  "type": "Feature",
  "properties": {
    "iso:country":"CH",
    "sg:address":"Marktgasse 39",
    "sg:city":"Winterthur",
    "sg:orig_category":"Grosshandel mit Schmuck Grosshandel mit Uhren",
    "sg:phone":"+41 32 342 33 27",
    "sg:postcode":"8400",
    "sg:province":"Z\u00fcrich",
    "wof:name":"Chaumet Horlogerie Sa",
    "wof:placetype":"venue"
},
  "geometry": {"coordinates":[7.291864872,47.16173172],"type":"Point"}
}