{
  "type": "Feature",
  "properties": {
    "iso:country":"CH",
    "sg:address":"Landstrasse 1",
    "sg:city":"Dietfurt",
    "sg:orig_category":"Herstellung von sonstigen landwirtschaftlichen Maschinen Mechanik",
    "sg:phone":"+41 52 364 27 64",
    "sg:postcode":"9615",
    "sg:province":"St. Gallen",
    "wof:name":"Staub Ag Hagenbuch",
    "wof:placetype":"venue"
},
  "geometry": {"coordinates":[8.8900880814,47.521648407],"type":"Point"}
}