{
  "type": "Feature",
  "properties": {
    "iso:country":"CH",
    "sg:address":"Route De France 3",
    "sg:city":"Boncourt",
    "sg:classifiers":[
        {
            "category":"Banks & Credit Unions",
            "subcategory":"Bank",
            "type":"Services"
        }
    ],
    "sg:phone":"+41 32755171",
    "sg:postcode":"2926",
    "sg:province":"Jura",
    "wof:name":"Banque Cantonale Du Jura",
    "wof:placetype":"venue"
},
  "geometry": {"coordinates":[7.015354,47.496506],"type":"Point"}
}