{
  "type": "Feature",
  "properties": {
    "iso:country":"CH",
    "sg:address":"Chemin Du Ruttet 5",
    "sg:city":"Gland",
    "sg:orig_category":"Instandhaltung U Reparatur von Automobilen",
    "sg:phone":"+41 79 200 54 17",
    "sg:postcode":"1196",
    "sg:province":"Vaud",
    "wof:name":"Auto-service Atelier M\u00e9canique-\u00e9lectricit\u00e9 Transformation Pour Conducteurs Handicap\u00e9s",
    "wof:placetype":"venue"
},
  "geometry": {"coordinates":[6.2733712196,46.4222717285],"type":"Point"}
}