{
  "type": "Feature",
  "properties": {
    "iso:country":"CH",
    "sg:address":"Bergstrasse 2 5430 Wettingen. Postfach",
    "sg:city":"Wettingen",
    "sg:orig_category":"Hardwareberatung",
    "sg:postcode":"5430",
    "sg:province":"Aargau",
    "wof:name":"Spic Networks, Spickmann Ren\u00e9",
    "wof:placetype":"venue"
},
  "geometry": {"coordinates":[8.3357391357,47.4673233032],"type":"Point"}
}