{
  "type": "Feature",
  "properties": {
    "iso:country":"CH",
    "sg:address":"Hummelbergstrasse 14",
    "sg:city":"Jona",
    "sg:orig_category":"Non-Classified Establishments",
    "sg:postcode":"8645",
    "sg:province":"St. Gallen",
    "wof:name":"Eugenio Priolo Malergesch\u00e4ft",
    "wof:placetype":"venue"
},
  "geometry": {"coordinates":[8.8387174606,47.2952842712],"type":"Point"}
}