{
  "type": "Feature",
  "properties": {
    "iso:country":"CH",
    "sg:address":"Quellenstrasse 1",
    "sg:city":"Goldach",
    "sg:orig_category":"Architektur U Ingenieurb\u00fcros",
    "sg:phone":"+41 71 841 05 23",
    "sg:postcode":"9403",
    "sg:province":"St. Gallen",
    "wof:name":"Barletta D. Consulting Consulting Und Handel",
    "wof:placetype":"venue"
},
  "geometry": {"coordinates":[9.47067,47.47263],"type":"Point"}
}