{
  "type": "Feature",
  "properties": {
    "iso:country":"CH",
    "sg:address":"Apothekerstrasse 8",
    "sg:city":"Uster",
    "sg:orig_category":"Instandhaltung U Reparatur von Automobilen",
    "sg:phone":"+41 19942030",
    "sg:postcode":"8610",
    "sg:province":"Z\u00fcrich",
    "wof:name":"Sennhauser H. Ag",
    "wof:placetype":"venue"
},
  "geometry": {"coordinates":[8.715045929,47.3469161987],"type":"Point"}
}