{
  "type": "Feature",
  "properties": {
    "iso:country":"CH",
    "sg:address":"Stockwisli 3",
    "sg:city":"Saland",
    "sg:orig_category":"Rolladen- and Storenmontage",
    "sg:phone":"+41 81 651 32 53",
    "sg:postcode":"8493",
    "sg:province":"Z\u00fcrich",
    "wof:name":"Karl Mani Rolladen & Storen",
    "wof:placetype":"venue"
},
  "geometry": {"coordinates":[9.4528369904,46.699344635],"type":"Point"}
}