{
  "type": "Feature",
  "properties": {
    "iso:country":"CH",
    "sg:address":"Baumackerstrasse 35 8050 Z\u00fcrich 50 Zust. Postfach 8050 Z\u00fcrich",
    "sg:city":"Zust",
    "sg:orig_category":"Saunas, Solarien, Fitnesszentren U \u00e4hnliches",
    "sg:postcode":"50",
    "wof:name":"Tsm Krafttraining Ag Krafttraining Mit Artzpraxis F\u00fcr Medizinische Kr\u00e4ftigungstherapie",
    "wof:placetype":"venue"
},
  "geometry": {"coordinates":[8.5741252899,47.3273048401],"type":"Point"}
}