{
  "type": "Feature",
  "properties": {
    "iso:country":"CH",
    "sg:address":"La Pran 32f",
    "sg:city":"Vicques",
    "sg:orig_category":"Vorschulen, Kinderg\u00e4rten",
    "sg:phone":"+41 32 435 65 59",
    "sg:postcode":"2824",
    "sg:province":"Jura",
    "wof:name":"Ecole Enfantine",
    "wof:placetype":"venue"
},
  "geometry": {"coordinates":[7.4162049294,47.3487281799],"type":"Point"}
}