{
  "type": "Feature",
  "properties": {
    "iso:country":"CH",
    "sg:address":"St\u00e4dtli 23",
    "sg:city":"Wiedlisbach",
    "sg:classifiers":[
        {
            "category":"Restaurant",
            "type":"Food & Drink"
        }
    ],
    "sg:phone":"+41 32 636 28 45",
    "sg:postcode":"4537",
    "sg:province":"Bern",
    "wof:name":"Restaurant Krone",
    "wof:placetype":"venue"
},
  "geometry": {"coordinates":[7.6467928886,47.2516822815],"type":"Point"}
}