{
  "type": "Feature",
  "properties": {
    "iso:country":"CH",
    "sg:address":"Place Du Tunnel 4",
    "sg:city":"Lausanne",
    "sg:orig_category":"Herstellung von elektrischen Lampen U Leuchten Sonstiger Grosshandel",
    "sg:phone":"+41 18057565",
    "sg:postcode":"1005",
    "sg:province":"Vaud",
    "wof:name":"Highlight Handels Ag",
    "wof:placetype":"venue"
},
  "geometry": {"coordinates":[8.6544208527,47.401550293],"type":"Point"}
}