{
  "type": "Feature",
  "properties": {
    "iso:country":"CH",
    "sg:address":"Schomattenstrasse 8",
    "sg:city":"Wattwil",
    "sg:orig_category":"Herstellung von Metallkonstruktionen Schlossereien",
    "sg:phone":"+41 71 988 11 57",
    "sg:postcode":"9630",
    "sg:province":"St. Gallen",
    "wof:name":"Werner Herzig Eisenkonstruktionen",
    "wof:placetype":"venue"
},
  "geometry": {"coordinates":[9.0842943192,47.3022460938],"type":"Point"}
}