{
  "type": "Feature",
  "properties": {
    "iso:country":"CH",
    "sg:address":"Blotzheimerstrasse 61",
    "sg:city":"Basel",
    "sg:classifiers":[
        {
            "category":"Government",
            "subcategory":"Post Office",
            "type":"Public Place"
        }
    ],
    "sg:phone":"+41 61 381 47 17",
    "sg:postcode":"4055",
    "sg:province":"Basel-Stadt",
    "sg:tags":[
        "caf\u00e9s",
        "tea-rooms"
    ],
    "wof:name":"Caf\u00e9 Capuccino",
    "wof:placetype":"venue"
},
  "geometry": {"coordinates":[7.5648198128,47.5612411499],"type":"Point"}
}