{
  "type": "Feature",
  "properties": {
    "iso:country":"CH",
    "sg:address":"Alte Gfennstrasse 15",
    "sg:city":"D\u00fcbendorf",
    "sg:orig_category":"D\u00e4mmung gegen K\u00e4lte, W\u00e4rme, Schall U Ersch\u00fctterung Herstellung von sonstigen Metallwaren",
    "sg:phone":"+41 79 352 29 45",
    "sg:postcode":"8600",
    "sg:province":"Z\u00fcrich",
    "wof:name":"Rd Fensterdichtungen Gmbh",
    "wof:placetype":"venue"
},
  "geometry": {"coordinates":[8.6267051697,47.3955841064],"type":"Point"}
}