{
  "type": "Feature",
  "properties": {
    "iso:country":"CH",
    "sg:address":"Gaiserstrasse 4a",
    "sg:city":"Appenzell",
    "sg:orig_category":"Kunsthandel",
    "sg:phone":"+41 71 787 10 06",
    "sg:postcode":"9050",
    "sg:province":"Appenzell Innerhoden",
    "wof:name":"Galerie Pappelhof",
    "wof:placetype":"venue"
},
  "geometry": {"coordinates":[9.4109363556,47.3310012817],"type":"Point"}
}