{
  "type": "Feature",
  "properties": {
    "iso:country":"CH",
    "sg:address":"Hammerstrasse 17 4410 Liestal. Postfach 489",
    "sg:city":"Liestal",
    "sg:orig_category":"Handel mit Automobilen",
    "sg:postcode":"4410",
    "sg:province":"Basel-Landschaft",
    "wof:name":"Auto Shillova",
    "wof:placetype":"venue"
},
  "geometry": {"coordinates":[8.8199157715,47.307559967],"type":"Point"}
}