{
  "type": "Feature",
  "properties": {
    "iso:country":"CH",
    "sg:address":"Sonnenberg 13",
    "sg:city":"Herisau",
    "sg:orig_category":"Bau U Wohngenossenschaften",
    "sg:postcode":"9100",
    "sg:province":"Appenzell Ausserrhoden",
    "wof:name":"Wohnbaugen.sonnenberg Herisau",
    "wof:placetype":"venue"
},
  "geometry": {"coordinates":[9.280127,47.38089],"type":"Point"}
}