{
  "type": "Feature",
  "properties": {
    "iso:country":"CH",
    "sg:address":"Stetterstrasse 25",
    "sg:city":"Mellingen",
    "sg:orig_category":"Non-Classified Establishments",
    "sg:postcode":"5507",
    "sg:province":"Aargau",
    "wof:name":"Domis Sa Conseils & Gestion De Soci\u00e9t\u00e9s",
    "wof:placetype":"venue"
},
  "geometry": {"coordinates":[6.1413788795,46.1846542358],"type":"Point"}
}