{
  "type": "Feature",
  "properties": {
    "iso:country":"CH",
    "sg:address":"6772",
    "sg:city":"Rodi-fiesso",
    "sg:orig_category":"Sportvereine Ballsport Fussball",
    "sg:phone":"+41 91 867 12 62",
    "sg:postcode":"6772",
    "sg:province":"Ticino",
    "wof:name":"As Rodi-fiesso",
    "wof:placetype":"venue"
},
  "geometry": {"coordinates":[8.7379398346,46.4897994995],"type":"Point"}
}