{
  "type": "Feature",
  "properties": {
    "iso:country":"CH",
    "sg:address":"M\u00fcnchensteinerstrasse 288 4053 Basel. Postfach",
    "sg:city":"Basel",
    "sg:orig_category":"Grosshandel mit Holz U Bauelementen aus Holz",
    "sg:phone":"+41 61 261 99 90",
    "sg:postcode":"4012",
    "sg:province":"Basel-Stadt",
    "wof:name":"Fournier Ag H\u00f6lzer, Fourniere Usw; Import U. Export.",
    "wof:placetype":"venue"
},
  "geometry": {"coordinates":[7.6097598076,47.5357017517],"type":"Point"}
}