{
  "type": "Feature",
  "properties": {
    "iso:country":"CH",
    "sg:address":"Feldwiesenstrasse 57",
    "sg:city":"L\u00fcchingen",
    "sg:orig_category":"Herstellung von keramischen Haushaltswaren U Ziergegenst\u00e4nden",
    "sg:phone":"+41 71 755 14 83",
    "sg:postcode":"9450",
    "sg:province":"St. Gallen",
    "wof:name":"Enzler Friedrich",
    "wof:placetype":"venue"
},
  "geometry": {"coordinates":[9.5544033051,47.3862304688],"type":"Point"}
}