{
  "type": "Feature",
  "properties": {
    "iso:country":"CH",
    "sg:address":"Bahnhofstrasse 40",
    "sg:city":"Root",
    "sg:orig_category":"Handel mit Motorr\u00e4dern, Teilen U Zubeh\u00f6r Instandhaltung U Reparatur von Motorr\u00e4dern",
    "sg:phone":"+41 17763436",
    "sg:postcode":"6037",
    "sg:province":"Luzern",
    "wof:name":"Power-bike Gmbh",
    "wof:placetype":"venue"
},
  "geometry": {"coordinates":[8.4508714676,47.2806625366],"type":"Point"}
}