{
  "type": "Feature",
  "properties": {
    "iso:country":"CH",
    "sg:address":"Route Brent 9",
    "sg:city":"Blonay",
    "sg:orig_category":"Sanit\u00e4r, Heizungs U L\u00fcftungsinstallation Sanit\u00e4rinstallation",
    "sg:phone":"+41 79 412 84 05",
    "sg:postcode":"1807",
    "sg:province":"Vaud",
    "wof:name":"Montet, Michel",
    "wof:placetype":"venue"
},
  "geometry": {"coordinates":[6.8938369751,46.4639358521],"type":"Point"}
}