{
  "type": "Feature",
  "properties": {
    "iso:country":"CH",
    "sg:address":"Les Moulins",
    "sg:city":"Bi\u00e8re",
    "sg:orig_category":"Non-Classified Establishments",
    "sg:postcode":"1145",
    "sg:province":"Vaud",
    "wof:name":"Soulier Sports S\u00e0rl",
    "wof:placetype":"venue"
},
  "geometry": {"coordinates":[6.3437142372,46.5316047668],"type":"Point"}
}