{
  "type": "Feature",
  "properties": {
    "iso:country":"CH",
    "sg:address":"Route De Renens 1 1030 Bussigny-lausanne. Postfach 192",
    "sg:city":"Bussigny-lausanne",
    "sg:orig_category":"Architektur U Ingenieurb\u00fcros Fernmeldedienste",
    "sg:phone":"+41 61 963 11 11",
    "sg:postcode":"1030",
    "sg:province":"Vaud",
    "wof:name":"Akas Engineering Ag",
    "wof:placetype":"venue"
},
  "geometry": {"coordinates":[7.752294,47.390701],"type":"Point"}
}