{
  "type": "Feature",
  "properties": {
    "iso:country":"CH",
    "sg:address":"Grand-rue 5",
    "sg:city":"Porrentruy",
    "sg:classifiers":[
        {
            "category":"Education",
            "subcategory":"Library",
            "type":"Public Place"
        }
    ],
    "sg:phone":"+41 32 465 78 90",
    "sg:postcode":"2900",
    "sg:province":"Jura",
    "sg:tags":[
        "u",
        "bibliotheken",
        "archive"
    ],
    "wof:name":"Biblioth\u00e8que Municipale",
    "wof:placetype":"venue"
},
  "geometry": {"coordinates":[7.07512,47.416607],"type":"Point"}
}