{
  "type": "Feature",
  "properties": {
    "addr:full":"Austrasse 5 Flamatt Fribourg 3175",
    "addr:housenumber":"5",
    "addr:postcode":"3175",
    "addr:street":"Austrasse",
    "iso:country":"CH",
    "sg:address":"Austrasse 5",
    "sg:city":"Flamatt",
    "sg:orig_category":"Bauschreinerei",
    "sg:phone":"+41 31 741 25 46",
    "sg:postcode":"3175",
    "sg:province":"Fribourg",
    "wof:name":"Ulrich Berger Schreinerei",
    "wof:placetype":"venue"
},
  "geometry": {"coordinates":[7.31216,46.890739],"type":"Point"}
}