{
  "type": "Feature",
  "properties": {
    "iso:country":"CH",
    "sg:address":"Fribourg Rue De 40 2503 Biel/bienne. Postfach",
    "sg:city":"Biel/bienne",
    "sg:orig_category":"Druckweiterverarbeitung",
    "sg:phone":"+41 32 323 93 80",
    "sg:postcode":"2503",
    "sg:province":"Bern",
    "wof:name":"Zingg Design",
    "wof:placetype":"venue"
},
  "geometry": {"coordinates":[7.2490200996,47.1324310303],"type":"Point"}
}