{
  "type": "Feature",
  "properties": {
    "iso:country":"CH",
    "sg:address":"Lindenstrasse 12",
    "sg:city":"Widnau",
    "sg:orig_category":"Massagestudios",
    "sg:phone":"+41 81 833 10 85",
    "sg:postcode":"9443",
    "sg:province":"St. Gallen",
    "wof:name":"Waldhaus Am See Massagen",
    "wof:placetype":"venue"
},
  "geometry": {"coordinates":[9.8484210968,46.4974937439],"type":"Point"}
}