{
  "type": "Feature",
  "properties": {
    "iso:country":"CH",
    "sg:address":"Motta Via Giuseppe 10",
    "sg:city":"Chiasso",
    "sg:orig_category":"Handels-H\u00e4user U Gesellschaften",
    "sg:phone":"+41 56 631 94 40",
    "sg:postcode":"6830",
    "sg:province":"Ticino",
    "wof:name":"Isko-trend Kovacs I.",
    "wof:placetype":"venue"
},
  "geometry": {"coordinates":[8.348241806,47.3481025696],"type":"Point"}
}