{
  "type": "Feature",
  "properties": {
    "iso:country":"CH",
    "sg:address":"Hauptstr. 13. 4702 Oensingen. Postfach 30",
    "sg:city":"Oensingen",
    "sg:orig_category":"Herstellung von Oberbekleidung",
    "sg:phone":"+41 62 396 19 59",
    "sg:postcode":"4702",
    "sg:province":"Solothurn",
    "wof:name":"Modehaus Peter Siegrist",
    "wof:placetype":"venue"
},
  "geometry": {"coordinates":[7.716673851,47.2904853821],"type":"Point"}
}