{
  "type": "Feature",
  "properties": {
    "iso:country":"CH",
    "sg:address":"Alte Gasse 23",
    "sg:city":"Zermatt",
    "sg:orig_category":"Informatikdienste",
    "sg:postcode":"3920",
    "sg:province":"Valais",
    "wof:name":"Tek-net Inc, Perren Raoul",
    "wof:placetype":"venue"
},
  "geometry": {"coordinates":[7.7432398796,46.0244255066],"type":"Point"}
}