{
  "type": "Feature",
  "properties": {
    "iso:country":"CH",
    "sg:address":"Piazza Grande 15",
    "sg:city":"Giubiasco",
    "sg:orig_category":"RESTAURANTS: TEA-ROOMS",
    "sg:phone":"+41 91 857 18 88",
    "sg:postcode":"6512",
    "sg:province":"Ticino",
    "wof:name":"Ristorante Cima Piazza",
    "wof:placetype":"venue"
},
  "geometry": {"coordinates":[9.0112724304,46.1707687378],"type":"Point"}
}