{
  "type": "Feature",
  "properties": {
    "iso:country":"CH",
    "sg:address":"Mittelg\u00e4ustrasse 63",
    "sg:city":"Gunzgen",
    "sg:orig_category":"Ger\u00fcstbau Sonstiger spezialisierter Hoch U Tiefbau",
    "sg:phone":"+41 62 216 04 02",
    "sg:postcode":"4617",
    "sg:province":"Solothurn",
    "wof:name":"Kamber Ger\u00fcste",
    "wof:placetype":"venue"
},
  "geometry": {"coordinates":[7.8263401985,47.3140640259],"type":"Point"}
}