{
  "type": "Feature",
  "properties": {
    "iso:country":"CH",
    "sg:address":"Rue De La Gare 19",
    "sg:city":"Montreux",
    "sg:orig_category":"Elektroinstallation",
    "sg:phone":"+41 79 606 25 63",
    "sg:postcode":"1820",
    "sg:province":"Vaud",
    "wof:name":"Rothen Andr\u00e9 Sa",
    "wof:placetype":"venue"
},
  "geometry": {"coordinates":[6.9115309715,46.4364395142],"type":"Point"}
}