{
  "type": "Feature",
  "properties": {
    "iso:country":"CH",
    "sg:address":"Lufenwies 5",
    "sg:city":"Altendorf",
    "sg:orig_category":"Werbung",
    "sg:phone":"+41 79 692 18 20",
    "sg:postcode":"8852",
    "sg:province":"Schwyz",
    "wof:name":"Knobel Marketing",
    "wof:placetype":"venue"
},
  "geometry": {"coordinates":[8.8333940506,47.192741394],"type":"Point"}
}