{
  "type": "Feature",
  "properties": {
    "iso:country":"CH",
    "sg:address":"Rue De La Forge 1",
    "sg:city":"Ch\u00e9zard-st-martin",
    "sg:orig_category":"Zimmerei, Dachdeckerei, Bauspenglerei U Abdichtung",
    "sg:phone":"+41 32 853 41 07",
    "sg:postcode":"2054",
    "sg:province":"Neuch\u00e2tel",
    "wof:name":"Bellenot Fr\u00e8res",
    "wof:placetype":"venue"
},
  "geometry": {"coordinates":[6.9226789474,47.0643043518],"type":"Point"}
}