{
  "type": "Feature",
  "properties": {
    "iso:country":"CH",
    "sg:address":"Florastrasse 14",
    "sg:city":"Uster",
    "sg:orig_category":"Kosmetikinstitute",
    "sg:phone":"+41 19421535",
    "sg:postcode":"8610",
    "sg:province":"Z\u00fcrich",
    "wof:name":"City Cosmetic Yvonne Bosshard-heiniger",
    "wof:placetype":"venue"
},
  "geometry": {"coordinates":[8.7195339203,47.34765625],"type":"Point"}
}