{
  "type": "Feature",
  "properties": {
    "iso:country":"CH",
    "sg:address":"M\u00fchleschlucht",
    "sg:city":"Gadmen",
    "sg:orig_category":"Sportvereine Ski",
    "sg:phone":"+41 33 975 14 61",
    "sg:postcode":"3863",
    "sg:province":"Bern",
    "wof:name":"Nord.skiclub O'hasli Meiringen",
    "wof:placetype":"venue"
},
  "geometry": {"coordinates":[8.3517541885,46.7367591858],"type":"Point"}
}