{
  "type": "Feature",
  "properties": {
    "iso:country":"CH",
    "sg:address":"Via Monte Generoso 12 B",
    "sg:city":"Balerna",
    "sg:orig_category":"Abbruch U Sprenggewerbe, Erdbewegungsarbeiten Erdbewegungsarbeiten",
    "sg:phone":"+41 91 683 06 71",
    "sg:postcode":"6828",
    "sg:province":"Ticino",
    "wof:name":"Arnaboldi Ernesto Sa",
    "wof:placetype":"venue"
},
  "geometry": {"coordinates":[9.003928,45.852974],"type":"Point"}
}