{
  "type": "Feature",
  "properties": {
    "iso:country":"CH",
    "sg:address":"Blumattstrasse 19",
    "sg:city":"Ennetb\u00fcrgen",
    "sg:orig_category":"Softwareentwicklung U beratung",
    "sg:phone":"+41 41 620 27 58",
    "sg:postcode":"6373",
    "sg:province":"Nidwalden",
    "wof:name":"Weber Hard- + Software",
    "wof:placetype":"venue"
},
  "geometry": {"coordinates":[8.4084796906,46.9824523926],"type":"Point"}
}