{
  "type": "Feature",
  "properties": {
    "iso:country":"CH",
    "sg:address":"Grottes Rue Des 9 1201 Gen\u00e8ve. Postfach",
    "sg:city":"Gen\u00e8ve",
    "sg:orig_category":"Sonstiger Fachdetailhandel mit Nahrungsmitteln, Getr\u00e4nken U Tabak in Verkaufsr\u00e4umen",
    "sg:postcode":"1201",
    "sg:province":"Gen\u00e8ve",
    "wof:name":"Yadigaroglu H.",
    "wof:placetype":"venue"
},
  "geometry": {"coordinates":[6.1392202377,46.2103652954],"type":"Point"}
}