{
  "type": "Feature",
  "properties": {
    "iso:country":"CH",
    "sg:address":"Hobacker 3852 Ringgenberg Be. Postfach",
    "sg:city":"Goldswil",
    "sg:orig_category":"Wohnheime",
    "sg:postcode":"3805",
    "sg:province":"Bern",
    "wof:name":"Seniorenvilla Allegro, Yvonne D\u00fcrig",
    "wof:placetype":"venue"
},
  "geometry": {"coordinates":[7.8954749107,46.7019309998],"type":"Point"}
}