{
  "type": "Feature",
  "properties": {
    "addr:full":"Winkelacker 7 Altnau Thurgau 8595",
    "addr:housenumber":"7",
    "addr:postcode":"8595",
    "addr:street":"Winkelacker",
    "iso:country":"CH",
    "sg:address":"Winkelacker 7",
    "sg:city":"Altnau",
    "sg:orig_category":"Bauspenglerei Zimmerei, Dachdeckerei, Bauspenglerei U Abdichtung",
    "sg:phone":"+41 71 695 18 29",
    "sg:postcode":"8595",
    "sg:province":"Thurgau",
    "wof:name":"Aeberhard Spenglerei & Sanit\u00e4r Gmbh",
    "wof:placetype":"venue"
},
  "geometry": {"coordinates":[9.256793,47.612167],"type":"Point"}
}