{
  "type": "Feature",
  "properties": {
    "iso:country":"CH",
    "sg:address":"Granois",
    "sg:city":"Chandolin-savi\u00e8se",
    "sg:orig_category":"RESTAURANTS: TEA-ROOMS",
    "sg:postcode":"1965",
    "sg:province":"Valais",
    "wof:name":"Roten Lucile, Mme.",
    "wof:placetype":"venue"
},
  "geometry": {"coordinates":[7.3407878876,46.2494010925],"type":"Point"}
}