{
  "type": "Feature",
  "properties": {
    "iso:country":"CH",
    "sg:address":"Place De La Libert\u00e9 6",
    "sg:city":"Vallorbe",
    "sg:orig_category":"Detailhandel mit Radio U Fernsehger\u00e4ten Detailhandel mit elektrischen Haushalts-,Radio U Fernsehger\u00e4",
    "sg:phone":"+41 21 843 28 27",
    "sg:postcode":"1337",
    "sg:province":"Vaud",
    "wof:name":"Vision 2000 Strehl & Pinter Radio Tv Hifi Vid\u00e9o",
    "wof:placetype":"venue"
},
  "geometry": {"coordinates":[6.3756899834,46.711894989],"type":"Point"}
}