{
  "type": "Feature",
  "properties": {
    "iso:country":"CH",
    "sg:address":"Feigelstrasse 40 4600 Olten. Postfach",
    "sg:city":"Olten",
    "sg:orig_category":"Baugewerbe Herstellung von Metallkonstruktionen",
    "sg:phone":"+41 62 212 12 46",
    "sg:postcode":"4600",
    "sg:province":"Solothurn",
    "wof:name":"Spleiss Und Montage Ag",
    "wof:placetype":"venue"
},
  "geometry": {"coordinates":[7.893781,47.352081],"type":"Point"}
}