{
  "type": "Feature",
  "properties": {
    "iso:country":"CH",
    "sg:address":"L\u00e4nggenstrasse 28",
    "sg:city":"Bachenb\u00fclach",
    "sg:orig_category":"Vermietung U Verpachtung von eigenen Immobilien",
    "sg:postcode":"8184",
    "sg:province":"Z\u00fcrich",
    "wof:name":"Mapa Immobilien Ag",
    "wof:placetype":"venue"
},
  "geometry": {"coordinates":[8.5401878357,47.5028610229],"type":"Point"}
}