{
  "type": "Feature",
  "properties": {
    "iso:country":"CH",
    "sg:address":"Alpenblick 13",
    "sg:city":"Neuenkirch",
    "sg:orig_category":"Unternehmensberatung Wirtschaftspr\u00fcfung, Steuerberatung U Treuhand",
    "sg:phone":"+41 41 468 00 54",
    "sg:postcode":"6206",
    "sg:province":"Luzern",
    "wof:name":"Waldburger Treuhand Rwt",
    "wof:placetype":"venue"
},
  "geometry": {"coordinates":[8.2003698349,47.096496582],"type":"Point"}
}