{
  "type": "Feature",
  "properties": {
    "iso:country":"CH",
    "sg:address":"Vogelsang",
    "sg:city":"Eich",
    "sg:orig_category":"Handelsvermittlung von Textilien, Bekleidung, Schuhen U Lederwaren Unternehmensberatung",
    "sg:phone":"+41 41 460 44 33",
    "sg:postcode":"6205",
    "sg:province":"Luzern",
    "wof:name":"Marc Daniel Personal-& Unternehmensberat.",
    "wof:placetype":"venue"
},
  "geometry": {"coordinates":[8.1756401062,47.1612701416],"type":"Point"}
}