{
  "type": "Feature",
  "properties": {
    "iso:country":"CH",
    "sg:address":"Laupenstrasse 1",
    "sg:city":"Bern",
    "sg:orig_category":"RESTAURANTS: TEA-ROOMS",
    "sg:phone":"+41 27 971 33 71",
    "sg:postcode":"3008",
    "sg:province":"Bern",
    "wof:name":"Restaurant Castle, Gschwendtner Peter",
    "wof:placetype":"venue"
},
  "geometry": {"coordinates":[8.2168703079,46.4560203552],"type":"Point"}
}