{
  "type": "Feature",
  "properties": {
    "iso:country":"CH",
    "sg:address":"Ehretstrasse 2",
    "sg:city":"H\u00fcnenberg",
    "sg:classifiers":[
        {
            "category":"Education",
            "subcategory":"Vocational School",
            "type":"Public Place"
        }
    ],
    "sg:phone":"+41 71 333 12 63",
    "sg:postcode":"6331",
    "sg:province":"Zug",
    "sg:tags":[
        "koch-",
        "haushaltschulen"
    ],
    "wof:name":"Haushaltungsschule Schulhaus H\u00f6rli",
    "wof:placetype":"venue"
},
  "geometry": {"coordinates":[9.3884601593,47.3905601501],"type":"Point"}
}