{
  "type": "Feature",
  "properties": {
    "iso:country":"CH",
    "sg:address":"Chemin Du Capelard 1",
    "sg:city":"Lausanne",
    "sg:orig_category":"Detailhandel mit Blumen U Pflanzen Fachdetailhandel in Verkaufsr\u00e4umen",
    "sg:phone":"+41 21 616 24 23",
    "sg:postcode":"1007",
    "sg:province":"Vaud",
    "wof:name":"La Corbeille Fleurie, Blanchet Antoinette",
    "wof:placetype":"venue"
},
  "geometry": {"coordinates":[6.608495,46.519135],"type":"Point"}
}