{
  "type": "Feature",
  "properties": {
    "iso:country":"CH",
    "sg:address":"Bachwies 6",
    "sg:city":"Effretikon",
    "sg:orig_category":"Institutionen f\u00fcr Behinderte Tagesheime f\u00fcr Behinderte, gesch\u00fctzte Werkst\u00e4tten",
    "sg:phone":"+41 52 343 10 21",
    "sg:postcode":"8307",
    "sg:province":"Z\u00fcrich",
    "wof:name":"Wohnheim Ilgenmoos",
    "wof:placetype":"venue"
},
  "geometry": {"coordinates":[8.6930322647,47.4201202393],"type":"Point"}
}