{
  "type": "Feature",
  "properties": {
    "iso:country":"CH",
    "sg:address":"Ausserstadel",
    "sg:city":"Muolen",
    "sg:orig_category":"Haltung von Rindern",
    "sg:postcode":"9313",
    "sg:province":"St. Gallen",
    "wof:name":"Braunviehzuchtgenossenschaft Muri",
    "wof:placetype":"venue"
},
  "geometry": {"coordinates":[8.3174819946,47.2825775146],"type":"Point"}
}