{
  "type": "Feature",
  "properties": {
    "iso:country":"CH",
    "sg:address":"Hertistudenstrasse 63",
    "sg:city":"Unteriberg",
    "sg:orig_category":"Herstellung von keramischen Wand U Bodenfliesen U platten",
    "sg:phone":"+41 71 966 31 73",
    "sg:postcode":"8842",
    "sg:province":"Schwyz",
    "wof:name":"Bruno Pircher, Keramische Plattenbel\u00e4ge",
    "wof:placetype":"venue"
},
  "geometry": {"coordinates":[8.9991559982,47.4750900269],"type":"Point"}
}