{
  "type": "Feature",
  "properties": {
    "iso:country":"CH",
    "sg:address":"Derri\u00e8re-les-jardins 1",
    "sg:city":"Fribourg",
    "sg:orig_category":"Grosshandel mit Nahrungsmitteln, Getr\u00e4nken U Tabakwaren ohne ausgepr\u00e4gten Schwerpunkt",
    "sg:phone":"+41 26 323 20 09",
    "sg:postcode":"1700",
    "sg:province":"Fribourg",
    "wof:name":"Lupita, Soto Gauch Mme Georgina",
    "wof:placetype":"venue"
},
  "geometry": {"coordinates":[7.167883873,46.8030128479],"type":"Point"}
}