{
  "type": "Feature",
  "properties": {
    "iso:country":"CH",
    "sg:address":"Via Riviera 7 6900 Lugano. Postfach",
    "sg:city":"Calprino",
    "sg:orig_category":"RESTAURANTS: TEA-ROOMS",
    "sg:postcode":"6900",
    "sg:province":"Ticino",
    "wof:name":"Gerusta Sa",
    "wof:placetype":"venue"
},
  "geometry": {"coordinates":[8.9709510803,46.0046234131],"type":"Point"}
}