{
  "type": "Feature",
  "properties": {
    "iso:country":"CH",
    "sg:address":"Gerenstrasse 64",
    "sg:city":"Regensdorf",
    "sg:orig_category":"G\u00fcterbef\u00f6rderung im Strassenverkehr",
    "sg:postcode":"8105",
    "sg:province":"Z\u00fcrich",
    "wof:name":"Kouider Boughrara Kubu",
    "wof:placetype":"venue"
},
  "geometry": {"coordinates":[8.4615459442,47.4331893921],"type":"Point"}
}