{
  "type": "Feature",
  "properties": {
    "iso:country":"CH",
    "sg:address":"Pumpwerkstrasse 33 8105 Regensdorf. Postfach 439",
    "sg:city":"Regensdorf",
    "sg:orig_category":"Herstellung von Anstrichmitteln, Druckfarben U Kitten",
    "sg:phone":"+41 18410012",
    "sg:postcode":"8105",
    "sg:province":"Z\u00fcrich",
    "wof:name":"Lackfarben Wagner Heinrich Ag",
    "wof:placetype":"venue"
},
  "geometry": {"coordinates":[8.4601135254,47.4448127747],"type":"Point"}
}