{
  "type": "Feature",
  "properties": {
    "iso:country":"CH",
    "sg:address":"Jurastrasse 26",
    "sg:city":"Seltisberg",
    "sg:orig_category":"Innenarchitekturb\u00fcros",
    "sg:phone":"+41 61 911 99 70",
    "sg:postcode":"4411",
    "sg:province":"Basel-Landschaft",
    "wof:name":"Andreas Holinger Innenarchitekt",
    "wof:placetype":"venue"
},
  "geometry": {"coordinates":[7.7244057655,47.4650154114],"type":"Point"}
}