{
  "type": "Feature",
  "properties": {
    "addr:full":"Bahnhofstr. 5 Subingen Solothurn 4553",
    "addr:housenumber":"5",
    "addr:postcode":"4553",
    "addr:street":"Bahnhofstr.",
    "iso:country":"CH",
    "sg:address":"Bahnhofstr. 5",
    "sg:city":"Subingen",
    "sg:classifiers":[
        {
            "category":"Banks & Credit Unions",
            "subcategory":"Bank",
            "type":"Services"
        }
    ],
    "sg:phone":"+41 32 614 23 64",
    "sg:postcode":"4553",
    "sg:province":"Solothurn",
    "wof:name":"Solothurner Bank Soba",
    "wof:placetype":"venue"
},
  "geometry": {"coordinates":[7.614073,47.19503],"type":"Point"}
}