{
  "type": "Feature",
  "properties": {
    "iso:country":"CH",
    "sg:address":"Dammstrasse 8 6300 Zug. Postfach",
    "sg:city":"Zug",
    "sg:orig_category":"Sonstige pers\u00f6nliche Dienstleistungen",
    "sg:postcode":"6300",
    "sg:province":"Zug",
    "wof:name":"G\u00fcgi Dr. P. Consulting",
    "wof:placetype":"venue"
},
  "geometry": {"coordinates":[8.5470619202,47.3245849609],"type":"Point"}
}