{
  "type": "Feature",
  "properties": {
    "iso:country":"CH",
    "sg:address":"Sur La Place 73a",
    "sg:city":"Bonfol",
    "sg:orig_category":"Detailhandel mit Milcherzeugnissen U Eiern",
    "sg:phone":"+41 32 474 44 52",
    "sg:postcode":"2944",
    "sg:province":"Jura",
    "wof:name":"Hans Anliker Laiterie",
    "wof:placetype":"venue"
},
  "geometry": {"coordinates":[7.1503820419,47.4783592224],"type":"Point"}
}