{
  "type": "Feature",
  "properties": {
    "iso:country":"CH",
    "sg:address":"Seestrasse 141",
    "sg:city":"Z\u00fcrich",
    "sg:classifiers":[
        {
            "category":"Travel",
            "subcategory":"Hotels & Motels",
            "type":"Entertainment"
        }
    ],
    "sg:phone":"+41 41 910 56 30",
    "sg:postcode":"8002",
    "sg:province":"Z\u00fcrich",
    "wof:name":"Chick B.a. & More Ag",
    "wof:placetype":"venue"
},
  "geometry": {"coordinates":[8.5210266113,47.1659355164],"type":"Point"}
}