{
  "type": "Feature",
  "properties": {
    "iso:country":"CH",
    "sg:address":"Rue De Ronzeru 6",
    "sg:city":"St-aubin-sauges",
    "sg:orig_category":"Bauschreinerei Einbau von Schreinerwaren",
    "sg:phone":"+41 32 835 12 23",
    "sg:postcode":"2024",
    "sg:province":"Neuch\u00e2tel",
    "wof:name":"Yves Meylan Menuiserie & Agencement",
    "wof:placetype":"venue"
},
  "geometry": {"coordinates":[6.762499,46.887241],"type":"Point"}
}