{
  "type": "Feature",
  "properties": {
    "iso:country":"CH",
    "sg:address":"Ernetschwilerstrasse 16",
    "sg:city":"Uznach",
    "sg:orig_category":"Herstellung von Elektromotoren, Generatoren U Transformatoren",
    "sg:phone":"+41 55 290 10 90",
    "sg:postcode":"8730",
    "sg:province":"St. Gallen",
    "wof:name":"Cotting Ingenieurb\u00fcro Ag",
    "wof:placetype":"venue"
},
  "geometry": {"coordinates":[8.988026619,47.2275238037],"type":"Point"}
}