{
  "type": "Feature",
  "properties": {
    "iso:country":"CH",
    "sg:address":"Dorfgasse 22",
    "sg:city":"Horgen",
    "sg:orig_category":"Detailhandel mit Uhren U Schmuck Herstellung von Uhren",
    "sg:phone":"+41 17252826",
    "sg:postcode":"8810",
    "sg:province":"Z\u00fcrich",
    "wof:name":"Uhren & Bijouterie Clock Ferenc Radvanszky",
    "wof:placetype":"venue"
},
  "geometry": {"coordinates":[8.599234581,47.2605476379],"type":"Point"}
}