{
  "type": "Feature",
  "properties": {
    "iso:country":"CH",
    "sg:address":"Zentralstrasse 30",
    "sg:city":"Neuhausen",
    "sg:classifiers":[
        {
            "category":"Education",
            "subcategory":"Library",
            "type":"Public Place"
        }
    ],
    "sg:postcode":"8212",
    "sg:province":"Schaffhausen",
    "sg:tags":[
        "u",
        "bibliotheken",
        "archive"
    ],
    "wof:name":"Bibliothek Der Evang.kirchgemeinde",
    "wof:placetype":"venue"
},
  "geometry": {"coordinates":[9.57633,46.98238],"type":"Point"}
}