{
  "type": "Feature",
  "properties": {
    "iso:country":"CH",
    "sg:address":"Sch\u00f6nengrundstrasse 9",
    "sg:city":"D\u00fcbendorf",
    "sg:orig_category":"Innenarchitekturb\u00fcros",
    "sg:phone":"+41 18200937",
    "sg:postcode":"8600",
    "sg:province":"Z\u00fcrich",
    "wof:name":"Willy Kempter Innenarchitekt",
    "wof:placetype":"venue"
},
  "geometry": {"coordinates":[8.6218709946,47.3919525146],"type":"Point"}
}