{
  "type": "Feature",
  "properties": {
    "iso:country":"CH",
    "sg:address":"Via Delle Scuole 16",
    "sg:city":"Lugano",
    "sg:orig_category":"Arztpraxen",
    "sg:phone":"+41 19702858",
    "sg:postcode":"6900",
    "sg:province":"Ticino",
    "wof:name":"Dr. Med. Tamara Von\u00e4sch Aerztin F.allgemeine Medizin",
    "wof:placetype":"venue"
},
  "geometry": {"coordinates":[8.800628,47.326641],"type":"Point"}
}