{
  "type": "Feature",
  "properties": {
    "iso:country":"CH",
    "sg:address":"Leytron Route De",
    "sg:city":"Saillon",
    "sg:orig_category":"Grosshandel mit Getr\u00e4nken",
    "sg:postcode":"1913",
    "sg:province":"Valais",
    "wof:name":"Cave Valcombe Sa",
    "wof:placetype":"venue"
},
  "geometry": {"coordinates":[7.1852998734,46.1719093323],"type":"Point"}
}