{
  "type": "Feature",
  "properties": {
    "iso:country":"CH",
    "sg:address":"Grande-rue 13 2316 Ponts-de-martel Case Postale 107",
    "sg:city":"Ponts-de-martel",
    "sg:orig_category":"Detailhandel mit Fleisch U Fleischwaren",
    "sg:phone":"+41 32 934 30 10",
    "sg:postcode":"2316",
    "sg:province":"Neuch\u00e2tel",
    "wof:name":"Montandon Sa Boucherie-charcuterie",
    "wof:placetype":"venue"
},
  "geometry": {"coordinates":[6.7323579788,46.9994926453],"type":"Point"}
}