{
  "type": "Feature",
  "properties": {
    "iso:country":"CH",
    "sg:address":"Falkenblickstrasse 7",
    "sg:city":"Eichberg",
    "sg:orig_category":"Datenverarbeitungsdienste Elektroinstallation",
    "sg:phone":"+41 71 755 41 35",
    "sg:postcode":"9453",
    "sg:province":"St. Gallen",
    "wof:name":"B\u00fcsser Ag",
    "wof:placetype":"venue"
},
  "geometry": {"coordinates":[9.52721,47.343594],"type":"Point"}
}