{
  "type": "Feature",
  "properties": {
    "iso:country":"CH",
    "sg:address":"Kappelisackerstrasse 75",
    "sg:city":"Ittigen",
    "sg:orig_category":"Vereine Gesang",
    "sg:phone":"+41 31 921 33 09",
    "sg:postcode":"3063",
    "sg:province":"Bern",
    "wof:name":"M\u00e4nnerchor Typographia Bern",
    "wof:placetype":"venue"
},
  "geometry": {"coordinates":[7.4767189026,46.9819831848],"type":"Point"}
}