{
  "type": "Feature",
  "properties": {
    "iso:country":"CH",
    "sg:address":"Schulhausstrasse 4",
    "sg:city":"Meilen",
    "sg:classifiers":[
        {
            "category":"Restaurant",
            "type":"Food & Drink"
        }
    ],
    "sg:phone":"+41 19231467",
    "sg:postcode":"8706",
    "sg:province":"Z\u00fcrich",
    "wof:name":"Restaurant Zum L\u00e4mmli",
    "wof:placetype":"venue"
},
  "geometry": {"coordinates":[8.6409540176,47.2687416077],"type":"Point"}
}