{
  "type": "Feature",
  "properties": {
    "iso:country":"CH",
    "sg:address":"Riedthofstrasse 63",
    "sg:city":"Regensdorf",
    "sg:orig_category":"Unclassifiable Establishments",
    "sg:postcode":"8105",
    "sg:province":"Z\u00fcrich",
    "wof:name":"Audio-video Ehling",
    "wof:placetype":"venue"
},
  "geometry": {"coordinates":[8.467918396,47.4365882874],"type":"Point"}
}