{
  "type": "Feature",
  "properties": {
    "addr:full":"Dorfstr. 16 H\u00e4ggenschwil St. Gallen 9312",
    "addr:housenumber":"16;st.",
    "addr:postcode":"9312",
    "addr:street":"Dorfstr.",
    "iso:country":"CH",
    "sg:address":"Dorfstr. 16",
    "sg:city":"H\u00e4ggenschwil",
    "sg:classifiers":[
        {
            "category":"Banks & Credit Unions",
            "subcategory":"Bank",
            "type":"Services"
        }
    ],
    "sg:phone":"+41 71 298 53 38",
    "sg:postcode":"9312",
    "sg:province":"St. Gallen",
    "wof:name":"Raiffeisenbank",
    "wof:placetype":"venue"
},
  "geometry": {"coordinates":[9.34625,47.49419],"type":"Point"}
}