{
  "type": "Feature",
  "properties": {
    "iso:country":"CH",
    "sg:address":"Haldenstrasse 4",
    "sg:city":"Luzern",
    "sg:orig_category":"Non-Classified Establishments",
    "sg:postcode":"6006",
    "sg:province":"Luzern",
    "wof:name":"Mara Investment Control Gmbh",
    "wof:placetype":"venue"
},
  "geometry": {"coordinates":[8.315032959,47.0548286438],"type":"Point"}
}