{
  "type": "Feature",
  "properties": {
    "iso:country":"CH",
    "sg:address":"Seefeldstrasse 23",
    "sg:city":"Luzern",
    "sg:orig_category":"Stukkateurgewerbe, Gipserei U Verputzerei",
    "sg:phone":"+41 41 370 34 92",
    "sg:postcode":"6006",
    "sg:province":"Luzern",
    "wof:name":"Pp Gips Gmbh",
    "wof:placetype":"venue"
},
  "geometry": {"coordinates":[8.3413982391,47.0506134033],"type":"Point"}
}