{
  "type": "Feature",
  "properties": {
    "iso:country":"CH",
    "sg:address":"Morgental 35",
    "sg:city":"Zumikon",
    "sg:orig_category":"Herstellung von pharmazeutischen Grundstoffen",
    "sg:phone":"+41 19187080",
    "sg:postcode":"8126",
    "sg:province":"Z\u00fcrich",
    "wof:name":"Pharmanet Services Gmbh",
    "wof:placetype":"venue"
},
  "geometry": {"coordinates":[8.6172447205,47.3369750977],"type":"Point"}
}