{
  "type": "Feature",
  "properties": {
    "addr:full":"Chemin Des Bossons 1b Lausanne Vaud 1018",
    "addr:housenumber":"1b",
    "addr:postcode":"1018",
    "addr:street":"Chemin Des Bossons",
    "iso:country":"CH",
    "sg:address":"Chemin Des Bossons 1b",
    "sg:city":"Lausanne",
    "sg:orig_category":"Arztpraxen",
    "sg:phone":"+41 79 210 46 52",
    "sg:postcode":"1018",
    "sg:province":"Vaud",
    "wof:name":"Dres T. Bessard & R. Bielinski M\u00e9decins G\u00e9n\u00e9ralistes Fmh",
    "wof:placetype":"venue"
},
  "geometry": {"coordinates":[6.620819,46.535465],"type":"Point"}
}