{
  "type": "Feature",
  "properties": {
    "iso:country":"CH",
    "sg:address":"Unterer Zielweg 79",
    "sg:city":"Dornach",
    "sg:orig_category":"Detailhandel mit Beleuchtungs U Haushaltsgegenst\u00e4nden Grosshandel mit sonstigen Gebrauchs U Verbrauc",
    "sg:phone":"+41 61 701 22 71",
    "sg:postcode":"4143",
    "sg:province":"Solothurn",
    "wof:name":"Farbenspiel Papeterie Spielsachen",
    "wof:placetype":"venue"
},
  "geometry": {"coordinates":[7.615784,47.485596],"type":"Point"}
}