{
  "type": "Feature",
  "properties": {
    "iso:country":"CH",
    "sg:address":"Viale Portone 43",
    "sg:city":"Arbedo",
    "sg:orig_category":"Tankstellen",
    "sg:phone":"+41 91 829 34 08",
    "sg:postcode":"6517",
    "sg:province":"Ticino",
    "wof:name":"Livia-gianna Guidi Stazione Di Servizio Shell",
    "wof:placetype":"venue"
},
  "geometry": {"coordinates":[9.0421924591,46.2133598328],"type":"Point"}
}