{
  "type": "Feature",
  "properties": {
    "iso:country":"CH",
    "sg:address":"Bahnhofstrasse 1",
    "sg:city":"Villmergen",
    "sg:orig_category":"Interessenvertretungen",
    "sg:postcode":"5612",
    "sg:province":"Aargau",
    "wof:name":"Bopp-bugnon-stiftung",
    "wof:placetype":"venue"
},
  "geometry": {"coordinates":[8.2446422577,47.3473358154],"type":"Point"}
}