{
  "type": "Feature",
  "properties": {
    "iso:country":"CH",
    "sg:address":"Dorfbachstrasse 46",
    "sg:city":"Schwyz",
    "sg:orig_category":"G\u00fcterbef\u00f6rderung im Strassenverkehr",
    "sg:phone":"+41 41 811 20 34",
    "sg:postcode":"6430",
    "sg:province":"Schwyz",
    "wof:name":"Steiner Reisen Autotransporte",
    "wof:placetype":"venue"
},
  "geometry": {"coordinates":[8.6588392258,47.024887085],"type":"Point"}
}