{
  "type": "Feature",
  "properties": {
    "iso:country":"CH",
    "sg:address":"Promenade-noire 1",
    "sg:city":"Neuch\u00e2tel",
    "sg:orig_category":"Personal U Stellenvermittlung Sonstige mit der Informatik verbundene T\u00e4tigkeiten",
    "sg:phone":"+41 32 729 80 00",
    "sg:postcode":"2000",
    "sg:province":"Neuch\u00e2tel",
    "wof:name":"Parity Eurosoft Sa",
    "wof:placetype":"venue"
},
  "geometry": {"coordinates":[6.9278931618,46.9902076721],"type":"Point"}
}