{
  "type": "Feature",
  "properties": {
    "iso:country":"CH",
    "sg:address":"Mont Rue Du 19/21",
    "sg:city":"Sitten",
    "sg:orig_category":"Detailhandel mit Waren verschiedener Art, Hauptrichtung Nahrungsmittel",
    "sg:postcode":"1950",
    "sg:province":"Valais",
    "wof:name":"D\u00e9fago Monique",
    "wof:placetype":"venue"
},
  "geometry": {"coordinates":[7.0122699738,46.1147918701],"type":"Point"}
}