{
  "type": "Feature",
  "properties": {
    "iso:country":"CH",
    "sg:address":"Ausstellungsstrasse 110 8005 Z\u00fcrich. Postfach",
    "sg:city":"Z\u00fcrich",
    "sg:orig_category":"Grosshandel mit sonstigen Nahrungsmitteln",
    "sg:phone":"+41 12725883",
    "sg:postcode":"8001",
    "sg:province":"Z\u00fcrich",
    "wof:name":"Schmidli Gottlieb. Tiefk\u00fchlprodukte; Vertrieb.",
    "wof:placetype":"venue"
},
  "geometry": {"coordinates":[8.5325183868,47.3846054077],"type":"Point"}
}