{
  "type": "Feature",
  "properties": {
    "iso:country":"CH",
    "sg:address":"Lenzb\u00fchl 6",
    "sg:city":"Sirnach",
    "sg:orig_category":"Unclassifiable Establishments",
    "sg:postcode":"8370",
    "sg:province":"Thurgau",
    "wof:name":"Autospritzwerk Roland Mosberger",
    "wof:placetype":"venue"
},
  "geometry": {"coordinates":[9.0248985291,47.4623336792],"type":"Point"}
}