{
  "type": "Feature",
  "properties": {
    "iso:country":"CH",
    "sg:address":"Kirchbergstrasse 25",
    "sg:city":"Biberstein",
    "sg:orig_category":"Geb\u00e4ude, Wohnungsreinigung",
    "sg:phone":"+41 62 827 18 78",
    "sg:postcode":"5023",
    "sg:province":"Aargau",
    "wof:name":"Willi Hunziker Glas-& Geb\u00e4udereinigung",
    "wof:placetype":"venue"
},
  "geometry": {"coordinates":[8.0732069016,47.4125137329],"type":"Point"}
}