{
  "type": "Feature",
  "properties": {
    "iso:country":"CH",
    "sg:address":"Wettsteinstrasse 5",
    "sg:city":"Russikon",
    "sg:orig_category":"Vereine Hundedressur",
    "sg:phone":"+41 19540307",
    "sg:postcode":"8332",
    "sg:province":"Z\u00fcrich",
    "wof:name":"Hundesport Effretikon & Umg.",
    "wof:placetype":"venue"
},
  "geometry": {"coordinates":[8.7761983871,47.3953590393],"type":"Point"}
}