{
  "type": "Feature",
  "properties": {
    "iso:country":"CH",
    "sg:address":"Bahnhofstrasse 78",
    "sg:city":"M\u00f6hlin",
    "sg:orig_category":"Kauf U Verkauf von Immobilien auf eigene Rechnung",
    "sg:phone":"+41 61 851 55 30",
    "sg:postcode":"4313",
    "sg:province":"Aargau",
    "wof:name":"Starnimmo Ag",
    "wof:placetype":"venue"
},
  "geometry": {"coordinates":[7.8446969986,47.5563621521],"type":"Point"}
}