{
  "type": "Feature",
  "properties": {
    "iso:country":"CH",
    "sg:address":"Z\u00fcrichstrasse 5",
    "sg:city":"Luzern",
    "sg:orig_category":"Detailhandel mit Damenbekleidung",
    "sg:phone":"+41 41 412 30 55",
    "sg:postcode":"6004",
    "sg:province":"Luzern",
    "wof:name":"Goldie Textil-ag",
    "wof:placetype":"venue"
},
  "geometry": {"coordinates":[8.310325,47.056435],"type":"Point"}
}