{
  "type": "Feature",
  "properties": {
    "iso:country":"CH",
    "sg:address":"Hauptstrasse 21",
    "sg:city":"B\u00f6nigen",
    "sg:orig_category":"Detailhandel mit Waren verschiedener Art, Hauptrichtung Nahrungsmittel",
    "sg:phone":"+41 33 822 12 93",
    "sg:postcode":"3806",
    "sg:province":"Bern",
    "wof:name":"Annemarie Jaggi Dorflade",
    "wof:placetype":"venue"
},
  "geometry": {"coordinates":[7.8925271034,46.6855239868],"type":"Point"}
}