{
  "type": "Feature",
  "properties": {
    "iso:country":"CH",
    "sg:address":"Sitli",
    "sg:city":"Menzingen",
    "sg:orig_category":"Detailhandel mit Gebrauchtwaren in Verkaufsr\u00e4umen",
    "sg:phone":"+41 41 755 10 33",
    "sg:postcode":"6313",
    "sg:province":"Zug",
    "wof:name":"Brockenstube Menzingen Edith Schmid",
    "wof:placetype":"venue"
},
  "geometry": {"coordinates":[8.591129303,47.1738586426],"type":"Point"}
}