{
  "type": "Feature",
  "properties": {
    "iso:country":"CH",
    "sg:address":"Flughafenstrasse 37",
    "sg:city":"Basel",
    "sg:orig_category":"Wirtschaftspr\u00fcfung, Steuerberatung U Treuhand",
    "sg:phone":"+41 61 383 85 30",
    "sg:postcode":"4056",
    "sg:province":"Basel-Stadt",
    "wof:name":"Acta-treuhand Motalla M\u00e9lanie",
    "wof:placetype":"venue"
},
  "geometry": {"coordinates":[7.5706481934,47.5677337646],"type":"Point"}
}