{
  "type": "Feature",
  "properties": {
    "iso:country":"CH",
    "sg:address":"Luzernerstrasse 105",
    "sg:city":"Muri",
    "sg:classifiers":[
        {
            "category":"Banks & Credit Unions",
            "subcategory":"Bureau De Change",
            "type":"Services"
        }
    ],
    "sg:phone":"+41 56 664 33 35",
    "sg:postcode":"5630",
    "sg:province":"Aargau",
    "sg:tags":[
        "card"
    ],
    "wof:name":"Fischer S\u00f6hne Ag",
    "wof:placetype":"venue"
},
  "geometry": {"coordinates":[8.350058,47.265377],"type":"Point"}
}