{
  "type": "Feature",
  "properties": {
    "iso:country":"CH",
    "sg:address":"Tr\u00fcmmelbach",
    "sg:city":"Lauterbrunnen",
    "sg:classifiers":[
        {
            "category":"Travel",
            "subcategory":"Hotels & Motels",
            "type":"Entertainment"
        }
    ],
    "sg:postcode":"3822",
    "sg:province":"Bern",
    "sg:tags":[
        "hotels",
        "mit",
        "restaurant"
    ],
    "wof:name":"Familie Kaspar Von Almen Ag",
    "wof:placetype":"venue"
},
  "geometry": {"coordinates":[7.9108309746,46.5710906982],"type":"Point"}
}