{
  "type": "Feature",
  "properties": {
    "iso:country":"CH",
    "sg:address":"3206 Rizenbach. Postfach",
    "sg:city":"M\u00fchleberg",
    "sg:orig_category":"Herstellung von sonstigen landwirtschaftlichen Maschinen",
    "sg:postcode":"3203",
    "sg:province":"Bern",
    "wof:name":"Herren Robert",
    "wof:placetype":"venue"
},
  "geometry": {"coordinates":[7.0118999481,46.277141571],"type":"Point"}
}