{
  "type": "Feature",
  "properties": {
    "iso:country":"CH",
    "sg:address":"Plaine Rue De La 22",
    "sg:city":"Yverdon-les-bains",
    "sg:orig_category":"Herstellung von Tanks U Sammelbeh\u00e4ltern aus Metall",
    "sg:phone":"+41 24 445 34 81",
    "sg:postcode":"1400",
    "sg:province":"Vaud",
    "wof:name":"Busset Yves",
    "wof:placetype":"venue"
},
  "geometry": {"coordinates":[6.6414198875,46.7786331177],"type":"Point"}
}