{
  "type": "Feature",
  "properties": {
    "iso:country":"CH",
    "sg:address":"Baarerstrasse 34",
    "sg:city":"Zug",
    "sg:orig_category":"Wirtschaftspr\u00fcfung, Steuerberatung U Treuhand",
    "sg:postcode":"6300",
    "sg:province":"Zug",
    "wof:name":"Scheidegger Treuhand Und Immobilien Ag",
    "wof:placetype":"venue"
},
  "geometry": {"coordinates":[7.56899786,47.0952148438],"type":"Point"}
}