{
  "type": "Feature",
  "properties": {
    "iso:country":"CH",
    "sg:address":"Weinreben 27",
    "sg:city":"H\u00fcnenberg",
    "sg:orig_category":"Gartenbau",
    "sg:phone":"+41 41 780 51 56",
    "sg:postcode":"6331",
    "sg:province":"Zug",
    "wof:name":"A. Scherer Gartenbau Inhaber L.fricker",
    "wof:placetype":"venue"
},
  "geometry": {"coordinates":[8.4238119125,47.1742553711],"type":"Point"}
}