{
  "type": "Feature",
  "properties": {
    "addr:full":"Pl. Centrale 6 Monthey Valais 1870",
    "addr:housenumber":"6",
    "addr:postcode":"1870",
    "addr:street":"Pl. Centrale",
    "iso:country":"CH",
    "sg:address":"Pl. Centrale 6",
    "sg:city":"Monthey",
    "sg:classifiers":[
        {
            "category":"Banks & Credit Unions",
            "subcategory":"Bank",
            "type":"Services"
        }
    ],
    "sg:phone":"+41 27 324 61 11",
    "sg:postcode":"1870",
    "sg:province":"Valais",
    "wof:name":"Banque Cantonale Du Valais",
    "wof:placetype":"venue"
},
  "geometry": {"coordinates":[7.35848,46.23241],"type":"Point"}
}