{
  "type": "Feature",
  "properties": {
    "iso:country":"CH",
    "sg:address":"Fabrikstrasse 6",
    "sg:city":"Herzogenbuchsee",
    "sg:orig_category":"Herstellung von Uhren",
    "sg:postcode":"3360",
    "sg:province":"Bern",
    "wof:name":"Silver Quest Gmbh",
    "wof:placetype":"venue"
},
  "geometry": {"coordinates":[7.7043018341,47.1881790161],"type":"Point"}
}