{
  "type": "Feature",
  "properties": {
    "iso:country":"CH",
    "sg:address":"Route De La Piscine",
    "sg:city":"Sion",
    "sg:orig_category":"Institutionen f\u00fcr Behinderte Tagesheime f\u00fcr Behinderte, gesch\u00fctzte Werkst\u00e4tten",
    "sg:phone":"+41 27 203 71 22",
    "sg:postcode":"1950",
    "sg:province":"Valais",
    "wof:name":"Atelier De La Manufacture",
    "wof:placetype":"venue"
},
  "geometry": {"coordinates":[7.3549551964,46.2249450684],"type":"Point"}
}