{
  "type": "Feature",
  "properties": {
    "iso:country":"CH",
    "sg:address":"Werkstrasse 3",
    "sg:city":"Safnern",
    "sg:orig_category":"Grosshandel mit sonstigen Gebrauchs U Verbrauchsg\u00fctern",
    "sg:phone":"+41 71 744 32 13",
    "sg:postcode":"2553",
    "sg:province":"Bern",
    "wof:name":"Bliem-bruderer H.",
    "wof:placetype":"venue"
},
  "geometry": {"coordinates":[9.6441221237,47.4466438293],"type":"Point"}
}