{
  "type": "Feature",
  "properties": {
    "iso:country":"CH",
    "sg:address":"Via Laveggio 15",
    "sg:city":"Stabio",
    "sg:orig_category":"Herstellung von Akkumulatoren U Batterien Herstellung von sonstigen Fahrzeugen",
    "sg:phone":"+41 91 640 72 80",
    "sg:postcode":"6855",
    "sg:province":"Ticino",
    "wof:name":"Mes-dea Sa",
    "wof:placetype":"venue"
},
  "geometry": {"coordinates":[8.9444074631,45.8479995728],"type":"Point"}
}