{
  "type": "Feature",
  "properties": {
    "iso:country":"CH",
    "sg:address":"Br\u00fcggmatte",
    "sg:city":"Boltigen",
    "sg:orig_category":"Bauschreinerei Herstellung von Konstruktionsteilen, Fertigbauteilen U Ausbauelementen aus Holz",
    "sg:phone":"+41 79 445 03 44",
    "sg:postcode":"3766",
    "sg:province":"Bern",
    "wof:name":"Aegerter Ernst",
    "wof:placetype":"venue"
},
  "geometry": {"coordinates":[7.392464,46.62949],"type":"Point"}
}