{
  "type": "Feature",
  "properties": {
    "iso:country":"CH",
    "sg:address":"Seestrasse 10",
    "sg:city":"Unter\u00e4geri",
    "sg:classifiers":[
        {
            "category":"Travel",
            "subcategory":"Hotels & Motels",
            "type":"Entertainment"
        }
    ],
    "sg:phone":"+41 41 750 27 27",
    "sg:postcode":"6314",
    "sg:province":"Zug",
    "sg:tags":[
        "hotels",
        "mit",
        "restaurant"
    ],
    "wof:name":"Sha Seminar Hotel Ag",
    "wof:placetype":"venue"
},
  "geometry": {"coordinates":[8.5864133835,47.137424469],"type":"Point"}
}