{
  "type": "Feature",
  "properties": {
    "iso:country":"CH",
    "sg:address":"Allmendstrasse 5 5612 Villmergen. Postfach",
    "sg:city":"Villmergen",
    "sg:orig_category":"Herstellung von sonstigen Produkten aus nichtmetallischen Mineralien",
    "sg:postcode":"5612",
    "sg:province":"Aargau",
    "wof:name":"Zisola Ag",
    "wof:placetype":"venue"
},
  "geometry": {"coordinates":[8.2497739792,47.3556022644],"type":"Point"}
}