{
  "type": "Feature",
  "properties": {
    "iso:country":"CH",
    "sg:address":"Avenue Du Mol\u00e9son 10",
    "sg:city":"Fribourg",
    "sg:orig_category":"Bezirks, Sekundar, Realschulen, Oberstufe der Primarschulen Primarschulen",
    "sg:phone":"+41 26 322 30 39",
    "sg:postcode":"1700",
    "sg:province":"Fribourg",
    "wof:name":"Ecole Libre Publique Primaire & Secondaire",
    "wof:placetype":"venue"
},
  "geometry": {"coordinates":[7.148506,46.806404],"type":"Point"}
}