{
  "type": "Feature",
  "properties": {
    "iso:country":"CH",
    "sg:address":"Schneidergasse 810",
    "sg:city":"Basel",
    "sg:orig_category":"Sportvereine Eissport Curling",
    "sg:postcode":"4051",
    "sg:province":"Basel-Stadt",
    "wof:name":"C.c.basel-dollyhay",
    "wof:placetype":"venue"
},
  "geometry": {"coordinates":[7.5344901085,47.545539856],"type":"Point"}
}