{
  "type": "Feature",
  "properties": {
    "iso:country":"CH",
    "sg:address":"6436",
    "sg:city":"Muotathal",
    "sg:orig_category":"Landwirtschaft, Jagd U damit verbundene Dienstleistungen Wohnheime",
    "sg:phone":"+41 41 830 11 14",
    "sg:postcode":"6436",
    "sg:province":"Schwyz",
    "wof:name":"Frauenkloster St.josef",
    "wof:placetype":"venue"
},
  "geometry": {"coordinates":[8.7582998276,46.9739761353],"type":"Point"}
}