{
  "type": "Feature",
  "properties": {
    "iso:country":"CH",
    "sg:address":"Place Village",
    "sg:city":"Bogis-bossey",
    "sg:orig_category":"Kunsthandel",
    "sg:phone":"+41 22 776 61 61",
    "sg:postcode":"1279",
    "sg:province":"Vaud",
    "wof:name":"Monique Dilitz Galerie D'art",
    "wof:placetype":"venue"
},
  "geometry": {"coordinates":[6.1625461578,46.3447494507],"type":"Point"}
}