{
  "type": "Feature",
  "properties": {
    "iso:country":"CH",
    "sg:address":"Hansmatt 32 6370 Stans. Postfach",
    "sg:city":"Stans",
    "sg:orig_category":"Markt U Meinungsforschung Unternehmensberatung",
    "sg:phone":"+41 41 610 84 11",
    "sg:postcode":"6371",
    "sg:province":"Nidwalden",
    "wof:name":"Zotter R.",
    "wof:placetype":"venue"
},
  "geometry": {"coordinates":[8.3516197205,46.9676933289],"type":"Point"}
}