{
  "type": "Feature",
  "properties": {
    "iso:country":"CH",
    "sg:address":"Haus Am See 3a",
    "sg:city":"Weesen",
    "sg:orig_category":"Wirtschaftspr\u00fcfung, Steuerberatung U Treuhand",
    "sg:postcode":"8872",
    "sg:province":"St. Gallen",
    "wof:name":"M\u00fcller-mathis Consulting",
    "wof:placetype":"venue"
},
  "geometry": {"coordinates":[9.1037797928,47.1354789734],"type":"Point"}
}