{
  "type": "Feature",
  "properties": {
    "iso:country":"CH",
    "sg:address":"Farbel Pont 1196 Gland. Postfach",
    "sg:city":"Gland",
    "sg:orig_category":"Non-Classified Establishments",
    "sg:postcode":"1196",
    "sg:province":"Vaud",
    "wof:name":"Elpr1mo Kommunikationskonzepte & Internetdienste B\u00e4chtiger Ernst",
    "wof:placetype":"venue"
},
  "geometry": {"coordinates":[8.8306446075,47.227684021],"type":"Point"}
}