{
  "type": "Feature",
  "properties": {
    "addr:full":"Piazzo Brusio Graubunden 7743",
    "addr:housenumber":"7743",
    "iso:country":"CH",
    "sg:address":"Piazzo",
    "sg:city":"Brusio",
    "sg:orig_category":"Allgemeiner Hoch U Tiefbau Hoch U Tiefbau",
    "sg:phone":"+41 91 791 58 94",
    "sg:postcode":"7743",
    "sg:province":"Graubunden",
    "wof:name":"Elia Verzeroli Impresa Di Costruzione",
    "wof:placetype":"venue"
},
  "geometry": {"coordinates":[8.725171,46.144245],"type":"Point"}
}