{
  "type": "Feature",
  "properties": {
    "iso:country":"CH",
    "sg:address":"4552 Derendingen. Postfach",
    "sg:city":"Derendingen",
    "sg:orig_category":"Vereine Musik/Blasmusik",
    "sg:phone":"+41 32 682 45 25",
    "sg:postcode":"4552",
    "sg:province":"Solothurn",
    "wof:name":"Musikgesellschaft",
    "wof:placetype":"venue"
},
  "geometry": {"coordinates":[7.5903201103,47.1920318604],"type":"Point"}
}