{
  "type": "Feature",
  "properties": {
    "iso:country":"CH",
    "sg:address":"Ruebisbachstrasse 56c",
    "sg:city":"Kloten",
    "sg:orig_category":"G\u00fcterbef\u00f6rderung im Strassenverkehr",
    "sg:postcode":"8302",
    "sg:province":"Z\u00fcrich",
    "wof:name":"Fischer Transport Ag",
    "wof:placetype":"venue"
},
  "geometry": {"coordinates":[8.5794763565,47.4633293152],"type":"Point"}
}