{
  "type": "Feature",
  "properties": {
    "iso:country":"CH",
    "sg:address":"Neuquartier 10",
    "sg:city":"Kriens",
    "sg:orig_category":"Instandhaltung U Reparatur von Automobilen",
    "sg:phone":"+41 41 320 76 29",
    "sg:postcode":"6010",
    "sg:province":"Luzern",
    "wof:name":"Garage Wigger Otto, Inhaber Vogel Hansruedi",
    "wof:placetype":"venue"
},
  "geometry": {"coordinates":[8.2711143494,47.0343894958],"type":"Point"}
}