{
  "type": "Feature",
  "properties": {
    "iso:country":"CH",
    "sg:address":"Els\u00e4sserstrasse 123",
    "sg:city":"Basel",
    "sg:classifiers":[
        {
            "category":"Professional",
            "subcategory":"Employment Agencies",
            "type":"Services"
        }
    ],
    "sg:phone":"+41 61 381 51 44",
    "sg:postcode":"4056",
    "sg:province":"Basel-Stadt",
    "sg:tags":[
        "personal",
        "u",
        "stellenvermittlung"
    ],
    "wof:name":"Personal-sektor Ntshoko R.",
    "wof:placetype":"venue"
},
  "geometry": {"coordinates":[7.5763449669,47.5724143982],"type":"Point"}
}