{
  "type": "Feature",
  "properties": {
    "iso:country":"CH",
    "sg:address":"Aarauerstrasse 29 5603 Staufen. Postfach",
    "sg:city":"Suhr",
    "sg:classifiers":[
        {
            "category":"Travel",
            "subcategory":"Hotels & Motels",
            "type":"Entertainment"
        }
    ],
    "sg:postcode":"5034",
    "sg:province":"Aargau",
    "sg:tags":[
        "hotels",
        "mit",
        "restaurant"
    ],
    "wof:name":"Vogel B.",
    "wof:placetype":"venue"
},
  "geometry": {"coordinates":[8.1679115295,47.3871116638],"type":"Point"}
}