{
  "type": "Feature",
  "properties": {
    "iso:country":"CH",
    "sg:address":"Breitenbachstr. 7",
    "sg:city":"B\u00fcsserach",
    "sg:classifiers":[
        {
            "category":"Home & Garden",
            "subcategory":"Furniture",
            "type":"Retail Goods"
        }
    ],
    "sg:phone":"+41 61 781 11 77",
    "sg:postcode":"4227",
    "sg:province":"Solothurn",
    "sg:tags":[
        "household",
        "wood"
    ],
    "wof:name":"Saner & Co",
    "wof:placetype":"venue"
},
  "geometry": {"coordinates":[7.539607048,47.3911323547],"type":"Point"}
}