{
  "type": "Feature",
  "properties": {
    "iso:country":"CH",
    "sg:address":"Limmatauweg 7",
    "sg:city":"Ennetbaden",
    "sg:orig_category":"Detailhandel mit Radio U Fernsehger\u00e4ten Vermietung von sonstigen Maschinen U Ger\u00e4ten",
    "sg:phone":"+41 56 210 96 76",
    "sg:postcode":"5408",
    "sg:province":"Aargau",
    "wof:name":"Roland Keller Audio-anlagen",
    "wof:placetype":"venue"
},
  "geometry": {"coordinates":[8.3106603622,47.4756736755],"type":"Point"}
}