{
  "type": "Feature",
  "properties": {
    "addr:full":"Nordstrasse 46 Gr\u00e4nichen Aargau 5722",
    "addr:housenumber":"46",
    "addr:postcode":"5722",
    "addr:street":"Nordstrasse",
    "iso:country":"CH",
    "sg:address":"Nordstrasse 46",
    "sg:city":"Gr\u00e4nichen",
    "sg:orig_category":"Architektur U Ingenieurb\u00fcros",
    "sg:phone":"+41 62 842 87 50",
    "sg:postcode":"5722",
    "sg:province":"Aargau",
    "wof:name":"Aim Kaspar Gmbh",
    "wof:placetype":"venue"
},
  "geometry": {"coordinates":[8.096962,47.368038],"type":"Point"}
}