{
  "type": "Feature",
  "properties": {
    "iso:country":"CH",
    "sg:address":"Les Brussattes 22c",
    "sg:city":"Bressaucourt",
    "sg:orig_category":"Grosshandel mit sonstigen Maschinen U Ausr\u00fcstungen f\u00fcr Industrie, Handel U Schiffahrt Mechanische We",
    "sg:phone":"+41 71 393 73 70",
    "sg:postcode":"2904",
    "sg:province":"Jura",
    "wof:name":"Branco Cnc-fertigung Ag Spanabhebende Fertigung Mit Konzentration Auf Kleine U. Mittelgrosse Serien Auszubauen Usw",
    "wof:placetype":"venue"
},
  "geometry": {"coordinates":[9.2117,47.442467],"type":"Point"}
}