{
  "type": "Feature",
  "properties": {
    "iso:country":"CH",
    "sg:address":"Obere Giesslistrasse 9",
    "sg:city":"Ilanz",
    "sg:orig_category":"Unclassifiable Establishments",
    "sg:postcode":"7130",
    "sg:province":"Graubunden",
    "wof:name":"Societad Cooperativa Pistrin Casut Sagogn",
    "wof:placetype":"venue"
},
  "geometry": {"coordinates":[9.2026309967,46.7740287781],"type":"Point"}
}