{
  "type": "Feature",
  "properties": {
    "iso:country":"CH",
    "sg:address":"Place Saint-fran\u00e7ois 5",
    "sg:city":"Lausanne",
    "sg:orig_category":"Unclassifiable Establishments",
    "sg:postcode":"1000",
    "sg:province":"Vaud",
    "wof:name":"Si Du Vieux Devin",
    "wof:placetype":"venue"
},
  "geometry": {"coordinates":[6.6329522133,46.5200996399],"type":"Point"}
}