{
  "type": "Feature",
  "properties": {
    "iso:country":"CH",
    "sg:address":"Hebelstrasse 132",
    "sg:city":"Basel",
    "sg:orig_category":"Sonstige mit der Informatik verbundene T\u00e4tigkeiten",
    "sg:phone":"+41 61 322 49 04",
    "sg:postcode":"4056",
    "sg:province":"Basel-Stadt",
    "wof:name":"Schenk Prospective Development",
    "wof:placetype":"venue"
},
  "geometry": {"coordinates":[7.5765180588,47.5644035339],"type":"Point"}
}