{
  "type": "Feature",
  "properties": {
    "iso:country":"CH",
    "sg:address":"Dorfstrasse 6 9213 Hauptwil. Postfach",
    "sg:city":"Hauptwil",
    "sg:orig_category":"Dachdeckerei Sanit\u00e4r, Heizungs U L\u00fcftungsinstallation",
    "sg:phone":"+41 71 422 35 31",
    "sg:postcode":"9213",
    "sg:province":"Thurgau",
    "wof:name":"Gebr\u00fcder Nater Betriebs Ag",
    "wof:placetype":"venue"
},
  "geometry": {"coordinates":[9.252066,47.479336],"type":"Point"}
}