{
  "type": "Feature",
  "properties": {
    "iso:country":"CH",
    "sg:address":"Rue Du Grand-pont 13",
    "sg:city":"Sion",
    "sg:orig_category":"RESTAURANTS: TEA-ROOMS",
    "sg:postcode":"1950",
    "sg:province":"Valais",
    "wof:name":"Boschetto Marie-claude Mme.",
    "wof:placetype":"venue"
},
  "geometry": {"coordinates":[7.3603520393,46.2339630127],"type":"Point"}
}