{
  "type": "Feature",
  "properties": {
    "iso:country":"CH",
    "sg:address":"Weidweg 5b",
    "sg:city":"Niederlenz",
    "sg:orig_category":"Non-Classified Establishments",
    "sg:phone":"+41 79 435 46 05",
    "sg:postcode":"5702",
    "sg:province":"Aargau",
    "wof:name":"Weiss Unitraders",
    "wof:placetype":"venue"
},
  "geometry": {"coordinates":[8.1716270447,47.408290863],"type":"Point"}
}