{
  "type": "Feature",
  "properties": {
    "iso:country":"CH",
    "sg:address":"Kornplatz 3 7000 Chur. Postfach 475",
    "sg:city":"Chur",
    "sg:orig_category":"Druck ohne Zeitungsdruck Offsetdruck",
    "sg:phone":"+41 81 252 12 27",
    "sg:postcode":"7002",
    "sg:province":"Graubunden",
    "wof:name":"Koch's Erben U.b.",
    "wof:placetype":"venue"
},
  "geometry": {"coordinates":[9.5313997269,46.8488349915],"type":"Point"}
}