{
  "type": "Feature",
  "properties": {
    "iso:country":"CH",
    "sg:address":"Rue Saint-pierre 18 1700 Fribourg. Postfach",
    "sg:city":"Fribourg",
    "sg:orig_category":"Notariate",
    "sg:phone":"+41 21 845 62 66",
    "sg:postcode":"1701",
    "sg:province":"Fribourg",
    "wof:name":"Pierre Badoux Etude De Notaire",
    "wof:placetype":"venue"
},
  "geometry": {"coordinates":[6.2312250137,46.6064987183],"type":"Point"}
}