{
  "type": "Feature",
  "properties": {
    "iso:country":"CH",
    "sg:address":"Acherwies 9 8852 Altendorf. Postfach",
    "sg:city":"Altendorf",
    "sg:orig_category":"Unternehmensberatung",
    "sg:postcode":"8852",
    "sg:province":"Schwyz",
    "wof:name":"Garex Conin Ag Unternehmensberatung Usw",
    "wof:placetype":"venue"
},
  "geometry": {"coordinates":[8.8286714554,47.1857833862],"type":"Point"}
}