{
  "type": "Feature",
  "properties": {
    "iso:country":"CH",
    "sg:address":"Viale Franscini 20",
    "sg:city":"Lugano",
    "sg:orig_category":"Softwareentwicklung U beratung",
    "sg:phone":"+41 91 910 07 50",
    "sg:postcode":"6900",
    "sg:province":"Ticino",
    "wof:name":"Serin Sa",
    "wof:placetype":"venue"
},
  "geometry": {"coordinates":[8.954044342,46.0099563599],"type":"Point"}
}