{
  "type": "Feature",
  "properties": {
    "iso:country":"CH",
    "sg:address":"Engelgasse 7",
    "sg:city":"Appenzell",
    "sg:orig_category":"Sonstige Kultur U Unterhaltungseinrichtungen",
    "sg:postcode":"9050",
    "sg:province":"Appenzell Innerhoden",
    "wof:name":"T & C Touristic Und Casino Ag",
    "wof:placetype":"venue"
},
  "geometry": {"coordinates":[9.4075737,47.3306808472],"type":"Point"}
}