{
  "type": "Feature",
  "properties": {
    "iso:country":"CH",
    "sg:address":"Irchelstrasse 32",
    "sg:city":"Freienstein",
    "sg:orig_category":"Mechanische Werkst\u00e4tten",
    "sg:phone":"+41 18651069",
    "sg:postcode":"8427",
    "sg:province":"Z\u00fcrich",
    "wof:name":"Karl Frei Mechanische Werkst\u00e4tte",
    "wof:placetype":"venue"
},
  "geometry": {"coordinates":[8.5816984177,47.5333442688],"type":"Point"}
}