{
  "type": "Feature",
  "properties": {
    "iso:country":"CH",
    "sg:address":"Rue Du Stand 40",
    "sg:city":"Gen\u00e8ve",
    "sg:orig_category":"Psychotherapie",
    "sg:phone":"+41 22 329 65 55",
    "sg:postcode":"1204",
    "sg:province":"Gen\u00e8ve",
    "wof:name":"Carole Bach Psychoth\u00e9rapie",
    "wof:placetype":"venue"
},
  "geometry": {"coordinates":[6.1381230354,46.2032775879],"type":"Point"}
}