{
  "type": "Feature",
  "properties": {
    "iso:country":"CH",
    "sg:address":"Avenue Du Rothorn 9b",
    "sg:city":"Sierre",
    "sg:classifiers":[
        {
            "category":"Professional",
            "subcategory":"Employment Agencies",
            "type":"Services"
        }
    ],
    "sg:phone":"+41 27 455 14 71",
    "sg:postcode":"3960",
    "sg:province":"Valais",
    "sg:tags":[
        "personal",
        "u",
        "stellenvermittlung"
    ],
    "wof:name":"Acces Job Sa",
    "wof:placetype":"venue"
},
  "geometry": {"coordinates":[7.5320620537,46.2934951782],"type":"Point"}
}