{
  "type": "Feature",
  "properties": {
    "iso:country":"CH",
    "sg:address":"Friedweg 24",
    "sg:city":"Biel/bienne",
    "sg:orig_category":"Bezirks, Sekundar, Realschulen, Oberstufe der Primarschulen",
    "sg:phone":"+41 32 365 65 66",
    "sg:postcode":"2503",
    "sg:province":"Bern",
    "wof:name":"Sekundarschule Madretsch",
    "wof:placetype":"venue"
},
  "geometry": {"coordinates":[7.254498,47.132114],"type":"Point"}
}