{
  "type": "Feature",
  "properties": {
    "iso:country":"CH",
    "sg:address":"Turmgasse",
    "sg:city":"K\u00fcblis",
    "sg:orig_category":"Forstwirtschaft ohne Dienstleistungen in der Forstwirtschaft",
    "sg:phone":"+41 81 332 28 45",
    "sg:postcode":"7240",
    "sg:province":"Graubunden",
    "wof:name":"Bersorger Paul",
    "wof:placetype":"venue"
},
  "geometry": {"coordinates":[9.7760829926,46.9135513306],"type":"Point"}
}