{
  "type": "Feature",
  "properties": {
    "iso:country":"CH",
    "sg:address":"Steistegstrasse 5",
    "sg:city":"Schwyz",
    "sg:orig_category":"Fotografische Ateliers",
    "sg:phone":"+41 26 670 00 18",
    "sg:postcode":"6430",
    "sg:province":"Schwyz",
    "wof:name":"Markus Tanner Foto Future Tanner",
    "wof:placetype":"venue"
},
  "geometry": {"coordinates":[7.1084527969,46.9252319336],"type":"Point"}
}