{
  "type": "Feature",
  "properties": {
    "iso:country":"CH",
    "sg:address":"Bruchstrasse 5 6003 Luzern. Postfach",
    "sg:city":"Luzern",
    "sg:orig_category":"Pensionskassen",
    "sg:postcode":"6003",
    "sg:province":"Luzern",
    "wof:name":"Personalf\u00fcrsorgestiftung Der E. Schloss Ag Luzern",
    "wof:placetype":"venue"
},
  "geometry": {"coordinates":[8.2992229462,47.051197052],"type":"Point"}
}