{
  "type": "Feature",
  "properties": {
    "iso:country":"CH",
    "sg:address":"Rue De L'industrie 3",
    "sg:city":"Lausanne",
    "sg:orig_category":"Detailhandel mit Geschenkartikeln U Souvenirs Herstellung von Reiseartikeln, Leder U Sattlerwaren",
    "sg:phone":"+41 21 320 74 66",
    "sg:postcode":"1005",
    "sg:province":"Vaud",
    "wof:name":"Andy West Fabrication D'articles De Cuir",
    "wof:placetype":"venue"
},
  "geometry": {"coordinates":[6.6378159523,46.5258674622],"type":"Point"}
}