{
  "type": "Feature",
  "properties": {
    "iso:country":"CH",
    "sg:address":"Via San Quirico 21 6648 Minusio. Postfach",
    "sg:city":"Minusio",
    "sg:orig_category":"Sonstiger Detailhandel nicht in Verkaufsr\u00e4umen",
    "sg:postcode":"6648",
    "sg:province":"Ticino",
    "wof:name":"Ristomatic Sa",
    "wof:placetype":"venue"
},
  "geometry": {"coordinates":[8.8129644394,46.174697876],"type":"Point"}
}