{
  "type": "Feature",
  "properties": {
    "iso:country":"CH",
    "sg:address":"Bellevuerain 8",
    "sg:city":"Hochdorf",
    "sg:orig_category":"Herstellung von Metallkonstruktionen",
    "sg:postcode":"6280",
    "sg:province":"Luzern",
    "wof:name":"Metallbau Brunner Beat",
    "wof:placetype":"venue"
},
  "geometry": {"coordinates":[8.2896404266,47.1705741882],"type":"Point"}
}