{
  "type": "Feature",
  "properties": {
    "iso:country":"CH",
    "sg:address":"Englisberg Route D' 11",
    "sg:city":"Granges-paccot",
    "sg:orig_category":"Pensionskassen",
    "sg:phone":"+41 22 361 75 01",
    "sg:postcode":"1763",
    "sg:province":"Fribourg",
    "wof:name":"Fondation De Pr\u00e9voyance Du Groupe Js",
    "wof:placetype":"venue"
},
  "geometry": {"coordinates":[7.1482000351,46.8223991394],"type":"Point"}
}