{
  "type": "Feature",
  "properties": {
    "iso:country":"CH",
    "sg:address":"Avenue De La Gare 2 2000 Neuenburg. Postfach",
    "sg:city":"Neuenburg",
    "sg:orig_category":"Grosshandel mit Getreide, Saatgut U Futtermitteln",
    "sg:postcode":"2000",
    "sg:province":"Neuch\u00e2tel",
    "wof:name":"Hutin G. Consulting",
    "wof:placetype":"venue"
},
  "geometry": {"coordinates":[6.9314060211,46.9933280945],"type":"Point"}
}