{
  "type": "Feature",
  "properties": {
    "iso:country":"CH",
    "sg:address":"Obere Oelerr\u00fctti 12",
    "sg:city":"Schattdorf",
    "sg:orig_category":"Sonstige Personenbef\u00f6rderung im Landverkehr",
    "sg:phone":"+41 41 870 00 66",
    "sg:postcode":"6467",
    "sg:province":"Uri",
    "wof:name":"Rekatours, Schuler & Zgraggen",
    "wof:placetype":"venue"
},
  "geometry": {"coordinates":[8.6453094482,46.8628730774],"type":"Point"}
}