{
  "type": "Feature",
  "properties": {
    "iso:country":"CH",
    "sg:address":"L\u00e4rchwaldweg 58",
    "sg:city":"Thusis",
    "sg:classifiers":[
        {
            "category":"Shopping",
            "subcategory":"Discount & Variety Stores",
            "type":"Retail Goods"
        }
    ],
    "sg:phone":"+41 844 255 255",
    "sg:postcode":"7430",
    "sg:province":"Graubunden",
    "sg:tags":[
        "register",
        "cash"
    ],
    "wof:name":"Lcr Ag",
    "wof:placetype":"venue"
},
  "geometry": {"coordinates":[9.435457,46.69696],"type":"Point"}
}