{
  "type": "Feature",
  "properties": {
    "iso:country":"CH",
    "sg:address":"Mittelstrasse 24 2560 Nidau. Postfach",
    "sg:city":"Biel/bienne",
    "sg:orig_category":"Softwareentwicklung U beratung",
    "sg:phone":"+41 32 332 92 50",
    "sg:postcode":"2502",
    "sg:province":"Bern",
    "wof:name":"Avicomp Services Ag",
    "wof:placetype":"venue"
},
  "geometry": {"coordinates":[7.238158226,47.1252098083],"type":"Point"}
}