{
  "type": "Feature",
  "properties": {
    "iso:country":"CH",
    "sg:address":"Viale A. Volta 4a 6830 Chiasso Casella Postale 455",
    "sg:city":"Chiasso",
    "sg:orig_category":"Unclassifiable Establishments",
    "sg:phone":"+41 91 682 83 03",
    "sg:postcode":"6830",
    "sg:province":"Ticino",
    "wof:name":"Yaracuy Sa Partecip. Finanziaria Ad Altre Societ\u00e0 Ecc",
    "wof:placetype":"venue"
},
  "geometry": {"coordinates":[9.0313053131,45.8347244263],"type":"Point"}
}