{
  "type": "Feature",
  "properties": {
    "iso:country":"CH",
    "sg:address":"Unterdorfstrasse 11",
    "sg:city":"Unterendingen",
    "sg:orig_category":"Non-Classified Establishments",
    "sg:phone":"+41 56 242 25 57",
    "sg:postcode":"5305",
    "sg:province":"Aargau",
    "wof:name":"Binder Ren\u00e9 Schreinerarbeiten, Montagen, Reparaturen",
    "wof:placetype":"venue"
},
  "geometry": {"coordinates":[8.2890739441,47.5466499329],"type":"Point"}
}