{
  "type": "Feature",
  "properties": {
    "iso:country":"CH",
    "sg:address":"Fliederweg 3",
    "sg:city":"Gansingen",
    "sg:orig_category":"Unternehmensberatung",
    "sg:phone":"+41 62 875 10 25",
    "sg:postcode":"5272",
    "sg:province":"Aargau",
    "wof:name":"4 M Consulting Gmbh",
    "wof:placetype":"venue"
},
  "geometry": {"coordinates":[8.1336526871,47.5462875366],"type":"Point"}
}