{
  "type": "Feature",
  "properties": {
    "iso:country":"CH",
    "sg:address":"Obgassweg 6",
    "sg:city":"Buochs",
    "sg:orig_category":"Fachdetailhandel in Verkaufsr\u00e4umen",
    "sg:postcode":"6374",
    "sg:province":"Nidwalden",
    "wof:name":"Paper House Trading, Wettstein Daniel",
    "wof:placetype":"venue"
},
  "geometry": {"coordinates":[8.4141597748,46.9707756042],"type":"Point"}
}