{
  "type": "Feature",
  "properties": {
    "iso:country":"CH",
    "sg:address":"Austrasse 32b",
    "sg:city":"Volketswil",
    "sg:orig_category":"Unternehmensberatung",
    "sg:phone":"+41 19461947",
    "sg:postcode":"8604",
    "sg:province":"Z\u00fcrich",
    "wof:name":"Qualit\u00e4tsmanagement-beratung Hugelshofer",
    "wof:placetype":"venue"
},
  "geometry": {"coordinates":[8.6918888092,47.3905982971],"type":"Point"}
}