{
  "type": "Feature",
  "properties": {
    "iso:country":"CH",
    "sg:address":"Kreuzlingerstrasse 22",
    "sg:city":"Neuwilen",
    "sg:orig_category":"Non-Classified Establishments",
    "sg:postcode":"8566",
    "sg:province":"Thurgau",
    "wof:name":"Sitterthal Ag",
    "wof:placetype":"venue"
},
  "geometry": {"coordinates":[9.1368846893,47.6221084595],"type":"Point"}
}