{
  "type": "Feature",
  "properties": {
    "iso:country":"CH",
    "sg:address":"Trevano Via 61",
    "sg:city":"Lugano",
    "sg:orig_category":"Hardwareberatung",
    "sg:postcode":"6900",
    "sg:province":"Ticino",
    "wof:name":"Print World Gmbh",
    "wof:placetype":"venue"
},
  "geometry": {"coordinates":[7.6207709312,46.7335853577],"type":"Point"}
}