{
  "type": "Feature",
  "properties": {
    "iso:country":"CH",
    "sg:address":"Lindenweg 12",
    "sg:city":"Magglingen/macolin",
    "sg:classifiers":[
        {
            "category":"Professional",
            "subcategory":"Employment Agencies",
            "type":"Services"
        }
    ],
    "sg:postcode":"2532",
    "sg:province":"Bern",
    "sg:tags":[
        "personal",
        "u",
        "stellenvermittlung"
    ],
    "wof:name":"Ernst Zysset Management Beratung",
    "wof:placetype":"venue"
},
  "geometry": {"coordinates":[7.217774868,47.1420135498],"type":"Point"}
}