{
  "type": "Feature",
  "properties": {
    "iso:country":"CH",
    "sg:address":"4533 Riedholz. Postfach 112",
    "sg:city":"Riedholz",
    "sg:orig_category":"Sportvereine Ballsport Fussball",
    "sg:phone":"+41 91 648 27 12",
    "sg:postcode":"4533",
    "sg:province":"Solothurn",
    "wof:name":"Fc Riva",
    "wof:placetype":"venue"
},
  "geometry": {"coordinates":[8.9712247849,45.9057006836],"type":"Point"}
}