{
  "type": "Feature",
  "properties": {
    "iso:country":"CH",
    "sg:address":"Place Des Balances",
    "sg:city":"Echallens",
    "sg:orig_category":"Zahnarztpraxen",
    "sg:phone":"+41 21 881 39 77",
    "sg:postcode":"1040",
    "sg:province":"Vaud",
    "wof:name":"Dr M\u00e9d. Dent. Uri Rosenzweig M\u00e9decin-dentiste",
    "wof:placetype":"venue"
},
  "geometry": {"coordinates":[6.6346821785,46.6419563293],"type":"Point"}
}