{
  "type": "Feature",
  "properties": {
    "iso:country":"CH",
    "sg:address":"Hauptstrasse",
    "sg:city":"Welschenrohr",
    "sg:classifiers":[
        {
            "category":"Banks & Credit Unions",
            "subcategory":"Bank",
            "type":"Services"
        }
    ],
    "sg:phone":"+41 4165491216",
    "sg:postcode":"4716",
    "sg:province":"Solothurn",
    "wof:name":"Solothurner Kantonalbank",
    "wof:placetype":"venue"
},
  "geometry": {"coordinates":[7.537245,47.28009],"type":"Point"}
}