{
  "type": "Feature",
  "properties": {
    "addr:full":"Im Wiesengrund 5 Wigoltingen Thurgau 8556",
    "addr:housenumber":"5",
    "addr:postcode":"8556",
    "addr:street":"Im Wiesengrund",
    "iso:country":"CH",
    "sg:address":"Im Wiesengrund 5",
    "sg:city":"Wigoltingen",
    "sg:orig_category":"Bau U Wohngenossenschaften",
    "sg:postcode":"8556",
    "sg:province":"Thurgau",
    "wof:name":"Genossenschaft Ch\u00fcrzi",
    "wof:placetype":"venue"
},
  "geometry": {"coordinates":[9.03389,47.599316],"type":"Point"}
}