{
  "type": "Feature",
  "properties": {
    "iso:country":"CH",
    "sg:address":"Ebenaustrasse 8a",
    "sg:city":"Horw",
    "sg:orig_category":"Non-Classified Establishments",
    "sg:postcode":"6048",
    "sg:province":"Luzern",
    "wof:name":"Jocasi Holding Ag",
    "wof:placetype":"venue"
},
  "geometry": {"coordinates":[8.3091154099,47.0155982971],"type":"Point"}
}