{
  "type": "Feature",
  "properties": {
    "iso:country":"CH",
    "sg:address":"Hohle Gasse 1",
    "sg:city":"Frutigen",
    "sg:orig_category":"Detailhandel mit Textilien",
    "sg:phone":"+41 81 302 29 13",
    "sg:postcode":"3714",
    "sg:province":"Bern",
    "wof:name":"Margrit Roth Handarbeiten",
    "wof:placetype":"venue"
},
  "geometry": {"coordinates":[9.5008525848,47.0007362366],"type":"Point"}
}