{
  "type": "Feature",
  "properties": {
    "iso:country":"CH",
    "sg:address":"Breitenstrasse 58",
    "sg:city":"Wilen",
    "sg:classifiers":[
        {
            "category":"Manufacturing",
            "subcategory":"Glass & Minerals",
            "type":"Manufacturing & Wholesale Goods"
        }
    ],
    "sg:phone":"+41 17861444",
    "sg:postcode":"8832",
    "sg:province":"Schwyz",
    "sg:tags":[
        "fitting"
    ],
    "wof:name":"Deco Fashion Optic Ag",
    "wof:placetype":"venue"
},
  "geometry": {"coordinates":[8.7419996262,47.1999588013],"type":"Point"}
}