{
  "type": "Feature",
  "properties": {
    "iso:country":"CH",
    "sg:address":"Rue Du Rh\u00f4ne 50 1200 Genf. Postfach",
    "sg:city":"Gen\u00e8ve",
    "sg:orig_category":"Architektur U Ingenieurb\u00fcros",
    "sg:postcode":"1201",
    "sg:province":"Gen\u00e8ve",
    "wof:name":"Gmp Studio Project Management S\u00e0rl",
    "wof:placetype":"venue"
},
  "geometry": {"coordinates":[6.14754,46.204086],"type":"Point"}
}