{
  "type": "Feature",
  "properties": {
    "iso:country":"CH",
    "sg:address":"Rue De Monruz 2",
    "sg:city":"Neuch\u00e2tel",
    "sg:classifiers":[
        {
            "category":"Wholesale",
            "subcategory":"Machinery & Supplies",
            "type":"Manufacturing & Wholesale Goods"
        }
    ],
    "sg:phone":"+41 32 729 60 20",
    "sg:postcode":"2000",
    "sg:province":"Neuch\u00e2tel",
    "sg:tags":[
        "equipment",
        "equipement",
        "precision",
        "timekeeping"
    ],
    "wof:name":"Gucci Group Watches",
    "wof:placetype":"venue"
},
  "geometry": {"coordinates":[6.9573578835,47.0026931763],"type":"Point"}
}