{
  "type": "Feature",
  "properties": {
    "iso:country":"CH",
    "sg:address":"Oberstadt 7",
    "sg:city":"Sursee",
    "sg:classifiers":[
        {
            "category":"Banks & Credit Unions",
            "subcategory":"Bank",
            "type":"Services"
        }
    ],
    "sg:phone":"+41 4145237111",
    "sg:postcode":"6210",
    "sg:province":"Luzern",
    "wof:name":"Luzerner Kantonalbank, Branch Sursee-oberstadt",
    "wof:placetype":"venue"
},
  "geometry": {"coordinates":[8.110535,47.172192],"type":"Point"}
}