{
  "type": "Feature",
  "properties": {
    "iso:country":"CH",
    "sg:address":"L\u00e4ngackerstrasse 12",
    "sg:city":"Aarburg",
    "sg:orig_category":"Elektroinstallation",
    "sg:postcode":"4663",
    "sg:province":"Aargau",
    "wof:name":"Inbamo Dubach Kurt",
    "wof:placetype":"venue"
},
  "geometry": {"coordinates":[7.9086809158,47.3337593079],"type":"Point"}
}