{
  "type": "Feature",
  "properties": {
    "iso:country":"CH",
    "sg:address":"Norimatt 11",
    "sg:city":"Laufen",
    "sg:orig_category":"Architektur U Ingenieurb\u00fcros",
    "sg:phone":"+41 61 761 48 79",
    "sg:postcode":"4242",
    "sg:province":"Basel-Landschaft",
    "wof:name":"Martin Schaad Pgt-planung Industriedesign",
    "wof:placetype":"venue"
},
  "geometry": {"coordinates":[7.50792,47.423016],"type":"Point"}
}