{
  "type": "Feature",
  "properties": {
    "iso:country":"CH",
    "sg:address":"Nordringstrasse 20",
    "sg:city":"Gerlafingen",
    "sg:orig_category":"Herstellung von Teppichen Verlegen von Fliesen U Platten",
    "sg:phone":"+41 32 675 33 47",
    "sg:postcode":"4563",
    "sg:province":"Solothurn",
    "wof:name":"R\u00e4tz-spielmann Fritz, Plattenbel\u00e4ge",
    "wof:placetype":"venue"
},
  "geometry": {"coordinates":[7.5726718903,47.1744995117],"type":"Point"}
}