{
  "type": "Feature",
  "properties": {
    "iso:country":"CH",
    "sg:address":"Bernstrasse 292",
    "sg:city":"Heimberg",
    "sg:classifiers":[
        {
            "category":"Home & Garden",
            "subcategory":"Household Appliances",
            "type":"Retail Goods"
        }
    ],
    "sg:phone":"+41 33 439 00 10",
    "sg:postcode":"3627",
    "sg:province":"Bern",
    "sg:tags":[
        "electric"
    ],
    "wof:name":"M. Schneider Elektro Ag",
    "wof:placetype":"venue"
},
  "geometry": {"coordinates":[7.6074728966,46.7905502319],"type":"Point"}
}