{
  "type": "Feature",
  "properties": {
    "iso:country":"CH",
    "sg:address":"Oberer Saltinadamm 16",
    "sg:city":"Glis",
    "sg:orig_category":"Detailhandel mit Textilien Herstellung von Reiseartikeln, Leder U Sattlerwaren",
    "sg:phone":"+41 27 923 92 80",
    "sg:postcode":"3902",
    "sg:province":"Valais",
    "wof:name":"Martig Gerhard Polsterei",
    "wof:placetype":"venue"
},
  "geometry": {"coordinates":[7.9883208275,46.3150138855],"type":"Point"}
}