{
  "type": "Feature",
  "properties": {
    "iso:country":"CH",
    "sg:address":"Jakob Peter-weg 25",
    "sg:city":"Z\u00fcrich",
    "sg:classifiers":[
        {
            "category":"Professional",
            "subcategory":"Computer Services",
            "type":"Services"
        }
    ],
    "sg:phone":"+41 14506842",
    "sg:postcode":"8055",
    "sg:province":"Z\u00fcrich",
    "sg:tags":[
        "administration",
        "software"
    ],
    "wof:name":"Teachsoft",
    "wof:placetype":"venue"
},
  "geometry": {"coordinates":[8.504813,47.363564],"type":"Point"}
}