{
  "type": "Feature",
  "properties": {
    "iso:country":"CH",
    "sg:address":"Lindenstrasse",
    "sg:city":"Aeschlen",
    "sg:classifiers":[
        {
            "category":"Restaurant",
            "type":"Food & Drink"
        }
    ],
    "sg:phone":"+41 31 771 13 46",
    "sg:postcode":"3672",
    "sg:province":"Bern",
    "wof:name":"Restaurant Sch\u00f6negg",
    "wof:placetype":"venue"
},
  "geometry": {"coordinates":[7.6498169899,46.8386116028],"type":"Point"}
}