{
  "type": "Feature",
  "properties": {
    "iso:country":"CH",
    "sg:address":"Schlifistrasse 2",
    "sg:city":"Berneck",
    "sg:orig_category":"RESTAURANTS: TEA-ROOMS",
    "sg:phone":"+41 34 445 26 41",
    "sg:postcode":"9442",
    "sg:province":"St. Gallen",
    "wof:name":"Rest. Traube, Stuber Rolf",
    "wof:placetype":"venue"
},
  "geometry": {"coordinates":[7.5838198662,47.0861434937],"type":"Point"}
}