{
  "type": "Feature",
  "properties": {
    "iso:country":"CH",
    "sg:address":"Florastrasse 10",
    "sg:city":"Biel/bienne",
    "sg:classifiers":[
        {
            "category":"Bars & Pubs",
            "type":"Food & Drink"
        }
    ],
    "sg:phone":"+41 32 322 11 10",
    "sg:postcode":"2502",
    "sg:province":"Bern",
    "sg:tags":[
        "restaurant"
    ],
    "wof:name":"Pizzeria & Bar Via Appia",
    "wof:placetype":"venue"
},
  "geometry": {"coordinates":[7.245885,47.137951],"type":"Point"}
}