{
  "type": "Feature",
  "properties": {
    "iso:country":"CH",
    "sg:address":"Weiherhofstrasse 9a",
    "sg:city":"Bronschhofen",
    "sg:orig_category":"Bauspenglerei Zimmerei, Dachdeckerei, Bauspenglerei U Abdichtung",
    "sg:phone":"+41 79 682 44 33",
    "sg:postcode":"9552",
    "sg:province":"St. Gallen",
    "wof:name":"Meile & S\u00f6hne Ag",
    "wof:placetype":"venue"
},
  "geometry": {"coordinates":[9.032921,47.478519],"type":"Point"}
}