{
  "type": "Feature",
  "properties": {
    "iso:country":"CH",
    "sg:address":"Im Halt 1",
    "sg:city":"Gebenstorf",
    "sg:orig_category":"Detailhandel Handel mit Motorr\u00e4dern, Teilen U Zubeh\u00f6r Instandhaltung U Reparatur von Motorr\u00e4dern Rep",
    "sg:phone":"+41 32 757 11 17",
    "sg:postcode":"5412",
    "sg:province":"Aargau",
    "wof:name":"Nicolas Sandoz",
    "wof:placetype":"venue"
},
  "geometry": {"coordinates":[7.0220851898,47.0382766724],"type":"Point"}
}