{
  "type": "Feature",
  "properties": {
    "iso:country":"CH",
    "sg:address":"Seestrasse 13",
    "sg:city":"Uster",
    "sg:classifiers":[
        {
            "category":"Insurance",
            "subcategory":"Insurance Agent",
            "type":"Services"
        }
    ],
    "sg:phone":"+41 34 445 05 66",
    "sg:postcode":"8610",
    "sg:province":"Z\u00fcrich",
    "sg:tags":[
        "versicherungsagenturen",
        "-broker"
    ],
    "wof:name":"Peter Baumann Versicherungsberatung",
    "wof:placetype":"venue"
},
  "geometry": {"coordinates":[7.587583065,47.0867996216],"type":"Point"}
}