{
  "type": "Feature",
  "properties": {
    "iso:country":"CH",
    "sg:address":"Seefeldstrasse 172",
    "sg:city":"Z\u00fcrich",
    "sg:orig_category":"Shiatsu-Therapie",
    "sg:phone":"+41 79 632 67 74",
    "sg:postcode":"8008",
    "sg:province":"Z\u00fcrich",
    "wof:name":"Sabina Rudolf-von-rohr Shiatsu",
    "wof:placetype":"venue"
},
  "geometry": {"coordinates":[8.556640625,47.3553543091],"type":"Point"}
}