{
  "type": "Feature",
  "properties": {
    "iso:country":"CH",
    "sg:address":"Kirchgasse 6",
    "sg:city":"Bischofszell",
    "sg:orig_category":"Detailhandel mit Radio U Fernsehger\u00e4ten",
    "sg:phone":"+41 71 385 40 40",
    "sg:postcode":"9220",
    "sg:province":"Thurgau",
    "wof:name":"Paul Bohren Radio-tv-service",
    "wof:placetype":"venue"
},
  "geometry": {"coordinates":[9.257393837,47.4168701172],"type":"Point"}
}