{
  "type": "Feature",
  "properties": {
    "iso:country":"CH",
    "sg:address":"Neumarkt 3",
    "sg:city":"Z\u00fcrich",
    "sg:orig_category":"Sonstiger Grosshandel",
    "sg:phone":"+41 12622223",
    "sg:postcode":"8001",
    "sg:province":"Z\u00fcrich",
    "wof:name":"Barbara Wick Ag",
    "wof:placetype":"venue"
},
  "geometry": {"coordinates":[8.5455818176,47.3725624084],"type":"Point"}
}