{
  "type": "Feature",
  "properties": {
    "iso:country":"CH",
    "sg:address":"Chilenaustrasse 7 8108 D\u00e4llikon. Postfach",
    "sg:city":"D\u00e4llikon",
    "sg:orig_category":"Reinigungsgewerbe",
    "sg:postcode":"8108",
    "sg:province":"Z\u00fcrich",
    "wof:name":"Allroundservice Kolcu",
    "wof:placetype":"venue"
},
  "geometry": {"coordinates":[8.4405031204,47.4407920837],"type":"Point"}
}