{
  "type": "Feature",
  "properties": {
    "iso:country":"CH",
    "sg:address":"8820",
    "sg:city":"W\u00e4denswil",
    "sg:orig_category":"Primarschulen",
    "sg:phone":"+41 71 244 69 29",
    "sg:postcode":"8820",
    "sg:province":"Z\u00fcrich",
    "wof:name":"Primarschule Gerhalden",
    "wof:placetype":"venue"
},
  "geometry": {"coordinates":[9.3857631683,47.4379234314],"type":"Point"}
}