{
  "type": "Feature",
  "properties": {
    "iso:country":"CH",
    "sg:address":"Via Trevano 63",
    "sg:city":"Lugano",
    "sg:orig_category":"Allgemeinbildende weiterf\u00fchrende Schulen",
    "sg:phone":"+41 91 994 15 01",
    "sg:postcode":"6900",
    "sg:province":"Ticino",
    "wof:name":"American Center For Education Ltd, St. Peter Port (guernsey) Ufficio Di Coordinamento Lugano.",
    "wof:placetype":"venue"
},
  "geometry": {"coordinates":[8.956417,46.01799],"type":"Point"}
}