{
  "type": "Feature",
  "properties": {
    "iso:country":"CH",
    "sg:address":"Ziegeleistrasse 3",
    "sg:city":"Basadingen",
    "sg:orig_category":"Grosshandel mit chemischen Erzeugnissen Herstellung von Seifen, Wasch U Reinigungsmitteln",
    "sg:phone":"+41 52 657 14 66",
    "sg:postcode":"8254",
    "sg:province":"Thurgau",
    "wof:name":"Hega Gmbh",
    "wof:placetype":"venue"
},
  "geometry": {"coordinates":[8.7468767166,47.6690711975],"type":"Point"}
}