{
  "type": "Feature",
  "properties": {
    "iso:country":"CH",
    "sg:address":"Im M\u00e4ttlein 9",
    "sg:city":"Zwingen",
    "sg:orig_category":"Non-Classified Establishments",
    "sg:postcode":"4222",
    "sg:province":"Basel-Landschaft",
    "wof:name":"Harald Fritschi Fh-consulting",
    "wof:placetype":"venue"
},
  "geometry": {"coordinates":[7.5324168205,47.438293457],"type":"Point"}
}