{
  "type": "Feature",
  "properties": {
    "iso:country":"CH",
    "sg:address":"Avenue De La Gare 34",
    "sg:city":"V\u00e9troz",
    "sg:orig_category":"Fahrschulen, Flugschulen",
    "sg:postcode":"1963",
    "sg:province":"Valais",
    "wof:name":"Raynald & Chantal Sauthier Auto-\u00e9cole",
    "wof:placetype":"venue"
},
  "geometry": {"coordinates":[7.2770462036,46.2242279053],"type":"Point"}
}