{
  "type": "Feature",
  "properties": {
    "iso:country":"CH",
    "sg:address":"Kirchgasse 55",
    "sg:city":"Meilen",
    "sg:orig_category":"Unclassifiable Establishments",
    "sg:postcode":"8706",
    "sg:province":"Z\u00fcrich",
    "wof:name":"B\u00e4ckerei-konditorei-tea-room, Heinzelmann & Eigenmann, Nachf. Eigenmann",
    "wof:placetype":"venue"
},
  "geometry": {"coordinates":[8.6415863037,47.2700233459],"type":"Point"}
}