{
  "type": "Feature",
  "properties": {
    "iso:country":"CH",
    "sg:address":"Els\u00e4sserstrasse 138",
    "sg:city":"Basel",
    "sg:classifiers":[
        {
            "category":"Restaurant",
            "type":"Food & Drink"
        }
    ],
    "sg:phone":"+41 61 321 33 40",
    "sg:postcode":"4056",
    "sg:province":"Basel-Stadt",
    "wof:name":"Restaurant Da Angelo",
    "wof:placetype":"venue"
},
  "geometry": {"coordinates":[7.5766401291,47.5725097656],"type":"Point"}
}