{
  "type": "Feature",
  "properties": {
    "iso:country":"CH",
    "sg:address":"Buchelistrasse 26",
    "sg:city":"Rorschach",
    "sg:orig_category":"Selbst\u00e4ndige bildende K\u00fcnstler",
    "sg:phone":"+41 55 442 15 75",
    "sg:postcode":"9400",
    "sg:province":"St. Gallen",
    "wof:name":"Bamert F., Bildhauer",
    "wof:placetype":"venue"
},
  "geometry": {"coordinates":[8.8612661362,47.1935653687],"type":"Point"}
}