{
  "type": "Feature",
  "properties": {
    "iso:country":"CH",
    "sg:address":"8887",
    "sg:city":"Mels",
    "sg:orig_category":"Wirtschaftsverb\u00e4nde Industrie, Handel and Gewerbe",
    "sg:phone":"+41 31 372 28 28",
    "sg:postcode":"8887",
    "sg:province":"St. Gallen",
    "wof:name":"Parit\u00e4tische Berufs- Bildungsstelle",
    "wof:placetype":"venue"
},
  "geometry": {"coordinates":[7.435997963,46.9402351379],"type":"Point"}
}