{
  "type": "Feature",
  "properties": {
    "iso:country":"CH",
    "sg:address":"Via A. Nessi 38b 6600 Locarno. Postfach",
    "sg:city":"Locarno",
    "sg:orig_category":"Detailhandel mit Waren verschiedener Art, Hauptrichtung Nahrungsmittel",
    "sg:phone":"+41 91 751 86 23",
    "sg:postcode":"6600",
    "sg:province":"Ticino",
    "wof:name":"Negozio Alimentari Arcobaleno Di Oezdemir Bandir Verdi",
    "wof:placetype":"venue"
},
  "geometry": {"coordinates":[8.7916202545,46.1623802185],"type":"Point"}
}