{
  "type": "Feature",
  "properties": {
    "iso:country":"CH",
    "sg:address":"Chemin De La Brume 9",
    "sg:city":"Morges",
    "sg:orig_category":"Architektur U Ingenieurb\u00fcros",
    "sg:phone":"+41 21 802 10 95",
    "sg:postcode":"1110",
    "sg:province":"Vaud",
    "wof:name":"E.r. Energies Rationnelles Sa",
    "wof:placetype":"venue"
},
  "geometry": {"coordinates":[6.499244,46.51799],"type":"Point"}
}