{
  "type": "Feature",
  "properties": {
    "iso:country":"CH",
    "sg:address":"Route De La Rippe",
    "sg:city":"Crassier",
    "sg:orig_category":"Mechanik Stahl U Leichtmetallbau",
    "sg:phone":"+41 22 367 13 60",
    "sg:postcode":"1263",
    "sg:province":"Vaud",
    "wof:name":"Charri\u00e8re Eric Sa",
    "wof:placetype":"venue"
},
  "geometry": {"coordinates":[6.1588149071,46.3799858093],"type":"Point"}
}