{
  "type": "Feature",
  "properties": {
    "iso:country":"CH",
    "sg:address":"6804",
    "sg:city":"Bironico",
    "sg:orig_category":"Herstellung von Schl\u00f6ssern U Beschl\u00e4gen",
    "sg:phone":"+41 22 342 06 00",
    "sg:postcode":"6804",
    "sg:province":"Ticino",
    "wof:name":"Medeco Transpat Sa Serrures & Cylindres",
    "wof:placetype":"venue"
},
  "geometry": {"coordinates":[6.1431488991,46.1864013672],"type":"Point"}
}