{
  "type": "Feature",
  "properties": {
    "iso:country":"CH",
    "sg:address":"Lufingerstrasse 1",
    "sg:city":"Winkel",
    "sg:orig_category":"Veterin\u00e4rwesen",
    "sg:phone":"+41 12112255",
    "sg:postcode":"8185",
    "sg:province":"Z\u00fcrich",
    "wof:name":"Tierrettungsdienst - Leben Hat Vortritt",
    "wof:placetype":"venue"
},
  "geometry": {"coordinates":[8.5537157059,47.479927063],"type":"Point"}
}