{
  "type": "Feature",
  "properties": {
    "iso:country":"CH",
    "sg:address":"Route Du Jorat 70",
    "sg:city":"Mont-sur-lausanne",
    "sg:orig_category":"Instandhaltung U Reparatur von Automobilen",
    "sg:phone":"+41 21 652 70 38",
    "sg:postcode":"1052",
    "sg:province":"Vaud",
    "wof:name":"Garage Des Roches Andr\u00e9 Chabloz",
    "wof:placetype":"venue"
},
  "geometry": {"coordinates":[6.6433439255,46.5625114441],"type":"Point"}
}