{
  "type": "Feature",
  "properties": {
    "iso:country":"CH",
    "sg:address":"Florastrasse 9",
    "sg:city":"Ostermundigen",
    "sg:orig_category":"Grafikateliers, Design",
    "sg:phone":"+41 61 961 02 66",
    "sg:postcode":"3072",
    "sg:province":"Bern",
    "wof:name":"Andr\u00e9 Aerni",
    "wof:placetype":"venue"
},
  "geometry": {"coordinates":[7.749475,47.388546],"type":"Point"}
}