{
  "type": "Feature",
  "properties": {
    "addr:full":"Anderhalbacher Feutersoey Bern 3784",
    "addr:postcode":"3784",
    "iso:country":"CH",
    "sg:address":"Anderhalbacher",
    "sg:city":"Feutersoey",
    "sg:orig_category":"Allgemeiner Hoch U Tiefbau Allgemeiner Hochbau",
    "sg:phone":"+41 33 755 10 21",
    "sg:postcode":"3784",
    "sg:province":"Bern",
    "wof:name":"M. Gehret Ag",
    "wof:placetype":"venue"
},
  "geometry": {"coordinates":[7.269859,46.415962],"type":"Point"}
}