{
  "type": "Feature",
  "properties": {
    "iso:country":"CH",
    "sg:address":"Via Nassa 22",
    "sg:city":"Lugano",
    "sg:orig_category":"Warenh\u00e4user",
    "sg:phone":"+41 91 923 91 12",
    "sg:postcode":"6900",
    "sg:province":"Ticino",
    "wof:name":"Epa Ag",
    "wof:placetype":"venue"
},
  "geometry": {"coordinates":[8.9497947693,46.0028152466],"type":"Point"}
}