{
  "type": "Feature",
  "properties": {
    "iso:country":"CH",
    "sg:address":"Im Sch\u00f6rli 3 8600 D\u00fcbendorf. Postfach 322",
    "sg:city":"Gelterkinden",
    "sg:orig_category":"Herstellung von Spielwaren",
    "sg:phone":"+41 18220325",
    "sg:postcode":"4460",
    "sg:province":"Basel-Landschaft",
    "wof:name":"Ppg Perner Publishing Group Ag",
    "wof:placetype":"venue"
},
  "geometry": {"coordinates":[8.6395969391,47.3946342468],"type":"Point"}
}