{
  "type": "Feature",
  "properties": {
    "iso:country":"CH",
    "sg:address":"Kirchstrasse 9",
    "sg:city":"Oftringen",
    "sg:orig_category":"Primarschulen",
    "sg:phone":"+41 62 789 81 88",
    "sg:postcode":"4665",
    "sg:province":"Aargau",
    "wof:name":"Primarschule Schulpavillon Oberfeld",
    "wof:placetype":"venue"
},
  "geometry": {"coordinates":[7.9302549362,47.3112373352],"type":"Point"}
}