{
  "type": "Feature",
  "properties": {
    "iso:country":"CH",
    "sg:address":"Roisch Plam Dil 4 7078 Lenzerheide/lai. Postfach",
    "sg:city":"Lenzerheide/lai",
    "sg:orig_category":"Sonstige mit der Informatik verbundene T\u00e4tigkeiten",
    "sg:postcode":"7078",
    "sg:province":"Graubunden",
    "wof:name":"Shine New Media, Parpan T.",
    "wof:placetype":"venue"
},
  "geometry": {"coordinates":[9.5557184219,46.725402832],"type":"Point"}
}