{
  "type": "Feature",
  "properties": {
    "addr:full":"1895 Vionnaz Valais 1895",
    "addr:housenumber":"1895;1895",
    "addr:street":"Vionnaz Valais",
    "iso:country":"CH",
    "sg:address":"1895",
    "sg:city":"Vionnaz",
    "sg:orig_category":"Betrieb von Taxis",
    "sg:phone":"+41 24 481 29 53",
    "sg:postcode":"1895",
    "sg:province":"Valais",
    "wof:name":"Bailly Bernadette",
    "wof:placetype":"venue"
},
  "geometry": {"coordinates":[6.899424,46.311699],"type":"Point"}
}