{
  "type": "Feature",
  "properties": {
    "addr:full":"6537 Grono Graubunden 6537",
    "addr:housenumber":"6537;6537",
    "addr:street":"Grono Graubunden",
    "iso:country":"CH",
    "sg:address":"6537",
    "sg:city":"Grono",
    "sg:classifiers":[
        {
            "category":"Bars & Pubs",
            "type":"Food & Drink"
        }
    ],
    "sg:phone":"+41 91 864 16 01",
    "sg:postcode":"6537",
    "sg:province":"Graubunden",
    "wof:name":"Bar Centrale",
    "wof:placetype":"venue"
},
  "geometry": {"coordinates":[8.90681,46.380268],"type":"Point"}
}