{
  "type": "Feature",
  "properties": {
    "iso:country":"CH",
    "sg:address":"Hadlaubstrasse 41",
    "sg:city":"Z\u00fcrich",
    "sg:classifiers":[
        {
            "category":"Travel",
            "subcategory":"Hotels & Motels",
            "type":"Entertainment"
        }
    ],
    "sg:phone":"+41 13625510",
    "sg:postcode":"8006",
    "sg:province":"Z\u00fcrich",
    "sg:tags":[
        "hotels",
        "mit",
        "restaurant"
    ],
    "wof:name":"W. Wahl Hotel Und Gastro-immobilien",
    "wof:placetype":"venue"
},
  "geometry": {"coordinates":[8.5538043976,47.3837471008],"type":"Point"}
}