{
  "type": "Feature",
  "properties": {
    "iso:country":"CH",
    "sg:address":"Route De Berne 47",
    "sg:city":"Lausanne",
    "sg:orig_category":"Berufsbildende weiterf\u00fchrende Schulen",
    "sg:phone":"+41 21 657 08 38",
    "sg:postcode":"1010",
    "sg:province":"Vaud",
    "wof:name":"Agr Services Formation De Vente",
    "wof:placetype":"venue"
},
  "geometry": {"coordinates":[6.647038,46.535625],"type":"Point"}
}