{
  "type": "Feature",
  "properties": {
    "iso:country":"CH",
    "sg:address":"Dorfstrasse 23",
    "sg:city":"Adelboden",
    "sg:orig_category":"Museen",
    "sg:phone":"+41 33 673 80 80",
    "sg:postcode":"3715",
    "sg:province":"Bern",
    "wof:name":"Heimatmuseum Adelboden",
    "wof:placetype":"venue"
},
  "geometry": {"coordinates":[7.5590629578,46.4925422668],"type":"Point"}
}