{
  "type": "Feature",
  "properties": {
    "iso:country":"CH",
    "sg:address":"Kehlhofstrasse 1",
    "sg:city":"Adligenswil",
    "sg:orig_category":"Gartenbau",
    "sg:phone":"+41 41 370 15 50",
    "sg:postcode":"6043",
    "sg:province":"Luzern",
    "wof:name":"Vetter Gartenbau Ag",
    "wof:placetype":"venue"
},
  "geometry": {"coordinates":[8.3616466522,47.0750427246],"type":"Point"}
}