{
  "type": "Feature",
  "properties": {
    "iso:country":"CH",
    "sg:address":"Bauisstrasse 3",
    "sg:city":"Zollikon",
    "sg:orig_category":"Wirtschaftspr\u00fcfung, Steuerberatung U Treuhand",
    "sg:phone":"+41 13915559",
    "sg:postcode":"8702",
    "sg:province":"Z\u00fcrich",
    "wof:name":"Ehrbar Walter Lic. Iur.",
    "wof:placetype":"venue"
},
  "geometry": {"coordinates":[8.5688009262,47.3414230347],"type":"Point"}
}