{
  "type": "Feature",
  "properties": {
    "iso:country":"CH",
    "sg:address":"Theaterplatz 2",
    "sg:city":"Bern",
    "sg:classifiers":[
        {
            "category":"Restaurant",
            "type":"Food & Drink"
        }
    ],
    "sg:phone":"+41 31 318 88 31",
    "sg:postcode":"3011",
    "sg:province":"Bern",
    "wof:name":"Adriano's Caf\u00e9",
    "wof:placetype":"venue"
},
  "geometry": {"coordinates":[7.4472990036,46.9478302002],"type":"Point"}
}