{
  "type": "Feature",
  "properties": {
    "iso:country":"CH",
    "sg:address":"Route De Sion 66",
    "sg:city":"Sierre",
    "sg:orig_category":"Instandhaltung U Reparatur von Automobilen",
    "sg:phone":"+41 27 455 11 48",
    "sg:postcode":"3960",
    "sg:province":"Valais",
    "wof:name":"Garage Cit\u00e9 Du Soleil Sa",
    "wof:placetype":"venue"
},
  "geometry": {"coordinates":[7.5177121162,46.2857704163],"type":"Point"}
}