{
  "type": "Feature",
  "properties": {
    "iso:country":"CH",
    "sg:address":"Belpstrasse 11 3007 Bern. Postfach",
    "sg:city":"Bern",
    "sg:orig_category":"Konsulate",
    "sg:phone":"+41 31 311 47 32",
    "sg:postcode":"3001",
    "sg:province":"Bern",
    "wof:name":"Ambassade Du Luxembourg",
    "wof:placetype":"venue"
},
  "geometry": {"coordinates":[7.4499430656,46.9478302002],"type":"Point"}
}