{
  "type": "Feature",
  "properties": {
    "iso:country":"CH",
    "sg:address":"Chemin De Grand-donzel 41",
    "sg:city":"Vessy",
    "sg:orig_category":"Herstellung von Teppichen Verlegen von Fussboden",
    "sg:phone":"+41 22 784 12 92",
    "sg:postcode":"1234",
    "sg:province":"Gen\u00e8ve",
    "wof:name":"Balzan Et Immer Sa",
    "wof:placetype":"venue"
},
  "geometry": {"coordinates":[6.1674890518,46.1682243347],"type":"Point"}
}