{
  "type": "Feature",
  "properties": {
    "iso:country":"CH",
    "sg:address":"Alte Winterthurerstrasse 11",
    "sg:city":"N\u00fcrensdorf",
    "sg:classifiers":[
        {
            "category":"Parking",
            "subcategory":"Lot",
            "type":"Transportation"
        }
    ],
    "sg:phone":"+41 18366010",
    "sg:postcode":"8309",
    "sg:province":"Z\u00fcrich",
    "sg:tags":[
        "screens",
        "sun",
        "wind",
        "shield",
        "sight"
    ],
    "wof:name":"Aluxol Ag",
    "wof:placetype":"venue"
},
  "geometry": {"coordinates":[8.643965,47.445812],"type":"Point"}
}