{
  "type": "Feature",
  "properties": {
    "iso:country":"CH",
    "sg:address":"2345 Les Breuleux. Postfach",
    "sg:city":"Chaux-des-breuleux",
    "sg:orig_category":"RESTAURANTS: TEA-ROOMS",
    "sg:postcode":"2345",
    "sg:province":"Jura",
    "wof:name":"Bourquenez Jean-pierre Et Marie-jos\u00e9e Restaurant Le Sapin",
    "wof:placetype":"venue"
},
  "geometry": {"coordinates":[7.0049629211,47.2118835449],"type":"Point"}
}