{
  "type": "Feature",
  "properties": {
    "iso:country":"CH",
    "sg:address":"6864",
    "sg:city":"Arzo",
    "sg:orig_category":"G\u00fcterbef\u00f6rderung im Strassenverkehr",
    "sg:postcode":"6864",
    "sg:province":"Ticino",
    "wof:name":"Filippini Rocco",
    "wof:placetype":"venue"
},
  "geometry": {"coordinates":[8.9395303726,45.8800201416],"type":"Point"}
}