{
  "type": "Feature",
  "properties": {
    "iso:country":"CH",
    "sg:address":"S\u00e4ntisstrasse 2",
    "sg:city":"Dietlikon",
    "sg:orig_category":"Nationale Postdienste",
    "sg:phone":"+41 18332293",
    "sg:postcode":"8305",
    "sg:province":"Z\u00fcrich",
    "wof:name":"Die Schweizerische Post",
    "wof:placetype":"venue"
},
  "geometry": {"coordinates":[8.6194210052,47.4219284058],"type":"Point"}
}