{
  "type": "Feature",
  "properties": {
    "iso:country":"CH",
    "sg:address":"Chemin Des Toises 5",
    "sg:city":"Ch\u00e2telard-lutry",
    "sg:orig_category":"Sonstiger Grosshandel",
    "sg:postcode":"1095",
    "sg:province":"Vaud",
    "wof:name":"Skandimport Lavanchy",
    "wof:placetype":"venue"
},
  "geometry": {"coordinates":[6.6880340576,46.5047645569],"type":"Point"}
}