{
  "type": "Feature",
  "properties": {
    "iso:country":"CH",
    "sg:address":"Bahnhofstrasse 1",
    "sg:city":"M\u00e4rstetten",
    "sg:orig_category":"G\u00fcterbef\u00f6rderung im Strassenverkehr",
    "sg:phone":"+41 71 657 22 11",
    "sg:postcode":"8560",
    "sg:province":"Thurgau",
    "wof:name":"Sch\u00f6nholzer Walter Ag Transport, Logistik, Spedition",
    "wof:placetype":"venue"
},
  "geometry": {"coordinates":[9.1485528946,47.5424194336],"type":"Point"}
}