{
  "type": "Feature",
  "properties": {
    "addr:full":"Thalstrasse 279 Laupersdorf Solothurn 4712",
    "addr:housenumber":"279",
    "addr:postcode":"4712",
    "addr:street":"Thalstrasse",
    "iso:country":"CH",
    "sg:address":"Thalstrasse 279",
    "sg:city":"Laupersdorf",
    "sg:orig_category":"Cardboard Sleeves, Tubes, Rolls",
    "sg:phone":"+41 62 391 44 15",
    "sg:postcode":"4712",
    "sg:province":"Solothurn",
    "wof:name":"Jura-papier Meier Ag",
    "wof:placetype":"venue"
},
  "geometry": {"coordinates":[7.647809,47.3111],"type":"Point"}
}