{
  "type": "Feature",
  "properties": {
    "iso:country":"CH",
    "sg:address":"Viale Castagnola 21g 6900 Lugano. Postfach 6906 Lugano",
    "sg:city":"Caselle",
    "sg:orig_category":"Detailhandel mit Bekleidung",
    "sg:phone":"+41 91 972 36 73",
    "sg:postcode":"6",
    "wof:name":"Modaseta Sa",
    "wof:placetype":"venue"
},
  "geometry": {"coordinates":[8.965856,46.006134],"type":"Point"}
}