{
  "type": "Feature",
  "properties": {
    "iso:country":"CH",
    "sg:address":"Beatenbergstrasse 111",
    "sg:city":"Unterseen",
    "sg:orig_category":"S\u00e4ge, Hobel U Holzimpr\u00e4gnierwerke S\u00e4gewerke",
    "sg:phone":"+41 33 822 03 60",
    "sg:postcode":"3800",
    "sg:province":"Bern",
    "wof:name":"Zenger S\u00e4gewerk Architekturb\u00fcro",
    "wof:placetype":"venue"
},
  "geometry": {"coordinates":[7.8414502144,46.6894111633],"type":"Point"}
}