{
  "type": "Feature",
  "properties": {
    "iso:country":"CH",
    "sg:address":"Mutschellenstrasse 93",
    "sg:city":"Z\u00fcrich",
    "sg:orig_category":"Vereine Quartier",
    "sg:postcode":"8038",
    "sg:province":"Z\u00fcrich",
    "wof:name":"Verein Z.erhaltung Alt-w'hofen",
    "wof:placetype":"venue"
},
  "geometry": {"coordinates":[8.5281944275,47.3488960266],"type":"Point"}
}