{
  "type": "Feature",
  "properties": {
    "iso:country":"CH",
    "sg:address":"Zugerstrasse 43 6314 Unter\u00e4geri. Postfach",
    "sg:city":"Unter\u00e4geri",
    "sg:orig_category":"Verwaltung von Immobilien",
    "sg:phone":"+41 79 643 75 40",
    "sg:postcode":"6314",
    "sg:province":"Zug",
    "wof:name":"Kaso B\u00f6hi K. Dienstleistungen Im Immobilienbereich, Warenhandel Usw",
    "wof:placetype":"venue"
},
  "geometry": {"coordinates":[8.5777931213,47.1378135681],"type":"Point"}
}