{
  "type": "Feature",
  "properties": {
    "iso:country":"CH",
    "sg:address":"Affolternstrasse 45",
    "sg:city":"Ottenbach",
    "sg:orig_category":"Bauspenglerei Zimmerei, Dachdeckerei, Bauspenglerei U Abdichtung",
    "sg:phone":"+41 17612185",
    "sg:postcode":"8913",
    "sg:province":"Z\u00fcrich",
    "wof:name":"Ritschard Hansruedi",
    "wof:placetype":"venue"
},
  "geometry": {"coordinates":[8.407932,47.277557],"type":"Point"}
}