{
  "type": "Feature",
  "properties": {
    "iso:country":"CH",
    "sg:address":"Kasernenstrasse 43",
    "sg:city":"Thun",
    "sg:orig_category":"Sanit\u00e4rinstallation",
    "sg:phone":"+41 33 222 25 44",
    "sg:postcode":"3600",
    "sg:province":"Bern",
    "wof:name":"Hermann Berger Sanit\u00e4re Rearaturen",
    "wof:placetype":"venue"
},
  "geometry": {"coordinates":[7.6172618866,46.7586097717],"type":"Point"}
}