{
  "type": "Feature",
  "properties": {
    "iso:country":"CH",
    "sg:address":"Centre Le Doubs",
    "sg:city":"St. Ursanne",
    "sg:classifiers":[
        {
            "category":"Banks & Credit Unions",
            "subcategory":"Bank",
            "type":"Services"
        }
    ],
    "sg:phone":"+41 24 481 82 79",
    "sg:postcode":"2882",
    "sg:province":"Jura",
    "wof:name":"Banque Raiffeisen Du Haut-l\u00e9man",
    "wof:placetype":"venue"
},
  "geometry": {"coordinates":[6.80548,46.39275],"type":"Point"}
}