{
  "type": "Feature",
  "properties": {
    "iso:country":"CH",
    "sg:address":"Aeschistrasse 13",
    "sg:city":"Nieder\u00f6nz",
    "sg:orig_category":"Erbringung von Dienstleistungen f\u00fcr Unternehmen Grosshandel mit Spielwaren",
    "sg:phone":"+41 62 961 01 31",
    "sg:postcode":"3362",
    "sg:province":"Bern",
    "wof:name":"Mth Modell-technik-hobby A.sommer",
    "wof:placetype":"venue"
},
  "geometry": {"coordinates":[7.6938538551,47.1854705811],"type":"Point"}
}