{
  "type": "Feature",
  "properties": {
    "iso:country":"CH",
    "sg:address":"Blausee-mitholz",
    "sg:city":"Kandergrund",
    "sg:orig_category":"Interessenvertretungen",
    "sg:postcode":"3716",
    "sg:province":"Bern",
    "wof:name":"Oskar Kambly-stiftung",
    "wof:placetype":"venue"
},
  "geometry": {"coordinates":[7.6699810028,46.530582428],"type":"Point"}
}