{
  "type": "Feature",
  "properties": {
    "iso:country":"CH",
    "sg:address":"Konstanzerstrasse 16",
    "sg:city":"Rossr\u00fcti",
    "sg:orig_category":"Detailhandel mit Milcherzeugnissen U Eiern Verarbeitung von Milch",
    "sg:phone":"+41 71 911 10 65",
    "sg:postcode":"9512",
    "sg:province":"St. Gallen",
    "wof:name":"Kaspar & Erika Christen Dorfch\u00e4si",
    "wof:placetype":"venue"
},
  "geometry": {"coordinates":[9.0607481003,47.4738464355],"type":"Point"}
}