{
  "type": "Feature",
  "properties": {
    "iso:country":"CH",
    "sg:address":"Rue Pr\u00e9 Guillaume",
    "sg:city":"Del\u00e9mont",
    "sg:orig_category":"Detailhandel mit elektrischen Haushalts-,Radio U Fernsehger\u00e4ten sowie Musikinstrumenten",
    "sg:postcode":"2800",
    "sg:province":"Jura",
    "wof:name":"Salon M\u00e9nager Sangsue Ernest",
    "wof:placetype":"venue"
},
  "geometry": {"coordinates":[7.3489551544,47.364025116],"type":"Point"}
}