{
  "type": "Feature",
  "properties": {
    "iso:country":"CH",
    "sg:address":"Villette 1",
    "sg:city":"Cham",
    "sg:orig_category":"Allgemeiner Hoch U Tiefbau",
    "sg:phone":"+41 41 781 45 45",
    "sg:postcode":"6330",
    "sg:province":"Zug",
    "wof:name":"Nrs Team Gmbh",
    "wof:placetype":"venue"
},
  "geometry": {"coordinates":[8.46061,47.179443],"type":"Point"}
}