{
  "type": "Feature",
  "properties": {
    "iso:country":"CH",
    "sg:address":"Vicolo Muggiasca 4",
    "sg:city":"Bellinzona",
    "sg:orig_category":"RESTAURANTS: TEA-ROOMS",
    "sg:postcode":"6500",
    "sg:province":"Ticino",
    "wof:name":"Giusal Sa",
    "wof:placetype":"venue"
},
  "geometry": {"coordinates":[9.0213956833,46.1908760071],"type":"Point"}
}