{
  "type": "Feature",
  "properties": {
    "iso:country":"CH",
    "sg:address":"St. Urbanstrasse 18",
    "sg:city":"Langenthal",
    "sg:orig_category":"Detailhandel mit Beleuchtungs U Haushaltsgegenst\u00e4nden Schmieden",
    "sg:phone":"+41 62 922 15 16",
    "sg:postcode":"4900",
    "sg:province":"Bern",
    "wof:name":"Hans B\u00fchler",
    "wof:placetype":"venue"
},
  "geometry": {"coordinates":[7.790661,47.212021],"type":"Point"}
}