{
  "type": "Feature",
  "properties": {
    "iso:country":"CH",
    "sg:address":"Fribourg Route De 14",
    "sg:city":"Marly",
    "sg:orig_category":"Erbringung von Dienstleistungen f\u00fcr Unternehmen",
    "sg:phone":"+41 26 435 33 42",
    "sg:postcode":"1723",
    "sg:province":"Fribourg",
    "wof:name":"Modemotech Ag",
    "wof:placetype":"venue"
},
  "geometry": {"coordinates":[7.1577301025,46.7780380249],"type":"Point"}
}