{
  "type": "Feature",
  "properties": {
    "iso:country":"CH",
    "sg:address":"Via Lucomagno",
    "sg:city":"Biasca",
    "sg:orig_category":"Forst\u00e4mter",
    "sg:phone":"+41 91 816 30 61",
    "sg:postcode":"6710",
    "sg:province":"Ticino",
    "wof:name":"Ufficio Forestale Ii Circondario",
    "wof:placetype":"venue"
},
  "geometry": {"coordinates":[8.9673404694,46.3699150085],"type":"Point"}
}