{
  "type": "Feature",
  "properties": {
    "iso:country":"CH",
    "sg:address":"Haldenbachstrasse 2",
    "sg:city":"Z\u00fcrich",
    "sg:orig_category":"Religi\u00f6se Vereinigungen",
    "sg:phone":"+41 12529833",
    "sg:postcode":"8006",
    "sg:province":"Z\u00fcrich",
    "wof:name":"Russisch-orthodoxe Kirche",
    "wof:placetype":"venue"
},
  "geometry": {"coordinates":[8.5471143723,47.3797607422],"type":"Point"}
}