{
  "type": "Feature",
  "properties": {
    "addr:full":"Waldeggstrasse 32 Rotkreuz Zug 6343",
    "addr:housenumber":"32",
    "addr:postcode":"6343",
    "addr:street":"Waldeggstrasse;Zug",
    "iso:country":"CH",
    "sg:address":"Waldeggstrasse 32",
    "sg:city":"Rotkreuz",
    "sg:orig_category":"Detailhandel mit Bekleidung Herstellung von sonstigen Metallwaren",
    "sg:phone":"+41 41 280 88 60",
    "sg:postcode":"6343",
    "sg:province":"Zug",
    "wof:name":"Laro Sport Ag",
    "wof:placetype":"venue"
},
  "geometry": {"coordinates":[8.433177,47.140411],"type":"Point"}
}