{
  "type": "Feature",
  "properties": {
    "iso:country":"CH",
    "sg:address":"Wallisberg 70",
    "sg:city":"Tscheppach",
    "sg:orig_category":"Detailhandel mit Ton U Bildtr\u00e4gern Detailhandel mit elektrischen Haushalts-,Radio U Fernsehger\u00e4ten s",
    "sg:phone":"+41 32 661 14 08",
    "sg:postcode":"4576",
    "sg:province":"Solothurn",
    "wof:name":"Bangerter Music- & Show Ag",
    "wof:placetype":"venue"
},
  "geometry": {"coordinates":[7.478495121,47.1437072754],"type":"Point"}
}