{
  "type": "Feature",
  "properties": {
    "iso:country":"CH",
    "sg:address":"Ch\u00e9salles Route De 48",
    "sg:city":"Marly",
    "sg:orig_category":"Herstellung von Kakao, Schokoladeerzeugnissen U Zuckerwaren",
    "sg:postcode":"1723",
    "sg:province":"Fribourg",
    "wof:name":"Trauffer B.",
    "wof:placetype":"venue"
},
  "geometry": {"coordinates":[9.819272995,46.7925987244],"type":"Point"}
}