{
  "type": "Feature",
  "properties": {
    "iso:country":"CH",
    "sg:address":"Dammweg 39",
    "sg:city":"Aarau",
    "sg:classifiers":[
        {
            "category":"Manufacturing",
            "subcategory":"Paper Products",
            "type":"Manufacturing & Wholesale Goods"
        }
    ],
    "sg:phone":"+41 62 834 13 00",
    "sg:postcode":"5001",
    "sg:province":"Aargau",
    "sg:tags":[
        "material",
        "-",
        "machine",
        "raw",
        "engineering",
        "printing",
        "mechanical",
        "cardboard"
    ],
    "wof:name":"Regia Holding",
    "wof:placetype":"venue"
},
  "geometry": {"coordinates":[8.0363302231,47.3864517212],"type":"Point"}
}