{
  "type": "Feature",
  "properties": {
    "iso:country":"CH",
    "sg:address":"Avenue De La Gare 29",
    "sg:city":"Martigny",
    "sg:orig_category":"Detailhandel mit Uhren U Schmuck",
    "sg:phone":"+41 27 722 13 71",
    "sg:postcode":"1920",
    "sg:province":"Valais",
    "wof:name":"Christine Huguenin Bijouti\u00e8re",
    "wof:placetype":"venue"
},
  "geometry": {"coordinates":[7.0771369934,46.1046524048],"type":"Point"}
}