{
  "type": "Feature",
  "properties": {
    "iso:country":"CH",
    "sg:address":"Kapellstr. 11 8862 Sch\u00fcbelbach. Postfach",
    "sg:city":"Siebnen",
    "sg:orig_category":"Zimmerei, Dachdeckerei, Bauspenglerei U Abdichtung",
    "sg:postcode":"8854",
    "sg:province":"Schwyz",
    "wof:name":"K\u00e4lin Bruno",
    "wof:placetype":"venue"
},
  "geometry": {"coordinates":[8.9009246826,47.1773071289],"type":"Point"}
}