{
  "type": "Feature",
  "properties": {
    "iso:country":"CH",
    "sg:address":"Via Mondacce 74",
    "sg:city":"Minusio",
    "sg:orig_category":"Unternehmensberatung",
    "sg:postcode":"6648",
    "sg:province":"Ticino",
    "wof:name":"Brem",
    "wof:placetype":"venue"
},
  "geometry": {"coordinates":[8.6820793152,47.26953125],"type":"Point"}
}