{
  "type": "Feature",
  "properties": {
    "iso:country":"CH",
    "sg:address":"Axenstrasse 2",
    "sg:city":"Brunnen",
    "sg:classifiers":[
        {
            "category":"Bars & Pubs",
            "type":"Food & Drink"
        }
    ],
    "sg:phone":"+41 27 957 14 10",
    "sg:postcode":"6440",
    "sg:province":"Schwyz",
    "wof:name":"Metro-bar",
    "wof:placetype":"venue"
},
  "geometry": {"coordinates":[7.933673,46.111717],"type":"Point"}
}