{
  "type": "Feature",
  "properties": {
    "iso:country":"CH",
    "sg:address":"Wydenweg 13",
    "sg:city":"B\u00e4ttwil-fl\u00fch",
    "sg:orig_category":"Schreib U \u00dcbersetzungsb\u00fcros",
    "sg:phone":"+41 61 733 10 05",
    "sg:postcode":"4112",
    "sg:province":"Solothurn",
    "wof:name":"Skinner-davies Language Solutions",
    "wof:placetype":"venue"
},
  "geometry": {"coordinates":[7.4967432022,47.4837150574],"type":"Point"}
}