{
  "type": "Feature",
  "properties": {
    "iso:country":"CH",
    "sg:address":"Baconni\u00e8re Chemin De La 49 2017 Boudry. Postfach",
    "sg:city":"Cormondr\u00e8che",
    "sg:orig_category":"Non-Classified Establishments",
    "sg:phone":"+41 32 731 87 12",
    "sg:postcode":"2036",
    "sg:province":"Neuch\u00e2tel",
    "wof:name":"Jean-fran\u00e7ois Simon",
    "wof:placetype":"venue"
},
  "geometry": {"coordinates":[6.838696003,46.9496192932],"type":"Point"}
}