{
  "type": "Feature",
  "properties": {
    "iso:country":"CH",
    "sg:address":"T\u00e4gerhardstrasse",
    "sg:city":"Wettingen",
    "sg:classifiers":[
        {
            "category":"Restaurant",
            "type":"Food & Drink"
        }
    ],
    "sg:phone":"+41 56 426 21 70",
    "sg:postcode":"5430",
    "sg:province":"Aargau",
    "wof:name":"Restaurant T\u00e4gerhard",
    "wof:placetype":"venue"
},
  "geometry": {"coordinates":[8.3253631592,47.4585990906],"type":"Point"}
}