{
  "type": "Feature",
  "properties": {
    "iso:country":"CH",
    "sg:address":"Chemin Des Boveresses 105",
    "sg:city":"Epalinges",
    "sg:orig_category":"Vermietung U Verpachtung von eigenen Immobilien",
    "sg:postcode":"1066",
    "sg:province":"Vaud",
    "wof:name":"Fiduciaire Et R\u00e9gie Du Golf, Rickli Silvana",
    "wof:placetype":"venue"
},
  "geometry": {"coordinates":[6.6669979095,46.5404472351],"type":"Point"}
}