{
  "type": "Feature",
  "properties": {
    "iso:country":"CH",
    "sg:address":"Vy-du-motti\u00e9 21",
    "sg:city":"Fontainemelon",
    "sg:orig_category":"Architektur U Ingenieurb\u00fcros",
    "sg:postcode":"2052",
    "sg:province":"Neuch\u00e2tel",
    "wof:name":"Basset Willy",
    "wof:placetype":"venue"
},
  "geometry": {"coordinates":[6.89565,47.05764],"type":"Point"}
}