{
  "type": "Feature",
  "properties": {
    "iso:country":"CH",
    "sg:address":"Ahornstrasse 33 4055 Basel. Postfach",
    "sg:city":"Basel",
    "sg:orig_category":"Detailhandel mit Fleisch U Fleischwaren Detailhandel mit Waren verschiedener Art, Hauptrichtung Nahr",
    "sg:phone":"+41 61 301 54 60",
    "sg:postcode":"4009",
    "sg:province":"Basel-Stadt",
    "wof:name":"Honegger Ag, Metzgerei Und Lebensmittel",
    "wof:placetype":"venue"
},
  "geometry": {"coordinates":[7.5723137856,47.5573654175],"type":"Point"}
}