{
  "type": "Feature",
  "properties": {
    "iso:country":"CH",
    "sg:address":"Rue Des Remparts 19",
    "sg:city":"Yverdon-les-bains",
    "sg:orig_category":"Unclassifiable Establishments",
    "sg:postcode":"1400",
    "sg:province":"Vaud",
    "wof:name":"Si Littoral G Sa",
    "wof:placetype":"venue"
},
  "geometry": {"coordinates":[6.639550209,46.7800788879],"type":"Point"}
}