{
  "type": "Feature",
  "properties": {
    "iso:country":"CH",
    "sg:address":"Contrada Via",
    "sg:city":"Melano",
    "sg:orig_category":"RESTAURANTS: TEA-ROOMS",
    "sg:postcode":"6818",
    "sg:province":"Ticino",
    "wof:name":"Ristorante Rusticanella Di Mariani Walter",
    "wof:placetype":"venue"
},
  "geometry": {"coordinates":[8.9860553741,45.9217758179],"type":"Point"}
}