{
  "type": "Feature",
  "properties": {
    "iso:country":"CH",
    "sg:address":"Bahnhofstrasse 4",
    "sg:city":"Bettwiesen",
    "sg:orig_category":"Nationale Postdienste",
    "sg:phone":"+41 33 676 11 05",
    "sg:postcode":"9553",
    "sg:province":"Thurgau",
    "wof:name":"Die Schweizerische Post",
    "wof:placetype":"venue"
},
  "geometry": {"coordinates":[7.6927142143,46.6253967285],"type":"Point"}
}