{
  "type": "Feature",
  "properties": {
    "iso:country":"CH",
    "sg:address":"Zollweg 11",
    "sg:city":"Walenstadt",
    "sg:orig_category":"Vermittlung von Immobilien Verwaltung von Immobilien",
    "sg:phone":"+41 22 786 09 00",
    "sg:postcode":"8880",
    "sg:province":"St. Gallen",
    "wof:name":"Serimo Service Immobilier Sa",
    "wof:placetype":"venue"
},
  "geometry": {"coordinates":[6.1422758102,46.2079963684],"type":"Point"}
}