{
  "type": "Feature",
  "properties": {
    "iso:country":"CH",
    "sg:address":"Hauptstrasse 9",
    "sg:city":"Sch\u00f6nengrund",
    "sg:orig_category":"Herstellung von Besen U B\u00fcrsten",
    "sg:phone":"+41 71 361 12 11",
    "sg:postcode":"9105",
    "sg:province":"Appenzell Ausserrhoden",
    "wof:name":"Albert Zellweger Besenfabrikation",
    "wof:placetype":"venue"
},
  "geometry": {"coordinates":[9.2246809006,47.328338623],"type":"Point"}
}