{
  "type": "Feature",
  "properties": {
    "iso:country":"CH",
    "sg:address":"Rue Des Tertres 2a",
    "sg:city":"Marin-epagnier",
    "sg:orig_category":"Politische Parteien SP",
    "sg:phone":"+41 32 721 11 80",
    "sg:postcode":"2074",
    "sg:province":"Neuch\u00e2tel",
    "wof:name":"Parti Socialiste Neuch\u00e2telois",
    "wof:placetype":"venue"
},
  "geometry": {"coordinates":[6.9460339546,46.999080658],"type":"Point"}
}