{
  "type": "Feature",
  "properties": {
    "iso:country":"CH",
    "sg:address":"Bernstrasse",
    "sg:city":"Lyss",
    "sg:orig_category":"Instandhaltung U Reparatur von Automobilen",
    "sg:phone":"+41 32 384 49 94",
    "sg:postcode":"3250",
    "sg:province":"Bern",
    "wof:name":"Autocenter Aebi Ag, Lyss",
    "wof:placetype":"venue"
},
  "geometry": {"coordinates":[7.3236150742,47.0673713684],"type":"Point"}
}