{
  "type": "Feature",
  "properties": {
    "iso:country":"CH",
    "sg:address":"Wylerringstrasse 60",
    "sg:city":"Bern",
    "sg:orig_category":"Buchf\u00fchrung Wirtschaftspr\u00fcfung, Steuerberatung U Treuhand",
    "sg:phone":"+41 56 470 33 44",
    "sg:postcode":"3014",
    "sg:province":"Bern",
    "wof:name":"A & O Treuhand Und Wirtschaftspr\u00fcfung Gmbh",
    "wof:placetype":"venue"
},
  "geometry": {"coordinates":[8.286017,47.454666],"type":"Point"}
}