{
  "type": "Feature",
  "properties": {
    "iso:country":"CH",
    "sg:address":"6938",
    "sg:city":"Vezio",
    "sg:classifiers":[
        {
            "category":"Restaurant",
            "type":"Food & Drink"
        }
    ],
    "sg:phone":"+41 91 609 11 37",
    "sg:postcode":"6938",
    "sg:province":"Ticino",
    "wof:name":"Osteria Busgnone",
    "wof:placetype":"venue"
},
  "geometry": {"coordinates":[8.8818702698,46.04529953],"type":"Point"}
}