{
  "type": "Feature",
  "properties": {
    "iso:country":"CH",
    "sg:address":"Alte Landstrasse 265",
    "sg:city":"M\u00e4nnedorf",
    "sg:orig_category":"Wirtschaftsverb\u00e4nde Gewerbeverb\u00e4nde/-vereine",
    "sg:phone":"+41 19201064",
    "sg:postcode":"8708",
    "sg:province":"Z\u00fcrich",
    "wof:name":"Gewerbeverein M\u00e4nnedorf",
    "wof:placetype":"venue"
},
  "geometry": {"coordinates":[8.6960763931,47.2533035278],"type":"Point"}
}