{
  "type": "Feature",
  "properties": {
    "iso:country":"CH",
    "sg:address":"Riva Vincenzo Vela 12 6900 Lugano. Postfach",
    "sg:city":"Lugano",
    "sg:orig_category":"Grosshandel mit sonstigen Halbwaren",
    "sg:postcode":"6900",
    "sg:province":"Ticino",
    "wof:name":"Crealine Case Fabrication F\u00fcllemann",
    "wof:placetype":"venue"
},
  "geometry": {"coordinates":[8.7984800339,47.3245201111],"type":"Point"}
}