{
  "type": "Feature",
  "properties": {
    "iso:country":"CH",
    "sg:address":"Hammerstrasse 86",
    "sg:city":"Basel",
    "sg:orig_category":"Architektur U Ingenieurb\u00fcros",
    "sg:phone":"+41 61 383 20 40",
    "sg:postcode":"4057",
    "sg:province":"Basel-Stadt",
    "wof:name":"Schmitz Bauwesen Gmbh B\u00fcro F\u00fcr Architektur, Bauhandwerk U. Liegenschaftsbetreuung Usw",
    "wof:placetype":"venue"
},
  "geometry": {"coordinates":[7.596069,47.564026],"type":"Point"}
}