{
  "type": "Feature",
  "properties": {
    "iso:country":"CH",
    "sg:address":"Hauptstrasse 20",
    "sg:city":"Rorschach",
    "sg:orig_category":"Bauschreinerei Herstellung von M\u00f6beln verschiedener Art",
    "sg:phone":"+41 71 841 21 63",
    "sg:postcode":"9400",
    "sg:province":"St. Gallen",
    "wof:name":"Venerando Romano",
    "wof:placetype":"venue"
},
  "geometry": {"coordinates":[9.496317,47.477901],"type":"Point"}
}