{
  "type": "Feature",
  "properties": {
    "iso:country":"CH",
    "sg:address":"Giacomettistrasse 16",
    "sg:city":"Bern",
    "sg:classifiers":[
        {
            "category":"Arena",
            "subcategory":"Sports Club",
            "type":"Entertainment"
        }
    ],
    "sg:postcode":"3006",
    "sg:province":"Bern",
    "sg:tags":[
        "karate",
        "judo",
        "sportvereine"
    ],
    "wof:name":"Universit\u00e4t Bern",
    "wof:placetype":"venue"
},
  "geometry": {"coordinates":[7.4735012054,46.9453239441],"type":"Point"}
}