{
  "type": "Feature",
  "properties": {
    "iso:country":"CH",
    "sg:address":"Stammrain 66",
    "sg:city":"Staffelbach",
    "sg:orig_category":"Herstellung von Mess U Kontrollinstrumenten U vorrichtungen",
    "sg:postcode":"5053",
    "sg:province":"Aargau",
    "wof:name":"Waaggenossenschaft Staffelbach",
    "wof:placetype":"venue"
},
  "geometry": {"coordinates":[8.0444478989,47.2828788757],"type":"Point"}
}