{
  "type": "Feature",
  "properties": {
    "iso:country":"CH",
    "sg:address":"Via Lavizzari 6",
    "sg:city":"Chiasso",
    "sg:orig_category":"Detailhandel mit Parf\u00fcmerieartikeln U K\u00f6rperpflegemitteln Parf\u00fcmerien U sonstiger Detailhandel mit k",
    "sg:phone":"+41 91 682 94 16",
    "sg:postcode":"6830",
    "sg:province":"Ticino",
    "wof:name":"Parf\u00fcmerie Douglas Ag",
    "wof:placetype":"venue"
},
  "geometry": {"coordinates":[9.0303907394,45.8350753784],"type":"Point"}
}