{
  "type": "Feature",
  "properties": {
    "iso:country":"CH",
    "sg:address":"Zentralstrasse 121 8212 Neuhausen. Postfach 1022",
    "sg:city":"Neuhausen",
    "sg:orig_category":"Handel mit Automobilen Tankstellen",
    "sg:phone":"+41 52 672 16 22",
    "sg:postcode":"8212",
    "sg:province":"Schaffhausen",
    "wof:name":"E + S Auto Corner Ag",
    "wof:placetype":"venue"
},
  "geometry": {"coordinates":[8.6221208572,47.6859474182],"type":"Point"}
}