{
  "type": "Feature",
  "properties": {
    "iso:country":"CH",
    "sg:address":"Ottenweg 29 8008 Z\u00fcrich. Postfach",
    "sg:city":"Z\u00fcrich",
    "sg:orig_category":"Hoch U Tiefbau",
    "sg:phone":"+41 12510750",
    "sg:postcode":"8032",
    "sg:province":"Z\u00fcrich",
    "wof:name":"Bryner & Co Baugesch\u00e4ft",
    "wof:placetype":"venue"
},
  "geometry": {"coordinates":[8.5537528992,47.3639221191],"type":"Point"}
}