{
  "type": "Feature",
  "properties": {
    "iso:country":"CH",
    "sg:address":"Seegartenstrasse 4 8353 Elgg. Postfach",
    "sg:city":"Elgg",
    "sg:orig_category":"Herstellung von sonstigen chemischen Erzeugnissen",
    "sg:postcode":"8353",
    "sg:province":"Z\u00fcrich",
    "wof:name":"Idowy, J. Dimmeler's Erben",
    "wof:placetype":"venue"
},
  "geometry": {"coordinates":[8.8659143448,47.4966392517],"type":"Point"}
}