{
  "type": "Feature",
  "properties": {
    "iso:country":"CH",
    "sg:address":"Rohrmattstrasse 4",
    "sg:city":"B\u00f6ckten",
    "sg:orig_category":"Sonstiger spezialisierter Hoch U Tiefbau",
    "sg:phone":"+41 32 757 24 18",
    "sg:postcode":"4461",
    "sg:province":"Basel-Landschaft",
    "wof:name":"Deshydrair, Manca G\u00e9rard.",
    "wof:placetype":"venue"
},
  "geometry": {"coordinates":[7.0321640968,47.0496444702],"type":"Point"}
}