{
  "type": "Feature",
  "properties": {
    "iso:country":"CH",
    "sg:address":"Lungolago Motta",
    "sg:city":"Locarno",
    "sg:classifiers":[
        {
            "category":"Bars & Pubs",
            "type":"Food & Drink"
        }
    ],
    "sg:phone":"+41 91 752 11 52",
    "sg:postcode":"6600",
    "sg:province":"Ticino",
    "wof:name":"Piano Bar Da Edy",
    "wof:placetype":"venue"
},
  "geometry": {"coordinates":[8.801355,46.168671],"type":"Point"}
}