{
  "type": "Feature",
  "properties": {
    "iso:country":"CH",
    "sg:address":"Hofmattweg 29",
    "sg:city":"Arlesheim",
    "sg:orig_category":"Grosshandel mit B\u00fcromaschinen Grosshandel mit Datenverarbeitungsger\u00e4ten",
    "sg:phone":"+41 79 356 24 65",
    "sg:postcode":"4144",
    "sg:province":"Basel-Landschaft",
    "wof:name":"Solutionware Ag",
    "wof:placetype":"venue"
},
  "geometry": {"coordinates":[7.6183781624,47.5038795471],"type":"Point"}
}