{
  "type": "Feature",
  "properties": {
    "iso:country":"CH",
    "sg:address":"Rietbachstrasse 5",
    "sg:city":"Schlieren",
    "sg:orig_category":"Interessenvertretungen",
    "sg:phone":"+41 17305161",
    "sg:postcode":"8952",
    "sg:province":"Z\u00fcrich",
    "wof:name":"Berufsschule F\u00fcr Kleinkindererziehung Bke",
    "wof:placetype":"venue"
},
  "geometry": {"coordinates":[8.438949585,47.4001693726],"type":"Point"}
}