{
  "type": "Feature",
  "properties": {
    "iso:country":"CH",
    "sg:address":"In Den Ziegelh\u00f6fen 167",
    "sg:city":"Basel",
    "sg:orig_category":"Softwareentwicklung U beratung",
    "sg:phone":"+41 61 303 18 80",
    "sg:postcode":"4054",
    "sg:province":"Basel-Stadt",
    "wof:name":"Gerber Infotech Gmbh Softwareentwicklung",
    "wof:placetype":"venue"
},
  "geometry": {"coordinates":[7.5569992065,47.5448455811],"type":"Point"}
}