{
  "type": "Feature",
  "properties": {
    "iso:country":"CH",
    "sg:address":"Im Langacker 4",
    "sg:city":"D\u00fcbendorf",
    "sg:orig_category":"Grosshandel mit Holz U Baustoffen",
    "sg:phone":"+41 79 216 45 21",
    "sg:postcode":"8600",
    "sg:province":"Z\u00fcrich",
    "wof:name":"Ff Gmbh",
    "wof:placetype":"venue"
},
  "geometry": {"coordinates":[8.6143360138,47.3926048279],"type":"Point"}
}