{
  "type": "Feature",
  "properties": {
    "iso:country":"CH",
    "sg:address":"1312",
    "sg:city":"Ecl\u00e9pens",
    "sg:orig_category":"Architektur U Ingenieurb\u00fcros",
    "sg:postcode":"1312",
    "sg:province":"Vaud",
    "wof:name":"Glass And Technics Gt Sa",
    "wof:placetype":"venue"
},
  "geometry": {"coordinates":[6.54448,46.652199],"type":"Point"}
}