{
  "type": "Feature",
  "properties": {
    "iso:country":"CH",
    "sg:address":"Stalden 31 4500 Solothurn. Postfach",
    "sg:city":"Solothurn",
    "sg:classifiers":[
        {
            "category":"Restaurant",
            "type":"Food & Drink"
        }
    ],
    "sg:phone":"+41 32 622 16 07",
    "sg:postcode":"4502",
    "sg:province":"Solothurn",
    "wof:name":"Restaurant Bucheggbergstube",
    "wof:placetype":"venue"
},
  "geometry": {"coordinates":[7.5350599289,47.2068595886],"type":"Point"}
}