{
  "type": "Feature",
  "properties": {
    "iso:country":"CH",
    "sg:address":"Bollstrasse 63",
    "sg:city":"Worb",
    "sg:orig_category":"Mechanische Werkst\u00e4tten",
    "sg:phone":"+41 31 839 45 44",
    "sg:postcode":"3076",
    "sg:province":"Bern",
    "wof:name":"Kowe Hydraulik-mechanik Ag",
    "wof:placetype":"venue"
},
  "geometry": {"coordinates":[7.5586400032,46.9380340576],"type":"Point"}
}