{
  "type": "Feature",
  "properties": {
    "iso:country":"CH",
    "sg:address":"Birseckstrasse 11 4144 Arlesheim. Postfach 437",
    "sg:city":"Arlesheim",
    "sg:orig_category":"Non-Classified Establishments",
    "sg:phone":"+41 61 703 12 90",
    "sg:postcode":"4144",
    "sg:province":"Basel-Landschaft",
    "wof:name":"Jaxx Gmbh",
    "wof:placetype":"venue"
},
  "geometry": {"coordinates":[7.6168570518,47.4982833862],"type":"Point"}
}