{
  "type": "Feature",
  "properties": {
    "addr:full":"Lausanne Rue De 91 1200 Genf. Postfach Gen\u00e8ve Gen\u00e8ve 1202",
    "addr:housenumber":"91",
    "addr:postcode":"1200 genf. postfach;1202",
    "addr:street":"Rue De",
    "iso:country":"CH",
    "sg:address":"Lausanne Rue De 91 1200 Genf. Postfach",
    "sg:city":"Gen\u00e8ve",
    "sg:orig_category":"Detailhandel mit Brot, Back U S\u00fcsswaren",
    "sg:postcode":"1202",
    "sg:province":"Gen\u00e8ve",
    "wof:name":"Loichet Georges Sa",
    "wof:placetype":"venue"
},
  "geometry": {"coordinates":[6.142701,46.208359],"type":"Point"}
}