{
  "type": "Feature",
  "properties": {
    "addr:full":"Baselstr. 55 Dagmersellen Luzern 6252",
    "addr:housenumber":"55",
    "addr:postcode":"6252",
    "addr:street":"Baselstr.",
    "iso:country":"CH",
    "sg:address":"Baselstr. 55",
    "sg:city":"Dagmersellen",
    "sg:classifiers":[
        {
            "category":"Manufacturing",
            "subcategory":"Chemicals & Compounds",
            "type":"Manufacturing & Wholesale Goods"
        }
    ],
    "sg:phone":"+41 62 748 20 30",
    "sg:postcode":"6252",
    "sg:province":"Luzern",
    "sg:tags":[
        "pharmaceutical",
        "chemistry",
        "-",
        "by-product"
    ],
    "wof:name":"Sericol Ag",
    "wof:placetype":"venue"
},
  "geometry": {"coordinates":[7.98256,47.219204],"type":"Point"}
}