{
  "type": "Feature",
  "properties": {
    "iso:country":"CH",
    "sg:address":"Postgeb\u00e4ude",
    "sg:city":"Grabs",
    "sg:orig_category":"Versicherungen Hauptagenturen",
    "sg:phone":"+41 55 442 38 38",
    "sg:postcode":"9472",
    "sg:province":"St. Gallen",
    "wof:name":"Winterthur-versicherungen Generalagentur",
    "wof:placetype":"venue"
},
  "geometry": {"coordinates":[8.8533735275,47.1925811768],"type":"Point"}
}