{
  "type": "Feature",
  "properties": {
    "iso:country":"CH",
    "sg:address":"Schachenstrasse 22",
    "sg:city":"Hochfelden",
    "sg:orig_category":"Berufsbildende weiterf\u00fchrende Schulen",
    "sg:phone":"+41 18620233",
    "sg:postcode":"8182",
    "sg:province":"Z\u00fcrich",
    "wof:name":"Massageschule & Praxis Trisana",
    "wof:placetype":"venue"
},
  "geometry": {"coordinates":[8.513747,47.526821],"type":"Point"}
}