{
  "type": "Feature",
  "properties": {
    "iso:country":"CH",
    "sg:address":"P\u00fcntenstr. 40",
    "sg:city":"Stallikon",
    "sg:orig_category":"Erbringung von Dienstleistungen f\u00fcr Unternehmen Erbringung von sonstigen Dienstleistungen f\u00fcr Untern",
    "sg:phone":"+41 17778607",
    "sg:postcode":"8143",
    "sg:province":"Z\u00fcrich",
    "wof:name":"Elle Deco-line",
    "wof:placetype":"venue"
},
  "geometry": {"coordinates":[8.4888896942,47.3266601562],"type":"Point"}
}