{
  "type": "Feature",
  "properties": {
    "iso:country":"CH",
    "sg:address":"Roncaglia Via",
    "sg:city":"Novazzano",
    "sg:orig_category":"Reparatur von Schuhen U Lederwaren",
    "sg:postcode":"6883",
    "sg:province":"Ticino",
    "wof:name":"Nature Way Sagl",
    "wof:placetype":"venue"
},
  "geometry": {"coordinates":[8.9951210022,45.8402671814],"type":"Point"}
}