{
  "type": "Feature",
  "properties": {
    "iso:country":"CH",
    "sg:address":"Rafour 7a",
    "sg:city":"St-aubin-sauges",
    "sg:orig_category":"Unternehmensberatung",
    "sg:postcode":"2024",
    "sg:province":"Neuch\u00e2tel",
    "wof:name":"Jacot Philippe, Consulting Technologie",
    "wof:placetype":"venue"
},
  "geometry": {"coordinates":[6.7791981697,46.8940544128],"type":"Point"}
}