{
  "type": "Feature",
  "properties": {
    "iso:country":"CH",
    "sg:address":"Boulevard L.-dapples 16",
    "sg:city":"Vevey",
    "sg:orig_category":"Personal U Stellenvermittlung Unternehmensberatung",
    "sg:phone":"+41 79 448 69 90",
    "sg:postcode":"1800",
    "sg:province":"Vaud",
    "wof:name":"Human Capital Ag",
    "wof:placetype":"venue"
},
  "geometry": {"coordinates":[6.8487458229,46.4632568359],"type":"Point"}
}