{
  "type": "Feature",
  "properties": {
    "iso:country":"CH",
    "sg:address":"Boulevard Carl-vogt 9",
    "sg:city":"Gen\u00e8ve",
    "sg:orig_category":"Mineralwasser Detailhandel Wein Detailhandel",
    "sg:phone":"+41 22 329 71 73",
    "sg:postcode":"1205",
    "sg:province":"Gen\u00e8ve",
    "wof:name":"Cave De La Jonction Vins Boissons",
    "wof:placetype":"venue"
},
  "geometry": {"coordinates":[6.1310682297,46.2008972168],"type":"Point"}
}