{
  "type": "Feature",
  "properties": {
    "iso:country":"CH",
    "sg:address":"Albertolli Riva 1",
    "sg:city":"Lugano",
    "sg:orig_category":"Detailhandel mit Schuhen U Lederwaren",
    "sg:postcode":"6900",
    "sg:province":"Ticino",
    "wof:name":"Margherita Sa",
    "wof:placetype":"venue"
},
  "geometry": {"coordinates":[8.9513053894,46.0029754639],"type":"Point"}
}