{
  "type": "Feature",
  "properties": {
    "iso:country":"CH",
    "sg:address":"3128",
    "sg:city":"R\u00fcmligen",
    "sg:orig_category":"Schulpflegen",
    "sg:postcode":"3128",
    "sg:province":"Bern",
    "wof:name":"Primarschulkommission Der Gemeinde R\u00fcti Bei B\u00fcren",
    "wof:placetype":"venue"
},
  "geometry": {"coordinates":[7.4135098457,47.1519584656],"type":"Point"}
}