{
  "type": "Feature",
  "properties": {
    "iso:country":"CH",
    "sg:address":"Rue De Lausanne 15",
    "sg:city":"Payerne",
    "sg:classifiers":[
        {
            "category":"Personal",
            "subcategory":"Sauna",
            "type":"Services"
        }
    ],
    "sg:phone":"+41 26 660 30 40",
    "sg:postcode":"1530",
    "sg:province":"Vaud",
    "wof:name":"City-relax Sauna",
    "wof:placetype":"venue"
},
  "geometry": {"coordinates":[6.9365100861,46.8199386597],"type":"Point"}
}