{
  "type": "Feature",
  "properties": {
    "iso:country":"CH",
    "sg:address":"Verger Rue Du 11",
    "sg:city":"B\u00f4le",
    "sg:orig_category":"Dienstleistungen von Beteiligungsgesellschaften",
    "sg:postcode":"2014",
    "sg:province":"Neuch\u00e2tel",
    "wof:name":"Pb Gestion Sa",
    "wof:placetype":"venue"
},
  "geometry": {"coordinates":[6.8470821381,46.9671096802],"type":"Point"}
}