{
  "type": "Feature",
  "properties": {
    "iso:country":"CH",
    "sg:address":"R\u00fcdigerstrasse 10",
    "sg:city":"Z\u00fcrich",
    "sg:orig_category":"Werbegrafikateliers",
    "sg:phone":"+41 12013292",
    "sg:postcode":"8045",
    "sg:province":"Z\u00fcrich",
    "wof:name":"Christina Meili Grafisches Atelier",
    "wof:placetype":"venue"
},
  "geometry": {"coordinates":[8.5218706131,47.3610153198],"type":"Point"}
}