{
  "type": "Feature",
  "properties": {
    "iso:country":"CH",
    "sg:address":"Netschb\u00fchl",
    "sg:city":"Eggiwil",
    "sg:orig_category":"Grosshandel mit lebenden Tieren",
    "sg:phone":"+41 34 491 11 49",
    "sg:postcode":"3537",
    "sg:province":"Bern",
    "wof:name":"Fritz Fankhauser Viehhandel",
    "wof:placetype":"venue"
},
  "geometry": {"coordinates":[7.7702660561,46.8847579956],"type":"Point"}
}