{
  "type": "Feature",
  "properties": {
    "iso:country":"CH",
    "sg:address":"Sax",
    "sg:city":"Sennwald",
    "sg:classifiers":[
        {
            "category":"Travel",
            "subcategory":"Hotels & Motels",
            "type":"Entertainment"
        }
    ],
    "sg:postcode":"9466",
    "sg:province":"St. Gallen",
    "sg:tags":[
        "hotels",
        "mit",
        "restaurant"
    ],
    "wof:name":"Schl\u00f6ssli Sax Ag",
    "wof:placetype":"venue"
},
  "geometry": {"coordinates":[9.4538497925,47.2411499023],"type":"Point"}
}