{
  "type": "Feature",
  "properties": {
    "iso:country":"CH",
    "sg:address":"Baronrain 5",
    "sg:city":"Balsthal",
    "sg:orig_category":"Architektur U Ingenieurb\u00fcros",
    "sg:phone":"+41 62 391 55 87",
    "sg:postcode":"4710",
    "sg:province":"Solothurn",
    "wof:name":"Architekturb\u00fcro Sidler Conrad",
    "wof:placetype":"venue"
},
  "geometry": {"coordinates":[7.688991,47.315327],"type":"Point"}
}