{
  "type": "Feature",
  "properties": {
    "iso:country":"CH",
    "sg:address":"Engelbergstrasse 28 6370 Stans. Postfach 1134",
    "sg:city":"Stans",
    "sg:orig_category":"Versicherungen Generalagenturen",
    "sg:phone":"+41 41 268 67 77",
    "sg:postcode":"6371",
    "sg:province":"Nidwalden",
    "wof:name":"Winterthur Versicherungen Generalagentur",
    "wof:placetype":"venue"
},
  "geometry": {"coordinates":[8.2761087418,47.0752449036],"type":"Point"}
}