{
  "type": "Feature",
  "properties": {
    "iso:country":"CH",
    "sg:address":"Breisacherstrasse 86",
    "sg:city":"Basel",
    "sg:orig_category":"Herstellung von sonstigen elektrischen Ausr\u00fcstungen",
    "sg:phone":"+41 61 692 28 61",
    "sg:postcode":"4057",
    "sg:province":"Basel-Stadt",
    "wof:name":"Huttenschmitt Handel",
    "wof:placetype":"venue"
},
  "geometry": {"coordinates":[7.5888991356,47.5679893494],"type":"Point"}
}