{
  "type": "Feature",
  "properties": {
    "iso:country":"CH",
    "sg:address":"Dufourstrasse 119",
    "sg:city":"Z\u00fcrich",
    "sg:orig_category":"Kunsthandel",
    "sg:phone":"+41 13836300",
    "sg:postcode":"8008",
    "sg:province":"Z\u00fcrich",
    "wof:name":"Jeannette G. Brun Kunst Der Antike",
    "wof:placetype":"venue"
},
  "geometry": {"coordinates":[8.5525140762,47.3580093384],"type":"Point"}
}