{
  "type": "Feature",
  "properties": {
    "iso:country":"CH",
    "sg:address":"Gr\u00e4tzlistrasse 25",
    "sg:city":"Opfikon",
    "sg:orig_category":"Softwareentwicklung U beratung",
    "sg:postcode":"8152",
    "sg:province":"Z\u00fcrich",
    "wof:name":"Excess Consulting Gmbh",
    "wof:placetype":"venue"
},
  "geometry": {"coordinates":[8.5797357559,47.4265289307],"type":"Point"}
}