{
  "type": "Feature",
  "properties": {
    "iso:country":"CH",
    "sg:address":"Galil\u00e9e Rue 15 1400 Yverdon-les-bains. Postfach",
    "sg:city":"Cheseaux-nor\u00e9az",
    "sg:orig_category":"Hochschulen U h\u00f6here Ausbildung",
    "sg:postcode":"1400",
    "sg:province":"Vaud",
    "wof:name":"Stuckitools Ag Handlungsorientertes Lernen Durch Herstellung U. Vertrieb Von Lehrmittel Usw.",
    "wof:placetype":"venue"
},
  "geometry": {"coordinates":[7.6164951324,46.7236251831],"type":"Point"}
}