{
  "type": "Feature",
  "properties": {
    "iso:country":"CH",
    "sg:address":"Holzwiesstrasse 35",
    "sg:city":"Jona",
    "sg:orig_category":"Erwachsenenbildung U Unterricht Unternehmensberatung",
    "sg:phone":"+41 55 212 55 54",
    "sg:postcode":"8645",
    "sg:province":"St. Gallen",
    "wof:name":"Marketing Perspectives Eberhard Pius Training U. Beratung Im Marketingbereich. Trainings-hilfsmittel, B\u00fccher; Handel",
    "wof:placetype":"venue"
},
  "geometry": {"coordinates":[8.8375673294,47.235458374],"type":"Point"}
}