{
  "type": "Feature",
  "properties": {
    "iso:country":"CH",
    "sg:address":"Murifeldweg 36 3006 Bern. Postfach",
    "sg:city":"Bern",
    "sg:orig_category":"Informatikdienste Softwareentwicklung U beratung",
    "sg:phone":"+41 31 351 89 19",
    "sg:postcode":"3006",
    "sg:province":"Bern",
    "wof:name":"Funke Projekterlebnisse Gmbh Dienstleistungen Im Ber. Der Informatik- U. Unternehmensberatung Usw.",
    "wof:placetype":"venue"
},
  "geometry": {"coordinates":[7.4725608826,46.9406509399],"type":"Point"}
}