{
  "type": "Feature",
  "properties": {
    "iso:country":"CH",
    "sg:address":"1018 Lausanne Case Postale 130",
    "sg:city":"Lausanne",
    "sg:orig_category":"Sportvereine P\u00e9tanque",
    "sg:phone":"+41 21 648 69 40",
    "sg:postcode":"1018",
    "sg:province":"Vaud",
    "wof:name":"P\u00e9tanque-club Les Alli\u00e9s",
    "wof:placetype":"venue"
},
  "geometry": {"coordinates":[6.634540081,46.5387687683],"type":"Point"}
}