{
  "type": "Feature",
  "properties": {
    "iso:country":"CH",
    "sg:address":"Camping Seerose",
    "sg:city":"Moosseedorf",
    "sg:orig_category":"Betrieb von Taxis",
    "sg:phone":"+41 77517272",
    "sg:postcode":"3302",
    "sg:province":"Bern",
    "wof:name":"Sollberger Limousine-service Bern Gmbh",
    "wof:placetype":"venue"
},
  "geometry": {"coordinates":[7.482055,47.016281],"type":"Point"}
}