{
  "type": "Feature",
  "properties": {
    "iso:country":"CH",
    "sg:address":"Bruggm\u00fchle 1",
    "sg:city":"Bischofszell",
    "sg:orig_category":"Sozialversicherung",
    "sg:phone":"+41 52 672 13 88",
    "sg:postcode":"9220",
    "sg:province":"Thurgau",
    "wof:name":"Egk-gesundheitskasse",
    "wof:placetype":"venue"
},
  "geometry": {"coordinates":[8.6188907623,47.6796264648],"type":"Point"}
}