{
  "type": "Feature",
  "properties": {
    "iso:country":"CH",
    "sg:address":"Bata-park 42",
    "sg:city":"M\u00f6hlin",
    "sg:orig_category":"G\u00fcterbef\u00f6rderung im Strassenverkehr",
    "sg:phone":"+41 79 277 22 86",
    "sg:postcode":"4313",
    "sg:province":"Aargau",
    "wof:name":"Osman Colakoglu Transporte",
    "wof:placetype":"venue"
},
  "geometry": {"coordinates":[7.8435168266,47.5756874084],"type":"Point"}
}