{
  "type": "Feature",
  "properties": {
    "iso:country":"CH",
    "sg:address":"Unterweg 81",
    "sg:city":"B\u00fclach",
    "sg:classifiers":[
        {
            "category":"Banks & Credit Unions",
            "subcategory":"Bank",
            "type":"Services"
        }
    ],
    "sg:phone":"+41 18601007",
    "sg:postcode":"8180",
    "sg:province":"Z\u00fcrich",
    "wof:name":"Rentenanstalt Swiss Life",
    "wof:placetype":"venue"
},
  "geometry": {"coordinates":[8.544225,47.529942],"type":"Point"}
}