{
  "type": "Feature",
  "properties": {
    "iso:country":"CH",
    "sg:address":"Route De L'allondon 26",
    "sg:city":"Satigny",
    "sg:orig_category":"Instandhaltung U Reparatur von Automobilen",
    "sg:phone":"+41 22 753 16 58",
    "sg:postcode":"1242",
    "sg:province":"Gen\u00e8ve",
    "wof:name":"Vincent Andr\u00e9",
    "wof:placetype":"venue"
},
  "geometry": {"coordinates":[6.0330200195,46.2154808044],"type":"Point"}
}