{
  "type": "Feature",
  "properties": {
    "addr:full":"Spitalgasse 27 Bern Bern 3011",
    "addr:housenumber":"27",
    "addr:postcode":"3011",
    "addr:street":"Spitalgasse",
    "iso:country":"CH",
    "sg:address":"Spitalgasse 27",
    "sg:city":"Bern",
    "sg:orig_category":"Detailhandel mit Brillen U anderen Sehhilfen Detailhandel mit medizinischen U orthop\u00e4dischen Artikel",
    "sg:phone":"+41 31 311 49 65",
    "sg:postcode":"3011",
    "sg:province":"Bern",
    "wof:name":"Micro-electric H\u00f6rger\u00e4te Ag",
    "wof:placetype":"venue"
},
  "geometry": {"coordinates":[7.442146,46.947948],"type":"Point"}
}