{
  "type": "Feature",
  "properties": {
    "iso:country":"CH",
    "sg:address":"Hauptstrasse 9",
    "sg:city":"Balterswil",
    "sg:orig_category":"Grosshandel mit Holz U Baustoffen",
    "sg:phone":"+41 71 971 17 67",
    "sg:postcode":"8362",
    "sg:province":"Thurgau",
    "wof:name":"Thoro Plattenhandel Roland Wey",
    "wof:placetype":"venue"
},
  "geometry": {"coordinates":[8.9324941635,47.4510612488],"type":"Point"}
}