{
  "type": "Feature",
  "properties": {
    "iso:country":"CH",
    "sg:address":"Benkenstrasse 14",
    "sg:city":"Therwil",
    "sg:orig_category":"Lampen and Beleuchtungsk\u00f6rper Grosshandel Vermietung von Gebrauchsg\u00fctern",
    "sg:postcode":"4106",
    "sg:province":"Basel-Landschaft",
    "wof:name":"Power Sound Veranstaltungs- Technik S\u00e9quin & B\u00fcchi",
    "wof:placetype":"venue"
},
  "geometry": {"coordinates":[7.5504641533,47.4991226196],"type":"Point"}
}