{
  "type": "Feature",
  "properties": {
    "iso:country":"CH",
    "sg:address":"Appenzellerstrasse 37",
    "sg:city":"Rheineck",
    "sg:orig_category":"Alters U Pflegeheime Wohnheime",
    "sg:phone":"+41 71 888 12 72",
    "sg:postcode":"9424",
    "sg:province":"St. Gallen",
    "wof:name":"Altersheim Altensteig",
    "wof:placetype":"venue"
},
  "geometry": {"coordinates":[9.587775,47.463425],"type":"Point"}
}