{
  "type": "Feature",
  "properties": {
    "iso:country":"CH",
    "sg:address":"Arbonerstrasse 62a",
    "sg:city":"Amriswil",
    "sg:orig_category":"Elektroinstallation",
    "sg:phone":"+41 71 411 15 33",
    "sg:postcode":"8580",
    "sg:province":"Thurgau",
    "wof:name":"Helfenberger + J\u00e4ggi Ag",
    "wof:placetype":"venue"
},
  "geometry": {"coordinates":[9.3185949326,47.5411300659],"type":"Point"}
}