{
  "type": "Feature",
  "properties": {
    "iso:country":"CH",
    "sg:address":"Spitalgasse 27 3011 Bern. Postfach",
    "sg:city":"Bern",
    "sg:orig_category":"Finanzierungsinstitutionen",
    "sg:phone":"+41 22 909 68 60",
    "sg:postcode":"3005",
    "sg:province":"Bern",
    "wof:name":"Telecel International Sa",
    "wof:placetype":"venue"
},
  "geometry": {"coordinates":[6.142677784,46.2057914734],"type":"Point"}
}