{
  "type": "Feature",
  "properties": {
    "iso:country":"CH",
    "sg:address":"La Mellette",
    "sg:city":"Montpreveyres",
    "sg:orig_category":"Vermietung U Verpachtung von eigenen Immobilien Vermittlung von Immobilien",
    "sg:phone":"+41 79 415 57 18",
    "sg:postcode":"1081",
    "sg:province":"Vaud",
    "wof:name":"Assumob Sa Agence Immobili\u00e8re",
    "wof:placetype":"venue"
},
  "geometry": {"coordinates":[6.7298679352,46.5795478821],"type":"Point"}
}