{
  "type": "Feature",
  "properties": {
    "iso:country":"CH",
    "sg:address":"Lagerhausstrasse 11 8400 Winterthur. Postfach 679",
    "sg:city":"Winterthur",
    "sg:orig_category":"Datenbanken Softwareentwicklung U beratung",
    "sg:phone":"+41 52 260 04 04",
    "sg:postcode":"8401",
    "sg:province":"Z\u00fcrich",
    "wof:name":"Nethorizon Ag",
    "wof:placetype":"venue"
},
  "geometry": {"coordinates":[8.724531,47.497513],"type":"Point"}
}