{
  "type": "Feature",
  "properties": {
    "iso:country":"CH",
    "sg:address":"Via Luserte 6",
    "sg:city":"Quartino",
    "sg:orig_category":"Handel mit Automobilen",
    "sg:phone":"+41 91 858 33 74",
    "sg:postcode":"6572",
    "sg:province":"Ticino",
    "wof:name":"Classic Cars Center Di D'andrea Francesco",
    "wof:placetype":"venue"
},
  "geometry": {"coordinates":[8.911614418,46.1510429382],"type":"Point"}
}