{
  "type": "Feature",
  "properties": {
    "iso:country":"CH",
    "sg:address":"Rosengartenstrasse 6",
    "sg:city":"Weesen",
    "sg:orig_category":"Arztpraxen",
    "sg:phone":"+41 55 616 11 62",
    "sg:postcode":"8872",
    "sg:province":"St. Gallen",
    "wof:name":"Dr.med.elisabeth Sulser Aerztin F.allgemeine Medizin",
    "wof:placetype":"venue"
},
  "geometry": {"coordinates":[9.093694,47.132362],"type":"Point"}
}