{
  "type": "Feature",
  "properties": {
    "iso:country":"CH",
    "sg:address":"Im Neuhof 44",
    "sg:city":"Emmenbr\u00fccke",
    "sg:orig_category":"Einbau von Schreinerwaren",
    "sg:phone":"+41 41 280 57 19",
    "sg:postcode":"6020",
    "sg:province":"Luzern",
    "wof:name":"Hansruedi Theiler",
    "wof:placetype":"venue"
},
  "geometry": {"coordinates":[8.2582788467,47.0698661804],"type":"Point"}
}