{
  "type": "Feature",
  "properties": {
    "iso:country":"CH",
    "sg:address":"Kasparstrasse 17/136",
    "sg:city":"Bern",
    "sg:orig_category":"Non-Classified Establishments",
    "sg:postcode":"3027",
    "sg:province":"Bern",
    "wof:name":"Dieter Elias, Malereibetrieb",
    "wof:placetype":"venue"
},
  "geometry": {"coordinates":[9.0708942413,46.9933204651],"type":"Point"}
}