{
  "type": "Feature",
  "properties": {
    "iso:country":"CH",
    "sg:address":"Chressibuech",
    "sg:city":"Hefenhofen",
    "sg:orig_category":"Obstbau",
    "sg:phone":"+41 71 411 15 92",
    "sg:postcode":"8580",
    "sg:province":"Thurgau",
    "wof:name":"Gottfried K\u00f6chli Obstbau",
    "wof:placetype":"venue"
},
  "geometry": {"coordinates":[9.3224897385,47.5590515137],"type":"Point"}
}