{
  "type": "Feature",
  "properties": {
    "iso:country":"CH",
    "sg:address":"Weiherhofstrasse 49",
    "sg:city":"Lausen",
    "sg:orig_category":"Technische B\u00fcros Elektro",
    "sg:phone":"+41 61 921 57 13",
    "sg:postcode":"4415",
    "sg:province":"Basel-Landschaft",
    "wof:name":"Adolf Reichen Elektro-planung",
    "wof:placetype":"venue"
},
  "geometry": {"coordinates":[7.7657318115,47.4749984741],"type":"Point"}
}