{
  "type": "Feature",
  "properties": {
    "iso:country":"CH",
    "sg:address":"6319",
    "sg:city":"Allenwinden",
    "sg:orig_category":"Primarschulen",
    "sg:phone":"+41 41 750 17 17",
    "sg:postcode":"6319",
    "sg:province":"Zug",
    "wof:name":"Primarschule",
    "wof:placetype":"venue"
},
  "geometry": {"coordinates":[8.5485897064,47.1634597778],"type":"Point"}
}