{
  "type": "Feature",
  "properties": {
    "iso:country":"CH",
    "sg:address":"Rue F.-gonseth 2a",
    "sg:city":"Sonvilier",
    "sg:orig_category":"Detailhandel mit Waren verschiedener Art, Hauptrichtung Nahrungsmittel Grosshandel mit Nahrungsmitte",
    "sg:phone":"+41 32 941 52 02",
    "sg:postcode":"2615",
    "sg:province":"Bern",
    "wof:name":"Le Primeur Santoro Roberto",
    "wof:placetype":"venue"
},
  "geometry": {"coordinates":[6.9651851654,47.1390609741],"type":"Point"}
}