{
  "type": "Feature",
  "properties": {
    "iso:country":"CH",
    "sg:address":"Hauptstrasse 82",
    "sg:city":"Muttenz",
    "sg:orig_category":"Arztpraxen",
    "sg:phone":"+41 81 756 61 70",
    "sg:postcode":"4132",
    "sg:province":"Basel-Landschaft",
    "wof:name":"Dr.med.werner Sch\u00f6b Arzt F.allgemeine Medizin Fmh",
    "wof:placetype":"venue"
},
  "geometry": {"coordinates":[9.476932,47.166973],"type":"Point"}
}