{
  "type": "Feature",
  "properties": {
    "iso:country":"CH",
    "sg:address":"Centrale Rue 2",
    "sg:city":"Ste-croix",
    "sg:orig_category":"Softwareentwicklung U beratung",
    "sg:postcode":"1450",
    "sg:province":"Vaud",
    "wof:name":"Soft Application, Mongin",
    "wof:placetype":"venue"
},
  "geometry": {"coordinates":[6.5010781288,46.8240737915],"type":"Point"}
}