{
  "type": "Feature",
  "properties": {
    "iso:country":"CH",
    "sg:address":"G\u00fcttinger Strasse 8",
    "sg:city":"Altnau",
    "sg:orig_category":"Vereine Musik/Blasmusik",
    "sg:postcode":"8595",
    "sg:province":"Thurgau",
    "wof:name":"Musikgesellschaft Amden",
    "wof:placetype":"venue"
},
  "geometry": {"coordinates":[9.0545148849,47.1724510193],"type":"Point"}
}