{
  "type": "Feature",
  "properties": {
    "iso:country":"CH",
    "sg:address":"Schlossackerstrasse 10",
    "sg:city":"Pratteln",
    "sg:orig_category":"Sportvereine Ski",
    "sg:phone":"+41 61 821 50 46",
    "sg:postcode":"4133",
    "sg:province":"Basel-Landschaft",
    "wof:name":"Skiclub Pratteln",
    "wof:placetype":"venue"
},
  "geometry": {"coordinates":[7.7022209167,47.5235671997],"type":"Point"}
}