{
  "type": "Feature",
  "properties": {
    "iso:country":"CH",
    "sg:address":"Unterdorf 34",
    "sg:city":"Lauperswil",
    "sg:classifiers":[
        {
            "category":"Bars & Pubs",
            "subcategory":"Dive Bar",
            "type":"Food & Drink"
        }
    ],
    "sg:phone":"+41 79 444 86 24",
    "sg:postcode":"3438",
    "sg:province":"Bern",
    "sg:tags":[
        "column",
        "granite"
    ],
    "wof:name":"Fl\u00dcha Gmbh",
    "wof:placetype":"venue"
},
  "geometry": {"coordinates":[7.7431697845,46.9671287537],"type":"Point"}
}