{
  "type": "Feature",
  "properties": {
    "iso:country":"CH",
    "sg:address":"Route Du Nant-d'avril 101",
    "sg:city":"Meyrin",
    "sg:orig_category":"Herstellung von Ger\u00e4ten der Elektrizit\u00e4tserzeugung, -verteilung u.\u00e4. -Herstellung von elektronischen",
    "sg:phone":"+41 22 782 76 28",
    "sg:postcode":"1217",
    "sg:province":"Gen\u00e8ve",
    "wof:name":"Ap Electronique S\u00e0rl",
    "wof:placetype":"venue"
},
  "geometry": {"coordinates":[6.0722098351,46.2284393311],"type":"Point"}
}