{
  "type": "Feature",
  "properties": {
    "iso:country":"CH",
    "sg:address":"Leginglenstrasse 17",
    "sg:city":"Sargans",
    "sg:orig_category":"Sportvereine Sch\u00fctzen Pistolen-& Gewehr",
    "sg:postcode":"7320",
    "sg:province":"St. Gallen",
    "wof:name":"Feldsch\u00fctzengesellschaft",
    "wof:placetype":"venue"
},
  "geometry": {"coordinates":[9.4315500259,47.0519218445],"type":"Point"}
}