{
  "type": "Feature",
  "properties": {
    "iso:country":"CH",
    "sg:address":"Junkholzweg 3",
    "sg:city":"Kaiseraugst",
    "sg:orig_category":"Unternehmensberatung",
    "sg:phone":"+41 61 813 04 04",
    "sg:postcode":"4303",
    "sg:province":"Aargau",
    "wof:name":"Oops Gmbh",
    "wof:placetype":"venue"
},
  "geometry": {"coordinates":[7.7308330536,47.5379562378],"type":"Point"}
}