{
  "type": "Feature",
  "properties": {
    "iso:country":"CH",
    "sg:address":"Stauffacherstrasse 60",
    "sg:city":"Z\u00fcrich",
    "sg:classifiers":[
        {
            "category":"Restaurant",
            "type":"Food & Drink"
        }
    ],
    "sg:phone":"+41 12404090",
    "sg:postcode":"8004",
    "sg:province":"Z\u00fcrich",
    "wof:name":"Restaurant Helvetiaplatz",
    "wof:placetype":"venue"
},
  "geometry": {"coordinates":[8.5271158218,47.3754844666],"type":"Point"}
}