{
  "type": "Feature",
  "properties": {
    "iso:country":"CH",
    "sg:address":"Schulstrasse 3",
    "sg:city":"Fischbach-g\u00f6slikon",
    "sg:orig_category":"Vermietung U Verpachtung von eigenen Immobilien",
    "sg:phone":"+41 56 622 01 66",
    "sg:postcode":"5525",
    "sg:province":"Aargau",
    "wof:name":"Menzin Ag",
    "wof:placetype":"venue"
},
  "geometry": {"coordinates":[8.3085365295,47.3702850342],"type":"Point"}
}