{
  "type": "Feature",
  "properties": {
    "iso:country":"CH",
    "sg:address":"Les Planettes",
    "sg:city":"Venth\u00f4ne",
    "sg:classifiers":[
        {
            "category":"Insurance",
            "subcategory":"Insurance Agent",
            "type":"Services"
        }
    ],
    "sg:phone":"+41 79 225 23 33",
    "sg:postcode":"3973",
    "sg:province":"Valais",
    "sg:tags":[
        "versicherungsagenturen",
        "-broker"
    ],
    "wof:name":"S\u00e9bastien Caloz Genevoise-assurances",
    "wof:placetype":"venue"
},
  "geometry": {"coordinates":[7.5206131935,46.3026161194],"type":"Point"}
}