{
  "type": "Feature",
  "properties": {
    "addr:full":"Allmendstrasse 193 Thun Bern 3603",
    "addr:housenumber":"193",
    "addr:postcode":"3603",
    "addr:street":"Allmendstrasse;Bern",
    "iso:country":"CH",
    "sg:address":"Allmendstrasse 193",
    "sg:city":"Thun",
    "sg:orig_category":"Autospenglereien",
    "sg:phone":"+41 33 222 57 00",
    "sg:postcode":"3603",
    "sg:province":"Bern",
    "wof:name":"Carrosserie Zollhaus Ag",
    "wof:placetype":"venue"
},
  "geometry": {"coordinates":[7.594287,46.762047],"type":"Point"}
}