{
  "type": "Feature",
  "properties": {
    "addr:full":"Schleifestrasse 7 M\u00e4rstetten Thurgau 8560",
    "addr:housenumber":"7",
    "addr:postcode":"8560",
    "addr:street":"Schleifestrasse;Thurgau",
    "iso:country":"CH",
    "sg:address":"Schleifestrasse 7",
    "sg:city":"M\u00e4rstetten",
    "sg:orig_category":"Bauschreinerei S\u00e4gewerke",
    "sg:phone":"+41 71 657 14 91",
    "sg:postcode":"8560",
    "sg:province":"Thurgau",
    "wof:name":"P. & M. Pupikofer Schreinerei & S\u00e4gerei",
    "wof:placetype":"venue"
},
  "geometry": {"coordinates":[9.07167,47.592346],"type":"Point"}
}