{
  "type": "Feature",
  "properties": {
    "addr:full":"Hauptstrasse H\u00f6chstetten-hells Bern 3429",
    "addr:postcode":"3429",
    "addr:street":"Hauptstrasse",
    "iso:country":"CH",
    "sg:address":"Hauptstrasse",
    "sg:city":"H\u00f6chstetten-hells",
    "sg:orig_category":"Allgemeiner Hoch U Tiefbau Hoch U Tiefbau",
    "sg:phone":"+41 33 822 40 09",
    "sg:postcode":"3429",
    "sg:province":"Bern",
    "wof:name":"Zurbuchen Samuel, Bauunternehmung",
    "wof:placetype":"venue"
},
  "geometry": {"coordinates":[7.88824,46.70171],"type":"Point"}
}