{
  "type": "Feature",
  "properties": {
    "iso:country":"CH",
    "sg:address":"Pr\u00e9-du-march\u00e9 Rue 3 1004 Lausanne. Postfach",
    "sg:city":"Lausanne",
    "sg:orig_category":"Reiseb\u00fcros U Reiseveranstalter",
    "sg:postcode":"1003",
    "sg:province":"Vaud",
    "wof:name":"J & L Voyages, Maria Helena Oliveira Agence De Voyages Etc",
    "wof:placetype":"venue"
},
  "geometry": {"coordinates":[6.6305890083,46.5233764648],"type":"Point"}
}