{
  "type": "Feature",
  "properties": {
    "iso:country":"CH",
    "sg:address":"Letzistrasse 17",
    "sg:city":"Zug",
    "sg:classifiers":[
        {
            "category":"Banks & Credit Unions",
            "subcategory":"Bureau De Change",
            "type":"Services"
        }
    ],
    "sg:phone":"+41 41 740 69 29",
    "sg:postcode":"6300",
    "sg:province":"Zug",
    "sg:tags":[
        "machine",
        "embroidery"
    ],
    "wof:name":"Cre-active Productions",
    "wof:placetype":"venue"
},
  "geometry": {"coordinates":[8.5007143021,47.1783294678],"type":"Point"}
}