{
  "type": "Feature",
  "properties": {
    "iso:country":"CH",
    "sg:address":"Route De La Chocolati\u00e8re 25",
    "sg:city":"Echandens",
    "sg:orig_category":"Instandhaltung U Reparatur von Automobilen",
    "sg:phone":"+41 79 449 22 69",
    "sg:postcode":"1026",
    "sg:province":"Vaud",
    "wof:name":"Garage Solazzo Autoreparaturwerkstatt. Neu Und Occasionswagen-handel",
    "wof:placetype":"venue"
},
  "geometry": {"coordinates":[6.5487217903,46.5396461487],"type":"Point"}
}