{
  "type": "Feature",
  "properties": {
    "addr:full":"Sous-vent Bex Vaud 1880",
    "addr:postcode":"1880",
    "iso:country":"CH",
    "sg:address":"Sous-vent",
    "sg:city":"Bex",
    "sg:classifiers":[
        {
            "category":"Bars & Pubs",
            "type":"Food & Drink"
        }
    ],
    "sg:postcode":"1880",
    "sg:province":"Vaud",
    "wof:name":"La Prairie, Mustafa",
    "wof:placetype":"venue"
},
  "geometry": {"coordinates":[7.015681,46.250259],"type":"Point"}
}