{
  "type": "Feature",
  "properties": {
    "iso:country":"CH",
    "sg:address":"Wartstrasse 29",
    "sg:city":"Winterthur",
    "sg:orig_category":"Architektur U Ingenieurb\u00fcros Architekturb\u00fcros",
    "sg:phone":"+41 52 212 22 72",
    "sg:postcode":"8400",
    "sg:province":"Z\u00fcrich",
    "wof:name":"Weber Architektur",
    "wof:placetype":"venue"
},
  "geometry": {"coordinates":[8.720726,47.501225],"type":"Point"}
}