{
  "type": "Feature",
  "properties": {
    "iso:country":"CH",
    "sg:address":"Tannacker 137",
    "sg:city":"Aetingen",
    "sg:orig_category":"Architektur U Ingenieurb\u00fcros",
    "sg:phone":"+41 41 670 00 02",
    "sg:postcode":"4587",
    "sg:province":"Solothurn",
    "wof:name":"Geotest Ag Ingenieurb\u00fcro",
    "wof:placetype":"venue"
},
  "geometry": {"coordinates":[8.265144,46.934715],"type":"Point"}
}