{
  "type": "Feature",
  "properties": {
    "iso:country":"CH",
    "sg:address":"R\u00fctihaldenstrasse 12 8956 Killwangen. Postfach",
    "sg:city":"Killwangen",
    "sg:orig_category":"Unclassifiable Establishments",
    "sg:postcode":"8956",
    "sg:province":"Aargau",
    "wof:name":"All-improve Holding Ag Beteiligungen Usw",
    "wof:placetype":"venue"
},
  "geometry": {"coordinates":[8.3484802246,47.4311943054],"type":"Point"}
}