{
  "type": "Feature",
  "properties": {
    "addr:full":"Asylweg 49 Zuchwil Solothurn 4528",
    "addr:housenumber":"49",
    "addr:postcode":"4528",
    "addr:street":"Asylweg",
    "iso:country":"CH",
    "sg:address":"Asylweg 49",
    "sg:city":"Zuchwil",
    "sg:classifiers":[
        {
            "category":"Social Services",
            "subcategory":"Retirement Home",
            "type":"Services"
        }
    ],
    "sg:phone":"+41 56 664 11 79",
    "sg:postcode":"4528",
    "sg:province":"Solothurn",
    "sg:tags":[
        "pflegeheime",
        "u",
        "alters"
    ],
    "wof:name":"St.martin Gemeindealtersheim",
    "wof:placetype":"venue"
},
  "geometry": {"coordinates":[8.317482,47.282578],"type":"Point"}
}