{
  "type": "Feature",
  "properties": {
    "iso:country":"CH",
    "sg:address":"Abendruh",
    "sg:city":"Interlaken",
    "sg:orig_category":"Wohnheime",
    "sg:phone":"+41 33 828 88 68",
    "sg:postcode":"3800",
    "sg:province":"Bern",
    "wof:name":"Verein Zentrum Artos Interlaken Der Evangelisch Methodistischen Kirche In Der Schweiz",
    "wof:placetype":"venue"
},
  "geometry": {"coordinates":[7.8534369469,46.6844787598],"type":"Point"}
}