{
  "type": "Feature",
  "properties": {
    "iso:country":"CH",
    "sg:address":"S\u00fcdstrasse 2",
    "sg:city":"Zofingen",
    "sg:orig_category":"Gartenbau",
    "sg:phone":"+41 62 752 33 12",
    "sg:postcode":"4800",
    "sg:province":"Aargau",
    "wof:name":"Hans-ulrich Klemensberger Gartenunterhalt",
    "wof:placetype":"venue"
},
  "geometry": {"coordinates":[7.9384880066,47.2797584534],"type":"Point"}
}