{
  "type": "Feature",
  "properties": {
    "iso:country":"CH",
    "sg:address":"Zenh\u00e4usernstrasse 95",
    "sg:city":"Glis",
    "sg:classifiers":[
        {
            "category":"Food & Beverages",
            "subcategory":"Specialty",
            "type":"Retail Goods"
        }
    ],
    "sg:phone":"+41 27 924 29 15",
    "sg:postcode":"3902",
    "sg:province":"Valais",
    "sg:tags":[
        "caterer"
    ],
    "wof:name":"Norbi U. Patricia Eyer Ap\u00e9ro & Partyservice",
    "wof:placetype":"venue"
},
  "geometry": {"coordinates":[7.98934,46.309471],"type":"Point"}
}