{
  "type": "Feature",
  "properties": {
    "iso:country":"CH",
    "sg:address":"1032",
    "sg:city":"Romanel-s-lausanne",
    "sg:orig_category":"Kauf U Verkauf von Immobilien auf eigene Rechnung",
    "sg:postcode":"1032",
    "sg:province":"Vaud",
    "wof:name":"Emaro Sa",
    "wof:placetype":"venue"
},
  "geometry": {"coordinates":[6.6079001427,46.5649299622],"type":"Point"}
}