{
  "type": "Feature",
  "properties": {
    "iso:country":"CH",
    "sg:address":"Dorfstrasse 1",
    "sg:city":"Udligenswil",
    "sg:orig_category":"Tierarztpraxis",
    "sg:phone":"+41 41 371 10 20",
    "sg:postcode":"6044",
    "sg:province":"Luzern",
    "wof:name":"Dres Landerer & Azzilonna Tier\u00e4rzte",
    "wof:placetype":"venue"
},
  "geometry": {"coordinates":[8.4008617401,47.0903968811],"type":"Point"}
}