{
  "type": "Feature",
  "properties": {
    "iso:country":"CH",
    "sg:address":"Lindenstrasse 33",
    "sg:city":"Binningen",
    "sg:orig_category":"Herstellung von B\u00fcro U Ladenm\u00f6beln",
    "sg:phone":"+41 34 402 66 06",
    "sg:postcode":"4102",
    "sg:province":"Basel-Landschaft",
    "wof:name":"Liechti Ladenbau Ag",
    "wof:placetype":"venue"
},
  "geometry": {"coordinates":[7.757589817,46.9491271973],"type":"Point"}
}