{
  "type": "Feature",
  "properties": {
    "iso:country":"CH",
    "sg:address":"Gewerbezentrum Holenstein",
    "sg:city":"Glarus",
    "sg:orig_category":"Allgemeiner Hoch U Tiefbau Bauingenieurb\u00fcros Hochbau",
    "sg:phone":"+41 55 650 15 07",
    "sg:postcode":"8750",
    "sg:province":"Glarus",
    "wof:name":"Ingenieurb\u00fcro Htl Graber Christian",
    "wof:placetype":"venue"
},
  "geometry": {"coordinates":[9.06809,47.03997],"type":"Point"}
}