{
  "type": "Feature",
  "properties": {
    "addr:full":"Bahnhofstrasse 14 Landquart Graubunden 7302",
    "addr:housenumber":"14",
    "addr:postcode":"7302",
    "addr:street":"Bahnhofstrasse",
    "iso:country":"CH",
    "sg:address":"Bahnhofstrasse 14",
    "sg:city":"Landquart",
    "sg:orig_category":"B\u00e4ckereien Konditoreien",
    "sg:phone":"+41 81 330 88 80",
    "sg:postcode":"7302",
    "sg:province":"Graubunden",
    "wof:name":"Arthur B\u00fchler Zuckerb\u00e4ckerei",
    "wof:placetype":"venue"
},
  "geometry": {"coordinates":[9.556381,46.96751],"type":"Point"}
}