{
  "type": "Feature",
  "properties": {
    "iso:country":"CH",
    "sg:address":"Im Wigarten 25",
    "sg:city":"Pratteln",
    "sg:orig_category":"Unternehmensberatung Wirtschaftspr\u00fcfung, Steuerberatung U Treuhand",
    "sg:phone":"+41 61 933 04 04",
    "sg:postcode":"4133",
    "sg:province":"Basel-Landschaft",
    "wof:name":"Stopp Gmbh Treuhand & Consulting Dienstl. In D. Bereichen Buchf\u00fchrung, Revisionen, Verm\u00f6gensverwaltung Usw",
    "wof:placetype":"venue"
},
  "geometry": {"coordinates":[7.6930260658,47.5163002014],"type":"Point"}
}