{
  "type": "Feature",
  "properties": {
    "iso:country":"CH",
    "sg:address":"Le Devin Case Postale 262",
    "sg:city":"Moudon",
    "sg:classifiers":[
        {
            "category":"Manufacturing",
            "subcategory":"Paper Products",
            "type":"Manufacturing & Wholesale Goods"
        }
    ],
    "sg:phone":"+41 21 905 85 00",
    "sg:postcode":"1510",
    "sg:province":"Vaud",
    "sg:tags":[
        "packaging",
        "material",
        "-",
        "cardboard"
    ],
    "wof:name":"Model Emballages Sa",
    "wof:placetype":"venue"
},
  "geometry": {"coordinates":[5.4362101555,45.7594604492],"type":"Point"}
}