{
  "type": "Feature",
  "properties": {
    "iso:country":"CH",
    "sg:address":"Mittlere Gasse 7",
    "sg:city":"Baden",
    "sg:orig_category":"Detailhandel mit Blumen U Pflanzen",
    "sg:phone":"+41 56 221 70 15",
    "sg:postcode":"5400",
    "sg:province":"Aargau",
    "wof:name":"Verena Floristik",
    "wof:placetype":"venue"
},
  "geometry": {"coordinates":[8.306958,47.472527],"type":"Point"}
}