{
  "type": "Feature",
  "properties": {
    "iso:country":"CH",
    "sg:address":"H\u00f6henstrasse 45",
    "sg:city":"Wallisellen",
    "sg:orig_category":"Sonstiger Grosshandel",
    "sg:postcode":"8304",
    "sg:province":"Z\u00fcrich",
    "wof:name":"Kawi-handel Katharina Kn\u00fcsel",
    "wof:placetype":"venue"
},
  "geometry": {"coordinates":[8.5879449844,47.4206237793],"type":"Point"}
}