{
  "type": "Feature",
  "properties": {
    "iso:country":"CH",
    "sg:address":"Z\u00e4hringerstrasse 33-35 8001 Z\u00fcrich. Postfach",
    "sg:city":"Z\u00fcrich",
    "sg:classifiers":[
        {
            "category":"Bars & Pubs",
            "type":"Food & Drink"
        }
    ],
    "sg:phone":"+41 12514656",
    "sg:postcode":"8025",
    "wof:name":"Bar Carrousel",
    "wof:placetype":"venue"
},
  "geometry": {"coordinates":[8.544402,47.375694],"type":"Point"}
}