{
  "type": "Feature",
  "properties": {
    "iso:country":"CH",
    "sg:address":"Rue Du Rh\u00f4ne 6",
    "sg:city":"Gen\u00e8ve",
    "sg:orig_category":"Detailhandel mit Damenbekleidung",
    "sg:phone":"+41 22 311 65 84",
    "sg:postcode":"1204",
    "sg:province":"Gen\u00e8ve",
    "wof:name":"La Maison Du Tricot Sa Confection Dames",
    "wof:placetype":"venue"
},
  "geometry": {"coordinates":[6.144515,46.204361],"type":"Point"}
}