{
  "type": "Feature",
  "properties": {
    "iso:country":"CH",
    "sg:address":"Sch\u00fctzengraben 24",
    "sg:city":"Schaffhausen",
    "sg:orig_category":"Sonstiges Versicherungsgewerbe",
    "sg:postcode":"8200",
    "sg:province":"Schaffhausen",
    "wof:name":"Generalagentur Urs Z\u00fcst Allianz Suisse",
    "wof:placetype":"venue"
},
  "geometry": {"coordinates":[8.6354541779,47.6989479065],"type":"Point"}
}