{
  "type": "Feature",
  "properties": {
    "iso:country":"CH",
    "sg:address":"Wilhelm-kutter-weg 2",
    "sg:city":"Biel/bienne",
    "sg:orig_category":"Mechanische Werkst\u00e4tten",
    "sg:phone":"+41 32 365 48 85",
    "sg:postcode":"2503",
    "sg:province":"Bern",
    "wof:name":"Claude Bianchi Mechanische Werkst\u00e4tte",
    "wof:placetype":"venue"
},
  "geometry": {"coordinates":[7.2536320686,47.1278305054],"type":"Point"}
}