{
  "type": "Feature",
  "properties": {
    "iso:country":"CH",
    "sg:address":"1428",
    "sg:city":"Provence",
    "sg:orig_category":"Primarschulen",
    "sg:postcode":"1428",
    "sg:province":"Vaud",
    "wof:name":"Ecole Primaire",
    "wof:placetype":"venue"
},
  "geometry": {"coordinates":[6.7277708054,46.8915061951],"type":"Point"}
}