{
  "type": "Feature",
  "properties": {
    "addr:full":"Marktgasse 20 6340 Baar. Postfach Baar Zug 6340",
    "addr:housenumber":"20",
    "addr:postcode":"6340 baar. postfach;6340",
    "addr:street":"Marktgasse;Zug",
    "iso:country":"CH",
    "sg:address":"Marktgasse 20 6340 Baar. Postfach",
    "sg:city":"Baar",
    "sg:orig_category":"Detailhandel mit Blumen U Pflanzen Fachdetailhandel in Verkaufsr\u00e4umen",
    "sg:phone":"+41 41 763 17 77",
    "sg:postcode":"6340",
    "sg:province":"Zug",
    "wof:name":"Ceccon Blumen Design",
    "wof:placetype":"venue"
},
  "geometry": {"coordinates":[8.528342,47.19606],"type":"Point"}
}