{
  "type": "Feature",
  "properties": {
    "iso:country":"CH",
    "sg:address":"1484",
    "sg:city":"Aumont",
    "sg:orig_category":"Vermietung U Verpachtung von eigenen Immobilien",
    "sg:phone":"+41 79 219 08 31",
    "sg:postcode":"1484",
    "sg:province":"Fribourg",
    "wof:name":"Scobi S\u00e0rl",
    "wof:placetype":"venue"
},
  "geometry": {"coordinates":[6.8496398926,46.8000106812],"type":"Point"}
}