{
  "type": "Feature",
  "properties": {
    "iso:country":"CH",
    "sg:address":"Bahnhofplatz 1a",
    "sg:city":"St.gallen",
    "sg:orig_category":"Non-Classified Establishments",
    "sg:postcode":"9000",
    "sg:province":"St. Gallen",
    "wof:name":"Schweizerische Text Akademie",
    "wof:placetype":"venue"
},
  "geometry": {"coordinates":[9.8309297562,46.8005867004],"type":"Point"}
}