{
  "type": "Feature",
  "properties": {
    "addr:full":"M\u00e4ttenbergstrasse 6 Th\u00f6rigen Bern 3367",
    "addr:housenumber":"6",
    "addr:postcode":"3367",
    "addr:street":"Maettenbergstrasse",
    "iso:country":"CH",
    "sg:address":"M\u00e4ttenbergstrasse 6",
    "sg:city":"Th\u00f6rigen",
    "sg:orig_category":"Bauschreinerei Herstellung von Konstruktionsteilen, Fertigbauteilen U Ausbauelementen aus Holz",
    "sg:phone":"+41 24 498 13 87",
    "sg:postcode":"3367",
    "sg:province":"Bern",
    "wof:name":"Christian Mazzucco Sa Menuiserie & Charpente",
    "wof:placetype":"venue"
},
  "geometry": {"coordinates":[7.090122,46.255051],"type":"Point"}
}