{
  "type": "Feature",
  "properties": {
    "iso:country":"CH",
    "sg:address":"Beethovenstrasse 7 8002 Z\u00fcrich. Postfach",
    "sg:city":"Z\u00fcrich",
    "sg:orig_category":"Non-Classified Establishments",
    "sg:postcode":"8001",
    "sg:province":"Z\u00fcrich",
    "wof:name":"Gibbs & Soell (schweiz) Gmbh \u00d6ffentlichkeitsarbeit. Werbe- U. Reklamet\u00e4tigkeit",
    "wof:placetype":"venue"
},
  "geometry": {"coordinates":[8.5372142792,47.3653411865],"type":"Point"}
}