{
  "type": "Feature",
  "properties": {
    "iso:country":"CH",
    "sg:address":"H\u00f6henweg 20",
    "sg:city":"Z\u00fcrich",
    "sg:orig_category":"Non-Classified Establishments",
    "sg:postcode":"8032",
    "sg:province":"Z\u00fcrich",
    "wof:name":"Tina Schulz Psychotherapie",
    "wof:placetype":"venue"
},
  "geometry": {"coordinates":[8.5683422089,47.3634529114],"type":"Point"}
}