{
  "type": "Feature",
  "properties": {
    "addr:full":"Route De Veyrier 263 Veyrier Gen\u00e8ve 1255",
    "addr:housenumber":"263",
    "addr:postcode":"1255",
    "addr:street":"Route De Veyrier",
    "iso:country":"CH",
    "sg:address":"Route De Veyrier 263",
    "sg:city":"Veyrier",
    "sg:orig_category":"Autogaragen",
    "sg:phone":"+41 22 784 20 11",
    "sg:postcode":"1255",
    "sg:province":"Gen\u00e8ve",
    "wof:name":"Jean Mauron Garage De Veyrier",
    "wof:placetype":"venue"
},
  "geometry": {"coordinates":[6.183793,46.16769],"type":"Point"}
}