{
  "type": "Feature",
  "properties": {
    "iso:country":"CH",
    "sg:address":"Rue De La Gare 28",
    "sg:city":"Aigle",
    "sg:classifiers":[
        {
            "category":"Travel",
            "subcategory":"Hotels & Motels",
            "type":"Entertainment"
        }
    ],
    "sg:phone":"+41 22 732 66 30",
    "sg:postcode":"1860",
    "sg:province":"Vaud",
    "sg:tags":[
        "hotels",
        "mit",
        "restaurant"
    ],
    "wof:name":"H\u00f4tel Suisse, Gen\u00e8ve, Sa",
    "wof:placetype":"venue"
},
  "geometry": {"coordinates":[6.1430940628,46.2093963623],"type":"Point"}
}