{
  "type": "Feature",
  "properties": {
    "iso:country":"CH",
    "sg:address":"L'evitaz",
    "sg:city":"Ch\u00e2teau-d'oex",
    "sg:orig_category":"Verwertung von Milch",
    "sg:phone":"+41 27 785 10 40",
    "sg:postcode":"1837",
    "wof:name":"Coop\u00e9rative Laiti\u00e8re Voll\u00e8ges-sembrancher-levron",
    "wof:placetype":"venue"
},
  "geometry": {"coordinates":[7.1772699356,46.0913352966],"type":"Point"}
}