{
  "type": "Feature",
  "properties": {
    "iso:country":"CH",
    "sg:address":"Burgerstrasse 35",
    "sg:city":"Luzern",
    "sg:classifiers":[
        {
            "category":"Travel",
            "subcategory":"Hotels & Motels",
            "type":"Entertainment"
        }
    ],
    "sg:postcode":"6003",
    "sg:province":"Luzern",
    "sg:tags":[
        "hotels",
        "mit",
        "restaurant"
    ],
    "wof:name":"Amrein Ren\u00e9",
    "wof:placetype":"venue"
},
  "geometry": {"coordinates":[8.3030319214,47.0490379333],"type":"Point"}
}