{
  "type": "Feature",
  "properties": {
    "iso:country":"CH",
    "sg:address":"Reussquai 1",
    "sg:city":"Emmen",
    "sg:orig_category":"Detailhandel mit Beleuchtungs U Haushaltsgegenst\u00e4nden Detailhandel mit elektrischen Haushalts, Radio",
    "sg:phone":"+41 41 260 52 25",
    "sg:postcode":"6032",
    "sg:province":"Luzern",
    "wof:name":"Markus Koller Haushaltger\u00e4te",
    "wof:placetype":"venue"
},
  "geometry": {"coordinates":[8.30902,47.081234],"type":"Point"}
}