{
  "type": "Feature",
  "properties": {
    "iso:country":"CH",
    "sg:address":"Welschd\u00f6rfli 2",
    "sg:city":"Chur",
    "sg:orig_category":"Diskotheken, Dancings, Night Clubs",
    "sg:phone":"+41 81 253 05 11",
    "sg:postcode":"7000",
    "sg:province":"Graubunden",
    "wof:name":"Discothek Halli Galli Gmbh",
    "wof:placetype":"venue"
},
  "geometry": {"coordinates":[9.5289554596,46.8477859497],"type":"Point"}
}