{
  "type": "Feature",
  "properties": {
    "iso:country":"CH",
    "sg:address":"Schw\u00e4ndi",
    "sg:city":"Vorderthal",
    "sg:orig_category":"Zimmerei, Dachdeckerei, Bauspenglerei U Abdichtung",
    "sg:phone":"+41 55 446 14 52",
    "sg:postcode":"8857",
    "sg:province":"Schwyz",
    "wof:name":"Bruhin Karl, Holzbau & Planungen",
    "wof:placetype":"venue"
},
  "geometry": {"coordinates":[8.8958377838,47.134765625],"type":"Point"}
}