{
  "type": "Feature",
  "properties": {
    "iso:country":"CH",
    "sg:address":"Grundstrasse 14",
    "sg:city":"Risch",
    "sg:orig_category":"Geb\u00e4ude, Wohnungsreinigung Reinigungsgewerbe",
    "sg:phone":"+41 71 277 82 01",
    "sg:postcode":"6343",
    "sg:province":"Zug",
    "wof:name":"Pronto-reinigung Ag",
    "wof:placetype":"venue"
},
  "geometry": {"coordinates":[9.5497522354,47.453414917],"type":"Point"}
}