{
  "type": "Feature",
  "properties": {
    "iso:country":"CH",
    "sg:address":"Burggartenstrasse 17",
    "sg:city":"Pratteln",
    "sg:orig_category":"Unclassifiable Establishments",
    "sg:phone":"+41 61 823 17 01",
    "sg:postcode":"4133",
    "sg:province":"Basel-Landschaft",
    "wof:name":"Pub Fourteen Andrejic",
    "wof:placetype":"venue"
},
  "geometry": {"coordinates":[7.6934947968,47.5209388733],"type":"Point"}
}