{
  "type": "Feature",
  "properties": {
    "iso:country":"CH",
    "sg:address":"Wiler Strasse 37",
    "sg:city":"Schwarzenbach",
    "sg:classifiers":[
        {
            "category":"Home & Garden",
            "subcategory":"Building Materials",
            "type":"Retail Goods"
        }
    ],
    "sg:phone":"+41 71 923 39 39",
    "sg:postcode":"9536",
    "sg:province":"St. Gallen",
    "sg:tags":[
        "garage",
        "door"
    ],
    "wof:name":"Peter Bauelemente Ag",
    "wof:placetype":"venue"
},
  "geometry": {"coordinates":[9.0735054016,47.4428825378],"type":"Point"}
}