{
  "type": "Feature",
  "properties": {
    "iso:country":"CH",
    "sg:address":"Rue Des Alpes 1",
    "sg:city":"Martigny",
    "sg:orig_category":"Architektur U Ingenieurb\u00fcros Architekturb\u00fcros",
    "sg:phone":"+41 27 722 31 16",
    "sg:postcode":"1920",
    "sg:province":"Valais",
    "wof:name":"Atelier D'architecture Coquoz Sa",
    "wof:placetype":"venue"
},
  "geometry": {"coordinates":[7.074673,46.100349],"type":"Point"}
}