{
  "type": "Feature",
  "properties": {
    "addr:full":"R\u00fcmlangstrasse 91 Z\u00fcrich Z\u00fcrich 8052",
    "addr:housenumber":"91",
    "addr:postcode":"8052",
    "addr:street":"Ruemlangstrasse",
    "iso:country":"CH",
    "sg:address":"R\u00fcmlangstrasse 91",
    "sg:city":"Z\u00fcrich",
    "sg:classifiers":[
        {
            "category":"Social Services",
            "subcategory":"Child Care",
            "type":"Services"
        }
    ],
    "sg:phone":"+41 13014060",
    "sg:postcode":"8052",
    "sg:province":"Z\u00fcrich",
    "sg:tags":[
        "broaching"
    ],
    "wof:name":"Okey Ag",
    "wof:placetype":"venue"
},
  "geometry": {"coordinates":[8.53995,47.430847],"type":"Point"}
}