{
  "type": "Feature",
  "properties": {
    "iso:country":"CH",
    "sg:address":"B\u00e4renstutz 7",
    "sg:city":"M\u00fcnsingen",
    "sg:orig_category":"Allgemeiner Gartenbau Gartenbau",
    "sg:phone":"+41 31 721 14 20",
    "sg:postcode":"3110",
    "sg:province":"Bern",
    "wof:name":"Johann Georg Daepp Baumschule",
    "wof:placetype":"venue"
},
  "geometry": {"coordinates":[7.563206,46.880054],"type":"Point"}
}