{
  "type": "Feature",
  "properties": {
    "iso:country":"CH",
    "sg:address":"Kanalweg 6",
    "sg:city":"Uster",
    "sg:orig_category":"Datenverarbeitungsdienste Softwareentwicklung U beratung",
    "sg:phone":"+41 19944701",
    "sg:postcode":"8610",
    "sg:province":"Z\u00fcrich",
    "wof:name":"Edix Informatik Meisterhans G.",
    "wof:placetype":"venue"
},
  "geometry": {"coordinates":[8.72678,47.345798],"type":"Point"}
}