{
  "type": "Feature",
  "properties": {
    "iso:country":"CH",
    "sg:address":"Marktstrasse 18a",
    "sg:city":"Muotathal",
    "sg:orig_category":"Malerei",
    "sg:phone":"+41 41 830 15 33",
    "sg:postcode":"6436",
    "sg:province":"Schwyz",
    "wof:name":"Ren\u00e9 Betschart Maler Betschart",
    "wof:placetype":"venue"
},
  "geometry": {"coordinates":[8.7605772018,46.9743156433],"type":"Point"}
}