{
  "type": "Feature",
  "properties": {
    "iso:country":"CH",
    "sg:address":"Route De La Capite 20",
    "sg:city":"Cologny",
    "sg:orig_category":"Grosshandel mit Nahrungsmitteln, Getr\u00e4nken U Tabakwaren ohne ausgepr\u00e4gten Schwerpunkt",
    "sg:phone":"+41 22 735 00 52",
    "sg:postcode":"1223",
    "sg:province":"Gen\u00e8ve",
    "wof:name":"Bozzo Luigi",
    "wof:placetype":"venue"
},
  "geometry": {"coordinates":[6.1829810143,46.2171630859],"type":"Point"}
}