{
  "type": "Feature",
  "properties": {
    "iso:country":"CH",
    "sg:address":"3934",
    "sg:city":"Zeneggen",
    "sg:orig_category":"Primarschulen",
    "sg:postcode":"3934",
    "sg:province":"Valais",
    "wof:name":"Primarschule",
    "wof:placetype":"venue"
},
  "geometry": {"coordinates":[7.8664097786,46.2730064392],"type":"Point"}
}