{
  "type": "Feature",
  "properties": {
    "iso:country":"CH",
    "sg:address":"Winkelstrasse 2",
    "sg:city":"Bannwil",
    "sg:orig_category":"Gemeindeverwaltungen",
    "sg:phone":"+41 52 653 13 82",
    "sg:postcode":"4913",
    "sg:province":"Bern",
    "wof:name":"Gemeindeverwaltung Bargen",
    "wof:placetype":"venue"
},
  "geometry": {"coordinates":[8.6124200821,47.7928199768],"type":"Point"}
}