{
  "type": "Feature",
  "properties": {
    "iso:country":"CH",
    "sg:address":"Buechschwendistrasse 5",
    "sg:city":"Rehetobel",
    "sg:orig_category":"Detailhandel mit Musikinstrumenten Detailhandel mit elektrischen Haushalts-,Radio U Fernsehger\u00e4ten s",
    "sg:phone":"+41 71 877 31 31",
    "sg:postcode":"9038",
    "sg:province":"Appenzell Ausserrhoden",
    "wof:name":"Etter Music P.a.fachgesch\u00e4ft",
    "wof:placetype":"venue"
},
  "geometry": {"coordinates":[9.48117733,47.4239311218],"type":"Point"}
}