{
  "type": "Feature",
  "properties": {
    "addr:full":"Corso San Gottardo 72 Chiasso Ticino 6830",
    "addr:housenumber":"72",
    "addr:postcode":"6830",
    "addr:street":"Corso San Gottardo;Ticino",
    "iso:country":"CH",
    "sg:address":"Corso San Gottardo 72",
    "sg:city":"Chiasso",
    "sg:orig_category":"Allgemeiner Hoch U Tiefbau",
    "sg:postcode":"6830",
    "sg:province":"Ticino",
    "wof:name":"Edilpass Sa",
    "wof:placetype":"venue"
},
  "geometry": {"coordinates":[9.026975,45.835766],"type":"Point"}
}