{
  "type": "Feature",
  "properties": {
    "iso:country":"CH",
    "sg:address":"Route De Duillier 24a",
    "sg:city":"Nyon",
    "sg:orig_category":"Schnelldruck U Kopierservice",
    "sg:phone":"+41 22 994 74 88",
    "sg:postcode":"1260",
    "sg:province":"Vaud",
    "wof:name":"Scan Graphic Solutions Pr\u00e9-presse Sa",
    "wof:placetype":"venue"
},
  "geometry": {"coordinates":[6.2361559868,46.3950691223],"type":"Point"}
}