{
  "type": "Feature",
  "properties": {
    "iso:country":"CH",
    "sg:address":"Reutlingerstrasse 17",
    "sg:city":"Winterthur",
    "sg:orig_category":"Grosshandel mit sonstigen Maschinen U Ausr\u00fcstungen f\u00fcr Industrie, Handel U Schiffahrt",
    "sg:phone":"+41 52 243 00 70",
    "sg:postcode":"8404",
    "sg:province":"Z\u00fcrich",
    "wof:name":"G\u00fcrtler Ag",
    "wof:placetype":"venue"
},
  "geometry": {"coordinates":[8.7558240891,47.5231552124],"type":"Point"}
}