{
  "type": "Feature",
  "properties": {
    "iso:country":"CH",
    "sg:address":"Im R\u00f6tel 20h",
    "sg:city":"Zug",
    "sg:orig_category":"Sportvereine Wassersport",
    "sg:phone":"+41 41 725 22 22",
    "sg:postcode":"6300",
    "sg:province":"Zug",
    "wof:name":"See-club Zug",
    "wof:placetype":"venue"
},
  "geometry": {"coordinates":[8.5263795853,47.166229248],"type":"Point"}
}