{
  "type": "Feature",
  "properties": {
    "iso:country":"CH",
    "sg:address":"Jurastrasse 12",
    "sg:city":"Unterentfelden",
    "sg:orig_category":"Fachdetailhandel mit pharmazeutischen Produkten",
    "sg:phone":"+41 800 300 001",
    "sg:postcode":"5035",
    "sg:province":"Aargau",
    "wof:name":"Linden-apotheke Dr. A. Brunner",
    "wof:placetype":"venue"
},
  "geometry": {"coordinates":[8.0434827805,47.3680915833],"type":"Point"}
}