{
  "type": "Feature",
  "properties": {
    "iso:country":"CH",
    "sg:address":"Hofgutweg 1a",
    "sg:city":"Burgdorf",
    "sg:orig_category":"Vereine Gesang",
    "sg:phone":"+41 34 422 16 37",
    "sg:postcode":"3400",
    "sg:province":"Bern",
    "wof:name":"M\u00e4nnerchor S\u00e4ngerbund",
    "wof:placetype":"venue"
},
  "geometry": {"coordinates":[7.6224131584,47.0508728027],"type":"Point"}
}