{
  "type": "Feature",
  "properties": {
    "iso:country":"CH",
    "sg:address":"Route Des Flumeaux 2 1008 Jouxtens-m\u00e9zery Case Postale 261",
    "sg:city":"Jouxtens-m\u00e9zery",
    "sg:orig_category":"Landesverteidigung, Sozialversicherung \u00d6ffentliche Verwaltung",
    "sg:phone":"+41 21 634 38 46",
    "sg:postcode":"1008",
    "sg:province":"Vaud",
    "wof:name":"Protection Civile R\u00e9gion Lausanne-nord",
    "wof:placetype":"venue"
},
  "geometry": {"coordinates":[6.6061439514,46.5340614319],"type":"Point"}
}