{
  "type": "Feature",
  "properties": {
    "iso:country":"CH",
    "sg:address":"Dauphin\u00e9 Rue Du 16",
    "sg:city":"Gen\u00e8ve",
    "sg:orig_category":"Grosshandel mit sonstigen Nahrungsmitteln",
    "sg:phone":"+41 22 309 40 40",
    "sg:postcode":"1203",
    "sg:province":"Gen\u00e8ve",
    "wof:name":"Lucas Gen\u00e8ve Sa",
    "wof:placetype":"venue"
},
  "geometry": {"coordinates":[6.1245188713,46.2105979919],"type":"Point"}
}