{
  "type": "Feature",
  "properties": {
    "iso:country":"CH",
    "sg:address":"Klosterstrasse 26 8406 Winterthur. Postfach 198",
    "sg:city":"Winterthur",
    "sg:orig_category":"Herstellung von Werkzeugmaschinen Mechanische Werkst\u00e4tten",
    "sg:phone":"+41 52 208 81 00",
    "sg:postcode":"8406",
    "sg:province":"Z\u00fcrich",
    "wof:name":"Netech Neeser Technik Ag",
    "wof:placetype":"venue"
},
  "geometry": {"coordinates":[8.7071075439,47.487953186],"type":"Point"}
}