{
  "type": "Feature",
  "properties": {
    "iso:country":"CH",
    "sg:address":"Sonnenberg-n",
    "sg:city":"Niederhelfenschwil",
    "sg:orig_category":"Grosshandel mit lebenden Tieren",
    "sg:phone":"+41 71 393 40 10",
    "sg:postcode":"9527",
    "sg:province":"St. Gallen",
    "wof:name":"Kurt & Iris Koller Viehhandel",
    "wof:placetype":"venue"
},
  "geometry": {"coordinates":[9.2117004395,47.4424667358],"type":"Point"}
}