{
  "type": "Feature",
  "properties": {
    "iso:country":"CH",
    "sg:address":"Bernstrasse 189 4852 Rothrist. Postfach",
    "sg:city":"Rothrist",
    "sg:orig_category":"Regionalbanken U Sparkassen",
    "sg:phone":"+41 62 785 88 88",
    "sg:postcode":"4852",
    "sg:province":"Aargau",
    "wof:name":"Neue Aargauer Bank",
    "wof:placetype":"venue"
},
  "geometry": {"coordinates":[7.8774271011,47.3053741455],"type":"Point"}
}