{
  "type": "Feature",
  "properties": {
    "iso:country":"CH",
    "sg:address":"Bahnhofstrasse 27",
    "sg:city":"Visp",
    "sg:orig_category":"Zahntechnische Laboratorien",
    "sg:phone":"+41 27 946 57 42",
    "sg:postcode":"3930",
    "sg:province":"Valais",
    "wof:name":"Bruno Leiggener Zahntechnisches Labor",
    "wof:placetype":"venue"
},
  "geometry": {"coordinates":[7.8814578056,46.2914009094],"type":"Point"}
}