{
  "type": "Feature",
  "properties": {
    "iso:country":"CH",
    "sg:address":"Selnaustrasse 13",
    "sg:city":"Z\u00fcrich",
    "sg:orig_category":"RESTAURANTS: TEA-ROOMS",
    "sg:phone":"+41 12026636",
    "sg:postcode":"8002",
    "sg:province":"Z\u00fcrich",
    "wof:name":"Tong's Thai Take Away, Inh. Maag Wanpen",
    "wof:placetype":"venue"
},
  "geometry": {"coordinates":[8.5322256088,47.370300293],"type":"Point"}
}