{
  "type": "Feature",
  "properties": {
    "iso:country":"CH",
    "sg:address":"Gros-bellet 14",
    "sg:city":"Monthey",
    "sg:orig_category":"Detailhandel mit Waren verschiedener Art, Hauptrichtung Nahrungsmittel",
    "sg:phone":"+41 24 471 80 65",
    "sg:postcode":"1870",
    "sg:province":"Valais",
    "wof:name":"Panchard J\u00e9r\u00f4me",
    "wof:placetype":"venue"
},
  "geometry": {"coordinates":[6.9426932335,46.2508811951],"type":"Point"}
}