{
  "type": "Feature",
  "properties": {
    "iso:country":"CH",
    "sg:address":"Schaufelgasse 28",
    "sg:city":"M\u00f6hlin",
    "sg:orig_category":"Veterin\u00e4rwesen",
    "sg:phone":"+41 61 851 10 25",
    "sg:postcode":"4313",
    "sg:province":"Aargau",
    "wof:name":"Tierklinik Am Sonnenberg Ag Verwaltung",
    "wof:placetype":"venue"
},
  "geometry": {"coordinates":[7.8534460068,47.55027771],"type":"Point"}
}