{
  "type": "Feature",
  "properties": {
    "iso:country":"CH",
    "sg:address":"Winkelriedstrasse 35",
    "sg:city":"Luzern",
    "sg:orig_category":"Berufliche Weiterbildung, Erwachsenenbildung",
    "sg:phone":"+41 41 228 52 52",
    "sg:postcode":"6002",
    "sg:province":"Luzern",
    "wof:name":"Berufs Und Studienberatung Kanton Luzern Bildungsinformationszentrum",
    "wof:placetype":"venue"
},
  "geometry": {"coordinates":[8.306777,47.047245],"type":"Point"}
}