{
  "type": "Feature",
  "properties": {
    "iso:country":"CH",
    "sg:address":"Binzm\u00fchlestrasse 11 8050 Z\u00fcrich. Postfach",
    "sg:city":"Z\u00fcrich",
    "sg:orig_category":"Br\u00fccken U Tunnelbau Strassenbau",
    "sg:phone":"+41 71 314 60 20",
    "sg:postcode":"8050",
    "sg:province":"Z\u00fcrich",
    "wof:name":"Batigroup Ag",
    "wof:placetype":"venue"
},
  "geometry": {"coordinates":[9.358758,47.414528],"type":"Point"}
}