{
  "type": "Feature",
  "properties": {
    "iso:country":"CH",
    "sg:address":"Via Roncaglia 7",
    "sg:city":"Novazzano",
    "sg:orig_category":"Einzelhandel mit Automobilteilen U Zubeh\u00f6r Herstellung von Bereifungen",
    "sg:phone":"+41 91 606 64 34",
    "sg:postcode":"6883",
    "sg:province":"Ticino",
    "wof:name":"M.t.ticino Reifen Sa",
    "wof:placetype":"venue"
},
  "geometry": {"coordinates":[8.9948797226,45.8395805359],"type":"Point"}
}