{
  "type": "Feature",
  "properties": {
    "iso:country":"CH",
    "sg:address":"Bachstrasse 16",
    "sg:city":"Zuckenriet",
    "sg:orig_category":"\u00dcbersetzungsb\u00fcros",
    "sg:phone":"+41 71 947 10 47",
    "sg:postcode":"9526",
    "sg:province":"St. Gallen",
    "wof:name":"Cornelia Schudel Uebersetzungen",
    "wof:placetype":"venue"
},
  "geometry": {"coordinates":[9.1594343185,47.4825325012],"type":"Point"}
}