{
  "type": "Feature",
  "properties": {
    "addr:full":"Burggraben 16 St.gallen St. Gallen 9000",
    "addr:housenumber":"16",
    "addr:postcode":"9000",
    "addr:street":"Burggraben",
    "iso:country":"CH",
    "sg:address":"Burggraben 16",
    "sg:city":"St.gallen",
    "sg:orig_category":"Architektur U Ingenieurb\u00fcros",
    "sg:phone":"+41 71 227 30 10",
    "sg:postcode":"9000",
    "sg:province":"St. Gallen",
    "wof:name":"Senn Bpm Ag",
    "wof:placetype":"venue"
},
  "geometry": {"coordinates":[9.378877,47.425411],"type":"Point"}
}