{
  "type": "Feature",
  "properties": {
    "iso:country":"CH",
    "sg:address":"Elvezia Corso 25",
    "sg:city":"Neggio",
    "sg:orig_category":"Elektroinstallation",
    "sg:phone":"+41 91 606 26 81",
    "sg:postcode":"6991",
    "sg:province":"Ticino",
    "wof:name":"Notari Angelo Sa",
    "wof:placetype":"venue"
},
  "geometry": {"coordinates":[8.8799104691,45.9871788025],"type":"Point"}
}