{
  "type": "Feature",
  "properties": {
    "iso:country":"CH",
    "sg:address":"Hauptstrasse 145",
    "sg:city":"T\u00e4gerwilen",
    "sg:orig_category":"Grosshandel mit Datenverarbeitungsger\u00e4ten Grosshandel mit Software",
    "sg:postcode":"8274",
    "sg:province":"Thurgau",
    "wof:name":"M3-software & Consulting Ag",
    "wof:placetype":"venue"
},
  "geometry": {"coordinates":[8.7852144241,47.2013130188],"type":"Point"}
}