{
  "type": "Feature",
  "properties": {
    "iso:country":"CH",
    "sg:address":"Gubelstrasse 22 6300 Zug. Postfach 574",
    "sg:city":"Zug",
    "sg:orig_category":"Elektro- and elektronische Maschinen Grosshandel Maschinen and Apparate divers Grosshandel",
    "sg:phone":"+41 62 834 07 07",
    "sg:postcode":"6301",
    "sg:province":"Zug",
    "wof:name":"Siemens Building Technologies (schweiz) Ag Landis & Staefa Division",
    "wof:placetype":"venue"
},
  "geometry": {"coordinates":[8.0812358856,47.4020767212],"type":"Point"}
}