{
  "type": "Feature",
  "properties": {
    "iso:country":"CH",
    "sg:address":"Rue De La Chaumont 14",
    "sg:city":"Porrentruy",
    "sg:orig_category":"Nationale Postdienste",
    "sg:phone":"+41 27 328 96 11",
    "sg:postcode":"2900",
    "sg:province":"Jura",
    "wof:name":"La Poste Suisse Sion 1",
    "wof:placetype":"venue"
},
  "geometry": {"coordinates":[7.3585290909,46.2292175293],"type":"Point"}
}