{
  "type": "Feature",
  "properties": {
    "iso:country":"CH",
    "sg:address":"Juraweg 45",
    "sg:city":"Rothrist",
    "sg:orig_category":"Herstellung von sonstigen chemischen Erzeugnissen Herstellung von sonstigen organischen Grundstoffen",
    "sg:phone":"+41 62 785 80 30",
    "sg:postcode":"4852",
    "sg:province":"Aargau",
    "wof:name":"Sch\u00e4rer & Schl\u00e4pfer Chemische Fabrik Ag",
    "wof:placetype":"venue"
},
  "geometry": {"coordinates":[7.8729701042,47.3065452576],"type":"Point"}
}