{
  "type": "Feature",
  "properties": {
    "iso:country":"CH",
    "sg:address":"Bahnhofstrasse 3",
    "sg:city":"Widnau",
    "sg:orig_category":"Wirtschaftspr\u00fcfung, Steuerberatung U Treuhand",
    "sg:phone":"+41 71 720 15 05",
    "sg:postcode":"9443",
    "sg:province":"St. Gallen",
    "wof:name":"Activa Treuhand + Consulting Gmbh",
    "wof:placetype":"venue"
},
  "geometry": {"coordinates":[9.6293144226,47.4079322815],"type":"Point"}
}