{
  "type": "Feature",
  "properties": {
    "iso:country":"CH",
    "sg:address":"Via Pretorio 9",
    "sg:city":"Lugano",
    "sg:classifiers":[
        {
            "category":"Banks & Credit Unions",
            "subcategory":"Bank",
            "type":"Services"
        }
    ],
    "sg:phone":"+41 4191236151",
    "sg:postcode":"6901",
    "sg:province":"Ticino",
    "wof:name":"Bank Finalba Ag",
    "wof:placetype":"venue"
},
  "geometry": {"coordinates":[8.951722,46.006348],"type":"Point"}
}