{
  "type": "Feature",
  "properties": {
    "iso:country":"CH",
    "sg:address":"Bruchstrasse 77",
    "sg:city":"Luzern",
    "sg:orig_category":"Vorschulen, Kinderg\u00e4rten",
    "sg:postcode":"6003",
    "sg:province":"Luzern",
    "wof:name":"St\u00e4dtischer Kindergarten",
    "wof:placetype":"venue"
},
  "geometry": {"coordinates":[8.3037633896,47.0458602905],"type":"Point"}
}