{
  "type": "Feature",
  "properties": {
    "iso:country":"CH",
    "sg:address":"M\u00fchleweg 18 5034 Suhr. Postfach",
    "sg:city":"Suhr",
    "sg:orig_category":"Stukkateurgewerbe, Gipserei U Verputzerei",
    "sg:phone":"+41 19843230",
    "sg:postcode":"5034",
    "sg:province":"Aargau",
    "wof:name":"Hubli",
    "wof:placetype":"venue"
},
  "geometry": {"coordinates":[8.6900548935,47.3005561829],"type":"Point"}
}