{
  "type": "Feature",
  "properties": {
    "iso:country":"CH",
    "sg:address":"Rislenstrasse 12",
    "sg:city":"Romanshorn",
    "sg:orig_category":"Malerei",
    "sg:phone":"+41 71 463 44 82",
    "sg:postcode":"8590",
    "sg:province":"Thurgau",
    "wof:name":"Karl Dr\u00f6fke Malergesch\u00e4ft",
    "wof:placetype":"venue"
},
  "geometry": {"coordinates":[9.3756656647,47.564163208],"type":"Point"}
}