{
  "type": "Feature",
  "properties": {
    "iso:country":"CH",
    "sg:address":"Sonnhaldenstrasse 840",
    "sg:city":"Mosnang",
    "sg:orig_category":"Herstellung von sonstigen elektrischen Ausr\u00fcstungen",
    "sg:postcode":"9607",
    "sg:province":"St. Gallen",
    "wof:name":"Truniger & Co.",
    "wof:placetype":"venue"
},
  "geometry": {"coordinates":[9.0490808487,47.3613891602],"type":"Point"}
}