{
  "type": "Feature",
  "properties": {
    "iso:country":"CH",
    "sg:address":"Eggb\u00fchlstrasse 14 8050 Z\u00fcrich. Postfach 8050 Z\u00fcrich",
    "sg:city":"Zust",
    "sg:orig_category":"Sonstiger Grosshandel",
    "sg:postcode":"50",
    "wof:name":"Diethelm Allhandel Und Allwork Warenhandel, Bes. An Marktst\u00e4nden Usw",
    "wof:placetype":"venue"
},
  "geometry": {"coordinates":[8.8579044342,47.2595062256],"type":"Point"}
}