{
  "type": "Feature",
  "properties": {
    "iso:country":"CH",
    "sg:address":"Gotthardstrasse",
    "sg:city":"Zug",
    "sg:orig_category":"Unternehmensberatung",
    "sg:postcode":"6300",
    "sg:province":"Zug",
    "wof:name":"Compas Informatik & Treuhand Ag",
    "wof:placetype":"venue"
},
  "geometry": {"coordinates":[8.5128583908,47.1726570129],"type":"Point"}
}