{
  "type": "Feature",
  "properties": {
    "iso:country":"CH",
    "sg:address":"Hauptstrasse 71",
    "sg:city":"Pratteln",
    "sg:orig_category":"RESTAURANTS: TEA-ROOMS",
    "sg:postcode":"4133",
    "sg:province":"Basel-Landschaft",
    "wof:name":"Ristorante Dario Cunsolo Giuseppe",
    "wof:placetype":"venue"
},
  "geometry": {"coordinates":[7.699452877,47.5172080994],"type":"Point"}
}