{
  "type": "Feature",
  "properties": {
    "iso:country":"CH",
    "sg:address":"Br\u00fchlstrasse 50",
    "sg:city":"Ettingen",
    "sg:orig_category":"Herstellung von Medikamenten U sonstigen pharmazeutischen Erzeugnissen Herstellung von pharmazeutisc",
    "sg:phone":"+41 61 721 30 01",
    "sg:postcode":"4107",
    "sg:province":"Basel-Landschaft",
    "wof:name":"Medichemie Bioline Ag Chemische, Pharmazeutische, Biologische, Nat\u00fcrliche Produkte; Handel",
    "wof:placetype":"venue"
},
  "geometry": {"coordinates":[7.5387687683,47.485748291],"type":"Point"}
}