{
  "type": "Feature",
  "properties": {
    "addr:full":"Anglikerstrasse 83 Villmergen Aargau 5612",
    "addr:housenumber":"83",
    "addr:postcode":"5612",
    "addr:street":"Anglikerstrasse",
    "iso:country":"CH",
    "sg:address":"Anglikerstrasse 83",
    "sg:city":"Villmergen",
    "sg:orig_category":"Benzin, Heiz\u00f6l and Mineral\u00f6lprodukte Grosshandel Tankstellen",
    "sg:phone":"+41 56 622 34 45",
    "sg:postcode":"5612",
    "sg:province":"Aargau",
    "wof:name":"Agip (suisse) Sa",
    "wof:placetype":"venue"
},
  "geometry": {"coordinates":[8.253892,47.352821],"type":"Point"}
}