{
  "type": "Feature",
  "properties": {
    "iso:country":"CH",
    "sg:address":"Lautengartenstrasse 12",
    "sg:city":"Basel",
    "sg:orig_category":"Unclassifiable Establishments",
    "sg:postcode":"4052",
    "sg:province":"Basel-Stadt",
    "wof:name":"Biotechnologie Ag F\u00fcr Emulsan",
    "wof:placetype":"venue"
},
  "geometry": {"coordinates":[7.5965218544,47.5528068542],"type":"Point"}
}