{
  "type": "Feature",
  "properties": {
    "iso:country":"CH",
    "sg:address":"2915",
    "sg:city":"Bure",
    "sg:orig_category":"Herstellung der Ausstattung von Uhren Herstellung von sonstigen Produkten aus nichtmetallischen Mine",
    "sg:phone":"+41 32 466 45 36",
    "sg:postcode":"2915",
    "sg:province":"Jura",
    "wof:name":"E. Crelier & Fils Sa Fabrique De Pierres Fines",
    "wof:placetype":"venue"
},
  "geometry": {"coordinates":[7.0065431595,47.4420890808],"type":"Point"}
}