{
  "type": "Feature",
  "properties": {
    "iso:country":"CH",
    "sg:address":"Hegenheimerstrasse 52",
    "sg:city":"Basel",
    "sg:orig_category":"Kaminfeger",
    "sg:phone":"+41 61 382 52 00",
    "sg:postcode":"4055",
    "sg:province":"Basel-Stadt",
    "wof:name":"Karl Kramer Kaminfegergesch\u00e4ft",
    "wof:placetype":"venue"
},
  "geometry": {"coordinates":[7.5711188316,47.5608406067],"type":"Point"}
}