{
  "type": "Feature",
  "properties": {
    "iso:country":"CH",
    "sg:address":"Austrasse 53",
    "sg:city":"Basel",
    "sg:orig_category":"Detailhandel mit Brot, Back U S\u00fcsswaren",
    "sg:phone":"+41 56 443 14 37",
    "sg:postcode":"4051",
    "sg:province":"Basel-Stadt",
    "wof:name":"Margrit Wernli B\u00e4ckerei",
    "wof:placetype":"venue"
},
  "geometry": {"coordinates":[8.10263,47.437771],"type":"Point"}
}