{
  "type": "Feature",
  "properties": {
    "iso:country":"CH",
    "sg:address":"Stampfgasse 4",
    "sg:city":"Glarus",
    "sg:orig_category":"Schlossereien Schmieden",
    "sg:phone":"+41 55 640 14 15",
    "sg:postcode":"8750",
    "sg:province":"Glarus",
    "wof:name":"Rudolf Bieri Mech.schmiede & Schlosserei",
    "wof:placetype":"venue"
},
  "geometry": {"coordinates":[9.0701675415,47.0399055481],"type":"Point"}
}