{
  "type": "Feature",
  "properties": {
    "iso:country":"CH",
    "sg:address":"Berggasse 12",
    "sg:city":"Schwarzenburg",
    "sg:orig_category":"Betrieb von Sportanlagen",
    "sg:postcode":"3150",
    "sg:province":"Bern",
    "wof:name":"Genossenschaft Sport Und Erholungszentrum Schwarzenburg",
    "wof:placetype":"venue"
},
  "geometry": {"coordinates":[7.33642,46.818775],"type":"Point"}
}