{
  "type": "Feature",
  "properties": {
    "iso:country":"CH",
    "sg:address":"Hegifeldstrasse 1a",
    "sg:city":"Stadel(winterthur)",
    "sg:orig_category":"Grosshandel mit sonstigen Maschinen U Ausr\u00fcstungen f\u00fcr Industrie, Handel U Schiffahrt",
    "sg:phone":"+41 56 266 50 50",
    "sg:postcode":"8404",
    "sg:province":"Z\u00fcrich",
    "wof:name":"Neumeyer Ag",
    "wof:placetype":"venue"
},
  "geometry": {"coordinates":[8.323381424,47.5245437622],"type":"Point"}
}