{
  "type": "Feature",
  "properties": {
    "iso:country":"CH",
    "sg:address":"Roemerstrasse 20",
    "sg:city":"Solothurn",
    "sg:classifiers":[
        {
            "category":"Banks & Credit Unions",
            "subcategory":"Financial Services",
            "type":"Services"
        }
    ],
    "sg:phone":"+41 32 625 44 44",
    "sg:postcode":"4502",
    "sg:province":"Solothurn",
    "sg:tags":[
        "banking",
        "finance",
        "insurance"
    ],
    "wof:name":"Reso Stiftung Rechenzentrum Fuer Krankenversicherung",
    "wof:placetype":"venue"
},
  "geometry": {"coordinates":[7.532466,47.204136],"type":"Point"}
}