{
  "type": "Feature",
  "properties": {
    "iso:country":"CH",
    "sg:address":"Thuraustr.",
    "sg:city":"Henau",
    "sg:classifiers":[
        {
            "category":"Farming",
            "subcategory":"Livestock Farm",
            "type":"Manufacturing & Wholesale Goods"
        }
    ],
    "sg:phone":"+41 71 951 40 72",
    "sg:postcode":"9247",
    "sg:province":"St. Gallen",
    "sg:tags":[
        "breeding",
        "agriculture",
        "animal"
    ],
    "wof:name":"Silvestri Ag",
    "wof:placetype":"venue"
},
  "geometry": {"coordinates":[9.120555,47.454525],"type":"Point"}
}