{
  "type": "Feature",
  "properties": {
    "iso:country":"CH",
    "sg:address":"Avenue Des Pr\u00e9s-beudin 20 1920 Martigny Case Postale 616",
    "sg:city":"Martigny",
    "sg:classifiers":[
        {
            "category":"Travel",
            "subcategory":"Hotels & Motels",
            "type":"Entertainment"
        }
    ],
    "sg:phone":"+41 21 921 23 22",
    "sg:postcode":"1920",
    "sg:province":"Valais",
    "sg:tags":[
        "hotels",
        "mit",
        "restaurant"
    ],
    "wof:name":"H\u00f4tel Du Parc",
    "wof:placetype":"venue"
},
  "geometry": {"coordinates":[6.8238101006,46.4825057983],"type":"Point"}
}