{
  "type": "Feature",
  "properties": {
    "iso:country":"CH",
    "sg:address":"H\u00e4gglingerstr. 3 5610 Wohlen Ag. Postfach",
    "sg:city":"Anglikon",
    "sg:orig_category":"Grosshandel mit lebenden Tieren",
    "sg:postcode":"5611",
    "sg:province":"Aargau",
    "wof:name":"Rohner Heinz",
    "wof:placetype":"venue"
},
  "geometry": {"coordinates":[8.2780704498,47.3505363464],"type":"Point"}
}