{
  "type": "Feature",
  "properties": {
    "iso:country":"CH",
    "sg:address":"Rue De Lausanne 43",
    "sg:city":"Payerne",
    "sg:orig_category":"Massagestudios",
    "sg:phone":"+41 79 357 18 76",
    "sg:postcode":"1530",
    "sg:province":"Vaud",
    "wof:name":"Daniel Marcuard Massage De Sant\u00e9",
    "wof:placetype":"venue"
},
  "geometry": {"coordinates":[6.937379837,46.8190193176],"type":"Point"}
}