{
  "type": "Feature",
  "properties": {
    "iso:country":"CH",
    "sg:address":"Milit\u00e4rstrasse 81",
    "sg:city":"Z\u00fcrich",
    "sg:orig_category":"Softwareentwicklung U beratung",
    "sg:phone":"+41 21 728 46 77",
    "sg:postcode":"8004",
    "sg:province":"Z\u00fcrich",
    "wof:name":"Contronix Sa",
    "wof:placetype":"venue"
},
  "geometry": {"coordinates":[6.6665029526,46.5248680115],"type":"Point"}
}