{
  "type": "Feature",
  "properties": {
    "iso:country":"CH",
    "sg:address":"Im Heimg\u00e4rtli 18",
    "sg:city":"Z\u00fcrich",
    "sg:orig_category":"Maler U Glasergewerbe",
    "sg:postcode":"8047",
    "sg:province":"Z\u00fcrich",
    "wof:name":"Senn Pittura Sagl",
    "wof:placetype":"venue"
},
  "geometry": {"coordinates":[8.7392292023,46.1512718201],"type":"Point"}
}