{
  "type": "Feature",
  "properties": {
    "addr:full":"Pian Scairolo Pazzallo Ticino 6912",
    "addr:postcode":"6912",
    "iso:country":"CH",
    "sg:address":"Pian Scairolo",
    "sg:city":"Pazzallo",
    "sg:orig_category":"Allgemeiner Hochbau D\u00e4mmung gegen K\u00e4lte, W\u00e4rme, Schall U Ersch\u00fctterung",
    "sg:phone":"+41 79 444 02 07",
    "sg:postcode":"6912",
    "sg:province":"Ticino",
    "wof:name":"Pini Lg Sa Impresa Gessatura",
    "wof:placetype":"venue"
},
  "geometry": {"coordinates":[8.942764,45.984329],"type":"Point"}
}