{
  "type": "Feature",
  "properties": {
    "iso:country":"CH",
    "sg:address":"Chesa Gaditsch R\u00fctigasse",
    "sg:city":"Sax",
    "sg:orig_category":"Detailhandel mit Teppichen Verlegen von Fussboden",
    "sg:phone":"+41 71 911 40 84",
    "sg:postcode":"9468",
    "sg:province":"St. Gallen",
    "wof:name":"Constantinos Ipsaryaris Floor-decor",
    "wof:placetype":"venue"
},
  "geometry": {"coordinates":[9.0516662598,47.4680328369],"type":"Point"}
}