{
  "type": "Feature",
  "properties": {
    "iso:country":"CH",
    "sg:address":"Grand-rue 4",
    "sg:city":"St-maurice",
    "sg:orig_category":"Fachdetailhandel mit pharmazeutischen Produkten",
    "sg:phone":"+41 24 485 33 94",
    "sg:postcode":"1890",
    "sg:province":"Valais",
    "wof:name":"Besse Jean-marc",
    "wof:placetype":"venue"
},
  "geometry": {"coordinates":[7.004655838,46.2178153992],"type":"Point"}
}