{
  "type": "Feature",
  "properties": {
    "iso:country":"CH",
    "sg:address":"Finkenweg 15",
    "sg:city":"Obergerlafingen",
    "sg:orig_category":"Detailhandel mit Fahrr\u00e4dern",
    "sg:phone":"+41 19751620",
    "sg:postcode":"4564",
    "sg:province":"Bern",
    "wof:name":"Windrad Gmbh Waren, Bes. Fahrr\u00e4der, Zubeh\u00f6r; Im, Export, Handel Usw",
    "wof:placetype":"venue"
},
  "geometry": {"coordinates":[8.7583827972,47.3051719666],"type":"Point"}
}