{
  "type": "Feature",
  "properties": {
    "iso:country":"CH",
    "sg:address":"Hubelstrasse 14",
    "sg:city":"Koppigen",
    "sg:orig_category":"Kauf U Verkauf von Immobilien auf eigene Rechnung",
    "sg:postcode":"3425",
    "sg:province":"Bern",
    "wof:name":"Kobag Koppiger Bauhandwerk",
    "wof:placetype":"venue"
},
  "geometry": {"coordinates":[7.6014528275,47.1291389465],"type":"Point"}
}