{
  "type": "Feature",
  "properties": {
    "iso:country":"CH",
    "sg:address":"Avenue Des Alpes 114",
    "sg:city":"Montreux",
    "sg:orig_category":"Vereine Damen Vereine Gesang",
    "sg:phone":"+41 21 963 24 02",
    "sg:postcode":"1820",
    "sg:province":"Vaud",
    "wof:name":"Choeur De Dames De L'assoc.des Vaudoises La Montreusienne",
    "wof:placetype":"venue"
},
  "geometry": {"coordinates":[6.9080810547,46.4388389587],"type":"Point"}
}