{
  "type": "Feature",
  "properties": {
    "iso:country":"CH",
    "sg:address":"Micheli-du-crest Rue 22 1205 Gen\u00e8ve. Postfach",
    "sg:city":"Gen\u00e8ve",
    "sg:orig_category":"Softwareentwicklung U beratung",
    "sg:postcode":"1201",
    "sg:province":"Gen\u00e8ve",
    "wof:name":"Storebyte S\u00e0rl",
    "wof:placetype":"venue"
},
  "geometry": {"coordinates":[6.1477689743,46.1944122314],"type":"Point"}
}