{
  "type": "Feature",
  "properties": {
    "iso:country":"CH",
    "sg:address":"Schmiedgasse 3 9212 Arnegg. Postfach",
    "sg:city":"Arnegg",
    "sg:orig_category":"Unclassifiable Establishments",
    "sg:postcode":"9212",
    "sg:province":"St. Gallen",
    "wof:name":"Garten Und Bau Bernhardsgr\u00fctter",
    "wof:placetype":"venue"
},
  "geometry": {"coordinates":[9.256278038,47.4447517395],"type":"Point"}
}