{
  "type": "Feature",
  "properties": {
    "iso:country":"CH",
    "sg:address":"Gliserallee 1",
    "sg:city":"Glis",
    "sg:orig_category":"Detailhandel mit Damenbekleidung Herstellung von W\u00e4sche",
    "sg:phone":"+41 27 923 80 60",
    "sg:postcode":"3902",
    "sg:province":"Valais",
    "wof:name":"Mode Ideal, Escher-seiler Bernadette",
    "wof:placetype":"venue"
},
  "geometry": {"coordinates":[7.9872961044,46.3155708313],"type":"Point"}
}