{
  "type": "Feature",
  "properties": {
    "iso:country":"CH",
    "sg:address":"Z\u00fcrcherstrasse 125 8102 Oberengstringen. Postfach",
    "sg:city":"Oberengstringen",
    "sg:orig_category":"Polizei",
    "sg:phone":"+41 17500349",
    "sg:postcode":"8102",
    "sg:province":"Z\u00fcrich",
    "wof:name":"Kantonspolizei",
    "wof:placetype":"venue"
},
  "geometry": {"coordinates":[8.4628896713,47.4088973999],"type":"Point"}
}