{
  "type": "Feature",
  "properties": {
    "iso:country":"CH",
    "sg:address":"9621",
    "sg:city":"Oberhelfenschwil",
    "sg:orig_category":"Sportvereine Sch\u00fctzen",
    "sg:postcode":"9621",
    "sg:province":"St. Gallen",
    "wof:name":"Feldsch\u00fctzengesellschaft",
    "wof:placetype":"venue"
},
  "geometry": {"coordinates":[9.1094970703,47.356918335],"type":"Point"}
}