{
  "type": "Feature",
  "properties": {
    "iso:country":"CH",
    "sg:address":"Lindenstrasse 16 6340 Baar. Postfach",
    "sg:city":"Zug",
    "sg:orig_category":"Detailhandel mit Brot, Back U S\u00fcsswaren",
    "sg:phone":"+41 41 729 29 29",
    "sg:postcode":"6300",
    "sg:province":"Zug",
    "wof:name":"Margo - Bakemark Schweiz Ag Waren, Backwaren; Entwicklung, Herstellung, Vertrieb",
    "wof:placetype":"venue"
},
  "geometry": {"coordinates":[8.517426,47.183182],"type":"Point"}
}