{
  "type": "Feature",
  "properties": {
    "iso:country":"CH",
    "sg:address":"Steinweg 10",
    "sg:city":"M\u00fcnchenstein",
    "sg:orig_category":"Maler U Glasergewerbe",
    "sg:phone":"+41 61 411 91 89",
    "sg:postcode":"4142",
    "sg:province":"Basel-Landschaft",
    "wof:name":"W. Gross S\u00f6hne Ag",
    "wof:placetype":"venue"
},
  "geometry": {"coordinates":[7.621969223,47.5124359131],"type":"Point"}
}