{
  "type": "Feature",
  "properties": {
    "iso:country":"CH",
    "sg:address":"Route De Thonon 117a",
    "sg:city":"Collonge-bellerive",
    "sg:orig_category":"Allgemeiner Hoch U Tiefbau Allgemeiner Hochbau",
    "sg:phone":"+41 22 752 13 92",
    "sg:postcode":"1245",
    "sg:province":"Gen\u00e8ve",
    "wof:name":"Giulietti Carmine",
    "wof:placetype":"venue"
},
  "geometry": {"coordinates":[6.213185,46.246964],"type":"Point"}
}