{
  "type": "Feature",
  "properties": {
    "addr:full":"Haus Terza Unterterzen St. Gallen 8882",
    "addr:postcode":"8882",
    "addr:street":"Unterterzen",
    "iso:country":"CH",
    "sg:address":"Haus Terza",
    "sg:city":"Unterterzen",
    "sg:classifiers":[
        {
            "category":"Banks & Credit Unions",
            "subcategory":"Bank",
            "type":"Services"
        }
    ],
    "sg:phone":"+41 81 738 16 55",
    "sg:postcode":"8882",
    "sg:province":"St. Gallen",
    "wof:name":"Bank Linth",
    "wof:placetype":"venue"
},
  "geometry": {"coordinates":[9.25304,47.113514],"type":"Point"}
}