{
  "type": "Feature",
  "properties": {
    "iso:country":"CH",
    "sg:address":"Tostelweg 10 8854 Siebnen. Postfach",
    "sg:city":"Siebnen",
    "sg:classifiers":[
        {
            "category":"Professional",
            "subcategory":"Employment Agencies",
            "type":"Services"
        }
    ],
    "sg:phone":"+41 55 440 31 43",
    "sg:postcode":"8854",
    "sg:province":"Schwyz",
    "sg:tags":[
        "personal",
        "u",
        "stellenvermittlung"
    ],
    "wof:name":"Diethelm Und Fuchs Kg, Siebnen, Nachfolger Alois Diethelm",
    "wof:placetype":"venue"
},
  "geometry": {"coordinates":[8.8918409348,47.1819648743],"type":"Point"}
}