{
  "type": "Feature",
  "properties": {
    "iso:country":"CH",
    "sg:address":"Obermatt 52",
    "sg:city":"Anwil",
    "sg:orig_category":"Handelsvermittlung U Grosshandel",
    "sg:phone":"+41 61 991 04 09",
    "sg:postcode":"4469",
    "sg:province":"Basel-Landschaft",
    "wof:name":"Landesprodukte M. Schaffner",
    "wof:placetype":"venue"
},
  "geometry": {"coordinates":[7.9393439293,47.4528388977],"type":"Point"}
}