{
  "type": "Feature",
  "properties": {
    "iso:country":"CH",
    "sg:address":"Rue Des Remparts 19",
    "sg:city":"Yverdon-les-bains",
    "sg:orig_category":"Wirtschaftspr\u00fcfung, Steuerberatung U Treuhand",
    "sg:phone":"+41 21 320 57 57",
    "sg:postcode":"1400",
    "sg:province":"Vaud",
    "wof:name":"Cabinet Fiduciaire & Fiscal Dino Venezia",
    "wof:placetype":"venue"
},
  "geometry": {"coordinates":[6.639550209,46.7800788879],"type":"Point"}
}