{
  "type": "Feature",
  "properties": {
    "iso:country":"CH",
    "sg:address":"Gesegnetmattstrasse 6",
    "sg:city":"Luzern",
    "sg:classifiers":[
        {
            "category":"Real Estate",
            "subcategory":"Real Estate Services",
            "type":"Services"
        }
    ],
    "sg:phone":"+41 41 410 80 27",
    "sg:postcode":"6006",
    "sg:province":"Luzern",
    "sg:tags":[
        "patent"
    ],
    "wof:name":"Staridee Ag",
    "wof:placetype":"venue"
},
  "geometry": {"coordinates":[8.3211221695,47.0557785034],"type":"Point"}
}