{
  "type": "Feature",
  "properties": {
    "iso:country":"CH",
    "sg:address":"Palmenstrasse 1",
    "sg:city":"Basel",
    "sg:classifiers":[
        {
            "category":"Social Services",
            "subcategory":"Job Training",
            "type":"Services"
        }
    ],
    "sg:phone":"+41 41 854 18 20",
    "sg:postcode":"4055",
    "sg:province":"Basel-Stadt",
    "sg:tags":[
        "preparation",
        "biological"
    ],
    "wof:name":"Omida Ag",
    "wof:placetype":"venue"
},
  "geometry": {"coordinates":[8.441568,47.081211],"type":"Point"}
}