{
  "type": "Feature",
  "properties": {
    "iso:country":"CH",
    "sg:address":"M\u00fcllernstrasse 29a",
    "sg:city":"Wettingen",
    "sg:orig_category":"Herstellung von Metallkonstruktionen",
    "sg:phone":"+41 56 426 67 54",
    "sg:postcode":"5430",
    "sg:province":"Aargau",
    "wof:name":"Walter Egloff Metallbau",
    "wof:placetype":"venue"
},
  "geometry": {"coordinates":[8.340593338,47.4687042236],"type":"Point"}
}