{
  "type": "Feature",
  "properties": {
    "iso:country":"CH",
    "sg:address":"Via Ferruccio Pelli 12",
    "sg:city":"Lugano",
    "sg:orig_category":"Autogaragen",
    "sg:phone":"+41 79 620 89 01",
    "sg:postcode":"6900",
    "sg:province":"Ticino",
    "wof:name":"Bixio Car",
    "wof:placetype":"venue"
},
  "geometry": {"coordinates":[8.951328,46.007847],"type":"Point"}
}