{
  "type": "Feature",
  "properties": {
    "iso:country":"CH",
    "sg:address":"Zurlindenstrasse 55",
    "sg:city":"Z\u00fcrich",
    "sg:orig_category":"Technische, physikalische U chemische Untersuchung",
    "sg:phone":"+41 71 311 19 08",
    "sg:postcode":"8003",
    "sg:province":"Z\u00fcrich",
    "wof:name":"Gaiatec Ag Projekte Im Umweltsektor; Umsetzung, Vermarktung Usw.",
    "wof:placetype":"venue"
},
  "geometry": {"coordinates":[9.3185386658,47.4241294861],"type":"Point"}
}