{
  "type": "Feature",
  "properties": {
    "iso:country":"CH",
    "sg:address":"Im B\u00e4renmoos 4",
    "sg:city":"Oberrieden",
    "sg:orig_category":"Kosmetikinstitute",
    "sg:phone":"+41 71 744 54 11",
    "sg:postcode":"8942",
    "sg:province":"Z\u00fcrich",
    "wof:name":"Yvonne M\u00fcller Open Hair Styling Yvonne",
    "wof:placetype":"venue"
},
  "geometry": {"coordinates":[9.6359519958,47.4498710632],"type":"Point"}
}