{
  "type": "Feature",
  "properties": {
    "iso:country":"CH",
    "sg:address":"8416",
    "sg:city":"Flaach",
    "sg:orig_category":"Vereine Gesang",
    "sg:postcode":"8416",
    "sg:province":"Z\u00fcrich",
    "wof:name":"Gemischter Chor Der Evang.-methodistischen Kirche",
    "wof:placetype":"venue"
},
  "geometry": {"coordinates":[8.6080780029,47.5752487183],"type":"Point"}
}