{
  "type": "Feature",
  "properties": {
    "iso:country":"CH",
    "sg:address":"Wittifeldstrasse",
    "sg:city":"Schwarzh\u00e4usern",
    "sg:orig_category":"Sportvereine Sch\u00fctzen",
    "sg:phone":"+41 62 923 25 64",
    "sg:postcode":"4911",
    "sg:province":"Bern",
    "wof:name":"Feldsch\u00fctzengesellschaft",
    "wof:placetype":"venue"
},
  "geometry": {"coordinates":[7.7646951675,47.2537994385],"type":"Point"}
}