{
  "type": "Feature",
  "properties": {
    "iso:country":"CH",
    "sg:address":"Av. De France 10",
    "sg:city":"Sion",
    "sg:orig_category":"Gesundheitswesen",
    "sg:postcode":"1950",
    "sg:province":"Valais",
    "wof:name":"Inter Clinica Sa",
    "wof:placetype":"venue"
},
  "geometry": {"coordinates":[7.3576030731,46.2282676697],"type":"Point"}
}