{
  "type": "Feature",
  "properties": {
    "iso:country":"CH",
    "sg:address":"Industriestrasse 14",
    "sg:city":"Kloten",
    "sg:orig_category":"Vermietung von Automobilen",
    "sg:phone":"+41 18385858",
    "sg:postcode":"8302",
    "sg:province":"Z\u00fcrich",
    "wof:name":"Budget Rent-a-car International, Inc., Wilmington (delaware/usa) Zweigniederlassung Bassersdorf",
    "wof:placetype":"venue"
},
  "geometry": {"coordinates":[8.5905427933,47.4496078491],"type":"Point"}
}