{
  "type": "Feature",
  "properties": {
    "iso:country":"CH",
    "sg:address":"Rue Des Peupliers 16",
    "sg:city":"Conthey",
    "sg:orig_category":"Erdbewegungsarbeiten G\u00fcterbef\u00f6rderung im Strassenverkehr",
    "sg:phone":"+41 27 346 14 87",
    "sg:postcode":"1964",
    "sg:province":"Valais",
    "wof:name":"Ev\u00e9quoz Sa Entreprise De Construction",
    "wof:placetype":"venue"
},
  "geometry": {"coordinates":[7.3101320267,46.2230873108],"type":"Point"}
}