{
  "type": "Feature",
  "properties": {
    "iso:country":"CH",
    "sg:address":"Stadtturmstrasse 17",
    "sg:city":"Baden",
    "sg:orig_category":"Offsetdruck Siebdruck",
    "sg:phone":"+41 56 221 77 77",
    "sg:postcode":"5400",
    "sg:province":"Aargau",
    "wof:name":"Rowi-druck Wirth R.",
    "wof:placetype":"venue"
},
  "geometry": {"coordinates":[8.3057432175,47.4755935669],"type":"Point"}
}