{
  "type": "Feature",
  "properties": {
    "iso:country":"CH",
    "sg:address":"Grand'rue 12",
    "sg:city":"Rolle",
    "sg:classifiers":[
        {
            "category":"Restaurant",
            "type":"Food & Drink"
        }
    ],
    "sg:phone":"+41 22 301 00 22",
    "sg:postcode":"1180",
    "sg:province":"Vaud",
    "wof:name":"Restaurant Le Parc",
    "wof:placetype":"venue"
},
  "geometry": {"coordinates":[6.1492547989,46.200881958],"type":"Point"}
}