{
  "type": "Feature",
  "properties": {
    "iso:country":"CH",
    "sg:address":"Talweg 32",
    "sg:city":"Erstfeld",
    "sg:classifiers":[
        {
            "category":"Travel",
            "subcategory":"Hotels & Motels",
            "type":"Entertainment"
        }
    ],
    "sg:phone":"+41 41 880 01 72",
    "sg:postcode":"6472",
    "sg:province":"Uri",
    "sg:tags":[
        "hotels",
        "mit",
        "restaurant"
    ],
    "wof:name":"Wyrsch-walker Markus Und Irene",
    "wof:placetype":"venue"
},
  "geometry": {"coordinates":[8.6404590607,46.8187866211],"type":"Point"}
}