{
  "type": "Feature",
  "properties": {
    "iso:country":"CH",
    "sg:address":"Rieden 4",
    "sg:city":"Stans",
    "sg:orig_category":"Grosshandel mit Holz U Baustoffen",
    "sg:phone":"+41 41 610 26 76",
    "sg:postcode":"6370",
    "sg:province":"Nidwalden",
    "wof:name":"Korodur Durop Baustoffe Gmbh",
    "wof:placetype":"venue"
},
  "geometry": {"coordinates":[8.3837413788,46.9650268555],"type":"Point"}
}