{
  "type": "Feature",
  "properties": {
    "iso:country":"CH",
    "sg:address":"Lindenstrasse 1",
    "sg:city":"Kloten",
    "sg:orig_category":"Hardwareberatung Softwareentwicklung U beratung",
    "sg:phone":"+41 19703165",
    "sg:postcode":"8302",
    "sg:province":"Z\u00fcrich",
    "wof:name":"Trachsler Electronics Gmbh",
    "wof:placetype":"venue"
},
  "geometry": {"coordinates":[8.8122186661,47.3311500549],"type":"Point"}
}