{
  "type": "Feature",
  "properties": {
    "iso:country":"CH",
    "sg:address":"Rue Cit\u00e9-derri\u00e8re 13",
    "sg:city":"Lausanne",
    "sg:orig_category":"RESTAURANTS: TEA-ROOMS",
    "sg:postcode":"1005",
    "sg:province":"Vaud",
    "wof:name":"La Potiniere Sa",
    "wof:placetype":"venue"
},
  "geometry": {"coordinates":[6.2112832069,46.2664871216],"type":"Point"}
}