{
  "type": "Feature",
  "properties": {
    "iso:country":"CH",
    "sg:address":"Wylerau",
    "sg:city":"Diemtigen",
    "sg:orig_category":"Zimmerei, Dachdeckerei, Bauspenglerei U Abdichtung",
    "sg:phone":"+41 33 681 22 69",
    "sg:postcode":"3754",
    "sg:province":"Bern",
    "wof:name":"Peter K\u00e4mpf Holzbau Ag",
    "wof:placetype":"venue"
},
  "geometry": {"coordinates":[7.5753798485,46.658706665],"type":"Point"}
}