{
  "type": "Feature",
  "properties": {
    "iso:country":"CH",
    "sg:address":"Morgentalstrasse 30",
    "sg:city":"Z\u00fcrich",
    "sg:orig_category":"Vereine Vaterl\u00e4ndische",
    "sg:phone":"+41 71 277 52 98",
    "sg:postcode":"8038",
    "sg:province":"Z\u00fcrich",
    "wof:name":"Alban.kulturverein Memedheu",
    "wof:placetype":"venue"
},
  "geometry": {"coordinates":[9.3512659073,47.4189682007],"type":"Point"}
}