{
  "type": "Feature",
  "properties": {
    "iso:country":"CH",
    "sg:address":"Riehentorstrasse 33",
    "sg:city":"Basel",
    "sg:orig_category":"Fussreflexzonenmassage",
    "sg:phone":"+41 81 833 75 17",
    "sg:postcode":"4058",
    "sg:province":"Basel-Stadt",
    "wof:name":"Eliane Von Senger Massagen",
    "wof:placetype":"venue"
},
  "geometry": {"coordinates":[9.8451538086,46.4983711243],"type":"Point"}
}