{
  "type": "Feature",
  "properties": {
    "iso:country":"CH",
    "sg:address":"Steinhaldenstrasse 20",
    "sg:city":"Geroldswil",
    "sg:orig_category":"Herstellung von Kunststoffwaren Herstellung von sonstigen Metallwaren",
    "sg:phone":"+41 31 371 16 34",
    "sg:postcode":"8954",
    "sg:province":"Z\u00fcrich",
    "wof:name":"Buchstaben Alfred Nacht",
    "wof:placetype":"venue"
},
  "geometry": {"coordinates":[7.426530838,46.9432182312],"type":"Point"}
}