{
  "type": "Feature",
  "properties": {
    "iso:country":"CH",
    "sg:address":"Viale Castagnola 21a",
    "sg:city":"Lugano",
    "sg:orig_category":"Physiotherapie",
    "sg:phone":"+41 91 970 18 28",
    "sg:postcode":"6900",
    "sg:province":"Ticino",
    "wof:name":"Fisioterapia Cassarate Dr.med. Nessi Mauro",
    "wof:placetype":"venue"
},
  "geometry": {"coordinates":[8.9658555984,46.0061340332],"type":"Point"}
}