{
  "type": "Feature",
  "properties": {
    "iso:country":"CH",
    "sg:address":"4450",
    "sg:city":"Sissach",
    "sg:orig_category":"Verarbeitung von Milch Verwertung von Milch",
    "sg:postcode":"4450",
    "sg:province":"Basel-Landschaft",
    "wof:name":"Milchgenossenschaft St.margrethen",
    "wof:placetype":"venue"
},
  "geometry": {"coordinates":[9.6123247147,47.4570541382],"type":"Point"}
}