{
  "type": "Feature",
  "properties": {
    "addr:full":"Ringacker Leuk-stadt Valais 3953",
    "addr:postcode":"3953",
    "iso:country":"CH",
    "sg:address":"Ringacker",
    "sg:city":"Leuk-stadt",
    "sg:orig_category":"Bildung and Forschung, Bildungsmedien",
    "sg:postcode":"3953",
    "sg:province":"Valais",
    "wof:name":"Europaeische Hochschule Fuer Berufstaetige Ehb",
    "wof:placetype":"venue"
},
  "geometry": {"coordinates":[7.635232,46.31443],"type":"Point"}
}