{
  "type": "Feature",
  "properties": {
    "iso:country":"CH",
    "sg:address":"Gupfstrasse 17",
    "sg:city":"B\u00e4retswil",
    "sg:orig_category":"Detailhandel mit Waren verschiedener Art, Hauptrichtung Nahrungsmittel",
    "sg:phone":"+41 19391235",
    "sg:postcode":"8344",
    "sg:province":"Z\u00fcrich",
    "wof:name":"Coop Center",
    "wof:placetype":"venue"
},
  "geometry": {"coordinates":[8.8549213409,47.3352012634],"type":"Point"}
}