{
  "type": "Feature",
  "properties": {
    "iso:country":"CH",
    "sg:address":"J\u00e4gerweg 26 3098 K\u00f6niz. Postfach",
    "sg:city":"Liebefeld",
    "sg:orig_category":"Herstellung von sonstigen elektrischen Ausr\u00fcstungen",
    "sg:postcode":"3097",
    "sg:province":"Bern",
    "wof:name":"Selco Ag",
    "wof:placetype":"venue"
},
  "geometry": {"coordinates":[7.4243021011,46.9319038391],"type":"Point"}
}