{
  "type": "Feature",
  "properties": {
    "iso:country":"CH",
    "sg:address":"Usterstrasse 10",
    "sg:city":"Volketswil",
    "sg:orig_category":"Instandhaltung U Reparatur von Automobilen",
    "sg:phone":"+41 19452970",
    "sg:postcode":"8604",
    "sg:province":"Z\u00fcrich",
    "wof:name":"Franz Tschudi Garage",
    "wof:placetype":"venue"
},
  "geometry": {"coordinates":[8.6762723923,47.3890228271],"type":"Point"}
}