{
  "type": "Feature",
  "properties": {
    "iso:country":"CH",
    "sg:address":"Rue De Rive 62",
    "sg:city":"Nyon",
    "sg:orig_category":"RESTAURANTS: TEA-ROOMS",
    "sg:phone":"+41 22 361 12 64",
    "sg:postcode":"1260",
    "sg:province":"Vaud",
    "wof:name":"Caf\u00e9-restaurant Au Cheval Blanc, Morel Didier",
    "wof:placetype":"venue"
},
  "geometry": {"coordinates":[6.2416892052,46.3815765381],"type":"Point"}
}