{
  "type": "Feature",
  "properties": {
    "iso:country":"CH",
    "sg:address":"Poststrasse 13",
    "sg:city":"Liestal",
    "sg:orig_category":"Detailhandel mit B\u00fcromaschinen U einrichtungen",
    "sg:phone":"+41 31 981 35 85",
    "sg:postcode":"4410",
    "sg:province":"Basel-Landschaft",
    "wof:name":"Sitag Ag B\u00fcrom\u00f6bel & St\u00fchle",
    "wof:placetype":"venue"
},
  "geometry": {"coordinates":[7.373194,46.920826],"type":"Point"}
}