{
  "type": "Feature",
  "properties": {
    "iso:country":"CH",
    "sg:address":"Zwingerstrasse 22 4053 Basel. Postfach",
    "sg:city":"Basel",
    "sg:orig_category":"Glaserei",
    "sg:phone":"+41 61 361 37 89",
    "sg:postcode":"4001",
    "sg:province":"Basel-Stadt",
    "wof:name":"Erwin Hangartner Glasreparaturen",
    "wof:placetype":"venue"
},
  "geometry": {"coordinates":[7.5928549767,47.5440177917],"type":"Point"}
}