{
  "type": "Feature",
  "properties": {
    "addr:full":"Avenue Des Alpes 33 Montreux Vaud 1820",
    "addr:housenumber":"33",
    "addr:postcode":"1820",
    "addr:street":"Avenue Des Alpes",
    "iso:country":"CH",
    "sg:address":"Avenue Des Alpes 33",
    "sg:city":"Montreux",
    "sg:classifiers":[
        {
            "category":"Shopping",
            "subcategory":"Books",
            "type":"Retail Goods"
        }
    ],
    "sg:phone":"+41 21 963 14 08",
    "sg:postcode":"1820",
    "sg:province":"Vaud",
    "wof:name":"Indigo-montangero S\u00e0rl",
    "wof:placetype":"venue"
},
  "geometry": {"coordinates":[6.910432,46.434669],"type":"Point"}
}