{
  "type": "Feature",
  "properties": {
    "iso:country":"CH",
    "sg:address":"Route Des Ilettes 29",
    "sg:city":"Massongex",
    "sg:orig_category":"Herstellung von Industriegasen Mineral\u00f6lverarbeitung",
    "sg:phone":"+41 24 472 32 55",
    "sg:postcode":"1869",
    "sg:province":"Valais",
    "wof:name":"Carbagas",
    "wof:placetype":"venue"
},
  "geometry": {"coordinates":[6.9809360504,46.2437744141],"type":"Point"}
}