{
  "type": "Feature",
  "properties": {
    "iso:country":"CH",
    "sg:address":"Wehntalerstrasse 25c",
    "sg:city":"H\u00f6ri",
    "sg:orig_category":"Grosshandel mit Eisenwaren sowie Installationsbedarf f\u00fcr Gas, Wasser U Heizung Herstellung von Elekt",
    "sg:phone":"+41 18620670",
    "sg:postcode":"8181",
    "sg:province":"Z\u00fcrich",
    "wof:name":"Schultheiss P. & Co Ag",
    "wof:placetype":"venue"
},
  "geometry": {"coordinates":[8.5085802078,47.5073013306],"type":"Point"}
}