{
  "type": "Feature",
  "properties": {
    "addr:full":"Neustadt 15 8200 Schaffhausen. Postfach Schaffhausen Schaffhausen 8201",
    "addr:housenumber":"15",
    "addr:postcode":"8200 schaffhausen. postfach;8201",
    "addr:street":"Neustadt",
    "iso:country":"CH",
    "sg:address":"Neustadt 15 8200 Schaffhausen. Postfach",
    "sg:city":"Schaffhausen",
    "sg:orig_category":"Bauspenglerei Sanit\u00e4r, Heizungs U L\u00fcftungsinstallation",
    "sg:phone":"+41 52 625 42 07",
    "sg:postcode":"8201",
    "sg:province":"Schaffhausen",
    "wof:name":"M\u00fcller Max.",
    "wof:placetype":"venue"
},
  "geometry": {"coordinates":[8.632049,47.694256],"type":"Point"}
}