{
  "type": "Feature",
  "properties": {
    "iso:country":"CH",
    "sg:address":"Rue Du Rh\u00f4ne 104",
    "sg:city":"Gen\u00e8ve",
    "sg:orig_category":"Detailhandel mit Schuhen",
    "sg:phone":"+41 22 818 13 61",
    "sg:postcode":"1204",
    "sg:province":"Gen\u00e8ve",
    "wof:name":"Salvatore Ferragamo Chaussures Pr\u00eat-\u00e0-porter",
    "wof:placetype":"venue"
},
  "geometry": {"coordinates":[6.1527571678,46.2029266357],"type":"Point"}
}