{
  "type": "Feature",
  "properties": {
    "iso:country":"CH",
    "sg:address":"Unterm Aspalter 1",
    "sg:city":"Veltheim",
    "sg:classifiers":[
        {
            "category":"Shopping",
            "subcategory":"Luggage & Leather Goods",
            "type":"Retail Goods"
        }
    ],
    "sg:phone":"+41 41 711 90 48",
    "sg:postcode":"5106",
    "sg:province":"Aargau",
    "sg:tags":[
        "shoe"
    ],
    "wof:name":"Aldo Group International Ag",
    "wof:placetype":"venue"
},
  "geometry": {"coordinates":[8.5075817108,47.1476821899],"type":"Point"}
}