{
  "type": "Feature",
  "properties": {
    "iso:country":"CH",
    "sg:address":"Oberdorf 56 8460 Marthalen. Postfach",
    "sg:city":"Marthalen",
    "sg:classifiers":[
        {
            "category":"Insurance",
            "subcategory":"Insurance Agent",
            "type":"Services"
        }
    ],
    "sg:phone":"+41 52 319 31 46",
    "sg:postcode":"8460",
    "sg:province":"Z\u00fcrich",
    "sg:tags":[
        "versicherungsagenturen",
        "-broker"
    ],
    "wof:name":"Winterthur Versicherungen Agentur",
    "wof:placetype":"venue"
},
  "geometry": {"coordinates":[8.6525201797,47.6242713928],"type":"Point"}
}