{
  "type": "Feature",
  "properties": {
    "iso:country":"CH",
    "sg:address":"Hotelgasse 1 3011 Bern. Postfach",
    "sg:city":"Bern",
    "sg:orig_category":"Verlagsgewerbe Zeitschriftenverlag",
    "sg:phone":"+41 31 312 61 16",
    "sg:postcode":"3001",
    "sg:province":"Bern",
    "wof:name":"Helveticmedien Ag",
    "wof:placetype":"venue"
},
  "geometry": {"coordinates":[7.4482722282,46.9477996826],"type":"Point"}
}