{
  "type": "Feature",
  "properties": {
    "iso:country":"CH",
    "sg:address":"Wallisellenstrasse 241",
    "sg:city":"Z\u00fcrich",
    "sg:orig_category":"Einzelhandel mit Automobilteilen U Zubeh\u00f6r Herstellung von Bereifungen",
    "sg:phone":"+41 71 841 33 74",
    "sg:postcode":"8050",
    "sg:province":"Z\u00fcrich",
    "wof:name":"Pneu Muggler Ag",
    "wof:placetype":"venue"
},
  "geometry": {"coordinates":[8.8385400772,47.2978286743],"type":"Point"}
}