{
  "type": "Feature",
  "properties": {
    "iso:country":"CH",
    "sg:address":"4900",
    "sg:city":"Langenthal",
    "sg:orig_category":"Vereine Fasnacht",
    "sg:phone":"+41 41 340 03 98",
    "sg:postcode":"4900",
    "sg:province":"Bern",
    "wof:name":"Loz\u00e4rner Fasnachtskomitee",
    "wof:placetype":"venue"
},
  "geometry": {"coordinates":[8.3089418411,47.0627288818],"type":"Point"}
}