{
  "type": "Feature",
  "properties": {
    "iso:country":"CH",
    "sg:address":"M\u00e4rwiler Strasse 50",
    "sg:city":"Affeltrangen",
    "sg:orig_category":"Herstellung von Schl\u00f6ssern U Beschl\u00e4gen Spezieller Tiefbau",
    "sg:phone":"+41 79 411 59 29",
    "sg:postcode":"9556",
    "sg:province":"Thurgau",
    "wof:name":"Rudolf Berglas Rohrleitungsbau & Montage",
    "wof:placetype":"venue"
},
  "geometry": {"coordinates":[9.0396203995,47.5250358582],"type":"Point"}
}