{
  "type": "Feature",
  "properties": {
    "iso:country":"CH",
    "sg:address":"Kampstrasse 33",
    "sg:city":"Schlieren",
    "sg:orig_category":"Malerei",
    "sg:phone":"+41 17308144",
    "sg:postcode":"8952",
    "sg:province":"Z\u00fcrich",
    "wof:name":"Cesar Savoya Malergesch\u00e4ft",
    "wof:placetype":"venue"
},
  "geometry": {"coordinates":[8.4425449371,47.3927879333],"type":"Point"}
}