{
  "type": "Feature",
  "properties": {
    "iso:country":"CH",
    "sg:address":"Ennerbergstrasse 10 6374 Buochs. Postfach 146",
    "sg:city":"Buochs",
    "sg:orig_category":"Herstellung von Elektrizit\u00e4tsverteilungs U schalteinrichtungen",
    "sg:phone":"+41 41 624 49 49",
    "sg:postcode":"6374",
    "sg:province":"Nidwalden",
    "wof:name":"Elsont Mess Und Regeltechnik Ag",
    "wof:placetype":"venue"
},
  "geometry": {"coordinates":[8.4192152023,46.9723205566],"type":"Point"}
}