{
  "type": "Feature",
  "properties": {
    "iso:country":"CH",
    "sg:address":"Oberdorfstrasse 21",
    "sg:city":"Steffisburg",
    "sg:orig_category":"Herstellung von keramischen Haushaltswaren U Ziergegenst\u00e4nden Herstellung von sonstigen keramischen ",
    "sg:phone":"+41 33 437 28 14",
    "sg:postcode":"3612",
    "sg:province":"Bern",
    "wof:name":"T\u00f6pferei-keramikatelier Franziska Mischler",
    "wof:placetype":"venue"
},
  "geometry": {"coordinates":[7.6336789131,46.7800979614],"type":"Point"}
}