{
  "type": "Feature",
  "properties": {
    "iso:country":"CH",
    "sg:address":"Rellikonstrasse 6",
    "sg:city":"Maur",
    "sg:classifiers":[
        {
            "category":"Restaurant",
            "type":"Food & Drink"
        }
    ],
    "sg:phone":"+41 19800107",
    "sg:postcode":"8124",
    "sg:province":"Z\u00fcrich",
    "wof:name":"Restaurant Freisch\u00fctz",
    "wof:placetype":"venue"
},
  "geometry": {"coordinates":[8.6713495255,47.3390426636],"type":"Point"}
}