{
  "type": "Feature",
  "properties": {
    "iso:country":"CH",
    "sg:address":"Baumgartenstrasse 19",
    "sg:city":"Schaffhausen",
    "sg:orig_category":"Kunsthandel",
    "sg:phone":"+41 52 625 24 18",
    "sg:postcode":"8200",
    "sg:province":"Schaffhausen",
    "wof:name":"Forum Vebikus Galerie",
    "wof:placetype":"venue"
},
  "geometry": {"coordinates":[8.6362781525,47.6944847107],"type":"Point"}
}