{
  "type": "Feature",
  "properties": {
    "iso:country":"CH",
    "sg:address":"Ennerfeldstrasse 49",
    "sg:city":"Kienberg",
    "sg:orig_category":"G\u00fcterbef\u00f6rderung im Strassenverkehr",
    "sg:phone":"+41 62 844 20 02",
    "sg:postcode":"4468",
    "sg:province":"Solothurn",
    "wof:name":"Andres Gubler Transporte",
    "wof:placetype":"venue"
},
  "geometry": {"coordinates":[7.9661588669,47.4384613037],"type":"Point"}
}