{
  "type": "Feature",
  "properties": {
    "iso:country":"CH",
    "sg:address":"Churerstrasse 38/40",
    "sg:city":"Altendorf",
    "sg:orig_category":"Unclassifiable Establishments",
    "sg:phone":"+41 55 442 57 92",
    "sg:postcode":"8852",
    "sg:province":"Schwyz",
    "wof:name":"Generali Versicherungen Agentur",
    "wof:placetype":"venue"
},
  "geometry": {"coordinates":[8.8361988068,47.1900787354],"type":"Point"}
}