{
  "type": "Feature",
  "properties": {
    "iso:country":"CH",
    "sg:address":"Route De La P\u00e2le 5",
    "sg:city":"Denges",
    "sg:orig_category":"G\u00fcterbef\u00f6rderung im Strassenverkehr",
    "sg:phone":"+41 21 802 18 73",
    "sg:postcode":"1026",
    "sg:province":"Vaud",
    "wof:name":"Leyvraz Jean Transports.",
    "wof:placetype":"venue"
},
  "geometry": {"coordinates":[6.5424699783,46.5171775818],"type":"Point"}
}