{
  "type": "Feature",
  "properties": {
    "iso:country":"CH",
    "sg:address":"Dorfstrasse 9",
    "sg:city":"Sch\u00f6ftland",
    "sg:orig_category":"Tanzschulen, Tanzlehrer",
    "sg:phone":"+41 62 721 25 59",
    "sg:postcode":"5040",
    "sg:province":"Aargau",
    "wof:name":"Monique G\u00e4chter Gymnastik-& Tanzstudio Monique",
    "wof:placetype":"venue"
},
  "geometry": {"coordinates":[8.0511245728,47.3046646118],"type":"Point"}
}