{
  "type": "Feature",
  "properties": {
    "iso:country":"CH",
    "sg:address":"Via Gaggiolo 26",
    "sg:city":"Stabio",
    "sg:orig_category":"Non-Classified Establishments",
    "sg:postcode":"6855",
    "sg:province":"Ticino",
    "wof:name":"Meeting Service Sagl",
    "wof:placetype":"venue"
},
  "geometry": {"coordinates":[8.929060936,45.8457870483],"type":"Point"}
}