{
  "type": "Feature",
  "properties": {
    "iso:country":"CH",
    "sg:address":"Aproz Route D' 4",
    "sg:city":"Sitten",
    "sg:orig_category":"Instandhaltung U Reparatur von Automobilen",
    "sg:postcode":"1950",
    "sg:province":"Valais",
    "wof:name":"Garage Du L\u00e9man Sa, Succursale De Sion",
    "wof:placetype":"venue"
},
  "geometry": {"coordinates":[7.3125910759,46.2087249756],"type":"Point"}
}