{
  "type": "Feature",
  "properties": {
    "iso:country":"CH",
    "sg:address":"Lausenerstr. 22",
    "sg:city":"Liestal",
    "sg:classifiers":[
        {
            "category":"Home & Garden",
            "subcategory":"Furniture",
            "type":"Retail Goods"
        }
    ],
    "sg:phone":"+41 61 926 77 00",
    "sg:postcode":"4410",
    "sg:province":"Basel-Landschaft",
    "sg:tags":[
        "household",
        "wood"
    ],
    "wof:name":"Inform M\u00d6belsysteme Ag",
    "wof:placetype":"venue"
},
  "geometry": {"coordinates":[7.749350071,47.4753379822],"type":"Point"}
}