{
  "type": "Feature",
  "properties": {
    "iso:country":"CH",
    "sg:address":"Ch. Du Lizet 8",
    "sg:city":"Echandens",
    "sg:orig_category":"Fachdetailhandel in Verkaufsr\u00e4umen",
    "sg:phone":"+41 21 701 25 64",
    "sg:postcode":"1026",
    "sg:province":"Vaud",
    "wof:name":"Widmer Paul",
    "wof:placetype":"venue"
},
  "geometry": {"coordinates":[6.5402569771,46.5376091003],"type":"Point"}
}