{
  "type": "Feature",
  "properties": {
    "iso:country":"CH",
    "sg:address":"Chemin Des Lilas 4",
    "sg:city":"Sierre",
    "sg:orig_category":"Sonstiger spezialisierter Hoch U Tiefbau",
    "sg:phone":"+41 27 455 74 02",
    "sg:postcode":"3960",
    "sg:province":"Valais",
    "wof:name":"Antille Ren\u00e9 Sa",
    "wof:placetype":"venue"
},
  "geometry": {"coordinates":[7.5256757736,46.2903022766],"type":"Point"}
}