{
  "type": "Feature",
  "properties": {
    "addr:full":"Gerechtigkeitsgasse 48 Bern Bern 3011",
    "addr:housenumber":"48",
    "addr:postcode":"3011",
    "addr:street":"Gerechtigkeitsgasse",
    "iso:country":"CH",
    "sg:address":"Gerechtigkeitsgasse 48",
    "sg:city":"Bern",
    "sg:orig_category":"Detailhandel mit Blumen U Pflanzen",
    "sg:phone":"+41 31 311 09 77",
    "sg:postcode":"3011",
    "sg:province":"Bern",
    "wof:name":"Art Floral Gafner Marianne Blumengesch\u00e4ft",
    "wof:placetype":"venue"
},
  "geometry": {"coordinates":[7.454149,46.948376],"type":"Point"}
}