{
  "type": "Feature",
  "properties": {
    "iso:country":"CH",
    "sg:address":"Kirchgasse 25",
    "sg:city":"Meilen",
    "sg:orig_category":"Sanit\u00e4r, Heizungs U L\u00fcftungsinstallation",
    "sg:postcode":"8706",
    "sg:province":"Z\u00fcrich",
    "wof:name":"Lehmann & Co.",
    "wof:placetype":"venue"
},
  "geometry": {"coordinates":[8.6407814026,47.2690315247],"type":"Point"}
}