{
  "type": "Feature",
  "properties": {
    "iso:country":"CH",
    "sg:address":"Ziegelmatt",
    "sg:city":"Entlebuch",
    "sg:orig_category":"G\u00fcterbef\u00f6rderung im Strassenverkehr",
    "sg:phone":"+41 22 796 62 58",
    "sg:postcode":"6162",
    "sg:province":"Luzern",
    "wof:name":"Marius Pralong Transports",
    "wof:placetype":"venue"
},
  "geometry": {"coordinates":[6.0931401253,46.200920105],"type":"Point"}
}