{
  "type": "Feature",
  "properties": {
    "iso:country":"CH",
    "sg:address":"Le Marigny Club 3962 Montana-vermala. Postfach",
    "sg:city":"Aminona",
    "sg:orig_category":"Fachdetailhandel in Verkaufsr\u00e4umen",
    "sg:phone":"+41 27 485 97 50",
    "sg:postcode":"3962",
    "wof:name":"Passer D\u00e9veloppements S\u00e0rl Articles De Sport, Accessoires Etc.; Conception, D\u00e9velopp., Production, Vente, Distr.",
    "wof:placetype":"venue"
},
  "geometry": {"coordinates":[7.4897050858,46.3110542297],"type":"Point"}
}