{
  "type": "Feature",
  "properties": {
    "iso:country":"CH",
    "sg:address":"Churerstrasse 160a 8807 Freienbach. Postfach",
    "sg:city":"Freienbach",
    "sg:orig_category":"Grosshandel mit Eisenwaren sowie Installationsbedarf f\u00fcr Gas, Wasser U Heizung",
    "sg:postcode":"8807",
    "sg:province":"Schwyz",
    "wof:name":"Garda Bad Gmbh",
    "wof:placetype":"venue"
},
  "geometry": {"coordinates":[8.7711877823,47.2022171021],"type":"Point"}
}