{
  "type": "Feature",
  "properties": {
    "iso:country":"CH",
    "sg:address":"Avenue Bois-de-la-chapelle 99",
    "sg:city":"Onex",
    "sg:orig_category":"Malerei Tapeziererei",
    "sg:phone":"+41 79 301 35 27",
    "sg:postcode":"1213",
    "sg:province":"Gen\u00e8ve",
    "wof:name":"Pascal Fortis Peinture Papiers Peints",
    "wof:placetype":"venue"
},
  "geometry": {"coordinates":[6.1011018753,46.1861953735],"type":"Point"}
}