{
  "type": "Feature",
  "properties": {
    "iso:country":"CH",
    "sg:address":"Roth\u00fcsli 9054 Haslen",
    "sg:city":"Appenzell",
    "sg:orig_category":"S\u00e4ge, Hobel U Holzimpr\u00e4gnierwerke",
    "sg:postcode":"9050",
    "sg:province":"Appenzell Innerhoden",
    "wof:name":"Gm\u00fcnder Beni",
    "wof:placetype":"venue"
},
  "geometry": {"coordinates":[9.4076833725,47.3314361572],"type":"Point"}
}