{
  "type": "Feature",
  "properties": {
    "iso:country":"CH",
    "sg:address":"Eichmatt",
    "sg:city":"Schwarzenburg",
    "sg:orig_category":"S\u00e4ge, Hobel U Holzimpr\u00e4gnierwerke",
    "sg:phone":"+41 31 731 20 81",
    "sg:postcode":"3150",
    "sg:province":"Bern",
    "wof:name":"Nydegger Walter",
    "wof:placetype":"venue"
},
  "geometry": {"coordinates":[7.3527169228,46.8267326355],"type":"Point"}
}