{
  "type": "Feature",
  "properties": {
    "iso:country":"CH",
    "sg:address":"Via Selva 8",
    "sg:city":"Massagno",
    "sg:orig_category":"Unclassifiable Establishments",
    "sg:postcode":"6900",
    "sg:province":"Ticino",
    "wof:name":"Bio-brisk Di Roberto Bruzzone",
    "wof:placetype":"venue"
},
  "geometry": {"coordinates":[8.9482126236,46.0126686096],"type":"Point"}
}