{
  "type": "Feature",
  "properties": {
    "iso:country":"CH",
    "sg:address":"Seestrasse 128",
    "sg:city":"W\u00e4denswil",
    "sg:orig_category":"Detailhandel mit Schuhen Detailhandel mit medizinischen U orthop\u00e4dischen Artikeln",
    "sg:phone":"+41 17809980",
    "sg:postcode":"8820",
    "sg:province":"Z\u00fcrich",
    "wof:name":"Normann Egger Orthop\u00e4die Sanit\u00e4tshaus",
    "wof:placetype":"venue"
},
  "geometry": {"coordinates":[8.6735830307,47.2307281494],"type":"Point"}
}