{
  "type": "Feature",
  "properties": {
    "iso:country":"CH",
    "sg:address":"6312 Steinhausen. Postfach 4",
    "sg:city":"Steinhausen",
    "sg:orig_category":"Politische Parteien Freiheits-Partei Schweiz",
    "sg:phone":"+41 41 760 06 88",
    "sg:postcode":"6312",
    "sg:province":"Zug",
    "wof:name":"Fps Kanton Zug",
    "wof:placetype":"venue"
},
  "geometry": {"coordinates":[8.4846382141,47.1969032288],"type":"Point"}
}