{
  "type": "Feature",
  "properties": {
    "iso:country":"CH",
    "sg:address":"Klotenerstrasse 72 8303 Bassersdorf. Postfach",
    "sg:city":"Kloten",
    "sg:orig_category":"Instandhaltung U Reparatur von Automobilen",
    "sg:phone":"+41 18130788",
    "sg:postcode":"8302",
    "sg:province":"Z\u00fcrich",
    "wof:name":"Flug-garage Ag",
    "wof:placetype":"venue"
},
  "geometry": {"coordinates":[8.6234636307,47.4449996948],"type":"Point"}
}