{
  "type": "Feature",
  "properties": {
    "iso:country":"CH",
    "sg:address":"Talacherstrasse 11",
    "sg:city":"Baar",
    "sg:orig_category":"Elektroinstallation",
    "sg:phone":"+41 56 622 17 24",
    "sg:postcode":"6340",
    "sg:province":"Zug",
    "wof:name":"Melliger Max",
    "wof:placetype":"venue"
},
  "geometry": {"coordinates":[8.2740831375,47.3466644287],"type":"Point"}
}