{
  "type": "Feature",
  "properties": {
    "iso:country":"CH",
    "sg:address":"Rebweg 3",
    "sg:city":"H\u00fcttikon",
    "sg:orig_category":"Detailhandel mit Uhren U Schmuck",
    "sg:phone":"+41 79 247 85 60",
    "sg:postcode":"8115",
    "sg:province":"Z\u00fcrich",
    "wof:name":"Gadee Amsler Goldschmiedatelier",
    "wof:placetype":"venue"
},
  "geometry": {"coordinates":[8.3886976242,47.4443511963],"type":"Point"}
}