{
  "type": "Feature",
  "properties": {
    "iso:country":"CH",
    "sg:address":"Im Dorf 8",
    "sg:city":"Thun",
    "sg:orig_category":"Detailhandel mit Brot, Back U S\u00fcsswaren",
    "sg:phone":"+41 33 336 36 80",
    "sg:postcode":"3608",
    "sg:province":"Bern",
    "wof:name":"Werner Krebs",
    "wof:placetype":"venue"
},
  "geometry": {"coordinates":[7.596135,46.742012],"type":"Point"}
}