{
  "type": "Feature",
  "properties": {
    "iso:country":"CH",
    "sg:address":"Marktplatz 2",
    "sg:city":"Basel",
    "sg:orig_category":"Non-Classified Establishments",
    "sg:phone":"+41 61 262 00 02",
    "sg:postcode":"4001",
    "sg:province":"Basel-Stadt",
    "wof:name":"Brezelk\u00f6nig N. Veapi",
    "wof:placetype":"venue"
},
  "geometry": {"coordinates":[7.5878272057,47.5586166382],"type":"Point"}
}