{
  "type": "Feature",
  "properties": {
    "addr:full":"Im M\u00fchlegarten 2a Ettingen Basel-Landschaft 4107",
    "addr:housenumber":"2a",
    "addr:postcode":"4107",
    "addr:street":"Im Muehlegarten",
    "iso:country":"CH",
    "sg:address":"Im M\u00fchlegarten 2a",
    "sg:city":"Ettingen",
    "sg:orig_category":"Architektur U Ingenieurb\u00fcros Architekturb\u00fcros",
    "sg:phone":"+41 61 721 43 96",
    "sg:postcode":"4107",
    "sg:province":"Basel-Landschaft",
    "wof:name":"Lachat A. Ag, Architekturb\u00fcro",
    "wof:placetype":"venue"
},
  "geometry": {"coordinates":[7.544688,47.47863],"type":"Point"}
}