{
  "type": "Feature",
  "properties": {
    "iso:country":"CH",
    "sg:address":"Hauptstrasse 3780 Gruben B. Gstaad. Postfach",
    "sg:city":"Gstaad",
    "sg:orig_category":"RESTAURANTS: TEA-ROOMS",
    "sg:postcode":"3780",
    "sg:province":"Bern",
    "wof:name":"Pernet C. + R. Ag",
    "wof:placetype":"venue"
},
  "geometry": {"coordinates":[7.2864098549,46.4733848572],"type":"Point"}
}