{
  "type": "Feature",
  "properties": {
    "iso:country":"CH",
    "sg:address":"H\u00fcnkelerweg 12",
    "sg:city":"F\u00fcllinsdorf",
    "sg:orig_category":"Massagestudios",
    "sg:phone":"+41 17618962",
    "sg:postcode":"4414",
    "sg:province":"Basel-Landschaft",
    "wof:name":"Massagepraxis Sunnehus",
    "wof:placetype":"venue"
},
  "geometry": {"coordinates":[8.4476108551,47.2763023376],"type":"Point"}
}