{
  "type": "Feature",
  "properties": {
    "iso:country":"CH",
    "sg:address":"Bahnhofstrasse 12",
    "sg:city":"Ostermundigen",
    "sg:orig_category":"Detailhandel mit Brot, Back U S\u00fcsswaren",
    "sg:phone":"+41 31 931 13 53",
    "sg:postcode":"3072",
    "sg:province":"Bern",
    "wof:name":"Marc Michel Feinb\u00e4ckerei-konditorei",
    "wof:placetype":"venue"
},
  "geometry": {"coordinates":[7.484341,46.954887],"type":"Point"}
}