{
  "type": "Feature",
  "properties": {
    "iso:country":"CH",
    "sg:address":"Renzligenstrasse 3b",
    "sg:city":"Wikon",
    "sg:orig_category":"Primarschulen",
    "sg:phone":"+41 62 752 20 42",
    "sg:postcode":"4806",
    "sg:province":"Luzern",
    "wof:name":"Primarschule",
    "wof:placetype":"venue"
},
  "geometry": {"coordinates":[7.9701800346,47.2627563477],"type":"Point"}
}