{
  "type": "Feature",
  "properties": {
    "iso:country":"CH",
    "sg:address":"Unterdorf 12",
    "sg:city":"Bauma",
    "sg:orig_category":"Tierheime",
    "sg:phone":"+41 52 386 21 79",
    "sg:postcode":"8494",
    "sg:province":"Z\u00fcrich",
    "wof:name":"Karl Bleuler Hundeheim",
    "wof:placetype":"venue"
},
  "geometry": {"coordinates":[8.8753099442,47.36876297],"type":"Point"}
}