{
  "type": "Feature",
  "properties": {
    "iso:country":"CH",
    "sg:address":"Abernstrasse 11",
    "sg:city":"Tann",
    "sg:orig_category":"Grosshandel mit B\u00fcromaschinen Grosshandel mit Datenverarbeitungsger\u00e4ten",
    "sg:phone":"+41 41 630 26 26",
    "sg:postcode":"8632",
    "sg:province":"Z\u00fcrich",
    "wof:name":"Websun Ag",
    "wof:placetype":"venue"
},
  "geometry": {"coordinates":[8.3091106415,46.9968795776],"type":"Point"}
}