{
  "type": "Feature",
  "properties": {
    "iso:country":"CH",
    "sg:address":"Pr\u00e9laz Chemin De 24",
    "sg:city":"Nyon",
    "sg:orig_category":"Sonstiger Grosshandel",
    "sg:phone":"+41 22 361 36 82",
    "sg:postcode":"1260",
    "sg:province":"Vaud",
    "wof:name":"Gasser Denis Gfg-romandie",
    "wof:placetype":"venue"
},
  "geometry": {"coordinates":[6.2390799522,46.3823661804],"type":"Point"}
}