{
  "type": "Feature",
  "properties": {
    "iso:country":"CH",
    "sg:address":"Horben 3755 Horboden. Postfach",
    "sg:city":"Horboden",
    "sg:orig_category":"Zimmerei, Dachdeckerei, Bauspenglerei U Abdichtung",
    "sg:postcode":"3755",
    "sg:province":"Bern",
    "wof:name":"Wiedmer Holzbau Ag",
    "wof:placetype":"venue"
},
  "geometry": {"coordinates":[7.5608119965,46.6320457458],"type":"Point"}
}