{
  "type": "Feature",
  "properties": {
    "iso:country":"CH",
    "sg:address":"Oberweid 5",
    "sg:city":"Inwil",
    "sg:orig_category":"Sonstige Institutionen des Sozialwesens ohne Beherbergung",
    "sg:phone":"+41 41 448 29 05",
    "sg:postcode":"6034",
    "sg:province":"Luzern",
    "wof:name":"Maria Kreienb\u00fchl M\u00fctterberatung",
    "wof:placetype":"venue"
},
  "geometry": {"coordinates":[8.3485555649,47.1248512268],"type":"Point"}
}