{
  "type": "Feature",
  "properties": {
    "iso:country":"CH",
    "sg:address":"Stauffacherstrasse 77",
    "sg:city":"Bern",
    "sg:orig_category":"Allgemeiner Hochbau Strassenbau",
    "sg:phone":"+41 31 333 06 13",
    "sg:postcode":"3014",
    "sg:province":"Bern",
    "wof:name":"Aeschlimann Ag Strassenbau & Asphaltierungen",
    "wof:placetype":"venue"
},
  "geometry": {"coordinates":[7.457865,46.966774],"type":"Point"}
}