{
  "type": "Feature",
  "properties": {
    "iso:country":"CH",
    "sg:address":"Industriestrasse 15",
    "sg:city":"Chur",
    "sg:orig_category":"Sanit\u00e4r, Heizungs U L\u00fcftungsinstallation Sanit\u00e4rinstallation",
    "sg:phone":"+41 81 284 64 24",
    "sg:postcode":"7000",
    "sg:province":"Graubunden",
    "wof:name":"Sanit\u00e4r Pl\u00fcss Ag",
    "wof:placetype":"venue"
},
  "geometry": {"coordinates":[9.5097894669,46.8564682007],"type":"Point"}
}