{
  "type": "Feature",
  "properties": {
    "iso:country":"CH",
    "sg:address":"Corso San Gottardo 32 6830 Chiasso. Postfach",
    "sg:city":"Chiasso",
    "sg:orig_category":"Grosshandel mit Holz U Baustoffen",
    "sg:postcode":"6830",
    "sg:province":"Ticino",
    "wof:name":"Legnoser Sagl",
    "wof:placetype":"venue"
},
  "geometry": {"coordinates":[9.0298786163,45.8341331482],"type":"Point"}
}