{
  "type": "Feature",
  "properties": {
    "iso:country":"CH",
    "sg:address":"Breitenstrasse 25",
    "sg:city":"Fulenbach",
    "sg:orig_category":"Bau U Wohngenossenschaften",
    "sg:phone":"+41 62 926 19 82",
    "sg:postcode":"4629",
    "sg:province":"Solothurn",
    "wof:name":"Wohnbaugen.holzbeerli Fulenb.",
    "wof:placetype":"venue"
},
  "geometry": {"coordinates":[7.836456,47.273941],"type":"Point"}
}