{
  "type": "Feature",
  "properties": {
    "iso:country":"CH",
    "sg:address":"Via Al Lago 46",
    "sg:city":"Barbengo",
    "sg:orig_category":"Vermietung U Verpachtung von eigenen Immobilien",
    "sg:postcode":"6917",
    "sg:province":"Ticino",
    "wof:name":"Orello Immobiliare Sa",
    "wof:placetype":"venue"
},
  "geometry": {"coordinates":[8.9250659943,45.9669761658],"type":"Point"}
}