{
  "type": "Feature",
  "properties": {
    "iso:country":"CH",
    "sg:address":"In Den Neusatzreben 8",
    "sg:city":"Pratteln",
    "sg:orig_category":"Unclassifiable Establishments",
    "sg:postcode":"4133",
    "sg:province":"Basel-Landschaft",
    "wof:name":"Mustafa Bostan, Handel Mit Waren Aller Art",
    "wof:placetype":"venue"
},
  "geometry": {"coordinates":[7.7102918625,47.5230026245],"type":"Point"}
}