{
  "type": "Feature",
  "properties": {
    "iso:country":"CH",
    "sg:address":"Schulhausstrasse 22",
    "sg:city":"Ebikon",
    "sg:orig_category":"Bezirks, Sekundar, Realschulen, Oberstufe der Primarschulen",
    "sg:phone":"+41 41 440 12 22",
    "sg:postcode":"6030",
    "sg:province":"Luzern",
    "wof:name":"Oberstufenschule Wydenhof",
    "wof:placetype":"venue"
},
  "geometry": {"coordinates":[8.339964,47.079815],"type":"Point"}
}