{
  "type": "Feature",
  "properties": {
    "iso:country":"CH",
    "sg:address":"Buochserstrasse 70",
    "sg:city":"Beckenried",
    "sg:orig_category":"Fachdetailhandel in Verkaufsr\u00e4umen Kunsthandel",
    "sg:phone":"+41 41 622 04 50",
    "sg:postcode":"6375",
    "sg:province":"Nidwalden",
    "wof:name":"Galerie Ruf Ag",
    "wof:placetype":"venue"
},
  "geometry": {"coordinates":[8.4565649033,46.9712371826],"type":"Point"}
}