{
  "type": "Feature",
  "properties": {
    "iso:country":"CH",
    "sg:address":"Luzernerstrasse 147",
    "sg:city":"Littau",
    "sg:orig_category":"Druck ohne Zeitungsdruck",
    "sg:phone":"+41 41 360 96 42",
    "sg:postcode":"6014",
    "sg:province":"Luzern",
    "wof:name":"Apag Ag",
    "wof:placetype":"venue"
},
  "geometry": {"coordinates":[8.2610845566,47.0491065979],"type":"Point"}
}