{
  "type": "Feature",
  "properties": {
    "iso:country":"CH",
    "sg:address":"Schellenbergstrasse 4",
    "sg:city":"Herdern",
    "sg:orig_category":"Unclassifiable Establishments",
    "sg:postcode":"8535",
    "sg:province":"Thurgau",
    "wof:name":"Lms-media Gmbh",
    "wof:placetype":"venue"
},
  "geometry": {"coordinates":[8.9071435928,47.6070823669],"type":"Point"}
}