{
  "type": "Feature",
  "properties": {
    "iso:country":"CH",
    "sg:address":"Centrale Rue 5",
    "sg:city":"Lausanne",
    "sg:orig_category":"Unclassifiable Establishments",
    "sg:phone":"+41 21 318 82 82",
    "sg:postcode":"1003",
    "sg:province":"Vaud",
    "wof:name":"Si Mon Repos-beau Site D",
    "wof:placetype":"venue"
},
  "geometry": {"coordinates":[6.6323571205,46.5207176208],"type":"Point"}
}