{
  "type": "Feature",
  "properties": {
    "iso:country":"CH",
    "sg:address":"8355 Aadorf. Postfach 302",
    "sg:city":"Aadorf",
    "sg:orig_category":"Sportvereine Triathlon Laufen, Schwimmen, Velo",
    "sg:postcode":"8355",
    "sg:province":"Thurgau",
    "wof:name":"Triathlon Team Aadorf",
    "wof:placetype":"venue"
},
  "geometry": {"coordinates":[8.9033498764,47.4896583557],"type":"Point"}
}