{
  "type": "Feature",
  "properties": {
    "iso:country":"CH",
    "sg:address":"Zollfreilager Embraport 8424 Embrach. Postfach 89",
    "sg:city":"Embrach",
    "sg:orig_category":"Detailhandel mit M\u00f6beln U Haushaltsgegenst\u00e4nden",
    "sg:phone":"+41 18662929",
    "sg:postcode":"8424",
    "sg:province":"Z\u00fcrich",
    "wof:name":"Hemag Orientteppichimport Ag",
    "wof:placetype":"venue"
},
  "geometry": {"coordinates":[8.5935716629,47.506690979],"type":"Point"}
}