{
  "type": "Feature",
  "properties": {
    "iso:country":"CH",
    "sg:address":"Hirsackerstrasse 84",
    "sg:city":"Horgen",
    "sg:orig_category":"Detailhandel Handel mit Motorr\u00e4dern, Teilen U Zubeh\u00f6r Instandhaltung U Reparatur von Motorr\u00e4dern Rep",
    "sg:phone":"+41 56 633 02 42",
    "sg:postcode":"8810",
    "sg:province":"Z\u00fcrich",
    "wof:name":"Caprez-motorsport",
    "wof:placetype":"venue"
},
  "geometry": {"coordinates":[8.3305883408,47.3542137146],"type":"Point"}
}