{
  "type": "Feature",
  "properties": {
    "iso:country":"CH",
    "sg:address":"Route Des Alpes 3 1470 Estavayer-le-lac. Postfach",
    "sg:city":"Estavayer-le-lac",
    "sg:orig_category":"Alters U Pflegeheime Gesundheitswesen",
    "sg:phone":"+41 26 663 50 50",
    "sg:postcode":"1470",
    "sg:province":"Fribourg",
    "wof:name":"Etablissement M\u00e9dico-social La Croix De Pierre",
    "wof:placetype":"venue"
},
  "geometry": {"coordinates":[6.854258,46.843613],"type":"Point"}
}