{
  "type": "Feature",
  "properties": {
    "iso:country":"CH",
    "sg:address":"Chevrier Route De 32",
    "sg:city":"Choulex",
    "sg:orig_category":"Allgemeiner Hoch U Tiefbau",
    "sg:postcode":"1244",
    "sg:province":"Gen\u00e8ve",
    "wof:name":"Guex Sa",
    "wof:placetype":"venue"
},
  "geometry": {"coordinates":[6.2244,46.223282],"type":"Point"}
}