{
  "type": "Feature",
  "properties": {
    "iso:country":"CH",
    "sg:address":"Kirchmattstrasse 48",
    "sg:city":"Riggisberg",
    "sg:orig_category":"Politische Parteien FDP",
    "sg:phone":"+41 31 809 06 69",
    "sg:postcode":"3132",
    "sg:province":"Bern",
    "wof:name":"Fdp Ortspartei Riggisberg",
    "wof:placetype":"venue"
},
  "geometry": {"coordinates":[7.4839720726,46.8107147217],"type":"Point"}
}