{
  "type": "Feature",
  "properties": {
    "iso:country":"CH",
    "sg:address":"San Cassiano",
    "sg:city":"Vicosoprano",
    "sg:orig_category":"Architektur U Ingenieurb\u00fcros Mechanische Werkst\u00e4tten",
    "sg:phone":"+41 81 822 13 92",
    "sg:postcode":"7603",
    "sg:province":"Graubunden",
    "wof:name":"Keller Alfred",
    "wof:placetype":"venue"
},
  "geometry": {"coordinates":[9.620166,46.352215],"type":"Point"}
}