{
  "type": "Feature",
  "properties": {
    "iso:country":"CH",
    "sg:address":"Chemin De La Gu\u00e9rite",
    "sg:city":"Lucens",
    "sg:orig_category":"Bauschreinerei Herstellung von Konstruktionsteilen, Fertigbauteilen U Ausbauelementen aus Holz",
    "sg:phone":"+41 81 325 17 46",
    "sg:postcode":"1522",
    "sg:province":"Vaud",
    "wof:name":"Aebli Hansj\u00f6rg",
    "wof:placetype":"venue"
},
  "geometry": {"coordinates":[9.638091,46.989906],"type":"Point"}
}