{
  "type": "Feature",
  "properties": {
    "iso:country":"CH",
    "sg:address":"Unterbiel 45",
    "sg:city":"Reigoldswil",
    "sg:orig_category":"Aktivit\u00e4ten der Krankenschwestern U Hebammen, Hauspflege Organisationen des Gesundheitswesen",
    "sg:phone":"+41 61 941 18 08",
    "sg:postcode":"4418",
    "sg:province":"Basel-Landschaft",
    "wof:name":"Spitex Hinteres Frenkental Haus-& Krankenpflege",
    "wof:placetype":"venue"
},
  "geometry": {"coordinates":[7.690549,47.400578],"type":"Point"}
}