{
  "type": "Feature",
  "properties": {
    "iso:country":"CH",
    "sg:address":"Bahnhofstrasse 9",
    "sg:city":"Lyss",
    "sg:classifiers":[
        {
            "category":"Professional",
            "subcategory":"Business Services",
            "type":"Services"
        }
    ],
    "sg:phone":"+41 32 332 84 52",
    "sg:postcode":"3250",
    "sg:province":"Bern",
    "sg:tags":[
        "marketing",
        "consulting"
    ],
    "wof:name":"Heribert Kuhn Ag",
    "wof:placetype":"venue"
},
  "geometry": {"coordinates":[7.3059840202,47.0757522583],"type":"Point"}
}