{
  "type": "Feature",
  "properties": {
    "iso:country":"CH",
    "sg:address":"Rebgasse 40",
    "sg:city":"Grenchen",
    "sg:orig_category":"Herstellung von Kunststoffwaren Herstellung von Werkzeugen",
    "sg:phone":"+41 32 653 34 01",
    "sg:postcode":"2540",
    "sg:province":"Solothurn",
    "wof:name":"Aubry Tools",
    "wof:placetype":"venue"
},
  "geometry": {"coordinates":[7.3959751129,47.2007865906],"type":"Point"}
}