{
  "type": "Feature",
  "properties": {
    "iso:country":"CH",
    "sg:address":"Unterfeldweg 15",
    "sg:city":"Lyss",
    "sg:orig_category":"Allgemeiner Hoch U Tiefbau",
    "sg:phone":"+41 79 214 59 14",
    "sg:postcode":"3250",
    "sg:province":"Bern",
    "wof:name":"M\u00fcller Bauspezialit\u00e4ten",
    "wof:placetype":"venue"
},
  "geometry": {"coordinates":[7.306261,47.07832],"type":"Point"}
}