{
  "type": "Feature",
  "properties": {
    "iso:country":"CH",
    "sg:address":"Valenistrasse 6",
    "sg:city":"Mels",
    "sg:orig_category":"Arztpraxen",
    "sg:phone":"+41 81 723 68 68",
    "sg:postcode":"8887",
    "sg:province":"St. Gallen",
    "wof:name":"Dr.med.christian Himmelberger Arzt F.allgemeine Medizin Fmh",
    "wof:placetype":"venue"
},
  "geometry": {"coordinates":[9.421577,47.050495],"type":"Point"}
}