{
  "type": "Feature",
  "properties": {
    "iso:country":"CH",
    "sg:address":"3928",
    "sg:city":"Randa",
    "sg:orig_category":"Zimmerei, Dachdeckerei, Bauspenglerei U Abdichtung",
    "sg:phone":"+41 27 956 12 38",
    "sg:postcode":"3928",
    "sg:province":"Valais",
    "wof:name":"Brantschen Gebr. Manfred & Marcel, Zimmerei",
    "wof:placetype":"venue"
},
  "geometry": {"coordinates":[7.7803549767,46.0985984802],"type":"Point"}
}