{
  "type": "Feature",
  "properties": {
    "iso:country":"CH",
    "sg:address":"Chauchy Chemin Du 7",
    "sg:city":"St-prex",
    "sg:orig_category":"Non-Classified Establishments",
    "sg:postcode":"1162",
    "sg:province":"Vaud",
    "wof:name":"Ideal Digital Gmbh",
    "wof:placetype":"venue"
},
  "geometry": {"coordinates":[9.348400116,47.4122657776],"type":"Point"}
}