{
  "type": "Feature",
  "properties": {
    "iso:country":"CH",
    "sg:address":"Stafflerstrasse 36 Hermetschwil 5626 Hermetschwil-staff. Postfach",
    "sg:city":"Hermetschwil-staff",
    "sg:orig_category":"Detektivb\u00fcros U \u00dcberwachung",
    "sg:postcode":"5626",
    "sg:province":"Aargau",
    "wof:name":"Security Point Karli Spk",
    "wof:placetype":"venue"
},
  "geometry": {"coordinates":[8.3433246613,47.3322257996],"type":"Point"}
}