{
  "type": "Feature",
  "properties": {
    "iso:country":"CH",
    "sg:address":"Gartematt 5",
    "sg:city":"B\u00fclach",
    "sg:classifiers":[
        {
            "category":"Insurance",
            "subcategory":"Insurance Agent",
            "type":"Services"
        }
    ],
    "sg:phone":"+41 18620300",
    "sg:postcode":"8180",
    "sg:province":"Z\u00fcrich",
    "sg:tags":[
        "versicherungsagenturen",
        "-broker"
    ],
    "wof:name":"Waadt Versicherungen Agentur",
    "wof:placetype":"venue"
},
  "geometry": {"coordinates":[8.5428819656,47.518447876],"type":"Point"}
}