{
  "type": "Feature",
  "properties": {
    "iso:country":"CH",
    "sg:address":"1937",
    "sg:city":"Orsi\u00e8res",
    "sg:orig_category":"Fussboden, Fliesen U Plattenlegerei, Tapeziererei",
    "sg:postcode":"1937",
    "sg:province":"Valais",
    "wof:name":"Volkart Heinz Ag St. Moritz",
    "wof:placetype":"venue"
},
  "geometry": {"coordinates":[9.8381910324,46.4970664978],"type":"Point"}
}