{
  "type": "Feature",
  "properties": {
    "iso:country":"CH",
    "sg:address":"Graben 4",
    "sg:city":"Zug",
    "sg:orig_category":"Benzin, Heiz\u00f6l and Mineral\u00f6lprodukte Grosshandel Herstellung von sonstigen chemischen Erzeugnissen",
    "sg:phone":"+41 41 720 20 80",
    "sg:postcode":"6300",
    "sg:province":"Zug",
    "wof:name":"Petrochem Carless Ag",
    "wof:placetype":"venue"
},
  "geometry": {"coordinates":[8.51659,47.167271],"type":"Point"}
}