{
  "type": "Feature",
  "properties": {
    "iso:country":"CH",
    "sg:address":"Via Antonio Ciseri 3",
    "sg:city":"Locarno",
    "sg:orig_category":"Reiseb\u00fcros U Reiseveranstalter",
    "sg:phone":"+41 91 752 34 50",
    "sg:postcode":"6600",
    "sg:province":"Ticino",
    "wof:name":"Professional Incoming Di Lombardi Claudia",
    "wof:placetype":"venue"
},
  "geometry": {"coordinates":[8.8004741669,46.16929245],"type":"Point"}
}