{
  "type": "Feature",
  "properties": {
    "iso:country":"CH",
    "sg:address":"Bouveries Chemin Des 29",
    "sg:city":"Chancy",
    "sg:orig_category":"Reiseb\u00fcros U Reiseveranstalter",
    "sg:phone":"+41 22 756 10 39",
    "sg:postcode":"1284",
    "sg:province":"Gen\u00e8ve",
    "wof:name":"Bruns Edith, Coordination Voyages",
    "wof:placetype":"venue"
},
  "geometry": {"coordinates":[5.9726748466,46.1494407654],"type":"Point"}
}