{
  "type": "Feature",
  "properties": {
    "iso:country":"CH",
    "sg:address":"Rue Des Rangiers 12",
    "sg:city":"Saignel\u00e9gier",
    "sg:classifiers":[
        {
            "category":"Retail",
            "subcategory":"Repair Shop",
            "type":"Services"
        }
    ],
    "sg:phone":"+41 32 951 13 88",
    "sg:postcode":"2350",
    "sg:province":"Jura",
    "sg:tags":[
        "workshop",
        "mechanical"
    ],
    "wof:name":"Migatec Sa",
    "wof:placetype":"venue"
},
  "geometry": {"coordinates":[6.9990558624,47.2577400208],"type":"Point"}
}