{
  "type": "Feature",
  "properties": {
    "iso:country":"CH",
    "sg:address":"3976 No\u00ebs. Postfach",
    "sg:city":"No\u00ebs",
    "sg:orig_category":"Dauerkulturbau",
    "sg:phone":"+41 27 456 53 40",
    "sg:postcode":"3976",
    "sg:province":"Valais",
    "wof:name":"Cave Du Vieux Village Monnet S\u00e0rl",
    "wof:placetype":"venue"
},
  "geometry": {"coordinates":[7.50538,46.280849],"type":"Point"}
}