{
  "type": "Feature",
  "properties": {
    "iso:country":"CH",
    "sg:address":"S\u00e4gewiesstrasse 7",
    "sg:city":"Heiden",
    "sg:orig_category":"Zahnarztpraxen",
    "sg:phone":"+41 19306616",
    "sg:postcode":"9410",
    "sg:province":"Appenzell Ausserrhoden",
    "wof:name":"Dr. Med. Dent. Willy Kunz Zahnarzt",
    "wof:placetype":"venue"
},
  "geometry": {"coordinates":[8.793258667,47.3277053833],"type":"Point"}
}