{
  "type": "Feature",
  "properties": {
    "iso:country":"CH",
    "sg:address":"Leuzingenweg 5",
    "sg:city":"Netstal",
    "sg:orig_category":"Dachdeckerei Zimmerei, Dachdeckerei, Bauspenglerei U Abdichtung",
    "sg:phone":"+41 55 640 11 29",
    "sg:postcode":"8754",
    "sg:province":"Glarus",
    "wof:name":"Forrer Bedachungen Ag",
    "wof:placetype":"venue"
},
  "geometry": {"coordinates":[9.059069,47.060604],"type":"Point"}
}