{
  "type": "Feature",
  "properties": {
    "iso:country":"CH",
    "sg:address":"Madinis",
    "sg:city":"Fideris",
    "sg:orig_category":"Herstellung von Konstruktionsteilen, Fertigbauteilen U Ausbauelementen aus Holz",
    "sg:phone":"+41 81 332 28 17",
    "sg:postcode":"7235",
    "sg:province":"Graubunden",
    "wof:name":"Rws Rudolf Walli-simmen",
    "wof:placetype":"venue"
},
  "geometry": {"coordinates":[9.7474565506,46.9160728455],"type":"Point"}
}