{
  "type": "Feature",
  "properties": {
    "iso:country":"CH",
    "sg:address":"Neuveville Rue De La 24",
    "sg:city":"Fribourg",
    "sg:orig_category":"Unternehmensberatung",
    "sg:phone":"+41 61 411 32 11",
    "sg:postcode":"1700",
    "sg:province":"Fribourg",
    "wof:name":"B\u00fchler Marketing",
    "wof:placetype":"venue"
},
  "geometry": {"coordinates":[7.6197938919,47.5284843445],"type":"Point"}
}