{
  "type": "Feature",
  "properties": {
    "iso:country":"CH",
    "sg:address":"Elisabethenanlage 11",
    "sg:city":"Basel",
    "sg:orig_category":"Unclassifiable Establishments",
    "sg:phone":"+41 61 278 96 00",
    "sg:postcode":"4051",
    "sg:province":"Basel-Stadt",
    "wof:name":"Otp Holding Ag",
    "wof:placetype":"venue"
},
  "geometry": {"coordinates":[7.5885748863,47.5489883423],"type":"Point"}
}