{
  "type": "Feature",
  "properties": {
    "iso:country":"CH",
    "sg:address":"Neudorfstrasse",
    "sg:city":"Thusis",
    "sg:orig_category":"RESTAURANTS: TEA-ROOMS",
    "sg:postcode":"7430",
    "sg:province":"Graubunden",
    "wof:name":"G. Kunfermann",
    "wof:placetype":"venue"
},
  "geometry": {"coordinates":[9.4395151138,46.6937904358],"type":"Point"}
}