{
  "type": "Feature",
  "properties": {
    "iso:country":"CH",
    "sg:address":"Ziegelmattweg 2",
    "sg:city":"Diegten",
    "sg:orig_category":"Grosshandel mit Parf\u00fcmerieartikeln U K\u00f6rperpflegemitteln Grosshandel mit chemischen Erzeugnissen",
    "sg:phone":"+41 61 971 63 61",
    "sg:postcode":"4457",
    "sg:province":"Basel-Landschaft",
    "wof:name":"Bc-agentur Reinigungs-& Pflegeprodukte",
    "wof:placetype":"venue"
},
  "geometry": {"coordinates":[7.8082242012,47.4077529907],"type":"Point"}
}