{
  "type": "Feature",
  "properties": {
    "iso:country":"CH",
    "sg:address":"In B\u00e4chlere 6",
    "sg:city":"D\u00e4llikon",
    "sg:orig_category":"Architektur U Ingenieurb\u00fcros",
    "sg:phone":"+41 33 437 89 24",
    "sg:postcode":"8108",
    "sg:province":"Z\u00fcrich",
    "wof:name":"Hans-peter Ryf",
    "wof:placetype":"venue"
},
  "geometry": {"coordinates":[7.65045,46.79612],"type":"Point"}
}