{
  "type": "Feature",
  "properties": {
    "iso:country":"CH",
    "sg:address":"Alte Bahnhofstrasse 23",
    "sg:city":"Schwerzenbach",
    "sg:orig_category":"Herstellung von Elektromotoren, Generatoren U Transformatoren",
    "sg:phone":"+41 18254222",
    "sg:postcode":"8603",
    "sg:province":"Z\u00fcrich",
    "wof:name":"F\u00fcrst + Z\u00fcnd Industrie-elektro Gmbh",
    "wof:placetype":"venue"
},
  "geometry": {"coordinates":[8.6588754654,47.3832397461],"type":"Point"}
}