{
  "type": "Feature",
  "properties": {
    "iso:country":"CH",
    "sg:address":"Via Pobbiette 6928 Manno. Postfach",
    "sg:city":"Manno",
    "sg:orig_category":"Non-Classified Establishments",
    "sg:postcode":"6928",
    "sg:province":"Ticino",
    "wof:name":"Iteco Contract Sagl Arredi Su Progetto; Import., Esport. Ecc",
    "wof:placetype":"venue"
},
  "geometry": {"coordinates":[8.9240379333,46.0319595337],"type":"Point"}
}