{
  "type": "Feature",
  "properties": {
    "iso:country":"CH",
    "sg:address":"Bahnhofstrasse 15",
    "sg:city":"Grossh\u00f6chstetten",
    "sg:orig_category":"Sonstige mit der Informatik verbundene T\u00e4tigkeiten",
    "sg:postcode":"3506",
    "sg:province":"Bern",
    "wof:name":"Isc R\u00f6thlisberger + Co.",
    "wof:placetype":"venue"
},
  "geometry": {"coordinates":[7.6353340149,46.9044342041],"type":"Point"}
}