{
  "type": "Feature",
  "properties": {
    "iso:country":"CH",
    "sg:address":"Wassergasse 17a",
    "sg:city":"Solothurn",
    "sg:orig_category":"Ingenieurb\u00fcros Umwelttechnik and \u00d6kologie Technische, physikalische U chemische Untersuchung",
    "sg:phone":"+41 32 622 99 07",
    "sg:postcode":"4500",
    "sg:province":"Solothurn",
    "wof:name":"Bgf, Marrer Heinz, B\u00fcro F\u00fcr Gew\u00e4sser Und Fischereifragen Ag",
    "wof:placetype":"venue"
},
  "geometry": {"coordinates":[7.5420198441,47.1998252869],"type":"Point"}
}