{
  "type": "Feature",
  "properties": {
    "iso:country":"CH",
    "sg:address":"Haselweg 2",
    "sg:city":"H\u00e4gglingen",
    "sg:orig_category":"Wirtschaftsverb\u00e4nde Pressewirtschaft",
    "sg:phone":"+41 32 373 24 32",
    "sg:postcode":"5607",
    "sg:province":"Aargau",
    "wof:name":"Sportjournalistenvereinigung Biel & Umgebung",
    "wof:placetype":"venue"
},
  "geometry": {"coordinates":[7.2728757858,47.1255493164],"type":"Point"}
}