{
  "type": "Feature",
  "properties": {
    "iso:country":"CH",
    "sg:address":"Gotthardstrasse 37",
    "sg:city":"Andermatt",
    "sg:orig_category":"Detailhandel an Verkaufsst\u00e4nden U auf M\u00e4rkten",
    "sg:postcode":"6490",
    "sg:province":"Uri",
    "wof:name":"Huonder Claudia, Bazar.",
    "wof:placetype":"venue"
},
  "geometry": {"coordinates":[8.59596,46.635616],"type":"Point"}
}