{
  "type": "Feature",
  "properties": {
    "iso:country":"CH",
    "sg:address":"Erlenstrasse 34 4058 Basel. Postfach",
    "sg:city":"Basel",
    "sg:orig_category":"Herstellung von Werkzeugmaschinen",
    "sg:phone":"+41 61 692 28 56",
    "sg:postcode":"4021",
    "wof:name":"Winkler Elektrowerkzeuge Gmbh",
    "wof:placetype":"venue"
},
  "geometry": {"coordinates":[7.6004128456,47.5683174133],"type":"Point"}
}