{
  "type": "Feature",
  "properties": {
    "iso:country":"CH",
    "sg:address":"B\u00fctzenweg 10",
    "sg:city":"Zug",
    "sg:orig_category":"Unclassifiable Establishments",
    "sg:postcode":"6300",
    "sg:province":"Zug",
    "wof:name":"Zundra Invest Ag",
    "wof:placetype":"venue"
},
  "geometry": {"coordinates":[8.521062851,47.1577110291],"type":"Point"}
}