{
  "type": "Feature",
  "properties": {
    "iso:country":"CH",
    "sg:address":"Kr\u00e4mermatt 3",
    "sg:city":"Cham",
    "sg:orig_category":"Wirtschaftspr\u00fcfung, Steuerberatung U Treuhand",
    "sg:phone":"+41 41 780 04 09",
    "sg:postcode":"6330",
    "sg:province":"Zug",
    "wof:name":"Smu Consulting + Technik Gmbh",
    "wof:placetype":"venue"
},
  "geometry": {"coordinates":[8.4511098862,47.1803245544],"type":"Point"}
}