{
  "type": "Feature",
  "properties": {
    "iso:country":"CH",
    "sg:address":"Schlossergasse 2",
    "sg:city":"Hochdorf",
    "sg:orig_category":"Herstellung von sonstigen elektrischen Ausr\u00fcstungen",
    "sg:phone":"+41 41 397 22 55",
    "sg:postcode":"6280",
    "sg:province":"Luzern",
    "wof:name":"Mitra Gmbh Hochdorf",
    "wof:placetype":"venue"
},
  "geometry": {"coordinates":[8.2869300842,47.1708106995],"type":"Point"}
}