{
  "type": "Feature",
  "properties": {
    "iso:country":"CH",
    "sg:address":"Lindenmatt 4",
    "sg:city":"Illgau",
    "sg:orig_category":"Dachdeckerei Zimmerei, Dachdeckerei, Bauspenglerei U Abdichtung",
    "sg:phone":"+41 81 300 44 00",
    "sg:postcode":"6434",
    "sg:province":"Schwyz",
    "wof:name":"Burkhardt & Co",
    "wof:placetype":"venue"
},
  "geometry": {"coordinates":[9.500714,47.01387],"type":"Point"}
}