{
  "type": "Feature",
  "properties": {
    "iso:country":"CH",
    "sg:address":"Zurich Rue De 12 1201 Gen\u00e8ve. Postfach",
    "sg:city":"Gen\u00e8ve",
    "sg:orig_category":"Sonstiger Grosshandel",
    "sg:phone":"+41 22 738 77 37",
    "sg:postcode":"1201",
    "sg:province":"Gen\u00e8ve",
    "wof:name":"Les Cygnes Du Rh\u00f4ne",
    "wof:placetype":"venue"
},
  "geometry": {"coordinates":[6.1476979256,46.2115516663],"type":"Point"}
}