{
  "type": "Feature",
  "properties": {
    "iso:country":"CH",
    "sg:address":"Haarbachstrasse 12",
    "sg:city":"Winterthur",
    "sg:orig_category":"Architektur U Ingenieurb\u00fcros",
    "sg:postcode":"8400",
    "sg:province":"Z\u00fcrich",
    "wof:name":"Ligrufa Planteam Ag",
    "wof:placetype":"venue"
},
  "geometry": {"coordinates":[8.769065,47.487854],"type":"Point"}
}