{
  "type": "Feature",
  "properties": {
    "iso:country":"CH",
    "sg:address":"Herzogenm\u00fchlestrasse 53",
    "sg:city":"Z\u00fcrich",
    "sg:orig_category":"Primarschulen",
    "sg:postcode":"8051",
    "sg:province":"Z\u00fcrich",
    "wof:name":"Primarschule Ausserdorf",
    "wof:placetype":"venue"
},
  "geometry": {"coordinates":[8.075630188,47.3880691528],"type":"Point"}
}