{
  "type": "Feature",
  "properties": {
    "addr:full":"Silbergasse 9 Biel/bienne Bern 2502",
    "addr:housenumber":"9",
    "addr:postcode":"2502",
    "addr:street":"Silbergasse",
    "iso:country":"CH",
    "sg:address":"Silbergasse 9",
    "sg:city":"Biel/bienne",
    "sg:orig_category":"Arztpraxen",
    "sg:phone":"+41 32 322 26 24",
    "sg:postcode":"2502",
    "sg:province":"Bern",
    "wof:name":"Dr.med.marcel Stampfli Spezialarzt",
    "wof:placetype":"venue"
},
  "geometry": {"coordinates":[7.245711,47.13422],"type":"Point"}
}