{
  "type": "Feature",
  "properties": {
    "iso:country":"CH",
    "sg:address":"Z\u00fcrcherstrasse 229",
    "sg:city":"Dietikon",
    "sg:orig_category":"RESTAURANTS: TEA-ROOMS",
    "sg:phone":"+41 17423939",
    "sg:postcode":"8953",
    "sg:province":"Z\u00fcrich",
    "wof:name":"Restaurant Sch\u00f6nenwerd, Friedrich Holstein",
    "wof:placetype":"venue"
},
  "geometry": {"coordinates":[8.4270210266,47.3973503113],"type":"Point"}
}