{
  "type": "Feature",
  "properties": {
    "iso:country":"CH",
    "sg:address":"Rue De Fin-de-praz 5",
    "sg:city":"St-aubin-sauges",
    "sg:orig_category":"Pensionskassen",
    "sg:postcode":"2024",
    "sg:province":"Neuch\u00e2tel",
    "wof:name":"Fondation En Faveur Du Personnel De La Soci\u00e9t\u00e9 Beka St-aubin Sa.",
    "wof:placetype":"venue"
},
  "geometry": {"coordinates":[6.7789711952,46.8970069885],"type":"Point"}
}