{
  "type": "Feature",
  "properties": {
    "iso:country":"CH",
    "sg:address":"Laufenburgerstrasse 16/11",
    "sg:city":"Rheinfelden",
    "sg:orig_category":"Sanit\u00e4r U Heizungsinstallation Sanit\u00e4r, Heizungs U L\u00fcftungsinstallation",
    "sg:phone":"+41 41 930 35 30",
    "sg:postcode":"4310",
    "sg:province":"Aargau",
    "wof:name":"Comfortfloor Ag",
    "wof:placetype":"venue"
},
  "geometry": {"coordinates":[8.1508779526,47.225025177],"type":"Point"}
}