{
  "type": "Feature",
  "properties": {
    "iso:country":"CH",
    "sg:address":"Avenue De Chailly 7",
    "sg:city":"Lausanne",
    "sg:orig_category":"Nationale Postdienste",
    "sg:phone":"+41 21 616 33 07",
    "sg:postcode":"1012",
    "sg:province":"Vaud",
    "wof:name":"La Poste Suisse Lausanne 13 Jordils",
    "wof:placetype":"venue"
},
  "geometry": {"coordinates":[6.6287870407,46.5118904114],"type":"Point"}
}