{
  "type": "Feature",
  "properties": {
    "iso:country":"CH",
    "sg:address":"Via Quiete 17",
    "sg:city":"Viganello",
    "sg:orig_category":"Advokaturb\u00fcros",
    "sg:phone":"+41 91 971 28 75",
    "sg:postcode":"6962",
    "sg:province":"Ticino",
    "wof:name":"Orlando Taschetta Studio Legale",
    "wof:placetype":"venue"
},
  "geometry": {"coordinates":[8.972186,46.015312],"type":"Point"}
}