{
  "type": "Feature",
  "properties": {
    "iso:country":"CH",
    "sg:address":"Kanzleistrasse 117",
    "sg:city":"Z\u00fcrich",
    "sg:orig_category":"Grosshandel mit Textilien Grosshandel mit sonstigen Konsumg\u00fctern",
    "sg:phone":"+41 12403810",
    "sg:postcode":"8004",
    "sg:province":"Z\u00fcrich",
    "wof:name":"Themata Ag",
    "wof:placetype":"venue"
},
  "geometry": {"coordinates":[8.5211105347,47.3765563965],"type":"Point"}
}