{
  "type": "Feature",
  "properties": {
    "addr:full":"Merkurstrasse 12 Winterthur Z\u00fcrich 8400",
    "addr:housenumber":"12",
    "addr:postcode":"8400",
    "addr:street":"Merkurstrasse",
    "iso:country":"CH",
    "sg:address":"Merkurstrasse 12",
    "sg:city":"Winterthur",
    "sg:orig_category":"Internet, Alle Internetdienstleistungen",
    "sg:phone":"+41 52 212 44 54",
    "sg:postcode":"8400",
    "sg:province":"Z\u00fcrich",
    "wof:name":"Agenz Ingenieurunternehmung Gmbh",
    "wof:placetype":"venue"
},
  "geometry": {"coordinates":[8.726392,47.501644],"type":"Point"}
}