{
  "type": "Feature",
  "properties": {
    "iso:country":"CH",
    "sg:address":"Schynweg 9",
    "sg:city":"Emmetten",
    "sg:orig_category":"Interessenvertretungen",
    "sg:postcode":"6376",
    "sg:province":"Nidwalden",
    "wof:name":"Strassengenossenschaft Rietli",
    "wof:placetype":"venue"
},
  "geometry": {"coordinates":[8.5053768158,46.9564971924],"type":"Point"}
}