{
  "type": "Feature",
  "properties": {
    "iso:country":"CH",
    "sg:address":"Rue D'aarberg 37 2500 Biel/bienne. Postfach",
    "sg:city":"Biel/bienne",
    "sg:orig_category":"Detektivb\u00fcros U \u00dcberwachung",
    "sg:postcode":"2503",
    "sg:province":"Bern",
    "wof:name":"As Protect'service, Schmidt Patrick & Cie",
    "wof:placetype":"venue"
},
  "geometry": {"coordinates":[7.2393040657,47.1308288574],"type":"Point"}
}