{
  "type": "Feature",
  "properties": {
    "iso:country":"CH",
    "sg:address":"Unterer Planchesweg 9 2514 Ligerz. Postfach",
    "sg:city":"Ligerz",
    "sg:orig_category":"Fachdetailhandel in Verkaufsr\u00e4umen",
    "sg:phone":"+41 32 315 72 63",
    "sg:postcode":"2514",
    "sg:province":"Bern",
    "wof:name":"H.m.s. Hari's Motorboot Und Segelschule",
    "wof:placetype":"venue"
},
  "geometry": {"coordinates":[7.1428980827,47.0916290283],"type":"Point"}
}