{
  "type": "Feature",
  "properties": {
    "addr:full":"St\u00f6cklisrainstrasse 15 4654 Lostorf. Postfach 115 Lostorf Solothurn 4654",
    "addr:housenumber":"15;115",
    "addr:postcode":"4654 lostorf.;4654",
    "addr:street":"Stoecklisrainstrasse;Postfach;Lostorf Solothurn",
    "iso:country":"CH",
    "sg:address":"St\u00f6cklisrainstrasse 15 4654 Lostorf. Postfach 115",
    "sg:city":"Lostorf",
    "sg:orig_category":"Architektur U Ingenieurb\u00fcros",
    "sg:phone":"+41 62 298 14 44",
    "sg:postcode":"4654",
    "sg:province":"Solothurn",
    "wof:name":"Graber Gerhard, Architekturb\u00fcro",
    "wof:placetype":"venue"
},
  "geometry": {"coordinates":[7.93806,47.386127],"type":"Point"}
}