{
  "type": "Feature",
  "properties": {
    "iso:country":"CH",
    "sg:address":"Wies 14",
    "sg:city":"Speicher",
    "sg:orig_category":"Instandhaltung U Reparatur von Automobilen",
    "sg:phone":"+41 71 344 24 04",
    "sg:postcode":"9042",
    "sg:province":"Appenzell Ausserrhoden",
    "wof:name":"Garage E. Huber",
    "wof:placetype":"venue"
},
  "geometry": {"coordinates":[9.4478435516,47.4125404358],"type":"Point"}
}