{
  "type": "Feature",
  "properties": {
    "iso:country":"CH",
    "sg:address":"Seegartenstrasse 6",
    "sg:city":"Z\u00fcrich",
    "sg:orig_category":"Unclassifiable Establishments",
    "sg:phone":"+41 43 499 08 08",
    "sg:postcode":"8008",
    "sg:province":"Z\u00fcrich",
    "wof:name":"Targetsim Ag",
    "wof:placetype":"venue"
},
  "geometry": {"coordinates":[8.5481863022,47.3612174988],"type":"Point"}
}