{
  "type": "Feature",
  "properties": {
    "iso:country":"CH",
    "sg:address":"Via Emilio Bossi",
    "sg:city":"Chiasso",
    "sg:orig_category":"Fachdetailhandel mit pharmazeutischen Produkten",
    "sg:phone":"+41 91 682 53 22",
    "sg:postcode":"6830",
    "sg:province":"Ticino",
    "wof:name":"Farmacia Liver Dr. Gianni Di Liver Lia",
    "wof:placetype":"venue"
},
  "geometry": {"coordinates":[9.0311231613,45.8375091553],"type":"Point"}
}