{
  "type": "Feature",
  "properties": {
    "iso:country":"CH",
    "sg:address":"Zimmereiweg 1",
    "sg:city":"Berikon",
    "sg:orig_category":"Kauf U Verkauf von Immobilien auf eigene Rechnung Verwaltung von Immobilien",
    "sg:phone":"+41 56 631 02 90",
    "sg:postcode":"8965",
    "sg:province":"Aargau",
    "wof:name":"Mevagor Ag Immobilien-& Verm\u00f6gensverw.",
    "wof:placetype":"venue"
},
  "geometry": {"coordinates":[8.3803873062,47.3484916687],"type":"Point"}
}