{
  "type": "Feature",
  "properties": {
    "iso:country":"CH",
    "sg:address":"Hauptstrasse 26",
    "sg:city":"Derendingen",
    "sg:orig_category":"Bauspenglerei Zimmerei, Dachdeckerei, Bauspenglerei U Abdichtung",
    "sg:phone":"+41 32 682 20 16",
    "sg:postcode":"4552",
    "sg:province":"Solothurn",
    "wof:name":"Schweingruber Robert, Spenglerei Und Sanit. Anlagen.",
    "wof:placetype":"venue"
},
  "geometry": {"coordinates":[7.584259,47.196899],"type":"Point"}
}