{
  "type": "Feature",
  "properties": {
    "iso:country":"CH",
    "sg:address":"L\u00e4nggassstrasse 53",
    "sg:city":"Bern",
    "sg:orig_category":"Architektur U Ingenieurb\u00fcros",
    "sg:postcode":"3012",
    "sg:province":"Bern",
    "wof:name":"Gysin & Partner Architekten Ag",
    "wof:placetype":"venue"
},
  "geometry": {"coordinates":[7.429497,46.954868],"type":"Point"}
}