{
  "type": "Feature",
  "properties": {
    "iso:country":"CH",
    "sg:address":"Chemin De La Seymaz 79",
    "sg:city":"Vandoeuvres",
    "sg:orig_category":"Unternehmensberatung",
    "sg:phone":"+41 22 869 00 90",
    "sg:postcode":"1253",
    "sg:province":"Gen\u00e8ve",
    "wof:name":"Bmc Business Management & Consulting Finance Sa",
    "wof:placetype":"venue"
},
  "geometry": {"coordinates":[6.2114868164,46.2126312256],"type":"Point"}
}