{
  "type": "Feature",
  "properties": {
    "iso:country":"CH",
    "sg:address":"Neum\u00fchlestrasse 42",
    "sg:city":"Winterthur",
    "sg:orig_category":"Sanit\u00e4r U Heizungsinstallation Sanit\u00e4rinstallation",
    "sg:phone":"+41 33 336 27 23",
    "sg:postcode":"8406",
    "sg:province":"Z\u00fcrich",
    "wof:name":"Steiner-stehlin Ag Heizungs-& Sanit\u00e4ranlagen",
    "wof:placetype":"venue"
},
  "geometry": {"coordinates":[7.6193671227,46.7321968079],"type":"Point"}
}