{
  "type": "Feature",
  "properties": {
    "iso:country":"CH",
    "sg:address":"M\u00fchlegasse 2a",
    "sg:city":"Elgg",
    "sg:orig_category":"Wirtschaftspr\u00fcfung, Steuerberatung U Treuhand",
    "sg:phone":"+41 52 364 18 28",
    "sg:postcode":"8353",
    "sg:province":"Z\u00fcrich",
    "wof:name":"Treuhandb\u00fcro Norbert Hutter Ag",
    "wof:placetype":"venue"
},
  "geometry": {"coordinates":[8.8640651703,47.4923667908],"type":"Point"}
}