{
  "type": "Feature",
  "properties": {
    "iso:country":"CH",
    "sg:address":"Z\u00fcrcherstrasse 35 4052 Basel. Postfach",
    "sg:city":"Basel",
    "sg:classifiers":[
        {
            "category":"Insurance",
            "subcategory":"Insurance Agent",
            "type":"Services"
        }
    ],
    "sg:phone":"+41 61 317 38 38",
    "sg:postcode":"4006",
    "sg:tags":[
        "versicherungsagenturen",
        "-broker"
    ],
    "wof:name":"Secura Versicherungen Gesch\u00e4ftsstelle Basel",
    "wof:placetype":"venue"
},
  "geometry": {"coordinates":[7.6089677811,47.5539016724],"type":"Point"}
}