{
  "type": "Feature",
  "properties": {
    "addr:full":"Dufourstrasse 10 Zollikon Z\u00fcrich 8702",
    "addr:housenumber":"10",
    "addr:postcode":"8702",
    "addr:street":"Dufourstrasse",
    "iso:country":"CH",
    "sg:address":"Dufourstrasse 10",
    "sg:city":"Zollikon",
    "sg:orig_category":"Apples, Fresh",
    "sg:phone":"+41 81 303 84 84",
    "sg:postcode":"8702",
    "sg:province":"Z\u00fcrich",
    "wof:name":"Ecco-j\u00e4ger Fr\u00fcchte + Gem\u00fcse Ag",
    "wof:placetype":"venue"
},
  "geometry": {"coordinates":[9.497469,47.014488],"type":"Point"}
}