{
  "type": "Feature",
  "properties": {
    "iso:country":"CH",
    "sg:address":"Schlossgasse 2a",
    "sg:city":"M\u00fcnchenstein",
    "sg:orig_category":"Softwareentwicklung U beratung Versandhandel",
    "sg:phone":"+41 61 413 70 01",
    "sg:postcode":"4142",
    "sg:province":"Basel-Landschaft",
    "wof:name":"Niobe Ltd",
    "wof:placetype":"venue"
},
  "geometry": {"coordinates":[7.6210489273,47.5124053955],"type":"Point"}
}