{
  "type": "Feature",
  "properties": {
    "iso:country":"CH",
    "sg:address":"Muttenzerstrasse 7",
    "sg:city":"Pratteln",
    "sg:orig_category":"Unclassifiable Establishments",
    "sg:postcode":"4133",
    "sg:province":"Basel-Landschaft",
    "wof:name":"Willi Transport Gmbh",
    "wof:placetype":"venue"
},
  "geometry": {"coordinates":[7.6906971931,47.5182380676],"type":"Point"}
}