{
  "type": "Feature",
  "properties": {
    "iso:country":"CH",
    "sg:address":"Sch\u00fctzeng\u00fctli 2",
    "sg:city":"Bischofszell",
    "sg:orig_category":"K\u00fcnstlerische U schriftstellerische T\u00e4tigkeiten U Darbietungen",
    "sg:postcode":"9220",
    "sg:province":"Thurgau",
    "wof:name":"Stiftung Pro Musica Antiqua",
    "wof:placetype":"venue"
},
  "geometry": {"coordinates":[9.2408246994,47.4942245483],"type":"Point"}
}