{
  "type": "Feature",
  "properties": {
    "iso:country":"CH",
    "sg:address":"Schneehaldenstrasse 4",
    "sg:city":"D\u00fcrnten",
    "sg:orig_category":"Vereine Gesang",
    "sg:phone":"+41 55 240 16 50",
    "sg:postcode":"8635",
    "sg:province":"Z\u00fcrich",
    "wof:name":"M\u00e4nnerchor S\u00e4ngerbund",
    "wof:placetype":"venue"
},
  "geometry": {"coordinates":[8.8424797058,47.2784576416],"type":"Point"}
}