{
  "type": "Feature",
  "properties": {
    "iso:country":"CH",
    "sg:address":"Windenweg 13 6345 Neuheim. Postfach",
    "sg:city":"Neuheim",
    "sg:orig_category":"Kauf U Verkauf von Immobilien auf eigene Rechnung",
    "sg:postcode":"6345",
    "sg:province":"Zug",
    "wof:name":"Schmid & Co Ag",
    "wof:placetype":"venue"
},
  "geometry": {"coordinates":[9.3754396439,47.4229011536],"type":"Point"}
}