{
  "type": "Feature",
  "properties": {
    "iso:country":"CH",
    "sg:address":"Pfahlbauerweg 8",
    "sg:city":"Muntelier",
    "sg:orig_category":"Reiseb\u00fcros U Reiseveranstalter",
    "sg:phone":"+41 26 670 60 50",
    "sg:postcode":"3286",
    "sg:province":"Fribourg",
    "wof:name":"Mathys Travels",
    "wof:placetype":"venue"
},
  "geometry": {"coordinates":[7.1301560402,46.938533783],"type":"Point"}
}