{
  "type": "Feature",
  "properties": {
    "iso:country":"CH",
    "sg:address":"Unterdorf 118f 3368 Bleienbach. Postfach",
    "sg:city":"Bleienbach",
    "sg:orig_category":"Herstellung von sonstigen Maschinen f\u00fcr unspezifische Verwendung",
    "sg:postcode":"3368",
    "sg:province":"Bern",
    "wof:name":"Albatech Ag",
    "wof:placetype":"venue"
},
  "geometry": {"coordinates":[7.756289959,47.1852073669],"type":"Point"}
}