{
  "type": "Feature",
  "properties": {
    "iso:country":"CH",
    "sg:address":"Cadruvi 2",
    "sg:city":"Trimmis",
    "sg:orig_category":"Sonstige mit der Informatik verbundene T\u00e4tigkeiten",
    "sg:phone":"+41 81 630 21 60",
    "sg:postcode":"7203",
    "sg:province":"Graubunden",
    "wof:name":"Markus Pfiffner, B\u00fcro F\u00fcr Edv-dienstleistungen",
    "wof:placetype":"venue"
},
  "geometry": {"coordinates":[9.5641937256,46.8962783813],"type":"Point"}
}