{
  "type": "Feature",
  "properties": {
    "iso:country":"CH",
    "sg:address":"Ruchstuckstrasse 14",
    "sg:city":"Br\u00fcttisellen",
    "sg:orig_category":"Wirtschaftsverb\u00e4nde Gewerbeverb\u00e4nde/-vereine",
    "sg:phone":"+41 18330109",
    "sg:postcode":"8306",
    "sg:province":"Z\u00fcrich",
    "wof:name":"Gewerbeverein Wangen/br\u00fctti- Sellen,pr\u00e4s.felix Huber/ifag",
    "wof:placetype":"venue"
},
  "geometry": {"coordinates":[8.629734993,47.4180335999],"type":"Point"}
}