{
  "type": "Feature",
  "properties": {
    "iso:country":"CH",
    "sg:address":"Hasenrainstrasse 85 4102 Binningen. Postfach",
    "sg:city":"Binningen",
    "sg:orig_category":"Sonstige pers\u00f6nliche Dienstleistungen",
    "sg:phone":"+41 61 423 17 03",
    "sg:postcode":"4102",
    "sg:province":"Basel-Landschaft",
    "wof:name":"Client Focus Gmbh",
    "wof:placetype":"venue"
},
  "geometry": {"coordinates":[7.572218895,47.5424766541],"type":"Point"}
}