{
  "type": "Feature",
  "properties": {
    "iso:country":"CH",
    "sg:address":"Haldenstrasse 22",
    "sg:city":"Balterswil",
    "sg:orig_category":"Grosshandel mit sonstigen Gebrauchs U Verbrauchsg\u00fctern Mechanische Werkst\u00e4tten",
    "sg:phone":"+41 71 971 25 46",
    "sg:postcode":"8362",
    "sg:province":"Thurgau",
    "wof:name":"Treml R. Photoreparaturen",
    "wof:placetype":"venue"
},
  "geometry": {"coordinates":[8.9374551773,47.4561004639],"type":"Point"}
}