{
  "type": "Feature",
  "properties": {
    "iso:country":"CH",
    "sg:address":"Altgraben 23",
    "sg:city":"H\u00e4rkingen",
    "sg:classifiers":[
        {
            "category":"Manufacturing",
            "subcategory":"Metals",
            "type":"Manufacturing & Wholesale Goods"
        }
    ],
    "sg:phone":"+41 62 398 45 45",
    "sg:postcode":"4624",
    "sg:province":"Solothurn",
    "sg:tags":[
        "u",
        "leichtmetallbau",
        "stahl"
    ],
    "wof:name":"Umacon Ag Br\u00fcstungskonzeptionen",
    "wof:placetype":"venue"
},
  "geometry": {"coordinates":[7.8119931221,47.3162574768],"type":"Point"}
}