{
  "type": "Feature",
  "properties": {
    "iso:country":"CH",
    "sg:address":"Gaichtstrasse 43k",
    "sg:city":"T\u00fcscherz-alferm\u00e9e",
    "sg:orig_category":"Maurerarbeiten Rebbau",
    "sg:phone":"+41 32 322 78 14",
    "sg:postcode":"2512",
    "sg:province":"Bern",
    "wof:name":"Markus Hirt Maurerarbeiten & Rebbau",
    "wof:placetype":"venue"
},
  "geometry": {"coordinates":[7.199160099,47.117401123],"type":"Point"}
}