{
  "type": "Feature",
  "properties": {
    "iso:country":"CH",
    "sg:address":"Baslerstrasse 30a",
    "sg:city":"Olten",
    "sg:orig_category":"RESTAURANTS: TEA-ROOMS",
    "sg:postcode":"4600",
    "sg:province":"Solothurn",
    "wof:name":"Tgs Thai Gastro Service Gmbh",
    "wof:placetype":"venue"
},
  "geometry": {"coordinates":[7.902818203,47.3508300781],"type":"Point"}
}