{
  "type": "Feature",
  "properties": {
    "addr:full":"Bern Bern 3000",
    "addr:postcode":"3000",
    "iso:country":"CH",
    "sg:city":"Bern",
    "sg:orig_category":"Dienstleistungen, Druck U Beschriftungen",
    "sg:postcode":"3000",
    "sg:province":"Bern",
    "wof:name":"Copyquick",
    "wof:placetype":"venue"
},
  "geometry": {"coordinates":[7.44821,46.948021],"type":"Point"}
}