{
  "type": "Feature",
  "properties": {
    "iso:country":"CH",
    "sg:address":"2542",
    "sg:city":"Pieterlen",
    "sg:orig_category":"Sportvereine Sch\u00fctzen",
    "sg:phone":"+41 32 377 29 52",
    "sg:postcode":"2542",
    "sg:province":"Bern",
    "wof:name":"Feldsch\u00fctzengesellschaft",
    "wof:placetype":"venue"
},
  "geometry": {"coordinates":[7.3368191719,47.1748771667],"type":"Point"}
}