{
  "type": "Feature",
  "properties": {
    "iso:country":"CH",
    "sg:address":"Zimmerbergstrasse 64",
    "sg:city":"Oberburg",
    "sg:orig_category":"Dienstleistungen im landwirtschaftlichen Pflanzen U Gartenbau G\u00fcterbef\u00f6rderung im Strassenverkehr",
    "sg:postcode":"3414",
    "sg:province":"Bern",
    "wof:name":"Jakob Bolzli",
    "wof:placetype":"venue"
},
  "geometry": {"coordinates":[7.6260499954,47.0390052795],"type":"Point"}
}