{
  "type": "Feature",
  "properties": {
    "iso:country":"CH",
    "sg:address":"Lengacker 123b",
    "sg:city":"Rohrbach",
    "sg:orig_category":"Mit dem Versicherungsgewerbe verbundene T\u00e4tigkeiten",
    "sg:phone":"+41 62 965 23 60",
    "sg:postcode":"4938",
    "sg:province":"Bern",
    "wof:name":"Versicherungs-treuhand Ernst Nyffeler",
    "wof:placetype":"venue"
},
  "geometry": {"coordinates":[7.8203420639,47.1376190186],"type":"Point"}
}