{
  "type": "Feature",
  "properties": {
    "iso:country":"CH",
    "sg:address":"7166",
    "sg:city":"Trun",
    "sg:orig_category":"Primarschulen",
    "sg:postcode":"7166",
    "sg:province":"Graubunden",
    "wof:name":"Primarschule",
    "wof:placetype":"venue"
},
  "geometry": {"coordinates":[8.9906148911,46.743106842],"type":"Point"}
}