{
  "type": "Feature",
  "properties": {
    "iso:country":"CH",
    "sg:address":"4133",
    "sg:city":"Pratteln",
    "sg:orig_category":"Vereine Frauen Vereine Gemeinn\u00fctzige",
    "sg:phone":"+41 32 351 49 60",
    "sg:postcode":"4133",
    "sg:province":"Basel-Landschaft",
    "wof:name":"Schweiz.gemeinn.frauenverein Sektion B\u00fcren & Umgebung",
    "wof:placetype":"venue"
},
  "geometry": {"coordinates":[7.3718671799,47.1398963928],"type":"Point"}
}