{
  "type": "Feature",
  "properties": {
    "iso:country":"CH",
    "sg:address":"Schulstrasse 11",
    "sg:city":"Degersheim",
    "sg:orig_category":"Primarschulen",
    "sg:phone":"+41 71 371 17 47",
    "sg:postcode":"9113",
    "sg:province":"St. Gallen",
    "wof:name":"Primarschule Sennr\u00fcti",
    "wof:placetype":"venue"
},
  "geometry": {"coordinates":[9.1946258545,47.3744354248],"type":"Point"}
}