{
  "type": "Feature",
  "properties": {
    "iso:country":"CH",
    "sg:address":"Dorfstrasse 56",
    "sg:city":"Embrach",
    "sg:orig_category":"Malerei Tapeziererei",
    "sg:phone":"+41 18651249",
    "sg:postcode":"8424",
    "sg:province":"Z\u00fcrich",
    "wof:name":"Meinrad Carigiet Malergesch\u00e4ft",
    "wof:placetype":"venue"
},
  "geometry": {"coordinates":[8.5940475464,47.5049285889],"type":"Point"}
}