{
  "type": "Feature",
  "properties": {
    "iso:country":"CH",
    "sg:address":"3613",
    "sg:city":"Steffisburg",
    "sg:orig_category":"Primarschulen",
    "sg:phone":"+41 71 931 13 32",
    "sg:postcode":"3613",
    "sg:province":"Bern",
    "wof:name":"Primarschule Sonnenhof",
    "wof:placetype":"venue"
},
  "geometry": {"coordinates":[9.0266399384,47.4199295044],"type":"Point"}
}