{
  "type": "Feature",
  "properties": {
    "iso:country":"CH",
    "sg:address":"Grienstrasse 45 4055 Basel. Postfach",
    "sg:city":"Basel",
    "sg:orig_category":"Kunststoff-Produkte",
    "sg:phone":"+41 61 321 93 09",
    "sg:postcode":"4051",
    "sg:province":"Basel-Stadt",
    "wof:name":"Kunbaks Schneuwly Kurt Kunststoffprodukte; Herstellung",
    "wof:placetype":"venue"
},
  "geometry": {"coordinates":[7.5650501251,47.562702179],"type":"Point"}
}