{
  "type": "Feature",
  "properties": {
    "iso:country":"CH",
    "sg:address":"9213",
    "sg:city":"Hauptwil",
    "sg:orig_category":"Sportvereine Turnen",
    "sg:postcode":"9213",
    "sg:province":"Thurgau",
    "wof:name":"Turnverein Hausen",
    "wof:placetype":"venue"
},
  "geometry": {"coordinates":[8.2081003189,47.462310791],"type":"Point"}
}