{
  "type": "Feature",
  "properties": {
    "iso:country":"CH",
    "sg:address":"Industriestrasse 7",
    "sg:city":"Liestal",
    "sg:orig_category":"Shiatsu-Therapie",
    "sg:phone":"+41 56 631 19 01",
    "sg:postcode":"4410",
    "sg:province":"Basel-Landschaft",
    "wof:name":"Evelyne Ruth Herren Shiatsu",
    "wof:placetype":"venue"
},
  "geometry": {"coordinates":[8.3398036957,47.3514518738],"type":"Point"}
}