{
  "type": "Feature",
  "properties": {
    "iso:country":"CH",
    "sg:address":"Rebhaldenstrasse 19",
    "sg:city":"Wettingen",
    "sg:orig_category":"Wirtschaftspr\u00fcfung, Steuerberatung U Treuhand",
    "sg:postcode":"5430",
    "sg:province":"Aargau",
    "wof:name":"Treier Barbara",
    "wof:placetype":"venue"
},
  "geometry": {"coordinates":[8.3253135681,47.4709892273],"type":"Point"}
}