{
  "type": "Feature",
  "properties": {
    "iso:country":"CH",
    "sg:address":"Gehrenholzstrasse 7",
    "sg:city":"Z\u00fcrich",
    "sg:orig_category":"Werbung",
    "sg:postcode":"8055",
    "sg:province":"Z\u00fcrich",
    "wof:name":"Script Lucette Graf & Partner Public Relation, Text, \u00dcbersetzungen; Dienstleistung Usw",
    "wof:placetype":"venue"
},
  "geometry": {"coordinates":[8.507932663,47.3634490967],"type":"Point"}
}