{
  "type": "Feature",
  "properties": {
    "addr:full":"Lindenplatz 14 Zofingen Aargau 4800",
    "addr:housenumber":"14",
    "addr:postcode":"4800",
    "addr:street":"Lindenplatz",
    "iso:country":"CH",
    "sg:address":"Lindenplatz 14",
    "sg:city":"Zofingen",
    "sg:orig_category":"Detailhandel mit Blumen U Pflanzen",
    "sg:phone":"+41 91 858 14 73",
    "sg:postcode":"4800",
    "sg:province":"Aargau",
    "wof:name":"Danilo Tognetti Fiori",
    "wof:placetype":"venue"
},
  "geometry": {"coordinates":[8.97895,46.153481],"type":"Point"}
}