{
  "type": "Feature",
  "properties": {
    "iso:country":"CH",
    "sg:address":"Furttalstrasse 56",
    "sg:city":"Z\u00fcrich",
    "sg:orig_category":"Sonstiges Verlagsgewerbe",
    "sg:phone":"+41 32 366 34 34",
    "sg:postcode":"8046",
    "sg:province":"Z\u00fcrich",
    "wof:name":"Biella Calender Ag",
    "wof:placetype":"venue"
},
  "geometry": {"coordinates":[7.2645449638,47.1192245483],"type":"Point"}
}