{
  "type": "Feature",
  "properties": {
    "iso:country":"CH",
    "sg:address":"Hofstettenstrasse 37b",
    "sg:city":"Thun",
    "sg:orig_category":"Detailhandel mit Musikinstrumenten Detailhandel mit elektrischen Haushalts-,Radio U Fernsehger\u00e4ten s",
    "sg:phone":"+41 33 222 89 73",
    "sg:postcode":"3600",
    "sg:province":"Bern",
    "wof:name":"Musikhaus Kunz Und Iseli Gmbh",
    "wof:placetype":"venue"
},
  "geometry": {"coordinates":[7.6365680695,46.7541923523],"type":"Point"}
}