{
  "type": "Feature",
  "properties": {
    "iso:country":"CH",
    "sg:address":"Zentrumsplatz 3",
    "sg:city":"Sch\u00f6nb\u00fchl-urtenen",
    "sg:orig_category":"Architektur U Ingenieurb\u00fcros",
    "sg:phone":"+41 31 852 11 33",
    "sg:postcode":"3322",
    "sg:province":"Bern",
    "wof:name":"Ibz Ingenieurb\u00fcro Z\u00fcrcher",
    "wof:placetype":"venue"
},
  "geometry": {"coordinates":[7.49847,47.0205],"type":"Point"}
}