{
  "type": "Feature",
  "properties": {
    "iso:country":"CH",
    "sg:address":"Kalchengasse 1",
    "sg:city":"Kloten",
    "sg:orig_category":"Interessenvertretungen",
    "sg:phone":"+41 18141514",
    "sg:postcode":"8302",
    "sg:province":"Z\u00fcrich",
    "wof:name":"Crossair Cockpit Personal",
    "wof:placetype":"venue"
},
  "geometry": {"coordinates":[8.5820903778,47.45154953],"type":"Point"}
}