{
  "type": "Feature",
  "properties": {
    "iso:country":"CH",
    "sg:address":"Riehenstrasse 314 4000 Basel. Postfach",
    "sg:city":"Basel",
    "sg:orig_category":"Betrieb von Taxis",
    "sg:postcode":"4051",
    "sg:province":"Basel-Stadt",
    "wof:name":"Selimovic Nihad",
    "wof:placetype":"venue"
},
  "geometry": {"coordinates":[7.615803,47.569565],"type":"Point"}
}