{
  "type": "Feature",
  "properties": {
    "iso:country":"CH",
    "sg:address":"Cordulaplatz 6",
    "sg:city":"Baden",
    "sg:orig_category":"Sonstiger Grosshandel",
    "sg:postcode":"5400",
    "sg:province":"Aargau",
    "wof:name":"Genius Trading Luef",
    "wof:placetype":"venue"
},
  "geometry": {"coordinates":[8.3067541122,47.4721183777],"type":"Point"}
}