{
  "type": "Feature",
  "properties": {
    "iso:country":"CH",
    "sg:address":"Rue Vaicle 15 2882 St-ursanne Case Postale 33",
    "sg:city":"St-ursanne",
    "sg:classifiers":[
        {
            "category":"Restaurant",
            "type":"Food & Drink"
        }
    ],
    "sg:phone":"+41 32 461 31 14",
    "sg:postcode":"2882",
    "sg:province":"Jura",
    "wof:name":"Restaurant De L'ours",
    "wof:placetype":"venue"
},
  "geometry": {"coordinates":[7.1550931931,47.3650131226],"type":"Point"}
}