{
  "type": "Feature",
  "properties": {
    "iso:country":"CH",
    "sg:address":"Rainstrasse 94",
    "sg:city":"Meilen",
    "sg:orig_category":"Unternehmensberatung",
    "sg:phone":"+41 56 640 14 46",
    "sg:postcode":"8706",
    "sg:province":"Z\u00fcrich",
    "wof:name":"Guide Gmbh",
    "wof:placetype":"venue"
},
  "geometry": {"coordinates":[8.4385242462,47.3228569031],"type":"Point"}
}