{
  "type": "Feature",
  "properties": {
    "iso:country":"CH",
    "sg:address":"Weissensteinstrasse 26",
    "sg:city":"Langendorf",
    "sg:orig_category":"RESTAURANTS: TEA-ROOMS",
    "sg:postcode":"4513",
    "sg:province":"Solothurn",
    "wof:name":"Witmer-schmassmann Urs",
    "wof:placetype":"venue"
},
  "geometry": {"coordinates":[7.5151882172,47.2210884094],"type":"Point"}
}