{
  "type": "Feature",
  "properties": {
    "iso:country":"CH",
    "sg:address":"Sonnental",
    "sg:city":"Muolen",
    "sg:orig_category":"Herstellung von Maschinen f\u00fcr das Druckgewerbe Herstellung von Metallerzeugnissen ohne Maschinenbau",
    "sg:phone":"+41 71 411 52 44",
    "sg:postcode":"9313",
    "sg:province":"St. Gallen",
    "wof:name":"Fermotec Gmbh",
    "wof:placetype":"venue"
},
  "geometry": {"coordinates":[9.3144598007,47.5224914551],"type":"Point"}
}