{
  "type": "Feature",
  "properties": {
    "iso:country":"CH",
    "sg:address":"J\u00e4gerstrasse 12",
    "sg:city":"Basel",
    "sg:orig_category":"Non-Classified Establishments",
    "sg:postcode":"4058",
    "sg:province":"Basel-Stadt",
    "wof:name":"Demiroglu",
    "wof:placetype":"venue"
},
  "geometry": {"coordinates":[7.6022782326,47.568611145],"type":"Point"}
}