{
  "type": "Feature",
  "properties": {
    "iso:country":"CH",
    "sg:address":"Rue Du Lac 10",
    "sg:city":"Yverdon-les-bains",
    "sg:orig_category":"Drogerien",
    "sg:phone":"+41 24 425 27 35",
    "sg:postcode":"1400",
    "sg:province":"Vaud",
    "wof:name":"Droguerie Et Herborisaterie Raposo R.",
    "wof:placetype":"venue"
},
  "geometry": {"coordinates":[6.6405739784,46.779083252],"type":"Point"}
}