{
  "type": "Feature",
  "properties": {
    "iso:country":"CH",
    "sg:address":"4423 Hersberg. Postfach",
    "sg:city":"Hersberg",
    "sg:orig_category":"Verwertung von Milch",
    "sg:postcode":"4423",
    "sg:province":"Basel-Landschaft",
    "wof:name":"Milchgenossenschaft Hertenstein",
    "wof:placetype":"venue"
},
  "geometry": {"coordinates":[8.2932138443,47.4866981506],"type":"Point"}
}