{
  "type": "Feature",
  "properties": {
    "iso:country":"CH",
    "sg:address":"Dienerstrasse 43",
    "sg:city":"Z\u00fcrich",
    "sg:orig_category":"Unternehmensberatung",
    "sg:phone":"+41 878 800 140",
    "sg:postcode":"8026",
    "sg:province":"Z\u00fcrich",
    "wof:name":"Wogatu Consulting Gmbh",
    "wof:placetype":"venue"
},
  "geometry": {"coordinates":[8.5268583298,47.3784675598],"type":"Point"}
}