{
  "type": "Feature",
  "properties": {
    "iso:country":"CH",
    "sg:address":"S\u00e4gewiesstrasse 9",
    "sg:city":"Heiden",
    "sg:orig_category":"Arztpraxen",
    "sg:phone":"+41 71 891 37 46",
    "sg:postcode":"9410",
    "sg:province":"Appenzell Ausserrhoden",
    "wof:name":"Dr.med.will Klunker Hom\u00f6opathie",
    "wof:placetype":"venue"
},
  "geometry": {"coordinates":[9.535638,47.436749],"type":"Point"}
}