{
  "type": "Feature",
  "properties": {
    "iso:country":"CH",
    "sg:address":"Riedhofstrasse 40 8400 Winterthur. Postfach",
    "sg:city":"Winterthur",
    "sg:orig_category":"Schreib U \u00dcbersetzungsb\u00fcros",
    "sg:postcode":"8408",
    "sg:province":"Z\u00fcrich",
    "wof:name":"Karaman Fikri",
    "wof:placetype":"venue"
},
  "geometry": {"coordinates":[8.6943321228,47.5123138428],"type":"Point"}
}