{
  "type": "Feature",
  "properties": {
    "iso:country":"CH",
    "sg:address":"Weingartenstrasse 12",
    "sg:city":"Hilterfingen",
    "sg:orig_category":"Verlagsgewerbe",
    "sg:phone":"+41 33 243 19 64",
    "sg:postcode":"3652",
    "sg:province":"Bern",
    "wof:name":"Albert Meier Verlag",
    "wof:placetype":"venue"
},
  "geometry": {"coordinates":[7.6576228142,46.7405014038],"type":"Point"}
}