{
  "type": "Feature",
  "properties": {
    "iso:country":"CH",
    "sg:address":"3911",
    "sg:city":"Ried-brig",
    "sg:orig_category":"Primarschulen",
    "sg:phone":"+41 27 923 82 30",
    "sg:postcode":"3911",
    "sg:province":"Valais",
    "wof:name":"Primarschule",
    "wof:placetype":"venue"
},
  "geometry": {"coordinates":[8.0152349472,46.3151245117],"type":"Point"}
}