{
  "type": "Feature",
  "properties": {
    "iso:country":"CH",
    "sg:address":"Idastrasse 28 8000 Z\u00fcrich. Postfach",
    "sg:city":"Z\u00fcrich",
    "sg:orig_category":"Werbung",
    "sg:postcode":"8001",
    "sg:province":"Z\u00fcrich",
    "wof:name":"Trend Tools Hirt B\u00e9atrice",
    "wof:placetype":"venue"
},
  "geometry": {"coordinates":[8.5152359009,47.3732681274],"type":"Point"}
}