{
  "type": "Feature",
  "properties": {
    "iso:country":"CH",
    "sg:address":"Poststrasse 44",
    "sg:city":"Vals",
    "sg:orig_category":"Detailhandel mit Getr\u00e4nken Detailhandel mit Waren verschiedener Art, Hauptrichtung Nahrungsmittel",
    "sg:phone":"+41 81 935 11 46",
    "sg:postcode":"7132",
    "sg:province":"Graubunden",
    "wof:name":"Apollonia Reinle Primo Lebensmittel",
    "wof:placetype":"venue"
},
  "geometry": {"coordinates":[9.1826667786,46.6232032776],"type":"Point"}
}