{
  "type": "Feature",
  "properties": {
    "iso:country":"CH",
    "sg:address":"Othmarstrasse 8",
    "sg:city":"Z\u00fcrich",
    "sg:classifiers":[
        {
            "category":"Banks & Credit Unions",
            "subcategory":"Financial Services",
            "type":"Services"
        }
    ],
    "sg:phone":"+41 4112612637",
    "sg:postcode":"8032",
    "sg:province":"Z\u00fcrich",
    "sg:tags":[
        "banking",
        "finance",
        "insurance"
    ],
    "wof:name":"Atlantic Forfaitierungs Ag",
    "wof:placetype":"venue"
},
  "geometry": {"coordinates":[8.549349,47.364605],"type":"Point"}
}