{
  "type": "Feature",
  "properties": {
    "iso:country":"CH",
    "sg:address":"2906",
    "sg:city":"Chevenez",
    "sg:orig_category":"Grosshandel mit lebenden Tieren",
    "sg:phone":"+41 41 850 17 08",
    "sg:postcode":"2906",
    "sg:province":"Jura",
    "wof:name":"Joseph Ott Viehhandlung",
    "wof:placetype":"venue"
},
  "geometry": {"coordinates":[8.4413146973,47.0852775574],"type":"Point"}
}