{
  "type": "Feature",
  "properties": {
    "iso:country":"CH",
    "sg:address":"Alleestrasse 10",
    "sg:city":"Sutz",
    "sg:classifiers":[
        {
            "category":"Transit Center",
            "subcategory":"Passenger",
            "type":"Transportation"
        }
    ],
    "sg:phone":"+41 32 397 17 17",
    "sg:postcode":"2572",
    "sg:province":"Bern",
    "sg:tags":[
        "blanket"
    ],
    "wof:name":"Leibold-wenk",
    "wof:placetype":"venue"
},
  "geometry": {"coordinates":[7.212778,47.095676],"type":"Point"}
}