{
  "type": "Feature",
  "properties": {
    "iso:country":"CH",
    "sg:address":"Via Cantine Di Sotto 8",
    "sg:city":"Mendrisio",
    "sg:orig_category":"Grosshandel mit Wasch U Reinigungsmitteln Herstellung von Seifen, Wasch U Reinigungsmitteln",
    "sg:phone":"+41 91 646 56 56",
    "sg:postcode":"6850",
    "sg:province":"Ticino",
    "wof:name":"Paolo Tettamanti Pro-net & Cons.di Informatica",
    "wof:placetype":"venue"
},
  "geometry": {"coordinates":[8.9849071503,45.8815460205],"type":"Point"}
}