{
  "type": "Feature",
  "properties": {
    "iso:country":"CH",
    "sg:address":"Zentrum 6",
    "sg:city":"Kradolf",
    "sg:orig_category":"Zahnarztpraxen",
    "sg:phone":"+41 55 410 29 79",
    "sg:postcode":"9214",
    "sg:province":"Thurgau",
    "wof:name":"Dr. Med. Dent. Enrico Ferrari Zahnarzt",
    "wof:placetype":"venue"
},
  "geometry": {"coordinates":[8.778793335,47.2024002075],"type":"Point"}
}