{
  "type": "Feature",
  "properties": {
    "iso:country":"CH",
    "sg:address":"Oberg\u00fctschrain 2",
    "sg:city":"Luzern",
    "sg:orig_category":"Unternehmensberatung",
    "sg:postcode":"6003",
    "sg:province":"Luzern",
    "wof:name":"Gt-consulting Georges Theiler",
    "wof:placetype":"venue"
},
  "geometry": {"coordinates":[8.2878417969,47.0461502075],"type":"Point"}
}