{
  "type": "Feature",
  "properties": {
    "iso:country":"CH",
    "sg:address":"3996",
    "sg:city":"Binn",
    "sg:classifiers":[
        {
            "category":"Education",
            "subcategory":"Library",
            "type":"Public Place"
        }
    ],
    "sg:postcode":"3996",
    "sg:province":"Valais",
    "sg:tags":[
        "u",
        "bibliotheken",
        "archive"
    ],
    "wof:name":"Katholische Pfarrbibliothek",
    "wof:placetype":"venue"
},
  "geometry": {"coordinates":[8.182741,46.364166],"type":"Point"}
}