{
  "type": "Feature",
  "properties": {
    "iso:country":"CH",
    "sg:address":"Brambergstrasse 28",
    "sg:city":"Luzern",
    "sg:orig_category":"Gesundheitswesen",
    "sg:postcode":"6004",
    "sg:province":"Luzern",
    "wof:name":"Unit Care Gmbh",
    "wof:placetype":"venue"
},
  "geometry": {"coordinates":[8.3027305603,47.057384491],"type":"Point"}
}