{
  "type": "Feature",
  "properties": {
    "iso:country":"CH",
    "sg:address":"Kronenstrasse 5",
    "sg:city":"St\u00e4fa",
    "sg:orig_category":"Sonstiger Grosshandel",
    "sg:postcode":"8712",
    "sg:province":"Z\u00fcrich",
    "wof:name":"Y. Locher Consulting",
    "wof:placetype":"venue"
},
  "geometry": {"coordinates":[8.7242918015,47.2417526245],"type":"Point"}
}