{
  "type": "Feature",
  "properties": {
    "iso:country":"CH",
    "sg:address":"Rigistrasse 7",
    "sg:city":"Dierikon",
    "sg:orig_category":"G\u00fcterbef\u00f6rderung im Strassenverkehr",
    "sg:phone":"+41 71 243 50 40",
    "sg:postcode":"6036",
    "sg:province":"Luzern",
    "wof:name":"Huber Ag St. Gallen",
    "wof:placetype":"venue"
},
  "geometry": {"coordinates":[9.396235466,47.4363365173],"type":"Point"}
}