{
  "type": "Feature",
  "properties": {
    "iso:country":"CH",
    "sg:address":"Hauptstr. 96",
    "sg:city":"Churwalden",
    "sg:orig_category":"Instandhaltung U Reparatur von Automobilen",
    "sg:postcode":"7075",
    "sg:province":"Graubunden",
    "wof:name":"Frei, Erwin",
    "wof:placetype":"venue"
},
  "geometry": {"coordinates":[9.5420656204,46.7826385498],"type":"Point"}
}