{
  "type": "Feature",
  "properties": {
    "iso:country":"CH",
    "sg:address":"Unterfeldstrasse 3b",
    "sg:city":"Frauenfeld",
    "sg:orig_category":"Unclassifiable Establishments",
    "sg:postcode":"8500",
    "sg:province":"Thurgau",
    "wof:name":"Widmer Malerbetrieb Gmbh",
    "wof:placetype":"venue"
},
  "geometry": {"coordinates":[8.9065237045,47.5556030273],"type":"Point"}
}