{
  "type": "Feature",
  "properties": {
    "iso:country":"CH",
    "sg:address":"Rotmattstrasse 6 6045 Meggen. Postfach 732",
    "sg:city":"Meggen",
    "sg:orig_category":"Grosshandel mit sonstigen Gebrauchs U Verbrauchsg\u00fctern Herstellung von Papier, Karton U Pappe",
    "sg:phone":"+41 41 377 05 05",
    "sg:postcode":"6045",
    "sg:province":"Luzern",
    "wof:name":"Ambiente Suisse Gmbh",
    "wof:placetype":"venue"
},
  "geometry": {"coordinates":[8.3745126724,47.0433044434],"type":"Point"}
}