{
  "type": "Feature",
  "properties": {
    "iso:country":"CH",
    "sg:address":"Blickensdorferstrasse 11",
    "sg:city":"Steinhausen",
    "sg:orig_category":"Softwareentwicklung U beratung",
    "sg:phone":"+41 41 740 06 87",
    "sg:postcode":"6312",
    "sg:province":"Zug",
    "wof:name":"Attosoft Gmbh",
    "wof:placetype":"venue"
},
  "geometry": {"coordinates":[8.4867944717,47.1972045898],"type":"Point"}
}