{
  "type": "Feature",
  "properties": {
    "addr:full":"Hauptstrasse Rohrbach Bern 4938",
    "addr:postcode":"4938",
    "addr:street":"Hauptstrasse",
    "iso:country":"CH",
    "sg:address":"Hauptstrasse",
    "sg:city":"Rohrbach",
    "sg:orig_category":"Autospenglereien",
    "sg:phone":"+41 79 422 95 26",
    "sg:postcode":"4938",
    "sg:province":"Bern",
    "wof:name":"Heinz Hasler Carrosserie",
    "wof:placetype":"venue"
},
  "geometry": {"coordinates":[7.822377,47.130405],"type":"Point"}
}