{
  "type": "Feature",
  "properties": {
    "iso:country":"CH",
    "sg:address":"Haut-du-village 201",
    "sg:city":"Plagne",
    "sg:orig_category":"Forstwirtschaft ohne Dienstleistungen in der Forstwirtschaft",
    "sg:phone":"+41 32 358 20 77",
    "sg:postcode":"2536",
    "sg:province":"Bern",
    "wof:name":"Grosjean Yves-alain",
    "wof:placetype":"venue"
},
  "geometry": {"coordinates":[7.2809281349,47.1869392395],"type":"Point"}
}