{
  "type": "Feature",
  "properties": {
    "iso:country":"CH",
    "sg:address":"Terrassenweg 17",
    "sg:city":"Ober\u00e4geri",
    "sg:orig_category":"Sonstiger Grosshandel Wirtschaftspr\u00fcfung, Steuerberatung U Treuhand",
    "sg:phone":"+41 18410173",
    "sg:postcode":"6315",
    "sg:province":"Zug",
    "wof:name":"Robu, Otter Ruth",
    "wof:placetype":"venue"
},
  "geometry": {"coordinates":[8.4613513947,47.4537887573],"type":"Point"}
}