{
  "type": "Feature",
  "properties": {
    "iso:country":"CH",
    "sg:address":"L\u00f6hliweg 9 3325 Hettiswil. Postfach",
    "sg:city":"Hettiswil",
    "sg:orig_category":"Erschliessung von Grundst\u00fccken",
    "sg:postcode":"3325",
    "sg:province":"Bern",
    "wof:name":"Glw Baugesellschaft F\u00fcr Lebensgef\u00fchl Und Wohnkomfort Gmbh",
    "wof:placetype":"venue"
},
  "geometry": {"coordinates":[7.5594167709,47.0292282104],"type":"Point"}
}