{
  "type": "Feature",
  "properties": {
    "iso:country":"CH",
    "sg:address":"Arbonerstrasse 29",
    "sg:city":"Kronb\u00fchl",
    "sg:orig_category":"Herstellung von Zement",
    "sg:phone":"+41 71 298 40 83",
    "sg:postcode":"9302",
    "wof:name":"Peter Zementwaren-werke Ag",
    "wof:placetype":"venue"
},
  "geometry": {"coordinates":[9.3943624496,47.4626731873],"type":"Point"}
}