{
  "type": "Feature",
  "properties": {
    "iso:country":"CH",
    "sg:address":"Ennert Holzgraben",
    "sg:city":"Brig",
    "sg:orig_category":"Herstellung von sonstigen elektrischen Ausr\u00fcstungen",
    "sg:postcode":"3900",
    "sg:province":"Valais",
    "wof:name":"Freizeitschiessanlage Pro Tir, Geissmann Peter",
    "wof:placetype":"venue"
},
  "geometry": {"coordinates":[7.9876461029,46.3158912659],"type":"Point"}
}