{
  "type": "Feature",
  "properties": {
    "iso:country":"CH",
    "sg:address":"Rue Dr-schwab 2",
    "sg:city":"St-imier",
    "sg:classifiers":[
        {
            "category":"Travel",
            "subcategory":"Hotels & Motels",
            "type":"Entertainment"
        }
    ],
    "sg:phone":"+41 32 941 29 56",
    "sg:postcode":"2610",
    "sg:province":"Bern",
    "sg:tags":[
        "hotels",
        "mit",
        "restaurant"
    ],
    "wof:name":"H\u00f4tel De La Fontaine",
    "wof:placetype":"venue"
},
  "geometry": {"coordinates":[7.000685215,47.153137207],"type":"Point"}
}