{
  "type": "Feature",
  "properties": {
    "iso:country":"CH",
    "sg:address":"Rte De Lausanne 347",
    "sg:city":"Creux-de-genthod",
    "sg:orig_category":"Handel mit Motorr\u00e4dern, Teilen U Zubeh\u00f6r Instandhaltung U Reparatur von Motorr\u00e4dern",
    "sg:postcode":"1294",
    "sg:province":"Gen\u00e8ve",
    "wof:name":"Olivier Motos, Thierrin",
    "wof:placetype":"venue"
},
  "geometry": {"coordinates":[6.1558299065,46.2558822632],"type":"Point"}
}