{
  "type": "Feature",
  "properties": {
    "iso:country":"CH",
    "sg:address":"Rue De Carouge 75",
    "sg:city":"Gen\u00e8ve",
    "sg:orig_category":"Detailhandel mit Uhren U Schmuck Fachdetailhandel in Verkaufsr\u00e4umen",
    "sg:phone":"+41 81 833 18 55",
    "sg:postcode":"1205",
    "sg:province":"Gen\u00e8ve",
    "wof:name":"Cartier Sa, Succursale De St. Moritz",
    "wof:placetype":"venue"
},
  "geometry": {"coordinates":[9.8381910324,46.4970664978],"type":"Point"}
}