{
  "type": "Feature",
  "properties": {
    "iso:country":"CH",
    "sg:address":"Strada Principale",
    "sg:city":"Brusio",
    "sg:classifiers":[
        {
            "category":"Food & Beverages",
            "subcategory":"Liquor & Beverages",
            "type":"Retail Goods"
        }
    ],
    "sg:phone":"+41 81 846 55 33",
    "sg:postcode":"7743",
    "sg:province":"Graubunden",
    "sg:tags":[
        "wine",
        "italian"
    ],
    "wof:name":"Cantina Al Poggio Sa",
    "wof:placetype":"venue"
},
  "geometry": {"coordinates":[10.120434761,46.260848999],"type":"Point"}
}