{
  "type": "Feature",
  "properties": {
    "iso:country":"CH",
    "sg:address":"H\u00e4nig\u00e4ssli 5",
    "sg:city":"Arch",
    "sg:orig_category":"Arbeitnehmerverb\u00e4nde",
    "sg:postcode":"3296",
    "sg:province":"Bern",
    "wof:name":"Schw.kader-organisat.grenchen",
    "wof:placetype":"venue"
},
  "geometry": {"coordinates":[7.430512,47.167999],"type":"Point"}
}