{
  "type": "Feature",
  "properties": {
    "iso:country":"CH",
    "sg:address":"Entenmoos",
    "sg:city":"Rechthalten",
    "sg:orig_category":"Herstellung von Konstruktionsteilen, Fertigbauteilen U Ausbauelementen aus Holz",
    "sg:phone":"+41 26 418 14 41",
    "sg:postcode":"1718",
    "sg:province":"Fribourg",
    "wof:name":"Jungo Johann Ag, Zimmerei Und Schreinerei.",
    "wof:placetype":"venue"
},
  "geometry": {"coordinates":[7.25,46.7667007446],"type":"Point"}
}