{
  "type": "Feature",
  "properties": {
    "iso:country":"CH",
    "sg:address":"Lochmatt",
    "sg:city":"Oberh\u00fcnigen",
    "sg:orig_category":"Herstellung von sonstigen landwirtschaftlichen Maschinen Schmieden",
    "sg:phone":"+41 31 791 03 59",
    "sg:postcode":"3504",
    "sg:province":"Bern",
    "wof:name":"Hans Stucki Schmiede & Landmaschinen",
    "wof:placetype":"venue"
},
  "geometry": {"coordinates":[7.658217907,46.8797988892],"type":"Point"}
}