{
  "type": "Feature",
  "properties": {
    "iso:country":"CH",
    "sg:address":"L\u00f6wenstrasse 1 8000 Z\u00fcrich. Postfach",
    "sg:city":"Z\u00fcrich",
    "sg:orig_category":"Unclassifiable Establishments",
    "sg:postcode":"8001",
    "sg:province":"Z\u00fcrich",
    "wof:name":"Thrupoint Switzerland Gmbh",
    "wof:placetype":"venue"
},
  "geometry": {"coordinates":[8.534318924,47.3728561401],"type":"Point"}
}