{
  "type": "Feature",
  "properties": {
    "iso:country":"CH",
    "sg:address":"S\u00e4gereistrasse 4 8362 Balterswil. Postfach",
    "sg:city":"Balterswil",
    "sg:orig_category":"Herstellung von K\u00fcchenm\u00f6beln",
    "sg:phone":"+41 52 720 94 84",
    "sg:postcode":"8362",
    "sg:province":"Thurgau",
    "wof:name":"Awl Lackner A.",
    "wof:placetype":"venue"
},
  "geometry": {"coordinates":[8.9413290024,47.4545974731],"type":"Point"}
}