{
  "type": "Feature",
  "properties": {
    "iso:country":"CH",
    "sg:address":"Rue Du Simplon 33",
    "sg:city":"Vevey",
    "sg:classifiers":[
        {
            "category":"Bars & Pubs",
            "type":"Food & Drink"
        }
    ],
    "sg:phone":"+41 27 957 39 57",
    "sg:postcode":"1800",
    "sg:province":"Vaud",
    "wof:name":"Why Not The Pub",
    "wof:placetype":"venue"
},
  "geometry": {"coordinates":[7.933673,46.111717],"type":"Point"}
}