{
  "type": "Feature",
  "properties": {
    "iso:country":"CH",
    "sg:address":"Talstr. 376",
    "sg:city":"Himmelried",
    "sg:orig_category":"Vermietung U Verpachtung von eigenen Immobilien",
    "sg:phone":"+41 61 741 11 89",
    "sg:postcode":"4204",
    "sg:province":"Solothurn",
    "wof:name":"Hochuli Immobilien Ag",
    "wof:placetype":"venue"
},
  "geometry": {"coordinates":[7.5948190689,47.421131134],"type":"Point"}
}