{
  "type": "Feature",
  "properties": {
    "iso:country":"CH",
    "sg:address":"Maschlinastrasse 60",
    "sg:city":"Triesen",
    "sg:orig_category":"Grosshandel mit B\u00fcromaschinen Grosshandel mit Datenverarbeitungsger\u00e4ten",
    "sg:phone":"+41 18846711",
    "sg:postcode":"9495",
    "wof:name":"Olu Onabanjo Computer-engineering",
    "wof:placetype":"venue"
},
  "geometry": {"coordinates":[8.4415426254,47.4566497803],"type":"Point"}
}