{
  "type": "Feature",
  "properties": {
    "iso:country":"CH",
    "sg:address":"Burgweggweg 7",
    "sg:city":"Aarberg",
    "sg:orig_category":"Sportschulen Fern\u00f6stliche Kampfsportarten Sportvereine Judo and Karate",
    "sg:postcode":"3270",
    "sg:province":"Bern",
    "wof:name":"Fudokan Karate Do Lyss",
    "wof:placetype":"venue"
},
  "geometry": {"coordinates":[7.2854499817,47.0414352417],"type":"Point"}
}