{
  "type": "Feature",
  "properties": {
    "iso:country":"CH",
    "sg:address":"Guggitalring 13d",
    "sg:city":"Zug",
    "sg:orig_category":"RESTAURANTS: TEA-ROOMS",
    "sg:phone":"+41 21 801 23 54",
    "sg:postcode":"6300",
    "sg:province":"Zug",
    "wof:name":"Bell's Pub Sa",
    "wof:placetype":"venue"
},
  "geometry": {"coordinates":[6.4988307953,46.5088157654],"type":"Point"}
}