{
  "type": "Feature",
  "properties": {
    "iso:country":"CH",
    "sg:address":"Chemin Fran\u00e7ois-chavaz 115",
    "sg:city":"Onex",
    "sg:orig_category":"Erschliessung von Grundst\u00fccken Sonstige Kultur U Unterhaltungseinrichtungen",
    "sg:phone":"+41 22 793 50 75",
    "sg:postcode":"1213",
    "sg:province":"Gen\u00e8ve",
    "wof:name":"Onex-jardin",
    "wof:placetype":"venue"
},
  "geometry": {"coordinates":[6.0945382118,46.1878967285],"type":"Point"}
}