{
  "type": "Feature",
  "properties": {
    "iso:country":"CH",
    "sg:address":"Edenstrasse 6",
    "sg:city":"Kesswil",
    "sg:orig_category":"Allgemeiner Hoch U Tiefbau",
    "sg:phone":"+41 71 463 62 27",
    "sg:postcode":"8593",
    "sg:province":"Thurgau",
    "wof:name":"Randelli Maurerarbeiten Gmbh",
    "wof:placetype":"venue"
},
  "geometry": {"coordinates":[9.321342,47.592896],"type":"Point"}
}