{
  "type": "Feature",
  "properties": {
    "iso:country":"CH",
    "sg:address":"Galgenried 2 6370 Stans. Postfach",
    "sg:city":"Stans",
    "sg:orig_category":"Grosshandel mit M\u00f6beln, Wohnbedarf, Teppichen U Bodenbel\u00e4gen",
    "sg:phone":"+41 41 630 28 12",
    "sg:postcode":"6371",
    "sg:province":"Nidwalden",
    "wof:name":"B\u00e4chler Top Track Ag Loipen- & Pistentechnik",
    "wof:placetype":"venue"
},
  "geometry": {"coordinates":[8.3461608887,46.9685935974],"type":"Point"}
}