{
  "type": "Feature",
  "properties": {
    "iso:country":"CH",
    "sg:address":"Rte Cantonale",
    "sg:city":"Charrat",
    "sg:orig_category":"Detailhandel mit elektrischen Haushalts-,Radio U Fernsehger\u00e4ten sowie Musikinstrumenten",
    "sg:postcode":"1906",
    "sg:province":"Valais",
    "wof:name":"Electro-m\u00e9nager Diffusion, Fumeaux Gilles",
    "wof:placetype":"venue"
},
  "geometry": {"coordinates":[7.1224279404,46.1242446899],"type":"Point"}
}