{
  "type": "Feature",
  "properties": {
    "iso:country":"CH",
    "sg:address":"Seetalcenter",
    "sg:city":"Hochdorf",
    "sg:orig_category":"Unclassifiable Establishments",
    "sg:phone":"+41 81 416 74 44",
    "sg:postcode":"6280",
    "sg:province":"Luzern",
    "wof:name":"Kosmetiksalon Fross",
    "wof:placetype":"venue"
},
  "geometry": {"coordinates":[9.8209161758,46.7938766479],"type":"Point"}
}