{
  "type": "Feature",
  "properties": {
    "iso:country":"CH",
    "sg:address":"Kapellenweg Ibergeregg",
    "sg:city":"Oberiberg",
    "sg:orig_category":"Detailhandel mit Sportartikeln Detailhandel mit Zeitungen U Zeitschriften Kioske",
    "sg:phone":"+41 56 493 44 55",
    "sg:postcode":"8843",
    "sg:province":"Schwyz",
    "wof:name":"Sport World Baregg Baden",
    "wof:placetype":"venue"
},
  "geometry": {"coordinates":[8.2843389511,47.4559783936],"type":"Point"}
}