{
  "type": "Feature",
  "properties": {
    "addr:full":"Hauptstrasse 12a B\u00e4ttwil Solothurn 4112",
    "addr:housenumber":"12a",
    "addr:postcode":"4112",
    "addr:street":"Hauptstrasse;Solothurn",
    "iso:country":"CH",
    "sg:address":"Hauptstrasse 12a",
    "sg:city":"B\u00e4ttwil",
    "sg:orig_category":"Bauspenglerei Dachdeckerei",
    "sg:phone":"+41 61 731 31 61",
    "sg:postcode":"4112",
    "sg:province":"Solothurn",
    "wof:name":"Pascal Studer Studer Spenglerei Sanit\u00e4r",
    "wof:placetype":"venue"
},
  "geometry": {"coordinates":[7.510193,47.490314],"type":"Point"}
}