{
  "type": "Feature",
  "properties": {
    "iso:country":"CH",
    "sg:address":"Kreuzlinger Strasse 30",
    "sg:city":"Romanshorn",
    "sg:orig_category":"Handelsvermittlung U Grosshandel mit Automobilteilen U Zubeh\u00f6r",
    "sg:phone":"+41 19317111",
    "sg:postcode":"8590",
    "sg:province":"Thurgau",
    "wof:name":"Daimler Chrysler Schweiz Ag",
    "wof:placetype":"venue"
},
  "geometry": {"coordinates":[8.7968702316,47.3330192566],"type":"Point"}
}