{
  "type": "Feature",
  "properties": {
    "addr:full":"Clarastrasse 55 Basel Basel-Stadt 4058",
    "addr:housenumber":"55",
    "addr:postcode":"4058",
    "addr:street":"Clarastrasse",
    "iso:country":"CH",
    "sg:address":"Clarastrasse 55",
    "sg:city":"Basel",
    "sg:orig_category":"Architekturb\u00fcros",
    "sg:phone":"+41 71 223 49 11",
    "sg:postcode":"4058",
    "sg:province":"Basel-Stadt",
    "wof:name":"Hanspeter Burkhart Architekturb\u00fcro",
    "wof:placetype":"venue"
},
  "geometry": {"coordinates":[9.391453,47.412186],"type":"Point"}
}