{
  "type": "Feature",
  "properties": {
    "iso:country":"CH",
    "sg:address":"Poststrasse 22 7000 Chur. Postfach",
    "sg:city":"Chur",
    "sg:orig_category":"Interessenvertretungen",
    "sg:postcode":"7000",
    "sg:province":"Graubunden",
    "wof:name":"B\u00fcvetta-stiftung Erforschung U. Geschichtliche Entwickung Des Mineralwassers Usw",
    "wof:placetype":"venue"
},
  "geometry": {"coordinates":[9.5322647095,46.8492965698],"type":"Point"}
}