{
  "type": "Feature",
  "properties": {
    "iso:country":"CH",
    "sg:address":"Hermance Route D' 172bis 1245 Collonge-bellerive. Postfach",
    "sg:city":"Collonge-bellerive",
    "sg:orig_category":"Vermietung U Verpachtung von eigenen Immobilien",
    "sg:postcode":"1245",
    "sg:province":"Gen\u00e8ve",
    "wof:name":"Bellerive-immobilier, Saland P. Immeubles Etc",
    "wof:placetype":"venue"
},
  "geometry": {"coordinates":[6.1956801414,46.255859375],"type":"Point"}
}