{
  "type": "Feature",
  "properties": {
    "iso:country":"CH",
    "sg:address":"R\u00e9sidence Neige Et Soleil",
    "sg:city":"Champ\u00e9ry",
    "sg:orig_category":"Detailhandel mit Waren verschiedener Art, Hauptrichtung Nahrungsmittel",
    "sg:phone":"+41 24 479 11 19",
    "sg:postcode":"1874",
    "sg:province":"Valais",
    "wof:name":"Coop Vaud Chablais Valaisan",
    "wof:placetype":"venue"
},
  "geometry": {"coordinates":[6.8706860542,46.1794052124],"type":"Point"}
}