{
  "type": "Feature",
  "properties": {
    "iso:country":"CH",
    "sg:address":"Toblerstrasse 76a",
    "sg:city":"Z\u00fcrich",
    "sg:orig_category":"Arztpraxen",
    "sg:phone":"+41 61 811 12 64",
    "sg:postcode":"8044",
    "sg:province":"Z\u00fcrich",
    "wof:name":"Dr.med.albert Hiltbrunner Arzt F.allgemeine Medizin Fmh",
    "wof:placetype":"venue"
},
  "geometry": {"coordinates":[7.712295,47.536655],"type":"Point"}
}