{
  "type": "Feature",
  "properties": {
    "iso:country":"CH",
    "sg:address":"Rue Du Ch\u00e2ble Bet 22",
    "sg:city":"Martigny",
    "sg:orig_category":"Grosshandel mit Blumen U Pflanzen Sonstige technische Beratung U Planung",
    "sg:phone":"+41 27 723 23 28",
    "sg:postcode":"1920",
    "sg:province":"Valais",
    "wof:name":"Valchanvre S\u00e0rl",
    "wof:placetype":"venue"
},
  "geometry": {"coordinates":[7.087706089,46.1003990173],"type":"Point"}
}