{
  "type": "Feature",
  "properties": {
    "iso:country":"CH",
    "sg:address":"Steistegstrasse 7 6430 Schwyz. Postfach 359",
    "sg:city":"Schwyz",
    "sg:orig_category":"Detailhandel mit Brillen U anderen Sehhilfen Fachdetailhandel in Verkaufsr\u00e4umen",
    "sg:postcode":"6431",
    "sg:province":"Schwyz",
    "wof:name":"Augenoptikeller Brillen Und Contactlinsen-praxis Ag",
    "wof:placetype":"venue"
},
  "geometry": {"coordinates":[8.651128,47.019382],"type":"Point"}
}