{
  "type": "Feature",
  "properties": {
    "iso:country":"CH",
    "sg:address":"Rue Du Commerce 3",
    "sg:city":"Monthey",
    "sg:orig_category":"Detailhandel mit Beleuchtungs U Haushaltsgegenst\u00e4nden Grosshandel mit sonstigen Gebrauchs U Verbrauc",
    "sg:phone":"+41 24 471 41 12",
    "sg:postcode":"1870",
    "sg:province":"Valais",
    "wof:name":"Armurerie Montheysanne Sa",
    "wof:placetype":"venue"
},
  "geometry": {"coordinates":[6.947879,46.252197],"type":"Point"}
}