{
  "type": "Feature",
  "properties": {
    "iso:country":"CH",
    "sg:address":"6705",
    "sg:city":"Cresciano",
    "sg:orig_category":"Architektur U Ingenieurb\u00fcros",
    "sg:postcode":"6705",
    "sg:province":"Ticino",
    "wof:name":"Studio Tecnico 2b Di Boer Mario-pietro E De Leoni Barbara Odis",
    "wof:placetype":"venue"
},
  "geometry": {"coordinates":[9.00375,46.281963],"type":"Point"}
}