{
  "type": "Feature",
  "properties": {
    "iso:country":"CH",
    "sg:address":"Gare",
    "sg:city":"Fribourg",
    "sg:orig_category":"Detailhandel mit Ton U Bildtr\u00e4gern Detailhandel mit elektrischen Haushalts-,Radio U Fernsehger\u00e4ten s",
    "sg:phone":"+41 26 322 52 71",
    "sg:postcode":"1700",
    "sg:province":"Fribourg",
    "wof:name":"City-disc Ag",
    "wof:placetype":"venue"
},
  "geometry": {"coordinates":[7.1506781578,46.8019294739],"type":"Point"}
}