{
  "type": "Feature",
  "properties": {
    "iso:country":"CH",
    "sg:address":"Bahnhofstrasse 24 6210 Sursee. Postfach 19",
    "sg:city":"Sursee",
    "sg:orig_category":"Detailhandel mit Bekleidung Detailhandel mit Geschenkartikeln U Souvenirs",
    "sg:phone":"+41 41 921 11 14",
    "sg:postcode":"6210",
    "sg:province":"Luzern",
    "wof:name":"Papillon Mode Ag",
    "wof:placetype":"venue"
},
  "geometry": {"coordinates":[8.103014,47.172714],"type":"Point"}
}