{
  "type": "Feature",
  "properties": {
    "iso:country":"CH",
    "sg:address":"Rheinstrasse 38",
    "sg:city":"F\u00fcllinsdorf",
    "sg:orig_category":"Sportvereine Flug Aero-Club",
    "sg:phone":"+41 61 313 28 41",
    "sg:postcode":"4414",
    "sg:province":"Basel-Landschaft",
    "wof:name":"Ae.c.s.modellfluggruppe Mbz",
    "wof:placetype":"venue"
},
  "geometry": {"coordinates":[7.7214927673,47.506187439],"type":"Point"}
}