{
  "type": "Feature",
  "properties": {
    "iso:country":"CH",
    "sg:address":"Etzelstrasse 44c",
    "sg:city":"W\u00e4denswil",
    "sg:orig_category":"Unternehmensberatung",
    "sg:phone":"+41 12020313",
    "sg:postcode":"8820",
    "sg:province":"Z\u00fcrich",
    "wof:name":"Katsura Suzuki Haltinner Consulting",
    "wof:placetype":"venue"
},
  "geometry": {"coordinates":[8.6798906326,47.2225570679],"type":"Point"}
}