{
  "type": "Feature",
  "properties": {
    "iso:country":"CH",
    "sg:address":"Industriestrasse 28",
    "sg:city":"Br\u00fcgg",
    "sg:classifiers":[
        {
            "category":"Manufacturing",
            "subcategory":"Metals",
            "type":"Manufacturing & Wholesale Goods"
        }
    ],
    "sg:phone":"+41 32 374 40 10",
    "sg:postcode":"2555",
    "sg:province":"Bern",
    "sg:tags":[
        "blanking",
        "dy"
    ],
    "wof:name":"Realtools Ag",
    "wof:placetype":"venue"
},
  "geometry": {"coordinates":[7.268397,47.122265],"type":"Point"}
}