{
  "type": "Feature",
  "properties": {
    "iso:country":"CH",
    "sg:address":"Hauptstrasse 33",
    "sg:city":"M\u00fclligen",
    "sg:orig_category":"Sonstiger Fachdetailhandel mit Nahrungsmitteln, Getr\u00e4nken U Tabak in Verkaufsr\u00e4umen",
    "sg:phone":"+41 56 225 02 29",
    "sg:postcode":"5243",
    "sg:province":"Aargau",
    "wof:name":"Ganzheitliches Naturzentrum",
    "wof:placetype":"venue"
},
  "geometry": {"coordinates":[8.2398996353,47.4578971863],"type":"Point"}
}