{
  "type": "Feature",
  "properties": {
    "iso:country":"CH",
    "sg:address":"Via Riasco 26 6614 Brissago. Postfach Caselle Postale 746",
    "sg:city":"Brissago",
    "sg:orig_category":"Effektenvermittlung Broker",
    "sg:phone":"+41 91 793 31 33",
    "sg:postcode":"6614",
    "sg:province":"Ticino",
    "wof:name":"Atv Analisi Tecnica Di Valori Sa",
    "wof:placetype":"venue"
},
  "geometry": {"coordinates":[8.7157869339,46.1288032532],"type":"Point"}
}