{
  "type": "Feature",
  "properties": {
    "iso:country":"CH",
    "sg:address":"Scheuermattweg 32",
    "sg:city":"R\u00fcnenberg",
    "sg:orig_category":"Herstellung von keramischen Haushaltswaren U Ziergegenst\u00e4nden",
    "sg:phone":"+41 61 981 43 30",
    "sg:postcode":"4497",
    "sg:province":"Basel-Landschaft",
    "wof:name":"Keramikwerkstatt O.platten",
    "wof:placetype":"venue"
},
  "geometry": {"coordinates":[7.8825039864,47.4362068176],"type":"Point"}
}