{
  "type": "Feature",
  "properties": {
    "iso:country":"CH",
    "sg:address":"Pilatusstrasse 12 6004 Luzern. Postfach",
    "sg:city":"Luzern",
    "sg:orig_category":"Reiseb\u00fcros U Reiseveranstalter",
    "sg:phone":"+41 41 210 25 25",
    "sg:postcode":"6002",
    "sg:province":"Luzern",
    "wof:name":"Hotelplan Internationale Reiseorganisation Ag",
    "wof:placetype":"venue"
},
  "geometry": {"coordinates":[8.3069782257,47.0493927002],"type":"Point"}
}