{
  "type": "Feature",
  "properties": {
    "iso:country":"CH",
    "sg:address":"Missionsstrasse 57",
    "sg:city":"Basel",
    "sg:orig_category":"Fachdetailhandel mit pharmazeutischen Produkten",
    "sg:phone":"+41 61 381 83 43",
    "sg:postcode":"4055",
    "sg:province":"Basel-Stadt",
    "wof:name":"Pilger Apotheke Dr. Ch. Meier Und Dr. R. Rupf",
    "wof:placetype":"venue"
},
  "geometry": {"coordinates":[7.5752968788,47.5609092712],"type":"Point"}
}