{
  "type": "Feature",
  "properties": {
    "iso:country":"CH",
    "sg:address":"S\u00e4gem\u00fchle",
    "sg:city":"Roggenburg",
    "sg:orig_category":"Landwirtschaftliche Ger\u00e4te Grosshandel",
    "sg:phone":"+41 32 431 19 08",
    "sg:postcode":"2814",
    "sg:province":"Basel-Landschaft",
    "wof:name":"Stawa Agritec Gmbh Delaval-service",
    "wof:placetype":"venue"
},
  "geometry": {"coordinates":[7.3386530876,47.4397010803],"type":"Point"}
}