{
  "type": "Feature",
  "properties": {
    "iso:country":"CH",
    "sg:address":"Vogelackerstrasse 12",
    "sg:city":"Guntershausen",
    "sg:orig_category":"Wasserversorgung",
    "sg:phone":"+41 71 455 17 51",
    "sg:postcode":"8357",
    "sg:province":"Thurgau",
    "wof:name":"Wasserkorporation Berg Bruno Eigenmann",
    "wof:placetype":"venue"
},
  "geometry": {"coordinates":[9.4173192978,47.4896469116],"type":"Point"}
}