{
  "type": "Feature",
  "properties": {
    "iso:country":"CH",
    "sg:address":"Riedenweg 15.",
    "sg:city":"Nunningen",
    "sg:orig_category":"G\u00fcterbef\u00f6rderung im Strassenverkehr",
    "sg:phone":"+41 61 791 00 75",
    "sg:postcode":"4208",
    "sg:province":"Solothurn",
    "wof:name":"Weishaupt Paul.",
    "wof:placetype":"venue"
},
  "geometry": {"coordinates":[7.6185708046,47.3962020874],"type":"Point"}
}