{
  "type": "Feature",
  "properties": {
    "iso:country":"CH",
    "sg:address":"Mythenstrasse 7",
    "sg:city":"Luzern",
    "sg:orig_category":"Fotografische Ateliers",
    "sg:phone":"+41 71 279 10 82",
    "sg:postcode":"6003",
    "sg:province":"Luzern",
    "wof:name":"Stefan Rohner Fotografisches Atelier",
    "wof:placetype":"venue"
},
  "geometry": {"coordinates":[9.3357839584,47.4102172852],"type":"Point"}
}