{
  "type": "Feature",
  "properties": {
    "iso:country":"CH",
    "sg:address":"Grand-rue 60",
    "sg:city":"Reconvilier",
    "sg:orig_category":"Notariate",
    "sg:phone":"+41 32 481 24 24",
    "sg:postcode":"2732",
    "sg:province":"Bern",
    "wof:name":"Boris Hunsperger Etude De Notaire",
    "wof:placetype":"venue"
},
  "geometry": {"coordinates":[7.2285790443,47.2349891663],"type":"Point"}
}