{
  "type": "Feature",
  "properties": {
    "iso:country":"CH",
    "sg:address":"Egelgasse 50",
    "sg:city":"Bern",
    "sg:orig_category":"Vorschulen, Kinderg\u00e4rten",
    "sg:phone":"+41 17130320",
    "sg:postcode":"3006",
    "sg:province":"Bern",
    "wof:name":"Kindergarten Eggwies",
    "wof:placetype":"venue"
},
  "geometry": {"coordinates":[8.5347690582,47.2846336365],"type":"Point"}
}