{
  "type": "Feature",
  "properties": {
    "iso:country":"CH",
    "sg:address":"A\u00efre Avenue D' 46",
    "sg:city":"Gen\u00e8ve",
    "sg:orig_category":"Unclassifiable Establishments",
    "sg:postcode":"1203",
    "sg:province":"Gen\u00e8ve",
    "wof:name":"A.l.i.c.e. (artisanat, Loisirs, Infographie Par Commerce Electronique), Stange",
    "wof:placetype":"venue"
},
  "geometry": {"coordinates":[6.1226501465,46.208190918],"type":"Point"}
}