{
  "type": "Feature",
  "properties": {
    "iso:country":"CH",
    "sg:address":"Klosterstrasse 16 6003 Luzern. Postfach",
    "sg:city":"Luzern",
    "sg:orig_category":"Softwareentwicklung U beratung",
    "sg:phone":"+41 41 242 01 73",
    "sg:postcode":"6003",
    "sg:province":"Luzern",
    "wof:name":"Softtools Gmbh Vermittlung Von Wissen Im Umgang Mit Computersoftware Usw",
    "wof:placetype":"venue"
},
  "geometry": {"coordinates":[8.2992696762,47.0488891602],"type":"Point"}
}