{
  "type": "Feature",
  "properties": {
    "addr:full":"Hinterer Schermen 44 Ittigen Bern 3063",
    "addr:housenumber":"44",
    "addr:postcode":"3063",
    "addr:street":"Hinterer Schermen",
    "iso:country":"CH",
    "sg:address":"Hinterer Schermen 44",
    "sg:city":"Ittigen",
    "sg:orig_category":"Architektur U Ingenieurb\u00fcros",
    "sg:phone":"+41 79 301 77 20",
    "sg:postcode":"3063",
    "sg:province":"Bern",
    "wof:name":"Marti Hans Planungen",
    "wof:placetype":"venue"
},
  "geometry": {"coordinates":[7.4824,46.972759],"type":"Point"}
}