{
  "type": "Feature",
  "properties": {
    "addr:full":"7743 Brusio Graubunden 7743",
    "addr:housenumber":"7743",
    "addr:postcode":"7743",
    "addr:street":"Brusio Graubunden",
    "iso:country":"CH",
    "sg:address":"7743",
    "sg:city":"Brusio",
    "sg:orig_category":"Autogaragen",
    "sg:phone":"+41 81 846 55 55",
    "sg:postcode":"7743",
    "sg:province":"Graubunden",
    "wof:name":"Remo Ferrari Garage Pergola",
    "wof:placetype":"venue"
},
  "geometry": {"coordinates":[10.125009,46.2589],"type":"Point"}
}