{
  "type": "Feature",
  "properties": {
    "iso:country":"CH",
    "sg:address":"Schimmelstrasse 2 8003 Z\u00fcrich. Postfach",
    "sg:city":"Z\u00fcrich",
    "sg:orig_category":"Non-Classified Establishments",
    "sg:postcode":"8003",
    "sg:province":"Z\u00fcrich",
    "wof:name":"Pizza-hauslieferdienst, Lendi Pizza Und Teigwaren-hauslieferdienst",
    "wof:placetype":"venue"
},
  "geometry": {"coordinates":[8.525891304,47.3695144653],"type":"Point"}
}