{
  "type": "Feature",
  "properties": {
    "iso:country":"CH",
    "sg:address":"Missionsstrasse 56",
    "sg:city":"Basel",
    "sg:orig_category":"Malerei",
    "sg:phone":"+41 79484954663937",
    "sg:postcode":"4055",
    "sg:province":"Basel-Stadt",
    "wof:name":"Maleratelier Ren\u00e9 Meyer",
    "wof:placetype":"venue"
},
  "geometry": {"coordinates":[7.5756859779,47.5609931946],"type":"Point"}
}