{
  "type": "Feature",
  "properties": {
    "iso:country":"CH",
    "sg:address":"Promenade",
    "sg:city":"Gstaad",
    "sg:orig_category":"Detailhandel mit Blumen U Pflanzen",
    "sg:phone":"+41 33 748 99 12",
    "sg:postcode":"3780",
    "sg:province":"Bern",
    "wof:name":"Wittwer Blumen Gartenbau Ag",
    "wof:placetype":"venue"
},
  "geometry": {"coordinates":[7.2865,46.472954],"type":"Point"}
}