{
  "type": "Feature",
  "properties": {
    "iso:country":"CH",
    "sg:address":"Helv\u00e9tique Bvd 27",
    "sg:city":"Gen\u00e8ve",
    "sg:orig_category":"Erbringung von Dienstleistungen f\u00fcr Unternehmen",
    "sg:postcode":"1207",
    "sg:province":"Gen\u00e8ve",
    "wof:name":"Centre Intercantonal D'information Sur Les Croyances Et Sur Les Activit\u00e9s Des Groupements \u00e0 Caract\u00e8re Spirituel, Religieux Ou \u00e9sot\u00e9rique",
    "wof:placetype":"venue"
},
  "geometry": {"coordinates":[6.1546468735,46.2018013],"type":"Point"}
}