{
  "type": "Feature",
  "properties": {
    "iso:country":"CH",
    "sg:address":"Rue Des Alpes 8 1196 Gland. Postfach",
    "sg:city":"Gland",
    "sg:orig_category":"Softwareentwicklung U beratung",
    "sg:postcode":"1196",
    "sg:province":"Vaud",
    "wof:name":"A.m.c.i. Molleyres Alexandre Consultant Informatique",
    "wof:placetype":"venue"
},
  "geometry": {"coordinates":[6.277176857,46.4186553955],"type":"Point"}
}