{
  "type": "Feature",
  "properties": {
    "iso:country":"CH",
    "sg:address":"Industrie Hegi 1a Postfach 28",
    "sg:city":"Thal",
    "sg:classifiers":[
        {
            "category":"Shopping",
            "subcategory":"Computers & Home Electronics",
            "type":"Retail Goods"
        }
    ],
    "sg:phone":"+41 71 886 46 46",
    "sg:postcode":"9425",
    "sg:province":"St. Gallen",
    "sg:tags":[
        "electronic",
        "electrical",
        "equipment"
    ],
    "wof:name":"Dorma Schweiz Ag",
    "wof:placetype":"venue"
},
  "geometry": {"coordinates":[8.6740636826,47.5308074951],"type":"Point"}
}