{
  "type": "Feature",
  "properties": {
    "iso:country":"CH",
    "sg:address":"Oberwilen.",
    "sg:city":"Sarnen",
    "sg:orig_category":"S\u00e4ge, Hobel U Holzimpr\u00e4gnierwerke",
    "sg:postcode":"6060",
    "sg:province":"Obwalden",
    "wof:name":"Burgener Christoph, S\u00e4gerei, Zimmerei",
    "wof:placetype":"venue"
},
  "geometry": {"coordinates":[7.9329299927,46.1355247498],"type":"Point"}
}