{
  "type": "Feature",
  "properties": {
    "iso:country":"CH",
    "sg:address":"Oltnerstrasse 502",
    "sg:city":"Egerkingen",
    "sg:orig_category":"G\u00fcterbef\u00f6rderung im Strassenverkehr",
    "sg:phone":"+41 32 925 90 90",
    "sg:postcode":"4622",
    "sg:province":"Solothurn",
    "wof:name":"Von Bergen Sa",
    "wof:placetype":"venue"
},
  "geometry": {"coordinates":[6.7831630707,47.0778656006],"type":"Point"}
}