{
  "type": "Feature",
  "properties": {
    "iso:country":"CH",
    "sg:address":"Steinackerstrasse 24 8902 Urdorf. Postfach",
    "sg:city":"Urdorf",
    "sg:orig_category":"Detailhandel mit Metallwaren, Anstrichmitteln, Glaswaren, Bau U Heimwerkerbedarf",
    "sg:postcode":"8902",
    "sg:province":"Z\u00fcrich",
    "wof:name":"N\u00fcesch-engineering Gmbh",
    "wof:placetype":"venue"
},
  "geometry": {"coordinates":[8.4219274521,47.3946533203],"type":"Point"}
}