{
  "type": "Feature",
  "properties": {
    "iso:country":"CH",
    "sg:address":"Rue De La Promenade 36",
    "sg:city":"Tramelan",
    "sg:orig_category":"Sportvereine Ballsport Tischtennis",
    "sg:phone":"+41 32 487 57 25",
    "sg:postcode":"2720",
    "sg:province":"Bern",
    "wof:name":"Ctt Tramelan",
    "wof:placetype":"venue"
},
  "geometry": {"coordinates":[7.0964369774,47.2211685181],"type":"Point"}
}