{
  "type": "Feature",
  "properties": {
    "iso:country":"CH",
    "sg:address":"Corso San Gottardo 14",
    "sg:city":"Chiasso",
    "sg:orig_category":"Detailhandel mit Bekleidung Detailhandel mit Geschenkartikeln U Souvenirs",
    "sg:phone":"+41 91 682 67 38",
    "sg:postcode":"6830",
    "sg:province":"Ticino",
    "wof:name":"Boutique Moda In Bruna Realini",
    "wof:placetype":"venue"
},
  "geometry": {"coordinates":[9.032182,45.833126],"type":"Point"}
}