{
  "type": "Feature",
  "properties": {
    "addr:full":"Allmendstrasse 5 Gelterkinden Basel-Landschaft 4460",
    "addr:housenumber":"5",
    "addr:postcode":"4460",
    "addr:street":"Allmendstrasse",
    "iso:country":"CH",
    "sg:address":"Allmendstrasse 5",
    "sg:city":"Gelterkinden",
    "sg:orig_category":"Blumen U Zierpflanzenbau Detailhandel mit Blumen U Pflanzen",
    "sg:phone":"+41 71 455 12 84",
    "sg:postcode":"4460",
    "sg:province":"Basel-Landschaft",
    "wof:name":"Ernst Lauchenauer",
    "wof:placetype":"venue"
},
  "geometry": {"coordinates":[9.3935,47.498535],"type":"Point"}
}