{
  "type": "Feature",
  "properties": {
    "addr:full":"Forchstrasse 61 Herrliberg Z\u00fcrich 8704",
    "addr:housenumber":"61",
    "addr:postcode":"8704",
    "addr:street":"Forchstrasse",
    "iso:country":"CH",
    "sg:address":"Forchstrasse 61",
    "sg:city":"Herrliberg",
    "sg:classifiers":[
        {
            "category":"Banks & Credit Unions",
            "subcategory":"Bank",
            "type":"Services"
        }
    ],
    "sg:phone":"+41 19153901",
    "sg:postcode":"8704",
    "sg:province":"Z\u00fcrich",
    "wof:name":"Schweiz. Mobiliar",
    "wof:placetype":"venue"
},
  "geometry": {"coordinates":[8.614283,47.286682],"type":"Point"}
}