{
  "type": "Feature",
  "properties": {
    "iso:country":"CH",
    "sg:address":"Sassenloh 8507 Salen-reutenen. Postfach",
    "sg:city":"Salen-reutenen",
    "sg:orig_category":"Herstellung von Werkzeugen",
    "sg:postcode":"8507",
    "sg:province":"Thurgau",
    "wof:name":"Silent Diamond Gmbh",
    "wof:placetype":"venue"
},
  "geometry": {"coordinates":[8.9711790085,47.6326408386],"type":"Point"}
}