{
  "type": "Feature",
  "properties": {
    "iso:country":"CH",
    "sg:address":"Churfirstenstrasse 6",
    "sg:city":"Walenstadt",
    "sg:orig_category":"Vereine Vogel-& Naturschutz",
    "sg:phone":"+41 81 735 15 50",
    "sg:postcode":"8880",
    "sg:province":"St. Gallen",
    "wof:name":"Ornithologischer Verein",
    "wof:placetype":"venue"
},
  "geometry": {"coordinates":[9.3100347519,47.1245040894],"type":"Point"}
}