{
  "type": "Feature",
  "properties": {
    "iso:country":"CH",
    "sg:address":"Sch\u00f6nried.",
    "sg:city":"Saanen",
    "sg:orig_category":"Sonstiger spezialisierter Hoch U Tiefbau",
    "sg:postcode":"3792",
    "sg:province":"Bern",
    "wof:name":"Ernst Jaggi",
    "wof:placetype":"venue"
},
  "geometry": {"coordinates":[7.2691807747,46.5160903931],"type":"Point"}
}