{
  "type": "Feature",
  "properties": {
    "iso:country":"CH",
    "sg:address":"Dufourstrasse 94",
    "sg:city":"Z\u00fcrich",
    "sg:orig_category":"Gesundheitswesen",
    "sg:phone":"+41 41 632 62 32",
    "sg:postcode":"8008",
    "sg:province":"Z\u00fcrich",
    "wof:name":"Adistra \u00c4rzte-genossenschaft",
    "wof:placetype":"venue"
},
  "geometry": {"coordinates":[8.3104372025,46.9823074341],"type":"Point"}
}