{
  "type": "Feature",
  "properties": {
    "iso:country":"CH",
    "sg:address":"Allenwindenstrasse 1",
    "sg:city":"Flurlingen",
    "sg:orig_category":"Grosshandel mit B\u00fcromaschinen Grosshandel mit Datenverarbeitungsger\u00e4ten",
    "sg:phone":"+41 79 227 02 57",
    "sg:postcode":"8247",
    "sg:province":"Z\u00fcrich",
    "wof:name":"Bettschen Elektronik Ag Engineering & Hardware",
    "wof:placetype":"venue"
},
  "geometry": {"coordinates":[8.6311950684,47.6888389587],"type":"Point"}
}