{
  "type": "Feature",
  "properties": {
    "iso:country":"CH",
    "sg:address":"Bahnhofstrasse 1",
    "sg:city":"T\u00e4gerwilen",
    "sg:orig_category":"Detailhandel mit Milcherzeugnissen U Eiern Verwertung von Milch",
    "sg:phone":"+41 26 652 21 72",
    "sg:postcode":"8274",
    "sg:province":"Thurgau",
    "wof:name":"Dumas Eug\u00e8ne",
    "wof:placetype":"venue"
},
  "geometry": {"coordinates":[6.9275698662,46.6799888611],"type":"Point"}
}