{
  "type": "Feature",
  "properties": {
    "iso:country":"CH",
    "sg:address":"Althardstrasse 120",
    "sg:city":"Regensdorf",
    "sg:orig_category":"Unclassifiable Establishments",
    "sg:postcode":"8105",
    "sg:province":"Z\u00fcrich",
    "wof:name":"Gerig Consulting Gmbh",
    "wof:placetype":"venue"
},
  "geometry": {"coordinates":[8.7607221603,47.4835586548],"type":"Point"}
}