{
  "type": "Feature",
  "properties": {
    "iso:country":"CH",
    "sg:address":"Chiesa Via Alla 6",
    "sg:city":"Capolago",
    "sg:orig_category":"Instandhaltung U Reparatur von Automobilen",
    "sg:postcode":"6825",
    "sg:province":"Ticino",
    "wof:name":"Valli Car",
    "wof:placetype":"venue"
},
  "geometry": {"coordinates":[8.9798841476,45.9038963318],"type":"Point"}
}