{
  "type": "Feature",
  "properties": {
    "iso:country":"CH",
    "sg:address":"Avenue De Lonay 19",
    "sg:city":"Morges",
    "sg:orig_category":"G\u00fcterbef\u00f6rderung im Strassenverkehr",
    "sg:phone":"+41 21 801 19 68",
    "sg:postcode":"1110",
    "sg:province":"Vaud",
    "wof:name":"Henri Gohl Transports & D\u00e9m\u00e9nagements",
    "wof:placetype":"venue"
},
  "geometry": {"coordinates":[6.5080962181,46.5194892883],"type":"Point"}
}