{
  "type": "Feature",
  "properties": {
    "iso:country":"CH",
    "sg:address":"Benziwil 23/165 6032 Emmen. Postfach",
    "sg:city":"Emmenbr\u00fccke",
    "sg:orig_category":"Versandhandel",
    "sg:phone":"+41 62 823 24 44",
    "sg:postcode":"6020",
    "sg:province":"Luzern",
    "wof:name":"Dvd-shop Ag",
    "wof:placetype":"venue"
},
  "geometry": {"coordinates":[8.0869503021,47.4043197632],"type":"Point"}
}