{
  "type": "Feature",
  "properties": {
    "iso:country":"CH",
    "sg:address":"Rebenstrasse 9",
    "sg:city":"Rossr\u00fcti",
    "sg:orig_category":"Maurerarbeiten Verlegen von Fussboden",
    "sg:postcode":"9512",
    "sg:province":"St. Gallen",
    "wof:name":"Leo Haag Ag",
    "wof:placetype":"venue"
},
  "geometry": {"coordinates":[9.0578994751,47.4761161804],"type":"Point"}
}