{
  "type": "Feature",
  "properties": {
    "iso:country":"CH",
    "sg:address":"Impasse Des Eglatines 1",
    "sg:city":"Fribourg",
    "sg:orig_category":"Unclassifiable Establishments",
    "sg:postcode":"1700",
    "sg:province":"Fribourg",
    "wof:name":"Kapy Sa",
    "wof:placetype":"venue"
},
  "geometry": {"coordinates":[7.1723389626,46.8086280823],"type":"Point"}
}