{
  "type": "Feature",
  "properties": {
    "iso:country":"CH",
    "sg:address":"Comercialstr. 20",
    "sg:city":"Chur",
    "sg:classifiers":[
        {
            "category":"Professional",
            "subcategory":"Advertising",
            "type":"Services"
        }
    ],
    "sg:phone":"+41 81 257 10 10",
    "sg:postcode":"7000",
    "sg:province":"Graubunden",
    "sg:tags":[
        "information",
        "medium",
        "communication"
    ],
    "wof:name":"Prisma Ag",
    "wof:placetype":"venue"
},
  "geometry": {"coordinates":[9.509887,46.847504],"type":"Point"}
}