{
  "type": "Feature",
  "properties": {
    "iso:country":"CH",
    "sg:address":"Kreuzstrasse",
    "sg:city":"Stans",
    "sg:orig_category":"Strassenverkehrs\u00e4mter and -inspektorate",
    "sg:phone":"+41 55 647 36 00",
    "sg:postcode":"6370",
    "sg:province":"Nidwalden",
    "wof:name":"Strassenverkehrsamt Des Kantons Glarus",
    "wof:placetype":"venue"
},
  "geometry": {"coordinates":[9.0761623383,46.9940757751],"type":"Point"}
}