{
  "type": "Feature",
  "properties": {
    "iso:country":"CH",
    "sg:address":"Rossfeldstrasse 27 3004 Bern. Postfach",
    "sg:city":"Bern",
    "sg:orig_category":"Betrieb U technische Hilfsdienste des Kultur U Unterhaltungswesens",
    "sg:phone":"+41 31 302 86 05",
    "sg:postcode":"3003",
    "sg:province":"Bern",
    "wof:name":"Human Events Jungi Lorenz Coaching. Events; Beratungen, Schulungen Usw",
    "wof:placetype":"venue"
},
  "geometry": {"coordinates":[7.444381,46.97197],"type":"Point"}
}