{
  "type": "Feature",
  "properties": {
    "iso:country":"CH",
    "sg:address":"Aeschenvorstadt 25 4051 Basel. Postfach",
    "sg:city":"Basel",
    "sg:orig_category":"Arztpraxen",
    "sg:phone":"+41 61 261 99 30",
    "sg:postcode":"4001",
    "sg:province":"Basel-Stadt",
    "wof:name":"Dr.med.thomas Andreas Cueni Spezialarzt",
    "wof:placetype":"venue"
},
  "geometry": {"coordinates":[7.592998,47.553082],"type":"Point"}
}