{
  "type": "Feature",
  "properties": {
    "iso:country":"CH",
    "sg:address":"Schulhausstrasse 73",
    "sg:city":"Z\u00fcrich",
    "sg:orig_category":"Ingenieurb\u00fcros Umwelttechnik and \u00d6kologie",
    "sg:phone":"+41 12028180",
    "sg:postcode":"8002",
    "sg:province":"Z\u00fcrich",
    "wof:name":"Susanna Z\u00fcst Umweltberatung",
    "wof:placetype":"venue"
},
  "geometry": {"coordinates":[8.5252981186,47.3601913452],"type":"Point"}
}