{
  "type": "Feature",
  "properties": {
    "iso:country":"CH",
    "sg:address":"Winkelstrasse 20 2502 Biel/bienne Case Postale 885",
    "sg:city":"Biel/bienne",
    "sg:orig_category":"Lichtpause U Reprografiebetriebe Offsetdruck",
    "sg:phone":"+41 32 322 44 22",
    "sg:postcode":"2501",
    "sg:province":"Bern",
    "wof:name":"Copytrend Ag Biel Reproduktionen, Heliographie, Plandruck Usw; Herstellung, Handel",
    "wof:placetype":"venue"
},
  "geometry": {"coordinates":[7.2462611198,47.1352806091],"type":"Point"}
}