{
  "type": "Feature",
  "properties": {
    "iso:country":"CH",
    "sg:address":"Chemin De Blandonnet 8",
    "sg:city":"Vernier",
    "sg:orig_category":"Unclassifiable Establishments",
    "sg:postcode":"1214",
    "sg:province":"Gen\u00e8ve",
    "wof:name":"Fiba F\u00e9d\u00e9ration Internationale De Basketball",
    "wof:placetype":"venue"
},
  "geometry": {"coordinates":[6.0985169411,46.2210502625],"type":"Point"}
}