{
  "type": "Feature",
  "properties": {
    "iso:country":"CH",
    "sg:address":"Gloriastrasse 66",
    "sg:city":"Z\u00fcrich",
    "sg:orig_category":"Unternehmensberatung",
    "sg:phone":"+41 12510023",
    "sg:postcode":"8044",
    "sg:province":"Z\u00fcrich",
    "wof:name":"Biland Lic. Oec. Susan, Controlling Consulting Betriebswirtschaftl. Controlling Usw.",
    "wof:placetype":"venue"
},
  "geometry": {"coordinates":[8.5562343597,47.3759307861],"type":"Point"}
}