{
  "type": "Feature",
  "properties": {
    "iso:country":"CH",
    "sg:address":"Blumenweg 14",
    "sg:city":"Andermatt",
    "sg:orig_category":"Maler U Glasergewerbe",
    "sg:postcode":"6490",
    "sg:province":"Uri",
    "wof:name":"Hughes-marcacci Bruna",
    "wof:placetype":"venue"
},
  "geometry": {"coordinates":[8.5951929092,46.6338233948],"type":"Point"}
}