{
  "type": "Feature",
  "properties": {
    "iso:country":"CH",
    "sg:address":"1180",
    "sg:city":"Rolle",
    "sg:orig_category":"Vereine Briefmarkensammler",
    "sg:postcode":"1180",
    "sg:province":"Vaud",
    "wof:name":"St\u00e9 Philat\u00e9lique S\u00e9dunoise",
    "wof:placetype":"venue"
},
  "geometry": {"coordinates":[7.347867012,46.2335968018],"type":"Point"}
}