{
  "type": "Feature",
  "properties": {
    "iso:country":"CH",
    "sg:address":"Neuhof",
    "sg:city":"Volketswil",
    "sg:orig_category":"Verwertung von Milch",
    "sg:postcode":"8604",
    "sg:province":"Z\u00fcrich",
    "wof:name":"Milchgenossenschaft Volketswil",
    "wof:placetype":"venue"
},
  "geometry": {"coordinates":[8.6963806152,47.3979492188],"type":"Point"}
}