{
  "type": "Feature",
  "properties": {
    "iso:country":"CH",
    "sg:address":"Curtgegn Davos",
    "sg:city":"Pratval",
    "sg:orig_category":"Informatikschulen",
    "sg:phone":"+41 81 655 15 32",
    "sg:postcode":"7415",
    "sg:province":"Graubunden",
    "wof:name":"Brigitte Barandun Computerschule",
    "wof:placetype":"venue"
},
  "geometry": {"coordinates":[9.4455299377,46.7330551147],"type":"Point"}
}