{
  "type": "Feature",
  "properties": {
    "iso:country":"CH",
    "sg:address":"Au Glapin",
    "sg:city":"St-prex",
    "sg:orig_category":"Datenverarbeitungsdienste Softwareentwicklung U beratung",
    "sg:phone":"+41 21 806 24 49",
    "sg:postcode":"1162",
    "sg:province":"Vaud",
    "wof:name":"Dodeica, Solliard Christian",
    "wof:placetype":"venue"
},
  "geometry": {"coordinates":[6.45895,46.486874],"type":"Point"}
}