{
  "type": "Feature",
  "properties": {
    "iso:country":"CH",
    "sg:address":"R\u00f6ntgenstrasse 6",
    "sg:city":"Z\u00fcrich",
    "sg:orig_category":"Bauschreinerei",
    "sg:phone":"+41 12715448",
    "sg:postcode":"8005",
    "sg:province":"Z\u00fcrich",
    "wof:name":"Ubaldo Gianini Schreinerei",
    "wof:placetype":"venue"
},
  "geometry": {"coordinates":[8.528767,47.382225],"type":"Point"}
}