{
  "type": "Feature",
  "properties": {
    "iso:country":"CH",
    "sg:address":"Heiterschenstrasse 15",
    "sg:city":"W\u00e4ngi",
    "sg:classifiers":[
        {
            "category":"Travel",
            "subcategory":"Hotels & Motels",
            "type":"Entertainment"
        }
    ],
    "sg:phone":"+41 52 378 12 18",
    "sg:postcode":"9545",
    "sg:province":"Thurgau",
    "sg:tags":[
        "hotels",
        "mit",
        "restaurant"
    ],
    "wof:name":"B\u00e4ren Heiterschen Ag",
    "wof:placetype":"venue"
},
  "geometry": {"coordinates":[8.9461097717,47.5028495789],"type":"Point"}
}