{
  "type": "Feature",
  "properties": {
    "iso:country":"CH",
    "sg:address":"Industriestrasse 39",
    "sg:city":"Dietlikon",
    "sg:orig_category":"Handel mit Automobilen",
    "sg:phone":"+41 18337200",
    "sg:postcode":"8305",
    "sg:province":"Z\u00fcrich",
    "wof:name":"Acd Auto-center Dietlikon Gmbh",
    "wof:placetype":"venue"
},
  "geometry": {"coordinates":[8.6169672012,47.4114646912],"type":"Point"}
}