{
  "type": "Feature",
  "properties": {
    "iso:country":"CH",
    "sg:address":"Rue De La Plaine 15",
    "sg:city":"Yverdon-les-bains",
    "sg:orig_category":"Grosshandel mit Getreide, Saatgut U Futtermitteln Handelsvermittlung U Grosshandel",
    "sg:phone":"+41 24 425 66 56",
    "sg:postcode":"1400",
    "sg:province":"Vaud",
    "wof:name":"\u00abla Ferme\u00bb - Roy G\u00e9rard S\u00e0rl",
    "wof:placetype":"venue"
},
  "geometry": {"coordinates":[6.6431441307,46.7778816223],"type":"Point"}
}