{
  "type": "Feature",
  "properties": {
    "iso:country":"CH",
    "sg:address":"Aegertaweg",
    "sg:city":"Churwalden",
    "sg:orig_category":"Herstellung von k\u00e4lte U lufttechnischen Erzeugnissen f\u00fcr gewerbliche Zwecke",
    "sg:postcode":"7075",
    "sg:province":"Graubunden",
    "wof:name":"Dreher Markus Gmbh",
    "wof:placetype":"venue"
},
  "geometry": {"coordinates":[8.7278995514,47.2013206482],"type":"Point"}
}