{
  "type": "Feature",
  "properties": {
    "iso:country":"CH",
    "sg:address":"Worbigstrasse 14",
    "sg:city":"Flaach",
    "sg:orig_category":"Malerei",
    "sg:phone":"+41 52 318 12 62",
    "sg:postcode":"8416",
    "sg:province":"Z\u00fcrich",
    "wof:name":"Rolf Schuler Malergesch\u00e4ft",
    "wof:placetype":"venue"
},
  "geometry": {"coordinates":[8.6144256592,47.5756645203],"type":"Point"}
}