{
  "type": "Feature",
  "properties": {
    "iso:country":"CH",
    "sg:address":"Rittergasse 25 4051 Basel. Postfach",
    "sg:city":"Basel",
    "sg:orig_category":"Unclassifiable Establishments",
    "sg:phone":"+41 61 286 44 00",
    "sg:postcode":"4051",
    "sg:province":"Basel-Stadt",
    "wof:name":"Munden Holding Ag Beteiligungen",
    "wof:placetype":"venue"
},
  "geometry": {"coordinates":[7.5936670303,47.5552787781],"type":"Point"}
}