{
  "type": "Feature",
  "properties": {
    "addr:full":"Brisenstrasse 13 Emmenbr\u00fccke Luzern 6020",
    "addr:housenumber":"13",
    "addr:postcode":"6020",
    "addr:street":"Brisenstrasse",
    "iso:country":"CH",
    "sg:address":"Brisenstrasse 13",
    "sg:city":"Emmenbr\u00fccke",
    "sg:orig_category":"Autotransporte M\u00f6bel Autotransporte international",
    "sg:phone":"+41 41 281 04 48",
    "sg:postcode":"6020",
    "sg:province":"Luzern",
    "wof:name":"Packimpex Ag Int.umz\u00fcge & Lagerung",
    "wof:placetype":"venue"
},
  "geometry": {"coordinates":[8.269428,47.077698],"type":"Point"}
}