{
  "type": "Feature",
  "properties": {
    "iso:country":"CH",
    "sg:address":"Luzernerstrasse 138",
    "sg:city":"Littau",
    "sg:orig_category":"Herstellung von Baubedarfsartikeln aus Kunststoff",
    "sg:phone":"+41 41 250 00 11",
    "sg:postcode":"6014",
    "sg:province":"Luzern",
    "wof:name":"Kufag Ag Kunststoff-fensterbau",
    "wof:placetype":"venue"
},
  "geometry": {"coordinates":[8.2638511658,47.0496864319],"type":"Point"}
}