{
  "type": "Feature",
  "properties": {
    "iso:country":"CH",
    "sg:address":"Grundweg 8",
    "sg:city":"Sax",
    "sg:orig_category":"Datenverarbeitungsdienste Unternehmensberatung",
    "sg:phone":"+41 81 740 43 34",
    "sg:postcode":"9468",
    "sg:province":"St. Gallen",
    "wof:name":"Cicero Consult Daniel Rauner",
    "wof:placetype":"venue"
},
  "geometry": {"coordinates":[9.45309,47.226254],"type":"Point"}
}