{
  "type": "Feature",
  "properties": {
    "iso:country":"CH",
    "sg:address":"R\u00fcmelinbachweg 21",
    "sg:city":"Basel",
    "sg:orig_category":"Arztpraxen",
    "sg:phone":"+41 32 631 22 22",
    "sg:postcode":"4054",
    "sg:province":"Basel-Stadt",
    "wof:name":"Dr.med.rainer Claus Spezialarzt Fmh",
    "wof:placetype":"venue"
},
  "geometry": {"coordinates":[7.656098,47.234413],"type":"Point"}
}