{
  "type": "Feature",
  "properties": {
    "iso:country":"CH",
    "sg:address":"Fuchsronstrasse 6",
    "sg:city":"Galgenen",
    "sg:orig_category":"Sonstiges Gesundheitswesen",
    "sg:phone":"+41 55 440 35 13",
    "sg:postcode":"8854",
    "sg:province":"Schwyz",
    "wof:name":"Krankenmobilien Frau Marlies Ziegler",
    "wof:placetype":"venue"
},
  "geometry": {"coordinates":[8.8691473007,47.1791954041],"type":"Point"}
}