{
  "type": "Feature",
  "properties": {
    "iso:country":"CH",
    "sg:address":"Franscini Viale 17",
    "sg:city":"Lugano",
    "sg:orig_category":"Non-Classified Establishments",
    "sg:postcode":"6900",
    "sg:province":"Ticino",
    "wof:name":"Ghibli Sa",
    "wof:placetype":"venue"
},
  "geometry": {"coordinates":[8.9538116455,46.0102424622],"type":"Point"}
}