{
  "type": "Feature",
  "properties": {
    "iso:country":"CH",
    "sg:address":"Zeughausgasse 12 3011 Bern. Postfach",
    "sg:city":"Bern",
    "sg:orig_category":"Unternehmensberatung",
    "sg:postcode":"3011",
    "sg:province":"Bern",
    "wof:name":"A + O Assessment + Outplacement Gmbh",
    "wof:placetype":"venue"
},
  "geometry": {"coordinates":[7.4455251694,46.949016571],"type":"Point"}
}