{
  "type": "Feature",
  "properties": {
    "iso:country":"CH",
    "sg:address":"Untere Allmendstrasse 13",
    "sg:city":"Steinhausen",
    "sg:orig_category":"Gymnastikschulen",
    "sg:phone":"+41 41 741 51 00",
    "sg:postcode":"6312",
    "sg:province":"Zug",
    "wof:name":"Gymnastik Studio Sana Frau Vreni Zaum",
    "wof:placetype":"venue"
},
  "geometry": {"coordinates":[8.4956245422,47.1924285889],"type":"Point"}
}