{
  "type": "Feature",
  "properties": {
    "iso:country":"CH",
    "sg:address":"Zentralschulhaus",
    "sg:city":"Dietikon",
    "sg:classifiers":[
        {
            "category":"Education",
            "subcategory":"Vocational School",
            "type":"Public Place"
        }
    ],
    "sg:postcode":"8953",
    "sg:province":"Z\u00fcrich",
    "sg:tags":[
        "koch-",
        "haushaltschulen"
    ],
    "wof:name":"Haushaltungsschule",
    "wof:placetype":"venue"
},
  "geometry": {"coordinates":[8.4036998749,47.4038887024],"type":"Point"}
}