{
  "type": "Feature",
  "properties": {
    "iso:country":"CH",
    "sg:address":"Koblenzerstrasse 42",
    "sg:city":"Klingnau",
    "sg:orig_category":"Autogaragen",
    "sg:phone":"+41 56 245 40 08",
    "sg:postcode":"5313",
    "sg:province":"Aargau",
    "wof:name":"Franz Eggsp\u00fchler Garage",
    "wof:placetype":"venue"
},
  "geometry": {"coordinates":[8.244576,47.585201],"type":"Point"}
}