{
  "type": "Feature",
  "properties": {
    "iso:country":"CH",
    "sg:address":"Seeacherweg 1 6047 Kastanienbaum. Postfach",
    "sg:city":"Kastanienbaum",
    "sg:orig_category":"Hochschulen U h\u00f6here Ausbildung",
    "sg:phone":"+41 41 349 65 00",
    "sg:postcode":"6047",
    "sg:province":"Luzern",
    "wof:name":"Itis International Tourism Management Institute Switzerland",
    "wof:placetype":"venue"
},
  "geometry": {"coordinates":[8.3377799988,47.0062484741],"type":"Point"}
}