{
  "type": "Feature",
  "properties": {
    "iso:country":"CH",
    "sg:address":"Untere Hauptgasse 12 3600 Thun. Postfach 1074",
    "sg:city":"Thun",
    "sg:orig_category":"Grosshandel mit elektrischen Haushaltsger\u00e4ten, Radio U Fernsehger\u00e4ten Herstellung von nachrichtentec",
    "sg:phone":"+41 33 222 88 78",
    "sg:postcode":"3601",
    "sg:province":"Bern",
    "wof:name":"Detraphone, Karl Trachsel",
    "wof:placetype":"venue"
},
  "geometry": {"coordinates":[7.6287808418,46.7602500916],"type":"Point"}
}