{
  "type": "Feature",
  "properties": {
    "iso:country":"CH",
    "sg:address":"Bizenenstrasse 11",
    "sg:city":"Muttenz",
    "sg:orig_category":"Herstellung von Werkzeugen Sonstiger spezialisierter Hoch U Tiefbau",
    "sg:phone":"+41 61 281 26 66",
    "sg:postcode":"4132",
    "sg:province":"Basel-Landschaft",
    "wof:name":"Diamantbohr Ag",
    "wof:placetype":"venue"
},
  "geometry": {"coordinates":[7.6511540413,47.5289573669],"type":"Point"}
}