{
  "type": "Feature",
  "properties": {
    "iso:country":"CH",
    "sg:address":"Industriestrasse 5",
    "sg:city":"Effretikon",
    "sg:orig_category":"Fachdetailhandel in Verkaufsr\u00e4umen Grosshandel mit Spielwaren",
    "sg:phone":"+41 52 343 88 80",
    "sg:postcode":"8307",
    "sg:province":"Z\u00fcrich",
    "wof:name":"Diha Gmbh",
    "wof:placetype":"venue"
},
  "geometry": {"coordinates":[8.6830873489,47.4192466736],"type":"Point"}
}