{
  "type": "Feature",
  "properties": {
    "iso:country":"CH",
    "sg:address":"Quai Des Forces-motrices 4",
    "sg:city":"Gen\u00e8ve",
    "sg:orig_category":"Non-Classified Establishments",
    "sg:postcode":"1204",
    "sg:province":"Gen\u00e8ve",
    "wof:name":"Caf\u00e9 Zanzibar",
    "wof:placetype":"venue"
},
  "geometry": {"coordinates":[6.1376738548,46.2040786743],"type":"Point"}
}