{
  "type": "Feature",
  "properties": {
    "iso:country":"CH",
    "sg:address":"Lindenplatz 3",
    "sg:city":"Winterthur",
    "sg:classifiers":[
        {
            "category":"Insurance",
            "subcategory":"Insurance Agent",
            "type":"Services"
        }
    ],
    "sg:phone":"+41 52 222 78 21",
    "sg:postcode":"8408",
    "sg:province":"Z\u00fcrich",
    "sg:tags":[
        "versicherungsagenturen",
        "-broker"
    ],
    "wof:name":"Z\u00fcrich-versicherungen Agentur W\u00fclflingen",
    "wof:placetype":"venue"
},
  "geometry": {"coordinates":[8.6938037872,47.5110054016],"type":"Point"}
}