{
  "type": "Feature",
  "properties": {
    "iso:country":"CH",
    "sg:address":"Sonnenh\u00fcgelstrasse 27 8589 Sitterdorf. Postfach",
    "sg:city":"Sitterdorf",
    "sg:orig_category":"Kalb U Schweine-M\u00e4sterei U Zucht",
    "sg:phone":"+41 79 603 77 30",
    "sg:postcode":"8589",
    "sg:province":"Thurgau",
    "wof:name":"Ernst Baumann",
    "wof:placetype":"venue"
},
  "geometry": {"coordinates":[9.2491779327,47.5073928833],"type":"Point"}
}