{
  "type": "Feature",
  "properties": {
    "iso:country":"CH",
    "sg:address":"G\u00fcterstrasse 6 8245 Feuerthalen. Postfach 74",
    "sg:city":"Feuerthalen",
    "sg:orig_category":"Architektur U Ingenieurb\u00fcros Handelsvermittlung U Grosshandel",
    "sg:phone":"+41 52 647 40 40",
    "sg:postcode":"8245",
    "sg:province":"Z\u00fcrich",
    "wof:name":"M\u00e4dler Norm Antrieb Ag",
    "wof:placetype":"venue"
},
  "geometry": {"coordinates":[8.645688,47.691162],"type":"Point"}
}