{
  "type": "Feature",
  "properties": {
    "iso:country":"CH",
    "sg:address":"Neuhofstrasse 36",
    "sg:city":"Aefligen",
    "sg:orig_category":"Bauschreinerei Innenausbau",
    "sg:phone":"+41 79 358 45 10",
    "sg:postcode":"3426",
    "sg:province":"Bern",
    "wof:name":"Cuizina",
    "wof:placetype":"venue"
},
  "geometry": {"coordinates":[7.55345,47.097748],"type":"Point"}
}