{
  "type": "Feature",
  "properties": {
    "iso:country":"CH",
    "sg:address":"Bissen",
    "sg:city":"Gstaad",
    "sg:orig_category":"Betrieb von Taxis",
    "sg:phone":"+41 79 656 12 33",
    "sg:postcode":"3780",
    "sg:province":"Bern",
    "wof:name":"Jakob Ummel Carreisen & Taxi",
    "wof:placetype":"venue"
},
  "geometry": {"coordinates":[7.29784,46.469769],"type":"Point"}
}