{
  "type": "Feature",
  "properties": {
    "iso:country":"CH",
    "sg:address":"Holzh\u00e4usernstrasse 4 6313 Menzingen. Postfach 330",
    "sg:city":"Menzingen",
    "sg:orig_category":"Detailhandel mit Brot, Back U S\u00fcsswaren",
    "sg:phone":"+41 41 756 01 51",
    "sg:postcode":"6313",
    "sg:province":"Zug",
    "wof:name":"Josef Schwegler B\u00e4ckerei-konditorei",
    "wof:placetype":"venue"
},
  "geometry": {"coordinates":[8.590685,47.178772],"type":"Point"}
}