{
  "type": "Feature",
  "properties": {
    "iso:country":"CH",
    "sg:address":"Lindliweg 25 8200 Schaffhausen. Postfach 77",
    "sg:city":"Schaffhausen",
    "sg:orig_category":"Rechtsberatung Unternehmensberatung",
    "sg:phone":"+41 52 624 67 10",
    "sg:postcode":"8202",
    "sg:province":"Schaffhausen",
    "wof:name":"Siruan Ag, Schaffhausen",
    "wof:placetype":"venue"
},
  "geometry": {"coordinates":[8.6519260406,47.6927375793],"type":"Point"}
}