{
  "type": "Feature",
  "properties": {
    "iso:country":"CH",
    "sg:address":"Kelchbachstrasse 16-18",
    "sg:city":"Naters",
    "sg:orig_category":"Fachdetailhandel in Verkaufsr\u00e4umen",
    "sg:phone":"+41 76 396 60 66",
    "sg:postcode":"3904",
    "sg:province":"Valais",
    "wof:name":"Nena's Spielwaren Und Geschenke, Muttenzer Peter",
    "wof:placetype":"venue"
},
  "geometry": {"coordinates":[7.9898910522,46.3251914978],"type":"Point"}
}