{
  "type": "Feature",
  "properties": {
    "iso:country":"CH",
    "sg:address":"Herbergsgasse 46 4051 Basel. Postfach",
    "sg:city":"Basel",
    "sg:orig_category":"Herstellung von sonstigen M\u00f6beln M\u00f6belveredelung U restaurierung",
    "sg:phone":"+41 61 261 60 06",
    "sg:postcode":"4003",
    "sg:province":"Basel-Stadt",
    "wof:name":"Niklaus Kn\u00f6ll Rahmenkunst Ag",
    "wof:placetype":"venue"
},
  "geometry": {"coordinates":[7.585100174,47.560508728],"type":"Point"}
}