{
  "type": "Feature",
  "properties": {
    "iso:country":"CH",
    "sg:address":"Seefeldstrasse 60",
    "sg:city":"Riedikon",
    "sg:orig_category":"Gewinnung von Kies U Sand",
    "sg:phone":"+41 19411097",
    "sg:postcode":"8616",
    "sg:province":"Z\u00fcrich",
    "wof:name":"Kieswerk Egli",
    "wof:placetype":"venue"
},
  "geometry": {"coordinates":[8.7103300095,47.3337287903],"type":"Point"}
}