{
  "type": "Feature",
  "properties": {
    "iso:country":"CH",
    "sg:address":"Route De Varandin 13 2905 Courtedoux Case Postale 18",
    "sg:city":"Courtedoux",
    "sg:orig_category":"Herstellung der Ausstattung von Uhren Herstellung von Uhren",
    "sg:phone":"+41 32 466 23 48",
    "sg:postcode":"2905",
    "sg:province":"Jura",
    "wof:name":"Montavon Denis Sa",
    "wof:placetype":"venue"
},
  "geometry": {"coordinates":[7.0406250954,47.4111328125],"type":"Point"}
}