{
  "type": "Feature",
  "properties": {
    "iso:country":"CH",
    "sg:address":"Uttwiler Strasse 3",
    "sg:city":"Dozwil",
    "sg:orig_category":"Herstellung von Kunststoffwaren",
    "sg:phone":"+41 55 282 39 48",
    "sg:postcode":"8580",
    "sg:province":"Thurgau",
    "wof:name":"Erich M\u00fchlemann Schaumstoffverarbeitung",
    "wof:placetype":"venue"
},
  "geometry": {"coordinates":[8.9446897507,47.2491989136],"type":"Point"}
}