{
  "type": "Feature",
  "properties": {
    "iso:country":"CH",
    "sg:address":"Quartierhof 3",
    "sg:city":"Bern",
    "sg:orig_category":"Allgemeiner Gartenbau Dienstleistungen im Gartenbau",
    "sg:phone":"+41 56 443 07 93",
    "sg:postcode":"3013",
    "sg:province":"Bern",
    "wof:name":"W\u00fcthrich Gartenbau",
    "wof:placetype":"venue"
},
  "geometry": {"coordinates":[8.141975,47.443214],"type":"Point"}
}