{
  "type": "Feature",
  "properties": {
    "iso:country":"CH",
    "sg:address":"Avenue De La Vog\u00e9az 12",
    "sg:city":"Morges",
    "sg:orig_category":"Malerei Stukkateurgewerbe, Gipserei U Verputzerei",
    "sg:phone":"+41 21 845 50 96",
    "sg:postcode":"1110",
    "sg:province":"Vaud",
    "wof:name":"Robert Jutzeler Gypserie & Peinture",
    "wof:placetype":"venue"
},
  "geometry": {"coordinates":[6.2143011093,46.589805603],"type":"Point"}
}