{
  "type": "Feature",
  "properties": {
    "iso:country":"CH",
    "sg:address":"Gladbachstrasse 51",
    "sg:city":"Z\u00fcrich",
    "sg:orig_category":"Forschung U Entwicklung im Bereich der Naturwissenschaften",
    "sg:phone":"+41 79 401 67 11",
    "sg:postcode":"8044",
    "sg:province":"Z\u00fcrich",
    "wof:name":"Physmatec Consulting Groh G. Dr. Technisch-wissenschaftliche Beratung Usw",
    "wof:placetype":"venue"
},
  "geometry": {"coordinates":[8.552781105,47.3817138672],"type":"Point"}
}