{
  "type": "Feature",
  "properties": {
    "iso:country":"CH",
    "sg:address":"Weiherhofstrasse 10",
    "sg:city":"Bronschhofen",
    "sg:orig_category":"Sportvereine Orientierungslauf",
    "sg:phone":"+41 79 460 89 38",
    "sg:postcode":"9552",
    "sg:province":"St. Gallen",
    "wof:name":"Ol-abteilung Stb",
    "wof:placetype":"venue"
},
  "geometry": {"coordinates":[7.5774769783,46.9273834229],"type":"Point"}
}