{
  "type": "Feature",
  "properties": {
    "iso:country":"CH",
    "sg:address":"St. Niklausstrasse 27 8103 Unterengstringen. Postfach",
    "sg:city":"Unterengstringen",
    "sg:orig_category":"Elektroinstallation",
    "sg:phone":"+41 17510801",
    "sg:postcode":"8103",
    "sg:province":"Z\u00fcrich",
    "wof:name":"K + H Elektro, Kuhn + Holenstein Elektroinstallationen",
    "wof:placetype":"venue"
},
  "geometry": {"coordinates":[8.43791008,47.4127998352],"type":"Point"}
}