{
  "type": "Feature",
  "properties": {
    "iso:country":"CH",
    "sg:address":"Nidfeldstrasse 5 6010 Kriens. Postfach",
    "sg:city":"Kriens",
    "sg:orig_category":"Softwareentwicklung U beratung",
    "sg:phone":"+41 41 637 02 30",
    "sg:postcode":"6010",
    "sg:province":"Luzern",
    "wof:name":"Aik Ag F\u00fcr Informatik Und Kommunikation",
    "wof:placetype":"venue"
},
  "geometry": {"coordinates":[8.2958450317,47.0304374695],"type":"Point"}
}