{
  "type": "Feature",
  "properties": {
    "iso:country":"CH",
    "sg:address":"Stauffacherstrasse 80",
    "sg:city":"Bern",
    "sg:orig_category":"Grosshandel mit lebenden Tieren",
    "sg:phone":"+41 61 331 71 11",
    "sg:postcode":"3014",
    "sg:province":"Bern",
    "wof:name":"Inter-carnex Ag",
    "wof:placetype":"venue"
},
  "geometry": {"coordinates":[7.5253500938,47.5052108765],"type":"Point"}
}