{
  "type": "Feature",
  "properties": {
    "iso:country":"CH",
    "sg:address":"Bergstrasse 10",
    "sg:city":"Zollikon",
    "sg:orig_category":"Polizei",
    "sg:phone":"+41 13914411",
    "sg:postcode":"8702",
    "sg:province":"Z\u00fcrich",
    "wof:name":"Gemeindepolizei",
    "wof:placetype":"venue"
},
  "geometry": {"coordinates":[8.5753307343,47.340549469],"type":"Point"}
}