{
  "type": "Feature",
  "properties": {
    "iso:country":"CH",
    "sg:address":"D\u00e4ttlikonerstrasse 5 8422 Pfungen. Postfach",
    "sg:city":"Pfungen",
    "sg:orig_category":"Herstellung von sonstigen elektrischen Ausr\u00fcstungen",
    "sg:phone":"+41 91 683 17 34",
    "sg:postcode":"8422",
    "sg:province":"Z\u00fcrich",
    "wof:name":"Precide Sa",
    "wof:placetype":"venue"
},
  "geometry": {"coordinates":[9.021197319,45.842212677],"type":"Point"}
}