{
  "type": "Feature",
  "properties": {
    "iso:country":"CH",
    "sg:address":"St\u00f6ckackerstrasse 108 3000 Bern. Postfach",
    "sg:city":"Bern",
    "sg:orig_category":"Non-Classified Establishments",
    "sg:postcode":"3003",
    "sg:province":"Bern",
    "wof:name":"Izeti Trans",
    "wof:placetype":"venue"
},
  "geometry": {"coordinates":[7.3981947899,46.9429588318],"type":"Point"}
}