{
  "type": "Feature",
  "properties": {
    "iso:country":"CH",
    "sg:address":"Lauetstr. 29",
    "sg:city":"Otelfingen",
    "sg:orig_category":"Herstellung von Teilen U Zubeh\u00f6r f\u00fcr Automobile Instandhaltung U Reparatur von Automobilen",
    "sg:phone":"+41 18443655",
    "sg:postcode":"8112",
    "sg:province":"Z\u00fcrich",
    "wof:name":"Karosserie, Erich Helm",
    "wof:placetype":"venue"
},
  "geometry": {"coordinates":[8.4071493149,47.4570121765],"type":"Point"}
}