{
  "type": "Feature",
  "properties": {
    "iso:country":"CH",
    "sg:address":"Fabrikstrasse 4",
    "sg:city":"Riedern",
    "sg:classifiers":[
        {
            "category":"Government",
            "subcategory":"Fire Station",
            "type":"Public Place"
        }
    ],
    "sg:phone":"+41 55 640 62 39",
    "sg:postcode":"8750",
    "sg:province":"Glarus",
    "sg:tags":[
        "monitoring",
        "system",
        "power"
    ],
    "wof:name":"Remtec Ag",
    "wof:placetype":"venue"
},
  "geometry": {"coordinates":[9.052397728,47.050617218],"type":"Point"}
}