{
  "type": "Feature",
  "properties": {
    "iso:country":"CH",
    "sg:address":"M\u00fchledorfstrasse 1/14 3018 Bern. Postfach",
    "sg:city":"Bern",
    "sg:orig_category":"Interessenvertretungen",
    "sg:postcode":"3018",
    "sg:province":"Bern",
    "wof:name":"Familiengartengenossenschaft Eymatt",
    "wof:placetype":"venue"
},
  "geometry": {"coordinates":[7.3916869164,46.94556427],"type":"Point"}
}