{
  "type": "Feature",
  "properties": {
    "iso:country":"CH",
    "sg:address":"Dorfstrasse 8",
    "sg:city":"W\u00e4ngi",
    "sg:orig_category":"Drogerien Parf\u00fcmerien U sonstiger Detailhandel mit kosmetischen Artikeln U K\u00f6rperpflegemitteln",
    "sg:phone":"+41 52 378 21 49",
    "sg:postcode":"9545",
    "sg:province":"Thurgau",
    "wof:name":"Aellig Christian",
    "wof:placetype":"venue"
},
  "geometry": {"coordinates":[8.9536447525,47.4971885681],"type":"Point"}
}