{
  "type": "Feature",
  "properties": {
    "iso:country":"CH",
    "sg:address":"Via Guioni 7",
    "sg:city":"Pregassona",
    "sg:orig_category":"Bauingenieurb\u00fcros allgemein",
    "sg:phone":"+41 91 972 67 75",
    "sg:postcode":"6963",
    "sg:province":"Ticino",
    "wof:name":"Arnoldo Frigerio Studio D'ingegneria",
    "wof:placetype":"venue"
},
  "geometry": {"coordinates":[8.969681,46.017357],"type":"Point"}
}