{
  "type": "Feature",
  "properties": {
    "iso:country":"CH",
    "sg:address":"Egelmoosstrasse 6",
    "sg:city":"K\u00f6lliken",
    "sg:orig_category":"Grosshandel mit Getreide, Saatgut U Futtermitteln",
    "sg:postcode":"5742",
    "sg:province":"Aargau",
    "wof:name":"Favetto G.",
    "wof:placetype":"venue"
},
  "geometry": {"coordinates":[8.6988162994,47.6564865112],"type":"Point"}
}