{
  "type": "Feature",
  "properties": {
    "iso:country":"CH",
    "sg:address":"Haltestelle",
    "sg:city":"Gondiswil",
    "sg:orig_category":"Instandhaltung U Reparatur von Automobilen",
    "sg:phone":"+41 62 962 04 28",
    "sg:postcode":"4955",
    "sg:province":"Bern",
    "wof:name":"Garage Burkhardt H.u.",
    "wof:placetype":"venue"
},
  "geometry": {"coordinates":[7.8839387894,47.1283226013],"type":"Point"}
}