{
  "type": "Feature",
  "properties": {
    "iso:country":"CH",
    "sg:address":"Br\u00f6ckligraben 8",
    "sg:city":"Thayngen",
    "sg:orig_category":"Vermietung U Verpachtung von eigenen Immobilien",
    "sg:postcode":"8240",
    "sg:province":"Schaffhausen",
    "wof:name":"Hauser & Co Immobilien",
    "wof:placetype":"venue"
},
  "geometry": {"coordinates":[8.7085962296,47.7518959045],"type":"Point"}
}