{
  "type": "Feature",
  "properties": {
    "iso:country":"CH",
    "sg:address":"Heiniswingerten 1",
    "sg:city":"Stettfurt",
    "sg:orig_category":"Sonstige mit der Informatik verbundene T\u00e4tigkeiten",
    "sg:phone":"+41 52 376 36 40",
    "sg:postcode":"9507",
    "sg:province":"Thurgau",
    "wof:name":"Urs Scheiwiller",
    "wof:placetype":"venue"
},
  "geometry": {"coordinates":[8.9572582245,47.5262413025],"type":"Point"}
}