{
  "type": "Feature",
  "properties": {
    "iso:country":"CH",
    "sg:address":"6362 Stansstad. Postfach 261",
    "sg:city":"Stansstad",
    "sg:orig_category":"Bezirks, Sekundar, Realschulen, Oberstufe der Primarschulen",
    "sg:phone":"+41 41 610 49 73",
    "sg:postcode":"6362",
    "sg:province":"Nidwalden",
    "wof:name":"Oberstufenschule",
    "wof:placetype":"venue"
},
  "geometry": {"coordinates":[8.32914,46.972328],"type":"Point"}
}