{
  "type": "Feature",
  "properties": {
    "iso:country":"CH",
    "sg:address":"Chemin Des Moulins-de-drize 11",
    "sg:city":"Troinex",
    "sg:orig_category":"Grosshandel mit sonstigen Maschinen U Ausr\u00fcstungen f\u00fcr Industrie, Handel U Schiffahrt Herstellung vo",
    "sg:phone":"+41 22 342 08 98",
    "sg:postcode":"1256",
    "sg:province":"Gen\u00e8ve",
    "wof:name":"Helvetol",
    "wof:placetype":"venue"
},
  "geometry": {"coordinates":[6.1429281235,46.1674308777],"type":"Point"}
}