{
  "type": "Feature",
  "properties": {
    "iso:country":"CH",
    "sg:address":"1874 Champ\u00e9ry. Postfach",
    "sg:city":"Champ\u00e9ry",
    "sg:orig_category":"Reiseb\u00fcros U Reiseveranstalter",
    "sg:postcode":"1874",
    "sg:province":"Valais",
    "wof:name":"Charm In Europe, Geninazzi Jeannot",
    "wof:placetype":"venue"
},
  "geometry": {"coordinates":[5.1808700562,45.8973388672],"type":"Point"}
}