{
  "type": "Feature",
  "properties": {
    "iso:country":"CH",
    "sg:address":"St. Jakobstrasse 7",
    "sg:city":"Cham",
    "sg:orig_category":"Unternehmensberatung",
    "sg:phone":"+41 41 780 83 67",
    "sg:postcode":"6330",
    "sg:province":"Zug",
    "wof:name":"Ausbildung & Beratung Elisabeth K\u00fcng-bachmann",
    "wof:placetype":"venue"
},
  "geometry": {"coordinates":[8.4506616592,47.1774864197],"type":"Point"}
}