{
  "type": "Feature",
  "properties": {
    "iso:country":"CH",
    "sg:address":"Via Besso 7",
    "sg:city":"Lugano",
    "sg:orig_category":"Detailhandel mit Geschenkartikeln U Souvenirs",
    "sg:phone":"+41 91 966 76 20",
    "sg:postcode":"6900",
    "sg:province":"Ticino",
    "wof:name":"Boutique Botteguccia Gigliola Pedrazzetti",
    "wof:placetype":"venue"
},
  "geometry": {"coordinates":[8.9437675476,46.0058555603],"type":"Point"}
}