{
  "type": "Feature",
  "properties": {
    "iso:country":"CH",
    "sg:address":"Saumackerstrasse 6",
    "sg:city":"Z\u00fcrich",
    "sg:orig_category":"Detektivb\u00fcros U \u00dcberwachung",
    "sg:phone":"+41 32 623 22 23",
    "sg:postcode":"8048",
    "sg:province":"Z\u00fcrich",
    "wof:name":"Vip-security",
    "wof:placetype":"venue"
},
  "geometry": {"coordinates":[7.5087099075,47.2333145142],"type":"Point"}
}