{
  "type": "Feature",
  "properties": {
    "iso:country":"CH",
    "sg:address":"Loch",
    "sg:city":"Wila",
    "sg:orig_category":"Strassenbau",
    "sg:phone":"+41 41 930 14 02",
    "sg:postcode":"8492",
    "sg:province":"Z\u00fcrich",
    "wof:name":"Josef Walpert Forst-& Strassenbau",
    "wof:placetype":"venue"
},
  "geometry": {"coordinates":[8.1462678909,47.226978302],"type":"Point"}
}