{
  "type": "Feature",
  "properties": {
    "addr:full":"Rindermarkt 5 Z\u00fcrich Z\u00fcrich 8001",
    "addr:housenumber":"5",
    "addr:postcode":"8001",
    "addr:street":"Rindermarkt",
    "iso:country":"CH",
    "sg:address":"Rindermarkt 5",
    "sg:city":"Z\u00fcrich",
    "sg:orig_category":"Allgemeiner Hoch U Tiefbau",
    "sg:phone":"+41 71 757 89 29",
    "sg:postcode":"8001",
    "sg:province":"Z\u00fcrich",
    "wof:name":"Architekturb\u00fcro Haedener + Huser",
    "wof:placetype":"venue"
},
  "geometry": {"coordinates":[9.544582,47.380077],"type":"Point"}
}