{
  "type": "Feature",
  "properties": {
    "iso:country":"CH",
    "sg:address":"Champs-des-piecettes 17",
    "sg:city":"Marin-centre",
    "sg:orig_category":"Sportvereine Ballsport Tennis",
    "sg:postcode":"2074",
    "sg:province":"Neuch\u00e2tel",
    "wof:name":"Tennisclub Marin Sports",
    "wof:placetype":"venue"
},
  "geometry": {"coordinates":[7.0181379318,47.0085754395],"type":"Point"}
}