{
  "type": "Feature",
  "properties": {
    "iso:country":"CH",
    "sg:address":"6571",
    "sg:city":"Indemini",
    "sg:classifiers":[
        {
            "category":"Restaurant",
            "type":"Food & Drink"
        }
    ],
    "sg:phone":"+41 91 795 14 67",
    "sg:postcode":"6571",
    "sg:province":"Ticino",
    "wof:name":"Ristorante Martini",
    "wof:placetype":"venue"
},
  "geometry": {"coordinates":[8.8270244598,46.0958175659],"type":"Point"}
}