{
  "type": "Feature",
  "properties": {
    "iso:country":"CH",
    "sg:address":"Bonnstrasse 16 3186 D\u00fcdingen. Postfach",
    "sg:city":"D\u00fcdingen",
    "sg:orig_category":"Grosshandel mit sonstigen Maschinen U Ausr\u00fcstungen f\u00fcr Industrie, Handel U Schiffahrt",
    "sg:phone":"+41 26 493 32 24",
    "sg:postcode":"3186",
    "sg:province":"Fribourg",
    "wof:name":"Anag Technologies Ag Internationaler Handel Mit Maschinen, Anlagen, Namentlich F\u00fcr Die Chemie, Pharmabranche Usw",
    "wof:placetype":"venue"
},
  "geometry": {"coordinates":[7.1854710579,46.8569717407],"type":"Point"}
}