{
  "type": "Feature",
  "properties": {
    "iso:country":"CH",
    "sg:address":"Seestrasse",
    "sg:city":"Merligen",
    "sg:orig_category":"Autogaragen",
    "sg:phone":"+41 33 251 22 22",
    "sg:postcode":"3658",
    "sg:province":"Bern",
    "wof:name":"Garage Wittwer D.& E.pattinson",
    "wof:placetype":"venue"
},
  "geometry": {"coordinates":[7.74058,46.69487],"type":"Point"}
}