{
  "type": "Feature",
  "properties": {
    "iso:country":"CH",
    "sg:address":"Bubenbergplatz 3 3011 Bern. Postfach",
    "sg:city":"Bern",
    "sg:orig_category":"Interessenvertretungen",
    "sg:postcode":"3005",
    "sg:province":"Bern",
    "wof:name":"Ellermann Wilhelm Und Mogens-stiftung Geldmittelbereitstellung F. J\u00e4hrliche Abhaltung Einer Wilhelm Bzw. Mogens Ellermann Gastvorlesung Usw",
    "wof:placetype":"venue"
},
  "geometry": {"coordinates":[7.4403529167,46.9472427368],"type":"Point"}
}