{
  "type": "Feature",
  "properties": {
    "addr:full":"Rue Du Rh\u00f4ne 27 Mayens-de-saxon Valais 1907",
    "addr:housenumber":"27;1907",
    "addr:street":"Rue Du Rho\u0302Ne",
    "iso:country":"CH",
    "sg:address":"Rue Du Rh\u00f4ne 27",
    "sg:city":"Mayens-de-saxon",
    "sg:orig_category":"Abdichtung Sanit\u00e4r, Heizungs U L\u00fcftungsinstallation",
    "sg:phone":"+41 27 744 35 60",
    "sg:postcode":"1907",
    "sg:province":"Valais",
    "wof:name":"Forre Saxon Sa",
    "wof:placetype":"venue"
},
  "geometry": {"coordinates":[4.70279,45.88036],"type":"Point"}
}