{
  "type": "Feature",
  "properties": {
    "iso:country":"CH",
    "sg:address":"Avenue Blanc 47",
    "sg:city":"Gen\u00e8ve",
    "sg:orig_category":"Konsulate",
    "sg:phone":"+41 22 731 75 40",
    "sg:postcode":"1202",
    "sg:province":"Gen\u00e8ve",
    "wof:name":"Consulat G\u00e9n\u00e9ral De L'union Myanmar",
    "wof:placetype":"venue"
},
  "geometry": {"coordinates":[6.1477560997,46.2208404541],"type":"Point"}
}