{
  "type": "Feature",
  "properties": {
    "iso:country":"CH",
    "sg:address":"Spitzenwiesstrasse 35",
    "sg:city":"Jona",
    "sg:orig_category":"Zimmerei, Dachdeckerei, Bauspenglerei U Abdichtung",
    "sg:postcode":"8645",
    "sg:province":"St. Gallen",
    "wof:name":"B\u00fcsser Hausbau Ag",
    "wof:placetype":"venue"
},
  "geometry": {"coordinates":[8.8195753098,47.2467727661],"type":"Point"}
}