{
  "type": "Feature",
  "properties": {
    "iso:country":"CH",
    "sg:address":"Chemin Des Vignes 6",
    "sg:city":"Clarens",
    "sg:orig_category":"Organisationen der Wohlfahrtspflege",
    "sg:phone":"+41 21 964 25 54",
    "sg:postcode":"1815",
    "sg:province":"Vaud",
    "wof:name":"Pro Juventute",
    "wof:placetype":"venue"
},
  "geometry": {"coordinates":[6.8908047676,46.4409446716],"type":"Point"}
}