{
  "type": "Feature",
  "properties": {
    "iso:country":"CH",
    "sg:address":"Bernstrasse 1 3543 Emmenmatt. Postfach",
    "sg:city":"Emmenmatt",
    "sg:orig_category":"R\u00fcckgewinnung U Vorbereitung f\u00fcr die Wiederverwertung Recycling von nichtmetallischen Altmaterialien",
    "sg:postcode":"3543",
    "sg:province":"Bern",
    "wof:name":"Agro-green F\u00f6rderung \u00f6kologischer Anliegen Auf Dem Gebiet Der Abfallverwertung, Bes. F\u00fcr Landwirte",
    "wof:placetype":"venue"
},
  "geometry": {"coordinates":[8.7831096649,47.1618118286],"type":"Point"}
}