{
  "type": "Feature",
  "properties": {
    "iso:country":"CH",
    "sg:address":"Th\u00fcrn 62 9554 T\u00e4gerschen. Postfach",
    "sg:city":"T\u00e4gerschen",
    "sg:orig_category":"Detailhandel mit elektrischen Haushalts-,Radio U Fernsehger\u00e4ten sowie Musikinstrumenten",
    "sg:phone":"+41 71 966 37 01",
    "sg:postcode":"9554",
    "sg:province":"Thurgau",
    "wof:name":"Holenstein Technik",
    "wof:placetype":"venue"
},
  "geometry": {"coordinates":[9.0301923752,47.5089416504],"type":"Point"}
}