{
  "type": "Feature",
  "properties": {
    "iso:country":"CH",
    "sg:address":"Via Oviga",
    "sg:city":"Brissago",
    "sg:orig_category":"Hoch U Tiefbau",
    "sg:phone":"+41 91 793 18 53",
    "sg:postcode":"6614",
    "sg:province":"Ticino",
    "wof:name":"Flavio Baccal\u00e0 Impresa Costruzioni",
    "wof:placetype":"venue"
},
  "geometry": {"coordinates":[8.7052488327,46.1141853333],"type":"Point"}
}