{
  "type": "Feature",
  "properties": {
    "iso:country":"CH",
    "sg:address":"Chemin Adrien-stoessel 28",
    "sg:city":"Meyrin",
    "sg:classifiers":[
        {
            "category":"Banks & Credit Unions",
            "subcategory":"Investment Brokerage",
            "type":"Services"
        }
    ],
    "sg:phone":"+41 32 925 97 70",
    "sg:postcode":"1217",
    "sg:province":"Gen\u00e8ve",
    "sg:tags":[
        "development",
        "electronics"
    ],
    "wof:name":"Mr Electronic S.a.",
    "wof:placetype":"venue"
},
  "geometry": {"coordinates":[6.811608,47.085701],"type":"Point"}
}