{
  "type": "Feature",
  "properties": {
    "iso:country":"CH",
    "sg:address":"Kirchlindachstrasse 2",
    "sg:city":"Ortschwaben",
    "sg:orig_category":"Detailhandel mit Waren verschiedener Art, Hauptrichtung Nahrungsmittel",
    "sg:phone":"+41 31 829 11 68",
    "sg:postcode":"3042",
    "sg:province":"Bern",
    "wof:name":"Hans-ruedi Sch\u00f6ni Handlung",
    "wof:placetype":"venue"
},
  "geometry": {"coordinates":[7.3985300064,46.9950294495],"type":"Point"}
}