{
  "type": "Feature",
  "properties": {
    "iso:country":"CH",
    "sg:address":"1782",
    "sg:city":"Formangueires",
    "sg:orig_category":"Bauschreinerei Innenausbau",
    "sg:phone":"+41 22 343 95 90",
    "sg:postcode":"1782",
    "sg:province":"Fribourg",
    "wof:name":"Roger Kellenberger Menuiserie & Agencement",
    "wof:placetype":"venue"
},
  "geometry": {"coordinates":[6.137116,46.18795],"type":"Point"}
}