{
  "type": "Feature",
  "properties": {
    "iso:country":"CH",
    "sg:address":"Berninastrasse 43 8057 Z\u00fcrich. Postfach 4117",
    "sg:city":"Z\u00fcrich",
    "sg:orig_category":"Non-Classified Establishments",
    "sg:phone":"+41 12412090",
    "sg:postcode":"8021",
    "sg:province":"Z\u00fcrich",
    "wof:name":"Srilankan Airlines Ltd, Colombo, Zurich Branch Lufttransporte Usw.",
    "wof:placetype":"venue"
},
  "geometry": {"coordinates":[8.5471897125,47.4035072327],"type":"Point"}
}