{
  "type": "Feature",
  "properties": {
    "iso:country":"CH",
    "sg:address":"Rue De La Villette 9 1400 Yverdon-les-bains. Postfach",
    "sg:city":"Yverdon-les-bains",
    "sg:orig_category":"Maler U Glasergewerbe",
    "sg:postcode":"1400",
    "sg:province":"Vaud",
    "wof:name":"Soller Roland",
    "wof:placetype":"venue"
},
  "geometry": {"coordinates":[6.6584248543,46.777256012],"type":"Point"}
}