{
  "type": "Feature",
  "properties": {
    "iso:country":"CH",
    "sg:address":"R\u00fctelti 583",
    "sg:city":"Triesenberg",
    "sg:orig_category":"P\u00e9dicure",
    "sg:phone":"+423 262 55 90",
    "sg:postcode":"9497",
    "wof:name":"Marlene Benz P\u00e9dicure",
    "wof:placetype":"venue"
},
  "geometry": {"coordinates":[9.5446863174,47.1146888733],"type":"Point"}
}