{
  "type": "Feature",
  "properties": {
    "iso:country":"CH",
    "sg:address":"Nordstrasse 15 8006 Z\u00fcrich. Postfach",
    "sg:city":"Z\u00fcrich",
    "sg:orig_category":"Interessenvertretungen",
    "sg:postcode":"8001",
    "sg:province":"Z\u00fcrich",
    "wof:name":"Schweizerische Gesellschaft F\u00fcr Chemische Industrie",
    "wof:placetype":"venue"
},
  "geometry": {"coordinates":[8.5391359329,47.3842544556],"type":"Point"}
}