{
  "type": "Feature",
  "properties": {
    "iso:country":"CH",
    "sg:address":"Spielhof",
    "sg:city":"Pfaffnau",
    "sg:orig_category":"Interessenvertretungen",
    "sg:postcode":"6264",
    "sg:province":"Luzern",
    "wof:name":"World Peace Organization",
    "wof:placetype":"venue"
},
  "geometry": {"coordinates":[7.8951401711,47.2250442505],"type":"Point"}
}