{
  "type": "Feature",
  "properties": {
    "iso:country":"CH",
    "sg:address":"Stadthausstrasse 91",
    "sg:city":"Winterthur",
    "sg:orig_category":"Detailhandel mit Textilien Herstellung von konfektionierten Textilwaren ohne Bekleidung",
    "sg:phone":"+41 52 212 40 30",
    "sg:postcode":"8400",
    "sg:province":"Z\u00fcrich",
    "wof:name":"Betten-supermarkt Strahm Ag",
    "wof:placetype":"venue"
},
  "geometry": {"coordinates":[8.7284936905,47.5000267029],"type":"Point"}
}