{
  "type": "Feature",
  "properties": {
    "iso:country":"CH",
    "sg:address":"Ospedale Via All' 6",
    "sg:city":"Locarno",
    "sg:orig_category":"Religi\u00f6se Vereinigungen",
    "sg:phone":"+41 91 751 12 22",
    "sg:postcode":"6600",
    "sg:province":"Ticino",
    "wof:name":"Associazione Missionaria Aim4christ International Ministries",
    "wof:placetype":"venue"
},
  "geometry": {"coordinates":[14.6601495743,41.5616722107],"type":"Point"}
}