{
  "type": "Feature",
  "properties": {
    "iso:country":"CH",
    "sg:address":"Seefeldstrasse 181",
    "sg:city":"Z\u00fcrich",
    "sg:orig_category":"Detailhandel mit Fleisch U Fleischwaren",
    "sg:phone":"+41 14223356",
    "sg:postcode":"8008",
    "sg:province":"Z\u00fcrich",
    "wof:name":"Pferdemetzgerei Seefeld, Fischbacher W.",
    "wof:placetype":"venue"
},
  "geometry": {"coordinates":[8.557559967,47.3546943665],"type":"Point"}
}