{
  "type": "Feature",
  "properties": {
    "iso:country":"CH",
    "sg:address":"Fluhweg 5",
    "sg:city":"Pieterlen",
    "sg:orig_category":"Werbeagenturen Werbegrafikateliers",
    "sg:phone":"+41 32 377 30 47",
    "sg:postcode":"2542",
    "sg:province":"Bern",
    "wof:name":"Lerch Design Studio",
    "wof:placetype":"venue"
},
  "geometry": {"coordinates":[7.3284368515,47.1750411987],"type":"Point"}
}