{
  "type": "Feature",
  "properties": {
    "iso:country":"CH",
    "sg:address":"Lindenegg 6",
    "sg:city":"Biel/bienne",
    "sg:orig_category":"Architekturb\u00fcros",
    "sg:phone":"+41 32 323 75 05",
    "sg:postcode":"2502",
    "sg:province":"Bern",
    "wof:name":"J\u00fcrg Rihs Architekturb\u00fcro",
    "wof:placetype":"venue"
},
  "geometry": {"coordinates":[7.2440390587,47.1412773132],"type":"Point"}
}