{
  "type": "Feature",
  "properties": {
    "iso:country":"CH",
    "sg:address":"Langgr\u00fctstrasse 172",
    "sg:city":"Z\u00fcrich",
    "sg:classifiers":[
        {
            "category":"Professional",
            "subcategory":"Employment Agencies",
            "type":"Services"
        }
    ],
    "sg:phone":"+41 19800300",
    "sg:postcode":"8047",
    "sg:province":"Z\u00fcrich",
    "sg:tags":[
        "personal",
        "u",
        "stellenvermittlung"
    ],
    "wof:name":"Baxtra Ag Personalmanagement",
    "wof:placetype":"venue"
},
  "geometry": {"coordinates":[8.4904079437,47.3745498657],"type":"Point"}
}