{
  "type": "Feature",
  "properties": {
    "iso:country":"CH",
    "sg:address":"Arkadenweg 5d",
    "sg:city":"D\u00fcbendorf",
    "sg:orig_category":"Unternehmensberatung",
    "sg:phone":"+41 71 622 80 70",
    "sg:postcode":"8600",
    "sg:province":"Z\u00fcrich",
    "wof:name":"Steffen & Rausch Unternehmensberatung Ag",
    "wof:placetype":"venue"
},
  "geometry": {"coordinates":[9.1227397919,47.5615997314],"type":"Point"}
}