{
  "type": "Feature",
  "properties": {
    "iso:country":"CH",
    "sg:address":"8133",
    "sg:city":"Esslingen",
    "sg:orig_category":"Vereine Gesang",
    "sg:postcode":"8133",
    "sg:province":"Z\u00fcrich",
    "wof:name":"M\u00e4nnerchor Esslingen",
    "wof:placetype":"venue"
},
  "geometry": {"coordinates":[8.7192001343,47.2897605896],"type":"Point"}
}