{
  "type": "Feature",
  "properties": {
    "iso:country":"CH",
    "sg:address":"Forstweg 22",
    "sg:city":"Selzach",
    "sg:orig_category":"Herstellung von Uhren Reparatur von Uhren U Schmuck",
    "sg:phone":"+41 19844414",
    "sg:postcode":"2545",
    "sg:province":"Solothurn",
    "wof:name":"Uhrenwerkstatt V\u00f6ckler Detlef",
    "wof:placetype":"venue"
},
  "geometry": {"coordinates":[8.6900548935,47.3005561829],"type":"Point"}
}