{
  "type": "Feature",
  "properties": {
    "iso:country":"CH",
    "sg:address":"Via San Gottardo 21 6943 Vezia. Postfach",
    "sg:city":"Vezia",
    "sg:orig_category":"Detailhandel mit Blumen U Pflanzen Fachdetailhandel in Verkaufsr\u00e4umen",
    "sg:phone":"+41 91 950 86 39",
    "sg:postcode":"6943",
    "sg:province":"Ticino",
    "wof:name":"Parole De Fleurs Sagl Piante, Fiori, Accessori Ecc.; Acquisto, Vendita, Commercializzaz.",
    "wof:placetype":"venue"
},
  "geometry": {"coordinates":[8.937171,46.024185],"type":"Point"}
}