{
  "type": "Feature",
  "properties": {
    "iso:country":"CH",
    "sg:address":"Im Heimg\u00e4rtli 22",
    "sg:city":"Z\u00fcrich",
    "sg:orig_category":"Reinigungsgewerbe",
    "sg:postcode":"8047",
    "sg:province":"Z\u00fcrich",
    "wof:name":"Bohni Albert, Reinigungen. Geb\u00e4ude- U. Steinreinigungen, Schleifen, Versiegeln U. Impr\u00e4gnieren V. Holz, Stein- U. Zementb\u00f6den.",
    "wof:placetype":"venue"
},
  "geometry": {"coordinates":[8.4894580841,47.3700904846],"type":"Point"}
}