{
  "type": "Feature",
  "properties": {
    "iso:country":"CH",
    "sg:address":"Florimont Avenue De 2bis 1006 Lausanne. Postfach",
    "sg:city":"Lausanne",
    "sg:orig_category":"Sonstiger Fachdetailhandel mit Nahrungsmitteln, Getr\u00e4nken U Tabak in Verkaufsr\u00e4umen",
    "sg:postcode":"1003",
    "sg:province":"Vaud",
    "wof:name":"Rivera Maria Del Carmen Epicerie",
    "wof:placetype":"venue"
},
  "geometry": {"coordinates":[6.6379141808,46.5161018372],"type":"Point"}
}