{
  "type": "Feature",
  "properties": {
    "iso:country":"CH",
    "sg:address":"B\u00e4ttelweg 186",
    "sg:city":"Boningen",
    "sg:orig_category":"Sportvereine Velo Rad-& Motorfahrer-Bund SRB",
    "sg:postcode":"4618",
    "sg:province":"Solothurn",
    "wof:name":"Arbeiter-touring-bund Atb",
    "wof:placetype":"venue"
},
  "geometry": {"coordinates":[7.8524751663,47.3064422607],"type":"Point"}
}