{
  "type": "Feature",
  "properties": {
    "iso:country":"CH",
    "sg:address":"Oberneuhofstrasse 11",
    "sg:city":"Baar",
    "sg:orig_category":"Herstellung von Gummiwaren Herstellung von sonstigen Gummiwaren",
    "sg:phone":"+41 18500131",
    "sg:postcode":"6340",
    "sg:province":"Zug",
    "wof:name":"Muraro Oberglatt, Fabrikation Von Und Handel Mit Techn. Gummiartikeln, Transportb\u00e4nder Und Vulkanisierservice",
    "wof:placetype":"venue"
},
  "geometry": {"coordinates":[8.5033273697,47.4808197021],"type":"Point"}
}