{
  "type": "Feature",
  "properties": {
    "iso:country":"CH",
    "sg:address":"Industriestrasse 21",
    "sg:city":"Hittnau",
    "sg:orig_category":"Detailhandel mit Metallwaren, Anstrichmitteln, Glaswaren, Bau U Heimwerkerbedarf",
    "sg:phone":"+41 19502402",
    "sg:postcode":"8335",
    "sg:province":"Z\u00fcrich",
    "wof:name":"Schellenberg Schweiz Gmbh Handel Mit Artikeln Der Do-it-yourself-branche",
    "wof:placetype":"venue"
},
  "geometry": {"coordinates":[8.8200101852,47.3669319153],"type":"Point"}
}