{
  "type": "Feature",
  "properties": {
    "iso:country":"CH",
    "sg:address":"Avenue Reverdil 2 1260 Nyon. Postfach",
    "sg:city":"Nyon",
    "sg:orig_category":"Grosshandel mit Datenverarbeitungsger\u00e4ten Sonstige mit der Informatik verbundene T\u00e4tigkeiten",
    "sg:phone":"+41 22 994 01 44",
    "sg:postcode":"1260",
    "sg:province":"Vaud",
    "wof:name":"Applic8 Sa Commercialisation D'\u00e9quipements Informatiques, Prestations De Service Dans Le Domaine Informatique",
    "wof:placetype":"venue"
},
  "geometry": {"coordinates":[6.234457016,46.382686615],"type":"Point"}
}