{
  "type": "Feature",
  "properties": {
    "iso:country":"CH",
    "sg:address":"Rue Du Bourg-aux-favre 1",
    "sg:city":"Troistorrents",
    "sg:orig_category":"Vermietung U Verpachtung von eigenen Immobilien",
    "sg:postcode":"1872",
    "sg:province":"Valais",
    "wof:name":"Domaines Bel Horizon Sa",
    "wof:placetype":"venue"
},
  "geometry": {"coordinates":[6.9183092117,46.2293548584],"type":"Point"}
}