{
  "type": "Feature",
  "properties": {
    "iso:country":"CH",
    "sg:address":"Mont-blanc Quai Du 29",
    "sg:city":"Gen\u00e8ve",
    "sg:orig_category":"Unclassifiable Establishments",
    "sg:phone":"+41 19321404",
    "sg:postcode":"1201",
    "sg:province":"Gen\u00e8ve",
    "wof:name":"Vid Security Gmbh",
    "wof:placetype":"venue"
},
  "geometry": {"coordinates":[8.7952899933,47.3097457886],"type":"Point"}
}