{
  "type": "Feature",
  "properties": {
    "iso:country":"CH",
    "sg:address":"Chemin Des Jardillets 43",
    "sg:city":"Hauterive",
    "sg:orig_category":"Fachdetailhandel in Verkaufsr\u00e4umen Grosshandel mit Uhren",
    "sg:phone":"+41 32 753 70 40",
    "sg:postcode":"2068",
    "sg:province":"Neuch\u00e2tel",
    "wof:name":"Aroma Watch Sa",
    "wof:placetype":"venue"
},
  "geometry": {"coordinates":[6.9658322334,47.0119361877],"type":"Point"}
}