{
  "type": "Feature",
  "properties": {
    "iso:country":"CH",
    "sg:address":"Via Pedemonte 34 6962 Viganello. Postfach",
    "sg:city":"Agno",
    "sg:orig_category":"Grosshandel mit Datenverarbeitungsger\u00e4ten Softwareentwicklung U beratung",
    "sg:phone":"+41 91 970 22 65",
    "sg:postcode":"6982",
    "sg:province":"Ticino",
    "wof:name":"Optiplan Systems Sa Software Per L'elaborazione Elettronica Dei Dati; Consulenza, Sviluppo Ecc",
    "wof:placetype":"venue"
},
  "geometry": {"coordinates":[8.9696331024,46.0137290955],"type":"Point"}
}