{
  "type": "Feature",
  "properties": {
    "iso:country":"CH",
    "sg:address":"Birnbaumstrasse 19",
    "sg:city":"Z\u00fcrich",
    "sg:orig_category":"Vermittlung von Immobilien Verwaltung von Immobilien",
    "sg:phone":"+41 13121818",
    "sg:postcode":"8050",
    "sg:province":"Z\u00fcrich",
    "wof:name":"Bosag Immobilien Ag",
    "wof:placetype":"venue"
},
  "geometry": {"coordinates":[8.5492753983,47.4118270874],"type":"Point"}
}