{
  "type": "Feature",
  "properties": {
    "iso:country":"CH",
    "sg:address":"7433",
    "sg:city":"Wergenstein",
    "sg:orig_category":"Gemeindeverwaltungen",
    "sg:phone":"+41 81 661 10 10",
    "sg:postcode":"7433",
    "sg:province":"Graubunden",
    "wof:name":"Gemeindeverwaltung Wergenstein",
    "wof:placetype":"venue"
},
  "geometry": {"coordinates":[9.4082403183,46.6270599365],"type":"Point"}
}