{
  "type": "Feature",
  "properties": {
    "iso:country":"CH",
    "sg:address":"Pf\u00e4ndwiesenstrasse 1",
    "sg:city":"Opfikon",
    "sg:orig_category":"Fahrschulen, Flugschulen",
    "sg:phone":"+41 18104208",
    "sg:postcode":"8152",
    "sg:province":"Z\u00fcrich",
    "wof:name":"Beat Bachmann Fahrschule Beba",
    "wof:placetype":"venue"
},
  "geometry": {"coordinates":[8.5729694366,47.4325218201],"type":"Point"}
}