{
  "type": "Feature",
  "properties": {
    "iso:country":"CH",
    "sg:address":"Haulenstrasse 134",
    "sg:city":"Herbetswil",
    "sg:orig_category":"Politische Parteien FDP",
    "sg:postcode":"4715",
    "sg:province":"Solothurn",
    "wof:name":"Fdp Ortspartei Herbetswil",
    "wof:placetype":"venue"
},
  "geometry": {"coordinates":[7.5905041695,47.298625946],"type":"Point"}
}