{
  "type": "Feature",
  "properties": {
    "iso:country":"CH",
    "sg:address":"Route De Vevey 26",
    "sg:city":"Ch\u00e2tel-st-denis",
    "sg:orig_category":"Arztpraxen",
    "sg:phone":"+41 21 948 83 75",
    "sg:postcode":"1618",
    "sg:province":"Fribourg",
    "wof:name":"Drs M\u00e9d. Onrubia & Gu\u00e9ron M\u00e9decins Sp\u00e9cialistes Fmh",
    "wof:placetype":"venue"
},
  "geometry": {"coordinates":[6.900288,46.526375],"type":"Point"}
}