{
  "type": "Feature",
  "properties": {
    "iso:country":"CH",
    "sg:address":"Eichenstrasse 4 6015 Reussb\u00fchl. Postfach",
    "sg:city":"Reussb\u00fchl",
    "sg:orig_category":"Fachdetailhandel in Verkaufsr\u00e4umen",
    "sg:postcode":"6015",
    "sg:province":"Luzern",
    "wof:name":"Ravljen Handels Gmbh",
    "wof:placetype":"venue"
},
  "geometry": {"coordinates":[8.2785978317,47.0608406067],"type":"Point"}
}