{
  "type": "Feature",
  "properties": {
    "iso:country":"CH",
    "sg:address":"Pfannenstiel 257",
    "sg:city":"H\u00e4rkingen",
    "sg:orig_category":"Datenverarbeitungsdienste",
    "sg:postcode":"4624",
    "sg:province":"Solothurn",
    "wof:name":"Prodlog Weber Consulting Beratung, Projektleitung In Den Bereichen Logistik U. Produktion",
    "wof:placetype":"venue"
},
  "geometry": {"coordinates":[8.969629,47.463352],"type":"Point"}
}