{
  "type": "Feature",
  "properties": {
    "iso:country":"CH",
    "sg:address":"Avenue De France 15",
    "sg:city":"Sion",
    "sg:orig_category":"Handel mit Motorr\u00e4dern, Teilen U Zubeh\u00f6r Instandhaltung U Reparatur von Motorr\u00e4dern",
    "sg:phone":"+41 27 322 60 22",
    "sg:postcode":"1950",
    "sg:province":"Valais",
    "wof:name":"Greg Motos, Membrez",
    "wof:placetype":"venue"
},
  "geometry": {"coordinates":[7.3553948402,46.2284088135],"type":"Point"}
}