{
  "type": "Feature",
  "properties": {
    "iso:country":"CH",
    "sg:address":"Mettmen",
    "sg:city":"Schongau",
    "sg:orig_category":"Mechanik",
    "sg:phone":"+41 41 917 31 35",
    "sg:postcode":"6288",
    "sg:province":"Luzern",
    "wof:name":"Arno Leuthold Schlosserei Gmbh",
    "wof:placetype":"venue"
},
  "geometry": {"coordinates":[8.2636003494,47.2677307129],"type":"Point"}
}