{
  "type": "Feature",
  "properties": {
    "iso:country":"CH",
    "sg:address":"B\u00fchlstrasse 11",
    "sg:city":"Schaffhausen",
    "sg:orig_category":"Kauf U Verkauf von Immobilien auf eigene Rechnung",
    "sg:postcode":"8200",
    "sg:province":"Schaffhausen",
    "wof:name":"Dupla Ag",
    "wof:placetype":"venue"
},
  "geometry": {"coordinates":[8.6246137619,47.699344635],"type":"Point"}
}