{
  "type": "Feature",
  "properties": {
    "iso:country":"CH",
    "sg:address":"Schwanengasse 34 2500 Biel/bienne. Postfach 314",
    "sg:city":"Biel/bienne",
    "sg:orig_category":"Grosshandel mit festen Brennstoffen U Mineral\u00f6lerzeugnissen",
    "sg:postcode":"2500",
    "sg:province":"Bern",
    "wof:name":"Jenny Hans Peter",
    "wof:placetype":"venue"
},
  "geometry": {"coordinates":[8.508108139,47.5980262756],"type":"Point"}
}