{
  "type": "Feature",
  "properties": {
    "iso:country":"CH",
    "sg:address":"Chem Crusilles",
    "sg:city":"Valeyres-sous-montagny",
    "sg:classifiers":[
        {
            "category":"Professional",
            "subcategory":"Engineering",
            "type":"Services"
        }
    ],
    "sg:phone":"+41 24 445 30 07",
    "sg:postcode":"1441",
    "sg:province":"Vaud",
    "sg:tags":[
        "machine",
        "-",
        "mechanical"
    ],
    "wof:name":"Usine De Mecanique De Precision Max Roth",
    "wof:placetype":"venue"
},
  "geometry": {"coordinates":[6.6114859581,46.7971954346],"type":"Point"}
}