{
  "type": "Feature",
  "properties": {
    "iso:country":"CH",
    "sg:address":"Neudorfstrasse 11 6313 Menzingen. Postfach 341",
    "sg:city":"Menzingen",
    "sg:classifiers":[
        {
            "category":"Travel",
            "subcategory":"Hotels & Motels",
            "type":"Entertainment"
        }
    ],
    "sg:phone":"+41 81 330 79 20",
    "sg:postcode":"6313",
    "sg:province":"Zug",
    "sg:tags":[
        "hotels",
        "mit",
        "restaurant"
    ],
    "wof:name":"Hotel Ochsen, C. Winkler",
    "wof:placetype":"venue"
},
  "geometry": {"coordinates":[9.5008687973,47.0030021667],"type":"Point"}
}