{
  "type": "Feature",
  "properties": {
    "iso:country":"CH",
    "sg:address":"Rue Hans-fries 1",
    "sg:city":"Fribourg",
    "sg:orig_category":"Finanzierungsinstitutionen",
    "sg:postcode":"1700",
    "sg:province":"Fribourg",
    "wof:name":"Ifag Investment & Finanz Ag",
    "wof:placetype":"venue"
},
  "geometry": {"coordinates":[7.1527738571,46.8000068665],"type":"Point"}
}