{
  "type": "Feature",
  "properties": {
    "iso:country":"CH",
    "sg:address":"Route De Moron 24",
    "sg:city":"B\u00e9vilard",
    "sg:orig_category":"Vorschulen, Kinderg\u00e4rten",
    "sg:phone":"+41 32 492 12 03",
    "sg:postcode":"2735",
    "sg:province":"Bern",
    "wof:name":"Ecole Enfantine Communale",
    "wof:placetype":"venue"
},
  "geometry": {"coordinates":[7.2827119827,47.236618042],"type":"Point"}
}