{
  "type": "Feature",
  "properties": {
    "iso:country":"CH",
    "sg:address":"Bigneras",
    "sg:city":"Falera",
    "sg:orig_category":"Detailhandel mit Brot, Back U S\u00fcsswaren",
    "sg:phone":"+41 81 921 53 23",
    "sg:postcode":"7153",
    "sg:province":"Graubunden",
    "wof:name":"Pasterneria-conditoria La Punt, Bernard Gartmann",
    "wof:placetype":"venue"
},
  "geometry": {"coordinates":[9.2256,46.802425],"type":"Point"}
}