{
  "type": "Feature",
  "properties": {
    "iso:country":"CH",
    "sg:address":"Hauptstrasse 48",
    "sg:city":"Bronschhofen",
    "sg:orig_category":"Herstellung von \u00d6fen U Brennern",
    "sg:phone":"+41 71 277 84 36",
    "sg:postcode":"9552",
    "sg:province":"St. Gallen",
    "wof:name":"Floiger Gmbh Ofenbau. Pl\u00e4ttliarbeiten U. Renovation Usw",
    "wof:placetype":"venue"
},
  "geometry": {"coordinates":[9.3391017914,47.4062080383],"type":"Point"}
}