{
  "type": "Feature",
  "properties": {
    "iso:country":"CH",
    "sg:address":"Hauptstrasse 11",
    "sg:city":"Diessenhofen",
    "sg:orig_category":"Grosshandel mit Textilien",
    "sg:postcode":"8253",
    "sg:province":"Thurgau",
    "wof:name":"Nova-line Ag",
    "wof:placetype":"venue"
},
  "geometry": {"coordinates":[9.3885173798,47.3923873901],"type":"Point"}
}