{
  "type": "Feature",
  "properties": {
    "addr:full":"Route De Lausanne 30 Meyriez Fribourg 3280",
    "addr:housenumber":"30",
    "addr:postcode":"3280",
    "addr:street":"Route De Lausanne;Fribourg",
    "iso:country":"CH",
    "sg:address":"Route De Lausanne 30",
    "sg:city":"Meyriez",
    "sg:orig_category":"Datenverarbeitungsdienste Herstellung von Elektrizit\u00e4tsverteilungs U schalteinrichtungen",
    "sg:phone":"+41 26 672 99 22",
    "sg:postcode":"3280",
    "sg:province":"Fribourg",
    "wof:name":"Gistrolon Ag",
    "wof:placetype":"venue"
},
  "geometry": {"coordinates":[7.105364,46.922333],"type":"Point"}
}