{
  "type": "Feature",
  "properties": {
    "iso:country":"CH",
    "sg:address":"Pace Via Della 1a",
    "sg:city":"Locarno",
    "sg:orig_category":"Unclassifiable Establishments",
    "sg:postcode":"6600",
    "sg:province":"Ticino",
    "wof:name":"Coen Holding Sa",
    "wof:placetype":"venue"
},
  "geometry": {"coordinates":[8.7986574173,46.1687812805],"type":"Point"}
}