{
  "type": "Feature",
  "properties": {
    "iso:country":"CH",
    "sg:address":"6315",
    "sg:city":"Morgarten",
    "sg:orig_category":"Sportvereine Sch\u00fctzen",
    "sg:postcode":"6315",
    "sg:province":"Zug",
    "wof:name":"Sch\u00fctzengesellschaft Ammerzwil-weingarten",
    "wof:placetype":"venue"
},
  "geometry": {"coordinates":[7.342110157,47.0682411194],"type":"Point"}
}