{
  "type": "Feature",
  "properties": {
    "iso:country":"CH",
    "sg:address":"1971",
    "sg:city":"Grimisuat",
    "sg:orig_category":"Schulpflegen",
    "sg:postcode":"1971",
    "sg:province":"Valais",
    "wof:name":"Commission Scolaire De L'\u00e9cole Secondaire",
    "wof:placetype":"venue"
},
  "geometry": {"coordinates":[6.7536802292,46.9927597046],"type":"Point"}
}