{
  "type": "Feature",
  "properties": {
    "iso:country":"CH",
    "sg:address":"Aarauerstrasse 16",
    "sg:city":"Oberentfelden",
    "sg:orig_category":"Detailhandel mit Schuhen Detailhandel mit Schuhen U Lederwaren",
    "sg:phone":"+41 62 723 23 44",
    "sg:postcode":"5036",
    "sg:province":"Aargau",
    "wof:name":"Rupp-tanner Schuhe",
    "wof:placetype":"venue"
},
  "geometry": {"coordinates":[8.0465545654,47.3581771851],"type":"Point"}
}