{
  "type": "Feature",
  "properties": {
    "iso:country":"CH",
    "sg:address":"B\u00e4ckerstrasse 52 8004 Z\u00fcrich. Postfach",
    "sg:city":"Z\u00fcrich",
    "sg:orig_category":"Reiseb\u00fcros U Reiseveranstalter",
    "sg:postcode":"8001",
    "sg:province":"Z\u00fcrich",
    "wof:name":"Eurotrain [schweiz] Ag Agenturen Auf D. Gebiet D. Tourismus Usw.",
    "wof:placetype":"venue"
},
  "geometry": {"coordinates":[8.5279893875,47.3753890991],"type":"Point"}
}