{
  "type": "Feature",
  "properties": {
    "iso:country":"CH",
    "sg:address":"Badenerstrasse 276",
    "sg:city":"Z\u00fcrich",
    "sg:orig_category":"Herstellung von sonstigen chemischen Erzeugnissen",
    "sg:postcode":"8004",
    "sg:province":"Z\u00fcrich",
    "wof:name":"Nu-trade Ag",
    "wof:placetype":"venue"
},
  "geometry": {"coordinates":[8.514582634,47.3766326904],"type":"Point"}
}