{
  "type": "Feature",
  "properties": {
    "iso:country":"CH",
    "sg:address":"Nord 5",
    "sg:city":"Rehetobel",
    "sg:orig_category":"Detailhandel mit Milcherzeugnissen U Eiern",
    "sg:phone":"+41 79 291 79 89",
    "sg:postcode":"9038",
    "sg:province":"Appenzell Ausserrhoden",
    "wof:name":"Hans Z\u00e4hner Milchprodukte",
    "wof:placetype":"venue"
},
  "geometry": {"coordinates":[9.4782533646,47.4331207275],"type":"Point"}
}