{
  "type": "Feature",
  "properties": {
    "iso:country":"CH",
    "sg:address":"Bahnhofstrasse 169",
    "sg:city":"Niederuzwil",
    "sg:orig_category":"Allgemeiner Hoch U Tiefbau Allgemeiner Hochbau",
    "sg:phone":"+41 79 411 25 66",
    "sg:postcode":"9244",
    "sg:province":"St. Gallen",
    "wof:name":"Mahler Gebr\u00fcder Ag",
    "wof:placetype":"venue"
},
  "geometry": {"coordinates":[9.148247,47.445923],"type":"Point"}
}