{
  "type": "Feature",
  "properties": {
    "iso:country":"CH",
    "sg:address":"Bohnenbergstrasse 12",
    "sg:city":"Neuhausen",
    "sg:orig_category":"Herstellung von Mess U Kontrollinstrumenten U vorrichtungen",
    "sg:phone":"+41 52 672 68 57",
    "sg:postcode":"8212",
    "sg:province":"Schaffhausen",
    "wof:name":"Widmer Messtechnik Gmbh",
    "wof:placetype":"venue"
},
  "geometry": {"coordinates":[8.6155805588,47.6888084412],"type":"Point"}
}