{
  "type": "Feature",
  "properties": {
    "iso:country":"CH",
    "sg:address":"Unterdorf 150",
    "sg:city":"Ursenbach",
    "sg:orig_category":"Stukkateurgewerbe, Gipserei U Verputzerei",
    "sg:phone":"+41 62 965 37 20",
    "sg:postcode":"4937",
    "sg:province":"Bern",
    "wof:name":"Fr. Strahm",
    "wof:placetype":"venue"
},
  "geometry": {"coordinates":[7.7725977898,47.1367874146],"type":"Point"}
}