{
  "type": "Feature",
  "properties": {
    "iso:country":"CH",
    "sg:address":"Kastanienbaumstrasse 4",
    "sg:city":"Horw",
    "sg:orig_category":"Schmieden",
    "sg:phone":"+41 41 340 67 67",
    "sg:postcode":"6048",
    "sg:province":"Luzern",
    "wof:name":"Willy Wermelinger Schmiede",
    "wof:placetype":"venue"
},
  "geometry": {"coordinates":[8.3091278076,47.0231437683],"type":"Point"}
}