{
  "type": "Feature",
  "properties": {
    "iso:country":"CH",
    "sg:address":"Ador Quai Gustave- 2 1207 Gen\u00e8ve. Postfach",
    "sg:city":"Gen\u00e8ve",
    "sg:orig_category":"Vermietung U Verpachtung von eigenen Immobilien",
    "sg:phone":"+41 22 786 88 66",
    "sg:postcode":"1201",
    "sg:province":"Gen\u00e8ve",
    "wof:name":"Racel Sa N\u00e9goce De Biens Mobiliers, Immobiliers Etc",
    "wof:placetype":"venue"
},
  "geometry": {"coordinates":[6.1550769806,46.2044410706],"type":"Point"}
}