{
  "type": "Feature",
  "properties": {
    "iso:country":"CH",
    "sg:address":"R\u00f6ntgenstrasse 66",
    "sg:city":"Z\u00fcrich",
    "sg:orig_category":"Detailhandel mit Waren verschiedener Art, Hauptrichtung Nahrungsmittel",
    "sg:phone":"+41 71 245 81 22",
    "sg:postcode":"8005",
    "sg:province":"Z\u00fcrich",
    "wof:name":"Dieter Tschanz Lebensmittelgesch\u00e4ft",
    "wof:placetype":"venue"
},
  "geometry": {"coordinates":[9.3775119781,47.4374313354],"type":"Point"}
}