{
  "type": "Feature",
  "properties": {
    "iso:country":"CH",
    "sg:address":"Galgenried 2",
    "sg:city":"Stans",
    "sg:orig_category":"Herstellung von sonstigen Maschinen f\u00fcr bestimmte Verwendung",
    "sg:phone":"+41 56 496 34 01",
    "sg:postcode":"6370",
    "sg:province":"Nidwalden",
    "wof:name":"B\u00e4uerliche Arbeitsgruppe Qualit\u00e4tskompost Regez Jakob, Schweizer Andreas, Traub Erich",
    "wof:placetype":"venue"
},
  "geometry": {"coordinates":[8.2937345505,47.4067192078],"type":"Point"}
}