{
  "type": "Feature",
  "properties": {
    "iso:country":"CH",
    "sg:address":"Via San Gottardo 42",
    "sg:city":"Bellinzona",
    "sg:orig_category":"RESTAURANTS: TEA-ROOMS",
    "sg:phone":"+41 91 825 12 96",
    "sg:postcode":"6500",
    "sg:province":"Ticino",
    "wof:name":"Bar Al Persico Di Valota Danilo",
    "wof:placetype":"venue"
},
  "geometry": {"coordinates":[9.0321378708,46.2004394531],"type":"Point"}
}