{
  "type": "Feature",
  "properties": {
    "iso:country":"CH",
    "sg:address":"Kannenb\u00fchlstrasse 5",
    "sg:city":"Hochdorf",
    "sg:classifiers":[
        {
            "category":"Banks & Credit Unions",
            "subcategory":"Bank",
            "type":"Services"
        }
    ],
    "sg:phone":"+41 4141882119",
    "sg:postcode":"6280",
    "sg:province":"Luzern",
    "wof:name":"Schweiz. Mobiliar",
    "wof:placetype":"venue"
},
  "geometry": {"coordinates":[8.291698,47.171078],"type":"Point"}
}