{
  "type": "Feature",
  "properties": {
    "iso:country":"CH",
    "sg:address":"Rue De La Plaine 28 1400 Yverdon-les-bains. Postfach",
    "sg:city":"Yverdon-les-bains",
    "sg:orig_category":"Fachdetailhandel in Verkaufsr\u00e4umen",
    "sg:postcode":"1400",
    "sg:province":"Vaud",
    "wof:name":"Les Ecritures S\u00e0rl",
    "wof:placetype":"venue"
},
  "geometry": {"coordinates":[6.6434907913,46.7773017883],"type":"Point"}
}