{
  "type": "Feature",
  "properties": {
    "iso:country":"CH",
    "sg:address":"Klosterweg 3",
    "sg:city":"Horgen",
    "sg:orig_category":"Politische Parteien CVP",
    "sg:phone":"+41 12062900",
    "sg:postcode":"8810",
    "sg:province":"Z\u00fcrich",
    "wof:name":"Cvp Sektion Kilchberg",
    "wof:placetype":"venue"
},
  "geometry": {"coordinates":[8.5378284454,47.314540863],"type":"Point"}
}