{
  "type": "Feature",
  "properties": {
    "addr:full":"Rue De L'evole 9 Neuch\u00e2tel Neuch\u00e2tel 2000",
    "addr:housenumber":"9",
    "addr:postcode":"2000",
    "addr:street":"Rue De L'Evole",
    "iso:country":"CH",
    "sg:address":"Rue De L'evole 9",
    "sg:city":"Neuch\u00e2tel",
    "sg:orig_category":"Detailhandel mit Antiquit\u00e4ten Detailhandel mit M\u00f6beln",
    "sg:phone":"+41 32 493 57 17",
    "sg:postcode":"2000",
    "sg:province":"Neuch\u00e2tel",
    "wof:name":"Daniel Bettex Meubles Du Vieux Battoir",
    "wof:placetype":"venue"
},
  "geometry": {"coordinates":[7.38547,47.304199],"type":"Point"}
}