{
  "type": "Feature",
  "properties": {
    "iso:country":"CH",
    "sg:address":"Lang\u00e4cker 36",
    "sg:city":"Wettingen",
    "sg:orig_category":"Herstellung von Armaturen",
    "sg:postcode":"5430",
    "sg:province":"Aargau",
    "wof:name":"Swiss Hydraulik J. Emmenegger",
    "wof:placetype":"venue"
},
  "geometry": {"coordinates":[9.0465898514,47.4184570312],"type":"Point"}
}