{
  "type": "Feature",
  "properties": {
    "iso:country":"CH",
    "sg:address":"Via Canonico Ghiringhelli 7",
    "sg:city":"Bellinzona",
    "sg:orig_category":"Politische Parteien CVP",
    "sg:phone":"+41 91 825 23 77",
    "sg:postcode":"6500",
    "sg:province":"Ticino",
    "wof:name":"Partito Popolare Democratico",
    "wof:placetype":"venue"
},
  "geometry": {"coordinates":[9.0189733505,46.1906929016],"type":"Point"}
}