{
  "type": "Feature",
  "properties": {
    "iso:country":"CH",
    "sg:address":"Luegetenstrasse 2 6313 Menzingen. Postfach 52",
    "sg:city":"Menzingen",
    "sg:orig_category":"Detailhandel mit Milcherzeugnissen U Eiern",
    "sg:phone":"+41 41 755 35 00",
    "sg:postcode":"6313",
    "sg:province":"Zug",
    "wof:name":"Agnes Christen Dorfmolki",
    "wof:placetype":"venue"
},
  "geometry": {"coordinates":[8.5919065475,47.1782913208],"type":"Point"}
}