{
  "type": "Feature",
  "properties": {
    "iso:country":"CH",
    "sg:address":"Metzgergasse 6",
    "sg:city":"K\u00f6lliken",
    "sg:orig_category":"Herstellung von sonstigen Maschinen f\u00fcr unspezifische Verwendung",
    "sg:phone":"+41 62 723 82 67",
    "sg:postcode":"5742",
    "sg:province":"Aargau",
    "wof:name":"Brack & Co",
    "wof:placetype":"venue"
},
  "geometry": {"coordinates":[8.0251922607,47.3309860229],"type":"Point"}
}