{
  "type": "Feature",
  "properties": {
    "iso:country":"CH",
    "sg:address":"Hauptstrasse 40a",
    "sg:city":"Oltingen",
    "sg:orig_category":"Gemeindeverwaltungen",
    "sg:phone":"+41 61 991 06 96",
    "sg:postcode":"4494",
    "sg:province":"Basel-Landschaft",
    "wof:name":"Gemeindeverwaltung Oltingen",
    "wof:placetype":"venue"
},
  "geometry": {"coordinates":[7.9329648018,47.4321937561],"type":"Point"}
}