{
  "type": "Feature",
  "properties": {
    "iso:country":"CH",
    "sg:address":"Industriestrasse 5",
    "sg:city":"Maienfeld",
    "sg:classifiers":[
        {
            "category":"Utilities",
            "subcategory":"Electric",
            "type":"Services"
        }
    ],
    "sg:phone":"+41 81 302 40 41",
    "sg:postcode":"7304",
    "sg:province":"Graubunden",
    "sg:tags":[
        "equipment",
        "electronic",
        "vehicle"
    ],
    "wof:name":"Caviezel & Conrad Ag",
    "wof:placetype":"venue"
},
  "geometry": {"coordinates":[9.5257101059,47.0017967224],"type":"Point"}
}