{
  "type": "Feature",
  "properties": {
    "iso:country":"CH",
    "sg:address":"Eichen 129",
    "sg:city":"Sch\u00e4nis",
    "sg:orig_category":"Grosshandel mit Holz U Baustoffen Herstellung von Elektromotoren, Generatoren U Transformatoren",
    "sg:phone":"+41 55 615 28 24",
    "sg:postcode":"8718",
    "sg:province":"St. Gallen",
    "wof:name":"Remo Riget Gmbh Garagentore",
    "wof:placetype":"venue"
},
  "geometry": {"coordinates":[9.0501260757,47.1541290283],"type":"Point"}
}