{
  "type": "Feature",
  "properties": {
    "iso:country":"CH",
    "sg:address":"Rue Centrale 47 2740 Montagne-moutier Case Postale 21",
    "sg:city":"Montagne-moutier",
    "sg:orig_category":"Bauingenieurb\u00fcros Heizung L\u00fcftung Klima Werbeagenturen",
    "sg:phone":"+41 19415055",
    "sg:postcode":"2740",
    "sg:province":"Bern",
    "wof:name":"Luginb\u00fchl & Partner Ag Ing. F. Energie- & Haustechnik",
    "wof:placetype":"venue"
},
  "geometry": {"coordinates":[8.560132,47.362724],"type":"Point"}
}