{
  "type": "Feature",
  "properties": {
    "iso:country":"CH",
    "sg:address":"La Poste",
    "sg:city":"Champ\u00e9ry",
    "sg:orig_category":"Nationale Postdienste",
    "sg:phone":"+41 24 479 12 65",
    "sg:postcode":"1874",
    "sg:province":"Valais",
    "wof:name":"La Poste Suisse",
    "wof:placetype":"venue"
},
  "geometry": {"coordinates":[6.8706860542,46.1794052124],"type":"Point"}
}