{
  "type": "Feature",
  "properties": {
    "addr:full":"Metzgergasse 17 Burgdorf Bern 3400",
    "addr:housenumber":"17",
    "addr:postcode":"3400",
    "addr:street":"Metzgergasse",
    "iso:country":"CH",
    "sg:address":"Metzgergasse 17",
    "sg:city":"Burgdorf",
    "sg:orig_category":"Detailhandel mit Brot, Back U S\u00fcsswaren",
    "sg:phone":"+41 34 422 27 73",
    "sg:postcode":"3400",
    "sg:province":"Bern",
    "wof:name":"Schwarz H.",
    "wof:placetype":"venue"
},
  "geometry": {"coordinates":[7.62661,47.057095],"type":"Point"}
}