{
  "type": "Feature",
  "properties": {
    "iso:country":"CH",
    "sg:address":"Burg 8",
    "sg:city":"Lichtensteig",
    "sg:orig_category":"Haltung von Rindern",
    "sg:postcode":"9620",
    "sg:province":"St. Gallen",
    "wof:name":"Viehzuchtgenossenschaft Lichtensteig",
    "wof:placetype":"venue"
},
  "geometry": {"coordinates":[9.088973999,47.3239135742],"type":"Point"}
}