{
  "type": "Feature",
  "properties": {
    "iso:country":"CH",
    "sg:address":"Rathausgasse 5",
    "sg:city":"Zofingen",
    "sg:orig_category":"Elektroinstallation",
    "sg:phone":"+41 62 746 00 00",
    "sg:postcode":"4800",
    "sg:province":"Aargau",
    "wof:name":"Elektro-r\u00fcegger Gmbh",
    "wof:placetype":"venue"
},
  "geometry": {"coordinates":[7.9465308189,47.2882003784],"type":"Point"}
}