{
  "type": "Feature",
  "properties": {
    "iso:country":"CH",
    "sg:address":"Lauerzweg 2",
    "sg:city":"Kriens",
    "sg:orig_category":"Herstellung von keramischen Wand U Bodenfliesen U platten Verlegen von Fliesen U Platten",
    "sg:phone":"+41 14934411",
    "sg:postcode":"6010",
    "sg:province":"Luzern",
    "wof:name":"Bosshard Keramische Wand Und Bodenbel\u00e4ge",
    "wof:placetype":"venue"
},
  "geometry": {"coordinates":[8.4707546234,47.3578414917],"type":"Point"}
}