{
  "type": "Feature",
  "properties": {
    "iso:country":"CH",
    "sg:address":"Bahnhofstrasse 20",
    "sg:city":"B\u00e4retswil",
    "sg:orig_category":"RESTAURANTS: TEA-ROOMS",
    "sg:postcode":"8344",
    "sg:province":"Z\u00fcrich",
    "wof:name":"Dulay Gmbh",
    "wof:placetype":"venue"
},
  "geometry": {"coordinates":[8.8525314331,47.3371543884],"type":"Point"}
}