{
  "type": "Feature",
  "properties": {
    "iso:country":"CH",
    "sg:address":"Hauptstrasse 26",
    "sg:city":"Derendingen",
    "sg:orig_category":"Bau U Wohngenossenschaften",
    "sg:postcode":"4552",
    "sg:province":"Solothurn",
    "wof:name":"Wohnbau-gen. Derendingen",
    "wof:placetype":"venue"
},
  "geometry": {"coordinates":[7.584259,47.196899],"type":"Point"}
}