{
  "type": "Feature",
  "properties": {
    "iso:country":"CH",
    "sg:address":"Sempacherstrasse 15 8032 Z\u00fcrich",
    "sg:city":"Zust",
    "sg:orig_category":"Unclassifiable Establishments",
    "sg:phone":"+41 14213337",
    "sg:postcode":"32",
    "wof:name":"Schauenburg Ag",
    "wof:placetype":"venue"
},
  "geometry": {"coordinates":[8.5679702759,47.3668403625],"type":"Point"}
}