{
  "type": "Feature",
  "properties": {
    "iso:country":"CH",
    "sg:address":"Sonnenweg 8",
    "sg:city":"Ormalingen",
    "sg:orig_category":"Herstellung von Teppichen",
    "sg:postcode":"4466",
    "sg:province":"Basel-Landschaft",
    "wof:name":"Reto Rossi Und Patrick Rossi",
    "wof:placetype":"venue"
},
  "geometry": {"coordinates":[7.8779602051,47.471157074],"type":"Point"}
}