{
  "type": "Feature",
  "properties": {
    "iso:country":"CH",
    "sg:address":"Brandbodenstrasse 10",
    "sg:city":"Dallenwil",
    "sg:orig_category":"Kauf U Verkauf von Immobilien auf eigene Rechnung",
    "sg:postcode":"6383",
    "sg:province":"Nidwalden",
    "wof:name":"Odermatt Verwaltungs Ag",
    "wof:placetype":"venue"
},
  "geometry": {"coordinates":[8.3901872635,46.9362602234],"type":"Point"}
}