{
  "type": "Feature",
  "properties": {
    "iso:country":"CH",
    "sg:address":"Klosterr\u00fctistrasse 9",
    "sg:city":"Neuenhof",
    "sg:orig_category":"Instandhaltung U Reparatur von Automobilen",
    "sg:phone":"+41 56 406 30 20",
    "sg:postcode":"5432",
    "sg:province":"Aargau",
    "wof:name":"Carrosserie & Autospritzwerk Vicari",
    "wof:placetype":"venue"
},
  "geometry": {"coordinates":[8.3094987869,47.4548683167],"type":"Point"}
}