{
  "type": "Feature",
  "properties": {
    "iso:country":"CH",
    "sg:address":"Soldini Via 23",
    "sg:city":"Chiasso",
    "sg:orig_category":"Sonstiger Grosshandel",
    "sg:phone":"+41 91 683 00 29",
    "sg:postcode":"6830",
    "sg:province":"Ticino",
    "wof:name":"Krystals Sagl",
    "wof:placetype":"venue"
},
  "geometry": {"coordinates":[9.0231666565,45.8339614868],"type":"Point"}
}