{
  "type": "Feature",
  "properties": {
    "iso:country":"CH",
    "sg:address":"Friedensgasse 58",
    "sg:city":"Basel",
    "sg:orig_category":"Kinderkrippen U horte",
    "sg:phone":"+41 61 381 72 29",
    "sg:postcode":"4056",
    "sg:province":"Basel-Stadt",
    "wof:name":"Kinderkrippe Zem Freie Spatz",
    "wof:placetype":"venue"
},
  "geometry": {"coordinates":[7.5765018463,47.5615844727],"type":"Point"}
}