{
  "type": "Feature",
  "properties": {
    "iso:country":"CH",
    "sg:address":"Staatsstrasse 94a",
    "sg:city":"H\u00fcnibach",
    "sg:orig_category":"Grosshandel mit festen Brennstoffen U Mineral\u00f6lerzeugnissen Mineral\u00f6lverarbeitung",
    "sg:phone":"+41 33 243 57 37",
    "sg:postcode":"3626",
    "sg:province":"Bern",
    "wof:name":"Cyclon Gmbh",
    "wof:placetype":"venue"
},
  "geometry": {"coordinates":[7.648015976,46.7437667847],"type":"Point"}
}