{
  "type": "Feature",
  "properties": {
    "iso:country":"CH",
    "sg:address":"Via S.sisto",
    "sg:city":"Poschiavo",
    "sg:orig_category":"Vereine Frauen Vereine Gemeinn\u00fctzige",
    "sg:postcode":"7742",
    "sg:province":"Graubunden",
    "wof:name":"Coop Frauenbund Sekt.poschiavo",
    "wof:placetype":"venue"
},
  "geometry": {"coordinates":[10.0568399429,46.3265647888],"type":"Point"}
}