{
  "type": "Feature",
  "properties": {
    "iso:country":"CH",
    "sg:address":"Nebikerstrasse 11",
    "sg:city":"Sch\u00f6tz",
    "sg:orig_category":"Herstellung von Bereifungen",
    "sg:phone":"+41 41 980 59 68",
    "sg:postcode":"6247",
    "sg:province":"Luzern",
    "wof:name":"Pneuh\u00fcsli Albisser Anton",
    "wof:placetype":"venue"
},
  "geometry": {"coordinates":[7.988199234,47.1726837158],"type":"Point"}
}