{
  "type": "Feature",
  "properties": {
    "addr:full":"Chemin Du Marais 8 Romanel-s-lausanne Vaud 1032",
    "addr:housenumber":"8",
    "addr:postcode":"1032",
    "addr:street":"Chemin Du Marais",
    "iso:country":"CH",
    "sg:address":"Chemin Du Marais 8",
    "sg:city":"Romanel-s-lausanne",
    "sg:orig_category":"Detailhandel mit Beleuchtungs U Haushaltsgegenst\u00e4nden",
    "sg:phone":"+41 21 647 81 81",
    "sg:postcode":"1032",
    "sg:province":"Vaud",
    "wof:name":"Lumimart",
    "wof:placetype":"venue"
},
  "geometry": {"coordinates":[6.615482,46.559036],"type":"Point"}
}