{
  "type": "Feature",
  "properties": {
    "iso:country":"CH",
    "sg:address":"Obgassweg 3",
    "sg:city":"Buochs",
    "sg:orig_category":"Kauf U Verkauf von Immobilien auf eigene Rechnung",
    "sg:postcode":"6374",
    "sg:province":"Nidwalden",
    "wof:name":"Abeka Handels + Immobilien Ag",
    "wof:placetype":"venue"
},
  "geometry": {"coordinates":[8.4143190384,46.9708061218],"type":"Point"}
}