{
  "type": "Feature",
  "properties": {
    "iso:country":"CH",
    "sg:address":"Le Ch\u00e2teau",
    "sg:city":"Aubonne",
    "sg:orig_category":"Bezirks, Sekundar, Realschulen, Oberstufe der Primarschulen",
    "sg:phone":"+41 26 475 30 79",
    "sg:postcode":"1170",
    "sg:province":"Vaud",
    "wof:name":"Ecole Secondaire",
    "wof:placetype":"venue"
},
  "geometry": {"coordinates":[7.146491,46.783302],"type":"Point"}
}