{
  "type": "Feature",
  "properties": {
    "iso:country":"CH",
    "sg:address":"Route Chiblins",
    "sg:city":"Gingins",
    "sg:classifiers":[
        {
            "category":"Banks & Credit Unions",
            "subcategory":"Bank",
            "type":"Services"
        }
    ],
    "sg:phone":"+41 27 281 12 89",
    "sg:postcode":"1261",
    "sg:province":"Vaud",
    "wof:name":"Banque Raiffeisen H\u00e9r\u00e9mence",
    "wof:placetype":"venue"
},
  "geometry": {"coordinates":[7.40466,46.183319],"type":"Point"}
}