{
  "type": "Feature",
  "properties": {
    "iso:country":"CH",
    "sg:address":"Predigergasse 15",
    "sg:city":"Z\u00fcrich",
    "sg:orig_category":"Werbegrafikateliers Zeitschriftenverlag",
    "sg:phone":"+41 12539190",
    "sg:postcode":"8001",
    "sg:province":"Z\u00fcrich",
    "wof:name":"Joss & Witschi Gmbh",
    "wof:placetype":"venue"
},
  "geometry": {"coordinates":[8.5457677841,47.3733940125],"type":"Point"}
}