{
  "type": "Feature",
  "properties": {
    "iso:country":"CH",
    "sg:address":"Chemin De Buchaux 36",
    "sg:city":"Bevaix",
    "sg:classifiers":[
        {
            "category":"Shopping",
            "subcategory":"Stationery & Office Supplies",
            "type":"Retail Goods"
        }
    ],
    "sg:phone":"+41 32 847 95 10",
    "sg:postcode":"2022",
    "sg:province":"Neuch\u00e2tel",
    "sg:tags":[
        "adhesive",
        "label"
    ],
    "wof:name":"Gern & Cie Sa",
    "wof:placetype":"venue"
},
  "geometry": {"coordinates":[6.82102,46.934483],"type":"Point"}
}