{
  "type": "Feature",
  "properties": {
    "iso:country":"CH",
    "sg:address":"Dorfstrasse D\u00e4twil",
    "sg:city":"Adlikon",
    "sg:orig_category":"Abbruch U Sprenggewerbe, Erdbewegungsarbeiten Erdbewegungsarbeiten",
    "sg:phone":"+41 52 383 24 01",
    "sg:postcode":"8452",
    "sg:province":"Z\u00fcrich",
    "wof:name":"K\u00fcndig & Winkler Ag",
    "wof:placetype":"venue"
},
  "geometry": {"coordinates":[8.813061,47.458035],"type":"Point"}
}