{
  "type": "Feature",
  "properties": {
    "iso:country":"CH",
    "sg:address":"D\u00fcrrbergstrasse 3",
    "sg:city":"Aarburg",
    "sg:orig_category":"Polizei",
    "sg:phone":"+41 62 791 59 59",
    "sg:postcode":"4663",
    "sg:province":"Aargau",
    "wof:name":"Kantonaler Polizeiposten",
    "wof:placetype":"venue"
},
  "geometry": {"coordinates":[7.8994379044,47.3222236633],"type":"Point"}
}