{
  "type": "Feature",
  "properties": {
    "addr:full":"Route De Saint-julien 82 Grand-lancy Gen\u00e8ve 1212",
    "addr:housenumber":"82",
    "addr:postcode":"1212",
    "addr:street":"Route De Saint-Julien",
    "iso:country":"CH",
    "sg:address":"Route De Saint-julien 82",
    "sg:city":"Grand-lancy",
    "sg:orig_category":"Architekturb\u00fcros",
    "sg:phone":"+41 22 301 21 21",
    "sg:postcode":"1212",
    "sg:province":"Gen\u00e8ve",
    "wof:name":"Pierre-henri & Bernard Gindre Bureau D'architecture",
    "wof:placetype":"venue"
},
  "geometry": {"coordinates":[6.126537,46.17289],"type":"Point"}
}