{
  "type": "Feature",
  "properties": {
    "iso:country":"CH",
    "sg:address":"Untertor 10",
    "sg:city":"Winterthur",
    "sg:orig_category":"Detailhandel mit Schuhen Detailhandel mit Schuhen U Lederwaren",
    "sg:phone":"+41 79 422 37 71",
    "sg:postcode":"8400",
    "sg:province":"Z\u00fcrich",
    "wof:name":"Boutique Antoinette Gmbh",
    "wof:placetype":"venue"
},
  "geometry": {"coordinates":[9.4717073441,47.1658706665],"type":"Point"}
}