{
  "type": "Feature",
  "properties": {
    "iso:country":"CH",
    "sg:address":"Cherweg",
    "sg:city":"Sarnen",
    "sg:orig_category":"Detailhandel mit Milcherzeugnissen U Eiern Verarbeitung von Milch",
    "sg:phone":"+41 41 660 16 30",
    "sg:postcode":"6060",
    "sg:province":"Obwalden",
    "wof:name":"Leo M\u00fcller Molkerei",
    "wof:placetype":"venue"
},
  "geometry": {"coordinates":[8.2445449829,46.893196106],"type":"Point"}
}