{
  "type": "Feature",
  "properties": {
    "iso:country":"CH",
    "sg:address":"Chemin Du Levant 23",
    "sg:city":"Lausanne",
    "sg:orig_category":"Verlagsgewerbe",
    "sg:phone":"+41 21 311 44 70",
    "sg:postcode":"1005",
    "sg:province":"Vaud",
    "wof:name":"International Registry Of Who's Who Sa",
    "wof:placetype":"venue"
},
  "geometry": {"coordinates":[6.6502799988,46.520324707],"type":"Point"}
}