{
  "type": "Feature",
  "properties": {
    "iso:country":"CH",
    "sg:address":"Z\u00fcrcherstrasse 25",
    "sg:city":"Oberengstringen",
    "sg:orig_category":"Chemische Reinigung",
    "sg:phone":"+41 17504280",
    "sg:postcode":"8102",
    "sg:province":"Z\u00fcrich",
    "wof:name":"Irma Esposito Textilreinigung Und W\u00e4scherei",
    "wof:placetype":"venue"
},
  "geometry": {"coordinates":[8.474887,47.405331],"type":"Point"}
}