{
  "type": "Feature",
  "properties": {
    "iso:country":"CH",
    "sg:address":"Schachenstrasse 36",
    "sg:city":"Sch\u00f6nenwerd",
    "sg:orig_category":"Grosshandel mit Getr\u00e4nken Grosshandel mit Wein U Spirituosen",
    "sg:phone":"+41 79 211 50 42",
    "sg:postcode":"5012",
    "sg:province":"Solothurn",
    "wof:name":"Giorgio Gavaz Weinimport",
    "wof:placetype":"venue"
},
  "geometry": {"coordinates":[8.0049123764,47.379699707],"type":"Point"}
}