{
  "type": "Feature",
  "properties": {
    "iso:country":"CH",
    "sg:address":"Am Wasser 65 8000 Z\u00fcrich. Postfach",
    "sg:city":"Z\u00fcrich",
    "sg:orig_category":"Herstellung von elektronischen Bauelementen",
    "sg:phone":"+41 18254814",
    "sg:postcode":"8049",
    "sg:province":"Z\u00fcrich",
    "wof:name":"Illert Elektronik Ag",
    "wof:placetype":"venue"
},
  "geometry": {"coordinates":[8.5040121078,47.3965263367],"type":"Point"}
}