{
  "type": "Feature",
  "properties": {
    "iso:country":"CH",
    "sg:address":"Im Geren 1",
    "sg:city":"Urdorf",
    "sg:orig_category":"Ingenieurb\u00fcros Maschinenbau",
    "sg:phone":"+41 17351110",
    "sg:postcode":"8902",
    "sg:province":"Z\u00fcrich",
    "wof:name":"Ingenieurb\u00fcro Rhyner",
    "wof:placetype":"venue"
},
  "geometry": {"coordinates":[8.4201965332,47.3810844421],"type":"Point"}
}