{
  "type": "Feature",
  "properties": {
    "iso:country":"CH",
    "sg:address":"Marktgasse 47",
    "sg:city":"Rheinfelden",
    "sg:orig_category":"Detailhandel mit Uhren U Schmuck Fachdetailhandel in Verkaufsr\u00e4umen",
    "sg:phone":"+41 61 831 70 60",
    "sg:postcode":"4310",
    "sg:province":"Aargau",
    "wof:name":"Stefan Baltensperger Schmuck-edelsteine-uhren Gmbh",
    "wof:placetype":"venue"
},
  "geometry": {"coordinates":[7.7916531563,47.5548324585],"type":"Point"}
}