{
  "type": "Feature",
  "properties": {
    "iso:country":"CH",
    "sg:address":"Chemin De Saule 69",
    "sg:city":"Bernex",
    "sg:orig_category":"Werbung",
    "sg:phone":"+41 22 757 67 68",
    "sg:postcode":"1233",
    "sg:province":"Gen\u00e8ve",
    "wof:name":"Leu Martin",
    "wof:placetype":"venue"
},
  "geometry": {"coordinates":[6.0684299469,46.1753692627],"type":"Point"}
}