{
  "type": "Feature",
  "properties": {
    "iso:country":"CH",
    "sg:address":"Blumenweg 3",
    "sg:city":"Horgen",
    "sg:orig_category":"Sonstiger Grosshandel",
    "sg:phone":"+41 32 841 65 32",
    "sg:postcode":"8810",
    "sg:province":"Z\u00fcrich",
    "wof:name":"Gretillat Import-export",
    "wof:placetype":"venue"
},
  "geometry": {"coordinates":[6.857986927,46.9656143188],"type":"Point"}
}