{
  "type": "Feature",
  "properties": {
    "iso:country":"CH",
    "sg:address":"Lerchenstrasse 15",
    "sg:city":"Muttenz",
    "sg:orig_category":"Gartenbau",
    "sg:phone":"+41 61 461 55 10",
    "sg:postcode":"4132",
    "sg:province":"Basel-Landschaft",
    "wof:name":"Walter Zehntner Gartenbau",
    "wof:placetype":"venue"
},
  "geometry": {"coordinates":[7.6355900764,47.5341072083],"type":"Point"}
}