{
  "type": "Feature",
  "properties": {
    "iso:country":"CH",
    "sg:address":"Schmiedengasse 6",
    "sg:city":"Biel/bienne",
    "sg:orig_category":"Detailhandel mit B\u00fcchern Detailhandel mit Gebrauchtwaren in Verkaufsr\u00e4umen",
    "sg:phone":"+41 32 322 33 86",
    "sg:postcode":"2502",
    "sg:province":"Bern",
    "wof:name":"Daniel Thierstein Antiquariat",
    "wof:placetype":"venue"
},
  "geometry": {"coordinates":[7.24563,47.140511],"type":"Point"}
}