{
  "type": "Feature",
  "properties": {
    "iso:country":"CH",
    "sg:address":"Les Granges 1837 Ch\u00e2teau-d'oex. Postfach",
    "sg:city":"Ch\u00e2teau-d'oex",
    "sg:orig_category":"Bau von Strassen, Sportanlagen U Bahnverkehrsstrecken",
    "sg:postcode":"1837",
    "wof:name":"Technoteam Ag",
    "wof:placetype":"venue"
},
  "geometry": {"coordinates":[8.578236,47.322563],"type":"Point"}
}