{
  "type": "Feature",
  "properties": {
    "iso:country":"CH",
    "sg:address":"Badhausstrasse 19",
    "sg:city":"Biel/bienne",
    "sg:orig_category":"Zahntechnische Laboratorien",
    "sg:phone":"+41 79 333 20 10",
    "sg:postcode":"2503",
    "sg:province":"Bern",
    "wof:name":"Umberto Montesi Zahntechnisches Labor",
    "wof:placetype":"venue"
},
  "geometry": {"coordinates":[7.2379159927,47.1322364807],"type":"Point"}
}