{
  "type": "Feature",
  "properties": {
    "iso:country":"CH",
    "sg:address":"St. Jakobs-strasse 10",
    "sg:city":"Muttenz",
    "sg:orig_category":"Zahnarztpraxen",
    "sg:phone":"+41 61 461 08 11",
    "sg:postcode":"4132",
    "sg:province":"Basel-Landschaft",
    "wof:name":"Dr. Med. Dent. Sedat Yolalan Zahnarzt",
    "wof:placetype":"venue"
},
  "geometry": {"coordinates":[7.6464390755,47.5284385681],"type":"Point"}
}