{
  "type": "Feature",
  "properties": {
    "iso:country":"CH",
    "sg:address":"Wallisstrasse",
    "sg:city":"Mellingen",
    "sg:orig_category":"Primarschulen",
    "sg:postcode":"5507",
    "sg:province":"Aargau",
    "wof:name":"Primarschule Kleine Kreuzzelg",
    "wof:placetype":"venue"
},
  "geometry": {"coordinates":[8.2687005997,47.4159431458],"type":"Point"}
}