{
  "type": "Feature",
  "properties": {
    "iso:country":"CH",
    "sg:address":"Avenue De Grandson",
    "sg:city":"Yverdon-les-bains",
    "sg:classifiers":[
        {
            "category":"Autos & Motor Vehicles",
            "subcategory":"Auto Supplies",
            "type":"Retail Goods"
        }
    ],
    "sg:phone":"+41 32 926 50 85",
    "sg:postcode":"1400",
    "sg:province":"Vaud",
    "sg:tags":[
        "car",
        "radio",
        "accessory"
    ],
    "wof:name":"Asticher Sa",
    "wof:placetype":"venue"
},
  "geometry": {"coordinates":[6.801051,47.085365],"type":"Point"}
}