{
  "type": "Feature",
  "properties": {
    "addr:full":"Harschwendi West 1036 Waldstatt Appenzell Ausserrhoden 9104",
    "addr:housenumber":"1036",
    "addr:postcode":"9104",
    "addr:street":"Ausserrhoden",
    "iso:country":"CH",
    "sg:address":"Harschwendi West 1036",
    "sg:city":"Waldstatt",
    "sg:orig_category":"Bauschreinerei Herstellung von Konstruktionsteilen, Fertigbauteilen U Ausbauelementen aus Holz",
    "sg:phone":"+41 71 352 17 48",
    "sg:postcode":"9104",
    "sg:province":"Appenzell Ausserrhoden",
    "wof:name":"Walter Kolb Schreinermontagen Innenausbau",
    "wof:placetype":"venue"
},
  "geometry": {"coordinates":[9.271818,47.353512],"type":"Point"}
}