{
  "type": "Feature",
  "properties": {
    "addr:full":"2923 Courtema\u00eeche Jura 2923",
    "addr:housenumber":"2923",
    "addr:postcode":"2923",
    "addr:street":"Courtemai\u0302Che Jura",
    "iso:country":"CH",
    "sg:address":"2923",
    "sg:city":"Courtema\u00eeche",
    "sg:orig_category":"Allgemeiner Hoch U Tiefbau Allgemeiner Hochbau",
    "sg:phone":"+41 79 408 44 41",
    "sg:postcode":"2923",
    "sg:province":"Jura",
    "wof:name":"Choulat Guy Sa",
    "wof:placetype":"venue"
},
  "geometry": {"coordinates":[7.04381,47.45895],"type":"Point"}
}