{
  "type": "Feature",
  "properties": {
    "iso:country":"CH",
    "sg:address":"Chemin David Munier 22a",
    "sg:city":"Cologny",
    "sg:orig_category":"Architektur U Ingenieurb\u00fcros",
    "sg:postcode":"1223",
    "sg:province":"Gen\u00e8ve",
    "wof:name":"Scitech, Prof. Dr. K. Andres, Physikalisch-technische Beratung",
    "wof:placetype":"venue"
},
  "geometry": {"coordinates":[8.588894,47.32143],"type":"Point"}
}