{
  "type": "Feature",
  "properties": {
    "iso:country":"CH",
    "sg:address":"Nant Rue Du 27",
    "sg:city":"Genf",
    "sg:orig_category":"Bauspenglerei Herstellung von keramischen Wand U Bodenfliesen U platten",
    "sg:postcode":"1200",
    "sg:province":"Gen\u00e8ve",
    "wof:name":"Intramuros Sa",
    "wof:placetype":"venue"
},
  "geometry": {"coordinates":[6.142701,46.208359],"type":"Point"}
}