{
  "type": "Feature",
  "properties": {
    "iso:country":"CH",
    "sg:address":"Germanenweg 12",
    "sg:city":"Muttenz",
    "sg:classifiers":[
        {
            "category":"Social Services",
            "subcategory":"Job Training",
            "type":"Services"
        }
    ],
    "sg:phone":"+41 61 463 21 05",
    "sg:postcode":"4132",
    "sg:province":"Basel-Landschaft",
    "sg:tags":[
        "mental"
    ],
    "wof:name":"Feusi Kompass",
    "wof:placetype":"venue"
},
  "geometry": {"coordinates":[7.632499218,47.5354347229],"type":"Point"}
}