{
  "type": "Feature",
  "properties": {
    "iso:country":"CH",
    "sg:address":"Tiefletzistrasse 2",
    "sg:city":"Wangs",
    "sg:orig_category":"G\u00fcterbef\u00f6rderung im Strassenverkehr",
    "sg:phone":"+41 81 723 16 45",
    "sg:postcode":"7323",
    "sg:province":"St. Gallen",
    "wof:name":"Erwin Schnider Ag Transporte",
    "wof:placetype":"venue"
},
  "geometry": {"coordinates":[9.4428768158,47.028011322],"type":"Point"}
}