{
  "type": "Feature",
  "properties": {
    "iso:country":"CH",
    "sg:address":"Unterdorf 10",
    "sg:city":"D\u00e4ttlikon",
    "sg:classifiers":[
        {
            "category":"Professional",
            "subcategory":"Engineering",
            "type":"Services"
        }
    ],
    "sg:phone":"+41 52 315 34 62",
    "sg:postcode":"8421",
    "sg:province":"Z\u00fcrich",
    "sg:tags":[
        "electrical"
    ],
    "wof:name":"Scherer Elektronik",
    "wof:placetype":"venue"
},
  "geometry": {"coordinates":[8.623257637,47.5251350403],"type":"Point"}
}