{
  "type": "Feature",
  "properties": {
    "iso:country":"CH",
    "sg:address":"Oberer Rheinweg 23",
    "sg:city":"Basel",
    "sg:orig_category":"Flachsaufbereitung U spinnerei",
    "sg:postcode":"4058",
    "sg:province":"Basel-Stadt",
    "wof:name":"Gotama Korkut",
    "wof:placetype":"venue"
},
  "geometry": {"coordinates":[7.5919251442,47.5599517822],"type":"Point"}
}