{
  "type": "Feature",
  "properties": {
    "iso:country":"CH",
    "sg:address":"Nebengasse 11",
    "sg:city":"F\u00fcllinsdorf",
    "sg:classifiers":[
        {
            "category":"Arena",
            "subcategory":"Sports Club",
            "type":"Entertainment"
        }
    ],
    "sg:postcode":"4414",
    "sg:province":"Basel-Landschaft",
    "sg:tags":[
        "karate",
        "judo",
        "sportvereine"
    ],
    "wof:name":"Budokai Liestal",
    "wof:placetype":"venue"
},
  "geometry": {"coordinates":[7.7275528908,47.5070152283],"type":"Point"}
}