{
  "type": "Feature",
  "properties": {
    "addr:full":"Bahnhofstrasse 10 Wolhusen Luzern 6110",
    "addr:housenumber":"10",
    "addr:postcode":"6110",
    "addr:street":"Bahnhofstrasse",
    "iso:country":"CH",
    "sg:address":"Bahnhofstrasse 10",
    "sg:city":"Wolhusen",
    "sg:orig_category":"Detailhandel mit Brillen U anderen Sehhilfen Fachdetailhandel in Verkaufsr\u00e4umen",
    "sg:postcode":"6110",
    "sg:province":"Luzern",
    "wof:name":"Portmann Franz",
    "wof:placetype":"venue"
},
  "geometry": {"coordinates":[8.073652,47.058395],"type":"Point"}
}