{
  "type": "Feature",
  "properties": {
    "iso:country":"CH",
    "sg:address":"H\u00e4bernbad",
    "sg:city":"Huttwil",
    "sg:orig_category":"RESTAURANTS: TEA-ROOMS",
    "sg:postcode":"4950",
    "sg:province":"Bern",
    "wof:name":"Nova Kontrast Gmbh",
    "wof:placetype":"venue"
},
  "geometry": {"coordinates":[7.8286018372,47.1169815063],"type":"Point"}
}