{
  "type": "Feature",
  "properties": {
    "iso:country":"CH",
    "sg:address":"Gossauerstrasse 25",
    "sg:city":"Niederb\u00fcren",
    "sg:orig_category":"Primarschulen",
    "sg:phone":"+41 71 951 82 68",
    "sg:postcode":"9246",
    "sg:province":"St. Gallen",
    "wof:name":"Primarschule",
    "wof:placetype":"venue"
},
  "geometry": {"coordinates":[9.208823204,47.4644966125],"type":"Point"}
}