{
  "type": "Feature",
  "properties": {
    "iso:country":"CH",
    "sg:address":"Ebmattstrasse 25",
    "sg:city":"Bubikon",
    "sg:orig_category":"Grosshandel mit B\u00fcromaschinen Grosshandel mit Datenverarbeitungsger\u00e4ten",
    "sg:phone":"+41 55 243 27 64",
    "sg:postcode":"8608",
    "sg:province":"Z\u00fcrich",
    "wof:name":"Pegasus Informatik",
    "wof:placetype":"venue"
},
  "geometry": {"coordinates":[8.8211202621,47.2676086426],"type":"Point"}
}