{
  "type": "Feature",
  "properties": {
    "iso:country":"CH",
    "sg:address":"6354",
    "sg:city":"Vitznau",
    "sg:orig_category":"Herstellung von Ger\u00e4ten der Elektrizit\u00e4tserzeugung, -verteilung u.\u00e4. -Herstellung von elektronischen",
    "sg:phone":"+41 18024411",
    "sg:postcode":"6354",
    "sg:province":"Luzern",
    "wof:name":"Mobile Solutions Ag",
    "wof:placetype":"venue"
},
  "geometry": {"coordinates":[8.639957428,47.394618988],"type":"Point"}
}