{
  "type": "Feature",
  "properties": {
    "iso:country":"CH",
    "sg:address":"Casa Motta Via Saliciolo",
    "sg:city":"Tenero",
    "sg:orig_category":"Vermietung von Automobilen",
    "sg:phone":"+41 79 230 13 38",
    "sg:postcode":"6598",
    "sg:province":"Ticino",
    "wof:name":"Peter Bussmann Noleggio Roulottes",
    "wof:placetype":"venue"
},
  "geometry": {"coordinates":[8.8498601913,46.180896759],"type":"Point"}
}