{
  "type": "Feature",
  "properties": {
    "iso:country":"CH",
    "sg:address":"Buholzstrasse 40 6032 Emmen. Postfach",
    "sg:city":"Emmen",
    "sg:orig_category":"Verkehrsverb\u00e4nde",
    "sg:phone":"+41 41 267 11 81",
    "sg:postcode":"6032",
    "sg:province":"Luzern",
    "wof:name":"Touring Club Schweiz Tcs",
    "wof:placetype":"venue"
},
  "geometry": {"coordinates":[8.3184213638,47.092918396],"type":"Point"}
}