{
  "type": "Feature",
  "properties": {
    "iso:country":"CH",
    "sg:address":"Felsenegg 20",
    "sg:city":"W\u00fcnnewil",
    "sg:orig_category":"Herstellung von Konstruktionsteilen, Fertigbauteilen U Ausbauelementen aus Holz Innenausbau",
    "sg:postcode":"3184",
    "sg:province":"Fribourg",
    "wof:name":"Br\u00fcgger, Hans",
    "wof:placetype":"venue"
},
  "geometry": {"coordinates":[7.2798771858,46.8707771301],"type":"Point"}
}