{
  "type": "Feature",
  "properties": {
    "addr:full":"Av. De La Gare 13 Conthey Valais 1964",
    "addr:housenumber":"13",
    "addr:postcode":"1964",
    "addr:street":"Av. De La Gare",
    "iso:country":"CH",
    "sg:address":"Av. De La Gare 13",
    "sg:city":"Conthey",
    "sg:classifiers":[
        {
            "category":"Banks & Credit Unions",
            "subcategory":"Bank",
            "type":"Services"
        }
    ],
    "sg:phone":"+41 27 346 32 32",
    "sg:postcode":"1964",
    "sg:province":"Valais",
    "wof:name":"Union De Banques Suisses",
    "wof:placetype":"venue"
},
  "geometry": {"coordinates":[7.30408,46.216881],"type":"Point"}
}