{
  "type": "Feature",
  "properties": {
    "iso:country":"CH",
    "sg:address":"Neue Winterthurerstrasse 30",
    "sg:city":"Dietlikon",
    "sg:orig_category":"Herstellung von Elektrizit\u00e4tsverteilungs U schalteinrichtungen",
    "sg:phone":"+41 18333734",
    "sg:postcode":"8305",
    "sg:province":"Z\u00fcrich",
    "wof:name":"Ga Schaltanlagen Ag",
    "wof:placetype":"venue"
},
  "geometry": {"coordinates":[8.6149206161,47.4125442505],"type":"Point"}
}