{
  "type": "Feature",
  "properties": {
    "iso:country":"CH",
    "sg:address":"Bahnhofplatz 9",
    "sg:city":"Sursee",
    "sg:orig_category":"Detailhandel mit Waren verschiedener Art, Hauptrichtung Nahrungsmittel Grosshandel mit Nahrungsmitte",
    "sg:phone":"+41 41 921 24 60",
    "sg:postcode":"6210",
    "sg:province":"Luzern",
    "wof:name":"Hunkeler Margrit",
    "wof:placetype":"venue"
},
  "geometry": {"coordinates":[8.0987844467,47.1704673767],"type":"Point"}
}