{
  "type": "Feature",
  "properties": {
    "iso:country":"CH",
    "sg:address":"Feldmattstrasse 13",
    "sg:city":"Emmen",
    "sg:orig_category":"Grosshandel mit Eisenwaren sowie Installationsbedarf f\u00fcr Gas, Wasser U Heizung Sanit\u00e4r, Heizungs U L",
    "sg:phone":"+41 41 369 29 29",
    "sg:postcode":"6032",
    "sg:province":"Luzern",
    "wof:name":"Sanit\u00e4r Material Ag B\u00e4der & K\u00fcchenausstellung",
    "wof:placetype":"venue"
},
  "geometry": {"coordinates":[8.3246116638,47.1083908081],"type":"Point"}
}