{
  "type": "Feature",
  "properties": {
    "iso:country":"CH",
    "sg:address":"Hauptstrasse 6",
    "sg:city":"Plaffeien",
    "sg:orig_category":"Detailhandel mit Brot, Back U S\u00fcsswaren",
    "sg:phone":"+41 26 419 11 22",
    "sg:postcode":"1716",
    "sg:province":"Fribourg",
    "wof:name":"B\u00e4ckerei Fontana Ag",
    "wof:placetype":"venue"
},
  "geometry": {"coordinates":[7.287295,46.742123],"type":"Point"}
}