{
  "type": "Feature",
  "properties": {
    "iso:country":"CH",
    "sg:address":"Faubourg De La Gare 16",
    "sg:city":"Bevaix",
    "sg:orig_category":"Softwareentwicklung U beratung",
    "sg:phone":"+41 22 343 14 24",
    "sg:postcode":"2022",
    "sg:province":"Neuch\u00e2tel",
    "wof:name":"Bel Maxime, Micro-informatique",
    "wof:placetype":"venue"
},
  "geometry": {"coordinates":[6.1414251328,46.1833114624],"type":"Point"}
}