{
  "type": "Feature",
  "properties": {
    "iso:country":"CH",
    "sg:address":"Hertensteinstrasse 42",
    "sg:city":"Luzern",
    "sg:orig_category":"Grosshandel mit sonstigen Gebrauchs U Verbrauchsg\u00fctern Sonstiger Fachdetailhandel in Verkaufsr\u00e4umen",
    "sg:phone":"+41 41 410 11 49",
    "sg:postcode":"6004",
    "sg:province":"Luzern",
    "wof:name":"Stampfli Fritz",
    "wof:placetype":"venue"
},
  "geometry": {"coordinates":[8.308218956,47.0542678833],"type":"Point"}
}