{
  "type": "Feature",
  "properties": {
    "iso:country":"CH",
    "sg:address":"Rue Voltaire 23",
    "sg:city":"Gen\u00e8ve",
    "sg:orig_category":"Detailhandel mit Brot, Back U S\u00fcsswaren",
    "sg:phone":"+41 22 344 75 44",
    "sg:postcode":"1201",
    "sg:province":"Gen\u00e8ve",
    "wof:name":"Faoro G.",
    "wof:placetype":"venue"
},
  "geometry": {"coordinates":[6.135808,46.20808],"type":"Point"}
}