{
  "type": "Feature",
  "properties": {
    "iso:country":"CH",
    "sg:address":"Crans-sur-sierre 3963 Crans-sur-sierre. Postfach",
    "sg:city":"Crans-sur-sierre",
    "sg:orig_category":"Herstellung von k\u00e4lte U lufttechnischen Erzeugnissen f\u00fcr gewerbliche Zwecke",
    "sg:phone":"+41 27 483 41 43",
    "sg:postcode":"3963",
    "sg:province":"Valais",
    "wof:name":"Emery Roger",
    "wof:placetype":"venue"
},
  "geometry": {"coordinates":[7.4787511826,46.3118667603],"type":"Point"}
}