{
  "type": "Feature",
  "properties": {
    "iso:country":"CH",
    "sg:address":"Seehofstrasse 9b",
    "sg:city":"Cham",
    "sg:orig_category":"Sonstige Aktivit\u00e4ten der nicht-\u00e4rztlichen Medizinalberufe",
    "sg:phone":"+41 41 780 03 40",
    "sg:postcode":"6330",
    "sg:province":"Zug",
    "wof:name":"Susanne Darphin Atemschulung",
    "wof:placetype":"venue"
},
  "geometry": {"coordinates":[8.461566925,47.1806793213],"type":"Point"}
}