{
  "type": "Feature",
  "properties": {
    "iso:country":"CH",
    "sg:address":"Turnerstrasse 1 8400 Winterthur. Postfach 290",
    "sg:city":"Winterthur",
    "sg:orig_category":"Handelsvermittlung",
    "sg:phone":"+41 52 343 69 70",
    "sg:postcode":"8401",
    "sg:province":"Z\u00fcrich",
    "wof:name":"Achermann Moderationsmaterial Grethe Achermann",
    "wof:placetype":"venue"
},
  "geometry": {"coordinates":[8.6994380951,47.455242157],"type":"Point"}
}