{
  "type": "Feature",
  "properties": {
    "iso:country":"CH",
    "sg:address":"Carouge Rue De 110",
    "sg:city":"Gen\u00e8ve",
    "sg:orig_category":"Detailhandel mit Bekleidung",
    "sg:postcode":"1205",
    "sg:province":"Gen\u00e8ve",
    "wof:name":"Wagner A. Et Ph.",
    "wof:placetype":"venue"
},
  "geometry": {"coordinates":[6.143034,46.189373],"type":"Point"}
}