{
  "type": "Feature",
  "properties": {
    "iso:country":"CH",
    "sg:address":"Ottenhusen",
    "sg:city":"Ballwil",
    "sg:orig_category":"Maschinen and Apparate divers Grosshandel Unternehmensberatung",
    "sg:postcode":"6275",
    "sg:province":"Luzern",
    "wof:name":"Zdt Gmbh Druckmaschinentechnik",
    "wof:placetype":"venue"
},
  "geometry": {"coordinates":[7.3577327728,46.9114761353],"type":"Point"}
}