{
  "type": "Feature",
  "properties": {
    "iso:country":"CH",
    "sg:address":"Mettlenbachstrasse 23",
    "sg:city":"M\u00f6nchaltorf",
    "sg:orig_category":"Dienstleistungen von Beteiligungsgesellschaften",
    "sg:phone":"+41 14930817",
    "sg:postcode":"8617",
    "sg:province":"Z\u00fcrich",
    "wof:name":"Merz Informatik Ag",
    "wof:placetype":"venue"
},
  "geometry": {"coordinates":[8.7222070694,47.304145813],"type":"Point"}
}