{
  "type": "Feature",
  "properties": {
    "iso:country":"CH",
    "sg:address":"Poststrasse 24",
    "sg:city":"Zug",
    "sg:orig_category":"Rechtsberatung",
    "sg:phone":"+41 41 710 16 77",
    "sg:postcode":"6300",
    "sg:province":"Zug",
    "wof:name":"Bexytol Ag",
    "wof:placetype":"venue"
},
  "geometry": {"coordinates":[8.5169010162,47.1708526611],"type":"Point"}
}