{
  "type": "Feature",
  "properties": {
    "iso:country":"CH",
    "sg:address":"Halden 40",
    "sg:city":"Aarau",
    "sg:orig_category":"Detailhandel mit Getr\u00e4nken Detailhandel mit Waren verschiedener Art, Hauptrichtung Nahrungsmittel",
    "sg:phone":"+41 62 823 25 55",
    "sg:postcode":"5000",
    "sg:province":"Aargau",
    "wof:name":"Paolo Lisandrelli Il Tartufo",
    "wof:placetype":"venue"
},
  "geometry": {"coordinates":[8.042134285,47.3928451538],"type":"Point"}
}