{
  "type": "Feature",
  "properties": {
    "iso:country":"CH",
    "sg:address":"Via Cagvils 12",
    "sg:city":"Domat/ems",
    "sg:orig_category":"Detailhandel mit Waren verschiedener Art, Hauptrichtung Nahrungsmittel Sonstiger Grosshandel",
    "sg:phone":"+41 81 353 59 19",
    "sg:postcode":"7013",
    "sg:province":"Graubunden",
    "wof:name":"Lagrischa Sa",
    "wof:placetype":"venue"
},
  "geometry": {"coordinates":[9.8358030319,46.4887466431],"type":"Point"}
}