{
  "type": "Feature",
  "properties": {
    "iso:country":"CH",
    "sg:address":"Aathalstrasse 10",
    "sg:city":"Uster",
    "sg:orig_category":"Detailhandel mit elektrischen Haushalts-,Radio U Fernsehger\u00e4ten sowie Musikinstrumenten",
    "sg:phone":"+41 79 631 90 74",
    "sg:postcode":"8610",
    "sg:province":"Z\u00fcrich",
    "wof:name":"Guitar Pleasure, Daniele Radicci",
    "wof:placetype":"venue"
},
  "geometry": {"coordinates":[8.7394170761,47.345790863],"type":"Point"}
}