{
  "type": "Feature",
  "properties": {
    "iso:country":"CH",
    "sg:address":"Chemin Claude Mandrot",
    "sg:city":"Morges",
    "sg:orig_category":"Bestattungswesen",
    "sg:phone":"+41 21 802 11 14",
    "sg:postcode":"1110",
    "sg:province":"Vaud",
    "wof:name":"Pompes Fun\u00e8bres Alpha Corinne Chevalier",
    "wof:placetype":"venue"
},
  "geometry": {"coordinates":[6.509796,46.518127],"type":"Point"}
}