{
  "type": "Feature",
  "properties": {
    "iso:country":"CH",
    "sg:address":"Spitalstrasse 20",
    "sg:city":"Breitenbach",
    "sg:orig_category":"Sportvereine Sch\u00fctzen",
    "sg:phone":"+41 61 781 15 78",
    "sg:postcode":"4226",
    "sg:province":"Solothurn",
    "wof:name":"Sch\u00fctzenges.breitenbach",
    "wof:placetype":"venue"
},
  "geometry": {"coordinates":[7.5498628616,47.4113922119],"type":"Point"}
}