{
  "type": "Feature",
  "properties": {
    "iso:country":"CH",
    "sg:address":"Roseli\u00e8re Rue De La 11",
    "sg:city":"Yverdon-les-bains",
    "sg:orig_category":"Softwareentwicklung U beratung",
    "sg:phone":"+41 24 426 25 18",
    "sg:postcode":"1400",
    "sg:province":"Vaud",
    "wof:name":"Quart\u00e9 Software, Lehmann, Mottaz Et Mottaz",
    "wof:placetype":"venue"
},
  "geometry": {"coordinates":[6.6387209892,46.787776947],"type":"Point"}
}