{
  "type": "Feature",
  "properties": {
    "iso:country":"CH",
    "sg:address":"Hauptstrasse 16b",
    "sg:city":"Weesen",
    "sg:orig_category":"Vermietung von Gebrauchsg\u00fctern Vermietung von Wasserfahrzeugen",
    "sg:phone":"+41 79 212 12 73",
    "sg:postcode":"8872",
    "sg:province":"St. Gallen",
    "wof:name":"Raymond Tsch\u00e4pp\u00e4t Location De Bateaux",
    "wof:placetype":"venue"
},
  "geometry": {"coordinates":[6.5979299545,46.5172386169],"type":"Point"}
}