{
  "type": "Feature",
  "properties": {
    "iso:country":"CH",
    "sg:address":"Haldenweg 8 F",
    "sg:city":"Lyss",
    "sg:orig_category":"Softwareentwicklung U beratung",
    "sg:postcode":"3250",
    "sg:province":"Bern",
    "wof:name":"Heiz-cad",
    "wof:placetype":"venue"
},
  "geometry": {"coordinates":[7.3079900742,47.0719146729],"type":"Point"}
}