{
  "type": "Feature",
  "properties": {
    "iso:country":"CH",
    "sg:address":"1948 Lourtier. Postfach",
    "sg:city":"Lourtier",
    "sg:classifiers":[
        {
            "category":"Travel",
            "subcategory":"Hotels & Motels",
            "type":"Entertainment"
        }
    ],
    "sg:postcode":"1948",
    "sg:province":"Valais",
    "sg:tags":[
        "hotels",
        "mit",
        "restaurant"
    ],
    "wof:name":"Pellissier Jean-marc",
    "wof:placetype":"venue"
},
  "geometry": {"coordinates":[7.3359398842,46.0026512146],"type":"Point"}
}