{
  "type": "Feature",
  "properties": {
    "iso:country":"CH",
    "sg:address":"Kantonsstrasse 2",
    "sg:city":"Igis",
    "sg:orig_category":"Hoch U Tiefbau",
    "sg:phone":"+41 81 322 62 76",
    "sg:postcode":"7206",
    "sg:province":"Graubunden",
    "wof:name":"Robert Tomaselli Renovationen",
    "wof:placetype":"venue"
},
  "geometry": {"coordinates":[9.5688734055,46.9442672729],"type":"Point"}
}