{
  "type": "Feature",
  "properties": {
    "iso:country":"CH",
    "sg:address":"Chemin Du Bois L",
    "sg:city":"Cortaillod",
    "sg:orig_category":"Grosshandel mit Geschenkartikeln U Souvenirs Grosshandel mit sonstigen Gebrauchs U Verbrauchsg\u00fctern",
    "sg:phone":"+41 32 842 28 70",
    "sg:postcode":"2016",
    "sg:province":"Neuch\u00e2tel",
    "wof:name":"Zoll Beat, Icp.",
    "wof:placetype":"venue"
},
  "geometry": {"coordinates":[6.8476080894,46.9500350952],"type":"Point"}
}