{
  "type": "Feature",
  "properties": {
    "iso:country":"CH",
    "sg:address":"Reitweg 2",
    "sg:city":"Winterthur",
    "sg:orig_category":"Dachdeckerei Kaminfeger",
    "sg:phone":"+41 52 383 14 19",
    "sg:postcode":"8400",
    "sg:province":"Z\u00fcrich",
    "wof:name":"K\u00fcnzli Bedachungen & Kaminfeger Gmbh",
    "wof:placetype":"venue"
},
  "geometry": {"coordinates":[8.82248,47.445675],"type":"Point"}
}