{
  "type": "Feature",
  "properties": {
    "iso:country":"CH",
    "sg:address":"Rue De Fer 11 2800 Delsberg. Postfach",
    "sg:city":"Del\u00e9mont",
    "sg:orig_category":"Wirtschaftspr\u00fcfung, Steuerberatung U Treuhand",
    "sg:postcode":"2800",
    "sg:province":"Jura",
    "wof:name":"G\u00e9fidec, J.-f. Eckert Sa",
    "wof:placetype":"venue"
},
  "geometry": {"coordinates":[7.3427791595,47.3655128479],"type":"Point"}
}