{
  "type": "Feature",
  "properties": {
    "iso:country":"CH",
    "sg:address":"Via Sirana",
    "sg:city":"Lamone",
    "sg:classifiers":[
        {
            "category":"Banks & Credit Unions",
            "subcategory":"Bank",
            "type":"Services"
        }
    ],
    "sg:phone":"+41 91 967 23 04",
    "sg:postcode":"6814",
    "sg:province":"Ticino",
    "wof:name":"Raiffeisen Di Lamone-cadempino",
    "wof:placetype":"venue"
},
  "geometry": {"coordinates":[8.933551,46.042171],"type":"Point"}
}