{
  "type": "Feature",
  "properties": {
    "iso:country":"CH",
    "sg:address":"Zimmerlistrasse 23",
    "sg:city":"Aarburg",
    "sg:orig_category":"Mechanik Schlossereien",
    "sg:phone":"+41 62 791 32 81",
    "sg:postcode":"4663",
    "sg:province":"Aargau",
    "wof:name":"H. Hostettler, Schlosserei",
    "wof:placetype":"venue"
},
  "geometry": {"coordinates":[7.9075140953,47.3173332214],"type":"Point"}
}