{
  "type": "Feature",
  "properties": {
    "iso:country":"CH",
    "sg:address":"Wesemlinstrasse 30",
    "sg:city":"Luzern",
    "sg:classifiers":[
        {
            "category":"Professional",
            "subcategory":"Employment Agencies",
            "type":"Services"
        }
    ],
    "sg:phone":"+41 71 911 73 23",
    "sg:postcode":"6006",
    "sg:province":"Luzern",
    "sg:tags":[
        "personal",
        "u",
        "stellenvermittlung"
    ],
    "wof:name":"Anima Personal Gmbh",
    "wof:placetype":"venue"
},
  "geometry": {"coordinates":[9.0492916107,47.4701728821],"type":"Point"}
}