{
  "type": "Feature",
  "properties": {
    "addr:full":"Botyre Ayent Valais 1966",
    "addr:housenumber":"1966",
    "iso:country":"CH",
    "sg:address":"Botyre",
    "sg:city":"Ayent",
    "sg:orig_category":"Advokaturb\u00fcros Notariate",
    "sg:phone":"+41 27 398 19 17",
    "sg:postcode":"1966",
    "sg:province":"Valais",
    "wof:name":"Nicolas Fardel Etude D'avocat & Notaire",
    "wof:placetype":"venue"
},
  "geometry": {"coordinates":[7.40682,46.276779],"type":"Point"}
}