{
  "type": "Feature",
  "properties": {
    "iso:country":"CH",
    "sg:address":"M\u00fclibach 574",
    "sg:city":"Wilchingen",
    "sg:orig_category":"Elektroinstallation",
    "sg:phone":"+41 31 337 52 52",
    "sg:postcode":"8217",
    "sg:province":"Schaffhausen",
    "wof:name":"Bering Ag Beratender Ingenieur - Elektroplanungen",
    "wof:placetype":"venue"
},
  "geometry": {"coordinates":[7.4600667953,46.9540596008],"type":"Point"}
}