{
  "type": "Feature",
  "properties": {
    "iso:country":"CH",
    "sg:address":"3375",
    "sg:city":"Inkwil",
    "sg:orig_category":"Schulpflegen",
    "sg:phone":"+41 62 961 76 13",
    "sg:postcode":"3375",
    "sg:province":"Bern",
    "wof:name":"Primarschulkommission Der Gemeinde Inkwil",
    "wof:placetype":"venue"
},
  "geometry": {"coordinates":[7.6651501656,47.2018013],"type":"Point"}
}