{
  "type": "Feature",
  "properties": {
    "iso:country":"CH",
    "sg:address":"Hauptstrasse 183",
    "sg:city":"Escholzmatt",
    "sg:orig_category":"Autogaragen",
    "sg:phone":"+41 33 676 10 22",
    "sg:postcode":"6182",
    "sg:province":"Luzern",
    "wof:name":"Beat Schmid Autogarage",
    "wof:placetype":"venue"
},
  "geometry": {"coordinates":[7.663501,46.607971],"type":"Point"}
}