{
  "type": "Feature",
  "properties": {
    "iso:country":"CH",
    "sg:address":"Vuillonnex Chemin De 42 1232 Confignon Case Postale",
    "sg:city":"Confignon",
    "sg:orig_category":"Wirtschaftspr\u00fcfung, Steuerberatung U Treuhand",
    "sg:phone":"+41 22 850 08 88",
    "sg:postcode":"1232",
    "sg:province":"Gen\u00e8ve",
    "wof:name":"Fdl Fiduciaire Du L\u00e9man Sa",
    "wof:placetype":"venue"
},
  "geometry": {"coordinates":[6.0801157951,46.1736373901],"type":"Point"}
}