{
  "type": "Feature",
  "properties": {
    "iso:country":"CH",
    "sg:address":"Reuschenstrasse 3",
    "sg:city":"Scherzingen",
    "sg:orig_category":"Detektivb\u00fcros U \u00dcberwachung",
    "sg:phone":"+41 71 680 08 50",
    "sg:postcode":"8596",
    "sg:province":"Thurgau",
    "wof:name":"Texet Gmbh",
    "wof:placetype":"venue"
},
  "geometry": {"coordinates":[9.2272396088,47.6300392151],"type":"Point"}
}