{
  "type": "Feature",
  "properties": {
    "iso:country":"CH",
    "sg:address":"Thunstrasse 26",
    "sg:city":"M\u00fcnsingen",
    "sg:orig_category":"RESTAURANTS: TEA-ROOMS",
    "sg:postcode":"3110",
    "sg:province":"Bern",
    "wof:name":"Rieder Alain",
    "wof:placetype":"venue"
},
  "geometry": {"coordinates":[6.93791008,46.6277694702],"type":"Point"}
}