{
  "type": "Feature",
  "properties": {
    "iso:country":"CH",
    "sg:address":"Hirschmattstrasse 56",
    "sg:city":"Luzern",
    "sg:orig_category":"Fussreflexzonenmassage",
    "sg:phone":"+41 19108744",
    "sg:postcode":"6003",
    "sg:province":"Luzern",
    "wof:name":"Margrit Werwinski Massagen",
    "wof:placetype":"venue"
},
  "geometry": {"coordinates":[8.5926885605,47.3068733215],"type":"Point"}
}