{
  "type": "Feature",
  "properties": {
    "iso:country":"CH",
    "sg:address":"Seidenweg 26 3012 Bern. Postfach",
    "sg:city":"Bern",
    "sg:orig_category":"Grosshandel mit lebenden Tieren",
    "sg:phone":"+41 91 827 18 58",
    "sg:postcode":"3005",
    "sg:province":"Bern",
    "wof:name":"Luigi Savoldelli Industria Vitelli & Conigli",
    "wof:placetype":"venue"
},
  "geometry": {"coordinates":[9.1073904037,46.2385597229],"type":"Point"}
}