{
  "type": "Feature",
  "properties": {
    "iso:country":"CH",
    "sg:address":"Dornwydenweg 2",
    "sg:city":"Arlesheim",
    "sg:orig_category":"Einbau von Schreinerwaren Herstellung von elektrischen Haushaltsger\u00e4ten",
    "sg:phone":"+41 61 706 96 86",
    "sg:postcode":"4144",
    "sg:province":"Basel-Landschaft",
    "wof:name":"Jeka Ag Ladeneinrichtungen + K\u00fchlm\u00f6belbau",
    "wof:placetype":"venue"
},
  "geometry": {"coordinates":[7.6084179878,47.4964942932],"type":"Point"}
}