{
  "type": "Feature",
  "properties": {
    "iso:country":"CH",
    "sg:address":"Hauptstr. 33 4417 Ziefen. Postfach",
    "sg:city":"Ziefen",
    "sg:orig_category":"Instandhaltung U Reparatur von Automobilen",
    "sg:phone":"+41 61 931 22 68",
    "sg:postcode":"4417",
    "sg:province":"Basel-Landschaft",
    "wof:name":"Gisin A., Garage",
    "wof:placetype":"venue"
},
  "geometry": {"coordinates":[7.7153520584,47.4333381653],"type":"Point"}
}