{
  "type": "Feature",
  "properties": {
    "iso:country":"CH",
    "sg:address":"Rue Du Grand-faubourg 1147 Montricher. Postfach",
    "sg:city":"Montricher",
    "sg:orig_category":"Forstwirtschaft ohne Dienstleistungen in der Forstwirtschaft",
    "sg:postcode":"1147",
    "sg:province":"Vaud",
    "wof:name":"Exploitation Foresti\u00e8re Failletaz Alain",
    "wof:placetype":"venue"
},
  "geometry": {"coordinates":[6.3787097931,46.6028137207],"type":"Point"}
}