{
  "type": "Feature",
  "properties": {
    "iso:country":"CH",
    "sg:address":"Hauptstrasse 247/253",
    "sg:city":"Magglingen/macolin",
    "sg:orig_category":"Sportvereine Ballsport Volleyball",
    "sg:phone":"+41 32 327 61 11",
    "sg:postcode":"2532",
    "sg:province":"Bern",
    "wof:name":"Volleyball-club Efgs Maggling. G.hefti C/o Eidg.sportschule",
    "wof:placetype":"venue"
},
  "geometry": {"coordinates":[7.2136301994,47.1387481689],"type":"Point"}
}