{
  "type": "Feature",
  "properties": {
    "iso:country":"CH",
    "sg:address":"Riehenstrasse 3",
    "sg:city":"Birsfelden",
    "sg:orig_category":"Vereine Haus- and Grundeigent\u00fcmer",
    "sg:postcode":"4127",
    "sg:province":"Basel-Landschaft",
    "wof:name":"Hans-& Grundeigent\u00fcmerverein",
    "wof:placetype":"venue"
},
  "geometry": {"coordinates":[7.6248078346,47.5565719604],"type":"Point"}
}