{
  "type": "Feature",
  "properties": {
    "addr:full":"Route Des Combes Grimisuat Valais 1971",
    "addr:postcode":"1971",
    "addr:street":"Route Des Combes",
    "iso:country":"CH",
    "sg:address":"Route Des Combes",
    "sg:city":"Grimisuat",
    "sg:orig_category":"Arztpraxen",
    "sg:phone":"+41 32 967 96 43",
    "sg:postcode":"1971",
    "sg:province":"Valais",
    "wof:name":"Dr M\u00e9d. Mauro Walter Gusmini M\u00e9decin G\u00e9n\u00e9raliste",
    "wof:placetype":"venue"
},
  "geometry": {"coordinates":[6.830084,47.103977],"type":"Point"}
}