{
  "type": "Feature",
  "properties": {
    "iso:country":"CH",
    "sg:address":"Boden",
    "sg:city":"Sigriswil",
    "sg:orig_category":"Abbruch U Sprenggewerbe, Erdbewegungsarbeiten Erdbewegungsarbeiten",
    "sg:phone":"+41 33 251 24 06",
    "sg:postcode":"3655",
    "sg:province":"Bern",
    "wof:name":"Tschanz P.",
    "wof:placetype":"venue"
},
  "geometry": {"coordinates":[7.731509,46.72303],"type":"Point"}
}