{
  "type": "Feature",
  "properties": {
    "iso:country":"CH",
    "sg:address":"Melchr\u00fctistrasse 28 8304 Wallisellen. Postfach",
    "sg:city":"Wallisellen",
    "sg:orig_category":"Grosshandel mit Holz U Baustoffen",
    "sg:postcode":"8304",
    "sg:province":"Z\u00fcrich",
    "wof:name":"P.u.r. Platten, Umbauten, Renovationen Gmbh",
    "wof:placetype":"venue"
},
  "geometry": {"coordinates":[8.5805015564,47.4183082581],"type":"Point"}
}