{
  "type": "Feature",
  "properties": {
    "iso:country":"CH",
    "sg:address":"R\u00f6nnimoosrain 4",
    "sg:city":"Littau",
    "sg:orig_category":"Dienstleistungen von Beteiligungsgesellschaften Unternehmensberatung",
    "sg:phone":"+41 22 737 03 00",
    "sg:postcode":"6014",
    "sg:province":"Luzern",
    "wof:name":"V.ships Switzerland Sa",
    "wof:placetype":"venue"
},
  "geometry": {"coordinates":[6.142701149,46.2083587646],"type":"Point"}
}