{
  "type": "Feature",
  "properties": {
    "iso:country":"CH",
    "sg:address":"Rte De Mont-fleury 70",
    "sg:city":"Satigny",
    "sg:orig_category":"Mechanik",
    "sg:postcode":"1242",
    "sg:province":"Gen\u00e8ve",
    "wof:name":"Toledano S.",
    "wof:placetype":"venue"
},
  "geometry": {"coordinates":[6.0684399605,46.2167396545],"type":"Point"}
}