{
  "type": "Feature",
  "properties": {
    "iso:country":"CH",
    "sg:address":"3784",
    "sg:city":"Feutersoey",
    "sg:classifiers":[
        {
            "category":"Government",
            "subcategory":"Post Office",
            "type":"Public Place"
        }
    ],
    "sg:phone":"+41 33 755 10 14",
    "sg:postcode":"3784",
    "sg:province":"Bern",
    "sg:tags":[
        "die",
        "poststellen"
    ],
    "wof:name":"Die Post",
    "wof:placetype":"venue"
},
  "geometry": {"coordinates":[7.271299839,46.4163208008],"type":"Point"}
}