{
  "type": "Feature",
  "properties": {
    "iso:country":"CH",
    "sg:address":"Badhaus 110",
    "sg:city":"Heimenschwand",
    "sg:orig_category":"Architektur U Ingenieurb\u00fcros Informatikdienste",
    "sg:phone":"+41 33 453 03 10",
    "sg:postcode":"3615",
    "sg:province":"Bern",
    "wof:name":"Beg Bau Und Edv Gmbh",
    "wof:placetype":"venue"
},
  "geometry": {"coordinates":[7.696945,46.828621],"type":"Point"}
}