{
  "type": "Feature",
  "properties": {
    "iso:country":"CH",
    "sg:address":"Rive Cours De 18 1207 Gen\u00e8ve. Postfach",
    "sg:city":"Gen\u00e8ve",
    "sg:orig_category":"RESTAURANTS: TEA-ROOMS",
    "sg:phone":"+41 21357450",
    "sg:postcode":"1201",
    "sg:province":"Gen\u00e8ve",
    "wof:name":"Martinez Martin",
    "wof:placetype":"venue"
},
  "geometry": {"coordinates":[6.5808749199,46.5352745056],"type":"Point"}
}