{
  "type": "Feature",
  "properties": {
    "iso:country":"CH",
    "sg:address":"Riveo",
    "sg:city":"Someo",
    "sg:orig_category":"Non-Classified Establishments",
    "sg:postcode":"6674",
    "sg:province":"Ticino",
    "wof:name":"Camanini Sergio",
    "wof:placetype":"venue"
},
  "geometry": {"coordinates":[8.6663808823,46.2863388062],"type":"Point"}
}