{
  "type": "Feature",
  "properties": {
    "iso:country":"CH",
    "sg:address":"Hauptstrasse 66",
    "sg:city":"Ettingen",
    "sg:orig_category":"Non-Classified Establishments",
    "sg:postcode":"4107",
    "sg:province":"Basel-Landschaft",
    "wof:name":"A Centre Th. Ramel",
    "wof:placetype":"venue"
},
  "geometry": {"coordinates":[7.5430150032,47.4786453247],"type":"Point"}
}