{
  "type": "Feature",
  "properties": {
    "iso:country":"CH",
    "sg:address":"Rue Du 31-d\u00e9cembre 16",
    "sg:city":"Gen\u00e8ve",
    "sg:orig_category":"P\u00e9dicure",
    "sg:phone":"+41 22 735 44 93",
    "sg:postcode":"1207",
    "sg:province":"Gen\u00e8ve",
    "wof:name":"Ir\u00e8ne Den Toom P\u00e9dicure",
    "wof:placetype":"venue"
},
  "geometry": {"coordinates":[6.1588521004,46.204158783],"type":"Point"}
}