{
  "type": "Feature",
  "properties": {
    "iso:country":"CH",
    "sg:address":"P\u00fcntenstrasse 16",
    "sg:city":"Winkel",
    "sg:orig_category":"Sanit\u00e4r U Heizungsinstallation Sanit\u00e4rinstallation",
    "sg:phone":"+41 18605140",
    "sg:postcode":"8185",
    "sg:province":"Z\u00fcrich",
    "wof:name":"B\u00fcnter & Schellenberg Ag Sanit\u00e4re Anlagen & Heizungen",
    "wof:placetype":"venue"
},
  "geometry": {"coordinates":[8.5648002625,47.4811286926],"type":"Point"}
}