{
  "type": "Feature",
  "properties": {
    "iso:country":"CH",
    "sg:address":"6442",
    "sg:city":"Gersau",
    "sg:classifiers":[
        {
            "category":"Travel",
            "subcategory":"Hotels & Motels",
            "type":"Entertainment"
        }
    ],
    "sg:phone":"+41 41 828 14 75",
    "sg:postcode":"6442",
    "sg:province":"Schwyz",
    "sg:tags":[
        "hotels",
        "mit",
        "restaurant"
    ],
    "wof:name":"Berggasthaus Rigi-scheidegg",
    "wof:placetype":"venue"
},
  "geometry": {"coordinates":[8.5251512527,46.9907875061],"type":"Point"}
}