{
  "type": "Feature",
  "properties": {
    "iso:country":"CH",
    "sg:address":"Obergasse 7 8854 Galgenen. Postfach 7781",
    "sg:city":"Galgenen",
    "sg:orig_category":"Grosshandel mit B\u00fcromaschinen Grosshandel mit Geschenkartikeln U Souvenirs",
    "sg:phone":"+41 55 450 50 30",
    "sg:postcode":"8854",
    "sg:province":"Schwyz",
    "wof:name":"Penta Vertriebs Ag",
    "wof:placetype":"venue"
},
  "geometry": {"coordinates":[8.8736991882,47.1772918701],"type":"Point"}
}