{
  "type": "Feature",
  "properties": {
    "iso:country":"CH",
    "sg:address":"6912 Pazzallo. Postfach",
    "sg:city":"Pazzallo",
    "sg:orig_category":"Herstellung von Pumpen U Kompressoren",
    "sg:postcode":"6912",
    "sg:province":"Ticino",
    "wof:name":"R.t. Impianti Sagl",
    "wof:placetype":"venue"
},
  "geometry": {"coordinates":[8.9498701096,45.980381012],"type":"Point"}
}