{
  "type": "Feature",
  "properties": {
    "iso:country":"CH",
    "sg:address":"Ch\u00eanes Chemin Des 17",
    "sg:city":"St-blaise",
    "sg:orig_category":"Schlachth\u00e4user",
    "sg:postcode":"2072",
    "sg:province":"Neuch\u00e2tel",
    "wof:name":"Volailles De Ferme Vfm Sa",
    "wof:placetype":"venue"
},
  "geometry": {"coordinates":[6.9901638031,47.0149078369],"type":"Point"}
}