{
  "type": "Feature",
  "properties": {
    "iso:country":"CH",
    "sg:address":"Al Giardino",
    "sg:city":"Vergeletto",
    "sg:orig_category":"Elektrizit\u00e4tsversorgung",
    "sg:phone":"+41 91 780 60 00",
    "sg:postcode":"6664",
    "sg:province":"Ticino",
    "wof:name":"Hydroelektra Sa Impianto Idroelettrico",
    "wof:placetype":"venue"
},
  "geometry": {"coordinates":[8.6004047394,46.2272758484],"type":"Point"}
}