{
  "type": "Feature",
  "properties": {
    "addr:full":"Lachenmatte Ufhusen Luzern 6153",
    "addr:postcode":"6153",
    "iso:country":"CH",
    "sg:address":"Lachenmatte",
    "sg:city":"Ufhusen",
    "sg:classifiers":[
        {
            "category":"Banks & Credit Unions",
            "subcategory":"Bank",
            "type":"Services"
        }
    ],
    "sg:phone":"+41 4145881933",
    "sg:postcode":"6153",
    "sg:province":"Luzern",
    "wof:name":"Schweiz. Mobiliar",
    "wof:placetype":"venue"
},
  "geometry": {"coordinates":[7.893843,47.117233],"type":"Point"}
}