{
  "type": "Feature",
  "properties": {
    "iso:country":"CH",
    "sg:address":"H\u00f4tel Du Parc",
    "sg:city":"Champ\u00e9ry",
    "sg:orig_category":"Grosshandel mit Sportartikeln",
    "sg:phone":"+41 24 479 13 13",
    "sg:postcode":"1874",
    "sg:province":"Valais",
    "wof:name":"Wax Boy International",
    "wof:placetype":"venue"
},
  "geometry": {"coordinates":[6.8706860542,46.1794052124],"type":"Point"}
}