{
  "type": "Feature",
  "properties": {
    "iso:country":"CH",
    "sg:address":"Rue De La B\u00e2tiaz 1 1920 Martigny. Postfach",
    "sg:city":"Martigny",
    "sg:orig_category":"Herstellung von Akkumulatoren U Batterien",
    "sg:postcode":"1920",
    "sg:province":"Valais",
    "wof:name":"Giovanola Pierre-yves",
    "wof:placetype":"venue"
},
  "geometry": {"coordinates":[7.0620651245,46.109588623],"type":"Point"}
}