{
  "type": "Feature",
  "properties": {
    "iso:country":"CH",
    "sg:address":"R\u00fcmelinbachweg 6 4054 Basel. Postfach",
    "sg:city":"Basel",
    "sg:orig_category":"Detailhandel mit Beleuchtungs U Haushaltsgegenst\u00e4nden Detailhandel mit Radio U Fernsehger\u00e4ten",
    "sg:phone":"+41 61 281 31 00",
    "sg:postcode":"4002",
    "sg:province":"Basel-Stadt",
    "wof:name":"Eschenmoser Ag Discounthaus Tv-hifi Foto-computer-cd-shop",
    "wof:placetype":"venue"
},
  "geometry": {"coordinates":[7.585216,47.55154],"type":"Point"}
}