{
  "type": "Feature",
  "properties": {
    "iso:country":"CH",
    "sg:address":"Plaz Grond",
    "sg:city":"M\u00fcstair",
    "sg:classifiers":[
        {
            "category":"Travel",
            "subcategory":"Hotels & Motels",
            "type":"Entertainment"
        }
    ],
    "sg:phone":"+41 81 858 54 01",
    "sg:postcode":"7537",
    "sg:province":"Graubunden",
    "sg:tags":[
        "hotels",
        "mit",
        "restaurant"
    ],
    "wof:name":"Hotel Chasa Chalavaina",
    "wof:placetype":"venue"
},
  "geometry": {"coordinates":[10.4475326538,46.6291351318],"type":"Point"}
}