{
  "type": "Feature",
  "properties": {
    "iso:country":"CH",
    "sg:address":"Via Cantonale 6573 Magadino. Postfach",
    "sg:city":"Magadino",
    "sg:orig_category":"RESTAURANTS: TEA-ROOMS",
    "sg:postcode":"6573",
    "sg:province":"Ticino",
    "wof:name":"Rivanina Antonio",
    "wof:placetype":"venue"
},
  "geometry": {"coordinates":[8.8608789444,46.1484909058],"type":"Point"}
}