{
  "type": "Feature",
  "properties": {
    "iso:country":"CH",
    "sg:address":"4937",
    "sg:city":"Ursenbach",
    "sg:orig_category":"Wasserversorgung",
    "sg:postcode":"4937",
    "sg:province":"Bern",
    "wof:name":"Wasserversorgungsgenossenschaft Ursenbach",
    "wof:placetype":"venue"
},
  "geometry": {"coordinates":[7.7725977898,47.1367874146],"type":"Point"}
}