{
  "type": "Feature",
  "properties": {
    "iso:country":"CH",
    "sg:address":"6772",
    "sg:city":"Rodi-fiesso",
    "sg:orig_category":"Elektrizit\u00e4tsversorgung",
    "sg:phone":"+41 91 822 20 11",
    "sg:postcode":"6772",
    "sg:province":"Ticino",
    "wof:name":"Azienda Elettrica Ticinese Capanna Lago Tremorgio",
    "wof:placetype":"venue"
},
  "geometry": {"coordinates":[8.7379398346,46.4897994995],"type":"Point"}
}