{
  "type": "Feature",
  "properties": {
    "iso:country":"CH",
    "sg:address":"Thujastrasse 4",
    "sg:city":"Z\u00fcrich",
    "sg:orig_category":"Technische, physikalische U chemische Untersuchung",
    "sg:phone":"+41 14810600",
    "sg:postcode":"8038",
    "sg:province":"Z\u00fcrich",
    "wof:name":"Studer Engineering",
    "wof:placetype":"venue"
},
  "geometry": {"coordinates":[8.5274400711,47.3499336243],"type":"Point"}
}