{
  "type": "Feature",
  "properties": {
    "iso:country":"CH",
    "sg:address":"Eichfeldstrasse 3",
    "sg:city":"Jona",
    "sg:orig_category":"Zahnarztpraxen",
    "sg:phone":"+41 55 210 57 32",
    "sg:postcode":"8645",
    "sg:province":"St. Gallen",
    "wof:name":"Dr. Med. Dent. Chr. Anderegg Zahn\u00e4rztin",
    "wof:placetype":"venue"
},
  "geometry": {"coordinates":[8.8330698013,47.2287902832],"type":"Point"}
}