{
  "type": "Feature",
  "properties": {
    "iso:country":"CH",
    "sg:address":"8570",
    "sg:city":"Weinfelden",
    "sg:orig_category":"Abwasserreinigung",
    "sg:phone":"+41 71 622 33 55",
    "sg:postcode":"8570",
    "sg:province":"Thurgau",
    "wof:name":"Abwasserverband Mittelthurgau",
    "wof:placetype":"venue"
},
  "geometry": {"coordinates":[9.107193,47.566093],"type":"Point"}
}