{
  "type": "Feature",
  "properties": {
    "addr:full":"Engelstrasse 62 Z\u00fcrich Z\u00fcrich 8004",
    "addr:housenumber":"62",
    "addr:postcode":"8004",
    "addr:street":"Engelstrasse",
    "iso:country":"CH",
    "sg:address":"Engelstrasse 62",
    "sg:city":"Z\u00fcrich",
    "sg:orig_category":"Detailhandel mit Bekleidung",
    "sg:postcode":"8004",
    "sg:province":"Z\u00fcrich",
    "wof:name":"Kink Rahm + Jacob",
    "wof:placetype":"venue"
},
  "geometry": {"coordinates":[8.523994,47.376678],"type":"Point"}
}