{
  "type": "Feature",
  "properties": {
    "iso:country":"CH",
    "sg:address":"Route Cantonale",
    "sg:city":"Grandval",
    "sg:orig_category":"Primarschulen",
    "sg:phone":"+41 32 499 95 83",
    "sg:postcode":"2745",
    "sg:province":"Bern",
    "wof:name":"Ecole Primaire",
    "wof:placetype":"venue"
},
  "geometry": {"coordinates":[7.4230508804,47.2830162048],"type":"Point"}
}