{
  "type": "Feature",
  "properties": {
    "iso:country":"CH",
    "sg:address":"Aarwangenstrasse 95",
    "sg:city":"Langenthal",
    "sg:orig_category":"Grosshandel mit Tabakwaren",
    "sg:phone":"+41 62 922 11 22",
    "sg:postcode":"4900",
    "sg:province":"Bern",
    "wof:name":"Growa Ag Cash & Carry",
    "wof:placetype":"venue"
},
  "geometry": {"coordinates":[7.778840065,47.2238464355],"type":"Point"}
}