{
  "type": "Feature",
  "properties": {
    "iso:country":"CH",
    "sg:address":"M\u00fchlering 16",
    "sg:city":"H\u00e4gendorf",
    "sg:orig_category":"Schaustellergewerbe U Vergn\u00fcgungsparks",
    "sg:phone":"+41 62 216 31 60",
    "sg:postcode":"4614",
    "sg:province":"Solothurn",
    "wof:name":"Armando's Attraktionen Ag",
    "wof:placetype":"venue"
},
  "geometry": {"coordinates":[7.8397779465,47.3344230652],"type":"Point"}
}