{
  "type": "Feature",
  "properties": {
    "iso:country":"CH",
    "sg:address":"Rathausplatz 2 8880 Walenstadt. Postfach 100",
    "sg:city":"Walenstadt",
    "sg:classifiers":[
        {
            "category":"Restaurant",
            "type":"Food & Drink"
        }
    ],
    "sg:phone":"+41 81 735 12 59",
    "sg:postcode":"8880",
    "sg:province":"St. Gallen",
    "wof:name":"Restaurant Traube",
    "wof:placetype":"venue"
},
  "geometry": {"coordinates":[9.3146247864,47.1241760254],"type":"Point"}
}