{
  "type": "Feature",
  "properties": {
    "addr:full":"Hallwylstrasse 26 Z\u00fcrich Z\u00fcrich 8004",
    "addr:housenumber":"26",
    "addr:postcode":"8004",
    "addr:street":"Hallwylstrasse",
    "iso:country":"CH",
    "sg:address":"Hallwylstrasse 26",
    "sg:city":"Z\u00fcrich",
    "sg:orig_category":"Architekturb\u00fcros",
    "sg:phone":"+41 12411033",
    "sg:postcode":"8004",
    "sg:province":"Z\u00fcrich",
    "wof:name":"Eberli, Weber & Braun Architekten",
    "wof:placetype":"venue"
},
  "geometry": {"coordinates":[8.529093,47.37196],"type":"Point"}
}