{
  "type": "Feature",
  "properties": {
    "iso:country":"CH",
    "sg:address":"Gruthweg 28",
    "sg:city":"M\u00fcnchenstein",
    "sg:orig_category":"Elektroinstallation",
    "sg:phone":"+41 31 839 22 02",
    "sg:postcode":"4142",
    "sg:province":"Basel-Landschaft",
    "wof:name":"Peter Stucki Elektro Ag",
    "wof:placetype":"venue"
},
  "geometry": {"coordinates":[7.5677490234,46.9268913269],"type":"Point"}
}