{
  "type": "Feature",
  "properties": {
    "iso:country":"CH",
    "sg:address":"Ifangstrasse 111 8153 R\u00fcmlang. Postfach",
    "sg:city":"R\u00fcmlang",
    "sg:orig_category":"Herstellung von Bergwerks U Baumaschinen",
    "sg:postcode":"8153",
    "sg:province":"Z\u00fcrich",
    "wof:name":"Schwing Baumaschinen (schweiz) Ag Sbs",
    "wof:placetype":"venue"
},
  "geometry": {"coordinates":[8.5391511917,47.4454612732],"type":"Point"}
}