{
  "type": "Feature",
  "properties": {
    "iso:country":"CH",
    "sg:address":"1875 Morgins. Postfach",
    "sg:city":"Morgins",
    "sg:classifiers":[
        {
            "category":"Travel",
            "subcategory":"Hotels & Motels",
            "type":"Entertainment"
        }
    ],
    "sg:postcode":"1875",
    "sg:province":"Valais",
    "sg:tags":[
        "hotels",
        "mit",
        "restaurant"
    ],
    "wof:name":"Diserens Brigitte",
    "wof:placetype":"venue"
},
  "geometry": {"coordinates":[6.8587532043,46.2375221252],"type":"Point"}
}