{
  "type": "Feature",
  "properties": {
    "iso:country":"CH",
    "sg:address":"Ifangstrasse 27 8604 Volketswil. Postfach",
    "sg:city":"Volketswil",
    "sg:orig_category":"Handel mit Automobilen",
    "sg:postcode":"8604",
    "sg:province":"Z\u00fcrich",
    "wof:name":"Kaine Automobile Autohandel",
    "wof:placetype":"venue"
},
  "geometry": {"coordinates":[8.6788282394,47.3908882141],"type":"Point"}
}