{
  "type": "Feature",
  "properties": {
    "iso:country":"CH",
    "sg:address":"Route De Crassier 9",
    "sg:city":"Bogis-bossey",
    "sg:orig_category":"Herstellung von Teppichen",
    "sg:phone":"+41 22 776 28 11",
    "sg:postcode":"1279",
    "sg:province":"Vaud",
    "wof:name":"Am Moquettes Et Parquets, Aubert Emmanuel",
    "wof:placetype":"venue"
},
  "geometry": {"coordinates":[6.1652050018,46.3564834595],"type":"Point"}
}