{
  "type": "Feature",
  "properties": {
    "iso:country":"CH",
    "sg:address":"Imbisb\u00fchlstrasse 165",
    "sg:city":"Z\u00fcrich",
    "sg:orig_category":"Herstellung von sonstigen elektrischen Ausr\u00fcstungen",
    "sg:postcode":"8049",
    "sg:province":"Z\u00fcrich",
    "wof:name":"Ryser + Bucher Gmbh",
    "wof:placetype":"venue"
},
  "geometry": {"coordinates":[8.8196706772,47.314956665],"type":"Point"}
}