{
  "type": "Feature",
  "properties": {
    "iso:country":"CH",
    "sg:address":"Villa Clairgil",
    "sg:city":"Gilly",
    "sg:orig_category":"Vereine Musik/Blasmusik",
    "sg:postcode":"1182",
    "sg:province":"Vaud",
    "wof:name":"Fanfare De Gilly",
    "wof:placetype":"venue"
},
  "geometry": {"coordinates":[6.2965598106,46.4576950073],"type":"Point"}
}