{
  "type": "Feature",
  "properties": {
    "iso:country":"CH",
    "sg:address":"Kapellenstrasse 5",
    "sg:city":"Bern",
    "sg:orig_category":"Detailhandel mit B\u00fcchern, Zeitungen, Schreib U Papeteriewaren",
    "sg:postcode":"3011",
    "sg:province":"Bern",
    "wof:name":"Salzmann & Co",
    "wof:placetype":"venue"
},
  "geometry": {"coordinates":[7.43588,46.944332],"type":"Point"}
}