{
  "type": "Feature",
  "properties": {
    "iso:country":"CH",
    "sg:address":"Grand-rue 82 1110 Morges. Postfach",
    "sg:city":"Morges",
    "sg:orig_category":"Non-Classified Establishments",
    "sg:phone":"+41 21 801 65 03",
    "sg:postcode":"1110",
    "sg:province":"Vaud",
    "wof:name":"Animatix, Gisiger Olivier Production Et Diffusion De Contenu Multim\u00e9dias Sur Internet Et Cd-rom",
    "wof:placetype":"venue"
},
  "geometry": {"coordinates":[6.4974579811,46.5084915161],"type":"Point"}
}