{
  "type": "Feature",
  "properties": {
    "iso:country":"CH",
    "sg:address":"Bahnhofstrasse 9",
    "sg:city":"Chur",
    "sg:orig_category":"Zahnarztpraxen",
    "sg:phone":"+41 81 252 09 44",
    "sg:postcode":"7000",
    "sg:province":"Graubunden",
    "wof:name":"Dr. Med. Dent. Toni Meier Zahnarzt",
    "wof:placetype":"venue"
},
  "geometry": {"coordinates":[9.5308618546,46.8526878357],"type":"Point"}
}