{
  "type": "Feature",
  "properties": {
    "iso:country":"CH",
    "sg:address":"Masanserstrasse",
    "sg:city":"Chur",
    "sg:orig_category":"Handelsvermittlung U Grosshandel mit Automobilen",
    "sg:phone":"+41 81 353 70 02",
    "sg:postcode":"7000",
    "sg:province":"Graubunden",
    "wof:name":"Alfred Ineichen Autohandel",
    "wof:placetype":"venue"
},
  "geometry": {"coordinates":[9.5349302292,46.8660736084],"type":"Point"}
}