{
  "type": "Feature",
  "properties": {
    "iso:country":"CH",
    "sg:address":"Bergwerkstrasse 33",
    "sg:city":"Horgen",
    "sg:orig_category":"Bau U Wohngenossenschaften Erschliessung von Grundst\u00fccken",
    "sg:phone":"+41 52 222 08 88",
    "sg:postcode":"8810",
    "sg:province":"Z\u00fcrich",
    "wof:name":"Gesewo, Genossenschaft F\u00fcr Selbstverwaltetes Wohnen",
    "wof:placetype":"venue"
},
  "geometry": {"coordinates":[8.768539,47.506367],"type":"Point"}
}