{
  "type": "Feature",
  "properties": {
    "iso:country":"CH",
    "sg:address":"Ebmattstrasse 13",
    "sg:city":"Bubikon",
    "sg:orig_category":"Sonstiger Grosshandel",
    "sg:postcode":"8608",
    "sg:province":"Z\u00fcrich",
    "wof:name":"Kos Heinz",
    "wof:placetype":"venue"
},
  "geometry": {"coordinates":[8.8225708008,47.268119812],"type":"Point"}
}