{
  "type": "Feature",
  "properties": {
    "addr:full":"Sils Im Domleschg Graubunden 7411",
    "addr:housenumber":"7411",
    "iso:country":"CH",
    "sg:city":"Sils Im Domleschg",
    "sg:orig_category":"Industrie, Sonstige Industrieunternehmungen",
    "sg:postcode":"7411",
    "sg:province":"Graubunden",
    "wof:name":"Euroboerse- Die Online-auktion",
    "wof:placetype":"venue"
},
  "geometry": {"coordinates":[9.455525,46.701817],"type":"Point"}
}