{
  "type": "Feature",
  "properties": {
    "addr:full":"Route Principale 13a Movelier Jura 2812",
    "addr:housenumber":"13a",
    "addr:postcode":"2812",
    "addr:street":"Route Principale;Jura",
    "iso:country":"CH",
    "sg:address":"Route Principale 13a",
    "sg:city":"Movelier",
    "sg:orig_category":"Autogaragen",
    "sg:phone":"+41 79 431 10 38",
    "sg:postcode":"2812",
    "sg:province":"Jura",
    "wof:name":"Bron Automobiles Kartings",
    "wof:placetype":"venue"
},
  "geometry": {"coordinates":[7.318077,47.409012],"type":"Point"}
}