{
  "type": "Feature",
  "properties": {
    "iso:country":"CH",
    "sg:address":"Bahnhofstrasse 16",
    "sg:city":"Engelberg",
    "sg:orig_category":"Spielsalons",
    "sg:phone":"+41 41 637 15 49",
    "sg:postcode":"6390",
    "sg:province":"Obwalden",
    "wof:name":"Kursaal-casino",
    "wof:placetype":"venue"
},
  "geometry": {"coordinates":[8.4020318985,46.820980072],"type":"Point"}
}