{
  "type": "Feature",
  "properties": {
    "addr:full":"Sonnenweg 6 Turgi Aargau 5300",
    "addr:housenumber":"6",
    "addr:postcode":"5300",
    "addr:street":"Sonnenweg",
    "iso:country":"CH",
    "sg:address":"Sonnenweg 6",
    "sg:city":"Turgi",
    "sg:orig_category":"Buchf\u00fchrung Verwaltung von Immobilien",
    "sg:postcode":"5300",
    "sg:province":"Aargau",
    "wof:name":"Paul Fischer Treuhand",
    "wof:placetype":"venue"
},
  "geometry": {"coordinates":[8.252895,47.49358],"type":"Point"}
}