{
  "type": "Feature",
  "properties": {
    "iso:country":"CH",
    "sg:address":"Weststrasse 26",
    "sg:city":"Kreuzlingen",
    "sg:orig_category":"Politische Parteien SP",
    "sg:postcode":"8280",
    "sg:province":"Thurgau",
    "wof:name":"Sp Ortspartei Kreuzlingen",
    "wof:placetype":"venue"
},
  "geometry": {"coordinates":[9.162566185,47.6516265869],"type":"Point"}
}