{
  "type": "Feature",
  "properties": {
    "iso:country":"CH",
    "sg:address":"Baslerstrasse 22",
    "sg:city":"Umiken",
    "sg:classifiers":[
        {
            "category":"Travel",
            "subcategory":"Hotels & Motels",
            "type":"Entertainment"
        }
    ],
    "sg:phone":"+41 56 441 12 17",
    "sg:postcode":"5222",
    "sg:province":"Aargau",
    "sg:tags":[
        "hotels",
        "mit",
        "restaurant"
    ],
    "wof:name":"Gasthaus L\u00f6wen Ennio Gamba",
    "wof:placetype":"venue"
},
  "geometry": {"coordinates":[8.1935443878,47.4837913513],"type":"Point"}
}