{
  "type": "Feature",
  "properties": {
    "iso:country":"CH",
    "sg:address":"Chemin Des Barri\u00e8res 27",
    "sg:city":"Martigny",
    "sg:orig_category":"Grosshandel mit Getr\u00e4nken Rebbau",
    "sg:phone":"+41 27 722 34 85",
    "sg:postcode":"1920",
    "sg:province":"Valais",
    "wof:name":"Alexis Jacqu\u00e9rioz Cave",
    "wof:placetype":"venue"
},
  "geometry": {"coordinates":[7.0677227974,46.1026725769],"type":"Point"}
}