{
  "type": "Feature",
  "properties": {
    "iso:country":"CH",
    "sg:address":"Paradieshofstrasse 138",
    "sg:city":"Basel",
    "sg:orig_category":"Finanzierungsinstitutionen",
    "sg:phone":"+41 61 301 28 16",
    "sg:postcode":"4054",
    "sg:province":"Basel-Stadt",
    "wof:name":"Finanzberatung Und Verm\u00f6gensverwaltung Roth Dr. Hanspeter",
    "wof:placetype":"venue"
},
  "geometry": {"coordinates":[7.5587491989,47.5471878052],"type":"Point"}
}