{
  "type": "Feature",
  "properties": {
    "addr:full":"Zauggenriedstrasse 1 Fraubrunnen Bern 3312",
    "addr:housenumber":"1",
    "addr:postcode":"3312",
    "addr:street":"Zauggenriedstrasse",
    "iso:country":"CH",
    "sg:address":"Zauggenriedstrasse 1",
    "sg:city":"Fraubrunnen",
    "sg:orig_category":"Bau\u00e4mter",
    "sg:phone":"+41 31 760 30 31",
    "sg:postcode":"3312",
    "sg:province":"Bern",
    "wof:name":"Bauverwaltung Der Gemeinde Fraubrunnen",
    "wof:placetype":"venue"
},
  "geometry": {"coordinates":[7.524957,47.084023],"type":"Point"}
}