{
  "type": "Feature",
  "properties": {
    "iso:country":"CH",
    "sg:address":"Reckenb\u00fchlstrasse 2",
    "sg:city":"Luzern",
    "sg:orig_category":"Forschung U Entwicklung im Bereich der Sozial U Humanwissenschaften Unternehmensberatung",
    "sg:phone":"+41 31 318 86 06",
    "sg:postcode":"6005",
    "sg:province":"Luzern",
    "wof:name":"Empiricon Ag Wirtschafts- U. Sozialwissenschaft; Beratung, Forschung U. Schulung Usw",
    "wof:placetype":"venue"
},
  "geometry": {"coordinates":[7.4499430656,46.9478302002],"type":"Point"}
}