{
  "type": "Feature",
  "properties": {
    "iso:country":"CH",
    "sg:address":"Pilatusstrasse 39",
    "sg:city":"Aarburg",
    "sg:orig_category":"D\u00e4mmung gegen K\u00e4lte, W\u00e4rme, Schall U Ersch\u00fctterung",
    "sg:phone":"+41 17130455",
    "sg:postcode":"4663",
    "sg:province":"Aargau",
    "wof:name":"Peter Erhardt Isolierungen",
    "wof:placetype":"venue"
},
  "geometry": {"coordinates":[8.5447149277,47.2870979309],"type":"Point"}
}