{
  "type": "Feature",
  "properties": {
    "iso:country":"CH",
    "sg:address":"Rue De L'ecluse 18-20",
    "sg:city":"Neuch\u00e2tel",
    "sg:orig_category":"Wohnheime",
    "sg:phone":"+41 32 724 69 16",
    "sg:postcode":"2000",
    "sg:province":"Neuch\u00e2tel",
    "wof:name":"Foyer F\u00e9minin De L'arm\u00e9e Du Salut",
    "wof:placetype":"venue"
},
  "geometry": {"coordinates":[6.9263792038,46.9931182861],"type":"Point"}
}