{
  "type": "Feature",
  "properties": {
    "iso:country":"CH",
    "sg:address":"Collina",
    "sg:city":"Bissone",
    "sg:orig_category":"Vorschulen, Kinderg\u00e4rten",
    "sg:phone":"+41 91 649 62 45",
    "sg:postcode":"6816",
    "sg:province":"Ticino",
    "wof:name":"Scuola Materna",
    "wof:placetype":"venue"
},
  "geometry": {"coordinates":[8.9689407349,45.9533424377],"type":"Point"}
}