{
  "type": "Feature",
  "properties": {
    "iso:country":"CH",
    "sg:address":"Perriaz En",
    "sg:city":"Chardonne",
    "sg:orig_category":"Verwertung von Milch",
    "sg:postcode":"1803",
    "sg:province":"Vaud",
    "wof:name":"Soci\u00e9t\u00e9 De Laiterie Du Mont-p\u00e8lerin",
    "wof:placetype":"venue"
},
  "geometry": {"coordinates":[6.8177161217,46.4878005981],"type":"Point"}
}