{
  "type": "Feature",
  "properties": {
    "iso:country":"CH",
    "sg:address":"Cantonale Via 50 6595 Riazzino. Postfach",
    "sg:city":"Riazzino",
    "sg:orig_category":"Unclassifiable Establishments",
    "sg:phone":"+41 91 850 51 51",
    "sg:postcode":"6595",
    "sg:province":"Ticino",
    "wof:name":"Imv Holding Sa",
    "wof:placetype":"venue"
},
  "geometry": {"coordinates":[8.896900177,46.1746406555],"type":"Point"}
}