{
  "type": "Feature",
  "properties": {
    "iso:country":"CH",
    "sg:address":"Wildbergstrasse 20 9243 Jonschwil. Postfach",
    "sg:city":"Jonschwil",
    "sg:orig_category":"Unclassifiable Establishments",
    "sg:postcode":"9243",
    "sg:province":"St. Gallen",
    "wof:name":"Gallus-trans Gmbh G\u00fctertransporte Usw",
    "wof:placetype":"venue"
},
  "geometry": {"coordinates":[9.0905818939,47.4227142334],"type":"Point"}
}