{
  "type": "Feature",
  "properties": {
    "iso:country":"CH",
    "sg:address":"Hauptstrasse 14a",
    "sg:city":"H\u00f6rhausen",
    "sg:orig_category":"Reparatur von Gebrauchsg\u00fctern",
    "sg:phone":"+41 61 712 03 12",
    "sg:postcode":"8507",
    "sg:province":"Thurgau",
    "wof:name":"Carrosserie & Spritzwerk Sch\u00e4fer Gmbh",
    "wof:placetype":"venue"
},
  "geometry": {"coordinates":[7.598074913,47.4858932495],"type":"Point"}
}