{
  "type": "Feature",
  "properties": {
    "iso:country":"CH",
    "sg:address":"Bahnhofstrasse 21",
    "sg:city":"Herisau",
    "sg:orig_category":"Unternehmensberatung",
    "sg:postcode":"9100",
    "sg:province":"Appenzell Ausserrhoden",
    "wof:name":"Ds Beratungs Und Treuhand-gmbh",
    "wof:placetype":"venue"
},
  "geometry": {"coordinates":[9.2765731812,47.388130188],"type":"Point"}
}