{
  "type": "Feature",
  "properties": {
    "iso:country":"CH",
    "sg:address":"1180",
    "sg:city":"Tartegnin",
    "sg:orig_category":"Sportvereine Sch\u00fctzen",
    "sg:postcode":"1180",
    "sg:province":"Vaud",
    "wof:name":"St\u00e9 De Tir Tartegnin",
    "wof:placetype":"venue"
},
  "geometry": {"coordinates":[6.316699028,46.4661178589],"type":"Point"}
}