{
  "type": "Feature",
  "properties": {
    "iso:country":"CH",
    "sg:address":"Spitzer-waldstrasse 13",
    "sg:city":"Romanshorn",
    "sg:orig_category":"Handelsvermittlung U Grosshandel Sonstiger Grosshandel",
    "sg:phone":"+41 79 355 12 29",
    "sg:postcode":"8590",
    "sg:province":"Thurgau",
    "wof:name":"Itram Ag",
    "wof:placetype":"venue"
},
  "geometry": {"coordinates":[9.343793869,47.5595703125],"type":"Point"}
}