{
  "type": "Feature",
  "properties": {
    "iso:country":"CH",
    "sg:address":"Avenue De Gilamont 32",
    "sg:city":"Vevey",
    "sg:orig_category":"Tierarztpraxis",
    "sg:phone":"+41 21 922 98 17",
    "sg:postcode":"1800",
    "sg:province":"Vaud",
    "wof:name":"Dr M\u00e9d. V\u00e9t. Jacques Terrail M\u00e9decin V\u00e9t\u00e9rinaire",
    "wof:placetype":"venue"
},
  "geometry": {"coordinates":[6.8490781784,46.4692001343],"type":"Point"}
}