{
  "type": "Feature",
  "properties": {
    "iso:country":"CH",
    "sg:address":"Freiheitsstrasse 16",
    "sg:city":"Altnau",
    "sg:orig_category":"Herstellung von medizinischen U chirurgischen Ger\u00e4ten sowie orthop\u00e4dischen Vorrichtungen",
    "sg:phone":"+41 79 631 00 60",
    "sg:postcode":"8595",
    "sg:province":"Thurgau",
    "wof:name":"Michael Roberz",
    "wof:placetype":"venue"
},
  "geometry": {"coordinates":[9.268029213,47.6201171875],"type":"Point"}
}