{
  "type": "Feature",
  "properties": {
    "iso:country":"CH",
    "sg:address":"Neuenburgstrasse 79",
    "sg:city":"Gampelen",
    "sg:orig_category":"Detailhandel mit Blumen U Pflanzen Fachdetailhandel in Verkaufsr\u00e4umen",
    "sg:phone":"+41 32 313 13 06",
    "sg:postcode":"3236",
    "sg:province":"Bern",
    "wof:name":"Blumenmarkt Dietrich",
    "wof:placetype":"venue"
},
  "geometry": {"coordinates":[7.044079,47.018902],"type":"Point"}
}