{
  "type": "Feature",
  "properties": {
    "iso:country":"CH",
    "sg:address":"St. Gallerstr. 1",
    "sg:city":"Rorschach",
    "sg:orig_category":"Detailhandel mit Geschenkartikeln U Souvenirs Fachdetailhandel in Verkaufsr\u00e4umen",
    "sg:phone":"+41 79 404 49 92",
    "sg:postcode":"9400",
    "sg:province":"St. Gallen",
    "wof:name":"Corredo De Solda",
    "wof:placetype":"venue"
},
  "geometry": {"coordinates":[9.4887113571,47.4788398743],"type":"Point"}
}