{
  "type": "Feature",
  "properties": {
    "iso:country":"CH",
    "sg:address":"H\u00fcgsamstr. 5",
    "sg:city":"Richterswil",
    "sg:orig_category":"Grosshandel mit sonstigen Nahrungsmitteln",
    "sg:phone":"+41 17848968",
    "sg:postcode":"8805",
    "sg:province":"Z\u00fcrich",
    "wof:name":"Rarog Meerfr\u00fcchte, Sindicic Roberta",
    "wof:placetype":"venue"
},
  "geometry": {"coordinates":[8.6807012558,47.1958656311],"type":"Point"}
}