{
  "type": "Feature",
  "properties": {
    "iso:country":"CH",
    "sg:address":"Rauenmattenweg 2",
    "sg:city":"M\u00fcntschemier",
    "sg:orig_category":"Softwareentwicklung U beratung",
    "sg:phone":"+41 32 313 45 08",
    "sg:postcode":"3225",
    "sg:province":"Bern",
    "wof:name":"Computeria Gmbh",
    "wof:placetype":"venue"
},
  "geometry": {"coordinates":[7.1443781853,46.9944648743],"type":"Point"}
}