{
  "type": "Feature",
  "properties": {
    "iso:country":"CH",
    "sg:address":"Seeblickweg 18 8274 T\u00e4gerwilen. Postfach 68",
    "sg:city":"T\u00e4gerwilen",
    "sg:orig_category":"Finanzierungsinstitutionen",
    "sg:phone":"+41 71 667 07 60",
    "sg:postcode":"8274",
    "sg:province":"Thurgau",
    "wof:name":"Michael Graf Finanzberatung & Verm\u00f6gensverwaltung",
    "wof:placetype":"venue"
},
  "geometry": {"coordinates":[9.1238212585,47.6536865234],"type":"Point"}
}