{
  "type": "Feature",
  "properties": {
    "iso:country":"CH",
    "sg:address":"Grubenstrasse 8",
    "sg:city":"Wynau",
    "sg:orig_category":"Herstellung von Transportbeton",
    "sg:phone":"+41 62 929 34 84",
    "sg:postcode":"4923",
    "sg:province":"Bern",
    "wof:name":"Wynag-beton Ag",
    "wof:placetype":"venue"
},
  "geometry": {"coordinates":[7.8219871521,47.2565917969],"type":"Point"}
}