{
  "type": "Feature",
  "properties": {
    "iso:country":"CH",
    "sg:address":"6390 Engelberg. Postfach 754",
    "sg:city":"Engelberg",
    "sg:classifiers":[
        {
            "category":"Bars & Pubs",
            "type":"Food & Drink"
        }
    ],
    "sg:phone":"+41 41 639 50 80",
    "sg:postcode":"6391",
    "sg:province":"Obwalden",
    "sg:tags":[
        "restaurant"
    ],
    "wof:name":"Panorama Restaurant Titlis & Bar",
    "wof:placetype":"venue"
},
  "geometry": {"coordinates":[8.42277,46.837051],"type":"Point"}
}