{
  "type": "Feature",
  "properties": {
    "iso:country":"CH",
    "sg:address":"Schmiedgasse 31",
    "sg:city":"Stans",
    "sg:orig_category":"Bauschreinerei",
    "sg:phone":"+41 79 340 89 28",
    "sg:postcode":"6370",
    "sg:province":"Nidwalden",
    "wof:name":"Josef Camenzind Schreinerei",
    "wof:placetype":"venue"
},
  "geometry": {"coordinates":[8.439938,47.151936],"type":"Point"}
}