{
  "type": "Feature",
  "properties": {
    "addr:full":"Leuengasse 8 Basel Basel-Stadt 4057",
    "addr:housenumber":"8",
    "addr:postcode":"4057",
    "addr:street":"Leuengasse",
    "iso:country":"CH",
    "sg:address":"Leuengasse 8",
    "sg:city":"Basel",
    "sg:orig_category":"Bauschreinerei Herstellung von M\u00f6beln verschiedener Art",
    "sg:phone":"+41 79 311 54 59",
    "sg:postcode":"4057",
    "sg:province":"Basel-Stadt",
    "wof:name":"Egon St\u00f6ger Antikschreinerei",
    "wof:placetype":"venue"
},
  "geometry": {"coordinates":[7.587481,47.565983],"type":"Point"}
}