{
  "type": "Feature",
  "properties": {
    "iso:country":"CH",
    "sg:address":"Gutstrasse 121",
    "sg:city":"Z\u00fcrich",
    "sg:orig_category":"Hardwareberatung",
    "sg:postcode":"8055",
    "sg:province":"Z\u00fcrich",
    "wof:name":"Computer Friends Telli",
    "wof:placetype":"venue"
},
  "geometry": {"coordinates":[8.5050935745,47.3724250793],"type":"Point"}
}