{
  "type": "Feature",
  "properties": {
    "iso:country":"CH",
    "sg:address":"Linth-escher-strasse 12",
    "sg:city":"Bilten",
    "sg:orig_category":"Oberfl\u00e4chenveredlung U W\u00e4rmebehandlung",
    "sg:phone":"+41 55 615 23 46",
    "sg:postcode":"8865",
    "sg:province":"Glarus",
    "wof:name":"Foma-galvanik Ag",
    "wof:placetype":"venue"
},
  "geometry": {"coordinates":[9.0266304016,47.152179718],"type":"Point"}
}