{
  "type": "Feature",
  "properties": {
    "iso:country":"CH",
    "sg:address":"Vorstadt 1",
    "sg:city":"Boswil",
    "sg:orig_category":"Kosmetikinstitute",
    "sg:phone":"+41 56 666 21 69",
    "sg:postcode":"5623",
    "sg:province":"Aargau",
    "wof:name":"Ursula Bucher Kosmetikinstitut & Solarium",
    "wof:placetype":"venue"
},
  "geometry": {"coordinates":[8.3156299591,47.2989807129],"type":"Point"}
}