{
  "type": "Feature",
  "properties": {
    "iso:country":"CH",
    "sg:address":"Via Orbello 22",
    "sg:city":"Arbedo",
    "sg:orig_category":"Arztpraxen",
    "sg:phone":"+41 91 829 20 00",
    "sg:postcode":"6517",
    "sg:province":"Ticino",
    "wof:name":"Dott.med.ezio Montedoro Specialista Fmh",
    "wof:placetype":"venue"
},
  "geometry": {"coordinates":[9.046903,46.217796],"type":"Point"}
}