{
  "type": "Feature",
  "properties": {
    "iso:country":"CH",
    "sg:address":"Via Cios",
    "sg:city":"Novazzano",
    "sg:orig_category":"Tankstellen",
    "sg:phone":"+41 91 647 16 24",
    "sg:postcode":"6883",
    "sg:province":"Ticino",
    "wof:name":"Piccadilly Sa",
    "wof:placetype":"venue"
},
  "geometry": {"coordinates":[8.9641017914,45.8456039429],"type":"Point"}
}