{
  "type": "Feature",
  "properties": {
    "iso:country":"CH",
    "sg:address":"Vorderi H\u00f6chi",
    "sg:city":"Hirzel",
    "sg:orig_category":"Vereine Vogel-& Naturschutz",
    "sg:postcode":"8816",
    "sg:province":"Z\u00fcrich",
    "wof:name":"Natur-& Vogelschutzverein",
    "wof:placetype":"venue"
},
  "geometry": {"coordinates":[8.6054592133,47.217716217],"type":"Point"}
}