{
  "type": "Feature",
  "properties": {
    "iso:country":"CH",
    "sg:address":"Rue Des Remparts 9 1400 Yverdon-les-bains Case Postale 3281",
    "sg:city":"Yverdon",
    "sg:classifiers":[
        {
            "category":"Professional",
            "subcategory":"Employment Agencies",
            "type":"Services"
        }
    ],
    "sg:phone":"+41 24 426 00 33",
    "sg:postcode":"1401",
    "sg:province":"Vaud",
    "sg:tags":[
        "personal",
        "u",
        "stellenvermittlung"
    ],
    "wof:name":"Max Studer Interim Sa",
    "wof:placetype":"venue"
},
  "geometry": {"coordinates":[6.640994072,46.7794723511],"type":"Point"}
}