{
  "type": "Feature",
  "properties": {
    "iso:country":"CH",
    "sg:address":"Via General Guisan 9",
    "sg:city":"Balerna",
    "sg:orig_category":"Innenarchitekturb\u00fcros Innendekorationsateliers",
    "sg:phone":"+41 22 311 42 77",
    "sg:postcode":"6828",
    "sg:province":"Ticino",
    "wof:name":"Rodolphe Lasser Eb\u00e9nisterie",
    "wof:placetype":"venue"
},
  "geometry": {"coordinates":[6.1461720467,46.2015457153],"type":"Point"}
}