{
  "type": "Feature",
  "properties": {
    "iso:country":"CH",
    "sg:address":"B\u00e4zweg 4",
    "sg:city":"Andermatt",
    "sg:orig_category":"Sanit\u00e4r, Heizungs U L\u00fcftungsinstallation Sanit\u00e4rinstallation",
    "sg:phone":"+41 79 230 43 83",
    "sg:postcode":"6490",
    "sg:province":"Uri",
    "wof:name":"Rutigliano Vincenzo Sa",
    "wof:placetype":"venue"
},
  "geometry": {"coordinates":[9.0045003891,46.0516586304],"type":"Point"}
}