{
  "type": "Feature",
  "properties": {
    "iso:country":"CH",
    "sg:address":"Lagerweg 18",
    "sg:city":"Langenthal",
    "sg:orig_category":"Handelsvermittlung U Grosshandel Sonstiger Grosshandel",
    "sg:phone":"+41 62 923 21 89",
    "sg:postcode":"4900",
    "sg:province":"Bern",
    "wof:name":"Darigo, Export-import, Stojanovic Slavisa",
    "wof:placetype":"venue"
},
  "geometry": {"coordinates":[7.7740988731,47.2177696228],"type":"Point"}
}