{
  "type": "Feature",
  "properties": {
    "iso:country":"CH",
    "sg:address":"Talstr. 45",
    "sg:city":"Arlesheim",
    "sg:classifiers":[
        {
            "category":"Manufacturing",
            "subcategory":"Chemicals & Compounds",
            "type":"Manufacturing & Wholesale Goods"
        }
    ],
    "sg:phone":"+41 61 705 15 15",
    "sg:postcode":"4144",
    "sg:province":"Basel-Landschaft",
    "sg:tags":[
        "pharmaceutical",
        "energy",
        "chemistry",
        "-",
        "by-product"
    ],
    "wof:name":"Suter Joerin Ag",
    "wof:placetype":"venue"
},
  "geometry": {"coordinates":[7.608591,47.497795],"type":"Point"}
}