{
  "type": "Feature",
  "properties": {
    "iso:country":"CH",
    "sg:address":"R\u00fctihaldestrasse 12",
    "sg:city":"Killwangen",
    "sg:orig_category":"Advokaturb\u00fcros",
    "sg:phone":"+41 56 401 58 25",
    "sg:postcode":"8956",
    "sg:province":"Aargau",
    "wof:name":"Bernasconi & Bernasconi Advokaturb\u00fcro",
    "wof:placetype":"venue"
},
  "geometry": {"coordinates":[8.34848,47.431194],"type":"Point"}
}