{
  "type": "Feature",
  "properties": {
    "iso:country":"CH",
    "sg:address":"Waldstrasse 2",
    "sg:city":"Gerlafingen",
    "sg:orig_category":"P\u00e9dicure",
    "sg:phone":"+41 32 675 28 29",
    "sg:postcode":"4563",
    "sg:province":"Solothurn",
    "wof:name":"Doris Hofer P\u00e9dicure",
    "wof:placetype":"venue"
},
  "geometry": {"coordinates":[7.5704832077,47.1680145264],"type":"Point"}
}