{
  "type": "Feature",
  "properties": {
    "iso:country":"CH",
    "sg:address":"Ausmattstrasse 1",
    "sg:city":"Muttenz",
    "sg:orig_category":"Sonstige Aktivit\u00e4ten der nicht-\u00e4rztlichen Medizinalberufe",
    "sg:phone":"+41 61 462 03 95",
    "sg:postcode":"4132",
    "sg:province":"Basel-Landschaft",
    "wof:name":"Sibylle Dapp Fussreflexzonen-massage",
    "wof:placetype":"venue"
},
  "geometry": {"coordinates":[7.6537861824,47.5254707336],"type":"Point"}
}