{
  "type": "Feature",
  "properties": {
    "iso:country":"CH",
    "sg:address":"Via Rinaldo Simen 3",
    "sg:city":"Minusio",
    "sg:orig_category":"Museen",
    "sg:phone":"+41 91 743 66 71",
    "sg:postcode":"6648",
    "sg:province":"Ticino",
    "wof:name":"Museo Elisarion",
    "wof:placetype":"venue"
},
  "geometry": {"coordinates":[8.8107652664,46.1735229492],"type":"Point"}
}