{
  "type": "Feature",
  "properties": {
    "iso:country":"CH",
    "sg:address":"Atelierhaus 8561 Ottoberg. Postfach",
    "sg:city":"Ottoberg",
    "sg:orig_category":"Softwareentwicklung U beratung",
    "sg:phone":"+41 31 376 12 06",
    "sg:postcode":"8561",
    "sg:province":"Thurgau",
    "wof:name":"Stone Soft Gmbh",
    "wof:placetype":"venue"
},
  "geometry": {"coordinates":[7.4196782112,46.9384689331],"type":"Point"}
}