{
  "type": "Feature",
  "properties": {
    "iso:country":"CH",
    "sg:address":"Reuchenettestrasse 7 2500 Biel/bienne. Postfach",
    "sg:city":"Biel/bienne",
    "sg:orig_category":"Herstellung von Arbeits U Berufsbekleidung",
    "sg:phone":"+41 32 342 46 76",
    "sg:postcode":"2502",
    "sg:province":"Bern",
    "wof:name":"Olivier Charles, Storz-olivier Frieda, Nachfolger",
    "wof:placetype":"venue"
},
  "geometry": {"coordinates":[7.2525048256,47.1463928223],"type":"Point"}
}