{
  "type": "Feature",
  "properties": {
    "iso:country":"CH",
    "sg:address":"Rue Industrielle 30",
    "sg:city":"Montreux",
    "sg:orig_category":"Detailhandel mit Ton U Bildtr\u00e4gern",
    "sg:phone":"+41 21 963 40 40",
    "sg:postcode":"1820",
    "sg:province":"Vaud",
    "wof:name":"Ekarloff S\u00e0rl Produits Multim\u00e9dia",
    "wof:placetype":"venue"
},
  "geometry": {"coordinates":[6.9134140015,46.4331817627],"type":"Point"}
}