{
  "type": "Feature",
  "properties": {
    "iso:country":"CH",
    "sg:address":"Hauptstrasse 63a",
    "sg:city":"Muotathal",
    "sg:orig_category":"Bauschreinerei Herstellung von Konstruktionsteilen, Fertigbauteilen U Ausbauelementen aus Holz",
    "sg:phone":"+41 41 830 16 36",
    "sg:postcode":"6436",
    "sg:province":"Schwyz",
    "wof:name":"Betschart's Jos. S\u00f6hne Ag",
    "wof:placetype":"venue"
},
  "geometry": {"coordinates":[8.761317,46.973045],"type":"Point"}
}