{
  "type": "Feature",
  "properties": {
    "iso:country":"CH",
    "sg:address":"Le Ch\u00e2teau",
    "sg:city":"Vuissens",
    "sg:orig_category":"Betrieb von Sportanlagen",
    "sg:postcode":"1486",
    "sg:province":"Fribourg",
    "wof:name":"Centre Sportif Du Ch\u00e2teau De Vuissens Sa",
    "wof:placetype":"venue"
},
  "geometry": {"coordinates":[6.766535,46.737514],"type":"Point"}
}