{
  "type": "Feature",
  "properties": {
    "iso:country":"CH",
    "sg:address":"Konstanzerstrasse 9",
    "sg:city":"Kreuzlingen",
    "sg:orig_category":"Kauf U Verkauf von Immobilien auf eigene Rechnung",
    "sg:postcode":"8280",
    "sg:province":"Thurgau",
    "wof:name":"Ensemble Artisanal Et Commercial De Riantbosson Sa",
    "wof:placetype":"venue"
},
  "geometry": {"coordinates":[9.1684331894,47.6545524597],"type":"Point"}
}