{
  "type": "Feature",
  "properties": {
    "iso:country":"CH",
    "sg:address":"B\u00fcrenstrasse 49",
    "sg:city":"Pieterlen",
    "sg:orig_category":"Allgemeiner Gartenbau",
    "sg:phone":"+41 32 377 27 30",
    "sg:postcode":"2542",
    "sg:province":"Bern",
    "wof:name":"Bendicht Schluep Baumschule",
    "wof:placetype":"venue"
},
  "geometry": {"coordinates":[7.354406,47.172516],"type":"Point"}
}