{
  "type": "Feature",
  "properties": {
    "iso:country":"CH",
    "sg:address":"Stab.commerciale Bolla",
    "sg:city":"Riazzino",
    "sg:orig_category":"Herstellung von Mess U Kontrollinstrumenten U vorrichtungen Mechanische Werkst\u00e4tten",
    "sg:phone":"+41 91 745 39 37",
    "sg:postcode":"6595",
    "sg:province":"Ticino",
    "wof:name":"Laus Flli. Sa",
    "wof:placetype":"venue"
},
  "geometry": {"coordinates":[8.8976049423,46.1745452881],"type":"Point"}
}