{
  "type": "Feature",
  "properties": {
    "iso:country":"CH",
    "sg:address":"Industriestrasse 23",
    "sg:city":"Trimbach",
    "sg:orig_category":"Herstellung von Metallerzeugnissen ohne Maschinenbau Herstellung von k\u00e4lte U lufttechnischen Erzeugn",
    "sg:phone":"+41 62 289 20 00",
    "sg:postcode":"4632",
    "sg:province":"Solothurn",
    "wof:name":"J\u00e4ggi/g\u00fcntner (schweiz) Ag",
    "wof:placetype":"venue"
},
  "geometry": {"coordinates":[7.906829834,47.3589096069],"type":"Point"}
}