{
  "type": "Feature",
  "properties": {
    "iso:country":"CH",
    "sg:address":"Via Vedeggio",
    "sg:city":"Lamone",
    "sg:orig_category":"Grosshandel mit Erzen U Metallen Herstellung von Metallkonstruktionen",
    "sg:phone":"+41 17343737",
    "sg:postcode":"6814",
    "sg:province":"Ticino",
    "wof:name":"Mts Metallbaubeschl\u00e4ge Ag",
    "wof:placetype":"venue"
},
  "geometry": {"coordinates":[8.9302968979,46.0393981934],"type":"Point"}
}