{
  "type": "Feature",
  "properties": {
    "iso:country":"CH",
    "sg:address":"Br\u00fcnischwand",
    "sg:city":"Stalden",
    "sg:classifiers":[
        {
            "category":"Banks & Credit Unions",
            "subcategory":"Bank",
            "type":"Services"
        }
    ],
    "sg:phone":"+41 4141664461",
    "sg:postcode":"6063",
    "sg:province":"Obwalden",
    "wof:name":"Rentenanstalt Swiss Life",
    "wof:placetype":"venue"
},
  "geometry": {"coordinates":[8.211209,46.886616],"type":"Point"}
}