{
  "type": "Feature",
  "properties": {
    "iso:country":"CH",
    "sg:address":"Rest. Seeblick 6365 Kehrsiten. Postfach",
    "sg:city":"Kehrsiten",
    "sg:orig_category":"RESTAURANTS: TEA-ROOMS",
    "sg:postcode":"6365",
    "sg:province":"Nidwalden",
    "wof:name":"Rest. Seeblick, F. Eberle",
    "wof:placetype":"venue"
},
  "geometry": {"coordinates":[8.3650484085,46.9994125366],"type":"Point"}
}