{
  "type": "Feature",
  "properties": {
    "iso:country":"CH",
    "sg:address":"Hauptstr. 4",
    "sg:city":"Sch\u00f6nengrund",
    "sg:classifiers":[
        {
            "category":"Professional",
            "subcategory":"Engineering",
            "type":"Services"
        }
    ],
    "sg:phone":"+41 71 361 12 24",
    "sg:postcode":"9105",
    "sg:province":"Appenzell Ausserrhoden",
    "sg:tags":[
        "machine",
        "-",
        "mechanical"
    ],
    "wof:name":"Zuberb\u00dchler Landmaschinen Ag",
    "wof:placetype":"venue"
},
  "geometry": {"coordinates":[9.2246809006,47.328338623],"type":"Point"}
}