{
  "type": "Feature",
  "properties": {
    "iso:country":"CH",
    "sg:address":"Via Ruvigliana 16",
    "sg:city":"Viganello",
    "sg:orig_category":"Herstellung von elektronischen Bauelementen",
    "sg:phone":"+41 91 682 01 31",
    "sg:postcode":"6962",
    "sg:province":"Ticino",
    "wof:name":"Conta-idea Sagl",
    "wof:placetype":"venue"
},
  "geometry": {"coordinates":[8.9712972641,46.0134086609],"type":"Point"}
}