{
  "type": "Feature",
  "properties": {
    "addr:full":"Kirchstrasse 13 Sins Aargau 5643",
    "addr:housenumber":"13",
    "addr:postcode":"5643",
    "addr:street":"Kirchstrasse",
    "iso:country":"CH",
    "sg:address":"Kirchstrasse 13",
    "sg:city":"Sins",
    "sg:orig_category":"Bauschreinerei Herstellung von Konstruktionsteilen, Fertigbauteilen U Ausbauelementen aus Holz",
    "sg:phone":"+41 41 787 28 23",
    "sg:postcode":"5643",
    "sg:province":"Aargau",
    "wof:name":"Beat Niederberger, Schreinerei",
    "wof:placetype":"venue"
},
  "geometry": {"coordinates":[8.394446,47.194965],"type":"Point"}
}