{
  "type": "Feature",
  "properties": {
    "iso:country":"CH",
    "sg:address":"Zandone",
    "sg:city":"Losone",
    "sg:orig_category":"Installation von Heizungs, L\u00fcftungs U Klimaanlagen",
    "sg:phone":"+41 79 620 32 83",
    "sg:postcode":"6616",
    "sg:province":"Ticino",
    "wof:name":"Fabbi Sa",
    "wof:placetype":"venue"
},
  "geometry": {"coordinates":[8.7371740341,46.1792068481],"type":"Point"}
}