{
  "type": "Feature",
  "properties": {
    "iso:country":"CH",
    "sg:address":"Nebikerstrasse 21",
    "sg:city":"Sch\u00f6tz",
    "sg:orig_category":"Unclassifiable Establishments",
    "sg:phone":"+41 41 980 28 33",
    "sg:postcode":"6247",
    "sg:province":"Luzern",
    "wof:name":"Portmann Rudolf",
    "wof:placetype":"venue"
},
  "geometry": {"coordinates":[7.9879999161,47.1731681824],"type":"Point"}
}