{
  "type": "Feature",
  "properties": {
    "addr:full":"Grabenstr. 6 Schwerzenbach Z\u00fcrich 8603",
    "addr:housenumber":"6",
    "addr:postcode":"8603",
    "addr:street":"Grabenstr.",
    "iso:country":"CH",
    "sg:address":"Grabenstr. 6",
    "sg:city":"Schwerzenbach",
    "sg:orig_category":"Architektur U Ingenieurb\u00fcros",
    "sg:phone":"+41 18250263",
    "sg:postcode":"8603",
    "sg:province":"Z\u00fcrich",
    "wof:name":"Hybrid Collection, Lombardi Marco Davide",
    "wof:placetype":"venue"
},
  "geometry": {"coordinates":[8.657853,47.382053],"type":"Point"}
}