{
  "type": "Feature",
  "properties": {
    "iso:country":"CH",
    "sg:address":"Vorstadtstrasse 82",
    "sg:city":"Dietikon",
    "sg:orig_category":"Finanzierungsinstitutionen Wirtschaftspr\u00fcfung, Steuerberatung U Treuhand",
    "sg:phone":"+41 17743435",
    "sg:postcode":"8953",
    "sg:province":"Z\u00fcrich",
    "wof:name":"Siag Swiss Investment Ag",
    "wof:placetype":"venue"
},
  "geometry": {"coordinates":[8.3996801376,47.4053688049],"type":"Point"}
}