{
  "type": "Feature",
  "properties": {
    "iso:country":"CH",
    "sg:address":"Wellenbergstrasse 12",
    "sg:city":"Felben",
    "sg:orig_category":"Grosshandel mit sonstigen Gebrauchs U Verbrauchsg\u00fctern Herstellung von Metallerzeugnissen ohne Masch",
    "sg:phone":"+41 52 765 22 10",
    "sg:postcode":"8552",
    "sg:province":"Thurgau",
    "wof:name":"Kohler Walter",
    "wof:placetype":"venue"
},
  "geometry": {"coordinates":[8.9425401688,47.5796318054],"type":"Point"}
}