{
  "type": "Feature",
  "properties": {
    "iso:country":"CH",
    "sg:address":"Ruchstuckstrasse 19",
    "sg:city":"Br\u00fcttisellen",
    "sg:orig_category":"Sportvereine Eissport Curling",
    "sg:phone":"+41 18333330",
    "sg:postcode":"8306",
    "sg:province":"Z\u00fcrich",
    "wof:name":"Curling Club Arosa-inter",
    "wof:placetype":"venue"
},
  "geometry": {"coordinates":[8.6307067871,47.4174385071],"type":"Point"}
}