{
  "type": "Feature",
  "properties": {
    "iso:country":"CH",
    "sg:address":"Vorstadt 21 Willisau 6130 K\u00e4ppelimatt. Postfach",
    "sg:city":"Willisau",
    "sg:orig_category":"Herstellung von k\u00e4lte U lufttechnischen Erzeugnissen f\u00fcr gewerbliche Zwecke",
    "sg:postcode":"6130",
    "sg:province":"Luzern",
    "wof:name":"Hyla Schweiz Gmbh",
    "wof:placetype":"venue"
},
  "geometry": {"coordinates":[7.9928841591,47.1222229004],"type":"Point"}
}