{
  "type": "Feature",
  "properties": {
    "iso:country":"CH",
    "sg:address":"Marktgasse 69",
    "sg:city":"Bern",
    "sg:classifiers":[
        {
            "category":"Restaurant",
            "type":"Food & Drink"
        }
    ],
    "sg:phone":"+41 31 318 29 25",
    "sg:postcode":"3011",
    "sg:province":"Bern",
    "sg:tags":[
        "tea-rooms",
        "restaurants"
    ],
    "wof:name":"Mister Chu",
    "wof:placetype":"venue"
},
  "geometry": {"coordinates":[7.4437432289,46.9481239319],"type":"Point"}
}