{
  "type": "Feature",
  "properties": {
    "iso:country":"CH",
    "sg:address":"Undelstrasse 17 8493 Saland. Postfach",
    "sg:city":"Saland",
    "sg:orig_category":"Sonstiger Grosshandel",
    "sg:phone":"+41 52 386 26 28",
    "sg:postcode":"8493",
    "sg:province":"Z\u00fcrich",
    "wof:name":"Repala Gmbh",
    "wof:placetype":"venue"
},
  "geometry": {"coordinates":[8.8541097641,47.3906326294],"type":"Point"}
}