{
  "type": "Feature",
  "properties": {
    "iso:country":"CH",
    "sg:address":"St\u00e4dtle 3",
    "sg:city":"Vaduz",
    "sg:classifiers":[
        {
            "category":"Restaurant",
            "type":"Food & Drink"
        }
    ],
    "sg:phone":"+423 232 84 84",
    "sg:postcode":"9490",
    "wof:name":"Restaurant Brau-stube",
    "wof:placetype":"venue"
},
  "geometry": {"coordinates":[9.5216808319,47.1411437988],"type":"Point"}
}