{
  "type": "Feature",
  "properties": {
    "iso:country":"CH",
    "sg:address":"Perron Rue Du 10",
    "sg:city":"Coppet",
    "sg:orig_category":"Wirtschaftspr\u00fcfung, Steuerberatung U Treuhand",
    "sg:phone":"+41 32 323 64 23",
    "sg:postcode":"1296",
    "sg:province":"Vaud",
    "wof:name":"Fiduciaire Fidac Sa, Bienne",
    "wof:placetype":"venue"
},
  "geometry": {"coordinates":[7.2514829636,47.1386985779],"type":"Point"}
}