{
  "type": "Feature",
  "properties": {
    "iso:country":"CH",
    "sg:address":"Chemin Du Plein-soleil 12 2740 Montagne-moutier Case Postale 65",
    "sg:city":"Montagne-moutier",
    "sg:orig_category":"Sonstiger spezialisierter Hoch U Tiefbau Verlegen von Fliesen U Platten",
    "sg:phone":"+41 32 493 35 42",
    "sg:postcode":"2740",
    "sg:province":"Bern",
    "wof:name":"John Domon Carrelage & Constr.chemin\u00e9es",
    "wof:placetype":"venue"
},
  "geometry": {"coordinates":[7.3577599525,47.2791366577],"type":"Point"}
}