{
  "type": "Feature",
  "properties": {
    "iso:country":"CH",
    "sg:address":"Fliederweg 8",
    "sg:city":"Neuenegg",
    "sg:orig_category":"Tierarztpraxis",
    "sg:phone":"+41 31 741 00 66",
    "sg:postcode":"3176",
    "sg:province":"Bern",
    "wof:name":"Dr. Med. Vet. Eli Schipper Tierarzt",
    "wof:placetype":"venue"
},
  "geometry": {"coordinates":[7.3225460052,46.8944969177],"type":"Point"}
}