{
  "type": "Feature",
  "properties": {
    "iso:country":"CH",
    "sg:address":"Rue De Vevey 60 1630 Bulle. Postfach",
    "sg:city":"Bulle",
    "sg:classifiers":[
        {
            "category":"Restaurant",
            "type":"Food & Drink"
        }
    ],
    "sg:phone":"+41 26 919 50 70",
    "sg:postcode":"1630",
    "sg:province":"Fribourg",
    "sg:tags":[
        "tea-rooms",
        "restaurants"
    ],
    "wof:name":"Caf\u00e9-restaurant-bar Edelweiss, Golpe Cristina",
    "wof:placetype":"venue"
},
  "geometry": {"coordinates":[7.0529088974,46.6155319214],"type":"Point"}
}