{
  "type": "Feature",
  "properties": {
    "iso:country":"CH",
    "sg:address":"Thesenacher 41",
    "sg:city":"Zumikon",
    "sg:orig_category":"Reiseb\u00fcros U Reiseveranstalter",
    "sg:phone":"+41 19422424",
    "sg:postcode":"8126",
    "sg:province":"Z\u00fcrich",
    "wof:name":"Iga Inter Group Ag",
    "wof:placetype":"venue"
},
  "geometry": {"coordinates":[8.6292953491,47.3275909424],"type":"Point"}
}