{
  "type": "Feature",
  "properties": {
    "iso:country":"CH",
    "sg:address":"Winzenberg 30",
    "sg:city":"L\u00fctisburg",
    "sg:orig_category":"Schweineaufzucht Schweinemast",
    "sg:postcode":"9604",
    "sg:province":"St. Gallen",
    "wof:name":"Philipp R\u00e4ss K\u00e4serei",
    "wof:placetype":"venue"
},
  "geometry": {"coordinates":[9.1208276749,47.396194458],"type":"Point"}
}