{
  "type": "Feature",
  "properties": {
    "iso:country":"CH",
    "sg:address":"4125 Riehen. Postfach 723",
    "sg:city":"Riehen",
    "sg:orig_category":"Wirtschaftsverb\u00e4nde Industrie, Handel and Gewerbe",
    "sg:phone":"+41 22 321 62 22",
    "sg:postcode":"4125",
    "sg:province":"Basel-Stadt",
    "wof:name":"Assoc.d.fabric.suisses De Bi- Jout./orf\u00e8vr.weber & Cie Sa",
    "wof:placetype":"venue"
},
  "geometry": {"coordinates":[6.1296157837,46.2014427185],"type":"Point"}
}