{
  "type": "Feature",
  "properties": {
    "iso:country":"CH",
    "sg:address":"Pierre Rue Saint- 10",
    "sg:city":"Fribourg",
    "sg:orig_category":"Fachdetailhandel mit pharmazeutischen Produkten",
    "sg:postcode":"1700",
    "sg:province":"Fribourg",
    "wof:name":"Pharmat D\u00e9veloppements Sa",
    "wof:placetype":"venue"
},
  "geometry": {"coordinates":[7.1555271149,46.8039703369],"type":"Point"}
}