{
  "type": "Feature",
  "properties": {
    "iso:country":"CH",
    "sg:address":"Juraweg 6 3073 G\u00fcmligen. Postfach",
    "sg:city":"G\u00fcmligen",
    "sg:orig_category":"Druck ohne Zeitungsdruck",
    "sg:phone":"+41 62 771 48 85",
    "sg:postcode":"3073",
    "sg:province":"Bern",
    "wof:name":"Hm-druck Ag",
    "wof:placetype":"venue"
},
  "geometry": {"coordinates":[8.1787900925,47.2336883545],"type":"Point"}
}