{
  "type": "Feature",
  "properties": {
    "iso:country":"CH",
    "sg:address":"Rosenbergstrasse 17",
    "sg:city":"Neuhausen",
    "sg:orig_category":"Vermietung U Verpachtung von eigenen Immobilien",
    "sg:phone":"+41 52 672 78 25",
    "sg:postcode":"8212",
    "sg:province":"Schaffhausen",
    "wof:name":"Dietschi Martin",
    "wof:placetype":"venue"
},
  "geometry": {"coordinates":[8.6155138016,47.6845207214],"type":"Point"}
}