{
  "type": "Feature",
  "properties": {
    "iso:country":"CH",
    "sg:address":"Seestrasse 7",
    "sg:city":"Maur",
    "sg:orig_category":"Grosshandel mit Nahrungsmitteln, Getr\u00e4nken U Tabakwaren",
    "sg:phone":"+41 56 493 03 77",
    "sg:postcode":"8124",
    "sg:province":"Z\u00fcrich",
    "wof:name":"Kurt Eduard Michel Confiserie-import",
    "wof:placetype":"venue"
},
  "geometry": {"coordinates":[8.2906999588,47.4518051147],"type":"Point"}
}