{
  "type": "Feature",
  "properties": {
    "iso:country":"CH",
    "sg:address":"Frikartstrasse 2",
    "sg:city":"Zofingen",
    "sg:orig_category":"Mit dem Versicherungsgewerbe verbundene T\u00e4tigkeiten",
    "sg:postcode":"4800",
    "sg:province":"Aargau",
    "wof:name":"Mitscherlich Florian S.j., Lic. Jur.",
    "wof:placetype":"venue"
},
  "geometry": {"coordinates":[7.9446377754,47.2840919495],"type":"Point"}
}