{
  "type": "Feature",
  "properties": {
    "iso:country":"CH",
    "sg:address":"La Stampa",
    "sg:city":"Canobbio",
    "sg:orig_category":"Herstellung von Werkzeugen Herstellung von sonstigen Werkzeugmaschinen",
    "sg:phone":"+41 19052424",
    "sg:postcode":"6952",
    "sg:province":"Ticino",
    "wof:name":"M\u00e4gerle Ag Maschinenfabrik",
    "wof:placetype":"venue"
},
  "geometry": {"coordinates":[8.9658908844,46.0353431702],"type":"Point"}
}