{
  "type": "Feature",
  "properties": {
    "iso:country":"CH",
    "sg:address":"Dorfstrasse 59",
    "sg:city":"Wettingen",
    "sg:orig_category":"Herstellung von Wein",
    "sg:postcode":"5430",
    "sg:province":"Aargau",
    "wof:name":"Weinbaugenossenschaft Wettingen",
    "wof:placetype":"venue"
},
  "geometry": {"coordinates":[8.331454277,47.4673500061],"type":"Point"}
}