{
  "type": "Feature",
  "properties": {
    "iso:country":"CH",
    "sg:address":"Herrenacker 3",
    "sg:city":"Schaffhausen",
    "sg:orig_category":"Alters U Hinterlassenenversicherung AHV, Invalidenversicherung IV, Arbeitslosenversicherung ALV",
    "sg:phone":"+41 52 632 72 78",
    "sg:postcode":"8200",
    "sg:province":"Schaffhausen",
    "wof:name":"Ausgleichskasse Des Kantons Schaffhausen",
    "wof:placetype":"venue"
},
  "geometry": {"coordinates":[8.633833,47.695248],"type":"Point"}
}