{
  "type": "Feature",
  "properties": {
    "iso:country":"CH",
    "sg:address":"Obere Briggasse 124 3902 Glis. Postfach",
    "sg:city":"Glis",
    "sg:orig_category":"Architektur U Ingenieurb\u00fcros",
    "sg:phone":"+41 27 923 30 62",
    "sg:postcode":"3902",
    "sg:province":"Valais",
    "wof:name":"Architekturb\u00fcro Summermatter",
    "wof:placetype":"venue"
},
  "geometry": {"coordinates":[7.982846,46.306477],"type":"Point"}
}