{
  "type": "Feature",
  "properties": {
    "iso:country":"CH",
    "sg:address":"Muttenzerstrasse 5",
    "sg:city":"Birsfelden",
    "sg:orig_category":"RESTAURANTS: TEA-ROOMS",
    "sg:postcode":"4127",
    "sg:province":"Basel-Landschaft",
    "wof:name":"Alfred Wahl-binda",
    "wof:placetype":"venue"
},
  "geometry": {"coordinates":[7.6241579056,47.5511283875],"type":"Point"}
}