{
  "type": "Feature",
  "properties": {
    "iso:country":"CH",
    "sg:address":"M\u00fcnzgraben 4",
    "sg:city":"Bern",
    "sg:orig_category":"Gelegenheitsflugverkehr",
    "sg:postcode":"3011",
    "sg:province":"Bern",
    "wof:name":"Aircraft Leasing Ltd",
    "wof:placetype":"venue"
},
  "geometry": {"coordinates":[7.4471149445,46.9470748901],"type":"Point"}
}