{
  "type": "Feature",
  "properties": {
    "iso:country":"CH",
    "sg:address":"Leoncavallo Via",
    "sg:city":"Brissago",
    "sg:orig_category":"Tankstellen",
    "sg:phone":"+41 91 608 26 76",
    "sg:postcode":"6614",
    "sg:province":"Ticino",
    "wof:name":"Leonida Govi Stazione Di Benzina Elf",
    "wof:placetype":"venue"
},
  "geometry": {"coordinates":[8.8005199432,45.9927215576],"type":"Point"}
}