{
  "type": "Feature",
  "properties": {
    "iso:country":"CH",
    "sg:address":"Rue De Jargonnant 2",
    "sg:city":"Gen\u00e8ve",
    "sg:orig_category":"Grosshandel mit Datenverarbeitungsger\u00e4ten",
    "sg:phone":"+41 22 707 78 00",
    "sg:postcode":"1207",
    "sg:province":"Gen\u00e8ve",
    "wof:name":"Sun Microsystems (suisse) Sa, Succursale De Gen\u00e8ve",
    "wof:placetype":"venue"
},
  "geometry": {"coordinates":[6.1597938538,46.2011184692],"type":"Point"}
}