{
  "type": "Feature",
  "properties": {
    "iso:country":"CH",
    "sg:address":"Brittnauerstrasse 3",
    "sg:city":"Strengelbach",
    "sg:orig_category":"Wasserversorgung",
    "sg:phone":"+41 62 746 03 20",
    "sg:postcode":"4802",
    "sg:province":"Aargau",
    "wof:name":"Wasserversorgung Gemeindeverwaltung",
    "wof:placetype":"venue"
},
  "geometry": {"coordinates":[7.9302048683,47.2781181335],"type":"Point"}
}