{
  "type": "Feature",
  "properties": {
    "iso:country":"CH",
    "sg:address":"Wagistr. 13 Postfach",
    "sg:city":"Schlieren",
    "sg:classifiers":[
        {
            "category":"Manufacturing",
            "subcategory":"Paper Products",
            "type":"Manufacturing & Wholesale Goods"
        }
    ],
    "sg:phone":"+41 31 340 89 00",
    "sg:postcode":"8952",
    "sg:province":"Z\u00fcrich",
    "sg:tags":[
        "raw",
        "material",
        "-",
        "cardboard"
    ],
    "wof:name":"Mpa Multitec Polygraph Ag",
    "wof:placetype":"venue"
},
  "geometry": {"coordinates":[7.4001741409,46.9423446655],"type":"Point"}
}