{
  "type": "Feature",
  "properties": {
    "iso:country":"CH",
    "sg:address":"Seefeldstrasse 56 8008 Z\u00fcrich. Postfach",
    "sg:city":"Z\u00fcrich",
    "sg:orig_category":"Erbringung von Dienstleistungen f\u00fcr Unternehmen Herstellung von Herren U Knabenoberbekleidung",
    "sg:phone":"+41 12626286",
    "sg:postcode":"8001",
    "sg:province":"Z\u00fcrich",
    "wof:name":"Berlin Patrice Design Fashion-atelier, Inhaberin Bachmann P. Fashion-atelier. Eigenkollektionen, Masskonfektionen; Entwurf, Verkauf",
    "wof:placetype":"venue"
},
  "geometry": {"coordinates":[8.5503616333,47.3623428345],"type":"Point"}
}