{
  "type": "Feature",
  "properties": {
    "iso:country":"CH",
    "sg:address":"Kirchstrasse 6 6205 Eich. Postfach 9",
    "sg:city":"Eich",
    "sg:orig_category":"Wirtschaftspr\u00fcfung, Steuerberatung U Treuhand",
    "sg:phone":"+41 41 460 15 37",
    "sg:postcode":"6205",
    "sg:province":"Luzern",
    "wof:name":"Amgwerd Christian Revisions Und Beratungs Ag",
    "wof:placetype":"venue"
},
  "geometry": {"coordinates":[8.1654138565,47.1545982361],"type":"Point"}
}