{
  "type": "Feature",
  "properties": {
    "iso:country":"CH",
    "sg:address":"Rathausplatz 3.",
    "sg:city":"Glarus",
    "sg:orig_category":"Fachdetailhandel in Verkaufsr\u00e4umen",
    "sg:postcode":"8750",
    "sg:province":"Glarus",
    "wof:name":"Nystrup Mathilde, Bijouterie & Uhren.",
    "wof:placetype":"venue"
},
  "geometry": {"coordinates":[9.0683679581,47.0401573181],"type":"Point"}
}