{
  "type": "Feature",
  "properties": {
    "iso:country":"CH",
    "sg:address":"St. Johanns-ring 18",
    "sg:city":"Basel",
    "sg:orig_category":"Detailhandel Reparatur von Gebrauchsg\u00fctern",
    "sg:phone":"+41 71 911 85 65",
    "sg:postcode":"4056",
    "sg:province":"Basel-Stadt",
    "wof:name":"Erotik-shop Altstadt-erothek",
    "wof:placetype":"venue"
},
  "geometry": {"coordinates":[9.0484819412,47.4656600952],"type":"Point"}
}