{
  "type": "Feature",
  "properties": {
    "iso:country":"CH",
    "sg:address":"Werkstrasse 4",
    "sg:city":"K\u00e4giswil",
    "sg:orig_category":"Autospenglereien",
    "sg:phone":"+41 41 497 32 50",
    "sg:postcode":"6056",
    "sg:province":"Obwalden",
    "wof:name":"Walter Fuchs Carrosserie",
    "wof:placetype":"venue"
},
  "geometry": {"coordinates":[8.14518,47.03598],"type":"Point"}
}