{
  "type": "Feature",
  "properties": {
    "iso:country":"CH",
    "sg:address":"Kirchbergstrasse 1",
    "sg:city":"Thundorf",
    "sg:orig_category":"Digital Indicators",
    "sg:phone":"+41 32 968 49 55",
    "sg:postcode":"8512",
    "sg:province":"Thurgau",
    "wof:name":"Gefran Acome S.a.",
    "wof:placetype":"venue"
},
  "geometry": {"coordinates":[6.83698,47.105396],"type":"Point"}
}