{
  "type": "Feature",
  "properties": {
    "iso:country":"CH",
    "sg:address":"Wohlerstrasse 16",
    "sg:city":"Fischbach-g\u00f6slikon",
    "sg:orig_category":"Sportvereine Ballsport Handball",
    "sg:phone":"+41 56 622 48 28",
    "sg:postcode":"5525",
    "sg:province":"Aargau",
    "wof:name":"Handballclub Tv Mellingen",
    "wof:placetype":"venue"
},
  "geometry": {"coordinates":[8.3029565811,47.3711891174],"type":"Point"}
}