{
  "type": "Feature",
  "properties": {
    "iso:country":"CH",
    "sg:address":"Rebbergstrasse 45d",
    "sg:city":"Ennetbaden",
    "sg:orig_category":"Erbringung von Dienstleistungen f\u00fcr Unternehmen Werbegrafikateliers",
    "sg:phone":"+41 56 222 78 24",
    "sg:postcode":"5408",
    "sg:province":"Aargau",
    "wof:name":"Native Heller & Co Gestaltungen",
    "wof:placetype":"venue"
},
  "geometry": {"coordinates":[8.3214063644,47.4824523926],"type":"Point"}
}