{
  "type": "Feature",
  "properties": {
    "iso:country":"CH",
    "sg:address":"Avenue De Ch\u00e2telaine 87",
    "sg:city":"Ch\u00e2telaine",
    "sg:orig_category":"Non-Classified Establishments",
    "sg:postcode":"1219",
    "sg:province":"Gen\u00e8ve",
    "wof:name":"Tedene S\u00e0rl Rev\u00eatement De Sol Parquets",
    "wof:placetype":"venue"
},
  "geometry": {"coordinates":[6.1122832298,46.210723877],"type":"Point"}
}