{
  "type": "Feature",
  "properties": {
    "iso:country":"CH",
    "sg:address":"Steinechtweg 14",
    "sg:city":"Itingen",
    "sg:orig_category":"Forschung U Entwicklung im Bereich der Naturwissenschaften",
    "sg:phone":"+41 61 973 06 06",
    "sg:postcode":"4452",
    "sg:province":"Basel-Landschaft",
    "wof:name":"Rippmann Dorothee Cliodora",
    "wof:placetype":"venue"
},
  "geometry": {"coordinates":[7.7842202187,47.4707298279],"type":"Point"}
}