{
  "type": "Feature",
  "properties": {
    "iso:country":"CH",
    "sg:address":"H\u00fceblistrasse",
    "sg:city":"Kaltbrunn",
    "sg:orig_category":"Hoch U Tiefbau",
    "sg:phone":"+41 17409988",
    "sg:postcode":"8722",
    "sg:province":"St. Gallen",
    "wof:name":"Urs Thalmann Bauunternehmung",
    "wof:placetype":"venue"
},
  "geometry": {"coordinates":[8.3967628479,47.4004592896],"type":"Point"}
}