{
  "type": "Feature",
  "properties": {
    "iso:country":"CH",
    "sg:address":"Rte Du Grand-lancy 6 1213 Petit-lancy. Postfach",
    "sg:city":"Grand-lancy",
    "sg:orig_category":"Herstellung von Ausbauelementen aus Metall",
    "sg:postcode":"1212",
    "sg:province":"Gen\u00e8ve",
    "wof:name":"Gr Entreprise, Rizzo G.",
    "wof:placetype":"venue"
},
  "geometry": {"coordinates":[6.1263852119,46.1878356934],"type":"Point"}
}