{
  "type": "Feature",
  "properties": {
    "addr:full":"Rue Centrale 47 Moutier Bern 2740",
    "addr:housenumber":"47",
    "addr:postcode":"2740",
    "addr:street":"Rue Centrale;Bern",
    "iso:country":"CH",
    "sg:address":"Rue Centrale 47",
    "sg:city":"Moutier",
    "sg:classifiers":[
        {
            "category":"Banks & Credit Unions",
            "subcategory":"Bank",
            "type":"Services"
        }
    ],
    "sg:phone":"+41 32945945",
    "sg:postcode":"2740",
    "sg:province":"Bern",
    "wof:name":"Banque Populaire Suisse",
    "wof:placetype":"venue"
},
  "geometry": {"coordinates":[7.37381,47.279488],"type":"Point"}
}