{
  "type": "Feature",
  "properties": {
    "iso:country":"CH",
    "sg:address":"6718",
    "sg:city":"Olivone",
    "sg:orig_category":"Allgemeiner Hoch U Tiefbau",
    "sg:phone":"+41 79 221 65 04",
    "sg:postcode":"6718",
    "sg:province":"Ticino",
    "wof:name":"Bianchi Edgardo Sagl",
    "wof:placetype":"venue"
},
  "geometry": {"coordinates":[8.93906,46.528801],"type":"Point"}
}