{
  "type": "Feature",
  "properties": {
    "iso:country":"CH",
    "sg:address":"Aeschenvorstadt 41 4051 Basel. Postfach",
    "sg:city":"Basel",
    "sg:orig_category":"Unclassifiable Establishments",
    "sg:postcode":"4051",
    "sg:province":"Basel-Stadt",
    "wof:name":"Teligaro Inc. Beteiligungen Usw",
    "wof:placetype":"venue"
},
  "geometry": {"coordinates":[7.5934281349,47.5526847839],"type":"Point"}
}