{
  "type": "Feature",
  "properties": {
    "iso:country":"CH",
    "sg:address":"Rue Centrale 63 2500 Biel/bienne. Postfach",
    "sg:city":"Biel/bienne",
    "sg:orig_category":"Herstellung von keramischen Haushaltswaren U Ziergegenst\u00e4nden",
    "sg:postcode":"2502",
    "sg:province":"Bern",
    "wof:name":"Lachat & Girardin",
    "wof:placetype":"venue"
},
  "geometry": {"coordinates":[7.2481870651,47.1356277466],"type":"Point"}
}