{
  "type": "Feature",
  "properties": {
    "iso:country":"CH",
    "sg:address":"Dammstrasse 21",
    "sg:city":"Solothurn",
    "sg:orig_category":"Unclassifiable Establishments",
    "sg:phone":"+41 32 623 21 23",
    "sg:postcode":"4500",
    "sg:province":"Solothurn",
    "wof:name":"Special Situation Holding Ag",
    "wof:placetype":"venue"
},
  "geometry": {"coordinates":[7.5324511528,47.205871582],"type":"Point"}
}