{
  "type": "Feature",
  "properties": {
    "iso:country":"CH",
    "sg:address":"Pfyn",
    "sg:city":"Susten",
    "sg:orig_category":"Campingpl\u00e4tze Detailhandel mit Zeitungen U Zeitschriften Kioske",
    "sg:phone":"+41 21 784 12 45",
    "sg:postcode":"3952",
    "sg:province":"Valais",
    "wof:name":"Camping Du Praz-collet",
    "wof:placetype":"venue"
},
  "geometry": {"coordinates":[6.68767,46.559551],"type":"Point"}
}