{
  "type": "Feature",
  "properties": {
    "iso:country":"CH",
    "sg:address":"Kirchgasse 1",
    "sg:city":"Russikon",
    "sg:orig_category":"Werbung",
    "sg:postcode":"8332",
    "sg:province":"Z\u00fcrich",
    "wof:name":"Rita Huber, Public Relations Marketing Communication",
    "wof:placetype":"venue"
},
  "geometry": {"coordinates":[8.7764377594,47.3945770264],"type":"Point"}
}