{
  "type": "Feature",
  "properties": {
    "iso:country":"CH",
    "sg:address":"Greifenseestrasse 59",
    "sg:city":"Schwerzenbach",
    "sg:orig_category":"Unternehmensberatung",
    "sg:postcode":"8603",
    "sg:province":"Z\u00fcrich",
    "wof:name":"E. Auf Der Maur Treuhand Und Verwaltungen",
    "wof:placetype":"venue"
},
  "geometry": {"coordinates":[8.6623926163,47.3764419556],"type":"Point"}
}