{
  "type": "Feature",
  "properties": {
    "iso:country":"CH",
    "sg:address":"Oberhusestrasse 30",
    "sg:city":"Marthalen",
    "sg:orig_category":"Sonstige Aktivit\u00e4ten der nicht-\u00e4rztlichen Medizinalberufe",
    "sg:phone":"+41 52 319 29 31",
    "sg:postcode":"8460",
    "sg:province":"Z\u00fcrich",
    "wof:name":"Silvia N\u00e4geli Kinesiologie",
    "wof:placetype":"venue"
},
  "geometry": {"coordinates":[8.656291008,47.6238059998],"type":"Point"}
}