{
  "type": "Feature",
  "properties": {
    "iso:country":"CH",
    "sg:address":"Via Carlo Maderno 10",
    "sg:city":"Lugano",
    "sg:orig_category":"Unclassifiable Establishments",
    "sg:postcode":"6900",
    "sg:province":"Ticino",
    "wof:name":"Studio D'ingegneria Giorgio Petoud",
    "wof:placetype":"venue"
},
  "geometry": {"coordinates":[8.9550743103,46.0090675354],"type":"Point"}
}