{
  "type": "Feature",
  "properties": {
    "addr:full":"Schachen Inwil Luzern 6034",
    "addr:postcode":"6034",
    "addr:street":"Schachen",
    "iso:country":"CH",
    "sg:address":"Schachen",
    "sg:city":"Inwil",
    "sg:orig_category":"Allgemeiner Hoch U Tiefbau Allgemeiner Hochbau",
    "sg:phone":"+41 41 449 41 70",
    "sg:postcode":"6034",
    "sg:province":"Luzern",
    "wof:name":"Batigroup Ag Werkhof",
    "wof:placetype":"venue"
},
  "geometry": {"coordinates":[8.341493,47.121136],"type":"Point"}
}