{
  "type": "Feature",
  "properties": {
    "iso:country":"CH",
    "sg:address":"Poststrasse 10",
    "sg:city":"Heiden",
    "sg:orig_category":"Massagestudios Naturheil\u00e4rzte and Heilpraktiker",
    "sg:phone":"+41 71 891 64 81",
    "sg:postcode":"9410",
    "sg:province":"Appenzell Ausserrhoden",
    "wof:name":"Kathrin Bollhalder Natur\u00e4rztin & Massagen",
    "wof:placetype":"venue"
},
  "geometry": {"coordinates":[9.5358285904,47.4442062378],"type":"Point"}
}