{
  "type": "Feature",
  "properties": {
    "iso:country":"CH",
    "sg:address":"Doossenweg 6",
    "sg:city":"Gr\u00e4nichen",
    "sg:orig_category":"Hardwareberatung",
    "sg:postcode":"5722",
    "sg:province":"Aargau",
    "wof:name":"Wyscha Ag",
    "wof:placetype":"venue"
},
  "geometry": {"coordinates":[8.1484870911,47.4461021423],"type":"Point"}
}