{
  "type": "Feature",
  "properties": {
    "iso:country":"CH",
    "sg:address":"Kreuzstrasse 4 8712 St\u00e4fa. Postfach 469",
    "sg:city":"St\u00e4fa",
    "sg:orig_category":"Handelsvermittlung U Grosshandel Herstellung von Metallkonstruktionen",
    "sg:phone":"+41 41 921 90 00",
    "sg:postcode":"8712",
    "sg:province":"Z\u00fcrich",
    "wof:name":"Lkt Lager + Kommissioniertechnik Gmbh",
    "wof:placetype":"venue"
},
  "geometry": {"coordinates":[8.1159219742,47.1648597717],"type":"Point"}
}