{
  "type": "Feature",
  "properties": {
    "iso:country":"CH",
    "sg:address":"Grand-rue",
    "sg:city":"Ch\u00e2teau-d'oex",
    "sg:orig_category":"Detailhandel mit Fleisch U Fleischwaren",
    "sg:phone":"+41 26 924 78 81",
    "sg:postcode":"1837",
    "wof:name":"Patrick & Eliane Buchs Boucherie-laiterie Du Village",
    "wof:placetype":"venue"
},
  "geometry": {"coordinates":[0.9477999806,45.3775024414],"type":"Point"}
}