{
  "type": "Feature",
  "properties": {
    "iso:country":"CH",
    "sg:address":"Hammerstrasse 151",
    "sg:city":"Basel",
    "sg:orig_category":"Unclassifiable Establishments",
    "sg:postcode":"4057",
    "sg:province":"Basel-Stadt",
    "wof:name":"Aida Solutions Schaub",
    "wof:placetype":"venue"
},
  "geometry": {"coordinates":[7.5946350098,47.5682449341],"type":"Point"}
}