{
  "type": "Feature",
  "properties": {
    "iso:country":"CH",
    "sg:address":"Stegstrasse 17",
    "sg:city":"W\u00e4denswil",
    "sg:orig_category":"Gymnastik U Fitnesszentren",
    "sg:phone":"+41 17806252",
    "sg:postcode":"8820",
    "sg:province":"Z\u00fcrich",
    "wof:name":"Fit-in-corner Fitness-center",
    "wof:placetype":"venue"
},
  "geometry": {"coordinates":[8.6678371429,47.2313041687],"type":"Point"}
}