{
  "type": "Feature",
  "properties": {
    "iso:country":"CH",
    "sg:address":"Arsenalstrasse 30",
    "sg:city":"Kriens",
    "sg:orig_category":"Innenausbau Zimmerei, Ingenieurholzbau",
    "sg:phone":"+41 41 210 87 44",
    "sg:postcode":"6010",
    "sg:province":"Luzern",
    "wof:name":"Weber Otto S\u00f6hne Zimmerei U. Schreinerei",
    "wof:placetype":"venue"
},
  "geometry": {"coordinates":[8.2962064743,47.033241272],"type":"Point"}
}