{
  "type": "Feature",
  "properties": {
    "iso:country":"CH",
    "sg:address":"Bielstrasse 12",
    "sg:city":"M\u00fcnchenbuchsee",
    "sg:orig_category":"Physiotherapie",
    "sg:phone":"+41 79 290 28 47",
    "sg:postcode":"3053",
    "sg:province":"Bern",
    "wof:name":"Thomas O'donnell Physioth\u00e9rapie De La Vall\u00e9e",
    "wof:placetype":"venue"
},
  "geometry": {"coordinates":[6.2354202271,46.6116218567],"type":"Point"}
}