{
  "type": "Feature",
  "properties": {
    "iso:country":"CH",
    "sg:address":"Reichenstein",
    "sg:city":"Oeschseite",
    "sg:orig_category":"Fuhrhaltereien",
    "sg:phone":"+41 79 208 97 79",
    "sg:postcode":"3776",
    "sg:province":"Bern",
    "wof:name":"Heinz Schwarz Fuhrhalterei",
    "wof:placetype":"venue"
},
  "geometry": {"coordinates":[7.3482899666,46.5293502808],"type":"Point"}
}