{
  "type": "Feature",
  "properties": {
    "iso:country":"CH",
    "sg:address":"B\u00fcnishoferstrasse 224",
    "sg:city":"Feldmeilen",
    "sg:orig_category":"Detailhandel mit Uhren U Schmuck",
    "sg:phone":"+41 79 446 77 47",
    "sg:postcode":"8706",
    "sg:province":"Z\u00fcrich",
    "wof:name":"B\u00e4r's Goldshop Martin B\u00e4r Schmuckmacherei",
    "wof:placetype":"venue"
},
  "geometry": {"coordinates":[8.6244630814,47.2822723389],"type":"Point"}
}