{
  "type": "Feature",
  "properties": {
    "iso:country":"CH",
    "sg:address":"Bernerstrasse Nord 206",
    "sg:city":"Z\u00fcrich",
    "sg:orig_category":"Geb\u00e4ude, Wohnungsreinigung Reinigungsgewerbe",
    "sg:phone":"+41 61 821 78 88",
    "sg:postcode":"8064",
    "sg:province":"Z\u00fcrich",
    "wof:name":"Rieder Peter, Geb\u00e4ude Und Unterhaltsreinigung",
    "wof:placetype":"venue"
},
  "geometry": {"coordinates":[7.6911668777,47.5182151794],"type":"Point"}
}