{
  "type": "Feature",
  "properties": {
    "iso:country":"CH",
    "sg:address":"Litternaring",
    "sg:city":"Visp",
    "sg:orig_category":"RESTAURANTS: TEA-ROOMS",
    "sg:postcode":"3930",
    "sg:province":"Valais",
    "wof:name":"Restaurant-bar Sonne, Gasser Manfred",
    "wof:placetype":"venue"
},
  "geometry": {"coordinates":[7.886496067,46.2927093506],"type":"Point"}
}