{
  "type": "Feature",
  "properties": {
    "iso:country":"CH",
    "sg:address":"Chemin De La Fruti\u00e8re 11",
    "sg:city":"Savigny",
    "sg:orig_category":"Mechanische Werkst\u00e4tten",
    "sg:phone":"+41 32 913 06 47",
    "sg:postcode":"1073",
    "sg:province":"Vaud",
    "wof:name":"Michel Rosselet Atelier \u00e9lectrom\u00e9canique",
    "wof:placetype":"venue"
},
  "geometry": {"coordinates":[6.8239040375,47.1004867554],"type":"Point"}
}