{
  "type": "Feature",
  "properties": {
    "iso:country":"CH",
    "sg:address":"H\u00e4dilochstrasse 44a",
    "sg:city":"Niederurnen",
    "sg:orig_category":"RESTAURANTS: TEA-ROOMS",
    "sg:postcode":"8867",
    "sg:province":"Glarus",
    "wof:name":"Schl\u00f6ssli-genossenschaft Niederurnen.",
    "wof:placetype":"venue"
},
  "geometry": {"coordinates":[9.0474596024,47.1251487732],"type":"Point"}
}