{
  "type": "Feature",
  "properties": {
    "iso:country":"CH",
    "sg:address":"Bahnhofplatz 7",
    "sg:city":"Visp",
    "sg:orig_category":"Zahnarztpraxen",
    "sg:phone":"+41 27 948 11 00",
    "sg:postcode":"3930",
    "sg:province":"Valais",
    "wof:name":"Dr.med.dent.jean-l. Heinzmann Zahnarzt",
    "wof:placetype":"venue"
},
  "geometry": {"coordinates":[7.8819918633,46.2933006287],"type":"Point"}
}