{
  "type": "Feature",
  "properties": {
    "iso:country":"CH",
    "sg:address":"Kantonsstrasse 8",
    "sg:city":"Visp",
    "sg:orig_category":"Warenh\u00e4user",
    "sg:phone":"+41 27 946 10 12",
    "sg:postcode":"3930",
    "sg:province":"Valais",
    "wof:name":"Loeb Ag Bern",
    "wof:placetype":"venue"
},
  "geometry": {"coordinates":[7.8808178902,46.2921562195],"type":"Point"}
}