{
  "type": "Feature",
  "properties": {
    "iso:country":"CH",
    "sg:address":"Rue Baulacre 13",
    "sg:city":"Gen\u00e8ve",
    "sg:orig_category":"Detailhandel mit Getr\u00e4nken Grosshandel mit Getr\u00e4nken",
    "sg:phone":"+41 22 343 79 33",
    "sg:postcode":"1202",
    "sg:province":"Gen\u00e8ve",
    "wof:name":"Cave Blavignac Sa Commerce De Vins",
    "wof:placetype":"venue"
},
  "geometry": {"coordinates":[6.1318149567,46.1804046631],"type":"Point"}
}