{
  "type": "Feature",
  "properties": {
    "iso:country":"CH",
    "sg:address":"Hegnauweg 16",
    "sg:city":"Z\u00fcrich",
    "sg:orig_category":"Sonstige k\u00fcnstlerische U schriftstellerische T\u00e4tigkeiten U Darbietungen",
    "sg:phone":"+41 13021508",
    "sg:postcode":"8052",
    "sg:province":"Z\u00fcrich",
    "wof:name":"Ernst Liebing Kunstgewerbliches Atelier",
    "wof:placetype":"venue"
},
  "geometry": {"coordinates":[8.5501861572,47.4204978943],"type":"Point"}
}