{
  "type": "Feature",
  "properties": {
    "iso:country":"CH",
    "sg:address":"En Reutet C Collombey-le-grand",
    "sg:city":"Collombey",
    "sg:orig_category":"Sonstiger Grosshandel",
    "sg:postcode":"1868",
    "sg:province":"Valais",
    "wof:name":"Spycher Et Stancu-romstar",
    "wof:placetype":"venue"
},
  "geometry": {"coordinates":[6.9433250427,46.277961731],"type":"Point"}
}