{
  "type": "Feature",
  "properties": {
    "iso:country":"CH",
    "sg:address":"R\u00f6merstrasse 3",
    "sg:city":"Dietikon",
    "sg:orig_category":"Detailhandel mit Schuhen U Lederwaren",
    "sg:postcode":"8953",
    "sg:province":"Z\u00fcrich",
    "wof:name":"Rodi Gmbh",
    "wof:placetype":"venue"
},
  "geometry": {"coordinates":[8.3964586258,47.4059791565],"type":"Point"}
}