{
  "type": "Feature",
  "properties": {
    "iso:country":"CH",
    "sg:address":"Fridgasse 24",
    "sg:city":"H\u00e4gendorf",
    "sg:orig_category":"Massagestudios",
    "sg:phone":"+41 81 826 51 63",
    "sg:postcode":"4614",
    "sg:province":"Solothurn",
    "wof:name":"Erika Rominger Sportmassagen",
    "wof:placetype":"venue"
},
  "geometry": {"coordinates":[9.7647953033,46.4297714233],"type":"Point"}
}