{
  "type": "Feature",
  "properties": {
    "iso:country":"CH",
    "sg:address":"Kasernenstrasse 12",
    "sg:city":"Liestal",
    "sg:orig_category":"Wirtschaftspr\u00fcfung, Steuerberatung U Treuhand",
    "sg:phone":"+41 61 921 12 95",
    "sg:postcode":"4410",
    "sg:province":"Basel-Landschaft",
    "wof:name":"B\u00fcrgin Ernst",
    "wof:placetype":"venue"
},
  "geometry": {"coordinates":[7.7367138863,47.4824981689],"type":"Point"}
}