{
  "type": "Feature",
  "properties": {
    "iso:country":"CH",
    "sg:address":"M\u00fchligasse 2",
    "sg:city":"Wimmis",
    "sg:orig_category":"Erbringung von Dienstleistungen f\u00fcr Unternehmen Herstellung von Reiseartikeln, Leder U Sattlerwaren",
    "sg:phone":"+41 79 432 95 50",
    "sg:postcode":"3752",
    "sg:province":"Bern",
    "wof:name":"Wyttenbach Innendekorationen",
    "wof:placetype":"venue"
},
  "geometry": {"coordinates":[7.6376719475,46.6742897034],"type":"Point"}
}