{
  "type": "Feature",
  "properties": {
    "iso:country":"CH",
    "sg:address":"Melchtalerstrasse 11b",
    "sg:city":"Kerns",
    "sg:orig_category":"Verlegen von Fliesen U Platten",
    "sg:phone":"+41 41 660 36 80",
    "sg:postcode":"6064",
    "sg:province":"Obwalden",
    "wof:name":"Alfred Baumgartner Plattenbel\u00e4ge & Chemin\u00e9ebau",
    "wof:placetype":"venue"
},
  "geometry": {"coordinates":[8.2767658234,46.8996734619],"type":"Point"}
}