{
  "type": "Feature",
  "properties": {
    "iso:country":"CH",
    "sg:address":"8002 Z\u00fcrich. Postfach",
    "sg:city":"Z\u00fcrich",
    "sg:orig_category":"Wirtschaftspr\u00fcfung, Steuerberatung U Treuhand",
    "sg:phone":"+41 12025500",
    "sg:postcode":"8039",
    "wof:name":"Rist Ag Inkasso-& Treuhandgesch\u00e4fte",
    "wof:placetype":"venue"
},
  "geometry": {"coordinates":[8.5352401733,47.3541717529],"type":"Point"}
}