{
  "type": "Feature",
  "properties": {
    "iso:country":"CH",
    "sg:address":"Schulhausstrasse 147 3465 D\u00fcrrenroth. Postfach",
    "sg:city":"D\u00fcrrenroth",
    "sg:orig_category":"Elektroinstallation",
    "sg:phone":"+41 19723939",
    "sg:postcode":"3465",
    "sg:province":"Bern",
    "wof:name":"Elektrotech Gmbh Elektrische Anlagen; Projektierung, Bau Usw",
    "wof:placetype":"venue"
},
  "geometry": {"coordinates":[8.7637166977,47.3014030457],"type":"Point"}
}