{
  "type": "Feature",
  "properties": {
    "iso:country":"CH",
    "sg:address":"Rennweg 19 4052 Basel. Postfach",
    "sg:city":"Basel",
    "sg:orig_category":"Interessenvertretungen",
    "sg:postcode":"4051",
    "sg:province":"Basel-Stadt",
    "wof:name":"Stiftung F\u00fcr Die Griechisch-orthodoxe Gemeinde Basel",
    "wof:placetype":"venue"
},
  "geometry": {"coordinates":[7.6053981781,47.5512084961],"type":"Point"}
}