{
  "type": "Feature",
  "properties": {
    "iso:country":"CH",
    "sg:address":"Rte Des Moui\u00e8res 5",
    "sg:city":"Satigny",
    "sg:orig_category":"Detailhandel mit B\u00fcchern, Zeitungen, Schreib U Papeteriewaren",
    "sg:phone":"+41 22 939 49 39",
    "sg:postcode":"1242",
    "sg:province":"Gen\u00e8ve",
    "wof:name":"Office Culturel Sa",
    "wof:placetype":"venue"
},
  "geometry": {"coordinates":[6.033025,46.215488],"type":"Point"}
}