{
  "type": "Feature",
  "properties": {
    "iso:country":"CH",
    "sg:address":"Dorfstrasse 33",
    "sg:city":"Uetendorf",
    "sg:orig_category":"Nationale Postdienste",
    "sg:phone":"+41 33 345 11 05",
    "sg:postcode":"3661",
    "sg:province":"Bern",
    "wof:name":"Die Schweizerische Post",
    "wof:placetype":"venue"
},
  "geometry": {"coordinates":[7.5737571716,46.7738456726],"type":"Point"}
}