{
  "type": "Feature",
  "properties": {
    "iso:country":"CH",
    "sg:address":"4106",
    "sg:city":"Therwil",
    "sg:orig_category":"Primarschulen",
    "sg:postcode":"4106",
    "sg:province":"Basel-Landschaft",
    "wof:name":"Primarschule M\u00fchleboden",
    "wof:placetype":"venue"
},
  "geometry": {"coordinates":[7.5566749573,47.4990844727],"type":"Point"}
}