{
  "type": "Feature",
  "properties": {
    "iso:country":"CH",
    "sg:address":"B\u00e4umlis\u00e4cherstrasse 14",
    "sg:city":"Wettswil",
    "sg:orig_category":"Vereine Vogel-& Naturschutz",
    "sg:phone":"+41 17000405",
    "sg:postcode":"8907",
    "sg:province":"Z\u00fcrich",
    "wof:name":"Natur-& Vogelschutzverein",
    "wof:placetype":"venue"
},
  "geometry": {"coordinates":[8.4704399109,47.3428993225],"type":"Point"}
}