{
  "type": "Feature",
  "properties": {
    "iso:country":"CH",
    "sg:address":"Hauptstrasse 64",
    "sg:city":"Weite",
    "sg:orig_category":"Elektroinstallation Sanit\u00e4rinstallation",
    "sg:phone":"+41 71 637 70 80",
    "sg:postcode":"9476",
    "sg:province":"St. Gallen",
    "wof:name":"Atel Elektrosanit\u00e4r Ag",
    "wof:placetype":"venue"
},
  "geometry": {"coordinates":[9.1639251709,47.5781211853],"type":"Point"}
}