{
  "type": "Feature",
  "properties": {
    "iso:country":"CH",
    "sg:address":"Weinbergstrasse 68 8006 Z\u00fcrich. Postfach",
    "sg:city":"Z\u00fcrich",
    "sg:orig_category":"Wirtschaftspr\u00fcfung, Steuerberatung U Treuhand",
    "sg:postcode":"8001",
    "sg:province":"Z\u00fcrich",
    "wof:name":"Quo Treuhand, Quadroni R.",
    "wof:placetype":"venue"
},
  "geometry": {"coordinates":[8.5437774658,47.3825263977],"type":"Point"}
}