{
  "type": "Feature",
  "properties": {
    "iso:country":"CH",
    "sg:address":"S\u00fcesswinkel 7",
    "sg:city":"Luzern",
    "sg:orig_category":"Finanzierungsinstitutionen",
    "sg:phone":"+41 41 370 53 33",
    "sg:postcode":"6003",
    "sg:province":"Luzern",
    "wof:name":"Consultimpex Verwaltungs Ag",
    "wof:placetype":"venue"
},
  "geometry": {"coordinates":[8.3046245575,47.0525665283],"type":"Point"}
}