{
  "type": "Feature",
  "properties": {
    "iso:country":"CH",
    "sg:address":"Birrfeldstrasse 12",
    "sg:city":"M\u00fclligen",
    "sg:orig_category":"Vermietung U Verpachtung von eigenen Immobilien",
    "sg:postcode":"5243",
    "sg:province":"Aargau",
    "wof:name":"Diodorina Ag",
    "wof:placetype":"venue"
},
  "geometry": {"coordinates":[8.2393426895,47.4561882019],"type":"Point"}
}