{
  "type": "Feature",
  "properties": {
    "iso:country":"CH",
    "sg:address":"Rue Du Rh\u00f4ne 65",
    "sg:city":"Gen\u00e8ve",
    "sg:orig_category":"Detailhandel mit Damenbekleidung Detailhandel mit Lederwaren U Reiseartikeln",
    "sg:phone":"+41 81 833 49 81",
    "sg:postcode":"1204",
    "sg:province":"Gen\u00e8ve",
    "wof:name":"Herm\u00e8s (suisse) Sa",
    "wof:placetype":"venue"
},
  "geometry": {"coordinates":[9.8399858475,46.4980926514],"type":"Point"}
}