{
  "type": "Feature",
  "properties": {
    "iso:country":"CH",
    "sg:address":"Ringstrasse 2 7000 Chur. Postfach",
    "sg:city":"Chur",
    "sg:orig_category":"Allgemeiner Hoch U Tiefbau ohne ausgepr\u00e4gten Schwerpunkt",
    "sg:phone":"+41 81 257 71 11",
    "sg:postcode":"7001",
    "sg:province":"Graubunden",
    "wof:name":"Kantonspolizei",
    "wof:placetype":"venue"
},
  "geometry": {"coordinates":[9.514885,46.847462],"type":"Point"}
}