{
  "type": "Feature",
  "properties": {
    "iso:country":"CH",
    "sg:address":"1687",
    "sg:city":"Vuisternens-romont",
    "sg:orig_category":"Landw. Genossenschaften Viehzucht",
    "sg:postcode":"1687",
    "sg:province":"Fribourg",
    "wof:name":"Syndicat D'\u00e9levage De La Race Tachet\u00e9e Rouge",
    "wof:placetype":"venue"
},
  "geometry": {"coordinates":[6.9288702011,46.6563987732],"type":"Point"}
}