{
  "type": "Feature",
  "properties": {
    "iso:country":"CH",
    "sg:address":"Utoquai 43",
    "sg:city":"Z\u00fcrich",
    "sg:orig_category":"Advokaturb\u00fcros",
    "sg:phone":"+41 12521065",
    "sg:postcode":"8008",
    "sg:province":"Z\u00fcrich",
    "wof:name":"Dr.werner Zuppinger Advokatorb\u00fcro",
    "wof:placetype":"venue"
},
  "geometry": {"coordinates":[8.547084,47.363216],"type":"Point"}
}