{
  "type": "Feature",
  "properties": {
    "iso:country":"CH",
    "sg:address":"Via Calloni 11",
    "sg:city":"Lugano",
    "sg:orig_category":"Herstellung von Betonerzeugnissen f\u00fcr den Bau",
    "sg:postcode":"6900",
    "sg:province":"Ticino",
    "wof:name":"Rossi Leone",
    "wof:placetype":"venue"
},
  "geometry": {"coordinates":[8.9428606033,45.9929084778],"type":"Point"}
}