{
  "type": "Feature",
  "properties": {
    "iso:country":"CH",
    "sg:address":"Gr\u00fcnfeldstrasse 25",
    "sg:city":"Jona",
    "sg:orig_category":"Unclassifiable Establishments",
    "sg:phone":"+41 55 212 25 16",
    "sg:postcode":"8645",
    "sg:province":"St. Gallen",
    "wof:name":"M.c.m. Service Gmbh",
    "wof:placetype":"venue"
},
  "geometry": {"coordinates":[8.8478097916,47.2215881348],"type":"Point"}
}