{
  "type": "Feature",
  "properties": {
    "iso:country":"CH",
    "sg:address":"Hauptstrasse 32",
    "sg:city":"Balgach",
    "sg:orig_category":"Detailhandel mit Fleisch U Fleischwaren",
    "sg:phone":"+41 71 722 21 80",
    "sg:postcode":"9436",
    "sg:province":"St. Gallen",
    "wof:name":"Huber Hermann.",
    "wof:placetype":"venue"
},
  "geometry": {"coordinates":[9.6093597412,47.4073486328],"type":"Point"}
}