{
  "type": "Feature",
  "properties": {
    "iso:country":"CH",
    "sg:address":"Siggehuse",
    "sg:city":"Sch\u00fcpfheim",
    "sg:orig_category":"Grosshandel mit lebenden Tieren",
    "sg:phone":"+41 41 484 21 45",
    "sg:postcode":"6170",
    "sg:province":"Luzern",
    "wof:name":"Josef Studer Viehhandel",
    "wof:placetype":"venue"
},
  "geometry": {"coordinates":[8.0141496658,46.9562072754],"type":"Point"}
}