{
  "type": "Feature",
  "properties": {
    "iso:country":"CH",
    "sg:address":"Moosstrasse 11",
    "sg:city":"Buchrain",
    "sg:orig_category":"Architektur U Ingenieurb\u00fcros",
    "sg:phone":"+41 41 440 47 81",
    "sg:postcode":"6033",
    "sg:province":"Luzern",
    "wof:name":"August H\u00fcppin Ingenieurb\u00fcro",
    "wof:placetype":"venue"
},
  "geometry": {"coordinates":[8.355206,47.093624],"type":"Point"}
}