{
  "type": "Feature",
  "properties": {
    "iso:country":"CH",
    "sg:address":"Dorfring 1",
    "sg:city":"Allenwinden",
    "sg:orig_category":"Gartenbau Strassenbau",
    "sg:phone":"+41 79 333 97 70",
    "sg:postcode":"6319",
    "sg:province":"Zug",
    "wof:name":"Urs Nussbaumer Tief-& Gartenbau Gmbh",
    "wof:placetype":"venue"
},
  "geometry": {"coordinates":[8.5539503098,47.1655883789],"type":"Point"}
}