{
  "type": "Feature",
  "properties": {
    "iso:country":"CH",
    "sg:address":"8307 Effretikon. Postfach 191",
    "sg:city":"Effretikon",
    "sg:orig_category":"Wirtschaftsverb\u00e4nde Gewerbeverb\u00e4nde/-vereine",
    "sg:phone":"+41 52 343 72 94",
    "sg:postcode":"8307",
    "sg:province":"Z\u00fcrich",
    "wof:name":"Gewerbeverein Illnau-effretikon",
    "wof:placetype":"venue"
},
  "geometry": {"coordinates":[8.7083997726,47.4293899536],"type":"Point"}
}