{
  "type": "Feature",
  "properties": {
    "iso:country":"CH",
    "sg:address":"Galgenm\u00e4ttli 14",
    "sg:city":"Laufen",
    "sg:orig_category":"Interessenvertretungen",
    "sg:postcode":"4242",
    "sg:province":"Basel-Landschaft",
    "wof:name":"Laufentaler-stiftung Der Portlandcementfabrik Laufen",
    "wof:placetype":"venue"
},
  "geometry": {"coordinates":[7.5077362061,47.4249458313],"type":"Point"}
}