{
  "type": "Feature",
  "properties": {
    "iso:country":"CH",
    "sg:address":"1643",
    "sg:city":"Gumefens",
    "sg:orig_category":"Campingpl\u00e4tze Detailhandel mit Zeitungen U Zeitschriften Kioske",
    "sg:phone":"+41 26 915 22 23",
    "sg:postcode":"1643",
    "sg:province":"Fribourg",
    "wof:name":"Camp La Pointe Bleue",
    "wof:placetype":"venue"
},
  "geometry": {"coordinates":[7.06859,46.67717],"type":"Point"}
}