{
  "type": "Feature",
  "properties": {
    "iso:country":"CH",
    "sg:address":"Sous-la-rive 81",
    "sg:city":"Eschert",
    "sg:orig_category":"Vermietung U Verpachtung von eigenen Immobilien",
    "sg:phone":"+41 32 493 31 10",
    "sg:postcode":"2743",
    "sg:province":"Bern",
    "wof:name":"Immovar S\u00e0rl",
    "wof:placetype":"venue"
},
  "geometry": {"coordinates":[7.3938760757,47.2789039612],"type":"Point"}
}