{
  "type": "Feature",
  "properties": {
    "iso:country":"CH",
    "sg:address":"6072",
    "sg:city":"Sachseln",
    "sg:orig_category":"Schulpflegen",
    "sg:phone":"+41 81 647 12 70",
    "sg:postcode":"6072",
    "sg:province":"Obwalden",
    "wof:name":"Schulrat Der Gemeinde Safien Platz",
    "wof:placetype":"venue"
},
  "geometry": {"coordinates":[9.3141298294,46.6809997559],"type":"Point"}
}