{
  "type": "Feature",
  "properties": {
    "iso:country":"CH",
    "sg:address":"Rue Du Grand-verger 14",
    "sg:city":"Martigny",
    "sg:orig_category":"Architekturb\u00fcros",
    "sg:phone":"+41 31 311 82 92",
    "sg:postcode":"1920",
    "sg:province":"Valais",
    "wof:name":"Jean-pierre Kuenzli Architekturb\u00fcro",
    "wof:placetype":"venue"
},
  "geometry": {"coordinates":[7.45376,46.94162],"type":"Point"}
}