{
  "type": "Feature",
  "properties": {
    "iso:country":"CH",
    "sg:address":"Avry-centre",
    "sg:city":"Avry-sur-matran",
    "sg:orig_category":"Sonstiger Detailhandel mit Metallwaren, Anstrichmitteln, Glaswaren, Bau U Heimwerkerbedarf",
    "sg:phone":"+41 26 470 15 92",
    "sg:postcode":"1754",
    "sg:province":"Fribourg",
    "wof:name":"Schaffner Sa Do It Yourself",
    "wof:placetype":"venue"
},
  "geometry": {"coordinates":[7.0721960068,46.7883262634],"type":"Point"}
}