{
  "type": "Feature",
  "properties": {
    "iso:country":"CH",
    "sg:address":"Achernstrasse 2",
    "sg:city":"Siebnen",
    "sg:orig_category":"Papier U Kartongewerbe R\u00fcckgewinnung U Vorbereitung f\u00fcr die Wiederverwertung Recycling",
    "sg:phone":"+41 31 381 02 54",
    "sg:postcode":"8854",
    "sg:province":"Schwyz",
    "wof:name":"Alpabern Ag",
    "wof:placetype":"venue"
},
  "geometry": {"coordinates":[7.4075198174,46.9471244812],"type":"Point"}
}