{
  "type": "Feature",
  "properties": {
    "iso:country":"CH",
    "sg:address":"Geiselweidstrasse 50",
    "sg:city":"Winterthur",
    "sg:orig_category":"Finanzierungsinstitutionen",
    "sg:phone":"+41 52 233 41 61",
    "sg:postcode":"8400",
    "sg:province":"Z\u00fcrich",
    "wof:name":"Revalt Consult Ag",
    "wof:placetype":"venue"
},
  "geometry": {"coordinates":[8.7450113297,47.4983024597],"type":"Point"}
}