{
  "type": "Feature",
  "properties": {
    "iso:country":"CH",
    "sg:address":"Obergasse 4 2500 Biel/bienne. Postfach",
    "sg:city":"Biel/bienne",
    "sg:orig_category":"Grosshandel mit Textilien",
    "sg:postcode":"2502",
    "sg:province":"Bern",
    "wof:name":"Minder-urfer M. & R.",
    "wof:placetype":"venue"
},
  "geometry": {"coordinates":[7.2467269897,47.1420249939],"type":"Point"}
}