{
  "type": "Feature",
  "properties": {
    "iso:country":"CH",
    "sg:address":"1955",
    "sg:city":"Chamoson",
    "sg:orig_category":"Stukkateurgewerbe, Gipserei U Verputzerei",
    "sg:postcode":"1955",
    "sg:province":"Valais",
    "wof:name":"Mayencourt Et Dessimoz",
    "wof:placetype":"venue"
},
  "geometry": {"coordinates":[7.2253789902,46.2008628845],"type":"Point"}
}