{
  "type": "Feature",
  "properties": {
    "iso:country":"CH",
    "sg:address":"7526",
    "sg:city":"Cinuos-chel",
    "sg:orig_category":"Sportvereine Ski",
    "sg:phone":"+41 81 854 28 00",
    "sg:postcode":"7526",
    "sg:province":"Graubunden",
    "wof:name":"Skilehrer-verein St.moritz",
    "wof:placetype":"venue"
},
  "geometry": {"coordinates":[10.0216598511,46.6399993896],"type":"Point"}
}