{
  "type": "Feature",
  "properties": {
    "iso:country":"CH",
    "sg:address":"5614 Sarmenstorf. Postfach 83",
    "sg:city":"Sarmenstorf",
    "sg:orig_category":"Sportvereine Ballsport Fussball",
    "sg:postcode":"5614",
    "sg:province":"Aargau",
    "wof:name":"Fc Sarnen",
    "wof:placetype":"venue"
},
  "geometry": {"coordinates":[8.24559021,46.895778656],"type":"Point"}
}