{
  "type": "Feature",
  "properties": {
    "iso:country":"CH",
    "sg:address":"2501",
    "sg:city":"Biel/bienne",
    "sg:classifiers":[
        {
            "category":"Structure",
            "subcategory":"Office Building",
            "type":"Public Place"
        }
    ],
    "sg:phone":"+41 32 342 02 42",
    "sg:postcode":"2501",
    "sg:province":"Bern",
    "sg:tags":[
        "assemblies",
        "erecting",
        "skeleton"
    ],
    "wof:name":"Compact Building Montage Gmbh",
    "wof:placetype":"venue"
},
  "geometry": {"coordinates":[7.24868,47.14381],"type":"Point"}
}