{
  "type": "Feature",
  "properties": {
    "iso:country":"CH",
    "sg:address":"Holeestrasse 10 4054 Basel. Postfach",
    "sg:city":"Basel",
    "sg:orig_category":"Maler U Glasergewerbe Malerei",
    "sg:phone":"+41 61 421 90 91",
    "sg:postcode":"4012",
    "sg:province":"Basel-Stadt",
    "wof:name":"Schenker & Kirschner",
    "wof:placetype":"venue"
},
  "geometry": {"coordinates":[7.5743589401,47.5446205139],"type":"Point"}
}