{
  "type": "Feature",
  "properties": {
    "iso:country":"CH",
    "sg:address":"Schneitstrasse 16",
    "sg:city":"Ober\u00e4geri",
    "sg:orig_category":"Sonstige Aktivit\u00e4ten der nicht-\u00e4rztlichen Medizinalberufe",
    "sg:phone":"+41 21 944 51 49",
    "sg:postcode":"6315",
    "sg:province":"Zug",
    "wof:name":"M. G\u00e9rard Costa & E. Rollier Logop\u00e9distes",
    "wof:placetype":"venue"
},
  "geometry": {"coordinates":[6.3048892021,46.3652610779],"type":"Point"}
}