{
  "type": "Feature",
  "properties": {
    "iso:country":"CH",
    "sg:address":"Simplon Rue Du 5",
    "sg:city":"Freiburg",
    "sg:orig_category":"Sonstiger Grosshandel",
    "sg:postcode":"1700",
    "sg:province":"Fribourg",
    "wof:name":"Cr Mystery Co Ltc, \u00e0 Londres, Succursale De Fribourg",
    "wof:placetype":"venue"
},
  "geometry": {"coordinates":[7.1518149376,46.7994804382],"type":"Point"}
}