{
  "type": "Feature",
  "properties": {
    "iso:country":"CH",
    "sg:address":"Luisenweg 1",
    "sg:city":"Thun",
    "sg:orig_category":"Architektur U Ingenieurb\u00fcros Architekturb\u00fcros",
    "sg:phone":"+41 27 932 16 18",
    "sg:postcode":"3600",
    "sg:province":"Bern",
    "wof:name":"Architekturb\u00fcro, Kalbermatter Lot",
    "wof:placetype":"venue"
},
  "geometry": {"coordinates":[7.75002,46.316296],"type":"Point"}
}