{
  "type": "Feature",
  "properties": {
    "iso:country":"CH",
    "sg:address":"Dorfstrasse 5",
    "sg:city":"Uetendorf",
    "sg:classifiers":[
        {
            "category":"Banks & Credit Unions",
            "subcategory":"Bank",
            "type":"Services"
        }
    ],
    "sg:phone":"+41 9881050",
    "sg:postcode":"3138",
    "wof:name":"Raiffeisenbank Ufhusen",
    "wof:placetype":"venue"
},
  "geometry": {"coordinates":[-122.796982,39.091446],"type":"Point"}
}