{
  "type": "Feature",
  "properties": {
    "iso:country":"CH",
    "sg:address":"Hertistrasse 30",
    "sg:city":"Wallisellen",
    "sg:classifiers":[
        {
            "category":"Home & Garden",
            "subcategory":"Building Materials",
            "type":"Retail Goods"
        }
    ],
    "sg:phone":"+41 43 233 00 63",
    "sg:postcode":"8304",
    "sg:province":"Z\u00fcrich",
    "sg:tags":[
        "tile",
        "ceramic"
    ],
    "wof:name":"Rogana Gmbh",
    "wof:placetype":"venue"
},
  "geometry": {"coordinates":[8.577384,47.414558],"type":"Point"}
}