{
  "type": "Feature",
  "properties": {
    "iso:country":"CH",
    "sg:address":"Donnerb\u00fchlweg 32 3012 Bern. Postfach",
    "sg:city":"Bern",
    "sg:orig_category":"Pensionskassen",
    "sg:phone":"+41 91 606 28 41",
    "sg:postcode":"3005",
    "sg:province":"Bern",
    "wof:name":"Personalf\u00fcrsorge-stiftung Der Filmgemeinschaft Bern",
    "wof:placetype":"venue"
},
  "geometry": {"coordinates":[7.431666851,46.9513206482],"type":"Point"}
}