{
  "type": "Feature",
  "properties": {
    "iso:country":"CH",
    "sg:address":"Zinggenstrasse",
    "sg:city":"Au",
    "sg:orig_category":"Children's Vehicles, Children's Sports Vehicles",
    "sg:phone":"+41 71 747 49 00",
    "sg:postcode":"9434",
    "sg:province":"St. Gallen",
    "wof:name":"Werner Haderer Gmbh",
    "wof:placetype":"venue"
},
  "geometry": {"coordinates":[9.637665,47.42453],"type":"Point"}
}