{
  "type": "Feature",
  "properties": {
    "iso:country":"CH",
    "sg:address":"Gottfried Keller-strasse 7",
    "sg:city":"Z\u00fcrich",
    "sg:orig_category":"Arztpraxen",
    "sg:phone":"+41 12623700",
    "sg:postcode":"8001",
    "sg:province":"Z\u00fcrich",
    "wof:name":"Dr.med.elsa Hotz Spezial\u00e4rztin Fmh",
    "wof:placetype":"venue"
},
  "geometry": {"coordinates":[8.547423,47.366417],"type":"Point"}
}