{
  "type": "Feature",
  "properties": {
    "iso:country":"CH",
    "sg:address":"8197",
    "sg:city":"Rafz",
    "sg:orig_category":"Haltung von Rindern",
    "sg:postcode":"8197",
    "sg:province":"Z\u00fcrich",
    "wof:name":"Fleckviehzucht-genossenschaft Rafz",
    "wof:placetype":"venue"
},
  "geometry": {"coordinates":[8.5392942429,47.6108932495],"type":"Point"}
}