{
  "type": "Feature",
  "properties": {
    "iso:country":"CH",
    "sg:address":"Kriesbachstrasse 3",
    "sg:city":"D\u00fcbendorf",
    "sg:orig_category":"Grosshandel mit Datenverarbeitungsger\u00e4ten Softwareentwicklung U beratung",
    "sg:phone":"+41 18026464",
    "sg:postcode":"8600",
    "sg:province":"Z\u00fcrich",
    "wof:name":"Hitachi Data Systems Ag Edv-systeme",
    "wof:placetype":"venue"
},
  "geometry": {"coordinates":[8.6168260574,47.4013290405],"type":"Point"}
}