{
  "type": "Feature",
  "properties": {
    "iso:country":"CH",
    "sg:address":"Worbenstrasse 20",
    "sg:city":"Studen",
    "sg:classifiers":[
        {
            "category":"Manufacturing",
            "subcategory":"Metals",
            "type":"Manufacturing & Wholesale Goods"
        }
    ],
    "sg:phone":"+41 32 373 11 11",
    "sg:postcode":"2557",
    "sg:province":"Bern",
    "sg:tags":[
        "press",
        "sinter",
        "presses",
        "cermet",
        "powder"
    ],
    "wof:name":"Meyer Sintermetall Ag",
    "wof:placetype":"venue"
},
  "geometry": {"coordinates":[7.2988882065,47.1080551147],"type":"Point"}
}