{
  "type": "Feature",
  "properties": {
    "iso:country":"CH",
    "sg:address":"Nidelbadstrasse 94",
    "sg:city":"Z\u00fcrich",
    "sg:orig_category":"Museen",
    "sg:phone":"+41 14816714",
    "sg:postcode":"8038",
    "sg:province":"Z\u00fcrich",
    "wof:name":"Expositio Gmbh Museums, Ausstellungsbereich Usw; Planung, Realisierung",
    "wof:placetype":"venue"
},
  "geometry": {"coordinates":[8.5350017548,47.3320465088],"type":"Point"}
}