{
  "type": "Feature",
  "properties": {
    "iso:country":"CH",
    "sg:address":"Glatthaldestrasse 18",
    "sg:city":"Flawil",
    "sg:orig_category":"Detailhandel mit Waren verschiedener Art, Hauptrichtung Nahrungsmittel",
    "sg:phone":"+41 71 393 62 83",
    "sg:postcode":"9230",
    "sg:province":"St. Gallen",
    "wof:name":"Antonio Siverio Lebensmittelhandel",
    "wof:placetype":"venue"
},
  "geometry": {"coordinates":[9.203789711,47.4105682373],"type":"Point"}
}