{
  "type": "Feature",
  "properties": {
    "iso:country":"CH",
    "sg:address":"Unterer Riederenweg 64",
    "sg:city":"Steffisburg",
    "sg:orig_category":"Grosshandel mit lebenden Tieren",
    "sg:phone":"+41 33 437 40 84",
    "sg:postcode":"3612",
    "sg:province":"Bern",
    "wof:name":"Hans Siegenthaler Viehhandel",
    "wof:placetype":"venue"
},
  "geometry": {"coordinates":[7.6133389473,46.7944984436],"type":"Point"}
}