{
  "type": "Feature",
  "properties": {
    "iso:country":"CH",
    "sg:address":"Rheinstrasse 36b",
    "sg:city":"Pratteln",
    "sg:orig_category":"Handel mit Automobilteilen U Zubeh\u00f6r Herstellung von elektronischen Bauelementen",
    "sg:phone":"+41 61 821 56 00",
    "sg:postcode":"4133",
    "sg:province":"Basel-Landschaft",
    "wof:name":"Auto Meter Ag",
    "wof:placetype":"venue"
},
  "geometry": {"coordinates":[7.6803498268,47.53125],"type":"Point"}
}