{
  "type": "Feature",
  "properties": {
    "iso:country":"CH",
    "sg:address":"Hauptstrasse 43",
    "sg:city":"Muttenz",
    "sg:orig_category":"Detailhandel mit Bekleidung",
    "sg:postcode":"4132",
    "sg:province":"Basel-Landschaft",
    "wof:name":"Dune Concept S\u00e0rl",
    "wof:placetype":"venue"
},
  "geometry": {"coordinates":[6.561132,46.525433],"type":"Point"}
}