{
  "type": "Feature",
  "properties": {
    "addr:full":"Floraweg 3 Schafisheim Aargau 5503",
    "addr:housenumber":"3",
    "addr:postcode":"5503",
    "addr:street":"Floraweg",
    "iso:country":"CH",
    "sg:address":"Floraweg 3",
    "sg:city":"Schafisheim",
    "sg:orig_category":"Datenverarbeitungsdienste Unternehmensberatung",
    "sg:phone":"+41 62 892 13 78",
    "sg:postcode":"5503",
    "sg:province":"Aargau",
    "wof:name":"B\u00f6hm Engineering & Training Informatik, Organisation; Unternehmensberatung. Wissenstranfer Usw",
    "wof:placetype":"venue"
},
  "geometry": {"coordinates":[8.149768,47.377792],"type":"Point"}
}