{
  "type": "Feature",
  "properties": {
    "iso:country":"CH",
    "sg:address":"Buchenstrasse 16",
    "sg:city":"Herisau",
    "sg:orig_category":"Interessenvertretungen",
    "sg:postcode":"9100",
    "sg:province":"Appenzell Ausserrhoden",
    "wof:name":"Frey-b\u00fccheler-stiftung Friedrich Und Anita",
    "wof:placetype":"venue"
},
  "geometry": {"coordinates":[9.2819671631,47.387336731],"type":"Point"}
}