{
  "type": "Feature",
  "properties": {
    "iso:country":"CH",
    "sg:address":"Avenue Paul-c\u00e9r\u00e9sole 14",
    "sg:city":"Vevey",
    "sg:orig_category":"Detailhandel mit Schuhen Detailhandel mit Schuhen U Lederwaren",
    "sg:phone":"+41 32 725 01 22",
    "sg:postcode":"1800",
    "sg:province":"Vaud",
    "wof:name":"L'escarpin, Von Gunten Anne-marie",
    "wof:placetype":"venue"
},
  "geometry": {"coordinates":[6.9309859276,46.9910850525],"type":"Point"}
}