{
  "type": "Feature",
  "properties": {
    "iso:country":"CH",
    "sg:address":"Gallusstrasse 12",
    "sg:city":"Uznach",
    "sg:orig_category":"Softwareentwicklung U beratung Webdesign",
    "sg:phone":"+41 55 280 51 78",
    "sg:postcode":"8730",
    "sg:province":"St. Gallen",
    "wof:name":"Pc-buster's Meile",
    "wof:placetype":"venue"
},
  "geometry": {"coordinates":[8.9788284302,47.2259025574],"type":"Point"}
}