{
  "type": "Feature",
  "properties": {
    "addr:full":"Kronengasse 5 Selzach Solothurn 2545",
    "addr:housenumber":"5",
    "addr:postcode":"2545",
    "addr:street":"Kronengasse",
    "iso:country":"CH",
    "sg:address":"Kronengasse 5",
    "sg:city":"Selzach",
    "sg:orig_category":"Architektur U Ingenieurb\u00fcros",
    "sg:phone":"+41 32 641 21 32",
    "sg:postcode":"2545",
    "sg:province":"Solothurn",
    "wof:name":"Viktor St\u00fcdeli Beratung & Projekte Beratung Und Projektbearbeitung Im \u00f6ffentlichen Bereich Usw",
    "wof:placetype":"venue"
},
  "geometry": {"coordinates":[7.452651,47.207218],"type":"Point"}
}