{
  "type": "Feature",
  "properties": {
    "iso:country":"CH",
    "sg:address":"Clarastrasse 19 5442 Fislisbach. Postfach",
    "sg:city":"Fislisbach",
    "sg:orig_category":"Herstellung von Elektromotoren, Generatoren U Transformatoren",
    "sg:postcode":"5442",
    "sg:province":"Aargau",
    "wof:name":"Contractis Gmbh",
    "wof:placetype":"venue"
},
  "geometry": {"coordinates":[9.8381910324,46.4970664978],"type":"Point"}
}