{
  "type": "Feature",
  "properties": {
    "iso:country":"CH",
    "sg:address":"1567",
    "sg:city":"Delley",
    "sg:orig_category":"Allgemeiner Hoch U Tiefbau",
    "sg:phone":"+41 24 481 68 33",
    "sg:postcode":"1567",
    "sg:province":"Fribourg",
    "wof:name":"Delseth-stadelmann Constructions S\u00e0rl",
    "wof:placetype":"venue"
},
  "geometry": {"coordinates":[6.931753,46.31284],"type":"Point"}
}