{
  "type": "Feature",
  "properties": {
    "iso:country":"CH",
    "sg:address":"7503",
    "sg:city":"Samedan",
    "sg:classifiers":[
        {
            "category":"Travel",
            "subcategory":"Hotels & Motels",
            "type":"Entertainment"
        }
    ],
    "sg:phone":"+41 18715111",
    "sg:postcode":"7503",
    "sg:province":"Graubunden",
    "sg:tags":[
        "hotels",
        "mit",
        "restaurant"
    ],
    "wof:name":"Hotel M\u00f6venpick Regensdorf Ag",
    "wof:placetype":"venue"
},
  "geometry": {"coordinates":[8.4675598145,47.4321556091],"type":"Point"}
}