{
  "type": "Feature",
  "properties": {
    "iso:country":"CH",
    "sg:address":"1729",
    "sg:city":"Bonnefontaine",
    "sg:orig_category":"RESTAURANTS: TEA-ROOMS",
    "sg:postcode":"1729",
    "wof:name":"Neuhaus Hedy",
    "wof:placetype":"venue"
},
  "geometry": {"coordinates":[7.2161898613,46.7434501648],"type":"Point"}
}