{
  "type": "Feature",
  "properties": {
    "iso:country":"CH",
    "sg:address":"1354",
    "sg:city":"Montcherand",
    "sg:orig_category":"Landesverteidigung, Sozialversicherung \u00d6ffentliche Verwaltung",
    "sg:phone":"+41 24 441 73 77",
    "sg:postcode":"1354",
    "sg:province":"Vaud",
    "wof:name":"Centre De Protection Civile",
    "wof:placetype":"venue"
},
  "geometry": {"coordinates":[6.5104799271,46.7344207764],"type":"Point"}
}