{
  "type": "Feature",
  "properties": {
    "iso:country":"CH",
    "sg:address":"Schulpavillon",
    "sg:city":"Frauenfeld",
    "sg:orig_category":"Primarschulen",
    "sg:phone":"+41 52 720 80 01",
    "sg:postcode":"8500",
    "sg:province":"Thurgau",
    "wof:name":"Primarschule Strass",
    "wof:placetype":"venue"
},
  "geometry": {"coordinates":[8.8972301483,47.5554885864],"type":"Point"}
}