{
  "type": "Feature",
  "properties": {
    "iso:country":"CH",
    "sg:address":"Sch\u00fctzengraben 27",
    "sg:city":"Schaffhausen",
    "sg:orig_category":"RESTAURANTS: TEA-ROOMS",
    "sg:phone":"+41 52 625 42 49",
    "sg:postcode":"8200",
    "sg:province":"Schaffhausen",
    "wof:name":"Restaurant Sch\u00fctzenstube Gmbh",
    "wof:placetype":"venue"
},
  "geometry": {"coordinates":[8.635052681,47.6988945007],"type":"Point"}
}