{
  "type": "Feature",
  "properties": {
    "iso:country":"CH",
    "sg:address":"Les Epineys",
    "sg:city":"Saillon",
    "sg:orig_category":"Bauschreinerei Herstellung von Fenstern U T\u00fcren aus Holz",
    "sg:phone":"+41 27 744 39 33",
    "sg:postcode":"1913",
    "sg:province":"Valais",
    "wof:name":"St\u00e9phane Fumeaux Menuiserie",
    "wof:placetype":"venue"
},
  "geometry": {"coordinates":[7.177848,46.158607],"type":"Point"}
}