{
  "type": "Feature",
  "properties": {
    "addr:full":"Chemin Du Pr\u00e9-fleuri 29 1228 Plan-les-ouates Case Postale 85 Plan-les-ouates Gen\u00e8ve 1228",
    "addr:housenumber":"29",
    "addr:postcode":"1228;85;1228",
    "addr:street":"Chemin Du Pre\u0301-Fleuri;Postale",
    "iso:country":"CH",
    "sg:address":"Chemin Du Pr\u00e9-fleuri 29 1228 Plan-les-ouates Case Postale 85",
    "sg:city":"Plan-les-ouates",
    "sg:orig_category":"Markt U Meinungsforschung",
    "sg:phone":"+41 22 706 90 00",
    "sg:postcode":"1228",
    "sg:province":"Gen\u00e8ve",
    "wof:name":"Hermes Communication Locher J., Vionnet Ph., Auberjonois P., Rohr Ph.",
    "wof:placetype":"venue"
},
  "geometry": {"coordinates":[6.106942,46.1651],"type":"Point"}
}