{
  "type": "Feature",
  "properties": {
    "iso:country":"CH",
    "sg:address":"R\u00fctistrasse 105",
    "sg:city":"Jona",
    "sg:orig_category":"Installation von Heizungs, L\u00fcftungs U Klimaanlagen",
    "sg:phone":"+41 55 210 21 15",
    "sg:postcode":"8645",
    "sg:province":"St. Gallen",
    "wof:name":"Elk-rapperswil Inh.fritz Spori Entstaubung-l\u00fcftung-klima",
    "wof:placetype":"venue"
},
  "geometry": {"coordinates":[8.83116436,47.2436180115],"type":"Point"}
}