{
  "type": "Feature",
  "properties": {
    "iso:country":"CH",
    "sg:address":"Schachen",
    "sg:city":"Hofstatt",
    "sg:classifiers":[
        {
            "category":"Restaurant",
            "type":"Food & Drink"
        }
    ],
    "sg:phone":"+41 41 978 11 31",
    "sg:postcode":"6154",
    "sg:province":"Luzern",
    "wof:name":"Schachen-pinte",
    "wof:placetype":"venue"
},
  "geometry": {"coordinates":[7.9148750305,47.0844955444],"type":"Point"}
}