{
  "type": "Feature",
  "properties": {
    "iso:country":"CH",
    "sg:address":"Via Bramantino 33",
    "sg:city":"Locarno",
    "sg:orig_category":"Architekturb\u00fcros",
    "sg:phone":"+41 91 751 40 73",
    "sg:postcode":"6600",
    "sg:province":"Ticino",
    "wof:name":"Livio Vacchini Studio D'architettura",
    "wof:placetype":"venue"
},
  "geometry": {"coordinates":[8.793985,46.166061],"type":"Point"}
}