{
  "type": "Feature",
  "properties": {
    "iso:country":"CH",
    "sg:address":"Bruggm\u00fchle 117 9403 Goldach. Postfach",
    "sg:city":"Goldach",
    "sg:orig_category":"Unclassifiable Establishments",
    "sg:phone":"+41 71 844 98 20",
    "sg:postcode":"9403",
    "sg:province":"St. Gallen",
    "wof:name":"Ostschweizerische M\u00fchlen Ag Goldach",
    "wof:placetype":"venue"
},
  "geometry": {"coordinates":[9.4616470337,47.4770278931],"type":"Point"}
}