{
  "type": "Feature",
  "properties": {
    "iso:country":"CH",
    "sg:address":"Rigistrasse 55 8006 Z\u00fcrich. Postfach",
    "sg:city":"T\u00e4gerwilen",
    "sg:orig_category":"Sonstige pers\u00f6nliche Dienstleistungen",
    "sg:phone":"+41 71 666 66 66",
    "sg:postcode":"8274",
    "sg:province":"Thurgau",
    "wof:name":"Rhine Venture Invest Sa",
    "wof:placetype":"venue"
},
  "geometry": {"coordinates":[8.5511112213,47.3855667114],"type":"Point"}
}