{
  "type": "Feature",
  "properties": {
    "iso:country":"CH",
    "sg:address":"Grabenackerstrasse 8b",
    "sg:city":"M\u00fcnchenstein",
    "sg:orig_category":"Herstellung von Metallerzeugnissen ohne Maschinenbau Herstellung von Pumpen U Kompressoren",
    "sg:phone":"+41 56 621 15 19",
    "sg:postcode":"4142",
    "sg:province":"Basel-Landschaft",
    "wof:name":"Schwarz Kompressoren Ag",
    "wof:placetype":"venue"
},
  "geometry": {"coordinates":[8.2781887054,47.3421058655],"type":"Point"}
}