{
  "type": "Feature",
  "properties": {
    "iso:country":"CH",
    "sg:address":"Eichholzstrasse 32 3084 Wabern. Postfach",
    "sg:city":"Wabern",
    "sg:orig_category":"Fernmeldedienste",
    "sg:postcode":"3084",
    "sg:province":"Bern",
    "wof:name":"Geresi Renaud",
    "wof:placetype":"venue"
},
  "geometry": {"coordinates":[7.050798893,46.6105995178],"type":"Point"}
}