{
  "type": "Feature",
  "properties": {
    "iso:country":"CH",
    "sg:address":"Nordstrasse 62",
    "sg:city":"Z\u00fcrich",
    "sg:orig_category":"Sonstiger Grosshandel",
    "sg:postcode":"8006",
    "sg:province":"Z\u00fcrich",
    "wof:name":"Fritzsche Marianne, Epa - Superdiscount",
    "wof:placetype":"venue"
},
  "geometry": {"coordinates":[9.0758829117,47.4413452148],"type":"Point"}
}