{
  "type": "Feature",
  "properties": {
    "iso:country":"CH",
    "sg:address":"Rue Du Lac 2",
    "sg:city":"Yverdon-les-bains",
    "sg:orig_category":"Detailhandel mit Radio U Fernsehger\u00e4ten Detailhandel mit fotografischen Artikeln",
    "sg:phone":"+41 24 426 24 34",
    "sg:postcode":"1400",
    "sg:province":"Vaud",
    "wof:name":"No\u00eble Tv Sa",
    "wof:placetype":"venue"
},
  "geometry": {"coordinates":[6.6409420967,46.7788734436],"type":"Point"}
}