{
  "type": "Feature",
  "properties": {
    "iso:country":"CH",
    "sg:address":"7077 Valbella. Postfach 52",
    "sg:city":"Valbella",
    "sg:classifiers":[
        {
            "category":"Travel",
            "subcategory":"Hotels & Motels",
            "type":"Entertainment"
        }
    ],
    "sg:phone":"+41 81 417 07 07",
    "sg:postcode":"7077",
    "sg:province":"Graubunden",
    "sg:tags":[
        "hotels",
        "mit",
        "restaurant"
    ],
    "wof:name":"Hotel Kulm",
    "wof:placetype":"venue"
},
  "geometry": {"coordinates":[9.8537502289,46.8327293396],"type":"Point"}
}