{
  "type": "Feature",
  "properties": {
    "iso:country":"CH",
    "sg:address":"Chemin De Palud 14",
    "sg:city":"Chamb\u00e9sy",
    "sg:orig_category":"Unternehmensberatung",
    "sg:postcode":"1292",
    "sg:province":"Gen\u00e8ve",
    "wof:name":"Pgv Organisation, Vulliemin P",
    "wof:placetype":"venue"
},
  "geometry": {"coordinates":[6.8771519661,47.0473823547],"type":"Point"}
}