{
  "type": "Feature",
  "properties": {
    "iso:country":"CH",
    "sg:address":"Dorfgasse 120",
    "sg:city":"Twann",
    "sg:orig_category":"Museen",
    "sg:postcode":"2513",
    "sg:province":"Bern",
    "wof:name":"Pfahlbau-sammlung Fraubrunnenhaus",
    "wof:placetype":"venue"
},
  "geometry": {"coordinates":[7.1578302383,47.0951538086],"type":"Point"}
}