{
  "type": "Feature",
  "properties": {
    "iso:country":"CH",
    "sg:address":"Chemin De La Tuilerie 21",
    "sg:city":"Courfaivre",
    "sg:classifiers":[
        {
            "category":"Home & Garden",
            "subcategory":"Building Materials",
            "type":"Retail Goods"
        }
    ],
    "sg:phone":"+41 32 426 81 91",
    "sg:postcode":"2853",
    "sg:province":"Jura",
    "sg:tags":[
        "aluminium",
        "window"
    ],
    "wof:name":"Sornalu S.a.",
    "wof:placetype":"venue"
},
  "geometry": {"coordinates":[7.2704,47.331848],"type":"Point"}
}