{
  "type": "Feature",
  "properties": {
    "iso:country":"CH",
    "sg:address":"Avenue Du Rothorn 10 3960 Sierre Case Postale 366",
    "sg:city":"Sierre",
    "sg:classifiers":[
        {
            "category":"Restaurant",
            "type":"Food & Drink"
        }
    ],
    "sg:phone":"+41 27 455 67 87",
    "sg:postcode":"3960",
    "sg:province":"Valais",
    "wof:name":"Restaurant-chinoise M\u00e9kong",
    "wof:placetype":"venue"
},
  "geometry": {"coordinates":[7.532348156,46.2938804626],"type":"Point"}
}