{
  "type": "Feature",
  "properties": {
    "iso:country":"CH",
    "sg:address":"Juchten",
    "sg:city":"Oschwand",
    "sg:orig_category":"Sportvereine Unihockey",
    "sg:phone":"+41 62 968 05 14",
    "sg:postcode":"3476",
    "sg:province":"Bern",
    "wof:name":"Uhc Lake Hill Oschwand",
    "wof:placetype":"venue"
},
  "geometry": {"coordinates":[7.7128300667,47.1407585144],"type":"Point"}
}