{
  "type": "Feature",
  "properties": {
    "iso:country":"CH",
    "sg:address":"Tobelstrasse 19 8632 Tann. Postfach",
    "sg:city":"Tann",
    "sg:orig_category":"Herstellung von sonstigen Nahrungsmitteln",
    "sg:phone":"+41 55 251 70 70",
    "sg:postcode":"8632",
    "sg:province":"Z\u00fcrich",
    "wof:name":"Pizza-beck Gmbh Mahlzeiten, Bes. Pizza, Teigwaren; Herstellung, Auslieferung",
    "wof:placetype":"venue"
},
  "geometry": {"coordinates":[8.8559303284,47.2665596008],"type":"Point"}
}