{
  "type": "Feature",
  "properties": {
    "iso:country":"CH",
    "sg:address":"B\u00fcrgenstrasse 16",
    "sg:city":"Luzern",
    "sg:orig_category":"Non-Classified Establishments",
    "sg:phone":"+41 41 360 67 24",
    "sg:postcode":"6005",
    "sg:province":"Luzern",
    "wof:name":"Patrick Steiner Parkettgesch\u00e4ft",
    "wof:placetype":"venue"
},
  "geometry": {"coordinates":[8.3155021667,47.0453834534],"type":"Point"}
}