{
  "type": "Feature",
  "properties": {
    "iso:country":"CH",
    "sg:address":"Riethalden 2171",
    "sg:city":"Wildhaus",
    "sg:orig_category":"Hardwareberatung Softwareentwicklung U beratung",
    "sg:phone":"+41 71 997 04 00",
    "sg:postcode":"9658",
    "sg:province":"St. Gallen",
    "wof:name":"Techno Wood Gmbh",
    "wof:placetype":"venue"
},
  "geometry": {"coordinates":[9.3558387756,47.2008743286],"type":"Point"}
}