{
  "type": "Feature",
  "properties": {
    "iso:country":"CH",
    "sg:address":"Waldhofstrasse 31",
    "sg:city":"Unter\u00e4geri",
    "sg:orig_category":"Non-Classified Establishments",
    "sg:postcode":"6314",
    "sg:province":"Zug",
    "wof:name":"Cdi Carpe Diem Investment Ag",
    "wof:placetype":"venue"
},
  "geometry": {"coordinates":[8.5728540421,47.1428833008],"type":"Point"}
}