{
  "type": "Feature",
  "properties": {
    "iso:country":"CH",
    "sg:address":"N\u00fcschelerstrasse 45 8001 Z\u00fcrich. Postfach",
    "sg:city":"Z\u00fcrich",
    "sg:orig_category":"Pensionskassen",
    "sg:postcode":"8001",
    "sg:province":"Z\u00fcrich",
    "wof:name":"Bvg-stiftung Der Charles Kolp & Co. Ag Und Der Ihr Angeschlossenen Firmen",
    "wof:placetype":"venue"
},
  "geometry": {"coordinates":[9.3019170761,47.3995246887],"type":"Point"}
}