{
  "type": "Feature",
  "properties": {
    "iso:country":"CH",
    "sg:address":"Haldeweg 6",
    "sg:city":"Marthalen",
    "sg:orig_category":"Sportvereine Sch\u00fctzen Armbrust",
    "sg:phone":"+41 52 319 25 62",
    "sg:postcode":"8460",
    "sg:province":"Z\u00fcrich",
    "wof:name":"Armbrustsch\u00fctzenverein",
    "wof:placetype":"venue"
},
  "geometry": {"coordinates":[8.6530246735,47.625541687],"type":"Point"}
}