{
  "type": "Feature",
  "properties": {
    "iso:country":"CH",
    "sg:address":"Rufelstrasse 1",
    "sg:city":"Subingen",
    "sg:orig_category":"Assembling, Disassembling",
    "sg:phone":"+41 32 614 17 75",
    "sg:postcode":"4553",
    "sg:province":"Solothurn",
    "wof:name":"Urs Flury",
    "wof:placetype":"venue"
},
  "geometry": {"coordinates":[7.620216,47.199924],"type":"Point"}
}