{
  "type": "Feature",
  "properties": {
    "iso:country":"CH",
    "sg:address":"Untere Halten 4",
    "sg:city":"Emmen",
    "sg:orig_category":"Sanit\u00e4r, Heizungs U L\u00fcftungsinstallation",
    "sg:postcode":"6032",
    "sg:province":"Luzern",
    "wof:name":"Gasser Sanit\u00e4r",
    "wof:placetype":"venue"
},
  "geometry": {"coordinates":[8.2914876938,47.0867996216],"type":"Point"}
}