{
  "type": "Feature",
  "properties": {
    "iso:country":"CH",
    "sg:address":"Kiener Avenue 69 1400 Yverdon-les-bains. Postfach",
    "sg:city":"Cheseaux-nor\u00e9az",
    "sg:orig_category":"M\u00f6belschreinereien",
    "sg:phone":"+41 24 426 61 46",
    "sg:postcode":"1400",
    "sg:province":"Vaud",
    "wof:name":"Campos Juan Manuel S\u00e0rl Menuiserie; Traveaux. Meubles Et Appareils De Cuisine; Importation Etc",
    "wof:placetype":"venue"
},
  "geometry": {"coordinates":[6.6323180199,46.7734718323],"type":"Point"}
}