{
  "type": "Feature",
  "properties": {
    "addr:full":"Rue Jean Jacques Rousseau 5 Vevey Vaud 1800",
    "addr:housenumber":"5",
    "addr:postcode":"1800",
    "addr:street":"Rue Jean Jacques Rousseau",
    "iso:country":"CH",
    "sg:address":"Rue Jean Jacques Rousseau 5",
    "sg:city":"Vevey",
    "sg:classifiers":[
        {
            "category":"Banks & Credit Unions",
            "subcategory":"Bank",
            "type":"Services"
        }
    ],
    "sg:phone":"+41 21 923 52 62",
    "sg:postcode":"1800",
    "sg:province":"Vaud",
    "wof:name":"Lombard Odier & Cie",
    "wof:placetype":"venue"
},
  "geometry": {"coordinates":[6.841538,46.460732],"type":"Point"}
}