{
  "type": "Feature",
  "properties": {
    "iso:country":"CH",
    "sg:address":"T\u00f6distrasse 42 8002 Z\u00fcrich. Postfach",
    "sg:city":"Z\u00fcrich",
    "sg:orig_category":"Unternehmensberatung",
    "sg:phone":"+41 12029209",
    "sg:postcode":"8027",
    "sg:province":"Z\u00fcrich",
    "wof:name":"Befin Consult Ag",
    "wof:placetype":"venue"
},
  "geometry": {"coordinates":[8.5342340469,47.3671340942],"type":"Point"}
}