{
  "type": "Feature",
  "properties": {
    "iso:country":"CH",
    "sg:address":"Rue Du 31-d\u00e9cembre 50",
    "sg:city":"Gen\u00e8ve",
    "sg:orig_category":"K\u00fcnstlerische Schulen",
    "sg:phone":"+41 21 312 44 41",
    "sg:postcode":"1207",
    "sg:province":"Gen\u00e8ve",
    "wof:name":"Ecole Sociale De Musique",
    "wof:placetype":"venue"
},
  "geometry": {"coordinates":[6.6341838837,46.5227203369],"type":"Point"}
}