{
  "type": "Feature",
  "properties": {
    "iso:country":"CH",
    "sg:address":"Grand-ch\u00eane Rue Du 6 1003 Lausanne. Postfach",
    "sg:city":"Gen\u00e8ve",
    "sg:orig_category":"Wirtschaftspr\u00fcfung, Steuerberatung U Treuhand",
    "sg:phone":"+41 41 210 71 73",
    "sg:postcode":"1201",
    "sg:province":"Gen\u00e8ve",
    "wof:name":"Sr Treuhand Untern\u00e4hrer Edgar & Cie Steuerberatungen, Revisionen, Treuhand Usw",
    "wof:placetype":"venue"
},
  "geometry": {"coordinates":[8.3028869629,47.0492210388],"type":"Point"}
}