{
  "type": "Feature",
  "properties": {
    "addr:full":"Castausio Via 4 Lugano Ticino 6900",
    "addr:housenumber":"4",
    "addr:postcode":"6900",
    "addr:street":"Via",
    "iso:country":"CH",
    "sg:address":"Castausio Via 4",
    "sg:city":"Lugano",
    "sg:orig_category":"Allgemeiner Hoch U Tiefbau",
    "sg:postcode":"6900",
    "sg:province":"Ticino",
    "wof:name":"Ds Discariche Sud Sa",
    "wof:placetype":"venue"
},
  "geometry": {"coordinates":[8.95414,46.013634],"type":"Point"}
}