{
  "type": "Feature",
  "properties": {
    "iso:country":"CH",
    "sg:address":"Weidentalweg 28",
    "sg:city":"Oberdorf",
    "sg:classifiers":[
        {
            "category":"Manufacturing",
            "subcategory":"Metals",
            "type":"Manufacturing & Wholesale Goods"
        }
    ],
    "sg:phone":"+41 61 965 94 00",
    "sg:postcode":"4436",
    "sg:province":"Basel-Landschaft",
    "sg:tags":[
        "metallurgy",
        "metalworking",
        "processing"
    ],
    "wof:name":"Eduard Fussinger Ag",
    "wof:placetype":"venue"
},
  "geometry": {"coordinates":[7.7561511993,47.3905906677],"type":"Point"}
}