{
  "type": "Feature",
  "properties": {
    "iso:country":"CH",
    "sg:address":"S\u00e4gestrasse 66 3098 K\u00f6niz. Postfach 556",
    "sg:city":"K\u00f6niz",
    "sg:orig_category":"Bau U Wohngenossenschaften",
    "sg:postcode":"3098",
    "sg:province":"Bern",
    "wof:name":"Wohnbaugen.f\u00fcr Bundes- Bedienstete Brugg",
    "wof:placetype":"venue"
},
  "geometry": {"coordinates":[8.2036,47.486469],"type":"Point"}
}