{
  "type": "Feature",
  "properties": {
    "iso:country":"CH",
    "sg:address":"Kehr 20",
    "sg:city":"Gais",
    "sg:orig_category":"Wohnheime f\u00fcr Kinder U Jugendliche",
    "sg:phone":"+41 71 793 13 47",
    "sg:postcode":"9056",
    "sg:province":"Appenzell Ausserrhoden",
    "wof:name":"Erholung F\u00fcr Mutter & Kind St\u00e4dt. Kinderkrippe,kinderhort",
    "wof:placetype":"venue"
},
  "geometry": {"coordinates":[9.4580364227,47.3628807068],"type":"Point"}
}