{
  "type": "Feature",
  "properties": {
    "iso:country":"CH",
    "sg:address":"Rheingasse 20 8246 Langwiesen. Postfach",
    "sg:city":"Langwiesen",
    "sg:orig_category":"Saunas, Solarien, Fitnesszentren U \u00e4hnliches",
    "sg:postcode":"8246",
    "sg:province":"Z\u00fcrich",
    "wof:name":"Sonnenstudio M. Harsy-vadas",
    "wof:placetype":"venue"
},
  "geometry": {"coordinates":[8.6639213562,47.6848602295],"type":"Point"}
}