{
  "type": "Feature",
  "properties": {
    "iso:country":"CH",
    "sg:address":"Alpsteinstrasse 23",
    "sg:city":"Uzwil",
    "sg:orig_category":"Betrieb von Taxis",
    "sg:phone":"+41 79 301 45 91",
    "sg:postcode":"9240",
    "sg:province":"St. Gallen",
    "wof:name":"Taxi Tout-coeur, Mammarella Eugenio",
    "wof:placetype":"venue"
},
  "geometry": {"coordinates":[6.868166,46.451202],"type":"Point"}
}