{
  "type": "Feature",
  "properties": {
    "iso:country":"CH",
    "sg:address":"Neudorfstrasse 36",
    "sg:city":"W\u00e4denswil",
    "sg:orig_category":"Grosshandel mit B\u00fcromaschinen Grosshandel mit Datenverarbeitungsger\u00e4ten",
    "sg:phone":"+41 17803086",
    "sg:postcode":"8820",
    "sg:province":"Z\u00fcrich",
    "wof:name":"Deltavision Elektronik & Software Derflinger M.",
    "wof:placetype":"venue"
},
  "geometry": {"coordinates":[8.6629257202,47.2340583801],"type":"Point"}
}