{
  "type": "Feature",
  "properties": {
    "iso:country":"CH",
    "sg:address":"Obstgarten",
    "sg:city":"Flawil",
    "sg:orig_category":"Zimmerei, Dachdeckerei, Bauspenglerei U Abdichtung",
    "sg:phone":"+41 71 931 11 83",
    "sg:postcode":"9230",
    "sg:province":"St. Gallen",
    "wof:name":"Weber Holzbau Ag",
    "wof:placetype":"venue"
},
  "geometry": {"coordinates":[9.0385494232,47.4111557007],"type":"Point"}
}