{
  "type": "Feature",
  "properties": {
    "iso:country":"CH",
    "sg:address":"Altersheimstrasse 1",
    "sg:city":"Muhen",
    "sg:orig_category":"Grosshandel mit lebenden Tieren",
    "sg:phone":"+41 62 723 84 79",
    "sg:postcode":"5037",
    "sg:province":"Aargau",
    "wof:name":"Otto Maurer Viehhandel",
    "wof:placetype":"venue"
},
  "geometry": {"coordinates":[8.0521593094,47.3367042542],"type":"Point"}
}