{
  "type": "Feature",
  "properties": {
    "iso:country":"CH",
    "sg:address":"Rue De Lausanne 91 1700 Fribourg Case Postale 525",
    "sg:city":"Fribourg",
    "sg:orig_category":"Advokaturb\u00fcros",
    "sg:phone":"+41 26 323 27 85",
    "sg:postcode":"1701",
    "sg:province":"Fribourg",
    "wof:name":"Paolo Ghidoni Etude D'avocat",
    "wof:placetype":"venue"
},
  "geometry": {"coordinates":[7.156549,46.805218],"type":"Point"}
}