{
  "type": "Feature",
  "properties": {
    "iso:country":"CH",
    "sg:address":"Widenmatt 32",
    "sg:city":"Malters",
    "sg:orig_category":"Handelsvermittlung U Grosshandel Sonstiger Grosshandel",
    "sg:phone":"+41 41 497 05 35",
    "sg:postcode":"6102",
    "sg:province":"Luzern",
    "wof:name":"Famis",
    "wof:placetype":"venue"
},
  "geometry": {"coordinates":[8.1748638153,47.0343551636],"type":"Point"}
}