{
  "type": "Feature",
  "properties": {
    "iso:country":"CH",
    "sg:address":"Via Ung\u00e8",
    "sg:city":"Torricella",
    "sg:orig_category":"Sportvereine Ballsport Tischtennis",
    "sg:phone":"+41 91 648 13 62",
    "sg:postcode":"6808",
    "sg:province":"Ticino",
    "wof:name":"Stt Riva San Vitale",
    "wof:placetype":"venue"
},
  "geometry": {"coordinates":[9.009595871,45.8600730896],"type":"Point"}
}