{
  "type": "Feature",
  "properties": {
    "addr:full":"Solothurnstrasse 1 Attiswil Bern 4536",
    "addr:housenumber":"1",
    "addr:postcode":"4536",
    "addr:street":"Solothurnstrasse",
    "iso:country":"CH",
    "sg:address":"Solothurnstrasse 1",
    "sg:city":"Attiswil",
    "sg:orig_category":"Darlehenskassen U Raiffeisenbanken",
    "sg:phone":"+41 32 637 07 37",
    "sg:postcode":"4536",
    "sg:province":"Bern",
    "wof:name":"Raiffeisenbank",
    "wof:placetype":"venue"
},
  "geometry": {"coordinates":[7.613112,47.246952],"type":"Point"}
}