{
  "type": "Feature",
  "properties": {
    "iso:country":"CH",
    "sg:address":"Avenue Du Mail 1",
    "sg:city":"Gen\u00e8ve",
    "sg:orig_category":"M\u00f6belveredelung U restaurierung",
    "sg:phone":"+41 22 328 11 80",
    "sg:postcode":"1205",
    "sg:province":"Gen\u00e8ve",
    "wof:name":"Rozalia Lerik Restaurat. De Meubles Anciens",
    "wof:placetype":"venue"
},
  "geometry": {"coordinates":[6.1398887634,46.2009468079],"type":"Point"}
}