{
  "type": "Feature",
  "properties": {
    "iso:country":"CH",
    "sg:address":"Rue De Neuch\u00e2tel 6 2022 Bevaix. Postfach",
    "sg:city":"Bevaix",
    "sg:orig_category":"Grosshandel mit B\u00fcromaschinen Grosshandel mit Datenverarbeitungsger\u00e4ten",
    "sg:phone":"+41 32 849 10 02",
    "sg:postcode":"2022",
    "sg:province":"Neuch\u00e2tel",
    "wof:name":"Alain Friedrich Af Infographie",
    "wof:placetype":"venue"
},
  "geometry": {"coordinates":[6.8165130615,46.9325256348],"type":"Point"}
}