{
  "type": "Feature",
  "properties": {
    "iso:country":"CH",
    "sg:address":"Sapelet",
    "sg:city":"Travers",
    "sg:orig_category":"Verwertung von Milch",
    "sg:postcode":"2105",
    "sg:province":"Neuch\u00e2tel",
    "wof:name":"Syndicat Des Producteurs De Lait Du Sapelet",
    "wof:placetype":"venue"
},
  "geometry": {"coordinates":[6.6732201576,46.9389686584],"type":"Point"}
}