{
  "type": "Feature",
  "properties": {
    "iso:country":"CH",
    "sg:address":"Bellevueweg 28 B",
    "sg:city":"Port",
    "sg:orig_category":"Unternehmensberatung",
    "sg:phone":"+41 79 251 20 81",
    "sg:postcode":"2562",
    "sg:province":"Bern",
    "wof:name":"Horizon Conseil, Pierre Sauthier",
    "wof:placetype":"venue"
},
  "geometry": {"coordinates":[7.2515769005,47.1113128662],"type":"Point"}
}