{
  "type": "Feature",
  "properties": {
    "iso:country":"CH",
    "sg:address":"Riedbachstrasse 51 3027 Bern. Postfach",
    "sg:city":"Bern",
    "sg:orig_category":"Allgemeiner Hoch U Tiefbau",
    "sg:postcode":"3027",
    "sg:province":"Bern",
    "wof:name":"Sydeco Ingenieurunternehmung Ag",
    "wof:placetype":"venue"
},
  "geometry": {"coordinates":[8.58066,47.358429],"type":"Point"}
}