{
  "type": "Feature",
  "properties": {
    "iso:country":"CH",
    "sg:address":"Nussbaumstrasse 38",
    "sg:city":"Bern",
    "sg:orig_category":"Herstellung von Werkzeugmaschinen",
    "sg:phone":"+41 31 371 09 13",
    "sg:postcode":"3007",
    "sg:province":"Bern",
    "wof:name":"Jost Engineering F\u00fcr Industrielle Automation",
    "wof:placetype":"venue"
},
  "geometry": {"coordinates":[7.4676628113,46.9539642334],"type":"Point"}
}