{
  "type": "Feature",
  "properties": {
    "iso:country":"CH",
    "sg:address":"7136",
    "sg:city":"Friggah\u00fcs",
    "sg:orig_category":"Grosshandel mit lebenden Tieren",
    "sg:phone":"+41 81 933 11 60",
    "sg:postcode":"7136",
    "sg:province":"Graubunden",
    "wof:name":"Anton Herrmann Viehhandel",
    "wof:placetype":"venue"
},
  "geometry": {"coordinates":[9.0655651093,46.7425460815],"type":"Point"}
}