{
  "type": "Feature",
  "properties": {
    "iso:country":"CH",
    "sg:address":"Chemin De La Montagne 122",
    "sg:city":"Ch\u00eane-bougeries",
    "sg:orig_category":"Architektur U Ingenieurb\u00fcros",
    "sg:phone":"+41 22 348 80 62",
    "sg:postcode":"1224",
    "sg:province":"Gen\u00e8ve",
    "wof:name":"Giorgio Girani Bureau Technique Betha",
    "wof:placetype":"venue"
},
  "geometry": {"coordinates":[6.200006,46.204697],"type":"Point"}
}