{
  "type": "Feature",
  "properties": {
    "iso:country":"CH",
    "sg:address":"Abl\u00e4ndschenstrasse 20",
    "sg:city":"Jaun",
    "sg:orig_category":"Bauschreinerei Verwertung von Milch",
    "sg:phone":"+41 26 929 81 29",
    "sg:postcode":"1656",
    "sg:province":"Fribourg",
    "wof:name":"Gebr\u00fcder Schuwey Schreinerei & Zimmerei",
    "wof:placetype":"venue"
},
  "geometry": {"coordinates":[7.287138,46.609875],"type":"Point"}
}