{
  "type": "Feature",
  "properties": {
    "iso:country":"CH",
    "sg:address":"Haldensteinstrasse 175",
    "sg:city":"Unterb\u00f6zberg",
    "sg:orig_category":"Druckweiterverarbeitung",
    "sg:phone":"+41 56 441 51 83",
    "sg:postcode":"5224",
    "sg:province":"Aargau",
    "wof:name":"St\u00e4uble Consulting Gmbh",
    "wof:placetype":"venue"
},
  "geometry": {"coordinates":[8.1458272934,47.4858055115],"type":"Point"}
}