{
  "type": "Feature",
  "properties": {
    "iso:country":"CH",
    "sg:address":"Leopoldstrasse 6 6210 Sursee. Postfach",
    "sg:city":"Sursee",
    "sg:orig_category":"Sonstige mit Sport verbundene T\u00e4tigkeiten",
    "sg:postcode":"6210",
    "sg:province":"Luzern",
    "wof:name":"Andreas Prinzing Golfschule Gmbh",
    "wof:placetype":"venue"
},
  "geometry": {"coordinates":[8.0987510681,47.1721496582],"type":"Point"}
}