{
  "type": "Feature",
  "properties": {
    "iso:country":"CH",
    "sg:address":"Ueberlandstrasse 151",
    "sg:city":"D\u00fcbendorf",
    "sg:orig_category":"Autospenglereien",
    "sg:phone":"+41 18214150",
    "sg:postcode":"8600",
    "sg:province":"Z\u00fcrich",
    "wof:name":"Antonio Bivinelli Carrosserie Nino",
    "wof:placetype":"venue"
},
  "geometry": {"coordinates":[8.614934,47.401062],"type":"Point"}
}