{
  "type": "Feature",
  "properties": {
    "iso:country":"CH",
    "sg:address":"Sihlbruggstrasse 105",
    "sg:city":"Baar",
    "sg:orig_category":"Unclassifiable Establishments",
    "sg:postcode":"6340",
    "sg:province":"Zug",
    "wof:name":"Zensura Gmbh",
    "wof:placetype":"venue"
},
  "geometry": {"coordinates":[8.5390930176,47.1977767944],"type":"Point"}
}