{
  "type": "Feature",
  "properties": {
    "iso:country":"CH",
    "sg:address":"Liesbergerstrasse 15",
    "sg:city":"Basel",
    "sg:orig_category":"Betrieb U technische Hilfsdienste des Kultur U Unterhaltungswesens",
    "sg:phone":"+41 61 333 22 11",
    "sg:postcode":"4053",
    "sg:province":"Basel-Stadt",
    "wof:name":"Stagecom Veranstaltungstechnik",
    "wof:placetype":"venue"
},
  "geometry": {"coordinates":[7.596495,47.541443],"type":"Point"}
}