{
  "type": "Feature",
  "properties": {
    "iso:country":"CH",
    "sg:address":"Herrengasse 38",
    "sg:city":"Lyss",
    "sg:orig_category":"Kunsthandel",
    "sg:phone":"+41 32 384 82 70",
    "sg:postcode":"3250",
    "sg:province":"Bern",
    "wof:name":"Bendicht Gn\u00e4gi Auktionshaus",
    "wof:placetype":"venue"
},
  "geometry": {"coordinates":[7.3069019318,47.0708580017],"type":"Point"}
}