{
  "type": "Feature",
  "properties": {
    "iso:country":"CH",
    "sg:address":"Ringstrasse 13",
    "sg:city":"Vilters",
    "sg:orig_category":"Organisationen des Gesundheitswesen",
    "sg:phone":"+41 81 723 44 52",
    "sg:postcode":"7324",
    "sg:province":"St. Gallen",
    "wof:name":"Samariterverein Pizol",
    "wof:placetype":"venue"
},
  "geometry": {"coordinates":[9.4543972015,47.0252532959],"type":"Point"}
}