{
  "type": "Feature",
  "properties": {
    "iso:country":"CH",
    "sg:address":"Ronchi Via Ai 14",
    "sg:city":"Canobbio",
    "sg:orig_category":"K\u00fcnstlerische U schriftstellerische T\u00e4tigkeiten U Darbietungen",
    "sg:postcode":"6952",
    "sg:province":"Ticino",
    "wof:name":"A.t.r. Arte E Tecnica Del Restauro Sagl",
    "wof:placetype":"venue"
},
  "geometry": {"coordinates":[8.9626579285,46.0376052856],"type":"Point"}
}