{
  "type": "Feature",
  "properties": {
    "iso:country":"CH",
    "sg:address":"Kirchbreiteweg 5 6033 Buchrain. Postfach",
    "sg:city":"Buchrain",
    "sg:orig_category":"Fahrschulen, Flugschulen",
    "sg:phone":"+41 77428111",
    "sg:postcode":"6033",
    "sg:province":"Luzern",
    "wof:name":"Franz & Christa Keel Autofahrschule",
    "wof:placetype":"venue"
},
  "geometry": {"coordinates":[8.349609375,47.0938835144],"type":"Point"}
}