{
  "type": "Feature",
  "properties": {
    "iso:country":"CH",
    "sg:address":"8330",
    "sg:city":"Hermatswil",
    "sg:classifiers":[
        {
            "category":"Restaurant",
            "type":"Food & Drink"
        }
    ],
    "sg:phone":"+41 19501418",
    "sg:postcode":"8330",
    "sg:province":"Z\u00fcrich",
    "wof:name":"Restaurant Eintracht",
    "wof:placetype":"venue"
},
  "geometry": {"coordinates":[8.8267097473,47.3947105408],"type":"Point"}
}