{
  "type": "Feature",
  "properties": {
    "iso:country":"CH",
    "sg:address":"Frieslirain 3a",
    "sg:city":"Sursee",
    "sg:classifiers":[
        {
            "category":"Coffee & Tea",
            "type":"Food & Drink"
        }
    ],
    "sg:phone":"+41 41 925 60 60",
    "sg:postcode":"6210",
    "sg:province":"Luzern",
    "sg:tags":[
        "raw",
        "decaffeinated"
    ],
    "wof:name":"Rost Ag",
    "wof:placetype":"venue"
},
  "geometry": {"coordinates":[8.11426,47.169765],"type":"Point"}
}