{
  "type": "Feature",
  "properties": {
    "iso:country":"CH",
    "sg:address":"Rte Des Fayards 60",
    "sg:city":"Bellevue",
    "sg:orig_category":"Instandhaltung U Reparatur von Automobilen",
    "sg:phone":"+41 26 496 21 38",
    "sg:postcode":"1293",
    "sg:province":"Gen\u00e8ve",
    "wof:name":"Garage Marcel Jungo Ag",
    "wof:placetype":"venue"
},
  "geometry": {"coordinates":[7.2401847839,46.8474845886],"type":"Point"}
}