{
  "type": "Feature",
  "properties": {
    "iso:country":"CH",
    "sg:address":"Breitingerstrasse 35 8002 Z\u00fcrich. Postfach",
    "sg:city":"Z\u00fcrich",
    "sg:orig_category":"Wirtschaftsverb\u00e4nde Industrie, Handel and Gewerbe",
    "sg:phone":"+41 55 619 66 00",
    "sg:postcode":"8027",
    "sg:province":"Z\u00fcrich",
    "wof:name":"Verb.schw.reisserei-karderie & Verw.betr.c/o Bico Birchler Co",
    "wof:placetype":"venue"
},
  "geometry": {"coordinates":[9.0545148849,47.1724510193],"type":"Point"}
}