{
  "type": "Feature",
  "properties": {
    "iso:country":"CH",
    "sg:address":"Hegibergstrasse 9",
    "sg:city":"Winterthur",
    "sg:orig_category":"Oberfl\u00e4chenveredlung U W\u00e4rmebehandlung",
    "sg:phone":"+41 52 233 69 69",
    "sg:postcode":"8400",
    "sg:province":"Z\u00fcrich",
    "wof:name":"Greub Metallspritzwerk Ag",
    "wof:placetype":"venue"
},
  "geometry": {"coordinates":[8.7748908997,47.5012245178],"type":"Point"}
}