{
  "type": "Feature",
  "properties": {
    "iso:country":"CH",
    "sg:address":"Place De L'h\u00f4tel-de-ville",
    "sg:city":"Oron-la-ville",
    "sg:orig_category":"Detailhandel mit Fleisch U Fleischwaren",
    "sg:phone":"+41 79 679 96 34",
    "sg:postcode":"1610",
    "sg:province":"Vaud",
    "wof:name":"Willy Dewarrat Boucherie",
    "wof:placetype":"venue"
},
  "geometry": {"coordinates":[6.8266201019,46.5714416504],"type":"Point"}
}