{
  "type": "Feature",
  "properties": {
    "iso:country":"CH",
    "sg:address":"Gerbestrasse 2",
    "sg:city":"Elgg",
    "sg:orig_category":"Gesundheitswesen Physiotherapie",
    "sg:phone":"+41 52 366 16 77",
    "sg:postcode":"8353",
    "sg:province":"Z\u00fcrich",
    "wof:name":"Physiotherapie Elgg Van Der Veen",
    "wof:placetype":"venue"
},
  "geometry": {"coordinates":[8.8668394089,47.4918403625],"type":"Point"}
}