{
  "type": "Feature",
  "properties": {
    "iso:country":"CH",
    "sg:address":"Rue Jean-daniel Colladon 3",
    "sg:city":"Gen\u00e8ve",
    "sg:orig_category":"Dienstleistungen von Beteiligungsgesellschaften",
    "sg:phone":"+41 22 311 34 70",
    "sg:postcode":"1204",
    "sg:province":"Gen\u00e8ve",
    "wof:name":"Finego Sa",
    "wof:placetype":"venue"
},
  "geometry": {"coordinates":[6.1478819847,46.1993560791],"type":"Point"}
}