{
  "type": "Feature",
  "properties": {
    "iso:country":"CH",
    "sg:address":"Dorfstrasse 44",
    "sg:city":"Uetendorf",
    "sg:orig_category":"Zahnarztpraxen",
    "sg:phone":"+41 81 416 22 88",
    "sg:postcode":"3661",
    "sg:province":"Bern",
    "wof:name":"Dr.med.dent.thomas Spielmann Zahnarzt",
    "wof:placetype":"venue"
},
  "geometry": {"coordinates":[9.8374385834,46.8056869507],"type":"Point"}
}