{
  "type": "Feature",
  "properties": {
    "iso:country":"CH",
    "sg:address":"Hauptgasse 33",
    "sg:city":"Willisau",
    "sg:orig_category":"Detailhandel mit Damenbekleidung Detailhandel mit Pelzwaren",
    "sg:phone":"+41 41 970 18 45",
    "sg:postcode":"6130",
    "sg:province":"Luzern",
    "wof:name":"Franz Sigrist Mode In Pelz & Leder",
    "wof:placetype":"venue"
},
  "geometry": {"coordinates":[7.9897689819,47.1202583313],"type":"Point"}
}