{
  "type": "Feature",
  "properties": {
    "iso:country":"CH",
    "sg:address":"Via Casa Del Frate 41",
    "sg:city":"Losone",
    "sg:orig_category":"Detailhandel mit Milcherzeugnissen U Eiern",
    "sg:phone":"+41 81 322 16 12",
    "sg:postcode":"6616",
    "sg:province":"Ticino",
    "wof:name":"Milch-zentrale W.& M.huber",
    "wof:placetype":"venue"
},
  "geometry": {"coordinates":[9.5758867264,46.9818763733],"type":"Point"}
}