{
  "type": "Feature",
  "properties": {
    "iso:country":"CH",
    "sg:address":"Dorfstrasse 12",
    "sg:city":"Safenwil",
    "sg:orig_category":"Instandhaltung U Reparatur von Automobilen",
    "sg:phone":"+41 79 330 54 92",
    "sg:postcode":"5745",
    "sg:province":"Aargau",
    "wof:name":"Garage Woodtli Marcel",
    "wof:placetype":"venue"
},
  "geometry": {"coordinates":[7.9849867821,47.3201904297],"type":"Point"}
}