{
  "type": "Feature",
  "properties": {
    "iso:country":"CH",
    "sg:address":"Weissensteinstrasse 102",
    "sg:city":"Solothurn",
    "sg:orig_category":"Institutionen f\u00fcr Behinderte Tagesheime f\u00fcr Behinderte, gesch\u00fctzte Werkst\u00e4tten",
    "sg:phone":"+41 61 721 14 22",
    "sg:postcode":"4500",
    "sg:province":"Solothurn",
    "wof:name":"Wwb Spitalhof Werkst\u00e4tten-& Wohnzentrum Basel Milchsuppe",
    "wof:placetype":"venue"
},
  "geometry": {"coordinates":[7.5278348923,47.5109062195],"type":"Point"}
}