{
  "type": "Feature",
  "properties": {
    "iso:country":"CH",
    "sg:address":"Rue Farel 3 1860 Aigle. Postfach",
    "sg:city":"Aigle",
    "sg:orig_category":"Vermietung U Verpachtung von eigenen Immobilien",
    "sg:phone":"+41 24 466 40 92",
    "sg:postcode":"1860",
    "sg:province":"Vaud",
    "wof:name":"Agence Immobili\u00e8re Schneeberger Fran\u00e7ois",
    "wof:placetype":"venue"
},
  "geometry": {"coordinates":[6.9690489769,46.3179664612],"type":"Point"}
}