{
  "type": "Feature",
  "properties": {
    "iso:country":"CH",
    "sg:address":"Baslerstrasse 15",
    "sg:city":"Laufenburg",
    "sg:orig_category":"Industrie, Elektronik U Elektrik",
    "sg:phone":"+41 8697900",
    "sg:postcode":"5080",
    "sg:province":"Aargau",
    "wof:name":"Produkteneuheiten Bezugsquellen",
    "wof:placetype":"venue"
},
  "geometry": {"coordinates":[8.058533,47.559601],"type":"Point"}
}