{
  "type": "Feature",
  "properties": {
    "iso:country":"CH",
    "sg:address":"Holzweidweg 36",
    "sg:city":"Rothrist",
    "sg:orig_category":"Sportvereine Ballsport Badminton",
    "sg:phone":"+41 62 752 18 39",
    "sg:postcode":"4852",
    "sg:province":"Aargau",
    "wof:name":"Badminton-club Rothrist",
    "wof:placetype":"venue"
},
  "geometry": {"coordinates":[7.8684492111,47.2955093384],"type":"Point"}
}