{
  "type": "Feature",
  "properties": {
    "iso:country":"CH",
    "sg:address":"Denkmalstrasse 3",
    "sg:city":"Luzern",
    "sg:orig_category":"Hom\u00f6opathie Naturheil\u00e4rzte and Heilpraktiker",
    "sg:postcode":"6006",
    "sg:province":"Luzern",
    "wof:name":"Brigitta Erb Naturheilpraxis",
    "wof:placetype":"venue"
},
  "geometry": {"coordinates":[8.3106079102,47.0574798584],"type":"Point"}
}