{
  "type": "Feature",
  "properties": {
    "iso:country":"CH",
    "sg:address":"Barcelona-strasse 4",
    "sg:city":"M\u00fcnchenstein",
    "sg:orig_category":"Grosshandel mit Getr\u00e4nken",
    "sg:phone":"+41 61 331 60 30",
    "sg:postcode":"4142",
    "sg:province":"Basel-Landschaft",
    "wof:name":"Vinothek Gazzola Gmbh",
    "wof:placetype":"venue"
},
  "geometry": {"coordinates":[7.6075229645,47.5309371948],"type":"Point"}
}