{
  "type": "Feature",
  "properties": {
    "iso:country":"CH",
    "sg:address":"Industriestrasse 40a",
    "sg:city":"Rorschach",
    "sg:orig_category":"Bestattungswesen G\u00fcterbef\u00f6rderung im Strassenverkehr",
    "sg:phone":"+41 71 841 22 15",
    "sg:postcode":"9400",
    "sg:province":"St. Gallen",
    "wof:name":"Richard Keller Muldenservice Bestattungsinstitut",
    "wof:placetype":"venue"
},
  "geometry": {"coordinates":[9.483292,47.475082],"type":"Point"}
}