{
  "type": "Feature",
  "properties": {
    "iso:country":"CH",
    "sg:address":"Langr\u00fctistrasse 68",
    "sg:city":"Einsiedeln",
    "sg:classifiers":[
        {
            "category":"Restaurant",
            "type":"Food & Drink"
        }
    ],
    "sg:phone":"+41 55 412 25 71",
    "sg:postcode":"8840",
    "sg:province":"Schwyz",
    "wof:name":"Restaurant Melone",
    "wof:placetype":"venue"
},
  "geometry": {"coordinates":[8.7426519394,47.123626709],"type":"Point"}
}