{
  "type": "Feature",
  "properties": {
    "iso:country":"CH",
    "sg:address":"Au Signal De Bougy",
    "sg:city":"Bougy-villars",
    "sg:orig_category":"Interessenvertretungen",
    "sg:phone":"+41 21 821 59 30",
    "sg:postcode":"1172",
    "sg:province":"Vaud",
    "wof:name":"Fondation Pr\u00e9-vert Du Signal De Bougy",
    "wof:placetype":"venue"
},
  "geometry": {"coordinates":[6.349105835,46.4814910889],"type":"Point"}
}