{
  "type": "Feature",
  "properties": {
    "iso:country":"CH",
    "sg:address":"Hofstetstrasse 14 9303 Wittenbach. Postfach",
    "sg:city":"Kronb\u00fchl",
    "sg:orig_category":"Druck ohne Zeitungsdruck Offsetdruck",
    "sg:phone":"+41 71 292 29 29",
    "sg:postcode":"9302",
    "wof:name":"Ostschweiz Druck Ag",
    "wof:placetype":"venue"
},
  "geometry": {"coordinates":[9.3930969238,47.4652900696],"type":"Point"}
}