{
  "type": "Feature",
  "properties": {
    "iso:country":"CH",
    "sg:address":"Bodenackerstrasse 79",
    "sg:city":"Dulliken",
    "sg:orig_category":"Sonstiger Grosshandel",
    "sg:postcode":"4657",
    "sg:province":"Solothurn",
    "wof:name":"Haas Walter, Billy-discount.",
    "wof:placetype":"venue"
},
  "geometry": {"coordinates":[9.1381845474,47.5666694641],"type":"Point"}
}