{
  "type": "Feature",
  "properties": {
    "iso:country":"CH",
    "sg:address":"Chr\u00e4nzlerstrasse 10 8302 Kloten. Postfach 311",
    "sg:city":"Kloten",
    "sg:orig_category":"Event Agenturen Herstellung von Werkzeugmaschinen",
    "sg:phone":"+41 55 410 54 93",
    "sg:postcode":"8302",
    "sg:province":"Z\u00fcrich",
    "wof:name":"Android Ventures Gmbh Projekte U. Veranstaltungen In Verbindung Mit Robotertechnik Usw.; Vermarktung, Nutzung",
    "wof:placetype":"venue"
},
  "geometry": {"coordinates":[8.778427124,47.2024307251],"type":"Point"}
}