{
  "type": "Feature",
  "properties": {
    "iso:country":"CH",
    "sg:address":"St.niklaus B.merzligen",
    "sg:city":"Hermrigen",
    "sg:classifiers":[
        {
            "category":"Restaurant",
            "type":"Food & Drink"
        }
    ],
    "sg:phone":"+41 32 381 12 17",
    "sg:postcode":"3274",
    "sg:province":"Bern",
    "wof:name":"Restaurant Waldschenke",
    "wof:placetype":"venue"
},
  "geometry": {"coordinates":[7.2438988686,47.0813140869],"type":"Point"}
}