{
  "type": "Feature",
  "properties": {
    "iso:country":"CH",
    "sg:address":"Chemin Des Batailles 22",
    "sg:city":"Vernier",
    "sg:orig_category":"Handel mit Automobilen",
    "sg:postcode":"1214",
    "sg:province":"Gen\u00e8ve",
    "wof:name":"S M. Aloui",
    "wof:placetype":"venue"
},
  "geometry": {"coordinates":[6.0869297981,46.2209777832],"type":"Point"}
}