{
  "type": "Feature",
  "properties": {
    "iso:country":"CH",
    "sg:address":"Seestrasse 151",
    "sg:city":"St\u00e4fa",
    "sg:orig_category":"Detailhandel mit Fahrr\u00e4dern Handel mit Motorr\u00e4dern, Teilen U Zubeh\u00f6r Instandhaltung U Reparatur von ",
    "sg:phone":"+41 19261822",
    "sg:postcode":"8712",
    "sg:province":"Z\u00fcrich",
    "wof:name":"Veloteria Vinz Niedermann",
    "wof:placetype":"venue"
},
  "geometry": {"coordinates":[8.7342596054,47.2345581055],"type":"Point"}
}