{
  "type": "Feature",
  "properties": {
    "iso:country":"CH",
    "sg:address":"Im Unteren Letten 4",
    "sg:city":"Duggingen",
    "sg:orig_category":"Sonstige mit der Informatik verbundene T\u00e4tigkeiten Sonstiger Fachdetailhandel in Verkaufsr\u00e4umen",
    "sg:phone":"+41 61 751 52 39",
    "sg:postcode":"4202",
    "sg:province":"Basel-Landschaft",
    "wof:name":"Daniel Dubler Unternehmensberatung",
    "wof:placetype":"venue"
},
  "geometry": {"coordinates":[7.6095471382,47.4540100098],"type":"Point"}
}