{
  "type": "Feature",
  "properties": {
    "iso:country":"CH",
    "sg:address":"Schw\u00e4rzere",
    "sg:city":"Koppigen",
    "sg:orig_category":"Planer f\u00fcr Alternativenergie and Solararchitektur Technische B\u00fcros Heizung, L\u00fcftung, Klima",
    "sg:phone":"+41 34 413 22 97",
    "sg:postcode":"3425",
    "sg:province":"Bern",
    "wof:name":"Christoph Gubser Planungsb\u00fcro Energieberatung",
    "wof:placetype":"venue"
},
  "geometry": {"coordinates":[7.6063499451,47.1334915161],"type":"Point"}
}