{
  "type": "Feature",
  "properties": {
    "iso:country":"CH",
    "sg:address":"Route De La Bordinette 5 1094 Paudex Case Postale 40",
    "sg:city":"Paudex",
    "sg:orig_category":"Primarschulen",
    "sg:phone":"+41 79 204 12 65",
    "sg:postcode":"1094",
    "sg:province":"Vaud",
    "wof:name":"Ecole Primaire",
    "wof:placetype":"venue"
},
  "geometry": {"coordinates":[6.5165247917,46.6591186523],"type":"Point"}
}