{
  "type": "Feature",
  "properties": {
    "iso:country":"CH",
    "sg:address":"8836",
    "sg:city":"Bennau",
    "sg:orig_category":"Personenbef\u00f6rderung im Linienverkehr zu Land",
    "sg:phone":"+41 55 412 11 50",
    "sg:postcode":"8836",
    "sg:province":"Schwyz",
    "wof:name":"Skilift Biberbrugg Ag",
    "wof:placetype":"venue"
},
  "geometry": {"coordinates":[8.7297801971,47.1484413147],"type":"Point"}
}