{
  "type": "Feature",
  "properties": {
    "iso:country":"CH",
    "sg:address":"Fischerweg 15 3012 Bern. Postfach",
    "sg:city":"Bern",
    "sg:orig_category":"Grosshandel mit Nahrungsmitteln, Getr\u00e4nken U Tabakwaren ohne ausgepr\u00e4gten Schwerpunkt",
    "sg:postcode":"3005",
    "sg:province":"Bern",
    "wof:name":"Marie Kistler-st\u00e4heli Lebensmittel-handel.",
    "wof:placetype":"venue"
},
  "geometry": {"coordinates":[7.4373550415,46.9548873901],"type":"Point"}
}