{
  "type": "Feature",
  "properties": {
    "iso:country":"CH",
    "sg:address":"M\u00f6hrlistrasse 97 8000 Z\u00fcrich. Postfach",
    "sg:city":"Z\u00fcrich",
    "sg:orig_category":"Mit dem Versicherungsgewerbe verbundene T\u00e4tigkeiten",
    "sg:postcode":"8001",
    "sg:province":"Z\u00fcrich",
    "wof:name":"Capital City Ltd",
    "wof:placetype":"venue"
},
  "geometry": {"coordinates":[8.5459814072,47.3925971985],"type":"Point"}
}