{
  "type": "Feature",
  "properties": {
    "iso:country":"CH",
    "sg:address":"Hohe Promenade",
    "sg:city":"Arosa",
    "sg:orig_category":"Malerei",
    "sg:phone":"+41 81 377 13 86",
    "sg:postcode":"7050",
    "sg:province":"Graubunden",
    "wof:name":"Peter Altmann Malergesch\u00e4ft",
    "wof:placetype":"venue"
},
  "geometry": {"coordinates":[9.6741228104,46.777507782],"type":"Point"}
}