{
  "type": "Feature",
  "properties": {
    "iso:country":"CH",
    "sg:address":"8560",
    "sg:city":"M\u00e4rstetten",
    "sg:orig_category":"Abwasserreinigung",
    "sg:phone":"+41 55 283 23 93",
    "sg:postcode":"8560",
    "sg:province":"Thurgau",
    "wof:name":"Abwasserreinigungsanlage Dorf",
    "wof:placetype":"venue"
},
  "geometry": {"coordinates":[9.00542,47.197639],"type":"Point"}
}