{
  "type": "Feature",
  "properties": {
    "iso:country":"CH",
    "sg:address":"Niederdorfstrasse 64",
    "sg:city":"Z\u00fcrich",
    "sg:classifiers":[
        {
            "category":"Restaurant",
            "type":"Food & Drink"
        }
    ],
    "sg:phone":"+41 12514133",
    "sg:postcode":"8001",
    "sg:province":"Z\u00fcrich",
    "wof:name":"Zum Schwarzen Chessel Restaurant",
    "wof:placetype":"venue"
},
  "geometry": {"coordinates":[8.5440359116,47.3754653931],"type":"Point"}
}