{
  "type": "Feature",
  "properties": {
    "iso:country":"CH",
    "sg:address":"Bellerivestrasse 53 8008 Z\u00fcrich. Postfach",
    "sg:city":"Z\u00fcrich",
    "sg:orig_category":"Datenbanken",
    "sg:postcode":"8001",
    "sg:province":"Z\u00fcrich",
    "wof:name":"Medical Network Emn Ag Informations, Fortbildungsprogramme F\u00fcr Oder \u00fcber Elektron. Medien Usw.; Herstellung, Verbreitung Usw",
    "wof:placetype":"venue"
},
  "geometry": {"coordinates":[8.551727,47.356361],"type":"Point"}
}