{
  "type": "Feature",
  "properties": {
    "iso:country":"CH",
    "sg:address":"Corso San Gottardo 89",
    "sg:city":"Chiasso",
    "sg:orig_category":"Unternehmensberatung -\u00dcbersetzungsb\u00fcros",
    "sg:phone":"+41 91 682 67 78",
    "sg:postcode":"6830",
    "sg:province":"Ticino",
    "wof:name":"Danna Giovanni",
    "wof:placetype":"venue"
},
  "geometry": {"coordinates":[9.0256509781,45.8360481262],"type":"Point"}
}