{
  "type": "Feature",
  "properties": {
    "iso:country":"CH",
    "sg:address":"3182",
    "sg:city":"Ueberstorf",
    "sg:orig_category":"Pensionskassen",
    "sg:postcode":"3182",
    "sg:province":"Fribourg",
    "wof:name":"Personalf\u00fcrsorgestiftung Der Landwirtschaftlichen Genossenschaft Ueberstorf Und Umgebung",
    "wof:placetype":"venue"
},
  "geometry": {"coordinates":[7.3105697632,46.8647842407],"type":"Point"}
}