{
  "type": "Feature",
  "properties": {
    "iso:country":"CH",
    "sg:address":"Mol\u00e9son Avenue Du 7",
    "sg:city":"Fribourg",
    "sg:orig_category":"Finanzierungsinstitutionen",
    "sg:phone":"+41 26 321 12 30",
    "sg:postcode":"1700",
    "sg:province":"Fribourg",
    "wof:name":"Les Jardins Du Couchant Sa",
    "wof:placetype":"venue"
},
  "geometry": {"coordinates":[7.1536831856,46.8037452698],"type":"Point"}
}