{
  "type": "Feature",
  "properties": {
    "iso:country":"CH",
    "sg:address":"Hebelstrasse 96 4056 Basel. Postfach",
    "sg:city":"Basel",
    "sg:orig_category":"Non-Classified Establishments",
    "sg:phone":"+41 61 279 78 95",
    "sg:postcode":"4056",
    "sg:province":"Basel-Stadt",
    "wof:name":"Meskif Holding Ag",
    "wof:placetype":"venue"
},
  "geometry": {"coordinates":[7.5779600143,47.563041687],"type":"Point"}
}