{
  "type": "Feature",
  "properties": {
    "iso:country":"CH",
    "sg:address":"Stosswald 5",
    "sg:city":"Lustm\u00fchle",
    "sg:orig_category":"Politische Parteien CVP",
    "sg:phone":"+41 71 333 22 43",
    "sg:postcode":"9062",
    "sg:province":"Appenzell Ausserrhoden",
    "wof:name":"Cvp Ortspartei Teufen",
    "wof:placetype":"venue"
},
  "geometry": {"coordinates":[9.3601818085,47.3985443115],"type":"Point"}
}