{
  "type": "Feature",
  "properties": {
    "iso:country":"CH",
    "sg:address":"Moosstrasse 2 3073 G\u00fcmligen. Postfach",
    "sg:city":"G\u00fcmligen",
    "sg:orig_category":"Grosshandel mit Getreide, Saatgut U Futtermitteln",
    "sg:phone":"+41 32 961 13 95",
    "sg:postcode":"3073",
    "sg:province":"Bern",
    "wof:name":"Godat Pierre",
    "wof:placetype":"venue"
},
  "geometry": {"coordinates":[6.8857798576,47.1768188477],"type":"Point"}
}