{
  "type": "Feature",
  "properties": {
    "iso:country":"CH",
    "sg:address":"Herisauerstrasse 20",
    "sg:city":"Gossau",
    "sg:classifiers":[
        {
            "category":"Banks & Credit Unions",
            "subcategory":"Bank",
            "type":"Services"
        }
    ],
    "sg:phone":"+41 4171854848",
    "sg:postcode":"9202",
    "wof:name":"Schweiz. Mobiliar",
    "wof:placetype":"venue"
},
  "geometry": {"coordinates":[9.249016,47.414482],"type":"Point"}
}