{
  "type": "Feature",
  "properties": {
    "iso:country":"CH",
    "sg:address":"Gartenstrasse 2",
    "sg:city":"Zug",
    "sg:orig_category":"Finanzierungsinstitutionen",
    "sg:postcode":"6300",
    "sg:province":"Zug",
    "wof:name":"Eb Marketing- + Vertriebs- Consulting Gmbh",
    "wof:placetype":"venue"
},
  "geometry": {"coordinates":[8.5151453018,47.1702308655],"type":"Point"}
}