{
  "type": "Feature",
  "properties": {
    "iso:country":"CH",
    "sg:address":"Tribschenstrasse 7",
    "sg:city":"Luzern",
    "sg:orig_category":"Betrieb U technische Hilfsdienste des Kultur U Unterhaltungswesens",
    "sg:postcode":"6005",
    "sg:province":"Luzern",
    "wof:name":"Inspe Gmbh",
    "wof:placetype":"venue"
},
  "geometry": {"coordinates":[8.3125286102,47.044052124],"type":"Point"}
}