{
  "type": "Feature",
  "properties": {
    "iso:country":"CH",
    "sg:address":"Hauptstrasse 34 8355 Aadorf. Postfach",
    "sg:city":"Aadorf",
    "sg:orig_category":"Kauf U Verkauf von Immobilien auf eigene Rechnung Vermittlung von Immobilien",
    "sg:phone":"+41 52 365 05 46",
    "sg:postcode":"8355",
    "sg:province":"Thurgau",
    "wof:name":"Immo-trust, Imhof + Hotz Gmbh",
    "wof:placetype":"venue"
},
  "geometry": {"coordinates":[8.8955020905,47.4925727844],"type":"Point"}
}