{
  "type": "Feature",
  "properties": {
    "iso:country":"CH",
    "sg:address":"L\u00f6wenstrasse 35",
    "sg:city":"Z\u00fcrich",
    "sg:orig_category":"Detailhandel mit Schuhen",
    "sg:phone":"+41 55 210 42 32",
    "sg:postcode":"8001",
    "sg:province":"Z\u00fcrich",
    "wof:name":"Pasito Ag",
    "wof:placetype":"venue"
},
  "geometry": {"coordinates":[8.8189811707,47.2271575928],"type":"Point"}
}