{
  "type": "Feature",
  "properties": {
    "iso:country":"CH",
    "sg:address":"Chlosterb\u00fcel 46",
    "sg:city":"Sch\u00fcpfheim",
    "sg:orig_category":"Grosshandel mit lebenden Tieren",
    "sg:phone":"+41 41 484 22 71",
    "sg:postcode":"6170",
    "sg:province":"Luzern",
    "wof:name":"Gottfried Emmenegger Viehhandel",
    "wof:placetype":"venue"
},
  "geometry": {"coordinates":[8.0255270004,46.9605255127],"type":"Point"}
}