{
  "type": "Feature",
  "properties": {
    "iso:country":"CH",
    "sg:address":"Zugerstrasse 53",
    "sg:city":"Baar",
    "sg:orig_category":"Berufliche Weiterbildung, Erwachsenenbildung Sprachschulen",
    "sg:phone":"+41 41 760 31 00",
    "sg:postcode":"6340",
    "sg:province":"Zug",
    "wof:name":"Institut F\u00fcr Aktives Lernen Gmbh",
    "wof:placetype":"venue"
},
  "geometry": {"coordinates":[8.520894,47.185783],"type":"Point"}
}