{
  "type": "Feature",
  "properties": {
    "iso:country":"CH",
    "sg:address":"Mittlerer Kreis 2",
    "sg:city":"Therwil",
    "sg:orig_category":"Arztpraxen",
    "sg:phone":"+41 61 811 40 50",
    "sg:postcode":"4106",
    "sg:province":"Basel-Landschaft",
    "wof:name":"Dr.med.thomas Reichenstein Spezialarzt Fmh",
    "wof:placetype":"venue"
},
  "geometry": {"coordinates":[7.72126,47.527882],"type":"Point"}
}