{
  "type": "Feature",
  "properties": {
    "iso:country":"CH",
    "sg:address":"Hochrainstrasse 20 6010 Kriens. Postfach 261",
    "sg:city":"Kriens",
    "sg:orig_category":"Detailhandel mit elektrischen Haushalts-,Radio U Fernsehger\u00e4ten sowie Musikinstrumenten",
    "sg:phone":"+41 41 310 10 09",
    "sg:postcode":"6011",
    "sg:province":"Luzern",
    "wof:name":"Radio Tv Ruckstuhl",
    "wof:placetype":"venue"
},
  "geometry": {"coordinates":[8.2894926071,47.0344238281],"type":"Point"}
}