{
  "type": "Feature",
  "properties": {
    "iso:country":"CH",
    "sg:address":"Oberwiesenstrasse",
    "sg:city":"Wallisellen",
    "sg:orig_category":"Handel mit Motorr\u00e4dern, Teilen U Zubeh\u00f6r Instandhaltung U Reparatur von Motorr\u00e4dern",
    "sg:phone":"+41 18305657",
    "sg:postcode":"8304",
    "sg:province":"Z\u00fcrich",
    "wof:name":"Merlino Giuseppe",
    "wof:placetype":"venue"
},
  "geometry": {"coordinates":[8.5884866714,47.4131317139],"type":"Point"}
}