{
  "type": "Feature",
  "properties": {
    "iso:country":"CH",
    "sg:address":"Hauptstrasse 30 9436 Balgach. Postfach",
    "sg:city":"Balgach",
    "sg:orig_category":"Gesundheitswesen",
    "sg:phone":"+41 71 722 34 32",
    "sg:postcode":"9436",
    "sg:province":"St. Gallen",
    "wof:name":"Aquadrom Knobelspiess Richard Schulungen, Vortr\u00e4ge U. Kurse Im Wellness, Fitness- U. Gesundheitsbereich Usw",
    "wof:placetype":"venue"
},
  "geometry": {"coordinates":[9.6096153259,47.407371521],"type":"Point"}
}