{
  "type": "Feature",
  "properties": {
    "iso:country":"CH",
    "sg:address":"Rue De L'h\u00f4pital 42",
    "sg:city":"Del\u00e9mont",
    "sg:orig_category":"Detailhandel mit Ton U Bildtr\u00e4gern Vermietung von Gebrauchsg\u00fctern",
    "sg:phone":"+41 32 423 24 60",
    "sg:postcode":"2800",
    "sg:province":"Jura",
    "wof:name":"Mp Video, Pouillard Martial",
    "wof:placetype":"venue"
},
  "geometry": {"coordinates":[7.3439698219,47.3653488159],"type":"Point"}
}