{
  "type": "Feature",
  "properties": {
    "iso:country":"CH",
    "sg:address":"Via Marcetto 28",
    "sg:city":"Novazzano",
    "sg:orig_category":"Arztpraxen",
    "sg:phone":"+41 91 683 83 34",
    "sg:postcode":"6883",
    "sg:province":"Ticino",
    "wof:name":"Dott.med.adrian B\u00fchrer Specialista Fmh",
    "wof:placetype":"venue"
},
  "geometry": {"coordinates":[8.982369,45.837067],"type":"Point"}
}