{
  "type": "Feature",
  "properties": {
    "iso:country":"CH",
    "sg:address":"Murbacherstrasse 3",
    "sg:city":"Luzern",
    "sg:orig_category":"Interessenvertretungen",
    "sg:postcode":"6003",
    "sg:province":"Luzern",
    "wof:name":"Huber-fond",
    "wof:placetype":"venue"
},
  "geometry": {"coordinates":[8.5438156128,47.3280067444],"type":"Point"}
}