{
  "type": "Feature",
  "properties": {
    "iso:country":"CH",
    "sg:address":"Gotthardstrasse 11 8800 Thalwil. Postfach",
    "sg:city":"Thalwil",
    "sg:orig_category":"Verwaltung der Rechtspflege, Gerichte",
    "sg:phone":"+41 17231240",
    "sg:postcode":"8800",
    "sg:province":"Z\u00fcrich",
    "wof:name":"Notariat,grundbuch-& Konkursamt Thalwil",
    "wof:placetype":"venue"
},
  "geometry": {"coordinates":[8.5650806427,47.294052124],"type":"Point"}
}