{
  "type": "Feature",
  "properties": {
    "iso:country":"CH",
    "sg:address":"Beim Skilift",
    "sg:city":"Bumbach",
    "sg:classifiers":[
        {
            "category":"Travel",
            "subcategory":"Hotels & Motels",
            "type":"Entertainment"
        }
    ],
    "sg:phone":"+41 34 493 34 37",
    "sg:postcode":"6197",
    "sg:province":"Bern",
    "sg:tags":[
        "hotels",
        "mit",
        "restaurant"
    ],
    "wof:name":"Hotel Rosegg",
    "wof:placetype":"venue"
},
  "geometry": {"coordinates":[7.8605628014,46.8275260925],"type":"Point"}
}