{
  "type": "Feature",
  "properties": {
    "iso:country":"CH",
    "sg:address":"6383 Dallenwil. Postfach 30",
    "sg:city":"Dallenwil",
    "sg:orig_category":"Sportvereine Ski",
    "sg:phone":"+41 81 416 47 49",
    "sg:postcode":"6383",
    "sg:province":"Nidwalden",
    "wof:name":"Skiclub Davos",
    "wof:placetype":"venue"
},
  "geometry": {"coordinates":[9.8402700424,46.8057403564],"type":"Point"}
}