{
  "type": "Feature",
  "properties": {
    "addr:full":"Dahlienweg 11 Oftringen Aargau 4665",
    "addr:housenumber":"11",
    "addr:postcode":"4665",
    "addr:street":"Dahlienweg",
    "iso:country":"CH",
    "sg:address":"Dahlienweg 11",
    "sg:city":"Oftringen",
    "sg:orig_category":"Architekturb\u00fcros",
    "sg:phone":"+41 71 244 12 39",
    "sg:postcode":"4665",
    "sg:province":"Aargau",
    "wof:name":"J\u00fcrg Ineichen Architekturb\u00fcro",
    "wof:placetype":"venue"
},
  "geometry": {"coordinates":[9.384329,47.435532],"type":"Point"}
}