{
  "type": "Feature",
  "properties": {
    "iso:country":"CH",
    "sg:address":"Mythencenterstrasse 18",
    "sg:city":"Ibach",
    "sg:orig_category":"Drogerien",
    "sg:phone":"+41 71 244 88 47",
    "sg:postcode":"6438",
    "sg:province":"Schwyz",
    "wof:name":"M\u00fcller's Drogerie Gmbh Drogerie. Natur- U. Gesundheitsprodukte; Handel, Einkauf U. Verkauf Usw.",
    "wof:placetype":"venue"
},
  "geometry": {"coordinates":[9.3909835815,47.4301605225],"type":"Point"}
}