{
  "type": "Feature",
  "properties": {
    "iso:country":"CH",
    "sg:address":"Simonstrasse 11 3012 Bern. Postfach",
    "sg:city":"Bern",
    "sg:orig_category":"Detailhandel mit Brot, Back U S\u00fcsswaren",
    "sg:phone":"+41 31 301 15 61",
    "sg:postcode":"3005",
    "sg:province":"Bern",
    "wof:name":"R. K\u00fcnzli B\u00e4ckerei-konditorei.",
    "wof:placetype":"venue"
},
  "geometry": {"coordinates":[7.433924,46.958248],"type":"Point"}
}