{
  "type": "Feature",
  "properties": {
    "iso:country":"CH",
    "sg:address":"Im Fahr 2",
    "sg:city":"Auenstein",
    "sg:orig_category":"Sportvereine Turnen Vereine Damen",
    "sg:phone":"+41 62 897 43 02",
    "sg:postcode":"5105",
    "sg:province":"Aargau",
    "wof:name":"Turnverein Stv Auenstein",
    "wof:placetype":"venue"
},
  "geometry": {"coordinates":[8.1541872025,47.4165802002],"type":"Point"}
}