{
  "type": "Feature",
  "properties": {
    "iso:country":"CH",
    "sg:address":"Apollostrasse 8 8032 Z\u00fcrich. Postfach 8032 Z\u00fcrich",
    "sg:city":"Zust",
    "sg:orig_category":"Unternehmensberatung",
    "sg:phone":"+41 13805177",
    "sg:postcode":"32",
    "wof:name":"Transphere Network Ag Komplexe Transformationsprozesse In Unternehmen Usw.; Management",
    "wof:placetype":"venue"
},
  "geometry": {"coordinates":[8.5559139252,47.3647041321],"type":"Point"}
}