{
  "type": "Feature",
  "properties": {
    "iso:country":"CH",
    "sg:address":"Les Champs A",
    "sg:city":"Oron-la-ville",
    "sg:orig_category":"Vermietung U Verpachtung von eigenen Immobilien",
    "sg:postcode":"1610",
    "sg:province":"Vaud",
    "wof:name":"Inter-casas S\u00e0rl",
    "wof:placetype":"venue"
},
  "geometry": {"coordinates":[6.8332290649,46.5655708313],"type":"Point"}
}