{
  "type": "Feature",
  "properties": {
    "iso:country":"CH",
    "sg:address":"Herbstackerstrasse 55a",
    "sg:city":"Seuzach",
    "sg:orig_category":"Unclassifiable Establishments",
    "sg:postcode":"8472",
    "sg:province":"Z\u00fcrich",
    "wof:name":"Swyss Application Engineering Gmbh",
    "wof:placetype":"venue"
},
  "geometry": {"coordinates":[8.7403745651,47.5378990173],"type":"Point"}
}