{
  "type": "Feature",
  "properties": {
    "iso:country":"CH",
    "sg:address":"Centro Luserte 2",
    "sg:city":"Quartino",
    "sg:classifiers":[
        {
            "category":"Home & Garden",
            "subcategory":"Home Furnishings",
            "type":"Retail Goods"
        }
    ],
    "sg:phone":"+41 91 858 20 37",
    "sg:postcode":"6572",
    "sg:province":"Ticino",
    "sg:tags":[
        "medicine",
        "bathroom",
        "cupboards",
        "cabinet"
    ],
    "wof:name":"L. & A. Caviola Armadi Componibili E Arredamenti",
    "wof:placetype":"venue"
},
  "geometry": {"coordinates":[8.91219,46.152325],"type":"Point"}
}