{
  "type": "Feature",
  "properties": {
    "iso:country":"CH",
    "sg:address":"Hauptstrasse 92",
    "sg:city":"B\u00f6nigen",
    "sg:orig_category":"Sportvereine Turnen",
    "sg:phone":"+41 32 384 39 15",
    "sg:postcode":"3806",
    "sg:province":"Bern",
    "wof:name":"Turnverein Stv B\u00fcren A/aare",
    "wof:placetype":"venue"
},
  "geometry": {"coordinates":[7.3792638779,47.1449279785],"type":"Point"}
}