{
  "type": "Feature",
  "properties": {
    "iso:country":"CH",
    "sg:address":"Parkterasse 10 3000 Bern. Postfach",
    "sg:city":"Bern",
    "sg:orig_category":"RESTAURANTS: TEA-ROOMS",
    "sg:postcode":"3003",
    "sg:province":"Bern",
    "wof:name":"Passerelle Da Vinci Venturo Vincenzo",
    "wof:placetype":"venue"
},
  "geometry": {"coordinates":[7.4378871918,46.9497108459],"type":"Point"}
}