{
  "type": "Feature",
  "properties": {
    "iso:country":"CH",
    "sg:address":"Rue Voltaire 18",
    "sg:city":"Gen\u00e8ve",
    "sg:orig_category":"Detailhandel mit Waren verschiedener Art, Hauptrichtung Nahrungsmittel",
    "sg:phone":"+41 22 949 09 49",
    "sg:postcode":"1201",
    "sg:province":"Gen\u00e8ve",
    "wof:name":"Coop Voltaire",
    "wof:placetype":"venue"
},
  "geometry": {"coordinates":[6.1372671127,46.2079772949],"type":"Point"}
}