{
  "type": "Feature",
  "properties": {
    "iso:country":"CH",
    "sg:address":"Knettnauweg 11",
    "sg:city":"Nidau",
    "sg:orig_category":"Gartenbau",
    "sg:postcode":"2560",
    "sg:province":"Bern",
    "wof:name":"Gantenbein Hanspeter",
    "wof:placetype":"venue"
},
  "geometry": {"coordinates":[7.2400631905,47.1239624023],"type":"Point"}
}