{
  "type": "Feature",
  "properties": {
    "addr:full":"Teufener Strasse 61 St.gallen St. Gallen 9000",
    "addr:housenumber":"61",
    "addr:postcode":"9000",
    "addr:street":"Teufener Strasse",
    "iso:country":"CH",
    "sg:address":"Teufener Strasse 61",
    "sg:city":"St.gallen",
    "sg:orig_category":"Architektur U Ingenieurb\u00fcros",
    "sg:phone":"+41 71 220 90 20",
    "sg:postcode":"9000",
    "sg:province":"St. Gallen",
    "wof:name":"Thurnheer + Gloor Gmbh",
    "wof:placetype":"venue"
},
  "geometry": {"coordinates":[9.367575,47.41745],"type":"Point"}
}