{
  "type": "Feature",
  "properties": {
    "iso:country":"CH",
    "sg:address":"Rue Du Vieux-village",
    "sg:city":"Bramois",
    "sg:classifiers":[
        {
            "category":"Government",
            "subcategory":"Post Office",
            "type":"Public Place"
        }
    ],
    "sg:phone":"+41 27 203 13 85",
    "sg:postcode":"1967",
    "sg:province":"Valais",
    "sg:tags":[
        "caf\u00e9s",
        "tea-rooms"
    ],
    "wof:name":"Tea-room Les Arcades",
    "wof:placetype":"venue"
},
  "geometry": {"coordinates":[7.4049649239,46.2329978943],"type":"Point"}
}