{
  "type": "Feature",
  "properties": {
    "iso:country":"CH",
    "sg:address":"Churerstrasse 48 8852 Altendorf. Postfach",
    "sg:city":"Altendorf",
    "sg:orig_category":"Architektur U Ingenieurb\u00fcros",
    "sg:phone":"+41 79 216 77 07",
    "sg:postcode":"8852",
    "sg:province":"Schwyz",
    "wof:name":"Hiestand Ingenieurb\u00fcro",
    "wof:placetype":"venue"
},
  "geometry": {"coordinates":[8.836427,47.189808],"type":"Point"}
}