{
  "type": "Feature",
  "properties": {
    "iso:country":"CH",
    "sg:address":"Ballasti\u00e8re La Zi",
    "sg:city":"Gland",
    "sg:orig_category":"Interessenvertretungen",
    "sg:postcode":"1196",
    "sg:province":"Vaud",
    "wof:name":"Apic, Jean-luc Th\u00e9venaz",
    "wof:placetype":"venue"
},
  "geometry": {"coordinates":[6.2602601051,46.4152374268],"type":"Point"}
}