{
  "type": "Feature",
  "properties": {
    "iso:country":"CH",
    "sg:address":"Pierre Rue Saint- 4",
    "sg:city":"Fribourg",
    "sg:orig_category":"G\u00fcterbef\u00f6rderung im Strassenverkehr",
    "sg:postcode":"1700",
    "sg:province":"Fribourg",
    "wof:name":"Art Transit & Associ\u00e9s Sa",
    "wof:placetype":"venue"
},
  "geometry": {"coordinates":[7.1546912193,46.8035240173],"type":"Point"}
}