{
  "type": "Feature",
  "properties": {
    "iso:country":"CH",
    "sg:address":"Hottingerstrasse 5",
    "sg:city":"Z\u00fcrich",
    "sg:orig_category":"Zahnarztpraxen",
    "sg:phone":"+41 12528282",
    "sg:postcode":"8032",
    "sg:province":"Z\u00fcrich",
    "wof:name":"Dr. Med. Dent. Rudolf M\u00fcller Zahnarzt",
    "wof:placetype":"venue"
},
  "geometry": {"coordinates":[8.5497665405,47.3705558777],"type":"Point"}
}