{
  "type": "Feature",
  "properties": {
    "iso:country":"CH",
    "sg:address":"Tirolerweg 4",
    "sg:city":"Zug",
    "sg:orig_category":"Gesundheitswesen",
    "sg:phone":"+41 56 633 71 69",
    "sg:postcode":"6300",
    "sg:province":"Zug",
    "wof:name":"Sibler B., Masseurin Svbm",
    "wof:placetype":"venue"
},
  "geometry": {"coordinates":[8.344452858,47.3506698608],"type":"Point"}
}