{
  "type": "Feature",
  "properties": {
    "iso:country":"CH",
    "sg:address":"Turmstrasse",
    "sg:city":"Flums",
    "sg:orig_category":"Allgemeiner Hoch U Tiefbau",
    "sg:phone":"+41 81 723 50 72",
    "sg:postcode":"8890",
    "sg:province":"St. Gallen",
    "wof:name":"John & Sommer Ag",
    "wof:placetype":"venue"
},
  "geometry": {"coordinates":[9.345206,47.09164],"type":"Point"}
}