{
  "type": "Feature",
  "properties": {
    "iso:country":"CH",
    "sg:address":"Richard Wagner-strasse 19",
    "sg:city":"Z\u00fcrich",
    "sg:orig_category":"Architektur U Ingenieurb\u00fcros",
    "sg:phone":"+41 12014539",
    "sg:postcode":"8002",
    "sg:province":"Z\u00fcrich",
    "wof:name":"Fl\u00fcckiger + Bosshard Ag",
    "wof:placetype":"venue"
},
  "geometry": {"coordinates":[8.532856,47.359787],"type":"Point"}
}