{
  "type": "Feature",
  "properties": {
    "iso:country":"CH",
    "sg:address":"Staatsstrasse 67",
    "sg:city":"S\u00e4riswil",
    "sg:orig_category":"Herstellung von Metallkonstruktionen Mechanische Werkst\u00e4tten",
    "sg:phone":"+41 31 829 01 94",
    "sg:postcode":"3044",
    "sg:province":"Bern",
    "wof:name":"Hans-ulrich Wiedmer Mech.werkst\u00e4tte & Metallbau",
    "wof:placetype":"venue"
},
  "geometry": {"coordinates":[7.3469409943,46.9944877625],"type":"Point"}
}