{
  "type": "Feature",
  "properties": {
    "iso:country":"CH",
    "sg:address":"Stadtmannhaus",
    "sg:city":"Gr\u00fcningen",
    "sg:orig_category":"Sonstiger spezialisierter Hoch U Tiefbau",
    "sg:postcode":"8627",
    "sg:province":"Z\u00fcrich",
    "wof:name":"Frischknecht Peter, Maurerarbeiten Und Holzschlag",
    "wof:placetype":"venue"
},
  "geometry": {"coordinates":[8.763625145,47.2843704224],"type":"Point"}
}