{
  "type": "Feature",
  "properties": {
    "iso:country":"CH",
    "sg:address":"Ennetb\u00fchlerstrasse 12",
    "sg:city":"Ennenda",
    "sg:orig_category":"Verlegen von Fliesen U Platten",
    "sg:phone":"+41 55 640 82 57",
    "sg:postcode":"8755",
    "sg:province":"Glarus",
    "wof:name":"Peter Streiff Ofenbau Plattenbel\u00e4ge",
    "wof:placetype":"venue"
},
  "geometry": {"coordinates":[9.0773458481,47.0352897644],"type":"Point"}
}