{
  "type": "Feature",
  "properties": {
    "iso:country":"CH",
    "sg:address":"Kreuzbuchstrasse 39",
    "sg:city":"Luzern",
    "sg:orig_category":"Maler U Glasergewerbe",
    "sg:postcode":"6006",
    "sg:province":"Luzern",
    "wof:name":"B\u00fchlmann S\u00f6hne Ag",
    "wof:placetype":"venue"
},
  "geometry": {"coordinates":[8.3372831345,47.0544548035],"type":"Point"}
}