{
  "type": "Feature",
  "properties": {
    "iso:country":"CH",
    "sg:address":"Egeten",
    "sg:city":"Werdenberg",
    "sg:orig_category":"Rebbau",
    "sg:phone":"+41 81 771 27 45",
    "sg:postcode":"9470",
    "sg:province":"St. Gallen",
    "wof:name":"Rudolf Sigrist Weinbau",
    "wof:placetype":"venue"
},
  "geometry": {"coordinates":[9.4603176117,47.1669387817],"type":"Point"}
}