{
  "type": "Feature",
  "properties": {
    "iso:country":"CH",
    "sg:address":"Ch. Des Crosettes 43",
    "sg:city":"Jongny",
    "sg:orig_category":"Detailhandel mit Metallwaren, Anstrichmitteln, Glaswaren, Bau U Heimwerkerbedarf",
    "sg:postcode":"1805",
    "sg:province":"Vaud",
    "wof:name":"Cherbuin Claude, Combined Technologies Comtech",
    "wof:placetype":"venue"
},
  "geometry": {"coordinates":[6.8493142128,46.4860115051],"type":"Point"}
}