{
  "type": "Feature",
  "properties": {
    "addr:full":"Steinbitzweg 10 Auenstein Aargau 5105",
    "addr:housenumber":"10",
    "addr:postcode":"5105",
    "addr:street":"Steinbitzweg",
    "iso:country":"CH",
    "sg:address":"Steinbitzweg 10",
    "sg:city":"Auenstein",
    "sg:orig_category":"Blumen U Zierpflanzenbau Gem\u00fcsebau",
    "sg:phone":"+41 62 893 14 44",
    "sg:postcode":"5105",
    "sg:province":"Aargau",
    "wof:name":"Weber & Co G\u00e4rtnerei",
    "wof:placetype":"venue"
},
  "geometry": {"coordinates":[8.134981,47.416702],"type":"Point"}
}