{
  "type": "Feature",
  "properties": {
    "iso:country":"CH",
    "sg:address":"Neubadstrasse 81",
    "sg:city":"Basel",
    "sg:orig_category":"Malerei",
    "sg:phone":"+41 61 361 69 95",
    "sg:postcode":"4054",
    "sg:province":"Basel-Stadt",
    "wof:name":"Urs Hasler Malergesch\u00e4ft",
    "wof:placetype":"venue"
},
  "geometry": {"coordinates":[7.5697832108,47.5488586426],"type":"Point"}
}