{
  "type": "Feature",
  "properties": {
    "iso:country":"CH",
    "sg:address":"Steinernstrasse 4",
    "sg:city":"Ottenbach",
    "sg:orig_category":"Tanzschulen, Tanzlehrer",
    "sg:phone":"+41 17612406",
    "sg:postcode":"8913",
    "sg:province":"Z\u00fcrich",
    "wof:name":"Nina Corti Tanzstudio",
    "wof:placetype":"venue"
},
  "geometry": {"coordinates":[8.4033679962,47.2840576172],"type":"Point"}
}