{
  "type": "Feature",
  "properties": {
    "iso:country":"CH",
    "sg:address":"Dorf",
    "sg:city":"M\u00f6tschwil",
    "sg:orig_category":"Erschliessung Kauf U Verkauf von Immobilien Vermietung U Verpachtung von eigenen Immobilien",
    "sg:phone":"+41 34 423 50 60",
    "sg:postcode":"3324",
    "sg:province":"Bern",
    "wof:name":"Bauform Creativ Ag",
    "wof:placetype":"venue"
},
  "geometry": {"coordinates":[7.5693049431,47.0496864319],"type":"Point"}
}