{
  "type": "Feature",
  "properties": {
    "iso:country":"CH",
    "sg:address":"Heidenerstrasse 66 9404 Rorschacherberg. Postfach",
    "sg:city":"Rorschacherberg",
    "sg:orig_category":"Kantinen",
    "sg:phone":"+41 71 855 50 55",
    "sg:postcode":"9404",
    "sg:province":"St. Gallen",
    "wof:name":"Mountain-food Gmbh",
    "wof:placetype":"venue"
},
  "geometry": {"coordinates":[9.5083999634,47.4706497192],"type":"Point"}
}