{
  "type": "Feature",
  "properties": {
    "iso:country":"CH",
    "sg:address":"Z\u00fcrcherstrasse 43",
    "sg:city":"Uznach",
    "sg:orig_category":"Massagestudios",
    "sg:phone":"+41 55 280 17 70",
    "sg:postcode":"8730",
    "sg:province":"St. Gallen",
    "wof:name":"Bruno Sacchi Massagen",
    "wof:placetype":"venue"
},
  "geometry": {"coordinates":[8.9776315689,47.2271575928],"type":"Point"}
}