{
  "type": "Feature",
  "properties": {
    "iso:country":"CH",
    "sg:address":"Bahnhofplatz 9",
    "sg:city":"Z\u00fcrich",
    "sg:orig_category":"Detailhandel mit Bekleidung Detailhandel mit Schuhen",
    "sg:phone":"+41 12103840",
    "sg:postcode":"8001",
    "sg:province":"Z\u00fcrich",
    "wof:name":"Soho Ag Store",
    "wof:placetype":"venue"
},
  "geometry": {"coordinates":[8.538987,47.377117],"type":"Point"}
}