{
  "type": "Feature",
  "properties": {
    "iso:country":"CH",
    "sg:address":"Rue Du Vieux-moulin 9",
    "sg:city":"Bassecourt",
    "sg:classifiers":[
        {
            "category":"Insurance",
            "subcategory":"Insurance Agent",
            "type":"Services"
        }
    ],
    "sg:phone":"+41 32 426 65 85",
    "sg:postcode":"2854",
    "sg:province":"Jura",
    "sg:tags":[
        "versicherungsagenturen",
        "-broker"
    ],
    "wof:name":"Winterthur-assurances Agence",
    "wof:placetype":"venue"
},
  "geometry": {"coordinates":[7.2466340065,47.3382301331],"type":"Point"}
}