{
  "type": "Feature",
  "properties": {
    "iso:country":"CH",
    "sg:address":"Kanzlerstrasse 24",
    "sg:city":"Frauenfeld",
    "sg:orig_category":"Werbung",
    "sg:postcode":"8500",
    "sg:province":"Thurgau",
    "wof:name":"Hildebrand Dominique",
    "wof:placetype":"venue"
},
  "geometry": {"coordinates":[8.9106521606,47.5595626831],"type":"Point"}
}