{
  "type": "Feature",
  "properties": {
    "iso:country":"CH",
    "sg:address":"Bahnhofstrasse 9",
    "sg:city":"M\u00e4genwil",
    "sg:orig_category":"R\u00fcckgewinnung U Vorbereitung f\u00fcr die Wiederverwertung Recycling von nichtmetallischen Altmaterialien",
    "sg:postcode":"5506",
    "sg:province":"Aargau",
    "wof:name":"Biodrive Ag",
    "wof:placetype":"venue"
},
  "geometry": {"coordinates":[8.2344093323,47.4140548706],"type":"Point"}
}