{
  "type": "Feature",
  "properties": {
    "iso:country":"CH",
    "sg:address":"Wit\u00f6feli",
    "sg:city":"Sch\u00e4nis",
    "sg:orig_category":"Detailhandel mit Sportartikeln Fachdetailhandel in Verkaufsr\u00e4umen",
    "sg:phone":"+41 55 615 21 01",
    "sg:postcode":"8718",
    "sg:province":"St. Gallen",
    "wof:name":"Ajt Sport-shop",
    "wof:placetype":"venue"
},
  "geometry": {"coordinates":[9.0414199829,47.1530838013],"type":"Point"}
}