{
  "type": "Feature",
  "properties": {
    "addr:full":"Chemin De Trembley 15a Prangins Vaud 1197",
    "addr:housenumber":"15a",
    "addr:postcode":"1197",
    "addr:street":"Chemin De Trembley",
    "iso:country":"CH",
    "sg:address":"Chemin De Trembley 15a",
    "sg:city":"Prangins",
    "sg:orig_category":"Datenverarbeitungsdienste",
    "sg:phone":"+41 22 362 32 55",
    "sg:postcode":"1197",
    "sg:province":"Vaud",
    "wof:name":"Multi Media Consult \u00ac Assistance Services Sa",
    "wof:placetype":"venue"
},
  "geometry": {"coordinates":[6.246365,46.391247],"type":"Point"}
}