{
  "type": "Feature",
  "properties": {
    "iso:country":"CH",
    "sg:address":"Dammstrasse 27 8702 Zollikon. Postfach",
    "sg:city":"Zollikon",
    "sg:orig_category":"Fotografische Ateliers Fotografisches Gewerbe U fotografische Laboratorien",
    "sg:phone":"+41 13963696",
    "sg:postcode":"8702",
    "sg:province":"Z\u00fcrich",
    "wof:name":"Blum Duncan Fotograf Gmbh Mode, Portraitfotografie",
    "wof:placetype":"venue"
},
  "geometry": {"coordinates":[8.5682134628,47.343536377],"type":"Point"}
}