{
  "type": "Feature",
  "properties": {
    "addr:full":"Haus Sunshine Fiesch Valais 3984",
    "addr:postcode":"3984",
    "iso:country":"CH",
    "sg:address":"Haus Sunshine",
    "sg:city":"Fiesch",
    "sg:orig_category":"Reisen, Unterk\u00fcnfte",
    "sg:phone":"+41 27 971 34 48",
    "sg:postcode":"3984",
    "sg:province":"Valais",
    "wof:name":"Herzlich Willkommen Bei Familie Imhasly-f\u00fcrst",
    "wof:placetype":"venue"
},
  "geometry": {"coordinates":[8.135188,46.403774],"type":"Point"}
}