{
  "type": "Feature",
  "properties": {
    "iso:country":"CH",
    "sg:address":"Seehagweg 9",
    "sg:city":"Nunningen",
    "sg:classifiers":[
        {
            "category":"Arena",
            "subcategory":"Sports Club",
            "type":"Entertainment"
        }
    ],
    "sg:phone":"+41 61 791 14 11",
    "sg:postcode":"4208",
    "sg:province":"Solothurn",
    "sg:tags":[
        "karate",
        "judo",
        "sportvereine"
    ],
    "wof:name":"Judo Club Nunningen",
    "wof:placetype":"venue"
},
  "geometry": {"coordinates":[7.6148610115,47.3952903748],"type":"Point"}
}