{
  "type": "Feature",
  "properties": {
    "iso:country":"CH",
    "sg:address":"6936",
    "sg:city":"Cademario",
    "sg:orig_category":"Landesverteidigung, Sozialversicherung \u00d6ffentliche Verwaltung",
    "sg:phone":"+41 91 605 24 18",
    "sg:postcode":"6936",
    "sg:province":"Ticino",
    "wof:name":"Centro Di Protezione Civile Di Cademario",
    "wof:placetype":"venue"
},
  "geometry": {"coordinates":[8.892999649,46.0219917297],"type":"Point"}
}