{
  "type": "Feature",
  "properties": {
    "iso:country":"CH",
    "sg:address":"Hofacher",
    "sg:city":"Krattigen",
    "sg:orig_category":"Unclassifiable Establishments",
    "sg:phone":"+41 33 654 52 29",
    "sg:postcode":"3704",
    "sg:province":"Bern",
    "wof:name":"Rubin Ag",
    "wof:placetype":"venue"
},
  "geometry": {"coordinates":[7.7283949852,46.6615715027],"type":"Point"}
}