{
  "type": "Feature",
  "properties": {
    "iso:country":"CH",
    "sg:address":"In Der Luberzen 17",
    "sg:city":"Urdorf",
    "sg:orig_category":"Herstellung von Elektrizit\u00e4tsverteilungs U schalteinrichtungen",
    "sg:phone":"+41 17351050",
    "sg:postcode":"8902",
    "sg:province":"Z\u00fcrich",
    "wof:name":"Solutec Automation Ag",
    "wof:placetype":"venue"
},
  "geometry": {"coordinates":[8.4212150574,47.3936004639],"type":"Point"}
}