{
  "type": "Feature",
  "properties": {
    "iso:country":"CH",
    "sg:address":"Lyssachstrasse 7a",
    "sg:city":"Burgdorf",
    "sg:orig_category":"Pensionskassen",
    "sg:postcode":"3400",
    "sg:province":"Bern",
    "wof:name":"Kader-vorsorgestiftung Der Markwalder + Partner Ag",
    "wof:placetype":"venue"
},
  "geometry": {"coordinates":[7.6244158745,47.0583152771],"type":"Point"}
}