{
  "type": "Feature",
  "properties": {
    "iso:country":"CH",
    "sg:address":"Lindenhofstrasse 18",
    "sg:city":"Oftringen",
    "sg:orig_category":"Arztpraxen",
    "sg:phone":"+41 62 797 75 70",
    "sg:postcode":"4665",
    "sg:province":"Aargau",
    "wof:name":"Dr.med.urs Vogel Spezialarzt Fmh",
    "wof:placetype":"venue"
},
  "geometry": {"coordinates":[7.920212,47.31657],"type":"Point"}
}