{
  "type": "Feature",
  "properties": {
    "iso:country":"CH",
    "sg:address":"Froschaugasse 26",
    "sg:city":"Z\u00fcrich",
    "sg:classifiers":[
        {
            "category":"Restaurant",
            "type":"Food & Drink"
        }
    ],
    "sg:phone":"+41 12618832",
    "sg:postcode":"8001",
    "sg:province":"Z\u00fcrich",
    "wof:name":"Restaurant Iseb\u00e4hnli",
    "wof:placetype":"venue"
},
  "geometry": {"coordinates":[8.5448789597,47.3732261658],"type":"Point"}
}