{
  "type": "Feature",
  "properties": {
    "iso:country":"CH",
    "sg:address":"Utoquai 41",
    "sg:city":"Z\u00fcrich",
    "sg:orig_category":"Architektur U Ingenieurb\u00fcros Architekturb\u00fcros",
    "sg:phone":"+41 32 341 51 41",
    "sg:postcode":"8008",
    "sg:province":"Z\u00fcrich",
    "wof:name":"Leutenegger W. & Partner Ag, Architekten Fsai",
    "wof:placetype":"venue"
},
  "geometry": {"coordinates":[7.266964,47.152477],"type":"Point"}
}