{
  "type": "Feature",
  "properties": {
    "iso:country":"CH",
    "sg:address":"Lindenstrasse 33",
    "sg:city":"Z\u00fcrich",
    "sg:orig_category":"Interessenvertretungen",
    "sg:postcode":"8008",
    "sg:province":"Z\u00fcrich",
    "wof:name":"Muntwyler-stiftung Willi",
    "wof:placetype":"venue"
},
  "geometry": {"coordinates":[9.8386106491,46.497631073],"type":"Point"}
}