{
  "type": "Feature",
  "properties": {
    "iso:country":"CH",
    "sg:address":"Zypressenstrasse 59",
    "sg:city":"Z\u00fcrich",
    "sg:orig_category":"Fernmeldedienste",
    "sg:phone":"+41 12401102",
    "sg:postcode":"8004",
    "sg:province":"Z\u00fcrich",
    "wof:name":"Mrs Internet Service Gmbh",
    "wof:placetype":"venue"
},
  "geometry": {"coordinates":[8.5135326385,47.3780288696],"type":"Point"}
}