{
  "type": "Feature",
  "properties": {
    "iso:country":"CH",
    "sg:address":"Bleichenbergstrasse 53 4528 Zuchwil. Postfach",
    "sg:city":"Zuchwil",
    "sg:orig_category":"Handelsvermittlung U Grosshandel",
    "sg:phone":"+41 32 685 27 20",
    "sg:postcode":"4528",
    "sg:province":"Solothurn",
    "wof:name":"Bhg Birchi Handelsgesellschaft",
    "wof:placetype":"venue"
},
  "geometry": {"coordinates":[7.5539159775,47.1967048645],"type":"Point"}
}