{
  "type": "Feature",
  "properties": {
    "iso:country":"CH",
    "sg:address":"Tivoli Piazza",
    "sg:city":"Spreitenbach",
    "sg:classifiers":[
        {
            "category":"Banks & Credit Unions",
            "subcategory":"Bank",
            "type":"Services"
        }
    ],
    "sg:phone":"+41 4156715491",
    "sg:postcode":"8957",
    "sg:province":"Aargau",
    "wof:name":"Bank Langenthal",
    "wof:placetype":"venue"
},
  "geometry": {"coordinates":[8.365684,47.418045],"type":"Point"}
}