{
  "type": "Feature",
  "properties": {
    "iso:country":"CH",
    "sg:address":"Anciens-moulins Ch. Des 13 1009 Pully Case Postale 171",
    "sg:city":"Pully",
    "sg:orig_category":"Stukkateurgewerbe, Gipserei U Verputzerei",
    "sg:phone":"+41 21 721 20 00",
    "sg:postcode":"1009",
    "sg:province":"Vaud",
    "wof:name":"Gamboni P. Sa",
    "wof:placetype":"venue"
},
  "geometry": {"coordinates":[6.670320034,46.510219574],"type":"Point"}
}