{
  "type": "Feature",
  "properties": {
    "iso:country":"CH",
    "sg:address":"Le Marchat",
    "sg:city":"St-cierges",
    "sg:orig_category":"Grosshandel mit B\u00fcromaschinen Grosshandel mit Datenverarbeitungsger\u00e4ten",
    "sg:phone":"+41 21 991 30 01",
    "sg:postcode":"1064",
    "wof:name":"Bull (suisse) Sa Ordinateurs Prod.bureautiques",
    "wof:placetype":"venue"
},
  "geometry": {"coordinates":[6.7363848686,46.6893157959],"type":"Point"}
}