{
  "type": "Feature",
  "properties": {
    "iso:country":"CH",
    "sg:address":"H\u00f6henring 15 8052 Seebach. Postfach",
    "sg:city":"Seebach",
    "sg:orig_category":"Architektur U Ingenieurb\u00fcros",
    "sg:postcode":"8052",
    "sg:province":"Z\u00fcrich",
    "wof:name":"Road And Traffic Systems Consulting Gmbh Dienstleistungen Im Ber. Bauleitung, Ingenieurwesen Usw",
    "wof:placetype":"venue"
},
  "geometry": {"coordinates":[8.54024,47.422482],"type":"Point"}
}