{
  "type": "Feature",
  "properties": {
    "iso:country":"CH",
    "sg:address":"1772",
    "sg:city":"Ponthaux",
    "sg:orig_category":"Landwirtschaft, Jagd U damit verbundene Dienstleistungen",
    "sg:phone":"+41 26 475 16 67",
    "sg:postcode":"1772",
    "sg:province":"Fribourg",
    "wof:name":"Guido Niggeler Ferme",
    "wof:placetype":"venue"
},
  "geometry": {"coordinates":[7.0426950455,46.8169708252],"type":"Point"}
}