{
  "type": "Feature",
  "properties": {
    "iso:country":"CH",
    "sg:address":"Walderstrasse 17",
    "sg:city":"Hinwil",
    "sg:classifiers":[
        {
            "category":"Restaurant",
            "type":"Food & Drink"
        }
    ],
    "sg:phone":"+41 19373315",
    "sg:postcode":"8340",
    "sg:province":"Z\u00fcrich",
    "wof:name":"Restaurant R\u00f6ssli/la Domanda",
    "wof:placetype":"venue"
},
  "geometry": {"coordinates":[8.8450994492,47.3013763428],"type":"Point"}
}