{
  "type": "Feature",
  "properties": {
    "iso:country":"CH",
    "sg:address":"Burgstrasse 52",
    "sg:city":"Uster",
    "sg:orig_category":"Vereine Gesang",
    "sg:phone":"+41 19405785",
    "sg:postcode":"8610",
    "sg:province":"Z\u00fcrich",
    "wof:name":"Ten Sing Connection Uster",
    "wof:placetype":"venue"
},
  "geometry": {"coordinates":[8.7241716385,47.3417472839],"type":"Point"}
}