{
  "type": "Feature",
  "properties": {
    "iso:country":"CH",
    "sg:address":"Rue Du Chapelat 2",
    "sg:city":"Glovelier",
    "sg:orig_category":"Blanking, Punching, Stamping, Embossing And Drawing Dies, Progressive Dies",
    "sg:phone":"+41 32 426 54 78",
    "sg:postcode":"2855",
    "sg:province":"Jura",
    "wof:name":"Cregon-femco S.a.",
    "wof:placetype":"venue"
},
  "geometry": {"coordinates":[7.205899,47.337036],"type":"Point"}
}