{
  "type": "Feature",
  "properties": {
    "iso:country":"CH",
    "sg:address":"Baarerstrasse 23",
    "sg:city":"Zug",
    "sg:orig_category":"Sonstiges Versicherungsgewerbe",
    "sg:postcode":"6300",
    "sg:province":"Zug",
    "wof:name":"Nbo Di Paolella Francesco Intermediazione Di Prodotti Assicurativi",
    "wof:placetype":"venue"
},
  "geometry": {"coordinates":[9.1265001297,46.2303390503],"type":"Point"}
}