{
  "type": "Feature",
  "properties": {
    "iso:country":"CH",
    "sg:address":"Obereyfeldweg 29",
    "sg:city":"Ittigen",
    "sg:orig_category":"Maler U Glasergewerbe",
    "sg:phone":"+41 26 677 13 63",
    "sg:postcode":"3063",
    "sg:province":"Bern",
    "wof:name":"Ziggy Peinture, Gerber Christophe",
    "wof:placetype":"venue"
},
  "geometry": {"coordinates":[6.9800829887,46.8900337219],"type":"Point"}
}