{
  "type": "Feature",
  "properties": {
    "iso:country":"CH",
    "sg:address":"Oberdorfstrasse 60",
    "sg:city":"Horgen",
    "sg:orig_category":"Vereine Vogel-& Naturschutz",
    "sg:phone":"+41 17250340",
    "sg:postcode":"8810",
    "sg:province":"Z\u00fcrich",
    "wof:name":"Ornithol.verein Oberrieden",
    "wof:placetype":"venue"
},
  "geometry": {"coordinates":[8.5915317535,47.2577514648],"type":"Point"}
}