{
  "type": "Feature",
  "properties": {
    "iso:country":"CH",
    "sg:address":"Uertestrasse 4",
    "sg:city":"Stansstad",
    "sg:orig_category":"Erwachsenenbildung U Unterricht",
    "sg:phone":"+41 41 612 14 63",
    "sg:postcode":"6362",
    "sg:province":"Nidwalden",
    "wof:name":"Transrey Gmbh",
    "wof:placetype":"venue"
},
  "geometry": {"coordinates":[8.3400421143,46.9706382751],"type":"Point"}
}