{
  "type": "Feature",
  "properties": {
    "iso:country":"CH",
    "sg:address":"Ebnat 9400 Rorschach. Postfach",
    "sg:city":"Rorschach",
    "sg:orig_category":"Haltung von Rindern",
    "sg:postcode":"9400",
    "sg:province":"St. Gallen",
    "wof:name":"Braunviehzuchtgenossenschaft Rorschacherberg.",
    "wof:placetype":"venue"
},
  "geometry": {"coordinates":[9.4952001572,47.4779396057],"type":"Point"}
}