{
  "type": "Feature",
  "properties": {
    "iso:country":"CH",
    "sg:address":"Chalet Chesery 3780 Gruben B. Gstaad. Postfach",
    "sg:city":"Gstaad",
    "sg:orig_category":"Herstellung von Konstruktionsteilen, Fertigbauteilen U Ausbauelementen aus Holz",
    "sg:postcode":"3780",
    "sg:province":"Bern",
    "wof:name":"Woodtli Eric Kundenschreinerei",
    "wof:placetype":"venue"
},
  "geometry": {"coordinates":[8.8506937027,47.1919746399],"type":"Point"}
}