{
  "type": "Feature",
  "properties": {
    "addr:full":"Gartenweg 3 Sissach Basel-Landschaft 4450",
    "addr:housenumber":"3",
    "addr:postcode":"4450",
    "addr:street":"Gartenweg",
    "iso:country":"CH",
    "sg:address":"Gartenweg 3",
    "sg:city":"Sissach",
    "sg:orig_category":"Detailhandel mit Damenbekleidung",
    "sg:phone":"+41 61 971 28 88",
    "sg:postcode":"4450",
    "sg:province":"Basel-Landschaft",
    "wof:name":"Claire Cleis Second Hand-shop",
    "wof:placetype":"venue"
},
  "geometry": {"coordinates":[7.812799,47.463047],"type":"Point"}
}