{
  "type": "Feature",
  "properties": {
    "iso:country":"CH",
    "sg:address":"Route Du Village",
    "sg:city":"Juriens",
    "sg:orig_category":"Non-Classified Establishments",
    "sg:postcode":"1326",
    "sg:province":"Vaud",
    "wof:name":"Tsf Terroir Sans Frontieres S\u00e0rl",
    "wof:placetype":"venue"
},
  "geometry": {"coordinates":[6.4538021088,46.69090271],"type":"Point"}
}