{
  "type": "Feature",
  "properties": {
    "iso:country":"CH",
    "sg:address":"Via Delle Vigne 14 6500 Bellinzona. Postfach",
    "sg:city":"Bellinzona",
    "sg:orig_category":"Herstellung von Nahrungsmitteln undGetr\u00e4nken Herstellung von sonstigen Nahrungsmitteln",
    "sg:phone":"+41 79 207 12 20",
    "sg:postcode":"6500",
    "sg:province":"Ticino",
    "wof:name":"Nutrego Sa",
    "wof:placetype":"venue"
},
  "geometry": {"coordinates":[9.033870697,46.1921577454],"type":"Point"}
}