{
  "type": "Feature",
  "properties": {
    "iso:country":"CH",
    "sg:address":"Rorschacherstrasse 44 9450 L\u00fcchingen. Postfach",
    "sg:city":"L\u00fcchingen",
    "sg:orig_category":"Fahrschulen, Flugschulen",
    "sg:phone":"+41 71 755 35 75",
    "sg:postcode":"9450",
    "sg:province":"St. Gallen",
    "wof:name":"Albert Steiger Autofahrschule",
    "wof:placetype":"venue"
},
  "geometry": {"coordinates":[9.5476446152,47.3824005127],"type":"Point"}
}