{
  "type": "Feature",
  "properties": {
    "iso:country":"CH",
    "sg:address":"Hauptstrasse 35",
    "sg:city":"Guntershausen",
    "sg:orig_category":"Detailhandel mit Sportartikeln",
    "sg:phone":"+41 52 365 23 22",
    "sg:postcode":"8357",
    "sg:province":"Thurgau",
    "wof:name":"G. & M. Krasensky Ag Pegasus Reitsport",
    "wof:placetype":"venue"
},
  "geometry": {"coordinates":[8.9155197144,47.4758758545],"type":"Point"}
}