{
  "type": "Feature",
  "properties": {
    "iso:country":"CH",
    "sg:address":"Grand-places 14",
    "sg:city":"Fribourg",
    "sg:orig_category":"Handelsvermittlung U Grosshandel Softwareentwicklung U beratung",
    "sg:phone":"+41 26 492 01 29",
    "sg:postcode":"1700",
    "sg:province":"Fribourg",
    "wof:name":"Crab Engineering Gmbh",
    "wof:placetype":"venue"
},
  "geometry": {"coordinates":[7.153151989,46.8025512695],"type":"Point"}
}