{
  "type": "Feature",
  "properties": {
    "iso:country":"CH",
    "sg:address":"Gr\u00e4uschenweg 1",
    "sg:city":"Pieterlen",
    "sg:classifiers":[
        {
            "category":"Manufacturing",
            "subcategory":"Printing",
            "type":"Manufacturing & Wholesale Goods"
        }
    ],
    "sg:phone":"+41 32 377 12 28",
    "sg:postcode":"2542",
    "sg:province":"Bern",
    "sg:tags":[
        "house",
        "book"
    ],
    "wof:name":"Pieterlen Ag",
    "wof:placetype":"venue"
},
  "geometry": {"coordinates":[7.340474,47.170658],"type":"Point"}
}