{
  "type": "Feature",
  "properties": {
    "iso:country":"CH",
    "sg:address":"Chemin De La Rochette 15",
    "sg:city":"Gen\u00e8ve",
    "sg:orig_category":"Erbringung von sonstigen Dienstleistungen f\u00fcr Unterhaltung, Erholung U Freizeit Sonstige Hilfsdienst",
    "sg:phone":"+41 22 733 22 22",
    "sg:postcode":"1202",
    "sg:province":"Gen\u00e8ve",
    "wof:name":"Tomisawa Kazuma",
    "wof:placetype":"venue"
},
  "geometry": {"coordinates":[6.1335320473,46.2221641541],"type":"Point"}
}