{
  "type": "Feature",
  "properties": {
    "iso:country":"CH",
    "sg:address":"Fenalet",
    "sg:city":"Bex",
    "sg:orig_category":"Mechanik",
    "sg:postcode":"1880",
    "sg:province":"Vaud",
    "wof:name":"M\u00e9rat Marcel, Mechanische Werkst\u00e4tte",
    "wof:placetype":"venue"
},
  "geometry": {"coordinates":[7.3615231514,47.1427192688],"type":"Point"}
}