{
  "type": "Feature",
  "properties": {
    "iso:country":"CH",
    "sg:address":"Felmisallee 17",
    "sg:city":"Horw",
    "sg:orig_category":"Unclassifiable Establishments",
    "sg:postcode":"6048",
    "sg:province":"Luzern",
    "wof:name":"K-brain Gmbh",
    "wof:placetype":"venue"
},
  "geometry": {"coordinates":[8.3240804672,47.0226593018],"type":"Point"}
}