{
  "type": "Feature",
  "properties": {
    "iso:country":"CH",
    "sg:address":"Tiefenaustrasse 86b 3004 Bern. Postfach 5805",
    "sg:city":"Bern",
    "sg:orig_category":"Interessenvertretungen",
    "sg:phone":"+41 31 301 17 35",
    "sg:postcode":"3001",
    "sg:province":"Bern",
    "wof:name":"Club Amical De Berne (cab)",
    "wof:placetype":"venue"
},
  "geometry": {"coordinates":[7.4498281479,46.972984314],"type":"Point"}
}