{
  "type": "Feature",
  "properties": {
    "addr:full":"Museggstrasse 3 Luzern Luzern 6004",
    "addr:housenumber":"3",
    "addr:postcode":"6004",
    "addr:street":"Museggstrasse",
    "iso:country":"CH",
    "sg:address":"Museggstrasse 3",
    "sg:city":"Luzern",
    "sg:orig_category":"Arztpraxen",
    "sg:phone":"+41 41 410 46 56",
    "sg:postcode":"6004",
    "sg:province":"Luzern",
    "wof:name":"Dr.med.claus Wimpfheimer Spezialarzt Fmh",
    "wof:placetype":"venue"
},
  "geometry": {"coordinates":[8.310304,47.055683],"type":"Point"}
}