{
  "type": "Feature",
  "properties": {
    "iso:country":"CH",
    "sg:address":"Br\u00fcnneliweg 505 5724 D\u00fcrren\u00e4sch. Postfach",
    "sg:city":"D\u00fcrren\u00e4sch",
    "sg:orig_category":"Herstellung von sonstiger Bekleidung U Bekleidungszubeh\u00f6r",
    "sg:phone":"+41 62 777 16 11",
    "sg:postcode":"5724",
    "sg:province":"Aargau",
    "wof:name":"Kinder Onlineshop, Lindenmann S. Kinderartikel, Kinderkleider, Spielwaren; Verkauf",
    "wof:placetype":"venue"
},
  "geometry": {"coordinates":[8.1604890823,47.3245162964],"type":"Point"}
}