{
  "type": "Feature",
  "properties": {
    "iso:country":"CH",
    "sg:address":"Poststrasse 8",
    "sg:city":"Turgi",
    "sg:orig_category":"Rechtsberatung Wirtschaftspr\u00fcfung, Steuerberatung U Treuhand",
    "sg:phone":"+41 56 201 00 40",
    "sg:postcode":"5300",
    "sg:province":"Aargau",
    "wof:name":"Concepta Treuhand Siegrist Ag",
    "wof:placetype":"venue"
},
  "geometry": {"coordinates":[8.2531013489,47.4934082031],"type":"Point"}
}