{
  "type": "Feature",
  "properties": {
    "iso:country":"CH",
    "sg:address":"Murifeldweg 10",
    "sg:city":"Bern",
    "sg:orig_category":"Erbringung von Dienstleistungen f\u00fcr Unternehmen",
    "sg:phone":"+41 18502000",
    "sg:postcode":"3006",
    "sg:province":"Bern",
    "wof:name":"Expo Management Em Gmbh",
    "wof:placetype":"venue"
},
  "geometry": {"coordinates":[8.4971370697,47.4868202209],"type":"Point"}
}