{
  "type": "Feature",
  "properties": {
    "iso:country":"CH",
    "sg:address":"S\u00fcsswinkelgasse 16",
    "sg:city":"Chur",
    "sg:orig_category":"Technische B\u00fcros Hoch-& Tiefbau",
    "sg:phone":"+41 81 252 60 10",
    "sg:postcode":"7000",
    "sg:province":"Graubunden",
    "wof:name":"Paul Erhart Bautechnisches B\u00fcro",
    "wof:placetype":"venue"
},
  "geometry": {"coordinates":[9.5334682465,46.8486747742],"type":"Point"}
}