{
  "type": "Feature",
  "properties": {
    "iso:country":"CH",
    "sg:address":"Berninastrasse 53 8057 Z\u00fcrich. Postfach",
    "sg:city":"Z\u00fcrich",
    "sg:orig_category":"Verlagsgewerbe",
    "sg:phone":"+41 13196430",
    "sg:postcode":"8057",
    "sg:province":"Z\u00fcrich",
    "wof:name":"Meister Verlag Ag Gesellschaft",
    "wof:placetype":"venue"
},
  "geometry": {"coordinates":[8.5480651855,47.403137207],"type":"Point"}
}