{
  "type": "Feature",
  "properties": {
    "iso:country":"CH",
    "sg:address":"Ringstrasse 25",
    "sg:city":"Rotkreuz",
    "sg:classifiers":[
        {
            "category":"Professional",
            "subcategory":"Employment Agencies",
            "type":"Services"
        }
    ],
    "sg:postcode":"6343",
    "sg:province":"Zug",
    "sg:tags":[
        "personal",
        "u",
        "stellenvermittlung"
    ],
    "wof:name":"Sangu Gmbh",
    "wof:placetype":"venue"
},
  "geometry": {"coordinates":[8.4255561829,47.1338729858],"type":"Point"}
}