{
  "type": "Feature",
  "properties": {
    "iso:country":"CH",
    "sg:address":"Ebenaustrasse 10 6048 Horw. Postfach",
    "sg:city":"Horw",
    "sg:orig_category":"Detailhandel mit elektrischen Haushalts-,Radio U Fernsehger\u00e4ten sowie Musikinstrumenten Grosshandel ",
    "sg:phone":"+41 41 340 45 34",
    "sg:postcode":"6048",
    "sg:province":"Luzern",
    "wof:name":"Koller Multimedia Ag",
    "wof:placetype":"venue"
},
  "geometry": {"coordinates":[8.3079395294,47.0138587952],"type":"Point"}
}