{
  "type": "Feature",
  "properties": {
    "iso:country":"CH",
    "sg:address":"Sulzstrasse 21 9403 Goldach. Postfach",
    "sg:city":"Goldach",
    "sg:orig_category":"Detailhandel mit Waren verschiedener Art, Hauptrichtung Nahrungsmittel",
    "sg:phone":"+41 71 841 33 23",
    "sg:postcode":"9403",
    "sg:province":"St. Gallen",
    "wof:name":"Landwirtschaftliche Genossenschaft Goldach Und Umgebung (agra)",
    "wof:placetype":"venue"
},
  "geometry": {"coordinates":[9.469244957,47.473072052],"type":"Point"}
}