{
  "type": "Feature",
  "properties": {
    "iso:country":"CH",
    "sg:address":"Via Pocobelli 1",
    "sg:city":"Melide",
    "sg:orig_category":"Grosshandel mit Bekleidung Grosshandel mit sonstigen Gebrauchs U Verbrauchsg\u00fctern",
    "sg:phone":"+41 21 635 62 34",
    "sg:postcode":"6815",
    "sg:province":"Ticino",
    "wof:name":"Werner Baer Textile",
    "wof:placetype":"venue"
},
  "geometry": {"coordinates":[6.5741519928,46.5369186401],"type":"Point"}
}