{
  "type": "Feature",
  "properties": {
    "iso:country":"CH",
    "sg:address":"Schlierbacherstrasse 1 6233 B\u00fcron. Postfach 56",
    "sg:city":"B\u00fcron",
    "sg:orig_category":"Regionalbanken U Sparkassen",
    "sg:phone":"+41 41 933 22 33",
    "sg:postcode":"6233",
    "sg:province":"Luzern",
    "wof:name":"Triba Partner Bank, Niederlassung B\u00fcron",
    "wof:placetype":"venue"
},
  "geometry": {"coordinates":[8.0945959091,47.2140388489],"type":"Point"}
}