{
  "type": "Feature",
  "properties": {
    "iso:country":"CH",
    "sg:address":"Rive Rue De 48",
    "sg:city":"Nyon",
    "sg:orig_category":"Herstellung von Speiseeis U Sorbets",
    "sg:postcode":"1260",
    "sg:province":"Vaud",
    "wof:name":"Dieci-progel Delli Colli",
    "wof:placetype":"venue"
},
  "geometry": {"coordinates":[8.8286447525,47.2318496704],"type":"Point"}
}