{
  "type": "Feature",
  "properties": {
    "iso:country":"CH",
    "sg:address":"Im Schmiedenhof 10",
    "sg:city":"Basel",
    "sg:orig_category":"Detailhandel mit Ton U Bildtr\u00e4gern",
    "sg:phone":"+41 61 262 10 20",
    "sg:postcode":"4001",
    "sg:province":"Basel-Stadt",
    "wof:name":"Silver Disc Media J. & R. B\u00e4rtschi",
    "wof:placetype":"venue"
},
  "geometry": {"coordinates":[7.5877108574,47.5570487976],"type":"Point"}
}