{
  "type": "Feature",
  "properties": {
    "iso:country":"CH",
    "sg:address":"C.postale 234/rue Haute 21",
    "sg:city":"Colombier",
    "sg:classifiers":[
        {
            "category":"Banks & Credit Unions",
            "subcategory":"Bank",
            "type":"Services"
        }
    ],
    "sg:phone":"+41 24 433 11 19",
    "sg:postcode":"2013",
    "sg:province":"Neuch\u00e2tel",
    "wof:name":"Banque Raiffeisen De Donneloye-orzens",
    "wof:placetype":"venue"
},
  "geometry": {"coordinates":[6.71512,46.742889],"type":"Point"}
}