{
  "type": "Feature",
  "properties": {
    "iso:country":"CH",
    "sg:address":"Rue Michel-chauvet 8",
    "sg:city":"Gen\u00e8ve",
    "sg:orig_category":"Kosmetikinstitute",
    "sg:phone":"+41 22 346 22 55",
    "sg:postcode":"1208",
    "sg:province":"Gen\u00e8ve",
    "wof:name":"Anita J\u00e4ggi Coiffure Boutique",
    "wof:placetype":"venue"
},
  "geometry": {"coordinates":[6.1567940712,46.197971344],"type":"Point"}
}