{
  "type": "Feature",
  "properties": {
    "iso:country":"CH",
    "sg:address":"M\u00fchlenstrasse 70 8200 Schaffhausen. Postfach",
    "sg:city":"Schaffhausen",
    "sg:orig_category":"Grosshandel mit B\u00fcromaschinen Satzherstellung U Reproduktion",
    "sg:phone":"+41 12720276",
    "sg:postcode":"8201",
    "sg:province":"Schaffhausen",
    "wof:name":"Rohner Informatik Z\u00fcrich Ag",
    "wof:placetype":"venue"
},
  "geometry": {"coordinates":[8.6254701614,47.6930885315],"type":"Point"}
}