{
  "type": "Feature",
  "properties": {
    "iso:country":"CH",
    "sg:address":"Ringstrasse 11",
    "sg:city":"Kiesen",
    "sg:orig_category":"Arztpraxen",
    "sg:phone":"+41 31 781 28 28",
    "sg:postcode":"3629",
    "sg:province":"Bern",
    "wof:name":"Dr.med.markus D\u00fcrst Arzt F.allgemeine Medizin Fmh",
    "wof:placetype":"venue"
},
  "geometry": {"coordinates":[7.583581,46.81815],"type":"Point"}
}