{
  "type": "Feature",
  "properties": {
    "iso:country":"CH",
    "sg:address":"Wabernstrasse 34 3007 Bern. Postfach",
    "sg:city":"Bern",
    "sg:orig_category":"Pensionskassen",
    "sg:phone":"+41 31 371 44 16",
    "sg:postcode":"3005",
    "sg:province":"Bern",
    "wof:name":"Patronale F\u00fcrsorgestiftung Der Moser + Suter Ag Architekten Sia",
    "wof:placetype":"venue"
},
  "geometry": {"coordinates":[7.4374108315,46.9389266968],"type":"Point"}
}