{
  "type": "Feature",
  "properties": {
    "iso:country":"CH",
    "sg:address":"Industrie B\u00e4nnli 16",
    "sg:city":"Wolfwil",
    "sg:orig_category":"Zimmerei, Dachdeckerei, Bauspenglerei U Abdichtung",
    "sg:postcode":"4628",
    "sg:province":"Solothurn",
    "wof:name":"Kistler J., Wintergarten, Bedachungen",
    "wof:placetype":"venue"
},
  "geometry": {"coordinates":[8.8520088196,47.1920852661],"type":"Point"}
}