{
  "type": "Feature",
  "properties": {
    "iso:country":"CH",
    "sg:address":"Gibelinstrasse 27",
    "sg:city":"Solothurn",
    "sg:classifiers":[
        {
            "category":"Shopping",
            "subcategory":"Jewelry",
            "type":"Retail Goods"
        }
    ],
    "sg:phone":"+41 32 621 61 31",
    "sg:postcode":"4500",
    "sg:province":"Solothurn",
    "sg:tags":[
        "watch"
    ],
    "wof:name":"Roamer Watch & Co Ag",
    "wof:placetype":"venue"
},
  "geometry": {"coordinates":[7.5257339478,47.2082633972],"type":"Point"}
}