{
  "type": "Feature",
  "properties": {
    "iso:country":"CH",
    "sg:address":"Via Chiasso",
    "sg:city":"Biasca",
    "sg:orig_category":"Elektrizit\u00e4tsversorgung Wasserversorgung",
    "sg:phone":"+41 91 756 65 71",
    "sg:postcode":"6710",
    "sg:province":"Ticino",
    "wof:name":"Officine Idroelettriche Di Blenio Sa Centrale Olivone",
    "wof:placetype":"venue"
},
  "geometry": {"coordinates":[8.9766597748,46.3404998779],"type":"Point"}
}