{
  "type": "Feature",
  "properties": {
    "iso:country":"CH",
    "sg:address":"9107",
    "sg:city":"Urn\u00e4sch",
    "sg:classifiers":[
        {
            "category":"Education",
            "subcategory":"Vocational School",
            "type":"Public Place"
        }
    ],
    "sg:phone":"+41 52 741 18 95",
    "sg:postcode":"9107",
    "sg:province":"Appenzell Ausserrhoden",
    "sg:tags":[
        "koch-",
        "haushaltschulen"
    ],
    "wof:name":"Schulhaus Hopfegarten Haushaltungsschule",
    "wof:placetype":"venue"
},
  "geometry": {"coordinates":[8.8598861694,47.6590652466],"type":"Point"}
}