{
  "type": "Feature",
  "properties": {
    "iso:country":"CH",
    "sg:address":"Schilfweg 12",
    "sg:city":"Biel/bienne",
    "sg:orig_category":"Schiffs U Bootsbau",
    "sg:phone":"+41 32 322 15 82",
    "sg:postcode":"2503",
    "sg:province":"Bern",
    "wof:name":"Peter Winkelmann Bootswerft",
    "wof:placetype":"venue"
},
  "geometry": {"coordinates":[7.237593174,47.1307792664],"type":"Point"}
}