{
  "type": "Feature",
  "properties": {
    "iso:country":"CH",
    "sg:address":"Huebwis 2",
    "sg:city":"F\u00e4llanden",
    "sg:orig_category":"Non-Classified Establishments",
    "sg:postcode":"8117",
    "sg:province":"Z\u00fcrich",
    "wof:name":"Techcon Gmbh",
    "wof:placetype":"venue"
},
  "geometry": {"coordinates":[7.586233139,47.4913825989],"type":"Point"}
}