{
  "type": "Feature",
  "properties": {
    "iso:country":"CH",
    "sg:address":"Les Oies 137 D",
    "sg:city":"Nods",
    "sg:orig_category":"Sonstige mit Sport verbundene T\u00e4tigkeiten",
    "sg:postcode":"2518",
    "sg:province":"Bern",
    "wof:name":"Zucht Und Handelsstall M\u00fchlehof Ag",
    "wof:placetype":"venue"
},
  "geometry": {"coordinates":[9.0545148849,47.1724510193],"type":"Point"}
}