{
  "type": "Feature",
  "properties": {
    "iso:country":"CH",
    "sg:address":"Winterhaldenstrasse 9",
    "sg:city":"Heimberg",
    "sg:orig_category":"Herstellung von Metallerzeugnissen ohne Maschinenbau Herstellung von Pumpen U Kompressoren",
    "sg:phone":"+41 41 632 50 75",
    "sg:postcode":"3627",
    "sg:province":"Bern",
    "wof:name":"Mte Tsch\u00fcmperlin Marco Engineering Ag",
    "wof:placetype":"venue"
},
  "geometry": {"coordinates":[8.2757520676,46.9359817505],"type":"Point"}
}