{
  "type": "Feature",
  "properties": {
    "iso:country":"CH",
    "sg:address":"Hohlenstein",
    "sg:city":"Glarus",
    "sg:orig_category":"Detailhandel mit Sportartikeln Fachdetailhandel in Verkaufsr\u00e4umen",
    "sg:phone":"+41 91 832 12 11",
    "sg:postcode":"8750",
    "sg:province":"Glarus",
    "wof:name":"Alpi Sport Sa Boutique",
    "wof:placetype":"venue"
},
  "geometry": {"coordinates":[9.1906404495,46.4630584717],"type":"Point"}
}