{
  "type": "Feature",
  "properties": {
    "iso:country":"CH",
    "sg:address":"Buchelistrasse 22",
    "sg:city":"Rorschach",
    "sg:orig_category":"Vorschulen, Kinderg\u00e4rten",
    "sg:phone":"+41 71 855 32 78",
    "sg:postcode":"9400",
    "sg:province":"St. Gallen",
    "wof:name":"Kindergarten Bucheli I & Ii",
    "wof:placetype":"venue"
},
  "geometry": {"coordinates":[9.4995479584,47.4718666077],"type":"Point"}
}