{
  "type": "Feature",
  "properties": {
    "addr:full":"1971 Grimisuat Valais 1971",
    "addr:postcode":"1971;1971",
    "iso:country":"CH",
    "sg:address":"1971",
    "sg:city":"Grimisuat",
    "sg:orig_category":"Detailhandel mit Boden U Wandbel\u00e4gen ohne Teppiche Verlegen von Fussboden",
    "sg:phone":"+41 27 398 26 72",
    "sg:postcode":"1971",
    "sg:province":"Valais",
    "wof:name":"L\u00e9on M\u00e9trailler Rev\u00eatements De Sols",
    "wof:placetype":"venue"
},
  "geometry": {"coordinates":[7.37887,46.254509],"type":"Point"}
}