{
  "type": "Feature",
  "properties": {
    "addr:full":"Chemin Des Communaux 4 Commugny Vaud 1291",
    "addr:housenumber":"4",
    "addr:postcode":"1291",
    "addr:street":"Chemin Des Communaux",
    "iso:country":"CH",
    "sg:address":"Chemin Des Communaux 4",
    "sg:city":"Commugny",
    "sg:orig_category":"Datenverarbeitungsdienste Sonstige mit der Informatik verbundene T\u00e4tigkeiten",
    "sg:phone":"+41 21 626 27 37",
    "sg:postcode":"1291",
    "sg:province":"Vaud",
    "wof:name":"Cia Computers Informatique Assistance Sa",
    "wof:placetype":"venue"
},
  "geometry": {"coordinates":[6.60484,46.526375],"type":"Point"}
}