{
  "type": "Feature",
  "properties": {
    "iso:country":"CH",
    "sg:address":"Bernstrasse 311",
    "sg:city":"Heimberg",
    "sg:orig_category":"Zahnarztpraxen",
    "sg:phone":"+41 33 439 69 69",
    "sg:postcode":"3627",
    "sg:province":"Bern",
    "wof:name":"Dr.med.dent.peter J. Portmann Zahnarzt",
    "wof:placetype":"venue"
},
  "geometry": {"coordinates":[7.6059131622,46.7920570374],"type":"Point"}
}