{
  "type": "Feature",
  "properties": {
    "iso:country":"CH",
    "sg:address":"Avenue De Beaumont 28",
    "sg:city":"Lausanne",
    "sg:orig_category":"Kinderkrippen U horte",
    "sg:phone":"+41 91 923 30 94",
    "sg:postcode":"1012",
    "sg:province":"Vaud",
    "wof:name":"Centro Assistenza Bambini",
    "wof:placetype":"venue"
},
  "geometry": {"coordinates":[8.9550895691,46.0135993958],"type":"Point"}
}