{
  "type": "Feature",
  "properties": {
    "iso:country":"CH",
    "sg:address":"Kaltensteinstrasse 30",
    "sg:city":"Forch",
    "sg:orig_category":"Unclassifiable Establishments",
    "sg:postcode":"8127",
    "sg:province":"Z\u00fcrich",
    "wof:name":"Ltm Lilo Tscharner Management Gmbh",
    "wof:placetype":"venue"
},
  "geometry": {"coordinates":[8.6495304108,47.3251228333],"type":"Point"}
}