{
  "type": "Feature",
  "properties": {
    "iso:country":"CH",
    "sg:address":"Rousseau Avenue J.-j.- 5",
    "sg:city":"Neuenburg",
    "sg:orig_category":"Forschung U Entwicklung im Bereich der Naturwissenschaften",
    "sg:phone":"+41 32 729 97 42",
    "sg:postcode":"2000",
    "sg:province":"Neuch\u00e2tel",
    "wof:name":"Ism Institut Pour La Recherche Socio-m\u00e9dicale Sa",
    "wof:placetype":"venue"
},
  "geometry": {"coordinates":[6.9331150055,46.9936141968],"type":"Point"}
}