{
  "type": "Feature",
  "properties": {
    "iso:country":"CH",
    "sg:address":"Hochwiesenstrasse 9",
    "sg:city":"Sirnach",
    "sg:orig_category":"Instandhaltung U Reparatur von Automobilen",
    "sg:phone":"+41 79 438 14 14",
    "sg:postcode":"8370",
    "sg:province":"Thurgau",
    "wof:name":"Brunschwiler Autohandels Ag",
    "wof:placetype":"venue"
},
  "geometry": {"coordinates":[8.9828052521,47.463432312],"type":"Point"}
}