{
  "type": "Feature",
  "properties": {
    "addr:full":"Avenue De Rochettaz 1 Pully Vaud 1009",
    "addr:housenumber":"1",
    "addr:postcode":"1009",
    "addr:street":"Avenue De Rochettaz",
    "iso:country":"CH",
    "sg:address":"Avenue De Rochettaz 1",
    "sg:city":"Pully",
    "sg:orig_category":"Architektur U Ingenieurb\u00fcros",
    "sg:phone":"+41 21 728 37 40",
    "sg:postcode":"1009",
    "sg:province":"Vaud",
    "wof:name":"Dts Dessin Technique Service, Favre C\u00e9dric",
    "wof:placetype":"venue"
},
  "geometry": {"coordinates":[6.664185,46.513142],"type":"Point"}
}