{
  "type": "Feature",
  "properties": {
    "iso:country":"CH",
    "sg:address":"G\u00e4rten 38 9496 Balzers. Postfach 133",
    "sg:city":"Balzers",
    "sg:orig_category":"G\u00fcterbef\u00f6rderung im Strassenverkehr",
    "sg:phone":"+41 79 697 28 34",
    "sg:postcode":"9496",
    "wof:name":"Franz Wille Autotransporte",
    "wof:placetype":"venue"
},
  "geometry": {"coordinates":[9.490486145,47.0626983643],"type":"Point"}
}