{
  "type": "Feature",
  "properties": {
    "iso:country":"CH",
    "sg:address":"Rue Du Pommier 12",
    "sg:city":"Neuch\u00e2tel",
    "sg:orig_category":"Sportvereine",
    "sg:postcode":"2000",
    "sg:province":"Neuch\u00e2tel",
    "wof:name":"Panathlon-club Neuch\u00e2tel",
    "wof:placetype":"venue"
},
  "geometry": {"coordinates":[6.9267101288,46.9912796021],"type":"Point"}
}