{
  "type": "Feature",
  "properties": {
    "iso:country":"CH",
    "sg:address":"Postplatz 230",
    "sg:city":"Jonen",
    "sg:orig_category":"Nationale Postdienste",
    "sg:phone":"+41 56 634 11 80",
    "sg:postcode":"8916",
    "sg:province":"Aargau",
    "wof:name":"Die Schweizerische Post",
    "wof:placetype":"venue"
},
  "geometry": {"coordinates":[8.3955526352,47.2963485718],"type":"Point"}
}