{
  "type": "Feature",
  "properties": {
    "iso:country":"CH",
    "sg:address":"Ifangstrasse 1a 8603 Schwerzenbach. Postfach",
    "sg:city":"Schwerzenbach",
    "sg:orig_category":"Handel mit Automobilen",
    "sg:phone":"+41 18262225",
    "sg:postcode":"8603",
    "sg:province":"Z\u00fcrich",
    "wof:name":"Akar Autohandel Occasionsautos; Im,-export, An Und Verkauf, Transport",
    "wof:placetype":"venue"
},
  "geometry": {"coordinates":[8.661488533,47.3838577271],"type":"Point"}
}