{
  "type": "Feature",
  "properties": {
    "iso:country":"CH",
    "sg:address":"Via Campagna 2a",
    "sg:city":"Bioggio",
    "sg:orig_category":"Herstellung von Duft U K\u00f6rperpflegemitteln Parf\u00fcmerien U sonstiger Detailhandel mit kosmetischen Art",
    "sg:phone":"+41 81 861 81 20",
    "sg:postcode":"6934",
    "sg:province":"Ticino",
    "wof:name":"Free-shop Fadrina",
    "wof:placetype":"venue"
},
  "geometry": {"coordinates":[10.3613004684,46.9444885254],"type":"Point"}
}