{
  "type": "Feature",
  "properties": {
    "iso:country":"CH",
    "sg:address":"Limmatquai 4 8001 Z\u00fcrich. Postfach",
    "sg:city":"Z\u00fcrich",
    "sg:orig_category":"Aktivit\u00e4t der Bankinstitute",
    "sg:phone":"+41 12679300",
    "sg:postcode":"8024",
    "sg:province":"Z\u00fcrich",
    "wof:name":"Bnp Paribas Private Bank (switzerland) Sa",
    "wof:placetype":"venue"
},
  "geometry": {"coordinates":[8.544896,47.367989],"type":"Point"}
}