{
  "type": "Feature",
  "properties": {
    "addr:full":"Aeussere Baselstrasse 255 Riehen Basel-Stadt 4125",
    "addr:housenumber":"255",
    "addr:postcode":"4125",
    "addr:street":"Aeussere Baselstrasse",
    "iso:country":"CH",
    "sg:address":"Aeussere Baselstrasse 255",
    "sg:city":"Riehen",
    "sg:orig_category":"Detailhandel mit Antiquit\u00e4ten Detailhandel mit Antiquit\u00e4ten U Gebrauchtwaren in Verkaufsr\u00e4umen",
    "sg:phone":"+41 61 601 88 18",
    "sg:postcode":"4125",
    "sg:province":"Basel-Stadt",
    "wof:name":"Luchsinger Antiquit\u00e4ten",
    "wof:placetype":"venue"
},
  "geometry": {"coordinates":[7.63548,47.575977],"type":"Point"}
}