{
  "type": "Feature",
  "properties": {
    "iso:country":"CH",
    "sg:address":"Langfeldstrasse 52 8500 Frauenfeld. Postfach",
    "sg:city":"Frauenfeld",
    "sg:orig_category":"Pensionskassen",
    "sg:phone":"+41 62 869 40 80",
    "sg:postcode":"8500",
    "sg:province":"Thurgau",
    "wof:name":"Personalvorsorgestiftung Der Kempchen-weber Ag",
    "wof:placetype":"venue"
},
  "geometry": {"coordinates":[8.0951356888,47.5309906006],"type":"Point"}
}