{
  "type": "Feature",
  "properties": {
    "iso:country":"CH",
    "sg:address":"G\u00e4\u00e4limatt 37",
    "sg:city":"Rain",
    "sg:orig_category":"Wirtschaftspr\u00fcfung, Steuerberatung U Treuhand",
    "sg:phone":"+41 41 458 18 20",
    "sg:postcode":"6026",
    "sg:province":"Luzern",
    "wof:name":"Betag Revision",
    "wof:placetype":"venue"
},
  "geometry": {"coordinates":[8.2482481003,47.1256256104],"type":"Point"}
}