{
  "type": "Feature",
  "properties": {
    "iso:country":"CH",
    "sg:address":"Zwingerstrasse 25",
    "sg:city":"Basel",
    "sg:orig_category":"Instandhaltung U Reparatur von Automobilen",
    "sg:phone":"+41 61 363 97 00",
    "sg:postcode":"4053",
    "sg:province":"Basel-Stadt",
    "wof:name":"Auto B\u00fcrki Gmbh",
    "wof:placetype":"venue"
},
  "geometry": {"coordinates":[7.5934882164,47.5442314148],"type":"Point"}
}