{
  "type": "Feature",
  "properties": {
    "iso:country":"CH",
    "sg:address":"Dufourstrasse 16",
    "sg:city":"Biel/bienne",
    "sg:orig_category":"Reiseb\u00fcros",
    "sg:phone":"+41 31 311 25 21",
    "sg:postcode":"2502",
    "sg:province":"Bern",
    "wof:name":"Ferex Reisen Ag",
    "wof:placetype":"venue"
},
  "geometry": {"coordinates":[7.4458861351,46.9479026794],"type":"Point"}
}