{
  "type": "Feature",
  "properties": {
    "iso:country":"CH",
    "sg:address":"Bleichemattstrasse 11",
    "sg:city":"Aarau",
    "sg:orig_category":"Interessenvertretungen",
    "sg:postcode":"5000",
    "sg:province":"Aargau",
    "wof:name":"Stephania + Fritz Metzger-stiftung",
    "wof:placetype":"venue"
},
  "geometry": {"coordinates":[8.0534210205,47.3905448914],"type":"Point"}
}