{
  "type": "Feature",
  "properties": {
    "iso:country":"CH",
    "sg:address":"Hutznaustrasse 3",
    "sg:city":"Wohlenschwil",
    "sg:orig_category":"Unternehmensberatung",
    "sg:phone":"+41 56 491 00 05",
    "sg:postcode":"5512",
    "sg:province":"Aargau",
    "wof:name":"Urs Angliker Aim Enterprise Profiling",
    "wof:placetype":"venue"
},
  "geometry": {"coordinates":[8.2591047287,47.4213256836],"type":"Point"}
}