{
  "type": "Feature",
  "properties": {
    "iso:country":"CH",
    "sg:address":"Burggartenstrasse 1",
    "sg:city":"Bottmingen",
    "sg:orig_category":"Schwimmb\u00e4der",
    "sg:phone":"+41 61 421 61 06",
    "sg:postcode":"4103",
    "sg:province":"Basel-Landschaft",
    "wof:name":"Hallenbad",
    "wof:placetype":"venue"
},
  "geometry": {"coordinates":[7.5684847832,47.5237617493],"type":"Point"}
}