{
  "type": "Feature",
  "properties": {
    "iso:country":"CH",
    "sg:address":"Le Coll\u00e8ge",
    "sg:city":"Servion",
    "sg:orig_category":"Maurerarbeiten Sonstiger spezialisierter Hoch U Tiefbau",
    "sg:phone":"+41 27 481 83 93",
    "sg:postcode":"1077",
    "sg:province":"Vaud",
    "wof:name":"Clavien Eric",
    "wof:placetype":"venue"
},
  "geometry": {"coordinates":[7.5190191269,46.3156738281],"type":"Point"}
}