{
  "type": "Feature",
  "properties": {
    "iso:country":"CH",
    "sg:address":"Hard 6",
    "sg:city":"Holziken",
    "sg:orig_category":"Gem\u00fcsebau",
    "sg:phone":"+41 79 657 35 00",
    "sg:postcode":"5043",
    "sg:province":"Aargau",
    "wof:name":"Heinz Morgenthaler Gem\u00fcsebau",
    "wof:placetype":"venue"
},
  "geometry": {"coordinates":[8.0427846909,47.3191184998],"type":"Point"}
}