{
  "type": "Feature",
  "properties": {
    "iso:country":"CH",
    "sg:address":"Staffelstrasse 8/10 8045 Z\u00fcrich",
    "sg:city":"Zust",
    "sg:classifiers":[
        {
            "category":"Professional",
            "subcategory":"Employment Agencies",
            "type":"Services"
        }
    ],
    "sg:postcode":"45",
    "sg:tags":[
        "personal",
        "u",
        "stellenvermittlung"
    ],
    "wof:name":"Jeco, Jeanne Confalonieri, Personalberatung & Stellenvermittlung",
    "wof:placetype":"venue"
},
  "geometry": {"coordinates":[8.5118503571,47.3567810059],"type":"Point"}
}