{
  "type": "Feature",
  "properties": {
    "iso:country":"CH",
    "sg:address":"4497",
    "sg:city":"R\u00fcnenberg",
    "sg:orig_category":"Vereine Musik/Blasmusik",
    "sg:phone":"+41 62 299 23 44",
    "sg:postcode":"4497",
    "sg:province":"Basel-Landschaft",
    "wof:name":"Musikverein",
    "wof:placetype":"venue"
},
  "geometry": {"coordinates":[7.8959298134,47.3936080933],"type":"Point"}
}