{
  "type": "Feature",
  "properties": {
    "iso:country":"CH",
    "sg:address":"Soodstrasse 91",
    "sg:city":"Adliswil",
    "sg:orig_category":"Tankstellen",
    "sg:phone":"+41 17103211",
    "sg:postcode":"8134",
    "sg:province":"Z\u00fcrich",
    "wof:name":"Agip Tankstelle Sood",
    "wof:placetype":"venue"
},
  "geometry": {"coordinates":[8.5215797424,47.3206596375],"type":"Point"}
}