{
  "type": "Feature",
  "properties": {
    "iso:country":"CH",
    "sg:address":"Fronwagplatz 24",
    "sg:city":"Schaffhausen",
    "sg:orig_category":"Arztpraxen",
    "sg:phone":"+41 52 625 20 44",
    "sg:postcode":"8200",
    "sg:province":"Schaffhausen",
    "wof:name":"Dres Med. H.-p. & U. Sch\u00e4fer Spezial\u00e4rzte Fmh",
    "wof:placetype":"venue"
},
  "geometry": {"coordinates":[8.633672,47.697235],"type":"Point"}
}