{
  "type": "Feature",
  "properties": {
    "iso:country":"CH",
    "sg:address":"Unter Bendlehn 30 9042 Speicher. Postfach",
    "sg:city":"Luzern",
    "sg:orig_category":"Sonstige pers\u00f6nliche Dienstleistungen",
    "sg:postcode":"6003",
    "sg:province":"Luzern",
    "wof:name":"Gotzner Consulting Ag Erbringen Betriebswirtschaftlicher Dienstleistung, Beratung Usw",
    "wof:placetype":"venue"
},
  "geometry": {"coordinates":[9.4527816772,47.4072723389],"type":"Point"}
}