{
  "type": "Feature",
  "properties": {
    "iso:country":"CH",
    "sg:address":"Chemin Saint-hubert 5",
    "sg:city":"Sion",
    "sg:classifiers":[
        {
            "category":"Manufacturing",
            "subcategory":"Printing",
            "type":"Manufacturing & Wholesale Goods"
        }
    ],
    "sg:phone":"+41 27 322 23 70",
    "sg:postcode":"1950",
    "sg:province":"Valais",
    "sg:tags":[
        "house",
        "book"
    ],
    "wof:name":"Valprint Sa",
    "wof:placetype":"venue"
},
  "geometry": {"coordinates":[7.351201,46.224827],"type":"Point"}
}