{
  "type": "Feature",
  "properties": {
    "iso:country":"CH",
    "sg:address":"3825",
    "sg:city":"M\u00fcrren",
    "sg:classifiers":[
        {
            "category":"Travel",
            "subcategory":"Hotels & Motels",
            "type":"Entertainment"
        }
    ],
    "sg:phone":"+41 33 855 13 61",
    "sg:postcode":"3825",
    "sg:province":"Bern",
    "sg:tags":[
        "hotels",
        "mit",
        "restaurant"
    ],
    "wof:name":"Hotel Alpina",
    "wof:placetype":"venue"
},
  "geometry": {"coordinates":[7.8951401711,46.560218811],"type":"Point"}
}