{
  "type": "Feature",
  "properties": {
    "iso:country":"CH",
    "sg:address":"Kesswiler Str. 16",
    "sg:city":"Dozwil",
    "sg:classifiers":[
        {
            "category":"Banks & Credit Unions",
            "subcategory":"Bank",
            "type":"Services"
        }
    ],
    "sg:phone":"+41 62 295 05 06",
    "sg:postcode":"8580",
    "sg:province":"Thurgau",
    "wof:name":"Raiffeisenbank Dulliken-starrkirch",
    "wof:placetype":"venue"
},
  "geometry": {"coordinates":[7.944655,47.346287],"type":"Point"}
}