{
  "type": "Feature",
  "properties": {
    "iso:country":"CH",
    "sg:address":"Obere Haldenstrasse 9",
    "sg:city":"T\u00fcbach",
    "sg:orig_category":"Grosshandel mit Textilien Grosshandel mit sonstigen Konsumg\u00fctern",
    "sg:phone":"+41 71 841 17 11",
    "sg:postcode":"9327",
    "sg:province":"St. Gallen",
    "wof:name":"K\u00f6nig Ernest",
    "wof:placetype":"venue"
},
  "geometry": {"coordinates":[9.4482984543,47.4827957153],"type":"Point"}
}