{
  "type": "Feature",
  "properties": {
    "iso:country":"CH",
    "sg:address":"Midi Ruelle Du 19",
    "sg:city":"Sion",
    "sg:orig_category":"Detailhandel mit Fleisch U Fleischwaren",
    "sg:phone":"+41 79 278 00 36",
    "sg:postcode":"1950",
    "sg:province":"Valais",
    "wof:name":"Pannatier Michel",
    "wof:placetype":"venue"
},
  "geometry": {"coordinates":[7.3588571548,46.2280921936],"type":"Point"}
}