{
  "type": "Feature",
  "properties": {
    "iso:country":"CH",
    "sg:address":"Stansstaderstrasse 104",
    "sg:city":"Stans",
    "sg:orig_category":"Zeitungsverlag",
    "sg:postcode":"6370",
    "sg:province":"Nidwalden",
    "wof:name":"Yakari Ag",
    "wof:placetype":"venue"
},
  "geometry": {"coordinates":[8.3518152237,46.9697914124],"type":"Point"}
}