{
  "type": "Feature",
  "properties": {
    "iso:country":"CH",
    "sg:address":"Kirchrain 1",
    "sg:city":"Hochwald",
    "sg:orig_category":"Regelm\u00e4ssige Personenbef\u00f6rderung im Fernverkehr",
    "sg:phone":"+41 61 751 48 92",
    "sg:postcode":"4146",
    "sg:province":"Solothurn",
    "wof:name":"Heinz Wohlgemuth Postautokurse & Garage",
    "wof:placetype":"venue"
},
  "geometry": {"coordinates":[7.6430130005,47.4554901123],"type":"Point"}
}