{
  "type": "Feature",
  "properties": {
    "iso:country":"CH",
    "sg:address":"Rue Des Jordils 65",
    "sg:city":"Yverdon-les-bains",
    "sg:orig_category":"Grafikateliers, Design",
    "sg:phone":"+41 24 425 85 55",
    "sg:postcode":"1400",
    "sg:province":"Vaud",
    "wof:name":"Michel Dubey Peinture Publicitaire",
    "wof:placetype":"venue"
},
  "geometry": {"coordinates":[6.6372470856,46.7774429321],"type":"Point"}
}