{
  "type": "Feature",
  "properties": {
    "iso:country":"CH",
    "sg:address":"6600 Locarno. Postfach Caselle Postale 1628",
    "sg:city":"Locarno",
    "sg:orig_category":"Sportvereine Eissport Eishockey",
    "sg:postcode":"6600",
    "sg:province":"Ticino",
    "wof:name":"Royal Hockey-club Lausanne",
    "wof:placetype":"venue"
},
  "geometry": {"coordinates":[6.6876702309,46.559551239],"type":"Point"}
}