{
  "type": "Feature",
  "properties": {
    "iso:country":"CH",
    "sg:address":"Gerbergasse 5 8001 Z\u00fcrich. Postfach",
    "sg:city":"Z\u00fcrich",
    "sg:orig_category":"Interessenvertretungen",
    "sg:phone":"+41 12265111",
    "sg:postcode":"8000",
    "sg:province":"Z\u00fcrich",
    "wof:name":"Verband Schweizerischer Elektrizit\u00e4tsunternehmen (vse)",
    "wof:placetype":"venue"
},
  "geometry": {"coordinates":[8.5369825363,47.3749275208],"type":"Point"}
}