{
  "type": "Feature",
  "properties": {
    "iso:country":"CH",
    "sg:address":"Steinhaldenweg 30",
    "sg:city":"Romanshorn",
    "sg:orig_category":"Herstellung von sonstigen elektrischen Ausr\u00fcstungen",
    "sg:postcode":"8590",
    "sg:province":"Thurgau",
    "wof:name":"Ochalek Jacek Export-import",
    "wof:placetype":"venue"
},
  "geometry": {"coordinates":[8.4392089844,47.455078125],"type":"Point"}
}