{
  "type": "Feature",
  "properties": {
    "iso:country":"CH",
    "sg:address":"Z\u00fcrcherstrasse 373",
    "sg:city":"Frauenfeld",
    "sg:classifiers":[
        {
            "category":"Restaurant",
            "type":"Food & Drink"
        }
    ],
    "sg:phone":"+41 71 244 68 21",
    "sg:postcode":"8500",
    "sg:province":"Thurgau",
    "wof:name":"Restaurant Scheitlinsb\u00fcchel",
    "wof:placetype":"venue"
},
  "geometry": {"coordinates":[9.3957958221,47.4240684509],"type":"Point"}
}