{
  "type": "Feature",
  "properties": {
    "addr:full":"Sihlaustrasse 21 Adliswil Z\u00fcrich 8134",
    "addr:housenumber":"21",
    "addr:postcode":"8134",
    "addr:street":"Sihlaustrasse",
    "iso:country":"CH",
    "sg:address":"Sihlaustrasse 21",
    "sg:city":"Adliswil",
    "sg:orig_category":"Bau U Wohngenossenschaften",
    "sg:phone":"+41 17107619",
    "sg:postcode":"8134",
    "sg:province":"Z\u00fcrich",
    "wof:name":"Genossenschaft F\u00fcr Jugend- Wohnungen Des Bezirks Horgen",
    "wof:placetype":"venue"
},
  "geometry": {"coordinates":[8.525511,47.30286],"type":"Point"}
}