{
  "type": "Feature",
  "properties": {
    "iso:country":"CH",
    "sg:address":"Clous Chemin Du 13 1897 Bouveret. Postfach",
    "sg:city":"Bouveret",
    "sg:orig_category":"Unclassifiable Establishments",
    "sg:postcode":"1897",
    "sg:province":"Valais",
    "wof:name":"Cachat Gabriel Et Fils S\u00e0rl Jardins, Parcs Etc.; Cr\u00e9ation, Entretien",
    "wof:placetype":"venue"
},
  "geometry": {"coordinates":[6.8527832031,46.3853225708],"type":"Point"}
}