{
  "type": "Feature",
  "properties": {
    "iso:country":"CH",
    "sg:address":"Krieswinkelstrasse 12",
    "sg:city":"Salmsach",
    "sg:orig_category":"Softwareentwicklung U beratung",
    "sg:postcode":"8599",
    "sg:province":"Thurgau",
    "wof:name":"Vg Technologies S\u00e0rl",
    "wof:placetype":"venue"
},
  "geometry": {"coordinates":[6.8834300041,46.4704742432],"type":"Point"}
}