{
  "type": "Feature",
  "properties": {
    "addr:full":"Ifangstrasse 111 R\u00fcmlang Z\u00fcrich 8153",
    "addr:housenumber":"111",
    "addr:postcode":"8153",
    "addr:street":"Ifangstrasse;Zuerich",
    "iso:country":"CH",
    "sg:address":"Ifangstrasse 111",
    "sg:city":"R\u00fcmlang",
    "sg:classifiers":[
        {
            "category":"Utilities",
            "subcategory":"Telephone",
            "type":"Services"
        }
    ],
    "sg:phone":"+41 18188040",
    "sg:postcode":"8153",
    "sg:province":"Z\u00fcrich",
    "sg:tags":[
        "platform",
        "aerial"
    ],
    "wof:name":"Bronto Skylift Ag",
    "wof:placetype":"venue"
},
  "geometry": {"coordinates":[8.539151,47.445461],"type":"Point"}
}