{
  "type": "Feature",
  "properties": {
    "iso:country":"CH",
    "sg:address":"Baumackerstrasse 24 8050 Z\u00fcrich. Postfach 9189",
    "sg:city":"Z\u00fcrich",
    "sg:orig_category":"Grosshandel mit Obst U Gem\u00fcse Grosshandel mit sonstigen Nahrungsmitteln",
    "sg:phone":"+41 56 266 50 60",
    "sg:postcode":"8050",
    "sg:province":"Z\u00fcrich",
    "wof:name":"Varistor Ag Handelsgesellschaft",
    "wof:placetype":"venue"
},
  "geometry": {"coordinates":[8.3162708282,47.5282592773],"type":"Point"}
}