{
  "type": "Feature",
  "properties": {
    "iso:country":"CH",
    "sg:address":"Via Cantonale 19",
    "sg:city":"Lugano",
    "sg:orig_category":"Herstellung von sonstigen Maschinen f\u00fcr bestimmte Verwendung",
    "sg:postcode":"6900",
    "sg:province":"Ticino",
    "wof:name":"Kinasol, Jean-bernard Carrupt",
    "wof:placetype":"venue"
},
  "geometry": {"coordinates":[6.778386116,46.5396842957],"type":"Point"}
}