{
  "type": "Feature",
  "properties": {
    "iso:country":"CH",
    "sg:address":"Spannortweg 7",
    "sg:city":"Rothrist",
    "sg:orig_category":"Sportvereine Flug Aero-Club",
    "sg:phone":"+41 62 794 26 08",
    "sg:postcode":"4852",
    "sg:province":"Aargau",
    "wof:name":"Ae.c.s.modellfluggruppe Olten",
    "wof:placetype":"venue"
},
  "geometry": {"coordinates":[7.9070558548,47.3023338318],"type":"Point"}
}