{
  "type": "Feature",
  "properties": {
    "iso:country":"CH",
    "sg:address":"Rue Neuve 16",
    "sg:city":"Nyon",
    "sg:orig_category":"Detailhandel mit Schuhen Detailhandel mit Sportartikeln",
    "sg:phone":"+41 21 960 34 61",
    "sg:postcode":"1260",
    "sg:province":"Vaud",
    "wof:name":"Ochsner Schuhe & Sport Ag",
    "wof:placetype":"venue"
},
  "geometry": {"coordinates":[6.9295902252,46.3618087769],"type":"Point"}
}