{
  "type": "Feature",
  "properties": {
    "iso:country":"CH",
    "sg:address":"Breitfeldstrasse 12",
    "sg:city":"Siebnen",
    "sg:orig_category":"Architekturb\u00fcros",
    "sg:phone":"+41 55 440 18 92",
    "sg:postcode":"8854",
    "sg:province":"Schwyz",
    "wof:name":"Alfred Walter Architekturb\u00fcro",
    "wof:placetype":"venue"
},
  "geometry": {"coordinates":[8.903229,47.179482],"type":"Point"}
}