{
  "type": "Feature",
  "properties": {
    "iso:country":"CH",
    "sg:address":"Breitschachenstrasse 10",
    "sg:city":"Gaiserwald",
    "sg:orig_category":"Herstellung von Maschinen f\u00fcr das Papiergewerbe",
    "sg:postcode":"9030",
    "sg:province":"St. Gallen",
    "wof:name":"Feedex Ag",
    "wof:placetype":"venue"
},
  "geometry": {"coordinates":[9.349360466,47.4439315796],"type":"Point"}
}