{
  "type": "Feature",
  "properties": {
    "iso:country":"CH",
    "sg:address":"B\u00fcmplizstrasse 190",
    "sg:city":"Bern",
    "sg:orig_category":"Detailhandel mit Zeitungen U Zeitschriften Kioske",
    "sg:phone":"+41 31 992 32 97",
    "sg:postcode":"3018",
    "sg:province":"Bern",
    "wof:name":"Kiosk Bahnhof B\u00fcmpliz-s\u00fcd",
    "wof:placetype":"venue"
},
  "geometry": {"coordinates":[7.3954048157,46.9378013611],"type":"Point"}
}