{
  "type": "Feature",
  "properties": {
    "iso:country":"CH",
    "sg:address":"Krummackerweg 40",
    "sg:city":"Olten",
    "sg:orig_category":"Sonstige pers\u00f6nliche Dienstleistungen",
    "sg:phone":"+41 62 296 86 96",
    "sg:postcode":"4600",
    "sg:province":"Solothurn",
    "wof:name":"Creat'yves, Oesch Yves",
    "wof:placetype":"venue"
},
  "geometry": {"coordinates":[7.9127621651,47.3470344543],"type":"Point"}
}