{
  "type": "Feature",
  "properties": {
    "iso:country":"CH",
    "sg:address":"Farbgasse 3",
    "sg:city":"Langenthal",
    "sg:orig_category":"Detailhandel mit M\u00f6beln Detailhandel mit M\u00f6beln U Haushaltsgegenst\u00e4nden",
    "sg:phone":"+41 79 354 54 70",
    "sg:postcode":"4900",
    "sg:province":"Bern",
    "wof:name":"Christian Siegenthaler Wohnstudio",
    "wof:placetype":"venue"
},
  "geometry": {"coordinates":[7.7894191742,47.2117385864],"type":"Point"}
}