{
  "type": "Feature",
  "properties": {
    "iso:country":"CH",
    "sg:address":"Voa Principala 68",
    "sg:city":"Lenzerheide/lai",
    "sg:orig_category":"Non-Classified Establishments",
    "sg:postcode":"7078",
    "sg:province":"Graubunden",
    "wof:name":"Castello Immobilien-service, Vitali & Mosimann",
    "wof:placetype":"venue"
},
  "geometry": {"coordinates":[9.5574216843,46.7292137146],"type":"Point"}
}