{
  "type": "Feature",
  "properties": {
    "iso:country":"CH",
    "sg:address":"Schulstrasse 5",
    "sg:city":"Widnau",
    "sg:orig_category":"Mechanik",
    "sg:phone":"+41 71 722 68 49",
    "sg:postcode":"9443",
    "sg:province":"St. Gallen",
    "wof:name":"Rwt Welti",
    "wof:placetype":"venue"
},
  "geometry": {"coordinates":[9.6332578659,47.4119033813],"type":"Point"}
}