{
  "type": "Feature",
  "properties": {
    "iso:country":"CH",
    "sg:address":"F\u00e4rberstrasse 31 8032 Z\u00fcrich",
    "sg:city":"Zust",
    "sg:orig_category":"Werbung",
    "sg:postcode":"32",
    "wof:name":"Brandner Marcel",
    "wof:placetype":"venue"
},
  "geometry": {"coordinates":[8.9586639404,47.4630966187],"type":"Point"}
}