{
  "type": "Feature",
  "properties": {
    "iso:country":"CH",
    "sg:address":"Neugonzenbach",
    "sg:city":"L\u00fctisburg",
    "sg:orig_category":"Sonstige mit Sport verbundene T\u00e4tigkeiten",
    "sg:postcode":"9604",
    "sg:province":"St. Gallen",
    "wof:name":"Bischofberger Bruno",
    "wof:placetype":"venue"
},
  "geometry": {"coordinates":[9.0732297897,47.3924636841],"type":"Point"}
}