{
  "type": "Feature",
  "properties": {
    "iso:country":"CH",
    "sg:address":"Rue Du Quartier-neuf 10",
    "sg:city":"Gen\u00e8ve",
    "sg:orig_category":"Bauschreinerei Herstellung von M\u00f6beln verschiedener Art",
    "sg:phone":"+41 22 329 33 58",
    "sg:postcode":"1205",
    "sg:province":"Gen\u00e8ve",
    "wof:name":"Sergi A.",
    "wof:placetype":"venue"
},
  "geometry": {"coordinates":[6.128586,46.201756],"type":"Point"}
}