{
  "type": "Feature",
  "properties": {
    "addr:full":"Wildischachenstrasse Brugg Aargau 5200",
    "addr:postcode":"5200",
    "addr:street":"Wildischachenstrasse",
    "iso:country":"CH",
    "sg:address":"Wildischachenstrasse",
    "sg:city":"Brugg",
    "sg:classifiers":[
        {
            "category":"Manufacturing",
            "subcategory":"Tools & Machinery",
            "type":"Manufacturing & Wholesale Goods"
        }
    ],
    "sg:phone":"+41 32 931 74 65",
    "sg:postcode":"5200",
    "sg:province":"Aargau",
    "sg:tags":[
        "machine",
        "automation"
    ],
    "wof:name":"Brulhart Electro Technique Application",
    "wof:placetype":"venue"
},
  "geometry": {"coordinates":[6.744392,47.053047],"type":"Point"}
}