{
  "type": "Feature",
  "properties": {
    "iso:country":"CH",
    "sg:address":"Weissensteinstrasse 81",
    "sg:city":"Solothurn",
    "sg:orig_category":"Detailhandel mit Musikinstrumenten Detailhandel mit elektrischen Haushalts-,Radio U Fernsehger\u00e4ten s",
    "sg:phone":"+41 32 623 92 66",
    "sg:postcode":"4500",
    "sg:province":"Solothurn",
    "wof:name":"Pro Sound Beschallungstechnik",
    "wof:placetype":"venue"
},
  "geometry": {"coordinates":[7.5201048851,47.2150115967],"type":"Point"}
}