{
  "type": "Feature",
  "properties": {
    "iso:country":"CH",
    "sg:address":"8536",
    "sg:city":"H\u00fcttwilen",
    "sg:classifiers":[
        {
            "category":"Education",
            "subcategory":"Vocational School",
            "type":"Public Place"
        }
    ],
    "sg:postcode":"8536",
    "sg:province":"Thurgau",
    "sg:tags":[
        "koch-",
        "haushaltschulen"
    ],
    "wof:name":"Haushaltungsschule",
    "wof:placetype":"venue"
},
  "geometry": {"coordinates":[8.7957801819,47.5542411804],"type":"Point"}
}