{
  "type": "Feature",
  "properties": {
    "iso:country":"CH",
    "sg:address":"Z\u00fcrichstrasse 46 8840 Einsiedeln. Postfach 143",
    "sg:city":"Einsiedeln",
    "sg:orig_category":"Unclassifiable Establishments",
    "sg:phone":"+41 55 418 83 38",
    "sg:postcode":"8840",
    "sg:province":"Schwyz",
    "wof:name":"Wepa-consult Ag",
    "wof:placetype":"venue"
},
  "geometry": {"coordinates":[8.7448863983,47.1332817078],"type":"Point"}
}