{
  "type": "Feature",
  "properties": {
    "iso:country":"CH",
    "sg:address":"Im Schossacher 12",
    "sg:city":"D\u00fcbendorf",
    "sg:orig_category":"Gesundheitswesen",
    "sg:phone":"+41 56 442 22 22",
    "sg:postcode":"8600",
    "sg:province":"Z\u00fcrich",
    "wof:name":"Praxis Sanava Massagen",
    "wof:placetype":"venue"
},
  "geometry": {"coordinates":[8.2060308456,47.4791870117],"type":"Point"}
}