{
  "type": "Feature",
  "properties": {
    "iso:country":"CH",
    "sg:address":"Hauptstrasse 27 9477 Tr\u00fcbbach. Postfach",
    "sg:city":"Tr\u00fcbbach",
    "sg:orig_category":"Detailhandel mit Bekleidung",
    "sg:phone":"+41 81 783 12 38",
    "sg:postcode":"9477",
    "sg:province":"St. Gallen",
    "wof:name":"Kauf Otto Tr\u00fcbbach Ag",
    "wof:placetype":"venue"
},
  "geometry": {"coordinates":[9.48145,47.074047],"type":"Point"}
}