{
  "type": "Feature",
  "properties": {
    "iso:country":"CH",
    "sg:address":"Route Cantonale 26",
    "sg:city":"Vaulruz",
    "sg:orig_category":"Nationale Postdienste",
    "sg:phone":"+41 26 912 78 68",
    "sg:postcode":"1627",
    "sg:province":"Fribourg",
    "wof:name":"La Poste Suisse",
    "wof:placetype":"venue"
},
  "geometry": {"coordinates":[6.9905180931,46.6209640503],"type":"Point"}
}