{
  "type": "Feature",
  "properties": {
    "iso:country":"CH",
    "sg:address":"Poststrasse 10 4500 Solothurn. Postfach",
    "sg:city":"Solothurn",
    "sg:orig_category":"Sonstiges Versicherungsgewerbe",
    "sg:postcode":"4500",
    "sg:province":"Solothurn",
    "wof:name":"De Tadd\u00e9o, Jacques G Generalagentur Der Schweiz. Lebensversicherungs, Rentenanstalt",
    "wof:placetype":"venue"
},
  "geometry": {"coordinates":[7.5331082344,47.206653595],"type":"Point"}
}