{
  "type": "Feature",
  "properties": {
    "iso:country":"CH",
    "sg:address":"Schulackerstrasse 6",
    "sg:city":"M\u00fcnchenstein",
    "sg:orig_category":"Primarschulen",
    "sg:postcode":"4142",
    "sg:province":"Basel-Landschaft",
    "wof:name":"Primarschule Pavillon Loog",
    "wof:placetype":"venue"
},
  "geometry": {"coordinates":[7.6117148399,47.5193901062],"type":"Point"}
}