{
  "type": "Feature",
  "properties": {
    "iso:country":"CH",
    "sg:address":"Industriestrasse 31 6300 Zug. Postfach",
    "sg:city":"Zug",
    "sg:orig_category":"Grosshandel mit chemischen Erzeugnissen Herstellung von sonstigen chemischen Erzeugnissen",
    "sg:phone":"+41 17640554",
    "sg:postcode":"6300",
    "sg:province":"Zug",
    "wof:name":"Hydro-x Ag",
    "wof:placetype":"venue"
},
  "geometry": {"coordinates":[8.5194377899,47.1763191223],"type":"Point"}
}