{
  "type": "Feature",
  "properties": {
    "iso:country":"CH",
    "sg:address":"Route D'evian 28",
    "sg:city":"Aigle",
    "sg:orig_category":"Sportvereine",
    "sg:phone":"+41 24 466 44 14",
    "sg:postcode":"1860",
    "sg:province":"Vaud",
    "wof:name":"Panathlon-club Chablais",
    "wof:placetype":"venue"
},
  "geometry": {"coordinates":[6.9701099396,46.3175506592],"type":"Point"}
}