{
  "type": "Feature",
  "properties": {
    "iso:country":"CH",
    "sg:address":"Rundbuckstrasse 6 8212 Neuhausen. Postfach",
    "sg:city":"Neuhausen",
    "sg:orig_category":"Finanzierungsinstitutionen",
    "sg:postcode":"8212",
    "sg:province":"Schaffhausen",
    "wof:name":"Grauf Matthias Finanzberatung U. Gesch\u00e4ftsvermittlung",
    "wof:placetype":"venue"
},
  "geometry": {"coordinates":[8.6040248871,47.6752586365],"type":"Point"}
}