{
  "type": "Feature",
  "properties": {
    "iso:country":"CH",
    "sg:address":"Rufacherstrasse 13",
    "sg:city":"Basel",
    "sg:orig_category":"Betrieb von Taxis",
    "sg:phone":"+41 61 302 00 19",
    "sg:postcode":"4055",
    "sg:province":"Basel-Stadt",
    "wof:name":"Peter Haas Taxi",
    "wof:placetype":"venue"
},
  "geometry": {"coordinates":[7.572075,47.557873],"type":"Point"}
}