{
  "type": "Feature",
  "properties": {
    "iso:country":"CH",
    "sg:address":"Via Locarno",
    "sg:city":"Ascona",
    "sg:orig_category":"HOTELS: MIT RESTAURANT Kongress- and Tagungshotels mit Restaurant",
    "sg:phone":"+41 91 791 37 98",
    "sg:postcode":"6612",
    "sg:province":"Ticino",
    "wof:name":"Albergo Sasso Boretto",
    "wof:placetype":"venue"
},
  "geometry": {"coordinates":[8.7699813843,46.157283783],"type":"Point"}
}