{
  "type": "Feature",
  "properties": {
    "iso:country":"CH",
    "sg:address":"Centrale Rue 8",
    "sg:city":"Bex",
    "sg:orig_category":"Non-Classified Establishments",
    "sg:postcode":"1880",
    "sg:province":"Vaud",
    "wof:name":"H\u00f4tel De Ville, Rapha\u00ebl Cossetto",
    "wof:placetype":"venue"
},
  "geometry": {"coordinates":[7.0136580467,46.2512550354],"type":"Point"}
}