{
  "type": "Feature",
  "properties": {
    "addr:full":"Avenue J.-d.-maillard 1 Meyrin Gen\u00e8ve 1217",
    "addr:housenumber":"1",
    "addr:postcode":"1217",
    "addr:street":"Avenue J.-D.-Maillard",
    "iso:country":"CH",
    "sg:address":"Avenue J.-d.-maillard 1",
    "sg:city":"Meyrin",
    "sg:orig_category":"Arztpraxen",
    "sg:phone":"+41 22 782 35 48",
    "sg:postcode":"1217",
    "sg:province":"Gen\u00e8ve",
    "wof:name":"Dr M\u00e9d. Christiane Blanchard M\u00e9decin Sp\u00e9cialiste Fmh",
    "wof:placetype":"venue"
},
  "geometry": {"coordinates":[6.067613,46.229645],"type":"Point"}
}