{
  "type": "Feature",
  "properties": {
    "addr:full":"Neufeld Thun Bern 3604",
    "addr:postcode":"3604",
    "addr:street":"Neufeld;Bern",
    "iso:country":"CH",
    "sg:address":"Neufeld",
    "sg:city":"Thun",
    "sg:classifiers":[
        {
            "category":"Banks & Credit Unions",
            "subcategory":"Bank",
            "type":"Services"
        }
    ],
    "sg:phone":"+41 33369262",
    "sg:postcode":"3604",
    "sg:province":"Bern",
    "wof:name":"Berner Kantonalbank",
    "wof:placetype":"venue"
},
  "geometry": {"coordinates":[7.60849,46.740574],"type":"Point"}
}