{
  "type": "Feature",
  "properties": {
    "iso:country":"CH",
    "sg:address":"Bernstrasse 3",
    "sg:city":"M\u00fcnchenbuchsee",
    "sg:classifiers":[
        {
            "category":"Travel",
            "subcategory":"Hotels & Motels",
            "type":"Entertainment"
        }
    ],
    "sg:postcode":"3053",
    "sg:province":"Bern",
    "sg:tags":[
        "hotels",
        "mit",
        "restaurant"
    ],
    "wof:name":"B\u00e4rtsch-keller Eliane, Hotel Kreuz Hotel/restaurant",
    "wof:placetype":"venue"
},
  "geometry": {"coordinates":[9.4881038666,47.209602356],"type":"Point"}
}