{
  "type": "Feature",
  "properties": {
    "iso:country":"CH",
    "sg:address":"Bahnhofstrasse 18",
    "sg:city":"Uznach",
    "sg:orig_category":"Detailhandel mit Waren verschiedener Art, Hauptrichtung Nahrungsmittel",
    "sg:phone":"+41 55 280 30 75",
    "sg:postcode":"8730",
    "sg:province":"St. Gallen",
    "wof:name":"Coop Center",
    "wof:placetype":"venue"
},
  "geometry": {"coordinates":[8.9817066193,47.2253799438],"type":"Point"}
}