{
  "type": "Feature",
  "properties": {
    "iso:country":"CH",
    "sg:address":"Z\u00fcrcherstrasse 42 8852 Altendorf. Postfach 58",
    "sg:city":"Altendorf",
    "sg:orig_category":"Maschinen-Fabrikation",
    "sg:postcode":"8852",
    "sg:province":"Schwyz",
    "wof:name":"Mig Ag F\u00fcr Maschinenindustrie",
    "wof:placetype":"venue"
},
  "geometry": {"coordinates":[8.824669838,47.1929016113],"type":"Point"}
}