{
  "type": "Feature",
  "properties": {
    "iso:country":"CH",
    "sg:address":"Voa Principala",
    "sg:city":"Valbella",
    "sg:orig_category":"Detailhandel mit Sportartikeln Herstellung von Sportger\u00e4ten",
    "sg:phone":"+41 81 384 18 82",
    "sg:postcode":"7077",
    "sg:province":"Graubunden",
    "wof:name":"Blaesi Walter, Sport-shop, Inh. Schmid Ren\u00e9",
    "wof:placetype":"venue"
},
  "geometry": {"coordinates":[9.5559949875,46.7430152893],"type":"Point"}
}