{
  "type": "Feature",
  "properties": {
    "iso:country":"CH",
    "sg:address":"Dorfbachstrasse 12",
    "sg:city":"Richterswil",
    "sg:orig_category":"Grosshandel mit Getr\u00e4nken",
    "sg:phone":"+41 17844472",
    "sg:postcode":"8805",
    "sg:province":"Z\u00fcrich",
    "wof:name":"Silvestri Orazio",
    "wof:placetype":"venue"
},
  "geometry": {"coordinates":[8.7045240402,47.2071800232],"type":"Point"}
}