{
  "type": "Feature",
  "properties": {
    "iso:country":"CH",
    "sg:address":"Grabenstrasse 26 3132 Riggisberg. Postfach",
    "sg:city":"Riggisberg",
    "sg:orig_category":"Handel mit Automobilen",
    "sg:phone":"+41 31 302 02 06",
    "sg:postcode":"3132",
    "sg:province":"Bern",
    "wof:name":"Autohandel Rasa Paramalingam",
    "wof:placetype":"venue"
},
  "geometry": {"coordinates":[7.4880671501,46.8115348816],"type":"Point"}
}