{
  "type": "Feature",
  "properties": {
    "iso:country":"CH",
    "sg:address":"Gemeindekanzlei",
    "sg:city":"Guarda",
    "sg:orig_category":"Interessenvertretungen",
    "sg:postcode":"7545",
    "sg:province":"Graubunden",
    "wof:name":"Pro Harmonia Mundi",
    "wof:placetype":"venue"
},
  "geometry": {"coordinates":[8.8226995468,47.446521759],"type":"Point"}
}