{
  "type": "Feature",
  "properties": {
    "iso:country":"CH",
    "sg:address":"Rainackerweg 20",
    "sg:city":"W\u00fcrenlingen",
    "sg:orig_category":"Detektivb\u00fcros U \u00dcberwachung",
    "sg:phone":"+41 56 281 34 80",
    "sg:postcode":"5303",
    "sg:province":"Aargau",
    "wof:name":"Wettinger-wache",
    "wof:placetype":"venue"
},
  "geometry": {"coordinates":[8.2490825653,47.5278282166],"type":"Point"}
}