{
  "type": "Feature",
  "properties": {
    "iso:country":"CH",
    "sg:address":"Wallisellenstrasse 485",
    "sg:city":"Z\u00fcrich",
    "sg:orig_category":"Detailhandel mit Musikinstrumenten",
    "sg:phone":"+41 13221900",
    "sg:postcode":"8050",
    "sg:province":"Z\u00fcrich",
    "wof:name":"Gabriel Zanoletti Piano-music",
    "wof:placetype":"venue"
},
  "geometry": {"coordinates":[8.5698013306,47.4105606079],"type":"Point"}
}