{
  "type": "Feature",
  "properties": {
    "iso:country":"CH",
    "sg:address":"2027",
    "sg:city":"Fresens",
    "sg:orig_category":"Bauschreinerei Herstellung von Konstruktionsteilen, Fertigbauteilen U Ausbauelementen aus Holz",
    "sg:phone":"+41 32 835 28 28",
    "sg:postcode":"2027",
    "sg:province":"Neuch\u00e2tel",
    "wof:name":"Gaille Sa",
    "wof:placetype":"venue"
},
  "geometry": {"coordinates":[6.746535,46.888702],"type":"Point"}
}