{
  "type": "Feature",
  "properties": {
    "iso:country":"CH",
    "sg:address":"Altgasse 54",
    "sg:city":"Baar",
    "sg:orig_category":"Grosshandel mit sonstigen Gebrauchs U Verbrauchsg\u00fctern",
    "sg:postcode":"6340",
    "sg:province":"Zug",
    "wof:name":"L'audace Form Sa",
    "wof:placetype":"venue"
},
  "geometry": {"coordinates":[8.5155591965,47.1920852661],"type":"Point"}
}