{
  "type": "Feature",
  "properties": {
    "iso:country":"CH",
    "sg:address":"Spitalgasse 14",
    "sg:city":"Bern",
    "sg:orig_category":"Detailhandel mit Uhren U Schmuck Fachdetailhandel in Verkaufsr\u00e4umen",
    "sg:phone":"+41 31 311 23 67",
    "sg:postcode":"3011",
    "sg:province":"Bern",
    "wof:name":"Zigerli & Iff Ag",
    "wof:placetype":"venue"
},
  "geometry": {"coordinates":[7.4428610802,46.9482116699],"type":"Point"}
}