{
  "type": "Feature",
  "properties": {
    "iso:country":"CH",
    "sg:address":"Via Verbano 2",
    "sg:city":"Tenero",
    "sg:classifiers":[
        {
            "category":"Coffee & Tea",
            "type":"Food & Drink"
        }
    ],
    "sg:phone":"+41 91 735 60 11",
    "sg:postcode":"6598",
    "sg:province":"Ticino",
    "sg:tags":[
        "aquavit"
    ],
    "wof:name":"Matasci Fratelli Sa",
    "wof:placetype":"venue"
},
  "geometry": {"coordinates":[8.85024,46.177792],"type":"Point"}
}