{
  "type": "Feature",
  "properties": {
    "addr:full":"Obere D\u00fcrrm\u00fchlestrasse 20 Niederbipp Bern 4704",
    "addr:housenumber":"20",
    "addr:postcode":"4704",
    "addr:street":"Obere Duerrmuehlestrasse",
    "iso:country":"CH",
    "sg:address":"Obere D\u00fcrrm\u00fchlestrasse 20",
    "sg:city":"Niederbipp",
    "sg:orig_category":"Autospenglereien",
    "sg:phone":"+41 32 633 11 75",
    "sg:postcode":"4704",
    "sg:province":"Bern",
    "wof:name":"Hugo Bloch Carrosserie-reparaturen",
    "wof:placetype":"venue"
},
  "geometry": {"coordinates":[7.68884,47.270435],"type":"Point"}
}