{
  "type": "Feature",
  "properties": {
    "iso:country":"CH",
    "sg:address":"Via Al Parco 14",
    "sg:city":"Orselina",
    "sg:classifiers":[
        {
            "category":"Travel",
            "subcategory":"Hotels & Motels",
            "type":"Entertainment"
        }
    ],
    "sg:phone":"+41 91 743 66 81",
    "sg:postcode":"6644",
    "sg:province":"Ticino",
    "sg:tags":[
        "hotels",
        "mit",
        "restaurant"
    ],
    "wof:name":"Albergo Stella",
    "wof:placetype":"venue"
},
  "geometry": {"coordinates":[8.7985467911,46.1784820557],"type":"Point"}
}