{
  "type": "Feature",
  "properties": {
    "iso:country":"CH",
    "sg:address":"Oberegg 435 9220 Bischofszell. Postfach",
    "sg:city":"Bischofszell",
    "sg:orig_category":"Verwertung von Milch",
    "sg:postcode":"9220",
    "sg:province":"Thurgau",
    "wof:name":"K\u00e4serei Oberegg Eberle",
    "wof:placetype":"venue"
},
  "geometry": {"coordinates":[9.2408246994,47.4942245483],"type":"Point"}
}