{
  "type": "Feature",
  "properties": {
    "iso:country":"CH",
    "sg:address":"Bachstrasse 2",
    "sg:city":"Lenzburg",
    "sg:orig_category":"Zahnarztpraxen",
    "sg:phone":"+41 62 891 98 71",
    "sg:postcode":"5600",
    "sg:province":"Aargau",
    "wof:name":"Dr. Med. Dent. Konrad R\u00fceger Zahnarzt",
    "wof:placetype":"venue"
},
  "geometry": {"coordinates":[8.1763782501,47.3879089355],"type":"Point"}
}