{
  "type": "Feature",
  "properties": {
    "iso:country":"CH",
    "sg:address":"Herrengasse 7/9 6430 Schwyz. Postfach 558",
    "sg:city":"Schwyz",
    "sg:orig_category":"Kauf U Verkauf von Immobilien auf eigene Rechnung Vermittlung von Immobilien",
    "sg:phone":"+41 41 811 41 01",
    "sg:postcode":"6431",
    "sg:province":"Schwyz",
    "wof:name":"Svito Ag",
    "wof:placetype":"venue"
},
  "geometry": {"coordinates":[8.6525468826,47.0214691162],"type":"Point"}
}