{
  "type": "Feature",
  "properties": {
    "iso:country":"CH",
    "sg:address":"Rue Des Indiennes 13a",
    "sg:city":"Marin-epagnier",
    "sg:classifiers":[
        {
            "category":"Manufacturing",
            "subcategory":"Glass & Minerals",
            "type":"Manufacturing & Wholesale Goods"
        }
    ],
    "sg:phone":"+41 32 937 13 83",
    "sg:postcode":"2074",
    "sg:province":"Neuch\u00e2tel",
    "sg:tags":[
        "crystal",
        "watch",
        "clock"
    ],
    "wof:name":"Les Fils De John Perret S.a.",
    "wof:placetype":"venue"
},
  "geometry": {"coordinates":[6.727979,46.998226],"type":"Point"}
}