{
  "type": "Feature",
  "properties": {
    "iso:country":"CH",
    "sg:address":"Rue Reichlen 11 1700 Fribourg. Postfach",
    "sg:city":"Freiburg",
    "sg:orig_category":"Herstellung von Oberbekleidung",
    "sg:phone":"+41 26 493 31 71",
    "sg:postcode":"1700",
    "sg:province":"Fribourg",
    "wof:name":"Nouveaut\u00e9s Georges Sa",
    "wof:placetype":"venue"
},
  "geometry": {"coordinates":[7.1514940262,46.7981414795],"type":"Point"}
}