{
  "type": "Feature",
  "properties": {
    "iso:country":"CH",
    "sg:address":"Bahnhofstrasse",
    "sg:city":"N\u00e4fels",
    "sg:orig_category":"Wirtschaftspr\u00fcfung, Steuerberatung U Treuhand",
    "sg:postcode":"8752",
    "sg:province":"Glarus",
    "wof:name":"Rexinter Ag",
    "wof:placetype":"venue"
},
  "geometry": {"coordinates":[9.063583374,47.099319458],"type":"Point"}
}