{
  "type": "Feature",
  "properties": {
    "iso:country":"CH",
    "sg:address":"Via Beltramina 10a",
    "sg:city":"Lugano",
    "sg:orig_category":"Sonstiger spezialisierter Hoch U Tiefbau",
    "sg:phone":"+41 91 972 20 51",
    "sg:postcode":"6900",
    "sg:province":"Ticino",
    "wof:name":"Pedrosa Da Silva Joaquim",
    "wof:placetype":"venue"
},
  "geometry": {"coordinates":[8.9576120377,46.0170326233],"type":"Point"}
}