{
  "type": "Feature",
  "properties": {
    "addr:full":"Fabrikstrasse 17 8102 Oberengstringen. Postfach Oberengstringen Z\u00fcrich 8102",
    "addr:housenumber":"17",
    "addr:postcode":"8102;postfach;8102",
    "addr:street":"Fabrikstrasse",
    "iso:country":"CH",
    "sg:address":"Fabrikstrasse 17 8102 Oberengstringen. Postfach",
    "sg:city":"Oberengstringen",
    "sg:orig_category":"Allgemeiner Hoch U Tiefbau",
    "sg:phone":"+41 17501797",
    "sg:postcode":"8102",
    "sg:province":"Z\u00fcrich",
    "wof:name":"Brunschweiler Bauunternehmung Ag",
    "wof:placetype":"venue"
},
  "geometry": {"coordinates":[8.463047,47.406315],"type":"Point"}
}