{
  "type": "Feature",
  "properties": {
    "iso:country":"CH",
    "sg:address":"Aspweg 51",
    "sg:city":"Olten",
    "sg:orig_category":"Interessenvertretungen",
    "sg:phone":"+41 62 212 77 07",
    "sg:postcode":"4600",
    "sg:province":"Solothurn",
    "wof:name":"Stiftung Tierheim Olten",
    "wof:placetype":"venue"
},
  "geometry": {"coordinates":[7.8812060356,47.3379249573],"type":"Point"}
}