{
  "type": "Feature",
  "properties": {
    "iso:country":"CH",
    "sg:address":"Im Rossweidli 33",
    "sg:city":"Z\u00fcrich",
    "sg:orig_category":"Vorschulen, Kinderg\u00e4rten",
    "sg:postcode":"8045",
    "sg:province":"Z\u00fcrich",
    "wof:name":"St\u00e4dtischer Kindergarten",
    "wof:placetype":"venue"
},
  "geometry": {"coordinates":[8.5049209595,47.3584861755],"type":"Point"}
}