{
  "type": "Feature",
  "properties": {
    "iso:country":"CH",
    "sg:address":"Poststrasse 3 6340 Baar. Postfach 440",
    "sg:city":"Baar",
    "sg:orig_category":"Handelsvermittlung U Grosshandel Sonstiger Grosshandel",
    "sg:phone":"+41 41 760 22 60",
    "sg:postcode":"6341",
    "sg:province":"Zug",
    "wof:name":"Red Bull Ag",
    "wof:placetype":"venue"
},
  "geometry": {"coordinates":[8.5237722397,47.1946487427],"type":"Point"}
}