{
  "type": "Feature",
  "properties": {
    "iso:country":"CH",
    "sg:address":"Schabeggweg 1 9620 Lichtensteig. Postfach 35",
    "sg:city":"Lichtensteig",
    "sg:classifiers":[
        {
            "category":"Restaurant",
            "type":"Food & Drink"
        }
    ],
    "sg:phone":"+41 71 988 16 41",
    "sg:postcode":"9620",
    "sg:province":"St. Gallen",
    "wof:name":"Restaurant Traube",
    "wof:placetype":"venue"
},
  "geometry": {"coordinates":[9.0882406235,47.3236274719],"type":"Point"}
}