{
  "type": "Feature",
  "properties": {
    "iso:country":"CH",
    "sg:address":"Kriessernstrasse 26",
    "sg:city":"Montlingen",
    "sg:orig_category":"Betrieb U technische Hilfsdienste des Kultur U Unterhaltungswesens Sonstige Kultur U Unterhaltungsei",
    "sg:phone":"+41 71 761 09 09",
    "sg:postcode":"9462",
    "sg:province":"St. Gallen",
    "wof:name":"Msg Kartbahn Ag",
    "wof:placetype":"venue"
},
  "geometry": {"coordinates":[9.590993,47.34943],"type":"Point"}
}