{
  "type": "Feature",
  "properties": {
    "iso:country":"CH",
    "sg:address":"Rue De La Monnaie 1-3",
    "sg:city":"Gen\u00e8ve",
    "sg:orig_category":"Detailhandel mit Bekleidung",
    "sg:phone":"+41 22 310 26 87",
    "sg:postcode":"1204",
    "sg:province":"Gen\u00e8ve",
    "wof:name":"Jacquet G., Chemisier, Herth Jean-philippe Successeur",
    "wof:placetype":"venue"
},
  "geometry": {"coordinates":[6.143505,46.204327],"type":"Point"}
}