{
  "type": "Feature",
  "properties": {
    "iso:country":"CH",
    "sg:address":"Route De Jussy 89",
    "sg:city":"Th\u00f4nex",
    "sg:orig_category":"Sanit\u00e4r U Heizungsinstallation",
    "sg:phone":"+41 22 301 61 10",
    "sg:postcode":"1226",
    "sg:province":"Gen\u00e8ve",
    "wof:name":"Eric Bruttin Chauffage & Entretien",
    "wof:placetype":"venue"
},
  "geometry": {"coordinates":[6.2155160904,46.20079422],"type":"Point"}
}