{
  "type": "Feature",
  "properties": {
    "iso:country":"CH",
    "sg:address":"3534",
    "sg:city":"Signau",
    "sg:orig_category":"Erschliessung von Grundst\u00fccken",
    "sg:phone":"+41 61 601 29 92",
    "sg:postcode":"3534",
    "sg:province":"Bern",
    "wof:name":"Baugenossenschaft Sunnig Heim",
    "wof:placetype":"venue"
},
  "geometry": {"coordinates":[7.6400489807,47.5690040588],"type":"Point"}
}