{
  "type": "Feature",
  "properties": {
    "iso:country":"CH",
    "sg:address":"T\u00f6sstalstrasse 101",
    "sg:city":"Hittnau",
    "sg:classifiers":[
        {
            "category":"Restaurant",
            "type":"Food & Drink"
        }
    ],
    "sg:phone":"+41 19505353",
    "sg:postcode":"8335",
    "sg:province":"Z\u00fcrich",
    "wof:name":"Restaurant Freihof",
    "wof:placetype":"venue"
},
  "geometry": {"coordinates":[8.8391475677,47.3832130432],"type":"Point"}
}