{
  "type": "Feature",
  "properties": {
    "iso:country":"CH",
    "sg:address":"Cingria Rue 3 1205 Gen\u00e8ve. Postfach",
    "sg:city":"Gen\u00e8ve",
    "sg:orig_category":"Grosshandel mit Nahrungsmitteln, Getr\u00e4nken U Tabakwaren ohne ausgepr\u00e4gten Schwerpunkt",
    "sg:postcode":"1205",
    "sg:province":"Gen\u00e8ve",
    "wof:name":"Citron-vert, Fr\u00e9d\u00e9ric Marti",
    "wof:placetype":"venue"
},
  "geometry": {"coordinates":[6.1462321281,46.1936225891],"type":"Point"}
}