{
  "type": "Feature",
  "properties": {
    "iso:country":"CH",
    "sg:address":"Klosterberg 13 4051 Basel. Postfach",
    "sg:city":"Basel",
    "sg:orig_category":"Interessenvertretungen",
    "sg:phone":"+41 61 228 96 96",
    "sg:postcode":"4010",
    "sg:province":"Basel-Stadt",
    "wof:name":"Atlantis Fan Club",
    "wof:placetype":"venue"
},
  "geometry": {"coordinates":[7.5905508995,47.5519828796],"type":"Point"}
}