{
  "type": "Feature",
  "properties": {
    "iso:country":"CH",
    "sg:address":"Via Maistra",
    "sg:city":"Schlarigna",
    "sg:orig_category":"Detailhandel mit Fleisch U Fleischwaren",
    "sg:phone":"+41 21 635 23 56",
    "sg:postcode":"7505",
    "sg:province":"Graubunden",
    "wof:name":"Hursehit Kazimoglu Boucherie",
    "wof:placetype":"venue"
},
  "geometry": {"coordinates":[6.5808420181,46.5374832153],"type":"Point"}
}