{
  "type": "Feature",
  "properties": {
    "addr:full":"Rue Des Creux 1936 Verbier. Postfach Verbier Valais 1936",
    "addr:postcode":"1936 verbier. postfach;1936",
    "addr:street":"Rue Des Creux",
    "iso:country":"CH",
    "sg:address":"Rue Des Creux 1936 Verbier. Postfach",
    "sg:city":"Verbier",
    "sg:orig_category":"Architektur U Ingenieurb\u00fcros",
    "sg:postcode":"1936",
    "sg:province":"Valais",
    "wof:name":"Architecture Morard S. & Coupy P. Sa",
    "wof:placetype":"venue"
},
  "geometry": {"coordinates":[7.224667,46.103741],"type":"Point"}
}