{
  "type": "Feature",
  "properties": {
    "iso:country":"CH",
    "sg:address":"Furkastrasse 4",
    "sg:city":"Kriens",
    "sg:orig_category":"Maler U Glasergewerbe Malerei",
    "sg:phone":"+41 41 310 94 21",
    "sg:postcode":"6010",
    "sg:province":"Luzern",
    "wof:name":"Haas Albert, Malergesch\u00e4ft",
    "wof:placetype":"venue"
},
  "geometry": {"coordinates":[8.2904672623,47.0313682556],"type":"Point"}
}