{
  "type": "Feature",
  "properties": {
    "iso:country":"CH",
    "sg:address":"Baldismattweg 14",
    "sg:city":"Rombach",
    "sg:orig_category":"Vereine Harmonika and Akkordeon",
    "sg:phone":"+41 62 827 10 47",
    "sg:postcode":"5022",
    "sg:province":"Aargau",
    "wof:name":"Harmonika Club Buchs",
    "wof:placetype":"venue"
},
  "geometry": {"coordinates":[8.0534582138,47.4057235718],"type":"Point"}
}