{
  "type": "Feature",
  "properties": {
    "iso:country":"CH",
    "sg:address":"Segetzstrasse 15 4500 Solothurn. Postfach",
    "sg:city":"Solothurn",
    "sg:orig_category":"Pensionskassen",
    "sg:phone":"+41 32 625 65 20",
    "sg:postcode":"4500",
    "sg:province":"Solothurn",
    "wof:name":"Personalvorsorgestiftung Der Glutz Ag",
    "wof:placetype":"venue"
},
  "geometry": {"coordinates":[7.5300188065,47.2074317932],"type":"Point"}
}