{
  "type": "Feature",
  "properties": {
    "iso:country":"CH",
    "sg:address":"Gersmattstrasse 8",
    "sg:city":"Sachseln",
    "sg:orig_category":"Selbst\u00e4ndige bildende K\u00fcnstler",
    "sg:phone":"+41 32 677 13 96",
    "sg:postcode":"6072",
    "sg:province":"Obwalden",
    "wof:name":"Hans Borer Bildhauer-atelier",
    "wof:placetype":"venue"
},
  "geometry": {"coordinates":[7.5248098373,47.1698112488],"type":"Point"}
}