{
  "type": "Feature",
  "properties": {
    "iso:country":"CH",
    "sg:address":"Hanflandstrasse 23",
    "sg:city":"D\u00fcrnten",
    "sg:orig_category":"Fahrschulen, Flugschulen",
    "sg:phone":"+41 55 284 17 17",
    "sg:postcode":"8635",
    "sg:province":"Z\u00fcrich",
    "wof:name":"Ernst & Doris Weder Autofahrschule",
    "wof:placetype":"venue"
},
  "geometry": {"coordinates":[8.9625606537,47.2460327148],"type":"Point"}
}