{
  "type": "Feature",
  "properties": {
    "iso:country":"CH",
    "sg:address":"Hauptstrasse 74",
    "sg:city":"Steinach",
    "sg:orig_category":"Zahntechnische Laboratorien",
    "sg:phone":"+41 71 911 33 63",
    "sg:postcode":"9323",
    "sg:province":"St. Gallen",
    "wof:name":"Guido Hug Zahntechnisches Labor",
    "wof:placetype":"venue"
},
  "geometry": {"coordinates":[9.0525770187,47.4609870911],"type":"Point"}
}