{
  "type": "Feature",
  "properties": {
    "iso:country":"CH",
    "sg:address":"Kasinostrasse 10 8030 Z\u00fcrich. Postfach",
    "sg:city":"Z\u00fcrich",
    "sg:orig_category":"Institutionen des Sozialwesens ohne Beherbergung",
    "sg:postcode":"8030",
    "wof:name":"Frieda Baumann-stiftung Der Neuapostolischen Kirche Schweiz",
    "wof:placetype":"venue"
},
  "geometry": {"coordinates":[8.5542993546,47.3688583374],"type":"Point"}
}