{
  "type": "Feature",
  "properties": {
    "iso:country":"CH",
    "sg:address":"Picardiestrasse 9",
    "sg:city":"Sch\u00f6ftland",
    "sg:orig_category":"Sportvereine Automobil",
    "sg:postcode":"5040",
    "sg:province":"Aargau",
    "wof:name":"Auto-moto-club Aare Aarau",
    "wof:placetype":"venue"
},
  "geometry": {"coordinates":[8.0456314087,47.3028755188],"type":"Point"}
}