{
  "type": "Feature",
  "properties": {
    "iso:country":"CH",
    "sg:address":"Rue De Lo\u00e8che 6",
    "sg:city":"Sion",
    "sg:orig_category":"Sonstiger Detailhandel mit Metallwaren, Anstrichmitteln, Glaswaren, Bau U Heimwerkerbedarf",
    "sg:phone":"+41 27 322 29 83",
    "sg:postcode":"1950",
    "sg:province":"Valais",
    "wof:name":"Jallut Sa Peintures & Vernis",
    "wof:placetype":"venue"
},
  "geometry": {"coordinates":[7.3608970642,46.2362785339],"type":"Point"}
}