{
  "type": "Feature",
  "properties": {
    "iso:country":"CH",
    "sg:address":"Badweg 4",
    "sg:city":"Sch\u00f6ftland",
    "sg:orig_category":"Grosshandel mit Holz U Bauelementen aus Holz S\u00e4ge, Hobel U Holzimpr\u00e4gnierwerke",
    "sg:phone":"+41 62 721 40 55",
    "sg:postcode":"5040",
    "sg:province":"Aargau",
    "wof:name":"Fl\u00fcckiger Holz Ag",
    "wof:placetype":"venue"
},
  "geometry": {"coordinates":[8.0474052429,47.3008499146],"type":"Point"}
}