{
  "type": "Feature",
  "properties": {
    "iso:country":"CH",
    "sg:address":"Furlenstrasse 3",
    "sg:city":"Lausen",
    "sg:orig_category":"Innenausbau Zimmerei, Ingenieurholzbau",
    "sg:phone":"+41 61 921 15 90",
    "sg:postcode":"4415",
    "sg:province":"Basel-Landschaft",
    "wof:name":"Andreas Reist Treppenbau & Zimmerei",
    "wof:placetype":"venue"
},
  "geometry": {"coordinates":[7.7602210045,47.4705238342],"type":"Point"}
}