{
  "type": "Feature",
  "properties": {
    "iso:country":"CH",
    "sg:address":"Hauptstrasse 77",
    "sg:city":"Galmiz",
    "sg:orig_category":"RESTAURANTS: TEA-ROOMS",
    "sg:postcode":"3285",
    "sg:province":"Fribourg",
    "wof:name":"Restaurant Zum Kreuz Stadelmann-duss Margrith",
    "wof:placetype":"venue"
},
  "geometry": {"coordinates":[7.9565200806,47.0838012695],"type":"Point"}
}