{
  "type": "Feature",
  "properties": {
    "iso:country":"CH",
    "sg:address":"Burgerstrasse 33 3600 Thun. Postfach 1074",
    "sg:city":"Thun",
    "sg:orig_category":"Vermittlung von Immobilien Verwaltung von Immobilien",
    "sg:phone":"+41 33 222 88 78",
    "sg:postcode":"3601",
    "sg:province":"Bern",
    "wof:name":"Detra Treuhand, Trachsel",
    "wof:placetype":"venue"
},
  "geometry": {"coordinates":[7.6133418083,46.7463607788],"type":"Point"}
}