{
  "type": "Feature",
  "properties": {
    "iso:country":"CH",
    "sg:address":"Chemin Des Vignettes 38 1008 Jouxtens-m\u00e9zery. Postfach",
    "sg:city":"Cery",
    "sg:orig_category":"Sonstiges Versicherungsgewerbe",
    "sg:postcode":"1008",
    "sg:province":"Vaud",
    "wof:name":"Natewa S\u00e0rl Produits D'assurances Et Financiers; Repr\u00e9sentation Et Commerce",
    "wof:placetype":"venue"
},
  "geometry": {"coordinates":[6.5945868492,46.5447235107],"type":"Point"}
}