{
  "type": "Feature",
  "properties": {
    "iso:country":"CH",
    "sg:address":"Via L. Lavizzari 6",
    "sg:city":"Chiasso",
    "sg:orig_category":"Markt U Meinungsforschung",
    "sg:phone":"+41 32 857 18 88",
    "sg:postcode":"6830",
    "sg:province":"Ticino",
    "wof:name":"M.d.i. Diffusions, Mario D'incau",
    "wof:placetype":"venue"
},
  "geometry": {"coordinates":[6.8718662262,47.0459213257],"type":"Point"}
}