{
  "type": "Feature",
  "properties": {
    "iso:country":"CH",
    "sg:address":"Mitteldorf 1 9490 Vaduz. Postfach 126",
    "sg:city":"Vaduz",
    "sg:orig_category":"Unternehmensberatung",
    "sg:phone":"+423 237 75 50",
    "sg:postcode":"9490",
    "wof:name":"Cml Consulting & Management Company Ltd",
    "wof:placetype":"venue"
},
  "geometry": {"coordinates":[9.5221538544,47.1427230835],"type":"Point"}
}