{
  "type": "Feature",
  "properties": {
    "iso:country":"CH",
    "sg:address":"Etang De Besse",
    "sg:city":"Grimisuat",
    "sg:orig_category":"Architekturb\u00fcros",
    "sg:phone":"+41 27 398 19 04",
    "sg:postcode":"1971",
    "sg:province":"Valais",
    "wof:name":"Jean-paul Balet Bureau D'architecture",
    "wof:placetype":"venue"
},
  "geometry": {"coordinates":[7.386774,46.260719],"type":"Point"}
}