{
  "type": "Feature",
  "properties": {
    "iso:country":"CH",
    "sg:address":"3234",
    "sg:city":"Vinelz",
    "sg:orig_category":"Campingpl\u00e4tze",
    "sg:postcode":"3234",
    "sg:province":"Bern",
    "wof:name":"Cervino-heiniger Anita",
    "wof:placetype":"venue"
},
  "geometry": {"coordinates":[7.12116,47.032242],"type":"Point"}
}