{
  "type": "Feature",
  "properties": {
    "iso:country":"CH",
    "sg:address":"Pollini Via 11",
    "sg:city":"Mendrisio",
    "sg:orig_category":"Handel mit Automobilen",
    "sg:postcode":"6850",
    "sg:province":"Ticino",
    "wof:name":"Vogacar Sagl",
    "wof:placetype":"venue"
},
  "geometry": {"coordinates":[8.9809627533,45.8694114685],"type":"Point"}
}