{
  "type": "Feature",
  "properties": {
    "iso:country":"CH",
    "sg:address":"M\u00e4derstrasse 1",
    "sg:city":"Baden",
    "sg:orig_category":"Massagestudios",
    "sg:phone":"+41 56 210 08 26",
    "sg:postcode":"5400",
    "sg:province":"Aargau",
    "wof:name":"Naturplus Gmbh Medicinal Massage Therapies",
    "wof:placetype":"venue"
},
  "geometry": {"coordinates":[8.3040218353,47.4773521423],"type":"Point"}
}