{
  "type": "Feature",
  "properties": {
    "iso:country":"CH",
    "sg:address":"Wilerstrasse 1",
    "sg:city":"Bazenheid",
    "sg:orig_category":"Malerei",
    "sg:phone":"+41 71 931 11 62",
    "sg:postcode":"9602",
    "sg:province":"St. Gallen",
    "wof:name":"Emil G\u00e4mperle Malerwerkstatt",
    "wof:placetype":"venue"
},
  "geometry": {"coordinates":[9.0691375732,47.4113502502],"type":"Point"}
}