{
  "type": "Feature",
  "properties": {
    "iso:country":"CH",
    "sg:address":"Urlatsch",
    "sg:city":"Curaglia",
    "sg:orig_category":"Sportvereine Sch\u00fctzen",
    "sg:phone":"+41 81 947 43 45",
    "sg:postcode":"7184",
    "sg:province":"Graubunden",
    "wof:name":"Union De Tir Scopi Medel/lucmagn",
    "wof:placetype":"venue"
},
  "geometry": {"coordinates":[8.858288765,46.6727561951],"type":"Point"}
}