{
  "type": "Feature",
  "properties": {
    "iso:country":"CH",
    "sg:address":"Ladendorf",
    "sg:city":"Langendorf",
    "sg:orig_category":"Chemische Reinigung",
    "sg:phone":"+41 62 822 54 09",
    "sg:postcode":"4513",
    "sg:province":"Solothurn",
    "wof:name":"Francesco Brighina Reinigung",
    "wof:placetype":"venue"
},
  "geometry": {"coordinates":[8.071082,47.392399],"type":"Point"}
}