{
  "type": "Feature",
  "properties": {
    "iso:country":"CH",
    "sg:address":"6822",
    "sg:city":"Arogno",
    "sg:orig_category":"Herstellung von Elektrizit\u00e4tsverteilungs U schalteinrichtungen",
    "sg:phone":"+41 91 649 67 36",
    "sg:postcode":"6822",
    "sg:province":"Ticino",
    "wof:name":"Guidi Duilio Atelier De R\u00e9glages",
    "wof:placetype":"venue"
},
  "geometry": {"coordinates":[8.9867334366,45.958896637],"type":"Point"}
}