{
  "type": "Feature",
  "properties": {
    "iso:country":"CH",
    "sg:address":"Vordergasse 31",
    "sg:city":"Schaffhausen",
    "sg:orig_category":"Detailhandel mit Ton U Bildtr\u00e4gern Detailhandel mit elektrischen Haushalts-,Radio U Fernsehger\u00e4ten s",
    "sg:phone":"+41 61 487 66 66",
    "sg:postcode":"8200",
    "sg:province":"Schaffhausen",
    "wof:name":"City-disc Ag",
    "wof:placetype":"venue"
},
  "geometry": {"coordinates":[8.6368093491,47.6960220337],"type":"Point"}
}