{
  "type": "Feature",
  "properties": {
    "iso:country":"CH",
    "sg:address":"Obere Gasse 28.",
    "sg:city":"Chur",
    "sg:orig_category":"Detailhandel mit Textilien",
    "sg:postcode":"7000",
    "sg:province":"Graubunden",
    "wof:name":"Kleger-malojer Paulina.",
    "wof:placetype":"venue"
},
  "geometry": {"coordinates":[9.5308227539,46.8480377197],"type":"Point"}
}