{
  "type": "Feature",
  "properties": {
    "iso:country":"CH",
    "sg:address":"6932",
    "sg:city":"Breganzona",
    "sg:orig_category":"Konsulate",
    "sg:phone":"+41 91 967 42 35",
    "sg:postcode":"6932",
    "sg:province":"Ticino",
    "wof:name":"Consolato Gen.onorario Della Repubblica Delle Filippine",
    "wof:placetype":"venue"
},
  "geometry": {"coordinates":[8.9279298782,46.0091590881],"type":"Point"}
}