{
  "type": "Feature",
  "properties": {
    "iso:country":"CH",
    "sg:address":"Weiherwiesstrasse 3a",
    "sg:city":"Arnegg",
    "sg:orig_category":"Parkettleger",
    "sg:phone":"+41 71 385 53 35",
    "sg:postcode":"9212",
    "sg:province":"St. Gallen",
    "wof:name":"Paul Hagmann Parkettgesch\u00e4ft",
    "wof:placetype":"venue"
},
  "geometry": {"coordinates":[9.2577810287,47.4394454956],"type":"Point"}
}