{
  "type": "Feature",
  "properties": {
    "iso:country":"CH",
    "sg:address":"Avenue De La Gare",
    "sg:city":"Montana-vermala",
    "sg:orig_category":"Detailhandel mit Uhren U Schmuck Reparatur von Uhren U Schmuck",
    "sg:phone":"+41 32 913 21 61",
    "sg:postcode":"3962",
    "wof:name":"Daniel Richardet Horlogerie De L'abeille",
    "wof:placetype":"venue"
},
  "geometry": {"coordinates":[6.825193882,47.1010055542],"type":"Point"}
}