{
  "type": "Feature",
  "properties": {
    "iso:country":"CH",
    "sg:address":"Wilerstrasse 4",
    "sg:city":"Sirnach",
    "sg:orig_category":"Fachdetailhandel in Verkaufsr\u00e4umen",
    "sg:phone":"+41 71 960 06 86",
    "sg:postcode":"8370",
    "sg:province":"Thurgau",
    "wof:name":"Ambiance Blumenboutique Sabatino Sandra",
    "wof:placetype":"venue"
},
  "geometry": {"coordinates":[8.997879982,47.4619827271],"type":"Point"}
}