{
  "type": "Feature",
  "properties": {
    "iso:country":"CH",
    "sg:address":"Burgstrasse 36",
    "sg:city":"Uster",
    "sg:orig_category":"Fachdetailhandel in Verkaufsr\u00e4umen",
    "sg:postcode":"8610",
    "sg:province":"Z\u00fcrich",
    "wof:name":"I & J Sport Und Freizeit Molnar Uster",
    "wof:placetype":"venue"
},
  "geometry": {"coordinates":[8.7218837738,47.3423576355],"type":"Point"}
}