{
  "type": "Feature",
  "properties": {
    "iso:country":"CH",
    "sg:address":"Neubr\u00fcckstrasse 147-149",
    "sg:city":"Bern",
    "sg:orig_category":"Sportvereine Ballsport Fussball Damen",
    "sg:phone":"+41 31 301 30 41",
    "sg:postcode":"3012",
    "sg:province":"Bern",
    "wof:name":"Fc Bern Abt.damen",
    "wof:placetype":"venue"
},
  "geometry": {"coordinates":[7.4329972267,46.9609985352],"type":"Point"}
}