{
  "type": "Feature",
  "properties": {
    "iso:country":"CH",
    "sg:address":"Hauptstrasse 125",
    "sg:city":"M\u00f6hlin",
    "sg:orig_category":"Herstellung von Teppichen Verlegen von Fussboden",
    "sg:phone":"+41 61 851 11 92",
    "sg:postcode":"4313",
    "sg:province":"Aargau",
    "wof:name":"Derrer Ag",
    "wof:placetype":"venue"
},
  "geometry": {"coordinates":[7.8510842323,47.5542831421],"type":"Point"}
}