{
  "type": "Feature",
  "properties": {
    "iso:country":"CH",
    "sg:address":"Breitenwiesstr. 6",
    "sg:city":"Hinwil",
    "sg:classifiers":[
        {
            "category":"Utilities",
            "subcategory":"Telephone",
            "type":"Services"
        }
    ],
    "sg:phone":"+41 4119373303",
    "sg:postcode":"8340",
    "sg:province":"Z\u00fcrich",
    "sg:tags":[
        "telecommunication"
    ],
    "wof:name":"F\u00c4wa-elektronik Ag Hadlikon",
    "wof:placetype":"venue"
},
  "geometry": {"coordinates":[8.8586368561,47.2871170044],"type":"Point"}
}