{
  "type": "Feature",
  "properties": {
    "iso:country":"CH",
    "sg:address":"Bernstrasse 62",
    "sg:city":"Schnottwil",
    "sg:classifiers":[
        {
            "category":"Restaurant",
            "type":"Food & Drink"
        }
    ],
    "sg:phone":"+41 32 351 24 26",
    "sg:postcode":"3253",
    "sg:province":"Solothurn",
    "wof:name":"Restaurant Zum R\u00f6ssli",
    "wof:placetype":"venue"
},
  "geometry": {"coordinates":[7.3917531967,47.1058387756],"type":"Point"}
}