{
  "type": "Feature",
  "properties": {
    "iso:country":"CH",
    "sg:address":"Via Alla Chiesa",
    "sg:city":"Torricella",
    "sg:orig_category":"Gemeindeverwaltungen",
    "sg:phone":"+41 91 935 75 10",
    "sg:postcode":"6808",
    "sg:province":"Ticino",
    "wof:name":"Amministrazione Comunale Di Torricella-taverne",
    "wof:placetype":"venue"
},
  "geometry": {"coordinates":[8.9221410751,46.0651702881],"type":"Point"}
}