{
  "type": "Feature",
  "properties": {
    "iso:country":"CH",
    "sg:address":"Gerbergasse 20 4001 Basel. Postfach 548",
    "sg:city":"Basel",
    "sg:orig_category":"Reiseb\u00fcros",
    "sg:phone":"+41 61 261 87 25",
    "sg:postcode":"4001",
    "sg:province":"Basel-Stadt",
    "wof:name":"Imholz Reisen",
    "wof:placetype":"venue"
},
  "geometry": {"coordinates":[7.5880451202,47.557144165],"type":"Point"}
}