{
  "type": "Feature",
  "properties": {
    "iso:country":"CH",
    "sg:address":"Ruelle De La Muraz 22",
    "sg:city":"Nyon",
    "sg:orig_category":"Sprachschulen",
    "sg:phone":"+41 22 361 17 64",
    "sg:postcode":"1260",
    "sg:province":"Vaud",
    "wof:name":"Ecole Pratique De Secr\u00e9tariat & De Langues",
    "wof:placetype":"venue"
},
  "geometry": {"coordinates":[6.2358598709,46.3824615479],"type":"Point"}
}