{
  "type": "Feature",
  "properties": {
    "iso:country":"CH",
    "sg:address":"1468",
    "sg:city":"Cheyres",
    "sg:orig_category":"Vorschulen, Kinderg\u00e4rten",
    "sg:phone":"+41 26 662 10 63",
    "sg:postcode":"1468",
    "sg:province":"Fribourg",
    "wof:name":"Ecole Enfantine",
    "wof:placetype":"venue"
},
  "geometry": {"coordinates":[6.8926100731,46.8147010803],"type":"Point"}
}