{
  "type": "Feature",
  "properties": {
    "iso:country":"CH",
    "sg:address":"Benglenstrasse 30",
    "sg:city":"Pfaffhausen",
    "sg:orig_category":"Vorschulen, Kinderg\u00e4rten",
    "sg:phone":"+41 18251842",
    "sg:postcode":"8118",
    "sg:province":"Z\u00fcrich",
    "wof:name":"Kindergarten Bommern",
    "wof:placetype":"venue"
},
  "geometry": {"coordinates":[8.6258831024,47.3619003296],"type":"Point"}
}