{
  "type": "Feature",
  "properties": {
    "addr:full":"Bernstrasse 306 Heimberg Bern 3627",
    "addr:housenumber":"306",
    "addr:postcode":"3627",
    "addr:street":"Bernstrasse",
    "iso:country":"CH",
    "sg:address":"Bernstrasse 306",
    "sg:city":"Heimberg",
    "sg:orig_category":"Advokaturb\u00fcros Notariate",
    "sg:phone":"+41 33 225 20 00",
    "sg:postcode":"3627",
    "sg:province":"Bern",
    "wof:name":"Andrea R\u00e4to Keller Advokatur-& Notariatsb\u00fcro",
    "wof:placetype":"venue"
},
  "geometry": {"coordinates":[7.607115,46.791248],"type":"Point"}
}