{
  "type": "Feature",
  "properties": {
    "iso:country":"CH",
    "sg:address":"Schulstrasse 16",
    "sg:city":"Romanshorn",
    "sg:orig_category":"Institutionen f\u00fcr Behinderte Sonderschulen",
    "sg:phone":"+41 71 463 27 35",
    "sg:postcode":"8590",
    "sg:province":"Thurgau",
    "wof:name":"Heilp\u00e4dagogische Schule",
    "wof:placetype":"venue"
},
  "geometry": {"coordinates":[9.3767623901,47.5620231628],"type":"Point"}
}