{
  "type": "Feature",
  "properties": {
    "iso:country":"CH",
    "sg:address":"Klosternrain 19",
    "sg:city":"Steffisburg",
    "sg:orig_category":"Herstellung von Schmuck, Gold U Silberschmiedwaren",
    "sg:phone":"+41 71 383 24 44",
    "sg:postcode":"3612",
    "sg:province":"Bern",
    "wof:name":"Goldschmiede-atelier Susanne Kr\u00fcsi",
    "wof:placetype":"venue"
},
  "geometry": {"coordinates":[9.2549495697,47.4144134521],"type":"Point"}
}