{
  "type": "Feature",
  "properties": {
    "iso:country":"CH",
    "sg:address":"B\u00fcelweg 196",
    "sg:city":"Wintersingen",
    "sg:orig_category":"Vereine Fasnacht",
    "sg:postcode":"4451",
    "sg:province":"Basel-Landschaft",
    "wof:name":"Messingk\u00e4fer",
    "wof:placetype":"venue"
},
  "geometry": {"coordinates":[7.8299398422,47.4932594299],"type":"Point"}
}