{
  "type": "Feature",
  "properties": {
    "iso:country":"CH",
    "sg:address":"Saugettaz Chemin De La 5",
    "sg:city":"Cheseaux-lausanne",
    "sg:orig_category":"Stukkateurgewerbe, Gipserei U Verputzerei",
    "sg:phone":"+41 21 731 39 84",
    "sg:postcode":"1033",
    "sg:province":"Vaud",
    "wof:name":"Gargano Alfonso",
    "wof:placetype":"venue"
},
  "geometry": {"coordinates":[6.6048598289,46.5855407715],"type":"Point"}
}