{
  "type": "Feature",
  "properties": {
    "iso:country":"CH",
    "sg:address":"Bernerhof 3003 Bern. Postfach",
    "sg:city":"Bern",
    "sg:orig_category":"Finanz\u00e4mter",
    "sg:phone":"+41 31 322 21 11",
    "sg:postcode":"3003",
    "sg:province":"Bern",
    "wof:name":"Eidg. Finanzdepartement",
    "wof:placetype":"venue"
},
  "geometry": {"coordinates":[7.4482097626,46.9480209351],"type":"Point"}
}