{
  "type": "Feature",
  "properties": {
    "iso:country":"CH",
    "sg:address":"Lavaterstrasse 55 8002 Z\u00fcrich. Postfach",
    "sg:city":"Z\u00fcrich",
    "sg:orig_category":"Grosshandel mit Textilien Grosshandel mit sonstigen Konsumg\u00fctern",
    "sg:phone":"+41 12022615",
    "sg:postcode":"8027",
    "sg:province":"Z\u00fcrich",
    "wof:name":"Zagoda Handels Ag",
    "wof:placetype":"venue"
},
  "geometry": {"coordinates":[8.5328531265,47.3618583679],"type":"Point"}
}