{
  "type": "Feature",
  "properties": {
    "iso:country":"CH",
    "sg:address":"B\u00e4umleingasse 9",
    "sg:city":"Basel",
    "sg:orig_category":"Interessenvertretungen",
    "sg:postcode":"4051",
    "sg:province":"Basel-Stadt",
    "wof:name":"Beyeler-stiftung",
    "wof:placetype":"venue"
},
  "geometry": {"coordinates":[7.5925140381,47.555065155],"type":"Point"}
}