{
  "type": "Feature",
  "properties": {
    "iso:country":"CH",
    "sg:address":"Grabenstrasse 4",
    "sg:city":"Thun",
    "sg:orig_category":"Physiotherapie",
    "sg:phone":"+41 33 223 20 24",
    "sg:postcode":"3600",
    "sg:province":"Bern",
    "wof:name":"Physiotherapie Grabengut",
    "wof:placetype":"venue"
},
  "geometry": {"coordinates":[7.6279602051,46.7617530823],"type":"Point"}
}