{
  "type": "Feature",
  "properties": {
    "iso:country":"CH",
    "sg:address":"Wilerstrasse 3a 9242 Oberuzwil. Postfach",
    "sg:city":"Oberuzwil",
    "sg:orig_category":"RESTAURANTS: TEA-ROOMS",
    "sg:postcode":"9242",
    "sg:province":"St. Gallen",
    "wof:name":"Restaurant Dorfplatz Hans Gerschwiler",
    "wof:placetype":"venue"
},
  "geometry": {"coordinates":[9.1227407455,47.4298973083],"type":"Point"}
}