{
  "type": "Feature",
  "properties": {
    "iso:country":"CH",
    "sg:address":"1441",
    "sg:city":"Valeyres-montagny",
    "sg:orig_category":"Schwimmb\u00e4der Tennis- and Squash-Centers Hallen",
    "sg:phone":"+41 91 966 78 48",
    "sg:postcode":"1441",
    "sg:province":"Vaud",
    "wof:name":"Centro Sportivo Val Gersa Tennis Club Val Gersa",
    "wof:placetype":"venue"
},
  "geometry": {"coordinates":[8.9436798096,46.0196495056],"type":"Point"}
}