{
  "type": "Feature",
  "properties": {
    "iso:country":"CH",
    "sg:address":"Sandweg 3",
    "sg:city":"Lenzburg",
    "sg:orig_category":"Architektur U Ingenieurb\u00fcros",
    "sg:postcode":"5600",
    "sg:province":"Aargau",
    "wof:name":"Schmid Werner Architekt Htl",
    "wof:placetype":"venue"
},
  "geometry": {"coordinates":[7.440002,46.976944],"type":"Point"}
}