{
  "type": "Feature",
  "properties": {
    "iso:country":"CH",
    "sg:address":"Obstgartenstrasse 3",
    "sg:city":"Schlattingen",
    "sg:orig_category":"Autogaragen",
    "sg:phone":"+41 52 657 14 67",
    "sg:postcode":"8255",
    "sg:province":"Thurgau",
    "wof:name":"Ernst Gamp Garage",
    "wof:placetype":"venue"
},
  "geometry": {"coordinates":[8.770012,47.665737],"type":"Point"}
}