{
  "type": "Feature",
  "properties": {
    "iso:country":"CH",
    "sg:address":"Sch\u00fctzenrain 8 Ortschwaben 3045 Meikirch. Postfach",
    "sg:city":"Ortschwaben",
    "sg:orig_category":"Unternehmensberatung",
    "sg:postcode":"3042",
    "sg:province":"Bern",
    "wof:name":"B\u00e4cher Projektmanagement",
    "wof:placetype":"venue"
},
  "geometry": {"coordinates":[7.3670520782,47.0093307495],"type":"Point"}
}