{
  "type": "Feature",
  "properties": {
    "iso:country":"CH",
    "sg:address":"Schneidersmatt 20a",
    "sg:city":"W\u00fcnnewil",
    "sg:orig_category":"Herstellung von keramischen Wand U Bodenfliesen U platten Verlegen von Fliesen U Platten",
    "sg:phone":"+41 61 731 14 32",
    "sg:postcode":"3184",
    "sg:province":"Fribourg",
    "wof:name":"Hermann Gusti Ag",
    "wof:placetype":"venue"
},
  "geometry": {"coordinates":[7.5155329704,47.4749755859],"type":"Point"}
}