{
  "type": "Feature",
  "properties": {
    "iso:country":"CH",
    "sg:address":"Wydenstr.28",
    "sg:city":"B\u00fcrglen",
    "sg:classifiers":[
        {
            "category":"Professional",
            "subcategory":"Engineering",
            "type":"Services"
        }
    ],
    "sg:phone":"+41 71 633 22 27",
    "sg:postcode":"8575",
    "sg:province":"Thurgau",
    "sg:tags":[
        "metallurgy",
        "good",
        "material",
        "-",
        "machine",
        "equipment",
        "handling",
        "mechanical",
        "metalworkin"
    ],
    "wof:name":"B\u00c4r & Mettler Ag",
    "wof:placetype":"venue"
},
  "geometry": {"coordinates":[9.1468276978,47.5533103943],"type":"Point"}
}