{
  "type": "Feature",
  "properties": {
    "iso:country":"CH",
    "sg:address":"Taastrasse 25 9442 Berneck. Postfach",
    "sg:city":"Berneck",
    "sg:orig_category":"Rechtsberatung",
    "sg:phone":"+41 71 744 36 12",
    "sg:postcode":"9442",
    "sg:province":"St. Gallen",
    "wof:name":"Patente Und Lizenzen D\u00f6ring Dr. H.c E. Bereck Patente U. Lizenzen; Verwertung",
    "wof:placetype":"venue"
},
  "geometry": {"coordinates":[9.6002550125,47.4242706299],"type":"Point"}
}