{
  "type": "Feature",
  "properties": {
    "iso:country":"CH",
    "sg:address":"Br\u00fcnneliacker 6",
    "sg:city":"Z\u00fcrich",
    "sg:orig_category":"Reiseb\u00fcros U Reiseveranstalter",
    "sg:phone":"+41 76 322 91 02",
    "sg:postcode":"8047",
    "sg:province":"Z\u00fcrich",
    "wof:name":"Albesa Reisen Matjani",
    "wof:placetype":"venue"
},
  "geometry": {"coordinates":[9.0400047302,47.4648094177],"type":"Point"}
}