{
  "type": "Feature",
  "properties": {
    "iso:country":"CH",
    "sg:address":"R\u00fctliweg 9a",
    "sg:city":"Meggen",
    "sg:orig_category":"Architektur U Ingenieurb\u00fcros",
    "sg:phone":"+41 41 377 37 86",
    "sg:postcode":"6045",
    "sg:province":"Luzern",
    "wof:name":"Ipag Immovativ Promotions Ag",
    "wof:placetype":"venue"
},
  "geometry": {"coordinates":[8.365448,47.050274],"type":"Point"}
}