{
  "type": "Feature",
  "properties": {
    "iso:country":"CH",
    "sg:address":"Route De Bossey 3",
    "sg:city":"Troinex",
    "sg:classifiers":[
        {
            "category":"Restaurant",
            "type":"Food & Drink"
        }
    ],
    "sg:phone":"+41 22 784 32 49",
    "sg:postcode":"1256",
    "sg:province":"Gen\u00e8ve",
    "wof:name":"Restaurant Maison Grise",
    "wof:placetype":"venue"
},
  "geometry": {"coordinates":[6.1527628899,46.1617355347],"type":"Point"}
}