{
  "type": "Feature",
  "properties": {
    "iso:country":"CH",
    "sg:address":"Rheingasse 1",
    "sg:city":"Langwiesen",
    "sg:orig_category":"Vorschulen, Kinderg\u00e4rten",
    "sg:phone":"+41 52 659 35 54",
    "sg:postcode":"8246",
    "sg:province":"Z\u00fcrich",
    "wof:name":"Kindergarten",
    "wof:placetype":"venue"
},
  "geometry": {"coordinates":[8.6631164551,47.6841316223],"type":"Point"}
}