{
  "type": "Feature",
  "properties": {
    "iso:country":"CH",
    "sg:address":"Chemin De La Moraine 14",
    "sg:city":"St-prex",
    "sg:orig_category":"Unternehmensberatung",
    "sg:phone":"+41 21 806 15 33",
    "sg:postcode":"1162",
    "sg:province":"Vaud",
    "wof:name":"David Cl\u00e9nin Conseils D'entreprises",
    "wof:placetype":"venue"
},
  "geometry": {"coordinates":[6.4515337944,46.4779663086],"type":"Point"}
}