{
  "type": "Feature",
  "properties": {
    "iso:country":"CH",
    "sg:address":"Place De La Libert\u00e9 2",
    "sg:city":"Del\u00e9mont",
    "sg:orig_category":"Unclassifiable Establishments",
    "sg:phone":"+41 32 423 21 38",
    "sg:postcode":"2800",
    "sg:province":"Jura",
    "wof:name":"Maxton Holding Sa",
    "wof:placetype":"venue"
},
  "geometry": {"coordinates":[7.3437600136,47.3652687073],"type":"Point"}
}