{
  "type": "Feature",
  "properties": {
    "iso:country":"CH",
    "sg:address":"Rainlihof 4",
    "sg:city":"Horw",
    "sg:orig_category":"Betrieb von Taxis",
    "sg:postcode":"6048",
    "sg:province":"Luzern",
    "wof:name":"Btq Gmbh",
    "wof:placetype":"venue"
},
  "geometry": {"coordinates":[8.301102,47.011494],"type":"Point"}
}