{
  "type": "Feature",
  "properties": {
    "iso:country":"CH",
    "sg:address":"8784 Braunwald. Postfach",
    "sg:city":"Braunwald",
    "sg:orig_category":"Fachdetailhandel in Verkaufsr\u00e4umen",
    "sg:phone":"+41 55 643 35 69",
    "sg:postcode":"8784",
    "sg:province":"Glarus",
    "wof:name":"Ahorn-sport Hutter F.",
    "wof:placetype":"venue"
},
  "geometry": {"coordinates":[8.9982004166,46.9389533997],"type":"Point"}
}