{
  "type": "Feature",
  "properties": {
    "iso:country":"CH",
    "sg:address":"Steigerstrasse 9",
    "sg:city":"St.gallen",
    "sg:orig_category":"Non-Classified Establishments",
    "sg:postcode":"9000",
    "sg:province":"St. Gallen",
    "wof:name":"M\u00fcller Naturprodukte",
    "wof:placetype":"venue"
},
  "geometry": {"coordinates":[9.392288208,47.4282684326],"type":"Point"}
}