{
  "type": "Feature",
  "properties": {
    "iso:country":"CH",
    "sg:address":"Marzilistrasse 8a",
    "sg:city":"Bern",
    "sg:classifiers":[
        {
            "category":"Personal",
            "subcategory":"Piercing",
            "type":"Services"
        }
    ],
    "sg:phone":"+41 31 311 47 88",
    "sg:postcode":"3005",
    "sg:province":"Bern",
    "sg:tags":[
        "tattoo"
    ],
    "wof:name":"Piercing Wild & Heart & Tattoo 32",
    "wof:placetype":"venue"
},
  "geometry": {"coordinates":[7.4432849884,46.9442481995],"type":"Point"}
}