{
  "type": "Feature",
  "properties": {
    "iso:country":"CH",
    "sg:address":"Haus Gorben B Gesch",
    "sg:city":"Niedergesteln",
    "sg:orig_category":"Baugewerbe",
    "sg:phone":"+41 62 216 62 84",
    "sg:postcode":"3942",
    "sg:province":"Valais",
    "wof:name":"Imw Ag Internat.montagen",
    "wof:placetype":"venue"
},
  "geometry": {"coordinates":[7.85655,47.339371],"type":"Point"}
}