{
  "type": "Feature",
  "properties": {
    "addr:full":"Rue Du M\u00f4le 42bis Gen\u00e8ve Gen\u00e8ve 1201",
    "addr:housenumber":"42bis",
    "addr:postcode":"1201",
    "addr:street":"Rue Du Mo\u0302Le",
    "iso:country":"CH",
    "sg:address":"Rue Du M\u00f4le 42bis",
    "sg:city":"Gen\u00e8ve",
    "sg:orig_category":"Autogaragen",
    "sg:phone":"+41 22 731 37 62",
    "sg:postcode":"1201",
    "sg:province":"Gen\u00e8ve",
    "wof:name":"A. Pedrina & A.greco Garage Le Royal",
    "wof:placetype":"venue"
},
  "geometry": {"coordinates":[6.146099,46.213566],"type":"Point"}
}