{
  "type": "Feature",
  "properties": {
    "iso:country":"CH",
    "sg:address":"Schwandstrasse 54",
    "sg:city":"Engelberg",
    "sg:orig_category":"Fachdetailhandel in Verkaufsr\u00e4umen",
    "sg:phone":"+41 41 637 03 26",
    "sg:postcode":"6390",
    "sg:province":"Obwalden",
    "wof:name":"Gloggner-gherbi Pictures",
    "wof:placetype":"venue"
},
  "geometry": {"coordinates":[8.4022703171,46.8237075806],"type":"Point"}
}