{
  "type": "Feature",
  "properties": {
    "addr:full":"Hof Fr\u00fcmsen St. Gallen 9467",
    "addr:housenumber":"9467",
    "iso:country":"CH",
    "sg:address":"Hof",
    "sg:city":"Fr\u00fcmsen",
    "sg:orig_category":"Bauschreinerei Herstellung von Konstruktionsteilen, Fertigbauteilen U Ausbauelementen aus Holz",
    "sg:phone":"+41 81 757 12 72",
    "sg:postcode":"9467",
    "sg:province":"St. Gallen",
    "wof:name":"Bernegger Hans Ag",
    "wof:placetype":"venue"
},
  "geometry": {"coordinates":[9.473477,47.245136],"type":"Point"}
}