{
  "type": "Feature",
  "properties": {
    "addr:full":"St.-johannes-strasse 2 Zug Zug 6300",
    "addr:housenumber":"2",
    "addr:postcode":"6300",
    "addr:street":"St.-Johannes-Strasse;Zug",
    "iso:country":"CH",
    "sg:address":"St.-johannes-strasse 2",
    "sg:city":"Zug",
    "sg:orig_category":"Architektur U Ingenieurb\u00fcros",
    "sg:phone":"+41 71 971 58 36",
    "sg:postcode":"6300",
    "sg:province":"Zug",
    "wof:name":"Bajka-bau Gmbh",
    "wof:placetype":"venue"
},
  "geometry": {"coordinates":[8.966999,47.460022],"type":"Point"}
}