{
  "type": "Feature",
  "properties": {
    "iso:country":"CH",
    "sg:address":"Limmattalstrasse 216",
    "sg:city":"Z\u00fcrich",
    "sg:orig_category":"Unclassifiable Establishments",
    "sg:postcode":"8049",
    "sg:province":"Z\u00fcrich",
    "wof:name":"Jos\u00e9 Monteiro",
    "wof:placetype":"venue"
},
  "geometry": {"coordinates":[8.4974145889,47.4022865295],"type":"Point"}
}