{
  "type": "Feature",
  "properties": {
    "iso:country":"CH",
    "sg:address":"Weinbergstrasse 131",
    "sg:city":"Z\u00fcrich",
    "sg:orig_category":"Architekturb\u00fcros",
    "sg:phone":"+41 13619628",
    "sg:postcode":"8006",
    "sg:province":"Z\u00fcrich",
    "wof:name":"Armando Lendi Dipl.architekt Eth",
    "wof:placetype":"venue"
},
  "geometry": {"coordinates":[8.540529,47.388203],"type":"Point"}
}