{
  "type": "Feature",
  "properties": {
    "iso:country":"CH",
    "sg:address":"Rorschacherstrasse 52",
    "sg:city":"Rheineck",
    "sg:orig_category":"Einzelhandel mit Automobilteilen U Zubeh\u00f6r Herstellung von Bereifungen",
    "sg:phone":"+41 71 888 33 35",
    "sg:postcode":"9424",
    "sg:province":"St. Gallen",
    "wof:name":"Pneu-b\u00f6rse Haering Gmbh",
    "wof:placetype":"venue"
},
  "geometry": {"coordinates":[9.5835075378,47.4720497131],"type":"Point"}
}