{
  "type": "Feature",
  "properties": {
    "addr:full":"Chottengass Pfaffnau Luzern 6264",
    "addr:postcode":"6264",
    "addr:street":"Chottengass",
    "iso:country":"CH",
    "sg:address":"Chottengass",
    "sg:city":"Pfaffnau",
    "sg:orig_category":"Arztpraxen",
    "sg:phone":"+41 62 747 30 10",
    "sg:postcode":"6264",
    "sg:province":"Luzern",
    "wof:name":"Dr.med.markus Wili Arzt F\u00fcr Allgemeine Medizin",
    "wof:placetype":"venue"
},
  "geometry": {"coordinates":[7.896968,47.226116],"type":"Point"}
}