{
  "type": "Feature",
  "properties": {
    "iso:country":"CH",
    "sg:address":"Hauptgasse 30/32 4600 Olten. Postfach",
    "sg:city":"Olten",
    "sg:orig_category":"Detailhandel mit Damenbekleidung Detailhandel mit Herrenbekleidung",
    "sg:phone":"+41 62 212 82 82",
    "sg:postcode":"4601",
    "sg:province":"Solothurn",
    "wof:name":"Schild Ag",
    "wof:placetype":"venue"
},
  "geometry": {"coordinates":[7.9031338692,47.3500785828],"type":"Point"}
}