{
  "type": "Feature",
  "properties": {
    "iso:country":"CH",
    "sg:address":"Burgrain 37",
    "sg:city":"Meilen",
    "sg:orig_category":"Herstellung von medizinischen U chirurgischen Ger\u00e4ten sowie orthop\u00e4dischen Vorrichtungen",
    "sg:postcode":"8706",
    "sg:province":"Z\u00fcrich",
    "wof:name":"Wasserfels Ag",
    "wof:placetype":"venue"
},
  "geometry": {"coordinates":[8.6410570145,47.2734375],"type":"Point"}
}