{
  "type": "Feature",
  "properties": {
    "iso:country":"CH",
    "sg:address":"Effingerstrasse 3 3011 Bern. Postfach 6922",
    "sg:city":"Bern",
    "sg:orig_category":"Wirtschaftsverb\u00e4nde Industrie, Handel and Gewerbe",
    "sg:phone":"+41 31 381 16 86",
    "sg:postcode":"3001",
    "sg:province":"Bern",
    "wof:name":"Verband Textilreiniger Schweiz",
    "wof:placetype":"venue"
},
  "geometry": {"coordinates":[7.436425209,46.9456787109],"type":"Point"}
}