{
  "type": "Feature",
  "properties": {
    "iso:country":"CH",
    "sg:address":"Rue Du Pont 5",
    "sg:city":"Noiraigue",
    "sg:orig_category":"Herstellung von Kakao U Schokoladeerzeugnissen Herstellung von Kakao, Schokoladeerzeugnissen U Zucke",
    "sg:phone":"+41 32 863 31 10",
    "sg:postcode":"2103",
    "sg:province":"Neuch\u00e2tel",
    "wof:name":"Jacot & Cie, Confiserie",
    "wof:placetype":"venue"
},
  "geometry": {"coordinates":[6.725030899,46.956577301],"type":"Point"}
}