{
  "type": "Feature",
  "properties": {
    "iso:country":"CH",
    "sg:address":"Martinsgasse 3",
    "sg:city":"Malters",
    "sg:orig_category":"Fachdetailhandel in Verkaufsr\u00e4umen Handel mit Motorr\u00e4dern, Teilen U Zubeh\u00f6r Instandhaltung U Reparat",
    "sg:phone":"+41 41 497 16 33",
    "sg:postcode":"6102",
    "sg:province":"Luzern",
    "wof:name":"Bucheli-koch H.",
    "wof:placetype":"venue"
},
  "geometry": {"coordinates":[8.1838274002,47.0365333557],"type":"Point"}
}