{
  "type": "Feature",
  "properties": {
    "iso:country":"CH",
    "sg:address":"Gellertstrasse 235 4052 Basel. Postfach 312",
    "sg:city":"Basel",
    "sg:orig_category":"Gymnastik U Fitnesszentren",
    "sg:phone":"+41 61 312 36 36",
    "sg:postcode":"4020",
    "sg:province":"Basel-Stadt",
    "wof:name":"Joggeli Fitness Club Basel",
    "wof:placetype":"venue"
},
  "geometry": {"coordinates":[7.6189498901,47.5448417664],"type":"Point"}
}