{
  "type": "Feature",
  "properties": {
    "iso:country":"CH",
    "sg:address":"Grubenstrasse 56 8045 Z\u00fcrich. Postfach",
    "sg:city":"Z\u00fcrich",
    "sg:orig_category":"Unternehmensberatung",
    "sg:phone":"+41 14555666",
    "sg:postcode":"8045",
    "sg:province":"Z\u00fcrich",
    "wof:name":"Piar Ag F\u00fcr Oeffentlichkeitsarbeit Und Werbung Unternehmensberatung F\u00fcr Kommunikation",
    "wof:placetype":"venue"
},
  "geometry": {"coordinates":[8.5104980469,47.362739563],"type":"Point"}
}