{
  "type": "Feature",
  "properties": {
    "addr:full":"D\u00fcrrmattstrasse 16 Niederlenz Aargau 5702",
    "addr:housenumber":"16",
    "addr:postcode":"5702",
    "addr:street":"Duerrmattstrasse",
    "iso:country":"CH",
    "sg:address":"D\u00fcrrmattstrasse 16",
    "sg:city":"Niederlenz",
    "sg:orig_category":"Allgemeiner Hoch U Tiefbau",
    "sg:postcode":"5702",
    "sg:province":"Aargau",
    "wof:name":"H\u00e4fliger Bau Ag",
    "wof:placetype":"venue"
},
  "geometry": {"coordinates":[7.910216,47.14666],"type":"Point"}
}