{
  "type": "Feature",
  "properties": {
    "iso:country":"CH",
    "sg:address":"Schmittegass 2a",
    "sg:city":"H\u00fcnenberg",
    "sg:orig_category":"Politische Parteien CVP",
    "sg:phone":"+41 41 780 62 76",
    "sg:postcode":"6331",
    "sg:province":"Zug",
    "wof:name":"Cvp Ortspartei H\u00fcnenberg",
    "wof:placetype":"venue"
},
  "geometry": {"coordinates":[8.4265041351,47.1740226746],"type":"Point"}
}