{
  "type": "Feature",
  "properties": {
    "iso:country":"CH",
    "sg:address":"Giebelegg",
    "sg:city":"Schwenden",
    "sg:orig_category":"Grosshandel mit lebenden Tieren",
    "sg:phone":"+41 33 684 11 37",
    "sg:postcode":"3757",
    "sg:province":"Bern",
    "wof:name":"Hans Knutti Viehhandel",
    "wof:placetype":"venue"
},
  "geometry": {"coordinates":[7.4917650223,46.5800590515],"type":"Point"}
}