{
  "type": "Feature",
  "properties": {
    "iso:country":"CH",
    "sg:address":"Route De Ch\u00e2tel 10",
    "sg:city":"Corseaux",
    "sg:orig_category":"Grosshandel mit B\u00fcromaschinen Herstellung von sonstigen Waren aus Papier, Karton U Pappe",
    "sg:phone":"+41 62 824 56 51",
    "sg:postcode":"1802",
    "sg:province":"Vaud",
    "wof:name":"Decofix Ag",
    "wof:placetype":"venue"
},
  "geometry": {"coordinates":[8.0821180344,47.3878936768],"type":"Point"}
}