{
  "type": "Feature",
  "properties": {
    "iso:country":"CH",
    "sg:address":"F\u00f6hrenweg 14 9496 Balzers. Postfach 130",
    "sg:city":"Balzers",
    "sg:orig_category":"Herstellung von Tanks U Sammelbeh\u00e4ltern aus Metall Sanit\u00e4r U Heizungsinstallation",
    "sg:phone":"+423 384 15 42",
    "sg:postcode":"9496",
    "wof:name":"Roman Frick Anstalt F\u00fcr Heizungen & Tankrevisionen",
    "wof:placetype":"venue"
},
  "geometry": {"coordinates":[9.5086841583,47.0757598877],"type":"Point"}
}