{
  "type": "Feature",
  "properties": {
    "iso:country":"CH",
    "sg:address":"Uitikonerstrasse 9",
    "sg:city":"Schlieren",
    "sg:orig_category":"Sonstiger Fachdetailhandel mit Nahrungsmitteln, Getr\u00e4nken U Tabak in Verkaufsr\u00e4umen",
    "sg:phone":"+41 17308270",
    "sg:postcode":"8952",
    "sg:province":"Z\u00fcrich",
    "wof:name":"Bioladen Bio Im Zentrum Lielienzentrum",
    "wof:placetype":"venue"
},
  "geometry": {"coordinates":[8.448266983,47.3970527649],"type":"Point"}
}