{
  "type": "Feature",
  "properties": {
    "iso:country":"CH",
    "sg:address":"Weinbergh\u00f6he 3",
    "sg:city":"Zug",
    "sg:orig_category":"Grosshandel mit elektrischen Haushaltsger\u00e4ten Herstellung von elektrischen Lampen U Leuchten",
    "sg:phone":"+41 41 720 30 62",
    "sg:postcode":"6300",
    "sg:province":"Zug",
    "wof:name":"Ecolight Els Ag",
    "wof:placetype":"venue"
},
  "geometry": {"coordinates":[8.526219368,47.1696014404],"type":"Point"}
}