{
  "type": "Feature",
  "properties": {
    "iso:country":"CH",
    "sg:address":"Wiesackerstrasse 133",
    "sg:city":"Regensdorf",
    "sg:orig_category":"Herstellung von Metallerzeugnissen ohne Maschinenbau Herstellung von k\u00e4lte U lufttechnischen Erzeugn",
    "sg:phone":"+41 18406500",
    "sg:postcode":"8105",
    "sg:province":"Z\u00fcrich",
    "wof:name":"Autok\u00fchler Ag",
    "wof:placetype":"venue"
},
  "geometry": {"coordinates":[8.4581727982,47.4404182434],"type":"Point"}
}