{
  "type": "Feature",
  "properties": {
    "iso:country":"CH",
    "sg:address":"Fraum\u00fcnsterstrasse 11",
    "sg:city":"Z\u00fcrich",
    "sg:orig_category":"Detailhandel mit Antiquit\u00e4ten U Gebrauchtwaren in Verkaufsr\u00e4umen",
    "sg:phone":"+41 12120162",
    "sg:postcode":"8001",
    "sg:province":"Z\u00fcrich",
    "wof:name":"Samar, Saideh Klotz Schmuck, Antiquit\u00e4ten, Bekleidung; Handel",
    "wof:placetype":"venue"
},
  "geometry": {"coordinates":[8.54068,47.368744],"type":"Point"}
}