{
  "type": "Feature",
  "properties": {
    "iso:country":"CH",
    "sg:address":"Eggh\u00f6lzlistrasse 3",
    "sg:city":"Bern",
    "sg:orig_category":"Softwareentwicklung U beratung",
    "sg:phone":"+41 61 713 21 40",
    "sg:postcode":"3006",
    "sg:province":"Bern",
    "wof:name":"R. U. N. Netwave Gmbh",
    "wof:placetype":"venue"
},
  "geometry": {"coordinates":[7.5900797844,47.4884529114],"type":"Point"}
}