{
  "type": "Feature",
  "properties": {
    "addr:full":"Bahnhofstrasse 62c Ins Bern 3232",
    "addr:housenumber":"62c",
    "addr:postcode":"3232",
    "addr:street":"Bahnhofstrasse;Bern",
    "iso:country":"CH",
    "sg:address":"Bahnhofstrasse 62c",
    "sg:city":"Ins",
    "sg:orig_category":"Allgemeiner Gartenbau Dienstleistungen im Gartenbau",
    "sg:phone":"+41 32 313 73 33",
    "sg:postcode":"3232",
    "sg:province":"Bern",
    "wof:name":"Garten Eden Gmbh",
    "wof:placetype":"venue"
},
  "geometry": {"coordinates":[7.101503,47.002731],"type":"Point"}
}