{
  "type": "Feature",
  "properties": {
    "iso:country":"CH",
    "sg:address":"Via Fontana",
    "sg:city":"Tesserete",
    "sg:orig_category":"Kantonalbanken",
    "sg:phone":"+41 91 943 53 33",
    "sg:postcode":"6950",
    "sg:province":"Ticino",
    "wof:name":"Banca Dello Stato Del Cantone Ticino",
    "wof:placetype":"venue"
},
  "geometry": {"coordinates":[8.9661169052,46.0668678284],"type":"Point"}
}