{
  "type": "Feature",
  "properties": {
    "iso:country":"CH",
    "sg:address":"Wiestistrasse 168 3920 Zermatt. Postfach 191",
    "sg:city":"Zermatt",
    "sg:classifiers":[
        {
            "category":"Travel",
            "subcategory":"Hotels & Motels",
            "type":"Entertainment"
        }
    ],
    "sg:phone":"+41 27 967 30 13",
    "sg:postcode":"3920",
    "sg:province":"Valais",
    "sg:tags":[
        "hotels",
        "mit",
        "restaurant"
    ],
    "wof:name":"Hotel Primavera",
    "wof:placetype":"venue"
},
  "geometry": {"coordinates":[7.7543201447,46.0239906311],"type":"Point"}
}