{
  "type": "Feature",
  "properties": {
    "iso:country":"CH",
    "sg:address":"Aeussere Lange Heid 35",
    "sg:city":"M\u00fcnchenstein",
    "sg:orig_category":"Primarschulen",
    "sg:phone":"+41 61 411 69 89",
    "sg:postcode":"4142",
    "sg:province":"Basel-Landschaft",
    "wof:name":"Primarschule Lange Heid",
    "wof:placetype":"venue"
},
  "geometry": {"coordinates":[7.6065530777,47.523601532],"type":"Point"}
}