{
  "type": "Feature",
  "properties": {
    "iso:country":"CH",
    "sg:address":"Winkelstrasse 8",
    "sg:city":"Reinach",
    "sg:classifiers":[
        {
            "category":"Building & Trades",
            "subcategory":"Construction",
            "type":"Services"
        }
    ],
    "sg:phone":"+41 62 765 07 07",
    "sg:postcode":"5734",
    "sg:province":"Aargau",
    "sg:tags":[
        "workshop",
        "grinding",
        "circular"
    ],
    "wof:name":"Erowa Ag",
    "wof:placetype":"venue"
},
  "geometry": {"coordinates":[8.18332,47.248608],"type":"Point"}
}