{
  "type": "Feature",
  "properties": {
    "iso:country":"CH",
    "sg:address":"Bois-de-finges Route Du 2",
    "sg:city":"Sierre",
    "sg:orig_category":"Herstellung von Schl\u00f6ssern U Beschl\u00e4gen",
    "sg:phone":"+41 27 455 39 10",
    "sg:postcode":"3960",
    "sg:province":"Valais",
    "wof:name":"Suppi Marie-th\u00e9r\u00e8se",
    "wof:placetype":"venue"
},
  "geometry": {"coordinates":[7.5448031425,46.2963600159],"type":"Point"}
}