{
  "type": "Feature",
  "properties": {
    "iso:country":"CH",
    "sg:address":"St. Galler Strasse 9",
    "sg:city":"Engelburg",
    "sg:classifiers":[
        {
            "category":"Restaurant",
            "type":"Food & Drink"
        }
    ],
    "sg:phone":"+41 71 278 23 28",
    "sg:postcode":"9032",
    "sg:province":"St. Gallen",
    "wof:name":"Restaurant Ochsen",
    "wof:placetype":"venue"
},
  "geometry": {"coordinates":[9.34171772,47.4436798096],"type":"Point"}
}