{
  "type": "Feature",
  "properties": {
    "iso:country":"CH",
    "sg:address":"Starenweg 9",
    "sg:city":"Gr\u00fcnenmatt",
    "sg:classifiers":[
        {
            "category":"Insurance",
            "subcategory":"Insurance Agent",
            "type":"Services"
        }
    ],
    "sg:phone":"+41 34 431 26 71",
    "sg:postcode":"3452",
    "sg:province":"Bern",
    "sg:tags":[
        "versicherungsagenturen",
        "-broker"
    ],
    "wof:name":"Winterthur-leben Agentur Paul Br\u00fcderlin",
    "wof:placetype":"venue"
},
  "geometry": {"coordinates":[7.7203397751,47.0087394714],"type":"Point"}
}