{
  "type": "Feature",
  "properties": {
    "iso:country":"CH",
    "sg:address":"Zentralstrasse",
    "sg:city":"Dierikon",
    "sg:orig_category":"Instandhaltung U Reparatur von Automobilen",
    "sg:phone":"+41 41 450 20 60",
    "sg:postcode":"6036",
    "sg:province":"Luzern",
    "wof:name":"Carrosserie & Spritzwerk Niederberger Werner Inhaber Odermatt D.",
    "wof:placetype":"venue"
},
  "geometry": {"coordinates":[8.3710947037,47.0987091064],"type":"Point"}
}