{
  "type": "Feature",
  "properties": {
    "iso:country":"CH",
    "sg:address":"Geissacher 8 8126 Zumikon. Postfach",
    "sg:city":"Zumikon",
    "sg:orig_category":"Unclassifiable Establishments",
    "sg:phone":"+41 19197171",
    "sg:postcode":"8126",
    "sg:province":"Z\u00fcrich",
    "wof:name":"Walroy Sa",
    "wof:placetype":"venue"
},
  "geometry": {"coordinates":[8.6274843216,47.3296813965],"type":"Point"}
}