{
  "type": "Feature",
  "properties": {
    "iso:country":"CH",
    "sg:address":"Oberrieterstrasse 24",
    "sg:city":"Eichberg",
    "sg:orig_category":"Detailhandel mit Waren verschiedener Art, Hauptrichtung Nahrungsmittel Grosshandel mit Nahrungsmitte",
    "sg:phone":"+41 71 755 70 40",
    "sg:postcode":"9453",
    "sg:province":"St. Gallen",
    "wof:name":"Hofstetter A.",
    "wof:placetype":"venue"
},
  "geometry": {"coordinates":[9.5311050415,47.3411178589],"type":"Point"}
}