{
  "type": "Feature",
  "properties": {
    "iso:country":"CH",
    "sg:address":"Gartenstrasse 10",
    "sg:city":"Toffen",
    "sg:orig_category":"Herstellung von Elektrizit\u00e4tsverteilungs U schalteinrichtungen",
    "sg:phone":"+41 31 819 71 12",
    "sg:postcode":"3125",
    "sg:province":"Bern",
    "wof:name":"Elbo Ag",
    "wof:placetype":"venue"
},
  "geometry": {"coordinates":[7.4904518127,46.8684768677],"type":"Point"}
}