{
  "type": "Feature",
  "properties": {
    "iso:country":"CH",
    "sg:address":"Route De Satigny 42",
    "sg:city":"Meyrin",
    "sg:orig_category":"Grosshandel mit Getr\u00e4nken Grosshandel mit Wein U Spirituosen",
    "sg:phone":"+41 22 341 10 77",
    "sg:postcode":"1217",
    "sg:province":"Gen\u00e8ve",
    "wof:name":"Alagna Vincent S\u00e0rl Vins; Import., Repr\u00e9sentation, Commerce",
    "wof:placetype":"venue"
},
  "geometry": {"coordinates":[6.0691370964,46.2185974121],"type":"Point"}
}