{
  "type": "Feature",
  "properties": {
    "iso:country":"CH",
    "sg:address":"Via Soave 9 -",
    "sg:city":"Lugano",
    "sg:classifiers":[
        {
            "category":"Professional",
            "subcategory":"Art Services",
            "type":"Services"
        }
    ],
    "sg:phone":"+41 91 922 78 82",
    "sg:postcode":"6900",
    "sg:province":"Ticino",
    "sg:tags":[
        "export-import"
    ],
    "wof:name":"Germany Consulate Honorary",
    "wof:placetype":"venue"
},
  "geometry": {"coordinates":[8.950287,46.004345],"type":"Point"}
}