{
  "type": "Feature",
  "properties": {
    "iso:country":"CH",
    "sg:address":"Seefeldstr. 539",
    "sg:city":"Meisterschwanden",
    "sg:orig_category":"Unternehmensberatung",
    "sg:phone":"+41 56 667 21 14",
    "sg:postcode":"5616",
    "sg:province":"Aargau",
    "wof:name":"Rogowski Dietrich Unternehmensberatung",
    "wof:placetype":"venue"
},
  "geometry": {"coordinates":[8.2272968292,47.2931022644],"type":"Point"}
}