{
  "type": "Feature",
  "properties": {
    "iso:country":"CH",
    "sg:address":"Via Esplanade 9",
    "sg:city":"Minusio",
    "sg:orig_category":"Sportvereine Wassersport Segeln",
    "sg:postcode":"6648",
    "sg:province":"Ticino",
    "wof:name":"Circolo Velico Di Locarno-riva",
    "wof:placetype":"venue"
},
  "geometry": {"coordinates":[8.8222084045,46.1797294617],"type":"Point"}
}