{
  "type": "Feature",
  "properties": {
    "iso:country":"CH",
    "sg:address":"Sommerauweg 4 4410 Liestal. Postfach 207",
    "sg:city":"Liestal",
    "sg:orig_category":"Softwareentwicklung U beratung",
    "sg:phone":"+41 61 923 23 05",
    "sg:postcode":"4410",
    "sg:province":"Basel-Landschaft",
    "wof:name":"Datavalue Gmbh Software; Herstellung, Vertrieb, Integration. Edv-dienstleistungen",
    "wof:placetype":"venue"
},
  "geometry": {"coordinates":[7.7324171066,47.485458374],"type":"Point"}
}