{
  "type": "Feature",
  "properties": {
    "iso:country":"CH",
    "sg:address":"Bahnhofstrasse 9",
    "sg:city":"Frick",
    "sg:orig_category":"Kaminfeger",
    "sg:phone":"+41 62 871 31 22",
    "sg:postcode":"5070",
    "sg:province":"Aargau",
    "wof:name":"Peter Herzog Kaminfegermeister",
    "wof:placetype":"venue"
},
  "geometry": {"coordinates":[8.0170497894,47.507938385],"type":"Point"}
}