{
  "type": "Feature",
  "properties": {
    "iso:country":"CH",
    "sg:address":"Amadio Via Degli 1 6900 Lugano. Postfach",
    "sg:city":"Lugano",
    "sg:orig_category":"R\u00fcckgewinnung U Vorbereitung f\u00fcr die Wiederverwertung Recycling von nichtmetallischen Altmaterialien",
    "sg:phone":"+41 21 960 29 07",
    "sg:postcode":"6900",
    "sg:province":"Ticino",
    "wof:name":"Rodec Sa",
    "wof:placetype":"venue"
},
  "geometry": {"coordinates":[6.9295902252,46.3618087769],"type":"Point"}
}