{
  "type": "Feature",
  "properties": {
    "iso:country":"CH",
    "sg:address":"Fribourg Route De 32",
    "sg:city":"Marly",
    "sg:orig_category":"Herstellung von Werkzeugen",
    "sg:phone":"+41 71 755 52 50",
    "sg:postcode":"1723",
    "sg:province":"Fribourg",
    "wof:name":"Mipro Tech Gmbh",
    "wof:placetype":"venue"
},
  "geometry": {"coordinates":[9.5576114655,47.3796081543],"type":"Point"}
}