{
  "type": "Feature",
  "properties": {
    "iso:country":"CH",
    "sg:address":"Rue G\u00e9n\u00e9ral-dufour 153 2500 Biel/bienne. Postfach",
    "sg:city":"Biel/bienne",
    "sg:orig_category":"Non-Classified Establishments",
    "sg:postcode":"2502",
    "sg:province":"Bern",
    "wof:name":"Eurotecnica Group Sa., Luxembourg, Succursale De Bienne",
    "wof:placetype":"venue"
},
  "geometry": {"coordinates":[7.2589321136,47.1452026367],"type":"Point"}
}