{
  "type": "Feature",
  "properties": {
    "iso:country":"CH",
    "sg:address":"Im Gl\u00f6gglihof 16",
    "sg:city":"Riehen",
    "sg:orig_category":"Sanit\u00e4r U Heizungsinstallation Sanit\u00e4rinstallation",
    "sg:phone":"+41 41 448 40 20",
    "sg:postcode":"4125",
    "sg:province":"Basel-Stadt",
    "wof:name":"Guido Fleischli Heizung Sanit\u00e4r",
    "wof:placetype":"venue"
},
  "geometry": {"coordinates":[8.3106651306,47.1307220459],"type":"Point"}
}