{
  "type": "Feature",
  "properties": {
    "iso:country":"CH",
    "sg:address":"Schulzentrum Alpha",
    "sg:city":"Naters",
    "sg:orig_category":"Allgemeinbildende weiterf\u00fchrende Schulen Primarschulen",
    "sg:phone":"+41 31 350 42 50",
    "sg:postcode":"3904",
    "sg:province":"Valais",
    "wof:name":"Evangelisches Seminar Muristalden, Bern",
    "wof:placetype":"venue"
},
  "geometry": {"coordinates":[7.459412,46.944508],"type":"Point"}
}