{
  "type": "Feature",
  "properties": {
    "iso:country":"CH",
    "sg:address":"Via Cantonale",
    "sg:city":"Mezzovico",
    "sg:orig_category":"Sicherheitsdienste",
    "sg:phone":"+41 71 923 60 65",
    "sg:postcode":"6805",
    "sg:province":"Ticino",
    "wof:name":"Secas Sicherheitsdienst",
    "wof:placetype":"venue"
},
  "geometry": {"coordinates":[9.0378227234,47.452167511],"type":"Point"}
}