{
  "type": "Feature",
  "properties": {
    "iso:country":"CH",
    "sg:address":"Biela",
    "sg:city":"Termen",
    "sg:orig_category":"Maler U Glasergewerbe",
    "sg:postcode":"3912",
    "sg:province":"Valais",
    "wof:name":"Maler-blitz L\u00fcthi",
    "wof:placetype":"venue"
},
  "geometry": {"coordinates":[8.2932138443,47.4866981506],"type":"Point"}
}