{
  "type": "Feature",
  "properties": {
    "iso:country":"CH",
    "sg:address":"Rue Du Seyon 17",
    "sg:city":"Neuch\u00e2tel",
    "sg:orig_category":"Personal U Stellenvermittlung Unternehmensberatung",
    "sg:phone":"+41 32 725 17 27",
    "sg:postcode":"2000",
    "sg:province":"Neuch\u00e2tel",
    "wof:name":"Adolac Consultants S\u00e0rl",
    "wof:placetype":"venue"
},
  "geometry": {"coordinates":[6.9280581474,46.9928359985],"type":"Point"}
}