{
  "type": "Feature",
  "properties": {
    "iso:country":"CH",
    "sg:address":"Oberdorfweg 12",
    "sg:city":"Herzogenbuchsee",
    "sg:orig_category":"Sportvereine Hornussen",
    "sg:phone":"+41 79 330 40 28",
    "sg:postcode":"3360",
    "sg:province":"Bern",
    "wof:name":"Hornussergesellschaft",
    "wof:placetype":"venue"
},
  "geometry": {"coordinates":[7.7118349075,47.1872406006],"type":"Point"}
}