{
  "type": "Feature",
  "properties": {
    "iso:country":"CH",
    "sg:address":"Rue Du Conseil-g\u00e9n\u00e9ral 35",
    "sg:city":"Gen\u00e8ve",
    "sg:classifiers":[
        {
            "category":"Restaurant",
            "type":"Food & Drink"
        }
    ],
    "sg:phone":"+41 22 366 15 76",
    "sg:postcode":"1205",
    "sg:province":"Gen\u00e8ve",
    "wof:name":"Caf\u00e9-restaurant Tivoli",
    "wof:placetype":"venue"
},
  "geometry": {"coordinates":[6.2182898521,46.4542808533],"type":"Point"}
}