{
  "type": "Feature",
  "properties": {
    "iso:country":"CH",
    "sg:address":"Burehof",
    "sg:city":"Hildisrieden",
    "sg:orig_category":"Herstellung von Mess U Kontrollinstrumenten U vorrichtungen",
    "sg:phone":"+41 41 460 13 75",
    "sg:postcode":"6024",
    "sg:province":"Luzern",
    "wof:name":"Br\u00fcckenwage-genossenschaft Hildisrieden",
    "wof:placetype":"venue"
},
  "geometry": {"coordinates":[8.2291088104,47.1507263184],"type":"Point"}
}