{
  "type": "Feature",
  "properties": {
    "iso:country":"CH",
    "sg:address":"St. Leonhardstrasse 35",
    "sg:city":"St.gallen",
    "sg:orig_category":"Unclassifiable Establishments",
    "sg:postcode":"9000",
    "sg:province":"St. Gallen",
    "wof:name":"Beck Destille Gmbh",
    "wof:placetype":"venue"
},
  "geometry": {"coordinates":[9.3705272675,47.4222297668],"type":"Point"}
}