{
  "type": "Feature",
  "properties": {
    "iso:country":"CH",
    "sg:address":"Weidenweg 16 4310 Rheinfelden. Postfach",
    "sg:city":"Rheinfelden",
    "sg:orig_category":"D\u00e4mmung gegen K\u00e4lte, W\u00e4rme, Schall U Ersch\u00fctterung",
    "sg:phone":"+41 61 692 48 30",
    "sg:postcode":"4310",
    "sg:province":"Aargau",
    "wof:name":"Novisol Ag",
    "wof:placetype":"venue"
},
  "geometry": {"coordinates":[7.773911953,47.5496253967],"type":"Point"}
}