{
  "type": "Feature",
  "properties": {
    "iso:country":"CH",
    "sg:address":"Zentweg 17",
    "sg:city":"Bern",
    "sg:orig_category":"Betrieb U technische Hilfsdienste des Kultur U Unterhaltungswesens",
    "sg:phone":"+41 31 370 02 00",
    "sg:postcode":"3006",
    "sg:province":"Bern",
    "wof:name":"Eventicum Ag",
    "wof:placetype":"venue"
},
  "geometry": {"coordinates":[7.474219799,46.9566879272],"type":"Point"}
}