{
  "type": "Feature",
  "properties": {
    "iso:country":"CH",
    "sg:address":"Feldstrasse 53",
    "sg:city":"G\u00fcmligen",
    "sg:orig_category":"G\u00fcterbef\u00f6rderung im Strassenverkehr R\u00fcckgewinnung U Vorbereitung f\u00fcr die Wiederverwertung Recycling",
    "sg:phone":"+41 31 951 00 14",
    "sg:postcode":"3073",
    "sg:province":"Bern",
    "wof:name":"E. Bigler Transporte Ag Abfallentsorgung",
    "wof:placetype":"venue"
},
  "geometry": {"coordinates":[7.5097999573,46.9279518127],"type":"Point"}
}