{
  "type": "Feature",
  "properties": {
    "iso:country":"CH",
    "sg:address":"Saum 30",
    "sg:city":"Herisau",
    "sg:orig_category":"G\u00fcterbef\u00f6rderung im Strassenverkehr",
    "sg:postcode":"9100",
    "sg:province":"Appenzell Ausserrhoden",
    "wof:name":"Lanker R. Transporte",
    "wof:placetype":"venue"
},
  "geometry": {"coordinates":[9.3093795776,47.3874893188],"type":"Point"}
}