{
  "type": "Feature",
  "properties": {
    "iso:country":"CH",
    "sg:address":"Vignalunga Via 11",
    "sg:city":"Mendrisio",
    "sg:orig_category":"Instandhaltung U Reparatur von Automobilen",
    "sg:phone":"+41 91 682 01 22",
    "sg:postcode":"6850",
    "sg:province":"Ticino",
    "wof:name":"Pasta Tiziano Automobili Sa",
    "wof:placetype":"venue"
},
  "geometry": {"coordinates":[8.983584404,45.8786354065],"type":"Point"}
}