{
  "type": "Feature",
  "properties": {
    "addr:full":"Seeweg A 199 Berlingen Thurgau 8267",
    "addr:housenumber":"199",
    "addr:postcode":"8267",
    "addr:street":"Seeweg A",
    "iso:country":"CH",
    "sg:address":"Seeweg A 199",
    "sg:city":"Berlingen",
    "sg:orig_category":"Architektur U Ingenieurb\u00fcros",
    "sg:postcode":"8267",
    "sg:province":"Thurgau",
    "wof:name":"Sur Culm Ag Management Und Generalunternehmung",
    "wof:placetype":"venue"
},
  "geometry": {"coordinates":[9.285231,46.836693],"type":"Point"}
}