{
  "type": "Feature",
  "properties": {
    "iso:country":"CH",
    "sg:address":"Dorfstrasse 5 5617 Tennwil. Postfach",
    "sg:city":"Tennwil",
    "sg:orig_category":"Kauf U Verkauf von Immobilien auf eigene Rechnung",
    "sg:postcode":"5617",
    "sg:province":"Aargau",
    "wof:name":"Rebe Immoblilien Ag",
    "wof:placetype":"venue"
},
  "geometry": {"coordinates":[8.2214603424,47.3059997559],"type":"Point"}
}