{
  "type": "Feature",
  "properties": {
    "iso:country":"CH",
    "sg:address":"Riva Vela 7",
    "sg:city":"Lugano",
    "sg:orig_category":"RESTAURANTS: TEA-ROOMS",
    "sg:phone":"+41 91 922 09 58",
    "sg:postcode":"6900",
    "sg:province":"Ticino",
    "wof:name":"Rest. Scala Sa",
    "wof:placetype":"venue"
},
  "geometry": {"coordinates":[8.949511528,46.000579834],"type":"Point"}
}