{
  "type": "Feature",
  "properties": {
    "iso:country":"CH",
    "sg:address":"Buonaserstr. 30",
    "sg:city":"Rotkreuz",
    "sg:classifiers":[
        {
            "category":"Shopping",
            "type":"Retail Goods"
        }
    ],
    "sg:phone":"+41 41 799 52 22",
    "sg:postcode":"6343",
    "sg:province":"Zug",
    "sg:tags":[
        "metallurgy",
        "finished",
        "-",
        "metalworking",
        "metallic"
    ],
    "wof:name":"Amc International Alfa Metalcraft Corp Ag",
    "wof:placetype":"venue"
},
  "geometry": {"coordinates":[8.4371337891,47.140586853],"type":"Point"}
}