{
  "type": "Feature",
  "properties": {
    "iso:country":"CH",
    "sg:address":"Emil Angst-strasse 29",
    "sg:city":"Basel",
    "sg:orig_category":"Malerei Tapeziererei",
    "sg:phone":"+41 79 322 51 70",
    "sg:postcode":"4059",
    "sg:province":"Basel-Stadt",
    "wof:name":"Niklaus Leuenberger Maler-& Tapezierergesch\u00e4ft",
    "wof:placetype":"venue"
},
  "geometry": {"coordinates":[7.6029958725,47.5315208435],"type":"Point"}
}