{
  "type": "Feature",
  "properties": {
    "iso:country":"CH",
    "sg:address":"W\u00fchrestrasse 63",
    "sg:city":"Uster",
    "sg:orig_category":"Unclassifiable Establishments",
    "sg:postcode":"8610",
    "sg:province":"Z\u00fcrich",
    "wof:name":"Wolf Beratungen",
    "wof:placetype":"venue"
},
  "geometry": {"coordinates":[8.7176599503,47.3409538269],"type":"Point"}
}