{
  "type": "Feature",
  "properties": {
    "iso:country":"CH",
    "sg:address":"Bahnhofstrasse 26",
    "sg:city":"Wollerau",
    "sg:orig_category":"Physiotherapie",
    "sg:phone":"+41 17861878",
    "sg:postcode":"8832",
    "sg:province":"Schwyz",
    "wof:name":"Nelly M.j. Kiljan Physiotherapie",
    "wof:placetype":"venue"
},
  "geometry": {"coordinates":[8.72453022,47.195350647],"type":"Point"}
}