{
  "type": "Feature",
  "properties": {
    "iso:country":"CH",
    "sg:address":"Hauptstrasse 11 3186 D\u00fcdingen. Postfach 25",
    "sg:city":"D\u00fcdingen",
    "sg:orig_category":"Versicherungen Generalagenturen",
    "sg:phone":"+41 26 492 92 11",
    "sg:postcode":"3186",
    "sg:province":"Fribourg",
    "wof:name":"Basler Versicherungen Generalagentur",
    "wof:placetype":"venue"
},
  "geometry": {"coordinates":[7.190841198,46.8473815918],"type":"Point"}
}