{
  "type": "Feature",
  "properties": {
    "iso:country":"CH",
    "sg:address":"Blumenweg 3",
    "sg:city":"Lyss",
    "sg:orig_category":"Handelsvermittlung U Grosshandel Sonstiger Grosshandel",
    "sg:phone":"+41 81 858 72 58",
    "sg:postcode":"3250",
    "sg:province":"Bern",
    "wof:name":"Quadras Ag",
    "wof:placetype":"venue"
},
  "geometry": {"coordinates":[10.4256095886,46.6001701355],"type":"Point"}
}