{
  "type": "Feature",
  "properties": {
    "iso:country":"CH",
    "sg:address":"Lindhubelweg 17",
    "sg:city":"Balsthal",
    "sg:orig_category":"Detailhandel mit Spielwaren",
    "sg:phone":"+41 62 391 47 49",
    "sg:postcode":"4710",
    "sg:province":"Solothurn",
    "wof:name":"Heuja Spielwaren-& Modellbaufachgesch\u00e4ft",
    "wof:placetype":"venue"
},
  "geometry": {"coordinates":[7.6986498833,47.3204727173],"type":"Point"}
}