{
  "type": "Feature",
  "properties": {
    "iso:country":"CH",
    "sg:address":"Altmannsteinstrasse 30 8181 H\u00f6ri. Postfach",
    "sg:city":"H\u00f6ri",
    "sg:orig_category":"Non-Classified Establishments",
    "sg:postcode":"8181",
    "sg:province":"Z\u00fcrich",
    "wof:name":"Polyusus Ag Beteiligungen Usw",
    "wof:placetype":"venue"
},
  "geometry": {"coordinates":[8.5423326492,47.3800926208],"type":"Point"}
}