{
  "type": "Feature",
  "properties": {
    "iso:country":"CH",
    "sg:address":"Terbinerstrasse 2",
    "sg:city":"Visp",
    "sg:orig_category":"Pensionskassen",
    "sg:phone":"+41 27 948 30 30",
    "sg:postcode":"3930",
    "sg:province":"Valais",
    "wof:name":"Personalf\u00fcrsorgestiftung Valgraph",
    "wof:placetype":"venue"
},
  "geometry": {"coordinates":[7.883245945,46.2934761047],"type":"Point"}
}