{
  "type": "Feature",
  "properties": {
    "addr:full":"L\u00e4rchenhof Appenzell Appenzell Innerhoden 9050",
    "addr:postcode":"9050",
    "addr:street":"Laerchenhof",
    "iso:country":"CH",
    "sg:address":"L\u00e4rchenhof",
    "sg:city":"Appenzell",
    "sg:orig_category":"Allgemeiner Hoch U Tiefbau",
    "sg:postcode":"9050",
    "sg:province":"Appenzell Innerhoden",
    "wof:name":"Rechsteiner Rolf Baugesch\u00e4ft Ag",
    "wof:placetype":"venue"
},
  "geometry": {"coordinates":[9.407683,47.331436],"type":"Point"}
}