{
  "type": "Feature",
  "properties": {
    "addr:full":"Rue Des Poteaux 3 Neuch\u00e2tel Neuch\u00e2tel 2000",
    "addr:housenumber":"3",
    "addr:postcode":"2000",
    "addr:street":"Rue Des Poteaux",
    "iso:country":"CH",
    "sg:address":"Rue Des Poteaux 3",
    "sg:city":"Neuch\u00e2tel",
    "sg:orig_category":"Detailhandel mit Damenbekleidung",
    "sg:phone":"+41 32 725 22 50",
    "sg:postcode":"2000",
    "sg:province":"Neuch\u00e2tel",
    "wof:name":"Fogal Sa Mode Pour La Jambe",
    "wof:placetype":"venue"
},
  "geometry": {"coordinates":[6.929839,46.991638],"type":"Point"}
}