{
  "type": "Feature",
  "properties": {
    "addr:full":"Greyerzstrasse 57 Bern Bern 3013",
    "addr:housenumber":"57",
    "addr:postcode":"3013",
    "addr:street":"Greyerzstrasse",
    "iso:country":"CH",
    "sg:address":"Greyerzstrasse 57",
    "sg:city":"Bern",
    "sg:orig_category":"Architektur U Ingenieurb\u00fcros",
    "sg:phone":"+41 31 333 03 60",
    "sg:postcode":"3013",
    "sg:province":"Bern",
    "wof:name":"Ott Christoph Ag, Architektur Und Innenarchitektur",
    "wof:placetype":"venue"
},
  "geometry": {"coordinates":[7.44936,46.956848],"type":"Point"}
}