{
  "type": "Feature",
  "properties": {
    "iso:country":"CH",
    "sg:address":"R\u00f6merstrasse 24 5400 Baden. Postfach",
    "sg:city":"Baden",
    "sg:classifiers":[
        {
            "category":"Travel",
            "subcategory":"Hotels & Motels",
            "type":"Entertainment"
        }
    ],
    "sg:phone":"+41 56 203 15 15",
    "sg:postcode":"5401",
    "sg:province":"Aargau",
    "sg:tags":[
        "hotels",
        "mit",
        "restaurant"
    ],
    "wof:name":"Hotel Du Parc",
    "wof:placetype":"venue"
},
  "geometry": {"coordinates":[8.3084459305,47.4810333252],"type":"Point"}
}