{
  "type": "Feature",
  "properties": {
    "iso:country":"CH",
    "sg:address":"Baumgartenstrasse 15",
    "sg:city":"Schaffhausen",
    "sg:orig_category":"Unclassifiable Establishments",
    "sg:phone":"+41 52 635 65 65",
    "sg:postcode":"8202",
    "sg:province":"Schaffhausen",
    "wof:name":"Lmh Les Manufactures Horlog\u00e8res Sa",
    "wof:placetype":"venue"
},
  "geometry": {"coordinates":[8.6368761063,47.6945114136],"type":"Point"}
}