{
  "type": "Feature",
  "properties": {
    "iso:country":"CH",
    "sg:address":"L\u00f6wenstrasse 16",
    "sg:city":"Kreuzlingen",
    "sg:orig_category":"Detailhandel mit Bekleidung Detailhandel mit Damenbekleidung",
    "sg:phone":"+41 71 672 88 82",
    "sg:postcode":"8280",
    "sg:province":"Thurgau",
    "wof:name":"La Copine Ag",
    "wof:placetype":"venue"
},
  "geometry": {"coordinates":[9.17179,47.647884],"type":"Point"}
}