{
  "type": "Feature",
  "properties": {
    "iso:country":"CH",
    "sg:address":"Conseil-g\u00e9n\u00e9ral Rue Du 20 1205 Gen\u00e8ve. Postfach",
    "sg:city":"Gen\u00e8ve",
    "sg:orig_category":"Finanzierungsinstitutionen",
    "sg:postcode":"1205",
    "sg:province":"Gen\u00e8ve",
    "wof:name":"Ferret Finance Ag Finanzdienstleistungen Usw",
    "wof:placetype":"venue"
},
  "geometry": {"coordinates":[8.5976400375,47.3148918152],"type":"Point"}
}