{
  "type": "Feature",
  "properties": {
    "addr:full":"Route De Lausanne 12 Cully Vaud 1096",
    "addr:housenumber":"12",
    "addr:postcode":"1096",
    "addr:street":"Route De Lausanne",
    "iso:country":"CH",
    "sg:address":"Route De Lausanne 12",
    "sg:city":"Cully",
    "sg:orig_category":"Arztpraxen",
    "sg:phone":"+41 21 799 28 28",
    "sg:postcode":"1096",
    "sg:province":"Vaud",
    "wof:name":"Dr M\u00e9d. Angela Cottier M\u00e9decin G\u00e9n\u00e9raliste Fmh",
    "wof:placetype":"venue"
},
  "geometry": {"coordinates":[6.727169,46.48753],"type":"Point"}
}