{
  "type": "Feature",
  "properties": {
    "iso:country":"CH",
    "sg:address":"Burggrabenstrasse 12",
    "sg:city":"Kreuzlingen",
    "sg:orig_category":"Sonstiger Grosshandel",
    "sg:phone":"+41 55 460 18 70",
    "sg:postcode":"8280",
    "sg:province":"Thurgau",
    "wof:name":"Schnapp-food Ag",
    "wof:placetype":"venue"
},
  "geometry": {"coordinates":[8.8634643555,47.193195343],"type":"Point"}
}