{
  "type": "Feature",
  "properties": {
    "iso:country":"CH",
    "sg:address":"Bergli 14",
    "sg:city":"Fr\u00e4schels",
    "sg:orig_category":"Gem\u00fcsebau",
    "sg:phone":"+41 31 755 54 40",
    "sg:postcode":"3284",
    "sg:province":"Fribourg",
    "wof:name":"Walter M\u00fchlemann Gem\u00fcsebau",
    "wof:placetype":"venue"
},
  "geometry": {"coordinates":[7.2098488808,46.9971656799],"type":"Point"}
}