{
  "type": "Feature",
  "properties": {
    "iso:country":"CH",
    "sg:address":"Rue Du Simplon 90",
    "sg:city":"Martigny",
    "sg:orig_category":"G\u00fcterbef\u00f6rderung im Strassenverkehr",
    "sg:phone":"+41 27 723 56 10",
    "sg:postcode":"1920",
    "sg:province":"Valais",
    "wof:name":"Swiss Car Barras Sa",
    "wof:placetype":"venue"
},
  "geometry": {"coordinates":[7.084458828,46.1057510376],"type":"Point"}
}