{
  "type": "Feature",
  "properties": {
    "iso:country":"CH",
    "sg:address":"Notre-dame Place De 4",
    "sg:city":"Fribourg",
    "sg:orig_category":"Non-Classified Establishments",
    "sg:postcode":"1700",
    "sg:province":"Fribourg",
    "wof:name":"Adoc Nettoyage Et Entretien S\u00e0rl",
    "wof:placetype":"venue"
},
  "geometry": {"coordinates":[7.0661759377,47.0576019287],"type":"Point"}
}