{
  "type": "Feature",
  "properties": {
    "iso:country":"CH",
    "sg:address":"Camp Dca 1666 Grandvillard. Postfach",
    "sg:city":"Grandvillard",
    "sg:orig_category":"RESTAURANTS: TEA-ROOMS",
    "sg:postcode":"1666",
    "sg:province":"Fribourg",
    "wof:name":"Bochud Monique",
    "wof:placetype":"venue"
},
  "geometry": {"coordinates":[7.0855789185,46.5394859314],"type":"Point"}
}