{
  "type": "Feature",
  "properties": {
    "addr:full":"Lyss-strasse 6a Kappelen Bern 3273",
    "addr:housenumber":"6a",
    "addr:postcode":"3273",
    "addr:street":"Lyss-Strasse",
    "iso:country":"CH",
    "sg:address":"Lyss-strasse 6a",
    "sg:city":"Kappelen",
    "sg:orig_category":"Abwasserreinigung",
    "sg:phone":"+41 32 392 31 63",
    "sg:postcode":"3273",
    "sg:province":"Bern",
    "wof:name":"Abwasserpumpwerk Kappelen",
    "wof:placetype":"venue"
},
  "geometry": {"coordinates":[7.274349,47.061043],"type":"Point"}
}