{
  "type": "Feature",
  "properties": {
    "iso:country":"CH",
    "sg:address":"Bruggacherstrasse 26 8117 F\u00e4llanden. Postfach 185",
    "sg:city":"F\u00e4llanden",
    "sg:orig_category":"Ausstellungs U Messeorganisation",
    "sg:phone":"+41 17518080",
    "sg:postcode":"8117",
    "sg:province":"Z\u00fcrich",
    "wof:name":"Pape Andreas, Werbeatelier",
    "wof:placetype":"venue"
},
  "geometry": {"coordinates":[8.440954,47.415848],"type":"Point"}
}