{
  "type": "Feature",
  "properties": {
    "iso:country":"CH",
    "sg:address":"Chemin Des Coquilles 56 1630 Bulle. Postfach",
    "sg:city":"Bulle",
    "sg:orig_category":"Sonstiger spezialisierter Hoch U Tiefbau",
    "sg:postcode":"1630",
    "sg:province":"Fribourg",
    "wof:name":"Brodard Gilbert Et Fils Sa",
    "wof:placetype":"venue"
},
  "geometry": {"coordinates":[7.0574998856,46.6305389404],"type":"Point"}
}