{
  "type": "Feature",
  "properties": {
    "iso:country":"CH",
    "sg:address":"Genferstrasse 35",
    "sg:city":"Z\u00fcrich",
    "sg:classifiers":[
        {
            "category":"Ice Cream",
            "type":"Food & Drink"
        }
    ],
    "sg:phone":"+41 12839393",
    "sg:postcode":"8002",
    "sg:province":"Z\u00fcrich",
    "sg:tags":[
        "barrier"
    ],
    "wof:name":"Est\u00e9e Lauder Gmbh",
    "wof:placetype":"venue"
},
  "geometry": {"coordinates":[8.533134,47.366249],"type":"Point"}
}