{
  "type": "Feature",
  "properties": {
    "iso:country":"CH",
    "sg:address":"Quartier De La Verrerie",
    "sg:city":"Montagne-moutier",
    "sg:orig_category":"Non-Classified Establishments",
    "sg:postcode":"2740",
    "sg:province":"Bern",
    "wof:name":"Weber F. + M.",
    "wof:placetype":"venue"
},
  "geometry": {"coordinates":[8.5081157684,47.4815979004],"type":"Point"}
}