{
  "type": "Feature",
  "properties": {
    "iso:country":"CH",
    "sg:address":"Bahnhofstrasse 24",
    "sg:city":"Wallisellen",
    "sg:orig_category":"Non-Classified Establishments",
    "sg:postcode":"8304",
    "sg:province":"Z\u00fcrich",
    "wof:name":"Wdm Verm\u00f6gensverwaltungs Gmbh",
    "wof:placetype":"venue"
},
  "geometry": {"coordinates":[8.5908870697,47.4140319824],"type":"Point"}
}