{
  "type": "Feature",
  "properties": {
    "iso:country":"CH",
    "sg:address":"Zone Industrielle La Pallaz 1530 Payerne. Postfach",
    "sg:city":"Payerne",
    "sg:orig_category":"Hardwareberatung",
    "sg:phone":"+41 19503067",
    "sg:postcode":"1530",
    "sg:province":"Vaud",
    "wof:name":"Pfister It Services Waren, Bes. Computer Usw.; Produktion, Vertrieb, Handel",
    "wof:placetype":"venue"
},
  "geometry": {"coordinates":[8.7880344391,47.3670692444],"type":"Point"}
}