{
  "type": "Feature",
  "properties": {
    "iso:country":"CH",
    "sg:address":"Unterdorfstrasse 54",
    "sg:city":"Widnau",
    "sg:orig_category":"Grafikateliers, Design",
    "sg:phone":"+41 71 722 52 58",
    "sg:postcode":"9443",
    "sg:province":"St. Gallen",
    "wof:name":"Beusch Design",
    "wof:placetype":"venue"
},
  "geometry": {"coordinates":[9.6348400116,47.4112892151],"type":"Point"}
}