{
  "type": "Feature",
  "properties": {
    "iso:country":"CH",
    "sg:address":"Via Luganetto 5",
    "sg:city":"Viganello",
    "sg:orig_category":"Finanzierungsinstitutionen",
    "sg:phone":"+41 91 973 58 11",
    "sg:postcode":"6962",
    "sg:province":"Ticino",
    "wof:name":"Enichem Finance Sa",
    "wof:placetype":"venue"
},
  "geometry": {"coordinates":[8.9607973099,46.0106582642],"type":"Point"}
}