{
  "type": "Feature",
  "properties": {
    "iso:country":"CH",
    "sg:address":"Brandschenkestrasse 20 8002 Z\u00fcrich. Postfach",
    "sg:city":"Z\u00fcrich",
    "sg:orig_category":"RESTAURANTS: TEA-ROOMS",
    "sg:phone":"+41 12801880",
    "sg:postcode":"8001",
    "sg:province":"Z\u00fcrich",
    "wof:name":"San Marco Restaurations Gmbh F\u00fchrung Von Gastst\u00e4tten. Kauf Und Verkauf Von Liegenschaften",
    "wof:placetype":"venue"
},
  "geometry": {"coordinates":[8.5326414108,47.369342804],"type":"Point"}
}