{
  "type": "Feature",
  "properties": {
    "iso:country":"CH",
    "sg:address":"Murtenstrasse 5",
    "sg:city":"Frauenkappelen",
    "sg:orig_category":"Allgemeiner Hoch U Tiefbau Zimmerei, Ingenieurholzbau",
    "sg:phone":"+41 31 926 19 73",
    "sg:postcode":"3202",
    "sg:province":"Bern",
    "wof:name":"Schibler & Haldi Bauunternehmung & Holzbau",
    "wof:placetype":"venue"
},
  "geometry": {"coordinates":[7.34699,46.95274],"type":"Point"}
}