{
  "type": "Feature",
  "properties": {
    "iso:country":"CH",
    "sg:address":"Route De Fribourg 45",
    "sg:city":"Courtepin",
    "sg:orig_category":"Handel mit Automobilen",
    "sg:phone":"+41 55 442 17 77",
    "sg:postcode":"1784",
    "sg:province":"Fribourg",
    "wof:name":"Auto Steinegger Ag",
    "wof:placetype":"venue"
},
  "geometry": {"coordinates":[8.847653389,47.1913642883],"type":"Point"}
}