{
  "type": "Feature",
  "properties": {
    "iso:country":"CH",
    "sg:address":"3803",
    "sg:city":"Beatenberg",
    "sg:orig_category":"Landwirtschaftliche Genossenschaften",
    "sg:phone":"+41 32 372 11 22",
    "sg:postcode":"3803",
    "sg:province":"Bern",
    "wof:name":"Landw.genossenschaft Br\u00fcgg-aegerten & Umgebung",
    "wof:placetype":"venue"
},
  "geometry": {"coordinates":[7.2785029411,47.1245613098],"type":"Point"}
}