{
  "type": "Feature",
  "properties": {
    "iso:country":"CH",
    "sg:address":"Rue De Varemb\u00e9 1",
    "sg:city":"Gen\u00e8ve",
    "sg:orig_category":"Miscellaneous Products",
    "sg:phone":"+41 22 749 01 11",
    "sg:postcode":"1202",
    "sg:province":"Gen\u00e8ve",
    "wof:name":"International Organization For Standardization (iso)",
    "wof:placetype":"venue"
},
  "geometry": {"coordinates":[6.1395249367,46.22108078],"type":"Point"}
}