{
  "type": "Feature",
  "properties": {
    "iso:country":"CH",
    "sg:address":"Alpenstrasse 15",
    "sg:city":"Zug",
    "sg:orig_category":"Finanzierungsinstitutionen",
    "sg:postcode":"6300",
    "sg:province":"Zug",
    "wof:name":"Weedinvest Gmbh",
    "wof:placetype":"venue"
},
  "geometry": {"coordinates":[8.5148057938,47.172958374],"type":"Point"}
}