{
  "type": "Feature",
  "properties": {
    "iso:country":"CH",
    "sg:address":"Chlosterb\u00fcel 9",
    "sg:city":"Sch\u00fcpfheim",
    "sg:orig_category":"Institutionen f\u00fcr Behinderte Sonderschulen",
    "sg:phone":"+41 41 874 13 40",
    "sg:postcode":"6170",
    "sg:province":"Luzern",
    "wof:name":"Heilp\u00e4dagogisches Zentrum Uri Sonderschule",
    "wof:placetype":"venue"
},
  "geometry": {"coordinates":[8.6442451477,46.8782920837],"type":"Point"}
}