{
  "type": "Feature",
  "properties": {
    "iso:country":"CH",
    "sg:address":"Bernstrasse 18 3110 M\u00fcnsingen. Postfach 1357",
    "sg:city":"M\u00fcnsingen",
    "sg:orig_category":"Grosshandel mit Textilien",
    "sg:phone":"+41 31 721 10 27",
    "sg:postcode":"3110",
    "sg:province":"Bern",
    "wof:name":"Mode Dubach",
    "wof:placetype":"venue"
},
  "geometry": {"coordinates":[7.5617341995,46.8779029846],"type":"Point"}
}