{
  "type": "Feature",
  "properties": {
    "iso:country":"CH",
    "sg:address":"Hauptstrasse 48",
    "sg:city":"Gurmels",
    "sg:orig_category":"Detailhandel mit M\u00f6beln U Haushaltsgegenst\u00e4nden Herstellung von Reiseartikeln, Leder U Sattlerwaren",
    "sg:phone":"+41 55 282 11 51",
    "sg:postcode":"3212",
    "sg:province":"Fribourg",
    "wof:name":"M\u00f6bel R\u00fcegg + Co",
    "wof:placetype":"venue"
},
  "geometry": {"coordinates":[8.921087265,47.2390861511],"type":"Point"}
}