{
  "type": "Feature",
  "properties": {
    "addr:full":"Reitgasse 5 Eriswil Bern 4952",
    "addr:housenumber":"5",
    "addr:postcode":"4952",
    "addr:street":"Reitgasse;Bern",
    "iso:country":"CH",
    "sg:address":"Reitgasse 5",
    "sg:city":"Eriswil",
    "sg:classifiers":[
        {
            "category":"Banks & Credit Unions",
            "subcategory":"Bank",
            "type":"Services"
        }
    ],
    "sg:phone":"+41 4163761192",
    "sg:postcode":"4952",
    "sg:province":"Bern",
    "wof:name":"Amtsersparniskasse Sumiswald",
    "wof:placetype":"venue"
},
  "geometry": {"coordinates":[7.850233,47.07785],"type":"Point"}
}