{
  "type": "Feature",
  "properties": {
    "iso:country":"CH",
    "sg:address":"Collombey-le-grand",
    "sg:city":"Collombey",
    "sg:orig_category":"Instandhaltung U Reparatur von Automobilen",
    "sg:postcode":"1868",
    "sg:province":"Valais",
    "wof:name":"Roulin Guy",
    "wof:placetype":"venue"
},
  "geometry": {"coordinates":[6.9480900764,46.2801589966],"type":"Point"}
}