{
  "type": "Feature",
  "properties": {
    "iso:country":"CH",
    "sg:address":"Mittlere Strasse 4",
    "sg:city":"Basel",
    "sg:orig_category":"Detailhandel mit Musikinstrumenten",
    "sg:phone":"+41 81 833 86 88",
    "sg:postcode":"4056",
    "sg:province":"Basel-Stadt",
    "wof:name":"Emanuele Lardi Musica Musikhaus",
    "wof:placetype":"venue"
},
  "geometry": {"coordinates":[9.8376636505,46.4874954224],"type":"Point"}
}