{
  "type": "Feature",
  "properties": {
    "iso:country":"CH",
    "sg:address":"Via San Salvatore 4",
    "sg:city":"Paradiso",
    "sg:orig_category":"Tierkliniken",
    "sg:phone":"+41 91 994 83 32",
    "sg:postcode":"6900",
    "sg:province":"Ticino",
    "wof:name":"Dottori Med.vet.w.& M. Rohr Clinica Veterinaria Gst",
    "wof:placetype":"venue"
},
  "geometry": {"coordinates":[8.9449996948,45.9922332764],"type":"Point"}
}