{
  "type": "Feature",
  "properties": {
    "iso:country":"CH",
    "sg:address":"Avenue Mon-repos 14",
    "sg:city":"Lausanne",
    "sg:orig_category":"Wirtschaftspr\u00fcfung, Steuerberatung U Treuhand",
    "sg:postcode":"1005",
    "sg:province":"Vaud",
    "wof:name":"Bfi Bureau Fiduciaire Informatique Quartier",
    "wof:placetype":"venue"
},
  "geometry": {"coordinates":[6.8300170898,47.102558136],"type":"Point"}
}