{
  "type": "Feature",
  "properties": {
    "addr:full":"Place Benjamin-constant 2 1003 Lausanne Case Postale 3673 Lausanne Vaud 1002",
    "addr:housenumber":"2",
    "addr:postcode":"1003;3673;1002",
    "addr:street":"Place Benjamin-Constant;Postale",
    "iso:country":"CH",
    "sg:address":"Place Benjamin-constant 2 1003 Lausanne Case Postale 3673",
    "sg:city":"Lausanne",
    "sg:orig_category":"Advokaturb\u00fcros",
    "sg:phone":"+41 21 312 78 54",
    "sg:postcode":"1002",
    "sg:province":"Vaud",
    "wof:name":"Chaudet Bovay Wyler Mustaki Etude D'avocat",
    "wof:placetype":"venue"
},
  "geometry": {"coordinates":[6.637338,46.519211],"type":"Point"}
}