{
  "type": "Feature",
  "properties": {
    "iso:country":"CH",
    "sg:address":"Hauptstrasse 129a",
    "sg:city":"Orpund",
    "sg:orig_category":"Detailhandel mit Schreib U Papeteriewaren Detailhandel mit Zeitungen U Zeitschriften Kioske",
    "sg:phone":"+41 32 355 11 57",
    "sg:postcode":"2552",
    "sg:province":"Bern",
    "wof:name":"Anna-rosa Werro Kiosk & Papeterie",
    "wof:placetype":"venue"
},
  "geometry": {"coordinates":[7.2998781204,47.1410484314],"type":"Point"}
}