{
  "type": "Feature",
  "properties": {
    "iso:country":"CH",
    "sg:address":"R. Village 26 1617 Remaufens. Postfach",
    "sg:city":"Remaufens",
    "sg:orig_category":"Herstellung von Heizk\u00f6rpern U kesseln f\u00fcr die Zentralheizung",
    "sg:postcode":"1617",
    "sg:province":"Fribourg",
    "wof:name":"Monney P. Chaudi\u00e8res \u00e0 Bois-conseils",
    "wof:placetype":"venue"
},
  "geometry": {"coordinates":[6.8790798187,46.5292396545],"type":"Point"}
}