{
  "type": "Feature",
  "properties": {
    "iso:country":"CH",
    "sg:address":"Vieux-coll\u00e8ge Rue Du 8 1204 Gen\u00e8ve. Postfach",
    "sg:city":"Genf",
    "sg:orig_category":"Unclassifiable Establishments",
    "sg:postcode":"1200",
    "sg:province":"Gen\u00e8ve",
    "wof:name":"Si Versoix-la-scie",
    "wof:placetype":"venue"
},
  "geometry": {"coordinates":[6.1509590149,46.2015304565],"type":"Point"}
}