{
  "type": "Feature",
  "properties": {
    "iso:country":"CH",
    "sg:address":"B\u00f6hnirainstrasse 16",
    "sg:city":"Thalwil",
    "sg:orig_category":"Vermietung U Verpachtung von eigenen Immobilien Vermittlung von Immobilien",
    "sg:phone":"+41 55 451 54 60",
    "sg:postcode":"8800",
    "sg:province":"Z\u00fcrich",
    "wof:name":"Obersee Immobilien Gmbh",
    "wof:placetype":"venue"
},
  "geometry": {"coordinates":[8.8529558182,47.1920051575],"type":"Point"}
}