{
  "type": "Feature",
  "properties": {
    "addr:full":"Avenue Beauregard 32 Fribourg Fribourg 1700",
    "addr:housenumber":"32",
    "addr:postcode":"1700",
    "addr:street":"Avenue Beauregard",
    "iso:country":"CH",
    "sg:address":"Avenue Beauregard 32",
    "sg:city":"Fribourg",
    "sg:orig_category":"Detailhandel mit Blumen U Pflanzen Fachdetailhandel in Verkaufsr\u00e4umen",
    "sg:phone":"+41 26 323 36 36",
    "sg:postcode":"1700",
    "sg:province":"Fribourg",
    "wof:name":"Fleurs En Folie C. Roubaty Magasin De Fleurs",
    "wof:placetype":"venue"
},
  "geometry": {"coordinates":[7.145651,46.801979],"type":"Point"}
}