{
  "type": "Feature",
  "properties": {
    "iso:country":"CH",
    "sg:address":"Chemin De La Grangette 38",
    "sg:city":"Lausanne",
    "sg:orig_category":"Berufsberatungen",
    "sg:phone":"+41 21 652 61 08",
    "sg:postcode":"1010",
    "sg:province":"Vaud",
    "wof:name":"Ginette Favre Orientation Professionnelle",
    "wof:placetype":"venue"
},
  "geometry": {"coordinates":[6.657498,46.533955],"type":"Point"}
}