{
  "type": "Feature",
  "properties": {
    "iso:country":"CH",
    "sg:address":"Gotthardstrasse 52 6415 Arth. Postfach",
    "sg:city":"Arth",
    "sg:orig_category":"Unclassifiable Establishments",
    "sg:postcode":"6415",
    "sg:province":"Schwyz",
    "wof:name":"Schweizerischer Staffordshire Bull Terrier Club (ssbtc)",
    "wof:placetype":"venue"
},
  "geometry": {"coordinates":[8.5262002945,47.0610122681],"type":"Point"}
}