{
  "type": "Feature",
  "properties": {
    "iso:country":"CH",
    "sg:address":"Kalchb\u00fchlstrasse 18",
    "sg:city":"Chur",
    "sg:orig_category":"Erbringung von Dienstleistungen f\u00fcr Unternehmen",
    "sg:phone":"+41 61 713 04 30",
    "sg:postcode":"7000",
    "sg:province":"Graubunden",
    "wof:name":"Ruppeiner-spaar Carol Cdesign",
    "wof:placetype":"venue"
},
  "geometry": {"coordinates":[7.5905518532,47.4872093201],"type":"Point"}
}