{
  "type": "Feature",
  "properties": {
    "iso:country":"CH",
    "sg:address":"Route Heitera 2",
    "sg:city":"Fribourg",
    "sg:orig_category":"P\u00e9dicure",
    "sg:phone":"+41 81 921 48 58",
    "sg:postcode":"1700",
    "sg:province":"Fribourg",
    "wof:name":"Jacqueline Moser Kosmetik & P\u00e9dicure",
    "wof:placetype":"venue"
},
  "geometry": {"coordinates":[9.2883176804,46.8262405396],"type":"Point"}
}