{
  "type": "Feature",
  "properties": {
    "iso:country":"CH",
    "sg:address":"Kilchbergsteig 4",
    "sg:city":"Z\u00fcrich",
    "sg:orig_category":"Herstellung von keramischen Haushaltswaren U Ziergegenst\u00e4nden",
    "sg:phone":"+41 14810810",
    "sg:postcode":"8038",
    "sg:province":"Z\u00fcrich",
    "wof:name":"Ars Et Terra Sonja Tanner T\u00f6pfer-& Modellieratelier",
    "wof:placetype":"venue"
},
  "geometry": {"coordinates":[8.5329284668,47.3432426453],"type":"Point"}
}