{
  "type": "Feature",
  "properties": {
    "addr:full":"Piazza Grande 83 Giubiasco Ticino 6512",
    "addr:housenumber":"83",
    "addr:postcode":"6512",
    "addr:street":"Piazza Grande",
    "iso:country":"CH",
    "sg:address":"Piazza Grande 83",
    "sg:city":"Giubiasco",
    "sg:classifiers":[
        {
            "category":"Banks & Credit Unions",
            "subcategory":"Bank",
            "type":"Services"
        }
    ],
    "sg:phone":"+41 4192275201",
    "sg:postcode":"6512",
    "sg:province":"Ticino",
    "wof:name":"Unione Di Banche Svizzere",
    "wof:placetype":"venue"
},
  "geometry": {"coordinates":[9.01112,46.172729],"type":"Point"}
}