{
  "type": "Feature",
  "properties": {
    "iso:country":"CH",
    "sg:address":"B\u00fctzbergstrasse 10",
    "sg:city":"Aarwangen",
    "sg:orig_category":"Mechanik",
    "sg:postcode":"4912",
    "sg:province":"Bern",
    "wof:name":"Egloff Ren\u00e9",
    "wof:placetype":"venue"
},
  "geometry": {"coordinates":[8.676779747,47.782459259],"type":"Point"}
}