{
  "type": "Feature",
  "properties": {
    "iso:country":"CH",
    "sg:address":"Parkstrasse 1",
    "sg:city":"Wallisellen",
    "sg:orig_category":"Sonstige mit der Informatik verbundene T\u00e4tigkeiten",
    "sg:postcode":"8304",
    "sg:province":"Z\u00fcrich",
    "wof:name":"Edv-service Fischer",
    "wof:placetype":"venue"
},
  "geometry": {"coordinates":[8.589050293,47.4166679382],"type":"Point"}
}