{
  "type": "Feature",
  "properties": {
    "iso:country":"CH",
    "sg:address":"Romanshornerstrasse 90",
    "sg:city":"Arbon",
    "sg:orig_category":"Fachdetailhandel in Verkaufsr\u00e4umen",
    "sg:phone":"+41 33 336 26 16",
    "sg:postcode":"9320",
    "sg:province":"Thurgau",
    "wof:name":"Sailing West, Sterchi Sterchi.",
    "wof:placetype":"venue"
},
  "geometry": {"coordinates":[7.6283330917,46.7315483093],"type":"Point"}
}