{
  "type": "Feature",
  "properties": {
    "iso:country":"CH",
    "sg:address":"Dorfstrasse 23",
    "sg:city":"Hirzel",
    "sg:orig_category":"Detailhandel mit Geschenkartikeln U Souvenirs Herstellung von keramischen Haushaltswaren U Ziergegen",
    "sg:phone":"+41 17298070",
    "sg:postcode":"8816",
    "sg:province":"Z\u00fcrich",
    "wof:name":"Atelier Keramos",
    "wof:placetype":"venue"
},
  "geometry": {"coordinates":[8.6084327698,47.2136192322],"type":"Point"}
}