{
  "type": "Feature",
  "properties": {
    "iso:country":"CH",
    "sg:address":"Neue Hard 7 8005 Z\u00fcrich. Postfach 4475",
    "sg:city":"Z\u00fcrich",
    "sg:orig_category":"Reiseb\u00fcros U Reiseveranstalter",
    "sg:phone":"+41 12774020",
    "sg:postcode":"8037",
    "sg:province":"Z\u00fcrich",
    "wof:name":"Kuoni Reisen Ag",
    "wof:placetype":"venue"
},
  "geometry": {"coordinates":[8.5204248428,47.3864784241],"type":"Point"}
}