{
  "type": "Feature",
  "properties": {
    "iso:country":"CH",
    "sg:address":"Route Des Flumeaux 1 1008 Prilly. Postfach",
    "sg:city":"Prilly",
    "sg:orig_category":"Detailhandel mit Sportartikeln",
    "sg:phone":"+41 21 624 24 70",
    "sg:postcode":"1008",
    "sg:province":"Vaud",
    "wof:name":"Roland-sports Roland Pittet & Myriam Butty",
    "wof:placetype":"venue"
},
  "geometry": {"coordinates":[6.6053237915,46.5336265564],"type":"Point"}
}