{
  "type": "Feature",
  "properties": {
    "iso:country":"CH",
    "sg:address":"Rue Du Centre 14",
    "sg:city":"St-sulpice",
    "sg:classifiers":[
        {
            "category":"Arts & Performance",
            "subcategory":"Art Gallery",
            "type":"Entertainment"
        }
    ],
    "sg:phone":"+41 21 654 27 50",
    "sg:postcode":"1025",
    "sg:province":"Vaud",
    "sg:tags":[
        "baseboard",
        "wood",
        "made"
    ],
    "wof:name":"Fabrique De Cadres Et Baguettes Sa",
    "wof:placetype":"venue"
},
  "geometry": {"coordinates":[6.633144,46.57095],"type":"Point"}
}