{
  "type": "Feature",
  "properties": {
    "iso:country":"CH",
    "sg:address":"Industriestrasse 11",
    "sg:city":"Rotkreuz",
    "sg:orig_category":"Unclassifiable Establishments",
    "sg:postcode":"6343",
    "sg:province":"Zug",
    "wof:name":"Foppa Ag Brandschutz Rauchabzugs Und L\u00fcftungssysteme",
    "wof:placetype":"venue"
},
  "geometry": {"coordinates":[9.4688100815,46.1876792908],"type":"Point"}
}