{
  "type": "Feature",
  "properties": {
    "iso:country":"CH",
    "sg:address":"L\u00e4nggasse 57 3600 Thun. Postfach 22",
    "sg:city":"Thun",
    "sg:orig_category":"Pensionskassen",
    "sg:phone":"+41 33253939",
    "sg:postcode":"3600",
    "sg:province":"Bern",
    "wof:name":"Personalf\u00fcrsorgestiftung Der Ott Verlag + Druck Ag",
    "wof:placetype":"venue"
},
  "geometry": {"coordinates":[7.6173958778,46.749835968],"type":"Point"}
}