{
  "type": "Feature",
  "properties": {
    "iso:country":"CH",
    "sg:address":"Route D'allaman",
    "sg:city":"Aubonne",
    "sg:orig_category":"Detailhandel mit Ton U Bildtr\u00e4gern Detailhandel mit elektrischen Haushalts-,Radio U Fernsehger\u00e4ten s",
    "sg:phone":"+41 21 808 58 40",
    "sg:postcode":"1170",
    "sg:province":"Vaud",
    "wof:name":"King's Brass Music, Chevailler J.-p.",
    "wof:placetype":"venue"
},
  "geometry": {"coordinates":[6.3952059746,46.4922218323],"type":"Point"}
}