{
  "type": "Feature",
  "properties": {
    "iso:country":"CH",
    "sg:address":"Eymattstrasse 9a 3027 Bern. Postfach",
    "sg:city":"Bern",
    "sg:orig_category":"Herstellung von Metallkonstruktionen Schlossereien",
    "sg:phone":"+41 71 912 20 50",
    "sg:postcode":"3018",
    "sg:province":"Bern",
    "wof:name":"Julio Rabazo Schlosserei Metallbau",
    "wof:placetype":"venue"
},
  "geometry": {"coordinates":[9.0338792801,47.460647583],"type":"Point"}
}