{
  "type": "Feature",
  "properties": {
    "iso:country":"CH",
    "sg:address":"Garbenstrasse 5",
    "sg:city":"Riehen",
    "sg:orig_category":"Unclassifiable Establishments",
    "sg:postcode":"4125",
    "sg:province":"Basel-Stadt",
    "wof:name":"Stiftung Per Aspera Ad Astra!",
    "wof:placetype":"venue"
},
  "geometry": {"coordinates":[7.6447119713,47.5770721436],"type":"Point"}
}