{
  "type": "Feature",
  "properties": {
    "iso:country":"CH",
    "sg:address":"Rue De Fontaine-andr\u00e9 3",
    "sg:city":"Neuch\u00e2tel",
    "sg:orig_category":"Allgemeiner Hoch U Tiefbau D\u00e4mmung gegen K\u00e4lte, W\u00e4rme, Schall U Ersch\u00fctterung",
    "sg:phone":"+41 21 653 58 91",
    "sg:postcode":"2000",
    "sg:province":"Neuch\u00e2tel",
    "wof:name":"Isolair",
    "wof:placetype":"venue"
},
  "geometry": {"coordinates":[6.938424,46.998955],"type":"Point"}
}