{
  "type": "Feature",
  "properties": {
    "iso:country":"CH",
    "sg:address":"Bruchons Chemin Des 9a",
    "sg:city":"Veyrier",
    "sg:orig_category":"Herstellung von Elektromotoren, Generatoren U Transformatoren",
    "sg:postcode":"1255",
    "sg:province":"Gen\u00e8ve",
    "wof:name":"N. Vuilleumer Ing\u00e9nieur-conseils Sarl",
    "wof:placetype":"venue"
},
  "geometry": {"coordinates":[6.185324192,46.1668891907],"type":"Point"}
}