{
  "type": "Feature",
  "properties": {
    "iso:country":"CH",
    "sg:address":"Centrum Au Pr\u00e4ttigauerstrasse",
    "sg:city":"Landquart",
    "sg:orig_category":"Physiotherapie",
    "sg:phone":"+41 81 322 21 04",
    "sg:postcode":"7302",
    "sg:province":"Graubunden",
    "wof:name":"Hans Rissi Physiotherapie",
    "wof:placetype":"venue"
},
  "geometry": {"coordinates":[9.5707998276,46.9684906006],"type":"Point"}
}