{
  "type": "Feature",
  "properties": {
    "iso:country":"CH",
    "sg:address":"Avenue De Marcelin 9",
    "sg:city":"Morges",
    "sg:classifiers":[
        {
            "category":"Travel",
            "subcategory":"Hotels & Motels",
            "type":"Entertainment"
        }
    ],
    "sg:phone":"+41 21 801 73 78",
    "sg:postcode":"1110",
    "sg:province":"Vaud",
    "sg:tags":[
        "hotels",
        "mit",
        "restaurant"
    ],
    "wof:name":"Coletta Serge",
    "wof:placetype":"venue"
},
  "geometry": {"coordinates":[6.4921979904,46.5134162903],"type":"Point"}
}