{
  "type": "Feature",
  "properties": {
    "iso:country":"CH",
    "sg:address":"Calas Avenue 8",
    "sg:city":"Gen\u00e8ve",
    "sg:orig_category":"Unclassifiable Establishments",
    "sg:postcode":"1206",
    "sg:province":"Gen\u00e8ve",
    "wof:name":"Fondation De Recherche Et D'aide Au Developpement Frad",
    "wof:placetype":"venue"
},
  "geometry": {"coordinates":[6.153470993,46.1894035339],"type":"Point"}
}