{
  "type": "Feature",
  "properties": {
    "addr:full":"Pflugstrasse 20 9490 Vaduz. Postfach 951 Vaduz 9490",
    "addr:housenumber":"20;951",
    "addr:postcode":"9490 vaduz.;9490",
    "addr:street":"Pflugstrasse;Postfach",
    "iso:country":"CH",
    "sg:address":"Pflugstrasse 20 9490 Vaduz. Postfach 951",
    "sg:city":"Vaduz",
    "sg:orig_category":"Advokaturb\u00fcros",
    "sg:phone":"+423 238 15 15",
    "sg:postcode":"9490",
    "wof:name":"Wolf & Hoch",
    "wof:placetype":"venue"
},
  "geometry": {"coordinates":[9.524486,47.125523],"type":"Point"}
}