{
  "type": "Feature",
  "properties": {
    "iso:country":"CH",
    "sg:address":"Rotackerstrasse 4 8304 Wallisellen. Postfach 1632",
    "sg:city":"Wallisellen",
    "sg:orig_category":"Kosmetikinstitute",
    "sg:phone":"+41 18310907",
    "sg:postcode":"8304",
    "sg:province":"Z\u00fcrich",
    "wof:name":"Viviane Berger Kosmetikinstitut",
    "wof:placetype":"venue"
},
  "geometry": {"coordinates":[8.596619606,47.4124794006],"type":"Point"}
}