{
  "type": "Feature",
  "properties": {
    "iso:country":"CH",
    "sg:address":"Rue Du Ch\u00e2teau 3",
    "sg:city":"Corsier-sur-vevey",
    "sg:orig_category":"Detailhandel mit Waren verschiedener Art, Hauptrichtung Nahrungsmittel",
    "sg:phone":"+41 21 921 18 43",
    "sg:postcode":"1804",
    "sg:province":"Vaud",
    "wof:name":"Primo Sudi Alimentation",
    "wof:placetype":"venue"
},
  "geometry": {"coordinates":[6.8430261612,46.4703140259],"type":"Point"}
}