{
  "type": "Feature",
  "properties": {
    "addr:full":"V. Ponteggia Casella Postale 67 Cadempino Ticino 6814",
    "addr:housenumber":"67",
    "addr:postcode":"6814",
    "addr:street":"Casella Postale",
    "iso:country":"CH",
    "sg:address":"V. Ponteggia Casella Postale 67",
    "sg:city":"Cadempino",
    "sg:classifiers":[
        {
            "category":"Wholesale",
            "subcategory":"Machinery & Supplies",
            "type":"Manufacturing & Wholesale Goods"
        }
    ],
    "sg:phone":"+41 91 960 71 11",
    "sg:postcode":"6814",
    "sg:province":"Ticino",
    "sg:tags":[
        "equipment",
        "equipement",
        "precision",
        "timekeeping"
    ],
    "wof:name":"R. Audemars Sa",
    "wof:placetype":"venue"
},
  "geometry": {"coordinates":[8.931515,46.045364],"type":"Point"}
}