{
  "type": "Feature",
  "properties": {
    "iso:country":"CH",
    "sg:address":"8363",
    "sg:city":"Bichelsee",
    "sg:classifiers":[
        {
            "category":"Restaurant",
            "type":"Food & Drink"
        }
    ],
    "sg:phone":"+41 71 971 17 03",
    "sg:postcode":"8363",
    "sg:province":"Thurgau",
    "wof:name":"Restaurant Steig",
    "wof:placetype":"venue"
},
  "geometry": {"coordinates":[8.9225101471,47.4480514526],"type":"Point"}
}