{
  "type": "Feature",
  "properties": {
    "iso:country":"CH",
    "sg:address":"L\u00fcssliweg 5a",
    "sg:city":"Thun",
    "sg:orig_category":"G\u00fcterbef\u00f6rderung im Strassenverkehr",
    "sg:phone":"+41 33 336 80 65",
    "sg:postcode":"3604",
    "sg:province":"Bern",
    "wof:name":"Hans Eschler Autotransporte",
    "wof:placetype":"venue"
},
  "geometry": {"coordinates":[7.6123900414,46.7381210327],"type":"Point"}
}