{
  "type": "Feature",
  "properties": {
    "iso:country":"CH",
    "sg:address":"Dorfplatz 1",
    "sg:city":"Horgen",
    "sg:orig_category":"Sonstige mit der Informatik verbundene T\u00e4tigkeiten",
    "sg:phone":"+41 17259505",
    "sg:postcode":"8810",
    "sg:province":"Z\u00fcrich",
    "wof:name":"Edv-verbund Rb Z\u00fcrichsee",
    "wof:placetype":"venue"
},
  "geometry": {"coordinates":[8.5975809097,47.2598724365],"type":"Point"}
}