{
  "type": "Feature",
  "properties": {
    "iso:country":"CH",
    "sg:address":"Avenue De La Gare 11",
    "sg:city":"Sion",
    "sg:orig_category":"Elektroinstallation",
    "sg:phone":"+41 27 323 42 44",
    "sg:postcode":"1950",
    "sg:province":"Valais",
    "wof:name":"Afn Frel\u00e9chox G\u00e9rald",
    "wof:placetype":"venue"
},
  "geometry": {"coordinates":[7.3585290909,46.2292175293],"type":"Point"}
}