{
  "type": "Feature",
  "properties": {
    "iso:country":"CH",
    "sg:address":"Efibach 38 6473 Silenen. Postfach",
    "sg:city":"Amsteg",
    "sg:classifiers":[
        {
            "category":"Manufacturing",
            "subcategory":"Metals",
            "type":"Manufacturing & Wholesale Goods"
        }
    ],
    "sg:phone":"+41 18261780",
    "sg:postcode":"6474",
    "sg:province":"Uri",
    "sg:tags":[
        "u",
        "leichtmetallbau",
        "stahl"
    ],
    "wof:name":"Walker Stahl Und Metallbau Gmbh",
    "wof:placetype":"venue"
},
  "geometry": {"coordinates":[8.6695671082,46.7983627319],"type":"Point"}
}