{
  "type": "Feature",
  "properties": {
    "iso:country":"CH",
    "sg:address":"K\u00f6nizstrasse 156",
    "sg:city":"Liebefeld",
    "sg:orig_category":"Dachdeckerei D\u00e4mmung gegen K\u00e4lte, W\u00e4rme, Schall U Ersch\u00fctterung",
    "sg:phone":"+41 31 971 74 14",
    "sg:postcode":"3097",
    "sg:province":"Bern",
    "wof:name":"Hans Scheidegger Flachbedachungen Isolierungen",
    "wof:placetype":"venue"
},
  "geometry": {"coordinates":[7.415669,46.936417],"type":"Point"}
}