{
  "type": "Feature",
  "properties": {
    "iso:country":"CH",
    "sg:address":"Seewadelstrasse 14",
    "sg:city":"Henggart",
    "sg:orig_category":"Handelsvermittlung U Grosshandel",
    "sg:phone":"+41 71 310 08 80",
    "sg:postcode":"8444",
    "sg:province":"Z\u00fcrich",
    "wof:name":"Pal Alp Gmbh Import, Export",
    "wof:placetype":"venue"
},
  "geometry": {"coordinates":[9.3163175583,47.4159812927],"type":"Point"}
}