{
  "type": "Feature",
  "properties": {
    "iso:country":"CH",
    "sg:address":"T\u00fcrliackerstrasse 16",
    "sg:city":"Wallisellen",
    "sg:classifiers":[
        {
            "category":"Communications",
            "subcategory":"Film & Video Production",
            "type":"Services"
        }
    ],
    "sg:phone":"+41 18305121",
    "sg:postcode":"8304",
    "sg:province":"Z\u00fcrich",
    "sg:tags":[
        "information",
        "consulting",
        "technology"
    ],
    "wof:name":"Glitsch Consulting Gmbh",
    "wof:placetype":"venue"
},
  "geometry": {"coordinates":[8.6011762619,47.4204483032],"type":"Point"}
}