{
  "type": "Feature",
  "properties": {
    "iso:country":"CH",
    "sg:address":"Im Jakobstal 9",
    "sg:city":"Hochfelden",
    "sg:orig_category":"Fachdetailhandel in Verkaufsr\u00e4umen",
    "sg:phone":"+41 55 211 11 70",
    "sg:postcode":"8182",
    "sg:province":"Z\u00fcrich",
    "wof:name":"Baumann Felix, Goldschmied",
    "wof:placetype":"venue"
},
  "geometry": {"coordinates":[8.8147964478,47.226398468],"type":"Point"}
}