{
  "type": "Feature",
  "properties": {
    "iso:country":"CH",
    "sg:address":"Buckstrasse 17",
    "sg:city":"Lufingen",
    "sg:orig_category":"Public-Relations-Agenturen",
    "sg:phone":"+41 18814494",
    "sg:postcode":"8426",
    "sg:province":"Z\u00fcrich",
    "wof:name":"Edpp Gmbh",
    "wof:placetype":"venue"
},
  "geometry": {"coordinates":[8.5987596512,47.4742660522],"type":"Point"}
}