{
  "type": "Feature",
  "properties": {
    "iso:country":"CH",
    "sg:address":"Neugutstrasse 28",
    "sg:city":"Oberengstringen",
    "sg:orig_category":"Unclassifiable Establishments",
    "sg:postcode":"8102",
    "sg:province":"Z\u00fcrich",
    "wof:name":"Polyschaum Gmbh",
    "wof:placetype":"venue"
},
  "geometry": {"coordinates":[8.4558639526,47.4083213806],"type":"Point"}
}