{
  "type": "Feature",
  "properties": {
    "iso:country":"CH",
    "sg:address":"Weystrasse 20 6006 Luzern. Postfach",
    "sg:city":"Luzern",
    "sg:orig_category":"Handel mit Automobilen",
    "sg:phone":"+41 41 417 11 11",
    "sg:postcode":"6006",
    "sg:province":"Luzern",
    "wof:name":"Auto Koch Ag",
    "wof:placetype":"venue"
},
  "geometry": {"coordinates":[8.3124685287,47.0568122864],"type":"Point"}
}