{
  "type": "Feature",
  "properties": {
    "iso:country":"CH",
    "sg:address":"Rue De La Girarde 10",
    "sg:city":"Epalinges",
    "sg:orig_category":"Architektur U Ingenieurb\u00fcros",
    "sg:phone":"+41 21 784 31 70",
    "sg:postcode":"1066",
    "sg:province":"Vaud",
    "wof:name":"Bureau D'etudes Roland Perrin",
    "wof:placetype":"venue"
},
  "geometry": {"coordinates":[6.675228,46.551216],"type":"Point"}
}