{
  "type": "Feature",
  "properties": {
    "iso:country":"CH",
    "sg:address":"Villa Les R\u00e2ches Haute-nendaz",
    "sg:city":"Haute-nendaz",
    "sg:orig_category":"Vermietung U Verpachtung von eigenen Immobilien Vermittlung von Immobilien",
    "sg:phone":"+41 22 716 50 50",
    "sg:postcode":"1997",
    "sg:province":"Valais",
    "wof:name":"Agence Immobili\u00e8re Rodolphe Burger Sa",
    "wof:placetype":"venue"
},
  "geometry": {"coordinates":[6.1456441879,46.2065734863],"type":"Point"}
}