{
  "type": "Feature",
  "properties": {
    "iso:country":"CH",
    "sg:address":"Breitestrasse 82",
    "sg:city":"Muttenz",
    "sg:orig_category":"Malerei",
    "sg:phone":"+41 61 461 05 78",
    "sg:postcode":"4132",
    "sg:province":"Basel-Landschaft",
    "wof:name":"Andreas Zwahlen Malergesch\u00e4ft",
    "wof:placetype":"venue"
},
  "geometry": {"coordinates":[7.6573410034,47.5239448547],"type":"Point"}
}