{
  "type": "Feature",
  "properties": {
    "iso:country":"CH",
    "sg:address":"Claro Via Pizzo Di 11",
    "sg:city":"Bellinzona",
    "sg:orig_category":"Herstellung von Reiseartikeln, Leder U Sattlerwaren",
    "sg:phone":"+41 91 825 20 25",
    "sg:postcode":"6500",
    "sg:province":"Ticino",
    "wof:name":"Selleria Santarelli Antonio",
    "wof:placetype":"venue"
},
  "geometry": {"coordinates":[9.0217933655,46.2023086548],"type":"Point"}
}