{
  "type": "Feature",
  "properties": {
    "iso:country":"CH",
    "sg:address":"Franz-zelgerstrasse 4 6023 Rothenburg. Postfach 103",
    "sg:city":"Rothenburg",
    "sg:orig_category":"Wirtschaftspr\u00fcfung, Steuerberatung U Treuhand",
    "sg:phone":"+41 41 280 02 22",
    "sg:postcode":"6023",
    "sg:province":"Luzern",
    "wof:name":"Modula Treuhand Minder + Partner",
    "wof:placetype":"venue"
},
  "geometry": {"coordinates":[8.2713851929,47.0945663452],"type":"Point"}
}