{
  "type": "Feature",
  "properties": {
    "iso:country":"CH",
    "sg:address":"Walligrund 32",
    "sg:city":"Eyholz",
    "sg:orig_category":"Detailhandel Einzelhandel mit Automobilen Reparatur von Gebrauchsg\u00fctern",
    "sg:phone":"+41 27 946 23 07",
    "sg:postcode":"3931",
    "sg:province":"Valais",
    "wof:name":"Caravan-service Kurt Siegenthaler",
    "wof:placetype":"venue"
},
  "geometry": {"coordinates":[7.9033398628,46.2992095947],"type":"Point"}
}