{
  "type": "Feature",
  "properties": {
    "iso:country":"CH",
    "sg:address":"Route Wilhelm-kaiser 9 1700 Fribourg. Postfach",
    "sg:city":"Fribourg",
    "sg:orig_category":"Glaserei Grosshandel mit keramischen Erzeugnissen, Glaswaren U Reinigungsmitteln",
    "sg:phone":"+41 21 617 39 39",
    "sg:postcode":"1705",
    "sg:province":"Fribourg",
    "wof:name":"Vitrerie Nouvelle, Zaccarini Roger",
    "wof:placetype":"venue"
},
  "geometry": {"coordinates":[6.6163730621,46.5170440674],"type":"Point"}
}