{
  "type": "Feature",
  "properties": {
    "iso:country":"CH",
    "sg:address":"Rue De Lausanne 16",
    "sg:city":"Morges",
    "sg:orig_category":"Unclassifiable Establishments",
    "sg:phone":"+41 21 801 30 65",
    "sg:postcode":"1110",
    "sg:province":"Vaud",
    "wof:name":"Si Des Jardins De Bourg Sa",
    "wof:placetype":"venue"
},
  "geometry": {"coordinates":[6.5008101463,46.5123786926],"type":"Point"}
}