{
  "type": "Feature",
  "properties": {
    "iso:country":"CH",
    "sg:address":"Binningerstrasse 94",
    "sg:city":"Allschwil",
    "sg:classifiers":[
        {
            "category":"Personal",
            "subcategory":"Barber",
            "type":"Services"
        }
    ],
    "sg:phone":"+41 61 486 71 11",
    "sg:postcode":"4123",
    "sg:province":"Basel-Landschaft",
    "sg:tags":[
        "barber's",
        "equipment"
    ],
    "wof:name":"Wella (suisse) S.a.",
    "wof:placetype":"venue"
},
  "geometry": {"coordinates":[7.54818,47.547817],"type":"Point"}
}