{
  "type": "Feature",
  "properties": {
    "iso:country":"CH",
    "sg:address":"Lindenstrasse 5",
    "sg:city":"Liestal",
    "sg:classifiers":[
        {
            "category":"Restaurant",
            "type":"Food & Drink"
        }
    ],
    "sg:postcode":"4410",
    "sg:province":"Basel-Landschaft",
    "wof:name":"Restaurant Lindenhof",
    "wof:placetype":"venue"
},
  "geometry": {"coordinates":[7.7360458374,47.485786438],"type":"Point"}
}