{
  "type": "Feature",
  "properties": {
    "iso:country":"CH",
    "sg:address":"Marktgasse 59",
    "sg:city":"Bern",
    "sg:orig_category":"Detailhandel mit B\u00fcchern",
    "sg:phone":"+41 31 326 46 46",
    "sg:postcode":"3000",
    "sg:province":"Bern",
    "wof:name":"Huber B\u00fccher Medien",
    "wof:placetype":"venue"
},
  "geometry": {"coordinates":[7.444418,46.947994],"type":"Point"}
}