{
  "type": "Feature",
  "properties": {
    "iso:country":"CH",
    "sg:address":"Bellariastrasse 23",
    "sg:city":"Z\u00fcrich",
    "sg:classifiers":[
        {
            "category":"Banks & Credit Unions",
            "subcategory":"Bank",
            "type":"Services"
        }
    ],
    "sg:postcode":"8002",
    "sg:province":"Z\u00fcrich",
    "wof:name":"Sydbank (schweiz) Ag",
    "wof:placetype":"venue"
},
  "geometry": {"coordinates":[8.29296,47.588821],"type":"Point"}
}