{
  "type": "Feature",
  "properties": {
    "iso:country":"CH",
    "sg:address":"Gubelstrasse",
    "sg:city":"Menzingen",
    "sg:orig_category":"Cardboard Sleeves, Tubes, Rolls",
    "sg:phone":"+41 41 755 12 82",
    "sg:postcode":"6313",
    "sg:province":"Zug",
    "wof:name":"Sonoco Caprex Karton- Und Papierverarbeitungs Ag",
    "wof:placetype":"venue"
},
  "geometry": {"coordinates":[8.590497,47.176754],"type":"Point"}
}