{
  "type": "Feature",
  "properties": {
    "addr:full":"Lehenmattstrasse 69 4052 Basel. Postfach Basel Basel-Stadt 4051",
    "addr:housenumber":"69",
    "addr:postcode":"4052;4051",
    "addr:street":"Lehenmattstrasse;Postfach",
    "iso:country":"CH",
    "sg:address":"Lehenmattstrasse 69 4052 Basel. Postfach",
    "sg:city":"Basel",
    "sg:orig_category":"Architektur U Ingenieurb\u00fcros",
    "sg:postcode":"4051",
    "sg:province":"Basel-Stadt",
    "wof:name":"Arcroi Gmbh Architekturb\u00fcro U. Aller Damit Zusammenh\u00e4ngender Dienstleistungen, Bes. Planungsarbeiten Usw",
    "wof:placetype":"venue"
},
  "geometry": {"coordinates":[7.61476,47.553329],"type":"Point"}
}