{
  "type": "Feature",
  "properties": {
    "iso:country":"CH",
    "sg:address":"Baslerstrasse 337",
    "sg:city":"Allschwil",
    "sg:orig_category":"Grosshandel mit pharmazeutischen Erzeugnissen, medizinischen U orthop\u00e4dischen Artikeln",
    "sg:phone":"+41 61 401 31 16",
    "sg:postcode":"4123",
    "sg:province":"Basel-Landschaft",
    "wof:name":"Cumino Gmbh",
    "wof:placetype":"venue"
},
  "geometry": {"coordinates":[7.5621538162,47.5576896667],"type":"Point"}
}