{
  "type": "Feature",
  "properties": {
    "iso:country":"CH",
    "sg:address":"Am Bach 1",
    "sg:city":"Tamins",
    "sg:orig_category":"Arbeitnehmerverb\u00e4nde",
    "sg:phone":"+41 81 641 36 46",
    "sg:postcode":"7015",
    "sg:province":"Graubunden",
    "wof:name":"Schweiz.verband Der Versich.- Inspektoren Hrn Emanuel Lendi",
    "wof:placetype":"venue"
},
  "geometry": {"coordinates":[9.406932,46.830078],"type":"Point"}
}