{
  "type": "Feature",
  "properties": {
    "iso:country":"CH",
    "sg:address":"Industriestrasse 13c",
    "sg:city":"Zug",
    "sg:orig_category":"Non-Classified Establishments",
    "sg:phone":"+41 61 716 56 56",
    "sg:postcode":"6300",
    "sg:province":"Zug",
    "wof:name":"Senn Marc Holding Ag",
    "wof:placetype":"venue"
},
  "geometry": {"coordinates":[7.5986847878,47.4886856079],"type":"Point"}
}