{
  "type": "Feature",
  "properties": {
    "iso:country":"CH",
    "sg:address":"Ergetenstrasse 30",
    "sg:city":"Rebstein",
    "sg:orig_category":"Erbringung von Dienstleistungen f\u00fcr Unternehmen",
    "sg:postcode":"9445",
    "sg:province":"St. Gallen",
    "wof:name":"Schmid Grafik-werbung-design",
    "wof:placetype":"venue"
},
  "geometry": {"coordinates":[9.5834970474,47.3947143555],"type":"Point"}
}