{
  "type": "Feature",
  "properties": {
    "iso:country":"CH",
    "sg:address":"Schmalzgasse 1",
    "sg:city":"Breitenbach",
    "sg:orig_category":"Architekturb\u00fcros",
    "sg:phone":"+41 61 781 32 79",
    "sg:postcode":"4226",
    "sg:province":"Solothurn",
    "wof:name":"Hanspeter Karrer Architekturb\u00fcro",
    "wof:placetype":"venue"
},
  "geometry": {"coordinates":[7.542909,47.4077],"type":"Point"}
}