{
  "type": "Feature",
  "properties": {
    "iso:country":"CH",
    "sg:address":"Parkstrasse 15",
    "sg:city":"Therwil",
    "sg:orig_category":"Markt U Meinungsforschung",
    "sg:phone":"+41 61 726 92 40",
    "sg:postcode":"4106",
    "sg:province":"Basel-Landschaft",
    "wof:name":"Bro Travel Ag",
    "wof:placetype":"venue"
},
  "geometry": {"coordinates":[7.5565309525,47.5001335144],"type":"Point"}
}