{
  "type": "Feature",
  "properties": {
    "iso:country":"CH",
    "sg:address":"Bahnhofstrasse 68",
    "sg:city":"Dietlikon",
    "sg:orig_category":"Schreibb\u00fcros",
    "sg:phone":"+41 32 384 31 26",
    "sg:postcode":"8305",
    "sg:province":"Z\u00fcrich",
    "wof:name":"Mfa-schreibdienst",
    "wof:placetype":"venue"
},
  "geometry": {"coordinates":[7.3127660751,47.0902252197],"type":"Point"}
}