{
  "type": "Feature",
  "properties": {
    "iso:country":"CH",
    "sg:address":"Wart 79",
    "sg:city":"Thun",
    "sg:orig_category":"Sonstige Hilfs U Nebent\u00e4tigkeiten f\u00fcr die Schiffahrt",
    "sg:postcode":"3600",
    "sg:province":"Bern",
    "wof:name":"Bootshaus-genossenschaft Thun",
    "wof:placetype":"venue"
},
  "geometry": {"coordinates":[7.643404007,46.7519569397],"type":"Point"}
}