{
  "type": "Feature",
  "properties": {
    "iso:country":"CH",
    "sg:address":"Via Molinazzi 2",
    "sg:city":"Lugano",
    "sg:classifiers":[
        {
            "category":"Bars & Pubs",
            "type":"Food & Drink"
        }
    ],
    "sg:postcode":"6900",
    "sg:province":"Ticino",
    "wof:name":"Liberty 93 Ag",
    "wof:placetype":"venue"
},
  "geometry": {"coordinates":[8.293214,47.486698],"type":"Point"}
}