{
  "type": "Feature",
  "properties": {
    "iso:country":"CH",
    "sg:address":"Route De Pr\u00e9-bois 15-17 1217 Meyrin. Postfach",
    "sg:city":"Meyrin",
    "sg:orig_category":"Sonstige Hilfs U Nebent\u00e4tigkeiten f\u00fcr die Luftfahrt Sonstige pers\u00f6nliche Dienstleistungen",
    "sg:phone":"+41 22 417 41 11",
    "sg:postcode":"1217",
    "sg:province":"Gen\u00e8ve",
    "wof:name":"Swisscontrol Sa Support Op\u00e9rationnel Li\u00e9 Aux Activit\u00e9s De S\u00e9curit\u00e9 Et De Navigation A\u00e9rienne Etc",
    "wof:placetype":"venue"
},
  "geometry": {"coordinates":[6.0993537903,46.2243003845],"type":"Point"}
}