{
  "type": "Feature",
  "properties": {
    "iso:country":"CH",
    "sg:address":"Rue Des Charpentiers 34",
    "sg:city":"Morges",
    "sg:orig_category":"Handelsvermittlung U Grosshandel",
    "sg:phone":"+41 21 801 88 39",
    "sg:postcode":"1110",
    "sg:province":"Vaud",
    "wof:name":"Pontrade Sa N\u00e9goce International",
    "wof:placetype":"venue"
},
  "geometry": {"coordinates":[6.4961547852,46.5093345642],"type":"Point"}
}