{
  "type": "Feature",
  "properties": {
    "iso:country":"CH",
    "sg:address":"Gaicht",
    "sg:city":"Twann",
    "sg:orig_category":"Gartenbau Rebbau",
    "sg:phone":"+41 32 315 31 10",
    "sg:postcode":"2513",
    "sg:province":"Bern",
    "wof:name":"Florian & Barbara Vetsch Naturgarten-& Bioweinbau",
    "wof:placetype":"venue"
},
  "geometry": {"coordinates":[7.16726017,47.1079750061],"type":"Point"}
}