{
  "type": "Feature",
  "properties": {
    "iso:country":"CH",
    "sg:address":"Eschenstrasse 1",
    "sg:city":"Rodersdorf",
    "sg:orig_category":"Sonstige mit Sport verbundene T\u00e4tigkeiten",
    "sg:phone":"+41 27 957 49 04",
    "sg:postcode":"4118",
    "sg:province":"Solothurn",
    "wof:name":"Paradise Snowboardschule Gmbh",
    "wof:placetype":"venue"
},
  "geometry": {"coordinates":[7.933672905,46.1117172241],"type":"Point"}
}