{
  "type": "Feature",
  "properties": {
    "iso:country":"CH",
    "sg:address":"Gerschniweg 1 6390 Engelberg. Postfach 745",
    "sg:city":"Engelberg",
    "sg:orig_category":"HOTELS: OHNE RESTAURANT",
    "sg:phone":"+41 41 637 45 75",
    "sg:postcode":"6391",
    "sg:province":"Obwalden",
    "wof:name":"Hotel Sonnwendhof",
    "wof:placetype":"venue"
},
  "geometry": {"coordinates":[8.3994836807,46.8193321228],"type":"Point"}
}