{
  "type": "Feature",
  "properties": {
    "iso:country":"CH",
    "sg:address":"1098",
    "sg:city":"Epesses",
    "sg:orig_category":"Dauerkulturbau Rebbau",
    "sg:phone":"+41 32 757 10 59",
    "sg:postcode":"1098",
    "sg:province":"Vaud",
    "wof:name":"Georges-edouard Vacher",
    "wof:placetype":"venue"
},
  "geometry": {"coordinates":[7.034446,47.052914],"type":"Point"}
}