{
  "type": "Feature",
  "properties": {
    "addr:full":"Zugerstrasse 1 Richterswil Z\u00fcrich 8805",
    "addr:housenumber":"1",
    "addr:postcode":"8805",
    "addr:street":"Zugerstrasse",
    "iso:country":"CH",
    "sg:address":"Zugerstrasse 1",
    "sg:city":"Richterswil",
    "sg:orig_category":"Betrieb von Taxis",
    "sg:phone":"+41 17814949",
    "sg:postcode":"8805",
    "sg:province":"Z\u00fcrich",
    "wof:name":"Behindertentransporte Linkes Z\u00fcrichseeufer",
    "wof:placetype":"venue"
},
  "geometry": {"coordinates":[8.70681,47.205303],"type":"Point"}
}