{
  "type": "Feature",
  "properties": {
    "iso:country":"CH",
    "sg:address":"6218",
    "sg:city":"Ettiswil",
    "sg:orig_category":"Vorschulen, Kinderg\u00e4rten",
    "sg:postcode":"6218",
    "sg:province":"Luzern",
    "wof:name":"Kindergarten",
    "wof:placetype":"venue"
},
  "geometry": {"coordinates":[8.017583847,47.147808075],"type":"Point"}
}