{
  "type": "Feature",
  "properties": {
    "iso:country":"CH",
    "sg:address":"Place St-martin",
    "sg:city":"Leytron",
    "sg:orig_category":"Detailhandel mit Fleisch U Fleischwaren",
    "sg:phone":"+41 32 968 40 23",
    "sg:postcode":"1912",
    "sg:province":"Valais",
    "wof:name":"Jean-claude Gaille Boucherie-charcuterie",
    "wof:placetype":"venue"
},
  "geometry": {"coordinates":[6.8329768181,47.1027870178],"type":"Point"}
}