{
  "type": "Feature",
  "properties": {
    "iso:country":"CH",
    "sg:address":"Asetstrasse 43",
    "sg:city":"Ibach",
    "sg:orig_category":"Bauschreinerei",
    "sg:phone":"+41 32 757 32 47",
    "sg:postcode":"6438",
    "sg:province":"Schwyz",
    "wof:name":"Ulrich Aeby Menuiserie",
    "wof:placetype":"venue"
},
  "geometry": {"coordinates":[7.021132,47.037601],"type":"Point"}
}