{
  "type": "Feature",
  "properties": {
    "iso:country":"CH",
    "sg:address":"Luriweg 12",
    "sg:city":"Hittnau",
    "sg:orig_category":"Elektroinstallation",
    "sg:postcode":"8335",
    "sg:province":"Z\u00fcrich",
    "wof:name":"Wagni\u00e8re Christian",
    "wof:placetype":"venue"
},
  "geometry": {"coordinates":[6.5610051155,46.8027954102],"type":"Point"}
}