{
  "type": "Feature",
  "properties": {
    "addr:full":"Carmenstrasse 6 Z\u00fcrich Z\u00fcrich 8032",
    "addr:housenumber":"6",
    "addr:postcode":"8032",
    "addr:street":"Carmenstrasse",
    "iso:country":"CH",
    "sg:address":"Carmenstrasse 6",
    "sg:city":"Z\u00fcrich",
    "sg:orig_category":"Shopping U Fachgesch\u00e4fte, Nahrungs- U Genu\u00dfmittel",
    "sg:phone":"+41 4112543300",
    "sg:postcode":"8032",
    "sg:province":"Z\u00fcrich",
    "wof:name":"Bols Cynar Ballantines Ag",
    "wof:placetype":"venue"
},
  "geometry": {"coordinates":[8.560908,47.370579],"type":"Point"}
}