{
  "type": "Feature",
  "properties": {
    "iso:country":"CH",
    "sg:address":"Ziegelmattstrasse 16",
    "sg:city":"Rubigen",
    "sg:orig_category":"Sportvereine Eissport Curling",
    "sg:phone":"+41 32 671 31 80",
    "sg:postcode":"3113",
    "sg:province":"Bern",
    "wof:name":"C.c.bern-z\u00e4hringer",
    "wof:placetype":"venue"
},
  "geometry": {"coordinates":[7.5403327942,46.8944625854],"type":"Point"}
}