{
  "type": "Feature",
  "properties": {
    "iso:country":"CH",
    "sg:address":"Unterdorfstrasse 7 3427 Utzenstorf. Postfach",
    "sg:city":"Utzenstorf",
    "sg:orig_category":"Kantonalbanken",
    "sg:phone":"+41 32 665 46 44",
    "sg:postcode":"3427",
    "sg:province":"Bern",
    "wof:name":"Berner Kantonalbank Bekb/bcbe",
    "wof:placetype":"venue"
},
  "geometry": {"coordinates":[7.5567498207,47.1371307373],"type":"Point"}
}