{
  "type": "Feature",
  "properties": {
    "addr:full":"Vicolo Del Borenco 24 Minusio Ticino 6648",
    "addr:housenumber":"24",
    "addr:postcode":"6648",
    "addr:street":"Vicolo Del Borenco",
    "iso:country":"CH",
    "sg:address":"Vicolo Del Borenco 24",
    "sg:city":"Minusio",
    "sg:orig_category":"Architektur U Ingenieurb\u00fcros",
    "sg:postcode":"6648",
    "sg:province":"Ticino",
    "wof:name":"Tse Sa",
    "wof:placetype":"venue"
},
  "geometry": {"coordinates":[8.81306,46.176483],"type":"Point"}
}