{
  "type": "Feature",
  "properties": {
    "iso:country":"CH",
    "sg:address":"Centro Oxalis 1-c. 6951 Bogno. Postfach",
    "sg:city":"Bogno",
    "sg:orig_category":"Handels-H\u00e4user U Gesellschaften",
    "sg:postcode":"6951",
    "sg:province":"Ticino",
    "wof:name":"Fit Terrasi Ingrid",
    "wof:placetype":"venue"
},
  "geometry": {"coordinates":[9.0344152451,46.0903358459],"type":"Point"}
}