{
  "type": "Feature",
  "properties": {
    "iso:country":"CH",
    "sg:address":"Obergrundstrasse 1",
    "sg:city":"Luzern",
    "sg:orig_category":"Schulpflegen",
    "sg:phone":"+41 41 208 87 60",
    "sg:postcode":"6003",
    "sg:province":"Luzern",
    "wof:name":"Rektorat Oberstufe Der Stadt Luzern",
    "wof:placetype":"venue"
},
  "geometry": {"coordinates":[8.3035049438,47.0487937927],"type":"Point"}
}