{
  "type": "Feature",
  "properties": {
    "iso:country":"CH",
    "sg:address":"Redig\u00e4cker 8 7307 Jenins. Postfach",
    "sg:city":"Jenins",
    "sg:orig_category":"Sonstiger spezialisierter Hoch U Tiefbau",
    "sg:postcode":"7307",
    "sg:province":"Graubunden",
    "wof:name":"Gort M., Maurer Und Verputzarbeiten",
    "wof:placetype":"venue"
},
  "geometry": {"coordinates":[9.5545530319,47.0034866333],"type":"Point"}
}