{
  "type": "Feature",
  "properties": {
    "iso:country":"CH",
    "sg:address":"8200",
    "sg:city":"Schaffhausen",
    "sg:orig_category":"Interessenvertretungen U sonstige Vereinigungen",
    "sg:postcode":"8200",
    "sg:province":"Schaffhausen",
    "wof:name":"Kantonaler Schwingerverband",
    "wof:placetype":"venue"
},
  "geometry": {"coordinates":[7.5608959198,47.5157814026],"type":"Point"}
}