{
  "type": "Feature",
  "properties": {
    "iso:country":"CH",
    "sg:address":"Gewerbestrasse 18 8800 Thalwil. Postfach 15",
    "sg:city":"Thalwil",
    "sg:orig_category":"Fachdetailhandel in Verkaufsr\u00e4umen",
    "sg:phone":"+41 17225060",
    "sg:postcode":"8800",
    "sg:province":"Z\u00fcrich",
    "wof:name":"Z\u00fcrcher Werner Ag",
    "wof:placetype":"venue"
},
  "geometry": {"coordinates":[8.5658521652,47.2859382629],"type":"Point"}
}