{
  "type": "Feature",
  "properties": {
    "iso:country":"CH",
    "sg:address":"Aeschistrasse 13",
    "sg:city":"Nieder\u00f6nz",
    "sg:orig_category":"Oberfl\u00e4chenveredlung U W\u00e4rmebehandlung",
    "sg:phone":"+41 62 961 26 06",
    "sg:postcode":"3362",
    "sg:province":"Bern",
    "wof:name":"Galvano Niederhauser & Co",
    "wof:placetype":"venue"
},
  "geometry": {"coordinates":[7.6938538551,47.1854705811],"type":"Point"}
}