{
  "type": "Feature",
  "properties": {
    "iso:country":"CH",
    "sg:address":"Ringstrasse 25",
    "sg:city":"Langenthal",
    "sg:classifiers":[
        {
            "category":"Social Services",
            "subcategory":"Retirement Home",
            "type":"Services"
        }
    ],
    "sg:phone":"+41 62 916 00 30",
    "sg:postcode":"4900",
    "sg:province":"Bern",
    "sg:tags":[
        "pflegeheime",
        "u",
        "alters"
    ],
    "wof:name":"Alterswohnheim Lindenhof",
    "wof:placetype":"venue"
},
  "geometry": {"coordinates":[7.781989,47.21283],"type":"Point"}
}