{
  "type": "Feature",
  "properties": {
    "iso:country":"CH",
    "sg:address":"Rue Du Petit-ch\u00eane 36",
    "sg:city":"Lausanne",
    "sg:orig_category":"Detailhandel mit Tabakwaren Detailhandel mit Zeitungen U Zeitschriften Kioske",
    "sg:phone":"+41 21 312 52 70",
    "sg:postcode":"1003",
    "sg:province":"Vaud",
    "wof:name":"Kiosque De Mornex, Formolo Olivo Tabacs, Journaux Etc; Comm",
    "wof:placetype":"venue"
},
  "geometry": {"coordinates":[6.629404068,46.518196106],"type":"Point"}
}