{
  "type": "Feature",
  "properties": {
    "addr:full":"Emmenhofstrasse 4/rampe 3 Derendingen Solothurn 4552",
    "addr:housenumber":"4 /;3",
    "addr:postcode":"4552",
    "addr:street":"Emmenhofstrasse;Rampe",
    "iso:country":"CH",
    "sg:address":"Emmenhofstrasse 4/rampe 3",
    "sg:city":"Derendingen",
    "sg:orig_category":"Adhesive Packaging Tapes With Advertising Imprints",
    "sg:phone":"+41 32 682 05 29",
    "sg:postcode":"4552",
    "sg:province":"Solothurn",
    "wof:name":"Easypack Gmbh",
    "wof:placetype":"venue"
},
  "geometry": {"coordinates":[7.59006,47.200336],"type":"Point"}
}