{
  "type": "Feature",
  "properties": {
    "iso:country":"CH",
    "sg:address":"Chemin Du Passe-loup 5",
    "sg:city":"Veyrier",
    "sg:orig_category":"Datenverarbeitungsdienste Softwareentwicklung U beratung",
    "sg:phone":"+41 22 784 25 94",
    "sg:postcode":"1255",
    "sg:province":"Gen\u00e8ve",
    "wof:name":"In Touch Services Informatique",
    "wof:placetype":"venue"
},
  "geometry": {"coordinates":[6.1734,46.16349],"type":"Point"}
}