{
  "type": "Feature",
  "properties": {
    "iso:country":"CH",
    "sg:address":"Industriestrasse 20a 8604 Volketswil. Postfach",
    "sg:city":"Volketswil",
    "sg:orig_category":"Saunas, Solarien, Fitnesszentren U \u00e4hnliches",
    "sg:phone":"+41 91 910 31 26",
    "sg:postcode":"8604",
    "sg:province":"Z\u00fcrich",
    "wof:name":"Ristorante Parco Maraini",
    "wof:placetype":"venue"
},
  "geometry": {"coordinates":[8.9483909607,46.0110931396],"type":"Point"}
}