{
  "type": "Feature",
  "properties": {
    "iso:country":"CH",
    "sg:address":"Rosenweg 1 6033 Buchrain. Postfach 149",
    "sg:city":"Buchrain",
    "sg:orig_category":"Kaminfeger",
    "sg:phone":"+41 32 954 14 83",
    "sg:postcode":"6033",
    "sg:province":"Luzern",
    "wof:name":"Maurice Cuenin Maitre Ramoneur",
    "wof:placetype":"venue"
},
  "geometry": {"coordinates":[6.9966001511,47.20703125],"type":"Point"}
}