{
  "type": "Feature",
  "properties": {
    "iso:country":"CH",
    "sg:address":"Haslerstrasse 1 8003 Z\u00fcrich. Postfach",
    "sg:city":"Z\u00fcrich",
    "sg:orig_category":"Handelsvermittlung U Grosshandel Vermietung von Gebrauchsg\u00fctern",
    "sg:phone":"+41 14610466",
    "sg:postcode":"8036",
    "sg:province":"Z\u00fcrich",
    "wof:name":"Liza Gmbh",
    "wof:placetype":"venue"
},
  "geometry": {"coordinates":[8.5181341171,47.3736915588],"type":"Point"}
}