{
  "type": "Feature",
  "properties": {
    "iso:country":"CH",
    "sg:address":"Av. Des Libellules 10",
    "sg:city":"Vernier",
    "sg:orig_category":"Wirtschaftspr\u00fcfung, Steuerberatung U Treuhand",
    "sg:phone":"+41 21 641 60 60",
    "sg:postcode":"1214",
    "sg:province":"Gen\u00e8ve",
    "wof:name":"Ofico Soci\u00e9t\u00e9 Fiduciaire",
    "wof:placetype":"venue"
},
  "geometry": {"coordinates":[6.6335749626,46.5319099426],"type":"Point"}
}