{
  "type": "Feature",
  "properties": {
    "iso:country":"CH",
    "sg:address":"Z\u00fcrcherstrasse 139 8952 Schlieren. Postfach",
    "sg:city":"Z\u00fcrich",
    "sg:orig_category":"Softwareentwicklung U beratung",
    "sg:phone":"+41 14001907",
    "sg:postcode":"8001",
    "sg:province":"Z\u00fcrich",
    "wof:name":"Swiss Asian Technology (sat) Ag Softwareprojekte; Entwicklung Und Realisierung. Produktevertrieb Usw",
    "wof:placetype":"venue"
},
  "geometry": {"coordinates":[8.4665288925,47.3962783813],"type":"Point"}
}