{
  "type": "Feature",
  "properties": {
    "iso:country":"CH",
    "sg:address":"Sch\u00fctzenstrasse 1",
    "sg:city":"Muotathal",
    "sg:orig_category":"Allgemeiner Hoch U Tiefbau D\u00e4mmung gegen K\u00e4lte, W\u00e4rme, Schall U Ersch\u00fctterung",
    "sg:phone":"+41 41 830 16 75",
    "sg:postcode":"6436",
    "sg:province":"Schwyz",
    "wof:name":"Betschart Ag, Bauunternehmung, Muotathal.",
    "wof:placetype":"venue"
},
  "geometry": {"coordinates":[8.75369,46.975906],"type":"Point"}
}