{
  "type": "Feature",
  "properties": {
    "iso:country":"CH",
    "sg:address":"Br\u00fcggstrasse 62 2500 Biel/bienne. Postfach",
    "sg:city":"Biel/bienne",
    "sg:orig_category":"Herstellung von Mess U Kontrollinstrumenten U vorrichtungen",
    "sg:phone":"+41 32 365 21 17",
    "sg:postcode":"2503",
    "sg:province":"Bern",
    "wof:name":"Heri Ren\u00e9",
    "wof:placetype":"venue"
},
  "geometry": {"coordinates":[7.2547769547,47.1293983459],"type":"Point"}
}