{
  "type": "Feature",
  "properties": {
    "iso:country":"CH",
    "sg:address":"Clavelaire En 1",
    "sg:city":"Aigle",
    "sg:orig_category":"Fachdetailhandel in Verkaufsr\u00e4umen",
    "sg:phone":"+41 81 667 11 66",
    "sg:postcode":"1860",
    "sg:province":"Vaud",
    "wof:name":"Dettli Sport",
    "wof:placetype":"venue"
},
  "geometry": {"coordinates":[9.5131464005,46.4727554321],"type":"Point"}
}