{
  "type": "Feature",
  "properties": {
    "iso:country":"CH",
    "sg:address":"5467",
    "sg:city":"Fisibach",
    "sg:orig_category":"Sportvereine Sch\u00fctzen",
    "sg:phone":"+41 41 870 31 67",
    "sg:postcode":"5467",
    "sg:province":"Aargau",
    "wof:name":"Sch\u00fctzengesellschaft",
    "wof:placetype":"venue"
},
  "geometry": {"coordinates":[8.4040002823,47.555229187],"type":"Point"}
}