{
  "type": "Feature",
  "properties": {
    "addr:full":"Im Wisli 3 B\u00fclach Z\u00fcrich 8180",
    "addr:housenumber":"3",
    "addr:postcode":"8180",
    "addr:street":"Im Wisli;Zuerich",
    "iso:country":"CH",
    "sg:address":"Im Wisli 3",
    "sg:city":"B\u00fclach",
    "sg:orig_category":"Bau U Wohngenossenschaften",
    "sg:postcode":"8180",
    "sg:province":"Z\u00fcrich",
    "wof:name":"Wohngen.b\u00fclach Wogeno",
    "wof:placetype":"venue"
},
  "geometry": {"coordinates":[8.540586,47.531944],"type":"Point"}
}