{
  "type": "Feature",
  "properties": {
    "iso:country":"CH",
    "sg:address":"Wehntalerstrasse 17 8181 H\u00f6ri. Postfach",
    "sg:city":"H\u00f6ri",
    "sg:orig_category":"Elektro- and elektronische Maschinen Grosshandel",
    "sg:phone":"+41 18620062",
    "sg:postcode":"8181",
    "sg:province":"Z\u00fcrich",
    "wof:name":"Amelec Electronic Gmbh Elektronische Bauelemente",
    "wof:placetype":"venue"
},
  "geometry": {"coordinates":[8.5085802078,47.5073013306],"type":"Point"}
}