{
  "type": "Feature",
  "properties": {
    "iso:country":"CH",
    "sg:address":"Casa Senda",
    "sg:city":"Breil/brigels",
    "sg:orig_category":"Regelm\u00e4ssige Personenbef\u00f6rderung im Fernverkehr",
    "sg:phone":"+41 79 430 62 13",
    "sg:postcode":"7165",
    "sg:province":"Graubunden",
    "wof:name":"Alfons Bearth Postautokurse",
    "wof:placetype":"venue"
},
  "geometry": {"coordinates":[9.0625333786,46.7674217224],"type":"Point"}
}