{
  "type": "Feature",
  "properties": {
    "addr:full":"Degenstrasse 3 Berneck St. Gallen 9442",
    "addr:housenumber":"3;st.",
    "addr:postcode":"9442",
    "addr:street":"Degenstrasse;Berneck",
    "iso:country":"CH",
    "sg:address":"Degenstrasse 3",
    "sg:city":"Berneck",
    "sg:classifiers":[
        {
            "category":"Banks & Credit Unions",
            "subcategory":"Bank",
            "type":"Services"
        }
    ],
    "sg:phone":"+41 4171713505",
    "sg:postcode":"9442",
    "sg:province":"St. Gallen",
    "wof:name":"Schweiz. Mobiliar",
    "wof:placetype":"venue"
},
  "geometry": {"coordinates":[9.604579,47.425949],"type":"Point"}
}