{
  "type": "Feature",
  "properties": {
    "iso:country":"CH",
    "sg:address":"Industriestrasse 11",
    "sg:city":"Zug",
    "sg:orig_category":"Unternehmensberatung",
    "sg:phone":"+41 91 857 03 65",
    "sg:postcode":"6300",
    "sg:province":"Zug",
    "wof:name":"Comasis Di Jungi Niklaus",
    "wof:placetype":"venue"
},
  "geometry": {"coordinates":[8.9927511215,46.1545944214],"type":"Point"}
}