{
  "type": "Feature",
  "properties": {
    "iso:country":"CH",
    "sg:address":"Les Quarres",
    "sg:city":"Engollon",
    "sg:orig_category":"Abwasserreinigung",
    "sg:phone":"+41 32 853 38 26",
    "sg:postcode":"2063",
    "sg:province":"Neuch\u00e2tel",
    "wof:name":"Station D'\u00e9puration Des Eaux Du Haut Val-de-ruz",
    "wof:placetype":"venue"
},
  "geometry": {"coordinates":[6.92753,47.032436],"type":"Point"}
}