{
  "type": "Feature",
  "properties": {
    "iso:country":"CH",
    "sg:address":"Rietweg",
    "sg:city":"Azmoos",
    "sg:orig_category":"Detailhandel mit Haustieren U zoologischem Bedarf Erbringung von sonstigen Dienstleistungen f\u00fcr Unte",
    "sg:phone":"+41 81 783 24 23",
    "sg:postcode":"9478",
    "sg:province":"St. Gallen",
    "wof:name":"Heini's Dog-shop Beck Heinrich",
    "wof:placetype":"venue"
},
  "geometry": {"coordinates":[9.4812002182,47.08360672],"type":"Point"}
}