{
  "type": "Feature",
  "properties": {
    "iso:country":"CH",
    "sg:address":"Waldheimstrasse 41 3012 Bern. Postfach",
    "sg:city":"Bern",
    "sg:orig_category":"Sonstiger Grosshandel",
    "sg:postcode":"3005",
    "sg:province":"Bern",
    "wof:name":"P. Reinhard Warenhandel",
    "wof:placetype":"venue"
},
  "geometry": {"coordinates":[7.4270119667,46.9542388916],"type":"Point"}
}