{
  "type": "Feature",
  "properties": {
    "iso:country":"CH",
    "sg:address":"Kantonsstrasse 320 Gamsen 3900 Berisal. Postfach",
    "sg:city":"Gamsen",
    "sg:orig_category":"Vermietung U Verpachtung von eigenen Immobilien",
    "sg:phone":"+41 41 811 62 27",
    "sg:postcode":"3900",
    "sg:province":"Valais",
    "wof:name":"Schwyzerhof Immobilien Ag",
    "wof:placetype":"venue"
},
  "geometry": {"coordinates":[8.6330451965,47.0260734558],"type":"Point"}
}