{
  "type": "Feature",
  "properties": {
    "iso:country":"CH",
    "sg:address":"Grossbruggerweg 2 7004 Chur. Postfach 195",
    "sg:city":"Chur",
    "sg:orig_category":"G\u00fcterbef\u00f6rderung im Strassenverkehr",
    "sg:phone":"+41 81 284 29 39",
    "sg:postcode":"7004",
    "sg:province":"Graubunden",
    "wof:name":"Grischa Transporte Ag",
    "wof:placetype":"venue"
},
  "geometry": {"coordinates":[9.531170845,46.8501968384],"type":"Point"}
}