{
  "type": "Feature",
  "properties": {
    "iso:country":"CH",
    "sg:address":"Hauptstrasse 18",
    "sg:city":"L\u00fcterswil",
    "sg:orig_category":"Instandhaltung U Reparatur von Automobilen",
    "sg:phone":"+41 32 351 19 63",
    "sg:postcode":"4584",
    "sg:province":"Solothurn",
    "wof:name":"Bartlome Fritz",
    "wof:placetype":"venue"
},
  "geometry": {"coordinates":[7.4391899109,47.1210479736],"type":"Point"}
}