{
  "type": "Feature",
  "properties": {
    "iso:country":"CH",
    "sg:address":"In Der Luberzen 25",
    "sg:city":"Urdorf",
    "sg:classifiers":[
        {
            "category":"Banks & Credit Unions",
            "subcategory":"Financial Services",
            "type":"Services"
        }
    ],
    "sg:phone":"+41 848 662 222",
    "sg:postcode":"8902",
    "sg:province":"Z\u00fcrich",
    "sg:tags":[
        "security",
        "system",
        "card"
    ],
    "wof:name":"Telekurs Card Solutions Ag",
    "wof:placetype":"venue"
},
  "geometry": {"coordinates":[8.424253,47.394161],"type":"Point"}
}