{
  "type": "Feature",
  "properties": {
    "addr:full":"W\u00fclflingerstr. 276 Winterthur Z\u00fcrich 8408",
    "addr:housenumber":"276",
    "addr:postcode":"8408",
    "iso:country":"CH",
    "sg:address":"W\u00fclflingerstr. 276",
    "sg:city":"Winterthur",
    "sg:classifiers":[
        {
            "category":"Building & Trades",
            "subcategory":"Construction",
            "type":"Services"
        }
    ],
    "sg:phone":"+41 52 222 14 21",
    "sg:postcode":"8408",
    "sg:province":"Z\u00fcrich",
    "sg:tags":[
        "electric",
        "-",
        "component",
        "equipment",
        "engineering",
        "electrical",
        "mechanical",
        "electronic",
        "mach"
    ],
    "wof:name":"Liggenstorfer Ag",
    "wof:placetype":"venue"
},
  "geometry": {"coordinates":[8.692092,47.510983],"type":"Point"}
}