{
  "type": "Feature",
  "properties": {
    "iso:country":"CH",
    "sg:address":"Sch\u00e4renmoosstrasse 9",
    "sg:city":"Seebach",
    "sg:orig_category":"Herstellung von Elektrizit\u00e4tsverteilungs U schalteinrichtungen",
    "sg:phone":"+41 13028330",
    "sg:postcode":"8052",
    "sg:province":"Z\u00fcrich",
    "wof:name":"Mrs Mechatronic Research Systems Gmbh",
    "wof:placetype":"venue"
},
  "geometry": {"coordinates":[8.5402402878,47.4224815369],"type":"Point"}
}