{
  "type": "Feature",
  "properties": {
    "iso:country":"CH",
    "sg:address":"Avenue Du Servan 36",
    "sg:city":"Lausanne",
    "sg:orig_category":"Detailhandel mit Brot, Back U S\u00fcsswaren Herstellung von Maschinen f\u00fcr die Nahrungsmittel, Getr\u00e4nkehe",
    "sg:phone":"+41 21 616 32 81",
    "sg:postcode":"1006",
    "sg:province":"Vaud",
    "wof:name":"Le Mirador Sa",
    "wof:placetype":"venue"
},
  "geometry": {"coordinates":[6.634733,46.510506],"type":"Point"}
}