{
  "type": "Feature",
  "properties": {
    "iso:country":"CH",
    "sg:address":"Wehntalerstrasse 564",
    "sg:city":"Z\u00fcrich",
    "sg:orig_category":"Vermietung von Gebrauchsg\u00fctern",
    "sg:phone":"+41 13716193",
    "sg:postcode":"8046",
    "sg:province":"Z\u00fcrich",
    "wof:name":"Eglish Movie Line T. Kunz",
    "wof:placetype":"venue"
},
  "geometry": {"coordinates":[8.5047492981,47.4198760986],"type":"Point"}
}