{
  "type": "Feature",
  "properties": {
    "iso:country":"CH",
    "sg:address":"Rindermarkt 11",
    "sg:city":"Z\u00fcrich",
    "sg:orig_category":"Interessenvertretungen",
    "sg:phone":"+41 12736888",
    "sg:postcode":"8001",
    "sg:province":"Z\u00fcrich",
    "wof:name":"Parate Labor Theatergenossenschaft F\u00f6rderung D. Darstellenden Kunst, Ihre Entw., Herstellung, Vermittlung Usw",
    "wof:placetype":"venue"
},
  "geometry": {"coordinates":[8.5444297791,47.3725090027],"type":"Point"}
}