{
  "type": "Feature",
  "properties": {
    "iso:country":"CH",
    "sg:address":"Beim Bahnhof",
    "sg:city":"Aathal-seegr\u00e4ben",
    "sg:classifiers":[
        {
            "category":"Restaurant",
            "type":"Food & Drink"
        }
    ],
    "sg:phone":"+41 71 744 68 44",
    "sg:postcode":"8607",
    "sg:province":"Z\u00fcrich",
    "wof:name":"American Snack Bar",
    "wof:placetype":"venue"
},
  "geometry": {"coordinates":[9.6348695755,47.4514694214],"type":"Point"}
}