{
  "type": "Feature",
  "properties": {
    "iso:country":"CH",
    "sg:address":"1542",
    "sg:city":"Rueyres-les-pr\u00e9s",
    "sg:orig_category":"Detailhandel mit M\u00f6beln",
    "sg:phone":"+41 26 667 15 72",
    "sg:postcode":"1542",
    "sg:province":"Fribourg",
    "wof:name":"Gis\u00e8le Brulhart Meubles Antiquit\u00e9s",
    "wof:placetype":"venue"
},
  "geometry": {"coordinates":[6.9126901627,46.8576507568],"type":"Point"}
}