{
  "type": "Feature",
  "properties": {
    "addr:full":"Bitsch Bitsch Valais 3982",
    "addr:housenumber":"3982",
    "iso:country":"CH",
    "sg:address":"Bitsch",
    "sg:city":"Bitsch",
    "sg:classifiers":[
        {
            "category":"Banks & Credit Unions",
            "subcategory":"Bank",
            "type":"Services"
        }
    ],
    "sg:phone":"+41 28272777",
    "sg:postcode":"3982",
    "sg:province":"Valais",
    "wof:name":"Raiffeisenbank",
    "wof:placetype":"venue"
},
  "geometry": {"coordinates":[8.014365,46.33493],"type":"Point"}
}