{
  "type": "Feature",
  "properties": {
    "iso:country":"CH",
    "sg:address":"Bahnhofstrasse 6 6003 Luzern. Postfach 3764",
    "sg:city":"Luzern",
    "sg:orig_category":"Banken sonstige",
    "sg:phone":"+41 62 834 75 75",
    "sg:postcode":"6003",
    "sg:province":"Luzern",
    "wof:name":"Migros Bank",
    "wof:placetype":"venue"
},
  "geometry": {"coordinates":[8.090435,47.386078],"type":"Point"}
}