{
  "type": "Feature",
  "properties": {
    "iso:country":"CH",
    "sg:address":"Grienbachstr. 17",
    "sg:city":"Zug",
    "sg:classifiers":[
        {
            "category":"Shopping",
            "subcategory":"Stationery & Office Supplies",
            "type":"Retail Goods"
        }
    ],
    "sg:phone":"+41 21 646 16 71",
    "sg:postcode":"6300",
    "sg:province":"Zug",
    "sg:tags":[
        "information",
        "technology",
        "telecommunication",
        "equipment"
    ],
    "wof:name":"Cardinaux Machines De Bureau Sa",
    "wof:placetype":"venue"
},
  "geometry": {"coordinates":[6.6267499924,46.5436820984],"type":"Point"}
}