{
  "type": "Feature",
  "properties": {
    "iso:country":"CH",
    "sg:address":"Promenade Du Pin 1",
    "sg:city":"Gen\u00e8ve",
    "sg:classifiers":[
        {
            "category":"Education",
            "subcategory":"Library",
            "type":"Public Place"
        }
    ],
    "sg:phone":"+41 22 310 41 88",
    "sg:postcode":"1204",
    "sg:province":"Gen\u00e8ve",
    "sg:tags":[
        "u",
        "bibliotheken",
        "archive"
    ],
    "wof:name":"Biblioth\u00e8que De La St\u00e9 Astron. Institut National Genevois",
    "wof:placetype":"venue"
},
  "geometry": {"coordinates":[6.150181,46.198635],"type":"Point"}
}