{
  "type": "Feature",
  "properties": {
    "iso:country":"CH",
    "sg:address":"Avenue Reverdil 2",
    "sg:city":"Nyon",
    "sg:orig_category":"Fachdetailhandel mit pharmazeutischen Produkten",
    "sg:phone":"+41 22 361 51 30",
    "sg:postcode":"1260",
    "sg:province":"Vaud",
    "wof:name":"Unyopharm Sa Pharmacie De La Combe",
    "wof:placetype":"venue"
},
  "geometry": {"coordinates":[6.234457016,46.382686615],"type":"Point"}
}