{
  "type": "Feature",
  "properties": {
    "iso:country":"CH",
    "sg:address":"Ebnatweg 8",
    "sg:city":"Schaffhausen",
    "sg:orig_category":"Herstellung von Karosserien U Anh\u00e4ngern",
    "sg:postcode":"8200",
    "sg:province":"Schaffhausen",
    "wof:name":"Kernen Ferdinand, Wohnwagen Und Zubeh\u00f6r",
    "wof:placetype":"venue"
},
  "geometry": {"coordinates":[7.3859891891,47.1432685852],"type":"Point"}
}