{
  "type": "Feature",
  "properties": {
    "iso:country":"CH",
    "sg:address":"Cantonale Strada",
    "sg:city":"Mezzovico",
    "sg:orig_category":"Herstellung von pharmazeutischen Grundstoffen",
    "sg:phone":"+41 91 935 91 10",
    "sg:postcode":"6805",
    "sg:province":"Ticino",
    "wof:name":"Pharma Innovation Sa",
    "wof:placetype":"venue"
},
  "geometry": {"coordinates":[8.9198827744,46.0879859924],"type":"Point"}
}