{
  "type": "Feature",
  "properties": {
    "iso:country":"CH",
    "sg:address":"Avenue Du L\u00e9man 70",
    "sg:city":"Lausanne",
    "sg:orig_category":"D\u00e4mmung gegen K\u00e4lte, W\u00e4rme, Schall U Ersch\u00fctterung Stukkateurgewerbe, Gipserei U Verputzerei",
    "sg:phone":"+41 21 728 11 09",
    "sg:postcode":"1005",
    "sg:province":"Vaud",
    "wof:name":"Delapierre Olivier.",
    "wof:placetype":"venue"
},
  "geometry": {"coordinates":[6.6536102295,46.5143013],"type":"Point"}
}