{
  "type": "Feature",
  "properties": {
    "iso:country":"CH",
    "sg:address":"6313 Menzingen. Postfach 38",
    "sg:city":"Menzingen",
    "sg:orig_category":"Verwaltung der Strafvollzuganstalten Wohnheime",
    "sg:phone":"+41 41 755 17 17",
    "sg:postcode":"6313",
    "sg:province":"Zug",
    "wof:name":"Strafanstalt Bostadel",
    "wof:placetype":"venue"
},
  "geometry": {"coordinates":[8.5906457901,47.1783485413],"type":"Point"}
}