{
  "type": "Feature",
  "properties": {
    "iso:country":"CH",
    "sg:address":"Tiguelet Chemin Du 16",
    "sg:city":"Givisiez",
    "sg:orig_category":"Unclassifiable Establishments",
    "sg:postcode":"1762",
    "sg:province":"Fribourg",
    "wof:name":"A Bis Z Bidzevic",
    "wof:placetype":"venue"
},
  "geometry": {"coordinates":[8.5046052933,47.4774971008],"type":"Point"}
}