{
  "type": "Feature",
  "properties": {
    "iso:country":"CH",
    "sg:address":"Vignerons Chemin Des 19",
    "sg:city":"Blonay",
    "sg:orig_category":"Fachdetailhandel in Verkaufsr\u00e4umen",
    "sg:phone":"+41 79 210 72 36",
    "sg:postcode":"1807",
    "sg:province":"Vaud",
    "wof:name":"Transworld Impex, Linn & Legrand",
    "wof:placetype":"venue"
},
  "geometry": {"coordinates":[6.8949828148,46.4651298523],"type":"Point"}
}