{
  "type": "Feature",
  "properties": {
    "iso:country":"CH",
    "sg:address":"Burgstr. 61 3307 Brunnenthal. Postfach",
    "sg:city":"Brunnenthal",
    "sg:orig_category":"Allgemeiner Hoch U Tiefbau",
    "sg:phone":"+41 31 765 54 84",
    "sg:postcode":"3307",
    "sg:province":"Solothurn",
    "wof:name":"Moser, Gebr.",
    "wof:placetype":"venue"
},
  "geometry": {"coordinates":[7.465927,47.085579],"type":"Point"}
}