{
  "type": "Feature",
  "properties": {
    "iso:country":"CH",
    "sg:address":"Route De Lausanne 16 1052 Mont-sur-lausanne. Postfach",
    "sg:city":"Mont-sur-lausanne",
    "sg:orig_category":"Gemeindeverwaltungen",
    "sg:phone":"+41 32 953 11 15",
    "sg:postcode":"1052",
    "sg:province":"Vaud",
    "wof:name":"Administration Communale De Le Noirmont",
    "wof:placetype":"venue"
},
  "geometry": {"coordinates":[6.9550209045,47.2249145508],"type":"Point"}
}