{
  "type": "Feature",
  "properties": {
    "iso:country":"CH",
    "sg:address":"Ch. Du Jordil 1",
    "sg:city":"Belfaux",
    "sg:orig_category":"Herstellung von konfektionierten Textilwaren ohne Bekleidung",
    "sg:phone":"+41 26 475 23 62",
    "sg:postcode":"1782",
    "sg:province":"Fribourg",
    "wof:name":"Couture Marion, Dousse Mme M.",
    "wof:placetype":"venue"
},
  "geometry": {"coordinates":[7.0972399712,46.8246803284],"type":"Point"}
}