{
  "type": "Feature",
  "properties": {
    "iso:country":"CH",
    "sg:address":"Montagne De Plagne",
    "sg:city":"Plagne",
    "sg:orig_category":"Naturheil\u00e4rzte and Heilpraktiker",
    "sg:phone":"+41 32 358 16 76",
    "sg:postcode":"2536",
    "sg:province":"Bern",
    "wof:name":"Max Schreyer Naturopathe",
    "wof:placetype":"venue"
},
  "geometry": {"coordinates":[7.2864580154,47.1881065369],"type":"Point"}
}