{
  "type": "Feature",
  "properties": {
    "iso:country":"CH",
    "sg:address":"Avenue De Milan 3",
    "sg:city":"Lausanne",
    "sg:orig_category":"G\u00fcterbef\u00f6rderung im Strassenverkehr",
    "sg:phone":"+41 79 250 23 17",
    "sg:postcode":"1007",
    "sg:province":"Vaud",
    "wof:name":"Demag Aktepe A. S\u00e0rl",
    "wof:placetype":"venue"
},
  "geometry": {"coordinates":[6.6238899231,46.5163803101],"type":"Point"}
}