{
  "type": "Feature",
  "properties": {
    "iso:country":"CH",
    "sg:address":"M\u00fchlebachweg 8",
    "sg:city":"Amriswil",
    "sg:orig_category":"Vorschulen, Kinderg\u00e4rten",
    "sg:phone":"+41 71 411 65 15",
    "sg:postcode":"8580",
    "sg:province":"Thurgau",
    "wof:name":"Kindergarten",
    "wof:placetype":"venue"
},
  "geometry": {"coordinates":[9.2785730362,47.5463027954],"type":"Point"}
}