{
  "type": "Feature",
  "properties": {
    "iso:country":"CH",
    "sg:address":"Meierhofstrasse 5 6032 Emmen. Postfach",
    "sg:city":"Emmen",
    "sg:orig_category":"Vermietung U Verpachtung von eigenen Immobilien",
    "sg:postcode":"6032",
    "sg:province":"Luzern",
    "wof:name":"Dil Internationale Leasinggesellschaft Objekt Luzer Mbh Immobilien-leasing Usw",
    "wof:placetype":"venue"
},
  "geometry": {"coordinates":[8.3037729263,47.0823020935],"type":"Point"}
}