{
  "type": "Feature",
  "properties": {
    "addr:full":"Pr\u00e9-du-march\u00e9 Rue 15 Lausanne Vaud 1004",
    "addr:housenumber":"15",
    "addr:postcode":"1004",
    "addr:street":"Rue",
    "iso:country":"CH",
    "sg:address":"Pr\u00e9-du-march\u00e9 Rue 15",
    "sg:city":"Lausanne",
    "sg:classifiers":[
        {
            "category":"Bars & Pubs",
            "type":"Food & Drink"
        }
    ],
    "sg:phone":"+41 21 312 96 87",
    "sg:postcode":"1004",
    "sg:province":"Vaud",
    "wof:name":"Diaz Servando",
    "wof:placetype":"venue"
},
  "geometry": {"coordinates":[6.629623,46.524048],"type":"Point"}
}