{
  "type": "Feature",
  "properties": {
    "addr:full":"Via Nosetto 6 Bellinzona Ticino 6500",
    "addr:housenumber":"6",
    "addr:postcode":"6500",
    "addr:street":"Via Nosetto",
    "iso:country":"CH",
    "sg:address":"Via Nosetto 6",
    "sg:city":"Bellinzona",
    "sg:orig_category":"Architekturb\u00fcros",
    "sg:phone":"+41 91 826 18 79",
    "sg:postcode":"6500",
    "sg:province":"Ticino",
    "wof:name":"Simone Comandini Eco-architetto",
    "wof:placetype":"venue"
},
  "geometry": {"coordinates":[9.022618,46.191193],"type":"Point"}
}