{
  "type": "Feature",
  "properties": {
    "iso:country":"CH",
    "sg:address":"Chelleracherstrasse 13",
    "sg:city":"K\u00fcnten",
    "sg:orig_category":"Vereine Musik/Blasmusik",
    "sg:phone":"+41 56 496 36 44",
    "sg:postcode":"5444",
    "sg:province":"Aargau",
    "wof:name":"Musikverein K\u00fcnten",
    "wof:placetype":"venue"
},
  "geometry": {"coordinates":[8.3304014206,47.3913612366],"type":"Point"}
}