{
  "type": "Feature",
  "properties": {
    "iso:country":"CH",
    "sg:address":"Ottikerweg 9",
    "sg:city":"Z\u00fcrich",
    "sg:orig_category":"Vorschulen, Kinderg\u00e4rten",
    "sg:phone":"+41 71 245 33 79",
    "sg:postcode":"8006",
    "sg:province":"Z\u00fcrich",
    "wof:name":"St\u00e4dtischer Kindergarten",
    "wof:placetype":"venue"
},
  "geometry": {"coordinates":[9.4027891159,47.4324531555],"type":"Point"}
}