{
  "type": "Feature",
  "properties": {
    "iso:country":"CH",
    "sg:address":"Hauptstrasse 26",
    "sg:city":"Ipsach",
    "sg:orig_category":"Herstellung von elektrischen Lampen U Leuchten Neonbeleuchtungsinstallation",
    "sg:phone":"+41 32 331 23 03",
    "sg:postcode":"2563",
    "sg:province":"Bern",
    "wof:name":"Jean-pierre Gueniat California-neon",
    "wof:placetype":"venue"
},
  "geometry": {"coordinates":[7.2330160141,47.114780426],"type":"Point"}
}