{
  "type": "Feature",
  "properties": {
    "iso:country":"CH",
    "sg:address":"Dottikerstrasse 33a",
    "sg:city":"Anglikon",
    "sg:orig_category":"Verlegen von Fliesen U Platten",
    "sg:phone":"+41 56 622 04 44",
    "sg:postcode":"5611",
    "sg:province":"Aargau",
    "wof:name":"Alfred Jordi Keramische Wand-& Bodenbel\u00e4ge",
    "wof:placetype":"venue"
},
  "geometry": {"coordinates":[8.2607440948,47.3658714294],"type":"Point"}
}