{
  "type": "Feature",
  "properties": {
    "iso:country":"CH",
    "sg:address":"Hohmattring 27",
    "sg:city":"Turbenthal",
    "sg:orig_category":"Unternehmensberatung",
    "sg:phone":"+41 52 397 23 23",
    "sg:postcode":"8488",
    "sg:province":"Z\u00fcrich",
    "wof:name":"Manfred Walliser Treuhandb\u00fcro",
    "wof:placetype":"venue"
},
  "geometry": {"coordinates":[8.8413600922,47.4434318542],"type":"Point"}
}