{
  "type": "Feature",
  "properties": {
    "iso:country":"CH",
    "sg:address":"Shopping Center 7052",
    "sg:city":"Spreitenbach",
    "sg:orig_category":"Non-Classified Establishments",
    "sg:phone":"+41 56 401 67 20",
    "sg:postcode":"8957",
    "sg:province":"Aargau",
    "wof:name":"Cellsan Body Concept Ag",
    "wof:placetype":"venue"
},
  "geometry": {"coordinates":[8.3683853149,47.4217185974],"type":"Point"}
}