{
  "type": "Feature",
  "properties": {
    "iso:country":"CH",
    "sg:address":"Udelbodenstrasse 43 6014 Littau. Postfach",
    "sg:city":"Littau",
    "sg:orig_category":"Allgemeiner Hoch U Tiefbau",
    "sg:postcode":"6014",
    "sg:province":"Luzern",
    "wof:name":"Petek Vladimir",
    "wof:placetype":"venue"
},
  "geometry": {"coordinates":[8.281369,47.053555],"type":"Point"}
}