{
  "type": "Feature",
  "properties": {
    "addr:full":"Unterhaus 30 Oberdiessbach Bern 3672",
    "addr:housenumber":"30",
    "addr:postcode":"3672",
    "addr:street":"Unterhaus",
    "iso:country":"CH",
    "sg:address":"Unterhaus 30",
    "sg:city":"Oberdiessbach",
    "sg:orig_category":"Dachdeckerei Zimmerei, Dachdeckerei, Bauspenglerei U Abdichtung",
    "sg:phone":"+41 31 771 02 89",
    "sg:postcode":"3672",
    "sg:province":"Bern",
    "wof:name":"Kauz Bedachungen Gmbh",
    "wof:placetype":"venue"
},
  "geometry": {"coordinates":[7.629127,46.8279],"type":"Point"}
}