{
  "type": "Feature",
  "properties": {
    "iso:country":"CH",
    "sg:address":"Ecusson Vaudois 1410 Thierrens. Postfach",
    "sg:city":"Thierrens",
    "sg:orig_category":"RESTAURANTS: TEA-ROOMS",
    "sg:postcode":"1410",
    "sg:province":"Vaud",
    "wof:name":"Pizzeria De L'ecusson Vaudois, Rodrigues Laurindo",
    "wof:placetype":"venue"
},
  "geometry": {"coordinates":[6.7543702126,46.7039604187],"type":"Point"}
}