{
  "type": "Feature",
  "properties": {
    "iso:country":"CH",
    "sg:address":"Plaz 111",
    "sg:city":"Zernez",
    "sg:orig_category":"Allgemeiner Hoch U Tiefbau Allgemeiner Hochbau",
    "sg:phone":"+41 81 856 11 66",
    "sg:postcode":"7530",
    "sg:province":"Graubunden",
    "wof:name":"Hew Ag Bauunternehmung Chur",
    "wof:placetype":"venue"
},
  "geometry": {"coordinates":[10.094984,46.701309],"type":"Point"}
}