{
  "type": "Feature",
  "properties": {
    "iso:country":"CH",
    "sg:address":"Hauptstrasse 92",
    "sg:city":"Kreuzlingen",
    "sg:orig_category":"Gartenbau Kauf U Verkauf von Immobilien auf eigene Rechnung",
    "sg:phone":"+41 81 911 34 76",
    "sg:postcode":"8280",
    "sg:province":"Thurgau",
    "wof:name":"Berger-immobilien Ag",
    "wof:placetype":"venue"
},
  "geometry": {"coordinates":[8.5392112732,47.3154029846],"type":"Point"}
}