{
  "type": "Feature",
  "properties": {
    "iso:country":"CH",
    "sg:address":"Azenwiese Schlattingen 8254 Basadingen. Postfach",
    "sg:city":"Schlattingen",
    "sg:orig_category":"Vermietung U Verpachtung von eigenen Immobilien",
    "sg:phone":"+41 52 657 26 78",
    "sg:postcode":"8255",
    "sg:province":"Thurgau",
    "wof:name":"Figu Gmbh",
    "wof:placetype":"venue"
},
  "geometry": {"coordinates":[8.7497997284,47.6682281494],"type":"Point"}
}