{
  "type": "Feature",
  "properties": {
    "iso:country":"CH",
    "sg:address":"Piazzetta Luigi Fontana 5",
    "sg:city":"Mendrisio",
    "sg:orig_category":"Werbeagenturen Werbegrafikateliers",
    "sg:phone":"+41 91 646 10 60",
    "sg:postcode":"6850",
    "sg:province":"Ticino",
    "wof:name":"Antonia & Cecilia Bremer Studio Grafico & Pubblicitario",
    "wof:placetype":"venue"
},
  "geometry": {"coordinates":[8.9877252579,45.8714103699],"type":"Point"}
}