{
  "type": "Feature",
  "properties": {
    "addr:full":"Arisd\u00f6rferstrasse 87a 4410 Liestal. Postfach Liestal Basel-Landschaft 4410",
    "addr:housenumber":"87a",
    "addr:postcode":"4410 liestal. postfach;4410",
    "addr:street":"Arisdoerferstrasse",
    "iso:country":"CH",
    "sg:address":"Arisd\u00f6rferstrasse 87a 4410 Liestal. Postfach",
    "sg:city":"Liestal",
    "sg:orig_category":"Betrieb von Taxis",
    "sg:phone":"+41 61 922 11 11",
    "sg:postcode":"4410",
    "sg:province":"Basel-Landschaft",
    "wof:name":"Kleinrath Ag",
    "wof:placetype":"venue"
},
  "geometry": {"coordinates":[7.750286,47.483429],"type":"Point"}
}