{
  "type": "Feature",
  "properties": {
    "iso:country":"CH",
    "sg:address":"Staffelenweg 16 4460 Gelterkinden. Postfach",
    "sg:city":"Gelterkinden",
    "sg:orig_category":"Unclassifiable Establishments",
    "sg:postcode":"4460",
    "sg:province":"Basel-Landschaft",
    "wof:name":"Gartenbau Herger Gmbh",
    "wof:placetype":"venue"
},
  "geometry": {"coordinates":[8.6302995682,47.0264511108],"type":"Point"}
}