{
  "type": "Feature",
  "properties": {
    "iso:country":"CH",
    "sg:address":"Chalet La Godille",
    "sg:city":"Morgins",
    "sg:orig_category":"Malerei",
    "sg:phone":"+41 24 477 14 72",
    "sg:postcode":"1875",
    "sg:province":"Valais",
    "wof:name":"Hermann Schwery Entreprise De Peinture",
    "wof:placetype":"venue"
},
  "geometry": {"coordinates":[6.8587532043,46.2375221252],"type":"Point"}
}