{
  "type": "Feature",
  "properties": {
    "iso:country":"CH",
    "sg:address":"Mitteldorfstrasse 7",
    "sg:city":"Ostermundigen",
    "sg:orig_category":"Herstellung von Musikinstrumenten",
    "sg:phone":"+41 31 931 32 91",
    "sg:postcode":"3072",
    "sg:province":"Bern",
    "wof:name":"Helmuth Lau Klavierbau-atelier",
    "wof:placetype":"venue"
},
  "geometry": {"coordinates":[7.4907121658,46.9571800232],"type":"Point"}
}