{
  "type": "Feature",
  "properties": {
    "iso:country":"CH",
    "sg:address":"Ferggerstrasse 5 9444 Diepoldsau. Postfach 38",
    "sg:city":"Diepoldsau",
    "sg:orig_category":"Softwareentwicklung U beratung",
    "sg:phone":"+41 71 730 03 00",
    "sg:postcode":"9444",
    "sg:province":"St. Gallen",
    "wof:name":"Th. B\u00e4nziger Informatik Gmbh",
    "wof:placetype":"venue"
},
  "geometry": {"coordinates":[9.6537761688,47.3820419312],"type":"Point"}
}