{
  "type": "Feature",
  "properties": {
    "iso:country":"CH",
    "sg:address":"Alosenstrasse 2",
    "sg:city":"Ober\u00e4geri",
    "sg:orig_category":"Zahnarztpraxen",
    "sg:phone":"+41 41 750 50 59",
    "sg:postcode":"6315",
    "sg:province":"Zug",
    "wof:name":"Dr. Med. Dent. Paul Oesch Zahnarzt",
    "wof:placetype":"venue"
},
  "geometry": {"coordinates":[8.6154346466,47.1351966858],"type":"Point"}
}