{
  "type": "Feature",
  "properties": {
    "addr:full":"Moulin-du-choc D Romanel-sur-morges Vaud 1122",
    "addr:housenumber":"1122",
    "iso:country":"CH",
    "sg:address":"Moulin-du-choc D",
    "sg:city":"Romanel-sur-morges",
    "sg:classifiers":[
        {
            "category":"Government",
            "subcategory":"Fire Station",
            "type":"Public Place"
        }
    ],
    "sg:phone":"+41 21 869 97 73",
    "sg:postcode":"1122",
    "sg:province":"Vaud",
    "sg:tags":[
        "alloy",
        "light",
        "aluminium",
        "processing"
    ],
    "wof:name":"Fran\u00e7ois De Bellis",
    "wof:placetype":"venue"
},
  "geometry": {"coordinates":[6.526441,46.56134],"type":"Point"}
}