{
  "type": "Feature",
  "properties": {
    "iso:country":"CH",
    "sg:address":"Rue Du Midi 2",
    "sg:city":"Gland",
    "sg:orig_category":"Stukkateurgewerbe, Gipserei U Verputzerei",
    "sg:postcode":"1196",
    "sg:province":"Vaud",
    "wof:name":"Dutoit Claude",
    "wof:placetype":"venue"
},
  "geometry": {"coordinates":[6.2717328072,46.4175949097],"type":"Point"}
}