{
  "type": "Feature",
  "properties": {
    "iso:country":"CH",
    "sg:address":"Bella Riva 4",
    "sg:city":"Capolago",
    "sg:orig_category":"Handels-H\u00e4user U Gesellschaften",
    "sg:postcode":"6825",
    "sg:province":"Ticino",
    "wof:name":"Ribbonbill Ltd, Croydon, Succursale Di Capolago",
    "wof:placetype":"venue"
},
  "geometry": {"coordinates":[8.9830350876,45.9078674316],"type":"Point"}
}