{
  "type": "Feature",
  "properties": {
    "iso:country":"CH",
    "sg:address":"Langackerstrasse 3",
    "sg:city":"M\u00fcnchenstein",
    "sg:orig_category":"Detailhandel mit Waren verschiedener Art, Hauptrichtung Nahrungsmittel",
    "sg:phone":"+41 61 411 76 70",
    "sg:postcode":"4142",
    "sg:province":"Basel-Landschaft",
    "wof:name":"Denner Top Superdiscount",
    "wof:placetype":"venue"
},
  "geometry": {"coordinates":[7.6166758537,47.5230560303],"type":"Point"}
}