{
  "type": "Feature",
  "properties": {
    "iso:country":"CH",
    "sg:address":"Holzhausen 201",
    "sg:city":"Gr\u00fcningen",
    "sg:orig_category":"Herstellung von sonstigen landwirtschaftlichen Maschinen",
    "sg:phone":"+41 62 771 41 51",
    "sg:postcode":"8627",
    "sg:province":"Z\u00fcrich",
    "wof:name":"Hauri Hans",
    "wof:placetype":"venue"
},
  "geometry": {"coordinates":[8.181977272,47.2636566162],"type":"Point"}
}