{
  "type": "Feature",
  "properties": {
    "iso:country":"CH",
    "sg:address":"Via Besso 41",
    "sg:city":"Lugano",
    "sg:orig_category":"Finanzierungsinstitutionen",
    "sg:postcode":"6900",
    "sg:province":"Ticino",
    "wof:name":"Muratore Giorgio",
    "wof:placetype":"venue"
},
  "geometry": {"coordinates":[8.9394950867,46.009147644],"type":"Point"}
}