{
  "type": "Feature",
  "properties": {
    "iso:country":"CH",
    "sg:address":"Wiler Strasse 83",
    "sg:city":"Bazenheid",
    "sg:orig_category":"Bau U Wohngenossenschaften",
    "sg:phone":"+41 71 931 16 05",
    "sg:postcode":"9602",
    "sg:province":"St. Gallen",
    "wof:name":"Genossenschaft F\u00fcr Landwirtschaftliches Bauen",
    "wof:placetype":"venue"
},
  "geometry": {"coordinates":[9.062227,47.419586],"type":"Point"}
}