{
  "type": "Feature",
  "properties": {
    "iso:country":"CH",
    "sg:address":"Broteggstrasse 16",
    "sg:city":"Frauenfeld",
    "sg:orig_category":"Architektur U Ingenieurb\u00fcros",
    "sg:phone":"+41 52 722 11 16",
    "sg:postcode":"8500",
    "sg:province":"Thurgau",
    "wof:name":"Hans Moser, Ingenieur Htl",
    "wof:placetype":"venue"
},
  "geometry": {"coordinates":[8.90479,47.551933],"type":"Point"}
}