{
  "type": "Feature",
  "properties": {
    "iso:country":"CH",
    "sg:address":"Klarastrasse 2",
    "sg:city":"Allschwil",
    "sg:orig_category":"Bauschreinerei Herstellung von Konstruktionsteilen, Fertigbauteilen U Ausbauelementen aus Holz",
    "sg:phone":"+41 61 481 08 40",
    "sg:postcode":"4123",
    "sg:province":"Basel-Landschaft",
    "wof:name":"Holzbau Allschwil & Basel Ag",
    "wof:placetype":"venue"
},
  "geometry": {"coordinates":[7.536028,47.552326],"type":"Point"}
}