{
  "type": "Feature",
  "properties": {
    "iso:country":"CH",
    "sg:address":"R\u00f6hrliberg 4",
    "sg:city":"Cham",
    "sg:classifiers":[
        {
            "category":"Banks & Credit Unions",
            "subcategory":"Investment Brokerage",
            "type":"Services"
        }
    ],
    "sg:phone":"+41 41 780 13 86",
    "sg:postcode":"6330",
    "sg:province":"Zug",
    "sg:tags":[
        "cnc",
        "milling"
    ],
    "wof:name":"Arcuri Gmbh",
    "wof:placetype":"venue"
},
  "geometry": {"coordinates":[8.454608,47.184898],"type":"Point"}
}