{
  "type": "Feature",
  "properties": {
    "iso:country":"CH",
    "sg:address":"Pestalozzi Rue 5",
    "sg:city":"Gen\u00e8ve",
    "sg:orig_category":"Non-Classified Establishments",
    "sg:postcode":"1202",
    "sg:province":"Gen\u00e8ve",
    "wof:name":"Transports Germanier Collombey-muraz S\u00e0rl Entreprise De Transport De Marchandises, De Mat\u00e9riaux En Tout Genres Etc",
    "wof:placetype":"venue"
},
  "geometry": {"coordinates":[6.9263191223,46.2791175842],"type":"Point"}
}