{
  "type": "Feature",
  "properties": {
    "iso:country":"CH",
    "sg:address":"Scie Route De La 12",
    "sg:city":"Estavayer-le-lac",
    "sg:orig_category":"Sanit\u00e4r, Heizungs U L\u00fcftungsinstallation",
    "sg:phone":"+41 79 412 76 52",
    "sg:postcode":"1470",
    "sg:province":"Fribourg",
    "wof:name":"Daniel Ansermet S\u00e0rl",
    "wof:placetype":"venue"
},
  "geometry": {"coordinates":[6.8482789993,46.8487930298],"type":"Point"}
}