{
  "type": "Feature",
  "properties": {
    "iso:country":"CH",
    "sg:address":"Hauptstrasse 12b 4552 Derendingen. Postfach",
    "sg:city":"Derendingen",
    "sg:orig_category":"Verwaltung von Immobilien",
    "sg:postcode":"4552",
    "sg:province":"Solothurn",
    "wof:name":"Rudin Immobilien-verwaltung Immobilien Usw",
    "wof:placetype":"venue"
},
  "geometry": {"coordinates":[7.582775116,47.1984405518],"type":"Point"}
}