{
  "type": "Feature",
  "properties": {
    "iso:country":"CH",
    "sg:address":"Klosterstrasse 9",
    "sg:city":"Engelberg",
    "sg:orig_category":"Wirtschaftspr\u00fcfung, Steuerberatung U Treuhand",
    "sg:phone":"+41 41 639 60 79",
    "sg:postcode":"6390",
    "sg:province":"Obwalden",
    "wof:name":"Ettlin Sepp Treuhand",
    "wof:placetype":"venue"
},
  "geometry": {"coordinates":[8.4059400558,46.820514679],"type":"Point"}
}