{
  "type": "Feature",
  "properties": {
    "iso:country":"CH",
    "sg:address":"Kirchweg 1",
    "sg:city":"Grellingen",
    "sg:orig_category":"Grosshandel mit sonstigen Maschinen U Ausr\u00fcstungen f\u00fcr Industrie, Handel U Schiffahrt Reparatur von ",
    "sg:postcode":"4203",
    "sg:province":"Basel-Landschaft",
    "wof:name":"Anton H\u00e4ssig Disco Sound & Light Material",
    "wof:placetype":"venue"
},
  "geometry": {"coordinates":[7.5870528221,47.4419898987],"type":"Point"}
}