{
  "type": "Feature",
  "properties": {
    "iso:country":"CH",
    "sg:address":"Rohrstrasse 29",
    "sg:city":"Biglen",
    "sg:orig_category":"Detailhandel mit Fahrr\u00e4dern Handel mit Motorr\u00e4dern, Teilen U Zubeh\u00f6r Instandhaltung U Reparatur von ",
    "sg:phone":"+41 31 701 02 10",
    "sg:postcode":"3507",
    "sg:province":"Bern",
    "wof:name":"Ernst Hasler Velos-motos",
    "wof:placetype":"venue"
},
  "geometry": {"coordinates":[7.6243920326,46.9265785217],"type":"Point"}
}