{
  "type": "Feature",
  "properties": {
    "iso:country":"CH",
    "sg:address":"Scheibenstrasse 29 3000 Bern. Postfach",
    "sg:city":"Bern",
    "sg:orig_category":"Finanzierungsinstitutionen",
    "sg:postcode":"3005",
    "sg:province":"Bern",
    "wof:name":"Meditec Nova Gmbh",
    "wof:placetype":"venue"
},
  "geometry": {"coordinates":[7.4531040192,46.9613685608],"type":"Point"}
}