{
  "type": "Feature",
  "properties": {
    "iso:country":"CH",
    "sg:address":"Hinterdorfstrasse 38 B",
    "sg:city":"Mollis",
    "sg:orig_category":"Vermittlung von Immobilien Verwaltung von Immobilien",
    "sg:phone":"+41 55 612 36 30",
    "sg:postcode":"8753",
    "sg:province":"Glarus",
    "wof:name":"Schimmob Ag Immobilien & Treuhand",
    "wof:placetype":"venue"
},
  "geometry": {"coordinates":[9.0756559372,47.0975379944],"type":"Point"}
}