{
  "type": "Feature",
  "properties": {
    "iso:country":"CH",
    "sg:address":"Gorenmattstrasse 6 4102 Binningen. Postfach",
    "sg:city":"Binningen",
    "sg:orig_category":"Allgemeiner Hoch U Tiefbau",
    "sg:phone":"+41 71 912 40 40",
    "sg:postcode":"4102",
    "sg:province":"Basel-Landschaft",
    "wof:name":"Rohrbiegerei Bommer Ag",
    "wof:placetype":"venue"
},
  "geometry": {"coordinates":[9.033879,47.460648],"type":"Point"}
}