{
  "type": "Feature",
  "properties": {
    "iso:country":"CH",
    "sg:address":"Ceneri Via Monte",
    "sg:city":"Cadenazzo",
    "sg:orig_category":"Detailhandel mit Teppichen Verlegen von Fussboden",
    "sg:phone":"+41 91 858 33 67",
    "sg:postcode":"6593",
    "sg:province":"Ticino",
    "wof:name":"Isidori Pavimenti Posa Pavimenti In Legno, Pvc, Gomma Ecc",
    "wof:placetype":"venue"
},
  "geometry": {"coordinates":[8.9471187592,46.1516571045],"type":"Point"}
}