{
  "type": "Feature",
  "properties": {
    "addr:full":"Friesenbergstrasse 98 Z\u00fcrich Z\u00fcrich 8055",
    "addr:housenumber":"98",
    "addr:postcode":"8055",
    "addr:street":"Friesenbergstrasse",
    "iso:country":"CH",
    "sg:address":"Friesenbergstrasse 98",
    "sg:city":"Z\u00fcrich",
    "sg:orig_category":"Architektur U Ingenieurb\u00fcros",
    "sg:postcode":"8055",
    "sg:province":"Z\u00fcrich",
    "wof:name":"D K Planungs Und Beratungs-gmbh",
    "wof:placetype":"venue"
},
  "geometry": {"coordinates":[8.510215,47.366283],"type":"Point"}
}