{
  "type": "Feature",
  "properties": {
    "iso:country":"CH",
    "sg:address":"Cantonale Via 10",
    "sg:city":"Savosa",
    "sg:orig_category":"Handelsvermittlung von Brennstoffen, Erzen, Metallen U Chemikalien",
    "sg:postcode":"6942",
    "sg:province":"Ticino",
    "wof:name":"Danmon Llc, Houston, Succursale Di Savosa",
    "wof:placetype":"venue"
},
  "geometry": {"coordinates":[8.9505434036,46.0234375],"type":"Point"}
}