{
  "type": "Feature",
  "properties": {
    "iso:country":"CH",
    "sg:address":"Enzenb\u00fchlstrasse 64",
    "sg:city":"Z\u00fcrich",
    "sg:orig_category":"Mit dem Versicherungsgewerbe verbundene T\u00e4tigkeiten",
    "sg:phone":"+41 14222220",
    "sg:postcode":"8032",
    "sg:province":"Z\u00fcrich",
    "wof:name":"R. Ambauen Jota Consult",
    "wof:placetype":"venue"
},
  "geometry": {"coordinates":[8.5767240524,47.3498077393],"type":"Point"}
}