{
  "type": "Feature",
  "properties": {
    "iso:country":"CH",
    "sg:address":"Vorderdorfstrasse 26",
    "sg:city":"Mollis",
    "sg:orig_category":"P\u00e9dicure",
    "sg:phone":"+41 55 612 48 39",
    "sg:postcode":"8753",
    "sg:province":"Glarus",
    "wof:name":"Andrea Zwicky P\u00e9dicure",
    "wof:placetype":"venue"
},
  "geometry": {"coordinates":[9.074637413,47.091583252],"type":"Point"}
}