{
  "type": "Feature",
  "properties": {
    "iso:country":"CH",
    "sg:address":"Sankt Gallerstr. 188",
    "sg:city":"Winterthur",
    "sg:classifiers":[
        {
            "category":"Professional",
            "type":"Services"
        }
    ],
    "sg:phone":"+41 52 235 17 00",
    "sg:postcode":"8404",
    "sg:province":"Z\u00fcrich",
    "sg:tags":[
        "transport",
        "road"
    ],
    "wof:name":"Thalmann Logistik Ag",
    "wof:placetype":"venue"
},
  "geometry": {"coordinates":[8.75822258,47.5065689087],"type":"Point"}
}