{
  "type": "Feature",
  "properties": {
    "iso:country":"CH",
    "sg:address":"Rainstrasse 8",
    "sg:city":"Jona",
    "sg:orig_category":"Sanit\u00e4r, Heizungs U L\u00fcftungsinstallation",
    "sg:postcode":"8645",
    "sg:province":"St. Gallen",
    "wof:name":"R\u00fcefa - Cantoni Haustechnik Ag",
    "wof:placetype":"venue"
},
  "geometry": {"coordinates":[8.2701711655,47.3585357666],"type":"Point"}
}