{
  "type": "Feature",
  "properties": {
    "iso:country":"CH",
    "sg:address":"Hauptstrasse 48 6436 Muotathal. Postfach 142",
    "sg:city":"Muotathal",
    "sg:orig_category":"Gemeindeverwaltungen",
    "sg:phone":"+41 41 830 11 07",
    "sg:postcode":"6436",
    "sg:province":"Schwyz",
    "wof:name":"Gemeindeverwaltung Muotathal",
    "wof:placetype":"venue"
},
  "geometry": {"coordinates":[8.7577676773,46.9740447998],"type":"Point"}
}