{
  "type": "Feature",
  "properties": {
    "iso:country":"CH",
    "sg:address":"Lochgasse 5",
    "sg:city":"Gr\u00e4nichen",
    "sg:orig_category":"Detailhandel mit Waren verschiedener Art, Hauptrichtung Nahrungsmittel",
    "sg:phone":"+41 62 842 38 23",
    "sg:postcode":"5722",
    "sg:province":"Aargau",
    "wof:name":"Salvatore Lumetta Lebensmittel",
    "wof:placetype":"venue"
},
  "geometry": {"coordinates":[8.0972957611,47.3587303162],"type":"Point"}
}