{
  "type": "Feature",
  "properties": {
    "iso:country":"CH",
    "sg:address":"Sulgeneckstrasse 37",
    "sg:city":"Bern",
    "sg:orig_category":"Architektur U Ingenieurb\u00fcros Architekturb\u00fcros",
    "sg:phone":"+41 31 381 50 22",
    "sg:postcode":"3007",
    "sg:province":"Bern",
    "wof:name":"Briner & Hagen Architekten Ag",
    "wof:placetype":"venue"
},
  "geometry": {"coordinates":[7.43775,46.942169],"type":"Point"}
}