{
  "type": "Feature",
  "properties": {
    "iso:country":"CH",
    "sg:address":"Avenue Du Temple 35",
    "sg:city":"Lausanne",
    "sg:orig_category":"Fahrschulen, Flugschulen",
    "sg:phone":"+41 79 250 57 57",
    "sg:postcode":"1012",
    "sg:province":"Vaud",
    "wof:name":"C\u00e9line Graf Auto-\u00e9cole Chailly",
    "wof:placetype":"venue"
},
  "geometry": {"coordinates":[6.650592804,46.5310287476],"type":"Point"}
}