{
  "type": "Feature",
  "properties": {
    "iso:country":"CH",
    "sg:address":"Schlosstalstrasse 210 8408 Winterthur. Postfach 351",
    "sg:city":"Winterthur",
    "sg:orig_category":"Buchverlag Verlagsgewerbe",
    "sg:phone":"+41 52 224 01 30",
    "sg:postcode":"8401",
    "sg:province":"Z\u00fcrich",
    "wof:name":"Edition Salz&pfeffer Ag",
    "wof:placetype":"venue"
},
  "geometry": {"coordinates":[8.686423,47.505154],"type":"Point"}
}