{
  "type": "Feature",
  "properties": {
    "iso:country":"CH",
    "sg:address":"Sihlfeldstrasse 32",
    "sg:city":"Z\u00fcrich",
    "sg:orig_category":"Herstellung U Veredlung von sonstigem Glas Herstellung von Metallerzeugnissen ohne Maschinenbau",
    "sg:phone":"+41 14637775",
    "sg:postcode":"8003",
    "sg:province":"Z\u00fcrich",
    "wof:name":"Christoffel Labor Und Betriebstechnik",
    "wof:placetype":"venue"
},
  "geometry": {"coordinates":[8.5170984268,47.374332428],"type":"Point"}
}