{
  "type": "Feature",
  "properties": {
    "iso:country":"CH",
    "sg:address":"Thunstrasse 73",
    "sg:city":"Bern",
    "sg:orig_category":"Reiseb\u00fcros U Reiseveranstalter",
    "sg:phone":"+41 31565858",
    "sg:postcode":"3006",
    "sg:province":"Bern",
    "wof:name":"Tourist-travel Prag Gmbh",
    "wof:placetype":"venue"
},
  "geometry": {"coordinates":[7.4613819122,46.9410057068],"type":"Point"}
}