{
  "type": "Feature",
  "properties": {
    "iso:country":"CH",
    "sg:address":"Via Bezzola 9",
    "sg:city":"Campione",
    "sg:classifiers":[
        {
            "category":"Restaurant",
            "type":"Food & Drink"
        }
    ],
    "sg:phone":"+41 91 996 23 01",
    "sg:postcode":"6911",
    "sg:province":"Ticino",
    "wof:name":"Ristorante La Sorgente",
    "wof:placetype":"venue"
},
  "geometry": {"coordinates":[8.9249000549,45.9329681396],"type":"Point"}
}