{
  "type": "Feature",
  "properties": {
    "iso:country":"CH",
    "sg:address":"Mutschellenstrasse 19",
    "sg:city":"Bellikon",
    "sg:orig_category":"Abwasserreinigung",
    "sg:phone":"+41 56 496 25 70",
    "sg:postcode":"5454",
    "sg:province":"Aargau",
    "wof:name":"Kl\u00e4ranlage K\u00fcnten-bellikon Gemeindeverwaltung",
    "wof:placetype":"venue"
},
  "geometry": {"coordinates":[8.345606,47.387371],"type":"Point"}
}