{
  "type": "Feature",
  "properties": {
    "iso:country":"CH",
    "sg:address":"Obere Leihofstrasse 41",
    "sg:city":"W\u00e4denswil",
    "sg:classifiers":[
        {
            "category":"Insurance",
            "subcategory":"Insurance Agent",
            "type":"Services"
        }
    ],
    "sg:phone":"+41 79 419 27 23",
    "sg:postcode":"8820",
    "sg:province":"Z\u00fcrich",
    "sg:tags":[
        "versicherungsagenturen",
        "-broker"
    ],
    "wof:name":"Basler Versicherungen Agentur Robert Flammer",
    "wof:placetype":"venue"
},
  "geometry": {"coordinates":[8.6666212082,47.2224082947],"type":"Point"}
}