{
  "type": "Feature",
  "properties": {
    "iso:country":"CH",
    "sg:address":"Route De Chalais 37",
    "sg:city":"Vercorin",
    "sg:orig_category":"Vermittlung von Immobilien",
    "sg:phone":"+41 27 281 23 33",
    "sg:postcode":"3967",
    "sg:province":"Valais",
    "wof:name":"Jean-louis & Freddy Rudaz Agence Immobili\u00e8re",
    "wof:placetype":"venue"
},
  "geometry": {"coordinates":[7.3860898018,46.184841156],"type":"Point"}
}