{
  "type": "Feature",
  "properties": {
    "iso:country":"CH",
    "sg:address":"Vi 320 7550 Scuol. Postfach",
    "sg:city":"Scuol",
    "sg:orig_category":"Technische, physikalische U chemische Untersuchung",
    "sg:postcode":"7550",
    "sg:province":"Graubunden",
    "wof:name":"Mathis + Nesa, B\u00fcro D'indschegners Forestals Ingenieurdienstleistungen Im Bereiche Wald, \u00d6kologie U. Umwelt",
    "wof:placetype":"venue"
},
  "geometry": {"coordinates":[10.3003044128,46.7983779907],"type":"Point"}
}