{
  "type": "Feature",
  "properties": {
    "iso:country":"CH",
    "sg:address":"6527",
    "sg:city":"Lodrino",
    "sg:orig_category":"Diskotheken, Dancings, Night Clubs",
    "sg:phone":"+41 91 863 35 95",
    "sg:postcode":"6527",
    "sg:province":"Ticino",
    "wof:name":"Night-club Euronotte",
    "wof:placetype":"venue"
},
  "geometry": {"coordinates":[8.9811306,46.2996673584],"type":"Point"}
}