{
  "type": "Feature",
  "properties": {
    "iso:country":"CH",
    "sg:address":"M\u00fchleweg 2",
    "sg:city":"Naters",
    "sg:classifiers":[
        {
            "category":"Food & Beverages",
            "subcategory":"Groceries & Convenience Stores",
            "type":"Retail Goods"
        }
    ],
    "sg:phone":"+41 27 922 16 65",
    "sg:postcode":"3904",
    "sg:province":"Valais",
    "sg:tags":[
        "product",
        "grain",
        "cereal",
        "related"
    ],
    "wof:name":"Gebr Augsburger Ag",
    "wof:placetype":"venue"
},
  "geometry": {"coordinates":[7.986036,46.320988],"type":"Point"}
}