{
  "type": "Feature",
  "properties": {
    "iso:country":"CH",
    "sg:address":"Sauverny Route De 8",
    "sg:city":"Versoix",
    "sg:orig_category":"Interessenvertretungen",
    "sg:postcode":"1290",
    "sg:province":"Gen\u00e8ve",
    "wof:name":"Fondation De La Confr\u00e9rie Des Vignerons De Vevey",
    "wof:placetype":"venue"
},
  "geometry": {"coordinates":[12.5734100342,42.5029983521],"type":"Point"}
}