{
  "type": "Feature",
  "properties": {
    "iso:country":"CH",
    "sg:address":"Friedenstrasse 29",
    "sg:city":"Bischofszell",
    "sg:orig_category":"Schulpflegen",
    "sg:phone":"+41 71 422 44 04",
    "sg:postcode":"9220",
    "sg:province":"Thurgau",
    "wof:name":"Oberstufengemeinde",
    "wof:placetype":"venue"
},
  "geometry": {"coordinates":[9.2492332458,47.4933624268],"type":"Point"}
}