{
  "type": "Feature",
  "properties": {
    "iso:country":"CH",
    "sg:address":"Grienackerweg 14",
    "sg:city":"Breitenbach",
    "sg:orig_category":"Kaufm\u00e4nnische Berufsschulen",
    "sg:phone":"+41 61 781 33 32",
    "sg:postcode":"4226",
    "sg:province":"Solothurn",
    "wof:name":"Kaufm.berufsschule Breitenbach",
    "wof:placetype":"venue"
},
  "geometry": {"coordinates":[7.5388112068,47.4087295532],"type":"Point"}
}