{
  "type": "Feature",
  "properties": {
    "iso:country":"CH",
    "sg:address":"Neugasse 24a",
    "sg:city":"Baar",
    "sg:orig_category":"M\u00f6belschreinerei M\u00f6belveredelung U restaurierung",
    "sg:phone":"+41 41 761 46 36",
    "sg:postcode":"6340",
    "sg:province":"Zug",
    "wof:name":"Hansj\u00f6rg Baumann Antik-& M\u00f6belschreinerei",
    "wof:placetype":"venue"
},
  "geometry": {"coordinates":[8.5227279663,47.1977233887],"type":"Point"}
}