{
  "type": "Feature",
  "properties": {
    "iso:country":"CH",
    "sg:address":"Chemin Du Creux-de-rave 5bis",
    "sg:city":"Orbe",
    "sg:orig_category":"Grosshandel mit Holz U Baustoffen Handelsvermittlung von Holz U Baustoffen",
    "sg:phone":"+41 24 441 42 51",
    "sg:postcode":"1350",
    "sg:province":"Vaud",
    "wof:name":"Cmcb - Christian Michoud Commerce De Bois S\u00e0rl",
    "wof:placetype":"venue"
},
  "geometry": {"coordinates":[6.5250220299,46.7162437439],"type":"Point"}
}