{
  "type": "Feature",
  "properties": {
    "iso:country":"CH",
    "sg:address":"Zentweg 3 3006 Bern. Postfach 6536",
    "sg:city":"Bern",
    "sg:orig_category":"Bauschreinerei Pensionskassen",
    "sg:phone":"+41 31 938 43 43",
    "sg:postcode":"3001",
    "sg:province":"Bern",
    "wof:name":"Personalvorsorgestiftung Der Herzog Bau Und Holzbau Ag",
    "wof:placetype":"venue"
},
  "geometry": {"coordinates":[7.472623,46.959026],"type":"Point"}
}