{
  "type": "Feature",
  "properties": {
    "iso:country":"CH",
    "sg:address":"Chemin De La Ruite 15",
    "sg:city":"Meinier",
    "sg:orig_category":"Physiotherapie",
    "sg:phone":"+41 22 752 41 14",
    "sg:postcode":"1252",
    "sg:province":"Gen\u00e8ve",
    "wof:name":"Physio-meinier",
    "wof:placetype":"venue"
},
  "geometry": {"coordinates":[6.2347230911,46.2482566833],"type":"Point"}
}