{
  "type": "Feature",
  "properties": {
    "iso:country":"CH",
    "sg:address":"Sempacherstrasse 15 8032 Z\u00fcrich. Postfach 8032 Z\u00fcrich",
    "sg:city":"Zust",
    "sg:orig_category":"Interessenvertretungen Wohnheime f\u00fcr Kinder U Jugendliche",
    "sg:phone":"+41 32 913 16 14",
    "sg:postcode":"32",
    "wof:name":"Fondation Jeanne-antide",
    "wof:placetype":"venue"
},
  "geometry": {"coordinates":[6.8185510635,47.0973739624],"type":"Point"}
}