{
  "type": "Feature",
  "properties": {
    "iso:country":"CH",
    "sg:address":"Clochettes Chemin Des 14 1206 Gen\u00e8ve. Postfach",
    "sg:city":"Gen\u00e8ve",
    "sg:orig_category":"Werbung",
    "sg:phone":"+41 19105510",
    "sg:postcode":"1201",
    "sg:province":"Gen\u00e8ve",
    "wof:name":"Infoplus Ag Mediaservice",
    "wof:placetype":"venue"
},
  "geometry": {"coordinates":[8.5926322937,47.3106803894],"type":"Point"}
}