{
  "type": "Feature",
  "properties": {
    "iso:country":"CH",
    "sg:address":"Rickenstrasse 28 9630 Wattwil. Postfach",
    "sg:city":"Lichtensteig",
    "sg:orig_category":"Grosshandel mit Getr\u00e4nken",
    "sg:postcode":"9620",
    "sg:province":"St. Gallen",
    "wof:name":"Getr\u00e4nke Haab",
    "wof:placetype":"venue"
},
  "geometry": {"coordinates":[9.0853939056,47.2993392944],"type":"Point"}
}