{
  "type": "Feature",
  "properties": {
    "iso:country":"CH",
    "sg:address":"Sitterh\u00f6fli 9032 Engelburg. Postfach",
    "sg:city":"Engelburg",
    "sg:orig_category":"Zimmerei, Dachdeckerei, Bauspenglerei U Abdichtung",
    "sg:phone":"+41 71 277 75 35",
    "sg:postcode":"9032",
    "sg:province":"St. Gallen",
    "wof:name":"Schrepfer Gmbh",
    "wof:placetype":"venue"
},
  "geometry": {"coordinates":[9.3417654037,47.4435043335],"type":"Point"}
}