{
  "type": "Feature",
  "properties": {
    "iso:country":"CH",
    "sg:address":"Via Pizzamiglio",
    "sg:city":"Vacallo",
    "sg:orig_category":"Herstellung von Arbeits U Berufsbekleidung Textilgewerbe",
    "sg:phone":"+41 91 683 03 91",
    "sg:postcode":"6833",
    "sg:province":"Ticino",
    "wof:name":"Spilag Vacallo Sa",
    "wof:placetype":"venue"
},
  "geometry": {"coordinates":[9.0323724747,45.8429107666],"type":"Point"}
}