{
  "type": "Feature",
  "properties": {
    "iso:country":"CH",
    "sg:address":"Gewerbestrasse 5",
    "sg:city":"Cham",
    "sg:orig_category":"Herstellung von k\u00e4lte U lufttechnischen Erzeugnissen f\u00fcr gewerbliche Zwecke",
    "sg:postcode":"6330",
    "sg:province":"Zug",
    "wof:name":"Ziegler Hans W\u00e4rmetechnik Ag",
    "wof:placetype":"venue"
},
  "geometry": {"coordinates":[8.8594455719,47.192905426],"type":"Point"}
}