{
  "type": "Feature",
  "properties": {
    "iso:country":"CH",
    "sg:address":"Bd De Perolles 42",
    "sg:city":"Fribourg",
    "sg:classifiers":[
        {
            "category":"Professional",
            "subcategory":"Printing & Photocopies",
            "type":"Services"
        }
    ],
    "sg:phone":"+41 26 426 41 11",
    "sg:postcode":"1705",
    "sg:province":"Fribourg",
    "sg:tags":[
        "publishing"
    ],
    "wof:name":"Imprimerie Et Librairies St Paul Sa",
    "wof:placetype":"venue"
},
  "geometry": {"coordinates":[7.1548099518,46.7970466614],"type":"Point"}
}