{
  "type": "Feature",
  "properties": {
    "addr:full":"Werkstrasse 8 Lyss Bern 3250",
    "addr:housenumber":"8",
    "addr:postcode":"3250",
    "addr:street":"Werkstrasse;Bern",
    "iso:country":"CH",
    "sg:address":"Werkstrasse 8",
    "sg:city":"Lyss",
    "sg:orig_category":"Allgemeiner Hochbau Ger\u00fcstbau",
    "sg:phone":"+41 32 387 06 06",
    "sg:postcode":"3250",
    "sg:province":"Bern",
    "wof:name":"Frepa Ag",
    "wof:placetype":"venue"
},
  "geometry": {"coordinates":[7.294847,47.07188],"type":"Point"}
}