{
  "type": "Feature",
  "properties": {
    "iso:country":"CH",
    "sg:address":"Coll\u00e8ge Rue Du 29",
    "sg:city":"Nyon",
    "sg:orig_category":"Fachdetailhandel in Verkaufsr\u00e4umen",
    "sg:phone":"+41 22 362 06 66",
    "sg:postcode":"1260",
    "sg:province":"Vaud",
    "wof:name":"Ono Atelier De Bijouterie-joaillerie, Christine Bontognali",
    "wof:placetype":"venue"
},
  "geometry": {"coordinates":[6.2374849319,46.3813285828],"type":"Point"}
}