{
  "type": "Feature",
  "properties": {
    "iso:country":"CH",
    "sg:address":"Rue Du Stand 33",
    "sg:city":"Gen\u00e8ve",
    "sg:orig_category":"Detailhandel mit Getr\u00e4nken Detailhandel mit Waren verschiedener Art, Hauptrichtung Nahrungsmittel",
    "sg:phone":"+41 22 329 27 07",
    "sg:postcode":"1204",
    "sg:province":"Gen\u00e8ve",
    "wof:name":"Suzanne Sabot Epicerie",
    "wof:placetype":"venue"
},
  "geometry": {"coordinates":[6.1379580498,46.2035140991],"type":"Point"}
}