{
  "type": "Feature",
  "properties": {
    "iso:country":"CH",
    "sg:address":"Aarburgerstrasse 3",
    "sg:city":"Olten",
    "sg:orig_category":"Kosmetikinstitute",
    "sg:phone":"+41 22 342 22 00",
    "sg:postcode":"4600",
    "sg:province":"Solothurn",
    "wof:name":"Doris Pfammatter Cashmir Esthetics",
    "wof:placetype":"venue"
},
  "geometry": {"coordinates":[6.1413288116,46.1848640442],"type":"Point"}
}