{
  "type": "Feature",
  "properties": {
    "iso:country":"CH",
    "sg:address":"Hauptstrasse 17",
    "sg:city":"Niederdorf",
    "sg:orig_category":"Architektur U Ingenieurb\u00fcros Herstellung von Elektromotoren, Generatoren U Transformatoren",
    "sg:phone":"+41 62 390 11 20",
    "sg:postcode":"4435",
    "sg:province":"Basel-Landschaft",
    "wof:name":"Enco Gmbh, Energie-consulting",
    "wof:placetype":"venue"
},
  "geometry": {"coordinates":[7.750713,47.403435],"type":"Point"}
}