{
  "type": "Feature",
  "properties": {
    "iso:country":"CH",
    "sg:address":"Kr\u00f6nleinstrasse 26",
    "sg:city":"Z\u00fcrich",
    "sg:orig_category":"Sonstige mit der Informatik verbundene T\u00e4tigkeiten",
    "sg:phone":"+41 12621047",
    "sg:postcode":"8044",
    "sg:province":"Z\u00fcrich",
    "wof:name":"Tony Bl\u00e4ttler Edv Consulting Ad Vice",
    "wof:placetype":"venue"
},
  "geometry": {"coordinates":[8.5607786179,47.3822746277],"type":"Point"}
}