{
  "type": "Feature",
  "properties": {
    "iso:country":"CH",
    "sg:address":"Avenue De Beauregard 10 1700 Fribourg Case Postale 560",
    "sg:city":"Fribourg",
    "sg:orig_category":"Binnenschiffahrt",
    "sg:phone":"+41 26 422 01 11",
    "sg:postcode":"1701",
    "sg:province":"Fribourg",
    "wof:name":"Adx Services Sa",
    "wof:placetype":"venue"
},
  "geometry": {"coordinates":[7.147868,46.80204],"type":"Point"}
}