{
  "type": "Feature",
  "properties": {
    "iso:country":"CH",
    "sg:address":"Via G. Motta 18",
    "sg:city":"Chiasso",
    "sg:classifiers":[
        {
            "category":"Communications",
            "subcategory":"Television Station",
            "type":"Services"
        }
    ],
    "sg:phone":"+41 91 690 04 45",
    "sg:postcode":"6830",
    "sg:province":"Ticino",
    "sg:tags":[
        "colour",
        "scanners",
        "scanner"
    ],
    "wof:name":"Buic Systems Ag",
    "wof:placetype":"venue"
},
  "geometry": {"coordinates":[9.0313053131,45.8347244263],"type":"Point"}
}