{
  "type": "Feature",
  "properties": {
    "iso:country":"CH",
    "sg:address":"Teufener Strasse 62",
    "sg:city":"St.gallen",
    "sg:orig_category":"HOTELS: MIT RESTAURANT RESTAURANTS: NICHT EIGENST\u00c4NDIG",
    "sg:phone":"+41 71 220 31 55",
    "sg:postcode":"9000",
    "sg:province":"St. Gallen",
    "wof:name":"Hotel Taj Mahal-tri Colore",
    "wof:placetype":"venue"
},
  "geometry": {"coordinates":[9.3670473099,47.4173965454],"type":"Point"}
}