{
  "type": "Feature",
  "properties": {
    "iso:country":"CH",
    "sg:address":"Landstrasse 126 A",
    "sg:city":"Adelboden",
    "sg:orig_category":"Instandhaltung U Reparatur von Automobilen",
    "sg:phone":"+41 33 673 31 11",
    "sg:postcode":"3715",
    "sg:province":"Bern",
    "wof:name":"Carrosserie M\u00fcller Gmbh",
    "wof:placetype":"venue"
},
  "geometry": {"coordinates":[7.5828900337,46.5053253174],"type":"Point"}
}