{
  "type": "Feature",
  "properties": {
    "iso:country":"CH",
    "sg:address":"Route St-germain",
    "sg:city":"Assens",
    "sg:classifiers":[
        {
            "category":"Restaurant",
            "type":"Food & Drink"
        }
    ],
    "sg:phone":"+41 21 882 14 14",
    "sg:postcode":"1042",
    "sg:province":"Vaud",
    "wof:name":"Restaurant L'epi D'or",
    "wof:placetype":"venue"
},
  "geometry": {"coordinates":[6.6214752197,46.6129493713],"type":"Point"}
}