{
  "type": "Feature",
  "properties": {
    "iso:country":"CH",
    "sg:address":"Route De Ch\u00e9salles 52",
    "sg:city":"Marly",
    "sg:orig_category":"Detailhandel mit Schuhen U Lederwaren Grosshandel mit Schuhen",
    "sg:phone":"+41 26 436 43 68",
    "sg:postcode":"1723",
    "sg:province":"Fribourg",
    "wof:name":"Saba Schuhagentur Gmbh",
    "wof:placetype":"venue"
},
  "geometry": {"coordinates":[7.1539578438,46.7730140686],"type":"Point"}
}