{
  "type": "Feature",
  "properties": {
    "iso:country":"CH",
    "sg:address":"Tigelbergstrasse 1",
    "sg:city":"Berneck",
    "sg:orig_category":"Unclassifiable Establishments",
    "sg:postcode":"9442",
    "sg:province":"St. Gallen",
    "wof:name":"Best-konf Holding Ag",
    "wof:placetype":"venue"
},
  "geometry": {"coordinates":[9.6094150543,47.4304847717],"type":"Point"}
}