{
  "type": "Feature",
  "properties": {
    "iso:country":"CH",
    "sg:address":"7213",
    "sg:city":"Valzeina",
    "sg:classifiers":[
        {
            "category":"Restaurant",
            "type":"Food & Drink"
        }
    ],
    "sg:phone":"+41 81 325 11 47",
    "sg:postcode":"7213",
    "sg:province":"Graubunden",
    "wof:name":"Restaurant Z. Alpenrose",
    "wof:placetype":"venue"
},
  "geometry": {"coordinates":[9.6028547287,46.9504089355],"type":"Point"}
}