{
  "type": "Feature",
  "properties": {
    "iso:country":"CH",
    "sg:address":"Avenue De La Gare",
    "sg:city":"Moutier",
    "sg:orig_category":"Detailhandel mit Blumen U Pflanzen Detailhandel mit Geschenkartikeln U Souvenirs",
    "sg:phone":"+41 32 493 73 74",
    "sg:postcode":"2740",
    "sg:province":"Bern",
    "wof:name":"Au Mimosa Fleurs",
    "wof:placetype":"venue"
},
  "geometry": {"coordinates":[7.379568,47.280594],"type":"Point"}
}