{
  "type": "Feature",
  "properties": {
    "addr:full":"Via Della Chiesa Castione Ticino 6532",
    "addr:postcode":"6532",
    "addr:street":"Via Della Chiesa",
    "iso:country":"CH",
    "sg:address":"Via Della Chiesa",
    "sg:city":"Castione",
    "sg:orig_category":"Allgemeiner Hoch U Tiefbau Hoch U Tiefbau",
    "sg:phone":"+41 91 829 18 61",
    "sg:postcode":"6532",
    "sg:province":"Ticino",
    "wof:name":"Lamberti Antonietta, Lamberti Alberto Successore",
    "wof:placetype":"venue"
},
  "geometry": {"coordinates":[9.048517,46.22588],"type":"Point"}
}