{
  "type": "Feature",
  "properties": {
    "iso:country":"CH",
    "sg:address":"G\u00fcterstrasse 455",
    "sg:city":"Egerkingen",
    "sg:orig_category":"Non-Classified Establishments",
    "sg:phone":"+41 62 398 40 30",
    "sg:postcode":"4622",
    "sg:province":"Solothurn",
    "wof:name":"Gerster Holding Ag",
    "wof:placetype":"venue"
},
  "geometry": {"coordinates":[7.7969999313,47.3149414062],"type":"Point"}
}