{
  "type": "Feature",
  "properties": {
    "iso:country":"CH",
    "sg:address":"Schanzm\u00e4ttelistrasse 5",
    "sg:city":"Aarau",
    "sg:orig_category":"Zahntechnische Laboratorien",
    "sg:phone":"+41 62 822 50 82",
    "sg:postcode":"5000",
    "sg:province":"Aargau",
    "wof:name":"Ruf Dental-labor Gmbh",
    "wof:placetype":"venue"
},
  "geometry": {"coordinates":[8.0432300568,47.3890304565],"type":"Point"}
}