{
  "type": "Feature",
  "properties": {
    "addr:full":"L\u00e4nggassstrasse 30 3012 Bern. Postfach Bern Bern 3012",
    "addr:housenumber":"30",
    "addr:postcode":"3012;postfach;3012",
    "addr:street":"Laenggassstrasse",
    "iso:country":"CH",
    "sg:address":"L\u00e4nggassstrasse 30 3012 Bern. Postfach",
    "sg:city":"Bern",
    "sg:orig_category":"Detailhandel mit Bekleidung",
    "sg:postcode":"3012",
    "sg:province":"Bern",
    "wof:name":"C. Balzli",
    "wof:placetype":"venue"
},
  "geometry": {"coordinates":[7.432548,46.95335],"type":"Point"}
}