{
  "type": "Feature",
  "properties": {
    "iso:country":"CH",
    "sg:address":"4574",
    "sg:city":"Nennigkofen",
    "sg:orig_category":"Sportvereine Sch\u00fctzen",
    "sg:phone":"+41 32 622 25 82",
    "sg:postcode":"4574",
    "sg:province":"Solothurn",
    "wof:name":"Sch\u00fctzengesellschaft",
    "wof:placetype":"venue"
},
  "geometry": {"coordinates":[7.4929361343,47.1867485046],"type":"Point"}
}