{
  "type": "Feature",
  "properties": {
    "iso:country":"CH",
    "sg:city":"Cugnasco",
    "sg:classifiers":[
        {
            "category":"Banks & Credit Unions",
            "subcategory":"Bank",
            "type":"Services"
        }
    ],
    "sg:phone":"+41 91 850 59 59",
    "sg:postcode":"6516",
    "sg:province":"Ticino",
    "wof:name":"Raiffeisen",
    "wof:placetype":"venue"
},
  "geometry": {"coordinates":[8.917745,46.175251],"type":"Point"}
}