{
  "type": "Feature",
  "properties": {
    "iso:country":"CH",
    "sg:address":"Rue Du Grand-pont 2bis",
    "sg:city":"Lausanne",
    "sg:orig_category":"Detailhandel mit Geschenkartikeln U Souvenirs Herstellung von keramischen Haushaltswaren U Ziergegen",
    "sg:phone":"+41 21 323 82 61",
    "sg:postcode":"1003",
    "sg:province":"Vaud",
    "wof:name":"Terres Cuites De Provence Lysiane Martin",
    "wof:placetype":"venue"
},
  "geometry": {"coordinates":[6.6319561005,46.5200805664],"type":"Point"}
}