{
  "type": "Feature",
  "properties": {
    "iso:country":"CH",
    "sg:address":"Bernerh\u00f6he 6415 Arth. Postfach",
    "sg:city":"Goldau",
    "sg:orig_category":"Campingpl\u00e4tze",
    "sg:phone":"+41 41 855 02 65",
    "sg:postcode":"6410",
    "sg:province":"Schwyz",
    "wof:name":"Gwerder-kenel Bruno",
    "wof:placetype":"venue"
},
  "geometry": {"coordinates":[8.560257,47.040745],"type":"Point"}
}