{
  "type": "Feature",
  "properties": {
    "iso:country":"CH",
    "sg:address":"R\u00fctenenweg 60 5408 Ennetbaden. Postfach",
    "sg:city":"Ennetbaden",
    "sg:orig_category":"Herstellung von Konstruktionsteilen, Fertigbauteilen U Ausbauelementen aus Holz",
    "sg:postcode":"5408",
    "sg:province":"Aargau",
    "wof:name":"Schreiner Schraner Gmbh",
    "wof:placetype":"venue"
},
  "geometry": {"coordinates":[8.3219604492,47.4784469604],"type":"Point"}
}