{
  "type": "Feature",
  "properties": {
    "iso:country":"CH",
    "sg:address":"Rebbergstrasse 4",
    "sg:city":"Oberlunkhofen",
    "sg:orig_category":"Handelsvermittlung U Grosshandel Sonstiger Grosshandel",
    "sg:phone":"+41 56 634 12 84",
    "sg:postcode":"8917",
    "sg:province":"Aargau",
    "wof:name":"Cassiopeia Accessoires Ag",
    "wof:placetype":"venue"
},
  "geometry": {"coordinates":[8.3903226852,47.3136482239],"type":"Point"}
}