{
  "type": "Feature",
  "properties": {
    "iso:country":"CH",
    "sg:address":"Grenchen",
    "sg:city":"Wilderswil",
    "sg:orig_category":"Unclassifiable Establishments",
    "sg:postcode":"3812",
    "sg:province":"Bern",
    "wof:name":"J\u00f6rg Hoch Und Tiefbau Ag, Wilderswil",
    "wof:placetype":"venue"
},
  "geometry": {"coordinates":[7.863694191,46.6601486206],"type":"Point"}
}