{
  "type": "Feature",
  "properties": {
    "iso:country":"CH",
    "sg:address":"R\u00fceggisingerstrasse 5",
    "sg:city":"Emmen",
    "sg:orig_category":"Mechanik",
    "sg:postcode":"6032",
    "sg:province":"Luzern",
    "wof:name":"Schupp Hans",
    "wof:placetype":"venue"
},
  "geometry": {"coordinates":[8.2929477692,47.0859069824],"type":"Point"}
}