{
  "type": "Feature",
  "properties": {
    "iso:country":"CH",
    "sg:address":"Rue De La Gare 15 C 1110 Morges. Postfach",
    "sg:city":"Morges",
    "sg:orig_category":"Reiseb\u00fcros U Reiseveranstalter",
    "sg:postcode":"1110",
    "sg:province":"Vaud",
    "wof:name":"Est Contact, Durel",
    "wof:placetype":"venue"
},
  "geometry": {"coordinates":[6.4955949783,46.5091247559],"type":"Point"}
}