{
  "type": "Feature",
  "properties": {
    "iso:country":"CH",
    "sg:address":"In Der Luberzen 29",
    "sg:city":"Urdorf",
    "sg:orig_category":"Unternehmensberatung",
    "sg:phone":"+41 17770101",
    "sg:postcode":"8902",
    "sg:province":"Z\u00fcrich",
    "wof:name":"Ncicube Ag Dienstleistungen F\u00fcr Internetfirmen",
    "wof:placetype":"venue"
},
  "geometry": {"coordinates":[8.4248199463,47.3946037292],"type":"Point"}
}