{
  "type": "Feature",
  "properties": {
    "iso:country":"CH",
    "sg:address":"Fontanaweg 29",
    "sg:city":"Muntelier",
    "sg:orig_category":"Sportvereine Velo Rad-& Motorfahrer-Bund SRB",
    "sg:postcode":"3286",
    "sg:province":"Fribourg",
    "wof:name":"Velo-moto-club Murten",
    "wof:placetype":"venue"
},
  "geometry": {"coordinates":[7.1266098022,46.9387817383],"type":"Point"}
}