{
  "type": "Feature",
  "properties": {
    "iso:country":"CH",
    "sg:address":"Oberdorfstrasse 8 8001 Z\u00fcrich. Postfach",
    "sg:city":"Z\u00fcrich",
    "sg:orig_category":"Verlagsgewerbe",
    "sg:phone":"+41 12514612",
    "sg:postcode":"8024",
    "sg:province":"Z\u00fcrich",
    "wof:name":"Hans R. Schwarzenbach Postgeschichte-verlag",
    "wof:placetype":"venue"
},
  "geometry": {"coordinates":[8.5458288193,47.3684196472],"type":"Point"}
}