{
  "type": "Feature",
  "properties": {
    "iso:country":"CH",
    "sg:address":"Muristrasse 4",
    "sg:city":"Boswil",
    "sg:orig_category":"RESTAURANTS: TEA-ROOMS",
    "sg:phone":"+41 56 666 28 00",
    "sg:postcode":"5623",
    "sg:province":"Aargau",
    "wof:name":"Pizzeria Armando Simoniello Ag",
    "wof:placetype":"venue"
},
  "geometry": {"coordinates":[8.3158359528,47.2987709045],"type":"Point"}
}