{
  "type": "Feature",
  "properties": {
    "addr:full":"Gyrenstrasse 6 Widen Aargau 8967",
    "addr:housenumber":"6",
    "addr:postcode":"8967",
    "addr:street":"Gyrenstrasse",
    "iso:country":"CH",
    "sg:address":"Gyrenstrasse 6",
    "sg:city":"Widen",
    "sg:orig_category":"Bauschreinerei Herstellung von Konstruktionsteilen, Fertigbauteilen U Ausbauelementen aus Holz",
    "sg:phone":"+41 56 633 18 85",
    "sg:postcode":"8967",
    "sg:province":"Aargau",
    "wof:name":"Stettler Schreinerei Ag",
    "wof:placetype":"venue"
},
  "geometry": {"coordinates":[8.355793,47.367287],"type":"Point"}
}