{
  "type": "Feature",
  "properties": {
    "iso:country":"CH",
    "sg:address":"Quai Du Haut 49 2502 Biel/bienne. Postfach",
    "sg:city":"Biel/bienne",
    "sg:orig_category":"Unclassifiable Establishments",
    "sg:phone":"+41 32 341 08 88",
    "sg:postcode":"2502",
    "sg:province":"Bern",
    "wof:name":"Mediasystem Technology S\u00e0rl Support Technique, Produits Multimedia Audio-ved\u00e9o; Consultation, Vente Etc",
    "wof:placetype":"venue"
},
  "geometry": {"coordinates":[7.2517647743,47.1396141052],"type":"Point"}
}