{
  "type": "Feature",
  "properties": {
    "iso:country":"CH",
    "sg:address":"Gottardo Via San 12 6900 Lugano. Postfach",
    "sg:city":"Lugano",
    "sg:orig_category":"Vermietung U Verpachtung von eigenen Immobilien",
    "sg:postcode":"6900",
    "sg:province":"Ticino",
    "wof:name":"Milena Sa",
    "wof:placetype":"venue"
},
  "geometry": {"coordinates":[8.9492397308,46.0088043213],"type":"Point"}
}