{
  "type": "Feature",
  "properties": {
    "addr:full":"N\u00fcschelerstrasse 35 8001 Z\u00fcrich. Postfach Z\u00fcrich Z\u00fcrich 8022",
    "addr:housenumber":"35",
    "addr:postcode":"8001 zuerich. postfach;8022",
    "addr:street":"Nueschelerstrasse",
    "iso:country":"CH",
    "sg:address":"N\u00fcschelerstrasse 35 8001 Z\u00fcrich. Postfach",
    "sg:city":"Z\u00fcrich",
    "sg:orig_category":"Advokaturb\u00fcros",
    "sg:phone":"+41 24 425 20 82",
    "sg:postcode":"8022",
    "sg:province":"Z\u00fcrich",
    "wof:name":"Treyvaud Gilliard & Munoz Etude D'avocat",
    "wof:placetype":"venue"
},
  "geometry": {"coordinates":[6.642147,46.778976],"type":"Point"}
}