{
  "type": "Feature",
  "properties": {
    "addr:full":"Echallens Avenue D' 125 1004 Lausanne. Postfach Lausanne Vaud 1003",
    "addr:housenumber":"125",
    "addr:postcode":"1004;postfach;1003",
    "addr:street":"Echallens Avenue D '",
    "iso:country":"CH",
    "sg:address":"Echallens Avenue D' 125 1004 Lausanne. Postfach",
    "sg:city":"Lausanne",
    "sg:orig_category":"Architektur U Ingenieurb\u00fcros",
    "sg:postcode":"1003",
    "sg:province":"Vaud",
    "wof:name":"Poncioni Constructions S\u00e0rl Activit\u00e9 Dans Le Dom. De La Construction, Immobili\u00e8res Etc",
    "wof:placetype":"venue"
},
  "geometry": {"coordinates":[6.61873,46.533489],"type":"Point"}
}