{
  "type": "Feature",
  "properties": {
    "iso:country":"CH",
    "sg:address":"Albricci Via Degli 6",
    "sg:city":"Chiasso",
    "sg:orig_category":"Sonstige Verkehrsvermittlung",
    "sg:phone":"+41 91 606 35 41",
    "sg:postcode":"6830",
    "sg:province":"Ticino",
    "wof:name":"Tresiana Sa",
    "wof:placetype":"venue"
},
  "geometry": {"coordinates":[8.8600940704,45.9678382874],"type":"Point"}
}