{
  "type": "Feature",
  "properties": {
    "iso:country":"CH",
    "sg:address":"B\u00e4renmattenstrasse 10 4434 H\u00f6lstein. Postfach 251",
    "sg:city":"H\u00f6lstein",
    "sg:orig_category":"Herstellung von keramischen Wand U Bodenfliesen U platten Verlegen von Fliesen U Platten",
    "sg:phone":"+41 61 953 19 59",
    "sg:postcode":"4434",
    "sg:province":"Basel-Landschaft",
    "wof:name":"Keramtech Gmbh Keramische Wand- U. Bodenbel\u00e4ge, Naturstein, Treppen- U. Bodenbel\u00e4ge; Verlegen",
    "wof:placetype":"venue"
},
  "geometry": {"coordinates":[7.7629370689,47.4415054321],"type":"Point"}
}