{
  "type": "Feature",
  "properties": {
    "iso:country":"CH",
    "sg:address":"Badenerstrasse 414 8001 Z\u00fcrich. Postfach",
    "sg:city":"Z\u00fcrich",
    "sg:orig_category":"Softwareentwicklung U beratung",
    "sg:postcode":"8001",
    "sg:province":"Z\u00fcrich",
    "wof:name":"Hardpro Gmbh Computer-hard, Software; Handel Usw",
    "wof:placetype":"venue"
},
  "geometry": {"coordinates":[8.7734136581,47.2015151978],"type":"Point"}
}