{
  "type": "Feature",
  "properties": {
    "iso:country":"CH",
    "sg:address":"Clairi\u00e8re Des Dailles",
    "sg:city":"Chernex",
    "sg:orig_category":"Maurerarbeiten Sonstiger spezialisierter Hoch U Tiefbau",
    "sg:phone":"+41 79 230 67 16",
    "sg:postcode":"1822",
    "sg:province":"Vaud",
    "wof:name":"Vittorio Pambianchi",
    "wof:placetype":"venue"
},
  "geometry": {"coordinates":[7.0663948059,46.6079711914],"type":"Point"}
}