{
  "type": "Feature",
  "properties": {
    "iso:country":"CH",
    "sg:address":"Laupenstrasse 2",
    "sg:city":"B\u00f6singen",
    "sg:orig_category":"Pensionskassen",
    "sg:postcode":"3178",
    "sg:province":"Fribourg",
    "wof:name":"Personalvorsorgestiftung Der Firma Eggimann & Hollenstein Ag M\u00f6belfabrik",
    "wof:placetype":"venue"
},
  "geometry": {"coordinates":[9.1234006882,47.4656410217],"type":"Point"}
}