{
  "type": "Feature",
  "properties": {
    "iso:country":"CH",
    "sg:address":"Rue Du Milieu 45",
    "sg:city":"Coeuve",
    "sg:orig_category":"Primarschulen",
    "sg:phone":"+41 32 466 81 61",
    "sg:postcode":"2932",
    "sg:province":"Jura",
    "wof:name":"Ecole Primaire",
    "wof:placetype":"venue"
},
  "geometry": {"coordinates":[7.09790802,47.4532775879],"type":"Point"}
}