{
  "type": "Feature",
  "properties": {
    "iso:country":"CH",
    "sg:address":"Alte Landstrasse 205",
    "sg:city":"M\u00e4nnedorf",
    "sg:orig_category":"Detailhandel mit fotografischen Artikeln Fachdetailhandel in Verkaufsr\u00e4umen",
    "sg:phone":"+41 19200104",
    "sg:postcode":"8708",
    "sg:province":"Z\u00fcrich",
    "wof:name":"Foto Gall Film - Foto - Video",
    "wof:placetype":"venue"
},
  "geometry": {"coordinates":[8.6918363571,47.2548217773],"type":"Point"}
}