{
  "type": "Feature",
  "properties": {
    "iso:country":"CH",
    "sg:address":"Gen\u00e8ve Rue De 40",
    "sg:city":"Ch\u00eane-bourg",
    "sg:orig_category":"Unclassifiable Establishments",
    "sg:postcode":"1225",
    "sg:province":"Gen\u00e8ve",
    "wof:name":"Bernasconi F. Et Cie Sa, Succursale De Ch\u00eane-bourg",
    "wof:placetype":"venue"
},
  "geometry": {"coordinates":[6.1958532333,46.1938934326],"type":"Point"}
}