{
  "type": "Feature",
  "properties": {
    "iso:country":"CH",
    "sg:address":"Hauptstrasse 9",
    "sg:city":"Laufen",
    "sg:orig_category":"Detailhandel mit Milcherzeugnissen U Eiern Grosshandel mit Nahrungsmitteln, Getr\u00e4nken U Tabakwaren o",
    "sg:phone":"+41 61 711 40 10",
    "sg:postcode":"4242",
    "sg:province":"Basel-Landschaft",
    "wof:name":"Primo Milchh\u00fcsli, Leu Josef",
    "wof:placetype":"venue"
},
  "geometry": {"coordinates":[7.5918931961,47.4932098389],"type":"Point"}
}