{
  "type": "Feature",
  "properties": {
    "iso:country":"CH",
    "sg:address":"Orbe Rue D' 96",
    "sg:city":"Yverdon-les-bains",
    "sg:orig_category":"Bau von Strassen, Sportanlagen U Bahnverkehrsstrecken",
    "sg:phone":"+41 24 425 15 22",
    "sg:postcode":"1400",
    "sg:province":"Vaud",
    "wof:name":"Piscines Fbe, Fardel Fr\u00e9d\u00e9ric",
    "wof:placetype":"venue"
},
  "geometry": {"coordinates":[6.628979,46.754066],"type":"Point"}
}