{
  "type": "Feature",
  "properties": {
    "iso:country":"CH",
    "sg:address":"G\u00fcterstrasse 86 4053 Basel. Postfach",
    "sg:city":"Basel",
    "sg:orig_category":"Druck ohne Zeitungsdruck Herstellung von Holzstoff, Papier, Karton U Pappe",
    "sg:phone":"+41 61 421 72 75",
    "sg:postcode":"4018",
    "sg:province":"Basel-Stadt",
    "wof:name":"Bimo Print Ag",
    "wof:placetype":"venue"
},
  "geometry": {"coordinates":[7.571366787,47.534576416],"type":"Point"}
}