{
  "type": "Feature",
  "properties": {
    "addr:full":"Z\u00fcrcherstrasse 27 Baden Aargau 5400",
    "addr:housenumber":"27",
    "addr:postcode":"5400",
    "addr:street":"Zuercherstrasse",
    "iso:country":"CH",
    "sg:address":"Z\u00fcrcherstrasse 27",
    "sg:city":"Baden",
    "sg:orig_category":"Berufliche Weiterbildung, Erwachsenenbildung HOTELS: MIT RESTAURANT",
    "sg:phone":"+41 56 203 05 05",
    "sg:postcode":"5400",
    "sg:province":"Aargau",
    "wof:name":"Schibli Consulting Ag Verhaltenstraining, Seminare Usw.; Entwicklung, Organisation Und Durchf\u00fchrung",
    "wof:placetype":"venue"
},
  "geometry": {"coordinates":[8.306172,47.469646],"type":"Point"}
}