{
  "type": "Feature",
  "properties": {
    "iso:country":"CH",
    "sg:address":"Lenzb\u00fchlstrasse 2",
    "sg:city":"Sirnach",
    "sg:orig_category":"Instandhaltung U Reparatur von Automobilen",
    "sg:postcode":"8370",
    "sg:province":"Thurgau",
    "wof:name":"Auto Carrosserie 2000 Osmani I.",
    "wof:placetype":"venue"
},
  "geometry": {"coordinates":[9.0232028961,47.4624710083],"type":"Point"}
}