{
  "type": "Feature",
  "properties": {
    "iso:country":"CH",
    "sg:address":"Hauptstrasse 8 3646 Einigen. Postfach",
    "sg:city":"Einigen",
    "sg:orig_category":"Herstellung von B\u00fcro U Ladenm\u00f6beln",
    "sg:phone":"+41 26 677 17 44",
    "sg:postcode":"3646",
    "sg:province":"Bern",
    "wof:name":"Grandjean Philippe",
    "wof:placetype":"venue"
},
  "geometry": {"coordinates":[6.9800801277,46.8900299072],"type":"Point"}
}