{
  "type": "Feature",
  "properties": {
    "iso:country":"CH",
    "sg:address":"Dorfgasse 9",
    "sg:city":"Sumiswald",
    "sg:orig_category":"Instandhaltung U Reparatur von Automobilen",
    "sg:phone":"+41 34 431 11 30",
    "sg:postcode":"3454",
    "sg:province":"Bern",
    "wof:name":"Guido Gm\u00fcr",
    "wof:placetype":"venue"
},
  "geometry": {"coordinates":[7.742937088,47.0299491882],"type":"Point"}
}