{
  "type": "Feature",
  "properties": {
    "iso:country":"CH",
    "sg:address":"1643",
    "sg:city":"Gumefens",
    "sg:orig_category":"Primarschulen",
    "sg:phone":"+41 26 915 29 21",
    "sg:postcode":"1643",
    "sg:province":"Fribourg",
    "wof:name":"Ecole Primaire",
    "wof:placetype":"venue"
},
  "geometry": {"coordinates":[7.0685901642,46.6771697998],"type":"Point"}
}