{
  "type": "Feature",
  "properties": {
    "iso:country":"CH",
    "sg:address":"P\u00e9rolles Boulevard De 37",
    "sg:city":"Freiburg",
    "sg:orig_category":"Non-Classified Establishments",
    "sg:postcode":"1700",
    "sg:province":"Fribourg",
    "wof:name":"Sara Hofstetter",
    "wof:placetype":"venue"
},
  "geometry": {"coordinates":[8.0206613541,46.8668632507],"type":"Point"}
}