{
  "type": "Feature",
  "properties": {
    "iso:country":"CH",
    "sg:address":"Bernstrasse 88 8953 Dietikon. Postfach 660",
    "sg:city":"Dietikon",
    "sg:orig_category":"Unternehmensberatung",
    "sg:phone":"+41 17152313",
    "sg:postcode":"8953",
    "sg:province":"Z\u00fcrich",
    "wof:name":"Helbling Consulting",
    "wof:placetype":"venue"
},
  "geometry": {"coordinates":[8.543381691,47.3293838501],"type":"Point"}
}