{
  "type": "Feature",
  "properties": {
    "iso:country":"CH",
    "sg:address":"Kirchb\u00fchl 6 6314 Unter\u00e4geri. Postfach",
    "sg:city":"Unter\u00e4geri",
    "sg:orig_category":"Grosshandel mit Nahrungsmitteln, Getr\u00e4nken U Tabakwaren ohne ausgepr\u00e4gten Schwerpunkt",
    "sg:postcode":"6314",
    "sg:province":"Zug",
    "wof:name":"Mmc Consulting Casutt",
    "wof:placetype":"venue"
},
  "geometry": {"coordinates":[8.5915126801,47.1265792847],"type":"Point"}
}