{
  "type": "Feature",
  "properties": {
    "iso:country":"CH",
    "sg:address":"Abtwilstrasse",
    "sg:city":"Ballwil",
    "sg:orig_category":"Non-Classified Establishments",
    "sg:postcode":"6275",
    "sg:province":"Luzern",
    "wof:name":"Fit Link Personaltraining By Marcel K. Felder",
    "wof:placetype":"venue"
},
  "geometry": {"coordinates":[8.3280858994,47.154132843],"type":"Point"}
}