{
  "type": "Feature",
  "properties": {
    "iso:country":"CH",
    "sg:address":"In Der Platten 4",
    "sg:city":"Maur",
    "sg:orig_category":"Installation von Heizungs, L\u00fcftungs U Klimaanlagen",
    "sg:phone":"+41 19800197",
    "sg:postcode":"8124",
    "sg:province":"Z\u00fcrich",
    "wof:name":"Rohrgeiss Sanit\u00e4r - Heizungen",
    "wof:placetype":"venue"
},
  "geometry": {"coordinates":[8.6598119736,47.3434944153],"type":"Point"}
}