{
  "type": "Feature",
  "properties": {
    "iso:country":"CH",
    "sg:address":"Maison De Lo\u00ebx",
    "sg:city":"Bernex",
    "sg:orig_category":"Haltung von Rindern",
    "sg:postcode":"1233",
    "sg:province":"Gen\u00e8ve",
    "wof:name":"Syndicat D'\u00e9levage Bovin De Bettens",
    "wof:placetype":"venue"
},
  "geometry": {"coordinates":[6.6791501045,46.6314811707],"type":"Point"}
}