{
  "type": "Feature",
  "properties": {
    "iso:country":"CH",
    "sg:address":"Dorfstrasse 13",
    "sg:city":"Kloten",
    "sg:orig_category":"Berufsbildende weiterf\u00fchrende Schulen Hochschulen U h\u00f6here Ausbildung",
    "sg:phone":"+41 18030323",
    "sg:postcode":"8302",
    "sg:province":"Z\u00fcrich",
    "wof:name":"Zem Fachschule Zehnder",
    "wof:placetype":"venue"
},
  "geometry": {"coordinates":[8.582109,47.453457],"type":"Point"}
}