{
  "type": "Feature",
  "properties": {
    "iso:country":"CH",
    "sg:address":"Pilatusstrasse 35 6003 Luzern. Postfach 3364",
    "sg:city":"Luzern",
    "sg:orig_category":"Wirtschaftspr\u00fcfung, Steuerberatung U Treuhand",
    "sg:phone":"+41 19100909",
    "sg:postcode":"6002",
    "sg:province":"Luzern",
    "wof:name":"I.o.s. Independent Office Support Bandinu Tatjana",
    "wof:placetype":"venue"
},
  "geometry": {"coordinates":[8.6018390656,47.3255233765],"type":"Point"}
}