{
  "type": "Feature",
  "properties": {
    "iso:country":"CH",
    "sg:address":"Voia Principala 53",
    "sg:city":"Lantsch/lenz",
    "sg:orig_category":"Grosshandel mit Nahrungsmitteln, Getr\u00e4nken U Tabakwaren ohne ausgepr\u00e4gten Schwerpunkt",
    "sg:phone":"+41 81 681 19 69",
    "sg:postcode":"7083",
    "sg:province":"Graubunden",
    "wof:name":"Puracenter Ag",
    "wof:placetype":"venue"
},
  "geometry": {"coordinates":[9.5630817413,46.6854743958],"type":"Point"}
}