{
  "type": "Feature",
  "properties": {
    "iso:country":"CH",
    "sg:address":"Solenbergstrasse 35",
    "sg:city":"Schaffhausen",
    "sg:orig_category":"Herstellung von Automobilen Stahl U Leichtmetallbau",
    "sg:phone":"+41 52 643 18 50",
    "sg:postcode":"8207",
    "sg:province":"Schaffhausen",
    "wof:name":"Metasol Ag Blechteile, Blech Und Metallkonstruktionen Usw.; Entwicklung, Herstellung",
    "wof:placetype":"venue"
},
  "geometry": {"coordinates":[8.6726694107,47.7210388184],"type":"Point"}
}