{
  "type": "Feature",
  "properties": {
    "addr:full":"Via Cave Di Marmo Arzo Ticino 6864",
    "addr:postcode":"6864",
    "addr:street":"Via Cave Di Marmo;Ticino",
    "iso:country":"CH",
    "sg:address":"Via Cave Di Marmo",
    "sg:city":"Arzo",
    "sg:orig_category":"Allgemeiner Hoch U Tiefbau Bauspenglerei",
    "sg:phone":"+41 91 646 61 26",
    "sg:postcode":"6864",
    "sg:province":"Ticino",
    "wof:name":"Caverzasio & Co Imp.sanitari & Riscaldamenti",
    "wof:placetype":"venue"
},
  "geometry": {"coordinates":[8.946705,45.876823],"type":"Point"}
}