{
  "type": "Feature",
  "properties": {
    "iso:country":"CH",
    "sg:address":"Avenue Des Bergi\u00e8res 50",
    "sg:city":"Lausanne",
    "sg:orig_category":"Tierarztpraxis",
    "sg:phone":"+41 21 683 33 33",
    "sg:postcode":"1004",
    "sg:province":"Vaud",
    "wof:name":"Dr M\u00e9d. V\u00e9t. Marc Vingerhoets M\u00e9decin V\u00e9t\u00e9rinaire",
    "wof:placetype":"venue"
},
  "geometry": {"coordinates":[6.61789608,46.5313072205],"type":"Point"}
}