{
  "type": "Feature",
  "properties": {
    "iso:country":"CH",
    "sg:address":"Rheinstrasse 25",
    "sg:city":"Chur",
    "sg:classifiers":[
        {
            "category":"Home & Garden",
            "subcategory":"Building Materials",
            "type":"Retail Goods"
        }
    ],
    "sg:phone":"+41 81 286 00 00",
    "sg:postcode":"7000",
    "sg:province":"Graubunden",
    "sg:tags":[
        "installation",
        "electric"
    ],
    "wof:name":"Hunger Ag",
    "wof:placetype":"venue"
},
  "geometry": {"coordinates":[9.5241479874,46.8523139954],"type":"Point"}
}