{
  "type": "Feature",
  "properties": {
    "iso:country":"CH",
    "sg:address":"Im Schmitteli 2",
    "sg:city":"Wolhusen",
    "sg:classifiers":[
        {
            "category":"Professional",
            "subcategory":"Employment Agencies",
            "type":"Services"
        }
    ],
    "sg:phone":"+41 41 492 50 30",
    "sg:postcode":"6110",
    "sg:province":"Luzern",
    "sg:tags":[
        "personal",
        "u",
        "stellenvermittlung"
    ],
    "wof:name":"Rav Regionales Arbeitsvermittlungszentrum",
    "wof:placetype":"venue"
},
  "geometry": {"coordinates":[8.0698728561,47.0583610535],"type":"Point"}
}