{
  "type": "Feature",
  "properties": {
    "iso:country":"CH",
    "sg:address":"3534",
    "sg:city":"Signau",
    "sg:orig_category":"Verarbeitung von Milch Verwertung von Milch",
    "sg:phone":"+41 34 497 13 67",
    "sg:postcode":"3534",
    "sg:province":"Bern",
    "wof:name":"K\u00e4sereigenossenschaft H\u00f6he",
    "wof:placetype":"venue"
},
  "geometry": {"coordinates":[7.7206711769,46.916934967],"type":"Point"}
}