{
  "type": "Feature",
  "properties": {
    "iso:country":"CH",
    "sg:address":"Frohburgerstrasse 21 4132 Muttenz. Postfach 164",
    "sg:city":"Muttenz",
    "sg:orig_category":"Sonstige Verkehrsvermittlung",
    "sg:phone":"+41 61 466 88 88",
    "sg:postcode":"4132",
    "sg:province":"Basel-Landschaft",
    "wof:name":"Balimpex Ag",
    "wof:placetype":"venue"
},
  "geometry": {"coordinates":[7.6530838013,47.529838562],"type":"Point"}
}