{
  "type": "Feature",
  "properties": {
    "iso:country":"CH",
    "sg:address":"P\u00e9lisserie Rue De La 16 1204 Gen\u00e8ve. Postfach",
    "sg:city":"Gen\u00e8ve",
    "sg:orig_category":"Grosshandel mit Erzen U Metallen",
    "sg:postcode":"1204",
    "sg:province":"Gen\u00e8ve",
    "wof:name":"Moser Alteisen Und Metalle",
    "wof:placetype":"venue"
},
  "geometry": {"coordinates":[9.5520477295,47.3750915527],"type":"Point"}
}