{
  "type": "Feature",
  "properties": {
    "iso:country":"CH",
    "sg:address":"Endingerstrasse 34 5303 W\u00fcrenlingen. Postfach",
    "sg:city":"W\u00fcrenlingen",
    "sg:orig_category":"Handel mit Motorr\u00e4dern, Teilen U Zubeh\u00f6r Instandhaltung U Reparatur von Motorr\u00e4dern",
    "sg:phone":"+41 56 281 27 78",
    "sg:postcode":"5303",
    "sg:province":"Aargau",
    "wof:name":"Mm Meier Motos 2-rad, Freizeit- U. Sportbekleidungshandel",
    "wof:placetype":"venue"
},
  "geometry": {"coordinates":[8.2618227005,47.5296096802],"type":"Point"}
}