{
  "type": "Feature",
  "properties": {
    "iso:country":"CH",
    "sg:address":"Bremgartenstrasse 20",
    "sg:city":"Merenschwand",
    "sg:orig_category":"Instandhaltung U Reparatur von Automobilen",
    "sg:phone":"+41 56 664 34 44",
    "sg:postcode":"5634",
    "sg:province":"Aargau",
    "wof:name":"Autospritzwerk Marcel Meier",
    "wof:placetype":"venue"
},
  "geometry": {"coordinates":[8.3712530136,47.2624206543],"type":"Point"}
}