{
  "type": "Feature",
  "properties": {
    "addr:full":"Jurastrasse 31 4900 Langenthal. Postfach 119 Langenthal Bern 4900",
    "addr:housenumber":"31;119",
    "addr:postcode":"4900;4900",
    "addr:street":"Jurastrasse;Postfach;Bern",
    "iso:country":"CH",
    "sg:address":"Jurastrasse 31 4900 Langenthal. Postfach 119",
    "sg:city":"Langenthal",
    "sg:orig_category":"Advokaturb\u00fcros Notariate",
    "sg:phone":"+41 62 922 03 33",
    "sg:postcode":"4900",
    "sg:province":"Bern",
    "wof:name":"Andreas Bandi Advokatur-& Notariatsb\u00fcro",
    "wof:placetype":"venue"
},
  "geometry": {"coordinates":[7.786887,47.214825],"type":"Point"}
}