{
  "type": "Feature",
  "properties": {
    "addr:full":"Weggisgasse 1 6004 Luzern. Postfach Luzern Luzern 6005",
    "addr:housenumber":"1",
    "addr:postcode":"6004;postfach;6005",
    "addr:street":"Weggisgasse",
    "iso:country":"CH",
    "sg:address":"Weggisgasse 1 6004 Luzern. Postfach",
    "sg:city":"Luzern",
    "sg:orig_category":"Aktivit\u00e4t der Bankinstitute",
    "sg:phone":"+41 41 417 17 17",
    "sg:postcode":"6005",
    "sg:province":"Luzern",
    "wof:name":"Ge Capital Bank",
    "wof:placetype":"venue"
},
  "geometry": {"coordinates":[8.306809,47.05336],"type":"Point"}
}