{
  "type": "Feature",
  "properties": {
    "iso:country":"CH",
    "sg:address":"Speicherstrasse 60",
    "sg:city":"St.gallen",
    "sg:orig_category":"Herstellung von elektrischen Lampen U Leuchten",
    "sg:phone":"+41 71 230 03 33",
    "sg:postcode":"9000",
    "sg:province":"St. Gallen",
    "wof:name":"Alm Luminati Thomas",
    "wof:placetype":"venue"
},
  "geometry": {"coordinates":[9.3910512924,47.4252471924],"type":"Point"}
}