{
  "type": "Feature",
  "properties": {
    "iso:country":"CH",
    "sg:address":"Zunstrasse 11 8152 Glattbrugg. Postfach",
    "sg:city":"Glattbrugg",
    "sg:orig_category":"Sanit\u00e4r, Heizungs U L\u00fcftungsinstallation Sanit\u00e4rinstallation",
    "sg:phone":"+41 18104876",
    "sg:postcode":"8152",
    "sg:province":"Z\u00fcrich",
    "wof:name":"Engelhard Gebr\u00fcder Ag",
    "wof:placetype":"venue"
},
  "geometry": {"coordinates":[8.570019722,47.4250984192],"type":"Point"}
}