{
  "type": "Feature",
  "properties": {
    "iso:country":"CH",
    "sg:address":"Sagerainstrasse 30",
    "sg:city":"Fehraltorf",
    "sg:orig_category":"Abwasserreinigung Abwasserreinigung, Abfallbeseitigung U sonstige Entsorgung",
    "sg:postcode":"8320",
    "sg:province":"Z\u00fcrich",
    "wof:name":"Brodbeck Franz",
    "wof:placetype":"venue"
},
  "geometry": {"coordinates":[7.597851,47.499268],"type":"Point"}
}