{
  "type": "Feature",
  "properties": {
    "addr:full":"Aarbergstrasse 26 Lyss Bern 3250",
    "addr:housenumber":"26",
    "addr:postcode":"3250",
    "addr:street":"Aarbergstrasse;Bern",
    "iso:country":"CH",
    "sg:address":"Aarbergstrasse 26",
    "sg:city":"Lyss",
    "sg:orig_category":"Bestattungswesen",
    "sg:phone":"+41 32 384 67 84",
    "sg:postcode":"3250",
    "sg:province":"Bern",
    "wof:name":"Werner Geiser Bestattungsdienste",
    "wof:placetype":"venue"
},
  "geometry": {"coordinates":[7.302836,47.072575],"type":"Point"}
}