{
  "type": "Feature",
  "properties": {
    "iso:country":"CH",
    "sg:address":"Vorburg 5",
    "sg:city":"Gams",
    "sg:orig_category":"Kauf U Verkauf von Immobilien auf eigene Rechnung",
    "sg:postcode":"9473",
    "sg:province":"St. Gallen",
    "wof:name":"Alpstein Bau Ag",
    "wof:placetype":"venue"
},
  "geometry": {"coordinates":[9.4400367737,47.2066040039],"type":"Point"}
}