{
  "type": "Feature",
  "properties": {
    "iso:country":"CH",
    "sg:address":"Route Du Grand-ch\u00eane 7/9",
    "sg:city":"Lausanne",
    "sg:orig_category":"Detailhandel mit Pelzwaren",
    "sg:phone":"+41 61 411 05 82",
    "sg:postcode":"1003",
    "sg:province":"Vaud",
    "wof:name":"Fourrures Holinger Sa",
    "wof:placetype":"venue"
},
  "geometry": {"coordinates":[7.6010842323,47.5128326416],"type":"Point"}
}