{
  "type": "Feature",
  "properties": {
    "iso:country":"CH",
    "sg:address":"Piazza San Simone",
    "sg:city":"Vacallo",
    "sg:orig_category":"Fachdetailhandel in Verkaufsr\u00e4umen Herstellung U Zusammensetzung von Uhren",
    "sg:postcode":"6833",
    "sg:province":"Ticino",
    "wof:name":"Livio Anna",
    "wof:placetype":"venue"
},
  "geometry": {"coordinates":[9.0294103622,45.8433990479],"type":"Point"}
}