{
  "type": "Feature",
  "properties": {
    "iso:country":"CH",
    "sg:address":"Im Aegelsee 2 8103 Unterengstringen. Postfach",
    "sg:city":"Unterengstringen",
    "sg:orig_category":"Grosshandel mit sonstigen Konsumg\u00fctern Sonstiger Grosshandel",
    "sg:phone":"+41 17504744",
    "sg:postcode":"8103",
    "sg:province":"Z\u00fcrich",
    "wof:name":"Metvac Ag",
    "wof:placetype":"venue"
},
  "geometry": {"coordinates":[8.4466056824,47.4143218994],"type":"Point"}
}