{
  "type": "Feature",
  "properties": {
    "iso:country":"CH",
    "sg:address":"Heidenerstrasse 5",
    "sg:city":"Eggersriet",
    "sg:orig_category":"Gemeindeverwaltungen",
    "sg:phone":"+41 71 877 19 33",
    "sg:postcode":"9034",
    "sg:province":"St. Gallen",
    "wof:name":"Gemeindeverwaltung Eggersriet",
    "wof:placetype":"venue"
},
  "geometry": {"coordinates":[9.473279953,47.4424133301],"type":"Point"}
}