{
  "type": "Feature",
  "properties": {
    "iso:country":"CH",
    "sg:address":"V\u00e9lodrome Rue Du 9 1205 Gen\u00e8ve. Postfach",
    "sg:city":"Gen\u00e8ve",
    "sg:orig_category":"Detailhandel mit Waren verschiedener Art, Hauptrichtung Nahrungsmittel",
    "sg:postcode":"1205",
    "sg:province":"Gen\u00e8ve",
    "wof:name":"Elio Scirocco",
    "wof:placetype":"venue"
},
  "geometry": {"coordinates":[6.130715847,46.2004051208],"type":"Point"}
}