{
  "type": "Feature",
  "properties": {
    "iso:country":"CH",
    "sg:address":"Grabenstrasse 14",
    "sg:city":"Zug",
    "sg:orig_category":"Detailhandel mit Milcherzeugnissen U Eiern Sonstiger Fachdetailhandel mit Nahrungsmitteln, Getr\u00e4nken",
    "sg:phone":"+41 41 711 00 47",
    "sg:postcode":"6300",
    "sg:province":"Zug",
    "wof:name":"Ch\u00e4s-ueli, Ulrich Martin",
    "wof:placetype":"venue"
},
  "geometry": {"coordinates":[8.5151357651,47.1657447815],"type":"Point"}
}