{
  "type": "Feature",
  "properties": {
    "iso:country":"CH",
    "sg:address":"Hackenbergstrasse 15",
    "sg:city":"Balterswil",
    "sg:orig_category":"Sportvereine Ballsport Badminton",
    "sg:phone":"+41 71 923 93 03",
    "sg:postcode":"8362",
    "sg:province":"Thurgau",
    "wof:name":"Badminton-club Eschlikon",
    "wof:placetype":"venue"
},
  "geometry": {"coordinates":[8.9399089813,47.4519615173],"type":"Point"}
}