{
  "type": "Feature",
  "properties": {
    "iso:country":"CH",
    "sg:address":"Utzenstorfstrasse 36",
    "sg:city":"Koppigen",
    "sg:orig_category":"Hoch U Tiefbau",
    "sg:phone":"+41 34 413 14 26",
    "sg:postcode":"3425",
    "sg:province":"Bern",
    "wof:name":"Schneider Ag Bauunternehmung",
    "wof:placetype":"venue"
},
  "geometry": {"coordinates":[7.5949950218,47.1297645569],"type":"Point"}
}