{
  "type": "Feature",
  "properties": {
    "iso:country":"CH",
    "sg:address":"Winkelstrasse 2",
    "sg:city":"Egerkingen",
    "sg:orig_category":"Cim Modules",
    "sg:phone":"+41 62 388 99 22",
    "sg:postcode":"4622",
    "sg:province":"Solothurn",
    "wof:name":"Eigner (switzerland) Ag",
    "wof:placetype":"venue"
},
  "geometry": {"coordinates":[7.796917,47.316162],"type":"Point"}
}