{
  "type": "Feature",
  "properties": {
    "iso:country":"CH",
    "sg:address":"Unterer Reckholder 4.",
    "sg:city":"Niederhelfenschwil",
    "sg:orig_category":"Allgemeiner Hoch U Tiefbau",
    "sg:phone":"+41 71 947 16 10",
    "sg:postcode":"9527",
    "sg:province":"St. Gallen",
    "wof:name":"Schefer Markus, Baugesch\u00e4ft.",
    "wof:placetype":"venue"
},
  "geometry": {"coordinates":[9.182403,47.473911],"type":"Point"}
}