{
  "type": "Feature",
  "properties": {
    "iso:country":"CH",
    "sg:address":"Eichtal 8634 Hombrechtikon. Postfach",
    "sg:city":"Hombrechtikon",
    "sg:orig_category":"Herstellung von sonstigen elektrischen Ausr\u00fcstungen",
    "sg:phone":"+41 62 771 21 60",
    "sg:postcode":"8634",
    "sg:province":"Z\u00fcrich",
    "wof:name":"F. Michel Elektr. Apparate Reinach",
    "wof:placetype":"venue"
},
  "geometry": {"coordinates":[8.1791858673,47.2550048828],"type":"Point"}
}