{
  "type": "Feature",
  "properties": {
    "iso:country":"CH",
    "sg:address":"Tanzg\u00e4sslein 2 4051 Basel. Postfach",
    "sg:city":"Basel",
    "sg:orig_category":"Zahnarztpraxen",
    "sg:phone":"+41 61 261 51 25",
    "sg:postcode":"4001",
    "sg:province":"Basel-Stadt",
    "wof:name":"Dr.med.dent.marianne Cathomen Zahn\u00e4rztin",
    "wof:placetype":"venue"
},
  "geometry": {"coordinates":[7.5876560211,47.5593833923],"type":"Point"}
}