{
  "type": "Feature",
  "properties": {
    "iso:country":"CH",
    "sg:address":"Schwerzistrasse 5",
    "sg:city":"Ruswil",
    "sg:orig_category":"Wirtschaftspr\u00fcfung, Steuerberatung U Treuhand",
    "sg:phone":"+41 41 495 28 75",
    "sg:postcode":"6017",
    "sg:province":"Luzern",
    "wof:name":"Rottal Treuhand Ag",
    "wof:placetype":"venue"
},
  "geometry": {"coordinates":[8.1264600754,47.0844116211],"type":"Point"}
}