{
  "type": "Feature",
  "properties": {
    "iso:country":"CH",
    "sg:address":"Bahnhofstrasse 12",
    "sg:city":"Sargans",
    "sg:orig_category":"Arztpraxen",
    "sg:phone":"+41 81 723 04 04",
    "sg:postcode":"7320",
    "sg:province":"St. Gallen",
    "wof:name":"Dr.med. Anna Barbara Vogt Spezial\u00e4rztin Fmh",
    "wof:placetype":"venue"
},
  "geometry": {"coordinates":[9.441901,47.04604],"type":"Point"}
}