{
  "type": "Feature",
  "properties": {
    "iso:country":"CH",
    "sg:address":"Chemin Des Brumes 2",
    "sg:city":"Crassier",
    "sg:orig_category":"Herstellung von sonstigen landwirtschaftlichen Maschinen Mechanik",
    "sg:phone":"+41 22 367 15 76",
    "sg:postcode":"1263",
    "sg:province":"Vaud",
    "wof:name":"Boulenaz Philippe S\u00e0rl",
    "wof:placetype":"venue"
},
  "geometry": {"coordinates":[6.1686577797,46.3698005676],"type":"Point"}
}