{
  "type": "Feature",
  "properties": {
    "iso:country":"CH",
    "sg:address":"Kernserstrasse 9",
    "sg:city":"Sarnen",
    "sg:orig_category":"Physiotherapie",
    "sg:phone":"+41 41 660 11 45",
    "sg:postcode":"6060",
    "sg:province":"Obwalden",
    "wof:name":"Helma Kaspers Physiotherapie",
    "wof:placetype":"venue"
},
  "geometry": {"coordinates":[8.2492780685,46.8961982727],"type":"Point"}
}