{
  "type": "Feature",
  "properties": {
    "iso:country":"CH",
    "sg:address":"Lochacker 11",
    "sg:city":"Hinwil",
    "sg:classifiers":[
        {
            "category":"Landmark",
            "subcategory":"Square",
            "type":"Public Place"
        }
    ],
    "sg:phone":"+41 19371751",
    "sg:postcode":"8340",
    "sg:province":"Z\u00fcrich",
    "sg:tags":[
        "fault",
        "location",
        "cable"
    ],
    "wof:name":"Gasenzer Ag",
    "wof:placetype":"venue"
},
  "geometry": {"coordinates":[8.85398,47.299419],"type":"Point"}
}