{
  "type": "Feature",
  "properties": {
    "iso:country":"CH",
    "sg:address":"Brunngasse 21",
    "sg:city":"Bern",
    "sg:classifiers":[
        {
            "category":"Communications",
            "subcategory":"Radio Station",
            "type":"Services"
        }
    ],
    "sg:phone":"+41 71 385 77 22",
    "sg:postcode":"3011",
    "sg:province":"Bern",
    "sg:tags":[
        "fernsehanstalten",
        "u"
    ],
    "wof:name":"Abella Musik Versand Ag Software, Klassik, Dvd, Vido Etc.",
    "wof:placetype":"venue"
},
  "geometry": {"coordinates":[9.2512149811,47.4132652283],"type":"Point"}
}