{
  "type": "Feature",
  "properties": {
    "iso:country":"CH",
    "sg:address":"Lerchenstrasse 5",
    "sg:city":"Wangs",
    "sg:orig_category":"Allgemeiner Hochbau Strassenbau",
    "sg:phone":"+41 79 293 35 26",
    "sg:postcode":"7323",
    "sg:province":"St. Gallen",
    "wof:name":"Albin Zimmermann Baugesch\u00e4ft",
    "wof:placetype":"venue"
},
  "geometry": {"coordinates":[9.431483,47.031666],"type":"Point"}
}