{
  "type": "Feature",
  "properties": {
    "iso:country":"CH",
    "sg:address":"Ettingerstrasse 16",
    "sg:city":"Therwil",
    "sg:orig_category":"Instandhaltung U Reparatur von Automobilen",
    "sg:phone":"+41 79 645 00 76",
    "sg:postcode":"4106",
    "sg:province":"Basel-Landschaft",
    "wof:name":"Garage Willi Gutzwiller Ag",
    "wof:placetype":"venue"
},
  "geometry": {"coordinates":[7.5520291328,47.4969902039],"type":"Point"}
}