{
  "type": "Feature",
  "properties": {
    "iso:country":"CH",
    "sg:address":"Ipsachstrasse 16 2560 Nidau. Postfach",
    "sg:city":"Nidau",
    "sg:orig_category":"Herstellung von sonstigen elektrischen Ausr\u00fcstungen",
    "sg:phone":"+41 32 332 74 74",
    "sg:postcode":"2560",
    "sg:province":"Bern",
    "wof:name":"C-mill-technologie Ag",
    "wof:placetype":"venue"
},
  "geometry": {"coordinates":[7.2376389503,47.1175041199],"type":"Point"}
}