{
  "type": "Feature",
  "properties": {
    "iso:country":"CH",
    "sg:address":"Kasinostrasse 32",
    "sg:city":"Aarau",
    "sg:orig_category":"Detailhandel mit Brillen U anderen Sehhilfen Detailhandel mit medizinischen U orthop\u00e4dischen Artikel",
    "sg:phone":"+41 62 824 88 78",
    "sg:postcode":"5000",
    "sg:province":"Aargau",
    "wof:name":"H\u00f6rzentrum Gfeller Stephan",
    "wof:placetype":"venue"
},
  "geometry": {"coordinates":[8.047051,47.391693],"type":"Point"}
}