{
  "type": "Feature",
  "properties": {
    "iso:country":"CH",
    "sg:address":"Utengasse 45",
    "sg:city":"Basel",
    "sg:orig_category":"Sonstige pers\u00f6nliche Dienstleistungen",
    "sg:phone":"+41 61 681 19 76",
    "sg:postcode":"4058",
    "sg:province":"Basel-Stadt",
    "wof:name":"R. & M. Zaugg",
    "wof:placetype":"venue"
},
  "geometry": {"coordinates":[7.5945401192,47.5592918396],"type":"Point"}
}