{
  "type": "Feature",
  "properties": {
    "iso:country":"CH",
    "sg:address":"Bahnhofstrasse 1 5322 Koblenz. Postfach 35",
    "sg:city":"Koblenz",
    "sg:orig_category":"Grosshandel mit sonstigen Maschinen U Ausr\u00fcstungen f\u00fcr Industrie, Handel U Schiffahrt",
    "sg:phone":"+41 56 246 22 33",
    "sg:postcode":"5322",
    "sg:province":"Aargau",
    "wof:name":"Flohr Industrietechnik",
    "wof:placetype":"venue"
},
  "geometry": {"coordinates":[8.2341403961,47.6077461243],"type":"Point"}
}