{
  "type": "Feature",
  "properties": {
    "iso:country":"CH",
    "sg:address":"Bahnhofstrasse 72",
    "sg:city":"Dottikon",
    "sg:orig_category":"Sonstiger Grosshandel",
    "sg:postcode":"5605",
    "sg:province":"Aargau",
    "wof:name":"Tim-trading, Tuncer Melek",
    "wof:placetype":"venue"
},
  "geometry": {"coordinates":[8.2341623306,47.3757896423],"type":"Point"}
}