{
  "type": "Feature",
  "properties": {
    "iso:country":"CH",
    "sg:address":"Im Feld 28 8424 Embrach. Postfach",
    "sg:city":"Embrach",
    "sg:orig_category":"Herstellung von medizinischen U chirurgischen Ger\u00e4ten sowie orthop\u00e4dischen Vorrichtungen",
    "sg:postcode":"8424",
    "sg:province":"Z\u00fcrich",
    "wof:name":"Amipa Dr. T.d. Tibetische Medizin Gmbh",
    "wof:placetype":"venue"
},
  "geometry": {"coordinates":[8.5926322937,47.5150794983],"type":"Point"}
}