{
  "type": "Feature",
  "properties": {
    "iso:country":"CH",
    "sg:address":"Baarerstrasse 110a",
    "sg:city":"Zug",
    "sg:orig_category":"Non-Classified Establishments",
    "sg:postcode":"6300",
    "sg:province":"Zug",
    "wof:name":"Rh-group Holding Ag",
    "wof:placetype":"venue"
},
  "geometry": {"coordinates":[9.5029401779,47.0111198425],"type":"Point"}
}