{
  "type": "Feature",
  "properties": {
    "iso:country":"CH",
    "sg:address":"Belpbergstrasse 14",
    "sg:city":"Belp",
    "sg:orig_category":"Detailhandel mit Fleisch U Fleischwaren Grosshandel mit Fleisch U Fleischwaren",
    "sg:postcode":"3123",
    "sg:province":"Bern",
    "wof:name":"Alfred Reber",
    "wof:placetype":"venue"
},
  "geometry": {"coordinates":[7.500316143,46.8888244629],"type":"Point"}
}