{
  "type": "Feature",
  "properties": {
    "iso:country":"CH",
    "sg:address":"Br\u00fcnigstrasse",
    "sg:city":"Meiringen",
    "sg:orig_category":"Sportvereine Turnen",
    "sg:phone":"+41 33 971 27 30",
    "sg:postcode":"3860",
    "sg:province":"Bern",
    "wof:name":"Turnverein Meiringen",
    "wof:placetype":"venue"
},
  "geometry": {"coordinates":[8.1782541275,46.7307891846],"type":"Point"}
}