{
  "type": "Feature",
  "properties": {
    "iso:country":"CH",
    "sg:address":"Centre Du Bief 1110 Morges Case Postale 328",
    "sg:city":"Morges",
    "sg:orig_category":"Detailhandel mit Bekleidung Grosshandel mit Bekleidung",
    "sg:phone":"+41 61 401 28 79",
    "sg:postcode":"1110",
    "sg:province":"Vaud",
    "wof:name":"City Fashion Thomas T\u00e4schler",
    "wof:placetype":"venue"
},
  "geometry": {"coordinates":[7.566477,47.513687],"type":"Point"}
}