{
  "type": "Feature",
  "properties": {
    "iso:country":"CH",
    "sg:address":"4324",
    "sg:city":"Obermumpf",
    "sg:orig_category":"Organisationen des Gesundheitswesen",
    "sg:phone":"+41 71 761 19 23",
    "sg:postcode":"4324",
    "sg:province":"Aargau",
    "wof:name":"Samariterverein Oberriet",
    "wof:placetype":"venue"
},
  "geometry": {"coordinates":[9.5689268112,47.3240852356],"type":"Point"}
}