{
  "type": "Feature",
  "properties": {
    "iso:country":"CH",
    "sg:address":"H\u00f6libachstrasse 36",
    "sg:city":"Obfelden",
    "sg:orig_category":"Detailhandel mit elektrischen Haushalts-,Radio U Fernsehger\u00e4ten sowie Musikinstrumenten Herstellung ",
    "sg:phone":"+41 17610414",
    "sg:postcode":"8912",
    "sg:province":"Z\u00fcrich",
    "wof:name":"Hansj\u00fcrg K\u00fcbler Atelier F\u00fcr Geigenbau",
    "wof:placetype":"venue"
},
  "geometry": {"coordinates":[8.4292383194,47.2689476013],"type":"Point"}
}