{
  "type": "Feature",
  "properties": {
    "iso:country":"CH",
    "sg:address":"Krummeneggweg 5",
    "sg:city":"Gasel",
    "sg:orig_category":"Malerei",
    "sg:phone":"+41 31 849 09 37",
    "sg:postcode":"3144",
    "sg:province":"Bern",
    "wof:name":"Hansruedi & Thomas Locher Malergesch\u00e4ft",
    "wof:placetype":"venue"
},
  "geometry": {"coordinates":[7.426117897,46.8905105591],"type":"Point"}
}