{
  "type": "Feature",
  "properties": {
    "iso:country":"CH",
    "sg:address":"Untere Allmeind 3a",
    "sg:city":"Ennenda",
    "sg:orig_category":"Herstellung von sonstigen landwirtschaftlichen Maschinen Mechanische Werkst\u00e4tten",
    "sg:phone":"+41 79 351 28 79",
    "sg:postcode":"8755",
    "sg:province":"Glarus",
    "wof:name":"Jakob M\u00fcller Mofa & Landmaschinen",
    "wof:placetype":"venue"
},
  "geometry": {"coordinates":[7.7121701241,46.7682914734],"type":"Point"}
}