{
  "type": "Feature",
  "properties": {
    "iso:country":"CH",
    "sg:address":"1595",
    "sg:city":"Faoug",
    "sg:classifiers":[
        {
            "category":"Travel",
            "subcategory":"Hotels & Motels",
            "type":"Entertainment"
        }
    ],
    "sg:phone":"+41 24 491 11 94",
    "sg:postcode":"1595",
    "sg:province":"Bern",
    "sg:tags":[
        "hotels",
        "mit",
        "restaurant"
    ],
    "wof:name":"H\u00f4tel Du Cerf",
    "wof:placetype":"venue"
},
  "geometry": {"coordinates":[7.0534849167,46.3616447449],"type":"Point"}
}