{
  "type": "Feature",
  "properties": {
    "iso:country":"CH",
    "sg:address":"Lerzenstrasse 13a",
    "sg:city":"Dietikon",
    "sg:orig_category":"Einzelhandel mit Automobilteilen U Zubeh\u00f6r Herstellung von Bereifungen",
    "sg:phone":"+41 17422842",
    "sg:postcode":"8953",
    "sg:province":"Z\u00fcrich",
    "wof:name":"Pneu O. Schreiber",
    "wof:placetype":"venue"
},
  "geometry": {"coordinates":[8.3989973068,47.4171142578],"type":"Point"}
}