{
  "type": "Feature",
  "properties": {
    "addr:full":"Schipfe 21 Z\u00fcrich Z\u00fcrich 8001",
    "addr:housenumber":"21",
    "addr:postcode":"8001",
    "addr:street":"Schipfe",
    "iso:country":"CH",
    "sg:address":"Schipfe 21",
    "sg:city":"Z\u00fcrich",
    "sg:orig_category":"Detailhandel mit Antiquit\u00e4ten",
    "sg:phone":"+41 12118928",
    "sg:postcode":"8001",
    "sg:province":"Z\u00fcrich",
    "wof:name":"Boutique Fou-knitting Art Ulrike Dittmann",
    "wof:placetype":"venue"
},
  "geometry": {"coordinates":[8.541638,47.372261],"type":"Point"}
}