{
  "type": "Feature",
  "properties": {
    "iso:country":"CH",
    "sg:address":"Schipfe 21",
    "sg:city":"Z\u00fcrich",
    "sg:orig_category":"Detailhandel mit Antiquit\u00e4ten",
    "sg:phone":"+41 12118928",
    "sg:postcode":"8001",
    "sg:province":"Z\u00fcrich",
    "wof:name":"Boutique Fou-knitting Art Ulrike Dittmann",
    "wof:placetype":"venue"
},
  "geometry": {"coordinates":[8.541638,47.372261],"type":"Point"}
}