{
  "type": "Feature",
  "properties": {
    "iso:country":"CH",
    "sg:address":"Temple Rue Du 11",
    "sg:city":"Payerne",
    "sg:orig_category":"Non-Classified Establishments",
    "sg:postcode":"1530",
    "sg:province":"Vaud",
    "wof:name":"Si Solair Sa",
    "wof:placetype":"venue"
},
  "geometry": {"coordinates":[6.9389801025,46.8207931519],"type":"Point"}
}