{
  "type": "Feature",
  "properties": {
    "iso:country":"CH",
    "sg:address":"Tribschenstrasse 9 6005 Luzern. Postfach 5004",
    "sg:city":"Luzern",
    "sg:orig_category":"Grosshandel mit chemischen Erzeugnissen Grosshandel mit festen Brennstoffen U Mineral\u00f6lerzeugnissen",
    "sg:phone":"+41 41 360 76 76",
    "sg:postcode":"6002",
    "sg:province":"Luzern",
    "wof:name":"Winkler & Fischer Ag",
    "wof:placetype":"venue"
},
  "geometry": {"coordinates":[8.3126792908,47.0440940857],"type":"Point"}
}