{
  "type": "Feature",
  "properties": {
    "iso:country":"CH",
    "sg:address":"Kyburgstrasse 29",
    "sg:city":"Z\u00fcrich",
    "sg:orig_category":"Sanit\u00e4r, Heizungs U L\u00fcftungsinstallation Sanit\u00e4rinstallation",
    "sg:phone":"+41 12726675",
    "sg:postcode":"8037",
    "sg:province":"Z\u00fcrich",
    "wof:name":"Debrunner V. Ag",
    "wof:placetype":"venue"
},
  "geometry": {"coordinates":[8.5261478424,47.3931007385],"type":"Point"}
}