{
  "type": "Feature",
  "properties": {
    "iso:country":"CH",
    "sg:address":"Hauptstrasse 90",
    "sg:city":"Pratteln",
    "sg:orig_category":"Gymnastik U Fitnesszentren Saunas, Solarien, Fitnesszentren U \u00e4hnliches",
    "sg:phone":"+41 32 731 09 59",
    "sg:postcode":"4133",
    "sg:province":"Basel-Landschaft",
    "wof:name":"Fitness Point Forme S\u00e0rl",
    "wof:placetype":"venue"
},
  "geometry": {"coordinates":[6.8840880394,46.9836235046],"type":"Point"}
}