{
  "type": "Feature",
  "properties": {
    "iso:country":"CH",
    "sg:address":"General Guisan-strasse 35 4144 Arlesheim. Postfach",
    "sg:city":"Arlesheim",
    "sg:orig_category":"Sonstige mit der Informatik verbundene T\u00e4tigkeiten",
    "sg:postcode":"4144",
    "sg:province":"Basel-Landschaft",
    "wof:name":"It1 Gmbh",
    "wof:placetype":"venue"
},
  "geometry": {"coordinates":[7.6142821312,47.5002174377],"type":"Point"}
}