{
  "type": "Feature",
  "properties": {
    "iso:country":"CH",
    "sg:address":"La Ruche",
    "sg:city":"Champvent",
    "sg:orig_category":"Grosshandel mit Getreide, Saatgut U Futtermitteln",
    "sg:phone":"+41 24 459 16 21",
    "sg:postcode":"1443",
    "sg:province":"Vaud",
    "wof:name":"M\u00fcller Johann",
    "wof:placetype":"venue"
},
  "geometry": {"coordinates":[6.5572400093,46.7774353027],"type":"Point"}
}