{
  "type": "Feature",
  "properties": {
    "iso:country":"CH",
    "sg:address":"R\u00e9sidence Bellevue F\u00fcrgien-ob 6363 F\u00fcrigen. Postfach",
    "sg:city":"F\u00fcrigen",
    "sg:orig_category":"Unclassifiable Establishments",
    "sg:postcode":"6363",
    "sg:province":"Nidwalden",
    "wof:name":"Elbet Ag",
    "wof:placetype":"venue"
},
  "geometry": {"coordinates":[9.3820972443,47.4427871704],"type":"Point"}
}