{
  "type": "Feature",
  "properties": {
    "iso:country":"CH",
    "sg:address":"Hofackerstr. 3",
    "sg:city":"B\u00fctschwil",
    "sg:classifiers":[
        {
            "category":"Professional",
            "type":"Services"
        }
    ],
    "sg:phone":"+41 71 982 82 82",
    "sg:postcode":"9606",
    "sg:province":"St. Gallen",
    "sg:tags":[
        "transport",
        "road"
    ],
    "wof:name":"Beat Scherrer Ag",
    "wof:placetype":"venue"
},
  "geometry": {"coordinates":[9.0750179291,47.3627586365],"type":"Point"}
}