{
  "type": "Feature",
  "properties": {
    "addr:full":"Gewerbestrasse 1 Suhr Aargau 5034",
    "addr:housenumber":"1",
    "addr:postcode":"5034",
    "addr:street":"Gewerbestrasse",
    "iso:country":"CH",
    "sg:address":"Gewerbestrasse 1",
    "sg:city":"Suhr",
    "sg:orig_category":"Bauspenglerei Zimmerei, Dachdeckerei, Bauspenglerei U Abdichtung",
    "sg:phone":"+41 79 240 72 36",
    "sg:postcode":"5034",
    "sg:province":"Aargau",
    "wof:name":"Fauguel & Cie.",
    "wof:placetype":"venue"
},
  "geometry": {"coordinates":[6.483489,46.904957],"type":"Point"}
}