{
  "type": "Feature",
  "properties": {
    "iso:country":"CH",
    "sg:address":"2950 Courgenay Case Postale 139",
    "sg:city":"Courgenay",
    "sg:orig_category":"Sportvereine Ballsport Tennis",
    "sg:postcode":"2950",
    "sg:province":"Jura",
    "wof:name":"Tennisclub Courgenay",
    "wof:placetype":"venue"
},
  "geometry": {"coordinates":[7.1266851425,47.403213501],"type":"Point"}
}