{
  "type": "Feature",
  "properties": {
    "iso:country":"CH",
    "sg:address":"Fabrikstrasse 8 3360 Herzogenbuchsee. Postfach",
    "sg:city":"Herzogenbuchsee",
    "sg:orig_category":"Elektrizit\u00e4tsversorgung Gasversorgung",
    "sg:phone":"+41 17252334",
    "sg:postcode":"3360",
    "sg:province":"Bern",
    "wof:name":"Gemeindewerke Horgen",
    "wof:placetype":"venue"
},
  "geometry": {"coordinates":[8.5971317291,47.2611961365],"type":"Point"}
}