{
  "type": "Feature",
  "properties": {
    "iso:country":"CH",
    "sg:address":"B\u00fchlwiesenstrasse 17",
    "sg:city":"Z\u00fcrich",
    "sg:orig_category":"Unternehmensberatung",
    "sg:phone":"+41 13003132",
    "sg:postcode":"8052",
    "sg:province":"Z\u00fcrich",
    "wof:name":"Consort B, Gloor, Hausammann & Co",
    "wof:placetype":"venue"
},
  "geometry": {"coordinates":[8.5481128693,47.4161148071],"type":"Point"}
}