{
  "type": "Feature",
  "properties": {
    "iso:country":"CH",
    "sg:address":"Riedtwilstrasse 8 3472 Wynigen. Postfach 194",
    "sg:city":"Wynigen",
    "sg:orig_category":"Sanit\u00e4r, Heizungs U L\u00fcftungsinstallation Sanit\u00e4rinstallation",
    "sg:phone":"+41 55 410 25 75",
    "sg:postcode":"3472",
    "sg:province":"Bern",
    "wof:name":"A. Moritz Ag, Sanit\u00e4re Anlagen",
    "wof:placetype":"venue"
},
  "geometry": {"coordinates":[8.777176857,47.2016677856],"type":"Point"}
}