{
  "type": "Feature",
  "properties": {
    "iso:country":"CH",
    "sg:address":"Rebenweg 262",
    "sg:city":"Hornussen",
    "sg:orig_category":"Detailhandel mit Beleuchtungs U Haushaltsgegenst\u00e4nden Detailhandel mit elektrischen Haushalts, Radio",
    "sg:phone":"+41 71 388 70 00",
    "sg:postcode":"5075",
    "sg:province":"Aargau",
    "wof:name":"Service 7000 Ag Haushaltapparate & -artikel",
    "wof:placetype":"venue"
},
  "geometry": {"coordinates":[9.23548,47.417671],"type":"Point"}
}