{
  "type": "Feature",
  "properties": {
    "iso:country":"CH",
    "sg:address":"Erlenweg 6",
    "sg:city":"Bern",
    "sg:orig_category":"Kosmetikinstitute",
    "sg:phone":"+41 31 312 16 45",
    "sg:postcode":"3005",
    "sg:province":"Bern",
    "wof:name":"Beatrice Ryser Kosmetik & Solarium Twice",
    "wof:placetype":"venue"
},
  "geometry": {"coordinates":[7.4415597916,46.9431495667],"type":"Point"}
}