{
  "type": "Feature",
  "properties": {
    "iso:country":"CH",
    "sg:address":"Rue De Bourg 8",
    "sg:city":"Lausanne",
    "sg:orig_category":"Detailhandel mit Bekleidung Detailhandel mit Damenbekleidung",
    "sg:phone":"+41 21 312 38 57",
    "sg:postcode":"1003",
    "sg:province":"Vaud",
    "wof:name":"Croquelois Lucilla",
    "wof:placetype":"venue"
},
  "geometry": {"coordinates":[6.635274,46.519894],"type":"Point"}
}