{
  "type": "Feature",
  "properties": {
    "iso:country":"CH",
    "sg:address":"Engehaldenstrasse 20",
    "sg:city":"Bern",
    "sg:orig_category":"Betrieb von Taxis",
    "sg:phone":"+41 31 301 00 11",
    "sg:postcode":"3012",
    "sg:province":"Bern",
    "wof:name":"Ac-taxi Rolf Casanovas",
    "wof:placetype":"venue"
},
  "geometry": {"coordinates":[7.43983,46.955482],"type":"Point"}
}