{
  "type": "Feature",
  "properties": {
    "iso:country":"CH",
    "sg:address":"1042",
    "sg:city":"Bioley-orjulaz",
    "sg:orig_category":"G\u00fcterbef\u00f6rderung im Strassenverkehr",
    "sg:phone":"+41 41 850 67 64",
    "sg:postcode":"1042",
    "sg:province":"Vaud",
    "wof:name":"Kostic Goran, Transporte",
    "wof:placetype":"venue"
},
  "geometry": {"coordinates":[8.4403686523,47.0841140747],"type":"Point"}
}