{
  "type": "Feature",
  "properties": {
    "iso:country":"CH",
    "sg:address":"Murtenstrasse 7",
    "sg:city":"Biel/bienne",
    "sg:orig_category":"Detailhandel mit Waren verschiedener Art, Hauptrichtung Nahrungsmittel",
    "sg:phone":"+41 32 322 62 04",
    "sg:postcode":"2502",
    "sg:province":"Bern",
    "wof:name":"Capri Traiteur Gmbh",
    "wof:placetype":"venue"
},
  "geometry": {"coordinates":[7.2456698418,47.1320762634],"type":"Point"}
}