{
  "type": "Feature",
  "properties": {
    "iso:country":"CH",
    "sg:address":"Dorfstrasse 4",
    "sg:city":"Uttigen",
    "sg:orig_category":"Elektroinstallation",
    "sg:phone":"+41 33 345 10 70",
    "sg:postcode":"3628",
    "sg:province":"Bern",
    "wof:name":"Brunner & Imboden Ag",
    "wof:placetype":"venue"
},
  "geometry": {"coordinates":[7.5736970901,46.7948951721],"type":"Point"}
}