{
  "type": "Feature",
  "properties": {
    "iso:country":"CH",
    "sg:address":"M\u00fcllheimerstrasse 83",
    "sg:city":"Basel",
    "sg:orig_category":"Interessenvertretungen",
    "sg:phone":"+41 61 691 99 16",
    "sg:postcode":"4057",
    "sg:province":"Basel-Stadt",
    "wof:name":"Rehovot-jesus Im Fremden",
    "wof:placetype":"venue"
},
  "geometry": {"coordinates":[7.5921359062,47.5674781799],"type":"Point"}
}