{
  "type": "Feature",
  "properties": {
    "iso:country":"CH",
    "sg:address":"Bei Der K\u00e4serei",
    "sg:city":"Reutigen",
    "sg:orig_category":"Allgemeiner Hoch U Tiefbau Hoch U Tiefbau",
    "sg:phone":"+41 71 686 86 65",
    "sg:postcode":"3647",
    "sg:province":"Bern",
    "wof:name":"Kiag",
    "wof:placetype":"venue"
},
  "geometry": {"coordinates":[9.199857,47.642509],"type":"Point"}
}