{
  "type": "Feature",
  "properties": {
    "iso:country":"CH",
    "sg:address":"Schulhausweg 2",
    "sg:city":"Niederwichtrach",
    "sg:orig_category":"Primarschulen",
    "sg:phone":"+41 31 781 12 09",
    "sg:postcode":"3114",
    "sg:province":"Bern",
    "wof:name":"Primarschule",
    "wof:placetype":"venue"
},
  "geometry": {"coordinates":[7.5780911446,46.8507652283],"type":"Point"}
}