{
  "type": "Feature",
  "properties": {
    "iso:country":"CH",
    "sg:address":"Friedaustrasse 9 8952 Schlieren. Postfach",
    "sg:city":"Schlieren",
    "sg:orig_category":"Instandhaltung U Reparatur von Automobilen",
    "sg:postcode":"8952",
    "sg:province":"Z\u00fcrich",
    "wof:name":"Garage Varini Giulio",
    "wof:placetype":"venue"
},
  "geometry": {"coordinates":[8.4504365921,47.4015388489],"type":"Point"}
}