{
  "type": "Feature",
  "properties": {
    "addr:full":"Klosbachstrasse 85 8032 Z\u00fcrich 32 Zust. Postfach Z\u00fcrich Z\u00fcrich 8032",
    "addr:housenumber":"85;32",
    "addr:postcode":"8032;8032",
    "addr:street":"Klosbachstrasse;Postfach",
    "iso:country":"CH",
    "sg:address":"Klosbachstrasse 85 8032 Z\u00fcrich 32 Zust. Postfach",
    "sg:city":"Z\u00fcrich",
    "sg:orig_category":"Detailhandel mit B\u00fcchern, Zeitungen, Schreib U Papeteriewaren",
    "sg:phone":"+41 12685240",
    "sg:postcode":"8032",
    "sg:province":"Z\u00fcrich",
    "wof:name":"Intervinum Ag",
    "wof:placetype":"venue"
},
  "geometry": {"coordinates":[8.56797,47.36684],"type":"Point"}
}