{
  "type": "Feature",
  "properties": {
    "iso:country":"CH",
    "sg:address":"In Gassen 16",
    "sg:city":"Z\u00fcrich",
    "sg:classifiers":[
        {
            "category":"Restaurant",
            "type":"Food & Drink"
        }
    ],
    "sg:phone":"+41 12211805",
    "sg:postcode":"8001",
    "sg:province":"Z\u00fcrich",
    "wof:name":"Restaurant Bierhalle Kropf",
    "wof:placetype":"venue"
},
  "geometry": {"coordinates":[8.5401554108,47.3706512451],"type":"Point"}
}