{
  "type": "Feature",
  "properties": {
    "iso:country":"CH",
    "sg:address":"Schaffhauserstrasse 285",
    "sg:city":"Z\u00fcrich",
    "sg:orig_category":"Kosmetikinstitute",
    "sg:phone":"+41 13112204",
    "sg:postcode":"8057",
    "sg:province":"Z\u00fcrich",
    "wof:name":"Mirella Laezza Kosmetikinstitut Artiface",
    "wof:placetype":"venue"
},
  "geometry": {"coordinates":[8.5481376648,47.4054374695],"type":"Point"}
}