{
  "type": "Feature",
  "properties": {
    "addr:full":"Merkurstrasse 12 Winterthur Z\u00fcrich 8400",
    "addr:housenumber":"12",
    "addr:postcode":"8400",
    "addr:street":"Merkurstrasse",
    "iso:country":"CH",
    "sg:address":"Merkurstrasse 12",
    "sg:city":"Winterthur",
    "sg:orig_category":"Architektur U Ingenieurb\u00fcros",
    "sg:phone":"+41 32 342 05 25",
    "sg:postcode":"8400",
    "sg:province":"Z\u00fcrich",
    "wof:name":"Agfar Ag F\u00fcr Automation Und Robotik",
    "wof:placetype":"venue"
},
  "geometry": {"coordinates":[7.255711,47.146076],"type":"Point"}
}