{
  "type": "Feature",
  "properties": {
    "iso:country":"CH",
    "sg:address":"Avenue Beauregard 12 1700 Fribourg. Postfach",
    "sg:city":"Fribourg",
    "sg:orig_category":"Wirtschaftspr\u00fcfung, Steuerberatung U Treuhand",
    "sg:phone":"+41 26 424 51 51",
    "sg:postcode":"1709",
    "sg:province":"Fribourg",
    "wof:name":"Bfb Soci\u00e9t\u00e9 Fiduciaire Bourquin Fr\u00e8res Et B\u00e9ran Sa, Succursale De Fribourg",
    "wof:placetype":"venue"
},
  "geometry": {"coordinates":[7.1475830078,46.802028656],"type":"Point"}
}