{
  "type": "Feature",
  "properties": {
    "iso:country":"CH",
    "sg:address":"Rte De Martherenges 12",
    "sg:city":"Moudon",
    "sg:orig_category":"Mechanik",
    "sg:phone":"+41 21 905 27 39",
    "sg:postcode":"1510",
    "sg:province":"Vaud",
    "wof:name":"Meystre M\u00e9canique Service",
    "wof:placetype":"venue"
},
  "geometry": {"coordinates":[6.7928500175,46.6731109619],"type":"Point"}
}