{
  "type": "Feature",
  "properties": {
    "iso:country":"CH",
    "sg:address":"Im Leib\u00fcel 5",
    "sg:city":"Elgg",
    "sg:orig_category":"Architekturb\u00fcros",
    "sg:phone":"+41 56 225 17 23",
    "sg:postcode":"8353",
    "sg:province":"Z\u00fcrich",
    "wof:name":"J\u00fcrg Willimann Architekturb\u00fcro",
    "wof:placetype":"venue"
},
  "geometry": {"coordinates":[8.244269,47.461193],"type":"Point"}
}