{
  "type": "Feature",
  "properties": {
    "iso:country":"CH",
    "sg:address":"Br\u00fchlstrasse 13",
    "sg:city":"Attiswil",
    "sg:orig_category":"Sportschulen Wassersport",
    "sg:phone":"+41 32 637 21 40",
    "sg:postcode":"4536",
    "sg:province":"Bern",
    "wof:name":"Urs Grossenbacher Bootsfahrschule",
    "wof:placetype":"venue"
},
  "geometry": {"coordinates":[7.6128358841,47.245552063],"type":"Point"}
}