{
  "type": "Feature",
  "properties": {
    "iso:country":"CH",
    "sg:address":"Bachlettenstrasse 8 4054 Basel. Postfach",
    "sg:city":"Basel",
    "sg:orig_category":"Herstellung von medizinischen U chirurgischen Ger\u00e4ten sowie orthop\u00e4dischen Vorrichtungen",
    "sg:phone":"+41 61 303 80 94",
    "sg:postcode":"4051",
    "sg:province":"Basel-Stadt",
    "wof:name":"Ceramik-art Dental Gmbh Zahntechnisches Labor Usw",
    "wof:placetype":"venue"
},
  "geometry": {"coordinates":[7.5808591843,47.5505485535],"type":"Point"}
}