{
  "type": "Feature",
  "properties": {
    "iso:country":"CH",
    "sg:address":"Freiburgstrasse 450",
    "sg:city":"Bern",
    "sg:orig_category":"Grosshandel mit sonstigen Konsumg\u00fctern Handelsvermittlung von Textilien, Bekleidung, Schuhen U Leder",
    "sg:phone":"+41 31 381 09 10",
    "sg:postcode":"3018",
    "sg:province":"Bern",
    "wof:name":"Wiedmer W. Ag Transporte, Bes. Wohnungs, B\u00fcroumz\u00fcge",
    "wof:placetype":"venue"
},
  "geometry": {"coordinates":[7.3890810013,46.9329681396],"type":"Point"}
}