{
  "type": "Feature",
  "properties": {
    "iso:country":"CH",
    "sg:address":"Gr\u00fcnstrasse 8",
    "sg:city":"Wettingen",
    "sg:orig_category":"Kosmetikinstitute",
    "sg:phone":"+41 19327973",
    "sg:postcode":"5430",
    "sg:province":"Aargau",
    "wof:name":"Elisabeth R\u00f6mming Kosmetikinstitut",
    "wof:placetype":"venue"
},
  "geometry": {"coordinates":[8.7992038727,47.3220939636],"type":"Point"}
}