{
  "type": "Feature",
  "properties": {
    "iso:country":"CH",
    "sg:address":"Bahnhofstrasse 32 6300 Zug. Postfach",
    "sg:city":"Zug",
    "sg:orig_category":"Erbringung von Dienstleistungen f\u00fcr Unternehmen Standbau",
    "sg:phone":"+41 56 621 08 08",
    "sg:postcode":"6300",
    "sg:province":"Zug",
    "wof:name":"Wagner Messebau Ag Ausstellungs, Messegestaltung Usw",
    "wof:placetype":"venue"
},
  "geometry": {"coordinates":[8.2775678635,47.3426055908],"type":"Point"}
}