{
  "type": "Feature",
  "properties": {
    "iso:country":"CH",
    "sg:address":"Fliederweg 2 5035 Unterentfelden. Postfach",
    "sg:city":"Unterentfelden",
    "sg:orig_category":"Kinderg\u00e4rten, Vor U Grundschulen",
    "sg:postcode":"5035",
    "sg:province":"Aargau",
    "wof:name":"Chinderw\u00e4lt, Itani & Partner",
    "wof:placetype":"venue"
},
  "geometry": {"coordinates":[8.0451231003,47.3672637939],"type":"Point"}
}