{
  "type": "Feature",
  "properties": {
    "iso:country":"CH",
    "sg:address":"Totentanz 8",
    "sg:city":"Basel",
    "sg:orig_category":"Detailhandel mit Uhren U Schmuck",
    "sg:phone":"+41 61 261 53 20",
    "sg:postcode":"4051",
    "sg:province":"Basel-Stadt",
    "wof:name":"Beatrice Chiquet Goldschmiede",
    "wof:placetype":"venue"
},
  "geometry": {"coordinates":[7.5861058235,47.5618896484],"type":"Point"}
}