{
  "type": "Feature",
  "properties": {
    "iso:country":"CH",
    "sg:address":"Chemin Du Cercle 5",
    "sg:city":"Onex",
    "sg:orig_category":"Verlegen von Fliesen U Platten",
    "sg:phone":"+41 76 570 46 40",
    "sg:postcode":"1213",
    "sg:province":"Gen\u00e8ve",
    "wof:name":"Montalto Carrelages Sa",
    "wof:placetype":"venue"
},
  "geometry": {"coordinates":[6.8718571663,46.5775718689],"type":"Point"}
}