{
  "type": "Feature",
  "properties": {
    "addr:full":"Via San Gottardo 113 Gordola Ticino 6596",
    "addr:housenumber":"113",
    "addr:postcode":"6596",
    "addr:street":"Via San Gottardo",
    "iso:country":"CH",
    "sg:address":"Via San Gottardo 113",
    "sg:city":"Gordola",
    "sg:orig_category":"Autogaragen",
    "sg:phone":"+41 91 745 00 79",
    "sg:postcode":"6596",
    "sg:province":"Ticino",
    "wof:name":"Marco Pelucca Automobili Sagl Garage",
    "wof:placetype":"venue"
},
  "geometry": {"coordinates":[8.86696,46.180721],"type":"Point"}
}