{
  "type": "Feature",
  "properties": {
    "iso:country":"CH",
    "sg:address":"M\u00fchlegasse 15",
    "sg:city":"Wiedlisbach",
    "sg:orig_category":"Institutionen f\u00fcr Behinderte Wohnheime",
    "sg:phone":"+41 338943",
    "sg:postcode":"4537",
    "sg:province":"Bern",
    "wof:name":"Arbeitsheim Wangen Zh, Heim Und Werkst\u00e4tte F\u00fcr Behinderte",
    "wof:placetype":"venue"
},
  "geometry": {"coordinates":[8.6544208527,47.401550293],"type":"Point"}
}