{
  "type": "Feature",
  "properties": {
    "iso:country":"CH",
    "sg:address":"Eichholzweg 6",
    "sg:city":"Steinhausen",
    "sg:orig_category":"Detailhandel mit M\u00f6beln U Haushaltsgegenst\u00e4nden",
    "sg:postcode":"6312",
    "sg:province":"Zug",
    "wof:name":"Relexa Gmbh",
    "wof:placetype":"venue"
},
  "geometry": {"coordinates":[8.4909200668,47.1936683655],"type":"Point"}
}