{
  "type": "Feature",
  "properties": {
    "iso:country":"CH",
    "sg:address":"Thunstrasse 5",
    "sg:city":"Toffen",
    "sg:orig_category":"Reparatur von Schuhen U Lederwaren",
    "sg:phone":"+41 31 819 48 02",
    "sg:postcode":"3125",
    "sg:province":"Bern",
    "wof:name":"Daniel & Patricia Kneissler Schuhmacherei",
    "wof:placetype":"venue"
},
  "geometry": {"coordinates":[7.4912190437,46.8585968018],"type":"Point"}
}