{
  "type": "Feature",
  "properties": {
    "iso:country":"CH",
    "sg:address":"Alberich Zwyssigstrasse 83",
    "sg:city":"Wettingen",
    "sg:orig_category":"Sportvereine Sch\u00fctzen",
    "sg:postcode":"5430",
    "sg:province":"Aargau",
    "wof:name":"Sch\u00fctzengesellschaft",
    "wof:placetype":"venue"
},
  "geometry": {"coordinates":[8.3259410858,47.4653968811],"type":"Point"}
}