{
  "type": "Feature",
  "properties": {
    "iso:country":"CH",
    "sg:address":"Rhodaniastrasse 6",
    "sg:city":"Naters",
    "sg:orig_category":"Sportvereine",
    "sg:phone":"+41 27 923 39 29",
    "sg:postcode":"3904",
    "sg:province":"Valais",
    "wof:name":"Panathlon-club Oberwallis",
    "wof:placetype":"venue"
},
  "geometry": {"coordinates":[7.9916539192,46.322177887],"type":"Point"}
}