{
  "type": "Feature",
  "properties": {
    "addr:full":"Grand'rue 52 Thielle-wavre Neuch\u00e2tel 2075",
    "addr:housenumber":"52",
    "addr:postcode":"2075",
    "addr:street":"Grand'Rue;Neucha\u0302Tel",
    "iso:country":"CH",
    "sg:address":"Grand'rue 52",
    "sg:city":"Thielle-wavre",
    "sg:orig_category":"Baugewerbe",
    "sg:phone":"+41 32 753 48 71",
    "sg:postcode":"2075",
    "sg:province":"Neuch\u00e2tel",
    "wof:name":"Carlosa Sa D\u00e9coupe Au Jet D'eau",
    "wof:placetype":"venue"
},
  "geometry": {"coordinates":[7.02195,47.02005],"type":"Point"}
}