{
  "type": "Feature",
  "properties": {
    "iso:country":"CH",
    "sg:address":"Bernstrasse 9",
    "sg:city":"Grossh\u00f6chstetten",
    "sg:orig_category":"Herstellung von Metallkonstruktionen",
    "sg:phone":"+41 31 711 30 13",
    "sg:postcode":"3506",
    "sg:province":"Bern",
    "wof:name":"Bettler + Siegrist, Inh. Hr. Siegrist",
    "wof:placetype":"venue"
},
  "geometry": {"coordinates":[7.636897,46.907944],"type":"Point"}
}