{
  "type": "Feature",
  "properties": {
    "iso:country":"CH",
    "sg:address":"8240",
    "sg:city":"Thayngen",
    "sg:orig_category":"Primarschulen",
    "sg:phone":"+41 55 220 73 43",
    "sg:postcode":"8240",
    "sg:province":"Schaffhausen",
    "wof:name":"Primarschule Hanfl\u00e4nder & Primarschulkommission",
    "wof:placetype":"venue"
},
  "geometry": {"coordinates":[8.7995347977,47.2133331299],"type":"Point"}
}