{
  "type": "Feature",
  "properties": {
    "iso:country":"CH",
    "sg:address":"6216",
    "sg:city":"Mauensee",
    "sg:orig_category":"Erschliessung von Grundst\u00fccken",
    "sg:postcode":"6216",
    "sg:province":"Luzern",
    "wof:name":"Baugenossenschaft Meilen",
    "wof:placetype":"venue"
},
  "geometry": {"coordinates":[8.8249025345,47.2293624878],"type":"Point"}
}