{
  "type": "Feature",
  "properties": {
    "iso:country":"CH",
    "sg:address":"Seestrasse 16",
    "sg:city":"Thalwil",
    "sg:orig_category":"Rechtsberatung",
    "sg:phone":"+41 17235050",
    "sg:postcode":"8800",
    "sg:province":"Z\u00fcrich",
    "wof:name":"Stemmle Publishers Gmbh",
    "wof:placetype":"venue"
},
  "geometry": {"coordinates":[8.5775728226,47.2833938599],"type":"Point"}
}