{
  "type": "Feature",
  "properties": {
    "iso:country":"CH",
    "sg:address":"Cour Avenue De 46",
    "sg:city":"Lausanne",
    "sg:orig_category":"Grosshandel mit Nahrungsmitteln, Getr\u00e4nken U Tabakwaren ohne ausgepr\u00e4gten Schwerpunkt",
    "sg:postcode":"1007",
    "sg:province":"Vaud",
    "wof:name":"Maison Russie, Didenko Ioulia",
    "wof:placetype":"venue"
},
  "geometry": {"coordinates":[6.7493038177,47.0567016602],"type":"Point"}
}