{
  "type": "Feature",
  "properties": {
    "iso:country":"CH",
    "sg:address":"Furlenstrasse 78",
    "sg:city":"Lausen",
    "sg:orig_category":"Grosshandel mit sonstigen Gebrauchs U Verbrauchsg\u00fctern Mineralien and Steine Detailhandel",
    "sg:phone":"+41 61 921 40 95",
    "sg:postcode":"4415",
    "sg:province":"Basel-Landschaft",
    "wof:name":"Sutter & W\u00fcthrich Edelsteinst\u00fcbli",
    "wof:placetype":"venue"
},
  "geometry": {"coordinates":[7.7584199905,47.464756012],"type":"Point"}
}