{
  "type": "Feature",
  "properties": {
    "iso:country":"CH",
    "sg:address":"La Corbaz 3 1628 Vuadens. Postfach",
    "sg:city":"Vuadens",
    "sg:orig_category":"Sonstiger spezialisierter Hoch U Tiefbau",
    "sg:postcode":"1628",
    "sg:province":"Fribourg",
    "wof:name":"Ziberi Armierungen Gmbh",
    "wof:placetype":"venue"
},
  "geometry": {"coordinates":[9.3632040024,47.4193382263],"type":"Point"}
}