{
  "type": "Feature",
  "properties": {
    "iso:country":"CH",
    "sg:address":"Sch\u00f6ngrundstrasse 1",
    "sg:city":"Horw",
    "sg:orig_category":"Unclassifiable Establishments",
    "sg:postcode":"6048",
    "sg:province":"Luzern",
    "wof:name":"Oriental Smoke S. Henry & I. Scheidegger",
    "wof:placetype":"venue"
},
  "geometry": {"coordinates":[8.3108663559,47.0149307251],"type":"Point"}
}