{
  "type": "Feature",
  "properties": {
    "iso:country":"CH",
    "sg:address":"Schlossstrasse 24 2560 Nidau. Postfach",
    "sg:city":"Nidau",
    "sg:orig_category":"Architektur U Ingenieurb\u00fcros",
    "sg:postcode":"2560",
    "sg:province":"Bern",
    "wof:name":"Reno Bau Nidau Gmbh Dienstleistungen Im Bausektor, Renovationen Usw.",
    "wof:placetype":"venue"
},
  "geometry": {"coordinates":[7.23528,47.127419],"type":"Point"}
}