{
  "type": "Feature",
  "properties": {
    "iso:country":"CH",
    "sg:address":"Cordulaplatz 6",
    "sg:city":"Baden",
    "sg:orig_category":"Arztpraxen",
    "sg:phone":"+41 56 221 12 56",
    "sg:postcode":"5400",
    "sg:province":"Aargau",
    "wof:name":"Dr.med.christian Roy Spezialarzt Fmh",
    "wof:placetype":"venue"
},
  "geometry": {"coordinates":[8.306754,47.472118],"type":"Point"}
}