{
  "type": "Feature",
  "properties": {
    "iso:country":"CH",
    "sg:address":"Goldauerstrasse 47",
    "sg:city":"Z\u00fcrich",
    "sg:orig_category":"Technische, physikalische U chemische Untersuchung",
    "sg:phone":"+41 18057676",
    "sg:postcode":"8006",
    "sg:province":"Z\u00fcrich",
    "wof:name":"Mds Pharma Services Switzerland Ag Biologische Laboratorien Usw",
    "wof:placetype":"venue"
},
  "geometry": {"coordinates":[8.643406868,47.412273407],"type":"Point"}
}