{
  "type": "Feature",
  "properties": {
    "iso:country":"CH",
    "sg:address":"Place De La Gare 1510 Moudon Case Postale 102",
    "sg:city":"Moudon",
    "sg:orig_category":"Giessereiindustrie Herstellung von Metallerzeugnissen ohne Maschinenbau",
    "sg:phone":"+41 21 905 80 00",
    "sg:postcode":"1510",
    "sg:province":"Vaud",
    "wof:name":"Fonderies De Moudon Sa",
    "wof:placetype":"venue"
},
  "geometry": {"coordinates":[6.8043351173,46.6698455811],"type":"Point"}
}