{
  "type": "Feature",
  "properties": {
    "iso:country":"CH",
    "sg:address":"Mesolcina Piazza 2",
    "sg:city":"Bellinzona",
    "sg:orig_category":"Unclassifiable Establishments",
    "sg:phone":"+41 91 825 05 10",
    "sg:postcode":"6500",
    "sg:province":"Ticino",
    "wof:name":"Assolo Networks Sa",
    "wof:placetype":"venue"
},
  "geometry": {"coordinates":[9.0258769989,46.1979103088],"type":"Point"}
}