{
  "type": "Feature",
  "properties": {
    "iso:country":"CH",
    "sg:address":"Br\u00fcglingerstrasse 21",
    "sg:city":"Basel",
    "sg:orig_category":"Sportschulen",
    "sg:phone":"+41 61 312 39 10",
    "sg:postcode":"4052",
    "sg:province":"Basel-Stadt",
    "wof:name":"Centrum St.jakob Fritz Seidler Sportschule St.jakob",
    "wof:placetype":"venue"
},
  "geometry": {"coordinates":[7.6178121567,47.5404548645],"type":"Point"}
}