{
  "type": "Feature",
  "properties": {
    "iso:country":"CH",
    "sg:address":"Picassoplatz 8",
    "sg:city":"Basel",
    "sg:orig_category":"Geb\u00e4ude, Wohnungsreinigung Reinigungsgewerbe",
    "sg:phone":"+41 21 635 74 42",
    "sg:postcode":"4052",
    "sg:province":"Basel-Stadt",
    "wof:name":"Flor\u00e9al Nettoyage S\u00e0rl",
    "wof:placetype":"venue"
},
  "geometry": {"coordinates":[6.5885848999,46.5352058411],"type":"Point"}
}