{
  "type": "Feature",
  "properties": {
    "iso:country":"CH",
    "sg:address":"Sch\u00f6ntalweg 1",
    "sg:city":"Ermatingen",
    "sg:orig_category":"Detailhandel mit Sportartikeln",
    "sg:phone":"+41 71 664 10 83",
    "sg:postcode":"8272",
    "sg:province":"Thurgau",
    "wof:name":"Francisco Belda Kelme Sport",
    "wof:placetype":"venue"
},
  "geometry": {"coordinates":[9.084944725,47.6714706421],"type":"Point"}
}