{
  "type": "Feature",
  "properties": {
    "iso:country":"CH",
    "sg:address":"Zentralplatz 6",
    "sg:city":"Mellingen",
    "sg:orig_category":"Unclassifiable Establishments",
    "sg:postcode":"5507",
    "sg:province":"Aargau",
    "wof:name":"Restaurant Al Ponte, Dias Antunes & Co.",
    "wof:placetype":"venue"
},
  "geometry": {"coordinates":[8.2746601105,47.4195556641],"type":"Point"}
}