{
  "type": "Feature",
  "properties": {
    "iso:country":"CH",
    "sg:address":"Stationsstrasse 5 Postfach",
    "sg:city":"H\u00fcnibach",
    "sg:classifiers":[
        {
            "category":"Manufacturing",
            "subcategory":"Printing",
            "type":"Manufacturing & Wholesale Goods"
        }
    ],
    "sg:phone":"+41 33 244 80 80",
    "sg:postcode":"3626",
    "sg:province":"Bern",
    "sg:tags":[
        "publishing"
    ],
    "wof:name":"Jost-druck Ag",
    "wof:placetype":"venue"
},
  "geometry": {"coordinates":[-6.1754698753,53.38098526],"type":"Point"}
}