{
  "type": "Feature",
  "properties": {
    "iso:country":"CH",
    "sg:address":"Werkhofstrasse 2a",
    "sg:city":"Biberist",
    "sg:orig_category":"Reiseb\u00fcros",
    "sg:phone":"+41 32 672 16 17",
    "sg:postcode":"4562",
    "sg:province":"Solothurn",
    "wof:name":"Neyzat Dagci Reiseb\u00fcro",
    "wof:placetype":"venue"
},
  "geometry": {"coordinates":[7.5557599068,47.1801605225],"type":"Point"}
}