{
  "type": "Feature",
  "properties": {
    "iso:country":"CH",
    "sg:address":"Im Chol\u00e4cher 4",
    "sg:city":"Wettswil",
    "sg:orig_category":"Allgemeiner Hoch U Tiefbau",
    "sg:phone":"+41 17848766",
    "sg:postcode":"8907",
    "sg:province":"Z\u00fcrich",
    "wof:name":"Bau-tech 2000 Ag, Wollerau",
    "wof:placetype":"venue"
},
  "geometry": {"coordinates":[8.734148,47.197395],"type":"Point"}
}