{
  "type": "Feature",
  "properties": {
    "iso:country":"CH",
    "sg:address":"Bahnhofmatten 2",
    "sg:city":"Hunzenschwil",
    "sg:orig_category":"Autogaragen Autospenglereien",
    "sg:phone":"+41 61 751 19 22",
    "sg:postcode":"5502",
    "sg:province":"Aargau",
    "wof:name":"Gebr\u00fcder Brunner Ag Garage & Carrosserie",
    "wof:placetype":"venue"
},
  "geometry": {"coordinates":[7.591449,47.477261],"type":"Point"}
}