{
  "type": "Feature",
  "properties": {
    "iso:country":"CH",
    "sg:address":"8500",
    "sg:city":"Frauenfeld",
    "sg:orig_category":"Wirtschafts- and Arbeitgeberverb\u00e4nde",
    "sg:postcode":"8500",
    "sg:province":"Thurgau",
    "wof:name":"Milchh\u00e4ndlergemeinschaft Thun & Umgebung",
    "wof:placetype":"venue"
},
  "geometry": {"coordinates":[7.6263408661,46.7264938354],"type":"Point"}
}