{
  "type": "Feature",
  "properties": {
    "iso:country":"CH",
    "sg:address":"Gen\u00e8ve Rue De 122",
    "sg:city":"Th\u00f4nex",
    "sg:orig_category":"Grosshandel mit elektrischen Haushaltsger\u00e4ten, Radio U Fernsehger\u00e4ten",
    "sg:phone":"+41 21 636 30 30",
    "sg:postcode":"1226",
    "sg:province":"Gen\u00e8ve",
    "wof:name":"Electro-mat\u00e9riel Sa",
    "wof:placetype":"venue"
},
  "geometry": {"coordinates":[6.5935330391,46.5269966125],"type":"Point"}
}