{
  "type": "Feature",
  "properties": {
    "iso:country":"CH",
    "sg:address":"Es Cr\u00eas 3",
    "sg:city":"Courrendlin",
    "sg:orig_category":"Handels-H\u00e4user U Gesellschaften",
    "sg:phone":"+41 32 422 02 93",
    "sg:postcode":"2830",
    "sg:province":"Jura",
    "wof:name":"Gunti Kurt H.",
    "wof:placetype":"venue"
},
  "geometry": {"coordinates":[7.3756608963,47.3401641846],"type":"Point"}
}