{
  "type": "Feature",
  "properties": {
    "iso:country":"CH",
    "sg:address":"Forte Via Al 8 6900 Lugano. Postfach",
    "sg:city":"Lugano",
    "sg:orig_category":"Technische, physikalische U chemische Untersuchung",
    "sg:postcode":"6900",
    "sg:province":"Ticino",
    "wof:name":"Projects For The Nature Llc, Cheyenne, Lugano Branch Sett. Del Recupero Del Sistema Ambientale E D. Protezione D. Natura; Consulenza, Realizzazione Di Progetti Ecc",
    "wof:placetype":"venue"
},
  "geometry": {"coordinates":[8.9513053894,46.0029754639],"type":"Point"}
}