{
  "type": "Feature",
  "properties": {
    "iso:country":"CH",
    "sg:address":"Landoltstrasse 62",
    "sg:city":"Bern",
    "sg:orig_category":"Sanit\u00e4r U Heizungsinstallation",
    "sg:phone":"+41 31 371 05 85",
    "sg:postcode":"3007",
    "sg:province":"Bern",
    "wof:name":"Hans L\u00f6rtscher Warmluftheizungen",
    "wof:placetype":"venue"
},
  "geometry": {"coordinates":[7.4409718513,46.9345016479],"type":"Point"}
}