{
  "type": "Feature",
  "properties": {
    "iso:country":"CH",
    "sg:address":"Spalenberg 23",
    "sg:city":"Basel",
    "sg:orig_category":"Detailhandel mit Bekleidung",
    "sg:postcode":"4051",
    "sg:province":"Basel-Stadt",
    "wof:name":"Mode Kunst Wohnen Fabulart, Kreutzer",
    "wof:placetype":"venue"
},
  "geometry": {"coordinates":[7.586063,47.556942],"type":"Point"}
}