{
  "type": "Feature",
  "properties": {
    "iso:country":"CH",
    "sg:address":"R\u00f6merstrasse 12",
    "sg:city":"Bellach",
    "sg:orig_category":"Herstellung von Teilen U Zubeh\u00f6r f\u00fcr Automobile",
    "sg:phone":"+41 32 618 19 73",
    "sg:postcode":"4512",
    "sg:province":"Solothurn",
    "wof:name":"Novitec Bordin Antonello",
    "wof:placetype":"venue"
},
  "geometry": {"coordinates":[7.5112061501,47.2128257751],"type":"Point"}
}