{
  "type": "Feature",
  "properties": {
    "iso:country":"CH",
    "sg:address":"Schulhausstrasse 9",
    "sg:city":"Dotzigen",
    "sg:orig_category":"Herstellung von Reiseartikeln, Leder U Sattlerwaren Innendekorationsateliers",
    "sg:phone":"+41 32 351 17 25",
    "sg:postcode":"3293",
    "sg:province":"Bern",
    "wof:name":"Walter Niggeler Sattler-tapezierer",
    "wof:placetype":"venue"
},
  "geometry": {"coordinates":[7.3375401497,47.1203422546],"type":"Point"}
}