{
  "type": "Feature",
  "properties": {
    "iso:country":"CH",
    "sg:address":"Bahnhofstrasse 8 8752 N\u00e4fels. Postfach",
    "sg:city":"N\u00e4fels",
    "sg:orig_category":"Fachdetailhandel in Verkaufsr\u00e4umen",
    "sg:phone":"+41 55 612 10 35",
    "sg:postcode":"8752",
    "sg:province":"Glarus",
    "wof:name":"Gallati-schnyder Kurt, Optik",
    "wof:placetype":"venue"
},
  "geometry": {"coordinates":[9.0650463104,47.0993347168],"type":"Point"}
}