{
  "type": "Feature",
  "properties": {
    "iso:country":"CH",
    "sg:address":"Hofstrasse 9",
    "sg:city":"B\u00fctschwil",
    "sg:orig_category":"Detailhandel mit Milcherzeugnissen U Eiern Verarbeitung von Milch",
    "sg:phone":"+41 71 983 17 64",
    "sg:postcode":"9606",
    "sg:province":"St. Gallen",
    "wof:name":"Albert Studer K\u00e4serei",
    "wof:placetype":"venue"
},
  "geometry": {"coordinates":[9.0724601746,47.3622779846],"type":"Point"}
}