{
  "type": "Feature",
  "properties": {
    "iso:country":"CH",
    "sg:address":"Bahnhofstrasse 2",
    "sg:city":"Aadorf",
    "sg:orig_category":"Arztpraxen",
    "sg:phone":"+41 52 365 41 41",
    "sg:postcode":"8355",
    "sg:province":"Thurgau",
    "wof:name":"Dr.med.heinz Engelhard Arzt F\u00fcr Allgemeine Medizin",
    "wof:placetype":"venue"
},
  "geometry": {"coordinates":[8.900802,47.489437],"type":"Point"}
}