{
  "type": "Feature",
  "properties": {
    "iso:country":"CH",
    "sg:address":"Stationsstrasse 107 6023 Rothenburg. Postfach 74",
    "sg:city":"Rothenburg",
    "sg:orig_category":"Grosshandel mit Erzen U Metallen",
    "sg:phone":"+41 41 280 91 81",
    "sg:postcode":"6023",
    "sg:province":"Luzern",
    "wof:name":"Stocker Stahl Ag Luzern",
    "wof:placetype":"venue"
},
  "geometry": {"coordinates":[8.2527742386,47.0912399292],"type":"Point"}
}