{
  "type": "Feature",
  "properties": {
    "iso:country":"CH",
    "sg:address":"Dornacker 27",
    "sg:city":"Konolfingen",
    "sg:orig_category":"Detailhandel Reparatur von Gebrauchsg\u00fctern",
    "sg:phone":"+41 79 651 78 52",
    "sg:postcode":"3510",
    "sg:province":"Bern",
    "wof:name":"Schmid Trocknungs Ag",
    "wof:placetype":"venue"
},
  "geometry": {"coordinates":[7.5972499847,46.8784942627],"type":"Point"}
}