{
  "type": "Feature",
  "properties": {
    "iso:country":"CH",
    "sg:address":"Freie Strasse 8",
    "sg:city":"Basel",
    "sg:orig_category":"Fussreflexzonenmassage",
    "sg:phone":"+41 61 262 20 66",
    "sg:postcode":"4001",
    "sg:province":"Basel-Stadt",
    "wof:name":"Aurum Astrum Fussreflexzonentherapie",
    "wof:placetype":"venue"
},
  "geometry": {"coordinates":[7.5886459351,47.5572624207],"type":"Point"}
}