{
  "type": "Feature",
  "properties": {
    "iso:country":"CH",
    "sg:address":"Dorfhalde 3",
    "sg:city":"St\u00e4fa",
    "sg:orig_category":"Ingenieurb\u00fcros Maschinenbau",
    "sg:phone":"+41 19264488",
    "sg:postcode":"8712",
    "sg:province":"Z\u00fcrich",
    "wof:name":"Hermann M\u00fcller Ag Ingenieurb\u00fcro",
    "wof:placetype":"venue"
},
  "geometry": {"coordinates":[8.7364225388,47.2414093018],"type":"Point"}
}