{
  "type": "Feature",
  "properties": {
    "iso:country":"CH",
    "sg:address":"Pogyre La",
    "sg:city":"Gr\u00f4ne",
    "sg:orig_category":"Detailhandel mit elektrischen Haushalts-,Radio U Fernsehger\u00e4ten sowie Musikinstrumenten",
    "sg:phone":"+41 27 458 50 30",
    "sg:postcode":"3979",
    "sg:province":"Valais",
    "wof:name":"Xavier H\u00e9ritier, Professionnel Syst\u00e8me Audio",
    "wof:placetype":"venue"
},
  "geometry": {"coordinates":[7.4565238953,46.2523498535],"type":"Point"}
}