{
  "type": "Feature",
  "properties": {
    "iso:country":"CH",
    "sg:address":"Sur-le-cr\u00eat",
    "sg:city":"Peney-le-jorat",
    "sg:orig_category":"Einbau von Schreinerwaren Herstellung von sonstigen Maschinen f\u00fcr unspezifische Verwendung",
    "sg:phone":"+41 18506644",
    "sg:postcode":"1059",
    "sg:province":"Vaud",
    "wof:name":"Rametall Ramseier + Ammann",
    "wof:placetype":"venue"
},
  "geometry": {"coordinates":[8.5024929047,47.4818725586],"type":"Point"}
}