{
  "type": "Feature",
  "properties": {
    "iso:country":"CH",
    "sg:address":"St. Leonhard-strasse 35",
    "sg:city":"St.gallen",
    "sg:orig_category":"Fachdetailhandel in Verkaufsr\u00e4umen",
    "sg:phone":"+41 71 223 23 63",
    "sg:postcode":"9000",
    "sg:province":"St. Gallen",
    "wof:name":"Flippy-shop Haefeli Peter H.",
    "wof:placetype":"venue"
},
  "geometry": {"coordinates":[-76.8703613281,43.1071128845],"type":"Point"}
}