{
  "type": "Feature",
  "properties": {
    "iso:country":"CH",
    "sg:address":"Central 1",
    "sg:city":"Z\u00fcrich",
    "sg:classifiers":[
        {
            "category":"Banks & Credit Unions",
            "subcategory":"Bank",
            "type":"Services"
        }
    ],
    "sg:phone":"+41 12514070",
    "sg:postcode":"8035",
    "sg:province":"Z\u00fcrich",
    "wof:name":"Union Bank Of Switzerland",
    "wof:placetype":"venue"
},
  "geometry": {"coordinates":[8.543647,47.377045],"type":"Point"}
}