{
  "type": "Feature",
  "properties": {
    "iso:country":"CH",
    "sg:address":"Spissenstrasse 76",
    "sg:city":"Meggen",
    "sg:orig_category":"Grosshandel mit Kaffee, Tee, Kakao U Gew\u00fcrzen Verarbeitung von Tee U Kaffee",
    "sg:phone":"+41 41 379 61 21",
    "sg:postcode":"6045",
    "sg:province":"Luzern",
    "wof:name":"Zwald Walter Coffee Buying & Consulting",
    "wof:placetype":"venue"
},
  "geometry": {"coordinates":[8.3811893463,47.0558891296],"type":"Point"}
}