{
  "type": "Feature",
  "properties": {
    "iso:country":"CH",
    "sg:address":"Eggh\u00f6lzlistrasse 1",
    "sg:city":"Bern",
    "sg:classifiers":[
        {
            "category":"Autos & Motor Vehicles",
            "subcategory":"Automobile Sales",
            "type":"Retail Goods"
        }
    ],
    "sg:phone":"+41 31 350 88 88",
    "sg:postcode":"3006",
    "sg:province":"Bern",
    "sg:tags":[
        "used",
        "vehicles"
    ],
    "wof:name":"Eggh\u00f6lzli-garage Ag",
    "wof:placetype":"venue"
},
  "geometry": {"coordinates":[7.475151062,46.9367713928],"type":"Point"}
}