{
  "type": "Feature",
  "properties": {
    "iso:country":"CH",
    "sg:address":"Mittlere Strasse 153 A",
    "sg:city":"Basel",
    "sg:orig_category":"Vorschulen, Kinderg\u00e4rten",
    "sg:phone":"+41 61 321 58 17",
    "sg:postcode":"4056",
    "sg:province":"Basel-Stadt",
    "wof:name":"Kindergarten",
    "wof:placetype":"venue"
},
  "geometry": {"coordinates":[7.5744781494,47.5647010803],"type":"Point"}
}