{
  "type": "Feature",
  "properties": {
    "iso:country":"CH",
    "sg:address":"Ochsenweg 1",
    "sg:city":"Erlinsbach",
    "sg:orig_category":"Detailhandel mit B\u00fcchern, Zeitungen, Schreib U Papeteriewaren Detailhandel mit Getr\u00e4nken",
    "sg:phone":"+41 81 756 43 28",
    "sg:postcode":"5018",
    "sg:province":"Solothurn",
    "wof:name":"Schwarzpeter Buchladen Philipp Heeb",
    "wof:placetype":"venue"
},
  "geometry": {"coordinates":[9.472551,47.16539],"type":"Point"}
}