{
  "type": "Feature",
  "properties": {
    "iso:country":"CH",
    "sg:address":"Chemin De La Renfile 7",
    "sg:city":"Vernier",
    "sg:orig_category":"Herstellung von Tanks U Sammelbeh\u00e4ltern aus Metall",
    "sg:phone":"+41 22 341 21 69",
    "sg:postcode":"1214",
    "sg:province":"Gen\u00e8ve",
    "wof:name":"Bossart & Fils Revision De Citernes",
    "wof:placetype":"venue"
},
  "geometry": {"coordinates":[6.0954151154,46.2194900513],"type":"Point"}
}