{
  "type": "Feature",
  "properties": {
    "iso:country":"CH",
    "sg:address":"Zentrum 2 5443 Niederrohrdorf. Postfach",
    "sg:city":"Niederrohrdorf",
    "sg:orig_category":"Sanit\u00e4r, Heizungs U L\u00fcftungsinstallation Sanit\u00e4rinstallation",
    "sg:phone":"+41 56 496 34 70",
    "sg:postcode":"5443",
    "sg:province":"Aargau",
    "wof:name":"Alfi Haustech Ag",
    "wof:placetype":"venue"
},
  "geometry": {"coordinates":[8.3051395416,47.4239196777],"type":"Point"}
}