{
  "type": "Feature",
  "properties": {
    "iso:country":"CH",
    "sg:address":"Oberrohrdorferstrasse 63",
    "sg:city":"Fislisbach",
    "sg:orig_category":"Reinigungsgewerbe",
    "sg:postcode":"5442",
    "sg:province":"Aargau",
    "wof:name":"Art Geb\u00e4udeunterhalt Gmbh",
    "wof:placetype":"venue"
},
  "geometry": {"coordinates":[8.2993907928,47.4361953735],"type":"Point"}
}