{
  "type": "Feature",
  "properties": {
    "iso:country":"CH",
    "sg:address":"Pargherastrasse 39",
    "sg:city":"Chur",
    "sg:orig_category":"Manicure Solarien",
    "sg:phone":"+41 81 252 16 76",
    "sg:postcode":"7000",
    "sg:province":"Graubunden",
    "wof:name":"Irene Meier Kosmetikstudio & Solarium",
    "wof:placetype":"venue"
},
  "geometry": {"coordinates":[9.5135536194,46.8453674316],"type":"Point"}
}