{
  "type": "Feature",
  "properties": {
    "iso:country":"CH",
    "sg:address":"3962",
    "sg:city":"Montana-vermala",
    "sg:classifiers":[
        {
            "category":"Travel",
            "subcategory":"Hotels & Motels",
            "type":"Entertainment"
        }
    ],
    "sg:phone":"+41 27 481 13 33",
    "sg:postcode":"3962",
    "sg:tags":[
        "hotels",
        "mit",
        "restaurant"
    ],
    "wof:name":"H\u00f4tel Eldorado",
    "wof:placetype":"venue"
},
  "geometry": {"coordinates":[7.4924340248,46.3144187927],"type":"Point"}
}