{
  "type": "Feature",
  "properties": {
    "addr:full":"M\u00fcnsterplatz 8 Schaffhausen Schaffhausen 8200",
    "addr:housenumber":"8",
    "addr:postcode":"8200",
    "addr:street":"Muensterplatz",
    "iso:country":"CH",
    "sg:address":"M\u00fcnsterplatz 8",
    "sg:city":"Schaffhausen",
    "sg:orig_category":"Detailhandel mit Damenbekleidung",
    "sg:phone":"+41 71 278 24 44",
    "sg:postcode":"8200",
    "sg:province":"Schaffhausen",
    "wof:name":"Boutique Silvana",
    "wof:placetype":"venue"
},
  "geometry": {"coordinates":[9.362769,47.411659],"type":"Point"}
}