{
  "type": "Feature",
  "properties": {
    "iso:country":"CH",
    "sg:address":"Bleikenstrasse 37",
    "sg:city":"Wattwil",
    "sg:orig_category":"Sonstiger spezialisierter Hoch U Tiefbau",
    "sg:postcode":"9630",
    "sg:province":"St. Gallen",
    "wof:name":"R\u00fcegg Alfred",
    "wof:placetype":"venue"
},
  "geometry": {"coordinates":[9.0894069672,47.2929344177],"type":"Point"}
}