{
  "type": "Feature",
  "properties": {
    "addr:full":"Shopping-center 7/7052 Spreitenbach Aargau 8957",
    "addr:housenumber":"7 / 7052",
    "addr:postcode":"8957",
    "addr:street":"Shopping-Center",
    "iso:country":"CH",
    "sg:address":"Shopping-center 7/7052",
    "sg:city":"Spreitenbach",
    "sg:orig_category":"Berufsbildende weiterf\u00fchrende Schulen Gesundheitswesen",
    "sg:phone":"+41 56 401 67 19",
    "sg:postcode":"8957",
    "sg:province":"Aargau",
    "wof:name":"Cellsan Ag",
    "wof:placetype":"venue"
},
  "geometry": {"coordinates":[8.369195,47.421894],"type":"Point"}
}