{
  "type": "Feature",
  "properties": {
    "iso:country":"CH",
    "sg:address":"Neugasse 25",
    "sg:city":"Zug",
    "sg:orig_category":"Handelsvermittlung von Brennstoffen, Erzen, Metallen U Chemikalien",
    "sg:phone":"+41 76 379 04 86",
    "sg:postcode":"6300",
    "sg:province":"Zug",
    "wof:name":"Alphin, Fleury & Partner",
    "wof:placetype":"venue"
},
  "geometry": {"coordinates":[8.515630722,47.1664276123],"type":"Point"}
}