{
  "type": "Feature",
  "properties": {
    "iso:country":"CH",
    "sg:address":"Rue De La Colombi\u00e8re 3",
    "sg:city":"Nyon",
    "sg:classifiers":[
        {
            "category":"Professional",
            "subcategory":"Employment Agencies",
            "type":"Services"
        }
    ],
    "sg:phone":"+41 22 362 16 60",
    "sg:postcode":"1260",
    "sg:province":"Vaud",
    "sg:tags":[
        "personal",
        "u",
        "stellenvermittlung"
    ],
    "wof:name":"Tonus Management Sa, Succursale De Nyon",
    "wof:placetype":"venue"
},
  "geometry": {"coordinates":[6.2419390678,46.3824424744],"type":"Point"}
}