{
  "type": "Feature",
  "properties": {
    "iso:country":"CH",
    "sg:address":"Rue D'or 96",
    "sg:city":"Fribourg",
    "sg:orig_category":"RESTAURANTS: TEA-ROOMS",
    "sg:phone":"+41 81 302 12 28",
    "sg:postcode":"1700",
    "sg:province":"Fribourg",
    "wof:name":"Egger Jules",
    "wof:placetype":"venue"
},
  "geometry": {"coordinates":[9.5005464554,47.0010719299],"type":"Point"}
}