{
  "type": "Feature",
  "properties": {
    "iso:country":"CH",
    "sg:address":"Poststrasse 12 6300 Zug. Postfach",
    "sg:city":"Zug",
    "sg:orig_category":"Vermietung U Verpachtung von eigenen Immobilien",
    "sg:postcode":"6300",
    "sg:province":"Zug",
    "wof:name":"Immvest Ag Immobilien Usw",
    "wof:placetype":"venue"
},
  "geometry": {"coordinates":[8.3411808014,47.3511123657],"type":"Point"}
}