{
  "type": "Feature",
  "properties": {
    "iso:country":"CH",
    "sg:address":"H\u00f4pital Rue De L' 32",
    "sg:city":"Yverdon-les-bains",
    "sg:orig_category":"Reiseb\u00fcros U Reiseveranstalter",
    "sg:postcode":"1400",
    "sg:province":"Vaud",
    "wof:name":"Creatour, Ryffel Tourism Consulting",
    "wof:placetype":"venue"
},
  "geometry": {"coordinates":[6.6414198875,46.778629303],"type":"Point"}
}