{
  "type": "Feature",
  "properties": {
    "iso:country":"CH",
    "sg:address":"Kasernenstrasse 1",
    "sg:city":"B\u00fclach",
    "sg:orig_category":"Non-Classified Establishments",
    "sg:postcode":"8180",
    "sg:province":"Z\u00fcrich",
    "wof:name":"Physiotherapie Neuhof Gmbh B\u00fclach",
    "wof:placetype":"venue"
},
  "geometry": {"coordinates":[8.5400724411,47.5188713074],"type":"Point"}
}