{
  "type": "Feature",
  "properties": {
    "iso:country":"CH",
    "sg:address":"Dorfstrasse 63",
    "sg:city":"Osterfingen",
    "sg:orig_category":"Landesverteidigung, Sozialversicherung \u00d6ffentliche Verwaltung",
    "sg:phone":"+41 31 930 14 14",
    "sg:postcode":"8218",
    "sg:province":"Schaffhausen",
    "wof:name":"Zivilschutzstelle Ostermundigen",
    "wof:placetype":"venue"
},
  "geometry": {"coordinates":[7.4956817627,46.957447052],"type":"Point"}
}