{
  "type": "Feature",
  "properties": {
    "iso:country":"CH",
    "sg:address":"Dickenstrasse 32",
    "sg:city":"Ebnat-kappel",
    "sg:orig_category":"Sonstiges Versicherungsgewerbe",
    "sg:phone":"+41 79 336 30 84",
    "sg:postcode":"9642",
    "sg:province":"St. Gallen",
    "wof:name":"Nvb Neutrales Versicherungs- B\u00fcro Hans-rudolf Helfenstein",
    "wof:placetype":"venue"
},
  "geometry": {"coordinates":[9.1249732971,47.2567520142],"type":"Point"}
}