{
  "type": "Feature",
  "properties": {
    "iso:country":"CH",
    "sg:address":"4313",
    "sg:city":"M\u00f6hlin",
    "sg:orig_category":"Vorschulen, Kinderg\u00e4rten",
    "sg:phone":"+41 61 851 44 31",
    "sg:postcode":"4313",
    "sg:province":"Aargau",
    "wof:name":"Kindergarten Aengerli",
    "wof:placetype":"venue"
},
  "geometry": {"coordinates":[7.8434958458,47.5606918335],"type":"Point"}
}