{
  "type": "Feature",
  "properties": {
    "iso:country":"CH",
    "sg:address":"M\u00fchleschlucht",
    "sg:city":"Gadmen",
    "sg:orig_category":"Detailhandel mit elektrischen Haushalts, Radio U Fernsehger\u00e4ten ohne ausgepr\u00e4gten Schwerpunkt",
    "sg:phone":"+41 33 975 12 24",
    "sg:postcode":"3863",
    "sg:province":"Bern",
    "wof:name":"Andreas Huber Elektrogesch\u00e4ft",
    "wof:placetype":"venue"
},
  "geometry": {"coordinates":[8.3517541885,46.7367591858],"type":"Point"}
}