{
  "type": "Feature",
  "properties": {
    "iso:country":"CH",
    "sg:address":"Bernex Rue De 341",
    "sg:city":"Bernex",
    "sg:orig_category":"Grosshandel mit Nahrungsmitteln, Getr\u00e4nken U Tabakwaren ohne ausgepr\u00e4gten Schwerpunkt",
    "sg:postcode":"1233",
    "sg:province":"Gen\u00e8ve",
    "wof:name":"Santos Do Coito Borda De Agua Sandra",
    "wof:placetype":"venue"
},
  "geometry": {"coordinates":[6.0684499741,46.1737632751],"type":"Point"}
}