{
  "type": "Feature",
  "properties": {
    "iso:country":"CH",
    "sg:address":"Rue Des Creusets 16",
    "sg:city":"Sion",
    "sg:classifiers":[
        {
            "category":"Insurance",
            "subcategory":"Insurance Agent",
            "type":"Services"
        }
    ],
    "sg:phone":"+41 27 327 30 00",
    "sg:postcode":"1950",
    "sg:province":"Valais",
    "sg:tags":[
        "versicherungsagenturen",
        "-broker"
    ],
    "wof:name":"L & C Consulting S\u00e0rl",
    "wof:placetype":"venue"
},
  "geometry": {"coordinates":[7.3593239784,46.2296905518],"type":"Point"}
}