{
  "type": "Feature",
  "properties": {
    "iso:country":"CH",
    "sg:address":"Stationsstrasse 41",
    "sg:city":"Hettlingen",
    "sg:orig_category":"Sonstige mit der Informatik verbundene T\u00e4tigkeiten",
    "sg:postcode":"8442",
    "sg:province":"Z\u00fcrich",
    "wof:name":"Integrale Informatik Sicherheit, W. Huber",
    "wof:placetype":"venue"
},
  "geometry": {"coordinates":[8.7021808624,47.5449638367],"type":"Point"}
}