{
  "type": "Feature",
  "properties": {
    "iso:country":"CH",
    "sg:address":"Rue Sismondi 6",
    "sg:city":"Gen\u00e8ve",
    "sg:orig_category":"Fachdetailhandel in Verkaufsr\u00e4umen Kunsthandel",
    "sg:phone":"+41 22 732 93 25",
    "sg:postcode":"1201",
    "sg:province":"Gen\u00e8ve",
    "wof:name":"Artaser Sa",
    "wof:placetype":"venue"
},
  "geometry": {"coordinates":[6.1477079391,46.2100601196],"type":"Point"}
}