{
  "type": "Feature",
  "properties": {
    "iso:country":"CH",
    "sg:address":"Route Henri-pestalozzi 1",
    "sg:city":"Fribourg",
    "sg:classifiers":[
        {
            "category":"Shopping",
            "subcategory":"Hobbies, Toys, & Games",
            "type":"Retail Goods"
        }
    ],
    "sg:phone":"+41 26 488 38 39",
    "sg:postcode":"1700",
    "sg:province":"Fribourg",
    "sg:tags":[
        "hobby",
        "handicraft",
        "supply"
    ],
    "wof:name":"Opitec Sa",
    "wof:placetype":"venue"
},
  "geometry": {"coordinates":[7.1799049377,46.8051834106],"type":"Point"}
}