{
  "type": "Feature",
  "properties": {
    "iso:country":"CH",
    "sg:address":"Kirchbergstrasse 102",
    "sg:city":"Burgdorf",
    "sg:orig_category":"Chemische Industrie",
    "sg:phone":"+41 31 424 12 00",
    "sg:postcode":"3400",
    "sg:province":"Bern",
    "wof:name":"Coop Tankstelle",
    "wof:placetype":"venue"
},
  "geometry": {"coordinates":[7.616381,47.062935],"type":"Point"}
}