{
  "type": "Feature",
  "properties": {
    "iso:country":"CH",
    "sg:address":"Hornweid 3083 Trimstein. Postfach",
    "sg:city":"Trimstein",
    "sg:orig_category":"Softwareentwicklung U beratung",
    "sg:postcode":"3083",
    "sg:province":"Bern",
    "wof:name":"Stucki Informatik",
    "wof:placetype":"venue"
},
  "geometry": {"coordinates":[7.5745778084,46.9042167664],"type":"Point"}
}