{
  "type": "Feature",
  "properties": {
    "iso:country":"CH",
    "sg:address":"Rue De La Dixence 49-51",
    "sg:city":"Sion",
    "sg:orig_category":"Grosshandel mit elektrischen Haushaltsger\u00e4ten",
    "sg:phone":"+41 32 935 11 63",
    "sg:postcode":"1950",
    "sg:province":"Valais",
    "wof:name":"Raygil Sa Fournitures Pour L'h\u00f4tellerie",
    "wof:placetype":"venue"
},
  "geometry": {"coordinates":[6.6068201065,46.9808044434],"type":"Point"}
}