{
  "type": "Feature",
  "properties": {
    "iso:country":"CH",
    "sg:address":"Rue Du Grand-pont 11",
    "sg:city":"Sion",
    "sg:orig_category":"Detailhandel mit B\u00fcchern Sonstiger Fachdetailhandel in Verkaufsr\u00e4umen",
    "sg:phone":"+41 27 322 37 49",
    "sg:postcode":"1950",
    "sg:province":"Valais",
    "wof:name":"Librairie Notre-dame De Fatima Articles Religieux",
    "wof:placetype":"venue"
},
  "geometry": {"coordinates":[7.360431,46.233765],"type":"Point"}
}