{
  "type": "Feature",
  "properties": {
    "iso:country":"CH",
    "sg:address":"Theaterstrasse 12 8001 Z\u00fcrich. Postfach 4177",
    "sg:city":"Z\u00fcrich",
    "sg:orig_category":"Aktivit\u00e4t der Bankinstitute Kreditinstitute ohne Spezialkreditinstitute",
    "sg:phone":"+41 22 839 19 19",
    "sg:postcode":"8001",
    "sg:province":"Z\u00fcrich",
    "wof:name":"Finansbank (suisse) Sa",
    "wof:placetype":"venue"
},
  "geometry": {"coordinates":[6.155699,46.196255],"type":"Point"}
}