{
  "type": "Feature",
  "properties": {
    "iso:country":"CH",
    "sg:address":"4414",
    "sg:city":"F\u00fcllinsdorf",
    "sg:orig_category":"Erschliessung von Grundst\u00fccken",
    "sg:phone":"+41 56 460 92 22",
    "sg:postcode":"4414",
    "sg:province":"Basel-Landschaft",
    "wof:name":"Gemiwo Ag Gemeinn\u00fctzige Mietwohn Ag",
    "wof:placetype":"venue"
},
  "geometry": {"coordinates":[8.211607933,47.4831886292],"type":"Point"}
}