{
  "type": "Feature",
  "properties": {
    "iso:country":"CH",
    "sg:address":"Route De Suisse 36",
    "sg:city":"Versoix",
    "sg:orig_category":"Detailhandel mit elektrischen Haushalts-,Radio U Fernsehger\u00e4ten sowie Musikinstrumenten",
    "sg:phone":"+41 19353849",
    "sg:postcode":"1290",
    "sg:province":"Gen\u00e8ve",
    "wof:name":"Radio Gruber Ag",
    "wof:placetype":"venue"
},
  "geometry": {"coordinates":[8.7570333481,47.3068351746],"type":"Point"}
}