{
  "type": "Feature",
  "properties": {
    "iso:country":"CH",
    "sg:address":"Grand'rue 15",
    "sg:city":"St-prex",
    "sg:orig_category":"Erbringung von Dienstleistungen f\u00fcr Unternehmen",
    "sg:postcode":"1162",
    "sg:province":"Vaud",
    "wof:name":"Atelier De Taille Douce S\u00e0rl",
    "wof:placetype":"venue"
},
  "geometry": {"coordinates":[6.4603710175,46.4790992737],"type":"Point"}
}