{
  "type": "Feature",
  "properties": {
    "iso:country":"CH",
    "sg:address":"Hauptstrasse 59",
    "sg:city":"Niederteufen",
    "sg:orig_category":"Herstellung von Metallkonstruktionen Schlossereien",
    "sg:phone":"+41 71 333 20 22",
    "sg:postcode":"9052",
    "sg:province":"Appenzell Ausserrhoden",
    "wof:name":"Markus Messmer Messmer Metallbau Stahlbau",
    "wof:placetype":"venue"
},
  "geometry": {"coordinates":[9.3707799911,47.3911781311],"type":"Point"}
}