{
  "type": "Feature",
  "properties": {
    "iso:country":"CH",
    "sg:address":"Via R. Leoncavallo 68 6614 Brissago. Postfach",
    "sg:city":"Brissago",
    "sg:orig_category":"Reiseb\u00fcros U Reiseveranstalter",
    "sg:postcode":"6614",
    "sg:province":"Ticino",
    "wof:name":"Rosa Dei Venti Sagl",
    "wof:placetype":"venue"
},
  "geometry": {"coordinates":[8.7060604095,46.1134185791],"type":"Point"}
}