{
  "type": "Feature",
  "properties": {
    "iso:country":"CH",
    "sg:address":"Im Baumgarten 10",
    "sg:city":"Stettlen",
    "sg:orig_category":"Zahnarztpraxen",
    "sg:phone":"+41 31 931 51 33",
    "sg:postcode":"3066",
    "sg:province":"Bern",
    "wof:name":"Dr.med.dent.peter E. Herrmann Zahnarzt",
    "wof:placetype":"venue"
},
  "geometry": {"coordinates":[7.5252118111,46.9578437805],"type":"Point"}
}