{
  "type": "Feature",
  "properties": {
    "iso:country":"CH",
    "sg:address":"Haldenstrasse 41 9642 Ebnat. Postfach",
    "sg:city":"Lichtensteig",
    "sg:orig_category":"Reiseb\u00fcros U Reiseveranstalter",
    "sg:phone":"+41 71 988 54 60",
    "sg:postcode":"9620",
    "sg:province":"St. Gallen",
    "wof:name":"Crossroads Travel, Brogli Ren\u00e9",
    "wof:placetype":"venue"
},
  "geometry": {"coordinates":[9.1167001724,47.25],"type":"Point"}
}