{
  "type": "Feature",
  "properties": {
    "iso:country":"CH",
    "sg:address":"Vattiz 7145 Degen. Postfach",
    "sg:city":"Vattiz",
    "sg:orig_category":"Maler U Glasergewerbe",
    "sg:postcode":"7146",
    "sg:province":"Graubunden",
    "wof:name":"Caduff Giachen Philipp",
    "wof:placetype":"venue"
},
  "geometry": {"coordinates":[9.1726398468,46.7045211792],"type":"Point"}
}