{
  "type": "Feature",
  "properties": {
    "addr:full":"6675 Cevio Ticino 6675",
    "addr:postcode":"6675;6675",
    "iso:country":"CH",
    "sg:address":"6675",
    "sg:city":"Cevio",
    "sg:orig_category":"Allgemeiner Hoch U Tiefbau",
    "sg:phone":"+41 91 754 10 31",
    "sg:postcode":"6675",
    "sg:province":"Ticino",
    "wof:name":"Milani Adriano",
    "wof:placetype":"venue"
},
  "geometry": {"coordinates":[8.602025,46.316906],"type":"Point"}
}