{
  "type": "Feature",
  "properties": {
    "iso:country":"CH",
    "sg:address":"Unterg\u00fctschstrasse 51 6003 Luzern. Postfach",
    "sg:city":"Luzern",
    "sg:orig_category":"Detailhandel mit M\u00f6beln U Haushaltsgegenst\u00e4nden",
    "sg:postcode":"6003",
    "sg:province":"Luzern",
    "wof:name":"Fortune Wohnbedarf Stepat & Co. Wohnzubeh\u00f6r; Handel En Gros.",
    "wof:placetype":"venue"
},
  "geometry": {"coordinates":[8.2920656204,47.0472145081],"type":"Point"}
}