{
  "type": "Feature",
  "properties": {
    "iso:country":"CH",
    "sg:address":"Via Delta 28",
    "sg:city":"Ascona",
    "sg:orig_category":"Herstellung von sonstigen Fahrzeugen Instandhaltung U Reparatur von Automobilen",
    "sg:phone":"+41 91 791 42 39",
    "sg:postcode":"6612",
    "sg:province":"Ticino",
    "wof:name":"Bernardi Rolando",
    "wof:placetype":"venue"
},
  "geometry": {"coordinates":[8.7768697739,46.1639709473],"type":"Point"}
}