{
  "type": "Feature",
  "properties": {
    "iso:country":"CH",
    "sg:address":"Oberdorf 10",
    "sg:city":"W\u00f6lflinswil",
    "sg:orig_category":"Sanit\u00e4r U Heizungsinstallation Sanit\u00e4r, Heizungs U L\u00fcftungsinstallation",
    "sg:phone":"+41 62 877 14 13",
    "sg:postcode":"5063",
    "sg:province":"Aargau",
    "wof:name":"Lenzin Heizungen Ag",
    "wof:placetype":"venue"
},
  "geometry": {"coordinates":[7.9983692169,47.4604530334],"type":"Point"}
}