{
  "type": "Feature",
  "properties": {
    "iso:country":"CH",
    "sg:address":"Galbutz 8",
    "sg:city":"Trimmis",
    "sg:orig_category":"Rechtsberatung",
    "sg:postcode":"7203",
    "sg:province":"Graubunden",
    "wof:name":"Stegmaier Consulta",
    "wof:placetype":"venue"
},
  "geometry": {"coordinates":[9.5630292892,46.8975143433],"type":"Point"}
}