{
  "type": "Feature",
  "properties": {
    "iso:country":"CH",
    "sg:address":"Hiltenweid 19 6110 Wolhusen. Postfach",
    "sg:city":"Wolhusen",
    "sg:orig_category":"Interessenvertretungen",
    "sg:postcode":"6110",
    "sg:province":"Luzern",
    "wof:name":"Eduard Geistlich Stiftung",
    "wof:placetype":"venue"
},
  "geometry": {"coordinates":[8.0732545853,47.0589408875],"type":"Point"}
}