{
  "type": "Feature",
  "properties": {
    "iso:country":"CH",
    "sg:address":"Saint-honor\u00e9 Rue 3",
    "sg:city":"Neuch\u00e2tel",
    "sg:orig_category":"Rechtsberatung",
    "sg:postcode":"2000",
    "sg:province":"Neuch\u00e2tel",
    "wof:name":"Kdm Services Sa",
    "wof:placetype":"venue"
},
  "geometry": {"coordinates":[6.9312009811,46.9907722473],"type":"Point"}
}