{
  "type": "Feature",
  "properties": {
    "iso:country":"CH",
    "sg:address":"Schaffhauserstrasse",
    "sg:city":"Frauenfeld",
    "sg:orig_category":"Handel mit Motorr\u00e4dern, Teilen U Zubeh\u00f6r Instandhaltung U Reparatur von Motorr\u00e4dern",
    "sg:phone":"+41 52 721 96 00",
    "sg:postcode":"8500",
    "sg:province":"Thurgau",
    "wof:name":"Bossi`s Bike Store, Bossart J\u00fcrg",
    "wof:placetype":"venue"
},
  "geometry": {"coordinates":[8.8808050156,47.5625762939],"type":"Point"}
}