{
  "type": "Feature",
  "properties": {
    "iso:country":"CH",
    "sg:address":"1473",
    "sg:city":"Font",
    "sg:orig_category":"Landesverteidigung, Sozialversicherung \u00d6ffentliche Verwaltung",
    "sg:phone":"+41 26 663 80 63",
    "sg:postcode":"1473",
    "sg:province":"Fribourg",
    "wof:name":"Centre De Protection Civile",
    "wof:placetype":"venue"
},
  "geometry": {"coordinates":[6.8206748962,46.8364982605],"type":"Point"}
}