{
  "type": "Feature",
  "properties": {
    "iso:country":"CH",
    "sg:address":"Weinfelder Strasse 82",
    "sg:city":"Amriswil",
    "sg:orig_category":"Wirtschaftspr\u00fcfung, Steuerberatung U Treuhand",
    "sg:phone":"+41 71 414 04 04",
    "sg:postcode":"8580",
    "sg:province":"Thurgau",
    "wof:name":"Promega Treuhand Ag",
    "wof:placetype":"venue"
},
  "geometry": {"coordinates":[9.2845010757,47.5448074341],"type":"Point"}
}