{
  "type": "Feature",
  "properties": {
    "iso:country":"CH",
    "sg:address":"8606 N\u00e4nikon. Postfach",
    "sg:city":"Greifensee",
    "sg:orig_category":"Interessenvertretungen",
    "sg:postcode":"8606",
    "sg:province":"Z\u00fcrich",
    "wof:name":"F\u00fcrsorgekasse Der Diakone Des Schweizerischen Reformierten Diakonenhauses",
    "wof:placetype":"venue"
},
  "geometry": {"coordinates":[8.6879301071,47.3698387146],"type":"Point"}
}