{
  "type": "Feature",
  "properties": {
    "iso:country":"CH",
    "sg:address":"Neuwiesenstrasse 3",
    "sg:city":"Winterthur",
    "sg:orig_category":"Alters U Hinterlassenenversicherung AHV, Invalidenversicherung IV, Arbeitslosenversicherung ALV",
    "sg:phone":"+41 52 262 36 62",
    "sg:postcode":"8400",
    "sg:province":"Z\u00fcrich",
    "wof:name":"Industrie-arbeitslosenkasse Winterthur",
    "wof:placetype":"venue"
},
  "geometry": {"coordinates":[8.717327,47.498425],"type":"Point"}
}