{
  "type": "Feature",
  "properties": {
    "iso:country":"CH",
    "sg:address":"R\u00fctmatt 7 6017 Ruswil. Postfach",
    "sg:city":"Ruswil",
    "sg:orig_category":"Non-Classified Establishments",
    "sg:postcode":"6017",
    "sg:province":"Luzern",
    "wof:name":"Siga Holding Ag Beteiligungen Usw",
    "wof:placetype":"venue"
},
  "geometry": {"coordinates":[8.1394329071,47.0810165405],"type":"Point"}
}