{
  "type": "Feature",
  "properties": {
    "iso:country":"CH",
    "sg:address":"Bahnhofstrasse 32",
    "sg:city":"Langenthal",
    "sg:orig_category":"Architektur U Ingenieurb\u00fcros Softwareentwicklung U beratung",
    "sg:phone":"+41 62 923 12 32",
    "sg:postcode":"4900",
    "sg:province":"Bern",
    "wof:name":"Rodel J\u00fcrg, Ingenieurb\u00fcro F\u00fcr Elektronik.",
    "wof:placetype":"venue"
},
  "geometry": {"coordinates":[7.78631,47.214161],"type":"Point"}
}