{
  "type": "Feature",
  "properties": {
    "iso:country":"CH",
    "sg:address":"M\u00fchlebachweg 41 4123 Allschwil. Postfach",
    "sg:city":"Allschwil",
    "sg:orig_category":"RESTAURANTS: TEA-ROOMS",
    "sg:postcode":"4123",
    "sg:province":"Basel-Landschaft",
    "wof:name":"Alma Restaurations Ag",
    "wof:placetype":"venue"
},
  "geometry": {"coordinates":[8.3112096786,46.9831390381],"type":"Point"}
}