{
  "type": "Feature",
  "properties": {
    "iso:country":"CH",
    "sg:address":"Route De La Chocolati\u00e8re 30",
    "sg:city":"Echandens",
    "sg:orig_category":"Grosshandel mit Sportartikeln",
    "sg:phone":"+41 21 701 49 44",
    "sg:postcode":"1026",
    "sg:province":"Vaud",
    "wof:name":"Estetika Sa Equipements De Fitness",
    "wof:placetype":"venue"
},
  "geometry": {"coordinates":[6.54941082,46.5423965454],"type":"Point"}
}