{
  "type": "Feature",
  "properties": {
    "iso:country":"CH",
    "sg:address":"Bachstrasse 6 Brig 3900 Berisal. Postfach",
    "sg:city":"Brig",
    "sg:orig_category":"Technische, physikalische U chemische Untersuchung",
    "sg:postcode":"3900",
    "sg:province":"Valais",
    "wof:name":"Asper Gmbh",
    "wof:placetype":"venue"
},
  "geometry": {"coordinates":[7.9876461029,46.3158912659],"type":"Point"}
}