{
  "type": "Feature",
  "properties": {
    "iso:country":"CH",
    "sg:address":"Stansstaderstrasse 49b 6370 Stans. Postfach",
    "sg:city":"Stans",
    "sg:orig_category":"Architektur U Ingenieurb\u00fcros",
    "sg:phone":"+41 41 619 15 40",
    "sg:postcode":"6370",
    "sg:province":"Nidwalden",
    "wof:name":"R\u00f6thlin + Partner Ingenieure Ag",
    "wof:placetype":"venue"
},
  "geometry": {"coordinates":[8.360525,46.961163],"type":"Point"}
}