{
  "type": "Feature",
  "properties": {
    "iso:country":"CH",
    "sg:address":"Talstrasse 543",
    "sg:city":"Oberstammheim",
    "sg:orig_category":"Datenverarbeitungsdienste Softwareentwicklung U beratung",
    "sg:phone":"+41 52 740 20 21",
    "sg:postcode":"8477",
    "sg:province":"Z\u00fcrich",
    "wof:name":"Reldata Ag",
    "wof:placetype":"venue"
},
  "geometry": {"coordinates":[8.80243,47.634331],"type":"Point"}
}