{
  "type": "Feature",
  "properties": {
    "iso:country":"CH",
    "sg:address":"Niederi Matten 3826 Gimmelwald. Postfach",
    "sg:city":"Gimmelwald",
    "sg:classifiers":[
        {
            "category":"Travel",
            "subcategory":"Hotels & Motels",
            "type":"Entertainment"
        }
    ],
    "sg:postcode":"3826",
    "sg:province":"Bern",
    "sg:tags":[
        "hotels",
        "mit",
        "restaurant"
    ],
    "wof:name":"Mountain-hostel, Petra + Walter Brunner",
    "wof:placetype":"venue"
},
  "geometry": {"coordinates":[7.889550209,46.5450553894],"type":"Point"}
}