{
  "type": "Feature",
  "properties": {
    "iso:country":"CH",
    "sg:address":"Traverse Chemin De La 11 1170 Aubonne. Postfach",
    "sg:city":"Aubonne",
    "sg:orig_category":"Herstellung von medizinischen U chirurgischen Ger\u00e4ten sowie orthop\u00e4dischen Vorrichtungen",
    "sg:phone":"+41 21 807 10 36",
    "sg:postcode":"1170",
    "sg:province":"Vaud",
    "wof:name":"Med-terapi S\u00e0rl D\u00e9velopp. De Nouveaux Produits M\u00e9dicaux Utilisant Les Techniques Etc",
    "wof:placetype":"venue"
},
  "geometry": {"coordinates":[6.391699791,46.4952468872],"type":"Point"}
}