{
  "type": "Feature",
  "properties": {
    "iso:country":"CH",
    "sg:address":"Spitalackerstrasse 65 3013 Bern. Postfach",
    "sg:city":"Bern",
    "sg:orig_category":"Architektur U Ingenieurb\u00fcros",
    "sg:phone":"+41 56 622 45 80",
    "sg:postcode":"3005",
    "sg:province":"Bern",
    "wof:name":"Architekturb\u00fcro Edgar Wirz",
    "wof:placetype":"venue"
},
  "geometry": {"coordinates":[8.26741,47.358864],"type":"Point"}
}