{
  "type": "Feature",
  "properties": {
    "iso:country":"CH",
    "sg:address":"Stadt\u00e4cker 20",
    "sg:city":"B\u00fclach",
    "sg:orig_category":"Fotografisches Gewerbe U fotografische Laboratorien",
    "sg:phone":"+41 13401690",
    "sg:postcode":"8180",
    "sg:province":"Z\u00fcrich",
    "wof:name":"Ip Innovation Und Produktion B. Feissli",
    "wof:placetype":"venue"
},
  "geometry": {"coordinates":[8.5458755493,47.5198822021],"type":"Point"}
}