{
  "type": "Feature",
  "properties": {
    "iso:country":"CH",
    "sg:address":"M\u00fchlegasse 9 4552 Derendingen. Postfach",
    "sg:city":"Derendingen",
    "sg:orig_category":"Sportvereine Turnen",
    "sg:phone":"+41 32 682 28 50",
    "sg:postcode":"4552",
    "sg:province":"Solothurn",
    "wof:name":"Turnverein Derendingen",
    "wof:placetype":"venue"
},
  "geometry": {"coordinates":[7.5854458809,47.1920471191],"type":"Point"}
}