{
  "type": "Feature",
  "properties": {
    "iso:country":"CH",
    "sg:address":"Mittelholzstrasse 11",
    "sg:city":"Herzogenbuchsee",
    "sg:orig_category":"Herstellung von \u00d6fen U Brennern Sanit\u00e4r U Heizungsinstallation",
    "sg:phone":"+41 62 961 40 83",
    "sg:postcode":"3360",
    "sg:province":"Bern",
    "wof:name":"Hans-jakob Jau Oel-& Gasfeuerungen",
    "wof:placetype":"venue"
},
  "geometry": {"coordinates":[7.7146081924,47.1875839233],"type":"Point"}
}