{
  "type": "Feature",
  "properties": {
    "addr:full":"Unterlowmatt 16 Udligenswil Luzern 6044",
    "addr:housenumber":"16",
    "addr:postcode":"6044",
    "addr:street":"Unterlowmatt",
    "iso:country":"CH",
    "sg:address":"Unterlowmatt 16",
    "sg:city":"Udligenswil",
    "sg:orig_category":"Architektur U Ingenieurb\u00fcros",
    "sg:phone":"+41 41 448 35 35",
    "sg:postcode":"6044",
    "sg:province":"Luzern",
    "wof:name":"Alltec Ruckli Joe",
    "wof:placetype":"venue"
},
  "geometry": {"coordinates":[8.40684,47.091042],"type":"Point"}
}