{
  "type": "Feature",
  "properties": {
    "iso:country":"CH",
    "sg:address":"Steistegstrasse 11 6430 Schwyz. Postfach 109",
    "sg:city":"Schwyz",
    "sg:orig_category":"Erschliessung von Grundst\u00fccken",
    "sg:postcode":"6431",
    "sg:province":"Schwyz",
    "wof:name":"Wohnbaugenossenschaft St. Martin",
    "wof:placetype":"venue"
},
  "geometry": {"coordinates":[8.6508197784,47.0194587708],"type":"Point"}
}