{
  "type": "Feature",
  "properties": {
    "iso:country":"CH",
    "sg:address":"Route De Sion 29",
    "sg:city":"Sierre",
    "sg:classifiers":[
        {
            "category":"Government",
            "subcategory":"Post Office",
            "type":"Public Place"
        }
    ],
    "sg:phone":"+41 27 455 83 95",
    "sg:postcode":"3960",
    "sg:province":"Valais",
    "sg:tags":[
        "caf\u00e9s",
        "tea-rooms"
    ],
    "wof:name":"Tea-room Domino",
    "wof:placetype":"venue"
},
  "geometry": {"coordinates":[7.5253791809,46.2902488708],"type":"Point"}
}