{
  "type": "Feature",
  "properties": {
    "iso:country":"CH",
    "sg:address":"Promenade 16",
    "sg:city":"Leukerbad",
    "sg:orig_category":"Bauschreinerei",
    "sg:phone":"+41 27 470 11 59",
    "sg:postcode":"3954",
    "sg:province":"Valais",
    "wof:name":"Adolf Zumofen Schreinerei",
    "wof:placetype":"venue"
},
  "geometry": {"coordinates":[7.629448,46.376118],"type":"Point"}
}