{
  "type": "Feature",
  "properties": {
    "iso:country":"CH",
    "sg:address":"Rue Du Clos-de-bulle 5",
    "sg:city":"Lausanne",
    "sg:classifiers":[
        {
            "category":"Government",
            "subcategory":"Post Office",
            "type":"Public Place"
        }
    ],
    "sg:phone":"+41 21 312 03 83",
    "sg:postcode":"1004",
    "sg:province":"Vaud",
    "sg:tags":[
        "caf\u00e9s",
        "tea-rooms"
    ],
    "wof:name":"Bar \u00e0 Caf\u00e9 Espresso-club City",
    "wof:placetype":"venue"
},
  "geometry": {"coordinates":[6.6303129196,46.5242233276],"type":"Point"}
}