{
  "type": "Feature",
  "properties": {
    "addr:full":"Rosenbergstrasse 115 Neuhausen Schaffhausen 8212",
    "addr:housenumber":"115",
    "addr:postcode":"8212",
    "addr:street":"Rosenbergstrasse",
    "iso:country":"CH",
    "sg:address":"Rosenbergstrasse 115",
    "sg:city":"Neuhausen",
    "sg:orig_category":"Detailhandel mit B\u00fcchern, Zeitungen, Schreib U Papeteriewaren",
    "sg:phone":"+41 52 672 78 22",
    "sg:postcode":"8212",
    "sg:province":"Schaffhausen",
    "wof:name":"Rosenfluh Publikationen Gmbh",
    "wof:placetype":"venue"
},
  "geometry": {"coordinates":[8.618099,47.691639],"type":"Point"}
}