{
  "type": "Feature",
  "properties": {
    "iso:country":"CH",
    "sg:address":"Werkstrasse 20 8404 Oberwinterthur. Postfach",
    "sg:city":"Winterthur",
    "sg:orig_category":"Interessenvertretungen",
    "sg:phone":"+41 52 234 18 18",
    "sg:postcode":"8404",
    "sg:province":"Z\u00fcrich",
    "wof:name":"Stiftung F\u00fcr Natur Und Umwelt",
    "wof:placetype":"venue"
},
  "geometry": {"coordinates":[8.7468099594,47.4995956421],"type":"Point"}
}