{
  "type": "Feature",
  "properties": {
    "iso:country":"CH",
    "sg:address":"Wisentalstrasse 9c 8185 Winkel. Postfach",
    "sg:city":"Winkel",
    "sg:orig_category":"Detailhandel mit Schuhen U Lederwaren",
    "sg:postcode":"8185",
    "sg:province":"Z\u00fcrich",
    "wof:name":"Von Der Goltz Ladina & Cie Leder Artikel U. Nylon; Vertrieb",
    "wof:placetype":"venue"
},
  "geometry": {"coordinates":[8.5523805618,47.4926338196],"type":"Point"}
}