{
  "type": "Feature",
  "properties": {
    "iso:country":"CH",
    "sg:address":"Immeuble Saturne",
    "sg:city":"Anz\u00e8re",
    "sg:orig_category":"Detailhandel mit Blumen U Pflanzen",
    "sg:phone":"+41 27 398 51 81",
    "sg:postcode":"1972",
    "sg:province":"Valais",
    "wof:name":"Edith & Heidi Blum Blum Fleurs",
    "wof:placetype":"venue"
},
  "geometry": {"coordinates":[7.400421,46.296982],"type":"Point"}
}