{
  "type": "Feature",
  "properties": {
    "addr:full":"Selnaustrasse 3 8002 Z\u00fcrich. Postfach Z\u00fcrich Z\u00fcrich 8002",
    "addr:housenumber":"3",
    "addr:postcode":"8002 zuerich. postfach;8002",
    "addr:street":"Selnaustrasse",
    "iso:country":"CH",
    "sg:address":"Selnaustrasse 3 8002 Z\u00fcrich. Postfach",
    "sg:city":"Z\u00fcrich",
    "sg:orig_category":"Berufsbildende weiterf\u00fchrende Schulen",
    "sg:phone":"+41 71 622 52 65",
    "sg:postcode":"8002",
    "sg:province":"Z\u00fcrich",
    "wof:name":"Hanspeter Meier Schreinerschule",
    "wof:placetype":"venue"
},
  "geometry": {"coordinates":[9.138185,47.566669],"type":"Point"}
}