{
  "type": "Feature",
  "properties": {
    "iso:country":"CH",
    "sg:address":"Valdani Via 1",
    "sg:city":"Chiasso",
    "sg:orig_category":"Sonstiges Textilgewerbe",
    "sg:postcode":"6830",
    "sg:province":"Ticino",
    "wof:name":"Velveta International Sa, Luxembourg-kirchberg, Succursale Di Chiasso",
    "wof:placetype":"venue"
},
  "geometry": {"coordinates":[9.0288763046,45.8359642029],"type":"Point"}
}