{
  "type": "Feature",
  "properties": {
    "iso:country":"CH",
    "sg:address":"Avenue De Beaulieu 26",
    "sg:city":"Lausanne",
    "sg:orig_category":"Instandhaltung U Reparatur von Automobilen",
    "sg:phone":"+41 21 647 18 82",
    "sg:postcode":"1004",
    "sg:province":"Vaud",
    "wof:name":"Auto-\u00e9lectricit\u00e9, Cosandey Christian",
    "wof:placetype":"venue"
},
  "geometry": {"coordinates":[6.6270418167,46.5265197754],"type":"Point"}
}