{
  "type": "Feature",
  "properties": {
    "iso:country":"CH",
    "sg:address":"Steinm\u00fcristr. 4 8124 Maur. Postfach",
    "sg:city":"Ebmatingen",
    "sg:orig_category":"G\u00fcterbef\u00f6rderung im Strassenverkehr",
    "sg:postcode":"8123",
    "sg:province":"Z\u00fcrich",
    "wof:name":"Cremona Bruno, Transporte",
    "wof:placetype":"venue"
},
  "geometry": {"coordinates":[8.6421718597,47.3496551514],"type":"Point"}
}