{
  "type": "Feature",
  "properties": {
    "iso:country":"CH",
    "sg:address":"Metzgergasse 14",
    "sg:city":"Aarau",
    "sg:orig_category":"Maler U Glasergewerbe",
    "sg:postcode":"5000",
    "sg:province":"Aargau",
    "wof:name":"Osmani Malergesch\u00e4ft",
    "wof:placetype":"venue"
},
  "geometry": {"coordinates":[8.0441417694,47.3935127258],"type":"Point"}
}