{
  "type": "Feature",
  "properties": {
    "iso:country":"CH",
    "sg:address":"Walkeweg 39",
    "sg:city":"Steffisburg",
    "sg:orig_category":"Malerei",
    "sg:phone":"+41 33 437 55 63",
    "sg:postcode":"3612",
    "sg:province":"Bern",
    "wof:name":"Hans Frey Malergesch\u00e4ft",
    "wof:placetype":"venue"
},
  "geometry": {"coordinates":[7.6374778748,46.78175354],"type":"Point"}
}