{
  "type": "Feature",
  "properties": {
    "iso:country":"CH",
    "sg:address":"Via Bocarello",
    "sg:city":"Arbedo",
    "sg:orig_category":"Herstellung von Metallkonstruktionen",
    "sg:phone":"+41 79 685 28 50",
    "sg:postcode":"6517",
    "sg:province":"Ticino",
    "wof:name":"Claudio Necchi Costruzioni In Ferro",
    "wof:placetype":"venue"
},
  "geometry": {"coordinates":[9.0429515839,46.2117004395],"type":"Point"}
}