{
  "type": "Feature",
  "properties": {
    "iso:country":"CH",
    "sg:address":"Piano Della Stampa",
    "sg:city":"Canobbio",
    "sg:orig_category":"Abbruch U Sprenggewerbe Erdbewegungsarbeiten",
    "sg:phone":"+41 91 941 50 12",
    "sg:postcode":"6952",
    "sg:province":"Ticino",
    "wof:name":"Aldo Silvagni & Figlio Sa Trasporti & Scavi",
    "wof:placetype":"venue"
},
  "geometry": {"coordinates":[8.965891,46.035343],"type":"Point"}
}