{
  "type": "Feature",
  "properties": {
    "iso:country":"CH",
    "sg:address":"Geissbergstrasse 1 5400 Baden. Postfach",
    "sg:city":"Baden",
    "sg:orig_category":"Erbringung von Dienstleistungen f\u00fcr Unternehmen",
    "sg:phone":"+41 56 222 61 18",
    "sg:postcode":"5400",
    "sg:province":"Aargau",
    "wof:name":"Atelier Perotka + Co",
    "wof:placetype":"venue"
},
  "geometry": {"coordinates":[8.3064451218,47.4743309021],"type":"Point"}
}