{
  "type": "Feature",
  "properties": {
    "iso:country":"CH",
    "sg:address":"Bahnhofstr.",
    "sg:city":"Reichenbach",
    "sg:classifiers":[
        {
            "category":"Banks & Credit Unions",
            "subcategory":"Bank",
            "type":"Services"
        }
    ],
    "sg:phone":"+41 33 676 17 88",
    "sg:postcode":"3713",
    "sg:province":"Bern",
    "wof:name":"Spar- Und Leihkasse Frutigen",
    "wof:placetype":"venue"
},
  "geometry": {"coordinates":[7.690002,46.62458],"type":"Point"}
}