{
  "type": "Feature",
  "properties": {
    "iso:country":"CH",
    "sg:address":"Hochfluhstrasse 30",
    "sg:city":"Goldau",
    "sg:orig_category":"Architekturb\u00fcros",
    "sg:phone":"+41 41 855 21 17",
    "sg:postcode":"6410",
    "sg:province":"Schwyz",
    "wof:name":"Frank Meyer Architekturb\u00fcro",
    "wof:placetype":"venue"
},
  "geometry": {"coordinates":[8.548639,47.045681],"type":"Point"}
}