{
  "type": "Feature",
  "properties": {
    "iso:country":"CH",
    "sg:address":"Studackerstrasse 8 8038 Z\u00fcrich. Postfach",
    "sg:city":"Z\u00fcrich",
    "sg:orig_category":"Detailhandel mit Blumen U Pflanzen Fachdetailhandel in Verkaufsr\u00e4umen",
    "sg:phone":"+41 14824142",
    "sg:postcode":"8038",
    "sg:province":"Z\u00fcrich",
    "wof:name":"Blumenhalle Wollishofen Ag Fachgesch\u00e4ft F\u00fcr Floristik",
    "wof:placetype":"venue"
},
  "geometry": {"coordinates":[8.530473,47.338543],"type":"Point"}
}