{
  "type": "Feature",
  "properties": {
    "iso:country":"CH",
    "sg:address":"Seftigenstrasse 400",
    "sg:city":"Kehrsatz",
    "sg:orig_category":"Feuerl\u00f6schapparate Herstellung",
    "sg:phone":"+41 31 961 06 77",
    "sg:postcode":"3122",
    "sg:province":"Bern",
    "wof:name":"Atlantis-feuerl\u00f6scher",
    "wof:placetype":"venue"
},
  "geometry": {"coordinates":[7.4708690643,46.9108428955],"type":"Point"}
}