{
  "type": "Feature",
  "properties": {
    "addr:full":"Silberbachstrasse 11 C 9032 Engelburg. Postfach Engelburg St. Gallen 9032",
    "addr:housenumber":"11 c",
    "addr:postcode":"9032 engelburg. postfach;9032",
    "addr:street":"Silberbachstrasse",
    "iso:country":"CH",
    "sg:address":"Silberbachstrasse 11 C 9032 Engelburg. Postfach",
    "sg:city":"Engelburg",
    "sg:orig_category":"Betrieb von Sportanlagen",
    "sg:phone":"+41 71 277 41 17",
    "sg:postcode":"9032",
    "sg:province":"St. Gallen",
    "wof:name":"Vereinigung Curling-halle Lerchenfeld",
    "wof:placetype":"venue"
},
  "geometry": {"coordinates":[9.347085,47.442677],"type":"Point"}
}