{
  "type": "Feature",
  "properties": {
    "iso:country":"CH",
    "sg:address":"Via Nosetot 36",
    "sg:city":"Caslano",
    "sg:orig_category":"Erbringung von Dienstleistungen f\u00fcr Unternehmen",
    "sg:postcode":"6987",
    "sg:province":"Ticino",
    "wof:name":"Ma Ca Design Di Cavegn Marcel",
    "wof:placetype":"venue"
},
  "geometry": {"coordinates":[8.8802957535,45.9787635803],"type":"Point"}
}