{
  "type": "Feature",
  "properties": {
    "iso:country":"CH",
    "sg:address":"Grand Rue 98",
    "sg:city":"Montreux",
    "sg:orig_category":"Erbringung von Dienstleistungen f\u00fcr Unternehmen",
    "sg:postcode":"1820",
    "sg:province":"Vaud",
    "wof:name":"Malherbe Gilbert",
    "wof:placetype":"venue"
},
  "geometry": {"coordinates":[6.9078831673,46.4376296997],"type":"Point"}
}