{
  "type": "Feature",
  "properties": {
    "iso:country":"CH",
    "sg:address":"Klybeckstrasse 74",
    "sg:city":"Basel",
    "sg:orig_category":"Detailhandel mit Waren verschiedener Art, Hauptrichtung Nahrungsmittel",
    "sg:phone":"+41 21 944 03 22",
    "sg:postcode":"4057",
    "sg:province":"Basel-Stadt",
    "wof:name":"Favero Liz",
    "wof:placetype":"venue"
},
  "geometry": {"coordinates":[6.3048892021,46.3652610779],"type":"Point"}
}