{
  "type": "Feature",
  "properties": {
    "iso:country":"CH",
    "sg:address":"Kornhausgasse 8",
    "sg:city":"Burgdorf",
    "sg:orig_category":"Detailhandel mit Waren verschiedener Art, Hauptrichtung Nahrungsmittel Grosshandel mit Nahrungsmitte",
    "sg:phone":"+41 34 422 49 55",
    "sg:postcode":"3400",
    "sg:province":"Bern",
    "wof:name":"Kummer Hugo",
    "wof:placetype":"venue"
},
  "geometry": {"coordinates":[7.627412796,47.0578536987],"type":"Point"}
}