{
  "type": "Feature",
  "properties": {
    "iso:country":"CH",
    "sg:address":"Faubourg 5",
    "sg:city":"Le Landeron",
    "sg:classifiers":[
        {
            "category":"Banks & Credit Unions",
            "subcategory":"Bank",
            "type":"Services"
        }
    ],
    "sg:phone":"+41 32 751 41 61",
    "sg:postcode":"2525",
    "sg:province":"Neuch\u00e2tel",
    "wof:name":"Raiffeisen Du Vignoble",
    "wof:placetype":"venue"
},
  "geometry": {"coordinates":[7.064438,47.055035],"type":"Point"}
}