{
  "type": "Feature",
  "properties": {
    "iso:country":"CH",
    "sg:address":"Via Chiasso 48",
    "sg:city":"Biasca",
    "sg:orig_category":"Abwasserreinigung",
    "sg:phone":"+41 91 862 30 60",
    "sg:postcode":"6710",
    "sg:province":"Ticino",
    "wof:name":"Consorzio Depurazione Acque Biasca & Dintorni",
    "wof:placetype":"venue"
},
  "geometry": {"coordinates":[8.979045,46.33173],"type":"Point"}
}