{
  "type": "Feature",
  "properties": {
    "iso:country":"CH",
    "sg:address":"Rue Des Petits Champs",
    "sg:city":"Yverdon-les-bains",
    "sg:orig_category":"Herstellung von sonstigen Maschinen f\u00fcr bestimmte Verwendung",
    "sg:phone":"+41 24 424 01 11",
    "sg:postcode":"1400",
    "sg:province":"Vaud",
    "wof:name":"Strid Sa",
    "wof:placetype":"venue"
},
  "geometry": {"coordinates":[6.6421508789,46.7595901489],"type":"Point"}
}