{
  "type": "Feature",
  "properties": {
    "iso:country":"CH",
    "sg:address":"Bahnhofstr. 14",
    "sg:city":"Biel/bienne",
    "sg:classifiers":[
        {
            "category":"Wholesale",
            "subcategory":"Machinery & Supplies",
            "type":"Manufacturing & Wholesale Goods"
        }
    ],
    "sg:phone":"+41 32 323 23 83",
    "sg:postcode":"2501",
    "sg:province":"Bern",
    "sg:tags":[
        "equipment",
        "equipement",
        "precision",
        "timekeeping"
    ],
    "wof:name":"Montres Odeon Sa",
    "wof:placetype":"venue"
},
  "geometry": {"coordinates":[7.2425208092,47.1330947876],"type":"Point"}
}