{
  "type": "Feature",
  "properties": {
    "iso:country":"CH",
    "sg:address":"Neueggstrasse 32",
    "sg:city":"Waldkirch",
    "sg:orig_category":"Fahrschulen, Flugschulen",
    "sg:phone":"+41 71 430 01 01",
    "sg:postcode":"9205",
    "sg:province":"St. Gallen",
    "wof:name":"Roland Keller Autofahrschule",
    "wof:placetype":"venue"
},
  "geometry": {"coordinates":[9.2801704407,47.4647865295],"type":"Point"}
}