{
  "type": "Feature",
  "properties": {
    "addr:full":"Via Santa Maria 46 Gordola Ticino 6596",
    "addr:housenumber":"46",
    "addr:postcode":"6596",
    "addr:street":"Via Santa Maria",
    "iso:country":"CH",
    "sg:address":"Via Santa Maria 46",
    "sg:city":"Gordola",
    "sg:orig_category":"Architektur U Ingenieurb\u00fcros Hoch U Tiefbau",
    "sg:phone":"+41 91 746 13 76",
    "sg:postcode":"6596",
    "sg:province":"Ticino",
    "wof:name":"Edy Salmina Impresa Di Costruzione",
    "wof:placetype":"venue"
},
  "geometry": {"coordinates":[8.865872,46.175446],"type":"Point"}
}