{
  "type": "Feature",
  "properties": {
    "iso:country":"CH",
    "sg:address":"Irchelstrasse 32",
    "sg:city":"Z\u00fcrich",
    "sg:orig_category":"Praxis f\u00fcr Atlaslogie",
    "sg:phone":"+41 13616380",
    "sg:postcode":"8057",
    "sg:province":"Z\u00fcrich",
    "wof:name":"Marcus H\u00e4berling Praxis F\u00fcr Atlaslogie",
    "wof:placetype":"venue"
},
  "geometry": {"coordinates":[8.5434427261,47.3962249756],"type":"Point"}
}