{
  "type": "Feature",
  "properties": {
    "iso:country":"CH",
    "sg:address":"Bergstrasse 3 8706 Meilen. Postfach 770",
    "sg:city":"Meilen",
    "sg:orig_category":"Vermietung U Verpachtung von eigenen Immobilien Vermittlung von Immobilien",
    "sg:phone":"+41 19236688",
    "sg:postcode":"8706",
    "sg:province":"Z\u00fcrich",
    "wof:name":"Dimag Dreispitz Immobilien Meilen Ag",
    "wof:placetype":"venue"
},
  "geometry": {"coordinates":[8.6508331299,47.2662963867],"type":"Point"}
}