{
  "type": "Feature",
  "properties": {
    "iso:country":"CH",
    "sg:address":"Hauptstrasse 28 6280 Hochdorf. Postfach 925",
    "sg:city":"Hochdorf",
    "sg:orig_category":"Detailhandel mit Schreib U Papeteriewaren",
    "sg:phone":"+41 41 910 10 68",
    "sg:postcode":"6281",
    "sg:province":"Luzern",
    "wof:name":"Von Matt Gmbh Papeterie",
    "wof:placetype":"venue"
},
  "geometry": {"coordinates":[8.2899618149,47.166519165],"type":"Point"}
}