{
  "type": "Feature",
  "properties": {
    "iso:country":"CH",
    "sg:address":"Grand-places 1",
    "sg:city":"Freiburg",
    "sg:orig_category":"Handel mit Automobilen",
    "sg:phone":"+41 26 322 37 44",
    "sg:postcode":"1700",
    "sg:province":"Fribourg",
    "wof:name":"Elite Sports Cars S.a.",
    "wof:placetype":"venue"
},
  "geometry": {"coordinates":[7.1545848846,46.8032188416],"type":"Point"}
}