{
  "type": "Feature",
  "properties": {
    "iso:country":"CH",
    "sg:address":"St. Alban-rheinweg 70 4052 Basel. Postfach",
    "sg:city":"Basel",
    "sg:orig_category":"RESTAURANTS: TEA-ROOMS",
    "sg:phone":"+41 61 271 06 44",
    "sg:postcode":"4051",
    "sg:province":"Basel-Stadt",
    "wof:name":"Gefl\u00fcgelte K\u00fcche Bohny Regina Gastronomieunternehmen",
    "wof:placetype":"venue"
},
  "geometry": {"coordinates":[7.60187006,47.5546607971],"type":"Point"}
}