{
  "type": "Feature",
  "properties": {
    "iso:country":"CH",
    "sg:address":"Rigistrasse 23",
    "sg:city":"Zumikon",
    "sg:orig_category":"Unclassifiable Establishments",
    "sg:phone":"+41 19918441",
    "sg:postcode":"8126",
    "sg:province":"Z\u00fcrich",
    "wof:name":"Acorn Holding Ag",
    "wof:placetype":"venue"
},
  "geometry": {"coordinates":[8.6287021637,47.3319282532],"type":"Point"}
}