{
  "type": "Feature",
  "properties": {
    "iso:country":"CH",
    "sg:address":"Gemeindehaus",
    "sg:city":"Stierva",
    "sg:orig_category":"Forst\u00e4mter",
    "sg:phone":"+41 81 681 21 13",
    "sg:postcode":"7459",
    "sg:province":"Graubunden",
    "wof:name":"Revierforstamt Mon Stierva Mutten",
    "wof:placetype":"venue"
},
  "geometry": {"coordinates":[9.5421047211,46.6626014709],"type":"Point"}
}