{
  "type": "Feature",
  "properties": {
    "addr:full":"Kanalstr. 8 Dietikon Z\u00fcrich 8953",
    "addr:housenumber":"8",
    "addr:postcode":"8953",
    "addr:street":"Kanalstr.",
    "iso:country":"CH",
    "sg:address":"Kanalstr. 8",
    "sg:city":"Dietikon",
    "sg:classifiers":[
        {
            "category":"Shopping",
            "subcategory":"Clothing, Apparel, & Fashions",
            "type":"Retail Goods"
        }
    ],
    "sg:phone":"+41 4117411170",
    "sg:postcode":"8953",
    "sg:province":"Z\u00fcrich",
    "sg:tags":[
        "textile",
        "clothing",
        "clothes"
    ],
    "wof:name":"Chicoree Mode Ag",
    "wof:placetype":"venue"
},
  "geometry": {"coordinates":[8.405848,47.412144],"type":"Point"}
}