{
  "type": "Feature",
  "properties": {
    "iso:country":"CH",
    "sg:address":"St\u00f6ckackerstrasse 79 3000 Bern. Postfach",
    "sg:city":"Bern",
    "sg:orig_category":"Fussboden, Fliesen U Plattenlegerei, Tapeziererei",
    "sg:postcode":"3003",
    "sg:province":"Bern",
    "wof:name":"Wicht Jean-marie.",
    "wof:placetype":"venue"
},
  "geometry": {"coordinates":[6.8572998047,46.6518135071],"type":"Point"}
}