{
  "type": "Feature",
  "properties": {
    "iso:country":"CH",
    "sg:address":"Via Alla Campagna 2a 6900 Lugano. Postfach Casa Postale",
    "sg:city":"Lugano",
    "sg:orig_category":"Vermietung U Verpachtung von eigenen Immobilien",
    "sg:postcode":"6900",
    "sg:province":"Ticino",
    "wof:name":"Recasa Sa Immobili",
    "wof:placetype":"venue"
},
  "geometry": {"coordinates":[8.9574308395,46.0145874023],"type":"Point"}
}