{
  "type": "Feature",
  "properties": {
    "iso:country":"CH",
    "sg:address":"M\u00fchlegasse 22",
    "sg:city":"Z\u00fcrich",
    "sg:orig_category":"RESTAURANTS: TEA-ROOMS",
    "sg:postcode":"8001",
    "sg:province":"Z\u00fcrich",
    "wof:name":"Reichmuth Albert Restaurant",
    "wof:placetype":"venue"
},
  "geometry": {"coordinates":[8.8169898987,47.2262916565],"type":"Point"}
}