{
  "type": "Feature",
  "properties": {
    "iso:country":"CH",
    "sg:address":"R\u00fcterwiesstrasse 24",
    "sg:city":"Zollikerberg",
    "sg:orig_category":"\u00dcbersetzungsb\u00fcros",
    "sg:phone":"+41 13920010",
    "sg:postcode":"8125",
    "sg:province":"Z\u00fcrich",
    "wof:name":"Expressis Verbis Uebersetzungen",
    "wof:placetype":"venue"
},
  "geometry": {"coordinates":[8.6010456085,47.3421134949],"type":"Point"}
}