{
  "type": "Feature",
  "properties": {
    "iso:country":"CH",
    "sg:address":"T\u00f6sstalstrasse 93",
    "sg:city":"Kollbrunn",
    "sg:orig_category":"G\u00fcterbef\u00f6rderung im Strassenverkehr",
    "sg:phone":"+41 41 850 30 33",
    "sg:postcode":"8483",
    "sg:province":"Z\u00fcrich",
    "wof:name":"Siegrist Bruno, Transporte",
    "wof:placetype":"venue"
},
  "geometry": {"coordinates":[8.4431762695,47.0839881897],"type":"Point"}
}