{
  "type": "Feature",
  "properties": {
    "iso:country":"CH",
    "sg:address":"Place De Cornavin 8",
    "sg:city":"Gen\u00e8ve",
    "sg:classifiers":[
        {
            "category":"Travel",
            "subcategory":"Hotels & Motels",
            "type":"Entertainment"
        }
    ],
    "sg:phone":"+41 22 906 47 00",
    "sg:postcode":"1201",
    "sg:province":"Gen\u00e8ve",
    "sg:tags":[
        "hotels",
        "mit",
        "restaurant"
    ],
    "wof:name":"H\u00f4tel Savoy",
    "wof:placetype":"venue"
},
  "geometry": {"coordinates":[6.1430010796,46.2092704773],"type":"Point"}
}