{
  "type": "Feature",
  "properties": {
    "addr:full":"Via Cavivens Rabius Graubunden 7172",
    "addr:postcode":"7172",
    "addr:street":"Via Cavivens;Graubunden",
    "iso:country":"CH",
    "sg:address":"Via Cavivens",
    "sg:city":"Rabius",
    "sg:orig_category":"Detailhandel mit Brot, Back U S\u00fcsswaren",
    "sg:phone":"+41 81 943 12 09",
    "sg:postcode":"7172",
    "sg:province":"Graubunden",
    "wof:name":"Tumaisch Baselgia B\u00e4ckerei-konditorei",
    "wof:placetype":"venue"
},
  "geometry": {"coordinates":[8.959642,46.734535],"type":"Point"}
}