{
  "type": "Feature",
  "properties": {
    "iso:country":"CH",
    "sg:address":"Schulstrasse 26",
    "sg:city":"Muttenz",
    "sg:orig_category":"Unclassifiable Establishments",
    "sg:postcode":"4132",
    "sg:province":"Basel-Landschaft",
    "wof:name":"Petitjean & Soller",
    "wof:placetype":"venue"
},
  "geometry": {"coordinates":[7.6486940384,47.5264854431],"type":"Point"}
}