{
  "type": "Feature",
  "properties": {
    "iso:country":"CH",
    "sg:address":"Emmentalstrasse 50",
    "sg:city":"Oberburg",
    "sg:orig_category":"Detailhandel mit M\u00f6beln Innenausbau",
    "sg:phone":"+41 34 423 40 28",
    "sg:postcode":"3414",
    "sg:province":"Bern",
    "wof:name":"Intrateam-organisation Innenarchitektur",
    "wof:placetype":"venue"
},
  "geometry": {"coordinates":[7.6265468597,47.038318634],"type":"Point"}
}