{
  "type": "Feature",
  "properties": {
    "iso:country":"CH",
    "sg:address":"Rigistrasse 54",
    "sg:city":"Basel",
    "sg:orig_category":"Erschliessung von Grundst\u00fccken",
    "sg:phone":"+41 61 301 13 18",
    "sg:postcode":"4054",
    "sg:province":"Basel-Stadt",
    "wof:name":"Gewona Genossenschaft F\u00fcr Wohnen Und Arbeiten",
    "wof:placetype":"venue"
},
  "geometry": {"coordinates":[7.5641031265,47.5537414551],"type":"Point"}
}