{
  "type": "Feature",
  "properties": {
    "iso:country":"CH",
    "sg:address":"Steinenvorstadt 58",
    "sg:city":"Basel",
    "sg:orig_category":"Vermietung U Verpachtung von eigenen Immobilien",
    "sg:phone":"+41 61 311 78 78",
    "sg:postcode":"4051",
    "sg:province":"Basel-Stadt",
    "wof:name":"Likuba Ag",
    "wof:placetype":"venue"
},
  "geometry": {"coordinates":[7.587556839,47.5518722534],"type":"Point"}
}