{
  "type": "Feature",
  "properties": {
    "iso:country":"CH",
    "sg:address":"Spitalstrasse 21",
    "sg:city":"Biel/bienne",
    "sg:classifiers":[
        {
            "category":"Restaurant",
            "type":"Food & Drink"
        }
    ],
    "sg:phone":"+41 32 322 20 60",
    "sg:postcode":"2502",
    "sg:province":"Bern",
    "wof:name":"Restaurant \u00e0 La Diligence",
    "wof:placetype":"venue"
},
  "geometry": {"coordinates":[7.2428088188,47.1362419128],"type":"Point"}
}