{
  "type": "Feature",
  "properties": {
    "iso:country":"CH",
    "sg:address":"Route Des Dailles 41",
    "sg:city":"Villars-sur-gl\u00e2ne",
    "sg:orig_category":"Wirtschaftspr\u00fcfung, Steuerberatung U Treuhand",
    "sg:phone":"+41 26 401 11 09",
    "sg:postcode":"1752",
    "sg:province":"Fribourg",
    "wof:name":"Gumy Jean-daniel",
    "wof:placetype":"venue"
},
  "geometry": {"coordinates":[7.1118431091,46.79504776],"type":"Point"}
}