{
  "type": "Feature",
  "properties": {
    "iso:country":"CH",
    "sg:address":"Spielgasse 4 3115 Gerzensee. Postfach 33",
    "sg:city":"Gerzensee",
    "sg:orig_category":"Maler U Glasergewerbe Malerei",
    "sg:phone":"+41 31 781 01 40",
    "sg:postcode":"3115",
    "sg:province":"Bern",
    "wof:name":"Winnewisser & Kohler Malerei Inh.samuel Kohler",
    "wof:placetype":"venue"
},
  "geometry": {"coordinates":[7.5444312096,46.8392066956],"type":"Point"}
}