{
  "type": "Feature",
  "properties": {
    "iso:country":"CH",
    "sg:address":"Rue Principale 15",
    "sg:city":"Villeret",
    "sg:orig_category":"Detailhandel mit Fleisch U Fleischwaren",
    "sg:phone":"+41 32 941 26 74",
    "sg:postcode":"2613",
    "sg:province":"Bern",
    "wof:name":"Fernand Indermaur Boucherie-charcuterie",
    "wof:placetype":"venue"
},
  "geometry": {"coordinates":[7.0188651085,47.158000946],"type":"Point"}
}