{
  "type": "Feature",
  "properties": {
    "iso:country":"CH",
    "sg:address":"B\u00e4reggstalden 3",
    "sg:city":"Trubschachen",
    "sg:orig_category":"Grosshandel mit landwirtschaftlichen Maschinen U Ger\u00e4ten Herstellung von sonstigen landwirtschaftlic",
    "sg:phone":"+41 34 495 62 64",
    "sg:postcode":"3555",
    "sg:province":"Bern",
    "wof:name":"Rehab Ag, Hofmechanisierung",
    "wof:placetype":"venue"
},
  "geometry": {"coordinates":[7.8302078247,46.9246101379],"type":"Point"}
}