{
  "type": "Feature",
  "properties": {
    "addr:full":"Windegg 4 9100 Herisau. Postfach Herisau Appenzell Ausserrhoden 9102",
    "addr:housenumber":"4",
    "addr:postcode":"9100 herisau. postfach;9102",
    "addr:street":"Windegg;Ausserrhoden",
    "iso:country":"CH",
    "sg:address":"Windegg 4 9100 Herisau. Postfach",
    "sg:city":"Herisau",
    "sg:orig_category":"Arztpraxen",
    "sg:phone":"+41 71 352 25 78",
    "sg:postcode":"9102",
    "sg:province":"Appenzell Ausserrhoden",
    "wof:name":"Dr.med.barbara Herzer Spezial\u00e4rztin",
    "wof:placetype":"venue"
},
  "geometry": {"coordinates":[9.27817,47.385101],"type":"Point"}
}