{
  "type": "Feature",
  "properties": {
    "iso:country":"CH",
    "sg:address":"Chemin Des Couayes",
    "sg:city":"Vouvry",
    "sg:orig_category":"Stukkateurgewerbe, Gipserei U Verputzerei",
    "sg:phone":"+41 79 219 47 50",
    "sg:postcode":"1896",
    "sg:province":"Valais",
    "wof:name":"Horta - Rodriguez Et Fils",
    "wof:placetype":"venue"
},
  "geometry": {"coordinates":[6.8841362,46.3335418701],"type":"Point"}
}