{
  "type": "Feature",
  "properties": {
    "iso:country":"CH",
    "sg:address":"Tiergartenstrasse 8",
    "sg:city":"Burgdorf",
    "sg:orig_category":"Grosshandel mit Eisenwaren sowie Installationsbedarf f\u00fcr Gas, Wasser U Heizung",
    "sg:phone":"+41 34 423 32 85",
    "sg:postcode":"3400",
    "sg:province":"Bern",
    "wof:name":"Giliberti & Co",
    "wof:placetype":"venue"
},
  "geometry": {"coordinates":[7.616464138,47.0619392395],"type":"Point"}
}