{
  "type": "Feature",
  "properties": {
    "iso:country":"CH",
    "sg:address":"Giacomettistrasse 98 7000 Chur. Postfach",
    "sg:city":"Chur",
    "sg:orig_category":"Herstellung von sonstigen Maschinen f\u00fcr unspezifische Verwendung",
    "sg:postcode":"7000",
    "sg:province":"Graubunden",
    "wof:name":"Aar-buchli M. Anlage, Apparate- U. Rohrleitungsbau Usw",
    "wof:placetype":"venue"
},
  "geometry": {"coordinates":[9.5265207291,46.8630371094],"type":"Point"}
}