{
  "type": "Feature",
  "properties": {
    "iso:country":"CH",
    "sg:address":"Chemin Cr\u00e9pon",
    "sg:city":"Chailly-montreux",
    "sg:orig_category":"Detailhandel mit Metallwaren, Anstrichmitteln, Glaswaren, Bau U Heimwerkerbedarf Sonstiger Grosshand",
    "sg:phone":"+41 21 964 83 07",
    "sg:postcode":"1816",
    "sg:province":"Vaud",
    "wof:name":"Techline Karl Grossmann",
    "wof:placetype":"venue"
},
  "geometry": {"coordinates":[6.893682003,46.4478492737],"type":"Point"}
}