{
  "type": "Feature",
  "properties": {
    "iso:country":"CH",
    "sg:address":"Retterswil 20",
    "sg:city":"Seon",
    "sg:orig_category":"Herstellung von Frucht U Gem\u00fcses\u00e4ften Herstellung von Obst U Fruchtweinen",
    "sg:phone":"+41 71 633 19 44",
    "sg:postcode":"5703",
    "sg:province":"Aargau",
    "wof:name":"Otto Aerni Mosterei & Getr\u00e4nkehandlung",
    "wof:placetype":"venue"
},
  "geometry": {"coordinates":[9.1545734406,47.5673713684],"type":"Point"}
}