{
  "type": "Feature",
  "properties": {
    "iso:country":"CH",
    "sg:address":"Eichr\u00fcti 11 6330 Cham. Postfach",
    "sg:city":"Zug",
    "sg:orig_category":"Vereine Tierschutz",
    "sg:phone":"+41 41 780 05 80",
    "sg:postcode":"6301",
    "sg:province":"Zug",
    "wof:name":"Tierschutzverein Des Kt.zug",
    "wof:placetype":"venue"
},
  "geometry": {"coordinates":[8.4483327866,47.16746521],"type":"Point"}
}