{
  "type": "Feature",
  "properties": {
    "iso:country":"CH",
    "sg:address":"H\u00e4gerlerstr. 3",
    "sg:city":"Remetschwil",
    "sg:orig_category":"Herstellung von k\u00e4lte U lufttechnischen Erzeugnissen f\u00fcr gewerbliche Zwecke",
    "sg:phone":"+41 79 346 87 78",
    "sg:postcode":"5453",
    "sg:province":"Aargau",
    "wof:name":"Zier Anlagenbau Ag Anlagen Und Komponenten Zum Reinhalten Der Luft; Projektierung, Herstellung, Im Und Export. Handel Mit Pumpen Usw",
    "wof:placetype":"venue"
},
  "geometry": {"coordinates":[8.3271303177,47.4077911377],"type":"Point"}
}