{
  "type": "Feature",
  "properties": {
    "iso:country":"CH",
    "sg:address":"L\u00e4ngackerstrasse 6",
    "sg:city":"Aarburg",
    "sg:orig_category":"Erbringung von Dienstleistungen f\u00fcr Unternehmen",
    "sg:phone":"+41 62 791 39 43",
    "sg:postcode":"4663",
    "sg:province":"Aargau",
    "wof:name":"Plotstudio Ripaprint Inhaber Ripa F.",
    "wof:placetype":"venue"
},
  "geometry": {"coordinates":[7.9080028534,47.3337593079],"type":"Point"}
}