{
  "type": "Feature",
  "properties": {
    "iso:country":"CH",
    "sg:address":"1997",
    "sg:city":"Haute-nendaz",
    "sg:orig_category":"Verarbeitung von Milch Verwertung von Milch",
    "sg:postcode":"1997",
    "sg:province":"Valais",
    "wof:name":"Soci\u00e9t\u00e9 De Laiterie De Hu\u00e9moz",
    "wof:placetype":"venue"
},
  "geometry": {"coordinates":[6.9953799248,46.2966117859],"type":"Point"}
}