{
  "type": "Feature",
  "properties": {
    "addr:full":"Els\u00e4sserstrasse 250 Basel Basel-Stadt 4056",
    "addr:housenumber":"250",
    "addr:postcode":"4056",
    "addr:street":"Elsaesserstrasse",
    "iso:country":"CH",
    "sg:address":"Els\u00e4sserstrasse 250",
    "sg:city":"Basel",
    "sg:orig_category":"Allgemeiner Hoch U Tiefbau",
    "sg:postcode":"4056",
    "sg:province":"Basel-Stadt",
    "wof:name":"Brobst Ag",
    "wof:placetype":"venue"
},
  "geometry": {"coordinates":[7.572837,47.576515],"type":"Point"}
}