{
  "type": "Feature",
  "properties": {
    "iso:country":"CH",
    "sg:address":"Hauptstrasse 3",
    "sg:city":"Sch\u00fcpfheim",
    "sg:classifiers":[
        {
            "category":"Restaurant",
            "type":"Food & Drink"
        }
    ],
    "sg:phone":"+41 41 484 10 70",
    "sg:postcode":"6170",
    "sg:province":"Luzern",
    "wof:name":"Restaurant R\u00f6ssli",
    "wof:placetype":"venue"
},
  "geometry": {"coordinates":[8.0182552338,46.9528274536],"type":"Point"}
}