{
  "type": "Feature",
  "properties": {
    "iso:country":"CH",
    "sg:address":"Artherstrasse 20 6300 Zug. Postfach 927",
    "sg:city":"Zug",
    "sg:orig_category":"Architektur U Ingenieurb\u00fcros Unternehmensberatung",
    "sg:phone":"+41 41 710 34 53",
    "sg:postcode":"6301",
    "sg:province":"Zug",
    "wof:name":"Miebach Logistik Ag",
    "wof:placetype":"venue"
},
  "geometry": {"coordinates":[8.513365,47.162296],"type":"Point"}
}