{
  "type": "Feature",
  "properties": {
    "iso:country":"CH",
    "sg:address":"Chesa Terza",
    "sg:city":"Zuoz",
    "sg:orig_category":"Herstellung von Reiseartikeln, Leder U Sattlerwaren Verlegen von Fussboden",
    "sg:phone":"+41 81 854 07 44",
    "sg:postcode":"7524",
    "sg:province":"Graubunden",
    "wof:name":"Sergio Zala Gmbh Innenausstattungen",
    "wof:placetype":"venue"
},
  "geometry": {"coordinates":[9.9553289413,46.6024932861],"type":"Point"}
}