{
  "type": "Feature",
  "properties": {
    "iso:country":"CH",
    "sg:address":"Beckenhofstrasse 5",
    "sg:city":"Z\u00fcrich",
    "sg:orig_category":"Sportvereine Sch\u00fctzen Pistolen-& Gewehr",
    "sg:postcode":"8006",
    "sg:province":"Z\u00fcrich",
    "wof:name":"Sch\u00fctzenverein Seewis Im Pr\u00e4ttigau",
    "wof:placetype":"venue"
},
  "geometry": {"coordinates":[9.6389703751,46.990070343],"type":"Point"}
}