{
  "type": "Feature",
  "properties": {
    "iso:country":"CH",
    "sg:address":"Perron Rue Du 10",
    "sg:city":"Coppet",
    "sg:orig_category":"Wirtschaftspr\u00fcfung, Steuerberatung U Treuhand",
    "sg:phone":"+41 21 903 25 81",
    "sg:postcode":"1296",
    "sg:province":"Vaud",
    "wof:name":"Fiduciaire Ficogest, Jung Bernard S\u00e0rl Fiscalit\u00e9, Informatique, Comptabilit\u00e9, Organisation, Gestion Etc",
    "wof:placetype":"venue"
},
  "geometry": {"coordinates":[6.7659840584,46.6073455811],"type":"Point"}
}