{
  "type": "Feature",
  "properties": {
    "iso:country":"CH",
    "sg:address":"Rue St-hubert 57",
    "sg:city":"Bassecourt",
    "sg:orig_category":"Instandhaltung U Reparatur von Automobilen",
    "sg:phone":"+41 32 426 76 88",
    "sg:postcode":"2854",
    "sg:province":"Jura",
    "wof:name":"Claude Chappuis",
    "wof:placetype":"venue"
},
  "geometry": {"coordinates":[7.2370991707,47.3363838196],"type":"Point"}
}