{
  "type": "Feature",
  "properties": {
    "addr:full":"Lettenstrasse 6 Rotkreuz Zug 6343",
    "addr:housenumber":"6",
    "addr:postcode":"6343",
    "addr:street":"Lettenstrasse;Zug",
    "iso:country":"CH",
    "sg:address":"Lettenstrasse 6",
    "sg:city":"Rotkreuz",
    "sg:classifiers":[
        {
            "category":"Government",
            "subcategory":"Office",
            "type":"Public Place"
        }
    ],
    "sg:phone":"+41 41 798 08 88",
    "sg:postcode":"6343",
    "sg:province":"Zug",
    "sg:tags":[
        "subassemblies",
        "assembly",
        "mechanical"
    ],
    "wof:name":"Gag Gelenkketten & Fertigungstechnik",
    "wof:placetype":"venue"
},
  "geometry": {"coordinates":[8.431786,47.148087],"type":"Point"}
}