{
  "type": "Feature",
  "properties": {
    "iso:country":"CH",
    "sg:address":"La Roul\u00e9maz",
    "sg:city":"Riaz",
    "sg:orig_category":"Herstellung von konfektionierten Textilwaren ohne Bekleidung",
    "sg:phone":"+41 41 630 30 73",
    "sg:postcode":"1632",
    "sg:province":"Fribourg",
    "wof:name":"Traumbetten Gmbh",
    "wof:placetype":"venue"
},
  "geometry": {"coordinates":[8.3130998611,46.9879989624],"type":"Point"}
}