{
  "type": "Feature",
  "properties": {
    "iso:country":"CH",
    "sg:address":"7423",
    "sg:city":"Sarn",
    "sg:orig_category":"Sportvereine Sch\u00fctzen",
    "sg:phone":"+41 41 811 76 51",
    "sg:postcode":"7423",
    "sg:province":"Graubunden",
    "wof:name":"Sch\u00fctzenverein",
    "wof:placetype":"venue"
},
  "geometry": {"coordinates":[9.4099559784,46.7195892334],"type":"Point"}
}