{
  "type": "Feature",
  "properties": {
    "iso:country":"CH",
    "sg:address":"Haldenstrasse 1 6340 Baar. Postfach 2321",
    "sg:city":"Baar",
    "sg:orig_category":"Markt U Meinungsforschung Werbeberatung",
    "sg:phone":"+41 41 761 38 07",
    "sg:postcode":"6342",
    "sg:province":"Zug",
    "wof:name":"Nussbaumer Rolf Marketing",
    "wof:placetype":"venue"
},
  "geometry": {"coordinates":[8.5362234116,47.1954154968],"type":"Point"}
}