{
  "type": "Feature",
  "properties": {
    "iso:country":"CH",
    "sg:address":"Oberhof",
    "sg:city":"Fischenthal",
    "sg:orig_category":"Dachdeckerei Zimmerei, Ingenieurholzbau",
    "sg:phone":"+41 55 245 12 46",
    "sg:postcode":"8497",
    "sg:province":"Z\u00fcrich",
    "wof:name":"Ueli Hadorn Holzbau & Bedachungen",
    "wof:placetype":"venue"
},
  "geometry": {"coordinates":[8.921392,47.330975],"type":"Point"}
}