{
  "type": "Feature",
  "properties": {
    "iso:country":"CH",
    "sg:address":"Gehrestrasse",
    "sg:city":"Hefenhofen",
    "sg:orig_category":"Handelsvermittlung U Grosshandel Sonstiger Grosshandel",
    "sg:phone":"+41 71 463 49 64",
    "sg:postcode":"8580",
    "sg:province":"Thurgau",
    "wof:name":"Trs-howald Gmbh",
    "wof:placetype":"venue"
},
  "geometry": {"coordinates":[9.3002748489,47.5621795654],"type":"Point"}
}