{
  "type": "Feature",
  "properties": {
    "iso:country":"CH",
    "sg:address":"Champ De L'augeoz",
    "sg:city":"Chardonne",
    "sg:orig_category":"Fachdetailhandel in Verkaufsr\u00e4umen",
    "sg:postcode":"1803",
    "sg:province":"Vaud",
    "wof:name":"Schmid Ernst.",
    "wof:placetype":"venue"
},
  "geometry": {"coordinates":[1.5296969414,45.1580657959],"type":"Point"}
}