{
  "type": "Feature",
  "properties": {
    "iso:country":"CH",
    "sg:address":"Frenkend\u00f6rferstrasse 42 4133 Pratteln. Postfach",
    "sg:city":"Pratteln",
    "sg:orig_category":"Herstellung von sonstigen elektrischen Ausr\u00fcstungen",
    "sg:postcode":"4133",
    "sg:province":"Basel-Landschaft",
    "wof:name":"Tamil Kadai, Uruthiramoorthy",
    "wof:placetype":"venue"
},
  "geometry": {"coordinates":[7.7131991386,47.534538269],"type":"Point"}
}