{
  "type": "Feature",
  "properties": {
    "addr:full":"Feldeggstrasse 4 Dachsen Z\u00fcrich 8447",
    "addr:housenumber":"4",
    "addr:postcode":"8447",
    "addr:street":"Feldeggstrasse",
    "iso:country":"CH",
    "sg:address":"Feldeggstrasse 4",
    "sg:city":"Dachsen",
    "sg:classifiers":[
        {
            "category":"Banks & Credit Unions",
            "subcategory":"Bank",
            "type":"Services"
        }
    ],
    "sg:phone":"+41 4153296138",
    "sg:postcode":"8447",
    "sg:province":"Z\u00fcrich",
    "wof:name":"Schweiz. Mobiliar",
    "wof:placetype":"venue"
},
  "geometry": {"coordinates":[8.613007,47.669807],"type":"Point"}
}