{
  "type": "Feature",
  "properties": {
    "iso:country":"CH",
    "sg:address":"Siedlung Oeschegg",
    "sg:city":"Derendingen",
    "sg:orig_category":"Landw. Genossenschaften Viehzucht",
    "sg:phone":"+41 32 682 47 54",
    "sg:postcode":"4552",
    "sg:province":"Solothurn",
    "wof:name":"Fleckviehzuchtgenossenschaft Paul Gasche",
    "wof:placetype":"venue"
},
  "geometry": {"coordinates":[7.5971927643,47.1931343079],"type":"Point"}
}