{
  "type": "Feature",
  "properties": {
    "iso:country":"CH",
    "sg:address":"Bahnhofstrasse 23 2540 Grenchen. Postfach 571",
    "sg:city":"Grenchen",
    "sg:orig_category":"Interessenvertretungen",
    "sg:postcode":"2540",
    "sg:province":"Solothurn",
    "wof:name":"Stiftung Girard Adrian Und Dessen Nachkommen Maria Dorer-girard U. Arthur Girard",
    "wof:placetype":"venue"
},
  "geometry": {"coordinates":[7.3964362144,47.1909332275],"type":"Point"}
}