{
  "type": "Feature",
  "properties": {
    "iso:country":"CH",
    "sg:address":"Reichenbachstrasse 61 3004 Bern. Postfach",
    "sg:city":"Bern",
    "sg:orig_category":"Softwareentwicklung U beratung",
    "sg:phone":"+41 31 996 26 26",
    "sg:postcode":"3004",
    "sg:province":"Bern",
    "wof:name":"Sysag Edv-produkte (systeme, Zubeh\u00f6r, Software); Handel, Dienstleistungen",
    "wof:placetype":"venue"
},
  "geometry": {"coordinates":[7.4452548027,46.9708137512],"type":"Point"}
}