{
  "type": "Feature",
  "properties": {
    "iso:country":"CH",
    "sg:address":"Marktgasse 18",
    "sg:city":"Kloten",
    "sg:orig_category":"Detailhandel mit Damenbekleidung Detailhandel mit Herrenbekleidung",
    "sg:phone":"+41 18134990",
    "sg:postcode":"8302",
    "sg:province":"Z\u00fcrich",
    "wof:name":"Mode-boutique Splash",
    "wof:placetype":"venue"
},
  "geometry": {"coordinates":[8.5843296051,47.4496955872],"type":"Point"}
}