{
  "type": "Feature",
  "properties": {
    "iso:country":"CH",
    "sg:address":"Alte Landstrasse 29",
    "sg:city":"Horgen",
    "sg:orig_category":"Handel mit Motorr\u00e4dern, Teilen U Zubeh\u00f6r Instandhaltung U Reparatur von Motorr\u00e4dern",
    "sg:phone":"+41 17254631",
    "sg:postcode":"8810",
    "sg:province":"Z\u00fcrich",
    "wof:name":"Velo Center, Hurter",
    "wof:placetype":"venue"
},
  "geometry": {"coordinates":[8.5953226089,47.2605247498],"type":"Point"}
}