{
  "type": "Feature",
  "properties": {
    "iso:country":"CH",
    "sg:address":"1652",
    "sg:city":"Villarbeney",
    "sg:orig_category":"Instandhaltung U Reparatur von Automobilen",
    "sg:phone":"+41 55 410 42 76",
    "sg:postcode":"1652",
    "sg:province":"Fribourg",
    "wof:name":"Reppro Ralph Meichtry",
    "wof:placetype":"venue"
},
  "geometry": {"coordinates":[8.778717041,47.2016487122],"type":"Point"}
}