{
  "type": "Feature",
  "properties": {
    "iso:country":"CH",
    "sg:address":"Kupfergasse 3",
    "sg:city":"Chur",
    "sg:orig_category":"Herstellung von Duft U K\u00f6rperpflegemitteln Kosmetikinstitute",
    "sg:phone":"+41 81 250 74 75",
    "sg:postcode":"7000",
    "sg:province":"Graubunden",
    "wof:name":"Art Cosmetics Gmbh",
    "wof:placetype":"venue"
},
  "geometry": {"coordinates":[9.5306720734,46.8483428955],"type":"Point"}
}