{
  "type": "Feature",
  "properties": {
    "iso:country":"CH",
    "sg:address":"Route De Vireloup 9",
    "sg:city":"Bellevue",
    "sg:orig_category":"Stukkateurgewerbe, Gipserei U Verputzerei",
    "sg:phone":"+41 22 774 25 78",
    "sg:postcode":"1293",
    "sg:province":"Gen\u00e8ve",
    "wof:name":"Fleury E. Hollenstein M. Sa",
    "wof:placetype":"venue"
},
  "geometry": {"coordinates":[6.1303257942,46.2557029724],"type":"Point"}
}