{
  "type": "Feature",
  "properties": {
    "iso:country":"CH",
    "sg:address":"Hochstrasse 59",
    "sg:city":"Basel",
    "sg:orig_category":"RESTAURANTS: TEA-ROOMS",
    "sg:phone":"+41 32 322 44 64",
    "sg:postcode":"4053",
    "sg:province":"Basel-Stadt",
    "wof:name":"Restaurant Beau-rivage",
    "wof:placetype":"venue"
},
  "geometry": {"coordinates":[7.2271609306,47.1335754395],"type":"Point"}
}