{
  "type": "Feature",
  "properties": {
    "iso:country":"CH",
    "sg:address":"3324",
    "sg:city":"Hindelbank",
    "sg:orig_category":"Wasserversorgung",
    "sg:postcode":"3324",
    "sg:province":"Bern",
    "wof:name":"Brunnengenossenschaft Hohfluh",
    "wof:placetype":"venue"
},
  "geometry": {"coordinates":[8.2025403976,46.7372512817],"type":"Point"}
}