{
  "type": "Feature",
  "properties": {
    "iso:country":"CH",
    "sg:address":"Hauptstrasse 16",
    "sg:city":"Zurzach",
    "sg:orig_category":"Kunsthandel",
    "sg:phone":"+41 56 249 24 12",
    "sg:postcode":"5330",
    "sg:province":"Aargau",
    "wof:name":"Galerie Zum Elephanten",
    "wof:placetype":"venue"
},
  "geometry": {"coordinates":[8.2921390533,47.5840187073],"type":"Point"}
}