{
  "type": "Feature",
  "properties": {
    "iso:country":"CH",
    "sg:address":"Corso San Gottardo 35",
    "sg:city":"Chiasso",
    "sg:orig_category":"Wirtschaftspr\u00fcfung, Steuerberatung U Treuhand",
    "sg:phone":"+41 17411107",
    "sg:postcode":"6830",
    "sg:province":"Ticino",
    "wof:name":"Arlas Treuhand Ag",
    "wof:placetype":"venue"
},
  "geometry": {"coordinates":[8.3857135773,47.3889694214],"type":"Point"}
}