{
  "type": "Feature",
  "properties": {
    "iso:country":"CH",
    "sg:address":"Alte Brauerei",
    "sg:city":"Celerina",
    "sg:orig_category":"Herstellung von Elektrizit\u00e4tsverteilungs U schalteinrichtungen",
    "sg:phone":"+41 62 873 16 73",
    "sg:postcode":"7505",
    "sg:province":"Graubunden",
    "wof:name":"Detron Ag, Stein",
    "wof:placetype":"venue"
},
  "geometry": {"coordinates":[7.9506788254,47.5426025391],"type":"Point"}
}