{
  "type": "Feature",
  "properties": {
    "iso:country":"CH",
    "sg:address":"Sempacherstrasse 6 6003 Luzern. Postfach",
    "sg:city":"Luzern",
    "sg:orig_category":"Pensionskassen",
    "sg:postcode":"6003",
    "sg:province":"Luzern",
    "wof:name":"Personalvorsorgestiftung Der Mathis-unternehmungen St. Moritz",
    "wof:placetype":"venue"
},
  "geometry": {"coordinates":[9.8195371628,46.4827308655],"type":"Point"}
}