{
  "type": "Feature",
  "properties": {
    "iso:country":"CH",
    "sg:address":"Chemin De Charcottet 32",
    "sg:city":"Bevaix",
    "sg:orig_category":"Unternehmensberatung",
    "sg:phone":"+41 71 388 95 00",
    "sg:postcode":"2022",
    "sg:province":"Neuch\u00e2tel",
    "wof:name":"Pathos Ag F\u00fcr Unternehmensberatung",
    "wof:placetype":"venue"
},
  "geometry": {"coordinates":[9.2471818924,47.4153900146],"type":"Point"}
}