{
  "type": "Feature",
  "properties": {
    "iso:country":"CH",
    "sg:address":"Rheingasse 80",
    "sg:city":"Basel",
    "sg:orig_category":"Wohnheime",
    "sg:phone":"+41 61 681 16 98",
    "sg:postcode":"4058",
    "sg:province":"Basel-Stadt",
    "wof:name":"M\u00e4nnerheim Rheinblick Der Heilsarmee",
    "wof:placetype":"venue"
},
  "geometry": {"coordinates":[7.593556881,47.5589332581],"type":"Point"}
}