{
  "type": "Feature",
  "properties": {
    "iso:country":"CH",
    "sg:address":"Bahnhofstrasse 8603 Schwerzenbach. Postfach",
    "sg:city":"Schwerzenbach",
    "sg:orig_category":"Erschliessung von Grundst\u00fccken",
    "sg:postcode":"8603",
    "sg:province":"Z\u00fcrich",
    "wof:name":"Baugesellschaft Zimikerried Ag, Schwerzenbach",
    "wof:placetype":"venue"
},
  "geometry": {"coordinates":[8.6541900635,47.3820991516],"type":"Point"}
}