{
  "type": "Feature",
  "properties": {
    "iso:country":"CH",
    "sg:address":"Stutzweg 3",
    "sg:city":"Niederdorf",
    "sg:orig_category":"Unternehmensberatung",
    "sg:phone":"+41 61 963 01 11",
    "sg:postcode":"4435",
    "sg:province":"Basel-Landschaft",
    "wof:name":"Agentur Am Stutz, Stroppel Angela",
    "wof:placetype":"venue"
},
  "geometry": {"coordinates":[7.7559661865,47.4088745117],"type":"Point"}
}