{
  "type": "Feature",
  "properties": {
    "iso:country":"CH",
    "sg:address":"Eichstrasse 4",
    "sg:city":"Volketswil",
    "sg:orig_category":"Herstellung von sonstigen elektrischen Ausr\u00fcstungen",
    "sg:phone":"+41 19461333",
    "sg:postcode":"8604",
    "sg:province":"Z\u00fcrich",
    "wof:name":"Evox-rifa Gmbh, Engen, Zweigniederlassung Volketswil",
    "wof:placetype":"venue"
},
  "geometry": {"coordinates":[8.6863193512,47.3941574097],"type":"Point"}
}