{
  "type": "Feature",
  "properties": {
    "iso:country":"CH",
    "sg:address":"Erachfeldstrasse 39",
    "sg:city":"B\u00fclach",
    "sg:orig_category":"Sportvereine Turnen Vereine Damen",
    "sg:postcode":"8180",
    "sg:province":"Z\u00fcrich",
    "wof:name":"Satus-frauenriege Hard",
    "wof:placetype":"venue"
},
  "geometry": {"coordinates":[8.5380773544,47.5140533447],"type":"Point"}
}