{
  "type": "Feature",
  "properties": {
    "iso:country":"CH",
    "sg:address":"Avenue De Bel-air 49 C 1225 Ch\u00eane-bourg. Postfach",
    "sg:city":"Ch\u00eane-bourg",
    "sg:orig_category":"Handel mit Automobilteilen U Zubeh\u00f6r",
    "sg:postcode":"1225",
    "sg:province":"Gen\u00e8ve",
    "wof:name":"Slide Cars S\u00e0rl",
    "wof:placetype":"venue"
},
  "geometry": {"coordinates":[6.1984648705,46.2012443542],"type":"Point"}
}