{
  "type": "Feature",
  "properties": {
    "iso:country":"CH",
    "sg:address":"Landhausstrasse 4b",
    "sg:city":"Baar",
    "sg:classifiers":[
        {
            "category":"Professional",
            "subcategory":"Employment Agencies",
            "type":"Services"
        }
    ],
    "sg:postcode":"6340",
    "sg:province":"Zug",
    "sg:tags":[
        "personal",
        "u",
        "stellenvermittlung"
    ],
    "wof:name":"Pebs Ag",
    "wof:placetype":"venue"
},
  "geometry": {"coordinates":[8.5197982788,47.1940689087],"type":"Point"}
}