{
  "type": "Feature",
  "properties": {
    "iso:country":"CH",
    "sg:address":"Kehlhofstrasse 28",
    "sg:city":"Felben-wellhausen",
    "sg:orig_category":"Grosshandel mit Holz U Baustoffen",
    "sg:phone":"+41 52 765 29 00",
    "sg:postcode":"8552",
    "sg:province":"Thurgau",
    "wof:name":"Phoenix-dachbauprodukte Tschanz-subit",
    "wof:placetype":"venue"
},
  "geometry": {"coordinates":[8.9467458725,47.5742111206],"type":"Point"}
}