{
  "type": "Feature",
  "properties": {
    "iso:country":"CH",
    "sg:address":"Hauptstrasse 22 9403 Goldach. Postfach",
    "sg:city":"Goldach",
    "sg:orig_category":"Druckgewerbe",
    "sg:phone":"+41 71 245 50 70",
    "sg:postcode":"9403",
    "sg:province":"St. Gallen",
    "wof:name":"Stiefel Ag Verlag",
    "wof:placetype":"venue"
},
  "geometry": {"coordinates":[9.3996839523,47.4320526123],"type":"Point"}
}