{
  "type": "Feature",
  "properties": {
    "addr:full":"Aeschenplatz 3 Basel Basel-Stadt 4052",
    "addr:housenumber":"3",
    "addr:postcode":"4052",
    "addr:street":"Aeschenplatz",
    "iso:country":"CH",
    "sg:address":"Aeschenplatz 3",
    "sg:city":"Basel",
    "sg:orig_category":"Detailhandel mit Brot, Back U S\u00fcsswaren",
    "sg:phone":"+41 71 913 95 40",
    "sg:postcode":"4052",
    "sg:province":"Basel-Stadt",
    "wof:name":"Br\u00f6tlihus D\u00fcrr Ag",
    "wof:placetype":"venue"
},
  "geometry": {"coordinates":[9.047483,47.465546],"type":"Point"}
}