{
  "type": "Feature",
  "properties": {
    "iso:country":"CH",
    "sg:address":"Niklaus-konrad-strasse 18 4500 Solothurn. Postfach",
    "sg:city":"Solothurn",
    "sg:orig_category":"Unternehmensberatung",
    "sg:phone":"+41 32 622 62 70",
    "sg:postcode":"4501",
    "sg:province":"Solothurn",
    "wof:name":"Permarket Ag",
    "wof:placetype":"venue"
},
  "geometry": {"coordinates":[7.5416750908,47.2047386169],"type":"Point"}
}