{
  "type": "Feature",
  "properties": {
    "iso:country":"CH",
    "sg:address":"S\u00e4gestrasse 25 3097 Liebefeld. Postfach",
    "sg:city":"Liebefeld",
    "sg:orig_category":"Sportvereine Billard",
    "sg:phone":"+41 31 979 15 15",
    "sg:postcode":"3097",
    "sg:province":"Bern",
    "wof:name":"Billard Pot Black",
    "wof:placetype":"venue"
},
  "geometry": {"coordinates":[7.4148468971,46.9269485474],"type":"Point"}
}