{
  "type": "Feature",
  "properties": {
    "iso:country":"CH",
    "sg:address":"Via Gen. Arcioni 18 6900 Lugano. Postfach 6906 Lugano",
    "sg:city":"Caselle",
    "sg:orig_category":"Herstellung von K\u00fcchenm\u00f6beln Herstellung von Metallerzeugnissen ohne Maschinenbau",
    "sg:phone":"+41 56 496 14 66",
    "sg:postcode":"6",
    "wof:name":"Stettbacher Ag",
    "wof:placetype":"venue"
},
  "geometry": {"coordinates":[8.2939882278,47.4476890564],"type":"Point"}
}