{
  "type": "Feature",
  "properties": {
    "iso:country":"CH",
    "sg:address":"Breitlenweg 5",
    "sg:city":"Hombrechtikon",
    "sg:orig_category":"Zimmerei, Dachdeckerei, Bauspenglerei U Abdichtung",
    "sg:postcode":"8634",
    "sg:province":"Z\u00fcrich",
    "wof:name":"Spenglerei J. Hitz",
    "wof:placetype":"venue"
},
  "geometry": {"coordinates":[8.7689504623,47.2526473999],"type":"Point"}
}