{
  "type": "Feature",
  "properties": {
    "iso:country":"CH",
    "sg:address":"Bahnhofstrasse 39",
    "sg:city":"Dietlikon",
    "sg:orig_category":"Detailhandel mit Beleuchtungs U Haushaltsgegenst\u00e4nden Herstellung von elektrischen Lampen U Leuchten",
    "sg:phone":"+41 18341212",
    "sg:postcode":"8305",
    "sg:province":"Z\u00fcrich",
    "wof:name":"Bb Lichtschau Gmbh",
    "wof:placetype":"venue"
},
  "geometry": {"coordinates":[8.619098,47.421745],"type":"Point"}
}