{
  "type": "Feature",
  "properties": {
    "iso:country":"CH",
    "sg:address":"Habsburgerstrasse 20 6003 Luzern. Postfach 4063",
    "sg:city":"Luzern",
    "sg:orig_category":"Datenverarbeitungsdienste Wirtschaftspr\u00fcfung, Steuerberatung U Treuhand",
    "sg:phone":"+41 41 210 34 46",
    "sg:postcode":"6002",
    "sg:province":"Luzern",
    "wof:name":"Partner Treuhand Ag, Luzern",
    "wof:placetype":"venue"
},
  "geometry": {"coordinates":[8.307447,47.047112],"type":"Point"}
}