{
  "type": "Feature",
  "properties": {
    "iso:country":"CH",
    "sg:address":"Franklinstrasse 19",
    "sg:city":"Rorschach",
    "sg:orig_category":"W\u00e4schereien",
    "sg:phone":"+41 71 841 71 51",
    "sg:postcode":"9400",
    "sg:province":"St. Gallen",
    "wof:name":"Maria Galanti W\u00e4scherei",
    "wof:placetype":"venue"
},
  "geometry": {"coordinates":[9.4904308319,47.4723091125],"type":"Point"}
}