{
  "type": "Feature",
  "properties": {
    "iso:country":"CH",
    "sg:address":"Kummetstrasse 36",
    "sg:city":"Attinghausen",
    "sg:orig_category":"Elektroinstallation Herstellung von Elektromotoren, Generatoren U Transformatoren",
    "sg:phone":"+41 41 870 53 35",
    "sg:postcode":"6468",
    "sg:province":"Uri",
    "wof:name":"Ag Elektro Agz",
    "wof:placetype":"venue"
},
  "geometry": {"coordinates":[8.6256046295,46.8604736328],"type":"Point"}
}