{
  "type": "Feature",
  "properties": {
    "iso:country":"CH",
    "sg:address":"Waldeggweg 4",
    "sg:city":"Lichtensteig",
    "sg:orig_category":"Bauschreinerei Zimmerei, Dachdeckerei, Bauspenglerei U Abdichtung",
    "sg:phone":"+41 71 988 87 70",
    "sg:postcode":"9620",
    "sg:province":"St. Gallen",
    "wof:name":"Hans Bleiker",
    "wof:placetype":"venue"
},
  "geometry": {"coordinates":[9.086722,47.328392],"type":"Point"}
}