{
  "type": "Feature",
  "properties": {
    "addr:full":"Badenerstrasse 248 8004 Z\u00fcrich. Postfach Z\u00fcrich Z\u00fcrich 8001",
    "addr:housenumber":"248",
    "addr:postcode":"8004 zuerich. postfach;8001",
    "addr:street":"Badenerstrasse",
    "iso:country":"CH",
    "sg:address":"Badenerstrasse 248 8004 Z\u00fcrich. Postfach",
    "sg:city":"Z\u00fcrich",
    "sg:orig_category":"Detailhandel mit Bekleidung",
    "sg:phone":"+41 12418020",
    "sg:postcode":"8001",
    "sg:province":"Z\u00fcrich",
    "wof:name":"Pelz Petit Pelze; Handel Usw",
    "wof:placetype":"venue"
},
  "geometry": {"coordinates":[8.51665,47.375671],"type":"Point"}
}