{
  "type": "Feature",
  "properties": {
    "iso:country":"CH",
    "sg:address":"Manessestrasse 192 8045 Z\u00fcrich. Postfach",
    "sg:city":"Z\u00fcrich",
    "sg:orig_category":"Detailhandel mit M\u00f6beln U Haushaltsgegenst\u00e4nden Grosshandel mit M\u00f6beln, Wohnbedarf, Teppichen U Bode",
    "sg:phone":"+41 12881543",
    "sg:postcode":"8027",
    "sg:province":"Z\u00fcrich",
    "wof:name":"Spag, Nebel E. Ag",
    "wof:placetype":"venue"
},
  "geometry": {"coordinates":[8.5224809647,47.361076355],"type":"Point"}
}