{
  "type": "Feature",
  "properties": {
    "iso:country":"CH",
    "sg:address":"Rue De L'avenir 21 2852 Court\u00e9telle. Postfach",
    "sg:city":"Court\u00e9telle",
    "sg:orig_category":"G\u00fcterbef\u00f6rderung im Strassenverkehr",
    "sg:phone":"+41 79 220 35 16",
    "sg:postcode":"2852",
    "sg:province":"Jura",
    "wof:name":"Jean Farquet Transports",
    "wof:placetype":"venue"
},
  "geometry": {"coordinates":[7.2124481201,46.0804595947],"type":"Point"}
}