{
  "type": "Feature",
  "properties": {
    "iso:country":"CH",
    "sg:address":"Vorstadtstrasse 188",
    "sg:city":"Laupersdorf",
    "sg:orig_category":"Detailhandel mit elektrischen Haushalts-,Radio U Fernsehger\u00e4ten sowie Musikinstrumenten",
    "sg:phone":"+41 62 391 30 71",
    "sg:postcode":"4712",
    "sg:province":"Solothurn",
    "wof:name":"Notenschreibstudio Graber",
    "wof:placetype":"venue"
},
  "geometry": {"coordinates":[7.6706061363,47.3125915527],"type":"Point"}
}