{
  "type": "Feature",
  "properties": {
    "iso:country":"CH",
    "sg:address":"M\u00fchlehofstrasse 7 6260 Reiden. Postfach 654",
    "sg:city":"Reiden",
    "sg:orig_category":"Architektur U Ingenieurb\u00fcros Architekturb\u00fcros",
    "sg:phone":"+41 79 352 21 11",
    "sg:postcode":"6260",
    "sg:province":"Luzern",
    "wof:name":"Architekturb\u00fcro Widmer Crameri Bauriedl",
    "wof:placetype":"venue"
},
  "geometry": {"coordinates":[9.835789,46.804451],"type":"Point"}
}