{
  "type": "Feature",
  "properties": {
    "iso:country":"CH",
    "sg:address":"Rue De Lausanne 25",
    "sg:city":"Gen\u00e8ve",
    "sg:orig_category":"Datenverarbeitungsdienste Dienstleistungen von Beteiligungsgesellschaften",
    "sg:phone":"+41 22 348 10 50",
    "sg:postcode":"1201",
    "sg:province":"Gen\u00e8ve",
    "wof:name":"Boss Ideas & Services Sarl",
    "wof:placetype":"venue"
},
  "geometry": {"coordinates":[6.144715,46.212246],"type":"Point"}
}