{
  "type": "Feature",
  "properties": {
    "iso:country":"CH",
    "sg:address":"Adlergartenstrasse 4",
    "sg:city":"Schattdorf",
    "sg:classifiers":[
        {
            "category":"Professional",
            "subcategory":"Employment Agencies",
            "type":"Services"
        }
    ],
    "sg:postcode":"6467",
    "sg:province":"Uri",
    "sg:tags":[
        "personal",
        "u",
        "stellenvermittlung"
    ],
    "wof:name":"Walker Manuela, Tempor\u00e4rb\u00fcro",
    "wof:placetype":"venue"
},
  "geometry": {"coordinates":[8.6543827057,46.8650054932],"type":"Point"}
}