{
  "type": "Feature",
  "properties": {
    "iso:country":"CH",
    "sg:address":"Reckholderhubel 4",
    "sg:city":"Oftringen",
    "sg:orig_category":"Vereine Abstinenten",
    "sg:phone":"+41 62 797 66 61",
    "sg:postcode":"4665",
    "sg:province":"Aargau",
    "wof:name":"Schweiz.verein Abstin.lehrer & Lehrerinnen,herrn E.strebel",
    "wof:placetype":"venue"
},
  "geometry": {"coordinates":[7.945130825,47.3030509949],"type":"Point"}
}