{
  "type": "Feature",
  "properties": {
    "iso:country":"CH",
    "sg:address":"B\u00fcrglistrasse 31",
    "sg:city":"Winterthur",
    "sg:classifiers":[
        {
            "category":"Utilities",
            "subcategory":"Water",
            "type":"Services"
        }
    ],
    "sg:phone":"+41 52 262 43 26",
    "sg:postcode":"8400",
    "sg:province":"Z\u00fcrich",
    "sg:tags":[
        "plant",
        "drinking",
        "treatment"
    ],
    "wof:name":"Va Tech Wabag Schweiz Ag",
    "wof:placetype":"venue"
},
  "geometry": {"coordinates":[8.7145414352,47.5054244995],"type":"Point"}
}