{
  "type": "Feature",
  "properties": {
    "iso:country":"CH",
    "sg:address":"Einsiedlerstrasse 31 8820 W\u00e4denswil. Postfach",
    "sg:city":"W\u00e4denswil",
    "sg:orig_category":"Grosshandel mit Textil, N\u00e4h U Strickmaschinen",
    "sg:phone":"+41 18334451",
    "sg:postcode":"8820",
    "sg:province":"Z\u00fcrich",
    "wof:name":"Trematex Ag Import/export",
    "wof:placetype":"venue"
},
  "geometry": {"coordinates":[8.6382465363,47.4079437256],"type":"Point"}
}