{
  "type": "Feature",
  "properties": {
    "addr:full":"Rothorn-center 3 6174 S\u00f6renberg. Postfach S\u00f6renberg Luzern 6174",
    "addr:housenumber":"3",
    "addr:postcode":"6174;6174",
    "addr:street":"Rothorn-Center;Postfach Soerenberg",
    "iso:country":"CH",
    "sg:address":"Rothorn-center 3 6174 S\u00f6renberg. Postfach",
    "sg:city":"S\u00f6renberg",
    "sg:orig_category":"Betrieb von Sportanlagen",
    "sg:postcode":"6174",
    "sg:province":"Luzern",
    "wof:name":"Hallenbad Ag S\u00f6renberg",
    "wof:placetype":"venue"
},
  "geometry": {"coordinates":[8.033968,46.822399],"type":"Point"}
}