{
  "type": "Feature",
  "properties": {
    "addr:full":"Giornicostrasse 237 Basel Basel-Stadt 4059",
    "addr:housenumber":"237",
    "addr:postcode":"4059",
    "addr:street":"Giornicostrasse",
    "iso:country":"CH",
    "sg:address":"Giornicostrasse 237",
    "sg:city":"Basel",
    "sg:orig_category":"Architektur U Ingenieurb\u00fcros",
    "sg:phone":"+41 61 363 21 01",
    "sg:postcode":"4059",
    "sg:province":"Basel-Stadt",
    "wof:name":"Wickli Richard Architekt & Dipl. Ing. Eth/sia",
    "wof:placetype":"venue"
},
  "geometry": {"coordinates":[7.591233,47.526493],"type":"Point"}
}