{
  "type": "Feature",
  "properties": {
    "iso:country":"CH",
    "sg:address":"Brandgasse 8",
    "sg:city":"Hinterforst",
    "sg:orig_category":"Herstellung von k\u00e4lte U lufttechnischen Erzeugnissen f\u00fcr gewerbliche Zwecke",
    "sg:phone":"+41 71 755 00 22",
    "sg:postcode":"9452",
    "sg:province":"St. Gallen",
    "wof:name":"Kako K\u00e4lte Konzept Ag",
    "wof:placetype":"venue"
},
  "geometry": {"coordinates":[9.5299272537,47.3599586487],"type":"Point"}
}