{
  "type": "Feature",
  "properties": {
    "iso:country":"CH",
    "sg:address":"Seftigenstrasse 370",
    "sg:city":"K\u00f6niz",
    "sg:orig_category":"Gesundheitswesen",
    "sg:postcode":"3098",
    "sg:province":"Bern",
    "wof:name":"Reha Ag",
    "wof:placetype":"venue"
},
  "geometry": {"coordinates":[7.4376401901,46.934337616],"type":"Point"}
}