{
  "type": "Feature",
  "properties": {
    "iso:country":"CH",
    "sg:address":"Eschikon 23 8315 Lindau. Postfach",
    "sg:city":"Lindau",
    "sg:orig_category":"Wirtschaftspr\u00fcfung, Steuerberatung U Treuhand",
    "sg:postcode":"8315",
    "sg:province":"Z\u00fcrich",
    "wof:name":"Agro-treuhand Lindau",
    "wof:placetype":"venue"
},
  "geometry": {"coordinates":[8.6802196503,47.4484481812],"type":"Point"}
}