{
  "type": "Feature",
  "properties": {
    "addr:full":"Kohlenberggasse 24 Basel Basel-Stadt 4051",
    "addr:housenumber":"24",
    "addr:postcode":"4051",
    "addr:street":"Kohlenberggasse",
    "iso:country":"CH",
    "sg:address":"Kohlenberggasse 24",
    "sg:city":"Basel",
    "sg:orig_category":"Allgemeiner Hoch U Tiefbau",
    "sg:postcode":"4051",
    "sg:province":"Basel-Stadt",
    "wof:name":"Durtschi Ag",
    "wof:placetype":"venue"
},
  "geometry": {"coordinates":[7.587255,47.552559],"type":"Point"}
}