{
  "type": "Feature",
  "properties": {
    "iso:country":"CH",
    "sg:address":"Gasthof L\u00f6wen 3156 Riffenmatt. Postfach",
    "sg:city":"Riffenmatt",
    "sg:classifiers":[
        {
            "category":"Travel",
            "subcategory":"Hotels & Motels",
            "type":"Entertainment"
        }
    ],
    "sg:phone":"+41 41 925 01 28",
    "sg:postcode":"3156",
    "sg:province":"Bern",
    "sg:tags":[
        "hotels",
        "mit",
        "restaurant"
    ],
    "wof:name":"Rogger-peter Sophie",
    "wof:placetype":"venue"
},
  "geometry": {"coordinates":[8.1154699326,47.157661438],"type":"Point"}
}