{
  "type": "Feature",
  "properties": {
    "iso:country":"CH",
    "sg:address":"Hintere Dammstrasse 11",
    "sg:city":"M\u00f6hlin",
    "sg:orig_category":"RESTAURANTS: TEA-ROOMS",
    "sg:phone":"+41 61 851 10 06",
    "sg:postcode":"4313",
    "sg:province":"Aargau",
    "wof:name":"Restaurant Bahnhof Muff-probst J.",
    "wof:placetype":"venue"
},
  "geometry": {"coordinates":[7.8347640038,47.5616836548],"type":"Point"}
}