{
  "type": "Feature",
  "properties": {
    "iso:country":"CH",
    "sg:address":"General Dufou-strasse 4",
    "sg:city":"Biel/bienne",
    "sg:orig_category":"Erschliessung von Grundst\u00fccken",
    "sg:phone":"+41 32 323 24 55",
    "sg:postcode":"2502",
    "sg:province":"Bern",
    "wof:name":"Baugenossenschaft Wyttenbach",
    "wof:placetype":"venue"
},
  "geometry": {"coordinates":[7.2464981079,47.1391716003],"type":"Point"}
}