{
  "type": "Feature",
  "properties": {
    "addr:full":"Rh\u00f4ne Rue Du 62 1204 Gen\u00e8ve. Postfach Gen\u00e8ve Gen\u00e8ve 1204",
    "addr:postcode":"1204;postfach;1204",
    "addr:street":"Rue Du 62",
    "iso:country":"CH",
    "sg:address":"Rh\u00f4ne Rue Du 62 1204 Gen\u00e8ve. Postfach",
    "sg:city":"Gen\u00e8ve",
    "sg:orig_category":"Detailhandel mit Bekleidung",
    "sg:phone":"+41 22 310 81 43",
    "sg:postcode":"1204",
    "sg:province":"Gen\u00e8ve",
    "wof:name":"Modes & Cr\u00e9ations Sa",
    "wof:placetype":"venue"
},
  "geometry": {"coordinates":[6.142701,46.208359],"type":"Point"}
}