{
  "type": "Feature",
  "properties": {
    "iso:country":"CH",
    "sg:address":"Sus-villars",
    "sg:city":"Bougy-villars",
    "sg:orig_category":"Hochschulen U h\u00f6here Ausbildung",
    "sg:postcode":"1172",
    "sg:province":"Vaud",
    "wof:name":"A La Plume Allegre Sa",
    "wof:placetype":"venue"
},
  "geometry": {"coordinates":[6.3596549034,46.480014801],"type":"Point"}
}