{
  "type": "Feature",
  "properties": {
    "iso:country":"CH",
    "sg:address":"Rue Liotard 42",
    "sg:city":"Gen\u00e8ve",
    "sg:orig_category":"Detailhandel mit Brot, Back U S\u00fcsswaren",
    "sg:phone":"+41 22 344 42 85",
    "sg:postcode":"1202",
    "sg:province":"Gen\u00e8ve",
    "wof:name":"Boulangerie-p\u00e2tisserie & Epicerie Bouclier Sa",
    "wof:placetype":"venue"
},
  "geometry": {"coordinates":[6.130888,46.211506],"type":"Point"}
}