{
  "type": "Feature",
  "properties": {
    "iso:country":"CH",
    "sg:address":"Badhaus",
    "sg:city":"Heimenschwand",
    "sg:orig_category":"Detailhandel mit Brot, Back U S\u00fcsswaren Grosshandel mit Nahrungsmitteln, Getr\u00e4nken U Tabakwaren ohne",
    "sg:phone":"+41 33 453 11 71",
    "sg:postcode":"3615",
    "sg:province":"Bern",
    "wof:name":"Andreas L\u00fcthi",
    "wof:placetype":"venue"
},
  "geometry": {"coordinates":[7.696945,46.828621],"type":"Point"}
}