{
  "type": "Feature",
  "properties": {
    "addr:full":"H\u00fcningenstrasse 15 Konolfingen Bern 3510",
    "addr:housenumber":"15",
    "addr:postcode":"3510",
    "addr:street":"Hueningenstrasse;Bern",
    "iso:country":"CH",
    "sg:address":"H\u00fcningenstrasse 15",
    "sg:city":"Konolfingen",
    "sg:orig_category":"Allgemeiner Hoch U Tiefbau",
    "sg:phone":"+41 31 791 17 21",
    "sg:postcode":"3510",
    "sg:province":"Bern",
    "wof:name":"Bay Management Ag",
    "wof:placetype":"venue"
},
  "geometry": {"coordinates":[7.624198,46.878647],"type":"Point"}
}