{
  "type": "Feature",
  "properties": {
    "iso:country":"CH",
    "sg:address":"Neumattstrasse 25",
    "sg:city":"Lenzburg",
    "sg:orig_category":"Grosshandel mit Maschinen U Ausr\u00fcstungen Grosshandel mit sonstigen Maschinen U Ausr\u00fcstungen f\u00fcr Indu",
    "sg:phone":"+41 62 891 84 81",
    "sg:postcode":"5600",
    "sg:province":"Aargau",
    "wof:name":"Mexpa Ltd",
    "wof:placetype":"venue"
},
  "geometry": {"coordinates":[8.1725082397,47.384147644],"type":"Point"}
}