{
  "type": "Feature",
  "properties": {
    "iso:country":"CH",
    "sg:address":"Ettenbergstrasse 22",
    "sg:city":"Wettswil",
    "sg:orig_category":"Herstellung von Elektrizit\u00e4tsverteilungs U schalteinrichtungen Herstellung von industriellen Prozess",
    "sg:phone":"+41 17004000",
    "sg:postcode":"8907",
    "sg:province":"Z\u00fcrich",
    "wof:name":"Meier Fausto Steuerungen Und Schaltanlagenbau",
    "wof:placetype":"venue"
},
  "geometry": {"coordinates":[8.4717998505,47.3408813477],"type":"Point"}
}