{
  "type": "Feature",
  "properties": {
    "iso:country":"CH",
    "sg:address":"Baselmattweg 195",
    "sg:city":"Allschwil",
    "sg:orig_category":"Fahrschulen, Flugschulen",
    "sg:phone":"+41 79 215 77 30",
    "sg:postcode":"4123",
    "sg:province":"Basel-Landschaft",
    "wof:name":"Kurt Schweighauser Autofahrschule",
    "wof:placetype":"venue"
},
  "geometry": {"coordinates":[7.5579838753,47.5600013733],"type":"Point"}
}