{
  "type": "Feature",
  "properties": {
    "iso:country":"CH",
    "sg:address":"Hofwiesenstrasse 143",
    "sg:city":"Z\u00fcrich",
    "sg:classifiers":[
        {
            "category":"Restaurant",
            "type":"Food & Drink"
        }
    ],
    "sg:phone":"+41 13623615",
    "sg:postcode":"8057",
    "sg:province":"Z\u00fcrich",
    "wof:name":"Zentrumskafi",
    "wof:placetype":"venue"
},
  "geometry": {"coordinates":[8.5336265564,47.4005775452],"type":"Point"}
}