{
  "type": "Feature",
  "properties": {
    "iso:country":"CH",
    "sg:address":"Gotthardstrasse 25 6414 Oberarth. Postfach",
    "sg:city":"Oberarth",
    "sg:orig_category":"Kauf U Verkauf von Immobilien auf eigene Rechnung",
    "sg:postcode":"6414",
    "sg:province":"Schwyz",
    "wof:name":"Olw Ag",
    "wof:placetype":"venue"
},
  "geometry": {"coordinates":[8.5335130692,47.0568847656],"type":"Point"}
}