{
  "type": "Feature",
  "properties": {
    "iso:country":"CH",
    "sg:address":"Wilerstrasse 15",
    "sg:city":"Bazenheid",
    "sg:orig_category":"Verkehrs- and Tourismusb\u00fcros",
    "sg:postcode":"9602",
    "sg:province":"St. Gallen",
    "wof:name":"Verkehrsverein Benken-maria-bildstein",
    "wof:placetype":"venue"
},
  "geometry": {"coordinates":[9.0054197311,47.1976394653],"type":"Point"}
}