{
  "type": "Feature",
  "properties": {
    "iso:country":"CH",
    "sg:address":"Quai Du Seujet 34",
    "sg:city":"Gen\u00e8ve",
    "sg:orig_category":"Sonderschulen Wohnheime f\u00fcr Kinder U Jugendliche",
    "sg:phone":"+41 22 731 46 74",
    "sg:postcode":"1201",
    "sg:province":"Gen\u00e8ve",
    "wof:name":"Horizon Astural Externat P\u00e9d. Th\u00e9rapeutique Pr Pet.enfance",
    "wof:placetype":"venue"
},
  "geometry": {"coordinates":[6.1331148148,46.2039451599],"type":"Point"}
}