{
  "type": "Feature",
  "properties": {
    "addr:full":"Landstrasse 41 Wolfhausen Z\u00fcrich 8633",
    "addr:housenumber":"41",
    "addr:postcode":"8633",
    "addr:street":"Landstrasse",
    "iso:country":"CH",
    "sg:address":"Landstrasse 41",
    "sg:city":"Wolfhausen",
    "sg:classifiers":[
        {
            "category":"Manufacturing",
            "subcategory":"Metals",
            "type":"Manufacturing & Wholesale Goods"
        }
    ],
    "sg:phone":"+41 55 243 31 34",
    "sg:postcode":"8633",
    "sg:province":"Z\u00fcrich",
    "sg:tags":[
        "router",
        "cnc"
    ],
    "wof:name":"Bruno Von B\u00fcren Gmbh",
    "wof:placetype":"venue"
},
  "geometry": {"coordinates":[8.806728,47.258488],"type":"Point"}
}