{
  "type": "Feature",
  "properties": {
    "iso:country":"CH",
    "sg:address":"Neugass 7-9a",
    "sg:city":"Berneck",
    "sg:classifiers":[
        {
            "category":"Professional",
            "subcategory":"Advertising",
            "type":"Services"
        }
    ],
    "sg:phone":"+41 71 747 47 10",
    "sg:postcode":"9442",
    "sg:province":"St. Gallen",
    "sg:tags":[
        "postcard"
    ],
    "wof:name":"Zoller & Co Ag",
    "wof:placetype":"venue"
},
  "geometry": {"coordinates":[9.611217,47.425434],"type":"Point"}
}