{
  "type": "Feature",
  "properties": {
    "iso:country":"CH",
    "sg:address":"Le Bourg A 1610 Ch\u00e2tillens. Postfach",
    "sg:city":"Ch\u00e2tillens",
    "sg:orig_category":"Reiseb\u00fcros U Reiseveranstalter",
    "sg:phone":"+41 21 691 11 88",
    "sg:postcode":"1610",
    "sg:province":"Vaud",
    "wof:name":"Equinoxe Cr\u00e9ation De Voyages, Elmiger Ch.",
    "wof:placetype":"venue"
},
  "geometry": {"coordinates":[6.5586180687,46.5114364624],"type":"Point"}
}