{
  "type": "Feature",
  "properties": {
    "iso:country":"CH",
    "sg:address":"Nordstrasse 10",
    "sg:city":"Amriswil",
    "sg:orig_category":"Organisationen des Gesundheitswesen",
    "sg:phone":"+41 71 411 35 54",
    "sg:postcode":"8580",
    "sg:province":"Thurgau",
    "wof:name":"Lungenliga Thurgau",
    "wof:placetype":"venue"
},
  "geometry": {"coordinates":[9.3028993607,47.5510482788],"type":"Point"}
}