{
  "type": "Feature",
  "properties": {
    "iso:country":"CH",
    "sg:address":"Z\u00fcrichstrasse 1",
    "sg:city":"Uster",
    "sg:orig_category":"W\u00e4scherei U chemische Reinigung",
    "sg:phone":"+41 19408890",
    "sg:postcode":"8610",
    "sg:province":"Z\u00fcrich",
    "wof:name":"Textilpflege Uster, K. + H. Leutenegger-renz",
    "wof:placetype":"venue"
},
  "geometry": {"coordinates":[8.7171792984,47.3484840393],"type":"Point"}
}