{
  "type": "Feature",
  "properties": {
    "iso:country":"CH",
    "sg:address":"Goetheanumstrasse 3",
    "sg:city":"Dornach",
    "sg:orig_category":"Grosshandel mit sonstigen Nahrungsmitteln Sonstiger Fachdetailhandel mit Nahrungsmitteln, Getr\u00e4nken ",
    "sg:phone":"+41 76 316 83 18",
    "sg:postcode":"4143",
    "sg:province":"Solothurn",
    "wof:name":"Reformhaus Persephone Inh. Meier Thomas",
    "wof:placetype":"venue"
},
  "geometry": {"coordinates":[7.6175122261,47.4845542908],"type":"Point"}
}