{
  "type": "Feature",
  "properties": {
    "iso:country":"CH",
    "sg:address":"Vorstadt 2",
    "sg:city":"Schaffhausen",
    "sg:orig_category":"Kosmetikinstitute",
    "sg:phone":"+41 71 311 43 76",
    "sg:postcode":"8200",
    "sg:province":"Schaffhausen",
    "wof:name":"Nicole Geeler Cosmetic Les Belles",
    "wof:placetype":"venue"
},
  "geometry": {"coordinates":[9.3160400391,47.4211997986],"type":"Point"}
}