{
  "type": "Feature",
  "properties": {
    "iso:country":"CH",
    "sg:address":"Route De L'industrie 10",
    "sg:city":"Etoy",
    "sg:orig_category":"Detailhandel mit M\u00f6beln",
    "sg:phone":"+41 21 821 81 11",
    "sg:postcode":"1163",
    "sg:province":"Vaud",
    "wof:name":"Pfister Meubles Sa Centre De L'habitat",
    "wof:placetype":"venue"
},
  "geometry": {"coordinates":[6.4248008728,46.4747467041],"type":"Point"}
}