{
  "type": "Feature",
  "properties": {
    "iso:country":"CH",
    "sg:address":"Aarauerstrasse 25 4600 Olten. Postfach",
    "sg:city":"Olten",
    "sg:orig_category":"Detailhandel mit elektrischen Haushaltsger\u00e4ten",
    "sg:phone":"+41 62 296 78 77",
    "sg:postcode":"4601",
    "sg:province":"Solothurn",
    "wof:name":"Walter Fischer N\u00e4hmaschinen",
    "wof:placetype":"venue"
},
  "geometry": {"coordinates":[7.9090151787,47.3486976624],"type":"Point"}
}