{
  "type": "Feature",
  "properties": {
    "addr:full":"Rue Centrale 10 Lausanne Vaud 1003",
    "addr:housenumber":"10",
    "addr:postcode":"1003",
    "addr:street":"Rue Centrale",
    "iso:country":"CH",
    "sg:address":"Rue Centrale 10",
    "sg:city":"Lausanne",
    "sg:orig_category":"Allgemeiner Hoch U Tiefbau Landschaftsplanungsb\u00fcros U Gartenarchitekturb\u00fcros",
    "sg:phone":"+41 21 311 80 75",
    "sg:postcode":"1003",
    "sg:province":"Vaud",
    "wof:name":"Vilar Sarl",
    "wof:placetype":"venue"
},
  "geometry": {"coordinates":[6.633373,46.520771],"type":"Point"}
}