{
  "type": "Feature",
  "properties": {
    "iso:country":"CH",
    "sg:address":"Lommiswilerstrasse 10",
    "sg:city":"Bellach",
    "sg:orig_category":"Grosshandel mit lebenden Tieren",
    "sg:phone":"+41 32 618 34 01",
    "sg:postcode":"4512",
    "sg:province":"Solothurn",
    "wof:name":"Walter Von Burg Viehhandlung",
    "wof:placetype":"venue"
},
  "geometry": {"coordinates":[7.4891009331,47.2183380127],"type":"Point"}
}