{
  "type": "Feature",
  "properties": {
    "iso:country":"CH",
    "sg:address":"Rue De Lausanne 26",
    "sg:city":"Payerne",
    "sg:orig_category":"Unclassifiable Establishments",
    "sg:postcode":"1530",
    "sg:province":"Vaud",
    "wof:name":"Soci\u00e9t\u00e9 Coop\u00e9rative Beaupr\u00e9, Payerne",
    "wof:placetype":"venue"
},
  "geometry": {"coordinates":[6.9363651276,46.820022583],"type":"Point"}
}