{
  "type": "Feature",
  "properties": {
    "iso:country":"CH",
    "sg:address":"Mattenstrasse 9",
    "sg:city":"G\u00fcmligen",
    "sg:orig_category":"Kauf U Verkauf von Immobilien auf eigene Rechnung",
    "sg:postcode":"3073",
    "sg:province":"Bern",
    "wof:name":"Immo Brawesa Ag",
    "wof:placetype":"venue"
},
  "geometry": {"coordinates":[7.5098400116,46.9335517883],"type":"Point"}
}