{
  "type": "Feature",
  "properties": {
    "iso:country":"CH",
    "sg:address":"Industriestrasse 7",
    "sg:city":"Steinhausen",
    "sg:orig_category":"Mineralwasser Detailhandel",
    "sg:phone":"+41 41 740 41 14",
    "sg:postcode":"6312",
    "sg:province":"Zug",
    "wof:name":"Rolf Schirle Valser-depot",
    "wof:placetype":"venue"
},
  "geometry": {"coordinates":[8.4858522415,47.1914520264],"type":"Point"}
}