{
  "type": "Feature",
  "properties": {
    "iso:country":"CH",
    "sg:address":"Turnweg 17 3013 Bern. Postfach",
    "sg:city":"Bern",
    "sg:orig_category":"Detailhandel mit elektrischen Haushalts-,Radio U Fernsehger\u00e4ten sowie Musikinstrumenten",
    "sg:postcode":"3005",
    "sg:province":"Bern",
    "wof:name":"By The Way Records Hoffmann A. Tontr\u00e4ger; Handel",
    "wof:placetype":"venue"
},
  "geometry": {"coordinates":[7.4475069046,46.9581260681],"type":"Point"}
}