{
  "type": "Feature",
  "properties": {
    "iso:country":"CH",
    "sg:address":"Ottenthalstrasse 2",
    "sg:city":"Lauerz",
    "sg:orig_category":"Praxis f\u00fcr Atlaslogie",
    "sg:phone":"+41 41 811 52 49",
    "sg:postcode":"6424",
    "sg:province":"Schwyz",
    "wof:name":"Heidi Tr\u00fctsch Atlaslogie",
    "wof:placetype":"venue"
},
  "geometry": {"coordinates":[8.6024875641,47.025894165],"type":"Point"}
}