{
  "type": "Feature",
  "properties": {
    "iso:country":"CH",
    "sg:address":"1304",
    "sg:city":"Cossonay-ville",
    "sg:orig_category":"Verarbeitung von Milch Verwertung von Milch",
    "sg:postcode":"1304",
    "sg:province":"Vaud",
    "wof:name":"Soci\u00e9t\u00e9 De Laiterie De Dompierre",
    "wof:placetype":"venue"
},
  "geometry": {"coordinates":[6.9903302193,46.8568611145],"type":"Point"}
}