{
  "type": "Feature",
  "properties": {
    "iso:country":"CH",
    "sg:address":"Busswilstrasse 4",
    "sg:city":"Lyss",
    "sg:orig_category":"Detailhandel Handel mit Motorr\u00e4dern, Teilen U Zubeh\u00f6r Instandhaltung U Reparatur von Motorr\u00e4dern Rep",
    "sg:phone":"+41 32 384 33 51",
    "sg:postcode":"3250",
    "sg:province":"Bern",
    "wof:name":"Peter Kaufmann Motos & Motorr\u00e4der",
    "wof:placetype":"venue"
},
  "geometry": {"coordinates":[7.3074560165,47.0760803223],"type":"Point"}
}