{
  "type": "Feature",
  "properties": {
    "iso:country":"CH",
    "sg:address":"Place Du Petit-saconnex 5",
    "sg:city":"Gen\u00e8ve",
    "sg:orig_category":"Detailhandel mit Brot, Back U S\u00fcsswaren",
    "sg:phone":"+41 22 733 89 98",
    "sg:postcode":"1209",
    "sg:province":"Gen\u00e8ve",
    "wof:name":"Boulangerie Contel Sa",
    "wof:placetype":"venue"
},
  "geometry": {"coordinates":[6.127671,46.222897],"type":"Point"}
}