{
  "type": "Feature",
  "properties": {
    "addr:full":"Bellariastrasse 23 Z\u00fcrich Z\u00fcrich 8002",
    "addr:housenumber":"23",
    "addr:postcode":"8002",
    "addr:street":"Bellariastrasse",
    "iso:country":"CH",
    "sg:address":"Bellariastrasse 23",
    "sg:city":"Z\u00fcrich",
    "sg:classifiers":[
        {
            "category":"Banks & Credit Unions",
            "subcategory":"Bank",
            "type":"Services"
        }
    ],
    "sg:postcode":"8002",
    "sg:province":"Z\u00fcrich",
    "wof:name":"Swissquote Bank",
    "wof:placetype":"venue"
},
  "geometry": {"coordinates":[6.26145,46.422401],"type":"Point"}
}