{
  "type": "Feature",
  "properties": {
    "iso:country":"CH",
    "sg:address":"K\u00e4sereistrasse 23 8260 Wagenhausen. Postfach",
    "sg:city":"Wagenhausen",
    "sg:orig_category":"Detailhandel mit Waren verschiedener Art, Hauptrichtung Nahrungsmittel",
    "sg:phone":"+41 18333409",
    "sg:postcode":"8260",
    "sg:province":"Schaffhausen",
    "wof:name":"Landi Wangen",
    "wof:placetype":"venue"
},
  "geometry": {"coordinates":[8.6544208527,47.401550293],"type":"Point"}
}