{
  "type": "Feature",
  "properties": {
    "addr:full":"Passwangstrasse 184 M\u00fcmliswil Solothurn 4717",
    "addr:housenumber":"184",
    "addr:postcode":"4717",
    "addr:street":"Passwangstrasse;Solothurn",
    "iso:country":"CH",
    "sg:address":"Passwangstrasse 184",
    "sg:city":"M\u00fcmliswil",
    "sg:orig_category":"Allgemeiner Hoch U Tiefbau",
    "sg:phone":"+41 62 391 06 23",
    "sg:postcode":"4717",
    "sg:province":"Solothurn",
    "wof:name":"Fluri Paul Ag",
    "wof:placetype":"venue"
},
  "geometry": {"coordinates":[7.656167,47.346622],"type":"Point"}
}