{
  "type": "Feature",
  "properties": {
    "iso:country":"CH",
    "sg:address":"Juchstrasse 28",
    "sg:city":"Matzingen",
    "sg:orig_category":"Mechanische Werkst\u00e4tten Pulvermetallurgie Schmieden, Pressen, Stanzen U Profilwalzen von Metallen",
    "sg:phone":"+41 52 369 61 61",
    "sg:postcode":"9548",
    "sg:province":"Thurgau",
    "wof:name":"Saxonia Ag",
    "wof:placetype":"venue"
},
  "geometry": {"coordinates":[8.9305410385,47.522819519],"type":"Point"}
}