{
  "type": "Feature",
  "properties": {
    "iso:country":"CH",
    "sg:address":"Nestl\u00e9strasse 20 6300 Zug. Postfach",
    "sg:city":"Cham",
    "sg:orig_category":"Sonstige mit der Informatik verbundene T\u00e4tigkeiten",
    "sg:postcode":"6330",
    "sg:province":"Zug",
    "wof:name":"Edv - Dienstleistungen Piccolo Paolo",
    "wof:placetype":"venue"
},
  "geometry": {"coordinates":[9.2036733627,47.5192527771],"type":"Point"}
}