{
  "type": "Feature",
  "properties": {
    "iso:country":"CH",
    "sg:address":"3256",
    "sg:city":"Dieterswil",
    "sg:classifiers":[
        {
            "category":"Government",
            "subcategory":"Post Office",
            "type":"Public Place"
        }
    ],
    "sg:phone":"+41 31 879 01 03",
    "sg:postcode":"3256",
    "sg:province":"Bern",
    "sg:tags":[
        "die",
        "poststellen"
    ],
    "wof:name":"Die Post",
    "wof:placetype":"venue"
},
  "geometry": {"coordinates":[7.4271001816,47.0543403625],"type":"Point"}
}