{
  "type": "Feature",
  "properties": {
    "iso:country":"CH",
    "sg:address":"Wendt Avenue 60 1203 Gen\u00e8ve. Postfach",
    "sg:city":"Gen\u00e8ve",
    "sg:orig_category":"Sonstige Kurierdienste",
    "sg:postcode":"1203",
    "sg:province":"Gen\u00e8ve",
    "wof:name":"Pharmadomicile S\u00e0rl",
    "wof:placetype":"venue"
},
  "geometry": {"coordinates":[6.1283340454,46.2124328613],"type":"Point"}
}