{
  "type": "Feature",
  "properties": {
    "iso:country":"CH",
    "sg:address":"Mandliwisstrasse 13",
    "sg:city":"Fehraltorf",
    "sg:orig_category":"Allgemeiner Hoch U Tiefbau Architekturb\u00fcros",
    "sg:phone":"+41 19541020",
    "sg:postcode":"8320",
    "sg:province":"Z\u00fcrich",
    "wof:name":"Baumann Robert Ag",
    "wof:placetype":"venue"
},
  "geometry": {"coordinates":[8.758841,47.392792],"type":"Point"}
}