{
  "type": "Feature",
  "properties": {
    "iso:country":"CH",
    "sg:address":"6210 Sursee. Postfach",
    "sg:city":"Sursee",
    "sg:orig_category":"Vermietung U Verpachtung von eigenen Immobilien",
    "sg:postcode":"6210",
    "sg:province":"Luzern",
    "wof:name":"Pinosa Ag",
    "wof:placetype":"venue"
},
  "geometry": {"coordinates":[9.0000734329,47.1998558044],"type":"Point"}
}