{
  "type": "Feature",
  "properties": {
    "iso:country":"CH",
    "sg:address":"Rue Du Midi 15",
    "sg:city":"Lausanne",
    "sg:orig_category":"Zahntechnische Laboratorien",
    "sg:phone":"+41 21 312 66 94",
    "sg:postcode":"1003",
    "sg:province":"Vaud",
    "wof:name":"Laboratoire Dentaire Proth\u00e8se & C\u00e9ramique, Blanc Dominique",
    "wof:placetype":"venue"
},
  "geometry": {"coordinates":[6.6337771416,46.5181045532],"type":"Point"}
}