{
  "type": "Feature",
  "properties": {
    "iso:country":"CH",
    "sg:address":"De-grenus Place 10 1201 Gen\u00e8ve. Postfach",
    "sg:city":"Gen\u00e8ve",
    "sg:orig_category":"Sonstige pers\u00f6nliche Dienstleistungen",
    "sg:postcode":"1201",
    "sg:province":"Gen\u00e8ve",
    "wof:name":"Beta-gamma-services Sa",
    "wof:placetype":"venue"
},
  "geometry": {"coordinates":[6.1432700157,46.2069854736],"type":"Point"}
}