{
  "type": "Feature",
  "properties": {
    "iso:country":"CH",
    "sg:address":"Benknerstrasse 23",
    "sg:city":"Kaltbrunn",
    "sg:orig_category":"Zimmerei, Ingenieurholzbau",
    "sg:phone":"+41 55 283 11 30",
    "sg:postcode":"8722",
    "sg:province":"St. Gallen",
    "wof:name":"Jakob Harder Holzbau",
    "wof:placetype":"venue"
},
  "geometry": {"coordinates":[9.0243730545,47.2109603882],"type":"Point"}
}