{
  "type": "Feature",
  "properties": {
    "iso:country":"CH",
    "sg:address":"St\u00f6cken 8865 Bilten. Postfach 158",
    "sg:city":"Bilten",
    "sg:orig_category":"Grosshandel mit lebenden Tieren",
    "sg:phone":"+41 55 615 10 30",
    "sg:postcode":"8865",
    "sg:province":"Glarus",
    "wof:name":"Linth-viehvermarktungs Ag",
    "wof:placetype":"venue"
},
  "geometry": {"coordinates":[9.0061502457,47.1579551697],"type":"Point"}
}