{
  "type": "Feature",
  "properties": {
    "iso:country":"CH",
    "sg:address":"Feld",
    "sg:city":"Berschis",
    "sg:orig_category":"Bauschreinerei Einbau von Schreinerwaren",
    "sg:phone":"+41 41 467 35 35",
    "sg:postcode":"8892",
    "sg:province":"St. Gallen",
    "wof:name":"Loosli Ag Schreinerei & K\u00fcchenbau",
    "wof:placetype":"venue"
},
  "geometry": {"coordinates":[8.191147,47.115833],"type":"Point"}
}