{
  "type": "Feature",
  "properties": {
    "iso:country":"CH",
    "sg:address":"Bahnhofpassage 94",
    "sg:city":"Z\u00fcrich",
    "sg:orig_category":"Detailhandel mit B\u00fcchern",
    "sg:phone":"+41 12154460",
    "sg:postcode":"8001",
    "sg:province":"Z\u00fcrich",
    "wof:name":"Alfred Barth Ag Buchhandlung",
    "wof:placetype":"venue"
},
  "geometry": {"coordinates":[8.53957,47.375931],"type":"Point"}
}