{
  "type": "Feature",
  "properties": {
    "iso:country":"CH",
    "sg:address":"Heglerstrasse 4",
    "sg:city":"Hitzkirch",
    "sg:orig_category":"Zimmerei, Dachdeckerei, Bauspenglerei U Abdichtung",
    "sg:phone":"+41 31 832 40 45",
    "sg:postcode":"6285",
    "sg:province":"Luzern",
    "wof:name":"Hofer Und Schenk Gmbh Holzbau - Bodenbel\u00e4ge",
    "wof:placetype":"venue"
},
  "geometry": {"coordinates":[7.558259964,46.9350585938],"type":"Point"}
}