{
  "type": "Feature",
  "properties": {
    "iso:country":"CH",
    "sg:address":"Seetalstrasse 6",
    "sg:city":"Seon",
    "sg:orig_category":"Herstellung von Radio U Fernsehger\u00e4ten sowie phono U videotechnischen Ger\u00e4ten",
    "sg:phone":"+41 62 775 45 70",
    "sg:postcode":"5703",
    "sg:province":"Aargau",
    "wof:name":"Reparatur-service Zuber",
    "wof:placetype":"venue"
},
  "geometry": {"coordinates":[8.159277916,47.3508033752],"type":"Point"}
}