{
  "type": "Feature",
  "properties": {
    "iso:country":"CH",
    "sg:address":"Z\u00fcrcherstrasse 1",
    "sg:city":"Bremgarten",
    "sg:classifiers":[
        {
            "category":"Banks & Credit Unions",
            "subcategory":"Bank",
            "type":"Services"
        }
    ],
    "sg:phone":"+41 4157311212",
    "sg:postcode":"5620",
    "sg:province":"Aargau",
    "wof:name":"Aargauische Kantonalbank",
    "wof:placetype":"venue"
},
  "geometry": {"coordinates":[8.344401,47.351101],"type":"Point"}
}