{
  "type": "Feature",
  "properties": {
    "addr:full":"Rehweg Grabs St. Gallen 9472",
    "addr:postcode":"9472",
    "addr:street":"Rehweg Grabs",
    "iso:country":"CH",
    "sg:address":"Rehweg",
    "sg:city":"Grabs",
    "sg:orig_category":"Architektur U Ingenieurb\u00fcros",
    "sg:phone":"+41 81 740 03 33",
    "sg:postcode":"9472",
    "sg:province":"St. Gallen",
    "wof:name":"Ingenieurb\u00fcro Steinmann",
    "wof:placetype":"venue"
},
  "geometry": {"coordinates":[9.451533,47.170757],"type":"Point"}
}