{
  "type": "Feature",
  "properties": {
    "iso:country":"CH",
    "sg:address":"Corso San Gottardo 25",
    "sg:city":"Chiasso",
    "sg:orig_category":"Fachdetailhandel in Verkaufsr\u00e4umen Reparatur von Uhren U Schmuck",
    "sg:phone":"+41 91 682 87 78",
    "sg:postcode":"6830",
    "sg:province":"Ticino",
    "wof:name":"Orologeria Audrino Di Giovanni Ardizzoni",
    "wof:placetype":"venue"
},
  "geometry": {"coordinates":[9.0317249298,45.8330116272],"type":"Point"}
}