{
  "type": "Feature",
  "properties": {
    "iso:country":"CH",
    "sg:address":"Locarno Via 6612 Ascona. Postfach Casa Postale",
    "sg:city":"Ascona",
    "sg:orig_category":"RESTAURANTS: TEA-ROOMS",
    "sg:postcode":"6612",
    "sg:province":"Ticino",
    "wof:name":"La Tana Ascona Sa Esercizi Pubblici Ecc",
    "wof:placetype":"venue"
},
  "geometry": {"coordinates":[8.7699813843,46.157283783],"type":"Point"}
}