{
  "type": "Feature",
  "properties": {
    "iso:country":"CH",
    "sg:address":"Wehntalerstrasse 9",
    "sg:city":"Sch\u00f6fflisdorf",
    "sg:orig_category":"Herstellung von Werkzeugen Herstellung von sonstigen Werkzeugmaschinen",
    "sg:phone":"+41 79 401 37 07",
    "sg:postcode":"8165",
    "sg:province":"Z\u00fcrich",
    "wof:name":"Duco Maschinen Ag",
    "wof:placetype":"venue"
},
  "geometry": {"coordinates":[8.4183111191,47.4995498657],"type":"Point"}
}