{
  "type": "Feature",
  "properties": {
    "iso:country":"CH",
    "sg:address":"Obergestadeckweg 10",
    "sg:city":"Liestal",
    "sg:orig_category":"Handel mit Motorr\u00e4dern, Teilen U Zubeh\u00f6r Instandhaltung U Reparatur von Motorr\u00e4dern",
    "sg:phone":"+41 61 923 90 90",
    "sg:postcode":"4410",
    "sg:province":"Basel-Landschaft",
    "wof:name":"Zweirad Thommen",
    "wof:placetype":"venue"
},
  "geometry": {"coordinates":[7.7367649078,47.4840011597],"type":"Point"}
}