{
  "type": "Feature",
  "properties": {
    "iso:country":"CH",
    "sg:address":"Rue De L'eglise 14",
    "sg:city":"Court\u00e9telle",
    "sg:orig_category":"Mechanische Werkst\u00e4tten",
    "sg:phone":"+41 32 422 88 07",
    "sg:postcode":"2852",
    "sg:province":"Jura",
    "wof:name":"Alfred Villoz Atelier M\u00e9canique",
    "wof:placetype":"venue"
},
  "geometry": {"coordinates":[7.3150801659,47.3407669067],"type":"Point"}
}