{
  "type": "Feature",
  "properties": {
    "iso:country":"CH",
    "sg:address":"Stationsstrasse 2",
    "sg:city":"Igis",
    "sg:orig_category":"Unclassifiable Establishments",
    "sg:phone":"+41 81 322 40 57",
    "sg:postcode":"7206",
    "sg:province":"Graubunden",
    "wof:name":"Leonhard Riedberger Schreinerei",
    "wof:placetype":"venue"
},
  "geometry": {"coordinates":[9.5644445419,46.9486885071],"type":"Point"}
}