{
  "type": "Feature",
  "properties": {
    "iso:country":"CH",
    "sg:address":"S\u00e4listrasse 80",
    "sg:city":"Olten",
    "sg:orig_category":"Reiseb\u00fcros U Reiseveranstalter",
    "sg:phone":"+41 79 401 32 34",
    "sg:postcode":"4600",
    "sg:province":"Solothurn",
    "wof:name":"Planet Diving, Aubry",
    "wof:placetype":"venue"
},
  "geometry": {"coordinates":[6.8602528572,46.9589805603],"type":"Point"}
}