{
  "type": "Feature",
  "properties": {
    "iso:country":"CH",
    "sg:address":"Husmattstr. 355",
    "sg:city":"Unterb\u00f6zberg",
    "sg:orig_category":"Allgemeiner Hoch U Tiefbau",
    "sg:phone":"+41 56 442 18 60",
    "sg:postcode":"5224",
    "sg:province":"Aargau",
    "wof:name":"H\u00e4feli Adrian Gmbh",
    "wof:placetype":"venue"
},
  "geometry": {"coordinates":[8.173425,47.4818],"type":"Point"}
}