{
  "type": "Feature",
  "properties": {
    "iso:country":"CH",
    "sg:address":"Bachstrasse 18",
    "sg:city":"Schaffhausen",
    "sg:classifiers":[
        {
            "category":"Restaurant",
            "type":"Food & Drink"
        }
    ],
    "sg:phone":"+41 52 625 57 98",
    "sg:postcode":"8200",
    "sg:province":"Schaffhausen",
    "wof:name":"Restaurant Schalcheneck",
    "wof:placetype":"venue"
},
  "geometry": {"coordinates":[8.6381225586,47.6961746216],"type":"Point"}
}