{
  "type": "Feature",
  "properties": {
    "addr:full":"Hauptstrasse 129 Ermatingen Thurgau 8272",
    "addr:housenumber":"129",
    "addr:postcode":"8272",
    "addr:street":"Hauptstrasse",
    "iso:country":"CH",
    "sg:address":"Hauptstrasse 129",
    "sg:city":"Ermatingen",
    "sg:orig_category":"Architekturb\u00fcros",
    "sg:phone":"+41 71 663 73 83",
    "sg:postcode":"8272",
    "sg:province":"Thurgau",
    "wof:name":"Eddi Singer Architekturb\u00fcro",
    "wof:placetype":"venue"
},
  "geometry": {"coordinates":[9.084279,47.669044],"type":"Point"}
}