{
  "type": "Feature",
  "properties": {
    "iso:country":"CH",
    "sg:address":"Noirmont Chemin Du 17",
    "sg:city":"Lausanne",
    "sg:orig_category":"Interessenvertretungen",
    "sg:postcode":"1004",
    "sg:province":"Vaud",
    "wof:name":"Fonds Du Jubil\u00e9 De La Soci\u00e9t\u00e9 Suisse De Radiologie",
    "wof:placetype":"venue"
},
  "geometry": {"coordinates":[6.8316879272,47.1135902405],"type":"Point"}
}