{
  "type": "Feature",
  "properties": {
    "iso:country":"CH",
    "sg:address":"Grand-rue 46",
    "sg:city":"Tavannes",
    "sg:orig_category":"Detailhandel mit Radio U Fernsehger\u00e4ten Detailhandel mit elektrischen Haushalts-,Radio U Fernsehger\u00e4",
    "sg:phone":"+41 32 481 27 41",
    "sg:postcode":"2710",
    "sg:province":"Bern",
    "wof:name":"Sonolux Henzi Audiovisuel",
    "wof:placetype":"venue"
},
  "geometry": {"coordinates":[7.2024970055,47.2220115662],"type":"Point"}
}