{
  "type": "Feature",
  "properties": {
    "iso:country":"CH",
    "sg:address":"Hofure 45",
    "sg:city":"Nennigkofen",
    "sg:orig_category":"Herstellung von elektrischen Lampen U Leuchten",
    "sg:postcode":"4574",
    "sg:province":"Solothurn",
    "wof:name":"Target, Jost, Hofmann Und Co",
    "wof:placetype":"venue"
},
  "geometry": {"coordinates":[7.4978179932,47.1844596863],"type":"Point"}
}