{
  "type": "Feature",
  "properties": {
    "iso:country":"CH",
    "sg:address":"Allmendstr. 28",
    "sg:city":"Interlaken",
    "sg:classifiers":[
        {
            "category":"Wholesale",
            "subcategory":"Medical Equipment & Supplies",
            "type":"Manufacturing & Wholesale Goods"
        }
    ],
    "sg:phone":"+41 33 823 28 88",
    "sg:postcode":"3800",
    "sg:province":"Bern",
    "sg:tags":[
        "instrument",
        "health",
        "-",
        "precision"
    ],
    "wof:name":"Servotec Instruments",
    "wof:placetype":"venue"
},
  "geometry": {"coordinates":[7.8694009781,46.6864700317],"type":"Point"}
}