{
  "type": "Feature",
  "properties": {
    "iso:country":"CH",
    "sg:address":"Bernstrasse 23",
    "sg:city":"Flamatt",
    "sg:orig_category":"W\u00e4scherei U chemische Reinigung",
    "sg:postcode":"3175",
    "sg:province":"Fribourg",
    "wof:name":"Sant'elia Martine",
    "wof:placetype":"venue"
},
  "geometry": {"coordinates":[6.1575808525,46.4464187622],"type":"Point"}
}