{
  "type": "Feature",
  "properties": {
    "iso:country":"CH",
    "sg:address":"Sternenfeldstrasse 8 4127 Birsfelden. Postfach",
    "sg:city":"Birsfelden",
    "sg:orig_category":"Architektur U Ingenieurb\u00fcros",
    "sg:postcode":"4127",
    "sg:province":"Basel-Landschaft",
    "wof:name":"Bwf Engineering Ag",
    "wof:placetype":"venue"
},
  "geometry": {"coordinates":[9.63637,47.431011],"type":"Point"}
}