{
  "type": "Feature",
  "properties": {
    "iso:country":"CH",
    "sg:address":"Avenue De La Sallaz 38",
    "sg:city":"Lausanne",
    "sg:orig_category":"Primarschulen",
    "sg:phone":"+41 21 652 17 09",
    "sg:postcode":"1010",
    "sg:province":"Vaud",
    "wof:name":"Ecole Primaire Sallaz",
    "wof:placetype":"venue"
},
  "geometry": {"coordinates":[6.6464657784,46.5320396423],"type":"Point"}
}