{
  "type": "Feature",
  "properties": {
    "iso:country":"CH",
    "sg:address":"Lothringerstrasse 115",
    "sg:city":"Basel",
    "sg:orig_category":"Bauspenglerei Sanit\u00e4rinstallation",
    "sg:phone":"+41 61 322 70 57",
    "sg:postcode":"4056",
    "sg:province":"Basel-Stadt",
    "wof:name":"Handschin Emil Ag Sanit\u00e4r- U. Spenglereigesch\u00e4ft Usw",
    "wof:placetype":"venue"
},
  "geometry": {"coordinates":[7.575458,47.570141],"type":"Point"}
}