{
  "type": "Feature",
  "properties": {
    "iso:country":"CH",
    "sg:address":"Stockstrasse 8",
    "sg:city":"Diepoldsau",
    "sg:orig_category":"Elektroinstallation",
    "sg:phone":"+41 79 696 42 01",
    "sg:postcode":"9444",
    "sg:province":"St. Gallen",
    "wof:name":"Rhv Elektrotechnik Ag Elektr. Anlagen, Ger\u00e4te Usw; Planung, Erstell, Betrieb, Verkauf, Verwaltung",
    "wof:placetype":"venue"
},
  "geometry": {"coordinates":[9.5452308655,47.3796920776],"type":"Point"}
}