{
  "type": "Feature",
  "properties": {
    "iso:country":"CH",
    "sg:address":"Echallens Route D' 1",
    "sg:city":"Romanel-s-lausanne",
    "sg:classifiers":[
        {
            "category":"Travel",
            "subcategory":"Hotels & Motels",
            "type":"Entertainment"
        }
    ],
    "sg:phone":"+41 31 711 30 77",
    "sg:postcode":"1032",
    "sg:province":"Vaud",
    "sg:tags":[
        "hotels",
        "mit",
        "restaurant"
    ],
    "wof:name":"Manfredini & Co",
    "wof:placetype":"venue"
},
  "geometry": {"coordinates":[9.0163011551,45.8542442322],"type":"Point"}
}