{
  "type": "Feature",
  "properties": {
    "iso:country":"CH",
    "sg:address":"Les Petits-ponts",
    "sg:city":"Brot-plamboz",
    "sg:orig_category":"Grosshandel mit Maschinen U Ausr\u00fcstungen",
    "sg:phone":"+41 32 937 11 81",
    "sg:postcode":"2318",
    "sg:province":"Neuch\u00e2tel",
    "wof:name":"Mc Culloch Service",
    "wof:placetype":"venue"
},
  "geometry": {"coordinates":[6.7584028244,46.9950828552],"type":"Point"}
}