{
  "type": "Feature",
  "properties": {
    "iso:country":"CH",
    "sg:address":"Bahnhofstrasse 9",
    "sg:city":"Schlieren",
    "sg:orig_category":"P\u00e9dicure",
    "sg:phone":"+41 17311830",
    "sg:postcode":"8952",
    "sg:province":"Z\u00fcrich",
    "wof:name":"Ursula B\u00fctikofer P\u00e9dicure",
    "wof:placetype":"venue"
},
  "geometry": {"coordinates":[8.4479827881,47.3982505798],"type":"Point"}
}