{
  "type": "Feature",
  "properties": {
    "iso:country":"CH",
    "sg:address":"Blumenbergstrasse 37",
    "sg:city":"Bern",
    "sg:orig_category":"Sonstige Aktivit\u00e4ten der nicht-\u00e4rztlichen Medizinalberufe Unternehmensberatung",
    "sg:phone":"+41 31 332 98 05",
    "sg:postcode":"3013",
    "sg:province":"Bern",
    "wof:name":"Karlen Rudolf U. Co",
    "wof:placetype":"venue"
},
  "geometry": {"coordinates":[7.4556131363,46.9554443359],"type":"Point"}
}