{
  "type": "Feature",
  "properties": {
    "iso:country":"CH",
    "sg:address":"Gewerbestrasse 28 4123 Allschwil. Postfach",
    "sg:city":"Allschwil",
    "sg:orig_category":"Pensionskassen",
    "sg:phone":"+41 71 761 11 67",
    "sg:postcode":"4123",
    "sg:province":"Basel-Landschaft",
    "wof:name":"Personalvorsorgestiftung Der K\u00fchnis Ag",
    "wof:placetype":"venue"
},
  "geometry": {"coordinates":[9.5681495667,47.3142471313],"type":"Point"}
}