{
  "type": "Feature",
  "properties": {
    "iso:country":"CH",
    "sg:address":"Goppisbergeralp",
    "sg:city":"Riederalp",
    "sg:orig_category":"Detailhandel mit Waren verschiedener Art, Hauptrichtung Nahrungsmittel",
    "sg:phone":"+41 27 927 10 55",
    "sg:postcode":"3987",
    "sg:province":"Valais",
    "wof:name":"Armin Bittel Handlung",
    "wof:placetype":"venue"
},
  "geometry": {"coordinates":[8.0325498581,46.3776931763],"type":"Point"}
}