{
  "type": "Feature",
  "properties": {
    "iso:country":"CH",
    "sg:address":"Rheinstr. 142 4410 Liestal. Postfach",
    "sg:city":"Liestal",
    "sg:orig_category":"Pensionskassen",
    "sg:postcode":"4410",
    "sg:province":"Basel-Landschaft",
    "wof:name":"Angestellten-versicherungskasse Der Schild A.g. Tuch Und Deckenfabriken Bern Und Liestal.",
    "wof:placetype":"venue"
},
  "geometry": {"coordinates":[7.7230858803,47.4983482361],"type":"Point"}
}