{
  "type": "Feature",
  "properties": {
    "iso:country":"CH",
    "sg:address":"Marktgasse 15 8302 Kloten. Postfach",
    "sg:city":"Kloten",
    "sg:orig_category":"Sportvereine Eissport Eishockey",
    "sg:phone":"+41 18001010",
    "sg:postcode":"8302",
    "sg:province":"Z\u00fcrich",
    "wof:name":"Eishockey-club Kloten",
    "wof:placetype":"venue"
},
  "geometry": {"coordinates":[8.5839395523,47.4497718811],"type":"Point"}
}