{
  "type": "Feature",
  "properties": {
    "iso:country":"CH",
    "sg:address":"Oberdorf",
    "sg:city":"D\u00fcrrenroth",
    "sg:orig_category":"Herstellung von gewirktem U gestricktem Stoff",
    "sg:phone":"+41 62 964 14 18",
    "sg:postcode":"3465",
    "sg:province":"Bern",
    "wof:name":"Armin Zaugg Strickerei",
    "wof:placetype":"venue"
},
  "geometry": {"coordinates":[7.7925357819,47.0879249573],"type":"Point"}
}