{
  "type": "Feature",
  "properties": {
    "iso:country":"CH",
    "sg:address":"Steingasse 20 4934 Madiswil. Postfach",
    "sg:city":"Madiswil",
    "sg:orig_category":"Herstellung von K\u00fcchenm\u00f6beln Verlegen von Fliesen U Platten",
    "sg:phone":"+41 32 758 73 73",
    "sg:postcode":"4934",
    "sg:province":"Bern",
    "wof:name":"Dubois Mat\u00e9riaux Sa",
    "wof:placetype":"venue"
},
  "geometry": {"coordinates":[7.0295181274,47.0444984436],"type":"Point"}
}