{
  "type": "Feature",
  "properties": {
    "iso:country":"CH",
    "sg:address":"Schl\u00f6sslistrasse 16 A",
    "sg:city":"Ennetbaden",
    "sg:orig_category":"Architektur U Ingenieurb\u00fcros",
    "sg:phone":"+41 56 210 96 66",
    "sg:postcode":"5408",
    "sg:province":"Aargau",
    "wof:name":"Hannes Burkard Architekt Bsa Swb",
    "wof:placetype":"venue"
},
  "geometry": {"coordinates":[8.311839,47.475025],"type":"Point"}
}