{
  "type": "Feature",
  "properties": {
    "iso:country":"CH",
    "sg:address":"Niesenweg 3a",
    "sg:city":"G\u00fcmligen",
    "sg:orig_category":"Sportvereine Ballsport Handball",
    "sg:postcode":"3073",
    "sg:province":"Bern",
    "wof:name":"Hbc Neuch\u00e2tel",
    "wof:placetype":"venue"
},
  "geometry": {"coordinates":[6.9463729858,46.9967689514],"type":"Point"}
}