{
  "type": "Feature",
  "properties": {
    "iso:country":"CH",
    "sg:address":"Rue Centrale 23a 1880 Bex. Postfach",
    "sg:city":"Bex",
    "sg:orig_category":"Versicherungen Hauptagenturen",
    "sg:phone":"+41 24 463 25 04",
    "sg:postcode":"1880",
    "sg:province":"Vaud",
    "wof:name":"Winterthur Assurances Agence Principale",
    "wof:placetype":"venue"
},
  "geometry": {"coordinates":[7.0148839951,46.2511291504],"type":"Point"}
}