{
  "type": "Feature",
  "properties": {
    "iso:country":"CH",
    "sg:address":"Meierhofweg 2 6032 Emmen. Postfach",
    "sg:city":"Emmen",
    "sg:orig_category":"Handel mit Motorr\u00e4dern, Teilen U Zubeh\u00f6r Instandhaltung U Reparatur von Motorr\u00e4dern",
    "sg:phone":"+41 41 260 33 43",
    "sg:postcode":"6032",
    "sg:province":"Luzern",
    "wof:name":"Gloggner Werner 2-rad Fachgesch\u00e4ft",
    "wof:placetype":"venue"
},
  "geometry": {"coordinates":[8.3071203232,47.0820121765],"type":"Point"}
}