{
  "type": "Feature",
  "properties": {
    "iso:country":"CH",
    "sg:address":"Les Brues 15",
    "sg:city":"Corg\u00e9mont",
    "sg:orig_category":"Arztpraxen",
    "sg:phone":"+41 32 489 17 66",
    "sg:postcode":"2606",
    "sg:province":"Bern",
    "wof:name":"Dr M\u00e9d. Ennio Salomoni M\u00e9decin G\u00e9n\u00e9raliste",
    "wof:placetype":"venue"
},
  "geometry": {"coordinates":[7.141333,47.193027],"type":"Point"}
}