{
  "type": "Feature",
  "properties": {
    "iso:country":"CH",
    "sg:address":"6900 Massagno. Postfach Caselle Postale 301",
    "sg:city":"Massagno",
    "sg:orig_category":"Sportvereine Ballsport Basketball",
    "sg:phone":"+41 91 966 51 26",
    "sg:postcode":"6900",
    "sg:province":"Ticino",
    "wof:name":"Sam Basket Massagno",
    "wof:placetype":"venue"
},
  "geometry": {"coordinates":[8.9451303482,46.0130462646],"type":"Point"}
}