{
  "type": "Feature",
  "properties": {
    "addr:full":"Wolfsacker 3 Gams St. Gallen 9473",
    "addr:housenumber":"3;st.",
    "addr:postcode":"9473",
    "addr:street":"Wolfsacker;Gams",
    "iso:country":"CH",
    "sg:address":"Wolfsacker 3",
    "sg:city":"Gams",
    "sg:orig_category":"Allgemeiner Hoch U Tiefbau",
    "sg:postcode":"9473",
    "sg:province":"St. Gallen",
    "wof:name":"Gantenbein L. & Co Ag",
    "wof:placetype":"venue"
},
  "geometry": {"coordinates":[9.432278,47.205429],"type":"Point"}
}