{
  "type": "Feature",
  "properties": {
    "iso:country":"CH",
    "sg:address":"Aargauerstrasse 251",
    "sg:city":"Z\u00fcrich",
    "sg:orig_category":"Bauschreinerei Innenausbau",
    "sg:phone":"+41 12523292",
    "sg:postcode":"8048",
    "sg:province":"Z\u00fcrich",
    "wof:name":"Hobel-genossenschaft",
    "wof:placetype":"venue"
},
  "geometry": {"coordinates":[8.489822,47.392708],"type":"Point"}
}