{
  "type": "Feature",
  "properties": {
    "iso:country":"CH",
    "sg:address":"Obergasse 13",
    "sg:city":"Bischofszell",
    "sg:classifiers":[
        {
            "category":"Restaurant",
            "type":"Food & Drink"
        }
    ],
    "sg:phone":"+41 71 422 15 60",
    "sg:postcode":"9220",
    "sg:province":"Thurgau",
    "wof:name":"Restaurant Sternen Chameleon",
    "wof:placetype":"venue"
},
  "geometry": {"coordinates":[9.2424850464,47.4940757751],"type":"Point"}
}