{
  "type": "Feature",
  "properties": {
    "iso:country":"CH",
    "sg:address":"Via San Gottardo 58e",
    "sg:city":"Bellinzona",
    "sg:orig_category":"Allgemeiner Hoch U Tiefbau",
    "sg:phone":"+41 91 825 51 53",
    "sg:postcode":"6500",
    "sg:province":"Ticino",
    "wof:name":"Muttoni Sa",
    "wof:placetype":"venue"
},
  "geometry": {"coordinates":[9.033408,46.201649],"type":"Point"}
}