{
  "type": "Feature",
  "properties": {
    "iso:country":"CH",
    "sg:address":"B\u00fcrglistrasse 29",
    "sg:city":"Wallisellen",
    "sg:orig_category":"Hardwareberatung",
    "sg:postcode":"8304",
    "sg:province":"Z\u00fcrich",
    "wof:name":"Dalco Electronics Dallmann",
    "wof:placetype":"venue"
},
  "geometry": {"coordinates":[8.5994682312,47.4156532288],"type":"Point"}
}