{
  "type": "Feature",
  "properties": {
    "iso:country":"CH",
    "sg:address":"Rue De La Gare 21",
    "sg:city":"Payerne",
    "sg:classifiers":[
        {
            "category":"Bars & Pubs",
            "type":"Food & Drink"
        }
    ],
    "sg:phone":"+41 26 660 43 95",
    "sg:postcode":"1530",
    "sg:province":"Vaud",
    "wof:name":"Pub Scorpion",
    "wof:placetype":"venue"
},
  "geometry": {"coordinates":[6.938936,46.819534],"type":"Point"}
}