{
  "type": "Feature",
  "properties": {
    "iso:country":"CH",
    "sg:address":"Alte Weissbadstrasse 4",
    "sg:city":"Appenzell",
    "sg:orig_category":"Herstellung von Metallkonstruktionen Sanit\u00e4rinstallation",
    "sg:phone":"+41 71 787 11 21",
    "sg:postcode":"9050",
    "sg:province":"Appenzell Innerhoden",
    "wof:name":"Karl Deutschle Sanit\u00e4re Anlagen & Metallbau",
    "wof:placetype":"venue"
},
  "geometry": {"coordinates":[9.4109649658,47.330078125],"type":"Point"}
}