{
  "type": "Feature",
  "properties": {
    "iso:country":"CH",
    "sg:address":"Unionstrasse 17",
    "sg:city":"Goldach",
    "sg:orig_category":"Zahnarztpraxen",
    "sg:phone":"+41 71 845 30 34",
    "sg:postcode":"9403",
    "sg:province":"St. Gallen",
    "wof:name":"Dentalab Gmbh",
    "wof:placetype":"venue"
},
  "geometry": {"coordinates":[9.463136673,47.4718055725],"type":"Point"}
}