{
  "type": "Feature",
  "properties": {
    "iso:country":"CH",
    "sg:address":"Champs-montants 16b",
    "sg:city":"Marin-centre",
    "sg:orig_category":"Herstellung von Mess U Kontrollinstrumenten U vorrichtungen Herstellung von Uhren",
    "sg:phone":"+41 32 925 95 25",
    "sg:postcode":"2074",
    "sg:province":"Neuch\u00e2tel",
    "wof:name":"Breitling Chronometrie Sa Montres M\u00e9caniques Et \u00e9lectroniques; Fabrication, Achat, Vente",
    "wof:placetype":"venue"
},
  "geometry": {"coordinates":[6.80339,47.08218],"type":"Point"}
}