{
  "type": "Feature",
  "properties": {
    "iso:country":"CH",
    "sg:address":"Place Du Cotterd 5 1122 Romanel-sur-morges. Postfach",
    "sg:city":"Romanel-sur-morges",
    "sg:orig_category":"Verwertung von Milch",
    "sg:postcode":"1122",
    "sg:province":"Vaud",
    "wof:name":"Aeby Marcel, K\u00e4serei",
    "wof:placetype":"venue"
},
  "geometry": {"coordinates":[7.2198591232,46.7409057617],"type":"Point"}
}