{
  "type": "Feature",
  "properties": {
    "iso:country":"CH",
    "sg:address":"Fatio Rue Pierre- 12 1204 Gen\u00e8ve. Postfach",
    "sg:city":"Gen\u00e8ve",
    "sg:orig_category":"Detailhandel mit Metallwaren, Anstrichmitteln, Glaswaren, Bau U Heimwerkerbedarf",
    "sg:phone":"+41 71 777 38 61",
    "sg:postcode":"1204",
    "sg:province":"Gen\u00e8ve",
    "wof:name":"Avs Enz",
    "wof:placetype":"venue"
},
  "geometry": {"coordinates":[9.5742292404,47.3838043213],"type":"Point"}
}