{
  "type": "Feature",
  "properties": {
    "iso:country":"CH",
    "sg:address":"Brauerstrasse 9 8004 Z\u00fcrich. Postfach",
    "sg:city":"Z\u00fcrich",
    "sg:orig_category":"RESTAURANTS: TEA-ROOMS",
    "sg:postcode":"8001",
    "sg:province":"Z\u00fcrich",
    "wof:name":"Ah-hua Gmbh Asiatische Gastronomie- U. Handelsbetriebe",
    "wof:placetype":"venue"
},
  "geometry": {"coordinates":[8.5281896591,47.377040863],"type":"Point"}
}