{
  "type": "Feature",
  "properties": {
    "iso:country":"CH",
    "sg:address":"Chemin Des Carrels 1",
    "sg:city":"Peseux",
    "sg:orig_category":"Detailhandel mit Waren verschiedener Art, Hauptrichtung Nahrungsmittel",
    "sg:phone":"+41 32 731 14 10",
    "sg:postcode":"2034",
    "sg:province":"Neuch\u00e2tel",
    "wof:name":"Coop Neuch\u00e2tel-jura",
    "wof:placetype":"venue"
},
  "geometry": {"coordinates":[6.8979258537,46.9879341125],"type":"Point"}
}