{
  "type": "Feature",
  "properties": {
    "addr:full":"2203 Rochefort 2203",
    "addr:housenumber":"2203",
    "addr:postcode":"2203",
    "addr:street":"Rochefort",
    "iso:country":"CH",
    "sg:address":"2203",
    "sg:city":"Rochefort",
    "sg:orig_category":"Betrieb von Taxis",
    "sg:phone":"+41 32 855 11 61",
    "sg:postcode":"2203",
    "wof:name":"Favre Excursions",
    "wof:placetype":"venue"
},
  "geometry": {"coordinates":[-0.9587,45.934818],"type":"Point"}
}