{
  "type": "Feature",
  "properties": {
    "iso:country":"CH",
    "sg:address":"Via Agostino Maspoli 41",
    "sg:city":"Mendrisio",
    "sg:orig_category":"G\u00fcterbef\u00f6rderung im Strassenverkehr",
    "sg:phone":"+41 55 210 15 76",
    "sg:postcode":"6850",
    "sg:province":"Ticino",
    "wof:name":"Gall Transport Ag",
    "wof:placetype":"venue"
},
  "geometry": {"coordinates":[8.8214540482,47.2258415222],"type":"Point"}
}