{
  "type": "Feature",
  "properties": {
    "iso:country":"CH",
    "sg:address":"Grabenstrasse 36 3600 Thun. Postfach 223",
    "sg:city":"Thun",
    "sg:orig_category":"Personenbef\u00f6rderung im Linienverkehr zu Land Personenbef\u00f6rderung im Nahverkehr",
    "sg:phone":"+41 33 225 13 13",
    "sg:postcode":"3605",
    "wof:name":"Verkehrsbetriebe Sti",
    "wof:placetype":"venue"
},
  "geometry": {"coordinates":[7.6245250702,46.7621688843],"type":"Point"}
}