{
  "type": "Feature",
  "properties": {
    "iso:country":"CH",
    "sg:address":"Carl-sprecher-strasse 11",
    "sg:city":"Oberentfelden",
    "sg:orig_category":"Bauschreinerei Zimmerei",
    "sg:phone":"+41 56 616 72 40",
    "sg:postcode":"5036",
    "sg:province":"Aargau",
    "wof:name":"Ad. Sch\u00e4fer & Cie Ag Schreinerei & Zimmerei",
    "wof:placetype":"venue"
},
  "geometry": {"coordinates":[8.056823,47.357113],"type":"Point"}
}