{
  "type": "Feature",
  "properties": {
    "addr:full":"Sottobisio Via 12 Balerna Ticino 6828",
    "addr:postcode":"6828",
    "addr:street":"Via 12",
    "iso:country":"CH",
    "sg:address":"Sottobisio Via 12",
    "sg:city":"Balerna",
    "sg:orig_category":"Architektur U Ingenieurb\u00fcros",
    "sg:postcode":"6828",
    "sg:province":"Ticino",
    "wof:name":"Sacir Sa",
    "wof:placetype":"venue"
},
  "geometry": {"coordinates":[9.007987,45.843185],"type":"Point"}
}