{
  "type": "Feature",
  "properties": {
    "iso:country":"CH",
    "sg:address":"Hauptstrasse 38 4144 Arlesheim. Postfach 622",
    "sg:city":"Arlesheim",
    "sg:orig_category":"Detailhandel mit M\u00f6beln Innendekorationsateliers",
    "sg:phone":"+41 61 701 13 87",
    "sg:postcode":"4144",
    "sg:province":"Basel-Landschaft",
    "wof:name":"Pinocchio Wohnbedarf M\u00f6bel & Einrahmungen",
    "wof:placetype":"venue"
},
  "geometry": {"coordinates":[7.6207890511,47.4939842224],"type":"Point"}
}