{
  "type": "Feature",
  "properties": {
    "iso:country":"CH",
    "sg:address":"H\u00e4gglingerstrasse 27",
    "sg:city":"Wohlenschwil",
    "sg:orig_category":"Instandhaltung U Reparatur von Automobilen R\u00fcckgewinnung U Vorbereitung f\u00fcr die Wiederverwertung Rec",
    "sg:phone":"+41 56 481 85 85",
    "sg:postcode":"5512",
    "sg:province":"Aargau",
    "wof:name":"Fab Auto Ag",
    "wof:placetype":"venue"
},
  "geometry": {"coordinates":[8.2602720261,47.4066314697],"type":"Point"}
}