{
  "type": "Feature",
  "properties": {
    "iso:country":"CH",
    "sg:address":"Obernauerstrasse 26",
    "sg:city":"Kriens",
    "sg:orig_category":"Elektroinstallation",
    "sg:phone":"+41 41 320 71 71",
    "sg:postcode":"6010",
    "sg:province":"Luzern",
    "wof:name":"Wasmer Engineering &",
    "wof:placetype":"venue"
},
  "geometry": {"coordinates":[8.2716426849,47.0341148376],"type":"Point"}
}