{
  "type": "Feature",
  "properties": {
    "iso:country":"CH",
    "sg:address":"Bahnhofstrasse 10",
    "sg:city":"K\u00fcsnacht",
    "sg:orig_category":"Foot-Powered Scooters",
    "sg:phone":"+41 19101122",
    "sg:postcode":"8700",
    "sg:province":"Z\u00fcrich",
    "wof:name":"Gebr\u00fcder Ouboter Ag",
    "wof:placetype":"venue"
},
  "geometry": {"coordinates":[8.580905,47.317936],"type":"Point"}
}