{
  "type": "Feature",
  "properties": {
    "iso:country":"CH",
    "sg:address":"Aargauerstrasse 250",
    "sg:city":"Z\u00fcrich",
    "sg:orig_category":"Handel mit Automobilen",
    "sg:phone":"+41 56 621 22 02",
    "sg:postcode":"8048",
    "sg:province":"Z\u00fcrich",
    "wof:name":"Garage Widmer Ren\u00e9 Gmbh",
    "wof:placetype":"venue"
},
  "geometry": {"coordinates":[8.2796936035,47.3533782959],"type":"Point"}
}