{
  "type": "Feature",
  "properties": {
    "iso:country":"CH",
    "sg:address":"Schwarzenburgstrasse 805 3145 Niederscherli. Postfach",
    "sg:city":"Niederscherli",
    "sg:orig_category":"Schreib U \u00dcbersetzungsb\u00fcros",
    "sg:postcode":"3145",
    "sg:province":"Bern",
    "wof:name":"Eml Office Service, Lechner",
    "wof:placetype":"venue"
},
  "geometry": {"coordinates":[7.38875103,46.8850250244],"type":"Point"}
}