{
  "type": "Feature",
  "properties": {
    "iso:country":"CH",
    "sg:address":"Sonnhaldenstrasse 4",
    "sg:city":"Bachenb\u00fclach",
    "sg:orig_category":"Sonstige Kurierdienste",
    "sg:phone":"+41 18611370",
    "sg:postcode":"8184",
    "sg:province":"Z\u00fcrich",
    "wof:name":"Albert Tschumi Alby's Warentaxi",
    "wof:placetype":"venue"
},
  "geometry": {"coordinates":[8.5511493683,47.5034065247],"type":"Point"}
}