{
  "type": "Feature",
  "properties": {
    "iso:country":"CH",
    "sg:address":"Rainweg 16",
    "sg:city":"Urdorf",
    "sg:orig_category":"Unclassifiable Establishments",
    "sg:postcode":"8902",
    "sg:province":"Z\u00fcrich",
    "wof:name":"Rieser Dienstleistungen",
    "wof:placetype":"venue"
},
  "geometry": {"coordinates":[8.4289941788,47.388420105],"type":"Point"}
}