{
  "type": "Feature",
  "properties": {
    "iso:country":"CH",
    "sg:address":"Neuwiesenstrasse 18",
    "sg:city":"Winterthur",
    "sg:orig_category":"Interessenvertretungen",
    "sg:postcode":"8400",
    "sg:province":"Z\u00fcrich",
    "wof:name":"Verein F\u00fcr Music & Performance",
    "wof:placetype":"venue"
},
  "geometry": {"coordinates":[8.721154213,47.502040863],"type":"Point"}
}