{
  "type": "Feature",
  "properties": {
    "iso:country":"CH",
    "sg:address":"Schulstrasse 15",
    "sg:city":"Sch\u00fcpfen",
    "sg:orig_category":"Primarschulen",
    "sg:phone":"+41 31 879 04 74",
    "sg:postcode":"3054",
    "sg:province":"Bern",
    "wof:name":"Primarschule",
    "wof:placetype":"venue"
},
  "geometry": {"coordinates":[7.3788328171,47.0376167297],"type":"Point"}
}