{
  "type": "Feature",
  "properties": {
    "iso:country":"CH",
    "sg:address":"En Bovery C",
    "sg:city":"Collombey",
    "sg:classifiers":[
        {
            "category":"Wholesale",
            "subcategory":"Machinery & Supplies",
            "type":"Manufacturing & Wholesale Goods"
        }
    ],
    "sg:phone":"+41 24 475 73 80",
    "sg:postcode":"1868",
    "sg:province":"Valais",
    "sg:tags":[
        "agricultural",
        "equipment"
    ],
    "wof:name":"Landi Fenaco Bas-valais",
    "wof:placetype":"venue"
},
  "geometry": {"coordinates":[6.945828,46.270473],"type":"Point"}
}