{
  "type": "Feature",
  "properties": {
    "iso:country":"CH",
    "sg:address":"Via Pizzo Di Claro 31",
    "sg:city":"Bellinzona",
    "sg:orig_category":"RESTAURANTS: TEA-ROOMS",
    "sg:phone":"+41 91 825 21 66",
    "sg:postcode":"6500",
    "sg:province":"Ticino",
    "wof:name":"Osteria Della Bett",
    "wof:placetype":"venue"
},
  "geometry": {"coordinates":[9.0244932175,46.2040710449],"type":"Point"}
}