{
  "type": "Feature",
  "properties": {
    "iso:country":"CH",
    "sg:address":"Obere Bahnhofstrasse 15 3920 Zermatt. Postfach",
    "sg:city":"Zermatt",
    "sg:orig_category":"Fachdetailhandel in Verkaufsr\u00e4umen",
    "sg:postcode":"3920",
    "sg:province":"Valais",
    "wof:name":"\u00abtom Tailor\u00bb Shop, Aufdenblatten Elias Boutique Mit Sportswearartikeln, Accessoires Etc",
    "wof:placetype":"venue"
},
  "geometry": {"coordinates":[7.7474689484,46.0223731995],"type":"Point"}
}