{
  "type": "Feature",
  "properties": {
    "iso:country":"CH",
    "sg:address":"Tobelhofstrasse 227 8044 Z\u00fcrich. Postfach",
    "sg:city":"Z\u00fcrich",
    "sg:orig_category":"Detailhandel mit elektrischen Haushalts-,Radio U Fernsehger\u00e4ten sowie Musikinstrumenten",
    "sg:phone":"+41 32 751 50 41",
    "sg:postcode":"8044",
    "sg:province":"Z\u00fcrich",
    "wof:name":"West Cleaning Laurence B\u00fcrki",
    "wof:placetype":"venue"
},
  "geometry": {"coordinates":[7.0914978981,47.063331604],"type":"Point"}
}