{
  "type": "Feature",
  "properties": {
    "addr:full":"Tscharnerstrasse 12 Bern Bern 3007",
    "addr:housenumber":"12",
    "addr:postcode":"3007",
    "addr:street":"Tscharnerstrasse",
    "iso:country":"CH",
    "sg:address":"Tscharnerstrasse 12",
    "sg:city":"Bern",
    "sg:classifiers":[
        {
            "category":"Building & Trades",
            "subcategory":"Cleaning & Sanitation",
            "type":"Services"
        }
    ],
    "sg:phone":"+41 31 352 26 86",
    "sg:postcode":"3007",
    "sg:province":"Bern",
    "sg:tags":[
        "escalator"
    ],
    "wof:name":"Fb Nice & Clean Gmbh",
    "wof:placetype":"venue"
},
  "geometry": {"coordinates":[7.429216,46.941349],"type":"Point"}
}