{
  "type": "Feature",
  "properties": {
    "iso:country":"CH",
    "sg:address":"Pilgerweg 27",
    "sg:city":"R\u00fcschlikon",
    "sg:orig_category":"Primarschulen",
    "sg:phone":"+41 17046010",
    "sg:postcode":"8803",
    "sg:province":"Z\u00fcrich",
    "wof:name":"Primarschule Dorf",
    "wof:placetype":"venue"
},
  "geometry": {"coordinates":[8.5553646088,47.30834198],"type":"Point"}
}