{
  "type": "Feature",
  "properties": {
    "iso:country":"CH",
    "sg:address":"Rue De La Coop\u00e9rative 6",
    "sg:city":"Lucens",
    "sg:orig_category":"Schmieden",
    "sg:phone":"+41 21 906 81 63",
    "sg:postcode":"1522",
    "sg:province":"Vaud",
    "wof:name":"Georges Th\u00e9venaz Mar\u00e9chalerie",
    "wof:placetype":"venue"
},
  "geometry": {"coordinates":[6.8409948349,46.7085723877],"type":"Point"}
}