{
  "type": "Feature",
  "properties": {
    "iso:country":"CH",
    "sg:address":"3904",
    "sg:city":"Naters",
    "sg:orig_category":"Bezirks, Sekundar, Realschulen, Oberstufe der Primarschulen",
    "sg:postcode":"3904",
    "sg:province":"Valais",
    "wof:name":"Sekundarschule",
    "wof:placetype":"venue"
},
  "geometry": {"coordinates":[7.989984,46.323429],"type":"Point"}
}