{
  "type": "Feature",
  "properties": {
    "addr:full":"Stauffacherstr. 16. 8000 Z\u00fcrich. Postfach Z\u00fcrich Z\u00fcrich 8004",
    "addr:housenumber":"16",
    "addr:postcode":"8000 zuerich. postfach;8004",
    "addr:street":"Stauffacherstr.",
    "iso:country":"CH",
    "sg:address":"Stauffacherstr. 16. 8000 Z\u00fcrich. Postfach",
    "sg:city":"Z\u00fcrich",
    "sg:orig_category":"Detailhandel mit Bekleidung",
    "sg:postcode":"8004",
    "sg:province":"Z\u00fcrich",
    "wof:name":"Boutique Naturel, Spotti Rosmarie",
    "wof:placetype":"venue"
},
  "geometry": {"coordinates":[8.529628,47.372391],"type":"Point"}
}