{
  "type": "Feature",
  "properties": {
    "iso:country":"CH",
    "sg:address":"L\u00e4ngackerstrasse 1",
    "sg:city":"Obergerlafingen",
    "sg:orig_category":"Detailhandel mit Geschenkartikeln U Souvenirs",
    "sg:phone":"+41 32 675 45 40",
    "sg:postcode":"4564",
    "sg:province":"Bern",
    "wof:name":"Boutique Marianne",
    "wof:placetype":"venue"
},
  "geometry": {"coordinates":[7.579843998,47.1635894775],"type":"Point"}
}