{
  "type": "Feature",
  "properties": {
    "iso:country":"CH",
    "sg:address":"Reinacherstrasse 101 4053 Basel. Postfach",
    "sg:city":"Basel",
    "sg:orig_category":"Herstellung von sonstigen elektrischen Ausr\u00fcstungen",
    "sg:postcode":"4051",
    "sg:province":"Basel-Stadt",
    "wof:name":"Electronics Service 97 Sagl",
    "wof:placetype":"venue"
},
  "geometry": {"coordinates":[9.0158262253,45.8467254639],"type":"Point"}
}