{
  "type": "Feature",
  "properties": {
    "iso:country":"CH",
    "sg:address":"Rickenstrasse 13",
    "sg:city":"Kaltbrunn",
    "sg:orig_category":"Bauschreinerei Herstellung von M\u00f6beln verschiedener Art",
    "sg:phone":"+41 55 283 16 91",
    "sg:postcode":"8722",
    "sg:province":"St. Gallen",
    "wof:name":"Romer Roland",
    "wof:placetype":"venue"
},
  "geometry": {"coordinates":[9.026865,47.216045],"type":"Point"}
}