{
  "type": "Feature",
  "properties": {
    "iso:country":"CH",
    "sg:address":"Staatsstrasse 138 3626 H\u00fcnibach. Postfach",
    "sg:city":"H\u00fcnibach",
    "sg:orig_category":"Drogerien",
    "sg:phone":"+41 33 243 43 78",
    "sg:postcode":"3626",
    "sg:province":"Bern",
    "wof:name":"Drogerie Chartreuse Stefan Von Arx",
    "wof:placetype":"venue"
},
  "geometry": {"coordinates":[7.6447591782,46.7454528809],"type":"Point"}
}