{
  "type": "Feature",
  "properties": {
    "iso:country":"CH",
    "sg:address":"Kantonsstrasse.",
    "sg:city":"Sch\u00fcbelbach",
    "sg:orig_category":"Herstellung von Sitzm\u00f6beln",
    "sg:phone":"+41 55 440 26 86",
    "sg:postcode":"8862",
    "sg:province":"Schwyz",
    "wof:name":"Landheer Gody.",
    "wof:placetype":"venue"
},
  "geometry": {"coordinates":[8.9304103851,47.1734237671],"type":"Point"}
}