{
  "type": "Feature",
  "properties": {
    "addr:full":"M\u00fcllerstrasse 9 2562 Port. Postfach Port Bern 2562",
    "addr:housenumber":"9",
    "addr:postcode":"2562;2562",
    "addr:street":"Muellerstrasse",
    "iso:country":"CH",
    "sg:address":"M\u00fcllerstrasse 9 2562 Port. Postfach",
    "sg:city":"Port",
    "sg:orig_category":"Allgemeiner Hoch U Tiefbau",
    "sg:postcode":"2562",
    "sg:province":"Bern",
    "wof:name":"Thermasteel Gmbh",
    "wof:placetype":"venue"
},
  "geometry": {"coordinates":[7.259149,47.115639],"type":"Point"}
}