{
  "type": "Feature",
  "properties": {
    "iso:country":"CH",
    "sg:address":"Gerbeweg 33",
    "sg:city":"M\u00e4nnedorf",
    "sg:orig_category":"Werbegrafikateliers",
    "sg:phone":"+41 19202881",
    "sg:postcode":"8708",
    "sg:province":"Z\u00fcrich",
    "wof:name":"Peter Hepp Grafik",
    "wof:placetype":"venue"
},
  "geometry": {"coordinates":[8.6859073639,47.2589454651],"type":"Point"}
}