{
  "type": "Feature",
  "properties": {
    "addr:full":"Seestrasse 355 Z\u00fcrich Z\u00fcrich 8038",
    "addr:housenumber":"355",
    "addr:postcode":"8038",
    "addr:street":"Seestrasse",
    "iso:country":"CH",
    "sg:address":"Seestrasse 355",
    "sg:city":"Z\u00fcrich",
    "sg:classifiers":[
        {
            "category":"Banks & Credit Unions",
            "subcategory":"Investment Brokerage",
            "type":"Services"
        }
    ],
    "sg:phone":"+41 14824443",
    "sg:postcode":"8038",
    "sg:province":"Z\u00fcrich",
    "sg:tags":[
        "ceiling",
        "covering"
    ],
    "wof:name":"Isolag Ag",
    "wof:placetype":"venue"
},
  "geometry": {"coordinates":[8.533423,47.345963],"type":"Point"}
}