{
  "type": "Feature",
  "properties": {
    "iso:country":"CH",
    "sg:address":"Im Tobel 6330 Cham. Postfach",
    "sg:city":"Hagendorn",
    "sg:orig_category":"Reinigungsgewerbe",
    "sg:phone":"+41 41 781 15 65",
    "sg:postcode":"6332",
    "sg:province":"Zug",
    "wof:name":"Hwd Hauswartdienst, Leuthold & Co.",
    "wof:placetype":"venue"
},
  "geometry": {"coordinates":[8.4372491837,47.2032318115],"type":"Point"}
}