{
  "type": "Feature",
  "properties": {
    "iso:country":"CH",
    "sg:address":"Ringstrasse 39",
    "sg:city":"Therwil",
    "sg:orig_category":"Grosshandel mit Datenverarbeitungsger\u00e4ten Grosshandel mit Software",
    "sg:phone":"+41 61 726 97 47",
    "sg:postcode":"4106",
    "sg:province":"Basel-Landschaft",
    "wof:name":"D-concept Gmbh",
    "wof:placetype":"venue"
},
  "geometry": {"coordinates":[7.5528659821,47.5050086975],"type":"Point"}
}