{
  "type": "Feature",
  "properties": {
    "iso:country":"CH",
    "sg:address":"Chemin Des Chambrettes 1",
    "sg:city":"Tolochenaz",
    "sg:orig_category":"Herstellung von Metallkonstruktionen",
    "sg:phone":"+41 21 802 34 47",
    "sg:postcode":"1131",
    "sg:province":"Vaud",
    "wof:name":"Rodolphe Zimmerli Sa Constructions M\u00e9talliques",
    "wof:placetype":"venue"
},
  "geometry": {"coordinates":[6.4735569954,46.4989700317],"type":"Point"}
}