{
  "type": "Feature",
  "properties": {
    "iso:country":"CH",
    "sg:address":"Gewerbestrasse 10",
    "sg:city":"Muhen",
    "sg:classifiers":[
        {
            "category":"Building & Trades",
            "subcategory":"Construction",
            "type":"Services"
        }
    ],
    "sg:phone":"+41 62 737 10 90",
    "sg:postcode":"5037",
    "sg:province":"Aargau",
    "sg:tags":[
        "screw",
        "ball"
    ],
    "wof:name":"Whg Antriebstechnik Ag",
    "wof:placetype":"venue"
},
  "geometry": {"coordinates":[8.051202,47.345356],"type":"Point"}
}