{
  "type": "Feature",
  "properties": {
    "iso:country":"CH",
    "sg:address":"Hobielstrasse 16",
    "sg:city":"Kerns",
    "sg:orig_category":"Herstellung von konfektionierten Textilwaren ohne Bekleidung",
    "sg:phone":"+41 41 660 20 88",
    "sg:postcode":"6064",
    "sg:province":"Obwalden",
    "wof:name":"Hans Aufdermauer Storenbau",
    "wof:placetype":"venue"
},
  "geometry": {"coordinates":[8.2700271606,46.9019584656],"type":"Point"}
}