{
  "type": "Feature",
  "properties": {
    "iso:country":"CH",
    "sg:address":"Windegg 2",
    "sg:city":"Herisau",
    "sg:orig_category":"Verarbeitung von Milch Verwertung von Milch",
    "sg:phone":"+41 71 351 18 47",
    "sg:postcode":"9100",
    "sg:province":"Appenzell Ausserrhoden",
    "wof:name":"Molkerei Forster Ag",
    "wof:placetype":"venue"
},
  "geometry": {"coordinates":[9.2787399292,47.3859405518],"type":"Point"}
}