{
  "type": "Feature",
  "properties": {
    "iso:country":"CH",
    "sg:address":"Im Tiergarten 50",
    "sg:city":"Z\u00fcrich",
    "sg:orig_category":"RESTAURANTS: TEA-ROOMS",
    "sg:postcode":"8055",
    "sg:province":"Z\u00fcrich",
    "wof:name":"Linde Wald Gmbh",
    "wof:placetype":"venue"
},
  "geometry": {"coordinates":[9.4951705933,47.4179801941],"type":"Point"}
}