{
  "type": "Feature",
  "properties": {
    "addr:full":"Andlauerstrasse 10 Muttenz Basel-Landschaft 4132",
    "addr:housenumber":"10",
    "addr:postcode":"4132",
    "addr:street":"Andlauerstrasse",
    "iso:country":"CH",
    "sg:address":"Andlauerstrasse 10",
    "sg:city":"Muttenz",
    "sg:orig_category":"Datenverarbeitungsdienste Softwareentwicklung U beratung",
    "sg:phone":"+41 61 461 49 78",
    "sg:postcode":"4132",
    "sg:province":"Basel-Landschaft",
    "wof:name":"Ag F.techn.informatik Meystre Edv-beratung",
    "wof:placetype":"venue"
},
  "geometry": {"coordinates":[7.64143,47.52702],"type":"Point"}
}