{
  "type": "Feature",
  "properties": {
    "iso:country":"CH",
    "sg:address":"Sch\u00fcrli 108",
    "sg:city":"Biglen",
    "sg:orig_category":"Dachdeckerei Zimmerei, Dachdeckerei, Bauspenglerei U Abdichtung",
    "sg:phone":"+41 31 701 16 35",
    "sg:postcode":"3507",
    "sg:province":"Bern",
    "wof:name":"Joss Ag",
    "wof:placetype":"venue"
},
  "geometry": {"coordinates":[7.629738,46.924862],"type":"Point"}
}