{
  "type": "Feature",
  "properties": {
    "iso:country":"CH",
    "sg:address":"4419",
    "sg:city":"Lupsingen",
    "sg:orig_category":"Sportvereine Turnen",
    "sg:postcode":"4419",
    "sg:province":"Basel-Landschaft",
    "wof:name":"Turnverein",
    "wof:placetype":"venue"
},
  "geometry": {"coordinates":[7.6995601654,47.4422492981],"type":"Point"}
}