{
  "type": "Feature",
  "properties": {
    "iso:country":"CH",
    "sg:address":"Hauptstrasse 61",
    "sg:city":"Magden",
    "sg:orig_category":"Einzelhandel mit Automobilteilen U Zubeh\u00f6r",
    "sg:phone":"+41 61 841 15 75",
    "sg:postcode":"4312",
    "sg:province":"Aargau",
    "wof:name":"Anton Frank Pneuhaus",
    "wof:placetype":"venue"
},
  "geometry": {"coordinates":[7.8084998131,47.5303192139],"type":"Point"}
}