{
  "type": "Feature",
  "properties": {
    "iso:country":"CH",
    "sg:address":"Dorfstrasse 17",
    "sg:city":"Gersau",
    "sg:orig_category":"Detailhandel mit fotografischen Artikeln Drogerien",
    "sg:phone":"+41 55 442 13 60",
    "sg:postcode":"6442",
    "sg:province":"Schwyz",
    "wof:name":"Drogerie Dobler Peter",
    "wof:placetype":"venue"
},
  "geometry": {"coordinates":[8.8511390686,47.1913757324],"type":"Point"}
}