{
  "type": "Feature",
  "properties": {
    "addr:full":"Aarbergergasse 5 Bern Bern 3011",
    "addr:housenumber":"5",
    "addr:postcode":"3011",
    "addr:street":"Aarbergergasse",
    "iso:country":"CH",
    "sg:address":"Aarbergergasse 5",
    "sg:city":"Bern",
    "sg:orig_category":"Detailhandel mit Computern U Software",
    "sg:phone":"+41 31 311 02 63",
    "sg:postcode":"3011",
    "sg:province":"Bern",
    "wof:name":"Interdiscount Ag Hi-fi Video Photo Radio",
    "wof:placetype":"venue"
},
  "geometry": {"coordinates":[7.443406,46.949337],"type":"Point"}
}