{
  "type": "Feature",
  "properties": {
    "iso:country":"CH",
    "sg:address":"Piazza San Silvestro",
    "sg:city":"Montagnola",
    "sg:classifiers":[
        {
            "category":"Military Area",
            "subcategory":"Air Force Base",
            "type":"Public Place"
        }
    ],
    "sg:phone":"+41 91 994 44 15",
    "sg:postcode":"6926",
    "sg:province":"Ticino",
    "sg:tags":[
        "equipment",
        "imaging",
        "x-ray",
        "digital"
    ],
    "wof:name":"Meditrend Sa",
    "wof:placetype":"venue"
},
  "geometry": {"coordinates":[8.9093799591,45.977268219],"type":"Point"}
}