{
  "type": "Feature",
  "properties": {
    "iso:country":"CH",
    "sg:address":"Schwarzlandstrasse 1",
    "sg:city":"Amriswil",
    "sg:orig_category":"Dachdeckerei Zimmerei, Dachdeckerei, Bauspenglerei U Abdichtung",
    "sg:phone":"+41 71 411 16 54",
    "sg:postcode":"8580",
    "sg:province":"Thurgau",
    "wof:name":"Weber Bedachungen",
    "wof:placetype":"venue"
},
  "geometry": {"coordinates":[9.292312,47.558029],"type":"Point"}
}