{
  "type": "Feature",
  "properties": {
    "iso:country":"CH",
    "sg:address":"Grundstrasse 24",
    "sg:city":"Rorbas",
    "sg:orig_category":"G\u00fcterbef\u00f6rderung im Strassenverkehr",
    "sg:phone":"+41 81 416 31 49",
    "sg:postcode":"8427",
    "sg:province":"Z\u00fcrich",
    "wof:name":"Wolfgang Kessler Transporte",
    "wof:placetype":"venue"
},
  "geometry": {"coordinates":[9.8537597656,46.8327331543],"type":"Point"}
}