{
  "type": "Feature",
  "properties": {
    "iso:country":"CH",
    "sg:address":"Chesa Funtauna",
    "sg:city":"Filisur",
    "sg:orig_category":"Architekturb\u00fcros",
    "sg:phone":"+41 19324731",
    "sg:postcode":"7477",
    "sg:province":"Graubunden",
    "wof:name":"Georg Brenner Architekturb\u00fcro",
    "wof:placetype":"venue"
},
  "geometry": {"coordinates":[8.785866,47.332962],"type":"Point"}
}