{
  "type": "Feature",
  "properties": {
    "iso:country":"CH",
    "sg:address":"Am Bach 3",
    "sg:city":"Obermumpf",
    "sg:orig_category":"G\u00fcterbef\u00f6rderung im Strassenverkehr",
    "sg:phone":"+41 32 931 31 65",
    "sg:postcode":"4324",
    "sg:province":"Aargau",
    "wof:name":"Transinox Sa",
    "wof:placetype":"venue"
},
  "geometry": {"coordinates":[6.8173551559,47.0506782532],"type":"Point"}
}