{
  "type": "Feature",
  "properties": {
    "iso:country":"CH",
    "sg:address":"T\u00f6sstalstrasse 14a",
    "sg:city":"Wallenwil",
    "sg:orig_category":"Sonstiger spezialisierter Hoch U Tiefbau",
    "sg:postcode":"8360",
    "sg:province":"Thurgau",
    "wof:name":"Subasic - Sprinkleranlagen - Montagen Gmbh",
    "wof:placetype":"venue"
},
  "geometry": {"coordinates":[8.9522886276,47.4605522156],"type":"Point"}
}