{
  "type": "Feature",
  "properties": {
    "iso:country":"CH",
    "sg:address":"Route Du Platy 2",
    "sg:city":"Villars-sur-gl\u00e2ne",
    "sg:orig_category":"Fachdetailhandel in Verkaufsr\u00e4umen",
    "sg:postcode":"1752",
    "sg:province":"Fribourg",
    "wof:name":"Christmas Colin Holdings",
    "wof:placetype":"venue"
},
  "geometry": {"coordinates":[7.137357235,46.7903137207],"type":"Point"}
}