{
  "type": "Feature",
  "properties": {
    "iso:country":"CH",
    "sg:address":"Voirons Chemin Des 3",
    "sg:city":"Coppet",
    "sg:orig_category":"Erwachsenenbildung U Unterricht",
    "sg:postcode":"1296",
    "sg:province":"Vaud",
    "wof:name":"Mann George",
    "wof:placetype":"venue"
},
  "geometry": {"coordinates":[6.1932439804,46.3162384033],"type":"Point"}
}