{
  "type": "Feature",
  "properties": {
    "iso:country":"CH",
    "sg:address":"B\u00fchl",
    "sg:city":"Nottwil",
    "sg:orig_category":"Detailhandel mit Waren verschiedener Art, Hauptrichtung Nahrungsmittel",
    "sg:phone":"+41 41 937 11 85",
    "sg:postcode":"6207",
    "sg:province":"Luzern",
    "wof:name":"Anna Egli Handlung",
    "wof:placetype":"venue"
},
  "geometry": {"coordinates":[8.1312055588,47.1358146667],"type":"Point"}
}