{
  "type": "Feature",
  "properties": {
    "iso:country":"CH",
    "sg:address":"Im Obmann 68",
    "sg:city":"Thalheim",
    "sg:orig_category":"Allgemeiner Hoch U Tiefbau Allgemeiner Hochbau",
    "sg:phone":"+41 52 336 16 94",
    "sg:postcode":"8478",
    "sg:province":"Z\u00fcrich",
    "wof:name":"Reinle Und Wettstein Ag",
    "wof:placetype":"venue"
},
  "geometry": {"coordinates":[8.75465,47.57811],"type":"Point"}
}