{
  "type": "Feature",
  "properties": {
    "iso:country":"CH",
    "sg:address":"M\u00fchlackerweg 5",
    "sg:city":"Altst\u00e4tten",
    "sg:classifiers":[
        {
            "category":"Organizations",
            "subcategory":"Labor Organization",
            "type":"Services"
        }
    ],
    "sg:phone":"+41 71 755 12 33",
    "sg:postcode":"9450",
    "sg:province":"St. Gallen",
    "sg:tags":[
        "work",
        "assembling",
        "assembly",
        "contract"
    ],
    "wof:name":"Arge Integral",
    "wof:placetype":"venue"
},
  "geometry": {"coordinates":[9.536959,47.377724],"type":"Point"}
}