{
  "type": "Feature",
  "properties": {
    "iso:country":"CH",
    "sg:address":"Bernstrasse 19",
    "sg:city":"B\u00fctzberg",
    "sg:orig_category":"Detailhandel mit Geschenkartikeln U Souvenirs",
    "sg:phone":"+41 62 963 02 20",
    "sg:postcode":"4922",
    "sg:province":"Bern",
    "wof:name":"Cornelia Walther Boutique Atlantis",
    "wof:placetype":"venue"
},
  "geometry": {"coordinates":[7.7456469536,47.2154197693],"type":"Point"}
}