{
  "type": "Feature",
  "properties": {
    "iso:country":"CH",
    "sg:address":"Erlenweg 489",
    "sg:city":"H\u00e4rkingen",
    "sg:orig_category":"Kauf U Verkauf von Immobilien auf eigene Rechnung",
    "sg:phone":"+41 62 398 18 65",
    "sg:postcode":"4624",
    "sg:province":"Solothurn",
    "wof:name":"Steiner Sebastian Gmbh",
    "wof:placetype":"venue"
},
  "geometry": {"coordinates":[7.8136501312,47.3024482727],"type":"Point"}
}