{
  "type": "Feature",
  "properties": {
    "iso:country":"CH",
    "sg:address":"Ile Falcon Rue De L' 9",
    "sg:city":"Sierre",
    "sg:orig_category":"Instandhaltung U Reparatur von Automobilen",
    "sg:phone":"+41 27 455 24 24",
    "sg:postcode":"3960",
    "sg:province":"Valais",
    "wof:name":"Fournier Willy Garage Et Carrosserie",
    "wof:placetype":"venue"
},
  "geometry": {"coordinates":[7.4553070068,46.2585716248],"type":"Point"}
}