{
  "type": "Feature",
  "properties": {
    "iso:country":"CH",
    "sg:address":"Chemin De La B\u00e2tie 1",
    "sg:city":"Petit-lancy",
    "sg:orig_category":"Sportvereine Eissport Eishockey",
    "sg:postcode":"1213",
    "sg:province":"Gen\u00e8ve",
    "wof:name":"Hockey-club Defi",
    "wof:placetype":"venue"
},
  "geometry": {"coordinates":[6.1213288307,46.1963233948],"type":"Point"}
}