{
  "type": "Feature",
  "properties": {
    "iso:country":"CH",
    "sg:address":"Bahnhofstrasse 3",
    "sg:city":"Rodersdorf",
    "sg:orig_category":"Detailhandel mit Waren verschiedener Art, Hauptrichtung Nahrungsmittel",
    "sg:phone":"+41 61 731 26 54",
    "sg:postcode":"4118",
    "sg:province":"Solothurn",
    "wof:name":"Der Laden Lebensmittel",
    "wof:placetype":"venue"
},
  "geometry": {"coordinates":[7.4570679665,47.4804573059],"type":"Point"}
}