{
  "type": "Feature",
  "properties": {
    "iso:country":"CH",
    "sg:address":"Ebnaterstrasse 147",
    "sg:city":"Ulisbach",
    "sg:classifiers":[
        {
            "category":"Shopping",
            "subcategory":"Comic Books",
            "type":"Retail Goods"
        }
    ],
    "sg:phone":"+41 71 988 19 17",
    "sg:postcode":"9631",
    "sg:province":"St. Gallen",
    "sg:tags":[
        "exercise"
    ],
    "wof:name":"Biwa Schulbedarf Ag",
    "wof:placetype":"venue"
},
  "geometry": {"coordinates":[9.1010704041,47.2875595093],"type":"Point"}
}