{
  "type": "Feature",
  "properties": {
    "iso:country":"CH",
    "sg:address":"Zugerstrasse 5 6330 Cham. Postfach 500",
    "sg:city":"Cham",
    "sg:orig_category":"Handelsvermittlung U Grosshandel",
    "sg:phone":"+41 41 780 50 55",
    "sg:postcode":"6330",
    "sg:province":"Zug",
    "wof:name":"Doba-chemin\u00e9ebau-technik A.dossenbach",
    "wof:placetype":"venue"
},
  "geometry": {"coordinates":[8.4598932266,47.1814994812],"type":"Point"}
}