{
  "type": "Feature",
  "properties": {
    "iso:country":"CH",
    "sg:address":"1534",
    "sg:city":"Sassel",
    "sg:orig_category":"RESTAURANTS: TEA-ROOMS",
    "sg:phone":"+41 81 420 09 09",
    "sg:postcode":"1534",
    "sg:province":"Fribourg",
    "wof:name":"Bi\u00e4sch Uschi",
    "wof:placetype":"venue"
},
  "geometry": {"coordinates":[9.8251085281,46.7960891724],"type":"Point"}
}