{
  "type": "Feature",
  "properties": {
    "iso:country":"CH",
    "sg:address":"Bahnhofstrasse 8",
    "sg:city":"Aadorf",
    "sg:orig_category":"Drogerien",
    "sg:phone":"+41 52 368 05 05",
    "sg:postcode":"8355",
    "sg:province":"Thurgau",
    "wof:name":"Apotheke-drogerie Aagena",
    "wof:placetype":"venue"
},
  "geometry": {"coordinates":[8.901386261,47.4891624451],"type":"Point"}
}