{
  "type": "Feature",
  "properties": {
    "iso:country":"CH",
    "sg:address":"Morgenstrasse 134 3018 Bern. Postfach",
    "sg:city":"Bern",
    "sg:orig_category":"Herstellung von elektrischen Lampen U Leuchten",
    "sg:postcode":"3018",
    "sg:province":"Bern",
    "wof:name":"Neon Bern H. Schumacher Leuchtreklamen; Neuanlage, Reparatur U. Reinigung.",
    "wof:placetype":"venue"
},
  "geometry": {"coordinates":[7.3886079788,46.9344825745],"type":"Point"}
}