{
  "type": "Feature",
  "properties": {
    "iso:country":"CH",
    "sg:address":"Webergasse 14",
    "sg:city":"St.gallen",
    "sg:orig_category":"Sonstiger Unterricht",
    "sg:phone":"+41 71 223 19 18",
    "sg:postcode":"9000",
    "sg:province":"St. Gallen",
    "wof:name":"Barbara Wegelin N\u00e4hkurse & Schule",
    "wof:placetype":"venue"
},
  "geometry": {"coordinates":[9.3748292923,47.4230690002],"type":"Point"}
}