{
  "type": "Feature",
  "properties": {
    "iso:country":"CH",
    "sg:address":"B\u00fcntenstrasse 1",
    "sg:city":"Fislisbach",
    "sg:orig_category":"Reiseb\u00fcros U Reiseveranstalter",
    "sg:postcode":"5442",
    "sg:province":"Aargau",
    "wof:name":"Outdoor Activity Sa",
    "wof:placetype":"venue"
},
  "geometry": {"coordinates":[7.0122699738,46.1147918701],"type":"Point"}
}