{
  "type": "Feature",
  "properties": {
    "iso:country":"CH",
    "sg:address":"Z\u00fcrcherstrasse 4",
    "sg:city":"Killwangen",
    "sg:orig_category":"Instandhaltung U Reparatur von Automobilen",
    "sg:phone":"+41 56 402 05 15",
    "sg:postcode":"8956",
    "sg:province":"Aargau",
    "wof:name":"Auto-service A. Oberholzer",
    "wof:placetype":"venue"
},
  "geometry": {"coordinates":[8.3465833664,47.4346427917],"type":"Point"}
}