{
  "type": "Feature",
  "properties": {
    "iso:country":"CH",
    "sg:address":"Wahlendorfstrasse 22",
    "sg:city":"Meikirch",
    "sg:orig_category":"Organisationen des Gesundheitswesen",
    "sg:postcode":"3045",
    "sg:province":"Bern",
    "wof:name":"Spitexverein Meikirch- Kirchlindach",
    "wof:placetype":"venue"
},
  "geometry": {"coordinates":[7.3577690125,47.0073928833],"type":"Point"}
}