{
  "type": "Feature",
  "properties": {
    "addr:full":"Rue Marterey 38 Lausanne Vaud 1005",
    "addr:housenumber":"38",
    "addr:postcode":"1005",
    "addr:street":"Rue Marterey",
    "iso:country":"CH",
    "sg:address":"Rue Marterey 38",
    "sg:city":"Lausanne",
    "sg:orig_category":"Detailhandel mit Damenbekleidung",
    "sg:phone":"+41 21 351 44 40",
    "sg:postcode":"1005",
    "sg:province":"Vaud",
    "wof:name":"Boutique Belle-rebelle Pr\u00eat-\u00e0-porter F\u00e9minin",
    "wof:placetype":"venue"
},
  "geometry": {"coordinates":[6.639032,46.520782],"type":"Point"}
}