{
  "type": "Feature",
  "properties": {
    "iso:country":"CH",
    "sg:address":"Rieschweg 8",
    "sg:city":"Allschwil",
    "sg:orig_category":"Herstellung von Schreinerwaren ohne ausgepr\u00e4gten Schwerpunkt",
    "sg:phone":"+41 61 481 27 05",
    "sg:postcode":"4123",
    "sg:province":"Basel-Landschaft",
    "wof:name":"Burkhard & Pelladoni Schreinerservice",
    "wof:placetype":"venue"
},
  "geometry": {"coordinates":[7.5295200348,47.5517044067],"type":"Point"}
}