{
  "type": "Feature",
  "properties": {
    "iso:country":"CH",
    "sg:address":"In Lampitz\u00e4ckern 3",
    "sg:city":"Dietlikon",
    "sg:classifiers":[
        {
            "category":"Insurance",
            "subcategory":"Insurance Agent",
            "type":"Services"
        }
    ],
    "sg:phone":"+41 61 716 91 91",
    "sg:postcode":"8305",
    "sg:province":"Z\u00fcrich",
    "sg:tags":[
        "versicherungsagenturen",
        "-broker"
    ],
    "wof:name":"Ren\u00e9 Martin Z\u00fcrich Versicherungen",
    "wof:placetype":"venue"
},
  "geometry": {"coordinates":[7.5158829689,47.4789619446],"type":"Point"}
}