{
  "type": "Feature",
  "properties": {
    "iso:country":"CH",
    "sg:address":"Baslerstrasse 60",
    "sg:city":"Binningen",
    "sg:orig_category":"Allgemeiner Hoch U Tiefbau",
    "sg:phone":"+41 61 712 50 62",
    "sg:postcode":"4102",
    "sg:province":"Basel-Landschaft",
    "wof:name":"Glanzmann Ag, Hoch Und Tiefbau",
    "wof:placetype":"venue"
},
  "geometry": {"coordinates":[7.595499,47.501049],"type":"Point"}
}