{
  "type": "Feature",
  "properties": {
    "iso:country":"CH",
    "sg:address":"Grand-rue 13",
    "sg:city":"Ch\u00e9zard-st-martin",
    "sg:orig_category":"Allgemeiner Hoch U Tiefbau Br\u00fccken U Tunnelbau",
    "sg:phone":"+41 81 830 02 22",
    "sg:postcode":"2054",
    "sg:province":"Neuch\u00e2tel",
    "wof:name":"Andrea Pitsch Ag Bauunternehmung Hauptsitz",
    "wof:placetype":"venue"
},
  "geometry": {"coordinates":[9.836801,46.497902],"type":"Point"}
}