{
  "type": "Feature",
  "properties": {
    "iso:country":"CH",
    "sg:address":"K\u00fcbachstrasse 9",
    "sg:city":"Berneck",
    "sg:orig_category":"Detailhandel mit Fleisch U Fleischwaren",
    "sg:phone":"+41 71 744 11 07",
    "sg:postcode":"9442",
    "sg:province":"St. Gallen",
    "wof:name":"Spiess Otto, Metzgerei & Fleischhandel.",
    "wof:placetype":"venue"
},
  "geometry": {"coordinates":[9.611456871,47.4271125793],"type":"Point"}
}