{
  "type": "Feature",
  "properties": {
    "iso:country":"CH",
    "sg:address":"Freimettigenstrasse 5",
    "sg:city":"Konolfingen",
    "sg:orig_category":"LANDW. GENOSSENSCHAFTEN GRASTROCKNUNGSANL",
    "sg:phone":"+41 31 791 04 50",
    "sg:postcode":"3510",
    "sg:province":"Bern",
    "wof:name":"Landw.genossenschaft Stalden-oberdiessbach",
    "wof:placetype":"venue"
},
  "geometry": {"coordinates":[7.6251749992,46.8712005615],"type":"Point"}
}