{
  "type": "Feature",
  "properties": {
    "iso:country":"CH",
    "sg:address":"Malbun Steg 101",
    "sg:city":"Triesenberg",
    "sg:classifiers":[
        {
            "category":"Restaurant",
            "type":"Food & Drink"
        }
    ],
    "sg:phone":"+423 263 10 16",
    "sg:postcode":"9497",
    "wof:name":"Sportcaf\u00e9 Bergst\u00fcbli",
    "wof:placetype":"venue"
},
  "geometry": {"coordinates":[9.6081409454,47.1026649475],"type":"Point"}
}