{
  "type": "Feature",
  "properties": {
    "iso:country":"CH",
    "sg:address":"Route De Sous-moulin 35",
    "sg:city":"Ch\u00eane-bourg",
    "sg:orig_category":"Instandhaltung U Reparatur von Automobilen",
    "sg:postcode":"1225",
    "sg:province":"Gen\u00e8ve",
    "wof:name":"Carrosserie Spenglerei + Spritzwerk, Frey Julius Autolackiererei Und Carrosseriewerkst\u00e4tte",
    "wof:placetype":"venue"
},
  "geometry": {"coordinates":[9.623044014,47.455783844],"type":"Point"}
}