{
  "type": "Feature",
  "properties": {
    "iso:country":"CH",
    "sg:address":"Criblet Rue Du 13",
    "sg:city":"Fribourg",
    "sg:orig_category":"Non-Classified Establishments",
    "sg:postcode":"1700",
    "sg:province":"Fribourg",
    "wof:name":"Ch\u00e4s K\u00e4ppeli Gmbh",
    "wof:placetype":"venue"
},
  "geometry": {"coordinates":[7.9010691643,46.7053871155],"type":"Point"}
}