{
  "type": "Feature",
  "properties": {
    "iso:country":"CH",
    "sg:address":"B\u00fcrgenstockstrasse 12 6362 Stansstad. Postfach 414",
    "sg:city":"Stansstad",
    "sg:orig_category":"Instandhaltung U Reparatur von Automobilen",
    "sg:phone":"+41 71 477 21 20",
    "sg:postcode":"6362",
    "sg:province":"Nidwalden",
    "wof:name":"Garage Holzer B.",
    "wof:placetype":"venue"
},
  "geometry": {"coordinates":[9.373459816,47.5331306458],"type":"Point"}
}