{
  "type": "Feature",
  "properties": {
    "iso:country":"CH",
    "sg:address":"W\u00e4ssermattstrasse 4",
    "sg:city":"Aarau",
    "sg:orig_category":"Detailhandel mit Metallwaren, Anstrichmitteln, Glaswaren, Bau U Heimwerkerbedarf Herstellung von Met",
    "sg:phone":"+41 62 832 52 52",
    "sg:postcode":"5000",
    "sg:province":"Aargau",
    "wof:name":"Pcc Flow Technologies (switzerland) Ag",
    "wof:placetype":"venue"
},
  "geometry": {"coordinates":[8.0679779053,47.3986358643],"type":"Point"}
}