{
  "type": "Feature",
  "properties": {
    "iso:country":"CH",
    "sg:address":"Pfadhagstrasse 5",
    "sg:city":"Wallisellen",
    "sg:orig_category":"Massagestudios",
    "sg:phone":"+41 18305651",
    "sg:postcode":"8304",
    "sg:province":"Z\u00fcrich",
    "wof:name":"Ursula Schreiner Ganzk\u00f6rpermassage",
    "wof:placetype":"venue"
},
  "geometry": {"coordinates":[8.5930500031,47.4183731079],"type":"Point"}
}