{
  "type": "Feature",
  "properties": {
    "iso:country":"CH",
    "sg:address":"Stationsstrasse 17",
    "sg:city":"Z\u00fcrich",
    "sg:classifiers":[
        {
            "category":"Internet Cafe",
            "subcategory":"None",
            "type":"Food & Drink"
        }
    ],
    "sg:phone":"+41 14576767",
    "sg:postcode":"8003",
    "sg:province":"Z\u00fcrich",
    "sg:tags":[
        "webdesign",
        "provider"
    ],
    "wof:name":"Riodata Ag Adsl Provider",
    "wof:placetype":"venue"
},
  "geometry": {"coordinates":[8.5195789337,47.3726196289],"type":"Point"}
}