{
  "type": "Feature",
  "properties": {
    "iso:country":"CH",
    "sg:address":"Gerenstrasse 2",
    "sg:city":"Bolligen",
    "sg:orig_category":"Unternehmensberatung",
    "sg:phone":"+41 31 921 35 75",
    "sg:postcode":"3065",
    "sg:province":"Bern",
    "wof:name":"Ebner Wolfgang.",
    "wof:placetype":"venue"
},
  "geometry": {"coordinates":[7.4914717674,46.9728965759],"type":"Point"}
}