{
  "type": "Feature",
  "properties": {
    "iso:country":"CH",
    "sg:address":"Oberglatterstrasse 8",
    "sg:city":"R\u00fcmlang",
    "sg:orig_category":"Kauf U Verkauf von Immobilien auf eigene Rechnung",
    "sg:postcode":"8153",
    "sg:province":"Z\u00fcrich",
    "wof:name":"B\u00fcchi H.j. Immobilien Ag",
    "wof:placetype":"venue"
},
  "geometry": {"coordinates":[8.5299749374,47.4572906494],"type":"Point"}
}