{
  "type": "Feature",
  "properties": {
    "iso:country":"CH",
    "sg:address":"Route Suisse 58",
    "sg:city":"Tannay",
    "sg:classifiers":[
        {
            "category":"Restaurant",
            "type":"Food & Drink"
        }
    ],
    "sg:phone":"+41 22 755 24 65",
    "sg:postcode":"1295",
    "sg:province":"Vaud",
    "wof:name":"Restaurant De La Plage",
    "wof:placetype":"venue"
},
  "geometry": {"coordinates":[6.1804499626,46.3049812317],"type":"Point"}
}