{
  "type": "Feature",
  "properties": {
    "iso:country":"CH",
    "sg:address":"Rue De La Dixence 25 1950 Sion Case Postale 767",
    "sg:city":"Sion",
    "sg:orig_category":"Reiseb\u00fcros",
    "sg:phone":"+41 27 322 05 67",
    "sg:postcode":"1951",
    "sg:province":"Valais",
    "wof:name":"Rhone-tours Ag",
    "wof:placetype":"venue"
},
  "geometry": {"coordinates":[7.364303112,46.2299919128],"type":"Point"}
}