{
  "type": "Feature",
  "properties": {
    "iso:country":"CH",
    "sg:address":"Innere Margarethenstrasse 2 4051 Basel. Postfach",
    "sg:city":"Basel",
    "sg:orig_category":"Wirtschaftsverb\u00e4nde Industrie, Handel and Gewerbe",
    "sg:phone":"+41 61 281 63 63",
    "sg:postcode":"4010",
    "sg:province":"Basel-Stadt",
    "wof:name":"Svit Sektion Beider Basel C/o Gribi Urs Immobilien Ag",
    "wof:placetype":"venue"
},
  "geometry": {"coordinates":[7.5867991447,47.5506706238],"type":"Point"}
}