{
  "type": "Feature",
  "properties": {
    "iso:country":"CH",
    "sg:address":"Via Paradiso 22",
    "sg:city":"Sorengo",
    "sg:orig_category":"Verwaltung von Immobilien",
    "sg:phone":"+41 91 993 10 22",
    "sg:postcode":"6924",
    "sg:province":"Ticino",
    "wof:name":"Finmoro Sa",
    "wof:placetype":"venue"
},
  "geometry": {"coordinates":[8.9391269684,45.99659729],"type":"Point"}
}