{
  "type": "Feature",
  "properties": {
    "iso:country":"CH",
    "sg:address":"Rue De L'est 9",
    "sg:city":"Moutier",
    "sg:classifiers":[
        {
            "category":"Restaurant",
            "type":"Food & Drink"
        }
    ],
    "sg:phone":"+41 32 493 44 43",
    "sg:postcode":"2740",
    "sg:province":"Bern",
    "wof:name":"Restaurant L\u00f6tschberg",
    "wof:placetype":"venue"
},
  "geometry": {"coordinates":[7.3724598885,47.2787208557],"type":"Point"}
}