{
  "type": "Feature",
  "properties": {
    "iso:country":"CH",
    "sg:address":"Flughofstrasse 49",
    "sg:city":"R\u00fcmlang",
    "sg:orig_category":"Sonstige mit Sport verbundene T\u00e4tigkeiten",
    "sg:phone":"+41 18534427",
    "sg:postcode":"8153",
    "sg:province":"Z\u00fcrich",
    "wof:name":"Z\u00fcrrer Roland Ag",
    "wof:placetype":"venue"
},
  "geometry": {"coordinates":[8.5368490219,47.4531784058],"type":"Point"}
}