{
  "type": "Feature",
  "properties": {
    "iso:country":"CH",
    "sg:address":"Quai Gustave-ador 50",
    "sg:city":"Gen\u00e8ve",
    "sg:orig_category":"Buchverlag Sonstige Institutionen des Sozialwesens ohne Beherbergung",
    "sg:phone":"+41 22 736 74 30",
    "sg:postcode":"1207",
    "sg:province":"Gen\u00e8ve",
    "wof:name":"Cema Sa",
    "wof:placetype":"venue"
},
  "geometry": {"coordinates":[6.161381,46.20715],"type":"Point"}
}