{
  "type": "Feature",
  "properties": {
    "iso:country":"CH",
    "sg:address":"Aarestrasse 2a",
    "sg:city":"D\u00f6ttingen",
    "sg:orig_category":"Fernmeldedienste",
    "sg:phone":"+41 56 250 00 05",
    "sg:postcode":"5312",
    "sg:province":"Aargau",
    "wof:name":"Hanspeter Humbel Handy Shop",
    "wof:placetype":"venue"
},
  "geometry": {"coordinates":[8.2544641495,47.5741233826],"type":"Point"}
}