{
  "type": "Feature",
  "properties": {
    "iso:country":"CH",
    "sg:address":"La Nois",
    "sg:city":"Surava",
    "sg:orig_category":"Bauschreinerei Herstellung von sonstigen M\u00f6beln",
    "sg:phone":"+41 79 407 55 21",
    "sg:postcode":"7472",
    "sg:province":"Graubunden",
    "wof:name":"Antic Atelier Cresta",
    "wof:placetype":"venue"
},
  "geometry": {"coordinates":[9.606299,46.66354],"type":"Point"}
}