{
  "type": "Feature",
  "properties": {
    "iso:country":"CH",
    "sg:address":"Cours De Rive 2 1204 Gen\u00e8ve Case Postale 3173",
    "sg:city":"Gen\u00e8ve",
    "sg:orig_category":"Reinigungsgewerbe Sonstiges Reinigungsgewerbe",
    "sg:phone":"+41 22 342 36 00",
    "sg:postcode":"1204",
    "sg:province":"Gen\u00e8ve",
    "wof:name":"Saded, Epuration Et D\u00e9sinfection R\u00e9unies Sa",
    "wof:placetype":"venue"
},
  "geometry": {"coordinates":[6.1323451996,46.1880149841],"type":"Point"}
}