{
  "type": "Feature",
  "properties": {
    "iso:country":"CH",
    "sg:address":"6288",
    "sg:city":"Schongau",
    "sg:orig_category":"Schulpflegen",
    "sg:phone":"+41 41 497 30 74",
    "sg:postcode":"6288",
    "sg:province":"Luzern",
    "wof:name":"Schulpflege Der Gemeinde Schwarzenberg",
    "wof:placetype":"venue"
},
  "geometry": {"coordinates":[8.1731996536,47.0156593323],"type":"Point"}
}