{
  "type": "Feature",
  "properties": {
    "iso:country":"CH",
    "sg:address":"Basadingerstrasse 14",
    "sg:city":"Diessenhofen",
    "sg:orig_category":"Detailhandel mit Bekleidung",
    "sg:phone":"+41 52 657 29 73",
    "sg:postcode":"8253",
    "sg:province":"Thurgau",
    "wof:name":"Textil-center Bruno Graber",
    "wof:placetype":"venue"
},
  "geometry": {"coordinates":[8.749993,47.687172],"type":"Point"}
}