{
  "type": "Feature",
  "properties": {
    "iso:country":"CH",
    "sg:address":"Olltenerstrasse 93",
    "sg:city":"Aarburg",
    "sg:orig_category":"Sonstige Kultur U Unterhaltungseinrichtungen Spielsalons",
    "sg:phone":"+41 62 296 01 86",
    "sg:postcode":"4663",
    "sg:province":"Aargau",
    "wof:name":"Spielsalon Eldorado",
    "wof:placetype":"venue"
},
  "geometry": {"coordinates":[7.9054999352,47.3318786621],"type":"Point"}
}