{
  "type": "Feature",
  "properties": {
    "iso:country":"CH",
    "sg:address":"Parkhotel Schoenegg",
    "sg:city":"Grindelwald",
    "sg:orig_category":"Non-Classified Establishments",
    "sg:postcode":"3818",
    "sg:province":"Bern",
    "wof:name":"Parkhotel Schoenegg Gmbh",
    "wof:placetype":"venue"
},
  "geometry": {"coordinates":[8.0346326828,46.624370575],"type":"Point"}
}