{
  "type": "Feature",
  "properties": {
    "iso:country":"CH",
    "sg:address":"Motta Via Giuseppe 23",
    "sg:city":"Mendrisio",
    "sg:orig_category":"Markt U Meinungsforschung",
    "sg:postcode":"6850",
    "sg:province":"Ticino",
    "wof:name":"Bmc Buob Marketing Consulting",
    "wof:placetype":"venue"
},
  "geometry": {"coordinates":[7.5651688576,46.9342079163],"type":"Point"}
}