{
  "type": "Feature",
  "properties": {
    "iso:country":"CH",
    "sg:address":"Franz Langweg 18",
    "sg:city":"Solothurn",
    "sg:orig_category":"Interessenvertretungen",
    "sg:postcode":"4500",
    "sg:province":"Solothurn",
    "wof:name":"Stiftung Altersheim St. Annahof",
    "wof:placetype":"venue"
},
  "geometry": {"coordinates":[7.5484552383,47.2131385803],"type":"Point"}
}