{
  "type": "Feature",
  "properties": {
    "iso:country":"CH",
    "sg:address":"Chemin Des Ormeaux 20",
    "sg:city":"Epalinges",
    "sg:orig_category":"Fachdetailhandel in Verkaufsr\u00e4umen",
    "sg:postcode":"1066",
    "sg:province":"Vaud",
    "wof:name":"Wilbreg, Wild Et Bregger",
    "wof:placetype":"venue"
},
  "geometry": {"coordinates":[6.6533789635,46.5446014404],"type":"Point"}
}