{
  "type": "Feature",
  "properties": {
    "iso:country":"CH",
    "sg:address":"Seestrasse 38",
    "sg:city":"Gersau",
    "sg:orig_category":"D\u00e4mmung gegen K\u00e4lte, W\u00e4rme, Schall U Ersch\u00fctterung Stukkateurgewerbe, Gipserei U Verputzerei",
    "sg:phone":"+41 41 828 26 26",
    "sg:postcode":"6442",
    "sg:province":"Schwyz",
    "wof:name":"Aqua Airsec Sa Ass\u00e8chement De B\u00e2timents",
    "wof:placetype":"venue"
},
  "geometry": {"coordinates":[8.5231590271,46.9927558899],"type":"Point"}
}