{
  "type": "Feature",
  "properties": {
    "iso:country":"CH",
    "sg:address":"Dorfstrasse 27",
    "sg:city":"Feusisberg",
    "sg:orig_category":"Diskotheken, Dancings, Night Clubs",
    "sg:phone":"+41 55 442 21 52",
    "sg:postcode":"8835",
    "sg:province":"Schwyz",
    "wof:name":"Disco-bar Dancing X-large",
    "wof:placetype":"venue"
},
  "geometry": {"coordinates":[8.8513183594,47.1923904419],"type":"Point"}
}