{
  "type": "Feature",
  "properties": {
    "iso:country":"CH",
    "sg:address":"B\u00f6sch 37",
    "sg:city":"H\u00fcnenberg",
    "sg:orig_category":"Public-Relations-Agenturen Werbeagenturen",
    "sg:phone":"+41 22 751 30 22",
    "sg:postcode":"6331",
    "sg:province":"Zug",
    "wof:name":"Communicore, Palivoda Robert",
    "wof:placetype":"venue"
},
  "geometry": {"coordinates":[6.2190899849,46.2641525269],"type":"Point"}
}