{
  "type": "Feature",
  "properties": {
    "addr:full":"Chemin Du Grand-clos 1 Villars-sur-gl\u00e2ne Fribourg 1752",
    "addr:housenumber":"1",
    "addr:postcode":"1752",
    "addr:street":"Chemin Du Grand-Clos",
    "iso:country":"CH",
    "sg:address":"Chemin Du Grand-clos 1",
    "sg:city":"Villars-sur-gl\u00e2ne",
    "sg:classifiers":[
        {
            "category":"Home & Garden",
            "subcategory":"Hardware",
            "type":"Retail Goods"
        }
    ],
    "sg:phone":"+41 26 401 00 60",
    "sg:postcode":"1752",
    "sg:province":"Fribourg",
    "sg:tags":[
        "component",
        "electronic"
    ],
    "wof:name":"Electronitel S.a.",
    "wof:placetype":"venue"
},
  "geometry": {"coordinates":[7.129021,46.793221],"type":"Point"}
}