{
  "type": "Feature",
  "properties": {
    "iso:country":"CH",
    "sg:address":"Montchoisy Rue De 74 1207 Gen\u00e8ve. Postfach",
    "sg:city":"Gen\u00e8ve",
    "sg:orig_category":"Reinigungsgewerbe",
    "sg:postcode":"1207",
    "sg:province":"Gen\u00e8ve",
    "wof:name":"Vallotto Et Cie",
    "wof:placetype":"venue"
},
  "geometry": {"coordinates":[6.1637501717,46.205039978],"type":"Point"}
}