{
  "type": "Feature",
  "properties": {
    "iso:country":"CH",
    "sg:address":"Brel Route Du 25 2068 Hauterive. Postfach",
    "sg:city":"Hauterive",
    "sg:orig_category":"Reinigungsgewerbe",
    "sg:postcode":"2068",
    "sg:province":"Neuch\u00e2tel",
    "wof:name":"Nigg Lucien Eidg. Dipl. Kaminfegermeister",
    "wof:placetype":"venue"
},
  "geometry": {"coordinates":[9.4626941681,47.169380188],"type":"Point"}
}