{
  "type": "Feature",
  "properties": {
    "addr:full":"Beckenriederstrasse 9 6374 Buochs. Postfach 307 Buochs Nidwalden 6374",
    "addr:housenumber":"9;307",
    "addr:postcode":"6374 buochs.;6374",
    "addr:street":"Beckenriederstrasse;Postfach",
    "iso:country":"CH",
    "sg:address":"Beckenriederstrasse 9 6374 Buochs. Postfach 307",
    "sg:city":"Buochs",
    "sg:orig_category":"Architekturb\u00fcros",
    "sg:phone":"+41 55 210 13 35",
    "sg:postcode":"6374",
    "sg:province":"Nidwalden",
    "wof:name":"Felix Schmid Partner Ag Architektur + Denkmalpflege",
    "wof:placetype":"venue"
},
  "geometry": {"coordinates":[8.422763,46.974003],"type":"Point"}
}