{
  "type": "Feature",
  "properties": {
    "addr:full":"Hauptstrasse 65 Schmerikon St. Gallen 8716",
    "addr:housenumber":"65",
    "addr:postcode":"8716",
    "addr:street":"Hauptstrasse",
    "iso:country":"CH",
    "sg:address":"Hauptstrasse 65",
    "sg:city":"Schmerikon",
    "sg:orig_category":"Bauschreinerei Zimmerei, Dachdeckerei, Bauspenglerei U Abdichtung",
    "sg:phone":"+41 55 282 14 46",
    "sg:postcode":"8716",
    "sg:province":"St. Gallen",
    "wof:name":"Weber Albert Ag",
    "wof:placetype":"venue"
},
  "geometry": {"coordinates":[8.944568,47.226089],"type":"Point"}
}