{
  "type": "Feature",
  "properties": {
    "iso:country":"CH",
    "sg:address":"Limmatauweg 9",
    "sg:city":"Ennetbaden",
    "sg:orig_category":"Erschliessung von Grundst\u00fccken",
    "sg:postcode":"5408",
    "sg:province":"Aargau",
    "wof:name":"Genossenschaft Limmatau, Ennetbaden",
    "wof:placetype":"venue"
},
  "geometry": {"coordinates":[8.3105678558,47.4752807617],"type":"Point"}
}