{
  "type": "Feature",
  "properties": {
    "iso:country":"CH",
    "sg:address":"Sennegasse 45 8476 Unterstammheim. Postfach",
    "sg:city":"Unterstammheim",
    "sg:orig_category":"Grosshandel mit Getreide, Saatgut U Futtermitteln",
    "sg:phone":"+41 52 745 10 25",
    "sg:postcode":"8476",
    "sg:province":"Z\u00fcrich",
    "wof:name":"Protanimal Ag",
    "wof:placetype":"venue"
},
  "geometry": {"coordinates":[8.7913179398,47.6364898682],"type":"Point"}
}