{
  "type": "Feature",
  "properties": {
    "iso:country":"CH",
    "sg:address":"Gruenenburg 241",
    "sg:city":"Kleinb\u00f6singen",
    "sg:orig_category":"Sonstige mit der Informatik verbundene T\u00e4tigkeiten",
    "sg:phone":"+41 26 674 35 43",
    "sg:postcode":"3213",
    "sg:province":"Fribourg",
    "wof:name":"Urus Consulting Gmbh",
    "wof:placetype":"venue"
},
  "geometry": {"coordinates":[7.1936130524,46.8886795044],"type":"Point"}
}