{
  "type": "Feature",
  "properties": {
    "iso:country":"CH",
    "sg:address":"Lindenbergstrasse 15 8700 K\u00fcsnacht Zh. Postfach",
    "sg:city":"B\u00e4retswil",
    "sg:orig_category":"Interessenvertretungen",
    "sg:phone":"+41 19107193",
    "sg:postcode":"8344",
    "sg:province":"Z\u00fcrich",
    "wof:name":"Stiftung F\u00fcr Jung'sche Psychologie",
    "wof:placetype":"venue"
},
  "geometry": {"coordinates":[8.588136673,47.3199157715],"type":"Point"}
}