{
  "type": "Feature",
  "properties": {
    "iso:country":"CH",
    "sg:address":"Rue Des Ecoles 14",
    "sg:city":"Chippis",
    "sg:orig_category":"Bauschreinerei Herstellung von M\u00f6beln verschiedener Art",
    "sg:phone":"+41 27 455 72 65",
    "sg:postcode":"3965",
    "sg:province":"Valais",
    "wof:name":"Maximilien Zanin Eb\u00e9nisterie",
    "wof:placetype":"venue"
},
  "geometry": {"coordinates":[7.539125,46.279354],"type":"Point"}
}