{
  "type": "Feature",
  "properties": {
    "iso:country":"CH",
    "sg:address":"Rue Du Lion-d'or 5-7 1003 Lausanne. Postfach",
    "sg:city":"Lausanne",
    "sg:orig_category":"Grossbanken",
    "sg:phone":"+41 21 340 11 11",
    "sg:postcode":"1002",
    "sg:province":"Vaud",
    "wof:name":"Credit Suisse",
    "wof:placetype":"venue"
},
  "geometry": {"coordinates":[6.6304497719,46.5199890137],"type":"Point"}
}