{
  "type": "Feature",
  "properties": {
    "iso:country":"CH",
    "sg:address":"Ifangstrasse 7",
    "sg:city":"Aadorf",
    "sg:classifiers":[
        {
            "category":"Professional",
            "subcategory":"Credit Reporting & Collection",
            "type":"Services"
        }
    ],
    "sg:phone":"+41 52 365 25 64",
    "sg:postcode":"8355",
    "sg:province":"Thurgau",
    "sg:tags":[
        "processing",
        "data"
    ],
    "wof:name":"Letter-shop Aadorf",
    "wof:placetype":"venue"
},
  "geometry": {"coordinates":[8.901218,47.496014],"type":"Point"}
}