{
  "type": "Feature",
  "properties": {
    "iso:country":"CH",
    "sg:address":"Sandgasse 3e",
    "sg:city":"B\u00fcetigen",
    "sg:orig_category":"Grosshandel mit sonstigen Gebrauchs U Verbrauchsg\u00fctern Mechanische Werkst\u00e4tten",
    "sg:phone":"+41 32 384 25 82",
    "sg:postcode":"3263",
    "sg:province":"Bern",
    "wof:name":"Dietsche Ag",
    "wof:placetype":"venue"
},
  "geometry": {"coordinates":[7.3441581726,47.1073989868],"type":"Point"}
}