{
  "type": "Feature",
  "properties": {
    "iso:country":"CH",
    "sg:address":"R\u00fctistrasse 4",
    "sg:city":"Hombrechtikon",
    "sg:orig_category":"Instandhaltung U Reparatur von Automobilen",
    "sg:phone":"+41 55 244 61 10",
    "sg:postcode":"8634",
    "sg:province":"Z\u00fcrich",
    "wof:name":"Garage Herzig, Herzig Peter",
    "wof:placetype":"venue"
},
  "geometry": {"coordinates":[8.7666978836,47.2515525818],"type":"Point"}
}