{
  "type": "Feature",
  "properties": {
    "iso:country":"CH",
    "sg:address":"Rainstrasse 29",
    "sg:city":"Romanshorn",
    "sg:orig_category":"Allgemeiner Hoch U Tiefbau Allgemeiner Hochbau",
    "sg:phone":"+41 41 870 58 12",
    "sg:postcode":"8590",
    "sg:province":"Thurgau",
    "wof:name":"Baumann + Epp Bau Gmbh",
    "wof:placetype":"venue"
},
  "geometry": {"coordinates":[8.675513,46.877823],"type":"Point"}
}