{
  "type": "Feature",
  "properties": {
    "iso:country":"CH",
    "sg:address":"Hohlstrasse 287",
    "sg:city":"Z\u00fcrich",
    "sg:orig_category":"Grosshandel mit Nahrungsmitteln, Getr\u00e4nken U Tabakwaren ohne ausgepr\u00e4gten Schwerpunkt",
    "sg:postcode":"8004",
    "sg:province":"Z\u00fcrich",
    "wof:name":"Nwaogu Import, Export & Trading, Consultant",
    "wof:placetype":"venue"
},
  "geometry": {"coordinates":[8.5127353668,47.3833885193],"type":"Point"}
}