{
  "type": "Feature",
  "properties": {
    "iso:country":"CH",
    "sg:address":"Fluhrhofstrasse 5",
    "sg:city":"Buochs",
    "sg:orig_category":"Allgemeiner Hoch U Tiefbau Allgemeiner Hochbau",
    "sg:phone":"+41 41 620 42 00",
    "sg:postcode":"6374",
    "sg:province":"Nidwalden",
    "wof:name":"Frank Bau Ag",
    "wof:placetype":"venue"
},
  "geometry": {"coordinates":[8.413878,46.978062],"type":"Point"}
}