{
  "type": "Feature",
  "properties": {
    "iso:country":"CH",
    "sg:address":"Waldegg",
    "sg:city":"Beatenberg",
    "sg:orig_category":"Grosshandel mit Nahrungsmitteln, Getr\u00e4nken U Tabakwaren ohne ausgepr\u00e4gten Schwerpunkt",
    "sg:postcode":"3803",
    "sg:province":"Bern",
    "wof:name":"B\u00fcrge Therese",
    "wof:placetype":"venue"
},
  "geometry": {"coordinates":[9.4979696274,47.0085983276],"type":"Point"}
}