{
  "type": "Feature",
  "properties": {
    "iso:country":"CH",
    "sg:address":"Parkstrasse 23 3800 Matten B. Interl. Postfach 98",
    "sg:city":"Interlaken",
    "sg:orig_category":"Arbeitnehmerverb\u00e4nde",
    "sg:phone":"+41 33 823 67 88",
    "sg:postcode":"3800",
    "sg:province":"Bern",
    "wof:name":"Gdp Sektion Bern-oberland",
    "wof:placetype":"venue"
},
  "geometry": {"coordinates":[7.862052,46.682484],"type":"Point"}
}