{
  "type": "Feature",
  "properties": {
    "iso:country":"CH",
    "sg:address":"Rue Des Pr\u00e9s 8",
    "sg:city":"Del\u00e9mont",
    "sg:orig_category":"Druck ohne Zeitungsdruck",
    "sg:phone":"+41 32 422 33 83",
    "sg:postcode":"2800",
    "sg:province":"Jura",
    "wof:name":"Imprimerie Frossard",
    "wof:placetype":"venue"
},
  "geometry": {"coordinates":[7.352616787,47.3635940552],"type":"Point"}
}