{
  "type": "Feature",
  "properties": {
    "iso:country":"CH",
    "sg:address":"Buochserstrasse 30",
    "sg:city":"Beckenried",
    "sg:orig_category":"Dachdeckerei Zimmerei, Dachdeckerei, Bauspenglerei U Abdichtung",
    "sg:phone":"+41 41 620 55 44",
    "sg:postcode":"6375",
    "sg:province":"Nidwalden",
    "wof:name":"Ruedy Polenz Ag Spenglerei & Flachbedachungen",
    "wof:placetype":"venue"
},
  "geometry": {"coordinates":[8.462416,46.971115],"type":"Point"}
}