{
  "type": "Feature",
  "properties": {
    "iso:country":"CH",
    "sg:address":"Landhausstrasse 4a",
    "sg:city":"Meiringen",
    "sg:orig_category":"Gymnastik U Fitnesszentren",
    "sg:phone":"+41 33 971 60 00",
    "sg:postcode":"3860",
    "sg:province":"Bern",
    "wof:name":"Fit & Fun Fitness-center Meiringen",
    "wof:placetype":"venue"
},
  "geometry": {"coordinates":[8.1888723373,46.7281608582],"type":"Point"}
}