{
  "type": "Feature",
  "properties": {
    "iso:country":"CH",
    "sg:address":"Lettenstrasse 5",
    "sg:city":"Rotkreuz",
    "sg:orig_category":"Grosshandel mit B\u00fcromaschinen Herstellung von elektronischen Bauelementen",
    "sg:phone":"+41 22 793 01 30",
    "sg:postcode":"6343",
    "sg:province":"Zug",
    "wof:name":"Sysatronic Equipments, Benamram S.",
    "wof:placetype":"venue"
},
  "geometry": {"coordinates":[6.1065568924,46.1913757324],"type":"Point"}
}