{
  "type": "Feature",
  "properties": {
    "iso:country":"CH",
    "sg:address":"G\u00fcrtelstrasse 11",
    "sg:city":"Chur",
    "sg:orig_category":"Grosshandel mit B\u00fcromaschinen Grosshandel mit Datenverarbeitungsger\u00e4ten",
    "sg:phone":"+41 71 311 44 04",
    "sg:postcode":"7000",
    "sg:province":"Graubunden",
    "wof:name":"Aroa Informatik Ag",
    "wof:placetype":"venue"
},
  "geometry": {"coordinates":[9.3947153091,47.443649292],"type":"Point"}
}