{
  "type": "Feature",
  "properties": {
    "iso:country":"CH",
    "sg:address":"Grand-rue 58 1530 Payerne. Postfach",
    "sg:city":"Payerne",
    "sg:orig_category":"Erwachsenenbildung U Unterricht",
    "sg:postcode":"1530",
    "sg:province":"Vaud",
    "wof:name":"Music School, Spicher, Wyss Et Gutknecht Ecole De Musique. Stages Et Ateliers Musicaux Etc",
    "wof:placetype":"venue"
},
  "geometry": {"coordinates":[6.9371051788,46.8212776184],"type":"Point"}
}