{
  "type": "Feature",
  "properties": {
    "iso:country":"CH",
    "sg:address":"Vordergasse 42",
    "sg:city":"Wermatswil",
    "sg:orig_category":"Massagestudios",
    "sg:phone":"+41 19941001",
    "sg:postcode":"8615",
    "sg:province":"Z\u00fcrich",
    "wof:name":"Peter Nyfeler Massage-praxis",
    "wof:placetype":"venue"
},
  "geometry": {"coordinates":[8.7468900681,47.3614044189],"type":"Point"}
}