{
  "type": "Feature",
  "properties": {
    "iso:country":"CH",
    "sg:address":"Bachstrasse 11",
    "sg:city":"H\u00e4gendorf",
    "sg:orig_category":"Interessenvertretungen",
    "sg:postcode":"4614",
    "sg:province":"Solothurn",
    "wof:name":"Betagtenstiftung Ludwina Giger",
    "wof:placetype":"venue"
},
  "geometry": {"coordinates":[7.843547821,47.3326148987],"type":"Point"}
}