{
  "type": "Feature",
  "properties": {
    "iso:country":"CH",
    "sg:address":"Bahnhofplatz",
    "sg:city":"G\u00f6schenen",
    "sg:orig_category":"Sonstiger Fachdetailhandel in Verkaufsr\u00e4umen Sonstiger Grosshandel",
    "sg:phone":"+41 41 885 13 72",
    "sg:postcode":"6487",
    "sg:province":"Uri",
    "wof:name":"Indergand Peter Familie",
    "wof:placetype":"venue"
},
  "geometry": {"coordinates":[8.588760376,46.6663513184],"type":"Point"}
}