{
  "type": "Feature",
  "properties": {
    "iso:country":"CH",
    "sg:address":"Eschenstrasse 5",
    "sg:city":"Schwerzenbach",
    "sg:orig_category":"Grosshandel mit Holz U Baustoffen Handelsvermittlung U Grosshandel",
    "sg:phone":"+41 844 800 810",
    "sg:postcode":"8603",
    "sg:province":"Z\u00fcrich",
    "wof:name":"Selma Ag",
    "wof:placetype":"venue"
},
  "geometry": {"coordinates":[8.6559495926,47.388469696],"type":"Point"}
}