{
  "type": "Feature",
  "properties": {
    "iso:country":"CH",
    "sg:address":"Z\u00fcrcherstrasse 7",
    "sg:city":"Eglisau",
    "sg:orig_category":"Vermietung U Verpachtung von eigenen Immobilien",
    "sg:postcode":"8193",
    "sg:province":"Z\u00fcrich",
    "wof:name":"M\u00fclag Ag",
    "wof:placetype":"venue"
},
  "geometry": {"coordinates":[8.5234870911,47.5735244751],"type":"Point"}
}