{
  "type": "Feature",
  "properties": {
    "iso:country":"CH",
    "sg:address":"Hofmattstrasse",
    "sg:city":"Zermatt",
    "sg:orig_category":"Detailhandel mit Damenbekleidung Detailhandel mit Herrenbekleidung",
    "sg:phone":"+41 27 966 27 28",
    "sg:postcode":"3920",
    "sg:province":"Valais",
    "wof:name":"Mode-sport Luisa Perren Boutique",
    "wof:placetype":"venue"
},
  "geometry": {"coordinates":[7.7488899231,46.0211410522],"type":"Point"}
}