{
  "type": "Feature",
  "properties": {
    "iso:country":"CH",
    "sg:address":"Route Des Rottes 31",
    "sg:city":"Conthey",
    "sg:orig_category":"Sanit\u00e4r, Heizungs U L\u00fcftungsinstallation Sanit\u00e4rinstallation",
    "sg:phone":"+41 27 346 46 03",
    "sg:postcode":"1964",
    "sg:province":"Valais",
    "wof:name":"Sanibad Mabillard Philippe",
    "wof:placetype":"venue"
},
  "geometry": {"coordinates":[7.3068399429,46.2234687805],"type":"Point"}
}