{
  "type": "Feature",
  "properties": {
    "iso:country":"CH",
    "sg:address":"Oberwilerstrasse 73",
    "sg:city":"N\u00fcrensdorf",
    "sg:orig_category":"Detailhandel mit Blumen U Pflanzen Detailhandel mit Spielwaren",
    "sg:phone":"+41 18886828",
    "sg:postcode":"8309",
    "sg:province":"Z\u00fcrich",
    "wof:name":"Ewa Bogdanowicz Bolli Die W\u00e4lder Von Isengard",
    "wof:placetype":"venue"
},
  "geometry": {"coordinates":[8.641789,47.461189],"type":"Point"}
}