{
  "type": "Feature",
  "properties": {
    "iso:country":"CH",
    "sg:address":"Dorfstrasse 12",
    "sg:city":"Oberehrendingen",
    "sg:orig_category":"Detailhandel mit Fleisch U Fleischwaren",
    "sg:phone":"+41 56 222 25 09",
    "sg:postcode":"5422",
    "wof:name":"Rudolf Felchlin Metzgerei",
    "wof:placetype":"venue"
},
  "geometry": {"coordinates":[8.3410482407,47.4939117432],"type":"Point"}
}