{
  "type": "Feature",
  "properties": {
    "iso:country":"CH",
    "sg:address":"Aeulistrasse 13",
    "sg:city":"Weinfelden",
    "sg:orig_category":"G\u00fcterbef\u00f6rderung im Strassenverkehr",
    "sg:phone":"+41 62 893 26 55",
    "sg:postcode":"8570",
    "sg:province":"Thurgau",
    "wof:name":"Werner Beck Transporte",
    "wof:placetype":"venue"
},
  "geometry": {"coordinates":[8.1896743774,47.4155578613],"type":"Point"}
}