{
  "type": "Feature",
  "properties": {
    "iso:country":"CH",
    "sg:address":"Keberlistrasse 31",
    "sg:city":"Triboltingen",
    "sg:orig_category":"Herstellung von k\u00e4lte U lufttechnischen Erzeugnissen f\u00fcr gewerbliche Zwecke Installation von Heizung",
    "sg:phone":"+41 71 664 26 44",
    "sg:postcode":"8273",
    "sg:province":"Thurgau",
    "wof:name":"Robert Isler Aerotechnik",
    "wof:placetype":"venue"
},
  "geometry": {"coordinates":[9.1055049896,47.661491394],"type":"Point"}
}