{
  "type": "Feature",
  "properties": {
    "iso:country":"CH",
    "sg:address":"Bahnhofstrasse 8 6422 Steinen. Postfach 154",
    "sg:city":"Steinen",
    "sg:orig_category":"Sonstige k\u00fcnstlerische U schriftstellerische T\u00e4tigkeiten U Darbietungen Vermietung von Gebrauchsg\u00fcte",
    "sg:phone":"+41 41 832 10 70",
    "sg:postcode":"6422",
    "sg:province":"Schwyz",
    "wof:name":"Thomas & Verena Steiger Maskenatelier",
    "wof:placetype":"venue"
},
  "geometry": {"coordinates":[8.6101341248,47.049030304],"type":"Point"}
}