{
  "type": "Feature",
  "properties": {
    "iso:country":"CH",
    "sg:address":"Bata-park",
    "sg:city":"M\u00f6hlin",
    "sg:orig_category":"Gymnastik U Fitnesszentren Saunas, Solarien, Fitnesszentren U \u00e4hnliches",
    "sg:phone":"+41 61 851 19 13",
    "sg:postcode":"4313",
    "sg:province":"Aargau",
    "wof:name":"Bronx-gym, Fitness Und Bodybuilding Studio Schneider",
    "wof:placetype":"venue"
},
  "geometry": {"coordinates":[7.8443222046,47.5739860535],"type":"Point"}
}