{
  "type": "Feature",
  "properties": {
    "iso:country":"CH",
    "sg:address":"Sources Chemin Des 52b",
    "sg:city":"Yverdon-les-bains",
    "sg:orig_category":"Detailhandel mit Metallwaren, Anstrichmitteln, Glaswaren, Bau U Heimwerkerbedarf",
    "sg:postcode":"1400",
    "sg:province":"Vaud",
    "wof:name":"Cm-celfa Membrantrenntechnik Ag",
    "wof:placetype":"venue"
},
  "geometry": {"coordinates":[8.6383857727,47.0238075256],"type":"Point"}
}