{
  "type": "Feature",
  "properties": {
    "iso:country":"CH",
    "sg:address":"Cr\u00eat-de-marche",
    "sg:city":"Chavannes-de-bogis",
    "sg:orig_category":"Erdbewegungsarbeiten Maurerarbeiten",
    "sg:phone":"+41 22 776 22 41",
    "sg:postcode":"1279",
    "sg:province":"Vaud",
    "wof:name":"Guido Pillon Sa Ma\u00e7onnerie & Terrassement",
    "wof:placetype":"venue"
},
  "geometry": {"coordinates":[6.1625461578,46.3447494507],"type":"Point"}
}