{
  "type": "Feature",
  "properties": {
    "iso:country":"CH",
    "sg:address":"Rue De La Poste 5 1920 Martigny Case Postale 196",
    "sg:city":"Villars-sur-ollon",
    "sg:orig_category":"Versicherungen Hauptagenturen",
    "sg:phone":"+41 27 721 71 00",
    "sg:postcode":"1884",
    "sg:province":"Vaud",
    "wof:name":"Nationale Suisse Assurances Agence Principale",
    "wof:placetype":"venue"
},
  "geometry": {"coordinates":[7.0767869949,46.1030273438],"type":"Point"}
}