{
  "type": "Feature",
  "properties": {
    "iso:country":"CH",
    "sg:address":"Allmendstrasse 219",
    "sg:city":"Basel",
    "sg:orig_category":"Sonstige Kultur U Unterhaltungseinrichtungen",
    "sg:phone":"+41 61 601 14 10",
    "sg:postcode":"4058",
    "sg:province":"Basel-Stadt",
    "wof:name":"Quartierspielplatz Robi Allmend",
    "wof:placetype":"venue"
},
  "geometry": {"coordinates":[7.6236829758,47.5640602112],"type":"Point"}
}