{
  "type": "Feature",
  "properties": {
    "iso:country":"CH",
    "sg:address":"Dorfstrasse 25",
    "sg:city":"Hindelbank",
    "sg:orig_category":"Handelsvermittlung U Grosshandel Sonstiger Grosshandel",
    "sg:phone":"+41 34 411 06 17",
    "sg:postcode":"3324",
    "sg:province":"Bern",
    "wof:name":"Royal Impex, Schmuck",
    "wof:placetype":"venue"
},
  "geometry": {"coordinates":[7.5408668518,47.0462226868],"type":"Point"}
}