{
  "type": "Feature",
  "properties": {
    "iso:country":"CH",
    "sg:address":"Houelbachstrasse 6",
    "sg:city":"Kriens",
    "sg:orig_category":"Interessenvertretungen",
    "sg:postcode":"6010",
    "sg:province":"Luzern",
    "wof:name":"Verein Zur F\u00f6rderung Asiatischer Kultur Und Handwerk",
    "wof:placetype":"venue"
},
  "geometry": {"coordinates":[8.2710666656,47.0302238464],"type":"Point"}
}