{
  "type": "Feature",
  "properties": {
    "iso:country":"CH",
    "sg:address":"1936",
    "sg:city":"Verbier",
    "sg:orig_category":"HOTELS: OHNE RESTAURANT",
    "sg:phone":"+41 27 771 63 64",
    "sg:postcode":"1936",
    "sg:province":"Valais",
    "wof:name":"H\u00f4tel Rois Mages",
    "wof:placetype":"venue"
},
  "geometry": {"coordinates":[7.2229599953,46.0967216492],"type":"Point"}
}