{
  "type": "Feature",
  "properties": {
    "iso:country":"CH",
    "sg:address":"Grand-rue 134",
    "sg:city":"Tramelan",
    "sg:orig_category":"Detailhandel mit Fleisch U Fleischwaren",
    "sg:postcode":"2720",
    "sg:province":"Bern",
    "wof:name":"Tuor Michel",
    "wof:placetype":"venue"
},
  "geometry": {"coordinates":[6.9953799248,46.2966117859],"type":"Point"}
}