{
  "type": "Feature",
  "properties": {
    "iso:country":"CH",
    "sg:address":"Rue Des Creusets 46 1950 Sion Case Postale 748",
    "sg:city":"Sion",
    "sg:orig_category":"Grosshandel mit sonstigen Nahrungsmitteln",
    "sg:phone":"+41 27 322 15 52",
    "sg:postcode":"1951",
    "sg:province":"Valais",
    "wof:name":"Organisation Deval J.& F.revaz Grossiste En Confiserie",
    "wof:placetype":"venue"
},
  "geometry": {"coordinates":[7.3554267883,46.2276954651],"type":"Point"}
}