{
  "type": "Feature",
  "properties": {
    "iso:country":"CH",
    "sg:address":"Sutvitg",
    "sg:city":"Vella",
    "sg:orig_category":"Bauschreinerei",
    "sg:phone":"+41 81 931 13 10",
    "sg:postcode":"7144",
    "sg:province":"Graubunden",
    "wof:name":"Alfons Cavegn Schreinerei",
    "wof:placetype":"venue"
},
  "geometry": {"coordinates":[9.174072,46.717064],"type":"Point"}
}