{
  "type": "Feature",
  "properties": {
    "iso:country":"CH",
    "sg:address":"Voltastrasse 35",
    "sg:city":"Luzern",
    "sg:orig_category":"Primarschulen",
    "sg:phone":"+41 41 310 12 76",
    "sg:postcode":"6005",
    "sg:province":"Luzern",
    "wof:name":"Primarschule Moosmatt",
    "wof:placetype":"venue"
},
  "geometry": {"coordinates":[8.3050069809,47.0396881104],"type":"Point"}
}