{
  "type": "Feature",
  "properties": {
    "iso:country":"CH",
    "sg:address":"Boulevard James-fazy 14",
    "sg:city":"Gen\u00e8ve",
    "sg:orig_category":"Detailhandel mit Uhren U Schmuck",
    "sg:phone":"+41 22 900 10 10",
    "sg:postcode":"1201",
    "sg:province":"Gen\u00e8ve",
    "wof:name":"Callas Bijouterie Cr\u00e9ation",
    "wof:placetype":"venue"
},
  "geometry": {"coordinates":[6.1406240463,46.2078361511],"type":"Point"}
}