{
  "type": "Feature",
  "properties": {
    "iso:country":"CH",
    "sg:address":"Chesa Quadrella",
    "sg:city":"Pontresina",
    "sg:orig_category":"Unclassifiable Establishments",
    "sg:phone":"+41 81 842 71 55",
    "sg:postcode":"7504",
    "sg:province":"Graubunden",
    "wof:name":"Pontresina Events Gmbh",
    "wof:placetype":"venue"
},
  "geometry": {"coordinates":[9.9011316299,46.4946479797],"type":"Point"}
}