{
  "type": "Feature",
  "properties": {
    "iso:country":"CH",
    "sg:address":"Isenrietstrasse 25",
    "sg:city":"M\u00f6nchaltorf",
    "sg:orig_category":"Sonstiger Grosshandel",
    "sg:phone":"+41 41 870 00 80",
    "sg:postcode":"8617",
    "sg:province":"Z\u00fcrich",
    "wof:name":"Baumann Milo",
    "wof:placetype":"venue"
},
  "geometry": {"coordinates":[8.614033699,46.8825302124],"type":"Point"}
}