{
  "type": "Feature",
  "properties": {
    "iso:country":"CH",
    "sg:address":"Sportplatzstrasse 1",
    "sg:city":"Amriswil",
    "sg:classifiers":[
        {
            "category":"Travel",
            "subcategory":"Hotels & Motels",
            "type":"Entertainment"
        }
    ],
    "sg:phone":"+41 71 411 41 21",
    "sg:postcode":"8580",
    "sg:province":"Thurgau",
    "sg:tags":[
        "hotels",
        "mit",
        "restaurant"
    ],
    "wof:name":"Byblos Golf-hotel",
    "wof:placetype":"venue"
},
  "geometry": {"coordinates":[9.2905502319,47.5451087952],"type":"Point"}
}