{
  "type": "Feature",
  "properties": {
    "iso:country":"CH",
    "sg:address":"Berglistrasse 28 8616 Riedikon. Postfach",
    "sg:city":"Riedikon",
    "sg:orig_category":"Herstellung von Elektrizit\u00e4tsverteilungs U schalteinrichtungen",
    "sg:phone":"+41 19424302",
    "sg:postcode":"8616",
    "sg:province":"Z\u00fcrich",
    "wof:name":"Messmatik Hiltbrunner",
    "wof:placetype":"venue"
},
  "geometry": {"coordinates":[8.712389946,47.3305015564],"type":"Point"}
}