{
  "type": "Feature",
  "properties": {
    "addr:full":"Pilatusstrasse 4 6010 Kriens. Postfach 305 Kriens Luzern 6011",
    "addr:housenumber":"4;305",
    "addr:postcode":"6010 kriens.;6011",
    "addr:street":"Pilatusstrasse;Postfach",
    "iso:country":"CH",
    "sg:address":"Pilatusstrasse 4 6010 Kriens. Postfach 305",
    "sg:city":"Kriens",
    "sg:orig_category":"Architekturb\u00fcros",
    "sg:phone":"+41 41 310 41 12",
    "sg:postcode":"6011",
    "sg:province":"Luzern",
    "wof:name":"Werner Schriber Architekturb\u00fcro",
    "wof:placetype":"venue"
},
  "geometry": {"coordinates":[8.289683,47.034058],"type":"Point"}
}