{
  "type": "Feature",
  "properties": {
    "iso:country":"CH",
    "sg:address":"Florhofstrasse 15 8820 W\u00e4denswil. Postfach 217",
    "sg:city":"W\u00e4denswil",
    "sg:orig_category":"Instandhaltung U Reparatur von Automobilen",
    "sg:phone":"+41 17839600",
    "sg:postcode":"8820",
    "sg:province":"Z\u00fcrich",
    "wof:name":"Delta-garage W\u00e4denswil Ag",
    "wof:placetype":"venue"
},
  "geometry": {"coordinates":[8.6701488495,47.2311515808],"type":"Point"}
}