{
  "type": "Feature",
  "properties": {
    "iso:country":"CH",
    "sg:address":"Bahnhofstrasse 35",
    "sg:city":"Grenchen",
    "sg:orig_category":"Detailhandel mit Brillen U anderen Sehhilfen Fachdetailhandel in Verkaufsr\u00e4umen",
    "sg:phone":"+41 21 944 26 22",
    "sg:postcode":"2540",
    "sg:province":"Solothurn",
    "wof:name":"Monnier, J.",
    "wof:placetype":"venue"
},
  "geometry": {"coordinates":[6.85684,46.453362],"type":"Point"}
}