{
  "type": "Feature",
  "properties": {
    "iso:country":"CH",
    "sg:address":"Rue Du Ch\u00e2teau 6",
    "sg:city":"Corsier-sur-vevey",
    "sg:orig_category":"Grosshandel mit Wein U Spirituosen",
    "sg:phone":"+41 21 922 05 90",
    "sg:postcode":"1804",
    "sg:province":"Vaud",
    "wof:name":"Fran\u00e7ois Hoehn Courtage En Vins",
    "wof:placetype":"venue"
},
  "geometry": {"coordinates":[6.8450508118,46.4701118469],"type":"Point"}
}