{
  "type": "Feature",
  "properties": {
    "iso:country":"CH",
    "sg:address":"Birkenstrasse 74",
    "sg:city":"Engelberg",
    "sg:orig_category":"Sonstige mit Sport verbundene T\u00e4tigkeiten",
    "sg:postcode":"6390",
    "sg:province":"Obwalden",
    "wof:name":"Stiftung Schweizerische Sportmittelschule Engelberg",
    "wof:placetype":"venue"
},
  "geometry": {"coordinates":[8.395401001,46.8170127869],"type":"Point"}
}