{
  "type": "Feature",
  "properties": {
    "iso:country":"CH",
    "sg:address":"Zugerstrasse 73",
    "sg:city":"Horgen",
    "sg:orig_category":"Detailhandel mit Radio U Fernsehger\u00e4ten Detailhandel mit elektrischen Haushalts-,Radio U Fernsehger\u00e4",
    "sg:phone":"+41 17251703",
    "sg:postcode":"8810",
    "sg:province":"Z\u00fcrich",
    "wof:name":"Wegm\u00fcller Paul",
    "wof:placetype":"venue"
},
  "geometry": {"coordinates":[8.6015825272,47.2565612793],"type":"Point"}
}