{
  "type": "Feature",
  "properties": {
    "iso:country":"CH",
    "sg:address":"Via Rinaldo Simen 9",
    "sg:city":"Chiasso",
    "sg:orig_category":"Vermietung U Verpachtung von eigenen Immobilien",
    "sg:postcode":"6830",
    "sg:province":"Ticino",
    "wof:name":"Macesa Immobiliare Sa",
    "wof:placetype":"venue"
},
  "geometry": {"coordinates":[9.0255231857,45.8381271362],"type":"Point"}
}