{
  "type": "Feature",
  "properties": {
    "iso:country":"CH",
    "sg:address":"Hanfl\u00e4nderstrasse 8880 Walenstadt. Postfach",
    "sg:city":"Berschis",
    "sg:orig_category":"Hardwareberatung",
    "sg:postcode":"8892",
    "sg:province":"St. Gallen",
    "wof:name":"Ecs Frei Arthur",
    "wof:placetype":"venue"
},
  "geometry": {"coordinates":[9.3422060013,47.111038208],"type":"Point"}
}