{
  "type": "Feature",
  "properties": {
    "addr:full":"Glarnerstrasse 33 Siebnen Schwyz 8854",
    "addr:housenumber":"33",
    "addr:postcode":"8854",
    "addr:street":"Glarnerstrasse;Schwyz",
    "iso:country":"CH",
    "sg:address":"Glarnerstrasse 33",
    "sg:city":"Siebnen",
    "sg:orig_category":"Detailhandel mit B\u00fcromaschinen U einrichtungen Detailhandel mit M\u00f6beln",
    "sg:phone":"+41 41 252 08 08",
    "sg:postcode":"8854",
    "sg:province":"Schwyz",
    "wof:name":"Marghitola Immobilien Ag",
    "wof:placetype":"venue"
},
  "geometry": {"coordinates":[8.304102,47.051785],"type":"Point"}
}