{
  "type": "Feature",
  "properties": {
    "addr:full":"Hauptstrasse 45 Niederurnen Glarus 8867",
    "addr:housenumber":"45",
    "addr:postcode":"8867",
    "addr:street":"Hauptstrasse",
    "iso:country":"CH",
    "sg:address":"Hauptstrasse 45",
    "sg:city":"Niederurnen",
    "sg:orig_category":"Autofahrschulen",
    "sg:phone":"+41 61 811 22 00",
    "sg:postcode":"8867",
    "sg:province":"Glarus",
    "wof:name":"Markus Keller-trevisan Liebr\u00fcti-fahrschule",
    "wof:placetype":"venue"
},
  "geometry": {"coordinates":[7.599985,47.471359],"type":"Point"}
}