{
  "type": "Feature",
  "properties": {
    "iso:country":"CH",
    "sg:address":"Hauptstrasse 17 9436 Balgach. Postfach",
    "sg:city":"Balgach",
    "sg:orig_category":"Softwareentwicklung U beratung",
    "sg:phone":"+41 71 720 19 44",
    "sg:postcode":"9436",
    "sg:province":"St. Gallen",
    "wof:name":"Eprogress Paschek - Software Entwicklung",
    "wof:placetype":"venue"
},
  "geometry": {"coordinates":[9.6110191345,47.4075584412],"type":"Point"}
}