{
  "type": "Feature",
  "properties": {
    "iso:country":"CH",
    "sg:address":"Immeuble Central B",
    "sg:city":"Chermignon",
    "sg:orig_category":"Unclassifiable Establishments",
    "sg:postcode":"3971",
    "sg:province":"Valais",
    "wof:name":"Potamos Sa",
    "wof:placetype":"venue"
},
  "geometry": {"coordinates":[7.473965168,46.2884407043],"type":"Point"}
}