{
  "type": "Feature",
  "properties": {
    "iso:country":"CH",
    "sg:address":"Aeussere Poststrasse 7050 Arosa. Postfach 363",
    "sg:city":"Arosa",
    "sg:classifiers":[
        {
            "category":"Travel",
            "subcategory":"Hotels & Motels",
            "type":"Entertainment"
        }
    ],
    "sg:phone":"+41 81 377 12 16",
    "sg:postcode":"7050",
    "sg:province":"Graubunden",
    "sg:tags":[
        "hotels",
        "mit",
        "restaurant"
    ],
    "wof:name":"Hotel Obersee",
    "wof:placetype":"venue"
},
  "geometry": {"coordinates":[9.6832551956,46.783164978],"type":"Point"}
}