{
  "type": "Feature",
  "properties": {
    "addr:full":"Glattalstrasse 501 R\u00fcmlang Z\u00fcrich 8153",
    "addr:housenumber":"501",
    "addr:postcode":"8153",
    "addr:street":"Glattalstrasse;Zuerich",
    "iso:country":"CH",
    "sg:address":"Glattalstrasse 501",
    "sg:city":"R\u00fcmlang",
    "sg:orig_category":"Bauschreinerei Herstellung von Konstruktionsteilen, Fertigbauteilen U Ausbauelementen aus Holz",
    "sg:phone":"+41 18171801",
    "sg:postcode":"8153",
    "sg:province":"Z\u00fcrich",
    "wof:name":"Daniel Merkli Schreinerei",
    "wof:placetype":"venue"
},
  "geometry": {"coordinates":[8.542779,47.433594],"type":"Point"}
}