{
  "type": "Feature",
  "properties": {
    "addr:full":"Gaiserau 40a Gais Appenzell Ausserrhoden 9056",
    "addr:housenumber":"40a",
    "addr:postcode":"9056",
    "addr:street":"Gaiserau;Appenzell Ausserrhoden",
    "iso:country":"CH",
    "sg:address":"Gaiserau 40a",
    "sg:city":"Gais",
    "sg:classifiers":[
        {
            "category":"Retail",
            "subcategory":"Repair Shop",
            "type":"Services"
        }
    ],
    "sg:phone":"+41 71 793 20 17",
    "sg:postcode":"9056",
    "sg:province":"Appenzell Ausserrhoden",
    "sg:tags":[
        "agricultural",
        "machinery"
    ],
    "wof:name":"H\u00f6hener Landmaschinen Ag",
    "wof:placetype":"venue"
},
  "geometry": {"coordinates":[9.451269,47.359482],"type":"Point"}
}