{
  "type": "Feature",
  "properties": {
    "iso:country":"CH",
    "sg:address":"Route De Sorvilier 21b",
    "sg:city":"B\u00e9vilard",
    "sg:orig_category":"Bauschreinerei Herstellung von M\u00f6beln verschiedener Art",
    "sg:phone":"+41 79 250 35 38",
    "sg:postcode":"2735",
    "sg:province":"Bern",
    "wof:name":"Sfdm S\u00e0rl Menuiserie & Charpente",
    "wof:placetype":"venue"
},
  "geometry": {"coordinates":[7.292384,47.240089],"type":"Point"}
}