{
  "type": "Feature",
  "properties": {
    "iso:country":"CH",
    "sg:address":"Morgentalstrasse 34",
    "sg:city":"Aadorf",
    "sg:orig_category":"Instandhaltung U Reparatur von Automobilen",
    "sg:phone":"+41 52 365 11 49",
    "sg:postcode":"8355",
    "sg:province":"Thurgau",
    "wof:name":"Garage M\u00fcller P.",
    "wof:placetype":"venue"
},
  "geometry": {"coordinates":[8.8960943222,47.4940986633],"type":"Point"}
}