{
  "type": "Feature",
  "properties": {
    "iso:country":"CH",
    "sg:address":"Soldanella Pany.",
    "sg:city":"Luzein",
    "sg:orig_category":"Allgemeiner Hoch U Tiefbau",
    "sg:postcode":"7242",
    "sg:province":"Graubunden",
    "wof:name":"Nizolino Ag",
    "wof:placetype":"venue"
},
  "geometry": {"coordinates":[7.824348,47.236748],"type":"Point"}
}