{
  "type": "Feature",
  "properties": {
    "iso:country":"CH",
    "sg:address":"Trottenstrasse 27",
    "sg:city":"Z\u00fcrich",
    "sg:orig_category":"Kosmetikinstitute",
    "sg:phone":"+41 12713284",
    "sg:postcode":"8037",
    "sg:province":"Z\u00fcrich",
    "wof:name":"Beaut\u00e9 Les Trouvailles",
    "wof:placetype":"venue"
},
  "geometry": {"coordinates":[8.5222625732,47.3949623108],"type":"Point"}
}