{
  "type": "Feature",
  "properties": {
    "iso:country":"CH",
    "sg:address":"Rue Du Perron 10",
    "sg:city":"Coppet",
    "sg:orig_category":"Dachdeckerei Herstellung von sonstigen Metallwaren",
    "sg:phone":"+41 41 240 22 70",
    "sg:postcode":"1296",
    "sg:province":"Vaud",
    "wof:name":"Sch\u00e4fer Stammbach Partner Ag",
    "wof:placetype":"venue"
},
  "geometry": {"coordinates":[8.298186,47.049011],"type":"Point"}
}