{
  "type": "Feature",
  "properties": {
    "iso:country":"CH",
    "sg:address":"Via Principala 692 7175 Sumvitg. Postfach",
    "sg:city":"Rabius",
    "sg:orig_category":"Herstellung von konfektionierten Textilwaren ohne Bekleidung",
    "sg:phone":"+41 81 943 16 30",
    "sg:postcode":"7172",
    "sg:province":"Graubunden",
    "wof:name":"Casada Decor Atelier, Bearth Silvia",
    "wof:placetype":"venue"
},
  "geometry": {"coordinates":[8.9354410172,46.7268486023],"type":"Point"}
}