{
  "type": "Feature",
  "properties": {
    "iso:country":"CH",
    "sg:address":"Neuhusweg 1",
    "sg:city":"Kaufdorf",
    "sg:orig_category":"Haltung von Schweinen",
    "sg:phone":"+41 71 761 13 67",
    "sg:postcode":"3126",
    "sg:province":"Bern",
    "wof:name":"K\u00e4mobag Ag, Oberriet",
    "wof:placetype":"venue"
},
  "geometry": {"coordinates":[9.563835144,47.3275184631],"type":"Point"}
}