{
  "type": "Feature",
  "properties": {
    "iso:country":"CH",
    "sg:address":"Bahnhofstr. 8",
    "sg:city":"Menziken",
    "sg:classifiers":[
        {
            "category":"Manufacturing",
            "subcategory":"Paper Products",
            "type":"Manufacturing & Wholesale Goods"
        }
    ],
    "sg:phone":"+41 62 771 14 27",
    "sg:postcode":"5737",
    "sg:province":"Aargau",
    "sg:tags":[
        "packaging",
        "material",
        "-",
        "cardboard"
    ],
    "wof:name":"Weber Druck U Kartonage Ag",
    "wof:placetype":"venue"
},
  "geometry": {"coordinates":[8.1887540817,47.2411384583],"type":"Point"}
}