{
  "type": "Feature",
  "properties": {
    "iso:country":"CH",
    "sg:address":"Wattstrasse 15 8050 Z\u00fcrich. Postfach",
    "sg:city":"Z\u00fcrich",
    "sg:orig_category":"Detailhandel mit Musikinstrumenten",
    "sg:phone":"+41 71 911 05 54",
    "sg:postcode":"8050",
    "sg:province":"Z\u00fcrich",
    "wof:name":"Fritz Felix Musikhaus",
    "wof:placetype":"venue"
},
  "geometry": {"coordinates":[9.0478105545,47.4653396606],"type":"Point"}
}