{
  "type": "Feature",
  "properties": {
    "iso:country":"CH",
    "sg:address":"Matzingerstrasse 2",
    "sg:city":"Thundorf",
    "sg:classifiers":[
        {
            "category":"Restaurant",
            "type":"Food & Drink"
        }
    ],
    "sg:phone":"+41 52 376 31 31",
    "sg:postcode":"8512",
    "sg:province":"Thurgau",
    "wof:name":"Restaurant Helvetia",
    "wof:placetype":"venue"
},
  "geometry": {"coordinates":[8.9631671906,47.545211792],"type":"Point"}
}