{
  "type": "Feature",
  "properties": {
    "iso:country":"CH",
    "sg:address":"Br\u00fcnneli 22 8124 Maur. Postfach",
    "sg:city":"Forch",
    "sg:orig_category":"Herstellung von k\u00e4lte U lufttechnischen Erzeugnissen f\u00fcr gewerbliche Zwecke",
    "sg:postcode":"8127",
    "sg:province":"Z\u00fcrich",
    "wof:name":"Mami\u00e9 Ren\u00e9, L\u00fcftungen - Spenglerei",
    "wof:placetype":"venue"
},
  "geometry": {"coordinates":[8.6077957153,46.8810882568],"type":"Point"}
}