{
  "type": "Feature",
  "properties": {
    "iso:country":"CH",
    "sg:address":"G\u00e4ssli",
    "sg:city":"Giffers",
    "sg:orig_category":"Erwachsenenbildung U Unterricht",
    "sg:postcode":"1735",
    "sg:province":"Fribourg",
    "wof:name":"Schafer Marie-claire",
    "wof:placetype":"venue"
},
  "geometry": {"coordinates":[7.2086567879,46.7622451782],"type":"Point"}
}