{
  "type": "Feature",
  "properties": {
    "iso:country":"CH",
    "sg:address":"1514",
    "sg:city":"Bussy-sur-moudon",
    "sg:orig_category":"Bauschreinerei M\u00f6belschreinerei",
    "sg:phone":"+41 21 905 48 33",
    "sg:postcode":"1514",
    "sg:province":"Vaud",
    "wof:name":"Dellai Fr\u00e8res Menuiserie & \u00e9b\u00e9nisterie",
    "wof:placetype":"venue"
},
  "geometry": {"coordinates":[6.80887,46.691212],"type":"Point"}
}