{
  "type": "Feature",
  "properties": {
    "iso:country":"CH",
    "sg:address":"H\u00f6henweg 9",
    "sg:city":"Lostorf",
    "sg:orig_category":"Architekturb\u00fcros",
    "sg:phone":"+41 62 298 10 55",
    "sg:postcode":"4654",
    "sg:province":"Solothurn",
    "wof:name":"Anja K. Heer Architekturb\u00fcro",
    "wof:placetype":"venue"
},
  "geometry": {"coordinates":[7.944176,47.390968],"type":"Point"}
}