{
  "type": "Feature",
  "properties": {
    "iso:country":"CH",
    "sg:address":"L\u00fceholzstrasse 26",
    "sg:city":"Hombrechtikon",
    "sg:orig_category":"Grosshandel mit B\u00fcromaschinen Grosshandel mit Datenverarbeitungsger\u00e4ten",
    "sg:phone":"+41 55 244 30 57",
    "sg:postcode":"8634",
    "sg:province":"Z\u00fcrich",
    "wof:name":"Ensobre Ag Engineering Software",
    "wof:placetype":"venue"
},
  "geometry": {"coordinates":[8.7637853622,47.2499237061],"type":"Point"}
}