{
  "type": "Feature",
  "properties": {
    "iso:country":"CH",
    "sg:address":"Rubiswilstrasse 8",
    "sg:city":"Ibach",
    "sg:orig_category":"Berufsberatungen",
    "sg:phone":"+41 41 819 11 24",
    "sg:postcode":"6438",
    "sg:province":"Schwyz",
    "wof:name":"Berufs- + Studienberatung",
    "wof:placetype":"venue"
},
  "geometry": {"coordinates":[8.648467,47.016617],"type":"Point"}
}