{
  "type": "Feature",
  "properties": {
    "iso:country":"CH",
    "sg:address":"Toggwilerstrasse 38",
    "sg:city":"Meilen",
    "sg:orig_category":"Saunas Schwimmb\u00e4der",
    "sg:phone":"+41 33 243 24 33",
    "sg:postcode":"8706",
    "sg:province":"Z\u00fcrich",
    "wof:name":"Hallenbad Und Fitnesscenter Oberhofen",
    "wof:placetype":"venue"
},
  "geometry": {"coordinates":[9.0390996933,47.2317276001],"type":"Point"}
}