{
  "type": "Feature",
  "properties": {
    "iso:country":"CH",
    "sg:address":"Gerberngasse 43 3011 Bern. Postfach",
    "sg:city":"Bern",
    "sg:orig_category":"Grosshandel mit Nahrungsmitteln, Getr\u00e4nken U Tabakwaren ohne ausgepr\u00e4gten Schwerpunkt",
    "sg:postcode":"3005",
    "sg:province":"Bern",
    "wof:name":"Di Rubba Frau. Lebensmittelhandel.",
    "wof:placetype":"venue"
},
  "geometry": {"coordinates":[7.4566311836,46.947265625],"type":"Point"}
}