{
  "type": "Feature",
  "properties": {
    "iso:country":"CH",
    "sg:address":"Mugerenstrasse 87",
    "sg:city":"Cham",
    "sg:orig_category":"Wirtschaftspr\u00fcfung, Steuerberatung U Treuhand",
    "sg:postcode":"6330",
    "sg:province":"Zug",
    "wof:name":"Pasadega Gmbh",
    "wof:placetype":"venue"
},
  "geometry": {"coordinates":[8.4660749435,47.1866760254],"type":"Point"}
}