{
  "type": "Feature",
  "properties": {
    "iso:country":"CH",
    "sg:address":"Schulstrasse 40",
    "sg:city":"Wiesendangen",
    "sg:orig_category":"Organisationen des Gesundheitswesen",
    "sg:phone":"+41 52 337 32 53",
    "sg:postcode":"8542",
    "sg:province":"Z\u00fcrich",
    "wof:name":"Samariterverein O'winterthur",
    "wof:placetype":"venue"
},
  "geometry": {"coordinates":[8.7909698486,47.5220413208],"type":"Point"}
}