{
  "type": "Feature",
  "properties": {
    "iso:country":"CH",
    "sg:address":"Rue Th\u00e9odore-lissignol 12",
    "sg:city":"Gen\u00e8ve",
    "sg:orig_category":"Hundesalons",
    "sg:phone":"+41 19105248",
    "sg:postcode":"1201",
    "sg:province":"Gen\u00e8ve",
    "wof:name":"Linda Faoro Hundesalon Bella",
    "wof:placetype":"venue"
},
  "geometry": {"coordinates":[8.5751886368,47.3280754089],"type":"Point"}
}