{
  "type": "Feature",
  "properties": {
    "addr:full":"Chemin Vuillonnex 65 Confignon Gen\u00e8ve 1232",
    "addr:housenumber":"65",
    "addr:postcode":"1232",
    "addr:street":"Chemin Vuillonnex",
    "iso:country":"CH",
    "sg:address":"Chemin Vuillonnex 65",
    "sg:city":"Confignon",
    "sg:orig_category":"Bauspenglerei Sanit\u00e4rinstallation U Spenglerei",
    "sg:phone":"+41 78 628 63 63",
    "sg:postcode":"1232",
    "sg:province":"Gen\u00e8ve",
    "wof:name":"Ren\u00e9 Jaggi T\u00f4lerie & Ventilation",
    "wof:placetype":"venue"
},
  "geometry": {"coordinates":[6.080425,46.173443],"type":"Point"}
}