{
  "type": "Feature",
  "properties": {
    "iso:country":"CH",
    "sg:address":"Paulistrasse 95",
    "sg:city":"Schindellegi",
    "sg:orig_category":"Non-Classified Establishments",
    "sg:postcode":"8834",
    "sg:province":"Schwyz",
    "wof:name":"Turicum Holding Ag",
    "wof:placetype":"venue"
},
  "geometry": {"coordinates":[8.7137823105,47.1808319092],"type":"Point"}
}