{
  "type": "Feature",
  "properties": {
    "iso:country":"CH",
    "sg:address":"Z\u00fcrcherstrasse 23",
    "sg:city":"Tagelswangen",
    "sg:orig_category":"Autogaragen",
    "sg:phone":"+41 52 343 63 76",
    "sg:postcode":"8317",
    "sg:province":"Z\u00fcrich",
    "wof:name":"Xaver Z\u00fcrcher Autoreparaturwerkstatt",
    "wof:placetype":"venue"
},
  "geometry": {"coordinates":[8.673995,47.431133],"type":"Point"}
}