{
  "type": "Feature",
  "properties": {
    "addr:full":"Feldeggstrasse 43 8008 Z\u00fcrich. Postfach Z\u00fcrich Z\u00fcrich 8001",
    "addr:housenumber":"43",
    "addr:postcode":"8008 zuerich. postfach;8001",
    "addr:street":"Feldeggstrasse",
    "iso:country":"CH",
    "sg:address":"Feldeggstrasse 43 8008 Z\u00fcrich. Postfach",
    "sg:city":"Z\u00fcrich",
    "sg:orig_category":"Sonstiger Grosshandel",
    "sg:phone":"+41 13832654",
    "sg:postcode":"8001",
    "sg:province":"Z\u00fcrich",
    "wof:name":"Iten Aug. Ag Manufakturwaren; Handel, Imp., Exp. Textilagentur",
    "wof:placetype":"venue"
},
  "geometry": {"coordinates":[8.551684,47.360397],"type":"Point"}
}