{
  "type": "Feature",
  "properties": {
    "iso:country":"CH",
    "sg:address":"Ueberbielstr. 10",
    "sg:city":"Visp",
    "sg:classifiers":[
        {
            "category":"Banks & Credit Unions",
            "subcategory":"Bank",
            "type":"Services"
        }
    ],
    "sg:phone":"+41 27 946 62 62",
    "sg:postcode":"3930",
    "sg:province":"Valais",
    "wof:name":"Raiffeisenbank",
    "wof:placetype":"venue"
},
  "geometry": {"coordinates":[7.882918,46.290989],"type":"Point"}
}