{
  "type": "Feature",
  "properties": {
    "iso:country":"CH",
    "sg:address":"Leopoldstrasse 6",
    "sg:city":"Sursee",
    "sg:orig_category":"Lagerh\u00e4user, G\u00fcterumschlag, Verteilzentren",
    "sg:postcode":"6210",
    "sg:province":"Luzern",
    "wof:name":"Dayuto Ag",
    "wof:placetype":"venue"
},
  "geometry": {"coordinates":[8.0987510681,47.1721496582],"type":"Point"}
}