{
  "type": "Feature",
  "properties": {
    "iso:country":"CH",
    "sg:address":"Bolengasse 3",
    "sg:city":"Glarus",
    "sg:orig_category":"Grosshandel mit Textilien",
    "sg:phone":"+41 55 640 83 30",
    "sg:postcode":"8750",
    "sg:province":"Glarus",
    "wof:name":"Textil Kuhn-baer Fredy",
    "wof:placetype":"venue"
},
  "geometry": {"coordinates":[9.0659475327,47.0393028259],"type":"Point"}
}