{
  "type": "Feature",
  "properties": {
    "iso:country":"CH",
    "sg:address":"Via Brione 6648 Minusio. Postfach Casa Postale",
    "sg:city":"Minusio",
    "sg:orig_category":"RESTAURANTS: TEA-ROOMS",
    "sg:postcode":"6648",
    "sg:province":"Ticino",
    "wof:name":"Martinoni Francesco, Ristorante Carmine.",
    "wof:placetype":"venue"
},
  "geometry": {"coordinates":[8.8107013702,46.1791038513],"type":"Point"}
}