{
  "type": "Feature",
  "properties": {
    "iso:country":"CH",
    "sg:address":"Zeughausstrasse 61",
    "sg:city":"Z\u00fcrich",
    "sg:orig_category":"RESTAURANTS: TEA-ROOMS",
    "sg:phone":"+41 12414339",
    "sg:postcode":"8004",
    "sg:province":"Z\u00fcrich",
    "wof:name":"Di Chiara Claudio, Ristorante Italia",
    "wof:placetype":"venue"
},
  "geometry": {"coordinates":[8.5292339325,47.3763656616],"type":"Point"}
}