{
  "type": "Feature",
  "properties": {
    "iso:country":"CH",
    "sg:address":"Murtenstrasse 350 3000 Bern. Postfach",
    "sg:city":"Bern",
    "sg:orig_category":"Finanzierungsinstitutionen",
    "sg:phone":"+41 21 944 92 05",
    "sg:postcode":"3000",
    "sg:province":"Bern",
    "wof:name":"Jaeger Jacqueline",
    "wof:placetype":"venue"
},
  "geometry": {"coordinates":[6.871735096,46.4482192993],"type":"Point"}
}