{
  "type": "Feature",
  "properties": {
    "iso:country":"CH",
    "sg:address":"Hauptstrasse 62",
    "sg:city":"Sch\u00f6nengrund",
    "sg:classifiers":[
        {
            "category":"Restaurant",
            "type":"Food & Drink"
        }
    ],
    "sg:phone":"+41 71 361 15 11",
    "sg:postcode":"9105",
    "sg:province":"Appenzell Ausserrhoden",
    "wof:name":"Expressbar",
    "wof:placetype":"venue"
},
  "geometry": {"coordinates":[9.2297687531,47.3303260803],"type":"Point"}
}