{
  "type": "Feature",
  "properties": {
    "iso:country":"CH",
    "sg:address":"Werkhofstrasse 29c",
    "sg:city":"Solothurn",
    "sg:orig_category":"Kauf U Verkauf von Immobilien auf eigene Rechnung",
    "sg:postcode":"4500",
    "sg:province":"Solothurn",
    "wof:name":"R\u00f6tihof Ag",
    "wof:placetype":"venue"
},
  "geometry": {"coordinates":[7.5367388725,47.2106323242],"type":"Point"}
}