{
  "type": "Feature",
  "properties": {
    "addr:full":"Hauptstrasse 5 Hochdorf Luzern 6280",
    "addr:housenumber":"5",
    "addr:postcode":"6280",
    "addr:street":"Hauptstrasse",
    "iso:country":"CH",
    "sg:address":"Hauptstrasse 5",
    "sg:city":"Hochdorf",
    "sg:orig_category":"Arztpraxen",
    "sg:phone":"+41 33 951 25 25",
    "sg:postcode":"6280",
    "sg:province":"Luzern",
    "wof:name":"Dr.med.kaspar L\u00fcthi Arzt F.allgemeine Medizin Fmh",
    "wof:placetype":"venue"
},
  "geometry": {"coordinates":[8.055492,46.759052],"type":"Point"}
}