{
  "type": "Feature",
  "properties": {
    "iso:country":"CH",
    "sg:address":"Grand-rue 53 1890 St-maurice. Postfach",
    "sg:city":"St-maurice",
    "sg:orig_category":"RESTAURANTS: TEA-ROOMS",
    "sg:postcode":"1890",
    "sg:province":"Valais",
    "wof:name":"Bongiovanni Roberta",
    "wof:placetype":"venue"
},
  "geometry": {"coordinates":[7.0044221878,46.2190284729],"type":"Point"}
}