{
  "type": "Feature",
  "properties": {
    "iso:country":"CH",
    "sg:address":"Centro Carvina 6",
    "sg:city":"Taverne",
    "sg:classifiers":[
        {
            "category":"Building & Trades",
            "subcategory":"Construction",
            "type":"Services"
        }
    ],
    "sg:phone":"+41 91 930 91 00",
    "sg:postcode":"6807",
    "sg:province":"Ticino",
    "sg:tags":[
        "insulating",
        "material",
        "engineering"
    ],
    "wof:name":"Edilconsulto",
    "wof:placetype":"venue"
},
  "geometry": {"coordinates":[8.9333286285,46.0671730042],"type":"Point"}
}