{
  "type": "Feature",
  "properties": {
    "addr:full":"Friedrichstrasse 21 Basel Basel-Stadt 4055",
    "addr:housenumber":"21",
    "addr:postcode":"4055",
    "addr:street":"Friedrichstrasse",
    "iso:country":"CH",
    "sg:address":"Friedrichstrasse 21",
    "sg:city":"Basel",
    "sg:orig_category":"Arztpraxen",
    "sg:phone":"+41 61 303 08 93",
    "sg:postcode":"4055",
    "sg:province":"Basel-Stadt",
    "wof:name":"Dr.med.rita Albiez Aerztin F.allgemeine Medizin",
    "wof:placetype":"venue"
},
  "geometry": {"coordinates":[7.574658,47.556805],"type":"Point"}
}