{
  "type": "Feature",
  "properties": {
    "iso:country":"CH",
    "sg:address":"Punto Franco 6593 Cadenazzo Casella Postale 59",
    "sg:city":"Cadenazzo",
    "sg:orig_category":"Autotransporte international",
    "sg:phone":"+41 91 858 17 25",
    "sg:postcode":"6593",
    "sg:province":"Ticino",
    "wof:name":"Mat Transport Ag",
    "wof:placetype":"venue"
},
  "geometry": {"coordinates":[8.952302,46.149578],"type":"Point"}
}