{
  "type": "Feature",
  "properties": {
    "iso:country":"CH",
    "sg:address":"Uhwiesenstrasse 23",
    "sg:city":"Feuerthalen",
    "sg:orig_category":"Detailhandel mit Damenbekleidung",
    "sg:phone":"+41 52 659 21 28",
    "sg:postcode":"8245",
    "sg:province":"Z\u00fcrich",
    "wof:name":"Brigitt's Schmuck & Shirt Box",
    "wof:placetype":"venue"
},
  "geometry": {"coordinates":[8.643485,47.693035],"type":"Point"}
}