{
  "type": "Feature",
  "properties": {
    "iso:country":"CH",
    "sg:address":"Oberlandstrasse 44",
    "sg:city":"Spiez",
    "sg:orig_category":"Grosshandel mit Eisenwaren sowie Installationsbedarf f\u00fcr Gas, Wasser U Heizung Grosshandel mit Erzen",
    "sg:phone":"+41 33 654 54 29",
    "sg:postcode":"3700",
    "sg:province":"Bern",
    "wof:name":"Mountain Tool Ag Cnc-stanzwerkzeuge",
    "wof:placetype":"venue"
},
  "geometry": {"coordinates":[7.6805830002,46.6869812012],"type":"Point"}
}