{
  "type": "Feature",
  "properties": {
    "iso:country":"CH",
    "sg:address":"Dorfstrasse 7 6362 Stansstad. Postfach 261",
    "sg:city":"Stansstad",
    "sg:orig_category":"Vorschulen, Kinderg\u00e4rten",
    "sg:phone":"+41 41 610 86 28",
    "sg:postcode":"6362",
    "sg:province":"Nidwalden",
    "wof:name":"Kindergarten Dorf",
    "wof:placetype":"venue"
},
  "geometry": {"coordinates":[8.3387928009,46.9788017273],"type":"Point"}
}