{
  "type": "Feature",
  "properties": {
    "addr:full":"Cadruvi Waltensburg Graubunden 7158",
    "addr:housenumber":"7158",
    "iso:country":"CH",
    "sg:address":"Cadruvi",
    "sg:city":"Waltensburg",
    "sg:classifiers":[
        {
            "category":"Banks & Credit Unions",
            "subcategory":"Bank",
            "type":"Services"
        }
    ],
    "sg:phone":"+41 81 941 10 84",
    "sg:postcode":"7158",
    "sg:province":"Graubunden",
    "wof:name":"Raiffeisenbank",
    "wof:placetype":"venue"
},
  "geometry": {"coordinates":[9.116836,46.776188],"type":"Point"}
}