{
  "type": "Feature",
  "properties": {
    "iso:country":"CH",
    "sg:address":"Hauptstrasse 46 4312 Magden. Postfach",
    "sg:city":"Magden",
    "sg:orig_category":"Pensionskassen",
    "sg:postcode":"4312",
    "sg:province":"Aargau",
    "wof:name":"Personalf\u00fcrsorgestiftung Der Firma Gebr\u00fcder Ceresola Ag",
    "wof:placetype":"venue"
},
  "geometry": {"coordinates":[7.8099508286,47.5290260315],"type":"Point"}
}