{
  "type": "Feature",
  "properties": {
    "iso:country":"CH",
    "sg:address":"9043",
    "sg:city":"Trogen",
    "sg:orig_category":"Vereine Frauen Vereine Gemeinn\u00fctzige",
    "sg:postcode":"9043",
    "sg:province":"Appenzell Ausserrhoden",
    "wof:name":"Gemeinn\u00fctziger Frauenverein",
    "wof:placetype":"venue"
},
  "geometry": {"coordinates":[9.3884601593,47.3905601501],"type":"Point"}
}