{
  "type": "Feature",
  "properties": {
    "iso:country":"CH",
    "sg:address":"Gemeindekanzlei 6373 Ennetb\u00fcrgen. Postfach",
    "sg:city":"Ennetb\u00fcrgen",
    "sg:orig_category":"Interessenvertretungen",
    "sg:phone":"+41 41 624 40 30",
    "sg:postcode":"6373",
    "sg:province":"Nidwalden",
    "wof:name":"Stiftung Altersf\u00fcrsorge Ennetb\u00fcrgen",
    "wof:placetype":"venue"
},
  "geometry": {"coordinates":[8.4138898849,46.9846916199],"type":"Point"}
}