{
  "type": "Feature",
  "properties": {
    "iso:country":"CH",
    "sg:address":"Hauptstrasse 18 9424 Rheineck. Postfach",
    "sg:city":"Rheineck",
    "sg:orig_category":"Fotografische Ateliers",
    "sg:phone":"+41 71 888 40 88",
    "sg:postcode":"9424",
    "sg:province":"St. Gallen",
    "wof:name":"Christof Sonderegger Fotografisches Atelier",
    "wof:placetype":"venue"
},
  "geometry": {"coordinates":[9.5899171829,47.4664077759],"type":"Point"}
}