{
  "type": "Feature",
  "properties": {
    "iso:country":"CH",
    "sg:address":"Neuenburgstrasse 6",
    "sg:city":"Gampelen",
    "sg:orig_category":"Alters U Pflegeheime Institutionen f\u00fcr Behinderte",
    "sg:phone":"+41 21 796 30 60",
    "sg:postcode":"3236",
    "sg:province":"Bern",
    "wof:name":"Les Arcades Sa Etablissement M\u00e9dico-social",
    "wof:placetype":"venue"
},
  "geometry": {"coordinates":[6.677415,46.513313],"type":"Point"}
}