{
  "type": "Feature",
  "properties": {
    "iso:country":"CH",
    "sg:address":"Angensteinerstrasse 19",
    "sg:city":"Basel",
    "sg:orig_category":"Grosshandel mit B\u00fcromaschinen Grosshandel mit Datenverarbeitungsger\u00e4ten",
    "sg:phone":"+41 41 269 41 81",
    "sg:postcode":"4052",
    "sg:province":"Basel-Stadt",
    "wof:name":"Assistent + Partner Ag",
    "wof:placetype":"venue"
},
  "geometry": {"coordinates":[8.2769861221,47.0734977722],"type":"Point"}
}