{
  "type": "Feature",
  "properties": {
    "iso:country":"CH",
    "sg:address":"Sternenfeldstrasse 31",
    "sg:city":"Birsfelden",
    "sg:orig_category":"Sonstiger spezialisierter Hoch U Tiefbau",
    "sg:phone":"+41 61 462 00 66",
    "sg:postcode":"4127",
    "sg:province":"Basel-Landschaft",
    "wof:name":"Bohrfix Gmbh",
    "wof:placetype":"venue"
},
  "geometry": {"coordinates":[7.632994175,47.554599762],"type":"Point"}
}