{
  "type": "Feature",
  "properties": {
    "iso:country":"CH",
    "sg:address":"Wagistrasse 23",
    "sg:city":"Schlieren",
    "sg:orig_category":"Rechtsberatung Unternehmensberatung",
    "sg:phone":"+41 17306570",
    "sg:postcode":"8952",
    "sg:province":"Z\u00fcrich",
    "wof:name":"Kommunikation & Recht, Lic. Iur. Demuth Walter",
    "wof:placetype":"venue"
},
  "geometry": {"coordinates":[8.4585237503,47.3994674683],"type":"Point"}
}