{
  "type": "Feature",
  "properties": {
    "iso:country":"CH",
    "sg:address":"Eckrainweg 12",
    "sg:city":"Buus",
    "sg:orig_category":"Non-Classified Establishments",
    "sg:postcode":"4463",
    "sg:province":"Basel-Landschaft",
    "wof:name":"Alles F\u00fcr's Haus, Christian Ryser",
    "wof:placetype":"venue"
},
  "geometry": {"coordinates":[7.863424778,47.5032463074],"type":"Point"}
}