{
  "type": "Feature",
  "properties": {
    "iso:country":"CH",
    "sg:address":"Rudolfstrasse 19",
    "sg:city":"Winterthur",
    "sg:orig_category":"Organisationen des Gesundheitswesen",
    "sg:phone":"+41 55 410 55 52",
    "sg:postcode":"8400",
    "sg:province":"Z\u00fcrich",
    "wof:name":"Lungenliga Schwyz",
    "wof:placetype":"venue"
},
  "geometry": {"coordinates":[8.778793335,47.2024002075],"type":"Point"}
}