{
  "type": "Feature",
  "properties": {
    "iso:country":"CH",
    "sg:address":"Gotthardstrasse 24",
    "sg:city":"Thalwil",
    "sg:orig_category":"Tanzschulen, Tanzlehrer",
    "sg:phone":"+41 17205977",
    "sg:postcode":"8800",
    "sg:province":"Z\u00fcrich",
    "wof:name":"Doris B\u00fcrgi Gymnastik-& Ballettstudio",
    "wof:placetype":"venue"
},
  "geometry": {"coordinates":[8.5639801025,47.2956733704],"type":"Point"}
}