{
  "type": "Feature",
  "properties": {
    "iso:country":"CH",
    "sg:address":"Im Z\u00e4lg",
    "sg:city":"Feschel-guttet",
    "sg:orig_category":"Herstellung von Automobilen",
    "sg:postcode":"3956",
    "sg:province":"Valais",
    "wof:name":"Lawa Lastwagen Ag",
    "wof:placetype":"venue"
},
  "geometry": {"coordinates":[7.6638350487,46.3247871399],"type":"Point"}
}