{
  "type": "Feature",
  "properties": {
    "iso:country":"CH",
    "sg:address":"Chemin Des Carri\u00e8res 34",
    "sg:city":"St-blaise",
    "sg:orig_category":"M\u00f6belschreinereien",
    "sg:postcode":"2072",
    "sg:province":"Neuch\u00e2tel",
    "wof:name":"Lassueur Philippe Et Guye Laurent",
    "wof:placetype":"venue"
},
  "geometry": {"coordinates":[6.9826431274,47.0183448792],"type":"Point"}
}