{
  "type": "Feature",
  "properties": {
    "iso:country":"CH",
    "sg:address":"R\u00fctistrasse 8",
    "sg:city":"D\u00fcrnten",
    "sg:orig_category":"Elektroinstallation Mechanische Werkst\u00e4tten",
    "sg:phone":"+41 21 635 71 00",
    "sg:postcode":"8635",
    "sg:province":"Z\u00fcrich",
    "wof:name":"Alpha Paratonnerres, Buompreda G.",
    "wof:placetype":"venue"
},
  "geometry": {"coordinates":[6.580561161,46.5394859314],"type":"Point"}
}