{
  "type": "Feature",
  "properties": {
    "addr:full":"Neubr\u00fcckstrasse 202a Bern Bern 3000",
    "addr:housenumber":"202a",
    "addr:postcode":"3000",
    "addr:street":"Neubrueckstrasse",
    "iso:country":"CH",
    "sg:address":"Neubr\u00fcckstrasse 202a",
    "sg:city":"Bern",
    "sg:orig_category":"Allgemeiner Hoch U Tiefbau",
    "sg:phone":"+41 79 311 70 76",
    "sg:postcode":"3000",
    "sg:province":"Bern",
    "wof:name":"Anton Herren",
    "wof:placetype":"venue"
},
  "geometry": {"coordinates":[7.427729,46.972702],"type":"Point"}
}