{
  "type": "Feature",
  "properties": {
    "iso:country":"CH",
    "sg:address":"1486",
    "sg:city":"Vuissens",
    "sg:orig_category":"Verlegen von Fliesen U Platten",
    "sg:phone":"+41 24 433 14 87",
    "sg:postcode":"1486",
    "sg:province":"Fribourg",
    "wof:name":"Bernard Mettraux Carrelage & Rev\u00eatements",
    "wof:placetype":"venue"
},
  "geometry": {"coordinates":[6.7675299644,46.7343101501],"type":"Point"}
}