{
  "type": "Feature",
  "properties": {
    "iso:country":"CH",
    "sg:address":"Stapfelberg 4 4051 Basel. Postfach 1157",
    "sg:city":"Basel",
    "sg:classifiers":[
        {
            "category":"Education",
            "subcategory":"Library",
            "type":"Public Place"
        }
    ],
    "sg:postcode":"4001",
    "sg:province":"Basel-Stadt",
    "sg:tags":[
        "u",
        "bibliotheken",
        "archive"
    ],
    "wof:name":"Schweiz.burgenarchiv Bibliothek",
    "wof:placetype":"venue"
},
  "geometry": {"coordinates":[7.589552,47.557484],"type":"Point"}
}