{
  "type": "Feature",
  "properties": {
    "iso:country":"CH",
    "sg:address":"Neuweilerstrasse 102",
    "sg:city":"Basel",
    "sg:orig_category":"Detailhandel mit Radio U Fernsehger\u00e4ten Herstellung von Radio U Fernsehger\u00e4ten sowie phono U videote",
    "sg:phone":"+41 61 301 44 77",
    "sg:postcode":"4054",
    "sg:province":"Basel-Stadt",
    "wof:name":"Electronic Service Ganz",
    "wof:placetype":"venue"
},
  "geometry": {"coordinates":[7.5574989319,47.5460510254],"type":"Point"}
}