{
  "type": "Feature",
  "properties": {
    "iso:country":"CH",
    "sg:address":"Ch. Henri-wissner 12",
    "sg:city":"Grand-lancy",
    "sg:orig_category":"Betrieb U technische Hilfsdienste des Kultur U Unterhaltungswesens",
    "sg:phone":"+41 22 792 61 63",
    "sg:postcode":"1212",
    "sg:province":"Gen\u00e8ve",
    "wof:name":"Golan David",
    "wof:placetype":"venue"
},
  "geometry": {"coordinates":[6.112591,46.179195],"type":"Point"}
}