{
  "type": "Feature",
  "properties": {
    "addr:full":"Bahnhofstrasse 12 Zweisimmen Bern 3770",
    "addr:housenumber":"12",
    "addr:postcode":"3770",
    "addr:street":"Bahnhofstrasse",
    "iso:country":"CH",
    "sg:address":"Bahnhofstrasse 12",
    "sg:city":"Zweisimmen",
    "sg:orig_category":"Detailhandel mit Bekleidung",
    "sg:postcode":"3770",
    "sg:province":"Bern",
    "wof:name":"J\u00f6rg-r\u00f6sti Heidi, La Boutique",
    "wof:placetype":"venue"
},
  "geometry": {"coordinates":[7.373678,46.55365],"type":"Point"}
}