{
  "type": "Feature",
  "properties": {
    "iso:country":"CH",
    "sg:address":"B\u00e4lliz 12",
    "sg:city":"Thun",
    "sg:orig_category":"Grosshandel mit Getr\u00e4nken",
    "sg:phone":"+41 71 999 28 55",
    "sg:postcode":"3600",
    "sg:province":"Bern",
    "wof:name":"Felder Albin",
    "wof:placetype":"venue"
},
  "geometry": {"coordinates":[9.2497396469,47.1857299805],"type":"Point"}
}