{
  "type": "Feature",
  "properties": {
    "iso:country":"CH",
    "sg:address":"Schimmelstrasse 2",
    "sg:city":"Z\u00fcrich",
    "sg:classifiers":[
        {
            "category":"Food & Beverages",
            "subcategory":"Specialty",
            "type":"Retail Goods"
        }
    ],
    "sg:phone":"+41 14505252",
    "sg:postcode":"8003",
    "sg:province":"Z\u00fcrich",
    "sg:tags":[
        "caterer"
    ],
    "wof:name":"Pizza-blitz Gmbh",
    "wof:placetype":"venue"
},
  "geometry": {"coordinates":[8.525891,47.369514],"type":"Point"}
}