{
  "type": "Feature",
  "properties": {
    "iso:country":"CH",
    "sg:address":"Gerra Piano",
    "sg:city":"Cugnasco",
    "sg:orig_category":"Detailhandel mit Waren verschiedener Art, Hauptrichtung Nahrungsmittel",
    "sg:phone":"+41 91 859 13 05",
    "sg:postcode":"6516",
    "sg:province":"Ticino",
    "wof:name":"Egidio Foletta Commestibili",
    "wof:placetype":"venue"
},
  "geometry": {"coordinates":[8.9116001129,46.174369812],"type":"Point"}
}