{
  "type": "Feature",
  "properties": {
    "iso:country":"CH",
    "sg:address":"Eichstrasse 1 8155 Niederhasli. Postfach 52",
    "sg:city":"Niederhasli",
    "sg:orig_category":"Vereine Musik/Blasmusik",
    "sg:phone":"+41 18136217",
    "sg:postcode":"8155",
    "sg:province":"Z\u00fcrich",
    "wof:name":"Musikgesellschaft",
    "wof:placetype":"venue"
},
  "geometry": {"coordinates":[8.4858369827,47.4850502014],"type":"Point"}
}