{
  "type": "Feature",
  "properties": {
    "addr:full":"Rue Du Conseil 14 Vevey Vaud 1800",
    "addr:housenumber":"14",
    "addr:postcode":"1800",
    "addr:street":"Rue Du Conseil",
    "iso:country":"CH",
    "sg:address":"Rue Du Conseil 14",
    "sg:city":"Vevey",
    "sg:orig_category":"Detailhandel mit Brot, Back U S\u00fcsswaren",
    "sg:phone":"+41 21 921 21 37",
    "sg:postcode":"1800",
    "sg:province":"Vaud",
    "wof:name":"Boulangerie-p\u00e2tisserie Gilgen Jean",
    "wof:placetype":"venue"
},
  "geometry": {"coordinates":[6.843837,46.460159],"type":"Point"}
}