{
  "type": "Feature",
  "properties": {
    "iso:country":"CH",
    "sg:address":"Chaibengasse 4",
    "sg:city":"Villmergen",
    "sg:orig_category":"Hardwareberatung",
    "sg:phone":"+41 33 951 05 50",
    "sg:postcode":"5612",
    "sg:province":"Aargau",
    "wof:name":"Computerfuchs Ag",
    "wof:placetype":"venue"
},
  "geometry": {"coordinates":[8.0582828522,46.7458648682],"type":"Point"}
}