{
  "type": "Feature",
  "properties": {
    "iso:country":"CH",
    "sg:address":"Haus A1",
    "sg:city":"Litzir\u00fcti",
    "sg:orig_category":"Bau U Wohngenossenschaften",
    "sg:postcode":"7058",
    "sg:province":"Graubunden",
    "wof:name":"Liberale Baugen.litzir\u00fcti",
    "wof:placetype":"venue"
},
  "geometry": {"coordinates":[9.702304,46.798431],"type":"Point"}
}