{
  "type": "Feature",
  "properties": {
    "iso:country":"CH",
    "sg:address":"Hofmattstrasse 7 5622 Waltenschwil. Postfach",
    "sg:city":"Waltenschwil",
    "sg:orig_category":"Sonstiger Grosshandel",
    "sg:postcode":"5622",
    "sg:province":"Aargau",
    "wof:name":"Treenet - Galova",
    "wof:placetype":"venue"
},
  "geometry": {"coordinates":[8.2969799042,47.3361473083],"type":"Point"}
}