{
  "type": "Feature",
  "properties": {
    "iso:country":"CH",
    "sg:address":"Landstrasse 17",
    "sg:city":"Untersiggenthal",
    "sg:orig_category":"RESTAURANTS: TEA-ROOMS",
    "sg:phone":"+41 56 288 10 28",
    "sg:postcode":"5417",
    "sg:province":"Aargau",
    "wof:name":"Restaurant Sch\u00f6negg",
    "wof:placetype":"venue"
},
  "geometry": {"coordinates":[8.2671785355,47.4963798523],"type":"Point"}
}