{
  "type": "Feature",
  "properties": {
    "addr:full":"Almendsberg Walzenhausen Appenzell Ausserrhoden 9428",
    "addr:postcode":"9428",
    "addr:street":"Almendsberg;Ausserrhoden",
    "iso:country":"CH",
    "sg:address":"Almendsberg",
    "sg:city":"Walzenhausen",
    "sg:classifiers":[
        {
            "category":"Social Services",
            "subcategory":"Retirement Home",
            "type":"Services"
        }
    ],
    "sg:phone":"+41 71 888 13 94",
    "sg:postcode":"9428",
    "sg:province":"Appenzell Ausserrhoden",
    "sg:tags":[
        "pflegeheime",
        "u",
        "alters"
    ],
    "wof:name":"Alters-& B\u00fcrgerheim",
    "wof:placetype":"venue"
},
  "geometry": {"coordinates":[9.59354,47.45499],"type":"Point"}
}