{
  "type": "Feature",
  "properties": {
    "iso:country":"CH",
    "sg:address":"Frankenstrasse 9 6000 Luzern. Postfach",
    "sg:city":"Luzern",
    "sg:orig_category":"Herstellung von Uhren",
    "sg:postcode":"6003",
    "sg:province":"Luzern",
    "wof:name":"Pgs Steimann Peter",
    "wof:placetype":"venue"
},
  "geometry": {"coordinates":[8.3084945679,47.0490341187],"type":"Point"}
}