{
  "type": "Feature",
  "properties": {
    "iso:country":"CH",
    "sg:address":"Spitzwaldstrasse 16",
    "sg:city":"Allschwil",
    "sg:orig_category":"Fachdetailhandel in Verkaufsr\u00e4umen Sonstiger Fachdetailhandel in Verkaufsr\u00e4umen",
    "sg:phone":"+41 61 483 07 07",
    "sg:postcode":"4123",
    "sg:province":"Basel-Landschaft",
    "wof:name":"Tresora Gmbh",
    "wof:placetype":"venue"
},
  "geometry": {"coordinates":[7.5611100197,47.5568237305],"type":"Point"}
}