{
  "type": "Feature",
  "properties": {
    "iso:country":"CH",
    "sg:address":"S\u00e9beillon Rue De 9b",
    "sg:city":"Lausanne",
    "sg:orig_category":"Fachdetailhandel in Verkaufsr\u00e4umen",
    "sg:phone":"+41 41 850 57 67",
    "sg:postcode":"1004",
    "sg:province":"Vaud",
    "wof:name":"Marine Center Innerschweiz Ag",
    "wof:placetype":"venue"
},
  "geometry": {"coordinates":[8.4456472397,47.089630127],"type":"Point"}
}