{
  "type": "Feature",
  "properties": {
    "iso:country":"CH",
    "sg:address":"Bottmingerstrasse 76",
    "sg:city":"Binningen",
    "sg:orig_category":"Bau U Wohngenossenschaften Erschliessung von Grundst\u00fccken",
    "sg:postcode":"4102",
    "sg:province":"Basel-Landschaft",
    "wof:name":"Wohngenossenschaft Waldeck",
    "wof:placetype":"venue"
},
  "geometry": {"coordinates":[7.572989,47.531071],"type":"Point"}
}