{
  "type": "Feature",
  "properties": {
    "iso:country":"CH",
    "sg:address":"G.-f.-heilmann-strasse 49",
    "sg:city":"Biel/bienne",
    "sg:orig_category":"Architekturb\u00fcros",
    "sg:phone":"+41 31 951 12 12",
    "sg:postcode":"2502",
    "sg:province":"Bern",
    "wof:name":"Bruno Reinli Architekturb\u00fcro",
    "wof:placetype":"venue"
},
  "geometry": {"coordinates":[7.485553,46.930553],"type":"Point"}
}