{
  "type": "Feature",
  "properties": {
    "iso:country":"CH",
    "sg:address":"Route De La Gruy\u00e8re 8 1700 Fribourg Case Postale 162",
    "sg:city":"Freiburg",
    "sg:orig_category":"Geb\u00e4ude, Wohnungsreinigung Reinigungsgewerbe",
    "sg:phone":"+41 26 424 16 05",
    "sg:postcode":"1700",
    "sg:province":"Fribourg",
    "wof:name":"Honegger Nettoyages Ag",
    "wof:placetype":"venue"
},
  "geometry": {"coordinates":[7.1424608231,46.7966423035],"type":"Point"}
}