{
  "type": "Feature",
  "properties": {
    "iso:country":"CH",
    "sg:address":"Matteg\u00e4ssli 3792 Saanen. Postfach",
    "sg:city":"Gstaad",
    "sg:orig_category":"Zimmerei, Dachdeckerei, Bauspenglerei U Abdichtung",
    "sg:postcode":"3780",
    "sg:province":"Bern",
    "wof:name":"M\u00f6sching Robert, Bedachungen Und Ger\u00fcstebau",
    "wof:placetype":"venue"
},
  "geometry": {"coordinates":[7.2801008224,46.4628639221],"type":"Point"}
}