{
  "type": "Feature",
  "properties": {
    "addr:full":"Byfangweg 1a 4051 Basel. Postfach Basel Basel-Stadt 4011",
    "addr:housenumber":"1a",
    "addr:postcode":"4051;4011",
    "addr:street":"Byfangweg;Postfach",
    "iso:country":"CH",
    "sg:address":"Byfangweg 1a 4051 Basel. Postfach",
    "sg:city":"Basel",
    "sg:orig_category":"Arztpraxen",
    "sg:phone":"+41 61 205 95 85",
    "sg:postcode":"4011",
    "sg:province":"Basel-Stadt",
    "wof:name":"Dres Curschellas & R\u00fcfenacht Spezial\u00e4rzte",
    "wof:placetype":"venue"
},
  "geometry": {"coordinates":[7.58327,47.552753],"type":"Point"}
}