{
  "type": "Feature",
  "properties": {
    "iso:country":"CH",
    "sg:address":"Garmiswilstrasse 45",
    "sg:city":"D\u00fcdingen",
    "sg:orig_category":"Sportvereine Velo Rad-& Motorfahrer-Bund SRB",
    "sg:phone":"+41 26 493 33 94",
    "sg:postcode":"3186",
    "sg:province":"Fribourg",
    "wof:name":"Vc Wanderlust Berg/schmitten",
    "wof:placetype":"venue"
},
  "geometry": {"coordinates":[7.1799321175,46.8395042419],"type":"Point"}
}