{
  "type": "Feature",
  "properties": {
    "iso:country":"CH",
    "sg:address":"Pelzgasse 2",
    "sg:city":"Aarau",
    "sg:orig_category":"Detailhandel mit Bekleidung",
    "sg:postcode":"5000",
    "sg:province":"Aargau",
    "wof:name":"M. Scheidegger Inh. Heidi Reinhardt Corsets Aarau",
    "wof:placetype":"venue"
},
  "geometry": {"coordinates":[8.04431,47.392887],"type":"Point"}
}