{
  "type": "Feature",
  "properties": {
    "iso:country":"CH",
    "sg:address":"In Zermatt",
    "sg:city":"Zermatt",
    "sg:orig_category":"RESTAURANTS: TEA-ROOMS",
    "sg:postcode":"3920",
    "sg:province":"Valais",
    "wof:name":"Kalbermatten Michael",
    "wof:placetype":"venue"
},
  "geometry": {"coordinates":[7.7539248466,46.0301589966],"type":"Point"}
}