{
  "type": "Feature",
  "properties": {
    "iso:country":"CH",
    "sg:address":"Marktgasse 12",
    "sg:city":"Baar",
    "sg:orig_category":"Detailhandel mit Radio U Fernsehger\u00e4ten Herstellung von Radio U Fernsehger\u00e4ten sowie phono U videote",
    "sg:phone":"+41 41 760 08 64",
    "sg:postcode":"6340",
    "sg:province":"Zug",
    "wof:name":"Niracom Ag",
    "wof:placetype":"venue"
},
  "geometry": {"coordinates":[8.5274553299,47.1957588196],"type":"Point"}
}