{
  "type": "Feature",
  "properties": {
    "iso:country":"CH",
    "sg:address":"Neur\u00fcti",
    "sg:city":"Heldswil",
    "sg:orig_category":"G\u00fcterbef\u00f6rderung im Strassenverkehr",
    "sg:phone":"+41 27 475 12 02",
    "sg:postcode":"9216",
    "sg:province":"Thurgau",
    "wof:name":"Albert Savioz Transports",
    "wof:placetype":"venue"
},
  "geometry": {"coordinates":[7.5843100548,46.1964187622],"type":"Point"}
}