{
  "type": "Feature",
  "properties": {
    "iso:country":"CH",
    "sg:address":"Klostermatt 9b",
    "sg:city":"Arth",
    "sg:orig_category":"Sanit\u00e4r, Heizungs U L\u00fcftungsinstallation Sanit\u00e4rinstallation",
    "sg:phone":"+41 41 855 44 05",
    "sg:postcode":"6415",
    "sg:province":"Schwyz",
    "wof:name":"Alfons Kurmann Gmbh, Heizung/sanit\u00e4r",
    "wof:placetype":"venue"
},
  "geometry": {"coordinates":[8.5269603729,47.0662193298],"type":"Point"}
}