{
  "type": "Feature",
  "properties": {
    "iso:country":"CH",
    "sg:address":"Im Moos",
    "sg:city":"Baar",
    "sg:orig_category":"Nahrungsmittel-Industrie: Rohstoffe",
    "sg:phone":"+41 79 216 25 04",
    "sg:postcode":"6340",
    "sg:province":"Zug",
    "wof:name":"Isi Import, Melillo J.",
    "wof:placetype":"venue"
},
  "geometry": {"coordinates":[8.2035999298,47.4864692688],"type":"Point"}
}