{
  "type": "Feature",
  "properties": {
    "iso:country":"CH",
    "sg:address":"Sedelstrasse 34 6020 Emmenbr\u00fccke. Postfach",
    "sg:city":"Emmenbr\u00fccke",
    "sg:orig_category":"Softwareentwicklung U beratung",
    "sg:phone":"+41 41 260 85 51",
    "sg:postcode":"6020",
    "sg:province":"Luzern",
    "wof:name":"Bucher W.",
    "wof:placetype":"venue"
},
  "geometry": {"coordinates":[8.2906608582,47.0705871582],"type":"Point"}
}