{
  "type": "Feature",
  "properties": {
    "iso:country":"CH",
    "sg:address":"Helv\u00e9tique Bvd 18 1207 Gen\u00e8ve. Postfach",
    "sg:city":"Gen\u00e8ve",
    "sg:orig_category":"Filmverleih U Videoprogrammanbieter",
    "sg:postcode":"1207",
    "sg:province":"Gen\u00e8ve",
    "wof:name":"Labofilms Sa",
    "wof:placetype":"venue"
},
  "geometry": {"coordinates":[6.1540789604,46.2002296448],"type":"Point"}
}