{
  "type": "Feature",
  "properties": {
    "iso:country":"CH",
    "sg:address":"M\u00fchlentalstrasse 28 8200 Schaffhausen. Postfach",
    "sg:city":"Schaffhausen",
    "sg:orig_category":"Medizinische Labors",
    "sg:phone":"+41 52 620 04 00",
    "sg:postcode":"8201",
    "sg:province":"Schaffhausen",
    "wof:name":"Dr.gerhard M. Risch Medizinisches Laboratorium",
    "wof:placetype":"venue"
},
  "geometry": {"coordinates":[8.6302223206,47.7006187439],"type":"Point"}
}