{
  "type": "Feature",
  "properties": {
    "iso:country":"CH",
    "sg:address":"Hauptstrasse 53",
    "sg:city":"Speicher",
    "sg:orig_category":"Allgemeiner Hoch U Tiefbau",
    "sg:phone":"+41 71 243 03 63",
    "sg:postcode":"9042",
    "sg:province":"Appenzell Ausserrhoden",
    "wof:name":"Stutz & Rudorf Ag",
    "wof:placetype":"venue"
},
  "geometry": {"coordinates":[9.383763,47.430389],"type":"Point"}
}