{
  "type": "Feature",
  "properties": {
    "iso:country":"CH",
    "sg:address":"Industriestrasse 15 2553 Safnern. Postfach 128",
    "sg:city":"Safnern",
    "sg:orig_category":"Herstellung der Ausstattung von Uhren Herstellung von Metallerzeugnissen ohne Maschinenbau",
    "sg:phone":"+41 22 989 08 50",
    "sg:postcode":"2553",
    "sg:province":"Bern",
    "wof:name":"Boucledor Sa",
    "wof:placetype":"venue"
},
  "geometry": {"coordinates":[6.061466217,46.2242431641],"type":"Point"}
}