{
  "type": "Feature",
  "properties": {
    "iso:country":"CH",
    "sg:address":"Juravorstadt 44",
    "sg:city":"Biel/bienne",
    "sg:orig_category":"Herstellung von Werkzeugen Maschinenbau",
    "sg:phone":"+41 71 850 08 20",
    "sg:postcode":"2502",
    "sg:province":"Bern",
    "wof:name":"Fma Staad Ag",
    "wof:placetype":"venue"
},
  "geometry": {"coordinates":[9.5429334641,47.4775428772],"type":"Point"}
}