{
  "type": "Feature",
  "properties": {
    "iso:country":"CH",
    "sg:address":"Pessina Via 9",
    "sg:city":"Lugano",
    "sg:orig_category":"Unternehmensberatung",
    "sg:phone":"+41 91 924 29 90",
    "sg:postcode":"6900",
    "sg:province":"Ticino",
    "wof:name":"Riem Identity Sa",
    "wof:placetype":"venue"
},
  "geometry": {"coordinates":[8.9502954483,46.0040588379],"type":"Point"}
}