{
  "type": "Feature",
  "properties": {
    "addr:full":"Glennerstr. 30 Ilanz Graubunden 7130",
    "addr:housenumber":"30",
    "addr:postcode":"7130",
    "addr:street":"Glennerstr.;Graubunden",
    "iso:country":"CH",
    "sg:address":"Glennerstr. 30",
    "sg:city":"Ilanz",
    "sg:classifiers":[
        {
            "category":"Sports & Exercise",
            "subcategory":"Tennis Court",
            "type":"Entertainment"
        }
    ],
    "sg:phone":"+41 81 925 17 47",
    "sg:postcode":"7130",
    "sg:province":"Graubunden",
    "sg:tags":[
        "textile",
        "product",
        "clothing",
        "miscellaneous",
        "clothes"
    ],
    "wof:name":"Menzli Sport Ag",
    "wof:placetype":"venue"
},
  "geometry": {"coordinates":[9.209756,46.774185],"type":"Point"}
}