{
  "type": "Feature",
  "properties": {
    "iso:country":"CH",
    "sg:address":"Gstaldenstrasse 17",
    "sg:city":"Horgen",
    "sg:orig_category":"Detailhandel Einzelhandel mit Automobilteilen U Zubeh\u00f6r Reparatur von Gebrauchsg\u00fctern",
    "sg:phone":"+41 17254107",
    "sg:postcode":"8810",
    "sg:province":"Z\u00fcrich",
    "wof:name":"D & D Speed Shop Volker Dreiner",
    "wof:placetype":"venue"
},
  "geometry": {"coordinates":[8.6028118134,47.2483978271],"type":"Point"}
}