{
  "type": "Feature",
  "properties": {
    "iso:country":"CH",
    "sg:address":"Prattelerstrasse 5",
    "sg:city":"Frenkendorf",
    "sg:orig_category":"Herstellung von sonstigen Maschinen f\u00fcr unspezifische Verwendung",
    "sg:phone":"+41 61 731 13 39",
    "sg:postcode":"4402",
    "sg:province":"Basel-Landschaft",
    "wof:name":"Seibel Kurt Ag",
    "wof:placetype":"venue"
},
  "geometry": {"coordinates":[7.7127509117,47.504070282],"type":"Point"}
}