{
  "type": "Feature",
  "properties": {
    "iso:country":"CH",
    "sg:address":"Poststrasse 7",
    "sg:city":"Chur",
    "sg:orig_category":"Detailhandel mit Damenbekleidung Detailhandel mit Herrenbekleidung",
    "sg:phone":"+41 81 252 69 45",
    "sg:postcode":"7000",
    "sg:province":"Graubunden",
    "wof:name":"Seima Mode Ag",
    "wof:placetype":"venue"
},
  "geometry": {"coordinates":[9.5323476791,46.8500976562],"type":"Point"}
}