{
  "type": "Feature",
  "properties": {
    "iso:country":"CH",
    "sg:address":"Buchserstrasse 30 3005 Bern. Postfach",
    "sg:city":"Bern",
    "sg:orig_category":"Pensionskassen",
    "sg:postcode":"3005",
    "sg:province":"Bern",
    "wof:name":"Patronaler Vorsorgefonds Der Sonnenhof Ag Bern",
    "wof:placetype":"venue"
},
  "geometry": {"coordinates":[7.474047184,46.9426460266],"type":"Point"}
}