{
  "type": "Feature",
  "properties": {
    "iso:country":"CH",
    "sg:address":"Aarauerstrasse 85",
    "sg:city":"Olten",
    "sg:orig_category":"Detailhandel mit Bekleidung",
    "sg:phone":"+41 62 296 31 55",
    "sg:postcode":"4600",
    "sg:province":"Solothurn",
    "wof:name":"Nice \u00c4nderungsatelier Serpil Oezcanli",
    "wof:placetype":"venue"
},
  "geometry": {"coordinates":[7.912637,47.349007],"type":"Point"}
}