{
  "type": "Feature",
  "properties": {
    "iso:country":"CH",
    "sg:address":"Rue St-germain 1",
    "sg:city":"Bussigny-lausanne",
    "sg:orig_category":"Kinderkrippen U horte",
    "sg:phone":"+41 21 701 33 77",
    "sg:postcode":"1030",
    "sg:province":"Vaud",
    "wof:name":"Garderie D'enfants La Ferme Des Enfants",
    "wof:placetype":"venue"
},
  "geometry": {"coordinates":[6.5507202148,46.5503196716],"type":"Point"}
}