{
  "type": "Feature",
  "properties": {
    "iso:country":"CH",
    "sg:address":"Schulstrasse 63",
    "sg:city":"Landquart",
    "sg:orig_category":"Maler U Glasergewerbe Malerei",
    "sg:phone":"+41 81 322 22 01",
    "sg:postcode":"7302",
    "sg:province":"Graubunden",
    "wof:name":"Maler Gujan Ag",
    "wof:placetype":"venue"
},
  "geometry": {"coordinates":[9.5610809326,46.9606285095],"type":"Point"}
}