{
  "type": "Feature",
  "properties": {
    "addr:full":"Avenue De La Croisette 20 Gen\u00e8ve Gen\u00e8ve 1205",
    "addr:housenumber":"20",
    "addr:postcode":"1205",
    "addr:street":"Avenue De La Croisette",
    "iso:country":"CH",
    "sg:address":"Avenue De La Croisette 20",
    "sg:city":"Gen\u00e8ve",
    "sg:classifiers":[
        {
            "category":"Banks & Credit Unions",
            "subcategory":"Investment Brokerage",
            "type":"Services"
        }
    ],
    "sg:phone":"+41 22 799 43 43",
    "sg:postcode":"1205",
    "sg:province":"Gen\u00e8ve",
    "sg:tags":[
        "training",
        "application",
        "processing",
        "consulting",
        "course",
        "data"
    ],
    "wof:name":"Em3 S.a.",
    "wof:placetype":"venue"
},
  "geometry": {"coordinates":[6.146478,46.189651],"type":"Point"}
}