{
  "type": "Feature",
  "properties": {
    "iso:country":"CH",
    "sg:address":"Chemin Du Buis 8",
    "sg:city":"Troistorrents",
    "sg:orig_category":"Non-Classified Establishments",
    "sg:postcode":"1872",
    "sg:province":"Valais",
    "wof:name":"Rest'ollaire - O. Bressoud",
    "wof:placetype":"venue"
},
  "geometry": {"coordinates":[6.9232931137,46.2270927429],"type":"Point"}
}