{
  "type": "Feature",
  "properties": {
    "iso:country":"CH",
    "sg:address":"Heiligbergstrasse 9",
    "sg:city":"Andelfingen",
    "sg:orig_category":"Verwaltung von Immobilien Wirtschaftspr\u00fcfung, Steuerberatung U Treuhand",
    "sg:phone":"+41 52 317 31 38",
    "sg:postcode":"8450",
    "sg:province":"Z\u00fcrich",
    "wof:name":"Flury Beratung & Treuhand",
    "wof:placetype":"venue"
},
  "geometry": {"coordinates":[8.6773414612,47.5931663513],"type":"Point"}
}