{
  "type": "Feature",
  "properties": {
    "iso:country":"CH",
    "sg:address":"Wiesenstrasse 17",
    "sg:city":"Dietikon",
    "sg:orig_category":"Handel mit Automobilen",
    "sg:postcode":"8953",
    "sg:province":"Z\u00fcrich",
    "wof:name":"Mehaidli Auto Export",
    "wof:placetype":"venue"
},
  "geometry": {"coordinates":[8.421749115,47.3961601257],"type":"Point"}
}