{
  "type": "Feature",
  "properties": {
    "iso:country":"CH",
    "sg:address":"Degersheimer Strasse 33",
    "sg:city":"Herisau",
    "sg:classifiers":[
        {
            "category":"Restaurant",
            "type":"Food & Drink"
        }
    ],
    "sg:phone":"+41 71 351 14 34",
    "sg:postcode":"9100",
    "sg:province":"Appenzell Ausserrhoden",
    "wof:name":"Restaurant Friedeck",
    "wof:placetype":"venue"
},
  "geometry": {"coordinates":[9.2677631378,47.3853988647],"type":"Point"}
}