{
  "type": "Feature",
  "properties": {
    "iso:country":"CH",
    "sg:address":"Kirchdorfstrasse 18",
    "sg:city":"Kriessern",
    "sg:orig_category":"Detailhandel mit Brot, Back U S\u00fcsswaren",
    "sg:postcode":"9451",
    "sg:province":"St. Gallen",
    "wof:name":"Reinhardt Peter.",
    "wof:placetype":"venue"
},
  "geometry": {"coordinates":[7.406825,46.276783],"type":"Point"}
}