{
  "type": "Feature",
  "properties": {
    "iso:country":"CH",
    "sg:address":"Rue De La Birse 14",
    "sg:city":"Courroux",
    "sg:orig_category":"Malerei",
    "sg:phone":"+41 32 422 82 70",
    "sg:postcode":"2822",
    "sg:province":"Jura",
    "wof:name":"Denis Girardin Entreprise De Peinture",
    "wof:placetype":"venue"
},
  "geometry": {"coordinates":[7.3705730438,47.3605499268],"type":"Point"}
}