{
  "type": "Feature",
  "properties": {
    "iso:country":"CH",
    "sg:address":"Rue Centrale 8",
    "sg:city":"Chamoson",
    "sg:classifiers":[
        {
            "category":"Home & Garden",
            "subcategory":"Building Materials",
            "type":"Retail Goods"
        }
    ],
    "sg:phone":"+41 27 306 60 30",
    "sg:postcode":"1955",
    "sg:province":"Valais",
    "sg:tags":[
        "garage",
        "door"
    ],
    "wof:name":"Hormalu S\u00e0rl",
    "wof:placetype":"venue"
},
  "geometry": {"coordinates":[7.2241148949,46.2006111145],"type":"Point"}
}