{
  "type": "Feature",
  "properties": {
    "iso:country":"CH",
    "sg:address":"Grand-rue 39",
    "sg:city":"Gen\u00e8ve",
    "sg:classifiers":[
        {
            "category":"Restaurant",
            "type":"Food & Drink"
        }
    ],
    "sg:phone":"+41 22 311 70 30",
    "sg:postcode":"1204",
    "sg:province":"Gen\u00e8ve",
    "wof:name":"Caf\u00e9 H\u00f4tel-de-ville",
    "wof:placetype":"venue"
},
  "geometry": {"coordinates":[6.1469488144,46.201259613],"type":"Point"}
}