{
  "type": "Feature",
  "properties": {
    "iso:country":"CH",
    "sg:address":"Sardonastrasse 4",
    "sg:city":"Chur",
    "sg:orig_category":"Primarschulen",
    "sg:phone":"+41 81 254 41 11",
    "sg:postcode":"7000",
    "sg:province":"Graubunden",
    "wof:name":"Primarschule Rheinau",
    "wof:placetype":"venue"
},
  "geometry": {"coordinates":[9.5167856216,46.8613700867],"type":"Point"}
}