{
  "type": "Feature",
  "properties": {
    "iso:country":"CH",
    "sg:address":"Werkstrasse 16",
    "sg:city":"Diepoldsau",
    "sg:orig_category":"G\u00fcterbef\u00f6rderung im Strassenverkehr Lagerung",
    "sg:phone":"+41 22 300 43 00",
    "sg:postcode":"9444",
    "sg:province":"St. Gallen",
    "wof:name":"Harsch Henri Hh Sa",
    "wof:placetype":"venue"
},
  "geometry": {"coordinates":[6.1337170601,46.1803016663],"type":"Point"}
}