{
  "type": "Feature",
  "properties": {
    "iso:country":"CH",
    "sg:address":"Rte Cantonale 3",
    "sg:city":"Sugiez",
    "sg:orig_category":"Reiseb\u00fcros U Reiseveranstalter",
    "sg:postcode":"1786",
    "sg:province":"Fribourg",
    "wof:name":"Agentur Jpg Jean-pierre Gaud",
    "wof:placetype":"venue"
},
  "geometry": {"coordinates":[7.1079277992,46.957408905],"type":"Point"}
}