{
  "type": "Feature",
  "properties": {
    "iso:country":"CH",
    "sg:address":"Bellerivestrasse 7",
    "sg:city":"Z\u00fcrich",
    "sg:orig_category":"Vermittlung von Immobilien Verwaltung von Immobilien",
    "sg:phone":"+41 31 382 50 82",
    "sg:postcode":"8008",
    "sg:province":"Z\u00fcrich",
    "wof:name":"Aaa Services Meier & Franzelli Treuhandb\u00fcro",
    "wof:placetype":"venue"
},
  "geometry": {"coordinates":[7.4170198441,46.9473342896],"type":"Point"}
}