{
  "type": "Feature",
  "properties": {
    "iso:country":"CH",
    "sg:address":"Hauensteinstrasse 92",
    "sg:city":"Basel",
    "sg:orig_category":"Architekturb\u00fcros",
    "sg:phone":"+41 31 981 20 69",
    "sg:postcode":"4059",
    "sg:province":"Basel-Stadt",
    "wof:name":"Reto Baer Architekt Bsa Swb",
    "wof:placetype":"venue"
},
  "geometry": {"coordinates":[7.381518,46.92625],"type":"Point"}
}