{
  "type": "Feature",
  "properties": {
    "iso:country":"CH",
    "sg:address":"Marktgasse 17",
    "sg:city":"Baar",
    "sg:orig_category":"Maler U Glasergewerbe",
    "sg:phone":"+41 41 761 06 63",
    "sg:postcode":"6340",
    "sg:province":"Zug",
    "wof:name":"Utiger Pius.",
    "wof:placetype":"venue"
},
  "geometry": {"coordinates":[8.5278253555,47.1961326599],"type":"Point"}
}