{
  "type": "Feature",
  "properties": {
    "iso:country":"CH",
    "sg:address":"Napoleonstrasse 124",
    "sg:city":"Glis",
    "sg:classifiers":[
        {
            "category":"Personal",
            "subcategory":"Nail Salon",
            "type":"Services"
        }
    ],
    "sg:phone":"+41 27 923 58 54",
    "sg:postcode":"3902",
    "sg:province":"Valais",
    "sg:tags":[
        "manicure"
    ],
    "wof:name":"Dorly Kronig Nail Kosmetik",
    "wof:placetype":"venue"
},
  "geometry": {"coordinates":[7.9878258705,46.3094062805],"type":"Point"}
}