{
  "type": "Feature",
  "properties": {
    "iso:country":"CH",
    "sg:address":"Avenue Du G\u00e9n\u00e9ral Guisan 15",
    "sg:city":"Sierre",
    "sg:orig_category":"Advokaturb\u00fcros Notariate",
    "sg:phone":"+41 27 455 87 87",
    "sg:postcode":"3960",
    "sg:province":"Valais",
    "wof:name":"Bernard Grand Etude D'avocat & Notaire",
    "wof:placetype":"venue"
},
  "geometry": {"coordinates":[7.530512,46.292259],"type":"Point"}
}