{
  "type": "Feature",
  "properties": {
    "iso:country":"CH",
    "sg:address":"Freie Strasse 40",
    "sg:city":"Basel",
    "sg:classifiers":[
        {
            "category":"Manufacturing",
            "subcategory":"Jewelry",
            "type":"Manufacturing & Wholesale Goods"
        }
    ],
    "sg:phone":"+41 61 261 40 00",
    "sg:postcode":"4001",
    "sg:province":"Basel-Stadt",
    "sg:tags":[
        "jewellery",
        "silver",
        "gold",
        "combined"
    ],
    "wof:name":"Bucherer Ag",
    "wof:placetype":"venue"
},
  "geometry": {"coordinates":[7.590003,47.556049],"type":"Point"}
}