{
  "type": "Feature",
  "properties": {
    "iso:country":"CH",
    "sg:address":"Sch\u00fctzenstrasse 56",
    "sg:city":"Feuerthalen",
    "sg:orig_category":"Bauspenglerei Sanit\u00e4r, Heizungs U L\u00fcftungsinstallation",
    "sg:phone":"+41 79 441 84 23",
    "sg:postcode":"8245",
    "sg:province":"Z\u00fcrich",
    "wof:name":"Z\u00fclle + Dietz Ag",
    "wof:placetype":"venue"
},
  "geometry": {"coordinates":[8.999692,47.476955],"type":"Point"}
}