{
  "type": "Feature",
  "properties": {
    "iso:country":"CH",
    "sg:address":"L\u00e4nggassstrasse 46 3012 Bern. Postfach",
    "sg:city":"Bern",
    "sg:orig_category":"Herstellung von Arbeits U Berufsbekleidung",
    "sg:phone":"+41 62 926 11 36",
    "sg:postcode":"3001",
    "sg:province":"Bern",
    "wof:name":"Hatex Ag Berufskleidung",
    "wof:placetype":"venue"
},
  "geometry": {"coordinates":[7.8371567726,47.2683372498],"type":"Point"}
}