{
  "type": "Feature",
  "properties": {
    "iso:country":"CH",
    "sg:address":"Baselstrasse 58",
    "sg:city":"Riehen",
    "sg:orig_category":"Detailhandel mit Waren verschiedener Art, Hauptrichtung Nahrungsmittel",
    "sg:phone":"+41 61 641 20 30",
    "sg:postcode":"4125",
    "sg:province":"Basel-Stadt",
    "wof:name":"Denner Top Superdiscount",
    "wof:placetype":"venue"
},
  "geometry": {"coordinates":[7.6500639915,47.5856666565],"type":"Point"}
}