{
  "type": "Feature",
  "properties": {
    "iso:country":"CH",
    "sg:address":"Tobeleggweg 21",
    "sg:city":"Z\u00fcrich",
    "sg:orig_category":"Allgemeiner Hoch U Tiefbau",
    "sg:postcode":"8049",
    "sg:province":"Z\u00fcrich",
    "wof:name":"Febi Ag, Zweigniederlassung Z\u00fcrich Hoch- U. Tiefbau",
    "wof:placetype":"venue"
},
  "geometry": {"coordinates":[8.502667,47.397896],"type":"Point"}
}