{
  "type": "Feature",
  "properties": {
    "iso:country":"CH",
    "sg:address":"Kreuzlingerstrasse 50",
    "sg:city":"Weinfelden",
    "sg:classifiers":[
        {
            "category":"Farming",
            "subcategory":"Poultry Farm",
            "type":"Manufacturing & Wholesale Goods"
        }
    ],
    "sg:phone":"+41 71 622 15 22",
    "sg:postcode":"8570",
    "sg:province":"Thurgau",
    "wof:name":"Burgmer Gefl\u00fcgelzucht Ag",
    "wof:placetype":"venue"
},
  "geometry": {"coordinates":[9.1305408478,47.5653343201],"type":"Point"}
}