{
  "type": "Feature",
  "properties": {
    "iso:country":"CH",
    "sg:address":"Sennh\u00fcttenstrasse 4",
    "sg:city":"Richterswil",
    "sg:orig_category":"Sonstige mit der Informatik verbundene T\u00e4tigkeiten",
    "sg:postcode":"8805",
    "sg:province":"Z\u00fcrich",
    "wof:name":"Edv-beratung, Mannhart H.",
    "wof:placetype":"venue"
},
  "geometry": {"coordinates":[8.948554039,47.1755104065],"type":"Point"}
}