{
  "type": "Feature",
  "properties": {
    "iso:country":"CH",
    "sg:address":"Infanteriestrasse 2",
    "sg:city":"Sursee",
    "sg:orig_category":"Grosshandel mit elektrischen Haushaltsger\u00e4ten, Radio U Fernsehger\u00e4ten Herstellung von sonstigen elek",
    "sg:phone":"+41 41 921 82 66",
    "sg:postcode":"6210",
    "sg:province":"Luzern",
    "wof:name":"Sigmatic Ag",
    "wof:placetype":"venue"
},
  "geometry": {"coordinates":[8.105178833,47.1793556213],"type":"Point"}
}