{
  "type": "Feature",
  "properties": {
    "iso:country":"CH",
    "sg:address":"Schoorenstrasse 5b",
    "sg:city":"Uerikon",
    "sg:orig_category":"Elektroinstallation Herstellung von sonstigen elektrischen Ausr\u00fcstungen",
    "sg:phone":"+41 17961212",
    "sg:postcode":"8713",
    "sg:province":"Z\u00fcrich",
    "wof:name":"Tesag Kommunikations- Schwachstrom-systeme",
    "wof:placetype":"venue"
},
  "geometry": {"coordinates":[8.7531280518,47.2352752686],"type":"Point"}
}