{
  "type": "Feature",
  "properties": {
    "iso:country":"CH",
    "sg:address":"Kriessernstrasse 16",
    "sg:city":"Montlingen",
    "sg:classifiers":[
        {
            "category":"Parking",
            "subcategory":"Garage",
            "type":"Transportation"
        }
    ],
    "sg:phone":"+41 71 761 40 60",
    "sg:postcode":"9462",
    "sg:province":"St. Gallen",
    "sg:tags":[
        "carport"
    ],
    "wof:name":"H. P. Benz Gmbh",
    "wof:placetype":"venue"
},
  "geometry": {"coordinates":[9.590442,47.342422],"type":"Point"}
}