{
  "type": "Feature",
  "properties": {
    "iso:country":"CH",
    "sg:address":"Oberhittnau",
    "sg:city":"Hittnau",
    "sg:orig_category":"G\u00fcterbef\u00f6rderung im Strassenverkehr",
    "sg:postcode":"8335",
    "sg:province":"Z\u00fcrich",
    "wof:name":"Hans R\u00fcegg, Autotransporte",
    "wof:placetype":"venue"
},
  "geometry": {"coordinates":[8.8222799301,47.3610916138],"type":"Point"}
}