{
  "type": "Feature",
  "properties": {
    "iso:country":"CH",
    "sg:address":"Freie Strasse 45 4051 Basel. Postfach",
    "sg:city":"Basel",
    "sg:orig_category":"Pensionskassen",
    "sg:phone":"+41 61 261 91 78",
    "sg:postcode":"4001",
    "sg:province":"Basel-Stadt",
    "wof:name":"Wohlfahrtsstiftung Des Heimatwerkes Basel",
    "wof:placetype":"venue"
},
  "geometry": {"coordinates":[7.5910711288,47.5552253723],"type":"Point"}
}