{
  "type": "Feature",
  "properties": {
    "addr:full":"K\u00f6niztalstrasse 22 K\u00f6niz Bern 3098",
    "addr:housenumber":"22",
    "addr:postcode":"3098",
    "addr:street":"Koeniztalstrasse",
    "iso:country":"CH",
    "sg:address":"K\u00f6niztalstrasse 22",
    "sg:city":"K\u00f6niz",
    "sg:orig_category":"Detailhandel mit Antiquit\u00e4ten",
    "sg:phone":"+41 79 301 97 38",
    "sg:postcode":"3098",
    "sg:province":"Bern",
    "wof:name":"Beat L\u00fcthi Antiquit\u00e4ten",
    "wof:placetype":"venue"
},
  "geometry": {"coordinates":[7.420047,46.917374],"type":"Point"}
}