{
  "type": "Feature",
  "properties": {
    "iso:country":"CH",
    "sg:address":"Hinterflueweg 8",
    "sg:city":"Kerns",
    "sg:orig_category":"Allgemeiner Hoch U Tiefbau Elektroinstallation",
    "sg:phone":"+41 79 415 63 47",
    "sg:postcode":"6064",
    "sg:province":"Obwalden",
    "wof:name":"Baumeler Leitungsbau Ag",
    "wof:placetype":"venue"
},
  "geometry": {"coordinates":[8.270231,46.900219],"type":"Point"}
}