{
  "type": "Feature",
  "properties": {
    "iso:country":"CH",
    "sg:address":"Avenue De Savoie 10 1003 Lausanne Case Postale 1135",
    "sg:city":"Lausanne",
    "sg:orig_category":"Verm\u00f6gensverwaltung",
    "sg:phone":"+41 17716855",
    "sg:postcode":"1001",
    "sg:province":"Vaud",
    "wof:name":"Norwisa Ag",
    "wof:placetype":"venue"
},
  "geometry": {"coordinates":[8.5484485626,47.3215179443],"type":"Point"}
}