{
  "type": "Feature",
  "properties": {
    "iso:country":"CH",
    "sg:address":"Ch. De Buchaux 34 2022 Bevaix Case Postale",
    "sg:city":"Bevaix",
    "sg:orig_category":"Satzherstellung U Reproduktion",
    "sg:phone":"+41 79 285 32 41",
    "sg:postcode":"2022",
    "sg:province":"Neuch\u00e2tel",
    "wof:name":"Manfred Rathfelder Photolithographie",
    "wof:placetype":"venue"
},
  "geometry": {"coordinates":[6.82918787,47.1067962646],"type":"Point"}
}