{
  "type": "Feature",
  "properties": {
    "iso:country":"CH",
    "sg:address":"Stadtbachstrasse 36b",
    "sg:city":"Bern",
    "sg:orig_category":"Institutionen f\u00fcr Finanzierungsleasing",
    "sg:phone":"+41 31 302 11 00",
    "sg:postcode":"3012",
    "sg:province":"Bern",
    "wof:name":"Savino Di Muro Auto-leasing",
    "wof:placetype":"venue"
},
  "geometry": {"coordinates":[7.4328632355,46.9490623474],"type":"Point"}
}