{
  "type": "Feature",
  "properties": {
    "addr:full":"Lagerstrasse 8 Dietikon Z\u00fcrich 8953",
    "addr:housenumber":"8",
    "addr:postcode":"8953",
    "addr:street":"Lagerstrasse",
    "iso:country":"CH",
    "sg:address":"Lagerstrasse 8",
    "sg:city":"Dietikon",
    "sg:classifiers":[
        {
            "category":"Transit Center",
            "subcategory":"Freight",
            "type":"Transportation"
        }
    ],
    "sg:phone":"+41 17433333",
    "sg:postcode":"8953",
    "sg:province":"Z\u00fcrich",
    "sg:tags":[
        "adhesive",
        "double-sided",
        "tapes",
        "also"
    ],
    "wof:name":"Kvt Koenig Verbindungstechnik Ag",
    "wof:placetype":"venue"
},
  "geometry": {"coordinates":[8.400095,47.41013],"type":"Point"}
}