{
  "type": "Feature",
  "properties": {
    "iso:country":"CH",
    "sg:address":"Boulevard De P\u00e9rolles 55",
    "sg:city":"Fribourg",
    "sg:orig_category":"Finanzierungsinstitutionen",
    "sg:phone":"+41 12710337",
    "sg:postcode":"1700",
    "sg:province":"Fribourg",
    "wof:name":"Refinanz Und Beteiligungs-ag",
    "wof:placetype":"venue"
},
  "geometry": {"coordinates":[8.6287937164,47.4124526978],"type":"Point"}
}