{
  "type": "Feature",
  "properties": {
    "iso:country":"CH",
    "sg:address":"7603",
    "sg:city":"Vicosoprano",
    "sg:orig_category":"Detailhandel mit Fleisch U Fleischwaren",
    "sg:phone":"+41 31 701 02 01",
    "sg:postcode":"7603",
    "sg:province":"Graubunden",
    "wof:name":"Chr. Gerber S\u00f6hne Ag Tanne Metzgerei",
    "wof:placetype":"venue"
},
  "geometry": {"coordinates":[7.6482429504,46.9479789734],"type":"Point"}
}