{
  "type": "Feature",
  "properties": {
    "iso:country":"CH",
    "sg:address":"Bahnhofstrasse 9 6340 Baar. Postfach 140",
    "sg:city":"Baar",
    "sg:orig_category":"Herstellung von Metallerzeugnissen ohne Maschinenbau Maschinenbau",
    "sg:phone":"+41 41 760 54 91",
    "sg:postcode":"6340",
    "sg:province":"Zug",
    "wof:name":"Dimatec Betriebssystem Ag",
    "wof:placetype":"venue"
},
  "geometry": {"coordinates":[8.5244979858,47.1954307556],"type":"Point"}
}