{
  "type": "Feature",
  "properties": {
    "iso:country":"CH",
    "sg:address":"Kapellenstrasse 7",
    "sg:city":"Bern",
    "sg:orig_category":"Unternehmensberatung",
    "sg:phone":"+41 31 371 70 11",
    "sg:postcode":"3011",
    "sg:province":"Bern",
    "wof:name":"Peter G. Winter",
    "wof:placetype":"venue"
},
  "geometry": {"coordinates":[7.4354381561,46.9445152283],"type":"Point"}
}