{
  "type": "Feature",
  "properties": {
    "iso:country":"CH",
    "sg:address":"Bleichemattstrasse 19",
    "sg:city":"Biberist",
    "sg:orig_category":"Herstellung von Tanks U Sammelbeh\u00e4ltern aus Metall Reinigungsgewerbe",
    "sg:phone":"+41 32 672 27 24",
    "sg:postcode":"4562",
    "sg:province":"Solothurn",
    "wof:name":"Kopp Tankrevisionen Gmbh",
    "wof:placetype":"venue"
},
  "geometry": {"coordinates":[7.5611400604,47.180431366],"type":"Point"}
}