{
  "type": "Feature",
  "properties": {
    "iso:country":"CH",
    "sg:address":"Eichelackerstrasse 21",
    "sg:city":"Adlikon",
    "sg:classifiers":[
        {
            "category":"Building & Trades",
            "subcategory":"Construction",
            "type":"Services"
        }
    ],
    "sg:phone":"+41 18410065",
    "sg:postcode":"8106",
    "sg:province":"Z\u00fcrich",
    "sg:tags":[
        "ceiling"
    ],
    "wof:name":"Daniel Bischoff Montagen",
    "wof:placetype":"venue"
},
  "geometry": {"coordinates":[8.459126,47.454151],"type":"Point"}
}