{
  "type": "Feature",
  "properties": {
    "iso:country":"CH",
    "sg:address":"Zwicky Areal Neugut 80",
    "sg:city":"Wallisellen",
    "sg:orig_category":"Herstellung von Konstruktionsteilen, Fertigbauteilen U Ausbauelementen aus Holz Innenausbau",
    "sg:phone":"+41 81 936 77 36",
    "sg:postcode":"8304",
    "sg:province":"Z\u00fcrich",
    "wof:name":"Marugg Schreinerei Gmbh",
    "wof:placetype":"venue"
},
  "geometry": {"coordinates":[9.2819824219,46.8325805664],"type":"Point"}
}