{
  "type": "Feature",
  "properties": {
    "iso:country":"CH",
    "sg:address":"Bergli",
    "sg:city":"Linthal",
    "sg:classifiers":[
        {
            "category":"Travel",
            "subcategory":"Hotels & Motels",
            "type":"Entertainment"
        }
    ],
    "sg:postcode":"8783",
    "sg:province":"Glarus",
    "sg:tags":[
        "hotels",
        "mit",
        "restaurant"
    ],
    "wof:name":"Zweifel Bergli Ag",
    "wof:placetype":"venue"
},
  "geometry": {"coordinates":[8.9786653519,46.9087791443],"type":"Point"}
}