{
  "type": "Feature",
  "properties": {
    "iso:country":"CH",
    "sg:address":"Hardgutstrasse 16",
    "sg:city":"Z\u00fcrich",
    "sg:orig_category":"Detektivb\u00fcros U \u00dcberwachung",
    "sg:phone":"+41 12892300",
    "sg:postcode":"8048",
    "sg:province":"Z\u00fcrich",
    "wof:name":"Michel, Rossi & Ravanello Gss Security Personenschutz, Bewachung, Informationsbeschaffung",
    "wof:placetype":"venue"
},
  "geometry": {"coordinates":[8.5030097961,47.3845214844],"type":"Point"}
}