{
  "type": "Feature",
  "properties": {
    "iso:country":"CH",
    "sg:address":"Industriestr. 4",
    "sg:city":"Altst\u00e4tten",
    "sg:classifiers":[
        {
            "category":"Shopping",
            "subcategory":"Bicycles & Sporting Goods",
            "type":"Retail Goods"
        }
    ],
    "sg:phone":"+41 71 757 73 73",
    "sg:postcode":"9450",
    "sg:province":"St. Gallen",
    "sg:tags":[
        "product",
        "sport",
        "miscellaneous"
    ],
    "wof:name":"Toko Ag",
    "wof:placetype":"venue"
},
  "geometry": {"coordinates":[9.5571689606,47.3769493103],"type":"Point"}
}