{
  "type": "Feature",
  "properties": {
    "iso:country":"CH",
    "sg:address":"Sch\u00f6neggstrasse 26",
    "sg:city":"Dietikon",
    "sg:orig_category":"Arztpraxen",
    "sg:phone":"+41 17412020",
    "sg:postcode":"8953",
    "sg:province":"Z\u00fcrich",
    "wof:name":"Dr.med.theo Leutenegger Arzt F.allgemeine Medizin Fmh",
    "wof:placetype":"venue"
},
  "geometry": {"coordinates":[8.404252,47.40139],"type":"Point"}
}