{
  "type": "Feature",
  "properties": {
    "iso:country":"CH",
    "sg:address":"Sous-le-pr\u00e9 Rue 20",
    "sg:city":"B\u00f4le",
    "sg:orig_category":"Grosshandel mit sonstigen Maschinen U Ausr\u00fcstungen f\u00fcr Industrie, Handel U Schiffahrt",
    "sg:postcode":"2014",
    "sg:province":"Neuch\u00e2tel",
    "wof:name":"Aquajet Sa",
    "wof:placetype":"venue"
},
  "geometry": {"coordinates":[6.8482317924,46.9680862427],"type":"Point"}
}