{
  "type": "Feature",
  "properties": {
    "iso:country":"CH",
    "sg:address":"3925",
    "sg:city":"Gr\u00e4chen",
    "sg:classifiers":[
        {
            "category":"Travel",
            "subcategory":"Hotels & Motels",
            "type":"Entertainment"
        }
    ],
    "sg:phone":"+41 27 955 23 00",
    "sg:postcode":"3925",
    "sg:province":"Valais",
    "sg:tags":[
        "hotels",
        "mit",
        "restaurant"
    ],
    "wof:name":"Aparthotel Des Alpes & Restaurant Weinstube, Ruff Familie",
    "wof:placetype":"venue"
},
  "geometry": {"coordinates":[7.8392400742,46.1961631775],"type":"Point"}
}