{
  "type": "Feature",
  "properties": {
    "iso:country":"CH",
    "sg:address":"Industriestrasse 9",
    "sg:city":"St\u00e4fa",
    "sg:orig_category":"Pensionskassen",
    "sg:phone":"+41 19281212",
    "sg:postcode":"8712",
    "sg:province":"Z\u00fcrich",
    "wof:name":"Sammelstiftung Blg",
    "wof:placetype":"venue"
},
  "geometry": {"coordinates":[8.7437953949,47.237651825],"type":"Point"}
}