{
  "type": "Feature",
  "properties": {
    "iso:country":"CH",
    "sg:address":"Wehntalerstr.108 Nassenwil",
    "sg:city":"Niederhasli",
    "sg:orig_category":"Einzelhandel mit Automobilteilen U Zubeh\u00f6r Handel mit Motorr\u00e4dern, Teilen U Zubeh\u00f6r Instandhaltung U",
    "sg:phone":"+41 18505330",
    "sg:postcode":"8155",
    "sg:province":"Z\u00fcrich",
    "wof:name":"Brico Ville Autozubeh\u00f6r Ag Auto Und T\u00f6ff Zubeh\u00f6r",
    "wof:placetype":"venue"
},
  "geometry": {"coordinates":[8.4839477539,47.4812355042],"type":"Point"}
}