{
  "type": "Feature",
  "properties": {
    "iso:country":"CH",
    "sg:address":"Rue Francillon 30",
    "sg:city":"St-imier",
    "sg:orig_category":"Versicherungen Hauptagenturen",
    "sg:phone":"+41 32 941 48 48",
    "sg:postcode":"2610",
    "sg:province":"Bern",
    "wof:name":"Zurich-assurances Agence Principale",
    "wof:placetype":"venue"
},
  "geometry": {"coordinates":[6.9997210503,47.1529083252],"type":"Point"}
}