{
  "type": "Feature",
  "properties": {
    "iso:country":"CH",
    "sg:address":"Wydacherstrasse 3",
    "sg:city":"Rubigen",
    "sg:orig_category":"Ingenieurb\u00fcros Maschinenbau Unternehmensberatung",
    "sg:phone":"+41 31 721 51 26",
    "sg:postcode":"3113",
    "sg:province":"Bern",
    "wof:name":"Hans-rudolf Frauenknecht Stengineering",
    "wof:placetype":"venue"
},
  "geometry": {"coordinates":[7.5522971153,46.9003715515],"type":"Point"}
}