{
  "type": "Feature",
  "properties": {
    "iso:country":"CH",
    "sg:address":"Piazza S.stefano",
    "sg:city":"Rancate",
    "sg:classifiers":[
        {
            "category":"Restaurant",
            "type":"Food & Drink"
        }
    ],
    "sg:phone":"+41 91 646 47 81",
    "sg:postcode":"6862",
    "sg:province":"Ticino",
    "wof:name":"Osteria Antica",
    "wof:placetype":"venue"
},
  "geometry": {"coordinates":[8.9681348801,45.8714981079],"type":"Point"}
}