{
  "type": "Feature",
  "properties": {
    "iso:country":"CH",
    "sg:address":"Via Prati Maggi",
    "sg:city":"Rancate",
    "sg:orig_category":"Grosshandel mit Getreide, Saatgut U Futtermitteln Landwirtschaft, Jagd U damit verbundene Dienstleis",
    "sg:phone":"+41 91 646 84 13",
    "sg:postcode":"6862",
    "sg:province":"Ticino",
    "wof:name":"Eliano Meroni Azienda Agricola",
    "wof:placetype":"venue"
},
  "geometry": {"coordinates":[8.9760131836,45.8869743347],"type":"Point"}
}