{
  "type": "Feature",
  "properties": {
    "iso:country":"CH",
    "sg:address":"Im Sch\u00f6rli 5",
    "sg:city":"D\u00fcbendorf",
    "sg:classifiers":[
        {
            "category":"Professional",
            "subcategory":"Computer Services",
            "type":"Services"
        }
    ],
    "sg:phone":"+41 61 486 66 00",
    "sg:postcode":"8600",
    "sg:province":"Z\u00fcrich",
    "sg:tags":[
        "information",
        "technology",
        "software"
    ],
    "wof:name":"Cad Rechenzentrum Ag",
    "wof:placetype":"venue"
},
  "geometry": {"coordinates":[7.5459961891,47.5587730408],"type":"Point"}
}