{
  "type": "Feature",
  "properties": {
    "iso:country":"CH",
    "sg:address":"Luzernerstrasse 45",
    "sg:city":"Cham",
    "sg:orig_category":"Grosshandel mit sonstigen Maschinen U Ausr\u00fcstungen f\u00fcr Industrie, Handel U Schiffahrt",
    "sg:postcode":"6330",
    "sg:province":"Zug",
    "wof:name":"Celludur Ag",
    "wof:placetype":"venue"
},
  "geometry": {"coordinates":[8.4545249939,47.1773834229],"type":"Point"}
}