{
  "type": "Feature",
  "properties": {
    "iso:country":"CH",
    "sg:address":"Jaquet Rue Jean- 15 1201 Gen\u00e8ve. Postfach",
    "sg:city":"Gen\u00e8ve",
    "sg:orig_category":"Mechanik",
    "sg:phone":"+41 52 337 11 43",
    "sg:postcode":"1207",
    "sg:province":"Gen\u00e8ve",
    "wof:name":"Rubin R.",
    "wof:placetype":"venue"
},
  "geometry": {"coordinates":[8.7976875305,47.5521469116],"type":"Point"}
}