{
  "type": "Feature",
  "properties": {
    "iso:country":"CH",
    "sg:address":"Leimenstrasse 48",
    "sg:city":"Basel",
    "sg:orig_category":"Unclassifiable Establishments",
    "sg:postcode":"4051",
    "sg:province":"Basel-Stadt",
    "wof:name":"Stiftung Christlich-j\u00fcdische Projekte",
    "wof:placetype":"venue"
},
  "geometry": {"coordinates":[7.5814261436,47.5532531738],"type":"Point"}
}