{
  "type": "Feature",
  "properties": {
    "iso:country":"CH",
    "sg:address":"Kasernenstrasse 17a 9100 Herisau. Postfach",
    "sg:city":"Herisau",
    "sg:orig_category":"Umwelt\u00e4mter",
    "sg:phone":"+41 71 353 61 11",
    "sg:postcode":"9102",
    "sg:province":"Appenzell Ausserrhoden",
    "wof:name":"Kantonale Umweltschutz-& Energiedirektion",
    "wof:placetype":"venue"
},
  "geometry": {"coordinates":[9.2824478149,47.3862838745],"type":"Point"}
}