{
  "type": "Feature",
  "properties": {
    "iso:country":"CH",
    "sg:address":"R\u00fctistrasse 21",
    "sg:city":"Schlieren",
    "sg:orig_category":"Gewinnung von Kies U Sand Herstellung von Transportbeton",
    "sg:phone":"+41 58 850 02 70",
    "sg:postcode":"8952",
    "sg:province":"Z\u00fcrich",
    "wof:name":"Kieswerk H\u00fcntwangen Ag Betonwerk Schlieren",
    "wof:placetype":"venue"
},
  "geometry": {"coordinates":[8.4535255432,47.4009246826],"type":"Point"}
}