{
  "type": "Feature",
  "properties": {
    "iso:country":"CH",
    "sg:address":"Rue De La Sagne 8",
    "sg:city":"Ste-croix",
    "sg:orig_category":"Vereine Radio, Film and Foto",
    "sg:phone":"+41 24 454 33 27",
    "sg:postcode":"1450",
    "sg:province":"Vaud",
    "wof:name":"Photo-cin\u00e9-club",
    "wof:placetype":"venue"
},
  "geometry": {"coordinates":[6.5017199516,46.8201141357],"type":"Point"}
}