{
  "type": "Feature",
  "properties": {
    "iso:country":"CH",
    "sg:address":"Jurastrasse 1",
    "sg:city":"Solothurn",
    "sg:orig_category":"Instandhaltung U Reparatur von Automobilen",
    "sg:phone":"+41 32 623 63 73",
    "sg:postcode":"4500",
    "sg:province":"Solothurn",
    "wof:name":"Ring-garage Carlo Pina",
    "wof:placetype":"venue"
},
  "geometry": {"coordinates":[7.5206699371,47.21251297],"type":"Point"}
}