{
  "type": "Feature",
  "properties": {
    "iso:country":"CH",
    "sg:address":"Brunnackerstrasse 2",
    "sg:city":"Lyssach",
    "sg:orig_category":"Grosshandel mit Schuhen",
    "sg:phone":"+41 34 445 01 70",
    "sg:postcode":"3421",
    "sg:province":"Bern",
    "wof:name":"Eugen Glauser Schuhagentur",
    "wof:placetype":"venue"
},
  "geometry": {"coordinates":[7.5816907883,47.0636138916],"type":"Point"}
}