{
  "type": "Feature",
  "properties": {
    "iso:country":"CH",
    "sg:address":"Weissensteinstrasse 29a",
    "sg:city":"Bern",
    "sg:orig_category":"Detailhandel mit Bekleidung Detailhandel mit Waren verschiedener Art, Hauptrichtung Nahrungsmittel",
    "sg:phone":"+41 31 371 77 59",
    "sg:postcode":"3008",
    "sg:province":"Bern",
    "wof:name":"Biolino",
    "wof:placetype":"venue"
},
  "geometry": {"coordinates":[7.419584,46.94099],"type":"Point"}
}