{
  "type": "Feature",
  "properties": {
    "iso:country":"CH",
    "sg:address":"1757",
    "sg:city":"Nor\u00e9az",
    "sg:orig_category":"Gemeindeverwaltungen",
    "sg:phone":"+41 26 470 23 19",
    "sg:postcode":"1757",
    "sg:province":"Fribourg",
    "wof:name":"Administration Communale De Nor\u00e9az",
    "wof:placetype":"venue"
},
  "geometry": {"coordinates":[7.0277352333,46.8016815186],"type":"Point"}
}