{
  "type": "Feature",
  "properties": {
    "iso:country":"CH",
    "sg:address":"Vordere P\u00fcntackerstrasse 3",
    "sg:city":"St\u00e4fa",
    "sg:orig_category":"Herstellung von sonstigen Metallwaren",
    "sg:phone":"+41 17962288",
    "sg:postcode":"8712",
    "sg:province":"Z\u00fcrich",
    "wof:name":"Gut G. Ag",
    "wof:placetype":"venue"
},
  "geometry": {"coordinates":[8.7197179794,47.249420166],"type":"Point"}
}