{
  "type": "Feature",
  "properties": {
    "iso:country":"CH",
    "sg:address":"Hauptstrasse 40",
    "sg:city":"Derendingen",
    "sg:orig_category":"Fachdetailhandel in Verkaufsr\u00e4umen",
    "sg:phone":"+41 32 682 20 20",
    "sg:postcode":"4552",
    "sg:province":"Solothurn",
    "wof:name":"Frei Otto",
    "wof:placetype":"venue"
},
  "geometry": {"coordinates":[7.5853190422,47.1952972412],"type":"Point"}
}