{
  "type": "Feature",
  "properties": {
    "iso:country":"CH",
    "sg:address":"Schulhausstrasse 1",
    "sg:city":"Horw",
    "sg:orig_category":"Non-Classified Establishments",
    "sg:postcode":"6048",
    "sg:province":"Luzern",
    "wof:name":"R. Eggimann",
    "wof:placetype":"venue"
},
  "geometry": {"coordinates":[7.8477888107,47.0466003418],"type":"Point"}
}