{
  "type": "Feature",
  "properties": {
    "iso:country":"CH",
    "sg:address":"Cantonale Via",
    "sg:city":"Claro",
    "sg:orig_category":"Allgemeiner Hoch U Tiefbau",
    "sg:phone":"+41 91 863 10 80",
    "sg:postcode":"6702",
    "sg:province":"Ticino",
    "wof:name":"Edilmera Sagl",
    "wof:placetype":"venue"
},
  "geometry": {"coordinates":[9.016418,46.265312],"type":"Point"}
}