{
  "type": "Feature",
  "properties": {
    "iso:country":"CH",
    "sg:address":"Babengasse 1 3930 Visp Case Postale 368",
    "sg:city":"Visp",
    "sg:orig_category":"K\u00fcnstlerische Schulen",
    "sg:phone":"+41 27 946 55 52",
    "sg:postcode":"3930",
    "sg:province":"Valais",
    "wof:name":"Musikschule Oberwallis Allgemeine",
    "wof:placetype":"venue"
},
  "geometry": {"coordinates":[7.8817000389,46.2906951904],"type":"Point"}
}