{
  "type": "Feature",
  "properties": {
    "iso:country":"CH",
    "sg:address":"Rue Des Eaux-vives 76",
    "sg:city":"Gen\u00e8ve",
    "sg:orig_category":"Detailhandel mit elektrischen Haushalts-,Radio U Fernsehger\u00e4ten sowie Musikinstrumenten Kunsthandel",
    "sg:phone":"+41 22 700 25 43",
    "sg:postcode":"1207",
    "sg:province":"Gen\u00e8ve",
    "wof:name":"Quatuor Sa",
    "wof:placetype":"venue"
},
  "geometry": {"coordinates":[6.1594400406,46.2046012878],"type":"Point"}
}