{
  "type": "Feature",
  "properties": {
    "iso:country":"CH",
    "sg:address":"Rh\u00f4ne Route Du",
    "sg:city":"Monthey",
    "sg:orig_category":"Herstellung von Metallkonstruktionen",
    "sg:postcode":"1870",
    "sg:province":"Valais",
    "wof:name":"Technotube Sa, Succursale De Villeneuve (vd) Montages Industriels, Constructions M\u00e9talliques Et La Tuyauterie",
    "wof:placetype":"venue"
},
  "geometry": {"coordinates":[6.926129818,46.3981781006],"type":"Point"}
}