{
  "type": "Feature",
  "properties": {
    "iso:country":"CH",
    "sg:address":"Badener-landstrasse 7",
    "sg:city":"Rafz",
    "sg:orig_category":"Vereine Heimatschutz",
    "sg:phone":"+41 18690088",
    "sg:postcode":"8197",
    "sg:province":"Z\u00fcrich",
    "wof:name":"Vereinigung Pro Rafz",
    "wof:placetype":"venue"
},
  "geometry": {"coordinates":[8.5372772217,47.610118866],"type":"Point"}
}