{
  "type": "Feature",
  "properties": {
    "iso:country":"CH",
    "sg:address":"St. Alban-anlage 33 4052 Basel. Postfach",
    "sg:city":"Basel",
    "sg:orig_category":"Grosshandel mit Textilien",
    "sg:phone":"+41 41 930 32 32",
    "sg:postcode":"4051",
    "sg:province":"Basel-Stadt",
    "wof:name":"Birke Handelshalle Ag",
    "wof:placetype":"venue"
},
  "geometry": {"coordinates":[8.1540994644,47.2197227478],"type":"Point"}
}