{
  "type": "Feature",
  "properties": {
    "iso:country":"CH",
    "sg:address":"Bella Riva 9",
    "sg:city":"Capolago",
    "sg:orig_category":"Erbringung von Dienstleistungen f\u00fcr Unternehmen",
    "sg:phone":"+41 91 994 22 71",
    "sg:postcode":"6825",
    "sg:province":"Ticino",
    "wof:name":"Verim Sa, Lussemburgo, Succursale Di Capolago",
    "wof:placetype":"venue"
},
  "geometry": {"coordinates":[8.9832906723,45.9092178345],"type":"Point"}
}