{
  "type": "Feature",
  "properties": {
    "iso:country":"CH",
    "sg:address":"B\u00fchlstrasse 43 8055 Z\u00fcrich. Postfach",
    "sg:city":"Z\u00fcrich",
    "sg:orig_category":"Vereine Gemeinn\u00fctzige",
    "sg:phone":"+41 14501932",
    "sg:postcode":"8045",
    "sg:province":"Z\u00fcrich",
    "wof:name":"Zukunft F\u00fcr Bosnien (bih) Humanit\u00e4rer Verein",
    "wof:placetype":"venue"
},
  "geometry": {"coordinates":[8.5134878159,47.3655014038],"type":"Point"}
}