{
  "type": "Feature",
  "properties": {
    "iso:country":"CH",
    "sg:address":"Alpsteinstrasse 14",
    "sg:city":"Weinfelden",
    "sg:orig_category":"Alters U Pflegeheime Institutionen f\u00fcr Behinderte",
    "sg:phone":"+41 71 622 32 36",
    "sg:postcode":"8570",
    "sg:province":"Thurgau",
    "wof:name":"Pflegeheim Weinfelden",
    "wof:placetype":"venue"
},
  "geometry": {"coordinates":[9.119856,47.563877],"type":"Point"}
}