{
  "type": "Feature",
  "properties": {
    "iso:country":"CH",
    "sg:address":"Im Holzerhurd 35 8046 Z\u00fcrich. Postfach",
    "sg:city":"Z\u00fcrich",
    "sg:orig_category":"Herstellung von sonstigen elektrischen Ausr\u00fcstungen",
    "sg:postcode":"8046",
    "sg:province":"Z\u00fcrich",
    "wof:name":"Pavlovic Elektronik",
    "wof:placetype":"venue"
},
  "geometry": {"coordinates":[8.4946832657,47.4239425659],"type":"Point"}
}