{
  "type": "Feature",
  "properties": {
    "iso:country":"CH",
    "sg:address":"Gliserallee 93",
    "sg:city":"Glis",
    "sg:orig_category":"Interessenvertretungen U sonstige Vereinigungen Organisationen der Wohlfahrtspflege",
    "sg:phone":"+41 27 923 24 21",
    "sg:postcode":"3902",
    "sg:province":"Valais",
    "wof:name":"Gaby Armangau Pro Juventute D.bezirkes Brig",
    "wof:placetype":"venue"
},
  "geometry": {"coordinates":[7.9828219414,46.3131790161],"type":"Point"}
}