{
  "type": "Feature",
  "properties": {
    "addr:full":"Steinerstrasse 42 Diessenhofen Thurgau 8253",
    "addr:housenumber":"42",
    "addr:postcode":"8253",
    "addr:street":"Steinerstrasse",
    "iso:country":"CH",
    "sg:address":"Steinerstrasse 42",
    "sg:city":"Diessenhofen",
    "sg:orig_category":"Bauspenglerei Zimmerei, Dachdeckerei, Bauspenglerei U Abdichtung",
    "sg:phone":"+41 52 657 27 37",
    "sg:postcode":"8253",
    "sg:province":"Thurgau",
    "wof:name":"Thomas Breitler San.installationen Spenglerei",
    "wof:placetype":"venue"
},
  "geometry": {"coordinates":[8.761358,47.685413],"type":"Point"}
}