{
  "type": "Feature",
  "properties": {
    "iso:country":"CH",
    "sg:address":"Limmattalstrasse 162 8049 Z\u00fcrich. Postfach 164",
    "sg:city":"Z\u00fcrich",
    "sg:orig_category":"Elektroinstallation Herstellung von sonstigen elektrischen Ausr\u00fcstungen",
    "sg:phone":"+41 41 930 47 47",
    "sg:postcode":"8049",
    "sg:province":"Z\u00fcrich",
    "wof:name":"Furrer Ch. Elektro Gmbh Elektroartikel, Elektronikartikel; Handel. Elektroinstallationen Usw",
    "wof:placetype":"venue"
},
  "geometry": {"coordinates":[8.1555290222,47.2190437317],"type":"Point"}
}