{
  "type": "Feature",
  "properties": {
    "iso:country":"CH",
    "sg:address":"Hitzkircherstrasse",
    "sg:city":"Gelfingen",
    "sg:orig_category":"Handel mit Motorr\u00e4dern, Teilen U Zubeh\u00f6r Instandhaltung U Reparatur von Motorr\u00e4dern",
    "sg:postcode":"6284",
    "sg:province":"Luzern",
    "wof:name":"Us Styger Urs Shocks",
    "wof:placetype":"venue"
},
  "geometry": {"coordinates":[8.2649850845,47.2174186707],"type":"Point"}
}