{
  "type": "Feature",
  "properties": {
    "iso:country":"CH",
    "sg:address":"Z\u00fcrichbergstrasse 26",
    "sg:city":"Z\u00fcrich",
    "sg:orig_category":"Schreibb\u00fcros Unternehmensberatung",
    "sg:phone":"+41 12606690",
    "sg:postcode":"8032",
    "sg:province":"Z\u00fcrich",
    "wof:name":"Sara Maria Sch\u00e4r Go Local",
    "wof:placetype":"venue"
},
  "geometry": {"coordinates":[8.5533447266,47.3734474182],"type":"Point"}
}