{
  "type": "Feature",
  "properties": {
    "iso:country":"CH",
    "sg:address":"Altsagenring 4",
    "sg:city":"Horw",
    "sg:orig_category":"Herstellung von Ger\u00e4ten der Elektrizit\u00e4tserzeugung, -verteilung u.\u00e4. -Herstellung von sonstigen elek",
    "sg:phone":"+41 41 630 37 77",
    "sg:postcode":"6048",
    "sg:province":"Luzern",
    "wof:name":"Ed Electronic Design Ag",
    "wof:placetype":"venue"
},
  "geometry": {"coordinates":[8.3077688217,46.9946365356],"type":"Point"}
}