{
  "type": "Feature",
  "properties": {
    "iso:country":"CH",
    "sg:address":"Bundesplatz 13",
    "sg:city":"Zug",
    "sg:orig_category":"Sonstiger Grosshandel",
    "sg:postcode":"6300",
    "sg:province":"Zug",
    "wof:name":"Avr Handels Und Verwaltungs Ag",
    "wof:placetype":"venue"
},
  "geometry": {"coordinates":[8.512430191,47.171672821],"type":"Point"}
}