{
  "type": "Feature",
  "properties": {
    "iso:country":"CH",
    "sg:address":"Obere Plessurstrasse 5 7000 Chur. Postfach",
    "sg:city":"Chur",
    "sg:orig_category":"Dienstleistungen von Beteiligungsgesellschaften Handelsvermittlung von Holz U Baustoffen",
    "sg:phone":"+41 81 258 33 10",
    "sg:postcode":"7002",
    "sg:province":"Graubunden",
    "wof:name":"Suncell Management Services Limited, Nassau (bahamas), Chur Branch",
    "wof:placetype":"venue"
},
  "geometry": {"coordinates":[9.5285902023,46.8486824036],"type":"Point"}
}