{
  "type": "Feature",
  "properties": {
    "addr:full":"Grenzstrasse 88 Thayngen Schaffhausen 8240",
    "addr:housenumber":"88",
    "addr:postcode":"8240",
    "addr:street":"Grenzstrasse",
    "iso:country":"CH",
    "sg:address":"Grenzstrasse 88",
    "sg:city":"Thayngen",
    "sg:orig_category":"Autotransporte M\u00f6bel Autotransporte international",
    "sg:phone":"+41 22 799 07 20",
    "sg:postcode":"8240",
    "sg:province":"Schaffhausen",
    "wof:name":"Schenker Suisse Sa Transports Bureau Palexpo",
    "wof:placetype":"venue"
},
  "geometry": {"coordinates":[6.121724,46.232517],"type":"Point"}
}