{
  "type": "Feature",
  "properties": {
    "iso:country":"CH",
    "sg:address":"Dufourstrasse 77",
    "sg:city":"Z\u00fcrich",
    "sg:orig_category":"Arztpraxen",
    "sg:phone":"+41 13836989",
    "sg:postcode":"8008",
    "sg:province":"Z\u00fcrich",
    "wof:name":"Dr.med.esther Guignard Aerztin F.allgemeine Medizin",
    "wof:placetype":"venue"
},
  "geometry": {"coordinates":[8.550514,47.360508],"type":"Point"}
}