{
  "type": "Feature",
  "properties": {
    "iso:country":"CH",
    "sg:address":"Germattstrasse 8",
    "sg:city":"Sch\u00f6tz",
    "sg:orig_category":"Herstellung von keramischen Wand U Bodenfliesen U platten Verlegen von Fliesen U Platten",
    "sg:phone":"+41 41 980 18 70",
    "sg:postcode":"6247",
    "sg:province":"Luzern",
    "wof:name":"K\u00fchnis Mark.",
    "wof:placetype":"venue"
},
  "geometry": {"coordinates":[7.9903488159,47.173538208],"type":"Point"}
}