{
  "type": "Feature",
  "properties": {
    "iso:country":"CH",
    "sg:address":"G\u00fctli",
    "sg:city":"Walzenhausen",
    "sg:orig_category":"Non-Classified Establishments",
    "sg:phone":"+41 71 888 47 07",
    "sg:postcode":"9428",
    "sg:province":"Appenzell Ausserrhoden",
    "wof:name":"Awag Wurster Walzenhausen Gmbh",
    "wof:placetype":"venue"
},
  "geometry": {"coordinates":[9.6049823761,47.4497756958],"type":"Point"}
}