{
  "type": "Feature",
  "properties": {
    "iso:country":"CH",
    "sg:address":"Kantonsstrasse 64a 3930 Visp. Postfach",
    "sg:city":"Visp",
    "sg:orig_category":"Herstellung von Werkzeugmaschinen f\u00fcr die Metallbearbeitung Mechanische Werkst\u00e4tten",
    "sg:phone":"+41 55 410 17 87",
    "sg:postcode":"3930",
    "sg:province":"Valais",
    "wof:name":"Max M\u00fcller Schweisstechnik",
    "wof:placetype":"venue"
},
  "geometry": {"coordinates":[8.7975950241,47.2022972107],"type":"Point"}
}