{
  "type": "Feature",
  "properties": {
    "addr:full":"Via Moscia 2 Ascona Ticino 6612",
    "addr:housenumber":"2",
    "addr:postcode":"6612",
    "addr:street":"Via Moscia",
    "iso:country":"CH",
    "sg:address":"Via Moscia 2",
    "sg:city":"Ascona",
    "sg:classifiers":[
        {
            "category":"Bars & Pubs",
            "type":"Food & Drink"
        }
    ],
    "sg:phone":"+41 91 791 10 65",
    "sg:postcode":"6612",
    "sg:province":"Ticino",
    "sg:tags":[
        "restaurant"
    ],
    "wof:name":"Ristorante Pizzeria Lago & Piano-bar",
    "wof:placetype":"venue"
},
  "geometry": {"coordinates":[8.766336,46.154903],"type":"Point"}
}