{
  "type": "Feature",
  "properties": {
    "iso:country":"CH",
    "sg:address":"Blegistrasse 1",
    "sg:city":"Rotkreuz",
    "sg:orig_category":"Unternehmensberatung",
    "sg:phone":"+41 41 790 06 46",
    "sg:postcode":"6343",
    "sg:province":"Zug",
    "wof:name":"Sidha Gmbh",
    "wof:placetype":"venue"
},
  "geometry": {"coordinates":[8.4361276627,47.1481895447],"type":"Point"}
}