{
  "type": "Feature",
  "properties": {
    "iso:country":"CH",
    "sg:address":"Pappelweg 20",
    "sg:city":"Horgen",
    "sg:orig_category":"Non-Classified Establishments",
    "sg:postcode":"8810",
    "sg:province":"Z\u00fcrich",
    "wof:name":"Alpineevents St. Moritz Gmbh",
    "wof:placetype":"venue"
},
  "geometry": {"coordinates":[9.8381910324,46.4970664978],"type":"Point"}
}