{
  "type": "Feature",
  "properties": {
    "iso:country":"CH",
    "sg:address":"8048 Z\u00fcrich. Postfach",
    "sg:city":"Z\u00fcrich",
    "sg:orig_category":"Wirtschaftspr\u00fcfung, Steuerberatung U Treuhand",
    "sg:phone":"+41 14311366",
    "sg:postcode":"8048",
    "sg:province":"Z\u00fcrich",
    "wof:name":"Treuhandb\u00fcro H\u00e4rter Urs",
    "wof:placetype":"venue"
},
  "geometry": {"coordinates":[8.4787302017,47.3856201172],"type":"Point"}
}