{
  "type": "Feature",
  "properties": {
    "addr:full":"De-grenus Rue 7 1201 Gen\u00e8ve. Postfach Gen\u00e8ve Gen\u00e8ve 1201",
    "addr:housenumber":"7",
    "addr:postcode":"1201;postfach;1201",
    "addr:street":"Rue",
    "iso:country":"CH",
    "sg:address":"De-grenus Rue 7 1201 Gen\u00e8ve. Postfach",
    "sg:city":"Gen\u00e8ve",
    "sg:classifiers":[
        {
            "category":"Bars & Pubs",
            "type":"Food & Drink"
        }
    ],
    "sg:phone":"+41 32 351 25 03",
    "sg:postcode":"1201",
    "sg:province":"Gen\u00e8ve",
    "wof:name":"Bauleuten-bar, Reber M.",
    "wof:placetype":"venue"
},
  "geometry": {"coordinates":[7.372096,47.140003],"type":"Point"}
}