{
  "type": "Feature",
  "properties": {
    "iso:country":"CH",
    "sg:address":"Rue De Zurich 5 1200 Gen\u00e8ve. Postfach",
    "sg:city":"Gen\u00e8ve",
    "sg:orig_category":"M\u00f6belschreinereien",
    "sg:postcode":"1201",
    "sg:province":"Gen\u00e8ve",
    "wof:name":"Bolay R. Menuiserie",
    "wof:placetype":"venue"
},
  "geometry": {"coordinates":[6.1483621597,46.2111167908],"type":"Point"}
}