{
  "type": "Feature",
  "properties": {
    "iso:country":"CH",
    "sg:address":"1958",
    "sg:city":"St-l\u00e9onard",
    "sg:orig_category":"Elektroinstallation",
    "sg:phone":"+41 27 203 28 81",
    "sg:postcode":"1958",
    "sg:province":"Valais",
    "wof:name":"Bitz Electricit\u00e9 Sa",
    "wof:placetype":"venue"
},
  "geometry": {"coordinates":[7.4179301262,46.2533912659],"type":"Point"}
}