{
  "type": "Feature",
  "properties": {
    "iso:country":"CH",
    "sg:address":"B\u00fcndtenweg 5",
    "sg:city":"Suhr",
    "sg:orig_category":"Vereine Gesang",
    "sg:phone":"+41 62 842 51 89",
    "sg:postcode":"5034",
    "sg:province":"Aargau",
    "wof:name":"Gemischter Chor Suhr",
    "wof:placetype":"venue"
},
  "geometry": {"coordinates":[8.0752658844,47.3768501282],"type":"Point"}
}