{
  "type": "Feature",
  "properties": {
    "addr:full":"Birmensdorferstrasse 67 8004 Z\u00fcrich. Postfach Z\u00fcrich Z\u00fcrich 8036",
    "addr:housenumber":"67",
    "addr:postcode":"8004 zuerich. postfach;8036",
    "addr:street":"Birmensdorferstrasse",
    "iso:country":"CH",
    "sg:address":"Birmensdorferstrasse 67 8004 Z\u00fcrich. Postfach",
    "sg:city":"Z\u00fcrich",
    "sg:orig_category":"Arbeitnehmerverb\u00e4nde",
    "sg:phone":"+41 12423576",
    "sg:postcode":"8036",
    "sg:province":"Z\u00fcrich",
    "wof:name":"Gewerkschaft Verkauf Handel Transport Lebensmittel",
    "wof:placetype":"venue"
},
  "geometry": {"coordinates":[8.524483,47.371227],"type":"Point"}
}