{
  "type": "Feature",
  "properties": {
    "iso:country":"CH",
    "sg:address":"Vadianstrasse 54",
    "sg:city":"St.gallen",
    "sg:orig_category":"Sonstige mit der Informatik verbundene T\u00e4tigkeiten Webdesign",
    "sg:phone":"+41 71 228 00 10",
    "sg:postcode":"9000",
    "sg:province":"St. Gallen",
    "wof:name":"Solution Studios Gmbh Internet",
    "wof:placetype":"venue"
},
  "geometry": {"coordinates":[9.3673906326,47.4205131531],"type":"Point"}
}