{
  "type": "Feature",
  "properties": {
    "iso:country":"CH",
    "sg:address":"Ch. Gd. Voiret 29b",
    "sg:city":"Plan-les-ouates",
    "sg:orig_category":"Kunststoff-Produkte",
    "sg:phone":"+41 41 449 91 00",
    "sg:postcode":"1228",
    "sg:province":"Gen\u00e8ve",
    "wof:name":"Polar Ag",
    "wof:placetype":"venue"
},
  "geometry": {"coordinates":[8.326125145,47.1216583252],"type":"Point"}
}