{
  "type": "Feature",
  "properties": {
    "iso:country":"CH",
    "sg:address":"Scheideggstrasse 30 8404 Oberwinterthur. Postfach",
    "sg:city":"Winterthur",
    "sg:orig_category":"Vermietung U Verpachtung von eigenen Immobilien",
    "sg:postcode":"8404",
    "sg:province":"Z\u00fcrich",
    "wof:name":"Lerchenfeld Immobilien Gmbh",
    "wof:placetype":"venue"
},
  "geometry": {"coordinates":[9.0442752838,47.4647254944],"type":"Point"}
}