{
  "type": "Feature",
  "properties": {
    "iso:country":"CH",
    "sg:address":"Poststrasse 5",
    "sg:city":"Geroldswil",
    "sg:orig_category":"Detailhandel mit Bekleidung",
    "sg:phone":"+41 17482105",
    "sg:postcode":"8954",
    "sg:province":"Z\u00fcrich",
    "wof:name":"Rolf Altorfer Mode Altorfer",
    "wof:placetype":"venue"
},
  "geometry": {"coordinates":[8.409611,47.42292],"type":"Point"}
}