{
  "type": "Feature",
  "properties": {
    "iso:country":"CH",
    "sg:address":"Els\u00e4sserstrasse 75",
    "sg:city":"Basel",
    "sg:orig_category":"Unternehmensberatung",
    "sg:phone":"+41 61 322 70 22",
    "sg:postcode":"4056",
    "sg:province":"Basel-Stadt",
    "wof:name":"Calmbach Unternehmensberatung",
    "wof:placetype":"venue"
},
  "geometry": {"coordinates":[7.5783147812,47.5700187683],"type":"Point"}
}