{
  "type": "Feature",
  "properties": {
    "iso:country":"CH",
    "sg:address":"Baderg\u00e4ssli 15",
    "sg:city":"Aarau",
    "sg:orig_category":"Arztpraxen",
    "sg:phone":"+41 62 297 16 02",
    "sg:postcode":"5000",
    "sg:province":"Aargau",
    "wof:name":"Dr.med. Beat Huser Spezialarzt Fmh",
    "wof:placetype":"venue"
},
  "geometry": {"coordinates":[8.04999,47.391815],"type":"Point"}
}