{
  "type": "Feature",
  "properties": {
    "iso:country":"CH",
    "sg:address":"Siebenhausen",
    "sg:city":"Muolen",
    "sg:orig_category":"Politische Parteien CVP",
    "sg:phone":"+41 31 951 68 32",
    "sg:postcode":"9313",
    "sg:province":"St. Gallen",
    "wof:name":"Cvp Ortspartei Muri-g\u00fcmligen",
    "wof:placetype":"venue"
},
  "geometry": {"coordinates":[7.4908452034,46.9278717041],"type":"Point"}
}