{
  "type": "Feature",
  "properties": {
    "iso:country":"CH",
    "sg:address":"Gass",
    "sg:city":"Triengen",
    "sg:orig_category":"Herstellung von Futtermitteln f\u00fcr Nutztiere",
    "sg:postcode":"6234",
    "sg:province":"Luzern",
    "wof:name":"Grastrocknungsgenossenschaft Surental",
    "wof:placetype":"venue"
},
  "geometry": {"coordinates":[8.0766963959,47.233127594],"type":"Point"}
}