{
  "type": "Feature",
  "properties": {
    "addr:full":"Zielackerstrasse 6 Wallisellen Z\u00fcrich 8304",
    "addr:housenumber":"6",
    "addr:postcode":"8304",
    "addr:street":"Zielackerstrasse",
    "iso:country":"CH",
    "sg:address":"Zielackerstrasse 6",
    "sg:city":"Wallisellen",
    "sg:orig_category":"Architektur U Ingenieurb\u00fcros",
    "sg:phone":"+41 18301039",
    "sg:postcode":"8304",
    "sg:province":"Z\u00fcrich",
    "wof:name":"Hellmuth Kolbe Ingenieurb\u00fcro",
    "wof:placetype":"venue"
},
  "geometry": {"coordinates":[8.603286,47.414879],"type":"Point"}
}