{
  "type": "Feature",
  "properties": {
    "iso:country":"CH",
    "sg:address":"Parkweg 27",
    "sg:city":"Kleind\u00f6ttingen",
    "sg:orig_category":"Fahrschulen, Flugschulen",
    "sg:phone":"+41 79 226 84 87",
    "sg:postcode":"5314",
    "sg:province":"Aargau",
    "wof:name":"Karl Meier Autofahrschule",
    "wof:placetype":"venue"
},
  "geometry": {"coordinates":[8.2431688309,47.5698776245],"type":"Point"}
}