{
  "type": "Feature",
  "properties": {
    "iso:country":"CH",
    "sg:address":"Dachslenbergstrasse 12",
    "sg:city":"B\u00fclach",
    "sg:orig_category":"Kosmetikinstitute",
    "sg:phone":"+41 18605261",
    "sg:postcode":"8180",
    "sg:province":"Z\u00fcrich",
    "wof:name":"Petra Silligmann Kosmetikinstitut",
    "wof:placetype":"venue"
},
  "geometry": {"coordinates":[8.5451869965,47.5218772888],"type":"Point"}
}