{
  "type": "Feature",
  "properties": {
    "iso:country":"CH",
    "sg:address":"Via Pico 26 6900 Lugano. Postfach 6906 Lugano",
    "sg:city":"Caselle",
    "sg:orig_category":"RESTAURANTS: TEA-ROOMS",
    "sg:postcode":"6",
    "wof:name":"Al Risto Sagl",
    "wof:placetype":"venue"
},
  "geometry": {"coordinates":[8.9696578979,46.0079994202],"type":"Point"}
}