{
  "type": "Feature",
  "properties": {
    "addr:full":"Ruchfeldstr. 15 M\u00fcnchenstein Basel-Landschaft 4142",
    "addr:housenumber":"15",
    "addr:postcode":"4142",
    "addr:street":"Ruchfeldstr.",
    "iso:country":"CH",
    "sg:address":"Ruchfeldstr. 15",
    "sg:city":"M\u00fcnchenstein",
    "sg:classifiers":[
        {
            "category":"Food & Beverages",
            "subcategory":"Fruits & Vegetables",
            "type":"Retail Goods"
        }
    ],
    "sg:phone":"+41 61 415 55 55",
    "sg:postcode":"4142",
    "sg:province":"Basel-Landschaft",
    "sg:tags":[
        "frozen",
        "product",
        "related"
    ],
    "wof:name":"Migros Gen.",
    "wof:placetype":"venue"
},
  "geometry": {"coordinates":[7.617346,47.520889],"type":"Point"}
}