{
  "type": "Feature",
  "properties": {
    "iso:country":"CH",
    "sg:address":"Haspiweg 6",
    "sg:city":"Krauchthal",
    "sg:orig_category":"Sportvereine Turnen Vereine Damen",
    "sg:phone":"+41 41 850 26 72",
    "sg:postcode":"3326",
    "sg:province":"Bern",
    "wof:name":"Damenturnverein Stv K\u00fcssnacht",
    "wof:placetype":"venue"
},
  "geometry": {"coordinates":[8.440328598,47.0850486755],"type":"Point"}
}