{
  "type": "Feature",
  "properties": {
    "iso:country":"CH",
    "sg:address":"G\u00fcterstrasse 137 4053 Basel. Postfach 3046",
    "sg:city":"Basel",
    "sg:orig_category":"Architektur U Ingenieurb\u00fcros",
    "sg:phone":"+41 62 873 34 66",
    "sg:postcode":"4002",
    "sg:province":"Basel-Stadt",
    "wof:name":"Gruneko Ag Zweigniederlassung Stein Ag",
    "wof:placetype":"venue"
},
  "geometry": {"coordinates":[7.953335,47.544334],"type":"Point"}
}