{
  "type": "Feature",
  "properties": {
    "iso:country":"CH",
    "sg:address":"Ober-spitzenofen",
    "sg:city":"Rohrmatt",
    "sg:orig_category":"Grosshandel mit lebenden Tieren",
    "sg:phone":"+41 41 970 23 87",
    "sg:postcode":"6132",
    "sg:province":"Luzern",
    "wof:name":"Josef B\u00e4ttig Viehhandlung",
    "wof:placetype":"venue"
},
  "geometry": {"coordinates":[7.9858899117,47.082950592],"type":"Point"}
}