{
  "type": "Feature",
  "properties": {
    "iso:country":"CH",
    "sg:address":"Riond-bosson 11",
    "sg:city":"Morges",
    "sg:orig_category":"Herstellung von Betonerzeugnissen f\u00fcr den Bau Herstellung von Zement",
    "sg:phone":"+41 21 634 71 93",
    "sg:postcode":"1110",
    "sg:province":"Vaud",
    "wof:name":"B\u00e9tonfrais & Pompages Sa Fabrication, Transport Et Pompages De B\u00e9ton",
    "wof:placetype":"venue"
},
  "geometry": {"coordinates":[6.4852838516,46.5030937195],"type":"Point"}
}