{
  "type": "Feature",
  "properties": {
    "iso:country":"CH",
    "sg:address":"Universit\u00e4tstrasse 118 8006 Z\u00fcrich. Postfach",
    "sg:city":"Z\u00fcrich",
    "sg:orig_category":"Detailhandel mit Bekleidung",
    "sg:phone":"+41 13623839",
    "sg:postcode":"8001",
    "sg:province":"Z\u00fcrich",
    "wof:name":"D'arcy Helen's Design Damen- U. Herrenbekleidung; Design, Produktion, Handel",
    "wof:placetype":"venue"
},
  "geometry": {"coordinates":[8.5487,47.385433],"type":"Point"}
}