{
  "type": "Feature",
  "properties": {
    "iso:country":"CH",
    "sg:address":"Maulbeerstrasse 69",
    "sg:city":"Basel",
    "sg:orig_category":"Mit dem Versicherungsgewerbe verbundene T\u00e4tigkeiten",
    "sg:phone":"+41 79 447 77 87",
    "sg:postcode":"4058",
    "sg:province":"Basel-Stadt",
    "wof:name":"Assu Neutrale Versicherungsberatung R\u00fcefli Werner & Partner Gmbh",
    "wof:placetype":"venue"
},
  "geometry": {"coordinates":[7.603328228,47.5679550171],"type":"Point"}
}