{
  "type": "Feature",
  "properties": {
    "iso:country":"CH",
    "sg:address":"Rue Des Nouettes 5",
    "sg:city":"Reconvilier",
    "sg:orig_category":"Herstellung von Pumpen U Kompressoren",
    "sg:phone":"+41 32 481 15 14",
    "sg:postcode":"2732",
    "sg:province":"Bern",
    "wof:name":"Pomtava Sa",
    "wof:placetype":"venue"
},
  "geometry": {"coordinates":[7.220261097,47.2314987183],"type":"Point"}
}