{
  "type": "Feature",
  "properties": {
    "iso:country":"CH",
    "sg:address":"Flugplatz 8589 Sitterdorf. Postfach",
    "sg:city":"Sitterdorf",
    "sg:orig_category":"Unclassifiable Establishments",
    "sg:phone":"+41 71 422 30 31",
    "sg:postcode":"8589",
    "sg:province":"Thurgau",
    "wof:name":"Berner E. Ag",
    "wof:placetype":"venue"
},
  "geometry": {"coordinates":[9.2486686707,47.5047721863],"type":"Point"}
}