{
  "type": "Feature",
  "properties": {
    "iso:country":"CH",
    "sg:address":"Quai Ernest-ansermet 38",
    "sg:city":"Gen\u00e8ve",
    "sg:orig_category":"Innendekorationsateliers",
    "sg:phone":"+41 22 329 61 15",
    "sg:postcode":"1205",
    "sg:province":"Gen\u00e8ve",
    "wof:name":"Louis Duchosal Tapissier-d\u00e9corateur",
    "wof:placetype":"venue"
},
  "geometry": {"coordinates":[6.1302981377,46.1992416382],"type":"Point"}
}