{
  "type": "Feature",
  "properties": {
    "addr:full":"Dorfstrasse 11 Schattdorf Uri 6467",
    "addr:housenumber":"11",
    "addr:postcode":"6467",
    "addr:street":"Dorfstrasse;Uri",
    "iso:country":"CH",
    "sg:address":"Dorfstrasse 11",
    "sg:city":"Schattdorf",
    "sg:orig_category":"Detailhandel mit Blumen U Pflanzen",
    "sg:phone":"+41 41 870 14 38",
    "sg:postcode":"6467",
    "sg:province":"Uri",
    "wof:name":"Shinobu B\u00fcrgin Blumenhaus",
    "wof:placetype":"venue"
},
  "geometry": {"coordinates":[8.652538,46.865231],"type":"Point"}
}