{
  "type": "Feature",
  "properties": {
    "iso:country":"CH",
    "sg:address":"Hubelstrasse",
    "sg:city":"Sch\u00f6nried",
    "sg:orig_category":"Sanit\u00e4r, Heizungs U L\u00fcftungsinstallation Sanit\u00e4rinstallation",
    "sg:phone":"+41 33 744 37 92",
    "sg:postcode":"3778",
    "sg:province":"Bern",
    "wof:name":"Hauswirth Hansruedi, Sanit\u00e4rinstallationen Und Heizungen",
    "wof:placetype":"venue"
},
  "geometry": {"coordinates":[7.2901220322,46.5077514648],"type":"Point"}
}