{
  "type": "Feature",
  "properties": {
    "iso:country":"CH",
    "sg:address":"Bachtalen 1",
    "sg:city":"Emmenbr\u00fccke",
    "sg:orig_category":"Organisationen des Gesundheitswesen Vereine Frauen",
    "sg:phone":"+41 61 401 13 87",
    "sg:postcode":"6020",
    "sg:province":"Luzern",
    "wof:name":"Frauenverein Oberwil Spitex-organisation",
    "wof:placetype":"venue"
},
  "geometry": {"coordinates":[7.5455908775,47.5121421814],"type":"Point"}
}