{
  "type": "Feature",
  "properties": {
    "iso:country":"CH",
    "sg:address":"Route De Rombuet 31",
    "sg:city":"Attalens",
    "sg:orig_category":"Fahrschulen, Flugschulen",
    "sg:phone":"+41 79 412 75 33",
    "sg:postcode":"1616",
    "sg:province":"Fribourg",
    "wof:name":"Auto-\u00e9cole Wicht S\u00e0rl",
    "wof:placetype":"venue"
},
  "geometry": {"coordinates":[6.8528079987,46.5098571777],"type":"Point"}
}