{
  "type": "Feature",
  "properties": {
    "iso:country":"CH",
    "sg:address":"Route D'allaman 30",
    "sg:city":"Etoy",
    "sg:orig_category":"Bauschreinerei Zimmerei, Ingenieurholzbau",
    "sg:phone":"+41 19325588",
    "sg:postcode":"1163",
    "sg:province":"Vaud",
    "wof:name":"Dietliker Holzbau Ag",
    "wof:placetype":"venue"
},
  "geometry": {"coordinates":[8.785487,47.329082],"type":"Point"}
}