{
  "type": "Feature",
  "properties": {
    "iso:country":"CH",
    "sg:address":"Jolimontstrasse 18",
    "sg:city":"Erlach",
    "sg:orig_category":"Kunsthandel",
    "sg:phone":"+41 32 338 32 20",
    "sg:postcode":"3235",
    "sg:province":"Bern",
    "wof:name":"Claude Parrat Galerie Jolimont",
    "wof:placetype":"venue"
},
  "geometry": {"coordinates":[7.0921440125,47.0416412354],"type":"Point"}
}