{
  "type": "Feature",
  "properties": {
    "iso:country":"CH",
    "sg:address":"Rue Centrale",
    "sg:city":"Arveyes",
    "sg:orig_category":"Vermietung U Verpachtung von eigenen Immobilien Vermittlung von Immobilien",
    "sg:phone":"+41 24 495 13 84",
    "sg:postcode":"1884",
    "sg:province":"Vaud",
    "wof:name":"Danrol Sa Gysin Agence Immobili\u00e8re",
    "wof:placetype":"venue"
},
  "geometry": {"coordinates":[7.0609917641,46.2908401489],"type":"Point"}
}