{
  "type": "Feature",
  "properties": {
    "iso:country":"CH",
    "sg:address":"Rigistrasse 23",
    "sg:city":"Littau",
    "sg:orig_category":"Grosshandel mit sonstigen Nahrungsmitteln",
    "sg:phone":"+41 41 250 44 13",
    "sg:postcode":"6014",
    "sg:province":"Luzern",
    "wof:name":"Eismann Tiefk\u00fchlheimservice M\u00fcller Toni",
    "wof:placetype":"venue"
},
  "geometry": {"coordinates":[8.2649888992,47.050491333],"type":"Point"}
}