{
  "type": "Feature",
  "properties": {
    "iso:country":"CH",
    "sg:address":"Zentralplatz 2",
    "sg:city":"Mellingen",
    "sg:orig_category":"Wirtschaftspr\u00fcfung, Steuerberatung U Treuhand",
    "sg:phone":"+41 56 470 66 77",
    "sg:postcode":"5507",
    "sg:province":"Aargau",
    "wof:name":"Treuhand Und Steuerberatungsb\u00fcro Koller Martin",
    "wof:placetype":"venue"
},
  "geometry": {"coordinates":[8.274605751,47.4192123413],"type":"Point"}
}