{
  "type": "Feature",
  "properties": {
    "iso:country":"CH",
    "sg:address":"Hellauerstrasse 16 8226 Schleitheim. Postfach",
    "sg:city":"Schleitheim",
    "sg:orig_category":"Verwaltung von Immobilien",
    "sg:phone":"+41 52 680 23 16",
    "sg:postcode":"8226",
    "sg:province":"Schaffhausen",
    "wof:name":"Bollinger Thomas Immobilien Gmbh Immobilienhandel",
    "wof:placetype":"venue"
},
  "geometry": {"coordinates":[8.4880142212,47.7504005432],"type":"Point"}
}