{
  "type": "Feature",
  "properties": {
    "iso:country":"CH",
    "sg:address":"4563",
    "sg:city":"Gerlafingen",
    "sg:orig_category":"Non-Classified Establishments",
    "sg:postcode":"4563",
    "sg:province":"Solothurn",
    "wof:name":"Hauswirtschaftsschule",
    "wof:placetype":"venue"
},
  "geometry": {"coordinates":[7.5732898712,47.169719696],"type":"Point"}
}