{
  "type": "Feature",
  "properties": {
    "addr:full":"Hertensteinstrasse 50 Luzern Luzern 6004",
    "addr:housenumber":"50",
    "addr:postcode":"6004",
    "addr:street":"Hertensteinstrasse",
    "iso:country":"CH",
    "sg:address":"Hertensteinstrasse 50",
    "sg:city":"Luzern",
    "sg:orig_category":"Chiropraktik",
    "sg:phone":"+41 31 931 46 96",
    "sg:postcode":"6004",
    "sg:province":"Luzern",
    "wof:name":"Dr.paul Moser Chiropraktor",
    "wof:placetype":"venue"
},
  "geometry": {"coordinates":[7.515227,46.958321],"type":"Point"}
}