{
  "type": "Feature",
  "properties": {
    "iso:country":"CH",
    "sg:address":"Wilerstrasse 7",
    "sg:city":"Suberg",
    "sg:orig_category":"Elektroinstallation",
    "sg:phone":"+41 79 251 18 56",
    "sg:postcode":"3262",
    "sg:province":"Bern",
    "wof:name":"Keller Elektro",
    "wof:placetype":"venue"
},
  "geometry": {"coordinates":[7.3353347778,47.0605392456],"type":"Point"}
}