{
  "type": "Feature",
  "properties": {
    "iso:country":"CH",
    "sg:address":"Pfarrhausstrasse 8",
    "sg:city":"Lufingen",
    "sg:orig_category":"Bauschreinerei Zimmerei, Dachdeckerei, Bauspenglerei U Abdichtung",
    "sg:phone":"+41 18140444",
    "sg:postcode":"8426",
    "sg:province":"Z\u00fcrich",
    "wof:name":"Urech Holzbau Gmbh",
    "wof:placetype":"venue"
},
  "geometry": {"coordinates":[8.5953,47.492214],"type":"Point"}
}