{
  "type": "Feature",
  "properties": {
    "iso:country":"CH",
    "sg:address":"K\u00fcfergasse 2",
    "sg:city":"Ober\u00e4geri",
    "sg:orig_category":"Grosshandel mit Getr\u00e4nken",
    "sg:postcode":"6315",
    "sg:province":"Zug",
    "wof:name":"Rogenmoser R.",
    "wof:placetype":"venue"
},
  "geometry": {"coordinates":[8.612402916,47.1346282959],"type":"Point"}
}