{
  "type": "Feature",
  "properties": {
    "iso:country":"CH",
    "sg:address":"Champs-montants 14 B",
    "sg:city":"Marin-centre",
    "sg:orig_category":"Reinigungsgewerbe",
    "sg:phone":"+41 32 755 73 53",
    "sg:postcode":"2074",
    "sg:province":"Neuch\u00e2tel",
    "wof:name":"Hld Clean Consult Sa",
    "wof:placetype":"venue"
},
  "geometry": {"coordinates":[7.0001649857,47.0123138428],"type":"Point"}
}