{
  "type": "Feature",
  "properties": {
    "iso:country":"CH",
    "sg:address":"Zielackerstrasse 2",
    "sg:city":"Dietikon",
    "sg:orig_category":"Grosshandel mit sonstigen Maschinen U Ausr\u00fcstungen f\u00fcr Industrie, Handel U Schiffahrt Handelsvermitt",
    "sg:phone":"+41 55 241 16 33",
    "sg:postcode":"8953",
    "sg:province":"Z\u00fcrich",
    "wof:name":"Interalumina Gmbh Industrieprodukte; Vermittlung, Verkauf. Beratung Von Nat\u00fcrlichen U. Juristischen Personen In Technischen Belangen Usw",
    "wof:placetype":"venue"
},
  "geometry": {"coordinates":[8.840965271,47.2556686401],"type":"Point"}
}