{
  "type": "Feature",
  "properties": {
    "addr:full":"R\u00fctistrasse Th\u00f6rigen Bern 3367",
    "addr:postcode":"3367",
    "addr:street":"Ruetistrasse",
    "iso:country":"CH",
    "sg:address":"R\u00fctistrasse",
    "sg:city":"Th\u00f6rigen",
    "sg:orig_category":"Architekturb\u00fcros",
    "sg:phone":"+41 62 961 53 60",
    "sg:postcode":"3367",
    "sg:province":"Bern",
    "wof:name":"Hans L\u00fcthi Architekturb\u00fcro",
    "wof:placetype":"venue"
},
  "geometry": {"coordinates":[7.727219,47.179153],"type":"Point"}
}