{
  "type": "Feature",
  "properties": {
    "iso:country":"CH",
    "sg:address":"Kirchstrasse 39",
    "sg:city":"Rorschach",
    "sg:orig_category":"Detailhandel mit Boden U Wandbel\u00e4gen ohne Teppiche",
    "sg:phone":"+41 71 841 94 03",
    "sg:postcode":"9400",
    "sg:province":"St. Gallen",
    "wof:name":"Karl-heinz Hilgers Tapetengesch\u00e4ft",
    "wof:placetype":"venue"
},
  "geometry": {"coordinates":[9.49076,47.47702],"type":"Point"}
}