{
  "type": "Feature",
  "properties": {
    "iso:country":"CH",
    "sg:address":"Verch\u00e8re Chemin Antoine- 6",
    "sg:city":"Meyrin",
    "sg:orig_category":"Grosshandel mit Getr\u00e4nken",
    "sg:postcode":"1217",
    "sg:province":"Gen\u00e8ve",
    "wof:name":"De Oliveira Jaime",
    "wof:placetype":"venue"
},
  "geometry": {"coordinates":[6.0716810226,46.2280693054],"type":"Point"}
}