{
  "type": "Feature",
  "properties": {
    "iso:country":"CH",
    "sg:address":"Route Cantonale 68d",
    "sg:city":"Cort\u00e9bert",
    "sg:orig_category":"Autogaragen",
    "sg:phone":"+41 32 489 13 13",
    "sg:postcode":"2607",
    "sg:province":"Bern",
    "wof:name":"Le Roset Sa Garage",
    "wof:placetype":"venue"
},
  "geometry": {"coordinates":[7.106765,47.19059],"type":"Point"}
}