{
  "type": "Feature",
  "properties": {
    "iso:country":"CH",
    "sg:address":"Albisstrasse 26",
    "sg:city":"Adliswil",
    "sg:classifiers":[
        {
            "category":"Restaurant",
            "type":"Food & Drink"
        }
    ],
    "sg:phone":"+41 17106244",
    "sg:postcode":"8134",
    "sg:province":"Z\u00fcrich",
    "wof:name":"Restaurant Al'capone's",
    "wof:placetype":"venue"
},
  "geometry": {"coordinates":[8.5253915787,47.3095817566],"type":"Point"}
}