{
  "type": "Feature",
  "properties": {
    "iso:country":"CH",
    "sg:address":"Mahrenstrasse 154",
    "sg:city":"Lostorf",
    "sg:orig_category":"Herstellung von Konstruktionsteilen, Fertigbauteilen U Ausbauelementen aus Holz",
    "sg:postcode":"4654",
    "sg:province":"Solothurn",
    "wof:name":"Schreinerei Meister Hugo",
    "wof:placetype":"venue"
},
  "geometry": {"coordinates":[7.8017058372,47.0451812744],"type":"Point"}
}