{
  "type": "Feature",
  "properties": {
    "addr:full":"Wilerstrasse Sirnach Thurgau 8370",
    "addr:postcode":"8370",
    "addr:street":"Wilerstrasse",
    "iso:country":"CH",
    "sg:address":"Wilerstrasse",
    "sg:city":"Sirnach",
    "sg:orig_category":"Detailhandel mit Antiquit\u00e4ten U Gebrauchtwaren in Verkaufsr\u00e4umen",
    "sg:postcode":"8370",
    "sg:province":"Thurgau",
    "wof:name":"Stebuni Ag",
    "wof:placetype":"venue"
},
  "geometry": {"coordinates":[9.2117,47.442467],"type":"Point"}
}