{
  "type": "Feature",
  "properties": {
    "iso:country":"CH",
    "sg:address":"Chemin De Riondet 1",
    "sg:city":"Vercorin",
    "sg:orig_category":"Nationale Postdienste",
    "sg:phone":"+41 27 455 13 92",
    "sg:postcode":"3967",
    "sg:province":"Valais",
    "wof:name":"La Poste Suisse",
    "wof:placetype":"venue"
},
  "geometry": {"coordinates":[7.5301709175,46.2554931641],"type":"Point"}
}