{
  "type": "Feature",
  "properties": {
    "iso:country":"CH",
    "sg:address":"Rue De La Fenatte 5",
    "sg:city":"Bassecourt",
    "sg:classifiers":[
        {
            "category":"Utilities",
            "subcategory":"Sewage",
            "type":"Services"
        }
    ],
    "sg:phone":"+41 32 957 65 00",
    "sg:postcode":"2854",
    "sg:province":"Jura",
    "sg:tags":[
        "embossing"
    ],
    "wof:name":"Joseph Baume S.a.",
    "wof:placetype":"venue"
},
  "geometry": {"coordinates":[6.962684,47.223934],"type":"Point"}
}