{
  "type": "Feature",
  "properties": {
    "iso:country":"CH",
    "sg:address":"Bruggerstrasse 17",
    "sg:city":"Wildegg",
    "sg:orig_category":"Mahl U Sch\u00e4lm\u00fchlen",
    "sg:phone":"+41 52 745 12 67",
    "sg:postcode":"5103",
    "sg:province":"Aargau",
    "wof:name":"Karl Striegl M\u00fchle",
    "wof:placetype":"venue"
},
  "geometry": {"coordinates":[8.8274497986,47.6247596741],"type":"Point"}
}