{
  "type": "Feature",
  "properties": {
    "iso:country":"CH",
    "sg:address":"Solothurnerstrasse 231",
    "sg:city":"Olten",
    "sg:orig_category":"Reinigungsgewerbe",
    "sg:phone":"+41 32 912 55 25",
    "sg:postcode":"4600",
    "sg:province":"Solothurn",
    "wof:name":"Netteco, Eric Henry",
    "wof:placetype":"venue"
},
  "geometry": {"coordinates":[6.8147659302,47.1018981934],"type":"Point"}
}