{
  "type": "Feature",
  "properties": {
    "iso:country":"CH",
    "sg:address":"Hasenbergstrasse 42",
    "sg:city":"Dietikon",
    "sg:orig_category":"Herstellung von Konstruktionsteilen, Fertigbauteilen U Ausbauelementen aus Holz",
    "sg:phone":"+41 56 633 97 22",
    "sg:postcode":"8953",
    "sg:province":"Z\u00fcrich",
    "wof:name":"Gemo-t\u00fcren Gehrig P.",
    "wof:placetype":"venue"
},
  "geometry": {"coordinates":[8.3930768967,47.397857666],"type":"Point"}
}