{
  "type": "Feature",
  "properties": {
    "iso:country":"CH",
    "sg:address":"Eschner Strasse 24",
    "sg:city":"Schaan",
    "sg:orig_category":"K\u00fcnstlerische Schulen",
    "sg:phone":"+423 232 16 04",
    "sg:postcode":"9494",
    "wof:name":"Werner Beck Handharmonikaschule",
    "wof:placetype":"venue"
},
  "geometry": {"coordinates":[9.5170326233,47.1718101501],"type":"Point"}
}