{
  "type": "Feature",
  "properties": {
    "iso:country":"CH",
    "sg:address":"Hauptstrasse 10 6283 Baldegg. Postfach",
    "sg:city":"Baldegg",
    "sg:orig_category":"Herstellung von Konstruktionsteilen, Fertigbauteilen U Ausbauelementen aus Holz",
    "sg:postcode":"6283",
    "sg:province":"Luzern",
    "wof:name":"Tom Egger Gmbh",
    "wof:placetype":"venue"
},
  "geometry": {"coordinates":[8.280752182,47.1852035522],"type":"Point"}
}