{
  "type": "Feature",
  "properties": {
    "iso:country":"CH",
    "sg:address":"Boulevard De La F\u00f4ret 22",
    "sg:city":"Pully",
    "sg:orig_category":"Non-Classified Establishments",
    "sg:postcode":"1009",
    "sg:province":"Vaud",
    "wof:name":"Ir\u00e8ne Abrecht Shiatsu",
    "wof:placetype":"venue"
},
  "geometry": {"coordinates":[6.6634979248,46.520904541],"type":"Point"}
}