{
  "type": "Feature",
  "properties": {
    "iso:country":"CH",
    "sg:address":"Zentralstrasse 90",
    "sg:city":"Wettingen",
    "sg:orig_category":"Offsetdruck Satzherstellung U Reproduktion",
    "sg:phone":"+41 56 430 00 22",
    "sg:postcode":"5430",
    "sg:province":"Aargau",
    "wof:name":"Meier-druck Ag",
    "wof:placetype":"venue"
},
  "geometry": {"coordinates":[8.3218183517,47.4651870728],"type":"Point"}
}