{
  "type": "Feature",
  "properties": {
    "iso:country":"CH",
    "sg:address":"Engelbergstrasse 34 6370 Stans. Postfach 1240",
    "sg:city":"Stans",
    "sg:orig_category":"Verwaltung Inneres",
    "sg:phone":"+41 22 319 21 11",
    "sg:postcode":"6371",
    "sg:province":"Nidwalden",
    "wof:name":"D\u00e9partement De L'int\u00e9rieur & De L'agriculture",
    "wof:placetype":"venue"
},
  "geometry": {"coordinates":[6.1469349861,46.2008590698],"type":"Point"}
}