{
  "type": "Feature",
  "properties": {
    "iso:country":"CH",
    "sg:address":"Rutschbergstrasse 5",
    "sg:city":"Bubikon",
    "sg:classifiers":[
        {
            "category":"Government",
            "subcategory":"Post Office",
            "type":"Public Place"
        }
    ],
    "sg:phone":"+41 55 243 24 74",
    "sg:postcode":"8608",
    "sg:province":"Z\u00fcrich",
    "sg:tags":[
        "caf\u00e9s",
        "tea-rooms"
    ],
    "wof:name":"Tea-room Rutz",
    "wof:placetype":"venue"
},
  "geometry": {"coordinates":[8.8175373077,47.268661499],"type":"Point"}
}