{
  "type": "Feature",
  "properties": {
    "iso:country":"CH",
    "sg:address":"Z\u00fcrichstrasse 16 4922 B\u00fctzberg. Postfach",
    "sg:city":"B\u00fctzberg",
    "sg:orig_category":"Druck ohne Zeitungsdruck Offsetdruck",
    "sg:phone":"+41 62 963 00 16",
    "sg:postcode":"4922",
    "sg:province":"Bern",
    "wof:name":"Offsetdruck M\u00fchlheim Ag",
    "wof:placetype":"venue"
},
  "geometry": {"coordinates":[7.7511019707,47.2164497375],"type":"Point"}
}