{
  "type": "Feature",
  "properties": {
    "iso:country":"CH",
    "sg:address":"Lehnfeldstrasse 4",
    "sg:city":"Oensingen",
    "sg:orig_category":"Fussreflexzonenmassage",
    "sg:phone":"+41 62 396 01 82",
    "sg:postcode":"4702",
    "sg:province":"Solothurn",
    "wof:name":"Jacqueline Allemann Fussreflexzonenmassage",
    "wof:placetype":"venue"
},
  "geometry": {"coordinates":[7.7038249969,47.2853736877],"type":"Point"}
}