{
  "type": "Feature",
  "properties": {
    "iso:country":"CH",
    "sg:address":"Chemin Du Prumay 5",
    "sg:city":"Echandens",
    "sg:orig_category":"Unclassifiable Establishments",
    "sg:phone":"+41 21 702 28 72",
    "sg:postcode":"1026",
    "sg:province":"Vaud",
    "wof:name":"Meldem Alain",
    "wof:placetype":"venue"
},
  "geometry": {"coordinates":[6.5412011147,46.5370140076],"type":"Point"}
}