{
  "type": "Feature",
  "properties": {
    "iso:country":"CH",
    "sg:address":"Pr\u00e4tschlistrasse",
    "sg:city":"Arosa",
    "sg:orig_category":"Detailhandel mit Lederwaren U Reiseartikeln",
    "sg:phone":"+41 81 377 36 79",
    "sg:postcode":"7050",
    "sg:province":"Graubunden",
    "wof:name":"Roswitha & Peter Moschin Coiffure-boutique Pierrot",
    "wof:placetype":"venue"
},
  "geometry": {"coordinates":[9.6742343903,46.787902832],"type":"Point"}
}