{
  "type": "Feature",
  "properties": {
    "iso:country":"CH",
    "sg:address":"Stazione Viale 19 6500 Bellinzona. Postfach",
    "sg:city":"Bellinzona",
    "sg:orig_category":"Unclassifiable Establishments",
    "sg:postcode":"6500",
    "sg:province":"Ticino",
    "wof:name":"Altair Shipping Sa",
    "wof:placetype":"venue"
},
  "geometry": {"coordinates":[9.0263080597,46.193813324],"type":"Point"}
}