{
  "type": "Feature",
  "properties": {
    "iso:country":"CH",
    "sg:address":"Vieux-chemin-d'onex 22",
    "sg:city":"Petit-lancy",
    "sg:orig_category":"Softwareentwicklung U beratung",
    "sg:postcode":"1213",
    "sg:province":"Gen\u00e8ve",
    "wof:name":"Constructiva Ag",
    "wof:placetype":"venue"
},
  "geometry": {"coordinates":[8.8822011948,47.1988563538],"type":"Point"}
}