{
  "type": "Feature",
  "properties": {
    "iso:country":"CH",
    "sg:address":"Wasserturmplatz 5",
    "sg:city":"Liestal",
    "sg:orig_category":"Saunas, Solarien, Fitnesszentren U \u00e4hnliches",
    "sg:phone":"+41 61 921 64 63",
    "sg:postcode":"4410",
    "sg:province":"Basel-Landschaft",
    "wof:name":"Kosmos Sonnenstudio Gmbh",
    "wof:placetype":"venue"
},
  "geometry": {"coordinates":[7.7351241112,47.4827041626],"type":"Point"}
}