{
  "type": "Feature",
  "properties": {
    "iso:country":"CH",
    "sg:address":"Le Ch\u00e2telard",
    "sg:city":"Vex",
    "sg:orig_category":"Museen",
    "sg:postcode":"1981",
    "sg:province":"Valais",
    "wof:name":"Fondation En Faveur De La Collection De Chasse Badan Henri",
    "wof:placetype":"venue"
},
  "geometry": {"coordinates":[7.4009318352,46.2150115967],"type":"Point"}
}