{
  "type": "Feature",
  "properties": {
    "iso:country":"CH",
    "sg:address":"Baarerstrasse 2",
    "sg:city":"Zug",
    "sg:orig_category":"Non-Classified Establishments",
    "sg:postcode":"6300",
    "sg:province":"Zug",
    "wof:name":"Vasilis Ag Bekleidung & Schuhe",
    "wof:placetype":"venue"
},
  "geometry": {"coordinates":[8.5781822205,47.3259353638],"type":"Point"}
}