{
  "type": "Feature",
  "properties": {
    "addr:full":"Emmetterstrasse 17 Beckenried Nidwalden 6375",
    "addr:housenumber":"17",
    "addr:postcode":"6375",
    "addr:street":"Emmetterstrasse",
    "iso:country":"CH",
    "sg:address":"Emmetterstrasse 17",
    "sg:city":"Beckenried",
    "sg:classifiers":[
        {
            "category":"Professional",
            "subcategory":"Advertising",
            "type":"Services"
        }
    ],
    "sg:phone":"+41 41 624 45 45",
    "sg:postcode":"6375",
    "sg:province":"Nidwalden",
    "sg:tags":[
        "paper"
    ],
    "wof:name":"Druckerei M\u00fcller",
    "wof:placetype":"venue"
},
  "geometry": {"coordinates":[8.484251,46.963097],"type":"Point"}
}