{
  "type": "Feature",
  "properties": {
    "iso:country":"CH",
    "sg:address":"Kloster Fahr",
    "sg:city":"Unterengstringen",
    "sg:orig_category":"Landwirtschaftliche Schulen",
    "sg:phone":"+41 17502133",
    "sg:postcode":"8103",
    "sg:province":"Z\u00fcrich",
    "wof:name":"B\u00e4uerinnenschule",
    "wof:placetype":"venue"
},
  "geometry": {"coordinates":[8.4433498383,47.4116592407],"type":"Point"}
}