{
  "type": "Feature",
  "properties": {
    "iso:country":"CH",
    "sg:address":"Rue De La Colombi\u00e8re 1",
    "sg:city":"Nyon",
    "sg:orig_category":"Detailhandel mit Waren verschiedener Art, Hauptrichtung Nahrungsmittel",
    "sg:phone":"+41 56 282 13 43",
    "sg:postcode":"1260",
    "sg:province":"Vaud",
    "wof:name":"Medin Abduloski Mini Market Auroa",
    "wof:placetype":"venue"
},
  "geometry": {"coordinates":[8.2899942398,47.4873313904],"type":"Point"}
}