{
  "type": "Feature",
  "properties": {
    "iso:country":"CH",
    "sg:address":"Via Ludovico Ariosto 6",
    "sg:city":"Lugano",
    "sg:orig_category":"Softwareentwicklung U beratung",
    "sg:postcode":"6900",
    "sg:province":"Ticino",
    "wof:name":"Elettrodata Suisse Sa",
    "wof:placetype":"venue"
},
  "geometry": {"coordinates":[8.9509096146,46.0059356689],"type":"Point"}
}