{
  "type": "Feature",
  "properties": {
    "iso:country":"CH",
    "sg:address":"Dellenstrasse 75",
    "sg:city":"Trimbach",
    "sg:orig_category":"Architektur U Ingenieurb\u00fcros",
    "sg:phone":"+41 62 293 40 60",
    "sg:postcode":"4632",
    "sg:province":"Solothurn",
    "wof:name":"Buxtorf Lerch & Partner Vermessungs-& Ingenieurb\u00fcro",
    "wof:placetype":"venue"
},
  "geometry": {"coordinates":[7.906281,47.359516],"type":"Point"}
}