{
  "type": "Feature",
  "properties": {
    "iso:country":"CH",
    "sg:address":"Rue De L'eglise 7",
    "sg:city":"Courgenay",
    "sg:classifiers":[
        {
            "category":"Travel",
            "subcategory":"Hotels & Motels",
            "type":"Entertainment"
        }
    ],
    "sg:phone":"+41 32 471 11 21",
    "sg:postcode":"2950",
    "sg:province":"Jura",
    "sg:tags":[
        "hotels",
        "mit",
        "restaurant"
    ],
    "wof:name":"H\u00f4tel Du Boeuf",
    "wof:placetype":"venue"
},
  "geometry": {"coordinates":[7.1268768311,47.4026947021],"type":"Point"}
}