{
  "type": "Feature",
  "properties": {
    "iso:country":"CH",
    "sg:address":"Talstrasse 66",
    "sg:city":"Z\u00fcrich",
    "sg:orig_category":"Pensionskassen",
    "sg:phone":"+41 12185611",
    "sg:postcode":"8001",
    "sg:province":"Z\u00fcrich",
    "wof:name":"Personalvorsorgestiftung Sg R\u00fcegg Bank Ag",
    "wof:placetype":"venue"
},
  "geometry": {"coordinates":[8.5351200104,47.3709793091],"type":"Point"}
}