{
  "type": "Feature",
  "properties": {
    "iso:country":"CH",
    "sg:address":"Pilgerweg 39",
    "sg:city":"R\u00fcschlikon",
    "sg:orig_category":"Vorschulen, Kinderg\u00e4rten",
    "sg:phone":"+41 52 763 16 37",
    "sg:postcode":"8803",
    "sg:province":"Z\u00fcrich",
    "wof:name":"Kindergarten S\u00e4ge",
    "wof:placetype":"venue"
},
  "geometry": {"coordinates":[9.0080013275,47.6046905518],"type":"Point"}
}