{
  "type": "Feature",
  "properties": {
    "iso:country":"CH",
    "sg:address":"Hauptstrasse 54",
    "sg:city":"Bonaduz",
    "sg:orig_category":"Instandhaltung U Reparatur von Automobilen",
    "sg:phone":"+41 79 335 44 81",
    "sg:postcode":"7402",
    "sg:province":"Graubunden",
    "wof:name":"Garage Elit, Item H.",
    "wof:placetype":"venue"
},
  "geometry": {"coordinates":[9.3991746902,46.8075218201],"type":"Point"}
}