{
  "type": "Feature",
  "properties": {
    "iso:country":"CH",
    "sg:address":"Sandstrasse",
    "sg:city":"Schmerikon",
    "sg:orig_category":"Vorschulen, Kinderg\u00e4rten",
    "sg:phone":"+41 55 282 20 36",
    "sg:postcode":"8716",
    "sg:province":"St. Gallen",
    "wof:name":"Kindergarten Sand",
    "wof:placetype":"venue"
},
  "geometry": {"coordinates":[8.9533901215,47.225692749],"type":"Point"}
}