{
  "type": "Feature",
  "properties": {
    "iso:country":"CH",
    "sg:address":"Frikartweg 10",
    "sg:city":"Bern",
    "sg:orig_category":"Physiotherapie",
    "sg:phone":"+41 31 352 42 72",
    "sg:postcode":"3006",
    "sg:province":"Bern",
    "wof:name":"Physiotherapie Elfenau",
    "wof:placetype":"venue"
},
  "geometry": {"coordinates":[7.4681401253,46.9348106384],"type":"Point"}
}