{
  "type": "Feature",
  "properties": {
    "iso:country":"CH",
    "sg:address":"Weinberglistrasse 20",
    "sg:city":"Luzern",
    "sg:orig_category":"Sportvereine Kegeln",
    "sg:phone":"+41 41 360 41 80",
    "sg:postcode":"6005",
    "sg:province":"Luzern",
    "wof:name":"Kegler-vereinigung Abl",
    "wof:placetype":"venue"
},
  "geometry": {"coordinates":[8.316783905,47.0411987305],"type":"Point"}
}