{
  "type": "Feature",
  "properties": {
    "iso:country":"CH",
    "sg:address":"Riedstrasse 3",
    "sg:city":"Dietikon",
    "sg:orig_category":"Non-Classified Establishments",
    "sg:postcode":"8953",
    "sg:province":"Z\u00fcrich",
    "wof:name":"Advanced Projects Ag",
    "wof:placetype":"venue"
},
  "geometry": {"coordinates":[8.3939390182,47.4198760986],"type":"Point"}
}