{
  "type": "Feature",
  "properties": {
    "iso:country":"CH",
    "sg:address":"Solothurnerstrasse 19",
    "sg:city":"Olten",
    "sg:orig_category":"Vereine Gesang",
    "sg:postcode":"4600",
    "sg:province":"Solothurn",
    "wof:name":"Gesangverein Olten",
    "wof:placetype":"venue"
},
  "geometry": {"coordinates":[7.8993048668,47.3499755859],"type":"Point"}
}