{
  "type": "Feature",
  "properties": {
    "iso:country":"CH",
    "sg:address":"Alte Bremgartenstrasse 8",
    "sg:city":"Rudolfstetten",
    "sg:orig_category":"Arztpraxen",
    "sg:phone":"+41 56 631 85 85",
    "sg:postcode":"8964",
    "sg:province":"Aargau",
    "wof:name":"Dr.med.ren\u00e9 Widmer Spezialarzt Fmh",
    "wof:placetype":"venue"
},
  "geometry": {"coordinates":[8.37872,47.367668],"type":"Point"}
}