{
  "type": "Feature",
  "properties": {
    "iso:country":"CH",
    "sg:address":"Chemin Des Tilleuls 14",
    "sg:city":"Couvet",
    "sg:orig_category":"Herstellung von homogenisierten U di\u00e4tetischen Nahrungsmitteln Herstellung von pharmazeutischen Grun",
    "sg:phone":"+41 32 863 11 55",
    "sg:postcode":"2108",
    "sg:province":"Neuch\u00e2tel",
    "wof:name":"Cernelle Sa",
    "wof:placetype":"venue"
},
  "geometry": {"coordinates":[6.6376638412,46.9288406372],"type":"Point"}
}