{
  "type": "Feature",
  "properties": {
    "iso:country":"CH",
    "sg:address":"Baselstrasse 88 4125 Riehen. Postfach",
    "sg:city":"Riehen",
    "sg:orig_category":"Maler U Glasergewerbe",
    "sg:postcode":"4125",
    "sg:province":"Basel-Stadt",
    "wof:name":"Meinzer Waldemar & Christian",
    "wof:placetype":"venue"
},
  "geometry": {"coordinates":[7.6511349678,47.5871543884],"type":"Point"}
}