{
  "type": "Feature",
  "properties": {
    "iso:country":"CH",
    "sg:address":"Aum\u00fchlestrasse",
    "sg:city":"Ennetb\u00fcrgen",
    "sg:orig_category":"Informatikschulen Softwareentwicklung U beratung",
    "sg:phone":"+41 79 208 78 89",
    "sg:postcode":"6373",
    "sg:province":"Nidwalden",
    "wof:name":"Nideroest Pc-schulungen",
    "wof:placetype":"venue"
},
  "geometry": {"coordinates":[8.4098501205,46.9821434021],"type":"Point"}
}