{
  "type": "Feature",
  "properties": {
    "addr:full":"Boulevard De Grancy 29 Lausanne Vaud 1006",
    "addr:housenumber":"29",
    "addr:postcode":"1006",
    "addr:street":"Boulevard De Grancy",
    "iso:country":"CH",
    "sg:address":"Boulevard De Grancy 29",
    "sg:city":"Lausanne",
    "sg:classifiers":[
        {
            "category":"Education",
            "subcategory":"Library",
            "type":"Public Place"
        }
    ],
    "sg:phone":"+41 21 617 23 40",
    "sg:postcode":"1006",
    "sg:province":"Vaud",
    "sg:tags":[
        "u",
        "bibliotheken",
        "archive"
    ],
    "wof:name":"Biblioth\u00e8que Catholique & Service Audiovisuel",
    "wof:placetype":"venue"
},
  "geometry": {"coordinates":[6.627646,46.515736],"type":"Point"}
}