{
  "type": "Feature",
  "properties": {
    "addr:full":"Kernserstrasse 13 K\u00e4giswil Obwalden 6056",
    "addr:housenumber":"13",
    "addr:postcode":"6056",
    "addr:street":"Kernserstrasse;Obwalden",
    "iso:country":"CH",
    "sg:address":"Kernserstrasse 13",
    "sg:city":"K\u00e4giswil",
    "sg:orig_category":"Autogaragen",
    "sg:phone":"+41 41 660 77 07",
    "sg:postcode":"6056",
    "sg:province":"Obwalden",
    "wof:name":"Auto Burch Gmbh",
    "wof:placetype":"venue"
},
  "geometry": {"coordinates":[8.26272,46.921661],"type":"Point"}
}