{
  "type": "Feature",
  "properties": {
    "iso:country":"CH",
    "sg:address":"Chesa Mengiots",
    "sg:city":"Pontresina",
    "sg:orig_category":"Herstellung von Teppichen Verlegen von Fliesen U Platten",
    "sg:phone":"+41 81 842 68 43",
    "sg:postcode":"7504",
    "sg:province":"Graubunden",
    "wof:name":"B\u00fchler O., Plattenbel\u00e4ge Und Fugenabdichtungen",
    "wof:placetype":"venue"
},
  "geometry": {"coordinates":[9.9006948471,46.4958839417],"type":"Point"}
}