{
  "type": "Feature",
  "properties": {
    "iso:country":"CH",
    "sg:address":"Luzernerstrasse 7",
    "sg:city":"Arth",
    "sg:orig_category":"RESTAURANTS: TEA-ROOMS",
    "sg:phone":"+41 41 855 15 12",
    "sg:postcode":"6415",
    "sg:province":"Schwyz",
    "wof:name":"Blaser Frau Marlys, Restaurant Theaterst\u00fcbli",
    "wof:placetype":"venue"
},
  "geometry": {"coordinates":[8.5215978622,47.0626373291],"type":"Point"}
}