{
  "type": "Feature",
  "properties": {
    "iso:country":"CH",
    "sg:address":"Sonnenstrasse 8",
    "sg:city":"Amriswil",
    "sg:orig_category":"Wirtschafts- and Arbeitgeberverb\u00e4nde",
    "sg:phone":"+41 71 411 59 75",
    "sg:postcode":"8580",
    "sg:province":"Thurgau",
    "wof:name":"Industrieverein Amriswil",
    "wof:placetype":"venue"
},
  "geometry": {"coordinates":[9.2905139923,47.5435676575],"type":"Point"}
}