{
  "type": "Feature",
  "properties": {
    "iso:country":"CH",
    "sg:address":"Schliffmatt 17",
    "sg:city":"Laufen",
    "sg:orig_category":"Sportvereine Turnen",
    "sg:postcode":"4242",
    "sg:province":"Basel-Landschaft",
    "wof:name":"Turnverein Stv B\u00e4tterkinden",
    "wof:placetype":"venue"
},
  "geometry": {"coordinates":[7.524810791,47.1698150635],"type":"Point"}
}