{
  "type": "Feature",
  "properties": {
    "iso:country":"CH",
    "sg:address":"Oberholzstrasse 1",
    "sg:city":"Schwerzenbach",
    "sg:orig_category":"Softwareentwicklung U beratung",
    "sg:phone":"+41 18251482",
    "sg:postcode":"8603",
    "sg:province":"Z\u00fcrich",
    "wof:name":"Whitesoft Gmbh",
    "wof:placetype":"venue"
},
  "geometry": {"coordinates":[8.6613168716,47.3807029724],"type":"Point"}
}