{
  "type": "Feature",
  "properties": {
    "iso:country":"CH",
    "sg:address":"Route Des Rangiers 12",
    "sg:city":"Cornol",
    "sg:classifiers":[
        {
            "category":"Restaurant",
            "type":"Food & Drink"
        }
    ],
    "sg:phone":"+41 32 462 22 20",
    "sg:postcode":"2952",
    "sg:province":"Jura",
    "wof:name":"Restaurant Du Lion D'or",
    "wof:placetype":"venue"
},
  "geometry": {"coordinates":[7.165705204,47.4054450989],"type":"Point"}
}