{
  "type": "Feature",
  "properties": {
    "iso:country":"CH",
    "sg:address":"Bibersteinerstrasse 60",
    "sg:city":"Rombach",
    "sg:orig_category":"Fahrschulen, Flugschulen Tankstellen",
    "sg:phone":"+41 62 873 33 63",
    "sg:postcode":"5022",
    "sg:province":"Aargau",
    "wof:name":"Benz Roland Gmbh Tankstelle Usw",
    "wof:placetype":"venue"
},
  "geometry": {"coordinates":[7.9532442093,47.5423240662],"type":"Point"}
}