{
  "type": "Feature",
  "properties": {
    "iso:country":"CH",
    "sg:address":"Via Greina 2 6900 Lugano. Postfach Caselle Postale 2250",
    "sg:city":"Lugano",
    "sg:orig_category":"Advokaturb\u00fcros",
    "sg:phone":"+41 91 922 74 44",
    "sg:postcode":"6901",
    "sg:province":"Ticino",
    "wof:name":"Luca Taddei Studio Legale",
    "wof:placetype":"venue"
},
  "geometry": {"coordinates":[8.955378,46.008556],"type":"Point"}
}