{
  "type": "Feature",
  "properties": {
    "iso:country":"CH",
    "sg:address":"Poststrasse 111",
    "sg:city":"Spreitenbach",
    "sg:orig_category":"Massagestudios",
    "sg:phone":"+41 56 401 49 42",
    "sg:postcode":"8957",
    "sg:province":"Aargau",
    "wof:name":"Charlotte Fischer Massagen",
    "wof:placetype":"venue"
},
  "geometry": {"coordinates":[8.3597307205,47.4249916077],"type":"Point"}
}