{
  "type": "Feature",
  "properties": {
    "iso:country":"CH",
    "sg:address":"Alpenstrasse 4 6300 Zug. Postfach",
    "sg:city":"Zug",
    "sg:orig_category":"Finanzierungsinstitutionen",
    "sg:postcode":"6301",
    "sg:province":"Zug",
    "wof:name":"Haberfin Ag",
    "wof:placetype":"venue"
},
  "geometry": {"coordinates":[8.5139045715,47.1710357666],"type":"Point"}
}