{
  "type": "Feature",
  "properties": {
    "iso:country":"CH",
    "sg:address":"Mattgrat",
    "sg:city":"Ennetb\u00fcrgen",
    "sg:orig_category":"G\u00fcterbef\u00f6rderung im Strassenverkehr",
    "sg:phone":"+41 41 620 68 92",
    "sg:postcode":"6373",
    "sg:province":"Nidwalden",
    "wof:name":"Alois Barmettler Kleintransporte",
    "wof:placetype":"venue"
},
  "geometry": {"coordinates":[8.4159765244,46.9983215332],"type":"Point"}
}