{
  "type": "Feature",
  "properties": {
    "iso:country":"CH",
    "sg:address":"Umfahrungsstrasse",
    "sg:city":"Varen",
    "sg:orig_category":"Dauerkulturbau",
    "sg:postcode":"3969",
    "wof:name":"Loretan & Schnyder, Weinbau",
    "wof:placetype":"venue"
},
  "geometry": {"coordinates":[32.1437,-27.37397],"type":"Point"}
}