{
  "type": "Feature",
  "properties": {
    "addr:full":"Schanzenstrasse 4 Solothurn Solothurn 4500",
    "addr:housenumber":"4",
    "addr:postcode":"4500",
    "addr:street":"Schanzenstrasse",
    "iso:country":"CH",
    "sg:address":"Schanzenstrasse 4",
    "sg:city":"Solothurn",
    "sg:orig_category":"Architekturb\u00fcros",
    "sg:phone":"+41 32 622 31 44",
    "sg:postcode":"4500",
    "sg:province":"Solothurn",
    "wof:name":"Xaver Herm. Jaeggi Architekturb\u00fcro",
    "wof:placetype":"venue"
},
  "geometry": {"coordinates":[7.533847,47.207203],"type":"Point"}
}