{
  "type": "Feature",
  "properties": {
    "iso:country":"CH",
    "sg:address":"En Mont\u00e9vaux",
    "sg:city":"Farvagny",
    "sg:orig_category":"Malerei",
    "sg:phone":"+41 26 411 31 57",
    "sg:postcode":"1726",
    "sg:province":"Fribourg",
    "wof:name":"Michel Rody Entreprise De Peinture",
    "wof:placetype":"venue"
},
  "geometry": {"coordinates":[7.0652561188,46.7214279175],"type":"Point"}
}