{
  "type": "Feature",
  "properties": {
    "iso:country":"CH",
    "sg:address":"Pestalozzistrasse 5 9400 Rorschach. Postfach",
    "sg:city":"Rorschach",
    "sg:orig_category":"Dienstleistungen von Beteiligungsgesellschaften",
    "sg:postcode":"9400",
    "sg:province":"St. Gallen",
    "wof:name":"Monachia Ag",
    "wof:placetype":"venue"
},
  "geometry": {"coordinates":[9.4907436371,47.4737052917],"type":"Point"}
}