{
  "type": "Feature",
  "properties": {
    "iso:country":"CH",
    "sg:address":"Im Dorf",
    "sg:city":"Fehraltorf",
    "sg:orig_category":"Pensionskassen",
    "sg:phone":"+41 19541149",
    "sg:postcode":"8320",
    "sg:province":"Z\u00fcrich",
    "wof:name":"Personalf\u00fcrsorgestiftung Der Ernst Sch\u00fctz Kies + Beton Ag",
    "wof:placetype":"venue"
},
  "geometry": {"coordinates":[8.7480688095,47.3893432617],"type":"Point"}
}