{
  "type": "Feature",
  "properties": {
    "iso:country":"CH",
    "sg:address":"Scuole Via Delle 3",
    "sg:city":"Viganello",
    "sg:orig_category":"Erschliessung von Grundst\u00fccken",
    "sg:postcode":"6962",
    "sg:province":"Ticino",
    "wof:name":"Ceresio, Societ\u00e0 Cooperativa Di Costruzione",
    "wof:placetype":"venue"
},
  "geometry": {"coordinates":[8.9654750824,46.0140304565],"type":"Point"}
}