{
  "type": "Feature",
  "properties": {
    "iso:country":"CH",
    "sg:address":"Rue Colombes 11",
    "sg:city":"Collombey",
    "sg:classifiers":[
        {
            "category":"Banks & Credit Unions",
            "subcategory":"Bank",
            "type":"Services"
        }
    ],
    "sg:phone":"+41 24 471 56 33",
    "sg:postcode":"1868",
    "sg:province":"Valais",
    "wof:name":"Raiffeisen",
    "wof:placetype":"venue"
},
  "geometry": {"coordinates":[6.947433,46.269142],"type":"Point"}
}