{
  "type": "Feature",
  "properties": {
    "iso:country":"CH",
    "sg:address":"Sch\u00fcchh\u00fcbel 78",
    "sg:city":"Gontenschwil",
    "sg:orig_category":"Sonstiges Gesundheitswesen",
    "sg:phone":"+41 79 204 89 56",
    "sg:postcode":"5728",
    "sg:province":"Aargau",
    "wof:name":"Krankenmobilien-magazin Frau Katharina R\u00f6thlisberger",
    "wof:placetype":"venue"
},
  "geometry": {"coordinates":[8.1392345428,47.276638031],"type":"Point"}
}