{
  "type": "Feature",
  "properties": {
    "iso:country":"CH",
    "sg:address":"Chemin De Cousson 4",
    "sg:city":"Romanel-s-lausanne",
    "sg:orig_category":"Pensionskassen",
    "sg:postcode":"1032",
    "sg:province":"Vaud",
    "wof:name":"Fondation Des Planchettes",
    "wof:placetype":"venue"
},
  "geometry": {"coordinates":[6.6052951813,46.5640220642],"type":"Point"}
}