{
  "type": "Feature",
  "properties": {
    "iso:country":"CH",
    "sg:address":"Schlossweg 12",
    "sg:city":"Leibstadt",
    "sg:orig_category":"Sonstige pers\u00f6nliche Dienstleistungen",
    "sg:phone":"+41 56 247 00 41",
    "sg:postcode":"5325",
    "sg:province":"Aargau",
    "wof:name":"Autoland Fahrzeugpflege Gmbh",
    "wof:placetype":"venue"
},
  "geometry": {"coordinates":[8.1717319489,47.5953559875],"type":"Point"}
}