{
  "type": "Feature",
  "properties": {
    "iso:country":"CH",
    "sg:address":"Solothurnerstrasse 90",
    "sg:city":"Basel",
    "sg:orig_category":"Handelsvermittlung U Grosshandel Sonstiger Grosshandel",
    "sg:phone":"+41 61 361 80 72",
    "sg:postcode":"4053",
    "sg:province":"Basel-Stadt",
    "wof:name":"Lestro Inter Ag",
    "wof:placetype":"venue"
},
  "geometry": {"coordinates":[7.5883750916,47.542049408],"type":"Point"}
}