{
  "type": "Feature",
  "properties": {
    "iso:country":"CH",
    "sg:address":"B\u00e4listeigstrasse 1",
    "sg:city":"Eschenz",
    "sg:orig_category":"Mit dem Versicherungsgewerbe verbundene T\u00e4tigkeiten",
    "sg:phone":"+41 52 649 18 84",
    "sg:postcode":"8264",
    "sg:province":"Thurgau",
    "wof:name":"Wmb Consulting Werthm\u00fcller Bruno",
    "wof:placetype":"venue"
},
  "geometry": {"coordinates":[8.8643722534,47.6511421204],"type":"Point"}
}