{
  "type": "Feature",
  "properties": {
    "iso:country":"CH",
    "sg:address":"Hammerstrasse 7",
    "sg:city":"F\u00fcllinsdorf",
    "sg:orig_category":"Sanit\u00e4r U Heizungsinstallation Sanit\u00e4rinstallation",
    "sg:phone":"+41 61 902 12 90",
    "sg:postcode":"4414",
    "sg:province":"Basel-Landschaft",
    "wof:name":"En Energie Ag Heizungen & L\u00fcftungen",
    "wof:placetype":"venue"
},
  "geometry": {"coordinates":[7.7243719101,47.4999313354],"type":"Point"}
}