{
  "type": "Feature",
  "properties": {
    "iso:country":"CH",
    "sg:address":"L\u00f6wenstrasse 56 8001 Z\u00fcrich. Postfach 661",
    "sg:city":"Z\u00fcrich",
    "sg:classifiers":[
        {
            "category":"Professional",
            "subcategory":"Employment Agencies",
            "type":"Services"
        }
    ],
    "sg:phone":"+41 55 220 77 77",
    "sg:postcode":"8021",
    "sg:province":"Z\u00fcrich",
    "sg:tags":[
        "personal",
        "u",
        "stellenvermittlung"
    ],
    "wof:name":"Manpower Ag",
    "wof:placetype":"venue"
},
  "geometry": {"coordinates":[8.8176851273,47.2261238098],"type":"Point"}
}