{
  "type": "Feature",
  "properties": {
    "iso:country":"CH",
    "sg:address":"Speerweg 1",
    "sg:city":"Hettlingen",
    "sg:orig_category":"Elektroinstallation",
    "sg:phone":"+41 52 222 40 24",
    "sg:postcode":"8442",
    "sg:province":"Z\u00fcrich",
    "wof:name":"Metratech Ag",
    "wof:placetype":"venue"
},
  "geometry": {"coordinates":[8.7028589249,47.5470848083],"type":"Point"}
}