{
  "type": "Feature",
  "properties": {
    "iso:country":"CH",
    "sg:address":"Aarauerstrasse",
    "sg:city":"Lenzburg",
    "sg:orig_category":"Vermietung U Verpachtung von eigenen Immobilien",
    "sg:postcode":"5600",
    "sg:province":"Aargau",
    "wof:name":"Balmer & Ammann",
    "wof:placetype":"venue"
},
  "geometry": {"coordinates":[8.169834137,47.3872756958],"type":"Point"}
}