{
  "type": "Feature",
  "properties": {
    "iso:country":"CH",
    "sg:address":"Vollandes Rue Des 23 1207 Gen\u00e8ve. Postfach",
    "sg:city":"Gen\u00e8ve",
    "sg:orig_category":"Pensionskassen",
    "sg:postcode":"1201",
    "sg:province":"Gen\u00e8ve",
    "wof:name":"Caisse De Pensions De La Soci\u00e9t\u00e9 G\u00e9n\u00e9rale D'affichage Et De Soci\u00e9t\u00e9s Du Groupe",
    "wof:placetype":"venue"
},
  "geometry": {"coordinates":[6.1611661911,46.2046546936],"type":"Point"}
}