{
  "type": "Feature",
  "properties": {
    "iso:country":"CH",
    "sg:address":"Gare Place De La 12 1003 Lausanne. Postfach",
    "sg:city":"Lausanne",
    "sg:orig_category":"Elektrizit\u00e4tsversorgung",
    "sg:phone":"+41 27 979 12 51",
    "sg:postcode":"1003",
    "sg:province":"Vaud",
    "wof:name":"Energie Electrique Du Simplon Sa (ees)",
    "wof:placetype":"venue"
},
  "geometry": {"coordinates":[6.632335186,46.5195960999],"type":"Point"}
}