{
  "type": "Feature",
  "properties": {
    "iso:country":"CH",
    "sg:address":"Sternengasse 23",
    "sg:city":"Basel",
    "sg:orig_category":"Herstellung von Metallkonstruktionen Sonstige Bauinstallation",
    "sg:phone":"+41 61 272 74 18",
    "sg:postcode":"4051",
    "sg:province":"Basel-Stadt",
    "wof:name":"M\u00fcller Montagen",
    "wof:placetype":"venue"
},
  "geometry": {"coordinates":[7.5924978256,47.5513534546],"type":"Point"}
}