{
  "type": "Feature",
  "properties": {
    "iso:country":"CH",
    "sg:address":"Sonnenrainstrasse 13",
    "sg:city":"D\u00fcrnten",
    "sg:orig_category":"Kosmetikinstitute",
    "sg:phone":"+41 55 240 43 32",
    "sg:postcode":"8635",
    "sg:province":"Z\u00fcrich",
    "wof:name":"Mich\u00e8le Glanzmann Kosmetikinstitut",
    "wof:placetype":"venue"
},
  "geometry": {"coordinates":[8.8763875961,47.276386261],"type":"Point"}
}