{
  "type": "Feature",
  "properties": {
    "iso:country":"CH",
    "sg:address":"Suettaz Chemin De La 4",
    "sg:city":"Prilly",
    "sg:orig_category":"Architektur U Ingenieurb\u00fcros",
    "sg:phone":"+41 79 438 61 06",
    "sg:postcode":"1008",
    "sg:province":"Vaud",
    "wof:name":"Tec-maintherm Sa",
    "wof:placetype":"venue"
},
  "geometry": {"coordinates":[6.140616,46.185322],"type":"Point"}
}