{
  "type": "Feature",
  "properties": {
    "iso:country":"CH",
    "sg:address":"Ulmenweg 1",
    "sg:city":"Othmarsingen",
    "sg:orig_category":"Allgemeiner Hoch U Tiefbau Sanit\u00e4rinstallation",
    "sg:phone":"+41 62 896 15 31",
    "sg:postcode":"5504",
    "sg:province":"Aargau",
    "wof:name":"Maurer Ernst",
    "wof:placetype":"venue"
},
  "geometry": {"coordinates":[8.217581,47.407845],"type":"Point"}
}