{
  "type": "Feature",
  "properties": {
    "iso:country":"CH",
    "sg:address":"Wangenstrasse 20",
    "sg:city":"Deitingen",
    "sg:orig_category":"Herstellung von Metallerzeugnissen ohne Maschinenbau Maschinenbau",
    "sg:phone":"+41 32 614 17 45",
    "sg:postcode":"4543",
    "sg:province":"Solothurn",
    "wof:name":"Risa Ag Deitingen",
    "wof:placetype":"venue"
},
  "geometry": {"coordinates":[7.6221051216,47.2143707275],"type":"Point"}
}