{
  "type": "Feature",
  "properties": {
    "addr:full":"Bismarck K\u00fcttigkofen Solothurn 4581",
    "addr:postcode":"4581",
    "iso:country":"CH",
    "sg:address":"Bismarck",
    "sg:city":"K\u00fcttigkofen",
    "sg:classifiers":[
        {
            "category":"Building & Trades",
            "subcategory":"Construction",
            "type":"Services"
        }
    ],
    "sg:phone":"+41 32 677 23 33",
    "sg:postcode":"4581",
    "sg:province":"Solothurn",
    "sg:tags":[
        "work",
        "public"
    ],
    "wof:name":"Rennhard Gartenbau Ag",
    "wof:placetype":"venue"
},
  "geometry": {"coordinates":[7.522983,47.154266],"type":"Point"}
}