{
  "type": "Feature",
  "properties": {
    "iso:country":"CH",
    "sg:address":"Place Des Epancheurs 6 2012 Auvernier Case Postale 88",
    "sg:city":"Auvernier",
    "sg:orig_category":"Grosshandel mit Getr\u00e4nken Rebbau",
    "sg:phone":"+41 32 731 21 15",
    "sg:postcode":"2012",
    "sg:province":"Neuch\u00e2tel",
    "wof:name":"Caves Du Ch\u00e2teau D'auvernier, Grosjean Thierry Et Cie.",
    "wof:placetype":"venue"
},
  "geometry": {"coordinates":[6.8773508072,46.9745521545],"type":"Point"}
}