{
  "type": "Feature",
  "properties": {
    "iso:country":"CH",
    "sg:address":"Chemin De Primerose 51",
    "sg:city":"Lausanne",
    "sg:orig_category":"Detailhandel mit Bekleidung Detailhandel mit Damenbekleidung",
    "sg:phone":"+41 21 648 75 48",
    "sg:postcode":"1007",
    "sg:province":"Vaud",
    "wof:name":"Boutique Marie-claire, La Casaque, Mme Vieux",
    "wof:placetype":"venue"
},
  "geometry": {"coordinates":[6.614359,46.514923],"type":"Point"}
}