{
  "type": "Feature",
  "properties": {
    "iso:country":"CH",
    "sg:address":"Gl\u00e4rnischstrasse 9 8633 Wolfhausen. Postfach",
    "sg:city":"Wolfhausen",
    "sg:orig_category":"Schreib U \u00dcbersetzungsb\u00fcros",
    "sg:phone":"+41 71 388 62 88",
    "sg:postcode":"8633",
    "sg:province":"Z\u00fcrich",
    "wof:name":"Infra Service Ag",
    "wof:placetype":"venue"
},
  "geometry": {"coordinates":[9.2514562607,47.4134788513],"type":"Point"}
}