{
  "type": "Feature",
  "properties": {
    "iso:country":"CH",
    "sg:address":"Bahnhofstrasse 34",
    "sg:city":"Appenzell",
    "sg:orig_category":"Herstellung von Metallkonstruktionen Stahl U Leichtmetallbau",
    "sg:phone":"+41 79 669 47 79",
    "sg:postcode":"9050",
    "sg:province":"Appenzell Innerhoden",
    "wof:name":"Musil Metallbau Gmbh",
    "wof:placetype":"venue"
},
  "geometry": {"coordinates":[9.4095497131,47.3260574341],"type":"Point"}
}