{
  "type": "Feature",
  "properties": {
    "iso:country":"CH",
    "sg:address":"Place Du Ch\u00e2teau 4",
    "sg:city":"Grandson",
    "sg:orig_category":"Polizei",
    "sg:phone":"+41 24 445 00 21",
    "sg:postcode":"1422",
    "sg:province":"Vaud",
    "wof:name":"Police Cantonale",
    "wof:placetype":"venue"
},
  "geometry": {"coordinates":[6.6460571289,46.8092193604],"type":"Point"}
}