{
  "type": "Feature",
  "properties": {
    "iso:country":"CH",
    "sg:address":"Pleggasse 491",
    "sg:city":"Reitnau",
    "sg:orig_category":"Sonstiger spezialisierter Hoch U Tiefbau",
    "sg:postcode":"5057",
    "sg:province":"Aargau",
    "wof:name":"Bolliger Kaminbau",
    "wof:placetype":"venue"
},
  "geometry": {"coordinates":[8.0431499481,47.2488517761],"type":"Point"}
}