{
  "type": "Feature",
  "properties": {
    "iso:country":"CH",
    "sg:address":"M\u00fchlemattstrasse 54",
    "sg:city":"Aarau",
    "sg:orig_category":"Unclassifiable Establishments",
    "sg:postcode":"5000",
    "sg:province":"Aargau",
    "wof:name":"Aginet Ag",
    "wof:placetype":"venue"
},
  "geometry": {"coordinates":[7.2548508644,46.7977333069],"type":"Point"}
}