{
  "type": "Feature",
  "properties": {
    "iso:country":"CH",
    "sg:address":"B\u00f6zingenstrasse 140 2504 Biel/bienne. Postfach",
    "sg:city":"Biel/bienne",
    "sg:orig_category":"Herstellung von K\u00fcchenm\u00f6beln",
    "sg:phone":"+41 32 341 58 68",
    "sg:postcode":"2504",
    "sg:province":"Bern",
    "wof:name":"K\u00fcchen-galerie Mdv Mario Del Vecchio",
    "wof:placetype":"venue"
},
  "geometry": {"coordinates":[7.2653999329,47.1515541077],"type":"Point"}
}