{
  "type": "Feature",
  "properties": {
    "iso:country":"CH",
    "sg:address":"8754",
    "sg:city":"Netstal",
    "sg:orig_category":"Detailhandel mit Zeitungen U Zeitschriften Kioske",
    "sg:phone":"+41 55 640 10 02",
    "sg:postcode":"8754",
    "sg:province":"Glarus",
    "wof:name":"Schwimmbad",
    "wof:placetype":"venue"
},
  "geometry": {"coordinates":[9.0356998444,47.0660896301],"type":"Point"}
}