{
  "type": "Feature",
  "properties": {
    "iso:country":"CH",
    "sg:address":"Bruderholzallee 220 4059 Basel. Postfach",
    "sg:city":"Basel",
    "sg:orig_category":"Innenarchitekturb\u00fcros",
    "sg:phone":"+41 61 332 10 20",
    "sg:postcode":"4024",
    "sg:province":"Basel-Stadt",
    "wof:name":"Bombazurra Design Zurlinden Ryhiner B\u00e9atrice R. M\u00f6bel, Gebrauchsgegenst\u00e4nde; Design. B\u00fchnenr\u00e4ume Usw; Gestaltung",
    "wof:placetype":"venue"
},
  "geometry": {"coordinates":[7.6002521515,47.5340003967],"type":"Point"}
}