{
  "type": "Feature",
  "properties": {
    "iso:country":"CH",
    "sg:address":"Gassenbach 275",
    "sg:city":"Zuzgen",
    "sg:orig_category":"Herstellung von Kunststoff in Prim\u00e4rformen Herstellung von Kunststoffwaren",
    "sg:phone":"+41 71 744 48 71",
    "sg:postcode":"4315",
    "sg:province":"Aargau",
    "wof:name":"Samaplast Ag",
    "wof:placetype":"venue"
},
  "geometry": {"coordinates":[9.6523456573,47.4473342896],"type":"Point"}
}