{
  "type": "Feature",
  "properties": {
    "iso:country":"CH",
    "sg:address":"Avenue Du Grey 14",
    "sg:city":"Lausanne",
    "sg:orig_category":"Wirtschaftspr\u00fcfung, Steuerberatung U Treuhand",
    "sg:phone":"+41 21 624 99 73",
    "sg:postcode":"1004",
    "sg:province":"Vaud",
    "wof:name":"Fidurom S \u00e0 R L",
    "wof:placetype":"venue"
},
  "geometry": {"coordinates":[6.6188268661,46.5324401855],"type":"Point"}
}