{
  "type": "Feature",
  "properties": {
    "iso:country":"CH",
    "sg:address":"Hofstrasse 23",
    "sg:city":"Zug",
    "sg:orig_category":"Handels-H\u00e4user U Gesellschaften",
    "sg:postcode":"6300",
    "sg:province":"Zug",
    "wof:name":"Altima Ag",
    "wof:placetype":"venue"
},
  "geometry": {"coordinates":[8.51516819,47.1586112976],"type":"Point"}
}