{
  "type": "Feature",
  "properties": {
    "iso:country":"CH",
    "sg:address":"Mol\u00e9son Rue Du 14 1202 Gen\u00e8ve. Postfach",
    "sg:city":"Gen\u00e8ve",
    "sg:orig_category":"Vermittlungen Wohnungs-Agenturen,",
    "sg:phone":"+41 22 345 08 22",
    "sg:postcode":"1202",
    "sg:province":"Gen\u00e8ve",
    "wof:name":"Corberia Sa",
    "wof:placetype":"venue"
},
  "geometry": {"coordinates":[6.1334347725,46.2110595703],"type":"Point"}
}