{
  "type": "Feature",
  "properties": {
    "iso:country":"CH",
    "sg:address":"Sch\u00f6nmatt 1",
    "sg:city":"Gempen",
    "sg:orig_category":"RESTAURANTS: TEA-ROOMS",
    "sg:phone":"+41 61 701 53 88",
    "sg:postcode":"4145",
    "sg:province":"Solothurn",
    "wof:name":"Restaurant Sch\u00f6nmatt Ag",
    "wof:placetype":"venue"
},
  "geometry": {"coordinates":[7.6537771225,47.4939498901],"type":"Point"}
}