{
  "type": "Feature",
  "properties": {
    "iso:country":"CH",
    "sg:address":"Weidweg 58 3032 Hinterkappelen. Postfach 361",
    "sg:city":"Hinterkappelen",
    "sg:orig_category":"Unternehmensberatung",
    "sg:phone":"+41 31 901 24 44",
    "sg:postcode":"3032",
    "sg:province":"Bern",
    "wof:name":"Input, Unternehmens Und Marketingberatungs Ag",
    "wof:placetype":"venue"
},
  "geometry": {"coordinates":[7.3912138939,46.9681663513],"type":"Point"}
}