{
  "type": "Feature",
  "properties": {
    "iso:country":"CH",
    "sg:address":"Paradiesweg 1",
    "sg:city":"Kappelen",
    "sg:orig_category":"Herstellung von sonstigen landwirtschaftlichen Maschinen Sanit\u00e4rinstallation",
    "sg:phone":"+41 32 392 51 70",
    "sg:postcode":"3273",
    "sg:province":"Bern",
    "wof:name":"Heinrich Ryser San.anlagen & Landmaschinen",
    "wof:placetype":"venue"
},
  "geometry": {"coordinates":[7.2656750679,47.0608329773],"type":"Point"}
}