{
  "type": "Feature",
  "properties": {
    "iso:country":"CH",
    "sg:address":"Frankenstrasse 70",
    "sg:city":"Bern",
    "sg:orig_category":"Instandhaltung U Reparatur von Automobilen",
    "sg:phone":"+41 31 992 94 93",
    "sg:postcode":"3018",
    "sg:province":"Bern",
    "wof:name":"Garage Urs Meyer Ag",
    "wof:placetype":"venue"
},
  "geometry": {"coordinates":[7.397600174,46.9392929077],"type":"Point"}
}