{
  "type": "Feature",
  "properties": {
    "iso:country":"CH",
    "sg:address":"R\u00fctihof 24",
    "sg:city":"Gr\u00e4nichen",
    "sg:orig_category":"Herstellung von Teppichen Verlegen von Fliesen U Platten",
    "sg:phone":"+41 71 333 16 31",
    "sg:postcode":"5722",
    "sg:province":"Aargau",
    "wof:name":"Flavio Mian Ag",
    "wof:placetype":"venue"
},
  "geometry": {"coordinates":[9.3786430359,47.3904953003],"type":"Point"}
}