{
  "type": "Feature",
  "properties": {
    "iso:country":"CH",
    "sg:address":"Schulhausstrasse 22",
    "sg:city":"Langenthal",
    "sg:orig_category":"Handel mit Automobilen",
    "sg:phone":"+41 62225555",
    "sg:postcode":"4900",
    "sg:province":"Bern",
    "wof:name":"Werner Leuenberger",
    "wof:placetype":"venue"
},
  "geometry": {"coordinates":[7.7843308449,47.2119483948],"type":"Point"}
}