{
  "type": "Feature",
  "properties": {
    "iso:country":"CH",
    "sg:address":"Uferstrasse 90 4057 Basel. Postfach 530",
    "sg:city":"Basel",
    "sg:orig_category":"Ingenieurb\u00fcros Elektro",
    "sg:phone":"+41 61 633 91 35",
    "sg:postcode":"4019",
    "sg:province":"Basel-Stadt",
    "wof:name":"Valentin Spiess Iart Ingenieurb\u00fcro",
    "wof:placetype":"venue"
},
  "geometry": {"coordinates":[7.587141037,47.5822372437],"type":"Point"}
}