{
  "type": "Feature",
  "properties": {
    "iso:country":"CH",
    "sg:address":"Grubenstrasse 109",
    "sg:city":"Sch\u00f6nb\u00fchl-urtenen",
    "sg:orig_category":"Architekturb\u00fcros",
    "sg:phone":"+41 31 859 34 41",
    "sg:postcode":"3322",
    "sg:province":"Bern",
    "wof:name":"Willi Siegenthaler & S\u00f6hne Architekturb\u00fcro",
    "wof:placetype":"venue"
},
  "geometry": {"coordinates":[7.49953,47.020424],"type":"Point"}
}