{
  "type": "Feature",
  "properties": {
    "iso:country":"CH",
    "sg:address":"Bahnhofstrasse 10",
    "sg:city":"Wolhusen",
    "sg:orig_category":"Detailhandel mit Brillen U anderen Sehhilfen Fachdetailhandel in Verkaufsr\u00e4umen",
    "sg:phone":"+41 22 908 11 00",
    "sg:postcode":"6110",
    "sg:province":"Luzern",
    "wof:name":"Pro-contact, Jean A. Kress & Cie Sa",
    "wof:placetype":"venue"
},
  "geometry": {"coordinates":[6.145472,46.207935],"type":"Point"}
}