{
  "type": "Feature",
  "properties": {
    "iso:country":"CH",
    "sg:address":"Wilstrasse 40 8600 D\u00fcbendorf. Postfach 624",
    "sg:city":"D\u00fcbendorf",
    "sg:orig_category":"Grosshandel mit Maschinen U Ausr\u00fcstungen Herstellung von Mess U Kontrollinstrumenten U vorrichtungen",
    "sg:phone":"+41 18210115",
    "sg:postcode":"8600",
    "sg:province":"Z\u00fcrich",
    "wof:name":"Fisch Und Partner Ag",
    "wof:placetype":"venue"
},
  "geometry": {"coordinates":[8.6168727875,47.3950958252],"type":"Point"}
}