{
  "type": "Feature",
  "properties": {
    "iso:country":"CH",
    "sg:address":"Chemin Du Coll\u00e8ge 5a",
    "sg:city":"Villars-sous-yens",
    "sg:orig_category":"Politische Parteien CVP",
    "sg:postcode":"1138",
    "wof:name":"Pdc Section Renens",
    "wof:placetype":"venue"
},
  "geometry": {"coordinates":[6.584444046,46.5415763855],"type":"Point"}
}