{
  "type": "Feature",
  "properties": {
    "iso:country":"CH",
    "sg:address":"Marktgasse 16",
    "sg:city":"Kloten",
    "sg:orig_category":"Unternehmensberatung",
    "sg:phone":"+41 56 622 88 66",
    "sg:postcode":"8302",
    "sg:province":"Z\u00fcrich",
    "wof:name":"Exacta Wirtschaftsberatungs Und Revisions Ag",
    "wof:placetype":"venue"
},
  "geometry": {"coordinates":[8.2690401077,47.3499107361],"type":"Point"}
}