{
  "type": "Feature",
  "properties": {
    "iso:country":"CH",
    "sg:address":"Vadianstrasse 29 9000 St.gallen. Postfach 1263",
    "sg:city":"St.gallen",
    "sg:orig_category":"Detailhandel mit Waren verschiedener Art, Hauptrichtung Nahrungsmittel",
    "sg:phone":"+41 71 226 78 78",
    "sg:postcode":"9000",
    "sg:province":"St. Gallen",
    "wof:name":"Lv-st.gallen",
    "wof:placetype":"venue"
},
  "geometry": {"coordinates":[9.3710517883,47.4216537476],"type":"Point"}
}