{
  "type": "Feature",
  "properties": {
    "addr:full":"Rue Des D\u00e9lices 17 Gen\u00e8ve Gen\u00e8ve 1203",
    "addr:housenumber":"17",
    "addr:postcode":"1203",
    "addr:street":"Rue Des De\u0301Lices",
    "iso:country":"CH",
    "sg:address":"Rue Des D\u00e9lices 17",
    "sg:city":"Gen\u00e8ve",
    "sg:orig_category":"Architekturb\u00fcros",
    "sg:phone":"+41 22 340 72 10",
    "sg:postcode":"1203",
    "sg:province":"Gen\u00e8ve",
    "wof:name":"Andr\u00e9 Bagattini Arch. Eaug/sia",
    "wof:placetype":"venue"
},
  "geometry": {"coordinates":[6.133379,46.206932],"type":"Point"}
}