{
  "type": "Feature",
  "properties": {
    "iso:country":"CH",
    "sg:address":"9050",
    "sg:city":"Appenzell",
    "sg:orig_category":"Vorschulen, Kinderg\u00e4rten",
    "sg:phone":"+41 62 721 39 20",
    "sg:postcode":"9050",
    "sg:province":"Appenzell Innerhoden",
    "wof:name":"Kindergarten Schulhaus I",
    "wof:placetype":"venue"
},
  "geometry": {"coordinates":[7.8228058815,47.2411155701],"type":"Point"}
}