{
  "type": "Feature",
  "properties": {
    "addr:full":"Leimistrasse 619 Enggistein Bern 3077",
    "addr:housenumber":"619",
    "addr:postcode":"3077",
    "addr:street":"Leimistrasse",
    "iso:country":"CH",
    "sg:address":"Leimistrasse 619",
    "sg:city":"Enggistein",
    "sg:orig_category":"Bauschreinerei",
    "sg:phone":"+41 31 839 05 71",
    "sg:postcode":"3077",
    "sg:province":"Bern",
    "wof:name":"Alfred Stucki Schreinerei",
    "wof:placetype":"venue"
},
  "geometry": {"coordinates":[7.597166,46.931828],"type":"Point"}
}