{
  "type": "Feature",
  "properties": {
    "iso:country":"CH",
    "sg:address":"Chemin Des Pav\u00e9s 15",
    "sg:city":"Neuch\u00e2tel",
    "sg:orig_category":"Detailhandel mit elektrischen Haushalts-,Radio U Fernsehger\u00e4ten sowie Musikinstrumenten Grosshandel ",
    "sg:phone":"+41 21 321 26 26",
    "sg:postcode":"2000",
    "sg:province":"Neuch\u00e2tel",
    "wof:name":"Audio-visuel Bt Sa",
    "wof:placetype":"venue"
},
  "geometry": {"coordinates":[6.6374430656,46.5226097107],"type":"Point"}
}