{
  "type": "Feature",
  "properties": {
    "iso:country":"CH",
    "sg:address":"Moostrasse 15",
    "sg:city":"Luzern",
    "sg:orig_category":"Religi\u00f6se Vereinigungen divers Vereine Geselligkeit",
    "sg:phone":"+41 41 210 16 53",
    "sg:postcode":"6003",
    "sg:province":"Luzern",
    "wof:name":"Club Kbr Kath.bekanntschaftsring",
    "wof:placetype":"venue"
},
  "geometry": {"coordinates":[8.3061056137,47.0457420349],"type":"Point"}
}