{
  "type": "Feature",
  "properties": {
    "iso:country":"CH",
    "sg:address":"Bachmattli",
    "sg:city":"Unter\u00e4geri",
    "sg:orig_category":"Allgemeiner Hochbau Strassenbau",
    "sg:phone":"+41 91 646 20 20",
    "sg:postcode":"6314",
    "sg:province":"Zug",
    "wof:name":"Aldo Martinelli & Co Impresa Costruzioni",
    "wof:placetype":"venue"
},
  "geometry": {"coordinates":[9.009596,45.860073],"type":"Point"}
}