{
  "type": "Feature",
  "properties": {
    "iso:country":"CH",
    "sg:address":"Tramweg 35 6415 Arth. Postfach",
    "sg:city":"Oberarth",
    "sg:orig_category":"Sonstiger Grosshandel",
    "sg:postcode":"6414",
    "sg:province":"Schwyz",
    "wof:name":"Massandra Trading Ag",
    "wof:placetype":"venue"
},
  "geometry": {"coordinates":[8.5263795853,47.0631217957],"type":"Point"}
}