{
  "type": "Feature",
  "properties": {
    "iso:country":"CH",
    "sg:address":"Matzenriedstrasse",
    "sg:city":"Bern",
    "sg:classifiers":[
        {
            "category":"Restaurant",
            "type":"Food & Drink"
        }
    ],
    "sg:phone":"+41 31 926 10 22",
    "sg:postcode":"3019",
    "sg:province":"Bern",
    "wof:name":"Restaurant Zum Hirschen",
    "wof:placetype":"venue"
},
  "geometry": {"coordinates":[7.3455090523,46.9332466125],"type":"Point"}
}