{
  "type": "Feature",
  "properties": {
    "iso:country":"CH",
    "sg:address":"2882 St-ursanne. Postfach 41",
    "sg:city":"St-ursanne",
    "sg:orig_category":"Sportvereine Ballsport Fussball",
    "sg:phone":"+41 896005604",
    "sg:postcode":"2882",
    "sg:province":"Jura",
    "wof:name":"Fc St.margrethen",
    "wof:placetype":"venue"
},
  "geometry": {"coordinates":[9.6348695755,47.4514694214],"type":"Point"}
}