{
  "type": "Feature",
  "properties": {
    "iso:country":"CH",
    "sg:address":"Rue Des Terreaux 4",
    "sg:city":"Lutry",
    "sg:orig_category":"Detailhandel mit Radio U Fernsehger\u00e4ten Detailhandel mit elektrischen Haushalts-,Radio U Fernsehger\u00e4",
    "sg:phone":"+41 32 725 12 00",
    "sg:postcode":"1095",
    "sg:province":"Vaud",
    "wof:name":"Vinyl S\u00e0rl",
    "wof:placetype":"venue"
},
  "geometry": {"coordinates":[6.9280700684,46.9931297302],"type":"Point"}
}