{
  "type": "Feature",
  "properties": {
    "iso:country":"CH",
    "sg:address":"Grand-rue 64",
    "sg:city":"Tavannes",
    "sg:orig_category":"Sanit\u00e4r, Heizungs U L\u00fcftungsinstallation",
    "sg:phone":"+41 21 944 17 76",
    "sg:postcode":"2710",
    "sg:province":"Bern",
    "wof:name":"Aellen Jean-claude",
    "wof:placetype":"venue"
},
  "geometry": {"coordinates":[6.8606758118,46.4580307007],"type":"Point"}
}