{
  "type": "Feature",
  "properties": {
    "iso:country":"CH",
    "sg:address":"Forchstrasse 233 8000 Z\u00fcrich. Postfach 8032 Z\u00fcrich",
    "sg:city":"Zust",
    "sg:orig_category":"Hardwareberatung",
    "sg:postcode":"32",
    "wof:name":"Netonet Costa Samuel",
    "wof:placetype":"venue"
},
  "geometry": {"coordinates":[8.5704469681,47.3591117859],"type":"Point"}
}