{
  "type": "Feature",
  "properties": {
    "iso:country":"CH",
    "sg:address":"Hellb\u00fchlerstrasse 22",
    "sg:city":"Ruswil",
    "sg:orig_category":"Shiatsu-Therapie",
    "sg:phone":"+41 19205038",
    "sg:postcode":"6017",
    "sg:province":"Luzern",
    "wof:name":"Shiatsu-zentrum Z\u00fcrichsee",
    "wof:placetype":"venue"
},
  "geometry": {"coordinates":[8.6868505478,47.2735176086],"type":"Point"}
}