{
  "type": "Feature",
  "properties": {
    "addr:full":"1142 Pampigny Vaud 1142",
    "addr:housenumber":"1142",
    "addr:postcode":"1142",
    "addr:street":"Pampigny",
    "iso:country":"CH",
    "sg:address":"1142",
    "sg:city":"Pampigny",
    "sg:orig_category":"Detailhandel mit Brot, Back U S\u00fcsswaren",
    "sg:phone":"+41 21 800 52 42",
    "sg:postcode":"1142",
    "sg:province":"Vaud",
    "wof:name":"Rochat Eric",
    "wof:placetype":"venue"
},
  "geometry": {"coordinates":[6.427823,46.580082],"type":"Point"}
}