{
  "type": "Feature",
  "properties": {
    "iso:country":"CH",
    "sg:address":"Feraschenstrasse 20 3970 Salgesch. Postfach",
    "sg:city":"Salgesch",
    "sg:orig_category":"Interessenvertretungen",
    "sg:phone":"+41 22 366 11 14",
    "sg:postcode":"3970",
    "sg:province":"Valais",
    "wof:name":"Fondation Du Parc Zoologique La Garenne Assurer La P\u00e9rennit\u00e9 De L'institution",
    "wof:placetype":"venue"
},
  "geometry": {"coordinates":[6.2354798317,46.4775047302],"type":"Point"}
}