{
  "type": "Feature",
  "properties": {
    "iso:country":"CH",
    "sg:address":"Plattenweg 42",
    "sg:city":"Schaffhausen",
    "sg:orig_category":"Sonstige Verkehrsvermittlung",
    "sg:phone":"+41 52 644 14 44",
    "sg:postcode":"8200",
    "sg:province":"Schaffhausen",
    "wof:name":"Miltraco Leu Consulting",
    "wof:placetype":"venue"
},
  "geometry": {"coordinates":[8.6269426346,47.7118759155],"type":"Point"}
}