{
  "type": "Feature",
  "properties": {
    "iso:country":"CH",
    "sg:address":"Othmarsingerstrasse 1",
    "sg:city":"Dottikon",
    "sg:orig_category":"Non-Classified Establishments",
    "sg:postcode":"5605",
    "sg:province":"Aargau",
    "wof:name":"Gefu Oberle",
    "wof:placetype":"venue"
},
  "geometry": {"coordinates":[8.2408857346,47.3842124939],"type":"Point"}
}