{
  "type": "Feature",
  "properties": {
    "iso:country":"CH",
    "sg:address":"Tschuoppisstrasse 39",
    "sg:city":"Netstal",
    "sg:orig_category":"Arztpraxen",
    "sg:phone":"+41 27 932 31 03",
    "sg:postcode":"8754",
    "sg:province":"Glarus",
    "wof:name":"Dr.med.marcel Lehner Arzt F.allgemeine Medizin Fmh",
    "wof:placetype":"venue"
},
  "geometry": {"coordinates":[7.746468,46.315315],"type":"Point"}
}