{
  "type": "Feature",
  "properties": {
    "iso:country":"CH",
    "sg:address":"Neuhaus",
    "sg:city":"Hirzel",
    "sg:orig_category":"RESTAURANTS: TEA-ROOMS",
    "sg:phone":"+41 17299141",
    "sg:postcode":"8816",
    "sg:province":"Z\u00fcrich",
    "wof:name":"Restaurant Zum Alten Hirschen, Landolt H. & Co",
    "wof:placetype":"venue"
},
  "geometry": {"coordinates":[8.599360466,47.2324981689],"type":"Point"}
}