{
  "type": "Feature",
  "properties": {
    "iso:country":"CH",
    "sg:address":"Rue De Bernex 268",
    "sg:city":"Bernex",
    "sg:orig_category":"Rebbau",
    "sg:phone":"+41 22 757 12 44",
    "sg:postcode":"1233",
    "sg:province":"Gen\u00e8ve",
    "wof:name":"Louis Cruz Viticulture",
    "wof:placetype":"venue"
},
  "geometry": {"coordinates":[6.0737547874,46.175868988],"type":"Point"}
}