{
  "type": "Feature",
  "properties": {
    "iso:country":"CH",
    "sg:address":"Birkenweg 18",
    "sg:city":"Uttigen",
    "sg:orig_category":"Hoch U Tiefbau",
    "sg:phone":"+41 79 656 56 22",
    "sg:postcode":"3628",
    "sg:province":"Bern",
    "wof:name":"Jakob Schenk Maurergesch\u00e4ft",
    "wof:placetype":"venue"
},
  "geometry": {"coordinates":[7.5801968575,46.795627594],"type":"Point"}
}