{
  "type": "Feature",
  "properties": {
    "iso:country":"CH",
    "sg:address":"5512",
    "sg:city":"Wohlenschwil",
    "sg:orig_category":"Sportvereine Sch\u00fctzen",
    "sg:phone":"+41 71 925 42 20",
    "sg:postcode":"5512",
    "sg:province":"Aargau",
    "wof:name":"Feldsch\u00fctzen",
    "wof:placetype":"venue"
},
  "geometry": {"coordinates":[8.2549600601,47.4160804749],"type":"Point"}
}