{
  "type": "Feature",
  "properties": {
    "iso:country":"CH",
    "sg:address":"Belpstrasse 11 3007 Bern. Postfach",
    "sg:city":"Bern",
    "sg:orig_category":"Konsulate",
    "sg:phone":"+41 31 302 08 11",
    "sg:postcode":"3001",
    "sg:province":"Bern",
    "wof:name":"Ambassade Du Japon",
    "wof:placetype":"venue"
},
  "geometry": {"coordinates":[7.4389948845,46.9593925476],"type":"Point"}
}