{
  "type": "Feature",
  "properties": {
    "iso:country":"CH",
    "sg:address":"Untere Z\u00e4une 9",
    "sg:city":"Z\u00fcrich",
    "sg:orig_category":"Arztpraxen",
    "sg:phone":"+41 12524550",
    "sg:postcode":"8001",
    "sg:province":"Z\u00fcrich",
    "wof:name":"Dr.med.fred Fischer Spezialarzt",
    "wof:placetype":"venue"
},
  "geometry": {"coordinates":[8.546323,47.371151],"type":"Point"}
}