{
  "type": "Feature",
  "properties": {
    "iso:country":"CH",
    "sg:address":"Zentweg 21",
    "sg:city":"Bern",
    "sg:orig_category":"Wirtschafts- and Arbeitgeberverb\u00e4nde",
    "sg:phone":"+41 31 931 38 68",
    "sg:postcode":"3006",
    "sg:province":"Bern",
    "wof:name":"Kant.-bern.autofahrlehrer- Verband",
    "wof:placetype":"venue"
},
  "geometry": {"coordinates":[7.4754772186,46.9568443298],"type":"Point"}
}