{
  "type": "Feature",
  "properties": {
    "iso:country":"CH",
    "sg:address":"Rue Etraz 1",
    "sg:city":"Lausanne",
    "sg:orig_category":"Caterer Fischverarbeitung",
    "sg:phone":"+41 21 311 11 12",
    "sg:postcode":"1003",
    "sg:province":"Vaud",
    "wof:name":"Sushi Zen Sa Traiteur Japonais",
    "wof:placetype":"venue"
},
  "geometry": {"coordinates":[6.638103,46.519562],"type":"Point"}
}