{
  "type": "Feature",
  "properties": {
    "iso:country":"CH",
    "sg:address":"Kapellenweg 1",
    "sg:city":"Grossh\u00f6chstetten",
    "sg:orig_category":"Maler U Glasergewerbe Malerei",
    "sg:phone":"+41 31 711 15 09",
    "sg:postcode":"3506",
    "sg:province":"Bern",
    "wof:name":"Kiener & Co Malergesch\u00e4ft",
    "wof:placetype":"venue"
},
  "geometry": {"coordinates":[7.6365208626,46.9079971313],"type":"Point"}
}