{
  "type": "Feature",
  "properties": {
    "iso:country":"CH",
    "sg:address":"Giessh\u00fcbelstrasse 4",
    "sg:city":"Z\u00fcrich",
    "sg:orig_category":"RESTAURANTS: TEA-ROOMS",
    "sg:phone":"+41 12017278",
    "sg:postcode":"8045",
    "sg:province":"Z\u00fcrich",
    "wof:name":"Cafeteria Attika, Tomic Svetlana",
    "wof:placetype":"venue"
},
  "geometry": {"coordinates":[8.5227613449,47.3600349426],"type":"Point"}
}