{
  "type": "Feature",
  "properties": {
    "iso:country":"CH",
    "sg:address":"Rizzi Via Giacomo 10",
    "sg:city":"Mendrisio",
    "sg:orig_category":"Herstellung von D\u00fcngemitteln U Stickstoffverbindungen",
    "sg:postcode":"6850",
    "sg:province":"Ticino",
    "wof:name":"Fertilizza Sa",
    "wof:placetype":"venue"
},
  "geometry": {"coordinates":[8.9812364578,45.8664665222],"type":"Point"}
}