{
  "type": "Feature",
  "properties": {
    "iso:country":"CH",
    "sg:address":"Sch\u00fctzenstrasse 30 3315 B\u00e4tterkinden. Postfach 24",
    "sg:city":"B\u00e4tterkinden",
    "sg:orig_category":"Mechanik",
    "sg:postcode":"3315",
    "sg:province":"Bern",
    "wof:name":"Bwb-buchser Ag",
    "wof:placetype":"venue"
},
  "geometry": {"coordinates":[7.5357961655,47.141960144],"type":"Point"}
}