{
  "type": "Feature",
  "properties": {
    "iso:country":"CH",
    "sg:address":"Dorfstr. 55.",
    "sg:city":"Thierachern",
    "sg:orig_category":"Grosshandel mit Nahrungsmitteln, Getr\u00e4nken U Tabakwaren ohne ausgepr\u00e4gten Schwerpunkt",
    "sg:postcode":"3634",
    "sg:province":"Bern",
    "wof:name":"Meier, F.",
    "wof:placetype":"venue"
},
  "geometry": {"coordinates":[7.5743341446,46.7530059814],"type":"Point"}
}