{
  "type": "Feature",
  "properties": {
    "iso:country":"CH",
    "sg:address":"Chemin De La Comba 9",
    "sg:city":"Attalens",
    "sg:orig_category":"Allgemeiner Hoch U Tiefbau",
    "sg:postcode":"1616",
    "sg:province":"Fribourg",
    "wof:name":"All-rent S\u00e0rl",
    "wof:placetype":"venue"
},
  "geometry": {"coordinates":[7.04263,47.020039],"type":"Point"}
}