{
  "type": "Feature",
  "properties": {
    "iso:country":"CH",
    "sg:address":"Kuttelgasse 4",
    "sg:city":"Z\u00fcrich",
    "sg:orig_category":"Unclassifiable Establishments",
    "sg:postcode":"8001",
    "sg:province":"Z\u00fcrich",
    "wof:name":"Hoeimmobil Ag Immobilien Usw; Bau, Kauf, Verwaltung, Verkauf",
    "wof:placetype":"venue"
},
  "geometry": {"coordinates":[8.5391187668,47.3730506897],"type":"Point"}
}