{
  "type": "Feature",
  "properties": {
    "iso:country":"CH",
    "sg:address":"Avouillons Route Des 16 1196 Gland Case Postale 319",
    "sg:city":"Gland",
    "sg:orig_category":"Banken sonstige",
    "sg:phone":"+41 22 999 98 98",
    "sg:postcode":"1196",
    "sg:province":"Vaud",
    "wof:name":"Swissquote Bank Activit\u00e9 Bancaire, N\u00e9gociant En Valeurs Mobili\u00e8res Etc",
    "wof:placetype":"venue"
},
  "geometry": {"coordinates":[6.266977,46.415733],"type":"Point"}
}