{
  "type": "Feature",
  "properties": {
    "iso:country":"CH",
    "sg:address":"Bachtalenstrasse",
    "sg:city":"M\u00f6hlin",
    "sg:orig_category":"Detailhandel mit Zeitungen U Zeitschriften Kioske",
    "sg:phone":"+41 61 851 30 70",
    "sg:postcode":"4313",
    "sg:province":"Aargau",
    "wof:name":"Schwimmbad",
    "wof:placetype":"venue"
},
  "geometry": {"coordinates":[7.839949131,47.5736427307],"type":"Point"}
}