{
  "type": "Feature",
  "properties": {
    "iso:country":"CH",
    "sg:address":"Salzh\u00fcsliweg 4 4600 Olten. Postfach",
    "sg:city":"Olten",
    "sg:orig_category":"RESTAURANTS: TEA-ROOMS",
    "sg:postcode":"4600",
    "sg:province":"Solothurn",
    "wof:name":"Child Hoang Teestube",
    "wof:placetype":"venue"
},
  "geometry": {"coordinates":[7.904323101,47.3495140076],"type":"Point"}
}