{
  "type": "Feature",
  "properties": {
    "iso:country":"CH",
    "sg:address":"Chemin De Champ-belluet 6 1807 Blonay. Postfach",
    "sg:city":"Blonay",
    "sg:orig_category":"Vermittlung von Immobilien Verwaltung von Immobilien",
    "sg:phone":"+41 21 943 60 01",
    "sg:postcode":"1807",
    "sg:province":"Vaud",
    "wof:name":"Groupimmo Sa Commersialisation De La Site Internet De La Sa. Services Internet Et De Franchisage Et Ses Filiales Etc",
    "wof:placetype":"venue"
},
  "geometry": {"coordinates":[6.8939380646,46.4653015137],"type":"Point"}
}