{
  "type": "Feature",
  "properties": {
    "iso:country":"CH",
    "sg:address":"Rottmannsbodenstrasse 131",
    "sg:city":"Binningen",
    "sg:orig_category":"Unternehmensberatung",
    "sg:phone":"+41 61 422 01 95",
    "sg:postcode":"4102",
    "sg:province":"Basel-Landschaft",
    "wof:name":"Siewal Trust Gmbh",
    "wof:placetype":"venue"
},
  "geometry": {"coordinates":[7.5557222366,47.540222168],"type":"Point"}
}