{
  "type": "Feature",
  "properties": {
    "iso:country":"CH",
    "sg:address":"Sch\u00f6nb\u00fchlring 19",
    "sg:city":"Luzern",
    "sg:orig_category":"G\u00fcterbef\u00f6rderung im Strassenverkehr",
    "sg:phone":"+41 41 360 06 58",
    "sg:postcode":"6005",
    "sg:province":"Luzern",
    "wof:name":"Kaufmann E. Transporte",
    "wof:placetype":"venue"
},
  "geometry": {"coordinates":[8.3273363113,47.0390739441],"type":"Point"}
}