{
  "type": "Feature",
  "properties": {
    "iso:country":"CH",
    "sg:address":"Bachpromenade 2",
    "sg:city":"Courgevaux",
    "sg:orig_category":"Unclassifiable Establishments",
    "sg:phone":"+41 26 670 23 15",
    "sg:postcode":"1796",
    "sg:province":"Fribourg",
    "wof:name":"A-z Gartenbau Ag",
    "wof:placetype":"venue"
},
  "geometry": {"coordinates":[7.1130270958,46.9085998535],"type":"Point"}
}