{
  "type": "Feature",
  "properties": {
    "iso:country":"CH",
    "sg:address":"1726",
    "sg:city":"Farvagny",
    "sg:orig_category":"Haltung von Rindern",
    "sg:postcode":"1726",
    "sg:province":"Fribourg",
    "wof:name":"Syndicat D'\u00e9levage De La Race Tachet\u00e9e Rouge De Farvagny",
    "wof:placetype":"venue"
},
  "geometry": {"coordinates":[7.0652561188,46.7214279175],"type":"Point"}
}