{
  "type": "Feature",
  "properties": {
    "addr:full":"Le Tr\u00e9si 9 Pr\u00e9verenges Vaud 1028",
    "addr:housenumber":"9",
    "addr:postcode":"1028",
    "iso:country":"CH",
    "sg:address":"Le Tr\u00e9si 9",
    "sg:city":"Pr\u00e9verenges",
    "sg:orig_category":"Allgemeiner Hoch U Tiefbau Test U Sondierbohrungen",
    "sg:phone":"+41 21 803 15 05",
    "sg:postcode":"1028",
    "sg:province":"Vaud",
    "wof:name":"Forasol Sa",
    "wof:placetype":"venue"
},
  "geometry": {"coordinates":[6.529939,46.52282],"type":"Point"}
}