{
  "type": "Feature",
  "properties": {
    "iso:country":"CH",
    "sg:address":"Neumarktstr. 28 2500 Biel/bienne. Postfach",
    "sg:city":"Biel/bienne",
    "sg:orig_category":"Interessenvertretungen",
    "sg:postcode":"2500",
    "sg:province":"Bern",
    "wof:name":"Stiftung Gesunde Schweiz Jetzt",
    "wof:placetype":"venue"
},
  "geometry": {"coordinates":[7.2488942146,47.1394348145],"type":"Point"}
}