{
  "type": "Feature",
  "properties": {
    "iso:country":"CH",
    "sg:address":"Via Gaggiolo 28",
    "sg:city":"Stabio",
    "sg:orig_category":"Tankstellen",
    "sg:phone":"+41 91 647 12 12",
    "sg:postcode":"6855",
    "sg:province":"Ticino",
    "wof:name":"Luigi & Liviana Covre Stazione Agip",
    "wof:placetype":"venue"
},
  "geometry": {"coordinates":[8.929060936,45.8457870483],"type":"Point"}
}