{
  "type": "Feature",
  "properties": {
    "iso:country":"CH",
    "sg:address":"Klybeckstrasse 101 4057 Basel. Postfach",
    "sg:city":"Basel",
    "sg:orig_category":"Grosshandel mit Nahrungsmitteln, Getr\u00e4nken U Tabakwaren ohne ausgepr\u00e4gten Schwerpunkt",
    "sg:postcode":"4051",
    "sg:province":"Basel-Stadt",
    "wof:name":"Jannetje Carai Lebensmittelhandel.",
    "wof:placetype":"venue"
},
  "geometry": {"coordinates":[7.5902180672,47.5691604614],"type":"Point"}
}