{
  "type": "Feature",
  "properties": {
    "iso:country":"CH",
    "sg:address":"Triemlistrasse 180",
    "sg:city":"Z\u00fcrich",
    "sg:orig_category":"Sonstige pers\u00f6nliche Dienstleistungen",
    "sg:phone":"+41 12619718",
    "sg:postcode":"8047",
    "sg:province":"Z\u00fcrich",
    "wof:name":"Famosaik Gmbh",
    "wof:placetype":"venue"
},
  "geometry": {"coordinates":[8.4937925339,47.3683395386],"type":"Point"}
}