{
  "type": "Feature",
  "properties": {
    "iso:country":"CH",
    "sg:address":"Oberholzweg 53",
    "sg:city":"Rothrist",
    "sg:orig_category":"Mechanik",
    "sg:phone":"+41 19101657",
    "sg:postcode":"4852",
    "sg:province":"Aargau",
    "wof:name":"Haefeli Hans, Schlosserei Und Apparatebau",
    "wof:placetype":"venue"
},
  "geometry": {"coordinates":[8.6010322571,47.3069114685],"type":"Point"}
}