{
  "type": "Feature",
  "properties": {
    "iso:country":"CH",
    "sg:address":"G\u00fcterstrasse 11",
    "sg:city":"Spreitenbach",
    "sg:classifiers":[
        {
            "category":"Utilities",
            "subcategory":"Telephone",
            "type":"Services"
        }
    ],
    "sg:phone":"+41 56 418 76 11",
    "sg:postcode":"8957",
    "sg:province":"Aargau",
    "sg:tags":[
        "telecommunication"
    ],
    "wof:name":"Se Lightmanagement Ag",
    "wof:placetype":"venue"
},
  "geometry": {"coordinates":[8.3596153259,47.4288787842],"type":"Point"}
}