{
  "type": "Feature",
  "properties": {
    "iso:country":"CH",
    "sg:address":"Rue De La Piscine",
    "sg:city":"Verbier",
    "sg:classifiers":[
        {
            "category":"Restaurant",
            "type":"Food & Drink"
        }
    ],
    "sg:phone":"+41 27 771 72 96",
    "sg:postcode":"1936",
    "sg:province":"Valais",
    "wof:name":"Restaurant Tart'in",
    "wof:placetype":"venue"
},
  "geometry": {"coordinates":[7.2217497826,46.0982284546],"type":"Point"}
}