{
  "type": "Feature",
  "properties": {
    "iso:country":"CH",
    "sg:address":"Spranglenstrasse 59",
    "sg:city":"Bassersdorf",
    "sg:orig_category":"Reiseb\u00fcros U Reiseveranstalter",
    "sg:phone":"+41 18371437",
    "sg:postcode":"8303",
    "sg:province":"Z\u00fcrich",
    "wof:name":"Peter M\u00e4gerle Travel",
    "wof:placetype":"venue"
},
  "geometry": {"coordinates":[8.6192169189,47.4427337646],"type":"Point"}
}