{
  "type": "Feature",
  "properties": {
    "iso:country":"CH",
    "sg:address":"1669",
    "sg:city":"Lessoc",
    "sg:orig_category":"Sportvereine Sch\u00fctzen",
    "sg:phone":"+41 80800800",
    "sg:postcode":"1669",
    "sg:province":"Fribourg",
    "wof:name":"St\u00e9 De Tir Martigny-ville",
    "wof:placetype":"venue"
},
  "geometry": {"coordinates":[7.0729198456,46.1013793945],"type":"Point"}
}