{
  "type": "Feature",
  "properties": {
    "addr:full":"Sch\u00fctzenhausstrasse 99 Embrach Z\u00fcrich 8424",
    "addr:housenumber":"99",
    "addr:postcode":"8424",
    "addr:street":"Schuetzenhausstrasse",
    "iso:country":"CH",
    "sg:address":"Sch\u00fctzenhausstrasse 99",
    "sg:city":"Embrach",
    "sg:orig_category":"Berufsbildende weiterf\u00fchrende Schulen Hochschulen U h\u00f6here Ausbildung",
    "sg:phone":"+41 18652090",
    "sg:postcode":"8424",
    "sg:province":"Z\u00fcrich",
    "wof:name":"Kammerlander Consulting",
    "wof:placetype":"venue"
},
  "geometry": {"coordinates":[8.59605,47.510349],"type":"Point"}
}