{
  "type": "Feature",
  "properties": {
    "iso:country":"CH",
    "sg:address":"Thunstrasse 53",
    "sg:city":"Steffisburg",
    "sg:orig_category":"Fernmeldedienste",
    "sg:phone":"+41 33 437 70 30",
    "sg:postcode":"3612",
    "sg:province":"Bern",
    "wof:name":"Tes Electronic, Wampfler H.",
    "wof:placetype":"venue"
},
  "geometry": {"coordinates":[7.6310091019,46.7658615112],"type":"Point"}
}