{
  "type": "Feature",
  "properties": {
    "iso:country":"CH",
    "sg:address":"Industriestrasse 24 8305 Dietlikon. Postfach",
    "sg:city":"Dietlikon",
    "sg:orig_category":"Bauingenieurb\u00fcros Heizung L\u00fcftung Klima Bauingenieurb\u00fcros Sanit\u00e4r",
    "sg:phone":"+41 71 385 65 15",
    "sg:postcode":"8305",
    "sg:province":"Z\u00fcrich",
    "wof:name":"L\u00fcssy + Partner Gmbh Ingnieurb\u00fcro F. Haustechnik Usw",
    "wof:placetype":"venue"
},
  "geometry": {"coordinates":[9.251324,47.415184],"type":"Point"}
}