{
  "type": "Feature",
  "properties": {
    "iso:country":"CH",
    "sg:address":"Rosiers Chemin Des 4 1700 Fribourg. Postfach",
    "sg:city":"Freiburg",
    "sg:orig_category":"Rechtsberatung",
    "sg:phone":"+41 26 425 82 82",
    "sg:postcode":"1700",
    "sg:province":"Fribourg",
    "wof:name":"Picotin Sa Droits D'auteur Etc.; \u00e9dition, Publicit\u00e9, Diffusion, Reproduction Et Commercialisation",
    "wof:placetype":"venue"
},
  "geometry": {"coordinates":[7.1597647667,46.8046836853],"type":"Point"}
}