{
  "type": "Feature",
  "properties": {
    "iso:country":"CH",
    "sg:address":"Hauptstrasse 19",
    "sg:city":"Gaiserwald",
    "sg:orig_category":"Geb\u00e4ude, Wohnungsreinigung Reinigungsgewerbe",
    "sg:postcode":"9030",
    "sg:province":"St. Gallen",
    "wof:name":"Hauswartungen Und Unterhaltsreinigungen Rhiner B.",
    "wof:placetype":"venue"
},
  "geometry": {"coordinates":[9.3184490204,47.4218940735],"type":"Point"}
}