{
  "type": "Feature",
  "properties": {
    "iso:country":"CH",
    "sg:address":"Gasometerstrasse 7",
    "sg:city":"Z\u00fcrich",
    "sg:orig_category":"Instandhaltung U Reparatur von Automobilen",
    "sg:phone":"+41 12734800",
    "sg:postcode":"8000",
    "sg:province":"Z\u00fcrich",
    "wof:name":"Bermuda Garage, Reith P.",
    "wof:placetype":"venue"
},
  "geometry": {"coordinates":[8.5284528732,47.383808136],"type":"Point"}
}