{
  "type": "Feature",
  "properties": {
    "addr:full":"Viktoriastrasse 8 Brunnen Schwyz 6440",
    "addr:housenumber":"8",
    "addr:postcode":"6440",
    "addr:street":"Viktoriastrasse;Schwyz",
    "iso:country":"CH",
    "sg:address":"Viktoriastrasse 8",
    "sg:city":"Brunnen",
    "sg:orig_category":"Architektur U Ingenieurb\u00fcros Softwareentwicklung U beratung",
    "sg:phone":"+41 41 822 00 00",
    "sg:postcode":"6440",
    "sg:province":"Schwyz",
    "wof:name":"Girsberger Informatik Ag Ingenieurb\u00fcro F\u00fcr Informatik, Edv-beratung Und Programmierung",
    "wof:placetype":"venue"
},
  "geometry": {"coordinates":[8.600818,46.994965],"type":"Point"}
}