{
  "type": "Feature",
  "properties": {
    "addr:full":"Haagerstrasse 9473 Gams. Postfach Gams St. Gallen 9473",
    "addr:postcode":"9473 gams. postfach gams;9473",
    "addr:street":"Haagerstrasse",
    "iso:country":"CH",
    "sg:address":"Haagerstrasse 9473 Gams. Postfach",
    "sg:city":"Gams",
    "sg:orig_category":"Bauschreinerei Zimmerei, Dachdeckerei, Bauspenglerei U Abdichtung",
    "sg:phone":"+41 71 333 30 40",
    "sg:postcode":"9473",
    "sg:province":"St. Gallen",
    "wof:name":"Heierli Emil",
    "wof:placetype":"venue"
},
  "geometry": {"coordinates":[9.362168,47.386242],"type":"Point"}
}