{
  "type": "Feature",
  "properties": {
    "iso:country":"CH",
    "sg:address":"Dorfplatz 8",
    "sg:city":"Tamins",
    "sg:orig_category":"Kantonalbanken",
    "sg:phone":"+41 81 641 26 20",
    "sg:postcode":"7015",
    "sg:province":"Graubunden",
    "wof:name":"Graub\u00fcndner Kantonalbank",
    "wof:placetype":"venue"
},
  "geometry": {"coordinates":[9.4072904587,46.8300132751],"type":"Point"}
}