{
  "type": "Feature",
  "properties": {
    "iso:country":"CH",
    "sg:address":"Chemin De Pr\u00e9-fleuri 8",
    "sg:city":"Crissier",
    "sg:orig_category":"Fahrschulen, Flugschulen",
    "sg:phone":"+41 26 477 37 18",
    "sg:postcode":"1023",
    "sg:province":"Vaud",
    "wof:name":"Daniel Neuhaus Auto-\u00e9cole",
    "wof:placetype":"venue"
},
  "geometry": {"coordinates":[7.0556650162,46.7652854919],"type":"Point"}
}