{
  "type": "Feature",
  "properties": {
    "iso:country":"CH",
    "sg:address":"Zollstrasse 22 9494 Schaan. Postfach 261",
    "sg:city":"Schaan",
    "sg:orig_category":"Bauschreinerei Herstellung von M\u00f6beln verschiedener Art",
    "sg:phone":"+423 232 16 36",
    "sg:postcode":"9494",
    "wof:name":"Ferdinand Frick Ag F\u00fcr Bau-& M\u00f6belschreinerei",
    "wof:placetype":"venue"
},
  "geometry": {"coordinates":[9.504394,47.168182],"type":"Point"}
}