{
  "type": "Feature",
  "properties": {
    "iso:country":"CH",
    "sg:address":"Bubenbergplatz 11",
    "sg:city":"Bern",
    "sg:orig_category":"Arztpraxen",
    "sg:phone":"+41 31 328 88 88",
    "sg:postcode":"3011",
    "sg:province":"Bern",
    "wof:name":"Dr.med. Albert Escher Arzt F.allgemeine Medizin Fmh",
    "wof:placetype":"venue"
},
  "geometry": {"coordinates":[7.439341,46.94722],"type":"Point"}
}