{
  "type": "Feature",
  "properties": {
    "iso:country":"CH",
    "sg:address":"3510",
    "sg:city":"H\u00e4utligen",
    "sg:orig_category":"Primarschulen",
    "sg:phone":"+41 34 402 17 76",
    "sg:postcode":"3510",
    "sg:province":"Bern",
    "wof:name":"Primarschule",
    "wof:placetype":"venue"
},
  "geometry": {"coordinates":[7.605219841,46.8570213318],"type":"Point"}
}