{
  "type": "Feature",
  "properties": {
    "iso:country":"CH",
    "sg:address":"Hauptstrasse 19",
    "sg:city":"Biberist",
    "sg:orig_category":"Herstellung von Schmuck, Gold U Silberschmiedwaren",
    "sg:postcode":"4562",
    "sg:province":"Solothurn",
    "wof:name":"Goldschmiede Maurer",
    "wof:placetype":"venue"
},
  "geometry": {"coordinates":[7.5613827705,47.1829910278],"type":"Point"}
}