{
  "type": "Feature",
  "properties": {
    "iso:country":"CH",
    "sg:address":"Kasernenstrasse 66 9100 Herisau. Postfach",
    "sg:city":"Herisau",
    "sg:orig_category":"Handel mit Automobilen",
    "sg:phone":"+41 71 351 51 56",
    "sg:postcode":"9102",
    "sg:province":"Appenzell Ausserrhoden",
    "wof:name":"Auto Widag Ag",
    "wof:placetype":"venue"
},
  "geometry": {"coordinates":[9.288731575,47.3890457153],"type":"Point"}
}