{
  "type": "Feature",
  "properties": {
    "iso:country":"CH",
    "sg:address":"Landskronstrasse 9 4144 Arlesheim. Postfach",
    "sg:city":"Arlesheim",
    "sg:orig_category":"Vermietung U Verpachtung von eigenen Immobilien",
    "sg:postcode":"4144",
    "sg:province":"Basel-Landschaft",
    "wof:name":"Immobiliengesellschaft Landskron Ag",
    "wof:placetype":"venue"
},
  "geometry": {"coordinates":[7.6127028465,47.4894485474],"type":"Point"}
}