{
  "type": "Feature",
  "properties": {
    "iso:country":"CH",
    "sg:address":"Via Milano 15",
    "sg:city":"Chiasso",
    "sg:orig_category":"Bauspenglerei Sanit\u00e4r, Heizungs U L\u00fcftungsinstallation",
    "sg:phone":"+41 91 683 28 37",
    "sg:postcode":"6830",
    "sg:province":"Ticino",
    "wof:name":"Inaudi Sa",
    "wof:placetype":"venue"
},
  "geometry": {"coordinates":[9.02012,45.831802],"type":"Point"}
}