{
  "type": "Feature",
  "properties": {
    "iso:country":"CH",
    "sg:address":"Diessenhoferstrasse 24",
    "sg:city":"Feuerthalen",
    "sg:orig_category":"Nationale Postdienste",
    "sg:phone":"+41 52 659 38 89",
    "sg:postcode":"8245",
    "sg:province":"Z\u00fcrich",
    "wof:name":"Die Schweizerische Post",
    "wof:placetype":"venue"
},
  "geometry": {"coordinates":[8.6459197998,47.6917533875],"type":"Point"}
}