{
  "type": "Feature",
  "properties": {
    "iso:country":"CH",
    "sg:address":"Stockern",
    "sg:city":"Wattenwil",
    "sg:orig_category":"Herstellung von elektrischen Haushaltsger\u00e4ten",
    "sg:postcode":"3665",
    "sg:province":"Bern",
    "wof:name":"Italcaffe Gmbh",
    "wof:placetype":"venue"
},
  "geometry": {"coordinates":[8.7979202271,47.3224182129],"type":"Point"}
}