{
  "type": "Feature",
  "properties": {
    "iso:country":"CH",
    "sg:address":"Quai Robert-comtesse 10",
    "sg:city":"Neuch\u00e2tel",
    "sg:orig_category":"RESTAURANTS: TEA-ROOMS",
    "sg:phone":"+41 32 725 51 82",
    "sg:postcode":"2000",
    "sg:province":"Neuch\u00e2tel",
    "wof:name":"Restaurant La Lagune, Walder",
    "wof:placetype":"venue"
},
  "geometry": {"coordinates":[6.9478259087,46.9945297241],"type":"Point"}
}