{
  "type": "Feature",
  "properties": {
    "iso:country":"CH",
    "sg:address":"Rue Du Lac 8",
    "sg:city":"Yverdon-les-bains",
    "sg:orig_category":"Detailhandel mit Spielwaren Detailhandel mit S\u00e4uglings U Kinderbekleidung",
    "sg:phone":"+41 24 426 32 73",
    "sg:postcode":"1400",
    "sg:province":"Vaud",
    "wof:name":"Boutique Sikymania Aurora & Didier Mottaz",
    "wof:placetype":"venue"
},
  "geometry": {"coordinates":[6.6406650543,46.7790374756],"type":"Point"}
}