{
  "type": "Feature",
  "properties": {
    "iso:country":"CH",
    "sg:address":"Sandstrasse 48",
    "sg:city":"Moosseedorf",
    "sg:orig_category":"Allgemeiner Hoch U Tiefbau Allgemeiner Hochbau",
    "sg:phone":"+41 32 941 38 18",
    "sg:postcode":"3302",
    "sg:province":"Bern",
    "wof:name":"Freiburghaus Btp Ergu\u00ebl Sa",
    "wof:placetype":"venue"
},
  "geometry": {"coordinates":[6.84388,47.111664],"type":"Point"}
}