{
  "type": "Feature",
  "properties": {
    "iso:country":"CH",
    "sg:address":"Speerstrasse 10",
    "sg:city":"Gaiserwald",
    "sg:orig_category":"Elektroinstallation",
    "sg:phone":"+41 71 311 27 25",
    "sg:postcode":"9030",
    "sg:province":"St. Gallen",
    "wof:name":"R\u00fctsche Antennenbau Ag",
    "wof:placetype":"venue"
},
  "geometry": {"coordinates":[9.3189172745,47.4293403625],"type":"Point"}
}