{
  "type": "Feature",
  "properties": {
    "iso:country":"CH",
    "sg:address":"Solothurnerstrasse 45 4710 Klus. Postfach 360",
    "sg:city":"Klus",
    "sg:orig_category":"Arztpraxen",
    "sg:phone":"+41 62 391 31 59",
    "sg:postcode":"4710",
    "sg:province":"Solothurn",
    "wof:name":"Dr.med. Andreas Vogt Spezialarzt Fmh",
    "wof:placetype":"venue"
},
  "geometry": {"coordinates":[7.693753,47.3055],"type":"Point"}
}