{
  "type": "Feature",
  "properties": {
    "iso:country":"CH",
    "sg:address":"Rue Du Temple 19 2610 St-imier. Postfach",
    "sg:city":"St-imier",
    "sg:orig_category":"Elektrizit\u00e4tsversorgung Wasserversorgung",
    "sg:phone":"+41 32 942 44 00",
    "sg:postcode":"2610",
    "sg:province":"Bern",
    "wof:name":"Services Techniques St-imier",
    "wof:placetype":"venue"
},
  "geometry": {"coordinates":[6.9981298447,47.1531562805],"type":"Point"}
}