{
  "type": "Feature",
  "properties": {
    "iso:country":"CH",
    "sg:address":"Binningerstrasse 5 4051 Basel. Postfach",
    "sg:city":"Basel",
    "sg:orig_category":"RESTAURANTS: TEA-ROOMS",
    "sg:postcode":"4051",
    "sg:province":"Basel-Stadt",
    "wof:name":"Ristorante Quattro Passi Gmbh Gastwirtschafts- U. Unterhaltungsbetriebe Usw",
    "wof:placetype":"venue"
},
  "geometry": {"coordinates":[7.5867581367,47.5506782532],"type":"Point"}
}