{
  "type": "Feature",
  "properties": {
    "iso:country":"CH",
    "sg:address":"Baslerstrasse 42 4665 Oftringen. Postfach",
    "sg:city":"Oftringen",
    "sg:orig_category":"Pensionskassen",
    "sg:phone":"+41 17162233",
    "sg:postcode":"4665",
    "sg:province":"Aargau",
    "wof:name":"Spezialf\u00fcrsorgefonds Der Chocoladefabriken Lindt & Spr\u00fcngli Aktiengesellschaft.",
    "wof:placetype":"venue"
},
  "geometry": {"coordinates":[8.5452337265,47.321598053],"type":"Point"}
}