{
  "type": "Feature",
  "properties": {
    "iso:country":"CH",
    "sg:address":"Chemin De La Jonch\u00e8re 1b",
    "sg:city":"Fontainemelon",
    "sg:orig_category":"Physiotherapie",
    "sg:phone":"+41 32 853 42 32",
    "sg:postcode":"2052",
    "sg:province":"Neuch\u00e2tel",
    "wof:name":"Pierre Matthey Physioth\u00e9rapie",
    "wof:placetype":"venue"
},
  "geometry": {"coordinates":[6.8889980316,47.0553855896],"type":"Point"}
}