{
  "type": "Feature",
  "properties": {
    "iso:country":"CH",
    "sg:address":"Holderbachweg 4",
    "sg:city":"Z\u00fcrich",
    "sg:orig_category":"Unternehmensberatung",
    "sg:postcode":"8046",
    "sg:province":"Z\u00fcrich",
    "wof:name":"Hassler Astrid",
    "wof:placetype":"venue"
},
  "geometry": {"coordinates":[9.3924770355,47.4324874878],"type":"Point"}
}