{
  "type": "Feature",
  "properties": {
    "iso:country":"CH",
    "sg:address":"Weidstrasse 11",
    "sg:city":"Rotkreuz",
    "sg:orig_category":"Stukkateurgewerbe, Gipserei U Verputzerei",
    "sg:phone":"+41 41 790 68 67",
    "sg:postcode":"6343",
    "sg:province":"Zug",
    "wof:name":"Gipsergesch\u00e4ft Buchser F. Gmbh",
    "wof:placetype":"venue"
},
  "geometry": {"coordinates":[8.4297609329,47.135887146],"type":"Point"}
}