{
  "type": "Feature",
  "properties": {
    "iso:country":"CH",
    "sg:address":"S\u00e4dlenweg 33",
    "sg:city":"Z\u00fcrich",
    "sg:orig_category":"Unternehmensberatung",
    "sg:phone":"+41 14639578",
    "sg:postcode":"8055",
    "sg:province":"Z\u00fcrich",
    "wof:name":"Giordanengo O., Unternehmensberatung",
    "wof:placetype":"venue"
},
  "geometry": {"coordinates":[8.4895133972,47.3668212891],"type":"Point"}
}