{
  "type": "Feature",
  "properties": {
    "iso:country":"CH",
    "sg:address":"M\u00fchle 250",
    "sg:city":"Thalheim",
    "sg:classifiers":[
        {
            "category":"Professional",
            "type":"Services"
        }
    ],
    "sg:phone":"+41 56 443 17 48",
    "sg:postcode":"5112",
    "sg:province":"Aargau",
    "sg:tags":[
        "transport"
    ],
    "wof:name":"Wernli Trans Ag",
    "wof:placetype":"venue"
},
  "geometry": {"coordinates":[8.1044073105,47.4369277954],"type":"Point"}
}