{
  "type": "Feature",
  "properties": {
    "iso:country":"CH",
    "sg:address":"St. Albanstrasse 12",
    "sg:city":"Pratteln",
    "sg:orig_category":"Herstellung von sonstigen Maschinen f\u00fcr unspezifische Verwendung",
    "sg:phone":"+41 61 821 46 04",
    "sg:postcode":"4133",
    "sg:province":"Basel-Landschaft",
    "wof:name":"Roland B\u00fcrgin Trading",
    "wof:placetype":"venue"
},
  "geometry": {"coordinates":[7.6892580986,47.5202598572],"type":"Point"}
}