{
  "type": "Feature",
  "properties": {
    "iso:country":"CH",
    "sg:address":"Gr\u00fcnaustrasse 6",
    "sg:city":"Horn",
    "sg:orig_category":"Sportvereine Flug Delta",
    "sg:postcode":"9326",
    "sg:province":"Thurgau",
    "wof:name":"Gleitschirmklub Glarnerland",
    "wof:placetype":"venue"
},
  "geometry": {"coordinates":[9.0545148849,47.1724510193],"type":"Point"}
}