{
  "type": "Feature",
  "properties": {
    "iso:country":"CH",
    "sg:address":"Salstrasse 68",
    "sg:city":"Winterthur",
    "sg:orig_category":"Sonstige Kultur U Unterhaltungseinrichtungen Spielsalons",
    "sg:phone":"+41 52 222 41 20",
    "sg:postcode":"8400",
    "sg:province":"Z\u00fcrich",
    "wof:name":"Billardhalle Winti P & U Gmbh",
    "wof:placetype":"venue"
},
  "geometry": {"coordinates":[8.7139320374,47.5052757263],"type":"Point"}
}