{
  "type": "Feature",
  "properties": {
    "iso:country":"CH",
    "sg:address":"Hohgantweg 8 3661 Uetendorf. Postfach",
    "sg:city":"Uetendorf",
    "sg:orig_category":"Maschinen-Fabrikation",
    "sg:phone":"+41 33 345 49 07",
    "sg:postcode":"3661",
    "sg:province":"Bern",
    "wof:name":"Wemont Eschler Walter Maschinen- U. Apparatebau",
    "wof:placetype":"venue"
},
  "geometry": {"coordinates":[7.5964012146,46.7744445801],"type":"Point"}
}