{
  "type": "Feature",
  "properties": {
    "iso:country":"CH",
    "sg:address":"Landweg 1 6052 Hergiswil Nw. Postfach",
    "sg:city":"Bassersdorf",
    "sg:orig_category":"Herstellung von sonstigen elektrischen Ausr\u00fcstungen",
    "sg:phone":"+41 18365551",
    "sg:postcode":"8303",
    "sg:province":"Z\u00fcrich",
    "wof:name":"Labosim Ag",
    "wof:placetype":"venue"
},
  "geometry": {"coordinates":[8.3114833832,46.9857254028],"type":"Point"}
}