{
  "type": "Feature",
  "properties": {
    "iso:country":"CH",
    "sg:address":"Chemin Du Braillon 15",
    "sg:city":"Lutry",
    "sg:orig_category":"Vermietung U Verpachtung von eigenen Immobilien Vermittlung von Immobilien",
    "sg:phone":"+41 21 791 51 55",
    "sg:postcode":"1095",
    "sg:province":"Vaud",
    "wof:name":"Forster Immobili\u00e8re Sa",
    "wof:placetype":"venue"
},
  "geometry": {"coordinates":[6.6801328659,46.508392334],"type":"Point"}
}