{
  "type": "Feature",
  "properties": {
    "iso:country":"CH",
    "sg:address":"Panoramastr. 19",
    "sg:city":"Kirchberg",
    "sg:classifiers":[
        {
            "category":"Manufacturing",
            "subcategory":"Wood Products",
            "type":"Manufacturing & Wholesale Goods"
        }
    ],
    "sg:phone":"+41 26 665 00 45",
    "sg:postcode":"9533",
    "sg:province":"St. Gallen",
    "sg:tags":[
        "professional",
        "furniture"
    ],
    "wof:name":"Tergon Gmbh",
    "wof:placetype":"venue"
},
  "geometry": {"coordinates":[6.8680329323,46.8162384033],"type":"Point"}
}