{
  "type": "Feature",
  "properties": {
    "iso:country":"CH",
    "sg:address":"Schwandistrasse 35",
    "sg:city":"Frutigen",
    "sg:orig_category":"Innenausbau Zimmerei, Ingenieurholzbau",
    "sg:phone":"+41 79 315 70 37",
    "sg:postcode":"3714",
    "sg:province":"Bern",
    "wof:name":"Christian Wandfluh Holz-& Treppenbau",
    "wof:placetype":"venue"
},
  "geometry": {"coordinates":[7.6622509956,46.5962486267],"type":"Point"}
}