{
  "type": "Feature",
  "properties": {
    "iso:country":"CH",
    "sg:address":"Rue Des Beaux-arts 6",
    "sg:city":"Neuch\u00e2tel",
    "sg:orig_category":"Arztpraxen",
    "sg:phone":"+41 32 724 12 52",
    "sg:postcode":"2000",
    "sg:province":"Neuch\u00e2tel",
    "wof:name":"Dr M\u00e9d. Gilles De Meuron M\u00e9decin Sp\u00e9cialiste",
    "wof:placetype":"venue"
},
  "geometry": {"coordinates":[6.936359,46.992062],"type":"Point"}
}