{
  "type": "Feature",
  "properties": {
    "iso:country":"CH",
    "sg:address":"6933",
    "sg:city":"Muzzano",
    "sg:orig_category":"Detailhandel mit Radio U Fernsehger\u00e4ten",
    "sg:phone":"+41 91 966 85 77",
    "sg:postcode":"6933",
    "sg:province":"Ticino",
    "wof:name":"Heinrich B\u00fctikofer Radio-televisione",
    "wof:placetype":"venue"
},
  "geometry": {"coordinates":[8.9140300751,46.0051193237],"type":"Point"}
}