{
  "type": "Feature",
  "properties": {
    "iso:country":"CH",
    "sg:address":"Golf Club Du Br\u00e9sil 1376 Eclagnens. Postfach",
    "sg:city":"Eclagnens",
    "sg:orig_category":"RESTAURANTS: TEA-ROOMS",
    "sg:postcode":"1376",
    "sg:province":"Vaud",
    "wof:name":"Pouch Fran\u00e7ois",
    "wof:placetype":"venue"
},
  "geometry": {"coordinates":[6.6045541763,46.6579742432],"type":"Point"}
}