{
  "type": "Feature",
  "properties": {
    "iso:country":"CH",
    "sg:address":"Route De Montana",
    "sg:city":"Veyras",
    "sg:classifiers":[
        {
            "category":"Restaurant",
            "type":"Food & Drink"
        }
    ],
    "sg:phone":"+41 27 455 04 29",
    "sg:postcode":"3968",
    "sg:province":"Valais",
    "wof:name":"Caf\u00e9 Crois\u00e9e",
    "wof:placetype":"venue"
},
  "geometry": {"coordinates":[7.5303797722,46.3018112183],"type":"Point"}
}