{
  "type": "Feature",
  "properties": {
    "iso:country":"CH",
    "sg:address":"Rue Central 33",
    "sg:city":"Montagne-moutier",
    "sg:orig_category":"Warenh\u00e4user",
    "sg:phone":"+41 32 493 31 16",
    "sg:postcode":"2740",
    "sg:province":"Bern",
    "wof:name":"Manor",
    "wof:placetype":"venue"
},
  "geometry": {"coordinates":[7.3748931885,47.2797431946],"type":"Point"}
}