{
  "type": "Feature",
  "properties": {
    "addr:full":"Witikonerstrasse 297 Z\u00fcrich Z\u00fcrich 8053",
    "addr:housenumber":"297",
    "addr:postcode":"8053",
    "addr:street":"Witikonerstrasse",
    "iso:country":"CH",
    "sg:address":"Witikonerstrasse 297",
    "sg:city":"Z\u00fcrich",
    "sg:orig_category":"Detailhandel mit Blumen U Pflanzen",
    "sg:phone":"+41 13812660",
    "sg:postcode":"8053",
    "sg:province":"Z\u00fcrich",
    "wof:name":"Helen Kuster Blumenhaus Witikon",
    "wof:placetype":"venue"
},
  "geometry": {"coordinates":[8.586588,47.358406],"type":"Point"}
}