{
  "type": "Feature",
  "properties": {
    "iso:country":"CH",
    "sg:address":"Witikonerstrasse 297",
    "sg:city":"Z\u00fcrich",
    "sg:orig_category":"Detailhandel mit Blumen U Pflanzen",
    "sg:phone":"+41 13812660",
    "sg:postcode":"8053",
    "sg:province":"Z\u00fcrich",
    "wof:name":"Helen Kuster Blumenhaus Witikon",
    "wof:placetype":"venue"
},
  "geometry": {"coordinates":[8.586588,47.358406],"type":"Point"}
}