{
  "type": "Feature",
  "properties": {
    "iso:country":"CH",
    "sg:address":"Sperrstrasse 3",
    "sg:city":"Basel",
    "sg:classifiers":[
        {
            "category":"Restaurant",
            "type":"Food & Drink"
        }
    ],
    "sg:phone":"+41 61 683 28 23",
    "sg:postcode":"4057",
    "sg:province":"Basel-Stadt",
    "wof:name":"Restaurant Neuer Sultan Saray",
    "wof:placetype":"venue"
},
  "geometry": {"coordinates":[7.5916252136,47.5645065308],"type":"Point"}
}