{
  "type": "Feature",
  "properties": {
    "iso:country":"CH",
    "sg:address":"S\u00fcdstrasse 11",
    "sg:city":"B\u00fclach",
    "sg:orig_category":"Architektur U Ingenieurb\u00fcros",
    "sg:phone":"+41 18606656",
    "sg:postcode":"8180",
    "sg:province":"Z\u00fcrich",
    "wof:name":"Ewald Spandel Ingenieurb\u00fcro",
    "wof:placetype":"venue"
},
  "geometry": {"coordinates":[8.540625,47.514706],"type":"Point"}
}