{
  "type": "Feature",
  "properties": {
    "iso:country":"CH",
    "sg:address":"Viale C. Olgiati 23",
    "sg:city":"Giubiasco",
    "sg:orig_category":"Sonstiger Grosshandel",
    "sg:phone":"+41 17373660",
    "sg:postcode":"6512",
    "sg:province":"Ticino",
    "wof:name":"Spinoff, Saiti R.",
    "wof:placetype":"venue"
},
  "geometry": {"coordinates":[8.4494972229,47.3552360535],"type":"Point"}
}