{
  "type": "Feature",
  "properties": {
    "iso:country":"CH",
    "sg:address":"Holzstrasse 1",
    "sg:city":"Muotathal",
    "sg:orig_category":"S\u00e4gewerke Zimmerei, Dachdeckerei, Bauspenglerei U Abdichtung",
    "sg:phone":"+41 71 923 29 29",
    "sg:postcode":"6436",
    "sg:province":"Schwyz",
    "wof:name":"Thalmann Holzbau Ag",
    "wof:placetype":"venue"
},
  "geometry": {"coordinates":[9.0448856354,47.4592323303],"type":"Point"}
}