{
  "type": "Feature",
  "properties": {
    "iso:country":"CH",
    "sg:address":"Seestrasse 990",
    "sg:city":"Meilen",
    "sg:orig_category":"Markt U Meinungsforschung Unternehmensberatung",
    "sg:phone":"+41 19253565",
    "sg:postcode":"8706",
    "sg:province":"Z\u00fcrich",
    "wof:name":"L.a.s. Modeinformation Ltd",
    "wof:placetype":"venue"
},
  "geometry": {"coordinates":[8.652130127,47.2653999329],"type":"Point"}
}