{
  "type": "Feature",
  "properties": {
    "iso:country":"CH",
    "sg:address":"Zentralstrasse 44 6003 Luzern. Postfach",
    "sg:city":"Luzern",
    "sg:orig_category":"Vereine Musik/Blasmusik",
    "sg:phone":"+41 41 210 34 87",
    "sg:postcode":"6003",
    "sg:province":"Luzern",
    "wof:name":"Tr\u00e4gerverein Luzerner Sinfonieorchester",
    "wof:placetype":"venue"
},
  "geometry": {"coordinates":[8.3097457886,47.0464324951],"type":"Point"}
}