{
  "type": "Feature",
  "properties": {
    "iso:country":"CH",
    "sg:address":"Ringgenmatt 18",
    "sg:city":"Schwarzenburg",
    "sg:orig_category":"S\u00e4gewerke",
    "sg:phone":"+41 31 731 05 45",
    "sg:postcode":"3150",
    "sg:province":"Bern",
    "wof:name":"Werner Bachmann S\u00e4gerei",
    "wof:placetype":"venue"
},
  "geometry": {"coordinates":[7.3494610786,46.8232154846],"type":"Point"}
}