{
  "type": "Feature",
  "properties": {
    "iso:country":"CH",
    "sg:address":"Bretzwilerstrasse 19",
    "sg:city":"Nunningen",
    "sg:orig_category":"Abwasserreinigung Wasserversorgung",
    "sg:phone":"+41 61 791 01 80",
    "sg:postcode":"4208",
    "sg:province":"Solothurn",
    "wof:name":"Wasserversorgung Nunningen",
    "wof:placetype":"venue"
},
  "geometry": {"coordinates":[7.621596,47.393772],"type":"Point"}
}