{
  "type": "Feature",
  "properties": {
    "iso:country":"CH",
    "sg:address":"5706",
    "sg:city":"Boniswil",
    "sg:classifiers":[
        {
            "category":"Education",
            "subcategory":"Library",
            "type":"Public Place"
        }
    ],
    "sg:phone":"+41 62 776 10 57",
    "sg:postcode":"5706",
    "sg:province":"Aargau",
    "sg:tags":[
        "u",
        "bibliotheken",
        "archive"
    ],
    "wof:name":"Volksbibliothek",
    "wof:placetype":"venue"
},
  "geometry": {"coordinates":[8.12676,47.328541],"type":"Point"}
}