{
  "type": "Feature",
  "properties": {
    "iso:country":"CH",
    "sg:address":"Schulstrasse 29 8000 Z\u00fcrich. Postfach 8050 Z\u00fcrich",
    "sg:city":"Zust",
    "sg:orig_category":"Finanzierungsinstitutionen",
    "sg:postcode":"50",
    "wof:name":"Awag Finanz Schneider A.",
    "wof:placetype":"venue"
},
  "geometry": {"coordinates":[8.5440664291,47.4090118408],"type":"Point"}
}