{
  "type": "Feature",
  "properties": {
    "iso:country":"CH",
    "sg:address":"Im B\u00e4chli 53",
    "sg:city":"Bassersdorf",
    "sg:orig_category":"Sportvereine Ballsport Tennis",
    "sg:phone":"+41 18371232",
    "sg:postcode":"8303",
    "sg:province":"Z\u00fcrich",
    "wof:name":"Tc 8152 Opfikon-glattbrugg",
    "wof:placetype":"venue"
},
  "geometry": {"coordinates":[8.6370487213,47.4379463196],"type":"Point"}
}