{
  "type": "Feature",
  "properties": {
    "iso:country":"CH",
    "sg:address":"7155",
    "sg:city":"Ladir",
    "sg:orig_category":"Fahrschulen, Flugschulen",
    "sg:phone":"+41 81 925 38 22",
    "sg:postcode":"7155",
    "sg:province":"Graubunden",
    "wof:name":"Toni Cadruvi Autofahrschule",
    "wof:placetype":"venue"
},
  "geometry": {"coordinates":[9.1978302002,46.8012619019],"type":"Point"}
}