{
  "type": "Feature",
  "properties": {
    "iso:country":"CH",
    "sg:address":"Bedastrasse 15",
    "sg:city":"St.gallen",
    "sg:orig_category":"Grosshandel mit Obst U Gem\u00fcse",
    "sg:postcode":"9000",
    "sg:province":"St. Gallen",
    "wof:name":"Gravano & Bruno",
    "wof:placetype":"venue"
},
  "geometry": {"coordinates":[9.3912601471,47.4288635254],"type":"Point"}
}