{
  "type": "Feature",
  "properties": {
    "iso:country":"CH",
    "sg:address":"Zentralstrasse 33 2502 Biel/bienne. Postfach",
    "sg:city":"Biel/bienne",
    "sg:orig_category":"Kauf U Verkauf von Immobilien auf eigene Rechnung",
    "sg:postcode":"2502",
    "sg:province":"Bern",
    "wof:name":"Sacapella Ag",
    "wof:placetype":"venue"
},
  "geometry": {"coordinates":[7.2458348274,47.1378135681],"type":"Point"}
}