{
  "type": "Feature",
  "properties": {
    "iso:country":"CH",
    "sg:address":"Lachenstrasse 14",
    "sg:city":"Basel",
    "sg:orig_category":"D\u00e4mmung gegen K\u00e4lte, W\u00e4rme, Schall U Ersch\u00fctterung Sonstiger spezialisierter Hoch U Tiefbau",
    "sg:phone":"+41 61 321 36 36",
    "sg:postcode":"4056",
    "sg:province":"Basel-Stadt",
    "wof:name":"Iso-fuga Gmbh",
    "wof:placetype":"venue"
},
  "geometry": {"coordinates":[7.5691428185,47.568687439],"type":"Point"}
}