{
  "type": "Feature",
  "properties": {
    "iso:country":"CH",
    "sg:address":"Gewerbezone 19",
    "sg:city":"Buttisholz",
    "sg:orig_category":"G\u00fcterbef\u00f6rderung im Strassenverkehr",
    "sg:phone":"+41 41 970 28 78",
    "sg:postcode":"6018",
    "sg:province":"Luzern",
    "wof:name":"Eiholzer Peter Transporte",
    "wof:placetype":"venue"
},
  "geometry": {"coordinates":[8.0811700821,47.1104698181],"type":"Point"}
}