{
  "type": "Feature",
  "properties": {
    "addr:full":"Castagni Sentiero Dei 3 Viganello Ticino 6962",
    "addr:housenumber":"3",
    "addr:postcode":"6962",
    "addr:street":"Sentiero Dei",
    "iso:country":"CH",
    "sg:address":"Castagni Sentiero Dei 3",
    "sg:city":"Viganello",
    "sg:orig_category":"Architektur U Ingenieurb\u00fcros",
    "sg:postcode":"6962",
    "sg:province":"Ticino",
    "wof:name":"Studio Tecnico Taddei Sagl",
    "wof:placetype":"venue"
},
  "geometry": {"coordinates":[8.970897,46.014988],"type":"Point"}
}