{
  "type": "Feature",
  "properties": {
    "iso:country":"CH",
    "sg:address":"1807",
    "sg:city":"Blonay",
    "sg:orig_category":"Vereine Milit\u00e4r",
    "sg:postcode":"1807",
    "sg:province":"Vaud",
    "wof:name":"St\u00e9 Militaire",
    "wof:placetype":"venue"
},
  "geometry": {"coordinates":[6.8949828148,46.4651298523],"type":"Point"}
}