{
  "type": "Feature",
  "properties": {
    "iso:country":"CH",
    "sg:address":"Hohlstrasse 100",
    "sg:city":"Z\u00fcrich",
    "sg:classifiers":[
        {
            "category":"Autos & Motor Vehicles",
            "subcategory":"Auto Supplies",
            "type":"Retail Goods"
        }
    ],
    "sg:phone":"+41 12993030",
    "sg:postcode":"8004",
    "sg:province":"Z\u00fcrich",
    "sg:tags":[
        "automobile",
        "accessory"
    ],
    "wof:name":"Burri Automobile Ag",
    "wof:placetype":"venue"
},
  "geometry": {"coordinates":[8.522876,47.378998],"type":"Point"}
}