{
  "type": "Feature",
  "properties": {
    "iso:country":"CH",
    "sg:address":"Ilgenstrasse 20",
    "sg:city":"St.gallen",
    "sg:orig_category":"Softwareentwicklung U beratung",
    "sg:phone":"+41 71 277 22 47",
    "sg:postcode":"9000",
    "sg:province":"St. Gallen",
    "wof:name":"Smg Softwareentwicklung Gerodetti Marco",
    "wof:placetype":"venue"
},
  "geometry": {"coordinates":[9.3605670929,47.4181365967],"type":"Point"}
}