{
  "type": "Feature",
  "properties": {
    "iso:country":"CH",
    "sg:address":"Rue Du 1er-mars 6",
    "sg:city":"Geneveys-coffrane",
    "sg:classifiers":[
        {
            "category":"Restaurant",
            "type":"Food & Drink"
        }
    ],
    "sg:phone":"+41 27 957 29 02",
    "sg:postcode":"2206",
    "sg:province":"Neuch\u00e2tel",
    "wof:name":"Tea-room La Cabane",
    "wof:placetype":"venue"
},
  "geometry": {"coordinates":[7.9365530014,46.1258087158],"type":"Point"}
}