{
  "type": "Feature",
  "properties": {
    "iso:country":"CH",
    "sg:address":"1189",
    "sg:city":"Saubraz",
    "sg:orig_category":"Primarschulen",
    "sg:phone":"+41 24 481 38 24",
    "sg:postcode":"1189",
    "sg:province":"Vaud",
    "wof:name":"Ecole Primaire",
    "wof:placetype":"venue"
},
  "geometry": {"coordinates":[6.3291602135,46.5189094543],"type":"Point"}
}