{
  "type": "Feature",
  "properties": {
    "iso:country":"CH",
    "sg:address":"Rue De La Gare 9",
    "sg:city":"Nyon",
    "sg:orig_category":"Fachdetailhandel mit pharmazeutischen Produkten",
    "sg:postcode":"1260",
    "sg:province":"Vaud",
    "wof:name":"Du Pasquier Ph.",
    "wof:placetype":"venue"
},
  "geometry": {"coordinates":[6.2382922173,46.3824768066],"type":"Point"}
}