{
  "type": "Feature",
  "properties": {
    "iso:country":"CH",
    "sg:address":"Case Postale 68",
    "sg:city":"Le Landeron",
    "sg:classifiers":[
        {
            "category":"Banks & Credit Unions",
            "subcategory":"Bank",
            "type":"Services"
        }
    ],
    "sg:phone":"+41 32 863 10 47",
    "sg:postcode":"2525",
    "sg:province":"Neuch\u00e2tel",
    "wof:name":"Banque Raiffeisen Du Val-de-travers",
    "wof:placetype":"venue"
},
  "geometry": {"coordinates":[6.67322,46.938969],"type":"Point"}
}