{
  "type": "Feature",
  "properties": {
    "iso:country":"CH",
    "sg:address":"Ulmenstrasse 76",
    "sg:city":"Frauenfeld",
    "sg:orig_category":"Stukkateurgewerbe, Gipserei U Verputzerei",
    "sg:phone":"+41 52 728 09 55",
    "sg:postcode":"8500",
    "sg:province":"Thurgau",
    "wof:name":"Hermann Hofmaier Gipser-& Malergesch\u00e4ft",
    "wof:placetype":"venue"
},
  "geometry": {"coordinates":[8.8731098175,47.5518417358],"type":"Point"}
}