{
  "type": "Feature",
  "properties": {
    "iso:country":"CH",
    "sg:address":"Route Des Jeunes 12",
    "sg:city":"Carouge",
    "sg:classifiers":[
        {
            "category":"Shopping",
            "subcategory":"Books",
            "type":"Retail Goods"
        }
    ],
    "sg:phone":"+41 71 260 22 05",
    "sg:postcode":"1227",
    "sg:province":"Gen\u00e8ve",
    "wof:name":"Vsb Verlag Gmbh",
    "wof:placetype":"venue"
},
  "geometry": {"coordinates":[9.333637,47.403866],"type":"Point"}
}