{
  "type": "Feature",
  "properties": {
    "iso:country":"CH",
    "sg:address":"4422",
    "sg:city":"Arisdorf",
    "sg:orig_category":"Sportvereine Turnen Vereine Damen",
    "sg:postcode":"4422",
    "sg:province":"Basel-Landschaft",
    "wof:name":"Damenriege",
    "wof:placetype":"venue"
},
  "geometry": {"coordinates":[7.7654452324,47.5093727112],"type":"Point"}
}