{
  "type": "Feature",
  "properties": {
    "iso:country":"CH",
    "sg:address":"Planchettes Rue Des 67",
    "sg:city":"Porrentruy",
    "sg:orig_category":"Interessenvertretungen",
    "sg:postcode":"2900",
    "sg:province":"Jura",
    "wof:name":"Coop\u00e9rative F\u00eates Des Paysans Jurassiens, Fpj",
    "wof:placetype":"venue"
},
  "geometry": {"coordinates":[7.0785369873,47.4122505188],"type":"Point"}
}