{
  "type": "Feature",
  "properties": {
    "iso:country":"CH",
    "sg:address":"Chemin De Pierrefleur 60",
    "sg:city":"Lausanne",
    "sg:orig_category":"Arztpraxen",
    "sg:phone":"+41 22 798 69 66",
    "sg:postcode":"1004",
    "sg:province":"Vaud",
    "wof:name":"Dr M\u00e9d. Claude Bolognini M\u00e9decin Sp\u00e9cialiste Fmh",
    "wof:placetype":"venue"
},
  "geometry": {"coordinates":[6.121597,46.23069],"type":"Point"}
}