{
  "type": "Feature",
  "properties": {
    "iso:country":"CH",
    "sg:address":"Bernstrasse 3",
    "sg:city":"Sch\u00fcpfen",
    "sg:orig_category":"Kosmetikinstitute",
    "sg:phone":"+41 81 413 13 62",
    "sg:postcode":"3054",
    "sg:province":"Bern",
    "wof:name":"Katharina Schluep",
    "wof:placetype":"venue"
},
  "geometry": {"coordinates":[9.8191509247,46.7910842896],"type":"Point"}
}