{
  "type": "Feature",
  "properties": {
    "iso:country":"CH",
    "sg:address":"Hinterrainweg 16 4710 Balsthal. Postfach 623",
    "sg:city":"Balsthal",
    "sg:orig_category":"Elektroinstallation Herstellung von Elektromotoren, Generatoren U Transformatoren",
    "sg:phone":"+41 62 391 13 35",
    "sg:postcode":"4710",
    "sg:province":"Solothurn",
    "wof:name":"Elektro Dec Ag",
    "wof:placetype":"venue"
},
  "geometry": {"coordinates":[7.6836547852,47.3135681152],"type":"Point"}
}