{
  "type": "Feature",
  "properties": {
    "iso:country":"CH",
    "sg:address":"Sch\u00f6nthal",
    "sg:city":"F\u00fcllinsdorf",
    "sg:orig_category":"W\u00e4scherei U chemische Reinigung",
    "sg:phone":"+41 61 401 41 08",
    "sg:postcode":"4414",
    "sg:province":"Basel-Landschaft",
    "wof:name":"Fab Textil-reinigung",
    "wof:placetype":"venue"
},
  "geometry": {"coordinates":[7.726650238,47.5009307861],"type":"Point"}
}