{
  "type": "Feature",
  "properties": {
    "iso:country":"CH",
    "sg:address":"Sonneckstrasse 10",
    "sg:city":"Jona",
    "sg:orig_category":"Non-Classified Establishments",
    "sg:phone":"+41 55 210 31 41",
    "sg:postcode":"8645",
    "sg:province":"St. Gallen",
    "wof:name":"Hpm Holding",
    "wof:placetype":"venue"
},
  "geometry": {"coordinates":[8.8224315643,47.2425422668],"type":"Point"}
}