{
  "type": "Feature",
  "properties": {
    "iso:country":"CH",
    "sg:address":"Grand-rue 1",
    "sg:city":"Travers",
    "sg:orig_category":"Elektroinstallation Herstellung von Radio U Fernsehger\u00e4ten sowie phono U videotechnischen Ger\u00e4ten",
    "sg:phone":"+41 32 863 36 30",
    "sg:postcode":"2105",
    "sg:province":"Neuch\u00e2tel",
    "wof:name":"Techno-services J.-p.baumeler Radio-tv Satellite \u00e9lectron.",
    "wof:placetype":"venue"
},
  "geometry": {"coordinates":[6.6765508652,46.9403800964],"type":"Point"}
}