{
  "type": "Feature",
  "properties": {
    "iso:country":"CH",
    "sg:address":"3032 Hinterkappelen. Postfach 70",
    "sg:city":"Hinterkappelen",
    "sg:orig_category":"Sportvereine Ballsport Tennis",
    "sg:phone":"+41 31 839 76 03",
    "sg:postcode":"3032",
    "sg:province":"Bern",
    "wof:name":"Tennisclub Worb",
    "wof:placetype":"venue"
},
  "geometry": {"coordinates":[7.5633797646,46.9297447205],"type":"Point"}
}