{
  "type": "Feature",
  "properties": {
    "iso:country":"CH",
    "sg:address":"Via Al Molino",
    "sg:city":"Ascona",
    "sg:orig_category":"Bauschreinerei Herstellung von Konstruktionsteilen, Fertigbauteilen U Ausbauelementen aus Holz",
    "sg:phone":"+41 91 791 61 83",
    "sg:postcode":"6612",
    "sg:province":"Ticino",
    "wof:name":"Donato Perucchi Falegnameria",
    "wof:placetype":"venue"
},
  "geometry": {"coordinates":[8.77754,46.162159],"type":"Point"}
}