{
  "type": "Feature",
  "properties": {
    "iso:country":"CH",
    "sg:address":"Schreberweg 7",
    "sg:city":"Z\u00fcrich",
    "sg:orig_category":"Erschliessung von Grundst\u00fccken",
    "sg:postcode":"8044",
    "sg:province":"Z\u00fcrich",
    "wof:name":"Widmenwies",
    "wof:placetype":"venue"
},
  "geometry": {"coordinates":[8.7893590927,47.3282775879],"type":"Point"}
}