{
  "type": "Feature",
  "properties": {
    "iso:country":"CH",
    "sg:address":"Hauptstrasse 11",
    "sg:city":"Ittenthal",
    "sg:orig_category":"Fotografisches Gewerbe U fotografische Laboratorien",
    "sg:phone":"+41 61 771 03 53",
    "sg:postcode":"5083",
    "sg:province":"Aargau",
    "wof:name":"Otto Fl\u00fcck",
    "wof:placetype":"venue"
},
  "geometry": {"coordinates":[7.4317951202,47.4036750793],"type":"Point"}
}