{
  "type": "Feature",
  "properties": {
    "addr:full":"Baumgartenweg 6 Niederlenz Aargau 5702",
    "addr:housenumber":"6",
    "addr:postcode":"5702",
    "addr:street":"Baumgartenweg",
    "iso:country":"CH",
    "sg:address":"Baumgartenweg 6",
    "sg:city":"Niederlenz",
    "sg:orig_category":"Detailhandel mit Bekleidung",
    "sg:phone":"+41 56 470 31 00",
    "sg:postcode":"5702",
    "sg:province":"Aargau",
    "wof:name":"R\u00fcebli-kurier Gmbh",
    "wof:placetype":"venue"
},
  "geometry": {"coordinates":[8.18018,47.398491],"type":"Point"}
}