{
  "type": "Feature",
  "properties": {
    "iso:country":"CH",
    "sg:address":"Sonnenstrasse 8-10",
    "sg:city":"Au",
    "sg:orig_category":"Auctions, Auction-Rooms, Special Auctions",
    "sg:phone":"+41 71 744 39 71",
    "sg:postcode":"9434",
    "sg:province":"St. Gallen",
    "wof:name":"Imt Armaturen Ag",
    "wof:placetype":"venue"
},
  "geometry": {"coordinates":[9.63727,47.434204],"type":"Point"}
}