{
  "type": "Feature",
  "properties": {
    "addr:full":"Luzernerstrasse 11 Zofingen Aargau 4800",
    "addr:housenumber":"11",
    "addr:postcode":"4800",
    "addr:street":"Luzernerstrasse",
    "iso:country":"CH",
    "sg:address":"Luzernerstrasse 11",
    "sg:city":"Zofingen",
    "sg:classifiers":[
        {
            "category":"Social Services",
            "subcategory":"Retirement Home",
            "type":"Services"
        }
    ],
    "sg:phone":"+41 62 751 54 66",
    "sg:postcode":"4800",
    "sg:province":"Aargau",
    "sg:tags":[
        "pflegeheime",
        "u",
        "alters"
    ],
    "wof:name":"Altersheim Im Tanner",
    "wof:placetype":"venue"
},
  "geometry": {"coordinates":[7.948542,47.284042],"type":"Point"}
}