{
  "type": "Feature",
  "properties": {
    "addr:full":"Via Balestra 11 Lugano Ticino 6900",
    "addr:housenumber":"11",
    "addr:postcode":"6900",
    "addr:street":"Via Balestra",
    "iso:country":"CH",
    "sg:address":"Via Balestra 11",
    "sg:city":"Lugano",
    "sg:classifiers":[
        {
            "category":"Banks & Credit Unions",
            "subcategory":"Bank",
            "type":"Services"
        }
    ],
    "sg:phone":"+41 91 910 01 01",
    "sg:postcode":"6900",
    "sg:province":"Ticino",
    "wof:name":"Abn Amro Bank",
    "wof:placetype":"venue"
},
  "geometry": {"coordinates":[8.954735,46.008133],"type":"Point"}
}