{
  "type": "Feature",
  "properties": {
    "iso:country":"CH",
    "sg:address":"Elfenaustrasse 3 2502 Biel/bienne Case Postale 902",
    "sg:city":"Biel/bienne",
    "sg:orig_category":"Sportvereine Eissport Curling",
    "sg:postcode":"2501",
    "sg:province":"Bern",
    "wof:name":"Curling Club Brienz",
    "wof:placetype":"venue"
},
  "geometry": {"coordinates":[8.036860466,46.7545585632],"type":"Point"}
}