{
  "type": "Feature",
  "properties": {
    "iso:country":"CH",
    "sg:address":"Sissacherstrasse 29 4052 Basel. Postfach 348",
    "sg:city":"Basel",
    "sg:orig_category":"Vermietung U Verpachtung von eigenen Immobilien Vermittlung von Immobilien",
    "sg:phone":"+41 61 311 84 00",
    "sg:postcode":"4020",
    "sg:province":"Basel-Stadt",
    "wof:name":"Mgw Immobilien Ag",
    "wof:placetype":"venue"
},
  "geometry": {"coordinates":[7.6084599495,47.5462913513],"type":"Point"}
}