{
  "type": "Feature",
  "properties": {
    "iso:country":"CH",
    "sg:address":"M\u00fchlebachstrasse 48 8008 Z\u00fcrich. Postfach",
    "sg:city":"Z\u00fcrich",
    "sg:orig_category":"Softwareentwicklung U beratung",
    "sg:postcode":"8008",
    "sg:province":"Z\u00fcrich",
    "wof:name":"Eichhorn Informatik",
    "wof:placetype":"venue"
},
  "geometry": {"coordinates":[8.5514593124,47.3638458252],"type":"Point"}
}