{
  "type": "Feature",
  "properties": {
    "iso:country":"CH",
    "sg:address":"Grametstrasse 9 5272 Gansingen. Postfach",
    "sg:city":"Gansingen",
    "sg:orig_category":"Unclassifiable Establishments",
    "sg:phone":"+41 62 875 09 91",
    "sg:postcode":"5272",
    "sg:province":"Aargau",
    "wof:name":"Cleopatra Beauty Permanent Make Up Biry Phannee Kosmetikstudio. Augenbrauen, Lidstriche, Lippen, Usw.; Pigmentieren",
    "wof:placetype":"venue"
},
  "geometry": {"coordinates":[8.1361865997,47.5443992615],"type":"Point"}
}