{
  "type": "Feature",
  "properties": {
    "addr:full":"Oberneuhofstrasse 3 Baar Zug 6340",
    "addr:housenumber":"3",
    "addr:postcode":"6340",
    "addr:street":"Oberneuhofstrasse;Zug",
    "iso:country":"CH",
    "sg:address":"Oberneuhofstrasse 3",
    "sg:city":"Baar",
    "sg:orig_category":"Datenverarbeitungsdienste Softwareentwicklung U beratung",
    "sg:phone":"+41 41 769 68 68",
    "sg:postcode":"6340",
    "sg:province":"Zug",
    "wof:name":"Sage Sesam Ltd",
    "wof:placetype":"venue"
},
  "geometry": {"coordinates":[8.51566,47.188763],"type":"Point"}
}