{
  "type": "Feature",
  "properties": {
    "iso:country":"CH",
    "sg:address":"Mittelbergsteig 15",
    "sg:city":"Z\u00fcrich",
    "sg:orig_category":"Technische, physikalische U chemische Untersuchung",
    "sg:postcode":"8044",
    "sg:province":"Z\u00fcrich",
    "wof:name":"Coserv, A. Wolfisberg",
    "wof:placetype":"venue"
},
  "geometry": {"coordinates":[8.8291730881,47.2207374573],"type":"Point"}
}