{
  "type": "Feature",
  "properties": {
    "iso:country":"CH",
    "sg:address":"Les Champs Aux Roses 1338 Ballaigues Case Postale 13",
    "sg:city":"Ballaigues",
    "sg:orig_category":"Herstellung von Kunststoffwaren Herstellung von sonstigen Maschinen f\u00fcr unspezifische Verwendung",
    "sg:phone":"+41 21 843 33 17",
    "sg:postcode":"1338",
    "sg:province":"Vaud",
    "wof:name":"Manuplast Sa",
    "wof:placetype":"venue"
},
  "geometry": {"coordinates":[6.4034152031,46.7271194458],"type":"Point"}
}