{
  "type": "Feature",
  "properties": {
    "iso:country":"CH",
    "sg:address":"Talweg 2",
    "sg:city":"Grellingen",
    "sg:classifiers":[
        {
            "category":"Insurance",
            "subcategory":"Insurance Agent",
            "type":"Services"
        }
    ],
    "sg:phone":"+41 61 741 23 53",
    "sg:postcode":"4203",
    "sg:province":"Basel-Landschaft",
    "sg:tags":[
        "versicherungsagenturen",
        "-broker"
    ],
    "wof:name":"Francesco Piccarreta Z\u00fcrich Versicherungen",
    "wof:placetype":"venue"
},
  "geometry": {"coordinates":[7.5933737755,47.4394874573],"type":"Point"}
}