{
  "type": "Feature",
  "properties": {
    "iso:country":"CH",
    "sg:address":"Chemin Des Colombaires 52",
    "sg:city":"Cully",
    "sg:orig_category":"Unternehmensberatung",
    "sg:phone":"+41 21 799 25 68",
    "sg:postcode":"1096",
    "sg:province":"Vaud",
    "wof:name":"Delay Philippe",
    "wof:placetype":"venue"
},
  "geometry": {"coordinates":[6.7226657867,46.4913787842],"type":"Point"}
}