{
  "type": "Feature",
  "properties": {
    "iso:country":"CH",
    "sg:address":"Herrenacker 11 8200 Schaffhausen. Postfach 312",
    "sg:city":"Schaffhausen",
    "sg:orig_category":"RESTAURANTS: TEA-ROOMS",
    "sg:phone":"+41 52 625 47 15",
    "sg:postcode":"8201",
    "sg:province":"Schaffhausen",
    "wof:name":"Wirtschaft Zum Frieden, Deventer T.",
    "wof:placetype":"venue"
},
  "geometry": {"coordinates":[8.632818222,47.6951980591],"type":"Point"}
}