{
  "type": "Feature",
  "properties": {
    "iso:country":"CH",
    "sg:address":"B\u00e4chigenstrasse 22",
    "sg:city":"Arnegg",
    "sg:orig_category":"Druck ohne Zeitungsdruck Offsetdruck",
    "sg:phone":"+41 71 385 63 24",
    "sg:postcode":"9212",
    "sg:province":"St. Gallen",
    "wof:name":"Printag Ag Offsetdruckerei",
    "wof:placetype":"venue"
},
  "geometry": {"coordinates":[9.2530670166,47.4434127808],"type":"Point"}
}