{
  "type": "Feature",
  "properties": {
    "iso:country":"CH",
    "sg:address":"Olivier Avenue Juste- 21",
    "sg:city":"Lausanne",
    "sg:orig_category":"Unternehmensberatung",
    "sg:phone":"+41 21 323 18 78",
    "sg:postcode":"1006",
    "sg:province":"Vaud",
    "wof:name":"Kemper G\u00e9rard",
    "wof:placetype":"venue"
},
  "geometry": {"coordinates":[6.6365032196,46.5141906738],"type":"Point"}
}