{
  "type": "Feature",
  "properties": {
    "iso:country":"CH",
    "sg:address":"Via San Bernardo 51",
    "sg:city":"Comano",
    "sg:orig_category":"Gartenbau",
    "sg:phone":"+41 71 911 21 91",
    "sg:postcode":"6949",
    "sg:province":"Ticino",
    "wof:name":"Felix Gartenbau Ag",
    "wof:placetype":"venue"
},
  "geometry": {"coordinates":[9.0582466125,47.4709510803],"type":"Point"}
}