{
  "type": "Feature",
  "properties": {
    "addr:full":"L\u00f6wenstrasse 19 Dietikon Z\u00fcrich 8953",
    "addr:housenumber":"19",
    "addr:postcode":"8953",
    "addr:street":"Loewenstrasse",
    "iso:country":"CH",
    "sg:address":"L\u00f6wenstrasse 19",
    "sg:city":"Dietikon",
    "sg:classifiers":[
        {
            "category":"Banks & Credit Unions",
            "subcategory":"Bank",
            "type":"Services"
        }
    ],
    "sg:phone":"+41 17439111",
    "sg:postcode":"8953",
    "sg:province":"Z\u00fcrich",
    "wof:name":"Cr\u00e9dit Suisse",
    "wof:placetype":"venue"
},
  "geometry": {"coordinates":[8.402598,47.405392],"type":"Point"}
}