{
  "type": "Feature",
  "properties": {
    "iso:country":"CH",
    "sg:address":"Judengasse 2",
    "sg:city":"Solothurn",
    "sg:orig_category":"RESTAURANTS: TEA-ROOMS",
    "sg:phone":"+41 32 622 33 30",
    "sg:postcode":"4500",
    "sg:province":"Solothurn",
    "wof:name":"Haudenschild Fritz",
    "wof:placetype":"venue"
},
  "geometry": {"coordinates":[7.536801815,47.2075042725],"type":"Point"}
}