{
  "type": "Feature",
  "properties": {
    "iso:country":"CH",
    "sg:address":"Brunnenthalstrasse 90",
    "sg:city":"Etzelkofen",
    "sg:orig_category":"Instandhaltung U Reparatur von Automobilen",
    "sg:phone":"+41 31 765 56 39",
    "sg:postcode":"3306",
    "sg:province":"Bern",
    "wof:name":"P. H\u00fcgli",
    "wof:placetype":"venue"
},
  "geometry": {"coordinates":[7.4759168625,47.0853118896],"type":"Point"}
}