{
  "type": "Feature",
  "properties": {
    "addr:full":"Zentrumsweg 36 Rothrist Aargau 4852",
    "addr:housenumber":"36",
    "addr:postcode":"4852",
    "addr:street":"Zentrumsweg",
    "iso:country":"CH",
    "sg:address":"Zentrumsweg 36",
    "sg:city":"Rothrist",
    "sg:orig_category":"Architektur U Ingenieurb\u00fcros",
    "sg:phone":"+41 62 794 28 41",
    "sg:postcode":"4852",
    "sg:province":"Aargau",
    "wof:name":"Wehrli Kurt, Konstruktionsb\u00fcro",
    "wof:placetype":"venue"
},
  "geometry": {"coordinates":[7.891129,47.306351],"type":"Point"}
}