{
  "type": "Feature",
  "properties": {
    "iso:country":"CH",
    "sg:address":"Cit\u00e9-ouest 17",
    "sg:city":"Gland",
    "sg:orig_category":"Fussboden, Fliesen U Plattenlegerei, Tapeziererei Tapeziererei",
    "sg:phone":"+41 22 995 04 45",
    "sg:postcode":"1196",
    "sg:province":"Vaud",
    "wof:name":"Crea Decor S\u00e0rl, Succursale De Gland",
    "wof:placetype":"venue"
},
  "geometry": {"coordinates":[6.2563591003,46.4232673645],"type":"Point"}
}