{
  "type": "Feature",
  "properties": {
    "iso:country":"CH",
    "sg:address":"Route Des Daillettes 21 1700 Fribourg Case Postale 976",
    "sg:city":"Fribourg",
    "sg:orig_category":"Grosse Gesch\u00e4fte 100-399 m2 Verwaltung von Immobilien",
    "sg:phone":"+41 26 460 26 70",
    "sg:postcode":"1700",
    "sg:province":"Fribourg",
    "wof:name":"Alvi-shop Sa",
    "wof:placetype":"venue"
},
  "geometry": {"coordinates":[7.1462688446,46.7925186157],"type":"Point"}
}