{
  "type": "Feature",
  "properties": {
    "iso:country":"CH",
    "sg:address":"Bertastrasse 1 8003 Z\u00fcrich. Postfach 304",
    "sg:city":"Uznach",
    "sg:orig_category":"Grosshandel mit B\u00fcromaschinen Softwareentwicklung U beratung",
    "sg:phone":"+41 55 285 86 00",
    "sg:postcode":"8730",
    "sg:province":"St. Gallen",
    "wof:name":"Music Network Gmbh",
    "wof:placetype":"venue"
},
  "geometry": {"coordinates":[8.5161180496,47.3752784729],"type":"Point"}
}