{
  "type": "Feature",
  "properties": {
    "iso:country":"CH",
    "sg:address":"Baarerstrasse 65",
    "sg:city":"Zug",
    "sg:classifiers":[
        {
            "category":"Restaurant",
            "type":"Food & Drink"
        }
    ],
    "sg:phone":"+41 41 711 25 35",
    "sg:postcode":"6300",
    "sg:province":"Zug",
    "wof:name":"Pizzeria Costa Smeralda",
    "wof:placetype":"venue"
},
  "geometry": {"coordinates":[8.5174379349,47.1763916016],"type":"Point"}
}