{
  "type": "Feature",
  "properties": {
    "iso:country":"CH",
    "sg:address":"Oberdorfstrasse 48",
    "sg:city":"Mels",
    "sg:orig_category":"Herstellung von Konstruktionsteilen, Fertigbauteilen U Ausbauelementen aus Holz Innenausbau",
    "sg:phone":"+41 81 723 13 60",
    "sg:postcode":"8887",
    "sg:province":"St. Gallen",
    "wof:name":"Lendi Bruno Schreinerei",
    "wof:placetype":"venue"
},
  "geometry": {"coordinates":[9.4161872864,47.044254303],"type":"Point"}
}