{
  "type": "Feature",
  "properties": {
    "iso:country":"CH",
    "sg:address":"Trolerstrasse 2",
    "sg:city":"Menziken",
    "sg:classifiers":[
        {
            "category":"Travel",
            "subcategory":"Hotels & Motels",
            "type":"Entertainment"
        }
    ],
    "sg:phone":"+41 62 771 13 45",
    "sg:postcode":"5737",
    "sg:province":"Aargau",
    "sg:tags":[
        "hotels",
        "mit",
        "restaurant"
    ],
    "wof:name":"Wirtshaus Trolerhof Thomi H. + Cathrein B.",
    "wof:placetype":"venue"
},
  "geometry": {"coordinates":[8.2018203735,47.2373199463],"type":"Point"}
}