{
  "type": "Feature",
  "properties": {
    "iso:country":"CH",
    "sg:address":"Staatsstrasse 99 9445 Rebstein. Postfach 163",
    "sg:city":"Rebstein",
    "sg:orig_category":"Regionalbanken U Sparkassen",
    "sg:phone":"+41 71 777 30 30",
    "sg:postcode":"9445",
    "sg:province":"St. Gallen",
    "wof:name":"Spar-& Leihkasse Rebstein",
    "wof:placetype":"venue"
},
  "geometry": {"coordinates":[9.5836267471,47.3980484009],"type":"Point"}
}