{
  "type": "Feature",
  "properties": {
    "iso:country":"CH",
    "sg:address":"Hauptstrasse 39 6182 Escholzmatt. Postfach 176",
    "sg:city":"Escholzmatt",
    "sg:orig_category":"Herstellung von Medikamenten U sonstigen pharmazeutischen Erzeugnissen Herstellung von pharmazeutisc",
    "sg:phone":"+41 41 462 62 11",
    "sg:postcode":"6182",
    "sg:province":"Luzern",
    "wof:name":"B. Braun Medical Ag",
    "wof:placetype":"venue"
},
  "geometry": {"coordinates":[8.1944198608,47.115650177],"type":"Point"}
}