{
  "type": "Feature",
  "properties": {
    "iso:country":"CH",
    "sg:address":"Z\u00fcrichstrasse 45a",
    "sg:city":"Adliswil",
    "sg:orig_category":"Einzelhandel mit Automobilteilen U Zubeh\u00f6r Herstellung von Bereifungen",
    "sg:phone":"+41 62 929 24 85",
    "sg:postcode":"8134",
    "sg:province":"Z\u00fcrich",
    "wof:name":"Pneu B\u00f6siger Ag",
    "wof:placetype":"venue"
},
  "geometry": {"coordinates":[7.8231768608,47.2405929565],"type":"Point"}
}