{
  "type": "Feature",
  "properties": {
    "iso:country":"CH",
    "sg:address":"Via San Salvatore 2",
    "sg:city":"Paradiso",
    "sg:orig_category":"Detailhandel mit Schuhen Reparatur von Schuhen U Lederwaren",
    "sg:phone":"+41 91 994 48 67",
    "sg:postcode":"6900",
    "sg:province":"Ticino",
    "wof:name":"Giuseppe Infantino",
    "wof:placetype":"venue"
},
  "geometry": {"coordinates":[8.9449720383,45.9922676086],"type":"Point"}
}