{
  "type": "Feature",
  "properties": {
    "iso:country":"CH",
    "sg:address":"Stadthausstrasse 16 8400 Winterthur. Postfach",
    "sg:city":"Winterthur",
    "sg:orig_category":"Grossbanken",
    "sg:phone":"+41 52 260 11 11",
    "sg:postcode":"8401",
    "sg:province":"Z\u00fcrich",
    "wof:name":"Credit Suisse",
    "wof:placetype":"venue"
},
  "geometry": {"coordinates":[8.7259836197,47.4999504089],"type":"Point"}
}