{
  "type": "Feature",
  "properties": {
    "iso:country":"CH",
    "sg:address":"Luzernerstrasse 287",
    "sg:city":"Merlischachen",
    "sg:orig_category":"Campingpl\u00e4tze Detailhandel mit Zeitungen U Zeitschriften Kioske",
    "sg:phone":"+41 41 850 08 04",
    "sg:postcode":"6402",
    "sg:province":"Schwyz",
    "wof:name":"Campingplatz Unterbergiswil",
    "wof:placetype":"venue"
},
  "geometry": {"coordinates":[8.40138,47.060886],"type":"Point"}
}