{
  "type": "Feature",
  "properties": {
    "iso:country":"CH",
    "sg:address":"Rikonerstrasse 18",
    "sg:city":"Effretikon",
    "sg:orig_category":"Physiotherapie",
    "sg:phone":"+41 52 343 23 04",
    "sg:postcode":"8307",
    "sg:province":"Z\u00fcrich",
    "wof:name":"Ellen Pool Physiotherapie",
    "wof:placetype":"venue"
},
  "geometry": {"coordinates":[8.6868591309,47.4291381836],"type":"Point"}
}