{
  "type": "Feature",
  "properties": {
    "iso:country":"CH",
    "sg:address":"Route De Saint-cergue 9",
    "sg:city":"Mies",
    "sg:orig_category":"Wohnheime",
    "sg:phone":"+41 22 755 31 25",
    "sg:postcode":"1295",
    "sg:province":"Vaud",
    "wof:name":"Maison De Retraite Du Cercle De Coppet",
    "wof:placetype":"venue"
},
  "geometry": {"coordinates":[6.1724910736,46.3082580566],"type":"Point"}
}