{
  "type": "Feature",
  "properties": {
    "iso:country":"CH",
    "sg:address":"Haldensteinstrasse 48",
    "sg:city":"Chur",
    "sg:orig_category":"Architekturb\u00fcros",
    "sg:phone":"+41 81 353 20 38",
    "sg:postcode":"7000",
    "sg:province":"Graubunden",
    "wof:name":"Markus Foi Architekturb\u00fcro",
    "wof:placetype":"venue"
},
  "geometry": {"coordinates":[9.532114,46.876854],"type":"Point"}
}