{
  "type": "Feature",
  "properties": {
    "iso:country":"CH",
    "sg:address":"Alte Thunstrasse 8",
    "sg:city":"Hilterfingen",
    "sg:orig_category":"Herstellung von sonstigen Maschinen f\u00fcr unspezifische Verwendung",
    "sg:postcode":"3652",
    "sg:province":"Bern",
    "wof:name":"Egger Apparatebau U. Vertrieb",
    "wof:placetype":"venue"
},
  "geometry": {"coordinates":[9.3040752411,47.4051628113],"type":"Point"}
}