{
  "type": "Feature",
  "properties": {
    "iso:country":"CH",
    "sg:address":"Via Cantonale",
    "sg:city":"Mezzovico",
    "sg:orig_category":"Herstellung von \u00d6fen U Brennern",
    "sg:phone":"+41 55 410 66 10",
    "sg:postcode":"6805",
    "sg:province":"Ticino",
    "wof:name":"Rhyner Werner",
    "wof:placetype":"venue"
},
  "geometry": {"coordinates":[8.7815437317,47.3674468994],"type":"Point"}
}