{
  "type": "Feature",
  "properties": {
    "iso:country":"CH",
    "sg:address":"Simplon Avenue Du 24",
    "sg:city":"St-maurice",
    "sg:orig_category":"Sonstiges Versicherungsgewerbe",
    "sg:phone":"+41 24 485 35 50",
    "sg:postcode":"1890",
    "sg:province":"Valais",
    "wof:name":"Esposito Franco",
    "wof:placetype":"venue"
},
  "geometry": {"coordinates":[7.0044598579,46.2167739868],"type":"Point"}
}