{
  "type": "Feature",
  "properties": {
    "iso:country":"CH",
    "sg:address":"Rue Fran\u00e7ois-perr\u00e9ard 4",
    "sg:city":"Ch\u00eane-bourg",
    "sg:classifiers":[
        {
            "category":"Transit Center",
            "subcategory":"Freight",
            "type":"Transportation"
        }
    ],
    "sg:phone":"+41 22 348 11 77",
    "sg:postcode":"1225",
    "sg:province":"Gen\u00e8ve",
    "sg:tags":[
        "necktie"
    ],
    "wof:name":"Anthime Mouley S.a.",
    "wof:placetype":"venue"
},
  "geometry": {"coordinates":[6.197026,46.195248],"type":"Point"}
}