{
  "type": "Feature",
  "properties": {
    "addr:full":"Rue De La Prulay 30 Meyrin Gen\u00e8ve 1217",
    "addr:housenumber":"30",
    "addr:postcode":"1217",
    "addr:street":"Rue De La Prulay",
    "iso:country":"CH",
    "sg:address":"Rue De La Prulay 30",
    "sg:city":"Meyrin",
    "sg:orig_category":"Bauspenglerei Gartenbau",
    "sg:phone":"+41 56 483 35 35",
    "sg:postcode":"1217",
    "sg:province":"Gen\u00e8ve",
    "wof:name":"Schoop + Co. Ag Bauspenglerei, Gartenbau",
    "wof:placetype":"venue"
},
  "geometry": {"coordinates":[8.29085,47.451553],"type":"Point"}
}