{
  "type": "Feature",
  "properties": {
    "iso:country":"CH",
    "sg:address":"St\u00e4dtle 49",
    "sg:city":"Vaduz",
    "sg:orig_category":"Bibliotheken U Archive Sonstige mit der \u00f6ffentlichen Verwaltung verbundene T\u00e4tigkeiten",
    "sg:postcode":"9490",
    "wof:name":"Landesarchiv",
    "wof:placetype":"venue"
},
  "geometry": {"coordinates":[9.522651,47.137184],"type":"Point"}
}