{
  "type": "Feature",
  "properties": {
    "iso:country":"CH",
    "sg:address":"Wiesenweg 40",
    "sg:city":"Rupperswil",
    "sg:orig_category":"Handelsvermittlung U Grosshandel Herstellung von k\u00e4lte U lufttechnischen Erzeugnissen f\u00fcr gewerblich",
    "sg:phone":"+41 62 897 06 60",
    "sg:postcode":"5102",
    "sg:province":"Aargau",
    "wof:name":"B\u00fcrge & Co Filter Und Lufttechnik",
    "wof:placetype":"venue"
},
  "geometry": {"coordinates":[8.1429290771,47.4085922241],"type":"Point"}
}