{
  "type": "Feature",
  "properties": {
    "iso:country":"CH",
    "sg:address":"Cardinal-journet Rue Du 25 1217 Meyrin Case Postale 8",
    "sg:city":"Meyrin",
    "sg:orig_category":"Werbung",
    "sg:phone":"+41 22 989 10 20",
    "sg:postcode":"1217",
    "sg:province":"Gen\u00e8ve",
    "wof:name":"Soci\u00e9t\u00e9 G\u00e9n\u00e9rale D'affichage, Succursale De Meyrin",
    "wof:placetype":"venue"
},
  "geometry": {"coordinates":[6.082253933,46.2249526978],"type":"Point"}
}