{
  "type": "Feature",
  "properties": {
    "iso:country":"CH",
    "sg:address":"Imbisb\u00fchlstrasse 12",
    "sg:city":"Z\u00fcrich",
    "sg:orig_category":"Sonstige mit der Informatik verbundene T\u00e4tigkeiten",
    "sg:postcode":"8049",
    "sg:province":"Z\u00fcrich",
    "wof:name":"Datadesign, Bosshart S.",
    "wof:placetype":"venue"
},
  "geometry": {"coordinates":[8.4945421219,47.4030265808],"type":"Point"}
}