{
  "type": "Feature",
  "properties": {
    "iso:country":"CH",
    "sg:address":"Spisermarkt Spisergasse 17",
    "sg:city":"St.gallen",
    "sg:classifiers":[
        {
            "category":"Restaurant",
            "type":"Food & Drink"
        }
    ],
    "sg:phone":"+41 56 633 09 55",
    "sg:postcode":"9000",
    "sg:province":"St. Gallen",
    "sg:tags":[
        "tea-rooms",
        "restaurants"
    ],
    "wof:name":"Restaurant Stadtkeller, Schaufelb\u00fchl Christina + Thomas",
    "wof:placetype":"venue"
},
  "geometry": {"coordinates":[9.3737154007,47.4263916016],"type":"Point"}
}