{
  "type": "Feature",
  "properties": {
    "iso:country":"CH",
    "sg:address":"Karlstrasse 3 8610 Uster. Postfach",
    "sg:city":"Uster",
    "sg:orig_category":"Druckweiterverarbeitung",
    "sg:postcode":"8610",
    "sg:province":"Z\u00fcrich",
    "wof:name":"Typefact Egli Christian",
    "wof:placetype":"venue"
},
  "geometry": {"coordinates":[8.7201213837,47.352394104],"type":"Point"}
}