{
  "type": "Feature",
  "properties": {
    "iso:country":"CH",
    "sg:address":"Brunaustrasse 167",
    "sg:city":"Fahrweid",
    "sg:orig_category":"Einbau von Schreinerwaren Elektroinstallation",
    "sg:phone":"+41 79 412 93 11",
    "sg:postcode":"8951",
    "sg:province":"Z\u00fcrich",
    "wof:name":"Rnb Baumontagen, Neeracher Rolf",
    "wof:placetype":"venue"
},
  "geometry": {"coordinates":[8.4187507629,47.411655426],"type":"Point"}
}