{
  "type": "Feature",
  "properties": {
    "addr:full":"Achslenstrasse 15 St. Gallen St. Gallen 9016",
    "addr:housenumber":"15",
    "addr:postcode":"9016",
    "addr:street":"Achslenstrasse;Gallen",
    "iso:country":"CH",
    "sg:address":"Achslenstrasse 15",
    "sg:city":"St. Gallen",
    "sg:orig_category":"Freizeit, Musik",
    "sg:phone":"+41 71 288 34 44",
    "sg:postcode":"9016",
    "sg:province":"St. Gallen",
    "wof:name":"Autoren",
    "wof:placetype":"venue"
},
  "geometry": {"coordinates":[9.412686,47.432083],"type":"Point"}
}