{
  "type": "Feature",
  "properties": {
    "iso:country":"CH",
    "sg:address":"Marais Chemin Des 4",
    "sg:city":"Crans-pr\u00e8s-c\u00e9ligny",
    "sg:orig_category":"Sonstige mit der Informatik verbundene T\u00e4tigkeiten",
    "sg:phone":"+41 22 362 20 38",
    "sg:postcode":"1299",
    "sg:province":"Vaud",
    "wof:name":"Consulting Bernard",
    "wof:placetype":"venue"
},
  "geometry": {"coordinates":[6.2061100006,46.3593864441],"type":"Point"}
}