{
  "type": "Feature",
  "properties": {
    "iso:country":"CH",
    "sg:address":"Pfarrer-k\u00fcnzleweg 11",
    "sg:city":"Zizers",
    "sg:classifiers":[
        {
            "category":"Social Services",
            "subcategory":"Retirement Home",
            "type":"Services"
        }
    ],
    "sg:phone":"+41 81 322 26 62",
    "sg:postcode":"7205",
    "sg:province":"Graubunden",
    "sg:tags":[
        "pflegeheime",
        "u",
        "alters"
    ],
    "wof:name":"Privates Alterswohnheim",
    "wof:placetype":"venue"
},
  "geometry": {"coordinates":[9.567832,46.943169],"type":"Point"}
}