{
  "type": "Feature",
  "properties": {
    "iso:country":"CH",
    "sg:address":"Piazza Giuseppe Motta",
    "sg:city":"Ascona",
    "sg:orig_category":"RESTAURANTS: TEA-ROOMS",
    "sg:phone":"+41 91 791 62 60",
    "sg:postcode":"6612",
    "sg:province":"Ticino",
    "wof:name":"Wagner Riccardo",
    "wof:placetype":"venue"
},
  "geometry": {"coordinates":[8.7676649094,46.1544151306],"type":"Point"}
}