{
  "type": "Feature",
  "properties": {
    "iso:country":"CH",
    "sg:address":"3123 Belp. Postfach 153",
    "sg:city":"Belp",
    "sg:orig_category":"Detailhandel mit Waren verschiedener Art, Hauptrichtung Nahrungsmittel",
    "sg:phone":"+41 71 636 11 41",
    "sg:postcode":"3123",
    "sg:province":"Bern",
    "wof:name":"Landi Berg",
    "wof:placetype":"venue"
},
  "geometry": {"coordinates":[9.1662521362,47.5793113708],"type":"Point"}
}