{
  "type": "Feature",
  "properties": {
    "addr:full":"Rue Du Tilleuls 22 Fribourg Fribourg 1700",
    "addr:postcode":"22;1700",
    "addr:street":"Rue Du Tilleuls",
    "iso:country":"CH",
    "sg:address":"Rue Du Tilleuls 22",
    "sg:city":"Fribourg",
    "sg:orig_category":"Detailhandel mit Beleuchtungs U Haushaltsgegenst\u00e4nden Detailhandel mit elektrischen Haushalts, Radio",
    "sg:phone":"+41 26 322 23 22",
    "sg:postcode":"1700",
    "sg:province":"Fribourg",
    "wof:name":"Edouard Aebischer Appareils M\u00e9nagers",
    "wof:placetype":"venue"
},
  "geometry": {"coordinates":[7.153683,46.803745],"type":"Point"}
}