{
  "type": "Feature",
  "properties": {
    "iso:country":"CH",
    "sg:address":"Rathaus Platz",
    "sg:city":"Klosters",
    "sg:orig_category":"Forst\u00e4mter",
    "sg:phone":"+41 81 422 39 30",
    "sg:postcode":"7250",
    "sg:province":"Graubunden",
    "wof:name":"Kreisforstamt 19",
    "wof:placetype":"venue"
},
  "geometry": {"coordinates":[9.8837299347,46.86901474],"type":"Point"}
}