{
  "type": "Feature",
  "properties": {
    "iso:country":"CH",
    "sg:address":"Via Medere 19",
    "sg:city":"Ascona",
    "sg:orig_category":"Malerei",
    "sg:phone":"+41 55 282 17 83",
    "sg:postcode":"6612",
    "sg:province":"Ticino",
    "wof:name":"Guido G\u00fcbeli Malerwerkst\u00e4tte",
    "wof:placetype":"venue"
},
  "geometry": {"coordinates":[8.9138555527,47.2421379089],"type":"Point"}
}