{
  "type": "Feature",
  "properties": {
    "iso:country":"CH",
    "sg:address":"Rodari Via 22",
    "sg:city":"Maroggia",
    "sg:orig_category":"Fachdetailhandel in Verkaufsr\u00e4umen",
    "sg:phone":"+41 71 333 34 43",
    "sg:postcode":"6817",
    "sg:province":"Ticino",
    "wof:name":"C. Frick - Bike-wear",
    "wof:placetype":"venue"
},
  "geometry": {"coordinates":[9.3906106949,47.3914108276],"type":"Point"}
}