{
  "type": "Feature",
  "properties": {
    "iso:country":"CH",
    "sg:address":"Rohrerstrasse 33",
    "sg:city":"Aarau",
    "sg:classifiers":[
        {
            "category":"Food & Beverages",
            "subcategory":"Fruits & Vegetables",
            "type":"Retail Goods"
        }
    ],
    "sg:phone":"+41 62 832 77 88",
    "sg:postcode":"5000",
    "sg:province":"Aargau",
    "sg:tags":[
        "gingerbread",
        "biscuit"
    ],
    "wof:name":"Berner Ag",
    "wof:placetype":"venue"
},
  "geometry": {"coordinates":[8.0581359863,47.3950233459],"type":"Point"}
}