{
  "type": "Feature",
  "properties": {
    "iso:country":"CH",
    "sg:address":"Les Fermes",
    "sg:city":"Cordast",
    "sg:orig_category":"Allgemeiner Hoch U Tiefbau Herstellung von Metallkonstruktionen",
    "sg:phone":"+41 26 684 27 13",
    "sg:postcode":"1792",
    "sg:province":"Fribourg",
    "wof:name":"Giuseppe Pugliese Ag Rohrleitungs-& Metallbau",
    "wof:placetype":"venue"
},
  "geometry": {"coordinates":[7.150705,46.87278],"type":"Point"}
}