{
  "type": "Feature",
  "properties": {
    "iso:country":"CH",
    "sg:address":"Rue De La Cr\u00eat 8",
    "sg:city":"Bassecourt",
    "sg:orig_category":"Bauschreinerei",
    "sg:phone":"+41 32 426 50 44",
    "sg:postcode":"2854",
    "sg:province":"Jura",
    "wof:name":"Denis Maitre Menuiserie",
    "wof:placetype":"venue"
},
  "geometry": {"coordinates":[7.2425,47.338051],"type":"Point"}
}