{
  "type": "Feature",
  "properties": {
    "iso:country":"CH",
    "sg:address":"Wangenstrasse 5",
    "sg:city":"D\u00fcbendorf",
    "sg:orig_category":"Herstellung von Teilen U Zubeh\u00f6r f\u00fcr Automobile",
    "sg:phone":"+41 41 720 26 26",
    "sg:postcode":"8600",
    "sg:province":"Z\u00fcrich",
    "wof:name":"Amatrade Diethelm R.",
    "wof:placetype":"venue"
},
  "geometry": {"coordinates":[8.509013176,47.147693634],"type":"Point"}
}