{
  "type": "Feature",
  "properties": {
    "iso:country":"CH",
    "sg:address":"Limmatstrasse 179 8005 Z\u00fcrich. Postfach",
    "sg:city":"Z\u00fcrich",
    "sg:orig_category":"Herstellung von sonstigen Metallwaren",
    "sg:postcode":"8001",
    "sg:province":"Z\u00fcrich",
    "wof:name":"Permit, Eugenie Peier Dichtungen, Gummiplatten, Kunststoffe U. Schl\u00e4uche; Handel Usw.",
    "wof:placetype":"venue"
},
  "geometry": {"coordinates":[8.5296888351,47.3858795166],"type":"Point"}
}