{
  "type": "Feature",
  "properties": {
    "iso:country":"CH",
    "sg:address":"Rathausplatz 1",
    "sg:city":"Glarus",
    "sg:orig_category":"Fahrschulen, Flugschulen",
    "sg:phone":"+41 79 419 60 89",
    "sg:postcode":"8750",
    "sg:province":"Glarus",
    "wof:name":"Tin Sedelberger Autofahrschule",
    "wof:placetype":"venue"
},
  "geometry": {"coordinates":[9.0683555603,47.0400276184],"type":"Point"}
}