{
  "type": "Feature",
  "properties": {
    "iso:country":"CH",
    "sg:address":"D\u00fcrrenbergstrasse 75",
    "sg:city":"Trimbach",
    "sg:orig_category":"Detailhandel mit Beleuchtungs U Haushaltsgegenst\u00e4nden Innendekorationsateliers",
    "sg:phone":"+41 62 293 51 38",
    "sg:postcode":"4632",
    "sg:province":"Solothurn",
    "wof:name":"Margrit Schenker Vorh\u00e4nge",
    "wof:placetype":"venue"
},
  "geometry": {"coordinates":[7.896502,47.368042],"type":"Point"}
}