{
  "type": "Feature",
  "properties": {
    "iso:country":"CH",
    "sg:address":"Zentralstrasse 7",
    "sg:city":"Uster",
    "sg:orig_category":"Werbegrafikateliers",
    "sg:phone":"+41 19304618",
    "sg:postcode":"8610",
    "sg:province":"Z\u00fcrich",
    "wof:name":"Robert Hess Grafisches Atelier",
    "wof:placetype":"venue"
},
  "geometry": {"coordinates":[8.7182188034,47.347618103],"type":"Point"}
}