{
  "type": "Feature",
  "properties": {
    "iso:country":"CH",
    "sg:address":"Poste Chemin De La 10 1027 Lonay. Postfach",
    "sg:city":"Lonay",
    "sg:orig_category":"K\u00fcnstlerische U schriftstellerische T\u00e4tigkeiten U Darbietungen",
    "sg:postcode":"1027",
    "sg:province":"Vaud",
    "wof:name":"Traktor Schalllabor Gmbh Musik; Produktion. Tontr\u00e4ger; Herstellung, Handel. Kulturelle Anl\u00e4sse Usw",
    "wof:placetype":"venue"
},
  "geometry": {"coordinates":[8.3504076004,47.3492698669],"type":"Point"}
}