{
  "type": "Feature",
  "properties": {
    "iso:country":"CH",
    "sg:address":"Dorfstrasse 36",
    "sg:city":"Lupfig",
    "sg:orig_category":"Fahrschulen, Flugschulen",
    "sg:phone":"+41 79 221 20 60",
    "sg:postcode":"5242",
    "sg:province":"Aargau",
    "wof:name":"Hansruedi K\u00f6chli Autofahrschule",
    "wof:placetype":"venue"
},
  "geometry": {"coordinates":[8.2008924484,47.4408302307],"type":"Point"}
}