{
  "type": "Feature",
  "properties": {
    "iso:country":"CH",
    "sg:address":"Feldstrasse 26",
    "sg:city":"Thun",
    "sg:orig_category":"Herstellung von Arbeits U Berufsbekleidung",
    "sg:postcode":"3604",
    "sg:province":"Bern",
    "wof:name":"Werner Frank",
    "wof:placetype":"venue"
},
  "geometry": {"coordinates":[7.6214871407,46.7419509888],"type":"Point"}
}