{
  "type": "Feature",
  "properties": {
    "iso:country":"CH",
    "sg:address":"Alpenstrasse 14",
    "sg:city":"Zug",
    "sg:orig_category":"Sonstige Finanzierungsinstitutionen",
    "sg:phone":"+41 41 710 44 05",
    "sg:postcode":"6300",
    "sg:province":"Zug",
    "wof:name":"5e Holding Ag",
    "wof:placetype":"venue"
},
  "geometry": {"coordinates":[8.5150566101,47.1726837158],"type":"Point"}
}