{
  "type": "Feature",
  "properties": {
    "iso:country":"CH",
    "sg:address":"Av. Mon-loisir 14",
    "sg:city":"Lausanne",
    "sg:classifiers":[
        {
            "category":"Communications",
            "subcategory":"Film & Video Production",
            "type":"Services"
        }
    ],
    "sg:phone":"+41 21 616 66 92",
    "sg:postcode":"1000",
    "sg:province":"Vaud",
    "sg:tags":[
        "videofilmherstellung",
        "u"
    ],
    "wof:name":"Vid\u00e9ovision, Wicky Jean",
    "wof:placetype":"venue"
},
  "geometry": {"coordinates":[6.631333828,46.5115242004],"type":"Point"}
}