{
  "type": "Feature",
  "properties": {
    "iso:country":"CH",
    "sg:address":"Bahnhofstrasse 17",
    "sg:city":"M\u00f6rschwil",
    "sg:orig_category":"Unclassifiable Establishments",
    "sg:postcode":"9402",
    "sg:province":"St. Gallen",
    "wof:name":"Riccarda Fischer Top-o-lino",
    "wof:placetype":"venue"
},
  "geometry": {"coordinates":[9.4199743271,47.4697341919],"type":"Point"}
}