{
  "type": "Feature",
  "properties": {
    "iso:country":"CH",
    "sg:address":"Galeria Roseg",
    "sg:city":"Pontresina",
    "sg:orig_category":"Detailhandel mit M\u00f6beln U Haushaltsgegenst\u00e4nden",
    "sg:postcode":"7504",
    "sg:province":"Graubunden",
    "wof:name":"T & P Shop Gmbh",
    "wof:placetype":"venue"
},
  "geometry": {"coordinates":[9.8987827301,46.4975738525],"type":"Point"}
}