{
  "type": "Feature",
  "properties": {
    "iso:country":"CH",
    "sg:address":"Zaunweg 6",
    "sg:city":"Biel/bienne",
    "sg:classifiers":[
        {
            "category":"Utilities",
            "subcategory":"Mobile Phone",
            "type":"Services"
        }
    ],
    "sg:phone":"+41 32 322 34 62",
    "sg:postcode":"2502",
    "sg:province":"Bern",
    "sg:tags":[
        "battery",
        "operated",
        "clock"
    ],
    "wof:name":"Montres Antima Sa",
    "wof:placetype":"venue"
},
  "geometry": {"coordinates":[7.263052,47.146187],"type":"Point"}
}