{
  "type": "Feature",
  "properties": {
    "addr:full":"Bahnhofstrasse Staldenried Valais 3933",
    "addr:postcode":"3933",
    "addr:street":"Bahnhofstrasse",
    "iso:country":"CH",
    "sg:address":"Bahnhofstrasse",
    "sg:city":"Staldenried",
    "sg:orig_category":"Darlehenskassen U Raiffeisenbanken",
    "sg:phone":"+41 27 953 68 10",
    "sg:postcode":"3933",
    "sg:province":"Valais",
    "wof:name":"Raiffeisenbank Vispertal",
    "wof:placetype":"venue"
},
  "geometry": {"coordinates":[7.885328,46.229862],"type":"Point"}
}