{
  "type": "Feature",
  "properties": {
    "addr:full":"Inzenberg 1043. 9113 Degersheim. Postfach Wolfertswil St. Gallen 9116",
    "addr:housenumber":"1043",
    "addr:postcode":"9113 degersheim. postfach;9116",
    "addr:street":"Inzenberg",
    "iso:country":"CH",
    "sg:address":"Inzenberg 1043. 9113 Degersheim. Postfach",
    "sg:city":"Wolfertswil",
    "sg:orig_category":"Allgemeiner Hoch U Tiefbau",
    "sg:postcode":"9116",
    "sg:province":"St. Gallen",
    "wof:name":"Andreas Hug, Leitungsbau",
    "wof:placetype":"venue"
},
  "geometry": {"coordinates":[9.200012,47.373943],"type":"Point"}
}