{
  "type": "Feature",
  "properties": {
    "iso:country":"CH",
    "sg:address":"Fola Via 6963 Pregassona. Postfach",
    "sg:city":"Pregassona",
    "sg:orig_category":"Vermietung U Verpachtung von eigenen Immobilien",
    "sg:postcode":"6963",
    "sg:province":"Ticino",
    "wof:name":"Siro A Sa Immobili Ecc",
    "wof:placetype":"venue"
},
  "geometry": {"coordinates":[8.9727811813,46.0194549561],"type":"Point"}
}