{
  "type": "Feature",
  "properties": {
    "iso:country":"CH",
    "sg:address":"Route Du Bois-des-fr\u00e8res 2 1214 Vernier. Postfach",
    "sg:city":"Vernier",
    "sg:orig_category":"Handel mit Motorr\u00e4dern, Teilen U Zubeh\u00f6r Instandhaltung U Reparatur von Motorr\u00e4dern",
    "sg:phone":"+41 61 753 86 81",
    "sg:postcode":"1214",
    "sg:province":"Gen\u00e8ve",
    "wof:name":"Cycles-b\u00f6rse Schmid",
    "wof:placetype":"venue"
},
  "geometry": {"coordinates":[7.5982618332,47.4681739807],"type":"Point"}
}