{
  "type": "Feature",
  "properties": {
    "iso:country":"CH",
    "sg:address":"Santelstrasse 4",
    "sg:city":"Egerkingen",
    "sg:orig_category":"Detailhandel mit M\u00f6beln U Haushaltsgegenst\u00e4nden Grosshandel mit M\u00f6beln, Wohnbedarf, Teppichen U Bode",
    "sg:phone":"+41 62 398 15 22",
    "sg:postcode":"4622",
    "sg:province":"Solothurn",
    "wof:name":"Tesil Ag Egerkingen",
    "wof:placetype":"venue"
},
  "geometry": {"coordinates":[7.8039040565,47.3249702454],"type":"Point"}
}