{
  "type": "Feature",
  "properties": {
    "iso:country":"CH",
    "sg:address":"Avenue Du Grey 34",
    "sg:city":"Lausanne",
    "sg:orig_category":"Massagestudios",
    "sg:phone":"+41 21 646 59 38",
    "sg:postcode":"1004",
    "sg:province":"Vaud",
    "wof:name":"Annamaria Abonyi Massage De Sant\u00e9",
    "wof:placetype":"venue"
},
  "geometry": {"coordinates":[6.6208610535,46.5333061218],"type":"Point"}
}