{
  "type": "Feature",
  "properties": {
    "iso:country":"CH",
    "sg:address":"Feldstrasse",
    "sg:city":"Altishofen",
    "sg:orig_category":"Grosshandel mit lebenden Tieren",
    "sg:phone":"+41 41 870 14 70",
    "sg:postcode":"6246",
    "sg:province":"Luzern",
    "wof:name":"Ernst Gisler Kleinviehhandel",
    "wof:placetype":"venue"
},
  "geometry": {"coordinates":[8.6731185913,46.8779335022],"type":"Point"}
}