{
  "type": "Feature",
  "properties": {
    "iso:country":"CH",
    "sg:address":"Chemin De La Fontanne 5",
    "sg:city":"Pr\u00e9verenges",
    "sg:orig_category":"Allgemeiner Hoch U Tiefbau",
    "sg:postcode":"1028",
    "sg:province":"Vaud",
    "wof:name":"Ectavd Entretien Et Contr\u00f4le Technique Abris Sa",
    "wof:placetype":"venue"
},
  "geometry": {"coordinates":[6.529604,46.520908],"type":"Point"}
}