{
  "type": "Feature",
  "properties": {
    "iso:country":"CH",
    "sg:address":"Sch\u00f6negg",
    "sg:city":"Mols",
    "sg:orig_category":"Stukkateurgewerbe, Gipserei U Verputzerei",
    "sg:phone":"+41 79 355 89 63",
    "sg:postcode":"8885",
    "sg:province":"St. Gallen",
    "wof:name":"Hobi Peter",
    "wof:placetype":"venue"
},
  "geometry": {"coordinates":[9.2764253616,47.1129493713],"type":"Point"}
}