{
  "type": "Feature",
  "properties": {
    "iso:country":"CH",
    "sg:address":"Stauffacherstrasse 5",
    "sg:city":"Bern",
    "sg:orig_category":"Elektroinstallation",
    "sg:postcode":"3014",
    "sg:province":"Bern",
    "wof:name":"Alfred Kr\u00e4henb\u00fchl Elektro-installationen",
    "wof:placetype":"venue"
},
  "geometry": {"coordinates":[7.4546489716,46.95936203],"type":"Point"}
}