{
  "type": "Feature",
  "properties": {
    "iso:country":"CH",
    "sg:address":"Graben 5 6300 Zug. Postfach",
    "sg:city":"Zug",
    "sg:orig_category":"Werbung",
    "sg:phone":"+41 31 951 85 25",
    "sg:postcode":"6300",
    "sg:province":"Zug",
    "wof:name":"Pr Beratung Lombard B\u00e9atrice",
    "wof:placetype":"venue"
},
  "geometry": {"coordinates":[7.4750118256,46.9327735901],"type":"Point"}
}