{
  "type": "Feature",
  "properties": {
    "iso:country":"CH",
    "sg:address":"Cantonale Via",
    "sg:city":"Morcote",
    "sg:orig_category":"Detailhandel mit Waren verschiedener Art, Hauptrichtung Nahrungsmittel",
    "sg:postcode":"6922",
    "sg:province":"Ticino",
    "wof:name":"Ulrich Peter Bruetsch",
    "wof:placetype":"venue"
},
  "geometry": {"coordinates":[8.9184484482,45.9235954285],"type":"Point"}
}