{
  "type": "Feature",
  "properties": {
    "iso:country":"CH",
    "sg:address":"4629",
    "sg:city":"Fulenbach",
    "sg:orig_category":"Sportvereine Sch\u00fctzen",
    "sg:phone":"+41 55 244 13 68",
    "sg:postcode":"4629",
    "sg:province":"Solothurn",
    "wof:name":"Sch\u00fctzengesellschaft",
    "wof:placetype":"venue"
},
  "geometry": {"coordinates":[7.8959298134,47.3936080933],"type":"Point"}
}