{
  "type": "Feature",
  "properties": {
    "iso:country":"CH",
    "sg:address":"Siewerdtstrasse 89",
    "sg:city":"Z\u00fcrich",
    "sg:orig_category":"Sonstige Hilfsdienste des Kultur U Unterhaltungswesens",
    "sg:phone":"+41 13124179",
    "sg:postcode":"8050",
    "sg:province":"Z\u00fcrich",
    "wof:name":"Renate Kramer Internat.k\u00fcnstleragentur",
    "wof:placetype":"venue"
},
  "geometry": {"coordinates":[8.5563230515,47.4123840332],"type":"Point"}
}