{
  "type": "Feature",
  "properties": {
    "iso:country":"CH",
    "sg:address":"Bruggwaldpark 23",
    "sg:city":"Wittenbach",
    "sg:orig_category":"Finanzierungsinstitutionen",
    "sg:postcode":"9303",
    "wof:name":"Hopinvest Gmbh",
    "wof:placetype":"venue"
},
  "geometry": {"coordinates":[9.3960475922,47.4478645325],"type":"Point"}
}