{
  "type": "Feature",
  "properties": {
    "addr:full":"Route Cantonale Bouveret Valais 1897",
    "addr:postcode":"1897",
    "addr:street":"Route Cantonale",
    "iso:country":"CH",
    "sg:address":"Route Cantonale",
    "sg:city":"Bouveret",
    "sg:orig_category":"Arztpraxen",
    "sg:phone":"+41 24 481 34 34",
    "sg:postcode":"1897",
    "sg:province":"Valais",
    "wof:name":"Dr M\u00e9d. Dinh Lam Toan M\u00e9decin G\u00e9n\u00e9raliste",
    "wof:placetype":"venue"
},
  "geometry": {"coordinates":[6.854365,46.383381],"type":"Point"}
}