{
  "type": "Feature",
  "properties": {
    "iso:country":"CH",
    "sg:address":"Rue Du Valentin 128",
    "sg:city":"Yverdon-les-bains",
    "sg:orig_category":"Detailhandel mit Radio U Fernsehger\u00e4ten Detailhandel mit fotografischen Artikeln",
    "sg:phone":"+41 24 425 90 63",
    "sg:postcode":"1400",
    "sg:province":"Vaud",
    "wof:name":"Ernest & Fernande Ryter Film-vid\u00e9o-photo",
    "wof:placetype":"venue"
},
  "geometry": {"coordinates":[6.6430401802,46.7703590393],"type":"Point"}
}