{
  "type": "Feature",
  "properties": {
    "iso:country":"CH",
    "sg:address":"1041",
    "sg:city":"Poliez-pittet",
    "sg:orig_category":"Sportvereine Sch\u00fctzen",
    "sg:postcode":"1041",
    "sg:province":"Vaud",
    "wof:name":"St\u00e9 De Tir Armes De Guerre",
    "wof:placetype":"venue"
},
  "geometry": {"coordinates":[6.6836800575,46.6280097961],"type":"Point"}
}