{
  "type": "Feature",
  "properties": {
    "iso:country":"CH",
    "sg:address":"Archeng\u00e4ssli 3 8304 Wallisellen. Postfach",
    "sg:city":"Wallisellen",
    "sg:orig_category":"Unternehmensberatung",
    "sg:postcode":"8304",
    "sg:province":"Z\u00fcrich",
    "wof:name":"Moser Roland Wirtschafts Und Investmentberatung Wirtschafts, Kapital Und Steuerberatung Usw",
    "wof:placetype":"venue"
},
  "geometry": {"coordinates":[8.5894117355,47.4139823914],"type":"Point"}
}