{
  "type": "Feature",
  "properties": {
    "iso:country":"CH",
    "sg:address":"3128",
    "sg:city":"R\u00fcmligen",
    "sg:orig_category":"Allgemeiner Hoch U Tiefbau Allgemeiner Hochbau",
    "sg:phone":"+41 71 761 40 41",
    "sg:postcode":"3128",
    "sg:province":"Bern",
    "wof:name":"B\u00fcchel E. Ag",
    "wof:placetype":"venue"
},
  "geometry": {"coordinates":[9.569581,47.326321],"type":"Point"}
}