{
  "type": "Feature",
  "properties": {
    "iso:country":"CH",
    "sg:address":"Gemmistrasse 3",
    "sg:city":"Thun",
    "sg:orig_category":"Detailhandel Handel mit Motorr\u00e4dern, Teilen U Zubeh\u00f6r Instandhaltung U Reparatur von Motorr\u00e4dern Rep",
    "sg:phone":"+41 33 335 14 15",
    "sg:postcode":"3604",
    "sg:province":"Bern",
    "wof:name":"Hofmann & Co Moto-center Thun",
    "wof:placetype":"venue"
},
  "geometry": {"coordinates":[7.6260051727,46.7385444641],"type":"Point"}
}