{
  "type": "Feature",
  "properties": {
    "iso:country":"CH",
    "sg:address":"Via San Michele 39",
    "sg:city":"Caslano",
    "sg:orig_category":"Unclassifiable Establishments",
    "sg:phone":"+41 91 600 92 77",
    "sg:postcode":"6987",
    "sg:province":"Ticino",
    "wof:name":"Teficon Sa",
    "wof:placetype":"venue"
},
  "geometry": {"coordinates":[8.8723306656,45.9705581665],"type":"Point"}
}