{
  "type": "Feature",
  "properties": {
    "iso:country":"CH",
    "sg:address":"Lindenstrasse 26",
    "sg:city":"Z\u00fcrich",
    "sg:orig_category":"Informatikdienste Softwareentwicklung U beratung",
    "sg:phone":"+41 61 425 95 25",
    "sg:postcode":"8008",
    "sg:province":"Z\u00fcrich",
    "wof:name":"Synlogic Ag, Niederlassung Z\u00fcrich Informatik-services - Beratung - Projekte",
    "wof:placetype":"venue"
},
  "geometry": {"coordinates":[8.5520620346,47.3576087952],"type":"Point"}
}