{
  "type": "Feature",
  "properties": {
    "iso:country":"CH",
    "sg:address":"Sensenau 10",
    "sg:city":"Ueberstorf",
    "sg:classifiers":[
        {
            "category":"Travel",
            "subcategory":"Bed & Breakfast",
            "type":"Entertainment"
        }
    ],
    "sg:phone":"+41 31 889 02 79",
    "sg:postcode":"3182",
    "sg:province":"Fribourg",
    "sg:tags":[
        "ladder"
    ],
    "wof:name":"Walter Kaufmann Leichtmetall-leitern",
    "wof:placetype":"venue"
},
  "geometry": {"coordinates":[7.3517827988,46.8816452026],"type":"Point"}
}