{
  "type": "Feature",
  "properties": {
    "iso:country":"CH",
    "sg:address":"Ringstrasse 9",
    "sg:city":"Allschwil",
    "sg:orig_category":"Druck ohne Zeitungsdruck",
    "sg:phone":"+41 61 483 80 80",
    "sg:postcode":"4123",
    "sg:province":"Basel-Landschaft",
    "wof:name":"Innoprint Ag",
    "wof:placetype":"venue"
},
  "geometry": {"coordinates":[7.5439038277,47.5578765869],"type":"Point"}
}