{
  "type": "Feature",
  "properties": {
    "iso:country":"CH",
    "sg:address":"Le Verney A",
    "sg:city":"Puidoux",
    "sg:orig_category":"Elektroinstallation Herstellung von elektronischen Bauelementen",
    "sg:phone":"+41 21 946 56 46",
    "sg:postcode":"1070",
    "sg:province":"Vaud",
    "wof:name":"Ramtec S\u00e0rl",
    "wof:placetype":"venue"
},
  "geometry": {"coordinates":[6.7685251236,46.4927902222],"type":"Point"}
}