{
  "type": "Feature",
  "properties": {
    "iso:country":"CH",
    "sg:address":"Dattikonstrasse 5",
    "sg:city":"Uznach",
    "sg:orig_category":"Interessenvertretungen",
    "sg:postcode":"8730",
    "sg:province":"St. Gallen",
    "wof:name":"Boner Stiftung F\u00fcr Kunst Und Kultur",
    "wof:placetype":"venue"
},
  "geometry": {"coordinates":[9.8199300766,46.7944068909],"type":"Point"}
}