{
  "type": "Feature",
  "properties": {
    "iso:country":"CH",
    "sg:address":"Rue Firmin-massot 4 1200 Genf. Postfach",
    "sg:city":"Gen\u00e8ve",
    "sg:orig_category":"Non-Classified Establishments",
    "sg:postcode":"1206",
    "sg:province":"Gen\u00e8ve",
    "wof:name":"Si Les Villas B",
    "wof:placetype":"venue"
},
  "geometry": {"coordinates":[6.1512022018,46.1962814331],"type":"Point"}
}