{
  "type": "Feature",
  "properties": {
    "iso:country":"CH",
    "sg:address":"Joos\u00e4ckerstrasse 12",
    "sg:city":"Spreitenbach",
    "sg:orig_category":"Detailhandel mit M\u00f6beln U Haushaltsgegenst\u00e4nden",
    "sg:phone":"+41 17155042",
    "sg:postcode":"8957",
    "sg:province":"Aargau",
    "wof:name":"Pandora Potnik-scotoni Ariella",
    "wof:placetype":"venue"
},
  "geometry": {"coordinates":[8.5521774292,47.3189849854],"type":"Point"}
}