{
  "type": "Feature",
  "properties": {
    "iso:country":"CH",
    "sg:address":"Rue Des Corbaz 11",
    "sg:city":"Belmont-lausanne",
    "sg:orig_category":"Handelsvermittlung U Grosshandel Sonstiger Grosshandel",
    "sg:phone":"+41 19321439",
    "sg:postcode":"1092",
    "sg:province":"Vaud",
    "wof:name":"Cd Handels Ag",
    "wof:placetype":"venue"
},
  "geometry": {"coordinates":[8.7896757126,47.3170089722],"type":"Point"}
}