{
  "type": "Feature",
  "properties": {
    "iso:country":"CH",
    "sg:address":"Tschingeley 28",
    "sg:city":"Unterseen",
    "sg:orig_category":"Hoch U Tiefbau",
    "sg:phone":"+41 79 219 56 71",
    "sg:postcode":"3800",
    "sg:province":"Bern",
    "wof:name":"Peter Frutiger Bauarbeiten & Akkordbau",
    "wof:placetype":"venue"
},
  "geometry": {"coordinates":[7.846268177,46.6784744263],"type":"Point"}
}