{
  "type": "Feature",
  "properties": {
    "iso:country":"CH",
    "sg:address":"Rte Jean-jacques Rigaud 24",
    "sg:city":"Ch\u00eane-bougeries",
    "sg:orig_category":"Sanit\u00e4r, Heizungs U L\u00fcftungsinstallation",
    "sg:postcode":"1224",
    "sg:province":"Gen\u00e8ve",
    "wof:name":"Meyer G\u00e9rald",
    "wof:placetype":"venue"
},
  "geometry": {"coordinates":[6.1933250427,46.2051124573],"type":"Point"}
}