{
  "type": "Feature",
  "properties": {
    "iso:country":"CH",
    "sg:address":"Rue De Gen\u00e8ve 6 1225 Ch\u00eane-bourg Case Postale 260",
    "sg:city":"Ch\u00eane-bourg",
    "sg:orig_category":"Bauschreinerei Innenausbau",
    "sg:phone":"+41 22 348 11 60",
    "sg:postcode":"1225",
    "sg:province":"Gen\u00e8ve",
    "wof:name":"Margairaz & Fils Sa",
    "wof:placetype":"venue"
},
  "geometry": {"coordinates":[6.192977,46.195023],"type":"Point"}
}