{
  "type": "Feature",
  "properties": {
    "iso:country":"CH",
    "sg:address":"Rietwies",
    "sg:city":"Mattwil",
    "sg:orig_category":"Haltung von Schweinen",
    "sg:phone":"+41 71 648 10 16",
    "sg:postcode":"8585",
    "sg:province":"Thurgau",
    "wof:name":"Ludwig Schwizer Schweinezucht",
    "wof:placetype":"venue"
},
  "geometry": {"coordinates":[9.2099342346,47.5787010193],"type":"Point"}
}