{
  "type": "Feature",
  "properties": {
    "iso:country":"CH",
    "sg:address":"F\u00f6rrlibuckstrasse 180",
    "sg:city":"Z\u00fcrich",
    "sg:orig_category":"Aktivit\u00e4ten der Generalunternehmen im Baugewerbe Vermittlung von Immobilien",
    "sg:phone":"+41 31 335 75 44",
    "sg:postcode":"8005",
    "sg:province":"Z\u00fcrich",
    "wof:name":"Losinger Construction Ag Generalunternehmung",
    "wof:placetype":"venue"
},
  "geometry": {"coordinates":[7.454037,46.965439],"type":"Point"}
}