{
  "type": "Feature",
  "properties": {
    "iso:country":"CH",
    "sg:address":"Bubenbergstrasse 10a",
    "sg:city":"Huttwil",
    "sg:orig_category":"Sonstige pers\u00f6nliche Dienstleistungen",
    "sg:phone":"+41 62 962 54 06",
    "sg:postcode":"4950",
    "sg:province":"Bern",
    "wof:name":"Angst, Engineering Und Beratung",
    "wof:placetype":"venue"
},
  "geometry": {"coordinates":[7.8411412239,47.1177635193],"type":"Point"}
}