{
  "type": "Feature",
  "properties": {
    "iso:country":"CH",
    "sg:address":"Lippestrasse 29",
    "sg:city":"Lausen",
    "sg:orig_category":"Informatikdienste Softwareentwicklung U beratung",
    "sg:phone":"+41 61 921 10 52",
    "sg:postcode":"4415",
    "sg:province":"Basel-Landschaft",
    "wof:name":"Etas Informatik Gmbh",
    "wof:placetype":"venue"
},
  "geometry": {"coordinates":[7.7628121376,47.4768867493],"type":"Point"}
}