{
  "type": "Feature",
  "properties": {
    "iso:country":"CH",
    "sg:address":"Halteliweg 3 6430 Schwyz. Postfach 425",
    "sg:city":"Schwyz",
    "sg:orig_category":"Sportvereine Ski",
    "sg:phone":"+41 41 811 64 33",
    "sg:postcode":"6431",
    "sg:province":"Schwyz",
    "wof:name":"Skiclub Ibach",
    "wof:placetype":"venue"
},
  "geometry": {"coordinates":[8.6583824158,47.0256881714],"type":"Point"}
}