{
  "type": "Feature",
  "properties": {
    "iso:country":"CH",
    "sg:address":"Obachstrasse 18",
    "sg:city":"Solothurn",
    "sg:orig_category":"Unclassifiable Establishments",
    "sg:postcode":"4500",
    "sg:province":"Solothurn",
    "wof:name":"Brigit Rust Ern\u00e4hrungsberatung",
    "wof:placetype":"venue"
},
  "geometry": {"coordinates":[7.5314512253,47.2058906555],"type":"Point"}
}