{
  "type": "Feature",
  "properties": {
    "iso:country":"CH",
    "sg:address":"Bremgartnerstrasse 78",
    "sg:city":"Dietikon",
    "sg:orig_category":"Aktivit\u00e4ten der Generalunternehmen im Baugewerbe Architektur U Ingenieurb\u00fcros",
    "sg:phone":"+41 17400905",
    "sg:postcode":"8953",
    "sg:province":"Z\u00fcrich",
    "wof:name":"Architektur Thiessen Gmbh Planungs, Architekturauftr\u00e4ge; Ausf\u00fchrung, Bearbeitung Usw",
    "wof:placetype":"venue"
},
  "geometry": {"coordinates":[8.398974,47.39817],"type":"Point"}
}