{
  "type": "Feature",
  "properties": {
    "iso:country":"CH",
    "sg:address":"Bachteleweg 27",
    "sg:city":"Jegenstorf",
    "sg:orig_category":"Allgemeiner Hoch U Tiefbau",
    "sg:phone":"+41 71 222 96 84",
    "sg:postcode":"3303",
    "sg:province":"Bern",
    "wof:name":"Jaggi & Jaggi",
    "wof:placetype":"venue"
},
  "geometry": {"coordinates":[9.362168,47.386242],"type":"Point"}
}