{
  "type": "Feature",
  "properties": {
    "iso:country":"CH",
    "sg:address":"Kirchweg 16 3902 Glis. Postfach 71",
    "sg:city":"Glis",
    "sg:orig_category":"G\u00fcterbef\u00f6rderung im Strassenverkehr Vermietung von Baumaschinen U ger\u00e4ten mit Bedienungspersonal",
    "sg:phone":"+41 27 923 23 55",
    "sg:postcode":"3902",
    "sg:province":"Valais",
    "wof:name":"Clausen Kran Ag Spezialtransporte",
    "wof:placetype":"venue"
},
  "geometry": {"coordinates":[7.9859671593,46.3130455017],"type":"Point"}
}