{
  "type": "Feature",
  "properties": {
    "iso:country":"CH",
    "sg:address":"Breitlandstrasse 5",
    "sg:city":"Geroldswil",
    "sg:orig_category":"Sonstige Aktivit\u00e4ten der nicht-\u00e4rztlichen Medizinalberufe",
    "sg:phone":"+41 71 333 29 53",
    "sg:postcode":"8954",
    "sg:province":"Z\u00fcrich",
    "wof:name":"Verena Isler Tobler Atemtherapie",
    "wof:placetype":"venue"
},
  "geometry": {"coordinates":[9.3621683121,47.3862419128],"type":"Point"}
}