{
  "type": "Feature",
  "properties": {
    "iso:country":"CH",
    "sg:address":"Route De Chamblioux 38",
    "sg:city":"Granges-paccot",
    "sg:classifiers":[
        {
            "category":"Insurance",
            "subcategory":"Insurance Agent",
            "type":"Services"
        }
    ],
    "sg:phone":"+41 79 230 69 20",
    "sg:postcode":"1763",
    "sg:province":"Fribourg",
    "sg:tags":[
        "versicherungsagenturen",
        "-broker"
    ],
    "wof:name":"Philippe Kapsopoulos Assurances B\u00e2loise",
    "wof:placetype":"venue"
},
  "geometry": {"coordinates":[7.1400799751,46.8153991699],"type":"Point"}
}