{
  "type": "Feature",
  "properties": {
    "iso:country":"CH",
    "sg:address":"Spitalstrasse 71",
    "sg:city":"Urdorf",
    "sg:orig_category":"Detailhandel mit Getr\u00e4nken",
    "sg:phone":"+41 81 771 22 72",
    "sg:postcode":"8902",
    "sg:province":"Z\u00fcrich",
    "wof:name":"H.& S. Righini Getr\u00e4nkehandel",
    "wof:placetype":"venue"
},
  "geometry": {"coordinates":[9.4925498962,47.212928772],"type":"Point"}
}