{
  "type": "Feature",
  "properties": {
    "iso:country":"CH",
    "sg:address":"Z\u00fcrichstrasse 8840 Einsiedeln. Postfach",
    "sg:city":"Einsiedeln",
    "sg:orig_category":"Einzelhandel mit Automobilteilen U Zubeh\u00f6r Herstellung von Bereifungen",
    "sg:phone":"+41 55 412 48 61",
    "sg:postcode":"8840",
    "sg:province":"Schwyz",
    "wof:name":"Buchegger Ag",
    "wof:placetype":"venue"
},
  "geometry": {"coordinates":[8.7440948486,47.1317939758],"type":"Point"}
}