{
  "type": "Feature",
  "properties": {
    "iso:country":"CH",
    "sg:address":"B\u00e4chligartenweg 7",
    "sg:city":"Kreuzlingen",
    "sg:orig_category":"Kaminfeger",
    "sg:phone":"+41 71 672 29 01",
    "sg:postcode":"8280",
    "sg:province":"Thurgau",
    "wof:name":"Hugo Bachmann Kaminfegergesch\u00e4ft",
    "wof:placetype":"venue"
},
  "geometry": {"coordinates":[9.1684942245,47.6459732056],"type":"Point"}
}