{
  "type": "Feature",
  "properties": {
    "iso:country":"CH",
    "sg:address":"Freiestrasse 3 8610 Uster. Postfach",
    "sg:city":"Uster",
    "sg:orig_category":"Herstellung von medizinischen U chirurgischen Ger\u00e4ten sowie orthop\u00e4dischen Vorrichtungen Zahntechnis",
    "sg:phone":"+41 19408110",
    "sg:postcode":"8610",
    "sg:province":"Z\u00fcrich",
    "wof:name":"Kieferorthop\u00e4die Labor Stalder Franziska Zahntechn. Labor Mit Spezialgebiet Kieferorthop\u00e4die Usw",
    "wof:placetype":"venue"
},
  "geometry": {"coordinates":[8.7200717926,47.3493537903],"type":"Point"}
}