{
  "type": "Feature",
  "properties": {
    "iso:country":"CH",
    "sg:address":"Marchairuz Route Du",
    "sg:city":"St-george",
    "sg:orig_category":"Grosshandel mit festen Brennstoffen U Mineral\u00f6lerzeugnissen",
    "sg:postcode":"1261",
    "sg:province":"Vaud",
    "wof:name":"Flamnat S\u00e0rl",
    "wof:placetype":"venue"
},
  "geometry": {"coordinates":[6.2611041069,46.51537323],"type":"Point"}
}