{
  "type": "Feature",
  "properties": {
    "iso:country":"CH",
    "sg:address":"Holzmattstrasse 29 8953 Dietikon. Postfach",
    "sg:city":"Dietikon",
    "sg:orig_category":"Sonstige Kurierdienste",
    "sg:phone":"+41 17405023",
    "sg:postcode":"8953",
    "sg:province":"Z\u00fcrich",
    "wof:name":"Ziehbrunner Transport Klein, Expresstransporte",
    "wof:placetype":"venue"
},
  "geometry": {"coordinates":[8.4008359909,47.3974266052],"type":"Point"}
}