{
  "type": "Feature",
  "properties": {
    "iso:country":"CH",
    "sg:address":"Wiesenstrasse 11",
    "sg:city":"Sirnach",
    "sg:orig_category":"Elektroinstallation",
    "sg:phone":"+41 71 966 22 17",
    "sg:postcode":"8370",
    "sg:province":"Thurgau",
    "wof:name":"St\u00e4heli & Keller Ag",
    "wof:placetype":"venue"
},
  "geometry": {"coordinates":[9.0016498566,47.4695587158],"type":"Point"}
}