{
  "type": "Feature",
  "properties": {
    "iso:country":"CH",
    "sg:address":"T\u00e4gerigerweg 37",
    "sg:city":"Mellingen",
    "sg:orig_category":"Unclassifiable Establishments",
    "sg:postcode":"5507",
    "sg:province":"Aargau",
    "wof:name":"Malergesch\u00c4ft Gschwend & Sol\u00c8r",
    "wof:placetype":"venue"
},
  "geometry": {"coordinates":[8.2763757706,47.4156990051],"type":"Point"}
}