{
  "type": "Feature",
  "properties": {
    "iso:country":"CH",
    "sg:address":"Obere Grabenmattstrasse 3",
    "sg:city":"Oberrohrdorf",
    "sg:classifiers":[
        {
            "category":"Autos & Motor Vehicles",
            "subcategory":"Fuel & Gas Station",
            "type":"Retail Goods"
        }
    ],
    "sg:phone":"+41 56 485 82 00",
    "sg:postcode":"5452",
    "sg:province":"Aargau",
    "sg:tags":[
        "machine",
        "tool"
    ],
    "wof:name":"Ramsauer Maschinen Ag",
    "wof:placetype":"venue"
},
  "geometry": {"coordinates":[8.3133115768,47.4196128845],"type":"Point"}
}