{
  "type": "Feature",
  "properties": {
    "iso:country":"CH",
    "sg:address":"Monbijoustrasse 23 3014 Bern. Postfach 6111",
    "sg:city":"Bern",
    "sg:orig_category":"Buchf\u00fchrung Finanzierungsinstitutionen",
    "sg:phone":"+41 56 664 56 06",
    "sg:postcode":"3001",
    "sg:province":"Bern",
    "wof:name":"Hawecon Wegelin Hans Consulting Dienstleistungen Im Finanzbereich U. Steuererkl\u00e4rungen",
    "wof:placetype":"venue"
},
  "geometry": {"coordinates":[8.317482,47.282578],"type":"Point"}
}