{
  "type": "Feature",
  "properties": {
    "iso:country":"CH",
    "sg:address":"Rue Des P\u00eacheurs 8",
    "sg:city":"Yverdon-les-bains",
    "sg:orig_category":"Gymnastik U Fitnesszentren Saunas, Solarien, Fitnesszentren U \u00e4hnliches",
    "sg:phone":"+41 26 496 27 27",
    "sg:postcode":"1400",
    "sg:province":"Vaud",
    "wof:name":"Let's Go Ruch R.",
    "wof:placetype":"venue"
},
  "geometry": {"coordinates":[7.2490491867,46.8625679016],"type":"Point"}
}