{
  "type": "Feature",
  "properties": {
    "iso:country":"CH",
    "sg:address":"Avenue G\u00e9n\u00e9ral-guisan 15",
    "sg:city":"Sierre",
    "sg:orig_category":"Herstellung von Bergwerks U Baumaschinen",
    "sg:phone":"+41 21 652 97 46",
    "sg:postcode":"3960",
    "sg:province":"Valais",
    "wof:name":"Tracosa Sa",
    "wof:placetype":"venue"
},
  "geometry": {"coordinates":[7.5305118561,46.2922592163],"type":"Point"}
}