{
  "type": "Feature",
  "properties": {
    "iso:country":"CH",
    "sg:address":"Industriering 1001",
    "sg:city":"K\u00f6lliken",
    "sg:orig_category":"Herstellung von Mess U Kontrollinstrumenten U vorrichtungen",
    "sg:phone":"+41 62 723 75 75",
    "sg:postcode":"5742",
    "sg:province":"Aargau",
    "wof:name":"Alwa Grunder Ag",
    "wof:placetype":"venue"
},
  "geometry": {"coordinates":[8.0130109787,47.3228492737],"type":"Point"}
}