{
  "type": "Feature",
  "properties": {
    "iso:country":"CH",
    "sg:address":"Roncaglia Via 5",
    "sg:city":"Novazzano",
    "sg:orig_category":"Handels-H\u00e4user U Gesellschaften",
    "sg:phone":"+41 91 682 52 45",
    "sg:postcode":"6883",
    "sg:province":"Ticino",
    "wof:name":"Freti Associates Sagl",
    "wof:placetype":"venue"
},
  "geometry": {"coordinates":[8.99518013,45.8398704529],"type":"Point"}
}