{
  "type": "Feature",
  "properties": {
    "iso:country":"CH",
    "sg:address":"Freieckgasse 7",
    "sg:city":"Z\u00fcrich",
    "sg:orig_category":"Detailhandel mit Schuhen",
    "sg:phone":"+41 12528355",
    "sg:postcode":"8001",
    "sg:province":"Z\u00fcrich",
    "wof:name":"Bigshoes Damenschuhe Ab Gr.41",
    "wof:placetype":"venue"
},
  "geometry": {"coordinates":[8.5459289551,47.3675117493],"type":"Point"}
}