{
  "type": "Feature",
  "properties": {
    "iso:country":"CH",
    "sg:address":"Josefstrasse 18",
    "sg:city":"Z\u00fcrich",
    "sg:orig_category":"Herstellung von Reiseartikeln, Leder U Sattlerwaren",
    "sg:phone":"+41 32 913 65 44",
    "sg:postcode":"8005",
    "sg:province":"Z\u00fcrich",
    "wof:name":"Lumorex Sa Bracelets Cuir",
    "wof:placetype":"venue"
},
  "geometry": {"coordinates":[6.8286762238,47.0987586975],"type":"Point"}
}