{
  "type": "Feature",
  "properties": {
    "iso:country":"CH",
    "sg:address":"Carolins Route Des 6",
    "sg:city":"Sitten",
    "sg:orig_category":"Reinigungsgewerbe",
    "sg:phone":"+41 27 323 37 00",
    "sg:postcode":"1950",
    "sg:province":"Valais",
    "wof:name":"Ga 36 Gini Pascal",
    "wof:placetype":"venue"
},
  "geometry": {"coordinates":[7.3588571548,46.2280921936],"type":"Point"}
}