{
  "type": "Feature",
  "properties": {
    "iso:country":"CH",
    "sg:address":"Oberwiesenstrasse 5",
    "sg:city":"Z\u00fcrich",
    "sg:orig_category":"Sanit\u00e4r, Heizungs U L\u00fcftungsinstallation Sanit\u00e4rinstallation",
    "sg:phone":"+41 13617189",
    "sg:postcode":"8057",
    "sg:province":"Z\u00fcrich",
    "wof:name":"H\u00e4uptli Herbert, Sanit\u00e4re Anlagen",
    "wof:placetype":"venue"
},
  "geometry": {"coordinates":[8.5310344696,47.4079551697],"type":"Point"}
}