{
  "type": "Feature",
  "properties": {
    "iso:country":"CH",
    "sg:address":"Pizolpark",
    "sg:city":"Mels",
    "sg:orig_category":"M\u00f6belschreinereien",
    "sg:phone":"+41 81 725 39 39",
    "sg:postcode":"8887",
    "sg:province":"St. Gallen",
    "wof:name":"M\u00f6bel-pfister Ag, Filiale Mels",
    "wof:placetype":"venue"
},
  "geometry": {"coordinates":[9.4317054749,47.0424537659],"type":"Point"}
}