{
  "type": "Feature",
  "properties": {
    "iso:country":"CH",
    "sg:address":"Z\u00fcrcherstrasse 305 8500 Frauenfeld. Postfach 471",
    "sg:city":"Frauenfeld",
    "sg:orig_category":"Architektur U Ingenieurb\u00fcros Architekturb\u00fcros",
    "sg:phone":"+41 52 722 22 64",
    "sg:postcode":"8500",
    "sg:province":"Thurgau",
    "wof:name":"Bierett Und Partner Ag Architekten Sia",
    "wof:placetype":"venue"
},
  "geometry": {"coordinates":[8.910085,47.564621],"type":"Point"}
}