{
  "type": "Feature",
  "properties": {
    "iso:country":"CH",
    "sg:address":"Kantonsstrasse 20",
    "sg:city":"Visp",
    "sg:orig_category":"Detailhandel mit Antiquit\u00e4ten U Gebrauchtwaren in Verkaufsr\u00e4umen",
    "sg:postcode":"3930",
    "sg:province":"Valais",
    "wof:name":"Urbi's Gebrauchtwaren Schnidrig Urban",
    "wof:placetype":"venue"
},
  "geometry": {"coordinates":[7.884744,46.292023],"type":"Point"}
}