{
  "type": "Feature",
  "properties": {
    "iso:country":"CH",
    "sg:address":"Nansenstrasse 16 8050 Z\u00fcrich. Postfach 8938",
    "sg:city":"Z\u00fcrich",
    "sg:orig_category":"Banken sonstige",
    "sg:phone":"+41 13154455",
    "sg:postcode":"8050",
    "sg:province":"Z\u00fcrich",
    "wof:name":"Pfandbriefbank Schweizerischer Hypothekarinstitute",
    "wof:placetype":"venue"
},
  "geometry": {"coordinates":[8.54463,47.41082],"type":"Point"}
}