{
  "type": "Feature",
  "properties": {
    "iso:country":"CH",
    "sg:address":"Salvatore Viale San 6 6900 Paradiso. Postfach",
    "sg:city":"Paradiso",
    "sg:orig_category":"Detailhandel mit Bekleidung",
    "sg:postcode":"6902",
    "sg:province":"Ticino",
    "wof:name":"Iniziative Ltc Sa, Luxembourg, Succursale Di Paradiso Comm. Di Articoli Di Abbigliamento",
    "wof:placetype":"venue"
},
  "geometry": {"coordinates":[8.945029,45.991943],"type":"Point"}
}