{
  "type": "Feature",
  "properties": {
    "iso:country":"CH",
    "sg:address":"Teufener Strasse 3",
    "sg:city":"St.gallen",
    "sg:orig_category":"Non-Classified Establishments",
    "sg:postcode":"9000",
    "sg:province":"St. Gallen",
    "wof:name":"Contan Holding Und Verwaltungs Ag",
    "wof:placetype":"venue"
},
  "geometry": {"coordinates":[9.3718414307,47.4210281372],"type":"Point"}
}