{
  "type": "Feature",
  "properties": {
    "iso:country":"CH",
    "sg:address":"Kirchstrasse 4",
    "sg:city":"Wallisellen",
    "sg:classifiers":[
        {
            "category":"Government",
            "subcategory":"Post Office",
            "type":"Public Place"
        }
    ],
    "sg:phone":"+41 18300670",
    "sg:postcode":"8304",
    "sg:province":"Z\u00fcrich",
    "sg:tags":[
        "caf\u00e9s",
        "tea-rooms"
    ],
    "wof:name":"Cafeteria Country",
    "wof:placetype":"venue"
},
  "geometry": {"coordinates":[8.5932397842,47.4141769409],"type":"Point"}
}