{
  "type": "Feature",
  "properties": {
    "iso:country":"CH",
    "sg:address":"3307",
    "sg:city":"Brunnenthal",
    "sg:orig_category":"Autogaragen Autospenglereien",
    "sg:phone":"+41 31 765 50 55",
    "sg:postcode":"3307",
    "sg:province":"Solothurn",
    "wof:name":"Toni Voegeli Garage & Carrosserie",
    "wof:placetype":"venue"
},
  "geometry": {"coordinates":[7.45675,47.084789],"type":"Point"}
}