{
  "type": "Feature",
  "properties": {
    "iso:country":"CH",
    "sg:address":"Engstringerstrasse 48",
    "sg:city":"Schlieren",
    "sg:orig_category":"Detailhandel mit Metallwaren, Anstrichmitteln, Glaswaren, Bau U Heimwerkerbedarf",
    "sg:postcode":"8952",
    "sg:province":"Z\u00fcrich",
    "wof:name":"Muff A.",
    "wof:placetype":"venue"
},
  "geometry": {"coordinates":[8.447924614,47.4071884155],"type":"Point"}
}