{
  "type": "Feature",
  "properties": {
    "addr:full":"Av D'ouchy 76 Lausanne Vaud 1008",
    "addr:housenumber":"76",
    "addr:postcode":"1008",
    "addr:street":"Av D'Ouchy",
    "iso:country":"CH",
    "sg:address":"Av D'ouchy 76",
    "sg:city":"Lausanne",
    "sg:classifiers":[
        {
            "category":"Banks & Credit Unions",
            "subcategory":"Bank",
            "type":"Services"
        }
    ],
    "sg:phone":"+41 21269442",
    "sg:postcode":"1008",
    "sg:province":"Vaud",
    "wof:name":"Banque Cantonale Vaudoise",
    "wof:placetype":"venue"
},
  "geometry": {"coordinates":[6.60305,46.543659],"type":"Point"}
}