{
  "type": "Feature",
  "properties": {
    "addr:full":"Rudolf Diesel-strasse 12 8404 Stadel(winterthur). Postfach Winterthur Z\u00fcrich 8401",
    "addr:housenumber":"12",
    "addr:postcode":"8404;postfach;8401",
    "addr:street":"Diesel-Strasse",
    "iso:country":"CH",
    "sg:address":"Rudolf Diesel-strasse 12 8404 Stadel(winterthur). Postfach",
    "sg:city":"Winterthur",
    "sg:orig_category":"Detailhandel mit Beleuchtungs U Haushaltsgegenst\u00e4nden",
    "sg:phone":"+41 79 674 40 71",
    "sg:postcode":"8401",
    "sg:province":"Z\u00fcrich",
    "wof:name":"Heinimann Ag Handel Mit Eisenwaren, Werkzeugen, Haushaltartikeln.",
    "wof:placetype":"venue"
},
  "geometry": {"coordinates":[7.749076,47.392403],"type":"Point"}
}