{
  "type": "Feature",
  "properties": {
    "addr:full":"R\u00fctistrasse 33 Appenzell Appenzell Innerhoden 9050",
    "addr:housenumber":"33",
    "addr:postcode":"9050",
    "addr:street":"Ruetistrasse",
    "iso:country":"CH",
    "sg:address":"R\u00fctistrasse 33",
    "sg:city":"Appenzell",
    "sg:orig_category":"Allgemeiner Hoch U Tiefbau Hoch U Tiefbau",
    "sg:phone":"+41 71 787 16 09",
    "sg:postcode":"9050",
    "sg:province":"Appenzell Innerhoden",
    "wof:name":"Gollino Gebr. Ag, Appenzell",
    "wof:placetype":"venue"
},
  "geometry": {"coordinates":[9.400142,47.332458],"type":"Point"}
}