{
  "type": "Feature",
  "properties": {
    "iso:country":"CH",
    "sg:address":"Thunstrasse 56",
    "sg:city":"M\u00fcnsingen",
    "sg:orig_category":"Detailhandel mit M\u00f6beln Detailhandel mit M\u00f6beln U Haushaltsgegenst\u00e4nden",
    "sg:phone":"+41 31 721 60 80",
    "sg:postcode":"3110",
    "sg:province":"Bern",
    "wof:name":"Rentsch M\u00f6belzentrum Gmbh",
    "wof:placetype":"venue"
},
  "geometry": {"coordinates":[7.5645828247,46.8650627136],"type":"Point"}
}