{
  "type": "Feature",
  "properties": {
    "iso:country":"CH",
    "sg:address":"Fennen 8",
    "sg:city":"Niederurnen",
    "sg:orig_category":"Allgemeiner Hochbau Hobel U Holzimpr\u00e4gnierwerke",
    "sg:phone":"+41 55 610 10 10",
    "sg:postcode":"8867",
    "sg:province":"Glarus",
    "wof:name":"Bisig & Oswald Bedachungen Ag",
    "wof:placetype":"venue"
},
  "geometry": {"coordinates":[9.041468,47.134815],"type":"Point"}
}