{
  "type": "Feature",
  "properties": {
    "iso:country":"CH",
    "sg:address":"Sotch\u00e0 681",
    "sg:city":"Scuol",
    "sg:orig_category":"Allgemeiner Hoch U Tiefbau",
    "sg:postcode":"7550",
    "sg:province":"Graubunden",
    "wof:name":"Quadroni Linard Sa",
    "wof:placetype":"venue"
},
  "geometry": {"coordinates":[10.307809,46.796837],"type":"Point"}
}