{
  "type": "Feature",
  "properties": {
    "addr:full":"Bahnhofstrasse Wimmis Bern 3752",
    "addr:postcode":"3752",
    "addr:street":"Bahnhofstrasse;Bern",
    "iso:country":"CH",
    "sg:address":"Bahnhofstrasse",
    "sg:city":"Wimmis",
    "sg:classifiers":[
        {
            "category":"Home & Garden",
            "subcategory":"Furniture",
            "type":"Retail Goods"
        }
    ],
    "sg:phone":"+41 33 657 20 21",
    "sg:postcode":"3752",
    "sg:province":"Bern",
    "sg:tags":[
        "accessory"
    ],
    "wof:name":"Andr\u00e9 W\u00e4lti Zaunbau",
    "wof:placetype":"venue"
},
  "geometry": {"coordinates":[7.636503,46.675915],"type":"Point"}
}