{
  "type": "Feature",
  "properties": {
    "iso:country":"CH",
    "sg:address":"Rue D'orbe 36",
    "sg:city":"Yverdon-les-bains",
    "sg:orig_category":"Instandhaltung U Reparatur von Automobilen",
    "sg:phone":"+41 24 425 35 80",
    "sg:postcode":"1400",
    "sg:province":"Vaud",
    "wof:name":"Charbon Y., Auto-\u00e9lectro-service.",
    "wof:placetype":"venue"
},
  "geometry": {"coordinates":[6.6414198875,46.778629303],"type":"Point"}
}