{
  "type": "Feature",
  "properties": {
    "iso:country":"CH",
    "sg:address":"Neuquartierstrasse 2",
    "sg:city":"Dottikon",
    "sg:orig_category":"Saunas Solarien",
    "sg:phone":"+41 61 751 37 36",
    "sg:postcode":"5605",
    "sg:province":"Aargau",
    "wof:name":"Guido Marbach Axis Fitnessclub",
    "wof:placetype":"venue"
},
  "geometry": {"coordinates":[7.5975060463,47.4683036804],"type":"Point"}
}