{
  "type": "Feature",
  "properties": {
    "iso:country":"CH",
    "sg:address":"Gl\u00e4ngweg 11",
    "sg:city":"Nebikon",
    "sg:orig_category":"Herstellung von Metallkonstruktionen",
    "sg:phone":"+41 55 615 11 91",
    "sg:postcode":"6244",
    "sg:province":"Luzern",
    "wof:name":"D\u00fcring Albert",
    "wof:placetype":"venue"
},
  "geometry": {"coordinates":[9.0545148849,47.1724510193],"type":"Point"}
}