{
  "type": "Feature",
  "properties": {
    "addr:full":"Glatthof 1 Oberb\u00fcren St. Gallen 9245",
    "addr:housenumber":"1;st.",
    "addr:postcode":"9245",
    "addr:street":"Glatthof",
    "iso:country":"CH",
    "sg:address":"Glatthof 1",
    "sg:city":"Oberb\u00fcren",
    "sg:orig_category":"Betrieb U technische Hilfsdienste des Kultur U Unterhaltungswesens",
    "sg:postcode":"9245",
    "sg:province":"St. Gallen",
    "wof:name":"Fatal 96 Veranstaltungsorganisation",
    "wof:placetype":"venue"
},
  "geometry": {"coordinates":[9.15372,47.445862],"type":"Point"}
}