{
  "type": "Feature",
  "properties": {
    "iso:country":"CH",
    "sg:address":"Im Mattenacher 2",
    "sg:city":"Maur",
    "sg:orig_category":"Vereine Vogel-& Naturschutz",
    "sg:phone":"+41 19802076",
    "sg:postcode":"8124",
    "sg:province":"Z\u00fcrich",
    "wof:name":"Natur-& Vogelschutzverein",
    "wof:placetype":"venue"
},
  "geometry": {"coordinates":[8.671587944,47.3405265808],"type":"Point"}
}