{
  "type": "Feature",
  "properties": {
    "iso:country":"CH",
    "sg:address":"Els\u00e4sserstr. 16",
    "sg:city":"Basel",
    "sg:classifiers":[
        {
            "category":"Banks & Credit Unions",
            "subcategory":"Bank",
            "type":"Services"
        }
    ],
    "sg:phone":"+41 61 385 22 44",
    "sg:postcode":"4056",
    "sg:province":"Basel-Stadt",
    "wof:name":"Swiss Bank Corporation, St. Johann",
    "wof:placetype":"venue"
},
  "geometry": {"coordinates":[7.580045,47.568619],"type":"Point"}
}