{
  "type": "Feature",
  "properties": {
    "iso:country":"CH",
    "sg:address":"Florissant Route De 55 1206 Gen\u00e8ve. Postfach",
    "sg:city":"Gen\u00e8ve",
    "sg:orig_category":"Erbringung von Dienstleistungen f\u00fcr Unternehmen",
    "sg:postcode":"1201",
    "sg:province":"Gen\u00e8ve",
    "wof:name":"Roviga S\u00e0rl",
    "wof:placetype":"venue"
},
  "geometry": {"coordinates":[6.1616811752,46.193572998],"type":"Point"}
}