{
  "type": "Feature",
  "properties": {
    "iso:country":"CH",
    "sg:address":"Stockeren 30",
    "sg:city":"Schnottwil",
    "sg:orig_category":"Landw. Genossenschaften Dresch",
    "sg:phone":"+41 32 351 25 80",
    "sg:postcode":"3253",
    "sg:province":"Solothurn",
    "wof:name":"Walter Ramser M\u00e4hdrescherei",
    "wof:placetype":"venue"
},
  "geometry": {"coordinates":[7.3862428665,47.1090660095],"type":"Point"}
}