{
  "type": "Feature",
  "properties": {
    "iso:country":"CH",
    "sg:address":"Heitern",
    "sg:city":"Toffen",
    "sg:orig_category":"Sportvereine Ballsport Volleyball",
    "sg:phone":"+41 31 819 12 19",
    "sg:postcode":"3125",
    "sg:province":"Bern",
    "wof:name":"Volleyball-club G\u00fcrbetal",
    "wof:placetype":"venue"
},
  "geometry": {"coordinates":[7.5051298141,46.8568992615],"type":"Point"}
}