{
  "type": "Feature",
  "properties": {
    "iso:country":"CH",
    "sg:address":"Zanggerweg 9",
    "sg:city":"Z\u00fcrich",
    "sg:orig_category":"Unclassifiable Establishments",
    "sg:postcode":"8006",
    "sg:province":"Z\u00fcrich",
    "wof:name":"Rudin Consulting",
    "wof:placetype":"venue"
},
  "geometry": {"coordinates":[8.5440654755,47.3922653198],"type":"Point"}
}