{
  "type": "Feature",
  "properties": {
    "iso:country":"CH",
    "sg:address":"Glash\u00fcttenweg 19",
    "sg:city":"Mels",
    "sg:orig_category":"Detailhandel mit Fahrr\u00e4dern Handel mit Motorr\u00e4dern, Teilen U Zubeh\u00f6r Instandhaltung U Reparatur von ",
    "sg:phone":"+41 62 875 13 54",
    "sg:postcode":"8887",
    "sg:province":"St. Gallen",
    "wof:name":"Ewald Weiss Velos Motos",
    "wof:placetype":"venue"
},
  "geometry": {"coordinates":[8.0989742279,47.5388832092],"type":"Point"}
}