{
  "type": "Feature",
  "properties": {
    "iso:country":"CH",
    "sg:address":"Bauherrenstrasse 56",
    "sg:city":"Z\u00fcrich",
    "sg:orig_category":"Interessenvertretungen",
    "sg:postcode":"8049",
    "sg:province":"Z\u00fcrich",
    "wof:name":"Pohl Rudolf-stiftung F\u00f6rderung Der Leiblichen, Sittlichen Und Seelischen Wohlfahrt Von Schweizer Wehrm\u00e4nnern Usw",
    "wof:placetype":"venue"
},
  "geometry": {"coordinates":[8.4979944229,47.401725769],"type":"Point"}
}