{
  "type": "Feature",
  "properties": {
    "iso:country":"CH",
    "sg:address":"Zollikerstrasse 153 8008 Z\u00fcrich. Postfach",
    "sg:city":"Z\u00fcrich",
    "sg:orig_category":"Sonstige mit der Informatik verbundene T\u00e4tigkeiten",
    "sg:phone":"+41 61 713 21 00",
    "sg:postcode":"8008",
    "sg:province":"Z\u00fcrich",
    "wof:name":"Think-simple",
    "wof:placetype":"venue"
},
  "geometry": {"coordinates":[7.5980730057,47.4854698181],"type":"Point"}
}