{
  "type": "Feature",
  "properties": {
    "iso:country":"CH",
    "sg:address":"Avenue Du Midi 39",
    "sg:city":"Sion",
    "sg:orig_category":"Kunstgewerbeschulen",
    "sg:phone":"+41 91 970 19 29",
    "sg:postcode":"1950",
    "sg:province":"Valais",
    "wof:name":"Centro Scolastico Industrie Artistiche",
    "wof:placetype":"venue"
},
  "geometry": {"coordinates":[8.9556713104,46.0181465149],"type":"Point"}
}