{
  "type": "Feature",
  "properties": {
    "iso:country":"CH",
    "sg:address":"Hinterbergstrasse 6330 Cham. Postfach 5012",
    "sg:city":"Cham",
    "sg:orig_category":"Herstellung von Betonerzeugnissen f\u00fcr den Bau",
    "sg:phone":"+41 41 741 85 65",
    "sg:postcode":"6330",
    "sg:province":"Zug",
    "wof:name":"Beton Ag, Cham",
    "wof:placetype":"venue"
},
  "geometry": {"coordinates":[8.4781150818,47.1880836487],"type":"Point"}
}