{
  "type": "Feature",
  "properties": {
    "iso:country":"CH",
    "sg:address":"3225",
    "sg:city":"M\u00fcntschemier",
    "sg:orig_category":"Sonstiger Fachdetailhandel mit Nahrungsmitteln, Getr\u00e4nken U Tabak in Verkaufsr\u00e4umen",
    "sg:phone":"+41 32 313 29 37",
    "sg:postcode":"3225",
    "sg:province":"Bern",
    "wof:name":"Niklaus-sommer Hansruedi.",
    "wof:placetype":"venue"
},
  "geometry": {"coordinates":[7.1492400169,46.995300293],"type":"Point"}
}