{
  "type": "Feature",
  "properties": {
    "iso:country":"CH",
    "sg:address":"Compois Chemin Du 18",
    "sg:city":"Evilard",
    "sg:orig_category":"Museen",
    "sg:phone":"+41 41 610 15 92",
    "sg:postcode":"2533",
    "sg:province":"Bern",
    "wof:name":"Ahas Art Ag Kunstausstellungen, Vernissagen U. Auktionen Usw",
    "wof:placetype":"venue"
},
  "geometry": {"coordinates":[8.3894338608,46.9587974548],"type":"Point"}
}