{
  "type": "Feature",
  "properties": {
    "iso:country":"CH",
    "sg:address":"7504",
    "sg:city":"Pontresina",
    "sg:orig_category":"Fachdetailhandel mit pharmazeutischen Produkten",
    "sg:phone":"+41 81 842 82 06",
    "sg:postcode":"7504",
    "sg:province":"Graubunden",
    "wof:name":"Roseg Ag",
    "wof:placetype":"venue"
},
  "geometry": {"coordinates":[9.9019098282,46.4935150146],"type":"Point"}
}