{
  "type": "Feature",
  "properties": {
    "iso:country":"CH",
    "sg:address":"Rue De La Libert\u00e9 75",
    "sg:city":"Develier",
    "sg:orig_category":"G\u00fcterbef\u00f6rderung im Strassenverkehr Handelsvermittlung U Grosshandel",
    "sg:phone":"+41 18691056",
    "sg:postcode":"2802",
    "sg:province":"Jura",
    "wof:name":"Kaiser Transport Landesprodukte Gmbh",
    "wof:placetype":"venue"
},
  "geometry": {"coordinates":[8.5086193085,47.604019165],"type":"Point"}
}