{
  "type": "Feature",
  "properties": {
    "iso:country":"CH",
    "sg:address":"3210",
    "sg:city":"Kerzers",
    "sg:orig_category":"Vereine Musik/Blasmusik",
    "sg:phone":"+41 81 756 75 06",
    "sg:postcode":"3210",
    "sg:province":"Fribourg",
    "wof:name":"Blechharmonie R\u00e4fis-burgerau",
    "wof:placetype":"venue"
},
  "geometry": {"coordinates":[9.4501104355,47.1685714722],"type":"Point"}
}