{
  "type": "Feature",
  "properties": {
    "iso:country":"CH",
    "sg:address":"Mettstrasse 23",
    "sg:city":"Biel/bienne",
    "sg:orig_category":"Grafikateliers, Design",
    "sg:phone":"+41 32 365 37 53",
    "sg:postcode":"2503",
    "sg:province":"Bern",
    "wof:name":"William Piasio Cin\u00e9collection",
    "wof:placetype":"venue"
},
  "geometry": {"coordinates":[7.2625231743,47.1394195557],"type":"Point"}
}