{
  "type": "Feature",
  "properties": {
    "iso:country":"CH",
    "sg:address":"6802",
    "sg:city":"Rivera",
    "sg:orig_category":"Elektroinstallation",
    "sg:phone":"+41 91 946 41 37",
    "sg:postcode":"6802",
    "sg:province":"Ticino",
    "wof:name":"Lamps-dad\u00f2 Sagl",
    "wof:placetype":"venue"
},
  "geometry": {"coordinates":[8.9231395721,46.1164894104],"type":"Point"}
}