{
  "type": "Feature",
  "properties": {
    "addr:full":"Bettingerstrasse 1 Riehen Basel-Stadt 4125",
    "addr:housenumber":"1",
    "addr:postcode":"4125",
    "addr:street":"Bettingerstrasse",
    "iso:country":"CH",
    "sg:address":"Bettingerstrasse 1",
    "sg:city":"Riehen",
    "sg:orig_category":"Detailhandel mit B\u00fcchern Kunsthandel",
    "sg:phone":"+41 61 641 66 51",
    "sg:postcode":"4125",
    "sg:province":"Basel-Stadt",
    "wof:name":"Robert Schibli Buch-& Kunstantiquariat",
    "wof:placetype":"venue"
},
  "geometry": {"coordinates":[7.648051,47.58268],"type":"Point"}
}