{
  "type": "Feature",
  "properties": {
    "iso:country":"CH",
    "sg:address":"Eichholzstrasse 16",
    "sg:city":"Meilen",
    "sg:orig_category":"Non-Classified Establishments",
    "sg:postcode":"8706",
    "sg:province":"Z\u00fcrich",
    "wof:name":"La Royale Ressource Vive Gmbh",
    "wof:placetype":"venue"
},
  "geometry": {"coordinates":[8.6252126694,47.2816696167],"type":"Point"}
}