{
  "type": "Feature",
  "properties": {
    "iso:country":"CH",
    "sg:address":"5643",
    "sg:city":"Alikon",
    "sg:classifiers":[
        {
            "category":"Restaurant",
            "type":"Food & Drink"
        }
    ],
    "sg:phone":"+41 41 787 12 48",
    "sg:postcode":"5643",
    "sg:province":"Aargau",
    "wof:name":"Restaurant Kaufmann",
    "wof:placetype":"venue"
},
  "geometry": {"coordinates":[8.3594799042,47.2003288269],"type":"Point"}
}