{
  "type": "Feature",
  "properties": {
    "iso:country":"CH",
    "sg:address":"Route De La Bellang\u00e8re",
    "sg:city":"Givrins",
    "sg:orig_category":"Handels-H\u00e4user U Gesellschaften",
    "sg:postcode":"1271",
    "sg:province":"Vaud",
    "wof:name":"Tag-courtage S\u00e0rl",
    "wof:placetype":"venue"
},
  "geometry": {"coordinates":[6.2009720802,46.4297637939],"type":"Point"}
}