{
  "type": "Feature",
  "properties": {
    "iso:country":"CH",
    "sg:address":"Sp\u00e4tach 11",
    "sg:city":"Erstfeld",
    "sg:orig_category":"Zimmerei, Dachdeckerei, Bauspenglerei U Abdichtung Zimmerei, Ingenieurholzbau",
    "sg:phone":"+41 41 880 10 50",
    "sg:postcode":"6472",
    "sg:province":"Uri",
    "wof:name":"Ambros Wipfli Holzbau",
    "wof:placetype":"venue"
},
  "geometry": {"coordinates":[8.6439752579,46.8185462952],"type":"Point"}
}