{
  "type": "Feature",
  "properties": {
    "iso:country":"CH",
    "sg:address":"Chemin De L'eglise 23 1066 Epalinges Case Postale 39",
    "sg:city":"Epalinges",
    "sg:orig_category":"Sportvereine Ballsport Basketball",
    "sg:phone":"+41 56 493 39 35",
    "sg:postcode":"1066",
    "sg:province":"Vaud",
    "wof:name":"Bc Hakoah",
    "wof:placetype":"venue"
},
  "geometry": {"coordinates":[8.2878799438,47.4522209167],"type":"Point"}
}