{
  "type": "Feature",
  "properties": {
    "iso:country":"CH",
    "sg:address":"Industriestrasse 44",
    "sg:city":"Wallisellen",
    "sg:orig_category":"Rechtsberatung Wirtschaftspr\u00fcfung, Steuerberatung U Treuhand",
    "sg:phone":"+41 32 722 18 41",
    "sg:postcode":"8304",
    "sg:province":"Z\u00fcrich",
    "wof:name":"Fm Trust Sa",
    "wof:placetype":"venue"
},
  "geometry": {"coordinates":[6.9267101288,46.9912796021],"type":"Point"}
}