{
  "type": "Feature",
  "properties": {
    "iso:country":"CH",
    "sg:address":"Neugutstrasse 14",
    "sg:city":"Glattbrugg",
    "sg:orig_category":"Sportvereine Behindertensport Vereine Diverse",
    "sg:phone":"+41 18108101",
    "sg:postcode":"8152",
    "sg:province":"Z\u00fcrich",
    "wof:name":"Zwirnitr\u00e4ff Freizeitclub F\u00fcr Behinderte Opfikon & Umgebung",
    "wof:placetype":"venue"
},
  "geometry": {"coordinates":[8.5640363693,47.433921814],"type":"Point"}
}