{
  "type": "Feature",
  "properties": {
    "iso:country":"CH",
    "sg:address":"Rosenauweg 14",
    "sg:city":"Wettingen",
    "sg:orig_category":"Architektur U Ingenieurb\u00fcros",
    "sg:phone":"+41 56 426 09 26",
    "sg:postcode":"5430",
    "sg:province":"Aargau",
    "wof:name":"G\u00f6seli Vogt Minikus",
    "wof:placetype":"venue"
},
  "geometry": {"coordinates":[8.322562,47.45929],"type":"Point"}
}