{
  "type": "Feature",
  "properties": {
    "iso:country":"CH",
    "sg:address":"Flurstrasse 11",
    "sg:city":"Baar",
    "sg:orig_category":"Kauf U Verkauf von Immobilien auf eigene Rechnung",
    "sg:postcode":"6340",
    "sg:province":"Zug",
    "wof:name":"Kmv Immobilien Gmbh",
    "wof:placetype":"venue"
},
  "geometry": {"coordinates":[8.5361509323,47.2005462646],"type":"Point"}
}