{
  "type": "Feature",
  "properties": {
    "iso:country":"CH",
    "sg:address":"Hopfenrain 19",
    "sg:city":"Bern",
    "sg:orig_category":"Druck ohne Zeitungsdruck",
    "sg:phone":"+41 31 371 04 03",
    "sg:postcode":"3007",
    "sg:province":"Bern",
    "wof:name":"Druckwerk R\u00fcfenacht",
    "wof:placetype":"venue"
},
  "geometry": {"coordinates":[7.4292221069,46.9403419495],"type":"Point"}
}