{
  "type": "Feature",
  "properties": {
    "iso:country":"CH",
    "sg:address":"Hauptstrasse 12",
    "sg:city":"Zuckenriet",
    "sg:orig_category":"Detailhandel mit Waren verschiedener Art, Hauptrichtung Nahrungsmittel",
    "sg:phone":"+41 71 947 12 70",
    "sg:postcode":"9526",
    "sg:province":"St. Gallen",
    "wof:name":"Volg-laden Ursula N\u00e4f",
    "wof:placetype":"venue"
},
  "geometry": {"coordinates":[9.1615762711,47.4845466614],"type":"Point"}
}