{
  "type": "Feature",
  "properties": {
    "iso:country":"CH",
    "sg:address":"Industria Via 16",
    "sg:city":"Mendrisio",
    "sg:orig_category":"RESTAURANTS: TEA-ROOMS",
    "sg:phone":"+41 91467112",
    "sg:postcode":"6850",
    "sg:province":"Ticino",
    "wof:name":"Panda Sa",
    "wof:placetype":"venue"
},
  "geometry": {"coordinates":[8.9913892746,45.8696136475],"type":"Point"}
}