{
  "type": "Feature",
  "properties": {
    "iso:country":"CH",
    "sg:address":"St. Gallerstrasse 17",
    "sg:city":"M\u00f6rschwil",
    "sg:classifiers":[
        {
            "category":"Government",
            "subcategory":"Fire Station",
            "type":"Public Place"
        }
    ],
    "sg:phone":"+41 71 860 02 62",
    "sg:postcode":"9402",
    "sg:province":"St. Gallen",
    "sg:tags":[
        "steel",
        "stainless",
        "drain",
        "trough"
    ],
    "wof:name":"Peter Huber",
    "wof:placetype":"venue"
},
  "geometry": {"coordinates":[9.4212808609,47.4669303894],"type":"Point"}
}