{
  "type": "Feature",
  "properties": {
    "iso:country":"CH",
    "sg:address":"Kradolfstrasse 15 8583 Sulgen. Postfach",
    "sg:city":"Sulgen",
    "sg:orig_category":"Landesverteidigung, Sozialversicherung \u00d6ffentliche Verwaltung",
    "sg:phone":"+41 71 642 13 42",
    "sg:postcode":"8583",
    "sg:province":"Thurgau",
    "wof:name":"Gemeindeverwaltung Sulgen",
    "wof:placetype":"venue"
},
  "geometry": {"coordinates":[9.1862287521,47.5367774963],"type":"Point"}
}