{
  "type": "Feature",
  "properties": {
    "iso:country":"CH",
    "sg:address":"Impasse De L' Epine 24",
    "sg:city":"Domdidier",
    "sg:classifiers":[
        {
            "category":"Shopping",
            "subcategory":"Baby Store",
            "type":"Retail Goods"
        }
    ],
    "sg:phone":"+41 26 675 25 25",
    "sg:postcode":"1564",
    "sg:province":"Fribourg",
    "sg:tags":[
        "food",
        "children's",
        "foods"
    ],
    "wof:name":"Milupa S.a.",
    "wof:placetype":"venue"
},
  "geometry": {"coordinates":[7.009068,46.869991],"type":"Point"}
}