{
  "type": "Feature",
  "properties": {
    "iso:country":"CH",
    "sg:address":"Avenue De Bel-air 1",
    "sg:city":"Ch\u00eane-bourg",
    "sg:orig_category":"Handel mit Motorr\u00e4dern, Teilen U Zubeh\u00f6r Instandhaltung U Reparatur von Motorr\u00e4dern",
    "sg:phone":"+41 22 349 57 65",
    "sg:postcode":"1225",
    "sg:province":"Gen\u00e8ve",
    "wof:name":"Cycles Loder.",
    "wof:placetype":"venue"
},
  "geometry": {"coordinates":[6.1930131912,46.1958847046],"type":"Point"}
}