{
  "type": "Feature",
  "properties": {
    "iso:country":"CH",
    "sg:address":"7012",
    "sg:city":"Felsberg",
    "sg:orig_category":"Haltung von Gefl\u00fcgel",
    "sg:phone":"+41 81 252 57 80",
    "sg:postcode":"7012",
    "sg:province":"Graubunden",
    "wof:name":"Ernst Alder Gefl\u00fcgelfarm",
    "wof:placetype":"venue"
},
  "geometry": {"coordinates":[9.4612102509,46.8582000732],"type":"Point"}
}