{
  "type": "Feature",
  "properties": {
    "iso:country":"CH",
    "sg:address":"Bahnhofstrasse 24 4950 Huttwil. Postfach 345",
    "sg:city":"Huttwil",
    "sg:orig_category":"Detailhandel mit Brillen U anderen Sehhilfen Fachdetailhandel in Verkaufsr\u00e4umen",
    "sg:phone":"+41 62 959 80 56",
    "sg:postcode":"4950",
    "sg:province":"Bern",
    "wof:name":"Sch\u00e4r Optik Ag",
    "wof:placetype":"venue"
},
  "geometry": {"coordinates":[7.844908,47.114079],"type":"Point"}
}