{
  "type": "Feature",
  "properties": {
    "iso:country":"CH",
    "sg:address":"Stade Immeuble Du",
    "sg:city":"Orsi\u00e8res",
    "sg:orig_category":"Non-Classified Establishments",
    "sg:postcode":"1937",
    "sg:province":"Valais",
    "wof:name":"J\u00e9r\u00f4me Rausis Fiduciaire",
    "wof:placetype":"venue"
},
  "geometry": {"coordinates":[7.142018795,46.0247955322],"type":"Point"}
}