{
  "type": "Feature",
  "properties": {
    "iso:country":"CH",
    "sg:address":"Rue Pr\u00e9vost-martin 4",
    "sg:city":"Gen\u00e8ve",
    "sg:orig_category":"Kunsthandel",
    "sg:phone":"+41 22 320 40 50",
    "sg:postcode":"1205",
    "sg:province":"Gen\u00e8ve",
    "wof:name":"Galerie Calart",
    "wof:placetype":"venue"
},
  "geometry": {"coordinates":[6.145430088,46.196056366],"type":"Point"}
}