{
  "type": "Feature",
  "properties": {
    "iso:country":"CH",
    "sg:address":"Marktgasse 14",
    "sg:city":"Interlaken",
    "sg:orig_category":"Reiseb\u00fcros U Reiseveranstalter",
    "sg:postcode":"3800",
    "sg:province":"Bern",
    "wof:name":"Reiseb\u00fcro Globy, Kalbermatten Daniela",
    "wof:placetype":"venue"
},
  "geometry": {"coordinates":[7.933672905,46.1117172241],"type":"Point"}
}