{
  "type": "Feature",
  "properties": {
    "iso:country":"CH",
    "sg:address":"Passbeltweg 3a 2542 Pieterlen. Postfach",
    "sg:city":"Pieterlen",
    "sg:orig_category":"Herstellung von Elektromotoren, Generatoren U Transformatoren",
    "sg:phone":"+41 32 377 36 08",
    "sg:postcode":"2542",
    "sg:province":"Bern",
    "wof:name":"Frigatech, Flury Martin Waren F\u00fcr Die Energie- U. Umwelttechnologie; Import U. Handel",
    "wof:placetype":"venue"
},
  "geometry": {"coordinates":[7.3400840759,47.1746101379],"type":"Point"}
}