{
  "type": "Feature",
  "properties": {
    "iso:country":"CH",
    "sg:address":"4912",
    "sg:city":"Aarwangen",
    "sg:orig_category":"Sportvereine Sch\u00fctzen Pistolen-& Gewehr",
    "sg:phone":"+41 56 664 48 35",
    "sg:postcode":"4912",
    "sg:province":"Bern",
    "wof:name":"Pistolensektion",
    "wof:placetype":"venue"
},
  "geometry": {"coordinates":[8.3409795761,47.2742385864],"type":"Point"}
}