{
  "type": "Feature",
  "properties": {
    "iso:country":"CH",
    "sg:address":"Mange 7",
    "sg:city":"Roggwil",
    "sg:classifiers":[
        {
            "category":"Airport",
            "subcategory":"General Aviation",
            "type":"Transportation"
        }
    ],
    "sg:phone":"+41 62 929 21 60",
    "sg:postcode":"4914",
    "sg:province":"Bern",
    "sg:tags":[
        "dehumidifiers",
        "air"
    ],
    "wof:name":"Elmar Ag",
    "wof:placetype":"venue"
},
  "geometry": {"coordinates":[7.820134,47.248375],"type":"Point"}
}