{
  "type": "Feature",
  "properties": {
    "iso:country":"CH",
    "sg:address":"G\u00e4rtnerstrasse 4a 8400 Winterthur. Postfach",
    "sg:city":"Winterthur",
    "sg:orig_category":"Gesundheitswesen",
    "sg:phone":"+41 52 268 03 03",
    "sg:postcode":"8411",
    "sg:province":"Z\u00fcrich",
    "wof:name":"Swica Gesundheitsorganisation Regionaldirektion Winterthur",
    "wof:placetype":"venue"
},
  "geometry": {"coordinates":[8.7364053726,47.498008728],"type":"Point"}
}