{
  "type": "Feature",
  "properties": {
    "iso:country":"CH",
    "sg:address":"Avenue Max-huber 12",
    "sg:city":"Sierre",
    "sg:orig_category":"Detailhandel mit M\u00f6beln U Haushaltsgegenst\u00e4nden",
    "sg:phone":"+41 27 456 73 60",
    "sg:postcode":"3960",
    "sg:province":"Valais",
    "wof:name":"C.b. Confort Et Bois S\u00e0rl",
    "wof:placetype":"venue"
},
  "geometry": {"coordinates":[7.536678791,46.2944755554],"type":"Point"}
}