{
  "type": "Feature",
  "properties": {
    "iso:country":"CH",
    "sg:address":"Ch. Du Bief St.-jean.",
    "sg:city":"Morges",
    "sg:orig_category":"Grosshandel mit Getr\u00e4nken",
    "sg:postcode":"1110",
    "sg:province":"Vaud",
    "wof:name":"Barroca Vital'eau S\u00e0rl",
    "wof:placetype":"venue"
},
  "geometry": {"coordinates":[6.8233909607,47.0991668701],"type":"Point"}
}