{
  "type": "Feature",
  "properties": {
    "iso:country":"CH",
    "sg:address":"Rue De La Gare 7",
    "sg:city":"Tramelan",
    "sg:classifiers":[
        {
            "category":"Wholesale",
            "subcategory":"Machinery & Supplies",
            "type":"Manufacturing & Wholesale Goods"
        }
    ],
    "sg:phone":"+41 32 933 00 55",
    "sg:postcode":"2720",
    "sg:province":"Bern",
    "sg:tags":[
        "equipment",
        "equipement",
        "precision",
        "timekeeping"
    ],
    "wof:name":"Bergeon & Cie Sa",
    "wof:placetype":"venue"
},
  "geometry": {"coordinates":[6.7457489967,47.0552635193],"type":"Point"}
}