{
  "type": "Feature",
  "properties": {
    "iso:country":"CH",
    "sg:address":"Gerschnialp",
    "sg:city":"Engelberg",
    "sg:classifiers":[
        {
            "category":"Restaurant",
            "type":"Food & Drink"
        }
    ],
    "sg:phone":"+41 41 637 22 12",
    "sg:postcode":"6390",
    "sg:province":"Obwalden",
    "wof:name":"Restaurant Gerschnialp & Caf\u00e9 Ritz",
    "wof:placetype":"venue"
},
  "geometry": {"coordinates":[8.4009590149,46.8079490662],"type":"Point"}
}