{
  "type": "Feature",
  "properties": {
    "iso:country":"CH",
    "sg:address":"Poststrasse 9",
    "sg:city":"Zug",
    "sg:orig_category":"Interessenvertretungen",
    "sg:postcode":"6300",
    "sg:province":"Zug",
    "wof:name":"Zehnder Egon P.s. Stiftung F\u00fcr Internationales Management",
    "wof:placetype":"venue"
},
  "geometry": {"coordinates":[8.5158243179,47.1677322388],"type":"Point"}
}