{
  "type": "Feature",
  "properties": {
    "iso:country":"CH",
    "sg:address":"Gasometerstrasse 24",
    "sg:city":"Z\u00fcrich",
    "sg:orig_category":"Handelsvermittlung U Grosshandel Sonstiger Grosshandel",
    "sg:phone":"+41 62 212 94 64",
    "sg:postcode":"8005",
    "sg:province":"Z\u00fcrich",
    "wof:name":"Albatros Import Tasevsky Ivan",
    "wof:placetype":"venue"
},
  "geometry": {"coordinates":[7.8675031662,47.3460845947],"type":"Point"}
}