{
  "type": "Feature",
  "properties": {
    "iso:country":"CH",
    "sg:address":"1783",
    "sg:city":"Cormagens",
    "sg:orig_category":"Zimmerei, Dachdeckerei, Bauspenglerei U Abdichtung",
    "sg:phone":"+41 26 466 83 02",
    "sg:postcode":"1783",
    "sg:province":"Fribourg",
    "wof:name":"Ferblanterie, Couverture, Sanitaire Du Lac, Remy & Wicht",
    "wof:placetype":"venue"
},
  "geometry": {"coordinates":[7.1344399452,46.8340988159],"type":"Point"}
}