{
  "type": "Feature",
  "properties": {
    "addr:full":"Hof\u00e4cherstrasse 25 8907 Wettswil. Postfach Z\u00fcrich Z\u00fcrich 8053",
    "addr:housenumber":"25",
    "addr:postcode":"8907 wettswil. postfach;8053",
    "addr:street":"Hofaecherstrasse",
    "iso:country":"CH",
    "sg:address":"Hof\u00e4cherstrasse 25 8907 Wettswil. Postfach",
    "sg:city":"Z\u00fcrich",
    "sg:orig_category":"Architektur U Ingenieurb\u00fcros",
    "sg:phone":"+41 13838253",
    "sg:postcode":"8053",
    "sg:province":"Z\u00fcrich",
    "wof:name":"Ideenfabrik Simmen Patric Produkte; Entwicklung, Design, Patentierung, Vertrieb",
    "wof:placetype":"venue"
},
  "geometry": {"coordinates":[8.473264,47.335964],"type":"Point"}
}