{
  "type": "Feature",
  "properties": {
    "iso:country":"CH",
    "sg:address":"Baumackerstrasse 24 8050 Z\u00fcrich 50 Zust. Postfach",
    "sg:city":"Turbenthal",
    "sg:orig_category":"Unclassifiable Establishments",
    "sg:phone":"+41 52 397 23 23",
    "sg:postcode":"8488",
    "sg:province":"Z\u00fcrich",
    "wof:name":"Quask Ag Edv Programme; Vertrieb, Projektierung, Realisierung",
    "wof:placetype":"venue"
},
  "geometry": {"coordinates":[8.5494403839,47.413520813],"type":"Point"}
}