{
  "type": "Feature",
  "properties": {
    "iso:country":"CH",
    "sg:address":"Kriegstettenstrasse 49",
    "sg:city":"Gerlafingen",
    "sg:orig_category":"Non-Classified Establishments",
    "sg:phone":"+41 81 416 28 28",
    "sg:postcode":"4563",
    "sg:province":"Solothurn",
    "wof:name":"Manubren Sa",
    "wof:placetype":"venue"
},
  "geometry": {"coordinates":[9.8340272903,46.8032302856],"type":"Point"}
}