{
  "type": "Feature",
  "properties": {
    "iso:country":"CH",
    "sg:address":"Oberwilerstrasse 23",
    "sg:city":"Berikon",
    "sg:orig_category":"Reiseb\u00fcros Sprachschulen",
    "sg:postcode":"8965",
    "sg:province":"Aargau",
    "wof:name":"Ails S\u00e9jours Linguistiques",
    "wof:placetype":"venue"
},
  "geometry": {"coordinates":[6.140185833,46.1815414429],"type":"Point"}
}