{
  "type": "Feature",
  "properties": {
    "addr:full":"Lindenstrasse 16 Baar Zug 6340",
    "addr:housenumber":"16",
    "addr:postcode":"6340",
    "addr:street":"Lindenstrasse;Zug",
    "iso:country":"CH",
    "sg:address":"Lindenstrasse 16",
    "sg:city":"Baar",
    "sg:orig_category":"Bauschreinerei Innenausbau",
    "sg:phone":"+41 31 301 02 22",
    "sg:postcode":"6340",
    "sg:province":"Zug",
    "wof:name":"Ringeisen & Co. Ag Schreinerei, Innenausbau, M\u00f6belherstellung",
    "wof:placetype":"venue"
},
  "geometry": {"coordinates":[7.431919,46.95401],"type":"Point"}
}