{
  "type": "Feature",
  "properties": {
    "iso:country":"CH",
    "sg:address":"Badenerstrasse 580",
    "sg:city":"Z\u00fcrich",
    "sg:orig_category":"Detailhandel mit Metallwaren, Anstrichmitteln, Glaswaren, Bau U Heimwerkerbedarf",
    "sg:postcode":"8048",
    "sg:province":"Z\u00fcrich",
    "wof:name":"Technicaps Gmbh",
    "wof:placetype":"venue"
},
  "geometry": {"coordinates":[9.0447759628,47.4117202759],"type":"Point"}
}