{
  "type": "Feature",
  "properties": {
    "iso:country":"CH",
    "sg:address":"Obsteinenweg 1",
    "sg:city":"Villigen",
    "sg:orig_category":"Nationale Postdienste",
    "sg:phone":"+41 56 284 12 01",
    "sg:postcode":"5234",
    "sg:province":"Aargau",
    "wof:name":"Die Schweizerische Post",
    "wof:placetype":"venue"
},
  "geometry": {"coordinates":[8.2154245377,47.5228614807],"type":"Point"}
}