{
  "type": "Feature",
  "properties": {
    "iso:country":"CH",
    "sg:address":"1661",
    "sg:city":"P\u00e2quier-montbarry",
    "sg:orig_category":"Fahrschulen, Flugschulen",
    "sg:phone":"+41 79 449 05 35",
    "sg:postcode":"1661",
    "sg:province":"Fribourg",
    "wof:name":"Jean-marie Surchat Auto-\u00e9cole",
    "wof:placetype":"venue"
},
  "geometry": {"coordinates":[6.9174199104,46.6955718994],"type":"Point"}
}