{
  "type": "Feature",
  "properties": {
    "iso:country":"CH",
    "sg:address":"Bernstrasse 3",
    "sg:city":"Nidau",
    "sg:orig_category":"Detailhandel mit elektrischen Haushaltsger\u00e4ten Herstellung von sonstigen Maschinen f\u00fcr unspezifische",
    "sg:phone":"+41 32 361 16 50",
    "sg:postcode":"2560",
    "sg:province":"Bern",
    "wof:name":"Aebi Industrievertretungen",
    "wof:placetype":"venue"
},
  "geometry": {"coordinates":[7.2428708076,47.1277542114],"type":"Point"}
}