{
  "type": "Feature",
  "properties": {
    "iso:country":"CH",
    "sg:address":"Reigoldswilerstrasse 6",
    "sg:city":"Liedertswil",
    "sg:orig_category":"G\u00fcterbef\u00f6rderung im Strassenverkehr Sonstige Kurierdienste",
    "sg:postcode":"4436",
    "sg:province":"Basel-Landschaft",
    "wof:name":"Ryser Transport Express",
    "wof:placetype":"venue"
},
  "geometry": {"coordinates":[7.7168722153,47.3916549683],"type":"Point"}
}