{
  "type": "Feature",
  "properties": {
    "iso:country":"CH",
    "sg:address":"Oetwilerstrasse 4",
    "sg:city":"Dietikon",
    "sg:orig_category":"Architektur U Ingenieurb\u00fcros Architekturb\u00fcros",
    "sg:phone":"+41 17408182",
    "sg:postcode":"8953",
    "sg:province":"Z\u00fcrich",
    "wof:name":"Universe, Architecture And Engineering Ltd",
    "wof:placetype":"venue"
},
  "geometry": {"coordinates":[8.397585,47.406567],"type":"Point"}
}