{
  "type": "Feature",
  "properties": {
    "iso:country":"CH",
    "sg:address":"Affanderweg 22",
    "sg:city":"W\u00fcrenlingen",
    "sg:orig_category":"Oberfl\u00e4chenveredlung U W\u00e4rmebehandlung",
    "sg:phone":"+41 56 281 25 80",
    "sg:postcode":"5303",
    "sg:province":"Aargau",
    "wof:name":"Pan San Nord-west Ag",
    "wof:placetype":"venue"
},
  "geometry": {"coordinates":[8.2513303757,47.5332183838],"type":"Point"}
}