{
  "type": "Feature",
  "properties": {
    "iso:country":"CH",
    "sg:address":"Alleestrasse 38",
    "sg:city":"Romanshorn",
    "sg:orig_category":"Detailhandel mit Uhren U Schmuck Herstellung von Schmuck, Gold U Silberschmiedwaren",
    "sg:phone":"+41 71 463 36 12",
    "sg:postcode":"8590",
    "sg:province":"Thurgau",
    "wof:name":"Z\u00fcrcher W. Goldschmied",
    "wof:placetype":"venue"
},
  "geometry": {"coordinates":[9.3776769638,47.5647087097],"type":"Point"}
}