{
  "type": "Feature",
  "properties": {
    "iso:country":"CH",
    "sg:address":"2560",
    "sg:city":"Nidau",
    "sg:orig_category":"Primarschulen",
    "sg:phone":"+41 61 711 70 83",
    "sg:postcode":"2560",
    "sg:province":"Bern",
    "wof:name":"Primarschule Weihermatt",
    "wof:placetype":"venue"
},
  "geometry": {"coordinates":[7.5914649963,47.4976997375],"type":"Point"}
}