{
  "type": "Feature",
  "properties": {
    "iso:country":"CH",
    "sg:address":"Massari Via Dei",
    "sg:city":"Morcote",
    "sg:orig_category":"K\u00fcnstlerische U schriftstellerische T\u00e4tigkeiten U Darbietungen",
    "sg:postcode":"6922",
    "sg:province":"Ticino",
    "wof:name":"Papa Gabriele E Annick",
    "wof:placetype":"venue"
},
  "geometry": {"coordinates":[8.9170398712,45.9230918884],"type":"Point"}
}