{
  "type": "Feature",
  "properties": {
    "addr:full":"Universit\u00e4tstrasse 29 Z\u00fcrich Z\u00fcrich 8006",
    "addr:housenumber":"29",
    "addr:postcode":"8006",
    "addr:street":"Universitaetstrasse",
    "iso:country":"CH",
    "sg:address":"Universit\u00e4tstrasse 29",
    "sg:city":"Z\u00fcrich",
    "sg:orig_category":"Detailhandel mit Brillen U anderen Sehhilfen",
    "sg:phone":"+41 12613696",
    "sg:postcode":"8006",
    "sg:province":"Z\u00fcrich",
    "wof:name":"Alfred Biefer Optikergesch\u00e4ft",
    "wof:placetype":"venue"
},
  "geometry": {"coordinates":[8.54794,47.379311],"type":"Point"}
}