{
  "type": "Feature",
  "properties": {
    "iso:country":"CH",
    "sg:address":"Quadratscha 18",
    "sg:city":"Samedan",
    "sg:orig_category":"Allgemeinbildende weiterf\u00fchrende Schulen Bezirks, Sekundar, Realschulen, Oberstufe der Primarschulen",
    "sg:phone":"+41 22 751 18 61",
    "sg:postcode":"7503",
    "sg:province":"Graubunden",
    "wof:name":"Association Du Coll\u00e8ge Saint-louis",
    "wof:placetype":"venue"
},
  "geometry": {"coordinates":[6.231987,46.257145],"type":"Point"}
}