{
  "type": "Feature",
  "properties": {
    "iso:country":"CH",
    "sg:address":"9466",
    "sg:city":"Sennwald",
    "sg:orig_category":"Vereine Musik/Blasmusik",
    "sg:phone":"+41 81 757 13 50",
    "sg:postcode":"9466",
    "sg:province":"St. Gallen",
    "wof:name":"Musikgesellschaft",
    "wof:placetype":"venue"
},
  "geometry": {"coordinates":[9.5036201477,47.2606582642],"type":"Point"}
}