{
  "type": "Feature",
  "properties": {
    "iso:country":"CH",
    "sg:address":"Chalet Efeu",
    "sg:city":"Gr\u00e4chen",
    "sg:orig_category":"Detailhandel mit elektrischen Haushalts, Radio U Fernsehger\u00e4ten ohne ausgepr\u00e4gten Schwerpunkt",
    "sg:phone":"+41 27 956 13 47",
    "sg:postcode":"3925",
    "sg:province":"Valais",
    "wof:name":"Karl Brigger Elektroapparate",
    "wof:placetype":"venue"
},
  "geometry": {"coordinates":[7.8392400742,46.1961631775],"type":"Point"}
}