{
  "type": "Feature",
  "properties": {
    "iso:country":"CH",
    "sg:address":"Burgstrasse 2 3600 Thun. Postfach",
    "sg:city":"Thun",
    "sg:orig_category":"Detailhandel mit Bekleidung",
    "sg:postcode":"3600",
    "sg:province":"Bern",
    "wof:name":"Okey Discount, Marko Ivankovic",
    "wof:placetype":"venue"
},
  "geometry": {"coordinates":[7.632331,46.759407],"type":"Point"}
}