{
  "type": "Feature",
  "properties": {
    "iso:country":"CH",
    "sg:address":"Rh\u00f4ne Rue Du 50",
    "sg:city":"Gen\u00e8ve",
    "sg:orig_category":"Non-Classified Establishments",
    "sg:postcode":"1204",
    "sg:province":"Gen\u00e8ve",
    "wof:name":"Itree Informatik Gmbh",
    "wof:placetype":"venue"
},
  "geometry": {"coordinates":[8.7148303986,50.001701355],"type":"Point"}
}