{
  "type": "Feature",
  "properties": {
    "iso:country":"CH",
    "sg:address":"Via Alla Selva 3",
    "sg:city":"Muzzano",
    "sg:orig_category":"Nationale Postdienste",
    "sg:phone":"+41 91 966 45 05",
    "sg:postcode":"6933",
    "sg:province":"Ticino",
    "wof:name":"La Posta Svizzera",
    "wof:placetype":"venue"
},
  "geometry": {"coordinates":[8.922668457,45.9983024597],"type":"Point"}
}