{
  "type": "Feature",
  "properties": {
    "iso:country":"CH",
    "sg:address":"Claridenstrasse 25 8002 Z\u00fcrich. Postfach 562",
    "sg:city":"Z\u00fcrich",
    "sg:orig_category":"Rechtsberatung Unternehmensberatung",
    "sg:phone":"+41 41 850 01 01",
    "sg:postcode":"8027",
    "sg:province":"Z\u00fcrich",
    "wof:name":"Unternehmensberatung Dr. Ch. M\u00fcller",
    "wof:placetype":"venue"
},
  "geometry": {"coordinates":[8.4324445724,47.0867843628],"type":"Point"}
}