{
  "type": "Feature",
  "properties": {
    "iso:country":"CH",
    "sg:address":"Balsbergweg 13",
    "sg:city":"Kloten",
    "sg:orig_category":"Sonstige Kurierdienste",
    "sg:phone":"+41 18141047",
    "sg:postcode":"8302",
    "sg:province":"Z\u00fcrich",
    "wof:name":"Igd Industrie & Gewerbedienstleistungen, Wegner Klaus",
    "wof:placetype":"venue"
},
  "geometry": {"coordinates":[8.5771312714,47.4436683655],"type":"Point"}
}