{
  "type": "Feature",
  "properties": {
    "iso:country":"CH",
    "sg:address":"Avenue Jacques-martin 11",
    "sg:city":"Ch\u00eane-bougeries",
    "sg:orig_category":"Non-Classified Establishments",
    "sg:postcode":"1224",
    "sg:province":"Gen\u00e8ve",
    "wof:name":"Simonin Philippe",
    "wof:placetype":"venue"
},
  "geometry": {"coordinates":[6.181371212,46.196811676],"type":"Point"}
}