{
  "type": "Feature",
  "properties": {
    "iso:country":"CH",
    "sg:address":"Route De Cornol 79",
    "sg:city":"Mi\u00e9court",
    "sg:orig_category":"Organisationen des Gesundheitswesen",
    "sg:phone":"+41 32 462 33 14",
    "sg:postcode":"2946",
    "sg:province":"Jura",
    "wof:name":"St\u00e9 Des Samaritains",
    "wof:placetype":"venue"
},
  "geometry": {"coordinates":[7.1735630035,47.4259796143],"type":"Point"}
}