{
  "type": "Feature",
  "properties": {
    "addr:full":"Rue Mi\u00e9ville 8 2105 Travers Case Postale 76 Travers Neuch\u00e2tel 2105",
    "addr:housenumber":"8;76",
    "addr:postcode":"2105;2105",
    "addr:street":"Rue Mie\u0301Ville;Travers Case Postale;Neucha\u0302Tel",
    "iso:country":"CH",
    "sg:address":"Rue Mi\u00e9ville 8 2105 Travers Case Postale 76",
    "sg:city":"Travers",
    "sg:orig_category":"Detailhandel mit B\u00fcchern Detailhandel mit B\u00fcchern, Zeitungen, Schreib U Papeteriewaren",
    "sg:phone":"+41 32 863 15 74",
    "sg:postcode":"2105",
    "sg:province":"Neuch\u00e2tel",
    "wof:name":"Papeterie Diana Sa",
    "wof:placetype":"venue"
},
  "geometry": {"coordinates":[6.675019,46.93993],"type":"Point"}
}