{
  "type": "Feature",
  "properties": {
    "iso:country":"CH",
    "sg:address":"Birkenstrasse 22",
    "sg:city":"Br\u00fcttisellen",
    "sg:orig_category":"Detailhandel mit Radio U Fernsehger\u00e4ten Detailhandel mit fotografischen Artikeln",
    "sg:phone":"+41 61 951 20 23",
    "sg:postcode":"8306",
    "sg:province":"Z\u00fcrich",
    "wof:name":"Josef Beierer Foto-studio 58",
    "wof:placetype":"venue"
},
  "geometry": {"coordinates":[7.748860836,47.3949890137],"type":"Point"}
}