{
  "type": "Feature",
  "properties": {
    "iso:country":"CH",
    "sg:address":"Birchstrasse 151",
    "sg:city":"Oberhasli",
    "sg:orig_category":"Malerei",
    "sg:phone":"+41 18503289",
    "sg:postcode":"8156",
    "sg:province":"Z\u00fcrich",
    "wof:name":"Hans Zuberb\u00fchler Malergesch\u00e4ft",
    "wof:placetype":"venue"
},
  "geometry": {"coordinates":[8.5000619888,47.465511322],"type":"Point"}
}