{
  "type": "Feature",
  "properties": {
    "iso:country":"CH",
    "sg:address":"Waldeckstrasse 29",
    "sg:city":"Ostermundigen",
    "sg:orig_category":"Detailhandel mit M\u00f6beln Innendekorationsateliers",
    "sg:phone":"+41 79 354 70 46",
    "sg:postcode":"3072",
    "sg:province":"Bern",
    "wof:name":"Bernhard Franz M\u00f6belgesch\u00e4ft",
    "wof:placetype":"venue"
},
  "geometry": {"coordinates":[7.4795789719,46.9555130005],"type":"Point"}
}