{
  "type": "Feature",
  "properties": {
    "iso:country":"CH",
    "sg:address":"Rosenbergstrasse 4",
    "sg:city":"W\u00e4denswil",
    "sg:orig_category":"Vereine Gesang",
    "sg:phone":"+41 17803095",
    "sg:postcode":"8820",
    "sg:province":"Z\u00fcrich",
    "wof:name":"Gemischter Chor Der Evang.-methodistischen Kirche",
    "wof:placetype":"venue"
},
  "geometry": {"coordinates":[8.6691493988,47.229549408],"type":"Point"}
}