{
  "type": "Feature",
  "properties": {
    "iso:country":"CH",
    "sg:address":"Ch. De Chamblioux 80 1762 Givisiez. Postfach",
    "sg:city":"Daillettes",
    "sg:orig_category":"Handels-H\u00e4user U Gesellschaften",
    "sg:postcode":"1700",
    "sg:province":"Fribourg",
    "wof:name":"Binz Michel",
    "wof:placetype":"venue"
},
  "geometry": {"coordinates":[7.131072998,46.8139228821],"type":"Point"}
}