{
  "type": "Feature",
  "properties": {
    "addr:full":"Tribunal-f\u00e9d\u00e9ral Av. Du 7 1005 Lausanne Case Postale Lausanne Vaud 1003",
    "addr:postcode":"1005;postale lausanne;1003",
    "addr:street":"Tribunal-Fe\u0301De\u0301Ral Av. Du 7",
    "iso:country":"CH",
    "sg:address":"Tribunal-f\u00e9d\u00e9ral Av. Du 7 1005 Lausanne Case Postale",
    "sg:city":"Lausanne",
    "sg:orig_category":"Bau von Strassen, Sportanlagen U Bahnverkehrsstrecken",
    "sg:postcode":"1003",
    "sg:province":"Vaud",
    "wof:name":"Travaux Et Routes Sa Travaux De G\u00e9nie Civil, Routes, Ponts, Terrassements Etc",
    "wof:placetype":"venue"
},
  "geometry": {"coordinates":[6.638888,46.520073],"type":"Point"}
}