{
  "type": "Feature",
  "properties": {
    "addr:full":"Rue Des Fontenailles 21 Lausanne Vaud 1007",
    "addr:housenumber":"21",
    "addr:postcode":"1007",
    "addr:street":"Rue Des Fontenailles",
    "iso:country":"CH",
    "sg:address":"Rue Des Fontenailles 21",
    "sg:city":"Lausanne",
    "sg:orig_category":"Bauingenieurb\u00fcros allgemein",
    "sg:phone":"+41 21 616 03 93",
    "sg:postcode":"1007",
    "sg:province":"Vaud",
    "wof:name":"Jean-fran\u00e7ois K\u00e4lin Bureau D'ing\u00e9nieur",
    "wof:placetype":"venue"
},
  "geometry": {"coordinates":[6.624228,46.511127],"type":"Point"}
}