{
  "type": "Feature",
  "properties": {
    "iso:country":"CH",
    "sg:address":"Les Masses",
    "sg:city":"H\u00e9r\u00e9mence",
    "sg:orig_category":"Oberfl\u00e4chenveredlung U W\u00e4rmebehandlung",
    "sg:postcode":"1987",
    "sg:province":"Valais",
    "wof:name":"A & T Tectra Ag",
    "wof:placetype":"venue"
},
  "geometry": {"coordinates":[7.3978528976,46.1791038513],"type":"Point"}
}