{
  "type": "Feature",
  "properties": {
    "iso:country":"CH",
    "sg:address":"Pierre Rue Saint- 18 1700 Freiburg Case Postale 751",
    "sg:city":"Freiburg",
    "sg:orig_category":"Non-Classified Establishments",
    "sg:phone":"+41 26 347 26 10",
    "sg:postcode":"1700",
    "sg:province":"Fribourg",
    "wof:name":"Gestion Et Participations Financi\u00e8res Sa",
    "wof:placetype":"venue"
},
  "geometry": {"coordinates":[7.1558661461,46.8040313721],"type":"Point"}
}