{
  "type": "Feature",
  "properties": {
    "iso:country":"CH",
    "sg:address":"Br\u00fcggmoosstrasse 4",
    "sg:city":"R\u00fcttenen",
    "sg:orig_category":"Hoch U Tiefbau",
    "sg:phone":"+41 32 622 97 61",
    "sg:postcode":"4522",
    "sg:province":"Solothurn",
    "wof:name":"Franz Von B\u00fcren Baugesch\u00e4ft",
    "wof:placetype":"venue"
},
  "geometry": {"coordinates":[7.5307159424,47.2270736694],"type":"Point"}
}