{
  "type": "Feature",
  "properties": {
    "iso:country":"CH",
    "sg:address":"Niederbleiken 109",
    "sg:city":"Bleiken",
    "sg:orig_category":"Dachdeckerei Zimmerei, Dachdeckerei, Bauspenglerei U Abdichtung",
    "sg:phone":"+41 79 218 88 49",
    "sg:postcode":"3674",
    "sg:province":"Bern",
    "wof:name":"Graf Bedachungen Ag",
    "wof:placetype":"venue"
},
  "geometry": {"coordinates":[7.633068,46.814186],"type":"Point"}
}