{
  "type": "Feature",
  "properties": {
    "iso:country":"CH",
    "sg:address":"B\u00e4lliz 48 3600 Thun. Postfach 1376",
    "sg:city":"Thun",
    "sg:orig_category":"Versicherungen Generalagenturen",
    "sg:phone":"+41 33 225 33 33",
    "sg:postcode":"3601",
    "sg:province":"Bern",
    "wof:name":"La Suisse Versicherungen Generalagentur",
    "wof:placetype":"venue"
},
  "geometry": {"coordinates":[7.6276860237,46.7580795288],"type":"Point"}
}