{
  "type": "Feature",
  "properties": {
    "iso:country":"CH",
    "sg:address":"Affolternstrasse 107",
    "sg:city":"Z\u00fcrich",
    "sg:orig_category":"Rechtsberatung Verm\u00f6gensverwaltung",
    "sg:phone":"+41 71 385 69 49",
    "sg:postcode":"8050",
    "sg:province":"Z\u00fcrich",
    "wof:name":"Manfred S\u00fcess Rechts-& Treuhandb\u00fcro",
    "wof:placetype":"venue"
},
  "geometry": {"coordinates":[9.2488908768,47.4135856628],"type":"Point"}
}