{
  "type": "Feature",
  "properties": {
    "addr:full":"Kornfeldweg 5 Baden Aargau 5400",
    "addr:housenumber":"5",
    "addr:postcode":"5400",
    "addr:street":"Kornfeldweg",
    "iso:country":"CH",
    "sg:address":"Kornfeldweg 5",
    "sg:city":"Baden",
    "sg:classifiers":[
        {
            "category":"Professional",
            "subcategory":"Advertising",
            "type":"Services"
        }
    ],
    "sg:phone":"+41 71 223 47 71",
    "sg:postcode":"5400",
    "sg:province":"Aargau",
    "sg:tags":[
        "poster"
    ],
    "wof:name":"Display-team Dt Ag",
    "wof:placetype":"venue"
},
  "geometry": {"coordinates":[9.366695,47.416546],"type":"Point"}
}