{
  "type": "Feature",
  "properties": {
    "iso:country":"CH",
    "sg:address":"Bettlachstr. 8",
    "sg:city":"Grenchen",
    "sg:classifiers":[
        {
            "category":"Wholesale",
            "subcategory":"Machinery & Supplies",
            "type":"Manufacturing & Wholesale Goods"
        }
    ],
    "sg:phone":"+41 32 652 53 01",
    "sg:postcode":"2540",
    "sg:province":"Solothurn",
    "sg:tags":[
        "equipment",
        "equipement",
        "precision",
        "timekeeping"
    ],
    "wof:name":"Movado Watch Company Sa",
    "wof:placetype":"venue"
},
  "geometry": {"coordinates":[7.3967862129,47.1927223206],"type":"Point"}
}