{
  "type": "Feature",
  "properties": {
    "iso:country":"CH",
    "sg:address":"Grand-rue 21",
    "sg:city":"Porrentruy",
    "sg:orig_category":"Detailhandel mit Damenbekleidung Detailhandel mit Herrenbekleidung",
    "sg:phone":"+41 32 466 13 41",
    "sg:postcode":"2900",
    "sg:province":"Jura",
    "wof:name":"Ernest M\u00fcller Confection Textiles",
    "wof:placetype":"venue"
},
  "geometry": {"coordinates":[7.0758662224,47.4157981873],"type":"Point"}
}