{
  "type": "Feature",
  "properties": {
    "iso:country":"CH",
    "sg:address":"Morgenstrasse 129",
    "sg:city":"Bern",
    "sg:orig_category":"Herstellung von sonstigen elektrischen Ausr\u00fcstungen Unternehmensberatung",
    "sg:phone":"+41 31 994 20 05",
    "sg:postcode":"3018",
    "sg:province":"Bern",
    "wof:name":"Walter Beat Elektronik Ag",
    "wof:placetype":"venue"
},
  "geometry": {"coordinates":[7.3894209862,46.9346656799],"type":"Point"}
}