{
  "type": "Feature",
  "properties": {
    "iso:country":"CH",
    "sg:address":"Grundstrasse 75",
    "sg:city":"St\u00e4fa",
    "sg:orig_category":"Allgemeiner Hoch U Tiefbau",
    "sg:phone":"+41 19266554",
    "sg:postcode":"8712",
    "sg:province":"Z\u00fcrich",
    "wof:name":"Getibau Ag",
    "wof:placetype":"venue"
},
  "geometry": {"coordinates":[8.727136,47.24435],"type":"Point"}
}