{
  "type": "Feature",
  "properties": {
    "iso:country":"CH",
    "sg:address":"Talstrasse 84 4144 Arlesheim. Postfach 648",
    "sg:city":"Arlesheim",
    "sg:orig_category":"Grosshandel mit Getr\u00e4nken Grosshandel mit Wein U Spirituosen",
    "sg:phone":"+41 61 303 06 15",
    "sg:postcode":"4144",
    "sg:province":"Basel-Landschaft",
    "wof:name":"Theodor Rietschi Ag",
    "wof:placetype":"venue"
},
  "geometry": {"coordinates":[7.6091899872,47.4987258911],"type":"Point"}
}