{
  "type": "Feature",
  "properties": {
    "iso:country":"CH",
    "sg:address":"Baarerstrasse 112",
    "sg:city":"Zug",
    "sg:orig_category":"Herstellung von Bergwerks U Baumaschinen",
    "sg:phone":"+41 55 241 12 43",
    "sg:postcode":"6300",
    "sg:province":"Zug",
    "wof:name":"Schmid Reinhard",
    "wof:placetype":"venue"
},
  "geometry": {"coordinates":[8.8686981201,47.254070282],"type":"Point"}
}