{
  "type": "Feature",
  "properties": {
    "iso:country":"CH",
    "sg:address":"Kolbenacker 4 8052 Z\u00fcrich. Postfach 121",
    "sg:city":"Z\u00fcrich",
    "sg:orig_category":"Detailhandel mit Teppichen Verlegen von Fussboden",
    "sg:phone":"+41 41 870 52 61",
    "sg:postcode":"8052",
    "sg:province":"Z\u00fcrich",
    "wof:name":"Peter Albert Bodenbel\u00e4ge",
    "wof:placetype":"venue"
},
  "geometry": {"coordinates":[8.6325397491,46.8797225952],"type":"Point"}
}