{
  "type": "Feature",
  "properties": {
    "iso:country":"CH",
    "sg:address":"Basse-nendaz",
    "sg:city":"Haute-nendaz",
    "sg:orig_category":"G\u00fcterbef\u00f6rderung im Strassenverkehr",
    "sg:postcode":"1997",
    "sg:province":"Valais",
    "wof:name":"Transport Fournier Et Cie Sa",
    "wof:placetype":"venue"
},
  "geometry": {"coordinates":[7.2958369255,46.1869621277],"type":"Point"}
}