{
  "type": "Feature",
  "properties": {
    "iso:country":"CH",
    "sg:address":"Dettenried 56b",
    "sg:city":"Weisslingen",
    "sg:orig_category":"Herstellung von Teilen U Zubeh\u00f6r f\u00fcr Automobile",
    "sg:phone":"+41 17618765",
    "sg:postcode":"8484",
    "sg:province":"Z\u00fcrich",
    "wof:name":"Pz Autozubeh\u00f6r, Paul Zickermann",
    "wof:placetype":"venue"
},
  "geometry": {"coordinates":[8.450050354,47.2830123901],"type":"Point"}
}