{
  "type": "Feature",
  "properties": {
    "iso:country":"CH",
    "sg:address":"Manessestrasse 46",
    "sg:city":"Z\u00fcrich",
    "sg:orig_category":"Herstellung von Teppichen",
    "sg:phone":"+41 14622809",
    "sg:postcode":"8003",
    "sg:province":"Z\u00fcrich",
    "wof:name":"Useini Parkett Gmbh",
    "wof:placetype":"venue"
},
  "geometry": {"coordinates":[8.5231981277,47.3676071167],"type":"Point"}
}