{
  "type": "Feature",
  "properties": {
    "iso:country":"CH",
    "sg:address":"Umfahrungsstrasse 9",
    "sg:city":"Schattdorf",
    "sg:orig_category":"Druck ohne Zeitungsdruck Offsetdruck",
    "sg:phone":"+41 79 434 35 00",
    "sg:postcode":"6467",
    "sg:province":"Uri",
    "wof:name":"Roli Satz Ernst Roland",
    "wof:placetype":"venue"
},
  "geometry": {"coordinates":[8.639752388,46.8559532166],"type":"Point"}
}