{
  "type": "Feature",
  "properties": {
    "iso:country":"CH",
    "sg:address":"Schaffhauserstrasse 128 8152 Glattbrugg. Postfach 3129",
    "sg:city":"Glattbrugg",
    "sg:orig_category":"Geb\u00e4ude, Wohnungsreinigung Reinigungsgewerbe",
    "sg:phone":"+41 18744455",
    "sg:postcode":"8152",
    "sg:province":"Z\u00fcrich",
    "wof:name":"Hatech Reinigungen Ag",
    "wof:placetype":"venue"
},
  "geometry": {"coordinates":[8.5675621033,47.4349250793],"type":"Point"}
}