{
  "type": "Feature",
  "properties": {
    "iso:country":"CH",
    "sg:address":"Usterstrasse 3",
    "sg:city":"D\u00fcbendorf",
    "sg:orig_category":"RESTAURANTS: TEA-ROOMS",
    "sg:postcode":"8600",
    "sg:province":"Z\u00fcrich",
    "wof:name":"Gastro - Ideen - Gmbh",
    "wof:placetype":"venue"
},
  "geometry": {"coordinates":[8.6189699173,47.3972625732],"type":"Point"}
}