{
  "type": "Feature",
  "properties": {
    "iso:country":"CH",
    "sg:address":"Bottmingerstrasse 1",
    "sg:city":"Binningen",
    "sg:orig_category":"Unclassifiable Establishments",
    "sg:postcode":"4102",
    "sg:province":"Basel-Landschaft",
    "wof:name":"Hemp Vision B\u00f6sch",
    "wof:placetype":"venue"
},
  "geometry": {"coordinates":[7.5755710602,47.537399292],"type":"Point"}
}