{
  "type": "Feature",
  "properties": {
    "iso:country":"CH",
    "sg:address":"T\u00f6belistrasse 80",
    "sg:city":"D\u00fcrnten",
    "sg:orig_category":"Elektroinstallation",
    "sg:phone":"+41 79 356 30 21",
    "sg:postcode":"8635",
    "sg:province":"Z\u00fcrich",
    "wof:name":"Elektro Jud Ag",
    "wof:placetype":"venue"
},
  "geometry": {"coordinates":[7.5753998756,46.9254264832],"type":"Point"}
}