{
  "type": "Feature",
  "properties": {
    "iso:country":"CH",
    "sg:address":"Quaderstrasse 2",
    "sg:city":"Schaan",
    "sg:orig_category":"Kosmetikinstitute",
    "sg:phone":"+423 232 33 75",
    "sg:postcode":"9494",
    "wof:name":"Margot Gassner Kosmetiksalon Margot",
    "wof:placetype":"venue"
},
  "geometry": {"coordinates":[9.5100498199,47.1609535217],"type":"Point"}
}