{
  "type": "Feature",
  "properties": {
    "iso:country":"CH",
    "sg:address":"Ilgenstrasse 28",
    "sg:city":"St.gallen",
    "sg:orig_category":"Erwachsenenbildung U Unterricht",
    "sg:postcode":"9000",
    "sg:province":"St. Gallen",
    "wof:name":"Keys N'sounds Senn Martin",
    "wof:placetype":"venue"
},
  "geometry": {"coordinates":[9.3598308563,47.41746521],"type":"Point"}
}