{
  "type": "Feature",
  "properties": {
    "iso:country":"CH",
    "sg:address":"4944",
    "sg:city":"Auswil",
    "sg:orig_category":"Haltung von Rindern",
    "sg:postcode":"4944",
    "sg:province":"Bern",
    "wof:name":"Viehzuchtgenossenschaft Auswil Und Umgebung",
    "wof:placetype":"venue"
},
  "geometry": {"coordinates":[7.8385601044,47.135761261],"type":"Point"}
}