{
  "type": "Feature",
  "properties": {
    "iso:country":"CH",
    "sg:address":"Rue De Rive 1",
    "sg:city":"Gen\u00e8ve",
    "sg:orig_category":"Detailhandel mit Uhren U Schmuck",
    "sg:phone":"+41 22 312 03 44",
    "sg:postcode":"1204",
    "sg:province":"Gen\u00e8ve",
    "wof:name":"Van Der Bauwede Bijouterie",
    "wof:placetype":"venue"
},
  "geometry": {"coordinates":[6.150053978,46.2025527954],"type":"Point"}
}