{
  "type": "Feature",
  "properties": {
    "iso:country":"CH",
    "sg:address":"Aarbergstrasse 100",
    "sg:city":"Biel/bienne",
    "sg:orig_category":"Non-Classified Establishments",
    "sg:postcode":"2502",
    "sg:province":"Bern",
    "wof:name":"Casa Shop Sa",
    "wof:placetype":"venue"
},
  "geometry": {"coordinates":[8.9731969833,46.1599578857],"type":"Point"}
}