{
  "type": "Feature",
  "properties": {
    "iso:country":"CH",
    "sg:address":"Frankfurtstr. 60",
    "sg:city":"M\u00fcnchenstein",
    "sg:classifiers":[
        {
            "category":"Transit Center",
            "subcategory":"Freight",
            "type":"Transportation"
        }
    ],
    "sg:phone":"+41 61 337 55 55",
    "sg:postcode":"4142",
    "sg:province":"Basel-Landschaft",
    "sg:tags":[
        "metallurgy",
        "pipe",
        "metalworking",
        "sheet"
    ],
    "wof:name":"Arfa R\u00d6renwerke Ag",
    "wof:placetype":"venue"
},
  "geometry": {"coordinates":[7.6081600189,47.5293502808],"type":"Point"}
}