{
  "type": "Feature",
  "properties": {
    "iso:country":"CH",
    "sg:address":"Rue Du Petit Ch\u00eane 34",
    "sg:city":"Lausanne",
    "sg:classifiers":[
        {
            "category":"Travel",
            "subcategory":"Hotels & Motels",
            "type":"Entertainment"
        }
    ],
    "sg:phone":"+41 21 323 01 31",
    "sg:postcode":"1003",
    "sg:province":"Vaud",
    "sg:tags":[
        "hotels",
        "business",
        "restaurant"
    ],
    "wof:name":"Hotel Alpha Sa",
    "wof:placetype":"venue"
},
  "geometry": {"coordinates":[6.629962,46.518379],"type":"Point"}
}