{
  "type": "Feature",
  "properties": {
    "iso:country":"CH",
    "sg:address":"Via Fossato 2/2a 6512 Giubiasco. Postfach",
    "sg:city":"Giubiasco",
    "sg:orig_category":"Grosshandel mit Textilien",
    "sg:postcode":"6512",
    "sg:province":"Ticino",
    "wof:name":"Mjkasa Sagl",
    "wof:placetype":"venue"
},
  "geometry": {"coordinates":[9.0159606934,46.1805152893],"type":"Point"}
}