{
  "type": "Feature",
  "properties": {
    "iso:country":"CH",
    "sg:address":"Burstwiesenstrasse 47",
    "sg:city":"Greifensee",
    "sg:orig_category":"Herstellung von industriellen Prozesssteuerungsanlagen",
    "sg:phone":"+41 19409960",
    "sg:postcode":"8606",
    "sg:province":"Z\u00fcrich",
    "wof:name":"Brunner H., Cnc Technik",
    "wof:placetype":"venue"
},
  "geometry": {"coordinates":[8.6789646149,47.373134613],"type":"Point"}
}