{
  "type": "Feature",
  "properties": {
    "iso:country":"CH",
    "sg:address":"Dorfstrasse 25 3115 Gerzensee. Postfach 35",
    "sg:city":"Gerzensee",
    "sg:orig_category":"Herstellung von Mess U Kontrollinstrumenten U vorrichtungen Herstellung von Metallerzeugnissen ohne ",
    "sg:phone":"+41 31 781 16 46",
    "sg:postcode":"3115",
    "sg:province":"Bern",
    "wof:name":"Wintion Ag, Analytische Instrumente",
    "wof:placetype":"venue"
},
  "geometry": {"coordinates":[7.5441842079,46.8385772705],"type":"Point"}
}