{
  "type": "Feature",
  "properties": {
    "iso:country":"CH",
    "sg:address":"Im H\u00fcgliacker 12",
    "sg:city":"Binningen",
    "sg:orig_category":"Non-Classified Establishments",
    "sg:postcode":"4102",
    "sg:province":"Basel-Landschaft",
    "wof:name":"Robin Holding Ag",
    "wof:placetype":"venue"
},
  "geometry": {"coordinates":[7.563598156,47.5383911133],"type":"Point"}
}