{
  "type": "Feature",
  "properties": {
    "iso:country":"CH",
    "sg:address":"St. Martinsplatz 4",
    "sg:city":"Chur",
    "sg:classifiers":[
        {
            "category":"Travel",
            "subcategory":"Hotels & Motels",
            "type":"Entertainment"
        }
    ],
    "sg:phone":"+41 81 253 63 33",
    "sg:postcode":"7000",
    "sg:province":"Graubunden",
    "sg:tags":[
        "hotels",
        "mit",
        "restaurant"
    ],
    "wof:name":"Hotel City Chur Ag",
    "wof:placetype":"venue"
},
  "geometry": {"coordinates":[9.5321502686,46.848285675],"type":"Point"}
}