{
  "type": "Feature",
  "properties": {
    "iso:country":"CH",
    "sg:address":"Route Du Jura 73 1700 Freiburg. Postfach",
    "sg:city":"Fribourg",
    "sg:orig_category":"Tankstellen",
    "sg:postcode":"1702",
    "sg:province":"Fribourg",
    "wof:name":"Beno\u00eet Dreyer",
    "wof:placetype":"venue"
},
  "geometry": {"coordinates":[7.1390619278,46.8113975525],"type":"Point"}
}