{
  "type": "Feature",
  "properties": {
    "addr:full":"Scheibenstrasse 58 Bern Bern 3014",
    "addr:housenumber":"58",
    "addr:postcode":"3014",
    "addr:street":"Scheibenstrasse",
    "iso:country":"CH",
    "sg:address":"Scheibenstrasse 58",
    "sg:city":"Bern",
    "sg:orig_category":"DELIMING DEVICES FOR BOILERS, HEAT EXCHANGERS, TANKS",
    "sg:phone":"+41 31 911 44 00",
    "sg:postcode":"3014",
    "sg:province":"Bern",
    "wof:name":"Gygax Entkalkungen Gmbh",
    "wof:placetype":"venue"
},
  "geometry": {"coordinates":[7.451386,46.9646],"type":"Point"}
}