{
  "type": "Feature",
  "properties": {
    "iso:country":"CH",
    "sg:address":"Hochstrasse 63 8044 Z\u00fcrich. Postfach",
    "sg:city":"Z\u00fcrich",
    "sg:orig_category":"Sonstige mit der Informatik verbundene T\u00e4tigkeiten",
    "sg:phone":"+41 12528004",
    "sg:postcode":"8044",
    "sg:province":"Z\u00fcrich",
    "wof:name":"Gehring Computer Support",
    "wof:placetype":"venue"
},
  "geometry": {"coordinates":[8.5557260513,47.3786354065],"type":"Point"}
}