{
  "type": "Feature",
  "properties": {
    "iso:country":"CH",
    "sg:address":"T\u00e4gerhardstr. 110",
    "sg:city":"Wettingen",
    "sg:classifiers":[
        {
            "category":"Manufacturing",
            "subcategory":"Motor Vehicles & Parts",
            "type":"Manufacturing & Wholesale Goods"
        }
    ],
    "sg:phone":"+41 56 438 10 10",
    "sg:postcode":"5430",
    "sg:province":"Aargau",
    "sg:tags":[
        "industrial",
        "motor-cars",
        "-",
        "machine",
        "equipment",
        "engineering",
        "mechanical",
        "transport"
    ],
    "wof:name":"Lufttechnik & Metallbau Ag",
    "wof:placetype":"venue"
},
  "geometry": {"coordinates":[8.3328008652,47.4565734863],"type":"Point"}
}