{
  "type": "Feature",
  "properties": {
    "iso:country":"CH",
    "sg:address":"Via Cantonale 2a",
    "sg:city":"Lugano",
    "sg:orig_category":"Bibliotheken U Archive Wohnheime",
    "sg:phone":"+41 56 664 11 94",
    "sg:postcode":"6900",
    "sg:province":"Ticino",
    "wof:name":"Werk-& Wohnheim Murimoos Bibliothek",
    "wof:placetype":"venue"
},
  "geometry": {"coordinates":[8.34098,47.274239],"type":"Point"}
}