{
  "type": "Feature",
  "properties": {
    "addr:full":"Rue De La Gare 23 Boudry Neuch\u00e2tel 2017",
    "addr:housenumber":"23",
    "addr:postcode":"2017",
    "addr:street":"Rue De La Gare;Neucha\u0302Tel",
    "iso:country":"CH",
    "sg:address":"Rue De La Gare 23",
    "sg:city":"Boudry",
    "sg:orig_category":"Architektur U Ingenieurb\u00fcros",
    "sg:phone":"+41 32 841 42 09",
    "sg:postcode":"2017",
    "sg:province":"Neuch\u00e2tel",
    "wof:name":"Ren\u00e9 Jeanbourquin Bureau Technique",
    "wof:placetype":"venue"
},
  "geometry": {"coordinates":[6.834647,46.955219],"type":"Point"}
}