{
  "type": "Feature",
  "properties": {
    "iso:country":"CH",
    "sg:address":"Hauptstrasse 46 4132 Muttenz. Postfach",
    "sg:city":"Muttenz",
    "sg:orig_category":"Softwareentwicklung U beratung",
    "sg:postcode":"4132",
    "sg:province":"Basel-Landschaft",
    "wof:name":"All - It Gmbh",
    "wof:placetype":"venue"
},
  "geometry": {"coordinates":[7.646697998,47.5249977112],"type":"Point"}
}