{
  "type": "Feature",
  "properties": {
    "iso:country":"CH",
    "sg:address":"Dorfstrasse 6",
    "sg:city":"Brittnau",
    "sg:classifiers":[
        {
            "category":"Travel",
            "subcategory":"Hotels & Motels",
            "type":"Entertainment"
        }
    ],
    "sg:phone":"+41 33 783 11 58",
    "sg:postcode":"4805",
    "sg:province":"Aargau",
    "sg:tags":[
        "hotels",
        "mit",
        "restaurant"
    ],
    "wof:name":"Hans Heimann",
    "wof:placetype":"venue"
},
  "geometry": {"coordinates":[7.4359397888,46.6566810608],"type":"Point"}
}