{
  "type": "Feature",
  "properties": {
    "iso:country":"CH",
    "sg:address":"Haldenstrasse 24 8967 Widen. Postfach",
    "sg:city":"Widen",
    "sg:orig_category":"Unternehmensberatung",
    "sg:postcode":"8967",
    "sg:province":"Aargau",
    "wof:name":"Brader Consulting",
    "wof:placetype":"venue"
},
  "geometry": {"coordinates":[8.3621530533,47.370639801],"type":"Point"}
}