{
  "type": "Feature",
  "properties": {
    "iso:country":"CH",
    "sg:address":"Unterer Bodenakcer 1 4436 Liedertswil. Postfach",
    "sg:city":"Liedertswil",
    "sg:orig_category":"Instandhaltung U Reparatur von Automobilen",
    "sg:postcode":"4436",
    "sg:province":"Basel-Landschaft",
    "wof:name":"Schmitter Us-cars Garage. Reparaturen An Autos Usw",
    "wof:placetype":"venue"
},
  "geometry": {"coordinates":[7.7176070213,47.3905754089],"type":"Point"}
}