{
  "type": "Feature",
  "properties": {
    "iso:country":"CH",
    "sg:address":"Pilatusstrasse 4 6210 Sursee. Postfach 427",
    "sg:city":"Sursee",
    "sg:orig_category":"Wirtschaftspr\u00fcfung, Steuerberatung U Treuhand",
    "sg:phone":"+41 41 921 28 93",
    "sg:postcode":"6210",
    "sg:province":"Luzern",
    "wof:name":"Felber Treuhand",
    "wof:placetype":"venue"
},
  "geometry": {"coordinates":[8.0968112946,47.171295166],"type":"Point"}
}