{
  "type": "Feature",
  "properties": {
    "iso:country":"CH",
    "sg:address":"Bahnhofstrasse 44 8180 B\u00fclach. Postfach",
    "sg:city":"B\u00fclach",
    "sg:orig_category":"Non-Classified Establishments",
    "sg:postcode":"8180",
    "sg:province":"Z\u00fcrich",
    "wof:name":"Nbt Media Gmbh",
    "wof:placetype":"venue"
},
  "geometry": {"coordinates":[8.5392551422,47.5220451355],"type":"Point"}
}