{
  "type": "Feature",
  "properties": {
    "iso:country":"CH",
    "sg:address":"Kaffeegasse 1",
    "sg:city":"Altnau",
    "sg:orig_category":"RESTAURANTS: TEA-ROOMS",
    "sg:phone":"+41 71 695 18 47",
    "sg:postcode":"8595",
    "sg:province":"Thurgau",
    "wof:name":"Urs Wilhelm",
    "wof:placetype":"venue"
},
  "geometry": {"coordinates":[9.2572050095,47.6075553894],"type":"Point"}
}