{
  "type": "Feature",
  "properties": {
    "iso:country":"CH",
    "sg:address":"Forchstrasse 45 8032 Z\u00fcrich. Postfach",
    "sg:city":"Z\u00fcrich",
    "sg:classifiers":[
        {
            "category":"Professional",
            "subcategory":"Employment Agencies",
            "type":"Services"
        }
    ],
    "sg:phone":"+41 13866767",
    "sg:postcode":"8032",
    "sg:province":"Z\u00fcrich",
    "sg:tags":[
        "personal",
        "u",
        "stellenvermittlung"
    ],
    "wof:name":"Ors Service Ag",
    "wof:placetype":"venue"
},
  "geometry": {"coordinates":[8.5581607819,47.3629264832],"type":"Point"}
}