{
  "type": "Feature",
  "properties": {
    "iso:country":"CH",
    "sg:address":"Sonnhaldenstrasse 14 8032 Z\u00fcrich. Postfach",
    "sg:city":"Z\u00fcrich",
    "sg:orig_category":"Werbeagenturen",
    "sg:phone":"+41 12520334",
    "sg:postcode":"8030",
    "wof:name":"Communication Unlimited Ag",
    "wof:placetype":"venue"
},
  "geometry": {"coordinates":[8.5631437302,47.3670578003],"type":"Point"}
}