{
  "type": "Feature",
  "properties": {
    "iso:country":"CH",
    "sg:address":"Kauffmannweg 5",
    "sg:city":"Luzern",
    "sg:orig_category":"Cutlery, Gold Plated",
    "sg:phone":"+41 41 210 54 82",
    "sg:postcode":"6003",
    "sg:province":"Luzern",
    "wof:name":"Armando Benedetti",
    "wof:placetype":"venue"
},
  "geometry": {"coordinates":[8.305538,47.047878],"type":"Point"}
}