{
  "type": "Feature",
  "properties": {
    "iso:country":"CH",
    "sg:address":"Gewerbegasse 115a",
    "sg:city":"Detligen",
    "sg:orig_category":"Datenverarbeitungsdienste",
    "sg:phone":"+41 31 825 60 10",
    "sg:postcode":"3036",
    "sg:province":"Bern",
    "wof:name":"Stefan Hunziker Edv-dienstleistungen",
    "wof:placetype":"venue"
},
  "geometry": {"coordinates":[7.272964,47.000801],"type":"Point"}
}