{
  "type": "Feature",
  "properties": {
    "iso:country":"CH",
    "sg:address":"Chemin De La Fauvette",
    "sg:city":"F\u00e9chy",
    "sg:orig_category":"Sonstige mit der Informatik verbundene T\u00e4tigkeiten",
    "sg:postcode":"1173",
    "sg:province":"Vaud",
    "wof:name":"Anderdell S\u00e0rl",
    "wof:placetype":"venue"
},
  "geometry": {"coordinates":[6.3742098808,46.4779815674],"type":"Point"}
}