{
  "type": "Feature",
  "properties": {
    "iso:country":"CH",
    "sg:address":"D\u00f6rfli 4",
    "sg:city":"Wolfenschiessen",
    "sg:orig_category":"Non-Classified Establishments",
    "sg:postcode":"6386",
    "sg:province":"Nidwalden",
    "wof:name":"Hotel-gasthaus Ochsen Gmbh",
    "wof:placetype":"venue"
},
  "geometry": {"coordinates":[8.3902015686,46.8967399597],"type":"Point"}
}