{
  "type": "Feature",
  "properties": {
    "iso:country":"CH",
    "sg:address":"Bahnhofstrasse 83 8803 R\u00fcschlikon. Postfach",
    "sg:city":"R\u00fcschlikon",
    "sg:orig_category":"Detailhandel mit Brot, Back U S\u00fcsswaren",
    "sg:phone":"+41 17240277",
    "sg:postcode":"8803",
    "sg:province":"Z\u00fcrich",
    "wof:name":"Aeschlimann Peter",
    "wof:placetype":"venue"
},
  "geometry": {"coordinates":[8.557913,47.304073],"type":"Point"}
}