{
  "type": "Feature",
  "properties": {
    "iso:country":"CH",
    "sg:address":"Rue De L'avenier 11 1950 Sion Case Postale 62",
    "sg:city":"Sion",
    "sg:orig_category":"Pensionskassen",
    "sg:phone":"+41 27 327 32 50",
    "sg:postcode":"1951",
    "sg:province":"Valais",
    "wof:name":"Assoc.valaisanne Des Entrepreneurs Ave",
    "wof:placetype":"venue"
},
  "geometry": {"coordinates":[7.2931518555,46.2272949219],"type":"Point"}
}