{
  "type": "Feature",
  "properties": {
    "iso:country":"CH",
    "sg:address":"San Gottardo Corso 106",
    "sg:city":"Chiasso",
    "sg:orig_category":"Herstellung von Elektrizit\u00e4tsverteilungs U schalteinrichtungen",
    "sg:phone":"+41 91 683 07 09",
    "sg:postcode":"6830",
    "sg:province":"Ticino",
    "wof:name":"Reglasystem Sagl",
    "wof:placetype":"venue"
},
  "geometry": {"coordinates":[9.0221986771,45.8381347656],"type":"Point"}
}