{
  "type": "Feature",
  "properties": {
    "iso:country":"CH",
    "sg:address":"Hirselenstrasse 3",
    "sg:city":"Dietwil",
    "sg:orig_category":"Herstellung von Teppichen Verlegen von Fussboden",
    "sg:phone":"+41 41 787 38 37",
    "sg:postcode":"6042",
    "sg:province":"Aargau",
    "wof:name":"Thomas Meier Gmbh",
    "wof:placetype":"venue"
},
  "geometry": {"coordinates":[8.3917741776,47.1503868103],"type":"Point"}
}