{
  "type": "Feature",
  "properties": {
    "iso:country":"CH",
    "sg:address":"Gattikonerstrasse 5",
    "sg:city":"Thalwil",
    "sg:orig_category":"Advokaturb\u00fcros",
    "sg:phone":"+41 14222088",
    "sg:postcode":"8800",
    "sg:province":"Z\u00fcrich",
    "wof:name":"Elmar Breitenmoser Advokaturb\u00fcro",
    "wof:placetype":"venue"
},
  "geometry": {"coordinates":[8.55733,47.287983],"type":"Point"}
}