{
  "type": "Feature",
  "properties": {
    "iso:country":"CH",
    "sg:address":"Oberdorf 2",
    "sg:city":"Obermumpf",
    "sg:orig_category":"Detailhandel mit Waren verschiedener Art, Hauptrichtung Nahrungsmittel",
    "sg:postcode":"4324",
    "sg:province":"Aargau",
    "wof:name":"Produktivgenossenschaft Obermumpf P.g.o",
    "wof:placetype":"venue"
},
  "geometry": {"coordinates":[7.9366340637,47.5306167603],"type":"Point"}
}