{
  "type": "Feature",
  "properties": {
    "iso:country":"CH",
    "sg:address":"Gesellschaftsstrasse 70",
    "sg:city":"Bern",
    "sg:orig_category":"Detailhandel mit Waren verschiedener Art, Hauptrichtung Nahrungsmittel Wein Detailhandel",
    "sg:phone":"+41 31 301 59 30",
    "sg:postcode":"3012",
    "sg:province":"Bern",
    "wof:name":"Rocco Venusia Bellusci Italienische Lebensmittel",
    "wof:placetype":"venue"
},
  "geometry": {"coordinates":[7.4324288368,46.9550094604],"type":"Point"}
}