{
  "type": "Feature",
  "properties": {
    "iso:country":"CH",
    "sg:address":"Industriestrasse 11",
    "sg:city":"Rotkreuz",
    "sg:classifiers":[
        {
            "category":"Organizations",
            "subcategory":"Professional Association",
            "type":"Services"
        }
    ],
    "sg:phone":"+41 41 790 59 01",
    "sg:postcode":"6343",
    "sg:province":"Zug",
    "sg:tags":[
        "holdings",
        "administration",
        "central"
    ],
    "wof:name":"Cardo Door (international) Ag",
    "wof:placetype":"venue"
},
  "geometry": {"coordinates":[8.4310493469,47.1514205933],"type":"Point"}
}