{
  "type": "Feature",
  "properties": {
    "iso:country":"CH",
    "sg:address":"Hauptstrasse 63 9400 Rorschach. Postfach",
    "sg:city":"Rorschach",
    "sg:orig_category":"Verkehrs- and Tourismusb\u00fcros",
    "sg:phone":"+41 71 841 70 34",
    "sg:postcode":"9401",
    "sg:province":"St. Gallen",
    "wof:name":"Verkehrsverein Verkehrsb\u00fcro",
    "wof:placetype":"venue"
},
  "geometry": {"coordinates":[9.4927864075,47.4782905579],"type":"Point"}
}