{
  "type": "Feature",
  "properties": {
    "iso:country":"CH",
    "sg:address":"Vy-d'etra 76",
    "sg:city":"Neuch\u00e2tel",
    "sg:classifiers":[
        {
            "category":"Manufacturing",
            "subcategory":"Tools & Machinery",
            "type":"Manufacturing & Wholesale Goods"
        }
    ],
    "sg:phone":"+41 32 753 87 44",
    "sg:postcode":"2000",
    "sg:province":"Neuch\u00e2tel",
    "sg:tags":[
        "machine",
        "cnc"
    ],
    "wof:name":"Jb Engineering Sa",
    "wof:placetype":"venue"
},
  "geometry": {"coordinates":[6.94145,46.982681],"type":"Point"}
}