{
  "type": "Feature",
  "properties": {
    "iso:country":"CH",
    "sg:address":"Th\u00fcrn 62 9554 T\u00e4gerschen. Postfach",
    "sg:city":"T\u00e4gerschen",
    "sg:orig_category":"Detailhandel mit elektrischen Haushalts-,Radio U Fernsehger\u00e4ten sowie Musikinstrumenten",
    "sg:postcode":"9554",
    "sg:province":"Thurgau",
    "wof:name":"Home Digi Vision, Mascaro",
    "wof:placetype":"venue"
},
  "geometry": {"coordinates":[8.8084897995,47.3316688538],"type":"Point"}
}