{
  "type": "Feature",
  "properties": {
    "iso:country":"CH",
    "sg:address":"Weiacherstrasse 50",
    "sg:city":"Pfungen",
    "sg:orig_category":"Blumen U Zierpflanzenbau Detailhandel mit Blumen U Pflanzen",
    "sg:phone":"+41 52 315 15 88",
    "sg:postcode":"8422",
    "sg:province":"Z\u00fcrich",
    "wof:name":"Gottfried Fischer",
    "wof:placetype":"venue"
},
  "geometry": {"coordinates":[8.636176,47.517162],"type":"Point"}
}