{
  "type": "Feature",
  "properties": {
    "iso:country":"CH",
    "sg:address":"Viktor Kaufmann-strasse 3",
    "sg:city":"Derendingen",
    "sg:orig_category":"Primarschulen",
    "sg:phone":"+41 32 675 21 45",
    "sg:postcode":"4552",
    "sg:province":"Solothurn",
    "wof:name":"Primarschule Steinmatt",
    "wof:placetype":"venue"
},
  "geometry": {"coordinates":[7.586909771,47.1977615356],"type":"Point"}
}