{
  "type": "Feature",
  "properties": {
    "iso:country":"CH",
    "sg:address":"Ruggh\u00f6lzli 2 5453 Remetschwil. Postfach",
    "sg:city":"Remetschwil",
    "sg:orig_category":"Sonstige mit der Informatik verbundene T\u00e4tigkeiten",
    "sg:postcode":"5453",
    "sg:province":"Aargau",
    "wof:name":"Zapcom Zappacosta Communication Support U. Schulungen, Informatikl\u00f6sungen Im Bereich Internet",
    "wof:placetype":"venue"
},
  "geometry": {"coordinates":[8.3134613037,47.4113464355],"type":"Point"}
}