{
  "type": "Feature",
  "properties": {
    "iso:country":"CH",
    "sg:address":"Ilgenweidstrasse 6",
    "sg:city":"Einsiedeln",
    "sg:classifiers":[
        {
            "category":"Travel",
            "subcategory":"Hotels & Motels",
            "type":"Entertainment"
        }
    ],
    "sg:phone":"+41 55 412 66 06",
    "sg:postcode":"8840",
    "sg:province":"Schwyz",
    "sg:tags":[
        "hotels",
        "mit",
        "restaurant"
    ],
    "wof:name":"Koch-willi Marie-theres, Hotel Katharinahof",
    "wof:placetype":"venue"
},
  "geometry": {"coordinates":[8.7499952316,47.1258544922],"type":"Point"}
}