{
  "type": "Feature",
  "properties": {
    "iso:country":"CH",
    "sg:address":"Amriswilerstrasse 155",
    "sg:city":"Weinfelden",
    "sg:orig_category":"Unternehmensberatung Wirtschaftspr\u00fcfung, Steuerberatung U Treuhand",
    "sg:phone":"+41 22 318 68 00",
    "sg:postcode":"8570",
    "sg:province":"Thurgau",
    "wof:name":"Grant Thornton Sa",
    "wof:placetype":"venue"
},
  "geometry": {"coordinates":[6.1436948776,46.2014884949],"type":"Point"}
}