{
  "type": "Feature",
  "properties": {
    "iso:country":"CH",
    "sg:address":"Steinhaldenstrasse 49",
    "sg:city":"Z\u00fcrich",
    "sg:orig_category":"Interessenvertretungen",
    "sg:phone":"+41 12015500",
    "sg:postcode":"8002",
    "sg:province":"Z\u00fcrich",
    "wof:name":"Graeser Camille-stiftung",
    "wof:placetype":"venue"
},
  "geometry": {"coordinates":[8.5277748108,47.3596343994],"type":"Point"}
}