{
  "type": "Feature",
  "properties": {
    "iso:country":"CH",
    "sg:address":"Cheseaux 1872 Troistorrents. Postfach",
    "sg:city":"Troistorrents",
    "sg:orig_category":"Informatikdienste Softwareentwicklung U beratung",
    "sg:phone":"+41 24 477 50 25",
    "sg:postcode":"1872",
    "sg:province":"Valais",
    "wof:name":"Morisod B. - Horizon Software",
    "wof:placetype":"venue"
},
  "geometry": {"coordinates":[6.9302778244,46.2411956787],"type":"Point"}
}