{
  "type": "Feature",
  "properties": {
    "iso:country":"CH",
    "sg:address":"Rue Delafl\u00e9ch\u00e8re 4",
    "sg:city":"Nyon",
    "sg:orig_category":"Herstellung von elektrischen Lampen U Leuchten Sonstige Bauinstallation",
    "sg:phone":"+41 81 416 40 40",
    "sg:postcode":"1260",
    "sg:province":"Vaud",
    "wof:name":"Viglino Luigi.",
    "wof:placetype":"venue"
},
  "geometry": {"coordinates":[9.83943367,46.8058395386],"type":"Point"}
}