{
  "type": "Feature",
  "properties": {
    "iso:country":"CH",
    "sg:address":"Ober-kuonimatt",
    "sg:city":"Kriens",
    "sg:orig_category":"Allgemeiner Hoch U Tiefbau Spezieller Tiefbau",
    "sg:phone":"+41 55 283 01 09",
    "sg:postcode":"6010",
    "sg:province":"Luzern",
    "wof:name":"Bauunternehmung Hofstetter Ag",
    "wof:placetype":"venue"
},
  "geometry": {"coordinates":[9.007848,47.204193],"type":"Point"}
}