{
  "type": "Feature",
  "properties": {
    "iso:country":"CH",
    "sg:address":"Rosengartenstrasse 1a 8037 Z\u00fcrich. Postfach",
    "sg:city":"Z\u00fcrich",
    "sg:orig_category":"Satzherstellung U Reproduktion Softwareentwicklung U beratung",
    "sg:phone":"+41 22 717 43 50",
    "sg:postcode":"8001",
    "sg:province":"Z\u00fcrich",
    "wof:name":"Systor Sa, Succursale Du Grand-saconnex Succursale De Gen\u00e8ve",
    "wof:placetype":"venue"
},
  "geometry": {"coordinates":[6.122862,46.238377],"type":"Point"}
}