{
  "type": "Feature",
  "properties": {
    "iso:country":"CH",
    "sg:address":"Gestadeckplatz 8 4410 Liestal. Postfach 640",
    "sg:city":"Liestal",
    "sg:orig_category":"F\u00fcrsorge\u00e4mter",
    "sg:phone":"+41 61 925 56 45",
    "sg:postcode":"4410",
    "sg:province":"Basel-Landschaft",
    "wof:name":"Kantonales F\u00fcrsorgeamt",
    "wof:placetype":"venue"
},
  "geometry": {"coordinates":[7.7375259399,47.4860076904],"type":"Point"}
}