{
  "type": "Feature",
  "properties": {
    "iso:country":"CH",
    "sg:address":"Baselstrasse 67",
    "sg:city":"Riehen",
    "sg:classifiers":[
        {
            "category":"Restaurant",
            "type":"Food & Drink"
        }
    ],
    "sg:phone":"+41 61 641 54 55",
    "sg:postcode":"4125",
    "sg:province":"Basel-Stadt",
    "wof:name":"Mongolian Han Barbecue Restaurant",
    "wof:placetype":"venue"
},
  "geometry": {"coordinates":[7.6503582001,47.5860862732],"type":"Point"}
}