{
  "type": "Feature",
  "properties": {
    "iso:country":"CH",
    "sg:address":"Hauptstrasse 112",
    "sg:city":"Kreuzlingen",
    "sg:orig_category":"Interessenvertretungen",
    "sg:postcode":"8280",
    "sg:province":"Thurgau",
    "wof:name":"Stiftung F\u00fcr Die Errichtung Einer Mittelschule Seetal In Kreuzlingen",
    "wof:placetype":"venue"
},
  "geometry": {"coordinates":[9.1800079346,47.6443443298],"type":"Point"}
}