{
  "type": "Feature",
  "properties": {
    "iso:country":"CH",
    "sg:address":"Eigerweg 26",
    "sg:city":"Kehrsatz",
    "sg:orig_category":"Instandhaltung U Reparatur von Automobilen",
    "sg:phone":"+41 31 961 11 01",
    "sg:postcode":"3122",
    "sg:province":"Bern",
    "wof:name":"Schulthess Autofahrschule",
    "wof:placetype":"venue"
},
  "geometry": {"coordinates":[7.4710202217,46.9165000916],"type":"Point"}
}