{
  "type": "Feature",
  "properties": {
    "iso:country":"CH",
    "sg:address":"Buchholz",
    "sg:city":"Glarus",
    "sg:orig_category":"Sportschulen Gleitschirm-& Deltaflugschulen",
    "sg:phone":"+41 55 640 12 42",
    "sg:postcode":"8750",
    "sg:province":"Glarus",
    "wof:name":"Michael M\u00fcller Alpine Flugschule",
    "wof:placetype":"venue"
},
  "geometry": {"coordinates":[9.061340332,47.0507507324],"type":"Point"}
}