{
  "type": "Feature",
  "properties": {
    "iso:country":"CH",
    "sg:address":"Zone Industrielle",
    "sg:city":"Tolochenaz",
    "sg:orig_category":"Herstellung von sonstigen Maschinen f\u00fcr bestimmte Verwendung",
    "sg:phone":"+41 21 803 77 44",
    "sg:postcode":"1131",
    "sg:province":"Vaud",
    "wof:name":"Tecnolab Maintenance Industrielle Sa",
    "wof:placetype":"venue"
},
  "geometry": {"coordinates":[6.4742050171,46.5053062439],"type":"Point"}
}