{
  "type": "Feature",
  "properties": {
    "iso:country":"CH",
    "sg:address":"Bollwerk 35",
    "sg:city":"Bern",
    "sg:orig_category":"Dienstleistungen, Umwelt",
    "sg:phone":"+41 31 311 99 91",
    "sg:postcode":"3000",
    "sg:province":"Bern",
    "wof:name":"\u00d6kozentrum Bern",
    "wof:placetype":"venue"
},
  "geometry": {"coordinates":[7.44145,46.951572],"type":"Point"}
}