{
  "type": "Feature",
  "properties": {
    "addr:full":"Piazza Della Posta Ascona Ticino 6612",
    "addr:postcode":"6612",
    "addr:street":"Piazza Della Posta",
    "iso:country":"CH",
    "sg:address":"Piazza Della Posta",
    "sg:city":"Ascona",
    "sg:classifiers":[
        {
            "category":"Bars & Pubs",
            "type":"Food & Drink"
        }
    ],
    "sg:phone":"+41 91 791 42 97",
    "sg:postcode":"6612",
    "sg:province":"Ticino",
    "sg:tags":[
        "restaurant"
    ],
    "wof:name":"Ristorante-bar Brio",
    "wof:placetype":"venue"
},
  "geometry": {"coordinates":[8.769861,46.156437],"type":"Point"}
}