{
  "type": "Feature",
  "properties": {
    "iso:country":"CH",
    "sg:address":"9248",
    "sg:city":"Bichwil",
    "sg:classifiers":[
        {
            "category":"Restaurant",
            "type":"Food & Drink"
        }
    ],
    "sg:phone":"+41 71 393 15 01",
    "sg:postcode":"9248",
    "sg:province":"St. Gallen",
    "wof:name":"Restaurant Eppenberg",
    "wof:placetype":"venue"
},
  "geometry": {"coordinates":[9.1364097595,47.4206199646],"type":"Point"}
}