{
  "type": "Feature",
  "properties": {
    "iso:country":"CH",
    "sg:address":"Hauptstr. 32",
    "sg:city":"Aadorf",
    "sg:orig_category":"Verwertung von Milch",
    "sg:postcode":"8355",
    "sg:province":"Thurgau",
    "wof:name":"M\u00fcller-beyeler Beda",
    "wof:placetype":"venue"
},
  "geometry": {"coordinates":[8.8956241608,47.4924736023],"type":"Point"}
}