{
  "type": "Feature",
  "properties": {
    "iso:country":"CH",
    "sg:address":"Riedbachstrasse 349",
    "sg:city":"Bern",
    "sg:orig_category":"Grosshandel mit sonstigen Maschinen U Ausr\u00fcstungen f\u00fcr Industrie, Handel U Schiffahrt",
    "sg:phone":"+41 31 926 10 13",
    "sg:postcode":"3020",
    "sg:province":"Bern",
    "wof:name":"Henro Ag",
    "wof:placetype":"venue"
},
  "geometry": {"coordinates":[7.3541340828,46.9437255859],"type":"Point"}
}