{
  "type": "Feature",
  "properties": {
    "iso:country":"CH",
    "sg:address":"Rank 2 6300 Zug. Postfach",
    "sg:city":"Zug",
    "sg:classifiers":[
        {
            "category":"Professional",
            "subcategory":"Employment Agencies",
            "type":"Services"
        }
    ],
    "sg:postcode":"6300",
    "sg:province":"Zug",
    "sg:tags":[
        "personal",
        "u",
        "stellenvermittlung"
    ],
    "wof:name":"Allbecon Personalmanagement Zug Ag Dienstl. In D. Bereichen Personal, Unternehmensberatung Usw",
    "wof:placetype":"venue"
},
  "geometry": {"coordinates":[8.4916419983,47.180065155],"type":"Point"}
}