{
  "type": "Feature",
  "properties": {
    "iso:country":"CH",
    "sg:address":"Le Bry 34 1473 Font Case Postale",
    "sg:city":"Font",
    "sg:orig_category":"Grosshandel mit sonstigen Gebrauchs U Verbrauchsg\u00fctern Siebdruck",
    "sg:phone":"+41 21 922 67 45",
    "sg:postcode":"1473",
    "sg:province":"Fribourg",
    "wof:name":"Atelier Bessat Michel",
    "wof:placetype":"venue"
},
  "geometry": {"coordinates":[5.1808700562,45.8973388672],"type":"Point"}
}