{
  "type": "Feature",
  "properties": {
    "iso:country":"CH",
    "sg:address":"Terbinerstrasse 15 3930 Visp. Postfach",
    "sg:city":"Visp",
    "sg:orig_category":"Unclassifiable Establishments",
    "sg:phone":"+41 27 946 82 78",
    "sg:postcode":"3930",
    "sg:province":"Valais",
    "wof:name":"Tel-tarif.ch Gmbh Inhalte In Online-diensten Wie Dem Internet; Erstellen, Publizieren",
    "wof:placetype":"venue"
},
  "geometry": {"coordinates":[7.8853979111,46.2907676697],"type":"Point"}
}