{
  "type": "Feature",
  "properties": {
    "iso:country":"CH",
    "sg:address":"Etzelmatt 3 5430 Wettingen. Postfach 192",
    "sg:city":"Wettingen",
    "sg:orig_category":"Aktivit\u00e4ten der Generalunternehmen im Baugewerbe Allgemeiner Hoch U Tiefbau",
    "sg:phone":"+41 56 427 42 66",
    "sg:postcode":"5430",
    "sg:province":"Aargau",
    "wof:name":"Imag Generalunternehmung Ag",
    "wof:placetype":"venue"
},
  "geometry": {"coordinates":[8.317803,47.460114],"type":"Point"}
}