{
  "type": "Feature",
  "properties": {
    "iso:country":"CH",
    "sg:address":"Karrenstrasse 10",
    "sg:city":"Horgen",
    "sg:orig_category":"Grosshandel mit sonstigen Gebrauchs U Verbrauchsg\u00fctern",
    "sg:phone":"+41 17260873",
    "sg:postcode":"8810",
    "sg:province":"Z\u00fcrich",
    "wof:name":"Werbe-presents, Honegger Peter",
    "wof:placetype":"venue"
},
  "geometry": {"coordinates":[8.6078891754,47.2539787292],"type":"Point"}
}