{
  "type": "Feature",
  "properties": {
    "iso:country":"CH",
    "sg:address":"2605 Sonceboz-sombeval. Postfach",
    "sg:city":"Sonceboz-sombeval",
    "sg:orig_category":"Pensionskassen",
    "sg:postcode":"2605",
    "sg:province":"Bern",
    "wof:name":"Fonds De Pr\u00e9voyance Pour Le Personnel De La Manufacture De Penduletteset R\u00e9veils Imhof Arthur Sa",
    "wof:placetype":"venue"
},
  "geometry": {"coordinates":[6.8280410767,47.1006164551],"type":"Point"}
}