{
  "type": "Feature",
  "properties": {
    "iso:country":"CH",
    "sg:address":"Le Coll\u00e8ge",
    "sg:city":"Juriens",
    "sg:orig_category":"Softwareentwicklung U beratung",
    "sg:phone":"+41 24 453 24 56",
    "sg:postcode":"1326",
    "sg:province":"Vaud",
    "wof:name":"Ferlet Christian Informatique Sa",
    "wof:placetype":"venue"
},
  "geometry": {"coordinates":[6.4502148628,46.6913414001],"type":"Point"}
}