{
  "type": "Feature",
  "properties": {
    "iso:country":"CH",
    "sg:address":"Thurtalstrasse 14 8450 Andelfingen. Postfach 315",
    "sg:city":"Andelfingen",
    "sg:classifiers":[
        {
            "category":"Insurance",
            "subcategory":"Insurance Agent",
            "type":"Services"
        }
    ],
    "sg:phone":"+41 19371116",
    "sg:postcode":"8450",
    "sg:province":"Z\u00fcrich",
    "sg:tags":[
        "versicherungsagenturen",
        "-broker"
    ],
    "wof:name":"Die Mobiliar Versicherungen & Vorsorge",
    "wof:placetype":"venue"
},
  "geometry": {"coordinates":[8.8552503586,47.2890396118],"type":"Point"}
}