{
  "type": "Feature",
  "properties": {
    "iso:country":"CH",
    "sg:address":"Hummelstrasse",
    "sg:city":"Frauenfeld",
    "sg:orig_category":"Grosshandel mit sonstigen Maschinen U Ausr\u00fcstungen f\u00fcr Industrie, Handel U Schiffahrt",
    "sg:phone":"+41 52 720 29 41",
    "sg:postcode":"8500",
    "sg:province":"Thurgau",
    "wof:name":"Omk Gmbh",
    "wof:placetype":"venue"
},
  "geometry": {"coordinates":[8.8837652206,47.5629386902],"type":"Point"}
}