{
  "type": "Feature",
  "properties": {
    "iso:country":"CH",
    "sg:address":"1585",
    "sg:city":"Salavaux",
    "sg:orig_category":"Arztpraxen",
    "sg:phone":"+41 26 677 13 08",
    "sg:postcode":"1585",
    "sg:province":"Vaud",
    "wof:name":"Dr M\u00e9d. Jean-marc Wandeler M\u00e9decin G\u00e9n\u00e9raliste Fmh",
    "wof:placetype":"venue"
},
  "geometry": {"coordinates":[7.02234,46.918159],"type":"Point"}
}