{
  "type": "Feature",
  "properties": {
    "iso:country":"CH",
    "sg:address":"Gewerbestrasse 5",
    "sg:city":"Sissach",
    "sg:orig_category":"Grosshandel mit sonstigen Maschinen U Ausr\u00fcstungen f\u00fcr Industrie, Handel U Schiffahrt Mechanik",
    "sg:phone":"+41 19291266",
    "sg:postcode":"4450",
    "sg:province":"Basel-Landschaft",
    "wof:name":"Messerli Paul",
    "wof:placetype":"venue"
},
  "geometry": {"coordinates":[8.7229585648,47.2685585022],"type":"Point"}
}