{
  "type": "Feature",
  "properties": {
    "iso:country":"CH",
    "sg:address":"Rue Des Bordgeais 35",
    "sg:city":"Del\u00e9mont",
    "sg:orig_category":"Architektur U Ingenieurb\u00fcros",
    "sg:phone":"+41 21 922 98 25",
    "sg:postcode":"2800",
    "sg:province":"Jura",
    "wof:name":"Angel Capital S\u00e0rl",
    "wof:placetype":"venue"
},
  "geometry": {"coordinates":[5.18087,45.897339],"type":"Point"}
}