{
  "type": "Feature",
  "properties": {
    "iso:country":"CH",
    "sg:address":"Eglise Catholiquerue De 8",
    "sg:city":"Montreux",
    "sg:orig_category":"Technische, physikalische U chemische Untersuchung",
    "sg:postcode":"1820",
    "sg:province":"Vaud",
    "wof:name":"Hintermann & Weber Sa",
    "wof:placetype":"venue"
},
  "geometry": {"coordinates":[6.9115548134,46.4310417175],"type":"Point"}
}