{
  "type": "Feature",
  "properties": {
    "iso:country":"CH",
    "sg:address":"Via Lucchini 1 6900 Lugano. Postfach Caselle Postale 3401",
    "sg:city":"Lugano",
    "sg:orig_category":"Architektur U Ingenieurb\u00fcros Architekturb\u00fcros",
    "sg:phone":"+41 91 827 30 33",
    "sg:postcode":"6901",
    "sg:province":"Ticino",
    "wof:name":"Studio Di Architettura Cereghetti Luigi Sagl",
    "wof:placetype":"venue"
},
  "geometry": {"coordinates":[9.128365,46.237606],"type":"Point"}
}