{
  "type": "Feature",
  "properties": {
    "iso:country":"CH",
    "sg:address":"Klingenstrasse 9 8005 Z\u00fcrich. Postfach",
    "sg:city":"Z\u00fcrich",
    "sg:orig_category":"Grosshandel mit Nahrungsmitteln, Getr\u00e4nken U Tabakwaren ohne ausgepr\u00e4gten Schwerpunkt",
    "sg:postcode":"8001",
    "sg:province":"Z\u00fcrich",
    "wof:name":"Ayfat. Handel M. Lebensmitteln U. Geschenkartikeln.",
    "wof:placetype":"venue"
},
  "geometry": {"coordinates":[8.5325193405,47.3813819885],"type":"Point"}
}