{
  "type": "Feature",
  "properties": {
    "addr:full":"Rue De L' Ouriette 179 Aubonne Vaud 1170",
    "addr:housenumber":"179",
    "addr:postcode":"1170",
    "addr:street":"Rue De L ' Ouriette",
    "iso:country":"CH",
    "sg:address":"Rue De L' Ouriette 179",
    "sg:city":"Aubonne",
    "sg:classifiers":[
        {
            "category":"Manufacturing",
            "subcategory":"Wood Products",
            "type":"Manufacturing & Wholesale Goods"
        }
    ],
    "sg:phone":"+41 21 808 63 33",
    "sg:postcode":"1170",
    "sg:province":"Vaud",
    "sg:tags":[
        "case"
    ],
    "wof:name":"Paul Bovy",
    "wof:placetype":"venue"
},
  "geometry": {"coordinates":[6.307631,46.508732],"type":"Point"}
}