{
  "type": "Feature",
  "properties": {
    "iso:country":"CH",
    "sg:address":"Brunaustrasse 15",
    "sg:city":"Z\u00fcrich",
    "sg:orig_category":"Fachdetailhandel in Verkaufsr\u00e4umen",
    "sg:phone":"+41 12016767",
    "sg:postcode":"8002",
    "sg:province":"Z\u00fcrich",
    "wof:name":"Collection Dobe",
    "wof:placetype":"venue"
},
  "geometry": {"coordinates":[8.531370163,47.3556671143],"type":"Point"}
}