{
  "type": "Feature",
  "properties": {
    "addr:full":"Chemin Cr\u00e9pon 32 1815 Clarens Case Postale 138 Clarens Vaud 1815",
    "addr:housenumber":"32",
    "addr:postcode":"1815;1815",
    "addr:street":"Chemin Cre\u0301Pon;Postale 138",
    "iso:country":"CH",
    "sg:address":"Chemin Cr\u00e9pon 32 1815 Clarens Case Postale 138",
    "sg:city":"Clarens",
    "sg:orig_category":"Alters U Pflegeheime Institutionen f\u00fcr Behinderte",
    "sg:phone":"+41 41 886 86 86",
    "sg:postcode":"1815",
    "sg:province":"Vaud",
    "wof:name":"Betagten-& Pflegeheim Oberes Reusstal",
    "wof:placetype":"venue"
},
  "geometry": {"coordinates":[8.60051,46.705429],"type":"Point"}
}