{
  "type": "Feature",
  "properties": {
    "iso:country":"CH",
    "sg:address":"Gare Avenue De La 17",
    "sg:city":"Sion",
    "sg:orig_category":"Non-Classified Establishments",
    "sg:phone":"+41 27 323 53 30",
    "sg:postcode":"1950",
    "sg:province":"Valais",
    "wof:name":"Pronto Pizza, Milena Cellamare",
    "wof:placetype":"venue"
},
  "geometry": {"coordinates":[7.3588571548,46.2280921936],"type":"Point"}
}