{
  "type": "Feature",
  "properties": {
    "iso:country":"CH",
    "sg:address":"Seujet Quai Du 14",
    "sg:city":"Gen\u00e8ve",
    "sg:orig_category":"Forschung U Entwicklung im Bereich der Naturwissenschaften",
    "sg:postcode":"1201",
    "sg:province":"Gen\u00e8ve",
    "wof:name":"Medrid-foundation (medical Research By Independent Doctors)",
    "wof:placetype":"venue"
},
  "geometry": {"coordinates":[7.4963231087,46.9264335632],"type":"Point"}
}