{
  "type": "Feature",
  "properties": {
    "iso:country":"CH",
    "sg:address":"Costa Di Fuori Via 2",
    "sg:city":"Brissago",
    "sg:orig_category":"Vermietung U Verpachtung von eigenen Immobilien",
    "sg:postcode":"6614",
    "sg:province":"Ticino",
    "wof:name":"Bea Sa",
    "wof:placetype":"venue"
},
  "geometry": {"coordinates":[8.7052307129,46.1125106812],"type":"Point"}
}