{
  "type": "Feature",
  "properties": {
    "iso:country":"CH",
    "sg:address":"Seefeldstrasse 9 8008 Z\u00fcrich. Postfach",
    "sg:city":"Z\u00fcrich",
    "sg:orig_category":"Dienstleistungen von Beteiligungsgesellschaften",
    "sg:phone":"+41 12512747",
    "sg:postcode":"8001",
    "sg:province":"Z\u00fcrich",
    "wof:name":"Safisa Services Administratifs Et Financiers Sa",
    "wof:placetype":"venue"
},
  "geometry": {"coordinates":[8.5486106873,47.3646087646],"type":"Point"}
}