{
  "type": "Feature",
  "properties": {
    "addr:full":"Rue Des Granges 8 Payerne Vaud 1530",
    "addr:housenumber":"8",
    "addr:postcode":"1530",
    "addr:street":"Rue Des Granges",
    "iso:country":"CH",
    "sg:address":"Rue Des Granges 8",
    "sg:city":"Payerne",
    "sg:orig_category":"Allgemeiner Hoch U Tiefbau",
    "sg:phone":"+41 21 905 31 00",
    "sg:postcode":"1530",
    "sg:province":"Vaud",
    "wof:name":"Clot Fr\u00e8res Sa, Succursale De Payerne",
    "wof:placetype":"venue"
},
  "geometry": {"coordinates":[6.937592,46.819302],"type":"Point"}
}