{
  "type": "Feature",
  "properties": {
    "iso:country":"CH",
    "sg:address":"Kornhausplatz 11 3011 Bern. Postfach",
    "sg:city":"Bern",
    "sg:orig_category":"Unclassifiable Establishments",
    "sg:postcode":"3005",
    "sg:province":"Bern",
    "wof:name":"Drogerie Walther Drogerie; Spirituosen U. Wein; Handel.",
    "wof:placetype":"venue"
},
  "geometry": {"coordinates":[7.4476909637,46.9485282898],"type":"Point"}
}