{
  "type": "Feature",
  "properties": {
    "addr:full":"Dorfstrasse 44 Wislikofen 8439",
    "addr:housenumber":"44",
    "addr:postcode":"8439",
    "addr:street":"Dorfstrasse",
    "iso:country":"CH",
    "sg:address":"Dorfstrasse 44",
    "sg:city":"Wislikofen",
    "sg:classifiers":[
        {
            "category":"Banks & Credit Unions",
            "subcategory":"Bank",
            "type":"Services"
        }
    ],
    "sg:phone":"+41 61 721 66 11",
    "sg:postcode":"8439",
    "wof:name":"Raiffeisenbank Witterswil-b\u00e4ttwil-rodersdorf",
    "wof:placetype":"venue"
},
  "geometry": {"coordinates":[7.52562,47.487591],"type":"Point"}
}