{
  "type": "Feature",
  "properties": {
    "iso:country":"CH",
    "sg:address":"Avenue De La Gare 1523 Granges-marnand Case Postale",
    "sg:city":"Granges-marnand",
    "sg:orig_category":"Allgemeiner Hoch U Tiefbau Strassenbau",
    "sg:phone":"+41 26 660 61 03",
    "sg:postcode":"1523",
    "sg:province":"Vaud",
    "wof:name":"Clot Fr\u00e8res Sa",
    "wof:placetype":"venue"
},
  "geometry": {"coordinates":[6.89174,46.760811],"type":"Point"}
}