{
  "type": "Feature",
  "properties": {
    "iso:country":"CH",
    "sg:address":"Badenerstrasse 816 8048 Z\u00fcrich. Postfach",
    "sg:city":"Z\u00fcrich",
    "sg:orig_category":"Architektur U Ingenieurb\u00fcros",
    "sg:postcode":"8008",
    "sg:province":"Z\u00fcrich",
    "wof:name":"Elbas Schweiz Ag",
    "wof:placetype":"venue"
},
  "geometry": {"coordinates":[8.473636,47.393539],"type":"Point"}
}