{
  "type": "Feature",
  "properties": {
    "iso:country":"CH",
    "sg:address":"Rue Du Pont 22",
    "sg:city":"Lausanne",
    "sg:orig_category":"Softwareentwicklung U beratung Sonstige mit der Informatik verbundene T\u00e4tigkeiten",
    "sg:phone":"+41 61 711 50 44",
    "sg:postcode":"1003",
    "sg:province":"Vaud",
    "wof:name":"Abconsultant Gmbh Gesamtheitliche It-dienstleistungen",
    "wof:placetype":"venue"
},
  "geometry": {"coordinates":[7.5885109901,47.4887771606],"type":"Point"}
}