{
  "type": "Feature",
  "properties": {
    "iso:country":"CH",
    "sg:address":"Markusstrasse 7",
    "sg:city":"Z\u00fcrich",
    "sg:orig_category":"Non-Classified Establishments",
    "sg:phone":"+41 13632182",
    "sg:postcode":"8006",
    "sg:province":"Z\u00fcrich",
    "wof:name":"Br\u00e4ndle Brigitte Productions",
    "wof:placetype":"venue"
},
  "geometry": {"coordinates":[8.5373392105,47.3876571655],"type":"Point"}
}