{
  "type": "Feature",
  "properties": {
    "iso:country":"CH",
    "sg:address":"Niederglatterstrasse 18",
    "sg:city":"Niederhasli",
    "sg:orig_category":"Sanit\u00e4r U Heizungsinstallation",
    "sg:phone":"+41 18501442",
    "sg:postcode":"8155",
    "sg:province":"Z\u00fcrich",
    "wof:name":"B. Imhof Ag Heizungsinstallationen",
    "wof:placetype":"venue"
},
  "geometry": {"coordinates":[8.4871292114,47.4811859131],"type":"Point"}
}