{
  "type": "Feature",
  "properties": {
    "iso:country":"CH",
    "sg:address":"Giacomettistrasse 107",
    "sg:city":"Chur",
    "sg:orig_category":"Maler U Glasergewerbe Tapeziererei",
    "sg:phone":"+41 81 353 99 50",
    "sg:postcode":"7000",
    "sg:province":"Graubunden",
    "wof:name":"Cadalbert, Tapeten-decor Und Malerei",
    "wof:placetype":"venue"
},
  "geometry": {"coordinates":[9.529540062,46.8637199402],"type":"Point"}
}