{
  "type": "Feature",
  "properties": {
    "iso:country":"CH",
    "sg:address":"Vers-encier",
    "sg:city":"Troistorrents",
    "sg:orig_category":"Non-Classified Establishments",
    "sg:postcode":"1872",
    "sg:province":"Valais",
    "wof:name":"Tout\u00e9lec Sa Electricit\u00e9-t\u00e9l\u00e9phones",
    "wof:placetype":"venue"
},
  "geometry": {"coordinates":[6.935710907,46.2452964783],"type":"Point"}
}