{
  "type": "Feature",
  "properties": {
    "iso:country":"CH",
    "sg:address":"Auf Dem R\u00fccken 1",
    "sg:city":"Riehen",
    "sg:orig_category":"Vermietung U Verpachtung von eigenen Immobilien",
    "sg:postcode":"4125",
    "sg:province":"Basel-Stadt",
    "wof:name":"Rimob Ag",
    "wof:placetype":"venue"
},
  "geometry": {"coordinates":[7.6643629074,47.5825920105],"type":"Point"}
}