{
  "type": "Feature",
  "properties": {
    "iso:country":"CH",
    "sg:address":"Karl-stamm-weg 2 8820 W\u00e4denswil. Postfach",
    "sg:city":"W\u00e4denswil",
    "sg:orig_category":"Unclassifiable Establishments",
    "sg:phone":"+41 71 945 94 70",
    "sg:postcode":"8820",
    "sg:province":"Z\u00fcrich",
    "wof:name":"Sieber-hydraulik Gmbh",
    "wof:placetype":"venue"
},
  "geometry": {"coordinates":[9.1125459671,47.4727210999],"type":"Point"}
}