{
  "type": "Feature",
  "properties": {
    "iso:country":"CH",
    "sg:address":"Scheuermattstrasse 3 6330 Cham. Postfach",
    "sg:city":"Cham",
    "sg:orig_category":"Elektroinstallation",
    "sg:phone":"+41 41 780 68 93",
    "sg:postcode":"6330",
    "sg:province":"Zug",
    "wof:name":"Schwarz Montagen Gmbh Baumontagen, Bes. Fenster Und T\u00fcrmontagen Usw",
    "wof:placetype":"venue"
},
  "geometry": {"coordinates":[8.464887619,47.1821746826],"type":"Point"}
}