{
  "type": "Feature",
  "properties": {
    "iso:country":"CH",
    "sg:address":"Corraterie Rue De La 9 1204 Gen\u00e8ve. Postfach",
    "sg:city":"Gen\u00e8ve",
    "sg:orig_category":"Unclassifiable Establishments",
    "sg:postcode":"1204",
    "sg:province":"Gen\u00e8ve",
    "wof:name":"Hadag Sa",
    "wof:placetype":"venue"
},
  "geometry": {"coordinates":[6.1434979439,46.2028160095],"type":"Point"}
}