{
  "type": "Feature",
  "properties": {
    "iso:country":"CH",
    "sg:address":"Kesslergasse 2",
    "sg:city":"L\u00fcterkofen-ichert",
    "sg:orig_category":"Architekturb\u00fcros",
    "sg:phone":"+41 32 677 25 55",
    "sg:postcode":"4571",
    "sg:province":"Solothurn",
    "wof:name":"Norag Architektur Ag",
    "wof:placetype":"venue"
},
  "geometry": {"coordinates":[7.511089,47.162884],"type":"Point"}
}