{
  "type": "Feature",
  "properties": {
    "iso:country":"CH",
    "sg:address":"Steinacherstrasse 38",
    "sg:city":"Illnau",
    "sg:orig_category":"Erwachsenenbildung U Unterricht K\u00fcnstlerische Schulen",
    "sg:phone":"+41 52 346 14 24",
    "sg:postcode":"8308",
    "sg:province":"Z\u00fcrich",
    "wof:name":"Verein Musikschule Effretikon Vme.",
    "wof:placetype":"venue"
},
  "geometry": {"coordinates":[8.7100639343,47.4113311768],"type":"Point"}
}