{
  "type": "Feature",
  "properties": {
    "iso:country":"CH",
    "sg:address":"8606",
    "sg:city":"Greifensee",
    "sg:orig_category":"Vorschulen, Kinderg\u00e4rten",
    "sg:phone":"+41 19406469",
    "sg:postcode":"8606",
    "sg:province":"Z\u00fcrich",
    "wof:name":"Kindergarten St\u00e4dtli",
    "wof:placetype":"venue"
},
  "geometry": {"coordinates":[8.677529335,47.365234375],"type":"Point"}
}