{
  "type": "Feature",
  "properties": {
    "addr:full":"Geissbrunnenweg 31 Itingen Basel-Landschaft 4452",
    "addr:housenumber":"31",
    "addr:postcode":"4452",
    "addr:street":"Geissbrunnenweg",
    "iso:country":"CH",
    "sg:address":"Geissbrunnenweg 31",
    "sg:city":"Itingen",
    "sg:orig_category":"Architektur U Ingenieurb\u00fcros",
    "sg:phone":"+41 61 973 94 24",
    "sg:postcode":"4452",
    "sg:province":"Basel-Landschaft",
    "wof:name":"Wirotec W. Rombach",
    "wof:placetype":"venue"
},
  "geometry": {"coordinates":[7.789562,47.466606],"type":"Point"}
}