{
  "type": "Feature",
  "properties": {
    "iso:country":"CH",
    "sg:address":"Industriestrasse 7 6300 Zug. Postfach",
    "sg:city":"Zug",
    "sg:orig_category":"Datenverarbeitungsdienste",
    "sg:phone":"+41 41 729 61 10",
    "sg:postcode":"6301",
    "sg:province":"Zug",
    "wof:name":"Computer Brainware Advisors Holding Ag",
    "wof:placetype":"venue"
},
  "geometry": {"coordinates":[8.517587,47.170769],"type":"Point"}
}