{
  "type": "Feature",
  "properties": {
    "addr:full":"Verkehrsb\u00fcro Stoos Stoos Schwyz 6433",
    "addr:postcode":"6433",
    "iso:country":"CH",
    "sg:address":"Verkehrsb\u00fcro Stoos",
    "sg:city":"Stoos",
    "sg:classifiers":[
        {
            "category":"Banks & Credit Unions",
            "subcategory":"Bank",
            "type":"Services"
        }
    ],
    "sg:phone":"+41 4143211550",
    "sg:postcode":"6433",
    "sg:province":"Schwyz",
    "wof:name":"Kantonalbank Schwyz",
    "wof:placetype":"venue"
},
  "geometry": {"coordinates":[8.66753,46.983261],"type":"Point"}
}