{
  "type": "Feature",
  "properties": {
    "iso:country":"CH",
    "sg:address":"Winterthurerstrasse 576",
    "sg:city":"Z\u00fcrich",
    "sg:orig_category":"Handel mit Automobilen",
    "sg:postcode":"8051",
    "sg:province":"Z\u00fcrich",
    "wof:name":"Autohaus Z\u00fcrich Nord Gmbh",
    "wof:placetype":"venue"
},
  "geometry": {"coordinates":[8.5775089264,47.4049263],"type":"Point"}
}