{
  "type": "Feature",
  "properties": {
    "iso:country":"CH",
    "sg:address":"Schellstrasse 16",
    "sg:city":"Unter\u00e4geri",
    "sg:orig_category":"Instandhaltung U Reparatur von Automobilen",
    "sg:postcode":"6314",
    "sg:province":"Zug",
    "wof:name":"Fl\u00fchler A.",
    "wof:placetype":"venue"
},
  "geometry": {"coordinates":[8.578291893,47.1365699768],"type":"Point"}
}