{
  "type": "Feature",
  "properties": {
    "iso:country":"CH",
    "sg:address":"Schwertgasse 13",
    "sg:city":"Zurzach",
    "sg:classifiers":[
        {
            "category":"Restaurant",
            "type":"Food & Drink"
        }
    ],
    "sg:phone":"+41 55 214 12 22",
    "sg:postcode":"5330",
    "sg:province":"Aargau",
    "sg:tags":[
        "tea-rooms",
        "restaurants"
    ],
    "wof:name":"Ristorante La Scala, Francabandiera Pietro",
    "wof:placetype":"venue"
},
  "geometry": {"coordinates":[8.8144884109,47.2261772156],"type":"Point"}
}