{
  "type": "Feature",
  "properties": {
    "iso:country":"CH",
    "sg:address":"Via D'ar\u00f6vens",
    "sg:city":"Pontresina",
    "sg:orig_category":"Architektur U Ingenieurb\u00fcros Verkehrs- and Tourismusb\u00fcros",
    "sg:phone":"+41 79 474 36 85",
    "sg:postcode":"7504",
    "sg:province":"Graubunden",
    "wof:name":"Engiadina Progets Gmbh",
    "wof:placetype":"venue"
},
  "geometry": {"coordinates":[9.886799,46.509411],"type":"Point"}
}