{
  "type": "Feature",
  "properties": {
    "iso:country":"CH",
    "sg:address":"Lerchenplatz 1 6045 Meggen. Postfach 417",
    "sg:city":"Meggen",
    "sg:orig_category":"Grosshandel mit medizinischen U orthop\u00e4dischen Artikeln Herstellung von medizinischen U chirurgische",
    "sg:phone":"+41 41 377 19 40",
    "sg:postcode":"6045",
    "sg:province":"Luzern",
    "wof:name":"Theramed Ag Therapie Und Medizintechnik",
    "wof:placetype":"venue"
},
  "geometry": {"coordinates":[8.3604660034,47.0417823792],"type":"Point"}
}