{
  "type": "Feature",
  "properties": {
    "iso:country":"CH",
    "sg:address":"Falknisstrasse 10",
    "sg:city":"Vilters",
    "sg:orig_category":"K\u00fcnstlerische U schriftstellerische T\u00e4tigkeiten U Darbietungen",
    "sg:phone":"+41 81 723 79 74",
    "sg:postcode":"7324",
    "sg:province":"St. Gallen",
    "wof:name":"Szories Happy-sound",
    "wof:placetype":"venue"
},
  "geometry": {"coordinates":[9.4515686035,47.0253639221],"type":"Point"}
}