{
  "type": "Feature",
  "properties": {
    "iso:country":"CH",
    "sg:address":"Kanonengasse 53",
    "sg:city":"Liestal",
    "sg:orig_category":"Detailhandel mit Uhren U Schmuck",
    "sg:phone":"+41 71 377 19 44",
    "sg:postcode":"4410",
    "sg:province":"Basel-Landschaft",
    "wof:name":"Lucas E. Schweizer Goldschmiede-atelier",
    "wof:placetype":"venue"
},
  "geometry": {"coordinates":[9.1741065979,47.3175086975],"type":"Point"}
}