{
  "type": "Feature",
  "properties": {
    "iso:country":"CH",
    "sg:address":"Hammerstrasse 47",
    "sg:city":"Liestal",
    "sg:classifiers":[
        {
            "category":"Manufacturing",
            "subcategory":"Tools & Machinery",
            "type":"Manufacturing & Wholesale Goods"
        }
    ],
    "sg:phone":"+41 61 906 93 55",
    "sg:postcode":"4410",
    "sg:province":"Basel-Landschaft",
    "sg:tags":[
        "part",
        "turned",
        "cnc"
    ],
    "wof:name":"Desco Ag Pr\u00e4zisionsteile",
    "wof:placetype":"venue"
},
  "geometry": {"coordinates":[7.725181,47.497711],"type":"Point"}
}