{
  "type": "Feature",
  "properties": {
    "iso:country":"CH",
    "sg:address":"Allmendg\u00fctlistrasse 26",
    "sg:city":"Horgen",
    "sg:orig_category":"Unternehmensberatung",
    "sg:phone":"+41 18136495",
    "sg:postcode":"8810",
    "sg:province":"Z\u00fcrich",
    "wof:name":"Hygex Gmbh",
    "wof:placetype":"venue"
},
  "geometry": {"coordinates":[8.6091117859,47.2529563904],"type":"Point"}
}