{
  "type": "Feature",
  "properties": {
    "iso:country":"CH",
    "sg:address":"Lugano Via 10",
    "sg:city":"Agno",
    "sg:orig_category":"Sonstige mit der Informatik verbundene T\u00e4tigkeiten",
    "sg:phone":"+41 21 922 27 65",
    "sg:postcode":"6982",
    "sg:province":"Ticino",
    "wof:name":"Media Aera, Bergaud Herv\u00e9",
    "wof:placetype":"venue"
},
  "geometry": {"coordinates":[5.1808700562,45.8973388672],"type":"Point"}
}