{
  "type": "Feature",
  "properties": {
    "iso:country":"CH",
    "sg:address":"Bettlachstrasse 276",
    "sg:city":"Grenchen",
    "sg:orig_category":"Herstellung von sonstigen Metallwaren Pulvermetallurgie Schmieden, Pressen, Stanzen U Profilwalzen v",
    "sg:phone":"+41 32 645 02 85",
    "sg:postcode":"2540",
    "sg:province":"Solothurn",
    "wof:name":"Meister Hans Ag",
    "wof:placetype":"venue"
},
  "geometry": {"coordinates":[7.4117951393,47.197769165],"type":"Point"}
}