{
  "type": "Feature",
  "properties": {
    "iso:country":"CH",
    "sg:address":"Rosshalde 28",
    "sg:city":"Rothenburg",
    "sg:orig_category":"Unclassifiable Establishments",
    "sg:postcode":"6023",
    "sg:province":"Luzern",
    "wof:name":"Feel It Gmbh",
    "wof:placetype":"venue"
},
  "geometry": {"coordinates":[8.2669639587,47.1032676697],"type":"Point"}
}