{
  "type": "Feature",
  "properties": {
    "iso:country":"CH",
    "sg:address":"Kengelwiesstrasse 5",
    "sg:city":"Tann",
    "sg:orig_category":"Architektur U Ingenieurb\u00fcros",
    "sg:postcode":"8632",
    "sg:province":"Z\u00fcrich",
    "wof:name":"Mabu Generalplanung Gmbh",
    "wof:placetype":"venue"
},
  "geometry": {"coordinates":[8.852265,47.264397],"type":"Point"}
}