{
  "type": "Feature",
  "properties": {
    "iso:country":"CH",
    "sg:address":"Boveresses Avenue Des 46",
    "sg:city":"Lausanne",
    "sg:orig_category":"Herstellung von Medikamenten U sonstigen pharmazeutischen Erzeugnissen",
    "sg:phone":"+41 21 651 74 74",
    "sg:postcode":"1010",
    "sg:province":"Vaud",
    "wof:name":"Kramer Pharma Sa",
    "wof:placetype":"venue"
},
  "geometry": {"coordinates":[6.6665630341,46.5356216431],"type":"Point"}
}