{
  "type": "Feature",
  "properties": {
    "iso:country":"CH",
    "sg:address":"Rue Des Granges 10",
    "sg:city":"Payerne",
    "sg:orig_category":"Detailhandel mit Waren verschiedener Art, Hauptrichtung Nahrungsmittel Fachdetailhandel mit Nahrungs",
    "sg:phone":"+41 26 660 45 18",
    "sg:postcode":"1530",
    "sg:province":"Vaud",
    "wof:name":"Godel, J.-p.",
    "wof:placetype":"venue"
},
  "geometry": {"coordinates":[6.9377160072,46.8193588257],"type":"Point"}
}