{
  "type": "Feature",
  "properties": {
    "iso:country":"CH",
    "sg:address":"Engadinstrasse",
    "sg:city":"Chur",
    "sg:orig_category":"Pensionskassen",
    "sg:postcode":"7000",
    "sg:province":"Graubunden",
    "wof:name":"Personalf\u00fcrsorgestiftung Der Th. Coray, Ag Chur",
    "wof:placetype":"venue"
},
  "geometry": {"coordinates":[9.5288553238,46.8507003784],"type":"Point"}
}