{
  "type": "Feature",
  "properties": {
    "iso:country":"CH",
    "sg:city":"Binningen",
    "sg:orig_category":"Bildung and Forschung, Schulen",
    "sg:postcode":"4102",
    "sg:province":"Basel-Landschaft",
    "wof:name":"Labtam-ag",
    "wof:placetype":"venue"
},
  "geometry": {"coordinates":[7.571217,47.538029],"type":"Point"}
}