{
  "type": "Feature",
  "properties": {
    "iso:country":"CH",
    "sg:address":"Bachtelstrasse 10",
    "sg:city":"Illnau",
    "sg:orig_category":"Vorschulen, Kinderg\u00e4rten",
    "sg:phone":"+41 81 832 31 71",
    "sg:postcode":"8308",
    "sg:province":"Z\u00fcrich",
    "wof:name":"Kindergarten Chesa Granda",
    "wof:placetype":"venue"
},
  "geometry": {"coordinates":[9.8399076462,46.4863548279],"type":"Point"}
}