{
  "type": "Feature",
  "properties": {
    "iso:country":"CH",
    "sg:address":"Neugasse 6",
    "sg:city":"Zug",
    "sg:classifiers":[
        {
            "category":"Bars & Pubs",
            "type":"Food & Drink"
        }
    ],
    "sg:phone":"+41 41 711 22 70",
    "sg:postcode":"6300",
    "sg:province":"Zug",
    "wof:name":"Bar Pub Why Not",
    "wof:placetype":"venue"
},
  "geometry": {"coordinates":[8.515429,47.167358],"type":"Point"}
}