{
  "type": "Feature",
  "properties": {
    "iso:country":"CH",
    "sg:address":"Hotelgasse 8",
    "sg:city":"Bern",
    "sg:orig_category":"Non-Classified Establishments",
    "sg:postcode":"3011",
    "sg:province":"Bern",
    "wof:name":"Uht Consulting & Services Ag",
    "wof:placetype":"venue"
},
  "geometry": {"coordinates":[7.4478988647,46.94764328],"type":"Point"}
}