{
  "type": "Feature",
  "properties": {
    "iso:country":"CH",
    "sg:address":"Neuve Route 6",
    "sg:city":"Aubonne",
    "sg:orig_category":"Softwareentwicklung U beratung",
    "sg:phone":"+41 878 878 510",
    "sg:postcode":"1170",
    "sg:province":"Vaud",
    "wof:name":"Blu Real Sa",
    "wof:placetype":"venue"
},
  "geometry": {"coordinates":[6.3931179047,46.4951934814],"type":"Point"}
}