{
  "type": "Feature",
  "properties": {
    "iso:country":"CH",
    "sg:address":"En Novallette",
    "sg:city":"Noville",
    "sg:orig_category":"Architektur U Ingenieurb\u00fcros",
    "sg:postcode":"1845",
    "sg:province":"Vaud",
    "wof:name":"Agence D'architecture Deillon A. & Vouilloz J.",
    "wof:placetype":"venue"
},
  "geometry": {"coordinates":[6.916774,46.692211],"type":"Point"}
}