{
  "type": "Feature",
  "properties": {
    "addr:full":"Rugenaustrasse 20 Interlaken Bern 3800",
    "addr:housenumber":"20",
    "addr:postcode":"3800",
    "addr:street":"Rugenaustrasse",
    "iso:country":"CH",
    "sg:address":"Rugenaustrasse 20",
    "sg:city":"Interlaken",
    "sg:orig_category":"Architektur U Ingenieurb\u00fcros Architekturb\u00fcros",
    "sg:phone":"+41 33 822 71 24",
    "sg:postcode":"3800",
    "sg:province":"Bern",
    "wof:name":"B\u00e4rtschi + M\u00fcller Architektur Gmbh",
    "wof:placetype":"venue"
},
  "geometry": {"coordinates":[7.852737,46.678871],"type":"Point"}
}