{
  "type": "Feature",
  "properties": {
    "iso:country":"CH",
    "sg:address":"Avenue Louis-casa\u00ef 54",
    "sg:city":"Cointrin",
    "sg:classifiers":[
        {
            "category":"Restaurant",
            "type":"Food & Drink"
        }
    ],
    "sg:phone":"+41 22 788 87 69",
    "sg:postcode":"1216",
    "sg:province":"Gen\u00e8ve",
    "wof:name":"Beau-site P'tit Music'hohl Restaurant",
    "wof:placetype":"venue"
},
  "geometry": {"coordinates":[6.1098508835,46.2231864929],"type":"Point"}
}