{
  "type": "Feature",
  "properties": {
    "iso:country":"CH",
    "sg:address":"Obergasse 15 7205 Zizers. Postfach",
    "sg:city":"Zizers",
    "sg:orig_category":"Hardwareberatung",
    "sg:postcode":"7205",
    "sg:province":"Graubunden",
    "wof:name":"Veraguth Informatik",
    "wof:placetype":"venue"
},
  "geometry": {"coordinates":[9.5676393509,46.9352035522],"type":"Point"}
}