{
  "type": "Feature",
  "properties": {
    "iso:country":"CH",
    "sg:address":"Chemin De Tr\u00e8fle-blanc 16",
    "sg:city":"Plan-les-ouates",
    "sg:orig_category":"Unclassifiable Establishments",
    "sg:postcode":"1228",
    "sg:province":"Gen\u00e8ve",
    "wof:name":"E.l Production Sarl",
    "wof:placetype":"venue"
},
  "geometry": {"coordinates":[6.1263170242,46.1717224121],"type":"Point"}
}