{
  "type": "Feature",
  "properties": {
    "iso:country":"CH",
    "sg:address":"3212",
    "sg:city":"Gurmels",
    "sg:orig_category":"Detailhandel mit Fahrr\u00e4dern Handel mit Motorr\u00e4dern, Teilen U Zubeh\u00f6r Instandhaltung U Reparatur von ",
    "sg:phone":"+41 71 923 60 51",
    "sg:postcode":"3212",
    "sg:province":"Fribourg",
    "wof:name":"Jakob L\u00fcber Velos-motos",
    "wof:placetype":"venue"
},
  "geometry": {"coordinates":[9.0708179474,47.4434700012],"type":"Point"}
}