{
  "type": "Feature",
  "properties": {
    "iso:country":"CH",
    "sg:address":"Balmbergstrasse 38",
    "sg:city":"G\u00fcnsberg",
    "sg:orig_category":"RESTAURANTS: TEA-ROOMS",
    "sg:phone":"+41 71 385 11 13",
    "sg:postcode":"4524",
    "sg:province":"Solothurn",
    "wof:name":"Freihof Ag Gossau",
    "wof:placetype":"venue"
},
  "geometry": {"coordinates":[9.2402191162,47.4124641418],"type":"Point"}
}