{
  "type": "Feature",
  "properties": {
    "iso:country":"CH",
    "sg:address":"Winkelriedstrasse 7",
    "sg:city":"Bern",
    "sg:classifiers":[
        {
            "category":"Banks & Credit Unions",
            "subcategory":"Bureau De Change",
            "type":"Services"
        }
    ],
    "sg:phone":"+41 31 348 88 00",
    "sg:postcode":"3014",
    "sg:province":"Bern",
    "sg:tags":[
        "solution",
        "complete",
        "internet"
    ],
    "wof:name":"Mps Gmbh",
    "wof:placetype":"venue"
},
  "geometry": {"coordinates":[7.4639720917,46.9652175903],"type":"Point"}
}