{
  "type": "Feature",
  "properties": {
    "iso:country":"CH",
    "sg:address":"Seestrasse 137",
    "sg:city":"St\u00e4fa",
    "sg:orig_category":"Architektur U Ingenieurb\u00fcros Architekturb\u00fcros",
    "sg:phone":"+41 79 420 04 44",
    "sg:postcode":"8712",
    "sg:province":"Z\u00fcrich",
    "wof:name":"Schwarzwald & Beeler Architekturb\u00fcro",
    "wof:placetype":"venue"
},
  "geometry": {"coordinates":[8.731893,47.235561],"type":"Point"}
}