{
  "type": "Feature",
  "properties": {
    "iso:country":"CH",
    "sg:address":"Entre-deux-rivi\u00e8res 4",
    "sg:city":"Fleurier",
    "sg:classifiers":[
        {
            "category":"Shopping Center",
            "type":"Public Place"
        }
    ],
    "sg:phone":"+41 32 861 10 91",
    "sg:postcode":"2114",
    "sg:province":"Neuch\u00e2tel",
    "sg:tags":[
        "aluminium",
        "casting"
    ],
    "wof:name":"Gilles Petit S.a.",
    "wof:placetype":"venue"
},
  "geometry": {"coordinates":[6.585061,46.906166],"type":"Point"}
}