{
  "type": "Feature",
  "properties": {
    "addr:full":"G\u00fcterstrasse 216 4053 Basel. Postfach Basel Basel-Stadt 4051",
    "addr:housenumber":"216",
    "addr:postcode":"4053;4051",
    "addr:street":"Gueterstrasse;Postfach",
    "iso:country":"CH",
    "sg:address":"G\u00fcterstrasse 216 4053 Basel. Postfach",
    "sg:city":"Basel",
    "sg:orig_category":"Betrieb U technische Hilfsdienste des Kultur U Unterhaltungswesens Wirtschafts U Arbeitgeberverb\u00e4nde",
    "sg:phone":"+41 61 362 05 21",
    "sg:postcode":"4051",
    "sg:province":"Basel-Stadt",
    "wof:name":"Iranisches Kultur Und Handelszentrum, Imhof Zohreh",
    "wof:placetype":"venue"
},
  "geometry": {"coordinates":[7.595444,47.542442],"type":"Point"}
}