{
  "type": "Feature",
  "properties": {
    "iso:country":"CH",
    "sg:address":"Route D'ambilly 39",
    "sg:city":"Th\u00f4nex",
    "sg:orig_category":"RESTAURANTS: TEA-ROOMS",
    "sg:postcode":"1226",
    "sg:province":"Gen\u00e8ve",
    "wof:name":"Baresa Ag",
    "wof:placetype":"venue"
},
  "geometry": {"coordinates":[9.821603775,46.7966651917],"type":"Point"}
}