{
  "type": "Feature",
  "properties": {
    "iso:country":"CH",
    "sg:address":"Gare Avenue De La 2",
    "sg:city":"Montagne-moutier",
    "sg:orig_category":"Elektroinstallation",
    "sg:postcode":"2740",
    "sg:province":"Bern",
    "wof:name":"Renggli Willy, Entreprise G\u00e9n\u00e9rale D'\u00e9lectricit\u00e9",
    "wof:placetype":"venue"
},
  "geometry": {"coordinates":[7.3724632263,47.2787246704],"type":"Point"}
}