{
  "type": "Feature",
  "properties": {
    "iso:country":"CH",
    "sg:address":"Bahnhofstrasse 1 6210 Sursee. Postfach 3308",
    "sg:city":"Sursee",
    "sg:orig_category":"Detailhandel mit Bekleidung Herstellung von Sportger\u00e4ten",
    "sg:phone":"+41 41 921 26 20",
    "sg:postcode":"6210",
    "sg:province":"Luzern",
    "wof:name":"Sch\u00e4r-sport",
    "wof:placetype":"venue"
},
  "geometry": {"coordinates":[8.107999,47.172421],"type":"Point"}
}