{
  "type": "Feature",
  "properties": {
    "iso:country":"CH",
    "sg:address":"Z\u00fcrichstrasse 128 8600 D\u00fcbendorf. Postfach 612",
    "sg:city":"D\u00fcbendorf",
    "sg:orig_category":"Grosshandel mit Erzen U Metallen",
    "sg:phone":"+41 18238800",
    "sg:postcode":"8600",
    "sg:province":"Z\u00fcrich",
    "wof:name":"Firth Ag",
    "wof:placetype":"venue"
},
  "geometry": {"coordinates":[8.6000566483,47.3961372375],"type":"Point"}
}