{
  "type": "Feature",
  "properties": {
    "iso:country":"CH",
    "sg:address":"Alpenweg 28",
    "sg:city":"D\u00fcdingen",
    "sg:orig_category":"P\u00e9dicure",
    "sg:phone":"+41 26 493 17 77",
    "sg:postcode":"3186",
    "sg:province":"Fribourg",
    "wof:name":"Heidi Fasel P\u00e9dicure",
    "wof:placetype":"venue"
},
  "geometry": {"coordinates":[7.1882429123,46.8434867859],"type":"Point"}
}