{
  "type": "Feature",
  "properties": {
    "iso:country":"CH",
    "sg:address":"Galizistrasse 15",
    "sg:city":"Buttwil",
    "sg:orig_category":"Gesundheits U Sozialwesen",
    "sg:phone":"+41 56 664 74 81",
    "sg:postcode":"5632",
    "sg:province":"Aargau",
    "wof:name":"1amassagen",
    "wof:placetype":"venue"
},
  "geometry": {"coordinates":[8.3109931946,47.2663192749],"type":"Point"}
}