{
  "type": "Feature",
  "properties": {
    "iso:country":"CH",
    "sg:address":"Lueg 535",
    "sg:city":"Kaltacker",
    "sg:classifiers":[
        {
            "category":"Restaurant",
            "type":"Food & Drink"
        }
    ],
    "sg:phone":"+41 34 435 12 23",
    "sg:postcode":"3413",
    "sg:province":"Bern",
    "wof:name":"Restaurant Zur Lueg",
    "wof:placetype":"venue"
},
  "geometry": {"coordinates":[7.7180261612,47.0799827576],"type":"Point"}
}