{
  "type": "Feature",
  "properties": {
    "iso:country":"CH",
    "sg:address":"B\u00e4nikon",
    "sg:city":"Bissegg",
    "sg:orig_category":"Detailhandel mit Fleisch U Fleischwaren",
    "sg:phone":"+41 71 651 14 26",
    "sg:postcode":"8514",
    "sg:province":"Thurgau",
    "wof:name":"Walter Wirz Metzgerei",
    "wof:placetype":"venue"
},
  "geometry": {"coordinates":[9.0454864502,47.5620269775],"type":"Point"}
}