{
  "type": "Feature",
  "properties": {
    "iso:country":"CH",
    "sg:address":"Neuve Vie La 9",
    "sg:city":"Courgenay",
    "sg:orig_category":"Herstellung von Konstruktionsteilen, Fertigbauteilen U Ausbauelementen aus Holz",
    "sg:postcode":"2950",
    "sg:province":"Jura",
    "wof:name":"Comment Philippe",
    "wof:placetype":"venue"
},
  "geometry": {"coordinates":[7.1280908585,47.4011268616],"type":"Point"}
}