{
  "type": "Feature",
  "properties": {
    "iso:country":"CH",
    "sg:address":"Furrenstrasse 5",
    "sg:city":"Gersau",
    "sg:orig_category":"Erbringung von sonstigen Dienstleistungen f\u00fcr Unterhaltung, Erholung U Freizeit",
    "sg:phone":"+41 79 642 69 37",
    "sg:postcode":"6442",
    "sg:province":"Schwyz",
    "wof:name":"Mix Max Music, Gabriela Camenzind-k\u00e4lin",
    "wof:placetype":"venue"
},
  "geometry": {"coordinates":[8.5236749649,46.9929008484],"type":"Point"}
}