{
  "type": "Feature",
  "properties": {
    "iso:country":"CH",
    "sg:address":"Bischmattstrasse 7a",
    "sg:city":"Bettlach",
    "sg:orig_category":"Mechanik Mechanische Werkst\u00e4tten",
    "sg:phone":"+41 32 645 45 47",
    "sg:postcode":"2544",
    "sg:province":"Solothurn",
    "wof:name":"Meier Alfred, Mechanische Werkstatt Gmbh",
    "wof:placetype":"venue"
},
  "geometry": {"coordinates":[7.43105793,47.1964797974],"type":"Point"}
}