{
  "type": "Feature",
  "properties": {
    "iso:country":"CH",
    "sg:address":"L\u00e4ndernachstrasse 20 9435 Heerbrugg. Postfach",
    "sg:city":"Heerbrugg",
    "sg:orig_category":"Rechtsberatung",
    "sg:postcode":"9435",
    "sg:province":"St. Gallen",
    "wof:name":"Molar-dent Ag Widnau",
    "wof:placetype":"venue"
},
  "geometry": {"coordinates":[9.626955986,47.4117050171],"type":"Point"}
}