{
  "type": "Feature",
  "properties": {
    "iso:country":"CH",
    "sg:address":"Berghaus Oberb\u00f6lchen",
    "sg:city":"Eptingen",
    "sg:orig_category":"Dienstleistungen in der Tierhaltung Tierhaltung",
    "sg:phone":"+41 81 756 31 47",
    "sg:postcode":"4458",
    "sg:province":"Basel-Landschaft",
    "wof:name":"Hundeschule Villa Bunterhund",
    "wof:placetype":"venue"
},
  "geometry": {"coordinates":[9.4843969345,47.165435791],"type":"Point"}
}