{
  "type": "Feature",
  "properties": {
    "iso:country":"CH",
    "sg:address":"4539",
    "sg:city":"Rumisberg",
    "sg:orig_category":"RESTAURANTS: TEA-ROOMS",
    "sg:postcode":"4539",
    "sg:province":"Bern",
    "wof:name":"Felber Hans J\u00fcrg, Restaurant Jura",
    "wof:placetype":"venue"
},
  "geometry": {"coordinates":[7.642095089,47.2641410828],"type":"Point"}
}