{
  "type": "Feature",
  "properties": {
    "iso:country":"CH",
    "sg:address":"Halsgasse 24",
    "sg:city":"Rapperswil",
    "sg:classifiers":[
        {
            "category":"Professional",
            "subcategory":"Management & Consulting",
            "type":"Services"
        }
    ],
    "sg:phone":"+41 55 214 22 92",
    "sg:postcode":"8640",
    "sg:province":"Schwyz",
    "sg:tags":[
        "project"
    ],
    "wof:name":"Pass Technologies Ag",
    "wof:placetype":"venue"
},
  "geometry": {"coordinates":[8.8189058304,47.2278251648],"type":"Point"}
}