{
  "type": "Feature",
  "properties": {
    "iso:country":"CH",
    "sg:address":"Bahnhofstrasse 11a 8586 Erlen. Postfach 122",
    "sg:city":"Erlen",
    "sg:orig_category":"Detailhandel mit Fleisch U Fleischwaren",
    "sg:phone":"+41 71 648 20 22",
    "sg:postcode":"8586",
    "sg:province":"Thurgau",
    "wof:name":"Frisch-fleisch-markt",
    "wof:placetype":"venue"
},
  "geometry": {"coordinates":[9.2259540558,47.5509567261],"type":"Point"}
}