{
  "type": "Feature",
  "properties": {
    "iso:country":"CH",
    "sg:address":"Neuenhoferstrasse 101",
    "sg:city":"Baden",
    "sg:classifiers":[
        {
            "category":"Professional",
            "subcategory":"Advertising",
            "type":"Services"
        }
    ],
    "sg:phone":"+41 56 203 25 00",
    "sg:postcode":"5400",
    "sg:province":"Aargau",
    "sg:tags":[
        "marketing",
        "direct"
    ],
    "wof:name":"Kik Ag",
    "wof:placetype":"venue"
},
  "geometry": {"coordinates":[8.3077106476,47.4633331299],"type":"Point"}
}