{
  "type": "Feature",
  "properties": {
    "addr:full":"T\u00f6distrasse 1 Tuggen Schwyz 8856",
    "addr:housenumber":"1",
    "addr:postcode":"8856",
    "addr:street":"Toedistrasse;Schwyz",
    "iso:country":"CH",
    "sg:address":"T\u00f6distrasse 1",
    "sg:city":"Tuggen",
    "sg:orig_category":"Detailhandel mit Brot, Back U S\u00fcsswaren",
    "sg:phone":"+41 55 445 11 30",
    "sg:postcode":"8856",
    "sg:province":"Schwyz",
    "wof:name":"B\u00e4ckerei-konditorei Janser Gmbh",
    "wof:placetype":"venue"
},
  "geometry": {"coordinates":[8.943246,47.202309],"type":"Point"}
}