{
  "type": "Feature",
  "properties": {
    "iso:country":"CH",
    "sg:address":"Rue Du Grand-pont 4",
    "sg:city":"Lausanne",
    "sg:orig_category":"Detailhandel mit Damenbekleidung",
    "sg:phone":"+41 21 323 40 22",
    "sg:postcode":"1003",
    "sg:province":"Vaud",
    "wof:name":"Lasacoche Sa. Boutiques D'articles De Mode, Maroquinerie Et Autres.",
    "wof:placetype":"venue"
},
  "geometry": {"coordinates":[6.631347,46.520771],"type":"Point"}
}