{
  "type": "Feature",
  "properties": {
    "iso:country":"CH",
    "sg:address":"Route De Denges 30",
    "sg:city":"Lonay",
    "sg:orig_category":"Verlegen von Fliesen U Platten",
    "sg:phone":"+41 21 802 33 49",
    "sg:postcode":"1027",
    "sg:province":"Vaud",
    "wof:name":"Raymond Burgy Entreprise De Carrelage",
    "wof:placetype":"venue"
},
  "geometry": {"coordinates":[6.5295290947,46.527885437],"type":"Point"}
}