{
  "type": "Feature",
  "properties": {
    "iso:country":"CH",
    "sg:address":"Unterm\u00fchlestrasse 14",
    "sg:city":"Cham",
    "sg:orig_category":"Sonstige mit der Informatik verbundene T\u00e4tigkeiten",
    "sg:phone":"+41 41 740 20 86",
    "sg:postcode":"6330",
    "sg:province":"Zug",
    "wof:name":"Happy Window Pfeiffer C.",
    "wof:placetype":"venue"
},
  "geometry": {"coordinates":[8.445854187,47.196231842],"type":"Point"}
}