{
  "type": "Feature",
  "properties": {
    "iso:country":"CH",
    "sg:address":"Ueberlandstrasse 327 8051 Z\u00fcrich. Postfach",
    "sg:city":"Z\u00fcrich",
    "sg:orig_category":"Zimmerei, Dachdeckerei, Bauspenglerei U Abdichtung",
    "sg:postcode":"8051",
    "sg:province":"Z\u00fcrich",
    "wof:name":"Sahinovic Ilfad Spenglerei",
    "wof:placetype":"venue"
},
  "geometry": {"coordinates":[8.5806341171,47.4087944031],"type":"Point"}
}