{
  "type": "Feature",
  "properties": {
    "iso:country":"CH",
    "sg:address":"3532",
    "sg:city":"Mirchel",
    "sg:orig_category":"Landesverteidigung, Sozialversicherung \u00d6ffentliche Verwaltung",
    "sg:phone":"+41 31 711 16 14",
    "sg:postcode":"3532",
    "sg:province":"Bern",
    "wof:name":"Zivilschutzstelle Mirchel",
    "wof:placetype":"venue"
},
  "geometry": {"coordinates":[7.6473450661,46.8940315247],"type":"Point"}
}