{
  "type": "Feature",
  "properties": {
    "iso:country":"CH",
    "sg:address":"M\u00fcllerstrasse 2 2562 Port. Postfach",
    "sg:city":"Port",
    "sg:orig_category":"Grosshandel mit Werkzeugmaschinen",
    "sg:phone":"+41 32 332 84 44",
    "sg:postcode":"2562",
    "sg:province":"Bern",
    "wof:name":"Perfecbore Werkzeugmaschinen Ag",
    "wof:placetype":"venue"
},
  "geometry": {"coordinates":[7.2572021484,47.1166000366],"type":"Point"}
}