{
  "type": "Feature",
  "properties": {
    "iso:country":"CH",
    "sg:address":"H\u00f6lzli 155",
    "sg:city":"Wattenwil",
    "sg:orig_category":"P\u00e9dicure",
    "sg:phone":"+41 62 873 24 36",
    "sg:postcode":"3665",
    "sg:province":"Bern",
    "wof:name":"Ursula Obrist P\u00e9dicure",
    "wof:placetype":"venue"
},
  "geometry": {"coordinates":[7.9516158104,47.5460395813],"type":"Point"}
}