{
  "type": "Feature",
  "properties": {
    "iso:country":"CH",
    "sg:address":"Grandes-communes Av. Des 44 1213 Onex. Postfach",
    "sg:city":"Onex",
    "sg:orig_category":"Detailhandel mit Waren verschiedener Art, Hauptrichtung Nahrungsmittel",
    "sg:postcode":"1213",
    "sg:province":"Gen\u00e8ve",
    "wof:name":"Saveur 2000 S\u00e0rl Produits Alimentaires Ou Manufactur\u00e9s Etc.; Im, Export.",
    "wof:placetype":"venue"
},
  "geometry": {"coordinates":[6.1028661728,46.1920776367],"type":"Point"}
}