{
  "type": "Feature",
  "properties": {
    "iso:country":"CH",
    "sg:address":"Innpark",
    "sg:city":"Celerina",
    "sg:orig_category":"Detailhandel mit elektrischen Haushalts-,Radio U Fernsehger\u00e4ten sowie Musikinstrumenten",
    "sg:postcode":"7505",
    "sg:province":"Graubunden",
    "wof:name":"Musica Et Ars Libera, Dr. J\u00fcrg Frei",
    "wof:placetype":"venue"
},
  "geometry": {"coordinates":[9.8600702286,46.5126800537],"type":"Point"}
}