{
  "type": "Feature",
  "properties": {
    "iso:country":"CH",
    "sg:address":"9425",
    "sg:city":"Thal",
    "sg:orig_category":"Herstellung von Papier, Karton U Pappe Herstellung von Wellpapier U pappe sowie von Verpackungsmitte",
    "sg:phone":"+41 71 744 66 10",
    "sg:postcode":"9425",
    "sg:province":"St. Gallen",
    "wof:name":"E. Ittensohn Ag Verpackungen",
    "wof:placetype":"venue"
},
  "geometry": {"coordinates":[9.6346359253,47.4533653259],"type":"Point"}
}