{
  "type": "Feature",
  "properties": {
    "iso:country":"CH",
    "sg:address":"Rebenstrasse 67",
    "sg:city":"Z\u00fcrich",
    "sg:orig_category":"Primarschulen",
    "sg:phone":"+41 14825595",
    "sg:postcode":"8041",
    "sg:province":"Z\u00fcrich",
    "wof:name":"Primarschule Falletsche",
    "wof:placetype":"venue"
},
  "geometry": {"coordinates":[8.5158987045,47.3340377808],"type":"Point"}
}