{
  "type": "Feature",
  "properties": {
    "iso:country":"CH",
    "sg:address":"6213",
    "sg:city":"Knutwil",
    "sg:orig_category":"Detailhandel mit Milcherzeugnissen U Eiern Verarbeitung von Milch",
    "sg:postcode":"6213",
    "sg:province":"Luzern",
    "wof:name":"K\u00e4sereigenossenschaft",
    "wof:placetype":"venue"
},
  "geometry": {"coordinates":[8.0723752975,47.1991119385],"type":"Point"}
}