{
  "type": "Feature",
  "properties": {
    "addr:full":"Albulastrasse 24 Z\u00fcrich Z\u00fcrich 8048",
    "addr:housenumber":"24",
    "addr:postcode":"8048",
    "addr:street":"Albulastrasse",
    "iso:country":"CH",
    "sg:address":"Albulastrasse 24",
    "sg:city":"Z\u00fcrich",
    "sg:orig_category":"Bauschreinerei Innenausbau",
    "sg:phone":"+41 14920855",
    "sg:postcode":"8048",
    "sg:province":"Z\u00fcrich",
    "wof:name":"C & R Schreinerei Ag M\u00f6bel Nach Mass",
    "wof:placetype":"venue"
},
  "geometry": {"coordinates":[8.494612,47.387928],"type":"Point"}
}