{
  "type": "Feature",
  "properties": {
    "iso:country":"CH",
    "sg:address":"Boulevard De P\u00e9rolles 35",
    "sg:city":"Fribourg",
    "sg:orig_category":"Detailhandel mit Zeitungen U Zeitschriften Kioske",
    "sg:phone":"+41 26 424 83 34",
    "sg:postcode":"1700",
    "sg:province":"Fribourg",
    "wof:name":"Franz Buser Kiosque Du Domino",
    "wof:placetype":"venue"
},
  "geometry": {"coordinates":[7.1534409523,46.7978172302],"type":"Point"}
}