{
  "type": "Feature",
  "properties": {
    "iso:country":"CH",
    "sg:address":"R\u00f6telstrasse 39",
    "sg:city":"Z\u00fcrich",
    "sg:orig_category":"Herstellung von \u00d6fen U Brennern Sanit\u00e4r U Heizungsinstallation",
    "sg:phone":"+41 13635430",
    "sg:postcode":"8037",
    "sg:province":"Z\u00fcrich",
    "wof:name":"Monarch Feuerungsservice Tr\u00fcmpy Josef",
    "wof:placetype":"venue"
},
  "geometry": {"coordinates":[8.5342597961,47.3930091858],"type":"Point"}
}