{
  "type": "Feature",
  "properties": {
    "iso:country":"CH",
    "sg:address":"Grandes Forges 2",
    "sg:city":"Vallorbe",
    "sg:orig_category":"Sportvereine P\u00e9tanque",
    "sg:postcode":"1337",
    "sg:province":"Vaud",
    "wof:name":"P\u00e9tanque-club L'ecureuil",
    "wof:placetype":"venue"
},
  "geometry": {"coordinates":[6.9233999252,46.6991119385],"type":"Point"}
}