{
  "type": "Feature",
  "properties": {
    "iso:country":"CH",
    "sg:address":"Bugnons Rue Des 6",
    "sg:city":"Meyrin",
    "sg:orig_category":"Sanit\u00e4r, Heizungs U L\u00fcftungsinstallation",
    "sg:postcode":"1217",
    "sg:province":"Gen\u00e8ve",
    "wof:name":"Senalada Miguel",
    "wof:placetype":"venue"
},
  "geometry": {"coordinates":[6.0767412186,46.2365608215],"type":"Point"}
}