{
  "type": "Feature",
  "properties": {
    "iso:country":"CH",
    "sg:address":"3401 Burgdorf. Postfach 647",
    "sg:city":"Burgdorf",
    "sg:orig_category":"Interessenvertretungen U sonstige Vereinigungen",
    "sg:postcode":"3401",
    "sg:province":"Bern",
    "wof:name":"Kant.-bern.eishockey-verband",
    "wof:placetype":"venue"
},
  "geometry": {"coordinates":[7.6269898415,47.056438446],"type":"Point"}
}