{
  "type": "Feature",
  "properties": {
    "iso:country":"CH",
    "sg:address":"Norastrasse 5",
    "sg:city":"Z\u00fcrich",
    "sg:orig_category":"Allgemeiner Hoch U Tiefbau",
    "sg:phone":"+41 14969060",
    "sg:postcode":"8001",
    "sg:province":"Z\u00fcrich",
    "wof:name":"R\u00fcegg + Ringger Verwaltungs Ag",
    "wof:placetype":"venue"
},
  "geometry": {"coordinates":[8.507145,47.380009],"type":"Point"}
}