{
  "type": "Feature",
  "properties": {
    "iso:country":"CH",
    "sg:address":"Luzernerstrasse",
    "sg:city":"Berom\u00fcnster",
    "sg:orig_category":"Geometerb\u00fcros",
    "sg:phone":"+41 41 930 24 74",
    "sg:postcode":"6215",
    "sg:province":"Luzern",
    "wof:name":"Alex Aregger Ingenieur-& Vermessungsb\u00fcro",
    "wof:placetype":"venue"
},
  "geometry": {"coordinates":[8.1995601654,47.2046737671],"type":"Point"}
}