{
  "type": "Feature",
  "properties": {
    "iso:country":"CH",
    "sg:address":"Duggelimatt 9 6330 Cham. Postfach 10",
    "sg:city":"Cham",
    "sg:orig_category":"Gartenbau",
    "sg:phone":"+41 41 780 39 74",
    "sg:postcode":"6330",
    "sg:province":"Zug",
    "wof:name":"Bucher Gartenbau Ag",
    "wof:placetype":"venue"
},
  "geometry": {"coordinates":[8.470656395,47.1839675903],"type":"Point"}
}