{
  "type": "Feature",
  "properties": {
    "iso:country":"CH",
    "sg:address":"Baarerstrasse 112",
    "sg:city":"Zug",
    "sg:orig_category":"Rechtsberatung",
    "sg:postcode":"6300",
    "sg:province":"Zug",
    "wof:name":"Gentech Investment Group Ag Immaterialg\u00fcterrechte, Bes. Marken, Patente, Muster, Modelle; Erwerb, Nutzung, Lizenzierung, Ver\u00e4usserung",
    "wof:placetype":"venue"
},
  "geometry": {"coordinates":[8.5190229416,47.1802215576],"type":"Point"}
}