{
  "type": "Feature",
  "properties": {
    "iso:country":"CH",
    "sg:address":"Staffeleggstrasse 35",
    "sg:city":"K\u00fcttigen",
    "sg:orig_category":"Instandhaltung U Reparatur von Automobilen",
    "sg:phone":"+41 22 796 76 11",
    "sg:postcode":"5024",
    "sg:province":"Aargau",
    "wof:name":"A.& P. Defago Carrosserie Nouvelle",
    "wof:placetype":"venue"
},
  "geometry": {"coordinates":[6.0996408463,46.2076072693],"type":"Point"}
}