{
  "type": "Feature",
  "properties": {
    "addr:full":"Hauptstrasse 57 Kreuzlingen Thurgau 8280",
    "addr:housenumber":"57",
    "addr:postcode":"8280",
    "addr:street":"Hauptstrasse",
    "iso:country":"CH",
    "sg:address":"Hauptstrasse 57",
    "sg:city":"Kreuzlingen",
    "sg:orig_category":"Detailhandel mit Brot, Back U S\u00fcsswaren",
    "sg:phone":"+41 71 669 17 69",
    "sg:postcode":"8280",
    "sg:province":"Thurgau",
    "wof:name":"Christian Walz B\u00e4ckerei-konditorei",
    "wof:placetype":"venue"
},
  "geometry": {"coordinates":[9.17509,47.648563],"type":"Point"}
}