{
  "type": "Feature",
  "properties": {
    "iso:country":"CH",
    "sg:address":"Winkelstrasse 15",
    "sg:city":"Horw",
    "sg:orig_category":"Grosshandel mit B\u00fcromaschinen Grosshandel mit Datenverarbeitungsger\u00e4ten",
    "sg:phone":"+41 41 340 55 77",
    "sg:postcode":"6048",
    "sg:province":"Luzern",
    "wof:name":"Andro-data",
    "wof:placetype":"venue"
},
  "geometry": {"coordinates":[8.3177471161,47.0129890442],"type":"Point"}
}