{
  "type": "Feature",
  "properties": {
    "iso:country":"CH",
    "sg:address":"Dorfstrasse 11",
    "sg:city":"Sch\u00f6ftland",
    "sg:orig_category":"Detailhandel mit Fleisch U Fleischwaren HOTELS: MIT RESTAURANT",
    "sg:phone":"+41 62 721 12 12",
    "sg:postcode":"5040",
    "sg:province":"Aargau",
    "wof:name":"E. + E. Schneider Ag",
    "wof:placetype":"venue"
},
  "geometry": {"coordinates":[8.0511417389,47.3050117493],"type":"Point"}
}