{
  "type": "Feature",
  "properties": {
    "iso:country":"CH",
    "sg:address":"Grand-pr\u00e9 Rue Du 25 1202 Gen\u00e8ve. Postfach",
    "sg:city":"Gen\u00e8ve",
    "sg:orig_category":"RESTAURANTS: TEA-ROOMS",
    "sg:postcode":"1202",
    "sg:province":"Gen\u00e8ve",
    "wof:name":"Monique Constantin",
    "wof:placetype":"venue"
},
  "geometry": {"coordinates":[6.1357841492,46.2138824463],"type":"Point"}
}