{
  "type": "Feature",
  "properties": {
    "iso:country":"CH",
    "sg:address":"Rotbuchstrasse 66",
    "sg:city":"Z\u00fcrich",
    "sg:orig_category":"Detailhandel mit Brot, Back U S\u00fcsswaren",
    "sg:phone":"+41 13610089",
    "sg:postcode":"8037",
    "sg:province":"Z\u00fcrich",
    "wof:name":"Anton Stadelmann B\u00e4ckerei-konditorei",
    "wof:placetype":"venue"
},
  "geometry": {"coordinates":[8.530749,47.393307],"type":"Point"}
}