{
  "type": "Feature",
  "properties": {
    "addr:full":"Leimenweg 9 Lupsingen Basel-Landschaft 4419",
    "addr:housenumber":"9",
    "addr:postcode":"4419",
    "addr:street":"Leimenweg",
    "iso:country":"CH",
    "sg:address":"Leimenweg 9",
    "sg:city":"Lupsingen",
    "sg:orig_category":"Bauingenieurb\u00fcros Heizung L\u00fcftung Klima",
    "sg:phone":"+41 22 343 81 40",
    "sg:postcode":"4419",
    "sg:province":"Basel-Landschaft",
    "wof:name":"Daniel Reiser Bureau D'ing\u00e9nieur",
    "wof:placetype":"venue"
},
  "geometry": {"coordinates":[6.132345,46.188015],"type":"Point"}
}