{
  "type": "Feature",
  "properties": {
    "iso:country":"CH",
    "sg:address":"Route D'erbignon 14b",
    "sg:city":"Conthey",
    "sg:classifiers":[
        {
            "category":"Insurance",
            "subcategory":"Insurance Agent",
            "type":"Services"
        }
    ],
    "sg:phone":"+41 79 221 12 08",
    "sg:postcode":"1964",
    "sg:province":"Valais",
    "sg:tags":[
        "versicherungsagenturen",
        "-broker"
    ],
    "wof:name":"Pierre Germanier Zurich Assurances",
    "wof:placetype":"venue"
},
  "geometry": {"coordinates":[7.2931518555,46.2272949219],"type":"Point"}
}