{
  "type": "Feature",
  "properties": {
    "iso:country":"CH",
    "sg:address":"Freilagerstrasse 47",
    "sg:city":"Z\u00fcrich",
    "sg:orig_category":"Detailhandel mit M\u00f6beln U Haushaltsgegenst\u00e4nden Grosshandel mit M\u00f6beln, Wohnbedarf, Teppichen U Bode",
    "sg:phone":"+41 62 776 01 26",
    "sg:postcode":"8043",
    "sg:province":"Z\u00fcrich",
    "wof:name":"Sit Mobilia Ag",
    "wof:placetype":"venue"
},
  "geometry": {"coordinates":[8.1199712753,47.3283424377],"type":"Point"}
}