{
  "type": "Feature",
  "properties": {
    "iso:country":"CH",
    "sg:address":"Langgartenweg 10",
    "sg:city":"Allschwil",
    "sg:orig_category":"Sanit\u00e4r U Heizungsinstallation Sanit\u00e4r, Heizungs U L\u00fcftungsinstallation",
    "sg:phone":"+41 61 481 93 68",
    "sg:postcode":"4123",
    "sg:province":"Basel-Landschaft",
    "wof:name":"R. Rossi Heizungen & Brennerservice Gmbh",
    "wof:placetype":"venue"
},
  "geometry": {"coordinates":[7.538380146,47.5505104065],"type":"Point"}
}