{
  "type": "Feature",
  "properties": {
    "iso:country":"CH",
    "sg:address":"Spillg\u00e4ssli 19",
    "sg:city":"Eich",
    "sg:orig_category":"Markt U Meinungsforschung",
    "sg:phone":"+41 41 610 91 44",
    "sg:postcode":"6205",
    "sg:province":"Luzern",
    "wof:name":"Triaxe Bulliard Analysen & Entwicklung",
    "wof:placetype":"venue"
},
  "geometry": {"coordinates":[8.1632080078,47.1527442932],"type":"Point"}
}