{
  "type": "Feature",
  "properties": {
    "iso:country":"CH",
    "sg:address":"Avenue Du L\u00e9man 71",
    "sg:city":"Lausanne",
    "sg:orig_category":"Fahrschulen, Flugschulen",
    "sg:phone":"+41 79 439 64 65",
    "sg:postcode":"1005",
    "sg:province":"Vaud",
    "wof:name":"Herbert Ackermann Autofahrschule",
    "wof:placetype":"venue"
},
  "geometry": {"coordinates":[7.5923790932,47.4709892273],"type":"Point"}
}