{
  "type": "Feature",
  "properties": {
    "iso:country":"CH",
    "sg:address":"Schwalbenweg 57",
    "sg:city":"Frauenfeld",
    "sg:orig_category":"Sportvereine Alpinismus",
    "sg:phone":"+41 52 745 21 13",
    "sg:postcode":"8500",
    "sg:province":"Thurgau",
    "wof:name":"Sac Sektion Thurgau",
    "wof:placetype":"venue"
},
  "geometry": {"coordinates":[8.9004898071,47.551361084],"type":"Point"}
}