{
  "type": "Feature",
  "properties": {
    "iso:country":"CH",
    "sg:address":"Schaffhauserstrasse 143",
    "sg:city":"Z\u00fcrich",
    "sg:orig_category":"Unternehmensberatung",
    "sg:postcode":"8057",
    "sg:province":"Z\u00fcrich",
    "wof:name":"Data Top Gmbh",
    "wof:placetype":"venue"
},
  "geometry": {"coordinates":[8.5413312912,47.3979110718],"type":"Point"}
}