{
  "type": "Feature",
  "properties": {
    "addr:full":"C. F. L. Lohnerstrasse 22 Gwatt Bern 3645",
    "addr:housenumber":"22",
    "addr:postcode":"3645",
    "addr:street":"C.;L. Lohnerstrasse",
    "iso:country":"CH",
    "sg:address":"C. F. L. Lohnerstrasse 22",
    "sg:city":"Gwatt",
    "sg:classifiers":[
        {
            "category":"Autos & Motor Vehicles",
            "subcategory":"Auto Supplies",
            "type":"Retail Goods"
        }
    ],
    "sg:phone":"+41 33 334 54 40",
    "sg:postcode":"3645",
    "sg:province":"Bern",
    "sg:tags":[
        "body",
        "car",
        "truck",
        "trailer",
        "superstructure"
    ],
    "wof:name":"Ernst Keller Ag",
    "wof:placetype":"venue"
},
  "geometry": {"coordinates":[7.619465,46.732868],"type":"Point"}
}