{
  "type": "Feature",
  "properties": {
    "iso:country":"CH",
    "sg:address":"Roosstrasse 32",
    "sg:city":"Wollerau",
    "sg:orig_category":"Installation von Heizungs, L\u00fcftungs U Klimaanlagen Sanit\u00e4r U Heizungsinstallation",
    "sg:phone":"+41 17875959",
    "sg:postcode":"8832",
    "sg:province":"Schwyz",
    "wof:name":"Gebr. Steimen Ag Heizung L\u00fcftung",
    "wof:placetype":"venue"
},
  "geometry": {"coordinates":[8.7199697495,47.1913490295],"type":"Point"}
}