{
  "type": "Feature",
  "properties": {
    "iso:country":"CH",
    "sg:address":"Postfach 3964",
    "sg:city":"Luzern",
    "sg:classifiers":[
        {
            "category":"Manufacturing",
            "subcategory":"Metals",
            "type":"Manufacturing & Wholesale Goods"
        }
    ],
    "sg:phone":"+41 33 334 56 56",
    "sg:postcode":"6002",
    "sg:province":"Luzern",
    "sg:tags":[
        "-",
        "machine",
        "equipment",
        "engineering",
        "machinery",
        "mechanical"
    ],
    "wof:name":"Nobag Nobs Engineering Ag",
    "wof:placetype":"venue"
},
  "geometry": {"coordinates":[7.6173901558,46.7084465027],"type":"Point"}
}