{
  "type": "Feature",
  "properties": {
    "iso:country":"CH",
    "sg:address":"Elisabeth-frei-strasse 12 2540 Grenchen. Postfach",
    "sg:city":"Grenchen",
    "sg:orig_category":"Zimmerei, Dachdeckerei, Bauspenglerei U Abdichtung",
    "sg:phone":"+41 26 652 23 35",
    "sg:postcode":"2540",
    "sg:province":"Solothurn",
    "wof:name":"Dafflon Pierre",
    "wof:placetype":"venue"
},
  "geometry": {"coordinates":[6.9275698662,46.6799888611],"type":"Point"}
}