{
  "type": "Feature",
  "properties": {
    "addr:full":"Girhaldenstrasse 22 Z\u00fcrich Z\u00fcrich 8048",
    "addr:housenumber":"22",
    "addr:postcode":"8048",
    "addr:street":"Girhaldenstrasse",
    "iso:country":"CH",
    "sg:address":"Girhaldenstrasse 22",
    "sg:city":"Z\u00fcrich",
    "sg:orig_category":"Aktivit\u00e4ten der Generalunternehmen im Baugewerbe Stukkateurgewerbe, Gipserei U Verputzerei",
    "sg:phone":"+41 14320656",
    "sg:postcode":"8048",
    "sg:province":"Z\u00fcrich",
    "wof:name":"Randazzo S. Ag",
    "wof:placetype":"venue"
},
  "geometry": {"coordinates":[8.478034,47.388729],"type":"Point"}
}