{
  "type": "Feature",
  "properties": {
    "iso:country":"CH",
    "sg:address":"Le Bosquet 1854 Leysin. Postfach",
    "sg:city":"Leysin",
    "sg:orig_category":"RESTAURANTS: TEA-ROOMS",
    "sg:postcode":"1854",
    "sg:province":"Vaud",
    "wof:name":"Titanic Imbiss Bar Gmbh Schnellimbiss",
    "wof:placetype":"venue"
},
  "geometry": {"coordinates":[9.0431556702,47.4620552063],"type":"Point"}
}