{
  "type": "Feature",
  "properties": {
    "iso:country":"CH",
    "sg:address":"Obere D\u00fcrrm\u00fchlestrasse 10",
    "sg:city":"Niederbipp",
    "sg:orig_category":"Mechanische Werkst\u00e4tten Schmieden",
    "sg:phone":"+41 32 633 15 40",
    "sg:postcode":"4704",
    "sg:province":"Bern",
    "wof:name":"Gottfried Iff Mech.werkst\u00e4tte & Schmiede",
    "wof:placetype":"venue"
},
  "geometry": {"coordinates":[7.6898131371,47.2711219788],"type":"Point"}
}