{
  "type": "Feature",
  "properties": {
    "iso:country":"CH",
    "sg:address":"Am Luzerbach 10",
    "sg:city":"Adligenswil",
    "sg:orig_category":"Herstellung von Werkzeugen",
    "sg:postcode":"6043",
    "sg:province":"Luzern",
    "wof:name":"Robutec Gmbh",
    "wof:placetype":"venue"
},
  "geometry": {"coordinates":[9.505777359,47.4444656372],"type":"Point"}
}