{
  "type": "Feature",
  "properties": {
    "iso:country":"CH",
    "sg:address":"Via Gana",
    "sg:city":"Novaggio",
    "sg:classifiers":[
        {
            "category":"Travel",
            "subcategory":"Hotels & Motels",
            "type":"Entertainment"
        }
    ],
    "sg:phone":"+41 91 606 31 04",
    "sg:postcode":"6986",
    "sg:province":"Ticino",
    "sg:tags":[
        "hotels",
        "mit",
        "restaurant"
    ],
    "wof:name":"Albergo Villa Monna Lisa",
    "wof:placetype":"venue"
},
  "geometry": {"coordinates":[8.8599700928,46.0091285706],"type":"Point"}
}