{
  "type": "Feature",
  "properties": {
    "iso:country":"CH",
    "sg:address":"Herzentalstrasse 5",
    "sg:city":"Dornach",
    "sg:orig_category":"Non-Classified Establishments",
    "sg:phone":"+41 61 706 94 24",
    "sg:postcode":"4143",
    "sg:province":"Solothurn",
    "wof:name":"Loh Holding Ag",
    "wof:placetype":"venue"
},
  "geometry": {"coordinates":[7.613134861,47.4854545593],"type":"Point"}
}