{
  "type": "Feature",
  "properties": {
    "iso:country":"CH",
    "sg:address":"Avenue De Fully 14",
    "sg:city":"Martigny",
    "sg:orig_category":"Fachdetailhandel in Verkaufsr\u00e4umen",
    "sg:postcode":"1920",
    "sg:province":"Valais",
    "wof:name":"Collombin Et Gaia",
    "wof:placetype":"venue"
},
  "geometry": {"coordinates":[7.0763301849,46.1073722839],"type":"Point"}
}