{
  "type": "Feature",
  "properties": {
    "iso:country":"CH",
    "sg:address":"Gerlikonerstrasse 11",
    "sg:city":"Frauenfeld",
    "sg:orig_category":"Vorschulen, Kinderg\u00e4rten",
    "sg:phone":"+41 52 720 16 29",
    "sg:postcode":"8500",
    "sg:province":"Thurgau",
    "wof:name":"Kindergarten Ergaten",
    "wof:placetype":"venue"
},
  "geometry": {"coordinates":[8.8900222778,47.5516700745],"type":"Point"}
}