{
  "type": "Feature",
  "properties": {
    "iso:country":"CH",
    "sg:address":"G\u00e4uggelistrasse 4",
    "sg:city":"Chur",
    "sg:orig_category":"Detailhandel mit Blumen U Pflanzen",
    "sg:phone":"+41 33 951 13 72",
    "sg:postcode":"7000",
    "sg:province":"Graubunden",
    "wof:name":"Paul Kunz Blumengesch\u00e4ft",
    "wof:placetype":"venue"
},
  "geometry": {"coordinates":[8.0252,46.755878],"type":"Point"}
}