{
  "type": "Feature",
  "properties": {
    "iso:country":"CH",
    "sg:address":"Chemin Des Ducats 1350 Orbe. Postfach",
    "sg:city":"Orbe",
    "sg:orig_category":"Sonstige Kultur U Unterhaltungseinrichtungen",
    "sg:phone":"+41 24 441 50 98",
    "sg:postcode":"1350",
    "sg:province":"Vaud",
    "wof:name":"Centro Portugu\u00eas Z.i.",
    "wof:placetype":"venue"
},
  "geometry": {"coordinates":[6.5309619904,46.7247772217],"type":"Point"}
}