{
  "type": "Feature",
  "properties": {
    "iso:country":"CH",
    "sg:address":"Obere Gasse 23",
    "sg:city":"Chur",
    "sg:orig_category":"Detailhandel mit Beleuchtungs U Haushaltsgegenst\u00e4nden Detailhandel mit elektrischen Haushalts-,Radio",
    "sg:phone":"+41 41 460 12 15",
    "sg:postcode":"7000",
    "sg:province":"Graubunden",
    "wof:name":"Kupper Eugen",
    "wof:placetype":"venue"
},
  "geometry": {"coordinates":[8.223583,47.131149],"type":"Point"}
}