{
  "type": "Feature",
  "properties": {
    "iso:country":"CH",
    "sg:address":"Oberhofstrasse 1",
    "sg:city":"Elgg",
    "sg:orig_category":"Sonstige mit Sport verbundene T\u00e4tigkeiten",
    "sg:phone":"+41 52 364 10 21",
    "sg:postcode":"8353",
    "sg:province":"Z\u00fcrich",
    "wof:name":"Weier Paul",
    "wof:placetype":"venue"
},
  "geometry": {"coordinates":[8.8696098328,47.4909591675],"type":"Point"}
}