{
  "type": "Feature",
  "properties": {
    "iso:country":"CH",
    "sg:address":"Technikumstrasse 82 8400 Winterthur. Postfach",
    "sg:city":"Winterthur",
    "sg:orig_category":"Pensionskassen",
    "sg:phone":"+41 52 212 73 22",
    "sg:postcode":"8401",
    "sg:province":"Z\u00fcrich",
    "wof:name":"Personalf\u00fcrsorge Der Firma Hartmann L.- Unfallverh\u00fctung, Ag, Winterthur",
    "wof:placetype":"venue"
},
  "geometry": {"coordinates":[8.7261610031,47.4981803894],"type":"Point"}
}