{
  "type": "Feature",
  "properties": {
    "iso:country":"CH",
    "sg:address":"Route De Pr\u00e9-marais 20",
    "sg:city":"Bernex",
    "sg:orig_category":"Allgemeiner Hoch U Tiefbau Gewinnung von Kies U Sand",
    "sg:phone":"+41 22 850 02 90",
    "sg:postcode":"1233",
    "sg:province":"Gen\u00e8ve",
    "wof:name":"Perrin Fr\u00e8res Sa",
    "wof:placetype":"venue"
},
  "geometry": {"coordinates":[6.079208,46.179977],"type":"Point"}
}