{
  "type": "Feature",
  "properties": {
    "iso:country":"CH",
    "sg:address":"Rue Fran\u00e7ois-perr\u00e9ard 16",
    "sg:city":"Ch\u00eane-bourg",
    "sg:orig_category":"Physiotherapie",
    "sg:phone":"+41 22 348 96 77",
    "sg:postcode":"1225",
    "sg:province":"Gen\u00e8ve",
    "wof:name":"Marl\u00e8ne Locca Physioth\u00e9rapie",
    "wof:placetype":"venue"
},
  "geometry": {"coordinates":[6.1992969513,46.1946868896],"type":"Point"}
}