{
  "type": "Feature",
  "properties": {
    "iso:country":"CH",
    "sg:address":"Bahnhofstrasse 14 6430 Schwyz. Postfach 563",
    "sg:city":"Schwyz",
    "sg:orig_category":"Druck ohne Zeitungsdruck Verlagsgewerbe",
    "sg:phone":"+41 22 328 06 88",
    "sg:postcode":"6431",
    "sg:province":"Schwyz",
    "wof:name":"Sediprint Sa",
    "wof:placetype":"venue"
},
  "geometry": {"coordinates":[6.1398301125,46.1968955994],"type":"Point"}
}