{
  "type": "Feature",
  "properties": {
    "iso:country":"CH",
    "sg:address":"Gliserallee 15",
    "sg:city":"Brig",
    "sg:orig_category":"Tankstellen",
    "sg:postcode":"3900",
    "sg:province":"Valais",
    "wof:name":"Tankstelle Oswald Albrecht",
    "wof:placetype":"venue"
},
  "geometry": {"coordinates":[7.9876461029,46.3158912659],"type":"Point"}
}