{
  "type": "Feature",
  "properties": {
    "iso:country":"CH",
    "sg:address":"M\u00fchlstatt 1017",
    "sg:city":"Z\u00fcrchersm\u00fchle",
    "sg:orig_category":"Selbst\u00e4ndige bildende K\u00fcnstler",
    "sg:phone":"+41 71 364 24 13",
    "sg:postcode":"9107",
    "sg:province":"Appenzell Ausserrhoden",
    "wof:name":"Hans Neff Holzbildhauer",
    "wof:placetype":"venue"
},
  "geometry": {"coordinates":[9.2835702896,47.3174514771],"type":"Point"}
}