{
  "type": "Feature",
  "properties": {
    "iso:country":"CH",
    "sg:address":"Eisengasse 3",
    "sg:city":"Ingenbohl",
    "sg:orig_category":"Detailhandel mit Sportartikeln Fachdetailhandel in Verkaufsr\u00e4umen",
    "sg:phone":"+41 41 820 11 40",
    "sg:postcode":"6440",
    "sg:province":"Schwyz",
    "wof:name":"Sport Life Bardill Gmbh",
    "wof:placetype":"venue"
},
  "geometry": {"coordinates":[8.6049413681,46.9945259094],"type":"Point"}
}