{
  "type": "Feature",
  "properties": {
    "iso:country":"CH",
    "sg:address":"Friedbergstrasse",
    "sg:city":"Uzwil",
    "sg:orig_category":"Grosshandel mit Eisenwaren sowie Installationsbedarf f\u00fcr Gas, Wasser U Heizung Zimmerei, Dachdeckere",
    "sg:phone":"+41 71 955 95 00",
    "sg:postcode":"9240",
    "sg:province":"St. Gallen",
    "wof:name":"Heboss Holzbautechnik Ag",
    "wof:placetype":"venue"
},
  "geometry": {"coordinates":[9.1304607391,47.4420509338],"type":"Point"}
}