{
  "type": "Feature",
  "properties": {
    "iso:country":"CH",
    "sg:address":"Nansenstrasse 16 8050 Z\u00fcrich",
    "sg:city":"Zust",
    "sg:orig_category":"Unclassifiable Establishments",
    "sg:postcode":"50",
    "wof:name":"Swiss-alaska-guiding, Deutschl\u00e4nder Lars",
    "wof:placetype":"venue"
},
  "geometry": {"coordinates":[7.7135767937,46.7171478271],"type":"Point"}
}