{
  "type": "Feature",
  "properties": {
    "iso:country":"CH",
    "sg:address":"Lindenstrasse 5",
    "sg:city":"Nieder\u00f6nz",
    "sg:orig_category":"Interessenvertretungen U sonstige Vereinigungen",
    "sg:phone":"+41 62 961 18 53",
    "sg:postcode":"3362",
    "sg:province":"Bern",
    "wof:name":"Kant.-bern.radfahrerverband",
    "wof:placetype":"venue"
},
  "geometry": {"coordinates":[7.689871788,47.1833114624],"type":"Point"}
}