{
  "type": "Feature",
  "properties": {
    "iso:country":"CH",
    "sg:address":"Rue Fr\u00e9d\u00e9ric Soguel 12",
    "sg:city":"Cernier",
    "sg:orig_category":"Detailhandel mit Fleisch U Fleischwaren",
    "sg:phone":"+41 32 853 21 49",
    "sg:postcode":"2053",
    "sg:province":"Neuch\u00e2tel",
    "wof:name":"Louis Lorimier Boucherie-charcuterie",
    "wof:placetype":"venue"
},
  "geometry": {"coordinates":[6.9019551277,47.0590705872],"type":"Point"}
}