{
  "type": "Feature",
  "properties": {
    "iso:country":"CH",
    "sg:address":"Grand-rue 24",
    "sg:city":"Payerne",
    "sg:orig_category":"Detailhandel mit Brot, Back U S\u00fcsswaren",
    "sg:phone":"+41 26 660 25 06",
    "sg:postcode":"1530",
    "sg:province":"Vaud",
    "wof:name":"Tea-room Gaston Jaques",
    "wof:placetype":"venue"
},
  "geometry": {"coordinates":[6.938752,46.82164],"type":"Point"}
}