{
  "type": "Feature",
  "properties": {
    "iso:country":"CH",
    "sg:address":"Worbstrasse 320 3073 G\u00fcmligen. Postfach",
    "sg:city":"G\u00fcmligen",
    "sg:orig_category":"Gesundheitswesen",
    "sg:postcode":"3073",
    "sg:province":"Bern",
    "wof:name":"Zentrum F\u00fcr Hyperbare Sauerstoff-medizin G\u00fcmligen Gmbh",
    "wof:placetype":"venue"
},
  "geometry": {"coordinates":[7.5147938728,46.9325675964],"type":"Point"}
}