{
  "type": "Feature",
  "properties": {
    "iso:country":"CH",
    "sg:address":"B\u00fcelisackerstrasse 23",
    "sg:city":"Waltenschwil",
    "sg:orig_category":"Sportvereine Sch\u00fctzen",
    "sg:phone":"+41 56 622 88 47",
    "sg:postcode":"5622",
    "sg:province":"Aargau",
    "wof:name":"Sch\u00fctzengesellschaft Uezwil",
    "wof:placetype":"venue"
},
  "geometry": {"coordinates":[8.2980470657,47.3312950134],"type":"Point"}
}