{
  "type": "Feature",
  "properties": {
    "iso:country":"CH",
    "sg:address":"Bettlachstrasse 250",
    "sg:city":"Grenchen",
    "sg:orig_category":"Herstellung von Konstruktionsteilen, Fertigbauteilen U Ausbauelementen aus Holz",
    "sg:postcode":"2540",
    "sg:province":"Solothurn",
    "wof:name":"Schreinerei Stuber",
    "wof:placetype":"venue"
},
  "geometry": {"coordinates":[7.4107160568,47.1975059509],"type":"Point"}
}