{
  "type": "Feature",
  "properties": {
    "iso:country":"CH",
    "sg:address":"Poststrasse 52",
    "sg:city":"Luterbach",
    "sg:orig_category":"Sportvereine Flug Aero-Club",
    "sg:phone":"+41 71 855 80 67",
    "sg:postcode":"4542",
    "sg:province":"Solothurn",
    "wof:name":"Ae.c.s.modellfluggruppe Thal",
    "wof:placetype":"venue"
},
  "geometry": {"coordinates":[9.5429334641,47.4775428772],"type":"Point"}
}