{
  "type": "Feature",
  "properties": {
    "iso:country":"CH",
    "sg:address":"Bernastrasse 7",
    "sg:city":"Interlaken",
    "sg:orig_category":"Wohnheime",
    "sg:phone":"+41 33 823 31 91",
    "sg:postcode":"3800",
    "sg:province":"Bern",
    "wof:name":"Wasme",
    "wof:placetype":"venue"
},
  "geometry": {"coordinates":[7.8530302048,46.6817588806],"type":"Point"}
}