{
  "type": "Feature",
  "properties": {
    "iso:country":"CH",
    "sg:address":"Zollikerstrasse 62",
    "sg:city":"Zollikon",
    "sg:classifiers":[
        {
            "category":"Professional",
            "subcategory":"Employment Agencies",
            "type":"Services"
        }
    ],
    "sg:phone":"+41 13913963",
    "sg:postcode":"8702",
    "sg:province":"Z\u00fcrich",
    "sg:tags":[
        "personal",
        "u",
        "stellenvermittlung"
    ],
    "wof:name":"Modeagentur Mich\u00e8le Raue Ag",
    "wof:placetype":"venue"
},
  "geometry": {"coordinates":[8.5720596313,47.3406524658],"type":"Point"}
}