{
  "type": "Feature",
  "properties": {
    "iso:country":"CH",
    "sg:address":"L\u00e4ndliweg 2 5400 Baden. Postfach",
    "sg:city":"Baden",
    "sg:orig_category":"Polizei",
    "sg:phone":"+41 62 822 25 42",
    "sg:postcode":"5401",
    "sg:province":"Aargau",
    "wof:name":"Kantonspolizei",
    "wof:placetype":"venue"
},
  "geometry": {"coordinates":[8.0723323822,47.3893280029],"type":"Point"}
}