{
  "type": "Feature",
  "properties": {
    "iso:country":"CH",
    "sg:address":"Fabrikstrasse 10",
    "sg:city":"Oftringen",
    "sg:orig_category":"Wirtschaftspr\u00fcfung, Steuerberatung U Treuhand",
    "sg:phone":"+41 62 789 30 20",
    "sg:postcode":"4665",
    "sg:province":"Aargau",
    "wof:name":"Wias Ag",
    "wof:placetype":"venue"
},
  "geometry": {"coordinates":[7.9251818657,47.3082427979],"type":"Point"}
}