{
  "type": "Feature",
  "properties": {
    "iso:country":"CH",
    "sg:address":"Alte Leutwilerstrasse 5",
    "sg:city":"Boniswil",
    "sg:orig_category":"Ingenieurb\u00fcros Umwelttechnik and \u00d6kologie",
    "sg:phone":"+41 62 777 30 08",
    "sg:postcode":"5706",
    "sg:province":"Aargau",
    "wof:name":"Capreola Wildtier\u00f6kologisches Beratungsb\u00fcro",
    "wof:placetype":"venue"
},
  "geometry": {"coordinates":[8.1805696487,47.3149490356],"type":"Point"}
}