{
  "type": "Feature",
  "properties": {
    "iso:country":"CH",
    "sg:address":"Fischbachstrasse 6a",
    "sg:city":"Steinmaur",
    "sg:orig_category":"Unternehmensberatung",
    "sg:phone":"+41 71 385 34 05",
    "sg:postcode":"8162",
    "sg:province":"Z\u00fcrich",
    "wof:name":"Robert Hidber Conprodes",
    "wof:placetype":"venue"
},
  "geometry": {"coordinates":[9.251865387,47.4103965759],"type":"Point"}
}