{
  "type": "Feature",
  "properties": {
    "iso:country":"CH",
    "sg:address":"Obertorweg 63 4123 Allschwil. Postfach",
    "sg:city":"Allschwil",
    "sg:orig_category":"Herstellung von Seifen, Wasch U Reinigungsmitteln",
    "sg:postcode":"4123",
    "sg:province":"Basel-Landschaft",
    "wof:name":"Organitech Cleaner Gmbh",
    "wof:placetype":"venue"
},
  "geometry": {"coordinates":[7.5283489227,47.5513534546],"type":"Point"}
}