{
  "type": "Feature",
  "properties": {
    "iso:country":"CH",
    "sg:address":"Sonnenb\u00fchlweg 1 6010 Kriens. Postfach 22",
    "sg:city":"Kriens",
    "sg:orig_category":"Handelsvermittlung U Grosshandel Handelsvermittlung U Grosshandel mit Automobilteilen U Zubeh\u00f6r",
    "sg:phone":"+41 41 310 01 25",
    "sg:postcode":"6011",
    "sg:province":"Luzern",
    "wof:name":"Technomag Ag Autoersatzteile Engros",
    "wof:placetype":"venue"
},
  "geometry": {"coordinates":[8.2913970947,47.0375556946],"type":"Point"}
}