{
  "type": "Feature",
  "properties": {
    "iso:country":"CH",
    "sg:address":"Sellenb\u00fcren 2",
    "sg:city":"Stallikon",
    "sg:orig_category":"Sonstiger Grosshandel",
    "sg:phone":"+41 17001525",
    "sg:postcode":"8143",
    "sg:province":"Z\u00fcrich",
    "wof:name":"Woodtli Handels Gmbh",
    "wof:placetype":"venue"
},
  "geometry": {"coordinates":[8.4797439575,47.3451805115],"type":"Point"}
}