{
  "type": "Feature",
  "properties": {
    "iso:country":"CH",
    "sg:address":"Schulstrasse 4",
    "sg:city":"Gisikon",
    "sg:orig_category":"Fachdetailhandel in Verkaufsr\u00e4umen Grosshandel mit Sportartikeln",
    "sg:phone":"+41 41 930 01 15",
    "sg:postcode":"6038",
    "sg:province":"Luzern",
    "wof:name":"Manifold Sportagentur Abler M.",
    "wof:placetype":"venue"
},
  "geometry": {"coordinates":[8.3999643326,47.1227836609],"type":"Point"}
}