{
  "type": "Feature",
  "properties": {
    "addr:full":"Beltramina Via 3a Lugano Ticino 6900",
    "addr:postcode":"6900",
    "addr:street":"Via 3A",
    "iso:country":"CH",
    "sg:address":"Beltramina Via 3a",
    "sg:city":"Lugano",
    "sg:orig_category":"Allgemeiner Hoch U Tiefbau",
    "sg:phone":"+41 41 260 20 44",
    "sg:postcode":"6900",
    "sg:province":"Ticino",
    "wof:name":"Casarex Systembau Ag",
    "wof:placetype":"venue"
},
  "geometry": {"coordinates":[8.28163,47.069874],"type":"Point"}
}