{
  "type": "Feature",
  "properties": {
    "iso:country":"CH",
    "sg:address":"Gasthaus Innerthal 8858 Innerthal. Postfach",
    "sg:city":"Innerthal",
    "sg:classifiers":[
        {
            "category":"Travel",
            "subcategory":"Hotels & Motels",
            "type":"Entertainment"
        }
    ],
    "sg:postcode":"8858",
    "sg:province":"Schwyz",
    "sg:tags":[
        "hotels",
        "mit",
        "restaurant"
    ],
    "wof:name":"Gasthaus Stausee Della Rossa Ruth Gasthaus Stausee Mit Dependance bad",
    "wof:placetype":"venue"
},
  "geometry": {"coordinates":[8.9160404205,47.1063041687],"type":"Point"}
}