{
  "type": "Feature",
  "properties": {
    "addr:full":"Via Bossi 6 Lugano Ticino 6900",
    "addr:housenumber":"6",
    "addr:postcode":"6900",
    "addr:street":"Via Bossi",
    "iso:country":"CH",
    "sg:address":"Via Bossi 6",
    "sg:city":"Lugano",
    "sg:classifiers":[
        {
            "category":"Banks & Credit Unions",
            "subcategory":"Bank",
            "type":"Services"
        }
    ],
    "sg:phone":"+41 91 641 64 11",
    "sg:postcode":"6900",
    "sg:province":"Ticino",
    "wof:name":"Banca Raiffeisen Novazzano-genestrerio",
    "wof:placetype":"venue"
},
  "geometry": {"coordinates":[8.98024,45.84214],"type":"Point"}
}