{
  "type": "Feature",
  "properties": {
    "iso:country":"CH",
    "sg:address":"Lehngasse 78c",
    "sg:city":"Wilderswil",
    "sg:orig_category":"Elektroinstallation",
    "sg:phone":"+41 33 821 11 33",
    "sg:postcode":"3812",
    "sg:province":"Bern",
    "wof:name":"Elektro Von Allmen Ag",
    "wof:placetype":"venue"
},
  "geometry": {"coordinates":[7.8632969856,46.6605377197],"type":"Point"}
}