{
  "type": "Feature",
  "properties": {
    "iso:country":"CH",
    "sg:address":"Werkstrasse 29",
    "sg:city":"Chur",
    "sg:orig_category":"Unclassifiable Establishments",
    "sg:phone":"+41 81 284 37 37",
    "sg:postcode":"7000",
    "sg:province":"Graubunden",
    "wof:name":"Euro Tv Consultancy Ag",
    "wof:placetype":"venue"
},
  "geometry": {"coordinates":[9.5270996094,46.8562507629],"type":"Point"}
}