{
  "type": "Feature",
  "properties": {
    "iso:country":"CH",
    "sg:address":"Sarganserstrasse 78 8887 Mels. Postfach",
    "sg:city":"Mels",
    "sg:orig_category":"Instandhaltung U Reparatur von Automobilen",
    "sg:phone":"+41 81 723 25 43",
    "sg:postcode":"8887",
    "sg:province":"St. Gallen",
    "wof:name":"Paulin E.",
    "wof:placetype":"venue"
},
  "geometry": {"coordinates":[9.4284925461,47.0491218567],"type":"Point"}
}