{
  "type": "Feature",
  "properties": {
    "iso:country":"CH",
    "sg:address":"Derendingenstrasse 21",
    "sg:city":"Deitingen",
    "sg:orig_category":"Vorschulen, Kinderg\u00e4rten",
    "sg:phone":"+41 32 614 20 78",
    "sg:postcode":"4543",
    "sg:province":"Solothurn",
    "wof:name":"Kindergarten Baschi",
    "wof:placetype":"venue"
},
  "geometry": {"coordinates":[7.6166529655,47.209651947],"type":"Point"}
}