{
  "type": "Feature",
  "properties": {
    "iso:country":"CH",
    "sg:address":"Geissensteinring 12",
    "sg:city":"Luzern",
    "sg:orig_category":"Sportvereine Wassersport Schwimmen",
    "sg:postcode":"6005",
    "sg:province":"Luzern",
    "wof:name":"Schwimmverein Emmen",
    "wof:placetype":"venue"
},
  "geometry": {"coordinates":[8.3100805283,47.039932251],"type":"Point"}
}