{
  "type": "Feature",
  "properties": {
    "addr:full":"Uznacherstrasse 2 Kaltbrunn St. Gallen 8722",
    "addr:housenumber":"2",
    "addr:postcode":"8722",
    "addr:street":"Uznacherstrasse",
    "iso:country":"CH",
    "sg:address":"Uznacherstrasse 2",
    "sg:city":"Kaltbrunn",
    "sg:orig_category":"Architektur U Ingenieurb\u00fcros",
    "sg:phone":"+41 79 441 74 09",
    "sg:postcode":"8722",
    "sg:province":"St. Gallen",
    "wof:name":"Bigler Ag, Ingenieure & Planer, Zweigniederlassung Kaltbrunn",
    "wof:placetype":"venue"
},
  "geometry": {"coordinates":[9.024658,47.213634],"type":"Point"}
}