{
  "type": "Feature",
  "properties": {
    "addr:full":"Landstrasse 176 Wettingen Aargau 5430",
    "addr:housenumber":"176",
    "addr:postcode":"5430",
    "addr:street":"Landstrasse",
    "iso:country":"CH",
    "sg:address":"Landstrasse 176",
    "sg:city":"Wettingen",
    "sg:orig_category":"Datenverarbeitungsdienste Softwareentwicklung U beratung",
    "sg:phone":"+41 41 790 30 22",
    "sg:postcode":"5430",
    "sg:province":"Aargau",
    "wof:name":"Pinck Softech Ag",
    "wof:placetype":"venue"
},
  "geometry": {"coordinates":[8.338235,47.460705],"type":"Point"}
}