{
  "type": "Feature",
  "properties": {
    "addr:full":"Via Nassa 7 Lugano Ticino 6900",
    "addr:housenumber":"7",
    "addr:postcode":"6900",
    "addr:street":"Via Nassa",
    "iso:country":"CH",
    "sg:address":"Via Nassa 7",
    "sg:city":"Lugano",
    "sg:orig_category":"Arztpraxen",
    "sg:phone":"+41 91 923 32 68",
    "sg:postcode":"6900",
    "sg:province":"Ticino",
    "wof:name":"Dott.med.gianni Casanova Specialista Fmh",
    "wof:placetype":"venue"
},
  "geometry": {"coordinates":[8.950071,46.002808],"type":"Point"}
}