{
  "type": "Feature",
  "properties": {
    "iso:country":"CH",
    "sg:address":"Industriestrasse 9 8712 St\u00e4fa. Postfach",
    "sg:city":"St\u00e4fa",
    "sg:orig_category":"Architektur U Ingenieurb\u00fcros",
    "sg:postcode":"8712",
    "sg:province":"Z\u00fcrich",
    "wof:name":"R\u00fctten Engineering",
    "wof:placetype":"venue"
},
  "geometry": {"coordinates":[8.743795,47.237652],"type":"Point"}
}