{
  "type": "Feature",
  "properties": {
    "addr:full":"Wielandplatz 2 Basel Basel-Stadt 4054",
    "addr:housenumber":"2",
    "addr:postcode":"4054",
    "addr:street":"Wielandplatz",
    "iso:country":"CH",
    "sg:address":"Wielandplatz 2",
    "sg:city":"Basel",
    "sg:orig_category":"Arztpraxen",
    "sg:phone":"+41 61 301 78 78",
    "sg:postcode":"4054",
    "sg:province":"Basel-Stadt",
    "wof:name":"Dr.med.thomas P. Ehrensperger Arzt F.allgemeine Medizin",
    "wof:placetype":"venue"
},
  "geometry": {"coordinates":[7.571948,47.553204],"type":"Point"}
}