{
  "type": "Feature",
  "properties": {
    "addr:full":"Zieglerstrasse 36 3007 Bern. Postfach Bern Bern 3005",
    "addr:housenumber":"36",
    "addr:postcode":"3007;postfach;3005",
    "addr:street":"Zieglerstrasse",
    "iso:country":"CH",
    "sg:address":"Zieglerstrasse 36 3007 Bern. Postfach",
    "sg:city":"Bern",
    "sg:orig_category":"Architektur U Ingenieurb\u00fcros",
    "sg:postcode":"3005",
    "sg:province":"Bern",
    "wof:name":"Michalski Engineering & Consulting Ingenieurb\u00fcro",
    "wof:placetype":"venue"
},
  "geometry": {"coordinates":[7.429864,46.943996],"type":"Point"}
}