{
  "type": "Feature",
  "properties": {
    "iso:country":"CH",
    "sg:address":"Chemin De Mon-repos 3",
    "sg:city":"Epalinges",
    "sg:orig_category":"Sanit\u00e4r, Heizungs U L\u00fcftungsinstallation Sanit\u00e4rinstallation",
    "sg:phone":"+41 79 449 04 09",
    "sg:postcode":"1066",
    "sg:province":"Vaud",
    "wof:name":"Ott Markus",
    "wof:placetype":"venue"
},
  "geometry": {"coordinates":[6.6733140945,46.5467643738],"type":"Point"}
}