{
  "type": "Feature",
  "properties": {
    "iso:country":"CH",
    "sg:address":"Badstrasse 15",
    "sg:city":"Baden",
    "sg:orig_category":"Unclassifiable Establishments",
    "sg:postcode":"5400",
    "sg:province":"Aargau",
    "wof:name":"Progress Holding Ag",
    "wof:placetype":"venue"
},
  "geometry": {"coordinates":[8.3080873489,47.4747886658],"type":"Point"}
}