{
  "type": "Feature",
  "properties": {
    "iso:country":"CH",
    "sg:address":"Via Patrizia 3",
    "sg:city":"Ascona",
    "sg:orig_category":"Grosshandel mit pharmazeutischen Erzeugnissen, medizinischen U orthop\u00e4dischen Artikeln Herstellung v",
    "sg:phone":"+41 19862161",
    "sg:postcode":"6612",
    "sg:province":"Ticino",
    "wof:name":"Globocare Ag",
    "wof:placetype":"venue"
},
  "geometry": {"coordinates":[8.6900548935,47.3005561829],"type":"Point"}
}