{
  "type": "Feature",
  "properties": {
    "iso:country":"CH",
    "sg:address":"Route Fin De La Croix 4",
    "sg:city":"Givisiez",
    "sg:orig_category":"Gartenbau",
    "sg:phone":"+41 26 466 45 54",
    "sg:postcode":"1762",
    "sg:province":"Fribourg",
    "wof:name":"Fran\u00e7ois B\u00fcrke Paysagiste",
    "wof:placetype":"venue"
},
  "geometry": {"coordinates":[7.1324429512,46.8143386841],"type":"Point"}
}