{
  "type": "Feature",
  "properties": {
    "iso:country":"CH",
    "sg:address":"Dorfplatz 6",
    "sg:city":"Stans",
    "sg:orig_category":"Non-Classified Establishments",
    "sg:postcode":"6370",
    "sg:province":"Nidwalden",
    "wof:name":"Weckmann Holding Ag",
    "wof:placetype":"venue"
},
  "geometry": {"coordinates":[8.366109848,46.9570732117],"type":"Point"}
}