{
  "type": "Feature",
  "properties": {
    "iso:country":"CH",
    "sg:address":"Industriestrasse 23 5303 W\u00fcrenlingen. Postfach",
    "sg:city":"W\u00fcrenlingen",
    "sg:orig_category":"Herstellung von Teppichen",
    "sg:postcode":"5303",
    "sg:province":"Aargau",
    "wof:name":"Euro Pl\u00e4ttli Gmbh Boden, Wand- U. Deckenbel\u00e4ge; Verlegung, Herstellung Usw",
    "wof:placetype":"venue"
},
  "geometry": {"coordinates":[8.2348766327,47.5250473022],"type":"Point"}
}