{
  "type": "Feature",
  "properties": {
    "iso:country":"CH",
    "sg:address":"Sporrengasse 2",
    "sg:city":"Schaffhausen",
    "sg:orig_category":"P\u00e9dicure",
    "sg:phone":"+41 52 625 78 80",
    "sg:postcode":"8200",
    "sg:province":"Schaffhausen",
    "wof:name":"Melanie Br\u00fcngger P\u00e9dicure",
    "wof:placetype":"venue"
},
  "geometry": {"coordinates":[8.6348209381,47.6964530945],"type":"Point"}
}