{
  "type": "Feature",
  "properties": {
    "iso:country":"CH",
    "sg:address":"Beau-site Quartier 11",
    "sg:city":"Crissier",
    "sg:orig_category":"Reinigungsgewerbe",
    "sg:phone":"+41 22 344 34 52",
    "sg:postcode":"1023",
    "sg:province":"Vaud",
    "wof:name":"Aquanet Services Sarl",
    "wof:placetype":"venue"
},
  "geometry": {"coordinates":[6.5777301788,46.5468254089],"type":"Point"}
}