{
  "type": "Feature",
  "properties": {
    "iso:country":"CH",
    "sg:address":"Chaletweg 1 8305 Dietlikon. Postfach",
    "sg:city":"Dietlikon",
    "sg:orig_category":"Unclassifiable Establishments",
    "sg:postcode":"8305",
    "sg:province":"Z\u00fcrich",
    "wof:name":"Massage & Cosmetik Institut Zarriello A. Kosmetik Und Massageinstitut",
    "wof:placetype":"venue"
},
  "geometry": {"coordinates":[8.6196746826,47.4219474792],"type":"Point"}
}