{
  "type": "Feature",
  "properties": {
    "addr:full":"1729 Mont\u00e9cu. Postfach Bonnefontaine 1729",
    "addr:housenumber":"1729",
    "addr:postcode":"1729",
    "addr:street":"Monte\u0301Cu Postfach",
    "iso:country":"CH",
    "sg:address":"1729 Mont\u00e9cu. Postfach",
    "sg:city":"Bonnefontaine",
    "sg:orig_category":"Campingpl\u00e4tze",
    "sg:postcode":"1729",
    "wof:name":"Pauli Louis",
    "wof:placetype":"venue"
},
  "geometry": {"coordinates":[7.194399,46.74081],"type":"Point"}
}