{
  "type": "Feature",
  "properties": {
    "iso:country":"CH",
    "sg:address":"Untertalweg 50 4144 Arlesheim. Postfach",
    "sg:city":"Arlesheim",
    "sg:orig_category":"Pensionskassen",
    "sg:postcode":"4144",
    "sg:province":"Basel-Landschaft",
    "wof:name":"Holle Wohlfahrtsstiftung",
    "wof:placetype":"venue"
},
  "geometry": {"coordinates":[7.6108579636,47.4980125427],"type":"Point"}
}