{
  "type": "Feature",
  "properties": {
    "iso:country":"CH",
    "sg:address":"Gen\u00e8ve Rue De 69",
    "sg:city":"Ch\u00eane-bourg",
    "sg:orig_category":"RESTAURANTS: TEA-ROOMS",
    "sg:postcode":"1225",
    "sg:province":"Gen\u00e8ve",
    "wof:name":"Folguera Juan",
    "wof:placetype":"venue"
},
  "geometry": {"coordinates":[6.1966347694,46.1941604614],"type":"Point"}
}