{
  "type": "Feature",
  "properties": {
    "iso:country":"CH",
    "sg:address":"Via Della Posta",
    "sg:city":"Bioggio",
    "sg:orig_category":"Grosshandel mit elektrischen Haushaltsger\u00e4ten, Radio U Fernsehger\u00e4ten Herstellung von Elektrizit\u00e4tsv",
    "sg:phone":"+41 91 605 18 14",
    "sg:postcode":"6934",
    "sg:province":"Ticino",
    "wof:name":"Distel Sa",
    "wof:placetype":"venue"
},
  "geometry": {"coordinates":[8.9105949402,46.0146942139],"type":"Point"}
}