{
  "type": "Feature",
  "properties": {
    "iso:country":"CH",
    "sg:address":"Route Des Pr\u00e9alpes 75",
    "sg:city":"Marly",
    "sg:orig_category":"Grosshandel mit Uhren",
    "sg:phone":"+41 32 329 39 80",
    "sg:postcode":"1723",
    "sg:province":"Fribourg",
    "wof:name":"Hanowa Gmbh Uhrenhandel",
    "wof:placetype":"venue"
},
  "geometry": {"coordinates":[7.2474341393,47.1398849487],"type":"Point"}
}