{
  "type": "Feature",
  "properties": {
    "iso:country":"CH",
    "sg:address":"Rothenring 8 6015 Reussb\u00fchl. Postfach",
    "sg:city":"Reussb\u00fchl",
    "sg:orig_category":"Herstellung von Reiseartikeln, Leder U Sattlerwaren",
    "sg:postcode":"6015",
    "sg:province":"Luzern",
    "wof:name":"Autosattlerei Sedak",
    "wof:placetype":"venue"
},
  "geometry": {"coordinates":[8.8035001755,47.3288803101],"type":"Point"}
}