{
  "type": "Feature",
  "properties": {
    "iso:country":"CH",
    "sg:address":"Rothenstrasse 45",
    "sg:city":"Reussb\u00fchl",
    "sg:orig_category":"Instandhaltung U Reparatur von Automobilen",
    "sg:phone":"+41 41 260 79 10",
    "sg:postcode":"6015",
    "sg:province":"Luzern",
    "wof:name":"Carrosserie D. Kaiser",
    "wof:placetype":"venue"
},
  "geometry": {"coordinates":[8.2766704559,47.0704917908],"type":"Point"}
}