{
  "type": "Feature",
  "properties": {
    "iso:country":"CH",
    "sg:address":"Chessibachstrasse 10",
    "sg:city":"Altendorf",
    "sg:orig_category":"Hundesalons",
    "sg:phone":"+41 55 442 56 36",
    "sg:postcode":"8852",
    "sg:province":"Schwyz",
    "wof:name":"Hundesalon Struppi Mares Hensler",
    "wof:placetype":"venue"
},
  "geometry": {"coordinates":[8.8260087967,47.1892700195],"type":"Point"}
}