{
  "type": "Feature",
  "properties": {
    "iso:country":"CH",
    "sg:address":"Rainstrasse 13",
    "sg:city":"Riedholz",
    "sg:orig_category":"Fachdetailhandel in Verkaufsr\u00e4umen",
    "sg:postcode":"4533",
    "sg:province":"Solothurn",
    "wof:name":"Markus Studer Augenoptische Dienstleistungen Gmbh",
    "wof:placetype":"venue"
},
  "geometry": {"coordinates":[7.557352066,47.2354011536],"type":"Point"}
}