{
  "type": "Feature",
  "properties": {
    "iso:country":"CH",
    "sg:address":"Heuelsteig 15 8000 Z\u00fcrich. Postfach 8032 Z\u00fcrich",
    "sg:city":"Zust",
    "sg:orig_category":"Betrieb U technische Hilfsdienste des Kultur U Unterhaltungswesens",
    "sg:postcode":"32",
    "wof:name":"Granary Sound Gmbh",
    "wof:placetype":"venue"
},
  "geometry": {"coordinates":[8.564904,47.368141],"type":"Point"}
}