{
  "type": "Feature",
  "properties": {
    "iso:country":"CH",
    "sg:address":"Fiesch",
    "sg:city":"Fiesch",
    "sg:classifiers":[
        {
            "category":"Banks & Credit Unions",
            "subcategory":"Bank",
            "type":"Services"
        }
    ],
    "sg:phone":"+41 28701200",
    "sg:postcode":"3984",
    "sg:province":"Valais",
    "wof:name":"Union Bank Of Switzerland",
    "wof:placetype":"venue"
},
  "geometry": {"coordinates":[8.06109,46.477242],"type":"Point"}
}