{
  "type": "Feature",
  "properties": {
    "iso:country":"CH",
    "sg:address":"Odern",
    "sg:city":"Eichberg",
    "sg:orig_category":"Gartenbau",
    "sg:phone":"+41 71 755 48 84",
    "sg:postcode":"9453",
    "sg:province":"St. Gallen",
    "wof:name":"Brunner Hans",
    "wof:placetype":"venue"
},
  "geometry": {"coordinates":[9.5310497284,47.3430290222],"type":"Point"}
}