{
  "type": "Feature",
  "properties": {
    "iso:country":"CH",
    "sg:address":"Z\u00fcrcherstrasse 125",
    "sg:city":"Frauenfeld",
    "sg:orig_category":"Architektur U Ingenieurb\u00fcros",
    "sg:postcode":"8500",
    "sg:province":"Thurgau",
    "wof:name":"Antriebe R\u00fcti Ag",
    "wof:placetype":"venue"
},
  "geometry": {"coordinates":[8.852587,47.254368],"type":"Point"}
}