{
  "type": "Feature",
  "properties": {
    "iso:country":"CH",
    "sg:address":"M\u00fchlestr. 1",
    "sg:city":"Menzingen",
    "sg:orig_category":"Sonstige mit der Informatik verbundene T\u00e4tigkeiten",
    "sg:postcode":"6313",
    "sg:province":"Zug",
    "wof:name":"M\u00fcller R. Edv-beratung",
    "wof:placetype":"venue"
},
  "geometry": {"coordinates":[8.5750789642,47.1806335449],"type":"Point"}
}