{
  "type": "Feature",
  "properties": {
    "iso:country":"CH",
    "sg:address":"Unterdorf",
    "sg:city":"Kernenried",
    "sg:orig_category":"Gasth\u00f6fe/Gasth\u00e4user mit Restaurant",
    "sg:phone":"+41 31 767 71 81",
    "sg:postcode":"3309",
    "sg:province":"Bern",
    "wof:name":"Gasthof Zum L\u00f6wen",
    "wof:placetype":"venue"
},
  "geometry": {"coordinates":[7.5497097969,47.0735168457],"type":"Point"}
}