{
  "type": "Feature",
  "properties": {
    "iso:country":"CH",
    "sg:address":"Bahnhofstrasse 15 6210 Sursee. Postfach",
    "sg:city":"Sursee",
    "sg:orig_category":"Wirtschaftspr\u00fcfung, Steuerberatung U Treuhand",
    "sg:postcode":"6210",
    "sg:province":"Luzern",
    "wof:name":"Baso Treuhand Ag",
    "wof:placetype":"venue"
},
  "geometry": {"coordinates":[8.1051187515,47.1723213196],"type":"Point"}
}