{
  "type": "Feature",
  "properties": {
    "iso:country":"CH",
    "sg:address":"Huobstrasse 3",
    "sg:city":"Meggen",
    "sg:orig_category":"Mechanik Schlossereien",
    "sg:phone":"+41 41 377 10 73",
    "sg:postcode":"6045",
    "sg:province":"Luzern",
    "wof:name":"Schiwe Ag",
    "wof:placetype":"venue"
},
  "geometry": {"coordinates":[8.3814525604,47.0508155823],"type":"Point"}
}