{
  "type": "Feature",
  "properties": {
    "iso:country":"CH",
    "sg:address":"Chemin De L'islettaz 1305 Penthalaz. Postfach",
    "sg:city":"Penthalaz",
    "sg:orig_category":"Herstellung von sonstigen Maschinen f\u00fcr unspezifische Verwendung",
    "sg:postcode":"1305",
    "sg:province":"Vaud",
    "wof:name":"Mecapro Sa",
    "wof:placetype":"venue"
},
  "geometry": {"coordinates":[6.5224580765,46.6078414917],"type":"Point"}
}