{
  "type": "Feature",
  "properties": {
    "addr:full":"Aarauerstrasse 2a Wildegg Aargau 5103",
    "addr:housenumber":"2a",
    "addr:postcode":"5103",
    "addr:street":"Aarauerstrasse",
    "iso:country":"CH",
    "sg:address":"Aarauerstrasse 2a",
    "sg:city":"Wildegg",
    "sg:orig_category":"Aktivit\u00e4ten der Generalunternehmen im Baugewerbe Allgemeiner Hoch U Tiefbau",
    "sg:phone":"+41 71 923 86 28",
    "sg:postcode":"5103",
    "sg:province":"Aargau",
    "wof:name":"Egli + Partner Ag",
    "wof:placetype":"venue"
},
  "geometry": {"coordinates":[9.05343,47.462879],"type":"Point"}
}