{
  "type": "Feature",
  "properties": {
    "iso:country":"CH",
    "sg:address":"Chemin Des Sources 35bis",
    "sg:city":"Yverdon-les-bains",
    "sg:orig_category":"Elektroinstallation",
    "sg:phone":"+41 24 425 05 63",
    "sg:postcode":"1400",
    "sg:province":"Vaud",
    "wof:name":"Richard Velen Installations \u00e9lectriques",
    "wof:placetype":"venue"
},
  "geometry": {"coordinates":[6.65980196,46.7738304138],"type":"Point"}
}