{
  "type": "Feature",
  "properties": {
    "iso:country":"CH",
    "sg:address":"Konsumhof 3",
    "sg:city":"Romanshorn",
    "sg:orig_category":"Organisationen der Wohlfahrtspflege",
    "sg:phone":"+41 71 461 20 90",
    "sg:postcode":"8590",
    "sg:province":"Thurgau",
    "wof:name":"Pro Senectute",
    "wof:placetype":"venue"
},
  "geometry": {"coordinates":[9.3770904541,47.5662956238],"type":"Point"}
}