{
  "type": "Feature",
  "properties": {
    "iso:country":"CH",
    "sg:address":"Hergiswaldstrasse 2 6012 Obernau. Postfach",
    "sg:city":"Obernau",
    "sg:orig_category":"Malerei Tapeziererei",
    "sg:phone":"+41 41 320 47 51",
    "sg:postcode":"6012",
    "sg:province":"Luzern",
    "wof:name":"Louis Rey Maler-& Tapezierergesch\u00e4ft",
    "wof:placetype":"venue"
},
  "geometry": {"coordinates":[8.2543096542,47.0329971313],"type":"Point"}
}