{
  "type": "Feature",
  "properties": {
    "iso:country":"CH",
    "sg:address":"Herrenmattstrasse 9",
    "sg:city":"Muttenz",
    "sg:orig_category":"Vereine Haus- and Grundeigent\u00fcmer",
    "sg:postcode":"4132",
    "sg:province":"Basel-Landschaft",
    "wof:name":"Hauseigent\u00fcmerverband R\u00fcti",
    "wof:placetype":"venue"
},
  "geometry": {"coordinates":[8.8498697281,47.2590713501],"type":"Point"}
}