{
  "type": "Feature",
  "properties": {
    "iso:country":"CH",
    "sg:address":"Viale Stazione",
    "sg:city":"Airolo",
    "sg:orig_category":"Architektur U Ingenieurb\u00fcros",
    "sg:phone":"+41 91 869 13 50",
    "sg:postcode":"6780",
    "sg:province":"Ticino",
    "wof:name":"Ceresa-rezzonico-gerrvasoni Studio D'ingegneria Sa",
    "wof:placetype":"venue"
},
  "geometry": {"coordinates":[8.604056,46.528194],"type":"Point"}
}