{
  "type": "Feature",
  "properties": {
    "iso:country":"CH",
    "sg:address":"Kunklerstrasse 30 8600 D\u00fcbendorf. Postfach",
    "sg:city":"D\u00fcbendorf",
    "sg:orig_category":"Interessenvertretungen",
    "sg:postcode":"8600",
    "sg:province":"Z\u00fcrich",
    "wof:name":"Genossenschaft Konkordia Z\u00fcrich",
    "wof:placetype":"venue"
},
  "geometry": {"coordinates":[8.6281309128,47.3996124268],"type":"Point"}
}