{
  "type": "Feature",
  "properties": {
    "iso:country":"CH",
    "sg:address":"Bauherrenstrasse 24",
    "sg:city":"Z\u00fcrich",
    "sg:orig_category":"Werbung",
    "sg:phone":"+41 32 853 54 54",
    "sg:postcode":"8049",
    "sg:province":"Z\u00fcrich",
    "wof:name":"Candaux J.-p.",
    "wof:placetype":"venue"
},
  "geometry": {"coordinates":[6.9187231064,47.0202217102],"type":"Point"}
}