{
  "type": "Feature",
  "properties": {
    "iso:country":"CH",
    "sg:address":"Oberg\u00fctschstrasse 9 6003 Luzern. Postfach",
    "sg:city":"Luzern",
    "sg:orig_category":"Sonstige mit der Informatik verbundene T\u00e4tigkeiten",
    "sg:phone":"+41 71 455 16 74",
    "sg:postcode":"6003",
    "sg:province":"Luzern",
    "wof:name":"Hanni Gosetto",
    "wof:placetype":"venue"
},
  "geometry": {"coordinates":[9.399061203,47.502456665],"type":"Point"}
}