{
  "type": "Feature",
  "properties": {
    "iso:country":"CH",
    "sg:address":"Welschd\u00f6rfli 11",
    "sg:city":"Chur",
    "sg:orig_category":"Detailhandel mit Geschenkartikeln U Souvenirs Textilveredlung",
    "sg:phone":"+41 81 252 09 33",
    "sg:postcode":"7000",
    "sg:province":"Graubunden",
    "wof:name":"Roman Christoffel",
    "wof:placetype":"venue"
},
  "geometry": {"coordinates":[9.5280361176,46.8475723267],"type":"Point"}
}