{
  "type": "Feature",
  "properties": {
    "iso:country":"CH",
    "sg:address":"Hofstettenstrasse 4 3600 Thun. Postfach",
    "sg:city":"Thun",
    "sg:orig_category":"Interessenvertretungen",
    "sg:postcode":"3600",
    "sg:province":"Bern",
    "wof:name":"Gjt Genossenschaft Jugendtourismus Thun",
    "wof:placetype":"venue"
},
  "geometry": {"coordinates":[7.6327571869,46.757434845],"type":"Point"}
}