{
  "type": "Feature",
  "properties": {
    "addr:full":"Hauptstrasse 49 Glarus Glarus 8750",
    "addr:housenumber":"49",
    "addr:postcode":"8750",
    "addr:street":"Hauptstrasse",
    "iso:country":"CH",
    "sg:address":"Hauptstrasse 49",
    "sg:city":"Glarus",
    "sg:orig_category":"Detailhandel mit Brillen U anderen Sehhilfen Fachdetailhandel in Verkaufsr\u00e4umen",
    "sg:phone":"+41 55 640 90 34",
    "sg:postcode":"8750",
    "sg:province":"Glarus",
    "wof:name":"Optikland Ag",
    "wof:placetype":"venue"
},
  "geometry": {"coordinates":[9.066986,47.041012],"type":"Point"}
}