{
  "type": "Feature",
  "properties": {
    "iso:country":"CH",
    "sg:address":"Kronenstrasse 2 8157 Dielsdorf. Postfach 162",
    "sg:city":"Dielsdorf",
    "sg:orig_category":"Instandhaltung U Reparatur von Automobilen",
    "sg:phone":"+41 18530300",
    "sg:postcode":"8157",
    "sg:province":"Z\u00fcrich",
    "wof:name":"Hugi Automobile Ag",
    "wof:placetype":"venue"
},
  "geometry": {"coordinates":[8.4559431076,47.4826049805],"type":"Point"}
}