{
  "type": "Feature",
  "properties": {
    "iso:country":"CH",
    "sg:address":"Ancienne Rte D'oron",
    "sg:city":"Ch\u00e2tillens",
    "sg:orig_category":"Einbau von Schreinerwaren Herstellung von K\u00fcchenm\u00f6beln",
    "sg:phone":"+41 21 907 70 30",
    "sg:postcode":"1610",
    "sg:province":"Vaud",
    "wof:name":"Glauser Agencements Sa",
    "wof:placetype":"venue"
},
  "geometry": {"coordinates":[6.8157148361,46.569103241],"type":"Point"}
}