{
  "type": "Feature",
  "properties": {
    "iso:country":"CH",
    "sg:address":"Alte Fahrstrasse 4",
    "sg:city":"Auenstein",
    "sg:classifiers":[
        {
            "category":"Professional",
            "subcategory":"Art Services",
            "type":"Services"
        }
    ],
    "sg:phone":"+41 62 897 34 47",
    "sg:postcode":"5105",
    "sg:province":"Aargau",
    "sg:tags":[
        "design",
        "advertising"
    ],
    "wof:name":"Fiori Colori",
    "wof:placetype":"venue"
},
  "geometry": {"coordinates":[8.152126,47.416142],"type":"Point"}
}