{
  "type": "Feature",
  "properties": {
    "iso:country":"CH",
    "sg:address":"Weinbergstrasse 102",
    "sg:city":"Z\u00fcrich",
    "sg:orig_category":"Architektur U Ingenieurb\u00fcros Architekturb\u00fcros",
    "sg:phone":"+41 13611266",
    "sg:postcode":"8006",
    "sg:province":"Z\u00fcrich",
    "wof:name":"M\u00fcller H.k. Planungs Und Architekturb\u00fcro Ag",
    "wof:placetype":"venue"
},
  "geometry": {"coordinates":[8.54261,47.385372],"type":"Point"}
}