{
  "type": "Feature",
  "properties": {
    "iso:country":"CH",
    "sg:address":"Bahnhofstrasse 28a 8001 Z\u00fcrich. Postfach",
    "sg:city":"Wallisellen",
    "sg:orig_category":"RESTAURANTS: TEA-ROOMS",
    "sg:postcode":"8304",
    "sg:province":"Z\u00fcrich",
    "wof:name":"Hammer Tony Restaurant Zeughauskeller",
    "wof:placetype":"venue"
},
  "geometry": {"coordinates":[8.5395030975,47.3698120117],"type":"Point"}
}