{
  "type": "Feature",
  "properties": {
    "iso:country":"CH",
    "sg:address":"Grand'rue 82",
    "sg:city":"Rolle",
    "sg:orig_category":"W\u00e4scherei U chemische Reinigung",
    "sg:phone":"+41 21 944 00 74",
    "sg:postcode":"1180",
    "sg:province":"Vaud",
    "wof:name":"Pressing La Tour Berardo Vieira Espinosa",
    "wof:placetype":"venue"
},
  "geometry": {"coordinates":[6.8567271233,46.4529266357],"type":"Point"}
}