{
  "type": "Feature",
  "properties": {
    "addr:full":"Via Vallemaggia Solduno Ticino 6600",
    "addr:postcode":"6600",
    "addr:street":"Via Vallemaggia",
    "iso:country":"CH",
    "sg:address":"Via Vallemaggia",
    "sg:city":"Solduno",
    "sg:classifiers":[
        {
            "category":"Banks & Credit Unions",
            "subcategory":"Bank",
            "type":"Services"
        }
    ],
    "sg:phone":"+41 91 752 10 62",
    "sg:postcode":"6600",
    "sg:province":"Ticino",
    "wof:name":"Raiffeisen Di Solduno",
    "wof:placetype":"venue"
},
  "geometry": {"coordinates":[8.77862,46.169941],"type":"Point"}
}