{
  "type": "Feature",
  "properties": {
    "iso:country":"CH",
    "sg:address":"Bleiche",
    "sg:city":"Azmoos",
    "sg:orig_category":"Bauschreinerei Herstellung von Teppichen",
    "sg:phone":"+41 81 783 10 29",
    "sg:postcode":"9478",
    "sg:province":"St. Gallen",
    "wof:name":"Heeb Gebr. Bodenbel\u00e4ge",
    "wof:placetype":"venue"
},
  "geometry": {"coordinates":[9.486405,47.08115],"type":"Point"}
}