{
  "type": "Feature",
  "properties": {
    "addr:full":"Sumatrastrasse 31 Z\u00fcrich Z\u00fcrich 8006",
    "addr:housenumber":"31",
    "addr:postcode":"8006",
    "addr:street":"Sumatrastrasse",
    "iso:country":"CH",
    "sg:address":"Sumatrastrasse 31",
    "sg:city":"Z\u00fcrich",
    "sg:orig_category":"Bezirks, Sekundar, Realschulen, Oberstufe der Primarschulen Maturit\u00e4tsschulen, Lehrerseminarien",
    "sg:phone":"+41 13608200",
    "sg:postcode":"8006",
    "sg:province":"Z\u00fcrich",
    "wof:name":"Freie Katholische Schulen",
    "wof:placetype":"venue"
},
  "geometry": {"coordinates":[8.542858,47.381916],"type":"Point"}
}