{
  "type": "Feature",
  "properties": {
    "iso:country":"CH",
    "sg:address":"La Crois\u00e9e",
    "sg:city":"Noville",
    "sg:orig_category":"Non-Classified Establishments",
    "sg:postcode":"1845",
    "sg:province":"Vaud",
    "wof:name":"Migrol Service, Antoine Sierro",
    "wof:placetype":"venue"
},
  "geometry": {"coordinates":[6.919754982,46.386680603],"type":"Point"}
}