{
  "type": "Feature",
  "properties": {
    "iso:country":"CH",
    "sg:address":"1225 Ch\u00eane-bourg Case Postale 132",
    "sg:city":"Ch\u00eane-bourg",
    "sg:orig_category":"Sportvereine Ballsport Tennis",
    "sg:phone":"+41 32 932 10 00",
    "sg:postcode":"1225",
    "sg:province":"Gen\u00e8ve",
    "wof:name":"Tennis-club Les Brenets",
    "wof:placetype":"venue"
},
  "geometry": {"coordinates":[6.6998171806,47.0632781982],"type":"Point"}
}