{
  "type": "Feature",
  "properties": {
    "iso:country":"CH",
    "sg:address":"Bahnstrasse 1",
    "sg:city":"T\u00e4gerwilen",
    "sg:orig_category":"Architektur U Ingenieurb\u00fcros",
    "sg:phone":"+41 71 666 70 00",
    "sg:postcode":"8274",
    "sg:province":"Thurgau",
    "wof:name":"Saf Simulation, Analysis And Forecasting Ag",
    "wof:placetype":"venue"
},
  "geometry": {"coordinates":[9.128542,47.660004],"type":"Point"}
}