{
  "type": "Feature",
  "properties": {
    "iso:country":"CH",
    "sg:address":"B\u00fctzbergstrasse 103 4900 Langenthal. Postfach 845",
    "sg:city":"Langenthal",
    "sg:orig_category":"Instandhaltung U Reparatur von Automobilen",
    "sg:phone":"+41 62 922 66 77",
    "sg:postcode":"4900",
    "sg:province":"Bern",
    "wof:name":"Markus Leuenberger",
    "wof:placetype":"venue"
},
  "geometry": {"coordinates":[7.7684211731,47.2174530029],"type":"Point"}
}