{
  "type": "Feature",
  "properties": {
    "addr:full":"Landstrasse 72 Netstal Glarus 8754",
    "addr:housenumber":"72",
    "addr:postcode":"8754",
    "addr:street":"Landstrasse",
    "iso:country":"CH",
    "sg:address":"Landstrasse 72",
    "sg:city":"Netstal",
    "sg:orig_category":"Detailhandel mit Brot, Back U S\u00fcsswaren",
    "sg:phone":"+41 55 640 20 67",
    "sg:postcode":"8754",
    "sg:province":"Glarus",
    "wof:name":"Kurt Villiger B\u00e4ckerei-konditorei",
    "wof:placetype":"venue"
},
  "geometry": {"coordinates":[9.052816,47.060429],"type":"Point"}
}