{
  "type": "Feature",
  "properties": {
    "iso:country":"CH",
    "sg:address":"Hintere Bahnstrasse 5",
    "sg:city":"K\u00f6lliken",
    "sg:orig_category":"P\u00e9dicure",
    "sg:phone":"+41 62 723 44 20",
    "sg:postcode":"5742",
    "sg:province":"Aargau",
    "wof:name":"Gertrud Remondini P\u00e9dicure",
    "wof:placetype":"venue"
},
  "geometry": {"coordinates":[8.0264453888,47.3344993591],"type":"Point"}
}