{
  "type": "Feature",
  "properties": {
    "iso:country":"CH",
    "sg:address":"Rue Sous-le-pr\u00e9 19a",
    "sg:city":"B\u00f4le",
    "sg:orig_category":"Kohle Grosshandel Tank Reinigung and Revision",
    "sg:postcode":"2014",
    "sg:province":"Neuch\u00e2tel",
    "wof:name":"Margot Mazout Sa",
    "wof:placetype":"venue"
},
  "geometry": {"coordinates":[6.8478851318,46.9683647156],"type":"Point"}
}