{
  "type": "Feature",
  "properties": {
    "iso:country":"CH",
    "sg:address":"Asylstrasse 50",
    "sg:city":"M\u00e4nnedorf",
    "sg:orig_category":"Sonstige Aktivit\u00e4ten der nicht-\u00e4rztlichen Medizinalberufe",
    "sg:phone":"+41 71 222 42 47",
    "sg:postcode":"8708",
    "sg:province":"Z\u00fcrich",
    "wof:name":"Corsana Praxis F\u00fcr Ganzheitliche Lebensenergie",
    "wof:placetype":"venue"
},
  "geometry": {"coordinates":[9.3814573288,47.3907775879],"type":"Point"}
}