{
  "type": "Feature",
  "properties": {
    "addr:full":"Route De Nendaz 2 Sion Valais 1950",
    "addr:housenumber":"2",
    "addr:postcode":"1950",
    "addr:street":"Route De Nendaz",
    "iso:country":"CH",
    "sg:address":"Route De Nendaz 2",
    "sg:city":"Sion",
    "sg:orig_category":"Bauschreinerei Herstellung von M\u00f6beln verschiedener Art",
    "sg:phone":"+41 27 203 43 78",
    "sg:postcode":"1950",
    "sg:province":"Valais",
    "wof:name":"Giuseppe Sofia Eb\u00e9nisterie",
    "wof:placetype":"venue"
},
  "geometry": {"coordinates":[7.366804,46.220013],"type":"Point"}
}