{
  "type": "Feature",
  "properties": {
    "iso:country":"CH",
    "sg:address":"Goppisbergeralp",
    "sg:city":"Riederalp",
    "sg:orig_category":"Detailhandel mit Waren verschiedener Art, Hauptrichtung Nahrungsmittel",
    "sg:phone":"+41 33 733 10 64",
    "sg:postcode":"3987",
    "sg:province":"Valais",
    "wof:name":"Armin Buchs Lebensmittel Eisenwaren",
    "wof:placetype":"venue"
},
  "geometry": {"coordinates":[7.4426198006,46.4583282471],"type":"Point"}
}