{
  "type": "Feature",
  "properties": {
    "iso:country":"CH",
    "sg:address":"Gewerbestrasse 5 6330 Cham. Postfach",
    "sg:city":"Cham",
    "sg:orig_category":"Grosshandel mit Getr\u00e4nken",
    "sg:postcode":"6330",
    "sg:province":"Zug",
    "wof:name":"Wyhuus St. Martin Ag",
    "wof:placetype":"venue"
},
  "geometry": {"coordinates":[8.4734659195,47.1885452271],"type":"Point"}
}