{
  "type": "Feature",
  "properties": {
    "iso:country":"CH",
    "sg:address":"Ottikerstrasse 2",
    "sg:city":"Z\u00fcrich",
    "sg:orig_category":"Sonstige Hilfs U Nebent\u00e4tigkeiten f\u00fcr die Schiffahrt",
    "sg:postcode":"8006",
    "sg:province":"Z\u00fcrich",
    "wof:name":"Winterlager Zsc",
    "wof:placetype":"venue"
},
  "geometry": {"coordinates":[8.5419111252,47.3852424622],"type":"Point"}
}