{
  "type": "Feature",
  "properties": {
    "iso:country":"CH",
    "sg:address":"Chemin De Champ-pamont 77",
    "sg:city":"Cheseaux-lausanne",
    "sg:orig_category":"Herstellung von Teppichen Verlegen von Fliesen U Platten",
    "sg:postcode":"1033",
    "sg:province":"Vaud",
    "wof:name":"Caloz Ren\u00e9",
    "wof:placetype":"venue"
},
  "geometry": {"coordinates":[6.6076822281,46.5887374878],"type":"Point"}
}