{
  "type": "Feature",
  "properties": {
    "iso:country":"CH",
    "sg:address":"Jurastrasse 6",
    "sg:city":"Aarwangen",
    "sg:orig_category":"RESTAURANTS: TEA-ROOMS",
    "sg:phone":"+41 62 922 63 63",
    "sg:postcode":"4912",
    "sg:province":"Bern",
    "wof:name":"Restaurant Rank, Pf\u00e4ffli Paulina",
    "wof:placetype":"venue"
},
  "geometry": {"coordinates":[7.7686800957,47.240447998],"type":"Point"}
}