{
  "type": "Feature",
  "properties": {
    "iso:country":"CH",
    "sg:address":"Miremont Immeuble Le",
    "sg:city":"Montana-vermala",
    "sg:orig_category":"Fachdetailhandel in Verkaufsr\u00e4umen",
    "sg:postcode":"3962",
    "wof:name":"Ski Rinaldo, Jacomelli",
    "wof:placetype":"venue"
},
  "geometry": {"coordinates":[7.4924340248,46.3144187927],"type":"Point"}
}