{
  "type": "Feature",
  "properties": {
    "iso:country":"CH",
    "sg:address":"Zugerstrasse 20",
    "sg:city":"Oberlunkhofen",
    "sg:orig_category":"Nationale Postdienste",
    "sg:phone":"+41 56 634 11 36",
    "sg:postcode":"8917",
    "sg:province":"Aargau",
    "wof:name":"Die Schweizerische Post",
    "wof:placetype":"venue"
},
  "geometry": {"coordinates":[8.3901281357,47.3115997314],"type":"Point"}
}