{
  "type": "Feature",
  "properties": {
    "iso:country":"CH",
    "sg:address":"Gladbachstrasse 105 8044 Z\u00fcrich. Postfach 610",
    "sg:city":"Z\u00fcrich",
    "sg:orig_category":"Finanzierungsinstitutionen Unternehmensberatung",
    "sg:phone":"+41 12519020",
    "sg:postcode":"8044",
    "sg:province":"Z\u00fcrich",
    "wof:name":"Kk Investment Research G.r.k\u00e4ser Unternehmensber.",
    "wof:placetype":"venue"
},
  "geometry": {"coordinates":[8.5573129654,47.3785896301],"type":"Point"}
}