{
  "type": "Feature",
  "properties": {
    "iso:country":"CH",
    "sg:address":"Aarestrasse 2",
    "sg:city":"Thun",
    "sg:orig_category":"Tierarztpraxis",
    "sg:phone":"+41 52 741 14 00",
    "sg:postcode":"3600",
    "sg:province":"Bern",
    "wof:name":"Dr. Med. Vet. Georg Steinbach Tierarzt",
    "wof:placetype":"venue"
},
  "geometry": {"coordinates":[8.8582897186,47.6603813171],"type":"Point"}
}