{
  "type": "Feature",
  "properties": {
    "iso:country":"CH",
    "sg:address":"Palazzo Stisa",
    "sg:city":"Cadenazzo",
    "sg:orig_category":"Grosshandel mit Kaffee, Tee, Kakao U Gew\u00fcrzen Grosshandel mit Nahrungsmitteln, Getr\u00e4nken U Tabakware",
    "sg:phone":"+41 91 858 29 63",
    "sg:postcode":"6593",
    "sg:province":"Ticino",
    "wof:name":"Rebu Sa Alimentari All'ingrosso",
    "wof:placetype":"venue"
},
  "geometry": {"coordinates":[8.9523019791,46.1495780945],"type":"Point"}
}