{
  "type": "Feature",
  "properties": {
    "iso:country":"CH",
    "sg:address":"Breitingerstrasse 21",
    "sg:city":"Z\u00fcrich",
    "sg:orig_category":"Handelsvermittlung U Grosshandel",
    "sg:phone":"+41 12027732",
    "sg:postcode":"8002",
    "sg:province":"Z\u00fcrich",
    "wof:name":"Aldino Ag",
    "wof:placetype":"venue"
},
  "geometry": {"coordinates":[8.5332479477,47.3622436523],"type":"Point"}
}