{
  "type": "Feature",
  "properties": {
    "iso:country":"CH",
    "sg:address":"Sternmattweg 4b 6010 Kriens. Postfach 2459",
    "sg:city":"Luzern",
    "sg:orig_category":"Herstellung von Akkumulatoren U Batterien Sonstiger Grosshandel",
    "sg:phone":"+41 32 621 29 91",
    "sg:postcode":"6002",
    "sg:province":"Luzern",
    "wof:name":"Mso Batterietechnik, Studer Markus",
    "wof:placetype":"venue"
},
  "geometry": {"coordinates":[7.5047302246,47.2339859009],"type":"Point"}
}