{
  "type": "Feature",
  "properties": {
    "iso:country":"CH",
    "sg:address":"Steinackerstrasse 3 8302 Kloten. Postfach",
    "sg:city":"Kloten",
    "sg:orig_category":"Grosshandel mit Erzen U Metallen",
    "sg:postcode":"8302",
    "sg:province":"Z\u00fcrich",
    "wof:name":"Gh Steel Ag",
    "wof:placetype":"venue"
},
  "geometry": {"coordinates":[8.5934362411,47.4502754211],"type":"Point"}
}