{
  "type": "Feature",
  "properties": {
    "iso:country":"CH",
    "sg:address":"In Der Hub 34",
    "sg:city":"Zuerich",
    "sg:orig_category":"Dienstleistungen, Soziales",
    "sg:postcode":"8057",
    "sg:province":"Z\u00fcrich",
    "wof:name":"Stiftung Monikaheim",
    "wof:placetype":"venue"
},
  "geometry": {"coordinates":[8.554763,47.397896],"type":"Point"}
}