{
  "type": "Feature",
  "properties": {
    "iso:country":"CH",
    "sg:address":"Freiestrasse 41 8032 Z\u00fcrich 32 Zust. Postfach 320",
    "sg:city":"Z\u00fcrich",
    "sg:orig_category":"Religi\u00f6se Vereinigungen",
    "sg:phone":"+41 12517519",
    "sg:postcode":"8032",
    "sg:province":"Z\u00fcrich",
    "wof:name":"Ueberseeische Missions-gemeinschaft",
    "wof:placetype":"venue"
},
  "geometry": {"coordinates":[8.5679702759,47.3668403625],"type":"Point"}
}