{
  "type": "Feature",
  "properties": {
    "addr:full":"Albisstrasse 133 Z\u00fcrich Z\u00fcrich 8038",
    "addr:housenumber":"133",
    "addr:postcode":"8038",
    "addr:street":"Albisstrasse",
    "iso:country":"CH",
    "sg:address":"Albisstrasse 133",
    "sg:city":"Z\u00fcrich",
    "sg:orig_category":"Architekturb\u00fcros",
    "sg:phone":"+41 14830500",
    "sg:postcode":"8038",
    "sg:province":"Z\u00fcrich",
    "wof:name":"Urs Weiss Architekturb\u00fcro",
    "wof:placetype":"venue"
},
  "geometry": {"coordinates":[8.530219,47.33588],"type":"Point"}
}