{
  "type": "Feature",
  "properties": {
    "iso:country":"CH",
    "sg:address":"Auberg 6",
    "sg:city":"Basel",
    "sg:orig_category":"Unclassifiable Establishments",
    "sg:postcode":"4051",
    "sg:province":"Basel-Stadt",
    "wof:name":"Berna Biotech Ag",
    "wof:placetype":"venue"
},
  "geometry": {"coordinates":[7.5850558281,47.5524711609],"type":"Point"}
}