{
  "type": "Feature",
  "properties": {
    "iso:country":"CH",
    "sg:address":"B\u00fcnn 19",
    "sg:city":"Magden",
    "sg:orig_category":"Sonstige Institutionen des Sozialwesens ohne Beherbergung",
    "sg:postcode":"4312",
    "sg:province":"Aargau",
    "wof:name":"La Leche Liga",
    "wof:placetype":"venue"
},
  "geometry": {"coordinates":[7.8170847893,47.5260887146],"type":"Point"}
}