{
  "type": "Feature",
  "properties": {
    "iso:country":"CH",
    "sg:address":"R\u00fctelti 535",
    "sg:city":"Triesenberg",
    "sg:orig_category":"Detailhandel mit M\u00f6beln Verlegen von Fussboden",
    "sg:phone":"+423 262 45 12",
    "sg:postcode":"9497",
    "wof:name":"Simon Beck Ag Polster-atelier",
    "wof:placetype":"venue"
},
  "geometry": {"coordinates":[9.5446863174,47.1146888733],"type":"Point"}
}