{
  "type": "Feature",
  "properties": {
    "iso:country":"CH",
    "sg:address":"Schaufelweg 5",
    "sg:city":"K\u00f6niz",
    "sg:orig_category":"Sonstige mit der Informatik verbundene T\u00e4tigkeiten",
    "sg:postcode":"3098",
    "sg:province":"Bern",
    "wof:name":"Edras-beratung Monnier Andr\u00e9",
    "wof:placetype":"venue"
},
  "geometry": {"coordinates":[7.4158120155,46.9106864929],"type":"Point"}
}