{
  "type": "Feature",
  "properties": {
    "iso:country":"CH",
    "sg:address":"St. Gallerstrasse 19 9042 Speicher. Postfach 246",
    "sg:city":"Speicher",
    "sg:classifiers":[
        {
            "category":"Manufacturing",
            "subcategory":"Metals",
            "type":"Manufacturing & Wholesale Goods"
        }
    ],
    "sg:phone":"+41 41 670 17 71",
    "sg:postcode":"9042",
    "sg:province":"Appenzell Ausserrhoden",
    "sg:tags":[
        "u",
        "leichtmetallbau",
        "stahl"
    ],
    "wof:name":"Ebag Edelstahlbau Ag",
    "wof:placetype":"venue"
},
  "geometry": {"coordinates":[8.2764205933,46.9400062561],"type":"Point"}
}