{
  "type": "Feature",
  "properties": {
    "iso:country":"CH",
    "sg:address":"Rue De La Gare 2",
    "sg:city":"Peseux",
    "sg:orig_category":"Bauschreinerei Herstellung von M\u00f6beln verschiedener Art",
    "sg:phone":"+41 32 731 13 92",
    "sg:postcode":"2034",
    "sg:province":"Neuch\u00e2tel",
    "wof:name":"Fl\u00fcckiger Claude Sa",
    "wof:placetype":"venue"
},
  "geometry": {"coordinates":[6.886221,46.985855],"type":"Point"}
}