{
  "type": "Feature",
  "properties": {
    "iso:country":"CH",
    "sg:address":"Baumgartenstrasse 5 8200 Schaffhausen. Postfach 309",
    "sg:city":"Schaffhausen",
    "sg:orig_category":"Berufsbildende weiterf\u00fchrende Schulen",
    "sg:postcode":"8200",
    "sg:province":"Schaffhausen",
    "wof:name":"Kv-schulhaus Schaffhausen Ag",
    "wof:placetype":"venue"
},
  "geometry": {"coordinates":[8.637946,47.694561],"type":"Point"}
}