{
  "type": "Feature",
  "properties": {
    "iso:country":"CH",
    "sg:address":"Buechstrasse 28",
    "sg:city":"Jona",
    "sg:orig_category":"Pensionskassen",
    "sg:phone":"+41 18001300",
    "sg:postcode":"8645",
    "sg:province":"St. Gallen",
    "wof:name":"Pensionskasse Der Scania Truck Ag",
    "wof:placetype":"venue"
},
  "geometry": {"coordinates":[8.8679361343,47.2272186279],"type":"Point"}
}