{
  "type": "Feature",
  "properties": {
    "iso:country":"CH",
    "sg:address":"Chemin Eug\u00e8ne-grasset 14",
    "sg:city":"Lausanne",
    "sg:orig_category":"Kinderkrippen U horte",
    "sg:phone":"+41 21 612 66 36",
    "sg:postcode":"1006",
    "sg:province":"Vaud",
    "wof:name":"Cr\u00e8che Du Servan",
    "wof:placetype":"venue"
},
  "geometry": {"coordinates":[6.6324257851,46.5123825073],"type":"Point"}
}