{
  "type": "Feature",
  "properties": {
    "iso:country":"CH",
    "sg:address":"Mara\u00eechers Rue Des 3 1205 Gen\u00e8ve. Postfach",
    "sg:city":"Gen\u00e8ve",
    "sg:orig_category":"Fachdetailhandel in Verkaufsr\u00e4umen",
    "sg:postcode":"1205",
    "sg:province":"Gen\u00e8ve",
    "wof:name":"S\u00e9chaud Daniel",
    "wof:placetype":"venue"
},
  "geometry": {"coordinates":[6.1342411041,46.1999206543],"type":"Point"}
}