{
  "type": "Feature",
  "properties": {
    "iso:country":"CH",
    "sg:address":"L\u00e4ngengrund",
    "sg:city":"Trub",
    "sg:orig_category":"Detailhandel mit Waren verschiedener Art, Hauptrichtung Nahrungsmittel",
    "sg:phone":"+41 34 495 58 26",
    "sg:postcode":"3556",
    "sg:province":"Bern",
    "wof:name":"Ernst Rentsch Lebensmittel",
    "wof:placetype":"venue"
},
  "geometry": {"coordinates":[7.8621730804,46.9316520691],"type":"Point"}
}