{
  "type": "Feature",
  "properties": {
    "iso:country":"CH",
    "sg:address":"Weidweg 8",
    "sg:city":"K\u00f6niz",
    "sg:orig_category":"Elektroinstallation",
    "sg:phone":"+41 31 971 00 36",
    "sg:postcode":"3098",
    "sg:province":"Bern",
    "wof:name":"Scherler Ag, Elektro Und Telematik",
    "wof:placetype":"venue"
},
  "geometry": {"coordinates":[7.4174809456,46.9218444824],"type":"Point"}
}