{
  "type": "Feature",
  "properties": {
    "iso:country":"CH",
    "sg:address":"Grand-rue 18",
    "sg:city":"Peseux",
    "sg:orig_category":"Organisationen der Wohlfahrtspflege",
    "sg:phone":"+41 71 245 66 23",
    "sg:postcode":"2034",
    "sg:province":"Neuch\u00e2tel",
    "wof:name":"Heilp\u00e4dagogischer Dienst St.gallen-appenzell-glarus",
    "wof:placetype":"venue"
},
  "geometry": {"coordinates":[9.3943805695,47.4284172058],"type":"Point"}
}