{
  "type": "Feature",
  "properties": {
    "iso:country":"CH",
    "sg:address":"Hauptstrasse 18",
    "sg:city":"Hochdorf",
    "sg:orig_category":"Non-Classified Establishments",
    "sg:postcode":"6280",
    "sg:province":"Luzern",
    "wof:name":"Halter Gmbh",
    "wof:placetype":"venue"
},
  "geometry": {"coordinates":[8.290473938,47.1665420532],"type":"Point"}
}