{
  "type": "Feature",
  "properties": {
    "iso:country":"CH",
    "sg:address":"Rh\u00f4ne Rue Du 114 1204 Gen\u00e8ve. Postfach",
    "sg:city":"Gen\u00e8ve",
    "sg:orig_category":"Grosshandel mit Holz U Baustoffen",
    "sg:postcode":"1204",
    "sg:province":"Gen\u00e8ve",
    "wof:name":"Europlan Ag",
    "wof:placetype":"venue"
},
  "geometry": {"coordinates":[8.7577753067,47.2063064575],"type":"Point"}
}