{
  "type": "Feature",
  "properties": {
    "iso:country":"CH",
    "sg:address":"Hardstrasse 319",
    "sg:city":"Z\u00fcrich",
    "sg:orig_category":"Axial Compressors",
    "sg:phone":"+41 12782211",
    "sg:postcode":"8005",
    "sg:province":"Z\u00fcrich",
    "wof:name":"Man Turbomaschinen Ag Schweiz",
    "wof:placetype":"venue"
},
  "geometry": {"coordinates":[8.521833,47.390533],"type":"Point"}
}