{
  "type": "Feature",
  "properties": {
    "iso:country":"CH",
    "sg:address":"Rue Du Seyon 17",
    "sg:city":"Neuch\u00e2tel",
    "sg:orig_category":"Elektroinstallation Herstellung von Radio U Fernsehger\u00e4ten sowie phono U videotechnischen Ger\u00e4ten",
    "sg:phone":"+41 32 725 00 00",
    "sg:postcode":"2000",
    "sg:province":"Neuch\u00e2tel",
    "wof:name":"E.c.s., Executive Communication Systems Neuch\u00e2tel Sa",
    "wof:placetype":"venue"
},
  "geometry": {"coordinates":[6.9280581474,46.9928359985],"type":"Point"}
}