{
  "type": "Feature",
  "properties": {
    "iso:country":"CH",
    "sg:address":"Dorfstrasse 129",
    "sg:city":"Obfelden",
    "sg:classifiers":[
        {
            "category":"Restaurant",
            "type":"Food & Drink"
        }
    ],
    "sg:phone":"+41 17614101",
    "sg:postcode":"8912",
    "sg:province":"Z\u00fcrich",
    "wof:name":"Restaurant R\u00fctli",
    "wof:placetype":"venue"
},
  "geometry": {"coordinates":[8.4074897766,47.2638473511],"type":"Point"}
}