{
  "type": "Feature",
  "properties": {
    "iso:country":"CH",
    "sg:address":"Baslerstrasse 1",
    "sg:city":"Olten",
    "sg:orig_category":"Detailhandel mit M\u00f6beln U Haushaltsgegenst\u00e4nden",
    "sg:phone":"+41 62 207 11 88",
    "sg:postcode":"4600",
    "sg:province":"Solothurn",
    "wof:name":"Inside. Home & Office Jud Norbert",
    "wof:placetype":"venue"
},
  "geometry": {"coordinates":[7.9025349617,47.3507194519],"type":"Point"}
}