{
  "type": "Feature",
  "properties": {
    "iso:country":"CH",
    "sg:address":"Leimenstrasse 68 4051 Basel. Postfach",
    "sg:city":"Basel",
    "sg:orig_category":"Institutionen des Sozialwesens ohne Beherbergung",
    "sg:postcode":"4051",
    "sg:province":"Basel-Stadt",
    "wof:name":"Samuel Und Rosalie Levaillant-wohlfahrtsstiftung F\u00f6rderung D. Sozialen Wohlfahrt, Bes. Unterst\u00fctzung D. J\u00fcdischen Heims La Charmille U. D. Altersheims Humanitas In Riehen",
    "wof:placetype":"venue"
},
  "geometry": {"coordinates":[7.5804228783,47.5522651672],"type":"Point"}
}