{
  "type": "Feature",
  "properties": {
    "iso:country":"CH",
    "sg:address":"Lenzburgerstrasse 17 5507 Mellingen. Postfach",
    "sg:city":"Mellingen",
    "sg:orig_category":"Instandhaltung U Reparatur von Automobilen Tankstellen",
    "sg:phone":"+41 56 491 16 16",
    "sg:postcode":"5507",
    "sg:province":"Aargau",
    "wof:name":"Garage Weber Ag",
    "wof:placetype":"venue"
},
  "geometry": {"coordinates":[8.2726888657,47.4159851074],"type":"Point"}
}