{
  "type": "Feature",
  "properties": {
    "addr:full":"Schaffhauserstrasse 139 8302 Kloten. Postfach 150 Kloten Z\u00fcrich 8302",
    "addr:housenumber":"139;150",
    "addr:postcode":"8302 kloten.;8302",
    "addr:street":"Schaffhauserstrasse;Postfach",
    "iso:country":"CH",
    "sg:address":"Schaffhauserstrasse 139 8302 Kloten. Postfach 150",
    "sg:city":"Kloten",
    "sg:orig_category":"Detailhandel mit Brot, Back U S\u00fcsswaren",
    "sg:phone":"+41 18137213",
    "sg:postcode":"8302",
    "sg:province":"Z\u00fcrich",
    "wof:name":"Hans Hofmann B\u00e4ckerei-konditorei",
    "wof:placetype":"venue"
},
  "geometry": {"coordinates":[8.580487,47.452114],"type":"Point"}
}