{
  "type": "Feature",
  "properties": {
    "iso:country":"CH",
    "sg:address":"Rue Du 1er-mars 6",
    "sg:city":"Geneveys-coffrane",
    "sg:classifiers":[
        {
            "category":"Restaurant",
            "type":"Food & Drink"
        }
    ],
    "sg:phone":"+41 91 832 01 31",
    "sg:postcode":"2206",
    "sg:province":"Neuch\u00e2tel",
    "wof:name":"Tea-room La Terrazza",
    "wof:placetype":"venue"
},
  "geometry": {"coordinates":[9.1906404495,46.4630584717],"type":"Point"}
}