{
  "type": "Feature",
  "properties": {
    "iso:country":"CH",
    "sg:address":"Reutistrasse 5a",
    "sg:city":"Kreuzlingen",
    "sg:orig_category":"Vermietung U Verpachtung von eigenen Immobilien",
    "sg:postcode":"8280",
    "sg:province":"Thurgau",
    "wof:name":"Trustag Ag",
    "wof:placetype":"venue"
},
  "geometry": {"coordinates":[9.1970558167,47.6402282715],"type":"Point"}
}