{
  "type": "Feature",
  "properties": {
    "iso:country":"CH",
    "sg:address":"Chemin Du Brit 9",
    "sg:city":"Yvonand",
    "sg:orig_category":"Mechanische Werkst\u00e4tten",
    "sg:phone":"+41 24 430 17 06",
    "sg:postcode":"1462",
    "sg:province":"Vaud",
    "wof:name":"Daniel Baumer M\u00e9canique De Pr\u00e9cision",
    "wof:placetype":"venue"
},
  "geometry": {"coordinates":[6.742082119,46.796836853],"type":"Point"}
}