{
  "type": "Feature",
  "properties": {
    "iso:country":"CH",
    "sg:address":"Avenue De Cour 18",
    "sg:city":"Lausanne",
    "sg:orig_category":"Wohnheime f\u00fcr Kinder U Jugendliche",
    "sg:phone":"+41 21 616 90 61",
    "sg:postcode":"1007",
    "sg:province":"Vaud",
    "wof:name":"Home D'accueil Pour Enfants",
    "wof:placetype":"venue"
},
  "geometry": {"coordinates":[6.6210107803,46.5138015747],"type":"Point"}
}