{
  "type": "Feature",
  "properties": {
    "iso:country":"CH",
    "sg:address":"Hebelstrasse 82",
    "sg:city":"Basel",
    "sg:orig_category":"Freizeit, Hobbies U Vereine",
    "sg:postcode":"4056",
    "sg:province":"Basel-Stadt",
    "wof:name":"Dvd Flixtrade",
    "wof:placetype":"venue"
},
  "geometry": {"coordinates":[7.578465,47.562557],"type":"Point"}
}