{
  "type": "Feature",
  "properties": {
    "iso:country":"CH",
    "sg:address":"Zugerstrasse 39",
    "sg:city":"Unter\u00e4geri",
    "sg:orig_category":"Zimmerei, Dachdeckerei, Bauspenglerei U Abdichtung",
    "sg:phone":"+41 41 750 31 71",
    "sg:postcode":"6314",
    "sg:province":"Zug",
    "wof:name":"Iten & Henggeler Holzbau Ag Zimmerei & Bodenbel\u00e4ge",
    "wof:placetype":"venue"
},
  "geometry": {"coordinates":[8.5786170959,47.1377296448],"type":"Point"}
}