{
  "type": "Feature",
  "properties": {
    "iso:country":"CH",
    "sg:address":"Birkenmatt 2 & 4",
    "sg:city":"Rotkreuz",
    "sg:orig_category":"Herstellung von k\u00e4lte U lufttechnischen Erzeugnissen f\u00fcr gewerbliche Zwecke",
    "sg:phone":"+41 41 790 03 15",
    "sg:postcode":"6343",
    "sg:province":"Zug",
    "wof:name":"Bentax Air-tec Ag",
    "wof:placetype":"venue"
},
  "geometry": {"coordinates":[8.429205,47.14357],"type":"Point"}
}