{
  "type": "Feature",
  "properties": {
    "iso:country":"CH",
    "sg:address":"Place Du Midi 36 1950 Sion Case Postale 33",
    "sg:city":"Sion",
    "sg:orig_category":"Wirtschafts- and Arbeitgeberverb\u00e4nde",
    "sg:phone":"+41 27 323 58 17",
    "sg:postcode":"1951",
    "sg:province":"Valais",
    "wof:name":"Assoc.valaisanne Des Maitres- Boulangers-p\u00e2tissiers",
    "wof:placetype":"venue"
},
  "geometry": {"coordinates":[7.3617019653,46.2314338684],"type":"Point"}
}