{
  "type": "Feature",
  "properties": {
    "iso:country":"CH",
    "sg:address":"Bernstrasse 13",
    "sg:city":"B\u00e4tterkinden",
    "sg:orig_category":"Primarschulen",
    "sg:phone":"+41 32 665 47 44",
    "sg:postcode":"3315",
    "sg:province":"Bern",
    "wof:name":"Primarschule",
    "wof:placetype":"venue"
},
  "geometry": {"coordinates":[7.5400772095,47.12890625],"type":"Point"}
}