{
  "type": "Feature",
  "properties": {
    "iso:country":"CH",
    "sg:address":"Huobmattstrasse 5 6045 Meggen. Postfach 28",
    "sg:city":"Meggen",
    "sg:orig_category":"Erwachsenenbildung U Unterricht Kauf U Verkauf von Immobilien auf eigene Rechnung",
    "sg:phone":"+41 41 227 30 36",
    "sg:postcode":"6045",
    "sg:province":"Luzern",
    "wof:name":"The Empowerment Company Gmbh",
    "wof:placetype":"venue"
},
  "geometry": {"coordinates":[8.3811388016,47.0506782532],"type":"Point"}
}