{
  "type": "Feature",
  "properties": {
    "iso:country":"CH",
    "sg:address":"Spitalstrasse 74 8952 Schlieren. Postfach",
    "sg:city":"Schlieren",
    "sg:orig_category":"Versandhandel",
    "sg:phone":"+41 71 911 74 37",
    "sg:postcode":"8952",
    "sg:province":"Z\u00fcrich",
    "wof:name":"Tag Handels Und Finanz-ag",
    "wof:placetype":"venue"
},
  "geometry": {"coordinates":[9.0449714661,47.4638404846],"type":"Point"}
}