{
  "type": "Feature",
  "properties": {
    "iso:country":"CH",
    "sg:address":"L\u00e4ndliweg 2 5400 Baden. Postfach",
    "sg:city":"Baden",
    "sg:orig_category":"Polizei",
    "sg:phone":"+41 56 200 11 11",
    "sg:postcode":"5401",
    "sg:province":"Aargau",
    "wof:name":"Kantonspolizei",
    "wof:placetype":"venue"
},
  "geometry": {"coordinates":[8.3071832657,47.4706230164],"type":"Point"}
}