{
  "type": "Feature",
  "properties": {
    "addr:full":"Ebnetstrasse 11 N\u00fcrensdorf Z\u00fcrich 8309",
    "addr:housenumber":"11",
    "addr:postcode":"8309",
    "addr:street":"Ebnetstrasse",
    "iso:country":"CH",
    "sg:address":"Ebnetstrasse 11",
    "sg:city":"N\u00fcrensdorf",
    "sg:orig_category":"Autospenglereien",
    "sg:phone":"+41 79 300 18 62",
    "sg:postcode":"8309",
    "sg:province":"Z\u00fcrich",
    "wof:name":"Manfred Oswald Autospenglerei",
    "wof:placetype":"venue"
},
  "geometry": {"coordinates":[8.650709,47.447117],"type":"Point"}
}