{
  "type": "Feature",
  "properties": {
    "iso:country":"CH",
    "sg:address":"Hinterdorfstrasse 17",
    "sg:city":"Mosnang",
    "sg:classifiers":[
        {
            "category":"Restaurant",
            "type":"Food & Drink"
        }
    ],
    "sg:phone":"+41 71 983 15 41",
    "sg:postcode":"9607",
    "sg:province":"St. Gallen",
    "wof:name":"Restaurant Adler",
    "wof:placetype":"venue"
},
  "geometry": {"coordinates":[9.0366182327,47.3627738953],"type":"Point"}
}