{
  "type": "Feature",
  "properties": {
    "iso:country":"CH",
    "sg:address":"T\u00e4nnelistrasse 1",
    "sg:city":"Montlingen",
    "sg:orig_category":"Bauschreinerei Herstellung von Konstruktionsteilen, Fertigbauteilen U Ausbauelementen aus Holz",
    "sg:phone":"+41 71 761 23 23",
    "sg:postcode":"9462",
    "sg:province":"St. Gallen",
    "wof:name":"Eichi-holz, Eicher Andr\u00e9 Und Erich",
    "wof:placetype":"venue"
},
  "geometry": {"coordinates":[9.590661,47.335304],"type":"Point"}
}