{
  "type": "Feature",
  "properties": {
    "iso:country":"CH",
    "sg:address":"Schaffhauserstrasse 452",
    "sg:city":"Z\u00fcrich",
    "sg:orig_category":"Reiseb\u00fcros U Reiseveranstalter",
    "sg:phone":"+41 13028787",
    "sg:postcode":"8052",
    "sg:province":"Z\u00fcrich",
    "wof:name":"Scotty's Reisen Ag",
    "wof:placetype":"venue"
},
  "geometry": {"coordinates":[8.5464448929,47.4177513123],"type":"Point"}
}