{
  "type": "Feature",
  "properties": {
    "iso:country":"CH",
    "sg:address":"Buchenweg 3",
    "sg:city":"Ipsach",
    "sg:orig_category":"Herstellung von sonstigen chemischen Erzeugnissen",
    "sg:phone":"+41 32 331 90 02",
    "sg:postcode":"2563",
    "sg:province":"Bern",
    "wof:name":"Nicolet Chimie",
    "wof:placetype":"venue"
},
  "geometry": {"coordinates":[7.2321081161,47.1128997803],"type":"Point"}
}