{
  "type": "Feature",
  "properties": {
    "iso:country":"CH",
    "sg:address":"Schaffhauserstrasse 232",
    "sg:city":"Z\u00fcrich",
    "sg:orig_category":"Softwareentwicklung U beratung",
    "sg:postcode":"8057",
    "sg:province":"Z\u00fcrich",
    "wof:name":"Perlink Gmbh",
    "wof:placetype":"venue"
},
  "geometry": {"coordinates":[8.5467386246,47.402469635],"type":"Point"}
}