{
  "type": "Feature",
  "properties": {
    "iso:country":"CH",
    "sg:address":"Dorf",
    "sg:city":"D\u00fcrrenroth",
    "sg:orig_category":"Detailhandel mit Brot, Back U S\u00fcsswaren",
    "sg:phone":"+41 31 839 21 96",
    "sg:postcode":"3465",
    "sg:province":"Bern",
    "wof:name":"Leni Wanner B\u00e4ckerei",
    "wof:placetype":"venue"
},
  "geometry": {"coordinates":[7.533846,46.929916],"type":"Point"}
}