{
  "type": "Feature",
  "properties": {
    "iso:country":"CH",
    "sg:address":"Ringstrasse 36",
    "sg:city":"Frauenfeld",
    "sg:orig_category":"Herstellung von Musikinstrumenten",
    "sg:phone":"+41 52 721 34 63",
    "sg:postcode":"8500",
    "sg:province":"Thurgau",
    "wof:name":"Josef Melich Musikinstrumentenbau",
    "wof:placetype":"venue"
},
  "geometry": {"coordinates":[8.9022960663,47.5592002869],"type":"Point"}
}