{
  "type": "Feature",
  "properties": {
    "iso:country":"CH",
    "sg:address":"Hauptstrasse 42",
    "sg:city":"Glarus",
    "sg:orig_category":"Detailhandel mit Spielwaren",
    "sg:phone":"+41 55 640 70 41",
    "sg:postcode":"8750",
    "sg:province":"Glarus",
    "wof:name":"Ernst Wild Pinocchio-spielwaren",
    "wof:placetype":"venue"
},
  "geometry": {"coordinates":[9.0676250458,47.0407295227],"type":"Point"}
}