{
  "type": "Feature",
  "properties": {
    "iso:country":"CH",
    "sg:address":"Romanshornerstrasse 70 8280 Kreuzlingen. Postfach",
    "sg:city":"Kreuzlingen",
    "sg:orig_category":"Nahrungsmittel-Industrie: Rohstoffe",
    "sg:phone":"+41 71 680 06 00",
    "sg:postcode":"8280",
    "sg:province":"Thurgau",
    "wof:name":"Il Mercatino Gmbh Ital. Spezialit\u00e4ten Usw.; Kauf, Verkauf",
    "wof:placetype":"venue"
},
  "geometry": {"coordinates":[9.1936664581,47.6401786804],"type":"Point"}
}