{
  "type": "Feature",
  "properties": {
    "iso:country":"CH",
    "sg:address":"Wollmattweg 8",
    "sg:city":"Dornach",
    "sg:orig_category":"Development Of Trade Fair Concepts",
    "sg:phone":"+41 61 703 89 94",
    "sg:postcode":"4143",
    "sg:province":"Solothurn",
    "wof:name":"Mena Reinigungs- + Messe-service",
    "wof:placetype":"venue"
},
  "geometry": {"coordinates":[7.6125240326,47.4877357483],"type":"Point"}
}