{
  "type": "Feature",
  "properties": {
    "iso:country":"CH",
    "sg:address":"5316",
    "sg:city":"Leuggern",
    "sg:orig_category":"Schulpflegen",
    "sg:phone":"+41 19365542",
    "sg:postcode":"5316",
    "sg:province":"Aargau",
    "wof:name":"Primarschulpflege Der Gemeinde Gossau",
    "wof:placetype":"venue"
},
  "geometry": {"coordinates":[8.7609100342,47.3074913025],"type":"Point"}
}