{
  "type": "Feature",
  "properties": {
    "iso:country":"CH",
    "sg:address":"Langr\u00fctistrasse 14",
    "sg:city":"Jona",
    "sg:orig_category":"Sanit\u00e4r, Heizungs U L\u00fcftungsinstallation Sanit\u00e4rinstallation",
    "sg:phone":"+41 55 410 48 10",
    "sg:postcode":"8645",
    "sg:province":"St. Gallen",
    "wof:name":"Abegg Haustechnik, Sanit\u00e4r, Heizung, Solar",
    "wof:placetype":"venue"
},
  "geometry": {"coordinates":[8.7404937744,47.2046585083],"type":"Point"}
}