{
  "type": "Feature",
  "properties": {
    "iso:country":"CH",
    "sg:address":"Badenerstrasse 865",
    "sg:city":"Z\u00fcrich",
    "sg:orig_category":"Detailhandel mit elektrischen Haushalts-,Radio U Fernsehger\u00e4ten sowie Musikinstrumenten Grosshandel ",
    "sg:phone":"+41 79 209 46 60",
    "sg:postcode":"8048",
    "sg:province":"Z\u00fcrich",
    "wof:name":"Apollo-inox Langone & Cie",
    "wof:placetype":"venue"
},
  "geometry": {"coordinates":[8.4722604752,47.3937034607],"type":"Point"}
}