{
  "type": "Feature",
  "properties": {
    "iso:country":"CH",
    "sg:address":"Pfisternweg 5 6015 Reussb\u00fchl. Postfach",
    "sg:city":"Reussb\u00fchl",
    "sg:orig_category":"Non-Classified Establishments",
    "sg:postcode":"6015",
    "sg:province":"Luzern",
    "wof:name":"Mdi Marble Design Steinegger Daniel",
    "wof:placetype":"venue"
},
  "geometry": {"coordinates":[8.2817163467,47.0664825439],"type":"Point"}
}