{
  "type": "Feature",
  "properties": {
    "iso:country":"CH",
    "sg:address":"S\u00e4getstr. 5",
    "sg:city":"Belp",
    "sg:classifiers":[
        {
            "category":"Transit Center",
            "subcategory":"Freight",
            "type":"Transportation"
        }
    ],
    "sg:phone":"+41 31 819 62 32",
    "sg:postcode":"3123",
    "sg:province":"Bern",
    "sg:tags":[
        "metallurgy",
        "pipe",
        "metalworking",
        "sheet"
    ],
    "wof:name":"Hirsig Blechtechnik Ag",
    "wof:placetype":"venue"
},
  "geometry": {"coordinates":[7.5009279251,46.8885688782],"type":"Point"}
}