{
  "type": "Feature",
  "properties": {
    "iso:country":"CH",
    "sg:address":"Kreuzackerstrasse 18",
    "sg:city":"Sch\u00f6nenwerd",
    "sg:orig_category":"Organisationen des Gesundheitswesen",
    "sg:phone":"+41 71 333 43 57",
    "sg:postcode":"5012",
    "sg:province":"Solothurn",
    "wof:name":"Krankenpflege Teufen Frau Annelies Str\u00fcbi",
    "wof:placetype":"venue"
},
  "geometry": {"coordinates":[9.3870401382,47.3886604309],"type":"Point"}
}