{
  "type": "Feature",
  "properties": {
    "iso:country":"CH",
    "sg:address":"Soldino Via 22 6900 Lugano. Postfach",
    "sg:city":"Lugano",
    "sg:orig_category":"Erbringung von Dienstleistungen f\u00fcr Unternehmen",
    "sg:postcode":"6900",
    "sg:province":"Ticino",
    "wof:name":"Colliard Publicit\u00e9 S\u00e0rl",
    "wof:placetype":"venue"
},
  "geometry": {"coordinates":[5.1808700562,45.8973388672],"type":"Point"}
}