{
  "type": "Feature",
  "properties": {
    "iso:country":"CH",
    "sg:address":"Rue Du Petit-ch\u00eane 27",
    "sg:city":"Lausanne",
    "sg:orig_category":"Detailhandel mit elektrischen Haushalts-,Radio U Fernsehger\u00e4ten sowie Musikinstrumenten Detailhandel",
    "sg:phone":"+41 21 320 85 20",
    "sg:postcode":"1003",
    "sg:province":"Vaud",
    "wof:name":"St\u00e4heli Georg Et Marie-jeanne",
    "wof:placetype":"venue"
},
  "geometry": {"coordinates":[6.629942894,46.5183143616],"type":"Point"}
}