{
  "type": "Feature",
  "properties": {
    "iso:country":"CH",
    "sg:address":"Zollhausstrasse 35/37",
    "sg:city":"Glarus",
    "sg:orig_category":"Detailhandel Reparatur von Gebrauchsg\u00fctern",
    "sg:phone":"+41 55 640 71 27",
    "sg:postcode":"8750",
    "sg:province":"Glarus",
    "wof:name":"Werner & Karin Jacober Gasl\u00e4deli Campingartikel",
    "wof:placetype":"venue"
},
  "geometry": {"coordinates":[9.0635499954,47.043094635],"type":"Point"}
}