{
  "type": "Feature",
  "properties": {
    "iso:country":"CH",
    "sg:address":"Blegistrasse 1",
    "sg:city":"Rotkreuz",
    "sg:classifiers":[
        {
            "category":"Manufacturing",
            "subcategory":"Chemicals & Compounds",
            "type":"Manufacturing & Wholesale Goods"
        }
    ],
    "sg:phone":"+41 41 792 02 06",
    "sg:postcode":"6343",
    "sg:province":"Zug",
    "sg:tags":[
        "chemical-pharmaceutical",
        "industry",
        "material",
        "basic"
    ],
    "wof:name":"Globe Interstar Ag",
    "wof:placetype":"venue"
},
  "geometry": {"coordinates":[8.436128,47.14819],"type":"Point"}
}