{
  "type": "Feature",
  "properties": {
    "addr:full":"H\u00fcnibachstrasse 31 Hilterfingen Bern 3652",
    "addr:housenumber":"31",
    "addr:postcode":"3652",
    "addr:street":"Huenibachstrasse",
    "iso:country":"CH",
    "sg:address":"H\u00fcnibachstrasse 31",
    "sg:city":"Hilterfingen",
    "sg:orig_category":"Blumen U Zierpflanzenbau",
    "sg:phone":"+41 33 243 58 58",
    "sg:postcode":"3652",
    "sg:province":"Bern",
    "wof:name":"Baumann G\u00e4rtnerei Ag",
    "wof:placetype":"venue"
},
  "geometry": {"coordinates":[7.654479,46.741077],"type":"Point"}
}