{
  "type": "Feature",
  "properties": {
    "iso:country":"CH",
    "sg:address":"Ch\u00e9telay 10b",
    "sg:city":"Courfaivre",
    "sg:orig_category":"Zimmerei, Dachdeckerei, Bauspenglerei U Abdichtung",
    "sg:postcode":"2853",
    "sg:province":"Jura",
    "wof:name":"Harco S\u00e0rl",
    "wof:placetype":"venue"
},
  "geometry": {"coordinates":[7.2807021141,47.3344116211],"type":"Point"}
}