{
  "type": "Feature",
  "properties": {
    "iso:country":"CH",
    "sg:address":"Obere Altmatt 234 4717 M\u00fcmliswil. Postfach 2",
    "sg:city":"M\u00fcmliswil",
    "sg:orig_category":"G\u00fcterbef\u00f6rderung im Strassenverkehr",
    "sg:phone":"+41 62 391 49 74",
    "sg:postcode":"4717",
    "sg:province":"Solothurn",
    "wof:name":"Bruno Disler Transporte",
    "wof:placetype":"venue"
},
  "geometry": {"coordinates":[7.706802845,47.3401451111],"type":"Point"}
}