{
  "type": "Feature",
  "properties": {
    "iso:country":"CH",
    "sg:address":"Schw\u00e4ntenmos 15",
    "sg:city":"Zumikon",
    "sg:orig_category":"Werbung",
    "sg:phone":"+41 19181617",
    "sg:postcode":"8126",
    "sg:province":"Z\u00fcrich",
    "wof:name":"Studio Pilone Ag",
    "wof:placetype":"venue"
},
  "geometry": {"coordinates":[8.6195573807,47.3390235901],"type":"Point"}
}