{
  "type": "Feature",
  "properties": {
    "iso:country":"CH",
    "sg:address":"St. Johanns-ring 108",
    "sg:city":"Basel",
    "sg:orig_category":"Sonstige k\u00fcnstlerische U schriftstellerische T\u00e4tigkeiten U Darbietungen",
    "sg:phone":"+41 71 333 38 11",
    "sg:postcode":"4056",
    "sg:province":"Basel-Stadt",
    "wof:name":"Gret Zellweger Kunstgewerbe Bauernmalerei",
    "wof:placetype":"venue"
},
  "geometry": {"coordinates":[9.3893232346,47.3896522522],"type":"Point"}
}