{
  "type": "Feature",
  "properties": {
    "iso:country":"CH",
    "sg:address":"Fallenstettenweg 21 8404 Reutlingen. Postfach",
    "sg:city":"Winterthur",
    "sg:orig_category":"Erschliessung von Grundst\u00fccken",
    "sg:postcode":"8404",
    "sg:province":"Z\u00fcrich",
    "wof:name":"Saalbaugenossenschaft Oberwinterthur",
    "wof:placetype":"venue"
},
  "geometry": {"coordinates":[8.749751091,47.527381897],"type":"Point"}
}