{
  "type": "Feature",
  "properties": {
    "iso:country":"CH",
    "sg:address":"Via Muraccio 60",
    "sg:city":"Ascona",
    "sg:orig_category":"Vermietung U Verpachtung von eigenen Immobilien",
    "sg:postcode":"6612",
    "sg:province":"Ticino",
    "wof:name":"Lavinia Sagl.",
    "wof:placetype":"venue"
},
  "geometry": {"coordinates":[8.7801952362,46.153717041],"type":"Point"}
}