{
  "type": "Feature",
  "properties": {
    "iso:country":"CH",
    "sg:address":"Blegistrasse 15",
    "sg:city":"Baar",
    "sg:classifiers":[
        {
            "category":"Professional",
            "subcategory":"Printing & Photocopies",
            "type":"Services"
        }
    ],
    "sg:phone":"+41 41 760 76 60",
    "sg:postcode":"6340",
    "sg:province":"Zug",
    "sg:tags":[
        "publishing"
    ],
    "wof:name":"Heil, Magnet- Und Werkzeugtechnik",
    "wof:placetype":"venue"
},
  "geometry": {"coordinates":[8.5686693192,47.2156143188],"type":"Point"}
}