{
  "type": "Feature",
  "properties": {
    "iso:country":"CH",
    "sg:address":"Beethovenstrasse 20 8002 Z\u00fcrich. Postfach 4838",
    "sg:city":"Z\u00fcrich",
    "sg:orig_category":"Interessenvertretungen",
    "sg:phone":"+41 71 274 90 90",
    "sg:postcode":"8022",
    "sg:province":"Z\u00fcrich",
    "wof:name":"Textilverband Schweiz (tvs), Gesamtverband Der Schweizerischen Textil Und Bekleidungsindustrie Vereinigung Von Juristen U. Nat\u00fcrlichen Personen",
    "wof:placetype":"venue"
},
  "geometry": {"coordinates":[8.5368890762,47.3663215637],"type":"Point"}
}