{
  "type": "Feature",
  "properties": {
    "iso:country":"CH",
    "sg:address":"Ecoliers Chemin Des",
    "sg:city":"Conthey",
    "sg:orig_category":"Vermietung U Verpachtung von eigenen Immobilien",
    "sg:postcode":"1964",
    "sg:province":"Valais",
    "wof:name":"Consultat, Alfred Metraux",
    "wof:placetype":"venue"
},
  "geometry": {"coordinates":[6.6930069923,46.548122406],"type":"Point"}
}