{
  "type": "Feature",
  "properties": {
    "iso:country":"CH",
    "sg:address":"Spitalgasse 26",
    "sg:city":"Bern",
    "sg:orig_category":"Arztpraxen",
    "sg:phone":"+41 61 401 33 55",
    "sg:postcode":"3011",
    "sg:province":"Bern",
    "wof:name":"Dr.med.feliks Plaszczyk Arzt F\u00fcr Allgemeine Medizin",
    "wof:placetype":"venue"
},
  "geometry": {"coordinates":[7.557374,47.514759],"type":"Point"}
}