{
  "type": "Feature",
  "properties": {
    "iso:country":"CH",
    "sg:address":"Hauptstr.",
    "sg:city":"Tinizong",
    "sg:classifiers":[
        {
            "category":"Travel",
            "subcategory":"Hotels & Motels",
            "type":"Entertainment"
        }
    ],
    "sg:postcode":"7453",
    "sg:province":"Graubunden",
    "sg:tags":[
        "hotels",
        "mit",
        "restaurant"
    ],
    "wof:name":"Margreth Georg.",
    "wof:placetype":"venue"
},
  "geometry": {"coordinates":[9.6248502731,46.5555267334],"type":"Point"}
}