{
  "type": "Feature",
  "properties": {
    "iso:country":"CH",
    "sg:address":"Chem De Maisonneuve 14",
    "sg:city":"Ch\u00e2telaine",
    "sg:classifiers":[
        {
            "category":"Wholesale",
            "subcategory":"Machinery & Supplies",
            "type":"Manufacturing & Wholesale Goods"
        }
    ],
    "sg:phone":"+41 32 328 30 30",
    "sg:postcode":"1219",
    "sg:province":"Gen\u00e8ve",
    "sg:tags":[
        "equipment",
        "equipement",
        "precision",
        "timekeeping"
    ],
    "wof:name":"Braloba Ag",
    "wof:placetype":"venue"
},
  "geometry": {"coordinates":[7.2468318939,47.1393280029],"type":"Point"}
}