{
  "type": "Feature",
  "properties": {
    "iso:country":"CH",
    "sg:address":"Im Glockenacker 68 8053 Z\u00fcrich. Postfach",
    "sg:city":"Z\u00fcrich",
    "sg:orig_category":"Elektroinstallation",
    "sg:phone":"+41 13816123",
    "sg:postcode":"8053",
    "sg:province":"Z\u00fcrich",
    "wof:name":"Gritti W.",
    "wof:placetype":"venue"
},
  "geometry": {"coordinates":[8.6021089554,47.3604812622],"type":"Point"}
}