{
  "type": "Feature",
  "properties": {
    "iso:country":"CH",
    "sg:address":"Hellb\u00fchlerstrasse 10 6017 Ruswil. Postfach 292",
    "sg:city":"Ruswil",
    "sg:orig_category":"Detailhandel mit Brot, Back U S\u00fcsswaren",
    "sg:phone":"+41 41 495 11 37",
    "sg:postcode":"6017",
    "sg:province":"Luzern",
    "wof:name":"Robert Erni B\u00e4ckerei-konditorei",
    "wof:placetype":"venue"
},
  "geometry": {"coordinates":[8.12757,47.082249],"type":"Point"}
}