{
  "type": "Feature",
  "properties": {
    "iso:country":"CH",
    "sg:address":"Museumstrasse 1 2502 Biel/bienne. Postfach",
    "sg:city":"Biel/bienne",
    "sg:orig_category":"Grosshandel mit Datenverarbeitungsger\u00e4ten Grosshandel mit Software",
    "sg:phone":"+41 61 723 85 75",
    "sg:postcode":"2501",
    "sg:province":"Bern",
    "wof:name":"Allewa Gmbh",
    "wof:placetype":"venue"
},
  "geometry": {"coordinates":[7.5253500938,47.5052108765],"type":"Point"}
}