{
  "type": "Feature",
  "properties": {
    "iso:country":"CH",
    "sg:address":"2014 B\u00f4le. Postfach 97",
    "sg:city":"B\u00f4le",
    "sg:orig_category":"Sportvereine Ballsport Fussball",
    "sg:phone":"+41 32 841 45 55",
    "sg:postcode":"2014",
    "sg:province":"Neuch\u00e2tel",
    "wof:name":"Fc B\u00f4le",
    "wof:placetype":"venue"
},
  "geometry": {"coordinates":[6.8359699249,46.9682388306],"type":"Point"}
}