{
  "type": "Feature",
  "properties": {
    "iso:country":"CH",
    "sg:address":"Route Des Colombettes 224",
    "sg:city":"Vuadens",
    "sg:orig_category":"Maler U Glasergewerbe Tapeziererei",
    "sg:postcode":"1628",
    "sg:province":"Fribourg",
    "wof:name":"Jaquet Roland",
    "wof:placetype":"venue"
},
  "geometry": {"coordinates":[6.9933109283,46.6104698181],"type":"Point"}
}