{
  "type": "Feature",
  "properties": {
    "iso:country":"CH",
    "sg:address":"Kreuzwiesen 25",
    "sg:city":"Z\u00fcrich",
    "sg:orig_category":"Geb\u00e4ude, Wohnungsreinigung Reinigungsgewerbe",
    "sg:phone":"+41 13211929",
    "sg:postcode":"8051",
    "sg:province":"Z\u00fcrich",
    "wof:name":"Meris Reinigungen Ag",
    "wof:placetype":"venue"
},
  "geometry": {"coordinates":[8.575512886,47.4065322876],"type":"Point"}
}