{
  "type": "Feature",
  "properties": {
    "iso:country":"CH",
    "sg:address":"L\u00e4ngfeldstrasse 68",
    "sg:city":"Ittigen",
    "sg:orig_category":"Non-Classified Establishments",
    "sg:phone":"+41 79 436 62 39",
    "sg:postcode":"3063",
    "sg:province":"Bern",
    "wof:name":"Vuillemin Patrick Paysagiste",
    "wof:placetype":"venue"
},
  "geometry": {"coordinates":[6.2151851654,46.2650604248],"type":"Point"}
}