{
  "type": "Feature",
  "properties": {
    "iso:country":"CH",
    "sg:address":"Rathausstrasse 42",
    "sg:city":"Liestal",
    "sg:orig_category":"Drogerien Parf\u00fcmerien U sonstiger Detailhandel mit kosmetischen Artikeln U K\u00f6rperpflegemitteln",
    "sg:phone":"+41 61 921 33 20",
    "sg:postcode":"4410",
    "sg:province":"Basel-Landschaft",
    "wof:name":"Drogerie Zum Rathaus Ag Parf\u00fcmerie",
    "wof:placetype":"venue"
},
  "geometry": {"coordinates":[7.7349147797,47.4840354919],"type":"Point"}
}