{
  "type": "Feature",
  "properties": {
    "iso:country":"CH",
    "sg:address":"Via Ai Saleggi 11 6600 Locarno Casella Postale 643",
    "sg:city":"Locarno",
    "sg:orig_category":"Elektroinstallation",
    "sg:phone":"+41 91 756 22 00",
    "sg:postcode":"6600",
    "sg:province":"Ticino",
    "wof:name":"Biscara Giovanettina Sa",
    "wof:placetype":"venue"
},
  "geometry": {"coordinates":[8.8003940582,46.1705741882],"type":"Point"}
}