{
  "type": "Feature",
  "properties": {
    "iso:country":"CH",
    "sg:address":"Birsstrasse 56",
    "sg:city":"Basel",
    "sg:classifiers":[
        {
            "category":"Shopping",
            "subcategory":"Clothing, Apparel, & Fashions",
            "type":"Retail Goods"
        }
    ],
    "sg:phone":"+41 61 311 31 31",
    "sg:postcode":"4052",
    "sg:province":"Basel-Stadt",
    "sg:tags":[
        "hanger",
        "clothes"
    ],
    "wof:name":"Dunkel Service",
    "wof:placetype":"venue"
},
  "geometry": {"coordinates":[7.62105,47.551533],"type":"Point"}
}