{
  "type": "Feature",
  "properties": {
    "iso:country":"CH",
    "sg:address":"Fabrikstrasse 8",
    "sg:city":"Sirnach",
    "sg:classifiers":[
        {
            "category":"Manufacturing",
            "subcategory":"Tools & Machinery",
            "type":"Manufacturing & Wholesale Goods"
        }
    ],
    "sg:phone":"+41 71 966 62 26",
    "sg:postcode":"8370",
    "sg:province":"Thurgau",
    "sg:tags":[
        "construction",
        "container",
        "apparatus"
    ],
    "wof:name":"Cunesta Apparatebau Gmbh",
    "wof:placetype":"venue"
},
  "geometry": {"coordinates":[8.991948,47.462559],"type":"Point"}
}