{
  "type": "Feature",
  "properties": {
    "iso:country":"CH",
    "sg:address":"Gelterkinderstr. 28",
    "sg:city":"Sissach",
    "sg:classifiers":[
        {
            "category":"Home & Garden",
            "subcategory":"Furniture",
            "type":"Retail Goods"
        }
    ],
    "sg:phone":"+41 61 971 40 70",
    "sg:postcode":"4450",
    "sg:province":"Basel-Landschaft",
    "sg:tags":[
        "household",
        "wood"
    ],
    "wof:name":"Wohntip Ag",
    "wof:placetype":"venue"
},
  "geometry": {"coordinates":[7.8228378296,47.4619140625],"type":"Point"}
}