{
  "type": "Feature",
  "properties": {
    "iso:country":"CH",
    "sg:address":"Neue Winterthurerstrasse 9",
    "sg:city":"Bassersdorf",
    "sg:orig_category":"Autolackierereien",
    "sg:phone":"+41 18887988",
    "sg:postcode":"8303",
    "sg:province":"Z\u00fcrich",
    "wof:name":"Avp Autopflege",
    "wof:placetype":"venue"
},
  "geometry": {"coordinates":[8.6433,47.428673],"type":"Point"}
}