{
  "type": "Feature",
  "properties": {
    "iso:country":"CH",
    "sg:address":"Schulstrasse 29",
    "sg:city":"Gebertingen",
    "sg:orig_category":"Innenausbau Zimmerei, Dachdeckerei, Bauspenglerei U Abdichtung",
    "sg:phone":"+41 55 284 10 51",
    "sg:postcode":"8725",
    "sg:province":"St. Gallen",
    "wof:name":"Paul R\u00fcegg Zimmerei Ag",
    "wof:placetype":"venue"
},
  "geometry": {"coordinates":[9.0056867599,47.2526817322],"type":"Point"}
}