{
  "type": "Feature",
  "properties": {
    "iso:country":"CH",
    "sg:address":"6716 Acquarossa. Postfach",
    "sg:city":"Pollegio",
    "sg:orig_category":"Detailhandel mit Fleisch U Fleischwaren",
    "sg:postcode":"6742",
    "sg:province":"Ticino",
    "wof:name":"Ul Nostran Sagl Macelleria",
    "wof:placetype":"venue"
},
  "geometry": {"coordinates":[8.9425296783,46.4558982849],"type":"Point"}
}