{
  "type": "Feature",
  "properties": {
    "iso:country":"CH",
    "sg:address":"B\u00e4tterkindenstrasse 67a",
    "sg:city":"Limpach",
    "sg:orig_category":"Herstellung von sonstigen landwirtschaftlichen Maschinen",
    "sg:postcode":"3317",
    "sg:province":"Bern",
    "wof:name":"Resag",
    "wof:placetype":"venue"
},
  "geometry": {"coordinates":[8.3190050125,47.1303749084],"type":"Point"}
}