{
  "type": "Feature",
  "properties": {
    "iso:country":"CH",
    "sg:address":"Dorf 162",
    "sg:city":"Urn\u00e4sch",
    "sg:orig_category":"Bauspenglerei Zimmerei, Dachdeckerei, Bauspenglerei U Abdichtung",
    "sg:phone":"+41 71 364 12 06",
    "sg:postcode":"9107",
    "sg:province":"Appenzell Ausserrhoden",
    "wof:name":"Werner Engler",
    "wof:placetype":"venue"
},
  "geometry": {"coordinates":[9.283021,47.317043],"type":"Point"}
}