{
  "type": "Feature",
  "properties": {
    "iso:country":"CH",
    "sg:address":"Wartstrasse 19",
    "sg:city":"Winterthur",
    "sg:orig_category":"Non-Classified Establishments",
    "sg:postcode":"8400",
    "sg:province":"Z\u00fcrich",
    "wof:name":"Tai Ji Verena M\u00fcller",
    "wof:placetype":"venue"
},
  "geometry": {"coordinates":[7.6357111931,46.3142280579],"type":"Point"}
}