{
  "type": "Feature",
  "properties": {
    "iso:country":"CH",
    "sg:address":"Feldblumenweg 13",
    "sg:city":"Villmergen",
    "sg:orig_category":"Hardwareberatung",
    "sg:phone":"+41 56 610 08 31",
    "sg:postcode":"5612",
    "sg:province":"Aargau",
    "wof:name":"Meier-pc",
    "wof:placetype":"venue"
},
  "geometry": {"coordinates":[8.2468776703,47.3495597839],"type":"Point"}
}