{
  "type": "Feature",
  "properties": {
    "iso:country":"CH",
    "sg:address":"Via Davos Must\u00e9r 17a",
    "sg:city":"Disentis/must\u00e9r",
    "sg:classifiers":[
        {
            "category":"Manufacturing",
            "subcategory":"Tools & Machinery",
            "type":"Manufacturing & Wholesale Goods"
        }
    ],
    "sg:phone":"+41 32 933 58 20",
    "sg:postcode":"7180",
    "sg:province":"Graubunden",
    "sg:tags":[
        "part",
        "turned",
        "cnc"
    ],
    "wof:name":"Dixi Cylindre Sa",
    "wof:placetype":"venue"
},
  "geometry": {"coordinates":[6.739214,47.052502],"type":"Point"}
}