{
  "type": "Feature",
  "properties": {
    "iso:country":"CH",
    "sg:address":"J\u00fcch",
    "sg:city":"Weissenburg",
    "sg:orig_category":"Allgemeiner Hoch U Tiefbau Hoch U Tiefbau",
    "sg:phone":"+41 79 414 68 73",
    "sg:postcode":"3764",
    "sg:province":"Bern",
    "wof:name":"Knutti A.",
    "wof:placetype":"venue"
},
  "geometry": {"coordinates":[7.47795,46.663574],"type":"Point"}
}