{
  "type": "Feature",
  "properties": {
    "iso:country":"CH",
    "sg:address":"Ayant Route D' 19 1971 Grimisuat. Postfach",
    "sg:city":"Grimisuat",
    "sg:orig_category":"RESTAURANTS: TEA-ROOMS",
    "sg:postcode":"1971",
    "sg:province":"Valais",
    "wof:name":"Mattioli, Trattoria Les Cr\u00eates",
    "wof:placetype":"venue"
},
  "geometry": {"coordinates":[7.3788700104,46.2545089722],"type":"Point"}
}