{
  "type": "Feature",
  "properties": {
    "iso:country":"CH",
    "sg:address":"Birmensdorferstrasse 83 8003 Z\u00fcrich. Postfach",
    "sg:city":"Z\u00fcrich",
    "sg:orig_category":"Fernmeldedienste",
    "sg:phone":"+41 14633294",
    "sg:postcode":"8001",
    "sg:province":"Z\u00fcrich",
    "wof:name":"Endeed Operations Ag Komplexe Internet, Intranetl\u00f6sungen; Strategische Beratung, Betrieb, Unterst\u00fctzung, Wartung",
    "wof:placetype":"venue"
},
  "geometry": {"coordinates":[8.523557663,47.3709754944],"type":"Point"}
}