{
  "type": "Feature",
  "properties": {
    "iso:country":"CH",
    "sg:address":"Ohmstalerstrasse 28 6247 Sch\u00f6tz. Postfach",
    "sg:city":"Sch\u00f6tz",
    "sg:orig_category":"Architekturb\u00fcros",
    "sg:phone":"+41 41 980 21 85",
    "sg:postcode":"6247",
    "sg:province":"Luzern",
    "wof:name":"Anton Bammert Architekturb\u00fcro",
    "wof:placetype":"venue"
},
  "geometry": {"coordinates":[7.984403,47.169437],"type":"Point"}
}