{
  "type": "Feature",
  "properties": {
    "iso:country":"CH",
    "sg:address":"Terreaux Rue Des 5",
    "sg:city":"Neuch\u00e2tel",
    "sg:orig_category":"Herstellung von sonstigen elektrischen Ausr\u00fcstungen",
    "sg:phone":"+41 32 724 51 61",
    "sg:postcode":"2000",
    "sg:province":"Neuch\u00e2tel",
    "wof:name":"Frischer Electronic Sa",
    "wof:placetype":"venue"
},
  "geometry": {"coordinates":[6.9303159714,46.992401123],"type":"Point"}
}