{
  "type": "Feature",
  "properties": {
    "iso:country":"CH",
    "sg:address":"2720 Tramelan. Postfach",
    "sg:city":"Tramlingen",
    "sg:orig_category":"Verwaltung von Immobilien",
    "sg:postcode":"2720",
    "sg:province":"Bern",
    "wof:name":"Soci\u00e9t\u00e9 Coop\u00e9rative Immobili\u00e8re La Verrerie",
    "wof:placetype":"venue"
},
  "geometry": {"coordinates":[6.9213700294,46.5899467468],"type":"Point"}
}