{
  "type": "Feature",
  "properties": {
    "iso:country":"CH",
    "sg:address":"Grossm\u00fcnsterplatz 7 8001 Z\u00fcrich. Postfach",
    "sg:city":"Z\u00fcrich",
    "sg:orig_category":"Detailhandel mit Getr\u00e4nken Grosshandel mit Wein U Spirituosen",
    "sg:phone":"+41 12518393",
    "sg:postcode":"8022",
    "sg:province":"Z\u00fcrich",
    "wof:name":"Midi Vins Sa",
    "wof:placetype":"venue"
},
  "geometry": {"coordinates":[8.5439367294,47.3697433472],"type":"Point"}
}