{
  "type": "Feature",
  "properties": {
    "iso:country":"CH",
    "sg:address":"Sonnhalderain 15 3250 Lyss. Postfach 220",
    "sg:city":"Lyss",
    "sg:orig_category":"Grosshandel mit chemischen Erzeugnissen",
    "sg:phone":"+41 32 387 89 22",
    "sg:postcode":"3250",
    "sg:province":"Bern",
    "wof:name":"Gerber Agro-handels Ag Fr\u00fcchte U. Gem\u00fcse; Handel, Import, Export Usw.",
    "wof:placetype":"venue"
},
  "geometry": {"coordinates":[7.3056030273,47.0804252625],"type":"Point"}
}