{
  "type": "Feature",
  "properties": {
    "iso:country":"CH",
    "sg:address":"Im Leimen 24",
    "sg:city":"F\u00fcllinsdorf",
    "sg:orig_category":"Gem\u00fcsebau",
    "sg:phone":"+41 61 901 31 31",
    "sg:postcode":"4414",
    "sg:province":"Basel-Landschaft",
    "wof:name":"Hans Eschbach Gem\u00fcsebau",
    "wof:placetype":"venue"
},
  "geometry": {"coordinates":[7.7283501625,47.520488739],"type":"Point"}
}