{
  "type": "Feature",
  "properties": {
    "iso:country":"CH",
    "sg:address":"Enggisteinstrasse 77",
    "sg:city":"Worb",
    "sg:orig_category":"Detailhandel mit Damenbekleidung",
    "sg:phone":"+41 31 839 98 88",
    "sg:postcode":"3076",
    "sg:province":"Bern",
    "wof:name":"Elvira Neukomm Second-hand-shop",
    "wof:placetype":"venue"
},
  "geometry": {"coordinates":[7.576014,46.927818],"type":"Point"}
}