{
  "type": "Feature",
  "properties": {
    "iso:country":"CH",
    "sg:address":"9477",
    "sg:city":"Tr\u00fcbbach",
    "sg:orig_category":"Gasth\u00f6fe/Gasth\u00e4user mit Restaurant HOTELS: MIT RESTAURANT",
    "sg:phone":"+41 71 377 12 15",
    "sg:postcode":"9477",
    "sg:province":"St. Gallen",
    "wof:name":"Landgasthof R\u00f6ssli",
    "wof:placetype":"venue"
},
  "geometry": {"coordinates":[9.1779050827,47.3179130554],"type":"Point"}
}