{
  "type": "Feature",
  "properties": {
    "iso:country":"CH",
    "sg:address":"Roosweg 7 5707 Seengen. Postfach",
    "sg:city":"Seengen",
    "sg:orig_category":"Interessenvertretungen",
    "sg:postcode":"5707",
    "sg:province":"Aargau",
    "wof:name":"Stiftung Kultur Landschaft Aargauer Seetal",
    "wof:placetype":"venue"
},
  "geometry": {"coordinates":[8.2089948654,47.3300247192],"type":"Point"}
}