{
  "type": "Feature",
  "properties": {
    "iso:country":"CH",
    "sg:address":"Toffenhohle 4",
    "sg:city":"Toffen",
    "sg:classifiers":[
        {
            "category":"Professional",
            "subcategory":"Engineering",
            "type":"Services"
        }
    ],
    "sg:phone":"+41 31 819 27 63",
    "sg:postcode":"3125",
    "sg:province":"Bern",
    "sg:tags":[
        "control",
        "instrumentation",
        "technology",
        "electronic"
    ],
    "wof:name":"Depro-electronic",
    "wof:placetype":"venue"
},
  "geometry": {"coordinates":[7.4899950027,46.8650627136],"type":"Point"}
}