{
  "type": "Feature",
  "properties": {
    "iso:country":"CH",
    "sg:address":"Grand-rue 85",
    "sg:city":"St-maurice",
    "sg:orig_category":"RESTAURANTS: TEA-ROOMS",
    "sg:postcode":"1890",
    "sg:province":"Valais",
    "wof:name":"Restaurant-pizzeria Ochsen, Prihoda Miroslav Und Stankovic Zoran",
    "wof:placetype":"venue"
},
  "geometry": {"coordinates":[7.5894289017,47.4921073914],"type":"Point"}
}