{
  "type": "Feature",
  "properties": {
    "iso:country":"CH",
    "sg:address":"Burgstrasse 16 3600 Thun. Postfach 338",
    "sg:city":"Thun",
    "sg:orig_category":"Detailhandel mit Radio U Fernsehger\u00e4ten Detailhandel mit elektrischen Haushalts-,Radio U Fernsehger\u00e4",
    "sg:phone":"+41 33 222 41 54",
    "sg:postcode":"3605",
    "wof:name":"Felix Alonso Radio-tv",
    "wof:placetype":"venue"
},
  "geometry": {"coordinates":[7.629650116,46.7612266541],"type":"Point"}
}