{
  "type": "Feature",
  "properties": {
    "iso:country":"CH",
    "sg:address":"General-wille-strasse 364",
    "sg:city":"Meilen",
    "sg:orig_category":"Unternehmensberatung",
    "sg:phone":"+41 19912626",
    "sg:postcode":"8706",
    "sg:province":"Z\u00fcrich",
    "wof:name":"Venezia Consulting",
    "wof:placetype":"venue"
},
  "geometry": {"coordinates":[8.6292448044,47.2720756531],"type":"Point"}
}