{
  "type": "Feature",
  "properties": {
    "iso:country":"CH",
    "sg:address":"Oberdorfstrasse 69",
    "sg:city":"Herisau",
    "sg:orig_category":"Fotografische Ateliers",
    "sg:phone":"+41 31 972 21 21",
    "sg:postcode":"9100",
    "sg:province":"Appenzell Ausserrhoden",
    "wof:name":"Toni Lutz Studio F\u00fcr Werbefotos",
    "wof:placetype":"venue"
},
  "geometry": {"coordinates":[7.4337940216,46.928855896],"type":"Point"}
}