{
  "type": "Feature",
  "properties": {
    "iso:country":"CH",
    "sg:address":"Alchenstorfstrasse 8",
    "sg:city":"Koppigen",
    "sg:orig_category":"Detailhandel mit Antiquit\u00e4ten Detailhandel mit Spielwaren",
    "sg:phone":"+41 34 413 10 52",
    "sg:postcode":"3425",
    "sg:province":"Bern",
    "wof:name":"Walter & Liesel Jakob Nostalgie Puppen",
    "wof:placetype":"venue"
},
  "geometry": {"coordinates":[7.616928,47.129612],"type":"Point"}
}