{
  "type": "Feature",
  "properties": {
    "iso:country":"CH",
    "sg:address":"Hauptstrasse 47",
    "sg:city":"Ermatingen",
    "sg:orig_category":"RESTAURANTS: TEA-ROOMS",
    "sg:phone":"+41 32 751 38 28",
    "sg:postcode":"8272",
    "sg:province":"Thurgau",
    "wof:name":"Fischer Eug\u00e8ne",
    "wof:placetype":"venue"
},
  "geometry": {"coordinates":[7.0642590523,47.0508918762],"type":"Point"}
}