{
  "type": "Feature",
  "properties": {
    "iso:country":"CH",
    "sg:address":"Talacker 41",
    "sg:city":"Z\u00fcrich",
    "sg:orig_category":"Non-Classified Establishments",
    "sg:postcode":"8001",
    "sg:province":"Z\u00fcrich",
    "wof:name":"Sc-soft & Ware Schena R.",
    "wof:placetype":"venue"
},
  "geometry": {"coordinates":[8.8593091965,47.2516746521],"type":"Point"}
}