{
  "type": "Feature",
  "properties": {
    "iso:country":"CH",
    "sg:address":"Thalerstrasse 31",
    "sg:city":"Rheineck",
    "sg:orig_category":"Herstellung von \u00d6fen U Brennern Verlegen von Fliesen U Platten",
    "sg:phone":"+41 71 888 21 70",
    "sg:postcode":"9424",
    "sg:province":"St. Gallen",
    "wof:name":"Wettler + Schwarz Ag",
    "wof:placetype":"venue"
},
  "geometry": {"coordinates":[9.5848922729,47.4668502808],"type":"Point"}
}