{
  "type": "Feature",
  "properties": {
    "iso:country":"CH",
    "sg:address":"Zaunackerstrasse 8 3113 Rubigen. Postfach 154",
    "sg:city":"Rubigen",
    "sg:orig_category":"Sportvereine Ski",
    "sg:phone":"+41 33 442 21 56",
    "sg:postcode":"3113",
    "sg:province":"Bern",
    "wof:name":"Skiclub Rubigen",
    "wof:placetype":"venue"
},
  "geometry": {"coordinates":[7.5389032364,46.9003334045],"type":"Point"}
}