{
  "type": "Feature",
  "properties": {
    "iso:country":"CH",
    "sg:address":"Rohrmattweg 6",
    "sg:city":"Sch\u00fcpfen",
    "sg:orig_category":"Herstellung von Metallkonstruktionen",
    "sg:phone":"+41 79 460 68 17",
    "sg:postcode":"3054",
    "sg:province":"Bern",
    "wof:name":"Kohler Metallbau",
    "wof:placetype":"venue"
},
  "geometry": {"coordinates":[7.3880500793,47.0426864624],"type":"Point"}
}