{
  "type": "Feature",
  "properties": {
    "iso:country":"CH",
    "sg:address":"Winkelriedstrasse 82 8203 Schaffhausen. Postfach",
    "sg:city":"Schaffhausen",
    "sg:orig_category":"Wasserversorgung",
    "sg:postcode":"8203",
    "sg:province":"Schaffhausen",
    "wof:name":"Cotwo Ag",
    "wof:placetype":"venue"
},
  "geometry": {"coordinates":[8.6585178375,47.6982688904],"type":"Point"}
}