{
  "type": "Feature",
  "properties": {
    "iso:country":"CH",
    "sg:address":"Petersgraben 27",
    "sg:city":"Basel",
    "sg:orig_category":"Wirtschafts- and Arbeitgeberverb\u00e4nde",
    "sg:phone":"+41 61 267 31 11",
    "sg:postcode":"4051",
    "sg:province":"Basel-Stadt",
    "wof:name":"Schweiz.musikforschende Ges. Herrn Dr.joseph Willimann",
    "wof:placetype":"venue"
},
  "geometry": {"coordinates":[7.5846509933,47.5593833923],"type":"Point"}
}