{
  "type": "Feature",
  "properties": {
    "iso:country":"CH",
    "sg:address":"Hirschenplatz 6",
    "sg:city":"Lyss",
    "sg:classifiers":[
        {
            "category":"Government",
            "subcategory":"Post Office",
            "type":"Public Place"
        }
    ],
    "sg:phone":"+41 32 385 13 10",
    "sg:postcode":"3250",
    "sg:province":"Bern",
    "sg:tags":[
        "caf\u00e9s",
        "tea-rooms"
    ],
    "wof:name":"Caf\u00e9-gelateria Piazza",
    "wof:placetype":"venue"
},
  "geometry": {"coordinates":[7.306306839,47.0742416382],"type":"Point"}
}