{
  "type": "Feature",
  "properties": {
    "iso:country":"CH",
    "sg:address":"Pfadackerstrasse 6",
    "sg:city":"Spreitenbach",
    "sg:classifiers":[
        {
            "category":"Professional",
            "subcategory":"Employment Agencies",
            "type":"Services"
        }
    ],
    "sg:phone":"+41 56 621 95 65",
    "sg:postcode":"8957",
    "sg:province":"Aargau",
    "sg:tags":[
        "personal",
        "u",
        "stellenvermittlung"
    ],
    "wof:name":"T + F Personalberatung Ag",
    "wof:placetype":"venue"
},
  "geometry": {"coordinates":[8.2621898651,47.3497200012],"type":"Point"}
}