{
  "type": "Feature",
  "properties": {
    "iso:country":"CH",
    "sg:address":"Riedstrasse 50a",
    "sg:city":"H\u00fcnibach",
    "sg:classifiers":[
        {
            "category":"Professional",
            "subcategory":"Engineering",
            "type":"Services"
        }
    ],
    "sg:phone":"+41 33 243 11 79",
    "sg:postcode":"3626",
    "sg:province":"Bern",
    "wof:name":"Ingenieurb\u00fcro F\u00fcr Maschinenbau",
    "wof:placetype":"venue"
},
  "geometry": {"coordinates":[7.675269,46.72868],"type":"Point"}
}