{
  "type": "Feature",
  "properties": {
    "iso:country":"CH",
    "sg:address":"Selib\u00fchlweg 8",
    "sg:city":"Worb",
    "sg:orig_category":"Verwaltung von Immobilien Wirtschaftspr\u00fcfung, Steuerberatung U Treuhand",
    "sg:phone":"+41 33 951 36 51",
    "sg:postcode":"3076",
    "sg:province":"Bern",
    "wof:name":"Implementus Treuhand Gmbh Treuhandb\u00fcro Usw.",
    "wof:placetype":"venue"
},
  "geometry": {"coordinates":[8.0316200256,46.7543945312],"type":"Point"}
}