{
  "type": "Feature",
  "properties": {
    "iso:country":"CH",
    "sg:address":"Breitenweg 8",
    "sg:city":"Oberhasli",
    "sg:orig_category":"Bauspenglerei Dachdeckerei",
    "sg:phone":"+41 18500705",
    "sg:postcode":"8156",
    "sg:province":"Z\u00fcrich",
    "wof:name":"Peter Bergamin Bauspengler",
    "wof:placetype":"venue"
},
  "geometry": {"coordinates":[8.500062,47.465511],"type":"Point"}
}