{
  "type": "Feature",
  "properties": {
    "iso:country":"CH",
    "sg:address":"Bielstrasse 77",
    "sg:city":"Grenchen",
    "sg:orig_category":"Institutionen f\u00fcr Behinderte Tagesheime f\u00fcr Behinderte, gesch\u00fctzte Werkst\u00e4tten",
    "sg:phone":"+41 32 652 51 34",
    "sg:postcode":"2540",
    "sg:province":"Solothurn",
    "wof:name":"Vebo Genossenschaft Solothurn. Eingliederungsst.f.behinderte",
    "wof:placetype":"venue"
},
  "geometry": {"coordinates":[7.3889169693,47.1894493103],"type":"Point"}
}