{
  "type": "Feature",
  "properties": {
    "iso:country":"CH",
    "sg:address":"Weststrasse 16",
    "sg:city":"Dietikon",
    "sg:orig_category":"Bauschreinerei",
    "sg:phone":"+41 79 411 94 83",
    "sg:postcode":"8953",
    "sg:province":"Z\u00fcrich",
    "wof:name":"Fridolin St\u00e4bler Schreinerei",
    "wof:placetype":"venue"
},
  "geometry": {"coordinates":[8.393576,47.403061],"type":"Point"}
}