{
  "type": "Feature",
  "properties": {
    "iso:country":"CH",
    "sg:address":"Bergstrasse 5",
    "sg:city":"Kreuzlingen",
    "sg:orig_category":"Herstellung von Pflanzenschutzmitteln U sonstigen agro- chemikalischen Erzeugnissen Herstellung von ",
    "sg:phone":"+41 79 607 27 48",
    "sg:postcode":"8280",
    "sg:province":"Thurgau",
    "wof:name":"Tybolin K. Althaus",
    "wof:placetype":"venue"
},
  "geometry": {"coordinates":[7.2493472099,47.1389007568],"type":"Point"}
}