{
  "type": "Feature",
  "properties": {
    "iso:country":"CH",
    "sg:address":"B\u00e4renloch",
    "sg:city":"Salez",
    "sg:orig_category":"Verarbeitung von Milch Verwertung von Milch",
    "sg:phone":"+41 41 497 27 50",
    "sg:postcode":"9465",
    "sg:province":"St. Gallen",
    "wof:name":"K\u00e4sereigenossenschaft Schachen",
    "wof:placetype":"venue"
},
  "geometry": {"coordinates":[8.1441202164,47.0363311768],"type":"Point"}
}