{
  "type": "Feature",
  "properties": {
    "iso:country":"CH",
    "sg:address":"Seestrasse 162",
    "sg:city":"Horgen",
    "sg:orig_category":"Vermittlung U Verwaltung von Immobilien Wirtschaftspr\u00fcfung, Steuerberatung U Treuhand",
    "sg:phone":"+41 17153373",
    "sg:postcode":"8810",
    "sg:province":"Z\u00fcrich",
    "wof:name":"Zimmermann Grob Immobilientreuhand",
    "wof:placetype":"venue"
},
  "geometry": {"coordinates":[8.546049118,47.3181304932],"type":"Point"}
}