{
  "type": "Feature",
  "properties": {
    "iso:country":"CH",
    "sg:address":"Rue Pr\u00e9fet Comte 4",
    "sg:city":"Court\u00e9telle",
    "sg:orig_category":"Sanit\u00e4r U Heizungsinstallation Sanit\u00e4rinstallation",
    "sg:postcode":"2852",
    "sg:province":"Jura",
    "wof:name":"Sanimann S\u00e0rl Grossiste Sanitaire",
    "wof:placetype":"venue"
},
  "geometry": {"coordinates":[7.3173742294,47.3416557312],"type":"Point"}
}