{
  "type": "Feature",
  "properties": {
    "iso:country":"CH",
    "sg:address":"Kreuzfeldstrasse 1",
    "sg:city":"Luterbach",
    "sg:orig_category":"Erschliessung von Grundst\u00fccken",
    "sg:postcode":"4542",
    "sg:province":"Solothurn",
    "wof:name":"Liberale Baugenossenschaft Poststrasse-ost",
    "wof:placetype":"venue"
},
  "geometry": {"coordinates":[7.5804448128,47.21251297],"type":"Point"}
}