{
  "type": "Feature",
  "properties": {
    "iso:country":"CH",
    "sg:address":"R\u00fctistrasse 6",
    "sg:city":"Steinen",
    "sg:orig_category":"Herstellung von Konstruktionsteilen, Fertigbauteilen U Ausbauelementen aus Holz",
    "sg:phone":"+41 41 832 11 49",
    "sg:postcode":"6422",
    "sg:province":"Schwyz",
    "wof:name":"Steiner & Camenzind, Schreinerei",
    "wof:placetype":"venue"
},
  "geometry": {"coordinates":[8.605381012,47.0496292114],"type":"Point"}
}