{
  "type": "Feature",
  "properties": {
    "iso:country":"CH",
    "sg:address":"Mostackerstrasse 5 4051 Basel. Postfach",
    "sg:city":"Basel",
    "sg:orig_category":"Druck ohne Zeitungsdruck",
    "sg:phone":"+41 61 486 73 73",
    "sg:postcode":"4051",
    "sg:province":"Basel-Stadt",
    "wof:name":"Gebr\u00fcder Strobel Ag, Buchdruckerei Und Verlag Druckerei. Druckerzeugnisse; Herst., Vertrieb Usw",
    "wof:placetype":"venue"
},
  "geometry": {"coordinates":[7.5823750496,47.5556983948],"type":"Point"}
}