{
  "type": "Feature",
  "properties": {
    "iso:country":"CH",
    "sg:address":"3926 Embd. Postfach",
    "sg:city":"Kalpetran",
    "sg:orig_category":"Elektrizit\u00e4tsversorgung",
    "sg:postcode":"3922",
    "sg:province":"Valais",
    "wof:name":"Genossenschaft F\u00fcr Stromversorgung Kalpetran Gsk",
    "wof:placetype":"venue"
},
  "geometry": {"coordinates":[7.8282060623,46.2169151306],"type":"Point"}
}