{
  "type": "Feature",
  "properties": {
    "iso:country":"CH",
    "sg:address":"Oberdorf",
    "sg:city":"Sufers",
    "sg:classifiers":[
        {
            "category":"Retail",
            "subcategory":"Driving School",
            "type":"Services"
        }
    ],
    "sg:phone":"+41 81 630 90 10",
    "sg:postcode":"7434",
    "sg:province":"Graubunden",
    "sg:tags":[
        "drive"
    ],
    "wof:name":"Rolf Gloor Engineering",
    "wof:placetype":"venue"
},
  "geometry": {"coordinates":[9.3666200638,46.5706214905],"type":"Point"}
}