{
  "type": "Feature",
  "properties": {
    "iso:country":"CH",
    "sg:address":"Tiers De Mart 4",
    "sg:city":"Chamoson",
    "sg:classifiers":[
        {
            "category":"Restaurant",
            "type":"Food & Drink"
        }
    ],
    "sg:phone":"+41 27 306 23 98",
    "sg:postcode":"1955",
    "sg:province":"Valais",
    "wof:name":"Restaurant Alpes",
    "wof:placetype":"venue"
},
  "geometry": {"coordinates":[7.2211580276,46.2002677917],"type":"Point"}
}