{
  "type": "Feature",
  "properties": {
    "iso:country":"CH",
    "sg:address":"Baarermatte",
    "sg:city":"Baar",
    "sg:orig_category":"Architektur U Ingenieurb\u00fcros",
    "sg:postcode":"6340",
    "sg:province":"Zug",
    "wof:name":"Architekturb\u00fcro Schiess + Partner",
    "wof:placetype":"venue"
},
  "geometry": {"coordinates":[8.5258,47.179569],"type":"Point"}
}