{
  "type": "Feature",
  "properties": {
    "addr:full":"H\u00f6henweg 15 Burgdorf Bern 3400",
    "addr:housenumber":"15",
    "addr:postcode":"3400",
    "addr:street":"Hoehenweg",
    "iso:country":"CH",
    "sg:address":"H\u00f6henweg 15",
    "sg:city":"Burgdorf",
    "sg:orig_category":"Architektur U Ingenieurb\u00fcros",
    "sg:phone":"+41 55 442 33 91",
    "sg:postcode":"3400",
    "sg:province":"Bern",
    "wof:name":"Replanco Architektur Ag",
    "wof:placetype":"venue"
},
  "geometry": {"coordinates":[8.853897,47.191139],"type":"Point"}
}