{
  "type": "Feature",
  "properties": {
    "iso:country":"CH",
    "sg:address":"Marktgasse 15",
    "sg:city":"Biel/bienne",
    "sg:orig_category":"Detailhandel mit Ton U Bildtr\u00e4gern Telecomshops",
    "sg:phone":"+41 32 322 39 68",
    "sg:postcode":"2502",
    "sg:province":"Bern",
    "wof:name":"The Phone House Sa Communication Centres",
    "wof:placetype":"venue"
},
  "geometry": {"coordinates":[7.2463822365,47.1401557922],"type":"Point"}
}