{
  "type": "Feature",
  "properties": {
    "iso:country":"CH",
    "sg:address":"Via Lucomagno",
    "sg:city":"Biasca",
    "sg:orig_category":"Erbringung von sonstigen Dienstleistungen f\u00fcr Unterhaltung, Erholung U Freizeit",
    "sg:postcode":"6710",
    "sg:province":"Ticino",
    "wof:name":"Agenzia A.t.s. Per Collocamento Di Musicisti E Cantanti Di Rodoni Artemio",
    "wof:placetype":"venue"
},
  "geometry": {"coordinates":[8.9673404694,46.3699150085],"type":"Point"}
}