{
  "type": "Feature",
  "properties": {
    "iso:country":"CH",
    "sg:address":"Sch\u00e4ferweg 16",
    "sg:city":"Basel",
    "sg:orig_category":"Handelsvermittlung U Grosshandel Herstellung von k\u00e4lte U lufttechnischen Erzeugnissen f\u00fcr gewerblich",
    "sg:phone":"+41 32 913 65 30",
    "sg:postcode":"4057",
    "sg:province":"Basel-Stadt",
    "wof:name":"Qla Quality Life Association S\u00e0rl",
    "wof:placetype":"venue"
},
  "geometry": {"coordinates":[6.8232607841,47.1018943787],"type":"Point"}
}