{
  "type": "Feature",
  "properties": {
    "iso:country":"CH",
    "sg:address":"Terreaux Rue Des 8",
    "sg:city":"Payerne",
    "sg:orig_category":"Grosshandel mit Getr\u00e4nken",
    "sg:postcode":"1530",
    "sg:province":"Vaud",
    "wof:name":"Danzeisen Jean-claude",
    "wof:placetype":"venue"
},
  "geometry": {"coordinates":[6.9400901794,46.8218994141],"type":"Point"}
}