{
  "type": "Feature",
  "properties": {
    "iso:country":"CH",
    "sg:address":"Waffenplatzstrasse 64",
    "sg:city":"Z\u00fcrich",
    "sg:orig_category":"Erbringung von Dienstleistungen f\u00fcr Unternehmen",
    "sg:phone":"+41 18252577",
    "sg:postcode":"8002",
    "sg:province":"Z\u00fcrich",
    "wof:name":"Interwega Internationaler Mahnservice Gmbh, Hamburg, Zweigniederlassung Z\u00fcrich",
    "wof:placetype":"venue"
},
  "geometry": {"coordinates":[8.5268802643,47.3575515747],"type":"Point"}
}