{
  "type": "Feature",
  "properties": {
    "iso:country":"CH",
    "sg:address":"Alte Strasse 2",
    "sg:city":"Adelboden",
    "sg:orig_category":"Allgemeiner Hochbau Bauschreinerei",
    "sg:phone":"+41 33 673 15 03",
    "sg:postcode":"3715",
    "sg:province":"Bern",
    "wof:name":"Pieren & Co Ag Bauunternehmung",
    "wof:placetype":"venue"
},
  "geometry": {"coordinates":[7.57285,46.496334],"type":"Point"}
}