{
  "type": "Feature",
  "properties": {
    "iso:country":"CH",
    "sg:address":"Via Nassa 40",
    "sg:city":"Lugano",
    "sg:orig_category":"Detailhandel mit Damenbekleidung",
    "sg:phone":"+41 91 923 41 31",
    "sg:postcode":"6900",
    "sg:province":"Ticino",
    "wof:name":"Beldona Ag",
    "wof:placetype":"venue"
},
  "geometry": {"coordinates":[8.949439,46.002102],"type":"Point"}
}