{
  "type": "Feature",
  "properties": {
    "iso:country":"CH",
    "sg:address":"Eisenwerkstrasse 47a",
    "sg:city":"Frauenfeld",
    "sg:orig_category":"Kauf U Verkauf von Immobilien auf eigene Rechnung",
    "sg:phone":"+41 52 720 47 66",
    "sg:postcode":"8500",
    "sg:province":"Thurgau",
    "wof:name":"Reality Keller & Sohn Ag",
    "wof:placetype":"venue"
},
  "geometry": {"coordinates":[8.8934736252,47.5604705811],"type":"Point"}
}