{
  "type": "Feature",
  "properties": {
    "iso:country":"CH",
    "sg:address":"Hauptstrasse 5",
    "sg:city":"Oensingen",
    "sg:orig_category":"Grosshandel mit chemischen Erzeugnissen",
    "sg:phone":"+41 34 493 34 54",
    "sg:postcode":"4702",
    "sg:province":"Solothurn",
    "wof:name":"Hans Scheidegger Hasma-k&s-klebstoffe",
    "wof:placetype":"venue"
},
  "geometry": {"coordinates":[7.896791935,46.8511428833],"type":"Point"}
}