{
  "type": "Feature",
  "properties": {
    "iso:country":"CH",
    "sg:address":"Luzernstrasse 9",
    "sg:city":"Zuchwil",
    "sg:orig_category":"Berufsbildende weiterf\u00fchrende Schulen",
    "sg:postcode":"4528",
    "sg:province":"Solothurn",
    "wof:name":"Neue Handelsschule Solothurn Gmbh",
    "wof:placetype":"venue"
},
  "geometry": {"coordinates":[7.548036,47.205299],"type":"Point"}
}