{
  "type": "Feature",
  "properties": {
    "iso:country":"CH",
    "sg:address":"1957",
    "sg:city":"Ardon",
    "sg:classifiers":[
        {
            "category":"Education",
            "subcategory":"Library",
            "type":"Public Place"
        }
    ],
    "sg:postcode":"1957",
    "sg:province":"Valais",
    "sg:tags":[
        "u",
        "bibliotheken",
        "archive"
    ],
    "wof:name":"Biblioth\u00e8que Populaire",
    "wof:placetype":"venue"
},
  "geometry": {"coordinates":[7.255545,46.208309],"type":"Point"}
}