{
  "type": "Feature",
  "properties": {
    "iso:country":"CH",
    "sg:address":"Lindenstrasse 27",
    "sg:city":"Allschwil",
    "sg:orig_category":"Grosshandel mit Software Grosshandel mit sonstigen Gebrauchs U Verbrauchsg\u00fctern",
    "sg:phone":"+41 61 483 91 38",
    "sg:postcode":"4123",
    "sg:province":"Basel-Landschaft",
    "wof:name":"Nebojsa Milisavljevic Milis Trade Business",
    "wof:placetype":"venue"
},
  "geometry": {"coordinates":[7.5609140396,47.5589981079],"type":"Point"}
}