{
  "type": "Feature",
  "properties": {
    "iso:country":"CH",
    "sg:address":"Hertizentrum 6",
    "sg:city":"Zug",
    "sg:orig_category":"Unclassifiable Establishments",
    "sg:postcode":"6300",
    "sg:province":"Zug",
    "wof:name":"Bl Finance Group Ag",
    "wof:placetype":"venue"
},
  "geometry": {"coordinates":[8.5061779022,47.1779022217],"type":"Point"}
}