{
  "type": "Feature",
  "properties": {
    "iso:country":"CH",
    "sg:address":"Chemin De Merdisel 27",
    "sg:city":"Satigny",
    "sg:orig_category":"G\u00fcterbef\u00f6rderung im Strassenverkehr",
    "sg:phone":"+41 22 753 15 52",
    "sg:postcode":"1242",
    "sg:province":"Gen\u00e8ve",
    "wof:name":"Serge Del\u00e8ze",
    "wof:placetype":"venue"
},
  "geometry": {"coordinates":[6.03586483,46.2125587463],"type":"Point"}
}