{
  "type": "Feature",
  "properties": {
    "iso:country":"CH",
    "sg:address":"Via Angelo Maspoli 21",
    "sg:city":"Mendrisio",
    "sg:orig_category":"Offsetdruck",
    "sg:phone":"+41 91 646 00 20",
    "sg:postcode":"6850",
    "sg:province":"Ticino",
    "wof:name":"Stamperia Della Frontiera Sa",
    "wof:placetype":"venue"
},
  "geometry": {"coordinates":[8.9784212112,45.8754234314],"type":"Point"}
}