{
  "type": "Feature",
  "properties": {
    "iso:country":"CH",
    "sg:address":"M\u00fcntschemiergasse 24",
    "sg:city":"Ins",
    "sg:orig_category":"Versicherungen Generalagenturen",
    "sg:phone":"+41 32 313 10 52",
    "sg:postcode":"3232",
    "sg:province":"Bern",
    "wof:name":"Die Mobiliar Versicherungen & Vorsorge",
    "wof:placetype":"venue"
},
  "geometry": {"coordinates":[7.1083340645,47.0049324036],"type":"Point"}
}