{
  "type": "Feature",
  "properties": {
    "iso:country":"CH",
    "sg:address":"6742",
    "sg:city":"Pollegio",
    "sg:orig_category":"Allgemeiner Hochbau Br\u00fccken U Tunnelbau",
    "sg:phone":"+41 62 836 97 36",
    "sg:postcode":"6742",
    "sg:province":"Ticino",
    "wof:name":"H\u00e4rdi & Fritschi Ag",
    "wof:placetype":"venue"
},
  "geometry": {"coordinates":[8.090554,47.386375],"type":"Point"}
}