{
  "type": "Feature",
  "properties": {
    "iso:country":"CH",
    "sg:address":"Gstaldenstrasse 35",
    "sg:city":"Horgen",
    "sg:orig_category":"Detailhandel mit M\u00f6beln U Haushaltsgegenst\u00e4nden",
    "sg:phone":"+41 17251044",
    "sg:postcode":"8810",
    "sg:province":"Z\u00fcrich",
    "wof:name":"Stuhl-import Deubelbeiss",
    "wof:placetype":"venue"
},
  "geometry": {"coordinates":[8.6048583984,47.2466659546],"type":"Point"}
}