{
  "type": "Feature",
  "properties": {
    "iso:country":"CH",
    "sg:address":"Breitfeldstrasse",
    "sg:city":"Worben",
    "sg:orig_category":"Vorschulen, Kinderg\u00e4rten",
    "sg:phone":"+41 32 384 23 95",
    "sg:postcode":"3252",
    "sg:province":"Bern",
    "wof:name":"Kindergarten",
    "wof:placetype":"venue"
},
  "geometry": {"coordinates":[7.2966551781,47.0997238159],"type":"Point"}
}