{
  "type": "Feature",
  "properties": {
    "iso:country":"CH",
    "sg:address":"Uetliberghalde 7",
    "sg:city":"Z\u00fcrich",
    "sg:orig_category":"Grosshandel mit Nahrungsmitteln, Getr\u00e4nken U Tabakwaren ohne ausgepr\u00e4gten Schwerpunkt Herstellung vo",
    "sg:phone":"+41 14615191",
    "sg:postcode":"8045",
    "sg:province":"Z\u00fcrich",
    "wof:name":"Jada Import Gmbh",
    "wof:placetype":"venue"
},
  "geometry": {"coordinates":[8.5087194443,47.3534431458],"type":"Point"}
}