{
  "type": "Feature",
  "properties": {
    "iso:country":"CH",
    "sg:address":"M\u00fchleweg 2",
    "sg:city":"Grossdietwil",
    "sg:orig_category":"Zimmerei, Dachdeckerei, Bauspenglerei U Abdichtung Zimmerei, Ingenieurholzbau",
    "sg:phone":"+41 62 927 11 85",
    "sg:postcode":"6146",
    "sg:province":"Luzern",
    "wof:name":"Sch\u00e4r W. Holzbau Ag",
    "wof:placetype":"venue"
},
  "geometry": {"coordinates":[7.8876171112,47.1691055298],"type":"Point"}
}