{
  "type": "Feature",
  "properties": {
    "iso:country":"CH",
    "sg:address":"Chemin Des Bains 1",
    "sg:city":"Pully",
    "sg:orig_category":"RESTAURANTS: TEA-ROOMS",
    "sg:phone":"+41 21 728 27 43",
    "sg:postcode":"1009",
    "sg:province":"Vaud",
    "wof:name":"De Francesco Aniello",
    "wof:placetype":"venue"
},
  "geometry": {"coordinates":[6.6653728485,46.5059280396],"type":"Point"}
}