{
  "type": "Feature",
  "properties": {
    "iso:country":"CH",
    "sg:address":"Englischgrusstrasse",
    "sg:city":"Brig",
    "sg:orig_category":"Verwaltung von Immobilien",
    "sg:phone":"+41 27 923 30 16",
    "sg:postcode":"3900",
    "sg:province":"Valais",
    "wof:name":"Saltimmo Gmbh",
    "wof:placetype":"venue"
},
  "geometry": {"coordinates":[7.9876461029,46.3158912659],"type":"Point"}
}