{
  "type": "Feature",
  "properties": {
    "iso:country":"CH",
    "sg:address":"Aspstrasse 59",
    "sg:city":"Seuzach",
    "sg:orig_category":"Bauingenieurb\u00fcros Hochbau Bauingenieurb\u00fcros allgemein",
    "sg:phone":"+41 52 320 00 80",
    "sg:postcode":"8472",
    "sg:province":"Z\u00fcrich",
    "wof:name":"Heierli Ag Ingenieurb\u00fcro",
    "wof:placetype":"venue"
},
  "geometry": {"coordinates":[8.699337,47.52549],"type":"Point"}
}