{
  "type": "Feature",
  "properties": {
    "iso:country":"CH",
    "sg:address":"Rue Adrien-lachenal 26",
    "sg:city":"Gen\u00e8ve",
    "sg:orig_category":"Instandhaltung U Reparatur von Automobilen Mechanische Werkst\u00e4tten",
    "sg:phone":"+41 22 735 47 66",
    "sg:postcode":"1207",
    "sg:province":"Gen\u00e8ve",
    "wof:name":"Garage S, Barr\u00e8s Jos\u00e9-maria.",
    "wof:placetype":"venue"
},
  "geometry": {"coordinates":[6.1562228203,46.1990737915],"type":"Point"}
}