{
  "type": "Feature",
  "properties": {
    "iso:country":"CH",
    "sg:address":"Corbi\u00e8res Rue De 29",
    "sg:city":"Bulle",
    "sg:orig_category":"Herstellung von Konstruktionsteilen, Fertigbauteilen U Ausbauelementen aus Holz",
    "sg:phone":"+41 61 961 05 18",
    "sg:postcode":"1630",
    "sg:province":"Fribourg",
    "wof:name":"Ml Locher Martin K\u00fcchen, B\u00e4dermontage Usw",
    "wof:placetype":"venue"
},
  "geometry": {"coordinates":[7.7193031311,47.391910553],"type":"Point"}
}