{
  "type": "Feature",
  "properties": {
    "iso:country":"CH",
    "sg:address":"Rossbergstrasse 5",
    "sg:city":"Steinen",
    "sg:classifiers":[
        {
            "category":"Restaurant",
            "type":"Food & Drink"
        }
    ],
    "sg:phone":"+41 41 832 11 19",
    "sg:postcode":"6422",
    "sg:province":"Schwyz",
    "wof:name":"Restaurant Hirschen",
    "wof:placetype":"venue"
},
  "geometry": {"coordinates":[8.6125736237,47.0503959656],"type":"Point"}
}