{
  "type": "Feature",
  "properties": {
    "iso:country":"CH",
    "sg:address":"3961",
    "sg:city":"St-luc",
    "sg:orig_category":"Landesverteidigung, Sozialversicherung \u00d6ffentliche Verwaltung",
    "sg:phone":"+41 27 475 15 39",
    "sg:postcode":"3961",
    "sg:province":"Valais",
    "wof:name":"Administration Communale Protection Civile",
    "wof:placetype":"venue"
},
  "geometry": {"coordinates":[7.5963401794,46.2207946777],"type":"Point"}
}