{
  "type": "Feature",
  "properties": {
    "iso:country":"CH",
    "sg:address":"1000 Lausanne Case Postale 599",
    "sg:city":"Lausanne",
    "sg:orig_category":"Interessenvertretungen U sonstige Vereinigungen",
    "sg:phone":"+41 21 620 56 50",
    "sg:postcode":"1001",
    "sg:province":"Vaud",
    "wof:name":"F\u00e9d\u00e9ration Suisse De P\u00e9tanque",
    "wof:placetype":"venue"
},
  "geometry": {"coordinates":[6.6876702309,46.559551239],"type":"Point"}
}