{
  "type": "Feature",
  "properties": {
    "iso:country":"CH",
    "sg:address":"Seestrasse 8",
    "sg:city":"Lauerz",
    "sg:orig_category":"Herstellung von sonstigen landwirtschaftlichen Maschinen",
    "sg:phone":"+41 41 811 84 43",
    "sg:postcode":"6424",
    "sg:province":"Schwyz",
    "wof:name":"Peter Troxler, Landmaschinen Und Kranservice",
    "wof:placetype":"venue"
},
  "geometry": {"coordinates":[8.5794248581,47.0352401733],"type":"Point"}
}