{
  "type": "Feature",
  "properties": {
    "iso:country":"CH",
    "sg:address":"Rue Place-d'armes 1",
    "sg:city":"Neuch\u00e2tel",
    "sg:orig_category":"Detailhandel mit M\u00f6beln Detailhandel mit M\u00f6beln U Haushaltsgegenst\u00e4nden",
    "sg:phone":"+41 61 721 33 03",
    "sg:postcode":"2000",
    "sg:province":"Neuch\u00e2tel",
    "wof:name":"Atelier Rideau H. Reimer",
    "wof:placetype":"venue"
},
  "geometry": {"coordinates":[7.5308589935,47.5035476685],"type":"Point"}
}