{
  "type": "Feature",
  "properties": {
    "iso:country":"CH",
    "sg:address":"Hauptstrasse 106",
    "sg:city":"Ziefen",
    "sg:orig_category":"Nationale Postdienste",
    "sg:phone":"+41 55 221 26 64",
    "sg:postcode":"4417",
    "sg:province":"Basel-Landschaft",
    "wof:name":"Die Schweizerische Post",
    "wof:placetype":"venue"
},
  "geometry": {"coordinates":[7.4126191139,47.0608825684],"type":"Point"}
}