{
  "type": "Feature",
  "properties": {
    "iso:country":"CH",
    "sg:address":"Aurorastrasse 91 8032 Z\u00fcrich. Postfach",
    "sg:city":"Neerach",
    "sg:orig_category":"Unternehmensberatung",
    "sg:phone":"+41 12513346",
    "sg:postcode":"8173",
    "sg:province":"Z\u00fcrich",
    "wof:name":"Abrell Hinterh\u00e4user Sgaravato Ag Unternehmensberatung, Bes. Bei Der Planung, Vorbereitung U. Ausf\u00fchrung Von Unternehmenszusammenschl\u00fcsse Usw",
    "wof:placetype":"venue"
},
  "geometry": {"coordinates":[8.5683937073,47.367893219],"type":"Point"}
}