{
  "type": "Feature",
  "properties": {
    "iso:country":"CH",
    "sg:address":"Bahnhofstrasse 11 6300 Zug. Postfach 953",
    "sg:city":"Zug",
    "sg:orig_category":"Advokaturb\u00fcros Notariate",
    "sg:phone":"+41 41 710 52 52",
    "sg:postcode":"6301",
    "sg:province":"Zug",
    "wof:name":"Dr.marco Weiss Advokatur-& Notariatsb\u00fcro",
    "wof:placetype":"venue"
},
  "geometry": {"coordinates":[8.515536,47.168819],"type":"Point"}
}