{
  "type": "Feature",
  "properties": {
    "iso:country":"CH",
    "sg:address":"Bahnhofstrasse 99",
    "sg:city":"M\u00f6hlin",
    "sg:orig_category":"Physiotherapie",
    "sg:phone":"+41 61 851 40 48",
    "sg:postcode":"4313",
    "sg:province":"Aargau",
    "wof:name":"Kurzentrum Rheinfelden Ag Physiotherapie",
    "wof:placetype":"venue"
},
  "geometry": {"coordinates":[7.8471951485,47.555015564],"type":"Point"}
}