{
  "type": "Feature",
  "properties": {
    "iso:country":"CH",
    "sg:address":"Neugasse 6",
    "sg:city":"Z\u00fcrich",
    "sg:classifiers":[
        {
            "category":"Cinema",
            "subcategory":"Movie Theater",
            "type":"Entertainment"
        }
    ],
    "sg:phone":"+41 14482070",
    "sg:postcode":"8005",
    "sg:province":"Z\u00fcrich",
    "sg:tags":[
        "radio",
        "videofilmherstellung",
        "fernsehanstalten",
        "u",
        "film"
    ],
    "wof:name":"Ava Scheiner Ag",
    "wof:placetype":"venue"
},
  "geometry": {"coordinates":[8.5320081711,47.381362915],"type":"Point"}
}