{
  "type": "Feature",
  "properties": {
    "iso:country":"CH",
    "sg:address":"Via Stazione",
    "sg:city":"Soazza",
    "sg:orig_category":"Allgemeiner Hoch U Tiefbau Strassenbau",
    "sg:phone":"+41 91 831 11 13",
    "sg:postcode":"6562",
    "sg:province":"Graubunden",
    "wof:name":"Impresa Zarro Sa",
    "wof:placetype":"venue"
},
  "geometry": {"coordinates":[9.222487,46.367683],"type":"Point"}
}