{
  "type": "Feature",
  "properties": {
    "iso:country":"CH",
    "sg:address":"Martin Route Antoine 4",
    "sg:city":"Vessy",
    "sg:orig_category":"Unclassifiable Establishments",
    "sg:postcode":"1234",
    "sg:province":"Gen\u00e8ve",
    "wof:name":"Savioz Martine",
    "wof:placetype":"venue"
},
  "geometry": {"coordinates":[6.1688117981,46.173866272],"type":"Point"}
}