{
  "type": "Feature",
  "properties": {
    "iso:country":"CH",
    "sg:address":"Sagenblickstrasse 31",
    "sg:city":"Ebikon",
    "sg:orig_category":"Handels-H\u00e4user U Gesellschaften",
    "sg:postcode":"6030",
    "sg:province":"Luzern",
    "wof:name":"Joma Ag",
    "wof:placetype":"venue"
},
  "geometry": {"coordinates":[8.3412542343,47.0732688904],"type":"Point"}
}