{
  "type": "Feature",
  "properties": {
    "addr:full":"Neuhardstrasse 28 Olten Solothurn 4600",
    "addr:housenumber":"28",
    "addr:postcode":"4600",
    "addr:street":"Neuhardstrasse",
    "iso:country":"CH",
    "sg:address":"Neuhardstrasse 28",
    "sg:city":"Olten",
    "sg:orig_category":"Bestattungswesen",
    "sg:phone":"+41 31 371 93 48",
    "sg:postcode":"4600",
    "sg:province":"Solothurn",
    "wof:name":"Bestattungsdienst Hedy Linder-walther Ag Vornahme U. Durchf\u00fchrung V. Bestattungs- U. Beerdigungsangelegenheiten Usw.",
    "wof:placetype":"venue"
},
  "geometry": {"coordinates":[7.432275,46.937939],"type":"Point"}
}