{
  "type": "Feature",
  "properties": {
    "iso:country":"CH",
    "sg:address":"Piazza Cioccaro 12",
    "sg:city":"Lugano",
    "sg:orig_category":"Unclassifiable Establishments",
    "sg:postcode":"6900",
    "sg:province":"Ticino",
    "wof:name":"Boutique Tattoo Cedrico Sa",
    "wof:placetype":"venue"
},
  "geometry": {"coordinates":[8.9497585297,46.0046157837],"type":"Point"}
}