{
  "type": "Feature",
  "properties": {
    "iso:country":"CH",
    "sg:address":"Via Cantonale 1",
    "sg:city":"Lugano",
    "sg:orig_category":"Unclassifiable Establishments",
    "sg:postcode":"6900",
    "sg:province":"Ticino",
    "wof:name":"Pim Partecipazioni Immobiliari E Mobiliari Sa",
    "wof:placetype":"venue"
},
  "geometry": {"coordinates":[8.9500703812,46.0066413879],"type":"Point"}
}