{
  "type": "Feature",
  "properties": {
    "iso:country":"CH",
    "sg:address":"Hirschengraben 46",
    "sg:city":"Z\u00fcrich",
    "sg:orig_category":"Primarschulen",
    "sg:phone":"+41 31 738 80 05",
    "sg:postcode":"8001",
    "sg:province":"Z\u00fcrich",
    "wof:name":"Primarschule Hirschhorn",
    "wof:placetype":"venue"
},
  "geometry": {"coordinates":[7.3771300316,46.7775154114],"type":"Point"}
}