{
  "type": "Feature",
  "properties": {
    "iso:country":"CH",
    "sg:address":"Sur-les-rochets 33",
    "sg:city":"Fontenais",
    "sg:orig_category":"Sportvereine Ski",
    "sg:phone":"+41 26 675 46 02",
    "sg:postcode":"2902",
    "sg:province":"Jura",
    "wof:name":"Ski-club Alaska Dompierre",
    "wof:placetype":"venue"
},
  "geometry": {"coordinates":[6.9854388237,46.8511314392],"type":"Point"}
}