{
  "type": "Feature",
  "properties": {
    "iso:country":"CH",
    "sg:address":"Flughafenstrasse 67 4056 Basel. Postfach",
    "sg:city":"Basel",
    "sg:orig_category":"Detailhandel mit Brot, Back U S\u00fcsswaren",
    "sg:phone":"+41 61 322 86 90",
    "sg:postcode":"4021",
    "wof:name":"Sutter Ag B\u00e4ckerei-konditorei",
    "wof:placetype":"venue"
},
  "geometry": {"coordinates":[7.569593,47.568928],"type":"Point"}
}