{
  "type": "Feature",
  "properties": {
    "iso:country":"CH",
    "sg:address":"3904",
    "sg:city":"Naters",
    "sg:orig_category":"Landw. Genossenschaften Viehzucht",
    "sg:postcode":"3904",
    "sg:province":"Valais",
    "wof:name":"Fleck-& Braunviehzucht- Genossenschaft Neftenbach",
    "wof:placetype":"venue"
},
  "geometry": {"coordinates":[8.6812343597,47.5417976379],"type":"Point"}
}