{
  "type": "Feature",
  "properties": {
    "iso:country":"CH",
    "sg:address":"Kaiserstuhlerstrasse 44",
    "sg:city":"Weiach",
    "sg:orig_category":"Detailhandel mit Waren verschiedener Art, Hauptrichtung Nahrungsmittel",
    "sg:phone":"+41 52 385 13 36",
    "sg:postcode":"8187",
    "sg:province":"Z\u00fcrich",
    "wof:name":"Landi Wila-turbenthal",
    "wof:placetype":"venue"
},
  "geometry": {"coordinates":[8.8457202911,47.4199676514],"type":"Point"}
}