{
  "type": "Feature",
  "properties": {
    "iso:country":"CH",
    "sg:address":"Les Petites-rames 5",
    "sg:city":"Fribourg",
    "sg:orig_category":"Sanit\u00e4r U Heizungsinstallation Sanit\u00e4r, Heizungs U L\u00fcftungsinstallation",
    "sg:phone":"+41 26 322 59 28",
    "sg:postcode":"1700",
    "sg:province":"Fribourg",
    "wof:name":"Riedo Clima Sa",
    "wof:placetype":"venue"
},
  "geometry": {"coordinates":[7.1602859497,46.8031005859],"type":"Point"}
}