{
  "type": "Feature",
  "properties": {
    "iso:country":"CH",
    "sg:address":"Friloweg 404",
    "sg:city":"Huttwil",
    "sg:classifiers":[
        {
            "category":"Shopping",
            "subcategory":"Clothing, Apparel, & Fashions",
            "type":"Retail Goods"
        }
    ],
    "sg:phone":"+41 62 962 11 19",
    "sg:postcode":"4950",
    "sg:province":"Bern",
    "sg:tags":[
        "textile",
        "clothing",
        "clothes"
    ],
    "wof:name":"Kurt Loosli Strickwarenfabrik Frilo",
    "wof:placetype":"venue"
},
  "geometry": {"coordinates":[7.836964,47.116291],"type":"Point"}
}