{
  "type": "Feature",
  "properties": {
    "iso:country":"CH",
    "sg:address":"Rue Peillonnex 19",
    "sg:city":"Ch\u00eane-bourg",
    "sg:orig_category":"Versicherungen Generalagenturen",
    "sg:phone":"+41 22 349 28 00",
    "sg:postcode":"1225",
    "sg:province":"Gen\u00e8ve",
    "wof:name":"Union Suisse Assurances Agence G\u00e9n\u00e9rale Ch\u00eane-th\u00f4nex",
    "wof:placetype":"venue"
},
  "geometry": {"coordinates":[6.1963682175,46.1948776245],"type":"Point"}
}