{
  "type": "Feature",
  "properties": {
    "iso:country":"CH",
    "sg:address":"Via Bagutti 22",
    "sg:city":"Lugano",
    "sg:orig_category":"Effekten U Warenterminb\u00f6rsen",
    "sg:phone":"+41 91 972 11 01",
    "sg:postcode":"6900",
    "sg:province":"Ticino",
    "wof:name":"Ita.ca Arredamenti Sagl",
    "wof:placetype":"venue"
},
  "geometry": {"coordinates":[8.9568910599,46.0160751343],"type":"Point"}
}