{
  "type": "Feature",
  "properties": {
    "iso:country":"CH",
    "sg:address":"Rue Micheli-du-crest 10 1200 Genf. Postfach",
    "sg:city":"Gen\u00e8ve",
    "sg:orig_category":"Herstellung von medizinischen U chirurgischen Ger\u00e4ten sowie orthop\u00e4dischen Vorrichtungen",
    "sg:postcode":"1201",
    "sg:province":"Gen\u00e8ve",
    "wof:name":"Bougantouche Et Cie",
    "wof:placetype":"venue"
},
  "geometry": {"coordinates":[6.1469168663,46.19506073],"type":"Point"}
}