{
  "type": "Feature",
  "properties": {
    "iso:country":"CH",
    "sg:address":"Bibernstrasse 18 3296 Arch. Postfach 23",
    "sg:city":"Arch",
    "sg:orig_category":"Instandhaltung U Reparatur von Automobilen",
    "sg:phone":"+41 32 679 37 77",
    "sg:postcode":"3296",
    "sg:province":"Bern",
    "wof:name":"Winiger Hans.",
    "wof:placetype":"venue"
},
  "geometry": {"coordinates":[7.4347710609,47.1670188904],"type":"Point"}
}