{
  "type": "Feature",
  "properties": {
    "iso:country":"CH",
    "sg:address":"Via Castausio 20",
    "sg:city":"Lugano",
    "sg:orig_category":"Technische B\u00fcros Heizung, L\u00fcftung, Klima Technische B\u00fcros Sanit\u00e4r",
    "sg:phone":"+41 91 923 79 81",
    "sg:postcode":"6900",
    "sg:province":"Ticino",
    "wof:name":"Diego Zocchetti Studio Tecnico",
    "wof:placetype":"venue"
},
  "geometry": {"coordinates":[8.9528121948,46.0152587891],"type":"Point"}
}