{
  "type": "Feature",
  "properties": {
    "iso:country":"CH",
    "sg:address":"Balierestrasse 29",
    "sg:city":"Frauenfeld",
    "sg:orig_category":"Erbringung von Dienstleistungen f\u00fcr Unternehmen",
    "sg:postcode":"8500",
    "sg:province":"Thurgau",
    "wof:name":"Beerli-rittmeyer Robert",
    "wof:placetype":"venue"
},
  "geometry": {"coordinates":[9.5426893234,47.4771995544],"type":"Point"}
}