{
  "type": "Feature",
  "properties": {
    "iso:country":"CH",
    "sg:address":"Gartenstrasse 1",
    "sg:city":"Gaiserwald",
    "sg:orig_category":"Grosshandel mit Textilien",
    "sg:phone":"+41 71 277 16 06",
    "sg:postcode":"9030",
    "sg:province":"St. Gallen",
    "wof:name":"Schlumpf Monika Textilhandel Und N\u00e4herei",
    "wof:placetype":"venue"
},
  "geometry": {"coordinates":[9.3491630554,47.4423713684],"type":"Point"}
}