{
  "type": "Feature",
  "properties": {
    "iso:country":"CH",
    "sg:address":"Eichwaldstrasse 15",
    "sg:city":"Zug",
    "sg:orig_category":"Sportvereine Turnen Vereine Damen",
    "sg:postcode":"6300",
    "sg:province":"Zug",
    "wof:name":"Damenriege Stammheimertal",
    "wof:placetype":"venue"
},
  "geometry": {"coordinates":[8.8264408112,47.6234130859],"type":"Point"}
}