{
  "type": "Feature",
  "properties": {
    "iso:country":"CH",
    "sg:address":"Nord Rue Du 5",
    "sg:city":"Martigny",
    "sg:orig_category":"Gesundheitswesen",
    "sg:phone":"+41 32 967 23 71",
    "sg:postcode":"1920",
    "sg:province":"Valais",
    "wof:name":"Fondation Des Laboratoires Des H\u00f4pitaux Du Canton De Neuch\u00e2tel (flhn)",
    "wof:placetype":"venue"
},
  "geometry": {"coordinates":[6.9015641212,47.04088974],"type":"Point"}
}