{
  "type": "Feature",
  "properties": {
    "iso:country":"CH",
    "sg:address":"Hundsiten / H\u00f6fenstrasse 8872 Weesen. Postfach 109",
    "sg:city":"Weesen",
    "sg:orig_category":"Energieversorgung",
    "sg:phone":"+41 55 616 50 30",
    "sg:postcode":"8872",
    "sg:province":"St. Gallen",
    "wof:name":"Soltec Ag Solar Und Pelletsysteme",
    "wof:placetype":"venue"
},
  "geometry": {"coordinates":[9.1016149521,47.1361846924],"type":"Point"}
}