{
  "type": "Feature",
  "properties": {
    "iso:country":"CH",
    "sg:address":"Im Schlat 477",
    "sg:city":"Unterstammheim",
    "sg:classifiers":[
        {
            "category":"Wholesale",
            "subcategory":"Farm Supplies",
            "type":"Manufacturing & Wholesale Goods"
        }
    ],
    "sg:phone":"+41 52 745 21 78",
    "sg:postcode":"8476",
    "sg:province":"Z\u00fcrich",
    "sg:tags":[
        "-",
        "machine",
        "equipment",
        "engineering",
        "machinery",
        "mechanical",
        "agriculture"
    ],
    "wof:name":"Brack Landmaschinen Ag",
    "wof:placetype":"venue"
},
  "geometry": {"coordinates":[8.790224,47.636818],"type":"Point"}
}