{
  "type": "Feature",
  "properties": {
    "iso:country":"CH",
    "sg:address":"Im Arbonerfeld 1.",
    "sg:city":"Arbon",
    "sg:orig_category":"Nahrungsmittel-Industrie: Rohstoffe",
    "sg:phone":"+41 71 446 56 64",
    "sg:postcode":"9320",
    "sg:province":"Thurgau",
    "wof:name":"Evo Egon V\u00f6lki",
    "wof:placetype":"venue"
},
  "geometry": {"coordinates":[9.421578,47.514385],"type":"Point"}
}