{
  "type": "Feature",
  "properties": {
    "iso:country":"CH",
    "sg:address":"Stauffenbach",
    "sg:city":"Ochlenberg",
    "sg:orig_category":"Detailhandel mit Milcherzeugnissen U Eiern Verarbeitung von Milch",
    "sg:phone":"+41 41 610 48 36",
    "sg:postcode":"3367",
    "sg:province":"Bern",
    "wof:name":"Karl Lussi K\u00e4serei",
    "wof:placetype":"venue"
},
  "geometry": {"coordinates":[8.3733491898,46.9565048218],"type":"Point"}
}