{
  "type": "Feature",
  "properties": {
    "iso:country":"CH",
    "sg:address":"Gartenstrasse 2",
    "sg:city":"Zug",
    "sg:orig_category":"Arztpraxen",
    "sg:phone":"+41 62 771 28 71",
    "sg:postcode":"6300",
    "sg:province":"Zug",
    "wof:name":"Dr.med.j\u00fcrg Steiner Spezialarzt Fmh",
    "wof:placetype":"venue"
},
  "geometry": {"coordinates":[8.182858,47.249382],"type":"Point"}
}