{
  "type": "Feature",
  "properties": {
    "iso:country":"CH",
    "sg:address":"Weissbadstrasse 14",
    "sg:city":"Appenzell",
    "sg:orig_category":"Unclassifiable Establishments",
    "sg:postcode":"9050",
    "sg:province":"Appenzell Innerhoden",
    "wof:name":"Gkk Kunststoff Holding Ag",
    "wof:placetype":"venue"
},
  "geometry": {"coordinates":[8.3124923706,46.9970169067],"type":"Point"}
}