{
  "type": "Feature",
  "properties": {
    "iso:country":"CH",
    "sg:address":"Alpenstrasse 4 6300 Zug. Postfach",
    "sg:city":"Zug",
    "sg:orig_category":"Softwareentwicklung U beratung Sonstige mit der Informatik verbundene T\u00e4tigkeiten",
    "sg:phone":"+41 41 710 27 77",
    "sg:postcode":"6304",
    "sg:province":"Zug",
    "wof:name":"Key-line Ag",
    "wof:placetype":"venue"
},
  "geometry": {"coordinates":[8.5139045715,47.1710357666],"type":"Point"}
}