{
  "type": "Feature",
  "properties": {
    "iso:country":"CH",
    "sg:address":"Route De Pr\u00e9verenges 12",
    "sg:city":"Denges",
    "sg:orig_category":"Instandhaltung U Reparatur von Automobilen",
    "sg:phone":"+41 21 802 16 54",
    "sg:postcode":"1026",
    "sg:province":"Vaud",
    "wof:name":"Garage Burnier Pierre-alain Sa",
    "wof:placetype":"venue"
},
  "geometry": {"coordinates":[6.5349411964,46.5245933533],"type":"Point"}
}