{
  "type": "Feature",
  "properties": {
    "iso:country":"CH",
    "sg:address":"In Der Sch\u00fcbleten 5",
    "sg:city":"Diepflingen",
    "sg:orig_category":"Allgemeiner Hoch U Tiefbau",
    "sg:phone":"+41 61 971 81 93",
    "sg:postcode":"4442",
    "sg:province":"Basel-Landschaft",
    "wof:name":"Merz Jakob Tiefbau Ag",
    "wof:placetype":"venue"
},
  "geometry": {"coordinates":[7.841884,47.446846],"type":"Point"}
}