{
  "type": "Feature",
  "properties": {
    "addr:full":"3600 Thun Bern 3600",
    "addr:postcode":"3600;3600",
    "iso:country":"CH",
    "sg:address":"3600",
    "sg:city":"Thun",
    "sg:orig_category":"Arbeitnehmerverb\u00e4nde",
    "sg:postcode":"3600",
    "sg:province":"Bern",
    "wof:name":"Ptt-union Sekt.berner-oberland",
    "wof:placetype":"venue"
},
  "geometry": {"coordinates":[7.62173,46.751041],"type":"Point"}
}