{
  "type": "Feature",
  "properties": {
    "iso:country":"CH",
    "sg:address":"Hof\u00e4cherstrasse 13b",
    "sg:city":"Wettswil",
    "sg:orig_category":"Non-Classified Establishments",
    "sg:postcode":"8907",
    "sg:province":"Z\u00fcrich",
    "wof:name":"G. Neubacher Engineering",
    "wof:placetype":"venue"
},
  "geometry": {"coordinates":[8.4732637405,47.3359642029],"type":"Point"}
}