{
  "type": "Feature",
  "properties": {
    "addr:full":"Ibelweg 18c Zug Zug 6300",
    "addr:housenumber":"18c",
    "addr:postcode":"6300",
    "addr:street":"Ibelweg;Zug",
    "iso:country":"CH",
    "sg:address":"Ibelweg 18c",
    "sg:city":"Zug",
    "sg:classifiers":[
        {
            "category":"Bars & Pubs",
            "subcategory":"Oxygen Bar",
            "type":"Food & Drink"
        }
    ],
    "sg:phone":"+41 41 766 48 00",
    "sg:postcode":"6300",
    "sg:province":"Zug",
    "sg:tags":[
        "copy",
        "cd"
    ],
    "wof:name":"Consol Office",
    "wof:placetype":"venue"
},
  "geometry": {"coordinates":[8.524916,47.181999],"type":"Point"}
}