{
  "type": "Feature",
  "properties": {
    "iso:country":"CH",
    "sg:address":"Schulhausstrasse 5",
    "sg:city":"Pfaffnau",
    "sg:orig_category":"Erschliessung von Grundst\u00fccken",
    "sg:postcode":"6264",
    "sg:province":"Luzern",
    "wof:name":"Wohnbaugenossenschaft Pfaffnau",
    "wof:placetype":"venue"
},
  "geometry": {"coordinates":[7.8999509811,47.2285842896],"type":"Point"}
}