{
  "type": "Feature",
  "properties": {
    "iso:country":"CH",
    "sg:address":"Av. Belv\u00e9d\u00e8re 1 2023 Gorgier. Postfach",
    "sg:city":"Chez-le-bart",
    "sg:orig_category":"Grosshandel mit Getr\u00e4nken",
    "sg:phone":"+41 32 835 23 40",
    "sg:postcode":"2025",
    "sg:province":"Neuch\u00e2tel",
    "wof:name":"Hertig Jean-pierre",
    "wof:placetype":"venue"
},
  "geometry": {"coordinates":[6.7964739799,46.9131355286],"type":"Point"}
}