{
  "type": "Feature",
  "properties": {
    "iso:country":"CH",
    "sg:address":"Poststrasse 7050 Arosa. Postfach 90",
    "sg:city":"Arosa",
    "sg:orig_category":"Reiseb\u00fcros U Reiseveranstalter",
    "sg:postcode":"7050",
    "sg:province":"Graubunden",
    "wof:name":"Arosa Tourismus",
    "wof:placetype":"venue"
},
  "geometry": {"coordinates":[9.6651620865,46.7756080627],"type":"Point"}
}