{
  "type": "Feature",
  "properties": {
    "iso:country":"CH",
    "sg:address":"Blattenmoosstrasse 18",
    "sg:city":"Littau",
    "sg:orig_category":"Betrieb von Taxis",
    "sg:phone":"+41 41 250 70 70",
    "sg:postcode":"6014",
    "sg:province":"Luzern",
    "wof:name":"Taxi Schwanen-airport",
    "wof:placetype":"venue"
},
  "geometry": {"coordinates":[8.271433,47.049873],"type":"Point"}
}