{
  "type": "Feature",
  "properties": {
    "iso:country":"CH",
    "sg:address":"Unterwerkstrasse 6",
    "sg:city":"Zweidlen",
    "sg:orig_category":"Sanit\u00e4r, Heizungs U L\u00fcftungsinstallation Sanit\u00e4rinstallation",
    "sg:phone":"+41 18671749",
    "sg:postcode":"8192",
    "sg:province":"Z\u00fcrich",
    "wof:name":"Keiser Hugo Ag",
    "wof:placetype":"venue"
},
  "geometry": {"coordinates":[8.5024900436,47.55884552],"type":"Point"}
}