{
  "type": "Feature",
  "properties": {
    "iso:country":"CH",
    "sg:address":"Bilchen Eggerstanden",
    "sg:city":"Appenzell",
    "sg:orig_category":"D\u00e4mmung gegen K\u00e4lte, W\u00e4rme, Schall U Ersch\u00fctterung Grosshandel mit lebenden Tieren",
    "sg:phone":"+41 71 787 16 43",
    "sg:postcode":"9050",
    "sg:province":"Appenzell Innerhoden",
    "wof:name":"R\u00e4ss Emil",
    "wof:placetype":"venue"
},
  "geometry": {"coordinates":[9.4076833725,47.3314361572],"type":"Point"}
}