{
  "type": "Feature",
  "properties": {
    "iso:country":"CH",
    "sg:address":"Rue De Varemb\u00e9 3",
    "sg:city":"Gen\u00e8ve",
    "sg:orig_category":"Interessenvertretungen U sonstige Vereinigungen Internationale Organisationen mit Beh\u00f6rdecharakter",
    "sg:phone":"+41 21 310 47 47",
    "sg:postcode":"1202",
    "sg:province":"Gen\u00e8ve",
    "wof:name":"F\u00e9d.equestre Internationale",
    "wof:placetype":"venue"
},
  "geometry": {"coordinates":[6.6414737701,46.5184822083],"type":"Point"}
}