{
  "type": "Feature",
  "properties": {
    "iso:country":"CH",
    "sg:address":"Chlingenstrasse 2",
    "sg:city":"Baar",
    "sg:orig_category":"Wirtschafts- and Arbeitgeberverb\u00e4nde",
    "sg:phone":"+41 41 790 22 19",
    "sg:postcode":"6340",
    "sg:province":"Zug",
    "wof:name":"Zuger Elektro-verband",
    "wof:placetype":"venue"
},
  "geometry": {"coordinates":[8.5342063904,47.2006759644],"type":"Point"}
}