{
  "type": "Feature",
  "properties": {
    "iso:country":"CH",
    "sg:address":"Winzerstrasse 16",
    "sg:city":"Dietikon",
    "sg:orig_category":"Sportvereine Wassersport Schwimmen",
    "sg:postcode":"8953",
    "sg:province":"Z\u00fcrich",
    "wof:name":"Cercle Des Nageurs",
    "wof:placetype":"venue"
},
  "geometry": {"coordinates":[6.2390799522,46.382358551],"type":"Point"}
}