{
  "type": "Feature",
  "properties": {
    "iso:country":"CH",
    "sg:address":"Rue Des Gorges 20 2738 Court. Postfach",
    "sg:city":"Court",
    "sg:orig_category":"Unclassifiable Establishments",
    "sg:postcode":"2738",
    "sg:province":"Bern",
    "wof:name":"Hostpoint Gmbh Dienstleistungen Im Bereich Der Information Technology, Bes. Vermieten Von Servern",
    "wof:placetype":"venue"
},
  "geometry": {"coordinates":[8.8142623901,47.226524353],"type":"Point"}
}