{
  "type": "Feature",
  "properties": {
    "iso:country":"CH",
    "sg:address":"Via Barazzo 10",
    "sg:city":"Gordola",
    "sg:orig_category":"Vermietung U Verpachtung von eigenen Immobilien",
    "sg:postcode":"6596",
    "sg:province":"Ticino",
    "wof:name":"Essagra Sa",
    "wof:placetype":"venue"
},
  "geometry": {"coordinates":[8.8605222702,46.1843566895],"type":"Point"}
}