{
  "type": "Feature",
  "properties": {
    "iso:country":"CH",
    "sg:address":"Boulevard Helv\u00e9tique 31bis",
    "sg:city":"Gen\u00e8ve",
    "sg:orig_category":"Grosshandel mit festen Brennstoffen U Mineral\u00f6lerzeugnissen",
    "sg:phone":"+41 22 735 68 22",
    "sg:postcode":"1207",
    "sg:province":"Gen\u00e8ve",
    "wof:name":"Socap Sa",
    "wof:placetype":"venue"
},
  "geometry": {"coordinates":[6.1548538208,46.2021942139],"type":"Point"}
}