{
  "type": "Feature",
  "properties": {
    "iso:country":"CH",
    "sg:address":"Champ Devant 107",
    "sg:city":"Corserey",
    "sg:orig_category":"Elektroinstallation",
    "sg:phone":"+41 26 470 10 55",
    "sg:postcode":"1747",
    "sg:province":"Fribourg",
    "wof:name":"Jean-marc Ding Installations \u00e9lectriques",
    "wof:placetype":"venue"
},
  "geometry": {"coordinates":[6.9962639809,46.7718048096],"type":"Point"}
}