{
  "type": "Feature",
  "properties": {
    "iso:country":"CH",
    "sg:address":"B\u00e4ckerstrasse 2",
    "sg:city":"Sch\u00f6nenwerd",
    "sg:classifiers":[
        {
            "category":"Travel",
            "subcategory":"Hotels & Motels",
            "type":"Entertainment"
        }
    ],
    "sg:phone":"+41 62 849 12 68",
    "sg:postcode":"5012",
    "sg:province":"Solothurn",
    "sg:tags":[
        "hotels",
        "mit",
        "restaurant"
    ],
    "wof:name":"Hotel Im Winkel",
    "wof:placetype":"venue"
},
  "geometry": {"coordinates":[8.0019302368,47.3698577881],"type":"Point"}
}