{
  "type": "Feature",
  "properties": {
    "iso:country":"CH",
    "sg:address":"H\u00f6chistrasse 16",
    "sg:city":"Uster",
    "sg:orig_category":"Informatikdienste Softwareentwicklung U beratung",
    "sg:phone":"+41 19405266",
    "sg:postcode":"8610",
    "sg:province":"Z\u00fcrich",
    "wof:name":"New Information Gmbh",
    "wof:placetype":"venue"
},
  "geometry": {"coordinates":[8.7333059311,47.3476867676],"type":"Point"}
}