{
  "type": "Feature",
  "properties": {
    "iso:country":"CH",
    "sg:address":"Bernastrasse 4",
    "sg:city":"Interlaken",
    "sg:orig_category":"Architektur U Ingenieurb\u00fcros",
    "sg:phone":"+41 33 821 09 81",
    "sg:postcode":"3800",
    "sg:province":"Bern",
    "wof:name":"Blatter Architekten Ag",
    "wof:placetype":"venue"
},
  "geometry": {"coordinates":[7.852718,46.682076],"type":"Point"}
}