{
  "type": "Feature",
  "properties": {
    "iso:country":"CH",
    "sg:address":"Freiestrasse 5 8406 Winterthur. Postfach 1196",
    "sg:city":"Winterthur",
    "sg:orig_category":"Allgemeiner Hoch U Tiefbau Allgemeiner Hochbau",
    "sg:phone":"+41 17618616",
    "sg:postcode":"8401",
    "sg:province":"Z\u00fcrich",
    "wof:name":"Baucal Ag Hoch-& Tiefbau",
    "wof:placetype":"venue"
},
  "geometry": {"coordinates":[8.452138,47.281013],"type":"Point"}
}