{
  "type": "Feature",
  "properties": {
    "iso:country":"CH",
    "sg:address":"Brand 132",
    "sg:city":"Untereggen",
    "sg:orig_category":"Grosshandel mit chemischen Erzeugnissen Grosshandel mit elektrischen Haushaltsger\u00e4ten",
    "sg:phone":"+41 71 860 02 45",
    "sg:postcode":"9033",
    "sg:province":"St. Gallen",
    "wof:name":"Sorma Ag Reinigungsmaschinen",
    "wof:placetype":"venue"
},
  "geometry": {"coordinates":[9.4543199539,47.4586143494],"type":"Point"}
}