{
  "type": "Feature",
  "properties": {
    "iso:country":"CH",
    "sg:address":"Hauptgasse 13",
    "sg:city":"Murten",
    "sg:orig_category":"Grossbanken",
    "sg:phone":"+41 844 800 844",
    "sg:postcode":"3280",
    "sg:province":"Fribourg",
    "wof:name":"Credit Suisse",
    "wof:placetype":"venue"
},
  "geometry": {"coordinates":[7.5891728401,47.4928321838],"type":"Point"}
}