{
  "type": "Feature",
  "properties": {
    "iso:country":"CH",
    "sg:address":"Dubsstr. 33 8000 Z\u00fcrich. Postfach",
    "sg:city":"Z\u00fcrich",
    "sg:orig_category":"Grosshandel mit Milch, Milcherzeugnissen, Eiern, Speise\u00f6len U Nahrungsfetten",
    "sg:phone":"+41 14620978",
    "sg:postcode":"8023",
    "sg:province":"Z\u00fcrich",
    "wof:name":"Eier Meyer & Co Eier, Eierprodukte; Handel",
    "wof:placetype":"venue"
},
  "geometry": {"coordinates":[8.5217695236,47.3672294617],"type":"Point"}
}