{
  "type": "Feature",
  "properties": {
    "iso:country":"CH",
    "sg:address":"Winznauerstrasse 101",
    "sg:city":"Trimbach",
    "sg:orig_category":"Detailhandel mit M\u00f6beln U Haushaltsgegenst\u00e4nden Grosshandel mit M\u00f6beln, Wohnbedarf, Teppichen U Bode",
    "sg:phone":"+41 62 293 10 23",
    "sg:postcode":"4632",
    "sg:province":"Solothurn",
    "wof:name":"Schibli W. Ag Schweizerm\u00f6bel-zentrum",
    "wof:placetype":"venue"
},
  "geometry": {"coordinates":[7.9082899094,47.3664016724],"type":"Point"}
}