{
  "type": "Feature",
  "properties": {
    "iso:country":"CH",
    "sg:address":"Route De Villars 21",
    "sg:city":"Freiburg",
    "sg:orig_category":"Detailhandel mit Fleisch U Fleischwaren",
    "sg:phone":"+41 26 424 43 24",
    "sg:postcode":"1700",
    "sg:province":"Fribourg",
    "wof:name":"Boucherie Jean-claude Gabriel",
    "wof:placetype":"venue"
},
  "geometry": {"coordinates":[7.1431231499,46.8010826111],"type":"Point"}
}