{
  "type": "Feature",
  "properties": {
    "iso:country":"CH",
    "sg:address":"Talstrasse 49",
    "sg:city":"G\u00e4chlingen",
    "sg:orig_category":"Allgemeiner Hoch U Tiefbau Hoch U Tiefbau",
    "sg:postcode":"8214",
    "sg:province":"Schaffhausen",
    "wof:name":"M\u00fcller, Ueli",
    "wof:placetype":"venue"
},
  "geometry": {"coordinates":[7.681037,46.610157],"type":"Point"}
}