{
  "type": "Feature",
  "properties": {
    "addr:full":"Obachstrasse 10 Solothurn Solothurn 4500",
    "addr:housenumber":"10",
    "addr:postcode":"4500",
    "addr:street":"Obachstrasse",
    "iso:country":"CH",
    "sg:address":"Obachstrasse 10",
    "sg:city":"Solothurn",
    "sg:orig_category":"Allgemeiner Hoch U Tiefbau Bauschreinerei",
    "sg:phone":"+41 32 623 12 12",
    "sg:postcode":"4500",
    "sg:province":"Solothurn",
    "wof:name":"Schenk + Cie Ag",
    "wof:placetype":"venue"
},
  "geometry": {"coordinates":[7.53235,47.205379],"type":"Point"}
}