{
  "type": "Feature",
  "properties": {
    "iso:country":"CH",
    "sg:address":"3920",
    "sg:city":"Zermatt",
    "sg:orig_category":"Grosshandel mit Nahrungsmitteln, Getr\u00e4nken U Tabakwaren ohne ausgepr\u00e4gten Schwerpunkt",
    "sg:phone":"+41 27 952 24 71",
    "sg:postcode":"3920",
    "sg:province":"Valais",
    "wof:name":"Konsumverband Vispertal",
    "wof:placetype":"venue"
},
  "geometry": {"coordinates":[7.8920350075,46.2011413574],"type":"Point"}
}