{
  "type": "Feature",
  "properties": {
    "iso:country":"CH",
    "sg:address":"Rue Du Pont Levis 7",
    "sg:city":"St-prex",
    "sg:orig_category":"Bauschreinerei Zimmerei, Dachdeckerei, Bauspenglerei U Abdichtung",
    "sg:phone":"+41 21 806 10 66",
    "sg:postcode":"1162",
    "sg:province":"Vaud",
    "wof:name":"Dessaux Roger",
    "wof:placetype":"venue"
},
  "geometry": {"coordinates":[6.459433,46.480217],"type":"Point"}
}