{
  "type": "Feature",
  "properties": {
    "iso:country":"CH",
    "sg:address":"G\u00f6sgerstrasse 79",
    "sg:city":"Niedererlinsbach",
    "sg:orig_category":"Sonstige mit der Informatik verbundene T\u00e4tigkeiten",
    "sg:phone":"+41 62 844 47 57",
    "sg:postcode":"5015",
    "sg:province":"Solothurn",
    "wof:name":"Pc Schule Lion & Lion's Software Inhaberin Shah-wuillemin Charlotte",
    "wof:placetype":"venue"
},
  "geometry": {"coordinates":[8.0077857971,47.3906822205],"type":"Point"}
}