{
  "type": "Feature",
  "properties": {
    "addr:full":"Hauptgasse 25 Olten Solothurn 4600",
    "addr:housenumber":"25",
    "addr:postcode":"4600",
    "addr:street":"Hauptgasse",
    "iso:country":"CH",
    "sg:address":"Hauptgasse 25",
    "sg:city":"Olten",
    "sg:orig_category":"Detailhandel mit Bekleidung Detailhandel mit Damenbekleidung",
    "sg:phone":"+41 62 212 82 11",
    "sg:postcode":"4600",
    "sg:province":"Solothurn",
    "wof:name":"Underground Ag Jeans & Mode",
    "wof:placetype":"venue"
},
  "geometry": {"coordinates":[7.903528,47.349846],"type":"Point"}
}