{
  "type": "Feature",
  "properties": {
    "iso:country":"CH",
    "sg:address":"Rue Des Boudines 1",
    "sg:city":"Meyrin",
    "sg:orig_category":"Fachdetailhandel in Verkaufsr\u00e4umen",
    "sg:phone":"+41 22 782 73 94",
    "sg:postcode":"1217",
    "sg:province":"Gen\u00e8ve",
    "wof:name":"Lodigiani Luciano",
    "wof:placetype":"venue"
},
  "geometry": {"coordinates":[6.0800981522,46.2334098816],"type":"Point"}
}