{
  "type": "Feature",
  "properties": {
    "iso:country":"CH",
    "sg:address":"Bergstrasse 6",
    "sg:city":"Sch\u00f6fflisdorf",
    "sg:orig_category":"Vorschulen, Kinderg\u00e4rten",
    "sg:phone":"+41 18560070",
    "sg:postcode":"8165",
    "sg:province":"Z\u00fcrich",
    "wof:name":"Kindergarten",
    "wof:placetype":"venue"
},
  "geometry": {"coordinates":[8.4124193192,47.5018882751],"type":"Point"}
}