{
  "type": "Feature",
  "properties": {
    "iso:country":"CH",
    "sg:address":"Avenue Des Ecoles 11",
    "sg:city":"Sierre",
    "sg:orig_category":"Detailhandel mit Fleisch U Fleischwaren",
    "sg:postcode":"3960",
    "sg:province":"Valais",
    "wof:name":"Cina Kurt",
    "wof:placetype":"venue"
},
  "geometry": {"coordinates":[7.5363149643,46.2949142456],"type":"Point"}
}