{
  "type": "Feature",
  "properties": {
    "iso:country":"CH",
    "sg:address":"Rue Du Lac 9",
    "sg:city":"Lausanne",
    "sg:orig_category":"Malerei",
    "sg:phone":"+41 21 616 79 23",
    "sg:postcode":"1007",
    "sg:province":"Vaud",
    "wof:name":"Espace-peinture",
    "wof:placetype":"venue"
},
  "geometry": {"coordinates":[6.6261968613,46.5076065063],"type":"Point"}
}