{
  "type": "Feature",
  "properties": {
    "addr:full":"Dynamostrasse 9 Baden Aargau 5400",
    "addr:housenumber":"9",
    "addr:postcode":"5400",
    "addr:street":"Dynamostrasse",
    "iso:country":"CH",
    "sg:address":"Dynamostrasse 9",
    "sg:city":"Baden",
    "sg:orig_category":"Allgemeiner Hoch U Tiefbau Strassenbau",
    "sg:phone":"+41 56 221 50 23",
    "sg:postcode":"5400",
    "sg:province":"Aargau",
    "wof:name":"M\u00e4der Ag Bauunternehmen",
    "wof:placetype":"venue"
},
  "geometry": {"coordinates":[8.305646,47.476669],"type":"Point"}
}