{
  "type": "Feature",
  "properties": {
    "iso:country":"CH",
    "sg:address":"Sperberweg 11 8500 Frauenfeld. Postfach",
    "sg:city":"Frauenfeld",
    "sg:orig_category":"Sonstiger Grosshandel",
    "sg:phone":"+41 52 720 96 79",
    "sg:postcode":"8500",
    "sg:province":"Thurgau",
    "wof:name":"Wirth Isabelle Warenhandel",
    "wof:placetype":"venue"
},
  "geometry": {"coordinates":[8.9041967392,47.5465278625],"type":"Point"}
}