{
  "type": "Feature",
  "properties": {
    "iso:country":"CH",
    "sg:address":"Herrengasse 9",
    "sg:city":"Balsthal",
    "sg:orig_category":"Detailhandel mit Schuhen Detailhandel mit Schuhen U Lederwaren",
    "sg:phone":"+41 62 391 31 24",
    "sg:postcode":"4710",
    "sg:province":"Solothurn",
    "wof:name":"Nasso Schuh Ag Schuh-& Adidas-shop",
    "wof:placetype":"venue"
},
  "geometry": {"coordinates":[7.6962919235,47.3160438538],"type":"Point"}
}