{
  "type": "Feature",
  "properties": {
    "iso:country":"CH",
    "sg:address":"Alte Landstrasse",
    "sg:city":"Steckborn",
    "sg:orig_category":"Vermittlung von Immobilien Verwaltung von Immobilien",
    "sg:phone":"+41 52 761 31 05",
    "sg:postcode":"8266",
    "sg:province":"Thurgau",
    "wof:name":"Bauer Immobilien Ag",
    "wof:placetype":"venue"
},
  "geometry": {"coordinates":[8.9897689819,47.6678276062],"type":"Point"}
}