{
  "type": "Feature",
  "properties": {
    "addr:full":"Bachstrasse 56 Mels St. Gallen 8887",
    "addr:housenumber":"56",
    "addr:postcode":"8887",
    "addr:street":"Bachstrasse",
    "iso:country":"CH",
    "sg:address":"Bachstrasse 56",
    "sg:city":"Mels",
    "sg:orig_category":"Betrieb von Taxis",
    "sg:phone":"+41 79 355 02 31",
    "sg:postcode":"8887",
    "sg:province":"St. Gallen",
    "wof:name":"Busunternehmen Sperandio Roger",
    "wof:placetype":"venue"
},
  "geometry": {"coordinates":[9.41698,47.050709],"type":"Point"}
}