{
  "type": "Feature",
  "properties": {
    "iso:country":"CH",
    "sg:address":"Rathaus 7430 Thusis. Postfach 180",
    "sg:city":"Thusis",
    "sg:orig_category":"F\u00fcrsorge\u00e4mter",
    "sg:phone":"+41 79 405 96 74",
    "sg:postcode":"7430",
    "sg:province":"Graubunden",
    "wof:name":"Kreisamt Thusis",
    "wof:placetype":"venue"
},
  "geometry": {"coordinates":[9.4371910095,46.6935539246],"type":"Point"}
}