{
  "type": "Feature",
  "properties": {
    "iso:country":"CH",
    "sg:address":"Burg 106",
    "sg:city":"Rheineck",
    "sg:orig_category":"Handels-H\u00e4user U Gesellschaften",
    "sg:phone":"+41 71 888 29 08",
    "sg:postcode":"9424",
    "sg:province":"St. Gallen",
    "wof:name":"Ibh Beteiligungs & Handels Ag",
    "wof:placetype":"venue"
},
  "geometry": {"coordinates":[9.5805807114,47.46326828],"type":"Point"}
}