{
  "type": "Feature",
  "properties": {
    "iso:country":"CH",
    "sg:address":"M\u00f6slere",
    "sg:city":"Etzelkofen",
    "sg:orig_category":"Ger\u00fcstbau Stukkateurgewerbe, Gipserei U Verputzerei",
    "sg:phone":"+41 34 445 80 01",
    "sg:postcode":"3306",
    "sg:province":"Bern",
    "wof:name":"Vetroma Ag Maler-& Gipsergesch\u00e4ft",
    "wof:placetype":"venue"
},
  "geometry": {"coordinates":[7.568983078,47.0876655579],"type":"Point"}
}