{
  "type": "Feature",
  "properties": {
    "iso:country":"CH",
    "sg:address":"8468",
    "sg:city":"Waltalingen",
    "sg:orig_category":"Verwertung von Milch",
    "sg:postcode":"8468",
    "sg:province":"Z\u00fcrich",
    "wof:name":"Milchgenossenschaft Guntalingen",
    "wof:placetype":"venue"
},
  "geometry": {"coordinates":[8.7788095474,47.6224937439],"type":"Point"}
}