{
  "type": "Feature",
  "properties": {
    "addr:full":"Au 151 9107 Urn\u00e4sch. Postfach Urn\u00e4sch Appenzell Ausserrhoden 9107",
    "addr:housenumber":"151",
    "addr:postcode":"9107;9107",
    "addr:street":"Au;Postfach;Ausserrhoden",
    "iso:country":"CH",
    "sg:address":"Au 151 9107 Urn\u00e4sch. Postfach",
    "sg:city":"Urn\u00e4sch",
    "sg:orig_category":"Alters U Pflegeheime Wohnheime",
    "sg:phone":"+41 71 364 18 59",
    "sg:postcode":"9107",
    "sg:province":"Appenzell Ausserrhoden",
    "wof:name":"Alters Und Betreuungsheim Au Ag",
    "wof:placetype":"venue"
},
  "geometry": {"coordinates":[9.28357,47.317451],"type":"Point"}
}