{
  "type": "Feature",
  "properties": {
    "iso:country":"CH",
    "sg:address":"Dorfmatt-zentrum",
    "sg:city":"Rotkreuz",
    "sg:orig_category":"Landesverteidigung, Sozialversicherung \u00d6ffentliche Verwaltung",
    "sg:phone":"+41 41 790 21 33",
    "sg:postcode":"6343",
    "sg:province":"Zug",
    "wof:name":"Zivilschutzstelle Risch",
    "wof:placetype":"venue"
},
  "geometry": {"coordinates":[8.4312238693,47.1412391663],"type":"Point"}
}