{
  "type": "Feature",
  "properties": {
    "iso:country":"CH",
    "sg:address":"Georg Kempf-strasse 11",
    "sg:city":"Z\u00fcrich",
    "sg:orig_category":"Interessenvertretungen",
    "sg:postcode":"8046",
    "sg:province":"Z\u00fcrich",
    "wof:name":"Koreanische Fliegender Adler Hap Ki Do Vereinigung (schweiz)",
    "wof:placetype":"venue"
},
  "geometry": {"coordinates":[8.4978084564,47.4211463928],"type":"Point"}
}