{
  "type": "Feature",
  "properties": {
    "iso:country":"CH",
    "sg:address":"Mattenstrasse 13",
    "sg:city":"Aegerten",
    "sg:orig_category":"Herstellung von Reiseartikeln, Leder U Sattlerwaren",
    "sg:postcode":"2558",
    "sg:province":"Bern",
    "wof:name":"Andrew J. Saddlery",
    "wof:placetype":"venue"
},
  "geometry": {"coordinates":[7.4042019844,47.1321258545],"type":"Point"}
}