{
  "type": "Feature",
  "properties": {
    "iso:country":"CH",
    "sg:address":"Poststrasse 15",
    "sg:city":"Zug",
    "sg:orig_category":"Fachdetailhandel in Verkaufsr\u00e4umen",
    "sg:postcode":"6300",
    "sg:province":"Zug",
    "wof:name":"Partridge Fine Arts Ag",
    "wof:placetype":"venue"
},
  "geometry": {"coordinates":[8.5161523819,47.1690673828],"type":"Point"}
}