{
  "type": "Feature",
  "properties": {
    "iso:country":"CH",
    "sg:address":"R\u00f6sslistrasse 11",
    "sg:city":"Erlen",
    "sg:orig_category":"Herstellung von Metallkonstruktionen Stahl U Leichtmetallbau",
    "sg:phone":"+41 32 373 52 67",
    "sg:postcode":"8586",
    "sg:province":"Thurgau",
    "wof:name":"Numatec Ag",
    "wof:placetype":"venue"
},
  "geometry": {"coordinates":[7.2683320045,47.1211471558],"type":"Point"}
}