{
  "type": "Feature",
  "properties": {
    "iso:country":"CH",
    "sg:address":"Lindengasse 7",
    "sg:city":"Br\u00fcttelen",
    "sg:orig_category":"Gemeindeverwaltungen",
    "sg:phone":"+41 32 313 15 20",
    "sg:postcode":"2578",
    "wof:name":"Gemeindeverwaltung Br\u00fcttelen",
    "wof:placetype":"venue"
},
  "geometry": {"coordinates":[7.1471409798,47.0227355957],"type":"Point"}
}