{
  "type": "Feature",
  "properties": {
    "iso:country":"CH",
    "sg:address":"Chemin De L'ancien-p\u00e9age 4 1290 Versoix Case Postale 267",
    "sg:city":"Versoix",
    "sg:orig_category":"Architekturb\u00fcros",
    "sg:phone":"+41 22 755 20 65",
    "sg:postcode":"1290",
    "sg:province":"Gen\u00e8ve",
    "wof:name":"Claude Lehmann Bureau D'architecture",
    "wof:placetype":"venue"
},
  "geometry": {"coordinates":[6.167765,46.275059],"type":"Point"}
}