{
  "type": "Feature",
  "properties": {
    "iso:country":"CH",
    "sg:address":"Rietwisstrasse 2a 9100 Herisau. Postfach",
    "sg:city":"Herisau",
    "sg:orig_category":"Herstellung von Tanks U Sammelbeh\u00e4ltern aus Metall Reinigungsgewerbe",
    "sg:phone":"+41 71 351 33 90",
    "sg:postcode":"9102",
    "sg:province":"Appenzell Ausserrhoden",
    "wof:name":"Andreas Allemann",
    "wof:placetype":"venue"
},
  "geometry": {"coordinates":[9.2638635635,47.3973846436],"type":"Point"}
}