{
  "type": "Feature",
  "properties": {
    "iso:country":"CH",
    "sg:address":"Kaspar-koppstrasse 39",
    "sg:city":"Ebikon",
    "sg:orig_category":"Satzherstellung U Reproduktion",
    "sg:postcode":"6030",
    "sg:province":"Luzern",
    "wof:name":"Herbert B\u00e4chli Bild + Text",
    "wof:placetype":"venue"
},
  "geometry": {"coordinates":[9.2330951691,47.5481987],"type":"Point"}
}