{
  "type": "Feature",
  "properties": {
    "iso:country":"CH",
    "sg:address":"Rue Du Vingt-trois-juin 4",
    "sg:city":"Porrentruy",
    "sg:orig_category":"Detailhandel mit Uhren U Schmuck Fachdetailhandel in Verkaufsr\u00e4umen",
    "sg:phone":"+41 32 466 13 36",
    "sg:postcode":"2900",
    "sg:province":"Jura",
    "wof:name":"R\u00e9fouss Sa, Horlogerie, Bijouterie",
    "wof:placetype":"venue"
},
  "geometry": {"coordinates":[7.0760197639,47.4169807434],"type":"Point"}
}