{
  "type": "Feature",
  "properties": {
    "iso:country":"CH",
    "sg:address":"Hauptgasse 31 6130 Willisau. Postfach",
    "sg:city":"Willisau",
    "sg:orig_category":"Detailhandel mit B\u00fcchern, Zeitungen, Schreib U Papeteriewaren",
    "sg:postcode":"6130",
    "sg:province":"Luzern",
    "wof:name":"Imhof Papeterie Und Buchhandlung",
    "wof:placetype":"venue"
},
  "geometry": {"coordinates":[7.98987,47.120281],"type":"Point"}
}