{
  "type": "Feature",
  "properties": {
    "iso:country":"CH",
    "sg:address":"Rue Faller 4",
    "sg:city":"Gen\u00e8ve",
    "sg:orig_category":"Vermittlung von Immobilien",
    "sg:phone":"+41 22 344 64 33",
    "sg:postcode":"1202",
    "sg:province":"Gen\u00e8ve",
    "wof:name":"Monique Piachaud Agence Immobili\u00e8re",
    "wof:placetype":"venue"
},
  "geometry": {"coordinates":[6.1306300163,46.2115287781],"type":"Point"}
}