{
  "type": "Feature",
  "properties": {
    "iso:country":"CH",
    "sg:address":"Herrengasse 25a",
    "sg:city":"Lyss",
    "sg:orig_category":"Herstellung von keramischen Haushaltswaren U Ziergegenst\u00e4nden",
    "sg:phone":"+41 32 386 74 46",
    "sg:postcode":"3250",
    "sg:province":"Bern",
    "wof:name":"Katharina Stegmann T\u00f6pferei",
    "wof:placetype":"venue"
},
  "geometry": {"coordinates":[7.3073868752,47.0705108643],"type":"Point"}
}