{
  "type": "Feature",
  "properties": {
    "iso:country":"CH",
    "sg:address":"Pr\u00e9vost-martin Rue 23 1205 Gen\u00e8ve. Postfach",
    "sg:city":"Gen\u00e8ve",
    "sg:orig_category":"Herstellung von Duft U K\u00f6rperpflegemitteln",
    "sg:postcode":"1205",
    "sg:province":"Gen\u00e8ve",
    "wof:name":"Soci\u00e9t\u00e9 De Distribution De Cosm\u00e9tiques Naturels, Maisonneuve J. & M.",
    "wof:placetype":"venue"
},
  "geometry": {"coordinates":[6.1458940506,46.1946678162],"type":"Point"}
}