{
  "type": "Feature",
  "properties": {
    "iso:country":"CH",
    "sg:address":"6218",
    "sg:city":"Ettiswil",
    "sg:orig_category":"Detailhandel mit Waren verschiedener Art, Hauptrichtung Nahrungsmittel",
    "sg:postcode":"6218",
    "sg:province":"Luzern",
    "wof:name":"Landwirtschaftliche Genossenschaft Finsterhennen",
    "wof:placetype":"venue"
},
  "geometry": {"coordinates":[7.1840701103,47.0295181274],"type":"Point"}
}