{
  "type": "Feature",
  "properties": {
    "addr:full":"Avenue De Champel 45 Gen\u00e8ve Gen\u00e8ve 1206",
    "addr:housenumber":"45",
    "addr:postcode":"1206",
    "addr:street":"Avenue De Champel",
    "iso:country":"CH",
    "sg:address":"Avenue De Champel 45",
    "sg:city":"Gen\u00e8ve",
    "sg:orig_category":"Arztpraxen",
    "sg:phone":"+41 22 347 00 07",
    "sg:postcode":"1206",
    "sg:province":"Gen\u00e8ve",
    "wof:name":"Dr M\u00e9d. Mihailo Lazovic M\u00e9decin Sp\u00e9cialiste Fmh",
    "wof:placetype":"venue"
},
  "geometry": {"coordinates":[6.153173,46.192467],"type":"Point"}
}