{
  "type": "Feature",
  "properties": {
    "iso:country":"CH",
    "sg:address":"5432 Neuenhof. Postfach 86",
    "sg:city":"Neuenhof",
    "sg:orig_category":"Maler U Glasergewerbe Malerei",
    "sg:phone":"+41 56 406 21 20",
    "sg:postcode":"5432",
    "sg:province":"Aargau",
    "wof:name":"Hochstrasser Oskar Ag",
    "wof:placetype":"venue"
},
  "geometry": {"coordinates":[8.3268165588,47.4499435425],"type":"Point"}
}