{
  "type": "Feature",
  "properties": {
    "iso:country":"CH",
    "sg:address":"Breitenrainstrasse 27",
    "sg:city":"Bern",
    "sg:orig_category":"Werbevermittlung Werbung",
    "sg:phone":"+41 31 388 83 83",
    "sg:postcode":"3013",
    "sg:province":"Bern",
    "wof:name":"Impuls Tbwa Ag",
    "wof:placetype":"venue"
},
  "geometry": {"coordinates":[7.4514322281,46.9574775696],"type":"Point"}
}