{
  "type": "Feature",
  "properties": {
    "iso:country":"CH",
    "sg:address":"6260",
    "sg:city":"Reiden",
    "sg:orig_category":"Primarschulen",
    "sg:postcode":"6260",
    "sg:province":"Luzern",
    "wof:name":"Primarschule Johanniter",
    "wof:placetype":"venue"
},
  "geometry": {"coordinates":[7.971282959,47.2432365417],"type":"Point"}
}