{
  "type": "Feature",
  "properties": {
    "iso:country":"CH",
    "sg:address":"Dr\u00f4ne 1965 Savi\u00e8se Case Postale 28",
    "sg:city":"Chandolin-savi\u00e8se",
    "sg:orig_category":"Erdbewegungsarbeiten Hoch U Tiefbau",
    "sg:phone":"+41 27 395 28 65",
    "sg:postcode":"1965",
    "sg:province":"Valais",
    "wof:name":"Terco Sa Terrassements Et Constructions",
    "wof:placetype":"venue"
},
  "geometry": {"coordinates":[7.3610739708,46.2553024292],"type":"Point"}
}