{
  "type": "Feature",
  "properties": {
    "iso:country":"CH",
    "sg:address":"Buhaldeweg 2",
    "sg:city":"Suhr",
    "sg:orig_category":"Sonstige pers\u00f6nliche Dienstleistungen",
    "sg:postcode":"5034",
    "sg:province":"Aargau",
    "wof:name":"Amsler & Co",
    "wof:placetype":"venue"
},
  "geometry": {"coordinates":[8.0866737366,47.3689994812],"type":"Point"}
}