{
  "type": "Feature",
  "properties": {
    "iso:country":"CH",
    "sg:address":"Binzstrasse 18",
    "sg:city":"Z\u00fcrich",
    "sg:orig_category":"Informatikdienste",
    "sg:phone":"+41 878 889 111",
    "sg:postcode":"8045",
    "sg:province":"Z\u00fcrich",
    "wof:name":"Genesis Communication Ag Gesch\u00e4ftsstelle",
    "wof:placetype":"venue"
},
  "geometry": {"coordinates":[8.5150213242,47.3627510071],"type":"Point"}
}