{
  "type": "Feature",
  "properties": {
    "iso:country":"CH",
    "sg:address":"Avenue Adrien-jeandin 37",
    "sg:city":"Th\u00f4nex",
    "sg:classifiers":[
        {
            "category":"Restaurant",
            "type":"Food & Drink"
        }
    ],
    "sg:phone":"+41 22 349 79 00",
    "sg:postcode":"1226",
    "sg:province":"Gen\u00e8ve",
    "wof:name":"Brasserie La Terrasse",
    "wof:placetype":"venue"
},
  "geometry": {"coordinates":[6.2005171776,46.1896781921],"type":"Point"}
}