{
  "type": "Feature",
  "properties": {
    "iso:country":"CH",
    "sg:address":"Langensandweg 1 6005 Luzern. Postfach",
    "sg:city":"Luzern",
    "sg:orig_category":"Softwareentwicklung U beratung",
    "sg:phone":"+41 41 496 03 46",
    "sg:postcode":"6005",
    "sg:province":"Luzern",
    "wof:name":"Burri Informatik",
    "wof:placetype":"venue"
},
  "geometry": {"coordinates":[8.3109407425,47.0444946289],"type":"Point"}
}