{
  "type": "Feature",
  "properties": {
    "iso:country":"CH",
    "sg:address":"Franz Zelgerstrasse 4",
    "sg:city":"Rothenburg",
    "sg:orig_category":"Architektur U Ingenieurb\u00fcros",
    "sg:postcode":"6023",
    "sg:province":"Luzern",
    "wof:name":"Riedi Thomas Immobilien Ag",
    "wof:placetype":"venue"
},
  "geometry": {"coordinates":[8.271385,47.094566],"type":"Point"}
}