{
  "type": "Feature",
  "properties": {
    "iso:country":"CH",
    "sg:address":"Route De St-cergue 308",
    "sg:city":"Nyon",
    "sg:orig_category":"Instandhaltung U Reparatur von Automobilen",
    "sg:phone":"+41 22 361 82 63",
    "sg:postcode":"1260",
    "sg:province":"Vaud",
    "wof:name":"John Chambaz Garage De L'asse",
    "wof:placetype":"venue"
},
  "geometry": {"coordinates":[6.2258372307,46.3941383362],"type":"Point"}
}