{
  "type": "Feature",
  "properties": {
    "iso:country":"CH",
    "sg:address":"Route De Berne 1",
    "sg:city":"Lausanne",
    "sg:orig_category":"Detailhandel mit Tabakwaren",
    "sg:phone":"+41 32 968 41 48",
    "sg:postcode":"1010",
    "sg:province":"Vaud",
    "wof:name":"Claudio Paltenghi Au Br\u00e9silien Mag.de Tabacs",
    "wof:placetype":"venue"
},
  "geometry": {"coordinates":[6.8316130638,47.1031990051],"type":"Point"}
}