{
  "type": "Feature",
  "properties": {
    "iso:country":"CH",
    "sg:address":"Augsterstrasse 35",
    "sg:city":"Pratteln",
    "sg:orig_category":"Veterin\u00e4rwesen",
    "sg:phone":"+41 61 811 35 83",
    "sg:postcode":"4133",
    "sg:province":"Basel-Landschaft",
    "wof:name":"Stiftung Sos F\u00fcr Tiere, Tierambulanz",
    "wof:placetype":"venue"
},
  "geometry": {"coordinates":[7.7117810249,47.5322990417],"type":"Point"}
}