{
  "type": "Feature",
  "properties": {
    "iso:country":"CH",
    "sg:address":"Unterer Rheinweg 26",
    "sg:city":"Basel",
    "sg:orig_category":"Kultur\u00e4mter",
    "sg:phone":"+41 61 267 66 25",
    "sg:postcode":"4058",
    "sg:province":"Basel-Stadt",
    "wof:name":"Basler Denkmalpflege",
    "wof:placetype":"venue"
},
  "geometry": {"coordinates":[7.5889348984,47.5629577637],"type":"Point"}
}