{
  "type": "Feature",
  "properties": {
    "iso:country":"CH",
    "sg:address":"Rue Centrale",
    "sg:city":"Dor\u00e9naz",
    "sg:orig_category":"Detailhandel mit Blumen U Pflanzen",
    "sg:phone":"+41 26 912 34 34",
    "sg:postcode":"1905",
    "sg:province":"Valais",
    "wof:name":"Anne-flore",
    "wof:placetype":"venue"
},
  "geometry": {"coordinates":[7.057696,46.618862],"type":"Point"}
}