{
  "type": "Feature",
  "properties": {
    "iso:country":"CH",
    "sg:address":"B\u00fchlwiesenstrasse 5 8309 N\u00fcrensdorf. Postfach",
    "sg:city":"N\u00fcrensdorf",
    "sg:orig_category":"Instandhaltung U Reparatur von Automobilen",
    "sg:phone":"+41 56 611 05 20",
    "sg:postcode":"8309",
    "sg:province":"Z\u00fcrich",
    "wof:name":"Garage Breitschmid Ag",
    "wof:placetype":"venue"
},
  "geometry": {"coordinates":[8.2749481201,47.3452758789],"type":"Point"}
}