{
  "type": "Feature",
  "properties": {
    "iso:country":"CH",
    "sg:address":"Route Du Coteau 15",
    "sg:city":"Villars-sur-gl\u00e2ne",
    "sg:orig_category":"Grosshandel mit Holz U Baustoffen",
    "sg:phone":"+41 26 401 07 84",
    "sg:postcode":"1752",
    "sg:province":"Fribourg",
    "wof:name":"Louis Corpataux Carrelages Et Rev\u00eatements S.\u00e0.r.l.",
    "wof:placetype":"venue"
},
  "geometry": {"coordinates":[7.1062679291,46.7934341431],"type":"Point"}
}