{
  "type": "Feature",
  "properties": {
    "iso:country":"CH",
    "sg:address":"Route De L'a\u00e9roport 33 1215 Gen\u00e8ve Case Postale 437 1215 Gen\u00e8ve",
    "sg:city":"D\u00e9p\u00f4t",
    "sg:orig_category":"Buchverlag Verlagsgewerbe",
    "sg:phone":"+41 22 788 27 88",
    "sg:postcode":"15",
    "wof:name":"Aerospace Media Publishing Sa",
    "wof:placetype":"venue"
},
  "geometry": {"coordinates":[6.111199,46.23275],"type":"Point"}
}