{
  "type": "Feature",
  "properties": {
    "iso:country":"CH",
    "sg:address":"B\u00fcrenstrasse 9",
    "sg:city":"Dotzigen",
    "sg:classifiers":[
        {
            "category":"Arena",
            "subcategory":"Bull Ring",
            "type":"Entertainment"
        }
    ],
    "sg:phone":"+41 32 351 41 44",
    "sg:postcode":"3293",
    "sg:province":"Bern",
    "sg:tags":[
        "band",
        "blade",
        "saw",
        "wood"
    ],
    "wof:name":"Walther S\u00e4genfabrikation",
    "wof:placetype":"venue"
},
  "geometry": {"coordinates":[7.341835,47.122299],"type":"Point"}
}