{
  "type": "Feature",
  "properties": {
    "iso:country":"CH",
    "sg:address":"Klarastrasse 30",
    "sg:city":"Olten",
    "sg:orig_category":"Tierarztpraxis",
    "sg:phone":"+41 62 296 77 77",
    "sg:postcode":"4600",
    "sg:province":"Solothurn",
    "wof:name":"Dr. Med. Vet. Bruno Fink Tierarzt",
    "wof:placetype":"venue"
},
  "geometry": {"coordinates":[7.9125180244,47.3504676819],"type":"Point"}
}