{
  "type": "Feature",
  "properties": {
    "iso:country":"CH",
    "sg:address":"Enzenb\u00fchlstrasse 99",
    "sg:city":"Flawil",
    "sg:orig_category":"Erschliessung von Grundst\u00fccken",
    "sg:postcode":"9230",
    "sg:province":"St. Gallen",
    "wof:name":"Genossenschaft Oekorama",
    "wof:placetype":"venue"
},
  "geometry": {"coordinates":[9.1767578125,47.417175293],"type":"Point"}
}