{
  "type": "Feature",
  "properties": {
    "iso:country":"CH",
    "sg:address":"Untere Gasse 329 4625 Oberbuchsiten. Postfach",
    "sg:city":"Oberbuchsiten",
    "sg:orig_category":"Herstellung von Schrauben, Nieten, Ketten U Federn",
    "sg:phone":"+41 62 393 12 58",
    "sg:postcode":"4625",
    "sg:province":"Solothurn",
    "wof:name":"Borer Walter Ag",
    "wof:placetype":"venue"
},
  "geometry": {"coordinates":[7.7691268921,47.3148040771],"type":"Point"}
}