{
  "type": "Feature",
  "properties": {
    "iso:country":"CH",
    "sg:address":"Route De La Communance 17",
    "sg:city":"Del\u00e9mont",
    "sg:orig_category":"Bau von Strassen, Sportanlagen U Bahnverkehrsstrecken Strassenbau",
    "sg:phone":"+41 32 422 23 63",
    "sg:postcode":"2800",
    "sg:province":"Jura",
    "wof:name":"K\u00fcnzi Sa Del\u00e9mont",
    "wof:placetype":"venue"
},
  "geometry": {"coordinates":[7.342224,47.355656],"type":"Point"}
}