{
  "type": "Feature",
  "properties": {
    "iso:country":"CH",
    "sg:address":"Sonnheim 6242 Wauwil. Postfach 31",
    "sg:city":"Wauwil",
    "sg:orig_category":"K\u00fcnstlerische U schriftstellerische T\u00e4tigkeiten U Darbietungen",
    "sg:phone":"+41 79 415 68 01",
    "sg:postcode":"6242",
    "sg:province":"Luzern",
    "wof:name":"Cormano Ag, Kreatives Atelier",
    "wof:placetype":"venue"
},
  "geometry": {"coordinates":[8.0336027145,47.1884231567],"type":"Point"}
}