{
  "type": "Feature",
  "properties": {
    "iso:country":"CH",
    "sg:address":"Landstrasse 8",
    "sg:city":"Wolfhausen",
    "sg:orig_category":"Vereine Vogel-& Naturschutz",
    "sg:phone":"+41 55 243 10 13",
    "sg:postcode":"8633",
    "sg:province":"Z\u00fcrich",
    "wof:name":"Ornithologischer Verein",
    "wof:placetype":"venue"
},
  "geometry": {"coordinates":[8.7972135544,47.2548065186],"type":"Point"}
}