{
  "type": "Feature",
  "properties": {
    "addr:full":"Aeschenvorstadt 24 Basel Basel-Stadt 4051",
    "addr:housenumber":"24",
    "addr:postcode":"4051",
    "addr:street":"Aeschenvorstadt",
    "iso:country":"CH",
    "sg:address":"Aeschenvorstadt 24",
    "sg:city":"Basel",
    "sg:orig_category":"Detailhandel mit Antiquit\u00e4ten Kunsthandel",
    "sg:phone":"+41 61 271 10 41",
    "sg:postcode":"4051",
    "sg:province":"Basel-Stadt",
    "wof:name":"Galerie Pidoux Inh.andreas Gobeli",
    "wof:placetype":"venue"
},
  "geometry": {"coordinates":[7.592717,47.552883],"type":"Point"}
}