{
  "type": "Feature",
  "properties": {
    "iso:country":"CH",
    "sg:address":"Spitalgasse 37",
    "sg:city":"Bern",
    "sg:classifiers":[
        {
            "category":"Restaurant",
            "type":"Food & Drink"
        }
    ],
    "sg:phone":"+41 31 311 94 10",
    "sg:postcode":"3011",
    "sg:province":"Bern",
    "wof:name":"Restaurant Al Forno",
    "wof:placetype":"venue"
},
  "geometry": {"coordinates":[7.4415960312,46.9477806091],"type":"Point"}
}