{
  "type": "Feature",
  "properties": {
    "iso:country":"CH",
    "sg:address":"W\u00e4seli 361.",
    "sg:city":"Berneck",
    "sg:orig_category":"Detailhandel mit Brot, Back U S\u00fcsswaren",
    "sg:phone":"+41 71 744 46 59",
    "sg:postcode":"9442",
    "sg:province":"St. Gallen",
    "wof:name":"B\u00e4ckerei-konditorei Stadelmann J.",
    "wof:placetype":"venue"
},
  "geometry": {"coordinates":[9.6117,47.427109],"type":"Point"}
}