{
  "type": "Feature",
  "properties": {
    "iso:country":"CH",
    "sg:address":"Brunaustrasse 6",
    "sg:city":"Z\u00fcrich",
    "sg:orig_category":"Gartenbau",
    "sg:phone":"+41 12016906",
    "sg:postcode":"8002",
    "sg:province":"Z\u00fcrich",
    "wof:name":"Hans Tanner Gartenbau",
    "wof:placetype":"venue"
},
  "geometry": {"coordinates":[8.5316123962,47.3564186096],"type":"Point"}
}