{
  "type": "Feature",
  "properties": {
    "iso:country":"CH",
    "sg:address":"Im B\u00e4ttel 238",
    "sg:city":"Boningen",
    "sg:orig_category":"Allgemeiner Hoch U Tiefbau",
    "sg:postcode":"4618",
    "sg:province":"Solothurn",
    "wof:name":"Lenz Carmen",
    "wof:placetype":"venue"
},
  "geometry": {"coordinates":[7.852191,47.305893],"type":"Point"}
}