{
  "type": "Feature",
  "properties": {
    "addr:full":"Werdstrasse 36 Z\u00fcrich Z\u00fcrich 8004",
    "addr:housenumber":"36",
    "addr:postcode":"8004",
    "addr:street":"Werdstrasse",
    "iso:country":"CH",
    "sg:address":"Werdstrasse 36",
    "sg:city":"Z\u00fcrich",
    "sg:orig_category":"Allgemeiner Hoch U Tiefbau",
    "sg:phone":"+41 12914900",
    "sg:postcode":"8004",
    "sg:province":"Z\u00fcrich",
    "wof:name":"Schwendener Baumanagement",
    "wof:placetype":"venue"
},
  "geometry": {"coordinates":[8.529425,47.372707],"type":"Point"}
}