{
  "type": "Feature",
  "properties": {
    "iso:country":"CH",
    "sg:address":"Rue De L'avenir 23",
    "sg:city":"Del\u00e9mont",
    "sg:orig_category":"Wirtschaftspr\u00fcfung, Steuerberatung U Treuhand",
    "sg:phone":"+41 22 735 73 66",
    "sg:postcode":"2800",
    "sg:province":"Jura",
    "wof:name":"Fiduciaire Kernohan & Associ\u00e9s Sa Activit\u00e9s Dans Le Domaine De La Comptabilit\u00e9, Ex\u00e9cution De Mandats Fiscaux Etc",
    "wof:placetype":"venue"
},
  "geometry": {"coordinates":[6.1958532333,46.1938934326],"type":"Point"}
}