{
  "type": "Feature",
  "properties": {
    "iso:country":"CH",
    "sg:address":"Quellenstrasse 18",
    "sg:city":"Adliswil",
    "sg:orig_category":"Werbung",
    "sg:phone":"+41 55863001",
    "sg:postcode":"8134",
    "sg:province":"Z\u00fcrich",
    "wof:name":"Werbung Bidoli",
    "wof:placetype":"venue"
},
  "geometry": {"coordinates":[8.8261785507,47.2294158936],"type":"Point"}
}