{
  "type": "Feature",
  "properties": {
    "iso:country":"CH",
    "sg:address":"1936",
    "sg:city":"Verbier",
    "sg:orig_category":"Vermittlung von Immobilien Verwaltung von Immobilien",
    "sg:phone":"+41 27 771 71 01",
    "sg:postcode":"1936",
    "sg:province":"Valais",
    "wof:name":"Guinnard Immobilier Sa",
    "wof:placetype":"venue"
},
  "geometry": {"coordinates":[7.2229599953,46.0967216492],"type":"Point"}
}