{
  "type": "Feature",
  "properties": {
    "iso:country":"CH",
    "sg:address":"Bahnhofstrasse 4",
    "sg:city":"Bettwiesen",
    "sg:orig_category":"Nationale Postdienste",
    "sg:phone":"+41 56 443 12 25",
    "sg:postcode":"9553",
    "sg:province":"Thurgau",
    "wof:name":"Die Schweizerische Post",
    "wof:placetype":"venue"
},
  "geometry": {"coordinates":[8.1671447754,47.4520301819],"type":"Point"}
}