{
  "type": "Feature",
  "properties": {
    "iso:country":"CH",
    "sg:address":"Rue Des Petits-clos 4 2114 Fleurier Case Postale 366",
    "sg:city":"Fleurier",
    "sg:orig_category":"Giessereiindustrie Herstellung von Metallerzeugnissen ohne Maschinenbau",
    "sg:phone":"+41 32 861 10 91",
    "sg:postcode":"2114",
    "sg:province":"Neuch\u00e2tel",
    "wof:name":"Fonderie Gilles Petit Sa",
    "wof:placetype":"venue"
},
  "geometry": {"coordinates":[6.5858688354,46.9051818848],"type":"Point"}
}