{
  "type": "Feature",
  "properties": {
    "iso:country":"CH",
    "sg:address":"Rue Du Lac 24",
    "sg:city":"Yverdon-les-bains",
    "sg:orig_category":"Detailhandel mit Geschenkartikeln U Souvenirs",
    "sg:phone":"+41 17616002",
    "sg:postcode":"1400",
    "sg:province":"Vaud",
    "wof:name":"Hans Winkler Kunstgew.artikel",
    "wof:placetype":"venue"
},
  "geometry": {"coordinates":[8.4581422806,47.2796783447],"type":"Point"}
}