{
  "type": "Feature",
  "properties": {
    "iso:country":"CH",
    "sg:address":"Tannenrauchstrasse 52 8038 Z\u00fcrich. Postfach",
    "sg:city":"Z\u00fcrich",
    "sg:orig_category":"G\u00fcterbef\u00f6rderung im Strassenverkehr",
    "sg:postcode":"8038",
    "sg:province":"Z\u00fcrich",
    "wof:name":"Sandoz R. & F. & Cie",
    "wof:placetype":"venue"
},
  "geometry": {"coordinates":[6.8996601105,47.0372200012],"type":"Point"}
}