{
  "type": "Feature",
  "properties": {
    "iso:country":"CH",
    "sg:address":"Spielhof 14a",
    "sg:city":"Glarus",
    "sg:orig_category":"Finanzierungsinstitutionen",
    "sg:phone":"+41 55 640 46 00",
    "sg:postcode":"8750",
    "sg:province":"Glarus",
    "wof:name":"Chriba Ag Anlage U. Verwaltung V. Kapitalien Usw.",
    "wof:placetype":"venue"
},
  "geometry": {"coordinates":[9.0660076141,47.0423088074],"type":"Point"}
}