{
  "type": "Feature",
  "properties": {
    "iso:country":"CH",
    "sg:address":"Piazza Motta 47",
    "sg:city":"Ascona",
    "sg:classifiers":[
        {
            "category":"Restaurant",
            "type":"Food & Drink"
        }
    ],
    "sg:phone":"+41 91 791 81 10",
    "sg:postcode":"6612",
    "sg:province":"Ticino",
    "wof:name":"Ristorante Al Gabbiano",
    "wof:placetype":"venue"
},
  "geometry": {"coordinates":[8.7701091766,46.1533699036],"type":"Point"}
}