{
  "type": "Feature",
  "properties": {
    "iso:country":"CH",
    "sg:address":"Route De Denges 6 1027 Lonay Case Postale",
    "sg:city":"Lonay",
    "sg:orig_category":"Grosshandel mit Eisenwaren sowie Installationsbedarf f\u00fcr Gas, Wasser U Heizung Grosshandel mit elekt",
    "sg:phone":"+41 21 811 31 31",
    "sg:postcode":"1027",
    "sg:province":"Vaud",
    "wof:name":"Hebor Sa",
    "wof:placetype":"venue"
},
  "geometry": {"coordinates":[6.52166605,46.5245628357],"type":"Point"}
}