{
  "type": "Feature",
  "properties": {
    "iso:country":"CH",
    "sg:address":"Unterdorf 6",
    "sg:city":"Altb\u00fcron",
    "sg:orig_category":"Herstellung von Reiseartikeln, Leder U Sattlerwaren",
    "sg:phone":"+41 62 927 18 85",
    "sg:postcode":"6147",
    "sg:province":"Luzern",
    "wof:name":"Hans B\u00fctikofer Sattlerei",
    "wof:placetype":"venue"
},
  "geometry": {"coordinates":[7.8799848557,47.1818351746],"type":"Point"}
}