{
  "type": "Feature",
  "properties": {
    "iso:country":"CH",
    "sg:address":"6703",
    "sg:city":"Osogna",
    "sg:orig_category":"Darlehenskassen U Raiffeisenbanken",
    "sg:phone":"+41 91 863 36 31",
    "sg:postcode":"6703",
    "sg:province":"Ticino",
    "wof:name":"Banca Raiffeisen",
    "wof:placetype":"venue"
},
  "geometry": {"coordinates":[8.988675,46.308765],"type":"Point"}
}