{
  "type": "Feature",
  "properties": {
    "iso:country":"CH",
    "sg:address":"Sinserstrasse 65",
    "sg:city":"Cham",
    "sg:orig_category":"Interessenvertretungen",
    "sg:phone":"+41 71 272 23 10",
    "sg:postcode":"6330",
    "sg:province":"Zug",
    "wof:name":"Management Forum St. Gallen Zeitgem\u00e4sse Vermittlung V Wissenschaftl. Erkenntnissen I Bereich D Wirtschaftswissenschaften I Die Managementpraxis Usw",
    "wof:placetype":"venue"
},
  "geometry": {"coordinates":[9.3363304138,47.4099197388],"type":"Point"}
}