{
  "type": "Feature",
  "properties": {
    "addr:full":"Via Dal Bagn 16 St. Moritz Graubunden 7500",
    "addr:housenumber":"16",
    "addr:postcode":"7500",
    "addr:street":"Via Dal Bagn",
    "iso:country":"CH",
    "sg:address":"Via Dal Bagn 16",
    "sg:city":"St. Moritz",
    "sg:classifiers":[
        {
            "category":"Banks & Credit Unions",
            "subcategory":"Bank",
            "type":"Services"
        }
    ],
    "sg:phone":"+41 41 822 25 25",
    "sg:postcode":"7500",
    "sg:province":"Graubunden",
    "wof:name":"Schweiz. Nationalbank",
    "wof:placetype":"venue"
},
  "geometry": {"coordinates":[9.834875,46.48962],"type":"Point"}
}