{
  "type": "Feature",
  "properties": {
    "iso:country":"CH",
    "sg:address":"Pfadackerstr. 9",
    "sg:city":"Spreitenbach",
    "sg:classifiers":[
        {
            "category":"Shopping",
            "subcategory":"Luggage & Leather Goods",
            "type":"Retail Goods"
        }
    ],
    "sg:phone":"+41 56 418 17 17",
    "sg:postcode":"8957",
    "sg:province":"Aargau",
    "sg:tags":[
        "shoe"
    ],
    "wof:name":"Esge Garant Ag",
    "wof:placetype":"venue"
},
  "geometry": {"coordinates":[8.3709726334,47.4253234863],"type":"Point"}
}