{
  "type": "Feature",
  "properties": {
    "iso:country":"CH",
    "sg:address":"Rosenmattstrasse 12",
    "sg:city":"Lyss",
    "sg:orig_category":"Vereine Gemeinn\u00fctzige",
    "sg:phone":"+41 32 384 22 20",
    "sg:postcode":"3250",
    "sg:province":"Bern",
    "wof:name":"Gemeinn\u00fctziger Verein",
    "wof:placetype":"venue"
},
  "geometry": {"coordinates":[7.3106708527,47.0773849487],"type":"Point"}
}