{
  "type": "Feature",
  "properties": {
    "iso:country":"CH",
    "sg:address":"Hauptstrasse 48",
    "sg:city":"Zuchwil",
    "sg:orig_category":"Sonstige Kultur U Unterhaltungseinrichtungen",
    "sg:phone":"+41 32 685 29 20",
    "sg:postcode":"4528",
    "sg:province":"Solothurn",
    "wof:name":"Lotto-stube Gmbh",
    "wof:placetype":"venue"
},
  "geometry": {"coordinates":[7.557844162,47.2034606934],"type":"Point"}
}