{
  "type": "Feature",
  "properties": {
    "iso:country":"CH",
    "sg:address":"L\u00e4nggassstrasse 71",
    "sg:city":"Bern",
    "sg:orig_category":"Fachdetailhandel in Verkaufsr\u00e4umen",
    "sg:phone":"+41 31 302 77 11",
    "sg:postcode":"3012",
    "sg:province":"Bern",
    "wof:name":"Bluemix H\u00e4ni Sonja",
    "wof:placetype":"venue"
},
  "geometry": {"coordinates":[7.4276309013,46.9554138184],"type":"Point"}
}