{
  "type": "Feature",
  "properties": {
    "iso:country":"CH",
    "sg:address":"Neugasse 20",
    "sg:city":"St.gallen",
    "sg:orig_category":"Detailhandel mit B\u00fcromaschinen U einrichtungen Detailhandel mit Computern U Software",
    "sg:postcode":"9000",
    "sg:province":"St. Gallen",
    "wof:name":"Office Tools B\u00fcromaschinen, B\u00fcroger\u00e4te",
    "wof:placetype":"venue"
},
  "geometry": {"coordinates":[9.462694,47.16938],"type":"Point"}
}