{
  "type": "Feature",
  "properties": {
    "iso:country":"CH",
    "sg:address":"Bundesstrasse 7",
    "sg:city":"Neuenhof",
    "sg:orig_category":"Detailhandel mit Metallwaren, Anstrichmitteln, Glaswaren, Bau U Heimwerkerbedarf",
    "sg:postcode":"5432",
    "sg:province":"Aargau",
    "wof:name":"Etra Tec Di Trachsler Ernst",
    "wof:placetype":"venue"
},
  "geometry": {"coordinates":[8.7835407257,46.1753082275],"type":"Point"}
}