{
  "type": "Feature",
  "properties": {
    "iso:country":"CH",
    "sg:address":"D\u00e9lices Chemin Des 9 1006 Lausanne. Postfach",
    "sg:city":"Lausanne",
    "sg:orig_category":"Pensionskassen",
    "sg:postcode":"1006",
    "sg:province":"Vaud",
    "wof:name":"Fondation En Faveur Du Personnel De Von Bergen Et Cie",
    "wof:placetype":"venue"
},
  "geometry": {"coordinates":[6.8132538795,47.0930747986],"type":"Point"}
}