{
  "type": "Feature",
  "properties": {
    "iso:country":"CH",
    "sg:address":"Le Lucet 1950 Sitten. Postfach",
    "sg:city":"Pont-de-la-morge",
    "sg:orig_category":"Stukkateurgewerbe, Gipserei U Verputzerei",
    "sg:postcode":"1962",
    "sg:province":"Valais",
    "wof:name":"Seghezzi Et Proz.",
    "wof:placetype":"venue"
},
  "geometry": {"coordinates":[7.3588571548,46.2280921936],"type":"Point"}
}