{
  "type": "Feature",
  "properties": {
    "iso:country":"CH",
    "sg:address":"Farnstrasse 8",
    "sg:city":"Mellingen",
    "sg:orig_category":"Non-Classified Establishments",
    "sg:postcode":"5507",
    "sg:province":"Aargau",
    "wof:name":"Edv Solutions Salanitro",
    "wof:placetype":"venue"
},
  "geometry": {"coordinates":[8.2723045349,47.4131011963],"type":"Point"}
}