{
  "type": "Feature",
  "properties": {
    "iso:country":"CH",
    "sg:address":"Weinbergstrasse 1",
    "sg:city":"Elgg",
    "sg:orig_category":"Herstellung von Fahrr\u00e4dern",
    "sg:phone":"+41 52 364 31 21",
    "sg:postcode":"8353",
    "sg:province":"Z\u00fcrich",
    "wof:name":"M\u00fcller Peter",
    "wof:placetype":"venue"
},
  "geometry": {"coordinates":[8.8619709015,47.5030097961],"type":"Point"}
}