{
  "type": "Feature",
  "properties": {
    "iso:country":"CH",
    "sg:address":"Gerlafingenstrasse 28",
    "sg:city":"Biberist",
    "sg:orig_category":"Ger\u00fcstbau Vermietung von Baumaschinen U ger\u00e4ten",
    "sg:phone":"+41 71 222 41 61",
    "sg:postcode":"4562",
    "sg:province":"Solothurn",
    "wof:name":"Roth Ger\u00fcste Ag",
    "wof:placetype":"venue"
},
  "geometry": {"coordinates":[9.3711948395,47.4235572815],"type":"Point"}
}