{
  "type": "Feature",
  "properties": {
    "iso:country":"CH",
    "sg:address":"Rue Lamartine 10",
    "sg:city":"Gen\u00e8ve",
    "sg:orig_category":"Datenverarbeitungsdienste Softwareentwicklung U beratung",
    "sg:phone":"+41 22 340 03 46",
    "sg:postcode":"1203",
    "sg:province":"Gen\u00e8ve",
    "wof:name":"Cl\u00e9ment Damien",
    "wof:placetype":"venue"
},
  "geometry": {"coordinates":[6.12865,46.209919],"type":"Point"}
}