{
  "type": "Feature",
  "properties": {
    "iso:country":"CH",
    "sg:address":"Dorfstrasse 21 9423 Altenrhein. Postfach",
    "sg:city":"Altenrhein",
    "sg:orig_category":"RESTAURANTS: TEA-ROOMS",
    "sg:postcode":"9423",
    "sg:province":"St. Gallen",
    "wof:name":"Tobler + Sieber Gastronomiebetrieb",
    "wof:placetype":"venue"
},
  "geometry": {"coordinates":[9.5537223816,47.4902305603],"type":"Point"}
}