{
  "type": "Feature",
  "properties": {
    "iso:country":"CH",
    "sg:address":"Sous Le Pavillon",
    "sg:city":"Chamblon",
    "sg:orig_category":"Stukkateurgewerbe, Gipserei U Verputzerei",
    "sg:phone":"+41 79 446 02 40",
    "sg:postcode":"1436",
    "sg:province":"Vaud",
    "wof:name":"Milici Patrizia",
    "wof:placetype":"venue"
},
  "geometry": {"coordinates":[6.6073861122,46.7775154114],"type":"Point"}
}