{
  "type": "Feature",
  "properties": {
    "iso:country":"CH",
    "sg:address":"Thalberg Rue Sigismond- 2 1200 Genf. Postfach",
    "sg:city":"Gen\u00e8ve",
    "sg:orig_category":"Allgemeinbildende weiterf\u00fchrende Schulen",
    "sg:phone":"+41 32 373 55 67",
    "sg:postcode":"1201",
    "sg:province":"Gen\u00e8ve",
    "wof:name":"Isea Institut F\u00fcr Sicherheit Und Ergonomie Am Arbeitsplatz, Van Der Maas & Van Uum",
    "wof:placetype":"venue"
},
  "geometry": {"coordinates":[7.272376,47.124748],"type":"Point"}
}