{
  "type": "Feature",
  "properties": {
    "iso:country":"CH",
    "sg:address":"Oberrieterstrasse 17",
    "sg:city":"Eichberg",
    "sg:orig_category":"Instandhaltung U Reparatur von Automobilen",
    "sg:postcode":"9453",
    "sg:province":"St. Gallen",
    "wof:name":"Garage Beat Motzer",
    "wof:placetype":"venue"
},
  "geometry": {"coordinates":[9.5308446884,47.3405036926],"type":"Point"}
}