{
  "type": "Feature",
  "properties": {
    "iso:country":"CH",
    "sg:address":"Dorfstrasse 50",
    "sg:city":"Oberhof",
    "sg:orig_category":"Datenverarbeitungsdienste Softwareentwicklung U beratung",
    "sg:phone":"+41 62 877 20 75",
    "sg:postcode":"5062",
    "sg:province":"Aargau",
    "wof:name":"Recom Gmbh",
    "wof:placetype":"venue"
},
  "geometry": {"coordinates":[8.005781,47.450699],"type":"Point"}
}