{
  "type": "Feature",
  "properties": {
    "iso:country":"CH",
    "sg:address":"Z\u00f6pflistrasse 8",
    "sg:city":"Inwil",
    "sg:orig_category":"Herstellung von Konstruktionsteilen, Fertigbauteilen U Ausbauelementen aus Holz",
    "sg:phone":"+41 41 448 20 24",
    "sg:postcode":"6034",
    "sg:province":"Luzern",
    "wof:name":"Kundenschreinerei Und Baumontagen Kempf Josef",
    "wof:placetype":"venue"
},
  "geometry": {"coordinates":[8.3497800827,47.1234817505],"type":"Point"}
}