{
  "type": "Feature",
  "properties": {
    "iso:country":"CH",
    "sg:address":"Zollikerstrasse 128",
    "sg:city":"Z\u00fcrich",
    "sg:orig_category":"Interessenvertretungen",
    "sg:postcode":"8008",
    "sg:province":"Z\u00fcrich",
    "wof:name":"Stiftung Zur Erhaltung Des Patumbah-parkes",
    "wof:placetype":"venue"
},
  "geometry": {"coordinates":[8.5596570969,47.3570175171],"type":"Point"}
}