{
  "type": "Feature",
  "properties": {
    "addr:full":"Route De L' Etraz Nyon Vaud 1260",
    "addr:postcode":"1260",
    "addr:street":"Route De L ' Etraz",
    "iso:country":"CH",
    "sg:address":"Route De L' Etraz",
    "sg:city":"Nyon",
    "sg:classifiers":[
        {
            "category":"Professional",
            "subcategory":"Testing Lab",
            "type":"Services"
        }
    ],
    "sg:phone":"+41 22 363 31 11",
    "sg:postcode":"1260",
    "sg:province":"Vaud",
    "sg:tags":[
        "development",
        "pharmaceutical",
        "clinical"
    ],
    "wof:name":"Novartis Consumer Health Sa",
    "wof:placetype":"venue"
},
  "geometry": {"coordinates":[6.239336,46.388054],"type":"Point"}
}