{
  "type": "Feature",
  "properties": {
    "iso:country":"CH",
    "sg:address":"Br\u00fcggstrasse 35",
    "sg:city":"Biel/bienne",
    "sg:orig_category":"Hardwareberatung Softwareentwicklung U beratung",
    "sg:phone":"+41 32 366 70 80",
    "sg:postcode":"2503",
    "sg:province":"Bern",
    "wof:name":"Sienersoft Ag",
    "wof:placetype":"venue"
},
  "geometry": {"coordinates":[7.2532930374,47.1309051514],"type":"Point"}
}