{
  "type": "Feature",
  "properties": {
    "iso:country":"CH",
    "sg:address":"Zelgstrasse 2",
    "sg:city":"Neuhausen",
    "sg:orig_category":"Instandhaltung U Reparatur von Automobilen",
    "sg:phone":"+41 52 672 81 91",
    "sg:postcode":"8212",
    "sg:province":"Schaffhausen",
    "wof:name":"Rosenberg Garage Ag",
    "wof:placetype":"venue"
},
  "geometry": {"coordinates":[8.6170597076,47.6824378967],"type":"Point"}
}