{
  "type": "Feature",
  "properties": {
    "iso:country":"CH",
    "sg:address":"Faucigny Rue P.-a.-de- 5",
    "sg:city":"Fribourg",
    "sg:orig_category":"Grosshandel mit sonstigen Maschinen U Ausr\u00fcstungen f\u00fcr Industrie, Handel U Schiffahrt",
    "sg:postcode":"1700",
    "sg:province":"Fribourg",
    "wof:name":"General Signal Europe Ltd, Stockport (england), Kindhausen Branch",
    "wof:placetype":"venue"
},
  "geometry": {"coordinates":[8.3857135773,47.3889694214],"type":"Point"}
}