{
  "type": "Feature",
  "properties": {
    "iso:country":"CH",
    "sg:address":"Ruggh\u00f6lzli 2",
    "sg:city":"Remetschwil",
    "sg:orig_category":"Grosshandel mit Holz U Baustoffen",
    "sg:phone":"+41 56 485 84 44",
    "sg:postcode":"5453",
    "sg:province":"Aargau",
    "wof:name":"Inter Flexa Ag",
    "wof:placetype":"venue"
},
  "geometry": {"coordinates":[8.3134613037,47.4113464355],"type":"Point"}
}