{
  "type": "Feature",
  "properties": {
    "addr:full":"Rue Du Village 28 Vernier Gen\u00e8ve 1214",
    "addr:housenumber":"28",
    "addr:postcode":"1214",
    "addr:street":"Rue Du Village",
    "iso:country":"CH",
    "sg:address":"Rue Du Village 28",
    "sg:city":"Vernier",
    "sg:orig_category":"Arztpraxen",
    "sg:phone":"+41 32 931 50 31",
    "sg:postcode":"1214",
    "sg:province":"Gen\u00e8ve",
    "wof:name":"Dr M\u00e9d. Emmanuel Darcey M\u00e9decin Sp\u00e9cialiste Fmh",
    "wof:placetype":"venue"
},
  "geometry": {"coordinates":[6.748963,47.058292],"type":"Point"}
}