{
  "type": "Feature",
  "properties": {
    "iso:country":"CH",
    "sg:address":"Stationsstrasse 9b",
    "sg:city":"Bonstetten",
    "sg:classifiers":[
        {
            "category":"Manufacturing",
            "subcategory":"Tools & Machinery",
            "type":"Manufacturing & Wholesale Goods"
        }
    ],
    "sg:phone":"+41 17011923",
    "sg:postcode":"8906",
    "sg:province":"Z\u00fcrich",
    "sg:tags":[
        "part",
        "turned",
        "cnc"
    ],
    "wof:name":"Daniel Tobler",
    "wof:placetype":"venue"
},
  "geometry": {"coordinates":[8.468137,47.31657],"type":"Point"}
}