{
  "type": "Feature",
  "properties": {
    "iso:country":"CH",
    "sg:address":"Faubourg De L'h\u00f4pital 104",
    "sg:city":"Neuch\u00e2tel",
    "sg:orig_category":"Zahnarztpraxen",
    "sg:phone":"+41 32 725 55 33",
    "sg:postcode":"2000",
    "sg:province":"Neuch\u00e2tel",
    "wof:name":"Dr M\u00e9d.dent.jos\u00e9-philippe Heyd M\u00e9decin-dentiste",
    "wof:placetype":"venue"
},
  "geometry": {"coordinates":[6.9363808632,46.9942970276],"type":"Point"}
}