{
  "type": "Feature",
  "properties": {
    "iso:country":"CH",
    "sg:address":"Hanfl\u00e4nderstrasse 70",
    "sg:city":"Jona",
    "sg:orig_category":"Vorschulen, Kinderg\u00e4rten",
    "sg:phone":"+41 55 210 93 16",
    "sg:postcode":"8645",
    "sg:province":"St. Gallen",
    "wof:name":"Kindergarten Hanfl\u00e4nder",
    "wof:placetype":"venue"
},
  "geometry": {"coordinates":[8.8264503479,47.2329292297],"type":"Point"}
}