{
  "type": "Feature",
  "properties": {
    "iso:country":"CH",
    "sg:address":"Mariabergstrasse 8 9400 Rorschach. Postfach",
    "sg:city":"Rorschach",
    "sg:orig_category":"Herstellung von Konstruktionsteilen, Fertigbauteilen U Ausbauelementen aus Holz",
    "sg:postcode":"9400",
    "sg:province":"St. Gallen",
    "wof:name":"Ak-montagen Gmbh Fenster; Montage. Schreienerarbeiten U. Warenhandel Usw",
    "wof:placetype":"venue"
},
  "geometry": {"coordinates":[9.4928178787,47.4775123596],"type":"Point"}
}