{
  "type": "Feature",
  "properties": {
    "iso:country":"CH",
    "sg:address":"Bahnhofstrasse 28 6300 Zug. Postfach",
    "sg:city":"Zug",
    "sg:orig_category":"Geschenk- and Werbeartikel Grosshandel Glas- and Porzellanwaren Grosshandel",
    "sg:phone":"+41 41 729 80 09",
    "sg:postcode":"6300",
    "sg:province":"Zug",
    "wof:name":"Bellissimo Casa Gmbh Waren, Bes. Haushalt Und Geschenkartikel; Handel",
    "wof:placetype":"venue"
},
  "geometry": {"coordinates":[8.5159921646,47.1701126099],"type":"Point"}
}