{
  "type": "Feature",
  "properties": {
    "iso:country":"CH",
    "sg:address":"Somvih 110",
    "sg:city":"M\u00fcstair",
    "sg:orig_category":"Handelsvermittlung U Grosshandel Versandhandel",
    "sg:phone":"+41 81 850 38 10",
    "sg:postcode":"7537",
    "sg:province":"Graubunden",
    "wof:name":"J\u00fcrg Baeder Agape-versandhandel",
    "wof:placetype":"venue"
},
  "geometry": {"coordinates":[10.4459352493,46.6206817627],"type":"Point"}
}