{
  "type": "Feature",
  "properties": {
    "iso:country":"CH",
    "sg:address":"Hopfengut",
    "sg:city":"Unterstammheim",
    "sg:orig_category":"Herstellung von Mess U Kontrollinstrumenten U vorrichtungen",
    "sg:postcode":"8476",
    "sg:province":"Z\u00fcrich",
    "wof:name":"Preisausgleichkasse F\u00fcr Schweizerhopfen",
    "wof:placetype":"venue"
},
  "geometry": {"coordinates":[8.7902240753,47.6368179321],"type":"Point"}
}