{
  "type": "Feature",
  "properties": {
    "iso:country":"CH",
    "sg:address":"Carona Via Marco Da 11",
    "sg:city":"Lugano",
    "sg:orig_category":"RESTAURANTS: TEA-ROOMS",
    "sg:phone":"+41 91 922 71 64",
    "sg:postcode":"6900",
    "sg:province":"Ticino",
    "wof:name":"Sassi Onorina",
    "wof:placetype":"venue"
},
  "geometry": {"coordinates":[8.958524704,46.012802124],"type":"Point"}
}