{
  "type": "Feature",
  "properties": {
    "addr:full":"Grenzstrasse 20c Lyss Bern 3250",
    "addr:housenumber":"20c",
    "addr:postcode":"3250",
    "addr:street":"Grenzstrasse;Bern",
    "iso:country":"CH",
    "sg:address":"Grenzstrasse 20c",
    "sg:city":"Lyss",
    "sg:orig_category":"Aktivit\u00e4ten der Generalunternehmen im Baugewerbe Bauingenieurb\u00fcros",
    "sg:phone":"+41 32 731 01 25",
    "sg:postcode":"3250",
    "sg:province":"Bern",
    "wof:name":"Gino Rotilio Ing\u00e9nierie",
    "wof:placetype":"venue"
},
  "geometry": {"coordinates":[6.899806,46.984447],"type":"Point"}
}