{
  "type": "Feature",
  "properties": {
    "iso:country":"CH",
    "sg:address":"Rue De La Vernie 11-13",
    "sg:city":"Crissier",
    "sg:classifiers":[
        {
            "category":"Food & Beverages",
            "subcategory":"Groceries & Convenience Stores",
            "type":"Retail Goods"
        }
    ],
    "sg:phone":"+41 21 634 77 33",
    "sg:postcode":"1023",
    "sg:province":"Vaud",
    "sg:tags":[
        "product",
        "related"
    ],
    "wof:name":"Gaterie Sa",
    "wof:placetype":"venue"
},
  "geometry": {"coordinates":[6.5728158951,46.545753479],"type":"Point"}
}