{
  "type": "Feature",
  "properties": {
    "iso:country":"CH",
    "sg:address":"Haselstr. 16",
    "sg:city":"Baden",
    "sg:classifiers":[
        {
            "category":"Banks & Credit Unions",
            "subcategory":"Financial Services",
            "type":"Services"
        }
    ],
    "sg:phone":"+41 56 205 11 11",
    "sg:postcode":"5401",
    "sg:province":"Aargau",
    "sg:tags":[
        "banking",
        "finance",
        "insurance"
    ],
    "wof:name":"Corporate Management Ag",
    "wof:placetype":"venue"
},
  "geometry": {"coordinates":[8.305656,47.478016],"type":"Point"}
}