{
  "type": "Feature",
  "properties": {
    "iso:country":"CH",
    "sg:address":"Rue De La Pontaise 13",
    "sg:city":"Lausanne",
    "sg:orig_category":"Detailhandel mit Geschenkartikeln U Souvenirs",
    "sg:phone":"+41 19100538",
    "sg:postcode":"1018",
    "sg:province":"Vaud",
    "wof:name":"Madeleine Gaignat Geschenk-boutique Zur Eule",
    "wof:placetype":"venue"
},
  "geometry": {"coordinates":[8.5818166733,47.3190231323],"type":"Point"}
}