{
  "type": "Feature",
  "properties": {
    "iso:country":"CH",
    "sg:address":"Maggio Via Al 3",
    "sg:city":"Montagnola",
    "sg:orig_category":"Hardwareberatung",
    "sg:postcode":"6926",
    "sg:province":"Ticino",
    "wof:name":"Tradesystem Sagl",
    "wof:placetype":"venue"
},
  "geometry": {"coordinates":[8.9169063568,45.981918335],"type":"Point"}
}