{
  "type": "Feature",
  "properties": {
    "iso:country":"CH",
    "sg:address":"L\u00f6wengasse 27 8810 Horgen. Postfach",
    "sg:city":"Horgen",
    "sg:orig_category":"Non-Classified Establishments",
    "sg:postcode":"8810",
    "sg:province":"Z\u00fcrich",
    "wof:name":"F.s.h.-beteiligungs Ag",
    "wof:placetype":"venue"
},
  "geometry": {"coordinates":[8.5992355347,47.2598838806],"type":"Point"}
}