{
  "type": "Feature",
  "properties": {
    "iso:country":"CH",
    "sg:address":"Lorzenstrasse 27",
    "sg:city":"Zug",
    "sg:orig_category":"Sonstige pers\u00f6nliche Dienstleistungen",
    "sg:postcode":"6300",
    "sg:province":"Zug",
    "wof:name":"Rust Consultance+dienstleistungen",
    "wof:placetype":"venue"
},
  "geometry": {"coordinates":[8.4935693741,47.1792945862],"type":"Point"}
}