{
  "type": "Feature",
  "properties": {
    "iso:country":"CH",
    "sg:address":"Aeschlimatt 248",
    "sg:city":"H\u00e4rkingen",
    "sg:orig_category":"Kauf U Verkauf von Immobilien auf eigene Rechnung",
    "sg:postcode":"4624",
    "sg:province":"Solothurn",
    "wof:name":"Lesley Ag",
    "wof:placetype":"venue"
},
  "geometry": {"coordinates":[7.8214201927,47.3067817688],"type":"Point"}
}