{
  "type": "Feature",
  "properties": {
    "iso:country":"CH",
    "sg:address":"Bergstrasse 150",
    "sg:city":"Samstagern",
    "sg:orig_category":"Detailhandel mit Gebrauchtwaren in Verkaufsr\u00e4umen",
    "sg:phone":"+41 17840764",
    "sg:postcode":"8833",
    "sg:province":"Z\u00fcrich",
    "wof:name":"Brockenstube Des Frauenvereins",
    "wof:placetype":"venue"
},
  "geometry": {"coordinates":[8.6791734695,47.1949653625],"type":"Point"}
}