{
  "type": "Feature",
  "properties": {
    "iso:country":"CH",
    "sg:address":"Laboratoriumstrasse 10",
    "sg:city":"Winterthur",
    "sg:orig_category":"Stukkateurgewerbe, Gipserei U Verputzerei",
    "sg:postcode":"8400",
    "sg:province":"Z\u00fcrich",
    "wof:name":"Bajrami Medzit Maler- & Gipsergesch\u00e4ft",
    "wof:placetype":"venue"
},
  "geometry": {"coordinates":[8.7191152573,47.5030479431],"type":"Point"}
}