{
  "type": "Feature",
  "properties": {
    "iso:country":"CH",
    "sg:address":"Zelgstrasse 3 8610 Uster. Postfach",
    "sg:city":"Uster",
    "sg:classifiers":[
        {
            "category":"Professional",
            "subcategory":"Employment Agencies",
            "type":"Services"
        }
    ],
    "sg:postcode":"8610",
    "sg:province":"Z\u00fcrich",
    "sg:tags":[
        "personal",
        "u",
        "stellenvermittlung"
    ],
    "wof:name":"Pmg Personalmanagement Gmbh Human Resources, Bes. Gehaltswesen, Personaladministration Usw",
    "wof:placetype":"venue"
},
  "geometry": {"coordinates":[8.708147049,47.3436164856],"type":"Point"}
}