{
  "type": "Feature",
  "properties": {
    "iso:country":"CH",
    "sg:address":"Herdern 8",
    "sg:city":"Ennetb\u00fcrgen",
    "sg:orig_category":"Handel mit Motorr\u00e4dern, Teilen U Zubeh\u00f6r Instandhaltung U Reparatur von Automobilen Instandhaltung U",
    "sg:phone":"+41 41 620 34 07",
    "sg:postcode":"6373",
    "sg:province":"Nidwalden",
    "wof:name":"Gabriel Ernst, Motos",
    "wof:placetype":"venue"
},
  "geometry": {"coordinates":[8.3949928284,46.9791717529],"type":"Point"}
}