{
  "type": "Feature",
  "properties": {
    "addr:full":"Via Rongia Losone Ticino 6616",
    "addr:postcode":"6616",
    "addr:street":"Via Rongia",
    "iso:country":"CH",
    "sg:address":"Via Rongia",
    "sg:city":"Losone",
    "sg:classifiers":[
        {
            "category":"Government",
            "subcategory":"Fire Station",
            "type":"Public Place"
        }
    ],
    "sg:phone":"+41 91 791 46 52",
    "sg:postcode":"6616",
    "sg:province":"Ticino",
    "sg:tags":[
        "steel",
        "chimney"
    ],
    "wof:name":"Valerio D\u00f6ring Metalcostruzioni",
    "wof:placetype":"venue"
},
  "geometry": {"coordinates":[8.736992,46.17823],"type":"Point"}
}