{
  "type": "Feature",
  "properties": {
    "iso:country":"CH",
    "sg:address":"Kirchgasse 3",
    "sg:city":"Schattdorf",
    "sg:orig_category":"Politische Parteien FDP",
    "sg:phone":"+41 56 443 11 67",
    "sg:postcode":"6467",
    "sg:province":"Uri",
    "wof:name":"Fdp Ortspartei Schinznach Bad",
    "wof:placetype":"venue"
},
  "geometry": {"coordinates":[8.1720371246,47.4488983154],"type":"Point"}
}