{
  "type": "Feature",
  "properties": {
    "iso:country":"CH",
    "sg:address":"4457",
    "sg:city":"Diegten",
    "sg:orig_category":"Vereine Gesang",
    "sg:postcode":"4457",
    "sg:province":"Basel-Landschaft",
    "wof:name":"M\u00e4nnerchor Diegten",
    "wof:placetype":"venue"
},
  "geometry": {"coordinates":[7.8104720116,47.4119491577],"type":"Point"}
}