{
  "type": "Feature",
  "properties": {
    "iso:country":"CH",
    "sg:address":"Schulhausstrasse 8",
    "sg:city":"Oberdiessbach",
    "sg:orig_category":"Detailhandel mit Brot, Back U S\u00fcsswaren",
    "sg:phone":"+41 31 771 01 32",
    "sg:postcode":"3672",
    "sg:province":"Bern",
    "wof:name":"Hans Wegm\u00fcller",
    "wof:placetype":"venue"
},
  "geometry": {"coordinates":[7.621295,46.840302],"type":"Point"}
}