{
  "type": "Feature",
  "properties": {
    "iso:country":"CH",
    "sg:address":"Hauptstrasse 10 4415 Lausen. Postfach",
    "sg:city":"Lausen",
    "sg:orig_category":"Herstellung der Ausstattung von Uhren Herstellung von Uhren",
    "sg:phone":"+41 32 910 94 94",
    "sg:postcode":"4415",
    "sg:province":"Basel-Landschaft",
    "wof:name":"Rubattel Et Weyermann Sa",
    "wof:placetype":"venue"
},
  "geometry": {"coordinates":[6.8190231323,47.097694397],"type":"Point"}
}