{
  "type": "Feature",
  "properties": {
    "iso:country":"CH",
    "sg:address":"Route De Saint-andr\u00e9 21 1872 Troistorrents. Postfach",
    "sg:city":"Troistorrents",
    "sg:orig_category":"Herstellung von Konstruktionsteilen, Fertigbauteilen U Ausbauelementen aus Holz",
    "sg:postcode":"1872",
    "sg:province":"Valais",
    "wof:name":"Granger Alexandre S\u00e0rl",
    "wof:placetype":"venue"
},
  "geometry": {"coordinates":[6.9270720482,46.2394943237],"type":"Point"}
}