{
  "type": "Feature",
  "properties": {
    "iso:country":"CH",
    "sg:address":"Place Bel-air 1",
    "sg:city":"Yverdon-les-bains",
    "sg:orig_category":"Detailhandel mit Sportartikeln Herstellung von elektrischen Ausr\u00fcstungen f\u00fcr Motoren U Fahrzeuge",
    "sg:phone":"+41 31 331 92 41",
    "sg:postcode":"1400",
    "sg:province":"Vaud",
    "wof:name":"Yc Nautica-sport Bern Ag",
    "wof:placetype":"venue"
},
  "geometry": {"coordinates":[7.4516677856,46.9553527832],"type":"Point"}
}