{
  "type": "Feature",
  "properties": {
    "addr:full":"B\u00fccklistrasse 17 Turgi Aargau 5300",
    "addr:housenumber":"17",
    "addr:postcode":"5300",
    "addr:street":"Buecklistrasse",
    "iso:country":"CH",
    "sg:address":"B\u00fccklistrasse 17",
    "sg:city":"Turgi",
    "sg:orig_category":"Autoreiseunternehmen",
    "sg:phone":"+423 370 15 60",
    "sg:postcode":"5300",
    "sg:province":"Aargau",
    "wof:name":"Wma Touristik Walter Marxer Autoreisen Ag",
    "wof:placetype":"venue"
},
  "geometry": {"coordinates":[9.5517,47.22345],"type":"Point"}
}