{
  "type": "Feature",
  "properties": {
    "iso:country":"CH",
    "sg:address":"Moortalstr. 11",
    "sg:city":"Gr\u00e4nichen",
    "sg:orig_category":"Chemicals and Pharmaceuticals Chemistry - by-products Energy Transport services",
    "sg:phone":"+41 62 855 24 00",
    "sg:postcode":"5722",
    "sg:province":"Aargau",
    "wof:name":"Dreier Ag Transsporte Logistic",
    "wof:placetype":"venue"
},
  "geometry": {"coordinates":[8.105515,47.35107],"type":"Point"}
}