{
  "type": "Feature",
  "properties": {
    "iso:country":"CH",
    "sg:address":"Im Holzerhurd 46 8000 Z\u00fcrich. Postfach 173",
    "sg:city":"Z\u00fcrich",
    "sg:orig_category":"Instandhaltung U Reparatur von Automobilen",
    "sg:postcode":"8046",
    "sg:province":"Z\u00fcrich",
    "wof:name":"Autohilfe Wima Gmbh",
    "wof:placetype":"venue"
},
  "geometry": {"coordinates":[8.4961891174,47.4235115051],"type":"Point"}
}