{
  "type": "Feature",
  "properties": {
    "iso:country":"CH",
    "sg:address":"B\u00fcrgenstrasse 12 6005 Luzern. Postfach",
    "sg:city":"Luzern",
    "sg:orig_category":"Unfall U Schadenversicherung",
    "sg:phone":"+41 41 361 12 10",
    "sg:postcode":"6002",
    "sg:province":"Luzern",
    "wof:name":"Css Versicherung Ag Unfall, Sachversicherungen Usw",
    "wof:placetype":"venue"
},
  "geometry": {"coordinates":[8.314663887,47.0459518433],"type":"Point"}
}