{
  "type": "Feature",
  "properties": {
    "iso:country":"CH",
    "sg:address":"Chamerstrasse 69",
    "sg:city":"Zug",
    "sg:orig_category":"Sportvereine Wassersport Motorboot",
    "sg:postcode":"6300",
    "sg:province":"Zug",
    "wof:name":"Zuger Motorboot-klub",
    "wof:placetype":"venue"
},
  "geometry": {"coordinates":[8.5004377365,47.17628479],"type":"Point"}
}