{
  "type": "Feature",
  "properties": {
    "iso:country":"CH",
    "sg:address":"M\u00f6renau",
    "sg:city":"Wuppenau",
    "sg:orig_category":"Grosshandel mit lebenden Tieren",
    "sg:postcode":"9514",
    "sg:province":"Thurgau",
    "wof:name":"Albert Kuster",
    "wof:placetype":"venue"
},
  "geometry": {"coordinates":[9.0890474319,47.4836997986],"type":"Point"}
}