{
  "type": "Feature",
  "properties": {
    "iso:country":"CH",
    "sg:address":"Wehntalerstrasse 108",
    "sg:city":"Nassenwil",
    "sg:classifiers":[
        {
            "category":"Bus Stop",
            "subcategory":"None",
            "type":"Transportation"
        }
    ],
    "sg:phone":"+41 18502435",
    "sg:postcode":"8155",
    "sg:province":"Z\u00fcrich",
    "sg:tags":[
        "trailer",
        "dump"
    ],
    "wof:name":"Hrb Heinemann Ag",
    "wof:placetype":"venue"
},
  "geometry": {"coordinates":[8.4839477539,47.4812355042],"type":"Point"}
}