{
  "type": "Feature",
  "properties": {
    "iso:country":"CH",
    "sg:address":"L\u00f6bernweg 10",
    "sg:city":"Cham",
    "sg:orig_category":"Maler U Glasergewerbe",
    "sg:postcode":"6330",
    "sg:province":"Zug",
    "wof:name":"Schmid Peter Malergesch\u00e4ft",
    "wof:placetype":"venue"
},
  "geometry": {"coordinates":[8.4617643356,47.1852340698],"type":"Point"}
}