{
  "type": "Feature",
  "properties": {
    "iso:country":"CH",
    "sg:address":"Rietgasse",
    "sg:city":"Grabs",
    "sg:orig_category":"Vereine Hundedressur",
    "sg:postcode":"9472",
    "sg:province":"St. Gallen",
    "wof:name":"Kynolog.verein.werdenberg",
    "wof:placetype":"venue"
},
  "geometry": {"coordinates":[9.4504299164,47.1861877441],"type":"Point"}
}