{
  "type": "Feature",
  "properties": {
    "addr:full":"S\u00e4nder Niedergesteln Valais 3942",
    "addr:postcode":"3942",
    "iso:country":"CH",
    "sg:address":"S\u00e4nder",
    "sg:city":"Niedergesteln",
    "sg:orig_category":"Betrieb von Taxis Sonstige Personenbef\u00f6rderung im Landverkehr",
    "sg:phone":"+41 27 934 26 49",
    "sg:postcode":"3942",
    "sg:province":"Valais",
    "wof:name":"Steiner A. & Co. Reisen",
    "wof:placetype":"venue"
},
  "geometry": {"coordinates":[7.775195,46.315193],"type":"Point"}
}