{
  "type": "Feature",
  "properties": {
    "addr:full":"Ringstrasse Nord 40 Lenzburg Aargau 5600",
    "addr:housenumber":"40",
    "addr:postcode":"5600",
    "addr:street":"Ringstrasse Nord",
    "iso:country":"CH",
    "sg:address":"Ringstrasse Nord 40",
    "sg:city":"Lenzburg",
    "sg:orig_category":"Allgemeiner Hochbau Dachdeckerei",
    "sg:phone":"+41 71 966 69 22",
    "sg:postcode":"5600",
    "sg:province":"Aargau",
    "wof:name":"Roland M\u00fcller Bedachungen & Fassadenbau",
    "wof:placetype":"venue"
},
  "geometry": {"coordinates":[8.994281,47.483162],"type":"Point"}
}