{
  "type": "Feature",
  "properties": {
    "iso:country":"CH",
    "sg:address":"Leutschenstrasse 20",
    "sg:city":"Kirchlindach",
    "sg:classifiers":[
        {
            "category":"Insurance",
            "subcategory":"Insurance Agent",
            "type":"Services"
        }
    ],
    "sg:phone":"+41 31 829 01 38",
    "sg:postcode":"3038",
    "sg:province":"Bern",
    "sg:tags":[
        "versicherungsagenturen",
        "-broker"
    ],
    "wof:name":"Winterthur-versicherungen Agentur Irene Niklaus",
    "wof:placetype":"venue"
},
  "geometry": {"coordinates":[7.4101338387,47.0051574707],"type":"Point"}
}