{
  "type": "Feature",
  "properties": {
    "iso:country":"CH",
    "sg:address":"Via Como 1",
    "sg:city":"Chiasso",
    "sg:orig_category":"Herstellung der Ausstattung von Uhren",
    "sg:phone":"+41 32 968 21 05",
    "sg:postcode":"6830",
    "sg:province":"Ticino",
    "wof:name":"Lnc S\u00e0rl",
    "wof:placetype":"venue"
},
  "geometry": {"coordinates":[6.8234901428,47.1066970825],"type":"Point"}
}