{
  "type": "Feature",
  "properties": {
    "iso:country":"CH",
    "sg:address":"V\u00e9troz Rue De 57 1964 Conthey. Postfach",
    "sg:city":"Conthey",
    "sg:orig_category":"Softwareentwicklung U beratung",
    "sg:postcode":"1964",
    "sg:province":"Valais",
    "wof:name":"Pocketstore S\u00e0rl",
    "wof:placetype":"venue"
},
  "geometry": {"coordinates":[7.3066477776,46.2291526794],"type":"Point"}
}