{
  "type": "Feature",
  "properties": {
    "iso:country":"CH",
    "sg:address":"8580 Amriswil. Postfach",
    "sg:city":"Biessenhofen",
    "sg:orig_category":"Unclassifiable Establishments",
    "sg:postcode":"8580",
    "sg:province":"Thurgau",
    "wof:name":"Elektra Biessenhofen.",
    "wof:placetype":"venue"
},
  "geometry": {"coordinates":[9.2995681763,47.54504776],"type":"Point"}
}