{
  "type": "Feature",
  "properties": {
    "iso:country":"CH",
    "sg:address":"Stutzstrasse 50 8834 Schindellegi. Postfach",
    "sg:city":"Schindellegi",
    "sg:orig_category":"Non-Classified Establishments",
    "sg:phone":"+41 19381514",
    "sg:postcode":"8834",
    "sg:province":"Schwyz",
    "wof:name":"M\u00fcller Gebr. Steinbruchbetrieb Ag, Zweigniederlassung Naturstein-center Z\u00fcri-oberland Natursteine; Gewinnung, Bearbeitung. Steine; Handel",
    "wof:placetype":"venue"
},
  "geometry": {"coordinates":[8.8398342133,47.3036689758],"type":"Point"}
}