{
  "type": "Feature",
  "properties": {
    "iso:country":"CH",
    "sg:address":"Schrotm\u00e4ttli 5",
    "sg:city":"Littau",
    "sg:orig_category":"Herstellung von sonstigen Metallwaren",
    "sg:phone":"+41 41 850 83 60",
    "sg:postcode":"6014",
    "sg:province":"Luzern",
    "wof:name":"Euraseal Ag",
    "wof:placetype":"venue"
},
  "geometry": {"coordinates":[8.4368066788,47.0692977905],"type":"Point"}
}