{
  "type": "Feature",
  "properties": {
    "iso:country":"CH",
    "sg:address":"Moosstrasse 4",
    "sg:city":"Huttwil",
    "sg:orig_category":"Pensionskassen",
    "sg:postcode":"4950",
    "sg:province":"Bern",
    "wof:name":"Personalvorsorgestiftung Der Fritz Mathys & Co Ag Bauunternehmung",
    "wof:placetype":"venue"
},
  "geometry": {"coordinates":[7.8435678482,47.1137237549],"type":"Point"}
}