{
  "type": "Feature",
  "properties": {
    "addr:full":"Gerbergasse 40 Basel Basel-Stadt 4001",
    "addr:housenumber":"40",
    "addr:postcode":"4001",
    "addr:street":"Gerbergasse",
    "iso:country":"CH",
    "sg:address":"Gerbergasse 40",
    "sg:city":"Basel",
    "sg:orig_category":"Wirtschaft U Handel, Wirtschaftliche Beratungsdienste",
    "sg:postcode":"4001",
    "sg:province":"Basel-Stadt",
    "wof:name":"Affinitas Gmbh",
    "wof:placetype":"venue"
},
  "geometry": {"coordinates":[7.588455,47.556217],"type":"Point"}
}