{
  "type": "Feature",
  "properties": {
    "iso:country":"CH",
    "sg:address":"B\u00f6sch 43 6331 H\u00fcnenberg. Postfach 742",
    "sg:city":"H\u00fcnenberg",
    "sg:orig_category":"Wirtschaftspr\u00fcfung, Steuerberatung U Treuhand",
    "sg:phone":"+41 41 780 37 36",
    "sg:postcode":"6331",
    "sg:province":"Zug",
    "wof:name":"Thode Treuhand Gmbh",
    "wof:placetype":"venue"
},
  "geometry": {"coordinates":[8.4376420975,47.1618881226],"type":"Point"}
}