{
  "type": "Feature",
  "properties": {
    "iso:country":"CH",
    "sg:address":"Rue Davel 7",
    "sg:city":"Cully",
    "sg:orig_category":"Reiseb\u00fcros U Reiseveranstalter",
    "sg:phone":"+41 21 799 19 18",
    "sg:postcode":"1096",
    "sg:province":"Vaud",
    "wof:name":"Cocktail Vacances, Chappuis Nathalie",
    "wof:placetype":"venue"
},
  "geometry": {"coordinates":[6.730987072,46.4881744385],"type":"Point"}
}