{
  "type": "Feature",
  "properties": {
    "iso:country":"CH",
    "sg:address":"Rue Centrale 55 2740 Moutier Case Postale 720",
    "sg:city":"Montagne-moutier",
    "sg:orig_category":"Drogerien Fachdetailhandel mit pharmazeutischen Produkten",
    "sg:phone":"+41 32 493 18 71",
    "sg:postcode":"2740",
    "sg:province":"Bern",
    "wof:name":"Pharmacie Et Droguerie Greppin Sa Droguerie",
    "wof:placetype":"venue"
},
  "geometry": {"coordinates":[7.3726701736,47.2794418335],"type":"Point"}
}