{
  "type": "Feature",
  "properties": {
    "iso:country":"CH",
    "sg:address":"Witikonstr. 14 8117 F\u00e4llanden. Postfach",
    "sg:city":"Binz",
    "sg:orig_category":"Grosshandel mit sonstigen Gebrauchs U Verbrauchsg\u00fctern",
    "sg:postcode":"8122",
    "sg:province":"Z\u00fcrich",
    "wof:name":"Ratnaloka, Delano Muller",
    "wof:placetype":"venue"
},
  "geometry": {"coordinates":[8.6254444122,47.3602561951],"type":"Point"}
}