{
  "type": "Feature",
  "properties": {
    "iso:country":"CH",
    "sg:address":"Birsstrasse 10",
    "sg:city":"Basel",
    "sg:orig_category":"Pensionskassen",
    "sg:phone":"+41 61 261 15 15",
    "sg:postcode":"4052",
    "sg:province":"Basel-Stadt",
    "wof:name":"F\u00fcrsorgestiftung Der Schweizerischen Zahn\u00e4rzte-gesellschaft",
    "wof:placetype":"venue"
},
  "geometry": {"coordinates":[7.6165890694,47.5541801453],"type":"Point"}
}