{
  "type": "Feature",
  "properties": {
    "iso:country":"CH",
    "sg:address":"Schachen 34 5000 Aarau. Postfach",
    "sg:city":"Aarau",
    "sg:orig_category":"Sonstige mit Sport verbundene T\u00e4tigkeiten",
    "sg:postcode":"5004",
    "sg:province":"Aargau",
    "wof:name":"Aarau Eagles Cheerleader",
    "wof:placetype":"venue"
},
  "geometry": {"coordinates":[8.0398797989,47.3914299011],"type":"Point"}
}