{
  "type": "Feature",
  "properties": {
    "iso:country":"CH",
    "sg:address":"Avenue De Bellevaux 18",
    "sg:city":"Neuch\u00e2tel",
    "sg:orig_category":"Physiotherapie",
    "sg:phone":"+41 32 725 91 25",
    "sg:postcode":"2000",
    "sg:province":"Neuch\u00e2tel",
    "wof:name":"Jeanne-louise Haeberli Physioth\u00e9rapie",
    "wof:placetype":"venue"
},
  "geometry": {"coordinates":[6.9270558357,46.9910430908],"type":"Point"}
}