{
  "type": "Feature",
  "properties": {
    "iso:country":"CH",
    "sg:address":"Grand Rue 8",
    "sg:city":"Echallens",
    "sg:orig_category":"Fachdetailhandel in Verkaufsr\u00e4umen",
    "sg:postcode":"1040",
    "sg:province":"Vaud",
    "wof:name":"H\u00e4mmerli Marie-louise",
    "wof:placetype":"venue"
},
  "geometry": {"coordinates":[6.6337399483,46.641456604],"type":"Point"}
}