{
  "type": "Feature",
  "properties": {
    "iso:country":"CH",
    "sg:address":"Kaserne",
    "sg:city":"Walenstadt",
    "sg:orig_category":"Kantinen",
    "sg:postcode":"8880",
    "sg:province":"St. Gallen",
    "wof:name":"Fl\u00fcck Sylvia",
    "wof:placetype":"venue"
},
  "geometry": {"coordinates":[9.3030033112,47.1262779236],"type":"Point"}
}