{
  "type": "Feature",
  "properties": {
    "iso:country":"CH",
    "sg:address":"H\u00f6henstrasse 4b",
    "sg:city":"Geroldswil",
    "sg:orig_category":"Maschinen and Apparate divers Grosshandel",
    "sg:phone":"+41 61 711 01 00",
    "sg:postcode":"8954",
    "sg:province":"Z\u00fcrich",
    "wof:name":"Heer Ag Gastgewerbe-maschinen, -apparate U. -einrichtungen; Fabr., Import, Handel Usw.",
    "wof:placetype":"venue"
},
  "geometry": {"coordinates":[7.59948,47.48632],"type":"Point"}
}