{
  "type": "Feature",
  "properties": {
    "iso:country":"CH",
    "sg:address":"Chemin De Champ-rond 3",
    "sg:city":"Lausanne",
    "sg:orig_category":"Vereine Gesang",
    "sg:phone":"+41 21 323 80 33",
    "sg:postcode":"1010",
    "sg:province":"Vaud",
    "wof:name":"St\u00e9 De Chant La Recr\u00e9ation",
    "wof:placetype":"venue"
},
  "geometry": {"coordinates":[6.6508932114,46.5322227478],"type":"Point"}
}