{
  "type": "Feature",
  "properties": {
    "iso:country":"CH",
    "sg:address":"Kantonsstrasse 7302 Landquart. Postfach",
    "sg:city":"Z\u00fcrich",
    "sg:orig_category":"Herstellung von Papier, Karton U Pappe",
    "sg:postcode":"8041",
    "sg:province":"Z\u00fcrich",
    "wof:name":"Portals-sihl Ag",
    "wof:placetype":"venue"
},
  "geometry": {"coordinates":[9.5626897812,46.9673309326],"type":"Point"}
}