{
  "type": "Feature",
  "properties": {
    "iso:country":"CH",
    "sg:address":"Lagerhaus A",
    "sg:city":"Embrach",
    "sg:orig_category":"Herstellung von Hebezeugen U F\u00f6rdermitteln",
    "sg:phone":"+41 18662020",
    "sg:postcode":"8424",
    "sg:province":"Z\u00fcrich",
    "wof:name":"System-gut Logistik Service Ag",
    "wof:placetype":"venue"
},
  "geometry": {"coordinates":[8.5976867676,47.5006790161],"type":"Point"}
}