{
  "type": "Feature",
  "properties": {
    "iso:country":"CH",
    "sg:address":"Avenue William-fraisse 1",
    "sg:city":"Lausanne",
    "sg:orig_category":"Detailhandel mit Blumen U Pflanzen Fachdetailhandel in Verkaufsr\u00e4umen",
    "sg:phone":"+41 21 616 05 97",
    "sg:postcode":"1006",
    "sg:province":"Vaud",
    "wof:name":"Floril\u00e8ge, Wasbauer Jacqui",
    "wof:placetype":"venue"
},
  "geometry": {"coordinates":[6.626339,46.516441],"type":"Point"}
}