{
  "type": "Feature",
  "properties": {
    "iso:country":"CH",
    "sg:address":"2608",
    "sg:city":"Courtelary",
    "sg:orig_category":"Pensionskassen",
    "sg:phone":"+41 32 944 17 17",
    "sg:postcode":"2608",
    "sg:province":"Bern",
    "wof:name":"Fondation Camille Bloch Sa",
    "wof:placetype":"venue"
},
  "geometry": {"coordinates":[7.0733680725,47.1785583496],"type":"Point"}
}