{
  "type": "Feature",
  "properties": {
    "iso:country":"CH",
    "sg:address":"Schulstrasse 11 9435 Heerbrugg. Postfach",
    "sg:city":"Heerbrugg",
    "sg:orig_category":"Vermietung U Verpachtung von eigenen Immobilien",
    "sg:postcode":"9435",
    "sg:province":"St. Gallen",
    "wof:name":"Oskebo-immobilien Ag",
    "wof:placetype":"venue"
},
  "geometry": {"coordinates":[9.6265449524,47.4178771973],"type":"Point"}
}