{
  "type": "Feature",
  "properties": {
    "iso:country":"CH",
    "sg:address":"Zollstrasse 94 8219 Trasadingen. Postfach",
    "sg:city":"Trasadingen",
    "sg:orig_category":"Grosshandel mit sonstigen Maschinen U Ausr\u00fcstungen f\u00fcr Industrie, Handel U Schiffahrt Herstellung vo",
    "sg:phone":"+41 52 682 22 91",
    "sg:postcode":"8219",
    "sg:province":"Schaffhausen",
    "wof:name":"Diwe Direktweg-handels Gmbh Fiberkeramik-kamine U. Produkte Der Umweltschutztechnik; Handel",
    "wof:placetype":"venue"
},
  "geometry": {"coordinates":[8.4323654175,47.6626472473],"type":"Point"}
}