{
  "type": "Feature",
  "properties": {
    "iso:country":"CH",
    "sg:address":"Z\u00fcrcher Strasse 27",
    "sg:city":"St.gallen",
    "sg:orig_category":"Grosshandel mit Holz U Baustoffen",
    "sg:phone":"+41 71 277 61 79",
    "sg:postcode":"9000",
    "sg:province":"St. Gallen",
    "wof:name":"Meplag",
    "wof:placetype":"venue"
},
  "geometry": {"coordinates":[9.355307579,47.4197273254],"type":"Point"}
}