{
  "type": "Feature",
  "properties": {
    "iso:country":"CH",
    "sg:address":"Route De Cho\u00ebx 117 1870 Monthey. Postfach",
    "sg:city":"Monthey",
    "sg:orig_category":"Handels-H\u00e4user U Gesellschaften",
    "sg:phone":"+41 24 471 81 60",
    "sg:postcode":"1870",
    "sg:province":"Valais",
    "wof:name":"Germanier Pierette Bureau De Courtage En Assurance",
    "wof:placetype":"venue"
},
  "geometry": {"coordinates":[6.9645757675,46.2399635315],"type":"Point"}
}