{
  "type": "Feature",
  "properties": {
    "iso:country":"CH",
    "sg:address":"8836",
    "sg:city":"Bennau",
    "sg:orig_category":"Sportvereine Sch\u00fctzen",
    "sg:phone":"+41 62 752 16 10",
    "sg:postcode":"8836",
    "sg:province":"Schwyz",
    "wof:name":"Sch\u00fctzengesellschaft",
    "wof:placetype":"venue"
},
  "geometry": {"coordinates":[8.7297801971,47.1484413147],"type":"Point"}
}