{
  "type": "Feature",
  "properties": {
    "iso:country":"CH",
    "sg:address":"Quai Du Mont-blanc 29 1200 Genf. Postfach",
    "sg:city":"Gen\u00e8ve",
    "sg:orig_category":"Finanzierungsinstitutionen",
    "sg:postcode":"1201",
    "sg:province":"Gen\u00e8ve",
    "wof:name":"Gerrard Energy Ventures Sa, Luxembourg, Geneva Branch",
    "wof:placetype":"venue"
},
  "geometry": {"coordinates":[6.1522188187,46.2112045288],"type":"Point"}
}