{
  "type": "Feature",
  "properties": {
    "iso:country":"CH",
    "sg:address":"S\u00e4gemattstrasse 11 3097 Liebefeld. Postfach",
    "sg:city":"Liebefeld",
    "sg:orig_category":"Druck ohne Zeitungsdruck",
    "sg:phone":"+41 31 978 33 33",
    "sg:postcode":"3097",
    "sg:province":"Bern",
    "wof:name":"Lang Druck Ag",
    "wof:placetype":"venue"
},
  "geometry": {"coordinates":[7.4152140617,46.9273147583],"type":"Point"}
}