{
  "type": "Feature",
  "properties": {
    "iso:country":"CH",
    "sg:address":"Avenue Auguste Forel 6",
    "sg:city":"Morges",
    "sg:orig_category":"Grosshandel mit Getreide, Saatgut U Futtermitteln Handelsvermittlung U Grosshandel",
    "sg:phone":"+41 21 811 22 80",
    "sg:postcode":"1110",
    "sg:province":"Vaud",
    "wof:name":"Audemars Piguet (suisse) Sa",
    "wof:placetype":"venue"
},
  "geometry": {"coordinates":[6.504073143,46.5184173584],"type":"Point"}
}