{
  "type": "Feature",
  "properties": {
    "iso:country":"CH",
    "sg:address":"Oberdorf 9444 Diepoldsau. Postfach",
    "sg:city":"Diepoldsau",
    "sg:orig_category":"Vermietung U Verpachtung von eigenen Immobilien",
    "sg:postcode":"9444",
    "sg:province":"St. Gallen",
    "wof:name":"Kuster-huber W.",
    "wof:placetype":"venue"
},
  "geometry": {"coordinates":[9.6561403275,47.38306427],"type":"Point"}
}