{
  "type": "Feature",
  "properties": {
    "iso:country":"CH",
    "sg:address":"Voa Viglia Lain 7082 Vaz/obervaz. Postfach 917",
    "sg:city":"Lenzerheide/lai",
    "sg:orig_category":"Massagestudios",
    "sg:phone":"+41 81 384 52 50",
    "sg:postcode":"7078",
    "sg:province":"Graubunden",
    "wof:name":"Willi Rieser Massagen",
    "wof:placetype":"venue"
},
  "geometry": {"coordinates":[9.5320672989,46.696723938],"type":"Point"}
}