{
  "type": "Feature",
  "properties": {
    "iso:country":"CH",
    "sg:address":"Brestenegg",
    "sg:city":"Ettiswil",
    "sg:orig_category":"Sportvereine Sch\u00fctzen Armbrust",
    "sg:phone":"+41 41 980 18 40",
    "sg:postcode":"6218",
    "sg:province":"Luzern",
    "wof:name":"Armbrustsch\u00fctzenverein Ettiswil",
    "wof:placetype":"venue"
},
  "geometry": {"coordinates":[8.0154151917,47.1428451538],"type":"Point"}
}