{
  "type": "Feature",
  "properties": {
    "addr:full":"Bahnhofstrasse 47 Roggwil Bern 4914",
    "addr:housenumber":"47",
    "addr:postcode":"4914",
    "addr:street":"Bahnhofstrasse",
    "iso:country":"CH",
    "sg:address":"Bahnhofstrasse 47",
    "sg:city":"Roggwil",
    "sg:orig_category":"Barcode Software",
    "sg:phone":"+41 62 929 40 22",
    "sg:postcode":"4914",
    "sg:province":"Bern",
    "wof:name":"Pele Computer",
    "wof:placetype":"venue"
},
  "geometry": {"coordinates":[7.815838,47.245052],"type":"Point"}
}