{
  "type": "Feature",
  "properties": {
    "iso:country":"CH",
    "sg:address":"Rue Versonnex 15",
    "sg:city":"Gen\u00e8ve",
    "sg:orig_category":"Detailhandel mit Brillen U anderen Sehhilfen Fachdetailhandel in Verkaufsr\u00e4umen",
    "sg:phone":"+41 56 664 02 05",
    "sg:postcode":"1207",
    "sg:province":"Gen\u00e8ve",
    "wof:name":"Ludin Andy Augenoptik",
    "wof:placetype":"venue"
},
  "geometry": {"coordinates":[8.317482,47.282578],"type":"Point"}
}