{
  "type": "Feature",
  "properties": {
    "iso:country":"CH",
    "sg:address":"Weberstrasse 10",
    "sg:city":"Z\u00fcrich",
    "sg:orig_category":"Ingenieurb\u00fcros Datenverarbeitung",
    "sg:phone":"+41 56 493 57 77",
    "sg:postcode":"8004",
    "sg:province":"Z\u00fcrich",
    "wof:name":"Karl-heinz Wild Informatik",
    "wof:placetype":"venue"
},
  "geometry": {"coordinates":[8.2922182083,47.4489364624],"type":"Point"}
}