{
  "type": "Feature",
  "properties": {
    "iso:country":"CH",
    "sg:address":"Elisabethenanlage 9 4051 Basel. Postfach",
    "sg:city":"Basel",
    "sg:orig_category":"Allgemeinbildende weiterf\u00fchrende Schulen",
    "sg:phone":"+41 61 270 97 97",
    "sg:postcode":"4051",
    "sg:province":"Basel-Stadt",
    "wof:name":"Nsh I-school Schule, Institut F\u00fcr Angewandte Gestaltung Usw",
    "wof:placetype":"venue"
},
  "geometry": {"coordinates":[7.589153,47.549126],"type":"Point"}
}