{
  "type": "Feature",
  "properties": {
    "iso:country":"CH",
    "sg:address":"Rigistrasse 16 8344 B\u00e4retswil. Postfach",
    "sg:city":"B\u00e4retswil",
    "sg:orig_category":"Markt U Meinungsforschung",
    "sg:postcode":"8344",
    "sg:province":"Z\u00fcrich",
    "wof:name":"De Monaco-marketing Gmbh",
    "wof:placetype":"venue"
},
  "geometry": {"coordinates":[8.8484573364,47.3394241333],"type":"Point"}
}