{
  "type": "Feature",
  "properties": {
    "addr:full":"Rue De La Borde 59 Lausanne Vaud 1018",
    "addr:housenumber":"59",
    "addr:postcode":"1018",
    "addr:street":"Rue De La Borde",
    "iso:country":"CH",
    "sg:address":"Rue De La Borde 59",
    "sg:city":"Lausanne",
    "sg:orig_category":"Arztpraxen",
    "sg:phone":"+41 21 647 23 23",
    "sg:postcode":"1018",
    "sg:province":"Vaud",
    "wof:name":"Dr M\u00e9d. P\u00e9ricl\u00e8s Mavrot M\u00e9decin G\u00e9n\u00e9raliste Fmh",
    "wof:placetype":"venue"
},
  "geometry": {"coordinates":[6.630022,46.531921],"type":"Point"}
}