{
  "type": "Feature",
  "properties": {
    "iso:country":"CH",
    "sg:address":"Jakob Stutz-strasse 100",
    "sg:city":"Oberhittnau",
    "sg:orig_category":"RESTAURANTS: TEA-ROOMS",
    "sg:phone":"+41 19501033",
    "sg:postcode":"8335",
    "sg:province":"Z\u00fcrich",
    "wof:name":"Crazy Shopping Gmbh",
    "wof:placetype":"venue"
},
  "geometry": {"coordinates":[8.8239250183,47.3613090515],"type":"Point"}
}