{
  "type": "Feature",
  "properties": {
    "iso:country":"CH",
    "sg:address":"Universit\u00e4tstrasse 87 8006 Z\u00fcrich. Postfach",
    "sg:city":"Z\u00fcrich",
    "sg:orig_category":"Wirtschaftspr\u00fcfung, Steuerberatung U Treuhand",
    "sg:phone":"+41 13633260",
    "sg:postcode":"8033",
    "sg:province":"Z\u00fcrich",
    "wof:name":"Interinkasso Ag",
    "wof:placetype":"venue"
},
  "geometry": {"coordinates":[8.5480298996,47.3832244873],"type":"Point"}
}