{
  "type": "Feature",
  "properties": {
    "addr:full":"Kradolfstrasse 23 Sulgen Thurgau 8583",
    "addr:housenumber":"23",
    "addr:postcode":"8583",
    "addr:street":"Kradolfstrasse",
    "iso:country":"CH",
    "sg:address":"Kradolfstrasse 23",
    "sg:city":"Sulgen",
    "sg:orig_category":"Bauschreinerei Herstellung von Konstruktionsteilen, Fertigbauteilen U Ausbauelementen aus Holz",
    "sg:phone":"+41 71 642 40 42",
    "sg:postcode":"8583",
    "sg:province":"Thurgau",
    "wof:name":"Schreinerei-zimmerei Hildebrand",
    "wof:placetype":"venue"
},
  "geometry": {"coordinates":[9.18644,47.535961],"type":"Point"}
}