{
  "type": "Feature",
  "properties": {
    "iso:country":"CH",
    "sg:address":"Bon Pirouz",
    "sg:city":"Vich",
    "sg:orig_category":"Unclassifiable Establishments",
    "sg:phone":"+41 22 364 22 06",
    "sg:postcode":"1267",
    "sg:province":"Vaud",
    "wof:name":"Gps Publishing Services, Lancaster Peter",
    "wof:placetype":"venue"
},
  "geometry": {"coordinates":[6.2480697632,46.4293746948],"type":"Point"}
}