{
  "type": "Feature",
  "properties": {
    "iso:country":"CH",
    "sg:address":"Langenthalstrasse 21a",
    "sg:city":"Th\u00f6rigen",
    "sg:classifiers":[
        {
            "category":"Banks & Credit Unions",
            "subcategory":"Bank",
            "type":"Services"
        }
    ],
    "sg:phone":"+41 4163611008",
    "sg:postcode":"3367",
    "sg:province":"Bern",
    "wof:name":"Berner Kantonalbank",
    "wof:placetype":"venue"
},
  "geometry": {"coordinates":[7.736344,47.174797],"type":"Point"}
}