{
  "type": "Feature",
  "properties": {
    "iso:country":"CH",
    "sg:address":"Louss\u00e9 Chemin Du 1911 Ovronnaz. Postfach",
    "sg:city":"Ovronnaz",
    "sg:orig_category":"Hardwareberatung",
    "sg:postcode":"1911",
    "sg:province":"Valais",
    "wof:name":"Compri-ch S\u00e0rl Commercialisation, Achat, Vente, Service Et Conseil Dans Le Dom. De L'informatique Etc",
    "wof:placetype":"venue"
},
  "geometry": {"coordinates":[7.172729969,46.1974182129],"type":"Point"}
}