{
  "type": "Feature",
  "properties": {
    "addr:full":"Rue De Neuch\u00e2tel 12 Yverdon-les-bains Vaud 1400",
    "addr:housenumber":"12",
    "addr:postcode":"1400",
    "addr:street":"Rue De Neucha\u0302Tel",
    "iso:country":"CH",
    "sg:address":"Rue De Neuch\u00e2tel 12",
    "sg:city":"Yverdon-les-bains",
    "sg:orig_category":"Detailhandel mit Blumen U Pflanzen Fachdetailhandel in Verkaufsr\u00e4umen",
    "sg:phone":"+41 24 425 23 55",
    "sg:postcode":"1400",
    "sg:province":"Vaud",
    "wof:name":"Roland Martin Belfleur Magasin De Fleurs",
    "wof:placetype":"venue"
},
  "geometry": {"coordinates":[6.636376,46.781464],"type":"Point"}
}