{
  "type": "Feature",
  "properties": {
    "iso:country":"CH",
    "sg:address":"Via Delle Scuole 4",
    "sg:city":"Locarno",
    "sg:orig_category":"Schiffs U Bootsbau",
    "sg:phone":"+41 16877700",
    "sg:postcode":"6600",
    "sg:province":"Ticino",
    "wof:name":"Bamert Urs, Marine-technik",
    "wof:placetype":"venue"
},
  "geometry": {"coordinates":[8.7370700836,47.2054214478],"type":"Point"}
}