{
  "type": "Feature",
  "properties": {
    "iso:country":"CH",
    "sg:address":"Feldrainstrasse 51",
    "sg:city":"Liebefeld",
    "sg:orig_category":"Sportvereine Sch\u00fctzen",
    "sg:postcode":"3097",
    "sg:province":"Bern",
    "wof:name":"Sch\u00fctzengesellschaft Felsenau",
    "wof:placetype":"venue"
},
  "geometry": {"coordinates":[7.4266967773,46.9278450012],"type":"Point"}
}