{
  "type": "Feature",
  "properties": {
    "iso:country":"CH",
    "sg:address":"3088",
    "sg:city":"R\u00fceggisberg",
    "sg:orig_category":"Primarschulen",
    "sg:phone":"+41 31 781 15 22",
    "sg:postcode":"3088",
    "sg:province":"Bern",
    "wof:name":"Primarschule",
    "wof:placetype":"venue"
},
  "geometry": {"coordinates":[7.5478601456,46.8207092285],"type":"Point"}
}