{
  "type": "Feature",
  "properties": {
    "iso:country":"CH",
    "sg:address":"Soodmattenstrasse 10",
    "sg:city":"Adliswil",
    "sg:orig_category":"Interessenvertretungen",
    "sg:postcode":"8134",
    "sg:province":"Z\u00fcrich",
    "wof:name":"Generali Bvg-stiftung",
    "wof:placetype":"venue"
},
  "geometry": {"coordinates":[8.5234088898,47.321056366],"type":"Point"}
}