{
  "type": "Feature",
  "properties": {
    "iso:country":"CH",
    "sg:address":"6772",
    "sg:city":"Rodi-fiesso",
    "sg:classifiers":[
        {
            "category":"Restaurant",
            "type":"Food & Drink"
        }
    ],
    "sg:phone":"+41 91 867 11 51",
    "sg:postcode":"6772",
    "sg:province":"Ticino",
    "wof:name":"Caff\u00e8 Gianella",
    "wof:placetype":"venue"
},
  "geometry": {"coordinates":[8.7379398346,46.4897994995],"type":"Point"}
}