{
  "type": "Feature",
  "properties": {
    "iso:country":"CH",
    "sg:address":"8566",
    "sg:city":"Lippoldswilen",
    "sg:orig_category":"Herstellung von sonstigen landwirtschaftlichen Maschinen Mechanik",
    "sg:phone":"+41 56 668 13 44",
    "sg:postcode":"8566",
    "sg:province":"Thurgau",
    "wof:name":"Franz K\u00fcng Ag",
    "wof:placetype":"venue"
},
  "geometry": {"coordinates":[8.3454179764,47.2320289612],"type":"Point"}
}