{
  "type": "Feature",
  "properties": {
    "iso:country":"CH",
    "sg:address":"En Bois-d\u00e9sert 1147 Montricher. Postfach",
    "sg:city":"Montricher",
    "sg:orig_category":"Schreib U \u00dcbersetzungsb\u00fcros",
    "sg:phone":"+41 21 864 52 95",
    "sg:postcode":"1147",
    "sg:province":"Vaud",
    "wof:name":"Fernhout Genevi\u00e8ve Traduction Anglais En Fran\u00e7ais",
    "wof:placetype":"venue"
},
  "geometry": {"coordinates":[6.378112793,46.6036148071],"type":"Point"}
}