{
  "type": "Feature",
  "properties": {
    "iso:country":"CH",
    "sg:address":"Place Du Bourg-de-four 22",
    "sg:city":"Gen\u00e8ve",
    "sg:orig_category":"Erbringung von Dienstleistungen f\u00fcr Unternehmen Kunsthandel",
    "sg:phone":"+41 62 756 08 08",
    "sg:postcode":"1204",
    "sg:province":"Gen\u00e8ve",
    "wof:name":"Qm-handels Gmbh Auktionshaus. Liegenschaften Usw",
    "wof:placetype":"venue"
},
  "geometry": {"coordinates":[7.9807572365,47.2135543823],"type":"Point"}
}