{
  "type": "Feature",
  "properties": {
    "iso:country":"CH",
    "sg:address":"Alte Bahnhofstrasse 8 3324 Hindelbank. Postfach",
    "sg:city":"Bern",
    "sg:orig_category":"Detailhandel mit Brot, Back U S\u00fcsswaren",
    "sg:postcode":"3005",
    "sg:province":"Bern",
    "wof:name":"Aryana B\u00e4ckerei Ag",
    "wof:placetype":"venue"
},
  "geometry": {"coordinates":[7.543481,47.048428],"type":"Point"}
}