{
  "type": "Feature",
  "properties": {
    "iso:country":"CH",
    "sg:address":"Champs-des-filles Chemin Du 33",
    "sg:city":"Plan-les-ouates",
    "sg:orig_category":"Kauf U Verkauf von Immobilien auf eigene Rechnung",
    "sg:phone":"+41 22 794 58 00",
    "sg:postcode":"1228",
    "sg:province":"Gen\u00e8ve",
    "wof:name":"Dunoyer Immobilier Sa",
    "wof:placetype":"venue"
},
  "geometry": {"coordinates":[6.1058897972,46.1654777527],"type":"Point"}
}