{
  "type": "Feature",
  "properties": {
    "iso:country":"CH",
    "sg:address":"Ried",
    "sg:city":"Sch\u00fcpbach",
    "sg:classifiers":[
        {
            "category":"Manufacturing",
            "subcategory":"Metals",
            "type":"Manufacturing & Wholesale Goods"
        }
    ],
    "sg:phone":"+41 34 497 11 44",
    "sg:postcode":"3535",
    "sg:province":"Bern",
    "sg:tags":[
        "cast",
        "unalloyed",
        "grey",
        "iron",
        "alloyed"
    ],
    "wof:name":"K\u00fcpfer Ag",
    "wof:placetype":"venue"
},
  "geometry": {"coordinates":[7.736743927,46.9297103882],"type":"Point"}
}