{
  "type": "Feature",
  "properties": {
    "iso:country":"CH",
    "sg:address":"Savi\u00e8se",
    "sg:city":"Savi\u00e8se",
    "sg:classifiers":[
        {
            "category":"Banks & Credit Unions",
            "subcategory":"Bank",
            "type":"Services"
        }
    ],
    "sg:phone":"+41 27 395 15 01",
    "sg:postcode":"1965",
    "sg:province":"Valais",
    "wof:name":"Soci\u00e9t\u00e9 De Banque Suisse",
    "wof:placetype":"venue"
},
  "geometry": {"coordinates":[7.338539,46.250473],"type":"Point"}
}