{
  "type": "Feature",
  "properties": {
    "iso:country":"CH",
    "sg:address":"Hauptstrasse 24",
    "sg:city":"Diessenhofen",
    "sg:orig_category":"Detailhandel mit Spielwaren Detailhandel mit S\u00e4uglings U Kinderbekleidung",
    "sg:postcode":"8253",
    "sg:province":"Thurgau",
    "wof:name":"Babaloo Kids Kindermode & Babybedarf",
    "wof:placetype":"venue"
},
  "geometry": {"coordinates":[9.8377895355,46.8068733215],"type":"Point"}
}