{
  "type": "Feature",
  "properties": {
    "iso:country":"CH",
    "sg:address":"Limmatquai 2",
    "sg:city":"Z\u00fcrich",
    "sg:orig_category":"Finanzierungsinstitutionen",
    "sg:postcode":"8001",
    "sg:province":"Z\u00fcrich",
    "wof:name":"Ilsebill Sa Anlage V. Kapitalien Usw",
    "wof:placetype":"venue"
},
  "geometry": {"coordinates":[8.5452203751,47.3677444458],"type":"Point"}
}