{
  "type": "Feature",
  "properties": {
    "iso:country":"CH",
    "sg:address":"Aarauerstrasse 26",
    "sg:city":"Muri",
    "sg:classifiers":[
        {
            "category":"Juice Bar",
            "subcategory":"None",
            "type":"Food & Drink"
        }
    ],
    "sg:phone":"+41 56 664 41 40",
    "sg:postcode":"5630",
    "sg:province":"Aargau",
    "sg:tags":[
        "apple"
    ],
    "wof:name":"Fremo Interdrink Ag",
    "wof:placetype":"venue"
},
  "geometry": {"coordinates":[8.336471,47.278793],"type":"Point"}
}