{
  "type": "Feature",
  "properties": {
    "iso:country":"CH",
    "sg:address":"Museumstrasse 1a",
    "sg:city":"Sarnen",
    "sg:orig_category":"Pensionskassen",
    "sg:phone":"+41 41 660 79 66",
    "sg:postcode":"6060",
    "sg:province":"Obwalden",
    "wof:name":"Personalversicherungskasse Des Kantons Obwalden",
    "wof:placetype":"venue"
},
  "geometry": {"coordinates":[8.2470903397,46.897819519],"type":"Point"}
}