{
  "type": "Feature",
  "properties": {
    "iso:country":"CH",
    "sg:address":"Avenue De La Harpe 27",
    "sg:city":"Lausanne",
    "sg:orig_category":"Sportvereine Eissport Curling",
    "sg:phone":"+41 21 617 46 77",
    "sg:postcode":"1007",
    "sg:province":"Vaud",
    "wof:name":"C.c.lausanne-olympique",
    "wof:placetype":"venue"
},
  "geometry": {"coordinates":[6.6261258125,46.5108413696],"type":"Point"}
}