{
  "type": "Feature",
  "properties": {
    "iso:country":"CH",
    "sg:address":"Avenue De La Gare 2",
    "sg:city":"Conthey",
    "sg:orig_category":"Handelskammern",
    "sg:phone":"+41 27 346 63 52",
    "sg:postcode":"1964",
    "sg:province":"Valais",
    "wof:name":"Chambre Valaisanne D'agriculture",
    "wof:placetype":"venue"
},
  "geometry": {"coordinates":[7.3042030334,46.217464447],"type":"Point"}
}