{
  "type": "Feature",
  "properties": {
    "iso:country":"CH",
    "sg:address":"Im Weingarten 8",
    "sg:city":"Kaltenbach",
    "sg:orig_category":"Bauingenieurb\u00fcros Tiefbau Bauingenieurb\u00fcros allgemein",
    "sg:phone":"+41 52 624 11 01",
    "sg:postcode":"8259",
    "sg:province":"Thurgau",
    "wof:name":"B\u00fcrgin Winzeler Partner Ag Ingenieurb\u00fcro F\u00fcr Tiefbau",
    "wof:placetype":"venue"
},
  "geometry": {"coordinates":[8.840363,47.650158],"type":"Point"}
}