{
  "type": "Feature",
  "properties": {
    "iso:country":"CH",
    "sg:address":"Bahnstrasse 102 8105 Regensdorf. Postfach",
    "sg:city":"Regensdorf",
    "sg:orig_category":"Satzherstellung U Reproduktion",
    "sg:postcode":"8105",
    "sg:province":"Z\u00fcrich",
    "wof:name":"Pixelnet Schweiz Ag Foto Und Bildmaterial; Entwicklung Und Bearbeitung Per Internet U. Per Post Usw",
    "wof:placetype":"venue"
},
  "geometry": {"coordinates":[8.4584140778,47.4442024231],"type":"Point"}
}