{
  "type": "Feature",
  "properties": {
    "iso:country":"CH",
    "sg:address":"Av. De La Gare.",
    "sg:city":"Aigle",
    "sg:orig_category":"Non-Classified Establishments",
    "sg:postcode":"1860",
    "sg:province":"Vaud",
    "wof:name":"Si Beau-site",
    "wof:placetype":"venue"
},
  "geometry": {"coordinates":[6.9647102356,46.3161048889],"type":"Point"}
}