{
  "type": "Feature",
  "properties": {
    "addr:full":"Blumenweg 17 9472 Grabs. Postfach Grabs St. Gallen 9472",
    "addr:housenumber":"17",
    "addr:postcode":"9472 grabs. postfach;9472",
    "addr:street":"Blumenweg",
    "iso:country":"CH",
    "sg:address":"Blumenweg 17 9472 Grabs. Postfach",
    "sg:city":"Grabs",
    "sg:orig_category":"Architektur U Ingenieurb\u00fcros Architekturb\u00fcros",
    "sg:phone":"+41 81 771 34 44",
    "sg:postcode":"9472",
    "sg:province":"St. Gallen",
    "wof:name":"Fuchs & Sutter Architekten Ag",
    "wof:placetype":"venue"
},
  "geometry": {"coordinates":[9.454039,47.178619],"type":"Point"}
}