{
  "type": "Feature",
  "properties": {
    "iso:country":"CH",
    "sg:address":"Route Du Nant-d'avril 107",
    "sg:city":"Meyrin",
    "sg:orig_category":"Grosshandel mit Milch, Milcherzeugnissen, Eiern, Speise\u00f6len U Nahrungsfetten",
    "sg:phone":"+41 22 780 15 30",
    "sg:postcode":"1217",
    "sg:province":"Gen\u00e8ve",
    "wof:name":"Petit Cr\u00e9mier Prod.laitiers Fromages Engros",
    "wof:placetype":"venue"
},
  "geometry": {"coordinates":[6.0722098351,46.2284393311],"type":"Point"}
}