{
  "type": "Feature",
  "properties": {
    "iso:country":"CH",
    "sg:address":"Hofstettenstrasse 8",
    "sg:city":"Thun",
    "sg:orig_category":"Arztpraxen",
    "sg:phone":"+41 33 222 03 53",
    "sg:postcode":"3600",
    "sg:province":"Bern",
    "wof:name":"Dr.med. Hans Habich Arzt F\u00fcr Allgemeine Medizin",
    "wof:placetype":"venue"
},
  "geometry": {"coordinates":[7.633422,46.757023],"type":"Point"}
}