{
  "type": "Feature",
  "properties": {
    "iso:country":"CH",
    "sg:address":"Bethlehemstrasse 40 3027 Bern. Postfach",
    "sg:city":"Bern",
    "sg:orig_category":"Pensionskassen",
    "sg:postcode":"3027",
    "sg:province":"Bern",
    "wof:name":"Hilfsfonds F\u00fcr Das Personal Der Firma Schwab Transportdienst Ag Bern",
    "wof:placetype":"venue"
},
  "geometry": {"coordinates":[7.3958301544,46.9467353821],"type":"Point"}
}