{
  "type": "Feature",
  "properties": {
    "iso:country":"CH",
    "sg:address":"Le Ch\u00e2teau",
    "sg:city":"Vaumarcus",
    "sg:orig_category":"Druck ohne Zeitungsdruck",
    "sg:postcode":"2028",
    "sg:province":"Neuch\u00e2tel",
    "wof:name":"Imprimerie De La Fontaine Des Eaux-vives Sa",
    "wof:placetype":"venue"
},
  "geometry": {"coordinates":[6.1293139458,46.2302589417],"type":"Point"}
}