{
  "type": "Feature",
  "properties": {
    "iso:country":"CH",
    "sg:address":"Nordstrasse 5 4665 Oftringen. Postfach",
    "sg:city":"Oftringen",
    "sg:orig_category":"Unclassifiable Establishments",
    "sg:postcode":"4665",
    "sg:province":"Aargau",
    "wof:name":"Alba Transporte Gmbh",
    "wof:placetype":"venue"
},
  "geometry": {"coordinates":[7.9294362068,47.3034706116],"type":"Point"}
}