{
  "type": "Feature",
  "properties": {
    "addr:full":"Rue Jean-calvin 2ter Gen\u00e8ve Gen\u00e8ve 1204",
    "addr:housenumber":"2ter",
    "addr:postcode":"1204",
    "addr:street":"Rue Jean-Calvin",
    "iso:country":"CH",
    "sg:address":"Rue Jean-calvin 2ter",
    "sg:city":"Gen\u00e8ve",
    "sg:orig_category":"Detailhandel mit B\u00fcchern Fachdetailhandel in Verkaufsr\u00e4umen",
    "sg:phone":"+41 22 310 47 57",
    "sg:postcode":"1204",
    "sg:province":"Gen\u00e8ve",
    "wof:name":"Galerie Bernard Letu Sa",
    "wof:placetype":"venue"
},
  "geometry": {"coordinates":[6.146221,46.202065],"type":"Point"}
}