{
  "type": "Feature",
  "properties": {
    "iso:country":"CH",
    "sg:address":"Les Places 38",
    "sg:city":"Glovelier",
    "sg:orig_category":"Sonstiger Grosshandel",
    "sg:postcode":"2855",
    "sg:province":"Jura",
    "wof:name":"Crea-com.ch S\u00e0rl",
    "wof:placetype":"venue"
},
  "geometry": {"coordinates":[7.2106890678,47.3404197693],"type":"Point"}
}