{
  "type": "Feature",
  "properties": {
    "iso:country":"CH",
    "sg:address":"Kleinzelglistrasse 6/4211",
    "sg:city":"Schlieren",
    "sg:orig_category":"Handelsvermittlung U Grosshandel R\u00fcckgewinnung U Vorbereitung f\u00fcr die Wiederverwertung Recycling",
    "sg:phone":"+41 79 661 05 11",
    "sg:postcode":"8952",
    "sg:province":"Z\u00fcrich",
    "wof:name":"Walter Spycher Alteisen & Metalle",
    "wof:placetype":"venue"
},
  "geometry": {"coordinates":[8.4334564209,47.3961791992],"type":"Point"}
}