{
  "type": "Feature",
  "properties": {
    "iso:country":"CH",
    "sg:address":"Ch\u00e4lenweg",
    "sg:city":"Aathal-seegr\u00e4ben",
    "sg:orig_category":"Landwirtschaft, Jagd U damit verbundene Dienstleistungen",
    "sg:phone":"+41 17151704",
    "sg:postcode":"8607",
    "sg:province":"Z\u00fcrich",
    "wof:name":"Gutsbetrieb Uf-stocken",
    "wof:placetype":"venue"
},
  "geometry": {"coordinates":[8.5402059555,47.3231391907],"type":"Point"}
}