{
  "type": "Feature",
  "properties": {
    "addr:full":"Dammstrasse 11 Burgdorf Bern 3400",
    "addr:housenumber":"11",
    "addr:postcode":"3400",
    "addr:street":"Dammstrasse",
    "iso:country":"CH",
    "sg:address":"Dammstrasse 11",
    "sg:city":"Burgdorf",
    "sg:orig_category":"Detailhandel mit Beleuchtungs U Haushaltsgegenst\u00e4nden Innendekorationsateliers",
    "sg:phone":"+41 34 422 76 59",
    "sg:postcode":"3400",
    "sg:province":"Bern",
    "wof:name":"Hedy Jufer Wohnboutique",
    "wof:placetype":"venue"
},
  "geometry": {"coordinates":[7.623262,47.062042],"type":"Point"}
}