{
  "type": "Feature",
  "properties": {
    "iso:country":"CH",
    "sg:address":"Steinenvorstadt 13",
    "sg:city":"Basel",
    "sg:orig_category":"Unclassifiable Establishments",
    "sg:postcode":"4051",
    "sg:province":"Basel-Stadt",
    "wof:name":"Avaloq Group Ag",
    "wof:placetype":"venue"
},
  "geometry": {"coordinates":[8.7330341339,47.2001991272],"type":"Point"}
}