{
  "type": "Feature",
  "properties": {
    "iso:country":"CH",
    "sg:address":"Croix-rouges Chemin Des 22 1007 Lausanne. Postfach",
    "sg:city":"Lausanne",
    "sg:orig_category":"Korrespondenz U Nachrichtenb\u00fcros, selbst\u00e4ndige Journalisten",
    "sg:postcode":"1003",
    "sg:province":"Vaud",
    "wof:name":"Zebra Productions, Tharin Jo\u00eblle & Pittet Christophe R\u00e9alisation De Reportages",
    "wof:placetype":"venue"
},
  "geometry": {"coordinates":[6.6192188263,46.5200119019],"type":"Point"}
}