{
  "type": "Feature",
  "properties": {
    "iso:country":"CH",
    "sg:address":"Grand-rue 42 1616 Attalens. Postfach",
    "sg:city":"Attalens",
    "sg:orig_category":"Fachdetailhandel in Verkaufsr\u00e4umen",
    "sg:phone":"+41 21 947 59 64",
    "sg:postcode":"1616",
    "sg:province":"Fribourg",
    "wof:name":"Aquadeal Sa",
    "wof:placetype":"venue"
},
  "geometry": {"coordinates":[6.8484601974,46.5100593567],"type":"Point"}
}