{
  "type": "Feature",
  "properties": {
    "iso:country":"CH",
    "sg:address":"Rosenweg 1",
    "sg:city":"Muhen",
    "sg:orig_category":"Detailhandel mit Metallwaren, Anstrichmitteln, Glaswaren, Bau U Heimwerkerbedarf Sonstige technische",
    "sg:phone":"+41 62 723 27 24",
    "sg:postcode":"5037",
    "sg:province":"Aargau",
    "wof:name":"Resatec Ag",
    "wof:placetype":"venue"
},
  "geometry": {"coordinates":[8.0529823303,47.3398399353],"type":"Point"}
}