{
  "type": "Feature",
  "properties": {
    "iso:country":"CH",
    "sg:address":"L\u00e4ndtestrasse 4",
    "sg:city":"Schwarzh\u00e4usern",
    "sg:orig_category":"Detailhandel mit Waren verschiedener Art, Hauptrichtung Nahrungsmittel",
    "sg:phone":"+41 62 922 30 82",
    "sg:postcode":"4911",
    "sg:province":"Bern",
    "wof:name":"Willy Bohnenblust Lebensmittelgesch\u00e4ft",
    "wof:placetype":"venue"
},
  "geometry": {"coordinates":[7.7664937973,47.2512359619],"type":"Point"}
}