{
  "type": "Feature",
  "properties": {
    "iso:country":"CH",
    "sg:address":"Kantonsstrasse",
    "sg:city":"Gettnau",
    "sg:orig_category":"Wasserversorgung",
    "sg:phone":"+41 41 970 23 19",
    "sg:postcode":"6142",
    "sg:province":"Luzern",
    "wof:name":"Wasserversorgung Gettnau",
    "wof:placetype":"venue"
},
  "geometry": {"coordinates":[7.9513301849,47.1363105774],"type":"Point"}
}