{
  "type": "Feature",
  "properties": {
    "iso:country":"CH",
    "sg:address":"Les Cluds",
    "sg:city":"Bullet",
    "sg:classifiers":[
        {
            "category":"Restaurant",
            "type":"Food & Drink"
        }
    ],
    "sg:phone":"+41 24 454 25 94",
    "sg:postcode":"1453",
    "sg:province":"Vaud",
    "wof:name":"Caf\u00e9 Des Cluds",
    "wof:placetype":"venue"
},
  "geometry": {"coordinates":[6.5607199669,46.8430900574],"type":"Point"}
}