{
  "type": "Feature",
  "properties": {
    "iso:country":"CH",
    "sg:address":"Buchenweg 8",
    "sg:city":"Kriens",
    "sg:orig_category":"Architektur U Ingenieurb\u00fcros",
    "sg:phone":"+41 41 320 85 20",
    "sg:postcode":"6010",
    "sg:province":"Luzern",
    "wof:name":"Dr.walter Zellweger Ingenieurb\u00fcro",
    "wof:placetype":"venue"
},
  "geometry": {"coordinates":[8.275931,47.037472],"type":"Point"}
}