{
  "type": "Feature",
  "properties": {
    "iso:country":"CH",
    "sg:address":"Furrenstrasse 3",
    "sg:city":"Unter\u00e4geri",
    "sg:orig_category":"Elektroinstallation",
    "sg:postcode":"6314",
    "sg:province":"Zug",
    "wof:name":"Elektro Und Telefoninstallationen Henggeler.",
    "wof:placetype":"venue"
},
  "geometry": {"coordinates":[8.5715913773,47.1380767822],"type":"Point"}
}