{
  "type": "Feature",
  "properties": {
    "iso:country":"CH",
    "sg:address":"Grabmattweg 3 2545 Selzach. Postfach",
    "sg:city":"Selzach",
    "sg:orig_category":"Hobel U Holzimpr\u00e4gnierwerke Mechanik",
    "sg:phone":"+41 32 641 32 32",
    "sg:postcode":"2545",
    "sg:province":"Solothurn",
    "wof:name":"Tamburrino Domenico",
    "wof:placetype":"venue"
},
  "geometry": {"coordinates":[7.4540491104,47.2019424438],"type":"Point"}
}