{
  "type": "Feature",
  "properties": {
    "iso:country":"CH",
    "sg:address":"Oberer Moosweg 7",
    "sg:city":"Grellingen",
    "sg:orig_category":"Herstellung von Pflanzenschutzmitteln U sonstigen agro- chemikalischen Erzeugnissen",
    "sg:postcode":"4203",
    "sg:province":"Basel-Landschaft",
    "wof:name":"Rbd Dienstleistungen Borer Ren\u00e9",
    "wof:placetype":"venue"
},
  "geometry": {"coordinates":[7.5883669853,47.4399414062],"type":"Point"}
}