{
  "type": "Feature",
  "properties": {
    "iso:country":"CH",
    "sg:address":"Buchzelgstrasse 64 8053 Z\u00fcrich. Postfach",
    "sg:city":"Z\u00fcrich",
    "sg:orig_category":"Gesundheitswesen",
    "sg:postcode":"8053",
    "sg:province":"Z\u00fcrich",
    "wof:name":"Iba Imageberatung Ackermann Imageberatungen F\u00fcr Damen Und Herren. Einzel, Gruppenberatungen Usw",
    "wof:placetype":"venue"
},
  "geometry": {"coordinates":[9.3974847794,47.4323272705],"type":"Point"}
}