{
  "type": "Feature",
  "properties": {
    "iso:country":"CH",
    "sg:address":"Bergstrasse 27a",
    "sg:city":"Urdorf",
    "sg:orig_category":"Geb\u00e4ude, Wohnungsreinigung",
    "sg:phone":"+41 41 760 46 53",
    "sg:postcode":"8902",
    "sg:province":"Z\u00fcrich",
    "wof:name":"Pyramid-services Gmbh Reinigungsunternehmung",
    "wof:placetype":"venue"
},
  "geometry": {"coordinates":[8.5257787704,47.1942024231],"type":"Point"}
}