{
  "type": "Feature",
  "properties": {
    "iso:country":"CH",
    "sg:address":"Freiestrasse 96 8032 Z\u00fcrich",
    "sg:city":"Zust",
    "sg:orig_category":"RESTAURANTS: TEA-ROOMS",
    "sg:postcode":"32",
    "wof:name":"Yellow Productions Gmbh",
    "wof:placetype":"venue"
},
  "geometry": {"coordinates":[8.5679702759,47.3668403625],"type":"Point"}
}