{
  "type": "Feature",
  "properties": {
    "iso:country":"CH",
    "sg:address":"Br\u00fcnigstrase 70",
    "sg:city":"Sachseln",
    "sg:orig_category":"Sportvereine Turnen",
    "sg:phone":"+41 41 660 10 62",
    "sg:postcode":"6072",
    "sg:province":"Obwalden",
    "wof:name":"Ktsv Sachseln",
    "wof:placetype":"venue"
},
  "geometry": {"coordinates":[8.2417058945,46.8709869385],"type":"Point"}
}