{
  "type": "Feature",
  "properties": {
    "iso:country":"CH",
    "sg:address":"Oberdorfstrasse 58",
    "sg:city":"Zermatt",
    "sg:orig_category":"Detailhandel mit Brennstoffen U Heizmaterial",
    "sg:phone":"+41 71 282 85 50",
    "sg:postcode":"3920",
    "sg:province":"Valais",
    "wof:name":"Ganz & Co Ag",
    "wof:placetype":"venue"
},
  "geometry": {"coordinates":[9.238832,47.418213],"type":"Point"}
}