{
  "type": "Feature",
  "properties": {
    "iso:country":"CH",
    "sg:address":"Belmontstrasse 9",
    "sg:city":"Chur",
    "sg:orig_category":"Fahrschulen, Flugschulen",
    "sg:postcode":"7000",
    "sg:province":"Graubunden",
    "wof:name":"Brechelmacher L.",
    "wof:placetype":"venue"
},
  "geometry": {"coordinates":[9.5266561508,46.8618469238],"type":"Point"}
}