{
  "type": "Feature",
  "properties": {
    "iso:country":"CH",
    "sg:address":"Via San Gotthardo 8",
    "sg:city":"Balerna",
    "sg:orig_category":"Handel mit Automobilen Sonstiger Grosshandel",
    "sg:phone":"+41 91 682 12 61",
    "sg:postcode":"6828",
    "sg:province":"Ticino",
    "wof:name":"Easy System Sagl",
    "wof:placetype":"venue"
},
  "geometry": {"coordinates":[9.0194854736,45.8397979736],"type":"Point"}
}