{
  "type": "Feature",
  "properties": {
    "addr:full":"Belchenstrasse 2a Basel Basel-Stadt 4054",
    "addr:housenumber":"2a",
    "addr:postcode":"4054",
    "addr:street":"Belchenstrasse",
    "iso:country":"CH",
    "sg:address":"Belchenstrasse 2a",
    "sg:city":"Basel",
    "sg:orig_category":"Bauschreinerei Herstellung von Metallkonstruktionen",
    "sg:phone":"+41 61 301 89 72",
    "sg:postcode":"4054",
    "sg:province":"Basel-Stadt",
    "wof:name":"Stolz Montagen Gmbh",
    "wof:placetype":"venue"
},
  "geometry": {"coordinates":[7.57391,47.554298],"type":"Point"}
}