{
  "type": "Feature",
  "properties": {
    "iso:country":"CH",
    "sg:address":"Waldstrasse 11",
    "sg:city":"Biberist",
    "sg:orig_category":"Detailhandel mit Haustieren U zoologischem Bedarf",
    "sg:phone":"+41 32 672 40 24",
    "sg:postcode":"4562",
    "sg:province":"Solothurn",
    "wof:name":"Silvano Bianchi Pet-shop Beo",
    "wof:placetype":"venue"
},
  "geometry": {"coordinates":[7.555434227,47.1874504089],"type":"Point"}
}