{
  "type": "Feature",
  "properties": {
    "iso:country":"CH",
    "sg:address":"Oberneuhofstrasse 5",
    "sg:city":"Baar",
    "sg:orig_category":"Non-Classified Establishments",
    "sg:postcode":"6340",
    "sg:province":"Zug",
    "wof:name":"Sardognola Rosaria Santandrea",
    "wof:placetype":"venue"
},
  "geometry": {"coordinates":[6.1379261017,46.1797676086],"type":"Point"}
}