{
  "type": "Feature",
  "properties": {
    "iso:country":"CH",
    "sg:address":"Rue Des P\u00e2quis 45",
    "sg:city":"Gen\u00e8ve",
    "sg:orig_category":"Detailhandel mit Bekleidung Herstellung von konfektionierten Textilwaren ohne Bekleidung",
    "sg:phone":"+41 22 731 78 36",
    "sg:postcode":"1201",
    "sg:province":"Gen\u00e8ve",
    "wof:name":"Angelo Argentini",
    "wof:placetype":"venue"
},
  "geometry": {"coordinates":[6.149926,46.212826],"type":"Point"}
}