{
  "type": "Feature",
  "properties": {
    "iso:country":"CH",
    "sg:address":"Hofstrasse 3 8590 Romanshorn. Postfach",
    "sg:city":"Romanshorn",
    "sg:orig_category":"Sonstiger Grosshandel Unternehmensberatung",
    "sg:phone":"+41 62 212 92 22",
    "sg:postcode":"8590",
    "sg:province":"Thurgau",
    "wof:name":"M\u00fcller Management Sa Waren; Handel. Unternehmensberatung",
    "wof:placetype":"venue"
},
  "geometry": {"coordinates":[7.2665920258,47.123046875],"type":"Point"}
}