{
  "type": "Feature",
  "properties": {
    "iso:country":"CH",
    "sg:address":"Rte D'alle 58 Case Postale 1212",
    "sg:city":"Porrentruy",
    "sg:classifiers":[
        {
            "category":"Shopping",
            "type":"Retail Goods"
        }
    ],
    "sg:phone":"+41 4117252911",
    "sg:postcode":"2900",
    "sg:province":"Jura",
    "sg:tags":[
        "metallurgy",
        "finished",
        "-",
        "metalworking",
        "metallic"
    ],
    "wof:name":"Ernst Sch\u00c4ppi & Co Ag",
    "wof:placetype":"venue"
},
  "geometry": {"coordinates":[8.5859947205,47.2586326599],"type":"Point"}
}