{
  "type": "Feature",
  "properties": {
    "iso:country":"CH",
    "sg:address":"Tramstrasse 121",
    "sg:city":"Suhr",
    "sg:orig_category":"Massagestudios",
    "sg:phone":"+41 62 824 22 30",
    "sg:postcode":"5034",
    "sg:province":"Aargau",
    "wof:name":"Praxis Im Feld Massagen",
    "wof:placetype":"venue"
},
  "geometry": {"coordinates":[8.0663328171,47.3872184753],"type":"Point"}
}