{
  "type": "Feature",
  "properties": {
    "iso:country":"CH",
    "sg:address":"1986",
    "sg:city":"Arolla",
    "sg:orig_category":"Sportschulen Ski-& Snowboardschulen",
    "sg:phone":"+41 27 283 15 50",
    "sg:postcode":"1986",
    "sg:province":"Valais",
    "wof:name":"Ecole Suisse De Ski D'arolla Monsieur Camille Bournissen",
    "wof:placetype":"venue"
},
  "geometry": {"coordinates":[7.4876799583,46.0387115479],"type":"Point"}
}