{
  "type": "Feature",
  "properties": {
    "iso:country":"CH",
    "sg:address":"Langg\u00fcetlistrasse 2",
    "sg:city":"Netstal",
    "sg:orig_category":"Detailhandel mit Waren verschiedener Art, Hauptrichtung Nahrungsmittel Grosshandel mit Nahrungsmitte",
    "sg:phone":"+41 55 640 24 58",
    "sg:postcode":"8754",
    "sg:province":"Glarus",
    "wof:name":"Sch\u00fctz Werner, Giro-laden",
    "wof:placetype":"venue"
},
  "geometry": {"coordinates":[9.0580501556,47.0630989075],"type":"Point"}
}