{
  "type": "Feature",
  "properties": {
    "iso:country":"CH",
    "sg:address":"General-guisan-strasse 4",
    "sg:city":"Zofingen",
    "sg:classifiers":[
        {
            "category":"Social Services",
            "subcategory":"Retirement Home",
            "type":"Services"
        }
    ],
    "sg:phone":"+41 62 751 18 01",
    "sg:postcode":"4800",
    "sg:province":"Aargau",
    "sg:tags":[
        "pflegeheime",
        "u",
        "alters"
    ],
    "wof:name":"Altersheim Blumenheim",
    "wof:placetype":"venue"
},
  "geometry": {"coordinates":[7.947489,47.286564],"type":"Point"}
}