{
  "type": "Feature",
  "properties": {
    "iso:country":"CH",
    "sg:address":"Via Speranza 5",
    "sg:city":"Lugano",
    "sg:orig_category":"Allgemeiner Hoch U Tiefbau",
    "sg:postcode":"6900",
    "sg:province":"Ticino",
    "wof:name":"Manugen Di Paparelli A.",
    "wof:placetype":"venue"
},
  "geometry": {"coordinates":[8.961562,46.009354],"type":"Point"}
}