{
  "type": "Feature",
  "properties": {
    "iso:country":"CH",
    "sg:address":"Via Locarno 42",
    "sg:city":"Ascona",
    "sg:orig_category":"Selbst\u00e4ndige bildende K\u00fcnstler",
    "sg:phone":"+41 91 791 29 29",
    "sg:postcode":"6612",
    "sg:province":"Ticino",
    "wof:name":"Paul Vogt Scultore In Pietra",
    "wof:placetype":"venue"
},
  "geometry": {"coordinates":[8.7726612091,46.1589431763],"type":"Point"}
}