{
  "type": "Feature",
  "properties": {
    "iso:country":"CH",
    "sg:address":"G\u00fcterstrasse 4",
    "sg:city":"Buochs",
    "sg:orig_category":"Sportvereine Sch\u00fctzen Bogen",
    "sg:phone":"+41 41 620 01 10",
    "sg:postcode":"6374",
    "sg:province":"Nidwalden",
    "wof:name":"Bogensch\u00fctzen Lsc",
    "wof:placetype":"venue"
},
  "geometry": {"coordinates":[8.4163408279,46.9706611633],"type":"Point"}
}