{
  "type": "Feature",
  "properties": {
    "iso:country":"CH",
    "sg:address":"Hauptstrasse 59",
    "sg:city":"Derendingen",
    "sg:orig_category":"Autogaragen",
    "sg:phone":"+41 32 682 38 31",
    "sg:postcode":"4552",
    "sg:province":"Solothurn",
    "wof:name":"Rank-garage",
    "wof:placetype":"venue"
},
  "geometry": {"coordinates":[7.587354,47.193066],"type":"Point"}
}