{
  "type": "Feature",
  "properties": {
    "iso:country":"CH",
    "sg:address":"Unterdorf 27 8752 N\u00e4fels. Postfach",
    "sg:city":"N\u00e4fels",
    "sg:orig_category":"RESTAURANTS: TEA-ROOMS",
    "sg:postcode":"8752",
    "sg:province":"Glarus",
    "wof:name":"Adler Betriebs Gmbh",
    "wof:placetype":"venue"
},
  "geometry": {"coordinates":[9.050078392,47.4631996155],"type":"Point"}
}