{
  "type": "Feature",
  "properties": {
    "iso:country":"CH",
    "sg:address":"1663",
    "sg:city":"Gruy\u00e8res",
    "sg:orig_category":"Vermietung U Verpachtung von eigenen Immobilien",
    "sg:postcode":"1663",
    "sg:province":"Fribourg",
    "wof:name":"Fondation Du Ch\u00e2teau St-germain",
    "wof:placetype":"venue"
},
  "geometry": {"coordinates":[7.0800590515,46.5818748474],"type":"Point"}
}