{
  "type": "Feature",
  "properties": {
    "iso:country":"CH",
    "sg:address":"Route De Nyon 27",
    "sg:city":"Borex",
    "sg:orig_category":"Fachdetailhandel in Verkaufsr\u00e4umen Handel mit Motorr\u00e4dern, Teilen U Zubeh\u00f6r Instandhaltung U Reparat",
    "sg:phone":"+41 22 367 13 15",
    "sg:postcode":"1277",
    "sg:province":"Vaud",
    "wof:name":"Berthoud Jacques",
    "wof:placetype":"venue"
},
  "geometry": {"coordinates":[6.1857118607,46.3801269531],"type":"Point"}
}