{
  "type": "Feature",
  "properties": {
    "iso:country":"CH",
    "sg:address":"Avenue Abraham Hermanjat 47",
    "sg:city":"Aubonne",
    "sg:orig_category":"Tierarztpraxis",
    "sg:phone":"+41 21 808 64 64",
    "sg:postcode":"1170",
    "sg:province":"Vaud",
    "wof:name":"Dr M\u00e9d. V\u00e9t. Michel Pilloud M\u00e9decin V\u00e9t\u00e9rinaire",
    "wof:placetype":"venue"
},
  "geometry": {"coordinates":[6.3873529434,46.4914932251],"type":"Point"}
}