{
  "type": "Feature",
  "properties": {
    "addr:full":"Steinackerstrasse 34 Kloten Z\u00fcrich 8302",
    "addr:housenumber":"34",
    "addr:postcode":"8302",
    "addr:street":"Steinackerstrasse",
    "iso:country":"CH",
    "sg:address":"Steinackerstrasse 34",
    "sg:city":"Kloten",
    "sg:classifiers":[
        {
            "category":"Shopping",
            "subcategory":"Computers & Home Electronics",
            "type":"Retail Goods"
        }
    ],
    "sg:phone":"+41 43 255 46 00",
    "sg:postcode":"8302",
    "sg:province":"Z\u00fcrich",
    "sg:tags":[
        "client-server",
        "software"
    ],
    "wof:name":"Softm Software Und Beratung (schweiz) Ag",
    "wof:placetype":"venue"
},
  "geometry": {"coordinates":[8.600313,47.448463],"type":"Point"}
}