{
  "type": "Feature",
  "properties": {
    "addr:full":"Z\u00fcrcherstrasse 305 Frauenfeld Thurgau 8500",
    "addr:housenumber":"305",
    "addr:postcode":"8500",
    "addr:street":"Zuercherstrasse",
    "iso:country":"CH",
    "sg:address":"Z\u00fcrcherstrasse 305",
    "sg:city":"Frauenfeld",
    "sg:orig_category":"Detailhandel mit Beleuchtungs U Haushaltsgegenst\u00e4nden Einbau von Schreinerwaren",
    "sg:phone":"+41 32 926 11 50",
    "sg:postcode":"8500",
    "sg:province":"Thurgau",
    "wof:name":"Fust Sa",
    "wof:placetype":"venue"
},
  "geometry": {"coordinates":[6.801,47.086208],"type":"Point"}
}