{
  "type": "Feature",
  "properties": {
    "iso:country":"CH",
    "sg:address":"L\u00e4ttichstrasse 8 6340 Baar. Postfach 438",
    "sg:city":"Baar",
    "sg:orig_category":"Unternehmensberatung",
    "sg:phone":"+41 62 797 55 34",
    "sg:postcode":"6341",
    "sg:province":"Zug",
    "wof:name":"Kehl Hansruedi Gmbh",
    "wof:placetype":"venue"
},
  "geometry": {"coordinates":[7.7069501877,46.6308898926],"type":"Point"}
}