{
  "type": "Feature",
  "properties": {
    "iso:country":"CH",
    "sg:address":"Emil Frey-strasse 181b 4142 M\u00fcnchenstein. Postfach",
    "sg:city":"M\u00fcnchenstein",
    "sg:orig_category":"Sonstige pers\u00f6nliche Dienstleistungen",
    "sg:phone":"+41 61 411 98 90",
    "sg:postcode":"4142",
    "sg:province":"Basel-Landschaft",
    "wof:name":"Gartmann-maurer Franziska Schulung, Beratung Aller Art",
    "wof:placetype":"venue"
},
  "geometry": {"coordinates":[7.6120901108,47.5281486511],"type":"Point"}
}