{
  "type": "Feature",
  "properties": {
    "addr:full":"1791 Courtaman Fribourg 1791",
    "addr:housenumber":"1791",
    "addr:postcode":"1791",
    "addr:street":"Courtaman Fribourg",
    "iso:country":"CH",
    "sg:address":"1791",
    "sg:city":"Courtaman",
    "sg:orig_category":"Bauschreinerei Einbau von Schreinerwaren",
    "sg:phone":"+41 26 684 12 88",
    "sg:postcode":"1791",
    "sg:province":"Fribourg",
    "wof:name":"Bernard Haas Cuisines & Menuiserie",
    "wof:placetype":"venue"
},
  "geometry": {"coordinates":[7.13106,46.871941],"type":"Point"}
}