{
  "type": "Feature",
  "properties": {
    "iso:country":"CH",
    "sg:address":"8627",
    "sg:city":"Gr\u00fcningen",
    "sg:orig_category":"Wasserversorgung",
    "sg:phone":"+41 19322388",
    "sg:postcode":"8627",
    "sg:province":"Z\u00fcrich",
    "wof:name":"Wasserversorgung Gr\u00fct & Gossau Zh",
    "wof:placetype":"venue"
},
  "geometry": {"coordinates":[8.785369873,47.3070907593],"type":"Point"}
}