{
  "type": "Feature",
  "properties": {
    "iso:country":"CH",
    "sg:address":"Rue Guillaume-techtermann 8",
    "sg:city":"Fribourg",
    "sg:orig_category":"Kinderkrippen U horte",
    "sg:phone":"+41 32 926 01 49",
    "sg:postcode":"1700",
    "sg:province":"Fribourg",
    "wof:name":"Cr\u00e8che Du Paradis",
    "wof:placetype":"venue"
},
  "geometry": {"coordinates":[6.8164992332,47.0961074829],"type":"Point"}
}