{
  "type": "Feature",
  "properties": {
    "iso:country":"CH",
    "sg:address":"9479",
    "sg:city":"Oberschan",
    "sg:orig_category":"Massagestudios",
    "sg:phone":"+41 81 783 20 40",
    "sg:postcode":"9479",
    "sg:province":"St. Gallen",
    "wof:name":"Cellsan Massagen",
    "wof:placetype":"venue"
},
  "geometry": {"coordinates":[9.4745798111,47.0990982056],"type":"Point"}
}