{
  "type": "Feature",
  "properties": {
    "iso:country":"CH",
    "sg:address":"Staatsstrasse 14",
    "sg:city":"Niederb\u00fcren",
    "sg:orig_category":"Herstellung von sonstigen Maschinen f\u00fcr unspezifische Verwendung",
    "sg:postcode":"9246",
    "sg:province":"St. Gallen",
    "wof:name":"Eisenegger Gmbh",
    "wof:placetype":"venue"
},
  "geometry": {"coordinates":[9.2004146576,47.4648971558],"type":"Point"}
}