{
  "type": "Feature",
  "properties": {
    "addr:full":"Elestastrasse Bad Ragaz St. Gallen 7310",
    "addr:postcode":"7310",
    "addr:street":"Elestastrasse Bad Ragaz",
    "iso:country":"CH",
    "sg:address":"Elestastrasse",
    "sg:city":"Bad Ragaz",
    "sg:classifiers":[
        {
            "category":"Banks & Credit Unions",
            "subcategory":"Bank",
            "type":"Services"
        }
    ],
    "sg:phone":"+41 81 302 82 41",
    "sg:postcode":"7310",
    "sg:province":"St. Gallen",
    "wof:name":"St. Gallische Kantonalbank",
    "wof:placetype":"venue"
},
  "geometry": {"coordinates":[9.50327,47.011555],"type":"Point"}
}