{
  "type": "Feature",
  "properties": {
    "iso:country":"CH",
    "sg:address":"Weingartenstrasse 9",
    "sg:city":"R\u00fcschlikon",
    "sg:orig_category":"Biological Process Technology",
    "sg:phone":"+41 17240888",
    "sg:postcode":"8803",
    "sg:province":"Z\u00fcrich",
    "wof:name":"Ytron F. Mundwiler & Co Ag",
    "wof:placetype":"venue"
},
  "geometry": {"coordinates":[8.554101,47.307831],"type":"Point"}
}