{
  "type": "Feature",
  "properties": {
    "iso:country":"CH",
    "sg:address":"Eigerweg 4 2563 Ipsach. Postfach 365",
    "sg:city":"Biel/bienne",
    "sg:orig_category":"Werbung",
    "sg:phone":"+41 32 323 31 61",
    "sg:postcode":"2500",
    "sg:province":"Bern",
    "wof:name":"Petraglio Hortense",
    "wof:placetype":"venue"
},
  "geometry": {"coordinates":[7.2374539375,47.1106452942],"type":"Point"}
}