{
  "type": "Feature",
  "properties": {
    "iso:country":"CH",
    "sg:address":"M\u00fclhauserstrasse 117 4000 Basel. Postfach",
    "sg:city":"Basel",
    "sg:orig_category":"Non-Classified Establishments",
    "sg:postcode":"4051",
    "sg:province":"Basel-Stadt",
    "wof:name":"Kosmetik-institut Dongiovanni Isabella",
    "wof:placetype":"venue"
},
  "geometry": {"coordinates":[7.576529026,47.5666770935],"type":"Point"}
}