{
  "type": "Feature",
  "properties": {
    "iso:country":"CH",
    "sg:address":"Rue Du Viaduc 21",
    "sg:city":"Moutier",
    "sg:classifiers":[
        {
            "category":"Banks & Credit Unions",
            "subcategory":"Investment Brokerage",
            "type":"Services"
        }
    ],
    "sg:phone":"+41 32 493 31 04",
    "sg:postcode":"2740",
    "sg:province":"Bern",
    "sg:tags":[
        "article",
        "production",
        "metal",
        "mass"
    ],
    "wof:name":"Michel Imhof S.a.",
    "wof:placetype":"venue"
},
  "geometry": {"coordinates":[7.372793,47.277477],"type":"Point"}
}