{
  "type": "Feature",
  "properties": {
    "iso:country":"CH",
    "sg:address":"Moosstrasse 5a",
    "sg:city":"Menzingen",
    "sg:orig_category":"Sonstige mit der Informatik verbundene T\u00e4tigkeiten",
    "sg:postcode":"6313",
    "sg:province":"Zug",
    "wof:name":"Roth It-secure Gmbh",
    "wof:placetype":"venue"
},
  "geometry": {"coordinates":[8.6004447937,47.174282074],"type":"Point"}
}