{
  "type": "Feature",
  "properties": {
    "addr:full":"Avenue De La Gare 3 Sierre Valais 3960",
    "addr:housenumber":"3",
    "addr:postcode":"3960",
    "addr:street":"Avenue De La Gare",
    "iso:country":"CH",
    "sg:address":"Avenue De La Gare 3",
    "sg:city":"Sierre",
    "sg:orig_category":"Arztpraxen",
    "sg:phone":"+41 27 456 30 30",
    "sg:postcode":"3960",
    "sg:province":"Valais",
    "wof:name":"Pd Dr M\u00e9d. Patrick Ruedin M\u00e9decin Sp\u00e9cialiste Fmh",
    "wof:placetype":"venue"
},
  "geometry": {"coordinates":[7.532301,46.292416],"type":"Point"}
}