{
  "type": "Feature",
  "properties": {
    "iso:country":"CH",
    "sg:address":"Fabrikstrasse 50",
    "sg:city":"Utzenstorf",
    "sg:orig_category":"Sonstige mit Sport verbundene T\u00e4tigkeiten",
    "sg:postcode":"3427",
    "sg:province":"Bern",
    "wof:name":"Reitsportanlage Landshut Ag",
    "wof:placetype":"venue"
},
  "geometry": {"coordinates":[7.5472798347,47.1442108154],"type":"Point"}
}