{
  "type": "Feature",
  "properties": {
    "iso:country":"CH",
    "sg:address":"Othmarstrasse 8 8008 Z\u00fcrich. Postfach 2067",
    "sg:city":"Z\u00fcrich",
    "sg:orig_category":"Finanzierungsinstitutionen",
    "sg:phone":"+41 41 632 62 88",
    "sg:postcode":"8032",
    "sg:province":"Z\u00fcrich",
    "wof:name":"Atlas Industrie & Entwicklung Ag",
    "wof:placetype":"venue"
},
  "geometry": {"coordinates":[8.3148832321,46.9920654297],"type":"Point"}
}