{
  "type": "Feature",
  "properties": {
    "iso:country":"CH",
    "sg:address":"Quai Du Seujet 28",
    "sg:city":"Gen\u00e8ve",
    "sg:orig_category":"Versicherungen Generalagenturen",
    "sg:phone":"+41 22 741 51 51",
    "sg:postcode":"1201",
    "sg:province":"Gen\u00e8ve",
    "wof:name":"La Suisse Assurances Agence G\u00e9n\u00e9rale",
    "wof:placetype":"venue"
},
  "geometry": {"coordinates":[6.1341490746,46.2044487],"type":"Point"}
}