{
  "type": "Feature",
  "properties": {
    "iso:country":"CH",
    "sg:address":"Rue Du Bourg 26",
    "sg:city":"Aigle",
    "sg:orig_category":"Grosshandel mit Getr\u00e4nken",
    "sg:postcode":"1860",
    "sg:province":"Vaud",
    "wof:name":"Pazos Victor",
    "wof:placetype":"venue"
},
  "geometry": {"coordinates":[6.968556881,46.3189239502],"type":"Point"}
}