{
  "type": "Feature",
  "properties": {
    "iso:country":"CH",
    "sg:address":"Sinserstrasse 65",
    "sg:city":"Cham",
    "sg:orig_category":"Lagerh\u00e4user, G\u00fcterumschlag, Verteilzentren",
    "sg:phone":"+41 81500383",
    "sg:postcode":"6330",
    "sg:province":"Zug",
    "wof:name":"Replay Warehouse Ag",
    "wof:placetype":"venue"
},
  "geometry": {"coordinates":[8.4521436691,47.1873893738],"type":"Point"}
}