{
  "type": "Feature",
  "properties": {
    "iso:country":"CH",
    "sg:address":"Niederwil",
    "sg:city":"Cham",
    "sg:orig_category":"Verwertung von Milch",
    "sg:postcode":"6330",
    "sg:province":"Zug",
    "wof:name":"Milchgenossenschaft Nussbaumen",
    "wof:placetype":"venue"
},
  "geometry": {"coordinates":[8.8177452087,47.6094284058],"type":"Point"}
}