{
  "type": "Feature",
  "properties": {
    "iso:country":"CH",
    "sg:address":"Wanneggstrasse 15",
    "sg:city":"Wiesendangen",
    "sg:orig_category":"Wirtschaftspr\u00fcfung, Steuerberatung U Treuhand",
    "sg:phone":"+41 52 337 14 24",
    "sg:postcode":"8542",
    "sg:province":"Z\u00fcrich",
    "wof:name":"Modalek Treuhand",
    "wof:placetype":"venue"
},
  "geometry": {"coordinates":[8.7845592499,47.5282058716],"type":"Point"}
}