{
  "type": "Feature",
  "properties": {
    "iso:country":"CH",
    "sg:address":"Industriestrasse 599",
    "sg:city":"Boswil",
    "sg:orig_category":"Pensionskassen",
    "sg:phone":"+41 56 666 01 55",
    "sg:postcode":"5623",
    "sg:province":"Aargau",
    "wof:name":"Personalf\u00fcrsorgestiftung Der Kork Ag Boswil",
    "wof:placetype":"venue"
},
  "geometry": {"coordinates":[8.3128499985,47.3079681396],"type":"Point"}
}