{
  "type": "Feature",
  "properties": {
    "iso:country":"CH",
    "sg:address":"Chemin De La Pointe-du-plan 15",
    "sg:city":"Vessy",
    "sg:orig_category":"Installation von Heizungs, L\u00fcftungs U Klimaanlagen",
    "sg:phone":"+41 22 300 10 30",
    "sg:postcode":"1234",
    "sg:province":"Gen\u00e8ve",
    "wof:name":"Pierre Hanggi Ventilation & Climatisation",
    "wof:placetype":"venue"
},
  "geometry": {"coordinates":[6.1467871666,46.175113678],"type":"Point"}
}