{
  "type": "Feature",
  "properties": {
    "iso:country":"CH",
    "sg:address":"Simplon Rue Du 7",
    "sg:city":"Lausanne",
    "sg:orig_category":"RESTAURANTS: TEA-ROOMS",
    "sg:postcode":"1006",
    "sg:province":"Vaud",
    "wof:name":"Schenk, Chr.",
    "wof:placetype":"venue"
},
  "geometry": {"coordinates":[7.39001894,46.9648246765],"type":"Point"}
}