{
  "type": "Feature",
  "properties": {
    "iso:country":"CH",
    "sg:address":"Montenachweg 7",
    "sg:city":"Belp",
    "sg:orig_category":"Vereine Musik/Blasmusik",
    "sg:phone":"+41 31 819 57 07",
    "sg:postcode":"3123",
    "sg:province":"Bern",
    "wof:name":"Musikgesellschaft Belp",
    "wof:placetype":"venue"
},
  "geometry": {"coordinates":[7.5055799484,46.891204834],"type":"Point"}
}