{
  "type": "Feature",
  "properties": {
    "iso:country":"CH",
    "sg:address":"Poststrasse 27 8953 Dietikon. Postfach 80",
    "sg:city":"Dietikon",
    "sg:orig_category":"Allgemeiner Hoch U Tiefbau",
    "sg:phone":"+41 18442326",
    "sg:postcode":"8953",
    "sg:province":"Z\u00fcrich",
    "wof:name":"Bauunternehmung Wiederkehr Josef Ag",
    "wof:placetype":"venue"
},
  "geometry": {"coordinates":[8.404103,47.402153],"type":"Point"}
}