{
  "type": "Feature",
  "properties": {
    "iso:country":"CH",
    "sg:address":"Kilchmattweg 9",
    "sg:city":"Th\u00fcrnen",
    "sg:orig_category":"Unternehmensberatung Weiterbildungskurse and Seminar Anbieter",
    "sg:phone":"+41 61 971 55 52",
    "sg:postcode":"4441",
    "sg:province":"Basel-Landschaft",
    "wof:name":"Rudolf M\u00fchry Schulung & Personalwesen",
    "wof:placetype":"venue"
},
  "geometry": {"coordinates":[7.8292880058,47.4581756592],"type":"Point"}
}