{
  "type": "Feature",
  "properties": {
    "addr:full":"Vermes Jura 2829",
    "addr:postcode":"2829",
    "addr:street":"Jura",
    "iso:country":"CH",
    "sg:city":"Vermes",
    "sg:classifiers":[
        {
            "category":"Banks & Credit Unions",
            "subcategory":"Bank",
            "type":"Services"
        }
    ],
    "sg:phone":"+41 32 438 82 73",
    "sg:postcode":"2829",
    "sg:province":"Jura",
    "wof:name":"Raiffeisen",
    "wof:placetype":"venue"
},
  "geometry": {"coordinates":[7.473955,47.328941],"type":"Point"}
}