{
  "type": "Feature",
  "properties": {
    "iso:country":"CH",
    "sg:address":"Obere Dorfstrasse 8",
    "sg:city":"Amden",
    "sg:orig_category":"Architekturb\u00fcros",
    "sg:phone":"+41 55 615 33 88",
    "sg:postcode":"8873",
    "sg:province":"St. Gallen",
    "wof:name":"Schwitter & Jud Ag Architekturb\u00fcro",
    "wof:placetype":"venue"
},
  "geometry": {"coordinates":[9.054515,47.172451],"type":"Point"}
}