{
  "type": "Feature",
  "properties": {
    "iso:country":"CH",
    "sg:address":"Route Cantonale",
    "sg:city":"Servion",
    "sg:orig_category":"D\u00e4mmung gegen K\u00e4lte, W\u00e4rme, Schall U Ersch\u00fctterung Herstellung von Konstruktionsteilen, Fertigbautei",
    "sg:phone":"+41 52 242 38 37",
    "sg:postcode":"1077",
    "sg:province":"Vaud",
    "wof:name":"Petersen Frank Decken Und Trennw\u00e4nde",
    "wof:placetype":"venue"
},
  "geometry": {"coordinates":[8.6809568405,47.5416069031],"type":"Point"}
}