{
  "type": "Feature",
  "properties": {
    "iso:country":"CH",
    "sg:address":"Unterer Strassackerweg 1",
    "sg:city":"Boll",
    "sg:orig_category":"Vorschulen, Kinderg\u00e4rten",
    "sg:phone":"+41 31 839 07 37",
    "sg:postcode":"3067",
    "sg:province":"Bern",
    "wof:name":"Kindergarten",
    "wof:placetype":"venue"
},
  "geometry": {"coordinates":[7.5616650581,46.9468002319],"type":"Point"}
}