{
  "type": "Feature",
  "properties": {
    "iso:country":"CH",
    "sg:address":"Wangenstrasse 7",
    "sg:city":"Deitingen",
    "sg:orig_category":"Schmieden",
    "sg:phone":"+41 32 614 22 15",
    "sg:postcode":"4543",
    "sg:province":"Solothurn",
    "wof:name":"Franz Emch Schmiede",
    "wof:placetype":"venue"
},
  "geometry": {"coordinates":[7.620100975,47.2127990723],"type":"Point"}
}