{
  "type": "Feature",
  "properties": {
    "iso:country":"CH",
    "sg:address":"Moosstrasse 3",
    "sg:city":"Huttwil",
    "sg:orig_category":"Detailhandel mit Geschenkartikeln U Souvenirs",
    "sg:phone":"+41 62 962 15 55",
    "sg:postcode":"4950",
    "sg:province":"Bern",
    "wof:name":"Boutique Mooshuus Jakob Ingold",
    "wof:placetype":"venue"
},
  "geometry": {"coordinates":[7.8437972069,47.1132926941],"type":"Point"}
}