{
  "type": "Feature",
  "properties": {
    "iso:country":"CH",
    "sg:address":"Route De La Carri\u00e8re 7 1023 Crissier. Postfach",
    "sg:city":"Crissier",
    "sg:orig_category":"Primarschulen",
    "sg:phone":"+41 21 634 15 22",
    "sg:postcode":"1023",
    "sg:province":"Vaud",
    "wof:name":"Ecole Primaire Coll\u00e8ge De Chisaz",
    "wof:placetype":"venue"
},
  "geometry": {"coordinates":[6.5765328407,46.5499382019],"type":"Point"}
}