{
  "type": "Feature",
  "properties": {
    "iso:country":"CH",
    "sg:address":"Lausanne Route De 25b 1180 Rolle. Postfach",
    "sg:city":"Rolle",
    "sg:orig_category":"Sonstige Hilfs U Nebent\u00e4tigkeiten f\u00fcr die Luftfahrt",
    "sg:postcode":"1180",
    "sg:province":"Vaud",
    "wof:name":"Ost Steiger Orlando Team-up Conseils Et Services Dans Le Dom. Des Transports A\u00e9riens Et Maritime",
    "wof:placetype":"venue"
},
  "geometry": {"coordinates":[6.3461389542,46.4630126953],"type":"Point"}
}