{
  "type": "Feature",
  "properties": {
    "iso:country":"CH",
    "sg:address":"Oberer Rolliring 3",
    "sg:city":"H\u00e4gendorf",
    "sg:classifiers":[
        {
            "category":"Insurance",
            "subcategory":"Insurance Agent",
            "type":"Services"
        }
    ],
    "sg:phone":"+41 62 216 26 31",
    "sg:postcode":"4614",
    "sg:province":"Solothurn",
    "sg:tags":[
        "versicherungsagenturen",
        "-broker"
    ],
    "wof:name":"Peter Haller Agentur Familia-leben & Union",
    "wof:placetype":"venue"
},
  "geometry": {"coordinates":[7.8348670006,47.3334236145],"type":"Point"}
}