{
  "type": "Feature",
  "properties": {
    "iso:country":"CH",
    "sg:address":"Route De Martigny 85",
    "sg:city":"Fully",
    "sg:orig_category":"Erbringung von Dienstleistungen f\u00fcr Unternehmen Wohnbedarf Grosshandel",
    "sg:phone":"+41 27 746 46 33",
    "sg:postcode":"1926",
    "sg:province":"Valais",
    "wof:name":"Eurodiffusion S\u00e0rl",
    "wof:placetype":"venue"
},
  "geometry": {"coordinates":[7.1100058556,46.1333618164],"type":"Point"}
}