{
  "type": "Feature",
  "properties": {
    "iso:country":"CH",
    "sg:address":"Archivstrasse 6",
    "sg:city":"Bern",
    "sg:orig_category":"Bauschreinerei Glaserei",
    "sg:phone":"+41 31 351 11 63",
    "sg:postcode":"3005",
    "sg:province":"Bern",
    "wof:name":"Heinz Aebischer Schreinerei & Glaserei",
    "wof:placetype":"venue"
},
  "geometry": {"coordinates":[7.4476,46.941814],"type":"Point"}
}