{
  "type": "Feature",
  "properties": {
    "iso:country":"CH",
    "sg:address":"Hauptstrasse 49",
    "sg:city":"Glarus",
    "sg:orig_category":"Herstellung von Ger\u00e4ten der Elektrizit\u00e4tserzeugung, -verteilung u.\u00e4. -Herstellung von Mess U Kontrol",
    "sg:phone":"+41 52 346 16 66",
    "sg:postcode":"8750",
    "sg:province":"Glarus",
    "wof:name":"Nivus Ag",
    "wof:placetype":"venue"
},
  "geometry": {"coordinates":[9.066986084,47.0410118103],"type":"Point"}
}