{
  "type": "Feature",
  "properties": {
    "iso:country":"CH",
    "sg:address":"Grand-rue 36 2732 Reconvilier Case Postale 89",
    "sg:city":"Reconvilier",
    "sg:orig_category":"Grosshandel mit Uhren",
    "sg:phone":"+41 32 481 42 22",
    "sg:postcode":"2732",
    "sg:province":"Bern",
    "wof:name":"Edox Montres March\u00e9 Suisse Sa",
    "wof:placetype":"venue"
},
  "geometry": {"coordinates":[7.226776123,47.2347450256],"type":"Point"}
}