{
  "type": "Feature",
  "properties": {
    "iso:country":"CH",
    "sg:address":"Place Des Bergues 27",
    "sg:city":"Gen\u00e8ve",
    "sg:classifiers":[
        {
            "category":"Government",
            "subcategory":"Post Office",
            "type":"Public Place"
        }
    ],
    "sg:phone":"+41 22 731 54 85",
    "sg:postcode":"1201",
    "sg:province":"Gen\u00e8ve",
    "sg:tags":[
        "caf\u00e9s",
        "tea-rooms"
    ],
    "wof:name":"Tea-room Bergues",
    "wof:placetype":"venue"
},
  "geometry": {"coordinates":[6.1456441879,46.2065734863],"type":"Point"}
}