{
  "type": "Feature",
  "properties": {
    "iso:country":"CH",
    "sg:address":"Konstanzerstrasse 20",
    "sg:city":"Kreuzlingen",
    "sg:orig_category":"Arztpraxen",
    "sg:phone":"+41 71 670 09 09",
    "sg:postcode":"8280",
    "sg:province":"Thurgau",
    "wof:name":"Dr.med.mark Kengelbacher Spezialarzt Fmh",
    "wof:placetype":"venue"
},
  "geometry": {"coordinates":[9.167778,47.65427],"type":"Point"}
}