{
  "type": "Feature",
  "properties": {
    "iso:country":"CH",
    "sg:address":"Ausserdorf 9",
    "sg:city":"Hallwil",
    "sg:orig_category":"Sonstige mit der Informatik verbundene T\u00e4tigkeiten",
    "sg:phone":"+41 62 777 54 42",
    "sg:postcode":"5705",
    "sg:province":"Aargau",
    "wof:name":"Tse-dr\u00fc Media-studio Viatte Christiane",
    "wof:placetype":"venue"
},
  "geometry": {"coordinates":[8.1797466278,47.3249015808],"type":"Point"}
}