{
  "type": "Feature",
  "properties": {
    "iso:country":"CH",
    "sg:address":"Rue St-germain 26",
    "sg:city":"Villars-le-comte",
    "sg:orig_category":"Fachdetailhandel in Verkaufsr\u00e4umen",
    "sg:postcode":"1515",
    "sg:province":"Vaud",
    "wof:name":"Bzr Sport - Bulloz R\u00e9mi",
    "wof:placetype":"venue"
},
  "geometry": {"coordinates":[6.7990951538,46.7105445862],"type":"Point"}
}