{
  "type": "Feature",
  "properties": {
    "iso:country":"CH",
    "sg:address":"Kanalstrasse 31a 9451 Kriessern. Postfach",
    "sg:city":"Kriessern",
    "sg:orig_category":"Interessenvertretungen",
    "sg:postcode":"9451",
    "sg:province":"St. Gallen",
    "wof:name":"Genossenschaft Mehrzweckhalle Kriessern",
    "wof:placetype":"venue"
},
  "geometry": {"coordinates":[9.6119937897,47.3653335571],"type":"Point"}
}