{
  "type": "Feature",
  "properties": {
    "iso:country":"CH",
    "sg:address":"Rue De Savoie 8",
    "sg:city":"Payerne",
    "sg:orig_category":"Detailhandel mit fotografischen Artikeln Fachdetailhandel in Verkaufsr\u00e4umen",
    "sg:phone":"+41 26 660 23 19",
    "sg:postcode":"1530",
    "sg:province":"Vaud",
    "wof:name":"Photos Juriens Sa",
    "wof:placetype":"venue"
},
  "geometry": {"coordinates":[6.9395780563,46.8209037781],"type":"Point"}
}