{
  "type": "Feature",
  "properties": {
    "iso:country":"CH",
    "sg:address":"Union Route De L' 2 1723 Marly. Postfach",
    "sg:city":"Marly",
    "sg:orig_category":"Non-Classified Establishments",
    "sg:phone":"+41 26 430 03 66",
    "sg:postcode":"1723",
    "sg:province":"Fribourg",
    "wof:name":"Pittypanda - Peiry & Obbad Fournisseur De Services, H\u00e9bergement De Sites Internet, E-commerce",
    "wof:placetype":"venue"
},
  "geometry": {"coordinates":[7.1607999802,46.7766113281],"type":"Point"}
}