{
  "type": "Feature",
  "properties": {
    "addr:full":"Alpenquai 30 Luzern Luzern 6005",
    "addr:housenumber":"30",
    "addr:postcode":"6005",
    "addr:street":"Alpenquai",
    "iso:country":"CH",
    "sg:address":"Alpenquai 30",
    "sg:city":"Luzern",
    "sg:classifiers":[
        {
            "category":"Professional",
            "subcategory":"Advertising",
            "type":"Services"
        }
    ],
    "sg:phone":"+41 41 368 18 18",
    "sg:postcode":"6005",
    "sg:province":"Luzern",
    "sg:tags":[
        "athletic"
    ],
    "wof:name":"T.e.a.m. Marketing Ag",
    "wof:placetype":"venue"
},
  "geometry": {"coordinates":[8.319399,47.045326],"type":"Point"}
}