{
  "type": "Feature",
  "properties": {
    "iso:country":"CH",
    "sg:address":"Vogelsang Bei Turgi",
    "sg:city":"Turgi",
    "sg:orig_category":"Vorschulen, Kinderg\u00e4rten",
    "sg:phone":"+41 56 241 22 72",
    "sg:postcode":"5300",
    "sg:province":"Aargau",
    "wof:name":"Kindergarten",
    "wof:placetype":"venue"
},
  "geometry": {"coordinates":[8.3305282593,47.5229263306],"type":"Point"}
}