{
  "type": "Feature",
  "properties": {
    "iso:country":"CH",
    "sg:address":"M\u00fchlackerstrasse 72",
    "sg:city":"Balgach",
    "sg:orig_category":"Fachdetailhandel in Verkaufsr\u00e4umen Herstellung von optischen Instrumenten",
    "sg:postcode":"9436",
    "sg:province":"St. Gallen",
    "wof:name":"Z\u00fcnd Precision Optics Ltd",
    "wof:placetype":"venue"
},
  "geometry": {"coordinates":[9.6026792526,47.4007492065],"type":"Point"}
}