{
  "type": "Feature",
  "properties": {
    "iso:country":"CH",
    "sg:address":"Passage De L' Intendant 6",
    "sg:city":"Carouge",
    "sg:classifiers":[
        {
            "category":"Professional",
            "subcategory":"Computer Services",
            "type":"Services"
        }
    ],
    "sg:phone":"+41 22 308 45 60",
    "sg:postcode":"1227",
    "sg:province":"Gen\u00e8ve",
    "sg:tags":[
        "services",
        "consulting",
        "internet"
    ],
    "wof:name":"Digigraphix Communication S.\u00e0.r.l.",
    "wof:placetype":"venue"
},
  "geometry": {"coordinates":[0.581668973,44.2027168274],"type":"Point"}
}