{
  "type": "Feature",
  "properties": {
    "iso:country":"CH",
    "sg:address":"Richard Wagner-strasse 6",
    "sg:city":"Z\u00fcrich",
    "sg:orig_category":"Wirtschaftspr\u00fcfung, Steuerberatung U Treuhand",
    "sg:phone":"+41 22 342 50 82",
    "sg:postcode":"8002",
    "sg:province":"Z\u00fcrich",
    "wof:name":"Lagger Pierre, Compta-head Et Head-info Comptabilit\u00e9, Administration Etc",
    "wof:placetype":"venue"
},
  "geometry": {"coordinates":[6.1420512199,46.1869354248],"type":"Point"}
}