{
  "type": "Feature",
  "properties": {
    "iso:country":"CH",
    "sg:address":"Les Fontaines-blanches",
    "sg:city":"Morgins",
    "sg:orig_category":"Verkehrs- and Tourismusb\u00fcros",
    "sg:phone":"+41 24 477 20 95",
    "sg:postcode":"1875",
    "sg:province":"Valais",
    "wof:name":"Office Du Tourisme",
    "wof:placetype":"venue"
},
  "geometry": {"coordinates":[6.8587532043,46.2375221252],"type":"Point"}
}