{
  "type": "Feature",
  "properties": {
    "iso:country":"CH",
    "sg:address":"1836 Rossini\u00e8re. Postfach",
    "sg:city":"Rossini\u00e8re",
    "sg:orig_category":"Softwareentwicklung U beratung",
    "sg:phone":"+41 26 924 79 41",
    "sg:postcode":"1836",
    "wof:name":"Sidem Systems Solutions, Michault Marc Logiciels Mat\u00e9riel Dans Le Dom. De L'informatique; Conseils, Formation Etc",
    "wof:placetype":"venue"
},
  "geometry": {"coordinates":[7.083630085,46.466960907],"type":"Point"}
}