{
  "type": "Feature",
  "properties": {
    "iso:country":"CH",
    "sg:address":"Knettnauweg 21",
    "sg:city":"Nidau",
    "sg:classifiers":[
        {
            "category":"Bars & Pubs",
            "type":"Food & Drink"
        }
    ],
    "sg:phone":"+41 32 331 74 73",
    "sg:postcode":"2560",
    "sg:province":"Bern",
    "sg:tags":[
        "lamp",
        "shade"
    ],
    "wof:name":"Neo-lamp Sa",
    "wof:placetype":"venue"
},
  "geometry": {"coordinates":[7.2390041351,47.123714447],"type":"Point"}
}