{
  "type": "Feature",
  "properties": {
    "iso:country":"CH",
    "sg:address":"Wohnstrasse 7",
    "sg:city":"Frasnacht",
    "sg:orig_category":"Detailhandel mit Geschenkartikeln U Souvenirs Sonstiger Detailhandel mit Metallwaren, Anstrichmittel",
    "sg:phone":"+41 71 446 94 86",
    "sg:postcode":"9320",
    "sg:province":"Thurgau",
    "wof:name":"Madeleine Gemperle Basteln & Geschenke",
    "wof:placetype":"venue"
},
  "geometry": {"coordinates":[9.4019813538,47.5295906067],"type":"Point"}
}