{
  "type": "Feature",
  "properties": {
    "iso:country":"CH",
    "sg:address":"Hauptstr. 21",
    "sg:city":"Herisau",
    "sg:orig_category":"Softwareentwicklung U beratung",
    "sg:phone":"+41 71 352 24 22",
    "sg:postcode":"9100",
    "sg:province":"Appenzell Ausserrhoden",
    "wof:name":"Memorex Telex Nv Amsterdam Nl, Filiale Herisau",
    "wof:placetype":"venue"
},
  "geometry": {"coordinates":[9.278169632,47.3851013184],"type":"Point"}
}