{
  "type": "Feature",
  "properties": {
    "iso:country":"CH",
    "sg:address":"Schwanengasse 22",
    "sg:city":"Biel/bienne",
    "sg:orig_category":"Grosshandel mit Getreide, Saatgut U Futtermitteln Handelsvermittlung U Grosshandel",
    "sg:phone":"+41 32 365 94 13",
    "sg:postcode":"2503",
    "sg:province":"Bern",
    "wof:name":"Einkaufsgenossenschaft Biel",
    "wof:placetype":"venue"
},
  "geometry": {"coordinates":[7.2536978722,47.1371841431],"type":"Point"}
}