{
  "type": "Feature",
  "properties": {
    "iso:country":"CH",
    "sg:address":"Unionstrasse 37",
    "sg:city":"Winterthur",
    "sg:orig_category":"Erschliessung von Grundst\u00fccken",
    "sg:phone":"+41 52 213 40 78",
    "sg:postcode":"8400",
    "sg:province":"Z\u00fcrich",
    "wof:name":"Baugenossenschaft Union",
    "wof:placetype":"venue"
},
  "geometry": {"coordinates":[8.7204914093,47.4891204834],"type":"Point"}
}