{
  "type": "Feature",
  "properties": {
    "iso:country":"CH",
    "sg:address":"Freienhofgasse 17 3600 Thun. Postfach",
    "sg:city":"Thun",
    "sg:orig_category":"Detailhandel mit Uhren U Schmuck",
    "sg:phone":"+41 33 222 24 77",
    "sg:postcode":"3602",
    "sg:province":"Bern",
    "wof:name":"Roger Moser Bijouterie",
    "wof:placetype":"venue"
},
  "geometry": {"coordinates":[7.6304459572,46.7570648193],"type":"Point"}
}