{
  "type": "Feature",
  "properties": {
    "iso:country":"CH",
    "sg:address":"En Bov\u00e9ry C 1868 Collombey. Postfach",
    "sg:city":"Collombey",
    "sg:orig_category":"Instandhaltung U Reparatur von Automobilen",
    "sg:phone":"+41 24 472 71 13",
    "sg:postcode":"1868",
    "sg:province":"Valais",
    "wof:name":"Garage Leprat Patrick",
    "wof:placetype":"venue"
},
  "geometry": {"coordinates":[6.945827961,46.2704734802],"type":"Point"}
}