{
  "type": "Feature",
  "properties": {
    "iso:country":"CH",
    "sg:address":"Speichergasse 37",
    "sg:city":"Bern",
    "sg:orig_category":"Werbeagenturen Werbung",
    "sg:phone":"+41 31 318 08 77",
    "sg:postcode":"3011",
    "sg:province":"Bern",
    "wof:name":"Nabel Advertainment Lenz R.",
    "wof:placetype":"venue"
},
  "geometry": {"coordinates":[7.4421300888,46.950302124],"type":"Point"}
}