{
  "type": "Feature",
  "properties": {
    "iso:country":"CH",
    "sg:address":"Eichwaldstrasse 8",
    "sg:city":"Giswil",
    "sg:orig_category":"G\u00fcterbef\u00f6rderung im Strassenverkehr",
    "sg:phone":"+41 79 634 36 34",
    "sg:postcode":"6074",
    "sg:province":"Obwalden",
    "wof:name":"Otto Eberli Transporte",
    "wof:placetype":"venue"
},
  "geometry": {"coordinates":[8.1707305908,46.8365974426],"type":"Point"}
}