{
  "type": "Feature",
  "properties": {
    "iso:country":"CH",
    "sg:address":"Marktplatz 2",
    "sg:city":"Interlaken",
    "sg:orig_category":"Detailhandel mit Damenbekleidung Detailhandel mit Herrenbekleidung",
    "sg:phone":"+41 62 291 16 88",
    "sg:postcode":"3800",
    "sg:province":"Bern",
    "wof:name":"Doris Renggli Dorf-boutique",
    "wof:placetype":"venue"
},
  "geometry": {"coordinates":[7.9826750755,47.3544006348],"type":"Point"}
}