{
  "type": "Feature",
  "properties": {
    "iso:country":"CH",
    "sg:address":"Temple Avenue Du 28d 1012 Lausanne. Postfach",
    "sg:city":"Lausanne",
    "sg:orig_category":"Wirtschaftspr\u00fcfung, Steuerberatung U Treuhand",
    "sg:phone":"+41 21 922 58 60",
    "sg:postcode":"1003",
    "sg:province":"Vaud",
    "wof:name":"Jaton Marie-louise",
    "wof:placetype":"venue"
},
  "geometry": {"coordinates":[5.1808700562,45.8973388672],"type":"Point"}
}