{
  "type": "Feature",
  "properties": {
    "addr:full":"Le Ch\u00e2teau De Tannay Mies Vaud 1295",
    "addr:housenumber":"1295",
    "iso:country":"CH",
    "sg:address":"Le Ch\u00e2teau De Tannay",
    "sg:city":"Mies",
    "sg:orig_category":"Architektur U Ingenieurb\u00fcros",
    "sg:postcode":"1295",
    "sg:province":"Vaud",
    "wof:name":"Designer Virchaux Ellen",
    "wof:placetype":"venue"
},
  "geometry": {"coordinates":[6.176099,46.30896],"type":"Point"}
}