{
  "type": "Feature",
  "properties": {
    "addr:full":"D\u00e9sertes Avenue Des 21 1009 Pully. Postfach Pully Vaud 1009",
    "addr:postcode":"1009;postfach;1009",
    "addr:street":"Avenue Des 21",
    "iso:country":"CH",
    "sg:address":"D\u00e9sertes Avenue Des 21 1009 Pully. Postfach",
    "sg:city":"Pully",
    "sg:orig_category":"Allgemeiner Hoch U Tiefbau",
    "sg:phone":"+41 21 728 09 78",
    "sg:postcode":"1009",
    "sg:province":"Vaud",
    "wof:name":"Srt Soci\u00e9t\u00e9 Romande De Travaux Sa, Succursale De Pully Entreprise G\u00e9n\u00e9rale, Notamm. Des B\u00e2timents-ouvrages Etc",
    "wof:placetype":"venue"
},
  "geometry": {"coordinates":[6.6598,46.510258],"type":"Point"}
}