{
  "type": "Feature",
  "properties": {
    "iso:country":"CH",
    "sg:address":"3917",
    "sg:city":"Kippel",
    "sg:orig_category":"Primarschulen",
    "sg:postcode":"3917",
    "sg:province":"Valais",
    "wof:name":"Primarschule",
    "wof:placetype":"venue"
},
  "geometry": {"coordinates":[7.7726101875,46.3995513916],"type":"Point"}
}