{
  "type": "Feature",
  "properties": {
    "iso:country":"CH",
    "sg:address":"Rue De La Treille 8",
    "sg:city":"Neuch\u00e2tel",
    "sg:orig_category":"Detailhandel mit Lederwaren U Reiseartikeln",
    "sg:phone":"+41 27 725 18 47",
    "sg:postcode":"2000",
    "sg:province":"Neuch\u00e2tel",
    "wof:name":"Newbag Sa Maroquinerie",
    "wof:placetype":"venue"
},
  "geometry": {"coordinates":[6.9294228554,46.99061203],"type":"Point"}
}