{
  "type": "Feature",
  "properties": {
    "iso:country":"CH",
    "sg:address":"Rue Centrale 7",
    "sg:city":"Court",
    "sg:orig_category":"Detailhandel mit Sportartikeln",
    "sg:phone":"+41 32 497 95 88",
    "sg:postcode":"2738",
    "sg:province":"Bern",
    "wof:name":"Sports-loisirs Jean-daniel Paroz",
    "wof:placetype":"venue"
},
  "geometry": {"coordinates":[7.3380317688,47.2400550842],"type":"Point"}
}