{
  "type": "Feature",
  "properties": {
    "iso:country":"CH",
    "sg:address":"Waldeggstrasse 2",
    "sg:city":"Rotkreuz",
    "sg:orig_category":"Herstellung von Metallerzeugnissen ohne Maschinenbau Herstellung von elektrischen Lampen U Leuchten",
    "sg:phone":"+41 56 618 73 73",
    "sg:postcode":"6343",
    "sg:province":"Zug",
    "wof:name":"Belux Ag",
    "wof:placetype":"venue"
},
  "geometry": {"coordinates":[8.2953500748,47.3473014832],"type":"Point"}
}