{
  "type": "Feature",
  "properties": {
    "iso:country":"CH",
    "sg:address":"Hungerberg 9 2565 Jens. Postfach",
    "sg:city":"Jens",
    "sg:orig_category":"Schlossereien",
    "sg:phone":"+41 32 331 00 05",
    "sg:postcode":"2565",
    "sg:province":"Bern",
    "wof:name":"Kurt Bingisser Schlosserei",
    "wof:placetype":"venue"
},
  "geometry": {"coordinates":[7.259349823,47.0999450684],"type":"Point"}
}