{
  "type": "Feature",
  "properties": {
    "iso:country":"CH",
    "sg:address":"Franklinstrasse 33",
    "sg:city":"Z\u00fcrich",
    "sg:classifiers":[
        {
            "category":"Professional",
            "subcategory":"Employment Agencies",
            "type":"Services"
        }
    ],
    "sg:phone":"+41 13775500",
    "sg:postcode":"8050",
    "sg:province":"Z\u00fcrich",
    "sg:tags":[
        "personal",
        "u",
        "stellenvermittlung"
    ],
    "wof:name":"Go4work Ag Dienstleistungen Auf Dem Personalsektor, Bes. Anwerbung U. Zurverf\u00fcgungstellung Von Personal",
    "wof:placetype":"venue"
},
  "geometry": {"coordinates":[8.5429563522,47.4099082947],"type":"Point"}
}