{
  "type": "Feature",
  "properties": {
    "iso:country":"CH",
    "sg:address":"Avenue Du Midi 7",
    "sg:city":"Fribourg",
    "sg:classifiers":[
        {
            "category":"Restaurant",
            "type":"Food & Drink"
        }
    ],
    "sg:phone":"+41 52 672 12 12",
    "sg:postcode":"1700",
    "sg:province":"Fribourg",
    "sg:tags":[
        "tea-rooms",
        "restaurants"
    ],
    "wof:name":"Caf\u00e9-restaurant Morgensonne Mauch Rita",
    "wof:placetype":"venue"
},
  "geometry": {"coordinates":[8.6173124313,47.6806182861],"type":"Point"}
}