{
  "type": "Feature",
  "properties": {
    "iso:country":"CH",
    "sg:address":"M\u00fchlegasse 129f",
    "sg:city":"Gondiswil",
    "sg:orig_category":"Organisationen des Gesundheitswesen",
    "sg:phone":"+41 79 333 35 05",
    "sg:postcode":"4955",
    "sg:province":"Bern",
    "wof:name":"Samariterverein Huttwil & Umg.",
    "wof:placetype":"venue"
},
  "geometry": {"coordinates":[7.8745517731,47.1418075562],"type":"Point"}
}