{
  "type": "Feature",
  "properties": {
    "iso:country":"CH",
    "sg:address":"3360 Herzogenbuchsee. Postfach 183",
    "sg:city":"Herzogenbuchsee",
    "sg:orig_category":"Sportvereine Ballsport Fussball",
    "sg:phone":"+41 62 961 44 81",
    "sg:postcode":"3360",
    "sg:province":"Bern",
    "wof:name":"Fc Herzogenbuchsee",
    "wof:placetype":"venue"
},
  "geometry": {"coordinates":[7.7037801743,47.1915435791],"type":"Point"}
}