{
  "type": "Feature",
  "properties": {
    "iso:country":"CH",
    "sg:address":"S\u00e4gemoos",
    "sg:city":"Niederstocken",
    "sg:orig_category":"Autospenglereien",
    "sg:phone":"+41 33 341 15 41",
    "sg:postcode":"3632",
    "sg:province":"Bern",
    "wof:name":"Rudolf Messerli Carrosserie",
    "wof:placetype":"venue"
},
  "geometry": {"coordinates":[7.586044,46.706631],"type":"Point"}
}