{
  "type": "Feature",
  "properties": {
    "iso:country":"CH",
    "sg:address":"Z\u00fcrichstrasse 77",
    "sg:city":"Adliswil",
    "sg:orig_category":"Erbringung von Dienstleistungen f\u00fcr Unternehmen",
    "sg:phone":"+41 17122386",
    "sg:postcode":"8134",
    "sg:province":"Z\u00fcrich",
    "wof:name":"Takemake Gmbh",
    "wof:placetype":"venue"
},
  "geometry": {"coordinates":[8.5286207199,47.3224334717],"type":"Point"}
}