{
  "type": "Feature",
  "properties": {
    "iso:country":"CH",
    "sg:address":"Lausanne Rue De 64",
    "sg:city":"Sion",
    "sg:orig_category":"RESTAURANTS: TEA-ROOMS",
    "sg:phone":"+41 27 323 62 43",
    "sg:postcode":"1950",
    "sg:province":"Valais",
    "wof:name":"Aymon St\u00e9phane",
    "wof:placetype":"venue"
},
  "geometry": {"coordinates":[7.3504071236,46.2305450439],"type":"Point"}
}