{
  "type": "Feature",
  "properties": {
    "iso:country":"CH",
    "sg:address":"Lange Gasse 6",
    "sg:city":"Basel",
    "sg:orig_category":"Non-Classified Establishments",
    "sg:phone":"+41 61 279 98 10",
    "sg:postcode":"4000",
    "sg:province":"Basel-Stadt",
    "wof:name":"Rouden, Messmer & Partners Communications Consultants Ltd",
    "wof:placetype":"venue"
},
  "geometry": {"coordinates":[7.5979170799,47.5493049622],"type":"Point"}
}