{
  "type": "Feature",
  "properties": {
    "iso:country":"CH",
    "sg:address":"Hauptstrasse 71",
    "sg:city":"Degersheim",
    "sg:orig_category":"Herstellung von Radio U Fernsehger\u00e4ten sowie phono U videotechnischen Ger\u00e4ten",
    "sg:phone":"+41 71 370 01 50",
    "sg:postcode":"9113",
    "sg:province":"St. Gallen",
    "wof:name":"Rocco Radio-tv, Inhaber Di Blasio",
    "wof:placetype":"venue"
},
  "geometry": {"coordinates":[9.1976890564,47.3732032776],"type":"Point"}
}