{
  "type": "Feature",
  "properties": {
    "iso:country":"CH",
    "sg:address":"Route Du Stand 17 1260 Nyon Case Postale 43",
    "sg:city":"Nyon",
    "sg:orig_category":"Getreide Grosshandel",
    "sg:phone":"+41 22 361 29 74",
    "sg:postcode":"1260",
    "sg:province":"Vaud",
    "wof:name":"Noel & Cie Produits Agricoles",
    "wof:placetype":"venue"
},
  "geometry": {"coordinates":[6.2238311768,46.3818664551],"type":"Point"}
}