{
  "type": "Feature",
  "properties": {
    "iso:country":"CH",
    "sg:address":"Dottenwil",
    "sg:city":"Wittenbach",
    "sg:orig_category":"Haltung von Schweinen",
    "sg:phone":"+41 71 298 29 82",
    "sg:postcode":"9303",
    "wof:name":"Adolf Fecker Schweinez\u00fcchterei",
    "wof:placetype":"venue"
},
  "geometry": {"coordinates":[9.3786897659,47.4766998291],"type":"Point"}
}