{
  "type": "Feature",
  "properties": {
    "iso:country":"CH",
    "sg:address":"Paracelsusstrasse 48",
    "sg:city":"Basel",
    "sg:orig_category":"Sonstiger Grosshandel",
    "sg:postcode":"4058",
    "sg:province":"Basel-Stadt",
    "wof:name":"Mundiac Wirtschaftspr\u00fcfung Ag",
    "wof:placetype":"venue"
},
  "geometry": {"coordinates":[7.6127061844,47.565410614],"type":"Point"}
}