{
  "type": "Feature",
  "properties": {
    "iso:country":"CH",
    "sg:address":"Distelbergstrasse 20",
    "sg:city":"Aarau",
    "sg:orig_category":"Unclassifiable Establishments",
    "sg:postcode":"5000",
    "sg:province":"Aargau",
    "wof:name":"Gesundheits-praxis Am See Bargellini Edinalva Gesundheitspraxis Und Kosmetikstudio",
    "wof:placetype":"venue"
},
  "geometry": {"coordinates":[8.5852336884,47.311126709],"type":"Point"}
}