{
  "type": "Feature",
  "properties": {
    "iso:country":"CH",
    "sg:address":"Seefeldstrasse 7",
    "sg:city":"Uster",
    "sg:orig_category":"Fahrschulen, Flugschulen",
    "sg:phone":"+41 19405970",
    "sg:postcode":"8610",
    "sg:province":"Z\u00fcrich",
    "wof:name":"Willi Frei Autofahrschule",
    "wof:placetype":"venue"
},
  "geometry": {"coordinates":[8.7036752701,47.3413925171],"type":"Point"}
}