{
  "type": "Feature",
  "properties": {
    "addr:full":"Brunismatt 411 3665 Wattenwil. Postfach Wattenwil Bern 3665",
    "addr:housenumber":"411",
    "addr:postcode":"3665;3665",
    "iso:country":"CH",
    "sg:address":"Brunismatt 411 3665 Wattenwil. Postfach",
    "sg:city":"Wattenwil",
    "sg:orig_category":"Dachdeckerei Zimmerei, Dachdeckerei, Bauspenglerei U Abdichtung",
    "sg:phone":"+41 33 356 02 01",
    "sg:postcode":"3665",
    "sg:province":"Bern",
    "wof:name":"Werner Kislig, Bedachungen",
    "wof:placetype":"venue"
},
  "geometry": {"coordinates":[7.50808,46.771252],"type":"Point"}
}