{
  "type": "Feature",
  "properties": {
    "iso:country":"CH",
    "sg:address":"Oberneuhofstrasse",
    "sg:city":"Baar",
    "sg:orig_category":"Unternehmensberatung",
    "sg:phone":"+41 41 760 94 24",
    "sg:postcode":"6340",
    "sg:province":"Zug",
    "wof:name":"Wbb Wolf, Brun, Boll & Partner Ag",
    "wof:placetype":"venue"
},
  "geometry": {"coordinates":[8.5149097443,47.1886901855],"type":"Point"}
}