{
  "type": "Feature",
  "properties": {
    "iso:country":"CH",
    "sg:address":"6527",
    "sg:city":"Lodrino",
    "sg:classifiers":[
        {
            "category":"Restaurant",
            "type":"Food & Drink"
        }
    ],
    "sg:phone":"+41 91 863 12 10",
    "sg:postcode":"6527",
    "sg:province":"Ticino",
    "wof:name":"Ristorante Tonelli",
    "wof:placetype":"venue"
},
  "geometry": {"coordinates":[8.9811306,46.2996673584],"type":"Point"}
}