{
  "type": "Feature",
  "properties": {
    "addr:full":"Binningerstrasse 4 Allschwil Basel-Landschaft 4123",
    "addr:housenumber":"4",
    "addr:postcode":"4123",
    "addr:street":"Binningerstrasse",
    "iso:country":"CH",
    "sg:address":"Binningerstrasse 4",
    "sg:city":"Allschwil",
    "sg:orig_category":"Binnenschiffahrt",
    "sg:postcode":"4123",
    "sg:province":"Basel-Landschaft",
    "wof:name":"Titania Gmbh",
    "wof:placetype":"venue"
},
  "geometry": {"coordinates":[7.539715,47.551834],"type":"Point"}
}