{
  "type": "Feature",
  "properties": {
    "iso:country":"CH",
    "sg:address":"Rue De La Plaine 41 1400 Yverdon-les-bains. Postfach",
    "sg:city":"Yverdon",
    "sg:orig_category":"Herstellung von Teppichen Verlegen von Fussboden",
    "sg:phone":"+41 79 230 25 55",
    "sg:postcode":"1401",
    "sg:province":"Vaud",
    "wof:name":"Notari Edy Sa",
    "wof:placetype":"venue"
},
  "geometry": {"coordinates":[9.1205949783,46.2361297607],"type":"Point"}
}