{
  "type": "Feature",
  "properties": {
    "iso:country":"CH",
    "sg:address":"Fortunagasse 15 8022 Z\u00fcrich. Postfach",
    "sg:city":"Z\u00fcrich",
    "sg:classifiers":[
        {
            "category":"Professional",
            "subcategory":"Employment Agencies",
            "type":"Services"
        }
    ],
    "sg:phone":"+41 12174545",
    "sg:postcode":"8022",
    "sg:province":"Z\u00fcrich",
    "sg:tags":[
        "personal",
        "u",
        "stellenvermittlung"
    ],
    "wof:name":"Professionelle Personalberatung Ag",
    "wof:placetype":"venue"
},
  "geometry": {"coordinates":[8.5396461487,47.373046875],"type":"Point"}
}