{
  "type": "Feature",
  "properties": {
    "iso:country":"CH",
    "sg:address":"Schiferliweg 28",
    "sg:city":"Bern",
    "sg:orig_category":"Physiotherapie",
    "sg:phone":"+41 31 351 37 96",
    "sg:postcode":"3006",
    "sg:province":"Bern",
    "wof:name":"Ursula Weber Physiotherapie",
    "wof:placetype":"venue"
},
  "geometry": {"coordinates":[7.4781999588,46.94298172],"type":"Point"}
}