{
  "type": "Feature",
  "properties": {
    "iso:country":"CH",
    "sg:address":"Lenzburgerstrasse 2",
    "sg:city":"Mellingen",
    "sg:orig_category":"Detailhandel mit Brot, Back U S\u00fcsswaren",
    "sg:postcode":"5507",
    "sg:province":"Aargau",
    "wof:name":"Konditorei-caf\u00e9 H\u00e4ntze W.",
    "wof:placetype":"venue"
},
  "geometry": {"coordinates":[8.272494,47.41777],"type":"Point"}
}