{
  "type": "Feature",
  "properties": {
    "iso:country":"CH",
    "sg:address":"Industriestrasse 23",
    "sg:city":"Frauenfeld",
    "sg:orig_category":"Betrieb U technische Hilfsdienste des Kultur U Unterhaltungswesens",
    "sg:phone":"+41 52 722 44 47",
    "sg:postcode":"8500",
    "sg:province":"Thurgau",
    "wof:name":"Vor-stadttheater",
    "wof:placetype":"venue"
},
  "geometry": {"coordinates":[8.894001,47.561283],"type":"Point"}
}