{
  "type": "Feature",
  "properties": {
    "iso:country":"CH",
    "sg:address":"Dammstrasse 30",
    "sg:city":"Biberist",
    "sg:classifiers":[
        {
            "category":"Manufacturing",
            "subcategory":"Tools & Machinery",
            "type":"Manufacturing & Wholesale Goods"
        }
    ],
    "sg:phone":"+41 32 672 30 20",
    "sg:postcode":"4562",
    "sg:province":"Solothurn",
    "sg:tags":[
        "part",
        "turned",
        "cnc"
    ],
    "wof:name":"Walter D\u00e9colletages Ag",
    "wof:placetype":"venue"
},
  "geometry": {"coordinates":[7.562027,47.177731],"type":"Point"}
}