{
  "type": "Feature",
  "properties": {
    "iso:country":"CH",
    "sg:address":"Rue G\u00e9n\u00e9ral-dufour 18",
    "sg:city":"Gen\u00e8ve",
    "sg:orig_category":"Vereine Gesang",
    "sg:phone":"+41 22 328 80 60",
    "sg:postcode":"1204",
    "sg:province":"Gen\u00e8ve",
    "wof:name":"Chorale Cath.du Sacr\u00e9-coeur",
    "wof:placetype":"venue"
},
  "geometry": {"coordinates":[6.1419510841,46.2006759644],"type":"Point"}
}