{
  "type": "Feature",
  "properties": {
    "iso:country":"CH",
    "sg:address":"Bergstrasse 110 8032 Z\u00fcrich. Postfach",
    "sg:city":"Z\u00fcrich",
    "sg:orig_category":"Wirtschaftsverb\u00e4nde Industrie, Handel and Gewerbe",
    "sg:phone":"+41 12669929",
    "sg:postcode":"8030",
    "wof:name":"Verband Schweizer Papier-& Packmaterial-grosshandels Vspg",
    "wof:placetype":"venue"
},
  "geometry": {"coordinates":[8.563955307,47.3687438965],"type":"Point"}
}