{
  "type": "Feature",
  "properties": {
    "iso:country":"CH",
    "sg:address":"Chemin Perrause 25",
    "sg:city":"Mont-sur-lausanne",
    "sg:orig_category":"Zahntechnische Laboratorien",
    "sg:phone":"+41 21 652 48 32",
    "sg:postcode":"1052",
    "sg:province":"Vaud",
    "wof:name":"Friedrich Krug Laboratoire Dentaire",
    "wof:placetype":"venue"
},
  "geometry": {"coordinates":[6.6306958199,46.5591125488],"type":"Point"}
}