{
  "type": "Feature",
  "properties": {
    "addr:full":"Via Loreto 6 6900 Lugano. Postfach Caselle Postale 3132 Lugano Ticino 6901",
    "addr:housenumber":"6",
    "addr:postcode":"6900;postale 3132;6901",
    "addr:street":"Via Loreto",
    "iso:country":"CH",
    "sg:address":"Via Loreto 6 6900 Lugano. Postfach Caselle Postale 3132",
    "sg:city":"Lugano",
    "sg:orig_category":"Advokaturb\u00fcros Notariate",
    "sg:phone":"+41 91 994 90 91",
    "sg:postcode":"6901",
    "sg:province":"Ticino",
    "wof:name":"Fabrizio Mion Studio Legale & Notarile",
    "wof:placetype":"venue"
},
  "geometry": {"coordinates":[8.947189,45.998734],"type":"Point"}
}