{
  "type": "Feature",
  "properties": {
    "iso:country":"CH",
    "sg:address":"Faido",
    "sg:city":"Faido",
    "sg:classifiers":[
        {
            "category":"Banks & Credit Unions",
            "subcategory":"Bank",
            "type":"Services"
        }
    ],
    "sg:phone":"+41 91 875 39 11",
    "sg:postcode":"6760",
    "sg:province":"Ticino",
    "wof:name":"Unione Di Banche Svizzere",
    "wof:placetype":"venue"
},
  "geometry": {"coordinates":[8.82089,46.489632],"type":"Point"}
}