{
  "type": "Feature",
  "properties": {
    "iso:country":"CH",
    "sg:address":"Bourg De L'auge 1 1636 Broc. Postfach",
    "sg:city":"Broc",
    "sg:orig_category":"Detailhandel mit B\u00fcchern, Zeitungen, Schreib U Papeteriewaren",
    "sg:postcode":"1636",
    "sg:province":"Fribourg",
    "wof:name":"Castella Corinne",
    "wof:placetype":"venue"
},
  "geometry": {"coordinates":[7.10035,46.603142],"type":"Point"}
}