{
  "type": "Feature",
  "properties": {
    "iso:country":"CH",
    "sg:address":"Seestrasse 404 8038 Z\u00fcrich. Postfach",
    "sg:city":"Z\u00fcrich",
    "sg:orig_category":"Unternehmensberatung",
    "sg:postcode":"8038",
    "sg:province":"Z\u00fcrich",
    "wof:name":"Kibag Management Und Logistik",
    "wof:placetype":"venue"
},
  "geometry": {"coordinates":[8.5357522964,47.342880249],"type":"Point"}
}