{
  "type": "Feature",
  "properties": {
    "iso:country":"CH",
    "sg:address":"Rue Du Grand-pont 4",
    "sg:city":"Lausanne",
    "sg:orig_category":"Detailhandel mit Parf\u00fcmerieartikeln U K\u00f6rperpflegemitteln Parf\u00fcmerien U sonstiger Detailhandel mit k",
    "sg:phone":"+41 21 312 22 71",
    "sg:postcode":"1003",
    "sg:province":"Vaud",
    "wof:name":"Parfumerie Lorelia, Kernen Antoinette",
    "wof:placetype":"venue"
},
  "geometry": {"coordinates":[6.6313471794,46.5207710266],"type":"Point"}
}