{
  "type": "Feature",
  "properties": {
    "iso:country":"CH",
    "sg:address":"6523",
    "sg:city":"Preonzo",
    "sg:orig_category":"Landw. Genossenschaften Viehzucht",
    "sg:postcode":"6523",
    "sg:province":"Ticino",
    "wof:name":"Consorzio Allevamento Bestiame Bovino",
    "wof:placetype":"venue"
},
  "geometry": {"coordinates":[8.9998292923,46.2651481628],"type":"Point"}
}