{
  "type": "Feature",
  "properties": {
    "iso:country":"CH",
    "sg:address":"Chemin Des Maladi\u00e8res 22 2022 Bevaix. Postfach",
    "sg:city":"Bevaix",
    "sg:orig_category":"Detailhandel mit Metallwaren, Anstrichmitteln, Glaswaren, Bau U Heimwerkerbedarf Grosshandel mit ele",
    "sg:phone":"+41 32 847 06 06",
    "sg:postcode":"2022",
    "sg:province":"Neuch\u00e2tel",
    "wof:name":"Candelux Sa",
    "wof:placetype":"venue"
},
  "geometry": {"coordinates":[6.8066391945,46.9196357727],"type":"Point"}
}