{
  "type": "Feature",
  "properties": {
    "addr:full":"Grand-rue 17 Gen\u00e8ve Gen\u00e8ve 1204",
    "addr:housenumber":"17",
    "addr:postcode":"1204",
    "addr:street":"Grand-Rue",
    "iso:country":"CH",
    "sg:address":"Grand-rue 17",
    "sg:city":"Gen\u00e8ve",
    "sg:orig_category":"Architektur U Ingenieurb\u00fcros Innenarchitekturb\u00fcros",
    "sg:phone":"+41 31 839 06 63",
    "sg:postcode":"1204",
    "sg:province":"Gen\u00e8ve",
    "wof:name":"Studer Architektur Und Bauleitungen Ag",
    "wof:placetype":"venue"
},
  "geometry": {"coordinates":[8.359496,47.03894],"type":"Point"}
}