{
  "type": "Feature",
  "properties": {
    "iso:country":"CH",
    "sg:address":"Enzenb\u00fchlstrasse 73",
    "sg:city":"Z\u00fcrich",
    "sg:orig_category":"Maler U Glasergewerbe Malerei",
    "sg:phone":"+41 62 771 49 80",
    "sg:postcode":"8008",
    "sg:province":"Z\u00fcrich",
    "wof:name":"Gr\u00fctter Malergesch\u00e4ft",
    "wof:placetype":"venue"
},
  "geometry": {"coordinates":[8.167224884,47.2552337646],"type":"Point"}
}