{
  "type": "Feature",
  "properties": {
    "iso:country":"CH",
    "sg:address":"Bonab\u00e9-dessous",
    "sg:city":"Saulcy",
    "sg:orig_category":"Tierheime",
    "sg:phone":"+41 32 426 51 72",
    "sg:postcode":"2873",
    "sg:province":"Jura",
    "wof:name":"Raymond Hamm Chenil & Pension Pour Animaux",
    "wof:placetype":"venue"
},
  "geometry": {"coordinates":[7.1539092064,47.3017807007],"type":"Point"}
}