{
  "type": "Feature",
  "properties": {
    "iso:country":"CH",
    "sg:address":"Nierenw\u00e4ldliweg 14",
    "sg:city":"R\u00fcttenen",
    "sg:orig_category":"Non-Classified Establishments",
    "sg:postcode":"4522",
    "sg:province":"Solothurn",
    "wof:name":"Eric Reichenbach, Eidg. Dipl. Hochbaupolier",
    "wof:placetype":"venue"
},
  "geometry": {"coordinates":[7.5286221504,47.2281913757],"type":"Point"}
}