{
  "type": "Feature",
  "properties": {
    "iso:country":"CH",
    "sg:address":"Unterau 68",
    "sg:city":"Weissbad",
    "sg:orig_category":"Gesundheitswesen",
    "sg:phone":"+41 71 799 16 80",
    "sg:postcode":"9057",
    "sg:province":"Appenzell Innerhoden",
    "wof:name":"K\u00fchnis Andrea, Massagepraxis",
    "wof:placetype":"venue"
},
  "geometry": {"coordinates":[9.4355287552,47.3037376404],"type":"Point"}
}