{
  "type": "Feature",
  "properties": {
    "iso:country":"CH",
    "sg:address":"Weisshalden 8633 Wolfhausen. Postfach",
    "sg:city":"Wolfhausen",
    "sg:orig_category":"Gemischte Landwirtschaft",
    "sg:phone":"+41 55 243 14 31",
    "sg:postcode":"8633",
    "sg:province":"Z\u00fcrich",
    "wof:name":"P\u00fcnter Stefan, Traktoren Und Landmaschinenbetrieb Landwirtschaftliche Arbeiten Gegen Entgelt Mit Hilfe Von Traktoren Und Landmaschinen Usw",
    "wof:placetype":"venue"
},
  "geometry": {"coordinates":[8.8010578156,47.259601593],"type":"Point"}
}