{
  "type": "Feature",
  "properties": {
    "iso:country":"CH",
    "sg:address":"R\u00f6ssligasse 19 4125 Riehen. Postfach",
    "sg:city":"Riehen",
    "sg:orig_category":"RESTAURANTS: TEA-ROOMS",
    "sg:postcode":"4125",
    "sg:province":"Basel-Stadt",
    "wof:name":"Aksu, Boztosun V. Restauratn U. Cafeteria Aksu",
    "wof:placetype":"venue"
},
  "geometry": {"coordinates":[7.6516342163,47.5857009888],"type":"Point"}
}