{
  "type": "Feature",
  "properties": {
    "iso:country":"CH",
    "sg:address":"Pasteur Via Luigi 1",
    "sg:city":"Chiasso",
    "sg:orig_category":"Verwaltung von Immobilien",
    "sg:phone":"+41 91 683 05 55",
    "sg:postcode":"6830",
    "sg:province":"Ticino",
    "wof:name":"Gave Sa",
    "wof:placetype":"venue"
},
  "geometry": {"coordinates":[9.0241270065,45.8334274292],"type":"Point"}
}