{
  "type": "Feature",
  "properties": {
    "iso:country":"CH",
    "sg:address":"Hauptstrasse 147",
    "sg:city":"Ermatingen",
    "sg:orig_category":"Fachdetailhandel in Verkaufsr\u00e4umen Innendekorationsateliers",
    "sg:phone":"+41 71 664 34 64",
    "sg:postcode":"8272",
    "sg:province":"Thurgau",
    "wof:name":"E. Billeter, Mon Bijou",
    "wof:placetype":"venue"
},
  "geometry": {"coordinates":[9.0864810944,47.6682548523],"type":"Point"}
}