{
  "type": "Feature",
  "properties": {
    "iso:country":"CH",
    "sg:address":"Chemin Bellevue 21 1400 Yverdon-les-bains. Postfach",
    "sg:city":"Cheseaux-nor\u00e9az",
    "sg:orig_category":"Vermietung U Verpachtung von eigenen Immobilien",
    "sg:postcode":"1400",
    "sg:province":"Vaud",
    "wof:name":"Si Cofibo Sa",
    "wof:placetype":"venue"
},
  "geometry": {"coordinates":[6.6652369499,46.7757453918],"type":"Point"}
}