{
  "type": "Feature",
  "properties": {
    "iso:country":"CH",
    "sg:address":"Vaudr\u00e8s Rue Des 11 1815 Clarens. Postfach",
    "sg:city":"Clarens",
    "sg:orig_category":"Elektroinstallation",
    "sg:phone":"+41 21 625 22 16",
    "sg:postcode":"1815",
    "sg:province":"Vaud",
    "wof:name":"Ciel Installations \u00e9lectriques",
    "wof:placetype":"venue"
},
  "geometry": {"coordinates":[6.6164579391,46.5201568604],"type":"Point"}
}