{
  "type": "Feature",
  "properties": {
    "iso:country":"CH",
    "sg:address":"Bollwiesstrasse 16",
    "sg:city":"Jona",
    "sg:orig_category":"Rechtsberatung",
    "sg:postcode":"8645",
    "sg:province":"St. Gallen",
    "wof:name":"Beratungen Zden\u00e8k",
    "wof:placetype":"venue"
},
  "geometry": {"coordinates":[8.8444290161,47.2309684753],"type":"Point"}
}