{
  "type": "Feature",
  "properties": {
    "iso:country":"CH",
    "sg:address":"Vogelsang 5",
    "sg:city":"Turgi",
    "sg:orig_category":"Herstellung von elektronischen Bauelementen",
    "sg:phone":"+41 56 201 04 88",
    "sg:postcode":"5300",
    "sg:province":"Aargau",
    "wof:name":"Bag Turgi Electronics Ag",
    "wof:placetype":"venue"
},
  "geometry": {"coordinates":[8.2520008087,47.49269104],"type":"Point"}
}