{
  "type": "Feature",
  "properties": {
    "iso:country":"CH",
    "sg:address":"Christoph Merian-ring 11",
    "sg:city":"Reinach",
    "sg:classifiers":[
        {
            "category":"Manufacturing",
            "subcategory":"Chemicals & Compounds",
            "type":"Manufacturing & Wholesale Goods"
        }
    ],
    "sg:phone":"+41 61 711 07 44",
    "sg:postcode":"4153",
    "sg:province":"Basel-Landschaft",
    "sg:tags":[
        "flavouring",
        "perfume"
    ],
    "wof:name":"Aprikus Ag",
    "wof:placetype":"venue"
},
  "geometry": {"coordinates":[7.598725,47.488815],"type":"Point"}
}