{
  "type": "Feature",
  "properties": {
    "iso:country":"CH",
    "sg:address":"Brunnersmoosstrasse",
    "sg:city":"Balsthal",
    "sg:orig_category":"Autogaragen",
    "sg:phone":"+41 62 391 02 22",
    "sg:postcode":"4710",
    "sg:province":"Solothurn",
    "wof:name":"Andreas Borer Garage",
    "wof:placetype":"venue"
},
  "geometry": {"coordinates":[7.677145,47.308361],"type":"Point"}
}