{
  "type": "Feature",
  "properties": {
    "iso:country":"CH",
    "sg:address":"Auwandel 22",
    "sg:city":"Arni-islisberg",
    "sg:orig_category":"Jugendorganisationen",
    "sg:phone":"+41 56 634 44 86",
    "sg:postcode":"8905",
    "sg:province":"Aargau",
    "wof:name":"Jugendriege Arni",
    "wof:placetype":"venue"
},
  "geometry": {"coordinates":[8.4226312637,47.3158988953],"type":"Point"}
}