{
  "type": "Feature",
  "properties": {
    "addr:full":"Rte De Cit\u00e9-des-jardins 13 Fribourg Fribourg 1700",
    "addr:housenumber":"13",
    "addr:postcode":"1700",
    "addr:street":"Rte De Cite\u0301-Des-Jardins",
    "iso:country":"CH",
    "sg:address":"Rte De Cit\u00e9-des-jardins 13",
    "sg:city":"Fribourg",
    "sg:orig_category":"Detailhandel mit Brot, Back U S\u00fcsswaren",
    "sg:postcode":"1700",
    "sg:province":"Fribourg",
    "wof:name":"Brustlein-barth D. Et M.-l.",
    "wof:placetype":"venue"
},
  "geometry": {"coordinates":[7.171481,46.809196],"type":"Point"}
}