{
  "type": "Feature",
  "properties": {
    "iso:country":"CH",
    "sg:address":"Moos 51a",
    "sg:city":"Twann",
    "sg:classifiers":[
        {
            "category":"Government",
            "subcategory":"Post Office",
            "type":"Public Place"
        }
    ],
    "sg:phone":"+41 32 315 13 75",
    "sg:postcode":"2513",
    "sg:province":"Bern",
    "sg:tags":[
        "caf\u00e9s",
        "tea-rooms"
    ],
    "wof:name":"Tea-room Moosg\u00e4rtli",
    "wof:placetype":"venue"
},
  "geometry": {"coordinates":[7.1558680534,47.0946769714],"type":"Point"}
}