{
  "type": "Feature",
  "properties": {
    "iso:country":"CH",
    "sg:address":"Unterdorf 326",
    "sg:city":"Uerkheim",
    "sg:orig_category":"Erbringung von Dienstleistungen f\u00fcr Unternehmen",
    "sg:postcode":"4813",
    "sg:province":"Aargau",
    "wof:name":"M + C Design & Autozubeh\u00f6r M\u00fcller M.",
    "wof:placetype":"venue"
},
  "geometry": {"coordinates":[8.0233659744,47.3102493286],"type":"Point"}
}