{
  "type": "Feature",
  "properties": {
    "iso:country":"CH",
    "sg:address":"Birren 18",
    "sg:city":"Seon",
    "sg:orig_category":"Herstellung von Schreibwaren U B\u00fcrobedarf aus Papier, Karton U Pappe",
    "sg:phone":"+41 62 775 45 60",
    "sg:postcode":"5703",
    "sg:province":"Aargau",
    "wof:name":"Jestor Ag",
    "wof:placetype":"venue"
},
  "geometry": {"coordinates":[8.1676979065,47.3620300293],"type":"Point"}
}