{
  "type": "Feature",
  "properties": {
    "iso:country":"CH",
    "sg:address":"Bruderholzstrasse 41",
    "sg:city":"M\u00fcnchenstein",
    "sg:orig_category":"RESTAURANTS: TEA-ROOMS",
    "sg:phone":"+41 61 411 81 81",
    "sg:postcode":"4142",
    "sg:province":"Basel-Landschaft",
    "wof:name":"Mutti Peter",
    "wof:placetype":"venue"
},
  "geometry": {"coordinates":[7.6042780876,47.5258331299],"type":"Point"}
}