{
  "type": "Feature",
  "properties": {
    "iso:country":"CH",
    "sg:address":"Wagnerstrasse 11",
    "sg:city":"Bern",
    "sg:orig_category":"Stukkateurgewerbe, Gipserei U Verputzerei",
    "sg:phone":"+41 31 372 43 72",
    "sg:postcode":"3007",
    "sg:province":"Bern",
    "wof:name":"Gipser Und Malergenossenschaft Bern",
    "wof:placetype":"venue"
},
  "geometry": {"coordinates":[7.4244861603,46.9439926147],"type":"Point"}
}