{
  "type": "Feature",
  "properties": {
    "iso:country":"CH",
    "sg:address":"Herrenweg 7",
    "sg:city":"Allschwil",
    "sg:orig_category":"Grosshandel mit Nahrungsmitteln, Getr\u00e4nken U Tabakwaren ohne ausgepr\u00e4gten Schwerpunkt",
    "sg:phone":"+41 71 911 12 64",
    "sg:postcode":"4123",
    "sg:province":"Basel-Landschaft",
    "wof:name":"Bischof Lebensmittel.",
    "wof:placetype":"venue"
},
  "geometry": {"coordinates":[9.0450754166,47.4627914429],"type":"Point"}
}