{
  "type": "Feature",
  "properties": {
    "iso:country":"CH",
    "sg:address":"Praz-s\u00e9chaud Chemin De 6 1010 Lausanne. Postfach",
    "sg:city":"Lausanne",
    "sg:orig_category":"Fachdetailhandel in Verkaufsr\u00e4umen",
    "sg:postcode":"1010",
    "sg:province":"Vaud",
    "wof:name":"Egemen S\u00e0rl Bijouteries, Horlogeries, Joailleries Etc",
    "wof:placetype":"venue"
},
  "geometry": {"coordinates":[6.664981842,46.5373001099],"type":"Point"}
}