{
  "type": "Feature",
  "properties": {
    "iso:country":"CH",
    "sg:address":"Paradiesstrasse 11",
    "sg:city":"Binningen",
    "sg:orig_category":"Arztpraxen",
    "sg:phone":"+41 61 421 21 22",
    "sg:postcode":"4102",
    "sg:province":"Basel-Landschaft",
    "wof:name":"Dr.med. Lilian Saemann Spezial\u00e4rztin",
    "wof:placetype":"venue"
},
  "geometry": {"coordinates":[7.569499,47.538013],"type":"Point"}
}