{
  "type": "Feature",
  "properties": {
    "iso:country":"CH",
    "sg:address":"Brunaustrasse 74",
    "sg:city":"Z\u00fcrich",
    "sg:orig_category":"Maler U Glasergewerbe",
    "sg:postcode":"8002",
    "sg:province":"Z\u00fcrich",
    "wof:name":"Asr Malergesch\u00e4ft Gmbh",
    "wof:placetype":"venue"
},
  "geometry": {"coordinates":[8.5251121521,47.353843689],"type":"Point"}
}