{
  "type": "Feature",
  "properties": {
    "iso:country":"CH",
    "sg:address":"B\u00fcren 9",
    "sg:city":"Gansingen",
    "sg:orig_category":"Herstellung von Reiseartikeln, Leder U Sattlerwaren Innendekorationsateliers",
    "sg:phone":"+41 62 875 23 38",
    "sg:postcode":"5272",
    "sg:province":"Aargau",
    "wof:name":"Egloff Arnold Wohngestaltung",
    "wof:placetype":"venue"
},
  "geometry": {"coordinates":[8.1384716034,47.5326423645],"type":"Point"}
}