{
  "type": "Feature",
  "properties": {
    "iso:country":"CH",
    "sg:address":"Piller Route Andr\u00e9 33e",
    "sg:city":"Givisiez",
    "sg:orig_category":"Herstellung von Werkzeugen",
    "sg:postcode":"1762",
    "sg:province":"Fribourg",
    "wof:name":"Diamant Boart Schweiz Ag",
    "wof:placetype":"venue"
},
  "geometry": {"coordinates":[7.117128849,46.811794281],"type":"Point"}
}