{
  "type": "Feature",
  "properties": {
    "iso:country":"CH",
    "sg:address":"Ifangstrasse 91 8153 R\u00fcmlang. Postfach 475",
    "sg:city":"Z\u00fcrich",
    "sg:orig_category":"Erbringung von Dienstleistungen f\u00fcr Unternehmen Pers\u00f6nliche Dienstleistungen",
    "sg:phone":"+41 18188000",
    "sg:postcode":"8052",
    "sg:province":"Z\u00fcrich",
    "wof:name":"Inkasso Arena Ag",
    "wof:placetype":"venue"
},
  "geometry": {"coordinates":[8.5381784439,47.4470672607],"type":"Point"}
}