{
  "type": "Feature",
  "properties": {
    "iso:country":"CH",
    "sg:address":"Richard-wagner-weg 15",
    "sg:city":"Luzern",
    "sg:orig_category":"Primarschulen",
    "sg:phone":"+41 41 368 08 42",
    "sg:postcode":"6005",
    "sg:province":"Luzern",
    "wof:name":"Primarschule Tribschen",
    "wof:placetype":"venue"
},
  "geometry": {"coordinates":[8.3258247375,47.0414619446],"type":"Point"}
}