{
  "type": "Feature",
  "properties": {
    "iso:country":"CH",
    "sg:address":"Via Muraccio 6",
    "sg:city":"Ascona",
    "sg:orig_category":"Autospenglereien",
    "sg:phone":"+41 91 791 20 31",
    "sg:postcode":"6612",
    "sg:province":"Ticino",
    "wof:name":"Sergio Stoppa Carrozzeria",
    "wof:placetype":"venue"
},
  "geometry": {"coordinates":[8.774374,46.154137],"type":"Point"}
}