{
  "type": "Feature",
  "properties": {
    "addr:full":"Meilistrasse 18 Winterthur Z\u00fcrich 8400",
    "addr:housenumber":"18",
    "addr:postcode":"8400",
    "addr:street":"Meilistrasse",
    "iso:country":"CH",
    "sg:address":"Meilistrasse 18",
    "sg:city":"Winterthur",
    "sg:orig_category":"Architektur U Ingenieurb\u00fcros",
    "sg:phone":"+41 79 417 75 69",
    "sg:postcode":"8400",
    "sg:province":"Z\u00fcrich",
    "wof:name":"Schiesser Bauingenieur Und Architekturb\u00fcro",
    "wof:placetype":"venue"
},
  "geometry": {"coordinates":[9.052732,46.976513],"type":"Point"}
}