{
  "type": "Feature",
  "properties": {
    "iso:country":"CH",
    "sg:address":"Dietlikonstrasse 18",
    "sg:city":"D\u00fcbendorf",
    "sg:orig_category":"Sanit\u00e4r U Heizungsinstallation Sanit\u00e4r, Heizungs U L\u00fcftungsinstallation",
    "sg:postcode":"8600",
    "sg:province":"Z\u00fcrich",
    "wof:name":"Dettling Gilbert",
    "wof:placetype":"venue"
},
  "geometry": {"coordinates":[8.6263170242,47.4046516418],"type":"Point"}
}