{
  "type": "Feature",
  "properties": {
    "iso:country":"CH",
    "sg:address":"Marktgasse 60",
    "sg:city":"Winterthur",
    "sg:orig_category":"Interessenvertretungen Vereine Z\u00fcnfte",
    "sg:postcode":"8400",
    "sg:province":"Z\u00fcrich",
    "wof:name":"Zunft Zum Turm",
    "wof:placetype":"venue"
},
  "geometry": {"coordinates":[8.7279701233,47.4996490479],"type":"Point"}
}