{
  "type": "Feature",
  "properties": {
    "iso:country":"CH",
    "sg:address":"Gotenstrasse 1",
    "sg:city":"Bern",
    "sg:orig_category":"Fachdetailhandel mit pharmazeutischen Produkten",
    "sg:phone":"+41 31 992 36 66",
    "sg:postcode":"3018",
    "sg:province":"Bern",
    "wof:name":"Schermen Apotheke Mauron",
    "wof:placetype":"venue"
},
  "geometry": {"coordinates":[7.3988471031,46.9439086914],"type":"Point"}
}