{
  "type": "Feature",
  "properties": {
    "iso:country":"CH",
    "sg:address":"Sonnmattstrasse 13",
    "sg:city":"Sarnen",
    "sg:orig_category":"Grosshandel mit Getr\u00e4nken",
    "sg:postcode":"6060",
    "sg:province":"Obwalden",
    "wof:name":"Agentur Jufer",
    "wof:placetype":"venue"
},
  "geometry": {"coordinates":[8.0787630081,47.3936424255],"type":"Point"}
}