{
  "type": "Feature",
  "properties": {
    "iso:country":"CH",
    "sg:address":"7504",
    "sg:city":"Pontresina",
    "sg:orig_category":"Saunas Schwimmb\u00e4der",
    "sg:phone":"+41 81 842 66 20",
    "sg:postcode":"7504",
    "sg:province":"Graubunden",
    "wof:name":"Hallenschwimmbad",
    "wof:placetype":"venue"
},
  "geometry": {"coordinates":[9.9019098282,46.4935150146],"type":"Point"}
}