{
  "type": "Feature",
  "properties": {
    "iso:country":"CH",
    "sg:address":"Oberdorf 1",
    "sg:city":"Krauchthal",
    "sg:orig_category":"Detailhandel mit Fleisch U Fleischwaren",
    "sg:phone":"+41 34 411 14 11",
    "sg:postcode":"3326",
    "sg:province":"Bern",
    "wof:name":"Ewald Trachsel Metzgerei",
    "wof:placetype":"venue"
},
  "geometry": {"coordinates":[7.5678501129,47.0088005066],"type":"Point"}
}