{
  "type": "Feature",
  "properties": {
    "iso:country":"CH",
    "sg:address":"Bahnhofstrasse 57",
    "sg:city":"Landquart",
    "sg:orig_category":"Herstellung von Sportger\u00e4ten Vermietung von Gebrauchsg\u00fctern",
    "sg:phone":"+41 81 322 45 20",
    "sg:postcode":"7302",
    "sg:province":"Graubunden",
    "wof:name":"Niklaus Badrutt Nb-climb Kletterw\u00e4nde",
    "wof:placetype":"venue"
},
  "geometry": {"coordinates":[9.5624904633,46.968170166],"type":"Point"}
}