{
  "type": "Feature",
  "properties": {
    "iso:country":"CH",
    "sg:address":"Sinserstrasse 3 6330 Cham. Postfach 172",
    "sg:city":"Cham",
    "sg:orig_category":"Detailhandel mit Uhren U Schmuck Grosshandel mit Erzen U Metallen",
    "sg:phone":"+41 41 780 11 67",
    "sg:postcode":"6330",
    "sg:province":"Zug",
    "wof:name":"Enzler Pius",
    "wof:placetype":"venue"
},
  "geometry": {"coordinates":[8.4586162567,47.1815071106],"type":"Point"}
}