{
  "type": "Feature",
  "properties": {
    "iso:country":"CH",
    "sg:address":"Rue De Fin-de-praz 2a 2024 St-aubin-sauges Case Postale 66",
    "sg:city":"St-aubin-sauges",
    "sg:orig_category":"Hobel U Holzimpr\u00e4gnierwerke S\u00e4gewerke",
    "sg:phone":"+41 79 637 29 57",
    "sg:postcode":"2024",
    "sg:province":"Neuch\u00e2tel",
    "wof:name":"Burgat Sa",
    "wof:placetype":"venue"
},
  "geometry": {"coordinates":[6.7777261734,46.8959350586],"type":"Point"}
}