{
  "type": "Feature",
  "properties": {
    "iso:country":"CH",
    "sg:address":"8574",
    "sg:city":"Lengwil-oberhofen",
    "sg:orig_category":"Primarschulen",
    "sg:phone":"+41 33 243 13 66",
    "sg:postcode":"8574",
    "sg:province":"Thurgau",
    "wof:name":"Primarschule Oberhofen",
    "wof:placetype":"venue"
},
  "geometry": {"coordinates":[8.1313076019,47.5544433594],"type":"Point"}
}