{
  "type": "Feature",
  "properties": {
    "iso:country":"CH",
    "sg:address":"Welsikerstrasse 13",
    "sg:city":"Dinhard",
    "sg:orig_category":"Arztpraxen",
    "sg:phone":"+41 52 336 19 38",
    "sg:postcode":"8474",
    "sg:province":"Z\u00fcrich",
    "wof:name":"Dr.med.martin Eidenbenz Spezialarzt Fmh",
    "wof:placetype":"venue"
},
  "geometry": {"coordinates":[8.767724,47.555126],"type":"Point"}
}