{
  "type": "Feature",
  "properties": {
    "iso:country":"CH",
    "sg:address":"Buckstrasse 37",
    "sg:city":"Endingen",
    "sg:orig_category":"Grosshandel mit B\u00fcromaschinen Grosshandel mit Datenverarbeitungsger\u00e4ten",
    "sg:phone":"+41 56 242 19 89",
    "sg:postcode":"5304",
    "sg:province":"Aargau",
    "wof:name":"Computer-service Kl\u00e4y",
    "wof:placetype":"venue"
},
  "geometry": {"coordinates":[8.2973508835,47.5349121094],"type":"Point"}
}