{
  "type": "Feature",
  "properties": {
    "iso:country":"CH",
    "sg:address":"Spalenring 126 4055 Basel. Postfach",
    "sg:city":"Basel",
    "sg:orig_category":"RESTAURANTS: TEA-ROOMS",
    "sg:postcode":"4051",
    "sg:province":"Basel-Stadt",
    "wof:name":"O.c.a.m. Gmbh",
    "wof:placetype":"venue"
},
  "geometry": {"coordinates":[7.5755581856,47.5557289124],"type":"Point"}
}