{
  "type": "Feature",
  "properties": {
    "iso:country":"CH",
    "sg:address":"B\u00f6szelg 50",
    "sg:city":"Z\u00fcrich",
    "sg:classifiers":[
        {
            "category":"Utilities",
            "subcategory":"Natural Gas",
            "type":"Services"
        }
    ],
    "sg:phone":"+41 13400202",
    "sg:postcode":"8051",
    "sg:province":"Z\u00fcrich",
    "sg:tags":[
        "heater",
        "electric"
    ],
    "wof:name":"A Bis Z Allrounder Gmbh",
    "wof:placetype":"venue"
},
  "geometry": {"coordinates":[8.5887413025,47.3950538635],"type":"Point"}
}