{
  "type": "Feature",
  "properties": {
    "iso:country":"CH",
    "sg:address":"Gartenstrasse 3",
    "sg:city":"Zug",
    "sg:orig_category":"Non-Classified Establishments",
    "sg:phone":"+41 71 333 37 51",
    "sg:postcode":"6300",
    "sg:province":"Zug",
    "wof:name":"Nove Marzo Ag",
    "wof:placetype":"venue"
},
  "geometry": {"coordinates":[9.3814573288,47.3907775879],"type":"Point"}
}