{
  "type": "Feature",
  "properties": {
    "iso:country":"CH",
    "sg:address":"Seestrasse 9",
    "sg:city":"Richterswil",
    "sg:orig_category":"Unternehmensberatung Verlagsgewerbe",
    "sg:phone":"+41 17867200",
    "sg:postcode":"8805",
    "sg:province":"Z\u00fcrich",
    "wof:name":"Think Tank Gmbh Waren U. Dienstleistungen, Bes. Unternehmens- U. Personalberatung F\u00fcr High-tech U. It-unternehmen; Handel U. Vermittlung",
    "wof:placetype":"venue"
},
  "geometry": {"coordinates":[8.7098197937,47.2059822083],"type":"Point"}
}