{
  "type": "Feature",
  "properties": {
    "iso:country":"CH",
    "sg:address":"Route Gollion 9",
    "sg:city":"Penthalaz",
    "sg:orig_category":"Haltung von Schweinen",
    "sg:phone":"+41 21 861 20 21",
    "sg:postcode":"1305",
    "sg:province":"Vaud",
    "wof:name":"Station D'elevage De Porcs Spf Sa",
    "wof:placetype":"venue"
},
  "geometry": {"coordinates":[6.5247030258,46.6025886536],"type":"Point"}
}