{
  "type": "Feature",
  "properties": {
    "iso:country":"CH",
    "sg:address":"Sandgrubenstrasse 1 8404 Oberwinterthur. Postfach",
    "sg:city":"Oberwinterthur",
    "sg:orig_category":"Grosshandel mit sonstigen Maschinen U Ausr\u00fcstungen f\u00fcr Industrie, Handel U Schiffahrt",
    "sg:postcode":"8404",
    "sg:province":"Z\u00fcrich",
    "wof:name":"Wenger Automation & Engineering Ag",
    "wof:placetype":"venue"
},
  "geometry": {"coordinates":[8.7722034454,47.5034713745],"type":"Point"}
}