{
  "type": "Feature",
  "properties": {
    "iso:country":"CH",
    "sg:address":"Pfrundweg 7",
    "sg:city":"D\u00fcdingen",
    "sg:orig_category":"Vermietung von Automobilen",
    "sg:phone":"+41 26 493 29 79",
    "sg:postcode":"3186",
    "sg:province":"Fribourg",
    "wof:name":"Autovermietung Memra",
    "wof:placetype":"venue"
},
  "geometry": {"coordinates":[7.1966300011,46.8427886963],"type":"Point"}
}