{
  "type": "Feature",
  "properties": {
    "iso:country":"CH",
    "sg:address":"Lance Avenue Eug\u00e8ne 11",
    "sg:city":"Grand-lancy",
    "sg:orig_category":"Grosshandel mit Holz U Baustoffen",
    "sg:postcode":"1212",
    "sg:province":"Gen\u00e8ve",
    "wof:name":"Jba Sa",
    "wof:placetype":"venue"
},
  "geometry": {"coordinates":[6.12292099,46.1822242737],"type":"Point"}
}