{
  "type": "Feature",
  "properties": {
    "iso:country":"CH",
    "sg:address":"Dufourstrasse 161",
    "sg:city":"St.gallen",
    "sg:orig_category":"RESTAURANTS: TEA-ROOMS",
    "sg:phone":"+41 71 277 62 43",
    "sg:postcode":"9000",
    "sg:province":"St. Gallen",
    "wof:name":"K\u00fcnzle Gastro",
    "wof:placetype":"venue"
},
  "geometry": {"coordinates":[9.3573045731,47.4220619202],"type":"Point"}
}