{
  "type": "Feature",
  "properties": {
    "iso:country":"CH",
    "sg:address":"Breitenweg 10",
    "sg:city":"Stans",
    "sg:orig_category":"Non-Classified Establishments",
    "sg:phone":"+41 71 898 35 00",
    "sg:postcode":"6370",
    "sg:province":"Nidwalden",
    "wof:name":"Erd Services Ag",
    "wof:placetype":"venue"
},
  "geometry": {"coordinates":[9.495141983,47.4422225952],"type":"Point"}
}