{
  "type": "Feature",
  "properties": {
    "iso:country":"CH",
    "sg:address":"B\u00fcntacher 31",
    "sg:city":"Hermetschwil-staff",
    "sg:orig_category":"Vereine Frauen Vereine Gemeinn\u00fctzige",
    "sg:phone":"+41 56 633 42 08",
    "sg:postcode":"5626",
    "sg:province":"Aargau",
    "wof:name":"Landfrauen Hermetschwil",
    "wof:placetype":"venue"
},
  "geometry": {"coordinates":[8.339304924,47.3279724121],"type":"Point"}
}