{
  "type": "Feature",
  "properties": {
    "iso:country":"CH",
    "sg:address":"Zugerstrasse 77 6340 Baar. Postfach",
    "sg:city":"Zug",
    "sg:orig_category":"Detektivb\u00fcros U \u00dcberwachung",
    "sg:phone":"+41 41 768 60 30",
    "sg:postcode":"6301",
    "sg:province":"Zug",
    "wof:name":"Securitas Ag Schweiz.bewachungsgesellschaft",
    "wof:placetype":"venue"
},
  "geometry": {"coordinates":[8.5199966431,47.1830482483],"type":"Point"}
}