{
  "type": "Feature",
  "properties": {
    "iso:country":"CH",
    "sg:address":"Via Luigi Lavizzari 19a 6850 Mendrisio. Postfach Caselle Postale 180",
    "sg:city":"Mendrisio",
    "sg:orig_category":"Advokaturb\u00fcros Notariate",
    "sg:phone":"+41 91 646 06 76",
    "sg:postcode":"6850",
    "sg:province":"Ticino",
    "wof:name":"Padlina & Baggio Studio Legale & Notarile",
    "wof:placetype":"venue"
},
  "geometry": {"coordinates":[8.986616,45.870468],"type":"Point"}
}