{
  "type": "Feature",
  "properties": {
    "iso:country":"CH",
    "sg:address":"6468",
    "sg:city":"Attinghausen",
    "sg:orig_category":"Herstellung von Konstruktionsteilen, Fertigbauteilen U Ausbauelementen aus Holz",
    "sg:postcode":"6468",
    "sg:province":"Uri",
    "wof:name":"Aschwanden Arthur Schreinerei",
    "wof:placetype":"venue"
},
  "geometry": {"coordinates":[8.6281385422,46.866558075],"type":"Point"}
}