{
  "type": "Feature",
  "properties": {
    "addr:full":"Breitlen 8 Basadingen Thurgau 8254",
    "addr:housenumber":"8",
    "addr:postcode":"8254",
    "addr:street":"Breitlen",
    "iso:country":"CH",
    "sg:address":"Breitlen 8",
    "sg:city":"Basadingen",
    "sg:orig_category":"Bauspenglerei Zimmerei, Dachdeckerei, Bauspenglerei U Abdichtung",
    "sg:phone":"+41 62 822 03 22",
    "sg:postcode":"8254",
    "sg:province":"Thurgau",
    "wof:name":"Ulrich Wyssling",
    "wof:placetype":"venue"
},
  "geometry": {"coordinates":[8.078823,47.386395],"type":"Point"}
}