{
  "type": "Feature",
  "properties": {
    "iso:country":"CH",
    "sg:address":"4655",
    "sg:city":"St\u00fcsslingen",
    "sg:orig_category":"Vereine Musik/Blasmusik",
    "sg:postcode":"4655",
    "sg:province":"Solothurn",
    "wof:name":"Musikgesellschaft",
    "wof:placetype":"venue"
},
  "geometry": {"coordinates":[7.9209198952,47.3165397644],"type":"Point"}
}