{
  "type": "Feature",
  "properties": {
    "iso:country":"CH",
    "sg:address":"Chemin De La Milice 20/22",
    "sg:city":"Plan-les-ouates",
    "sg:orig_category":"Grosshandel mit Getr\u00e4nken",
    "sg:phone":"+41 22 706 22 33",
    "sg:postcode":"1228",
    "sg:province":"Gen\u00e8ve",
    "wof:name":"Liechti J. & Fils",
    "wof:placetype":"venue"
},
  "geometry": {"coordinates":[6.1259841919,46.1687698364],"type":"Point"}
}