{
  "type": "Feature",
  "properties": {
    "iso:country":"CH",
    "sg:address":"Rheinstrasse 22",
    "sg:city":"Diessenhofen",
    "sg:orig_category":"Massagestudios",
    "sg:phone":"+41 52 657 48 40",
    "sg:postcode":"8253",
    "sg:province":"Thurgau",
    "wof:name":"Goran Orlic Massage Praxis",
    "wof:placetype":"venue"
},
  "geometry": {"coordinates":[8.7479372025,47.6904296875],"type":"Point"}
}