{
  "type": "Feature",
  "properties": {
    "iso:country":"CH",
    "sg:address":"Stadthausstrasse 2",
    "sg:city":"Luzern",
    "sg:orig_category":"Unternehmensberatung",
    "sg:phone":"+41 41 210 15 33",
    "sg:postcode":"6003",
    "sg:province":"Luzern",
    "wof:name":"Urs Kauffmann Gmbh",
    "wof:placetype":"venue"
},
  "geometry": {"coordinates":[8.3055047989,47.0494117737],"type":"Point"}
}