{
  "type": "Feature",
  "properties": {
    "iso:country":"CH",
    "sg:address":"Baslerstrasse 10",
    "sg:city":"Trimbach",
    "sg:orig_category":"Instandhaltung U Reparatur von Automobilen",
    "sg:phone":"+41 62 293 25 23",
    "sg:postcode":"4632",
    "sg:province":"Solothurn",
    "wof:name":"Hanyk Zdenek",
    "wof:placetype":"venue"
},
  "geometry": {"coordinates":[7.9009199142,47.3573493958],"type":"Point"}
}