{
  "type": "Feature",
  "properties": {
    "iso:country":"CH",
    "sg:address":"Poststrasse 18",
    "sg:city":"Zug",
    "sg:orig_category":"Unclassifiable Establishments",
    "sg:phone":"+41 41 729 69 89",
    "sg:postcode":"6300",
    "sg:province":"Zug",
    "wof:name":"Swaropart Ag",
    "wof:placetype":"venue"
},
  "geometry": {"coordinates":[8.5168533325,47.1703605652],"type":"Point"}
}