{
  "type": "Feature",
  "properties": {
    "iso:country":"CH",
    "sg:address":"Grimselpassh\u00f6he Hotel Grimsel 3864 Guttannen. Postfach",
    "sg:city":"Guttannen",
    "sg:orig_category":"Botanische U zoologische G\u00e4rten sowie Naturparks",
    "sg:phone":"+41 27 761 15 62",
    "sg:postcode":"3864",
    "sg:province":"Bern",
    "wof:name":"Piscine & Zoo Des Mar\u00e9cottes",
    "wof:placetype":"venue"
},
  "geometry": {"coordinates":[7.012272,46.114796],"type":"Point"}
}