{
  "type": "Feature",
  "properties": {
    "iso:country":"CH",
    "sg:address":"Vernand Rte De Bl\u00e9cherette 8a 1000 Lausanne. Postfach",
    "sg:city":"Lausanne",
    "sg:orig_category":"Sonstige mit der Informatik verbundene T\u00e4tigkeiten",
    "sg:postcode":"1000",
    "sg:province":"Vaud",
    "wof:name":"Agrebi Computer Business Consulting",
    "wof:placetype":"venue"
},
  "geometry": {"coordinates":[6.6947751045,46.5545883179],"type":"Point"}
}