{
  "type": "Feature",
  "properties": {
    "iso:country":"CH",
    "sg:address":"Vela Via Vincenzo 11",
    "sg:city":"Locarno",
    "sg:orig_category":"Beherbergungsgewerbe",
    "sg:phone":"+41 91 751 88 35",
    "sg:postcode":"6600",
    "sg:province":"Ticino",
    "wof:name":"Fondazione Pedrazzini Alberto Colonia Climatica Di Cerentino",
    "wof:placetype":"venue"
},
  "geometry": {"coordinates":[8.795318,46.167488],"type":"Point"}
}