{
  "type": "Feature",
  "properties": {
    "iso:country":"CH",
    "sg:address":"3822",
    "sg:city":"Lauterbrunnen",
    "sg:orig_category":"RESTAURANTS: TEA-ROOMS",
    "sg:postcode":"3822",
    "sg:province":"Bern",
    "wof:name":"Thomas Trachsel",
    "wof:placetype":"venue"
},
  "geometry": {"coordinates":[7.9075479507,46.5979499817],"type":"Point"}
}