{
  "type": "Feature",
  "properties": {
    "iso:country":"CH",
    "sg:address":"Lorrainestrasse 19+21 3013 Bern. Postfach",
    "sg:city":"Bern",
    "sg:orig_category":"Detailhandel mit elektrischen Haushalts-,Radio U Fernsehger\u00e4ten sowie Musikinstrumenten",
    "sg:phone":"+41 31 331 23 24",
    "sg:postcode":"3005",
    "sg:province":"Bern",
    "wof:name":"Gr\u00fcnig Radio-tv Ag Fernseh, Radio, Hi-fi-ger\u00e4te Usw; Handel, Installation, Rep.",
    "wof:placetype":"venue"
},
  "geometry": {"coordinates":[7.4446687698,46.9568214417],"type":"Point"}
}