{
  "type": "Feature",
  "properties": {
    "iso:country":"CH",
    "sg:address":"Sch\u00f6naustrasse 19",
    "sg:city":"Baden",
    "sg:orig_category":"Architekturb\u00fcros",
    "sg:phone":"+41 56 221 66 46",
    "sg:postcode":"5400",
    "sg:province":"Aargau",
    "wof:name":"Thomas & Franziska Hasler Architekturb\u00fcro",
    "wof:placetype":"venue"
},
  "geometry": {"coordinates":[8.31609,47.47044],"type":"Point"}
}