{
  "type": "Feature",
  "properties": {
    "iso:country":"CH",
    "sg:address":"Florastrasse 32 2502 Biel/bienne. Postfach",
    "sg:city":"Biel/bienne",
    "sg:orig_category":"Zahnarztpraxen",
    "sg:phone":"+41 32 329 30 30",
    "sg:postcode":"2501",
    "sg:province":"Bern",
    "wof:name":"Dr. Med. Dent. Dieter Stuck Zahnarzt",
    "wof:placetype":"venue"
},
  "geometry": {"coordinates":[7.2493472099,47.1389007568],"type":"Point"}
}