{
  "type": "Feature",
  "properties": {
    "iso:country":"CH",
    "sg:address":"3453",
    "sg:city":"Heimisbach",
    "sg:orig_category":"Bauspenglerei Sanit\u00e4rinstallation U Spenglerei",
    "sg:phone":"+41 34 431 11 92",
    "sg:postcode":"3453",
    "sg:province":"Bern",
    "wof:name":"David Ramseier",
    "wof:placetype":"venue"
},
  "geometry": {"coordinates":[7.76031,47.011749],"type":"Point"}
}