{
  "type": "Feature",
  "properties": {
    "iso:country":"CH",
    "sg:address":"Birmihalde 1",
    "sg:city":"Aegeri",
    "sg:orig_category":"Non-Classified Establishments",
    "sg:postcode":"6314",
    "sg:province":"Zug",
    "wof:name":"Zuger Verband Der Friedensrichter",
    "wof:placetype":"venue"
},
  "geometry": {"coordinates":[8.5626058578,47.1532859802],"type":"Point"}
}