{
  "type": "Feature",
  "properties": {
    "iso:country":"CH",
    "sg:address":"Ohne Dom.",
    "sg:city":"M\u00f6rel",
    "sg:orig_category":"Allgemeiner Hoch U Tiefbau",
    "sg:phone":"+41 61 319 94 42",
    "sg:postcode":"3983",
    "sg:province":"Valais",
    "wof:name":"Bawal Bau Ag",
    "wof:placetype":"venue"
},
  "geometry": {"coordinates":[8.045341,46.35556],"type":"Point"}
}