{
  "type": "Feature",
  "properties": {
    "iso:country":"CH",
    "sg:address":"Luzernstrasse 33",
    "sg:city":"Malters",
    "sg:orig_category":"Hoch U Tiefbau",
    "sg:phone":"+41 41 497 26 30",
    "sg:postcode":"6102",
    "sg:province":"Luzern",
    "wof:name":"Roger Bucheli Baugesch\u00e4ft",
    "wof:placetype":"venue"
},
  "geometry": {"coordinates":[8.1763696671,47.0365600586],"type":"Point"}
}