{
  "type": "Feature",
  "properties": {
    "iso:country":"CH",
    "sg:address":"Grand-pont Rue Du 1003 Lausanne. Postfach",
    "sg:city":"Lausanne",
    "sg:orig_category":"Vermietung U Verpachtung von eigenen Immobilien",
    "sg:postcode":"1003",
    "sg:province":"Vaud",
    "wof:name":"La Sendaz Sa",
    "wof:placetype":"venue"
},
  "geometry": {"coordinates":[6.6301088333,46.5216293335],"type":"Point"}
}