{
  "type": "Feature",
  "properties": {
    "iso:country":"CH",
    "sg:address":"Fabrikstrasse 8",
    "sg:city":"Sirnach",
    "sg:orig_category":"Sanit\u00e4r, Heizungs U L\u00fcftungsinstallation Sanit\u00e4rinstallation",
    "sg:phone":"+41 31 809 30 44",
    "sg:postcode":"8370",
    "sg:province":"Thurgau",
    "wof:name":"Wasserfallen & B\u00fchlmann",
    "wof:placetype":"venue"
},
  "geometry": {"coordinates":[7.4485859871,46.7816314697],"type":"Point"}
}