{
  "type": "Feature",
  "properties": {
    "iso:country":"CH",
    "sg:address":"Hausstr. 5",
    "sg:city":"Baar",
    "sg:classifiers":[
        {
            "category":"Utilities",
            "subcategory":"Telephone",
            "type":"Services"
        }
    ],
    "sg:phone":"+41 41 768 67 67",
    "sg:postcode":"6342",
    "sg:province":"Zug",
    "sg:tags":[
        "telecommunication"
    ],
    "wof:name":"Miracom Ag",
    "wof:placetype":"venue"
},
  "geometry": {"coordinates":[8.5262966156,47.1947250366],"type":"Point"}
}