{
  "type": "Feature",
  "properties": {
    "iso:country":"CH",
    "sg:address":"Vogt Bvd Carl- 53 1205 Gen\u00e8ve. Postfach",
    "sg:city":"Gen\u00e8ve",
    "sg:orig_category":"Fleischverarbeitung",
    "sg:phone":"+41 81 854 14 40",
    "sg:postcode":"1205",
    "sg:province":"Gen\u00e8ve",
    "wof:name":"Laudenbacher Riccardo",
    "wof:placetype":"venue"
},
  "geometry": {"coordinates":[9.9322147369,46.5750732422],"type":"Point"}
}