{
  "type": "Feature",
  "properties": {
    "iso:country":"CH",
    "sg:address":"Hauptstrasse 11 5604 Hendschiken. Postfach",
    "sg:city":"Hendschiken",
    "sg:orig_category":"Maler U Glasergewerbe Malerei",
    "sg:postcode":"5604",
    "sg:province":"Aargau",
    "wof:name":"Malermeister Obrist Gmbh",
    "wof:placetype":"venue"
},
  "geometry": {"coordinates":[8.2183580399,47.3868293762],"type":"Point"}
}