{
  "type": "Feature",
  "properties": {
    "iso:country":"CH",
    "sg:address":"Rankenweg 6",
    "sg:city":"Biberist",
    "sg:orig_category":"Fussreflexzonenmassage",
    "sg:phone":"+41 32 672 30 23",
    "sg:postcode":"4562",
    "sg:province":"Solothurn",
    "wof:name":"Marlis L\u00fcdi Fuss-& Ganzk\u00f6rpermassage",
    "wof:placetype":"venue"
},
  "geometry": {"coordinates":[7.5583891869,47.1744766235],"type":"Point"}
}