{
  "type": "Feature",
  "properties": {
    "iso:country":"CH",
    "sg:address":"Landstrasse 182",
    "sg:city":"Klosters",
    "sg:orig_category":"Detailhandel mit Beleuchtungs U Haushaltsgegenst\u00e4nden Detailhandel mit elektrischen Haushalts-,Radio",
    "sg:phone":"+41 81 422 14 78",
    "sg:postcode":"7250",
    "sg:province":"Graubunden",
    "wof:name":"Jegen S. Ag",
    "wof:placetype":"venue"
},
  "geometry": {"coordinates":[9.883055,46.867134],"type":"Point"}
}