{
  "type": "Feature",
  "properties": {
    "iso:country":"CH",
    "sg:address":"Sura Via 66",
    "sg:city":"Zernez",
    "sg:orig_category":"Sonstiger Grosshandel",
    "sg:postcode":"7530",
    "sg:province":"Graubunden",
    "wof:name":"Bezzola Duri R. + Co",
    "wof:placetype":"venue"
},
  "geometry": {"coordinates":[10.0933980942,46.699180603],"type":"Point"}
}