{
  "type": "Feature",
  "properties": {
    "iso:country":"CH",
    "sg:address":"Luzernerstrasse 3 6247 Sch\u00f6tz. Postfach",
    "sg:city":"Sch\u00f6tz",
    "sg:orig_category":"Detailhandel mit Sportartikeln Fachdetailhandel in Verkaufsr\u00e4umen",
    "sg:phone":"+41 41 980 29 33",
    "sg:postcode":"6247",
    "sg:province":"Luzern",
    "wof:name":"Kunz Sport",
    "wof:placetype":"venue"
},
  "geometry": {"coordinates":[7.9897108078,47.1705055237],"type":"Point"}
}