{
  "type": "Feature",
  "properties": {
    "iso:country":"CH",
    "sg:address":"Steigstrasse 9",
    "sg:city":"Feuerthalen",
    "sg:orig_category":"Bauschreinerei Herstellung von Konstruktionsteilen, Fertigbauteilen U Ausbauelementen aus Holz",
    "sg:phone":"+41 52 659 23 77",
    "sg:postcode":"8245",
    "sg:province":"Z\u00fcrich",
    "wof:name":"Gasser Peter Schreinerei Ag Schreinerei, Glaserei, Innenausbau, Montagebau U. Warenhandel",
    "wof:placetype":"venue"
},
  "geometry": {"coordinates":[8.639358,47.692417],"type":"Point"}
}