{
  "type": "Feature",
  "properties": {
    "iso:country":"CH",
    "sg:address":"Luzernerstrasse 3",
    "sg:city":"Sursee",
    "sg:orig_category":"Interessenvertretungen",
    "sg:phone":"+41 41 921 33 46",
    "sg:postcode":"6210",
    "sg:province":"Luzern",
    "wof:name":"Beck-stiftung, Carl",
    "wof:placetype":"venue"
},
  "geometry": {"coordinates":[8.1125326157,47.1706581116],"type":"Point"}
}