{
  "type": "Feature",
  "properties": {
    "iso:country":"CH",
    "sg:address":"F\u00e4rbeweg 8",
    "sg:city":"Aarburg",
    "sg:orig_category":"Herstellung von Konstruktionsteilen, Fertigbauteilen U Ausbauelementen aus Holz",
    "sg:phone":"+41 62 752 96 86",
    "sg:postcode":"4663",
    "sg:province":"Aargau",
    "wof:name":"Schreineratelier Bolliger Gmbh",
    "wof:placetype":"venue"
},
  "geometry": {"coordinates":[7.8972902298,47.3184623718],"type":"Point"}
}