{
  "type": "Feature",
  "properties": {
    "iso:country":"CH",
    "sg:address":"Unterdorf 1",
    "sg:city":"Treiten",
    "sg:orig_category":"Detailhandel mit Waren verschiedener Art, Hauptrichtung Nahrungsmittel",
    "sg:phone":"+41 32 313 30 08",
    "sg:postcode":"3226",
    "sg:province":"Bern",
    "wof:name":"Landwirtschaftliche Genossenschaft Treiten",
    "wof:placetype":"venue"
},
  "geometry": {"coordinates":[7.1610250473,47.0088806152],"type":"Point"}
}