{
  "type": "Feature",
  "properties": {
    "iso:country":"CH",
    "sg:address":"Tr\u00e9lex Route De",
    "sg:city":"Gingins",
    "sg:orig_category":"Softwareentwicklung U beratung",
    "sg:phone":"+41 22 369 90 52",
    "sg:postcode":"1276",
    "sg:province":"Vaud",
    "wof:name":"Siliwoud S\u00e0rl",
    "wof:placetype":"venue"
},
  "geometry": {"coordinates":[6.1783900261,46.4088439941],"type":"Point"}
}