{
  "type": "Feature",
  "properties": {
    "iso:country":"CH",
    "sg:address":"Hauptstrasse 23 6280 Hochdorf. Postfach 26",
    "sg:city":"Hochdorf",
    "sg:orig_category":"Detailhandel mit Uhren U Schmuck Herstellung von Schmuck, Gold U Silberschmiedwaren",
    "sg:phone":"+41 81 826 55 63",
    "sg:postcode":"6281",
    "sg:province":"Luzern",
    "wof:name":"Goldschmiede Kuppelwieser",
    "wof:placetype":"venue"
},
  "geometry": {"coordinates":[9.7641716003,46.4287643433],"type":"Point"}
}