{
  "type": "Feature",
  "properties": {
    "iso:country":"CH",
    "sg:address":"Sumpfstrasse 21/23 6312 Steinhausen. Postfach",
    "sg:city":"Steinhausen",
    "sg:orig_category":"Unclassifiable Establishments",
    "sg:phone":"+41 41 748 58 00",
    "sg:postcode":"6312",
    "sg:province":"Zug",
    "wof:name":"Megomat Holding Ag",
    "wof:placetype":"venue"
},
  "geometry": {"coordinates":[8.4875640869,47.1867141724],"type":"Point"}
}