{
  "type": "Feature",
  "properties": {
    "iso:country":"CH",
    "sg:address":"2885",
    "sg:city":"Epauvillers",
    "sg:orig_category":"Detailhandel mit Waren verschiedener Art, Hauptrichtung Nahrungsmittel",
    "sg:phone":"+41 32 461 39 23",
    "sg:postcode":"2885",
    "sg:province":"Jura",
    "wof:name":"Theiller Danielle",
    "wof:placetype":"venue"
},
  "geometry": {"coordinates":[7.1158800125,47.3352966309],"type":"Point"}
}