{
  "type": "Feature",
  "properties": {
    "iso:country":"CH",
    "sg:address":"Via Stazione 5",
    "sg:city":"Caslano",
    "sg:orig_category":"Herstellung von Werkzeugmaschinen Sonstiger spezialisierter Hoch U Tiefbau",
    "sg:phone":"+41 79 337 42 52",
    "sg:postcode":"6987",
    "sg:province":"Ticino",
    "wof:name":"Fresatech Sagl",
    "wof:placetype":"venue"
},
  "geometry": {"coordinates":[8.8821601868,45.9716415405],"type":"Point"}
}