{
  "type": "Feature",
  "properties": {
    "iso:country":"CH",
    "sg:address":"Borgo Via 30 Piazza Ambrosol",
    "sg:city":"Ascona",
    "sg:orig_category":"Detailhandel mit Bekleidung",
    "sg:phone":"+41 91 791 39 75",
    "sg:postcode":"6612",
    "sg:province":"Ticino",
    "wof:name":"Mad House Du Ferraro Leone E Theme Ferraro Katharina",
    "wof:placetype":"venue"
},
  "geometry": {"coordinates":[8.769861,46.156437],"type":"Point"}
}