{
  "type": "Feature",
  "properties": {
    "iso:country":"CH",
    "sg:address":"Le Pralet",
    "sg:city":"Essertes",
    "sg:orig_category":"Informatikdienste",
    "sg:postcode":"1078",
    "sg:province":"Vaud",
    "wof:name":"Patrick Leemann Conseils En Informatique",
    "wof:placetype":"venue"
},
  "geometry": {"coordinates":[6.7812299728,46.5599746704],"type":"Point"}
}