{
  "type": "Feature",
  "properties": {
    "iso:country":"CH",
    "sg:address":"Kreuzackerstrasse 24",
    "sg:city":"Sch\u00f6nenwerd",
    "sg:orig_category":"Alters U Pflegeheime Institutionen f\u00fcr Behinderte",
    "sg:phone":"+41 62 858 43 00",
    "sg:postcode":"5012",
    "sg:province":"Solothurn",
    "wof:name":"Alters-& Pflegeheim Der Region Sch\u00f6nenwerd",
    "wof:placetype":"venue"
},
  "geometry": {"coordinates":[8.000506,47.366505],"type":"Point"}
}