{
  "type": "Feature",
  "properties": {
    "iso:country":"CH",
    "sg:address":"2912",
    "sg:city":"Roche-d'or",
    "sg:orig_category":"Gemeindeverwaltungen",
    "sg:phone":"+41 32 476 65 39",
    "sg:postcode":"2912",
    "sg:province":"Jura",
    "wof:name":"Administration Communale De Roche-d'or",
    "wof:placetype":"venue"
},
  "geometry": {"coordinates":[149.1374053955,-35.1838493347],"type":"Point"}
}