{
  "type": "Feature",
  "properties": {
    "iso:country":"CH",
    "sg:address":"Cerisiers Chemin Des 1789 Lugnorre. Postfach",
    "sg:city":"Lugnorre",
    "sg:orig_category":"Schaustellergewerbe U Vergn\u00fcgungsparks",
    "sg:postcode":"1789",
    "sg:province":"Fribourg",
    "wof:name":"Midnight Production, Pantillon Production Et Management Artistique",
    "wof:placetype":"venue"
},
  "geometry": {"coordinates":[7.0823712349,46.947933197],"type":"Point"}
}