{
  "type": "Feature",
  "properties": {
    "addr:full":"Dr. Martin Erb Strasse 5 Zurzach Aargau 5330",
    "addr:housenumber":"5",
    "addr:postcode":"5330",
    "addr:street":"Erb Strasse",
    "iso:country":"CH",
    "sg:address":"Dr. Martin Erb Strasse 5",
    "sg:city":"Zurzach",
    "sg:classifiers":[
        {
            "category":"Travel",
            "subcategory":"Hotels & Motels",
            "type":"Entertainment"
        }
    ],
    "sg:phone":"+41 56 269 77 77",
    "sg:postcode":"5330",
    "sg:province":"Aargau",
    "sg:tags":[
        "oder",
        "bar",
        "restaurant"
    ],
    "wof:name":"Hotel Zurzacherhof",
    "wof:placetype":"venue"
},
  "geometry": {"coordinates":[8.28903,47.58807],"type":"Point"}
}