{
  "type": "Feature",
  "properties": {
    "iso:country":"CH",
    "sg:address":"Haselstrasse 8",
    "sg:city":"Oberehrendingen",
    "sg:orig_category":"Non-Classified Establishments",
    "sg:postcode":"5422",
    "wof:name":"Georg Frei Bauleistungs Gmbh",
    "wof:placetype":"venue"
},
  "geometry": {"coordinates":[8.3376989365,47.4913482666],"type":"Point"}
}