{
  "type": "Feature",
  "properties": {
    "iso:country":"CH",
    "sg:address":"Lausanne Rue De 22 1950 Sion. Postfach",
    "sg:city":"Sion",
    "sg:orig_category":"Interessenvertretungen",
    "sg:postcode":"1950",
    "sg:province":"Valais",
    "wof:name":"Fondation Villa Reale Marlia Prot\u00e9ger, Entretenir, Am\u00e9liorer Le Bien Immobilier Etc",
    "wof:placetype":"venue"
},
  "geometry": {"coordinates":[7.3568668365,46.2320404053],"type":"Point"}
}