{
  "type": "Feature",
  "properties": {
    "iso:country":"CH",
    "sg:address":"Bahnhofstr. 1",
    "sg:city":"Thun",
    "sg:classifiers":[
        {
            "category":"Banks & Credit Unions",
            "subcategory":"Bank",
            "type":"Services"
        }
    ],
    "sg:phone":"+41 33 227 11 11",
    "sg:postcode":"3600",
    "sg:province":"Bern",
    "wof:name":"Berner Kantonalbank",
    "wof:placetype":"venue"
},
  "geometry": {"coordinates":[7.629834,46.756248],"type":"Point"}
}