{
  "type": "Feature",
  "properties": {
    "iso:country":"CH",
    "sg:address":"Grindelstrasse 19",
    "sg:city":"Volketswil",
    "sg:orig_category":"Datenverarbeitungsdienste Wirtschaftspr\u00fcfung, Steuerberatung U Treuhand",
    "sg:phone":"+41 19456549",
    "sg:postcode":"8604",
    "sg:province":"Z\u00fcrich",
    "wof:name":"Tpk Treuhand Peter Kunz",
    "wof:placetype":"venue"
},
  "geometry": {"coordinates":[8.665534,47.386528],"type":"Point"}
}