{
  "type": "Feature",
  "properties": {
    "iso:country":"CH",
    "sg:address":"Rue Emile-yung 4",
    "sg:city":"Gen\u00e8ve",
    "sg:orig_category":"Arztpraxen",
    "sg:phone":"+41 32 866 12 57",
    "sg:postcode":"1205",
    "sg:province":"Gen\u00e8ve",
    "wof:name":"Dr M\u00e9d. Jean-marc Rothen M\u00e9decin G\u00e9n\u00e9raliste",
    "wof:placetype":"venue"
},
  "geometry": {"coordinates":[6.492405,46.906525],"type":"Point"}
}