{
  "type": "Feature",
  "properties": {
    "iso:country":"CH",
    "sg:address":"B\u00fchlstrasse 19",
    "sg:city":"Egerkingen",
    "sg:classifiers":[
        {
            "category":"Building & Trades",
            "subcategory":"Pest Control",
            "type":"Services"
        }
    ],
    "sg:phone":"+41 62 398 21 66",
    "sg:postcode":"4622",
    "sg:province":"Solothurn",
    "wof:name":"Oltex Ag",
    "wof:placetype":"venue"
},
  "geometry": {"coordinates":[7.7973599434,47.3231391907],"type":"Point"}
}