{
  "type": "Feature",
  "properties": {
    "iso:country":"CH",
    "sg:address":"Pommiers Chemin Des 26 1860 Aigle. Postfach",
    "sg:city":"Aigle",
    "sg:orig_category":"Architektur U Ingenieurb\u00fcros",
    "sg:postcode":"1860",
    "sg:province":"Vaud",
    "wof:name":"Schweizer Et Cie Travaux De Construction, D'entretien, De R\u00e9novation De B\u00e2timents Etc",
    "wof:placetype":"venue"
},
  "geometry": {"coordinates":[6.9701099396,46.3175544739],"type":"Point"}
}