{
  "type": "Feature",
  "properties": {
    "iso:country":"CH",
    "sg:address":"G\u00fcmligentalstrasse 83 B 3072 Ostermundigen. Postfach",
    "sg:city":"Ostermundigen",
    "sg:orig_category":"M\u00f6belschreinereien",
    "sg:postcode":"3072",
    "sg:province":"Bern",
    "wof:name":"Ballif Philippe, Menuiserie",
    "wof:placetype":"venue"
},
  "geometry": {"coordinates":[6.8668699265,46.7416305542],"type":"Point"}
}