{
  "type": "Feature",
  "properties": {
    "iso:country":"CH",
    "sg:address":"Tschumi Rue Adolphe- 3 1201 Gen\u00e8ve. Postfach",
    "sg:city":"Gen\u00e8ve",
    "sg:orig_category":"Gesundheitswesen",
    "sg:postcode":"1201",
    "sg:province":"Gen\u00e8ve",
    "wof:name":"Salon Patchouly S\u00e0rl",
    "wof:placetype":"venue"
},
  "geometry": {"coordinates":[6.1369171143,46.2099189758],"type":"Point"}
}