{
  "type": "Feature",
  "properties": {
    "iso:country":"CH",
    "sg:address":"Hegibergstrasse 9 Areal Aeschbach Ag",
    "sg:city":"Winterthur",
    "sg:orig_category":"Instandhaltung U Reparatur von Automobilen",
    "sg:phone":"+41 52 233 14 40",
    "sg:postcode":"8409",
    "sg:province":"Z\u00fcrich",
    "wof:name":"Br\u00fcniger Automobile Winterthur",
    "wof:placetype":"venue"
},
  "geometry": {"coordinates":[8.7716197968,47.5080108643],"type":"Point"}
}