{
  "type": "Feature",
  "properties": {
    "iso:country":"CH",
    "sg:address":"Ch\u00e2telard Chemin Du 33",
    "sg:city":"Aigle",
    "sg:orig_category":"Grosshandel mit Milch, Milcherzeugnissen, Eiern, Speise\u00f6len U Nahrungsfetten",
    "sg:phone":"+41 24 466 38 01",
    "sg:postcode":"1860",
    "sg:province":"Vaud",
    "wof:name":"Afepo Sa",
    "wof:placetype":"venue"
},
  "geometry": {"coordinates":[6.9562511444,46.3119697571],"type":"Point"}
}