{
  "type": "Feature",
  "properties": {
    "iso:country":"CH",
    "sg:address":"Rathausstrasse 40",
    "sg:city":"Liestal",
    "sg:orig_category":"Detailhandel mit Damenbekleidung",
    "sg:phone":"+41 61 922 15 15",
    "sg:postcode":"4410",
    "sg:province":"Basel-Landschaft",
    "wof:name":"Kleidi Damenmode I.niederberger",
    "wof:placetype":"venue"
},
  "geometry": {"coordinates":[7.734846,47.4841],"type":"Point"}
}