{
  "type": "Feature",
  "properties": {
    "iso:country":"CH",
    "sg:address":"Schulhausstrasse 13",
    "sg:city":"Wimmis",
    "sg:orig_category":"Bezirks, Sekundar, Realschulen, Oberstufe der Primarschulen Primarschulen",
    "sg:phone":"+41 79 297 86 31",
    "sg:postcode":"3752",
    "sg:province":"Bern",
    "wof:name":"Primar-& Oberstufenschule Schulhaus Chr\u00fcmig",
    "wof:placetype":"venue"
},
  "geometry": {"coordinates":[7.641832,46.679581],"type":"Point"}
}