{
  "type": "Feature",
  "properties": {
    "iso:country":"CH",
    "sg:address":"Chemin De La Rami\u00e8re 17",
    "sg:city":"Pr\u00e9verenges",
    "sg:orig_category":"Unternehmensberatung",
    "sg:phone":"+41 21 801 04 69",
    "sg:postcode":"1028",
    "sg:province":"Vaud",
    "wof:name":"Hacom Consulting, Halter Peter O.",
    "wof:placetype":"venue"
},
  "geometry": {"coordinates":[6.5337052345,46.5141563416],"type":"Point"}
}