{
  "type": "Feature",
  "properties": {
    "iso:country":"CH",
    "sg:address":"Bahnhofstrasse 7",
    "sg:city":"Belp",
    "sg:orig_category":"Zahnarztpraxen",
    "sg:phone":"+41 61 401 42 52",
    "sg:postcode":"3123",
    "sg:province":"Bern",
    "wof:name":"Dr.med.dent.sebnem Lopez-asal Zahn\u00e4rztin",
    "wof:placetype":"venue"
},
  "geometry": {"coordinates":[7.5610308647,47.516456604],"type":"Point"}
}