{
  "type": "Feature",
  "properties": {
    "iso:country":"CH",
    "sg:address":"2812",
    "sg:city":"Movelier",
    "sg:orig_category":"Verwertung von Milch",
    "sg:postcode":"2812",
    "sg:province":"Jura",
    "wof:name":"Soci\u00e9t\u00e9 De Laiterie De Movelier",
    "wof:placetype":"venue"
},
  "geometry": {"coordinates":[7.3171548843,47.4090995789],"type":"Point"}
}