{
  "type": "Feature",
  "properties": {
    "iso:country":"CH",
    "sg:address":"Hauptstrasse 14",
    "sg:city":"Wohlen",
    "sg:classifiers":[
        {
            "category":"Banks & Credit Unions",
            "subcategory":"Bank",
            "type":"Services"
        }
    ],
    "sg:phone":"+41 31 829 33 11",
    "sg:postcode":"3033",
    "sg:province":"Bern",
    "wof:name":"Gewerbebank In Bern",
    "wof:placetype":"venue"
},
  "geometry": {"coordinates":[7.354747,46.971153],"type":"Point"}
}