{
  "type": "Feature",
  "properties": {
    "iso:country":"CH",
    "sg:address":"Rotfluhstrasse 58 8702 Zollikon. Postfach",
    "sg:city":"Zollikon",
    "sg:orig_category":"Detailhandel mit Brennstoffen U Heizmaterial Grosshandel mit festen Brennstoffen U Mineral\u00f6lerzeugni",
    "sg:phone":"+41 13918410",
    "sg:postcode":"8702",
    "sg:province":"Z\u00fcrich",
    "wof:name":"Baumann E. & Co Ag",
    "wof:placetype":"venue"
},
  "geometry": {"coordinates":[8.576869,47.342648],"type":"Point"}
}