{
  "type": "Feature",
  "properties": {
    "iso:country":"CH",
    "sg:address":"Loretostrasse 61",
    "sg:city":"Lichtensteig",
    "sg:orig_category":"Interessenvertretungen",
    "sg:postcode":"9620",
    "sg:province":"St. Gallen",
    "wof:name":"Gebr\u00fcder K\u00e4gi Stiftung",
    "wof:placetype":"venue"
},
  "geometry": {"coordinates":[9.08497715,47.3268089294],"type":"Point"}
}