{
  "type": "Feature",
  "properties": {
    "iso:country":"CH",
    "sg:address":"Z\u00fcrcherstrasse 94",
    "sg:city":"Altendorf",
    "sg:orig_category":"Herstellung von Metallerzeugnissen ohne Maschinenbau Maschinenbau",
    "sg:phone":"+41 32 358 02 00",
    "sg:postcode":"8852",
    "sg:province":"Schwyz",
    "wof:name":"Lns Sa",
    "wof:placetype":"venue"
},
  "geometry": {"coordinates":[7.2196149826,47.1617965698],"type":"Point"}
}