{
  "type": "Feature",
  "properties": {
    "iso:country":"CH",
    "sg:address":"Weinreben 1",
    "sg:city":"Zug",
    "sg:orig_category":"Vermietung von Gebrauchsg\u00fctern",
    "sg:postcode":"6300",
    "sg:province":"Zug",
    "wof:name":"Miza Unternehmung Zanetti M.",
    "wof:placetype":"venue"
},
  "geometry": {"coordinates":[8.5258398056,47.1711273193],"type":"Point"}
}