{
  "type": "Feature",
  "properties": {
    "iso:country":"CH",
    "sg:address":"Spelterinistrasse 6",
    "sg:city":"Bern",
    "sg:orig_category":"Detailhandel mit B\u00fcromaschinen U einrichtungen",
    "sg:phone":"+41 31 931 15 91",
    "sg:postcode":"3006",
    "sg:province":"Bern",
    "wof:name":"Erwin Zeller B\u00fcroeinrichtungen",
    "wof:placetype":"venue"
},
  "geometry": {"coordinates":[7.4773,46.957325],"type":"Point"}
}