{
  "type": "Feature",
  "properties": {
    "iso:country":"CH",
    "sg:address":"Lettenweg 118",
    "sg:city":"Allschwil",
    "sg:orig_category":"Sonstige mit der Informatik verbundene T\u00e4tigkeiten",
    "sg:postcode":"4123",
    "sg:province":"Basel-Landschaft",
    "wof:name":"Mai Net Independent Solution Center",
    "wof:placetype":"venue"
},
  "geometry": {"coordinates":[9.0591077805,47.4686508179],"type":"Point"}
}