{
  "type": "Feature",
  "properties": {
    "iso:country":"CH",
    "sg:address":"Hauptstrasse 333",
    "sg:city":"Uerkheim",
    "sg:orig_category":"Nationale Postdienste",
    "sg:phone":"+41 62 721 13 04",
    "sg:postcode":"4813",
    "sg:province":"Aargau",
    "wof:name":"Die Schweizerische Post",
    "wof:placetype":"venue"
},
  "geometry": {"coordinates":[8.0228538513,47.3032073975],"type":"Point"}
}