{
  "type": "Feature",
  "properties": {
    "iso:country":"CH",
    "sg:address":"Pestalozzi Place 8",
    "sg:city":"Yverdon-les-bains",
    "sg:orig_category":"Pensionskassen",
    "sg:postcode":"1400",
    "sg:province":"Vaud",
    "wof:name":"Fonds De Pr\u00e9voyance En Faveur Du Personnel De Multi Media Masters And Machinery Sa Et Des Soci\u00e9t\u00e9s Connexes",
    "wof:placetype":"venue"
},
  "geometry": {"coordinates":[6.6411190033,46.7785606384],"type":"Point"}
}