{
  "type": "Feature",
  "properties": {
    "addr:full":"Schulstrasse 7 Arch Bern 3296",
    "addr:housenumber":"7",
    "addr:postcode":"3296",
    "addr:street":"Schulstrasse",
    "iso:country":"CH",
    "sg:address":"Schulstrasse 7",
    "sg:city":"Arch",
    "sg:orig_category":"Bezirks, Sekundar, Realschulen, Oberstufe der Primarschulen",
    "sg:phone":"+41 32 679 36 76",
    "sg:postcode":"3296",
    "sg:province":"Bern",
    "wof:name":"Sekundarschule",
    "wof:placetype":"venue"
},
  "geometry": {"coordinates":[7.427157,47.164974],"type":"Point"}
}