{
  "type": "Feature",
  "properties": {
    "iso:country":"CH",
    "sg:address":"Seggen",
    "sg:city":"Linthal",
    "sg:orig_category":"Arztpraxen",
    "sg:phone":"+41 55 643 15 13",
    "sg:postcode":"8783",
    "sg:province":"Glarus",
    "wof:name":"Dr.med.ernst Fasol Arzt F.allgemeine Medizin Fmh",
    "wof:placetype":"venue"
},
  "geometry": {"coordinates":[9.00178,46.925476],"type":"Point"}
}