{
  "type": "Feature",
  "properties": {
    "iso:country":"CH",
    "sg:address":"Via Cantonale",
    "sg:city":"Pambio-noranco",
    "sg:orig_category":"Fachdetailhandel in Verkaufsr\u00e4umen",
    "sg:phone":"+41 91 994 74 52",
    "sg:postcode":"6915",
    "sg:province":"Ticino",
    "wof:name":"Serra Fiorita Sa",
    "wof:placetype":"venue"
},
  "geometry": {"coordinates":[8.9336853027,45.9883117676],"type":"Point"}
}