{
  "type": "Feature",
  "properties": {
    "iso:country":"CH",
    "sg:address":"Solothurnerstrasse 259 Postfach",
    "sg:city":"Olten",
    "sg:classifiers":[
        {
            "category":"Health Services",
            "subcategory":"Podiatrist",
            "type":"Services"
        }
    ],
    "sg:phone":"+41 62 205 99 66",
    "sg:postcode":"4603",
    "sg:province":"Solothurn",
    "sg:tags":[
        "instrument",
        "measurement",
        "-",
        "precision",
        "equipment"
    ],
    "wof:name":"Dionex Switzerland Ag",
    "wof:placetype":"venue"
},
  "geometry": {"coordinates":[-101.235496521,25.7841300964],"type":"Point"}
}