{
  "type": "Feature",
  "properties": {
    "iso:country":"CH",
    "sg:address":"Freihofweg 11 5000 Aarau. Postfach",
    "sg:city":"Aarau",
    "sg:orig_category":"Interessenvertretungen",
    "sg:phone":"+41 62 824 58 57",
    "sg:postcode":"5000",
    "sg:province":"Aargau",
    "wof:name":"Anl Ag Natur & Landschaft",
    "wof:placetype":"venue"
},
  "geometry": {"coordinates":[8.0500707626,47.3948020935],"type":"Point"}
}