{
  "type": "Feature",
  "properties": {
    "iso:country":"CH",
    "sg:address":"2613",
    "sg:city":"Villeret",
    "sg:orig_category":"Herstellung von sonstigen landwirtschaftlichen Maschinen",
    "sg:postcode":"2613",
    "sg:province":"Bern",
    "wof:name":"Agro-pi\u00e8ces S\u00e0rl",
    "wof:placetype":"venue"
},
  "geometry": {"coordinates":[7.0182671547,47.1577110291],"type":"Point"}
}