{
  "type": "Feature",
  "properties": {
    "iso:country":"CH",
    "sg:address":"Zentralstrasse 95 5430 Wettingen. Postfach",
    "sg:city":"Wettingen",
    "sg:orig_category":"Tankstellen",
    "sg:postcode":"5430",
    "sg:province":"Aargau",
    "wof:name":"Elf Service-center Morell A. & Walser M. Tankstelle Mit Waschanlage Usw",
    "wof:placetype":"venue"
},
  "geometry": {"coordinates":[8.3225250244,47.4651489258],"type":"Point"}
}