{
  "type": "Feature",
  "properties": {
    "addr:full":"Goldermattenstrasse 39 Steinhausen Zug 6312",
    "addr:housenumber":"39",
    "addr:postcode":"6312",
    "addr:street":"Goldermattenstrasse;Zug",
    "iso:country":"CH",
    "sg:address":"Goldermattenstrasse 39",
    "sg:city":"Steinhausen",
    "sg:orig_category":"Architektur U Ingenieurb\u00fcros",
    "sg:phone":"+41 41 741 56 70",
    "sg:postcode":"6312",
    "sg:province":"Zug",
    "wof:name":"Joachim Pauli Ingenieurb\u00fcro",
    "wof:placetype":"venue"
},
  "geometry": {"coordinates":[8.486004,47.192772],"type":"Point"}
}