{
  "type": "Feature",
  "properties": {
    "iso:country":"CH",
    "sg:address":"Bahnhofstrasse 1 3315 B\u00e4tterkinden. Postfach",
    "sg:city":"B\u00e4tterkinden",
    "sg:orig_category":"Betrieb U technische Hilfsdienste des Kultur U Unterhaltungswesens",
    "sg:phone":"+41 32 665 34 34",
    "sg:postcode":"3315",
    "sg:province":"Bern",
    "wof:name":"Krone Kultur- & Kulinarik-ag",
    "wof:placetype":"venue"
},
  "geometry": {"coordinates":[7.539204,47.130535],"type":"Point"}
}