{
  "type": "Feature",
  "properties": {
    "iso:country":"CH",
    "sg:address":"Marktgasse 26 4900 Langenthal. Postfach 540",
    "sg:city":"Langenthal",
    "sg:orig_category":"Fachdetailhandel mit pharmazeutischen Produkten",
    "sg:phone":"+41 62 922 01 22",
    "sg:postcode":"4902",
    "sg:province":"Bern",
    "wof:name":"Dr.walter Jetzer Apotheke",
    "wof:placetype":"venue"
},
  "geometry": {"coordinates":[7.7885627747,47.2117118835],"type":"Point"}
}