{
  "type": "Feature",
  "properties": {
    "iso:country":"CH",
    "sg:address":"1978 Lens. Postfach",
    "sg:city":"Lens",
    "sg:orig_category":"Detailhandel mit Waren verschiedener Art, Hauptrichtung Nahrungsmittel",
    "sg:postcode":"1978",
    "sg:province":"Valais",
    "wof:name":"Soci\u00e9t\u00e9 Coop\u00e9rative De Consommation De Lens",
    "wof:placetype":"venue"
},
  "geometry": {"coordinates":[7.4485402107,46.2786102295],"type":"Point"}
}