{
  "type": "Feature",
  "properties": {
    "iso:country":"CH",
    "sg:address":"Bellefontaine Rue 8",
    "sg:city":"Lausanne",
    "sg:orig_category":"Unclassifiable Establishments",
    "sg:postcode":"1003",
    "sg:province":"Vaud",
    "wof:name":"Tmc Consulting, Antonio Mirante",
    "wof:placetype":"venue"
},
  "geometry": {"coordinates":[6.6390910149,46.5165519714],"type":"Point"}
}