{
  "type": "Feature",
  "properties": {
    "iso:country":"CH",
    "sg:address":"L\u00e4gernstrasse 25",
    "sg:city":"D\u00fcbendorf",
    "sg:orig_category":"Werbung",
    "sg:postcode":"8600",
    "sg:province":"Z\u00fcrich",
    "wof:name":"Wtw Tele Werbe Ag",
    "wof:placetype":"venue"
},
  "geometry": {"coordinates":[8.620672226,47.403553009],"type":"Point"}
}