{
  "type": "Feature",
  "properties": {
    "iso:country":"CH",
    "sg:address":"Calprino Via 12 6900 Paradiso. Postfach",
    "sg:city":"Paradiso",
    "sg:orig_category":"Bestattungswesen",
    "sg:postcode":"6900",
    "sg:province":"Ticino",
    "wof:name":"Minoretti Sa",
    "wof:placetype":"venue"
},
  "geometry": {"coordinates":[8.94048,45.988625],"type":"Point"}
}