{
  "type": "Feature",
  "properties": {
    "iso:country":"CH",
    "sg:address":"Route Du Village 10 1807 Blonay Case Postale 176",
    "sg:city":"Blonay",
    "sg:orig_category":"Reiseb\u00fcros U Reiseveranstalter",
    "sg:phone":"+41 21 943 03 00",
    "sg:postcode":"1807",
    "sg:province":"Vaud",
    "wof:name":"Cap Sud Voyages Sa",
    "wof:placetype":"venue"
},
  "geometry": {"coordinates":[6.8939881325,46.4675331116],"type":"Point"}
}