{
  "type": "Feature",
  "properties": {
    "iso:country":"CH",
    "sg:address":"Lenkstrasse 36",
    "sg:city":"Zweisimmen",
    "sg:orig_category":"Detailhandel mit Fahrr\u00e4dern Handel mit Motorr\u00e4dern, Teilen U Zubeh\u00f6r Instandhaltung U Reparatur von ",
    "sg:phone":"+41 41 670 12 66",
    "sg:postcode":"3770",
    "sg:province":"Bern",
    "wof:name":"Josef Durrer Velos-motos",
    "wof:placetype":"venue"
},
  "geometry": {"coordinates":[8.2690048218,46.9398612976],"type":"Point"}
}