{
  "type": "Feature",
  "properties": {
    "iso:country":"CH",
    "sg:address":"Eselweidweg 5 8833 Samstagern. Postfach",
    "sg:city":"Samstagern",
    "sg:orig_category":"Maschinen-Fabrikation",
    "sg:phone":"+41 33 335 18 18",
    "sg:postcode":"8833",
    "sg:province":"Z\u00fcrich",
    "wof:name":"Nobag, Nobs Engineering Ag",
    "wof:placetype":"venue"
},
  "geometry": {"coordinates":[7.6206221581,46.7238922119],"type":"Point"}
}