{
  "type": "Feature",
  "properties": {
    "iso:country":"CH",
    "sg:address":"Rheinquai 12",
    "sg:city":"Schaffhausen",
    "sg:orig_category":"Aktivit\u00e4ten der Generalunternehmen im Baugewerbe Architektur U Ingenieurb\u00fcros",
    "sg:phone":"+41 52 624 38 31",
    "sg:postcode":"8200",
    "sg:province":"Schaffhausen",
    "wof:name":"Immowert H\u00e4berli Beat",
    "wof:placetype":"venue"
},
  "geometry": {"coordinates":[8.643022,47.695396],"type":"Point"}
}