{
  "type": "Feature",
  "properties": {
    "iso:country":"CH",
    "sg:address":"Burstera",
    "sg:city":"Schwarzsee",
    "sg:orig_category":"Interessenvertretungen",
    "sg:postcode":"1711",
    "wof:name":"Interessengenossenschaft Burstera-schwarzsee",
    "wof:placetype":"venue"
},
  "geometry": {"coordinates":[7.2838859558,46.6706886292],"type":"Point"}
}