{
  "type": "Feature",
  "properties": {
    "iso:country":"CH",
    "sg:address":"Hofackerstrasse 33 8032 Z\u00fcrich 32 Zust. Postfach 8032 Z\u00fcrich",
    "sg:city":"Zust",
    "sg:orig_category":"Unclassifiable Establishments",
    "sg:postcode":"32",
    "wof:name":"Schaub Roland",
    "wof:placetype":"venue"
},
  "geometry": {"coordinates":[6.8216757774,47.1017990112],"type":"Point"}
}