{
  "type": "Feature",
  "properties": {
    "iso:country":"CH",
    "sg:address":"Austrasse 2",
    "sg:city":"Klingnau",
    "sg:orig_category":"Fischzucht, Teichwirtschaft",
    "sg:phone":"+41 56 268 60 00",
    "sg:postcode":"5313",
    "sg:province":"Aargau",
    "wof:name":"Koi-farm Gmbh Fischzucht",
    "wof:placetype":"venue"
},
  "geometry": {"coordinates":[8.2394638062,47.5916976929],"type":"Point"}
}