{
  "type": "Feature",
  "properties": {
    "addr:full":"Birkenstrasse 78 Engelberg Obwalden 6390",
    "addr:housenumber":"78",
    "addr:postcode":"6390",
    "addr:street":"Birkenstrasse",
    "iso:country":"CH",
    "sg:address":"Birkenstrasse 78",
    "sg:city":"Engelberg",
    "sg:orig_category":"Bau von Strassen, Sportanlagen U Bahnverkehrsstrecken",
    "sg:phone":"+41 19372624",
    "sg:postcode":"6390",
    "sg:province":"Obwalden",
    "wof:name":"Strazo Ag, Strassenbau",
    "wof:placetype":"venue"
},
  "geometry": {"coordinates":[8.84353,47.30233],"type":"Point"}
}