{
  "type": "Feature",
  "properties": {
    "iso:country":"CH",
    "sg:address":"Bundesplatz 14 6003 Luzern. Postfach",
    "sg:city":"Luzern",
    "sg:orig_category":"Interessenvertretungen Organisationen des Gesundheitswesen",
    "sg:phone":"+41 41 226 11 88",
    "sg:postcode":"6002",
    "sg:province":"Luzern",
    "wof:name":"Pro Senectute Kanton Luzern - F\u00fcr Das Alter",
    "wof:placetype":"venue"
},
  "geometry": {"coordinates":[8.3085269928,47.0458145142],"type":"Point"}
}