{
  "type": "Feature",
  "properties": {
    "iso:country":"CH",
    "sg:address":"Bahnhofstrasse 45 8001 Z\u00fcrich. Postfach",
    "sg:city":"Z\u00fcrich",
    "sg:orig_category":"Personenbef\u00f6rderung im Linienverkehr zu Land",
    "sg:postcode":"8001",
    "sg:province":"Z\u00fcrich",
    "wof:name":"Ubs-polybahn Ag",
    "wof:placetype":"venue"
},
  "geometry": {"coordinates":[8.5382375717,47.3720016479],"type":"Point"}
}