{
  "type": "Feature",
  "properties": {
    "iso:country":"CH",
    "sg:address":"Feldbergstrasse 1 4057 Basel. Postfach",
    "sg:city":"Basel",
    "sg:orig_category":"Grosshandel mit Getr\u00e4nken",
    "sg:phone":"+41 61 692 33 46",
    "sg:postcode":"4057",
    "sg:province":"Basel-Stadt",
    "wof:name":"Frau V. Donati",
    "wof:placetype":"venue"
},
  "geometry": {"coordinates":[7.5875492096,47.5655632019],"type":"Point"}
}