{
  "type": "Feature",
  "properties": {
    "iso:country":"CH",
    "sg:address":"Rue Haute 10",
    "sg:city":"Grandson",
    "sg:orig_category":"Verwaltung von Immobilien",
    "sg:phone":"+41 24 445 12 23",
    "sg:postcode":"1422",
    "sg:province":"Vaud",
    "wof:name":"Jaton Alfred",
    "wof:placetype":"venue"
},
  "geometry": {"coordinates":[6.6446580887,46.8089790344],"type":"Point"}
}