{
  "type": "Feature",
  "properties": {
    "iso:country":"CH",
    "sg:address":"Trockenriedstrasse 22",
    "sg:city":"Niederhasli",
    "sg:orig_category":"Grosshandel mit Datenverarbeitungsger\u00e4ten Softwareentwicklung U beratung",
    "sg:phone":"+41 61 813 15 05",
    "sg:postcode":"8155",
    "sg:province":"Z\u00fcrich",
    "wof:name":"Micom System, Sogor Michael",
    "wof:placetype":"venue"
},
  "geometry": {"coordinates":[8.4927396774,47.4841766357],"type":"Point"}
}