{
  "type": "Feature",
  "properties": {
    "iso:country":"CH",
    "sg:address":"Rue De La Plaine 43",
    "sg:city":"Yverdon-les-bains",
    "sg:orig_category":"Tanzschulen, Tanzlehrer",
    "sg:phone":"+41 22 791 01 33",
    "sg:postcode":"1400",
    "sg:province":"Vaud",
    "wof:name":"Bc Swing Ecole De Danse & De Ballet",
    "wof:placetype":"venue"
},
  "geometry": {"coordinates":[6.1161608696,46.2276229858],"type":"Point"}
}