{
  "type": "Feature",
  "properties": {
    "iso:country":"CH",
    "sg:address":"Bahnhofstrasse 22",
    "sg:city":"Ilanz",
    "sg:orig_category":"Detailhandel mit Schuhen",
    "sg:phone":"+41 81 925 11 96",
    "sg:postcode":"7130",
    "sg:province":"Graubunden",
    "wof:name":"Pasito Ag",
    "wof:placetype":"venue"
},
  "geometry": {"coordinates":[9.2067298889,46.7750663757],"type":"Point"}
}