{
  "type": "Feature",
  "properties": {
    "iso:country":"CH",
    "sg:address":"Kleinh\u00fcningerstrasse 177 4057 Basel. Postfach",
    "sg:city":"Basel",
    "sg:orig_category":"Fachdetailhandel in Verkaufsr\u00e4umen",
    "sg:postcode":"4057",
    "sg:province":"Basel-Stadt",
    "wof:name":"Geschenke-direct Gmbh Geschenkartikel; Import, Export",
    "wof:placetype":"venue"
},
  "geometry": {"coordinates":[7.5907330513,47.5798721313],"type":"Point"}
}