{
  "type": "Feature",
  "properties": {
    "iso:country":"CH",
    "sg:address":"Giessenmattstrasse 9",
    "sg:city":"Dallenwil",
    "sg:orig_category":"Grosshandel mit Nahrungsmitteln, Getr\u00e4nken U Tabakwaren ohne ausgepr\u00e4gten Schwerpunkt",
    "sg:postcode":"6383",
    "sg:province":"Nidwalden",
    "wof:name":"Tiefk\u00fchlservice Wyss Robert",
    "wof:placetype":"venue"
},
  "geometry": {"coordinates":[8.3920192719,46.931968689],"type":"Point"}
}