{
  "type": "Feature",
  "properties": {
    "iso:country":"CH",
    "sg:address":"Zofingerstrasse 8",
    "sg:city":"Brittnau",
    "sg:orig_category":"Bauschreinerei Innenausbau",
    "sg:phone":"+41 62 751 91 03",
    "sg:postcode":"4805",
    "sg:province":"Aargau",
    "wof:name":"Kunz Ag",
    "wof:placetype":"venue"
},
  "geometry": {"coordinates":[7.94907,47.272461],"type":"Point"}
}