{
  "type": "Feature",
  "properties": {
    "iso:country":"CH",
    "sg:address":"Altwiesenstrasse 163",
    "sg:city":"Z\u00fcrich",
    "sg:orig_category":"Sonstige Kurierdienste",
    "sg:phone":"+41 13212610",
    "sg:postcode":"8051",
    "sg:province":"Z\u00fcrich",
    "wof:name":"Eslava Nelson Kurierdienste",
    "wof:placetype":"venue"
},
  "geometry": {"coordinates":[8.5843820572,47.4022750854],"type":"Point"}
}