{
  "type": "Feature",
  "properties": {
    "iso:country":"CH",
    "sg:address":"Hauptstrasse 61",
    "sg:city":"Muttenz",
    "sg:orig_category":"Detailhandel mit fotografischen Artikeln Fotografisches Gewerbe U fotografische Laboratorien",
    "sg:phone":"+41 21 921 92 65",
    "sg:postcode":"4132",
    "sg:province":"Basel-Landschaft",
    "wof:name":"Photo Arcades, Jacqueline Kespy",
    "wof:placetype":"venue"
},
  "geometry": {"coordinates":[5.1808700562,45.8973388672],"type":"Point"}
}