{
  "type": "Feature",
  "properties": {
    "iso:country":"CH",
    "sg:address":"Metzgplatz 10",
    "sg:city":"Lenzburg",
    "sg:orig_category":"Unclassifiable Establishments",
    "sg:postcode":"5600",
    "sg:province":"Aargau",
    "wof:name":"Didac Design Kause L.",
    "wof:placetype":"venue"
},
  "geometry": {"coordinates":[8.1811771393,47.3867874146],"type":"Point"}
}