{
  "type": "Feature",
  "properties": {
    "iso:country":"CH",
    "sg:address":"Reckental",
    "sg:city":"Kandergrund",
    "sg:orig_category":"Detailhandel mit Fahrr\u00e4dern Handel mit Motorr\u00e4dern, Teilen U Zubeh\u00f6r Instandhaltung U Reparatur von ",
    "sg:phone":"+41 33 671 26 00",
    "sg:postcode":"3716",
    "sg:province":"Bern",
    "wof:name":"Hansj\u00fcrg Grossen Velos-mofas",
    "wof:placetype":"venue"
},
  "geometry": {"coordinates":[7.6589360237,46.5603675842],"type":"Point"}
}