{
  "type": "Feature",
  "properties": {
    "iso:country":"CH",
    "sg:address":"Waaghausgasse 18",
    "sg:city":"Bern",
    "sg:orig_category":"Non-Classified Establishments",
    "sg:phone":"+41 31 312 01 07",
    "sg:postcode":"3011",
    "sg:province":"Bern",
    "wof:name":"Starbucks Coffee",
    "wof:placetype":"venue"
},
  "geometry": {"coordinates":[7.4441261292,46.948928833],"type":"Point"}
}