{
  "type": "Feature",
  "properties": {
    "iso:country":"CH",
    "sg:address":"G\u00f6ssikon 203",
    "sg:city":"Zumikon",
    "sg:orig_category":"Grosshandel mit Textilien",
    "sg:postcode":"8126",
    "sg:province":"Z\u00fcrich",
    "wof:name":"B & B Konfektion Gmbh",
    "wof:placetype":"venue"
},
  "geometry": {"coordinates":[8.6159200668,47.3316917419],"type":"Point"}
}