{
  "type": "Feature",
  "properties": {
    "iso:country":"CH",
    "sg:address":"St.-johannes-strasse 6",
    "sg:city":"Zug",
    "sg:classifiers":[
        {
            "category":"Professional",
            "subcategory":"Employment Agencies",
            "type":"Services"
        }
    ],
    "sg:phone":"+41 41 741 55 09",
    "sg:postcode":"6300",
    "sg:province":"Zug",
    "sg:tags":[
        "personal",
        "u",
        "stellenvermittlung"
    ],
    "wof:name":"Hauser Heinz",
    "wof:placetype":"venue"
},
  "geometry": {"coordinates":[8.5064287186,47.179523468],"type":"Point"}
}