{
  "type": "Feature",
  "properties": {
    "addr:full":"Rue De Soleure 4 Gen\u00e8ve Gen\u00e8ve 1207",
    "addr:housenumber":"4",
    "addr:postcode":"1207",
    "addr:street":"Rue De Soleure",
    "iso:country":"CH",
    "sg:address":"Rue De Soleure 4",
    "sg:city":"Gen\u00e8ve",
    "sg:orig_category":"Arztpraxen",
    "sg:phone":"+41 22 736 81 90",
    "sg:postcode":"1207",
    "sg:province":"Gen\u00e8ve",
    "wof:name":"Dr M\u00e9d. Christian Berret M\u00e9decin G\u00e9n\u00e9raliste Fmh",
    "wof:placetype":"venue"
},
  "geometry": {"coordinates":[6.16361,46.205761],"type":"Point"}
}