{
  "type": "Feature",
  "properties": {
    "iso:country":"CH",
    "sg:address":"Route Ancien Sierre 9",
    "sg:city":"Sierre",
    "sg:orig_category":"Unternehmensberatung",
    "sg:phone":"+41 27 451 73 00",
    "sg:postcode":"3960",
    "sg:province":"Valais",
    "wof:name":"Alcan Technology & Management Ag",
    "wof:placetype":"venue"
},
  "geometry": {"coordinates":[7.5288891792,46.2853355408],"type":"Point"}
}