{
  "type": "Feature",
  "properties": {
    "iso:country":"CH",
    "sg:address":"Rue Du Clos 12",
    "sg:city":"Gen\u00e8ve",
    "sg:orig_category":"Erbringung von Dienstleistungen f\u00fcr Unternehmen Innendekorationsateliers",
    "sg:phone":"+41 22 700 16 70",
    "sg:postcode":"1207",
    "sg:province":"Gen\u00e8ve",
    "wof:name":"Borella M. Et M.-a., Vogue D\u00e9coration",
    "wof:placetype":"venue"
},
  "geometry": {"coordinates":[6.1620259285,46.2055931091],"type":"Point"}
}