{
  "type": "Feature",
  "properties": {
    "iso:country":"CH",
    "sg:address":"Alpenstrasse 82",
    "sg:city":"Schaffhausen",
    "sg:orig_category":"Wirtschaftspr\u00fcfung, Steuerberatung U Treuhand",
    "sg:phone":"+41 52 624 88 49",
    "sg:postcode":"8200",
    "sg:province":"Schaffhausen",
    "wof:name":"R\u00fceger Treuhand Und Marketing",
    "wof:placetype":"venue"
},
  "geometry": {"coordinates":[8.6499271393,47.6987228394],"type":"Point"}
}