{
  "type": "Feature",
  "properties": {
    "addr:full":"Hechtgasse 10 Wolfhalden Appenzell Ausserrhoden 9427",
    "addr:housenumber":"10",
    "addr:postcode":"9427",
    "addr:street":"Hechtgasse;Ausserrhoden",
    "iso:country":"CH",
    "sg:address":"Hechtgasse 10",
    "sg:city":"Wolfhalden",
    "sg:orig_category":"Betrieb von Taxis",
    "sg:phone":"+41 71 891 55 55",
    "sg:postcode":"9427",
    "sg:province":"Appenzell Ausserrhoden",
    "wof:name":"Anna Eyben Hella Nacht-taxi & Kur-taxi",
    "wof:placetype":"venue"
},
  "geometry": {"coordinates":[9.549919,47.45372],"type":"Point"}
}