{
  "type": "Feature",
  "properties": {
    "iso:country":"CH",
    "sg:address":"Bethlehemstr. 2",
    "sg:city":"Bern",
    "sg:classifiers":[
        {
            "category":"Banks & Credit Unions",
            "subcategory":"Bank",
            "type":"Services"
        }
    ],
    "sg:phone":"+41 31 992 65 65",
    "sg:postcode":"3027",
    "sg:province":"Bern",
    "wof:name":"Spar- U. Leihkasse In Bern",
    "wof:placetype":"venue"
},
  "geometry": {"coordinates":[7.393741,46.948975],"type":"Point"}
}