{
  "type": "Feature",
  "properties": {
    "iso:country":"CH",
    "sg:address":"5016",
    "sg:city":"Obererlinsbach",
    "sg:orig_category":"Wirtschaftsverb\u00e4nde Gewerbeverb\u00e4nde/-vereine",
    "sg:phone":"+41 56 631 75 07",
    "sg:postcode":"5016",
    "wof:name":"Handwerker-& Gewerbeverein Hgv",
    "wof:placetype":"venue"
},
  "geometry": {"coordinates":[8.3199033737,47.3591003418],"type":"Point"}
}