{
  "type": "Feature",
  "properties": {
    "iso:country":"CH",
    "sg:address":"Avenue Du Grammont 1",
    "sg:city":"Lausanne",
    "sg:orig_category":"Fotografische Ateliers",
    "sg:phone":"+41 21 617 72 24",
    "sg:postcode":"1007",
    "sg:province":"Vaud",
    "wof:name":"R.& T. Wicky Sa Atelier De Photographie",
    "wof:placetype":"venue"
},
  "geometry": {"coordinates":[6.6272997856,46.5114517212],"type":"Point"}
}