{
  "type": "Feature",
  "properties": {
    "iso:country":"CH",
    "sg:address":"Lindenb\u00fchl 163",
    "sg:city":"Uebeschi",
    "sg:orig_category":"Technische, physikalische U chemische Untersuchung",
    "sg:phone":"+41 33 345 62 13",
    "sg:postcode":"3635",
    "sg:province":"Bern",
    "wof:name":"Sch\u00fcpbach Environment And Communications",
    "wof:placetype":"venue"
},
  "geometry": {"coordinates":[7.5552830696,46.7397422791],"type":"Point"}
}