{
  "type": "Feature",
  "properties": {
    "iso:country":"CH",
    "sg:address":"Boulevard De P\u00e9rolles 33",
    "sg:city":"Fribourg",
    "sg:classifiers":[
        {
            "category":"Government",
            "subcategory":"Post Office",
            "type":"Public Place"
        }
    ],
    "sg:phone":"+41 26 322 07 97",
    "sg:postcode":"1700",
    "sg:province":"Fribourg",
    "sg:tags":[
        "caf\u00e9s",
        "tea-rooms"
    ],
    "wof:name":"Tea-room Domino",
    "wof:placetype":"venue"
},
  "geometry": {"coordinates":[7.1531500816,46.7981414795],"type":"Point"}
}