{
  "type": "Feature",
  "properties": {
    "addr:full":"M\u00fcnsterberg 2 Basel Basel-Stadt 4051",
    "addr:housenumber":"2",
    "addr:postcode":"4051",
    "addr:street":"Muensterberg",
    "iso:country":"CH",
    "sg:address":"M\u00fcnsterberg 2",
    "sg:city":"Basel",
    "sg:classifiers":[
        {
            "category":"Ferry Terminal",
            "type":"Transportation"
        }
    ],
    "sg:phone":"+41 61 272 53 34",
    "sg:postcode":"4051",
    "sg:province":"Basel-Stadt",
    "sg:tags":[
        "casual",
        "shirt"
    ],
    "wof:name":"Metzger & Lampert Ag",
    "wof:placetype":"venue"
},
  "geometry": {"coordinates":[7.591122,47.555134],"type":"Point"}
}