{
  "type": "Feature",
  "properties": {
    "iso:country":"CH",
    "sg:address":"Haldengasse 198",
    "sg:city":"Eschen",
    "sg:orig_category":"Eisenwaren Detailhandel",
    "sg:phone":"+423 373 63 34",
    "sg:postcode":"9492",
    "wof:name":"Rita Sch\u00e4chle Eisenwaren",
    "wof:placetype":"venue"
},
  "geometry": {"coordinates":[9.5191297531,47.2097892761],"type":"Point"}
}