{
  "type": "Feature",
  "properties": {
    "iso:country":"CH",
    "sg:address":"Casa Margherita",
    "sg:city":"Weggis",
    "sg:orig_category":"Reiseb\u00fcros U Reiseveranstalter",
    "sg:phone":"+41 61 712 04 02",
    "sg:postcode":"6353",
    "sg:province":"Luzern",
    "wof:name":"Rina Reisen Ag",
    "wof:placetype":"venue"
},
  "geometry": {"coordinates":[7.5894851685,47.4911994934],"type":"Point"}
}