{
  "type": "Feature",
  "properties": {
    "iso:country":"CH",
    "sg:address":"Etzelstrasse 4",
    "sg:city":"Hombrechtikon",
    "sg:classifiers":[
        {
            "category":"Restaurant",
            "type":"Food & Drink"
        }
    ],
    "sg:phone":"+41 55 244 10 55",
    "sg:postcode":"8634",
    "sg:province":"Z\u00fcrich",
    "wof:name":"Pizzeria Baumgarten",
    "wof:placetype":"venue"
},
  "geometry": {"coordinates":[8.778752327,47.2528915405],"type":"Point"}
}