{
  "type": "Feature",
  "properties": {
    "iso:country":"CH",
    "sg:address":"Rue Des Alpes 10a",
    "sg:city":"Gland",
    "sg:orig_category":"Detailhandel mit Brot, Back U S\u00fcsswaren",
    "sg:phone":"+41 22 364 64 34",
    "sg:postcode":"1196",
    "sg:province":"Vaud",
    "wof:name":"Marc Lecoultre Boulangerie & P\u00e2tisserie",
    "wof:placetype":"venue"
},
  "geometry": {"coordinates":[6.27603,46.418694],"type":"Point"}
}