{
  "type": "Feature",
  "properties": {
    "iso:country":"CH",
    "sg:address":"Avenue Beauregard 12",
    "sg:city":"Fribourg",
    "sg:orig_category":"Grosshandel mit Datenverarbeitungsger\u00e4ten Grosshandel mit Software",
    "sg:phone":"+41 71 950 01 27",
    "sg:postcode":"1700",
    "sg:province":"Fribourg",
    "wof:name":"Nft New Future Technologies Gmbh",
    "wof:placetype":"venue"
},
  "geometry": {"coordinates":[9.3949289322,47.4374046326],"type":"Point"}
}