{
  "type": "Feature",
  "properties": {
    "iso:country":"CH",
    "sg:address":"Rohrgasse 24",
    "sg:city":"Breitenbach",
    "sg:orig_category":"Werbung",
    "sg:postcode":"4226",
    "sg:province":"Solothurn",
    "wof:name":"H\u00e4ner Marketing",
    "wof:placetype":"venue"
},
  "geometry": {"coordinates":[7.5463438034,47.4107551575],"type":"Point"}
}