{
  "type": "Feature",
  "properties": {
    "iso:country":"CH",
    "sg:address":"Saumackerstrasse 29",
    "sg:city":"Z\u00fcrich",
    "sg:orig_category":"Wirtschaftsverb\u00e4nde Gewerbeverb\u00e4nde/-vereine",
    "sg:phone":"+41 14325511",
    "sg:postcode":"8048",
    "sg:province":"Z\u00fcrich",
    "wof:name":"Gewerbeverein Altstetten/gr\u00fcnau",
    "wof:placetype":"venue"
},
  "geometry": {"coordinates":[8.488825798,47.3879890442],"type":"Point"}
}