{
  "type": "Feature",
  "properties": {
    "iso:country":"CH",
    "sg:address":"Sulzstr. 10-12",
    "sg:city":"Goldach",
    "sg:classifiers":[
        {
            "category":"Communications",
            "subcategory":"Newspaper",
            "type":"Services"
        }
    ],
    "sg:phone":"+41 41 268 68 68",
    "sg:postcode":"9403",
    "sg:province":"St. Gallen",
    "sg:tags":[
        "printing",
        "publishing"
    ],
    "wof:name":"Beag Druck Ag",
    "wof:placetype":"venue"
},
  "geometry": {"coordinates":[8.2736492157,47.0740013123],"type":"Point"}
}