{
  "type": "Feature",
  "properties": {
    "iso:country":"CH",
    "sg:address":"Poststrasse 2",
    "sg:city":"L\u00fctisburg",
    "sg:orig_category":"Organisationen des Gesundheitswesen",
    "sg:phone":"+41 71 931 31 77",
    "sg:postcode":"9604",
    "sg:province":"St. Gallen",
    "wof:name":"Schweizer Kneippverband",
    "wof:placetype":"venue"
},
  "geometry": {"coordinates":[9.0792226791,47.3954429626],"type":"Point"}
}