{
  "type": "Feature",
  "properties": {
    "iso:country":"CH",
    "sg:address":"B\u00e4chelsr\u00fcti 322",
    "sg:city":"Gr\u00fcningen",
    "sg:orig_category":"Grosshandel mit Nahrungsmitteln, Getr\u00e4nken U Tabakwaren ohne ausgepr\u00e4gten Schwerpunkt",
    "sg:postcode":"8627",
    "sg:province":"Z\u00fcrich",
    "wof:name":"M. Mermer Oberdorfladen Gmbh",
    "wof:placetype":"venue"
},
  "geometry": {"coordinates":[8.8566493988,47.2608413696],"type":"Point"}
}