{
  "type": "Feature",
  "properties": {
    "iso:country":"CH",
    "sg:address":"K\u00e4nerkinderstrasse 9",
    "sg:city":"Diegten",
    "sg:orig_category":"Datenverarbeitungsdienste Sonstige pers\u00f6nliche Dienstleistungen",
    "sg:phone":"+41 31 348 13 33",
    "sg:postcode":"4457",
    "sg:province":"Basel-Landschaft",
    "wof:name":"Metropolitan S\u00e0rl Communication. Ev\u00e9nements; Marketing, Organisation Etc",
    "wof:placetype":"venue"
},
  "geometry": {"coordinates":[7.449724,46.952354],"type":"Point"}
}