{
  "type": "Feature",
  "properties": {
    "iso:country":"CH",
    "sg:address":"Erspelstrasse 2",
    "sg:city":"Bubikon",
    "sg:orig_category":"Softwareentwicklung U beratung",
    "sg:postcode":"8608",
    "sg:province":"Z\u00fcrich",
    "wof:name":"Tobbol Gmbh",
    "wof:placetype":"venue"
},
  "geometry": {"coordinates":[8.819940567,47.2702827454],"type":"Point"}
}