{
  "type": "Feature",
  "properties": {
    "addr:full":"Fracht West Z\u00fcrich Z\u00fcrich 8058",
    "addr:postcode":"8058",
    "addr:street":"West",
    "iso:country":"CH",
    "sg:address":"Fracht West",
    "sg:city":"Z\u00fcrich",
    "sg:classifiers":[
        {
            "category":"Airport",
            "type":"Transportation"
        }
    ],
    "sg:phone":"+41 43 816 32 42",
    "sg:postcode":"8058",
    "sg:province":"Z\u00fcrich",
    "sg:tags":[
        "air-freight",
        "forwarders"
    ],
    "wof:name":"Total Freight Management Gmbh",
    "wof:placetype":"venue"
},
  "geometry": {"coordinates":[8.568706,47.452812],"type":"Point"}
}