{
  "type": "Feature",
  "properties": {
    "iso:country":"CH",
    "sg:address":"Vordere Gasse 26",
    "sg:city":"Wenslingen",
    "sg:orig_category":"Malerei-Gipserei Stukkateurgewerbe, Gipserei U Verputzerei",
    "sg:phone":"+41 41 410 32 46",
    "sg:postcode":"4493",
    "sg:province":"Basel-Landschaft",
    "wof:name":"Max Duss Gipsergesch\u00e4ft",
    "wof:placetype":"venue"
},
  "geometry": {"coordinates":[8.3125123978,47.0562400818],"type":"Point"}
}