{
  "type": "Feature",
  "properties": {
    "addr:full":"Arelien Gr\u00fcsch Graubunden 7214",
    "addr:housenumber":"7214",
    "iso:country":"CH",
    "sg:address":"Arelien",
    "sg:city":"Gr\u00fcsch",
    "sg:orig_category":"Architektur U Ingenieurb\u00fcros",
    "sg:phone":"+41 81 325 35 35",
    "sg:postcode":"7214",
    "sg:province":"Graubunden",
    "wof:name":"Z\u00fcst-stock, Hans-luzi",
    "wof:placetype":"venue"
},
  "geometry": {"coordinates":[9.646708,46.980743],"type":"Point"}
}