{
  "type": "Feature",
  "properties": {
    "iso:country":"CH",
    "sg:address":"Obere Zollgasse 29b",
    "sg:city":"Ostermundigen",
    "sg:orig_category":"Dienstleistungen von Beteiligungsgesellschaften Grosshandel mit B\u00fcromaschinen",
    "sg:phone":"+41 17407788",
    "sg:postcode":"3072",
    "sg:province":"Bern",
    "wof:name":"Graphax Ag",
    "wof:placetype":"venue"
},
  "geometry": {"coordinates":[8.3948001862,47.42004776],"type":"Point"}
}