{
  "type": "Feature",
  "properties": {
    "iso:country":"CH",
    "sg:address":"Grossbachstr. 13",
    "sg:city":"Einsiedeln",
    "sg:orig_category":"Non-Classified Establishments",
    "sg:phone":"+41 71 911 53 10",
    "sg:postcode":"8840",
    "sg:province":"Schwyz",
    "wof:name":"Arthur Marty Holding Ag",
    "wof:placetype":"venue"
},
  "geometry": {"coordinates":[9.0612068176,47.4679641724],"type":"Point"}
}