{
  "type": "Feature",
  "properties": {
    "iso:country":"CH",
    "sg:address":"Elisabethenstrasse 41 4051 Basel. Postfach",
    "sg:city":"Basel",
    "sg:orig_category":"RESTAURANTS: TEA-ROOMS",
    "sg:postcode":"4051",
    "sg:province":"Basel-Stadt",
    "wof:name":"Caf\u00e9 G\u00fcrtler",
    "wof:placetype":"venue"
},
  "geometry": {"coordinates":[-94.7642822266,41.4454193115],"type":"Point"}
}