{
  "type": "Feature",
  "properties": {
    "iso:country":"CH",
    "sg:address":"Frickermattenstrasse 7 5222 Umiken. Postfach",
    "sg:city":"Umiken",
    "sg:orig_category":"Gesundheitswesen",
    "sg:postcode":"5222",
    "sg:province":"Aargau",
    "wof:name":"Knoth Stefan",
    "wof:placetype":"venue"
},
  "geometry": {"coordinates":[8.1899499893,47.4808235168],"type":"Point"}
}