{
  "type": "Feature",
  "properties": {
    "iso:country":"CH",
    "sg:address":"S\u00fcdstrasse 1 3110 M\u00fcnsingen. Postfach 1176",
    "sg:city":"M\u00fcnsingen",
    "sg:orig_category":"Geschenk- and Werbeartikel Grosshandel",
    "sg:phone":"+41 31 724 72 72",
    "sg:postcode":"3110",
    "sg:province":"Bern",
    "wof:name":"Promo'plus Ag Werbemittel-agentur",
    "wof:placetype":"venue"
},
  "geometry": {"coordinates":[7.5633740425,46.868724823],"type":"Point"}
}