{
  "type": "Feature",
  "properties": {
    "iso:country":"CH",
    "sg:address":"Loorenstr. 9",
    "sg:city":"Dietlikon",
    "sg:classifiers":[
        {
            "category":"Manufacturing",
            "subcategory":"Rubber & Plastics",
            "type":"Manufacturing & Wholesale Goods"
        }
    ],
    "sg:phone":"+41 4118331050",
    "sg:postcode":"8305",
    "sg:province":"Z\u00fcrich",
    "sg:tags":[
        "machine",
        "engineering",
        "-",
        "mechanical"
    ],
    "wof:name":"Abt Ag",
    "wof:placetype":"venue"
},
  "geometry": {"coordinates":[8.6143302917,47.4256782532],"type":"Point"}
}