{
  "type": "Feature",
  "properties": {
    "iso:country":"CH",
    "sg:address":"1564",
    "sg:city":"Domdidier",
    "sg:orig_category":"Primarschulen",
    "sg:phone":"+41 26 675 40 98",
    "sg:postcode":"1564",
    "sg:province":"Fribourg",
    "wof:name":"Ecole Primaire",
    "wof:placetype":"venue"
},
  "geometry": {"coordinates":[7.0151348114,46.8653068542],"type":"Point"}
}