{
  "type": "Feature",
  "properties": {
    "iso:country":"CH",
    "sg:address":"Seestrasse 457 8038 Z\u00fcrich. Postfach",
    "sg:city":"Z\u00fcrich",
    "sg:orig_category":"Non-Classified Establishments",
    "sg:postcode":"8001",
    "sg:province":"Z\u00fcrich",
    "wof:name":"Anteprima Ag Gastronomiebetrieb, Modegesch\u00e4fte; Einrichtung, F\u00fchrung",
    "wof:placetype":"venue"
},
  "geometry": {"coordinates":[8.5383472443,47.340171814],"type":"Point"}
}