{
  "type": "Feature",
  "properties": {
    "iso:country":"CH",
    "sg:address":"1882",
    "sg:city":"Gryon",
    "sg:orig_category":"Allgemeinbildende weiterf\u00fchrende Schulen",
    "sg:phone":"+41 24 498 12 04",
    "sg:postcode":"1882",
    "sg:province":"Vaud",
    "wof:name":"Roth Bertrand",
    "wof:placetype":"venue"
},
  "geometry": {"coordinates":[7.06179,46.273869],"type":"Point"}
}