{
  "type": "Feature",
  "properties": {
    "iso:country":"CH",
    "sg:address":"Wolfisb\u00fchl 30 6020 Emmenbr\u00fccke. Postfach",
    "sg:city":"Emmenbr\u00fccke",
    "sg:orig_category":"Handel mit Automobilteilen U Zubeh\u00f6r",
    "sg:postcode":"6020",
    "sg:province":"Luzern",
    "wof:name":"Abozu Auto- & Bootszubeh\u00f6r, Braun",
    "wof:placetype":"venue"
},
  "geometry": {"coordinates":[8.2511081696,47.068321228],"type":"Point"}
}