{
  "type": "Feature",
  "properties": {
    "addr:full":"Dorniackerstrasse 6 Sch\u00f6nb\u00fchl-urtenen Bern 3322",
    "addr:housenumber":"6",
    "addr:postcode":"3322",
    "addr:street":"Dorniackerstrasse",
    "iso:country":"CH",
    "sg:address":"Dorniackerstrasse 6",
    "sg:city":"Sch\u00f6nb\u00fchl-urtenen",
    "sg:orig_category":"Datenverarbeitungsdienste Fernmeldedienste",
    "sg:phone":"+41 31 852 03 31",
    "sg:postcode":"3322",
    "sg:province":"Bern",
    "wof:name":"Herren Martin Gmbh",
    "wof:placetype":"venue"
},
  "geometry": {"coordinates":[7.511157,47.020306],"type":"Point"}
}