{
  "type": "Feature",
  "properties": {
    "iso:country":"CH",
    "sg:address":"Zentrum Riedpark",
    "sg:city":"Neerach",
    "sg:orig_category":"Grosshandel mit Getr\u00e4nken",
    "sg:postcode":"8173",
    "sg:province":"Z\u00fcrich",
    "wof:name":"Schmid Walter Valserdepot Neerach",
    "wof:placetype":"venue"
},
  "geometry": {"coordinates":[8.4715433121,47.5125999451],"type":"Point"}
}