{
  "type": "Feature",
  "properties": {
    "iso:country":"CH",
    "sg:address":"Gassweidli 7 8856 Tuggen. Postfach",
    "sg:city":"Tuggen",
    "sg:orig_category":"Allgemeiner Hoch U Tiefbau Geb\u00e4ude, Wohnungsreinigung",
    "sg:phone":"+41 55 445 15 19",
    "sg:postcode":"8856",
    "sg:province":"Schwyz",
    "wof:name":"Mb-reinigungen Gmbh",
    "wof:placetype":"venue"
},
  "geometry": {"coordinates":[8.936475,47.202343],"type":"Point"}
}