{
  "type": "Feature",
  "properties": {
    "iso:country":"CH",
    "sg:address":"Ch. Des Vergers 44",
    "sg:city":"Crissier",
    "sg:orig_category":"Sanit\u00e4r, Heizungs U L\u00fcftungsinstallation",
    "sg:phone":"+41 21 635 84 91",
    "sg:postcode":"1023",
    "sg:province":"Vaud",
    "wof:name":"Rochat Michel",
    "wof:placetype":"venue"
},
  "geometry": {"coordinates":[6.5830521584,46.5533638],"type":"Point"}
}