{
  "type": "Feature",
  "properties": {
    "iso:country":"CH",
    "sg:address":"Piazzale Roncaa 4 6850 Mendrisio Casella Postale",
    "sg:city":"Mendrisio",
    "sg:orig_category":"Grosshandel mit Bekleidung Herstellung von Oberbekleidung",
    "sg:phone":"+41 91 858 19 23",
    "sg:postcode":"6850",
    "sg:province":"Ticino",
    "wof:name":"Confezioni Bernardi Sa",
    "wof:placetype":"venue"
},
  "geometry": {"coordinates":[8.9789562225,46.1534881592],"type":"Point"}
}