{
  "type": "Feature",
  "properties": {
    "iso:country":"CH",
    "sg:address":"Karl B\u00fcgler-strasse 6",
    "sg:city":"Neftenbach",
    "sg:orig_category":"Herstellung von Werkzeugen",
    "sg:phone":"+41 79 356 87 71",
    "sg:postcode":"8413",
    "sg:province":"Z\u00fcrich",
    "wof:name":"Natur-decor Menzi Wilhelm",
    "wof:placetype":"venue"
},
  "geometry": {"coordinates":[8.6590766907,47.5189361572],"type":"Point"}
}