{
  "type": "Feature",
  "properties": {
    "iso:country":"CH",
    "sg:address":"Schwarzenburgstrasse 200 3097 Liebefeld. Postfach 4",
    "sg:city":"Liebefeld",
    "sg:orig_category":"Fotografische Ateliers",
    "sg:phone":"+41 31 971 04 04",
    "sg:postcode":"3097",
    "sg:province":"Bern",
    "wof:name":"Rolf Weiss Fotografisches Atelier",
    "wof:placetype":"venue"
},
  "geometry": {"coordinates":[7.4186468124,46.9286460876],"type":"Point"}
}