{
  "type": "Feature",
  "properties": {
    "iso:country":"CH",
    "sg:address":"Bahnhofstrasse 11",
    "sg:city":"Belp",
    "sg:orig_category":"Detailhandel mit Brillen U anderen Sehhilfen Fachdetailhandel in Verkaufsr\u00e4umen",
    "sg:phone":"+41 31 819 21 81",
    "sg:postcode":"3123",
    "sg:province":"Bern",
    "wof:name":"Roder Optik",
    "wof:placetype":"venue"
},
  "geometry": {"coordinates":[7.498031,46.890301],"type":"Point"}
}