{
  "type": "Feature",
  "properties": {
    "iso:country":"CH",
    "sg:address":"Cantonale Route 185",
    "sg:city":"V\u00e9troz",
    "sg:orig_category":"Dauerkulturbau",
    "sg:postcode":"1963",
    "sg:province":"Valais",
    "wof:name":"Doviva Sa",
    "wof:placetype":"venue"
},
  "geometry": {"coordinates":[7.28257,46.225746],"type":"Point"}
}