{
  "type": "Feature",
  "properties": {
    "iso:country":"CH",
    "sg:address":"Gempenturmstrasse 15",
    "sg:city":"Gempen",
    "sg:classifiers":[
        {
            "category":"Restaurant",
            "type":"Food & Drink"
        }
    ],
    "sg:phone":"+41 61 701 32 20",
    "sg:postcode":"4145",
    "sg:province":"Solothurn",
    "wof:name":"Restaurant Gempenturm",
    "wof:placetype":"venue"
},
  "geometry": {"coordinates":[7.6495628357,47.4776992798],"type":"Point"}
}