{
  "type": "Feature",
  "properties": {
    "iso:country":"CH",
    "sg:address":"Tellistrasse 67",
    "sg:city":"Aarau",
    "sg:orig_category":"Nationale Postdienste",
    "sg:phone":"+41 61 481 30 30",
    "sg:postcode":"5004",
    "sg:province":"Aargau",
    "wof:name":"Die Schweizerische Post Allschwil 1",
    "wof:placetype":"venue"
},
  "geometry": {"coordinates":[7.5450367928,47.5526199341],"type":"Point"}
}