{
  "type": "Feature",
  "properties": {
    "iso:country":"CH",
    "sg:address":"Hofmatte C",
    "sg:city":"Baltschieder",
    "sg:orig_category":"Sportvereine Unihockey",
    "sg:phone":"+41 27 946 19 02",
    "sg:postcode":"3937",
    "sg:province":"Valais",
    "wof:name":"Uhc Visper Lions",
    "wof:placetype":"venue"
},
  "geometry": {"coordinates":[7.8640441895,46.306930542],"type":"Point"}
}