{
  "type": "Feature",
  "properties": {
    "iso:country":"CH",
    "sg:address":"Am Schanzengraben 13a",
    "sg:city":"Z\u00fcrich",
    "sg:orig_category":"Unternehmensberatung",
    "sg:phone":"+41 12013633",
    "sg:postcode":"8002",
    "sg:province":"Z\u00fcrich",
    "wof:name":"Fischmi Consulting Group Ag Management-consulting; Vermittlung, Dienste Usw",
    "wof:placetype":"venue"
},
  "geometry": {"coordinates":[8.5364170074,47.3686485291],"type":"Point"}
}