{
  "type": "Feature",
  "properties": {
    "iso:country":"CH",
    "sg:address":"Ch. De La Pr\u00e9v\u00f4t\u00e9 7 / Propsteiweg 7",
    "sg:city":"Biel/bienne",
    "sg:orig_category":"Herstellung von Drahtwaren Herstellung von Schrauben, Nieten, Ketten U Federn",
    "sg:phone":"+41 32 341 30 79",
    "sg:postcode":"2504",
    "sg:province":"Bern",
    "wof:name":"Favre-steudler Sa",
    "wof:placetype":"venue"
},
  "geometry": {"coordinates":[7.2761301994,47.1589012146],"type":"Point"}
}