{
  "type": "Feature",
  "properties": {
    "iso:country":"CH",
    "sg:address":"Stadtturmstrasse 19 5400 Baden. Postfach",
    "sg:city":"Baden",
    "sg:orig_category":"Verlagsgewerbe Zeitungsverlag",
    "sg:phone":"+41 56 204 24 24",
    "sg:postcode":"5401",
    "sg:province":"Aargau",
    "wof:name":"Aargauer Zeitung Ag",
    "wof:placetype":"venue"
},
  "geometry": {"coordinates":[8.3055353165,47.4757881165],"type":"Point"}
}