{
  "type": "Feature",
  "properties": {
    "iso:country":"CH",
    "sg:address":"B\u00f6zingenstr. 157 2500 Biel/bienne. Postfach",
    "sg:city":"Biel/bienne",
    "sg:orig_category":"Zimmerei, Dachdeckerei, Bauspenglerei U Abdichtung",
    "sg:postcode":"2504",
    "sg:province":"Bern",
    "wof:name":"Franconi Jean",
    "wof:placetype":"venue"
},
  "geometry": {"coordinates":[7.2653079033,47.1518516541],"type":"Point"}
}