{
  "type": "Feature",
  "properties": {
    "iso:country":"CH",
    "sg:address":"Route Andr\u00e9-piller 21 1762 Givisiez Case Postale 78",
    "sg:city":"Givisiez",
    "sg:orig_category":"Wirtschaftspr\u00fcfung, Steuerberatung U Treuhand",
    "sg:phone":"+41 26 466 78 78",
    "sg:postcode":"1762",
    "sg:province":"Fribourg",
    "wof:name":"Stratman Sa",
    "wof:placetype":"venue"
},
  "geometry": {"coordinates":[7.1199622154,46.8123397827],"type":"Point"}
}