{
  "type": "Feature",
  "properties": {
    "iso:country":"CH",
    "sg:address":"Route De Riaz 2",
    "sg:city":"Bulle",
    "sg:orig_category":"Sonstiger Grosshandel",
    "sg:phone":"+41 2939700",
    "sg:postcode":"1630",
    "sg:province":"Fribourg",
    "wof:name":"Sts, Selective Trading Systems, Shifteh Le Marquand C.",
    "wof:placetype":"venue"
},
  "geometry": {"coordinates":[7.0583148003,46.6213150024],"type":"Point"}
}