{
  "type": "Feature",
  "properties": {
    "iso:country":"CH",
    "sg:address":"Ried 3616 Schwarzenegg. Postfach",
    "sg:city":"Schwarzenegg",
    "sg:orig_category":"Herstellung von sonstigen landwirtschaftlichen Maschinen",
    "sg:phone":"+41 77311763",
    "sg:postcode":"3616",
    "sg:province":"Bern",
    "wof:name":"Mehli Eduard",
    "wof:placetype":"venue"
},
  "geometry": {"coordinates":[7.2964959145,47.1177139282],"type":"Point"}
}