{
  "type": "Feature",
  "properties": {
    "iso:country":"CH",
    "sg:address":"Hundsbrunn 108",
    "sg:city":"R\u00fcnenberg",
    "sg:orig_category":"Wirtschaftspr\u00fcfung, Steuerberatung U Treuhand",
    "sg:phone":"+41 61 983 94 55",
    "sg:postcode":"4497",
    "sg:province":"Basel-Landschaft",
    "wof:name":"Treuhandb\u00fcro H.furer & Co",
    "wof:placetype":"venue"
},
  "geometry": {"coordinates":[7.8842592239,47.4285392761],"type":"Point"}
}