{
  "type": "Feature",
  "properties": {
    "iso:country":"CH",
    "sg:address":"Poststrasse 3",
    "sg:city":"Chur",
    "sg:orig_category":"Detailhandel mit Geschenkartikeln U Souvenirs Detailhandel mit Parf\u00fcmerieartikeln U K\u00f6rperpflegemitt",
    "sg:phone":"+41 81 253 66 41",
    "sg:postcode":"7000",
    "sg:province":"Graubunden",
    "wof:name":"Sisley Sa",
    "wof:placetype":"venue"
},
  "geometry": {"coordinates":[9.5322351456,46.850315094],"type":"Point"}
}