{
  "type": "Feature",
  "properties": {
    "addr:full":"Birkenweg 2 Menzingen Zug 6313",
    "addr:housenumber":"2",
    "addr:postcode":"6313",
    "addr:street":"Birkenweg;Zug",
    "iso:country":"CH",
    "sg:address":"Birkenweg 2",
    "sg:city":"Menzingen",
    "sg:orig_category":"Architektur U Ingenieurb\u00fcros",
    "sg:postcode":"6313",
    "sg:province":"Zug",
    "wof:name":"Be-ma-so Gmbh",
    "wof:placetype":"venue"
},
  "geometry": {"coordinates":[8.592583,47.177952],"type":"Point"}
}