{
  "type": "Feature",
  "properties": {
    "iso:country":"CH",
    "sg:address":"Florastrasse 32",
    "sg:city":"Dietikon",
    "sg:orig_category":"Sonstige pers\u00f6nliche Dienstleistungen",
    "sg:phone":"+41 71 385 71 79",
    "sg:postcode":"8953",
    "sg:province":"Z\u00fcrich",
    "wof:name":"Bagos Gmbh",
    "wof:placetype":"venue"
},
  "geometry": {"coordinates":[9.2579221725,47.4160575867],"type":"Point"}
}