{
  "type": "Feature",
  "properties": {
    "iso:country":"CH",
    "sg:address":"9240 Uzwil. Postfach 23",
    "sg:city":"Uzwil",
    "sg:orig_category":"Sportvereine Ballsport Fussball",
    "sg:phone":"+41 79 431 84 12",
    "sg:postcode":"9240",
    "sg:province":"St. Gallen",
    "wof:name":"Fc N.k.croatia",
    "wof:placetype":"venue"
},
  "geometry": {"coordinates":[9.1329545975,47.4371452332],"type":"Point"}
}