{
  "type": "Feature",
  "properties": {
    "iso:country":"CH",
    "sg:address":"Talg\u00fcetlistrasse 18",
    "sg:city":"Bassersdorf",
    "sg:orig_category":"Vereine Fasnacht",
    "sg:phone":"+41 18367618",
    "sg:postcode":"8303",
    "sg:province":"Z\u00fcrich",
    "wof:name":"Fasnachts Komitee",
    "wof:placetype":"venue"
},
  "geometry": {"coordinates":[8.6205196381,47.4463424683],"type":"Point"}
}