{
  "type": "Feature",
  "properties": {
    "iso:country":"CH",
    "sg:address":"Bahnhofstrasse 745",
    "sg:city":"Wigoltingen",
    "sg:orig_category":"Detailhandel mit Radio U Fernsehger\u00e4ten Herstellung von Radio U Fernsehger\u00e4ten sowie phono U videote",
    "sg:phone":"+41 52 762 70 00",
    "sg:postcode":"8556",
    "sg:province":"Thurgau",
    "wof:name":"Audio-plan, Willi & Partner",
    "wof:placetype":"venue"
},
  "geometry": {"coordinates":[9.0308103561,47.5975608826],"type":"Point"}
}