{
  "type": "Feature",
  "properties": {
    "iso:country":"CH",
    "sg:address":"Parc Le",
    "sg:city":"Ch\u00e2teau-d'oex",
    "sg:orig_category":"Unclassifiable Establishments",
    "sg:postcode":"1837",
    "wof:name":"Bowling Du Parc Sa",
    "wof:placetype":"venue"
},
  "geometry": {"coordinates":[0.3826749921,49.5512084961],"type":"Point"}
}