{
  "type": "Feature",
  "properties": {
    "iso:country":"CH",
    "sg:address":"Kirchstrasse 16a",
    "sg:city":"Dietikon",
    "sg:orig_category":"Fachdetailhandel in Verkaufsr\u00e4umen",
    "sg:phone":"+41 17410676",
    "sg:postcode":"8953",
    "sg:province":"Z\u00fcrich",
    "wof:name":"Ballonhuus Butterfly, M\u00e4der Edith",
    "wof:placetype":"venue"
},
  "geometry": {"coordinates":[8.4030570984,47.4056510925],"type":"Point"}
}