{
  "type": "Feature",
  "properties": {
    "iso:country":"CH",
    "sg:address":"Ischlagweg 3",
    "sg:city":"Aefligen",
    "sg:orig_category":"Primarschulen",
    "sg:phone":"+41 34 445 27 26",
    "sg:postcode":"3426",
    "sg:province":"Bern",
    "wof:name":"Primarschule",
    "wof:placetype":"venue"
},
  "geometry": {"coordinates":[7.5534820557,47.0969696045],"type":"Point"}
}