{
  "type": "Feature",
  "properties": {
    "iso:country":"CH",
    "sg:address":"Hofmatt 2 6048 Horw. Postfach",
    "sg:city":"Horw",
    "sg:orig_category":"Konkurs- and Betreibungs\u00e4mter",
    "sg:phone":"+41 41 349 12 35",
    "sg:postcode":"6048",
    "sg:province":"Luzern",
    "wof:name":"Betreibungsamt",
    "wof:placetype":"venue"
},
  "geometry": {"coordinates":[8.312710762,47.0201454163],"type":"Point"}
}