{
  "type": "Feature",
  "properties": {
    "addr:full":"Avenue De La Gare 17 Lausanne Vaud 1003",
    "addr:housenumber":"17",
    "addr:postcode":"1003",
    "addr:street":"Avenue De La Gare",
    "iso:country":"CH",
    "sg:address":"Avenue De La Gare 17",
    "sg:city":"Lausanne",
    "sg:orig_category":"Chiropraktik",
    "sg:phone":"+41 22 342 80 70",
    "sg:postcode":"1003",
    "sg:province":"Vaud",
    "wof:name":"Lucie Riondel Bellier Chiropraticienne",
    "wof:placetype":"venue"
},
  "geometry": {"coordinates":[6.135198,46.187988],"type":"Point"}
}