{
  "type": "Feature",
  "properties": {
    "iso:country":"CH",
    "sg:address":"Rebenstrasse 63d",
    "sg:city":"Ottenbach",
    "sg:orig_category":"Werbung",
    "sg:phone":"+41 17613814",
    "sg:postcode":"8913",
    "sg:province":"Z\u00fcrich",
    "wof:name":"Messerli Werben Werbeagentur",
    "wof:placetype":"venue"
},
  "geometry": {"coordinates":[8.4081897736,47.2806396484],"type":"Point"}
}