{
  "type": "Feature",
  "properties": {
    "addr:full":"Tramstrasse 85 Muttenz Basel-Landschaft 4132",
    "addr:housenumber":"85",
    "addr:postcode":"4132",
    "addr:street":"Tramstrasse",
    "iso:country":"CH",
    "sg:address":"Tramstrasse 85",
    "sg:city":"Muttenz",
    "sg:orig_category":"Detailhandel mit Beleuchtungs U Haushaltsgegenst\u00e4nden Einbau von Schreinerwaren",
    "sg:phone":"+41 32 953 14 03",
    "sg:postcode":"4132",
    "sg:province":"Basel-Landschaft",
    "wof:name":"Joseph Haefeli Sa",
    "wof:placetype":"venue"
},
  "geometry": {"coordinates":[6.960741,47.224968],"type":"Point"}
}