{
  "type": "Feature",
  "properties": {
    "iso:country":"CH",
    "sg:address":"Lenzhardweg 7",
    "sg:city":"Niederlenz",
    "sg:orig_category":"Herstellung von Metallkonstruktionen",
    "sg:phone":"+41 62 891 16 33",
    "sg:postcode":"5702",
    "sg:province":"Aargau",
    "wof:name":"St. W\u00fclser Gmbh",
    "wof:placetype":"venue"
},
  "geometry": {"coordinates":[8.1720094681,47.4008331299],"type":"Point"}
}