{
  "type": "Feature",
  "properties": {
    "iso:country":"CH",
    "sg:address":"Sch\u00f6nau 101",
    "sg:city":"Hittnau",
    "sg:orig_category":"Hardwareberatung",
    "sg:phone":"+41 19503048",
    "sg:postcode":"8335",
    "sg:province":"Z\u00fcrich",
    "wof:name":"Waespi B., Daten-netzwerk-installationen",
    "wof:placetype":"venue"
},
  "geometry": {"coordinates":[8.8259792328,47.3791351318],"type":"Point"}
}