{
  "type": "Feature",
  "properties": {
    "addr:full":"Belchenstrasse 2a Basel Basel-Stadt 4054",
    "addr:housenumber":"2a",
    "addr:postcode":"4054",
    "addr:street":"Belchenstrasse",
    "iso:country":"CH",
    "sg:address":"Belchenstrasse 2a",
    "sg:city":"Basel",
    "sg:classifiers":[
        {
            "category":"Banks & Credit Unions",
            "subcategory":"Investment Brokerage",
            "type":"Services"
        }
    ],
    "sg:phone":"+41 61 301 63 01",
    "sg:postcode":"4054",
    "sg:province":"Basel-Stadt",
    "sg:tags":[
        "table",
        "all-purpose",
        "roller"
    ],
    "wof:name":"Scan Modul System Ag",
    "wof:placetype":"venue"
},
  "geometry": {"coordinates":[7.57391,47.554298],"type":"Point"}
}