{
  "type": "Feature",
  "properties": {
    "iso:country":"CH",
    "sg:address":"Avenue Des Toises 8",
    "sg:city":"Lausanne",
    "sg:orig_category":"Sonstiges Versicherungsgewerbe",
    "sg:phone":"+41 21 323 15 66",
    "sg:postcode":"1005",
    "sg:province":"Vaud",
    "wof:name":"Ezri Edmond Et Fils Sa",
    "wof:placetype":"venue"
},
  "geometry": {"coordinates":[6.6406011581,46.5178604126],"type":"Point"}
}