{
  "type": "Feature",
  "properties": {
    "iso:country":"CH",
    "sg:address":"Avenue De France 2",
    "sg:city":"Lausanne",
    "sg:orig_category":"Detailhandel mit medizinischen U orthop\u00e4dischen Artikeln Herstellung von medizinischen U chirurgisch",
    "sg:phone":"+41 21 624 79 08",
    "sg:postcode":"1004",
    "sg:province":"Vaud",
    "wof:name":"Dessabo Fernando",
    "wof:placetype":"venue"
},
  "geometry": {"coordinates":[6.6248021126,46.5239181519],"type":"Point"}
}