{
  "type": "Feature",
  "properties": {
    "iso:country":"CH",
    "sg:address":"Niffel",
    "sg:city":"Hochdorf",
    "sg:orig_category":"Herstellung von Konstruktionsteilen, Fertigbauteilen U Ausbauelementen aus Holz",
    "sg:phone":"+41 41 910 48 16",
    "sg:postcode":"6280",
    "sg:province":"Luzern",
    "wof:name":"Schacher Z\u00e4une Ag",
    "wof:placetype":"venue"
},
  "geometry": {"coordinates":[8.2743797302,47.1609382629],"type":"Point"}
}