{
  "type": "Feature",
  "properties": {
    "iso:country":"CH",
    "sg:address":"Dorfstrasse 13a 6340 Baar. Postfach",
    "sg:city":"Baar",
    "sg:orig_category":"Kauf U Verkauf von Immobilien auf eigene Rechnung",
    "sg:postcode":"6340",
    "sg:province":"Zug",
    "wof:name":"Immotre Ag",
    "wof:placetype":"venue"
},
  "geometry": {"coordinates":[8.5252084732,47.1940345764],"type":"Point"}
}