{
  "type": "Feature",
  "properties": {
    "iso:country":"CH",
    "sg:address":"Jakob F\u00fcgli-strasse 2",
    "sg:city":"Z\u00fcrich",
    "sg:orig_category":"Mechanik",
    "sg:phone":"+41 14304242",
    "sg:postcode":"8048",
    "sg:province":"Z\u00fcrich",
    "wof:name":"Transtechnik Bertsch",
    "wof:placetype":"venue"
},
  "geometry": {"coordinates":[8.4846496582,47.3897476196],"type":"Point"}
}