{
  "type": "Feature",
  "properties": {
    "addr:full":"Landstrasse 51 8450 Andelfingen. Postfach 173 Andelfingen Z\u00fcrich 8450",
    "addr:housenumber":"51;173",
    "addr:postcode":"8450 andelfingen.;8450",
    "addr:street":"Landstrasse;Postfach",
    "iso:country":"CH",
    "sg:address":"Landstrasse 51 8450 Andelfingen. Postfach 173",
    "sg:city":"Andelfingen",
    "sg:orig_category":"Bauingenieurb\u00fcros Geometerb\u00fcros",
    "sg:phone":"+41 52 305 22 55",
    "sg:postcode":"8450",
    "sg:province":"Z\u00fcrich",
    "wof:name":"Hofmann, Stegemann + Partner",
    "wof:placetype":"venue"
},
  "geometry": {"coordinates":[8.677713,47.594624],"type":"Point"}
}