{
  "type": "Feature",
  "properties": {
    "iso:country":"CH",
    "sg:address":"Steinmatte",
    "sg:city":"Zermatt",
    "sg:classifiers":[
        {
            "category":"Travel",
            "subcategory":"Hotels & Motels",
            "type":"Entertainment"
        }
    ],
    "sg:postcode":"3920",
    "sg:province":"Valais",
    "sg:tags":[
        "hotels",
        "mit",
        "restaurant"
    ],
    "wof:name":"Julen C\u00e4sar.",
    "wof:placetype":"venue"
},
  "geometry": {"coordinates":[7.74958992,46.018901825],"type":"Point"}
}