{
  "type": "Feature",
  "properties": {
    "iso:country":"CH",
    "sg:address":"Eisenburgstrasse 10 8854 Siebnen. Postfach",
    "sg:city":"Siebnen",
    "sg:orig_category":"Pensionskassen",
    "sg:postcode":"8854",
    "sg:province":"Schwyz",
    "wof:name":"Pensionsfonds Der Firma Wirth & Co Ag Siebnen",
    "wof:placetype":"venue"
},
  "geometry": {"coordinates":[8.8982648849,47.1741981506],"type":"Point"}
}