{
  "type": "Feature",
  "properties": {
    "iso:country":"CH",
    "sg:address":"5300",
    "sg:city":"Turgi",
    "sg:orig_category":"Primarschulen",
    "sg:phone":"+41 56 223 16 21",
    "sg:postcode":"5300",
    "sg:province":"Aargau",
    "wof:name":"Primarschule",
    "wof:placetype":"venue"
},
  "geometry": {"coordinates":[8.2524995804,47.4925689697],"type":"Point"}
}