{
  "type": "Feature",
  "properties": {
    "iso:country":"CH",
    "sg:address":"Hauptstrasse 12",
    "sg:city":"Effretikon",
    "sg:orig_category":"Grosshandel mit sonstigen Halbwaren Herstellung von sonstigen Kunststoffwaren",
    "sg:phone":"+41 52 343 62 62",
    "sg:postcode":"8307",
    "sg:province":"Z\u00fcrich",
    "wof:name":"Compasei Ag",
    "wof:placetype":"venue"
},
  "geometry": {"coordinates":[8.695921,47.411781],"type":"Point"}
}