{
  "type": "Feature",
  "properties": {
    "iso:country":"CH",
    "sg:address":"Via Peri 17",
    "sg:city":"Lugano",
    "sg:orig_category":"Planer f\u00fcr Energiekonzepte",
    "sg:phone":"+41 91 913 39 40",
    "sg:postcode":"6900",
    "sg:province":"Ticino",
    "wof:name":"Ralipa Trading B. Amsterdam Lugano Branch",
    "wof:placetype":"venue"
},
  "geometry": {"coordinates":[8.9504804611,46.0060806274],"type":"Point"}
}