{
  "type": "Feature",
  "properties": {
    "iso:country":"CH",
    "sg:address":"Hauptstrasse 15",
    "sg:city":"Lausen",
    "sg:orig_category":"Unclassifiable Establishments",
    "sg:postcode":"4415",
    "sg:province":"Basel-Landschaft",
    "wof:name":"Libasit Gmbh",
    "wof:placetype":"venue"
},
  "geometry": {"coordinates":[7.7527198792,47.4749412537],"type":"Point"}
}