{
  "type": "Feature",
  "properties": {
    "addr:full":"Friedhofstrasse 30 Derendingen Solothurn 4552",
    "addr:housenumber":"30",
    "addr:postcode":"4552",
    "addr:street":"Friedhofstrasse",
    "iso:country":"CH",
    "sg:address":"Friedhofstrasse 30",
    "sg:city":"Derendingen",
    "sg:orig_category":"Detailhandel mit Brot, Back U S\u00fcsswaren",
    "sg:phone":"+41 32 682 20 49",
    "sg:postcode":"4552",
    "sg:province":"Solothurn",
    "wof:name":"Markus Oesch B\u00e4ckerei-konditorei",
    "wof:placetype":"venue"
},
  "geometry": {"coordinates":[7.585901,47.195492],"type":"Point"}
}