{
  "type": "Feature",
  "properties": {
    "iso:country":"CH",
    "sg:address":"Rue De L'ancienne-poste 4",
    "sg:city":"Yverdon-les-bains",
    "sg:classifiers":[
        {
            "category":"Education",
            "subcategory":"Library",
            "type":"Public Place"
        }
    ],
    "sg:phone":"+41 32 751 44 14",
    "sg:postcode":"1400",
    "sg:province":"Vaud",
    "sg:tags":[
        "u",
        "bibliotheken",
        "archive"
    ],
    "wof:name":"Biblioth\u00e8que Publique",
    "wof:placetype":"venue"
},
  "geometry": {"coordinates":[6.061729,48.150242],"type":"Point"}
}