{
  "type": "Feature",
  "properties": {
    "iso:country":"CH",
    "sg:address":"V\u00e9lodrome Rue Du 12 1205 Gen\u00e8ve. Postfach",
    "sg:city":"Gen\u00e8ve",
    "sg:orig_category":"Satzherstellung U Reproduktion",
    "sg:phone":"+41 22 782 54 12",
    "sg:postcode":"1205",
    "sg:province":"Gen\u00e8ve",
    "wof:name":"Champagne Jean-claude",
    "wof:placetype":"venue"
},
  "geometry": {"coordinates":[6.1312308311,46.1997718811],"type":"Point"}
}