{
  "type": "Feature",
  "properties": {
    "iso:country":"CH",
    "sg:address":"G\u00fcrbeweg 20",
    "sg:city":"Belp",
    "sg:orig_category":"Werbegrafikateliers",
    "sg:phone":"+41 17847597",
    "sg:postcode":"3123",
    "sg:province":"Bern",
    "wof:name":"Grafik & Gestaltung Robert Geiter",
    "wof:placetype":"venue"
},
  "geometry": {"coordinates":[8.7426996231,47.2001037598],"type":"Point"}
}