{
  "type": "Feature",
  "properties": {
    "iso:country":"CH",
    "sg:address":"Seewydenstrasse 3",
    "sg:city":"Goldach",
    "sg:orig_category":"P\u00e9dicure",
    "sg:phone":"+41 71 841 94 71",
    "sg:postcode":"9403",
    "sg:province":"St. Gallen",
    "wof:name":"Claudia Ridolfi Kosmetik & P\u00e9dicure Claudia",
    "wof:placetype":"venue"
},
  "geometry": {"coordinates":[9.4797315598,47.4801330566],"type":"Point"}
}