{
  "type": "Feature",
  "properties": {
    "iso:country":"CH",
    "sg:address":"Neubadstrasse 7 4054 Basel. Postfach",
    "sg:city":"Basel",
    "sg:orig_category":"Grosshandel mit chemischen Erzeugnissen",
    "sg:phone":"+41 56 633 48 15",
    "sg:postcode":"4015",
    "sg:province":"Basel-Stadt",
    "wof:name":"Cermak Solutions",
    "wof:placetype":"venue"
},
  "geometry": {"coordinates":[8.3434915543,47.3511543274],"type":"Point"}
}