{
  "type": "Feature",
  "properties": {
    "iso:country":"CH",
    "sg:address":"R\u00fcdtligenstrasse 2",
    "sg:city":"Aefligen",
    "sg:orig_category":"Herstellung von Metallkonstruktionen",
    "sg:postcode":"3426",
    "sg:province":"Bern",
    "wof:name":"Iseli Metabau Ag",
    "wof:placetype":"venue"
},
  "geometry": {"coordinates":[7.557393074,47.0938262939],"type":"Point"}
}