{
  "type": "Feature",
  "properties": {
    "iso:country":"CH",
    "sg:address":"7450",
    "sg:city":"Tiefencastel",
    "sg:orig_category":"Polizei",
    "sg:phone":"+41 81 681 11 08",
    "sg:postcode":"7450",
    "sg:province":"Graubunden",
    "wof:name":"Kantonale Polizei",
    "wof:placetype":"venue"
},
  "geometry": {"coordinates":[9.5771245956,46.6626968384],"type":"Point"}
}