{
  "type": "Feature",
  "properties": {
    "iso:country":"CH",
    "sg:address":"Vieux-port Chemin Du 20",
    "sg:city":"Versoix",
    "sg:orig_category":"Unclassifiable Establishments",
    "sg:postcode":"1290",
    "sg:province":"Gen\u00e8ve",
    "wof:name":"Buvette Du Brand, Bapst Josianne",
    "wof:placetype":"venue"
},
  "geometry": {"coordinates":[7.1539611816,46.6860542297],"type":"Point"}
}