{
  "type": "Feature",
  "properties": {
    "iso:country":"CH",
    "sg:address":"Ausserdorf 5",
    "sg:city":"Ettiswil",
    "sg:orig_category":"Handel mit Motorr\u00e4dern, Teilen U Zubeh\u00f6r Instandhaltung U Reparatur von Motorr\u00e4dern",
    "sg:phone":"+41 61 911 02 00",
    "sg:postcode":"6218",
    "sg:province":"Luzern",
    "wof:name":"Von Allmen Walter Motos",
    "wof:placetype":"venue"
},
  "geometry": {"coordinates":[7.6738190651,47.4497718811],"type":"Point"}
}