{
  "type": "Feature",
  "properties": {
    "iso:country":"CH",
    "sg:address":"Sch\u00fcrlistrasse 21",
    "sg:city":"Dietikon",
    "sg:orig_category":"Softwareentwicklung U beratung",
    "sg:postcode":"8953",
    "sg:province":"Z\u00fcrich",
    "wof:name":"Pm It-consulting Gmbh",
    "wof:placetype":"venue"
},
  "geometry": {"coordinates":[8.3874759674,47.4004669189],"type":"Point"}
}