{
  "type": "Feature",
  "properties": {
    "iso:country":"CH",
    "sg:address":"Gehrlistrasse 2",
    "sg:city":"Eichberg",
    "sg:classifiers":[
        {
            "category":"Shopping",
            "subcategory":"Used Merchandise",
            "type":"Retail Goods"
        }
    ],
    "sg:phone":"+41 71 755 36 26",
    "sg:postcode":"9453",
    "sg:province":"St. Gallen",
    "sg:tags":[
        "agricultural",
        "machinery"
    ],
    "wof:name":"Br\u00fclisauer Landmaschinen Gmbh",
    "wof:placetype":"venue"
},
  "geometry": {"coordinates":[9.528049,47.340866],"type":"Point"}
}