{
  "type": "Feature",
  "properties": {
    "iso:country":"CH",
    "sg:address":"Rubigenstrasse 91 3076 Bangerten B. Worb. Postfach",
    "sg:city":"Worb",
    "sg:orig_category":"Herstellung von Reiseartikeln, Leder U Sattlerwaren",
    "sg:phone":"+41 31 838 37 37",
    "sg:postcode":"3076",
    "sg:province":"Bern",
    "wof:name":"W. Bernhard Ag",
    "wof:placetype":"venue"
},
  "geometry": {"coordinates":[7.5645651817,46.9146461487],"type":"Point"}
}