{
  "type": "Feature",
  "properties": {
    "iso:country":"CH",
    "sg:address":"Hauptstrasse",
    "sg:city":"Ch\u00e2teau-d'oex",
    "sg:orig_category":"Herstellung von sonstigen Nahrungsmitteln",
    "sg:postcode":"1837",
    "wof:name":"Tartepain Sa",
    "wof:placetype":"venue"
},
  "geometry": {"coordinates":[0.6858400106,45.2460517883],"type":"Point"}
}