{
  "type": "Feature",
  "properties": {
    "iso:country":"CH",
    "sg:address":"Mettlenweg 34",
    "sg:city":"Biel/bienne",
    "sg:orig_category":"Steuerberatung",
    "sg:phone":"+41 33 336 86 66",
    "sg:postcode":"2504",
    "sg:province":"Bern",
    "wof:name":"Heinz Bercher Vorsorge- & Steuerberatung",
    "wof:placetype":"venue"
},
  "geometry": {"coordinates":[7.6331510544,46.7141838074],"type":"Point"}
}