{
  "type": "Feature",
  "properties": {
    "iso:country":"CH",
    "sg:address":"Lonzastrasse 3930 Visp. Postfach",
    "sg:city":"Visp",
    "sg:orig_category":"Herstellung von D\u00fcngemitteln U Stickstoffverbindungen Herstellung von Kunststoff in Prim\u00e4rformen",
    "sg:phone":"+41 27 948 51 11",
    "sg:postcode":"3930",
    "sg:province":"Valais",
    "wof:name":"Lonza Group Ag",
    "wof:placetype":"venue"
},
  "geometry": {"coordinates":[7.8835601807,46.2947311401],"type":"Point"}
}