{
  "type": "Feature",
  "properties": {
    "iso:country":"CH",
    "sg:address":"Rue Abb\u00e9-monnin 38",
    "sg:city":"Bassecourt",
    "sg:orig_category":"Reiseb\u00fcros",
    "sg:phone":"+41 32 426 83 43",
    "sg:postcode":"2854",
    "sg:province":"Jura",
    "wof:name":"Voyages Allemann",
    "wof:placetype":"venue"
},
  "geometry": {"coordinates":[7.2476229668,47.3373222351],"type":"Point"}
}