{
  "type": "Feature",
  "properties": {
    "iso:country":"CH",
    "sg:address":"Lindenfeldweg 1",
    "sg:city":"Therwil",
    "sg:orig_category":"Detailhandel mit M\u00f6beln Innendekorationsateliers",
    "sg:phone":"+41 61 721 36 46",
    "sg:postcode":"4106",
    "sg:province":"Basel-Landschaft",
    "wof:name":"Walter Hanel Werkst\u00e4tte F\u00fcr Polsterm\u00f6bel",
    "wof:placetype":"venue"
},
  "geometry": {"coordinates":[7.547990799,47.498664856],"type":"Point"}
}