{
  "type": "Feature",
  "properties": {
    "iso:country":"CH",
    "sg:address":"Saluferstrasse 37 7000 Chur. Postfach",
    "sg:city":"Chur",
    "sg:orig_category":"Reinigungsgewerbe",
    "sg:postcode":"7000",
    "sg:province":"Graubunden",
    "wof:name":"Sf Geb\u00e4udereinigung Fejzaj S. & Co",
    "wof:placetype":"venue"
},
  "geometry": {"coordinates":[9.5340337753,46.8634719849],"type":"Point"}
}