{
  "type": "Feature",
  "properties": {
    "iso:country":"CH",
    "sg:address":"Rue Du Molage 48",
    "sg:city":"Aigle",
    "sg:orig_category":"Schreib U \u00dcbersetzungsb\u00fcros",
    "sg:postcode":"1860",
    "sg:province":"Vaud",
    "wof:name":"Cinetrans Ag",
    "wof:placetype":"venue"
},
  "geometry": {"coordinates":[8.3082056046,46.9945297241],"type":"Point"}
}