{
  "type": "Feature",
  "properties": {
    "iso:country":"CH",
    "sg:address":"Rue Basse 42",
    "sg:city":"St-ursanne",
    "sg:classifiers":[
        {
            "category":"Insurance",
            "subcategory":"Insurance Agent",
            "type":"Services"
        }
    ],
    "sg:phone":"+41 79 354 59 25",
    "sg:postcode":"2882",
    "sg:province":"Jura",
    "sg:tags":[
        "versicherungsagenturen",
        "-broker"
    ],
    "wof:name":"Elvia Assurances Agence",
    "wof:placetype":"venue"
},
  "geometry": {"coordinates":[7.1552667618,47.3649253845],"type":"Point"}
}