{
  "type": "Feature",
  "properties": {
    "iso:country":"CH",
    "sg:address":"Benkenstrasse 38",
    "sg:city":"Basel",
    "sg:orig_category":"Fussreflexzonenmassage",
    "sg:phone":"+41 61 281 28 26",
    "sg:postcode":"4054",
    "sg:province":"Basel-Stadt",
    "wof:name":"Ursula Treier Fussreflexzonentherapie",
    "wof:placetype":"venue"
},
  "geometry": {"coordinates":[7.5727791786,47.5484580994],"type":"Point"}
}