{
  "type": "Feature",
  "properties": {
    "iso:country":"CH",
    "sg:address":"Hans-hugi-strasse 2 2502 Biel/bienne Case Postale 620",
    "sg:city":"Biel/bienne",
    "sg:orig_category":"Handelskammern Wirtschafts- and Arbeitgeberverb\u00e4nde",
    "sg:phone":"+41 32 322 46 84",
    "sg:postcode":"2501",
    "sg:province":"Bern",
    "wof:name":"Handels-& Industrieverein Des Kantons Bern",
    "wof:placetype":"venue"
},
  "geometry": {"coordinates":[7.2453460693,47.1329841614],"type":"Point"}
}