{
  "type": "Feature",
  "properties": {
    "iso:country":"CH",
    "sg:address":"S\u00e4gemattstrasse 2",
    "sg:city":"Liebefeld",
    "sg:orig_category":"Sonstige Kultur U Unterhaltungseinrichtungen Tanzschulen, Tanzlehrer",
    "sg:phone":"+41 31 382 65 54",
    "sg:postcode":"3097",
    "sg:province":"Bern",
    "wof:name":"Ballett Studio Spiegel",
    "wof:placetype":"venue"
},
  "geometry": {"coordinates":[7.4162139893,46.9273490906],"type":"Point"}
}