{
  "type": "Feature",
  "properties": {
    "iso:country":"CH",
    "sg:address":"Rue Des Tanneurs 7",
    "sg:city":"Porrentruy",
    "sg:orig_category":"Softwareentwicklung U beratung",
    "sg:phone":"+41 32 466 81 51",
    "sg:postcode":"2900",
    "sg:province":"Jura",
    "wof:name":"Solution Informatique Vallat & Muller S\u00e0rl",
    "wof:placetype":"venue"
},
  "geometry": {"coordinates":[7.0773191452,47.4177398682],"type":"Point"}
}