{
  "type": "Feature",
  "properties": {
    "iso:country":"CH",
    "sg:address":"Rebbergstrasse 15",
    "sg:city":"Zufikon",
    "sg:orig_category":"Detektivb\u00fcros U \u00dcberwachung",
    "sg:postcode":"5621",
    "sg:province":"Aargau",
    "wof:name":"Dupr\u00e9 Sicherheitsdienst - Mds",
    "wof:placetype":"venue"
},
  "geometry": {"coordinates":[8.3558673859,47.3539924622],"type":"Point"}
}