{
  "type": "Feature",
  "properties": {
    "iso:country":"CH",
    "sg:address":"Villarvassaux",
    "sg:city":"Gumefens",
    "sg:orig_category":"Erwachsenenbildung U Unterricht",
    "sg:phone":"+41 29911003",
    "sg:postcode":"1643",
    "sg:province":"Fribourg",
    "wof:name":"Dialogue Ecole De Langues Jorio Eva Cours Et Traductions",
    "wof:placetype":"venue"
},
  "geometry": {"coordinates":[7.0768499374,46.6772918701],"type":"Point"}
}