{
  "type": "Feature",
  "properties": {
    "iso:country":"CH",
    "sg:address":"Gottfried-keller-strasse 13",
    "sg:city":"Romanshorn",
    "sg:orig_category":"Herstellung von Tanks U Sammelbeh\u00e4ltern aus Metall",
    "sg:phone":"+41 71 463 25 22",
    "sg:postcode":"8590",
    "sg:province":"Thurgau",
    "wof:name":"Bentivoglio Gmbh Tank-service Revisionen & Reinigung",
    "wof:placetype":"venue"
},
  "geometry": {"coordinates":[9.3736047745,47.566696167],"type":"Point"}
}