{
  "type": "Feature",
  "properties": {
    "iso:country":"CH",
    "sg:address":"Rue St-joseph 24",
    "sg:city":"Bulle",
    "sg:orig_category":"Herstellung von \u00d6fen U Brennern Sanit\u00e4r U Heizungsinstallation",
    "sg:phone":"+41 26 912 98 77",
    "sg:postcode":"1630",
    "sg:province":"Fribourg",
    "wof:name":"Michaud Claude",
    "wof:placetype":"venue"
},
  "geometry": {"coordinates":[7.0435791016,46.6151046753],"type":"Point"}
}