{
  "type": "Feature",
  "properties": {
    "iso:country":"CH",
    "sg:address":"Ferme De Jolimont 18",
    "sg:city":"Glovelier",
    "sg:classifiers":[
        {
            "category":"Restaurant",
            "type":"Food & Drink"
        }
    ],
    "sg:phone":"+41 32 426 57 21",
    "sg:postcode":"2855",
    "sg:province":"Jura",
    "wof:name":"Auberge Jolimont",
    "wof:placetype":"venue"
},
  "geometry": {"coordinates":[7.1992797852,47.3326377869],"type":"Point"}
}