{
  "type": "Feature",
  "properties": {
    "iso:country":"CH",
    "sg:address":"Via Simmen 100",
    "sg:city":"Minusio",
    "sg:orig_category":"Architektur U Ingenieurb\u00fcros Architekturb\u00fcros",
    "sg:phone":"+41 91 730 16 61",
    "sg:postcode":"6648",
    "sg:province":"Ticino",
    "wof:name":"Albrecht + Schnorf Architetti Sagl",
    "wof:placetype":"venue"
},
  "geometry": {"coordinates":[8.826918,46.177589],"type":"Point"}
}