{
  "type": "Feature",
  "properties": {
    "iso:country":"CH",
    "sg:address":"Viktoriastrasse 61",
    "sg:city":"Bern",
    "sg:orig_category":"Interessenvertretungen",
    "sg:phone":"+41 31 331 59 10",
    "sg:postcode":"3013",
    "sg:province":"Bern",
    "wof:name":"Rudolf Von Tavel-gedenkst\u00e4tte Stiftung Der Berner Freistudenten",
    "wof:placetype":"venue"
},
  "geometry": {"coordinates":[7.4534912109,46.9539527893],"type":"Point"}
}