{
  "type": "Feature",
  "properties": {
    "addr:full":"Industriestrasse West 21 H\u00e4gendorf Solothurn 4614",
    "addr:housenumber":"21",
    "addr:postcode":"4614",
    "addr:street":"Industriestrasse West;Solothurn",
    "iso:country":"CH",
    "sg:address":"Industriestrasse West 21",
    "sg:city":"H\u00e4gendorf",
    "sg:orig_category":"Blousons",
    "sg:phone":"+41 62 209 60 00",
    "sg:postcode":"4614",
    "sg:province":"Solothurn",
    "wof:name":"Textil-agentur Gehrig Ag",
    "wof:placetype":"venue"
},
  "geometry": {"coordinates":[7.833884,47.328899],"type":"Point"}
}