{
  "type": "Feature",
  "properties": {
    "iso:country":"CH",
    "sg:address":"Aprikosenstrasse 21",
    "sg:city":"Z\u00fcrich",
    "sg:orig_category":"Unternehmensberatung",
    "sg:phone":"+41 13212929",
    "sg:postcode":"8051",
    "sg:province":"Z\u00fcrich",
    "wof:name":"Mst-quality Ag",
    "wof:placetype":"venue"
},
  "geometry": {"coordinates":[8.5697479248,47.4065666199],"type":"Point"}
}