{
  "type": "Feature",
  "properties": {
    "iso:country":"CH",
    "sg:address":"Chalet Le D\u00e9serteur 1936 Verbier. Postfach",
    "sg:city":"Verbier",
    "sg:orig_category":"Fische and Fischprodukte Grosshandel Nahrungsmittel-Industrie: Rohstoffe",
    "sg:postcode":"1936",
    "sg:province":"Valais",
    "wof:name":"Sushi-switzerland S\u00e0rl Produits Frais, Sushis, Sashimis Etc.; Fabrication, Achat, Vente",
    "wof:placetype":"venue"
},
  "geometry": {"coordinates":[7.2229619026,46.0967292786],"type":"Point"}
}