{
  "type": "Feature",
  "properties": {
    "iso:country":"CH",
    "sg:address":"Wydenstrasse 5",
    "sg:city":"Birr-lupfig",
    "sg:orig_category":"Reiseb\u00fcros U Reiseveranstalter",
    "sg:postcode":"5242",
    "sg:province":"Aargau",
    "wof:name":"Rwt Round World Tours Gmbh",
    "wof:placetype":"venue"
},
  "geometry": {"coordinates":[8.2027254105,47.4361724854],"type":"Point"}
}