{
  "type": "Feature",
  "properties": {
    "iso:country":"CH",
    "sg:address":"Dorfstrasse 7",
    "sg:city":"Thundorf",
    "sg:orig_category":"Herstellung von keramischen Wand U Bodenfliesen U platten",
    "sg:phone":"+41 52 376 25 23",
    "sg:postcode":"8512",
    "sg:province":"Thurgau",
    "wof:name":"As Keramik Wand Und Bodenbel\u00e4ge S\u00fcrekli Alp",
    "wof:placetype":"venue"
},
  "geometry": {"coordinates":[8.9618616104,47.5467376709],"type":"Point"}
}