{
  "type": "Feature",
  "properties": {
    "iso:country":"CH",
    "sg:address":"3993",
    "sg:city":"Grengiols",
    "sg:classifiers":[
        {
            "category":"Insurance",
            "subcategory":"Insurance Agent",
            "type":"Services"
        }
    ],
    "sg:phone":"+41 27 927 23 49",
    "sg:postcode":"3993",
    "sg:province":"Valais",
    "sg:tags":[
        "versicherungsagenturen",
        "-broker"
    ],
    "wof:name":"Die Mobiliar Versicherungen & Vorsorge",
    "wof:placetype":"venue"
},
  "geometry": {"coordinates":[8.0929260254,46.3724136353],"type":"Point"}
}