{
  "type": "Feature",
  "properties": {
    "iso:country":"CH",
    "sg:address":"G\u00fcterstrasse 7",
    "sg:city":"Lostorf",
    "sg:orig_category":"Wirtschaftspr\u00fcfung, Steuerberatung U Treuhand",
    "sg:phone":"+41 62 298 02 10",
    "sg:postcode":"4654",
    "sg:province":"Solothurn",
    "wof:name":"De Ma Treuhand Deppeler Matthias",
    "wof:placetype":"venue"
},
  "geometry": {"coordinates":[7.9513378143,47.3773574829],"type":"Point"}
}