{
  "type": "Feature",
  "properties": {
    "iso:country":"CH",
    "sg:address":"Merkurstrasse 7",
    "sg:city":"Emmenbr\u00fccke",
    "sg:orig_category":"Grosshandel mit medizinischen U orthop\u00e4dischen Artikeln",
    "sg:phone":"+41 61 487 94 00",
    "sg:postcode":"6020",
    "sg:province":"Luzern",
    "wof:name":"Reha-sys Rehabilitations- Systeme Ag",
    "wof:placetype":"venue"
},
  "geometry": {"coordinates":[7.5505027771,47.5470237732],"type":"Point"}
}