{
  "type": "Feature",
  "properties": {
    "iso:country":"CH",
    "sg:address":"Eschenrain 26",
    "sg:city":"Grenchen",
    "sg:orig_category":"Sportvereine Turnen",
    "sg:phone":"+41 32 653 14 59",
    "sg:postcode":"2540",
    "sg:province":"Solothurn",
    "wof:name":"M\u00e4nnerturnverein Stv Grenchen",
    "wof:placetype":"venue"
},
  "geometry": {"coordinates":[7.3893489838,47.1866416931],"type":"Point"}
}