{
  "type": "Feature",
  "properties": {
    "iso:country":"CH",
    "sg:address":"Thunstrasse 49",
    "sg:city":"Bern",
    "sg:orig_category":"Arztpraxen",
    "sg:phone":"+41 31 351 27 43",
    "sg:postcode":"3005",
    "sg:province":"Bern",
    "wof:name":"Dr.med.rolf Imboden Spezialarzt Fmh",
    "wof:placetype":"venue"
},
  "geometry": {"coordinates":[7.457077,46.941113],"type":"Point"}
}