{
  "type": "Feature",
  "properties": {
    "iso:country":"CH",
    "sg:address":"Oberdorfstrasse 9",
    "sg:city":"Flaach",
    "sg:orig_category":"Bauschreinerei Gartenbau",
    "sg:phone":"+41 52 318 11 47",
    "sg:postcode":"8416",
    "sg:province":"Z\u00fcrich",
    "wof:name":"Kurt & Silvia Zimmermann",
    "wof:placetype":"venue"
},
  "geometry": {"coordinates":[8.612042,47.575279],"type":"Point"}
}