{
  "type": "Feature",
  "properties": {
    "iso:country":"CH",
    "sg:address":"Dassier Rue Jean- 11 1201 Gen\u00e8ve. Postfach",
    "sg:city":"Gen\u00e8ve",
    "sg:orig_category":"Religi\u00f6se Vereinigungen",
    "sg:postcode":"1201",
    "sg:province":"Gen\u00e8ve",
    "wof:name":"Association Protestante D'aide Technique Saint-gervais-philippeville",
    "wof:placetype":"venue"
},
  "geometry": {"coordinates":[6.1388502121,46.2087669373],"type":"Point"}
}