{
  "type": "Feature",
  "properties": {
    "iso:country":"CH",
    "sg:address":"B\u00fcndtenstrasse 6",
    "sg:city":"Egerkingen",
    "sg:classifiers":[
        {
            "category":"Insurance",
            "subcategory":"Insurance Agent",
            "type":"Services"
        }
    ],
    "sg:phone":"+41 800 808 080",
    "sg:postcode":"4622",
    "sg:province":"Solothurn",
    "sg:tags":[
        "versicherungsagenturen",
        "-broker"
    ],
    "wof:name":"Z\u00fcrich Versicherungen Agentur Christian Sulser",
    "wof:placetype":"venue"
},
  "geometry": {"coordinates":[7.7903590202,47.3208198547],"type":"Point"}
}