{
  "type": "Feature",
  "properties": {
    "iso:country":"CH",
    "sg:address":"Oberdierikonerstrasse 76 6030 Ebikon. Postfach 269",
    "sg:city":"Ebikon",
    "sg:orig_category":"Finanzierungsinstitutionen Wirtschaftspr\u00fcfung, Steuerberatung U Treuhand",
    "sg:phone":"+41 41 440 45 20",
    "sg:postcode":"6031",
    "sg:province":"Luzern",
    "wof:name":"Top Consulting, Lic. Oec. Hsg Keller Fritz",
    "wof:placetype":"venue"
},
  "geometry": {"coordinates":[8.3561630249,47.0873908997],"type":"Point"}
}