{
  "type": "Feature",
  "properties": {
    "iso:country":"CH",
    "sg:address":"Obere Wanne 495",
    "sg:city":"Birrwil",
    "sg:orig_category":"Non-Classified Establishments",
    "sg:postcode":"5708",
    "sg:province":"Aargau",
    "wof:name":"Lkc Landolfo-k\u00f6hler Commerce",
    "wof:placetype":"venue"
},
  "geometry": {"coordinates":[8.1966238022,47.2879371643],"type":"Point"}
}