{
  "type": "Feature",
  "properties": {
    "iso:country":"CH",
    "sg:address":"Avenue Du Mont-blanc 31",
    "sg:city":"Gland",
    "sg:orig_category":"Grosshandel mit Wein U Spirituosen",
    "sg:phone":"+41 22 354 25 00",
    "sg:postcode":"1196",
    "sg:province":"Vaud",
    "wof:name":"Boissons D'alessandro Sa Boissons La C\u00f4te",
    "wof:placetype":"venue"
},
  "geometry": {"coordinates":[6.2720861435,46.4159889221],"type":"Point"}
}