{
  "type": "Feature",
  "properties": {
    "iso:country":"CH",
    "sg:address":"Ottnerstrasse 77 4663 Aarburg. Postfach",
    "sg:city":"Aarburg",
    "sg:orig_category":"Herstellung von Konstruktionsteilen, Fertigbauteilen U Ausbauelementen aus Holz",
    "sg:postcode":"4663",
    "sg:province":"Aargau",
    "wof:name":"Bugmann Viktor",
    "wof:placetype":"venue"
},
  "geometry": {"coordinates":[7.9043588638,47.3294410706],"type":"Point"}
}