{
  "type": "Feature",
  "properties": {
    "iso:country":"CH",
    "sg:address":"R\u00fctligasse 1",
    "sg:city":"Luzern",
    "sg:orig_category":"Erbringung von Dienstleistungen f\u00fcr Unternehmen",
    "sg:phone":"+41 41 249 43 60",
    "sg:postcode":"6003",
    "sg:province":"Luzern",
    "wof:name":"Infra Management Ag",
    "wof:placetype":"venue"
},
  "geometry": {"coordinates":[8.3025865555,47.0501480103],"type":"Point"}
}