{
  "type": "Feature",
  "properties": {
    "iso:country":"CH",
    "sg:address":"Route De Florissant 119",
    "sg:city":"Conches",
    "sg:orig_category":"Sprachschulen",
    "sg:phone":"+41 22 311 32 50",
    "sg:postcode":"1231",
    "sg:province":"Gen\u00e8ve",
    "wof:name":"Ecole De Perfectionnement De Fran\u00e7ais,monsieur Ak\u00e9la Golay",
    "wof:placetype":"venue"
},
  "geometry": {"coordinates":[6.1685109138,46.1886138916],"type":"Point"}
}