{
  "type": "Feature",
  "properties": {
    "addr:full":"Vallombreuse Av. De La 109 1008 Prilly. Postfach Prilly Vaud 1008",
    "addr:housenumber":"109",
    "addr:postcode":"1008 prilly. postfach prilly;1008",
    "addr:street":"Vallombreuse Av. De La",
    "iso:country":"CH",
    "sg:address":"Vallombreuse Av. De La 109 1008 Prilly. Postfach",
    "sg:city":"Prilly",
    "sg:orig_category":"Architektur U Ingenieurb\u00fcros",
    "sg:phone":"+41 21 646 13 24",
    "sg:postcode":"1008",
    "sg:province":"Vaud",
    "wof:name":"Open Net S\u00e0rl Nouvelles Technologies De L'information; Services, Consulting Et Gestion De Projets",
    "wof:placetype":"venue"
},
  "geometry": {"coordinates":[6.608616,46.54055],"type":"Point"}
}