{
  "type": "Feature",
  "properties": {
    "iso:country":"CH",
    "sg:address":"Z\u00fcrcherstrasse 17 8173 Neerach. Postfach",
    "sg:city":"Neerach",
    "sg:orig_category":"Detailhandel mit Bekleidung",
    "sg:postcode":"8173",
    "sg:province":"Z\u00fcrich",
    "wof:name":"Mollig & Chic Gmbh",
    "wof:placetype":"venue"
},
  "geometry": {"coordinates":[8.476822,47.511887],"type":"Point"}
}