{
  "type": "Feature",
  "properties": {
    "iso:country":"CH",
    "sg:address":"Ahornstrasse 2",
    "sg:city":"Fislisbach",
    "sg:orig_category":"Detailhandel mit Waren verschiedener Art, Hauptrichtung Nahrungsmittel",
    "sg:phone":"+41 26 477 11 75",
    "sg:postcode":"5442",
    "sg:province":"Aargau",
    "wof:name":"Yvonne Mettraux Alimentation",
    "wof:placetype":"venue"
},
  "geometry": {"coordinates":[7.0673542023,46.7684822083],"type":"Point"}
}