{
  "type": "Feature",
  "properties": {
    "iso:country":"CH",
    "sg:address":"Lengghalde 6 8008 Z\u00fcrich. Postfach",
    "sg:city":"Z\u00fcrich",
    "sg:orig_category":"Interessenvertretungen",
    "sg:phone":"+41 17611528",
    "sg:postcode":"8001",
    "sg:province":"Z\u00fcrich",
    "wof:name":"Stiftung Schule T\u00e4gerst",
    "wof:placetype":"venue"
},
  "geometry": {"coordinates":[8.4395618439,47.2759475708],"type":"Point"}
}