{
  "type": "Feature",
  "properties": {
    "iso:country":"CH",
    "sg:address":"2610",
    "sg:city":"St-imier",
    "sg:orig_category":"Herstellung U Zusammensetzung von Uhren Herstellung U Zusammensetzung von Uhrwerken",
    "sg:phone":"+41 91 640 30 10",
    "sg:postcode":"2610",
    "sg:province":"Bern",
    "wof:name":"Swatch Group Watch Assembly Sa",
    "wof:placetype":"venue"
},
  "geometry": {"coordinates":[9.0074520111,45.8611679077],"type":"Point"}
}