{
  "type": "Feature",
  "properties": {
    "iso:country":"CH",
    "sg:address":"Rietbachstrasse 7",
    "sg:city":"N\u00fcrensdorf",
    "sg:orig_category":"Herstellung von Elektrizit\u00e4tsverteilungs U schalteinrichtungen",
    "sg:phone":"+41 19324859",
    "sg:postcode":"8309",
    "sg:province":"Z\u00fcrich",
    "wof:name":"Moser R. Ag",
    "wof:placetype":"venue"
},
  "geometry": {"coordinates":[8.7902460098,47.3177566528],"type":"Point"}
}