{
  "type": "Feature",
  "properties": {
    "iso:country":"CH",
    "sg:address":"Via Centrala 1",
    "sg:city":"Ilanz",
    "sg:orig_category":"Detailhandel mit Uhren U Schmuck Fachdetailhandel in Verkaufsr\u00e4umen",
    "sg:phone":"+41 19307827",
    "sg:postcode":"7130",
    "sg:province":"Graubunden",
    "wof:name":"Caveng, Uhren Und Schmuck",
    "wof:placetype":"venue"
},
  "geometry": {"coordinates":[8.7985029221,47.3268547058],"type":"Point"}
}