{
  "type": "Feature",
  "properties": {
    "iso:country":"CH",
    "sg:address":"Langackerstrasse 1",
    "sg:city":"Dielsdorf",
    "sg:orig_category":"G\u00fcterbef\u00f6rderung im Strassenverkehr",
    "sg:phone":"+41 18530330",
    "sg:postcode":"8157",
    "sg:province":"Z\u00fcrich",
    "wof:name":"Aschwanden Felix",
    "wof:placetype":"venue"
},
  "geometry": {"coordinates":[8.4561548233,47.4779319763],"type":"Point"}
}