{
  "type": "Feature",
  "properties": {
    "iso:country":"CH",
    "sg:address":"Z\u00fcrcherstrasse 5",
    "sg:city":"Tuggen",
    "sg:orig_category":"Nationale Postdienste",
    "sg:phone":"+41 55 445 11 05",
    "sg:postcode":"8856",
    "sg:province":"Schwyz",
    "wof:name":"Die Schweizerische Post",
    "wof:placetype":"venue"
},
  "geometry": {"coordinates":[8.9415626526,47.2028923035],"type":"Point"}
}