{
  "type": "Feature",
  "properties": {
    "iso:country":"CH",
    "sg:address":"Gartenstrasse 2",
    "sg:city":"Zug",
    "sg:orig_category":"Detailhandel mit Metallwaren, Anstrichmitteln, Glaswaren, Bau U Heimwerkerbedarf",
    "sg:phone":"+41 71 244 81 12",
    "sg:postcode":"6300",
    "sg:province":"Zug",
    "wof:name":"Insa Trading Gmbh",
    "wof:placetype":"venue"
},
  "geometry": {"coordinates":[9.3848905563,47.4366531372],"type":"Point"}
}