{
  "type": "Feature",
  "properties": {
    "iso:country":"CH",
    "sg:address":"Eggh\u00f6lzlistrasse 41",
    "sg:city":"Bern",
    "sg:orig_category":"Reiseb\u00fcros",
    "sg:phone":"+41 31 352 86 76",
    "sg:postcode":"3006",
    "sg:province":"Bern",
    "wof:name":"Lorenzo Sedelli Reiseb\u00fcro",
    "wof:placetype":"venue"
},
  "geometry": {"coordinates":[7.473361969,46.9360122681],"type":"Point"}
}