{
  "type": "Feature",
  "properties": {
    "iso:country":"CH",
    "sg:address":"Pr\u00e9-olivier",
    "sg:city":"Chavannes-des-bois",
    "sg:orig_category":"Gesundheitswesen",
    "sg:phone":"+41 22 779 28 42",
    "sg:postcode":"1290",
    "sg:province":"Gen\u00e8ve",
    "wof:name":"Association Du Centre De Recherche & D'application En Th\u00e9rapies Naturelles & M\u00e9decines Douces",
    "wof:placetype":"venue"
},
  "geometry": {"coordinates":[6.1313419342,46.313369751],"type":"Point"}
}