{
  "type": "Feature",
  "properties": {
    "iso:country":"CH",
    "sg:address":"Lyon Rue De 64 1203 Gen\u00e8ve. Postfach",
    "sg:city":"Gen\u00e8ve",
    "sg:orig_category":"Softwareentwicklung U beratung",
    "sg:postcode":"1203",
    "sg:province":"Gen\u00e8ve",
    "wof:name":"Bitmap, Ecuvillon Philippe Prestations Relatives Au Traitement De L'information Num\u00e9rique",
    "wof:placetype":"venue"
},
  "geometry": {"coordinates":[6.142701149,46.2083587646],"type":"Point"}
}