{
  "type": "Feature",
  "properties": {
    "iso:country":"CH",
    "sg:address":"Aeschbach 513",
    "sg:city":"Walzenhausen",
    "sg:orig_category":"Grosshandel mit Eisenwaren sowie Installationsbedarf f\u00fcr Gas, Wasser U Heizung Herstellung von k\u00e4lte",
    "sg:phone":"+41 71 888 07 71",
    "sg:postcode":"9428",
    "sg:province":"Appenzell Ausserrhoden",
    "wof:name":"Marty Hugo Vertrieb Heiztechnischer Produkte",
    "wof:placetype":"venue"
},
  "geometry": {"coordinates":[9.6187829971,47.4466972351],"type":"Point"}
}