{
  "type": "Feature",
  "properties": {
    "iso:country":"CH",
    "sg:address":"Hirschengraben 19",
    "sg:city":"Luzern",
    "sg:orig_category":"Dienstleistungen von Beteiligungsgesellschaften",
    "sg:phone":"+41 41 210 85 48",
    "sg:postcode":"6003",
    "sg:province":"Luzern",
    "wof:name":"Petra Handels Und Verwaltungs-ag Luzern",
    "wof:placetype":"venue"
},
  "geometry": {"coordinates":[8.3028335571,47.0488433838],"type":"Point"}
}