{
  "type": "Feature",
  "properties": {
    "iso:country":"CH",
    "sg:address":"Langgasse 26a",
    "sg:city":"Baar",
    "sg:orig_category":"Herstellung von Teppichen",
    "sg:phone":"+41 41 760 17 33",
    "sg:postcode":"6340",
    "sg:province":"Zug",
    "wof:name":"Lottenbach Marcel",
    "wof:placetype":"venue"
},
  "geometry": {"coordinates":[8.5330400467,47.1963500977],"type":"Point"}
}