{
  "type": "Feature",
  "properties": {
    "iso:country":"CH",
    "sg:address":"R\u00fctihofstrasse 21",
    "sg:city":"Z\u00fcrich",
    "sg:orig_category":"Detailhandel mit Fahrr\u00e4dern Handel mit Motorr\u00e4dern, Teilen U Zubeh\u00f6r Instandhaltung U Reparatur von ",
    "sg:phone":"+41 13410293",
    "sg:postcode":"8049",
    "sg:province":"Z\u00fcrich",
    "wof:name":"Jomes Moise Ioan",
    "wof:placetype":"venue"
},
  "geometry": {"coordinates":[8.4793901443,47.4141387939],"type":"Point"}
}