{
  "type": "Feature",
  "properties": {
    "iso:country":"CH",
    "sg:address":"Steineloh",
    "sg:city":"Frasnacht",
    "sg:classifiers":[
        {
            "category":"Restaurant",
            "type":"Food & Drink"
        }
    ],
    "sg:phone":"+41 71 761 11 32",
    "sg:postcode":"9320",
    "sg:province":"Thurgau",
    "wof:name":"Restaurant Sternen",
    "wof:placetype":"venue"
},
  "geometry": {"coordinates":[9.5680961609,47.3239212036],"type":"Point"}
}