{
  "type": "Feature",
  "properties": {
    "iso:country":"CH",
    "sg:address":"Maurstrasse 33",
    "sg:city":"F\u00e4llanden",
    "sg:orig_category":"Jugendherbergen U H\u00fctten",
    "sg:phone":"+41 18253144",
    "sg:postcode":"8117",
    "sg:province":"Z\u00fcrich",
    "wof:name":"Jugendherberge Sjh",
    "wof:placetype":"venue"
},
  "geometry": {"coordinates":[8.6532964706,47.3608474731],"type":"Point"}
}