{
  "type": "Feature",
  "properties": {
    "iso:country":"CH",
    "sg:address":"Lommiserstrasse 1",
    "sg:city":"W\u00e4ngi",
    "sg:classifiers":[
        {
            "category":"Restaurant",
            "type":"Food & Drink"
        }
    ],
    "sg:phone":"+41 79 336 44 33",
    "sg:postcode":"9545",
    "sg:province":"Thurgau",
    "wof:name":"Gasthaus Linde",
    "wof:placetype":"venue"
},
  "geometry": {"coordinates":[8.9548892975,47.5010108948],"type":"Point"}
}