{
  "type": "Feature",
  "properties": {
    "iso:country":"CH",
    "sg:address":"Sternenmattstrasse 1",
    "sg:city":"Walchwil",
    "sg:orig_category":"Fussreflexzonenmassage",
    "sg:phone":"+41 41 758 16 01",
    "sg:postcode":"6318",
    "sg:province":"Zug",
    "wof:name":"Susi H\u00fcrlimann Fussreflexzonenmassage",
    "wof:placetype":"venue"
},
  "geometry": {"coordinates":[8.5129575729,47.1009025574],"type":"Point"}
}