{
  "type": "Feature",
  "properties": {
    "iso:country":"CH",
    "sg:address":"Alte Landstrasse 2",
    "sg:city":"Menzingen",
    "sg:orig_category":"Bezirks, Sekundar, Realschulen, Oberstufe der Primarschulen Primarschulen",
    "sg:phone":"+41 41 755 01 18",
    "sg:postcode":"6313",
    "sg:province":"Zug",
    "wof:name":"Schulhaus Dorf",
    "wof:placetype":"venue"
},
  "geometry": {"coordinates":[8.590033,47.177963],"type":"Point"}
}