{
  "type": "Feature",
  "properties": {
    "iso:country":"CH",
    "sg:address":"Niederwiesstrasse 1a 8730 Uznach. Postfach",
    "sg:city":"Uznach",
    "sg:orig_category":"Tierarztpraxis",
    "sg:phone":"+41 55 280 41 14",
    "sg:postcode":"8730",
    "sg:province":"St. Gallen",
    "wof:name":"Dres Med.vet. R.& B. Pool Tier\u00e4rzte",
    "wof:placetype":"venue"
},
  "geometry": {"coordinates":[8.9908943176,47.2237854004],"type":"Point"}
}