{
  "type": "Feature",
  "properties": {
    "iso:country":"CH",
    "sg:address":"Teichstrasse 86 4106 Therwil. Postfach",
    "sg:city":"Therwil",
    "sg:orig_category":"Softwareentwicklung U beratung",
    "sg:postcode":"4106",
    "sg:province":"Basel-Landschaft",
    "wof:name":"M & S Informatik-ausbildung, Mulas & Scheuble",
    "wof:placetype":"venue"
},
  "geometry": {"coordinates":[7.5478281975,47.5014305115],"type":"Point"}
}