{
  "type": "Feature",
  "properties": {
    "iso:country":"CH",
    "sg:address":"Bruggtobel",
    "sg:city":"Trogen",
    "sg:orig_category":"Bauspenglerei Dachdeckerei",
    "sg:phone":"+41 71 344 13 34",
    "sg:postcode":"9043",
    "sg:province":"Appenzell Ausserrhoden",
    "wof:name":"Hansruedi Eugster Spenglerei & Bedachungen",
    "wof:placetype":"venue"
},
  "geometry": {"coordinates":[9.48951,47.397064],"type":"Point"}
}