{
  "type": "Feature",
  "properties": {
    "iso:country":"CH",
    "sg:address":"Via Livio 10",
    "sg:city":"Chiasso",
    "sg:orig_category":"Detailhandel mit Fleisch U Fleischwaren Grosshandel mit Fleisch U Fleischwaren",
    "sg:phone":"+41 91 695 27 40",
    "sg:postcode":"6830",
    "sg:province":"Ticino",
    "wof:name":"Agrofood Sa",
    "wof:placetype":"venue"
},
  "geometry": {"coordinates":[9.0289382935,45.8337287903],"type":"Point"}
}