{
  "type": "Feature",
  "properties": {
    "iso:country":"CH",
    "sg:address":"Dersbach 6331 H\u00fcnenberg. Postfach",
    "sg:city":"Cham",
    "sg:orig_category":"Non-Classified Establishments",
    "sg:postcode":"6330",
    "sg:province":"Zug",
    "wof:name":"Christen Alois Gartenbau Gartenbau, Garten- U. Gr\u00fcnanlagen; Beratung, Planung U. Ausf\u00fchrung. Gartenpflege U. Unterhalt",
    "wof:placetype":"venue"
},
  "geometry": {"coordinates":[8.4540147781,47.1659812927],"type":"Point"}
}