{
  "type": "Feature",
  "properties": {
    "addr:full":"Cours De Rive 13 Gen\u00e8ve Gen\u00e8ve 1204",
    "addr:housenumber":"13",
    "addr:postcode":"1204",
    "addr:street":"Cours De Rive",
    "iso:country":"CH",
    "sg:address":"Cours De Rive 13",
    "sg:city":"Gen\u00e8ve",
    "sg:orig_category":"Detailhandel mit Bekleidung Detailhandel mit Schuhen",
    "sg:phone":"+41 55 211 06 11",
    "sg:postcode":"1204",
    "sg:province":"Gen\u00e8ve",
    "wof:name":"Boutiuqe Scream Fashion & Shoes",
    "wof:placetype":"venue"
},
  "geometry": {"coordinates":[8.816399,47.225761],"type":"Point"}
}