{
  "type": "Feature",
  "properties": {
    "iso:country":"CH",
    "sg:address":"Wolfsackerstrasse 1",
    "sg:city":"Lenzburg",
    "sg:orig_category":"Public-Relations-Agenturen",
    "sg:phone":"+41 62 888 81 10",
    "sg:postcode":"5600",
    "sg:province":"Aargau",
    "wof:name":"B\u00fcrgi & Partner Ag",
    "wof:placetype":"venue"
},
  "geometry": {"coordinates":[8.1734724045,47.392364502],"type":"Point"}
}