{
  "type": "Feature",
  "properties": {
    "iso:country":"CH",
    "sg:address":"Seestrasse 185",
    "sg:city":"St\u00e4fa",
    "sg:orig_category":"Herstellung von Maschinen f\u00fcr die Nahrungsmittel, Getr\u00e4nkeherstellung U die Tabakverarbeitung Mechan",
    "sg:phone":"+41 52 242 31 50",
    "sg:postcode":"8712",
    "sg:province":"Z\u00fcrich",
    "wof:name":"Mechanik + Design, Etzensperger Hk.",
    "wof:placetype":"venue"
},
  "geometry": {"coordinates":[8.7716197968,47.5080108643],"type":"Point"}
}