{
  "type": "Feature",
  "properties": {
    "iso:country":"CH",
    "sg:address":"Albulastrasse 4a",
    "sg:city":"Schaffhausen",
    "sg:orig_category":"Wirtschaftspr\u00fcfung, Steuerberatung U Treuhand",
    "sg:postcode":"8200",
    "sg:province":"Schaffhausen",
    "wof:name":"Stoll Treuhand Ag",
    "wof:placetype":"venue"
},
  "geometry": {"coordinates":[8.650472641,47.6985473633],"type":"Point"}
}