{
  "type": "Feature",
  "properties": {
    "addr:full":"G\u00e4rtli Schangnau Bern 6197",
    "addr:postcode":"6197",
    "iso:country":"CH",
    "sg:address":"G\u00e4rtli",
    "sg:city":"Schangnau",
    "sg:orig_category":"Darlehenskassen U Raiffeisenbanken",
    "sg:phone":"+41 61 735 91 00",
    "sg:postcode":"6197",
    "sg:province":"Bern",
    "wof:name":"Raiffeisenbank Oberes Leimental",
    "wof:placetype":"venue"
},
  "geometry": {"coordinates":[7.516951,47.475708],"type":"Point"}
}