{
  "type": "Feature",
  "properties": {
    "iso:country":"CH",
    "sg:address":"Seefeldstrasse 249",
    "sg:city":"Z\u00fcrich",
    "sg:orig_category":"Softwareentwicklung U beratung",
    "sg:phone":"+41 13804770",
    "sg:postcode":"8008",
    "sg:province":"Z\u00fcrich",
    "wof:name":"Fbc Frederik Bugglin Consulting",
    "wof:placetype":"venue"
},
  "geometry": {"coordinates":[8.5625162125,47.3503799438],"type":"Point"}
}