{
  "type": "Feature",
  "properties": {
    "iso:country":"CH",
    "sg:address":"Route De Moncor 2",
    "sg:city":"Villars-sur-gl\u00e2ne",
    "sg:orig_category":"Enamel Badges",
    "sg:phone":"+41 26 402 22 00",
    "sg:postcode":"1752",
    "sg:province":"Fribourg",
    "wof:name":"Symbolhaus Ag",
    "wof:placetype":"venue"
},
  "geometry": {"coordinates":[7.126728,46.798557],"type":"Point"}
}