{
  "type": "Feature",
  "properties": {
    "iso:country":"CH",
    "sg:address":"R\u00f6hrliberg 18",
    "sg:city":"Cham",
    "sg:orig_category":"Verkehrsverb\u00e4nde",
    "sg:phone":"+41 41 780 88 38",
    "sg:postcode":"6330",
    "sg:province":"Zug",
    "wof:name":"Verkehrs-club Der Schweiz Vcs Sektion Zug",
    "wof:placetype":"venue"
},
  "geometry": {"coordinates":[8.4525651932,47.1863441467],"type":"Point"}
}