{
  "type": "Feature",
  "properties": {
    "iso:country":"CH",
    "sg:address":"Avenue Tissot 2bis",
    "sg:city":"Lausanne",
    "sg:orig_category":"Werbevermittlung Werbung",
    "sg:phone":"+41 21 312 29 50",
    "sg:postcode":"1006",
    "sg:province":"Vaud",
    "wof:name":"Studio P\u00e9russet Sa",
    "wof:placetype":"venue"
},
  "geometry": {"coordinates":[6.6335511208,46.5159950256],"type":"Point"}
}