{
  "type": "Feature",
  "properties": {
    "iso:country":"CH",
    "sg:address":"Chemin De Salette 8a",
    "sg:city":"Crissier",
    "sg:orig_category":"Betrieb von Taxis",
    "sg:phone":"+41 21 634 17 61",
    "sg:postcode":"1023",
    "sg:province":"Vaud",
    "wof:name":"Jean Scherer Taxi",
    "wof:placetype":"venue"
},
  "geometry": {"coordinates":[6.58239,46.553337],"type":"Point"}
}