{
  "type": "Feature",
  "properties": {
    "iso:country":"CH",
    "sg:address":"Schwyzerstrasse 23",
    "sg:city":"Richterswil",
    "sg:orig_category":"Mit dem Versicherungsgewerbe verbundene T\u00e4tigkeiten",
    "sg:postcode":"8805",
    "sg:province":"Z\u00fcrich",
    "wof:name":"Baur Rebekka Consulting Rbc",
    "wof:placetype":"venue"
},
  "geometry": {"coordinates":[8.709318161,47.2032623291],"type":"Point"}
}