{
  "type": "Feature",
  "properties": {
    "iso:country":"CH",
    "sg:address":"4812",
    "sg:city":"M\u00fchlethal",
    "sg:orig_category":"Sportvereine Sch\u00fctzen",
    "sg:phone":"+41 62 293 52 29",
    "sg:postcode":"4812",
    "sg:province":"Aargau",
    "wof:name":"Feldsch\u00fctzengesellschaft",
    "wof:placetype":"venue"
},
  "geometry": {"coordinates":[7.9802799225,47.3040084839],"type":"Point"}
}