{
  "type": "Feature",
  "properties": {
    "iso:country":"CH",
    "sg:address":"B\u00e4lliz 73a.",
    "sg:city":"Thun",
    "sg:orig_category":"Non-Classified Establishments",
    "sg:postcode":"3600",
    "sg:province":"Bern",
    "wof:name":"Schlatter",
    "wof:placetype":"venue"
},
  "geometry": {"coordinates":[7.6301932335,46.7573165894],"type":"Point"}
}