{
  "type": "Feature",
  "properties": {
    "iso:country":"CH",
    "sg:address":"Seegartenstrasse 2 8008 Z\u00fcrich. Postfach",
    "sg:city":"Z\u00fcrich",
    "sg:orig_category":"Unclassifiable Establishments",
    "sg:postcode":"8001",
    "sg:province":"Z\u00fcrich",
    "wof:name":"Chemolio Holding Ag",
    "wof:placetype":"venue"
},
  "geometry": {"coordinates":[8.5480899811,47.3612442017],"type":"Point"}
}