{
  "type": "Feature",
  "properties": {
    "iso:country":"CH",
    "sg:address":"H\u00fcttenweg 15",
    "sg:city":"Basadingen",
    "sg:orig_category":"Fotografische Ateliers Fotografisches Gewerbe U fotografische Laboratorien",
    "sg:phone":"+41 52 657 41 87",
    "sg:postcode":"8254",
    "sg:province":"Thurgau",
    "wof:name":"Jb Foto Jacqueline Berther",
    "wof:placetype":"venue"
},
  "geometry": {"coordinates":[8.7466859818,47.6707496643],"type":"Point"}
}