{
  "type": "Feature",
  "properties": {
    "iso:country":"CH",
    "sg:address":"Cadepiano Via 6917 Barbengo. Postfach",
    "sg:city":"Barbengo",
    "sg:orig_category":"Grosshandel mit sonstigen Gebrauchs U Verbrauchsg\u00fctern",
    "sg:postcode":"6917",
    "sg:province":"Ticino",
    "wof:name":"Swizzle Gmbh",
    "wof:placetype":"venue"
},
  "geometry": {"coordinates":[8.8590669632,47.6645317078],"type":"Point"}
}