{
  "type": "Feature",
  "properties": {
    "iso:country":"CH",
    "sg:address":"3063 Ittigen. Postfach",
    "sg:city":"Ittigen",
    "sg:orig_category":"Sportvereine Ballsport Tennis",
    "sg:phone":"+41 31 859 56 25",
    "sg:postcode":"3063",
    "sg:province":"Bern",
    "wof:name":"Tennisclub Ittingen",
    "wof:placetype":"venue"
},
  "geometry": {"coordinates":[7.4793901443,46.9816894531],"type":"Point"}
}