{
  "type": "Feature",
  "properties": {
    "iso:country":"CH",
    "sg:address":"Avenir Rue De L' 19",
    "sg:city":"Bassecourt",
    "sg:orig_category":"Reiseb\u00fcros U Reiseveranstalter",
    "sg:postcode":"2854",
    "sg:province":"Jura",
    "wof:name":"Tam Tam Travel, Madame Meyer",
    "wof:placetype":"venue"
},
  "geometry": {"coordinates":[-72.4746627808,45.8789253235],"type":"Point"}
}