{
  "type": "Feature",
  "properties": {
    "iso:country":"CH",
    "sg:address":"Alexanderstrasse 16",
    "sg:city":"Chur",
    "sg:orig_category":"Architektur U Ingenieurb\u00fcros",
    "sg:postcode":"7000",
    "sg:province":"Graubunden",
    "wof:name":"Heer A. Dipl. Ing. Eth",
    "wof:placetype":"venue"
},
  "geometry": {"coordinates":[9.531555,46.853073],"type":"Point"}
}