{
  "type": "Feature",
  "properties": {
    "iso:country":"CH",
    "sg:address":"Baud-bovy Passage Daniel 10 1205 Gen\u00e8ve. Postfach",
    "sg:city":"Gen\u00e8ve",
    "sg:orig_category":"Herstellung von optischen U fotografischen Ger\u00e4ten",
    "sg:phone":"+41 22 329 15 10",
    "sg:postcode":"1205",
    "sg:province":"Gen\u00e8ve",
    "wof:name":"Daniel K\u00fcnzi",
    "wof:placetype":"venue"
},
  "geometry": {"coordinates":[6.1378688812,46.195602417],"type":"Point"}
}