{
  "type": "Feature",
  "properties": {
    "iso:country":"CH",
    "sg:address":"Witellikerstrasse 50",
    "sg:city":"Z\u00fcrich",
    "sg:orig_category":"Kosmetikinstitute",
    "sg:phone":"+41 14229455",
    "sg:postcode":"8032",
    "sg:province":"Z\u00fcrich",
    "wof:name":"Doris Baumgartner Kosmetikinstitut",
    "wof:placetype":"venue"
},
  "geometry": {"coordinates":[8.5770273209,47.3504638672],"type":"Point"}
}