{
  "type": "Feature",
  "properties": {
    "addr:full":"In Vigana 51 Camorino Ticino 6528",
    "addr:housenumber":"51",
    "addr:postcode":"6528",
    "iso:country":"CH",
    "sg:address":"In Vigana 51",
    "sg:city":"Camorino",
    "sg:classifiers":[
        {
            "category":"Structure",
            "subcategory":"Office Building",
            "type":"Public Place"
        }
    ],
    "sg:phone":"+41 22 366 38 28",
    "sg:postcode":"6528",
    "sg:province":"Ticino",
    "sg:tags":[
        "equipment",
        "alarm",
        "installation",
        "system"
    ],
    "wof:name":"Habitat Protection Matelec Sa",
    "wof:placetype":"venue"
},
  "geometry": {"coordinates":[6.219692,46.453678],"type":"Point"}
}