{
  "type": "Feature",
  "properties": {
    "iso:country":"CH",
    "sg:address":"Oristalstrasse 22b",
    "sg:city":"Liestal",
    "sg:orig_category":"Herstellung von sonstigen Maschinen f\u00fcr unspezifische Verwendung",
    "sg:postcode":"4410",
    "sg:province":"Basel-Landschaft",
    "wof:name":"Alro Kohout",
    "wof:placetype":"venue"
},
  "geometry": {"coordinates":[7.7309341431,47.481716156],"type":"Point"}
}