{
  "type": "Feature",
  "properties": {
    "iso:country":"CH",
    "sg:address":"Stockackerstrasse 500",
    "sg:city":"Kestenholz",
    "sg:orig_category":"Kauf U Verkauf von Immobilien auf eigene Rechnung",
    "sg:postcode":"4703",
    "sg:province":"Solothurn",
    "wof:name":"Huf Franz",
    "wof:placetype":"venue"
},
  "geometry": {"coordinates":[7.7468500137,47.2747383118],"type":"Point"}
}