{
  "type": "Feature",
  "properties": {
    "iso:country":"CH",
    "sg:address":"Niesenberg Oberniesenberg",
    "sg:city":"Kallern",
    "sg:orig_category":"Bauschreinerei",
    "sg:phone":"+41 56 666 11 40",
    "sg:postcode":"5625",
    "sg:province":"Aargau",
    "wof:name":"Siegmund Keller Schreinerei",
    "wof:placetype":"venue"
},
  "geometry": {"coordinates":[8.279343,47.301674],"type":"Point"}
}