{
  "type": "Feature",
  "properties": {
    "iso:country":"CH",
    "sg:address":"Bahnhofstrasse 25",
    "sg:city":"Affeltrangen",
    "sg:orig_category":"Herstellung von Schuhen",
    "sg:phone":"+41 71 917 22 19",
    "sg:postcode":"9556",
    "sg:province":"Thurgau",
    "wof:name":"Heuberger Willy",
    "wof:placetype":"venue"
},
  "geometry": {"coordinates":[9.0317678452,47.5235748291],"type":"Point"}
}