{
  "type": "Feature",
  "properties": {
    "iso:country":"CH",
    "sg:address":"Solistrasse 25",
    "sg:city":"B\u00fclach",
    "sg:orig_category":"Druckguss-Werke",
    "sg:phone":"+41 18636363",
    "sg:postcode":"8180",
    "sg:province":"Z\u00fcrich",
    "wof:name":"B\u00fclachguss Giesserei Ag",
    "wof:placetype":"venue"
},
  "geometry": {"coordinates":[8.5386142731,47.5260543823],"type":"Point"}
}