{
  "type": "Feature",
  "properties": {
    "iso:country":"CH",
    "sg:address":"Stade Rue Du 16",
    "sg:city":"Sion",
    "sg:orig_category":"Vermietung U Verpachtung von eigenen Immobilien",
    "sg:postcode":"1950",
    "sg:province":"Valais",
    "wof:name":"St\u00f6ckmatten Immobilien Ag",
    "wof:placetype":"venue"
},
  "geometry": {"coordinates":[7.5253500938,47.5052108765],"type":"Point"}
}