{
  "type": "Feature",
  "properties": {
    "iso:country":"CH",
    "sg:address":"1905",
    "sg:city":"Dor\u00e9naz",
    "sg:orig_category":"Vorschulen, Kinderg\u00e4rten",
    "sg:postcode":"1905",
    "sg:province":"Valais",
    "wof:name":"Ecole Enfantine",
    "wof:placetype":"venue"
},
  "geometry": {"coordinates":[7.0422902107,46.1487998962],"type":"Point"}
}