{
  "type": "Feature",
  "properties": {
    "iso:country":"CH",
    "sg:address":"Ormeaux Rue Des 4 1201 Gen\u00e8ve. Postfach",
    "sg:city":"Gen\u00e8ve",
    "sg:orig_category":"Rechtsberatung",
    "sg:phone":"+41 22 731 84 10",
    "sg:postcode":"1201",
    "sg:province":"Gen\u00e8ve",
    "wof:name":"D. & Co S\u00e0rl Licences, Promotion, D\u00e9p\u00f4t De Marques Etc",
    "wof:placetype":"venue"
},
  "geometry": {"coordinates":[6.1374988556,46.2060775757],"type":"Point"}
}