{
  "type": "Feature",
  "properties": {
    "iso:country":"CH",
    "sg:address":"Les Places 38 Eco Centre",
    "sg:city":"Glovelier",
    "sg:orig_category":"Korrespondenz U Nachrichtenb\u00fcros, selbst\u00e4ndige Journalisten",
    "sg:phone":"+41 32 426 82 82",
    "sg:postcode":"2855",
    "sg:province":"Jura",
    "wof:name":"Api-media, Monti Jean-philippe",
    "wof:placetype":"venue"
},
  "geometry": {"coordinates":[7.1992797852,47.3326377869],"type":"Point"}
}