{
  "type": "Feature",
  "properties": {
    "addr:full":"Hardturmstr.181 Z\u00fcrich Z\u00fcrich 8010",
    "addr:postcode":"8010",
    "iso:country":"CH",
    "sg:address":"Hardturmstr.181",
    "sg:city":"Z\u00fcrich",
    "sg:classifiers":[
        {
            "category":"Professional",
            "subcategory":"Advertising",
            "type":"Services"
        }
    ],
    "sg:phone":"+41 4112791711",
    "sg:postcode":"8010",
    "sg:province":"Z\u00fcrich",
    "sg:tags":[
        "marketing",
        "medium",
        "communication"
    ],
    "wof:name":"Moneyline Telerate (switzerland) Gmbh",
    "wof:placetype":"venue"
},
  "geometry": {"coordinates":[8.510674,47.393551],"type":"Point"}
}