{
  "type": "Feature",
  "properties": {
    "iso:country":"CH",
    "sg:address":"1958",
    "sg:city":"St-l\u00e9onard",
    "sg:classifiers":[
        {
            "category":"Restaurant",
            "type":"Food & Drink"
        }
    ],
    "sg:phone":"+41 27 203 22 88",
    "sg:postcode":"1958",
    "sg:province":"Valais",
    "wof:name":"Caf\u00e9 Place",
    "wof:placetype":"venue"
},
  "geometry": {"coordinates":[7.4179301262,46.2533912659],"type":"Point"}
}