{
  "type": "Feature",
  "properties": {
    "iso:country":"CH",
    "sg:address":"Schachenallee 29",
    "sg:city":"Aarau",
    "sg:orig_category":"Berufliche Weiterbildung, Erwachsenenbildung Berufsbildende weiterf\u00fchrende Schulen",
    "sg:phone":"+41 62 824 54 08",
    "sg:postcode":"5000",
    "sg:province":"Aargau",
    "wof:name":"Ausbildungszentrum Coiffeure Kant.aarg.coiffeurmeisterverb.",
    "wof:placetype":"venue"
},
  "geometry": {"coordinates":[8.04062,47.39027],"type":"Point"}
}