{
  "type": "Feature",
  "properties": {
    "iso:country":"CH",
    "sg:address":"Ohmstrasse 40",
    "sg:city":"Z\u00fcrich",
    "sg:orig_category":"Sonstige Aktivit\u00e4ten der nicht-\u00e4rztlichen Medizinalberufe",
    "sg:phone":"+41 13121417",
    "sg:postcode":"8050",
    "sg:province":"Z\u00fcrich",
    "wof:name":"Sylvia Ehrensperger Atemtherapie",
    "wof:placetype":"venue"
},
  "geometry": {"coordinates":[8.5465202332,47.4122581482],"type":"Point"}
}