{
  "type": "Feature",
  "properties": {
    "iso:country":"CH",
    "sg:address":"Dormatt 2",
    "sg:city":"Rotkreuz",
    "sg:classifiers":[
        {
            "category":"Banks & Credit Unions",
            "subcategory":"Bank",
            "type":"Services"
        }
    ],
    "sg:phone":"+41 4142641266",
    "sg:postcode":"6343",
    "sg:province":"Zug",
    "wof:name":"Zuger Kantonalbank",
    "wof:placetype":"venue"
},
  "geometry": {"coordinates":[8.466031,47.13414],"type":"Point"}
}