{
  "type": "Feature",
  "properties": {
    "iso:country":"CH",
    "sg:address":"Alte Kappelerstrasse 21",
    "sg:city":"Baar",
    "sg:orig_category":"G\u00fcterbef\u00f6rderung im Strassenverkehr",
    "sg:postcode":"6340",
    "sg:province":"Zug",
    "wof:name":"Casillo Transporte",
    "wof:placetype":"venue"
},
  "geometry": {"coordinates":[8.5185098648,47.2058296204],"type":"Point"}
}