{
  "type": "Feature",
  "properties": {
    "iso:country":"CH",
    "sg:address":"1796",
    "sg:city":"Courgevaux",
    "sg:orig_category":"Verarbeitung von Milch Verwertung von Milch",
    "sg:postcode":"1796",
    "sg:province":"Fribourg",
    "wof:name":"Milchgenossenschaft Dickbuch",
    "wof:placetype":"venue"
},
  "geometry": {"coordinates":[8.853597641,47.4728622437],"type":"Point"}
}