{
  "type": "Feature",
  "properties": {
    "iso:country":"CH",
    "sg:address":"Alte Poststrasse 1",
    "sg:city":"Untersiggenthal",
    "sg:orig_category":"RESTAURANTS: TEA-ROOMS",
    "sg:phone":"+41 56 288 15 81",
    "sg:postcode":"5417",
    "sg:province":"Aargau",
    "wof:name":"Caf\u00e9-konditorei B\u00e4ckerst\u00fcbli E. H\u00f6hn-peterhans",
    "wof:placetype":"venue"
},
  "geometry": {"coordinates":[8.261179924,47.4984855652],"type":"Point"}
}