{
  "type": "Feature",
  "properties": {
    "iso:country":"CH",
    "sg:address":"Stersm\u00fchlestrasse 32",
    "sg:city":"Tentlingen",
    "sg:orig_category":"Herstellung sonstiger Textilien Herstellung von Lederwaren U Schuhen",
    "sg:phone":"+41 26 418 11 91",
    "sg:postcode":"1734",
    "sg:province":"Fribourg",
    "wof:name":"Robert Aebischer Technische Gummiartikel",
    "wof:placetype":"venue"
},
  "geometry": {"coordinates":[7.1976041794,46.7624969482],"type":"Point"}
}