{
  "type": "Feature",
  "properties": {
    "iso:country":"CH",
    "sg:address":"L\u00f6wenstrasse 59 8001 Z\u00fcrich. Postfach",
    "sg:city":"Z\u00fcrich",
    "sg:orig_category":"Kauf U Verkauf von Immobilien auf eigene Rechnung Vermittlung U Verwaltung von Immobilien",
    "sg:phone":"+41 12121500",
    "sg:postcode":"8021",
    "sg:province":"Z\u00fcrich",
    "wof:name":"W & R Z\u00fcrich Ag",
    "wof:placetype":"venue"
},
  "geometry": {"coordinates":[8.5378446579,47.376739502],"type":"Point"}
}