{
  "type": "Feature",
  "properties": {
    "iso:country":"CH",
    "sg:address":"Konstanzerstrasse 12",
    "sg:city":"T\u00e4gerwilen",
    "sg:orig_category":"Detailhandel mit Waren verschiedener Art, Hauptrichtung Nahrungsmittel Lagerung",
    "sg:phone":"+41 71 930 00 31",
    "sg:postcode":"8274",
    "sg:province":"Thurgau",
    "wof:name":"Landi Kirchberg",
    "wof:placetype":"venue"
},
  "geometry": {"coordinates":[9.0408983231,47.4111747742],"type":"Point"}
}