{
  "type": "Feature",
  "properties": {
    "iso:country":"CH",
    "sg:address":"Zollhausstrasse 37",
    "sg:city":"Glarus",
    "sg:orig_category":"Vermietung U Verpachtung von eigenen Immobilien",
    "sg:phone":"+41 79 640 90 15",
    "sg:postcode":"8750",
    "sg:province":"Glarus",
    "wof:name":"Glarogas Gmbh",
    "wof:placetype":"venue"
},
  "geometry": {"coordinates":[9.0635204315,47.0432319641],"type":"Point"}
}