{
  "type": "Feature",
  "properties": {
    "iso:country":"CH",
    "sg:address":"Rue Juste Olivier 18",
    "sg:city":"Nyon",
    "sg:orig_category":"Architektur U Ingenieurb\u00fcros Architekturb\u00fcros",
    "sg:phone":"+41 22 361 18 88",
    "sg:postcode":"1260",
    "sg:province":"Vaud",
    "wof:name":"Magnin Jean-pierre & Cie S\u00e0rl",
    "wof:placetype":"venue"
},
  "geometry": {"coordinates":[6.237715,46.384659],"type":"Point"}
}