{
  "type": "Feature",
  "properties": {
    "iso:country":"CH",
    "sg:address":"Nordstrasse 118",
    "sg:city":"Schaffhausen",
    "sg:orig_category":"Kosmetikinstitute",
    "sg:phone":"+41 71 223 30 24",
    "sg:postcode":"8200",
    "sg:province":"Schaffhausen",
    "wof:name":"Coiffure Martinique Zuber",
    "wof:placetype":"venue"
},
  "geometry": {"coordinates":[9.376619339,47.4253158569],"type":"Point"}
}