{
  "type": "Feature",
  "properties": {
    "iso:country":"CH",
    "sg:address":"Morgenstrasse 123",
    "sg:city":"Bern",
    "sg:orig_category":"Herstellung von Fenstern U T\u00fcren aus Holz",
    "sg:phone":"+41 56 648 95 95",
    "sg:postcode":"3018",
    "sg:province":"Bern",
    "wof:name":"Svedex-kellpax Ag",
    "wof:placetype":"venue"
},
  "geometry": {"coordinates":[8.3356399536,47.343837738],"type":"Point"}
}