{
  "type": "Feature",
  "properties": {
    "iso:country":"CH",
    "sg:address":"Widenacherstrasse 8",
    "sg:city":"Hedingen",
    "sg:orig_category":"Herstellung von Konstruktionsteilen, Fertigbauteilen U Ausbauelementen aus Holz",
    "sg:phone":"+41 17610936",
    "sg:postcode":"8908",
    "sg:province":"Z\u00fcrich",
    "wof:name":"Meier Martin",
    "wof:placetype":"venue"
},
  "geometry": {"coordinates":[8.4491224289,47.292350769],"type":"Point"}
}