{
  "type": "Feature",
  "properties": {
    "iso:country":"CH",
    "sg:address":"Gr\u00fcndenstrasse 50",
    "sg:city":"Muttenz",
    "sg:orig_category":"Herstellung von medizinischen U chirurgischen Ger\u00e4ten sowie orthop\u00e4dischen Vorrichtungen Zahntechnis",
    "sg:phone":"+41 61 461 08 23",
    "sg:postcode":"4132",
    "sg:province":"Basel-Landschaft",
    "wof:name":"Dtm Dental Technik Muttenz Gmbh",
    "wof:placetype":"venue"
},
  "geometry": {"coordinates":[7.6354289055,47.5339126587],"type":"Point"}
}