{
  "type": "Feature",
  "properties": {
    "iso:country":"CH",
    "sg:address":"Birmensdorferstrasse 122 8902 Urdorf. Postfach",
    "sg:city":"Urdorf",
    "sg:orig_category":"Softwareentwicklung U beratung",
    "sg:postcode":"8902",
    "sg:province":"Z\u00fcrich",
    "wof:name":"Magirus Schweiz Ag Edv-hard Und Software; Handel",
    "wof:placetype":"venue"
},
  "geometry": {"coordinates":[8.4226951599,47.3811454773],"type":"Point"}
}