{
  "type": "Feature",
  "properties": {
    "iso:country":"CH",
    "sg:address":"Im L\u00f6chli",
    "sg:city":"Bottighofen",
    "sg:orig_category":"Mechanik Mechanische Werkst\u00e4tten",
    "sg:phone":"+41 71 688 40 75",
    "sg:postcode":"8598",
    "sg:province":"Thurgau",
    "wof:name":"Bader R. Konstruktionswerkst\u00e4tte Ag",
    "wof:placetype":"venue"
},
  "geometry": {"coordinates":[9.2088499069,47.6402397156],"type":"Point"}
}