{
  "type": "Feature",
  "properties": {
    "addr:full":"Viale Stazione 10 Bellinzona Ticino 6500",
    "addr:housenumber":"10",
    "addr:postcode":"6500",
    "addr:street":"Viale Stazione",
    "iso:country":"CH",
    "sg:address":"Viale Stazione 10",
    "sg:city":"Bellinzona",
    "sg:orig_category":"Detailhandel mit Brillen U anderen Sehhilfen Fachdetailhandel in Verkaufsr\u00e4umen",
    "sg:phone":"+41 91 826 43 44",
    "sg:postcode":"6500",
    "sg:province":"Ticino",
    "wof:name":"Mister Optic Sa",
    "wof:placetype":"venue"
},
  "geometry": {"coordinates":[9.024612,46.192413],"type":"Point"}
}