{
  "type": "Feature",
  "properties": {
    "iso:country":"CH",
    "sg:address":"Aachstrasse 22",
    "sg:city":"Arbon",
    "sg:orig_category":"Handelsvermittlung U Grosshandel",
    "sg:phone":"+41 71 446 58 47",
    "sg:postcode":"9320",
    "sg:province":"Thurgau",
    "wof:name":"Markus Andermatt Landesprodukte",
    "wof:placetype":"venue"
},
  "geometry": {"coordinates":[9.42370224,47.5083198547],"type":"Point"}
}