{
  "type": "Feature",
  "properties": {
    "iso:country":"CH",
    "sg:address":"Oberdorfstrasse 16b",
    "sg:city":"Z\u00fcrich",
    "sg:orig_category":"Buchf\u00fchrung Wirtschaftspr\u00fcfung, Steuerberatung U Treuhand",
    "sg:phone":"+41 12619434",
    "sg:postcode":"8001",
    "sg:province":"Z\u00fcrich",
    "wof:name":"K\u00fcpfer Rita, Treuhand",
    "wof:placetype":"venue"
},
  "geometry": {"coordinates":[8.545588,47.368809],"type":"Point"}
}