{
  "type": "Feature",
  "properties": {
    "iso:country":"CH",
    "sg:address":"Fellerstrasse 11 3027 Bern. Postfach 267",
    "sg:city":"Bern",
    "sg:orig_category":"Herstellung von keramischen Wand U Bodenfliesen U platten",
    "sg:phone":"+41 79 205 41 25",
    "sg:postcode":"3027",
    "sg:province":"Bern",
    "wof:name":"Petro Jean-paul",
    "wof:placetype":"venue"
},
  "geometry": {"coordinates":[6.1364197731,46.1839294434],"type":"Point"}
}