{
  "type": "Feature",
  "properties": {
    "iso:country":"CH",
    "sg:address":"Buchzelgstrasse 23",
    "sg:city":"Z\u00fcrich",
    "sg:orig_category":"Zahnarztpraxen",
    "sg:phone":"+41 13811280",
    "sg:postcode":"8053",
    "sg:province":"Z\u00fcrich",
    "wof:name":"Dr.med.dent.liliane Gautschi Zahn\u00e4rztin",
    "wof:placetype":"venue"
},
  "geometry": {"coordinates":[8.5854854584,47.3597984314],"type":"Point"}
}