{
  "type": "Feature",
  "properties": {
    "iso:country":"CH",
    "sg:address":"Lyssstrasse 33",
    "sg:city":"Sch\u00fcpfen",
    "sg:orig_category":"Autogaragen Lastwagen and Nutzfahrzeuge",
    "sg:phone":"+41 79 651 67 71",
    "sg:postcode":"3054",
    "sg:province":"Bern",
    "wof:name":"Inderm\u00fchle Chr. Ag",
    "wof:placetype":"venue"
},
  "geometry": {"coordinates":[7.374473,47.044147],"type":"Point"}
}