{
  "type": "Feature",
  "properties": {
    "iso:country":"CH",
    "sg:address":"8051 Z\u00fcrich. Postfach 28",
    "sg:city":"Z\u00fcrich",
    "sg:orig_category":"Sportvereine Ballsport Fussball Vereine Damen",
    "sg:phone":"+41 13224339",
    "sg:postcode":"8051",
    "sg:province":"Z\u00fcrich",
    "wof:name":"Fc Schwamendingen Abt.damen",
    "wof:placetype":"venue"
},
  "geometry": {"coordinates":[8.5767803192,47.4015808105],"type":"Point"}
}