{
  "type": "Feature",
  "properties": {
    "iso:country":"CH",
    "sg:address":"Kapplerstrasse 23",
    "sg:city":"Ebnat",
    "sg:orig_category":"Herstellung von sonstigen keramischen Erzeugnissen",
    "sg:postcode":"9642",
    "sg:province":"St. Gallen",
    "wof:name":"Amacker Heidi",
    "wof:placetype":"venue"
},
  "geometry": {"coordinates":[9.1198415756,47.2659225464],"type":"Point"}
}