{
  "type": "Feature",
  "properties": {
    "iso:country":"CH",
    "sg:address":"B\u00f6ltschi",
    "sg:city":"Rothenburg",
    "sg:orig_category":"Allgemeiner Gartenbau G\u00fcterbef\u00f6rderung im Strassenverkehr",
    "sg:phone":"+41 61 756 55 55",
    "sg:postcode":"6023",
    "sg:province":"Luzern",
    "wof:name":"Wenger Ag Gartenbau & Baumschule",
    "wof:placetype":"venue"
},
  "geometry": {"coordinates":[7.59807,47.466969],"type":"Point"}
}