{
  "type": "Feature",
  "properties": {
    "iso:country":"CH",
    "sg:address":"R\u00f6merstrasse 97 8404 Oberwinterthur. Postfach",
    "sg:city":"Winterthur",
    "sg:orig_category":"Herstellung von Konstruktionsteilen, Fertigbauteilen U Ausbauelementen aus Holz",
    "sg:phone":"+41 52 246 08 00",
    "sg:postcode":"8404",
    "sg:province":"Z\u00fcrich",
    "wof:name":"Bvi Innenausbau Gmbh",
    "wof:placetype":"venue"
},
  "geometry": {"coordinates":[8.7499341965,47.5031166077],"type":"Point"}
}