{
  "type": "Feature",
  "properties": {
    "iso:country":"CH",
    "sg:address":"Chemin De Renens 11",
    "sg:city":"Lausanne",
    "sg:orig_category":"Sportvereine Ballsport Tischtennis",
    "sg:phone":"+41 21 624 22 75",
    "sg:postcode":"1004",
    "sg:province":"Vaud",
    "wof:name":"Ctt Trams",
    "wof:placetype":"venue"
},
  "geometry": {"coordinates":[6.6137590408,46.5268974304],"type":"Point"}
}