{
  "type": "Feature",
  "properties": {
    "iso:country":"CH",
    "sg:address":"Bahnhofplatz 6170 Sch\u00fcpfheim. Postfach 116",
    "sg:city":"Sch\u00fcpfheim",
    "sg:orig_category":"Abbruch U Sprenggewerbe Hoch U Tiefbau",
    "sg:phone":"+41 41 484 25 55",
    "sg:postcode":"6170",
    "sg:province":"Luzern",
    "wof:name":"Pk Bau Ag Sch\u00fcpfheim",
    "wof:placetype":"venue"
},
  "geometry": {"coordinates":[8.015545,46.950562],"type":"Point"}
}