{
  "type": "Feature",
  "properties": {
    "iso:country":"CH",
    "sg:address":"Route De Sugnens",
    "sg:city":"Poliez-le-grand",
    "sg:orig_category":"Bestattungswesen",
    "sg:postcode":"1041",
    "sg:province":"Vaud",
    "wof:name":"Aac Aide Et Assistance Cl\u00e9ment Sa",
    "wof:placetype":"venue"
},
  "geometry": {"coordinates":[6.66457,46.637192],"type":"Point"}
}