{
  "type": "Feature",
  "properties": {
    "iso:country":"CH",
    "sg:address":"Dorfstrasse 39",
    "sg:city":"Bachenb\u00fclach",
    "sg:orig_category":"Herstellung von Hebezeugen U F\u00f6rdermitteln",
    "sg:phone":"+41 18606485",
    "sg:postcode":"8184",
    "sg:province":"Z\u00fcrich",
    "wof:name":"Liftmontage Meier Jak.",
    "wof:placetype":"venue"
},
  "geometry": {"coordinates":[8.5502576828,47.5035591125],"type":"Point"}
}