{
  "type": "Feature",
  "properties": {
    "iso:country":"CH",
    "sg:address":"Artisans Promenade Des 30",
    "sg:city":"Meyrin",
    "sg:orig_category":"Herstellung von sonstigen elektrischen Ausr\u00fcstungen",
    "sg:postcode":"1217",
    "sg:province":"Gen\u00e8ve",
    "wof:name":"Casa Services S\u00e0rl",
    "wof:placetype":"venue"
},
  "geometry": {"coordinates":[6.0722160339,46.2284431458],"type":"Point"}
}