{
  "type": "Feature",
  "properties": {
    "iso:country":"CH",
    "sg:address":"K\u00e4sereistrasse 188 8581 Schocherswil. Postfach",
    "sg:city":"Schocherswil",
    "sg:orig_category":"Instandhaltung U Reparatur von Automobilen",
    "sg:postcode":"8581",
    "sg:province":"Thurgau",
    "wof:name":"Garage Rohner H. Hondavertretung",
    "wof:placetype":"venue"
},
  "geometry": {"coordinates":[9.27140522,47.536277771],"type":"Point"}
}