{
  "type": "Feature",
  "properties": {
    "iso:country":"CH",
    "sg:address":"Rue Alexander-sch\u00f6ni 18 2500 Biel/bienne. Postfach",
    "sg:city":"Biel/bienne",
    "sg:orig_category":"RESTAURANTS: TEA-ROOMS",
    "sg:postcode":"2503",
    "sg:province":"Bern",
    "wof:name":"Placer Camilo",
    "wof:placetype":"venue"
},
  "geometry": {"coordinates":[7.2479500771,47.1362457275],"type":"Point"}
}