{
  "type": "Feature",
  "properties": {
    "iso:country":"CH",
    "sg:address":"Bahnweg Nord 16",
    "sg:city":"Sevelen",
    "sg:orig_category":"Vermietung U Verpachtung von eigenen Immobilien",
    "sg:postcode":"9475",
    "sg:province":"St. Gallen",
    "wof:name":"Sedroz Sa",
    "wof:placetype":"venue"
},
  "geometry": {"coordinates":[6.8227171898,47.1001586914],"type":"Point"}
}