{
  "type": "Feature",
  "properties": {
    "iso:country":"CH",
    "sg:address":"Industriestrasse",
    "sg:city":"Inwil",
    "sg:orig_category":"Non-Classified Establishments",
    "sg:phone":"+41 41 448 03 33",
    "sg:postcode":"6034",
    "sg:province":"Luzern",
    "wof:name":"Robert Stadelmann Eurostaro Schr\u00e4nke",
    "wof:placetype":"venue"
},
  "geometry": {"coordinates":[8.3493375778,47.1181678772],"type":"Point"}
}