{
  "type": "Feature",
  "properties": {
    "iso:country":"CH",
    "sg:address":"3322",
    "sg:city":"Sch\u00f6nb\u00fchl-urtenen",
    "sg:orig_category":"Schulpflegen",
    "sg:phone":"+41 31 859 59 49",
    "sg:postcode":"3322",
    "sg:province":"Bern",
    "wof:name":"Schulkommission Der Gemeinde Sch\u00f6nb\u00fchl",
    "wof:placetype":"venue"
},
  "geometry": {"coordinates":[7.5026469231,47.018119812],"type":"Point"}
}