{
  "type": "Feature",
  "properties": {
    "iso:country":"CH",
    "sg:address":"Wettsteinallee 53 4058 Basel. Postfach",
    "sg:city":"Basel",
    "sg:orig_category":"Fotografische Ateliers Korrespondenz U Nachrichtenb\u00fcros",
    "sg:phone":"+41 61 692 54 32",
    "sg:postcode":"4006",
    "wof:name":"Andr\u00e9 Muelhaupt Fotoatelier",
    "wof:placetype":"venue"
},
  "geometry": {"coordinates":[7.601626873,47.5608177185],"type":"Point"}
}