{
  "type": "Feature",
  "properties": {
    "iso:country":"CH",
    "sg:address":"Poststrasse 16",
    "sg:city":"Richterswil",
    "sg:orig_category":"Sportvereine Turnen",
    "sg:phone":"+41 17841466",
    "sg:postcode":"8805",
    "sg:province":"Z\u00fcrich",
    "wof:name":"Turnverein Richterswil",
    "wof:placetype":"venue"
},
  "geometry": {"coordinates":[8.7057189941,47.2082862854],"type":"Point"}
}