{
  "type": "Feature",
  "properties": {
    "iso:country":"CH",
    "sg:address":"Lagerstrasse 8",
    "sg:city":"Volketswil",
    "sg:orig_category":"G\u00fcterbef\u00f6rderung im Strassenverkehr",
    "sg:phone":"+41 77661047",
    "sg:postcode":"8604",
    "sg:province":"Z\u00fcrich",
    "wof:name":"Robert Ochsner Transporte",
    "wof:placetype":"venue"
},
  "geometry": {"coordinates":[8.6760263443,47.3848724365],"type":"Point"}
}