{
  "type": "Feature",
  "properties": {
    "iso:country":"CH",
    "sg:address":"Gerbone Via 8",
    "sg:city":"Vezia",
    "sg:orig_category":"Unclassifiable Establishments",
    "sg:postcode":"6943",
    "sg:province":"Ticino",
    "wof:name":"Pentaholding Ag",
    "wof:placetype":"venue"
},
  "geometry": {"coordinates":[8.935259819,46.0225410461],"type":"Point"}
}