{
  "type": "Feature",
  "properties": {
    "addr:full":"Rue De Bourg 33 1003 Lausanne Case Postale 2792 Lausanne Vaud 1002",
    "addr:housenumber":"33",
    "addr:postcode":"1003;2792;1002",
    "addr:street":"Rue De Bourg;Postale",
    "iso:country":"CH",
    "sg:address":"Rue De Bourg 33 1003 Lausanne Case Postale 2792",
    "sg:city":"Lausanne",
    "sg:orig_category":"Advokaturb\u00fcros",
    "sg:phone":"+41 41 870 07 77",
    "sg:postcode":"1002",
    "sg:province":"Vaud",
    "wof:name":"Muheim Ziegler & Planzer Advokaturb\u00fcro",
    "wof:placetype":"venue"
},
  "geometry": {"coordinates":[8.643652,46.881886],"type":"Point"}
}