{
  "type": "Feature",
  "properties": {
    "iso:country":"CH",
    "sg:address":"Seestatt 20 8852 Altendorf. Postfach",
    "sg:city":"Altendorf",
    "sg:orig_category":"Finanzierungsinstitutionen",
    "sg:phone":"+41 55 451 56 10",
    "sg:postcode":"8852",
    "sg:province":"Schwyz",
    "wof:name":"Sanjo Finanz Ag",
    "wof:placetype":"venue"
},
  "geometry": {"coordinates":[8.8316869736,47.1946372986],"type":"Point"}
}