{
  "type": "Feature",
  "properties": {
    "iso:country":"CH",
    "sg:address":"Kirchgasse",
    "sg:city":"Fanas",
    "sg:orig_category":"Verkehrs- and Tourismusb\u00fcros",
    "sg:phone":"+41 81 325 31 91",
    "sg:postcode":"7215",
    "sg:province":"Graubunden",
    "wof:name":"Verkehrsverein Fanas",
    "wof:placetype":"venue"
},
  "geometry": {"coordinates":[9.6665182114,46.9846458435],"type":"Point"}
}