{
  "type": "Feature",
  "properties": {
    "iso:country":"CH",
    "sg:address":"Spirgartenstrasse 4",
    "sg:city":"Z\u00fcrich",
    "sg:orig_category":"Non-Classified Establishments",
    "sg:postcode":"8048",
    "sg:province":"Z\u00fcrich",
    "wof:name":"Diagonal Technik J\u00fcrg Berther + Co F\u00f6rderanlagen, Handhabungsger\u00e4te Usw; Konstruktion",
    "wof:placetype":"venue"
},
  "geometry": {"coordinates":[8.4846849442,47.3877067566],"type":"Point"}
}