{
  "type": "Feature",
  "properties": {
    "iso:country":"CH",
    "sg:address":"Weizenstrasse 5",
    "sg:city":"Z\u00fcrich",
    "sg:orig_category":"Bauschreinerei Erbringung von Dienstleistungen f\u00fcr Unternehmen",
    "sg:phone":"+41 13628825",
    "sg:postcode":"8037",
    "sg:province":"Z\u00fcrich",
    "wof:name":"H\u00e4chler Ren\u00e9 Modellbau",
    "wof:placetype":"venue"
},
  "geometry": {"coordinates":[8.535101,47.389557],"type":"Point"}
}