{
  "type": "Feature",
  "properties": {
    "iso:country":"CH",
    "sg:address":"Centralstrasse 14",
    "sg:city":"Berom\u00fcnster",
    "sg:orig_category":"Detailhandel mit fotografischen Artikeln",
    "sg:phone":"+41 21 631 01 15",
    "sg:postcode":"6215",
    "sg:province":"Luzern",
    "wof:name":"Fotomat Sa",
    "wof:placetype":"venue"
},
  "geometry": {"coordinates":[6.5912661552,46.5279464722],"type":"Point"}
}