{
  "type": "Feature",
  "properties": {
    "iso:country":"CH",
    "sg:address":"Gartenstrasse 59 4052 Basel. Postfach",
    "sg:city":"Basel",
    "sg:orig_category":"Unternehmensberatung",
    "sg:phone":"+41 21 691 71 13",
    "sg:postcode":"4051",
    "sg:province":"Basel-Stadt",
    "wof:name":"Tmc Technology & Management Consulting S\u00e0rl",
    "wof:placetype":"venue"
},
  "geometry": {"coordinates":[6.5550599098,46.519985199],"type":"Point"}
}