{
  "type": "Feature",
  "properties": {
    "iso:country":"CH",
    "sg:address":"Stansstaderstrasse 20",
    "sg:city":"Stans",
    "sg:classifiers":[
        {
            "category":"Professional",
            "subcategory":"Employment Agencies",
            "type":"Services"
        }
    ],
    "sg:phone":"+41 41 619 18 18",
    "sg:postcode":"6370",
    "sg:province":"Nidwalden",
    "sg:tags":[
        "personal",
        "u",
        "stellenvermittlung"
    ],
    "wof:name":"Dag Personal",
    "wof:placetype":"venue"
},
  "geometry": {"coordinates":[8.3641519547,46.9587249756],"type":"Point"}
}