{
  "type": "Feature",
  "properties": {
    "iso:country":"CH",
    "sg:address":"Schl\u00f6sslirain 9",
    "sg:city":"Luzern",
    "sg:orig_category":"Unclassifiable Establishments",
    "sg:phone":"+41 41 370 69 31",
    "sg:postcode":"6006",
    "sg:province":"Luzern",
    "wof:name":"M\u00dcller + Antonietty Ag",
    "wof:placetype":"venue"
},
  "geometry": {"coordinates":[8.33735466,47.0557327271],"type":"Point"}
}