{
  "type": "Feature",
  "properties": {
    "iso:country":"CH",
    "sg:address":"Au Raffour",
    "sg:city":"Maracon",
    "sg:orig_category":"Physiotherapie",
    "sg:phone":"+41 21 907 79 77",
    "sg:postcode":"1613",
    "sg:province":"Vaud",
    "wof:name":"C. Tinghir & F. Chollet Physioth\u00e9rapie",
    "wof:placetype":"venue"
},
  "geometry": {"coordinates":[6.8727149963,46.5517692566],"type":"Point"}
}