{
  "type": "Feature",
  "properties": {
    "iso:country":"CH",
    "sg:address":"Ponteggia Via",
    "sg:city":"Cadempino",
    "sg:orig_category":"Herstellung von Werkzeugmaschinen",
    "sg:phone":"+41 91 950 80 70",
    "sg:postcode":"6814",
    "sg:province":"Ticino",
    "wof:name":"Soltech Sagl",
    "wof:placetype":"venue"
},
  "geometry": {"coordinates":[8.9320726395,46.0322265625],"type":"Point"}
}