{
  "type": "Feature",
  "properties": {
    "iso:country":"CH",
    "sg:address":"Schwerzistrasse 30 8807 Freienbach. Postfach 363",
    "sg:city":"Freienbach",
    "sg:orig_category":"Handelsvermittlung U Grosshandel",
    "sg:phone":"+41 55 415 18 68",
    "sg:postcode":"8807",
    "sg:province":"Schwyz",
    "wof:name":"Rudolf Uiker Inh.aldo Corrieri",
    "wof:placetype":"venue"
},
  "geometry": {"coordinates":[8.7601232529,47.2014045715],"type":"Point"}
}