{
  "type": "Feature",
  "properties": {
    "iso:country":"CH",
    "sg:address":"Viale Stefano Franscini 27",
    "sg:city":"Lugano",
    "sg:orig_category":"Zahnarztpraxen",
    "sg:phone":"+41 91 923 26 89",
    "sg:postcode":"6900",
    "sg:province":"Ticino",
    "wof:name":"Dott. Med. Dent. G. Bernasconi Dentista",
    "wof:placetype":"venue"
},
  "geometry": {"coordinates":[8.9544477463,46.0112342834],"type":"Point"}
}