{
  "type": "Feature",
  "properties": {
    "iso:country":"CH",
    "sg:address":"Breitenrain 35",
    "sg:city":"Hinterkappelen",
    "sg:orig_category":"Reiseb\u00fcros",
    "sg:phone":"+41 31 901 32 28",
    "sg:postcode":"3032",
    "sg:province":"Bern",
    "wof:name":"B.a.s.s. Gmbh-business Air Service Switzerland",
    "wof:placetype":"venue"
},
  "geometry": {"coordinates":[7.3765730858,46.969417572],"type":"Point"}
}