{
  "type": "Feature",
  "properties": {
    "addr:full":"Wetzikon Wetzikon Z\u00fcrich 8620",
    "addr:postcode":"8620",
    "addr:street":"Zuerich",
    "iso:country":"CH",
    "sg:address":"Wetzikon",
    "sg:city":"Wetzikon",
    "sg:classifiers":[
        {
            "category":"Banks & Credit Unions",
            "subcategory":"Bank",
            "type":"Services"
        }
    ],
    "sg:phone":"+41 19335400",
    "sg:postcode":"8620",
    "sg:province":"Z\u00fcrich",
    "wof:name":"Sparkasse, Z\u00fcrcher Oberland",
    "wof:placetype":"venue"
},
  "geometry": {"coordinates":[8.80395,47.320808],"type":"Point"}
}