{
  "type": "Feature",
  "properties": {
    "iso:country":"CH",
    "sg:address":"Sch\u00f6nblickstrasse 14",
    "sg:city":"Meggen",
    "sg:orig_category":"Architektur U Ingenieurb\u00fcros",
    "sg:phone":"+41 41 377 18 53",
    "sg:postcode":"6045",
    "sg:province":"Luzern",
    "wof:name":"Wyrsch Hugo",
    "wof:placetype":"venue"
},
  "geometry": {"coordinates":[8.370584,47.044659],"type":"Point"}
}