{
  "type": "Feature",
  "properties": {
    "iso:country":"CH",
    "sg:address":"Au Br\u00eat",
    "sg:city":"Remaufens",
    "sg:orig_category":"Stukkateurgewerbe, Gipserei U Verputzerei",
    "sg:postcode":"1617",
    "sg:province":"Fribourg",
    "wof:name":"Thuillard S\u00e0rl",
    "wof:placetype":"venue"
},
  "geometry": {"coordinates":[6.8786277771,46.5339622498],"type":"Point"}
}