{
  "type": "Feature",
  "properties": {
    "iso:country":"CH",
    "sg:address":"Rue Du 23-juin 230.",
    "sg:city":"Alle",
    "sg:orig_category":"Fachdetailhandel mit pharmazeutischen Produkten",
    "sg:postcode":"2942",
    "sg:province":"Jura",
    "wof:name":"Pharmacie Erard Cl., Succursale De Alle.",
    "wof:placetype":"venue"
},
  "geometry": {"coordinates":[7.1321601868,47.427028656],"type":"Point"}
}