{
  "type": "Feature",
  "properties": {
    "iso:country":"CH",
    "sg:address":"Rue Cime De L'est 5",
    "sg:city":"St-maurice",
    "sg:classifiers":[
        {
            "category":"Restaurant",
            "type":"Food & Drink"
        }
    ],
    "sg:phone":"+41 24 485 29 91",
    "sg:postcode":"1890",
    "sg:province":"Valais",
    "wof:name":"Restaurant La Charbonni\u00e8re",
    "wof:placetype":"venue"
},
  "geometry": {"coordinates":[7.0024261475,46.212638855],"type":"Point"}
}