{
  "type": "Feature",
  "properties": {
    "iso:country":"CH",
    "sg:address":"Huber Avenue Max 10",
    "sg:city":"Sierre",
    "sg:orig_category":"Vermietung U Verpachtung von eigenen Immobilien",
    "sg:phone":"+41 34 445 33 11",
    "sg:postcode":"3960",
    "sg:province":"Valais",
    "wof:name":"Massivbau Immobilien Ag",
    "wof:placetype":"venue"
},
  "geometry": {"coordinates":[7.5851860046,47.0828590393],"type":"Point"}
}