{
  "type": "Feature",
  "properties": {
    "iso:country":"CH",
    "sg:address":"F\u00f6rrlibuckstrasse 150",
    "sg:city":"Z\u00fcrich",
    "sg:orig_category":"Handels-H\u00e4user U Gesellschaften",
    "sg:phone":"+41 12723868",
    "sg:postcode":"8005",
    "sg:province":"Z\u00fcrich",
    "wof:name":"Royal-kredit Gmbh",
    "wof:placetype":"venue"
},
  "geometry": {"coordinates":[8.5114393234,47.3922538757],"type":"Point"}
}