{
  "type": "Feature",
  "properties": {
    "iso:country":"CH",
    "sg:address":"Route Du Village 26",
    "sg:city":"Blonay",
    "sg:orig_category":"Detailhandel mit Geschenkartikeln U Souvenirs",
    "sg:phone":"+41 22 301 45 25",
    "sg:postcode":"1807",
    "sg:province":"Vaud",
    "wof:name":"Boutique Arcade G.& N.lombardo",
    "wof:placetype":"venue"
},
  "geometry": {"coordinates":[6.1406412125,46.1861915588],"type":"Point"}
}