{
  "type": "Feature",
  "properties": {
    "iso:country":"CH",
    "sg:address":"R\u00f6sslistrasse 29",
    "sg:city":"Wallisellen",
    "sg:orig_category":"Elektro- and elektronische Maschinen Grosshandel",
    "sg:phone":"+41 18307474",
    "sg:postcode":"8304",
    "sg:province":"Z\u00fcrich",
    "wof:name":"H.r. Keller Elektronische Ger\u00e4te",
    "wof:placetype":"venue"
},
  "geometry": {"coordinates":[8.6069297791,47.4123916626],"type":"Point"}
}