{
  "type": "Feature",
  "properties": {
    "iso:country":"CH",
    "sg:address":"M\u00fchlenberg 5",
    "sg:city":"Basel",
    "sg:orig_category":"Architektur U Ingenieurb\u00fcros",
    "sg:postcode":"4052",
    "sg:province":"Basel-Stadt",
    "wof:name":"Rolf Scheiwiller",
    "wof:placetype":"venue"
},
  "geometry": {"coordinates":[8.304703,46.991245],"type":"Point"}
}