{
  "type": "Feature",
  "properties": {
    "iso:country":"CH",
    "sg:address":"Altweg 13 8752 N\u00e4fels. Postfach",
    "sg:city":"N\u00e4fels",
    "sg:orig_category":"Non-Classified Establishments",
    "sg:postcode":"8752",
    "sg:province":"Glarus",
    "wof:name":"Hauser Webdesign",
    "wof:placetype":"venue"
},
  "geometry": {"coordinates":[9.0584220886,47.0953292847],"type":"Point"}
}