{
  "type": "Feature",
  "properties": {
    "iso:country":"CH",
    "sg:address":"Avenue Druey 1",
    "sg:city":"Lausanne",
    "sg:orig_category":"Reiseb\u00fcros U Reiseveranstalter",
    "sg:phone":"+41 21 320 77 70",
    "sg:postcode":"1018",
    "sg:province":"Vaud",
    "wof:name":"Destination Brasil, Serex Nilceia",
    "wof:placetype":"venue"
},
  "geometry": {"coordinates":[6.6303920746,46.5282402039],"type":"Point"}
}