{
  "type": "Feature",
  "properties": {
    "iso:country":"CH",
    "sg:address":"Grosswiesenstrasse 61",
    "sg:city":"Z\u00fcrich",
    "sg:orig_category":"Reiseb\u00fcros U Reiseveranstalter",
    "sg:postcode":"8051",
    "sg:province":"Z\u00fcrich",
    "wof:name":"Z & H Reisen, Z. Grisevic",
    "wof:placetype":"venue"
},
  "geometry": {"coordinates":[8.5847463608,47.4035224915],"type":"Point"}
}