{
  "type": "Feature",
  "properties": {
    "iso:country":"CH",
    "sg:address":"Chemin Du Foron 16",
    "sg:city":"Th\u00f4nex",
    "sg:orig_category":"Werbung",
    "sg:phone":"+41 22 869 88 77",
    "sg:postcode":"1226",
    "sg:province":"Gen\u00e8ve",
    "wof:name":"Publicitron Francis Dzikowski Agence De Publicit\u00e9",
    "wof:placetype":"venue"
},
  "geometry": {"coordinates":[6.2113471031,46.1938247681],"type":"Point"}
}