{
  "type": "Feature",
  "properties": {
    "addr:full":"Viale Bartolomeo Papio 5 Ascona Ticino 6612",
    "addr:housenumber":"5",
    "addr:postcode":"6612",
    "addr:street":"Viale Bartolomeo Papio",
    "iso:country":"CH",
    "sg:address":"Viale Bartolomeo Papio 5",
    "sg:city":"Ascona",
    "sg:classifiers":[
        {
            "category":"Banks & Credit Unions",
            "subcategory":"Bank",
            "type":"Services"
        }
    ],
    "sg:phone":"+41 24 492 36 42",
    "sg:postcode":"6612",
    "sg:province":"Ticino",
    "wof:name":"Swiss Bank Corp.",
    "wof:placetype":"venue"
},
  "geometry": {"coordinates":[7.158712,46.35004],"type":"Point"}
}