{
  "type": "Feature",
  "properties": {
    "addr:full":"Burgstrasse 20 Thun Bern 3601",
    "addr:housenumber":"20",
    "addr:postcode":"3601",
    "addr:street":"Burgstrasse;Bern",
    "iso:country":"CH",
    "sg:address":"Burgstrasse 20",
    "sg:city":"Thun",
    "sg:classifiers":[
        {
            "category":"Banks & Credit Unions",
            "subcategory":"Bank",
            "type":"Services"
        }
    ],
    "sg:phone":"+41 33227444",
    "sg:postcode":"3601",
    "sg:province":"Bern",
    "wof:name":"Credit Suisse",
    "wof:placetype":"venue"
},
  "geometry": {"coordinates":[7.629318,46.761402],"type":"Point"}
}