{
  "type": "Feature",
  "properties": {
    "iso:country":"CH",
    "sg:address":"Rue Du Man\u00e8ge 1 2500 Biel/bienne. Postfach",
    "sg:city":"Biel/bienne",
    "sg:orig_category":"Herstellung von elektrischen Ausr\u00fcstungen f\u00fcr Motoren U Fahrzeuge",
    "sg:phone":"+41 32 323 22 52",
    "sg:postcode":"2502",
    "sg:province":"Bern",
    "wof:name":"Kamal Seeland S\u00e0rl",
    "wof:placetype":"venue"
},
  "geometry": {"coordinates":[7.2899799347,47.1467399597],"type":"Point"}
}