{
  "type": "Feature",
  "properties": {
    "iso:country":"CH",
    "sg:address":"1036",
    "sg:city":"Sullens",
    "sg:orig_category":"Unternehmensberatung",
    "sg:phone":"+41 71 222 56 22",
    "sg:postcode":"1036",
    "sg:province":"Vaud",
    "wof:name":"Camtec Pulverbeschichtungssysteme Ag",
    "wof:placetype":"venue"
},
  "geometry": {"coordinates":[9.6344804764,47.4550552368],"type":"Point"}
}