{
  "type": "Feature",
  "properties": {
    "iso:country":"CH",
    "sg:address":"B\u00f6zingenstrasse 162 2504 Biel/bienne. Postfach",
    "sg:city":"Biel/bienne",
    "sg:orig_category":"Vermietung U Verpachtung von eigenen Immobilien",
    "sg:postcode":"2502",
    "sg:province":"Bern",
    "wof:name":"Wyssbrod Immobilien & Cie",
    "wof:placetype":"venue"
},
  "geometry": {"coordinates":[7.2669639587,47.1524772644],"type":"Point"}
}