{
  "type": "Feature",
  "properties": {
    "iso:country":"CH",
    "sg:address":"Lessingstr. 5 Pf 8027",
    "sg:city":"Z\u00fcrich",
    "sg:classifiers":[
        {
            "category":"Wholesale",
            "subcategory":"Machinery & Supplies",
            "type":"Manufacturing & Wholesale Goods"
        }
    ],
    "sg:phone":"+41 4112026650",
    "sg:postcode":"8002",
    "sg:province":"Z\u00fcrich",
    "sg:tags":[
        "equipment",
        "equipement",
        "precision",
        "timekeeping"
    ],
    "wof:name":"Mondaine Watch Ltd",
    "wof:placetype":"venue"
},
  "geometry": {"coordinates":[8.5395498276,47.3770599365],"type":"Point"}
}