{
  "type": "Feature",
  "properties": {
    "addr:full":"Hauptstrasse 3 Binningen Basel-Landschaft 4102",
    "addr:housenumber":"3",
    "addr:postcode":"4102",
    "addr:street":"Hauptstrasse",
    "iso:country":"CH",
    "sg:address":"Hauptstrasse 3",
    "sg:city":"Binningen",
    "sg:orig_category":"Arztpraxen",
    "sg:phone":"+41 61 421 18 68",
    "sg:postcode":"4102",
    "sg:province":"Basel-Landschaft",
    "wof:name":"Dr.med.urs Beat Gr\u00f6flin Spezialarzt Fmh",
    "wof:placetype":"venue"
},
  "geometry": {"coordinates":[7.575513,47.543434],"type":"Point"}
}