{
  "type": "Feature",
  "properties": {
    "iso:country":"CH",
    "sg:address":"Gr\u00f6blistrasse 11 9014 St. Gallen 14 Zust. Postfach 9014 St. Gallen",
    "sg:city":"Zust",
    "sg:orig_category":"Unclassifiable Establishments",
    "sg:phone":"+41 62 958 51 95",
    "sg:postcode":"14",
    "wof:name":"Glas Tr\u00f6sch Beteiligungs Ag Beteiligungen Usw",
    "wof:placetype":"venue"
},
  "geometry": {"coordinates":[8.3037157059,46.9888801575],"type":"Point"}
}