{
  "type": "Feature",
  "properties": {
    "iso:country":"CH",
    "sg:address":"Chemin Des Osches",
    "sg:city":"St-l\u00e9gier",
    "sg:orig_category":"Stukkateurgewerbe, Gipserei U Verputzerei",
    "sg:phone":"+41 21 943 14 56",
    "sg:postcode":"1806",
    "sg:province":"Vaud",
    "wof:name":"Nicola, Ren\u00e9-michel",
    "wof:placetype":"venue"
},
  "geometry": {"coordinates":[5.2554798126,49.0477790833],"type":"Point"}
}