{
  "type": "Feature",
  "properties": {
    "addr:full":"Via Caguils 36 Domat/ems Graubunden 7013",
    "addr:housenumber":"36",
    "addr:postcode":"7013",
    "addr:street":"Via Caguils",
    "iso:country":"CH",
    "sg:address":"Via Caguils 36",
    "sg:city":"Domat/ems",
    "sg:orig_category":"Advokaturb\u00fcros Notariate",
    "sg:phone":"+41 81 633 16 16",
    "sg:postcode":"7013",
    "sg:province":"Graubunden",
    "wof:name":"Dr.sigis Rageth Advokatur- & Notariatsb\u00fcro",
    "wof:placetype":"venue"
},
  "geometry": {"coordinates":[9.461024,46.835438],"type":"Point"}
}