{
  "type": "Feature",
  "properties": {
    "iso:country":"CH",
    "sg:address":"Schwandelstrasse 30",
    "sg:city":"Thalwil",
    "sg:orig_category":"Kauf U Verkauf von Immobilien auf eigene Rechnung",
    "sg:postcode":"8800",
    "sg:province":"Z\u00fcrich",
    "wof:name":"Buser Louis Ag",
    "wof:placetype":"venue"
},
  "geometry": {"coordinates":[8.5604906082,47.2926712036],"type":"Point"}
}