{
  "type": "Feature",
  "properties": {
    "iso:country":"CH",
    "sg:address":"Langgasse",
    "sg:city":"St.gallen",
    "sg:orig_category":"Detailhandel mit M\u00f6beln U Haushaltsgegenst\u00e4nden",
    "sg:phone":"+41 71 244 50 60",
    "sg:postcode":"9000",
    "sg:province":"St. Gallen",
    "wof:name":"Gobbo Info Soft Ag",
    "wof:placetype":"venue"
},
  "geometry": {"coordinates":[9.3811149597,47.424533844],"type":"Point"}
}