{
  "type": "Feature",
  "properties": {
    "iso:country":"CH",
    "sg:address":"Obergestadeckplatz 21",
    "sg:city":"Liestal",
    "sg:orig_category":"Vereine Stenographen",
    "sg:phone":"+41 61 922 15 75",
    "sg:postcode":"4410",
    "sg:province":"Basel-Landschaft",
    "wof:name":"Stenographie-sektion Des Kaufm.vereins Bl",
    "wof:placetype":"venue"
},
  "geometry": {"coordinates":[7.7371602058,47.484916687],"type":"Point"}
}