{
  "type": "Feature",
  "properties": {
    "iso:country":"CH",
    "sg:address":"Untere Br\u00fchlstrasse 21",
    "sg:city":"Zofingen",
    "sg:orig_category":"Verwaltung von Immobilien",
    "sg:phone":"+41 62 752 86 16",
    "sg:postcode":"4800",
    "sg:province":"Aargau",
    "wof:name":"Theodor Klopfenstein Immo Terra Verwaltungen",
    "wof:placetype":"venue"
},
  "geometry": {"coordinates":[7.933257103,47.2933654785],"type":"Point"}
}