{
  "type": "Feature",
  "properties": {
    "iso:country":"CH",
    "sg:address":"Stanserstrasse 19",
    "sg:city":"Stansstad",
    "sg:orig_category":"RESTAURANTS: TEA-ROOMS",
    "sg:postcode":"6362",
    "sg:province":"Nidwalden",
    "wof:name":"Esda Gmbh",
    "wof:placetype":"venue"
},
  "geometry": {"coordinates":[8.3413820267,46.9761009216],"type":"Point"}
}