{
  "type": "Feature",
  "properties": {
    "iso:country":"CH",
    "sg:address":"Wallisellenstrasse 301",
    "sg:city":"Z\u00fcrich",
    "sg:classifiers":[
        {
            "category":"Cinema",
            "subcategory":"Movie Theater",
            "type":"Entertainment"
        }
    ],
    "sg:phone":"+41 13223041",
    "sg:postcode":"8050",
    "sg:province":"Z\u00fcrich",
    "sg:tags":[
        "radio",
        "videofilmherstellung",
        "fernsehanstalten",
        "u",
        "film"
    ],
    "wof:name":"Prospot Z Ag",
    "wof:placetype":"venue"
},
  "geometry": {"coordinates":[8.561829567,47.4110298157],"type":"Point"}
}