{
  "type": "Feature",
  "properties": {
    "iso:country":"CH",
    "sg:address":"Hauptstrasse 137 4625 Oberbuchsiten. Postfach",
    "sg:city":"Oberbuchsiten",
    "sg:orig_category":"Detailhandel mit Textilien",
    "sg:postcode":"4625",
    "sg:province":"Solothurn",
    "wof:name":"Rupp's Monika Wulle-st\u00fcbli",
    "wof:placetype":"venue"
},
  "geometry": {"coordinates":[7.7651371956,47.3091506958],"type":"Point"}
}