{
  "type": "Feature",
  "properties": {
    "iso:country":"CH",
    "sg:address":"Stalden",
    "sg:city":"Stalden",
    "sg:classifiers":[
        {
            "category":"Banks & Credit Unions",
            "subcategory":"Bank",
            "type":"Services"
        }
    ],
    "sg:phone":"+41 41661421",
    "sg:postcode":"3922",
    "sg:province":"Valais",
    "wof:name":"Obwaldner Kantonalbank",
    "wof:placetype":"venue"
},
  "geometry": {"coordinates":[7.866755,46.23151],"type":"Point"}
}