{
  "type": "Feature",
  "properties": {
    "iso:country":"CH",
    "sg:address":"H\u00f6ngerstrasse 238",
    "sg:city":"Laupersdorf",
    "sg:orig_category":"Architekturb\u00fcros",
    "sg:phone":"+41 79 332 97 23",
    "sg:postcode":"4712",
    "sg:province":"Solothurn",
    "wof:name":"Jakob Gasser Architekturb\u00fcro",
    "wof:placetype":"venue"
},
  "geometry": {"coordinates":[7.657739,47.31321],"type":"Point"}
}