{
  "type": "Feature",
  "properties": {
    "iso:country":"CH",
    "sg:address":"Passage Vuillermet 1",
    "sg:city":"Rolle",
    "sg:orig_category":"Mechanische Werkst\u00e4tten",
    "sg:phone":"+41 56 493 56 00",
    "sg:postcode":"1180",
    "sg:province":"Vaud",
    "wof:name":"Jean-pierre Perroud Mechanische Werkstatt",
    "wof:placetype":"venue"
},
  "geometry": {"coordinates":[8.2934989929,47.4490432739],"type":"Point"}
}