{
  "type": "Feature",
  "properties": {
    "iso:country":"CH",
    "sg:address":"6556 Leggia. Postfach Caselle Postale 12",
    "sg:city":"Leggia",
    "sg:orig_category":"Sportvereine Ballsport Fussball",
    "sg:postcode":"6556",
    "sg:province":"Graubunden",
    "wof:name":"Us Gloria",
    "wof:placetype":"venue"
},
  "geometry": {"coordinates":[9.1634750366,46.2618293762],"type":"Point"}
}