{
  "type": "Feature",
  "properties": {
    "iso:country":"CH",
    "sg:address":"Baumackerstrasse 42 8050 Z\u00fcrich. Postfach",
    "sg:city":"Z\u00fcrich",
    "sg:orig_category":"Architektur U Ingenieurb\u00fcros",
    "sg:phone":"+41 12527480",
    "sg:postcode":"8050",
    "sg:province":"Z\u00fcrich",
    "wof:name":"Suter Von K\u00e4nel Wild Ag Orts Und Regionalplaner Fsu Sia",
    "wof:placetype":"venue"
},
  "geometry": {"coordinates":[8.543101,47.40947],"type":"Point"}
}