{
  "type": "Feature",
  "properties": {
    "iso:country":"CH",
    "sg:address":"Rue De La Monder\u00e8che 2",
    "sg:city":"Sierre",
    "sg:orig_category":"Herstellung von sonstigen landwirtschaftlichen Maschinen",
    "sg:phone":"+41 27 455 12 69",
    "sg:postcode":"3960",
    "sg:province":"Valais",
    "wof:name":"Fioroni-faust Arnaldo",
    "wof:placetype":"venue"
},
  "geometry": {"coordinates":[7.5305199623,46.2908096313],"type":"Point"}
}