{
  "type": "Feature",
  "properties": {
    "iso:country":"CH",
    "sg:address":"Monthoux Rue De 17",
    "sg:city":"Gen\u00e8ve",
    "sg:orig_category":"Unclassifiable Establishments",
    "sg:postcode":"1201",
    "sg:province":"Gen\u00e8ve",
    "wof:name":"Misako S\u00e0rl",
    "wof:placetype":"venue"
},
  "geometry": {"coordinates":[6.1488389969,46.2102851868],"type":"Point"}
}