{
  "type": "Feature",
  "properties": {
    "iso:country":"CH",
    "sg:address":"Limmatquai 94 8001 Z\u00fcrich. Postfach",
    "sg:city":"Z\u00fcrich",
    "sg:orig_category":"Advokaturb\u00fcros",
    "sg:phone":"+41 12511020",
    "sg:postcode":"8025",
    "wof:name":"Schmid & Staffelbach Advokaturb\u00fcro",
    "wof:placetype":"venue"
},
  "geometry": {"coordinates":[8.543092,47.374203],"type":"Point"}
}