{
  "type": "Feature",
  "properties": {
    "iso:country":"CH",
    "sg:address":"Gasterstrasse 66",
    "sg:city":"Kaltbrunn",
    "sg:orig_category":"Handels-H\u00e4user U Gesellschaften",
    "sg:postcode":"8722",
    "sg:province":"St. Gallen",
    "wof:name":"Thoma-furger Consulting & Trading",
    "wof:placetype":"venue"
},
  "geometry": {"coordinates":[9.0326786041,47.2083930969],"type":"Point"}
}