{
  "type": "Feature",
  "properties": {
    "addr:full":"Allemannweg 5 Chur Graubunden 7000",
    "addr:housenumber":"5",
    "addr:postcode":"7000",
    "addr:street":"Allemannweg",
    "iso:country":"CH",
    "sg:address":"Allemannweg 5",
    "sg:city":"Chur",
    "sg:orig_category":"Arbeitnehmerverb\u00e4nde",
    "sg:phone":"+41 81 284 82 86",
    "sg:postcode":"7000",
    "sg:province":"Graubunden",
    "wof:name":"Schweiz.maschinensetzerverband Sekt.chur,herrn F.rusterholz",
    "wof:placetype":"venue"
},
  "geometry": {"coordinates":[9.518237,46.85471],"type":"Point"}
}