{
  "type": "Feature",
  "properties": {
    "addr:full":"Baslerstrasse 66 4600 Olten. Postfach Olten Solothurn 4603",
    "addr:housenumber":"66",
    "addr:postcode":"4600 olten. postfach;4603",
    "addr:street":"Baslerstrasse",
    "iso:country":"CH",
    "sg:address":"Baslerstrasse 66 4600 Olten. Postfach",
    "sg:city":"Olten",
    "sg:orig_category":"Arbeitnehmerverb\u00e4nde",
    "sg:phone":"+41 62 212 02 32",
    "sg:postcode":"4603",
    "sg:province":"Solothurn",
    "wof:name":"Kaufm\u00e4nnischer Verein Olten Vereinssekretariat",
    "wof:placetype":"venue"
},
  "geometry": {"coordinates":[7.902748,47.352741],"type":"Point"}
}