{
  "type": "Feature",
  "properties": {
    "iso:country":"CH",
    "sg:address":"Gaswerkstrasse 16",
    "sg:city":"Frauenfeld",
    "sg:orig_category":"Bauingenieurb\u00fcros Heizung L\u00fcftung Klima Bauingenieurb\u00fcros Sanit\u00e4r",
    "sg:phone":"+41 17161000",
    "sg:postcode":"8500",
    "sg:province":"Thurgau",
    "wof:name":"Hp Engineering Gmbh",
    "wof:placetype":"venue"
},
  "geometry": {"coordinates":[8.538592,47.316364],"type":"Point"}
}