{
  "type": "Feature",
  "properties": {
    "iso:country":"CH",
    "sg:address":"Rue Des Pierres-du-niton 17 1200 Genf. Postfach",
    "sg:city":"Gen\u00e8ve",
    "sg:orig_category":"Architektur U Ingenieurb\u00fcros",
    "sg:postcode":"1207",
    "sg:province":"Gen\u00e8ve",
    "wof:name":"Cliveden Petroleum Sa",
    "wof:placetype":"venue"
},
  "geometry": {"coordinates":[6.157372,46.203674],"type":"Point"}
}