{
  "type": "Feature",
  "properties": {
    "addr:full":"Avenue Du Grand-st-bernard 6 Martigny Valais 1920",
    "addr:housenumber":"6",
    "addr:postcode":"1920",
    "addr:street":"Avenue Du Grand-St-Bernard",
    "iso:country":"CH",
    "sg:address":"Avenue Du Grand-st-bernard 6",
    "sg:city":"Martigny",
    "sg:orig_category":"Autospenglereien",
    "sg:phone":"+41 27 722 25 40",
    "sg:postcode":"1920",
    "sg:province":"Valais",
    "wof:name":"Pierre Germano Carrosserie",
    "wof:placetype":"venue"
},
  "geometry": {"coordinates":[7.071013,46.100784],"type":"Point"}
}