{
  "type": "Feature",
  "properties": {
    "iso:country":"CH",
    "sg:address":"F\u00fcllerichstrasse 15",
    "sg:city":"G\u00fcmligen",
    "sg:orig_category":"Erbringung von sonstigen Dienstleistungen f\u00fcr Unternehmen",
    "sg:phone":"+41 31 352 90 41",
    "sg:postcode":"3073",
    "sg:province":"Bern",
    "wof:name":"Greth Schmalzl Architektur-modellbau",
    "wof:placetype":"venue"
},
  "geometry": {"coordinates":[7.4980778694,46.9325866699],"type":"Point"}
}