{
  "type": "Feature",
  "properties": {
    "iso:country":"CH",
    "sg:address":"1555",
    "sg:city":"Villarzel",
    "sg:orig_category":"Landw. Genossenschaften Viehzucht",
    "sg:postcode":"1555",
    "sg:province":"Vaud",
    "wof:name":"Syndicat D'\u00e9levage De La Race Tachet\u00e9e Rouge",
    "wof:placetype":"venue"
},
  "geometry": {"coordinates":[6.8259902,46.523311615],"type":"Point"}
}