{
  "type": "Feature",
  "properties": {
    "iso:country":"CH",
    "sg:address":"Rue D'italie 11",
    "sg:city":"Gen\u00e8ve",
    "sg:orig_category":"Grosshandel mit festen Brennstoffen U Mineral\u00f6lerzeugnissen Handelsvermittlung von Brennstoffen, Erz",
    "sg:phone":"+41 22 311 54 54",
    "sg:postcode":"1204",
    "sg:province":"Gen\u00e8ve",
    "wof:name":"Petroleum Resources (petrus) Sa",
    "wof:placetype":"venue"
},
  "geometry": {"coordinates":[6.1510128975,46.2032814026],"type":"Point"}
}