{
  "type": "Feature",
  "properties": {
    "iso:country":"CH",
    "sg:address":"Limmatquai 112",
    "sg:city":"Z\u00fcrich",
    "sg:orig_category":"Finanzierungsinstitutionen",
    "sg:phone":"+41 12548080",
    "sg:postcode":"8001",
    "sg:province":"Z\u00fcrich",
    "wof:name":"Lasalle Brokerage Ag Finanzierung V. Gesellschaften",
    "wof:placetype":"venue"
},
  "geometry": {"coordinates":[8.5434646606,47.3751564026],"type":"Point"}
}