{
  "type": "Feature",
  "properties": {
    "iso:country":"CH",
    "sg:address":"Galgenb\u00fchl-weg 2 3770 Zweisimmen. Postfach 367",
    "sg:city":"Zweisimmen",
    "sg:orig_category":"Betrieb von Taxis Reiseb\u00fcros U Reiseveranstalter",
    "sg:phone":"+41 79 449 06 32",
    "sg:postcode":"3770",
    "sg:province":"Bern",
    "wof:name":"Jakob Wieland Ag Sch\u00fclertransporte",
    "wof:placetype":"venue"
},
  "geometry": {"coordinates":[7.108453,46.925232],"type":"Point"}
}