{
  "type": "Feature",
  "properties": {
    "iso:country":"CH",
    "sg:address":"Chemin Delay 25 1217 Meyrin. Postfach",
    "sg:city":"Meyrin",
    "sg:orig_category":"Instandhaltung U Reparatur von Automobilen",
    "sg:postcode":"1217",
    "sg:province":"Gen\u00e8ve",
    "wof:name":"Centre Automobile Colarusso Fr\u00e8res",
    "wof:placetype":"venue"
},
  "geometry": {"coordinates":[6.0765900612,46.2207984924],"type":"Point"}
}