{
  "type": "Feature",
  "properties": {
    "iso:country":"CH",
    "sg:address":"R\u00fcssenstr. 16",
    "sg:city":"Baar",
    "sg:classifiers":[
        {
            "category":"Manufacturing",
            "subcategory":"Chemicals & Compounds",
            "type":"Manufacturing & Wholesale Goods"
        }
    ],
    "sg:phone":"+41 41 761 60 30",
    "sg:postcode":"6340",
    "sg:province":"Zug",
    "sg:tags":[
        "pharmaceutical",
        "chemistry"
    ],
    "wof:name":"Alcor Chemie Holding Ag",
    "wof:placetype":"venue"
},
  "geometry": {"coordinates":[8.563418,47.212181],"type":"Point"}
}