{
  "type": "Feature",
  "properties": {
    "iso:country":"CH",
    "sg:address":"Hauptstrasse 55",
    "sg:city":"Derendingen",
    "sg:orig_category":"RESTAURANTS: TEA-ROOMS",
    "sg:phone":"+41 32 682 20 87",
    "sg:postcode":"4552",
    "sg:province":"Solothurn",
    "wof:name":"B\u00fcchi-eggler Nelly",
    "wof:placetype":"venue"
},
  "geometry": {"coordinates":[7.586689949,47.1935882568],"type":"Point"}
}