{
  "type": "Feature",
  "properties": {
    "addr:full":"Sulgeneckstrasse 38 Bern Bern 3007",
    "addr:housenumber":"38",
    "addr:postcode":"3007",
    "addr:street":"Sulgeneckstrasse",
    "iso:country":"CH",
    "sg:address":"Sulgeneckstrasse 38",
    "sg:city":"Bern",
    "sg:orig_category":"Advokaturb\u00fcros",
    "sg:phone":"+41 32 725 77 78",
    "sg:postcode":"3007",
    "sg:province":"Bern",
    "wof:name":"Daniel Perdrizat Etude D'avocat",
    "wof:placetype":"venue"
},
  "geometry": {"coordinates":[6.930358,46.991783],"type":"Point"}
}