{
  "type": "Feature",
  "properties": {
    "iso:country":"CH",
    "sg:address":"Dr. Schneider-strasse 1",
    "sg:city":"Nidau",
    "sg:orig_category":"Instandhaltung U Reparatur von Automobilen",
    "sg:phone":"+41 32 331 13 40",
    "sg:postcode":"2560",
    "sg:province":"Bern",
    "wof:name":"Garage Baumgartner",
    "wof:placetype":"venue"
},
  "geometry": {"coordinates":[7.2397909164,47.1290054321],"type":"Point"}
}