{
  "type": "Feature",
  "properties": {
    "iso:country":"CH",
    "sg:address":"Bahnhofstrasse 2",
    "sg:city":"Ermatingen",
    "sg:orig_category":"RESTAURANTS: TEA-ROOMS",
    "sg:postcode":"8272",
    "sg:province":"Thurgau",
    "wof:name":"Hildebar Gmbh",
    "wof:placetype":"venue"
},
  "geometry": {"coordinates":[9.0842924118,47.6697349548],"type":"Point"}
}