{
  "type": "Feature",
  "properties": {
    "iso:country":"CH",
    "sg:address":"Fach H\u00f6henweg 14b",
    "sg:city":"Sattel",
    "sg:orig_category":"Unclassifiable Establishments",
    "sg:postcode":"6417",
    "sg:province":"Schwyz",
    "wof:name":"Weber Gartencenter Gmbh",
    "wof:placetype":"venue"
},
  "geometry": {"coordinates":[8.2831048965,47.4908676147],"type":"Point"}
}