{
  "type": "Feature",
  "properties": {
    "iso:country":"CH",
    "sg:address":"Hauptstrasse 22",
    "sg:city":"Kreuzlingen",
    "sg:orig_category":"Kauf U Verkauf von Immobilien auf eigene Rechnung Restaurants",
    "sg:phone":"+41 71 672 61 61",
    "sg:postcode":"8280",
    "sg:province":"Thurgau",
    "wof:name":"Elite A.g. Kreuzlingen.",
    "wof:placetype":"venue"
},
  "geometry": {"coordinates":[9.1736078262,47.6524772644],"type":"Point"}
}