{
  "type": "Feature",
  "properties": {
    "iso:country":"CH",
    "sg:address":"Obere Hauptgasse 65",
    "sg:city":"Thun",
    "sg:orig_category":"Sonstige Aktivit\u00e4ten der nicht-\u00e4rztlichen Medizinalberufe",
    "sg:phone":"+41 19101374",
    "sg:postcode":"3600",
    "sg:province":"Bern",
    "wof:name":"Susanne Brandenberger Kinesiologie",
    "wof:placetype":"venue"
},
  "geometry": {"coordinates":[8.5920581818,47.3057975769],"type":"Point"}
}