{
  "type": "Feature",
  "properties": {
    "iso:country":"CH",
    "sg:address":"Kirchrain 24 8816 Hirzel. Postfach",
    "sg:city":"Hirzel",
    "sg:orig_category":"Verwaltung von Immobilien",
    "sg:phone":"+41 17299196",
    "sg:postcode":"8816",
    "sg:province":"Z\u00fcrich",
    "wof:name":"Feierabend Kurt Immobilien, Wasserwerk Und Kantine",
    "wof:placetype":"venue"
},
  "geometry": {"coordinates":[8.6077136993,47.2176246643],"type":"Point"}
}