{
  "type": "Feature",
  "properties": {
    "addr:full":"Kantonsstrasse 2 Altishofen Luzern 6246",
    "addr:housenumber":"2",
    "addr:postcode":"6246",
    "addr:street":"Kantonsstrasse",
    "iso:country":"CH",
    "sg:address":"Kantonsstrasse 2",
    "sg:city":"Altishofen",
    "sg:orig_category":"Autotransporte international",
    "sg:phone":"+41 62 748 80 80",
    "sg:postcode":"6246",
    "sg:province":"Luzern",
    "wof:name":"Galliker Transport Ag",
    "wof:placetype":"venue"
},
  "geometry": {"coordinates":[7.971441,47.200443],"type":"Point"}
}