{
  "type": "Feature",
  "properties": {
    "iso:country":"CH",
    "sg:city":"Oberhofen",
    "sg:orig_category":"Reisen, Reiseveranstalter",
    "sg:phone":"+41 33 243 27 50",
    "sg:postcode":"3653",
    "sg:province":"Bern",
    "wof:name":"Mtb Online Destination Management For Europe",
    "wof:placetype":"venue"
},
  "geometry": {"coordinates":[7.6667,46.733299],"type":"Point"}
}