{
  "type": "Feature",
  "properties": {
    "iso:country":"CH",
    "sg:address":"5025",
    "sg:city":"Asp",
    "sg:orig_category":"Vereine Musik/Blasmusik",
    "sg:phone":"+41 62 878 10 69",
    "sg:postcode":"5025",
    "sg:province":"Aargau",
    "wof:name":"Musikgesellschaft",
    "wof:placetype":"venue"
},
  "geometry": {"coordinates":[8.0537996292,47.4421386719],"type":"Point"}
}