{
  "type": "Feature",
  "properties": {
    "iso:country":"CH",
    "sg:address":"Solari Via Dei",
    "sg:city":"Lugano",
    "sg:orig_category":"Herstellung von Anstrichmitteln, Druckfarben U Kitten",
    "sg:phone":"+41 91 922 97 25",
    "sg:postcode":"6900",
    "sg:province":"Ticino",
    "wof:name":"Solnok Sa",
    "wof:placetype":"venue"
},
  "geometry": {"coordinates":[8.950220108,46.0036506653],"type":"Point"}
}