{
  "type": "Feature",
  "properties": {
    "iso:country":"CH",
    "sg:address":"Rue Jean-pelletier 6 1225 Ch\u00eane-bourg Case Postale 157",
    "sg:city":"Ch\u00eane-bourg",
    "sg:orig_category":"Architektur U Ingenieurb\u00fcros Architekturb\u00fcros",
    "sg:phone":"+41 22 348 36 80",
    "sg:postcode":"1225",
    "sg:province":"Gen\u00e8ve",
    "wof:name":"U. Tschumi - M. Heurteux, Architectes Associ\u00e9s Sa",
    "wof:placetype":"venue"
},
  "geometry": {"coordinates":[6.193654,46.193851],"type":"Point"}
}