{
  "type": "Feature",
  "properties": {
    "iso:country":"CH",
    "sg:address":"Esslingerstrasse 8",
    "sg:city":"M\u00f6nchaltorf",
    "sg:orig_category":"Verwaltung von Immobilien Wirtschaftspr\u00fcfung, Steuerberatung U Treuhand",
    "sg:phone":"+41 19480330",
    "sg:postcode":"8617",
    "sg:province":"Z\u00fcrich",
    "wof:name":"Treuhand Und Verwaltungspraxis Pfister Werner",
    "wof:placetype":"venue"
},
  "geometry": {"coordinates":[8.7212572098,47.3083343506],"type":"Point"}
}