{
  "type": "Feature",
  "properties": {
    "iso:country":"CH",
    "sg:address":"Via Ai Grotti 6862 Rancate Casella Postale 33",
    "sg:city":"Rancate",
    "sg:orig_category":"Detailhandel mit Bekleidung",
    "sg:phone":"+41 91 646 89 31",
    "sg:postcode":"6862",
    "sg:province":"Ticino",
    "wof:name":"Lior Sa",
    "wof:placetype":"venue"
},
  "geometry": {"coordinates":[8.968135,45.871498],"type":"Point"}
}