{
  "type": "Feature",
  "properties": {
    "iso:country":"CH",
    "sg:address":"Octodure Rue D' 11",
    "sg:city":"Martigny",
    "sg:orig_category":"Gesundheitswesen",
    "sg:phone":"+41 79 220 73 73",
    "sg:postcode":"1920",
    "sg:province":"Valais",
    "wof:name":"Alpha-rh\u00f4ne Sa",
    "wof:placetype":"venue"
},
  "geometry": {"coordinates":[7.0729198456,46.1013793945],"type":"Point"}
}