{
  "type": "Feature",
  "properties": {
    "iso:country":"CH",
    "sg:address":"Algierstrasse 9",
    "sg:city":"Zufikon",
    "sg:orig_category":"Unternehmensberatung",
    "sg:phone":"+41 56 633 77 51",
    "sg:postcode":"5621",
    "sg:province":"Aargau",
    "wof:name":"Dr.florian Studer Unternehmensberatung",
    "wof:placetype":"venue"
},
  "geometry": {"coordinates":[8.3554964066,47.3409004211],"type":"Point"}
}