{
  "type": "Feature",
  "properties": {
    "iso:country":"CH",
    "sg:address":"Solothurnerstrasse 59 4000 Basel. Postfach",
    "sg:city":"Basel",
    "sg:orig_category":"G\u00fcterbef\u00f6rderung im Strassenverkehr",
    "sg:phone":"+41 61 361 63 53",
    "sg:postcode":"4002",
    "sg:province":"Basel-Stadt",
    "wof:name":"Moser Ag Warentransporte Im In Und Ausland, Verzollungen Und Lagerungen",
    "wof:placetype":"venue"
},
  "geometry": {"coordinates":[7.5899238586,47.5433387756],"type":"Point"}
}