{
  "type": "Feature",
  "properties": {
    "iso:country":"CH",
    "sg:address":"Haute-brise Chemin De 16",
    "sg:city":"Mont-sur-lausanne",
    "sg:orig_category":"Allgemeiner Hoch U Tiefbau",
    "sg:postcode":"1052",
    "sg:province":"Vaud",
    "wof:name":"Gasser, Construction Et G\u00e9nie Civil Sa",
    "wof:placetype":"venue"
},
  "geometry": {"coordinates":[6.635395,46.556896],"type":"Point"}
}