{
  "type": "Feature",
  "properties": {
    "iso:country":"CH",
    "sg:address":"Route De Tranchepied 35",
    "sg:city":"Borex",
    "sg:orig_category":"Grosshandel mit Parf\u00fcmerieartikeln U K\u00f6rperpflegemitteln Grosshandel mit Textilien",
    "sg:phone":"+41 79 212 16 60",
    "sg:postcode":"1277",
    "sg:province":"Vaud",
    "wof:name":"Favige Sa",
    "wof:placetype":"venue"
},
  "geometry": {"coordinates":[6.1727099419,46.3835525513],"type":"Point"}
}