{
  "type": "Feature",
  "properties": {
    "iso:country":"CH",
    "sg:address":"Lielistrasse 2a",
    "sg:city":"Birmensdorf",
    "sg:classifiers":[
        {
            "category":"Banks & Credit Unions",
            "subcategory":"Bank",
            "type":"Services"
        }
    ],
    "sg:phone":"+41 17370606",
    "sg:postcode":"8903",
    "sg:province":"Z\u00fcrich",
    "wof:name":"Z\u00fcrcher Kantonalbank",
    "wof:placetype":"venue"
},
  "geometry": {"coordinates":[8.436379,47.353134],"type":"Point"}
}