{
  "type": "Feature",
  "properties": {
    "iso:country":"CH",
    "sg:address":"Leimgr\u00fcbelstrasse 18",
    "sg:city":"Z\u00fcrich",
    "sg:orig_category":"Vereine Quartier",
    "sg:postcode":"8052",
    "sg:province":"Z\u00fcrich",
    "wof:name":"Quartierverein Seebach",
    "wof:placetype":"venue"
},
  "geometry": {"coordinates":[8.5432500839,47.4287605286],"type":"Point"}
}