{
  "type": "Feature",
  "properties": {
    "iso:country":"CH",
    "sg:address":"Rue Bel-air 2 2350 Saignel\u00e9gier. Postfach",
    "sg:city":"Saignel\u00e9gier",
    "sg:classifiers":[
        {
            "category":"Restaurant",
            "type":"Food & Drink"
        }
    ],
    "sg:phone":"+41 32 725 14 10",
    "sg:postcode":"2350",
    "sg:province":"Jura",
    "wof:name":"Caf\u00e9 Du Jura",
    "wof:placetype":"venue"
},
  "geometry": {"coordinates":[6.9296488762,46.9904022217],"type":"Point"}
}