{
  "type": "Feature",
  "properties": {
    "iso:country":"CH",
    "sg:address":"Kreuzstrasse 32 8712 St\u00e4fa. Postfach",
    "sg:city":"St\u00e4fa",
    "sg:orig_category":"Erwachsenenbildung U Unterricht",
    "sg:postcode":"8712",
    "sg:province":"Z\u00fcrich",
    "wof:name":"Gremminger Consulting Gmbh Beratungen Und Dienstleistungen Im Bereich Management, Marketing Usw",
    "wof:placetype":"venue"
},
  "geometry": {"coordinates":[8.7311687469,47.2377128601],"type":"Point"}
}