{
  "type": "Feature",
  "properties": {
    "iso:country":"CH",
    "sg:address":"Rebgasse 17",
    "sg:city":"Basel",
    "sg:orig_category":"Fachdetailhandel in Verkaufsr\u00e4umen",
    "sg:postcode":"4058",
    "sg:province":"Basel-Stadt",
    "wof:name":"Green Corner Gmbh",
    "wof:placetype":"venue"
},
  "geometry": {"coordinates":[7.594865799,47.5604972839],"type":"Point"}
}