{
  "type": "Feature",
  "properties": {
    "addr:full":"Grebelackerstrasse 7 Z\u00fcrich Z\u00fcrich 8057",
    "addr:housenumber":"7",
    "addr:postcode":"8057",
    "addr:street":"Grebelackerstrasse",
    "iso:country":"CH",
    "sg:address":"Grebelackerstrasse 7",
    "sg:city":"Z\u00fcrich",
    "sg:orig_category":"Airbrush Work, Illustrations, Designs",
    "sg:phone":"+41 13620707",
    "sg:postcode":"8057",
    "sg:province":"Z\u00fcrich",
    "wof:name":"Trickfilmladen",
    "wof:placetype":"venue"
},
  "geometry": {"coordinates":[8.536787,47.400066],"type":"Point"}
}