{
  "type": "Feature",
  "properties": {
    "iso:country":"CH",
    "sg:address":"Gestade",
    "sg:city":"Raron",
    "sg:orig_category":"Handel, Instandhaltung U Reparatur von Automobilen Instandhaltung U Reparatur von Automobilen Tankst",
    "sg:phone":"+41 27 934 55 11",
    "sg:postcode":"3942",
    "sg:province":"Valais",
    "wof:name":"Hadi Hess Auto Drive And Investment",
    "wof:placetype":"venue"
},
  "geometry": {"coordinates":[7.803355217,46.3093414307],"type":"Point"}
}