{
  "type": "Feature",
  "properties": {
    "iso:country":"CH",
    "sg:address":"Bahnhofstrasse 60",
    "sg:city":"Spreitenbach",
    "sg:orig_category":"Sonstiger Grosshandel",
    "sg:postcode":"8957",
    "sg:province":"Aargau",
    "wof:name":"Icc Amadeo Drigatti",
    "wof:placetype":"venue"
},
  "geometry": {"coordinates":[8.3633394241,47.4231681824],"type":"Point"}
}