{
  "type": "Feature",
  "properties": {
    "iso:country":"CH",
    "sg:address":"Fleischengasse 7 7206 Igis. Postfach",
    "sg:city":"Igis",
    "sg:orig_category":"Schaustellergewerbe U Vergn\u00fcgungsparks",
    "sg:postcode":"7206",
    "sg:province":"Graubunden",
    "wof:name":"Cindarella - Agentur - Dermon Artisten, Artistinnen, K\u00fcnstler; Vermittlung",
    "wof:placetype":"venue"
},
  "geometry": {"coordinates":[9.5762395859,46.9459152222],"type":"Point"}
}