{
  "type": "Feature",
  "properties": {
    "iso:country":"CH",
    "sg:address":"Alchisgraben 2572 Sutz. Postfach",
    "sg:city":"Sutz",
    "sg:orig_category":"Fachdetailhandel in Verkaufsr\u00e4umen Herstellung von Verbrennungsmotoren U Turbinen ohne Motoren f\u00fcr L",
    "sg:phone":"+41 32 397 53 55",
    "sg:postcode":"2572",
    "sg:province":"Bern",
    "wof:name":"Stoller Bootsmotoren Gmbh Boote, Bootsmotoren; Handel, Unterhalt",
    "wof:placetype":"venue"
},
  "geometry": {"coordinates":[7.2145090103,47.0947036743],"type":"Point"}
}