{
  "type": "Feature",
  "properties": {
    "iso:country":"CH",
    "sg:address":"Himmelrichstrasse 7",
    "sg:city":"Horn",
    "sg:orig_category":"Vorschulen, Kinderg\u00e4rten",
    "sg:phone":"+41 71 841 68 39",
    "sg:postcode":"9326",
    "sg:province":"Thurgau",
    "wof:name":"Kindergarten Oberdorf I & Ii",
    "wof:placetype":"venue"
},
  "geometry": {"coordinates":[9.4610862732,47.491771698],"type":"Point"}
}