{
  "type": "Feature",
  "properties": {
    "iso:country":"CH",
    "sg:address":"Limmatquai 16",
    "sg:city":"Z\u00fcrich",
    "sg:orig_category":"Kinos",
    "sg:phone":"+41 12505520",
    "sg:postcode":"8001",
    "sg:province":"Z\u00fcrich",
    "wof:name":"Kino Nord-s\u00fcd Studio",
    "wof:placetype":"venue"
},
  "geometry": {"coordinates":[8.5437297821,47.3689346313],"type":"Point"}
}