{
  "type": "Feature",
  "properties": {
    "addr:full":"In Der M\u00fchle 2 Hinwil Z\u00fcrich 8340",
    "addr:housenumber":"2",
    "addr:postcode":"8340",
    "addr:street":"In Der Muehle",
    "iso:country":"CH",
    "sg:address":"In Der M\u00fchle 2",
    "sg:city":"Hinwil",
    "sg:classifiers":[
        {
            "category":"Food & Beverages",
            "subcategory":"Specialty",
            "type":"Retail Goods"
        }
    ],
    "sg:phone":"+41 19375155",
    "sg:postcode":"8340",
    "sg:province":"Z\u00fcrich",
    "sg:tags":[
        "caterer"
    ],
    "wof:name":"Brunoldi Catering, Sprenger Beat Party-service, Betriebsverpflegung",
    "wof:placetype":"venue"
},
  "geometry": {"coordinates":[8.845827,47.302731],"type":"Point"}
}