{
  "type": "Feature",
  "properties": {
    "iso:country":"CH",
    "sg:address":"Chemin De Tr\u00e8fle-blanc 18",
    "sg:city":"Plan-les-ouates",
    "sg:orig_category":"Fernmeldedienste Herstellung von Radio U Fernsehger\u00e4ten sowie phono U videotechnischen Ger\u00e4ten",
    "sg:phone":"+41 22 580 70 11",
    "sg:postcode":"1228",
    "sg:province":"Gen\u00e8ve",
    "wof:name":"Mci Worldcom Sa",
    "wof:placetype":"venue"
},
  "geometry": {"coordinates":[6.1268401146,46.1714057922],"type":"Point"}
}