{
  "type": "Feature",
  "properties": {
    "iso:country":"CH",
    "sg:address":"1972 Anz\u00e8re Case Postale 33",
    "sg:city":"Anz\u00e8re",
    "sg:orig_category":"Sportschulen Gleitschirm-& Deltaflugschulen",
    "sg:phone":"+41 27 398 52 24",
    "sg:postcode":"1972",
    "sg:province":"Valais",
    "wof:name":"Ecole De Parapente Du Valais Central",
    "wof:placetype":"venue"
},
  "geometry": {"coordinates":[7.4004211426,46.2969818115],"type":"Point"}
}