{
  "type": "Feature",
  "properties": {
    "iso:country":"CH",
    "sg:address":"Thorenbergstrasse 44",
    "sg:city":"Littau",
    "sg:orig_category":"G\u00fcterbef\u00f6rderung im Strassenverkehr",
    "sg:phone":"+41 41 250 44 33",
    "sg:postcode":"6014",
    "sg:province":"Luzern",
    "wof:name":"Brunner Martin Transport Ag",
    "wof:placetype":"venue"
},
  "geometry": {"coordinates":[8.2565393448,47.0552062988],"type":"Point"}
}