{
  "type": "Feature",
  "properties": {
    "iso:country":"CH",
    "sg:address":"Gottardo Via San",
    "sg:city":"Cadenazzo",
    "sg:orig_category":"Autoreiseunternehmen Pensionskassen",
    "sg:phone":"+41 56 485 82 60",
    "sg:postcode":"6593",
    "sg:province":"Ticino",
    "wof:name":"Personalf\u00fcrsorgestiftung Der Twerenbold Reisen + Transport Ag",
    "wof:placetype":"venue"
},
  "geometry": {"coordinates":[8.31325,47.406349],"type":"Point"}
}