{
  "type": "Feature",
  "properties": {
    "iso:country":"CH",
    "sg:address":"Fliederweg 5",
    "sg:city":"Uetendorf",
    "sg:orig_category":"Sportvereine Sch\u00fctzen",
    "sg:phone":"+41 34 461 29 35",
    "sg:postcode":"3661",
    "sg:province":"Bern",
    "wof:name":"Feldsch\u00fctzen L\u00fctzelfl\u00fch",
    "wof:placetype":"venue"
},
  "geometry": {"coordinates":[7.6784501076,47.0036315918],"type":"Point"}
}