{
  "type": "Feature",
  "properties": {
    "iso:country":"CH",
    "sg:address":"Avenue De La Gare 7 1860 Aigle Case Postale 277",
    "sg:city":"Aigle",
    "sg:orig_category":"Notariate",
    "sg:phone":"+41 79 355 32 32",
    "sg:postcode":"1860",
    "sg:province":"Vaud",
    "wof:name":"Charles-pascal Ghiringhelli Etude De Notaire",
    "wof:placetype":"venue"
},
  "geometry": {"coordinates":[6.9677047729,46.3177642822],"type":"Point"}
}