{
  "type": "Feature",
  "properties": {
    "iso:country":"CH",
    "sg:address":"K\u00f6nizstrasse 238",
    "sg:city":"Liebefeld",
    "sg:orig_category":"Detailhandel mit Bekleidung Detailhandel mit Damenbekleidung",
    "sg:phone":"+41 31 311 05 96",
    "sg:postcode":"3097",
    "sg:province":"Bern",
    "wof:name":"Hosen Saloon Thommen Ag",
    "wof:placetype":"venue"
},
  "geometry": {"coordinates":[7.416268,46.929905],"type":"Point"}
}