{
  "type": "Feature",
  "properties": {
    "iso:country":"CH",
    "sg:address":"Bahnhofstrasse 4",
    "sg:city":"Berikon",
    "sg:orig_category":"Sonstige Kultur U Unterhaltungseinrichtungen",
    "sg:phone":"+41 56 631 75 43",
    "sg:postcode":"8965",
    "sg:province":"Aargau",
    "wof:name":"Jugendtreff Mutschellen",
    "wof:placetype":"venue"
},
  "geometry": {"coordinates":[8.3690757751,47.3529777527],"type":"Point"}
}