{
  "type": "Feature",
  "properties": {
    "iso:country":"CH",
    "sg:address":"Chemin Neuf 9",
    "sg:city":"Chamoson",
    "sg:orig_category":"Landesverteidigung, Sozialversicherung \u00d6ffentliche Verwaltung",
    "sg:phone":"+41 27 306 52 32",
    "sg:postcode":"1955",
    "sg:province":"Valais",
    "wof:name":"Centre De Protection Civile",
    "wof:placetype":"venue"
},
  "geometry": {"coordinates":[7.2232170105,46.2014274597],"type":"Point"}
}