{
  "type": "Feature",
  "properties": {
    "iso:country":"CH",
    "sg:address":"Gladbachstrasse 74",
    "sg:city":"Z\u00fcrich",
    "sg:orig_category":"Herstellung von sonstigen Metallwaren Mechanische Werkst\u00e4tten",
    "sg:phone":"+41 32 841 25 25",
    "sg:postcode":"8044",
    "sg:province":"Z\u00fcrich",
    "wof:name":"Hauser J. & Cie",
    "wof:placetype":"venue"
},
  "geometry": {"coordinates":[6.8808541298,46.9838027954],"type":"Point"}
}