{
  "type": "Feature",
  "properties": {
    "iso:country":"CH",
    "sg:address":"Rainstrasse 8",
    "sg:city":"Unter\u00e4geri",
    "sg:orig_category":"Unternehmensberatung",
    "sg:phone":"+41 79 302 96 74",
    "sg:postcode":"6314",
    "sg:province":"Zug",
    "wof:name":"Zellerengineering Gmbh",
    "wof:placetype":"venue"
},
  "geometry": {"coordinates":[8.5785894394,47.1358261108],"type":"Point"}
}