{
  "type": "Feature",
  "properties": {
    "iso:country":"CH",
    "sg:address":"Bahnhofstr. 3",
    "sg:city":"Z\u00fcrich",
    "sg:classifiers":[
        {
            "category":"Banks & Credit Unions",
            "subcategory":"Bank",
            "type":"Services"
        }
    ],
    "sg:phone":"+41 12837111",
    "sg:postcode":"8022",
    "sg:province":"Z\u00fcrich",
    "wof:name":"Bank J. Vontobel & Co Ag",
    "wof:placetype":"venue"
},
  "geometry": {"coordinates":[8.539848,47.367672],"type":"Point"}
}