{
  "type": "Feature",
  "properties": {
    "iso:country":"CH",
    "sg:address":"Chemin Thury 12 1200 Genf. Postfach",
    "sg:city":"Gen\u00e8ve",
    "sg:orig_category":"Finanzierungsinstitutionen",
    "sg:postcode":"1206",
    "sg:province":"Gen\u00e8ve",
    "wof:name":"Futures Brokerage Inc Sa",
    "wof:placetype":"venue"
},
  "geometry": {"coordinates":[6.1514201164,46.1911430359],"type":"Point"}
}