{
  "type": "Feature",
  "properties": {
    "iso:country":"CH",
    "sg:address":"Birkenweg 5 6280 Hochdorf. Postfach 250",
    "sg:city":"Hochdorf",
    "sg:orig_category":"Sportvereine Ballsport Fussball",
    "sg:phone":"+41 41 910 04 39",
    "sg:postcode":"6281",
    "sg:province":"Luzern",
    "wof:name":"Fc Hochdorf",
    "wof:placetype":"venue"
},
  "geometry": {"coordinates":[8.2917337418,47.1684799194],"type":"Point"}
}