{
  "type": "Feature",
  "properties": {
    "iso:country":"CH",
    "sg:address":"Route Des Arsenaux 33",
    "sg:city":"Fribourg",
    "sg:orig_category":"Parkettleger",
    "sg:phone":"+41 26 424 00 02",
    "sg:postcode":"1700",
    "sg:province":"Fribourg",
    "wof:name":"S K Revetements De Sols S\u00e0rl Parquet",
    "wof:placetype":"venue"
},
  "geometry": {"coordinates":[7.1510500908,46.797077179],"type":"Point"}
}