{
  "type": "Feature",
  "properties": {
    "addr:full":"Hinterfeldstrasse 13 Laufen Basel-Landschaft 4242",
    "addr:housenumber":"13",
    "addr:postcode":"4242",
    "addr:street":"Hinterfeldstrasse",
    "iso:country":"CH",
    "sg:address":"Hinterfeldstrasse 13",
    "sg:city":"Laufen",
    "sg:orig_category":"Architektur U Ingenieurb\u00fcros",
    "sg:phone":"+41 61 761 15 15",
    "sg:postcode":"4242",
    "sg:province":"Basel-Landschaft",
    "wof:name":"Epl Energieplan Laufen Ag",
    "wof:placetype":"venue"
},
  "geometry": {"coordinates":[7.498944,47.420292],"type":"Point"}
}