{
  "type": "Feature",
  "properties": {
    "iso:country":"CH",
    "sg:address":"Dorfstrasse 2 3084 Wabern. Postfach",
    "sg:city":"Wabern",
    "sg:orig_category":"RESTAURANTS: TEA-ROOMS",
    "sg:postcode":"3084",
    "sg:province":"Bern",
    "wof:name":"Tai Yien Gmbh",
    "wof:placetype":"venue"
},
  "geometry": {"coordinates":[7.4477210045,46.9301452637],"type":"Point"}
}