{
  "type": "Feature",
  "properties": {
    "iso:country":"CH",
    "sg:address":"3655",
    "sg:city":"Sigriswil",
    "sg:classifiers":[
        {
            "category":"Education",
            "subcategory":"Vocational School",
            "type":"Public Place"
        }
    ],
    "sg:phone":"+41 61 751 28 44",
    "sg:postcode":"3655",
    "sg:province":"Bern",
    "sg:tags":[
        "koch-",
        "haushaltschulen"
    ],
    "wof:name":"Haushaltungsschule Aesch-pfeffingen",
    "wof:placetype":"venue"
},
  "geometry": {"coordinates":[7.5980701447,47.4669685364],"type":"Point"}
}