{
  "type": "Feature",
  "properties": {
    "addr:full":"Hauptstrasse 2 Affeltrangen Thurgau 9556",
    "addr:housenumber":"2",
    "addr:postcode":"9556",
    "addr:street":"Hauptstrasse",
    "iso:country":"CH",
    "sg:address":"Hauptstrasse 2",
    "sg:city":"Affeltrangen",
    "sg:orig_category":"Detailhandel mit Blumen U Pflanzen Fachdetailhandel in Verkaufsr\u00e4umen",
    "sg:phone":"+41 22 301 28 14",
    "sg:postcode":"9556",
    "sg:province":"Thurgau",
    "wof:name":"Les 5 Sens, Gaillard-albert V\u00e9ronique",
    "wof:placetype":"venue"
},
  "geometry": {"coordinates":[6.14042,46.184914],"type":"Point"}
}