{
  "type": "Feature",
  "properties": {
    "iso:country":"CH",
    "sg:address":"Dorfstrasse 8 9213 Hauptwil. Postfach",
    "sg:city":"Hauptwil",
    "sg:orig_category":"Elektroinstallation",
    "sg:phone":"+41 71 422 18 28",
    "sg:postcode":"9213",
    "sg:province":"Thurgau",
    "wof:name":"Elektro H\u00e4uselmann Ag",
    "wof:placetype":"venue"
},
  "geometry": {"coordinates":[9.25258255,47.4793510437],"type":"Point"}
}