{
  "type": "Feature",
  "properties": {
    "addr:full":"Dorfstrasse 266 Walde Aargau 5046",
    "addr:housenumber":"266",
    "addr:postcode":"5046",
    "addr:street":"Dorfstrasse",
    "iso:country":"CH",
    "sg:address":"Dorfstrasse 266",
    "sg:city":"Walde",
    "sg:classifiers":[
        {
            "category":"Manufacturing",
            "subcategory":"Tools & Machinery",
            "type":"Manufacturing & Wholesale Goods"
        }
    ],
    "sg:phone":"+41 62 726 23 06",
    "sg:postcode":"5046",
    "sg:province":"Aargau",
    "sg:tags":[
        "construction",
        "container",
        "apparatus"
    ],
    "wof:name":"Stb-montagen",
    "wof:placetype":"venue"
},
  "geometry": {"coordinates":[8.108515,47.262619],"type":"Point"}
}