{
  "type": "Feature",
  "properties": {
    "iso:country":"CH",
    "sg:address":"Nassacher 6",
    "sg:city":"Effretikon",
    "sg:orig_category":"Vereine Diverse",
    "sg:phone":"+41 52 343 27 96",
    "sg:postcode":"8307",
    "sg:province":"Z\u00fcrich",
    "wof:name":"Aktive Bisiker",
    "wof:placetype":"venue"
},
  "geometry": {"coordinates":[8.6939496994,47.4127044678],"type":"Point"}
}