{
  "type": "Feature",
  "properties": {
    "iso:country":"CH",
    "sg:address":"Brennerstrasse 12",
    "sg:city":"Allschwil",
    "sg:orig_category":"Non-Classified Establishments",
    "sg:postcode":"4123",
    "sg:province":"Basel-Landschaft",
    "wof:name":"Aerztehaus Allschwil Ag",
    "wof:placetype":"venue"
},
  "geometry": {"coordinates":[7.546107769,47.5477142334],"type":"Point"}
}