{
  "type": "Feature",
  "properties": {
    "iso:country":"CH",
    "sg:address":"Champs-pr\u00e9vost 30",
    "sg:city":"Vernier",
    "sg:orig_category":"Instandhaltung U Reparatur von Automobilen",
    "sg:phone":"+41 79 408 59 27",
    "sg:postcode":"1214",
    "sg:province":"Gen\u00e8ve",
    "wof:name":"Dominik Steiner Autoelektro",
    "wof:placetype":"venue"
},
  "geometry": {"coordinates":[8.4415683746,47.0812110901],"type":"Point"}
}