{
  "type": "Feature",
  "properties": {
    "iso:country":"CH",
    "sg:address":"1675",
    "sg:city":"Vauderens",
    "sg:orig_category":"Allgemeiner Hoch U Tiefbau",
    "sg:phone":"+41 21095101",
    "sg:postcode":"1675",
    "sg:province":"Fribourg",
    "wof:name":"Deschenaux Pierre, Entreprise De Construction",
    "wof:placetype":"venue"
},
  "geometry": {"coordinates":[6.85081,46.622532],"type":"Point"}
}