{
  "type": "Feature",
  "properties": {
    "iso:country":"CH",
    "sg:address":"R\u00fctistrasse 15",
    "sg:city":"D\u00fcrnten",
    "sg:orig_category":"Grosshandel mit lebenden Tieren",
    "sg:phone":"+41 55 240 68 31",
    "sg:postcode":"8635",
    "sg:province":"Z\u00fcrich",
    "wof:name":"Robert Hess Viehhandel",
    "wof:placetype":"venue"
},
  "geometry": {"coordinates":[8.845580101,47.275806427],"type":"Point"}
}