{
  "type": "Feature",
  "properties": {
    "iso:country":"CH",
    "sg:address":"Buchenstrasse 20",
    "sg:city":"Herisau",
    "sg:orig_category":"Allgemeiner Hoch U Tiefbau Strassenbau",
    "sg:phone":"+41 71 351 31 36",
    "sg:postcode":"9100",
    "sg:province":"Appenzell Ausserrhoden",
    "wof:name":"Kaufmann & Co",
    "wof:placetype":"venue"
},
  "geometry": {"coordinates":[9.281941,47.387512],"type":"Point"}
}