{
  "type": "Feature",
  "properties": {
    "iso:country":"CH",
    "sg:address":"Bundesplatz 10 6300 Zug. Postfach 5330 6305 Zug",
    "sg:city":"Annahme",
    "sg:orig_category":"Fachdetailhandel mit pharmazeutischen Produkten",
    "sg:phone":"+41 41 729 50 60",
    "sg:postcode":"5",
    "wof:name":"Wyss Pharma Ag Apotheke",
    "wof:placetype":"venue"
},
  "geometry": {"coordinates":[8.5151939392,47.1716957092],"type":"Point"}
}