{
  "type": "Feature",
  "properties": {
    "iso:country":"CH",
    "sg:address":"Hilfikerstrasse 2",
    "sg:city":"Sarmenstorf",
    "sg:orig_category":"Detailhandel mit Waren verschiedener Art, Hauptrichtung Nahrungsmittel Grosshandel mit Nahrungsmitte",
    "sg:phone":"+41 56 667 32 08",
    "sg:postcode":"5614",
    "sg:province":"Aargau",
    "wof:name":"Denner-satellit Meyer Sonja",
    "wof:placetype":"venue"
},
  "geometry": {"coordinates":[8.2470712662,47.3100128174],"type":"Point"}
}