{
  "type": "Feature",
  "properties": {
    "iso:country":"CH",
    "sg:address":"Flaachtalstrasse 20",
    "sg:city":"Volken",
    "sg:orig_category":"Unclassifiable Establishments",
    "sg:phone":"+41 52 318 12 42",
    "sg:postcode":"8459",
    "sg:province":"Z\u00fcrich",
    "wof:name":"Nova Star Gmbh",
    "wof:placetype":"venue"
},
  "geometry": {"coordinates":[8.6243629456,47.5740013123],"type":"Point"}
}