{
  "type": "Feature",
  "properties": {
    "iso:country":"CH",
    "sg:address":"Kasernenstrasse 4 8180 B\u00fclach. Postfach",
    "sg:city":"B\u00fclach",
    "sg:orig_category":"Vermietung von Gebrauchsg\u00fctern",
    "sg:postcode":"8180",
    "sg:province":"Z\u00fcrich",
    "wof:name":"Kost\u00fcmverleih Varia, Altorfer Herren M. + Oswald Ch.",
    "wof:placetype":"venue"
},
  "geometry": {"coordinates":[8.5397434235,47.5190315247],"type":"Point"}
}