{
  "type": "Feature",
  "properties": {
    "iso:country":"CH",
    "sg:address":"Im Heidenb\u00fchl 3",
    "sg:city":"R\u00e4terschen",
    "sg:orig_category":"Unclassifiable Establishments",
    "sg:postcode":"8352",
    "sg:province":"Z\u00fcrich",
    "wof:name":"Patric Grin Haus Und Solartechnik",
    "wof:placetype":"venue"
},
  "geometry": {"coordinates":[8.8023319244,47.505317688],"type":"Point"}
}