{
  "type": "Feature",
  "properties": {
    "iso:country":"CH",
    "sg:address":"Passwangstrasse 1",
    "sg:city":"Erschwil",
    "sg:classifiers":[
        {
            "category":"Restaurant",
            "type":"Food & Drink"
        }
    ],
    "sg:phone":"+41 71 911 13 78",
    "sg:postcode":"4228",
    "sg:province":"Solothurn",
    "wof:name":"Restaurant Tiger",
    "wof:placetype":"venue"
},
  "geometry": {"coordinates":[9.05037117,47.4665336609],"type":"Point"}
}