{
  "type": "Feature",
  "properties": {
    "iso:country":"CH",
    "sg:address":"Juraweg 3",
    "sg:city":"Oftringen",
    "sg:orig_category":"Unclassifiable Establishments",
    "sg:postcode":"4665",
    "sg:province":"Aargau",
    "wof:name":"Tony's Pizza Express Gmbh",
    "wof:placetype":"venue"
},
  "geometry": {"coordinates":[7.9369950294,47.2969551086],"type":"Point"}
}