{
  "type": "Feature",
  "properties": {
    "addr:full":"Dorfstr. 13 Dachsen Z\u00fcrich 8447",
    "addr:housenumber":"13",
    "addr:postcode":"8447",
    "addr:street":"Dorfstr.",
    "iso:country":"CH",
    "sg:address":"Dorfstr. 13",
    "sg:city":"Dachsen",
    "sg:orig_category":"Allgemeiner Hoch U Tiefbau",
    "sg:phone":"+41 52 659 16 65",
    "sg:postcode":"8447",
    "sg:province":"Z\u00fcrich",
    "wof:name":"Ernst Erich Bautreuhand",
    "wof:placetype":"venue"
},
  "geometry": {"coordinates":[8.616907,47.665554],"type":"Point"}
}