{
  "type": "Feature",
  "properties": {
    "iso:country":"CH",
    "sg:address":"Chemin De Longet 10 1284 Chancy. Postfach",
    "sg:city":"Chancy",
    "sg:orig_category":"Herstellung von Metallkonstruktionen",
    "sg:postcode":"1284",
    "sg:province":"Gen\u00e8ve",
    "wof:name":"Ymc Industriemontagen Straumann",
    "wof:placetype":"venue"
},
  "geometry": {"coordinates":[7.8703651428,47.3405761719],"type":"Point"}
}