{
  "type": "Feature",
  "properties": {
    "iso:country":"CH",
    "sg:address":"St. Gallerstrasse 5",
    "sg:city":"Arbon",
    "sg:orig_category":"Fachdetailhandel mit pharmazeutischen Produkten",
    "sg:phone":"+41 71 446 44 43",
    "sg:postcode":"9320",
    "sg:province":"Thurgau",
    "wof:name":"Dankelmann Bernhard, See-apotheke",
    "wof:placetype":"venue"
},
  "geometry": {"coordinates":[9.4324760437,47.5121040344],"type":"Point"}
}