{
  "type": "Feature",
  "properties": {
    "iso:country":"CH",
    "sg:address":"R\u00fctenenstrasse 13",
    "sg:city":"Killwangen",
    "sg:orig_category":"Aktivit\u00e4ten der Generalunternehmen im Baugewerbe Architektur U Ingenieurb\u00fcros",
    "sg:phone":"+41 56 401 53 53",
    "sg:postcode":"8956",
    "sg:province":"Aargau",
    "wof:name":"Odermatt + Partner Ag, Architektur Und Immobilien",
    "wof:placetype":"venue"
},
  "geometry": {"coordinates":[8.348321,47.43071],"type":"Point"}
}