{
  "type": "Feature",
  "properties": {
    "iso:country":"CH",
    "sg:address":"Rue Neuve-du-molard 7",
    "sg:city":"Gen\u00e8ve",
    "sg:classifiers":[
        {
            "category":"Restaurant",
            "type":"Food & Drink"
        }
    ],
    "sg:phone":"+41 32 913 10 80",
    "sg:postcode":"1204",
    "sg:province":"Gen\u00e8ve",
    "wof:name":"Snack-bar Istanbul",
    "wof:placetype":"venue"
},
  "geometry": {"coordinates":[6.823551178,47.0992622375],"type":"Point"}
}