{
  "type": "Feature",
  "properties": {
    "iso:country":"CH",
    "sg:address":"Holzwiesweg 43",
    "sg:city":"Z\u00fcrich",
    "sg:orig_category":"Berufliche Weiterbildung, Erwachsenenbildung Film U Videofilmherstellung",
    "sg:phone":"+41 14935669",
    "sg:postcode":"8047",
    "sg:province":"Z\u00fcrich",
    "wof:name":"Gurena Productions Ag Theater- U. Filmproduktionen Usw",
    "wof:placetype":"venue"
},
  "geometry": {"coordinates":[8.496305,47.376434],"type":"Point"}
}