{
  "type": "Feature",
  "properties": {
    "iso:country":"CH",
    "sg:address":"Ueberbach 3",
    "sg:city":"Untervaz",
    "sg:orig_category":"Maler U Glasergewerbe Malerei",
    "sg:phone":"+41 71 385 18 84",
    "sg:postcode":"7204",
    "sg:province":"Graubunden",
    "wof:name":"Magnaguagno Enrico",
    "wof:placetype":"venue"
},
  "geometry": {"coordinates":[9.2488145828,47.4124298096],"type":"Point"}
}