{
  "type": "Feature",
  "properties": {
    "iso:country":"CH",
    "sg:address":"Dorfstrasse 10",
    "sg:city":"Kaisten",
    "sg:orig_category":"Detailhandel mit Blumen U Pflanzen",
    "sg:phone":"+41 62 874 23 68",
    "sg:postcode":"5082",
    "sg:province":"Aargau",
    "wof:name":"Blumen Merkofer",
    "wof:placetype":"venue"
},
  "geometry": {"coordinates":[8.044197,47.539707],"type":"Point"}
}