{
  "type": "Feature",
  "properties": {
    "iso:country":"CH",
    "sg:address":"Poste Rue De La 22",
    "sg:city":"Pully",
    "sg:orig_category":"Non-Classified Establishments",
    "sg:phone":"+41 32 751 14 22",
    "sg:postcode":"1009",
    "sg:province":"Vaud",
    "wof:name":"Bar \u00e0 Caf\u00e9 Milord",
    "wof:placetype":"venue"
},
  "geometry": {"coordinates":[7.0922417641,47.0635223389],"type":"Point"}
}