{
  "type": "Feature",
  "properties": {
    "iso:country":"CH",
    "sg:address":"Winterthurerstrasse 537",
    "sg:city":"Z\u00fcrich",
    "sg:orig_category":"Elektroinstallation",
    "sg:phone":"+41 17881834",
    "sg:postcode":"8051",
    "sg:province":"Z\u00fcrich",
    "wof:name":"B\u00e4rlocher A.",
    "wof:placetype":"venue"
},
  "geometry": {"coordinates":[8.6460647583,47.1944541931],"type":"Point"}
}