{
  "type": "Feature",
  "properties": {
    "iso:country":"CH",
    "sg:address":"Dersbachstrasse 23 6330 Cham. Postfach",
    "sg:city":"Cham",
    "sg:orig_category":"Allgemeiner Hoch U Tiefbau",
    "sg:postcode":"6330",
    "sg:province":"Zug",
    "wof:name":"Christen Ag, Filiale H\u00fcnenberg",
    "wof:placetype":"venue"
},
  "geometry": {"coordinates":[8.451617,47.172234],"type":"Point"}
}