{
  "type": "Feature",
  "properties": {
    "iso:country":"CH",
    "sg:address":"Ti\u00e8che Rue Edouard- 7",
    "sg:city":"B\u00e9vilard",
    "sg:orig_category":"Herstellung von sonstigen landwirtschaftlichen Maschinen",
    "sg:phone":"+41 32 492 14 42",
    "sg:postcode":"2735",
    "sg:province":"Bern",
    "wof:name":"Heimann Fr\u00e8res S\u00e0rl",
    "wof:placetype":"venue"
},
  "geometry": {"coordinates":[7.2827119827,47.236618042],"type":"Point"}
}