{
  "type": "Feature",
  "properties": {
    "iso:country":"CH",
    "sg:address":"Ambassador",
    "sg:city":"Leysin",
    "sg:orig_category":"Hochschulen U h\u00f6here Ausbildung Sprachschulen",
    "sg:phone":"+41 24 493 17 17",
    "sg:postcode":"1854",
    "sg:province":"Vaud",
    "wof:name":"Hosta Sa, Ecole H\u00f4teli\u00e8re, D'administration, Langues Et Tourisme",
    "wof:placetype":"venue"
},
  "geometry": {"coordinates":[7.0130829811,46.3435630798],"type":"Point"}
}