{
  "type": "Feature",
  "properties": {
    "iso:country":"CH",
    "sg:address":"Feldbergstrasse 23",
    "sg:city":"Basel",
    "sg:classifiers":[
        {
            "category":"Restaurant",
            "type":"Food & Drink"
        }
    ],
    "sg:phone":"+41 32 652 35 45",
    "sg:postcode":"4057",
    "sg:province":"Basel-Stadt",
    "wof:name":"Restaurant Zentrum",
    "wof:placetype":"venue"
},
  "geometry": {"coordinates":[7.3672361374,47.1835746765],"type":"Point"}
}