{
  "type": "Feature",
  "properties": {
    "iso:country":"CH",
    "sg:address":"Place Du Temple 3 1304 Cossonay-ville Case Postale 102",
    "sg:city":"Cossonay-ville",
    "sg:orig_category":"Zahnarztpraxen",
    "sg:phone":"+41 21 861 13 12",
    "sg:postcode":"1304",
    "sg:province":"Vaud",
    "wof:name":"Dr M\u00e9d. Dent. St\u00e9phan Givel M\u00e9decin-dentiste",
    "wof:placetype":"venue"
},
  "geometry": {"coordinates":[6.4875569344,46.6005821228],"type":"Point"}
}