{
  "type": "Feature",
  "properties": {
    "iso:country":"CH",
    "sg:address":"7537",
    "sg:city":"M\u00fcstair",
    "sg:orig_category":"Kantonalbanken",
    "sg:phone":"+41 81 858 52 85",
    "sg:postcode":"7537",
    "sg:province":"Graubunden",
    "wof:name":"Graub\u00fcndner Kantonalbank",
    "wof:placetype":"venue"
},
  "geometry": {"coordinates":[10.4457979202,46.6244239807],"type":"Point"}
}