{
  "type": "Feature",
  "properties": {
    "iso:country":"CH",
    "sg:address":"Floraweg 22 8200 Schaffhausen. Postfach 633",
    "sg:city":"Schaffhausen",
    "sg:orig_category":"Allgemeiner Hoch U Tiefbau",
    "sg:phone":"+41 52 624 89 44",
    "sg:postcode":"8200",
    "sg:province":"Schaffhausen",
    "wof:name":"Wohnbau Ag Schaffhausen",
    "wof:placetype":"venue"
},
  "geometry": {"coordinates":[8.62758,47.710026],"type":"Point"}
}