{
  "type": "Feature",
  "properties": {
    "iso:country":"CH",
    "sg:address":"Martinsbergstrasse 38",
    "sg:city":"Baden",
    "sg:orig_category":"Saunas, Solarien, Fitnesszentren U \u00e4hnliches",
    "sg:phone":"+41 56 203 10 10",
    "sg:postcode":"5400",
    "sg:province":"Aargau",
    "wof:name":"Berufsausbildung F\u00fcr Gymnastik Dietrich + Piller",
    "wof:placetype":"venue"
},
  "geometry": {"coordinates":[8.3013782501,47.4762496948],"type":"Point"}
}