{
  "type": "Feature",
  "properties": {
    "iso:country":"CH",
    "sg:address":"R\u00f6merstrasse 10",
    "sg:city":"Bellach",
    "sg:orig_category":"Instandhaltung U Reparatur von Automobilen",
    "sg:postcode":"4512",
    "sg:province":"Solothurn",
    "wof:name":"Garage V. Musliu",
    "wof:placetype":"venue"
},
  "geometry": {"coordinates":[7.5110077858,47.2128295898],"type":"Point"}
}