{
  "type": "Feature",
  "properties": {
    "addr:full":"Schulriederstrasse 11 Dotzigen Bern 3293",
    "addr:housenumber":"11",
    "addr:postcode":"3293",
    "addr:street":"Schulriederstrasse",
    "iso:country":"CH",
    "sg:address":"Schulriederstrasse 11",
    "sg:city":"Dotzigen",
    "sg:orig_category":"Autospenglereien",
    "sg:phone":"+41 32 351 54 55",
    "sg:postcode":"3293",
    "sg:province":"Bern",
    "wof:name":"Markus Engeli Carrosserie",
    "wof:placetype":"venue"
},
  "geometry": {"coordinates":[7.333707,47.117249],"type":"Point"}
}