{
  "type": "Feature",
  "properties": {
    "iso:country":"CH",
    "sg:address":"M\u00e4lsner Dorf 19",
    "sg:city":"Balzers",
    "sg:orig_category":"Grosshandel mit B\u00fcromaschinen Grosshandel mit Datenverarbeitungsger\u00e4ten",
    "sg:phone":"+41 19327970",
    "sg:postcode":"9496",
    "wof:name":"Matrix Computer Ag",
    "wof:placetype":"venue"
},
  "geometry": {"coordinates":[8.7953767776,47.3225784302],"type":"Point"}
}