{
  "type": "Feature",
  "properties": {
    "iso:country":"CH",
    "sg:address":"3961",
    "sg:city":"Grimentz",
    "sg:orig_category":"G\u00fcterbef\u00f6rderung im Strassenverkehr Spezieller Tiefbau",
    "sg:phone":"+41 61 321 40 69",
    "sg:postcode":"3961",
    "sg:province":"Valais",
    "wof:name":"Savioz & H\u00e9ritier",
    "wof:placetype":"venue"
},
  "geometry": {"coordinates":[7.5763998032,46.1804466248],"type":"Point"}
}