{
  "type": "Feature",
  "properties": {
    "iso:country":"CH",
    "sg:address":"Golino 6655 Intragna. Postfach",
    "sg:city":"Golino",
    "sg:orig_category":"RESTAURANTS: TEA-ROOMS",
    "sg:postcode":"6656",
    "sg:province":"Ticino",
    "wof:name":"Th\u00fcr Ernst.",
    "wof:placetype":"venue"
},
  "geometry": {"coordinates":[9.5388059616,47.3781280518],"type":"Point"}
}