{
  "type": "Feature",
  "properties": {
    "iso:country":"CH",
    "sg:address":"Industrieplatz 9",
    "sg:city":"Neuhausen",
    "sg:orig_category":"Detailhandel mit Brot, Back U S\u00fcsswaren",
    "sg:phone":"+41 19803001",
    "sg:postcode":"8212",
    "sg:province":"Schaffhausen",
    "wof:name":"Scharrenberg, Vollkornb\u00e4ckerei",
    "wof:placetype":"venue"
},
  "geometry": {"coordinates":[8.72677,47.277805],"type":"Point"}
}