{
  "type": "Feature",
  "properties": {
    "iso:country":"CH",
    "sg:address":"Poststrasse 9 9410 Heiden. Postfach",
    "sg:city":"Heiden",
    "sg:orig_category":"Interessenvertretungen",
    "sg:postcode":"9410",
    "sg:province":"Appenzell Ausserrhoden",
    "wof:name":"Stiftung Heiden Unterst\u00fctzung U. F\u00f6rderung \u00f6ffentlicher Interessen In Der Gemeinde",
    "wof:placetype":"venue"
},
  "geometry": {"coordinates":[9.5357933044,47.4440231323],"type":"Point"}
}