{
  "type": "Feature",
  "properties": {
    "iso:country":"CH",
    "sg:address":"Cattaneo Via Carlo 5",
    "sg:city":"Chiasso",
    "sg:orig_category":"G\u00fcterbef\u00f6rderung im Strassenverkehr",
    "sg:phone":"+41 91 695 38 96",
    "sg:postcode":"6830",
    "sg:province":"Ticino",
    "wof:name":"M\u00f6bel-transport Ag",
    "wof:placetype":"venue"
},
  "geometry": {"coordinates":[9.0263547897,45.8312416077],"type":"Point"}
}