{
  "type": "Feature",
  "properties": {
    "iso:country":"CH",
    "sg:address":"Bergstrasse 22 8890 Flums. Postfach 49",
    "sg:city":"Flums",
    "sg:orig_category":"Verwaltung der Strafvollzuganstalten Wohnheime",
    "sg:phone":"+41 81 733 24 44",
    "sg:postcode":"8890",
    "sg:province":"St. Gallen",
    "wof:name":"Bezirksgef\u00e4ngnis",
    "wof:placetype":"venue"
},
  "geometry": {"coordinates":[9.3417863846,47.0889930725],"type":"Point"}
}