{
  "type": "Feature",
  "properties": {
    "iso:country":"CH",
    "sg:address":"Villa Smith",
    "sg:city":"B\u00fcrgenstock",
    "sg:orig_category":"Erbringung von Dienstleistungen f\u00fcr Unternehmen",
    "sg:postcode":"6363",
    "sg:province":"Nidwalden",
    "wof:name":"Infra Beratung Gmbh Wirtschaftsberatung Im Bereich Informations, Kommunikationstechnik Usw",
    "wof:placetype":"venue"
},
  "geometry": {"coordinates":[8.3511486053,46.9822006226],"type":"Point"}
}