{
  "type": "Feature",
  "properties": {
    "iso:country":"CH",
    "sg:address":"Rebenweg 9",
    "sg:city":"Russikon",
    "sg:orig_category":"Instandhaltung U Reparatur von Automobilen",
    "sg:phone":"+41 19542324",
    "sg:postcode":"8332",
    "sg:province":"Z\u00fcrich",
    "wof:name":"Dorfgarage Russikon, R\u00f6thlin F. Ag",
    "wof:placetype":"venue"
},
  "geometry": {"coordinates":[8.777215004,47.3932342529],"type":"Point"}
}