{
  "type": "Feature",
  "properties": {
    "iso:country":"CH",
    "sg:address":"Untere Bruech 116",
    "sg:city":"Meilen",
    "sg:orig_category":"Grosshandel mit Eisenwaren sowie Installationsbedarf f\u00fcr Gas, Wasser U Heizung",
    "sg:phone":"+41 19101440",
    "sg:postcode":"8706",
    "sg:province":"Z\u00fcrich",
    "wof:name":"Gamag Ag",
    "wof:placetype":"venue"
},
  "geometry": {"coordinates":[8.5854263306,47.3161201477],"type":"Point"}
}