{
  "type": "Feature",
  "properties": {
    "iso:country":"CH",
    "sg:address":"Heinrich Suppigerstrasse 5 6234 Triengen. Postfach 332",
    "sg:city":"Triengen",
    "sg:orig_category":"Blumen U Zierpflanzenbau Elektroinstallation",
    "sg:phone":"+41 79 422 83 38",
    "sg:postcode":"6234",
    "sg:province":"Luzern",
    "wof:name":"Fischer & Fries Elektro Gmbh",
    "wof:placetype":"venue"
},
  "geometry": {"coordinates":[8.074997,47.235893],"type":"Point"}
}