{
  "type": "Feature",
  "properties": {
    "iso:country":"CH",
    "sg:address":"Som-martel 2",
    "sg:city":"Ponts-de-martel",
    "sg:orig_category":"Unclassifiable Establishments",
    "sg:postcode":"2316",
    "sg:province":"Neuch\u00e2tel",
    "wof:name":"Fross Immobilien Management Ag",
    "wof:placetype":"venue"
},
  "geometry": {"coordinates":[9.8289518356,46.798286438],"type":"Point"}
}