{
  "type": "Feature",
  "properties": {
    "iso:country":"CH",
    "sg:address":"Limmatquai 16",
    "sg:city":"Z\u00fcrich",
    "sg:orig_category":"Werbeagenturen",
    "sg:phone":"+41 12677040",
    "sg:postcode":"8001",
    "sg:province":"Z\u00fcrich",
    "wof:name":"R\u00fcegg Werbung",
    "wof:placetype":"venue"
},
  "geometry": {"coordinates":[8.5437297821,47.3689346313],"type":"Point"}
}