{
  "type": "Feature",
  "properties": {
    "addr:full":"Hauptstrasse 5 Lienz St. Gallen 9464",
    "addr:housenumber":"5",
    "addr:postcode":"9464",
    "addr:street":"Hauptstrasse",
    "iso:country":"CH",
    "sg:address":"Hauptstrasse 5",
    "sg:city":"Lienz",
    "sg:classifiers":[
        {
            "category":"Banks & Credit Unions",
            "subcategory":"Bank",
            "type":"Services"
        }
    ],
    "sg:phone":"+41 27 957 20 63",
    "sg:postcode":"9464",
    "sg:province":"St. Gallen",
    "wof:name":"Raiffeisenbank Saas Fee",
    "wof:placetype":"venue"
},
  "geometry": {"coordinates":[7.93367,46.11171],"type":"Point"}
}