{
  "type": "Feature",
  "properties": {
    "iso:country":"CH",
    "sg:address":"Valavran Route De 68",
    "sg:city":"Bellevue",
    "sg:orig_category":"Erbringung von Dienstleistungen f\u00fcr Unternehmen",
    "sg:phone":"+41 79 417 60 56",
    "sg:postcode":"1293",
    "sg:province":"Gen\u00e8ve",
    "wof:name":"Mosa\u00efque Int\u00e9riors, Kitmitto Huda",
    "wof:placetype":"venue"
},
  "geometry": {"coordinates":[6.1432828903,46.2582702637],"type":"Point"}
}