{
  "type": "Feature",
  "properties": {
    "iso:country":"CH",
    "sg:address":"Badenerstrasse 281 8003 Z\u00fcrich. Postfach",
    "sg:city":"Z\u00fcrich",
    "sg:orig_category":"Versicherungen Generalagenturen",
    "sg:phone":"+41 21 623 92 23",
    "sg:postcode":"8040",
    "sg:province":"Z\u00fcrich",
    "wof:name":"Das Protection Juridique Sa",
    "wof:placetype":"venue"
},
  "geometry": {"coordinates":[6.6113600731,46.5234107971],"type":"Point"}
}