{
  "type": "Feature",
  "properties": {
    "iso:country":"CH",
    "sg:address":"H\u00fcrtimattstrasse 11",
    "sg:city":"Weggis",
    "sg:orig_category":"Stukkateurgewerbe, Gipserei U Verputzerei",
    "sg:postcode":"6353",
    "sg:province":"Luzern",
    "wof:name":"Gipsart Gipsergesch\u00e4ft Gmbh",
    "wof:placetype":"venue"
},
  "geometry": {"coordinates":[7.5997920036,47.4891166687],"type":"Point"}
}