{
  "type": "Feature",
  "properties": {
    "iso:country":"CH",
    "sg:address":"Grande Rue.",
    "sg:city":"Chexbres",
    "sg:orig_category":"Erbringung von Dienstleistungen f\u00fcr Unternehmen",
    "sg:postcode":"1071",
    "sg:province":"Vaud",
    "wof:name":"Meystre, D.",
    "wof:placetype":"venue"
},
  "geometry": {"coordinates":[6.7769379616,46.4816894531],"type":"Point"}
}