{
  "type": "Feature",
  "properties": {
    "iso:country":"CH",
    "sg:address":"Crans",
    "sg:city":"Lens",
    "sg:orig_category":"Verwaltung von Immobilien",
    "sg:phone":"+41 33 243 24 87",
    "sg:postcode":"1978",
    "sg:province":"Valais",
    "wof:name":"F. Rosat",
    "wof:placetype":"venue"
},
  "geometry": {"coordinates":[7.6720571518,46.732208252],"type":"Point"}
}