{
  "type": "Feature",
  "properties": {
    "iso:country":"CH",
    "sg:address":"Alpenstrasse 2",
    "sg:city":"Zug",
    "sg:orig_category":"Non-Classified Establishments",
    "sg:postcode":"6300",
    "sg:province":"Zug",
    "wof:name":"Jedame Holding Ag",
    "wof:placetype":"venue"
},
  "geometry": {"coordinates":[8.5138454437,47.1707572937],"type":"Point"}
}