{
  "type": "Feature",
  "properties": {
    "iso:country":"CH",
    "sg:address":"Avenue Des Alpes 15",
    "sg:city":"Montreux",
    "sg:classifiers":[
        {
            "category":"Travel",
            "subcategory":"Hotels & Motels",
            "type":"Entertainment"
        }
    ],
    "sg:phone":"+41 21 963 74 04",
    "sg:postcode":"1820",
    "sg:province":"Vaud",
    "sg:tags":[
        "hotels",
        "mit",
        "restaurant"
    ],
    "wof:name":"H\u00f4tel Europe",
    "wof:placetype":"venue"
},
  "geometry": {"coordinates":[6.9109368324,46.4327659607],"type":"Point"}
}