{
  "type": "Feature",
  "properties": {
    "iso:country":"CH",
    "sg:address":"Via Cantonale 40",
    "sg:city":"Comano",
    "sg:orig_category":"Nationale Postdienste",
    "sg:phone":"+41 91 941 27 26",
    "sg:postcode":"6949",
    "sg:province":"Ticino",
    "wof:name":"La Posta Svizzera",
    "wof:placetype":"venue"
},
  "geometry": {"coordinates":[8.9552469254,46.0358734131],"type":"Point"}
}