{
  "type": "Feature",
  "properties": {
    "iso:country":"CH",
    "sg:address":"Gewerbezone 7",
    "sg:city":"Buttisholz",
    "sg:orig_category":"Grosshandel mit landwirtschaftlichen Maschinen U Ger\u00e4ten Herstellung von Metallkonstruktionen",
    "sg:phone":"+41 79 418 35 48",
    "sg:postcode":"6018",
    "sg:province":"Luzern",
    "wof:name":"Gr\u00fcter-handels Ag",
    "wof:placetype":"venue"
},
  "geometry": {"coordinates":[8.0823583603,47.1095848083],"type":"Point"}
}