{
  "type": "Feature",
  "properties": {
    "iso:country":"CH",
    "sg:address":"M\u00fcselacher 9 8614 Bertschikon. Postfach",
    "sg:city":"Bertschikon",
    "sg:classifiers":[
        {
            "category":"Professional",
            "subcategory":"Employment Agencies",
            "type":"Services"
        }
    ],
    "sg:postcode":"8614",
    "sg:province":"Z\u00fcrich",
    "sg:tags":[
        "personal",
        "u",
        "stellenvermittlung"
    ],
    "wof:name":"Rising Job Ag",
    "wof:placetype":"venue"
},
  "geometry": {"coordinates":[8.7562532425,47.3231163025],"type":"Point"}
}