{
  "type": "Feature",
  "properties": {
    "iso:country":"CH",
    "sg:address":"Obere Wanne 505",
    "sg:city":"Birrwil",
    "sg:orig_category":"Kauf U Verkauf von Immobilien auf eigene Rechnung",
    "sg:postcode":"5708",
    "sg:province":"Aargau",
    "wof:name":"Haus&kauf Gmbh",
    "wof:placetype":"venue"
},
  "geometry": {"coordinates":[8.1966238022,47.2879371643],"type":"Point"}
}