{
  "type": "Feature",
  "properties": {
    "iso:country":"CH",
    "sg:address":"3920 Zermatt. Postfach",
    "sg:city":"Zermatt",
    "sg:orig_category":"RESTAURANTS: TEA-ROOMS",
    "sg:phone":"+41 27 967 11 82",
    "sg:postcode":"3920",
    "sg:province":"Valais",
    "wof:name":"Restaurant Kegelstube, Knust Simone",
    "wof:placetype":"venue"
},
  "geometry": {"coordinates":[7.7484002113,46.024143219],"type":"Point"}
}