{
  "type": "Feature",
  "properties": {
    "iso:country":"CH",
    "sg:address":"Chemin Du Ch\u00e2ble 1",
    "sg:city":"Neuch\u00e2tel",
    "sg:orig_category":"Gartenbau",
    "sg:phone":"+41 21 634 40 17",
    "sg:postcode":"2000",
    "sg:province":"Neuch\u00e2tel",
    "wof:name":"Philippe Morel Etablissements Horticole",
    "wof:placetype":"venue"
},
  "geometry": {"coordinates":[6.5911540985,46.5432929993],"type":"Point"}
}