{
  "type": "Feature",
  "properties": {
    "iso:country":"CH",
    "sg:address":"1963 V\u00e9troz Case Postale 126",
    "sg:city":"V\u00e9troz",
    "sg:orig_category":"Sportvereine Sch\u00fctzen",
    "sg:phone":"+41 27 306 24 84",
    "sg:postcode":"1963",
    "sg:province":"Valais",
    "wof:name":"St\u00e9 De Tir Armes R\u00e9unies",
    "wof:placetype":"venue"
},
  "geometry": {"coordinates":[7.2825698853,46.2257461548],"type":"Point"}
}