{
  "type": "Feature",
  "properties": {
    "iso:country":"CH",
    "sg:address":"Kantonsstrasse 61",
    "sg:city":"Triengen",
    "sg:orig_category":"Grosshandel mit Eisenwaren sowie Installationsbedarf f\u00fcr Gas, Wasser U Heizung",
    "sg:phone":"+41 41 933 28 74",
    "sg:postcode":"6234",
    "sg:province":"Luzern",
    "wof:name":"Scherer H.",
    "wof:placetype":"venue"
},
  "geometry": {"coordinates":[8.0757513046,47.2357597351],"type":"Point"}
}