{
  "type": "Feature",
  "properties": {
    "iso:country":"CH",
    "sg:address":"2952",
    "sg:city":"Cornol",
    "sg:classifiers":[
        {
            "category":"Restaurant",
            "type":"Food & Drink"
        }
    ],
    "sg:phone":"+41 32 471 16 22",
    "sg:postcode":"2952",
    "sg:province":"Jura",
    "wof:name":"Caf\u00e9 Derri\u00e8re Monterri",
    "wof:placetype":"venue"
},
  "geometry": {"coordinates":[7.1613950729,47.407371521],"type":"Point"}
}