{
  "type": "Feature",
  "properties": {
    "iso:country":"CH",
    "sg:address":"W\u00e4gitalstrasse 4",
    "sg:city":"Siebnen",
    "sg:orig_category":"Zahnarztpraxen",
    "sg:phone":"+41 55 440 87 64",
    "sg:postcode":"8854",
    "sg:province":"Schwyz",
    "wof:name":"Dr. Med. Dent. Gisela Stutz Zahn\u00e4rztin",
    "wof:placetype":"venue"
},
  "geometry": {"coordinates":[8.8967142105,47.1740226746],"type":"Point"}
}