{
  "type": "Feature",
  "properties": {
    "iso:country":"CH",
    "sg:address":"Bertastrasse 97",
    "sg:city":"Z\u00fcrich",
    "sg:orig_category":"Zahnarztpraxen",
    "sg:phone":"+41 71 278 21 61",
    "sg:postcode":"8003",
    "sg:province":"Z\u00fcrich",
    "wof:name":"Dr. Med. Dent. Ernst Blum Zahnarzt",
    "wof:placetype":"venue"
},
  "geometry": {"coordinates":[9.3686027527,47.4085655212],"type":"Point"}
}