{
  "type": "Feature",
  "properties": {
    "iso:country":"CH",
    "sg:address":"Froideville Chemin De",
    "sg:city":"Grandson",
    "sg:orig_category":"Fachdetailhandel in Verkaufsr\u00e4umen",
    "sg:phone":"+41 24 445 25 00",
    "sg:postcode":"1422",
    "sg:province":"Vaud",
    "wof:name":"Gallet Sa",
    "wof:placetype":"venue"
},
  "geometry": {"coordinates":[6.622262001,46.7972564697],"type":"Point"}
}