{
  "type": "Feature",
  "properties": {
    "iso:country":"CH",
    "sg:address":"Blumenstrasse 7",
    "sg:city":"Berneck",
    "sg:orig_category":"Unclassifiable Establishments",
    "sg:postcode":"9442",
    "sg:province":"St. Gallen",
    "wof:name":"Elektro-service Willi Fehr",
    "wof:placetype":"venue"
},
  "geometry": {"coordinates":[8.5953025818,47.5686836243],"type":"Point"}
}