{
  "type": "Feature",
  "properties": {
    "iso:country":"CH",
    "sg:address":"Via Castelrotto 20",
    "sg:city":"Locarno",
    "sg:orig_category":"Datenverarbeitungsdienste Hardwareberatung",
    "sg:phone":"+41 91 760 01 68",
    "sg:postcode":"6600",
    "sg:province":"Ticino",
    "wof:name":"Infodevice Sagl Informatica",
    "wof:placetype":"venue"
},
  "geometry": {"coordinates":[8.789482,46.169029],"type":"Point"}
}