{
  "type": "Feature",
  "properties": {
    "iso:country":"CH",
    "sg:address":"St. Karli-strasse 71",
    "sg:city":"Luzern",
    "sg:orig_category":"Druckweiterverarbeitung",
    "sg:phone":"+41 41 240 12 94",
    "sg:postcode":"6004",
    "sg:province":"Luzern",
    "wof:name":"Rupert Notter Buchbinderei",
    "wof:placetype":"venue"
},
  "geometry": {"coordinates":[8.2883138657,47.0575866699],"type":"Point"}
}