{
  "type": "Feature",
  "properties": {
    "iso:country":"CH",
    "sg:address":"Weststrasse 17",
    "sg:city":"Zofingen",
    "sg:orig_category":"Grosshandel mit festen Brennstoffen U Mineral\u00f6lerzeugnissen",
    "sg:phone":"+41 62 751 21 02",
    "sg:postcode":"4800",
    "sg:province":"Aargau",
    "wof:name":"Rythoma Gmbh",
    "wof:placetype":"venue"
},
  "geometry": {"coordinates":[7.9360380173,47.2859153748],"type":"Point"}
}