{
  "type": "Feature",
  "properties": {
    "iso:country":"CH",
    "sg:address":"Via Maistra 35a",
    "sg:city":"Zuoz",
    "sg:orig_category":"Kantonalbanken",
    "sg:phone":"+41 81 854 13 36",
    "sg:postcode":"7524",
    "sg:province":"Graubunden",
    "wof:name":"Graub\u00fcndner Kantonalbank",
    "wof:placetype":"venue"
},
  "geometry": {"coordinates":[9.959985733,46.6027412415],"type":"Point"}
}