{
  "type": "Feature",
  "properties": {
    "iso:country":"CH",
    "sg:address":"D\u00f6rfli",
    "sg:city":"Silenen",
    "sg:orig_category":"Arztpraxen",
    "sg:phone":"+41 41 883 12 12",
    "sg:postcode":"6473",
    "sg:province":"Uri",
    "wof:name":"Dr.med.dzemal Demirovic Arzt F\u00fcr Allgemeine Medizin",
    "wof:placetype":"venue"
},
  "geometry": {"coordinates":[8.6722,46.779526],"type":"Point"}
}