{
  "type": "Feature",
  "properties": {
    "iso:country":"CH",
    "sg:address":"K\u00fcblereiweg 9.",
    "sg:city":"Chur",
    "sg:orig_category":"Grosshandel mit Holz U Baustoffen",
    "sg:phone":"+41 61 811 28 08",
    "sg:postcode":"7000",
    "sg:province":"Graubunden",
    "wof:name":"L. Girod Verkaufs-ag",
    "wof:placetype":"venue"
},
  "geometry": {"coordinates":[7.7178678513,47.5353279114],"type":"Point"}
}