{
  "type": "Feature",
  "properties": {
    "iso:country":"CH",
    "sg:address":"L\u00e4nggasse 15",
    "sg:city":"Thun",
    "sg:orig_category":"Herstellung von Elektromotoren, Generatoren U Transformatoren",
    "sg:phone":"+41 33 222 69 33",
    "sg:postcode":"3600",
    "sg:province":"Bern",
    "wof:name":"Enercal Ag",
    "wof:placetype":"venue"
},
  "geometry": {"coordinates":[7.6228909492,46.7521476746],"type":"Point"}
}