{
  "type": "Feature",
  "properties": {
    "iso:country":"CH",
    "sg:address":"Z\u00fcrcherstrasse 109",
    "sg:city":"Schlieren",
    "sg:orig_category":"Handel mit Automobilen",
    "sg:phone":"+41 31 339 77 44",
    "sg:postcode":"8952",
    "sg:province":"Z\u00fcrich",
    "wof:name":"Mercedes-benz Automobil Ag Fahrzeuge Und Fahrzeugbestandteile; Vertrieb, Wartung",
    "wof:placetype":"venue"
},
  "geometry": {"coordinates":[7.4682459831,46.9666557312],"type":"Point"}
}