{
  "type": "Feature",
  "properties": {
    "iso:country":"CH",
    "sg:address":"Route Suisse 32",
    "sg:city":"Mies",
    "sg:orig_category":"Instandhaltung U Reparatur von Automobilen",
    "sg:postcode":"1295",
    "sg:province":"Vaud",
    "wof:name":"Lanzilotto Giuseppe.",
    "wof:placetype":"venue"
},
  "geometry": {"coordinates":[6.1741418839,46.3004302979],"type":"Point"}
}