{
  "type": "Feature",
  "properties": {
    "iso:country":"CH",
    "sg:address":"Gottardo Via San 8",
    "sg:city":"Muralto",
    "sg:classifiers":[
        {
            "category":"Travel",
            "subcategory":"Hotels & Motels",
            "type":"Entertainment"
        }
    ],
    "sg:postcode":"6600",
    "sg:province":"Ticino",
    "sg:tags":[
        "hotels",
        "mit",
        "restaurant"
    ],
    "wof:name":"Gerhard M\u00e4tzener",
    "wof:placetype":"venue"
},
  "geometry": {"coordinates":[8.0380096436,46.7220306396],"type":"Point"}
}