{
  "type": "Feature",
  "properties": {
    "iso:country":"CH",
    "sg:address":"Lahngasse 9",
    "sg:city":"Hallau",
    "sg:orig_category":"Grosshandel mit Zucker, Schokolade U S\u00fcsswaren Herstellung von Kakao, Schokoladeerzeugnissen U Zucke",
    "sg:phone":"+41 52 681 16 35",
    "sg:postcode":"8215",
    "sg:province":"Schaffhausen",
    "wof:name":"Bringolf K. Gmbh",
    "wof:placetype":"venue"
},
  "geometry": {"coordinates":[8.4572668076,47.6976852417],"type":"Point"}
}