{
  "type": "Feature",
  "properties": {
    "iso:country":"CH",
    "sg:address":"Haltingerstrasse 80",
    "sg:city":"Basel",
    "sg:orig_category":"Stukkateurgewerbe, Gipserei U Verputzerei",
    "sg:postcode":"4057",
    "sg:province":"Basel-Stadt",
    "wof:name":"Tomi's Renovierungen, Tomislav Buljan",
    "wof:placetype":"venue"
},
  "geometry": {"coordinates":[7.5959119797,47.56615448],"type":"Point"}
}