{
  "type": "Feature",
  "properties": {
    "addr:full":"Solothurnstrasse 122 Biel/bienne Bern 2504",
    "addr:housenumber":"122",
    "addr:postcode":"2504",
    "addr:street":"Solothurnstrasse",
    "iso:country":"CH",
    "sg:address":"Solothurnstrasse 122",
    "sg:city":"Biel/bienne",
    "sg:orig_category":"Detailhandel mit Beleuchtungs U Haushaltsgegenst\u00e4nden Einbau von Schreinerwaren",
    "sg:phone":"+41 32 344 16 00",
    "sg:postcode":"2504",
    "sg:province":"Bern",
    "wof:name":"Fust Ag Fust-center",
    "wof:placetype":"venue"
},
  "geometry": {"coordinates":[7.278094,47.159653],"type":"Point"}
}