{
  "type": "Feature",
  "properties": {
    "iso:country":"CH",
    "sg:address":"Zeughausgasse 2",
    "sg:city":"St.gallen",
    "sg:orig_category":"RESTAURANTS: TEA-ROOMS",
    "sg:phone":"+41 71 222 44 68",
    "sg:postcode":"9000",
    "sg:province":"St. Gallen",
    "wof:name":"Restaurant Zeughaus, Geeler A.",
    "wof:placetype":"venue"
},
  "geometry": {"coordinates":[9.3777837753,47.4241409302],"type":"Point"}
}