{
  "type": "Feature",
  "properties": {
    "iso:country":"CH",
    "sg:address":"Solothurnerstrasse 62",
    "sg:city":"Basel",
    "sg:orig_category":"Detailhandel mit Bekleidung Detailhandel mit M\u00f6beln U Haushaltsgegenst\u00e4nden",
    "sg:phone":"+41 61 361 21 91",
    "sg:postcode":"4053",
    "sg:province":"Basel-Stadt",
    "wof:name":"Galerie Sascha, Ahmed S.",
    "wof:placetype":"venue"
},
  "geometry": {"coordinates":[7.589573,47.543468],"type":"Point"}
}