{
  "type": "Feature",
  "properties": {
    "iso:country":"CH",
    "sg:address":"Furet Chemin Fran\u00e7ois- 53 1203 Gen\u00e8ve. Postfach",
    "sg:city":"Gen\u00e8ve",
    "sg:orig_category":"Betrieb von Taxis",
    "sg:postcode":"1203",
    "sg:province":"Gen\u00e8ve",
    "wof:name":"Tinguely Emile-a.",
    "wof:placetype":"venue"
},
  "geometry": {"coordinates":[6.121742,46.206711],"type":"Point"}
}