{
  "type": "Feature",
  "properties": {
    "iso:country":"CH",
    "sg:address":"Hintere Engehaldenstrasse 74",
    "sg:city":"Bern",
    "sg:orig_category":"Werbung",
    "sg:phone":"+41 31 311 17 80",
    "sg:postcode":"3004",
    "sg:province":"Bern",
    "wof:name":"Candrian Claudia",
    "wof:placetype":"venue"
},
  "geometry": {"coordinates":[7.4469199181,46.9708938599],"type":"Point"}
}