{
  "type": "Feature",
  "properties": {
    "addr:full":"Weinmarkt 8 Luzern Luzern 6004",
    "addr:housenumber":"8",
    "addr:postcode":"6004",
    "addr:street":"Weinmarkt",
    "iso:country":"CH",
    "sg:address":"Weinmarkt 8",
    "sg:city":"Luzern",
    "sg:orig_category":"Buchantiquariate Detailhandel mit B\u00fcchern",
    "sg:phone":"+41 41 410 49 61",
    "sg:postcode":"6004",
    "sg:province":"Luzern",
    "wof:name":"Daniel Good Scientia Curiosa",
    "wof:placetype":"venue"
},
  "geometry": {"coordinates":[8.304285,47.051819],"type":"Point"}
}