{
  "type": "Feature",
  "properties": {
    "iso:country":"CH",
    "sg:address":"Rue Pierre-p\u00e9quignat 4",
    "sg:city":"Del\u00e9mont",
    "sg:orig_category":"Fast-Foodrestaurants Restaurants",
    "sg:phone":"+41 81 756 74 57",
    "sg:postcode":"2800",
    "sg:province":"Jura",
    "wof:name":"Pizza-express Restaurant Bistro Take Away",
    "wof:placetype":"venue"
},
  "geometry": {"coordinates":[9.4715366364,47.1652412415],"type":"Point"}
}