{
  "type": "Feature",
  "properties": {
    "iso:country":"CH",
    "sg:address":"Alpsteinstrasse 15a",
    "sg:city":"Herisau",
    "sg:orig_category":"Detailhandel mit B\u00fcchern, Zeitungen, Schreib U Papeteriewaren Detailhandel mit Zeitungen U Zeitschri",
    "sg:phone":"+41 71 352 62 01",
    "sg:postcode":"9100",
    "sg:province":"Appenzell Ausserrhoden",
    "wof:name":"Kiosk S\u00e4ge Calzavara Renato Kiosk. Tabak, Esswaren; Verkauf",
    "wof:placetype":"venue"
},
  "geometry": {"coordinates":[9.27907,47.37817],"type":"Point"}
}