{
  "type": "Feature",
  "properties": {
    "iso:country":"CH",
    "sg:address":"Br\u00fcnigstrasse 104",
    "sg:city":"Sarnen",
    "sg:orig_category":"Architektur U Ingenieurb\u00fcros Architekturb\u00fcros",
    "sg:phone":"+41 41 660 11 36",
    "sg:postcode":"6060",
    "sg:province":"Obwalden",
    "wof:name":"Mennel Architekten Architekturb\u00fcro Ag",
    "wof:placetype":"venue"
},
  "geometry": {"coordinates":[8.246443,46.900497],"type":"Point"}
}