{
  "type": "Feature",
  "properties": {
    "iso:country":"CH",
    "sg:address":"Moosgasse 2",
    "sg:city":"Ins",
    "sg:orig_category":"Drogerien",
    "sg:phone":"+41 41 870 50 81",
    "sg:postcode":"3232",
    "sg:province":"Bern",
    "wof:name":"Baumann Robert Drogerie",
    "wof:placetype":"venue"
},
  "geometry": {"coordinates":[8.6438703537,46.88073349],"type":"Point"}
}