{
  "type": "Feature",
  "properties": {
    "iso:country":"CH",
    "sg:address":"M\u00fcntzbergstrasse 8",
    "sg:city":"Baden",
    "sg:orig_category":"Grosshandel mit sonstigen Maschinen U Ausr\u00fcstungen f\u00fcr Industrie, Handel U Schiffahrt Handelsvermitt",
    "sg:phone":"+41 56 222 09 30",
    "sg:postcode":"5400",
    "sg:province":"Aargau",
    "wof:name":"Ec Energoconsult Dipl.ing.a.k.wunsch",
    "wof:placetype":"venue"
},
  "geometry": {"coordinates":[8.2848653793,47.4741592407],"type":"Point"}
}