{
  "type": "Feature",
  "properties": {
    "iso:country":"CH",
    "sg:address":"Hardstrasse 139 4052 Basel. Postfach",
    "sg:city":"Basel",
    "sg:orig_category":"Detailhandel mit Radio U Fernsehger\u00e4ten Detailhandel mit elektrischen Haushalts-,Radio U Fernsehger\u00e4",
    "sg:phone":"+41 61 311 69 51",
    "sg:postcode":"4020",
    "sg:province":"Basel-Stadt",
    "wof:name":"Radio-tv-foto Best",
    "wof:placetype":"venue"
},
  "geometry": {"coordinates":[7.6091461182,47.5483474731],"type":"Point"}
}