{
  "type": "Feature",
  "properties": {
    "iso:country":"CH",
    "sg:address":"Vanoni Via 2",
    "sg:city":"Lugano",
    "sg:orig_category":"Reiseb\u00fcros U Reiseveranstalter",
    "sg:phone":"+41 91 994 12 03",
    "sg:postcode":"6900",
    "sg:province":"Ticino",
    "wof:name":"Diamond Travel Sa",
    "wof:placetype":"venue"
},
  "geometry": {"coordinates":[8.9542446136,46.0110206604],"type":"Point"}
}