{
  "type": "Feature",
  "properties": {
    "iso:country":"CH",
    "sg:address":"Riedtlistrasse 15a",
    "sg:city":"Z\u00fcrich",
    "sg:orig_category":"Hochschulen U h\u00f6here Ausbildung",
    "sg:phone":"+41 71 912 31 32",
    "sg:postcode":"8006",
    "sg:province":"Z\u00fcrich",
    "wof:name":"Erfolgs Impuls Schulung Und Beratung Gallus Marc",
    "wof:placetype":"venue"
},
  "geometry": {"coordinates":[9.0507497787,47.4659500122],"type":"Point"}
}