{
  "type": "Feature",
  "properties": {
    "iso:country":"CH",
    "sg:address":"Buchmattstrasse 25",
    "sg:city":"Burgdorf",
    "sg:orig_category":"Innenausbau Verlegen von Fussboden",
    "sg:phone":"+41 34 420 62 60",
    "sg:postcode":"3400",
    "sg:province":"Bern",
    "wof:name":"Atelier L Bodenbel\u00e4ge & Innenausbau",
    "wof:placetype":"venue"
},
  "geometry": {"coordinates":[7.6042041779,47.0651092529],"type":"Point"}
}