{
  "type": "Feature",
  "properties": {
    "iso:country":"CH",
    "sg:address":"F\u00fcllerichstrasse 53",
    "sg:city":"G\u00fcmligen",
    "sg:classifiers":[
        {
            "category":"Banks & Credit Unions",
            "subcategory":"Bank",
            "type":"Services"
        }
    ],
    "sg:phone":"+41 31 951 70 17",
    "sg:postcode":"3073",
    "sg:province":"Bern",
    "wof:name":"Gewerbekasse In Bern",
    "wof:placetype":"venue"
},
  "geometry": {"coordinates":[7.503644,46.932262],"type":"Point"}
}