{
  "type": "Feature",
  "properties": {
    "addr:full":"Seestrasse 6 Spiez Bern 3700",
    "addr:housenumber":"6",
    "addr:postcode":"3700",
    "addr:street":"Seestrasse",
    "iso:country":"CH",
    "sg:address":"Seestrasse 6",
    "sg:city":"Spiez",
    "sg:orig_category":"Detailhandel mit Brillen U anderen Sehhilfen",
    "sg:phone":"+41 77518831",
    "sg:postcode":"3700",
    "sg:province":"Bern",
    "wof:name":"Wenger H\u00f6rger\u00e4te-akustik Ag",
    "wof:placetype":"venue"
},
  "geometry": {"coordinates":[7.680734,46.686684],"type":"Point"}
}