{
  "type": "Feature",
  "properties": {
    "iso:country":"CH",
    "sg:address":"Zugerstrasse 8a",
    "sg:city":"Baar",
    "sg:orig_category":"Wirtschaftspr\u00fcfung, Steuerberatung U Treuhand",
    "sg:postcode":"6340",
    "sg:province":"Zug",
    "wof:name":"Dimaro Progesco Ag",
    "wof:placetype":"venue"
},
  "geometry": {"coordinates":[8.5227413177,47.192527771],"type":"Point"}
}