{
  "type": "Feature",
  "properties": {
    "iso:country":"CH",
    "sg:address":"Oberdorfstrasse 6",
    "sg:city":"Herisau",
    "sg:orig_category":"Detailhandel mit Brot, Back U S\u00fcsswaren",
    "sg:phone":"+41 71 351 14 80",
    "sg:postcode":"9100",
    "sg:province":"Appenzell Ausserrhoden",
    "wof:name":"B\u00e4ckerei-konditorei Schl\u00e4pfer Gmbh",
    "wof:placetype":"venue"
},
  "geometry": {"coordinates":[9.279214,47.385334],"type":"Point"}
}