{
  "type": "Feature",
  "properties": {
    "addr:full":"R\u00fctiweg 65 Ostermundigen Bern 3072",
    "addr:housenumber":"65",
    "addr:postcode":"3072",
    "addr:street":"Ruetiweg",
    "iso:country":"CH",
    "sg:address":"R\u00fctiweg 65",
    "sg:city":"Ostermundigen",
    "sg:orig_category":"Datenverarbeitungsdienste Softwareentwicklung U beratung",
    "sg:phone":"+41 31 931 10 10",
    "sg:postcode":"3072",
    "sg:province":"Bern",
    "wof:name":"Alfa-bit Ag",
    "wof:placetype":"venue"
},
  "geometry": {"coordinates":[7.50647,46.957634],"type":"Point"}
}