{
  "type": "Feature",
  "properties": {
    "iso:country":"CH",
    "sg:address":"Geissb\u00fcelstrasse 5",
    "sg:city":"Herrliberg",
    "sg:classifiers":[
        {
            "category":"Professional",
            "subcategory":"Employment Agencies",
            "type":"Services"
        }
    ],
    "sg:phone":"+41 19152632",
    "sg:postcode":"8704",
    "sg:province":"Z\u00fcrich",
    "sg:tags":[
        "personal",
        "u",
        "stellenvermittlung"
    ],
    "wof:name":"Can-au-pair Rappold C.",
    "wof:placetype":"venue"
},
  "geometry": {"coordinates":[8.6062822342,47.2911911011],"type":"Point"}
}