{
  "type": "Feature",
  "properties": {
    "iso:country":"CH",
    "sg:address":"Blosenberg",
    "sg:city":"Gunzwil",
    "sg:orig_category":"Detailhandel mit Milcherzeugnissen U Eiern Verarbeitung von Milch",
    "sg:postcode":"6222",
    "sg:province":"Luzern",
    "wof:name":"K\u00e4sereigenossenschaft Wili-blosenberg-erlosen",
    "wof:placetype":"venue"
},
  "geometry": {"coordinates":[8.1836795807,47.1863212585],"type":"Point"}
}