{
  "type": "Feature",
  "properties": {
    "iso:country":"CH",
    "sg:address":"Via Cantonale 21",
    "sg:city":"Porza",
    "sg:orig_category":"Interessenvertretungen",
    "sg:postcode":"6948",
    "sg:province":"Ticino",
    "wof:name":"Casa Del Popolo",
    "wof:placetype":"venue"
},
  "geometry": {"coordinates":[8.9521360397,46.02602005],"type":"Point"}
}