{
  "type": "Feature",
  "properties": {
    "iso:country":"CH",
    "sg:address":"Andelfingerstrasse 12 8475 Ossingen. Postfach 26",
    "sg:city":"Ossingen",
    "sg:orig_category":"Detailhandel mit Antiquit\u00e4ten Innendekorationsateliers",
    "sg:phone":"+41 52 317 25 76",
    "sg:postcode":"8475",
    "sg:province":"Z\u00fcrich",
    "wof:name":"Bruno Giacobbo Klimbim Wohnladen Antiquit.",
    "wof:placetype":"venue"
},
  "geometry": {"coordinates":[8.7258710861,47.6118392944],"type":"Point"}
}