{
  "type": "Feature",
  "properties": {
    "iso:country":"CH",
    "sg:address":"D\u00f6ttingerstrasse 1 5303 W\u00fcrenlingen. Postfach",
    "sg:city":"W\u00fcrenlingen",
    "sg:orig_category":"Non-Classified Establishments",
    "sg:postcode":"5303",
    "sg:province":"Aargau",
    "wof:name":"B\u00e4chli Ag",
    "wof:placetype":"venue"
},
  "geometry": {"coordinates":[8.2448949814,47.5360527039],"type":"Point"}
}