{
  "type": "Feature",
  "properties": {
    "iso:country":"CH",
    "sg:address":"Unterstadt 38/40 8200 Schaffhausen. Postfach",
    "sg:city":"Schaffhausen",
    "sg:orig_category":"Handelsvermittlung U Grosshandel mit Automobilteilen U Zubeh\u00f6r Herstellung von sonstigen Gummiwaren",
    "sg:phone":"+41 52 625 73 41",
    "sg:postcode":"8202",
    "sg:province":"Schaffhausen",
    "wof:name":"Roost & Co Gummi Haus Inhaber R.doggwiler",
    "wof:placetype":"venue"
},
  "geometry": {"coordinates":[8.6386985779,47.6959381104],"type":"Point"}
}