{
  "type": "Feature",
  "properties": {
    "iso:country":"CH",
    "sg:address":"R\u00fctistrasse 2",
    "sg:city":"Baden",
    "sg:orig_category":"Forschung U Entwicklung im Bereich der Naturwissenschaften",
    "sg:phone":"+41 22 301 35 00",
    "sg:postcode":"5400",
    "sg:province":"Aargau",
    "wof:name":"Me-ti Sa",
    "wof:placetype":"venue"
},
  "geometry": {"coordinates":[6.1420040131,46.1848373413],"type":"Point"}
}