{
  "type": "Feature",
  "properties": {
    "iso:country":"CH",
    "sg:address":"M\u00fchlemattstrasse 10",
    "sg:city":"Luzern",
    "sg:orig_category":"Wirtschafts U Arbeitgeberverb\u00e4nde",
    "sg:phone":"+41 71 277 47 27",
    "sg:postcode":"6004",
    "sg:province":"Luzern",
    "wof:name":"Zimmermeister-verband Sg",
    "wof:placetype":"venue"
},
  "geometry": {"coordinates":[9.3325805664,47.4035568237],"type":"Point"}
}