{
  "type": "Feature",
  "properties": {
    "iso:country":"CH",
    "sg:address":"Obergmeind",
    "sg:city":"Tschappina",
    "sg:classifiers":[
        {
            "category":"Travel",
            "subcategory":"Hotels & Motels",
            "type":"Entertainment"
        }
    ],
    "sg:phone":"+41 81 651 39 75",
    "sg:postcode":"7428",
    "sg:province":"Graubunden",
    "sg:tags":[
        "hotels",
        "mit",
        "restaurant"
    ],
    "wof:name":"Hotel Solaria",
    "wof:placetype":"venue"
},
  "geometry": {"coordinates":[9.3602237701,46.6919403076],"type":"Point"}
}