{
  "type": "Feature",
  "properties": {
    "iso:country":"CH",
    "sg:address":"Langhaldenstrasse 6a",
    "sg:city":"Kreuzlingen",
    "sg:orig_category":"Detailhandel mit B\u00fcchern",
    "sg:phone":"+41 81 413 21 91",
    "sg:postcode":"8280",
    "sg:province":"Thurgau",
    "wof:name":"Erika Patzen B\u00fcecher-egga",
    "wof:placetype":"venue"
},
  "geometry": {"coordinates":[9.824162,46.799107],"type":"Point"}
}