{
  "type": "Feature",
  "properties": {
    "iso:country":"CH",
    "sg:address":"Alte Landstrasse 392",
    "sg:city":"M\u00e4nnedorf",
    "sg:orig_category":"Erwachsenenbildung U sonstiger Unterricht Softwareentwicklung U beratung",
    "sg:phone":"+41 17901685",
    "sg:postcode":"8708",
    "sg:province":"Z\u00fcrich",
    "wof:name":"Rase Raponi Marco Software Engineering",
    "wof:placetype":"venue"
},
  "geometry": {"coordinates":[8.7054653168,47.2478218079],"type":"Point"}
}