{
  "type": "Feature",
  "properties": {
    "iso:country":"CH",
    "sg:address":"Via San Materno 4 6616 Losone. Postfach Caselle Postale 832",
    "sg:city":"Losone",
    "sg:orig_category":"Detailhandel mit Fleisch U Fleischwaren",
    "sg:phone":"+41 91 791 16 53",
    "sg:postcode":"6616",
    "sg:province":"Ticino",
    "wof:name":"Manciana Fratelli & Pinoia Macelleria Moderna",
    "wof:placetype":"venue"
},
  "geometry": {"coordinates":[8.761428833,46.1641464233],"type":"Point"}
}