{
  "type": "Feature",
  "properties": {
    "iso:country":"CH",
    "sg:address":"Rishaldenweg 31 4852 Rothrist. Postfach",
    "sg:city":"Rothrist",
    "sg:orig_category":"Architektur U Ingenieurb\u00fcros Unternehmensberatung",
    "sg:phone":"+41 62 785 80 05",
    "sg:postcode":"4852",
    "sg:province":"Aargau",
    "wof:name":"Tecpac Ag",
    "wof:placetype":"venue"
},
  "geometry": {"coordinates":[7.89082,47.31031],"type":"Point"}
}