{
  "type": "Feature",
  "properties": {
    "iso:country":"CH",
    "sg:address":"Flachsacker 5 6330 Cham. Postfach 474",
    "sg:city":"Cham",
    "sg:orig_category":"Kaminfeger Reinigungsgewerbe",
    "sg:phone":"+41 41 780 41 24",
    "sg:postcode":"6330",
    "sg:province":"Zug",
    "wof:name":"Heinrich Ulmann Kaminfegergesch\u00e4ft",
    "wof:placetype":"venue"
},
  "geometry": {"coordinates":[8.4662237167,47.1840286255],"type":"Point"}
}