{
  "type": "Feature",
  "properties": {
    "iso:country":"CH",
    "sg:address":"Neuhaus",
    "sg:city":"Wangenried",
    "sg:orig_category":"Haltung von Rindern",
    "sg:postcode":"3374",
    "sg:province":"Bern",
    "wof:name":"Viehzuchtgenossenschaft Wangenried Und Umgebung",
    "wof:placetype":"venue"
},
  "geometry": {"coordinates":[7.6556391716,47.2183570862],"type":"Point"}
}