{
  "type": "Feature",
  "properties": {
    "addr:full":"Rue De Bourg 20 Lausanne Vaud 1003",
    "addr:housenumber":"20",
    "addr:postcode":"1003",
    "addr:street":"Rue De Bourg",
    "iso:country":"CH",
    "sg:address":"Rue De Bourg 20",
    "sg:city":"Lausanne",
    "sg:orig_category":"Detailhandel mit Damenbekleidung",
    "sg:phone":"+41 21 320 03 65",
    "sg:postcode":"1003",
    "sg:province":"Vaud",
    "wof:name":"Esprit Shop Bollag-guggenheim Ag",
    "wof:placetype":"venue"
},
  "geometry": {"coordinates":[6.63566,46.519936],"type":"Point"}
}