{
  "type": "Feature",
  "properties": {
    "iso:country":"CH",
    "sg:address":"Rue Des Corps-saints 4",
    "sg:city":"Gen\u00e8ve",
    "sg:classifiers":[
        {
            "category":"Restaurant",
            "type":"Food & Drink"
        }
    ],
    "sg:phone":"+41 22 732 45 72",
    "sg:postcode":"1201",
    "sg:province":"Gen\u00e8ve",
    "wof:name":"Caf\u00e9 St-gervais",
    "wof:placetype":"venue"
},
  "geometry": {"coordinates":[6.1414151192,46.2063102722],"type":"Point"}
}