{
  "type": "Feature",
  "properties": {
    "iso:country":"CH",
    "sg:address":"Bahnhofstrasse 43",
    "sg:city":"Maienfeld",
    "sg:orig_category":"Baugewerbe Herstellung von Metallkonstruktionen",
    "sg:phone":"+41 55 282 48 23",
    "sg:postcode":"7304",
    "sg:province":"Graubunden",
    "wof:name":"Gsm Maschinenbau Ag",
    "wof:placetype":"venue"
},
  "geometry": {"coordinates":[8.922432,47.237293],"type":"Point"}
}