{
  "type": "Feature",
  "properties": {
    "iso:country":"CH",
    "sg:address":"Bahnhofstrasse 42",
    "sg:city":"Baden",
    "sg:orig_category":"Rechtsberatung",
    "sg:phone":"+41 56 203 30 23",
    "sg:postcode":"5400",
    "sg:province":"Aargau",
    "wof:name":"Binder Dr. Markus",
    "wof:placetype":"venue"
},
  "geometry": {"coordinates":[8.3088083267,47.4775505066],"type":"Point"}
}