{
  "type": "Feature",
  "properties": {
    "iso:country":"CH",
    "sg:address":"Riet",
    "sg:city":"Wildhaus",
    "sg:orig_category":"Allgemeiner Gartenbau Dienstleistungen im Gartenbau",
    "sg:phone":"+41 71 999 33 20",
    "sg:postcode":"9658",
    "sg:province":"St. Gallen",
    "wof:name":"Ruedi Reich Transporte & Erdbewegungen",
    "wof:placetype":"venue"
},
  "geometry": {"coordinates":[9.326185,47.200333],"type":"Point"}
}