{
  "type": "Feature",
  "properties": {
    "iso:country":"CH",
    "sg:address":"Poststrasse 3",
    "sg:city":"Rorschach",
    "sg:orig_category":"Detailhandel mit Brillen U anderen Sehhilfen Detailhandel mit medizinischen U orthop\u00e4dischen Artikel",
    "sg:phone":"+41 71 841 11 22",
    "sg:postcode":"9400",
    "sg:province":"St. Gallen",
    "wof:name":"H\u00f6r-center P.fritschi Ag",
    "wof:placetype":"venue"
},
  "geometry": {"coordinates":[9.491373,47.478161],"type":"Point"}
}