{
  "type": "Feature",
  "properties": {
    "iso:country":"CH",
    "sg:address":"R\u00fctistrasse 3 5634 Merenschwand. Postfach",
    "sg:city":"Merenschwand",
    "sg:orig_category":"Polizei",
    "sg:phone":"+41 56 664 12 28",
    "sg:postcode":"5634",
    "sg:province":"Aargau",
    "wof:name":"Kantonspolizei",
    "wof:placetype":"venue"
},
  "geometry": {"coordinates":[8.3738689423,47.2603569031],"type":"Point"}
}