{
  "type": "Feature",
  "properties": {
    "iso:country":"CH",
    "sg:address":"Riazzino 6595 Riazzino. Postfach",
    "sg:city":"Riazzino",
    "sg:orig_category":"RESTAURANTS: TEA-ROOMS",
    "sg:postcode":"6595",
    "sg:province":"Ticino",
    "wof:name":"Snack Bar Tennis Sagl",
    "wof:placetype":"venue"
},
  "geometry": {"coordinates":[8.9139242172,46.3790473938],"type":"Point"}
}