{
  "type": "Feature",
  "properties": {
    "iso:country":"CH",
    "sg:address":"Les Collons",
    "sg:city":"Vex",
    "sg:orig_category":"Fachdetailhandel in Verkaufsr\u00e4umen",
    "sg:postcode":"1981",
    "sg:province":"Valais",
    "wof:name":"Theytaz Sports, Theytaz Fran\u00e7ois",
    "wof:placetype":"venue"
},
  "geometry": {"coordinates":[7.3985052109,46.2118530273],"type":"Point"}
}