{
  "type": "Feature",
  "properties": {
    "iso:country":"CH",
    "sg:address":"Wampflenstrasse 7 8706 Meilen. Postfach 228",
    "sg:city":"Meilen",
    "sg:orig_category":"Grosshandel mit Obst U Gem\u00fcse",
    "sg:phone":"+41 19250110",
    "sg:postcode":"8706",
    "sg:province":"Z\u00fcrich",
    "wof:name":"Selenati Trading Ag Fr\u00fcchteimport",
    "wof:placetype":"venue"
},
  "geometry": {"coordinates":[8.6454610825,47.2739524841],"type":"Point"}
}