{
  "type": "Feature",
  "properties": {
    "iso:country":"CH",
    "sg:address":"1636",
    "sg:city":"Broc",
    "sg:orig_category":"Gemeindeverwaltungen",
    "sg:phone":"+41 26 921 15 13",
    "sg:postcode":"1636",
    "sg:province":"Fribourg",
    "wof:name":"Administration Communale De Broc",
    "wof:placetype":"venue"
},
  "geometry": {"coordinates":[7.1003518105,46.6031494141],"type":"Point"}
}