{
  "type": "Feature",
  "properties": {
    "iso:country":"CH",
    "sg:address":"Horburgstrasse 47",
    "sg:city":"Basel",
    "sg:orig_category":"G\u00fcterbef\u00f6rderung im Strassenverkehr",
    "sg:phone":"+41 61 693 37 06",
    "sg:postcode":"4057",
    "sg:province":"Basel-Stadt",
    "wof:name":"Mehmet Aksu Aksu Transport",
    "wof:placetype":"venue"
},
  "geometry": {"coordinates":[7.5933351517,47.5708618164],"type":"Point"}
}