{
  "type": "Feature",
  "properties": {
    "addr:full":"Gabismatt 12 Langenthal Bern 4900",
    "addr:housenumber":"12",
    "addr:postcode":"4900",
    "addr:street":"Gabismatt;Bern",
    "iso:country":"CH",
    "sg:address":"Gabismatt 12",
    "sg:city":"Langenthal",
    "sg:orig_category":"Bauschreinerei Innenausbau",
    "sg:phone":"+41 71 393 15 89",
    "sg:postcode":"4900",
    "sg:province":"Bern",
    "wof:name":"Helbling Ag Schreinerei & Innenausbau",
    "wof:placetype":"venue"
},
  "geometry": {"coordinates":[9.168609,47.41724],"type":"Point"}
}