{
  "type": "Feature",
  "properties": {
    "addr:full":"Rheinecker Strasse 5b 9425 Thal. Postfach 251 Thal St. Gallen 9425",
    "addr:housenumber":"5b;251",
    "addr:postcode":"9425;9425",
    "addr:street":"Rheinecker Strasse;Postfach",
    "iso:country":"CH",
    "sg:address":"Rheinecker Strasse 5b 9425 Thal. Postfach 251",
    "sg:city":"Thal",
    "sg:orig_category":"Architektur U Ingenieurb\u00fcros",
    "sg:phone":"+41 71 888 30 20",
    "sg:postcode":"9425",
    "sg:province":"St. Gallen",
    "wof:name":"Felix Wagner Gmbh",
    "wof:placetype":"venue"
},
  "geometry": {"coordinates":[9.570804,47.464832],"type":"Point"}
}