{
  "type": "Feature",
  "properties": {
    "iso:country":"CH",
    "sg:address":"Paradiesweg 11",
    "sg:city":"Goldach",
    "sg:orig_category":"Gesundheitswesen",
    "sg:postcode":"9403",
    "sg:province":"St. Gallen",
    "wof:name":"Norico Gmbh",
    "wof:placetype":"venue"
},
  "geometry": {"coordinates":[9.4710826874,47.4707794189],"type":"Point"}
}