{
  "type": "Feature",
  "properties": {
    "iso:country":"CH",
    "sg:address":"3150",
    "sg:city":"Schwarzenburg",
    "sg:orig_category":"Interessenvertretungen",
    "sg:postcode":"3150",
    "sg:province":"Bern",
    "wof:name":"Rosina Jenni Und Bertha Dubach-fonds",
    "wof:placetype":"venue"
},
  "geometry": {"coordinates":[7.3419699669,46.8187217712],"type":"Point"}
}