{
  "type": "Feature",
  "properties": {
    "iso:country":"CH",
    "sg:address":"Waffenplatzstrasse 51",
    "sg:city":"Z\u00fcrich",
    "sg:orig_category":"Grosshandel mit Eisenwaren sowie Installationsbedarf f\u00fcr Gas, Wasser U Heizung Sonstiger Grosshandel",
    "sg:phone":"+41 12013622",
    "sg:postcode":"8002",
    "sg:province":"Z\u00fcrich",
    "wof:name":"Hawegro-handels Ag",
    "wof:placetype":"venue"
},
  "geometry": {"coordinates":[8.527141571,47.3589553833],"type":"Point"}
}