{
  "type": "Feature",
  "properties": {
    "iso:country":"CH",
    "sg:address":"Les Croisettes 1066 Epalinges Case Postale 68",
    "sg:city":"Epalinges",
    "sg:orig_category":"Technische, physikalische U chemische Untersuchung",
    "sg:phone":"+41 21 316 43 43",
    "sg:postcode":"1066",
    "sg:province":"Vaud",
    "wof:name":"Laboratoire Cantonal Contr\u00f4le Denr\u00e9es Alimentaires",
    "wof:placetype":"venue"
},
  "geometry": {"coordinates":[6.658539772,46.5448684692],"type":"Point"}
}