{
  "type": "Feature",
  "properties": {
    "iso:country":"CH",
    "sg:address":"Rochettes Rue Des 2",
    "sg:city":"Cortaillod",
    "sg:orig_category":"Interessenvertretungen",
    "sg:postcode":"2016",
    "sg:province":"Neuch\u00e2tel",
    "wof:name":"Fondation De Pr\u00e9voyance En Faveur Du Personnel De Silicon Graphics Manufacturing Sa Et De Toutes Les Soci\u00e9t\u00e9s \u00e9conomiquement Affili\u00e9es",
    "wof:placetype":"venue"
},
  "geometry": {"coordinates":[6.842233181,46.9459381104],"type":"Point"}
}