{
  "type": "Feature",
  "properties": {
    "addr:full":"Unt. Bahnhofstr. 21 Rapperswil Schwyz 8640",
    "addr:housenumber":"21",
    "addr:postcode":"8640",
    "addr:street":"Bahnhofstr.;Schwyz",
    "iso:country":"CH",
    "sg:address":"Unt. Bahnhofstr. 21",
    "sg:city":"Rapperswil",
    "sg:classifiers":[
        {
            "category":"Banks & Credit Unions",
            "subcategory":"Bank",
            "type":"Services"
        }
    ],
    "sg:phone":"+41 55 210 94 94",
    "sg:postcode":"8640",
    "sg:province":"Schwyz",
    "wof:name":"Migros Bank",
    "wof:placetype":"venue"
},
  "geometry": {"coordinates":[8.818504,47.225971],"type":"Point"}
}