{
  "type": "Feature",
  "properties": {
    "iso:country":"CH",
    "sg:address":"Via S. Bernardino",
    "sg:city":"Castione",
    "sg:orig_category":"Grosshandel mit Wein U Spirituosen Herstellung von Bier",
    "sg:phone":"+41 91 835 80 88",
    "sg:postcode":"6532",
    "sg:province":"Ticino",
    "wof:name":"La Tana Del Luppolo Sagl Birreria",
    "wof:placetype":"venue"
},
  "geometry": {"coordinates":[9.0526809692,46.2243881226],"type":"Point"}
}