{
  "type": "Feature",
  "properties": {
    "iso:country":"CH",
    "sg:address":"6915",
    "sg:city":"Pambio-noranco",
    "sg:orig_category":"Herstellung von sonstigen Erzeugnissen",
    "sg:phone":"+41 21 845 63 61",
    "sg:postcode":"6915",
    "sg:province":"Ticino",
    "wof:name":"Sabattini G\u00e9rald",
    "wof:placetype":"venue"
},
  "geometry": {"coordinates":[6.2120537758,46.582359314],"type":"Point"}
}