{
  "type": "Feature",
  "properties": {
    "iso:country":"CH",
    "sg:address":"Ferdinand-hodler-weg 6",
    "sg:city":"Thun",
    "sg:orig_category":"Vereine Radio, Film and Foto",
    "sg:postcode":"3600",
    "sg:province":"Bern",
    "wof:name":"Film-& Amateur-club Thun",
    "wof:placetype":"venue"
},
  "geometry": {"coordinates":[7.6228599548,46.7513504028],"type":"Point"}
}