{
  "type": "Feature",
  "properties": {
    "iso:country":"CH",
    "sg:address":"Seefeldstrasse 104",
    "sg:city":"Z\u00fcrich",
    "sg:orig_category":"Werbung",
    "sg:postcode":"8008",
    "sg:province":"Z\u00fcrich",
    "wof:name":"Weber Stefan, Konzept, Text, Ton",
    "wof:placetype":"venue"
},
  "geometry": {"coordinates":[8.5924005508,47.3076095581],"type":"Point"}
}