{
  "type": "Feature",
  "properties": {
    "iso:country":"CH",
    "sg:address":"6122",
    "sg:city":"Menznau",
    "sg:orig_category":"Instandhaltung U Reparatur von Automobilen",
    "sg:postcode":"6122",
    "sg:province":"Luzern",
    "wof:name":"Blum Toni Garage",
    "wof:placetype":"venue"
},
  "geometry": {"coordinates":[8.0390977859,47.082950592],"type":"Point"}
}