{
  "type": "Feature",
  "properties": {
    "iso:country":"CH",
    "sg:address":"3935",
    "sg:city":"B\u00fcrchen",
    "sg:orig_category":"Landesverteidigung, Sozialversicherung \u00d6ffentliche Verwaltung",
    "sg:phone":"+41 41 870 20 22",
    "sg:postcode":"3935",
    "sg:province":"Valais",
    "wof:name":"Zivilschutzstelle B\u00fcrglen",
    "wof:placetype":"venue"
},
  "geometry": {"coordinates":[8.6634397507,46.87525177],"type":"Point"}
}