{
  "type": "Feature",
  "properties": {
    "iso:country":"CH",
    "sg:address":"Binzstrasse 39",
    "sg:city":"Z\u00fcrich",
    "sg:classifiers":[
        {
            "category":"Professional",
            "subcategory":"Advertising",
            "type":"Services"
        }
    ],
    "sg:phone":"+41 12613538",
    "sg:postcode":"8045",
    "sg:province":"Z\u00fcrich",
    "sg:tags":[
        "agency"
    ],
    "wof:name":"Brun & B\u00fcrgin",
    "wof:placetype":"venue"
},
  "geometry": {"coordinates":[8.511875,47.361675],"type":"Point"}
}