{
  "type": "Feature",
  "properties": {
    "iso:country":"CH",
    "sg:address":"Blau\u00e4cker 21 8051 Z\u00fcrich. Postfach 55",
    "sg:city":"Z\u00fcrich",
    "sg:orig_category":"Sportvereine Turnen",
    "sg:phone":"+41 13229840",
    "sg:postcode":"8051",
    "sg:province":"Z\u00fcrich",
    "wof:name":"Turnverein Schwamendingen",
    "wof:placetype":"venue"
},
  "geometry": {"coordinates":[8.571516037,47.406047821],"type":"Point"}
}