{
  "type": "Feature",
  "properties": {
    "iso:country":"CH",
    "sg:address":"Chauderon Place 5",
    "sg:city":"Lausanne",
    "sg:orig_category":"Unternehmensberatung",
    "sg:phone":"+41 21 312 01 67",
    "sg:postcode":"1003",
    "sg:province":"Vaud",
    "wof:name":"Zisyadis J.",
    "wof:placetype":"venue"
},
  "geometry": {"coordinates":[6.6259770393,46.5231742859],"type":"Point"}
}