{
  "type": "Feature",
  "properties": {
    "iso:country":"CH",
    "sg:address":"S\u00e4gebachstr. 2",
    "sg:city":"Lenggenwil",
    "sg:classifiers":[
        {
            "category":"Home & Garden",
            "subcategory":"Furniture",
            "type":"Retail Goods"
        }
    ],
    "sg:phone":"+41 71 948 70 70",
    "sg:postcode":"9525",
    "sg:province":"St. Gallen",
    "sg:tags":[
        "household",
        "wood"
    ],
    "wof:name":"M\u00dcllersafe Ag",
    "wof:placetype":"venue"
},
  "geometry": {"coordinates":[9.1485490799,47.4758644104],"type":"Point"}
}