{
  "type": "Feature",
  "properties": {
    "iso:country":"CH",
    "sg:address":"Via Serafino Balestra 27 6900 Lugano. Postfach",
    "sg:city":"Lugano",
    "sg:orig_category":"Finanzierungsinstitutionen",
    "sg:postcode":"6900",
    "sg:province":"Ticino",
    "wof:name":"Fairfield Greenwich Sa Rappresentanza Di Fondi Di Investimento, Attivit\u00e0 Commerciali Ecc",
    "wof:placetype":"venue"
},
  "geometry": {"coordinates":[8.9577894211,46.0079498291],"type":"Point"}
}