{
  "type": "Feature",
  "properties": {
    "iso:country":"CH",
    "sg:address":"Rue Du Pr\u00e9 Jorat 30 2108 Couvet Case Postale 105",
    "sg:city":"Couvet",
    "sg:orig_category":"Herstellung von pharmazeutischen Grundstoffen Herstellung von sonstigen organischen Grundstoffen U C",
    "sg:phone":"+41 22 782 95 25",
    "sg:postcode":"2108",
    "sg:province":"Neuch\u00e2tel",
    "wof:name":"Arcolab Sa",
    "wof:placetype":"venue"
},
  "geometry": {"coordinates":[6.0761470795,46.2231826782],"type":"Point"}
}