{
  "type": "Feature",
  "properties": {
    "iso:country":"CH",
    "sg:address":"Casa Merah Muda 6821 Rovio. Postfach",
    "sg:city":"Rovio",
    "sg:orig_category":"Unternehmensberatung",
    "sg:postcode":"6821",
    "sg:province":"Ticino",
    "wof:name":"Rpo Consulting Sagl Consulenza Aziendale, Assunzione Di Rappresentanze Ecc",
    "wof:placetype":"venue"
},
  "geometry": {"coordinates":[8.9870500565,45.9332351685],"type":"Point"}
}