{
  "type": "Feature",
  "properties": {
    "iso:country":"CH",
    "sg:address":"G\u00fcttinger Strasse 40",
    "sg:city":"Altnau",
    "sg:orig_category":"Elektroinstallation",
    "sg:phone":"+41 71 695 18 19",
    "sg:postcode":"8595",
    "sg:province":"Thurgau",
    "wof:name":"Uhler Kurt",
    "wof:placetype":"venue"
},
  "geometry": {"coordinates":[9.2622013092,47.6089286804],"type":"Point"}
}