{
  "type": "Feature",
  "properties": {
    "iso:country":"CH",
    "sg:address":"Haldenstrasse 30",
    "sg:city":"Oberembrach",
    "sg:orig_category":"Grosshandel mit Eisenwaren sowie Installationsbedarf f\u00fcr Gas, Wasser U Heizung Grosshandel mit sonst",
    "sg:phone":"+41 18817777",
    "sg:postcode":"8425",
    "sg:province":"Z\u00fcrich",
    "wof:name":"Tecnotool Ag",
    "wof:placetype":"venue"
},
  "geometry": {"coordinates":[8.6168603897,47.4893302917],"type":"Point"}
}