{
  "type": "Feature",
  "properties": {
    "iso:country":"CH",
    "sg:address":"Kempttalstrasse 26",
    "sg:city":"Fehraltorf",
    "sg:orig_category":"Handel mit Automobilen",
    "sg:postcode":"8320",
    "sg:province":"Z\u00fcrich",
    "wof:name":"Nansy Auto-center, Kadour Ibrahim",
    "wof:placetype":"venue"
},
  "geometry": {"coordinates":[9.2382574081,47.4170074463],"type":"Point"}
}