{
  "type": "Feature",
  "properties": {
    "iso:country":"CH",
    "sg:address":"S\u00e4riswilstrasse 10 3043 Uettligen. Postfach 169",
    "sg:city":"Uettligen",
    "sg:orig_category":"Mechanische Werkst\u00e4tten Schmieden",
    "sg:phone":"+41 31 829 01 69",
    "sg:postcode":"3043",
    "sg:province":"Bern",
    "wof:name":"Brunner Ag Uettligen Mech.werkst\u00e4tte & Schmiede",
    "wof:placetype":"venue"
},
  "geometry": {"coordinates":[7.3836832047,46.9879493713],"type":"Point"}
}