{
  "type": "Feature",
  "properties": {
    "iso:country":"CH",
    "sg:address":"Banackerweg 27",
    "sg:city":"Neuendorf",
    "sg:classifiers":[
        {
            "category":"Insurance",
            "subcategory":"Insurance Agent",
            "type":"Services"
        }
    ],
    "sg:phone":"+41 62 398 27 17",
    "sg:postcode":"4623",
    "sg:province":"Solothurn",
    "sg:tags":[
        "versicherungsagenturen",
        "-broker"
    ],
    "wof:name":"Barbara Hunziker Versicherungs-dienstleistungen",
    "wof:placetype":"venue"
},
  "geometry": {"coordinates":[7.7959480286,47.2962112427],"type":"Point"}
}