{
  "type": "Feature",
  "properties": {
    "iso:country":"CH",
    "sg:address":"Fadenbr\u00fccke 12",
    "sg:city":"Buochs",
    "sg:classifiers":[
        {
            "category":"Autos & Motor Vehicles",
            "subcategory":"Automobile Sales",
            "type":"Retail Goods"
        }
    ],
    "sg:phone":"+41 41 620 67 69",
    "sg:postcode":"6374",
    "sg:province":"Nidwalden",
    "sg:tags":[
        "equipment",
        "motor-cars",
        "transport"
    ],
    "wof:name":"Schiltrac Fahrzeugbau Gmbh",
    "wof:placetype":"venue"
},
  "geometry": {"coordinates":[8.4036340714,46.9702453613],"type":"Point"}
}