{
  "type": "Feature",
  "properties": {
    "iso:country":"CH",
    "sg:address":"H\u00f6schstrasse 25",
    "sg:city":"Feldmeilen",
    "sg:orig_category":"Vermietung U Verpachtung von eigenen Immobilien Vermittlung von Immobilien",
    "sg:phone":"+41 71 245 70 75",
    "sg:postcode":"8706",
    "sg:province":"Z\u00fcrich",
    "wof:name":"Br\u00fcschweiler Immobilien Ag",
    "wof:placetype":"venue"
},
  "geometry": {"coordinates":[9.3830432892,47.4364051819],"type":"Point"}
}