{
  "type": "Feature",
  "properties": {
    "iso:country":"CH",
    "sg:address":"Oberdorfstrasse 4",
    "sg:city":"Reiden",
    "sg:orig_category":"Sonstige pers\u00f6nliche Dienstleistungen",
    "sg:phone":"+41 62 758 21 24",
    "sg:postcode":"6260",
    "sg:province":"Luzern",
    "wof:name":"3g Services Gschwend",
    "wof:placetype":"venue"
},
  "geometry": {"coordinates":[7.9723677635,47.2465820312],"type":"Point"}
}