{
  "type": "Feature",
  "properties": {
    "iso:country":"CH",
    "sg:address":"G\u00fcetli 188",
    "sg:city":"Walzenhausen",
    "sg:orig_category":"Handelsvermittlung U Grosshandel Herstellung von k\u00e4lte U lufttechnischen Erzeugnissen f\u00fcr gewerblich",
    "sg:phone":"+41 71 633 37 37",
    "sg:postcode":"9428",
    "sg:province":"Appenzell Ausserrhoden",
    "wof:name":"Gh Technik Gmbh",
    "wof:placetype":"venue"
},
  "geometry": {"coordinates":[9.1590948105,47.5485191345],"type":"Point"}
}