{
  "type": "Feature",
  "properties": {
    "iso:country":"CH",
    "sg:address":"Dorf 14",
    "sg:city":"Herrliberg",
    "sg:orig_category":"Grosshandel mit Fleisch U Fleischwaren Grosshandel mit Obst U Gem\u00fcse",
    "sg:phone":"+41 19154220",
    "sg:postcode":"8704",
    "sg:province":"Z\u00fcrich",
    "wof:name":"Il Buongustaio Gmbh",
    "wof:placetype":"venue"
},
  "geometry": {"coordinates":[8.6156892776,47.2861938477],"type":"Point"}
}