{
  "type": "Feature",
  "properties": {
    "iso:country":"CH",
    "sg:address":"Bahnhofstrasse 8 3860 Meiringen. Postfach 265",
    "sg:city":"Meiringen",
    "sg:classifiers":[
        {
            "category":"Travel",
            "subcategory":"Hotels & Motels",
            "type":"Entertainment"
        }
    ],
    "sg:phone":"+41 33 971 14 23",
    "sg:postcode":"3860",
    "sg:province":"Bern",
    "sg:tags":[
        "hotels",
        "mit",
        "restaurant"
    ],
    "wof:name":"Hotel Brunner",
    "wof:placetype":"venue"
},
  "geometry": {"coordinates":[8.1858148575,46.727809906],"type":"Point"}
}