{
  "type": "Feature",
  "properties": {
    "iso:country":"CH",
    "sg:address":"Bubenried",
    "sg:city":"Gurzelen",
    "sg:orig_category":"Betrieb von Taxis",
    "sg:phone":"+41 33 345 36 23",
    "sg:postcode":"3663",
    "sg:province":"Bern",
    "wof:name":"Landtaxi Gmbh",
    "wof:placetype":"venue"
},
  "geometry": {"coordinates":[7.536223,46.769436],"type":"Point"}
}