{
  "type": "Feature",
  "properties": {
    "addr:full":"Lenzburgerstrasse 2 Niederlenz Aargau 5702",
    "addr:housenumber":"2",
    "addr:postcode":"5702",
    "addr:street":"Lenzburgerstrasse",
    "iso:country":"CH",
    "sg:address":"Lenzburgerstrasse 2",
    "sg:city":"Niederlenz",
    "sg:classifiers":[
        {
            "category":"Shopping",
            "subcategory":"Department Store",
            "type":"Retail Goods"
        }
    ],
    "sg:phone":"+41 62 892 27 77",
    "sg:postcode":"5702",
    "sg:province":"Aargau",
    "sg:tags":[
        "linen",
        "bed"
    ],
    "wof:name":"Hiltex Ag",
    "wof:placetype":"venue"
},
  "geometry": {"coordinates":[8.177565,47.399075],"type":"Point"}
}