{
  "type": "Feature",
  "properties": {
    "iso:country":"CH",
    "sg:address":"Landstrasse 8",
    "sg:city":"Kaiseraugst",
    "sg:orig_category":"Bauspenglerei Sanit\u00e4r, Heizungs U L\u00fcftungsinstallation",
    "sg:phone":"+41 71 244 76 48",
    "sg:postcode":"4303",
    "sg:province":"Aargau",
    "wof:name":"Schmucki Sanit\u00e4rtechnik Gmbh",
    "wof:placetype":"venue"
},
  "geometry": {"coordinates":[9.392208,47.436169],"type":"Point"}
}