{
  "type": "Feature",
  "properties": {
    "iso:country":"CH",
    "sg:address":"Aarburgerstrasse 31",
    "sg:city":"Zofingen",
    "sg:orig_category":"Autospenglereien",
    "sg:phone":"+41 62 751 53 88",
    "sg:postcode":"4800",
    "sg:province":"Aargau",
    "wof:name":"Marcel Tonini Carrosserie",
    "wof:placetype":"venue"
},
  "geometry": {"coordinates":[7.937349,47.295086],"type":"Point"}
}