{
  "type": "Feature",
  "properties": {
    "iso:country":"CH",
    "sg:address":"Breitschachenstrasse 9030 Abtwil Sg. Postfach",
    "sg:city":"Engelburg",
    "sg:orig_category":"Sonstiges Versicherungsgewerbe",
    "sg:postcode":"9032",
    "sg:province":"St. Gallen",
    "wof:name":"Vieh-versicherungs-genossenschaft Engelburg",
    "wof:placetype":"venue"
},
  "geometry": {"coordinates":[9.3191003799,47.4219245911],"type":"Point"}
}