{
  "type": "Feature",
  "properties": {
    "iso:country":"CH",
    "sg:address":"Dorf 6/8",
    "sg:city":"Altb\u00fcron",
    "sg:orig_category":"Detailhandel mit Waren verschiedener Art, Hauptrichtung Nahrungsmittel Grosshandel mit Nahrungsmitte",
    "sg:phone":"+41 62 927 11 63",
    "sg:postcode":"6147",
    "sg:province":"Luzern",
    "wof:name":"Sch\u00fcrch Ant.",
    "wof:placetype":"venue"
},
  "geometry": {"coordinates":[7.8813180923,47.1819839478],"type":"Point"}
}