{
  "type": "Feature",
  "properties": {
    "iso:country":"CH",
    "sg:address":"Bielstrasse 39",
    "sg:city":"Glis",
    "sg:orig_category":"Erzeugung U Erstbearbeitung von Aluminium Herstellung von Metallkonstruktionen",
    "sg:phone":"+41 27 923 73 43",
    "sg:postcode":"3902",
    "sg:province":"Valais",
    "wof:name":"Hans Heldner & A.kenzelmann Metallbauschlosserei",
    "wof:placetype":"venue"
},
  "geometry": {"coordinates":[7.962831974,46.3093757629],"type":"Point"}
}