{
  "type": "Feature",
  "properties": {
    "iso:country":"CH",
    "sg:address":"Seidenhausweg 2",
    "sg:city":"M\u00e4nnedorf",
    "sg:classifiers":[
        {
            "category":"Restaurant",
            "type":"Food & Drink"
        }
    ],
    "sg:phone":"+41 81 733 15 73",
    "sg:postcode":"8708",
    "sg:province":"Z\u00fcrich",
    "wof:name":"Restaurant Wiesental",
    "wof:placetype":"venue"
},
  "geometry": {"coordinates":[9.3716802597,47.0830192566],"type":"Point"}
}