{
  "type": "Feature",
  "properties": {
    "iso:country":"CH",
    "sg:address":"Rue Des Epancheurs 10",
    "sg:city":"Auvernier",
    "sg:orig_category":"Detailhandel mit Getr\u00e4nken Grosshandel mit Getr\u00e4nken",
    "sg:phone":"+41 32 731 21 08",
    "sg:postcode":"2012",
    "sg:province":"Neuch\u00e2tel",
    "wof:name":"Godet Henri-alexandre - Au Prieur\u00e9 St-pierre Sa",
    "wof:placetype":"venue"
},
  "geometry": {"coordinates":[6.8783378601,46.9756202698],"type":"Point"}
}