{
  "type": "Feature",
  "properties": {
    "iso:country":"CH",
    "sg:address":"Brunngasse 157",
    "sg:city":"Fehren",
    "sg:orig_category":"Sportvereine Motorrad",
    "sg:postcode":"4232",
    "sg:province":"Solothurn",
    "wof:name":"Moto-club Laufen & Umgebung",
    "wof:placetype":"venue"
},
  "geometry": {"coordinates":[7.57858181,47.3961791992],"type":"Point"}
}