{
  "type": "Feature",
  "properties": {
    "iso:country":"CH",
    "sg:address":"Talstrasse 20a",
    "sg:city":"Safnern",
    "sg:orig_category":"Sportvereine Turnen",
    "sg:phone":"+41 31 879 17 23",
    "sg:postcode":"2553",
    "sg:province":"Bern",
    "wof:name":"Turnverein Stv Rapperswil Be",
    "wof:placetype":"venue"
},
  "geometry": {"coordinates":[7.4121198654,47.0641288757],"type":"Point"}
}