{
  "type": "Feature",
  "properties": {
    "iso:country":"CH",
    "sg:address":"D\u00fcbendorfstrasse 300",
    "sg:city":"Z\u00fcrich",
    "sg:orig_category":"Primarschulen",
    "sg:phone":"+41 13222800",
    "sg:postcode":"8051",
    "sg:province":"Z\u00fcrich",
    "wof:name":"Primarschule Mattenhof",
    "wof:placetype":"venue"
},
  "geometry": {"coordinates":[8.589679718,47.3991203308],"type":"Point"}
}