{
  "type": "Feature",
  "properties": {
    "iso:country":"CH",
    "sg:address":"Simplon Rue Du 34 1006 Lausanne. Postfach",
    "sg:city":"Lausanne",
    "sg:orig_category":"Architektur U Ingenieurb\u00fcros",
    "sg:phone":"+41 21 617 64 44",
    "sg:postcode":"1003",
    "sg:province":"Vaud",
    "wof:name":"Iec Institut Pour L'economie Et La Construction Sa Activit\u00e9 Dans Le Dom. De L'architecture, De La Construction Etc",
    "wof:placetype":"venue"
},
  "geometry": {"coordinates":[6.626859,46.51672],"type":"Point"}
}