{
  "type": "Feature",
  "properties": {
    "addr:full":"Altgasse 50 Baar Zug 6340",
    "addr:housenumber":"50",
    "addr:postcode":"6340",
    "addr:street":"Altgasse;Zug",
    "iso:country":"CH",
    "sg:address":"Altgasse 50",
    "sg:city":"Baar",
    "sg:orig_category":"Architektur U Ingenieurb\u00fcros",
    "sg:postcode":"6340",
    "sg:province":"Zug",
    "wof:name":"Maxaba Gmbh",
    "wof:placetype":"venue"
},
  "geometry": {"coordinates":[8.516125,47.192108],"type":"Point"}
}