{
  "type": "Feature",
  "properties": {
    "iso:country":"CH",
    "sg:address":"Drehergasse 2",
    "sg:city":"Z\u00fcrich",
    "sg:orig_category":"Werbung",
    "sg:phone":"+41 13962050",
    "sg:postcode":"8008",
    "sg:province":"Z\u00fcrich",
    "wof:name":"Merz & Partner Events Ag",
    "wof:placetype":"venue"
},
  "geometry": {"coordinates":[8.5544023514,47.3632698059],"type":"Point"}
}