{
  "type": "Feature",
  "properties": {
    "iso:country":"CH",
    "sg:address":"Viale Giuseppe Cattori 3",
    "sg:city":"Paradiso",
    "sg:orig_category":"Fachdetailhandel in Verkaufsr\u00e4umen",
    "sg:postcode":"6900",
    "sg:province":"Ticino",
    "wof:name":"Marathon Sport Ag",
    "wof:placetype":"venue"
},
  "geometry": {"coordinates":[8.9455699921,45.9928817749],"type":"Point"}
}