{
  "type": "Feature",
  "properties": {
    "iso:country":"CH",
    "sg:address":"Trottenstrasse 41",
    "sg:city":"Z\u00fcrich",
    "sg:orig_category":"Elektro- and elektronische Maschinen Grosshandel Grosshandel mit Radio U Fernsehger\u00e4ten",
    "sg:postcode":"8037",
    "sg:province":"Z\u00fcrich",
    "wof:name":"Bechtle Comsoft Direct Ag",
    "wof:placetype":"venue"
},
  "geometry": {"coordinates":[8.520822525,47.395324707],"type":"Point"}
}