{
  "type": "Feature",
  "properties": {
    "iso:country":"CH",
    "sg:address":"Rosenstrasse 6",
    "sg:city":"M\u00fcnchenstein",
    "sg:orig_category":"Korrespondenz U Nachrichtenb\u00fcros, selbst\u00e4ndige Journalisten",
    "sg:postcode":"4142",
    "sg:province":"Basel-Landschaft",
    "wof:name":"Purple Communications Gmbh",
    "wof:placetype":"venue"
},
  "geometry": {"coordinates":[7.6151528358,47.522354126],"type":"Point"}
}