{
  "type": "Feature",
  "properties": {
    "iso:country":"CH",
    "sg:address":"Avenue De La Gare 26",
    "sg:city":"Sion",
    "sg:orig_category":"Sanit\u00e4r U Heizungsinstallation",
    "sg:phone":"+41 27 322 20 09",
    "sg:postcode":"1950",
    "sg:province":"Valais",
    "wof:name":"Marcel Recrosio Termica Chauffages",
    "wof:placetype":"venue"
},
  "geometry": {"coordinates":[7.3582229614,46.2304916382],"type":"Point"}
}