{
  "type": "Feature",
  "properties": {
    "iso:country":"CH",
    "sg:address":"Route De Cossonay",
    "sg:city":"Echallens",
    "sg:orig_category":"Maler U Glasergewerbe",
    "sg:phone":"+41 19354491",
    "sg:postcode":"1040",
    "sg:province":"Vaud",
    "wof:name":"Moser Peter",
    "wof:placetype":"venue"
},
  "geometry": {"coordinates":[8.7624673843,47.3060379028],"type":"Point"}
}