{
  "type": "Feature",
  "properties": {
    "iso:country":"CH",
    "sg:address":"Rue Du Vallon 16",
    "sg:city":"Lausanne",
    "sg:orig_category":"Fotografische Ateliers",
    "sg:phone":"+41 21 311 22 88",
    "sg:postcode":"1005",
    "sg:province":"Vaud",
    "wof:name":"Pierre-michel Delessert Atelier De Photographie",
    "wof:placetype":"venue"
},
  "geometry": {"coordinates":[6.637070179,46.5261497498],"type":"Point"}
}