{
  "type": "Feature",
  "properties": {
    "iso:country":"CH",
    "sg:address":"Letzistrasse 6 5432 Neuenhof. Postfach",
    "sg:city":"Neuenhof",
    "sg:orig_category":"Sanit\u00e4r, Heizungs U L\u00fcftungsinstallation",
    "sg:postcode":"5432",
    "sg:province":"Aargau",
    "wof:name":"Zentrale Haustechnik, Imboden S. Sanit\u00e4re Installationen In Neu- U. Umbauten Usw",
    "wof:placetype":"venue"
},
  "geometry": {"coordinates":[8.3314962387,47.4469451904],"type":"Point"}
}