{
  "type": "Feature",
  "properties": {
    "iso:country":"CH",
    "sg:address":"Zumhofstrasse 16",
    "sg:city":"Horw",
    "sg:orig_category":"Technische, physikalische U chemische Untersuchung",
    "sg:phone":"+41 41 340 07 67",
    "sg:postcode":"6048",
    "sg:province":"Luzern",
    "wof:name":"Foen Fachgemeinschaft Oekologie & Naturschutz",
    "wof:placetype":"venue"
},
  "geometry": {"coordinates":[8.3122749329,47.0224266052],"type":"Point"}
}