{
  "type": "Feature",
  "properties": {
    "iso:country":"CH",
    "sg:address":"Avenue De Tourbillon 100",
    "sg:city":"Sion",
    "sg:orig_category":"Elektro- and elektronische Maschinen Grosshandel Maschinen and Apparate divers Grosshandel",
    "sg:phone":"+41 21 323 61 40",
    "sg:postcode":"1950",
    "sg:province":"Valais",
    "wof:name":"Siemens Building Technologies (schweiz) Ag Landis & Staefa Division",
    "wof:placetype":"venue"
},
  "geometry": {"coordinates":[7.3691601753,46.2327270508],"type":"Point"}
}