{
  "type": "Feature",
  "properties": {
    "iso:country":"CH",
    "sg:address":"Allmendgasse 7",
    "sg:city":"Kaiseraugst",
    "sg:orig_category":"Allgemeiner Hoch U Tiefbau Maurerarbeiten",
    "sg:phone":"+41 61 811 31 88",
    "sg:postcode":"4303",
    "sg:province":"Aargau",
    "wof:name":"Martin Frech Kundenmaurer & Plattenbel\u00e4ge",
    "wof:placetype":"venue"
},
  "geometry": {"coordinates":[7.726539,47.540504],"type":"Point"}
}