{
  "type": "Feature",
  "properties": {
    "iso:country":"CH",
    "sg:address":"3975",
    "sg:city":"Bluche-randogne",
    "sg:orig_category":"Sanit\u00e4r, Heizungs U L\u00fcftungsinstallation",
    "sg:phone":"+41 81 833 40 63",
    "sg:postcode":"3975",
    "sg:province":"Valais",
    "wof:name":"Gini A. Heizung-sanit\u00e4r-l\u00fcftung, Vormals Dosch R.",
    "wof:placetype":"venue"
},
  "geometry": {"coordinates":[9.8381900787,46.4970588684],"type":"Point"}
}