{
  "type": "Feature",
  "properties": {
    "iso:country":"CH",
    "sg:address":"Theaterstrasse 12 8001 Z\u00fcrich. Postfach",
    "sg:city":"Z\u00fcrich",
    "sg:orig_category":"Warenh\u00e4user",
    "sg:phone":"+41 12614484",
    "sg:postcode":"8024",
    "sg:province":"Z\u00fcrich",
    "wof:name":"Abm Au Bon March\u00e9",
    "wof:placetype":"venue"
},
  "geometry": {"coordinates":[8.5463895798,47.3665008545],"type":"Point"}
}