{
  "type": "Feature",
  "properties": {
    "iso:country":"CH",
    "sg:address":"Bielstrasse 44",
    "sg:city":"Solothurn",
    "sg:orig_category":"Softwareentwicklung U beratung",
    "sg:phone":"+41 52 770 12 70",
    "sg:postcode":"4500",
    "sg:province":"Solothurn",
    "wof:name":"Impos Informatik, Dr. Gabriel Schenker",
    "wof:placetype":"venue"
},
  "geometry": {"coordinates":[8.9512195587,47.6170845032],"type":"Point"}
}