{
  "type": "Feature",
  "properties": {
    "iso:country":"CH",
    "sg:address":"Allmend",
    "sg:city":"M\u00fchlau",
    "sg:orig_category":"Verarbeitung von Milch Verwertung von Milch",
    "sg:postcode":"5642",
    "sg:province":"Aargau",
    "wof:name":"K\u00e4sereigenossenschaft M\u00fchlau",
    "wof:placetype":"venue"
},
  "geometry": {"coordinates":[8.3954677582,47.2331008911],"type":"Point"}
}