{
  "type": "Feature",
  "properties": {
    "iso:country":"CH",
    "sg:address":"Kirchgasse 50",
    "sg:city":"Chur",
    "sg:orig_category":"Sportvereine Unihockey",
    "sg:phone":"+41 81 353 20 04",
    "sg:postcode":"7000",
    "sg:province":"Graubunden",
    "wof:name":"Uhc Pegasus Chur",
    "wof:placetype":"venue"
},
  "geometry": {"coordinates":[9.5332098007,46.8480415344],"type":"Point"}
}