{
  "type": "Feature",
  "properties": {
    "iso:country":"CH",
    "sg:address":"Schafisheimerstrasse 11",
    "sg:city":"Staufen",
    "sg:orig_category":"Sportvereine Sch\u00fctzen Pistolen-& Gewehr",
    "sg:phone":"+41 62 891 87 84",
    "sg:postcode":"5603",
    "sg:province":"Aargau",
    "wof:name":"Sch\u00fctzengesellschaft",
    "wof:placetype":"venue"
},
  "geometry": {"coordinates":[8.1600561142,47.3841667175],"type":"Point"}
}