{
  "type": "Feature",
  "properties": {
    "iso:country":"CH",
    "sg:address":"R\u00fcteliweg 12",
    "sg:city":"Giebenach",
    "sg:orig_category":"Detailhandel mit Damenbekleidung Fachdetailhandel in Verkaufsr\u00e4umen",
    "sg:phone":"+41 41 410 68 68",
    "sg:postcode":"4304",
    "sg:province":"Basel-Landschaft",
    "wof:name":"Temo Luzern Ag",
    "wof:placetype":"venue"
},
  "geometry": {"coordinates":[7.740855217,47.5210113525],"type":"Point"}
}