{
  "type": "Feature",
  "properties": {
    "iso:country":"CH",
    "sg:address":"Jurastr. 20",
    "sg:city":"Grenchen",
    "sg:classifiers":[
        {
            "category":"Wholesale",
            "subcategory":"Machinery & Supplies",
            "type":"Manufacturing & Wholesale Goods"
        }
    ],
    "sg:phone":"+41 32 655 65 20",
    "sg:postcode":"2540",
    "sg:province":"Solothurn",
    "sg:tags":[
        "equipment",
        "equipement",
        "precision",
        "timekeeping"
    ],
    "wof:name":"Vereinigte Pignonsfabriken Ag",
    "wof:placetype":"venue"
},
  "geometry": {"coordinates":[7.4003329277,47.1966972351],"type":"Point"}
}