{
  "type": "Feature",
  "properties": {
    "iso:country":"CH",
    "sg:address":"Strengelbacherstrasse 5",
    "sg:city":"Brittnau",
    "sg:orig_category":"Blumen U Zierpflanzenbau Detailhandel mit Blumen U Pflanzen",
    "sg:phone":"+41 62 751 16 20",
    "sg:postcode":"4805",
    "sg:province":"Aargau",
    "wof:name":"Eugen Zimmerli",
    "wof:placetype":"venue"
},
  "geometry": {"coordinates":[7.94449,47.261349],"type":"Point"}
}