{
  "type": "Feature",
  "properties": {
    "iso:country":"CH",
    "sg:address":"Steinenbachstrasse",
    "sg:city":"Ebnat-kappel",
    "sg:orig_category":"Bauspenglerei Dachdeckerei",
    "sg:phone":"+41 62 212 66 56",
    "sg:postcode":"9642",
    "sg:province":"St. Gallen",
    "wof:name":"Husi Markus Sanit\u00e4r Heizung Sanit\u00e4ren Installationen, Heizungsanlagen Usw",
    "wof:placetype":"venue"
},
  "geometry": {"coordinates":[7.873545,47.344597],"type":"Point"}
}