{
  "type": "Feature",
  "properties": {
    "iso:country":"CH",
    "sg:address":"Via San Bernardo",
    "sg:city":"Comano",
    "sg:orig_category":"Malerei Tapeziererei",
    "sg:phone":"+41 91 941 75 72",
    "sg:postcode":"6949",
    "sg:province":"Ticino",
    "wof:name":"Renato Mattei Impresa Di Pittura",
    "wof:placetype":"venue"
},
  "geometry": {"coordinates":[8.9550523758,46.0394210815],"type":"Point"}
}