{
  "type": "Feature",
  "properties": {
    "iso:country":"CH",
    "sg:address":"Dorfplatz 9",
    "sg:city":"Zumikon",
    "sg:classifiers":[
        {
            "category":"Education",
            "subcategory":"Library",
            "type":"Public Place"
        }
    ],
    "sg:phone":"+41 19181948",
    "sg:postcode":"8126",
    "sg:province":"Z\u00fcrich",
    "sg:tags":[
        "u",
        "bibliotheken",
        "archive"
    ],
    "wof:name":"Gemeindebibliothek Gemeinschaftszentrum",
    "wof:placetype":"venue"
},
  "geometry": {"coordinates":[8.62373,47.331806],"type":"Point"}
}