{
  "type": "Feature",
  "properties": {
    "iso:country":"CH",
    "sg:address":"Rotmatt 35",
    "sg:city":"Hermetschwil-staff",
    "sg:orig_category":"Detailhandel mit M\u00f6beln U Haushaltsgegenst\u00e4nden Innenausbau",
    "sg:phone":"+41 22 342 23 23",
    "sg:postcode":"5626",
    "sg:province":"Aargau",
    "wof:name":"Teo Jakob Tagliabue Sa",
    "wof:placetype":"venue"
},
  "geometry": {"coordinates":[6.1417188644,46.1874656677],"type":"Point"}
}