{
  "type": "Feature",
  "properties": {
    "iso:country":"CH",
    "sg:address":"Oberdorf 3",
    "sg:city":"N\u00e4fels",
    "sg:orig_category":"Allgemeiner Hoch U Tiefbau",
    "sg:phone":"+41 79 693 22 23",
    "sg:postcode":"8752",
    "sg:province":"Glarus",
    "wof:name":"Tinufa Gmbh",
    "wof:placetype":"venue"
},
  "geometry": {"coordinates":[9.063539,47.097557],"type":"Point"}
}