{
  "type": "Feature",
  "properties": {
    "iso:country":"CH",
    "sg:address":"S\u00e4gebachweg",
    "sg:city":"Oberwichtrach",
    "sg:orig_category":"Sonstige Kultur U Unterhaltungseinrichtungen",
    "sg:phone":"+41 31 780 20 20",
    "sg:postcode":"3114",
    "sg:province":"Bern",
    "wof:name":"Sportzentrum Aaretal",
    "wof:placetype":"venue"
},
  "geometry": {"coordinates":[7.5765061378,46.8433647156],"type":"Point"}
}