{
  "type": "Feature",
  "properties": {
    "iso:country":"CH",
    "sg:address":"Wesenplatz 3",
    "sg:city":"Flaach",
    "sg:orig_category":"Lagerung",
    "sg:phone":"+41 52 318 22 57",
    "sg:postcode":"8416",
    "sg:province":"Z\u00fcrich",
    "wof:name":"Decopar Gmbh",
    "wof:placetype":"venue"
},
  "geometry": {"coordinates":[8.608546257,47.5757598877],"type":"Point"}
}