{
  "type": "Feature",
  "properties": {
    "iso:country":"CH",
    "sg:address":"Rive Cours De 4 1204 Gen\u00e8ve. Postfach",
    "sg:city":"Gen\u00e8ve",
    "sg:orig_category":"Non-Classified Establishments",
    "sg:postcode":"1204",
    "sg:province":"Gen\u00e8ve",
    "wof:name":"Soci\u00e9t\u00e9 Immobili\u00e8re Aux Grandes Vignes",
    "wof:placetype":"venue"
},
  "geometry": {"coordinates":[7.4068250656,46.2767829895],"type":"Point"}
}