{
  "type": "Feature",
  "properties": {
    "iso:country":"CH",
    "sg:address":"Klosterplatz 24",
    "sg:city":"Metzerlen",
    "sg:classifiers":[
        {
            "category":"Travel",
            "subcategory":"Hotels & Motels",
            "type":"Entertainment"
        }
    ],
    "sg:postcode":"4116",
    "sg:province":"Solothurn",
    "sg:tags":[
        "hotels",
        "mit",
        "restaurant"
    ],
    "wof:name":"Hjs H\u00f4tels S\u00e0rl",
    "wof:placetype":"venue"
},
  "geometry": {"coordinates":[7.1649050713,46.7464141846],"type":"Point"}
}