{
  "type": "Feature",
  "properties": {
    "iso:country":"CH",
    "sg:address":"Avenue Krieg 28",
    "sg:city":"Gen\u00e8ve",
    "sg:orig_category":"Einzelhandel mit Automobilteilen U Zubeh\u00f6r",
    "sg:phone":"+41 32 384 43 09",
    "sg:postcode":"1208",
    "sg:province":"Gen\u00e8ve",
    "wof:name":"Alfred Gerber Pneuhandel",
    "wof:placetype":"venue"
},
  "geometry": {"coordinates":[7.3266468048,47.1009674072],"type":"Point"}
}