{
  "type": "Feature",
  "properties": {
    "iso:country":"CH",
    "sg:address":"Rue De Gen\u00e8ve 154",
    "sg:city":"Th\u00f4nex",
    "sg:classifiers":[
        {
            "category":"Restaurant",
            "type":"Food & Drink"
        }
    ],
    "sg:phone":"+41 22 348 61 06",
    "sg:postcode":"1226",
    "sg:province":"Gen\u00e8ve",
    "wof:name":"Caf\u00e9-restaurant De La Douane",
    "wof:placetype":"venue"
},
  "geometry": {"coordinates":[6.206384182,46.1920585632],"type":"Point"}
}