{
  "type": "Feature",
  "properties": {
    "iso:country":"CH",
    "sg:address":"5245",
    "sg:city":"Habsburg",
    "sg:orig_category":"Sportvereine Sch\u00fctzen",
    "sg:postcode":"5245",
    "sg:province":"Aargau",
    "wof:name":"Sch\u00fctzengesellschaft",
    "wof:placetype":"venue"
},
  "geometry": {"coordinates":[8.1239700317,47.5564689636],"type":"Point"}
}