{
  "type": "Feature",
  "properties": {
    "iso:country":"CH",
    "sg:address":"Grafenauweg 12",
    "sg:city":"Zug",
    "sg:orig_category":"Unclassifiable Establishments",
    "sg:phone":"+41 41 729 29 44",
    "sg:postcode":"6300",
    "sg:province":"Zug",
    "wof:name":"Unilever Overseas Holdings Ag",
    "wof:placetype":"venue"
},
  "geometry": {"coordinates":[8.5119304657,47.1742553711],"type":"Point"}
}