{
  "type": "Feature",
  "properties": {
    "iso:country":"CH",
    "sg:address":"Lenggenbachstrasse 9",
    "sg:city":"Fahrweid",
    "sg:orig_category":"Installation von Heizungs, L\u00fcftungs U Klimaanlagen",
    "sg:phone":"+41 17470585",
    "sg:postcode":"8951",
    "sg:province":"Z\u00fcrich",
    "wof:name":"Airtop Gmbh L\u00fcftung Klima K\u00e4lte",
    "wof:placetype":"venue"
},
  "geometry": {"coordinates":[8.4154319763,47.4120483398],"type":"Point"}
}