{
  "type": "Feature",
  "properties": {
    "iso:country":"CH",
    "sg:address":"Amthausstrasse 2",
    "sg:city":"Breitenbach",
    "sg:orig_category":"Konkurs- and Betreibungs\u00e4mter",
    "sg:phone":"+41 61 781 24 52",
    "sg:postcode":"4226",
    "sg:province":"Solothurn",
    "wof:name":"Kant. Betreibungs-& Konkursamt",
    "wof:placetype":"venue"
},
  "geometry": {"coordinates":[7.5436468124,47.4049758911],"type":"Point"}
}