{
  "type": "Feature",
  "properties": {
    "iso:country":"CH",
    "sg:address":"Chemin Champ-belluet 16c",
    "sg:city":"Blonay",
    "sg:orig_category":"Instandhaltung U Reparatur von Automobilen",
    "sg:phone":"+41 21 943 33 36",
    "sg:postcode":"1807",
    "sg:province":"Vaud",
    "wof:name":"Garage De Blonay, Ribordy Yves.",
    "wof:placetype":"venue"
},
  "geometry": {"coordinates":[6.8935961723,46.4659461975],"type":"Point"}
}