{
  "type": "Feature",
  "properties": {
    "iso:country":"CH",
    "sg:address":"Krieg Avenue 42 1208 Gen\u00e8ve. Postfach",
    "sg:city":"Gen\u00e8ve",
    "sg:orig_category":"Unclassifiable Establishments",
    "sg:postcode":"1208",
    "sg:province":"Gen\u00e8ve",
    "wof:name":"Soci\u00e9t\u00e9 Immobili\u00e8re Du Garage Des P\u00e2quis",
    "wof:placetype":"venue"
},
  "geometry": {"coordinates":[6.1620202065,46.1946487427],"type":"Point"}
}