{
  "type": "Feature",
  "properties": {
    "iso:country":"CH",
    "sg:address":"Franscini Viale 3",
    "sg:city":"Lugano",
    "sg:orig_category":"Religi\u00f6se Vereinigungen",
    "sg:postcode":"6900",
    "sg:province":"Ticino",
    "wof:name":"Lama Gangchen World Pence Foundation International Charitable Trust",
    "wof:placetype":"venue"
},
  "geometry": {"coordinates":[8.9526252747,46.0081977844],"type":"Point"}
}