{
  "type": "Feature",
  "properties": {
    "iso:country":"CH",
    "sg:address":"Kronenstrasse 9",
    "sg:city":"St\u00e4fa",
    "sg:orig_category":"Rechtsberatung Wirtschaftspr\u00fcfung, Steuerberatung U Treuhand",
    "sg:phone":"+41 55 415 40 60",
    "sg:postcode":"8712",
    "sg:province":"Z\u00fcrich",
    "wof:name":"Convisa Ag",
    "wof:placetype":"venue"
},
  "geometry": {"coordinates":[8.7771053314,47.2004928589],"type":"Point"}
}