{
  "type": "Feature",
  "properties": {
    "iso:country":"CH",
    "sg:address":"Seestrasse 52",
    "sg:city":"Gersau",
    "sg:orig_category":"Instandhaltung U Reparatur von Automobilen",
    "sg:phone":"+41 41 828 16 81",
    "sg:postcode":"6442",
    "sg:province":"Schwyz",
    "wof:name":"Seegarage Gersau",
    "wof:placetype":"venue"
},
  "geometry": {"coordinates":[8.5216989517,46.9931335449],"type":"Point"}
}