{
  "type": "Feature",
  "properties": {
    "iso:country":"CH",
    "sg:address":"Am Bachweg 4",
    "sg:city":"Uttigen",
    "sg:orig_category":"Grosshandel mit lebenden Tieren",
    "sg:phone":"+41 33 345 53 00",
    "sg:postcode":"3628",
    "sg:province":"Bern",
    "wof:name":"Hans Jakob Viehhandel",
    "wof:placetype":"venue"
},
  "geometry": {"coordinates":[7.5745711327,46.7938079834],"type":"Point"}
}