{
  "type": "Feature",
  "properties": {
    "iso:country":"CH",
    "sg:address":"Im H\u00f6fli",
    "sg:city":"Haldenstein",
    "sg:orig_category":"Interessenvertretungen",
    "sg:postcode":"7023",
    "sg:province":"Graubunden",
    "wof:name":"Wohnmitte",
    "wof:placetype":"venue"
},
  "geometry": {"coordinates":[9.5266046524,46.8787574768],"type":"Point"}
}