{
  "type": "Feature",
  "properties": {
    "iso:country":"CH",
    "sg:address":"Avenue De Corsier 3",
    "sg:city":"Vevey",
    "sg:orig_category":"Detailhandel mit Brot, Back U S\u00fcsswaren",
    "sg:phone":"+41 21 923 53 73",
    "sg:postcode":"1800",
    "sg:province":"Vaud",
    "wof:name":"Georges Pisu Boulangerie-p\u00e2tisserie",
    "wof:placetype":"venue"
},
  "geometry": {"coordinates":[6.844743,46.466526],"type":"Point"}
}