{
  "type": "Feature",
  "properties": {
    "iso:country":"CH",
    "sg:address":"Grossweid 41",
    "sg:city":"Aathal-seegr\u00e4ben",
    "sg:orig_category":"Allgemeiner Hoch U Tiefbau Hoch U Tiefbau",
    "sg:phone":"+41 71 244 68 79",
    "sg:postcode":"8607",
    "sg:province":"Z\u00fcrich",
    "wof:name":"Remo-bau, Moser Renato",
    "wof:placetype":"venue"
},
  "geometry": {"coordinates":[9.392048,47.436722],"type":"Point"}
}