{
  "type": "Feature",
  "properties": {
    "iso:country":"CH",
    "sg:address":"Hauptstrasse 8",
    "sg:city":"Steinmaur",
    "sg:orig_category":"Vereine Vogel-& Naturschutz",
    "sg:phone":"+41 18534049",
    "sg:postcode":"8162",
    "sg:province":"Z\u00fcrich",
    "wof:name":"Natur-& Vogelschutzverein",
    "wof:placetype":"venue"
},
  "geometry": {"coordinates":[8.4469928741,47.4930152893],"type":"Point"}
}