{
  "type": "Feature",
  "properties": {
    "iso:country":"CH",
    "sg:address":"Trungen",
    "sg:city":"Bronschhofen",
    "sg:orig_category":"Verarbeitung von Milch Verwertung von Milch",
    "sg:phone":"+41 71 622 18 39",
    "sg:postcode":"9552",
    "sg:province":"St. Gallen",
    "wof:name":"Schindler Werner",
    "wof:placetype":"venue"
},
  "geometry": {"coordinates":[9.1381845474,47.5666694641],"type":"Point"}
}