{
  "type": "Feature",
  "properties": {
    "iso:country":"CH",
    "sg:address":"Laubbach Hirschmatt",
    "sg:city":"Guggisberg",
    "sg:orig_category":"Detailhandel mit Brot, Back U S\u00fcsswaren Detailhandel mit Waren verschiedener Art, Hauptrichtung Nahr",
    "sg:phone":"+41 31 735 51 15",
    "sg:postcode":"3158",
    "sg:province":"Bern",
    "wof:name":"E. Zbinden",
    "wof:placetype":"venue"
},
  "geometry": {"coordinates":[7.323758,46.756149],"type":"Point"}
}