{
  "type": "Feature",
  "properties": {
    "iso:country":"CH",
    "sg:address":"Mon-repos Avenue 10",
    "sg:city":"Lausanne",
    "sg:orig_category":"Fernmeldedienste",
    "sg:phone":"+41 41 872 02 38",
    "sg:postcode":"1005",
    "sg:province":"Vaud",
    "wof:name":"Binatec Ag Nachrichten- U. Kommunikationstechnik Usw.; Dienstleistungen",
    "wof:placetype":"venue"
},
  "geometry": {"coordinates":[8.6455793381,46.8809242249],"type":"Point"}
}