{
  "type": "Feature",
  "properties": {
    "iso:country":"CH",
    "sg:address":"Eschenmosen 362 8180 B\u00fclach. Postfach",
    "sg:city":"B\u00fclach",
    "sg:orig_category":"Herstellung von Automobilen",
    "sg:postcode":"8180",
    "sg:province":"Z\u00fcrich",
    "wof:name":"Mwm Werk 4 Meier + Wacker",
    "wof:placetype":"venue"
},
  "geometry": {"coordinates":[8.5669240952,47.5157470703],"type":"Point"}
}