{
  "type": "Feature",
  "properties": {
    "iso:country":"CH",
    "sg:address":"Alpenstrasse 11 6300 Zug. Postfach 4819",
    "sg:city":"Zug",
    "sg:orig_category":"Vereine Haus- and Grundeigent\u00fcmer",
    "sg:phone":"+41 41 710 65 20",
    "sg:postcode":"6304",
    "sg:province":"Zug",
    "wof:name":"Hauseigent\u00fcmerverband Zug & Umgebung",
    "wof:placetype":"venue"
},
  "geometry": {"coordinates":[8.5145874023,47.1726150513],"type":"Point"}
}