{
  "type": "Feature",
  "properties": {
    "iso:country":"CH",
    "sg:address":"Tonishofstrasse 14",
    "sg:city":"Walchwil",
    "sg:orig_category":"Druckweiterverarbeitung",
    "sg:phone":"+41 41 758 25 38",
    "sg:postcode":"6318",
    "sg:province":"Zug",
    "wof:name":"Grafisches Atelier Hildbrand Kurt",
    "wof:placetype":"venue"
},
  "geometry": {"coordinates":[8.5176172256,47.1007194519],"type":"Point"}
}