{
  "type": "Feature",
  "properties": {
    "iso:country":"CH",
    "sg:address":"Via Pini 1",
    "sg:city":"Biasca",
    "sg:orig_category":"Detailhandel mit Brot, Back U S\u00fcsswaren",
    "sg:phone":"+41 91 862 21 60",
    "sg:postcode":"6710",
    "sg:province":"Ticino",
    "wof:name":"Fabrizio & Claudio Conti Pasticceria & Panetteria",
    "wof:placetype":"venue"
},
  "geometry": {"coordinates":[8.970715,46.359879],"type":"Point"}
}