{
  "type": "Feature",
  "properties": {
    "iso:country":"CH",
    "sg:address":"Dorfstrasse 27",
    "sg:city":"Emmetten",
    "sg:orig_category":"Unclassifiable Establishments",
    "sg:postcode":"6376",
    "sg:province":"Nidwalden",
    "wof:name":"Dr. Med. Semun Abdili Arzt F\u00fcr Allgemeine Medizin",
    "wof:placetype":"venue"
},
  "geometry": {"coordinates":[8.5130147934,46.9569702148],"type":"Point"}
}