{
  "type": "Feature",
  "properties": {
    "iso:country":"CH",
    "sg:address":"Bahnhofstrasse 10 5000 Aarau. Postfach",
    "sg:city":"Aarau",
    "sg:orig_category":"Politische Parteien FDP",
    "sg:phone":"+41 32 724 66 91",
    "sg:postcode":"5001",
    "sg:province":"Aargau",
    "wof:name":"Parti Radical Democratique Neuch\u00e2telois",
    "wof:placetype":"venue"
},
  "geometry": {"coordinates":[6.9290781021,46.9904403687],"type":"Point"}
}