{
  "type": "Feature",
  "properties": {
    "iso:country":"CH",
    "sg:address":"7405",
    "sg:city":"Rothenbrunnen",
    "sg:orig_category":"Bauspenglerei Zimmerei, Dachdeckerei, Bauspenglerei U Abdichtung",
    "sg:phone":"+41 81 655 13 00",
    "sg:postcode":"7405",
    "sg:province":"Graubunden",
    "wof:name":"Wechler Marco",
    "wof:placetype":"venue"
},
  "geometry": {"coordinates":[9.42094,46.778278],"type":"Point"}
}