{
  "type": "Feature",
  "properties": {
    "iso:country":"CH",
    "sg:address":"Kirchgasse 11",
    "sg:city":"Olten",
    "sg:orig_category":"Psychotherapie",
    "sg:phone":"+41 62 212 36 73",
    "sg:postcode":"4600",
    "sg:province":"Solothurn",
    "wof:name":"Andreas Widmer Psychotherapie",
    "wof:placetype":"venue"
},
  "geometry": {"coordinates":[7.9016809464,47.3496894836],"type":"Point"}
}