{
  "type": "Feature",
  "properties": {
    "iso:country":"CH",
    "sg:address":"Mythenstrasse 48 8400 Winterthur. Postfach 155",
    "sg:city":"Winterthur",
    "sg:orig_category":"Handelsvermittlung U Grosshandel",
    "sg:phone":"+41 52 203 16 16",
    "sg:postcode":"8407",
    "wof:name":"Prinova Ag",
    "wof:placetype":"venue"
},
  "geometry": {"coordinates":[8.7094373703,47.4967575073],"type":"Point"}
}