{
  "type": "Feature",
  "properties": {
    "iso:country":"CH",
    "sg:address":"Gabris Heiligkreuz",
    "sg:city":"Hosenruck",
    "sg:classifiers":[
        {
            "category":"Restaurant",
            "type":"Food & Drink"
        }
    ],
    "sg:phone":"+41 71 947 12 58",
    "sg:postcode":"9515",
    "sg:province":"Thurgau",
    "wof:name":"Restaurant Traube",
    "wof:placetype":"venue"
},
  "geometry": {"coordinates":[9.122209549,47.4905891418],"type":"Point"}
}