{
  "type": "Feature",
  "properties": {
    "iso:country":"CH",
    "sg:address":"Bahnhofstrasse 8",
    "sg:city":"M\u00fcntschemier",
    "sg:orig_category":"Vereine Gesang",
    "sg:postcode":"3225",
    "sg:province":"Bern",
    "wof:name":"M\u00e4nnerchor Aesta Ins",
    "wof:placetype":"venue"
},
  "geometry": {"coordinates":[7.142165184,46.9946632385],"type":"Point"}
}