{
  "type": "Feature",
  "properties": {
    "addr:full":"R\u00fctschetenstrasse 1 Liestal Basel-Landschaft 4410",
    "addr:housenumber":"1",
    "addr:postcode":"4410",
    "addr:street":"Ruetschetenstrasse",
    "iso:country":"CH",
    "sg:address":"R\u00fctschetenstrasse 1",
    "sg:city":"Liestal",
    "sg:orig_category":"Architektur U Ingenieurb\u00fcros Elektrizit\u00e4tsversorgung",
    "sg:phone":"+41 61 923 02 03",
    "sg:postcode":"4410",
    "sg:province":"Basel-Landschaft",
    "wof:name":"Altermo Ag Ingenieurb\u00fcro F\u00fcr Elektrotechnik Und Elektroplanung",
    "wof:placetype":"venue"
},
  "geometry": {"coordinates":[7.732305,47.474728],"type":"Point"}
}