{
  "type": "Feature",
  "properties": {
    "iso:country":"CH",
    "sg:address":"Gassackerweg 11",
    "sg:city":"Lupsingen",
    "sg:orig_category":"Handel mit Automobilen",
    "sg:postcode":"4419",
    "sg:province":"Basel-Landschaft",
    "wof:name":"E. Neuschwander Autohandel",
    "wof:placetype":"venue"
},
  "geometry": {"coordinates":[7.6895608902,47.4443817139],"type":"Point"}
}