{
  "type": "Feature",
  "properties": {
    "iso:country":"CH",
    "sg:address":"R\u00f6telstrasse 24",
    "sg:city":"Z\u00fcrich",
    "sg:orig_category":"Erbringung von Dienstleistungen f\u00fcr Unternehmen Werbung",
    "sg:phone":"+41 13643180",
    "sg:postcode":"8004",
    "sg:province":"Z\u00fcrich",
    "wof:name":"Christian Kitzmueller Illustration, Graphik",
    "wof:placetype":"venue"
},
  "geometry": {"coordinates":[8.5371217728,47.3908653259],"type":"Point"}
}