{
  "type": "Feature",
  "properties": {
    "iso:country":"CH",
    "sg:address":"Gerbestrasse 10",
    "sg:city":"R\u00fcegsauschachen",
    "sg:orig_category":"RESTAURANTS: TEA-ROOMS",
    "sg:phone":"+41 34 461 38 98",
    "sg:postcode":"3415",
    "sg:province":"Bern",
    "wof:name":"Forster Bruno, Tea-room Pony",
    "wof:placetype":"venue"
},
  "geometry": {"coordinates":[7.6617732048,47.0175437927],"type":"Point"}
}