{
  "type": "Feature",
  "properties": {
    "iso:country":"CH",
    "sg:address":"Bruggerstrasse 4",
    "sg:city":"Mellingen",
    "sg:orig_category":"Reiseb\u00fcros",
    "sg:phone":"+41 56 491 02 23",
    "sg:postcode":"5507",
    "sg:province":"Aargau",
    "wof:name":"Alpen Lee Reisen",
    "wof:placetype":"venue"
},
  "geometry": {"coordinates":[8.2735290527,47.4188995361],"type":"Point"}
}