{
  "type": "Feature",
  "properties": {
    "iso:country":"CH",
    "sg:address":"Galleria Della Carr\u00e0",
    "sg:city":"Ascona",
    "sg:orig_category":"Non-Classified Establishments",
    "sg:postcode":"6612",
    "sg:province":"Ticino",
    "wof:name":"Immobiliare Carr\u00e0 Sagl",
    "wof:placetype":"venue"
},
  "geometry": {"coordinates":[8.7682847977,46.1553192139],"type":"Point"}
}