{
  "type": "Feature",
  "properties": {
    "iso:country":"CH",
    "sg:address":"Morand Rue Marc 1",
    "sg:city":"Martigny",
    "sg:orig_category":"Non-Classified Establishments",
    "sg:postcode":"1920",
    "sg:province":"Valais",
    "wof:name":"Le Baobab Martigny S\u00e0rl",
    "wof:placetype":"venue"
},
  "geometry": {"coordinates":[7.0733399391,46.1018447876],"type":"Point"}
}