{
  "type": "Feature",
  "properties": {
    "iso:country":"CH",
    "sg:address":"Im Gr\u00fct 12",
    "sg:city":"Wettswil",
    "sg:orig_category":"Sportvereine Motorrad",
    "sg:postcode":"8907",
    "sg:province":"Z\u00fcrich",
    "wof:name":"Motorradfahrerbund Davos",
    "wof:placetype":"venue"
},
  "geometry": {"coordinates":[9.8201246262,46.7896270752],"type":"Point"}
}