{
  "type": "Feature",
  "properties": {
    "iso:country":"CH",
    "sg:address":"Rue De La Gare 39",
    "sg:city":"Nyon",
    "sg:orig_category":"Detailhandel mit Lederwaren U Reiseartikeln",
    "sg:phone":"+41 22 361 98 90",
    "sg:postcode":"1260",
    "sg:province":"Vaud",
    "wof:name":"Mode Azur Mode Enfantine & Future-maman",
    "wof:placetype":"venue"
},
  "geometry": {"coordinates":[6.2363038063,46.383430481],"type":"Point"}
}