{
  "type": "Feature",
  "properties": {
    "iso:country":"CH",
    "sg:address":"Via S. Franscini 2",
    "sg:city":"Chiasso",
    "sg:orig_category":"Vermietung U Verpachtung von eigenen Immobilien",
    "sg:postcode":"6830",
    "sg:province":"Ticino",
    "wof:name":"Sottobisio Sa",
    "wof:placetype":"venue"
},
  "geometry": {"coordinates":[9.0281076431,45.8362503052],"type":"Point"}
}