{
  "type": "Feature",
  "properties": {
    "iso:country":"CH",
    "sg:address":"Krummackerweg 9",
    "sg:city":"Olten",
    "sg:orig_category":"Vorschulen, Kinderg\u00e4rten",
    "sg:phone":"+41 62 296 29 55",
    "sg:postcode":"4600",
    "sg:province":"Solothurn",
    "wof:name":"Kindergarten St.marien",
    "wof:placetype":"venue"
},
  "geometry": {"coordinates":[7.9131689072,47.3481636047],"type":"Point"}
}