{
  "type": "Feature",
  "properties": {
    "iso:country":"CH",
    "sg:address":"Birkenmatte",
    "sg:city":"Rotkreuz",
    "sg:orig_category":"HERSTELLUNG VON GER\u00c4TEN DER ELEKTRIZIT\u00c4TSERZEUGUNG, -VERTEILUNG U.\u00c4 Herstellung von sonstigen elektr",
    "sg:postcode":"6343",
    "sg:province":"Zug",
    "wof:name":"Hotz & Gerber Ag",
    "wof:placetype":"venue"
},
  "geometry": {"coordinates":[8.4941072464,47.4997596741],"type":"Point"}
}