{
  "type": "Feature",
  "properties": {
    "addr:full":"Felsweg 4 5727 Oberkulm. Postfach Oberkulm Aargau 5727",
    "addr:housenumber":"4",
    "addr:postcode":"5727;5727",
    "addr:street":"Felsweg",
    "iso:country":"CH",
    "sg:address":"Felsweg 4 5727 Oberkulm. Postfach",
    "sg:city":"Oberkulm",
    "sg:orig_category":"Dachdeckerei Zimmerei, Dachdeckerei, Bauspenglerei U Abdichtung",
    "sg:phone":"+41 62 776 25 55",
    "sg:postcode":"5727",
    "sg:province":"Aargau",
    "wof:name":"Hirt Isolierbau Aktiengesellschaft",
    "wof:placetype":"venue"
},
  "geometry": {"coordinates":[8.125994,47.300625],"type":"Point"}
}