{
  "type": "Feature",
  "properties": {
    "iso:country":"CH",
    "sg:address":"Boulevard Georges-favon 1 1204 Gen\u00e8ve. Postfach 1215 Gen\u00e8ve",
    "sg:city":"D\u00e9p\u00f4t",
    "sg:orig_category":"Mit dem Versicherungsgewerbe verbundene T\u00e4tigkeiten",
    "sg:phone":"+41 22 929 86 83",
    "sg:postcode":"15",
    "wof:name":"Primogefi Sa",
    "wof:placetype":"venue"
},
  "geometry": {"coordinates":[6.1401247978,46.2039718628],"type":"Point"}
}