{
  "type": "Feature",
  "properties": {
    "iso:country":"CH",
    "sg:address":"Chemin Des Pr\u00e9alpes 33",
    "sg:city":"Bulle",
    "sg:orig_category":"Unclassifiable Establishments",
    "sg:postcode":"1630",
    "sg:province":"Fribourg",
    "wof:name":"Aaa Aba Taxis S.\u00e0 R.l.",
    "wof:placetype":"venue"
},
  "geometry": {"coordinates":[7.0514779091,46.618019104],"type":"Point"}
}