{
  "type": "Feature",
  "properties": {
    "iso:country":"CH",
    "sg:address":"Worbstrasse 191",
    "sg:city":"G\u00fcmligen",
    "sg:orig_category":"Erbringung von Dienstleistungen f\u00fcr Unternehmen",
    "sg:postcode":"3073",
    "sg:province":"Bern",
    "wof:name":"Dekor Greb. Frau",
    "wof:placetype":"venue"
},
  "geometry": {"coordinates":[9.0145845413,47.4487686157],"type":"Point"}
}