{
  "type": "Feature",
  "properties": {
    "iso:country":"CH",
    "sg:address":"Bielstrasse 42",
    "sg:city":"Lyss",
    "sg:orig_category":"Bauschreinerei Innenausbau",
    "sg:phone":"+41 32 384 24 74",
    "sg:postcode":"3250",
    "sg:province":"Bern",
    "wof:name":"Robert Fahrer M\u00f6belschreinerei Innenausbau",
    "wof:placetype":"venue"
},
  "geometry": {"coordinates":[7.303018,47.077976],"type":"Point"}
}