{
  "type": "Feature",
  "properties": {
    "iso:country":"CH",
    "sg:address":"Zellfeld",
    "sg:city":"Schenkon",
    "sg:classifiers":[
        {
            "category":"Sports & Exercise",
            "subcategory":"Tennis Court",
            "type":"Entertainment"
        }
    ],
    "sg:phone":"+41 41 921 34 63",
    "sg:postcode":"6214",
    "sg:province":"Luzern",
    "sg:tags":[
        "squash-centers",
        "hallen",
        "tennis-"
    ],
    "wof:name":"Tenniscenter",
    "wof:placetype":"venue"
},
  "geometry": {"coordinates":[8.1263837814,47.1813163757],"type":"Point"}
}