{
  "type": "Feature",
  "properties": {
    "addr:full":"Nestl\u00e9strasse 7 Cham Zug 6330",
    "addr:housenumber":"7",
    "addr:postcode":"6330",
    "addr:street":"Nestle\u0301Strasse;Zug",
    "iso:country":"CH",
    "sg:address":"Nestl\u00e9strasse 7",
    "sg:city":"Cham",
    "sg:orig_category":"Detailhandel mit B\u00fcromaschinen U einrichtungen",
    "sg:phone":"+41 41 780 01 13",
    "sg:postcode":"6330",
    "sg:province":"Zug",
    "wof:name":"Hoeko H\u00f6hener Pr\u00e4sentationssysteme",
    "wof:placetype":"venue"
},
  "geometry": {"coordinates":[8.463864,47.180981],"type":"Point"}
}