{
  "type": "Feature",
  "properties": {
    "iso:country":"CH",
    "sg:address":"Dubematt 1",
    "sg:city":"Rain",
    "sg:orig_category":"Sportvereine Velo Rad-& Motorfahrer-Bund SRB",
    "sg:phone":"+41 71 385 95 29",
    "sg:postcode":"6026",
    "sg:province":"Luzern",
    "wof:name":"Rad-& Moto-club Gossau",
    "wof:placetype":"venue"
},
  "geometry": {"coordinates":[9.2417068481,47.415813446],"type":"Point"}
}