{
  "type": "Feature",
  "properties": {
    "iso:country":"CH",
    "sg:address":"Haselstrasse 29",
    "sg:city":"Baden",
    "sg:classifiers":[
        {
            "category":"Bars & Pubs",
            "type":"Food & Drink"
        }
    ],
    "sg:phone":"+41 56 222 08 81",
    "sg:postcode":"5400",
    "sg:province":"Aargau",
    "wof:name":"Bar Lounge Rossini",
    "wof:placetype":"venue"
},
  "geometry": {"coordinates":[8.304932,47.477451],"type":"Point"}
}