{
  "type": "Feature",
  "properties": {
    "iso:country":"CH",
    "sg:address":"Via Geretta 2",
    "sg:city":"Paradiso",
    "sg:orig_category":"Interessenvertretungen",
    "sg:postcode":"6900",
    "sg:province":"Ticino",
    "wof:name":"Fondazione Foscale Luigi E Walda",
    "wof:placetype":"venue"
},
  "geometry": {"coordinates":[8.9472389221,45.9913063049],"type":"Point"}
}