{
  "type": "Feature",
  "properties": {
    "iso:country":"CH",
    "sg:address":"St.-antons-gasse 4a 6300 Zug. Postfach",
    "sg:city":"Zug",
    "sg:orig_category":"Wirtschaftspr\u00fcfung, Steuerberatung U Treuhand",
    "sg:phone":"+41 41 710 45 45",
    "sg:postcode":"6301",
    "sg:province":"Zug",
    "wof:name":"Trobag Ag",
    "wof:placetype":"venue"
},
  "geometry": {"coordinates":[8.5165901184,47.1672706604],"type":"Point"}
}