{
  "type": "Feature",
  "properties": {
    "iso:country":"CH",
    "sg:address":"Calandastrasse 13 8048 Z\u00fcrich. Postfach",
    "sg:city":"Z\u00fcrich",
    "sg:orig_category":"Offsetdruck",
    "sg:phone":"+41 14322676",
    "sg:postcode":"8048",
    "sg:province":"Z\u00fcrich",
    "wof:name":"Rolf Stoffel Druckerei",
    "wof:placetype":"venue"
},
  "geometry": {"coordinates":[8.4890241623,47.3880500793],"type":"Point"}
}