{
  "type": "Feature",
  "properties": {
    "iso:country":"CH",
    "sg:address":"H\u00e4rdlistrasse 15",
    "sg:city":"Spreitenbach",
    "sg:orig_category":"Grosshandel mit Radio U Fernsehger\u00e4ten Herstellung von sonstigen elektrischen Ausr\u00fcstungen",
    "sg:phone":"+41 56 410 22 22",
    "sg:postcode":"8957",
    "sg:province":"Aargau",
    "wof:name":"Europhone Ag Akustiksysteme Akustiksysteme",
    "wof:placetype":"venue"
},
  "geometry": {"coordinates":[8.3679733276,47.4311828613],"type":"Point"}
}