{
  "type": "Feature",
  "properties": {
    "iso:country":"CH",
    "sg:address":"Dorfstrasse 13 6030 Ebikon. Postfach 355",
    "sg:city":"Ebikon",
    "sg:orig_category":"Organisationen der Wohlfahrtspflege",
    "sg:phone":"+41 71 222 12 91",
    "sg:postcode":"6031",
    "sg:province":"Luzern",
    "wof:name":"Winterhilfe Kanton St.gallen",
    "wof:placetype":"venue"
},
  "geometry": {"coordinates":[9.3733863831,47.426940918],"type":"Point"}
}