{
  "type": "Feature",
  "properties": {
    "iso:country":"CH",
    "sg:address":"Ziegelh\u00fctte 589",
    "sg:city":"Flaach",
    "sg:classifiers":[
        {
            "category":"Restaurant",
            "type":"Food & Drink"
        }
    ],
    "sg:phone":"+41 55 246 32 81",
    "sg:postcode":"8416",
    "sg:province":"Z\u00fcrich",
    "wof:name":"Restaurant Zipfel",
    "wof:placetype":"venue"
},
  "geometry": {"coordinates":[8.9413003922,47.2884101868],"type":"Point"}
}