{
  "type": "Feature",
  "properties": {
    "iso:country":"CH",
    "sg:address":"Obere Z\u00e4une 24",
    "sg:city":"Z\u00fcrich",
    "sg:orig_category":"Non-Classified Establishments",
    "sg:phone":"+41 12624740",
    "sg:postcode":"8001",
    "sg:province":"Z\u00fcrich",
    "wof:name":"Walo Bertschinger Holding Ag",
    "wof:placetype":"venue"
},
  "geometry": {"coordinates":[8.5453042984,47.3715248108],"type":"Point"}
}