{
  "type": "Feature",
  "properties": {
    "iso:country":"CH",
    "sg:address":"Weststrasse 24",
    "sg:city":"Neuenhof",
    "sg:orig_category":"Herstellung von k\u00e4lte U lufttechnischen Erzeugnissen f\u00fcr gewerbliche Zwecke",
    "sg:phone":"+41 56 406 10 93",
    "sg:postcode":"5432",
    "sg:province":"Aargau",
    "wof:name":"Fischer + Co.",
    "wof:placetype":"venue"
},
  "geometry": {"coordinates":[8.3205738068,47.4530334473],"type":"Point"}
}