{
  "type": "Feature",
  "properties": {
    "iso:country":"CH",
    "sg:address":"Sch\u00f6nauweg 3",
    "sg:city":"Langenthal",
    "sg:orig_category":"Detailhandel mit Metallwaren, Anstrichmitteln, Glaswaren, Bau U Heimwerkerbedarf Handelsvermittlung ",
    "sg:phone":"+41 71 945 70 20",
    "sg:postcode":"4900",
    "sg:province":"Bern",
    "wof:name":"Rotex Kunststofftechnik Ag Technische Vertretungen",
    "wof:placetype":"venue"
},
  "geometry": {"coordinates":[9.1234006882,47.4656410217],"type":"Point"}
}