{
  "type": "Feature",
  "properties": {
    "iso:country":"CH",
    "sg:address":"Freilerstrasse 23",
    "sg:city":"Dielsdorf",
    "sg:orig_category":"Finanzierungsinstitutionen",
    "sg:phone":"+41 18534411",
    "sg:postcode":"8157",
    "sg:province":"Z\u00fcrich",
    "wof:name":"Pohle Ren\u00e9, Vorsorge Und Finanzberatung",
    "wof:placetype":"venue"
},
  "geometry": {"coordinates":[8.4516506195,47.4746437073],"type":"Point"}
}