{
  "type": "Feature",
  "properties": {
    "iso:country":"CH",
    "sg:address":"Hotel Allalin",
    "sg:city":"Gr\u00e4chen",
    "sg:orig_category":"Detailhandel mit Brennstoffen U Heizmaterial Detailhandel mit Waren verschiedener Art, Hauptrichtung",
    "sg:phone":"+41 26 467 35 11",
    "sg:postcode":"3925",
    "sg:province":"Valais",
    "wof:name":"Boucherie Coop Broye-fribourg-mol\u00e9son",
    "wof:placetype":"venue"
},
  "geometry": {"coordinates":[6.914253,46.692986],"type":"Point"}
}