{
  "type": "Feature",
  "properties": {
    "iso:country":"CH",
    "sg:address":"Dorfstrasse 2",
    "sg:city":"Ins",
    "sg:orig_category":"Vermittlung von Immobilien Verwaltung von Immobilien",
    "sg:phone":"+41 41 368 10 85",
    "sg:postcode":"3232",
    "sg:province":"Bern",
    "wof:name":"Studhalter Immobilien Ag",
    "wof:placetype":"venue"
},
  "geometry": {"coordinates":[8.3324298859,47.0359840393],"type":"Point"}
}