{
  "type": "Feature",
  "properties": {
    "iso:country":"CH",
    "sg:address":"Rue De La Cure 5 2610 St-imier. Postfach",
    "sg:city":"St-imier",
    "sg:orig_category":"Detailhandel mit Uhren U Schmuck",
    "sg:phone":"+41 32 941 52 75",
    "sg:postcode":"2610",
    "sg:province":"Bern",
    "wof:name":"Oreve Bijouterie Joaillerie",
    "wof:placetype":"venue"
},
  "geometry": {"coordinates":[6.9967632294,47.1531066895],"type":"Point"}
}