{
  "type": "Feature",
  "properties": {
    "iso:country":"CH",
    "sg:address":"Industriestrasse 12",
    "sg:city":"B\u00fctzberg",
    "sg:orig_category":"Grosshandel mit Werkzeugmaschinen Herstellung von sonstigen Werkzeugmaschinen",
    "sg:phone":"+41 71 886 70 77",
    "sg:postcode":"4922",
    "sg:province":"Bern",
    "wof:name":"Seh Service, Engineering Und Handels Gmbh",
    "wof:placetype":"venue"
},
  "geometry": {"coordinates":[9.5429334641,47.4775428772],"type":"Point"}
}