{
  "type": "Feature",
  "properties": {
    "iso:country":"CH",
    "sg:address":"Sagenmatt",
    "sg:city":"Schwyz",
    "sg:orig_category":"Mit dem Versicherungsgewerbe verbundene T\u00e4tigkeiten",
    "sg:phone":"+41 41 811 48 14",
    "sg:postcode":"6430",
    "sg:province":"Schwyz",
    "wof:name":"Kaspar Betschart Versicherungsberatungen",
    "wof:placetype":"venue"
},
  "geometry": {"coordinates":[8.6621637344,47.0184440613],"type":"Point"}
}