{
  "type": "Feature",
  "properties": {
    "addr:full":"Postweg 5 Holderbank Aargau 5113",
    "addr:housenumber":"5",
    "addr:postcode":"5113",
    "addr:street":"Postweg",
    "iso:country":"CH",
    "sg:address":"Postweg 5",
    "sg:city":"Holderbank",
    "sg:classifiers":[
        {
            "category":"Science Facility",
            "type":"Public Place"
        }
    ],
    "sg:phone":"+41 62 893 34 67",
    "sg:postcode":"5113",
    "sg:province":"Aargau",
    "sg:tags":[
        "cnc",
        "flamecutting",
        "installation",
        "combined",
        "drilling"
    ],
    "wof:name":"Peter-mechanik Ag",
    "wof:placetype":"venue"
},
  "geometry": {"coordinates":[8.168616,47.426964],"type":"Point"}
}