{
  "type": "Feature",
  "properties": {
    "iso:country":"CH",
    "sg:address":"Baarerstrasse 79",
    "sg:city":"Zug",
    "sg:orig_category":"Forschung U Entwicklung im Bereich der Naturwissenschaften",
    "sg:phone":"+41 41 711 99 55",
    "sg:postcode":"6300",
    "sg:province":"Zug",
    "wof:name":"Ibs Innovative Bone Surgery Ag",
    "wof:placetype":"venue"
},
  "geometry": {"coordinates":[8.5177192688,47.1772003174],"type":"Point"}
}