{
  "type": "Feature",
  "properties": {
    "iso:country":"CH",
    "sg:address":"Grauensteinweg 20",
    "sg:city":"Gelterkinden",
    "sg:orig_category":"Unclassifiable Establishments",
    "sg:phone":"+41 31 832 14 64",
    "sg:postcode":"4460",
    "sg:province":"Basel-Landschaft",
    "wof:name":"G. Fedier Citron Press\u00e9",
    "wof:placetype":"venue"
},
  "geometry": {"coordinates":[7.56310606,46.9295349121],"type":"Point"}
}