{
  "type": "Feature",
  "properties": {
    "addr:full":"M\u00fchlebachstrasse 8 Z\u00fcrich Z\u00fcrich 8055",
    "addr:housenumber":"8",
    "addr:postcode":"8055",
    "addr:street":"Muehlebachstrasse",
    "iso:country":"CH",
    "sg:address":"M\u00fchlebachstrasse 8",
    "sg:city":"Z\u00fcrich",
    "sg:orig_category":"Allgemeiner Hoch U Tiefbau",
    "sg:phone":"+41 14514600",
    "sg:postcode":"8055",
    "sg:province":"Z\u00fcrich",
    "wof:name":"Ernst R\u00fccker + Partner Generalunternehmung Ag",
    "wof:placetype":"venue"
},
  "geometry": {"coordinates":[8.549459,47.365513],"type":"Point"}
}