{
  "type": "Feature",
  "properties": {
    "iso:country":"CH",
    "sg:address":"Marktweg 2 6106 Werthenstein. Postfach",
    "sg:city":"Wolhusen",
    "sg:orig_category":"Gemeindeverwaltungen",
    "sg:phone":"+41 41 490 23 23",
    "sg:postcode":"6110",
    "sg:province":"Luzern",
    "wof:name":"Gemeindeverwaltung Werthenstein",
    "wof:placetype":"venue"
},
  "geometry": {"coordinates":[8.0700817108,47.0565910339],"type":"Point"}
}