{
  "type": "Feature",
  "properties": {
    "iso:country":"CH",
    "sg:address":"Cantonale Via 6",
    "sg:city":"Lugano",
    "sg:orig_category":"Wirtschaftspr\u00fcfung, Steuerberatung U Treuhand",
    "sg:postcode":"6900",
    "sg:province":"Ticino",
    "wof:name":"Mpp Finanziaria Sa",
    "wof:placetype":"venue"
},
  "geometry": {"coordinates":[8.9503126144,46.0076599121],"type":"Point"}
}