{
  "type": "Feature",
  "properties": {
    "iso:country":"CH",
    "sg:address":"Route Du Simplon 23",
    "sg:city":"Paudex",
    "sg:orig_category":"Unclassifiable Establishments",
    "sg:postcode":"1094",
    "sg:province":"Vaud",
    "wof:name":"Strahm Philippe David",
    "wof:placetype":"venue"
},
  "geometry": {"coordinates":[6.6728172302,46.5068244934],"type":"Point"}
}