{
  "type": "Feature",
  "properties": {
    "iso:country":"CH",
    "sg:address":"Bahnhofstrasse 54 8001 Z\u00fcrich. Postfach",
    "sg:city":"Z\u00fcrich",
    "sg:orig_category":"Personal U Stellenvermittlung Unternehmensberatung",
    "sg:phone":"+41 12121227",
    "sg:postcode":"8001",
    "sg:province":"Z\u00fcrich",
    "wof:name":"Brunner Georg Mentoring Kommunikationsforum F. Menschen In Herausfordernden Bereichen",
    "wof:placetype":"venue"
},
  "geometry": {"coordinates":[8.5384531021,47.3729476929],"type":"Point"}
}