{
  "type": "Feature",
  "properties": {
    "iso:country":"CH",
    "sg:address":"R. Blancherie 63",
    "sg:city":"Sion",
    "sg:classifiers":[
        {
            "category":"Wholesale",
            "subcategory":"Machinery & Supplies",
            "type":"Manufacturing & Wholesale Goods"
        }
    ],
    "sg:phone":"+41 32 930 80 80",
    "sg:postcode":"1950",
    "sg:province":"Valais",
    "sg:tags":[
        "equipment",
        "equipement",
        "precision",
        "timekeeping"
    ],
    "wof:name":"Isa Swiss Sa",
    "wof:placetype":"venue"
},
  "geometry": {"coordinates":[6.7047200203,47.0679893494],"type":"Point"}
}