{
  "type": "Feature",
  "properties": {
    "iso:country":"CH",
    "sg:address":"Rue Du Coll\u00e8ge 2",
    "sg:city":"Martigny",
    "sg:orig_category":"Fachdetailhandel in Verkaufsr\u00e4umen",
    "sg:postcode":"1920",
    "sg:province":"Valais",
    "wof:name":"Saunier Gaston.",
    "wof:placetype":"venue"
},
  "geometry": {"coordinates":[7.0736260414,46.1014671326],"type":"Point"}
}