{
  "type": "Feature",
  "properties": {
    "iso:country":"CH",
    "sg:address":"Kohlr\u00fcti 6",
    "sg:city":"R\u00f6schenz",
    "sg:orig_category":"Architektur U Ingenieurb\u00fcros",
    "sg:phone":"+41 61 971 80 50",
    "sg:postcode":"4244",
    "sg:province":"Basel-Landschaft",
    "wof:name":"Hewyta Planungsb\u00fcro",
    "wof:placetype":"venue"
},
  "geometry": {"coordinates":[7.458475,47.436581],"type":"Point"}
}