{
  "type": "Feature",
  "properties": {
    "iso:country":"CH",
    "sg:address":"Steinacherstrasse 150 8820 W\u00e4denswil. Postfach 419",
    "sg:city":"W\u00e4denswil",
    "sg:orig_category":"Grosshandel mit Holz U Baustoffen Sonstiger Grosshandel",
    "sg:phone":"+41 32 757 28 88",
    "sg:postcode":"8820",
    "sg:province":"Z\u00fcrich",
    "wof:name":"Np Espace Immobilier S\u00e0rl",
    "wof:placetype":"venue"
},
  "geometry": {"coordinates":[7.037689209,47.0510253906],"type":"Point"}
}