{
  "type": "Feature",
  "properties": {
    "iso:country":"CH",
    "sg:address":"Alte Landstrasse 87",
    "sg:city":"Rebstein",
    "sg:orig_category":"RESTAURANTS: TEA-ROOMS",
    "sg:postcode":"9445",
    "sg:province":"St. Gallen",
    "wof:name":"Resoda Ag",
    "wof:placetype":"venue"
},
  "geometry": {"coordinates":[9.5811567307,47.3978118896],"type":"Point"}
}