{
  "type": "Feature",
  "properties": {
    "iso:country":"CH",
    "sg:address":"Hofurlistrasse",
    "sg:city":"Ennetb\u00fcrgen",
    "sg:orig_category":"Architektur U Ingenieurb\u00fcros",
    "sg:phone":"+41 41 610 94 40",
    "sg:postcode":"6373",
    "sg:province":"Nidwalden",
    "wof:name":"Mathys Ag, Dipl. Ingenieure Eth-l",
    "wof:placetype":"venue"
},
  "geometry": {"coordinates":[8.404941,46.984558],"type":"Point"}
}