{
  "type": "Feature",
  "properties": {
    "iso:country":"CH",
    "sg:address":"Klettgauerstr. 36",
    "sg:city":"Neuhausen",
    "sg:orig_category":"Sonstiger Fachdetailhandel mit Nahrungsmitteln, Getr\u00e4nken U Tabak in Verkaufsr\u00e4umen",
    "sg:postcode":"8212",
    "sg:province":"Schaffhausen",
    "wof:name":"Hartmann Anton",
    "wof:placetype":"venue"
},
  "geometry": {"coordinates":[8.612903595,47.6837043762],"type":"Point"}
}