{
  "type": "Feature",
  "properties": {
    "iso:country":"CH",
    "sg:address":"Worbstrasse 170",
    "sg:city":"G\u00fcmligen",
    "sg:orig_category":"Hardwareberatung Softwareentwicklung U beratung",
    "sg:phone":"+41 31 951 23 27",
    "sg:postcode":"3073",
    "sg:province":"Bern",
    "wof:name":"Benova T.c.",
    "wof:placetype":"venue"
},
  "geometry": {"coordinates":[7.500333786,46.9345550537],"type":"Point"}
}