{
  "type": "Feature",
  "properties": {
    "iso:country":"CH",
    "sg:address":"Spyristrasse 17",
    "sg:city":"Z\u00fcrich",
    "sg:orig_category":"Softwareentwicklung U beratung",
    "sg:postcode":"8044",
    "sg:province":"Z\u00fcrich",
    "wof:name":"Schumatec Schumacher Technik Hard- U. Software; Entwicklung, Verkauf",
    "wof:placetype":"venue"
},
  "geometry": {"coordinates":[8.5518283844,47.3825531006],"type":"Point"}
}