{
  "type": "Feature",
  "properties": {
    "iso:country":"CH",
    "sg:address":"Promenade-noire 10",
    "sg:city":"Neuch\u00e2tel",
    "sg:orig_category":"Detailhandel mit Sportartikeln Fachdetailhandel in Verkaufsr\u00e4umen",
    "sg:phone":"+41 32 725 35 19",
    "sg:postcode":"2000",
    "sg:province":"Neuch\u00e2tel",
    "wof:name":"Mag Street Shop, David Bonavita",
    "wof:placetype":"venue"
},
  "geometry": {"coordinates":[6.9274368286,46.9906234741],"type":"Point"}
}