{
  "type": "Feature",
  "properties": {
    "iso:country":"CH",
    "sg:address":"Alte Steinhauserstrasse 3",
    "sg:city":"Cham",
    "sg:orig_category":"Zahnarztpraxen",
    "sg:phone":"+41 41 740 12 20",
    "sg:postcode":"6330",
    "sg:province":"Zug",
    "wof:name":"Dr.med.dent.patrick Sequeira Zahnarzt",
    "wof:placetype":"venue"
},
  "geometry": {"coordinates":[8.4730377197,47.1864471436],"type":"Point"}
}