{
  "type": "Feature",
  "properties": {
    "iso:country":"CH",
    "sg:address":"Via Stazione",
    "sg:city":"Balerna",
    "sg:orig_category":"Architektur U Ingenieurb\u00fcros",
    "sg:phone":"+41 91 683 30 19",
    "sg:postcode":"6828",
    "sg:province":"Ticino",
    "wof:name":"Riva Mario",
    "wof:placetype":"venue"
},
  "geometry": {"coordinates":[9.006365,45.849087],"type":"Point"}
}