{
  "type": "Feature",
  "properties": {
    "iso:country":"CH",
    "sg:address":"Wehntalerstrasse 17",
    "sg:city":"Z\u00fcrich",
    "sg:orig_category":"Softwareentwicklung U beratung",
    "sg:phone":"+41 79 300 86 65",
    "sg:postcode":"8057",
    "sg:province":"Z\u00fcrich",
    "wof:name":"Arco Business Services Ag",
    "wof:placetype":"venue"
},
  "geometry": {"coordinates":[7.4869909286,46.9317207336],"type":"Point"}
}