{
  "type": "Feature",
  "properties": {
    "iso:country":"CH",
    "sg:address":"Florissant Route De 61 1206 Gen\u00e8ve. Postfach",
    "sg:city":"Gen\u00e8ve",
    "sg:orig_category":"Textilveredlung",
    "sg:phone":"+41 22 347 30 44",
    "sg:postcode":"1201",
    "sg:province":"Gen\u00e8ve",
    "wof:name":"Rieu Parc Teinturerie Sa",
    "wof:placetype":"venue"
},
  "geometry": {"coordinates":[6.1627807617,46.1930770874],"type":"Point"}
}