{
  "type": "Feature",
  "properties": {
    "iso:country":"CH",
    "sg:address":"Juchstrasse 2",
    "sg:city":"Tafers",
    "sg:orig_category":"Versicherungen Hauptagenturen",
    "sg:phone":"+41 34 402 25 03",
    "sg:postcode":"1712",
    "sg:province":"Fribourg",
    "wof:name":"Generali Versicherungen Hauptagentur Emmental",
    "wof:placetype":"venue"
},
  "geometry": {"coordinates":[7.757589817,46.9491271973],"type":"Point"}
}