{
  "type": "Feature",
  "properties": {
    "iso:country":"CH",
    "sg:address":"3706",
    "sg:city":"Leissigen",
    "sg:orig_category":"Vereine Frauen Vereine Gemeinn\u00fctzige",
    "sg:phone":"+41 33 847 13 44",
    "sg:postcode":"3706",
    "sg:province":"Bern",
    "wof:name":"Gemeinn\u00fctziger Frauenverein",
    "wof:placetype":"venue"
},
  "geometry": {"coordinates":[7.7740898132,46.6546554565],"type":"Point"}
}