{
  "type": "Feature",
  "properties": {
    "iso:country":"CH",
    "sg:address":"Murtenstr. 45",
    "sg:city":"Frauenkappelen",
    "sg:classifiers":[
        {
            "category":"Banks & Credit Unions",
            "subcategory":"Bank",
            "type":"Services"
        }
    ],
    "sg:phone":"+41 31 926 10 03",
    "sg:postcode":"3202",
    "sg:province":"Bern",
    "wof:name":"Gewerbekasse In Bern",
    "wof:placetype":"venue"
},
  "geometry": {"coordinates":[7.339008,46.953934],"type":"Point"}
}