{
  "type": "Feature",
  "properties": {
    "iso:country":"CH",
    "sg:address":"Via Leoncavallo 6614 Brissago. Postfach Caselle Postale 541",
    "sg:city":"Brissago",
    "sg:orig_category":"Elektroinstallation",
    "sg:phone":"+41 91 793 15 15",
    "sg:postcode":"6614",
    "sg:province":"Ticino",
    "wof:name":"Elettricit\u00e0 Jelmoni Sa",
    "wof:placetype":"venue"
},
  "geometry": {"coordinates":[8.7111787796,46.1198768616],"type":"Point"}
}