{
  "type": "Feature",
  "properties": {
    "addr:full":"Rue De Bourg 8 Lausanne Vaud 1003",
    "addr:housenumber":"8",
    "addr:postcode":"1003",
    "addr:street":"Rue De Bourg",
    "iso:country":"CH",
    "sg:address":"Rue De Bourg 8",
    "sg:city":"Lausanne",
    "sg:orig_category":"Detailhandel mit Bekleidung",
    "sg:phone":"+41 21 311 07 88",
    "sg:postcode":"1003",
    "sg:province":"Vaud",
    "wof:name":"Grant Oliver St-fran\u00e7ois Sa",
    "wof:placetype":"venue"
},
  "geometry": {"coordinates":[6.635274,46.519894],"type":"Point"}
}