{
  "type": "Feature",
  "properties": {
    "iso:country":"CH",
    "sg:address":"Baumg\u00e4rtli 7",
    "sg:city":"Schattdorf",
    "sg:orig_category":"Vorschulen, Kinderg\u00e4rten",
    "sg:phone":"+41 41 870 98 22",
    "sg:postcode":"6467",
    "sg:province":"Uri",
    "wof:name":"Kindergarten Baumg\u00e4rtli",
    "wof:placetype":"venue"
},
  "geometry": {"coordinates":[8.6502656937,46.8653068542],"type":"Point"}
}