{
  "type": "Feature",
  "properties": {
    "iso:country":"CH",
    "sg:address":"1042",
    "sg:city":"Malapalud",
    "sg:orig_category":"S\u00e4ge, Hobel U Holzimpr\u00e4gnierwerke S\u00e4gewerke",
    "sg:phone":"+41 21 881 18 36",
    "sg:postcode":"1042",
    "sg:province":"Vaud",
    "wof:name":"Scierie Allaz Georges Sa",
    "wof:placetype":"venue"
},
  "geometry": {"coordinates":[6.6413722038,46.6211051941],"type":"Point"}
}