{
  "type": "Feature",
  "properties": {
    "addr:full":"Schulhausstrasse 25 4563 Gerlafingen. Postfach Gerlafingen Solothurn 4563",
    "addr:housenumber":"25",
    "addr:postcode":"4563 gerlafingen. postfach;4563",
    "addr:street":"Schulhausstrasse",
    "iso:country":"CH",
    "sg:address":"Schulhausstrasse 25 4563 Gerlafingen. Postfach",
    "sg:city":"Gerlafingen",
    "sg:orig_category":"Arztpraxen",
    "sg:phone":"+41 32 675 45 45",
    "sg:postcode":"4563",
    "sg:province":"Solothurn",
    "wof:name":"Dres Med. Scartazzini & Jordi Spezial\u00e4rzte Fmh",
    "wof:placetype":"venue"
},
  "geometry": {"coordinates":[7.569359,47.168095],"type":"Point"}
}