{
  "type": "Feature",
  "properties": {
    "iso:country":"CH",
    "sg:address":"Gerechtigkeitsgasse 42",
    "sg:city":"Bern",
    "sg:orig_category":"Sportvereine Sch\u00fctzen",
    "sg:phone":"+41 31 311 31 55",
    "sg:postcode":"3011",
    "sg:province":"Bern",
    "wof:name":"Reismusketen-sch\u00fctzenges.bern",
    "wof:placetype":"venue"
},
  "geometry": {"coordinates":[7.4544000626,46.948387146],"type":"Point"}
}