{
  "type": "Feature",
  "properties": {
    "iso:country":"CH",
    "sg:address":"Seestrasse 94",
    "sg:city":"Oberrieden",
    "sg:orig_category":"Vereine Gesang Vereine Gesang and Jodler",
    "sg:phone":"+41 17212058",
    "sg:postcode":"8942",
    "sg:province":"Z\u00fcrich",
    "wof:name":"Jodler-doppelquartett Des Tvh",
    "wof:placetype":"venue"
},
  "geometry": {"coordinates":[8.5857048035,47.2702484131],"type":"Point"}
}