{
  "type": "Feature",
  "properties": {
    "iso:country":"CH",
    "sg:address":"Buchenrain 5",
    "sg:city":"Kriens",
    "sg:orig_category":"Herstellung von Teppichen",
    "sg:postcode":"6010",
    "sg:province":"Luzern",
    "wof:name":"Floorcom Consulting Wyss Bodenbelags-sektor; Beratung. Warenhandel",
    "wof:placetype":"venue"
},
  "geometry": {"coordinates":[8.306394577,46.9852828979],"type":"Point"}
}