{
  "type": "Feature",
  "properties": {
    "addr:full":"Bendererstrasse 29 9494 Schaan. Postfach Schaan 9494",
    "addr:housenumber":"29",
    "addr:postcode":"9494;9494",
    "addr:street":"Bendererstrasse;Postfach",
    "iso:country":"CH",
    "sg:address":"Bendererstrasse 29 9494 Schaan. Postfach",
    "sg:city":"Schaan",
    "sg:orig_category":"Datenverarbeitungsdienste",
    "sg:phone":"+41 18510367",
    "sg:postcode":"9494",
    "wof:name":"Ncs Nyfeler Computer Service",
    "wof:placetype":"venue"
},
  "geometry": {"coordinates":[8.496913,47.493938],"type":"Point"}
}