{
  "type": "Feature",
  "properties": {
    "iso:country":"CH",
    "sg:address":"Bahnhofstrasse 4",
    "sg:city":"Herisau",
    "sg:orig_category":"Fachdetailhandel mit pharmazeutischen Produkten Grosshandel mit pharmazeutischen Erzeugnissen",
    "sg:phone":"+41 71 350 11 55",
    "sg:postcode":"9100",
    "sg:province":"Appenzell Ausserrhoden",
    "wof:name":"Ebco Medana Gmbh",
    "wof:placetype":"venue"
},
  "geometry": {"coordinates":[9.2797355652,47.3862571716],"type":"Point"}
}