{
  "type": "Feature",
  "properties": {
    "iso:country":"CH",
    "sg:address":"Sch\u00f6neggstrasse 34",
    "sg:city":"Dietikon",
    "sg:orig_category":"Autogaragen",
    "sg:phone":"+41 17405880",
    "sg:postcode":"8953",
    "sg:province":"Z\u00fcrich",
    "wof:name":"Angelo Pallavicini Autogarage",
    "wof:placetype":"venue"
},
  "geometry": {"coordinates":[8.405338,47.400967],"type":"Point"}
}