{
  "type": "Feature",
  "properties": {
    "iso:country":"CH",
    "sg:address":"Via Cantonale",
    "sg:city":"Mezzovico",
    "sg:orig_category":"Vermietung U Verpachtung von eigenen Immobilien",
    "sg:postcode":"6805",
    "sg:province":"Ticino",
    "wof:name":"Taddeca Sa",
    "wof:placetype":"venue"
},
  "geometry": {"coordinates":[8.9198827744,46.0879859924],"type":"Point"}
}