{
  "type": "Feature",
  "properties": {
    "iso:country":"CH",
    "sg:address":"Seestrasse 166",
    "sg:city":"Horgen",
    "sg:orig_category":"Architektur U Ingenieurb\u00fcros Architekturb\u00fcros",
    "sg:phone":"+41 17703110",
    "sg:postcode":"8810",
    "sg:province":"Z\u00fcrich",
    "wof:name":"Archipelago Ag",
    "wof:placetype":"venue"
},
  "geometry": {"coordinates":[8.599927,47.259827],"type":"Point"}
}