{
  "type": "Feature",
  "properties": {
    "iso:country":"CH",
    "sg:address":"Z\u00fcrcherstrasse 140",
    "sg:city":"Basel",
    "sg:orig_category":"Detailhandel mit Spielwaren Detailhandel mit S\u00e4uglings U Kinderbekleidung",
    "sg:phone":"+41 61 313 30 00",
    "sg:postcode":"4052",
    "sg:province":"Basel-Stadt",
    "wof:name":"Strizzi Kinderb\u00f6rse",
    "wof:placetype":"venue"
},
  "geometry": {"coordinates":[7.6126198769,47.5550231934],"type":"Point"}
}