{
  "type": "Feature",
  "properties": {
    "iso:country":"CH",
    "sg:address":"Rossbodenstrasse 51",
    "sg:city":"Tamins",
    "sg:orig_category":"Extracts From Tropical Fruit For Drinks",
    "sg:phone":"+41 81 650 22 00",
    "sg:postcode":"7015",
    "sg:province":"Graubunden",
    "wof:name":"Belfrut Ag",
    "wof:placetype":"venue"
},
  "geometry": {"coordinates":[9.4084701538,46.8256111145],"type":"Point"}
}