{
  "type": "Feature",
  "properties": {
    "iso:country":"CH",
    "sg:address":"Austrasse 3",
    "sg:city":"Lichtensteig",
    "sg:orig_category":"Sonstiges Textilgewerbe",
    "sg:phone":"+41 56 633 30 40",
    "sg:postcode":"9620",
    "sg:province":"St. Gallen",
    "wof:name":"Gumotex Ag",
    "wof:placetype":"venue"
},
  "geometry": {"coordinates":[8.3373966217,47.3500862122],"type":"Point"}
}