{
  "type": "Feature",
  "properties": {
    "iso:country":"CH",
    "sg:address":"Seebacherstrasse 34",
    "sg:city":"Z\u00fcrich",
    "sg:orig_category":"Kinderkrippen U horte",
    "sg:phone":"+41 13013193",
    "sg:postcode":"8052",
    "sg:province":"Z\u00fcrich",
    "wof:name":"Kinderkrippe Der Reformierten Kirchgemeinde Seebach",
    "wof:placetype":"venue"
},
  "geometry": {"coordinates":[8.5456523895,47.4219551086],"type":"Point"}
}