{
  "type": "Feature",
  "properties": {
    "iso:country":"CH",
    "sg:address":"Via Luigi Lavizzari 1",
    "sg:city":"Chiasso",
    "sg:orig_category":"Reiseb\u00fcros U Reiseveranstalter",
    "sg:phone":"+41 91 682 11 33",
    "sg:postcode":"6830",
    "sg:province":"Ticino",
    "wof:name":"Xtramondo Sa",
    "wof:placetype":"venue"
},
  "geometry": {"coordinates":[9.02967453,45.8345603943],"type":"Point"}
}