{
  "type": "Feature",
  "properties": {
    "addr:full":"Alte Landstrasse 112 Zollikon Z\u00fcrich 8702",
    "addr:housenumber":"112",
    "addr:postcode":"8702",
    "addr:street":"Alte Landstrasse",
    "iso:country":"CH",
    "sg:address":"Alte Landstrasse 112",
    "sg:city":"Zollikon",
    "sg:orig_category":"Arztpraxen",
    "sg:phone":"+41 61 402 11 00",
    "sg:postcode":"8702",
    "sg:province":"Z\u00fcrich",
    "wof:name":"Dr.med.susanne Bickel Spezial\u00e4rztin Fmh",
    "wof:placetype":"venue"
},
  "geometry": {"coordinates":[7.558012,47.516785],"type":"Point"}
}