{
  "type": "Feature",
  "properties": {
    "iso:country":"CH",
    "sg:address":"Wiesholzerstrasse 410",
    "sg:city":"Ramsen",
    "sg:orig_category":"Mechanik Stahl U Leichtmetallbau",
    "sg:phone":"+41 52 743 13 52",
    "sg:postcode":"8262",
    "sg:province":"Schaffhausen",
    "wof:name":"Gn\u00e4dinger Franz Ag",
    "wof:placetype":"venue"
},
  "geometry": {"coordinates":[8.8225164413,47.7086791992],"type":"Point"}
}