{
  "type": "Feature",
  "properties": {
    "iso:country":"CH",
    "sg:address":"Martin Disteli-strasse 26 4600 Olten. Postfach",
    "sg:city":"Olten",
    "sg:orig_category":"Pensionskassen",
    "sg:postcode":"4600",
    "sg:province":"Solothurn",
    "wof:name":"Erg\u00e4nzungsstiftung Der Zibatra Beteiligungen Ag",
    "wof:placetype":"venue"
},
  "geometry": {"coordinates":[7.8549938202,47.3366966248],"type":"Point"}
}