{
  "type": "Feature",
  "properties": {
    "iso:country":"CH",
    "sg:address":"Poststrasse 8",
    "sg:city":"Z\u00fcrich",
    "sg:orig_category":"Interessenvertretungen",
    "sg:postcode":"8001",
    "sg:province":"Z\u00fcrich",
    "wof:name":"Elysium Fondation",
    "wof:placetype":"venue"
},
  "geometry": {"coordinates":[6.9172902107,46.989692688],"type":"Point"}
}