{
  "type": "Feature",
  "properties": {
    "iso:country":"CH",
    "sg:address":"Morillonstrasse 8 3000 Bern. Postfach",
    "sg:city":"Bern",
    "sg:orig_category":"Herstellung von Teppichen",
    "sg:postcode":"3005",
    "sg:province":"Bern",
    "wof:name":"Aslan",
    "wof:placetype":"venue"
},
  "geometry": {"coordinates":[7.435778141,46.9364395142],"type":"Point"}
}