{
  "type": "Feature",
  "properties": {
    "iso:country":"CH",
    "sg:address":"8400 Winterthur. Postfach 353",
    "sg:city":"Winterthur",
    "sg:classifiers":[
        {
            "category":"Professional",
            "subcategory":"Employment Agencies",
            "type":"Services"
        }
    ],
    "sg:phone":"+41 52 212 01 01",
    "sg:postcode":"8400",
    "sg:province":"Z\u00fcrich",
    "sg:tags":[
        "personal",
        "u",
        "stellenvermittlung"
    ],
    "wof:name":"Time Work Personal Ag",
    "wof:placetype":"venue"
},
  "geometry": {"coordinates":[8.7265195847,47.4920501709],"type":"Point"}
}