{
  "type": "Feature",
  "properties": {
    "iso:country":"CH",
    "sg:address":"1272 Genolier Case Postale 21",
    "sg:city":"Genolier",
    "sg:orig_category":"Sportvereine P\u00e9tanque",
    "sg:postcode":"1272",
    "sg:province":"Vaud",
    "wof:name":"P\u00e9tanque-club La Bourdonnette",
    "wof:placetype":"venue"
},
  "geometry": {"coordinates":[6.6876702309,46.559551239],"type":"Point"}
}