{
  "type": "Feature",
  "properties": {
    "addr:full":"Laupenstrasse 5a Bern Bern 3008",
    "addr:housenumber":"5a",
    "addr:postcode":"3008",
    "addr:street":"Laupenstrasse",
    "iso:country":"CH",
    "sg:address":"Laupenstrasse 5a",
    "sg:city":"Bern",
    "sg:classifiers":[
        {
            "category":"Professional",
            "subcategory":"Advertising",
            "type":"Services"
        }
    ],
    "sg:phone":"+41 31 381 93 96",
    "sg:postcode":"3008",
    "sg:province":"Bern",
    "sg:tags":[
        "agency"
    ],
    "wof:name":"Maurer Und Staudenmann Werbeagentur",
    "wof:placetype":"venue"
},
  "geometry": {"coordinates":[7.436917,46.947102],"type":"Point"}
}