{
  "type": "Feature",
  "properties": {
    "iso:country":"CH",
    "sg:address":"Innerfeld 51 9606 B\u00fctschwil. Postfach 59",
    "sg:city":"B\u00fctschwil",
    "sg:orig_category":"Handel mit Automobilen",
    "sg:phone":"+41 79 207 47 20",
    "sg:postcode":"9606",
    "sg:province":"St. Gallen",
    "wof:name":"Feldgarage B\u00fctschwil Ag, 9606 B\u00fctschwil",
    "wof:placetype":"venue"
},
  "geometry": {"coordinates":[9.0739812851,47.354675293],"type":"Point"}
}