{
  "type": "Feature",
  "properties": {
    "iso:country":"CH",
    "sg:address":"Rue Du Levant 116",
    "sg:city":"Martigny",
    "sg:orig_category":"Herstellung von keramischen Wand U Bodenfliesen U platten Stukkateurgewerbe, Gipserei U Verputzerei",
    "sg:phone":"+41 79 353 89 18",
    "sg:postcode":"1920",
    "sg:province":"Valais",
    "wof:name":"Frehner Et Fils Sa",
    "wof:placetype":"venue"
},
  "geometry": {"coordinates":[7.0855951309,46.1005935669],"type":"Point"}
}