{
  "type": "Feature",
  "properties": {
    "iso:country":"CH",
    "sg:address":"Hoschet",
    "sg:city":"Engi",
    "sg:orig_category":"Detailhandel mit Fleisch U Fleischwaren",
    "sg:phone":"+41 55 642 11 42",
    "sg:postcode":"8765",
    "sg:province":"Glarus",
    "wof:name":"Z\u00fcrn Gebhard",
    "wof:placetype":"venue"
},
  "geometry": {"coordinates":[9.1608428955,46.9762458801],"type":"Point"}
}