{
  "type": "Feature",
  "properties": {
    "iso:country":"CH",
    "sg:address":"Blumenweg 9",
    "sg:city":"Baar",
    "sg:orig_category":"Unternehmensberatung",
    "sg:phone":"+41 79 340 25 04",
    "sg:postcode":"6340",
    "sg:province":"Zug",
    "wof:name":"Multidata Engineering + Management Ag",
    "wof:placetype":"venue"
},
  "geometry": {"coordinates":[8.5263109207,47.1984100342],"type":"Point"}
}