{
  "type": "Feature",
  "properties": {
    "iso:country":"CH",
    "sg:address":"2514",
    "sg:city":"Ligerz",
    "sg:classifiers":[
        {
            "category":"Government",
            "subcategory":"Post Office",
            "type":"Public Place"
        }
    ],
    "sg:phone":"+41 32 315 15 05",
    "sg:postcode":"2514",
    "sg:province":"Bern",
    "sg:tags":[
        "die",
        "poststellen"
    ],
    "wof:name":"Die Post",
    "wof:placetype":"venue"
},
  "geometry": {"coordinates":[7.1352510452,47.0840110779],"type":"Point"}
}