{
  "type": "Feature",
  "properties": {
    "iso:country":"CH",
    "sg:address":"Im Langen Loh 231 4054 Basel. Postfach",
    "sg:city":"Basel",
    "sg:orig_category":"Kauf U Verkauf von Immobilien auf eigene Rechnung",
    "sg:postcode":"4051",
    "sg:province":"Basel-Stadt",
    "wof:name":"Tinoba Gmbh Liegenschaften Usw",
    "wof:placetype":"venue"
},
  "geometry": {"coordinates":[7.5603342056,47.5484886169],"type":"Point"}
}