{
  "type": "Feature",
  "properties": {
    "addr:full":"Hofstettenstrasse 33 Thun Bern 3600",
    "addr:housenumber":"33",
    "addr:postcode":"3600",
    "addr:street":"Hofstettenstrasse;Bern",
    "iso:country":"CH",
    "sg:address":"Hofstettenstrasse 33",
    "sg:city":"Thun",
    "sg:orig_category":"Allgemeinbildende weiterf\u00fchrende Schulen Primarschulen",
    "sg:phone":"+41 33 222 41 08",
    "sg:postcode":"3600",
    "sg:province":"Bern",
    "wof:name":"Berntor-schulen Ag",
    "wof:placetype":"venue"
},
  "geometry": {"coordinates":[7.636026,46.754768],"type":"Point"}
}