{
  "type": "Feature",
  "properties": {
    "iso:country":"CH",
    "sg:address":"Kolbenstrasse 22",
    "sg:city":"Emmen",
    "sg:orig_category":"Sportvereine Behindertensport",
    "sg:phone":"+41 41 280 69 60",
    "sg:postcode":"6032",
    "sg:province":"Luzern",
    "wof:name":"Svbs Emmenbr\u00fccke",
    "wof:placetype":"venue"
},
  "geometry": {"coordinates":[8.2939682007,47.0919380188],"type":"Point"}
}