{
  "type": "Feature",
  "properties": {
    "iso:country":"CH",
    "sg:address":"In Den Neumatten 38",
    "sg:city":"Riehen",
    "sg:orig_category":"G\u00fcterbef\u00f6rderung im Strassenverkehr",
    "sg:phone":"+41 22 366 12 60",
    "sg:postcode":"4125",
    "sg:province":"Basel-Stadt",
    "wof:name":"Alphonse Jaquet Transports",
    "wof:placetype":"venue"
},
  "geometry": {"coordinates":[6.2182898521,46.4542808533],"type":"Point"}
}