{
  "type": "Feature",
  "properties": {
    "iso:country":"CH",
    "sg:address":"Alte Simplonstrasse 24 3900 Brig. Postfach",
    "sg:city":"Visp",
    "sg:orig_category":"Sonstige pers\u00f6nliche Dienstleistungen Tattoo and Piercing",
    "sg:phone":"+41 27 924 66 22",
    "sg:postcode":"3930",
    "sg:province":"Valais",
    "wof:name":"Creativ Tattoo-piercing-kosmetik, Ruppen Piercing, Tattoos, Brandung U. Kosmetik. Schmuck, Textilien, Geschenkartikel Usw.; Kauf, Verkauf",
    "wof:placetype":"venue"
},
  "geometry": {"coordinates":[7.9902281761,46.3155975342],"type":"Point"}
}