{
  "type": "Feature",
  "properties": {
    "addr:full":"Br\u00fcggstrasse 64 Biel/bienne Bern 2503",
    "addr:housenumber":"64",
    "addr:postcode":"2503",
    "addr:street":"Brueggstrasse",
    "iso:country":"CH",
    "sg:address":"Br\u00fcggstrasse 64",
    "sg:city":"Biel/bienne",
    "sg:orig_category":"Blumen U Zierpflanzenbau Detailhandel mit Blumen U Pflanzen",
    "sg:phone":"+41 32 365 45 25",
    "sg:postcode":"2503",
    "sg:province":"Bern",
    "wof:name":"Batschelet Gebr\u00fcder, G\u00e4rtnerei Und Blumen",
    "wof:placetype":"venue"
},
  "geometry": {"coordinates":[7.255085,47.129326],"type":"Point"}
}