{
  "type": "Feature",
  "properties": {
    "iso:country":"CH",
    "sg:address":"Seefeldstrasse 269",
    "sg:city":"Z\u00fcrich",
    "sg:orig_category":"Grosshandel mit Getr\u00e4nken",
    "sg:phone":"+41 13811446",
    "sg:postcode":"8008",
    "sg:province":"Z\u00fcrich",
    "wof:name":"Scaramella Weine",
    "wof:placetype":"venue"
},
  "geometry": {"coordinates":[8.5631093979,47.3491134644],"type":"Point"}
}