{
  "type": "Feature",
  "properties": {
    "iso:country":"CH",
    "sg:address":"Beethovenstrasse 20",
    "sg:city":"Z\u00fcrich",
    "sg:orig_category":"Kunsthandel Sonstiger Grosshandel",
    "sg:phone":"+41 34 445 98 89",
    "sg:postcode":"8002",
    "sg:province":"Z\u00fcrich",
    "wof:name":"Kobel Attar Gmbh",
    "wof:placetype":"venue"
},
  "geometry": {"coordinates":[7.5787730217,47.0898666382],"type":"Point"}
}