{
  "type": "Feature",
  "properties": {
    "iso:country":"CH",
    "sg:address":"6763",
    "sg:city":"Osco",
    "sg:orig_category":"S\u00e4ge, Hobel U Holzimpr\u00e4gnierwerke",
    "sg:postcode":"6763",
    "sg:province":"Ticino",
    "wof:name":"Segheria Cattaneo Sa",
    "wof:placetype":"venue"
},
  "geometry": {"coordinates":[8.7807064056,46.4939498901],"type":"Point"}
}