{
  "type": "Feature",
  "properties": {
    "iso:country":"CH",
    "sg:address":"Piazzetta Achille Borella",
    "sg:city":"Mendrisio",
    "sg:orig_category":"Detailhandel mit Uhren U Schmuck Fachdetailhandel in Verkaufsr\u00e4umen",
    "sg:phone":"+41 91 646 24 51",
    "sg:postcode":"6850",
    "sg:province":"Ticino",
    "wof:name":"Caldelari Alba",
    "wof:placetype":"venue"
},
  "geometry": {"coordinates":[8.9863195419,45.8692359924],"type":"Point"}
}