{
  "type": "Feature",
  "properties": {
    "addr:full":"Parallelstrasse 26 Frutigen Bern 3714",
    "addr:housenumber":"26",
    "addr:postcode":"3714",
    "addr:street":"Parallelstrasse",
    "iso:country":"CH",
    "sg:address":"Parallelstrasse 26",
    "sg:city":"Frutigen",
    "sg:orig_category":"Bauschreinerei Einbau von Schreinerwaren",
    "sg:phone":"+41 33 671 10 80",
    "sg:postcode":"3714",
    "sg:province":"Bern",
    "wof:name":"M\u00fcller K\u00fcchen Ag K\u00fcchenbau Leichentransporte",
    "wof:placetype":"venue"
},
  "geometry": {"coordinates":[7.652486,46.587421],"type":"Point"}
}