{
  "type": "Feature",
  "properties": {
    "iso:country":"CH",
    "sg:address":"Rue Des Rosiers 29",
    "sg:city":"Ste-croix",
    "sg:orig_category":"Universit\u00e4tsspit\u00e4ler, Spit\u00e4ler f\u00fcr allgemeine Pflege",
    "sg:phone":"+41 32 727 11 11",
    "sg:postcode":"1450",
    "sg:province":"Vaud",
    "wof:name":"H\u00f4pital Pourtal\u00e8s",
    "wof:placetype":"venue"
},
  "geometry": {"coordinates":[6.9422140121,46.9976577759],"type":"Point"}
}