{
  "type": "Feature",
  "properties": {
    "iso:country":"CH",
    "sg:address":"Margarethenstrasse 41",
    "sg:city":"Binningen",
    "sg:orig_category":"Architekturb\u00fcros",
    "sg:phone":"+41 61 421 77 12",
    "sg:postcode":"4102",
    "sg:province":"Basel-Landschaft",
    "wof:name":"Tony Rickenbacher Architekturb\u00fcro",
    "wof:placetype":"venue"
},
  "geometry": {"coordinates":[7.577931,47.536774],"type":"Point"}
}