{
  "type": "Feature",
  "properties": {
    "iso:country":"CH",
    "sg:address":"R\u00fcckimattweg 2",
    "sg:city":"Fraubrunnen",
    "sg:orig_category":"G\u00fcterbef\u00f6rderung im Strassenverkehr",
    "sg:phone":"+41 31 767 87 75",
    "sg:postcode":"3312",
    "sg:province":"Bern",
    "wof:name":"Roger Lenzin Transporte",
    "wof:placetype":"venue"
},
  "geometry": {"coordinates":[7.5257849693,47.0862998962],"type":"Point"}
}