{
  "type": "Feature",
  "properties": {
    "iso:country":"CH",
    "sg:address":"Avenue De S\u00e9velin 13",
    "sg:city":"Lausanne",
    "sg:orig_category":"Grosshandel mit Fleisch U Fleischwaren Schlachten U Fleischverarbeitung",
    "sg:phone":"+41 21 623 66 44",
    "sg:postcode":"1004",
    "sg:province":"Vaud",
    "wof:name":"Locindus Sa",
    "wof:placetype":"venue"
},
  "geometry": {"coordinates":[6.6157441139,46.5213165283],"type":"Point"}
}