{
  "type": "Feature",
  "properties": {
    "iso:country":"CH",
    "sg:address":"Via Mercetto 3",
    "sg:city":"Novazzano",
    "sg:orig_category":"Fachdetailhandel mit pharmazeutischen Produkten",
    "sg:phone":"+41 91 682 03 23",
    "sg:postcode":"6883",
    "sg:province":"Ticino",
    "wof:name":"Farmacia Quisisana Di Mascetti Rossi Lavinia",
    "wof:placetype":"venue"
},
  "geometry": {"coordinates":[8.980298996,45.8403587341],"type":"Point"}
}