{
  "type": "Feature",
  "properties": {
    "iso:country":"CH",
    "sg:address":"Fischmarkt 10",
    "sg:city":"Zug",
    "sg:orig_category":"Sonstige k\u00fcnstlerische U schriftstellerische T\u00e4tigkeiten U Darbietungen",
    "sg:phone":"+41 41 710 15 75",
    "sg:postcode":"6300",
    "sg:province":"Zug",
    "wof:name":"V. Indergand & T. Kuster Glaskunstatelier Am Zyturm",
    "wof:placetype":"venue"
},
  "geometry": {"coordinates":[8.5146913528,47.1663017273],"type":"Point"}
}