{
  "type": "Feature",
  "properties": {
    "iso:country":"CH",
    "sg:address":"Nunwilstrasse 40",
    "sg:city":"Hochdorf",
    "sg:orig_category":"Abwasserreinigung",
    "sg:phone":"+41 41 910 25 72",
    "sg:postcode":"6280",
    "sg:province":"Luzern",
    "wof:name":"Kl\u00e4ranlage",
    "wof:placetype":"venue"
},
  "geometry": {"coordinates":[8.281018,47.177593],"type":"Point"}
}