{
  "type": "Feature",
  "properties": {
    "iso:country":"CH",
    "sg:address":"L\u00f6wenstrasse 6",
    "sg:city":"Kreuzlingen",
    "sg:orig_category":"Detailhandel mit Bekleidung Detailhandel mit Damenbekleidung",
    "sg:phone":"+41 71 672 41 33",
    "sg:postcode":"8280",
    "sg:province":"Thurgau",
    "wof:name":"Susanne L\u00f6ser Boutique Sue",
    "wof:placetype":"venue"
},
  "geometry": {"coordinates":[9.17432,47.647732],"type":"Point"}
}