{
  "type": "Feature",
  "properties": {
    "iso:country":"CH",
    "sg:address":"Favre Avenue William- 36 1207 Gen\u00e8ve. Postfach",
    "sg:city":"Gen\u00e8ve",
    "sg:orig_category":"Softwareentwicklung U beratung",
    "sg:postcode":"1207",
    "sg:province":"Gen\u00e8ve",
    "wof:name":"Claus Software S\u00e0rl",
    "wof:placetype":"venue"
},
  "geometry": {"coordinates":[6.1665539742,46.2040138245],"type":"Point"}
}