{
  "type": "Feature",
  "properties": {
    "iso:country":"CH",
    "sg:address":"Dorf 19",
    "sg:city":"Milken",
    "sg:classifiers":[
        {
            "category":"Restaurant",
            "type":"Food & Drink"
        }
    ],
    "sg:phone":"+41 31 731 02 04",
    "sg:postcode":"3157",
    "sg:province":"Bern",
    "wof:name":"Restaurant Zwahlen",
    "wof:placetype":"venue"
},
  "geometry": {"coordinates":[7.3595099449,46.793258667],"type":"Point"}
}