{
  "type": "Feature",
  "properties": {
    "iso:country":"CH",
    "sg:address":"Nansenstrasse 2",
    "sg:city":"Z\u00fcrich",
    "sg:orig_category":"Architektur U Ingenieurb\u00fcros",
    "sg:phone":"+41 61 403 00 31",
    "sg:postcode":"8050",
    "sg:province":"Z\u00fcrich",
    "wof:name":"Ingenieurb\u00fcro Zwimpfer K.",
    "wof:placetype":"venue"
},
  "geometry": {"coordinates":[7.553645,47.512756],"type":"Point"}
}