{
  "type": "Feature",
  "properties": {
    "iso:country":"CH",
    "sg:address":"Kastelsstrasse 81b",
    "sg:city":"Grenchen",
    "sg:orig_category":"Fahrschulen, Flugschulen",
    "sg:phone":"+41 79 341 05 05",
    "sg:postcode":"2540",
    "sg:province":"Solothurn",
    "wof:name":"Pierre Huguenin Auto- & Motorradfahrschule",
    "wof:placetype":"venue"
},
  "geometry": {"coordinates":[7.401266098,47.1994781494],"type":"Point"}
}