{
  "type": "Feature",
  "properties": {
    "iso:country":"CH",
    "sg:address":"D\u00e4derizstrasse 82",
    "sg:city":"Grenchen",
    "sg:orig_category":"Elektroinstallation",
    "sg:phone":"+41 32 652 53 54",
    "sg:postcode":"2540",
    "sg:province":"Solothurn",
    "wof:name":"Kurt Knuchel Elektrische Installationen",
    "wof:placetype":"venue"
},
  "geometry": {"coordinates":[7.3878769875,47.1944351196],"type":"Point"}
}