{
  "type": "Feature",
  "properties": {
    "iso:country":"CH",
    "sg:address":"Centre Artisanale Zone E",
    "sg:city":"Fenil-sur-corsier",
    "sg:classifiers":[
        {
            "category":"Military Area",
            "subcategory":"Air Force Base",
            "type":"Public Place"
        }
    ],
    "sg:phone":"+41 21 922 26 27",
    "sg:postcode":"1809",
    "sg:province":"Vaud",
    "sg:tags":[
        "blinds",
        "protection",
        "vertical",
        "solar"
    ],
    "wof:name":"Von B\u00fcren-doutaz Stores S.a.r.l.",
    "wof:placetype":"venue"
},
  "geometry": {"coordinates":[6.8649868965,46.4827766418],"type":"Point"}
}