{
  "type": "Feature",
  "properties": {
    "iso:country":"CH",
    "sg:address":"W\u00fclflingerstrasse 265 8408 Winterthur. Postfach 139",
    "sg:city":"Winterthur",
    "sg:orig_category":"Unclassifiable Establishments",
    "sg:phone":"+41 52 222 21 11",
    "sg:postcode":"8408",
    "sg:province":"Z\u00fcrich",
    "wof:name":"Treuhandb\u00fcro Werner Eicher Verwaltungs Und Treuhand Ag",
    "wof:placetype":"venue"
},
  "geometry": {"coordinates":[8.6922149658,47.5104866028],"type":"Point"}
}