{
  "type": "Feature",
  "properties": {
    "iso:country":"CH",
    "sg:address":"Route Principale 21",
    "sg:city":"Vicques",
    "sg:orig_category":"Schreib U \u00dcbersetzungsb\u00fcros",
    "sg:phone":"+41 32 423 05 78",
    "sg:postcode":"2824",
    "sg:province":"Jura",
    "wof:name":"Egs H\u00e4geli Christine",
    "wof:placetype":"venue"
},
  "geometry": {"coordinates":[7.4118700027,47.3486747742],"type":"Point"}
}