{
  "type": "Feature",
  "properties": {
    "iso:country":"CH",
    "sg:address":"Vorholzstrasse 52 3800 Unterseen. Postfach",
    "sg:city":"Unterseen",
    "sg:orig_category":"Fotografische Ateliers Satzherstellung U Reproduktion",
    "sg:phone":"+41 33 823 47 08",
    "sg:postcode":"3800",
    "sg:province":"Bern",
    "wof:name":"Ulrich Thomas Visual Impact Gmbh Dienstleistungen Auf Dem Gebiet Der Fotografie Und Des Filmschaffens, Bes. Herstellung, Vertrieb, Verwaltung, Handel Mit Entsprechenden Produkten Usw",
    "wof:placetype":"venue"
},
  "geometry": {"coordinates":[7.8352828026,46.6848754883],"type":"Point"}
}