{
  "type": "Feature",
  "properties": {
    "iso:country":"CH",
    "sg:address":"Zelgstrasse 9",
    "sg:city":"Kreuzlingen",
    "sg:orig_category":"Datenverarbeitungsdienste Softwareentwicklung U beratung",
    "sg:phone":"+41 71 686 91 21",
    "sg:postcode":"8280",
    "sg:province":"Thurgau",
    "wof:name":"Data Migration Gmbh",
    "wof:placetype":"venue"
},
  "geometry": {"coordinates":[9.201754,47.642426],"type":"Point"}
}