{
  "type": "Feature",
  "properties": {
    "iso:country":"CH",
    "sg:address":"Pl\u00e4nkestrasse 20 2502 Biel/bienne. Postfach",
    "sg:city":"Biel/bienne",
    "sg:orig_category":"Erschliessung von Grundst\u00fccken",
    "sg:postcode":"2502",
    "sg:province":"Bern",
    "wof:name":"Vescocasa Gmbh",
    "wof:placetype":"venue"
},
  "geometry": {"coordinates":[7.2444682121,47.1370010376],"type":"Point"}
}