{
  "type": "Feature",
  "properties": {
    "iso:country":"CH",
    "sg:address":"Spinnereistrasse 29",
    "sg:city":"Rapperswil",
    "sg:classifiers":[
        {
            "category":"Travel",
            "subcategory":"Bed & Breakfast",
            "type":"Entertainment"
        }
    ],
    "sg:phone":"+41 55 220 86 00",
    "sg:postcode":"8640",
    "sg:province":"Schwyz",
    "sg:tags":[
        "air-cushioned"
    ],
    "wof:name":"Aqua Dynamic Ag",
    "wof:placetype":"venue"
},
  "geometry": {"coordinates":[8.831693,47.231144],"type":"Point"}
}