{
  "type": "Feature",
  "properties": {
    "iso:country":"CH",
    "sg:address":"Casa Fraissen",
    "sg:city":"Sevgein",
    "sg:orig_category":"Politische Parteien CVP",
    "sg:phone":"+41 81 925 21 17",
    "sg:postcode":"7127",
    "sg:province":"Graubunden",
    "wof:name":"Cvp Graub\u00fcnden",
    "wof:placetype":"venue"
},
  "geometry": {"coordinates":[9.2202348709,46.7645721436],"type":"Point"}
}