{
  "type": "Feature",
  "properties": {
    "iso:country":"CH",
    "sg:address":"Luzernerstrasse 4",
    "sg:city":"Ermensee",
    "sg:orig_category":"Mechanik Mechanische Werkst\u00e4tten",
    "sg:phone":"+41 41 917 04 24",
    "sg:postcode":"6294",
    "sg:province":"Luzern",
    "wof:name":"Fribatec Fries L.",
    "wof:placetype":"venue"
},
  "geometry": {"coordinates":[8.2420501709,47.2274932861],"type":"Point"}
}