{
  "type": "Feature",
  "properties": {
    "iso:country":"CH",
    "sg:address":"Chemin Des Acacias 6",
    "sg:city":"Crissier",
    "sg:orig_category":"Detailhandel mit Radio U Fernsehger\u00e4ten",
    "sg:phone":"+41 21 634 00 84",
    "sg:postcode":"1023",
    "sg:province":"Vaud",
    "wof:name":"Jean-claude Fricker T\u00e9l\u00e9secours Radio-tv",
    "wof:placetype":"venue"
},
  "geometry": {"coordinates":[6.5785031319,46.5421447754],"type":"Point"}
}