{
  "type": "Feature",
  "properties": {
    "iso:country":"CH",
    "sg:address":"1562",
    "sg:city":"Corcelles-payerne",
    "sg:orig_category":"Instandhaltung U Reparatur von Automobilen",
    "sg:phone":"+41 26 660 15 55",
    "sg:postcode":"1562",
    "sg:province":"Vaud",
    "wof:name":"Garage De La Broye Sa",
    "wof:placetype":"venue"
},
  "geometry": {"coordinates":[6.9492001534,46.8255996704],"type":"Point"}
}