{
  "type": "Feature",
  "properties": {
    "iso:country":"CH",
    "sg:address":"Herrengasse",
    "sg:city":"Oberneunforn",
    "sg:orig_category":"Sportvereine Turnen",
    "sg:phone":"+41 52 745 23 31",
    "sg:postcode":"8526",
    "sg:province":"Thurgau",
    "wof:name":"Turnverein Wilen-neunforn",
    "wof:placetype":"venue"
},
  "geometry": {"coordinates":[8.768289566,47.6055259705],"type":"Point"}
}