{
  "type": "Feature",
  "properties": {
    "iso:country":"CH",
    "sg:address":"S\u00e4gestrasse 45 5600 Lenzburg. Postfach",
    "sg:city":"Lenzburg",
    "sg:orig_category":"Zimmerei, Dachdeckerei, Bauspenglerei U Abdichtung",
    "sg:postcode":"5600",
    "sg:province":"Aargau",
    "wof:name":"M\u00fcller Dach Und Fassaden Ag",
    "wof:placetype":"venue"
},
  "geometry": {"coordinates":[8.1778278351,47.3928794861],"type":"Point"}
}