{
  "type": "Feature",
  "properties": {
    "iso:country":"CH",
    "sg:address":"Seematt 20",
    "sg:city":"Unter\u00e4geri",
    "sg:orig_category":"Grosshandel mit Datenverarbeitungsger\u00e4ten Hardwareberatung",
    "sg:phone":"+41 41 750 74 14",
    "sg:postcode":"6314",
    "sg:province":"Zug",
    "wof:name":"Andreas Schenk Elektronik Entwicklung",
    "wof:placetype":"venue"
},
  "geometry": {"coordinates":[8.5886707306,47.1355285645],"type":"Point"}
}