{
  "type": "Feature",
  "properties": {
    "iso:country":"CH",
    "sg:address":"Neustadtgasse 2",
    "sg:city":"Z\u00fcrich",
    "sg:orig_category":"Kunsthandel",
    "sg:phone":"+41 12122136",
    "sg:postcode":"8001",
    "sg:province":"Z\u00fcrich",
    "wof:name":"Ursula Wiedenkeller Galerie",
    "wof:placetype":"venue"
},
  "geometry": {"coordinates":[8.545624733,47.3695869446],"type":"Point"}
}