{
  "type": "Feature",
  "properties": {
    "iso:country":"CH",
    "sg:address":"Fischerg\u00e4sschen 14. 8200 Schaffhausen. Postfach",
    "sg:city":"Schaffhausen",
    "sg:orig_category":"RESTAURANTS: TEA-ROOMS",
    "sg:phone":"+41 22 743 00 30",
    "sg:postcode":"8200",
    "sg:province":"Schaffhausen",
    "wof:name":"Pantschier Gmbh",
    "wof:placetype":"venue"
},
  "geometry": {"coordinates":[8.7843599319,47.3668251038],"type":"Point"}
}