{
  "type": "Feature",
  "properties": {
    "iso:country":"CH",
    "sg:address":"H\u00fceblistrasse 46",
    "sg:city":"Oberweningen",
    "sg:orig_category":"Politische Vereinigungen",
    "sg:phone":"+41 18560959",
    "sg:postcode":"8165",
    "sg:province":"Z\u00fcrich",
    "wof:name":"Politisch Interessierte Frauen",
    "wof:placetype":"venue"
},
  "geometry": {"coordinates":[8.4021215439,47.5011482239],"type":"Point"}
}