{
  "type": "Feature",
  "properties": {
    "iso:country":"CH",
    "sg:address":"Buchholzstrasse 6",
    "sg:city":"Thun",
    "sg:orig_category":"Maler U Glasergewerbe Stukkateurgewerbe, Gipserei U Verputzerei",
    "sg:postcode":"3604",
    "sg:province":"Bern",
    "wof:name":"Michel, Willy.",
    "wof:placetype":"venue"
},
  "geometry": {"coordinates":[7.6162757874,46.7437934875],"type":"Point"}
}