{
  "type": "Feature",
  "properties": {
    "addr:full":"Im B\u00f6sch 6331 H\u00fcnenberg. Postfach H\u00fcnenberg Zug 6331",
    "addr:housenumber":"6331",
    "addr:postcode":"6331",
    "addr:street":"Im Boesch;Postfach Huenenberg Zug",
    "iso:country":"CH",
    "sg:address":"Im B\u00f6sch 6331 H\u00fcnenberg. Postfach",
    "sg:city":"H\u00fcnenberg",
    "sg:orig_category":"Baugewerbe",
    "sg:phone":"+41 41 780 52 52",
    "sg:postcode":"6331",
    "sg:province":"Zug",
    "wof:name":"Hotz Martin Ag",
    "wof:placetype":"venue"
},
  "geometry": {"coordinates":[8.434065,47.162876],"type":"Point"}
}