{
  "type": "Feature",
  "properties": {
    "iso:country":"CH",
    "sg:address":"Pflugg\u00e4sslein 2 4001 Basel. Postfach 309",
    "sg:city":"Basel",
    "sg:orig_category":"Wirtschaftsverb\u00e4nde Industrie, Handel and Gewerbe",
    "sg:phone":"+41 31 301 20 91",
    "sg:postcode":"4001",
    "sg:province":"Basel-Stadt",
    "wof:name":"Schweiz.fachst.f.informations- Technologien Im Bildungswesen",
    "wof:placetype":"venue"
},
  "geometry": {"coordinates":[7.4317059517,46.9517784119],"type":"Point"}
}