{
  "type": "Feature",
  "properties": {
    "iso:country":"CH",
    "sg:address":"Grundstrasse 41",
    "sg:city":"Rorbas",
    "sg:orig_category":"Sonstiger Grosshandel",
    "sg:postcode":"8427",
    "sg:province":"Z\u00fcrich",
    "wof:name":"Herrmann Peter",
    "wof:placetype":"venue"
},
  "geometry": {"coordinates":[8.5687294006,47.5344696045],"type":"Point"}
}