{
  "type": "Feature",
  "properties": {
    "iso:country":"CH",
    "sg:address":"Schulstrasse 6",
    "sg:city":"Ilanz",
    "sg:classifiers":[
        {
            "category":"Professional",
            "subcategory":"Art Services",
            "type":"Services"
        }
    ],
    "sg:phone":"+41 81 925 34 03",
    "sg:postcode":"7130",
    "sg:province":"Graubunden",
    "sg:tags":[
        "graphic",
        "designer"
    ],
    "wof:name":"Marius Hublard Graphisches Atelier",
    "wof:placetype":"venue"
},
  "geometry": {"coordinates":[9.2058696747,46.7736587524],"type":"Point"}
}