{
  "type": "Feature",
  "properties": {
    "iso:country":"CH",
    "sg:address":"Churfirstenstrasse 54",
    "sg:city":"Wil",
    "sg:classifiers":[
        {
            "category":"Shopping",
            "subcategory":"Crafts & Fabrics",
            "type":"Retail Goods"
        }
    ],
    "sg:phone":"+41 71 929 40 00",
    "sg:postcode":"9500",
    "sg:province":"St. Gallen",
    "sg:tags":[
        "decorative",
        "felt"
    ],
    "wof:name":"Wiler Filz Ag",
    "wof:placetype":"venue"
},
  "geometry": {"coordinates":[9.04699,47.455978],"type":"Point"}
}