{
  "type": "Feature",
  "properties": {
    "iso:country":"CH",
    "sg:address":"Bettmeralp 3981 Blitzingen. Postfach",
    "sg:city":"Bettmeralp",
    "sg:orig_category":"Gesundheitswesen",
    "sg:phone":"+41 41 260 60 33",
    "sg:postcode":"3992",
    "sg:province":"Valais",
    "wof:name":"Health Praxis Emmen Str\u00f6lin Peter",
    "wof:placetype":"venue"
},
  "geometry": {"coordinates":[8.2876653671,47.0753822327],"type":"Point"}
}