{
  "type": "Feature",
  "properties": {
    "iso:country":"CH",
    "sg:address":"Schweighofstrasse 226",
    "sg:city":"Z\u00fcrich",
    "sg:orig_category":"Detailhandel mit Waren verschiedener Art, Hauptrichtung Nahrungsmittel",
    "sg:phone":"+41 14620206",
    "sg:postcode":"8045",
    "sg:province":"Z\u00fcrich",
    "wof:name":"Coop Center",
    "wof:placetype":"venue"
},
  "geometry": {"coordinates":[8.5065603256,47.3608474731],"type":"Point"}
}