{
  "type": "Feature",
  "properties": {
    "iso:country":"CH",
    "sg:address":"Wiesenstrasse 13",
    "sg:city":"Rebstein",
    "sg:orig_category":"Detailhandel mit Waren verschiedener Art, Hauptrichtung Nahrungsmittel",
    "sg:phone":"+41 71 777 22 13",
    "sg:postcode":"9445",
    "sg:province":"St. Gallen",
    "wof:name":"Anny Ritter Gem\u00fcse",
    "wof:placetype":"venue"
},
  "geometry": {"coordinates":[9.5850896835,47.3971748352],"type":"Point"}
}