{
  "type": "Feature",
  "properties": {
    "iso:country":"CH",
    "sg:address":"Via Patocchi 34",
    "sg:city":"Orselina",
    "sg:orig_category":"Erdbewegungsarbeiten Unterhalt U Reparatur im Hoch U Tiefbau",
    "sg:postcode":"6644",
    "sg:province":"Ticino",
    "wof:name":"Bopp All-round Casa & Giardino Sagl",
    "wof:placetype":"venue"
},
  "geometry": {"coordinates":[8.7951860428,46.1786117554],"type":"Point"}
}