{
  "type": "Feature",
  "properties": {
    "iso:country":"CH",
    "sg:address":"Bahnhofstrasse 9",
    "sg:city":"M\u00e4genwil",
    "sg:orig_category":"Malerei",
    "sg:phone":"+41 52 741 15 65",
    "sg:postcode":"5506",
    "sg:province":"Aargau",
    "wof:name":"Malerwerkstatt Gn\u00e4dinger",
    "wof:placetype":"venue"
},
  "geometry": {"coordinates":[8.8552131653,47.6624832153],"type":"Point"}
}