{
  "type": "Feature",
  "properties": {
    "iso:country":"CH",
    "sg:address":"Mattenstrasse 135 2503 Biel/bienne Case Postale 1139",
    "sg:city":"Biel/bienne",
    "sg:orig_category":"Wirtschaftspr\u00fcfung, Steuerberatung U Treuhand",
    "sg:phone":"+41 32 366 50 05",
    "sg:postcode":"2501",
    "sg:province":"Bern",
    "wof:name":"Testor Treuhand",
    "wof:placetype":"venue"
},
  "geometry": {"coordinates":[7.2565259933,47.1374053955],"type":"Point"}
}