{
  "type": "Feature",
  "properties": {
    "iso:country":"CH",
    "sg:address":"Oberlandstrasse 10",
    "sg:city":"Spiez",
    "sg:orig_category":"Herstellung von sonstigen Maschinen f\u00fcr unspezifische Verwendung",
    "sg:phone":"+41 32 666 25 25",
    "sg:postcode":"3700",
    "sg:province":"Bern",
    "wof:name":"Bsz Produktionstechnik Ag",
    "wof:placetype":"venue"
},
  "geometry": {"coordinates":[7.556707859,47.1512069702],"type":"Point"}
}