{
  "type": "Feature",
  "properties": {
    "iso:country":"CH",
    "sg:address":"R\u00fcselmattstrasse 4",
    "sg:city":"Arch",
    "sg:orig_category":"Sonstige pers\u00f6nliche Dienstleistungen",
    "sg:postcode":"3296",
    "sg:province":"Bern",
    "wof:name":"Wtm & Partner Gmbh",
    "wof:placetype":"venue"
},
  "geometry": {"coordinates":[7.4230031967,47.1659584045],"type":"Point"}
}