{
  "type": "Feature",
  "properties": {
    "iso:country":"CH",
    "sg:address":"W\u00f6lferstrasse 13",
    "sg:city":"F\u00fcllinsdorf",
    "sg:orig_category":"Abwasserreinigung",
    "sg:phone":"+41 61 901 43 39",
    "sg:postcode":"4414",
    "sg:province":"Basel-Landschaft",
    "wof:name":"Abwasserreinigungsanlage Ergolz Ii",
    "wof:placetype":"venue"
},
  "geometry": {"coordinates":[7.725276,47.514389],"type":"Point"}
}