{
  "type": "Feature",
  "properties": {
    "iso:country":"CH",
    "sg:address":"Hofstattstrasse 7",
    "sg:city":"Kreuzlingen",
    "sg:orig_category":"Organisationen der Wohlfahrtspflege Tagesheime f\u00fcr Behinderte, gesch\u00fctzte Werkst\u00e4tten",
    "sg:phone":"+41 71 670 00 96",
    "sg:postcode":"8280",
    "sg:province":"Thurgau",
    "wof:name":"Kompass,stiftung F\u00fcr Menschen Mit Einer Behinderung",
    "wof:placetype":"venue"
},
  "geometry": {"coordinates":[9.1789512634,47.6433486938],"type":"Point"}
}