{
  "type": "Feature",
  "properties": {
    "iso:country":"CH",
    "sg:address":"6998 Termine. Postfach",
    "sg:city":"Termine",
    "sg:orig_category":"Architektur U Ingenieurb\u00fcros",
    "sg:postcode":"6998",
    "sg:province":"Ticino",
    "wof:name":"Bazeco Ag",
    "wof:placetype":"venue"
},
  "geometry": {"coordinates":[8.80266,45.998058],"type":"Point"}
}