{
  "type": "Feature",
  "properties": {
    "iso:country":"CH",
    "sg:address":"Bleichestrasse 5",
    "sg:city":"Winterthur",
    "sg:orig_category":"Gesundheitswesen",
    "sg:phone":"+41 61 401 45 94",
    "sg:postcode":"8400",
    "sg:province":"Z\u00fcrich",
    "wof:name":"Ern\u00e4hrungsberatung Von Rotz Caroline",
    "wof:placetype":"venue"
},
  "geometry": {"coordinates":[8.7174911499,47.5034942627],"type":"Point"}
}