{
  "type": "Feature",
  "properties": {
    "iso:country":"CH",
    "sg:address":"Les Gasses 27a",
    "sg:city":"Mi\u00e9court",
    "sg:orig_category":"Granit",
    "sg:postcode":"2946",
    "sg:province":"Jura",
    "wof:name":"Soca Sa",
    "wof:placetype":"venue"
},
  "geometry": {"coordinates":[7.1752409935,47.4280586243],"type":"Point"}
}