{
  "type": "Feature",
  "properties": {
    "iso:country":"CH",
    "sg:address":"Rue Du Vingt-trois-juin 19",
    "sg:city":"Porrentruy",
    "sg:orig_category":"Fahrschulen, Flugschulen",
    "sg:phone":"+41 32 466 55 55",
    "sg:postcode":"2900",
    "sg:province":"Jura",
    "wof:name":"Centre De Conduite",
    "wof:placetype":"venue"
},
  "geometry": {"coordinates":[7.0738120079,47.4160385132],"type":"Point"}
}