{
  "type": "Feature",
  "properties": {
    "addr:full":"Seehofmatt 7a 6314 Unter\u00e4geri. Postfach Unter\u00e4geri Zug 6314",
    "addr:housenumber":"7a",
    "addr:postcode":"6314;6314",
    "addr:street":"Seehofmatt;Postfach Unteraegeri Zug",
    "iso:country":"CH",
    "sg:address":"Seehofmatt 7a 6314 Unter\u00e4geri. Postfach",
    "sg:city":"Unter\u00e4geri",
    "sg:orig_category":"Abdichtung Herstellung von sonstigen Metallwaren",
    "sg:phone":"+41 41 750 63 41",
    "sg:postcode":"6314",
    "sg:province":"Zug",
    "wof:name":"R + L Abdichtungen Gmbh Abdichtungsarbeiten Mit Bitumendichtungsbahnen Im Hoch Und Tiefbau Usw",
    "wof:placetype":"venue"
},
  "geometry": {"coordinates":[8.589231,47.133755],"type":"Point"}
}