{
  "type": "Feature",
  "properties": {
    "iso:country":"CH",
    "sg:address":"Zieglerstrasse 9",
    "sg:city":"Bern",
    "sg:orig_category":"Allgemeiner Hoch U Tiefbau Hoch U Tiefbau",
    "sg:phone":"+41 31 381 20 55",
    "sg:postcode":"3007",
    "sg:province":"Bern",
    "wof:name":"Natur-bau Cdz Ag",
    "wof:placetype":"venue"
},
  "geometry": {"coordinates":[7.429258,46.946987],"type":"Point"}
}