{
  "type": "Feature",
  "properties": {
    "iso:country":"CH",
    "sg:address":"Rue Cornavin 11",
    "sg:city":"Gen\u00e8ve",
    "sg:orig_category":"Detailhandel mit Damenbekleidung",
    "sg:phone":"+41 22 732 55 60",
    "sg:postcode":"1201",
    "sg:province":"Gen\u00e8ve",
    "wof:name":"Mod Elle Sa Boutique Super Star",
    "wof:placetype":"venue"
},
  "geometry": {"coordinates":[6.142276,46.207996],"type":"Point"}
}