{
  "type": "Feature",
  "properties": {
    "iso:country":"CH",
    "sg:address":"Graben 36",
    "sg:city":"Aarau",
    "sg:orig_category":"Detailhandel mit Uhren U Schmuck Reparatur von Uhren U Schmuck",
    "sg:phone":"+41 62 822 47 57",
    "sg:postcode":"5000",
    "sg:province":"Aargau",
    "wof:name":"Franz Deubelbeiss Juwelen Uhren",
    "wof:placetype":"venue"
},
  "geometry": {"coordinates":[8.0448760986,47.3919563293],"type":"Point"}
}