{
  "type": "Feature",
  "properties": {
    "iso:country":"CH",
    "sg:address":"Lagerstrasse 107",
    "sg:city":"Z\u00fcrich",
    "sg:orig_category":"Non-Classified Establishments",
    "sg:postcode":"8004",
    "sg:province":"Z\u00fcrich",
    "wof:name":"Q Group Ag",
    "wof:placetype":"venue"
},
  "geometry": {"coordinates":[8.3064451218,47.4743309021],"type":"Point"}
}