{
  "type": "Feature",
  "properties": {
    "iso:country":"CH",
    "sg:address":"T\u00f6distrasse 45",
    "sg:city":"Z\u00fcrich",
    "sg:orig_category":"Herstellung von sonstigen organischen Grundstoffen U Chemikalien",
    "sg:postcode":"8002",
    "sg:province":"Z\u00fcrich",
    "wof:name":"Emox Ag",
    "wof:placetype":"venue"
},
  "geometry": {"coordinates":[8.5339298248,47.3672485352],"type":"Point"}
}