{
  "type": "Feature",
  "properties": {
    "iso:country":"CH",
    "sg:address":"Meierskappelerstrasse 8",
    "sg:city":"Rotkreuz",
    "sg:orig_category":"Unternehmensberatung",
    "sg:postcode":"6343",
    "sg:province":"Zug",
    "wof:name":"Geofix Ag",
    "wof:placetype":"venue"
},
  "geometry": {"coordinates":[8.4298810959,47.140411377],"type":"Point"}
}