{
  "type": "Feature",
  "properties": {
    "iso:country":"CH",
    "sg:address":"Oberlandstrasse 47",
    "sg:city":"Uster",
    "sg:orig_category":"Arztpraxen",
    "sg:phone":"+41 19401400",
    "sg:postcode":"8610",
    "sg:province":"Z\u00fcrich",
    "wof:name":"Dr.med.ruth Keller Spezial\u00e4rztin Fmh",
    "wof:placetype":"venue"
},
  "geometry": {"coordinates":[8.714612,47.355545],"type":"Point"}
}