{
  "type": "Feature",
  "properties": {
    "addr:full":"En Forchy Rueyres 1414",
    "addr:postcode":"1414",
    "addr:street":"Rueyres",
    "iso:country":"CH",
    "sg:address":"En Forchy",
    "sg:city":"Rueyres",
    "sg:orig_category":"Bauschreinerei S\u00e4gewerke",
    "sg:phone":"+41 21 887 78 16",
    "sg:postcode":"1414",
    "wof:name":"Scierie Zahnd Sa",
    "wof:placetype":"venue"
},
  "geometry": {"coordinates":[6.691933,46.693241],"type":"Point"}
}