{
  "type": "Feature",
  "properties": {
    "iso:country":"CH",
    "sg:address":"Breitenstrasse 106",
    "sg:city":"Stans",
    "sg:orig_category":"Einzelhandel mit Automobilen Innenausbau",
    "sg:phone":"+41 41 610 33 06",
    "sg:postcode":"6370",
    "sg:province":"Nidwalden",
    "wof:name":"Kaiser Motorhomes Gmbh Motorhomes U. Wohnmobile; Herstellung, Innenausbau, Reparatur, Vermietung U. Handel",
    "wof:placetype":"venue"
},
  "geometry": {"coordinates":[8.379904747,46.9627151489],"type":"Point"}
}