{
  "type": "Feature",
  "properties": {
    "iso:country":"CH",
    "sg:address":"Beim Kreuz Berg",
    "sg:city":"Weissbad",
    "sg:orig_category":"Non-Classified Establishments",
    "sg:postcode":"9057",
    "sg:province":"Appenzell Innerhoden",
    "wof:name":"F\u00e4ssler Zaunbau Gmbh",
    "wof:placetype":"venue"
},
  "geometry": {"coordinates":[9.4352722168,47.3014221191],"type":"Point"}
}