{
  "type": "Feature",
  "properties": {
    "iso:country":"CH",
    "sg:address":"Untere Allmende",
    "sg:city":"Spl\u00fcgen",
    "sg:orig_category":"Forst\u00e4mter",
    "sg:phone":"+41 81 664 11 79",
    "sg:postcode":"7435",
    "sg:province":"Graubunden",
    "wof:name":"Revierforstamt Rheinwald",
    "wof:placetype":"venue"
},
  "geometry": {"coordinates":[9.3164844513,46.5507087708],"type":"Point"}
}