{
  "type": "Feature",
  "properties": {
    "iso:country":"CH",
    "sg:address":"Hauptstrasse 32",
    "sg:city":"Guntershausen",
    "sg:orig_category":"Nationale Postdienste",
    "sg:phone":"+41 52 365 14 44",
    "sg:postcode":"8357",
    "sg:province":"Thurgau",
    "wof:name":"Die Schweizerische Post",
    "wof:placetype":"venue"
},
  "geometry": {"coordinates":[8.9144563675,47.476234436],"type":"Point"}
}