{
  "type": "Feature",
  "properties": {
    "iso:country":"CH",
    "sg:address":"Balgacherstrasse 219",
    "sg:city":"Heerbrugg",
    "sg:orig_category":"Sonstige mit der Informatik verbundene T\u00e4tigkeiten",
    "sg:phone":"+41 71 720 05 90",
    "sg:postcode":"9435",
    "sg:province":"St. Gallen",
    "wof:name":"Multimedia Maschek Gmbh",
    "wof:placetype":"venue"
},
  "geometry": {"coordinates":[9.6239099503,47.4098091125],"type":"Point"}
}