{
  "type": "Feature",
  "properties": {
    "iso:country":"CH",
    "sg:address":"Gl\u00e2ne Route De La 7",
    "sg:city":"Fribourg",
    "sg:orig_category":"Unternehmensberatung",
    "sg:postcode":"1700",
    "sg:province":"Fribourg",
    "wof:name":"Vemanag Gmbh",
    "wof:placetype":"venue"
},
  "geometry": {"coordinates":[7.57143116,46.9276275635],"type":"Point"}
}