{
  "type": "Feature",
  "properties": {
    "iso:country":"CH",
    "sg:address":"Vorstadt 32 6300 Zug. Postfach",
    "sg:city":"Zug",
    "sg:orig_category":"Finanzierungsinstitutionen",
    "sg:phone":"+41 19916130",
    "sg:postcode":"6300",
    "sg:province":"Zug",
    "wof:name":"Invest-consult Ag",
    "wof:placetype":"venue"
},
  "geometry": {"coordinates":[8.717423439,47.2499008179],"type":"Point"}
}