{
  "type": "Feature",
  "properties": {
    "iso:country":"CH",
    "sg:address":"Chemin Jean-portier 5",
    "sg:city":"Veyrier",
    "sg:orig_category":"Arztpraxen",
    "sg:phone":"+41 22 784 11 33",
    "sg:postcode":"1255",
    "sg:province":"Gen\u00e8ve",
    "wof:name":"Dr M\u00e9d. Dora-christine Knauer M\u00e9decin Sp\u00e9cialiste Fmh",
    "wof:placetype":"venue"
},
  "geometry": {"coordinates":[6.181057,46.165974],"type":"Point"}
}