{
  "type": "Feature",
  "properties": {
    "iso:country":"CH",
    "sg:address":"Fellenbergstrasse 288",
    "sg:city":"Z\u00fcrich",
    "sg:orig_category":"Kosmetikinstitute",
    "sg:phone":"+41 14919572",
    "sg:postcode":"8047",
    "sg:province":"Z\u00fcrich",
    "wof:name":"Ruth Lieberherr Kosmetikinstitut",
    "wof:placetype":"venue"
},
  "geometry": {"coordinates":[8.4902572632,47.3754577637],"type":"Point"}
}