{
  "type": "Feature",
  "properties": {
    "iso:country":"CH",
    "sg:address":"Gewerbehaus M\u00fchle",
    "sg:city":"Ebersecken",
    "sg:classifiers":[
        {
            "category":"Shopping",
            "subcategory":"Discount & Variety Stores",
            "type":"Retail Goods"
        }
    ],
    "sg:phone":"+41 62 748 70 50",
    "sg:postcode":"6245",
    "sg:province":"Luzern",
    "sg:tags":[
        "type",
        "ceramics"
    ],
    "wof:name":"Marmobisa Ag",
    "wof:placetype":"venue"
},
  "geometry": {"coordinates":[7.932855,47.1824],"type":"Point"}
}