{
  "type": "Feature",
  "properties": {
    "iso:country":"CH",
    "sg:address":"Rue Du Concert 6",
    "sg:city":"Neuch\u00e2tel",
    "sg:orig_category":"Herstellung von Uhren",
    "sg:postcode":"2000",
    "sg:province":"Neuch\u00e2tel",
    "wof:name":"Concept Design Gros-gaudenier",
    "wof:placetype":"venue"
},
  "geometry": {"coordinates":[6.8237938881,47.0952148438],"type":"Point"}
}