{
  "type": "Feature",
  "properties": {
    "iso:country":"CH",
    "sg:address":"Unterr\u00fctiweg 34",
    "sg:city":"Winterthur",
    "sg:orig_category":"Vorschulen, Kinderg\u00e4rten",
    "sg:phone":"+41 52 213 21 17",
    "sg:postcode":"8400",
    "sg:province":"Z\u00fcrich",
    "wof:name":"Kindergarten Unterr\u00fctiweg",
    "wof:placetype":"venue"
},
  "geometry": {"coordinates":[8.7176933289,47.516292572],"type":"Point"}
}