{
  "type": "Feature",
  "properties": {
    "addr:full":"Chemin Du Pr\u00e9-fleuri 21b Plan-les-ouates Gen\u00e8ve 1228",
    "addr:housenumber":"21b",
    "addr:postcode":"1228",
    "addr:street":"Chemin Du Pre\u0301-Fleuri",
    "iso:country":"CH",
    "sg:address":"Chemin Du Pr\u00e9-fleuri 21b",
    "sg:city":"Plan-les-ouates",
    "sg:orig_category":"Gaskets, Washers, Seals",
    "sg:phone":"+41 22 706 17 30",
    "sg:postcode":"1228",
    "sg:province":"Gen\u00e8ve",
    "wof:name":"Daniel Schulthess Sa",
    "wof:placetype":"venue"
},
  "geometry": {"coordinates":[6.108552,46.166016],"type":"Point"}
}