{
  "type": "Feature",
  "properties": {
    "iso:country":"CH",
    "sg:address":"Seestrasse 115 8610 Uster. Postfach",
    "sg:city":"Uster",
    "sg:orig_category":"Detailhandel mit Waren verschiedener Art, Hauptrichtung Nahrungsmittel",
    "sg:phone":"+41 19402094",
    "sg:postcode":"8610",
    "sg:province":"Z\u00fcrich",
    "wof:name":"Konsumgenossenschaft Niederuster",
    "wof:placetype":"venue"
},
  "geometry": {"coordinates":[8.6923131943,47.3512420654],"type":"Point"}
}