{
  "type": "Feature",
  "properties": {
    "iso:country":"CH",
    "sg:address":"Bohlstrasse 9a",
    "sg:city":"Zug",
    "sg:orig_category":"Unclassifiable Establishments",
    "sg:phone":"+41 27 933 10 40",
    "sg:postcode":"6300",
    "sg:province":"Zug",
    "wof:name":"Sat Akkumulatoren Technik Steg Ag",
    "wof:placetype":"venue"
},
  "geometry": {"coordinates":[7.7464599609,46.3153114319],"type":"Point"}
}