{
  "type": "Feature",
  "properties": {
    "iso:country":"CH",
    "sg:address":"Charmilles Rue Des 10 1400 Yverdon-les-bains. Postfach",
    "sg:city":"Cheseaux-nor\u00e9az",
    "sg:orig_category":"Finanzierungsinstitutionen",
    "sg:phone":"+41 24 426 65 10",
    "sg:postcode":"1400",
    "sg:province":"Vaud",
    "wof:name":"Cochand Thierry Conseils Financiers Et Gestion De Patrimoines",
    "wof:placetype":"venue"
},
  "geometry": {"coordinates":[6.6311321259,46.7779045105],"type":"Point"}
}