{
  "type": "Feature",
  "properties": {
    "iso:country":"CH",
    "sg:address":"Oberriedstrasse 274",
    "sg:city":"Gasel",
    "sg:orig_category":"K\u00fcnstlerische U schriftstellerische T\u00e4tigkeiten U Darbietungen",
    "sg:phone":"+41 31 849 04 94",
    "sg:postcode":"3144",
    "sg:province":"Bern",
    "wof:name":"D\u00e4hler Grabmal Und Steinhaueratelier",
    "wof:placetype":"venue"
},
  "geometry": {"coordinates":[7.4018540382,46.8999481201],"type":"Point"}
}