{
  "type": "Feature",
  "properties": {
    "iso:country":"CH",
    "sg:address":"6132",
    "sg:city":"Rohrmatt",
    "sg:orig_category":"Detailhandel mit Milcherzeugnissen U Eiern Verarbeitung von Milch",
    "sg:postcode":"6132",
    "sg:province":"Luzern",
    "wof:name":"K\u00e4sereigenossenschaft Scheimatt Bernhard Kurmann",
    "wof:placetype":"venue"
},
  "geometry": {"coordinates":[7.9858798981,47.0829391479],"type":"Point"}
}