{
  "type": "Feature",
  "properties": {
    "iso:country":"CH",
    "sg:address":"S\u00e4listrasse 7",
    "sg:city":"Zofingen",
    "sg:classifiers":[
        {
            "category":"Manufacturing",
            "subcategory":"Printing",
            "type":"Manufacturing & Wholesale Goods"
        }
    ],
    "sg:phone":"+41 62 751 99 88",
    "sg:postcode":"4800",
    "sg:province":"Aargau",
    "sg:tags":[
        "plate",
        "offset"
    ],
    "wof:name":"Retra Ag",
    "wof:placetype":"venue"
},
  "geometry": {"coordinates":[7.9462180138,47.2914886475],"type":"Point"}
}