{
  "type": "Feature",
  "properties": {
    "iso:country":"CH",
    "sg:address":"Bahnstrasse 102",
    "sg:city":"Regensdorf",
    "sg:classifiers":[
        {
            "category":"Communications",
            "subcategory":"Film & Video Production",
            "type":"Services"
        }
    ],
    "sg:phone":"+41 18840488",
    "sg:postcode":"8105",
    "sg:province":"Z\u00fcrich",
    "sg:tags":[
        "videofilmherstellung",
        "u"
    ],
    "wof:name":"Imaculix Gmbh Videoproduktionen, Multimediaanwendungen; Erstellung Usw",
    "wof:placetype":"venue"
},
  "geometry": {"coordinates":[8.4584140778,47.4442024231],"type":"Point"}
}