{
  "type": "Feature",
  "properties": {
    "iso:country":"CH",
    "sg:address":"Oberwilerweg 4/6",
    "sg:city":"Frauenfeld",
    "sg:orig_category":"Allgemeiner Hoch U Tiefbau",
    "sg:postcode":"8500",
    "sg:province":"Thurgau",
    "wof:name":"Ed. Vetter Ag, Lommis",
    "wof:placetype":"venue"
},
  "geometry": {"coordinates":[8.886981,47.552464],"type":"Point"}
}