{
  "type": "Feature",
  "properties": {
    "addr:full":"Bahnhofstrasse 53 Brunnen Schwyz 6440",
    "addr:housenumber":"53",
    "addr:postcode":"6440",
    "addr:street":"Bahnhofstrasse;Schwyz",
    "iso:country":"CH",
    "sg:address":"Bahnhofstrasse 53",
    "sg:city":"Brunnen",
    "sg:orig_category":"Allgemeiner Gartenbau",
    "sg:phone":"+41 41 822 03 65",
    "sg:postcode":"6440",
    "sg:province":"Schwyz",
    "wof:name":"Huber & Achermann G\u00e4rtnerei",
    "wof:placetype":"venue"
},
  "geometry": {"coordinates":[8.609277,46.998688],"type":"Point"}
}