{
  "type": "Feature",
  "properties": {
    "iso:country":"CH",
    "sg:address":"H\u00fchnerb\u00fchlstr. 14 3065 Bolligen. Postfach",
    "sg:city":"Bolligen",
    "sg:orig_category":"Non-Classified Establishments",
    "sg:phone":"+41 31 921 46 32",
    "sg:postcode":"3065",
    "sg:province":"Bern",
    "wof:name":"Blaser H. Ag",
    "wof:placetype":"venue"
},
  "geometry": {"coordinates":[7.4986391068,46.9728927612],"type":"Point"}
}