{
  "type": "Feature",
  "properties": {
    "iso:country":"CH",
    "sg:address":"1483",
    "sg:city":"Vesin",
    "sg:orig_category":"Bauschreinerei Herstellung von Konstruktionsteilen, Fertigbauteilen U Ausbauelementen aus Holz",
    "sg:phone":"+41 81 733 40 54",
    "sg:postcode":"1483",
    "sg:province":"Fribourg",
    "wof:name":"Manfred Wildhaber",
    "wof:placetype":"venue"
},
  "geometry": {"coordinates":[9.285299,47.094254],"type":"Point"}
}