{
  "type": "Feature",
  "properties": {
    "iso:country":"CH",
    "sg:address":"Ruessenstrasse 5",
    "sg:city":"Baar",
    "sg:orig_category":"Grosshandel mit keramischen Erzeugnissen, Glaswaren U Reinigungsmitteln Herstellung U Veredlung von ",
    "sg:phone":"+41 26 651 95 19",
    "sg:postcode":"6340",
    "sg:province":"Zug",
    "wof:name":"Erie Electroverre Sa",
    "wof:placetype":"venue"
},
  "geometry": {"coordinates":[6.927674,46.702427],"type":"Point"}
}