{
  "type": "Feature",
  "properties": {
    "iso:country":"CH",
    "sg:address":"Talstrasse 82 8001 Z\u00fcrich. Postfach 2828",
    "sg:city":"Z\u00fcrich",
    "sg:orig_category":"Herstellung von Papier, Karton U Pappe",
    "sg:phone":"+41 17493939",
    "sg:postcode":"8001",
    "sg:province":"Z\u00fcrich",
    "wof:name":"Leitz Holding Gmbh",
    "wof:placetype":"venue"
},
  "geometry": {"coordinates":[8.4198637009,47.4102325439],"type":"Point"}
}