{
  "type": "Feature",
  "properties": {
    "iso:country":"CH",
    "sg:address":"Staufferstrasse 8",
    "sg:city":"Bern",
    "sg:orig_category":"Grosshandel mit pharmazeutischen Erzeugnissen, medizinischen U orthop\u00e4dischen Artikeln",
    "sg:postcode":"3006",
    "sg:province":"Bern",
    "wof:name":"Du Mai Gmbh",
    "wof:placetype":"venue"
},
  "geometry": {"coordinates":[7.4641427994,46.939994812],"type":"Point"}
}