{
  "type": "Feature",
  "properties": {
    "iso:country":"CH",
    "sg:address":"Sihlweidstrasse 32",
    "sg:city":"Z\u00fcrich",
    "sg:orig_category":"Sprachschulen",
    "sg:phone":"+41 14827883",
    "sg:postcode":"8041",
    "sg:province":"Z\u00fcrich",
    "wof:name":"Peter Hegetschweiler Link Sprachschule",
    "wof:placetype":"venue"
},
  "geometry": {"coordinates":[8.516740799,47.326335907],"type":"Point"}
}