{
  "type": "Feature",
  "properties": {
    "iso:country":"CH",
    "sg:address":"Brunnhaldenstrasse 37b 8102 Oberengstringen. Postfach",
    "sg:city":"Oberengstringen",
    "sg:orig_category":"Architektur U Ingenieurb\u00fcros",
    "sg:phone":"+41 18700501",
    "sg:postcode":"8102",
    "sg:province":"Z\u00fcrich",
    "wof:name":"Ingenieur- & Planungsb\u00dcro Bogatzki Ag",
    "wof:placetype":"venue"
},
  "geometry": {"coordinates":[8.459733,47.413624],"type":"Point"}
}