{
  "type": "Feature",
  "properties": {
    "iso:country":"CH",
    "sg:address":"Avenue Louis-casa\u00ef 75-77 1216 Cointrin Case Postale 159",
    "sg:city":"Cointrin",
    "sg:orig_category":"HOTELS: MIT RESTAURANT Kongress- and Tagungshotels mit Restaurant",
    "sg:phone":"+41 22 710 30 00",
    "sg:postcode":"1216",
    "sg:province":"Gen\u00e8ve",
    "wof:name":"Hotel Penta Forum Park",
    "wof:placetype":"venue"
},
  "geometry": {"coordinates":[6.1071429253,46.2249603271],"type":"Point"}
}