{
  "type": "Feature",
  "properties": {
    "iso:country":"CH",
    "sg:address":"Reinhold Frei-strasse 17",
    "sg:city":"Z\u00fcrich",
    "sg:orig_category":"Unternehmensberatung",
    "sg:postcode":"8049",
    "sg:province":"Z\u00fcrich",
    "wof:name":"Kull R., Consulting And Trading Unternehmensberatung, Schulung, Treuhandgesch\u00e4fte Usw",
    "wof:placetype":"venue"
},
  "geometry": {"coordinates":[8.4857931137,47.4085464478],"type":"Point"}
}