{
  "type": "Feature",
  "properties": {
    "iso:country":"CH",
    "sg:address":"Gwattstrasse",
    "sg:city":"Pf\u00e4ffikon",
    "sg:orig_category":"Fish, Frozen",
    "sg:phone":"+41 55 410 70 40",
    "sg:postcode":"8808",
    "sg:province":"Schwyz",
    "wof:name":"Bettio Comestibles Gmbh",
    "wof:placetype":"venue"
},
  "geometry": {"coordinates":[8.7886457443,47.2017974854],"type":"Point"}
}