{
  "type": "Feature",
  "properties": {
    "iso:country":"CH",
    "sg:address":"Rue Maurice-braillard 8",
    "sg:city":"Gen\u00e8ve",
    "sg:orig_category":"Arztpraxen",
    "sg:phone":"+41 22 730 40 90",
    "sg:postcode":"1202",
    "sg:province":"Gen\u00e8ve",
    "wof:name":"Drs M\u00e9d. Hoffmann & Schopfer M\u00e9decins Sp\u00e9cialistes Fmh",
    "wof:placetype":"venue"
},
  "geometry": {"coordinates":[6.132109,46.220066],"type":"Point"}
}