{
  "type": "Feature",
  "properties": {
    "iso:country":"CH",
    "sg:address":"L\u00e4rchenstrasse 10",
    "sg:city":"M\u00fcnchenstein",
    "sg:orig_category":"Fotografische Ateliers",
    "sg:phone":"+41 61 411 38 22",
    "sg:postcode":"4142",
    "sg:province":"Basel-Landschaft",
    "wof:name":"Peter Gartmann Grafikdesign & Fotografie",
    "wof:placetype":"venue"
},
  "geometry": {"coordinates":[7.6130452156,47.5234794617],"type":"Point"}
}