{
  "type": "Feature",
  "properties": {
    "iso:country":"CH",
    "sg:address":"Lenkstrasse 15 3770 Zweisimmen. Postfach 320",
    "sg:city":"Zweisimmen",
    "sg:orig_category":"G\u00fcterbef\u00f6rderung im Strassenverkehr Herstellung von sonstigen Maschinen f\u00fcr bestimmte Verwendung",
    "sg:phone":"+41 33 722 41 63",
    "sg:postcode":"3770",
    "sg:province":"Bern",
    "wof:name":"Erich Schnidrig Kehrichtabfuhr",
    "wof:placetype":"venue"
},
  "geometry": {"coordinates":[7.374548912,46.5518074036],"type":"Point"}
}