{
  "type": "Feature",
  "properties": {
    "iso:country":"CH",
    "sg:address":"7205 Zizers. Postfach",
    "sg:city":"Zizers",
    "sg:orig_category":"Sportvereine Ballsport Tennis",
    "sg:phone":"+41 81 322 51 88",
    "sg:postcode":"7205",
    "sg:province":"Graubunden",
    "wof:name":"Tennisclub Zizers",
    "wof:placetype":"venue"
},
  "geometry": {"coordinates":[9.5652751923,46.9360046387],"type":"Point"}
}