{
  "type": "Feature",
  "properties": {
    "iso:country":"CH",
    "sg:address":"Chemin Des P\u00e2les 2",
    "sg:city":"Cortaillod",
    "sg:orig_category":"Instandhaltung U Reparatur von Automobilen",
    "sg:phone":"+41 32 842 10 60",
    "sg:postcode":"2016",
    "sg:province":"Neuch\u00e2tel",
    "wof:name":"Torche Pierre-alain",
    "wof:placetype":"venue"
},
  "geometry": {"coordinates":[6.8452129364,46.9446716309],"type":"Point"}
}