{
  "type": "Feature",
  "properties": {
    "iso:country":"CH",
    "sg:address":"2612",
    "sg:city":"Cormoret",
    "sg:orig_category":"Autogaragen",
    "sg:phone":"+41 32 373 58 58",
    "sg:postcode":"2612",
    "sg:province":"Bern",
    "wof:name":"K & K Automobile Garage",
    "wof:placetype":"venue"
},
  "geometry": {"coordinates":[7.312975,47.109009],"type":"Point"}
}