{
  "type": "Feature",
  "properties": {
    "iso:country":"CH",
    "sg:address":"Chemin Des Vauches 7 2900 Porrentruy Case Postale 297",
    "sg:city":"Pruntrut",
    "sg:orig_category":"Elektroinstallation",
    "sg:phone":"+41 71 311 15 22",
    "sg:postcode":"2900",
    "sg:province":"Jura",
    "wof:name":"Adrian Manser Adi Blitz Elektromontagen",
    "wof:placetype":"venue"
},
  "geometry": {"coordinates":[9.3127689362,47.4103736877],"type":"Point"}
}