{
  "type": "Feature",
  "properties": {
    "addr:full":"Feldstrasse 37 Oberhelfenschwil St. Gallen 9621",
    "addr:housenumber":"37",
    "addr:postcode":"9621",
    "addr:street":"Feldstrasse",
    "iso:country":"CH",
    "sg:address":"Feldstrasse 37",
    "sg:city":"Oberhelfenschwil",
    "sg:orig_category":"Architektur U Ingenieurb\u00fcros",
    "sg:phone":"+41 56 282 22 40",
    "sg:postcode":"9621",
    "sg:province":"St. Gallen",
    "wof:name":"Tonrec Gmbh Produkte Aller Art, Herstellung, Handel, Bes. Recycling Von Produkten Im Edv-bereich",
    "wof:placetype":"venue"
},
  "geometry": {"coordinates":[8.297795,47.486355],"type":"Point"}
}