{
  "type": "Feature",
  "properties": {
    "iso:country":"CH",
    "sg:address":"Rue Des Tanneurs 21",
    "sg:city":"Porrentruy",
    "sg:orig_category":"Vermietung U Verpachtung von eigenen Immobilien",
    "sg:phone":"+41 32 466 46 36",
    "sg:postcode":"2900",
    "sg:province":"Jura",
    "wof:name":"Roth Ernest Immeubles Sa",
    "wof:placetype":"venue"
},
  "geometry": {"coordinates":[7.0778198242,47.4175605774],"type":"Point"}
}