{
  "type": "Feature",
  "properties": {
    "iso:country":"CH",
    "sg:address":"Rue De La Vernie 17",
    "sg:city":"Crissier",
    "sg:orig_category":"Miscellaneous Products",
    "sg:phone":"+41 21 623 27 00",
    "sg:postcode":"1023",
    "sg:province":"Vaud",
    "wof:name":"Durafourg Sa",
    "wof:placetype":"venue"
},
  "geometry": {"coordinates":[6.6147108078,46.5248641968],"type":"Point"}
}