{
  "type": "Feature",
  "properties": {
    "iso:country":"CH",
    "sg:address":"Chemin De La Cr\u00e9taux",
    "sg:city":"Gland",
    "sg:orig_category":"Grosshandel mit Parf\u00fcmerieartikeln U K\u00f6rperpflegemitteln",
    "sg:phone":"+41 21 633 34 35",
    "sg:postcode":"1196",
    "sg:province":"Vaud",
    "wof:name":"Predige Sa",
    "wof:placetype":"venue"
},
  "geometry": {"coordinates":[6.5902590752,46.543800354],"type":"Point"}
}