{
  "type": "Feature",
  "properties": {
    "iso:country":"CH",
    "sg:address":"Elfenaustrasse 3",
    "sg:city":"Biel/bienne",
    "sg:orig_category":"Fachdetailhandel in Verkaufsr\u00e4umen",
    "sg:phone":"+41 32 325 36 66",
    "sg:postcode":"2502",
    "sg:province":"Bern",
    "wof:name":"About Diving Ag",
    "wof:placetype":"venue"
},
  "geometry": {"coordinates":[7.2389860153,47.137348175],"type":"Point"}
}