{
  "type": "Feature",
  "properties": {
    "iso:country":"CH",
    "sg:address":"Stansstaderstrasse 11",
    "sg:city":"Stans",
    "sg:orig_category":"Detailhandel mit Brot, Back U S\u00fcsswaren",
    "sg:phone":"+41 41 610 13 71",
    "sg:postcode":"6370",
    "sg:province":"Nidwalden",
    "wof:name":"B\u00e4ckerei Odermatt-portmann W.",
    "wof:placetype":"venue"
},
  "geometry": {"coordinates":[8.364396,46.958302],"type":"Point"}
}