{
  "type": "Feature",
  "properties": {
    "iso:country":"CH",
    "sg:address":"Poststrasse 9",
    "sg:city":"Zug",
    "sg:orig_category":"Handels-H\u00e4user U Gesellschaften",
    "sg:postcode":"6300",
    "sg:province":"Zug",
    "wof:name":"Ernst Ruoss Ag",
    "wof:placetype":"venue"
},
  "geometry": {"coordinates":[8.3861522675,47.3358306885],"type":"Point"}
}