{
  "type": "Feature",
  "properties": {
    "iso:country":"CH",
    "sg:address":"Marktgasse 21",
    "sg:city":"Z\u00fcrich",
    "sg:classifiers":[
        {
            "category":"Restaurant",
            "type":"Food & Drink"
        }
    ],
    "sg:phone":"+41 61 713 28 28",
    "sg:postcode":"8001",
    "sg:province":"Z\u00fcrich",
    "wof:name":"Trattoria Da Checco Sternenhof",
    "wof:placetype":"venue"
},
  "geometry": {"coordinates":[7.5964260101,47.4890975952],"type":"Point"}
}