{
  "type": "Feature",
  "properties": {
    "iso:country":"CH",
    "sg:address":"Obere Chros 500",
    "sg:city":"Twann",
    "sg:orig_category":"Detailhandel mit elektrischen Haushalts-,Radio U Fernsehger\u00e4ten sowie Musikinstrumenten Sonstige Hil",
    "sg:phone":"+41 32 315 21 29",
    "sg:postcode":"2513",
    "sg:province":"Bern",
    "wof:name":"Classic 2000, Schweizer Alfred",
    "wof:placetype":"venue"
},
  "geometry": {"coordinates":[7.1650238037,47.1031913757],"type":"Point"}
}