{
  "type": "Feature",
  "properties": {
    "iso:country":"CH",
    "sg:address":"Trevano Via 49",
    "sg:city":"Lugano",
    "sg:orig_category":"Bestattungswesen",
    "sg:postcode":"6900",
    "sg:province":"Ticino",
    "wof:name":"Cogeflay Sa",
    "wof:placetype":"venue"
},
  "geometry": {"coordinates":[8.955908,46.016945],"type":"Point"}
}