{
  "type": "Feature",
  "properties": {
    "iso:country":"CH",
    "sg:address":"4934",
    "sg:city":"Madiswil",
    "sg:orig_category":"Vereine Damen Vereine Gesang",
    "sg:postcode":"4934",
    "sg:province":"Bern",
    "wof:name":"Frauenchor Matten",
    "wof:placetype":"venue"
},
  "geometry": {"coordinates":[7.8534369469,46.6844787598],"type":"Point"}
}