{
  "type": "Feature",
  "properties": {
    "iso:country":"CH",
    "sg:address":"Am Bach 2",
    "sg:city":"Oberb\u00fcren",
    "sg:orig_category":"Fotografisches Gewerbe U fotografische Laboratorien",
    "sg:postcode":"9245",
    "sg:province":"St. Gallen",
    "wof:name":"Fotodesign Hubacher",
    "wof:placetype":"venue"
},
  "geometry": {"coordinates":[9.1393928528,47.4594993591],"type":"Point"}
}