{
  "type": "Feature",
  "properties": {
    "iso:country":"CH",
    "sg:address":"Ronmatt 2",
    "sg:city":"Root",
    "sg:orig_category":"Vereine Gemeinn\u00fctzige",
    "sg:phone":"+41 41 450 33 96",
    "sg:postcode":"6037",
    "sg:province":"Luzern",
    "wof:name":"Verein Sozialvernetzte Lebensgemeinschaft Sgl",
    "wof:placetype":"venue"
},
  "geometry": {"coordinates":[8.3832883835,47.1096000671],"type":"Point"}
}