{
  "type": "Feature",
  "properties": {
    "iso:country":"CH",
    "sg:address":"Balli Viale Francesco 2",
    "sg:city":"Locarno",
    "sg:orig_category":"Non-Classified Establishments",
    "sg:postcode":"6600",
    "sg:province":"Ticino",
    "wof:name":"Local Tabaco Sa",
    "wof:placetype":"venue"
},
  "geometry": {"coordinates":[8.7341480255,47.1973953247],"type":"Point"}
}