{
  "type": "Feature",
  "properties": {
    "iso:country":"CH",
    "sg:address":"5108",
    "sg:city":"Oberflachs",
    "sg:orig_category":"Primarschulen",
    "sg:postcode":"5108",
    "sg:province":"Aargau",
    "wof:name":"Primarschule",
    "wof:placetype":"venue"
},
  "geometry": {"coordinates":[8.1698598862,47.447681427],"type":"Point"}
}