{
  "type": "Feature",
  "properties": {
    "iso:country":"CH",
    "sg:address":"St. Gallerstrasse 6",
    "sg:city":"Eggersriet",
    "sg:orig_category":"Erdbewegungsarbeiten Strassenbau",
    "sg:phone":"+41 26 413 16 95",
    "sg:postcode":"9034",
    "sg:province":"St. Gallen",
    "wof:name":"Cotting Fr\u00e8res Sa Transports & Terrassements",
    "wof:placetype":"venue"
},
  "geometry": {"coordinates":[7.1431279182,46.7420806885],"type":"Point"}
}