{
  "type": "Feature",
  "properties": {
    "iso:country":"CH",
    "sg:address":"Kirchgasse 39",
    "sg:city":"Meilen",
    "sg:orig_category":"Kosmetikinstitute",
    "sg:phone":"+41 19238383",
    "sg:postcode":"8706",
    "sg:province":"Z\u00fcrich",
    "wof:name":"Gaby Schlagenhauf Kosmetik Am Dorfbach",
    "wof:placetype":"venue"
},
  "geometry": {"coordinates":[8.6410522461,47.2695350647],"type":"Point"}
}