{
  "type": "Feature",
  "properties": {
    "iso:country":"CH",
    "sg:address":"8952",
    "sg:city":"Schlieren",
    "sg:orig_category":"Vereine Frauen Vereine Gemeinn\u00fctzige",
    "sg:postcode":"8952",
    "sg:province":"Z\u00fcrich",
    "wof:name":"Gemeinn\u00fctziger Frauenverein",
    "wof:placetype":"venue"
},
  "geometry": {"coordinates":[8.447259903,47.3944702148],"type":"Point"}
}