{
  "type": "Feature",
  "properties": {
    "iso:country":"CH",
    "sg:address":"Buriet 9425 Thal. Postfach 4",
    "sg:city":"Thal",
    "sg:orig_category":"Schiffs U Bootsbau",
    "sg:phone":"+41 17151344",
    "sg:postcode":"9425",
    "sg:province":"St. Gallen",
    "wof:name":"Boesch Motorboote Ag Chantier Naval",
    "wof:placetype":"venue"
},
  "geometry": {"coordinates":[8.5524263382,47.3186912537],"type":"Point"}
}