{
  "type": "Feature",
  "properties": {
    "iso:country":"CH",
    "sg:address":"Chemin Du Molard 29",
    "sg:city":"Versoix",
    "sg:orig_category":"Herstellung von k\u00e4lte U lufttechnischen Erzeugnissen f\u00fcr gewerbliche Zwecke",
    "sg:phone":"+41 22 755 40 85",
    "sg:postcode":"1290",
    "sg:province":"Gen\u00e8ve",
    "wof:name":"Ruffino Jean-pierre.",
    "wof:placetype":"venue"
},
  "geometry": {"coordinates":[6.1651530266,46.2758483887],"type":"Point"}
}