{
  "type": "Feature",
  "properties": {
    "iso:country":"CH",
    "sg:address":"Seestrasse 281",
    "sg:city":"Unterseen",
    "sg:classifiers":[
        {
            "category":"Restaurant",
            "type":"Food & Drink"
        }
    ],
    "sg:phone":"+41 33 822 80 81",
    "sg:postcode":"3800",
    "sg:province":"Bern",
    "wof:name":"Restaurant Landhaus Manor Farm",
    "wof:placetype":"venue"
},
  "geometry": {"coordinates":[7.8121318817,46.6821556091],"type":"Point"}
}