{
  "type": "Feature",
  "properties": {
    "iso:country":"CH",
    "sg:address":"H\u00fcbelweg 3",
    "sg:city":"Nenzlingen",
    "sg:orig_category":"Fussboden, Fliesen U Plattenlegerei, Tapeziererei",
    "sg:postcode":"4224",
    "sg:province":"Basel-Landschaft",
    "wof:name":"Studer R. Gmbh",
    "wof:placetype":"venue"
},
  "geometry": {"coordinates":[7.5578432083,47.4460678101],"type":"Point"}
}