{
  "type": "Feature",
  "properties": {
    "iso:country":"CH",
    "sg:address":"Urdorferstrasse 68",
    "sg:city":"Schlieren",
    "sg:orig_category":"Tierarztpraxis",
    "sg:phone":"+41 17305918",
    "sg:postcode":"8952",
    "sg:province":"Z\u00fcrich",
    "wof:name":"Dr. Med. Vet. Max Bachmann Tierarzt",
    "wof:placetype":"venue"
},
  "geometry": {"coordinates":[8.4356594086,47.3943977356],"type":"Point"}
}