{
  "type": "Feature",
  "properties": {
    "iso:country":"CH",
    "sg:address":"L\u00e4ngackerstrasse 11",
    "sg:city":"Langendorf",
    "sg:orig_category":"Bau U Wohngenossenschaften",
    "sg:postcode":"4513",
    "sg:province":"Solothurn",
    "wof:name":"Wohnbaugen.der Rosegg-angest.",
    "wof:placetype":"venue"
},
  "geometry": {"coordinates":[7.517254,47.219925],"type":"Point"}
}