{
  "type": "Feature",
  "properties": {
    "iso:country":"CH",
    "sg:address":"Flawilerstrasse 80",
    "sg:city":"Gossau",
    "sg:classifiers":[
        {
            "category":"Retail",
            "subcategory":"Auto Repair",
            "type":"Services"
        }
    ],
    "sg:phone":"+41 71 385 03 06",
    "sg:postcode":"9200",
    "sg:province":"St. Gallen",
    "sg:tags":[
        "body",
        "car"
    ],
    "wof:name":"A & S Aerne & Sutter Honda-sport",
    "wof:placetype":"venue"
},
  "geometry": {"coordinates":[9.227918,47.408161],"type":"Point"}
}