{
  "type": "Feature",
  "properties": {
    "iso:country":"CH",
    "sg:address":"Buen 65 Oberhittnau",
    "sg:city":"Hittnau",
    "sg:orig_category":"Herstellung von sonstigen elektrischen Ausr\u00fcstungen",
    "sg:postcode":"8335",
    "sg:province":"Z\u00fcrich",
    "wof:name":"Elektronik - Fischer",
    "wof:placetype":"venue"
},
  "geometry": {"coordinates":[8.8228635788,47.3693885803],"type":"Point"}
}