{
  "type": "Feature",
  "properties": {
    "iso:country":"CH",
    "sg:address":"H\u00fcslibachstrasse 92 8041 Z\u00fcrich. Postfach",
    "sg:city":"Z\u00fcrich",
    "sg:orig_category":"Erschliessung von Grundst\u00fccken",
    "sg:phone":"+41 14820582",
    "sg:postcode":"8041",
    "sg:province":"Z\u00fcrich",
    "wof:name":"Baugenossenschaft Freiblick Z\u00fcrich",
    "wof:placetype":"venue"
},
  "geometry": {"coordinates":[8.5164279938,47.3287582397],"type":"Point"}
}