{
  "type": "Feature",
  "properties": {
    "iso:country":"CH",
    "sg:address":"Schlossstrasse 10",
    "sg:city":"Nidau",
    "sg:orig_category":"Instandhaltung U Reparatur von Automobilen",
    "sg:phone":"+41 32 331 65 50",
    "sg:postcode":"2560",
    "sg:province":"Bern",
    "wof:name":"Carrosserie Camazo Ag",
    "wof:placetype":"venue"
},
  "geometry": {"coordinates":[7.2378702164,47.126865387],"type":"Point"}
}