{
  "type": "Feature",
  "properties": {
    "iso:country":"CH",
    "sg:address":"C\u00f4tes-de-montbenon Rue 16 1003 Lausanne. Postfach",
    "sg:city":"Lausanne",
    "sg:orig_category":"Zeitungsverlag",
    "sg:phone":"+41 21 323 41 30",
    "sg:postcode":"1003",
    "sg:province":"Vaud",
    "wof:name":"Fertile, Dentan & Maibach Journal Satirique; Cr\u00e9ation, R\u00e9daction, Diffusion",
    "wof:placetype":"venue"
},
  "geometry": {"coordinates":[6.6262578964,46.5213851929],"type":"Point"}
}