{
  "type": "Feature",
  "properties": {
    "iso:country":"CH",
    "sg:address":"Via Balestra 40",
    "sg:city":"Locarno",
    "sg:classifiers":[
        {
            "category":"Restaurant",
            "type":"Food & Drink"
        }
    ],
    "sg:phone":"+41 91 752 24 81",
    "sg:postcode":"6600",
    "sg:province":"Ticino",
    "wof:name":"Caff\u00e8 Robinia",
    "wof:placetype":"venue"
},
  "geometry": {"coordinates":[8.7980575562,46.162273407],"type":"Point"}
}