{
  "type": "Feature",
  "properties": {
    "iso:country":"CH",
    "sg:address":"Rue Beau-s\u00e9jour 10 1003 Lausanne Case Postale 2860",
    "sg:city":"Lausanne",
    "sg:orig_category":"Advokaturb\u00fcros",
    "sg:phone":"+41 26 913 96 30",
    "sg:postcode":"1002",
    "sg:province":"Vaud",
    "wof:name":"Jacques Bonfils Etude D'avocat",
    "wof:placetype":"venue"
},
  "geometry": {"coordinates":[7.05545,46.618839],"type":"Point"}
}