{
  "type": "Feature",
  "properties": {
    "iso:country":"CH",
    "sg:address":"Rue De Bourg 33 1003 Lausanne Case Postale 2792",
    "sg:city":"Lausanne",
    "sg:orig_category":"Advokaturb\u00fcros",
    "sg:phone":"+41 21 323 63 25",
    "sg:postcode":"1002",
    "sg:province":"Vaud",
    "wof:name":"Mouquin Merz & Micheli Etude D'avocat",
    "wof:placetype":"venue"
},
  "geometry": {"coordinates":[6.635711,46.520088],"type":"Point"}
}