{
  "type": "Feature",
  "properties": {
    "iso:country":"CH",
    "sg:address":"Eysins Chemin D' 49b",
    "sg:city":"Nyon",
    "sg:orig_category":"Softwareentwicklung U beratung",
    "sg:postcode":"1260",
    "sg:province":"Vaud",
    "wof:name":"Mai Consulting, M'baye Mamadou",
    "wof:placetype":"venue"
},
  "geometry": {"coordinates":[6.2390799522,46.382358551],"type":"Point"}
}