{
  "type": "Feature",
  "properties": {
    "iso:country":"CH",
    "sg:address":"Rue Marcello 18",
    "sg:city":"Fribourg",
    "sg:classifiers":[
        {
            "category":"Autos & Motor Vehicles",
            "subcategory":"Auto Supplies",
            "type":"Retail Goods"
        }
    ],
    "sg:phone":"+41 26 322 96 00",
    "sg:postcode":"1700",
    "sg:province":"Fribourg",
    "sg:tags":[
        "car",
        "radio",
        "accessory"
    ],
    "wof:name":"Ab Electronics S\u00e0rl",
    "wof:placetype":"venue"
},
  "geometry": {"coordinates":[7.154391,46.807877],"type":"Point"}
}