{
  "type": "Feature",
  "properties": {
    "addr:full":"R\u00f6schenzstrasse 24 4242 Laufen. Postfach Laufen Basel-Landschaft 4242",
    "addr:housenumber":"24",
    "addr:postcode":"4242 laufen. postfach;4242",
    "addr:street":"Roeschenzstrasse",
    "iso:country":"CH",
    "sg:address":"R\u00f6schenzstrasse 24 4242 Laufen. Postfach",
    "sg:city":"Laufen",
    "sg:orig_category":"Advokaturb\u00fcros",
    "sg:phone":"+41 61 765 90 65",
    "sg:postcode":"4242",
    "sg:province":"Basel-Landschaft",
    "wof:name":"Alexander Imhof Advokaturb\u00fcro",
    "wof:placetype":"venue"
},
  "geometry": {"coordinates":[7.497849,47.4216],"type":"Point"}
}