{
  "type": "Feature",
  "properties": {
    "iso:country":"CH",
    "sg:address":"Rue Beau-s\u00e9jour 29",
    "sg:city":"Lausanne",
    "sg:classifiers":[
        {
            "category":"Restaurant",
            "type":"Food & Drink"
        }
    ],
    "sg:phone":"+41 21 312 88 87",
    "sg:postcode":"1003",
    "sg:province":"Vaud",
    "wof:name":"Caf\u00e9 Lyrique",
    "wof:placetype":"venue"
},
  "geometry": {"coordinates":[6.6376609802,46.5175514221],"type":"Point"}
}