{
  "type": "Feature",
  "properties": {
    "iso:country":"CH",
    "sg:address":"Fauquez Route Aloys- 105",
    "sg:city":"Lausanne",
    "sg:orig_category":"Fachdetailhandel mit pharmazeutischen Produkten",
    "sg:postcode":"1018",
    "sg:province":"Vaud",
    "wof:name":"Junod Dominique",
    "wof:placetype":"venue"
},
  "geometry": {"coordinates":[6.6336579323,46.5380325317],"type":"Point"}
}