{
  "type": "Feature",
  "properties": {
    "iso:country":"CH",
    "sg:address":"Rue Du Bourg 25",
    "sg:city":"Martigny",
    "sg:orig_category":"RESTAURANTS: TEA-ROOMS",
    "sg:postcode":"1920",
    "sg:province":"Valais",
    "wof:name":"Deecaf Marktbistro Yildirim D.",
    "wof:placetype":"venue"
},
  "geometry": {"coordinates":[9.1381845474,47.5666694641],"type":"Point"}
}