{
  "type": "Feature",
  "properties": {
    "iso:country":"CH",
    "sg:address":"Schachenallee 29 5000 Aarau. Postfach",
    "sg:city":"Aarau",
    "sg:orig_category":"Oberfl\u00e4chenreinigung Sandstrahlen Siebdruck",
    "sg:phone":"+41 41 930 45 30",
    "sg:postcode":"5001",
    "sg:province":"Aargau",
    "wof:name":"Adolf Steininger Pink Point Print",
    "wof:placetype":"venue"
},
  "geometry": {"coordinates":[8.157995224,47.2221755981],"type":"Point"}
}