{
  "type": "Feature",
  "properties": {
    "iso:country":"CH",
    "sg:address":"Marktgasse 2",
    "sg:city":"Stans",
    "sg:orig_category":"Detailhandel mit Waren verschiedener Art, Hauptrichtung Nahrungsmittel Grosshandel mit Nahrungsmitte",
    "sg:phone":"+41 41 610 13 94",
    "sg:postcode":"6370",
    "sg:province":"Nidwalden",
    "wof:name":"Detaillist Mit Migros Produkten, Waser Thomas",
    "wof:placetype":"venue"
},
  "geometry": {"coordinates":[8.3661775589,46.9565048218],"type":"Point"}
}