{
  "type": "Feature",
  "properties": {
    "iso:country":"CH",
    "sg:address":"Kasernenstrasse 2",
    "sg:city":"Herisau",
    "sg:orig_category":"Fachdetailhandel mit Nahrungsmitteln, Getr\u00e4nken U Tabakwaren in Verkaufsr\u00e4umen",
    "sg:phone":"+41 71 311 49 59",
    "sg:postcode":"9100",
    "sg:province":"Appenzell Ausserrhoden",
    "wof:name":"Spar Supermarkt",
    "wof:placetype":"venue"
},
  "geometry": {"coordinates":[9.3130712509,47.4050674438],"type":"Point"}
}