{
  "type": "Feature",
  "properties": {
    "iso:country":"CH",
    "sg:address":"Isenacher 2.",
    "sg:city":"St\u00e4fa",
    "sg:orig_category":"Unternehmensberatung",
    "sg:phone":"+41 71 245 11 51",
    "sg:postcode":"8712",
    "sg:province":"Z\u00fcrich",
    "wof:name":"Strauss Ag",
    "wof:placetype":"venue"
},
  "geometry": {"coordinates":[9.3951749802,47.4311218262],"type":"Point"}
}