{
  "type": "Feature",
  "properties": {
    "iso:country":"CH",
    "sg:address":"Birkenweg 7",
    "sg:city":"Nidau",
    "sg:orig_category":"Herstellung von Lederwaren U Schuhen Textilgewerbe",
    "sg:phone":"+41 32 331 67 23",
    "sg:postcode":"2560",
    "sg:province":"Bern",
    "wof:name":"Dgw (swiss) - Zweigniederlassung Schweiz, Biel Be, Der Dgw-deutsche Gesellschaft F\u00fcr Recycling Mbh",
    "wof:placetype":"venue"
},
  "geometry": {"coordinates":[7.2374529839,47.119682312],"type":"Point"}
}