{
  "type": "Feature",
  "properties": {
    "addr:full":"Baselstrasse 61 6252 Dagmersellen. Postfach 133 Dagmersellen Luzern 6252",
    "addr:housenumber":"61;133",
    "addr:postcode":"6252 dagmersellen.;6252",
    "addr:street":"Baselstrasse;Postfach",
    "iso:country":"CH",
    "sg:address":"Baselstrasse 61 6252 Dagmersellen. Postfach 133",
    "sg:city":"Dagmersellen",
    "sg:orig_category":"Herstellung von Schl\u00f6ssern U Beschl\u00e4gen",
    "sg:phone":"+41 62 748 60 60",
    "sg:postcode":"6252",
    "sg:province":"Luzern",
    "wof:name":"Bekon-koralle Ag Techn. Artikel, Bes. F\u00fcr Die Sanit\u00e4rbranche; Herstellung, Handel Usw",
    "wof:placetype":"venue"
},
  "geometry": {"coordinates":[7.982236,47.219707],"type":"Point"}
}