{
  "type": "Feature",
  "properties": {
    "iso:country":"CH",
    "sg:address":"Oberdorf 321",
    "sg:city":"Hellikon",
    "sg:orig_category":"Instandhaltung U Reparatur von Automobilen",
    "sg:phone":"+41 61 871 09 07",
    "sg:postcode":"4316",
    "sg:province":"Aargau",
    "wof:name":"Waldmeier Ulrich Garage Ag",
    "wof:placetype":"venue"
},
  "geometry": {"coordinates":[7.9187660217,47.5087585449],"type":"Point"}
}