{
  "type": "Feature",
  "properties": {
    "addr:full":"Leimenstrasse 59 Basel Basel-Stadt 4051",
    "addr:housenumber":"59",
    "addr:postcode":"4051",
    "addr:street":"Leimenstrasse",
    "iso:country":"CH",
    "sg:address":"Leimenstrasse 59",
    "sg:city":"Basel",
    "sg:orig_category":"Architekturb\u00fcros",
    "sg:phone":"+41 61 271 67 30",
    "sg:postcode":"4051",
    "sg:province":"Basel-Stadt",
    "wof:name":"Fritz Kettner Architekturb\u00fcro",
    "wof:placetype":"venue"
},
  "geometry": {"coordinates":[7.580885,47.552246],"type":"Point"}
}