{
  "type": "Feature",
  "properties": {
    "iso:country":"CH",
    "sg:address":"Route De Mon-id\u00e9e 4",
    "sg:city":"Th\u00f4nex",
    "sg:orig_category":"Zoll- and Grenzb\u00fcros",
    "sg:phone":"+41 22 348 85 68",
    "sg:postcode":"1226",
    "sg:province":"Gen\u00e8ve",
    "wof:name":"Douane Suisse Bureau Mon-id\u00e9e",
    "wof:placetype":"venue"
},
  "geometry": {"coordinates":[6.2228808403,46.2022743225],"type":"Point"}
}