{
  "type": "Feature",
  "properties": {
    "addr:full":"Lohstrasse 19a Balterswil Thurgau 8362",
    "addr:housenumber":"19a",
    "addr:postcode":"8362",
    "addr:street":"Lohstrasse",
    "iso:country":"CH",
    "sg:address":"Lohstrasse 19a",
    "sg:city":"Balterswil",
    "sg:orig_category":"Bauschreinerei Herstellung von Konstruktionsteilen, Fertigbauteilen U Ausbauelementen aus Holz",
    "sg:phone":"+41 31 747 73 91",
    "sg:postcode":"8362",
    "sg:province":"Thurgau",
    "wof:name":"Schneider Fritz, Schreinerei-formenbau",
    "wof:placetype":"venue"
},
  "geometry": {"coordinates":[7.236583,46.90667],"type":"Point"}
}