{
  "type": "Feature",
  "properties": {
    "iso:country":"CH",
    "sg:address":"Niederau",
    "sg:city":"Bauma",
    "sg:orig_category":"Ger\u00fcstbau Vermietung von Baumaschinen U ger\u00e4ten",
    "sg:phone":"+41 79 644 43 44",
    "sg:postcode":"8494",
    "sg:province":"Z\u00fcrich",
    "wof:name":"Fridolin Mathys Ger\u00fcstbau",
    "wof:placetype":"venue"
},
  "geometry": {"coordinates":[7.5917959213,47.4755897522],"type":"Point"}
}