{
  "type": "Feature",
  "properties": {
    "iso:country":"CH",
    "sg:address":"Schulstrasse 161",
    "sg:city":"Regensdorf",
    "sg:classifiers":[
        {
            "category":"Health Services",
            "subcategory":"Medical Lab",
            "type":"Services"
        }
    ],
    "sg:phone":"+41 18840600",
    "sg:postcode":"8105",
    "sg:province":"Z\u00fcrich",
    "sg:tags":[
        "technology"
    ],
    "wof:name":"Medizintechnik Basler Ag",
    "wof:placetype":"venue"
},
  "geometry": {"coordinates":[8.4694633484,47.4371871948],"type":"Point"}
}