{
  "type": "Feature",
  "properties": {
    "iso:country":"CH",
    "sg:address":"Via Muro Della Rossa 7",
    "sg:city":"Locarno",
    "sg:orig_category":"Sportvereine J and S Fachleiter Sportvereine Wassersport Schwimmen",
    "sg:postcode":"6600",
    "sg:province":"Ticino",
    "wof:name":"J & S Fachleiter",
    "wof:placetype":"venue"
},
  "geometry": {"coordinates":[8.7753582001,46.1689300537],"type":"Point"}
}