{
  "type": "Feature",
  "properties": {
    "iso:country":"CH",
    "sg:address":"6593",
    "sg:city":"Cadenazzo",
    "sg:orig_category":"Allgemeiner Hoch U Tiefbau",
    "sg:postcode":"6593",
    "sg:province":"Ticino",
    "wof:name":"Mancini & Marti Sa Succursale Di Cadenazzo",
    "wof:placetype":"venue"
},
  "geometry": {"coordinates":[8.95638,46.150631],"type":"Point"}
}