{
  "type": "Feature",
  "properties": {
    "iso:country":"CH",
    "sg:address":"Grossmatte 6260 Reiden. Postfach",
    "sg:city":"Reiden",
    "sg:orig_category":"Reiseb\u00fcros U Reiseveranstalter",
    "sg:phone":"+41 62 758 26 66",
    "sg:postcode":"6260",
    "sg:province":"Luzern",
    "wof:name":"Meyer-reisen",
    "wof:placetype":"venue"
},
  "geometry": {"coordinates":[7.9697651863,47.2414360046],"type":"Point"}
}