{
  "type": "Feature",
  "properties": {
    "iso:country":"CH",
    "sg:address":"Uttins Rue Des 34",
    "sg:city":"Yverdon-les-bains",
    "sg:orig_category":"Instandhaltung U Reparatur von Automobilen",
    "sg:phone":"+41 24 446 29 20",
    "sg:postcode":"1400",
    "sg:province":"Vaud",
    "wof:name":"Autorep, Potterat Jean",
    "wof:placetype":"venue"
},
  "geometry": {"coordinates":[6.6414198875,46.7786331177],"type":"Point"}
}