{
  "type": "Feature",
  "properties": {
    "addr:full":"Dorfstrasse 12 6064 Kerns. Postfach 165 Kerns Obwalden 6064",
    "addr:housenumber":"12;165",
    "addr:postcode":"6064 kerns.;6064",
    "addr:street":"Dorfstrasse;Postfach",
    "iso:country":"CH",
    "sg:address":"Dorfstrasse 12 6064 Kerns. Postfach 165",
    "sg:city":"Kerns",
    "sg:orig_category":"B\u00e4ckereien Detailhandel mit Waren verschiedener Art, Hauptrichtung Nahrungsmittel",
    "sg:phone":"+41 41 660 13 94",
    "sg:postcode":"6064",
    "sg:province":"Obwalden",
    "wof:name":"Albert Reinhard B\u00e4ckerei Lebensmittel",
    "wof:placetype":"venue"
},
  "geometry": {"coordinates":[8.275727,46.901375],"type":"Point"}
}