{
  "type": "Feature",
  "properties": {
    "addr:full":"Villars Sur Ollon Villars Sur Ollon Vaud 1884",
    "addr:postcode":"1884",
    "addr:street":"Villars;Villars",
    "iso:country":"CH",
    "sg:address":"Villars Sur Ollon",
    "sg:city":"Villars Sur Ollon",
    "sg:classifiers":[
        {
            "category":"Banks & Credit Unions",
            "subcategory":"Bank",
            "type":"Services"
        }
    ],
    "sg:phone":"+41 25352435",
    "sg:postcode":"1884",
    "sg:province":"Vaud",
    "wof:name":"Banque Vaudoise De Credit",
    "wof:placetype":"venue"
},
  "geometry": {"coordinates":[7.055,46.296959],"type":"Point"}
}