{
  "type": "Feature",
  "properties": {
    "iso:country":"CH",
    "sg:address":"Industriestrasse 3",
    "sg:city":"Neuheim",
    "sg:orig_category":"Bauschreinerei Herstellung von Konstruktionsteilen, Fertigbauteilen U Ausbauelementen aus Holz",
    "sg:phone":"+41 81 322 14 40",
    "sg:postcode":"6345",
    "sg:province":"Zug",
    "wof:name":"Singer Ulr. Ag",
    "wof:placetype":"venue"
},
  "geometry": {"coordinates":[9.572108,46.977253],"type":"Point"}
}