{
  "type": "Feature",
  "properties": {
    "iso:country":"CH",
    "sg:address":"Suhrgasse 6",
    "sg:city":"Oberentfelden",
    "sg:orig_category":"G\u00fcterbef\u00f6rderung im Strassenverkehr",
    "sg:postcode":"5036",
    "sg:province":"Aargau",
    "wof:name":"H. Siegrist Transporte",
    "wof:placetype":"venue"
},
  "geometry": {"coordinates":[8.0610265732,47.3556365967],"type":"Point"}
}