{
  "type": "Feature",
  "properties": {
    "iso:country":"CH",
    "sg:address":"Reitbahnstr. 31b",
    "sg:city":"Rorschach",
    "sg:orig_category":"Vermietung U Verpachtung von eigenen Immobilien",
    "sg:postcode":"9400",
    "sg:province":"St. Gallen",
    "wof:name":"M\u00fcller Fritz Immobilien Ag Rorschach",
    "wof:placetype":"venue"
},
  "geometry": {"coordinates":[9.4874258041,47.4761123657],"type":"Point"}
}