{
  "type": "Feature",
  "properties": {
    "iso:country":"CH",
    "sg:address":"Gubelstrasse 7",
    "sg:city":"Zug",
    "sg:orig_category":"Finanzierungsinstitutionen",
    "sg:phone":"+41 41 710 79 66",
    "sg:postcode":"6300",
    "sg:province":"Zug",
    "wof:name":"Mittelst\u00e4ndische Investmentberatungs Ag Vae",
    "wof:placetype":"venue"
},
  "geometry": {"coordinates":[8.5183372498,47.1742172241],"type":"Point"}
}