{
  "type": "Feature",
  "properties": {
    "iso:country":"CH",
    "sg:address":"Schorenstrasse 12",
    "sg:city":"Thun",
    "sg:orig_category":"Architekturb\u00fcros",
    "sg:phone":"+41 33 438 88 38",
    "sg:postcode":"3604",
    "sg:province":"Bern",
    "wof:name":"Ronald E. Schertenleib Architekturb\u00fcro Resa",
    "wof:placetype":"venue"
},
  "geometry": {"coordinates":[7.623467,46.737999],"type":"Point"}
}