{
  "type": "Feature",
  "properties": {
    "iso:country":"CH",
    "sg:address":"Blausee-mitholz",
    "sg:city":"Kandergrund",
    "sg:orig_category":"Interessenvertretungen",
    "sg:postcode":"3716",
    "sg:province":"Bern",
    "wof:name":"Osthilfe-stiftung Schneuwly",
    "wof:placetype":"venue"
},
  "geometry": {"coordinates":[9.3887834549,47.4398727417],"type":"Point"}
}