{
  "type": "Feature",
  "properties": {
    "iso:country":"CH",
    "sg:address":"M\u00fchlerain 3",
    "sg:city":"Meilen",
    "sg:orig_category":"Unternehmensberatung",
    "sg:phone":"+41 31 879 09 25",
    "sg:postcode":"8706",
    "sg:province":"Z\u00fcrich",
    "wof:name":"Gasser Betriebs Ag Unternehmensberatung Usw",
    "wof:placetype":"venue"
},
  "geometry": {"coordinates":[7.4305348396,47.0409164429],"type":"Point"}
}