{
  "type": "Feature",
  "properties": {
    "iso:country":"CH",
    "sg:address":"Avenue Du Grand-champsec 1",
    "sg:city":"Sion",
    "sg:orig_category":"Interessenvertretungen",
    "sg:postcode":"1950",
    "sg:province":"Valais",
    "wof:name":"Association Des Commer\u00e7anst Et Artisants De Grand Champsec",
    "wof:placetype":"venue"
},
  "geometry": {"coordinates":[7.3815898895,46.2286987305],"type":"Point"}
}