{
  "type": "Feature",
  "properties": {
    "iso:country":"CH",
    "sg:address":"Ettenriedweg 396",
    "sg:city":"Leuggern",
    "sg:orig_category":"Detailhandel mit Sportartikeln",
    "sg:phone":"+41 56 245 20 24",
    "sg:postcode":"5316",
    "sg:province":"Aargau",
    "wof:name":"Othmar B\u00e4chli B\u00e4chli's Ski-keller",
    "wof:placetype":"venue"
},
  "geometry": {"coordinates":[8.2245998383,47.5858306885],"type":"Point"}
}