{
  "type": "Feature",
  "properties": {
    "iso:country":"CH",
    "sg:address":"St. Urbanstrasse 6",
    "sg:city":"Langenthal",
    "sg:orig_category":"Detailhandel mit Uhren U Schmuck Fachdetailhandel in Verkaufsr\u00e4umen",
    "sg:phone":"+41 62 922 05 30",
    "sg:postcode":"4900",
    "sg:province":"Bern",
    "wof:name":"Preiss Uhren-bijouterie",
    "wof:placetype":"venue"
},
  "geometry": {"coordinates":[7.7902889252,47.2119445801],"type":"Point"}
}