{
  "type": "Feature",
  "properties": {
    "iso:country":"CH",
    "sg:address":"In Der Au 5 8406 Winterthur. Postfach",
    "sg:city":"Winterthur",
    "sg:orig_category":"Energieversorgung Herstellung von Elektromotoren, Generatoren U Transformatoren",
    "sg:phone":"+41 52 269 11 69",
    "sg:postcode":"8406",
    "sg:province":"Z\u00fcrich",
    "wof:name":"Escort Energietechnik Ag Handels- U. Beratungsunternehmen Im Bereich Energietechnik",
    "wof:placetype":"venue"
},
  "geometry": {"coordinates":[8.7040605545,47.4852676392],"type":"Point"}
}