{
  "type": "Feature",
  "properties": {
    "iso:country":"CH",
    "sg:address":"Untere M\u00fchle",
    "sg:city":"Bottighofen",
    "sg:orig_category":"Unclassifiable Establishments",
    "sg:postcode":"8598",
    "sg:province":"Thurgau",
    "wof:name":"Umb Holding Ag",
    "wof:placetype":"venue"
},
  "geometry": {"coordinates":[9.2052230835,47.6354141235],"type":"Point"}
}