{
  "type": "Feature",
  "properties": {
    "addr:full":"Bachtelstrasse 25 Winterthur Z\u00fcrich 8400",
    "addr:housenumber":"25",
    "addr:postcode":"8400",
    "addr:street":"Bachtelstrasse",
    "iso:country":"CH",
    "sg:address":"Bachtelstrasse 25",
    "sg:city":"Winterthur",
    "sg:orig_category":"Chemische Reinigung",
    "sg:phone":"+41 52 213 26 38",
    "sg:postcode":"8400",
    "sg:province":"Z\u00fcrich",
    "wof:name":"Athanase Christakis Chemische Reinigung Rex",
    "wof:placetype":"venue"
},
  "geometry": {"coordinates":[8.72091,47.50927],"type":"Point"}
}