{
  "type": "Feature",
  "properties": {
    "iso:country":"CH",
    "sg:address":"Rheinstrasse 9",
    "sg:city":"Landquart",
    "sg:orig_category":"Detailhandel mit Zeitungen U Zeitschriften Kioske",
    "sg:phone":"+41 81 322 21 30",
    "sg:postcode":"7302",
    "sg:province":"Graubunden",
    "wof:name":"Christian Br\u00fcgger Kiosk",
    "wof:placetype":"venue"
},
  "geometry": {"coordinates":[9.5589447021,46.9618339539],"type":"Point"}
}