{
  "type": "Feature",
  "properties": {
    "iso:country":"CH",
    "sg:address":"Ebnaterstrasse 5",
    "sg:city":"Wattwil",
    "sg:orig_category":"Pensionskassen",
    "sg:phone":"+41 71 988 26 61",
    "sg:postcode":"9630",
    "sg:province":"St. Gallen",
    "wof:name":"Wohlfahrtsfonds Der Genossenschaft Schweizerische Textil, Bekleidungs Und Modefachschule",
    "wof:placetype":"venue"
},
  "geometry": {"coordinates":[9.0889816284,47.3027229309],"type":"Point"}
}