{
  "type": "Feature",
  "properties": {
    "iso:country":"CH",
    "sg:address":"Hauptstrasse",
    "sg:city":"Susch",
    "sg:orig_category":"RESTAURANTS: TEA-ROOMS",
    "sg:postcode":"7542",
    "sg:province":"Graubunden",
    "wof:name":"Restorant Crusch Alba, Ursina Gapp-caprez",
    "wof:placetype":"venue"
},
  "geometry": {"coordinates":[10.0803976059,46.7506256104],"type":"Point"}
}