{
  "type": "Feature",
  "properties": {
    "iso:country":"CH",
    "sg:address":"Avenue Du Midi 10 1950 Sion Case Postale 612",
    "sg:city":"Sion",
    "sg:orig_category":"Versicherungen Generalagenturen",
    "sg:phone":"+41 27 322 88 46",
    "sg:postcode":"1951",
    "sg:province":"Valais",
    "wof:name":"St\u00e9 D'assur. Mobili\u00e8re Suisse Agence G\u00e9n\u00e9rale",
    "wof:placetype":"venue"
},
  "geometry": {"coordinates":[7.3591470718,46.2307052612],"type":"Point"}
}