{
  "type": "Feature",
  "properties": {
    "iso:country":"CH",
    "sg:address":"Rainstr. 12",
    "sg:city":"St\u00e4fa",
    "sg:classifiers":[
        {
            "category":"Utilities",
            "subcategory":"Cable",
            "type":"Services"
        }
    ],
    "sg:phone":"+41 4119262084",
    "sg:postcode":"8712",
    "sg:province":"Z\u00fcrich",
    "sg:tags":[
        "tv",
        "medien",
        "u",
        "radio"
    ],
    "wof:name":"Aurora Verlag St\u00e4fa",
    "wof:placetype":"venue"
},
  "geometry": {"coordinates":[8.721015,47.244068],"type":"Point"}
}