{
  "type": "Feature",
  "properties": {
    "iso:country":"CH",
    "sg:address":"Praz-s\u00e9chaud Chemin De 28",
    "sg:city":"Lausanne",
    "sg:orig_category":"Unclassifiable Establishments",
    "sg:postcode":"1010",
    "sg:province":"Vaud",
    "wof:name":"David Andrade",
    "wof:placetype":"venue"
},
  "geometry": {"coordinates":[6.6654877663,46.5392723083],"type":"Point"}
}