{
  "type": "Feature",
  "properties": {
    "iso:country":"CH",
    "sg:address":"Zementweg 8",
    "sg:city":"Olten",
    "sg:orig_category":"Installation von Heizungs, L\u00fcftungs U Klimaanlagen",
    "sg:phone":"+41 62 205 80 80",
    "sg:postcode":"4600",
    "sg:province":"Solothurn",
    "wof:name":"Riggenbach Ag, L\u00fcftungs Und Klimatechnik",
    "wof:placetype":"venue"
},
  "geometry": {"coordinates":[7.9040288925,47.3521194458],"type":"Point"}
}