{
  "type": "Feature",
  "properties": {
    "iso:country":"CH",
    "sg:address":"Schauenburgerstrasse 15 4402 Frenkendorf. Postfach 341",
    "sg:city":"Frenkendorf",
    "sg:orig_category":"Mit dem Versicherungsgewerbe verbundene T\u00e4tigkeiten",
    "sg:phone":"+41 61 903 02 30",
    "sg:postcode":"4402",
    "sg:province":"Basel-Landschaft",
    "wof:name":"Optimal Versicherungstreuhand Versicherung Vorsorge Finanzplanung Weisshaar Lukas",
    "wof:placetype":"venue"
},
  "geometry": {"coordinates":[7.7128801346,47.5023422241],"type":"Point"}
}