{
  "type": "Feature",
  "properties": {
    "iso:country":"CH",
    "sg:address":"Les Crosets",
    "sg:city":"Val-d'illiez",
    "sg:orig_category":"Verwaltung von Immobilien",
    "sg:postcode":"1873",
    "sg:province":"Valais",
    "wof:name":"Aedes Ag St. Gallen",
    "wof:placetype":"venue"
},
  "geometry": {"coordinates":[9.3852109909,47.4388961792],"type":"Point"}
}