{
  "type": "Feature",
  "properties": {
    "iso:country":"CH",
    "sg:address":"Route Belved\u00e8re 8",
    "sg:city":"Villars-sur-gl\u00e2ne",
    "sg:orig_category":"Sportvereine Ballsport Tennis",
    "sg:phone":"+41 79 301 17 25",
    "sg:postcode":"1752",
    "sg:province":"Fribourg",
    "wof:name":"Tc Aiglon",
    "wof:placetype":"venue"
},
  "geometry": {"coordinates":[7.1331019402,46.800403595],"type":"Point"}
}