{
  "type": "Feature",
  "properties": {
    "iso:country":"CH",
    "sg:address":"Wisentalstrasse 9 8634 Hombrechtikon. Postfach",
    "sg:city":"St\u00e4fa",
    "sg:orig_category":"Sportvereine Ballsport Fussball",
    "sg:postcode":"8712",
    "sg:province":"Z\u00fcrich",
    "wof:name":"Fc St\u00e4fa",
    "wof:placetype":"venue"
},
  "geometry": {"coordinates":[8.7669401169,47.2505340576],"type":"Point"}
}