{
  "type": "Feature",
  "properties": {
    "iso:country":"CH",
    "sg:address":"Luzernerstr. 15",
    "sg:city":"Hildisrieden",
    "sg:orig_category":"Herstellung von Konstruktionsteilen, Fertigbauteilen U Ausbauelementen aus Holz",
    "sg:postcode":"6024",
    "sg:province":"Luzern",
    "wof:name":"M\u00fcller, Franz",
    "wof:placetype":"venue"
},
  "geometry": {"coordinates":[7.9620099068,47.1195907593],"type":"Point"}
}