{
  "type": "Feature",
  "properties": {
    "iso:country":"CH",
    "sg:address":"Gourgas Rue 12",
    "sg:city":"Gen\u00e8ve",
    "sg:orig_category":"Non-Classified Establishments",
    "sg:postcode":"1205",
    "sg:province":"Gen\u00e8ve",
    "wof:name":"Sporthilfe Schweiz Ag",
    "wof:placetype":"venue"
},
  "geometry": {"coordinates":[6.1382431984,46.1995124817],"type":"Point"}
}