{
  "type": "Feature",
  "properties": {
    "iso:country":"CH",
    "sg:address":"Les Grandes Vernes",
    "sg:city":"Boudevilliers",
    "sg:orig_category":"Allgemeiner Hoch U Tiefbau",
    "sg:phone":"+41 32 857 10 94",
    "sg:postcode":"2043",
    "sg:province":"Neuch\u00e2tel",
    "wof:name":"Ctm Aquaterra Sa",
    "wof:placetype":"venue"
},
  "geometry": {"coordinates":[6.858544,47.026886],"type":"Point"}
}