{
  "type": "Feature",
  "properties": {
    "iso:country":"CH",
    "sg:address":"1035",
    "sg:city":"Bournens",
    "sg:orig_category":"RESTAURANTS: TEA-ROOMS",
    "sg:postcode":"1035",
    "sg:province":"Vaud",
    "wof:name":"Nieto-porchet A.",
    "wof:placetype":"venue"
},
  "geometry": {"coordinates":[6.5645799637,46.6088981628],"type":"Point"}
}