{
  "type": "Feature",
  "properties": {
    "iso:country":"CH",
    "sg:address":"Artherstrasse 60",
    "sg:city":"Immensee",
    "sg:classifiers":[
        {
            "category":"Coffee & Tea",
            "type":"Food & Drink"
        }
    ],
    "sg:phone":"+41 41 854 46 00",
    "sg:postcode":"6405",
    "sg:province":"Schwyz",
    "sg:tags":[
        "apple"
    ],
    "wof:name":"Dr. D\u00fcnner Ag",
    "wof:placetype":"venue"
},
  "geometry": {"coordinates":[8.4588,47.09325],"type":"Point"}
}