{
  "type": "Feature",
  "properties": {
    "iso:country":"CH",
    "sg:address":"Pilatusstrasse 34",
    "sg:city":"Sursee",
    "sg:classifiers":[
        {
            "category":"Professional",
            "subcategory":"Advertising",
            "type":"Services"
        }
    ],
    "sg:phone":"+41 41 921 10 38",
    "sg:postcode":"6210",
    "sg:province":"Luzern",
    "sg:tags":[
        "candle"
    ],
    "wof:name":"Herzog Kerzen Ag",
    "wof:placetype":"venue"
},
  "geometry": {"coordinates":[8.098864,47.169079],"type":"Point"}
}