{
  "type": "Feature",
  "properties": {
    "addr:full":"Gerusalemme Via 10a 6614 Brissago. Postfach Brissago Ticino 6614",
    "addr:housenumber":"10a",
    "addr:postcode":"6614 brissago. postfach;6614",
    "addr:street":"Via",
    "iso:country":"CH",
    "sg:address":"Gerusalemme Via 10a 6614 Brissago. Postfach",
    "sg:city":"Brissago",
    "sg:orig_category":"Architektur U Ingenieurb\u00fcros",
    "sg:postcode":"6614",
    "sg:province":"Ticino",
    "wof:name":"Eta Electronic Design Sagl Progetti Nel Campo D. Tecnologia Elettronica; Realizzazione, Sviluppo",
    "wof:placetype":"venue"
},
  "geometry": {"coordinates":[8.710389,46.119759],"type":"Point"}
}