{
  "type": "Feature",
  "properties": {
    "iso:country":"CH",
    "sg:address":"Grabenstrasse 8",
    "sg:city":"Schwerzenbach",
    "sg:orig_category":"Dienstleistungen von Beteiligungsgesellschaften",
    "sg:postcode":"8603",
    "sg:province":"Z\u00fcrich",
    "wof:name":"Vewa Verwaltungs Ag",
    "wof:placetype":"venue"
},
  "geometry": {"coordinates":[8.8520793915,47.2602500916],"type":"Point"}
}