{
  "type": "Feature",
  "properties": {
    "iso:country":"CH",
    "sg:address":"Sch\u00fctzenstrasse 8",
    "sg:city":"Herisau",
    "sg:orig_category":"Non-Classified Establishments",
    "sg:postcode":"9100",
    "sg:province":"Appenzell Ausserrhoden",
    "wof:name":"Wordwright - Laurence Matson",
    "wof:placetype":"venue"
},
  "geometry": {"coordinates":[9.2817239761,47.3891868591],"type":"Point"}
}