{
  "type": "Feature",
  "properties": {
    "iso:country":"CH",
    "sg:address":"Spiegelbergstrasse 2",
    "sg:city":"Walchwil",
    "sg:orig_category":"Vermietung U Verpachtung von eigenen Immobilien",
    "sg:postcode":"6318",
    "sg:province":"Zug",
    "wof:name":"Hans + Ueli B\u00fcrgler Immobilien Gmbh",
    "wof:placetype":"venue"
},
  "geometry": {"coordinates":[8.5182447433,47.0993804932],"type":"Point"}
}