{
  "type": "Feature",
  "properties": {
    "iso:country":"CH",
    "sg:address":"Chemin Du Parc De Valency 19 1000 Lausanne. Postfach",
    "sg:city":"Lausanne",
    "sg:orig_category":"Non-Classified Establishments",
    "sg:postcode":"1000",
    "sg:province":"Vaud",
    "wof:name":"Phytotherapie Verband Schweiz",
    "wof:placetype":"venue"
},
  "geometry": {"coordinates":[8.7927894592,47.361541748],"type":"Point"}
}