{
  "type": "Feature",
  "properties": {
    "iso:country":"CH",
    "sg:address":"Rue Marterey 5 1005 Lausanne Case Postale 2585",
    "sg:city":"Lausanne",
    "sg:orig_category":"Detektivb\u00fcros U \u00dcberwachung",
    "sg:phone":"+41 21 312 41 22",
    "sg:postcode":"1002",
    "sg:province":"Vaud",
    "wof:name":"Agence Duport S\u00e0rl",
    "wof:placetype":"venue"
},
  "geometry": {"coordinates":[6.6379141808,46.5203781128],"type":"Point"}
}