{
  "type": "Feature",
  "properties": {
    "iso:country":"CH",
    "sg:address":"Unter Br\u00fcglingen 5",
    "sg:city":"Basel",
    "sg:orig_category":"Gem\u00fcsebau Obstbau",
    "sg:phone":"+41 61 311 76 10",
    "sg:postcode":"4052",
    "sg:province":"Basel-Stadt",
    "wof:name":"Br\u00fcglingerhof Bio-gem\u00fcse Obst & Beeren",
    "wof:placetype":"venue"
},
  "geometry": {"coordinates":[7.6178121567,47.5404548645],"type":"Point"}
}