{
  "type": "Feature",
  "properties": {
    "iso:country":"CH",
    "sg:address":"Liotard Rue 5 1202 Gen\u00e8ve. Postfach",
    "sg:city":"Gen\u00e8ve",
    "sg:orig_category":"Architektur U Ingenieurb\u00fcros",
    "sg:phone":"+41 22 344 74 40",
    "sg:postcode":"1201",
    "sg:province":"Gen\u00e8ve",
    "wof:name":"G. Vaterlaus Sa",
    "wof:placetype":"venue"
},
  "geometry": {"coordinates":[6.134333,46.20929],"type":"Point"}
}