{
  "type": "Feature",
  "properties": {
    "iso:country":"CH",
    "sg:address":"M\u00fchlerainstrasse 21 4414 F\u00fcllinsdorf. Postfach",
    "sg:city":"F\u00fcllinsdorf",
    "sg:orig_category":"RESTAURANTS: TEA-ROOMS",
    "sg:postcode":"4414",
    "sg:province":"Basel-Landschaft",
    "wof:name":"Restaurant Pizzeria Soleil, Gandoy Echeverria-memaj & Kayis-memaj",
    "wof:placetype":"venue"
},
  "geometry": {"coordinates":[6.8230400085,47.0984153748],"type":"Point"}
}