{
  "type": "Feature",
  "properties": {
    "iso:country":"CH",
    "sg:address":"Ferdinand Holder-strasse 42",
    "sg:city":"Z\u00fcrich",
    "sg:orig_category":"Reiseb\u00fcros U Reiseveranstalter",
    "sg:phone":"+41 22 301 01 04",
    "sg:postcode":"8049",
    "sg:province":"Z\u00fcrich",
    "wof:name":"Look Voyage, Palfi",
    "wof:placetype":"venue"
},
  "geometry": {"coordinates":[6.1407580376,46.1815872192],"type":"Point"}
}