{
  "type": "Feature",
  "properties": {
    "iso:country":"CH",
    "sg:address":"Weidstrasse 11 6343 Rotkreuz. Postfach",
    "sg:city":"Rotkreuz",
    "sg:orig_category":"Detailhandel mit M\u00f6beln U Haushaltsgegenst\u00e4nden",
    "sg:postcode":"6343",
    "sg:province":"Zug",
    "wof:name":"Vd Wohndesign Gmbh Waren, Bes. M\u00f6bel; Handel. Beratungen Usw",
    "wof:placetype":"venue"
},
  "geometry": {"coordinates":[8.4297609329,47.135887146],"type":"Point"}
}