{
  "type": "Feature",
  "properties": {
    "iso:country":"CH",
    "sg:address":"3780",
    "sg:city":"Gstaad",
    "sg:orig_category":"Organisationen des Gesundheitswesen",
    "sg:phone":"+41 81 332 10 55",
    "sg:postcode":"3780",
    "sg:province":"Bern",
    "wof:name":"Samariterverein Saas",
    "wof:placetype":"venue"
},
  "geometry": {"coordinates":[9.8068876266,46.9113845825],"type":"Point"}
}