{
  "type": "Feature",
  "properties": {
    "iso:country":"CH",
    "sg:address":"Hasenbergstrasse 8",
    "sg:city":"Bellikon",
    "sg:orig_category":"Bauspenglerei Dachdeckerei",
    "sg:phone":"+41 56 496 61 39",
    "sg:postcode":"5454",
    "sg:province":"Aargau",
    "wof:name":"Hans Benninger Bedachungen & Spenglerei",
    "wof:placetype":"venue"
},
  "geometry": {"coordinates":[8.345772,47.388264],"type":"Point"}
}