{
  "type": "Feature",
  "properties": {
    "iso:country":"CH",
    "sg:address":"Verbier 1936 Verbier. Postfach",
    "sg:city":"Verbier",
    "sg:orig_category":"Herstellung von Konstruktionsteilen, Fertigbauteilen U Ausbauelementen aus Holz",
    "sg:phone":"+41 27 771 21 27",
    "sg:postcode":"1936",
    "sg:province":"Valais",
    "wof:name":"Corthay Bois Sa",
    "wof:placetype":"venue"
},
  "geometry": {"coordinates":[7.2192759514,46.0961456299],"type":"Point"}
}