{
  "type": "Feature",
  "properties": {
    "iso:country":"CH",
    "sg:address":"Kurlistrasse 25",
    "sg:city":"Winterthur",
    "sg:orig_category":"Sonstiger Grosshandel",
    "sg:postcode":"8400",
    "sg:province":"Z\u00fcrich",
    "wof:name":"Kars Ag",
    "wof:placetype":"venue"
},
  "geometry": {"coordinates":[8.7462930679,47.504650116],"type":"Point"}
}