{
  "type": "Feature",
  "properties": {
    "iso:country":"CH",
    "sg:address":"Kantonsstrasse 5",
    "sg:city":"Eischoll",
    "sg:orig_category":"Fahrschulen, Flugschulen",
    "sg:phone":"+41 27 934 16 06",
    "sg:postcode":"3943",
    "sg:province":"Valais",
    "wof:name":"Amacker Christoph Autofahrschule.",
    "wof:placetype":"venue"
},
  "geometry": {"coordinates":[7.783703804,46.2932777405],"type":"Point"}
}