{
  "type": "Feature",
  "properties": {
    "iso:country":"CH",
    "sg:address":"Schaffhauserstrasse 126",
    "sg:city":"Z\u00fcrich",
    "sg:orig_category":"Einzelhandel mit Automobilteilen U Zubeh\u00f6r Handel mit Automobilteilen U Zubeh\u00f6r",
    "sg:phone":"+41 55 246 28 94",
    "sg:postcode":"8057",
    "sg:province":"Z\u00fcrich",
    "wof:name":"Chemuwa Autozubeh\u00f6r Ag Autoshop",
    "wof:placetype":"venue"
},
  "geometry": {"coordinates":[8.9390354156,47.2693862915],"type":"Point"}
}