{
  "type": "Feature",
  "properties": {
    "iso:country":"CH",
    "sg:address":"Kalchb\u00fchlstrasse 40",
    "sg:city":"Chur",
    "sg:orig_category":"Herstellung von Hebezeugen U F\u00f6rdermitteln",
    "sg:phone":"+41 848 821 821",
    "sg:postcode":"7000",
    "sg:province":"Graubunden",
    "wof:name":"Schindler Aufz\u00fcge Ag",
    "wof:placetype":"venue"
},
  "geometry": {"coordinates":[9.5068750381,46.8466873169],"type":"Point"}
}