{
  "type": "Feature",
  "properties": {
    "iso:country":"CH",
    "sg:address":"Ackerstrasse 21 8005 Z\u00fcrich. Postfach",
    "sg:city":"Z\u00fcrich",
    "sg:orig_category":"Grosshandel mit Getr\u00e4nken",
    "sg:phone":"+41 12716565",
    "sg:postcode":"8001",
    "sg:province":"Z\u00fcrich",
    "wof:name":"Vinimport Zanini Sa Alkoholische Getr\u00e4nke, Insbes. Import V. Weinen.",
    "wof:placetype":"venue"
},
  "geometry": {"coordinates":[8.5314617157,47.3823928833],"type":"Point"}
}