{
  "type": "Feature",
  "properties": {
    "iso:country":"CH",
    "sg:address":"Rue Des Uttins 30",
    "sg:city":"Yverdon-les-bains",
    "sg:orig_category":"Non-Classified Establishments",
    "sg:phone":"+41 24 445 82 42",
    "sg:postcode":"1400",
    "sg:province":"Vaud",
    "wof:name":"Cogeba Sa",
    "wof:placetype":"venue"
},
  "geometry": {"coordinates":[6.6259069443,46.7845344543],"type":"Point"}
}