{
  "type": "Feature",
  "properties": {
    "addr:full":"T\u00fcbacherstrasse 25 9403 Goldach. Postfach 184 Goldach St. Gallen 9403",
    "addr:housenumber":"25;184",
    "addr:postcode":"9403 goldach.;9403",
    "addr:street":"Tuebacherstrasse;Postfach",
    "iso:country":"CH",
    "sg:address":"T\u00fcbacherstrasse 25 9403 Goldach. Postfach 184",
    "sg:city":"Goldach",
    "sg:orig_category":"Architektur U Ingenieurb\u00fcros",
    "sg:phone":"+41 71 844 69 69",
    "sg:postcode":"9403",
    "sg:province":"St. Gallen",
    "wof:name":"Enerop Ag, Beratende Ingenieure F\u00fcr Energietechnik, Heizung, L\u00fcftung, Klima Und K\u00e4lte",
    "wof:placetype":"venue"
},
  "geometry": {"coordinates":[9.466559,47.479961],"type":"Point"}
}