{
  "type": "Feature",
  "properties": {
    "iso:country":"CH",
    "sg:address":"Zona Vala",
    "sg:city":"Contone",
    "sg:orig_category":"G\u00fcterbef\u00f6rderung im Strassenverkehr",
    "sg:phone":"+41 91 858 30 60",
    "sg:postcode":"6594",
    "sg:province":"Ticino",
    "wof:name":"Antonia De Girolamo Trasporti",
    "wof:placetype":"venue"
},
  "geometry": {"coordinates":[8.9326944351,46.1497192383],"type":"Point"}
}