{
  "type": "Feature",
  "properties": {
    "iso:country":"CH",
    "sg:address":"La Coie",
    "sg:city":"Vendlincourt",
    "sg:orig_category":"Sanit\u00e4r U Heizungsinstallation Sanit\u00e4rinstallation",
    "sg:phone":"+41 32 474 44 74",
    "sg:postcode":"2943",
    "sg:province":"Jura",
    "wof:name":"Siess Sa Inst. Chauff. Sanitaire",
    "wof:placetype":"venue"
},
  "geometry": {"coordinates":[7.1528730392,47.4505996704],"type":"Point"}
}