{
  "type": "Feature",
  "properties": {
    "iso:country":"CH",
    "sg:address":"Route De Chandoline 2",
    "sg:city":"Sion",
    "sg:orig_category":"Handel mit Automobilen",
    "sg:phone":"+41 79 290 62 91",
    "sg:postcode":"1950",
    "sg:province":"Valais",
    "wof:name":"Carrosserie Eichb\u00fchl Ag",
    "wof:placetype":"venue"
},
  "geometry": {"coordinates":[8.7254400253,47.273815155],"type":"Point"}
}