{
  "type": "Feature",
  "properties": {
    "iso:country":"CH",
    "sg:address":"Rue De L'industrie 2 1632 Riaz. Postfach",
    "sg:city":"Riaz",
    "sg:orig_category":"Bauschreinerei Herstellung von M\u00f6beln verschiedener Art",
    "sg:phone":"+41 79 325 85 38",
    "sg:postcode":"1632",
    "sg:province":"Fribourg",
    "wof:name":"Marcel Oberson & Fils Menuiserie & \u00e9b\u00e9nisterie",
    "wof:placetype":"venue"
},
  "geometry": {"coordinates":[7.068145,46.642944],"type":"Point"}
}