{
  "type": "Feature",
  "properties": {
    "iso:country":"CH",
    "sg:address":"Chiesey",
    "sg:city":"Troistorrents",
    "sg:orig_category":"Grosshandel mit sonstigen Gebrauchs U Verbrauchsg\u00fctern",
    "sg:postcode":"1872",
    "sg:province":"Valais",
    "wof:name":"Leprat Jean-no\u00ebl",
    "wof:placetype":"venue"
},
  "geometry": {"coordinates":[6.906829834,46.2229804993],"type":"Point"}
}