{
  "type": "Feature",
  "properties": {
    "iso:country":"CH",
    "sg:address":"Rue De Lausanne 91",
    "sg:city":"Fribourg",
    "sg:orig_category":"Psychotherapie",
    "sg:postcode":"1700",
    "sg:province":"Fribourg",
    "wof:name":"Fran\u00e7oise Zurich Psychoth\u00e9rapie",
    "wof:placetype":"venue"
},
  "geometry": {"coordinates":[7.1565489769,46.8052177429],"type":"Point"}
}