{
  "type": "Feature",
  "properties": {
    "iso:country":"CH",
    "sg:address":"Riedweg 8",
    "sg:city":"Jegenstorf",
    "sg:orig_category":"Detailhandel mit Fahrr\u00e4dern Handel mit Motorr\u00e4dern, Teilen U Zubeh\u00f6r Instandhaltung U Reparatur von ",
    "sg:phone":"+41 79 415 79 48",
    "sg:postcode":"3303",
    "sg:province":"Bern",
    "wof:name":"Thomas Burn Velos-motos Rasenm\u00e4her",
    "wof:placetype":"venue"
},
  "geometry": {"coordinates":[7.5118699074,47.0522689819],"type":"Point"}
}