{
  "type": "Feature",
  "properties": {
    "iso:country":"CH",
    "sg:address":"Chemin Des Ormeaux 20",
    "sg:city":"Epalinges",
    "sg:orig_category":"Allgemeiner Hoch U Tiefbau Allgemeiner Hochbau",
    "sg:phone":"+41 21 635 40 35",
    "sg:postcode":"1066",
    "sg:province":"Vaud",
    "wof:name":"Witschi Guillaume Sa, Succursale D'epalinges",
    "wof:placetype":"venue"
},
  "geometry": {"coordinates":[6.653379,46.544601],"type":"Point"}
}