{
  "type": "Feature",
  "properties": {
    "iso:country":"CH",
    "sg:address":"Bahnhofstrasse 30",
    "sg:city":"Zug",
    "sg:classifiers":[
        {
            "category":"Personal",
            "subcategory":"Nail Salon",
            "type":"Services"
        }
    ],
    "sg:phone":"+41 41 727 76 26",
    "sg:postcode":"6300",
    "sg:province":"Zug",
    "sg:tags":[
        "manicure"
    ],
    "wof:name":"Royal Nails Ag",
    "wof:placetype":"venue"
},
  "geometry": {"coordinates":[8.5160140991,47.1702613831],"type":"Point"}
}