{
  "type": "Feature",
  "properties": {
    "iso:country":"CH",
    "sg:address":"Freiestrasse 4",
    "sg:city":"Uster",
    "sg:orig_category":"Versicherungen Generalagenturen",
    "sg:phone":"+41 19407030",
    "sg:postcode":"8610",
    "sg:province":"Z\u00fcrich",
    "wof:name":"La Suisse Versicherungen Generalagentur Zh-oberland",
    "wof:placetype":"venue"
},
  "geometry": {"coordinates":[8.7196760178,47.3492012024],"type":"Point"}
}