{
  "type": "Feature",
  "properties": {
    "iso:country":"CH",
    "sg:address":"Varenna Via Bartolomeo 70 6600 Locarno. Postfach",
    "sg:city":"Solduno",
    "sg:orig_category":"Detailhandel mit B\u00fcchern, Zeitungen, Schreib U Papeteriewaren",
    "sg:postcode":"6604",
    "sg:province":"Ticino",
    "wof:name":"Zenta Sagl",
    "wof:placetype":"venue"
},
  "geometry": {"coordinates":[8.789811,46.167992],"type":"Point"}
}