{
  "type": "Feature",
  "properties": {
    "iso:country":"CH",
    "sg:address":"Hinterburgstrasse 46",
    "sg:city":"Neuheim",
    "sg:orig_category":"Non-Classified Establishments",
    "sg:postcode":"6345",
    "sg:province":"Zug",
    "wof:name":"4solutions Gmbh",
    "wof:placetype":"venue"
},
  "geometry": {"coordinates":[8.5717935562,47.1957092285],"type":"Point"}
}