{
  "type": "Feature",
  "properties": {
    "iso:country":"CH",
    "sg:address":"Hauptstrasse 10",
    "sg:city":"Binningen",
    "sg:orig_category":"Detailhandel mit Teppichen",
    "sg:phone":"+41 61 421 37 91",
    "sg:postcode":"4102",
    "sg:province":"Basel-Landschaft",
    "wof:name":"Boutique Illusion",
    "wof:placetype":"venue"
},
  "geometry": {"coordinates":[7.5750169754,47.5431900024],"type":"Point"}
}