{
  "type": "Feature",
  "properties": {
    "iso:country":"CH",
    "sg:address":"Rotackerstrasse 32 8304 Wallisellen. Postfach",
    "sg:city":"Wallisellen",
    "sg:orig_category":"Unclassifiable Establishments",
    "sg:postcode":"8304",
    "sg:province":"Z\u00fcrich",
    "wof:name":"A Bis Z Transporte Und Reinigungen Gmbh",
    "wof:placetype":"venue"
},
  "geometry": {"coordinates":[8.5046052933,47.4774971008],"type":"Point"}
}