{
  "type": "Feature",
  "properties": {
    "iso:country":"CH",
    "sg:address":"Germaniastrasse 15",
    "sg:city":"Z\u00fcrich",
    "sg:orig_category":"Bauingenieurb\u00fcros Hochbau Bauingenieurb\u00fcros allgemein",
    "sg:phone":"+41 13619610",
    "sg:postcode":"8006",
    "sg:province":"Z\u00fcrich",
    "wof:name":"Rolf Siegenthaler Ingenieurb\u00fcro",
    "wof:placetype":"venue"
},
  "geometry": {"coordinates":[8.551761,47.390938],"type":"Point"}
}