{
  "type": "Feature",
  "properties": {
    "iso:country":"CH",
    "sg:address":"Rue Du Midi 8",
    "sg:city":"Couvet",
    "sg:orig_category":"Grosshandel mit Getr\u00e4nken",
    "sg:phone":"+41 32 863 22 20",
    "sg:postcode":"2108",
    "sg:province":"Neuch\u00e2tel",
    "wof:name":"Raineri D. Sa",
    "wof:placetype":"venue"
},
  "geometry": {"coordinates":[6.637357235,46.9236869812],"type":"Point"}
}