{
  "type": "Feature",
  "properties": {
    "iso:country":"CH",
    "sg:address":"Alte Landstrasse 33",
    "sg:city":"Islikon",
    "sg:orig_category":"Chemin\u00e9e- and Ofenbau",
    "sg:phone":"+41 52 375 14 20",
    "sg:postcode":"8546",
    "sg:province":"Thurgau",
    "wof:name":"Claudio & Astrid Sasso Ofen-& Chemin\u00e9ebau",
    "wof:placetype":"venue"
},
  "geometry": {"coordinates":[8.845811,47.548317],"type":"Point"}
}