{
  "type": "Feature",
  "properties": {
    "iso:country":"CH",
    "sg:address":"Hauptstrasse 94",
    "sg:city":"Rorschach",
    "sg:orig_category":"Detailhandel mit Schuhen Reparatur von Schuhen U Lederwaren",
    "sg:phone":"+41 71 841 09 21",
    "sg:postcode":"9400",
    "sg:province":"St. Gallen",
    "wof:name":"Carmelo Chinzi",
    "wof:placetype":"venue"
},
  "geometry": {"coordinates":[9.4896650314,47.4790496826],"type":"Point"}
}