{
  "type": "Feature",
  "properties": {
    "iso:country":"CH",
    "sg:address":"Lottenweg 18",
    "sg:city":"Muhen",
    "sg:orig_category":"Wirtschaftspr\u00fcfung, Steuerberatung U Treuhand",
    "sg:phone":"+423 373 12 53",
    "sg:postcode":"5037",
    "sg:province":"Aargau",
    "wof:name":"Intromex Treuhandb\u00fcro",
    "wof:placetype":"venue"
},
  "geometry": {"coordinates":[9.5463590622,47.2173690796],"type":"Point"}
}