{
  "type": "Feature",
  "properties": {
    "iso:country":"CH",
    "sg:address":"Epagny 1663 Gruy\u00e8res. Postfach",
    "sg:city":"Epagny",
    "sg:orig_category":"G\u00fcterbef\u00f6rderung im Strassenverkehr",
    "sg:postcode":"1664",
    "wof:name":"Aellen Max",
    "wof:placetype":"venue"
},
  "geometry": {"coordinates":[7.0843801498,46.5889816284],"type":"Point"}
}