{
  "type": "Feature",
  "properties": {
    "iso:country":"CH",
    "sg:address":"Wylerau 1a",
    "sg:city":"Diemtigen",
    "sg:orig_category":"Herstellung von Frucht U Gem\u00fcses\u00e4ften Herstellung von Obst U Fruchtweinen",
    "sg:phone":"+41 79 356 06 74",
    "sg:postcode":"3754",
    "sg:province":"Bern",
    "wof:name":"Fritz St\u00e4hli Brennerei & Mosterei",
    "wof:placetype":"venue"
},
  "geometry": {"coordinates":[7.5734171867,46.658706665],"type":"Point"}
}