{
  "type": "Feature",
  "properties": {
    "iso:country":"CH",
    "sg:address":"Kantonsstrasse 56 8807 Freienbach. Postfach",
    "sg:city":"Adliswil",
    "sg:orig_category":"Sonstige mit der Informatik verbundene T\u00e4tigkeiten",
    "sg:phone":"+41 17092911",
    "sg:postcode":"8134",
    "sg:province":"Z\u00fcrich",
    "wof:name":"Dls It Systems Gmbh Dienstleistungen Im Informatik, Beratungs Und Schulungsbereich",
    "wof:placetype":"venue"
},
  "geometry": {"coordinates":[8.7526903152,47.2068099976],"type":"Point"}
}