{
  "type": "Feature",
  "properties": {
    "iso:country":"CH",
    "sg:address":"1978",
    "sg:city":"Lens",
    "sg:classifiers":[
        {
            "category":"Insurance",
            "subcategory":"Insurance Agent",
            "type":"Services"
        }
    ],
    "sg:phone":"+41 27 483 21 20",
    "sg:postcode":"1978",
    "sg:province":"Valais",
    "sg:tags":[
        "versicherungsagenturen",
        "-broker"
    ],
    "wof:name":"Jean-marc B\u00e9trisey Conseils En Assurances",
    "wof:placetype":"venue"
},
  "geometry": {"coordinates":[7.4485402107,46.2786102295],"type":"Point"}
}