{
  "type": "Feature",
  "properties": {
    "iso:country":"CH",
    "sg:address":"Le Chanet",
    "sg:city":"Bevaix",
    "sg:orig_category":"Allgemeiner Gartenbau",
    "sg:phone":"+41 32 846 32 20",
    "sg:postcode":"2022",
    "sg:province":"Neuch\u00e2tel",
    "wof:name":"P\u00e9pini\u00e8re Cantonale",
    "wof:placetype":"venue"
},
  "geometry": {"coordinates":[6.815225,46.930077],"type":"Point"}
}