{
  "type": "Feature",
  "properties": {
    "iso:country":"CH",
    "sg:address":"Rue Michel-chauvet 22",
    "sg:city":"Gen\u00e8ve",
    "sg:orig_category":"Primarschulen",
    "sg:phone":"+41 22 751 18 86",
    "sg:postcode":"1208",
    "sg:province":"Gen\u00e8ve",
    "wof:name":"Ecole Primaire Corsier-village",
    "wof:placetype":"venue"
},
  "geometry": {"coordinates":[6.2183699608,46.2690315247],"type":"Point"}
}