{
  "type": "Feature",
  "properties": {
    "iso:country":"CH",
    "sg:address":"G\u00fctschstrasse 4 6312 Steinhausen. Postfach 328",
    "sg:city":"Steinhausen",
    "sg:orig_category":"Fachdetailhandel in Verkaufsr\u00e4umen",
    "sg:phone":"+41 41 741 59 51",
    "sg:postcode":"6312",
    "sg:province":"Zug",
    "wof:name":"New Art Ltd For Jewels And Objects",
    "wof:placetype":"venue"
},
  "geometry": {"coordinates":[8.4767093658,47.1996955872],"type":"Point"}
}