{
  "type": "Feature",
  "properties": {
    "iso:country":"CH",
    "sg:address":"Bielstrasse 50 4500 Solothurn. Postfach",
    "sg:city":"Solothurn",
    "sg:orig_category":"Instandhaltung U Reparatur von Automobilen",
    "sg:phone":"+41 32 622 29 62",
    "sg:postcode":"4503",
    "sg:province":"Solothurn",
    "wof:name":"Garage Gysin Ag",
    "wof:placetype":"venue"
},
  "geometry": {"coordinates":[7.5282039642,47.2105331421],"type":"Point"}
}