{
  "type": "Feature",
  "properties": {
    "iso:country":"CH",
    "sg:address":"Hauptstr. 19",
    "sg:city":"Einsiedeln",
    "sg:classifiers":[
        {
            "category":"Banks & Credit Unions",
            "subcategory":"Bank",
            "type":"Services"
        }
    ],
    "sg:phone":"+41 27 952 25 26",
    "sg:postcode":"8840",
    "sg:province":"Schwyz",
    "wof:name":"Raiffeisenbank Embd",
    "wof:placetype":"venue"
},
  "geometry": {"coordinates":[7.8282,46.216911],"type":"Point"}
}