{
  "type": "Feature",
  "properties": {
    "iso:country":"CH",
    "sg:address":"Blumenstrasse 194c",
    "sg:city":"Leissigen",
    "sg:orig_category":"Organisationen des Gesundheitswesen",
    "sg:phone":"+41 33 847 13 76",
    "sg:postcode":"3706",
    "sg:province":"Bern",
    "wof:name":"Samariterverein Leissigen",
    "wof:placetype":"venue"
},
  "geometry": {"coordinates":[7.7760429382,46.6549415588],"type":"Point"}
}