{
  "type": "Feature",
  "properties": {
    "iso:country":"CH",
    "sg:address":"Rollirain",
    "sg:city":"Mammern",
    "sg:orig_category":"Landwirtschaft, Jagd U damit verbundene Dienstleistungen",
    "sg:phone":"+41 52 741 28 07",
    "sg:postcode":"8265",
    "sg:province":"Thurgau",
    "wof:name":"Peter Z\u00fcblin Gutsbetrieb",
    "wof:placetype":"venue"
},
  "geometry": {"coordinates":[8.9429931641,47.6511154175],"type":"Point"}
}