{
  "type": "Feature",
  "properties": {
    "iso:country":"CH",
    "sg:address":"Bahnhofstrasse 16 6300 Zug. Postfach",
    "sg:city":"Zug",
    "sg:orig_category":"Vermietung U Verpachtung von eigenen Immobilien",
    "sg:phone":"+41 71 940 05 29",
    "sg:postcode":"6300",
    "sg:province":"Zug",
    "wof:name":"Z\u00fcrcher Alfred Ag Zuzwil Sg",
    "wof:placetype":"venue"
},
  "geometry": {"coordinates":[9.1070156097,47.4752349854],"type":"Point"}
}