{
  "type": "Feature",
  "properties": {
    "addr:full":"Rue De Lyon 57 Gen\u00e8ve Gen\u00e8ve 1203",
    "addr:housenumber":"57",
    "addr:postcode":"1203",
    "addr:street":"Rue De Lyon",
    "iso:country":"CH",
    "sg:address":"Rue De Lyon 57",
    "sg:city":"Gen\u00e8ve",
    "sg:orig_category":"Allgemeiner Hochbau",
    "sg:phone":"+41 22 344 12 11",
    "sg:postcode":"1203",
    "sg:province":"Gen\u00e8ve",
    "wof:name":"Kenitex Fa\u00e7ades S\u00e0rl",
    "wof:placetype":"venue"
},
  "geometry": {"coordinates":[6.132221,46.20879],"type":"Point"}
}