{
  "type": "Feature",
  "properties": {
    "iso:country":"CH",
    "sg:address":"Grand-rue 31",
    "sg:city":"Ch\u00e2telard-lutry",
    "sg:orig_category":"Fachdetailhandel in Verkaufsr\u00e4umen Gold- and Silberschmuck Detailhandel",
    "sg:phone":"+41 21 792 10 75",
    "sg:postcode":"1095",
    "sg:province":"Vaud",
    "wof:name":"Au 13 Or, Barben Stephan",
    "wof:placetype":"venue"
},
  "geometry": {"coordinates":[6.685585022,46.5023193359],"type":"Point"}
}