{
  "type": "Feature",
  "properties": {
    "iso:country":"CH",
    "sg:address":"Fruthwilerstrasse 80",
    "sg:city":"Ermatingen",
    "sg:orig_category":"Unternehmensberatung",
    "sg:phone":"+41 14921817",
    "sg:postcode":"8272",
    "sg:province":"Thurgau",
    "wof:name":"Vetterli Peter",
    "wof:placetype":"venue"
},
  "geometry": {"coordinates":[8.4606580734,47.3709754944],"type":"Point"}
}