{
  "type": "Feature",
  "properties": {
    "iso:country":"CH",
    "sg:address":"Hochwachtstrasse 27a",
    "sg:city":"Winterthur",
    "sg:orig_category":"Unclassifiable Establishments",
    "sg:postcode":"8400",
    "sg:province":"Z\u00fcrich",
    "wof:name":"Stiftung Amadeus",
    "wof:placetype":"venue"
},
  "geometry": {"coordinates":[8.7265634537,47.4928207397],"type":"Point"}
}