{
  "type": "Feature",
  "properties": {
    "iso:country":"CH",
    "sg:address":"Zullwilerstrasse 2",
    "sg:city":"Nunningen",
    "sg:classifiers":[
        {
            "category":"Restaurant",
            "type":"Food & Drink"
        }
    ],
    "sg:phone":"+41 61 791 07 91",
    "sg:postcode":"4208",
    "sg:province":"Solothurn",
    "wof:name":"Wirtshaus Zum R\u00f6ssli",
    "wof:placetype":"venue"
},
  "geometry": {"coordinates":[7.6189060211,47.3932266235],"type":"Point"}
}