{
  "type": "Feature",
  "properties": {
    "iso:country":"CH",
    "sg:address":"3992",
    "sg:city":"Bettmeralp",
    "sg:orig_category":"Verkehrs- and Tourismusb\u00fcros",
    "sg:phone":"+41 27 927 12 91",
    "sg:postcode":"3992",
    "sg:province":"Valais",
    "wof:name":"Verkehrsb\u00fcro",
    "wof:placetype":"venue"
},
  "geometry": {"coordinates":[8.0611801147,46.3894996643],"type":"Point"}
}