{
  "type": "Feature",
  "properties": {
    "iso:country":"CH",
    "sg:address":"Rest. Ochsen",
    "sg:city":"Sch\u00f6nengrund",
    "sg:classifiers":[
        {
            "category":"Travel",
            "subcategory":"Hotels & Motels",
            "type":"Entertainment"
        }
    ],
    "sg:postcode":"9105",
    "sg:province":"Appenzell Ausserrhoden",
    "sg:tags":[
        "hotels",
        "mit",
        "restaurant"
    ],
    "wof:name":"Heinrich Nufer",
    "wof:placetype":"venue"
},
  "geometry": {"coordinates":[9.227145195,47.3293418884],"type":"Point"}
}