{
  "type": "Feature",
  "properties": {
    "iso:country":"CH",
    "sg:address":"Hauptstrasse 12",
    "sg:city":"Balterswil",
    "sg:orig_category":"Haltung von Gefl\u00fcgel",
    "sg:phone":"+41 71 971 17 23",
    "sg:postcode":"8362",
    "sg:province":"Thurgau",
    "wof:name":"Josef & Ludwig K\u00f6chli Gefl\u00fcgelzucht",
    "wof:placetype":"venue"
},
  "geometry": {"coordinates":[8.9337825775,47.4511947632],"type":"Point"}
}