{
  "type": "Feature",
  "properties": {
    "iso:country":"CH",
    "sg:address":"Landstrasse 35",
    "sg:city":"Vaduz",
    "sg:orig_category":"Innenarchitekturb\u00fcros",
    "sg:postcode":"9490",
    "wof:name":"Atelier 88 B\u00fcro F\u00fcr Innenarchitektur",
    "wof:placetype":"venue"
},
  "geometry": {"coordinates":[9.515376091,47.1447525024],"type":"Point"}
}