{
  "type": "Feature",
  "properties": {
    "iso:country":"CH",
    "sg:address":"Riedikon",
    "sg:city":"Uster",
    "sg:orig_category":"Non-Classified Establishments",
    "sg:postcode":"8610",
    "sg:province":"Z\u00fcrich",
    "wof:name":"Heeb + Partner Gmbh",
    "wof:placetype":"venue"
},
  "geometry": {"coordinates":[9.567407608,47.3922233582],"type":"Point"}
}