{
  "type": "Feature",
  "properties": {
    "iso:country":"CH",
    "sg:address":"Sundgauerstrasse 18",
    "sg:city":"Basel",
    "sg:orig_category":"Druckweiterverarbeitung Softwareentwicklung U beratung",
    "sg:phone":"+41 22 700 31 13",
    "sg:postcode":"4055",
    "sg:province":"Basel-Stadt",
    "wof:name":"Disa Sa",
    "wof:placetype":"venue"
},
  "geometry": {"coordinates":[6.1418061256,46.1833534241],"type":"Point"}
}