{
  "type": "Feature",
  "properties": {
    "iso:country":"CH",
    "sg:address":"Asylweg 30",
    "sg:city":"Bern",
    "sg:orig_category":"Unclassifiable Establishments",
    "sg:postcode":"3027",
    "sg:province":"Bern",
    "wof:name":"Mconsult Gmbh",
    "wof:placetype":"venue"
},
  "geometry": {"coordinates":[7.3831071854,46.9465141296],"type":"Point"}
}