{
  "type": "Feature",
  "properties": {
    "iso:country":"CH",
    "sg:address":"Trenschenstieg 8",
    "sg:city":"Schaffhausen",
    "sg:orig_category":"Handelsvermittlung U Grosshandel",
    "sg:phone":"+41 52 643 56 25",
    "sg:postcode":"8207",
    "sg:province":"Schaffhausen",
    "wof:name":"Bms Finanz & Management Ag",
    "wof:placetype":"venue"
},
  "geometry": {"coordinates":[8.6654567719,47.7268562317],"type":"Point"}
}