{
  "type": "Feature",
  "properties": {
    "iso:country":"CH",
    "sg:address":"Mattenstalden 3764 Weissenburg. Postfach",
    "sg:city":"Weissenburg",
    "sg:orig_category":"G\u00fcterbef\u00f6rderung im Strassenverkehr",
    "sg:postcode":"3764",
    "sg:province":"Bern",
    "wof:name":"Knutti Daniel, Transporte",
    "wof:placetype":"venue"
},
  "geometry": {"coordinates":[7.4780130386,46.6574821472],"type":"Point"}
}