{
  "type": "Feature",
  "properties": {
    "iso:country":"CH",
    "sg:address":"Feldhofstrasse 2",
    "sg:city":"Uster",
    "sg:orig_category":"Tankstellen",
    "sg:postcode":"8610",
    "sg:province":"Z\u00fcrich",
    "wof:name":"Frund Jean-philippe",
    "wof:placetype":"venue"
},
  "geometry": {"coordinates":[6.5836801529,46.5333061218],"type":"Point"}
}