{
  "type": "Feature",
  "properties": {
    "iso:country":"CH",
    "sg:address":"Rue Des Sabli\u00e8res 5 1242 Satigny Case Postale 635",
    "sg:city":"Vernier",
    "sg:orig_category":"Grosshandel mit Wein U Spirituosen",
    "sg:phone":"+41 22 341 41 14",
    "sg:postcode":"1214",
    "sg:province":"Gen\u00e8ve",
    "wof:name":"Solera Sa Import.de Vins & Spiritueux",
    "wof:placetype":"venue"
},
  "geometry": {"coordinates":[6.0586848259,46.2184333801],"type":"Point"}
}