{
  "type": "Feature",
  "properties": {
    "iso:country":"CH",
    "sg:address":"Kanalstrasse 235",
    "sg:city":"Uerkheim",
    "sg:orig_category":"Wasserversorgung",
    "sg:postcode":"4813",
    "sg:province":"Aargau",
    "wof:name":"Wasser-genossenschaft Wvg Oberdorf Uerkheim",
    "wof:placetype":"venue"
},
  "geometry": {"coordinates":[8.0187120438,47.298160553],"type":"Point"}
}