{
  "type": "Feature",
  "properties": {
    "iso:country":"CH",
    "sg:address":"Forchstrasse 2",
    "sg:city":"Z\u00fcrich",
    "sg:orig_category":"Detailhandel mit Brot, Back U S\u00fcsswaren",
    "sg:phone":"+41 13834996",
    "sg:postcode":"8008",
    "sg:province":"Z\u00fcrich",
    "wof:name":"Urs Stocker B\u00e4ckerei-konditorei",
    "wof:placetype":"venue"
},
  "geometry": {"coordinates":[8.554772,47.364464],"type":"Point"}
}