{
  "type": "Feature",
  "properties": {
    "iso:country":"CH",
    "sg:address":"Derri\u00e8re Montet 51",
    "sg:city":"Diesse",
    "sg:orig_category":"Architektur U Ingenieurb\u00fcros Architekturb\u00fcros",
    "sg:phone":"+41 55 240 77 31",
    "sg:postcode":"2517",
    "sg:province":"Bern",
    "wof:name":"Meienberger M. W. Architekturb\u00fcro Ag",
    "wof:placetype":"venue"
},
  "geometry": {"coordinates":[8.853017,47.253483],"type":"Point"}
}