{
  "type": "Feature",
  "properties": {
    "addr:full":"Chemin De La Cassinette 17 Lausanne Vaud 1018",
    "addr:housenumber":"17",
    "addr:postcode":"1018",
    "addr:street":"Chemin De La Cassinette",
    "iso:country":"CH",
    "sg:address":"Chemin De La Cassinette 17",
    "sg:city":"Lausanne",
    "sg:orig_category":"Betrieb von Taxis",
    "sg:phone":"+41 21 646 73 64",
    "sg:postcode":"1018",
    "sg:province":"Vaud",
    "wof:name":"G\u00e9rald Bonjour Taxis",
    "wof:placetype":"venue"
},
  "geometry": {"coordinates":[6.621674,46.540546],"type":"Point"}
}