{
  "type": "Feature",
  "properties": {
    "iso:country":"CH",
    "sg:address":"3034",
    "sg:city":"Murzelen",
    "sg:classifiers":[
        {
            "category":"Government",
            "subcategory":"Post Office",
            "type":"Public Place"
        }
    ],
    "sg:phone":"+41 31 829 25 86",
    "sg:postcode":"3034",
    "sg:province":"Bern",
    "sg:tags":[
        "die",
        "poststellen"
    ],
    "wof:name":"Die Post",
    "wof:placetype":"venue"
},
  "geometry": {"coordinates":[7.3164401054,46.9816398621],"type":"Point"}
}