{
  "type": "Feature",
  "properties": {
    "iso:country":"CH",
    "sg:address":"Z\u00fcrichstrasse 3",
    "sg:city":"Merenschwand",
    "sg:orig_category":"Detailhandel mit Blumen U Pflanzen Fachdetailhandel in Verkaufsr\u00e4umen",
    "sg:phone":"+41 56 664 32 72",
    "sg:postcode":"5634",
    "sg:province":"Aargau",
    "wof:name":"Steffi's Bluemelade Keller S.",
    "wof:placetype":"venue"
},
  "geometry": {"coordinates":[8.37552,47.259621],"type":"Point"}
}