{
  "type": "Feature",
  "properties": {
    "iso:country":"CH",
    "sg:address":"Oberfrick",
    "sg:city":"Gipf-oberfrick",
    "sg:orig_category":"Sportvereine Velo Rad-& Motorfahrer-Bund SRB",
    "sg:postcode":"5073",
    "sg:province":"Aargau",
    "wof:name":"Veloclub Thierstein",
    "wof:placetype":"venue"
},
  "geometry": {"coordinates":[7.9991698265,47.493560791],"type":"Point"}
}