{
  "type": "Feature",
  "properties": {
    "iso:country":"CH",
    "sg:address":"Industriestrasse 1",
    "sg:city":"Winterthur",
    "sg:orig_category":"Architektur U Ingenieurb\u00fcros Herstellung von Metallerzeugnissen ohne Maschinenbau",
    "sg:phone":"+41 52 232 08 26",
    "sg:postcode":"8404",
    "sg:province":"Z\u00fcrich",
    "wof:name":"Fluitec Georg Ag",
    "wof:placetype":"venue"
},
  "geometry": {"coordinates":[8.748406,47.496571],"type":"Point"}
}