{
  "type": "Feature",
  "properties": {
    "iso:country":"CH",
    "sg:address":"Alleestrasse 11b",
    "sg:city":"Kreuzlingen",
    "sg:orig_category":"Vorschulen, Kinderg\u00e4rten",
    "sg:phone":"+41 52 625 25 88",
    "sg:postcode":"8280",
    "sg:province":"Thurgau",
    "wof:name":"Rudolf Steiner-schule Kreuzlingen, Kindergarten",
    "wof:placetype":"venue"
},
  "geometry": {"coordinates":[9.1701936722,47.6508903503],"type":"Point"}
}