{
  "type": "Feature",
  "properties": {
    "addr:full":"Eggerstanden Appenzell Appenzell Innerhoden 9050",
    "addr:postcode":"9050",
    "iso:country":"CH",
    "sg:address":"Eggerstanden",
    "sg:city":"Appenzell",
    "sg:orig_category":"Bauingenieurb\u00fcros Hochbau Bauingenieurb\u00fcros allgemein",
    "sg:phone":"+41 56 426 43 88",
    "sg:postcode":"9050",
    "sg:province":"Appenzell Innerhoden",
    "wof:name":"Reto Walser Ingenieurb\u00fcro",
    "wof:placetype":"venue"
},
  "geometry": {"coordinates":[8.322525,47.465149],"type":"Point"}
}