{
  "type": "Feature",
  "properties": {
    "iso:country":"CH",
    "sg:address":"Steinenring 5",
    "sg:city":"Basel",
    "sg:orig_category":"Arztpraxen",
    "sg:phone":"+41 61 272 38 44",
    "sg:postcode":"4051",
    "sg:province":"Basel-Stadt",
    "wof:name":"Dr.med.paul Tittel Spezialarzt Fmh",
    "wof:placetype":"venue"
},
  "geometry": {"coordinates":[7.5781,47.552578],"type":"Point"}
}