{
  "type": "Feature",
  "properties": {
    "iso:country":"CH",
    "sg:address":"Lindenplatz 6 8048 Z\u00fcrich. Postfach",
    "sg:city":"Z\u00fcrich",
    "sg:orig_category":"Reiseb\u00fcros U Reiseveranstalter",
    "sg:phone":"+41 61 277 27 71",
    "sg:postcode":"8048",
    "sg:province":"Z\u00fcrich",
    "wof:name":"Esco-reisen Ag",
    "wof:placetype":"venue"
},
  "geometry": {"coordinates":[8.4854784012,47.3876953125],"type":"Point"}
}