{
  "type": "Feature",
  "properties": {
    "iso:country":"CH",
    "sg:address":"Weinfelderstrasse 45",
    "sg:city":"Amriswil",
    "sg:orig_category":"Politische Parteien FDP",
    "sg:phone":"+41 71 411 51 34",
    "sg:postcode":"8580",
    "sg:province":"Thurgau",
    "wof:name":"Fdp Ortspartei Amriswil",
    "wof:placetype":"venue"
},
  "geometry": {"coordinates":[9.2894859314,47.5444641113],"type":"Point"}
}