{
  "type": "Feature",
  "properties": {
    "addr:full":"Spitalackerstrasse 65 Bern Bern 3013",
    "addr:housenumber":"65",
    "addr:postcode":"3013",
    "addr:street":"Spitalackerstrasse",
    "iso:country":"CH",
    "sg:address":"Spitalackerstrasse 65",
    "sg:city":"Bern",
    "sg:classifiers":[
        {
            "category":"Health Services",
            "subcategory":"Dentist",
            "type":"Services"
        }
    ],
    "sg:phone":"+41 31 332 67 04",
    "sg:postcode":"3013",
    "sg:province":"Bern",
    "sg:tags":[
        "material",
        "dental",
        "ceramic"
    ],
    "wof:name":"Dental-team Immler + Sieber",
    "wof:placetype":"venue"
},
  "geometry": {"coordinates":[7.451396,46.956944],"type":"Point"}
}