{
  "type": "Feature",
  "properties": {
    "iso:country":"CH",
    "sg:address":"Untertalweg 56",
    "sg:city":"Arlesheim",
    "sg:orig_category":"Allgemeiner Hochbau Hobel U Holzimpr\u00e4gnierwerke",
    "sg:phone":"+41 61 691 35 45",
    "sg:postcode":"4144",
    "sg:province":"Basel-Landschaft",
    "wof:name":"Amirage Ag",
    "wof:placetype":"venue"
},
  "geometry": {"coordinates":[7.610665,47.49921],"type":"Point"}
}