{
  "type": "Feature",
  "properties": {
    "iso:country":"CH",
    "sg:address":"5004 Aarau. Postfach 610",
    "sg:city":"Aarau",
    "sg:orig_category":"Sportvereine Ballsport Fussball",
    "sg:phone":"+41 62 823 03 83",
    "sg:postcode":"5004",
    "sg:province":"Aargau",
    "wof:name":"Fc San Paolo",
    "wof:placetype":"venue"
},
  "geometry": {"coordinates":[8.0603399277,47.4006195068],"type":"Point"}
}