{
  "type": "Feature",
  "properties": {
    "iso:country":"CH",
    "sg:address":"Wygarten 5",
    "sg:city":"Zufikon",
    "sg:orig_category":"Sportvereine Turnen Vereine Damen",
    "sg:phone":"+41 71 277 65 84",
    "sg:postcode":"5621",
    "sg:province":"Aargau",
    "wof:name":"Damen-& Frauenriege Stv Sg",
    "wof:placetype":"venue"
},
  "geometry": {"coordinates":[9.3382301331,47.4098587036],"type":"Point"}
}