{
  "type": "Feature",
  "properties": {
    "iso:country":"CH",
    "sg:address":"Via Vallemaggia 18",
    "sg:city":"Locarno",
    "sg:orig_category":"Organisationen des Gesundheitswesen",
    "sg:phone":"+41 41 988 20 33",
    "sg:postcode":"6600",
    "sg:province":"Ticino",
    "wof:name":"Amb.krankenpflege D.gemeinden Altb\u00fcron Fischbach Ufhusen",
    "wof:placetype":"venue"
},
  "geometry": {"coordinates":[7.9087600708,47.1533203125],"type":"Point"}
}