{
  "type": "Feature",
  "properties": {
    "iso:country":"CH",
    "sg:address":"Moosweg 13",
    "sg:city":"Arch",
    "sg:orig_category":"Politische Parteien FDP",
    "sg:postcode":"3296",
    "sg:province":"Bern",
    "wof:name":"Fdp Amt B\u00fcren",
    "wof:placetype":"venue"
},
  "geometry": {"coordinates":[7.4357590675,47.1654891968],"type":"Point"}
}