{
  "type": "Feature",
  "properties": {
    "iso:country":"CH",
    "sg:address":"Lindenhof 6 6060 Sarnen. Postfach",
    "sg:city":"Sarnen",
    "sg:orig_category":"Unternehmensberatung",
    "sg:postcode":"6060",
    "sg:province":"Obwalden",
    "wof:name":"Bsp Management Gmbh",
    "wof:placetype":"venue"
},
  "geometry": {"coordinates":[8.2468185425,46.8967704773],"type":"Point"}
}