{
  "type": "Feature",
  "properties": {
    "iso:country":"CH",
    "sg:address":"Rue Pestalozzi 15",
    "sg:city":"Gen\u00e8ve",
    "sg:orig_category":"Advokaturb\u00fcros",
    "sg:phone":"+41 22 733 01 13",
    "sg:postcode":"1202",
    "sg:province":"Gen\u00e8ve",
    "wof:name":"Suzette Chevalier Etude D'avocat",
    "wof:placetype":"venue"
},
  "geometry": {"coordinates":[6.128388,46.216679],"type":"Point"}
}