{
  "type": "Feature",
  "properties": {
    "iso:country":"CH",
    "sg:address":"Andreasstrasse 5",
    "sg:city":"St.gallen",
    "sg:orig_category":"Instandhaltung U Reparatur von Automobilen",
    "sg:phone":"+41 71 278 39 28",
    "sg:postcode":"9000",
    "sg:province":"St. Gallen",
    "wof:name":"Rohrer-garage.",
    "wof:placetype":"venue"
},
  "geometry": {"coordinates":[9.3555650711,47.4207038879],"type":"Point"}
}