{
  "type": "Feature",
  "properties": {
    "iso:country":"CH",
    "sg:address":"Chantemerle 98 T",
    "sg:city":"Courtedoux",
    "sg:orig_category":"Non-Classified Establishments",
    "sg:postcode":"2905",
    "sg:province":"Jura",
    "wof:name":"Albert Biolley, Absaphir",
    "wof:placetype":"venue"
},
  "geometry": {"coordinates":[7.0408549309,47.4050292969],"type":"Point"}
}