{
  "type": "Feature",
  "properties": {
    "iso:country":"CH",
    "sg:address":"3634",
    "sg:city":"Thierachern",
    "sg:orig_category":"Mechanik Schlossereien",
    "sg:postcode":"3634",
    "sg:province":"Bern",
    "wof:name":"Werner Bieri",
    "wof:placetype":"venue"
},
  "geometry": {"coordinates":[7.5724902153,46.7520446777],"type":"Point"}
}