{
  "type": "Feature",
  "properties": {
    "iso:country":"CH",
    "sg:address":"Saule Chemin De 51",
    "sg:city":"Bernex",
    "sg:orig_category":"Interessenvertretungen",
    "sg:phone":"+41 22 757 11 16",
    "sg:postcode":"1233",
    "sg:province":"Gen\u00e8ve",
    "wof:name":"Fondation Hainard",
    "wof:placetype":"venue"
},
  "geometry": {"coordinates":[6.0726900101,46.1749458313],"type":"Point"}
}