{
  "type": "Feature",
  "properties": {
    "iso:country":"CH",
    "sg:address":"Chemin Des Rosiers 9",
    "sg:city":"Granges-paccot",
    "sg:orig_category":"Grosshandel mit B\u00fcromaschinen Grosshandel mit Datenverarbeitungsger\u00e4ten",
    "sg:phone":"+41 26 469 07 00",
    "sg:postcode":"1763",
    "sg:province":"Fribourg",
    "wof:name":"Link Computer Services Sa",
    "wof:placetype":"venue"
},
  "geometry": {"coordinates":[7.1390352249,46.8141937256],"type":"Point"}
}