{
  "type": "Feature",
  "properties": {
    "iso:country":"CH",
    "sg:address":"Premploz",
    "sg:city":"Erde",
    "sg:orig_category":"Malerei Stukkateurgewerbe, Gipserei U Verputzerei",
    "sg:phone":"+41 27 346 19 86",
    "sg:postcode":"1976",
    "sg:province":"Valais",
    "wof:name":"Gaby Ev\u00e9quoz Gypserie & Peinture",
    "wof:placetype":"venue"
},
  "geometry": {"coordinates":[7.2959799767,46.2425804138],"type":"Point"}
}