{
  "type": "Feature",
  "properties": {
    "iso:country":"CH",
    "sg:address":"3984",
    "sg:city":"Fiesch",
    "sg:orig_category":"Betrieb von Taxis",
    "sg:phone":"+41 27 971 18 18",
    "sg:postcode":"3984",
    "sg:province":"Valais",
    "wof:name":"Transporte Wellig",
    "wof:placetype":"venue"
},
  "geometry": {"coordinates":[8.06109,46.477242],"type":"Point"}
}