{
  "type": "Feature",
  "properties": {
    "iso:country":"CH",
    "sg:address":"Poststrasse 28",
    "sg:city":"Bischofszell",
    "sg:orig_category":"Arztpraxen",
    "sg:phone":"+41 56 496 51 50",
    "sg:postcode":"9220",
    "sg:province":"Thurgau",
    "wof:name":"Dr.med.markus Egolf Arzt F.allgemeine Medizin Fmh",
    "wof:placetype":"venue"
},
  "geometry": {"coordinates":[8.312524,47.404091],"type":"Point"}
}