{
  "type": "Feature",
  "properties": {
    "iso:country":"CH",
    "sg:address":"Derr. Le Ch\u00eane",
    "sg:city":"Poliez-le-grand",
    "sg:orig_category":"Instandhaltung U Reparatur von Automobilen",
    "sg:phone":"+41 21 881 47 06",
    "sg:postcode":"1041",
    "sg:province":"Vaud",
    "wof:name":"Fontannaz Richard",
    "wof:placetype":"venue"
},
  "geometry": {"coordinates":[6.6604199409,46.6171188354],"type":"Point"}
}