{
  "type": "Feature",
  "properties": {
    "iso:country":"CH",
    "sg:address":"Steineloh",
    "sg:city":"Frasnacht",
    "sg:orig_category":"Detailhandel mit Milcherzeugnissen U Eiern Verarbeitung von Milch",
    "sg:phone":"+41 71 446 13 91",
    "sg:postcode":"9320",
    "sg:province":"Thurgau",
    "wof:name":"Josef Ineichen Molkerei",
    "wof:placetype":"venue"
},
  "geometry": {"coordinates":[9.4349451065,47.5160446167],"type":"Point"}
}