{
  "type": "Feature",
  "properties": {
    "iso:country":"CH",
    "sg:address":"Golino 6656 Golino. Postfach",
    "sg:city":"Golino",
    "sg:orig_category":"Verwaltung von Immobilien",
    "sg:postcode":"6656",
    "sg:province":"Ticino",
    "wof:name":"Palmag",
    "wof:placetype":"venue"
},
  "geometry": {"coordinates":[8.4416713715,47.4588851929],"type":"Point"}
}