{
  "type": "Feature",
  "properties": {
    "iso:country":"CH",
    "sg:address":"Seestrasse 6440 Brunnen. Postfach",
    "sg:city":"Mettlen",
    "sg:orig_category":"Allgemeiner Hoch U Tiefbau",
    "sg:postcode":"9517",
    "sg:province":"Thurgau",
    "wof:name":"Gwerder F. Und S\u00f6hne Ag, Hoch Und Tiefbau, Muotathal, Zweigniederlassung Ingenbohl.",
    "wof:placetype":"venue"
},
  "geometry": {"coordinates":[8.613959,47.000652],"type":"Point"}
}