{
  "type": "Feature",
  "properties": {
    "iso:country":"CH",
    "sg:address":"R\u00f6schibachstrasse 22",
    "sg:city":"Z\u00fcrich",
    "sg:orig_category":"Detailhandel mit Waren verschiedener Art, Hauptrichtung Nahrungsmittel",
    "sg:phone":"+41 12713064",
    "sg:postcode":"8037",
    "sg:province":"Z\u00fcrich",
    "wof:name":"Coop Center Wipkingerbr\u00fccke",
    "wof:placetype":"venue"
},
  "geometry": {"coordinates":[8.5247402191,47.392780304],"type":"Point"}
}