{
  "type": "Feature",
  "properties": {
    "iso:country":"CH",
    "sg:address":"En La Fin",
    "sg:city":"Ch\u00e9serex",
    "sg:orig_category":"Markt U Meinungsforschung",
    "sg:postcode":"1275",
    "sg:province":"Vaud",
    "wof:name":"Griffiths Business Consultancy",
    "wof:placetype":"venue"
},
  "geometry": {"coordinates":[6.1732301712,46.3966598511],"type":"Point"}
}