{
  "type": "Feature",
  "properties": {
    "iso:country":"CH",
    "sg:address":"Sarbach",
    "sg:city":"Neuheim",
    "sg:orig_category":"Herstellung von Konstruktionsteilen, Fertigbauteilen U Ausbauelementen aus Holz",
    "sg:postcode":"6345",
    "sg:province":"Zug",
    "wof:name":"Schreinerei R\u00f6llin",
    "wof:placetype":"venue"
},
  "geometry": {"coordinates":[8.5824260712,47.2033920288],"type":"Point"}
}