{
  "type": "Feature",
  "properties": {
    "iso:country":"CH",
    "sg:address":"6803",
    "sg:city":"Camignolo",
    "sg:orig_category":"Herstellung von Ausbauelementen aus Metall",
    "sg:phone":"+41 91 946 15 80",
    "sg:postcode":"6803",
    "sg:province":"Ticino",
    "wof:name":"Giordano Mantegazzi Sa",
    "wof:placetype":"venue"
},
  "geometry": {"coordinates":[8.9504499435,46.1043701172],"type":"Point"}
}