{
  "type": "Feature",
  "properties": {
    "iso:country":"CH",
    "sg:address":"Lausenerstrasse 17",
    "sg:city":"Liestal",
    "sg:orig_category":"Finanzierungsinstitutionen Verm\u00f6gensverwaltung",
    "sg:phone":"+41 61 921 71 10",
    "sg:postcode":"4410",
    "sg:province":"Basel-Landschaft",
    "wof:name":"Opportunity Ag",
    "wof:placetype":"venue"
},
  "geometry": {"coordinates":[7.7487120628,47.4759292603],"type":"Point"}
}