{
  "type": "Feature",
  "properties": {
    "iso:country":"CH",
    "sg:address":"Rue Du Grand-pont 2",
    "sg:city":"Sion",
    "sg:orig_category":"Verwertung von Milch",
    "sg:postcode":"1950",
    "sg:province":"Valais",
    "wof:name":"Martin Georges",
    "wof:placetype":"venue"
},
  "geometry": {"coordinates":[7.3607120514,46.2332229614],"type":"Point"}
}