{
  "type": "Feature",
  "properties": {
    "iso:country":"CH",
    "sg:address":"Landstrasse 18",
    "sg:city":"Naters",
    "sg:orig_category":"Ingenieurb\u00fcros Geologie",
    "sg:phone":"+41 27 924 21 21",
    "sg:postcode":"3904",
    "sg:province":"Valais",
    "wof:name":"Theo Lauber Geologie Gehytec",
    "wof:placetype":"venue"
},
  "geometry": {"coordinates":[7.9906411171,46.3255271912],"type":"Point"}
}