{
  "type": "Feature",
  "properties": {
    "iso:country":"CH",
    "sg:address":"Unterlinden",
    "sg:city":"Weggis",
    "sg:orig_category":"Zimmerei, Dachdeckerei, Bauspenglerei U Abdichtung",
    "sg:phone":"+41 32 351 36 41",
    "sg:postcode":"6353",
    "sg:province":"Luzern",
    "wof:name":"Holzbau Stuber H.",
    "wof:placetype":"venue"
},
  "geometry": {"coordinates":[7.3804488182,47.1419372559],"type":"Point"}
}