{
  "type": "Feature",
  "properties": {
    "iso:country":"CH",
    "sg:address":"Riburgerstrasse 5",
    "sg:city":"Rheinfelden",
    "sg:orig_category":"Herstellung von Elektromotoren, Generatoren U Transformatoren",
    "sg:phone":"+41 61 833 12 40",
    "sg:postcode":"4310",
    "sg:province":"Aargau",
    "wof:name":"Bec Ag",
    "wof:placetype":"venue"
},
  "geometry": {"coordinates":[7.8047528267,47.5527153015],"type":"Point"}
}