{
  "type": "Feature",
  "properties": {
    "iso:country":"CH",
    "sg:address":"Chemin Du Basset 5 1802 Corseaux. Postfach",
    "sg:city":"Corseaux",
    "sg:orig_category":"RESTAURANTS: TEA-ROOMS",
    "sg:postcode":"1802",
    "sg:province":"Vaud",
    "wof:name":"Berger David",
    "wof:placetype":"venue"
},
  "geometry": {"coordinates":[6.8340778351,46.4712409973],"type":"Point"}
}