{
  "type": "Feature",
  "properties": {
    "iso:country":"CH",
    "sg:address":"Seestrasse 3",
    "sg:city":"Zug",
    "sg:classifiers":[
        {
            "category":"Bars & Pubs",
            "type":"Food & Drink"
        }
    ],
    "sg:phone":"+41 41 711 09 04",
    "sg:postcode":"6300",
    "sg:province":"Zug",
    "sg:tags":[
        "restaurant"
    ],
    "wof:name":"Restaurant Gotth\u00e4rdli Am See & Bar",
    "wof:placetype":"venue"
},
  "geometry": {"coordinates":[8.515113,47.167366],"type":"Point"}
}