{
  "type": "Feature",
  "properties": {
    "iso:country":"CH",
    "sg:address":"Alpenstrasse 24",
    "sg:city":"Ostermundigen",
    "sg:orig_category":"Allgemeiner Hoch U Tiefbau Verwaltung von Immobilien",
    "sg:phone":"+41 79 439 25 25",
    "sg:postcode":"3072",
    "sg:province":"Bern",
    "wof:name":"Gfeller Bauplanungs Ag",
    "wof:placetype":"venue"
},
  "geometry": {"coordinates":[7.484289,46.953915],"type":"Point"}
}