{
  "type": "Feature",
  "properties": {
    "iso:country":"CH",
    "sg:address":"Wehntalerstrasse 26",
    "sg:city":"Dielsdorf",
    "sg:orig_category":"RESTAURANTS: TEA-ROOMS",
    "sg:phone":"+41 18531219",
    "sg:postcode":"8157",
    "sg:province":"Z\u00fcrich",
    "wof:name":"Restaurant Metzgerhalle",
    "wof:placetype":"venue"
},
  "geometry": {"coordinates":[8.4530897141,47.4830284119],"type":"Point"}
}