{
  "type": "Feature",
  "properties": {
    "iso:country":"CH",
    "sg:address":"Golpisberg",
    "sg:city":"Walkringen",
    "sg:orig_category":"Landw. Genossenschaften Dresch",
    "sg:postcode":"3512",
    "sg:province":"Bern",
    "wof:name":"Dreschgenossenschaft Biglen W.w\u00fcthrich",
    "wof:placetype":"venue"
},
  "geometry": {"coordinates":[7.626431942,46.9446029663],"type":"Point"}
}