{
  "type": "Feature",
  "properties": {
    "iso:country":"CH",
    "sg:address":"Bergstrasse 95",
    "sg:city":"D\u00fcbendorf",
    "sg:orig_category":"Herstellung von Reiseartikeln, Leder U Sattlerwaren",
    "sg:phone":"+41 71 385 81 44",
    "sg:postcode":"8600",
    "sg:province":"Z\u00fcrich",
    "wof:name":"Spirig Peter August, Sattlerei Und Pferdesport Ag",
    "wof:placetype":"venue"
},
  "geometry": {"coordinates":[9.2603025436,47.4168205261],"type":"Point"}
}