{
  "type": "Feature",
  "properties": {
    "iso:country":"CH",
    "sg:address":"Unterwinklenstrasse 7",
    "sg:city":"Frutigen",
    "sg:orig_category":"Sonstiges Versicherungsgewerbe",
    "sg:postcode":"3714",
    "sg:province":"Bern",
    "wof:name":"Beck Laurent.",
    "wof:placetype":"venue"
},
  "geometry": {"coordinates":[6.1424689293,46.2061309814],"type":"Point"}
}