{
  "type": "Feature",
  "properties": {
    "iso:country":"CH",
    "sg:address":"Nizzola Via 7",
    "sg:city":"Bellinzona",
    "sg:orig_category":"Herstellung von sonstigen Erzeugnissen",
    "sg:postcode":"6500",
    "sg:province":"Ticino",
    "wof:name":"Roca Sagl",
    "wof:placetype":"venue"
},
  "geometry": {"coordinates":[9.0241193771,46.1944618225],"type":"Point"}
}