{
  "type": "Feature",
  "properties": {
    "iso:country":"CH",
    "sg:address":"Zone Industrielle",
    "sg:city":"Matran",
    "sg:classifiers":[
        {
            "category":"Retail",
            "subcategory":"Repair Shop",
            "type":"Services"
        }
    ],
    "sg:phone":"+41 41 671 05 25",
    "sg:postcode":"1753",
    "sg:province":"Fribourg",
    "sg:tags":[
        "agricultural",
        "machinery"
    ],
    "wof:name":"Hans Rohrer",
    "wof:placetype":"venue"
},
  "geometry": {"coordinates":[8.278487,46.942394],"type":"Point"}
}