{
  "type": "Feature",
  "properties": {
    "iso:country":"CH",
    "sg:address":"H\u00fchnerhubelstrasse 66",
    "sg:city":"Belp",
    "sg:orig_category":"Grosshandel mit Milch, Milcherzeugnissen, Eiern, Speise\u00f6len U Nahrungsfetten",
    "sg:phone":"+41 31 812 01 81",
    "sg:postcode":"3123",
    "sg:province":"Bern",
    "wof:name":"Emmi Interfrais Sa",
    "wof:placetype":"venue"
},
  "geometry": {"coordinates":[7.4956498146,46.9058074951],"type":"Point"}
}