{
  "type": "Feature",
  "properties": {
    "iso:country":"CH",
    "sg:address":"Route De Courgenay 289",
    "sg:city":"Fontenais",
    "sg:orig_category":"Rolladen- and Storenmontage",
    "sg:phone":"+41 32 466 47 32",
    "sg:postcode":"2902",
    "sg:province":"Jura",
    "wof:name":"Stores De Boni Sa",
    "wof:placetype":"venue"
},
  "geometry": {"coordinates":[7.0865068436,47.4049758911],"type":"Point"}
}