{
  "type": "Feature",
  "properties": {
    "iso:country":"CH",
    "sg:address":"Obersecki 19",
    "sg:city":"Walchwil",
    "sg:orig_category":"Grosshandel mit Datenverarbeitungsger\u00e4ten Wirtschaftspr\u00fcfung, Steuerberatung U Treuhand",
    "sg:phone":"+41 41 758 05 77",
    "sg:postcode":"6318",
    "sg:province":"Zug",
    "wof:name":"Symatrix Services Ag",
    "wof:placetype":"venue"
},
  "geometry": {"coordinates":[8.5194282532,47.0973358154],"type":"Point"}
}