{
  "type": "Feature",
  "properties": {
    "iso:country":"CH",
    "sg:address":"Aeschland",
    "sg:city":"Ruswil",
    "sg:orig_category":"Vereine Musik/Blasmusik",
    "sg:phone":"+41 41 495 36 77",
    "sg:postcode":"6017",
    "sg:province":"Luzern",
    "wof:name":"Ortsmusik",
    "wof:placetype":"venue"
},
  "geometry": {"coordinates":[8.121006012,47.086353302],"type":"Point"}
}