{
  "type": "Feature",
  "properties": {
    "iso:country":"CH",
    "sg:address":"Weidstrasse 20 4656 Starrkirch-wil. Postfach",
    "sg:city":"Starrkirch-wil",
    "sg:orig_category":"Herstellung von Werkzeugmaschinen",
    "sg:phone":"+41 62 295 01 51",
    "sg:postcode":"4656",
    "sg:province":"Solothurn",
    "wof:name":"Wapf Consulting Mechanische Und Elektrische Komponenten F\u00fcr Die Kunststoff Und Lebensmittelherstellung; Beratung Und Verkauf",
    "wof:placetype":"venue"
},
  "geometry": {"coordinates":[7.9247431755,47.3532104492],"type":"Point"}
}