{
  "type": "Feature",
  "properties": {
    "iso:country":"CH",
    "sg:address":"Rebbergstrasse 26",
    "sg:city":"Tegerfelden",
    "sg:orig_category":"Architekturb\u00fcros",
    "sg:phone":"+41 56 245 28 59",
    "sg:postcode":"5306",
    "sg:province":"Aargau",
    "wof:name":"Ren\u00e9 Deppeler Architekturb\u00fcro",
    "wof:placetype":"venue"
},
  "geometry": {"coordinates":[8.284465,47.561153],"type":"Point"}
}