{
  "type": "Feature",
  "properties": {
    "iso:country":"CH",
    "sg:address":"Hauptstrasse 55",
    "sg:city":"Hilfikon",
    "sg:orig_category":"Bauschreinerei",
    "sg:phone":"+41 62 216 21 78",
    "sg:postcode":"5613",
    "sg:province":"Aargau",
    "wof:name":"Robert Ritter Schreinerei",
    "wof:placetype":"venue"
},
  "geometry": {"coordinates":[7.847795,47.324234],"type":"Point"}
}