{
  "type": "Feature",
  "properties": {
    "iso:country":"CH",
    "sg:address":"Route De Choulex 2",
    "sg:city":"Vandoeuvres",
    "sg:classifiers":[
        {
            "category":"Restaurant",
            "type":"Food & Drink"
        }
    ],
    "sg:phone":"+41 22 750 18 64",
    "sg:postcode":"1253",
    "sg:province":"Gen\u00e8ve",
    "wof:name":"Auberge Communale De Vandoeuvres",
    "wof:placetype":"venue"
},
  "geometry": {"coordinates":[6.2028579712,46.2212371826],"type":"Point"}
}