{
  "type": "Feature",
  "properties": {
    "addr:full":"Vallemaggia Via 86 Solduno Ticino 6600",
    "addr:housenumber":"86",
    "addr:postcode":"6600",
    "addr:street":"Via",
    "iso:country":"CH",
    "sg:address":"Vallemaggia Via 86",
    "sg:city":"Solduno",
    "sg:orig_category":"Allgemeiner Hoch U Tiefbau",
    "sg:phone":"+41 19303720",
    "sg:postcode":"6600",
    "sg:province":"Ticino",
    "wof:name":"Fabiano + Scoppa Gmbh",
    "wof:placetype":"venue"
},
  "geometry": {"coordinates":[8.799917,47.322536],"type":"Point"}
}