{
  "type": "Feature",
  "properties": {
    "iso:country":"CH",
    "sg:address":"Lenzburgerstrasse 8",
    "sg:city":"Mellingen",
    "sg:orig_category":"Tankstellen",
    "sg:phone":"+41 56 481 81 62",
    "sg:postcode":"5507",
    "sg:province":"Aargau",
    "wof:name":"Erich Huber Autogarage",
    "wof:placetype":"venue"
},
  "geometry": {"coordinates":[8.2725639343,47.4173812866],"type":"Point"}
}