{
  "type": "Feature",
  "properties": {
    "iso:country":"CH",
    "sg:address":"Wehntalerstrasse 6",
    "sg:city":"Dielsdorf",
    "sg:orig_category":"Unclassifiable Establishments",
    "sg:postcode":"8157",
    "sg:province":"Z\u00fcrich",
    "wof:name":"Haas Reisen + Transport Gmbh",
    "wof:placetype":"venue"
},
  "geometry": {"coordinates":[8.452580452,47.4852905273],"type":"Point"}
}