{
  "type": "Feature",
  "properties": {
    "iso:country":"CH",
    "sg:address":"Europe Avenue De L' 38b",
    "sg:city":"Monthey",
    "sg:orig_category":"Herstellung von Metallkonstruktionen",
    "sg:phone":"+41 24 472 33 16",
    "sg:postcode":"1870",
    "sg:province":"Valais",
    "wof:name":"Olivier Sch\u00f6nmann, Espace Plus",
    "wof:placetype":"venue"
},
  "geometry": {"coordinates":[6.9471402168,46.2516212463],"type":"Point"}
}