{
  "type": "Feature",
  "properties": {
    "iso:country":"CH",
    "sg:address":"Chamerstrasse 52",
    "sg:city":"Zug",
    "sg:orig_category":"Sonstige mit der Informatik verbundene T\u00e4tigkeiten",
    "sg:phone":"+41 41 710 42 82",
    "sg:postcode":"6300",
    "sg:province":"Zug",
    "wof:name":"Zwyssig Mbm",
    "wof:placetype":"venue"
},
  "geometry": {"coordinates":[8.5054988861,47.1739578247],"type":"Point"}
}