{
  "type": "Feature",
  "properties": {
    "iso:country":"CH",
    "sg:address":"Postgasse 29",
    "sg:city":"Glarus",
    "sg:orig_category":"F\u00fcrsorge\u00e4mter",
    "sg:phone":"+41 55 646 66 00",
    "sg:postcode":"8750",
    "sg:province":"Glarus",
    "wof:name":"Kantonale Sanit\u00e4ts-& F\u00fcrsorgedirektion",
    "wof:placetype":"venue"
},
  "geometry": {"coordinates":[9.0673074722,47.0415802002],"type":"Point"}
}