{
  "type": "Feature",
  "properties": {
    "iso:country":"CH",
    "sg:address":"Seestrasse 28",
    "sg:city":"Uster",
    "sg:orig_category":"Versandhandel",
    "sg:phone":"+41 19420244",
    "sg:postcode":"8610",
    "sg:province":"Z\u00fcrich",
    "wof:name":"Heinz Kleiner Polysan-versand",
    "wof:placetype":"venue"
},
  "geometry": {"coordinates":[8.7114849091,47.3460197449],"type":"Point"}
}