{
  "type": "Feature",
  "properties": {
    "iso:country":"CH",
    "sg:address":"Feldeggstrasse 4 8008 Z\u00fcrich. Postfach",
    "sg:city":"Z\u00fcrich",
    "sg:orig_category":"Sonstige Finanzierungsinstitutionen",
    "sg:phone":"+41 41 630 04 50",
    "sg:postcode":"8034",
    "sg:province":"Z\u00fcrich",
    "wof:name":"Alcopor Holding Ag",
    "wof:placetype":"venue"
},
  "geometry": {"coordinates":[8.3120708466,46.9978294373],"type":"Point"}
}