{
  "type": "Feature",
  "properties": {
    "iso:country":"CH",
    "sg:address":"Lagerhausstrasse 3 8400 Winterthur. Postfach",
    "sg:city":"Winterthur",
    "sg:orig_category":"Grosshandel mit Schmuck Grosshandel mit sonstigen Gebrauchs U Verbrauchsg\u00fctern",
    "sg:phone":"+41 52 214 14 14",
    "sg:postcode":"8401",
    "sg:province":"Z\u00fcrich",
    "wof:name":"Grafgem",
    "wof:placetype":"venue"
},
  "geometry": {"coordinates":[8.7257947922,47.4974441528],"type":"Point"}
}