{
  "type": "Feature",
  "properties": {
    "iso:country":"CH",
    "sg:address":"Milchh\u00fcslistrasse 232",
    "sg:city":"M\u00f6nthal",
    "sg:orig_category":"Unclassifiable Establishments",
    "sg:postcode":"5237",
    "sg:province":"Aargau",
    "wof:name":"Informatik & Engineering M\u00fcller",
    "wof:placetype":"venue"
},
  "geometry": {"coordinates":[8.1434078217,47.5186309814],"type":"Point"}
}