{
  "type": "Feature",
  "properties": {
    "iso:country":"CH",
    "sg:address":"Untere Allmendstrasse 11 6312 Steinhausen. Postfach 36",
    "sg:city":"Steinhausen",
    "sg:orig_category":"Grosshandel mit Textilien Grosshandel mit sonstigen Maschinen U Ausr\u00fcstungen f\u00fcr Industrie, Handel U",
    "sg:phone":"+41 41 740 09 09",
    "sg:postcode":"6312",
    "sg:province":"Zug",
    "wof:name":"Conis Ag",
    "wof:placetype":"venue"
},
  "geometry": {"coordinates":[8.4956245422,47.1924285889],"type":"Point"}
}