{
  "type": "Feature",
  "properties": {
    "iso:country":"CH",
    "sg:address":"Rathausstrasse 29",
    "sg:city":"Liestal",
    "sg:orig_category":"Detailhandel mit Waren verschiedener Art, Hauptrichtung Nahrungsmittel",
    "sg:phone":"+41 61 921 20 50",
    "sg:postcode":"4410",
    "sg:province":"Basel-Landschaft",
    "wof:name":"Merkur Ag",
    "wof:placetype":"venue"
},
  "geometry": {"coordinates":[7.734568119,47.4844741821],"type":"Point"}
}