{
  "type": "Feature",
  "properties": {
    "iso:country":"CH",
    "sg:address":"Promenade 13 2316 Martel-dernier Case Postale",
    "sg:city":"Martel-dernier",
    "sg:orig_category":"Herstellung von Uhren",
    "sg:phone":"+41 32 967 90 80",
    "sg:postcode":"2316",
    "sg:province":"Neuch\u00e2tel",
    "wof:name":"Montremo Sa",
    "wof:placetype":"venue"
},
  "geometry": {"coordinates":[6.822034,47.106827],"type":"Point"}
}