{
  "type": "Feature",
  "properties": {
    "iso:country":"CH",
    "sg:address":"Strittenmatt 6",
    "sg:city":"Wolhusen",
    "sg:orig_category":"Erschliessung von Grundst\u00fccken",
    "sg:phone":"+41 41 490 27 82",
    "sg:postcode":"6110",
    "sg:province":"Luzern",
    "wof:name":"Wohnbaugenossenschaft Pro Familia Wolhusen",
    "wof:placetype":"venue"
},
  "geometry": {"coordinates":[8.0746259689,47.0630226135],"type":"Point"}
}