{
  "type": "Feature",
  "properties": {
    "iso:country":"CH",
    "sg:address":"Metzgergasse 24",
    "sg:city":"St.gallen",
    "sg:orig_category":"RESTAURANTS: TEA-ROOMS",
    "sg:postcode":"9000",
    "sg:province":"St. Gallen",
    "wof:name":"O Porto Bar-restaurant",
    "wof:placetype":"venue"
},
  "geometry": {"coordinates":[12.6166849136,47.8045310974],"type":"Point"}
}