{
  "type": "Feature",
  "properties": {
    "iso:country":"CH",
    "sg:address":"Hof",
    "sg:city":"Lichtensteig",
    "sg:classifiers":[
        {
            "category":"Organizations",
            "subcategory":"Community Association",
            "type":"Services"
        }
    ],
    "sg:phone":"+41 71 988 36 42",
    "sg:postcode":"9620",
    "sg:province":"St. Gallen",
    "sg:tags":[
        "box",
        "cardboard"
    ],
    "wof:name":"Arbeitsst\u00e4tte Verein Casiprint",
    "wof:placetype":"venue"
},
  "geometry": {"coordinates":[9.0857,47.325661],"type":"Point"}
}