{
  "type": "Feature",
  "properties": {
    "iso:country":"CH",
    "sg:address":"Chemin Neuf 4",
    "sg:city":"Chamoson",
    "sg:orig_category":"Vermittlung von Immobilien Wirtschaftspr\u00fcfung, Steuerberatung U Treuhand",
    "sg:phone":"+41 27 306 53 03",
    "sg:postcode":"1955",
    "sg:province":"Valais",
    "wof:name":"Fiduciaire Moulin Charly Sa",
    "wof:placetype":"venue"
},
  "geometry": {"coordinates":[7.2232432365,46.201877594],"type":"Point"}
}