{
  "type": "Feature",
  "properties": {
    "iso:country":"CH",
    "sg:address":"H\u00f6fli",
    "sg:city":"Greppen",
    "sg:orig_category":"Sonstiger Fachdetailhandel mit Nahrungsmitteln, Getr\u00e4nken U Tabak in Verkaufsr\u00e4umen Verarbeitung von",
    "sg:phone":"+41 71 222 28 59",
    "sg:postcode":"6404",
    "sg:province":"Luzern",
    "wof:name":"Fuchs H.",
    "wof:placetype":"venue"
},
  "geometry": {"coordinates":[9.3753814697,47.4229698181],"type":"Point"}
}