{
  "type": "Feature",
  "properties": {
    "iso:country":"CH",
    "sg:address":"Wydackerstrasse 9",
    "sg:city":"Dielsdorf",
    "sg:orig_category":"Verwertung von Milch",
    "sg:postcode":"8157",
    "sg:province":"Z\u00fcrich",
    "wof:name":"Milchgenossenschaft Dielsdorf",
    "wof:placetype":"venue"
},
  "geometry": {"coordinates":[8.4518165588,47.4851036072],"type":"Point"}
}