{
  "type": "Feature",
  "properties": {
    "iso:country":"CH",
    "sg:address":"Gotthardstrasse 5",
    "sg:city":"Oberarth",
    "sg:classifiers":[
        {
            "category":"Restaurant",
            "type":"Food & Drink"
        }
    ],
    "sg:phone":"+41 41 855 11 88",
    "sg:postcode":"6414",
    "sg:province":"Schwyz",
    "wof:name":"Restaurant Sch\u00f6ntal",
    "wof:placetype":"venue"
},
  "geometry": {"coordinates":[8.5319509506,47.0581283569],"type":"Point"}
}