{
  "type": "Feature",
  "properties": {
    "iso:country":"CH",
    "sg:address":"Staatsstrasse 126",
    "sg:city":"Innerberg-s\u00e4riswil",
    "sg:classifiers":[
        {
            "category":"Travel",
            "subcategory":"Hotels & Motels",
            "type":"Entertainment"
        }
    ],
    "sg:phone":"+41 31 829 35 98",
    "sg:postcode":"3044",
    "sg:province":"Bern",
    "sg:tags":[
        "hotels",
        "mit",
        "restaurant"
    ],
    "wof:name":"Gasthof Restaurant Storchen",
    "wof:placetype":"venue"
},
  "geometry": {"coordinates":[7.3345060349,46.9918823242],"type":"Point"}
}