{
  "type": "Feature",
  "properties": {
    "iso:country":"CH",
    "sg:address":"Haldenm\u00fchleweg 14",
    "sg:city":"Goldach",
    "sg:orig_category":"Non-Classified Establishments",
    "sg:postcode":"9403",
    "sg:province":"St. Gallen",
    "wof:name":"Kaufmann Ronny - Berater",
    "wof:placetype":"venue"
},
  "geometry": {"coordinates":[9.4567689896,47.4718284607],"type":"Point"}
}