{
  "type": "Feature",
  "properties": {
    "iso:country":"CH",
    "sg:address":"Bahnhofstrasse 18 6210 Sursee. Postfach 81",
    "sg:city":"Sursee",
    "sg:orig_category":"Grossbanken",
    "sg:phone":"+41 844 800 888",
    "sg:postcode":"6210",
    "sg:province":"Luzern",
    "wof:name":"Credit Suisse",
    "wof:placetype":"venue"
},
  "geometry": {"coordinates":[8.1047267914,47.1726722717],"type":"Point"}
}