{
  "type": "Feature",
  "properties": {
    "iso:country":"CH",
    "sg:address":"Hauptstrasse 61",
    "sg:city":"Hellsau",
    "sg:orig_category":"Instandhaltung U Reparatur von Automobilen",
    "sg:phone":"+41 33 336 26 27",
    "sg:postcode":"3429",
    "sg:province":"Bern",
    "wof:name":"Luginb\u00fchl & Moser Gmbh",
    "wof:placetype":"venue"
},
  "geometry": {"coordinates":[7.6170139313,46.7243232727],"type":"Point"}
}