{
  "type": "Feature",
  "properties": {
    "iso:country":"CH",
    "sg:address":"Forrerstrasse 3",
    "sg:city":"Bern",
    "sg:orig_category":"Primarschulen",
    "sg:postcode":"3006",
    "sg:province":"Bern",
    "wof:name":"Primarschule Elfenau Pav.i",
    "wof:placetype":"venue"
},
  "geometry": {"coordinates":[7.4648528099,46.9350738525],"type":"Point"}
}