{
  "type": "Feature",
  "properties": {
    "addr:full":"Steinbruggstrasse Oberweningen Z\u00fcrich 8165",
    "addr:postcode":"8165",
    "addr:street":"Steinbruggstrasse",
    "iso:country":"CH",
    "sg:address":"Steinbruggstrasse",
    "sg:city":"Oberweningen",
    "sg:orig_category":"Blumen U Zierpflanzenbau Detailhandel mit Blumen U Pflanzen",
    "sg:phone":"+41 18560550",
    "sg:postcode":"8165",
    "sg:province":"Z\u00fcrich",
    "wof:name":"Andreas Gartmann",
    "wof:placetype":"venue"
},
  "geometry": {"coordinates":[8.40992,47.499565],"type":"Point"}
}