{
  "type": "Feature",
  "properties": {
    "iso:country":"CH",
    "sg:address":"Untere M\u00fchlestrasse 1",
    "sg:city":"Regensdorf",
    "sg:orig_category":"Polizei",
    "sg:phone":"+41 18404141",
    "sg:postcode":"8105",
    "sg:province":"Z\u00fcrich",
    "wof:name":"Kantonspolizei",
    "wof:placetype":"venue"
},
  "geometry": {"coordinates":[8.4642534256,47.430519104],"type":"Point"}
}