{
  "type": "Feature",
  "properties": {
    "iso:country":"CH",
    "sg:address":"La C\u00f4te 862",
    "sg:city":"Fontenais",
    "sg:orig_category":"Sportvereine Velo Rad-& Motorfahrer-Bund SRB",
    "sg:phone":"+41 32 466 87 41",
    "sg:postcode":"2902",
    "sg:province":"Jura",
    "wof:name":"Les Cyclos Du Gsa",
    "wof:placetype":"venue"
},
  "geometry": {"coordinates":[7.078619957,47.3998184204],"type":"Point"}
}