{
  "type": "Feature",
  "properties": {
    "iso:country":"CH",
    "sg:address":"Badweg 8",
    "sg:city":"Gelterkinden",
    "sg:orig_category":"Organisationen der Wohlfahrtspflege",
    "sg:phone":"+41 61 981 32 07",
    "sg:postcode":"4460",
    "sg:province":"Basel-Landschaft",
    "wof:name":"Pro Juventute",
    "wof:placetype":"venue"
},
  "geometry": {"coordinates":[7.8491940498,47.4671669006],"type":"Point"}
}