{
  "type": "Feature",
  "properties": {
    "iso:country":"CH",
    "sg:address":"Dorfackerstrasse 45",
    "sg:city":"Zuchwil",
    "sg:orig_category":"Detailhandel mit Schuhen Detailhandel mit Sportartikeln",
    "sg:phone":"+41 32 685 80 20",
    "sg:postcode":"4528",
    "sg:province":"Solothurn",
    "wof:name":"Dosenbach Schuhe & Sport",
    "wof:placetype":"venue"
},
  "geometry": {"coordinates":[7.5689711571,47.2013397217],"type":"Point"}
}