{
  "type": "Feature",
  "properties": {
    "iso:country":"CH",
    "sg:address":"Bernstrasse 88",
    "sg:city":"Dietikon",
    "sg:orig_category":"Allgemeiner Hoch U Tiefbau",
    "sg:phone":"+41 17451080",
    "sg:postcode":"8953",
    "sg:province":"Z\u00fcrich",
    "wof:name":"Reproad Ag",
    "wof:placetype":"venue"
},
  "geometry": {"coordinates":[8.429985,47.399189],"type":"Point"}
}