{
  "type": "Feature",
  "properties": {
    "iso:country":"CH",
    "sg:address":"Ch. Des Hortensias 44",
    "sg:city":"Chamb\u00e9sy",
    "sg:orig_category":"Non-Classified Establishments",
    "sg:postcode":"1292",
    "sg:province":"Gen\u00e8ve",
    "wof:name":"Si La Strada",
    "wof:placetype":"venue"
},
  "geometry": {"coordinates":[6.1349701881,46.2445716858],"type":"Point"}
}