{
  "type": "Feature",
  "properties": {
    "iso:country":"CH",
    "sg:address":"Sch\u00fctzenhausstrasse 581",
    "sg:city":"Maur",
    "sg:orig_category":"Markt U Meinungsforschung",
    "sg:phone":"+41 87858",
    "sg:postcode":"8124",
    "sg:province":"Z\u00fcrich",
    "wof:name":"Amako, Agentur F\u00fcr Marktkommunikation, W\u00fcthrich",
    "wof:placetype":"venue"
},
  "geometry": {"coordinates":[8.659910202,47.3426208496],"type":"Point"}
}