{
  "type": "Feature",
  "properties": {
    "iso:country":"CH",
    "sg:address":"Klarastrasse 3 4600 Olten. Postfach",
    "sg:city":"Olten",
    "sg:orig_category":"Non-Classified Establishments",
    "sg:postcode":"4601",
    "sg:province":"Solothurn",
    "wof:name":"Coiffeur Graber",
    "wof:placetype":"venue"
},
  "geometry": {"coordinates":[7.9122838974,47.3490715027],"type":"Point"}
}