{
  "type": "Feature",
  "properties": {
    "iso:country":"CH",
    "sg:address":"Theaterstrasse 12 8001 Z\u00fcrich. Postfach",
    "sg:city":"Z\u00fcrich",
    "sg:orig_category":"Mit dem Versicherungsgewerbe verbundene T\u00e4tigkeiten Verm\u00f6gensverwaltung",
    "sg:phone":"+41 16257272",
    "sg:postcode":"8022",
    "sg:province":"Z\u00fcrich",
    "wof:name":"Zurich Scudder Investments Ag",
    "wof:placetype":"venue"
},
  "geometry": {"coordinates":[8.5463895798,47.3665008545],"type":"Point"}
}