{
  "type": "Feature",
  "properties": {
    "iso:country":"CH",
    "sg:address":"Lavaterstrasse 87",
    "sg:city":"Z\u00fcrich",
    "sg:orig_category":"RESTAURANTS: TEA-ROOMS",
    "sg:phone":"+41 12011613",
    "sg:postcode":"8002",
    "sg:province":"Z\u00fcrich",
    "wof:name":"Restaurant Da Bernasconi Ag",
    "wof:placetype":"venue"
},
  "geometry": {"coordinates":[8.533331871,47.3602142334],"type":"Point"}
}