{
  "type": "Feature",
  "properties": {
    "iso:country":"CH",
    "sg:address":"Zelgli 39 3179 Kriechenwil. Postfach",
    "sg:city":"Kriechenwil",
    "sg:orig_category":"Grosshandel mit Getr\u00e4nken",
    "sg:postcode":"3179",
    "sg:province":"Bern",
    "wof:name":"Uhlmann Getr\u00e4nke Getr\u00e4nkehandel",
    "wof:placetype":"venue"
},
  "geometry": {"coordinates":[7.2196450233,46.9090576172],"type":"Point"}
}