{
  "type": "Feature",
  "properties": {
    "iso:country":"CH",
    "sg:address":"Zeiningerstrasse 1",
    "sg:city":"Maisprach",
    "sg:orig_category":"Wasserversorgung",
    "sg:phone":"+41 61 841 14 46",
    "sg:postcode":"4464",
    "sg:province":"Basel-Landschaft",
    "wof:name":"Wasserversorgung Maisprach",
    "wof:placetype":"venue"
},
  "geometry": {"coordinates":[7.8472962379,47.5250740051],"type":"Point"}
}