{
  "type": "Feature",
  "properties": {
    "iso:country":"CH",
    "sg:address":"Haus Erika",
    "sg:city":"Peist",
    "sg:orig_category":"Allgemeiner Hoch U Tiefbau Allgemeiner Hochbau",
    "sg:phone":"+41 81 374 14 97",
    "sg:postcode":"7029",
    "sg:province":"Graubunden",
    "wof:name":"Castelli Romano",
    "wof:placetype":"venue"
},
  "geometry": {"coordinates":[9.673376,46.832912],"type":"Point"}
}