{
  "type": "Feature",
  "properties": {
    "iso:country":"CH",
    "sg:address":"Alte Gerlafingenstrasse 1",
    "sg:city":"Biberist",
    "sg:orig_category":"Detailhandel mit Beleuchtungs U Haushaltsgegenst\u00e4nden Detailhandel mit elektrischen Haushalts, Radio",
    "sg:phone":"+41 32 675 53 53",
    "sg:postcode":"4562",
    "sg:province":"Solothurn",
    "wof:name":"Repag Gmbh Haushaltapparate",
    "wof:placetype":"venue"
},
  "geometry": {"coordinates":[7.565195,47.180065],"type":"Point"}
}