{
  "type": "Feature",
  "properties": {
    "iso:country":"CH",
    "sg:address":"Bramois 1967 Bramois. Postfach",
    "sg:city":"Bramois",
    "sg:orig_category":"Detailhandel mit Fleisch U Fleischwaren",
    "sg:postcode":"1967",
    "sg:province":"Valais",
    "wof:name":"Ebener M.",
    "wof:placetype":"venue"
},
  "geometry": {"coordinates":[7.3976430893,46.2284355164],"type":"Point"}
}