{
  "type": "Feature",
  "properties": {
    "iso:country":"CH",
    "sg:address":"Parallelstrasse 14",
    "sg:city":"Frutigen",
    "sg:orig_category":"Zimmerei, Dachdeckerei, Bauspenglerei U Abdichtung",
    "sg:phone":"+41 33 671 21 43",
    "sg:postcode":"3714",
    "sg:province":"Bern",
    "wof:name":"Allenbach Fritz, Ingenieurb\u00fcro F\u00fcr Holzbau",
    "wof:placetype":"venue"
},
  "geometry": {"coordinates":[7.6517567635,46.5860748291],"type":"Point"}
}