{
  "type": "Feature",
  "properties": {
    "iso:country":"CH",
    "sg:address":"Saint-laurent Rue 38 1003 Lausanne. Postfach",
    "sg:city":"Lausanne",
    "sg:orig_category":"RESTAURANTS: TEA-ROOMS",
    "sg:phone":"+41 21 312 73 47",
    "sg:postcode":"1003",
    "sg:province":"Vaud",
    "wof:name":"Zito Antonio Caf\u00e9-restaurant-bar \u00e0 L'ens El Chiringuito",
    "wof:placetype":"venue"
},
  "geometry": {"coordinates":[6.6306900978,46.5223999023],"type":"Point"}
}