{
  "type": "Feature",
  "properties": {
    "iso:country":"CH",
    "sg:address":"Z\u00fcrichstrasse 46",
    "sg:city":"Einsiedeln",
    "sg:orig_category":"Industrie, Industrieorganisationen",
    "sg:phone":"+41 55 418 83 00",
    "sg:postcode":"8840",
    "sg:province":"Schwyz",
    "wof:name":"Poly.-plastic Ag",
    "wof:placetype":"venue"
},
  "geometry": {"coordinates":[8.744886,47.133282],"type":"Point"}
}