{
  "type": "Feature",
  "properties": {
    "iso:country":"CH",
    "sg:address":"Rue De L'eglise 10",
    "sg:city":"Courroux",
    "sg:orig_category":"Detailhandel mit Waren verschiedener Art, Hauptrichtung Nahrungsmittel",
    "sg:phone":"+41 32 423 52 23",
    "sg:postcode":"2822",
    "sg:province":"Jura",
    "wof:name":"Primo D.& S.schmassmann Magasin D'alimentation",
    "wof:placetype":"venue"
},
  "geometry": {"coordinates":[7.3746118546,47.3624534607],"type":"Point"}
}