{
  "type": "Feature",
  "properties": {
    "iso:country":"CH",
    "sg:address":"Steigstrasse 8",
    "sg:city":"Wolfertswil",
    "sg:orig_category":"Sportvereine Ballsport Handball Sportvereine Turnen",
    "sg:phone":"+41 71 393 47 01",
    "sg:postcode":"9116",
    "sg:province":"St. Gallen",
    "wof:name":"Turnverein Stv Flawil",
    "wof:placetype":"venue"
},
  "geometry": {"coordinates":[9.1809864044,47.395198822],"type":"Point"}
}