{
  "type": "Feature",
  "properties": {
    "iso:country":"CH",
    "sg:address":"Obergrundstrasse 28",
    "sg:city":"Luzern",
    "sg:orig_category":"Detailhandel mit Radio U Fernsehger\u00e4ten",
    "sg:phone":"+41 41 240 23 66",
    "sg:postcode":"6003",
    "sg:province":"Luzern",
    "wof:name":"Tele-ren\u00e9 Siegrist",
    "wof:placetype":"venue"
},
  "geometry": {"coordinates":[8.3039627075,47.046836853],"type":"Point"}
}