{
  "type": "Feature",
  "properties": {
    "iso:country":"CH",
    "sg:address":"Schulgasse 9 6430 Schwyz. Postfach 537",
    "sg:city":"Schwyz",
    "sg:orig_category":"Detailhandel mit Textilien Grosshandel mit Textilien",
    "sg:phone":"+41 41 813 12 50",
    "sg:postcode":"6431",
    "sg:province":"Schwyz",
    "wof:name":"Scherrer Textil",
    "wof:placetype":"venue"
},
  "geometry": {"coordinates":[8.6534833908,47.0217323303],"type":"Point"}
}