{
  "type": "Feature",
  "properties": {
    "iso:country":"CH",
    "sg:address":"Ottigenb\u00fchlring 9",
    "sg:city":"Ebikon",
    "sg:orig_category":"Sonstige mit der Informatik verbundene T\u00e4tigkeiten",
    "sg:postcode":"6030",
    "sg:province":"Luzern",
    "wof:name":"Unternehmungsberatung + Werbeagentur Rolf Auer",
    "wof:placetype":"venue"
},
  "geometry": {"coordinates":[8.3544158936,47.0857887268],"type":"Point"}
}