{
  "type": "Feature",
  "properties": {
    "iso:country":"CH",
    "sg:address":"Alter Postplatz 1 6370 Stans. Postfach 849",
    "sg:city":"Stans",
    "sg:orig_category":"Grosshandel mit B\u00fcromaschinen Grosshandel mit Datenverarbeitungsger\u00e4ten",
    "sg:phone":"+41 41 610 00 76",
    "sg:postcode":"6371",
    "sg:province":"Nidwalden",
    "wof:name":"Computer-checkpoint Ramji",
    "wof:placetype":"venue"
},
  "geometry": {"coordinates":[8.3655376434,46.9577255249],"type":"Point"}
}