{
  "type": "Feature",
  "properties": {
    "iso:country":"CH",
    "sg:address":"Ospedale Via All' 14",
    "sg:city":"Locarno",
    "sg:orig_category":"Interessenvertretungen",
    "sg:phone":"+41 91 751 87 20",
    "sg:postcode":"6600",
    "sg:province":"Ticino",
    "wof:name":"Fondo Assistenziale Della Corporazione Borghese Di Locarno",
    "wof:placetype":"venue"
},
  "geometry": {"coordinates":[14.6601495743,41.5616722107],"type":"Point"}
}