{
  "type": "Feature",
  "properties": {
    "iso:country":"CH",
    "sg:address":"B\u00f6schenweg 6",
    "sg:city":"Tuggen",
    "sg:orig_category":"Grosshandel mit Textil, N\u00e4h U Strickmaschinen Herstellung von Maschinen f\u00fcr die Textil, Bekleidungsh",
    "sg:phone":"+41 55 465 17 81",
    "sg:postcode":"8856",
    "sg:province":"Schwyz",
    "wof:name":"Mts Meierhofer - Tex-service Ag",
    "wof:placetype":"venue"
},
  "geometry": {"coordinates":[8.9479427338,47.2015533447],"type":"Point"}
}