{
  "type": "Feature",
  "properties": {
    "iso:country":"CH",
    "sg:address":"Hauptstrasse 3 9424 Rheineck. Postfach",
    "sg:city":"Rheineck",
    "sg:classifiers":[
        {
            "category":"Insurance",
            "subcategory":"Insurance Agent",
            "type":"Services"
        }
    ],
    "sg:phone":"+41 71 888 27 64",
    "sg:postcode":"9424",
    "sg:province":"St. Gallen",
    "sg:tags":[
        "versicherungsagenturen",
        "-broker"
    ],
    "wof:name":"Winterthur-versicherungen Agentur",
    "wof:placetype":"venue"
},
  "geometry": {"coordinates":[9.5891494751,47.467300415],"type":"Point"}
}