{
  "type": "Feature",
  "properties": {
    "iso:country":"CH",
    "sg:address":"Chemin Du Stade 1",
    "sg:city":"Moutier",
    "sg:classifiers":[
        {
            "category":"Bars & Pubs",
            "type":"Food & Drink"
        }
    ],
    "sg:phone":"+41 32 493 33 25",
    "sg:postcode":"2740",
    "sg:province":"Bern",
    "wof:name":"Bar Derby",
    "wof:placetype":"venue"
},
  "geometry": {"coordinates":[7.360388,47.272957],"type":"Point"}
}