{
  "type": "Feature",
  "properties": {
    "iso:country":"CH",
    "sg:address":"Sandstrasse 48",
    "sg:city":"Glarus",
    "sg:orig_category":"Erschliessung von Grundst\u00fccken",
    "sg:phone":"+41 55 640 66 02",
    "sg:postcode":"8750",
    "sg:province":"Glarus",
    "wof:name":"Jenny Imovert Gmbh",
    "wof:placetype":"venue"
},
  "geometry": {"coordinates":[9.0656671524,47.0413551331],"type":"Point"}
}