{
  "type": "Feature",
  "properties": {
    "iso:country":"CH",
    "sg:address":"G\u00e4sslistieg 2",
    "sg:city":"Beringen",
    "sg:orig_category":"Reinigungsgewerbe",
    "sg:postcode":"8222",
    "sg:province":"Schaffhausen",
    "wof:name":"Gyr's Sauber-zauber",
    "wof:placetype":"venue"
},
  "geometry": {"coordinates":[8.5862598419,47.696598053],"type":"Point"}
}