{
  "type": "Feature",
  "properties": {
    "iso:country":"CH",
    "sg:address":"R\u00fctistrasse 25",
    "sg:city":"Th\u00f6rigen",
    "sg:orig_category":"Praxis f\u00fcr Atlaslogie",
    "sg:phone":"+41 62 961 03 63",
    "sg:postcode":"3367",
    "sg:province":"Bern",
    "wof:name":"Hugo Jordi Atlaslogie",
    "wof:placetype":"venue"
},
  "geometry": {"coordinates":[7.7268848419,47.1792373657],"type":"Point"}
}