{
  "type": "Feature",
  "properties": {
    "iso:country":"CH",
    "sg:address":"Seltisbergerstrasse 22",
    "sg:city":"Lupsingen",
    "sg:orig_category":"Maler U Glasergewerbe",
    "sg:postcode":"4419",
    "sg:province":"Basel-Landschaft",
    "wof:name":"Jenni M. Malergesch\u00e4ft",
    "wof:placetype":"venue"
},
  "geometry": {"coordinates":[7.6963210106,47.4459533691],"type":"Point"}
}