{
  "type": "Feature",
  "properties": {
    "iso:country":"CH",
    "sg:address":"Rue De L'ancienne Ecole 14",
    "sg:city":"Cudrefin",
    "sg:orig_category":"Gem\u00fcsebau",
    "sg:phone":"+41 26 677 10 38",
    "sg:postcode":"1588",
    "sg:province":"Vaud",
    "wof:name":"Maurice Pellet Maraicher",
    "wof:placetype":"venue"
},
  "geometry": {"coordinates":[7.0292038918,46.9477386475],"type":"Point"}
}