{
  "type": "Feature",
  "properties": {
    "iso:country":"CH",
    "sg:address":"Mellingerstrasse 1 5400 Baden. Postfach",
    "sg:city":"Baden",
    "sg:orig_category":"Unclassifiable Establishments",
    "sg:postcode":"5400",
    "sg:province":"Aargau",
    "wof:name":"Adin Ag Beteiligungen Usw",
    "wof:placetype":"venue"
},
  "geometry": {"coordinates":[8.3151817322,46.9913482666],"type":"Point"}
}