{
  "type": "Feature",
  "properties": {
    "iso:country":"CH",
    "sg:address":"Chemin Du Ruttet 9",
    "sg:city":"Gland",
    "sg:orig_category":"Kaminfeger Reinigungsgewerbe",
    "sg:phone":"+41 22 364 17 01",
    "sg:postcode":"1196",
    "sg:province":"Vaud",
    "wof:name":"Devaud Jean-louis",
    "wof:placetype":"venue"
},
  "geometry": {"coordinates":[6.2731781006,46.4225883484],"type":"Point"}
}