{
  "type": "Feature",
  "properties": {
    "iso:country":"CH",
    "sg:address":"Hauptstrasse 33",
    "sg:city":"Pratteln",
    "sg:orig_category":"Herstellung von Teppichen Verlegen von Fussboden",
    "sg:phone":"+41 61 821 17 77",
    "sg:postcode":"4133",
    "sg:province":"Basel-Landschaft",
    "wof:name":"Pfirter A. Bodenbel\u00e4ge",
    "wof:placetype":"venue"
},
  "geometry": {"coordinates":[7.6956439018,47.5171699524],"type":"Point"}
}