{
  "type": "Feature",
  "properties": {
    "iso:country":"CH",
    "sg:address":"Aeusserer Turmacker 11",
    "sg:city":"Halten",
    "sg:orig_category":"Planer f\u00fcr Alternativenergie and Solararchitektur Planer f\u00fcr Sonnenkollektoren",
    "sg:phone":"+41 31 872 03 07",
    "sg:postcode":"4566",
    "sg:province":"Solothurn",
    "wof:name":"Hans Jud Solartechnik",
    "wof:placetype":"venue"
},
  "geometry": {"coordinates":[7.3940701485,47.0571899414],"type":"Point"}
}