{
  "type": "Feature",
  "properties": {
    "iso:country":"CH",
    "sg:address":"Via Maderno",
    "sg:city":"Lugano",
    "sg:orig_category":"Pensionskassen",
    "sg:postcode":"6900",
    "sg:province":"Ticino",
    "wof:name":"Cassa Pensioni E Fondo Di Previdenza Per I Dipendenti Della Ditta Casa Vinicola Fabbroni Sa",
    "wof:placetype":"venue"
},
  "geometry": {"coordinates":[8.9555501938,46.0110664368],"type":"Point"}
}