{
  "type": "Feature",
  "properties": {
    "iso:country":"CH",
    "sg:address":"Rigistrasse 24",
    "sg:city":"Luzern",
    "sg:orig_category":"Erbringung von Dienstleistungen f\u00fcr Unternehmen",
    "sg:postcode":"6006",
    "sg:province":"Luzern",
    "wof:name":"Maeder Kathrine",
    "wof:placetype":"venue"
},
  "geometry": {"coordinates":[8.3220844269,47.0563926697],"type":"Point"}
}