{
  "type": "Feature",
  "properties": {
    "iso:country":"CH",
    "sg:address":"Rue Bautte 9 1200 Genf. Postfach",
    "sg:city":"Gen\u00e8ve",
    "sg:orig_category":"Stukkateurgewerbe, Gipserei U Verputzerei",
    "sg:postcode":"1201",
    "sg:province":"Gen\u00e8ve",
    "wof:name":"Jo\u00ebl Verduystert Sarl",
    "wof:placetype":"venue"
},
  "geometry": {"coordinates":[6.1396780014,46.2077598572],"type":"Point"}
}