{
  "type": "Feature",
  "properties": {
    "iso:country":"CH",
    "sg:address":"Rue Joseph-reichlen 5",
    "sg:city":"Fribourg",
    "sg:orig_category":"Sanit\u00e4r, Heizungs U L\u00fcftungsinstallation",
    "sg:postcode":"1700",
    "sg:province":"Fribourg",
    "wof:name":"Aebischer Jean-claude",
    "wof:placetype":"venue"
},
  "geometry": {"coordinates":[7.1523079872,46.7983932495],"type":"Point"}
}