{
  "type": "Feature",
  "properties": {
    "iso:country":"CH",
    "sg:address":"Rue Des Remparts 18",
    "sg:city":"Yverdon-les-bains",
    "sg:orig_category":"Grosshandel mit H\u00e4uten, Fellen U Leder",
    "sg:phone":"+41 24 425 84 23",
    "sg:postcode":"1400",
    "sg:province":"Vaud",
    "wof:name":"Jutzeler Alain",
    "wof:placetype":"venue"
},
  "geometry": {"coordinates":[6.639731884,46.780002594],"type":"Point"}
}