{
  "type": "Feature",
  "properties": {
    "iso:country":"CH",
    "sg:address":"Flugplatzstrasse 59b",
    "sg:city":"Grenchen",
    "sg:orig_category":"Herstellung von Metallerzeugnissen ohne Maschinenbau Luft U Raumfahrzeugbau",
    "sg:phone":"+41 32 653 83 10",
    "sg:postcode":"2540",
    "sg:province":"Solothurn",
    "wof:name":"Christen-airtech Ag",
    "wof:placetype":"venue"
},
  "geometry": {"coordinates":[7.3994011879,47.1928863525],"type":"Point"}
}