{
  "type": "Feature",
  "properties": {
    "iso:country":"CH",
    "sg:address":"Brauerstrasse 51",
    "sg:city":"Z\u00fcrich",
    "sg:orig_category":"Instandhaltung U Reparatur von Automobilen",
    "sg:phone":"+41 12413191",
    "sg:postcode":"8004",
    "sg:province":"Z\u00fcrich",
    "wof:name":"Kreis 4 Garage Autohandels, Service, Reparaturgarage Usw",
    "wof:placetype":"venue"
},
  "geometry": {"coordinates":[8.5258598328,47.3782615662],"type":"Point"}
}