{
  "type": "Feature",
  "properties": {
    "iso:country":"CH",
    "sg:address":"Gemsweg 2",
    "sg:city":"Chur",
    "sg:orig_category":"Tierarztpraxis",
    "sg:phone":"+41 34 437 19 31",
    "sg:postcode":"7000",
    "sg:province":"Graubunden",
    "wof:name":"Dr. Med. Vet. Rita Zgraggen Tier\u00e4rztin",
    "wof:placetype":"venue"
},
  "geometry": {"coordinates":[7.7976531982,47.0435676575],"type":"Point"}
}