{
  "type": "Feature",
  "properties": {
    "iso:country":"CH",
    "sg:address":"Place Centrale 49 2500 Biel/bienne. Postfach",
    "sg:city":"Biel/bienne",
    "sg:orig_category":"Museen",
    "sg:postcode":"2500",
    "sg:province":"Bern",
    "wof:name":"Fondation Des Amis De La Tour Historique De La Tour-de-tr\u00eame",
    "wof:placetype":"venue"
},
  "geometry": {"coordinates":[7.0638518333,46.607257843],"type":"Point"}
}