{
  "type": "Feature",
  "properties": {
    "iso:country":"CH",
    "sg:address":"Rigistrasse 6",
    "sg:city":"Zug",
    "sg:orig_category":"Herstellung von Erzeugnissen aus Beton, Gips U Zement Herstellung von Werkzeugen",
    "sg:phone":"+41 41 710 90 13",
    "sg:postcode":"6300",
    "sg:province":"Zug",
    "wof:name":"Jiffy Products Internat.ltd Gartenbaubedarfsartikel",
    "wof:placetype":"venue"
},
  "geometry": {"coordinates":[8.5147066116,47.1699905396],"type":"Point"}
}