{
  "type": "Feature",
  "properties": {
    "iso:country":"CH",
    "sg:address":"Z\u00fcrichstr. 9",
    "sg:city":"Zollikofen",
    "sg:classifiers":[
        {
            "category":"Manufacturing",
            "subcategory":"Metals",
            "type":"Manufacturing & Wholesale Goods"
        }
    ],
    "sg:phone":"+41 31 910 31 11",
    "sg:postcode":"3052",
    "sg:province":"Bern",
    "sg:tags":[
        "metallurgy",
        "metalworking",
        "processing"
    ],
    "wof:name":"Fromalp Ag",
    "wof:placetype":"venue"
},
  "geometry": {"coordinates":[7.4638910294,47.0055084229],"type":"Point"}
}