{
  "type": "Feature",
  "properties": {
    "iso:country":"CH",
    "sg:address":"Belchenweg 2",
    "sg:city":"Safenwil",
    "sg:orig_category":"Organisationen des Gesundheitswesen",
    "sg:phone":"+41 62 797 91 30",
    "sg:postcode":"5745",
    "sg:province":"Aargau",
    "wof:name":"Samariterverein Safenwil",
    "wof:placetype":"venue"
},
  "geometry": {"coordinates":[7.9699659348,47.3186225891],"type":"Point"}
}