{
  "type": "Feature",
  "properties": {
    "iso:country":"CH",
    "sg:address":"Routes Des Alouettes 2b",
    "sg:city":"Givisiez",
    "sg:orig_category":"Sportvereine Sch\u00fctzen",
    "sg:postcode":"1762",
    "sg:province":"Fribourg",
    "wof:name":"St\u00e9 De Tir De Marly",
    "wof:placetype":"venue"
},
  "geometry": {"coordinates":[7.131072998,46.8139228821],"type":"Point"}
}