{
  "type": "Feature",
  "properties": {
    "iso:country":"CH",
    "sg:address":"Av. Cardinal-mermillod 36",
    "sg:city":"Carouge",
    "sg:classifiers":[
        {
            "category":"Professional",
            "subcategory":"Art Services",
            "type":"Services"
        }
    ],
    "sg:phone":"+41 22 307 02 50",
    "sg:postcode":"1227",
    "sg:province":"Gen\u00e8ve",
    "sg:tags":[
        "design",
        "event"
    ],
    "wof:name":"Xl Marketing Sa",
    "wof:placetype":"venue"
},
  "geometry": {"coordinates":[6.1434750557,46.1856079102],"type":"Point"}
}