{
  "type": "Feature",
  "properties": {
    "iso:country":"CH",
    "sg:address":"Sulgenauweg 22 3007 Bern. Postfach",
    "sg:city":"Bern",
    "sg:orig_category":"Sonstige mit der Informatik verbundene T\u00e4tigkeiten",
    "sg:postcode":"3005",
    "sg:province":"Bern",
    "wof:name":"Personal Computer, Rozumny S.a. El. Ing. Htl Computer U Informatik; Ausbildung, Beratung, Software-herstellung Usw",
    "wof:placetype":"venue"
},
  "geometry": {"coordinates":[7.4346108437,46.9384803772],"type":"Point"}
}