{
  "type": "Feature",
  "properties": {
    "iso:country":"CH",
    "sg:address":"Stationsstrasse 12 3098 K\u00f6niz. Postfach 171",
    "sg:city":"K\u00f6niz",
    "sg:orig_category":"Bauingenieurb\u00fcros allgemein Sonstige pers\u00f6nliche Dienstleistungen",
    "sg:phone":"+41 41 410 30 01",
    "sg:postcode":"3098",
    "sg:province":"Bern",
    "wof:name":"Steiger Baucontrol Ag",
    "wof:placetype":"venue"
},
  "geometry": {"coordinates":[8.297927,47.05479],"type":"Point"}
}