{
  "type": "Feature",
  "properties": {
    "addr:full":"F\u00fcrstenlandstrasse 96 9014 St. Gallen 14 Zust. Postfach 9014 St. Gallen Zust 14",
    "addr:housenumber":"96;14;14",
    "addr:postcode":"9014;9014",
    "addr:street":"Fuerstenlandstrasse;Gallen;Postfach",
    "iso:country":"CH",
    "sg:address":"F\u00fcrstenlandstrasse 96 9014 St. Gallen 14 Zust. Postfach 9014 St. Gallen",
    "sg:city":"Zust",
    "sg:orig_category":"Architektur U Ingenieurb\u00fcros",
    "sg:phone":"+41 71 274 57 37",
    "sg:postcode":"14",
    "wof:name":"H.j. Schmid",
    "wof:placetype":"venue"
},
  "geometry": {"coordinates":[9.33633,47.40992],"type":"Point"}
}