{
  "type": "Feature",
  "properties": {
    "iso:country":"CH",
    "sg:address":"Cuno Amiet Strasse 21",
    "sg:city":"Herzogenbuchsee",
    "sg:orig_category":"Sportvereine Turnen",
    "sg:phone":"+41 62 961 70 14",
    "sg:postcode":"3360",
    "sg:province":"Bern",
    "wof:name":"Turnverein Stv Herzogenbuchsee",
    "wof:placetype":"venue"
},
  "geometry": {"coordinates":[7.7022371292,47.1838493347],"type":"Point"}
}