{
  "type": "Feature",
  "properties": {
    "iso:country":"CH",
    "sg:address":"Langgr\u00fctstrasse 172",
    "sg:city":"Z\u00fcrich",
    "sg:orig_category":"Wirtschaftspr\u00fcfung, Steuerberatung U Treuhand",
    "sg:phone":"+41 21 944 30 54",
    "sg:postcode":"8047",
    "sg:province":"Z\u00fcrich",
    "wof:name":"Office De Contr\u00f4le & D'expertise Sa",
    "wof:placetype":"venue"
},
  "geometry": {"coordinates":[6.8568081856,46.4532928467],"type":"Point"}
}