{
  "type": "Feature",
  "properties": {
    "iso:country":"CH",
    "sg:address":"Aarestrasse 40 3600 Thun. Postfach 1476",
    "sg:city":"Thun",
    "sg:orig_category":"Detailhandel mit Brillen U anderen Sehhilfen Fachdetailhandel in Verkaufsr\u00e4umen",
    "sg:phone":"+41 33 222 38 63",
    "sg:postcode":"3601",
    "sg:province":"Bern",
    "wof:name":"Wittwer Optik",
    "wof:placetype":"venue"
},
  "geometry": {"coordinates":[7.629176,46.756592],"type":"Point"}
}