{
  "type": "Feature",
  "properties": {
    "iso:country":"CH",
    "sg:address":"Ostring 52",
    "sg:city":"Regensdorf",
    "sg:orig_category":"Grosshandel mit Sportartikeln",
    "sg:phone":"+41 16872590",
    "sg:postcode":"8105",
    "sg:province":"Z\u00fcrich",
    "wof:name":"Alba-trading E. Albericci Ag Waffen & Zubeh\u00f6r",
    "wof:placetype":"venue"
},
  "geometry": {"coordinates":[8.7327060699,47.2033500671],"type":"Point"}
}