{
  "type": "Feature",
  "properties": {
    "iso:country":"CH",
    "sg:address":"Corso Elvezia 10",
    "sg:city":"Lugano",
    "sg:orig_category":"Softwareentwicklung U beratung",
    "sg:phone":"+41 41 720 02 70",
    "sg:postcode":"6900",
    "sg:province":"Ticino",
    "wof:name":"Verisoft Ag",
    "wof:placetype":"venue"
},
  "geometry": {"coordinates":[8.5085077286,47.1431846619],"type":"Point"}
}