{
  "type": "Feature",
  "properties": {
    "iso:country":"CH",
    "sg:address":"Kirchbergstrasse 68",
    "sg:city":"K\u00fcttigen",
    "sg:orig_category":"Bicycle Generators",
    "sg:phone":"+41 62 827 48 27",
    "sg:postcode":"5024",
    "sg:province":"Aargau",
    "wof:name":"Dynosys Ag",
    "wof:placetype":"venue"
},
  "geometry": {"coordinates":[8.057941,47.411034],"type":"Point"}
}