{
  "type": "Feature",
  "properties": {
    "addr:full":"Hinterdorfstrasse 3 Fischbach-g\u00f6slikon Aargau 5525",
    "addr:housenumber":"3",
    "addr:postcode":"5525",
    "addr:street":"Hinterdorfstrasse",
    "iso:country":"CH",
    "sg:address":"Hinterdorfstrasse 3",
    "sg:city":"Fischbach-g\u00f6slikon",
    "sg:orig_category":"Bauschreinerei Herstellung von Konstruktionsteilen, Fertigbauteilen U Ausbauelementen aus Holz",
    "sg:phone":"+41 56 621 25 25",
    "sg:postcode":"5525",
    "sg:province":"Aargau",
    "wof:name":"Richner M. + R. Gmbh",
    "wof:placetype":"venue"
},
  "geometry": {"coordinates":[8.304133,47.373486],"type":"Point"}
}