{
  "type": "Feature",
  "properties": {
    "iso:country":"CH",
    "sg:address":"Salomon Landoltstrasse 3",
    "sg:city":"Andelfingen",
    "sg:orig_category":"Allgemeinbildende weiterf\u00fchrende Schulen",
    "sg:postcode":"8450",
    "sg:province":"Z\u00fcrich",
    "wof:name":"Akademie F\u00fcr Lerntechnik Und Sch\u00fclerf\u00f6rderung L.u.s. Gmbh",
    "wof:placetype":"venue"
},
  "geometry": {"coordinates":[8.67716,47.597389],"type":"Point"}
}