{
  "type": "Feature",
  "properties": {
    "iso:country":"CH",
    "sg:address":"Grand-rue 87 2720 Tramelan Case Postale 324",
    "sg:city":"Tramelan",
    "sg:orig_category":"Instandhaltung U Reparatur von Automobilen",
    "sg:phone":"+41 32 486 96 00",
    "sg:postcode":"2720",
    "sg:province":"Bern",
    "wof:name":"Lerch & Cie",
    "wof:placetype":"venue"
},
  "geometry": {"coordinates":[7.1079502106,47.2237091064],"type":"Point"}
}