{
  "type": "Feature",
  "properties": {
    "iso:country":"CH",
    "sg:address":"Im Rainacker 17",
    "sg:city":"Witterswil",
    "sg:orig_category":"Elektrizit\u00e4tsversorgung",
    "sg:phone":"+41 61 723 00 03",
    "sg:postcode":"4108",
    "sg:province":"Solothurn",
    "wof:name":"Herger Ren\u00e9 Umwelttechnik",
    "wof:placetype":"venue"
},
  "geometry": {"coordinates":[7.5189161301,47.4861831665],"type":"Point"}
}