{
  "type": "Feature",
  "properties": {
    "iso:country":"CH",
    "sg:address":"Luisenstrasse 21",
    "sg:city":"Z\u00fcrich",
    "sg:orig_category":"Grafikateliers, Design Siebdruck",
    "sg:phone":"+41 12730777",
    "sg:postcode":"8005",
    "sg:province":"Z\u00fcrich",
    "wof:name":"Peter Schweizer Beschriftungen Siebdruck",
    "wof:placetype":"venue"
},
  "geometry": {"coordinates":[8.5291795731,47.3833885193],"type":"Point"}
}