{
  "type": "Feature",
  "properties": {
    "iso:country":"CH",
    "sg:address":"Moli\u00e8re Rue De La 22 2800 Del\u00e9mont. Postfach",
    "sg:city":"Delsberg",
    "sg:orig_category":"Sonstiges Versicherungsgewerbe",
    "sg:postcode":"2800",
    "sg:province":"Jura",
    "wof:name":"Vis Insurance Group Ag",
    "wof:placetype":"venue"
},
  "geometry": {"coordinates":[8.6399774551,47.4104652405],"type":"Point"}
}