{
  "type": "Feature",
  "properties": {
    "iso:country":"CH",
    "sg:address":"1784",
    "sg:city":"Wallenried",
    "sg:orig_category":"Sportvereine Sch\u00fctzen",
    "sg:postcode":"1784",
    "sg:province":"Fribourg",
    "wof:name":"St\u00e9 De Tir",
    "wof:placetype":"venue"
},
  "geometry": {"coordinates":[6.6260199547,46.5942802429],"type":"Point"}
}