{
  "type": "Feature",
  "properties": {
    "iso:country":"CH",
    "sg:address":"S\u00e4liring 5 4656 Starrkirch-wil. Postfach 433",
    "sg:city":"Hombrechtikon",
    "sg:orig_category":"Herstellung von Anstrichmitteln, Druckfarben U Kitten",
    "sg:phone":"+41 32 913 08 33",
    "sg:postcode":"8634",
    "sg:province":"Z\u00fcrich",
    "wof:name":"Beffa E. Sa",
    "wof:placetype":"venue"
},
  "geometry": {"coordinates":[6.8299050331,47.102809906],"type":"Point"}
}