{
  "type": "Feature",
  "properties": {
    "iso:country":"CH",
    "sg:address":"Rebenweg 8",
    "sg:city":"H\u00fcnenberg",
    "sg:orig_category":"Kosmetikinstitute",
    "sg:phone":"+41 62 823 26 06",
    "sg:postcode":"6331",
    "sg:province":"Zug",
    "wof:name":"Beatrice Bitterlin Kosmetikinstitut",
    "wof:placetype":"venue"
},
  "geometry": {"coordinates":[8.0709733963,47.4006233215],"type":"Point"}
}