{
  "type": "Feature",
  "properties": {
    "iso:country":"CH",
    "sg:address":"R\u00f6ven 21",
    "sg:city":"Zernez",
    "sg:orig_category":"Naturheil\u00e4rzte and Heilpraktiker",
    "sg:phone":"+41 71 750 08 50",
    "sg:postcode":"7530",
    "sg:province":"Graubunden",
    "wof:name":"Reinhilde Heinzle Naturheilpraxis",
    "wof:placetype":"venue"
},
  "geometry": {"coordinates":[9.5431070328,47.378364563],"type":"Point"}
}