{
  "type": "Feature",
  "properties": {
    "iso:country":"CH",
    "sg:address":"Les Rochers",
    "sg:city":"Chandolin-savi\u00e8se",
    "sg:orig_category":"Grosshandel mit Holz U Baustoffen",
    "sg:phone":"+41 79 219 27 69",
    "sg:postcode":"1965",
    "sg:province":"Valais",
    "wof:name":"Dubuis St\u00e9phane Gypserie-peinture, Papiers-peints, Isolation Ext\u00e9rieure",
    "wof:placetype":"venue"
},
  "geometry": {"coordinates":[7.3521699905,46.261756897],"type":"Point"}
}