{
  "type": "Feature",
  "properties": {
    "iso:country":"CH",
    "sg:address":"Luegislandstrasse 173",
    "sg:city":"Z\u00fcrich",
    "sg:orig_category":"Schwimmb\u00e4der",
    "sg:phone":"+41 13216145",
    "sg:postcode":"8051",
    "sg:province":"Z\u00fcrich",
    "wof:name":"Schulhaus Aubr\u00fccke Betriebsleitung Hallenbad",
    "wof:placetype":"venue"
},
  "geometry": {"coordinates":[8.5712566376,47.4093856812],"type":"Point"}
}