{
  "type": "Feature",
  "properties": {
    "iso:country":"CH",
    "sg:address":"Via Cantonale",
    "sg:city":"Mezzovico",
    "sg:classifiers":[
        {
            "category":"Government",
            "subcategory":"Department Of Motor Vehicles",
            "type":"Public Place"
        }
    ],
    "sg:phone":"+41 91 946 34 54",
    "sg:postcode":"6805",
    "sg:province":"Ticino",
    "sg:tags":[
        "dyestuff",
        "dispersion"
    ],
    "wof:name":"Chemiplast S.a.",
    "wof:placetype":"venue"
},
  "geometry": {"coordinates":[8.9198827744,46.0879859924],"type":"Point"}
}