{
  "type": "Feature",
  "properties": {
    "iso:country":"CH",
    "sg:address":"Dammweg 7 3800 Interlaken. Postfach",
    "sg:city":"Interlaken",
    "sg:orig_category":"Unclassifiable Establishments",
    "sg:postcode":"3800",
    "sg:province":"Bern",
    "wof:name":"Alpenet Gmbh Dienstleistungen Im Bereich Des Webdesign U. Der Edv. Hard- U. Software; Handel Usw",
    "wof:placetype":"venue"
},
  "geometry": {"coordinates":[7.8758020401,46.6921005249],"type":"Point"}
}