{
  "type": "Feature",
  "properties": {
    "iso:country":"CH",
    "sg:address":"Unterstadt 37",
    "sg:city":"Schaffhausen",
    "sg:orig_category":"Detailhandel mit Uhren U Schmuck Reparatur von Uhren U Schmuck",
    "sg:phone":"+41 61 641 40 40",
    "sg:postcode":"8200",
    "sg:province":"Schaffhausen",
    "wof:name":"Armin Zwahl Uhren-bijouterie",
    "wof:placetype":"venue"
},
  "geometry": {"coordinates":[7.6538748741,47.5840110779],"type":"Point"}
}