{
  "type": "Feature",
  "properties": {
    "iso:country":"CH",
    "sg:address":"Margrethenstrasse 6",
    "sg:city":"Ballwil",
    "sg:orig_category":"Herstellung von Metallerzeugnissen ohne Maschinenbau Herstellung von Verbrennungsmotoren U Turbinen ",
    "sg:phone":"+41 41 449 77 77",
    "sg:postcode":"6275",
    "sg:province":"Luzern",
    "wof:name":"F. Gehrig Ag,haushaltapparate Reinigungs-& Sp\u00fclautomaten",
    "wof:placetype":"venue"
},
  "geometry": {"coordinates":[8.3186616898,47.1521530151],"type":"Point"}
}