{
  "type": "Feature",
  "properties": {
    "iso:country":"CH",
    "sg:address":"6375",
    "sg:city":"Beckenried",
    "sg:orig_category":"Steuer\u00e4mter",
    "sg:phone":"+41 55 442 11 91",
    "sg:postcode":"6375",
    "sg:province":"Nidwalden",
    "wof:name":"Steueramt",
    "wof:placetype":"venue"
},
  "geometry": {"coordinates":[8.8508253098,47.1924476624],"type":"Point"}
}