{
  "type": "Feature",
  "properties": {
    "iso:country":"CH",
    "sg:address":"Place De T\u00fcbingen 5",
    "sg:city":"Monthey",
    "sg:orig_category":"Herstellung von homogenisierten U di\u00e4tetischen Nahrungsmitteln Kosmetikinstitute",
    "sg:phone":"+41 24 471 77 27",
    "sg:postcode":"1870",
    "sg:province":"Valais",
    "wof:name":"Esth\u00e9tique & Di\u00e9t\u00e9tique Delacoste Sa",
    "wof:placetype":"venue"
},
  "geometry": {"coordinates":[6.9474520683,46.2524032593],"type":"Point"}
}