{
  "type": "Feature",
  "properties": {
    "iso:country":"CH",
    "sg:address":"Burggasse 9",
    "sg:city":"Weisslingen",
    "sg:orig_category":"Non-Classified Establishments",
    "sg:phone":"+41 52 384 25 90",
    "sg:postcode":"8484",
    "sg:province":"Z\u00fcrich",
    "wof:name":"Weiss Datahelp",
    "wof:placetype":"venue"
},
  "geometry": {"coordinates":[8.7619428635,47.4330406189],"type":"Point"}
}