{
  "type": "Feature",
  "properties": {
    "iso:country":"CH",
    "sg:address":"Dorf 6231 Schlierbach. Postfach",
    "sg:city":"Schlierbach",
    "sg:orig_category":"Landesverteidigung, Sozialversicherung \u00d6ffentliche Verwaltung",
    "sg:phone":"+41 41 933 13 07",
    "sg:postcode":"6231",
    "sg:province":"Luzern",
    "wof:name":"Zivilschutzstelle Schlierbach",
    "wof:placetype":"venue"
},
  "geometry": {"coordinates":[8.1114807129,47.2239532471],"type":"Point"}
}