{
  "type": "Feature",
  "properties": {
    "iso:country":"CH",
    "sg:address":"1967",
    "sg:city":"Bramois",
    "sg:orig_category":"Detailhandel mit Fleisch U Fleischwaren",
    "sg:phone":"+41 27 203 11 42",
    "sg:postcode":"1967",
    "sg:province":"Valais",
    "wof:name":"Meyer, Peter.",
    "wof:placetype":"venue"
},
  "geometry": {"coordinates":[7.4026799202,46.2301216125],"type":"Point"}
}