{
  "type": "Feature",
  "properties": {
    "iso:country":"CH",
    "sg:address":"Via Cantonale",
    "sg:city":"Mezzovico",
    "sg:orig_category":"Fountain-Type Drawing Pens",
    "sg:phone":"+41 79 620 47 68",
    "sg:postcode":"6805",
    "sg:province":"Ticino",
    "wof:name":"Cigi Trading Sa",
    "wof:placetype":"venue"
},
  "geometry": {"coordinates":[8.9198827744,46.0879859924],"type":"Point"}
}