{
  "type": "Feature",
  "properties": {
    "addr:full":"Promenadenstrasse 17 8200 Schaffhausen. Postfach 1125 Schaffhausen Schaffhausen 8201",
    "addr:housenumber":"17",
    "addr:postcode":"8200 schaffhausen.;1125;8201",
    "addr:street":"Promenadenstrasse;Postfach",
    "iso:country":"CH",
    "sg:address":"Promenadenstrasse 17 8200 Schaffhausen. Postfach 1125",
    "sg:city":"Schaffhausen",
    "sg:orig_category":"Architektur U Ingenieurb\u00fcros Sonstiger Grosshandel",
    "sg:phone":"+41 52 630 08 08",
    "sg:postcode":"8201",
    "sg:province":"Schaffhausen",
    "wof:name":"Plan Marine",
    "wof:placetype":"venue"
},
  "geometry": {"coordinates":[8.628141,47.694695],"type":"Point"}
}