{
  "type": "Feature",
  "properties": {
    "addr:full":"2830 Courrendlin Jura 2830",
    "addr:housenumber":"2830",
    "addr:postcode":"2830",
    "addr:street":"Courrendlin Jura",
    "iso:country":"CH",
    "sg:address":"2830",
    "sg:city":"Courrendlin",
    "sg:orig_category":"Bezirks, Sekundar, Realschulen, Oberstufe der Primarschulen",
    "sg:phone":"+41 32 931 18 37",
    "sg:postcode":"2830",
    "sg:province":"Jura",
    "wof:name":"Ecole Secondaire",
    "wof:placetype":"venue"
},
  "geometry": {"coordinates":[6.743925,47.055267],"type":"Point"}
}