{
  "type": "Feature",
  "properties": {
    "iso:country":"CH",
    "sg:address":"Im Oberen Boden 31",
    "sg:city":"Z\u00fcrich",
    "sg:orig_category":"Sportvereine Ballsport Tennis",
    "sg:phone":"+41 13410722",
    "sg:postcode":"8049",
    "sg:province":"Z\u00fcrich",
    "wof:name":"Tennisclub H\u00f6ngg",
    "wof:placetype":"venue"
},
  "geometry": {"coordinates":[8.4791603088,47.4162597656],"type":"Point"}
}