{
  "type": "Feature",
  "properties": {
    "iso:country":"CH",
    "sg:address":"Winterhaldenstrasse 60a",
    "sg:city":"Turgi",
    "sg:orig_category":"Handelsvermittlung U Grosshandel Herstellung von Pumpen U Kompressoren",
    "sg:phone":"+41 56 223 22 64",
    "sg:postcode":"5300",
    "sg:province":"Aargau",
    "wof:name":"Grob-airatec Ag",
    "wof:placetype":"venue"
},
  "geometry": {"coordinates":[8.2539825439,47.4889640808],"type":"Point"}
}