{
  "type": "Feature",
  "properties": {
    "iso:country":"CH",
    "sg:address":"Knobelstrasse 12",
    "sg:city":"Anglikon",
    "sg:orig_category":"Detailhandel mit Getr\u00e4nken",
    "sg:phone":"+41 56 622 30 50",
    "sg:postcode":"5611",
    "sg:province":"Aargau",
    "wof:name":"Hans Engel Most & Mineralwasser",
    "wof:placetype":"venue"
},
  "geometry": {"coordinates":[8.2643213272,47.3659362793],"type":"Point"}
}