{
  "type": "Feature",
  "properties": {
    "iso:country":"CH",
    "sg:address":"Weiningerstrasse 1 8103 Unterengstringen. Postfach",
    "sg:city":"Unterengstringen",
    "sg:orig_category":"Autogaragen",
    "sg:phone":"+41 79 400 40 06",
    "sg:postcode":"8103",
    "sg:province":"Z\u00fcrich",
    "wof:name":"Ernst Stucki Autogarage",
    "wof:placetype":"venue"
},
  "geometry": {"coordinates":[8.447595,47.408539],"type":"Point"}
}