{
  "type": "Feature",
  "properties": {
    "iso:country":"CH",
    "sg:address":"G\u00fcrtelstrasse 24 7000 Chur. Postfach",
    "sg:city":"Chur",
    "sg:orig_category":"Sonstige Institutionen des Sozialwesens ohne Beherbergung",
    "sg:phone":"+41 81 284 80 75",
    "sg:postcode":"7001",
    "sg:province":"Graubunden",
    "wof:name":"Frauenzentrale Graub\u00fcnden",
    "wof:placetype":"venue"
},
  "geometry": {"coordinates":[9.5271730423,46.8534240723],"type":"Point"}
}