{
  "type": "Feature",
  "properties": {
    "iso:country":"CH",
    "sg:address":"Hauptstrasse 39",
    "sg:city":"Kreuzlingen",
    "sg:orig_category":"Verkehrs- and Tourismusb\u00fcros",
    "sg:phone":"+41 71 672 38 40",
    "sg:postcode":"8280",
    "sg:province":"Thurgau",
    "wof:name":"Verkehrsverein & Verkehrsb\u00fcro",
    "wof:placetype":"venue"
},
  "geometry": {"coordinates":[9.1746692657,47.6502876282],"type":"Point"}
}