{
  "type": "Feature",
  "properties": {
    "iso:country":"CH",
    "sg:address":"Hauptstrasse 22",
    "sg:city":"R\u00fcttenen",
    "sg:orig_category":"Nationale Postdienste",
    "sg:phone":"+41 32 622 25 05",
    "sg:postcode":"4522",
    "sg:province":"Solothurn",
    "wof:name":"Die Schweizerische Post",
    "wof:placetype":"venue"
},
  "geometry": {"coordinates":[7.5287837982,47.2293586731],"type":"Point"}
}