{
  "type": "Feature",
  "properties": {
    "iso:country":"CH",
    "sg:address":"Lochezen",
    "sg:city":"Walenstadt",
    "sg:orig_category":"Gewinnung von Kies U Sand Herstellung von sonstigen Produkten aus nichtmetallischen Mineralien",
    "sg:phone":"+41 81 302 40 64",
    "sg:postcode":"8880",
    "sg:province":"St. Gallen",
    "wof:name":"See Kies Ag",
    "wof:placetype":"venue"
},
  "geometry": {"coordinates":[9.2932548523,47.1286315918],"type":"Point"}
}