{
  "type": "Feature",
  "properties": {
    "addr:full":"C\u00e4cilienstrasse 21 Bern Bern 3007",
    "addr:housenumber":"21",
    "addr:postcode":"3007",
    "addr:street":"Caecilienstrasse",
    "iso:country":"CH",
    "sg:address":"C\u00e4cilienstrasse 21",
    "sg:city":"Bern",
    "sg:orig_category":"Bauingenieurb\u00fcros Heizung L\u00fcftung Klima Herstellung von k\u00e4lte U lufttechnischen Erzeugnissen f\u00fcr gew",
    "sg:phone":"+41 61 991 09 72",
    "sg:postcode":"3007",
    "sg:province":"Bern",
    "wof:name":"Ls Gmbh L\u00fcftungs-systeme",
    "wof:placetype":"venue"
},
  "geometry": {"coordinates":[7.427623,46.940849],"type":"Point"}
}