{
  "type": "Feature",
  "properties": {
    "iso:country":"CH",
    "sg:address":"Dorfstrasse 18 5102 Rupperswil. Postfach 135",
    "sg:city":"Rupperswil",
    "sg:orig_category":"Maschinenbau",
    "sg:phone":"+41 79 448 71 72",
    "sg:postcode":"5102",
    "sg:province":"Aargau",
    "wof:name":"Georges Hediger Gmbh, Montagen Und Service",
    "wof:placetype":"venue"
},
  "geometry": {"coordinates":[8.1284828186,47.4006767273],"type":"Point"}
}