{
  "type": "Feature",
  "properties": {
    "iso:country":"CH",
    "sg:address":"Tostelweg 7a",
    "sg:city":"Siebnen",
    "sg:orig_category":"Vereine Musik/Blasmusik",
    "sg:phone":"+41 55 440 10 68",
    "sg:postcode":"8854",
    "sg:province":"Schwyz",
    "wof:name":"Harmonie Musikverein Lachen",
    "wof:placetype":"venue"
},
  "geometry": {"coordinates":[8.8916397095,47.1823272705],"type":"Point"}
}