{
  "type": "Feature",
  "properties": {
    "iso:country":"CH",
    "sg:address":"Sch\u00f6neggstrasse 13",
    "sg:city":"R\u00fcti",
    "sg:classifiers":[
        {
            "category":"Manufacturing",
            "subcategory":"Glass & Minerals",
            "type":"Manufacturing & Wholesale Goods"
        }
    ],
    "sg:phone":"+41 55 251 20 10",
    "sg:postcode":"8630",
    "sg:province":"Z\u00fcrich",
    "sg:tags":[
        "measuring",
        "fibre",
        "optic",
        "cable",
        "tester",
        "equipment"
    ],
    "wof:name":"Acet Ag",
    "wof:placetype":"venue"
},
  "geometry": {"coordinates":[8.8458251953,47.2594299316],"type":"Point"}
}