{
  "type": "Feature",
  "properties": {
    "iso:country":"CH",
    "sg:address":"Gsteigstrasse 41",
    "sg:city":"Z\u00fcrich",
    "sg:orig_category":"Zimmerei, Dachdeckerei, Bauspenglerei U Abdichtung",
    "sg:phone":"+41 13417678",
    "sg:postcode":"8049",
    "sg:province":"Z\u00fcrich",
    "wof:name":"Frehner-schlatter Hans Rudolf Dachdeckerarbeiten",
    "wof:placetype":"venue"
},
  "geometry": {"coordinates":[8.5025854111,47.4034233093],"type":"Point"}
}