{
  "type": "Feature",
  "properties": {
    "iso:country":"CH",
    "sg:address":"Herrenmatt 12",
    "sg:city":"Hochwald",
    "sg:orig_category":"Sonstige pers\u00f6nliche Dienstleistungen",
    "sg:phone":"+41 61 751 60 60",
    "sg:postcode":"4146",
    "sg:province":"Solothurn",
    "wof:name":"Schmid Margrit, Image Und Pers\u00f6nlichkeitsberatung",
    "wof:placetype":"venue"
},
  "geometry": {"coordinates":[7.6237831116,47.4570083618],"type":"Point"}
}