{
  "type": "Feature",
  "properties": {
    "iso:country":"CH",
    "sg:address":"Kirchgasse",
    "sg:city":"Baar",
    "sg:orig_category":"Wasserversorgung",
    "sg:postcode":"6340",
    "sg:province":"Zug",
    "wof:name":"Wasserversorgungs-genossenschaft Allenwinden",
    "wof:placetype":"venue"
},
  "geometry": {"coordinates":[8.522026062,47.1933097839],"type":"Point"}
}