{
  "type": "Feature",
  "properties": {
    "iso:country":"CH",
    "sg:address":"Avenue Mercier De Molin 6",
    "sg:city":"Sierre",
    "sg:orig_category":"Detailhandel mit Geschenkartikeln U Souvenirs Herstellung von W\u00e4sche",
    "sg:phone":"+41 27 456 32 00",
    "sg:postcode":"3960",
    "sg:province":"Valais",
    "wof:name":"Rosy Marzollini Boutique Tat-too",
    "wof:placetype":"venue"
},
  "geometry": {"coordinates":[7.5282759666,46.2927284241],"type":"Point"}
}