{
  "type": "Feature",
  "properties": {
    "iso:country":"CH",
    "sg:address":"Sch\u00e4ppi-n\u00e4fstrasse 9",
    "sg:city":"Oberrieden",
    "sg:orig_category":"Sanit\u00e4r, Heizungs U L\u00fcftungsinstallation",
    "sg:phone":"+41 41 637 01 62",
    "sg:postcode":"8942",
    "sg:province":"Z\u00fcrich",
    "wof:name":"En-es-te Engelberg Ag",
    "wof:placetype":"venue"
},
  "geometry": {"coordinates":[8.5773305893,47.2749061584],"type":"Point"}
}