{
  "type": "Feature",
  "properties": {
    "iso:country":"CH",
    "sg:address":"1993",
    "sg:city":"Veysonnaz",
    "sg:orig_category":"Schulpflegen",
    "sg:postcode":"1993",
    "sg:province":"Valais",
    "wof:name":"Commission Scolaire De L'\u00e9cole Primaire",
    "wof:placetype":"venue"
},
  "geometry": {"coordinates":[7.3388028145,46.1959838867],"type":"Point"}
}