{
  "type": "Feature",
  "properties": {
    "iso:country":"CH",
    "sg:address":"Schlachthofstrasse 55",
    "sg:city":"Basel",
    "sg:orig_category":"Detailhandel mit Fleisch U Fleischwaren",
    "sg:phone":"+41 61 311 42 81",
    "sg:postcode":"4056",
    "sg:province":"Basel-Stadt",
    "wof:name":"Eiche Metzgerei & Party-service Ag",
    "wof:placetype":"venue"
},
  "geometry": {"coordinates":[7.5662817955,47.5761756897],"type":"Point"}
}