{
  "type": "Feature",
  "properties": {
    "iso:country":"CH",
    "sg:address":"Atlantis Center",
    "sg:city":"Vuadens",
    "sg:orig_category":"Herstellung von Konstruktionsteilen, Fertigbauteilen U Ausbauelementen aus Holz",
    "sg:phone":"+41 21 781 19 38",
    "sg:postcode":"1628",
    "sg:province":"Fribourg",
    "wof:name":"Topaz, Espaces & Vivre S\u00e0rl",
    "wof:placetype":"venue"
},
  "geometry": {"coordinates":[6.7695250511,46.5411186218],"type":"Point"}
}