{
  "type": "Feature",
  "properties": {
    "iso:country":"CH",
    "sg:address":"M\u00e4rtplatz 3",
    "sg:city":"Effretikon",
    "sg:orig_category":"Grosshandel mit M\u00f6beln, Wohnbedarf, Teppichen U Bodenbel\u00e4gen Herstellung von Schmuck, Gold U Silbers",
    "sg:phone":"+41 52 343 19 18",
    "sg:postcode":"8307",
    "sg:province":"Z\u00fcrich",
    "wof:name":"Effi Goldschmiede Ag",
    "wof:placetype":"venue"
},
  "geometry": {"coordinates":[8.6861228943,47.4281806946],"type":"Point"}
}