{
  "type": "Feature",
  "properties": {
    "iso:country":"CH",
    "sg:address":"St.urbangasse 4",
    "sg:city":"Z\u00fcrich",
    "sg:orig_category":"Arztpraxen",
    "sg:phone":"+41 41 854 20 80",
    "sg:postcode":"8001",
    "sg:province":"Z\u00fcrich",
    "wof:name":"Dr.med.benno Eggenschwiler Arzt F.allgemeine Medizin Fmh",
    "wof:placetype":"venue"
},
  "geometry": {"coordinates":[8.440127,47.081837],"type":"Point"}
}