{
  "type": "Feature",
  "properties": {
    "iso:country":"CH",
    "sg:address":"Niederstetten 9240 Uzwil. Postfach",
    "sg:city":"Niederstetten",
    "sg:orig_category":"Grosshandel mit Textilien",
    "sg:postcode":"9249",
    "sg:province":"St. Gallen",
    "wof:name":"Wirth Carl Jun.",
    "wof:placetype":"venue"
},
  "geometry": {"coordinates":[9.1329545975,47.4371452332],"type":"Point"}
}