{
  "type": "Feature",
  "properties": {
    "iso:country":"CH",
    "sg:address":"Sonnhalde 4",
    "sg:city":"Sch\u00f6ftland",
    "sg:orig_category":"Sanit\u00e4r U Heizungsinstallation Sanit\u00e4rinstallation",
    "sg:phone":"+41 62 721 11 29",
    "sg:postcode":"5040",
    "sg:province":"Aargau",
    "wof:name":"Wilfried Morgenthaler Sanit\u00e4r & Heizung",
    "wof:placetype":"venue"
},
  "geometry": {"coordinates":[8.0564126968,47.3060035706],"type":"Point"}
}