{
  "type": "Feature",
  "properties": {
    "iso:country":"CH",
    "sg:address":"Alte Badenerstrasse 11a",
    "sg:city":"Neerach",
    "sg:orig_category":"Grosshandel mit sonstigen Maschinen U Ausr\u00fcstungen f\u00fcr Industrie, Handel U Schiffahrt",
    "sg:phone":"+41 17371408",
    "sg:postcode":"8173",
    "sg:province":"Z\u00fcrich",
    "wof:name":"Pro Clean Maschinenhandel Gmbh",
    "wof:placetype":"venue"
},
  "geometry": {"coordinates":[8.4676103592,47.5108413696],"type":"Point"}
}