{
  "type": "Feature",
  "properties": {
    "iso:country":"CH",
    "sg:address":"Bergacker",
    "sg:city":"Kleinb\u00f6singen",
    "sg:orig_category":"Vereine Gesang",
    "sg:phone":"+41 26 674 19 97",
    "sg:postcode":"3213",
    "sg:province":"Fribourg",
    "wof:name":"M\u00e4nnerchor Laupen",
    "wof:placetype":"venue"
},
  "geometry": {"coordinates":[7.2036099434,46.8982200623],"type":"Point"}
}