{
  "type": "Feature",
  "properties": {
    "iso:country":"CH",
    "sg:address":"5072",
    "sg:city":"Oeschgen",
    "sg:orig_category":"Organisationen des Gesundheitswesen",
    "sg:phone":"+41 62 295 28 82",
    "sg:postcode":"5072",
    "sg:province":"Aargau",
    "wof:name":"Samariterverein Oftringen",
    "wof:placetype":"venue"
},
  "geometry": {"coordinates":[7.9209198952,47.3165397644],"type":"Point"}
}