{
  "type": "Feature",
  "properties": {
    "iso:country":"CH",
    "sg:address":"Schmiedengasse 1",
    "sg:city":"Burgdorf",
    "sg:orig_category":"RESTAURANTS: TEA-ROOMS",
    "sg:postcode":"3400",
    "sg:province":"Bern",
    "wof:name":"Emil Kurz",
    "wof:placetype":"venue"
},
  "geometry": {"coordinates":[7.6265311241,47.0557289124],"type":"Point"}
}