{
  "type": "Feature",
  "properties": {
    "iso:country":"CH",
    "sg:address":"Sonnengasse 16 5313 Klingnau. Postfach",
    "sg:city":"Klingnau",
    "sg:classifiers":[
        {
            "category":"Travel",
            "subcategory":"Hotels & Motels",
            "type":"Entertainment"
        }
    ],
    "sg:phone":"+41 41 670 12 55",
    "sg:postcode":"5313",
    "sg:province":"Aargau",
    "sg:tags":[
        "hotels",
        "mit",
        "restaurant"
    ],
    "wof:name":"Hotel Pilatus Kulm & Bellevue",
    "wof:placetype":"venue"
},
  "geometry": {"coordinates":[8.25,46.9833297729],"type":"Point"}
}