{
  "type": "Feature",
  "properties": {
    "iso:country":"CH",
    "sg:address":"Chemin De La Tour-de-pinchat 2",
    "sg:city":"Vessy",
    "sg:orig_category":"Primarschulen",
    "sg:phone":"+41 22 784 25 93",
    "sg:postcode":"1234",
    "sg:province":"Gen\u00e8ve",
    "wof:name":"Ecole Primaire Pinchat-la-tour",
    "wof:placetype":"venue"
},
  "geometry": {"coordinates":[6.153028965,46.1753349304],"type":"Point"}
}