{
  "type": "Feature",
  "properties": {
    "addr:full":"Buchzelgweg 5 Z\u00fcrich Z\u00fcrich 8053",
    "addr:housenumber":"5",
    "addr:postcode":"8053",
    "addr:street":"Buchzelgweg",
    "iso:country":"CH",
    "sg:address":"Buchzelgweg 5",
    "sg:city":"Z\u00fcrich",
    "sg:orig_category":"Architekturb\u00fcros Herstellung von Mess U Kontrollinstrumenten U vorrichtungen",
    "sg:phone":"+41 13815394",
    "sg:postcode":"8053",
    "sg:province":"Z\u00fcrich",
    "wof:name":"B\u00e9atrice Langraf Architekturb\u00fcro",
    "wof:placetype":"venue"
},
  "geometry": {"coordinates":[8.584057,47.35984],"type":"Point"}
}