{
  "type": "Feature",
  "properties": {
    "iso:country":"CH",
    "sg:address":"Scheurenstrasse 7",
    "sg:city":"Dotzigen",
    "sg:orig_category":"Herstellung von konfektionierten Textilwaren ohne Bekleidung",
    "sg:postcode":"3293",
    "sg:province":"Bern",
    "wof:name":"Realis Roland Gastl",
    "wof:placetype":"venue"
},
  "geometry": {"coordinates":[7.3362979889,47.1195716858],"type":"Point"}
}