{
  "type": "Feature",
  "properties": {
    "iso:country":"CH",
    "sg:address":"St. Gallerstrasse 23",
    "sg:city":"Arbon",
    "sg:orig_category":"RESTAURANTS: TEA-ROOMS",
    "sg:phone":"+41 71 446 19 58",
    "sg:postcode":"9320",
    "sg:province":"Thurgau",
    "wof:name":"Ruf Hedwig",
    "wof:placetype":"venue"
},
  "geometry": {"coordinates":[9.4285459518,47.5110664368],"type":"Point"}
}