{
  "type": "Feature",
  "properties": {
    "iso:country":"CH",
    "sg:address":"Scex Place Du 11",
    "sg:city":"Sitten",
    "sg:orig_category":"Non-Classified Establishments",
    "sg:postcode":"1950",
    "sg:province":"Valais",
    "wof:name":"So-blond Inc. S\u00e0rl",
    "wof:placetype":"venue"
},
  "geometry": {"coordinates":[7.3588571548,46.2280921936],"type":"Point"}
}