{
  "type": "Feature",
  "properties": {
    "iso:country":"CH",
    "sg:address":"Le Centre 2",
    "sg:city":"Courtepin",
    "sg:orig_category":"Detailhandel mit Bekleidung Detailhandel mit Textilien",
    "sg:phone":"+41 26 684 22 21",
    "sg:postcode":"1784",
    "sg:province":"Fribourg",
    "wof:name":"Boutique Stucky Eliane",
    "wof:placetype":"venue"
},
  "geometry": {"coordinates":[7.124128,46.864994],"type":"Point"}
}