{
  "type": "Feature",
  "properties": {
    "iso:country":"CH",
    "sg:address":"Sanzenberg 149",
    "sg:city":"Fisibach",
    "sg:orig_category":"Sportvereine Turnen",
    "sg:phone":"+41 18581456",
    "sg:postcode":"5467",
    "sg:province":"Aargau",
    "wof:name":"Turnverein",
    "wof:placetype":"venue"
},
  "geometry": {"coordinates":[8.4105443954,47.5623703003],"type":"Point"}
}