{
  "type": "Feature",
  "properties": {
    "iso:country":"CH",
    "sg:address":"Neur\u00fctistrasse",
    "sg:city":"Hellb\u00fchl",
    "sg:orig_category":"G\u00fcterbef\u00f6rderung im Strassenverkehr",
    "sg:phone":"+41 41 467 13 55",
    "sg:postcode":"6016",
    "sg:province":"Luzern",
    "wof:name":"Josef Ineichen Transporte",
    "wof:placetype":"venue"
},
  "geometry": {"coordinates":[8.1968288422,47.0704956055],"type":"Point"}
}