{
  "type": "Feature",
  "properties": {
    "addr:full":"G\u00e4rtnerstrasse 12 Solothurn Solothurn 4500",
    "addr:housenumber":"12",
    "addr:postcode":"4500",
    "addr:street":"Gaertnerstrasse",
    "iso:country":"CH",
    "sg:address":"G\u00e4rtnerstrasse 12",
    "sg:city":"Solothurn",
    "sg:orig_category":"Arztpraxen",
    "sg:phone":"+41 32 622 09 22",
    "sg:postcode":"4500",
    "sg:province":"Solothurn",
    "wof:name":"Dres Med. H. & H. Probst Spezial\u00e4rzte Fmh",
    "wof:placetype":"venue"
},
  "geometry": {"coordinates":[7.535077,47.211506],"type":"Point"}
}