{
  "type": "Feature",
  "properties": {
    "iso:country":"CH",
    "sg:address":"Bahn 720",
    "sg:city":"Waldstatt",
    "sg:orig_category":"Allgemeiner Hoch U Tiefbau Allgemeiner Hochbau",
    "sg:phone":"+41 71 351 22 15",
    "sg:postcode":"9104",
    "sg:province":"Appenzell Ausserrhoden",
    "wof:name":"Walter Preisig Ag Baugesch\u00e4ft",
    "wof:placetype":"venue"
},
  "geometry": {"coordinates":[9.288922,47.359455],"type":"Point"}
}