{
  "type": "Feature",
  "properties": {
    "iso:country":"CH",
    "sg:address":"Hardstrasse 7",
    "sg:city":"Z\u00fcrich",
    "sg:orig_category":"RESTAURANTS: TEA-ROOMS",
    "sg:phone":"+41 33 654 29 73",
    "sg:postcode":"8004",
    "sg:province":"Z\u00fcrich",
    "wof:name":"Rindisbacher Daniel, Restaurant Panorama",
    "wof:placetype":"venue"
},
  "geometry": {"coordinates":[7.6955251694,46.6565361023],"type":"Point"}
}