{
  "type": "Feature",
  "properties": {
    "addr:full":"K\u00f6llikerstrasse 5 Sch\u00f6nenwerd Solothurn 5012",
    "addr:housenumber":"5",
    "addr:postcode":"5012",
    "addr:street":"Koellikerstrasse;Schoenenwerd Solothurn",
    "iso:country":"CH",
    "sg:address":"K\u00f6llikerstrasse 5",
    "sg:city":"Sch\u00f6nenwerd",
    "sg:orig_category":"Allgemeiner Hoch U Tiefbau",
    "sg:phone":"+41 62 746 88 11",
    "sg:postcode":"5012",
    "sg:province":"Solothurn",
    "wof:name":"M\u00fcller Gottlieb & Cie Ag",
    "wof:placetype":"venue"
},
  "geometry": {"coordinates":[7.998568,47.364395],"type":"Point"}
}