{
  "type": "Feature",
  "properties": {
    "iso:country":"CH",
    "sg:address":"Grabenstrasse 21",
    "sg:city":"Frauenfeld",
    "sg:classifiers":[
        {
            "category":"Restaurant",
            "type":"Food & Drink"
        }
    ],
    "sg:phone":"+41 52 721 22 88",
    "sg:postcode":"8500",
    "sg:province":"Thurgau",
    "sg:tags":[
        "tea-rooms",
        "restaurants"
    ],
    "wof:name":"Restaurant Golden River Ha",
    "wof:placetype":"venue"
},
  "geometry": {"coordinates":[8.8979539871,47.5575866699],"type":"Point"}
}