{
  "type": "Feature",
  "properties": {
    "iso:country":"CH",
    "sg:address":"Fliederweg 69",
    "sg:city":"Uetendorf",
    "sg:orig_category":"Detailhandel mit Computern U Software Hardwareberatung",
    "sg:phone":"+41 33 345 54 01",
    "sg:postcode":"3661",
    "sg:province":"Bern",
    "wof:name":"Frank L\u00fcthi Informatik",
    "wof:placetype":"venue"
},
  "geometry": {"coordinates":[7.578916,46.770367],"type":"Point"}
}