{
  "type": "Feature",
  "properties": {
    "iso:country":"CH",
    "sg:address":"Nidelbadstrasse 5 8038 Z\u00fcrich. Postfach",
    "sg:city":"Z\u00fcrich",
    "sg:orig_category":"Grosshandel mit Textilien Sonstiges Textilgewerbe",
    "sg:phone":"+41 21 323 58 72",
    "sg:postcode":"8060",
    "sg:province":"Z\u00fcrich",
    "wof:name":"Dumas Jean-pierre Sa.",
    "wof:placetype":"venue"
},
  "geometry": {"coordinates":[6.6320028305,46.5231132507],"type":"Point"}
}