{
  "type": "Feature",
  "properties": {
    "iso:country":"CH",
    "sg:address":"Hauptstrasse 93",
    "sg:city":"Kreuzlingen",
    "sg:orig_category":"Coiffeursalons Damen Wirtschafts- and Arbeitgeberverb\u00e4nde",
    "sg:phone":"+41 71 670 00 44",
    "sg:postcode":"8280",
    "sg:province":"Thurgau",
    "wof:name":"Coiffeurmeisterverband Sh",
    "wof:placetype":"venue"
},
  "geometry": {"coordinates":[9.180172,47.644596],"type":"Point"}
}