{
  "type": "Feature",
  "properties": {
    "iso:country":"CH",
    "sg:address":"Bahnhofstrasse 3",
    "sg:city":"W\u00fcrenlos",
    "sg:orig_category":"Grosshandel mit elektrischen Haushaltsger\u00e4ten Herstellung von sonstigen elektrischen Ausr\u00fcstungen",
    "sg:phone":"+41 56 424 13 66",
    "sg:postcode":"5436",
    "sg:province":"Aargau",
    "wof:name":"Minilux Ag",
    "wof:placetype":"venue"
},
  "geometry": {"coordinates":[8.3598165512,47.4455375671],"type":"Point"}
}