{
  "type": "Feature",
  "properties": {
    "iso:country":"CH",
    "sg:address":"8566",
    "sg:city":"Dotnacht",
    "sg:classifiers":[
        {
            "category":"Restaurant",
            "type":"Food & Drink"
        }
    ],
    "sg:phone":"+41 71 699 15 55",
    "sg:postcode":"8566",
    "sg:province":"Thurgau",
    "wof:name":"Restaurant Sonne",
    "wof:placetype":"venue"
},
  "geometry": {"coordinates":[9.1413497925,47.5999183655],"type":"Point"}
}