{
  "type": "Feature",
  "properties": {
    "iso:country":"CH",
    "sg:address":"Rue Du Ch\u00eane 15",
    "sg:city":"Aubonne",
    "sg:orig_category":"Herstellung von medizinischen U chirurgischen Ger\u00e4ten sowie orthop\u00e4dischen Vorrichtungen Zahntechnis",
    "sg:phone":"+41 21 808 72 36",
    "sg:postcode":"1170",
    "sg:province":"Vaud",
    "wof:name":"Logiceram Mercoli Michel",
    "wof:placetype":"venue"
},
  "geometry": {"coordinates":[6.3923621178,46.4946937561],"type":"Point"}
}