{
  "type": "Feature",
  "properties": {
    "iso:country":"CH",
    "sg:address":"7543",
    "sg:city":"Lavin",
    "sg:classifiers":[
        {
            "category":"Travel",
            "subcategory":"Hotels & Motels",
            "type":"Entertainment"
        }
    ],
    "sg:phone":"+41 81 862 26 26",
    "sg:postcode":"7543",
    "sg:province":"Graubunden",
    "sg:tags":[
        "hotels",
        "mit",
        "restaurant"
    ],
    "wof:name":"Hotel Piz Linard",
    "wof:placetype":"venue"
},
  "geometry": {"coordinates":[10.1114444733,46.7686805725],"type":"Point"}
}