{
  "type": "Feature",
  "properties": {
    "iso:country":"CH",
    "sg:address":"Via G. Motta 10",
    "sg:city":"Chiasso",
    "sg:orig_category":"Rechtsberatung",
    "sg:postcode":"6830",
    "sg:province":"Ticino",
    "wof:name":"M\u00e4rly Sa",
    "wof:placetype":"venue"
},
  "geometry": {"coordinates":[9.0330457687,45.8321609497],"type":"Point"}
}