{
  "type": "Feature",
  "properties": {
    "iso:country":"CH",
    "sg:address":"Rue De Lo\u00e8che 26",
    "sg:city":"Sion",
    "sg:orig_category":"Verlegen von Fliesen U Platten",
    "sg:phone":"+41 71 923 78 66",
    "sg:postcode":"1950",
    "sg:province":"Valais",
    "wof:name":"M\u00fcller Marcel Ag Wand, Bodenbel\u00e4ge Usw; Verlegen",
    "wof:placetype":"venue"
},
  "geometry": {"coordinates":[9.0506019592,47.4415893555],"type":"Point"}
}