{
  "type": "Feature",
  "properties": {
    "iso:country":"CH",
    "sg:address":"Route De Prilly 16",
    "sg:city":"Prilly",
    "sg:orig_category":"Elektroinstallation",
    "sg:postcode":"1008",
    "sg:province":"Vaud",
    "wof:name":"Coste + Iseli Blitzschutz",
    "wof:placetype":"venue"
},
  "geometry": {"coordinates":[7.4930348396,46.927734375],"type":"Point"}
}