{
  "type": "Feature",
  "properties": {
    "iso:country":"CH",
    "sg:address":"Bettelr\u00fcti",
    "sg:city":"Wolfenschiessen",
    "sg:orig_category":"Abbruch U Sprenggewerbe, Erdbewegungsarbeiten",
    "sg:postcode":"6386",
    "sg:province":"Nidwalden",
    "wof:name":"Mathis Baggerbetrieb Gmbh",
    "wof:placetype":"venue"
},
  "geometry": {"coordinates":[8.393629,46.889359],"type":"Point"}
}