{
  "type": "Feature",
  "properties": {
    "iso:country":"CH",
    "sg:address":"Riedgrabenstrasse 13",
    "sg:city":"R\u00fcmlang",
    "sg:orig_category":"Herstellung von Bergwerks U Baumaschinen Herstellung von Metallerzeugnissen ohne Maschinenbau",
    "sg:phone":"+41 18171939",
    "sg:postcode":"8153",
    "sg:province":"Z\u00fcrich",
    "wof:name":"Stury Fredi Ag",
    "wof:placetype":"venue"
},
  "geometry": {"coordinates":[8.5196056366,47.4621315002],"type":"Point"}
}