{
  "type": "Feature",
  "properties": {
    "iso:country":"CH",
    "sg:address":"Rue Du Coll\u00e8ge 6",
    "sg:city":"Noiraigue",
    "sg:orig_category":"Gemeindeverwaltungen",
    "sg:phone":"+41 32 863 31 21",
    "sg:postcode":"2103",
    "sg:province":"Neuch\u00e2tel",
    "wof:name":"Administration Communale De Noiraigue",
    "wof:placetype":"venue"
},
  "geometry": {"coordinates":[6.7248950005,46.9556236267],"type":"Point"}
}