{
  "type": "Feature",
  "properties": {
    "iso:country":"CH",
    "sg:address":"D\u00fcr's B\u00e4chli",
    "sg:city":"Weissenburg",
    "sg:orig_category":"Wirtschaftspr\u00fcfung, Steuerberatung U Treuhand",
    "sg:postcode":"3764",
    "sg:province":"Bern",
    "wof:name":"Bixx.ch Ag",
    "wof:placetype":"venue"
},
  "geometry": {"coordinates":[11.3414039612,50.7117805481],"type":"Point"}
}