{
  "type": "Feature",
  "properties": {
    "iso:country":"CH",
    "sg:address":"Haselgasse 90",
    "sg:city":"Glis",
    "sg:orig_category":"Unclassifiable Establishments",
    "sg:postcode":"3902",
    "sg:province":"Valais",
    "wof:name":"Modellflugtechnik Schumacher",
    "wof:placetype":"venue"
},
  "geometry": {"coordinates":[7.9890298843,46.3084526062],"type":"Point"}
}