{
  "type": "Feature",
  "properties": {
    "iso:country":"CH",
    "sg:address":"Im Weidgrund 8",
    "sg:city":"D\u00fcbendorf",
    "sg:orig_category":"Vereine Quartier",
    "sg:phone":"+41 71 277 88 25",
    "sg:postcode":"8600",
    "sg:province":"Z\u00fcrich",
    "wof:name":"Verein Wohnliches Otmar",
    "wof:placetype":"venue"
},
  "geometry": {"coordinates":[9.3430871964,47.4086532593],"type":"Point"}
}