{
  "type": "Feature",
  "properties": {
    "iso:country":"CH",
    "sg:address":"Hauptstrasse 65",
    "sg:city":"Sevelen",
    "sg:orig_category":"Detailhandel mit Sportartikeln Fachdetailhandel in Verkaufsr\u00e4umen",
    "sg:phone":"+41 81 740 12 40",
    "sg:postcode":"9475",
    "sg:province":"St. Gallen",
    "wof:name":"Beat Sport Beat Schlegel",
    "wof:placetype":"venue"
},
  "geometry": {"coordinates":[9.4859733582,47.1204910278],"type":"Point"}
}