{
  "type": "Feature",
  "properties": {
    "iso:country":"CH",
    "sg:address":"6815",
    "sg:city":"Melide",
    "sg:orig_category":"Organisationen des Gesundheitswesen",
    "sg:postcode":"6815",
    "sg:province":"Ticino",
    "wof:name":"Samariter Verein Pf\u00e4ffikon",
    "wof:placetype":"venue"
},
  "geometry": {"coordinates":[8.737616539,47.2042045593],"type":"Point"}
}