{
  "type": "Feature",
  "properties": {
    "iso:country":"CH",
    "sg:address":"Florastrasse 14",
    "sg:city":"Interlaken",
    "sg:orig_category":"Zimmerei, Dachdeckerei, Bauspenglerei U Abdichtung",
    "sg:phone":"+41 33 822 67 67",
    "sg:postcode":"3800",
    "sg:province":"Bern",
    "wof:name":"Ws Spenglerei Ag",
    "wof:placetype":"venue"
},
  "geometry": {"coordinates":[7.854019165,46.6831283569],"type":"Point"}
}