{
  "type": "Feature",
  "properties": {
    "iso:country":"CH",
    "sg:address":"Schiffl\u00e4nde 22 8001 Z\u00fcrich. Postfach",
    "sg:city":"Z\u00fcrich",
    "sg:orig_category":"Unternehmensberatung",
    "sg:phone":"+41 12685430",
    "sg:postcode":"8001",
    "sg:province":"Z\u00fcrich",
    "wof:name":"Sungard Eprocess Intelligence Gmbh",
    "wof:placetype":"venue"
},
  "geometry": {"coordinates":[8.5444602966,47.3688201904],"type":"Point"}
}