{
  "type": "Feature",
  "properties": {
    "iso:country":"CH",
    "sg:address":"Bacavoine 167",
    "sg:city":"Fontenais",
    "sg:orig_category":"M\u00f6belschreinereien",
    "sg:postcode":"2902",
    "sg:province":"Jura",
    "wof:name":"Juillerat & Li\u00e8vre",
    "wof:placetype":"venue"
},
  "geometry": {"coordinates":[7.0786118507,47.4042549133],"type":"Point"}
}