{
  "type": "Feature",
  "properties": {
    "iso:country":"CH",
    "sg:address":"Hilfikerstrasse 2",
    "sg:city":"Sarmenstorf",
    "sg:orig_category":"Datenverarbeitungsdienste",
    "sg:phone":"+41 56 667 33 15",
    "sg:postcode":"5614",
    "sg:province":"Aargau",
    "wof:name":"Mk Consult",
    "wof:placetype":"venue"
},
  "geometry": {"coordinates":[8.247071,47.310013],"type":"Point"}
}