{
  "type": "Feature",
  "properties": {
    "iso:country":"CH",
    "sg:address":"Hauptstrasse 48",
    "sg:city":"Diegten",
    "sg:orig_category":"Detailhandel mit Getr\u00e4nken Detailhandel mit Waren verschiedener Art, Hauptrichtung Nahrungsmittel",
    "sg:phone":"+41 71 744 40 45",
    "sg:postcode":"4457",
    "sg:province":"Basel-Landschaft",
    "wof:name":"Michele Cianciarulo Ital.& Span.spezialit\u00e4ten",
    "wof:placetype":"venue"
},
  "geometry": {"coordinates":[9.6356687546,47.4518318176],"type":"Point"}
}