{
  "type": "Feature",
  "properties": {
    "iso:country":"CH",
    "sg:address":"Untere Allmendstrasse 3",
    "sg:city":"Steinhausen",
    "sg:orig_category":"Non-Classified Establishments",
    "sg:postcode":"6312",
    "sg:province":"Zug",
    "wof:name":"Quality Sports Group Ag",
    "wof:placetype":"venue"
},
  "geometry": {"coordinates":[8.7901973724,47.2036628723],"type":"Point"}
}