{
  "type": "Feature",
  "properties": {
    "iso:country":"CH",
    "sg:address":"Austrasse 111",
    "sg:city":"Basel",
    "sg:orig_category":"Fotografische Ateliers",
    "sg:phone":"+41 61 274 06 16",
    "sg:postcode":"4051",
    "sg:province":"Basel-Stadt",
    "wof:name":"G\u00e9rard Rozeck Modefotograf",
    "wof:placetype":"venue"
},
  "geometry": {"coordinates":[7.5763888359,47.555431366],"type":"Point"}
}