{
  "type": "Feature",
  "properties": {
    "iso:country":"CH",
    "sg:address":"Uetendorfberg",
    "sg:city":"Uetendorf",
    "sg:orig_category":"Institutionen f\u00fcr Behinderte Tagesheime f\u00fcr Behinderte, gesch\u00fctzte Werkst\u00e4tten",
    "sg:phone":"+41 33 345 12 82",
    "sg:postcode":"3661",
    "sg:province":"Bern",
    "wof:name":"Stiftung Uetendorfberg Wohn-& Arbeitsgemeinschaft",
    "wof:placetype":"venue"
},
  "geometry": {"coordinates":[7.555970192,46.7703933716],"type":"Point"}
}