{
  "type": "Feature",
  "properties": {
    "iso:country":"CH",
    "sg:address":"Sonnenstrasse 16",
    "sg:city":"Kreuzlingen",
    "sg:orig_category":"Detailhandel mit Geschenkartikeln U Souvenirs",
    "sg:phone":"+41 71 672 87 07",
    "sg:postcode":"8280",
    "sg:province":"Thurgau",
    "wof:name":"Extra-boutique",
    "wof:placetype":"venue"
},
  "geometry": {"coordinates":[9.1733627319,47.6504211426],"type":"Point"}
}