{
  "type": "Feature",
  "properties": {
    "iso:country":"CH",
    "sg:address":"Schaffhauserstrasse 51",
    "sg:city":"Oerlingen",
    "sg:orig_category":"Vorschulen, Kinderg\u00e4rten",
    "sg:phone":"+41 52 319 28 36",
    "sg:postcode":"8461",
    "sg:province":"Z\u00fcrich",
    "wof:name":"Kindergarten",
    "wof:placetype":"venue"
},
  "geometry": {"coordinates":[8.6737260818,47.6252174377],"type":"Point"}
}