{
  "type": "Feature",
  "properties": {
    "iso:country":"CH",
    "sg:address":"Beundengasse 1 3250 Lyss. Postfach 349",
    "sg:city":"Lyss",
    "sg:orig_category":"Elektrizit\u00e4tsversorgung Herstellung von Elektromotoren, Generatoren U Transformatoren",
    "sg:phone":"+41 32 387 02 22",
    "sg:postcode":"3250",
    "sg:province":"Bern",
    "wof:name":"Energie Seeland Ag",
    "wof:placetype":"venue"
},
  "geometry": {"coordinates":[7.3018608093,47.0724525452],"type":"Point"}
}