{
  "type": "Feature",
  "properties": {
    "iso:country":"CH",
    "sg:address":"Kantonsstrasse 6207 Nottwil. Postfach 161",
    "sg:city":"Nottwil",
    "sg:orig_category":"Berufliche Weiterbildung, Erwachsenenbildung Interessenvertretungen",
    "sg:phone":"+41 41 939 23 23",
    "sg:postcode":"6207",
    "sg:province":"Luzern",
    "wof:name":"Rotkreuzstiftung Ausbildungszentrum Srk",
    "wof:placetype":"venue"
},
  "geometry": {"coordinates":[8.128386,47.139793],"type":"Point"}
}