{
  "type": "Feature",
  "properties": {
    "iso:country":"CH",
    "sg:address":"Wehntalerstrasse 510",
    "sg:city":"Z\u00fcrich",
    "sg:orig_category":"Aktivit\u00e4ten der Krankenschwestern U Hebammen, Hauspflege Organisationen des Gesundheitswesen",
    "sg:phone":"+41 13715151",
    "sg:postcode":"8046",
    "sg:province":"Z\u00fcrich",
    "wof:name":"Spitex-dienste Affoltern Gemeindekrankenpflege",
    "wof:placetype":"venue"
},
  "geometry": {"coordinates":[8.50988,47.418011],"type":"Point"}
}