{
  "type": "Feature",
  "properties": {
    "iso:country":"CH",
    "sg:address":"Les Petites-lacherelles",
    "sg:city":"Travers",
    "sg:orig_category":"Allgemeiner Hoch U Tiefbau Handelsvermittlung U Grosshandel",
    "sg:phone":"+41 32 863 10 27",
    "sg:postcode":"2105",
    "sg:province":"Neuch\u00e2tel",
    "wof:name":"Gestion 3000, Gasser Didier",
    "wof:placetype":"venue"
},
  "geometry": {"coordinates":[6.67322,46.938969],"type":"Point"}
}