{
  "type": "Feature",
  "properties": {
    "iso:country":"CH",
    "sg:address":"Hinteregg 176",
    "sg:city":"Wolfhalden",
    "sg:orig_category":"Sportvereine Turnen Damen",
    "sg:postcode":"9427",
    "sg:province":"Appenzell Ausserrhoden",
    "wof:name":"Dtv Wolfhalden",
    "wof:placetype":"venue"
},
  "geometry": {"coordinates":[9.5512285233,47.4494438171],"type":"Point"}
}