{
  "type": "Feature",
  "properties": {
    "iso:country":"CH",
    "sg:address":"Rue Du Coppet 4",
    "sg:city":"Monthey",
    "sg:orig_category":"Unclassifiable Establishments",
    "sg:postcode":"1870",
    "sg:province":"Valais",
    "wof:name":"Jacqueline Schreiber Coiffure",
    "wof:placetype":"venue"
},
  "geometry": {"coordinates":[6.9491910934,46.2522583008],"type":"Point"}
}