{
  "type": "Feature",
  "properties": {
    "iso:country":"CH",
    "sg:address":"1624",
    "sg:city":"Grattavache",
    "sg:orig_category":"Zimmerei, Dachdeckerei, Bauspenglerei U Abdichtung Zimmerei, Ingenieurholzbau",
    "sg:phone":"+41 26 918 51 90",
    "sg:postcode":"1624",
    "sg:province":"Fribourg",
    "wof:name":"Vuagniaux Francis.",
    "wof:placetype":"venue"
},
  "geometry": {"coordinates":[6.9144601822,46.5952606201],"type":"Point"}
}