{
  "type": "Feature",
  "properties": {
    "iso:country":"CH",
    "sg:address":"Seestrasse.",
    "sg:city":"Gersau",
    "sg:classifiers":[
        {
            "category":"Travel",
            "subcategory":"Hotels & Motels",
            "type":"Entertainment"
        }
    ],
    "sg:postcode":"6442",
    "sg:province":"Schwyz",
    "sg:tags":[
        "hotels",
        "mit",
        "restaurant"
    ],
    "wof:name":"Hotel Seehof, Wiget & Henzi.",
    "wof:placetype":"venue"
},
  "geometry": {"coordinates":[8.5276432037,46.9908294678],"type":"Point"}
}