{
  "type": "Feature",
  "properties": {
    "iso:country":"CH",
    "sg:address":"Nelkenweg 7",
    "sg:city":"Muttenz",
    "sg:orig_category":"Vereine Fasnacht",
    "sg:phone":"+41 61 461 93 47",
    "sg:postcode":"4132",
    "sg:province":"Basel-Landschaft",
    "wof:name":"Grienschn\u00e4bel",
    "wof:placetype":"venue"
},
  "geometry": {"coordinates":[7.6368489265,47.5327529907],"type":"Point"}
}