{
  "type": "Feature",
  "properties": {
    "iso:country":"CH",
    "sg:address":"8453",
    "sg:city":"Alten",
    "sg:orig_category":"Sportvereine Sch\u00fctzen Pistolen-& Gewehr",
    "sg:phone":"+41 81 738 25 83",
    "sg:postcode":"8453",
    "sg:province":"Z\u00fcrich",
    "wof:name":"Milit\u00e4rsch\u00fctzenverein",
    "wof:placetype":"venue"
},
  "geometry": {"coordinates":[8.6396102905,47.5991516113],"type":"Point"}
}