{
  "type": "Feature",
  "properties": {
    "addr:full":"Weggisgasse 1/falkenplatz Luzern Luzern 6004",
    "addr:housenumber":"1 /",
    "addr:postcode":"6004",
    "addr:street":"Weggisgasse;Falkenplatz",
    "iso:country":"CH",
    "sg:address":"Weggisgasse 1/falkenplatz",
    "sg:city":"Luzern",
    "sg:classifiers":[
        {
            "category":"Banks & Credit Unions",
            "subcategory":"Bank",
            "type":"Services"
        }
    ],
    "sg:phone":"+41 32 465 13 01",
    "sg:postcode":"6004",
    "sg:province":"Luzern",
    "wof:name":"Promindus S.a",
    "wof:placetype":"venue"
},
  "geometry": {"coordinates":[7.078227,47.41703],"type":"Point"}
}