{
  "type": "Feature",
  "properties": {
    "iso:country":"CH",
    "sg:address":"Hauptstrasse 33",
    "sg:city":"Frick",
    "sg:orig_category":"Non-Classified Establishments",
    "sg:postcode":"5070",
    "sg:province":"Aargau",
    "wof:name":"Raiffeisenbank Gipf-oberfrick- Frick-wittnau-oeschgen",
    "wof:placetype":"venue"
},
  "geometry": {"coordinates":[8.0180959702,47.5092277527],"type":"Point"}
}