{
  "type": "Feature",
  "properties": {
    "iso:country":"CH",
    "sg:address":"B\u00e4umlihofstrasse 48 4058 Basel. Postfach",
    "sg:city":"Basel",
    "sg:orig_category":"Geb\u00e4ude, Wohnungsreinigung Hardwareberatung",
    "sg:phone":"+41 22 343 77 40",
    "sg:postcode":"4016",
    "sg:province":"Basel-Stadt",
    "wof:name":"All-net Ag",
    "wof:placetype":"venue"
},
  "geometry": {"coordinates":[6.1414251328,46.1833114624],"type":"Point"}
}