{
  "type": "Feature",
  "properties": {
    "iso:country":"CH",
    "sg:address":"B\u00fcren 41",
    "sg:city":"Gansingen",
    "sg:orig_category":"Non-Classified Establishments",
    "sg:phone":"+41 62 875 20 00",
    "sg:postcode":"5272",
    "sg:province":"Aargau",
    "wof:name":"Florian Gansingen Gmbh",
    "wof:placetype":"venue"
},
  "geometry": {"coordinates":[8.1384716034,47.5326423645],"type":"Point"}
}