{
  "type": "Feature",
  "properties": {
    "iso:country":"CH",
    "sg:address":"Hardstrasse 251",
    "sg:city":"Herbetswil",
    "sg:orig_category":"Mechanik",
    "sg:phone":"+41 79 334 03 63",
    "sg:postcode":"4715",
    "sg:province":"Solothurn",
    "wof:name":"Schlosserei Willi Gmbh",
    "wof:placetype":"venue"
},
  "geometry": {"coordinates":[7.5985188484,47.2980651855],"type":"Point"}
}