{
  "type": "Feature",
  "properties": {
    "iso:country":"CH",
    "sg:address":"Residenza Francesca A",
    "sg:city":"Tenero",
    "sg:orig_category":"D\u00e4mmung gegen K\u00e4lte, W\u00e4rme, Schall U Ersch\u00fctterung Stukkateurgewerbe, Gipserei U Verputzerei",
    "sg:phone":"+41 79 233 14 15",
    "sg:postcode":"6598",
    "sg:province":"Ticino",
    "wof:name":"Mifal Di Michele Falcetta Impresa Di Gessatura",
    "wof:placetype":"venue"
},
  "geometry": {"coordinates":[8.8498601913,46.180896759],"type":"Point"}
}