{
  "type": "Feature",
  "properties": {
    "iso:country":"CH",
    "sg:address":"Hubel",
    "sg:city":"Sch\u00fcpfen",
    "sg:orig_category":"G\u00fcterbef\u00f6rderung im Strassenverkehr",
    "sg:phone":"+41 77516707",
    "sg:postcode":"3054",
    "sg:province":"Bern",
    "wof:name":"Dieter Burri Transporte",
    "wof:placetype":"venue"
},
  "geometry": {"coordinates":[7.3824448586,47.0429039001],"type":"Point"}
}