{
  "type": "Feature",
  "properties": {
    "iso:country":"CH",
    "sg:address":"Alte R\u00f6merstrasse 18 8404 Oberwinterthur. Postfach",
    "sg:city":"Winterthur",
    "sg:orig_category":"Kauf U Verkauf von Immobilien auf eigene Rechnung",
    "sg:phone":"+41 52 242 38 71",
    "sg:postcode":"8404",
    "sg:province":"Z\u00fcrich",
    "wof:name":"Immotech Ag",
    "wof:placetype":"venue"
},
  "geometry": {"coordinates":[8.7497110367,47.5050697327],"type":"Point"}
}