{
  "type": "Feature",
  "properties": {
    "addr:full":"Kasinostrasse Liestal Basel-Landschaft 4410",
    "addr:postcode":"4410",
    "addr:street":"Kasinostrasse",
    "iso:country":"CH",
    "sg:address":"Kasinostrasse",
    "sg:city":"Liestal",
    "sg:orig_category":"Berufliche Weiterbildung, Erwachsenenbildung",
    "sg:phone":"+41 61 921 59 16",
    "sg:postcode":"4410",
    "sg:province":"Basel-Landschaft",
    "wof:name":"Zollverwaltung Ausbildungszentrum Der",
    "wof:placetype":"venue"
},
  "geometry": {"coordinates":[7.74289,47.47945],"type":"Point"}
}