{
  "type": "Feature",
  "properties": {
    "iso:country":"CH",
    "sg:address":"Hollenweg 46",
    "sg:city":"Arlesheim",
    "sg:orig_category":"Vereine Haus- and Grundeigent\u00fcmer",
    "sg:phone":"+41 61 701 78 35",
    "sg:postcode":"4144",
    "sg:province":"Basel-Landschaft",
    "wof:name":"Hauseigent\u00fcmerver.arlesheim",
    "wof:placetype":"venue"
},
  "geometry": {"coordinates":[7.6261701584,47.4865455627],"type":"Point"}
}