{
  "type": "Feature",
  "properties": {
    "iso:country":"CH",
    "sg:address":"Via R. Simen 71a",
    "sg:city":"Minusio",
    "sg:orig_category":"Vermietung U Verpachtung von eigenen Immobilien",
    "sg:postcode":"6648",
    "sg:province":"Ticino",
    "wof:name":"Feria Sa",
    "wof:placetype":"venue"
},
  "geometry": {"coordinates":[8.8245763779,46.1773338318],"type":"Point"}
}