{
  "type": "Feature",
  "properties": {
    "iso:country":"CH",
    "sg:address":"Rue De L'ale 1-3",
    "sg:city":"Lausanne",
    "sg:orig_category":"Physiotherapie",
    "sg:phone":"+41 56 633 27 45",
    "sg:postcode":"1003",
    "sg:province":"Vaud",
    "wof:name":"Didier Anchise Physiotherapie",
    "wof:placetype":"venue"
},
  "geometry": {"coordinates":[8.3482694626,47.3526954651],"type":"Point"}
}