{
  "type": "Feature",
  "properties": {
    "iso:country":"CH",
    "sg:address":"Staatsstrasse",
    "sg:city":"Wildhaus",
    "sg:orig_category":"Einbau von Schreinerwaren Herstellung von Metallkonstruktionen",
    "sg:phone":"+41 71 999 27 45",
    "sg:postcode":"9658",
    "sg:province":"St. Gallen",
    "wof:name":"Vetsch Hans Ag",
    "wof:placetype":"venue"
},
  "geometry": {"coordinates":[9.3186693192,47.1979942322],"type":"Point"}
}