{
  "type": "Feature",
  "properties": {
    "iso:country":"CH",
    "sg:address":"Landstrasse 47",
    "sg:city":"Wettingen",
    "sg:orig_category":"RESTAURANTS: TEA-ROOMS",
    "sg:postcode":"5430",
    "sg:province":"Aargau",
    "wof:name":"Yildiz Yusuf, Globibal Caf\u00e9-restaurant / Imbiss",
    "wof:placetype":"venue"
},
  "geometry": {"coordinates":[8.3218669891,47.4681129456],"type":"Point"}
}