{
  "type": "Feature",
  "properties": {
    "addr:full":"Bernstrasse 5 R\u00fcdtligen Bern 3422",
    "addr:housenumber":"5",
    "addr:postcode":"3422",
    "addr:street":"Bernstrasse",
    "iso:country":"CH",
    "sg:address":"Bernstrasse 5",
    "sg:city":"R\u00fcdtligen",
    "sg:orig_category":"Detailhandel mit Antiquit\u00e4ten Detailhandel mit M\u00f6beln",
    "sg:phone":"+41 34 445 10 79",
    "sg:postcode":"3422",
    "sg:province":"Bern",
    "wof:name":"Eduard Maurer Neum\u00f6bel & Antiquit\u00e4ten",
    "wof:placetype":"venue"
},
  "geometry": {"coordinates":[7.58445,47.08519],"type":"Point"}
}