{
  "type": "Feature",
  "properties": {
    "iso:country":"CH",
    "sg:address":"Chemin Des Vieux-pressoir 5",
    "sg:city":"Tannay",
    "sg:orig_category":"Detailhandel mit Pelzwaren",
    "sg:phone":"+41 22 776 34 17",
    "sg:postcode":"1295",
    "sg:province":"Vaud",
    "wof:name":"Merc\u00e9d\u00e8s Stolz Artisane En Fourrure",
    "wof:placetype":"venue"
},
  "geometry": {"coordinates":[6.1744799614,46.3105201721],"type":"Point"}
}