{
  "type": "Feature",
  "properties": {
    "iso:country":"CH",
    "sg:address":"1694",
    "sg:city":"Villarsiviriaux",
    "sg:orig_category":"Landesverteidigung, Sozialversicherung \u00d6ffentliche Verwaltung",
    "sg:phone":"+41 26 653 11 50",
    "sg:postcode":"1694",
    "sg:province":"Fribourg",
    "wof:name":"Centre De Protection Civile",
    "wof:placetype":"venue"
},
  "geometry": {"coordinates":[7.0112099648,46.6991996765],"type":"Point"}
}