{
  "type": "Feature",
  "properties": {
    "addr:full":"Wettingerstrasse Baden Aargau 5400",
    "addr:postcode":"5400",
    "addr:street":"Wettingerstrasse",
    "iso:country":"CH",
    "sg:address":"Wettingerstrasse",
    "sg:city":"Baden",
    "sg:classifiers":[
        {
            "category":"Social Services",
            "subcategory":"Retirement Home",
            "type":"Services"
        }
    ],
    "sg:phone":"+41 56 203 82 80",
    "sg:postcode":"5400",
    "sg:province":"Aargau",
    "sg:tags":[
        "pflegeheime",
        "u",
        "alters"
    ],
    "wof:name":"Altersheim St.anna",
    "wof:placetype":"venue"
},
  "geometry": {"coordinates":[8.312125,47.471779],"type":"Point"}
}