{
  "type": "Feature",
  "properties": {
    "iso:country":"CH",
    "sg:address":"Thurtalstrasse 146",
    "sg:city":"Altikon",
    "sg:orig_category":"Bauschreinerei",
    "sg:phone":"+41 52 336 12 67",
    "sg:postcode":"8479",
    "sg:province":"Z\u00fcrich",
    "wof:name":"Gerhard Wegmann Mechanische Schreinerei",
    "wof:placetype":"venue"
},
  "geometry": {"coordinates":[8.78187,47.573212],"type":"Point"}
}