{
  "type": "Feature",
  "properties": {
    "addr:full":"Rue Du Cribelet 13 1700 Fribourg Case Postale 610 Fribourg Fribourg 1701",
    "addr:housenumber":"13",
    "addr:postcode":"1700;case;610;1701",
    "addr:street":"Rue Du Cribelet;Postale",
    "iso:country":"CH",
    "sg:address":"Rue Du Cribelet 13 1700 Fribourg Case Postale 610",
    "sg:city":"Fribourg",
    "sg:orig_category":"Advokaturb\u00fcros",
    "sg:phone":"+41 26 322 20 75",
    "sg:postcode":"1701",
    "sg:province":"Fribourg",
    "wof:name":"Piller & Brunner Etude D'avocat",
    "wof:placetype":"venue"
},
  "geometry": {"coordinates":[7.154561,46.805061],"type":"Point"}
}