{
  "type": "Feature",
  "properties": {
    "iso:country":"CH",
    "sg:address":"Thalerstrasse 111",
    "sg:city":"Rorschacherberg",
    "sg:orig_category":"Non-Classified Establishments",
    "sg:postcode":"9404",
    "sg:province":"St. Gallen",
    "wof:name":"Bonetti Architektur & Immobiliensch\u00e4tzungen",
    "wof:placetype":"venue"
},
  "geometry": {"coordinates":[9.5247116089,47.4764289856],"type":"Point"}
}