{
  "type": "Feature",
  "properties": {
    "iso:country":"CH",
    "sg:address":"Habsburgerstrasse 19 6000 Luzern. Postfach",
    "sg:city":"Luzern",
    "sg:orig_category":"Detailhandel mit medizinischen U orthop\u00e4dischen Artikeln",
    "sg:postcode":"6003",
    "sg:province":"Luzern",
    "wof:name":"H\u00f6rakustik H\u00f6rmann Ag",
    "wof:placetype":"venue"
},
  "geometry": {"coordinates":[8.307682991,47.0469169617],"type":"Point"}
}