{
  "type": "Feature",
  "properties": {
    "iso:country":"CH",
    "sg:address":"Aernih\u00fcsli",
    "sg:city":"Sch\u00fcpfheim",
    "sg:orig_category":"Wohnheime",
    "sg:postcode":"6170",
    "sg:province":"Luzern",
    "wof:name":"Stiftung Werken Und Wohnen F\u00fcr Behinderte Im Entlebuch",
    "wof:placetype":"venue"
},
  "geometry": {"coordinates":[8.0194749832,46.9536094666],"type":"Point"}
}