{
  "type": "Feature",
  "properties": {
    "iso:country":"CH",
    "sg:address":"David-moning-strasse 7 2504 Biel/bienne. Postfach 352",
    "sg:city":"Biel/bienne",
    "sg:orig_category":"Oberfl\u00e4chenveredlung U W\u00e4rmebehandlung",
    "sg:phone":"+41 22 989 89 89",
    "sg:postcode":"2501",
    "sg:province":"Bern",
    "wof:name":"Praxair Surface Technologies (europe) Sa",
    "wof:placetype":"venue"
},
  "geometry": {"coordinates":[6.062048912,46.227432251],"type":"Point"}
}