{
  "type": "Feature",
  "properties": {
    "iso:country":"CH",
    "sg:address":"Strehlgasse 19 8704 Herrliberg. Postfach",
    "sg:city":"Herrliberg",
    "sg:orig_category":"Handelsvermittlung von Brennstoffen, Erzen, Metallen U Chemikalien",
    "sg:phone":"+41 19158585",
    "sg:postcode":"8704",
    "sg:province":"Z\u00fcrich",
    "wof:name":"Iko-trading Gmbh Waren, Bes. Rohstoffe U. Lebensmittel; Handel",
    "wof:placetype":"venue"
},
  "geometry": {"coordinates":[8.6077880859,47.2903404236],"type":"Point"}
}