{
  "type": "Feature",
  "properties": {
    "iso:country":"CH",
    "sg:address":"Langmauerweg 15c 3011 Bern. Postfach",
    "sg:city":"Bern",
    "sg:orig_category":"Werbung",
    "sg:postcode":"3005",
    "sg:province":"Bern",
    "wof:name":"Zaugg Daniel, Atelier F\u00fcr Werbe Und Pressefoto",
    "wof:placetype":"venue"
},
  "geometry": {"coordinates":[7.4563422203,46.9497184753],"type":"Point"}
}