{
  "type": "Feature",
  "properties": {
    "iso:country":"CH",
    "sg:address":"Badstrasse 33",
    "sg:city":"Niederurnen",
    "sg:orig_category":"Gartenbau",
    "sg:phone":"+41 55 620 15 58",
    "sg:postcode":"8867",
    "sg:province":"Glarus",
    "wof:name":"Heribert Bachl Netstal Gartenunterhalt Inh.h.zahner",
    "wof:placetype":"venue"
},
  "geometry": {"coordinates":[9.0532903671,47.127872467],"type":"Point"}
}