{
  "type": "Feature",
  "properties": {
    "iso:country":"CH",
    "sg:address":"Avenue C.-f.-ramuz 92",
    "sg:city":"Pully",
    "sg:orig_category":"Kosmetikinstitute",
    "sg:phone":"+41 79 417 18 02",
    "sg:postcode":"1009",
    "sg:province":"Vaud",
    "wof:name":"Farida Bouali Institut De Beaut\u00e9 Fyms",
    "wof:placetype":"venue"
},
  "geometry": {"coordinates":[6.6424298286,46.5097389221],"type":"Point"}
}