{
  "type": "Feature",
  "properties": {
    "iso:country":"CH",
    "sg:address":"Industriestrasse 1",
    "sg:city":"Volketswil",
    "sg:orig_category":"Unclassifiable Establishments",
    "sg:postcode":"8604",
    "sg:province":"Z\u00fcrich",
    "wof:name":"Kleiner Konditorei-b\u00e4ckerei Ag",
    "wof:placetype":"venue"
},
  "geometry": {"coordinates":[8.6681413651,47.3819656372],"type":"Point"}
}