{
  "type": "Feature",
  "properties": {
    "iso:country":"CH",
    "sg:address":"Birkenstrasse 27 4055 Basel. Postfach",
    "sg:city":"Basel",
    "sg:orig_category":"Sonstige pers\u00f6nliche Dienstleistungen",
    "sg:phone":"+41 61 301 40 25",
    "sg:postcode":"4051",
    "sg:province":"Basel-Stadt",
    "wof:name":"Meili.ch Therapie, Trainings- U. Gesundheitskonzepte U. -systeme; Entwickl., Produzieren, Verkaufen",
    "wof:placetype":"venue"
},
  "geometry": {"coordinates":[7.5735559464,47.5570373535],"type":"Point"}
}