{
  "type": "Feature",
  "properties": {
    "iso:country":"CH",
    "sg:address":"L\u00f6chliweg 27",
    "sg:city":"Bern",
    "sg:orig_category":"Agriculture and Livestock Business advice and other services Horticulture Professional bodies",
    "sg:phone":"+41 31 330 40 40",
    "sg:postcode":"3014",
    "sg:province":"Bern",
    "wof:name":"Blumenb\u00d6rse Bern",
    "wof:placetype":"venue"
},
  "geometry": {"coordinates":[7.466581,46.970112],"type":"Point"}
}