{
  "type": "Feature",
  "properties": {
    "iso:country":"CH",
    "sg:address":"Rue De Neuch\u00e2tel 42 1400 Yverdon-les-bains. Postfach",
    "sg:city":"Yverdon",
    "sg:classifiers":[
        {
            "category":"Insurance",
            "subcategory":"Insurance Agent",
            "type":"Services"
        }
    ],
    "sg:phone":"+41 79 636 19 22",
    "sg:postcode":"1401",
    "sg:province":"Vaud",
    "sg:tags":[
        "versicherungsagenturen",
        "-broker"
    ],
    "wof:name":"Secura Versicherungen Agentur",
    "wof:placetype":"venue"
},
  "geometry": {"coordinates":[8.9727392197,47.4674873352],"type":"Point"}
}