{
  "type": "Feature",
  "properties": {
    "iso:country":"CH",
    "sg:address":"Kopfgasse 4 8180 B\u00fclach. Postfach",
    "sg:city":"B\u00fclach",
    "sg:orig_category":"Herstellung von Schmuck, Gold U Silberschmiedwaren Kunsthandel",
    "sg:phone":"+41 18608566",
    "sg:postcode":"8180",
    "sg:province":"Z\u00fcrich",
    "wof:name":"Quadro, Cusumano Francesco Inh. Francesco Cusumano",
    "wof:placetype":"venue"
},
  "geometry": {"coordinates":[8.5415868759,47.5186882019],"type":"Point"}
}