{
  "type": "Feature",
  "properties": {
    "iso:country":"CH",
    "sg:address":"Correvon Rue Henry 13",
    "sg:city":"Yverdon-les-bains",
    "sg:orig_category":"Non-Classified Establishments",
    "sg:phone":"+41 24 425 41 75",
    "sg:postcode":"1400",
    "sg:province":"Vaud",
    "wof:name":"Alfredo Vieira",
    "wof:placetype":"venue"
},
  "geometry": {"coordinates":[6.6557731628,46.7774772644],"type":"Point"}
}