{
  "type": "Feature",
  "properties": {
    "iso:country":"CH",
    "sg:address":"Kantonsstrasse 32 3930 Visp. Postfach",
    "sg:city":"Visp",
    "sg:orig_category":"Grosshandel mit Eisenwaren sowie Installationsbedarf f\u00fcr Gas, Wasser U Heizung Grosshandel mit Holz ",
    "sg:phone":"+41 27 948 84 30",
    "sg:postcode":"3930",
    "sg:province":"Valais",
    "wof:name":"Bringhen Ag Handel Mit Baumaterialien",
    "wof:placetype":"venue"
},
  "geometry": {"coordinates":[7.88915205,46.2920303345],"type":"Point"}
}