{
  "type": "Feature",
  "properties": {
    "iso:country":"CH",
    "sg:address":"Via Nuova",
    "sg:city":"Poschiavo",
    "sg:orig_category":"Sportvereine Velo Rad-& Motorfahrer-Bund SRB",
    "sg:postcode":"7742",
    "sg:province":"Graubunden",
    "wof:name":"Veloclub Vals",
    "wof:placetype":"venue"
},
  "geometry": {"coordinates":[8.4509782791,47.277305603],"type":"Point"}
}