{
  "type": "Feature",
  "properties": {
    "addr:full":"Grubenstrasse 79 8200 Schaffhausen. Postfach 20 Schaffhausen 8206",
    "addr:housenumber":"79;20",
    "addr:postcode":"8200 schaffhausen.;8206",
    "addr:street":"Grubenstrasse;Postfach",
    "iso:country":"CH",
    "sg:address":"Grubenstrasse 79 8200 Schaffhausen. Postfach 20",
    "sg:city":"Schaffhausen",
    "sg:orig_category":"Autogaragen",
    "sg:phone":"+41 52 625 62 23",
    "sg:postcode":"8206",
    "wof:name":"Benny Baldinger Garage",
    "wof:placetype":"venue"
},
  "geometry": {"coordinates":[8.645302,47.703388],"type":"Point"}
}