{
  "type": "Feature",
  "properties": {
    "iso:country":"CH",
    "sg:address":"In Letten 4",
    "sg:city":"Dietlikon",
    "sg:orig_category":"Grosshandel mit Software",
    "sg:phone":"+41 18331542",
    "sg:postcode":"8305",
    "sg:province":"Z\u00fcrich",
    "wof:name":"Qdatech Gmbh Q-datentechnik",
    "wof:placetype":"venue"
},
  "geometry": {"coordinates":[8.6114196777,47.4250144958],"type":"Point"}
}