{
  "type": "Feature",
  "properties": {
    "iso:country":"CH",
    "sg:address":"Obere Steingrubenstrasse 44",
    "sg:city":"Solothurn",
    "sg:orig_category":"Sonstige Aktivit\u00e4ten der nicht-\u00e4rztlichen Medizinalberufe",
    "sg:phone":"+41 32 622 87 62",
    "sg:postcode":"4500",
    "sg:province":"Solothurn",
    "wof:name":"Heinz Krapf Atemtherapie",
    "wof:placetype":"venue"
},
  "geometry": {"coordinates":[7.5346889496,47.2173614502],"type":"Point"}
}