{
  "type": "Feature",
  "properties": {
    "iso:country":"CH",
    "sg:address":"Haus Marina Betlis",
    "sg:city":"Amden",
    "sg:orig_category":"Dienstleistungen von Beteiligungsgesellschaften",
    "sg:postcode":"8873",
    "sg:province":"St. Gallen",
    "wof:name":"Oggenfuss R. + G., B\u00fcro F. Admin. Dienstleistungen",
    "wof:placetype":"venue"
},
  "geometry": {"coordinates":[9.1382074356,47.1490058899],"type":"Point"}
}