{
  "type": "Feature",
  "properties": {
    "iso:country":"CH",
    "sg:address":"Gishubel 2",
    "sg:city":"Richenthal",
    "sg:orig_category":"Grosshandel mit Nahrungsmitteln, Getr\u00e4nken U Tabakwaren Grosshandel mit medizinischen U orthop\u00e4disch",
    "sg:phone":"+41 62 758 16 36",
    "sg:postcode":"6263",
    "sg:province":"Luzern",
    "wof:name":"Von Senger & Co S & B Handelshaus",
    "wof:placetype":"venue"
},
  "geometry": {"coordinates":[7.9437499046,47.217124939],"type":"Point"}
}