{
  "type": "Feature",
  "properties": {
    "addr:full":"B\u00e4rengasse 1 Glarus Glarus 8750",
    "addr:housenumber":"1",
    "addr:postcode":"8750",
    "addr:street":"Baerengasse",
    "iso:country":"CH",
    "sg:address":"B\u00e4rengasse 1",
    "sg:city":"Glarus",
    "sg:classifiers":[
        {
            "category":"Banks & Credit Unions",
            "subcategory":"Bank",
            "type":"Services"
        }
    ],
    "sg:phone":"+41 58 616 01 61",
    "sg:postcode":"8750",
    "sg:province":"Glarus",
    "wof:name":"Swiss Bank Corp.",
    "wof:placetype":"venue"
},
  "geometry": {"coordinates":[9.06935,47.039371],"type":"Point"}
}