{
  "type": "Feature",
  "properties": {
    "iso:country":"CH",
    "sg:address":"Gaicht",
    "sg:city":"Twann",
    "sg:classifiers":[
        {
            "category":"Restaurant",
            "type":"Food & Drink"
        }
    ],
    "sg:phone":"+41 32 315 11 16",
    "sg:postcode":"2513",
    "sg:province":"Bern",
    "wof:name":"Restaurant Tanne",
    "wof:placetype":"venue"
},
  "geometry": {"coordinates":[7.16726017,47.1079750061],"type":"Point"}
}