{
  "type": "Feature",
  "properties": {
    "iso:country":"CH",
    "sg:address":"Eichmatt 5",
    "sg:city":"Rotkreuz",
    "sg:orig_category":"Wirtschaftspr\u00fcfung, Steuerberatung U Treuhand",
    "sg:phone":"+41 41 790 05 09",
    "sg:postcode":"6343",
    "sg:province":"Zug",
    "wof:name":"Mtb Treuhand, Benz Maria-theresia",
    "wof:placetype":"venue"
},
  "geometry": {"coordinates":[8.4246482849,47.1351928711],"type":"Point"}
}