{
  "type": "Feature",
  "properties": {
    "iso:country":"CH",
    "sg:address":"H\u00f6henstrasse 9",
    "sg:city":"Edlibach",
    "sg:orig_category":"Non-Classified Establishments",
    "sg:postcode":"6313",
    "sg:province":"Zug",
    "wof:name":"All4you By Jutz",
    "wof:placetype":"venue"
},
  "geometry": {"coordinates":[8.5722827911,47.182598114],"type":"Point"}
}