{
  "type": "Feature",
  "properties": {
    "iso:country":"CH",
    "sg:address":"Stieg 413 9492 Eschen. Postfach 140",
    "sg:city":"Eschen",
    "sg:orig_category":"Kunsthandel",
    "sg:phone":"+41 75 232 13 79",
    "sg:postcode":"9492",
    "wof:name":"Susi Nissl Kunsthandel",
    "wof:placetype":"venue"
},
  "geometry": {"coordinates":[9.515337944,47.2179679871],"type":"Point"}
}