{
  "type": "Feature",
  "properties": {
    "iso:country":"CH",
    "sg:address":"Forchstrasse 178 8125 Zollikerberg. Postfach",
    "sg:city":"Zollikerberg",
    "sg:orig_category":"Unclassifiable Establishments",
    "sg:phone":"+41 13914502",
    "sg:postcode":"8125",
    "sg:province":"Z\u00fcrich",
    "wof:name":"Galbier Gmbh",
    "wof:placetype":"venue"
},
  "geometry": {"coordinates":[8.6019773483,47.3461608887],"type":"Point"}
}