{
  "type": "Feature",
  "properties": {
    "iso:country":"CH",
    "sg:address":"Sustenstrasse 3",
    "sg:city":"Susten",
    "sg:orig_category":"Gemeindeverwaltungen",
    "sg:phone":"+41 27 474 96 60",
    "sg:postcode":"3952",
    "sg:province":"Valais",
    "wof:name":"Gemeindeverwaltung Leuk",
    "wof:placetype":"venue"
},
  "geometry": {"coordinates":[7.6406021118,46.3115959167],"type":"Point"}
}