{
  "type": "Feature",
  "properties": {
    "iso:country":"CH",
    "sg:address":"Ribi 6465 Untersch\u00e4chen. Postfach",
    "sg:city":"Untersch\u00e4chen",
    "sg:orig_category":"Zimmerei, Dachdeckerei, Bauspenglerei U Abdichtung",
    "sg:postcode":"6465",
    "sg:province":"Uri",
    "wof:name":"Klaus Arnold, Holzbau",
    "wof:placetype":"venue"
},
  "geometry": {"coordinates":[8.7818813324,46.864276886],"type":"Point"}
}