{
  "type": "Feature",
  "properties": {
    "iso:country":"CH",
    "sg:address":"Stampfenbachstrasse 42",
    "sg:city":"Z\u00fcrich",
    "sg:orig_category":"Zahnarztpraxen",
    "sg:phone":"+41 81 750 07 00",
    "sg:postcode":"8006",
    "sg:province":"Z\u00fcrich",
    "wof:name":"Dr.med.dent.urs Sch\u00f6nenberger Zahnarzt",
    "wof:placetype":"venue"
},
  "geometry": {"coordinates":[9.4717073441,47.1658706665],"type":"Point"}
}