{
  "type": "Feature",
  "properties": {
    "addr:full":"Avenue Des Sports 11 Yverdon Vaud 1400",
    "addr:housenumber":"11",
    "addr:postcode":"1400",
    "addr:street":"Avenue Des Sports",
    "iso:country":"CH",
    "sg:address":"Avenue Des Sports 11",
    "sg:city":"Yverdon",
    "sg:classifiers":[
        {
            "category":"Bars & Pubs",
            "subcategory":"Gay Bar",
            "type":"Food & Drink"
        }
    ],
    "sg:phone":"+41 24 426 92 85",
    "sg:postcode":"1400",
    "sg:province":"Vaud",
    "sg:tags":[
        "chemical",
        "pharmaceutical",
        "product",
        "chemistry",
        "related"
    ],
    "wof:name":"Arkina Sa",
    "wof:placetype":"venue"
},
  "geometry": {"coordinates":[6.670759,46.781742],"type":"Point"}
}