{
  "type": "Feature",
  "properties": {
    "iso:country":"CH",
    "sg:address":"Oberdorfstrasse 4",
    "sg:city":"H\u00fcttlingen",
    "sg:classifiers":[
        {
            "category":"Insurance",
            "subcategory":"Insurance Agent",
            "type":"Services"
        }
    ],
    "sg:phone":"+41 52 765 13 75",
    "sg:postcode":"8553",
    "sg:province":"Thurgau",
    "sg:tags":[
        "versicherungsagenturen",
        "-broker"
    ],
    "wof:name":"Z\u00fcrich-versicherungen Agentur",
    "wof:placetype":"venue"
},
  "geometry": {"coordinates":[8.9688920975,47.5762329102],"type":"Point"}
}