{
  "type": "Feature",
  "properties": {
    "iso:country":"CH",
    "sg:address":"Altstetterstrasse 145",
    "sg:city":"Z\u00fcrich",
    "sg:orig_category":"Detailhandel mit Damenbekleidung Detailhandel mit Herrenbekleidung",
    "sg:phone":"+41 81 740 03 10",
    "sg:postcode":"8048",
    "sg:province":"Z\u00fcrich",
    "wof:name":"Willy Korn Ag Jeans Shop",
    "wof:placetype":"venue"
},
  "geometry": {"coordinates":[9.471824646,47.1656150818],"type":"Point"}
}