{
  "type": "Feature",
  "properties": {
    "iso:country":"CH",
    "sg:address":"Alte Landstrasse 18",
    "sg:city":"Eglisau",
    "sg:orig_category":"Herstellung von sonstigen landwirtschaftlichen Maschinen",
    "sg:postcode":"8193",
    "sg:province":"Z\u00fcrich",
    "wof:name":"Bigab Farma Swiss Gmbh",
    "wof:placetype":"venue"
},
  "geometry": {"coordinates":[8.5242233276,47.5717544556],"type":"Point"}
}