{
  "type": "Feature",
  "properties": {
    "iso:country":"CH",
    "sg:address":"Thurfeldstrasse 5",
    "sg:city":"Bischofszell",
    "sg:orig_category":"Kalb U Schweine-M\u00e4sterei U Zucht",
    "sg:postcode":"9220",
    "sg:province":"Thurgau",
    "wof:name":"Schweinezucht Muggensturm Ag, Bischofszell",
    "wof:placetype":"venue"
},
  "geometry": {"coordinates":[9.2271671295,47.4926948547],"type":"Point"}
}