{
  "type": "Feature",
  "properties": {
    "iso:country":"CH",
    "sg:address":"Burgmatt 11",
    "sg:city":"Baar",
    "sg:orig_category":"Sonstige mit der Informatik verbundene T\u00e4tigkeiten",
    "sg:phone":"+41 41 763 07 95",
    "sg:postcode":"6340",
    "sg:province":"Zug",
    "wof:name":"N\u00fcnlist Informatik",
    "wof:placetype":"venue"
},
  "geometry": {"coordinates":[8.5262966156,47.1947250366],"type":"Point"}
}