{
  "type": "Feature",
  "properties": {
    "iso:country":"CH",
    "sg:address":"Siewerdtstrasse 105",
    "sg:city":"Z\u00fcrich",
    "sg:orig_category":"Unternehmensberatung",
    "sg:phone":"+41 32 344 06 78",
    "sg:postcode":"8050",
    "sg:province":"Z\u00fcrich",
    "wof:name":"Business Start Center Bsc Ag Beratung U. Planung Im Bereiche Von Unternehmensgr\u00fcndungen. Planung, Konzeptionierung U. Realisierung Von Generalvorhaben Usw",
    "wof:placetype":"venue"
},
  "geometry": {"coordinates":[7.266201973,47.1440238953],"type":"Point"}
}