{
  "type": "Feature",
  "properties": {
    "iso:country":"CH",
    "sg:address":"Felbenstrasse 16",
    "sg:city":"Goldach",
    "sg:classifiers":[
        {
            "category":"Wholesale",
            "subcategory":"Chemicals & Plastics",
            "type":"Manufacturing & Wholesale Goods"
        }
    ],
    "sg:phone":"+41 71 841 42 48",
    "sg:postcode":"9403",
    "sg:province":"St. Gallen",
    "sg:tags":[
        "pipe",
        "industrial",
        "cleaning"
    ],
    "wof:name":"Zuka Gmbh",
    "wof:placetype":"venue"
},
  "geometry": {"coordinates":[9.4681463242,47.4852104187],"type":"Point"}
}