{
  "type": "Feature",
  "properties": {
    "iso:country":"CH",
    "sg:address":"Vall\u00e9estrasse 133a",
    "sg:city":"Vals",
    "sg:orig_category":"Detailhandel mit Waren verschiedener Art, Hauptrichtung Nahrungsmittel",
    "sg:phone":"+41 18690863",
    "sg:postcode":"7132",
    "sg:province":"Graubunden",
    "wof:name":"Landwirtschaftliche Konsumgenossenschaft Wil",
    "wof:placetype":"venue"
},
  "geometry": {"coordinates":[8.5070877075,47.605594635],"type":"Point"}
}