{
  "type": "Feature",
  "properties": {
    "iso:country":"CH",
    "sg:address":"Wiler Strasse 55",
    "sg:city":"Sirnach",
    "sg:orig_category":"Kosmetikinstitute",
    "sg:phone":"+41 71 966 40 44",
    "sg:postcode":"8370",
    "sg:province":"Thurgau",
    "wof:name":"Beaurty Inn Ag",
    "wof:placetype":"venue"
},
  "geometry": {"coordinates":[9.0094470978,47.4641113281],"type":"Point"}
}