{
  "type": "Feature",
  "properties": {
    "iso:country":"CH",
    "sg:city":"Zeneggen",
    "sg:orig_category":"Reisen, Unterk\u00fcnfte",
    "sg:postcode":"3934",
    "sg:province":"Valais",
    "wof:name":"Hotel Alpenblick Zeneggen",
    "wof:placetype":"venue"
},
  "geometry": {"coordinates":[7.86641,46.273006],"type":"Point"}
}