{
  "type": "Feature",
  "properties": {
    "iso:country":"CH",
    "sg:address":"Grossmattstrasse 3",
    "sg:city":"H\u00e4gendorf",
    "sg:orig_category":"Softwareentwicklung U beratung Sonstige mit der Informatik verbundene T\u00e4tigkeiten",
    "sg:phone":"+41 62 297 18 28",
    "sg:postcode":"4614",
    "sg:province":"Solothurn",
    "wof:name":"Meister Oliver Creabyte",
    "wof:placetype":"venue"
},
  "geometry": {"coordinates":[7.8473501205,47.3293113708],"type":"Point"}
}