{
  "type": "Feature",
  "properties": {
    "iso:country":"CH",
    "sg:address":"Rindelstrasse 9",
    "sg:city":"Arth",
    "sg:orig_category":"Maler U Glasergewerbe",
    "sg:phone":"+41 41 855 35 13",
    "sg:postcode":"6415",
    "sg:province":"Schwyz",
    "wof:name":"Tapeziergesch\u00e4ft Peter Romer",
    "wof:placetype":"venue"
},
  "geometry": {"coordinates":[8.5246047974,47.0612220764],"type":"Point"}
}