{
  "type": "Feature",
  "properties": {
    "iso:country":"CH",
    "sg:address":"Dorfstrasse 33",
    "sg:city":"H\u00fcntwangen",
    "sg:orig_category":"Architektur U Ingenieurb\u00fcros",
    "sg:postcode":"8194",
    "sg:province":"Z\u00fcrich",
    "wof:name":"Gfeller Gilbert Dipl. Arch. Eth Sia",
    "wof:placetype":"venue"
},
  "geometry": {"coordinates":[8.493975,47.594734],"type":"Point"}
}