{
  "type": "Feature",
  "properties": {
    "addr:full":"Kirchplatz Heiden Appenzell Ausserrhoden 9410",
    "addr:postcode":"9410",
    "addr:street":"Kirchplatz;Ausserrhoden",
    "iso:country":"CH",
    "sg:address":"Kirchplatz",
    "sg:city":"Heiden",
    "sg:classifiers":[
        {
            "category":"Banks & Credit Unions",
            "subcategory":"Bank",
            "type":"Services"
        }
    ],
    "sg:phone":"+41 4171913752",
    "sg:postcode":"9410",
    "sg:province":"Appenzell Ausserrhoden",
    "wof:name":"Appenzell-ausserrhodische, Kantonalbank",
    "wof:placetype":"venue"
},
  "geometry": {"coordinates":[9.534922,47.445335],"type":"Point"}
}