{
  "type": "Feature",
  "properties": {
    "iso:country":"CH",
    "sg:address":"Heimigen",
    "sg:city":"Wyssachen",
    "sg:orig_category":"Detailhandel mit Sportartikeln Herstellung von Konstruktionsteilen, Fertigbauteilen U Ausbauelemente",
    "sg:phone":"+41 34 445 18 28",
    "sg:postcode":"4954",
    "sg:province":"Bern",
    "wof:name":"H. Habegger",
    "wof:placetype":"venue"
},
  "geometry": {"coordinates":[7.5834112167,47.0850944519],"type":"Point"}
}