{
  "type": "Feature",
  "properties": {
    "iso:country":"CH",
    "sg:address":"Dachslernstrasse 22",
    "sg:city":"Z\u00fcrich",
    "sg:orig_category":"Forschung U Entwicklung im Bereich der Naturwissenschaften",
    "sg:postcode":"8048",
    "sg:province":"Z\u00fcrich",
    "wof:name":"Gesellschaft F\u00fcr Schweizer Unterwasser-arch\u00e4ologie",
    "wof:placetype":"venue"
},
  "geometry": {"coordinates":[8.4803733826,47.388633728],"type":"Point"}
}