{
  "type": "Feature",
  "properties": {
    "iso:country":"CH",
    "sg:address":"Rue Du Paddock 14",
    "sg:city":"Bassecourt",
    "sg:orig_category":"Physiotherapie",
    "sg:phone":"+41 32 426 54 25",
    "sg:postcode":"2854",
    "sg:province":"Jura",
    "wof:name":"Philippe Mottiez Physioth\u00e9rapie",
    "wof:placetype":"venue"
},
  "geometry": {"coordinates":[7.2376441956,47.3348312378],"type":"Point"}
}