{
  "type": "Feature",
  "properties": {
    "iso:country":"CH",
    "sg:address":"Rosengartenstrasse 2 6440 Brunnen. Postfach 337",
    "sg:city":"Brunnen",
    "sg:orig_category":"Mechanik Schlossereien",
    "sg:phone":"+41 79 644 25 88",
    "sg:postcode":"6440",
    "sg:province":"Schwyz",
    "wof:name":"Toni Wenger",
    "wof:placetype":"venue"
},
  "geometry": {"coordinates":[7.597342968,47.4720573425],"type":"Point"}
}