{
  "type": "Feature",
  "properties": {
    "iso:country":"CH",
    "sg:address":"Geissensteinring 41",
    "sg:city":"Luzern",
    "sg:classifiers":[
        {
            "category":"Communications",
            "subcategory":"Film & Video Production",
            "type":"Services"
        }
    ],
    "sg:phone":"+41 32 724 28 23",
    "sg:postcode":"6005",
    "sg:province":"Luzern",
    "sg:tags":[
        "videofilmherstellung",
        "u"
    ],
    "wof:name":"Cantin & Cie Productions Vid\u00e9o & Films",
    "wof:placetype":"venue"
},
  "geometry": {"coordinates":[6.916413784,46.9915237427],"type":"Point"}
}