{
  "type": "Feature",
  "properties": {
    "addr:full":"Champs-montants 12b Marin-epagnier Neuch\u00e2tel 2074",
    "addr:housenumber":"12b",
    "addr:postcode":"2074",
    "addr:street":"Champs-Montants;Neucha\u0302Tel",
    "iso:country":"CH",
    "sg:address":"Champs-montants 12b",
    "sg:city":"Marin-epagnier",
    "sg:classifiers":[
        {
            "category":"Wholesale",
            "subcategory":"Machinery & Supplies",
            "type":"Manufacturing & Wholesale Goods"
        }
    ],
    "sg:phone":"+41 32 751 27 43",
    "sg:postcode":"2074",
    "sg:province":"Neuch\u00e2tel",
    "sg:tags":[
        "equipment",
        "equipement",
        "precision",
        "timekeeping"
    ],
    "wof:name":"Aigat Sa",
    "wof:placetype":"venue"
},
  "geometry": {"coordinates":[7.08745,47.061321],"type":"Point"}
}