{
  "type": "Feature",
  "properties": {
    "iso:country":"CH",
    "sg:address":"Wehntalerstrasse 444",
    "sg:city":"Z\u00fcrich",
    "sg:classifiers":[
        {
            "category":"Restaurant",
            "type":"Food & Drink"
        }
    ],
    "sg:phone":"+41 13712881",
    "sg:postcode":"8046",
    "sg:province":"Z\u00fcrich",
    "wof:name":"Restaurant Frieden",
    "wof:placetype":"venue"
},
  "geometry": {"coordinates":[8.5132827759,47.4157409668],"type":"Point"}
}