{
  "type": "Feature",
  "properties": {
    "iso:country":"CH",
    "sg:address":"Wesemlinstrasse 25",
    "sg:city":"Luzern",
    "sg:orig_category":"Detailhandel mit Fahrr\u00e4dern Handel mit Motorr\u00e4dern, Teilen U Zubeh\u00f6r Instandhaltung U Reparatur von ",
    "sg:phone":"+41 41 420 72 20",
    "sg:postcode":"6006",
    "sg:province":"Luzern",
    "wof:name":"Bernhard Blum Velos Motorroller",
    "wof:placetype":"venue"
},
  "geometry": {"coordinates":[8.3095941544,47.0607719421],"type":"Point"}
}