{
  "type": "Feature",
  "properties": {
    "iso:country":"CH",
    "sg:address":"Bachstrasse 5",
    "sg:city":"Brig",
    "sg:orig_category":"Sonstiger Grosshandel",
    "sg:phone":"+41 27 923 34 15",
    "sg:postcode":"3900",
    "sg:province":"Valais",
    "wof:name":"Own, Monnier & Co.",
    "wof:placetype":"venue"
},
  "geometry": {"coordinates":[7.9945192337,46.3134803772],"type":"Point"}
}