{
  "type": "Feature",
  "properties": {
    "iso:country":"CH",
    "sg:address":"R\u00fctenenstrasse 30",
    "sg:city":"Killwangen",
    "sg:orig_category":"Handels-H\u00e4user U Gesellschaften",
    "sg:phone":"+41 56 402 10 40",
    "sg:postcode":"8956",
    "sg:province":"Aargau",
    "wof:name":"Schmid Vermittlungs Und Handelsagentur",
    "wof:placetype":"venue"
},
  "geometry": {"coordinates":[8.34877491,47.4299468994],"type":"Point"}
}