{
  "type": "Feature",
  "properties": {
    "iso:country":"CH",
    "sg:address":"Talstrasse 20 8001 Z\u00fcrich. Postfach",
    "sg:city":"Z\u00fcrich",
    "sg:orig_category":"Rechtsberatung Wirtschaftspr\u00fcfung, Steuerberatung U Treuhand",
    "sg:phone":"+41 71 966 39 33",
    "sg:postcode":"8022",
    "sg:province":"Z\u00fcrich",
    "wof:name":"K\u00f6nig Treuhand Ag Treuhandb\u00fcro",
    "wof:placetype":"venue"
},
  "geometry": {"coordinates":[9.0022296906,47.4901809692],"type":"Point"}
}