{
  "type": "Feature",
  "properties": {
    "iso:country":"CH",
    "sg:address":"Hausmattstrasse 5",
    "sg:city":"H\u00f6lstein",
    "sg:orig_category":"Hoch U Tiefbau",
    "sg:phone":"+41 61 951 13 79",
    "sg:postcode":"4434",
    "sg:province":"Basel-Landschaft",
    "wof:name":"Peter Hertenstein Bauunternehmung",
    "wof:placetype":"venue"
},
  "geometry": {"coordinates":[7.7733998299,47.4283256531],"type":"Point"}
}