{
  "type": "Feature",
  "properties": {
    "iso:country":"CH",
    "sg:address":"Wieshofstrasse 24",
    "sg:city":"Winterthur",
    "sg:classifiers":[
        {
            "category":"Professional",
            "subcategory":"Advertising",
            "type":"Services"
        }
    ],
    "sg:phone":"+41 52 222 01 48",
    "sg:postcode":"8408",
    "sg:province":"Z\u00fcrich",
    "sg:tags":[
        "sign"
    ],
    "wof:name":"Arthur Bachmann Schriften Ag",
    "wof:placetype":"venue"
},
  "geometry": {"coordinates":[8.675571,47.501999],"type":"Point"}
}