{
  "type": "Feature",
  "properties": {
    "iso:country":"CH",
    "sg:address":"Grand-pr\u00e9 Route Du 26",
    "sg:city":"Fribourg",
    "sg:orig_category":"Grosshandel mit Erzen U Metallen",
    "sg:phone":"+41 26 418 10 92",
    "sg:postcode":"1700",
    "sg:province":"Fribourg",
    "wof:name":"Extramet (international) Limited",
    "wof:placetype":"venue"
},
  "geometry": {"coordinates":[7.1639819145,46.8052864075],"type":"Point"}
}