{
  "type": "Feature",
  "properties": {
    "iso:country":"CH",
    "sg:address":"Cheminet Rue Du 26",
    "sg:city":"Yverdon-les-bains",
    "sg:orig_category":"Non-Classified Establishments",
    "sg:postcode":"1400",
    "sg:province":"Vaud",
    "wof:name":"Fondation Du Centre Logop\u00e9dique Et P\u00e9dagogique Du Nord Vaudois (clp)",
    "wof:placetype":"venue"
},
  "geometry": {"coordinates":[6.6302127838,46.7821540833],"type":"Point"}
}