{
  "type": "Feature",
  "properties": {
    "iso:country":"CH",
    "sg:address":"Gartenstrasse 15 4132 Muttenz. Postfach 78",
    "sg:city":"Muttenz",
    "sg:orig_category":"Pensionskassen",
    "sg:phone":"+41 61 467 67 67",
    "sg:postcode":"4132",
    "sg:province":"Basel-Landschaft",
    "wof:name":"Personalvorsorgestiftung Der Jauslin + Stebler, Ingenieure Ag",
    "wof:placetype":"venue"
},
  "geometry": {"coordinates":[7.645857811,47.5295333862],"type":"Point"}
}