{
  "type": "Feature",
  "properties": {
    "iso:country":"CH",
    "sg:address":"Eggishof",
    "sg:city":"Fruthwilen",
    "sg:orig_category":"Grosshandel mit Blumen U Pflanzen Grosshandel mit Getreide, Saatgut U Futtermitteln",
    "sg:phone":"+41 71 664 11 60",
    "sg:postcode":"8559",
    "wof:name":"D\u00e4hler Agro Ag",
    "wof:placetype":"venue"
},
  "geometry": {"coordinates":[27.1611003876,42.8340988159],"type":"Point"}
}