{
  "type": "Feature",
  "properties": {
    "iso:country":"CH",
    "sg:address":"Aeschwuhrstrasse 15",
    "sg:city":"Oftringen",
    "sg:orig_category":"Herstellung von sonstigen elektrischen Ausr\u00fcstungen",
    "sg:phone":"+41 79 330 59 15",
    "sg:postcode":"4665",
    "sg:province":"Aargau",
    "wof:name":"Elektro-woodtli Ag",
    "wof:placetype":"venue"
},
  "geometry": {"coordinates":[7.929693222,47.2992477417],"type":"Point"}
}