{
  "type": "Feature",
  "properties": {
    "iso:country":"CH",
    "sg:address":"Neustadtstrasse 44",
    "sg:city":"Luzern",
    "sg:orig_category":"Detailhandel mit Beleuchtungs U Haushaltsgegenst\u00e4nden Detailhandel mit elektrischen Haushalts, Radio",
    "sg:phone":"+41 19301949",
    "sg:postcode":"6003",
    "sg:province":"Luzern",
    "wof:name":"Hans Mittelholzer Haushaltapparate Beleuchtungen",
    "wof:placetype":"venue"
},
  "geometry": {"coordinates":[8.795511,47.326637],"type":"Point"}
}