{
  "type": "Feature",
  "properties": {
    "iso:country":"CH",
    "sg:address":"Im Grendel 13",
    "sg:city":"Eiken",
    "sg:orig_category":"Sonstige pers\u00f6nliche Dienstleistungen",
    "sg:postcode":"5074",
    "sg:province":"Aargau",
    "wof:name":"Buser + Co",
    "wof:placetype":"venue"
},
  "geometry": {"coordinates":[7.9863510132,47.5343856812],"type":"Point"}
}