{
  "type": "Feature",
  "properties": {
    "iso:country":"CH",
    "sg:address":"Route De Porrentruy 74",
    "sg:city":"Del\u00e9mont",
    "sg:orig_category":"Mechanik",
    "sg:phone":"+41 32 423 09 13",
    "sg:postcode":"2800",
    "sg:province":"Jura",
    "wof:name":"Ruiz Productions S\u00e0rl",
    "wof:placetype":"venue"
},
  "geometry": {"coordinates":[7.3354110718,47.3606529236],"type":"Point"}
}