{
  "type": "Feature",
  "properties": {
    "iso:country":"CH",
    "sg:address":"M\u00fchleweg 4",
    "sg:city":"W\u00fcrenlingen",
    "sg:classifiers":[
        {
            "category":"Social Services",
            "subcategory":"Retirement Home",
            "type":"Services"
        }
    ],
    "sg:phone":"+41 55 282 10 35",
    "sg:postcode":"5303",
    "sg:province":"Aargau",
    "sg:tags":[
        "pflegeheime",
        "u",
        "alters"
    ],
    "wof:name":"Altersheim",
    "wof:placetype":"venue"
},
  "geometry": {"coordinates":[8.921012,47.238621],"type":"Point"}
}