{
  "type": "Feature",
  "properties": {
    "iso:country":"CH",
    "sg:address":"Uttigenstrasse 3",
    "sg:city":"Uetendorf",
    "sg:orig_category":"Blumen U Zierpflanzenbau",
    "sg:phone":"+41 33 243 23 23",
    "sg:postcode":"3661",
    "sg:province":"Bern",
    "wof:name":"Rudolf Roggli Ag Pflanzenzucht & Samenbau",
    "wof:placetype":"venue"
},
  "geometry": {"coordinates":[7.586963,46.782387],"type":"Point"}
}