{
  "type": "Feature",
  "properties": {
    "iso:country":"CH",
    "sg:address":"Efringerstrasse 1",
    "sg:city":"Basel",
    "sg:orig_category":"RESTAURANTS: TEA-ROOMS",
    "sg:phone":"+41 61 692 11 75",
    "sg:postcode":"4051",
    "sg:province":"Basel-Stadt",
    "wof:name":"Restaurant Efringerhof, Iseini R.",
    "wof:placetype":"venue"
},
  "geometry": {"coordinates":[7.5963401794,47.5673561096],"type":"Point"}
}