{
  "type": "Feature",
  "properties": {
    "iso:country":"CH",
    "sg:address":"B\u00fcntackerstrasse 40",
    "sg:city":"Kriegstetten",
    "sg:orig_category":"Reparatur von Uhren U Schmuck",
    "sg:phone":"+41 32 675 53 26",
    "sg:postcode":"4566",
    "sg:province":"Solothurn",
    "wof:name":"Ren\u00e9 Brenckl\u00e9 Uhrenatelier",
    "wof:placetype":"venue"
},
  "geometry": {"coordinates":[7.595541954,47.173992157],"type":"Point"}
}