{
  "type": "Feature",
  "properties": {
    "iso:country":"CH",
    "sg:address":"Cantonale Via 17",
    "sg:city":"Lugano",
    "sg:orig_category":"Interessenvertretungen",
    "sg:postcode":"6900",
    "sg:province":"Ticino",
    "wof:name":"Associazione Evolution",
    "wof:placetype":"venue"
},
  "geometry": {"coordinates":[8.9503211975,46.0086708069],"type":"Point"}
}