{
  "type": "Feature",
  "properties": {
    "iso:country":"CH",
    "sg:address":"B\u00fcnzweg 1",
    "sg:city":"Othmarsingen",
    "sg:orig_category":"Architektur U Ingenieurb\u00fcros",
    "sg:postcode":"5504",
    "sg:province":"Aargau",
    "wof:name":"Sch\u00f6nenberger & Grau",
    "wof:placetype":"venue"
},
  "geometry": {"coordinates":[8.216001,47.400993],"type":"Point"}
}