{
  "type": "Feature",
  "properties": {
    "iso:country":"CH",
    "sg:address":"Ob. Bendlehn 25",
    "sg:city":"Speicher",
    "sg:orig_category":"Grosshandel mit Getr\u00e4nken",
    "sg:phone":"+41 71 344 10 19",
    "sg:postcode":"9042",
    "sg:province":"Appenzell Ausserrhoden",
    "wof:name":"Wuethrich Import + Handel",
    "wof:placetype":"venue"
},
  "geometry": {"coordinates":[9.4437513351,47.4104042053],"type":"Point"}
}