{
  "type": "Feature",
  "properties": {
    "iso:country":"CH",
    "sg:address":"Langenwilweg 47",
    "sg:city":"Schwarzenburg",
    "sg:orig_category":"Vermittlung von Immobilien Verwaltung von Immobilien",
    "sg:phone":"+41 31 731 26 06",
    "sg:postcode":"3150",
    "sg:province":"Bern",
    "wof:name":"Jean-pierre Weyermann Treuhandb\u00fcro",
    "wof:placetype":"venue"
},
  "geometry": {"coordinates":[7.337539196,46.8138275146],"type":"Point"}
}