{
  "type": "Feature",
  "properties": {
    "iso:country":"CH",
    "sg:address":"Oppligen 3629 Kiesen. Postfach",
    "sg:city":"Kiesen",
    "sg:orig_category":"Haltung von Rindern",
    "sg:postcode":"3629",
    "sg:province":"Bern",
    "wof:name":"Alpgenossenschaft Horrgass-kuchim\u00f6\u00f6sli",
    "wof:placetype":"venue"
},
  "geometry": {"coordinates":[7.5825629234,46.8194007874],"type":"Point"}
}