{
  "type": "Feature",
  "properties": {
    "iso:country":"CH",
    "sg:address":"Wiligraben 37 5603 Staufen. Postfach 65",
    "sg:city":"Staufen",
    "sg:orig_category":"Herstellung von Reiseartikeln, Leder U Sattlerwaren",
    "sg:phone":"+41 62 891 48 68",
    "sg:postcode":"5603",
    "sg:province":"Aargau",
    "wof:name":"Werner Rohr",
    "wof:placetype":"venue"
},
  "geometry": {"coordinates":[8.1707849503,47.383228302],"type":"Point"}
}