{
  "type": "Feature",
  "properties": {
    "iso:country":"CH",
    "sg:address":"Bahnhofstrasse 15",
    "sg:city":"Diessenhofen",
    "sg:orig_category":"Drogerien",
    "sg:phone":"+41 52 657 24 00",
    "sg:postcode":"8253",
    "sg:province":"Thurgau",
    "wof:name":"Drogerie Zwerger",
    "wof:placetype":"venue"
},
  "geometry": {"coordinates":[8.7519445419,47.6858940125],"type":"Point"}
}