{
  "type": "Feature",
  "properties": {
    "iso:country":"CH",
    "sg:address":"Neumattstrasse 4",
    "sg:city":"Belp",
    "sg:orig_category":"Detailhandel mit Waren verschiedener Art, Hauptrichtung Nahrungsmittel",
    "sg:phone":"+41 31 819 48 81",
    "sg:postcode":"3123",
    "sg:province":"Bern",
    "wof:name":"Migros-markt",
    "wof:placetype":"venue"
},
  "geometry": {"coordinates":[7.4957771301,46.8960800171],"type":"Point"}
}