{
  "type": "Feature",
  "properties": {
    "iso:country":"CH",
    "sg:address":"Werchlaubengasse 14 6000 Luzern. Postfach",
    "sg:city":"Luzern",
    "sg:orig_category":"Fachdetailhandel in Verkaufsr\u00e4umen",
    "sg:phone":"+41 41 412 39 90",
    "sg:postcode":"6000",
    "sg:province":"Luzern",
    "wof:name":"Viper Activewear Gmbh Freizeit Und Sportmode; Handel, Verkauf Usw",
    "wof:placetype":"venue"
},
  "geometry": {"coordinates":[8.305896759,47.0527305603],"type":"Point"}
}