{
  "type": "Feature",
  "properties": {
    "addr:full":"Rue Du Puits-godet 8a Neuch\u00e2tel Neuch\u00e2tel 2000",
    "addr:housenumber":"8a",
    "addr:postcode":"2000",
    "addr:street":"Rue Du Puits-Godet",
    "iso:country":"CH",
    "sg:address":"Rue Du Puits-godet 8a",
    "sg:city":"Neuch\u00e2tel",
    "sg:orig_category":"Datenverarbeitungsdienste Hardwareberatung",
    "sg:phone":"+41 32 724 74 34",
    "sg:postcode":"2000",
    "sg:province":"Neuch\u00e2tel",
    "wof:name":"Acn Advanced Communications Networks Sa",
    "wof:placetype":"venue"
},
  "geometry": {"coordinates":[6.91401,46.998722],"type":"Point"}
}