{
  "type": "Feature",
  "properties": {
    "iso:country":"CH",
    "sg:address":"Via San Gottardo 177",
    "sg:city":"Minusio",
    "sg:classifiers":[
        {
            "category":"Bars & Pubs",
            "type":"Food & Drink"
        }
    ],
    "sg:phone":"+41 91 743 23 44",
    "sg:postcode":"6648",
    "sg:province":"Ticino",
    "wof:name":"Bar Jolly",
    "wof:placetype":"venue"
},
  "geometry": {"coordinates":[8.825087,46.178936],"type":"Point"}
}