{
  "type": "Feature",
  "properties": {
    "iso:country":"CH",
    "sg:address":"Rue Du Temple 2",
    "sg:city":"Fleurier",
    "sg:orig_category":"Detailhandel mit elektrischen Haushalts-,Radio U Fernsehger\u00e4ten sowie Musikinstrumenten",
    "sg:phone":"+41 32 861 19 74",
    "sg:postcode":"2114",
    "sg:province":"Neuch\u00e2tel",
    "wof:name":"Fatton Francis Chauffages",
    "wof:placetype":"venue"
},
  "geometry": {"coordinates":[6.5843400955,46.9017715454],"type":"Point"}
}