{
  "type": "Feature",
  "properties": {
    "iso:country":"CH",
    "sg:address":"Maison Villageoise",
    "sg:city":"Seigneux",
    "sg:orig_category":"Reinigungsgewerbe",
    "sg:postcode":"1525",
    "sg:province":"Vaud",
    "wof:name":"Natec, Chassot Et Moser",
    "wof:placetype":"venue"
},
  "geometry": {"coordinates":[6.8782730103,46.7276344299],"type":"Point"}
}