{
  "type": "Feature",
  "properties": {
    "iso:country":"CH",
    "sg:address":"Rue Du Sablon 3",
    "sg:city":"Morges",
    "sg:orig_category":"Druck ohne Zeitungsdruck Offsetdruck",
    "sg:phone":"+41 21 801 42 86",
    "sg:postcode":"1110",
    "sg:province":"Vaud",
    "wof:name":"Pierre Degaudenzi Imprimerie Nouvelle",
    "wof:placetype":"venue"
},
  "geometry": {"coordinates":[6.4976201057,46.5124168396],"type":"Point"}
}