{
  "type": "Feature",
  "properties": {
    "iso:country":"CH",
    "sg:address":"Fl\u00fchgasse 31",
    "sg:city":"Z\u00fcrich",
    "sg:orig_category":"Instandhaltung U Reparatur von Automobilen",
    "sg:phone":"+41 31 738 81 88",
    "sg:postcode":"8008",
    "sg:province":"Z\u00fcrich",
    "wof:name":"Bartlome Ag",
    "wof:placetype":"venue"
},
  "geometry": {"coordinates":[7.4180898666,46.7700996399],"type":"Point"}
}