{
  "type": "Feature",
  "properties": {
    "iso:country":"CH",
    "sg:address":"Oberb\u00fcrglenweg 10",
    "sg:city":"Baar",
    "sg:orig_category":"Gesundheitswesen",
    "sg:postcode":"6340",
    "sg:province":"Zug",
    "wof:name":"Massage Fachschule Stiege, Untern\u00e4hrer Kurt",
    "wof:placetype":"venue"
},
  "geometry": {"coordinates":[8.6600856781,46.8742713928],"type":"Point"}
}