{
  "type": "Feature",
  "properties": {
    "addr:full":"Route Du Simplon 7 Mayens-de-saxon Valais 1907",
    "addr:housenumber":"7;1907",
    "addr:street":"Route Du Simplon",
    "iso:country":"CH",
    "sg:address":"Route Du Simplon 7",
    "sg:city":"Mayens-de-saxon",
    "sg:orig_category":"Architekturb\u00fcros",
    "sg:phone":"+41 27 744 33 01",
    "sg:postcode":"1907",
    "sg:province":"Valais",
    "wof:name":"V. Vouillamoz & A.-v. Nahrath Architectes Epfl",
    "wof:placetype":"venue"
},
  "geometry": {"coordinates":[7.179457,46.15184],"type":"Point"}
}