{
  "type": "Feature",
  "properties": {
    "iso:country":"CH",
    "sg:address":"Simmentalstrasse 3763 D\u00e4rstetten. Postfach",
    "sg:city":"D\u00e4rstetten",
    "sg:orig_category":"Detailhandel mit Waren verschiedener Art, Hauptrichtung Nahrungsmittel",
    "sg:postcode":"3763",
    "sg:province":"Bern",
    "wof:name":"Landwirtschaftliche Genossenschaft D\u00e4rstetten Und Umgebung",
    "wof:placetype":"venue"
},
  "geometry": {"coordinates":[7.4959168434,46.6583328247],"type":"Point"}
}