{
  "type": "Feature",
  "properties": {
    "iso:country":"CH",
    "sg:address":"Bahnhofstrasse 11",
    "sg:city":"Romanshorn",
    "sg:orig_category":"Werbung",
    "sg:postcode":"8590",
    "sg:province":"Thurgau",
    "wof:name":"Kuhn & Partner Gmbh",
    "wof:placetype":"venue"
},
  "geometry": {"coordinates":[9.3762760162,47.5658493042],"type":"Point"}
}