{
  "type": "Feature",
  "properties": {
    "iso:country":"CH",
    "sg:address":"Steinenvorstadt 23",
    "sg:city":"Basel",
    "sg:orig_category":"RESTAURANTS: TEA-ROOMS",
    "sg:phone":"+41 61 281 82 86",
    "sg:postcode":"4051",
    "sg:province":"Basel-Stadt",
    "wof:name":"Di\u00e4trestaurant Gleich, Inhaber Otto Kummer-dames",
    "wof:placetype":"venue"
},
  "geometry": {"coordinates":[7.5891580582,47.5532798767],"type":"Point"}
}