{
  "type": "Feature",
  "properties": {
    "iso:country":"CH",
    "sg:address":"Rennweg 28",
    "sg:city":"Z\u00fcrich",
    "sg:orig_category":"Vermietung U Verpachtung von eigenen Immobilien",
    "sg:phone":"+41 13831110",
    "sg:postcode":"8001",
    "sg:province":"Z\u00fcrich",
    "wof:name":"Forturenn Immobilien Ag Immob.-gesch\u00e4fte.",
    "wof:placetype":"venue"
},
  "geometry": {"coordinates":[8.5395679474,47.3732032776],"type":"Point"}
}