{
  "type": "Feature",
  "properties": {
    "iso:country":"CH",
    "sg:address":"S. Antonio",
    "sg:city":"Balerna",
    "sg:orig_category":"RESTAURANTS: TEA-ROOMS",
    "sg:postcode":"6828",
    "sg:province":"Ticino",
    "wof:name":"Caroccia Antonio",
    "wof:placetype":"venue"
},
  "geometry": {"coordinates":[9.005361557,45.8430099487],"type":"Point"}
}