{
  "type": "Feature",
  "properties": {
    "iso:country":"CH",
    "sg:address":"Beau-site Rue 1 A 1203 Gen\u00e8ve. Postfach",
    "sg:city":"Gen\u00e8ve",
    "sg:orig_category":"Herstellung von sonstigen Nahrungsmitteln",
    "sg:postcode":"1203",
    "sg:province":"Gen\u00e8ve",
    "wof:name":"Grand Gabriella Et Humbert Nathalie",
    "wof:placetype":"venue"
},
  "geometry": {"coordinates":[6.1298689842,46.2044525146],"type":"Point"}
}