{
  "type": "Feature",
  "properties": {
    "iso:country":"CH",
    "sg:address":"St\u00f6cken",
    "sg:city":"Rengg",
    "sg:orig_category":"Grosshandel mit Eisenwaren sowie Installationsbedarf f\u00fcr Gas, Wasser U Heizung Grosshandel mit sonst",
    "sg:phone":"+41 41 480 10 11",
    "sg:postcode":"6162",
    "sg:province":"Luzern",
    "wof:name":"Di\u00e9mo Handels Ag",
    "wof:placetype":"venue"
},
  "geometry": {"coordinates":[8.0649986267,46.9928016663],"type":"Point"}
}