{
  "type": "Feature",
  "properties": {
    "iso:country":"CH",
    "sg:address":"Poststrasse 2",
    "sg:city":"Lohn-ammannsegg",
    "sg:orig_category":"Detailhandel mit Waren verschiedener Art, Hauptrichtung Nahrungsmittel",
    "sg:phone":"+41 32 677 10 13",
    "sg:postcode":"4573",
    "sg:province":"Solothurn",
    "wof:name":"Coop Mittelland",
    "wof:placetype":"venue"
},
  "geometry": {"coordinates":[7.5239071846,47.1692581177],"type":"Point"}
}