{
  "type": "Feature",
  "properties": {
    "iso:country":"CH",
    "sg:address":"Rautistrasse 77",
    "sg:city":"Z\u00fcrich",
    "sg:orig_category":"Dienstleistungen von Beteiligungsgesellschaften Sonstige Finanzierungsinstitutionen",
    "sg:phone":"+41 41 632 68 58",
    "sg:postcode":"8048",
    "sg:province":"Z\u00fcrich",
    "wof:name":"Fabrel Ag",
    "wof:placetype":"venue"
},
  "geometry": {"coordinates":[8.314081192,46.9885826111],"type":"Point"}
}