{
  "type": "Feature",
  "properties": {
    "iso:country":"CH",
    "sg:address":"Luzernerstrasse 19 6415 Arth. Postfach 42",
    "sg:city":"Arth",
    "sg:orig_category":"Wohnheime",
    "sg:phone":"+41 41 855 21 80",
    "sg:postcode":"6415",
    "sg:province":"Schwyz",
    "wof:name":"Asylbewerber - Betreuung",
    "wof:placetype":"venue"
},
  "geometry": {"coordinates":[8.520275116,47.0618171692],"type":"Point"}
}