{
  "type": "Feature",
  "properties": {
    "iso:country":"CH",
    "sg:address":"Place Du Tilleul 7",
    "sg:city":"Savagnier",
    "sg:orig_category":"Bauspenglerei Sanit\u00e4rinstallation",
    "sg:phone":"+41 32 853 28 17",
    "sg:postcode":"2065",
    "sg:province":"Neuch\u00e2tel",
    "wof:name":"Gilbert Gyger Ferblanterie & Sanitaire",
    "wof:placetype":"venue"
},
  "geometry": {"coordinates":[6.952827,47.053696],"type":"Point"}
}