{
  "type": "Feature",
  "properties": {
    "iso:country":"CH",
    "sg:address":"Friedhofstrasse 4 8413 Neftenbach. Postfach 207",
    "sg:city":"Neftenbach",
    "sg:orig_category":"Detailhandel mit Blumen U Pflanzen Fachdetailhandel in Verkaufsr\u00e4umen",
    "sg:phone":"+41 52 315 18 25",
    "sg:postcode":"8413",
    "sg:province":"Z\u00fcrich",
    "wof:name":"Blumenschopf Oberholzer-hug Hans U. Hildegard",
    "wof:placetype":"venue"
},
  "geometry": {"coordinates":[8.670413,47.525291],"type":"Point"}
}