{
  "type": "Feature",
  "properties": {
    "iso:country":"CH",
    "sg:address":"Ruopigenring 49",
    "sg:city":"Littau",
    "sg:orig_category":"Unternehmensberatung",
    "sg:postcode":"6014",
    "sg:province":"Luzern",
    "wof:name":"K\u00fcchler Beratungen Ag",
    "wof:placetype":"venue"
},
  "geometry": {"coordinates":[8.2730026245,47.0626869202],"type":"Point"}
}