{
  "type": "Feature",
  "properties": {
    "iso:country":"CH",
    "sg:address":"Neustadtgasse 26",
    "sg:city":"Winterthur",
    "sg:orig_category":"Unternehmensberatung",
    "sg:phone":"+41 52 212 67 66",
    "sg:postcode":"8400",
    "sg:province":"Z\u00fcrich",
    "wof:name":"Heinz C. Schartel Unternehmensberatung",
    "wof:placetype":"venue"
},
  "geometry": {"coordinates":[8.7328424454,47.499370575],"type":"Point"}
}