{
  "type": "Feature",
  "properties": {
    "iso:country":"CH",
    "sg:address":"Gaiserstrasse 1",
    "sg:city":"Appenzell",
    "sg:classifiers":[
        {
            "category":"Restaurant",
            "type":"Food & Drink"
        }
    ],
    "sg:phone":"+41 71 787 11 17",
    "sg:postcode":"9050",
    "sg:province":"Appenzell Innerhoden",
    "wof:name":"Restaurant B\u00e4rli",
    "wof:placetype":"venue"
},
  "geometry": {"coordinates":[9.4109363556,47.3310012817],"type":"Point"}
}