{
  "type": "Feature",
  "properties": {
    "iso:country":"CH",
    "sg:address":"Altikofenstrasse 54",
    "sg:city":"Worblaufen",
    "sg:orig_category":"Unternehmensberatung",
    "sg:postcode":"3048",
    "sg:province":"Bern",
    "wof:name":"Toma Consulting Gmbh",
    "wof:placetype":"venue"
},
  "geometry": {"coordinates":[7.4635820389,46.981754303],"type":"Point"}
}