{
  "type": "Feature",
  "properties": {
    "iso:country":"CH",
    "sg:address":"Stegreutiweg 12 B",
    "sg:city":"M\u00fcnsingen",
    "sg:orig_category":"Herstellung von k\u00e4lte U lufttechnischen Erzeugnissen f\u00fcr gewerbliche Zwecke",
    "sg:postcode":"3110",
    "sg:province":"Bern",
    "wof:name":"Schramm Commissioning 6 Consulting",
    "wof:placetype":"venue"
},
  "geometry": {"coordinates":[8.2932138443,47.4866981506],"type":"Point"}
}