{
  "type": "Feature",
  "properties": {
    "iso:country":"CH",
    "sg:address":"B\u00fcrenstrasse 18a",
    "sg:city":"Lyss",
    "sg:orig_category":"Sanit\u00e4rinstallation Zimmerei, Dachdeckerei, Bauspenglerei U Abdichtung",
    "sg:phone":"+41 71 911 17 27",
    "sg:postcode":"3250",
    "sg:province":"Bern",
    "wof:name":"M\u00e4chler Franz",
    "wof:placetype":"venue"
},
  "geometry": {"coordinates":[9.0504388809,47.4666213989],"type":"Point"}
}