{
  "type": "Feature",
  "properties": {
    "iso:country":"CH",
    "sg:address":"Badenerstrasse 332",
    "sg:city":"Z\u00fcrich",
    "sg:orig_category":"Arbeitnehmerverb\u00e4nde",
    "sg:phone":"+41 14912581",
    "sg:postcode":"8004",
    "sg:province":"Z\u00fcrich",
    "wof:name":"Angestelltenverb\u00e4nde Vsa Vereinigung Schweiz.",
    "wof:placetype":"venue"
},
  "geometry": {"coordinates":[8.511494,47.377983],"type":"Point"}
}