{
  "type": "Feature",
  "properties": {
    "iso:country":"CH",
    "sg:address":"L\u00e4ngacker 3",
    "sg:city":"Subingen",
    "sg:classifiers":[
        {
            "category":"Professional",
            "subcategory":"Employment Agencies",
            "type":"Services"
        }
    ],
    "sg:postcode":"4553",
    "sg:province":"Solothurn",
    "sg:tags":[
        "personal",
        "u",
        "stellenvermittlung"
    ],
    "wof:name":"Job-line Tempor\u00e4r Service Rudiger H.",
    "wof:placetype":"venue"
},
  "geometry": {"coordinates":[7.6214032173,47.1983261108],"type":"Point"}
}