{
  "type": "Feature",
  "properties": {
    "iso:country":"CH",
    "sg:address":"Aeschenvorstadt 71 4051 Basel. Postfach",
    "sg:city":"Basel",
    "sg:orig_category":"Lichtpause U Reprografiebetriebe",
    "sg:phone":"+41 61 225 44 44",
    "sg:postcode":"4010",
    "sg:province":"Basel-Stadt",
    "wof:name":"World-wide Business Centers Ag",
    "wof:placetype":"venue"
},
  "geometry": {"coordinates":[7.5944361687,47.5518875122],"type":"Point"}
}