{
  "type": "Feature",
  "properties": {
    "iso:country":"CH",
    "sg:address":"Spalenring 11 4055 Basel. Postfach",
    "sg:city":"Basel",
    "sg:orig_category":"Detailhandel mit Schuhen Detailhandel mit Schuhen U Lederwaren",
    "sg:phone":"+41 61 302 47 35",
    "sg:postcode":"4012",
    "sg:province":"Basel-Stadt",
    "wof:name":"Huber Schuh Ag",
    "wof:placetype":"venue"
},
  "geometry": {"coordinates":[7.5743107796,47.5611953735],"type":"Point"}
}