{
  "type": "Feature",
  "properties": {
    "addr:full":"Ankerstrasse 113 8004 Z\u00fcrich. Postfach Z\u00fcrich Z\u00fcrich 8001",
    "addr:housenumber":"113",
    "addr:postcode":"8004 zuerich. postfach;8001",
    "addr:street":"Ankerstrasse",
    "iso:country":"CH",
    "sg:address":"Ankerstrasse 113 8004 Z\u00fcrich. Postfach",
    "sg:city":"Z\u00fcrich",
    "sg:classifiers":[
        {
            "category":"Bars & Pubs",
            "type":"Food & Drink"
        }
    ],
    "sg:postcode":"8001",
    "sg:province":"Z\u00fcrich",
    "wof:name":"Fanny Hill Bar, Inhaberin Jaksic D.",
    "wof:placetype":"venue"
},
  "geometry": {"coordinates":[8.527776,47.376308],"type":"Point"}
}