{
  "type": "Feature",
  "properties": {
    "iso:country":"CH",
    "sg:address":"Ueberbielstrasse 1 3930 Visp. Postfach",
    "sg:city":"Visp",
    "sg:classifiers":[
        {
            "category":"Restaurant",
            "type":"Food & Drink"
        }
    ],
    "sg:phone":"+41 27 946 21 30",
    "sg:postcode":"3930",
    "sg:province":"Valais",
    "wof:name":"Restaurant Old Dublin",
    "wof:placetype":"venue"
},
  "geometry": {"coordinates":[7.8816571236,46.2908401489],"type":"Point"}
}