{
  "type": "Feature",
  "properties": {
    "iso:country":"CH",
    "sg:address":"Steinhauserstrasse 29",
    "sg:city":"Zug",
    "sg:orig_category":"Unclassifiable Establishments",
    "sg:postcode":"6300",
    "sg:province":"Zug",
    "wof:name":"Hk Beratungen Gmbh",
    "wof:placetype":"venue"
},
  "geometry": {"coordinates":[8.4937448502,47.1837387085],"type":"Point"}
}