{
  "type": "Feature",
  "properties": {
    "iso:country":"CH",
    "sg:address":"Gaselstr. 10",
    "sg:city":"K\u00f6niz",
    "sg:orig_category":"Sonstige mit der Informatik verbundene T\u00e4tigkeiten",
    "sg:phone":"+41 31 952 76 48",
    "sg:postcode":"3098",
    "sg:province":"Bern",
    "wof:name":"Cyber Wolf",
    "wof:placetype":"venue"
},
  "geometry": {"coordinates":[7.4863967896,46.9318771362],"type":"Point"}
}