{
  "type": "Feature",
  "properties": {
    "iso:country":"CH",
    "sg:address":"Alpes Avenue Des 44 1006 Lausanne. Postfach",
    "sg:city":"Lausanne",
    "sg:orig_category":"K\u00fcnstlerische U schriftstellerische T\u00e4tigkeiten U Darbietungen",
    "sg:postcode":"1003",
    "sg:province":"Vaud",
    "wof:name":"Egemann - Music, E. Lackner",
    "wof:placetype":"venue"
},
  "geometry": {"coordinates":[8.2780704498,47.3505363464],"type":"Point"}
}