{
  "type": "Feature",
  "properties": {
    "iso:country":"CH",
    "sg:address":"2523",
    "sg:city":"Ligni\u00e8res",
    "sg:orig_category":"Vereine Gesang",
    "sg:postcode":"2523",
    "sg:province":"Neuch\u00e2tel",
    "wof:name":"Choeur Mixte L'avenir Ormont-dessus",
    "wof:placetype":"venue"
},
  "geometry": {"coordinates":[7.1587100029,46.3500404358],"type":"Point"}
}