{
  "type": "Feature",
  "properties": {
    "iso:country":"CH",
    "sg:address":"Mittlere Strasse 15 4056 Basel. Postfach",
    "sg:city":"Basel",
    "sg:orig_category":"Alters U Pflegeheime Wohnheime",
    "sg:phone":"+41 61 266 99 11",
    "sg:postcode":"4003",
    "sg:province":"Basel-Stadt",
    "wof:name":"Adullam-stiftung Basel",
    "wof:placetype":"venue"
},
  "geometry": {"coordinates":[7.579628,47.560184],"type":"Point"}
}