{
  "type": "Feature",
  "properties": {
    "addr:full":"Bahnhofstrasse 15 6003 Luzern. Postfach Luzern Luzern 6002",
    "addr:housenumber":"15",
    "addr:postcode":"6003;postfach;6002",
    "addr:street":"Bahnhofstrasse",
    "iso:country":"CH",
    "sg:address":"Bahnhofstrasse 15 6003 Luzern. Postfach",
    "sg:city":"Luzern",
    "sg:orig_category":"Allgemeine \u00f6ffentliche Verwaltung",
    "sg:phone":"+41 41 228 51 11",
    "sg:postcode":"6002",
    "sg:province":"Luzern",
    "wof:name":"Staatskanzlei",
    "wof:placetype":"venue"
},
  "geometry": {"coordinates":[8.304392,47.050396],"type":"Point"}
}