{
  "type": "Feature",
  "properties": {
    "addr:full":"Bahnhofplatz 4 R\u00fcmlang Z\u00fcrich 8153",
    "addr:housenumber":"4",
    "addr:postcode":"8153",
    "addr:street":"Bahnhofplatz;Zuerich",
    "iso:country":"CH",
    "sg:address":"Bahnhofplatz 4",
    "sg:city":"R\u00fcmlang",
    "sg:orig_category":"Detailhandel mit Brot, Back U S\u00fcsswaren",
    "sg:phone":"+41 18170275",
    "sg:postcode":"8153",
    "sg:province":"Z\u00fcrich",
    "wof:name":"Heinz Marthaler B\u00e4ckerei-konditorei",
    "wof:placetype":"venue"
},
  "geometry": {"coordinates":[8.532988,47.453388],"type":"Point"}
}