{
  "type": "Feature",
  "properties": {
    "iso:country":"CH",
    "sg:address":"Sennweidstrasse 16",
    "sg:city":"Bubikon",
    "sg:classifiers":[
        {
            "category":"Food & Beverages",
            "subcategory":"Specialty",
            "type":"Retail Goods"
        }
    ],
    "sg:phone":"+41 55 263 10 81",
    "sg:postcode":"8608",
    "sg:province":"Z\u00fcrich",
    "sg:tags":[
        "caterer"
    ],
    "wof:name":"Sayan Kwanthong Party-service",
    "wof:placetype":"venue"
},
  "geometry": {"coordinates":[8.824474,47.273418],"type":"Point"}
}