{
  "type": "Feature",
  "properties": {
    "iso:country":"CH",
    "sg:address":"Staatsstrasse 36a",
    "sg:city":"Rebstein",
    "sg:orig_category":"Interessenvertretungen U sonstige Vereinigungen",
    "sg:postcode":"9445",
    "sg:province":"St. Gallen",
    "wof:name":"Kantonalsch\u00fctzenverein Ai",
    "wof:placetype":"venue"
},
  "geometry": {"coordinates":[9.5904569626,47.4009666443],"type":"Point"}
}