{
  "type": "Feature",
  "properties": {
    "iso:country":"CH",
    "sg:address":"H\u00f6chhusmatt 11",
    "sg:city":"Willisau",
    "sg:orig_category":"Herstellung von Teppichen",
    "sg:postcode":"6130",
    "sg:province":"Luzern",
    "wof:name":"Fetaxid Spezilab\u00f6den Fetahi Sara",
    "wof:placetype":"venue"
},
  "geometry": {"coordinates":[7.9788889885,47.1189155579],"type":"Point"}
}