{
  "type": "Feature",
  "properties": {
    "iso:country":"CH",
    "sg:address":"Staatsstrasse 7b",
    "sg:city":"Werdenberg",
    "sg:orig_category":"Herstellung von sonstigen landwirtschaftlichen Maschinen Landwirtschaftliche Maschinen Wartung and R",
    "sg:phone":"+41 81 771 22 66",
    "sg:postcode":"9470",
    "sg:province":"St. Gallen",
    "wof:name":"Eicher Willi Delaval Service + Verkauf Melktechnik; Verkauf, Service",
    "wof:placetype":"venue"
},
  "geometry": {"coordinates":[9.4588413239,47.1700286865],"type":"Point"}
}