{
  "type": "Feature",
  "properties": {
    "iso:country":"CH",
    "sg:address":"Industriestrasse 10",
    "sg:city":"Birmensdorf",
    "sg:classifiers":[
        {
            "category":"Utilities",
            "subcategory":"Recycling",
            "type":"Services"
        }
    ],
    "sg:phone":"+41 17373244",
    "sg:postcode":"8903",
    "sg:province":"Z\u00fcrich",
    "sg:tags":[
        "metal"
    ],
    "wof:name":"Ernst Iten Ag",
    "wof:placetype":"venue"
},
  "geometry": {"coordinates":[8.4284992218,47.3655357361],"type":"Point"}
}