{
  "type": "Feature",
  "properties": {
    "iso:country":"CH",
    "sg:address":"S\u00e4geweg 24",
    "sg:city":"Kallnach",
    "sg:orig_category":"Grosshandel mit Holz U Bauelementen aus Holz S\u00e4gewerke",
    "sg:phone":"+41 32 392 14 48",
    "sg:postcode":"3283",
    "sg:province":"Bern",
    "wof:name":"Fritz Meer S\u00e4gerei & Holzhandlung Ag",
    "wof:placetype":"venue"
},
  "geometry": {"coordinates":[7.2384109497,47.0269317627],"type":"Point"}
}