{
  "type": "Feature",
  "properties": {
    "iso:country":"CH",
    "sg:address":"Via Suot Chesas 15",
    "sg:city":"Champf\u00e8r",
    "sg:orig_category":"Geb\u00e4ude, Wohnungsreinigung Reinigungsgewerbe",
    "sg:postcode":"7512",
    "sg:province":"Graubunden",
    "wof:name":"Time - Reinigungen, Meier Und Mastragelis",
    "wof:placetype":"venue"
},
  "geometry": {"coordinates":[8.2004270554,47.4816627502],"type":"Point"}
}