{
  "type": "Feature",
  "properties": {
    "iso:country":"CH",
    "sg:address":"Allmeindstr. 19",
    "sg:city":"Schmerikon",
    "sg:classifiers":[
        {
            "category":"Manufacturing",
            "subcategory":"Rubber & Plastics",
            "type":"Manufacturing & Wholesale Goods"
        }
    ],
    "sg:phone":"+41 55 286 17 00",
    "sg:postcode":"8716",
    "sg:province":"St. Gallen",
    "sg:tags":[
        "machine",
        "engineering",
        "-",
        "mechanical"
    ],
    "wof:name":"Wild Und K\u00dcpfer Ag",
    "wof:placetype":"venue"
},
  "geometry": {"coordinates":[8.9557952881,47.2234992981],"type":"Point"}
}