{
  "type": "Feature",
  "properties": {
    "iso:country":"CH",
    "sg:address":"Obere Geerenstrasse 12",
    "sg:city":"Gockhausen",
    "sg:orig_category":"Handelsvermittlung U Grosshandel Herstellung von Radio U Fernsehger\u00e4ten sowie phono U videotechnisch",
    "sg:phone":"+41 18223334",
    "sg:postcode":"8044",
    "sg:province":"Z\u00fcrich",
    "wof:name":"Celphone Girsberger Martin Gmbh",
    "wof:placetype":"venue"
},
  "geometry": {"coordinates":[8.5998916626,47.3812255859],"type":"Point"}
}