{
  "type": "Feature",
  "properties": {
    "iso:country":"CH",
    "sg:address":"Rue Industrielle 30 Bis",
    "sg:city":"Montreux",
    "sg:orig_category":"Arztpraxen",
    "sg:postcode":"1820",
    "sg:province":"Vaud",
    "wof:name":"Odile Stucki M\u00e9decin V\u00e9t\u00e9rinaire",
    "wof:placetype":"venue"
},
  "geometry": {"coordinates":[6.913414,46.433182],"type":"Point"}
}