{
  "type": "Feature",
  "properties": {
    "iso:country":"CH",
    "sg:address":"Reberastrasse 5 9494 Schaan. Postfach 180",
    "sg:city":"Schaan",
    "sg:orig_category":"Vermittlung von Immobilien Verwaltung von Immobilien",
    "sg:phone":"+423 232 16 18",
    "sg:postcode":"9494",
    "wof:name":"Patra Patent Treuhand-anstalt",
    "wof:placetype":"venue"
},
  "geometry": {"coordinates":[9.5123519897,47.1675949097],"type":"Point"}
}