{
  "type": "Feature",
  "properties": {
    "iso:country":"CH",
    "sg:address":"Via Centro Sportivo 2",
    "sg:city":"Savosa",
    "sg:orig_category":"Vorschulen, Kinderg\u00e4rten",
    "sg:postcode":"6942",
    "sg:province":"Ticino",
    "wof:name":"Scuola Materna",
    "wof:placetype":"venue"
},
  "geometry": {"coordinates":[8.9402704239,46.0164642334],"type":"Point"}
}