{
  "type": "Feature",
  "properties": {
    "iso:country":"CH",
    "sg:address":"Rue De L'ouriette 140",
    "sg:city":"Aubonne",
    "sg:orig_category":"Grosshandel mit sonstigen Maschinen U Ausr\u00fcstungen f\u00fcr Industrie, Handel U Schiffahrt",
    "sg:phone":"+41 21 807 16 22",
    "sg:postcode":"1170",
    "sg:province":"Vaud",
    "wof:name":"Wayne Switzerland Dresser Europe Sa",
    "wof:placetype":"venue"
},
  "geometry": {"coordinates":[6.3076310158,46.508731842],"type":"Point"}
}