{
  "type": "Feature",
  "properties": {
    "iso:country":"CH",
    "sg:address":"Route De La Galaise 32 1228 Plan-les-ouates Case Postale 169",
    "sg:city":"Plan-les-ouates",
    "sg:orig_category":"Grosshandel mit pharmazeutischen Erzeugnissen Interessenvertretungen",
    "sg:phone":"+41 22 343 09 70",
    "sg:postcode":"1228",
    "sg:province":"Gen\u00e8ve",
    "wof:name":"Dolisos (suisse) Sa",
    "wof:placetype":"venue"
},
  "geometry": {"coordinates":[6.1030659676,46.1676979065],"type":"Point"}
}