{
  "type": "Feature",
  "properties": {
    "iso:country":"CH",
    "sg:address":"Tellistrasse 35",
    "sg:city":"Aarau",
    "sg:orig_category":"Architektur U Ingenieurb\u00fcros",
    "sg:phone":"+41 62 824 76 66",
    "sg:postcode":"5000",
    "sg:province":"Aargau",
    "wof:name":"Weplan Ag",
    "wof:placetype":"venue"
},
  "geometry": {"coordinates":[8.054207,47.39658],"type":"Point"}
}