{
  "type": "Feature",
  "properties": {
    "iso:country":"CH",
    "sg:address":"Castausio Via 2",
    "sg:city":"Lugano",
    "sg:orig_category":"Sonstige Kurierdienste",
    "sg:postcode":"6900",
    "sg:province":"Ticino",
    "wof:name":"Canguro Sa",
    "wof:placetype":"venue"
},
  "geometry": {"coordinates":[8.9545259476,46.0130119324],"type":"Point"}
}