{
  "type": "Feature",
  "properties": {
    "iso:country":"CH",
    "sg:address":"Bergboden 11",
    "sg:city":"Wolhusen",
    "sg:orig_category":"Herstellung von Seifen, Wasch U Reinigungsmitteln",
    "sg:phone":"+41 41 490 25 27",
    "sg:postcode":"6110",
    "sg:province":"Luzern",
    "wof:name":"Rast-egli Judith Reka Und Hyla Beratung",
    "wof:placetype":"venue"
},
  "geometry": {"coordinates":[8.0669298172,47.0641822815],"type":"Point"}
}