{
  "type": "Feature",
  "properties": {
    "iso:country":"CH",
    "sg:address":"Rebhaldenstrasse 3",
    "sg:city":"Unterengstringen",
    "sg:orig_category":"Grosshandel mit Getr\u00e4nken",
    "sg:postcode":"8103",
    "sg:province":"Z\u00fcrich",
    "wof:name":"D\u00f6nni's Weinimport",
    "wof:placetype":"venue"
},
  "geometry": {"coordinates":[8.4485521317,47.4163398743],"type":"Point"}
}