{
  "type": "Feature",
  "properties": {
    "iso:country":"CH",
    "sg:address":"Ch.-de Mont-de-fourches 7",
    "sg:city":"St-prex",
    "sg:orig_category":"Unternehmensberatung",
    "sg:phone":"+41 21 806 50 31",
    "sg:postcode":"1162",
    "sg:province":"Vaud",
    "wof:name":"Vauclair Alain Consultant",
    "wof:placetype":"venue"
},
  "geometry": {"coordinates":[6.4536237717,46.4812660217],"type":"Point"}
}