{
  "type": "Feature",
  "properties": {
    "iso:country":"CH",
    "sg:address":"Mauracker 3935 B\u00fcrchen. Postfach",
    "sg:city":"B\u00fcrchen",
    "sg:orig_category":"Sanit\u00e4r, Heizungs U L\u00fcftungsinstallation",
    "sg:postcode":"3935",
    "sg:province":"Valais",
    "wof:name":"Imesch Heinrich Ag, Sanit\u00e4rinstallationen Und Bedachungen",
    "wof:placetype":"venue"
},
  "geometry": {"coordinates":[7.8142299652,46.2837295532],"type":"Point"}
}