{
  "type": "Feature",
  "properties": {
    "iso:country":"CH",
    "sg:address":"Chemin Du Paradis 5",
    "sg:city":"Duillier",
    "sg:orig_category":"Unternehmensberatung",
    "sg:phone":"+41 22 362 04 01",
    "sg:postcode":"1266",
    "sg:province":"Vaud",
    "wof:name":"Jr Management 2000 Jos\u00e9 Riquez",
    "wof:placetype":"venue"
},
  "geometry": {"coordinates":[6.2374677658,46.4124565125],"type":"Point"}
}