{
  "type": "Feature",
  "properties": {
    "iso:country":"CH",
    "sg:address":"Breitestrasse 50",
    "sg:city":"Zurzach",
    "sg:orig_category":"Detailhandel mit Teppichen Verlegen von Fussboden",
    "sg:phone":"+41 56 249 28 64",
    "sg:postcode":"5330",
    "sg:province":"Aargau",
    "wof:name":"Guido M\u00fchlebach Teppich-& Bodenbel\u00e4ge Parkett",
    "wof:placetype":"venue"
},
  "geometry": {"coordinates":[8.3035011292,47.5810127258],"type":"Point"}
}