{
  "type": "Feature",
  "properties": {
    "iso:country":"CH",
    "sg:address":"Poststrasse 17 4542 Luterbach. Postfach",
    "sg:city":"Luterbach",
    "sg:orig_category":"Druck ohne Zeitungsdruck Offsetdruck",
    "sg:postcode":"4542",
    "sg:province":"Solothurn",
    "wof:name":"Ricciardi, Graphische Offizin",
    "wof:placetype":"venue"
},
  "geometry": {"coordinates":[7.5850419998,47.2159080505],"type":"Point"}
}