{
  "type": "Feature",
  "properties": {
    "iso:country":"CH",
    "sg:address":"Scheideggstrasse 16 8400 Winterthur. Postfach",
    "sg:city":"Winterthur",
    "sg:orig_category":"Reinigungsgewerbe",
    "sg:postcode":"8400",
    "sg:province":"Z\u00fcrich",
    "wof:name":"Aliji Isolationen Aussen Und Innenisolationen, Reinigungsarbeiten",
    "wof:placetype":"venue"
},
  "geometry": {"coordinates":[8.7503824234,47.4923477173],"type":"Point"}
}