{
  "type": "Feature",
  "properties": {
    "iso:country":"CH",
    "sg:address":"Servette Rue De La 2 1201 Gen\u00e8ve. Postfach",
    "sg:city":"Gen\u00e8ve",
    "sg:orig_category":"Herstellung von Karosserien U Anh\u00e4ngern",
    "sg:phone":"+41 79 457 37 92",
    "sg:postcode":"1201",
    "sg:province":"Gen\u00e8ve",
    "wof:name":"Carrosserie De Lutry, R. Sch\u00e4rli",
    "wof:placetype":"venue"
},
  "geometry": {"coordinates":[6.6777420044,46.5129203796],"type":"Point"}
}