{
  "type": "Feature",
  "properties": {
    "addr:full":"Unterdorfstrasse 10 3612 Steffisburg. Postfach 90 Steffisburg Bern 3612",
    "addr:housenumber":"10;90",
    "addr:postcode":"3612 steffisburg.;3612",
    "addr:street":"Unterdorfstrasse;Postfach;Bern",
    "iso:country":"CH",
    "sg:address":"Unterdorfstrasse 10 3612 Steffisburg. Postfach 90",
    "sg:city":"Steffisburg",
    "sg:orig_category":"Grosshandel mit elektrischen Haushaltsger\u00e4ten Sonstiger Grosshandel",
    "sg:phone":"+41 33 437 65 15",
    "sg:postcode":"3612",
    "sg:province":"Bern",
    "wof:name":"Intresa, Caggiano G.",
    "wof:placetype":"venue"
},
  "geometry": {"coordinates":[7.634509,46.777737],"type":"Point"}
}