{
  "type": "Feature",
  "properties": {
    "iso:country":"CH",
    "sg:address":"Fronwagplatz 28",
    "sg:city":"Schaffhausen",
    "sg:orig_category":"Advokaturb\u00fcros",
    "sg:phone":"+41 52 625 12 77",
    "sg:postcode":"8200",
    "sg:province":"Schaffhausen",
    "wof:name":"Dr.bruno Nater Advokaturb\u00fcro",
    "wof:placetype":"venue"
},
  "geometry": {"coordinates":[8.633652,47.697353],"type":"Point"}
}