{
  "type": "Feature",
  "properties": {
    "iso:country":"CH",
    "sg:address":"Mator\u00e8ll Via 31b 6926 Montagnola. Postfach",
    "sg:city":"Montagnola",
    "sg:orig_category":"Sonstige mit der Informatik verbundene T\u00e4tigkeiten",
    "sg:postcode":"6926",
    "sg:province":"Ticino",
    "wof:name":"Leyland & Partners Di Corti E Mastropietro Consulenza Informatica",
    "wof:placetype":"venue"
},
  "geometry": {"coordinates":[8.9169063568,45.981918335],"type":"Point"}
}