{
  "type": "Feature",
  "properties": {
    "iso:country":"CH",
    "sg:address":"Hegiberg 20",
    "sg:city":"Niederhelfenschwil",
    "sg:orig_category":"Kosmetikinstitute",
    "sg:phone":"+41 71 947 19 87",
    "sg:postcode":"9527",
    "sg:province":"St. Gallen",
    "wof:name":"Claudia Zwicky Kosmetikinstitut",
    "wof:placetype":"venue"
},
  "geometry": {"coordinates":[9.1913547516,47.4808082581],"type":"Point"}
}