{
  "type": "Feature",
  "properties": {
    "iso:country":"CH",
    "sg:address":"8484 Weisslingen. Postfach",
    "sg:city":"Weisslingen",
    "sg:orig_category":"Pensionskassen",
    "sg:postcode":"8484",
    "sg:province":"Z\u00fcrich",
    "wof:name":"Personalf\u00fcrsorgestiftung Der Firma Widmer Zimmerei Innenausbau Ag",
    "wof:placetype":"venue"
},
  "geometry": {"coordinates":[8.7637138367,47.4315261841],"type":"Point"}
}