{
  "type": "Feature",
  "properties": {
    "iso:country":"CH",
    "sg:address":"Schillerstrasse 2",
    "sg:city":"Birsfelden",
    "sg:orig_category":"Unternehmensberatung",
    "sg:phone":"+41 19121732",
    "sg:postcode":"4127",
    "sg:province":"Basel-Landschaft",
    "wof:name":"Kuster J\u00fcrg R. Unternehmensberatung",
    "wof:placetype":"venue"
},
  "geometry": {"coordinates":[8.6002616882,47.3222427368],"type":"Point"}
}