{
  "type": "Feature",
  "properties": {
    "iso:country":"CH",
    "sg:address":"Sonnenrain 23",
    "sg:city":"Luzern",
    "sg:orig_category":"Softwareentwicklung U beratung",
    "sg:phone":"+41 41 211 27 02",
    "sg:postcode":"6006",
    "sg:province":"Luzern",
    "wof:name":"Artsoft Gmbh",
    "wof:placetype":"venue"
},
  "geometry": {"coordinates":[8.3121728897,47.0576629639],"type":"Point"}
}