{
  "type": "Feature",
  "properties": {
    "iso:country":"CH",
    "sg:address":"K\u00e4sernstrasse 2a",
    "sg:city":"Aadorf",
    "sg:orig_category":"Handel mit Automobilen",
    "sg:phone":"+41 52 366 29 66",
    "sg:postcode":"8355",
    "sg:province":"Thurgau",
    "wof:name":"Auto Sonderegger Auto-und Occasionshandel",
    "wof:placetype":"venue"
},
  "geometry": {"coordinates":[8.9023122787,47.489315033],"type":"Point"}
}