{
  "type": "Feature",
  "properties": {
    "addr:full":"Ch\u00eane Route De 130 Ch\u00eane-bougeries Gen\u00e8ve 1224",
    "addr:housenumber":"130",
    "addr:postcode":"1224",
    "addr:street":"Route De",
    "iso:country":"CH",
    "sg:address":"Ch\u00eane Route De 130",
    "sg:city":"Ch\u00eane-bougeries",
    "sg:orig_category":"Architektur U Ingenieurb\u00fcros",
    "sg:phone":"+41 22 860 06 00",
    "sg:postcode":"1224",
    "sg:province":"Gen\u00e8ve",
    "wof:name":"La Taupe, Guy Kastel",
    "wof:placetype":"venue"
},
  "geometry": {"coordinates":[6.187205,46.197926],"type":"Point"}
}