{
  "type": "Feature",
  "properties": {
    "iso:country":"CH",
    "sg:address":"Hermesb\u00fchlstrasse 49",
    "sg:city":"Solothurn",
    "sg:orig_category":"Sportvereine Flug Aero-Club",
    "sg:postcode":"4500",
    "sg:province":"Solothurn",
    "wof:name":"Ae.c.s.sektion Solothurn",
    "wof:placetype":"venue"
},
  "geometry": {"coordinates":[7.5289268494,47.2093963623],"type":"Point"}
}