{
  "type": "Feature",
  "properties": {
    "iso:country":"CH",
    "sg:address":"Concordia Vicolo 1",
    "sg:city":"Breganzona",
    "sg:orig_category":"Technische, physikalische U chemische Untersuchung",
    "sg:phone":"+41 41 467 25 13",
    "sg:postcode":"6932",
    "sg:province":"Ticino",
    "wof:name":"Planteam Ghs Ag",
    "wof:placetype":"venue"
},
  "geometry": {"coordinates":[8.1976528168,47.1162338257],"type":"Point"}
}