{
  "type": "Feature",
  "properties": {
    "iso:country":"CH",
    "sg:address":"Boveresses Chemin Des 128",
    "sg:city":"Epalinges",
    "sg:orig_category":"Unclassifiable Establishments",
    "sg:phone":"+41 21 349 45 45",
    "sg:postcode":"1066",
    "sg:province":"Vaud",
    "wof:name":"Lamuni\u00e8re Sa",
    "wof:placetype":"venue"
},
  "geometry": {"coordinates":[6.6676387787,46.5402107239],"type":"Point"}
}