{
  "type": "Feature",
  "properties": {
    "iso:country":"CH",
    "sg:address":"Urstalden",
    "sg:city":"Gohl",
    "sg:orig_category":"Mechanik Schmieden",
    "sg:phone":"+41 34 402 34 03",
    "sg:postcode":"3553",
    "sg:province":"Bern",
    "wof:name":"Z\u00fcrcher Christian",
    "wof:placetype":"venue"
},
  "geometry": {"coordinates":[7.8069791794,46.9549293518],"type":"Point"}
}