{
  "type": "Feature",
  "properties": {
    "iso:country":"CH",
    "sg:address":"Industriestrasse 40",
    "sg:city":"Zug",
    "sg:orig_category":"Non-Classified Establishments",
    "sg:postcode":"6300",
    "sg:province":"Zug",
    "wof:name":"Btts Corporation",
    "wof:placetype":"venue"
},
  "geometry": {"coordinates":[8.5199146271,47.1766090393],"type":"Point"}
}