{
  "type": "Feature",
  "properties": {
    "iso:country":"CH",
    "sg:address":"Altmattweg 5",
    "sg:city":"Strengelbach",
    "sg:orig_category":"Kosmetikinstitute",
    "sg:phone":"+41 61 751 80 55",
    "sg:postcode":"4802",
    "sg:province":"Aargau",
    "wof:name":"Doris Sch\u00e4r",
    "wof:placetype":"venue"
},
  "geometry": {"coordinates":[7.6029429436,47.4784431458],"type":"Point"}
}