{
  "type": "Feature",
  "properties": {
    "iso:country":"CH",
    "sg:address":"Ch. Des Cr\u00eats-de-champel 3 1206 Gen\u00e8ve. Postfach",
    "sg:city":"Gen\u00e8ve",
    "sg:orig_category":"Unternehmensberatung",
    "sg:phone":"+41 22 700 19 90",
    "sg:postcode":"1201",
    "sg:province":"Gen\u00e8ve",
    "wof:name":"Kessler Et Associ\u00e9s",
    "wof:placetype":"venue"
},
  "geometry": {"coordinates":[6.1525092125,46.1890220642],"type":"Point"}
}