{
  "type": "Feature",
  "properties": {
    "iso:country":"CH",
    "sg:address":"Giessereistrasse 1",
    "sg:city":"Wetzikon",
    "sg:classifiers":[
        {
            "category":"Professional",
            "subcategory":"Advertising",
            "type":"Services"
        }
    ],
    "sg:phone":"+41 19723388",
    "sg:postcode":"8620",
    "sg:province":"Z\u00fcrich",
    "sg:tags":[
        "agency"
    ],
    "wof:name":"St\u00e4ubli Kommunikation",
    "wof:placetype":"venue"
},
  "geometry": {"coordinates":[8.78526,47.325821],"type":"Point"}
}