{
  "type": "Feature",
  "properties": {
    "iso:country":"CH",
    "sg:address":"Rudenzweg 27",
    "sg:city":"Z\u00fcrich",
    "sg:classifiers":[
        {
            "category":"Professional",
            "subcategory":"Computer Services",
            "type":"Services"
        }
    ],
    "sg:phone":"+41 14003730",
    "sg:postcode":"8048",
    "sg:province":"Z\u00fcrich",
    "sg:tags":[
        "development",
        "software"
    ],
    "wof:name":"Devotec Engineering Ag",
    "wof:placetype":"venue"
},
  "geometry": {"coordinates":[8.4991874695,47.3842811584],"type":"Point"}
}