{
  "type": "Feature",
  "properties": {
    "iso:country":"CH",
    "sg:address":"Br\u00fcnigstrasse 42",
    "sg:city":"Giswil",
    "sg:orig_category":"Nationale Postdienste",
    "sg:phone":"+41 81 740 32 71",
    "sg:postcode":"6074",
    "sg:province":"Obwalden",
    "wof:name":"Die Schweizerische Post",
    "wof:placetype":"venue"
},
  "geometry": {"coordinates":[9.4889059067,47.20911026],"type":"Point"}
}