{
  "type": "Feature",
  "properties": {
    "iso:country":"CH",
    "sg:address":"Hauptstrasse 32",
    "sg:city":"Au",
    "sg:classifiers":[
        {
            "category":"Bars & Pubs",
            "type":"Food & Drink"
        }
    ],
    "sg:phone":"+41 71 744 90 15",
    "sg:postcode":"9434",
    "sg:province":"St. Gallen",
    "sg:tags":[
        "knife",
        "bread"
    ],
    "wof:name":"Messerschmiede Eugen B\u00e4nziger Inh. Otto B\u00e4nziger",
    "wof:placetype":"venue"
},
  "geometry": {"coordinates":[9.639022,47.437439],"type":"Point"}
}