{
  "type": "Feature",
  "properties": {
    "iso:country":"CH",
    "sg:address":"Haus Waldwiese Maranerstrasse 7050 Arosa. Postfach",
    "sg:city":"Arosa",
    "sg:orig_category":"Sportvereine Eissport Eishockey",
    "sg:postcode":"7050",
    "sg:province":"Graubunden",
    "wof:name":"Eishockey-club Arosa",
    "wof:placetype":"venue"
},
  "geometry": {"coordinates":[9.6765518188,46.7778625488],"type":"Point"}
}