{
  "type": "Feature",
  "properties": {
    "iso:country":"CH",
    "sg:address":"Postweg 5",
    "sg:city":"Ennetbaden",
    "sg:orig_category":"Nationale Postdienste",
    "sg:phone":"+41 62 822 13 43",
    "sg:postcode":"5408",
    "sg:province":"Aargau",
    "wof:name":"Die Schweizerische Post",
    "wof:placetype":"venue"
},
  "geometry": {"coordinates":[8.0707387924,47.3893470764],"type":"Point"}
}