{
  "type": "Feature",
  "properties": {
    "iso:country":"CH",
    "sg:address":"Heidenerstrasse 3",
    "sg:city":"Eggersriet",
    "sg:orig_category":"Nationale Postdienste",
    "sg:phone":"+41 71 877 11 32",
    "sg:postcode":"9034",
    "sg:province":"St. Gallen",
    "wof:name":"Die Schweizerische Post",
    "wof:placetype":"venue"
},
  "geometry": {"coordinates":[9.4730272293,47.442489624],"type":"Point"}
}