{
  "type": "Feature",
  "properties": {
    "iso:country":"CH",
    "sg:address":"Im Winkel 1",
    "sg:city":"Frick",
    "sg:orig_category":"Zahnarztpraxen",
    "sg:phone":"+41 56 282 43 33",
    "sg:postcode":"5070",
    "sg:province":"Aargau",
    "wof:name":"Dr. Med. Dent. Milan Mitrovic Zahnarzt",
    "wof:placetype":"venue"
},
  "geometry": {"coordinates":[8.2854280472,47.4887695312],"type":"Point"}
}