{
  "type": "Feature",
  "properties": {
    "iso:country":"CH",
    "sg:address":"Rue Du Vieux-moulin 46",
    "sg:city":"Court\u00e9telle",
    "sg:orig_category":"Herstellung von Metallerzeugnissen ohne Maschinenbau Herstellung von M\u00fcnzen U Medaillen",
    "sg:phone":"+41 32 422 39 14",
    "sg:postcode":"2852",
    "sg:province":"Jura",
    "wof:name":"Louis Imhof Sa",
    "wof:placetype":"venue"
},
  "geometry": {"coordinates":[7.306101799,47.338634491],"type":"Point"}
}