{
  "type": "Feature",
  "properties": {
    "iso:country":"CH",
    "sg:address":"Oberdorfstrasse 15",
    "sg:city":"Wohlenschwil",
    "sg:orig_category":"Stukkateurgewerbe, Gipserei U Verputzerei Verlegen von Fussboden",
    "sg:phone":"+41 24 459 18 64",
    "sg:postcode":"5512",
    "sg:province":"Aargau",
    "wof:name":"Rigo R.",
    "wof:placetype":"venue"
},
  "geometry": {"coordinates":[6.5610051155,46.8027954102],"type":"Point"}
}