{
  "type": "Feature",
  "properties": {
    "iso:country":"CH",
    "sg:address":"Chemin De Champ Claude 1a",
    "sg:city":"Vernier",
    "sg:orig_category":"Detailhandel mit Radio U Fernsehger\u00e4ten",
    "sg:phone":"+41 27 957 18 52",
    "sg:postcode":"1214",
    "sg:province":"Gen\u00e8ve",
    "wof:name":"Leander Locher Radio-tv",
    "wof:placetype":"venue"
},
  "geometry": {"coordinates":[7.933672905,46.1117172241],"type":"Point"}
}