{
  "type": "Feature",
  "properties": {
    "iso:country":"CH",
    "sg:address":"Talstrasse 70 8001 Z\u00fcrich. Postfach 823",
    "sg:city":"Z\u00fcrich",
    "sg:orig_category":"Banken sonstige",
    "sg:phone":"+41 12120050",
    "sg:postcode":"8001",
    "sg:province":"Z\u00fcrich",
    "wof:name":"Sella Bank Ag",
    "wof:placetype":"venue"
},
  "geometry": {"coordinates":[8.534702,47.371395],"type":"Point"}
}