{
  "type": "Feature",
  "properties": {
    "iso:country":"CH",
    "sg:address":"Center Communal",
    "sg:city":"Morissen",
    "sg:orig_category":"Gemeindeverwaltungen",
    "sg:phone":"+41 81 931 21 81",
    "sg:postcode":"7143",
    "sg:province":"Graubunden",
    "wof:name":"Gemeindeverwaltung Morissen",
    "wof:placetype":"venue"
},
  "geometry": {"coordinates":[9.1810760498,46.7301597595],"type":"Point"}
}