{
  "type": "Feature",
  "properties": {
    "iso:country":"CH",
    "sg:address":"H\u00fchnerhubelstrasse 81 3123 Belp. Postfach",
    "sg:city":"Belp",
    "sg:orig_category":"Grosshandel mit Datenverarbeitungsger\u00e4ten Softwareentwicklung U beratung",
    "sg:phone":"+41 90575737",
    "sg:postcode":"3123",
    "sg:province":"Bern",
    "wof:name":"Dm Electronics Ag Hard-& Software",
    "wof:placetype":"venue"
},
  "geometry": {"coordinates":[7.4939360619,46.9050941467],"type":"Point"}
}