{
  "type": "Feature",
  "properties": {
    "iso:country":"CH",
    "sg:address":"Boden Rietbad",
    "sg:city":"Ennetb\u00fchl",
    "sg:orig_category":"Herstellung von Ger\u00e4ten der Elektrizit\u00e4tserzeugung, -verteilung u.\u00e4. -Herstellung von sonstigen elek",
    "sg:phone":"+41 71 858 29 01",
    "sg:postcode":"9651",
    "sg:province":"St. Gallen",
    "wof:name":"C + M Technics Ag",
    "wof:placetype":"venue"
},
  "geometry": {"coordinates":[9.5439109802,47.4842224121],"type":"Point"}
}