{
  "type": "Feature",
  "properties": {
    "iso:country":"CH",
    "sg:address":"Gontenstrasse 17",
    "sg:city":"Appenzell",
    "sg:orig_category":"Sanit\u00e4r, Heizungs U L\u00fcftungsinstallation Sanit\u00e4rinstallation",
    "sg:phone":"+41 71 383 15 80",
    "sg:postcode":"9050",
    "sg:province":"Appenzell Innerhoden",
    "wof:name":"Dream-bad, Engetschwiler P. + Co., Haldenstr. 6",
    "wof:placetype":"venue"
},
  "geometry": {"coordinates":[9.2468910217,47.4159202576],"type":"Point"}
}