{
  "type": "Feature",
  "properties": {
    "iso:country":"CH",
    "sg:address":"Hauptstrasse 33",
    "sg:city":"Brunegg",
    "sg:orig_category":"Mit Sport verbundene T\u00e4tigkeiten",
    "sg:phone":"+41 32 968 27 82",
    "sg:postcode":"5505",
    "sg:province":"Aargau",
    "wof:name":"Willy Gerber Man\u00e8ge & \u00e9cole D'\u00e9quitation",
    "wof:placetype":"venue"
},
  "geometry": {"coordinates":[6.8408460617,47.0917434692],"type":"Point"}
}