{
  "type": "Feature",
  "properties": {
    "iso:country":"CH",
    "sg:address":"Tellenmattstrasse 6",
    "sg:city":"Stans",
    "sg:orig_category":"Detailhandel mit Brillen U anderen Sehhilfen Detailhandel mit medizinischen U orthop\u00e4dischen Artikel",
    "sg:phone":"+41 41 610 81 31",
    "sg:postcode":"6370",
    "sg:province":"Nidwalden",
    "wof:name":"Micro-electric H\u00f6rger\u00e4te Ag",
    "wof:placetype":"venue"
},
  "geometry": {"coordinates":[8.367378,46.95715],"type":"Point"}
}