{
  "type": "Feature",
  "properties": {
    "iso:country":"CH",
    "sg:address":"Leihgasse 46",
    "sg:city":"Baar",
    "sg:orig_category":"Grosshandel mit Textilien",
    "sg:postcode":"6340",
    "sg:province":"Zug",
    "wof:name":"Seng\u00fcl Mehmet",
    "wof:placetype":"venue"
},
  "geometry": {"coordinates":[8.5330619812,47.1944732666],"type":"Point"}
}