{
  "type": "Feature",
  "properties": {
    "iso:country":"CH",
    "sg:address":"Pilatusstrasse 1",
    "sg:city":"Zug",
    "sg:orig_category":"Zahntechnische Laboratorien",
    "sg:phone":"+41 19204743",
    "sg:postcode":"6300",
    "sg:province":"Zug",
    "wof:name":"Urs Marty & Stefan Schafroth Zahntechnisches Labor",
    "wof:placetype":"venue"
},
  "geometry": {"coordinates":[8.6793642044,47.2677955627],"type":"Point"}
}