{
  "type": "Feature",
  "properties": {
    "iso:country":"CH",
    "sg:address":"Oetenbachgasse 13",
    "sg:city":"Z\u00fcrich",
    "sg:orig_category":"Kosmetikinstitute",
    "sg:phone":"+41 12213640",
    "sg:postcode":"8001",
    "sg:province":"Z\u00fcrich",
    "wof:name":"Hia Vogel Kosmetikinstitut",
    "wof:placetype":"venue"
},
  "geometry": {"coordinates":[8.5392980576,47.3738288879],"type":"Point"}
}