{
  "type": "Feature",
  "properties": {
    "iso:country":"CH",
    "sg:address":"Via Mondadiscio 20",
    "sg:city":"Agno",
    "sg:orig_category":"Druck ohne Zeitungsdruck",
    "sg:postcode":"6982",
    "sg:province":"Ticino",
    "wof:name":"Assunta Sa",
    "wof:placetype":"venue"
},
  "geometry": {"coordinates":[8.9022893906,46.0116500854],"type":"Point"}
}