{
  "type": "Feature",
  "properties": {
    "iso:country":"CH",
    "sg:address":"Hammerstrasse 56",
    "sg:city":"Z\u00fcrich",
    "sg:orig_category":"Sonstige Aktivit\u00e4ten der nicht-\u00e4rztlichen Medizinalberufe",
    "sg:phone":"+41 14225038",
    "sg:postcode":"8032",
    "sg:province":"Z\u00fcrich",
    "wof:name":"Cornelia Novaglia Atemtherapie",
    "wof:placetype":"venue"
},
  "geometry": {"coordinates":[8.5620708466,47.3602409363],"type":"Point"}
}