{
  "type": "Feature",
  "properties": {
    "iso:country":"CH",
    "sg:address":"Maley Le",
    "sg:city":"St-blaise",
    "sg:orig_category":"Non-Classified Establishments",
    "sg:postcode":"2072",
    "sg:province":"Neuch\u00e2tel",
    "wof:name":"B. Jordan S\u00e0rl",
    "wof:placetype":"venue"
},
  "geometry": {"coordinates":[6.9998459816,47.0406112671],"type":"Point"}
}