{
  "type": "Feature",
  "properties": {
    "iso:country":"CH",
    "sg:address":"Bahnhofstrasse 21",
    "sg:city":"Zug",
    "sg:orig_category":"Schaustellergewerbe U Vergn\u00fcgungsparks",
    "sg:postcode":"6300",
    "sg:province":"Zug",
    "wof:name":"Works By Senteler Hedi Representing",
    "wof:placetype":"venue"
},
  "geometry": {"coordinates":[8.5156917572,47.1697540283],"type":"Point"}
}