{
  "type": "Feature",
  "properties": {
    "iso:country":"CH",
    "sg:address":"R\u00fcediswilerstrasse 98 6017 Ruswil. Postfach 95",
    "sg:city":"Ruswil",
    "sg:orig_category":"Instandhaltung U Reparatur von Automobilen Tankstellen",
    "sg:phone":"+41 41 495 35 36",
    "sg:postcode":"6017",
    "sg:province":"Luzern",
    "wof:name":"Garage Roos Ruswil",
    "wof:placetype":"venue"
},
  "geometry": {"coordinates":[8.114569664,47.0878295898],"type":"Point"}
}