{
  "type": "Feature",
  "properties": {
    "iso:country":"CH",
    "sg:address":"Brunnengasse 3 8180 B\u00fclach. Postfach",
    "sg:city":"B\u00fclach",
    "sg:orig_category":"RESTAURANTS: TEA-ROOMS",
    "sg:postcode":"8180",
    "sg:province":"Z\u00fcrich",
    "wof:name":"Arvini Radimak Andrea",
    "wof:placetype":"venue"
},
  "geometry": {"coordinates":[8.5417089462,47.5177459717],"type":"Point"}
}