{
  "type": "Feature",
  "properties": {
    "iso:country":"CH",
    "sg:address":"Rue De L'envol 3",
    "sg:city":"Sion",
    "sg:orig_category":"Institutionen f\u00fcr Behinderte Tagesheime f\u00fcr Behinderte, gesch\u00fctzte Werkst\u00e4tten",
    "sg:phone":"+41 22 309 11 50",
    "sg:postcode":"1950",
    "sg:province":"Valais",
    "wof:name":"Foyer-handicap",
    "wof:placetype":"venue"
},
  "geometry": {"coordinates":[6.134376049,46.1877059937],"type":"Point"}
}