{
  "type": "Feature",
  "properties": {
    "addr:full":"Rue Du Petit-ch\u00eane 18 1003 Lausanne Case Postale 3420 Lausanne Vaud 1002",
    "addr:housenumber":"18",
    "addr:postcode":"1003;3420;1002",
    "addr:street":"Rue Du Petit-Che\u0302Ne;Postale",
    "iso:country":"CH",
    "sg:address":"Rue Du Petit-ch\u00eane 18 1003 Lausanne Case Postale 3420",
    "sg:city":"Lausanne",
    "sg:orig_category":"Advokaturb\u00fcros",
    "sg:phone":"+41 21 320 18 07",
    "sg:postcode":"1002",
    "sg:province":"Vaud",
    "wof:name":"Patrick Foetisch Etude D'avocat",
    "wof:placetype":"venue"
},
  "geometry": {"coordinates":[6.630285,46.51899],"type":"Point"}
}