{
  "type": "Feature",
  "properties": {
    "iso:country":"CH",
    "sg:address":"Sydebusweg 9",
    "sg:city":"Biel/bienne",
    "sg:orig_category":"Non-Classified Establishments",
    "sg:postcode":"2502",
    "sg:province":"Bern",
    "wof:name":"Manufacture Des Montres Rolex Management Ag",
    "wof:placetype":"venue"
},
  "geometry": {"coordinates":[7.2413229942,47.1438331604],"type":"Point"}
}