{
  "type": "Feature",
  "properties": {
    "iso:country":"CH",
    "sg:address":"Route De Porrentruy 33 2800 Del\u00e9mont Case Postale 165",
    "sg:city":"Delsberg",
    "sg:orig_category":"Detailhandel mit Eisen U Metallwaren Detailhandel mit Metallwaren, Anstrichmitteln, Glaswaren, Bau U",
    "sg:phone":"+41 32 422 99 55",
    "sg:postcode":"2800",
    "sg:province":"Jura",
    "wof:name":"Bocks Schmid Sa Outillage, Machines Et Ferrements",
    "wof:placetype":"venue"
},
  "geometry": {"coordinates":[7.3399958611,47.3618202209],"type":"Point"}
}