{
  "type": "Feature",
  "properties": {
    "iso:country":"CH",
    "sg:address":"Ackersteinstrasse 203 8049 Z\u00fcrich. Postfach",
    "sg:city":"Z\u00fcrich",
    "sg:orig_category":"Grosshandel mit Obst U Gem\u00fcse",
    "sg:phone":"+41 13415100",
    "sg:postcode":"8049",
    "sg:province":"Z\u00fcrich",
    "wof:name":"Interfrut Ag",
    "wof:placetype":"venue"
},
  "geometry": {"coordinates":[8.4990253448,47.4015312195],"type":"Point"}
}