{
  "type": "Feature",
  "properties": {
    "iso:country":"CH",
    "sg:address":"Unterer Bollh\u00f6lzliweg 15a",
    "sg:city":"Boll",
    "sg:orig_category":"Unternehmensberatung",
    "sg:phone":"+41 31 839 67 37",
    "sg:postcode":"3067",
    "sg:province":"Bern",
    "wof:name":"Dr.a. Sager & Partner Unternehmensberatung",
    "wof:placetype":"venue"
},
  "geometry": {"coordinates":[7.5494608879,46.9527359009],"type":"Point"}
}