{
  "type": "Feature",
  "properties": {
    "iso:country":"CH",
    "sg:address":"9658",
    "sg:city":"Wildhaus",
    "sg:orig_category":"Vereine Gesang",
    "sg:postcode":"9658",
    "sg:province":"St. Gallen",
    "wof:name":"Reformierter Kirchenchor",
    "wof:placetype":"venue"
},
  "geometry": {"coordinates":[9.3509206772,47.2028656006],"type":"Point"}
}