{
  "type": "Feature",
  "properties": {
    "iso:country":"CH",
    "sg:address":"Schachenstrasse 34",
    "sg:city":"Oensingen",
    "sg:orig_category":"Instandhaltung U Reparatur von Automobilen",
    "sg:phone":"+41 79 218 85 40",
    "sg:postcode":"4702",
    "sg:province":"Solothurn",
    "wof:name":"Hermann Pichler West Garage",
    "wof:placetype":"venue"
},
  "geometry": {"coordinates":[7.7097420692,47.2899932861],"type":"Point"}
}