{
  "type": "Feature",
  "properties": {
    "iso:country":"CH",
    "sg:address":"Rue Saint-sebastien 24",
    "sg:city":"Del\u00e9mont",
    "sg:orig_category":"Herstellung U Zusammensetzung von Uhren Herstellung von Uhren",
    "sg:phone":"+41 21 845 01 23",
    "sg:postcode":"2800",
    "sg:province":"Jura",
    "wof:name":"Manufacture Jaeger-le Coultre Sa",
    "wof:placetype":"venue"
},
  "geometry": {"coordinates":[6.2310299873,46.6077919006],"type":"Point"}
}