{
  "type": "Feature",
  "properties": {
    "iso:country":"CH",
    "sg:address":"1937 Orsi\u00e8res Case Postale 21",
    "sg:city":"Orsi\u00e8res",
    "sg:orig_category":"Sportvereine Ballsport Tischtennis",
    "sg:postcode":"1937",
    "sg:province":"Valais",
    "wof:name":"Club De Tennis De Table Dor\u00e9naz",
    "wof:placetype":"venue"
},
  "geometry": {"coordinates":[7.1462898254,46.0306968689],"type":"Point"}
}