{
  "type": "Feature",
  "properties": {
    "iso:country":"CH",
    "sg:address":"8462",
    "sg:city":"Rheinau",
    "sg:orig_category":"Sportvereine Sch\u00fctzen",
    "sg:phone":"+41 52 319 19 42",
    "sg:postcode":"8462",
    "sg:province":"Z\u00fcrich",
    "wof:name":"Milit\u00e4rschiessverein",
    "wof:placetype":"venue"
},
  "geometry": {"coordinates":[8.6046323776,47.6444511414],"type":"Point"}
}