{
  "type": "Feature",
  "properties": {
    "iso:country":"CH",
    "sg:address":"Chemin Du Cornalin 29",
    "sg:city":"Sierre",
    "sg:orig_category":"Markt U Meinungsforschung",
    "sg:phone":"+41 79 276 55 28",
    "sg:postcode":"3960",
    "sg:province":"Valais",
    "wof:name":"Zebmarketing Gmbh",
    "wof:placetype":"venue"
},
  "geometry": {"coordinates":[7.5434708595,46.294052124],"type":"Point"}
}