{
  "type": "Feature",
  "properties": {
    "iso:country":"CH",
    "sg:address":"Bahnhofstrasse 39",
    "sg:city":"Z\u00fcrich",
    "sg:orig_category":"Detailhandel mit Bekleidung Herstellung von Duft U K\u00f6rperpflegemitteln",
    "sg:phone":"+41 12111781",
    "sg:postcode":"8001",
    "sg:province":"Z\u00fcrich",
    "wof:name":"Chanel Sa Gen\u00e8ve",
    "wof:placetype":"venue"
},
  "geometry": {"coordinates":[8.538526,47.371445],"type":"Point"}
}