{
  "type": "Feature",
  "properties": {
    "iso:country":"CH",
    "sg:address":"Wannenweg 3 4133 Pratteln. Postfach 1744",
    "sg:city":"Pratteln",
    "sg:orig_category":"G\u00fcterbef\u00f6rderung im Strassenverkehr",
    "sg:phone":"+41 61 482 02 02",
    "sg:postcode":"4133",
    "sg:province":"Basel-Landschaft",
    "wof:name":"Ernst Pfirter Ag",
    "wof:placetype":"venue"
},
  "geometry": {"coordinates":[7.7119789124,47.5240859985],"type":"Point"}
}