{
  "type": "Feature",
  "properties": {
    "iso:country":"CH",
    "sg:address":"6655",
    "sg:city":"Intragna",
    "sg:orig_category":"Landesverteidigung, Sozialversicherung \u00d6ffentliche Verwaltung",
    "sg:phone":"+41 91 796 11 14",
    "sg:postcode":"6655",
    "sg:province":"Ticino",
    "wof:name":"Centro Di Protezione Civile Di Intragna",
    "wof:placetype":"venue"
},
  "geometry": {"coordinates":[8.7009353638,46.1777114868],"type":"Point"}
}