{
  "type": "Feature",
  "properties": {
    "iso:country":"CH",
    "sg:address":"Robert-durrerstrasse 4a 6370 Stans. Postfach 1224",
    "sg:city":"Stans",
    "sg:orig_category":"Institutionen f\u00fcr Behinderte Sonderschulen",
    "sg:phone":"+41 41 618 74 15",
    "sg:postcode":"6371",
    "sg:province":"Nidwalden",
    "wof:name":"Heilp\u00e4dagogische Schule",
    "wof:placetype":"venue"
},
  "geometry": {"coordinates":[8.3685388565,46.9593315125],"type":"Point"}
}