{
  "type": "Feature",
  "properties": {
    "iso:country":"CH",
    "sg:address":"Chamerstrasse 18",
    "sg:city":"Zug",
    "sg:orig_category":"Architektur U Ingenieurb\u00fcros",
    "sg:phone":"+41 41 758 15 37",
    "sg:postcode":"6300",
    "sg:province":"Zug",
    "wof:name":"Noesis, Schweizer Hans-peter",
    "wof:placetype":"venue"
},
  "geometry": {"coordinates":[8.51108,47.172009],"type":"Point"}
}