{
  "type": "Feature",
  "properties": {
    "iso:country":"CH",
    "sg:address":"Offenburgerstrasse 32",
    "sg:city":"Basel",
    "sg:classifiers":[
        {
            "category":"Restaurant",
            "type":"Food & Drink"
        }
    ],
    "sg:phone":"+41 61 691 75 08",
    "sg:postcode":"4057",
    "sg:province":"Basel-Stadt",
    "wof:name":"Restaurant Breisacherhof",
    "wof:placetype":"venue"
},
  "geometry": {"coordinates":[7.5884490013,47.5691184998],"type":"Point"}
}