{
  "type": "Feature",
  "properties": {
    "iso:country":"CH",
    "sg:address":"Himmelrichstrasse 91",
    "sg:city":"Kriens",
    "sg:orig_category":"Reparatur von Uhren U Schmuck",
    "sg:phone":"+41 41 310 84 33",
    "sg:postcode":"6010",
    "sg:province":"Luzern",
    "wof:name":"Bruno Reindl Uhrmacher",
    "wof:placetype":"venue"
},
  "geometry": {"coordinates":[8.2880353928,47.0254135132],"type":"Point"}
}