{
  "type": "Feature",
  "properties": {
    "iso:country":"CH",
    "sg:address":"B\u00fcrgenstrasse 34-36",
    "sg:city":"Luzern",
    "sg:classifiers":[
        {
            "category":"Professional",
            "subcategory":"Advertising",
            "type":"Services"
        }
    ],
    "sg:phone":"+41 41 360 00 36",
    "sg:postcode":"6005",
    "sg:province":"Luzern",
    "sg:tags":[
        "poster"
    ],
    "wof:name":"Fabrik Studios Ag",
    "wof:placetype":"venue"
},
  "geometry": {"coordinates":[8.31742,47.043972],"type":"Point"}
}