{
  "type": "Feature",
  "properties": {
    "iso:country":"CH",
    "sg:address":"Badenerstrasse 2 5442 Fislisbach. Postfach 19",
    "sg:city":"Fislisbach",
    "sg:orig_category":"Regionalbanken U Sparkassen",
    "sg:phone":"+41 56 483 41 41",
    "sg:postcode":"5442",
    "sg:province":"Aargau",
    "wof:name":"Neue Aargauer Bank",
    "wof:placetype":"venue"
},
  "geometry": {"coordinates":[8.2914571762,47.435710907],"type":"Point"}
}