{
  "type": "Feature",
  "properties": {
    "iso:country":"CH",
    "sg:address":"Oberalpstrasse 31 4054 Basel. Postfach",
    "sg:city":"Basel",
    "sg:orig_category":"Grosshandel mit Datenverarbeitungsger\u00e4ten",
    "sg:phone":"+41 61 303 96 56",
    "sg:postcode":"4009",
    "sg:province":"Basel-Stadt",
    "wof:name":"Christian Burkhalter Cbis Informatik Systeme",
    "wof:placetype":"venue"
},
  "geometry": {"coordinates":[7.5643420219,47.5487937927],"type":"Point"}
}