{
  "type": "Feature",
  "properties": {
    "iso:country":"CH",
    "sg:address":"Alte Landstrasse 34 5027 Herznach. Postfach 52",
    "sg:city":"Herznach",
    "sg:orig_category":"Grosshandel mit B\u00fcromaschinen Herstellung von Schreibwaren U B\u00fcrobedarf aus Papier, Karton U Pappe",
    "sg:phone":"+41 62 878 13 61",
    "sg:postcode":"5027",
    "sg:province":"Aargau",
    "wof:name":"Schulmaterialien Peter Inhaber Thomas Deiss",
    "wof:placetype":"venue"
},
  "geometry": {"coordinates":[8.0521411896,47.4786682129],"type":"Point"}
}