{
  "type": "Feature",
  "properties": {
    "iso:country":"CH",
    "sg:address":"Fl\u00fchlistrasse 48",
    "sg:city":"Steffisburg",
    "sg:orig_category":"Unclassifiable Establishments",
    "sg:phone":"+41 33 437 23 48",
    "sg:postcode":"3612",
    "sg:province":"Bern",
    "wof:name":"Fritz Zwicky",
    "wof:placetype":"venue"
},
  "geometry": {"coordinates":[7.6315050125,46.7861289978],"type":"Point"}
}