{
  "type": "Feature",
  "properties": {
    "iso:country":"CH",
    "sg:address":"Guisan Av. Du G\u00e9n\u00e9ral 18 3960 Sierre. Postfach",
    "sg:city":"Sierre",
    "sg:orig_category":"Non-Classified Establishments",
    "sg:postcode":"3960",
    "sg:province":"Valais",
    "wof:name":"Si Race Montana Sa",
    "wof:placetype":"venue"
},
  "geometry": {"coordinates":[7.5308489799,46.2925376892],"type":"Point"}
}