{
  "type": "Feature",
  "properties": {
    "iso:country":"CH",
    "sg:address":"H\u00f6henstrasse 2",
    "sg:city":"Elgg",
    "sg:orig_category":"Grosshandel mit Holz U Baustoffen Unternehmensberatung",
    "sg:phone":"+41 52 364 20 02",
    "sg:postcode":"8353",
    "sg:province":"Z\u00fcrich",
    "wof:name":"Ice Interconsult Engineering Ag",
    "wof:placetype":"venue"
},
  "geometry": {"coordinates":[8.8610534668,47.5024757385],"type":"Point"}
}