{
  "type": "Feature",
  "properties": {
    "iso:country":"CH",
    "sg:address":"Z\u00fcrcherstrasse 26 8245 Feuerthalen. Postfach 14",
    "sg:city":"Feuerthalen",
    "sg:orig_category":"Dienstleistungen von Beteiligungsgesellschaften",
    "sg:phone":"+41 79 405 62 82",
    "sg:postcode":"8245",
    "sg:province":"Z\u00fcrich",
    "wof:name":"Boss B\u00fcro Organisation Sandtner Silvia",
    "wof:placetype":"venue"
},
  "geometry": {"coordinates":[8.6434059143,47.6931762695],"type":"Point"}
}