{
  "type": "Feature",
  "properties": {
    "iso:country":"CH",
    "sg:address":"Avenue Adrien-jeandin 4",
    "sg:city":"Th\u00f4nex",
    "sg:orig_category":"Futtermittel, Heu and Stroh Grosshandel Zoo- and Haustier-Futtermittel Grosshandel",
    "sg:phone":"+41 22 348 26 98",
    "sg:postcode":"1226",
    "sg:province":"Gen\u00e8ve",
    "wof:name":"Cats And Dogs Sa",
    "wof:placetype":"venue"
},
  "geometry": {"coordinates":[6.2021870613,46.1922416687],"type":"Point"}
}