{
  "type": "Feature",
  "properties": {
    "addr:full":"Bahnhofstrasse 25 9230 Flawil. Postfach Flawil St. Gallen 9230",
    "addr:housenumber":"25",
    "addr:postcode":"9230 flawil. postfach;9230",
    "addr:street":"Bahnhofstrasse",
    "iso:country":"CH",
    "sg:address":"Bahnhofstrasse 25 9230 Flawil. Postfach",
    "sg:city":"Flawil",
    "sg:orig_category":"Detailhandel mit Beleuchtungs U Haushaltsgegenst\u00e4nden Grosshandel mit Eisenwaren sowie Installations",
    "sg:phone":"+41 71 393 12 20",
    "sg:postcode":"9230",
    "sg:province":"St. Gallen",
    "wof:name":"Heiz & Co.",
    "wof:placetype":"venue"
},
  "geometry": {"coordinates":[9.188456,47.414696],"type":"Point"}
}