{
  "type": "Feature",
  "properties": {
    "iso:country":"CH",
    "sg:address":"Guisan Via General 12",
    "sg:city":"Balerna",
    "sg:orig_category":"Herstellung von sonstigen Erzeugnissen",
    "sg:postcode":"6828",
    "sg:province":"Ticino",
    "wof:name":"Antoniazzi Luciano",
    "wof:placetype":"venue"
},
  "geometry": {"coordinates":[9.0086936951,45.8466415405],"type":"Point"}
}