{
  "type": "Feature",
  "properties": {
    "iso:country":"CH",
    "sg:address":"Au Tyle",
    "sg:city":"Ecoteaux",
    "sg:orig_category":"Forstwirtschaft ohne Dienstleistungen in der Forstwirtschaft",
    "sg:postcode":"1612",
    "sg:province":"Vaud",
    "wof:name":"Entreprise Foresti\u00e8re M\u00e9canis\u00e9e Fbs D. Francey, J-p Bovey, T. Schmuki",
    "wof:placetype":"venue"
},
  "geometry": {"coordinates":[6.8593711853,46.5424575806],"type":"Point"}
}