{
  "type": "Feature",
  "properties": {
    "iso:country":"CH",
    "sg:address":"Ferdinand Hodler-strasse 44 8049 Z\u00fcrich. Postfach",
    "sg:city":"Z\u00fcrich",
    "sg:orig_category":"Softwareentwicklung U beratung",
    "sg:postcode":"8049",
    "sg:province":"Z\u00fcrich",
    "wof:name":"Compulex Shah Raymond",
    "wof:placetype":"venue"
},
  "geometry": {"coordinates":[8.4979887009,47.4049072266],"type":"Point"}
}