{
  "type": "Feature",
  "properties": {
    "iso:country":"CH",
    "sg:address":"Rue De La Planche 2",
    "sg:city":"Moudon",
    "sg:orig_category":"Detailhandel mit Fleisch U Fleischwaren",
    "sg:phone":"+41 21 866 76 76",
    "sg:postcode":"1510",
    "sg:province":"Vaud",
    "wof:name":"Claude Martin Boucherie-charcuterie",
    "wof:placetype":"venue"
},
  "geometry": {"coordinates":[6.3135261536,46.6674957275],"type":"Point"}
}