{
  "type": "Feature",
  "properties": {
    "iso:country":"CH",
    "sg:address":"Webereistrasse 45",
    "sg:city":"Adliswil",
    "sg:orig_category":"Herstellung von Metallkonstruktionen",
    "sg:phone":"+41 17107555",
    "sg:postcode":"8134",
    "sg:province":"Z\u00fcrich",
    "wof:name":"Bruno Hefti Metallbau",
    "wof:placetype":"venue"
},
  "geometry": {"coordinates":[8.5259923935,47.3073501587],"type":"Point"}
}