{
  "type": "Feature",
  "properties": {
    "iso:country":"CH",
    "sg:address":"Embergweg 1",
    "sg:city":"Steffisburg",
    "sg:orig_category":"Mechanik Mechanische Werkst\u00e4tten",
    "sg:phone":"+41 33 437 65 02",
    "sg:postcode":"3612",
    "sg:province":"Bern",
    "wof:name":"Weibel Anton, Mech. Werkstatt",
    "wof:placetype":"venue"
},
  "geometry": {"coordinates":[7.6422119141,46.7831840515],"type":"Point"}
}