{
  "type": "Feature",
  "properties": {
    "iso:country":"CH",
    "sg:address":"Chemin De La Colline 9",
    "sg:city":"Lausanne",
    "sg:orig_category":"Instandhaltung U Reparatur von Automobilen",
    "sg:phone":"+41 21 624 30 87",
    "sg:postcode":"1007",
    "sg:province":"Vaud",
    "wof:name":"Garage Gambino",
    "wof:placetype":"venue"
},
  "geometry": {"coordinates":[6.6110739708,46.5217437744],"type":"Point"}
}