{
  "type": "Feature",
  "properties": {
    "iso:country":"CH",
    "sg:address":"4416",
    "sg:city":"Bubendorf",
    "sg:orig_category":"Wasserversorgung",
    "sg:phone":"+41 62 756 11 42",
    "sg:postcode":"4416",
    "sg:province":"Basel-Landschaft",
    "wof:name":"Wasserversorgung Der Gemeinde Buchs",
    "wof:placetype":"venue"
},
  "geometry": {"coordinates":[8.0369100571,47.2019081116],"type":"Point"}
}