{
  "type": "Feature",
  "properties": {
    "iso:country":"CH",
    "sg:address":"Ambilly Route D' 3",
    "sg:city":"Th\u00f4nex",
    "sg:orig_category":"Tankstellen",
    "sg:postcode":"1226",
    "sg:province":"Gen\u00e8ve",
    "wof:name":"Schorno Michel",
    "wof:placetype":"venue"
},
  "geometry": {"coordinates":[6.1983990669,46.1901130676],"type":"Point"}
}