{
  "type": "Feature",
  "properties": {
    "iso:country":"CH",
    "sg:address":"Kantonsstrasse",
    "sg:city":"Dallenwil",
    "sg:orig_category":"Grafikateliers, Design Werbung",
    "sg:phone":"+41 41 628 03 50",
    "sg:postcode":"6383",
    "sg:province":"Nidwalden",
    "wof:name":"Reklame-atelier Gasser M.",
    "wof:placetype":"venue"
},
  "geometry": {"coordinates":[8.3924322128,46.9322166443],"type":"Point"}
}