{
  "type": "Feature",
  "properties": {
    "iso:country":"CH",
    "sg:address":"Mangelegg 96",
    "sg:city":"Schwyz",
    "sg:orig_category":"Allgemeiner Hoch U Tiefbau",
    "sg:phone":"+41 41 811 55 72",
    "sg:postcode":"6430",
    "sg:province":"Schwyz",
    "wof:name":"Bolfing Oskar, Generalunternehmer",
    "wof:placetype":"venue"
},
  "geometry": {"coordinates":[8.656273,47.028904],"type":"Point"}
}