{
  "type": "Feature",
  "properties": {
    "iso:country":"CH",
    "sg:address":"Feldstrasse 43",
    "sg:city":"Urdorf",
    "sg:orig_category":"Erbringung von sonstigen Dienstleistungen f\u00fcr Unterhaltung, Erholung U Freizeit",
    "sg:phone":"+41 17341009",
    "sg:postcode":"8902",
    "sg:province":"Z\u00fcrich",
    "wof:name":"Artisten-agentur D. Tommasi",
    "wof:placetype":"venue"
},
  "geometry": {"coordinates":[8.4237308502,47.3873672485],"type":"Point"}
}