{
  "type": "Feature",
  "properties": {
    "iso:country":"CH",
    "sg:address":"5737 Menziken. Postfach",
    "sg:city":"Menziken",
    "sg:orig_category":"Verkehrs- and Tourismusb\u00fcros",
    "sg:phone":"+41 62 771 25 79",
    "sg:postcode":"5737",
    "sg:province":"Aargau",
    "wof:name":"Verkehrsverein Menziken",
    "wof:placetype":"venue"
},
  "geometry": {"coordinates":[8.1877918243,47.2399864197],"type":"Point"}
}