{
  "type": "Feature",
  "properties": {
    "addr:full":"Kaufdorfstrasse 2 Toffen Bern 3125",
    "addr:housenumber":"2",
    "addr:postcode":"3125",
    "addr:street":"Kaufdorfstrasse",
    "iso:country":"CH",
    "sg:address":"Kaufdorfstrasse 2",
    "sg:city":"Toffen",
    "sg:orig_category":"Detailhandel mit Beleuchtungs U Haushaltsgegenst\u00e4nden Detailhandel mit elektrischen Haushalts, Radio",
    "sg:phone":"+41 31 819 10 94",
    "sg:postcode":"3125",
    "sg:province":"Bern",
    "wof:name":"Paul Liebi Elektrohaushaltger\u00e4te",
    "wof:placetype":"venue"
},
  "geometry": {"coordinates":[7.491578,46.85656],"type":"Point"}
}