{
  "type": "Feature",
  "properties": {
    "iso:country":"CH",
    "sg:address":"Via Alle Vigne 11",
    "sg:city":"Pregassona",
    "sg:orig_category":"Herstellung von k\u00e4lte U lufttechnischen Erzeugnissen f\u00fcr gewerbliche Zwecke Installation von Heizung",
    "sg:phone":"+41 91 941 10 49",
    "sg:postcode":"6963",
    "sg:province":"Ticino",
    "wof:name":"Avram Malz Impianti Frigoriferi",
    "wof:placetype":"venue"
},
  "geometry": {"coordinates":[8.9676113129,46.0206565857],"type":"Point"}
}