{
  "type": "Feature",
  "properties": {
    "iso:country":"CH",
    "sg:address":"Industrie Allmend 5612 Villmergen. Postfach 60",
    "sg:city":"Villmergen",
    "sg:orig_category":"Herstellung von keramischen Wand U Bodenfliesen U platten",
    "sg:phone":"+41 56 622 17 01",
    "sg:postcode":"5612",
    "sg:province":"Aargau",
    "wof:name":"Josef Meier Ag Villmergen",
    "wof:placetype":"venue"
},
  "geometry": {"coordinates":[8.244600296,47.3474121094],"type":"Point"}
}