{
  "type": "Feature",
  "properties": {
    "addr:full":"Rue Manoir 16 Gen\u00e8ve Gen\u00e8ve 1207",
    "addr:housenumber":"16",
    "addr:postcode":"1207",
    "addr:street":"Rue Manoir",
    "iso:country":"CH",
    "sg:address":"Rue Manoir 16",
    "sg:city":"Gen\u00e8ve",
    "sg:orig_category":"Arztpraxen",
    "sg:phone":"+41 22 788 35 50",
    "sg:postcode":"1207",
    "sg:province":"Gen\u00e8ve",
    "wof:name":"Dr M\u00e9d. Julia Vecsey M\u00e9decin Sp\u00e9cialiste Fmh",
    "wof:placetype":"venue"
},
  "geometry": {"coordinates":[6.160151,46.203678],"type":"Point"}
}