{
  "type": "Feature",
  "properties": {
    "addr:full":"Schwalbenweg 77a Frauenfeld Thurgau 8500",
    "addr:housenumber":"77a",
    "addr:postcode":"8500",
    "addr:street":"Schwalbenweg",
    "iso:country":"CH",
    "sg:address":"Schwalbenweg 77a",
    "sg:city":"Frauenfeld",
    "sg:orig_category":"Bauingenieurb\u00fcros Hochbau Bauingenieurb\u00fcros allgemein",
    "sg:phone":"+41 52 728 90 40",
    "sg:postcode":"8500",
    "sg:province":"Thurgau",
    "wof:name":"Sjb.partner Ag Ingenieurb\u00fcro",
    "wof:placetype":"venue"
},
  "geometry": {"coordinates":[8.900591,47.551197],"type":"Point"}
}