{
  "type": "Feature",
  "properties": {
    "iso:country":"CH",
    "sg:address":"D\u00f6rfliweg 1",
    "sg:city":"Horw",
    "sg:orig_category":"Arbeitnehmerverb\u00e4nde",
    "sg:phone":"+41 41 340 48 41",
    "sg:postcode":"6048",
    "sg:province":"Luzern",
    "wof:name":"Christl.landangestellten- Verband Luzern",
    "wof:placetype":"venue"
},
  "geometry": {"coordinates":[8.30554,47.011818],"type":"Point"}
}