{
  "type": "Feature",
  "properties": {
    "iso:country":"CH",
    "sg:address":"Katzenbachstrasse 105",
    "sg:city":"Z\u00fcrich",
    "sg:orig_category":"Sportvereine Sch\u00fctzen",
    "sg:postcode":"8052",
    "sg:province":"Z\u00fcrich",
    "wof:name":"Sch\u00fctzengesellschaft Sils-f\u00fcrstenau",
    "wof:placetype":"venue"
},
  "geometry": {"coordinates":[9.4555253983,46.7018165588],"type":"Point"}
}