{
  "type": "Feature",
  "properties": {
    "iso:country":"CH",
    "sg:address":"Chemin Des Sapins 7",
    "sg:city":"Cointrin",
    "sg:classifiers":[
        {
            "category":"Travel",
            "subcategory":"Hotels & Motels",
            "type":"Entertainment"
        }
    ],
    "sg:phone":"+41 22 798 07 57",
    "sg:postcode":"1216",
    "sg:province":"Gen\u00e8ve",
    "sg:tags":[
        "hotels",
        "mit",
        "restaurant"
    ],
    "wof:name":"H\u00f4tel Cerf-volant",
    "wof:placetype":"venue"
},
  "geometry": {"coordinates":[6.1091508865,46.2250404358],"type":"Point"}
}