{
  "type": "Feature",
  "properties": {
    "iso:country":"CH",
    "sg:address":"Froburgstrasse 21",
    "sg:city":"Basel",
    "sg:orig_category":"Allgemeinbildende weiterf\u00fchrende Schulen Sprachschulen",
    "sg:phone":"+41 61 312 36 11",
    "sg:postcode":"4052",
    "sg:province":"Basel-Stadt",
    "wof:name":"Maple Leaf School Of English Tschopp-james Linda & Co.",
    "wof:placetype":"venue"
},
  "geometry": {"coordinates":[7.612076,47.555508],"type":"Point"}
}