{
  "type": "Feature",
  "properties": {
    "iso:country":"CH",
    "sg:address":"Baslerstrasse 23 4600 Olten. Postfach",
    "sg:city":"Olten",
    "sg:orig_category":"RESTAURANTS: TEA-ROOMS",
    "sg:phone":"+41 62 212 21 80",
    "sg:postcode":"4603",
    "sg:province":"Solothurn",
    "wof:name":"Restaurant Rendez-vous Moser Willy Und Maria",
    "wof:placetype":"venue"
},
  "geometry": {"coordinates":[7.9025268555,47.3513221741],"type":"Point"}
}