{
  "type": "Feature",
  "properties": {
    "iso:country":"CH",
    "sg:address":"Mettlen 134",
    "sg:city":"Urn\u00e4sch",
    "sg:orig_category":"Primarschulen",
    "sg:phone":"+41 405421",
    "sg:postcode":"9107",
    "sg:province":"Appenzell Ausserrhoden",
    "wof:name":"Primarschule Mettlen",
    "wof:placetype":"venue"
},
  "geometry": {"coordinates":[8.7926301956,47.3628730774],"type":"Point"}
}