{
  "type": "Feature",
  "properties": {
    "iso:country":"CH",
    "sg:address":"Bellariastrasse 63",
    "sg:city":"Z\u00fcrich",
    "sg:orig_category":"\u00dcbersetzungsb\u00fcros",
    "sg:phone":"+41 14820626",
    "sg:postcode":"8038",
    "sg:province":"Z\u00fcrich",
    "wof:name":"Wolfgang Schnekenburger \u00dcbersetzungen",
    "wof:placetype":"venue"
},
  "geometry": {"coordinates":[8.529425621,47.3487548828],"type":"Point"}
}