{
  "type": "Feature",
  "properties": {
    "iso:country":"CH",
    "sg:address":"Preyergasse 13",
    "sg:city":"Z\u00fcrich",
    "sg:orig_category":"Reiseb\u00fcros U Reiseveranstalter",
    "sg:postcode":"8001",
    "sg:province":"Z\u00fcrich",
    "wof:name":"Cruise & Ferry Center, Dinger Jean-paul Et Edith",
    "wof:placetype":"venue"
},
  "geometry": {"coordinates":[6.2382597923,46.4797019958],"type":"Point"}
}