{
  "type": "Feature",
  "properties": {
    "iso:country":"CH",
    "sg:address":"Avenue De Rhodanie 60",
    "sg:city":"Lausanne",
    "sg:classifiers":[
        {
            "category":"Shopping",
            "subcategory":"Jewelry",
            "type":"Retail Goods"
        }
    ],
    "sg:phone":"+41 21 613 77 77",
    "sg:postcode":"1007",
    "sg:province":"Vaud",
    "sg:tags":[
        "diamond"
    ],
    "wof:name":"Golay Buchel & Cie Sa",
    "wof:placetype":"venue"
},
  "geometry": {"coordinates":[6.6079702377,46.5155715942],"type":"Point"}
}