{
  "type": "Feature",
  "properties": {
    "iso:country":"CH",
    "sg:address":"Niederholzstrasse 32",
    "sg:city":"Riehen",
    "sg:orig_category":"Detailhandel mit Computern U Software Hardwareberatung",
    "sg:postcode":"4125",
    "sg:province":"Basel-Stadt",
    "wof:name":"Yellowbyte Gmbh Edv-dienstleistung",
    "wof:placetype":"venue"
},
  "geometry": {"coordinates":[7.634905,47.574501],"type":"Point"}
}