{
  "type": "Feature",
  "properties": {
    "iso:country":"CH",
    "sg:address":"Rue St-randoald 9",
    "sg:city":"Del\u00e9mont",
    "sg:orig_category":"Schlossereien",
    "sg:phone":"+41 32 423 36 29",
    "sg:postcode":"2800",
    "sg:province":"Jura",
    "wof:name":"Eloi Ch\u00e8vre Atelier De Serrurerie",
    "wof:placetype":"venue"
},
  "geometry": {"coordinates":[7.3440499306,47.3548545837],"type":"Point"}
}