{
  "type": "Feature",
  "properties": {
    "iso:country":"CH",
    "sg:address":"Gibelhalde 4",
    "sg:city":"Herisau",
    "sg:orig_category":"Druck ohne Zeitungsdruck",
    "sg:postcode":"9100",
    "sg:province":"Appenzell Ausserrhoden",
    "wof:name":"Fust Consulting Beratungen",
    "wof:placetype":"venue"
},
  "geometry": {"coordinates":[9.2934236526,47.3895721436],"type":"Point"}
}