{
  "type": "Feature",
  "properties": {
    "iso:country":"CH",
    "sg:address":"Poststrasse 6",
    "sg:city":"Zug",
    "sg:orig_category":"Unclassifiable Establishments",
    "sg:phone":"+41 41 727 20 50",
    "sg:postcode":"6300",
    "sg:province":"Zug",
    "wof:name":"Aae Ahaus Alst\u00e4tter Eisenbahn Holding Ag",
    "wof:placetype":"venue"
},
  "geometry": {"coordinates":[8.5164813995,47.1685256958],"type":"Point"}
}