{
  "type": "Feature",
  "properties": {
    "iso:country":"CH",
    "sg:address":"Steinackerstrasse 13",
    "sg:city":"Lohn-ammannsegg",
    "sg:orig_category":"Detailhandel mit Metallwaren, Anstrichmitteln, Glaswaren, Bau U Heimwerkerbedarf Grosshandel mit Eis",
    "sg:phone":"+41 79 206 00 41",
    "sg:postcode":"4573",
    "sg:province":"Solothurn",
    "wof:name":"Menerga Ag",
    "wof:placetype":"venue"
},
  "geometry": {"coordinates":[7.5289850235,47.1714172363],"type":"Point"}
}