{
  "type": "Feature",
  "properties": {
    "iso:country":"CH",
    "sg:address":"Saint-pierre Rue 2 1003 Lausanne. Postfach",
    "sg:city":"Lausanne",
    "sg:orig_category":"Herstellung von K\u00fcchenm\u00f6beln",
    "sg:postcode":"1003",
    "sg:province":"Vaud",
    "wof:name":"Baranyi & Co",
    "wof:placetype":"venue"
},
  "geometry": {"coordinates":[8.8559570312,47.1953086853],"type":"Point"}
}