{
  "type": "Feature",
  "properties": {
    "iso:country":"CH",
    "sg:address":"Boulevard Carl-vogt 60",
    "sg:city":"Gen\u00e8ve",
    "sg:orig_category":"Elektro- and elektronische Maschinen Grosshandel",
    "sg:phone":"+41 22 800 02 40",
    "sg:postcode":"1205",
    "sg:province":"Gen\u00e8ve",
    "wof:name":"D\u00e9fi Technique Sa",
    "wof:placetype":"venue"
},
  "geometry": {"coordinates":[6.1358537674,46.1978683472],"type":"Point"}
}