{
  "type": "Feature",
  "properties": {
    "iso:country":"CH",
    "sg:address":"Im Gatter 2",
    "sg:city":"Benglen",
    "sg:classifiers":[
        {
            "category":"Insurance",
            "subcategory":"Insurance Agent",
            "type":"Services"
        }
    ],
    "sg:phone":"+41 18250744",
    "sg:postcode":"8121",
    "sg:province":"Z\u00fcrich",
    "sg:tags":[
        "versicherungsagenturen",
        "-broker"
    ],
    "wof:name":"Markus Herzog Axa Versicherungen",
    "wof:placetype":"venue"
},
  "geometry": {"coordinates":[8.6361179352,47.3626785278],"type":"Point"}
}