{
  "type": "Feature",
  "properties": {
    "iso:country":"CH",
    "sg:address":"Rue Hoffmann 1",
    "sg:city":"Gen\u00e8ve",
    "sg:orig_category":"Physiotherapie",
    "sg:phone":"+41 79 332 27 75",
    "sg:postcode":"1202",
    "sg:province":"Gen\u00e8ve",
    "wof:name":"Ch. Noiset & O. Adamkiewicz Institut De Physioth\u00e9rapie",
    "wof:placetype":"venue"
},
  "geometry": {"coordinates":[6.5809421539,46.5355224609],"type":"Point"}
}