{
  "type": "Feature",
  "properties": {
    "addr:full":"Luzernerstrasse 68 6330 Cham. Postfach 504 Cham Zug 6330",
    "addr:housenumber":"68;504",
    "addr:postcode":"6330;6330",
    "addr:street":"Luzernerstrasse;Postfach;Zug",
    "iso:country":"CH",
    "sg:address":"Luzernerstrasse 68 6330 Cham. Postfach 504",
    "sg:city":"Cham",
    "sg:orig_category":"Autogaragen",
    "sg:phone":"+41 41 785 60 80",
    "sg:postcode":"6330",
    "sg:province":"Zug",
    "wof:name":"Alfred Staub Touring-garage",
    "wof:placetype":"venue"
},
  "geometry": {"coordinates":[8.451752,47.175865],"type":"Point"}
}