{
  "type": "Feature",
  "properties": {
    "iso:country":"CH",
    "sg:address":"Innere G\u00fcterstrasse 4 6300 Zug. Postfach",
    "sg:city":"Chur",
    "sg:orig_category":"Sonstige Kultur U Unterhaltungseinrichtungen",
    "sg:phone":"+41 81 253 54 27",
    "sg:postcode":"7000",
    "sg:province":"Graubunden",
    "wof:name":"Casinos Austria (international) Ag",
    "wof:placetype":"venue"
},
  "geometry": {"coordinates":[8.5169610977,47.1777954102],"type":"Point"}
}