{
  "type": "Feature",
  "properties": {
    "iso:country":"CH",
    "sg:address":"Feldeggstrasse 5 8152 Glattbrugg. Postfach",
    "sg:city":"Glattbrugg",
    "sg:orig_category":"Herstellung von Teppichen",
    "sg:postcode":"8152",
    "sg:province":"Z\u00fcrich",
    "wof:name":"Ukaj Bodenbel\u00e4ge Parkette, Teppiche, Bodenbel\u00e4ge Usw.; Verlegung",
    "wof:placetype":"venue"
},
  "geometry": {"coordinates":[8.5602836609,47.4325904846],"type":"Point"}
}