{
  "type": "Feature",
  "properties": {
    "iso:country":"CH",
    "sg:address":"Bleicherweg 33 8002 Z\u00fcrich. Postfach",
    "sg:city":"Z\u00fcrich",
    "sg:orig_category":"Pensionskassen",
    "sg:phone":"+41 12042424",
    "sg:postcode":"8002",
    "sg:province":"Z\u00fcrich",
    "wof:name":"Credit Suisse Fides Zusatz-vorsorgestiftung",
    "wof:placetype":"venue"
},
  "geometry": {"coordinates":[8.5336637497,47.3668365479],"type":"Point"}
}