{
  "type": "Feature",
  "properties": {
    "iso:country":"CH",
    "sg:address":"Seestrasse 359",
    "sg:city":"Z\u00fcrich",
    "sg:orig_category":"Herstellung von sonstigen chemischen Erzeugnissen",
    "sg:phone":"+41 55 417 45 20",
    "sg:postcode":"8002",
    "sg:province":"Z\u00fcrich",
    "wof:name":"Jaro Trading Corporation Ag Chemisch-technische Und Petrochemische Produkte, Rohstoffe, Konsumg\u00fcter; Handel",
    "wof:placetype":"venue"
},
  "geometry": {"coordinates":[8.7901973724,47.2036628723],"type":"Point"}
}