{
  "type": "Feature",
  "properties": {
    "iso:country":"CH",
    "sg:address":"Reichsgasse 18 7000 Chur. Postfach",
    "sg:city":"Chur",
    "sg:classifiers":[
        {
            "category":"Travel",
            "subcategory":"Hotels & Motels",
            "type":"Entertainment"
        }
    ],
    "sg:phone":"+41 81 252 92 29",
    "sg:postcode":"7000",
    "sg:province":"Graubunden",
    "sg:tags":[
        "hotels",
        "mit",
        "restaurant"
    ],
    "wof:name":"Sch\u00e4llibaum Gebr.",
    "wof:placetype":"venue"
},
  "geometry": {"coordinates":[9.5338783264,46.8509750366],"type":"Point"}
}