{
  "type": "Feature",
  "properties": {
    "iso:country":"CH",
    "sg:address":"Tiefenwinkel",
    "sg:city":"M\u00fchlehorn",
    "sg:orig_category":"Schiffs U Bootsbau",
    "sg:phone":"+41 55 614 19 42",
    "sg:postcode":"8874",
    "sg:province":"Glarus",
    "wof:name":"Thoma Walter Bootsbau Gmbh",
    "wof:placetype":"venue"
},
  "geometry": {"coordinates":[9.18820858,47.1136741638],"type":"Point"}
}