{
  "type": "Feature",
  "properties": {
    "iso:country":"CH",
    "sg:address":"Wiesweg 6",
    "sg:city":"Glarus",
    "sg:orig_category":"Sonstiger Grosshandel",
    "sg:postcode":"8750",
    "sg:province":"Glarus",
    "wof:name":"Tepakom Ag",
    "wof:placetype":"venue"
},
  "geometry": {"coordinates":[9.0634098053,47.0424995422],"type":"Point"}
}