{
  "type": "Feature",
  "properties": {
    "iso:country":"CH",
    "sg:address":"Zwischenb\u00e4chen 8",
    "sg:city":"Z\u00fcrich",
    "sg:orig_category":"Sonstiger Grosshandel",
    "sg:postcode":"8048",
    "sg:province":"Z\u00fcrich",
    "wof:name":"Weroma-handels-ag Z\u00fcrich Warenhandel. Import, Export- U. Transitgesch\u00e4fte Usw",
    "wof:placetype":"venue"
},
  "geometry": {"coordinates":[8.481303215,47.385433197],"type":"Point"}
}