{
  "type": "Feature",
  "properties": {
    "iso:country":"CH",
    "sg:address":"Aeschstrasse 55",
    "sg:city":"Wettingen",
    "sg:orig_category":"Herstellung von k\u00e4lte U lufttechnischen Erzeugnissen f\u00fcr gewerbliche Zwecke Installation von Heizung",
    "sg:phone":"+41 56 426 64 42",
    "sg:postcode":"5430",
    "sg:province":"Aargau",
    "wof:name":"Meister Werner K\u00e4lte+klima",
    "wof:placetype":"venue"
},
  "geometry": {"coordinates":[8.3415327072,47.4671592712],"type":"Point"}
}