{
  "type": "Feature",
  "properties": {
    "iso:country":"CH",
    "sg:address":"Rathausstrasse 35",
    "sg:city":"Weinfelden",
    "sg:orig_category":"Detailhandel mit Tabakwaren",
    "sg:phone":"+41 34 402 13 71",
    "sg:postcode":"8570",
    "sg:province":"Thurgau",
    "wof:name":"K\u00fchni H.",
    "wof:placetype":"venue"
},
  "geometry": {"coordinates":[7.757589817,46.9491271973],"type":"Point"}
}