{
  "type": "Feature",
  "properties": {
    "iso:country":"CH",
    "sg:address":"Grundackerweg 53",
    "sg:city":"Berikon",
    "sg:orig_category":"Sportvereine Ballsport Handball",
    "sg:postcode":"8965",
    "sg:province":"Aargau",
    "wof:name":"Hr Tsv Berikon",
    "wof:placetype":"venue"
},
  "geometry": {"coordinates":[8.3680486679,47.3594741821],"type":"Point"}
}