{
  "type": "Feature",
  "properties": {
    "iso:country":"CH",
    "sg:address":"Rue Du Ch\u00e2teau 8-10",
    "sg:city":"Neuch\u00e2tel",
    "sg:orig_category":"Fachdetailhandel in Verkaufsr\u00e4umen Kunsthandel",
    "sg:phone":"+41 32 724 57 00",
    "sg:postcode":"2000",
    "sg:province":"Neuch\u00e2tel",
    "wof:name":"Galerie Ditesheim",
    "wof:placetype":"venue"
},
  "geometry": {"coordinates":[6.9280247688,46.9917793274],"type":"Point"}
}