{
  "type": "Feature",
  "properties": {
    "iso:country":"CH",
    "sg:address":"Avenue Tronchet 34",
    "sg:city":"Th\u00f4nex",
    "sg:orig_category":"Elektro- and elektronische Maschinen Grosshandel Softwareentwicklung U beratung",
    "sg:phone":"+41 19524444",
    "sg:postcode":"1226",
    "sg:province":"Gen\u00e8ve",
    "wof:name":"Ics Identcode Systeme Ag",
    "wof:placetype":"venue"
},
  "geometry": {"coordinates":[8.7871980667,47.3664970398],"type":"Point"}
}