{
  "type": "Feature",
  "properties": {
    "iso:country":"CH",
    "sg:address":"Wichlernweg 9",
    "sg:city":"Kriens",
    "sg:orig_category":"Vereine Gesang",
    "sg:postcode":"6010",
    "sg:province":"Luzern",
    "wof:name":"M\u00e4nnerchor Kriens",
    "wof:placetype":"venue"
},
  "geometry": {"coordinates":[8.2735996246,47.0319290161],"type":"Point"}
}