{
  "type": "Feature",
  "properties": {
    "iso:country":"CH",
    "sg:address":"T\u00f6distrasse 1 7000 Chur. Postfach",
    "sg:city":"Chur",
    "sg:orig_category":"Vermietung U Verpachtung von eigenen Immobilien Vermittlung von Immobilien",
    "sg:phone":"+41 26 665 00 52",
    "sg:postcode":"7000",
    "sg:province":"Graubunden",
    "wof:name":"Alex Hofstetter-colson Immocontact",
    "wof:placetype":"venue"
},
  "geometry": {"coordinates":[6.8680329323,46.8162384033],"type":"Point"}
}