{
  "type": "Feature",
  "properties": {
    "iso:country":"CH",
    "sg:address":"Sch\u00f6neggstrasse 62",
    "sg:city":"Grenchen",
    "sg:orig_category":"Unclassifiable Establishments",
    "sg:postcode":"2540",
    "sg:province":"Solothurn",
    "wof:name":"Restaurant Sch\u00f6negg Mostapha Sehli",
    "wof:placetype":"venue"
},
  "geometry": {"coordinates":[7.3936748505,47.2006912231],"type":"Point"}
}