{
  "type": "Feature",
  "properties": {
    "iso:country":"CH",
    "sg:address":"Fabrikstrasse 9",
    "sg:city":"H\u00e4gendorf",
    "sg:classifiers":[
        {
            "category":"Professional",
            "subcategory":"Accounting & Tax Preparation",
            "type":"Services"
        }
    ],
    "sg:phone":"+41 62 209 60 30",
    "sg:postcode":"4614",
    "sg:province":"Solothurn",
    "sg:tags":[
        "printers",
        "label",
        "printer",
        "bar-code"
    ],
    "wof:name":"Zidatech Ag",
    "wof:placetype":"venue"
},
  "geometry": {"coordinates":[7.83903,47.329418],"type":"Point"}
}