{
  "type": "Feature",
  "properties": {
    "iso:country":"CH",
    "sg:address":"La Tour De Chenaux",
    "sg:city":"Cully",
    "sg:orig_category":"Non-Classified Establishments",
    "sg:phone":"+41 21 799 21 40",
    "sg:postcode":"1096",
    "sg:province":"Vaud",
    "wof:name":"G9, Gilles Wannaz",
    "wof:placetype":"venue"
},
  "geometry": {"coordinates":[6.7287511826,46.4904594421],"type":"Point"}
}