{
  "type": "Feature",
  "properties": {
    "iso:country":"CH",
    "sg:address":"Route De La Venoge",
    "sg:city":"Echandens",
    "sg:orig_category":"Herstellung von Karosserien U Anh\u00e4ngern",
    "sg:phone":"+41 21 701 39 79",
    "sg:postcode":"1026",
    "sg:province":"Vaud",
    "wof:name":"Carrosserie Gianni, Giovanni Arduini",
    "wof:placetype":"venue"
},
  "geometry": {"coordinates":[6.5485367775,46.5366401672],"type":"Point"}
}