{
  "type": "Feature",
  "properties": {
    "iso:country":"CH",
    "sg:address":"Avenue Du Mail 17",
    "sg:city":"Gen\u00e8ve",
    "sg:orig_category":"Detailhandel mit Radio U Fernsehger\u00e4ten",
    "sg:phone":"+41 32 913 11 16",
    "sg:postcode":"1205",
    "sg:province":"Gen\u00e8ve",
    "wof:name":"Vid\u00e9o Le Trocad\u00e9ro",
    "wof:placetype":"venue"
},
  "geometry": {"coordinates":[6.8257350922,47.0997772217],"type":"Point"}
}