{
  "type": "Feature",
  "properties": {
    "iso:country":"CH",
    "sg:address":"Witikonerstrasse 470",
    "sg:city":"Z\u00fcrich",
    "sg:orig_category":"Herstellung von nachrichtentechnischen Ger\u00e4ten U Einrichtungen",
    "sg:postcode":"8053",
    "sg:province":"Z\u00fcrich",
    "wof:name":"Global Prepaid Card Center Gmbh",
    "wof:placetype":"venue"
},
  "geometry": {"coordinates":[8.5989522934,47.3608627319],"type":"Point"}
}