{
  "type": "Feature",
  "properties": {
    "iso:country":"CH",
    "sg:address":"Trestenberg 22",
    "sg:city":"Basadingen",
    "sg:orig_category":"Datenverarbeitungsdienste Softwareentwicklung U beratung",
    "sg:phone":"+41 52 657 37 90",
    "sg:postcode":"8254",
    "sg:province":"Thurgau",
    "wof:name":"Magic Web Jost Webdesign",
    "wof:placetype":"venue"
},
  "geometry": {"coordinates":[8.749614,47.665554],"type":"Point"}
}