{
  "type": "Feature",
  "properties": {
    "iso:country":"CH",
    "sg:address":"7180 Disentis/must\u00e9r. Postfach",
    "sg:city":"Disentis/must\u00e9r",
    "sg:orig_category":"Detailhandel mit elektrischen Haushalts-,Radio U Fernsehger\u00e4ten sowie Musikinstrumenten",
    "sg:postcode":"7180",
    "sg:province":"Graubunden",
    "wof:name":"Manetsch Sa",
    "wof:placetype":"venue"
},
  "geometry": {"coordinates":[8.8531293869,46.7046012878],"type":"Point"}
}