{
  "type": "Feature",
  "properties": {
    "iso:country":"CH",
    "sg:address":"Hauptstrasse 147",
    "sg:city":"Ormalingen",
    "sg:orig_category":"Gartenbau",
    "sg:phone":"+41 61 981 22 19",
    "sg:postcode":"4466",
    "sg:province":"Basel-Landschaft",
    "wof:name":"Bieber C. Gartenbau",
    "wof:placetype":"venue"
},
  "geometry": {"coordinates":[7.8764019012,47.4685249329],"type":"Point"}
}