{
  "type": "Feature",
  "properties": {
    "iso:country":"CH",
    "sg:address":"6344",
    "sg:city":"Meierskappel",
    "sg:orig_category":"Interessenvertretungen",
    "sg:phone":"+41 31 381 60 08",
    "sg:postcode":"6344",
    "sg:province":"Luzern",
    "wof:name":"Hauseigent\u00fcmerverband Bern Und Umgebung",
    "wof:placetype":"venue"
},
  "geometry": {"coordinates":[7.4338312149,46.9436950684],"type":"Point"}
}