{
  "type": "Feature",
  "properties": {
    "iso:country":"CH",
    "sg:address":"Im Werd 8",
    "sg:city":"Schlieren",
    "sg:orig_category":"Event Agenturen Unterhaltung, Kultur U Sport",
    "sg:postcode":"8952",
    "sg:province":"Z\u00fcrich",
    "wof:name":"Octagon Worldwide Limited",
    "wof:placetype":"venue"
},
  "geometry": {"coordinates":[8.4514198303,47.3982124329],"type":"Point"}
}