{
  "type": "Feature",
  "properties": {
    "iso:country":"CH",
    "sg:address":"G\u00fcrtelstrasse 23",
    "sg:city":"Chur",
    "sg:orig_category":"Wirtschafts U Arbeitgeberverb\u00e4nde",
    "sg:phone":"+41 31 312 55 65",
    "sg:postcode":"7000",
    "sg:province":"Graubunden",
    "wof:name":"Promarca Schweizerischer Markenartikelverband F\u00f6rderung Der Zusammenarbeit Zwischen Firmen Und Branchenverb\u00e4nden Usw",
    "wof:placetype":"venue"
},
  "geometry": {"coordinates":[7.4429187775,46.9480171204],"type":"Point"}
}