{
  "type": "Feature",
  "properties": {
    "iso:country":"CH",
    "sg:address":"Sch\u00fctzengasse 6",
    "sg:city":"St.gallen",
    "sg:orig_category":"Detailhandel mit Geschenkartikeln U Souvenirs Sonstiger Grosshandel",
    "sg:phone":"+41 71 925 33 25",
    "sg:postcode":"9000",
    "sg:province":"St. Gallen",
    "wof:name":"El Tumi Ag",
    "wof:placetype":"venue"
},
  "geometry": {"coordinates":[9.3723335266,47.4240036011],"type":"Point"}
}