{
  "type": "Feature",
  "properties": {
    "iso:country":"CH",
    "sg:address":"Rebbergstrasse 15b",
    "sg:city":"Wettingen",
    "sg:orig_category":"G\u00fcterbef\u00f6rderung im Strassenverkehr",
    "sg:phone":"+41 61 711 29 84",
    "sg:postcode":"5430",
    "sg:province":"Aargau",
    "wof:name":"Paul Blasowitsch Transporte",
    "wof:placetype":"venue"
},
  "geometry": {"coordinates":[7.5879769325,47.488861084],"type":"Point"}
}