{
  "type": "Feature",
  "properties": {
    "iso:country":"CH",
    "sg:address":"6662 Russo. Postfach",
    "sg:city":"Russo",
    "sg:orig_category":"S\u00e4ge, Hobel U Holzimpr\u00e4gnierwerke",
    "sg:postcode":"6662",
    "sg:province":"Ticino",
    "wof:name":"Segheria Coletta Di Ueli Pfenninger",
    "wof:placetype":"venue"
},
  "geometry": {"coordinates":[8.623298645,46.2024459839],"type":"Point"}
}