{
  "type": "Feature",
  "properties": {
    "iso:country":"CH",
    "sg:address":"Reussgasse 1",
    "sg:city":"Seon",
    "sg:orig_category":"Detailhandel mit Brillen U anderen Sehhilfen Fachdetailhandel in Verkaufsr\u00e4umen",
    "sg:phone":"+41 62 775 13 32",
    "sg:postcode":"5703",
    "sg:province":"Aargau",
    "wof:name":"W. Tschumi",
    "wof:placetype":"venue"
},
  "geometry": {"coordinates":[8.160601,47.345497],"type":"Point"}
}