{
  "type": "Feature",
  "properties": {
    "iso:country":"CH",
    "sg:address":"Hertenstrasse 41",
    "sg:city":"Frauenfeld",
    "sg:orig_category":"Botanische U zoologische G\u00e4rten sowie Naturparks RESTAURANTS: TEA-ROOMS",
    "sg:phone":"+41 52 720 81 91",
    "sg:postcode":"8500",
    "sg:province":"Thurgau",
    "wof:name":"Pl\u00e4ttli-zoo Ag",
    "wof:placetype":"venue"
},
  "geometry": {"coordinates":[8.916076,47.560318],"type":"Point"}
}