{
  "type": "Feature",
  "properties": {
    "iso:country":"CH",
    "sg:address":"Buchserstrasse 30",
    "sg:city":"Aarau",
    "sg:orig_category":"Datenverarbeitungsdienste Sonstige mit der Informatik verbundene T\u00e4tigkeiten",
    "sg:phone":"+41 62 837 57 72",
    "sg:postcode":"5000",
    "sg:province":"Aargau",
    "wof:name":"Som-data-service M. Sommerhalder",
    "wof:placetype":"venue"
},
  "geometry": {"coordinates":[8.060125,47.390884],"type":"Point"}
}