{
  "type": "Feature",
  "properties": {
    "iso:country":"CH",
    "sg:address":"Via Maraini 20",
    "sg:city":"Pregassona",
    "sg:orig_category":"Handelsvermittlung U Grosshandel Handelsvermittlung U Grosshandel mit Automobilteilen U Zubeh\u00f6r",
    "sg:phone":"+41 91 936 32 10",
    "sg:postcode":"6963",
    "sg:province":"Ticino",
    "wof:name":"Derendinger Sa Freni-frizioni",
    "wof:placetype":"venue"
},
  "geometry": {"coordinates":[8.9692182541,46.0269165039],"type":"Point"}
}