{
  "type": "Feature",
  "properties": {
    "addr:full":"Seefeld Buochs Nidwalden 6374",
    "addr:postcode":"6374",
    "addr:street":"Seefeld",
    "iso:country":"CH",
    "sg:address":"Seefeld",
    "sg:city":"Buochs",
    "sg:orig_category":"Campingpl\u00e4tze",
    "sg:phone":"+41 41 620 34 74",
    "sg:postcode":"6374",
    "sg:province":"Nidwalden",
    "wof:name":"Tcs Campingplatz",
    "wof:placetype":"venue"
},
  "geometry": {"coordinates":[8.420034,46.979389],"type":"Point"}
}