{
  "type": "Feature",
  "properties": {
    "iso:country":"CH",
    "sg:address":"Baselstrasse 59",
    "sg:city":"Dagmersellen",
    "sg:orig_category":"Erschliessung von Grundst\u00fccken",
    "sg:postcode":"6252",
    "sg:province":"Luzern",
    "wof:name":"Gemeinn\u00fctzige Siedlungsgenossenschaft Hostetsmatte",
    "wof:placetype":"venue"
},
  "geometry": {"coordinates":[7.9823441505,47.2195396423],"type":"Point"}
}