{
  "type": "Feature",
  "properties": {
    "iso:country":"CH",
    "sg:address":"Viale Castagnola",
    "sg:city":"Lugano",
    "sg:classifiers":[
        {
            "category":"Bars & Pubs",
            "type":"Food & Drink"
        }
    ],
    "sg:phone":"+41 91 971 14 97",
    "sg:postcode":"6900",
    "sg:province":"Ticino",
    "wof:name":"Riva Rosa Bar",
    "wof:placetype":"venue"
},
  "geometry": {"coordinates":[8.960729,46.00589],"type":"Point"}
}