{
  "type": "Feature",
  "properties": {
    "iso:country":"CH",
    "sg:address":"8423 Embrach-embraport. Postfach 200",
    "sg:city":"Embrach-embraport",
    "sg:orig_category":"Detailhandel mit B\u00fcromaschinen U einrichtungen",
    "sg:phone":"+41 71 250 02 51",
    "sg:postcode":"8423",
    "sg:province":"Z\u00fcrich",
    "wof:name":"B\u00dcro-plan Grossweiler Ph. B\u00fcroeinrichtungen",
    "wof:placetype":"venue"
},
  "geometry": {"coordinates":[9.373715,47.426392],"type":"Point"}
}