{
  "type": "Feature",
  "properties": {
    "iso:country":"CH",
    "sg:address":"Gotthardstrasse 61",
    "sg:city":"Meggen",
    "sg:orig_category":"Verlegen von Fliesen U Platten",
    "sg:phone":"+41 41 377 31 23",
    "sg:postcode":"6045",
    "sg:province":"Luzern",
    "wof:name":"K\u00e4lin Hafner-& Platten-ag",
    "wof:placetype":"venue"
},
  "geometry": {"coordinates":[8.3922796249,47.0558776855],"type":"Point"}
}