{
  "type": "Feature",
  "properties": {
    "iso:country":"CH",
    "sg:address":"Felsenstrasse 62",
    "sg:city":"Wollerau",
    "sg:orig_category":"Architektur U Ingenieurb\u00fcros",
    "sg:phone":"+41 16873070",
    "sg:postcode":"8832",
    "sg:province":"Schwyz",
    "wof:name":"H\u00fcppi Architektur Ag",
    "wof:placetype":"venue"
},
  "geometry": {"coordinates":[8.716736,47.192963],"type":"Point"}
}