{
  "type": "Feature",
  "properties": {
    "iso:country":"CH",
    "sg:address":"8575",
    "sg:city":"Istighofen",
    "sg:orig_category":"Schulpflegen",
    "sg:postcode":"8575",
    "sg:province":"Thurgau",
    "wof:name":"Schulkommission Der Gemeinde Istighofen",
    "wof:placetype":"venue"
},
  "geometry": {"coordinates":[9.1485204697,47.5406417847],"type":"Point"}
}