{
  "type": "Feature",
  "properties": {
    "iso:country":"CH",
    "sg:address":"Bachtalen 18 6020 Emmenbr\u00fccke. Postfach",
    "sg:city":"Emmenbr\u00fccke",
    "sg:orig_category":"Herstellung von Duft U K\u00f6rperpflegemitteln",
    "sg:phone":"+41 41 281 17 06",
    "sg:postcode":"6020",
    "sg:province":"Luzern",
    "wof:name":"Perera Steve Cosmetics",
    "wof:placetype":"venue"
},
  "geometry": {"coordinates":[8.2709474564,47.089679718],"type":"Point"}
}