{
  "type": "Feature",
  "properties": {
    "addr:full":"Altgasse 46 6340 Baar. Postfach 122 Baar Zug 6341",
    "addr:housenumber":"46;122",
    "addr:postcode":"6340 baar.;6341",
    "addr:street":"Altgasse;Postfach;Zug",
    "iso:country":"CH",
    "sg:address":"Altgasse 46 6340 Baar. Postfach 122",
    "sg:city":"Baar",
    "sg:orig_category":"Aktivit\u00e4ten der Generalunternehmen im Baugewerbe Kauf U Verkauf von Immobilien auf eigene Rechnung",
    "sg:phone":"+41 41 761 80 22",
    "sg:postcode":"6341",
    "sg:province":"Zug",
    "wof:name":"Beerli Walter & Co.",
    "wof:placetype":"venue"
},
  "geometry": {"coordinates":[8.51747,47.192657],"type":"Point"}
}