{
  "type": "Feature",
  "properties": {
    "iso:country":"CH",
    "sg:address":"Schneckelerstrasse 4b",
    "sg:city":"F\u00fcllinsdorf",
    "sg:orig_category":"Sonstiges Versicherungsgewerbe",
    "sg:phone":"+41 61 906 63 11",
    "sg:postcode":"4414",
    "sg:province":"Basel-Landschaft",
    "wof:name":"Berner Versicherungen, Generalagentur Burgunder Markus, F\u00fcllinsdorf",
    "wof:placetype":"venue"
},
  "geometry": {"coordinates":[7.7213630676,47.5130958557],"type":"Point"}
}