{
  "type": "Feature",
  "properties": {
    "iso:country":"CH",
    "sg:address":"Lange Gasse 47",
    "sg:city":"Basel",
    "sg:orig_category":"Grosshandel mit festen Brennstoffen U Mineral\u00f6lerzeugnissen Mineral\u00f6lverarbeitung",
    "sg:phone":"+41 32 466 12 61",
    "sg:postcode":"4052",
    "sg:province":"Basel-Stadt",
    "wof:name":"Braichet Fernand Et & Cie, Succ. Beureux P. Et Schaffter P.",
    "wof:placetype":"venue"
},
  "geometry": {"coordinates":[7.0786027908,47.42004776],"type":"Point"}
}