{
  "type": "Feature",
  "properties": {
    "iso:country":"CH",
    "sg:address":"Kr\u00e4hholzweg 3 3324 Hindelbank. Postfach",
    "sg:city":"Hindelbank",
    "sg:orig_category":"Architektur U Ingenieurb\u00fcros",
    "sg:postcode":"3324",
    "sg:province":"Bern",
    "wof:name":"Processtec Gmbh",
    "wof:placetype":"venue"
},
  "geometry": {"coordinates":[7.545915,47.046932],"type":"Point"}
}