{
  "type": "Feature",
  "properties": {
    "iso:country":"CH",
    "sg:address":"Chemin Des Rosiers 5",
    "sg:city":"Aigle",
    "sg:orig_category":"Sportvereine Turnen",
    "sg:postcode":"1860",
    "sg:province":"Vaud",
    "wof:name":"St\u00e9 De Gymnastique Ancienne",
    "wof:placetype":"venue"
},
  "geometry": {"coordinates":[6.9623332024,46.3174743652],"type":"Point"}
}