{
  "type": "Feature",
  "properties": {
    "iso:country":"CH",
    "sg:address":"Unterdorfstrasse 53",
    "sg:city":"Br\u00fctten",
    "sg:orig_category":"Elektroinstallation Herstellung von Elektromotoren, Generatoren U Transformatoren",
    "sg:phone":"+41 52 347 13 80",
    "sg:postcode":"8311",
    "sg:province":"Z\u00fcrich",
    "wof:name":"Z\u00fcnd Elektro Ag",
    "wof:placetype":"venue"
},
  "geometry": {"coordinates":[8.6793270111,47.4720191956],"type":"Point"}
}