{
  "type": "Feature",
  "properties": {
    "iso:country":"CH",
    "sg:address":"6774",
    "sg:city":"Dalpe",
    "sg:classifiers":[
        {
            "category":"Education",
            "subcategory":"Library",
            "type":"Public Place"
        }
    ],
    "sg:postcode":"6774",
    "sg:province":"Ticino",
    "sg:tags":[
        "u",
        "bibliotheken",
        "archive"
    ],
    "wof:name":"Biblioteca Popolare Parrocchiale",
    "wof:placetype":"venue"
},
  "geometry": {"coordinates":[8.774479,46.474903],"type":"Point"}
}