{
  "type": "Feature",
  "properties": {
    "iso:country":"CH",
    "sg:address":"Ch Des Coquelicots 16",
    "sg:city":"Gen\u00e8ve",
    "sg:classifiers":[
        {
            "category":"Banks & Credit Unions",
            "subcategory":"Bank",
            "type":"Services"
        }
    ],
    "sg:postcode":"1215",
    "sg:province":"Gen\u00e8ve",
    "wof:name":"Robeco Bank (suisse) Sa",
    "wof:placetype":"venue"
},
  "geometry": {"coordinates":[6.094722,46.221958],"type":"Point"}
}