{
  "type": "Feature",
  "properties": {
    "iso:country":"CH",
    "sg:address":"Bahnhofstrasse 25",
    "sg:city":"Kiesen",
    "sg:classifiers":[
        {
            "category":"Food & Beverages",
            "subcategory":"Fruits & Vegetables",
            "type":"Retail Goods"
        }
    ],
    "sg:phone":"+41 31 780 11 11",
    "sg:postcode":"3629",
    "sg:province":"Bern",
    "sg:tags":[
        "juice",
        "concentrate"
    ],
    "wof:name":"Pomdor Ag Kiesen",
    "wof:placetype":"venue"
},
  "geometry": {"coordinates":[7.5765638351,46.8195381165],"type":"Point"}
}