{
  "type": "Feature",
  "properties": {
    "iso:country":"CH",
    "sg:address":"Avenue Ernest-hentsch 1",
    "sg:city":"Gen\u00e8ve",
    "sg:orig_category":"Innenarchitekturb\u00fcros",
    "sg:phone":"+41 22 735 25 95",
    "sg:postcode":"1207",
    "sg:province":"Gen\u00e8ve",
    "wof:name":"Claude Duccini Architecture D'int\u00e9rieur",
    "wof:placetype":"venue"
},
  "geometry": {"coordinates":[6.1640667915,46.203830719],"type":"Point"}
}