{
  "type": "Feature",
  "properties": {
    "iso:country":"CH",
    "sg:address":"Grendelstrasse 10 6000 Luzern. Postfach",
    "sg:city":"Luzern",
    "sg:orig_category":"Allgemeiner Hoch U Tiefbau",
    "sg:postcode":"6004",
    "sg:province":"Luzern",
    "wof:name":"Swiss Bauservice Sbs Gmbh",
    "wof:placetype":"venue"
},
  "geometry": {"coordinates":[8.306919,47.053558],"type":"Point"}
}