{
  "type": "Feature",
  "properties": {
    "iso:country":"CH",
    "sg:address":"St. Johanns-ring 108",
    "sg:city":"Basel",
    "sg:orig_category":"Glaserei",
    "sg:phone":"+41 61 321 58 01",
    "sg:postcode":"4056",
    "sg:province":"Basel-Stadt",
    "wof:name":"Alois Schweizer Glastechnische Werkst\u00e4tte",
    "wof:placetype":"venue"
},
  "geometry": {"coordinates":[7.5757060051,47.5630989075],"type":"Point"}
}