{
  "type": "Feature",
  "properties": {
    "iso:country":"CH",
    "sg:address":"Strada Cantonale",
    "sg:city":"Quartino",
    "sg:classifiers":[
        {
            "category":"Restaurant",
            "type":"Food & Drink"
        }
    ],
    "sg:phone":"+41 91 858 34 02",
    "sg:postcode":"6572",
    "sg:province":"Ticino",
    "sg:tags":[
        "pasta"
    ],
    "wof:name":"Pastificio Simona Sa",
    "wof:placetype":"venue"
},
  "geometry": {"coordinates":[8.9064464569,46.1532821655],"type":"Point"}
}