{
  "type": "Feature",
  "properties": {
    "iso:country":"CH",
    "sg:address":"G\u00fcterstrasse 2",
    "sg:city":"Luzern",
    "sg:orig_category":"Dvd Productions",
    "sg:phone":"+41 41 361 02 44",
    "sg:postcode":"6005",
    "sg:province":"Luzern",
    "wof:name":"Calypso Film Ag",
    "wof:placetype":"venue"
},
  "geometry": {"coordinates":[8.3138608932,47.0469551086],"type":"Point"}
}