{
  "type": "Feature",
  "properties": {
    "iso:country":"CH",
    "sg:address":"Schulstrasse 7",
    "sg:city":"W\u00fcrenlingen",
    "sg:orig_category":"Fachdetailhandel mit pharmazeutischen Produkten",
    "sg:phone":"+41 56 297 10 10",
    "sg:postcode":"5303",
    "sg:province":"Aargau",
    "wof:name":"Dorf-apotheke W\u00fcrenlingen",
    "wof:placetype":"venue"
},
  "geometry": {"coordinates":[8.2582578659,47.5328598022],"type":"Point"}
}