{
  "type": "Feature",
  "properties": {
    "iso:country":"CH",
    "sg:address":"Bodenstrasse",
    "sg:city":"Sch\u00fcpfen",
    "sg:orig_category":"Sonstiger spezialisierter Hoch U Tiefbau",
    "sg:phone":"+41 31 879 10 80",
    "sg:postcode":"3054",
    "sg:province":"Bern",
    "wof:name":"Berger Ger\u00dcstbau Ag",
    "wof:placetype":"venue"
},
  "geometry": {"coordinates":[7.3808450699,47.0405235291],"type":"Point"}
}