{
  "type": "Feature",
  "properties": {
    "iso:country":"CH",
    "sg:address":"Dorfstrasse 7",
    "sg:city":"Kaltbrunn",
    "sg:orig_category":"Advokaturb\u00fcros",
    "sg:phone":"+41 71 225 40 90",
    "sg:postcode":"8722",
    "sg:province":"St. Gallen",
    "wof:name":"Jakob Huber Advokaturb\u00fcro",
    "wof:placetype":"venue"
},
  "geometry": {"coordinates":[9.025019,47.213505],"type":"Point"}
}