{
  "type": "Feature",
  "properties": {
    "iso:country":"CH",
    "sg:address":"Steinackerstrasse 8902 Urdorf. Postfach",
    "sg:city":"Urdorf",
    "sg:orig_category":"Herstellung von sonstigen Maschinen f\u00fcr bestimmte Verwendung",
    "sg:postcode":"8902",
    "sg:province":"Z\u00fcrich",
    "wof:name":"Sr Urdorf, Rosenstiel B.",
    "wof:placetype":"venue"
},
  "geometry": {"coordinates":[8.4244804382,47.3956832886],"type":"Point"}
}