{
  "type": "Feature",
  "properties": {
    "iso:country":"CH",
    "sg:address":"Im B\u00fchl",
    "sg:city":"Bussnang",
    "sg:orig_category":"Mechanik",
    "sg:postcode":"9565",
    "sg:province":"Thurgau",
    "wof:name":"Wolf T.",
    "wof:placetype":"venue"
},
  "geometry": {"coordinates":[9.0787296295,47.5577392578],"type":"Point"}
}