{
  "type": "Feature",
  "properties": {
    "addr:full":"Avenue J.-d.- Maillard 1 Meyrin Gen\u00e8ve 1217",
    "addr:housenumber":"1",
    "addr:postcode":"1217",
    "addr:street":"Avenue J.-D. Maillard",
    "iso:country":"CH",
    "sg:address":"Avenue J.-d.- Maillard 1",
    "sg:city":"Meyrin",
    "sg:orig_category":"Brillen Detailhandel",
    "sg:phone":"+41 22 782 96 33",
    "sg:postcode":"1217",
    "sg:province":"Gen\u00e8ve",
    "wof:name":"Visilab Sa",
    "wof:placetype":"venue"
},
  "geometry": {"coordinates":[6.067613,46.229645],"type":"Point"}
}