{
  "type": "Feature",
  "properties": {
    "iso:country":"CH",
    "sg:address":"Carl Spitteler-strasse 70",
    "sg:city":"Z\u00fcrich",
    "sg:orig_category":"Physiotherapie",
    "sg:phone":"+41 21 691 76 54",
    "sg:postcode":"8053",
    "sg:province":"Z\u00fcrich",
    "wof:name":"Bernard & Marianne Gloor Physioth\u00e9rapie",
    "wof:placetype":"venue"
},
  "geometry": {"coordinates":[6.5645470619,46.5291633606],"type":"Point"}
}