{
  "type": "Feature",
  "properties": {
    "iso:country":"CH",
    "sg:address":"Via Vallemaggia 61 6600 Locarno. Postfach",
    "sg:city":"Solduno",
    "sg:orig_category":"Fachdetailhandel mit pharmazeutischen Produkten",
    "sg:postcode":"6600",
    "sg:province":"Ticino",
    "wof:name":"Farmacia Soldati Sa",
    "wof:placetype":"venue"
},
  "geometry": {"coordinates":[8.7891702652,46.169719696],"type":"Point"}
}