{
  "type": "Feature",
  "properties": {
    "iso:country":"CH",
    "sg:address":"Br\u00fcnigstrasse 130 6072 Sachseln. Postfach",
    "sg:city":"Sachseln",
    "sg:orig_category":"Pensionskassen",
    "sg:postcode":"6072",
    "sg:province":"Obwalden",
    "wof:name":"Personalf\u00fcrsorgestiftung Der Firma Karl Omlin Ag, M\u00f6belfabrik.",
    "wof:placetype":"venue"
},
  "geometry": {"coordinates":[8.2340774536,46.8665504456],"type":"Point"}
}