{
  "type": "Feature",
  "properties": {
    "iso:country":"CH",
    "sg:address":"Dorfstrasse 17",
    "sg:city":"Zumikon",
    "sg:orig_category":"Unclassifiable Establishments",
    "sg:phone":"+41 19198800",
    "sg:postcode":"8126",
    "sg:province":"Z\u00fcrich",
    "wof:name":"Allmediacompany Ag",
    "wof:placetype":"venue"
},
  "geometry": {"coordinates":[8.6192026138,47.3362503052],"type":"Point"}
}