{
  "type": "Feature",
  "properties": {
    "iso:country":"CH",
    "sg:address":"Alter Markt 2",
    "sg:city":"Burgdorf",
    "sg:orig_category":"Interessenvertretungen",
    "sg:postcode":"3400",
    "sg:province":"Bern",
    "wof:name":"Genossenschaft Berna-haus",
    "wof:placetype":"venue"
},
  "geometry": {"coordinates":[7.6288428307,47.0558547974],"type":"Point"}
}