{
  "type": "Feature",
  "properties": {
    "iso:country":"CH",
    "sg:address":"K\u00fcrzeweg 8a",
    "sg:city":"Zunzgen",
    "sg:orig_category":"Unternehmensberatung",
    "sg:phone":"+41 61 973 11 60",
    "sg:postcode":"4455",
    "sg:province":"Basel-Landschaft",
    "wof:name":"Horst Jetzer Feuerschutz Security",
    "wof:placetype":"venue"
},
  "geometry": {"coordinates":[7.806101799,47.4520339966],"type":"Point"}
}