{
  "type": "Feature",
  "properties": {
    "iso:country":"CH",
    "sg:address":"Kirchstrasse 10",
    "sg:city":"Oberdiessbach",
    "sg:orig_category":"Herstellung von Konstruktionsteilen, Fertigbauteilen U Ausbauelementen aus Holz",
    "sg:phone":"+41 31 771 02 77",
    "sg:postcode":"3672",
    "sg:province":"Bern",
    "wof:name":"Paul Baumgartner Schreinerei - Fensterbau",
    "wof:placetype":"venue"
},
  "geometry": {"coordinates":[7.620639801,46.8399200439],"type":"Point"}
}