{
  "type": "Feature",
  "properties": {
    "iso:country":"CH",
    "sg:address":"2054",
    "sg:city":"Ch\u00e9zard-st-martin",
    "sg:orig_category":"Verwertung von Milch",
    "sg:postcode":"2054",
    "sg:province":"Neuch\u00e2tel",
    "wof:name":"Soci\u00e9t\u00e9 De Laiterie De Pertuis",
    "wof:placetype":"venue"
},
  "geometry": {"coordinates":[6.9220199585,47.0640907288],"type":"Point"}
}