{
  "type": "Feature",
  "properties": {
    "iso:country":"CH",
    "sg:address":"8462",
    "sg:city":"Rheinau",
    "sg:orig_category":"Abwasserreinigung",
    "sg:phone":"+41 52 319 24 86",
    "sg:postcode":"8462",
    "sg:province":"Z\u00fcrich",
    "wof:name":"Kl\u00e4ranlage",
    "wof:placetype":"venue"
},
  "geometry": {"coordinates":[8.604632,47.644451],"type":"Point"}
}