{
  "type": "Feature",
  "properties": {
    "iso:country":"CH",
    "sg:address":"Winklerstrasse 14",
    "sg:city":"Embrach",
    "sg:orig_category":"Grosshandel mit Wasch U Reinigungsmitteln Herstellung von sonstigen organischen Grundstoffen U Chemi",
    "sg:postcode":"8424",
    "sg:province":"Z\u00fcrich",
    "wof:name":"Russ Clean Dish Gmbh",
    "wof:placetype":"venue"
},
  "geometry": {"coordinates":[8.5920696259,47.5007820129],"type":"Point"}
}