{
  "type": "Feature",
  "properties": {
    "addr:full":"Rue De Courtelary 40 Tramelan Bern 2720",
    "addr:housenumber":"40",
    "addr:postcode":"2720",
    "addr:street":"Rue De Courtelary",
    "iso:country":"CH",
    "sg:address":"Rue De Courtelary 40",
    "sg:city":"Tramelan",
    "sg:classifiers":[
        {
            "category":"Government",
            "subcategory":"Fire Station",
            "type":"Public Place"
        }
    ],
    "sg:phone":"+41 32 487 50 25",
    "sg:postcode":"2720",
    "sg:province":"Bern",
    "sg:tags":[
        "component",
        "watch",
        "clock"
    ],
    "wof:name":"Jean-pierre Cl\u00e9ment & Cie Sa",
    "wof:placetype":"venue"
},
  "geometry": {"coordinates":[7.093513,47.217842],"type":"Point"}
}