{
  "type": "Feature",
  "properties": {
    "iso:country":"CH",
    "sg:address":"Dorfstrasse 36",
    "sg:city":"Spreitenbach",
    "sg:orig_category":"Polizei",
    "sg:phone":"+41 56 401 23 33",
    "sg:postcode":"8957",
    "sg:province":"Aargau",
    "wof:name":"Kantonspolizei",
    "wof:placetype":"venue"
},
  "geometry": {"coordinates":[8.3669471741,47.4188423157],"type":"Point"}
}