{
  "type": "Feature",
  "properties": {
    "iso:country":"CH",
    "sg:address":"Kyburgstrasse 12",
    "sg:city":"Bern",
    "sg:orig_category":"Vereine Quartier",
    "sg:postcode":"3013",
    "sg:province":"Bern",
    "wof:name":"Lorraine-breitenrain-leist",
    "wof:placetype":"venue"
},
  "geometry": {"coordinates":[7.4483718872,46.9567947388],"type":"Point"}
}