{
  "type": "Feature",
  "properties": {
    "iso:country":"CH",
    "sg:address":"Chemin Des Meures 6",
    "sg:city":"Ch\u00eane-bourg",
    "sg:orig_category":"Wirtschaftspr\u00fcfung, Steuerberatung U Treuhand",
    "sg:postcode":"1225",
    "sg:province":"Gen\u00e8ve",
    "wof:name":"Compta-gest, Leonardi",
    "wof:placetype":"venue"
},
  "geometry": {"coordinates":[6.1998472214,46.2004356384],"type":"Point"}
}