{
  "type": "Feature",
  "properties": {
    "iso:country":"CH",
    "sg:address":"Rasch\u00e4renstrasse 48",
    "sg:city":"Chur",
    "sg:orig_category":"Grosshandel mit sonstigen Nahrungsmitteln",
    "sg:phone":"+41 81 250 65 15",
    "sg:postcode":"7000",
    "sg:province":"Graubunden",
    "wof:name":"R\u00fcegg G., Frisch Und Tiefk\u00fchlprodukte Gmbh",
    "wof:placetype":"venue"
},
  "geometry": {"coordinates":[9.5071439743,46.8509597778],"type":"Point"}
}