{
  "type": "Feature",
  "properties": {
    "iso:country":"CH",
    "sg:address":"Ch. Des Mouettes 3",
    "sg:city":"Belmont-lausanne",
    "sg:orig_category":"Wirtschaftspr\u00fcfung, Steuerberatung U Treuhand",
    "sg:postcode":"1092",
    "sg:province":"Vaud",
    "wof:name":"Dhellin G.",
    "wof:placetype":"venue"
},
  "geometry": {"coordinates":[6.6778478622,46.5177726746],"type":"Point"}
}