{
  "type": "Feature",
  "properties": {
    "iso:country":"CH",
    "sg:address":"Freiestrasse 204 8032 Z\u00fcrich 32 Zust. Postfach 8032 Z\u00fcrich",
    "sg:city":"Zust",
    "sg:orig_category":"Kunststoff-Produkte",
    "sg:postcode":"32",
    "wof:name":"Lengen & Partner Ag, Synthetic Products & Services",
    "wof:placetype":"venue"
},
  "geometry": {"coordinates":[8.2228937149,46.8812065125],"type":"Point"}
}