{
  "type": "Feature",
  "properties": {
    "iso:country":"CH",
    "sg:address":"L\u00e4rchenweg 20",
    "sg:city":"Oberlunkhofen",
    "sg:classifiers":[
        {
            "category":"Travel",
            "subcategory":"Hotels & Motels",
            "type":"Entertainment"
        }
    ],
    "sg:postcode":"8917",
    "sg:province":"Aargau",
    "sg:tags":[
        "hotels",
        "mit",
        "restaurant"
    ],
    "wof:name":"Anemo Ag",
    "wof:placetype":"venue"
},
  "geometry": {"coordinates":[8.4022541046,47.3122711182],"type":"Point"}
}