{
  "type": "Feature",
  "properties": {
    "iso:country":"CH",
    "sg:address":"K\u00fcnzlistrasse 24",
    "sg:city":"Z\u00fcrich",
    "sg:orig_category":"K\u00fcnstlerische U schriftstellerische T\u00e4tigkeiten U Darbietungen",
    "sg:phone":"+41 13628986",
    "sg:postcode":"8057",
    "sg:province":"Z\u00fcrich",
    "wof:name":"Artowin Gmbh",
    "wof:placetype":"venue"
},
  "geometry": {"coordinates":[8.5335617065,47.4060668945],"type":"Point"}
}