{
  "type": "Feature",
  "properties": {
    "iso:country":"CH",
    "sg:address":"Ruberbaumstrasse 33",
    "sg:city":"M\u00e4rstetten",
    "sg:orig_category":"G\u00fcterbef\u00f6rderung im Strassenverkehr",
    "sg:phone":"+41 19201165",
    "sg:postcode":"8560",
    "sg:province":"Thurgau",
    "wof:name":"Lehnherr & Co Transporte",
    "wof:placetype":"venue"
},
  "geometry": {"coordinates":[8.6769866943,47.2593955994],"type":"Point"}
}