{
  "type": "Feature",
  "properties": {
    "iso:country":"CH",
    "sg:address":"Dorfstrasse 87",
    "sg:city":"Untersiggenthal",
    "sg:orig_category":"Herstellung von Metallerzeugnissen ohne Maschinenbau",
    "sg:phone":"+41 56 288 14 08",
    "sg:postcode":"5417",
    "sg:province":"Aargau",
    "wof:name":"Koller Fritz",
    "wof:placetype":"venue"
},
  "geometry": {"coordinates":[8.2517356873,47.5018577576],"type":"Point"}
}