{
  "type": "Feature",
  "properties": {
    "iso:country":"CH",
    "sg:address":"Grabenstrasse 32",
    "sg:city":"Zug",
    "sg:orig_category":"Unclassifiable Establishments",
    "sg:phone":"+41 41 711 26 27",
    "sg:postcode":"6300",
    "sg:province":"Zug",
    "wof:name":"Interpart Holding Ag",
    "wof:placetype":"venue"
},
  "geometry": {"coordinates":[8.5146417618,47.1651420593],"type":"Point"}
}