{
  "type": "Feature",
  "properties": {
    "iso:country":"CH",
    "sg:address":"Schlundstrasse 2 7205 Zizers. Postfach",
    "sg:city":"Zizers",
    "sg:orig_category":"Herstellung von K\u00fcchenm\u00f6beln Innenausbau",
    "sg:phone":"+41 81 322 27 23",
    "sg:postcode":"7205",
    "sg:province":"Graubunden",
    "wof:name":"A. Sohler Gmbh Einbauk\u00fcchen & Innenausbau",
    "wof:placetype":"venue"
},
  "geometry": {"coordinates":[9.5688037872,46.9421615601],"type":"Point"}
}