{
  "type": "Feature",
  "properties": {
    "iso:country":"CH",
    "sg:address":"Steinrietb\u00fcnt 7",
    "sg:city":"Sevelen",
    "sg:orig_category":"Unclassifiable Establishments",
    "sg:postcode":"9475",
    "sg:province":"St. Gallen",
    "wof:name":"Chasetta Ceramica Arioli",
    "wof:placetype":"venue"
},
  "geometry": {"coordinates":[9.4907808304,47.1264343262],"type":"Point"}
}