{
  "type": "Feature",
  "properties": {
    "iso:country":"CH",
    "sg:address":"Schaffhauserstrasse 424 8050 Z\u00fcrich. Postfach",
    "sg:city":"Z\u00fcrich",
    "sg:orig_category":"Gasversorgung Wasserversorgung",
    "sg:phone":"+41 13021455",
    "sg:postcode":"8050",
    "sg:province":"Z\u00fcrich",
    "wof:name":"Petroplan Ag Tankanlagen Und Rohrleitungen F\u00fcr Treibstoffe",
    "wof:placetype":"venue"
},
  "geometry": {"coordinates":[8.545465,47.415501],"type":"Point"}
}