{
  "type": "Feature",
  "properties": {
    "iso:country":"CH",
    "sg:address":"Chemin Du Premier-ao\u00fbt 3",
    "sg:city":"Grand-lancy",
    "sg:orig_category":"Detailhandel mit Metallwaren, Anstrichmitteln, Glaswaren, Bau U Heimwerkerbedarf Glaserei",
    "sg:phone":"+41 22 794 62 92",
    "sg:postcode":"1212",
    "sg:province":"Gen\u00e8ve",
    "wof:name":"Vitreries-stores De Lancy",
    "wof:placetype":"venue"
},
  "geometry": {"coordinates":[6.1221861839,46.1827392578],"type":"Point"}
}