{
  "type": "Feature",
  "properties": {
    "addr:full":"8592 Uttwil Thurgau 8592",
    "addr:postcode":"8592;8592",
    "iso:country":"CH",
    "sg:address":"8592",
    "sg:city":"Uttwil",
    "sg:orig_category":"Campingpl\u00e4tze",
    "sg:phone":"+41 71 463 23 98",
    "sg:postcode":"8592",
    "sg:province":"Thurgau",
    "wof:name":"Campingplatz Royal Gebr.hausammann Ag",
    "wof:placetype":"venue"
},
  "geometry": {"coordinates":[9.343112,47.582409],"type":"Point"}
}