{
  "type": "Feature",
  "properties": {
    "iso:country":"CH",
    "sg:address":"2735",
    "sg:city":"B\u00e9vilard",
    "sg:orig_category":"Verwertung von Milch",
    "sg:postcode":"2735",
    "sg:province":"Bern",
    "wof:name":"Soci\u00e9t\u00e9 De Fromagerie De Champoz",
    "wof:placetype":"venue"
},
  "geometry": {"coordinates":[7.2827119827,47.236618042],"type":"Point"}
}