{
  "type": "Feature",
  "properties": {
    "iso:country":"CH",
    "sg:address":"Claragraben 78",
    "sg:city":"Basel",
    "sg:orig_category":"Herstellung von Konstruktionsteilen, Fertigbauteilen U Ausbauelementen aus Holz",
    "sg:postcode":"4058",
    "sg:province":"Basel-Stadt",
    "wof:name":"Milvas Blagojevic",
    "wof:placetype":"venue"
},
  "geometry": {"coordinates":[7.5945000648,47.5622940063],"type":"Point"}
}