{
  "type": "Feature",
  "properties": {
    "iso:country":"CH",
    "sg:address":"Albisstrasse 133",
    "sg:city":"Z\u00fcrich",
    "sg:orig_category":"Herstellung von Metallkonstruktionen",
    "sg:postcode":"8038",
    "sg:province":"Z\u00fcrich",
    "wof:name":"Liquidationshaus Gehrig Ag",
    "wof:placetype":"venue"
},
  "geometry": {"coordinates":[8.5302190781,47.3358802795],"type":"Point"}
}