{
  "type": "Feature",
  "properties": {
    "iso:country":"CH",
    "sg:address":"Route De Corbaroche",
    "sg:city":"Marly",
    "sg:orig_category":"RESTAURANTS: TEA-ROOMS",
    "sg:postcode":"1723",
    "sg:province":"Fribourg",
    "wof:name":"Boschung Fran\u00e7ois.",
    "wof:placetype":"venue"
},
  "geometry": {"coordinates":[7.1621627808,46.7705383301],"type":"Point"}
}