{
  "type": "Feature",
  "properties": {
    "iso:country":"CH",
    "sg:address":"Poststrasse 2 9220 Bischofszell. Postfach",
    "sg:city":"Bischofszell",
    "sg:orig_category":"Versicherungen Generalagenturen",
    "sg:phone":"+41 71 424 20 60",
    "sg:postcode":"9220",
    "sg:province":"Thurgau",
    "wof:name":"Die Mobiliar Versicherungen & Vorsorge",
    "wof:placetype":"venue"
},
  "geometry": {"coordinates":[9.2424144745,47.4930877686],"type":"Point"}
}