{
  "type": "Feature",
  "properties": {
    "iso:country":"CH",
    "sg:address":"3432 L\u00fctzelfl\u00fch-goldb. Postfach 56",
    "sg:city":"L\u00fctzelfl\u00fch-goldb",
    "sg:orig_category":"Detailhandel mit M\u00f6beln U Haushaltsgegenst\u00e4nden Verlegen von Fussboden",
    "sg:phone":"+41 34 461 38 48",
    "sg:postcode":"3432",
    "sg:province":"Bern",
    "wof:name":"M\u00f6bel-tschannen Spezialgesch\u00e4ft F\u00fcr Wohneinrichtungen",
    "wof:placetype":"venue"
},
  "geometry": {"coordinates":[7.6784548759,47.0036315918],"type":"Point"}
}