{
  "type": "Feature",
  "properties": {
    "iso:country":"CH",
    "sg:address":"Route De La Comba 50",
    "sg:city":"Posieux",
    "sg:orig_category":"R\u00fcckgewinnung U Vorbereitung f\u00fcr die Wiederverwertung Recycling von nichtmetallischen Altmaterialien",
    "sg:phone":"+41 26 401 25 15",
    "sg:postcode":"1725",
    "sg:province":"Fribourg",
    "wof:name":"Sfr Soci\u00e9t\u00e9 Fribourgeoise De Recyclage Sa",
    "wof:placetype":"venue"
},
  "geometry": {"coordinates":[7.0953011513,46.7606010437],"type":"Point"}
}