{
  "type": "Feature",
  "properties": {
    "iso:country":"CH",
    "sg:address":"Widenweg 1",
    "sg:city":"Baden",
    "sg:orig_category":"Sanit\u00e4r, Heizungs U L\u00fcftungsinstallation Sanit\u00e4rinstallation",
    "sg:phone":"+41 56 222 32 71",
    "sg:postcode":"5400",
    "sg:province":"Aargau",
    "wof:name":"Vetterli's Halden Express Heizungen Und Sanit\u00e4r-reparaturen",
    "wof:placetype":"venue"
},
  "geometry": {"coordinates":[8.2904472351,47.4737052917],"type":"Point"}
}