{
  "type": "Feature",
  "properties": {
    "iso:country":"CH",
    "sg:address":"Holbeinstrasse 31",
    "sg:city":"Z\u00fcrich",
    "sg:orig_category":"Architektur U Ingenieurb\u00fcros",
    "sg:phone":"+41 12627354",
    "sg:postcode":"8008",
    "sg:province":"Z\u00fcrich",
    "wof:name":"Paul D. Osborne & Associates",
    "wof:placetype":"venue"
},
  "geometry": {"coordinates":[8.54978,47.364365],"type":"Point"}
}