{
  "type": "Feature",
  "properties": {
    "addr:full":"D\u00fcrntnerstrasse 12 Hinwil Z\u00fcrich 8340",
    "addr:housenumber":"12",
    "addr:postcode":"8340",
    "addr:street":"Duerntnerstrasse",
    "iso:country":"CH",
    "sg:address":"D\u00fcrntnerstrasse 12",
    "sg:city":"Hinwil",
    "sg:classifiers":[
        {
            "category":"Social Services",
            "subcategory":"Retirement Home",
            "type":"Services"
        }
    ],
    "sg:phone":"+41 19383232",
    "sg:postcode":"8340",
    "sg:province":"Z\u00fcrich",
    "sg:tags":[
        "pflegeheime",
        "u",
        "alters"
    ],
    "wof:name":"Alters-& Pflegeheim",
    "wof:placetype":"venue"
},
  "geometry": {"coordinates":[8.842271,47.300991],"type":"Point"}
}