{
  "type": "Feature",
  "properties": {
    "iso:country":"CH",
    "sg:address":"Zwingstrasse 6 5737 Menziken. Postfach",
    "sg:city":"Menziken",
    "sg:orig_category":"Druck ohne Zeitungsdruck Verlagsgewerbe",
    "sg:phone":"+41 62 765 13 13",
    "sg:postcode":"5737",
    "sg:province":"Aargau",
    "wof:name":"Druckerei Baumann Ag, Menziken",
    "wof:placetype":"venue"
},
  "geometry": {"coordinates":[8.1854076385,47.2403411865],"type":"Point"}
}