{
  "type": "Feature",
  "properties": {
    "iso:country":"CH",
    "sg:address":"Europe Avenue De L' 55 1870 Monthey. Postfach",
    "sg:city":"Monthey",
    "sg:orig_category":"Herstellung von K\u00fcchenm\u00f6beln",
    "sg:phone":"+41 24 471 41 35",
    "sg:postcode":"1870",
    "sg:province":"Valais",
    "wof:name":"Revaz Jean-francis Am\u00e9nagements De Cuisines; Achat, Vente, Installation",
    "wof:placetype":"venue"
},
  "geometry": {"coordinates":[6.9471402168,46.2516212463],"type":"Point"}
}