{
  "type": "Feature",
  "properties": {
    "iso:country":"CH",
    "sg:address":"Goldacherstrasse 11",
    "sg:city":"T\u00fcbach",
    "sg:orig_category":"Instandhaltung U Reparatur von Automobilen",
    "sg:phone":"+41 33 951 33 00",
    "sg:postcode":"9327",
    "sg:province":"St. Gallen",
    "wof:name":"Bruno Zobrist Autoelektro",
    "wof:placetype":"venue"
},
  "geometry": {"coordinates":[8.0459098816,46.7533988953],"type":"Point"}
}