{
  "type": "Feature",
  "properties": {
    "iso:country":"CH",
    "sg:address":"Kolinplatz 2",
    "sg:city":"Zug",
    "sg:orig_category":"Non-Classified Establishments",
    "sg:phone":"+41 41 728 73 73",
    "sg:postcode":"6300",
    "sg:province":"Zug",
    "wof:name":"Vm-verlags + Medien Holding Ag",
    "wof:placetype":"venue"
},
  "geometry": {"coordinates":[8.515376091,47.1663856506],"type":"Point"}
}