{
  "type": "Feature",
  "properties": {
    "iso:country":"CH",
    "sg:address":"Landshutstrasse 50",
    "sg:city":"Utzenstorf",
    "sg:orig_category":"Detailhandel mit Fleisch U Fleischwaren Grosshandel mit lebenden Tieren",
    "sg:phone":"+41 32 665 40 62",
    "sg:postcode":"3427",
    "sg:province":"Bern",
    "wof:name":"Metzgerei Aeschlimann Ag",
    "wof:placetype":"venue"
},
  "geometry": {"coordinates":[7.5482349396,47.1332168579],"type":"Point"}
}