{
  "type": "Feature",
  "properties": {
    "iso:country":"CH",
    "sg:address":"Avenue Juste-olivier 25",
    "sg:city":"Lausanne",
    "sg:orig_category":"Handelsvermittlung U Grosshandel",
    "sg:phone":"+41 21 320 08 10",
    "sg:postcode":"1006",
    "sg:province":"Vaud",
    "wof:name":"Ack-products",
    "wof:placetype":"venue"
},
  "geometry": {"coordinates":[6.6365838051,46.5138053894],"type":"Point"}
}