{
  "type": "Feature",
  "properties": {
    "iso:country":"CH",
    "sg:address":"Imbisb\u00fchlhalde 7",
    "sg:city":"Z\u00fcrich",
    "sg:orig_category":"Arbeitnehmerverb\u00e4nde",
    "sg:phone":"+41 13415648",
    "sg:postcode":"8049",
    "sg:province":"Z\u00fcrich",
    "wof:name":"Schweiz.werklehrerverein Swv Frau Ursula Homberger",
    "wof:placetype":"venue"
},
  "geometry": {"coordinates":[8.483777,47.406883],"type":"Point"}
}