{
  "type": "Feature",
  "properties": {
    "iso:country":"CH",
    "sg:address":"Davidstrasse 45",
    "sg:city":"St.gallen",
    "sg:orig_category":"Grosshandel mit B\u00fcromaschinen Grosshandel mit Datenverarbeitungsger\u00e4ten",
    "sg:phone":"+41 71 228 60 60",
    "sg:postcode":"9000",
    "sg:province":"St. Gallen",
    "wof:name":"Ahp Elektronik Ag",
    "wof:placetype":"venue"
},
  "geometry": {"coordinates":[9.3665800095,47.4192008972],"type":"Point"}
}