{
  "type": "Feature",
  "properties": {
    "iso:country":"CH",
    "sg:address":"K\u00e4sereistrasse",
    "sg:city":"Rohrbach",
    "sg:orig_category":"Sonstiger Grosshandel",
    "sg:phone":"+41 62 965 13 47",
    "sg:postcode":"4938",
    "sg:province":"Bern",
    "wof:name":"Lanz-beutler, Meya",
    "wof:placetype":"venue"
},
  "geometry": {"coordinates":[7.8127098083,47.1357841492],"type":"Point"}
}