{
  "type": "Feature",
  "properties": {
    "iso:country":"CH",
    "sg:address":"Eintrachtweg 1",
    "sg:city":"Fahrwangen",
    "sg:orig_category":"Architektur U Ingenieurb\u00fcros Einbau von Schreinerwaren",
    "sg:phone":"+41 56 667 16 11",
    "sg:postcode":"5615",
    "sg:province":"Aargau",
    "wof:name":"Morandi Architektur + K\u00fcchenbau Ag",
    "wof:placetype":"venue"
},
  "geometry": {"coordinates":[8.24542,47.294338],"type":"Point"}
}