{
  "type": "Feature",
  "properties": {
    "iso:country":"CH",
    "sg:address":"Neuwiesenstrasse 15",
    "sg:city":"Winterthur",
    "sg:orig_category":"Kauf U Verkauf von Immobilien auf eigene Rechnung",
    "sg:postcode":"8400",
    "sg:province":"Z\u00fcrich",
    "wof:name":"H. B\u00e4chli & Cie",
    "wof:placetype":"venue"
},
  "geometry": {"coordinates":[8.0715484619,47.3896865845],"type":"Point"}
}