{
  "type": "Feature",
  "properties": {
    "iso:country":"CH",
    "sg:address":"Rue Du Coll\u00e8ge 10",
    "sg:city":"Clarens",
    "sg:orig_category":"Fahrschulen, Flugschulen",
    "sg:phone":"+41 21 964 50 54",
    "sg:postcode":"1815",
    "sg:province":"Vaud",
    "wof:name":"Ren\u00e9 Vidoz Auto-\u00e9cole",
    "wof:placetype":"venue"
},
  "geometry": {"coordinates":[6.8957881927,46.4436454773],"type":"Point"}
}