{
  "type": "Feature",
  "properties": {
    "iso:country":"CH",
    "sg:address":"Altenbergstrasse 86 3013 Bern. Postfach",
    "sg:city":"Bern",
    "sg:orig_category":"Unclassifiable Establishments",
    "sg:postcode":"3005",
    "sg:province":"Bern",
    "wof:name":"Schlumpf-wyss Walter Hotel Schweizerhof, Weinhandlung",
    "wof:placetype":"venue"
},
  "geometry": {"coordinates":[9.2849197388,47.1935844421],"type":"Point"}
}