{
  "type": "Feature",
  "properties": {
    "iso:country":"CH",
    "sg:address":"Favon Bvd Georges- 20 1204 Gen\u00e8ve. Postfach",
    "sg:city":"Gen\u00e8ve",
    "sg:orig_category":"Sonstige mit der Informatik verbundene T\u00e4tigkeiten",
    "sg:postcode":"1204",
    "sg:province":"Gen\u00e8ve",
    "wof:name":"Gerfi G\u00e9rance Informatique Sa",
    "wof:placetype":"venue"
},
  "geometry": {"coordinates":[6.1399698257,46.2024345398],"type":"Point"}
}