{
  "type": "Feature",
  "properties": {
    "iso:country":"CH",
    "sg:address":"Bachwiesenstrasse 34 8400 Winterthur. Postfach",
    "sg:city":"Winterthur",
    "sg:orig_category":"Fernmeldedienste",
    "sg:phone":"+41 52 232 10 10",
    "sg:postcode":"8405",
    "sg:province":"Z\u00fcrich",
    "wof:name":"Websun Telecom, H. Neracher",
    "wof:placetype":"venue"
},
  "geometry": {"coordinates":[8.770321846,47.4847145081],"type":"Point"}
}