{
  "type": "Feature",
  "properties": {
    "iso:country":"CH",
    "sg:address":"Rue Pierre P\u00e9quignat 5",
    "sg:city":"Courgenay",
    "sg:orig_category":"Unclassifiable Establishments",
    "sg:postcode":"2950",
    "sg:province":"Jura",
    "wof:name":"Ugv Holding Sa",
    "wof:placetype":"venue"
},
  "geometry": {"coordinates":[7.124756813,47.4036941528],"type":"Point"}
}