{
  "type": "Feature",
  "properties": {
    "addr:full":"Hauptgasse 24 6130 Willisau. Postfach Willisau Luzern 6130",
    "addr:housenumber":"24",
    "addr:postcode":"6130 willisau. postfach;6130",
    "addr:street":"Hauptgasse",
    "iso:country":"CH",
    "sg:address":"Hauptgasse 24 6130 Willisau. Postfach",
    "sg:city":"Willisau",
    "sg:orig_category":"Detailhandel mit Brot, Back U S\u00fcsswaren",
    "sg:phone":"+41 41 970 11 14",
    "sg:postcode":"6130",
    "sg:province":"Luzern",
    "wof:name":"Walter Renggli B\u00e4ckerei-konditorei Amrein",
    "wof:placetype":"venue"
},
  "geometry": {"coordinates":[7.990554,47.120716],"type":"Point"}
}