{
  "type": "Feature",
  "properties": {
    "iso:country":"CH",
    "sg:address":"Via Riviera 6976 Castagnola. Postfach",
    "sg:city":"Castagnola",
    "sg:orig_category":"Schiffsbau ohne Boots U Yachtbau",
    "sg:postcode":"6976",
    "sg:province":"Ticino",
    "wof:name":"Sa Di Navigazione Marittima Dorado",
    "wof:placetype":"venue"
},
  "geometry": {"coordinates":[8.9768590927,46.0011177063],"type":"Point"}
}