{
  "type": "Feature",
  "properties": {
    "iso:country":"CH",
    "sg:address":"Chemin De Conches 5a",
    "sg:city":"Conches",
    "sg:orig_category":"Arztpraxen",
    "sg:phone":"+41 22 789 14 06",
    "sg:postcode":"1231",
    "sg:province":"Gen\u00e8ve",
    "wof:name":"Dr M\u00e9d. Claude Vauthier M\u00e9decin Sp\u00e9cialiste Fmh",
    "wof:placetype":"venue"
},
  "geometry": {"coordinates":[6.173824,46.183311],"type":"Point"}
}