{
  "type": "Feature",
  "properties": {
    "iso:country":"CH",
    "sg:address":"Dorf 8767 Elm. Postfach",
    "sg:city":"Elm",
    "sg:classifiers":[
        {
            "category":"Travel",
            "subcategory":"Hotels & Motels",
            "type":"Entertainment"
        }
    ],
    "sg:phone":"+41 55 642 12 32",
    "sg:postcode":"8767",
    "sg:province":"Glarus",
    "sg:tags":[
        "hotels",
        "mit",
        "restaurant"
    ],
    "wof:name":"Gasthaus Sonne, Zarnitz-fux Meinolf",
    "wof:placetype":"venue"
},
  "geometry": {"coordinates":[9.1722660065,46.9192466736],"type":"Point"}
}