{
  "type": "Feature",
  "properties": {
    "iso:country":"CH",
    "sg:address":"Weiherstrasse 1",
    "sg:city":"Rorschach",
    "sg:orig_category":"Architektur U Ingenieurb\u00fcros",
    "sg:phone":"+41 71 855 70 01",
    "sg:postcode":"9400",
    "sg:province":"St. Gallen",
    "wof:name":"Schwarz Bauunterst\u00fctzung Kollektivgesellschaft",
    "wof:placetype":"venue"
},
  "geometry": {"coordinates":[9.507602,47.476559],"type":"Point"}
}