{
  "type": "Feature",
  "properties": {
    "iso:country":"CH",
    "sg:address":"Schlossallee 9",
    "sg:city":"Greng",
    "sg:orig_category":"Herstellung von W\u00e4sche",
    "sg:postcode":"3280",
    "sg:province":"Fribourg",
    "wof:name":"Loup-k\u00e4lin Mme Marie-claire",
    "wof:placetype":"venue"
},
  "geometry": {"coordinates":[6.8432750702,46.4621353149],"type":"Point"}
}