{
  "type": "Feature",
  "properties": {
    "iso:country":"CH",
    "sg:address":"Kleinh\u00fcningerstrasse 162",
    "sg:city":"Basel",
    "sg:orig_category":"Allgemeiner Hoch U Tiefbau Hoch U Tiefbau",
    "sg:phone":"+41 26 322 19 71",
    "sg:postcode":"4057",
    "sg:province":"Basel-Stadt",
    "wof:name":"Egger Adolf",
    "wof:placetype":"venue"
},
  "geometry": {"coordinates":[7.198825,46.795513],"type":"Point"}
}