{
  "type": "Feature",
  "properties": {
    "iso:country":"CH",
    "sg:address":"Bennenegg 20",
    "sg:city":"Littau",
    "sg:orig_category":"Gewinnung von Kies U Sand",
    "sg:phone":"+41 41 280 72 72",
    "sg:postcode":"6014",
    "sg:province":"Luzern",
    "wof:name":"Zumb\u00fchl Kies Ag Littau",
    "wof:placetype":"venue"
},
  "geometry": {"coordinates":[8.2568511963,47.0490722656],"type":"Point"}
}