{
  "type": "Feature",
  "properties": {
    "iso:country":"CH",
    "sg:address":"P\u00fcntenstrasse 2",
    "sg:city":"Winterthur",
    "sg:classifiers":[
        {
            "category":"Arts & Performance",
            "subcategory":"Dance",
            "type":"Entertainment"
        }
    ],
    "sg:phone":"+41 71 278 88 22",
    "sg:postcode":"8404",
    "sg:province":"Z\u00fcrich",
    "sg:tags":[
        "casting"
    ],
    "wof:name":"Lehner Kunstgiesserei",
    "wof:placetype":"venue"
},
  "geometry": {"coordinates":[9.322069,47.410488],"type":"Point"}
}