{
  "type": "Feature",
  "properties": {
    "iso:country":"CH",
    "sg:address":"Chemin Du Vieux-v\u00e9senaz 56",
    "sg:city":"V\u00e9senaz",
    "sg:orig_category":"W\u00e4scherei U chemische Reinigung",
    "sg:phone":"+41 55 442 17 57",
    "sg:postcode":"1222",
    "sg:province":"Gen\u00e8ve",
    "wof:name":"Nettgens Rolf, Chemisch Reinigung",
    "wof:placetype":"venue"
},
  "geometry": {"coordinates":[8.8531122208,47.1904411316],"type":"Point"}
}