{
  "type": "Feature",
  "properties": {
    "iso:country":"CH",
    "sg:address":"Fangh\u00f6fli 8",
    "sg:city":"Littau",
    "sg:classifiers":[
        {
            "category":"Home & Garden",
            "subcategory":"Home Furnishings",
            "type":"Retail Goods"
        }
    ],
    "sg:phone":"+41 41 250 83 83",
    "sg:postcode":"6014",
    "sg:province":"Luzern",
    "sg:tags":[
        "metal",
        "furniture"
    ],
    "wof:name":"Glm Novitas Gmbh",
    "wof:placetype":"venue"
},
  "geometry": {"coordinates":[8.2616558075,47.0496673584],"type":"Point"}
}