{
  "type": "Feature",
  "properties": {
    "iso:country":"CH",
    "sg:address":"Albisriederstrasse 232",
    "sg:city":"Z\u00fcrich",
    "sg:orig_category":"Fachdetailhandel mit pharmazeutischen Produkten",
    "sg:phone":"+41 14925232",
    "sg:postcode":"8047",
    "sg:province":"Z\u00fcrich",
    "wof:name":"Beat Egloff Apotheke Utogrund",
    "wof:placetype":"venue"
},
  "geometry": {"coordinates":[8.4944705963,47.3789405823],"type":"Point"}
}