{
  "type": "Feature",
  "properties": {
    "iso:country":"CH",
    "sg:address":"Feldbergstrasse 44",
    "sg:city":"Basel",
    "sg:orig_category":"Detailhandel mit S\u00e4uglings U Kinderbekleidung Herstellung von sonstiger Bekleidung U Bekleidungszube",
    "sg:phone":"+41 61 691 64 88",
    "sg:postcode":"4057",
    "sg:province":"Basel-Stadt",
    "wof:name":"J\u00e4ger's Babyland, Inhaber J\u00e4ger Dominik",
    "wof:placetype":"venue"
},
  "geometry": {"coordinates":[7.590526104,47.5660514832],"type":"Point"}
}