{
  "type": "Feature",
  "properties": {
    "iso:country":"CH",
    "sg:address":"Via San Damiano 4",
    "sg:city":"Mendrisio",
    "sg:orig_category":"Detailhandel mit Fleisch U Fleischwaren",
    "sg:phone":"+41 91 646 35 70",
    "sg:postcode":"6850",
    "sg:province":"Ticino",
    "wof:name":"Maurizio Molina Macelleria Equina",
    "wof:placetype":"venue"
},
  "geometry": {"coordinates":[8.9881210327,45.8709411621],"type":"Point"}
}