{
  "type": "Feature",
  "properties": {
    "iso:country":"CH",
    "sg:address":"8022 Z\u00fcrich. Postfach 4283",
    "sg:city":"Z\u00fcrich",
    "sg:orig_category":"Vereine Geselligkeit",
    "sg:phone":"+41 238871",
    "sg:postcode":"8022",
    "sg:province":"Z\u00fcrich",
    "wof:name":"Schweiz.klub Langer Menschen",
    "wof:placetype":"venue"
},
  "geometry": {"coordinates":[8.7801494598,47.3748970032],"type":"Point"}
}