{
  "type": "Feature",
  "properties": {
    "iso:country":"CH",
    "sg:address":"Sch\u00fctzenstrasse 19",
    "sg:city":"Schwyz",
    "sg:orig_category":"Kauf U Verkauf von Immobilien auf eigene Rechnung",
    "sg:postcode":"6430",
    "sg:province":"Schwyz",
    "wof:name":"Gleissner & Co.",
    "wof:placetype":"venue"
},
  "geometry": {"coordinates":[8.6551208496,47.0190162659],"type":"Point"}
}