{
  "type": "Feature",
  "properties": {
    "iso:country":"CH",
    "sg:address":"Obstgartenstrasse 15",
    "sg:city":"Gattikon",
    "sg:orig_category":"Vorschulen, Kinderg\u00e4rten",
    "sg:phone":"+41 17200862",
    "sg:postcode":"8136",
    "sg:province":"Z\u00fcrich",
    "wof:name":"Kindergarten Altes Schulhaus",
    "wof:placetype":"venue"
},
  "geometry": {"coordinates":[8.5494432449,47.2842941284],"type":"Point"}
}