{
  "type": "Feature",
  "properties": {
    "iso:country":"CH",
    "sg:address":"Rue Des Peupliers 1",
    "sg:city":"Yverdon-les-bains",
    "sg:orig_category":"Sanit\u00e4r, Heizungs U L\u00fcftungsinstallation",
    "sg:postcode":"1400",
    "sg:province":"Vaud",
    "wof:name":"Bovey Jacques",
    "wof:placetype":"venue"
},
  "geometry": {"coordinates":[6.6365599632,46.7856483459],"type":"Point"}
}