{
  "type": "Feature",
  "properties": {
    "iso:country":"CH",
    "sg:address":"Grubenweg 2",
    "sg:city":"Zuchwil",
    "sg:orig_category":"Glaserei Grosshandel mit keramischen Erzeugnissen, Glaswaren U Reinigungsmitteln",
    "sg:phone":"+41 22 782 08 88",
    "sg:postcode":"4528",
    "sg:province":"Solothurn",
    "wof:name":"Lamelle-glass Sa",
    "wof:placetype":"venue"
},
  "geometry": {"coordinates":[6.0687460899,46.2298469543],"type":"Point"}
}