{
  "type": "Feature",
  "properties": {
    "iso:country":"CH",
    "sg:address":"Z\u00fcrcherstrasse 92",
    "sg:city":"Uznach",
    "sg:classifiers":[
        {
            "category":"Restaurant",
            "type":"Food & Drink"
        }
    ],
    "sg:phone":"+41 55 280 27 81",
    "sg:postcode":"8730",
    "sg:province":"St. Gallen",
    "wof:name":"Restaurant Sch\u00fctzenhaus",
    "wof:placetype":"venue"
},
  "geometry": {"coordinates":[8.9657745361,47.2295951843],"type":"Point"}
}