{
  "type": "Feature",
  "properties": {
    "iso:country":"CH",
    "sg:address":"Chemin De La Baconni\u00e8re 49b",
    "sg:city":"Boudry",
    "sg:classifiers":[
        {
            "category":"Utilities",
            "subcategory":"Telephone",
            "type":"Services"
        }
    ],
    "sg:phone":"+41 32 841 70 30",
    "sg:postcode":"2017",
    "sg:province":"Neuch\u00e2tel",
    "sg:tags":[
        "device",
        "electromechanical",
        "assembly",
        "electronic"
    ],
    "wof:name":"Cavitech",
    "wof:placetype":"venue"
},
  "geometry": {"coordinates":[6.840211,46.95673],"type":"Point"}
}