{
  "type": "Feature",
  "properties": {
    "iso:country":"CH",
    "sg:address":"Birsstrasse 15",
    "sg:city":"Muttenz",
    "sg:orig_category":"Bauspenglerei Sanit\u00e4rinstallation",
    "sg:phone":"+41 71 755 44 70",
    "sg:postcode":"4132",
    "sg:province":"Basel-Landschaft",
    "wof:name":"Scheiwiler Haustechnik Ag",
    "wof:placetype":"venue"
},
  "geometry": {"coordinates":[9.548108,47.376957],"type":"Point"}
}