{
  "type": "Feature",
  "properties": {
    "iso:country":"CH",
    "sg:address":"Jupiterstrasse 4 8032 Z\u00fcrich",
    "sg:city":"Zust",
    "sg:orig_category":"Softwareentwicklung U beratung",
    "sg:phone":"+41 71 944 31 71",
    "sg:postcode":"32",
    "wof:name":"I-2000",
    "wof:placetype":"venue"
},
  "geometry": {"coordinates":[9.0974340439,47.4745903015],"type":"Point"}
}