{
  "type": "Feature",
  "properties": {
    "iso:country":"CH",
    "sg:address":"Seewiesenstrasse 1 9322 Egnach. Postfach",
    "sg:city":"Egnach",
    "sg:orig_category":"Herstellung von Werkzeugmaschinen",
    "sg:phone":"+41 71 477 10 80",
    "sg:postcode":"9322",
    "sg:province":"Thurgau",
    "wof:name":"Cadero High-tech Gmbh Schneiderosion F\u00fcr Formen- U. Werkzeugbau",
    "wof:placetype":"venue"
},
  "geometry": {"coordinates":[9.3733692169,47.547252655],"type":"Point"}
}