{
  "type": "Feature",
  "properties": {
    "iso:country":"CH",
    "sg:address":"Bahnhofstrasse 23",
    "sg:city":"Zug",
    "sg:orig_category":"Datenverarbeitungsdienste",
    "sg:phone":"+41 41 712 06 33",
    "sg:postcode":"6300",
    "sg:province":"Zug",
    "wof:name":"Bcd Wirth Marcel",
    "wof:placetype":"venue"
},
  "geometry": {"coordinates":[8.515671,47.169979],"type":"Point"}
}