{
  "type": "Feature",
  "properties": {
    "iso:country":"CH",
    "sg:address":"Marktgasse 8 4051 Basel. Postfach",
    "sg:city":"Basel",
    "sg:classifiers":[
        {
            "category":"Communications",
            "subcategory":"Radio Station",
            "type":"Services"
        }
    ],
    "sg:phone":"+41 61 261 95 00",
    "sg:postcode":"4001",
    "sg:province":"Basel-Stadt",
    "sg:tags":[
        "fernsehanstalten",
        "u"
    ],
    "wof:name":"Radio Basilisk Betriebs Ag",
    "wof:placetype":"venue"
},
  "geometry": {"coordinates":[7.5872421265,47.5595474243],"type":"Point"}
}