{
  "type": "Feature",
  "properties": {
    "iso:country":"CH",
    "sg:address":"Sous-bois Chemin De 6",
    "sg:city":"Jouxtens-m\u00e9zery",
    "sg:orig_category":"Gartenbau",
    "sg:postcode":"1008",
    "sg:province":"Vaud",
    "wof:name":"P\u00e9pini\u00e8res Thonney",
    "wof:placetype":"venue"
},
  "geometry": {"coordinates":[6.6018710136,46.5501213074],"type":"Point"}
}