{
  "type": "Feature",
  "properties": {
    "iso:country":"CH",
    "sg:address":"Gerlikonerstrasse 19",
    "sg:city":"Frauenfeld",
    "sg:orig_category":"Elektroinstallation",
    "sg:phone":"+41 52 720 37 73",
    "sg:postcode":"8500",
    "sg:province":"Thurgau",
    "wof:name":"Allrounder Pianese",
    "wof:placetype":"venue"
},
  "geometry": {"coordinates":[8.8894681931,47.5507621765],"type":"Point"}
}