{
  "type": "Feature",
  "properties": {
    "iso:country":"CH",
    "sg:address":"Schw\u00e4bismattweg 8 3613 Steffisburg. Postfach",
    "sg:city":"Steffisburg",
    "sg:orig_category":"Herstellung von Elektrizit\u00e4tsverteilungs U schalteinrichtungen Herstellung von sonstigen elektrische",
    "sg:phone":"+41 33 439 65 65",
    "sg:postcode":"3613",
    "sg:province":"Bern",
    "wof:name":"B\u00fcrki Electric Ag",
    "wof:placetype":"venue"
},
  "geometry": {"coordinates":[7.6142678261,46.7676849365],"type":"Point"}
}