{
  "type": "Feature",
  "properties": {
    "iso:country":"CH",
    "sg:address":"Langholzstrasse 30 6330 Cham. Postfach",
    "sg:city":"Cham",
    "sg:orig_category":"Finanzierungsinstitutionen",
    "sg:postcode":"6330",
    "sg:province":"Zug",
    "wof:name":"Transbras Gmbh Finanzdienstleistungen, Verm\u00f6gensverwaltung, Beratungen",
    "wof:placetype":"venue"
},
  "geometry": {"coordinates":[8.4462842941,47.1728515625],"type":"Point"}
}