{
  "type": "Feature",
  "properties": {
    "iso:country":"CH",
    "sg:address":"Champ-bosson 11",
    "sg:city":"Riaz",
    "sg:orig_category":"RESTAURANTS: TEA-ROOMS",
    "sg:phone":"+41 2931025",
    "sg:postcode":"1632",
    "sg:province":"Fribourg",
    "wof:name":"Pittet Jean-claude Sa",
    "wof:placetype":"venue"
},
  "geometry": {"coordinates":[7.0605101585,46.6353607178],"type":"Point"}
}