{
  "type": "Feature",
  "properties": {
    "iso:country":"CH",
    "sg:address":"Ober-emmenweid 38",
    "sg:city":"Emmenbr\u00fccke",
    "sg:orig_category":"Non-Classified Establishments",
    "sg:postcode":"6020",
    "sg:province":"Luzern",
    "wof:name":"Swiss Highlander Gmbh",
    "wof:placetype":"venue"
},
  "geometry": {"coordinates":[8.2657499313,47.0736465454],"type":"Point"}
}