{
  "type": "Feature",
  "properties": {
    "iso:country":"CH",
    "sg:address":"Sch\u00f6nenbergstrasse 3",
    "sg:city":"W\u00e4denswil",
    "sg:orig_category":"Massagestudios",
    "sg:phone":"+41 17807551",
    "sg:postcode":"8820",
    "sg:province":"Z\u00fcrich",
    "wof:name":"Massage-praxis Cellsan",
    "wof:placetype":"venue"
},
  "geometry": {"coordinates":[8.6719732285,47.2291755676],"type":"Point"}
}