{
  "type": "Feature",
  "properties": {
    "iso:country":"CH",
    "sg:address":"Rue De L'epervier 3",
    "sg:city":"Cernier",
    "sg:orig_category":"Detailhandel mit Bekleidung Detailhandel mit Damenbekleidung",
    "sg:phone":"+41 32 487 12 62",
    "sg:postcode":"2053",
    "sg:province":"Neuch\u00e2tel",
    "wof:name":"Boutique Oasis Porret & Piot Confect.dames Hommes Enfants",
    "wof:placetype":"venue"
},
  "geometry": {"coordinates":[6.902262,47.05986],"type":"Point"}
}