{
  "type": "Feature",
  "properties": {
    "iso:country":"CH",
    "sg:address":"Aeschenvorstadt 48 4051 Basel. Postfach",
    "sg:city":"Basel",
    "sg:orig_category":"Kauf U Verkauf von Immobilien auf eigene Rechnung",
    "sg:postcode":"4051",
    "sg:province":"Basel-Stadt",
    "wof:name":"Aarintra Ag Liegenschaften Usw",
    "wof:placetype":"venue"
},
  "geometry": {"coordinates":[7.5934348106,47.552230835],"type":"Point"}
}