{
  "type": "Feature",
  "properties": {
    "iso:country":"CH",
    "sg:address":"1052 Mont-sur-lausanne Case Postale 191",
    "sg:city":"Mont-sur-lausanne",
    "sg:orig_category":"Sportvereine Ballsport Fussball",
    "sg:postcode":"1052",
    "sg:province":"Vaud",
    "wof:name":"Fc Le Noirmont",
    "wof:placetype":"venue"
},
  "geometry": {"coordinates":[6.9572901726,47.2244682312],"type":"Point"}
}