{
  "type": "Feature",
  "properties": {
    "iso:country":"CH",
    "sg:address":"Pelikanstrasse 18 8001 Z\u00fcrich. Postfach",
    "sg:city":"Z\u00fcrich",
    "sg:classifiers":[
        {
            "category":"Education",
            "subcategory":"Library",
            "type":"Public Place"
        }
    ],
    "sg:phone":"+41 12113322",
    "sg:postcode":"8023",
    "sg:province":"Z\u00fcrich",
    "sg:tags":[
        "u",
        "bibliotheken",
        "archive"
    ],
    "wof:name":"Bibliothek Des Kaufm\u00e4nnischen Verbandes",
    "wof:placetype":"venue"
},
  "geometry": {"coordinates":[8.536468,47.371723],"type":"Point"}
}