{
  "type": "Feature",
  "properties": {
    "iso:country":"CH",
    "sg:address":"Stockenstr. 27",
    "sg:city":"Algetshausen",
    "sg:classifiers":[
        {
            "category":"Manufacturing",
            "subcategory":"Motor Vehicles & Parts",
            "type":"Manufacturing & Wholesale Goods"
        }
    ],
    "sg:phone":"+41 71 951 66 22",
    "sg:postcode":"9249",
    "sg:province":"St. Gallen",
    "sg:tags":[
        "engine",
        "machine",
        "engineering",
        "-",
        "mechanical"
    ],
    "wof:name":"Turbal Turbinenbau Ag",
    "wof:placetype":"venue"
},
  "geometry": {"coordinates":[9.1111917496,47.4456748962],"type":"Point"}
}