{
  "type": "Feature",
  "properties": {
    "iso:country":"CH",
    "sg:address":"Nordstrasse 220 8037 Z\u00fcrich. Postfach",
    "sg:city":"Z\u00fcrich",
    "sg:orig_category":"Wirtschaftsverb\u00e4nde Industrie, Handel and Gewerbe",
    "sg:phone":"+41 12721315",
    "sg:postcode":"8037",
    "sg:province":"Z\u00fcrich",
    "wof:name":"Verband F\u00fcr Tank-& Beh\u00e4lter- Schutz Der Schweiz,sekretariat",
    "wof:placetype":"venue"
},
  "geometry": {"coordinates":[8.5292186737,47.3936538696],"type":"Point"}
}