{
  "type": "Feature",
  "properties": {
    "iso:country":"CH",
    "sg:address":"\u00c4lplistrasse 291",
    "sg:city":"Krinau",
    "sg:orig_category":"Kaminfeger",
    "sg:phone":"+41 71 985 06 62",
    "sg:postcode":"9622",
    "sg:province":"St. Gallen",
    "wof:name":"Boris Hunziker Kaminfegermeister",
    "wof:placetype":"venue"
},
  "geometry": {"coordinates":[9.0480146408,47.3175086975],"type":"Point"}
}