{
  "type": "Feature",
  "properties": {
    "iso:country":"CH",
    "sg:address":"Rue De Saint-gu\u00e9rin 4",
    "sg:city":"Sion",
    "sg:orig_category":"Bauingenieurb\u00fcros allgemein",
    "sg:phone":"+41 27 322 52 62",
    "sg:postcode":"1950",
    "sg:province":"Valais",
    "wof:name":"Jean-pierre Berthouzoz Bureau D'ing\u00e9nieur",
    "wof:placetype":"venue"
},
  "geometry": {"coordinates":[7.34822,46.230629],"type":"Point"}
}