{
  "type": "Feature",
  "properties": {
    "iso:country":"CH",
    "sg:address":"Oberdorfstrasse 6",
    "sg:city":"H\u00fcttwilen",
    "sg:orig_category":"Aktivit\u00e4ten der Krankenschwestern U Hebammen, Hauspflege",
    "sg:phone":"+41 52 747 17 25",
    "sg:postcode":"8536",
    "sg:province":"Thurgau",
    "wof:name":"Spitex-dienste Seebachtal M.foglia",
    "wof:placetype":"venue"
},
  "geometry": {"coordinates":[8.868929,47.611069],"type":"Point"}
}