{
  "type": "Feature",
  "properties": {
    "addr:full":"Grossackerstr. 36 Glattbrugg Z\u00fcrich 8152",
    "addr:housenumber":"36",
    "addr:postcode":"8152",
    "addr:street":"Grossackerstr.",
    "iso:country":"CH",
    "sg:address":"Grossackerstr. 36",
    "sg:city":"Glattbrugg",
    "sg:orig_category":"Detailhandel mit Antiquit\u00e4ten U Gebrauchtwaren in Verkaufsr\u00e4umen",
    "sg:phone":"+41 18102921",
    "sg:postcode":"8152",
    "sg:province":"Z\u00fcrich",
    "wof:name":"Eresa Trade, Theresia L\u00f6tscher-iten",
    "wof:placetype":"venue"
},
  "geometry": {"coordinates":[8.57401,47.429298],"type":"Point"}
}