{
  "type": "Feature",
  "properties": {
    "iso:country":"CH",
    "sg:address":"G\u00f6ldistrasse 19",
    "sg:city":"Richterswil",
    "sg:orig_category":"Bezirks, Sekundar, Realschulen, Oberstufe der Primarschulen",
    "sg:phone":"+41 12922902",
    "sg:postcode":"8805",
    "sg:province":"Z\u00fcrich",
    "wof:name":"Oberstufenschule Breite",
    "wof:placetype":"venue"
},
  "geometry": {"coordinates":[8.721765,47.269909],"type":"Point"}
}