{
  "type": "Feature",
  "properties": {
    "iso:country":"CH",
    "sg:address":"Cebbia",
    "sg:city":"Mesocco",
    "sg:orig_category":"Bauschreinerei Herstellung von M\u00f6beln verschiedener Art",
    "sg:phone":"+41 52 385 14 54",
    "sg:postcode":"6563",
    "sg:province":"Graubunden",
    "wof:name":"Furrer Ag Schreinerei",
    "wof:placetype":"venue"
},
  "geometry": {"coordinates":[8.847827,47.418835],"type":"Point"}
}