{
  "type": "Feature",
  "properties": {
    "iso:country":"CH",
    "sg:address":"6162",
    "sg:city":"Entlebuch",
    "sg:orig_category":"Grosshandel mit lebenden Tieren",
    "sg:phone":"+41 79 642 26 72",
    "sg:postcode":"6162",
    "sg:province":"Luzern",
    "wof:name":"Roth Gebr. Schweinehandel.",
    "wof:placetype":"venue"
},
  "geometry": {"coordinates":[8.0649986267,46.9928016663],"type":"Point"}
}