{
  "type": "Feature",
  "properties": {
    "iso:country":"CH",
    "sg:address":"Limmattalstrasse 211",
    "sg:city":"Z\u00fcrich",
    "sg:orig_category":"Elektroinstallation",
    "sg:phone":"+41 81 750 61 61",
    "sg:postcode":"8049",
    "sg:province":"Z\u00fcrich",
    "wof:name":"Marquart Elektroplanung + Beratung Ag",
    "wof:placetype":"venue"
},
  "geometry": {"coordinates":[9.4816951752,47.1518211365],"type":"Point"}
}