{
  "type": "Feature",
  "properties": {
    "iso:country":"CH",
    "sg:address":"Gubelstrasse 22",
    "sg:city":"Zug",
    "sg:orig_category":"Wirtschaftspr\u00fcfung, Steuerberatung U Treuhand",
    "sg:phone":"+41 19323405",
    "sg:postcode":"6300",
    "sg:province":"Zug",
    "wof:name":"Kellenberger Ag",
    "wof:placetype":"venue"
},
  "geometry": {"coordinates":[8.7857513428,47.3250007629],"type":"Point"}
}