{
  "type": "Feature",
  "properties": {
    "iso:country":"CH",
    "sg:address":"Drahtzugstrasse 14 4057 Basel. Postfach 1104",
    "sg:city":"Basel",
    "sg:orig_category":"Sportvereine Ballsport Fussball",
    "sg:phone":"+41 61 692 45 58",
    "sg:postcode":"4001",
    "sg:province":"Basel-Stadt",
    "wof:name":"Bsc Olympia Basel",
    "wof:placetype":"venue"
},
  "geometry": {"coordinates":[7.5947108269,47.5629463196],"type":"Point"}
}