{
  "type": "Feature",
  "properties": {
    "iso:country":"CH",
    "sg:address":"Via Zorzi 29",
    "sg:city":"Paradiso",
    "sg:orig_category":"Handelsvermittlung U Grosshandel",
    "sg:phone":"+41 19322020",
    "sg:postcode":"6900",
    "sg:province":"Ticino",
    "wof:name":"Engel & Co Technische Erzeugnisse",
    "wof:placetype":"venue"
},
  "geometry": {"coordinates":[8.7942695618,47.3143997192],"type":"Point"}
}