{
  "type": "Feature",
  "properties": {
    "iso:country":"CH",
    "sg:address":"Buechweid",
    "sg:city":"Berom\u00fcnster",
    "sg:orig_category":"Allgemeiner Hoch U Tiefbau",
    "sg:postcode":"6215",
    "sg:province":"Luzern",
    "wof:name":"Krasniqi Ali",
    "wof:placetype":"venue"
},
  "geometry": {"coordinates":[8.262522,47.349606],"type":"Point"}
}