{
  "type": "Feature",
  "properties": {
    "iso:country":"CH",
    "sg:address":"6952",
    "sg:city":"Canobbio",
    "sg:orig_category":"Allgemeiner Hoch U Tiefbau Allgemeiner Hochbau",
    "sg:phone":"+41 91 940 41 40",
    "sg:postcode":"6952",
    "sg:province":"Ticino",
    "wof:name":"Pescia Luciano.",
    "wof:placetype":"venue"
},
  "geometry": {"coordinates":[8.96873,46.036221],"type":"Point"}
}