{
  "type": "Feature",
  "properties": {
    "iso:country":"CH",
    "sg:address":"R\u00f6hrliberg 14a",
    "sg:city":"Cham",
    "sg:orig_category":"RESTAURANTS: TEA-ROOMS",
    "sg:postcode":"6330",
    "sg:province":"Zug",
    "wof:name":"Lanna Thai Gmbh",
    "wof:placetype":"venue"
},
  "geometry": {"coordinates":[8.4528369904,47.1861495972],"type":"Point"}
}