{
  "type": "Feature",
  "properties": {
    "iso:country":"CH",
    "sg:address":"Keramikweg 11",
    "sg:city":"Ebikon",
    "sg:orig_category":"Erschliessung von Grundst\u00fccken",
    "sg:phone":"+41 41 420 14 14",
    "sg:postcode":"6030",
    "sg:province":"Luzern",
    "wof:name":"Gfwl Genossenschaft Zur F\u00f6rderung Des Wohneigentums",
    "wof:placetype":"venue"
},
  "geometry": {"coordinates":[8.3188648224,47.0684928894],"type":"Point"}
}