{
  "type": "Feature",
  "properties": {
    "iso:country":"CH",
    "sg:address":"Hauptstrasse",
    "sg:city":"Zernez",
    "sg:orig_category":"Architektur U Ingenieurb\u00fcros Architekturb\u00fcros",
    "sg:phone":"+41 81 856 16 88",
    "sg:postcode":"7530",
    "sg:province":"Graubunden",
    "wof:name":"Ida Fancoli Architekturb\u00fcro",
    "wof:placetype":"venue"
},
  "geometry": {"coordinates":[10.09463,46.700298],"type":"Point"}
}