{
  "type": "Feature",
  "properties": {
    "iso:country":"CH",
    "sg:address":"Turnhallenweg 8",
    "sg:city":"M\u00fcnsingen",
    "sg:orig_category":"Bezirks, Sekundar, Realschulen, Oberstufe der Primarschulen",
    "sg:phone":"+41 31 721 39 74",
    "sg:postcode":"3110",
    "sg:province":"Bern",
    "wof:name":"Sekundarschule Rebacker",
    "wof:placetype":"venue"
},
  "geometry": {"coordinates":[7.563855,46.877659],"type":"Point"}
}