{
  "type": "Feature",
  "properties": {
    "iso:country":"CH",
    "sg:address":"Casa Pitsch",
    "sg:city":"Arosa",
    "sg:orig_category":"Sonstiger Grosshandel",
    "sg:postcode":"7050",
    "sg:province":"Graubunden",
    "wof:name":"Sexy Blondie Wagner-zappa Laetitia",
    "wof:placetype":"venue"
},
  "geometry": {"coordinates":[9.6765518188,46.7778625488],"type":"Point"}
}