{
  "type": "Feature",
  "properties": {
    "iso:country":"CH",
    "sg:address":"Hinterdorf 52",
    "sg:city":"Barzheim",
    "sg:orig_category":"Malerei Verlegen von Fliesen U Platten",
    "sg:phone":"+41 52 625 74 93",
    "sg:postcode":"8241",
    "sg:province":"Schaffhausen",
    "wof:name":"Walter Hahn Malergesch\u00e4ft",
    "wof:placetype":"venue"
},
  "geometry": {"coordinates":[8.7198801041,47.7598381042],"type":"Point"}
}