{
  "type": "Feature",
  "properties": {
    "iso:country":"CH",
    "sg:address":"Industriestrasse 11",
    "sg:city":"Chur",
    "sg:orig_category":"Anticorrosives",
    "sg:phone":"+41 81 284 76 79",
    "sg:postcode":"7000",
    "sg:province":"Graubunden",
    "wof:name":"Erwin Turnell Korrosionsschutz",
    "wof:placetype":"venue"
},
  "geometry": {"coordinates":[9.50994,46.85614],"type":"Point"}
}