{
  "type": "Feature",
  "properties": {
    "iso:country":"CH",
    "sg:address":"Drahtzugstrasse 17",
    "sg:city":"Z\u00fcrich",
    "sg:orig_category":"Architekturb\u00fcros",
    "sg:phone":"+41 13812220",
    "sg:postcode":"8008",
    "sg:province":"Z\u00fcrich",
    "wof:name":"Wolfgang Ruehrl Architekturb\u00fcro",
    "wof:placetype":"venue"
},
  "geometry": {"coordinates":[8.56124,47.360775],"type":"Point"}
}