{
  "type": "Feature",
  "properties": {
    "iso:country":"CH",
    "sg:address":"Dachslenbergstrasse 57",
    "sg:city":"B\u00fclach",
    "sg:orig_category":"Unternehmensberatung",
    "sg:phone":"+41 87889020",
    "sg:postcode":"8180",
    "sg:province":"Z\u00fcrich",
    "wof:name":"Cmc Roost Dr. Jakob & Partners Change Management And Communication",
    "wof:placetype":"venue"
},
  "geometry": {"coordinates":[8.5495882034,47.5270080566],"type":"Point"}
}