{
  "type": "Feature",
  "properties": {
    "iso:country":"CH",
    "sg:address":"Kasernenstrasse 39",
    "sg:city":"Herisau",
    "sg:orig_category":"Architektur U Ingenieurb\u00fcros",
    "sg:phone":"+41 71 227 62 62",
    "sg:postcode":"9100",
    "sg:province":"Appenzell Ausserrhoden",
    "wof:name":"Eigenmann, Rey, Rietmann; Raumplaner Bsp",
    "wof:placetype":"venue"
},
  "geometry": {"coordinates":[9.285271,47.387596],"type":"Point"}
}