{
  "type": "Feature",
  "properties": {
    "iso:country":"CH",
    "sg:address":"2043",
    "sg:city":"Boudevilliers",
    "sg:orig_category":"Verwertung von Milch",
    "sg:postcode":"2043",
    "sg:province":"Neuch\u00e2tel",
    "wof:name":"Soci\u00e9t\u00e9 De Laiterie De Boudevilliers",
    "wof:placetype":"venue"
},
  "geometry": {"coordinates":[6.889480114,47.0277748108],"type":"Point"}
}