{
  "type": "Feature",
  "properties": {
    "iso:country":"CH",
    "sg:address":"Obere B\u00fcelhalde 5",
    "sg:city":"Merenschwand",
    "sg:orig_category":"Unternehmensberatung",
    "sg:postcode":"5634",
    "sg:province":"Aargau",
    "wof:name":"M\u00fcller Management Consulting",
    "wof:placetype":"venue"
},
  "geometry": {"coordinates":[8.3733463287,47.2563858032],"type":"Point"}
}