{
  "type": "Feature",
  "properties": {
    "iso:country":"CH",
    "sg:address":"Haslen 8833 Samstagern. Postfach",
    "sg:city":"Samstagern",
    "sg:orig_category":"Abfallbeseitigung Abwasserreinigung, Abfallbeseitigung U sonstige Entsorgung",
    "sg:phone":"+41 32 843 82 11",
    "sg:postcode":"8833",
    "sg:province":"Z\u00fcrich",
    "wof:name":"Sa Pour L'incin\u00e9ration Des Ordures Et D\u00e9chets",
    "wof:placetype":"venue"
},
  "geometry": {"coordinates":[6.848414,46.972538],"type":"Point"}
}