{
  "type": "Feature",
  "properties": {
    "iso:country":"CH",
    "sg:address":"Route Des Fayards 60 1239 Collex Case Postale 60",
    "sg:city":"Collex",
    "sg:orig_category":"Grosshandel mit medizinischen U orthop\u00e4dischen Artikeln Herstellung von medizinischen U chirurgische",
    "sg:phone":"+41 22 774 11 55",
    "sg:postcode":"1239",
    "sg:province":"Gen\u00e8ve",
    "wof:name":"Umm Unit\u00e9s M\u00e9dicales Mobiles Sa",
    "wof:placetype":"venue"
},
  "geometry": {"coordinates":[6.12508,46.27224],"type":"Point"}
}