{
  "type": "Feature",
  "properties": {
    "iso:country":"CH",
    "sg:address":"En Fouet",
    "sg:city":"Chamblon",
    "sg:orig_category":"Werbevermittlung",
    "sg:phone":"+41 24 445 15 18",
    "sg:postcode":"1436",
    "sg:province":"Vaud",
    "wof:name":"Troquet Adverteam R\u00e9alisations Publicitaires",
    "wof:placetype":"venue"
},
  "geometry": {"coordinates":[6.6073760986,46.781452179],"type":"Point"}
}