{
  "type": "Feature",
  "properties": {
    "iso:country":"CH",
    "sg:address":"Quai Du Bas 37",
    "sg:city":"Biel/bienne",
    "sg:orig_category":"RESTAURANTS: TEA-ROOMS",
    "sg:phone":"+41 32 323 86 66",
    "sg:postcode":"2500",
    "sg:province":"Bern",
    "wof:name":"Ohayon Albert",
    "wof:placetype":"venue"
},
  "geometry": {"coordinates":[7.2449522018,47.1366195679],"type":"Point"}
}