{
  "type": "Feature",
  "properties": {
    "iso:country":"CH",
    "sg:address":"Rue Du Centre 29",
    "sg:city":"Crissier",
    "sg:orig_category":"G\u00fcterbef\u00f6rderung im Strassenverkehr",
    "sg:phone":"+41 79 213 96 07",
    "sg:postcode":"1023",
    "sg:province":"Vaud",
    "wof:name":"Transports Richard Fr\u00e8res.",
    "wof:placetype":"venue"
},
  "geometry": {"coordinates":[6.5792369843,46.5507888794],"type":"Point"}
}