{
  "type": "Feature",
  "properties": {
    "iso:country":"CH",
    "sg:address":"Richtistrasse 12",
    "sg:city":"Wallisellen",
    "sg:orig_category":"Reiseb\u00fcros U Reiseveranstalter",
    "sg:phone":"+41 22 731 53 16",
    "sg:postcode":"8304",
    "sg:province":"Z\u00fcrich",
    "wof:name":"Mica Travel, Isabelle Gajardo",
    "wof:placetype":"venue"
},
  "geometry": {"coordinates":[6.1414489746,46.2063751221],"type":"Point"}
}