{
  "type": "Feature",
  "properties": {
    "iso:country":"CH",
    "sg:address":"Rue Des Jardins 18 2500 Biel/bienne. Postfach",
    "sg:city":"Biel/bienne",
    "sg:orig_category":"Handels-H\u00e4user U Gesellschaften",
    "sg:postcode":"2503",
    "sg:province":"Bern",
    "wof:name":"Choffat Jean-pierre",
    "wof:placetype":"venue"
},
  "geometry": {"coordinates":[7.2486171722,47.137550354],"type":"Point"}
}