{
  "type": "Feature",
  "properties": {
    "iso:country":"CH",
    "sg:address":"Riedstrasse 7",
    "sg:city":"Cham",
    "sg:orig_category":"Grosshandel mit sonstigen Maschinen U Ausr\u00fcstungen f\u00fcr Industrie, Handel U Schiffahrt",
    "sg:phone":"+41 41 741 78 78",
    "sg:postcode":"6330",
    "sg:province":"Zug",
    "wof:name":"Abel-technik, Brugger Rosemarie",
    "wof:placetype":"venue"
},
  "geometry": {"coordinates":[8.4766769409,47.1891326904],"type":"Point"}
}