{
  "type": "Feature",
  "properties": {
    "iso:country":"CH",
    "sg:address":"Edikerstrasse 22a",
    "sg:city":"D\u00fcrnten",
    "sg:orig_category":"S\u00e4ge, Hobel U Holzimpr\u00e4gnierwerke S\u00e4gewerke",
    "sg:phone":"+41 55 240 22 54",
    "sg:postcode":"8635",
    "sg:province":"Z\u00fcrich",
    "wof:name":"Bleuler Karl Ag",
    "wof:placetype":"venue"
},
  "geometry": {"coordinates":[8.8435993195,47.2849998474],"type":"Point"}
}