{
  "type": "Feature",
  "properties": {
    "iso:country":"CH",
    "sg:address":"Wilfriedstrasse 12 8032 Z\u00fcrich 32 Zust. Postfach 8032 Z\u00fcrich",
    "sg:city":"Zust",
    "sg:orig_category":"Wirtschaftspr\u00fcfung, Steuerberatung U Treuhand",
    "sg:postcode":"32",
    "wof:name":"M\u00fcrner Liselotte",
    "wof:placetype":"venue"
},
  "geometry": {"coordinates":[7.6936101913,46.6225547791],"type":"Point"}
}