{
  "type": "Feature",
  "properties": {
    "iso:country":"CH",
    "sg:address":"In Der Luberzen 25 8902 Urdorf. Postfach",
    "sg:city":"Urdorf",
    "sg:orig_category":"Grosshandel mit Schreibwaren, B\u00fcchern U Zeitungen",
    "sg:phone":"+41 17361030",
    "sg:postcode":"8902",
    "sg:province":"Z\u00fcrich",
    "wof:name":"Gu-print Ag Generaluntern.f\u00fcr Printmedien",
    "wof:placetype":"venue"
},
  "geometry": {"coordinates":[8.4242534637,47.3941612244],"type":"Point"}
}