{
  "type": "Feature",
  "properties": {
    "iso:country":"CH",
    "sg:address":"Chemin Des Finages 4",
    "sg:city":"Del\u00e9mont",
    "sg:orig_category":"Elektroinstallation",
    "sg:phone":"+41 27 722 21 71",
    "sg:postcode":"2800",
    "sg:province":"Jura",
    "wof:name":"Bruchez Sa Installations \u00e9lectriques",
    "wof:placetype":"venue"
},
  "geometry": {"coordinates":[7.0688090324,46.0969924927],"type":"Point"}
}