{
  "type": "Feature",
  "properties": {
    "iso:country":"CH",
    "sg:address":"3718",
    "sg:city":"Kandersteg",
    "sg:orig_category":"Gemeindeverwaltungen",
    "sg:phone":"+41 17641130",
    "sg:postcode":"3718",
    "sg:province":"Bern",
    "wof:name":"Gemeindeverwaltung Kappel Am Albis",
    "wof:placetype":"venue"
},
  "geometry": {"coordinates":[8.5244445801,47.2287712097],"type":"Point"}
}