{
  "type": "Feature",
  "properties": {
    "iso:country":"CH",
    "sg:address":"Chemin Des Bocages 3",
    "sg:city":"Delsberg",
    "sg:orig_category":"Erwachsenenbildung U Unterricht",
    "sg:postcode":"2800",
    "sg:province":"Jura",
    "wof:name":"Lll S\u00e0rl",
    "wof:placetype":"venue"
},
  "geometry": {"coordinates":[7.3557648659,47.3746452332],"type":"Point"}
}