{
  "type": "Feature",
  "properties": {
    "iso:country":"CH",
    "sg:address":"Chemin De La Tuliere 1",
    "sg:city":"Mont-sur-lausanne",
    "sg:orig_category":"Instandhaltung U Reparatur von Automobilen",
    "sg:phone":"+41 21 646 43 45",
    "sg:postcode":"1052",
    "sg:province":"Vaud",
    "wof:name":"Procomteur Sa Auto-\u00e9lectricit\u00e9",
    "wof:placetype":"venue"
},
  "geometry": {"coordinates":[6.625690937,46.5450706482],"type":"Point"}
}