{
  "type": "Feature",
  "properties": {
    "iso:country":"CH",
    "sg:address":"Martinstrasse 10 8854 Galgenen. Postfach",
    "sg:city":"Siebnen",
    "sg:orig_category":"Detailhandel mit Fleisch U Fleischwaren",
    "sg:phone":"+41 55 440 15 79",
    "sg:postcode":"8854",
    "sg:province":"Schwyz",
    "wof:name":"Ernst Rickenbach, Metzgerei Und Wursterei",
    "wof:placetype":"venue"
},
  "geometry": {"coordinates":[8.874835968,47.180973053],"type":"Point"}
}