{
  "type": "Feature",
  "properties": {
    "iso:country":"CH",
    "sg:address":"Dorfstr. 1420 Zweidlen",
    "sg:city":"Glattfelden",
    "sg:orig_category":"Herstellung von Schreibwaren U B\u00fcrobedarf aus Papier, Karton U Pappe",
    "sg:postcode":"8192",
    "sg:province":"Z\u00fcrich",
    "wof:name":"Fabrikoop, Kooperative Fabrik Glattfelden",
    "wof:placetype":"venue"
},
  "geometry": {"coordinates":[8.5024900436,47.55884552],"type":"Point"}
}