{
  "type": "Feature",
  "properties": {
    "iso:country":"CH",
    "sg:address":"4415",
    "sg:city":"Lausen",
    "sg:orig_category":"Vereine Vogel-& Naturschutz",
    "sg:postcode":"4415",
    "sg:province":"Basel-Landschaft",
    "wof:name":"Vogelschutzverein",
    "wof:placetype":"venue"
},
  "geometry": {"coordinates":[7.7655301094,47.4701957703],"type":"Point"}
}