{
  "type": "Feature",
  "properties": {
    "iso:country":"CH",
    "sg:address":"Unterdorf 35",
    "sg:city":"Lauperswil",
    "sg:orig_category":"Malerei",
    "sg:phone":"+41 34 496 81 71",
    "sg:postcode":"3438",
    "sg:province":"Bern",
    "wof:name":"Ulrich Fl\u00fckiger Malergesch\u00e4ft",
    "wof:placetype":"venue"
},
  "geometry": {"coordinates":[7.7434978485,46.9674987793],"type":"Point"}
}