{
  "type": "Feature",
  "properties": {
    "iso:country":"CH",
    "sg:address":"Campingstrasse 3",
    "sg:city":"B\u00f6nigen",
    "sg:orig_category":"Detailhandel mit Geschenkartikeln U Souvenirs",
    "sg:phone":"+41 33 822 47 39",
    "sg:postcode":"3806",
    "sg:province":"Bern",
    "wof:name":"Boutique Pinte Lily M\u00f6hl",
    "wof:placetype":"venue"
},
  "geometry": {"coordinates":[7.8935809135,46.6902809143],"type":"Point"}
}