{
  "type": "Feature",
  "properties": {
    "iso:country":"CH",
    "sg:address":"Ziegeleistrasse 2 4614 H\u00e4gendorf. Postfach",
    "sg:city":"H\u00e4gendorf",
    "sg:orig_category":"Grosshandel mit Baumaterialien Grosshandel mit Holz U Baustoffen",
    "sg:phone":"+41 62 209 55 00",
    "sg:postcode":"4614",
    "sg:province":"Solothurn",
    "wof:name":"Bmh Baumaterial H\u00e4gendorf Ag",
    "wof:placetype":"venue"
},
  "geometry": {"coordinates":[7.8511347771,47.3361778259],"type":"Point"}
}