{
  "type": "Feature",
  "properties": {
    "iso:country":"CH",
    "sg:address":"Dorfstrasse 12",
    "sg:city":"R\u00fcschlikon",
    "sg:orig_category":"Architekturb\u00fcros",
    "sg:phone":"+41 13443030",
    "sg:postcode":"8803",
    "sg:province":"Z\u00fcrich",
    "wof:name":"Urs M. Weidmann Architekturb\u00fcro",
    "wof:placetype":"venue"
},
  "geometry": {"coordinates":[8.557278,47.309597],"type":"Point"}
}