{
  "type": "Feature",
  "properties": {
    "iso:country":"CH",
    "sg:address":"Mattenweg 5",
    "sg:city":"Goldach",
    "sg:orig_category":"Non-Classified Establishments",
    "sg:postcode":"9403",
    "sg:province":"St. Gallen",
    "wof:name":"Atweb Web Solutions Ben Hamida & Sigrist",
    "wof:placetype":"venue"
},
  "geometry": {"coordinates":[9.4702568054,47.4684829712],"type":"Point"}
}