{
  "type": "Feature",
  "properties": {
    "iso:country":"CH",
    "sg:address":"Thunstrasse 3",
    "sg:city":"M\u00fcnsingen",
    "sg:classifiers":[
        {
            "category":"Bars & Pubs",
            "type":"Food & Drink"
        }
    ],
    "sg:phone":"+41 31 721 64 10",
    "sg:postcode":"3110",
    "sg:province":"Bern",
    "wof:name":"Caf\u00e9 Sport",
    "wof:placetype":"venue"
},
  "geometry": {"coordinates":[7.562583,46.873634],"type":"Point"}
}