{
  "type": "Feature",
  "properties": {
    "iso:country":"CH",
    "sg:address":"Alte Badenerstrasse 9",
    "sg:city":"Neerach",
    "sg:orig_category":"Softwareentwicklung U beratung",
    "sg:phone":"+41 18581017",
    "sg:postcode":"8173",
    "sg:province":"Z\u00fcrich",
    "wof:name":"S.f.g. Gmbh",
    "wof:placetype":"venue"
},
  "geometry": {"coordinates":[8.4678764343,47.5109176636],"type":"Point"}
}