{
  "type": "Feature",
  "properties": {
    "iso:country":"CH",
    "sg:address":"Wydenm\u00f6slistrasse 20 8280 Kreuzlingen. Postfach 69",
    "sg:city":"Kreuzlingen",
    "sg:orig_category":"Unternehmensberatung",
    "sg:phone":"+41 71 686 58 88",
    "sg:postcode":"8280",
    "sg:province":"Thurgau",
    "wof:name":"Luchsinger & Partner Wirtschaftsberatung",
    "wof:placetype":"venue"
},
  "geometry": {"coordinates":[9.1834068298,47.6360282898],"type":"Point"}
}