{
  "type": "Feature",
  "properties": {
    "iso:country":"CH",
    "sg:address":"Holzmattstrasse 45",
    "sg:city":"Binningen",
    "sg:orig_category":"Wirtschaftspr\u00fcfung, Steuerberatung U Treuhand",
    "sg:phone":"+41 61 301 38 44",
    "sg:postcode":"4102",
    "sg:province":"Basel-Landschaft",
    "wof:name":"Lehmann P. Treuhand",
    "wof:placetype":"venue"
},
  "geometry": {"coordinates":[7.55473423,47.5422134399],"type":"Point"}
}