{
  "type": "Feature",
  "properties": {
    "iso:country":"CH",
    "sg:address":"Route De Gen\u00e8ve 14",
    "sg:city":"Pr\u00e9verenges",
    "sg:orig_category":"Softwareentwicklung U beratung",
    "sg:phone":"+41 21 802 50 11",
    "sg:postcode":"1028",
    "sg:province":"Vaud",
    "wof:name":"Roch Michel Informatique",
    "wof:placetype":"venue"
},
  "geometry": {"coordinates":[6.5186800957,46.5177307129],"type":"Point"}
}