{
  "type": "Feature",
  "properties": {
    "iso:country":"CH",
    "sg:address":"Belpstrasse 6 3113 Rubigen. Postfach 171",
    "sg:city":"Rubigen",
    "sg:orig_category":"Bauschreinerei Herstellung von Konstruktionsteilen, Fertigbauteilen U Ausbauelementen aus Holz",
    "sg:phone":"+41 26 418 12 53",
    "sg:postcode":"3113",
    "sg:province":"Bern",
    "wof:name":"Reinhard Kolly Schreinerei & Holzbau",
    "wof:placetype":"venue"
},
  "geometry": {"coordinates":[7.219154,46.739922],"type":"Point"}
}