{
  "type": "Feature",
  "properties": {
    "iso:country":"CH",
    "sg:address":"Via Luigi Lavizzari 19a",
    "sg:city":"Mendrisio",
    "sg:classifiers":[
        {
            "category":"Insurance",
            "subcategory":"Insurance Agent",
            "type":"Services"
        }
    ],
    "sg:phone":"+41 32 841 33 00",
    "sg:postcode":"6850",
    "sg:province":"Ticino",
    "sg:tags":[
        "versicherungsagenturen",
        "-broker"
    ],
    "wof:name":"Assidu Sa, Succursale Di Lugano Rami Assicurativi, Prodotti Finanziari; Amministrazione, Vendita Ecc",
    "wof:placetype":"venue"
},
  "geometry": {"coordinates":[6.8597660065,46.9691162109],"type":"Point"}
}