{
  "type": "Feature",
  "properties": {
    "iso:country":"CH",
    "sg:address":"Reichsgasse 10",
    "sg:city":"Chur",
    "sg:orig_category":"Unternehmensberatung",
    "sg:postcode":"7000",
    "sg:province":"Graubunden",
    "wof:name":"La Bella Consulting",
    "wof:placetype":"venue"
},
  "geometry": {"coordinates":[9.5339040756,46.8511543274],"type":"Point"}
}