{
  "type": "Feature",
  "properties": {
    "iso:country":"CH",
    "sg:address":"Affolternstrasse 52 8050 Oerlikon. Postfach",
    "sg:city":"Oerlikon",
    "sg:orig_category":"Elektroinstallation",
    "sg:phone":"+41 13107151",
    "sg:postcode":"8050",
    "sg:province":"Z\u00fcrich",
    "wof:name":"Eltra Gmbh",
    "wof:placetype":"venue"
},
  "geometry": {"coordinates":[8.5558795929,47.4107589722],"type":"Point"}
}