{
  "type": "Feature",
  "properties": {
    "addr:full":"Burgdorf Bern 3400",
    "addr:postcode":"3400",
    "iso:country":"CH",
    "sg:city":"Burgdorf",
    "sg:orig_category":"Freizeit, Sport",
    "sg:postcode":"3400",
    "sg:province":"Bern",
    "wof:name":"Reitzentrum Emme Gmbh",
    "wof:placetype":"venue"
},
  "geometry": {"coordinates":[7.624515,47.054844],"type":"Point"}
}