{
  "type": "Feature",
  "properties": {
    "iso:country":"CH",
    "sg:address":"Route De Sauverny 6",
    "sg:city":"Versoix",
    "sg:orig_category":"Werbung",
    "sg:phone":"+41 32 721 17 54",
    "sg:postcode":"1290",
    "sg:province":"Gen\u00e8ve",
    "wof:name":"Objectif Lune Sarl Courtage Publicitaire Et D'information Etc",
    "wof:placetype":"venue"
},
  "geometry": {"coordinates":[6.1648240089,46.2838439941],"type":"Point"}
}