{
  "type": "Feature",
  "properties": {
    "iso:country":"CH",
    "sg:address":"M\u00fchlehofstrasse 1 6260 Reiden. Postfach",
    "sg:city":"Reiden",
    "sg:orig_category":"Allgemeiner Hochbau Br\u00fcckenbau",
    "sg:phone":"+41 62 758 17 77",
    "sg:postcode":"6260",
    "sg:province":"Luzern",
    "wof:name":"Bau-ag Hoch-& Tiefbau",
    "wof:placetype":"venue"
},
  "geometry": {"coordinates":[7.968946,47.240498],"type":"Point"}
}