{
  "type": "Feature",
  "properties": {
    "iso:country":"CH",
    "sg:address":"Sonnengartenstrasse 53",
    "sg:city":"Zollikerberg",
    "sg:orig_category":"Fahrschulen, Flugschulen",
    "sg:phone":"+41 61 311 06 13",
    "sg:postcode":"8125",
    "sg:province":"Z\u00fcrich",
    "wof:name":"Andr\u00e9 Holzer Ring Autofahrschule",
    "wof:placetype":"venue"
},
  "geometry": {"coordinates":[7.5180668831,47.5080451965],"type":"Point"}
}