{
  "type": "Feature",
  "properties": {
    "iso:country":"CH",
    "sg:address":"Hofwiesenstrasse 6 8057 Z\u00fcrich. Postfach",
    "sg:city":"Z\u00fcrich",
    "sg:orig_category":"Aktivit\u00e4ten der Krankenschwestern U Hebammen, Hauspflege Gesundheitswesen",
    "sg:phone":"+41 13626633",
    "sg:postcode":"8057",
    "sg:province":"Z\u00fcrich",
    "wof:name":"Ambulante Krankenpflege Csida Helga",
    "wof:placetype":"venue"
},
  "geometry": {"coordinates":[8.538509,47.392059],"type":"Point"}
}