{
  "type": "Feature",
  "properties": {
    "iso:country":"CH",
    "sg:address":"Fabrikstrasse 8 8370 Sirnach. Postfach",
    "sg:city":"Sirnach",
    "sg:orig_category":"Fachdetailhandel in Verkaufsr\u00e4umen",
    "sg:postcode":"8370",
    "sg:province":"Thurgau",
    "wof:name":"Pso Gmbh Sportartikel; Handel, Herstellung Usw",
    "wof:placetype":"venue"
},
  "geometry": {"coordinates":[8.9919481277,47.4625587463],"type":"Point"}
}