{
  "type": "Feature",
  "properties": {
    "iso:country":"CH",
    "sg:address":"Hinterweg 14",
    "sg:city":"Therwil",
    "sg:orig_category":"Architektur U Ingenieurb\u00fcros Architekturb\u00fcros",
    "sg:phone":"+41 61 721 88 81",
    "sg:postcode":"4106",
    "sg:province":"Basel-Landschaft",
    "wof:name":"Degen Hettenbach, Hettenbach-degen, M\u00fcller Gygax",
    "wof:placetype":"venue"
},
  "geometry": {"coordinates":[7.555104,47.500175],"type":"Point"}
}