{
  "type": "Feature",
  "properties": {
    "iso:country":"CH",
    "sg:address":"Schlossstrasse 67 8207 Schaffhausen. Postfach",
    "sg:city":"Schaffhausen",
    "sg:orig_category":"Detailhandel mit M\u00f6beln U Haushaltsgegenst\u00e4nden Detailhandel mit Textilien",
    "sg:phone":"+41 52 643 22 25",
    "sg:postcode":"8207",
    "sg:province":"Schaffhausen",
    "wof:name":"Casaswiss M\u00f6bel Collection Gmbh M\u00f6bel, Polsterm\u00f6bel, Teppiche, Vorh\u00e4nge Usw.; Verkauf",
    "wof:placetype":"venue"
},
  "geometry": {"coordinates":[8.6618204117,47.7266769409],"type":"Point"}
}