{
  "type": "Feature",
  "properties": {
    "iso:country":"CH",
    "sg:address":"Im Dorf 11",
    "sg:city":"Thun",
    "sg:orig_category":"Primarschulen",
    "sg:phone":"+41 33 336 22 51",
    "sg:postcode":"3608",
    "sg:province":"Bern",
    "wof:name":"Primarschule Allmendingen",
    "wof:placetype":"venue"
},
  "geometry": {"coordinates":[7.5960621834,46.7425003052],"type":"Point"}
}