{
  "type": "Feature",
  "properties": {
    "addr:full":"Gotthardstrasse 27 Oberarth Schwyz 6414",
    "addr:housenumber":"27",
    "addr:postcode":"6414",
    "addr:street":"Gotthardstrasse;Schwyz",
    "iso:country":"CH",
    "sg:address":"Gotthardstrasse 27",
    "sg:city":"Oberarth",
    "sg:orig_category":"Bauspenglerei Dachdeckerei",
    "sg:phone":"+41 41 855 34 71",
    "sg:postcode":"6414",
    "sg:province":"Schwyz",
    "wof:name":"Leo Reichlin Bedachungen & Spenglerei",
    "wof:placetype":"venue"
},
  "geometry": {"coordinates":[8.534417,47.056221],"type":"Point"}
}