{
  "type": "Feature",
  "properties": {
    "iso:country":"CH",
    "sg:address":"Hauptstrasse 41a",
    "sg:city":"Ermatingen",
    "sg:orig_category":"Herstellung von medizinischen U chirurgischen Ger\u00e4ten sowie orthop\u00e4dischen Vorrichtungen",
    "sg:postcode":"8272",
    "sg:province":"Thurgau",
    "wof:name":"Dentaprod Sa",
    "wof:placetype":"venue"
},
  "geometry": {"coordinates":[9.0730066299,47.6700897217],"type":"Point"}
}