{
  "type": "Feature",
  "properties": {
    "iso:country":"CH",
    "sg:address":"Chemin Du Chaney",
    "sg:city":"Echandens",
    "sg:orig_category":"Vorschulen, Kinderg\u00e4rten",
    "sg:phone":"+41 21 701 33 96",
    "sg:postcode":"1026",
    "sg:province":"Vaud",
    "wof:name":"Ecole Enfantine I & Ii",
    "wof:placetype":"venue"
},
  "geometry": {"coordinates":[6.5402569771,46.5315132141],"type":"Point"}
}