{
  "type": "Feature",
  "properties": {
    "iso:country":"CH",
    "sg:address":"Sempacherstrasse 2",
    "sg:city":"Basel",
    "sg:orig_category":"Detailhandel Reparatur von Gebrauchsg\u00fctern",
    "sg:phone":"+41 55 260 13 01",
    "sg:postcode":"4053",
    "sg:province":"Basel-Stadt",
    "wof:name":"Erotica 4",
    "wof:placetype":"venue"
},
  "geometry": {"coordinates":[8.8491401672,47.2587509155],"type":"Point"}
}