{
  "type": "Feature",
  "properties": {
    "iso:country":"CH",
    "sg:address":"Poststrasse 6",
    "sg:city":"Uster",
    "sg:orig_category":"Non-Classified Establishments",
    "sg:postcode":"8610",
    "sg:province":"Z\u00fcrich",
    "wof:name":"Accroalu S\u00e0rl",
    "wof:placetype":"venue"
},
  "geometry": {"coordinates":[6.6876702309,46.559551239],"type":"Point"}
}