{
  "type": "Feature",
  "properties": {
    "iso:country":"CH",
    "sg:address":"La Benderette",
    "sg:city":"Monts-de-corsier",
    "sg:orig_category":"Maurerarbeiten",
    "sg:phone":"+41 21 921 61 65",
    "sg:postcode":"1808",
    "sg:province":"Vaud",
    "wof:name":"Jules Berdoz Ma\u00e7onnerie",
    "wof:placetype":"venue"
},
  "geometry": {"coordinates":[6.8812398911,46.5034866333],"type":"Point"}
}