{
  "type": "Feature",
  "properties": {
    "iso:country":"CH",
    "sg:address":"Hauptstrasse 41 9424 Rheineck. Postfach",
    "sg:city":"Rheineck",
    "sg:orig_category":"Detailhandel mit elektrischen Haushalts-,Radio U Fernsehger\u00e4ten sowie Musikinstrumenten",
    "sg:postcode":"9424",
    "sg:province":"St. Gallen",
    "wof:name":"Expert Humbel Ag Tv-/radio-gesch\u00e4ft Usw.",
    "wof:placetype":"venue"
},
  "geometry": {"coordinates":[9.590798378,47.4651412964],"type":"Point"}
}