{
  "type": "Feature",
  "properties": {
    "iso:country":"CH",
    "sg:address":"Murerh\u00fcsli 7",
    "sg:city":"Schenkon",
    "sg:orig_category":"Fachdetailhandel in Verkaufsr\u00e4umen Grosshandel mit Foto U Kinoger\u00e4ten, feinmechanischen U optischen ",
    "sg:phone":"+41 41 920 25 50",
    "sg:postcode":"6214",
    "sg:province":"Luzern",
    "wof:name":"Belvoir Optic Gmbh",
    "wof:placetype":"venue"
},
  "geometry": {"coordinates":[8.1376724243,47.1816444397],"type":"Point"}
}