{
  "type": "Feature",
  "properties": {
    "iso:country":"CH",
    "sg:address":"Grand-rue 49",
    "sg:city":"Cort\u00e9bert",
    "sg:orig_category":"Herstellung von sonstigen elektrischen Ausr\u00fcstungen Softwareentwicklung U beratung",
    "sg:phone":"+41 32 489 27 87",
    "sg:postcode":"2607",
    "sg:province":"Bern",
    "wof:name":"Stevil Electronique Sa Projets Informatiques; Conseils Et \u00e9tudes. Appareils \u00e9lectronique Etc",
    "wof:placetype":"venue"
},
  "geometry": {"coordinates":[7.1035761833,47.1893043518],"type":"Point"}
}