{
  "type": "Feature",
  "properties": {
    "iso:country":"CH",
    "sg:address":"Quaderstrasse 8 7000 Chur. Postfach",
    "sg:city":"Chur",
    "sg:orig_category":"Fachdetailhandel mit pharmazeutischen Produkten",
    "sg:postcode":"7000",
    "sg:province":"Graubunden",
    "wof:name":"Newpharm International Group Gmbh Waren, Bes. Pharmazeutische U. Kosmetische Produkte; Handel Usw",
    "wof:placetype":"venue"
},
  "geometry": {"coordinates":[9.5325269699,46.8522148132],"type":"Point"}
}