{
  "type": "Feature",
  "properties": {
    "iso:country":"CH",
    "sg:address":"Bernstrasse 33",
    "sg:city":"B\u00fctzberg",
    "sg:orig_category":"RESTAURANTS: TEA-ROOMS",
    "sg:postcode":"4922",
    "sg:province":"Bern",
    "wof:name":"Sch\u00e4r Ralph",
    "wof:placetype":"venue"
},
  "geometry": {"coordinates":[9.3818778992,47.5442619324],"type":"Point"}
}