{
  "type": "Feature",
  "properties": {
    "addr:full":"Viale Verbano 7 6600 Muralto. Postfach Muralto Ticino 6600",
    "addr:housenumber":"7",
    "addr:postcode":"6600 muralto. postfach;6600",
    "addr:street":"Viale Verbano",
    "iso:country":"CH",
    "sg:address":"Viale Verbano 7 6600 Muralto. Postfach",
    "sg:city":"Muralto",
    "sg:orig_category":"Aktivit\u00e4t der Bankinstitute Pensionskassen",
    "sg:phone":"+41 91 743 89 51",
    "sg:postcode":"6600",
    "sg:province":"Ticino",
    "wof:name":"Fondo Di Previdenza Per Il Personale Della Kredietbank (suisse) Lugano Sa",
    "wof:placetype":"venue"
},
  "geometry": {"coordinates":[8.8016,46.171322],"type":"Point"}
}