{
  "type": "Feature",
  "properties": {
    "iso:country":"CH",
    "sg:address":"La Tuili\u00e8re",
    "sg:city":"Villars-sous-yens",
    "sg:orig_category":"Rebbau",
    "sg:phone":"+41 56 443 17 69",
    "sg:postcode":"1138",
    "wof:name":"Georg Bayer Weinbau",
    "wof:placetype":"venue"
},
  "geometry": {"coordinates":[8.1350326538,47.4449768066],"type":"Point"}
}