{
  "type": "Feature",
  "properties": {
    "iso:country":"CH",
    "sg:address":"Rue De La Poste",
    "sg:city":"Avenches",
    "sg:orig_category":"Nationale Postdienste",
    "sg:phone":"+41 26 675 11 75",
    "sg:postcode":"1580",
    "sg:province":"Vaud",
    "wof:name":"La Poste Suisse",
    "wof:placetype":"venue"
},
  "geometry": {"coordinates":[7.0392680168,46.8811264038],"type":"Point"}
}