{
  "type": "Feature",
  "properties": {
    "iso:country":"CH",
    "sg:address":"Rennweg 24",
    "sg:city":"Z\u00fcrich",
    "sg:orig_category":"Detailhandel mit Schuhen",
    "sg:phone":"+41 12120655",
    "sg:postcode":"8001",
    "sg:province":"Z\u00fcrich",
    "wof:name":"Ladiva Schuhe Ag Schuhgesch\u00e4ft, -handel Usw",
    "wof:placetype":"venue"
},
  "geometry": {"coordinates":[8.5397262573,47.3729896545],"type":"Point"}
}