{
  "type": "Feature",
  "properties": {
    "iso:country":"CH",
    "sg:address":"Moosweg 36",
    "sg:city":"Gwatt",
    "sg:classifiers":[
        {
            "category":"Military Area",
            "subcategory":"Air Force Base",
            "type":"Public Place"
        }
    ],
    "sg:phone":"+41 33 334 40 00",
    "sg:postcode":"3645",
    "sg:province":"Bern",
    "sg:tags":[
        "profile",
        "aluminium",
        "window"
    ],
    "wof:name":"Elemetal Ag",
    "wof:placetype":"venue"
},
  "geometry": {"coordinates":[7.616495,46.723625],"type":"Point"}
}