{
  "type": "Feature",
  "properties": {
    "iso:country":"CH",
    "sg:address":"Rolandstr. 6",
    "sg:city":"Z\u00fcrich",
    "sg:orig_category":"Datenverarbeitungsdienste Sonstige mit der Informatik verbundene T\u00e4tigkeiten",
    "sg:phone":"+41 13401626",
    "sg:postcode":"8000",
    "sg:province":"Z\u00fcrich",
    "wof:name":"Testa Informatic",
    "wof:placetype":"venue"
},
  "geometry": {"coordinates":[8.527126,47.379002],"type":"Point"}
}