{
  "type": "Feature",
  "properties": {
    "iso:country":"CH",
    "sg:address":"Route De Bellebouche",
    "sg:city":"Meinier",
    "sg:orig_category":"Gem\u00fcsebau",
    "sg:phone":"+41 22 771 17 10",
    "sg:postcode":"1252",
    "sg:province":"Gen\u00e8ve",
    "wof:name":"Henri Clavenna Maraicher",
    "wof:placetype":"venue"
},
  "geometry": {"coordinates":[6.1379947662,46.1439323425],"type":"Point"}
}