{
  "type": "Feature",
  "properties": {
    "iso:country":"CH",
    "sg:address":"Rheinfelderstrasse 29",
    "sg:city":"Birsfelden",
    "sg:orig_category":"Interessenvertretungen U sonstige Vereinigungen",
    "sg:postcode":"4127",
    "sg:province":"Basel-Landschaft",
    "wof:name":"Satus-wasserf.-verb.d.schweiz",
    "wof:placetype":"venue"
},
  "geometry": {"coordinates":[7.6281318665,47.5488815308],"type":"Point"}
}