{
  "type": "Feature",
  "properties": {
    "addr:full":"Fraum\u00fcnsterstrasse 19 Z\u00fcrich Z\u00fcrich 8001",
    "addr:housenumber":"19",
    "addr:postcode":"8001",
    "addr:street":"Fraumuensterstrasse",
    "iso:country":"CH",
    "sg:address":"Fraum\u00fcnsterstrasse 19",
    "sg:city":"Z\u00fcrich",
    "sg:orig_category":"Bestattungswesen",
    "sg:phone":"+41 12110150",
    "sg:postcode":"8001",
    "sg:province":"Z\u00fcrich",
    "wof:name":"Funebris Pf\u00e4ndler J. Ag",
    "wof:placetype":"venue"
},
  "geometry": {"coordinates":[8.54093,47.36816],"type":"Point"}
}