{
  "type": "Feature",
  "properties": {
    "iso:country":"CH",
    "sg:address":"Am Lintli 30",
    "sg:city":"N\u00e4fels",
    "sg:orig_category":"Museen",
    "sg:phone":"+41 79 273 94 94",
    "sg:postcode":"8752",
    "sg:province":"Glarus",
    "wof:name":"Naturwissenschaftl.sammlungen Des Kts.glarus,herrn R.m\u00fcller",
    "wof:placetype":"venue"
},
  "geometry": {"coordinates":[9.0666074753,47.1100196838],"type":"Point"}
}