{
  "type": "Feature",
  "properties": {
    "iso:country":"CH",
    "sg:address":"Baselstrasse 59",
    "sg:city":"Dagmersellen",
    "sg:orig_category":"Bau U Wohngenossenschaften",
    "sg:postcode":"6252",
    "sg:province":"Luzern",
    "wof:name":"Gemein.siedlungsgen.chr\u00fczberg C/o Giger & Gut Ag",
    "wof:placetype":"venue"
},
  "geometry": {"coordinates":[7.982344,47.21954],"type":"Point"}
}