{
  "type": "Feature",
  "properties": {
    "iso:country":"CH",
    "sg:address":"Saint-jean Rue De 98",
    "sg:city":"Gen\u00e8ve",
    "sg:orig_category":"Non-Classified Establishments",
    "sg:postcode":"1201",
    "sg:province":"Gen\u00e8ve",
    "wof:name":"San Martin Mining Research And Investment Company Ltd",
    "wof:placetype":"venue"
},
  "geometry": {"coordinates":[6.1379828453,46.2062683105],"type":"Point"}
}