{
  "type": "Feature",
  "properties": {
    "iso:country":"CH",
    "sg:address":"Eschenstrasse 8",
    "sg:city":"Gerlafingen",
    "sg:orig_category":"Architektur U Ingenieurb\u00fcros",
    "sg:phone":"+41 32 674 51 45",
    "sg:postcode":"4563",
    "sg:province":"Solothurn",
    "wof:name":"R & B Architekten Gmbh",
    "wof:placetype":"venue"
},
  "geometry": {"coordinates":[7.582689,47.175049],"type":"Point"}
}