{
  "type": "Feature",
  "properties": {
    "iso:country":"CH",
    "sg:address":"Chriesbaumstrasse 4",
    "sg:city":"Volketswil",
    "sg:classifiers":[
        {
            "category":"Health Services",
            "subcategory":"Medical Lab",
            "type":"Services"
        }
    ],
    "sg:phone":"+41 19464590",
    "sg:postcode":"8604",
    "sg:province":"Z\u00fcrich",
    "sg:tags":[
        "pharmaceutical",
        "agent"
    ],
    "wof:name":"Castiglione Medica Gmbh",
    "wof:placetype":"venue"
},
  "geometry": {"coordinates":[8.6803779602,47.3822097778],"type":"Point"}
}