{
  "type": "Feature",
  "properties": {
    "iso:country":"CH",
    "sg:address":"Chemin De La Vy-d'etra 10",
    "sg:city":"Boudry",
    "sg:orig_category":"Elektroinstallation",
    "sg:postcode":"2017",
    "sg:province":"Neuch\u00e2tel",
    "wof:name":"R & R Consulting Gmbh",
    "wof:placetype":"venue"
},
  "geometry": {"coordinates":[8.5987300873,47.328956604],"type":"Point"}
}