{
  "type": "Feature",
  "properties": {
    "iso:country":"CH",
    "sg:address":"Zollikerstrasse 238 8000 Z\u00fcrich. Postfach",
    "sg:city":"Z\u00fcrich",
    "sg:orig_category":"Gesundheitswesen",
    "sg:postcode":"8008",
    "sg:province":"Z\u00fcrich",
    "wof:name":"Schriber Suasnne - Beratung, Schulung",
    "wof:placetype":"venue"
},
  "geometry": {"coordinates":[8.5658502579,47.3479309082],"type":"Point"}
}