{
  "type": "Feature",
  "properties": {
    "iso:country":"CH",
    "sg:address":"Guggachstrasse 11",
    "sg:city":"Z\u00fcrich",
    "sg:orig_category":"Primarschulen",
    "sg:phone":"+41 13634150",
    "sg:postcode":"8057",
    "sg:province":"Z\u00fcrich",
    "wof:name":"Primarschule Milchbuck A",
    "wof:placetype":"venue"
},
  "geometry": {"coordinates":[8.5387659073,47.396068573],"type":"Point"}
}