{
  "type": "Feature",
  "properties": {
    "iso:country":"CH",
    "sg:address":"B\u00f6zingenstr. 79a. 2500 Biel/bienne. Postfach",
    "sg:city":"Biel/bienne",
    "sg:orig_category":"RESTAURANTS: TEA-ROOMS",
    "sg:postcode":"2500",
    "sg:province":"Bern",
    "wof:name":"Emch Jean.",
    "wof:placetype":"venue"
},
  "geometry": {"coordinates":[7.2596988678,47.1489868164],"type":"Point"}
}