{
  "type": "Feature",
  "properties": {
    "iso:country":"CH",
    "sg:address":"Poststrasse 4",
    "sg:city":"Degersheim",
    "sg:orig_category":"Architektur U Ingenieurb\u00fcros",
    "sg:phone":"+41 71 371 17 33",
    "sg:postcode":"9113",
    "sg:province":"St. Gallen",
    "wof:name":"Geologieb\u00fcro Lienert & Haering Ag",
    "wof:placetype":"venue"
},
  "geometry": {"coordinates":[9.197716,47.372387],"type":"Point"}
}