{
  "type": "Feature",
  "properties": {
    "iso:country":"CH",
    "sg:address":"Via Suro 14",
    "sg:city":"Rh\u00e4z\u00fcns",
    "sg:orig_category":"Sonstiger spezialisierter Hoch U Tiefbau Strassenbau",
    "sg:phone":"+41 81 641 25 38",
    "sg:postcode":"7403",
    "sg:province":"Graubunden",
    "wof:name":"Berther Pflaesterungen Ag",
    "wof:placetype":"venue"
},
  "geometry": {"coordinates":[9.3964519501,46.8010673523],"type":"Point"}
}