{
  "type": "Feature",
  "properties": {
    "addr:full":"Bubenbergplatz 9 Bern Bern 3011",
    "addr:housenumber":"9",
    "addr:postcode":"3011",
    "addr:street":"Bubenbergplatz",
    "iso:country":"CH",
    "sg:address":"Bubenbergplatz 9",
    "sg:city":"Bern",
    "sg:orig_category":"Detailhandel mit Blumen U Pflanzen Fachdetailhandel in Verkaufsr\u00e4umen",
    "sg:phone":"+41 31 311 33 35",
    "sg:postcode":"3011",
    "sg:province":"Bern",
    "wof:name":"Blumen-galli Ag",
    "wof:placetype":"venue"
},
  "geometry": {"coordinates":[7.439482,46.947247],"type":"Point"}
}