{
  "type": "Feature",
  "properties": {
    "iso:country":"CH",
    "sg:address":"Seestrasse 658",
    "sg:city":"Meilen",
    "sg:orig_category":"G\u00fcterbef\u00f6rderung im Strassenverkehr",
    "sg:phone":"+41 79 380 42 38",
    "sg:postcode":"8706",
    "sg:province":"Z\u00fcrich",
    "wof:name":"Rtm Reusser Rudolf Transporte Meilen",
    "wof:placetype":"venue"
},
  "geometry": {"coordinates":[8.6444854736,47.267665863],"type":"Point"}
}