{
  "type": "Feature",
  "properties": {
    "addr:full":"Weinbergstrasse 18 Z\u00fcrich Z\u00fcrich 8001",
    "addr:housenumber":"18",
    "addr:postcode":"8001",
    "addr:street":"Weinbergstrasse",
    "iso:country":"CH",
    "sg:address":"Weinbergstrasse 18",
    "sg:city":"Z\u00fcrich",
    "sg:orig_category":"Advokaturb\u00fcros",
    "sg:phone":"+41 31 312 25 25",
    "sg:postcode":"8001",
    "sg:province":"Z\u00fcrich",
    "wof:name":"Michael Bader Advokaturb\u00fcro",
    "wof:placetype":"venue"
},
  "geometry": {"coordinates":[7.450458,46.947601],"type":"Point"}
}