{
  "type": "Feature",
  "properties": {
    "iso:country":"CH",
    "sg:address":"Via Cantonale",
    "sg:city":"Grono",
    "sg:classifiers":[
        {
            "category":"Health Services",
            "subcategory":"Hospital",
            "type":"Services"
        }
    ],
    "sg:phone":"+41 91 820 30 50",
    "sg:postcode":"6537",
    "sg:province":"Graubunden",
    "sg:tags":[
        "tableware",
        "cardboard",
        "disposable"
    ],
    "wof:name":"Swimpack Sa",
    "wof:placetype":"venue"
},
  "geometry": {"coordinates":[9.156456,46.252972],"type":"Point"}
}