{
  "type": "Feature",
  "properties": {
    "iso:country":"CH",
    "sg:address":"Rigistrasse 2 6374 Buochs. Postfach",
    "sg:city":"Buochs",
    "sg:orig_category":"Sonstiger Grosshandel",
    "sg:postcode":"6374",
    "sg:province":"Nidwalden",
    "wof:name":"Die Karawanen Gmbh Dienstleistungen Auf Dem Gebiet Export, Import, Tourismus Und Consulting",
    "wof:placetype":"venue"
},
  "geometry": {"coordinates":[8.4225912094,46.9771080017],"type":"Point"}
}