{
  "type": "Feature",
  "properties": {
    "iso:country":"CH",
    "sg:address":"6601 Locarno. Postfach Caselle Postale 1865",
    "sg:city":"Locarno",
    "sg:orig_category":"Sportvereine Ballsport Fussball",
    "sg:phone":"+41 91 756 15 45",
    "sg:postcode":"6601",
    "sg:province":"Ticino",
    "wof:name":"As Esperia-tazebau",
    "wof:placetype":"venue"
},
  "geometry": {"coordinates":[8.7945299149,46.1704788208],"type":"Point"}
}