{
  "type": "Feature",
  "properties": {
    "iso:country":"CH",
    "sg:address":"Sonnhalde 6013 Eigenthal. Postfach",
    "sg:city":"Eigenthal",
    "sg:orig_category":"Detektivb\u00fcros U \u00dcberwachung",
    "sg:postcode":"6013",
    "sg:province":"Luzern",
    "wof:name":"Sicherheitsdienste Protective Spieler Reto",
    "wof:placetype":"venue"
},
  "geometry": {"coordinates":[8.2100887299,47.0099182129],"type":"Point"}
}