{
  "type": "Feature",
  "properties": {
    "iso:country":"CH",
    "sg:address":"Fischrainweg 5 3048 Worblaufen. Postfach",
    "sg:city":"Worblaufen",
    "sg:orig_category":"Detailhandel mit elektrischen Haushalts-,Radio U Fernsehger\u00e4ten sowie Musikinstrumenten",
    "sg:postcode":"3048",
    "sg:province":"Bern",
    "wof:name":"Rinitec Nipote",
    "wof:placetype":"venue"
},
  "geometry": {"coordinates":[7.4615721703,46.9784164429],"type":"Point"}
}