{
  "type": "Feature",
  "properties": {
    "iso:country":"CH",
    "sg:address":"Rischli 6173 Fl\u00fchli Lu. Postfach",
    "sg:city":"S\u00f6renberg",
    "sg:orig_category":"G\u00fcterbef\u00f6rderung im Strassenverkehr",
    "sg:postcode":"6174",
    "sg:province":"Luzern",
    "wof:name":"Wigger-emmenegger Herm.",
    "wof:placetype":"venue"
},
  "geometry": {"coordinates":[8.0188684464,46.8269424438],"type":"Point"}
}