{
  "type": "Feature",
  "properties": {
    "addr:full":"M\u00fchlehole 99a Oberwil Bern 3298",
    "addr:housenumber":"99a",
    "addr:postcode":"3298",
    "addr:street":"Muehlehole",
    "iso:country":"CH",
    "sg:address":"M\u00fchlehole 99a",
    "sg:city":"Oberwil",
    "sg:classifiers":[
        {
            "category":"Shopping",
            "subcategory":"Antiques",
            "type":"Retail Goods"
        }
    ],
    "sg:phone":"+41 32 351 33 93",
    "sg:postcode":"3298",
    "sg:province":"Bern",
    "sg:tags":[
        "furniture"
    ],
    "wof:name":"Peter Kislig Antiker Innenausbau",
    "wof:placetype":"venue"
},
  "geometry": {"coordinates":[7.4047,47.12891],"type":"Point"}
}