{
  "type": "Feature",
  "properties": {
    "iso:country":"CH",
    "sg:address":"Zimmerlistrasse 32",
    "sg:city":"Aarburg",
    "sg:orig_category":"Grosshandel mit Getr\u00e4nken",
    "sg:phone":"+41 62 791 40 88",
    "sg:postcode":"4663",
    "sg:province":"Aargau",
    "wof:name":"In-cider Verkauf August Burkart",
    "wof:placetype":"venue"
},
  "geometry": {"coordinates":[7.9059801102,47.3163719177],"type":"Point"}
}