{
  "type": "Feature",
  "properties": {
    "iso:country":"CH",
    "sg:address":"Oberr\u00fctelistrase 32",
    "sg:city":"Mollis",
    "sg:orig_category":"Interessenvertretungen",
    "sg:postcode":"8753",
    "sg:province":"Glarus",
    "wof:name":"Weber Milly Stiftung",
    "wof:placetype":"venue"
},
  "geometry": {"coordinates":[9.8381910324,46.4970664978],"type":"Point"}
}