{
  "type": "Feature",
  "properties": {
    "iso:country":"CH",
    "sg:address":"Route D'anniviers",
    "sg:city":"Vercorin",
    "sg:classifiers":[
        {
            "category":"Bars & Pubs",
            "type":"Food & Drink"
        }
    ],
    "sg:phone":"+41 27 452 29 00",
    "sg:postcode":"3967",
    "sg:province":"Valais",
    "sg:tags":[
        "restaurant"
    ],
    "wof:name":"Restaurant Margueron & Pub",
    "wof:placetype":"venue"
},
  "geometry": {"coordinates":[7.531761,46.255848],"type":"Point"}
}