{
  "type": "Feature",
  "properties": {
    "addr:full":"6146 Grossdietwil Luzern 6146",
    "addr:housenumber":"6146",
    "addr:postcode":"6146",
    "addr:street":"Grossdietwil",
    "iso:country":"CH",
    "sg:address":"6146",
    "sg:city":"Grossdietwil",
    "sg:orig_category":"Bezirks, Sekundar, Realschulen, Oberstufe der Primarschulen Primarschulen",
    "sg:postcode":"6146",
    "sg:province":"Luzern",
    "wof:name":"Primar-/oberstufenschule Dorf",
    "wof:placetype":"venue"
},
  "geometry": {"coordinates":[7.888073,47.170208],"type":"Point"}
}