{
  "type": "Feature",
  "properties": {
    "iso:country":"CH",
    "sg:address":"Dorfstrasse 2",
    "sg:city":"Plaffeien",
    "sg:orig_category":"HOTELS: MIT RESTAURANT Kongress- and Tagungshotels mit Restaurant",
    "sg:phone":"+41 26 419 11 14",
    "sg:postcode":"1716",
    "sg:province":"Fribourg",
    "wof:name":"Landgasthof Hirschen",
    "wof:placetype":"venue"
},
  "geometry": {"coordinates":[7.2851161957,46.7417793274],"type":"Point"}
}