{
  "type": "Feature",
  "properties": {
    "iso:country":"CH",
    "sg:address":"Obermoos",
    "sg:city":"Russikon",
    "sg:classifiers":[
        {
            "category":"Farming",
            "subcategory":"Farm",
            "type":"Manufacturing & Wholesale Goods"
        }
    ],
    "sg:phone":"+41 33 822 20 54",
    "sg:postcode":"8332",
    "sg:province":"Z\u00fcrich",
    "sg:tags":[
        "horticulture",
        "agriculture",
        "livestock"
    ],
    "wof:name":"H Gosteli Ag",
    "wof:placetype":"venue"
},
  "geometry": {"coordinates":[7.864939,46.680321],"type":"Point"}
}