{
  "type": "Feature",
  "properties": {
    "iso:country":"CH",
    "sg:address":"Alleeweg 8",
    "sg:city":"Rheinfelden",
    "sg:orig_category":"Arztpraxen",
    "sg:phone":"+41 61 831 38 76",
    "sg:postcode":"4310",
    "sg:province":"Aargau",
    "wof:name":"Dr.med.marianne Bruppacher Spezial\u00e4rztin Fmh",
    "wof:placetype":"venue"
},
  "geometry": {"coordinates":[7.793104,47.549774],"type":"Point"}
}