{
  "type": "Feature",
  "properties": {
    "iso:country":"CH",
    "sg:address":"Ratenstrasse",
    "sg:city":"Bennau",
    "sg:orig_category":"Grosshandel mit Holz U Bauelementen aus Holz S\u00e4gewerke",
    "sg:phone":"+41 55 284 53 43",
    "sg:postcode":"8836",
    "sg:province":"Schwyz",
    "wof:name":"Christian Eicher S\u00e4gerei & Holzhandlung",
    "wof:placetype":"venue"
},
  "geometry": {"coordinates":[9.0695314407,47.2788391113],"type":"Point"}
}