{
  "type": "Feature",
  "properties": {
    "iso:country":"CH",
    "sg:address":"Hinterdorf 24",
    "sg:city":"Uezwil",
    "sg:orig_category":"Mechanische Werkst\u00e4tten",
    "sg:phone":"+41 19500003",
    "sg:postcode":"5619",
    "sg:province":"Aargau",
    "wof:name":"Anton Rohner Mechanische Werkst\u00e4tte",
    "wof:placetype":"venue"
},
  "geometry": {"coordinates":[8.7917995453,47.3605003357],"type":"Point"}
}