{
  "type": "Feature",
  "properties": {
    "iso:country":"CH",
    "sg:address":"Bruggmoos 5",
    "sg:city":"Speicher",
    "sg:orig_category":"Detailhandel mit Fleisch U Fleischwaren",
    "sg:phone":"+41 71 344 13 40",
    "sg:postcode":"9042",
    "sg:province":"Appenzell Ausserrhoden",
    "wof:name":"Otto Fitzi-altherr",
    "wof:placetype":"venue"
},
  "geometry": {"coordinates":[9.4462623596,47.4079589844],"type":"Point"}
}