{
  "type": "Feature",
  "properties": {
    "iso:country":"CH",
    "sg:address":"Loostud",
    "sg:city":"Berikon",
    "sg:classifiers":[
        {
            "category":"Sports & Exercise",
            "subcategory":"Stables",
            "type":"Entertainment"
        }
    ],
    "sg:phone":"+41 56 633 12 87",
    "sg:postcode":"8965",
    "sg:province":"Aargau",
    "sg:tags":[
        "gate",
        "door"
    ],
    "wof:name":"Koch Farmtech",
    "wof:placetype":"venue"
},
  "geometry": {"coordinates":[8.3821659088,47.354019165],"type":"Point"}
}