{
  "type": "Feature",
  "properties": {
    "iso:country":"CH",
    "sg:address":"Via Della Posta 6934 Bioggio Casella Postale",
    "sg:city":"Bioggio",
    "sg:orig_category":"Elektro- and elektronische Maschinen Grosshandel",
    "sg:phone":"+41 91 610 07 00",
    "sg:postcode":"6934",
    "sg:province":"Ticino",
    "wof:name":"Tyco Electronics Augat Ag Parti Meccaniche, Elettriche Ecc. P. L'industria Informatica Ed Automobilistica; Fabbr., Lavoraz.",
    "wof:placetype":"venue"
},
  "geometry": {"coordinates":[8.9086551666,46.0143966675],"type":"Point"}
}