{
  "type": "Feature",
  "properties": {
    "iso:country":"CH",
    "sg:address":"Bottigenstrasse 9",
    "sg:city":"Bern",
    "sg:orig_category":"Non-Classified Establishments",
    "sg:postcode":"3018",
    "sg:province":"Bern",
    "wof:name":"Rentenanstalt Swiss Life Generalagentur Bern - West Christian Schmid",
    "wof:placetype":"venue"
},
  "geometry": {"coordinates":[7.3894968033,46.9394264221],"type":"Point"}
}