{
  "type": "Feature",
  "properties": {
    "iso:country":"CH",
    "sg:address":"M\u00fbriers Chemin Des 1",
    "sg:city":"Aubonne",
    "sg:orig_category":"Softwareentwicklung U beratung",
    "sg:phone":"+41 13410636",
    "sg:postcode":"1170",
    "sg:province":"Vaud",
    "wof:name":"Gerber-netcon",
    "wof:placetype":"venue"
},
  "geometry": {"coordinates":[8.4634513855,47.2786865234],"type":"Point"}
}