{
  "type": "Feature",
  "properties": {
    "iso:country":"CH",
    "sg:address":"Solibodenstrasse 16",
    "sg:city":"B\u00fclach",
    "sg:orig_category":"Erschliessung von Grundst\u00fccken",
    "sg:phone":"+41 55 410 81 12",
    "sg:postcode":"8180",
    "sg:province":"Z\u00fcrich",
    "wof:name":"Topfloor International Gmbh Scl\u00fcsselfertige Wohn, Gewerbe, Industriebauten; Erstellung",
    "wof:placetype":"venue"
},
  "geometry": {"coordinates":[8.7791414261,47.1991539001],"type":"Point"}
}