{
  "type": "Feature",
  "properties": {
    "iso:country":"CH",
    "sg:address":"Petite Rue",
    "sg:city":"Allaman",
    "sg:orig_category":"Fachdetailhandel in Verkaufsr\u00e4umen",
    "sg:phone":"+41 21 807 39 24",
    "sg:postcode":"1165",
    "sg:province":"Vaud",
    "wof:name":"Bijouterie Wolleb Jean-pierre",
    "wof:placetype":"venue"
},
  "geometry": {"coordinates":[6.3968749046,46.4711494446],"type":"Point"}
}