{
  "type": "Feature",
  "properties": {
    "iso:country":"CH",
    "sg:address":"Ruchackerstrasse 16",
    "sg:city":"Luterbach",
    "sg:orig_category":"Unternehmensberatung",
    "sg:phone":"+41 32 682 01 71",
    "sg:postcode":"4542",
    "sg:province":"Solothurn",
    "wof:name":"Inner Management Fernando Christian",
    "wof:placetype":"venue"
},
  "geometry": {"coordinates":[7.5845470428,47.2120704651],"type":"Point"}
}