{
  "type": "Feature",
  "properties": {
    "iso:country":"CH",
    "sg:address":"Kehrstrasse 9",
    "sg:city":"B\u00e4retswil",
    "sg:orig_category":"Markt U Meinungsforschung",
    "sg:phone":"+41 61 321 70 29",
    "sg:postcode":"8344",
    "sg:province":"Z\u00fcrich",
    "wof:name":"Gn Associates Consulting Gmbh",
    "wof:placetype":"venue"
},
  "geometry": {"coordinates":[8.8527374268,47.3389968872],"type":"Point"}
}