{
  "type": "Feature",
  "properties": {
    "iso:country":"CH",
    "sg:address":"Seestrasse 497",
    "sg:city":"Z\u00fcrich",
    "sg:classifiers":[
        {
            "category":"Autos & Motor Vehicles",
            "subcategory":"Boat Sales",
            "type":"Retail Goods"
        }
    ],
    "sg:phone":"+41 14829944",
    "sg:postcode":"8038",
    "sg:province":"Z\u00fcrich",
    "sg:tags":[
        "fishing"
    ],
    "wof:name":"St\u00e4mpfli Racing Boats Ag",
    "wof:placetype":"venue"
},
  "geometry": {"coordinates":[8.5389328003,47.3378334045],"type":"Point"}
}