{
  "type": "Feature",
  "properties": {
    "iso:country":"CH",
    "sg:address":"Niederweg 87",
    "sg:city":"Wettswil",
    "sg:orig_category":"Grosshandel mit Nahrungsmitteln, Getr\u00e4nken U Tabakwaren ohne ausgepr\u00e4gten Schwerpunkt",
    "sg:phone":"+41 17002980",
    "sg:postcode":"8907",
    "sg:province":"Z\u00fcrich",
    "wof:name":"Mesotrend Gmbh",
    "wof:placetype":"venue"
},
  "geometry": {"coordinates":[8.4751224518,47.3287620544],"type":"Point"}
}