{
  "type": "Feature",
  "properties": {
    "iso:country":"CH",
    "sg:address":"Rathausgasse 2",
    "sg:city":"Diessenhofen",
    "sg:orig_category":"Unternehmensberatung Wirtschaftspr\u00fcfung, Steuerberatung U Treuhand",
    "sg:phone":"+41 52 657 28 07",
    "sg:postcode":"8253",
    "sg:province":"Thurgau",
    "wof:name":"Util Ag Treuhand & Unternehmensber.",
    "wof:placetype":"venue"
},
  "geometry": {"coordinates":[8.7522306442,47.6892051697],"type":"Point"}
}