{
  "type": "Feature",
  "properties": {
    "iso:country":"CH",
    "sg:address":"Katzerenstrasse 41",
    "sg:city":"Horgen",
    "sg:orig_category":"Unternehmensberatung",
    "sg:postcode":"8810",
    "sg:province":"Z\u00fcrich",
    "wof:name":"K\u00fcpfer Trade Consulting",
    "wof:placetype":"venue"
},
  "geometry": {"coordinates":[8.5985374451,47.2516136169],"type":"Point"}
}