{
  "type": "Feature",
  "properties": {
    "iso:country":"CH",
    "sg:address":"Grossmattweg 28",
    "sg:city":"Therwil",
    "sg:orig_category":"Gewinnung von Kies U Sand Grosshandel mit Holz U Baustoffen",
    "sg:phone":"+41 61 331 01 20",
    "sg:postcode":"4106",
    "sg:province":"Basel-Landschaft",
    "wof:name":"Rohkiesund Heinis Ag",
    "wof:placetype":"venue"
},
  "geometry": {"coordinates":[7.5499119759,47.4960289001],"type":"Point"}
}