{
  "type": "Feature",
  "properties": {
    "iso:country":"CH",
    "sg:address":"Bellerivestrasse 219",
    "sg:city":"Z\u00fcrich",
    "sg:orig_category":"Softwareentwicklung U beratung",
    "sg:postcode":"8008",
    "sg:province":"Z\u00fcrich",
    "wof:name":"Conceptual Data Architecture Coda Gmbh",
    "wof:placetype":"venue"
},
  "geometry": {"coordinates":[8.5594005585,47.3516044617],"type":"Point"}
}