{
  "type": "Feature",
  "properties": {
    "iso:country":"CH",
    "sg:address":"Peupliers Rue Des 2 1205 Gen\u00e8ve. Postfach",
    "sg:city":"Gen\u00e8ve",
    "sg:orig_category":"Kauf U Verkauf von Immobilien auf eigene Rechnung",
    "sg:postcode":"1201",
    "sg:province":"Gen\u00e8ve",
    "wof:name":"Iodimar Sa",
    "wof:placetype":"venue"
},
  "geometry": {"coordinates":[6.144753933,46.1880531311],"type":"Point"}
}