{
  "type": "Feature",
  "properties": {
    "iso:country":"CH",
    "sg:address":"Seonerstrasse 37",
    "sg:city":"Lenzburg",
    "sg:orig_category":"Grosshandel mit sonstigen Gebrauchs U Verbrauchsg\u00fctern",
    "sg:phone":"+41 71 244 18 23",
    "sg:postcode":"5600",
    "sg:province":"Aargau",
    "wof:name":"H\u00f6gger Oskar, Nachfolger H\u00f6gger Daniel Werbegeschenke; Handel. Immobilien; Kauf, Verkauf Usw.",
    "wof:placetype":"venue"
},
  "geometry": {"coordinates":[9.3882684708,47.4358978271],"type":"Point"}
}