{
  "type": "Feature",
  "properties": {
    "iso:country":"CH",
    "sg:address":"Weidhof Agasul",
    "sg:city":"Illnau",
    "sg:orig_category":"Grosshandel mit lebenden Tieren",
    "sg:phone":"+41 26 652 22 91",
    "sg:postcode":"8308",
    "sg:province":"Z\u00fcrich",
    "wof:name":"Albert Bourqui Commerce De B\u00e9tail",
    "wof:placetype":"venue"
},
  "geometry": {"coordinates":[6.9275698662,46.6799888611],"type":"Point"}
}