{
  "type": "Feature",
  "properties": {
    "iso:country":"CH",
    "sg:address":"S\u00fcdstr. 115",
    "sg:city":"Z\u00fcrich",
    "sg:classifiers":[
        {
            "category":"Professional",
            "subcategory":"Business Services",
            "type":"Services"
        }
    ],
    "sg:phone":"+41 4113816120",
    "sg:postcode":"8008",
    "sg:province":"Z\u00fcrich",
    "sg:tags":[
        "training",
        "advice"
    ],
    "wof:name":"S\u00dcdhalde Berufsschule F. Gesundheit U. Krankenpflege",
    "wof:placetype":"venue"
},
  "geometry": {"coordinates":[8.568116,47.349728],"type":"Point"}
}