{
  "type": "Feature",
  "properties": {
    "iso:country":"CH",
    "sg:address":"Kirchgasse 22",
    "sg:city":"Sissach",
    "sg:orig_category":"Schnelldruck U Kopierservice",
    "sg:phone":"+41 61 971 63 55",
    "sg:postcode":"4450",
    "sg:province":"Basel-Landschaft",
    "wof:name":"Copy-center Sissach Inh.gloor-gisin-corti & Jost",
    "wof:placetype":"venue"
},
  "geometry": {"coordinates":[7.8105578423,47.4657554626],"type":"Point"}
}