{
  "type": "Feature",
  "properties": {
    "iso:country":"CH",
    "sg:address":"Saut-du-loup Chemin Du 9",
    "sg:city":"Ch\u00eane-bourg",
    "sg:orig_category":"Sonstige mit der Informatik verbundene T\u00e4tigkeiten",
    "sg:phone":"+41 22 349 42 52",
    "sg:postcode":"1225",
    "sg:province":"Gen\u00e8ve",
    "wof:name":"Thompson, Consulting En Micro Informatique",
    "wof:placetype":"venue"
},
  "geometry": {"coordinates":[6.2022471428,46.2006111145],"type":"Point"}
}