{
  "type": "Feature",
  "properties": {
    "iso:country":"CH",
    "sg:address":"Limmatquai 138 8001 Z\u00fcrich. Postfach",
    "sg:city":"Z\u00fcrich",
    "sg:orig_category":"Fachdetailhandel in Verkaufsr\u00e4umen",
    "sg:postcode":"8001",
    "sg:province":"Z\u00fcrich",
    "wof:name":"Berber Boutique Gmbh",
    "wof:placetype":"venue"
},
  "geometry": {"coordinates":[8.5436782837,47.3759231567],"type":"Point"}
}