{
  "type": "Feature",
  "properties": {
    "iso:country":"CH",
    "sg:address":"Seestrasse 13",
    "sg:city":"Uster",
    "sg:classifiers":[
        {
            "category":"Insurance",
            "subcategory":"Insurance Agent",
            "type":"Services"
        }
    ],
    "sg:phone":"+41 19416200",
    "sg:postcode":"8610",
    "sg:province":"Z\u00fcrich",
    "sg:tags":[
        "versicherungsagenturen",
        "-broker"
    ],
    "wof:name":"Pensionskassenberatung Hanspeter Diethelm",
    "wof:placetype":"venue"
},
  "geometry": {"coordinates":[8.714600563,47.3473243713],"type":"Point"}
}