{
  "type": "Feature",
  "properties": {
    "iso:country":"CH",
    "sg:address":"Schneckelerstrasse 1",
    "sg:city":"F\u00fcllinsdorf",
    "sg:orig_category":"Herstellung von M\u00f6beln verschiedener Art",
    "sg:phone":"+41 61 903 10 66",
    "sg:postcode":"4414",
    "sg:province":"Basel-Landschaft",
    "wof:name":"Heidi K\u00e4ser K\u00e4ser Wasserbetten",
    "wof:placetype":"venue"
},
  "geometry": {"coordinates":[7.7210078239,47.5124969482],"type":"Point"}
}