{
  "type": "Feature",
  "properties": {
    "iso:country":"CH",
    "sg:address":"Baarerstrasse 43b",
    "sg:city":"Zug",
    "sg:orig_category":"Vermietung U Verpachtung von eigenen Immobilien",
    "sg:postcode":"6300",
    "sg:province":"Zug",
    "wof:name":"Vic Village Industriel Au Chenit Sa",
    "wof:placetype":"venue"
},
  "geometry": {"coordinates":[6.2306790352,46.6076850891],"type":"Point"}
}