{
  "type": "Feature",
  "properties": {
    "iso:country":"CH",
    "sg:address":"Rorschacherstrasse 271",
    "sg:city":"M\u00f6rschwil",
    "sg:orig_category":"Instandhaltung U Reparatur von Automobilen",
    "sg:phone":"+41 71 866 24 24",
    "sg:postcode":"9402",
    "sg:province":"St. Gallen",
    "wof:name":"Hans Mauchle Wisental-garage",
    "wof:placetype":"venue"
},
  "geometry": {"coordinates":[9.4235897064,47.4553718567],"type":"Point"}
}