{
  "type": "Feature",
  "properties": {
    "iso:country":"CH",
    "sg:address":"Rue De L'eglise",
    "sg:city":"Fully",
    "sg:classifiers":[
        {
            "category":"Restaurant",
            "type":"Food & Drink"
        }
    ],
    "sg:phone":"+41 27 746 34 95",
    "sg:postcode":"1926",
    "sg:province":"Valais",
    "wof:name":"Caf\u00e9 Place",
    "wof:placetype":"venue"
},
  "geometry": {"coordinates":[7.1151638031,46.1387557983],"type":"Point"}
}