{
  "type": "Feature",
  "properties": {
    "iso:country":"CH",
    "sg:address":"1450 Ste-croix Case Postale 291",
    "sg:city":"Ste-croix",
    "sg:orig_category":"Sportvereine Ballsport Volleyball",
    "sg:phone":"+41 24 454 21 37",
    "sg:postcode":"1450",
    "sg:province":"Vaud",
    "wof:name":"Volleyball-club De Ste-croix",
    "wof:placetype":"venue"
},
  "geometry": {"coordinates":[6.5010499954,46.8242111206],"type":"Point"}
}