{
  "type": "Feature",
  "properties": {
    "iso:country":"CH",
    "sg:address":"Kilchbergstrasse 15",
    "sg:city":"Z\u00fcrich",
    "sg:classifiers":[
        {
            "category":"Restaurant",
            "type":"Food & Drink"
        }
    ],
    "sg:phone":"+41 14828100",
    "sg:postcode":"8038",
    "sg:province":"Z\u00fcrich",
    "wof:name":"Restaurant Z. B\u00fcrgli",
    "wof:placetype":"venue"
},
  "geometry": {"coordinates":[8.5337028503,47.3428421021],"type":"Point"}
}