{
  "type": "Feature",
  "properties": {
    "iso:country":"CH",
    "sg:address":"Schleifrain 17",
    "sg:city":"Sch\u00f6tz",
    "sg:orig_category":"Schulpflegen",
    "sg:phone":"+41 41 980 48 77",
    "sg:postcode":"6247",
    "sg:province":"Luzern",
    "wof:name":"Schulpflege Der Gemeinde Sch\u00f6tz",
    "wof:placetype":"venue"
},
  "geometry": {"coordinates":[7.9845399857,47.1740493774],"type":"Point"}
}