{
  "type": "Feature",
  "properties": {
    "iso:country":"CH",
    "sg:address":"Route De Phare 20 1871 Cho\u00ebx. Postfach",
    "sg:city":"Cho\u00ebx",
    "sg:orig_category":"Herstellung von Metallkonstruktionen",
    "sg:postcode":"1871",
    "sg:province":"Valais",
    "wof:name":"Jean Woeffray",
    "wof:placetype":"venue"
},
  "geometry": {"coordinates":[6.9558639526,46.2400360107],"type":"Point"}
}