{
  "type": "Feature",
  "properties": {
    "addr:full":"Selnaustr. 32 Z\u00fcrich 8039",
    "addr:housenumber":"32",
    "addr:postcode":"8039",
    "addr:street":"Selnaustr.",
    "iso:country":"CH",
    "sg:address":"Selnaustr. 32",
    "sg:city":"Z\u00fcrich",
    "sg:classifiers":[
        {
            "category":"Banks & Credit Unions",
            "subcategory":"Financial Services",
            "type":"Services"
        }
    ],
    "sg:phone":"+41 22 317 27 27",
    "sg:postcode":"8039",
    "sg:tags":[
        "banking",
        "insurance",
        "institution",
        "finance"
    ],
    "wof:name":"Banque Cantonale De Gen\u00c8ve",
    "wof:placetype":"venue"
},
  "geometry": {"coordinates":[6.13993,46.203819],"type":"Point"}
}