{
  "type": "Feature",
  "properties": {
    "iso:country":"CH",
    "sg:address":"Schulhausstrasse 34",
    "sg:city":"Walchwil",
    "sg:orig_category":"Markt U Meinungsforschung",
    "sg:phone":"+41 41 758 02 61",
    "sg:postcode":"6318",
    "sg:province":"Zug",
    "wof:name":"Walkers Development Gunkel Dieter",
    "wof:placetype":"venue"
},
  "geometry": {"coordinates":[8.517083168,47.0975379944],"type":"Point"}
}