{
  "type": "Feature",
  "properties": {
    "iso:country":"CH",
    "sg:address":"3674",
    "sg:city":"Bleiken",
    "sg:orig_category":"Sportvereine Sch\u00fctzen",
    "sg:postcode":"3674",
    "sg:province":"Bern",
    "wof:name":"Milit\u00e4rsch\u00fctzengesellschaft",
    "wof:placetype":"venue"
},
  "geometry": {"coordinates":[7.6413598061,46.8179702759],"type":"Point"}
}