{
  "type": "Feature",
  "properties": {
    "iso:country":"CH",
    "sg:address":"Reism\u00fchleweg 52 8409 Hegi (winterthur). Postfach",
    "sg:city":"Winterthur",
    "sg:orig_category":"Detailhandel mit elektrischen Haushalts-,Radio U Fernsehger\u00e4ten sowie Musikinstrumenten",
    "sg:postcode":"8409",
    "sg:province":"Z\u00fcrich",
    "wof:name":"Reco-design, Keller & Vendramini",
    "wof:placetype":"venue"
},
  "geometry": {"coordinates":[8.7701263428,47.5057754517],"type":"Point"}
}