{
  "type": "Feature",
  "properties": {
    "iso:country":"CH",
    "sg:address":"Hauptstrasse 10",
    "sg:city":"Ottoberg",
    "sg:orig_category":"Sanit\u00e4rinstallation Sanit\u00e4rinstallation U Spenglerei",
    "sg:postcode":"8561",
    "sg:province":"Thurgau",
    "wof:name":"Gebr\u00fcder Vogel Sanit\u00e4r Heizungen",
    "wof:placetype":"venue"
},
  "geometry": {"coordinates":[9.0848312378,47.5878944397],"type":"Point"}
}