{
  "type": "Feature",
  "properties": {
    "iso:country":"CH",
    "sg:address":"Simplongasse 4",
    "sg:city":"Frutigen",
    "sg:orig_category":"Grosshandel mit lebenden Tieren",
    "sg:postcode":"3714",
    "sg:province":"Bern",
    "wof:name":"Gotthard Pl\u00fcss-sch\u00e4r",
    "wof:placetype":"venue"
},
  "geometry": {"coordinates":[7.8286399841,47.2406997681],"type":"Point"}
}