{
  "type": "Feature",
  "properties": {
    "iso:country":"CH",
    "sg:address":"Hammerstrasse 7",
    "sg:city":"Steinhausen",
    "sg:orig_category":"Sportvereine Velo Rad-& Motorfahrer-Bund SRB",
    "sg:phone":"+41 41 741 18 27",
    "sg:postcode":"6312",
    "sg:province":"Zug",
    "wof:name":"Velo-club Steinhausen",
    "wof:placetype":"venue"
},
  "geometry": {"coordinates":[8.4839391708,47.1979560852],"type":"Point"}
}