{
  "type": "Feature",
  "properties": {
    "iso:country":"CH",
    "sg:address":"Rathausgasse 23",
    "sg:city":"Lenzburg",
    "sg:orig_category":"RESTAURANTS: TEA-ROOMS",
    "sg:postcode":"5600",
    "sg:province":"Aargau",
    "wof:name":"Cafeteria Rathaus, Noor A.",
    "wof:placetype":"venue"
},
  "geometry": {"coordinates":[8.180513382,47.387462616],"type":"Point"}
}