{
  "type": "Feature",
  "properties": {
    "iso:country":"CH",
    "sg:address":"Unterer Hardeggweg 20",
    "sg:city":"Steffisburg",
    "sg:orig_category":"Gesundheitswesen",
    "sg:phone":"+41 33 437 15 78",
    "sg:postcode":"3612",
    "sg:province":"Bern",
    "wof:name":"Blaser Markus",
    "wof:placetype":"venue"
},
  "geometry": {"coordinates":[7.6198987961,46.7813911438],"type":"Point"}
}