{
  "type": "Feature",
  "properties": {
    "iso:country":"CH",
    "sg:address":"R\u00f6merstrasse West 49",
    "sg:city":"Arch",
    "sg:orig_category":"Automatic Lathes, Automatic Magazine Lathes For Aftertreatment",
    "sg:phone":"+41 32 679 55 30",
    "sg:postcode":"3296",
    "sg:province":"Bern",
    "wof:name":"Junker Swiss Tecnology Ltd",
    "wof:placetype":"venue"
},
  "geometry": {"coordinates":[7.420033,47.164219],"type":"Point"}
}