{
  "type": "Feature",
  "properties": {
    "addr:full":"1165 Allaman Vaud 1165",
    "addr:housenumber":"1165",
    "addr:postcode":"1165",
    "addr:street":"Allaman",
    "iso:country":"CH",
    "sg:address":"1165",
    "sg:city":"Allaman",
    "sg:orig_category":"Detailhandel mit Brot, Back U S\u00fcsswaren",
    "sg:phone":"+41 21 807 30 51",
    "sg:postcode":"1165",
    "sg:province":"Vaud",
    "wof:name":"Jacqueline Racoursier Boulangerie-p\u00e2tisserie",
    "wof:placetype":"venue"
},
  "geometry": {"coordinates":[6.394621,46.471004],"type":"Point"}
}