{
  "type": "Feature",
  "properties": {
    "iso:country":"CH",
    "sg:address":"Hauptstrasse 42 5726 Unterkulm. Postfach 112",
    "sg:city":"Unterkulm",
    "sg:orig_category":"Zimmerei, Dachdeckerei, Bauspenglerei U Abdichtung",
    "sg:postcode":"5726",
    "sg:province":"Aargau",
    "wof:name":"Kaufmann W. Ag",
    "wof:placetype":"venue"
},
  "geometry": {"coordinates":[8.1138648987,47.3129806519],"type":"Point"}
}