{
  "type": "Feature",
  "properties": {
    "iso:country":"CH",
    "sg:address":"Alte Winterthurerstrasse 46",
    "sg:city":"N\u00fcrensdorf",
    "sg:orig_category":"Museen",
    "sg:phone":"+41 18367203",
    "sg:postcode":"8309",
    "sg:province":"Z\u00fcrich",
    "wof:name":"Ortsmuseum N\u00fcrensdorf",
    "wof:placetype":"venue"
},
  "geometry": {"coordinates":[8.6601295471,47.4610481262],"type":"Point"}
}