{
  "type": "Feature",
  "properties": {
    "iso:country":"CH",
    "sg:address":"Lusg\u00e4ssli 12 8880 Walenstadt. Postfach 143",
    "sg:city":"Walenstadt",
    "sg:orig_category":"Sportvereine Fischerei",
    "sg:phone":"+41 56 622 14 15",
    "sg:postcode":"8880",
    "sg:province":"St. Gallen",
    "wof:name":"Sportfischerverein Wohlen",
    "wof:placetype":"venue"
},
  "geometry": {"coordinates":[8.2737455368,47.3513259888],"type":"Point"}
}