{
  "type": "Feature",
  "properties": {
    "iso:country":"CH",
    "sg:address":"Moosstrasse 75",
    "sg:city":"Z\u00fcrich",
    "sg:orig_category":"Werbeagenturen Werbegrafikateliers",
    "sg:phone":"+41 14810414",
    "sg:postcode":"8038",
    "sg:province":"Z\u00fcrich",
    "wof:name":"Eggmann Visuelle Kommunikation",
    "wof:placetype":"venue"
},
  "geometry": {"coordinates":[8.5289449692,47.3351631165],"type":"Point"}
}