{
  "type": "Feature",
  "properties": {
    "iso:country":"CH",
    "sg:address":"Avouillons Route Des 4 1196 Gland Case Postale 202",
    "sg:city":"Gland",
    "sg:orig_category":"Herstellung von konfektionierten Textilwaren ohne Bekleidung",
    "sg:phone":"+41 22 364 22 61",
    "sg:postcode":"1196",
    "sg:province":"Vaud",
    "wof:name":"Starprint Sa Gland",
    "wof:placetype":"venue"
},
  "geometry": {"coordinates":[6.2690029144,46.4162101746],"type":"Point"}
}