{
  "type": "Feature",
  "properties": {
    "iso:country":"CH",
    "sg:address":"Stadthausgasse 1 8200 Schaffhausen. Postfach",
    "sg:city":"Schaffhausen",
    "sg:orig_category":"Architektur U Ingenieurb\u00fcros",
    "sg:postcode":"8200",
    "sg:province":"Schaffhausen",
    "wof:name":"Abakus Architektur + Generalunternehmung, Fertiggaragen, Rauchenstein F.",
    "wof:placetype":"venue"
},
  "geometry": {"coordinates":[8.855991,47.192905],"type":"Point"}
}