{
  "type": "Feature",
  "properties": {
    "iso:country":"CH",
    "sg:address":"Untertalweg 32",
    "sg:city":"Arlesheim",
    "sg:orig_category":"Herstellung von Radio U Fernsehger\u00e4ten sowie phono U videotechnischen Ger\u00e4ten",
    "sg:postcode":"4144",
    "sg:province":"Basel-Landschaft",
    "wof:name":"Gatronic, Gamma G.",
    "wof:placetype":"venue"
},
  "geometry": {"coordinates":[8.2675590515,47.3540267944],"type":"Point"}
}