{
  "type": "Feature",
  "properties": {
    "iso:country":"CH",
    "sg:address":"Eigenackerstrasse 37",
    "sg:city":"Eglisau",
    "sg:orig_category":"Detailhandel mit Beleuchtungs U Haushaltsgegenst\u00e4nden Innendekorationsateliers",
    "sg:phone":"+41 18675020",
    "sg:postcode":"8193",
    "sg:province":"Z\u00fcrich",
    "wof:name":"Giovanna Huber Innendekorationen Vorh\u00e4nge",
    "wof:placetype":"venue"
},
  "geometry": {"coordinates":[8.516361,47.579868],"type":"Point"}
}