{
  "type": "Feature",
  "properties": {
    "iso:country":"CH",
    "sg:address":"Saint-michel Place 1",
    "sg:city":"Martigny",
    "sg:orig_category":"Sonstiges Versicherungsgewerbe",
    "sg:phone":"+41 27 722 25 51",
    "sg:postcode":"1920",
    "sg:province":"Valais",
    "wof:name":"Caisse-maladie Eos",
    "wof:placetype":"venue"
},
  "geometry": {"coordinates":[7.0601267815,46.0884742737],"type":"Point"}
}