{
  "type": "Feature",
  "properties": {
    "iso:country":"CH",
    "sg:address":"Ammerswilerstrasse 445 5704 Egliswil. Postfach",
    "sg:city":"Egliswil",
    "sg:orig_category":"Grosshandel mit Datenverarbeitungsger\u00e4ten Softwareentwicklung U beratung",
    "sg:phone":"+41 71 222 11 10",
    "sg:postcode":"5704",
    "sg:province":"Aargau",
    "wof:name":"Keller Guido, Handel Und Beratung",
    "wof:placetype":"venue"
},
  "geometry": {"coordinates":[9.3851528168,47.4251441956],"type":"Point"}
}