{
  "type": "Feature",
  "properties": {
    "addr:full":"Hauptstr. 36 Bronschhofen St. Gallen 9552",
    "addr:housenumber":"36",
    "addr:postcode":"9552",
    "addr:street":"Hauptstr.",
    "iso:country":"CH",
    "sg:address":"Hauptstr. 36",
    "sg:city":"Bronschhofen",
    "sg:classifiers":[
        {
            "category":"Banks & Credit Unions",
            "subcategory":"Bank",
            "type":"Services"
        }
    ],
    "sg:phone":"+41 71 913 55 55",
    "sg:postcode":"9552",
    "sg:province":"St. Gallen",
    "wof:name":"Raiffeisenbank Wil Und Umgebung",
    "wof:placetype":"venue"
},
  "geometry": {"coordinates":[9.05343,47.462879],"type":"Point"}
}