{
  "type": "Feature",
  "properties": {
    "iso:country":"CH",
    "sg:address":"Obere Hauptgasse 51",
    "sg:city":"Thun",
    "sg:orig_category":"Unclassifiable Establishments",
    "sg:postcode":"3601",
    "sg:province":"Bern",
    "wof:name":"Verein Oeko-laden Thun",
    "wof:placetype":"venue"
},
  "geometry": {"coordinates":[7.6304349899,46.758518219],"type":"Point"}
}