{
  "type": "Feature",
  "properties": {
    "iso:country":"CH",
    "sg:address":"Oberstrasse 3",
    "sg:city":"Herzogenbuchsee",
    "sg:orig_category":"Erbringung von Dienstleistungen f\u00fcr Unternehmen Verlegen von Fussboden",
    "sg:postcode":"3360",
    "sg:province":"Bern",
    "wof:name":"Ren\u00e9 Kern",
    "wof:placetype":"venue"
},
  "geometry": {"coordinates":[7.6689810753,46.7315635681],"type":"Point"}
}