{
  "type": "Feature",
  "properties": {
    "iso:country":"CH",
    "sg:address":"Strassburgerallee 106",
    "sg:city":"Basel",
    "sg:orig_category":"Sanit\u00e4rinstallation Sanit\u00e4rinstallation U Spenglerei",
    "sg:phone":"+41 61 382 68 70",
    "sg:postcode":"4055",
    "sg:province":"Basel-Stadt",
    "wof:name":"Hanauer Sanit\u00e4re Anlagen Spenglerei",
    "wof:placetype":"venue"
},
  "geometry": {"coordinates":[7.5683898926,47.5611877441],"type":"Point"}
}