{
  "type": "Feature",
  "properties": {
    "iso:country":"CH",
    "sg:address":"Kr\u00fcmmenswilerstrasse 53",
    "sg:city":"Krummenau",
    "sg:orig_category":"Handelsvermittlung U Grosshandel",
    "sg:phone":"+41 71 994 29 27",
    "sg:postcode":"9643",
    "sg:province":"St. Gallen",
    "wof:name":"Willy Altenburger Handelsvertretungen",
    "wof:placetype":"venue"
},
  "geometry": {"coordinates":[9.1713256836,47.2484703064],"type":"Point"}
}