{
  "type": "Feature",
  "properties": {
    "iso:country":"CH",
    "sg:address":"Emmetstrasse 22 8303 Bassersdorf. Postfach",
    "sg:city":"Bassersdorf",
    "sg:orig_category":"RESTAURANTS: TEA-ROOMS",
    "sg:postcode":"8303",
    "sg:province":"Z\u00fcrich",
    "wof:name":"Chili Mex, Inhaber Singh Restaurantbetrieb",
    "wof:placetype":"venue"
},
  "geometry": {"coordinates":[8.6240262985,47.4473419189],"type":"Point"}
}