{
  "type": "Feature",
  "properties": {
    "iso:country":"CH",
    "sg:address":"8868",
    "sg:city":"Oberurnen",
    "sg:orig_category":"Sportvereine Sch\u00fctzen",
    "sg:phone":"+41 52 761 18 69",
    "sg:postcode":"8868",
    "sg:province":"Glarus",
    "wof:name":"Feldsch\u00fctzengesellschaft",
    "wof:placetype":"venue"
},
  "geometry": {"coordinates":[9.0593395233,47.1152076721],"type":"Point"}
}