{
  "type": "Feature",
  "properties": {
    "iso:country":"CH",
    "sg:address":"Lindenweg 1",
    "sg:city":"Lenzburg",
    "sg:orig_category":"Verlegen von Fliesen U Platten",
    "sg:phone":"+41 62 891 33 30",
    "sg:postcode":"5600",
    "sg:province":"Aargau",
    "wof:name":"Daniel Hartmann Ofen-& Chemin\u00e9ebau",
    "wof:placetype":"venue"
},
  "geometry": {"coordinates":[8.1715021133,47.3914985657],"type":"Point"}
}