{
  "type": "Feature",
  "properties": {
    "iso:country":"CH",
    "sg:address":"Waaggasse 6",
    "sg:city":"Z\u00fcrich",
    "sg:orig_category":"Kosmetikinstitute",
    "sg:phone":"+41 12210385",
    "sg:postcode":"8001",
    "sg:province":"Z\u00fcrich",
    "wof:name":"Le Salon Ag Kosmetikinstitut",
    "wof:placetype":"venue"
},
  "geometry": {"coordinates":[8.5397510529,47.3702812195],"type":"Point"}
}