{
  "type": "Feature",
  "properties": {
    "iso:country":"CH",
    "sg:address":"Obergasse 7",
    "sg:city":"B\u00fclach",
    "sg:orig_category":"Gold- and Silberschmuck Detailhandel",
    "sg:phone":"+41 18620916",
    "sg:postcode":"8180",
    "sg:province":"Z\u00fcrich",
    "wof:name":"Walter Richard Schumacher Goldschmied",
    "wof:placetype":"venue"
},
  "geometry": {"coordinates":[8.5417966843,47.5182762146],"type":"Point"}
}