{
  "type": "Feature",
  "properties": {
    "addr:full":"Cheleweg 2 Richenthal Luzern 6263",
    "addr:housenumber":"2",
    "addr:postcode":"6263",
    "addr:street":"Cheleweg",
    "iso:country":"CH",
    "sg:address":"Cheleweg 2",
    "sg:city":"Richenthal",
    "sg:orig_category":"Bauspenglerei Dachdeckerei",
    "sg:phone":"+41 32 931 82 23",
    "sg:postcode":"6263",
    "sg:province":"Luzern",
    "wof:name":"Karl Wagner Ferblanterie-couverture",
    "wof:placetype":"venue"
},
  "geometry": {"coordinates":[6.746745,47.056477],"type":"Point"}
}