{
  "type": "Feature",
  "properties": {
    "iso:country":"CH",
    "sg:address":"3236 Gampelen. Postfach",
    "sg:city":"Gampelen",
    "sg:orig_category":"RESTAURANTS: TEA-ROOMS",
    "sg:phone":"+41 32 313 43 73",
    "sg:postcode":"3236",
    "sg:province":"Bern",
    "wof:name":"Marti-iseli Paul",
    "wof:placetype":"venue"
},
  "geometry": {"coordinates":[7.0584812164,47.0145874023],"type":"Point"}
}