{
  "type": "Feature",
  "properties": {
    "iso:country":"CH",
    "sg:address":"Mus\u00e9e Chemin Du 12",
    "sg:city":"Fribourg",
    "sg:orig_category":"Gesundheitswesen",
    "sg:phone":"+41 26 300 85 30",
    "sg:postcode":"1702",
    "sg:province":"Fribourg",
    "wof:name":"Frimorfo Sa",
    "wof:placetype":"venue"
},
  "geometry": {"coordinates":[7.1536831856,46.8037452698],"type":"Point"}
}