{
  "type": "Feature",
  "properties": {
    "iso:country":"CH",
    "sg:address":"Schneit",
    "sg:city":"Ober\u00e4geri",
    "sg:orig_category":"Detailhandel mit Milcherzeugnissen U Eiern Verarbeitung von Milch",
    "sg:phone":"+41 41 750 52 39",
    "sg:postcode":"6315",
    "sg:province":"Zug",
    "wof:name":"Hanspeter Dittli K\u00e4serei",
    "wof:placetype":"venue"
},
  "geometry": {"coordinates":[8.6083106995,47.1381034851],"type":"Point"}
}