{
  "type": "Feature",
  "properties": {
    "iso:country":"CH",
    "sg:address":"Fabrikweg 4",
    "sg:city":"Krummenau",
    "sg:orig_category":"S\u00e4ge, Hobel U Holzimpr\u00e4gnierwerke",
    "sg:phone":"+41 71 466 74 74",
    "sg:postcode":"9643",
    "sg:province":"St. Gallen",
    "wof:name":"Bohag, Holzwaren, Uttwil",
    "wof:placetype":"venue"
},
  "geometry": {"coordinates":[9.1713256836,47.2484703064],"type":"Point"}
}