{
  "type": "Feature",
  "properties": {
    "iso:country":"CH",
    "sg:address":"Baslerstrasse 66 4600 Olten. Postfach",
    "sg:city":"Olten",
    "sg:orig_category":"Versicherungen Generalagenturen",
    "sg:phone":"+41 62 205 19 09",
    "sg:postcode":"4601",
    "sg:province":"Solothurn",
    "wof:name":"National-versicherung Generalagentur",
    "wof:placetype":"venue"
},
  "geometry": {"coordinates":[7.9027481079,47.3527412415],"type":"Point"}
}