{
  "type": "Feature",
  "properties": {
    "iso:country":"CH",
    "sg:address":"Bohnenbergstrasse 11 8212 Neuhausen. Postfach",
    "sg:city":"Neuhausen",
    "sg:orig_category":"Unternehmensberatung",
    "sg:postcode":"8212",
    "sg:province":"Schaffhausen",
    "wof:name":"Wenzler Moni Wirtschaftsberatungen",
    "wof:placetype":"venue"
},
  "geometry": {"coordinates":[8.6159420013,47.6886329651],"type":"Point"}
}