{
  "type": "Feature",
  "properties": {
    "iso:country":"CH",
    "sg:address":"Endingerstrasse 59",
    "sg:city":"W\u00fcrenlingen",
    "sg:orig_category":"G\u00fcterbef\u00f6rderung im Strassenverkehr",
    "sg:phone":"+41 56 281 12 20",
    "sg:postcode":"5303",
    "sg:province":"Aargau",
    "wof:name":"Hans B\u00e4chli Holztransporte",
    "wof:placetype":"venue"
},
  "geometry": {"coordinates":[8.2630195618,47.5298233032],"type":"Point"}
}