{
  "type": "Feature",
  "properties": {
    "iso:country":"CH",
    "sg:address":"Fruthwilerstrasse 26",
    "sg:city":"Ermatingen",
    "sg:orig_category":"Grosshandel mit Nahrungsmitteln, Getr\u00e4nken U Tabakwaren ohne ausgepr\u00e4gten Schwerpunkt Verarbeitung v",
    "sg:phone":"+41 71 664 16 46",
    "sg:postcode":"8272",
    "sg:province":"Thurgau",
    "wof:name":"Werner Hiltbrunner K\u00e4serei",
    "wof:placetype":"venue"
},
  "geometry": {"coordinates":[9.0797119141,47.6672897339],"type":"Point"}
}