{
  "type": "Feature",
  "properties": {
    "iso:country":"CH",
    "sg:address":"Prairie Chemin De La 16 1007 Lausanne. Postfach",
    "sg:city":"Lausanne",
    "sg:orig_category":"Grosshandel mit Textilien",
    "sg:phone":"+41 33 681 29 40",
    "sg:postcode":"1003",
    "sg:province":"Vaud",
    "wof:name":"Mendimotion Gmbh Konsumg\u00fcter, Textilien, Kleidung, Schmuck Usw.; Produktion, Handel, Einkauf/verkauf",
    "wof:placetype":"venue"
},
  "geometry": {"coordinates":[7.8617801666,49.1125106812],"type":"Point"}
}