{
  "type": "Feature",
  "properties": {
    "iso:country":"CH",
    "sg:address":"Gallusstrasse 20",
    "sg:city":"St.gallen",
    "sg:orig_category":"Pensionskassen",
    "sg:phone":"+41 71 227 47 57",
    "sg:postcode":"9000",
    "sg:province":"St. Gallen",
    "wof:name":"Personal-f\u00fcrsorgestiftung Der Leobuchhandlung.",
    "wof:placetype":"venue"
},
  "geometry": {"coordinates":[9.3760995865,47.4233818054],"type":"Point"}
}