{
  "type": "Feature",
  "properties": {
    "iso:country":"CH",
    "sg:address":"Hofackerstrasse 6",
    "sg:city":"B\u00fctschwil",
    "sg:orig_category":"Grosshandel mit sonstigen Maschinen U Ausr\u00fcstungen f\u00fcr Industrie, Handel U Schiffahrt",
    "sg:phone":"+41 71 982 72 70",
    "sg:postcode":"9606",
    "sg:province":"St. Gallen",
    "wof:name":"Omb Reinigungssysteme Ag",
    "wof:placetype":"venue"
},
  "geometry": {"coordinates":[9.0755729675,47.3645820618],"type":"Point"}
}