{
  "type": "Feature",
  "properties": {
    "iso:country":"CH",
    "sg:address":"Badstrasse 43 9230 Flawil. Postfach",
    "sg:city":"Flawil",
    "sg:orig_category":"Vermietung U Verpachtung von eigenen Immobilien Vermittlung von Immobilien",
    "sg:phone":"+41 33 336 48 00",
    "sg:postcode":"9230",
    "sg:province":"St. Gallen",
    "wof:name":"Arpad Immobilien Ag",
    "wof:placetype":"venue"
},
  "geometry": {"coordinates":[7.6166009903,46.7276306152],"type":"Point"}
}