{
  "type": "Feature",
  "properties": {
    "iso:country":"CH",
    "sg:address":"Ausserfeldstrasse 9",
    "sg:city":"Oberentfelden",
    "sg:orig_category":"Detailhandel mit M\u00f6beln U Haushaltsgegenst\u00e4nden Grosshandel mit M\u00f6beln, Wohnbedarf, Teppichen U Bode",
    "sg:phone":"+41 62 724 94 44",
    "sg:postcode":"5036",
    "sg:province":"Aargau",
    "wof:name":"Westana Teppich Ag",
    "wof:placetype":"venue"
},
  "geometry": {"coordinates":[8.056060791,47.3549804688],"type":"Point"}
}