{
  "type": "Feature",
  "properties": {
    "iso:country":"CH",
    "sg:address":"Breiti",
    "sg:city":"Jonschwil",
    "sg:orig_category":"Herstellung von Metallkonstruktionen Stahl U Leichtmetallbau",
    "sg:phone":"+41 71 929 75 75",
    "sg:postcode":"9243",
    "sg:province":"St. Gallen",
    "wof:name":"Eisenring Ag, Jonschwil",
    "wof:placetype":"venue"
},
  "geometry": {"coordinates":[9.1038703918,47.4057540894],"type":"Point"}
}