{
  "type": "Feature",
  "properties": {
    "iso:country":"CH",
    "sg:address":"Alpenstrasse 32",
    "sg:city":"Grenchen",
    "sg:orig_category":"Detailhandel mit Uhren U Schmuck",
    "sg:phone":"+41 32 652 20 22",
    "sg:postcode":"2540",
    "sg:province":"Solothurn",
    "wof:name":"Robert Sch\u00f6nauer Goldschmied",
    "wof:placetype":"venue"
},
  "geometry": {"coordinates":[7.3970661163,47.1989860535],"type":"Point"}
}