{
  "type": "Feature",
  "properties": {
    "iso:country":"CH",
    "sg:address":"Strickstrasse 15",
    "sg:city":"Uster",
    "sg:orig_category":"Architektur U Ingenieurb\u00fcros",
    "sg:phone":"+41 26 913 17 70",
    "sg:postcode":"8610",
    "sg:province":"Z\u00fcrich",
    "wof:name":"Enginews Engineering Workshop Pasquier",
    "wof:placetype":"venue"
},
  "geometry": {"coordinates":[7.057281,46.619877],"type":"Point"}
}