{
  "type": "Feature",
  "properties": {
    "addr:full":"Rappenhalde 21 Effretikon Z\u00fcrich 8307",
    "addr:housenumber":"21",
    "addr:postcode":"8307",
    "addr:street":"Rappenhalde",
    "iso:country":"CH",
    "sg:address":"Rappenhalde 21",
    "sg:city":"Effretikon",
    "sg:classifiers":[
        {
            "category":"Banks & Credit Unions",
            "subcategory":"Bank",
            "type":"Services"
        }
    ],
    "sg:phone":"+41 4152321137",
    "sg:postcode":"8307",
    "sg:province":"Z\u00fcrich",
    "wof:name":"Rentenanstalt Swiss Life",
    "wof:placetype":"venue"
},
  "geometry": {"coordinates":[8.698802,47.421471],"type":"Point"}
}