{
  "type": "Feature",
  "properties": {
    "iso:country":"CH",
    "sg:address":"Sagirain 4",
    "sg:city":"Gutenswil",
    "sg:orig_category":"Bau von Strassen, Sportanlagen U Bahnverkehrsstrecken Strassenbau",
    "sg:phone":"+41 19450913",
    "sg:postcode":"8605",
    "sg:province":"Z\u00fcrich",
    "wof:name":"Rolf Kaufmann Strassenbau Ag",
    "wof:placetype":"venue"
},
  "geometry": {"coordinates":[8.715518,47.385593],"type":"Point"}
}