{
  "type": "Feature",
  "properties": {
    "iso:country":"CH",
    "sg:address":"Widenmatt 46",
    "sg:city":"Malters",
    "sg:orig_category":"Tierarztpraxis",
    "sg:phone":"+41 71 385 02 66",
    "sg:postcode":"6102",
    "sg:province":"Luzern",
    "wof:name":"Dr. Med. Vet. Markus Loretz Tierarzt",
    "wof:placetype":"venue"
},
  "geometry": {"coordinates":[9.274638176,47.4407730103],"type":"Point"}
}