{
  "type": "Feature",
  "properties": {
    "iso:country":"CH",
    "sg:address":"3126",
    "sg:city":"Kaufdorf",
    "sg:orig_category":"Primarschulen",
    "sg:phone":"+41 31 809 04 72",
    "sg:postcode":"3126",
    "sg:province":"Bern",
    "wof:name":"Primarschule",
    "wof:placetype":"venue"
},
  "geometry": {"coordinates":[7.4986290932,46.8381843567],"type":"Point"}
}