{
  "type": "Feature",
  "properties": {
    "iso:country":"CH",
    "sg:address":"Bois-de-menton Ch. Du 19",
    "sg:city":"Epalinges",
    "sg:orig_category":"Grosshandel mit Holz U Baustoffen",
    "sg:phone":"+41 21 784 39 20",
    "sg:postcode":"1066",
    "sg:province":"Vaud",
    "wof:name":"Md Construction Sa Biens Mobiliers Dans Le Dom. De La Construction Etc.; Commerce",
    "wof:placetype":"venue"
},
  "geometry": {"coordinates":[6.6735291481,46.5420646667],"type":"Point"}
}