{
  "type": "Feature",
  "properties": {
    "iso:country":"CH",
    "sg:address":"Obere Reueberg 3",
    "sg:city":"Grossaffoltern",
    "sg:orig_category":"Grosshandel mit Kaffee, Tee, Kakao U Gew\u00fcrzen Sonstiger Grosshandel",
    "sg:phone":"+41 32 389 22 73",
    "sg:postcode":"3257",
    "sg:province":"Bern",
    "wof:name":"Wiedmer Isabelle, Handel + Beratung",
    "wof:placetype":"venue"
},
  "geometry": {"coordinates":[7.3512568474,47.0664901733],"type":"Point"}
}