{
  "type": "Feature",
  "properties": {
    "addr:full":"Seestr. 105 Steckborn Thurgau 8266",
    "addr:housenumber":"105",
    "addr:postcode":"8266",
    "iso:country":"CH",
    "sg:address":"Seestr. 105",
    "sg:city":"Steckborn",
    "sg:classifiers":[
        {
            "category":"Shopping",
            "subcategory":"Clothing, Apparel, & Fashions",
            "type":"Retail Goods"
        }
    ],
    "sg:phone":"+41 52 761 20 84",
    "sg:postcode":"8266",
    "sg:province":"Thurgau",
    "sg:tags":[
        "textile",
        "clothing",
        "clothes"
    ],
    "wof:name":"Boutique Palm-beach",
    "wof:placetype":"venue"
},
  "geometry": {"coordinates":[8.982179,47.667767],"type":"Point"}
}