{
  "type": "Feature",
  "properties": {
    "addr:full":"Erlimattstrasse 2 Sirnach Thurgau 8370",
    "addr:housenumber":"2",
    "addr:postcode":"8370",
    "addr:street":"Erlimattstrasse",
    "iso:country":"CH",
    "sg:address":"Erlimattstrasse 2",
    "sg:city":"Sirnach",
    "sg:orig_category":"Bauspenglerei Sanit\u00e4r, Heizungs U L\u00fcftungsinstallation",
    "sg:phone":"+41 71 966 27 38",
    "sg:postcode":"8370",
    "sg:province":"Thurgau",
    "wof:name":"Weinhappl Roland Ag",
    "wof:placetype":"venue"
},
  "geometry": {"coordinates":[9.003389,47.469223],"type":"Point"}
}