{
  "type": "Feature",
  "properties": {
    "iso:country":"CH",
    "sg:address":"Weierb\u00fchlweg 6",
    "sg:city":"K\u00f6niz",
    "sg:orig_category":"Softwareentwicklung U beratung",
    "sg:phone":"+41 31 972 56 82",
    "sg:postcode":"3098",
    "sg:province":"Bern",
    "wof:name":"Weiss Informatik Gmbh",
    "wof:placetype":"venue"
},
  "geometry": {"coordinates":[7.4119172096,46.9208297729],"type":"Point"}
}