{
  "type": "Feature",
  "properties": {
    "iso:country":"CH",
    "sg:address":"Urtenenweg 15",
    "sg:city":"M\u00fcnchringen",
    "sg:orig_category":"Sportvereine Ballsport Tischtennis",
    "sg:phone":"+41 31 761 00 94",
    "sg:postcode":"3303",
    "sg:province":"Bern",
    "wof:name":"Ttc Mattstetten",
    "wof:placetype":"venue"
},
  "geometry": {"coordinates":[7.5202269554,47.0473518372],"type":"Point"}
}