{
  "type": "Feature",
  "properties": {
    "iso:country":"CH",
    "sg:address":"Bahnhofplatz",
    "sg:city":"Thusis",
    "sg:orig_category":"Vereine Frauen Vereine Gemeinn\u00fctzige",
    "sg:postcode":"7430",
    "sg:province":"Graubunden",
    "wof:name":"Coop Frauenbund Fk Aarau",
    "wof:placetype":"venue"
},
  "geometry": {"coordinates":[8.2780599594,47.350528717],"type":"Point"}
}