{
  "type": "Feature",
  "properties": {
    "addr:full":"Kapuzinerstrasse 11 4500 Solothurn. Postfach Solothurn Solothurn 4501",
    "addr:housenumber":"11",
    "addr:postcode":"4500 solothurn. postfach;4501",
    "addr:street":"Kapuzinerstrasse",
    "iso:country":"CH",
    "sg:address":"Kapuzinerstrasse 11 4500 Solothurn. Postfach",
    "sg:city":"Solothurn",
    "sg:orig_category":"Architektur U Ingenieurb\u00fcros Unternehmensberatung",
    "sg:phone":"+41 32 623 36 45",
    "sg:postcode":"4501",
    "sg:province":"Solothurn",
    "wof:name":"Dbi Dienstleistungs- Beratungen Mosconi & Co",
    "wof:placetype":"venue"
},
  "geometry": {"coordinates":[7.532896,47.210392],"type":"Point"}
}