{
  "type": "Feature",
  "properties": {
    "iso:country":"CH",
    "sg:address":"Viale Stefano Franscini 1",
    "sg:city":"Lugano",
    "sg:orig_category":"Unclassifiable Establishments",
    "sg:phone":"+41 17133606",
    "sg:postcode":"6900",
    "sg:province":"Ticino",
    "wof:name":"Dajoeri Ag Panfl\u00f6tenschule",
    "wof:placetype":"venue"
},
  "geometry": {"coordinates":[8.5374956131,47.282371521],"type":"Point"}
}