{
  "type": "Feature",
  "properties": {
    "iso:country":"CH",
    "sg:address":"Route De Chancy 28 1213 Petit-lancy Case Postale Case Postale 302",
    "sg:city":"Petit-lancy",
    "sg:orig_category":"Arztpraxen",
    "sg:phone":"+41 22 735 21 78",
    "sg:postcode":"1213",
    "sg:province":"Gen\u00e8ve",
    "wof:name":"Dr M\u00e9d. Liliane Nasi M\u00e9decin G\u00e9n\u00e9raliste",
    "wof:placetype":"venue"
},
  "geometry": {"coordinates":[6.119057,46.190388],"type":"Point"}
}