{
  "type": "Feature",
  "properties": {
    "iso:country":"CH",
    "sg:address":"Franziskanerstrasse 22",
    "sg:city":"Bellach",
    "sg:orig_category":"G\u00fcterbef\u00f6rderung im Strassenverkehr",
    "sg:phone":"+41 32 618 12 52",
    "sg:postcode":"4512",
    "sg:province":"Solothurn",
    "wof:name":"Steffen Max Transporte",
    "wof:placetype":"venue"
},
  "geometry": {"coordinates":[7.511703968,47.2132415771],"type":"Point"}
}