{
  "type": "Feature",
  "properties": {
    "iso:country":"CH",
    "sg:address":"Kannenb\u00fchlstrasse 28",
    "sg:city":"Hochdorf",
    "sg:orig_category":"Bauschreinerei",
    "sg:phone":"+41 41 930 11 51",
    "sg:postcode":"6280",
    "sg:province":"Luzern",
    "wof:name":"Hugo Baumgartner Kundenschreinerei",
    "wof:placetype":"venue"
},
  "geometry": {"coordinates":[8.293304,47.172611],"type":"Point"}
}