{
  "type": "Feature",
  "properties": {
    "iso:country":"CH",
    "sg:address":"B\u00fcfigstrasse 4",
    "sg:city":"Sch\u00fcpfheim",
    "sg:classifiers":[
        {
            "category":"Insurance",
            "subcategory":"Insurance Agent",
            "type":"Services"
        }
    ],
    "sg:phone":"+41 41 484 15 37",
    "sg:postcode":"6170",
    "sg:province":"Luzern",
    "sg:tags":[
        "versicherungsagenturen",
        "-broker"
    ],
    "wof:name":"La Suisse Versicherungen Agentur Amt Entlebuch",
    "wof:placetype":"venue"
},
  "geometry": {"coordinates":[8.0237512589,46.9534187317],"type":"Point"}
}