{
  "type": "Feature",
  "properties": {
    "iso:country":"CH",
    "sg:address":"Schorenweg 15 4058 Basel. Postfach",
    "sg:city":"Basel",
    "sg:orig_category":"Handels-H\u00e4user U Gesellschaften",
    "sg:postcode":"4051",
    "sg:province":"Basel-Stadt",
    "wof:name":"Handelsagentur Erismann R.",
    "wof:placetype":"venue"
},
  "geometry": {"coordinates":[8.8157396317,47.2264938354],"type":"Point"}
}