{
  "type": "Feature",
  "properties": {
    "iso:country":"CH",
    "sg:address":"Austrasse 58 4051 Basel. Postfach",
    "sg:city":"Basel",
    "sg:orig_category":"M\u00f6belschreinereien",
    "sg:phone":"+41 61 271 84 34",
    "sg:postcode":"4051",
    "sg:province":"Basel-Stadt",
    "wof:name":"Inside, Jakob & Partner, Atelier F\u00fcr Individuelle Raumgestaltung M\u00f6bel, Artikel D. Inneneinrichtung; Im, Export, Fabr, Vertrieb",
    "wof:placetype":"venue"
},
  "geometry": {"coordinates":[7.581223011,47.5540237427],"type":"Point"}
}