{
  "type": "Feature",
  "properties": {
    "iso:country":"CH",
    "sg:address":"Holzackerstrasse 290",
    "sg:city":"Full-reuenthal",
    "sg:orig_category":"Haltung von Schweinen",
    "sg:phone":"+41 56 246 19 86",
    "sg:postcode":"5324",
    "sg:province":"Aargau",
    "wof:name":"Walter Thalmann Schweinem\u00e4sterei",
    "wof:placetype":"venue"
},
  "geometry": {"coordinates":[8.2054214478,47.6001014709],"type":"Point"}
}