{
  "type": "Feature",
  "properties": {
    "iso:country":"CH",
    "sg:address":"Rietzaunstrasse 2",
    "sg:city":"Grabs",
    "sg:orig_category":"Allgemeiner Hoch U Tiefbau",
    "sg:phone":"+41 81 771 42 42",
    "sg:postcode":"9472",
    "sg:province":"St. Gallen",
    "wof:name":"Bts Ag",
    "wof:placetype":"venue"
},
  "geometry": {"coordinates":[9.448858,47.186161],"type":"Point"}
}