{
  "type": "Feature",
  "properties": {
    "iso:country":"CH",
    "sg:address":"G\u00fcrtelstrasse 14 7000 Chur. Postfach",
    "sg:city":"Chur",
    "sg:orig_category":"Non-Classified Establishments",
    "sg:postcode":"7000",
    "sg:province":"Graubunden",
    "wof:name":"Akina Holding",
    "wof:placetype":"venue"
},
  "geometry": {"coordinates":[9.5274496078,46.8524703979],"type":"Point"}
}