{
  "type": "Feature",
  "properties": {
    "iso:country":"CH",
    "sg:address":"Luisenstrasse 40 8005 Z\u00fcrich. Postfach",
    "sg:city":"Z\u00fcrich",
    "sg:orig_category":"RESTAURANTS: TEA-ROOMS",
    "sg:phone":"+41 12713740",
    "sg:postcode":"8036",
    "sg:province":"Z\u00fcrich",
    "wof:name":"La Cucina Gastro Gmbh Restaurants Usw",
    "wof:placetype":"venue"
},
  "geometry": {"coordinates":[8.530412674,47.3841552734],"type":"Point"}
}