{
  "type": "Feature",
  "properties": {
    "iso:country":"CH",
    "sg:address":"Fruthwilerstrasse 5",
    "sg:city":"Ermatingen",
    "sg:orig_category":"Primarschulen",
    "sg:phone":"+41 71 664 22 46",
    "sg:postcode":"8272",
    "sg:province":"Thurgau",
    "wof:name":"Primarschule Ermatingen",
    "wof:placetype":"venue"
},
  "geometry": {"coordinates":[9.0802774429,47.668838501],"type":"Point"}
}