{
  "type": "Feature",
  "properties": {
    "iso:country":"CH",
    "sg:address":"Kantonsstrasse 33c",
    "sg:city":"Freienbach",
    "sg:orig_category":"Grosshandel mit Textilien Grosshandel mit sonstigen Konsumg\u00fctern",
    "sg:phone":"+41 55 410 14 07",
    "sg:postcode":"8807",
    "sg:province":"Schwyz",
    "wof:name":"Rentsch & Co",
    "wof:placetype":"venue"
},
  "geometry": {"coordinates":[8.7488136292,47.2061882019],"type":"Point"}
}