{
  "type": "Feature",
  "properties": {
    "iso:country":"CH",
    "sg:address":"Route Aloys-fauquez 130 1000 Lausanne. Postfach",
    "sg:city":"Lausanne",
    "sg:orig_category":"Grosshandel mit sonstigen Gebrauchs U Verbrauchsg\u00fctern",
    "sg:postcode":"1002",
    "sg:province":"Vaud",
    "wof:name":"S & P Trading, Chevalier Samira",
    "wof:placetype":"venue"
},
  "geometry": {"coordinates":[6.6337552071,46.5417404175],"type":"Point"}
}