{
  "type": "Feature",
  "properties": {
    "iso:country":"CH",
    "sg:address":"3963",
    "sg:city":"Crans-sur-sierre",
    "sg:classifiers":[
        {
            "category":"Travel",
            "subcategory":"Hotels & Motels",
            "type":"Entertainment"
        }
    ],
    "sg:phone":"+41 27 281 15 75",
    "sg:postcode":"3963",
    "sg:province":"Valais",
    "sg:tags":[
        "hotels",
        "mit",
        "restaurant"
    ],
    "wof:name":"H\u00f4tel Sporting",
    "wof:placetype":"venue"
},
  "geometry": {"coordinates":[7.3860898018,46.184841156],"type":"Point"}
}