{
  "type": "Feature",
  "properties": {
    "iso:country":"CH",
    "sg:address":"Bahnhofstrasse 15 3904 Naters. Postfach",
    "sg:city":"Naters",
    "sg:orig_category":"Softwareentwicklung U beratung",
    "sg:phone":"+41 79 286 77 19",
    "sg:postcode":"3904",
    "sg:province":"Valais",
    "wof:name":"Sos-pc, Favre Nicolas",
    "wof:placetype":"venue"
},
  "geometry": {"coordinates":[6.7701849937,46.5957489014],"type":"Point"}
}