{
  "type": "Feature",
  "properties": {
    "iso:country":"CH",
    "sg:address":"Drize Route De 73",
    "sg:city":"Vessy",
    "sg:orig_category":"Non-Classified Establishments",
    "sg:postcode":"1234",
    "sg:province":"Gen\u00e8ve",
    "wof:name":"Bev Immobilien Ag",
    "wof:placetype":"venue"
},
  "geometry": {"coordinates":[8.7607221603,47.4835586548],"type":"Point"}
}