{
  "type": "Feature",
  "properties": {
    "iso:country":"CH",
    "sg:address":"Louye Chemin De La",
    "sg:city":"Vufflens-ch\u00e2teau",
    "sg:orig_category":"Herstellung von medizinischen U chirurgischen Ger\u00e4ten sowie orthop\u00e4dischen Vorrichtungen",
    "sg:postcode":"1134",
    "sg:province":"Vaud",
    "wof:name":"Cbm Cybermed Sa",
    "wof:placetype":"venue"
},
  "geometry": {"coordinates":[-96.83545684809999,43.4464607239],"type":"Point"}
}