{
  "type": "Feature",
  "properties": {
    "iso:country":"CH",
    "sg:address":"Meikirchstrasse 38 3045 Meikirch. Postfach",
    "sg:city":"Meikirch",
    "sg:orig_category":"Herstellung von Konstruktionsteilen, Fertigbauteilen U Ausbauelementen aus Holz",
    "sg:postcode":"3045",
    "sg:province":"Bern",
    "wof:name":"Sommer + Jenni Gebr. Ag Schreinerei",
    "wof:placetype":"venue"
},
  "geometry": {"coordinates":[7.3968410492,46.9959106445],"type":"Point"}
}