{
  "type": "Feature",
  "properties": {
    "iso:country":"CH",
    "sg:address":"M\u00fchlig\u00e4ssli 10",
    "sg:city":"Allschwil",
    "sg:orig_category":"Physiotherapie",
    "sg:phone":"+41 61 481 90 86",
    "sg:postcode":"4123",
    "sg:province":"Basel-Landschaft",
    "wof:name":"Esther Schilling Physiotherapie",
    "wof:placetype":"venue"
},
  "geometry": {"coordinates":[7.5353369713,47.5489082336],"type":"Point"}
}