{
  "type": "Feature",
  "properties": {
    "iso:country":"CH",
    "sg:address":"Via Pocobelli 15",
    "sg:city":"Melide",
    "sg:orig_category":"Medizinische Labors",
    "sg:phone":"+41 91 649 94 80",
    "sg:postcode":"6815",
    "sg:province":"Ticino",
    "wof:name":"Galeno Labor Sa Prodotti Farmaceutici",
    "wof:placetype":"venue"
},
  "geometry": {"coordinates":[8.9473114014,45.9546012878],"type":"Point"}
}