{
  "type": "Feature",
  "properties": {
    "iso:country":"CH",
    "sg:address":"Campeun Via",
    "sg:city":"Rh\u00e4z\u00fcns",
    "sg:orig_category":"Maler U Glasergewerbe",
    "sg:phone":"+41 79 446 15 25",
    "sg:postcode":"7403",
    "sg:province":"Graubunden",
    "wof:name":"Ciaccio Angelo",
    "wof:placetype":"venue"
},
  "geometry": {"coordinates":[6.8480401039,47.0920448303],"type":"Point"}
}