{
  "type": "Feature",
  "properties": {
    "iso:country":"CH",
    "sg:address":"Grand-pont 24",
    "sg:city":"Sion",
    "sg:classifiers":[
        {
            "category":"Restaurant",
            "type":"Food & Drink"
        }
    ],
    "sg:phone":"+41 27 322 47 09",
    "sg:postcode":"1950",
    "sg:province":"Valais",
    "wof:name":"Caf\u00e9 Grenette",
    "wof:placetype":"venue"
},
  "geometry": {"coordinates":[7.3605709076,46.2344589233],"type":"Point"}
}