{
  "type": "Feature",
  "properties": {
    "iso:country":"CH",
    "sg:address":"Rue De La Plaine 34",
    "sg:city":"Yverdon-les-bains",
    "sg:orig_category":"Stukkateurgewerbe, Gipserei U Verputzerei",
    "sg:postcode":"1400",
    "sg:province":"Vaud",
    "wof:name":"Scheidegger, Marcel",
    "wof:placetype":"venue"
},
  "geometry": {"coordinates":[6.6437029839,46.7772293091],"type":"Point"}
}