{
  "type": "Feature",
  "properties": {
    "addr:full":"Endweg Grindelwald Bern 3818",
    "addr:postcode":"3818",
    "addr:street":"Endweg",
    "iso:country":"CH",
    "sg:address":"Endweg",
    "sg:city":"Grindelwald",
    "sg:orig_category":"Arztpraxen",
    "sg:phone":"+41 33 854 10 10",
    "sg:postcode":"3818",
    "sg:province":"Bern",
    "wof:name":"Dres Med. B. & T. Haefeli Spezial\u00e4rzte Fmh",
    "wof:placetype":"venue"
},
  "geometry": {"coordinates":[8.0293,46.621513],"type":"Point"}
}