{
  "type": "Feature",
  "properties": {
    "iso:country":"CH",
    "sg:address":"Rue Fr\u00e9d\u00e9ric-soguel 4 2053 Cernier Case Postale",
    "sg:city":"Cernier",
    "sg:orig_category":"Fachdetailhandel mit pharmazeutischen Produkten",
    "sg:postcode":"2053",
    "sg:province":"Neuch\u00e2tel",
    "wof:name":"Marti Fr\u00e9d\u00e9ric Et Ariane Pharmacie-droguerie",
    "wof:placetype":"venue"
},
  "geometry": {"coordinates":[6.9012618065,47.0589103699],"type":"Point"}
}