{
  "type": "Feature",
  "properties": {
    "iso:country":"CH",
    "sg:address":"Sch\u00f6nb\u00fchlstrand 18",
    "sg:city":"Luzern",
    "sg:orig_category":"Unternehmensberatung",
    "sg:phone":"+41 79 437 86 80",
    "sg:postcode":"6005",
    "sg:province":"Luzern",
    "wof:name":"Zwicky Unternehmensberatung Ag",
    "wof:placetype":"venue"
},
  "geometry": {"coordinates":[8.7505187988,47.306678772],"type":"Point"}
}