{
  "type": "Feature",
  "properties": {
    "iso:country":"CH",
    "sg:address":"Gotthardstrasse 84",
    "sg:city":"Erstfeld",
    "sg:orig_category":"HOTELS: MIT RESTAURANT Kongress- and Tagungshotels mit Restaurant",
    "sg:phone":"+41 81 322 44 35",
    "sg:postcode":"6472",
    "sg:province":"Uri",
    "wof:name":"Hotel F\u00fcnf D\u00f6rfer",
    "wof:placetype":"venue"
},
  "geometry": {"coordinates":[9.5585346222,46.9340286255],"type":"Point"}
}