{
  "type": "Feature",
  "properties": {
    "iso:country":"CH",
    "sg:address":"Friedheim",
    "sg:city":"Seelisberg",
    "sg:orig_category":"Bauschreinerei Herstellung von Konstruktionsteilen, Fertigbauteilen U Ausbauelementen aus Holz",
    "sg:phone":"+41 41 820 16 76",
    "sg:postcode":"6377",
    "sg:province":"Uri",
    "wof:name":"Zwyssig Werner.",
    "wof:placetype":"venue"
},
  "geometry": {"coordinates":[8.58538,46.974854],"type":"Point"}
}