{
  "type": "Feature",
  "properties": {
    "iso:country":"CH",
    "sg:address":"Wehntalerstrasse 585",
    "sg:city":"Z\u00fcrich",
    "sg:orig_category":"Tankstellen",
    "sg:postcode":"8046",
    "sg:province":"Z\u00fcrich",
    "wof:name":"Stanulov Veselin Servicestation, Autoreparatur, Elektrowerkst\u00e4tte",
    "wof:placetype":"venue"
},
  "geometry": {"coordinates":[8.5029163361,47.4203567505],"type":"Point"}
}