{
  "type": "Feature",
  "properties": {
    "iso:country":"CH",
    "sg:address":"Dickistrasse 2",
    "sg:city":"Hallau",
    "sg:orig_category":"Lagerung Mahl U Sch\u00e4lm\u00fchlen",
    "sg:phone":"+41 52 681 38 17",
    "sg:postcode":"8215",
    "sg:province":"Schaffhausen",
    "wof:name":"L\u00fcscher Gmbh Neum\u00fchle",
    "wof:placetype":"venue"
},
  "geometry": {"coordinates":[8.4683742523,47.6922187805],"type":"Point"}
}