{
  "type": "Feature",
  "properties": {
    "iso:country":"CH",
    "sg:address":"Rieden 4",
    "sg:city":"Stans",
    "sg:orig_category":"Sonstiger Grosshandel",
    "sg:phone":"+41 56 282 46 07",
    "sg:postcode":"6370",
    "sg:province":"Nidwalden",
    "wof:name":"Washington Walter Industrial Trading Enterprise",
    "wof:placetype":"venue"
},
  "geometry": {"coordinates":[8.2963380814,47.4878044128],"type":"Point"}
}