{
  "type": "Feature",
  "properties": {
    "iso:country":"CH",
    "sg:address":"Hostalenweg 37 3037 Herrenschwanden. Postfach",
    "sg:city":"Herrenschwanden",
    "sg:orig_category":"Mit dem Versicherungsgewerbe verbundene T\u00e4tigkeiten",
    "sg:phone":"+41 31 302 85 51",
    "sg:postcode":"3037",
    "sg:province":"Bern",
    "wof:name":"Bvv Gmbh",
    "wof:placetype":"venue"
},
  "geometry": {"coordinates":[7.4180898666,46.9780311584],"type":"Point"}
}