{
  "type": "Feature",
  "properties": {
    "iso:country":"CH",
    "sg:address":"Kanalstrasse 9",
    "sg:city":"Montlingen",
    "sg:orig_category":"Elektrizit\u00e4tsversorgung",
    "sg:phone":"+41 71 763 71 50",
    "sg:postcode":"9462",
    "sg:province":"St. Gallen",
    "wof:name":"St. Gallisch-appenzellische Kraftwerke Ag Sak Sak Regionalvertretung",
    "wof:placetype":"venue"
},
  "geometry": {"coordinates":[9.5793371201,47.3323898315],"type":"Point"}
}