{
  "type": "Feature",
  "properties": {
    "iso:country":"CH",
    "sg:address":"Fuchsiastrasse 10",
    "sg:city":"Z\u00fcrich",
    "sg:classifiers":[
        {
            "category":"Professional",
            "subcategory":"Engineering",
            "type":"Services"
        }
    ],
    "sg:phone":"+41 21 317 59 00",
    "sg:postcode":"8048",
    "sg:province":"Z\u00fcrich",
    "sg:tags":[
        "technical",
        "personnel",
        "high-qualified",
        "temporary"
    ],
    "wof:name":"Denial Ressources Humaines",
    "wof:placetype":"venue"
},
  "geometry": {"coordinates":[6.6795787811,46.5386009216],"type":"Point"}
}