{
  "type": "Feature",
  "properties": {
    "iso:country":"CH",
    "sg:address":"Dr\u00f4ne",
    "sg:city":"Chandolin-savi\u00e8se",
    "sg:orig_category":"Sportvereine P\u00e9tanque",
    "sg:postcode":"1965",
    "sg:province":"Valais",
    "wof:name":"P\u00e9tanque-club La Savi\u00e8sanne",
    "wof:placetype":"venue"
},
  "geometry": {"coordinates":[7.3653569221,46.2585906982],"type":"Point"}
}