{
  "type": "Feature",
  "properties": {
    "iso:country":"CH",
    "sg:address":"Hauptstrasse 74",
    "sg:city":"M\u00fcnchenstein",
    "sg:orig_category":"Sonstiger Fachdetailhandel in Verkaufsr\u00e4umen Versandhandel",
    "sg:phone":"+41 61 411 33 52",
    "sg:postcode":"4142",
    "sg:province":"Basel-Landschaft",
    "wof:name":"Philatelie-versand Peter Graf",
    "wof:placetype":"venue"
},
  "geometry": {"coordinates":[7.6201968193,47.5092811584],"type":"Point"}
}