{
  "type": "Feature",
  "properties": {
    "iso:country":"CH",
    "sg:address":"Steinenbruggstrasse 3",
    "sg:city":"Reichenburg",
    "sg:orig_category":"Zimmerei, Ingenieurholzbau",
    "sg:phone":"+41 55 444 22 42",
    "sg:postcode":"8864",
    "sg:province":"Schwyz",
    "wof:name":"Anton Diethelm Holzbau",
    "wof:placetype":"venue"
},
  "geometry": {"coordinates":[8.9807348251,47.1723442078],"type":"Point"}
}