{
  "type": "Feature",
  "properties": {
    "iso:country":"CH",
    "sg:address":"Sempacherstrasse 1",
    "sg:city":"Luzern",
    "sg:orig_category":"Unternehmensberatung Wirtschaftspr\u00fcfung, Steuerberatung U Treuhand",
    "sg:phone":"+41 41 226 61 41",
    "sg:postcode":"6003",
    "sg:province":"Luzern",
    "wof:name":"Modena & Partner Ag",
    "wof:placetype":"venue"
},
  "geometry": {"coordinates":[8.307179451,47.0491943359],"type":"Point"}
}