{
  "type": "Feature",
  "properties": {
    "iso:country":"CH",
    "sg:address":"Pozzolo Vicolo 1",
    "sg:city":"Vacallo",
    "sg:orig_category":"Unclassifiable Establishments",
    "sg:postcode":"6833",
    "sg:province":"Ticino",
    "wof:name":"Fondazione Luigi (gino) Pagliarani",
    "wof:placetype":"venue"
},
  "geometry": {"coordinates":[9.0364618301,45.8480644226],"type":"Point"}
}