{
  "type": "Feature",
  "properties": {
    "iso:country":"CH",
    "sg:address":"Hauptstrasse 115 4450 Sissach. Postfach",
    "sg:city":"Sissach",
    "sg:orig_category":"Verwaltung der Rechtspflege, Gerichte",
    "sg:phone":"+41 61 976 11 00",
    "sg:postcode":"4450",
    "sg:province":"Basel-Landschaft",
    "wof:name":"Grundbuchamt Des Bezirkes Sissach",
    "wof:placetype":"venue"
},
  "geometry": {"coordinates":[7.8081660271,47.4647293091],"type":"Point"}
}