{
  "type": "Feature",
  "properties": {
    "iso:country":"CH",
    "sg:address":"Kirschetmatte 9 6373 Ennetb\u00fcrgen. Postfach 236",
    "sg:city":"Ennetb\u00fcrgen",
    "sg:orig_category":"Grosshandel mit sonstigen Halbwaren",
    "sg:phone":"+41 41 620 53 50",
    "sg:postcode":"6373",
    "sg:province":"Nidwalden",
    "wof:name":"Europac Ag",
    "wof:placetype":"venue"
},
  "geometry": {"coordinates":[8.4187898636,46.9898796082],"type":"Point"}
}