{
  "type": "Feature",
  "properties": {
    "iso:country":"CH",
    "sg:address":"Les Fangu\u00e9s",
    "sg:city":"St-l\u00e9onard",
    "sg:orig_category":"Detailhandel mit elektrischen Haushalts-,Radio U Fernsehger\u00e4ten sowie Musikinstrumenten",
    "sg:postcode":"1958",
    "sg:province":"Valais",
    "wof:name":"C.b. C\u00e9ramique De Boh\u00e8me, Balzacchi Thierry",
    "wof:placetype":"venue"
},
  "geometry": {"coordinates":[7.4241948128,46.2517967224],"type":"Point"}
}