{
  "type": "Feature",
  "properties": {
    "iso:country":"CH",
    "sg:address":"B\u00e4umleingasse 6",
    "sg:city":"Basel",
    "sg:orig_category":"Detailhandel mit Geschenkartikeln U Souvenirs",
    "sg:phone":"+41 61 272 77 22",
    "sg:postcode":"4051",
    "sg:province":"Basel-Stadt",
    "wof:name":"Capaul Ren\u00e9 Ag Warenhandel Bes. Mit Damen- U. Herrenbekleidung Usw",
    "wof:placetype":"venue"
},
  "geometry": {"coordinates":[7.5920329094,47.5546875],"type":"Point"}
}