{
  "type": "Feature",
  "properties": {
    "iso:country":"CH",
    "sg:address":"Dumas Avenue 21a 1206 Gen\u00e8ve. Postfach",
    "sg:city":"Gen\u00e8ve",
    "sg:orig_category":"Non-Classified Establishments",
    "sg:postcode":"1201",
    "sg:province":"Gen\u00e8ve",
    "wof:name":"Si Les Petites Fontaines",
    "wof:placetype":"venue"
},
  "geometry": {"coordinates":[6.1560759544,46.1911849976],"type":"Point"}
}