{
  "type": "Feature",
  "properties": {
    "iso:country":"CH",
    "sg:address":"Heldstrasse 35",
    "sg:city":"Widnau",
    "sg:classifiers":[
        {
            "category":"Professional",
            "subcategory":"Advertising",
            "type":"Services"
        }
    ],
    "sg:phone":"+41 71 722 52 58",
    "sg:postcode":"9443",
    "sg:province":"St. Gallen",
    "sg:tags":[
        "ball",
        "pens",
        "point",
        "utensil",
        "writing",
        "purpose"
    ],
    "wof:name":"B & O Gmbh",
    "wof:placetype":"venue"
},
  "geometry": {"coordinates":[9.634892,47.397839],"type":"Point"}
}