{
  "type": "Feature",
  "properties": {
    "iso:country":"CH",
    "sg:address":"Lagerhausstrasse 1",
    "sg:city":"Solothurn",
    "sg:orig_category":"Allgemeinbildende weiterf\u00fchrende Schulen",
    "sg:phone":"+41 32 621 26 30",
    "sg:postcode":"4500",
    "sg:province":"Solothurn",
    "wof:name":"Sil Boll",
    "wof:placetype":"venue"
},
  "geometry": {"coordinates":[7.533651,47.206394],"type":"Point"}
}