{
  "type": "Feature",
  "properties": {
    "iso:country":"CH",
    "sg:address":"Via Vela 5",
    "sg:city":"Bellinzona",
    "sg:orig_category":"Herstellung von Teigwaren",
    "sg:phone":"+41 62 836 25 55",
    "sg:postcode":"6500",
    "sg:province":"Ticino",
    "wof:name":"Jowa Pasta Buchs Ag",
    "wof:placetype":"venue"
},
  "geometry": {"coordinates":[8.075630188,47.3880691528],"type":"Point"}
}