{
  "type": "Feature",
  "properties": {
    "iso:country":"CH",
    "sg:address":"Industriepark Asp",
    "sg:city":"Spreitenbach",
    "sg:orig_category":"Herstellung von Karosserien U Anh\u00e4ngern Vermietung von sonstigen Landfahrzeugen",
    "sg:phone":"+41 56 401 29 29",
    "sg:postcode":"8957",
    "sg:province":"Aargau",
    "wof:name":"Schneider Caravancenter Ag",
    "wof:placetype":"venue"
},
  "geometry": {"coordinates":[8.3680782318,47.4252662659],"type":"Point"}
}