{
  "type": "Feature",
  "properties": {
    "iso:country":"CH",
    "sg:address":"Hallwylstrasse 19",
    "sg:city":"Romanshorn",
    "sg:orig_category":"Herstellung von konfektionierten Textilwaren ohne Bekleidung Herstellung von sonstigen konfektionier",
    "sg:phone":"+41 71 463 17 66",
    "sg:postcode":"8590",
    "sg:province":"Thurgau",
    "wof:name":"Huber Emil, Inh. K. Maag",
    "wof:placetype":"venue"
},
  "geometry": {"coordinates":[9.3695926666,47.5606994629],"type":"Point"}
}