{
  "type": "Feature",
  "properties": {
    "iso:country":"CH",
    "sg:address":"Rebacker",
    "sg:city":"Wallbach",
    "sg:orig_category":"Fachdetailhandel in Verkaufsr\u00e4umen",
    "sg:postcode":"4323",
    "sg:province":"Aargau",
    "wof:name":"Amazonas-vivarium Ramseier J. + M.",
    "wof:placetype":"venue"
},
  "geometry": {"coordinates":[7.9459810257,47.54139328],"type":"Point"}
}