{
  "type": "Feature",
  "properties": {
    "iso:country":"CH",
    "sg:address":"6442",
    "sg:city":"Gersau",
    "sg:orig_category":"Schulpflegen",
    "sg:postcode":"6442",
    "sg:province":"Schwyz",
    "wof:name":"Schulrat Des Bezirks Oberrheintal",
    "wof:placetype":"venue"
},
  "geometry": {"coordinates":[9.549697876,47.375202179],"type":"Point"}
}