{
  "type": "Feature",
  "properties": {
    "iso:country":"CH",
    "sg:address":"Dielsdorferstrasse 172",
    "sg:city":"Niederhasli",
    "sg:orig_category":"Haltung von Schafen, Ziegen, Pferden U Eseln",
    "sg:phone":"+41 18501930",
    "sg:postcode":"8155",
    "sg:province":"Z\u00fcrich",
    "wof:name":"Schwindibode Ag",
    "wof:placetype":"venue"
},
  "geometry": {"coordinates":[8.4792118073,47.4820518494],"type":"Point"}
}