{
  "type": "Feature",
  "properties": {
    "iso:country":"CH",
    "sg:address":"Dorfstrasse 16",
    "sg:city":"Brittnau",
    "sg:orig_category":"Detailhandel mit Schreib U Papeteriewaren Detailhandel mit Tabakwaren",
    "sg:phone":"+41 62 752 14 04",
    "sg:postcode":"4805",
    "sg:province":"Aargau",
    "wof:name":"Marlise W\u00fcest-leu",
    "wof:placetype":"venue"
},
  "geometry": {"coordinates":[7.9474458694,47.2595062256],"type":"Point"}
}