{
  "type": "Feature",
  "properties": {
    "iso:country":"CH",
    "sg:address":"Avenue G\u00e9n\u00e9ral-guisan 41",
    "sg:city":"Rolle",
    "sg:orig_category":"Softwareentwicklung U beratung",
    "sg:postcode":"1180",
    "sg:province":"Vaud",
    "wof:name":"Igetech E. Favre",
    "wof:placetype":"venue"
},
  "geometry": {"coordinates":[6.3300180435,46.455997467],"type":"Point"}
}