{
  "type": "Feature",
  "properties": {
    "iso:country":"CH",
    "sg:address":"Albisstrasse 60",
    "sg:city":"Z\u00fcrich",
    "sg:orig_category":"Elektroinstallation",
    "sg:phone":"+41 14822085",
    "sg:postcode":"8038",
    "sg:province":"Z\u00fcrich",
    "wof:name":"Trachsler + Co Kaminfegergesch\u00e4ft",
    "wof:placetype":"venue"
},
  "geometry": {"coordinates":[8.5307102203,47.3426856995],"type":"Point"}
}