{
  "type": "Feature",
  "properties": {
    "iso:country":"CH",
    "sg:address":"Honerethof 5",
    "sg:city":"Bergdietikon",
    "sg:orig_category":"Grosshandel mit B\u00fcromaschinen Grosshandel mit Datenverarbeitungsger\u00e4ten",
    "sg:phone":"+41 17438060",
    "sg:postcode":"8962",
    "sg:province":"Aargau",
    "wof:name":"Risc-rosenberg Information System Consulting",
    "wof:placetype":"venue"
},
  "geometry": {"coordinates":[8.3922367096,47.388381958],"type":"Point"}
}