{
  "type": "Feature",
  "properties": {
    "iso:country":"CH",
    "sg:address":"6742",
    "sg:city":"Pollegio",
    "sg:orig_category":"Schulpflegen",
    "sg:postcode":"6742",
    "sg:province":"Ticino",
    "wof:name":"Delegazione Scolastica Del Comune Di Ponte Tresa",
    "wof:placetype":"venue"
},
  "geometry": {"coordinates":[8.862950325,45.9702606201],"type":"Point"}
}