{
  "type": "Feature",
  "properties": {
    "iso:country":"CH",
    "sg:address":"Riederbach 29",
    "sg:city":"Seedorf",
    "sg:classifiers":[
        {
            "category":"Banks & Credit Unions",
            "subcategory":"Bank",
            "type":"Services"
        }
    ],
    "sg:phone":"+41 41 870 88 20",
    "sg:postcode":"6462",
    "sg:province":"Uri",
    "wof:name":"Raiffeisenbank, Verwalterin Gisler Berti",
    "wof:placetype":"venue"
},
  "geometry": {"coordinates":[8.61891,46.881142],"type":"Point"}
}