{
  "type": "Feature",
  "properties": {
    "iso:country":"CH",
    "sg:address":"6523",
    "sg:city":"Preonzo",
    "sg:orig_category":"Gemeindeverwaltungen",
    "sg:phone":"+41 91 863 17 37",
    "sg:postcode":"6523",
    "sg:province":"Ticino",
    "wof:name":"Amministrazione Comunale Di Preonzo",
    "wof:placetype":"venue"
},
  "geometry": {"coordinates":[8.9998292923,46.2651481628],"type":"Point"}
}