{
  "type": "Feature",
  "properties": {
    "iso:country":"CH",
    "sg:address":"Zeltnerweg 16",
    "sg:city":"Solothurn",
    "sg:orig_category":"Public-Relations-Agenturen",
    "sg:phone":"+41 32 623 04 30",
    "sg:postcode":"4500",
    "sg:province":"Solothurn",
    "wof:name":"Pr-partner.ch Gerspacher Boll",
    "wof:placetype":"venue"
},
  "geometry": {"coordinates":[7.5310797691,47.2195701599],"type":"Point"}
}