{
  "type": "Feature",
  "properties": {
    "iso:country":"CH",
    "sg:address":"Grundstrasse 6 6343 Rotkreuz. Postfach",
    "sg:city":"Rotkreuz",
    "sg:orig_category":"Softwareentwicklung U beratung",
    "sg:postcode":"6343",
    "sg:province":"Zug",
    "wof:name":"E-concept Ag",
    "wof:placetype":"venue"
},
  "geometry": {"coordinates":[7.2593250275,46.8226890564],"type":"Point"}
}