{
  "type": "Feature",
  "properties": {
    "iso:country":"CH",
    "sg:address":"Solothurnerstrasse 31",
    "sg:city":"Basel",
    "sg:orig_category":"Detailhandel mit Brot, Back U S\u00fcsswaren",
    "sg:phone":"+41 61 361 85 35",
    "sg:postcode":"4053",
    "sg:province":"Basel-Stadt",
    "wof:name":"Rudolf L\u00fcthi B\u00e4ckerei-konditorei",
    "wof:placetype":"venue"
},
  "geometry": {"coordinates":[7.591052,47.544682],"type":"Point"}
}