{
  "type": "Feature",
  "properties": {
    "iso:country":"CH",
    "sg:address":"8867",
    "sg:city":"Niederurnen",
    "sg:orig_category":"Finanzierungsinstitutionen",
    "sg:phone":"+41 55228734",
    "sg:postcode":"8867",
    "sg:province":"Glarus",
    "wof:name":"Inselhold Ag",
    "wof:placetype":"venue"
},
  "geometry": {"coordinates":[9.052895546,47.1254081726],"type":"Point"}
}