{
  "type": "Feature",
  "properties": {
    "iso:country":"CH",
    "sg:address":"Route Suisse",
    "sg:city":"Etoy",
    "sg:orig_category":"Instandhaltung U Reparatur von Automobilen",
    "sg:phone":"+41 21 807 39 27",
    "sg:postcode":"1163",
    "sg:province":"Vaud",
    "wof:name":"Garage D'etoy, Mirra Agostino.",
    "wof:placetype":"venue"
},
  "geometry": {"coordinates":[6.4085278511,46.4738693237],"type":"Point"}
}