{
  "type": "Feature",
  "properties": {
    "iso:country":"CH",
    "sg:address":"Neuriedere Landstuhl",
    "sg:city":"Neuenegg",
    "sg:orig_category":"Detailhandel mit Teppichen Verlegen von Fussboden",
    "sg:phone":"+41 31 741 19 75",
    "sg:postcode":"3176",
    "sg:province":"Bern",
    "wof:name":"Daniel K\u00f6nig Innendekorationen",
    "wof:placetype":"venue"
},
  "geometry": {"coordinates":[7.3190717697,46.9054222107],"type":"Point"}
}