{
  "type": "Feature",
  "properties": {
    "iso:country":"CH",
    "sg:address":"Quellenstrasse 40",
    "sg:city":"Rheinfelden",
    "sg:orig_category":"Herstellung von Konstruktionsteilen, Fertigbauteilen U Ausbauelementen aus Holz Innenausbau",
    "sg:phone":"+41 61 833 13 00",
    "sg:postcode":"4310",
    "sg:province":"Aargau",
    "wof:name":"Gd Ausbautechnik Gmbh",
    "wof:placetype":"venue"
},
  "geometry": {"coordinates":[7.786989212,47.5505065918],"type":"Point"}
}