{
  "type": "Feature",
  "properties": {
    "iso:country":"CH",
    "sg:address":"Kapplerstrasse 24",
    "sg:city":"Ebnat",
    "sg:orig_category":"Fachdetailhandel in Verkaufsr\u00e4umen",
    "sg:phone":"+41 19301185",
    "sg:postcode":"9642",
    "sg:province":"St. Gallen",
    "wof:name":"R\u00fcedi-zurfl\u00fch Paul, Inh. Gujer Peter",
    "wof:placetype":"venue"
},
  "geometry": {"coordinates":[8.7983446121,47.3245735168],"type":"Point"}
}