{
  "type": "Feature",
  "properties": {
    "iso:country":"CH",
    "sg:address":"Route Du Stade 7",
    "sg:city":"V\u00e9troz",
    "sg:orig_category":"Softwareentwicklung U beratung",
    "sg:postcode":"1963",
    "sg:province":"Valais",
    "wof:name":"R & R Systems, Roh Et Rapillard",
    "wof:placetype":"venue"
},
  "geometry": {"coordinates":[7.2715377808,46.2211837769],"type":"Point"}
}