{
  "type": "Feature",
  "properties": {
    "iso:country":"CH",
    "sg:address":"Rue Du Sex 5",
    "sg:city":"Sion",
    "sg:orig_category":"Handel mit Motorr\u00e4dern, Teilen U Zubeh\u00f6r Instandhaltung U Reparatur von Motorr\u00e4dern Tankstellen",
    "sg:phone":"+41 77281748",
    "sg:postcode":"1950",
    "sg:province":"Valais",
    "wof:name":"Ferrero Philippe",
    "wof:placetype":"venue"
},
  "geometry": {"coordinates":[7.3629589081,46.2319793701],"type":"Point"}
}