{
  "type": "Feature",
  "properties": {
    "iso:country":"CH",
    "sg:address":"Gartenstrasse 7",
    "sg:city":"Freienbach",
    "sg:orig_category":"Non-Classified Establishments",
    "sg:postcode":"8807",
    "sg:province":"Schwyz",
    "wof:name":"Rudolf Brauchli, Dipl. Treuhandexperte",
    "wof:placetype":"venue"
},
  "geometry": {"coordinates":[8.7539567947,47.2064208984],"type":"Point"}
}