{
  "type": "Feature",
  "properties": {
    "iso:country":"CH",
    "sg:address":"Kurzfeldstrasse 5",
    "sg:city":"Frauenfeld",
    "sg:orig_category":"Wirtschafts- and Arbeitgeberverb\u00e4nde",
    "sg:phone":"+41 52 720 16 81",
    "sg:postcode":"8500",
    "sg:province":"Thurgau",
    "wof:name":"Thurgauische Aerztegesellschaft",
    "wof:placetype":"venue"
},
  "geometry": {"coordinates":[8.8925418854,47.5579490662],"type":"Point"}
}