{
  "type": "Feature",
  "properties": {
    "iso:country":"CH",
    "sg:address":"Franzeng\u00e4ssli 3",
    "sg:city":"Thayngen",
    "sg:orig_category":"Sanit\u00e4r, Heizungs U L\u00fcftungsinstallation Sanit\u00e4rinstallation",
    "sg:phone":"+41 79 416 45 31",
    "sg:postcode":"8240",
    "sg:province":"Schaffhausen",
    "wof:name":"Stamm Urs Heizungen, Sanit\u00e4r",
    "wof:placetype":"venue"
},
  "geometry": {"coordinates":[8.7133970261,47.7478027344],"type":"Point"}
}