{
  "type": "Feature",
  "properties": {
    "iso:country":"CH",
    "sg:address":"Rue De Rossettan 3 1920 Martigny. Postfach",
    "sg:city":"Martigny-croix",
    "sg:orig_category":"Detailhandel mit Radio U Fernsehger\u00e4ten Detailhandel mit elektrischen Haushalts-,Radio U Fernsehger\u00e4",
    "sg:phone":"+41 27 722 45 05",
    "sg:postcode":"1921",
    "sg:province":"Valais",
    "wof:name":"T\u00e9l\u00e9bourg B. Jansen",
    "wof:placetype":"venue"
},
  "geometry": {"coordinates":[7.0636172295,46.0936088562],"type":"Point"}
}