{
  "type": "Feature",
  "properties": {
    "iso:country":"CH",
    "sg:address":"Ch\u00f6renmattstrasse 42",
    "sg:city":"Berikon",
    "sg:orig_category":"Sportvereine",
    "sg:phone":"+41 56 631 80 55",
    "sg:postcode":"8965",
    "sg:province":"Aargau",
    "wof:name":"Alter & Sport Mutschellen",
    "wof:placetype":"venue"
},
  "geometry": {"coordinates":[8.3689088821,47.3583984375],"type":"Point"}
}