{
  "type": "Feature",
  "properties": {
    "iso:country":"CH",
    "sg:address":"Weidstrasse 1",
    "sg:city":"Fischbach-g\u00f6slikon",
    "sg:orig_category":"Grosshandel mit Geschenkartikeln U Souvenirs Grosshandel mit sonstigen Gebrauchs U Verbrauchsg\u00fctern",
    "sg:phone":"+41 71 385 46 88",
    "sg:postcode":"5525",
    "sg:province":"Aargau",
    "wof:name":"Juma-werbung Spinell Markus",
    "wof:placetype":"venue"
},
  "geometry": {"coordinates":[9.2663211823,47.4146461487],"type":"Point"}
}