{
  "type": "Feature",
  "properties": {
    "iso:country":"CH",
    "sg:address":"Zehntenhof",
    "sg:city":"Illighausen",
    "sg:orig_category":"Wohnheime",
    "sg:phone":"+41 71 688 65 02",
    "sg:postcode":"8574",
    "sg:province":"Thurgau",
    "wof:name":"Stiftung Sos",
    "wof:placetype":"venue"
},
  "geometry": {"coordinates":[9.1937875748,47.6247749329],"type":"Point"}
}