{
  "type": "Feature",
  "properties": {
    "addr:full":"Hauptstrasse 92 Murgenthal Aargau 4853",
    "addr:housenumber":"92",
    "addr:postcode":"4853",
    "addr:street":"Hauptstrasse",
    "iso:country":"CH",
    "sg:address":"Hauptstrasse 92",
    "sg:city":"Murgenthal",
    "sg:orig_category":"Darlehenskassen U Raiffeisenbanken",
    "sg:phone":"+41 62 917 01 50",
    "sg:postcode":"4853",
    "sg:province":"Aargau",
    "wof:name":"Raiffeisenbank Fulenbach-murgenthal",
    "wof:placetype":"venue"
},
  "geometry": {"coordinates":[7.829385,47.264866],"type":"Point"}
}