{
  "type": "Feature",
  "properties": {
    "iso:country":"CH",
    "sg:address":"1762",
    "sg:city":"Givisiez",
    "sg:orig_category":"Pensionskassen",
    "sg:phone":"+41 26 467 81 11",
    "sg:postcode":"1762",
    "sg:province":"Fribourg",
    "wof:name":"Fonds De Pr\u00e9voyance En Faveur Du Personnel De Glasson Mat\u00e9riaux Sa",
    "wof:placetype":"venue"
},
  "geometry": {"coordinates":[7.1255397797,46.8128013611],"type":"Point"}
}