{
  "type": "Feature",
  "properties": {
    "iso:country":"CH",
    "sg:address":"Stockerstrasse 42",
    "sg:city":"Z\u00fcrich",
    "sg:orig_category":"Geb\u00e4ude, Wohnungsreinigung",
    "sg:phone":"+41 12020784",
    "sg:postcode":"8002",
    "sg:province":"Z\u00fcrich",
    "wof:name":"Schellenberg J., Reinigungen Unterhaltsreinigungen",
    "wof:placetype":"venue"
},
  "geometry": {"coordinates":[8.5346050262,47.3677978516],"type":"Point"}
}