{
  "type": "Feature",
  "properties": {
    "iso:country":"CH",
    "sg:address":"Hauptstrasse 35",
    "sg:city":"K\u00f6lliken",
    "sg:orig_category":"Zimmerei, Dachdeckerei, Bauspenglerei U Abdichtung",
    "sg:phone":"+41 62 723 62 22",
    "sg:postcode":"5742",
    "sg:province":"Aargau",
    "wof:name":"Baumann Kurt Ag",
    "wof:placetype":"venue"
},
  "geometry": {"coordinates":[8.0244245529,47.3352432251],"type":"Point"}
}