{
  "type": "Feature",
  "properties": {
    "iso:country":"CH",
    "sg:address":"Postgasse 3",
    "sg:city":"Sissach",
    "sg:orig_category":"Informatikdienste Sonstige mit der Informatik verbundene T\u00e4tigkeiten",
    "sg:phone":"+41 61 976 92 76",
    "sg:postcode":"4450",
    "sg:province":"Basel-Landschaft",
    "wof:name":"Inside Solutions Ag",
    "wof:placetype":"venue"
},
  "geometry": {"coordinates":[7.811727047,47.4639396667],"type":"Point"}
}