{
  "type": "Feature",
  "properties": {
    "iso:country":"CH",
    "sg:address":"Am Wald 36",
    "sg:city":"Biel/bienne",
    "sg:orig_category":"Unternehmensberatung",
    "sg:phone":"+41 18221160",
    "sg:postcode":"2500",
    "sg:province":"Bern",
    "wof:name":"Cid Unternehmensberatung Ag",
    "wof:placetype":"venue"
},
  "geometry": {"coordinates":[8.6250162125,47.3966712952],"type":"Point"}
}