{
  "type": "Feature",
  "properties": {
    "iso:country":"CH",
    "sg:address":"Turnhallenstrasse 18",
    "sg:city":"Langenthal",
    "sg:classifiers":[
        {
            "category":"Education",
            "subcategory":"Vocational School",
            "type":"Public Place"
        }
    ],
    "sg:phone":"+41 56 441 63 36",
    "sg:postcode":"4900",
    "sg:province":"Bern",
    "sg:tags":[
        "koch-",
        "haushaltschulen"
    ],
    "wof:name":"Hauswirtschaftsschule Freudenstein Sekundarschule",
    "wof:placetype":"venue"
},
  "geometry": {"coordinates":[8.2023057938,47.4846191406],"type":"Point"}
}