{
  "type": "Feature",
  "properties": {
    "iso:country":"CH",
    "sg:address":"Ahornstrasse 3 4055 Basel. Postfach",
    "sg:city":"Basel",
    "sg:orig_category":"RESTAURANTS: TEA-ROOMS",
    "sg:postcode":"4051",
    "sg:province":"Basel-Stadt",
    "wof:name":"Walder Ren\u00e9. Restaurant.",
    "wof:placetype":"venue"
},
  "geometry": {"coordinates":[7.5749340057,47.5570640564],"type":"Point"}
}