{
  "type": "Feature",
  "properties": {
    "iso:country":"CH",
    "sg:address":"Allmendstrasse 6",
    "sg:city":"Sursee",
    "sg:orig_category":"Grosshandel mit sonstigen Maschinen U Ausr\u00fcstungen f\u00fcr Industrie, Handel U Schiffahrt Handelsvermitt",
    "sg:phone":"+41 22 347 08 04",
    "sg:postcode":"6210",
    "sg:province":"Luzern",
    "wof:name":"Unirax Sa Mat\u00e9riels Pour L'industrie",
    "wof:placetype":"venue"
},
  "geometry": {"coordinates":[6.1545171738,46.194732666],"type":"Point"}
}