{
  "type": "Feature",
  "properties": {
    "iso:country":"CH",
    "sg:address":"Tramstrasse 8",
    "sg:city":"Diepoldsau",
    "sg:orig_category":"Herstellung von Metallkonstruktionen Stahl U Leichtmetallbau",
    "sg:phone":"+41 71 733 11 77",
    "sg:postcode":"9444",
    "sg:province":"St. Gallen",
    "wof:name":"Zellweger Paul Ag",
    "wof:placetype":"venue"
},
  "geometry": {"coordinates":[9.6535673141,47.387260437],"type":"Point"}
}