{
  "type": "Feature",
  "properties": {
    "iso:country":"CH",
    "sg:address":"Kaserloch 3b",
    "sg:city":"Oftringen",
    "sg:orig_category":"Gesundheitswesen",
    "sg:phone":"+41 62 797 55 19",
    "sg:postcode":"4665",
    "sg:province":"Aargau",
    "wof:name":"De Ruijter",
    "wof:placetype":"venue"
},
  "geometry": {"coordinates":[7.9572238922,47.3012199402],"type":"Point"}
}