{
  "type": "Feature",
  "properties": {
    "iso:country":"CH",
    "sg:address":"Avenue De Chillon 2",
    "sg:city":"Territet-veytaux",
    "sg:orig_category":"Architekturb\u00fcros Herstellung von Metallkonstruktionen",
    "sg:phone":"+41 79 371 22 42",
    "sg:postcode":"1820",
    "sg:province":"Vaud",
    "wof:name":"Kollbrunner Thomas",
    "wof:placetype":"venue"
},
  "geometry": {"coordinates":[6.931485,46.409611],"type":"Point"}
}