{
  "type": "Feature",
  "properties": {
    "iso:country":"CH",
    "sg:address":"Fellstrasse 1",
    "sg:city":"Birmenstorf",
    "sg:orig_category":"Biopesticides",
    "sg:phone":"+41 56 201 45 45",
    "sg:postcode":"5413",
    "sg:province":"Aargau",
    "wof:name":"Leu + Gygax Ag",
    "wof:placetype":"venue"
},
  "geometry": {"coordinates":[8.253631,47.458778],"type":"Point"}
}