{
  "type": "Feature",
  "properties": {
    "iso:country":"CH",
    "sg:address":"Kasernenstrasse 163",
    "sg:city":"Chur",
    "sg:orig_category":"Unclassifiable Establishments",
    "sg:postcode":"7000",
    "sg:province":"Graubunden",
    "wof:name":"Autohandel Maljici Mirhad",
    "wof:placetype":"venue"
},
  "geometry": {"coordinates":[9.5110464096,46.8461151123],"type":"Point"}
}