{
  "type": "Feature",
  "properties": {
    "iso:country":"CH",
    "sg:address":"Dorfstrasse 3902 Glis",
    "sg:city":"Brig",
    "sg:orig_category":"RESTAURANTS: TEA-ROOMS",
    "sg:postcode":"3900",
    "sg:province":"Valais",
    "wof:name":"Restaurant Maltesekreuz, Steiner Josef",
    "wof:placetype":"venue"
},
  "geometry": {"coordinates":[7.9876461029,46.3158912659],"type":"Point"}
}