{
  "type": "Feature",
  "properties": {
    "iso:country":"CH",
    "sg:address":"Jurastrasse 25",
    "sg:city":"Langenthal",
    "sg:orig_category":"Kosmetikinstitute",
    "sg:phone":"+41 62 922 35 09",
    "sg:postcode":"4900",
    "sg:province":"Bern",
    "wof:name":"Gabriela Schneider Kosmetik Beim Theater",
    "wof:placetype":"venue"
},
  "geometry": {"coordinates":[7.7878298759,47.2143325806],"type":"Point"}
}