{
  "type": "Feature",
  "properties": {
    "iso:country":"CH",
    "sg:address":"Bucher Strasse 10",
    "sg:city":"Affeltrangen",
    "sg:orig_category":"S\u00e4ge, Hobel U Holzimpr\u00e4gnierwerke S\u00e4gewerke",
    "sg:phone":"+41 71 918 79 79",
    "sg:postcode":"9556",
    "sg:province":"Thurgau",
    "wof:name":"Holzwerk Schneider & Co.",
    "wof:placetype":"venue"
},
  "geometry": {"coordinates":[9.0391740799,47.5274162292],"type":"Point"}
}