{
  "type": "Feature",
  "properties": {
    "iso:country":"CH",
    "sg:address":"Jungstrasse 45",
    "sg:city":"Basel",
    "sg:orig_category":"Maler U Glasergewerbe",
    "sg:postcode":"4056",
    "sg:province":"Basel-Stadt",
    "wof:name":"Rehman Malergesch\u00e4ft",
    "wof:placetype":"venue"
},
  "geometry": {"coordinates":[7.5779972076,47.5667495728],"type":"Point"}
}