{
  "type": "Feature",
  "properties": {
    "iso:country":"CH",
    "sg:address":"1914",
    "sg:city":"Is\u00e9rables",
    "sg:orig_category":"RESTAURANTS: TEA-ROOMS",
    "sg:phone":"+41 71 923 25 98",
    "sg:postcode":"1914",
    "sg:province":"Valais",
    "wof:name":"Ceta Boza, Rest. Signal.",
    "wof:placetype":"venue"
},
  "geometry": {"coordinates":[9.043721199,47.4603919983],"type":"Point"}
}