{
  "type": "Feature",
  "properties": {
    "iso:country":"CH",
    "sg:address":"Maiholzstrasse 20",
    "sg:city":"Frauenfeld",
    "sg:orig_category":"Vermietung U Verpachtung von eigenen Immobilien",
    "sg:postcode":"8500",
    "sg:province":"Thurgau",
    "wof:name":"Hescha Immobilien Ag",
    "wof:placetype":"venue"
},
  "geometry": {"coordinates":[8.8869285583,47.5586891174],"type":"Point"}
}