{
  "type": "Feature",
  "properties": {
    "addr:full":"Eisenbahnstrasse 7 Rorschach St. Gallen 9400",
    "addr:housenumber":"7",
    "addr:postcode":"9400",
    "addr:street":"Eisenbahnstrasse",
    "iso:country":"CH",
    "sg:address":"Eisenbahnstrasse 7",
    "sg:city":"Rorschach",
    "sg:orig_category":"Datenverarbeitungsdienste",
    "sg:phone":"+41 71 845 44 43",
    "sg:postcode":"9400",
    "sg:province":"St. Gallen",
    "wof:name":"Consultrade Wyss Edv-komplettl\u00f6sungen Beratung",
    "wof:placetype":"venue"
},
  "geometry": {"coordinates":[9.497585,47.476814],"type":"Point"}
}