{
  "type": "Feature",
  "properties": {
    "iso:country":"CH",
    "sg:address":"Bahnhofstrasse 95a",
    "sg:city":"M\u00f6hlin",
    "sg:orig_category":"Fahrschulen, Flugschulen",
    "sg:phone":"+41 61 851 06 56",
    "sg:postcode":"4313",
    "sg:province":"Aargau",
    "wof:name":"Hanspeter Bachmann Fahrschule",
    "wof:placetype":"venue"
},
  "geometry": {"coordinates":[7.8465280533,47.5553436279],"type":"Point"}
}