{
  "type": "Feature",
  "properties": {
    "iso:country":"CH",
    "sg:address":"Baslerstrasse 31",
    "sg:city":"Binningen",
    "sg:orig_category":"RESTAURANTS: TEA-ROOMS",
    "sg:postcode":"4102",
    "sg:province":"Basel-Landschaft",
    "wof:name":"Yvonne Frey",
    "wof:placetype":"venue"
},
  "geometry": {"coordinates":[7.5763049126,47.5401649475],"type":"Point"}
}