{
  "type": "Feature",
  "properties": {
    "iso:country":"CH",
    "sg:address":"Steinweg 25c",
    "sg:city":"Lyss",
    "sg:orig_category":"Detailhandel mit B\u00fcchern, Zeitungen, Schreib U Papeteriewaren Detailhandel mit Waren verschiedener A",
    "sg:phone":"+41 32 384 17 91",
    "sg:postcode":"3250",
    "sg:province":"Bern",
    "wof:name":"Pierino Giusto Kiosk Fr\u00fcchte & Gem\u00fcse",
    "wof:placetype":"venue"
},
  "geometry": {"coordinates":[7.3039369583,47.0792732239],"type":"Point"}
}