{
  "type": "Feature",
  "properties": {
    "iso:country":"CH",
    "sg:address":"Im Oberfeld 16",
    "sg:city":"Vaduz",
    "sg:orig_category":"Unternehmensberatung",
    "sg:phone":"+423 232 93 22",
    "sg:postcode":"9490",
    "wof:name":"Ipr Management Services Ag",
    "wof:placetype":"venue"
},
  "geometry": {"coordinates":[9.5173330307,47.1478691101],"type":"Point"}
}