{
  "type": "Feature",
  "properties": {
    "iso:country":"CH",
    "sg:address":"Feldstrasse 20",
    "sg:city":"Unterentfelden",
    "sg:orig_category":"Datenverarbeitungsdienste Softwareentwicklung U beratung",
    "sg:phone":"+41 62 723 34 34",
    "sg:postcode":"5035",
    "sg:province":"Aargau",
    "wof:name":"Graber Edv-treuhand",
    "wof:placetype":"venue"
},
  "geometry": {"coordinates":[8.041224,47.367996],"type":"Point"}
}