{
  "type": "Feature",
  "properties": {
    "iso:country":"CH",
    "sg:address":"M\u00fchle",
    "sg:city":"B\u00fchler",
    "sg:classifiers":[
        {
            "category":"Shopping",
            "subcategory":"Crafts & Fabrics",
            "type":"Retail Goods"
        }
    ],
    "sg:phone":"+41 71 791 81 81",
    "sg:postcode":"9055",
    "sg:province":"Appenzell Ausserrhoden",
    "sg:tags":[
        "knitted"
    ],
    "wof:name":"Christian Eschler Ag",
    "wof:placetype":"venue"
},
  "geometry": {"coordinates":[9.4249200821,47.3730773926],"type":"Point"}
}