{
  "type": "Feature",
  "properties": {
    "iso:country":"CH",
    "sg:address":"Hartbertstrasse 9",
    "sg:city":"Chur",
    "sg:orig_category":"Unclassifiable Establishments",
    "sg:postcode":"7000",
    "sg:province":"Graubunden",
    "wof:name":"Thesarim Ag",
    "wof:placetype":"venue"
},
  "geometry": {"coordinates":[9.532201767,46.8532371521],"type":"Point"}
}