{
  "type": "Feature",
  "properties": {
    "iso:country":"CH",
    "sg:address":"Rue De Ch\u00eane-bougeries 7",
    "sg:city":"Ch\u00eane-bougeries",
    "sg:classifiers":[
        {
            "category":"Restaurant",
            "type":"Food & Drink"
        }
    ],
    "sg:phone":"+41 22 343 75 98",
    "sg:postcode":"1224",
    "sg:province":"Gen\u00e8ve",
    "wof:name":"Caf\u00e9 La Poste",
    "wof:placetype":"venue"
},
  "geometry": {"coordinates":[6.1410579681,46.1831474304],"type":"Point"}
}