{
  "type": "Feature",
  "properties": {
    "iso:country":"CH",
    "sg:address":"Via San Gottardo 10",
    "sg:city":"Lugano",
    "sg:orig_category":"Grosshandel mit sonstigen Maschinen U Ausr\u00fcstungen f\u00fcr Industrie, Handel U Schiffahrt Handelsvermitt",
    "sg:phone":"+41 71 244 01 24",
    "sg:postcode":"6900",
    "sg:province":"Ticino",
    "wof:name":"Serva-technik Ag",
    "wof:placetype":"venue"
},
  "geometry": {"coordinates":[9.3913049698,47.4327163696],"type":"Point"}
}