{
  "type": "Feature",
  "properties": {
    "iso:country":"CH",
    "sg:address":"Via T. Rodari 2 6500 Bellinzona Casella Postale 33",
    "sg:city":"Bellinzona",
    "sg:orig_category":"Bestattungswesen",
    "sg:phone":"+41 79 444 21 20",
    "sg:postcode":"6500",
    "sg:province":"Ticino",
    "wof:name":"Barenco Agenzia Funebre Di Pietro Fu Ezio",
    "wof:placetype":"venue"
},
  "geometry": {"coordinates":[9.024119,46.194462],"type":"Point"}
}