{
  "type": "Feature",
  "properties": {
    "iso:country":"CH",
    "sg:address":"Rue De La Borde 30",
    "sg:city":"Lausanne",
    "sg:orig_category":"Sportvereine Ballsport Fussball",
    "sg:postcode":"1018",
    "sg:province":"Vaud",
    "wof:name":"Us Portugaise",
    "wof:placetype":"venue"
},
  "geometry": {"coordinates":[6.6320419312,46.5304946899],"type":"Point"}
}