{
  "type": "Feature",
  "properties": {
    "iso:country":"CH",
    "sg:address":"Wartenbergstrasse 22",
    "sg:city":"Pratteln",
    "sg:orig_category":"Architektur U Ingenieurb\u00fcros",
    "sg:postcode":"4133",
    "sg:province":"Basel-Landschaft",
    "wof:name":"Enzmann Beratungs Gmbh",
    "wof:placetype":"venue"
},
  "geometry": {"coordinates":[7.686695,47.517284],"type":"Point"}
}