{
  "type": "Feature",
  "properties": {
    "iso:country":"CH",
    "sg:address":"Schmiedengasse 33",
    "sg:city":"Sch\u00f6nenwerd",
    "sg:orig_category":"Wasserversorgung",
    "sg:phone":"+41 41 921 49 29",
    "sg:postcode":"5012",
    "sg:province":"Solothurn",
    "wof:name":"G\u00e4hwiler Ag Wasseraufbereitung Und Sanit\u00e4rarmaturen",
    "wof:placetype":"venue"
},
  "geometry": {"coordinates":[8.111741066,47.153755188],"type":"Point"}
}