{
  "type": "Feature",
  "properties": {
    "iso:country":"CH",
    "sg:address":"Rebenstrasse 46",
    "sg:city":"Arbon",
    "sg:orig_category":"Dienstleistungen, Auskunft- U Recherchierdienste",
    "sg:phone":"+41 71 440 03 63",
    "sg:postcode":"9320",
    "sg:province":"Thurgau",
    "wof:name":"Chemierecherchen - Pharmarecherchen - Patentrecherchen",
    "wof:placetype":"venue"
},
  "geometry": {"coordinates":[9.426288,47.51429],"type":"Point"}
}