{
  "type": "Feature",
  "properties": {
    "iso:country":"CH",
    "sg:address":"Bundesstrasse 3 6300 Zug. Postfach 4547",
    "sg:city":"Zug",
    "sg:orig_category":"Technische B\u00fcros Apparatebau",
    "sg:phone":"+41 41 720 46 30",
    "sg:postcode":"6304",
    "sg:province":"Zug",
    "wof:name":"Mariposa Consulting Ag",
    "wof:placetype":"venue"
},
  "geometry": {"coordinates":[8.5136566162,47.1713104248],"type":"Point"}
}