{
  "type": "Feature",
  "properties": {
    "iso:country":"CH",
    "sg:address":"Sch\u00fctzenhausstrasse 42",
    "sg:city":"Embrach",
    "sg:orig_category":"Grosshandel mit Holz U Baustoffen Herstellung von Zement",
    "sg:phone":"+41 18650571",
    "sg:postcode":"8424",
    "sg:province":"Z\u00fcrich",
    "wof:name":"Albrecht Ernst Zementwaren Ag",
    "wof:placetype":"venue"
},
  "geometry": {"coordinates":[8.5959243774,47.5051307678],"type":"Point"}
}