{
  "type": "Feature",
  "properties": {
    "iso:country":"CH",
    "sg:address":"Dorfstrasse 1",
    "sg:city":"Linn",
    "sg:orig_category":"Landesverteidigung, Sozialversicherung \u00d6ffentliche Verwaltung",
    "sg:phone":"+41 56 441 60 89",
    "sg:postcode":"5224",
    "sg:province":"Aargau",
    "wof:name":"Zivilschutzstelle Linn",
    "wof:placetype":"venue"
},
  "geometry": {"coordinates":[8.1314620972,47.4703102112],"type":"Point"}
}