{
  "type": "Feature",
  "properties": {
    "iso:country":"CH",
    "sg:address":"Via Antonio Ciseri 7",
    "sg:city":"Lugano",
    "sg:orig_category":"Verwaltung von Immobilien",
    "sg:postcode":"6900",
    "sg:province":"Ticino",
    "wof:name":"Pagodite Sa",
    "wof:placetype":"venue"
},
  "geometry": {"coordinates":[8.9519920349,46.0102882385],"type":"Point"}
}