{
  "type": "Feature",
  "properties": {
    "iso:country":"CH",
    "sg:address":"Baumgartenstrasse 5",
    "sg:city":"Goldach",
    "sg:orig_category":"Sportvereine Turnen",
    "sg:postcode":"9403",
    "sg:province":"St. Gallen",
    "wof:name":"Polizeiturnverein St.gallen",
    "wof:placetype":"venue"
},
  "geometry": {"coordinates":[9.4631900787,47.4793930054],"type":"Point"}
}