{
  "type": "Feature",
  "properties": {
    "iso:country":"CH",
    "sg:address":"Br\u00fchlstrasse 38",
    "sg:city":"Br\u00fctten",
    "sg:orig_category":"Autospenglereien",
    "sg:phone":"+41 71 891 15 84",
    "sg:postcode":"8311",
    "sg:province":"Z\u00fcrich",
    "wof:name":"Willi Jenni Carrosserie",
    "wof:placetype":"venue"
},
  "geometry": {"coordinates":[9.51425,47.446968],"type":"Point"}
}