{
  "type": "Feature",
  "properties": {
    "iso:country":"CH",
    "sg:address":"6838",
    "sg:city":"Cabbio",
    "sg:orig_category":"Non-Classified Establishments",
    "sg:phone":"+41 91 684 11 52",
    "sg:postcode":"6838",
    "sg:province":"Ticino",
    "wof:name":"Osteria Del Cervo",
    "wof:placetype":"venue"
},
  "geometry": {"coordinates":[9.0454540253,45.8984184265],"type":"Point"}
}