{
  "type": "Feature",
  "properties": {
    "iso:country":"CH",
    "sg:address":"Romaine Ruelle",
    "sg:city":"St-saphorin-lavaux",
    "sg:orig_category":"Grosshandel mit Getr\u00e4nken",
    "sg:phone":"+41 21 921 53 70",
    "sg:postcode":"1813",
    "wof:name":"Cave Et Vinoth\u00e8que, Dutoit Pierre-alain",
    "wof:placetype":"venue"
},
  "geometry": {"coordinates":[6.7959570885,46.4733009338],"type":"Point"}
}