{
  "type": "Feature",
  "properties": {
    "iso:country":"CH",
    "sg:address":"Tann\u00e4gertenstrasse 2 8608 Bubikon. Postfach",
    "sg:city":"Bubikon",
    "sg:orig_category":"Detailhandel mit medizinischen U orthop\u00e4dischen Artikeln",
    "sg:phone":"+41 55 253 80 00",
    "sg:postcode":"8608",
    "sg:province":"Z\u00fcrich",
    "wof:name":"Phonak Schweiz Ag H\u00f6rger\u00e4te, Produkte Der Drahtlosen Kommunikation Usw.; Vertrieb, Montage",
    "wof:placetype":"venue"
},
  "geometry": {"coordinates":[8.8337402344,47.2634887695],"type":"Point"}
}