{
  "type": "Feature",
  "properties": {
    "iso:country":"CH",
    "sg:address":"Viale Verbano 3a",
    "sg:city":"Muralto",
    "sg:classifiers":[
        {
            "category":"Arena",
            "subcategory":"Sports Club",
            "type":"Entertainment"
        }
    ],
    "sg:postcode":"6600",
    "sg:province":"Ticino",
    "sg:tags":[
        "karate",
        "judo",
        "sportvereine"
    ],
    "wof:name":"Karate Club Locarno",
    "wof:placetype":"venue"
},
  "geometry": {"coordinates":[8.8008861542,46.1710090637],"type":"Point"}
}