{
  "type": "Feature",
  "properties": {
    "iso:country":"CH",
    "sg:address":"Route De Cossonay 33",
    "sg:city":"Prilly",
    "sg:orig_category":"Detailhandel mit elektrischen Haushalts-,Radio U Fernsehger\u00e4ten sowie Musikinstrumenten Grosshandel ",
    "sg:phone":"+41 844 848 848",
    "sg:postcode":"1008",
    "sg:province":"Vaud",
    "wof:name":"Sibir Haushalttechnik Sa",
    "wof:placetype":"venue"
},
  "geometry": {"coordinates":[6.6043601036,46.5352325439],"type":"Point"}
}