{
  "type": "Feature",
  "properties": {
    "iso:country":"CH",
    "sg:address":"Via Rovedo 16 6600 Locarno. Postfach",
    "sg:city":"Locarno",
    "sg:orig_category":"Architektur U Ingenieurb\u00fcros Architekturb\u00fcros",
    "sg:phone":"+41 91 751 51 61",
    "sg:postcode":"6601",
    "sg:province":"Ticino",
    "wof:name":"Tiziano Vannini Studio D'architettura",
    "wof:placetype":"venue"
},
  "geometry": {"coordinates":[8.787499,46.166237],"type":"Point"}
}