{
  "type": "Feature",
  "properties": {
    "addr:full":"Seeg\u00e4rtli Leissigen Bern 3706",
    "addr:postcode":"3706",
    "iso:country":"CH",
    "sg:address":"Seeg\u00e4rtli",
    "sg:city":"Leissigen",
    "sg:orig_category":"Bauschreinerei Boots U Yachtbau",
    "sg:phone":"+41 33 847 15 62",
    "sg:postcode":"3706",
    "sg:province":"Bern",
    "wof:name":"Dietrich Kurt",
    "wof:placetype":"venue"
},
  "geometry": {"coordinates":[7.77409,46.654655],"type":"Point"}
}