{
  "type": "Feature",
  "properties": {
    "iso:country":"CH",
    "sg:address":"Kreuzstrasse 28b",
    "sg:city":"Kriens",
    "sg:orig_category":"Grosshandel mit Eisenwaren sowie Installationsbedarf f\u00fcr Gas, Wasser U Heizung Herstellung von Heizk",
    "sg:phone":"+41 41 340 90 55",
    "sg:postcode":"6010",
    "sg:province":"Luzern",
    "wof:name":"Vescal Sa",
    "wof:placetype":"venue"
},
  "geometry": {"coordinates":[8.298833847,47.0207099915],"type":"Point"}
}