{
  "type": "Feature",
  "properties": {
    "iso:country":"CH",
    "sg:address":"Bl\u00e4uistrasse 2",
    "sg:city":"Gersau",
    "sg:orig_category":"Sportvereine Ballsport Tennis",
    "sg:phone":"+41 41 828 21 31",
    "sg:postcode":"6442",
    "sg:province":"Schwyz",
    "wof:name":"Tc Gersau",
    "wof:placetype":"venue"
},
  "geometry": {"coordinates":[8.5268745422,46.9930686951],"type":"Point"}
}