{
  "type": "Feature",
  "properties": {
    "iso:country":"CH",
    "sg:address":"Lavizzari Via 4",
    "sg:city":"Lugano",
    "sg:orig_category":"Finanzierungsinstitutionen",
    "sg:phone":"+41 91 911 71 11",
    "sg:postcode":"6900",
    "sg:province":"Ticino",
    "wof:name":"Veco Finance Sa",
    "wof:placetype":"venue"
},
  "geometry": {"coordinates":[8.9583463669,46.0064620972],"type":"Point"}
}