{
  "type": "Feature",
  "properties": {
    "iso:country":"CH",
    "sg:address":"Bergstrasse 22",
    "sg:city":"Regensdorf",
    "sg:classifiers":[
        {
            "category":"Insurance",
            "subcategory":"Insurance Agent",
            "type":"Services"
        }
    ],
    "sg:phone":"+41 18402003",
    "sg:postcode":"8105",
    "sg:province":"Z\u00fcrich",
    "sg:tags":[
        "versicherungsagenturen",
        "-broker"
    ],
    "wof:name":"Gerhard Payer Vers'beratungen",
    "wof:placetype":"venue"
},
  "geometry": {"coordinates":[8.4654951096,47.42786026],"type":"Point"}
}