{
  "type": "Feature",
  "properties": {
    "iso:country":"CH",
    "sg:address":"Lohwisstrasse 42",
    "sg:city":"Ebmatingen",
    "sg:orig_category":"Grosshandel mit elektrischen Haushaltsger\u00e4ten, Radio U Fernsehger\u00e4ten Herstellung von Mess U Kontrol",
    "sg:phone":"+41 71 744 70 91",
    "sg:postcode":"8123",
    "sg:province":"Z\u00fcrich",
    "wof:name":"Pms Photo-mess-systeme Ag",
    "wof:placetype":"venue"
},
  "geometry": {"coordinates":[9.6362390518,47.4521484375],"type":"Point"}
}