{
  "type": "Feature",
  "properties": {
    "iso:country":"CH",
    "sg:address":"6675",
    "sg:city":"Cevio",
    "sg:orig_category":"Reparatur von Uhren U Schmuck",
    "sg:phone":"+41 91 606 62 44",
    "sg:postcode":"6675",
    "sg:province":"Ticino",
    "wof:name":"Antonio Lumiella Laboratorio Orologi",
    "wof:placetype":"venue"
},
  "geometry": {"coordinates":[8.8604135513,45.9691696167],"type":"Point"}
}