{
  "type": "Feature",
  "properties": {
    "iso:country":"CH",
    "sg:address":"Opfikonerstrasse 95",
    "sg:city":"Wallisellen",
    "sg:orig_category":"Allgemeiner Gartenbau",
    "sg:phone":"+41 14626262",
    "sg:postcode":"8304",
    "sg:province":"Z\u00fcrich",
    "wof:name":"Spross Ga-la-bau-ag Baumschulen",
    "wof:placetype":"venue"
},
  "geometry": {"coordinates":[8.578859,47.421307],"type":"Point"}
}