{
  "type": "Feature",
  "properties": {
    "iso:country":"CH",
    "sg:address":"Zweiengasse 6",
    "sg:city":"Pratteln",
    "sg:orig_category":"Erbringung von Dienstleistungen f\u00fcr Unternehmen Grafikateliers, Design",
    "sg:phone":"+41 61 821 56 89",
    "sg:postcode":"4133",
    "sg:province":"Basel-Landschaft",
    "wof:name":"Dill John Ag",
    "wof:placetype":"venue"
},
  "geometry": {"coordinates":[7.7020959854,47.5218238831],"type":"Point"}
}