{
  "type": "Feature",
  "properties": {
    "iso:country":"CH",
    "sg:address":"Seestrandweg 3234 Vinelz. Postfach",
    "sg:city":"Vinelz",
    "sg:orig_category":"Detailhandel mit B\u00fcchern, Zeitungen, Schreib U Papeteriewaren",
    "sg:postcode":"3234",
    "sg:province":"Bern",
    "wof:name":"Miranda Sergio Camping Kiosk Strand",
    "wof:placetype":"venue"
},
  "geometry": {"coordinates":[7.105584,47.037708],"type":"Point"}
}