{
  "type": "Feature",
  "properties": {
    "iso:country":"CH",
    "sg:address":"Am Linthli 28",
    "sg:city":"N\u00e4fels",
    "sg:orig_category":"Grosshandel mit B\u00fcromaschinen Grosshandel mit B\u00fcrom\u00f6beln",
    "sg:phone":"+41 55 612 41 41",
    "sg:postcode":"8752",
    "sg:province":"Glarus",
    "wof:name":"Glatex Ag",
    "wof:placetype":"venue"
},
  "geometry": {"coordinates":[9.0666294098,47.1097755432],"type":"Point"}
}