{
  "type": "Feature",
  "properties": {
    "iso:country":"CH",
    "sg:address":"Wydenstrasse 17",
    "sg:city":"Unter\u00e4geri",
    "sg:orig_category":"Ingenieurb\u00fcros Datenverarbeitung Ingenieurb\u00fcros Maschinenbau",
    "sg:phone":"+41 41 750 04 45",
    "sg:postcode":"6314",
    "sg:province":"Zug",
    "wof:name":"Ren\u00e9 Baumgartner Ingenieurb\u00fcro 3k",
    "wof:placetype":"venue"
},
  "geometry": {"coordinates":[8.5877971649,47.1419410706],"type":"Point"}
}