{
  "type": "Feature",
  "properties": {
    "iso:country":"CH",
    "sg:address":"St. Jakobs-strasse 200 4052 Basel. Postfach",
    "sg:city":"Basel",
    "sg:orig_category":"G\u00fcterbef\u00f6rderung im Strassenverkehr Pensionskassen",
    "sg:phone":"+41 61 313 88 11",
    "sg:postcode":"4002",
    "sg:province":"Basel-Stadt",
    "wof:name":"Patronale Vorsorgestiftung Der Meyer Fritz Holding Ag",
    "wof:placetype":"venue"
},
  "geometry": {"coordinates":[7.6071028709,47.5438766479],"type":"Point"}
}