{
  "type": "Feature",
  "properties": {
    "iso:country":"CH",
    "sg:address":"1038",
    "sg:city":"Bercher",
    "sg:orig_category":"RESTAURANTS: TEA-ROOMS",
    "sg:postcode":"1038",
    "sg:province":"Vaud",
    "wof:name":"Bonnemain Christianne",
    "wof:placetype":"venue"
},
  "geometry": {"coordinates":[6.7114901543,46.6916313171],"type":"Point"}
}