{
  "type": "Feature",
  "properties": {
    "iso:country":"CH",
    "sg:address":"Elisabethenanlage 11 4051 Basel. Postfach",
    "sg:city":"Basel",
    "sg:orig_category":"Wirtschaftspr\u00fcfung, Steuerberatung U Treuhand",
    "sg:phone":"+41 71 755 54 54",
    "sg:postcode":"4002",
    "sg:province":"Basel-Stadt",
    "wof:name":"Rhenum Treuhand Ag",
    "wof:placetype":"venue"
},
  "geometry": {"coordinates":[9.5398807526,47.3787651062],"type":"Point"}
}