{
  "type": "Feature",
  "properties": {
    "iso:country":"CH",
    "sg:address":"Tschumi Rue Adolphe- 3",
    "sg:city":"Gen\u00e8ve",
    "sg:orig_category":"Unclassifiable Establishments",
    "sg:phone":"+41 22 740 27 34",
    "sg:postcode":"1201",
    "sg:province":"Gen\u00e8ve",
    "wof:name":"Domforall, Rouiller",
    "wof:placetype":"venue"
},
  "geometry": {"coordinates":[6.1369171143,46.2099189758],"type":"Point"}
}