{
  "type": "Feature",
  "properties": {
    "iso:country":"CH",
    "sg:address":"Hasenhof 137",
    "sg:city":"Fisibach",
    "sg:orig_category":"Detailhandel mit Blumen U Pflanzen",
    "sg:phone":"+41 22 798 79 22",
    "sg:postcode":"5467",
    "sg:province":"Aargau",
    "wof:name":"Marie-jos\u00e9 Bard Boutique De Fleurs",
    "wof:placetype":"venue"
},
  "geometry": {"coordinates":[6.12329,46.233925],"type":"Point"}
}