{
  "type": "Feature",
  "properties": {
    "addr:full":"Sechtbachweg 29 B\u00fclach Z\u00fcrich 8180",
    "addr:housenumber":"29",
    "addr:postcode":"8180",
    "addr:street":"Sechtbachweg;Zuerich",
    "iso:country":"CH",
    "sg:address":"Sechtbachweg 29",
    "sg:city":"B\u00fclach",
    "sg:orig_category":"Architektur U Ingenieurb\u00fcros",
    "sg:postcode":"8180",
    "sg:province":"Z\u00fcrich",
    "wof:name":"E + H Ingenieurb\u00fcro F\u00fcr Energie + Haustechnik Ag, Niederlassung B\u00fclach",
    "wof:placetype":"venue"
},
  "geometry": {"coordinates":[8.548529,47.519859],"type":"Point"}
}