{
  "type": "Feature",
  "properties": {
    "iso:country":"CH",
    "sg:address":"Saint Eloi Route 31 1470 Estavayer-le-lac. Postfach",
    "sg:city":"Estavayer-le-lac",
    "sg:orig_category":"Instandhaltung U Reparatur von Automobilen",
    "sg:phone":"+41 26 663 81 28",
    "sg:postcode":"1470",
    "sg:province":"Fribourg",
    "wof:name":"Haymoz G. S\u00e0rl V\u00e9hicules \u00e0 Moteur; Achat, Vente De Toutes Fournitures Etc",
    "wof:placetype":"venue"
},
  "geometry": {"coordinates":[6.856361866,46.8474578857],"type":"Point"}
}