{
  "type": "Feature",
  "properties": {
    "iso:country":"CH",
    "sg:address":"Rotachstrasse 33",
    "sg:city":"Z\u00fcrich",
    "sg:orig_category":"RESTAURANTS: TEA-ROOMS",
    "sg:postcode":"8003",
    "sg:province":"Z\u00fcrich",
    "wof:name":"Pius Niederberger",
    "wof:placetype":"venue"
},
  "geometry": {"coordinates":[8.5147924423,47.3707275391],"type":"Point"}
}