{
  "type": "Feature",
  "properties": {
    "iso:country":"CH",
    "sg:address":"Stampfenbachstrasse 73",
    "sg:city":"Z\u00fcrich",
    "sg:orig_category":"Sonstiger Grosshandel",
    "sg:postcode":"8006",
    "sg:province":"Z\u00fcrich",
    "wof:name":"E.c.i.t. Ag",
    "wof:placetype":"venue"
},
  "geometry": {"coordinates":[8.5416574478,47.3817901611],"type":"Point"}
}