{
  "type": "Feature",
  "properties": {
    "iso:country":"CH",
    "sg:address":"Klingelbergstrasse 77",
    "sg:city":"Basel",
    "sg:orig_category":"Werbegrafikateliers",
    "sg:phone":"+41 61 321 22 34",
    "sg:postcode":"4056",
    "sg:province":"Basel-Stadt",
    "wof:name":"Annette Br\u00e4uning Grafisches Atelier",
    "wof:placetype":"venue"
},
  "geometry": {"coordinates":[7.5794830322,47.5635490417],"type":"Point"}
}