{
  "type": "Feature",
  "properties": {
    "iso:country":"CH",
    "sg:address":"Rigistrasse 1",
    "sg:city":"Cham",
    "sg:orig_category":"Betrieb von Sportanlagen",
    "sg:phone":"+41 41 784 05 81",
    "sg:postcode":"6330",
    "sg:province":"Zug",
    "wof:name":"Sport Und Leistungszentrum Wiget Stephan",
    "wof:placetype":"venue"
},
  "geometry": {"coordinates":[8.455793,47.181347],"type":"Point"}
}