{
  "type": "Feature",
  "properties": {
    "iso:country":"CH",
    "sg:address":"Gerliswilstrasse 50",
    "sg:city":"Emmenbr\u00fccke",
    "sg:orig_category":"Grosshandel mit sonstigen Gebrauchs U Verbrauchsg\u00fctern Sonstiger Fachdetailhandel in Verkaufsr\u00e4umen",
    "sg:phone":"+41 41 260 33 83",
    "sg:postcode":"6020",
    "sg:province":"Luzern",
    "wof:name":"Beat Dahinden Waffengesch\u00e4ft",
    "wof:placetype":"venue"
},
  "geometry": {"coordinates":[8.2774543762,47.0740585327],"type":"Point"}
}