{
  "type": "Feature",
  "properties": {
    "iso:country":"CH",
    "sg:address":"Maugwil",
    "sg:city":"Bronschhofen",
    "sg:orig_category":"Grosshandel mit lebenden Tieren",
    "sg:phone":"+41 71 911 04 53",
    "sg:postcode":"9552",
    "sg:province":"St. Gallen",
    "wof:name":"Braun Walter",
    "wof:placetype":"venue"
},
  "geometry": {"coordinates":[9.0478000641,47.4887695312],"type":"Point"}
}