{
  "type": "Feature",
  "properties": {
    "iso:country":"CH",
    "sg:address":"Langgartenstrasse 9 8280 Kreuzlingen. Postfach",
    "sg:city":"Kreuzlingen",
    "sg:orig_category":"Hardwareberatung Informatikdienste",
    "sg:postcode":"8280",
    "sg:province":"Thurgau",
    "wof:name":"Pc-top Jetzer Pc-support Und Verkauf. Webdesign",
    "wof:placetype":"venue"
},
  "geometry": {"coordinates":[9.1686658859,47.6443557739],"type":"Point"}
}