{
  "type": "Feature",
  "properties": {
    "iso:country":"CH",
    "sg:address":"Allmendweg 4",
    "sg:city":"Zuchwil",
    "sg:orig_category":"Sonstige pers\u00f6nliche Dienstleistungen",
    "sg:postcode":"4528",
    "sg:province":"Solothurn",
    "wof:name":"G&d Callcenter Gmbh",
    "wof:placetype":"venue"
},
  "geometry": {"coordinates":[7.5512962341,47.2001037598],"type":"Point"}
}