{
  "type": "Feature",
  "properties": {
    "iso:country":"CH",
    "sg:address":"M\u00fcllernstrasse 2",
    "sg:city":"Rothenthurm",
    "sg:orig_category":"Nationale Postdienste",
    "sg:phone":"+41 41 930 18 10",
    "sg:postcode":"6418",
    "sg:province":"Schwyz",
    "wof:name":"Die Schweizerische Post",
    "wof:placetype":"venue"
},
  "geometry": {"coordinates":[8.1550931931,47.2186546326],"type":"Point"}
}