{
  "type": "Feature",
  "properties": {
    "iso:country":"CH",
    "sg:address":"Vidollet Rue Du 5 1202 Gen\u00e8ve. Postfach",
    "sg:city":"Gen\u00e8ve",
    "sg:orig_category":"Elektrizit\u00e4tsversorgung",
    "sg:postcode":"1201",
    "sg:province":"Gen\u00e8ve",
    "wof:name":"Redi Renewable Energy Development Institut Sa",
    "wof:placetype":"venue"
},
  "geometry": {"coordinates":[6.1390900612,46.2163543701],"type":"Point"}
}