{
  "type": "Feature",
  "properties": {
    "iso:country":"CH",
    "sg:address":"Innere Margarethenstrasse 9",
    "sg:city":"Basel",
    "sg:orig_category":"Sonstige Verkehrsvermittlung",
    "sg:phone":"+41 61 283 70 20",
    "sg:postcode":"4051",
    "sg:province":"Basel-Stadt",
    "wof:name":"Die_fahrschule Maja Finazzi & Mauro Menoia",
    "wof:placetype":"venue"
},
  "geometry": {"coordinates":[7.5870141983,47.5502891541],"type":"Point"}
}