{
  "type": "Feature",
  "properties": {
    "iso:country":"CH",
    "sg:address":"Durachweg 25",
    "sg:city":"Schaffhausen",
    "sg:orig_category":"Ergotherapie",
    "sg:phone":"+41 52 620 06 57",
    "sg:postcode":"8200",
    "sg:province":"Schaffhausen",
    "wof:name":"Regula Steger Praxis F\u00fcr Ergotherapie",
    "wof:placetype":"venue"
},
  "geometry": {"coordinates":[8.6314754486,47.6998825073],"type":"Point"}
}