{
  "type": "Feature",
  "properties": {
    "iso:country":"CH",
    "sg:address":"Zur Alten Post 9478 Azmoos. Postfach",
    "sg:city":"Tr\u00fcbbach",
    "sg:orig_category":"Grosshandel mit Textilien",
    "sg:phone":"+41 81 783 11 39",
    "sg:postcode":"9477",
    "sg:province":"St. Gallen",
    "wof:name":"Gabathuler H. + M.",
    "wof:placetype":"venue"
},
  "geometry": {"coordinates":[9.4766893387,47.0802955627],"type":"Point"}
}