{
  "type": "Feature",
  "properties": {
    "addr:full":"Im Holzacker 1 Wallisellen Z\u00fcrich 8304",
    "addr:housenumber":"1",
    "addr:postcode":"8304",
    "addr:street":"Im Holzacker",
    "iso:country":"CH",
    "sg:address":"Im Holzacker 1",
    "sg:city":"Wallisellen",
    "sg:classifiers":[
        {
            "category":"Banks & Credit Unions",
            "subcategory":"Bank",
            "type":"Services"
        }
    ],
    "sg:phone":"+41 22 707 09 09",
    "sg:postcode":"8304",
    "sg:province":"Z\u00fcrich",
    "wof:name":"Kbc Bank (suisse) Sa",
    "wof:placetype":"venue"
},
  "geometry": {"coordinates":[6.154617,46.20369],"type":"Point"}
}