{
  "type": "Feature",
  "properties": {
    "addr:full":"Obertor 21 Winterthur Z\u00fcrich 8400",
    "addr:housenumber":"21",
    "addr:postcode":"8400",
    "addr:street":"Obertor",
    "iso:country":"CH",
    "sg:address":"Obertor 21",
    "sg:city":"Winterthur",
    "sg:orig_category":"Detailhandel mit Brot, Back U S\u00fcsswaren",
    "sg:phone":"+41 26 918 51 45",
    "sg:postcode":"8400",
    "sg:province":"Z\u00fcrich",
    "wof:name":"Pittet Bernard",
    "wof:placetype":"venue"
},
  "geometry": {"coordinates":[6.910448,46.609623],"type":"Point"}
}