{
  "type": "Feature",
  "properties": {
    "iso:country":"CH",
    "sg:address":"Village Rue Du 16",
    "sg:city":"Corseaux",
    "sg:orig_category":"Detailhandel mit Brot, Back U S\u00fcsswaren",
    "sg:postcode":"1802",
    "sg:province":"Vaud",
    "wof:name":"Charles Marcel S\u00e0rl",
    "wof:placetype":"venue"
},
  "geometry": {"coordinates":[6.832858,46.472244],"type":"Point"}
}