{
  "type": "Feature",
  "properties": {
    "iso:country":"CH",
    "sg:address":"R\u00fctihalde 5",
    "sg:city":"Herisau",
    "sg:orig_category":"Arbeitnehmerverb\u00e4nde",
    "sg:phone":"+41 71 351 65 31",
    "sg:postcode":"9100",
    "sg:province":"Appenzell Ausserrhoden",
    "wof:name":"Gewerkschaftsbund Ar Pr\u00e4s.herrn Matthias Weber",
    "wof:placetype":"venue"
},
  "geometry": {"coordinates":[9.286489,47.395088],"type":"Point"}
}