{
  "type": "Feature",
  "properties": {
    "iso:country":"CH",
    "sg:address":"Kasinostrasse 30",
    "sg:city":"Aarau",
    "sg:orig_category":"Detailhandel mit Schuhen Detailhandel mit Schuhen U Lederwaren",
    "sg:phone":"+41 62 822 43 20",
    "sg:postcode":"5000",
    "sg:province":"Aargau",
    "wof:name":"Schuh Treff Wehrli",
    "wof:placetype":"venue"
},
  "geometry": {"coordinates":[8.0468358994,47.3919754028],"type":"Point"}
}