{
  "type": "Feature",
  "properties": {
    "iso:country":"CH",
    "sg:address":"Schulstrasse 81",
    "sg:city":"Schlieren",
    "sg:orig_category":"Herstellung von Metallkonstruktionen",
    "sg:phone":"+41 17731777",
    "sg:postcode":"8952",
    "sg:province":"Z\u00fcrich",
    "wof:name":"Celik Erkan, Ec-planung",
    "wof:placetype":"venue"
},
  "geometry": {"coordinates":[8.4627513885,47.3962364197],"type":"Point"}
}