{
  "type": "Feature",
  "properties": {
    "iso:country":"CH",
    "sg:address":"Industriestrasse 10 6170 Sch\u00fcpfheim. Postfach 161",
    "sg:city":"Sch\u00fcpfheim",
    "sg:orig_category":"Herstellung von Verpackungsmitteln aus Holz Herstellung von Verpackungsmittelnaus Holz",
    "sg:phone":"+41 41 484 17 37",
    "sg:postcode":"6170",
    "sg:province":"Luzern",
    "wof:name":"Kistag Dekopack Ag",
    "wof:placetype":"venue"
},
  "geometry": {"coordinates":[8.0139732361,46.9501838684],"type":"Point"}
}