{
  "type": "Feature",
  "properties": {
    "iso:country":"CH",
    "sg:address":"Haltenstrasse 21",
    "sg:city":"Walchwil",
    "sg:orig_category":"Personal U Stellenvermittlung Unternehmensberatung",
    "sg:phone":"+41 41 759 07 50",
    "sg:postcode":"6318",
    "sg:province":"Zug",
    "wof:name":"Pe-con Institut Ag Personal-& Unternehmensberat.",
    "wof:placetype":"venue"
},
  "geometry": {"coordinates":[8.5165233612,47.1023368835],"type":"Point"}
}