{
  "type": "Feature",
  "properties": {
    "addr:full":"Amselweg 1 Ostermundigen Bern 3072",
    "addr:housenumber":"1",
    "addr:postcode":"3072",
    "addr:street":"Amselweg",
    "iso:country":"CH",
    "sg:address":"Amselweg 1",
    "sg:city":"Ostermundigen",
    "sg:orig_category":"Bauspenglerei Zimmerei, Dachdeckerei, Bauspenglerei U Abdichtung",
    "sg:phone":"+41 31 931 16 56",
    "sg:postcode":"3072",
    "sg:province":"Bern",
    "wof:name":"W\u00e4lti Ag, Ostermundigen",
    "wof:placetype":"venue"
},
  "geometry": {"coordinates":[7.48378,46.954231],"type":"Point"}
}