{
  "type": "Feature",
  "properties": {
    "iso:country":"CH",
    "sg:address":"Engelgasse 109 4052 Basel. Postfach",
    "sg:city":"Basel",
    "sg:orig_category":"Unclassifiable Establishments",
    "sg:phone":"+41 61 706 48 48",
    "sg:postcode":"4051",
    "sg:province":"Basel-Stadt",
    "wof:name":"Pentapharm Holding Ag Beteiligungen Usw",
    "wof:placetype":"venue"
},
  "geometry": {"coordinates":[7.604989,47.547611],"type":"Point"}
}