{
  "type": "Feature",
  "properties": {
    "iso:country":"CH",
    "sg:address":"Ganischastrasse 7",
    "sg:city":"Flums",
    "sg:orig_category":"D\u00e4mmung gegen K\u00e4lte, W\u00e4rme, Schall U Ersch\u00fctterung",
    "sg:phone":"+41 32 652 74 44",
    "sg:postcode":"8890",
    "sg:province":"St. Gallen",
    "wof:name":"Hans Unger Isolationen",
    "wof:placetype":"venue"
},
  "geometry": {"coordinates":[7.3631238937,47.1785125732],"type":"Point"}
}