{
  "type": "Feature",
  "properties": {
    "iso:country":"CH",
    "sg:address":"F\u00e4llandenstrasse 6",
    "sg:city":"Maur",
    "sg:orig_category":"Kauf U Verkauf von Immobilien auf eigene Rechnung",
    "sg:postcode":"8124",
    "sg:province":"Z\u00fcrich",
    "wof:name":"P\u00fcntacker Ag",
    "wof:placetype":"venue"
},
  "geometry": {"coordinates":[8.6691169739,47.3413085938],"type":"Point"}
}