{
  "type": "Feature",
  "properties": {
    "iso:country":"CH",
    "sg:address":"Route De Movelier 2",
    "sg:city":"Mettembert",
    "sg:orig_category":"Instandhaltung U Reparatur von Automobilen",
    "sg:phone":"+41 32 422 68 48",
    "sg:postcode":"2806",
    "sg:province":"Jura",
    "wof:name":"Garage Ch\u00e8vre Sa",
    "wof:placetype":"venue"
},
  "geometry": {"coordinates":[7.3198652267,47.3980560303],"type":"Point"}
}