{
  "type": "Feature",
  "properties": {
    "iso:country":"CH",
    "sg:address":"Schupfenzelgstrasse 1",
    "sg:city":"Diessenhofen",
    "sg:orig_category":"Hardwareberatung",
    "sg:postcode":"8253",
    "sg:province":"Thurgau",
    "wof:name":"Dajo-pc, Matuzic Dragan",
    "wof:placetype":"venue"
},
  "geometry": {"coordinates":[8.7568750381,47.6846046448],"type":"Point"}
}