{
  "type": "Feature",
  "properties": {
    "iso:country":"CH",
    "sg:address":"Terbinerstrasse 21",
    "sg:city":"Visp",
    "sg:orig_category":"HOTELS: OHNE RESTAURANT",
    "sg:phone":"+41 27 946 25 02",
    "sg:postcode":"3930",
    "sg:province":"Valais",
    "wof:name":"Pension Haus Sch\u00f6nblick",
    "wof:placetype":"venue"
},
  "geometry": {"coordinates":[7.8856511116,46.2898521423],"type":"Point"}
}