{
  "type": "Feature",
  "properties": {
    "iso:country":"CH",
    "sg:address":"Haldenstrasse 23 8957 Spreitenbach. Postfach 1414",
    "sg:city":"Spreitenbach",
    "sg:orig_category":"Datenverarbeitungsdienste Hardwareberatung",
    "sg:phone":"+41 79 357 20 90",
    "sg:postcode":"8957",
    "sg:province":"Aargau",
    "wof:name":"Walther Communications",
    "wof:placetype":"venue"
},
  "geometry": {"coordinates":[8.364854,47.414982],"type":"Point"}
}