{
  "type": "Feature",
  "properties": {
    "iso:country":"CH",
    "sg:address":"H\u00e4ngelenstrasse 1 3325 Hettiswil. Postfach",
    "sg:city":"Hettiswil",
    "sg:orig_category":"Fachdetailhandel in Verkaufsr\u00e4umen",
    "sg:postcode":"3325",
    "sg:province":"Bern",
    "wof:name":"Schneiter V. Ag",
    "wof:placetype":"venue"
},
  "geometry": {"coordinates":[8.3174819946,47.2825775146],"type":"Point"}
}