{
  "type": "Feature",
  "properties": {
    "addr:full":"Kurzenbergstrasse 6 St.gallen St. Gallen 9000",
    "addr:housenumber":"6",
    "addr:postcode":"9000",
    "addr:street":"Kurzenbergstrasse",
    "iso:country":"CH",
    "sg:address":"Kurzenbergstrasse 6",
    "sg:city":"St.gallen",
    "sg:orig_category":"Architektur U Ingenieurb\u00fcros",
    "sg:phone":"+41 71 277 17 68",
    "sg:postcode":"9000",
    "sg:province":"St. Gallen",
    "wof:name":"Wiemann Wilhelm Ag, St. Gallen",
    "wof:placetype":"venue"
},
  "geometry": {"coordinates":[9.361717,47.424],"type":"Point"}
}