{
  "type": "Feature",
  "properties": {
    "iso:country":"CH",
    "sg:address":"Niederholzstrasse 9",
    "sg:city":"Kesswil",
    "sg:orig_category":"Handelsvermittlung U Grosshandel",
    "sg:phone":"+41 62 842 68 18",
    "sg:postcode":"8593",
    "sg:province":"Thurgau",
    "wof:name":"Rc Handel & Vertrieb Christian Rufer",
    "wof:placetype":"venue"
},
  "geometry": {"coordinates":[8.07234478,47.3840751648],"type":"Point"}
}