{
  "type": "Feature",
  "properties": {
    "iso:country":"CH",
    "sg:address":"1971",
    "sg:city":"Grimisuat",
    "sg:orig_category":"Bauspenglerei Dachdeckerei",
    "sg:phone":"+41 79 685 16 48",
    "sg:postcode":"1971",
    "sg:province":"Valais",
    "wof:name":"Manz Isolazioni Sa",
    "wof:placetype":"venue"
},
  "geometry": {"coordinates":[8.920732,46.096455],"type":"Point"}
}