{
  "type": "Feature",
  "properties": {
    "iso:country":"CH",
    "sg:address":"Biblisweg 32",
    "sg:city":"Herzogenbuchsee",
    "sg:classifiers":[
        {
            "category":"Banks & Credit Unions",
            "subcategory":"Financial Services",
            "type":"Services"
        }
    ],
    "sg:phone":"+41 81 322 61 31",
    "sg:postcode":"3360",
    "sg:province":"Bern",
    "sg:tags":[
        "cutting",
        "gear"
    ],
    "wof:name":"Hofmann Ag",
    "wof:placetype":"venue"
},
  "geometry": {"coordinates":[9.5669994354,46.9532699585],"type":"Point"}
}