{
  "type": "Feature",
  "properties": {
    "iso:country":"CH",
    "sg:address":"Rathausgasse 10 5400 Baden. Postfach",
    "sg:city":"Baden",
    "sg:classifiers":[
        {
            "category":"Bars & Pubs",
            "type":"Food & Drink"
        }
    ],
    "sg:postcode":"5400",
    "sg:province":"Aargau",
    "wof:name":"Gastrobetrieb Rissi",
    "wof:placetype":"venue"
},
  "geometry": {"coordinates":[8.308805,47.473152],"type":"Point"}
}