{
  "type": "Feature",
  "properties": {
    "iso:country":"CH",
    "sg:address":"G\u00e4ssliackerweg 4",
    "sg:city":"Breitenbach",
    "sg:orig_category":"Kosmetikinstitute",
    "sg:phone":"+41 61 781 36 90",
    "sg:postcode":"4226",
    "sg:province":"Solothurn",
    "wof:name":"Annemarie Jermann Kosmetikinstitut",
    "wof:placetype":"venue"
},
  "geometry": {"coordinates":[7.5467882156,47.4065246582],"type":"Point"}
}