{
  "type": "Feature",
  "properties": {
    "addr:full":"S\u00e4genstr. 75 Chur Graubunden 7000",
    "addr:housenumber":"75",
    "addr:postcode":"7000",
    "addr:street":"Saegenstr.",
    "iso:country":"CH",
    "sg:address":"S\u00e4genstr. 75",
    "sg:city":"Chur",
    "sg:orig_category":"Immobilien U Baugewerbe, Baustoffe U Bauelemente",
    "sg:phone":"+41 81 253 70 71",
    "sg:postcode":"7000",
    "sg:province":"Graubunden",
    "wof:name":"Gas-center M. Honegger Ag",
    "wof:placetype":"venue"
},
  "geometry": {"coordinates":[9.525008,46.84877],"type":"Point"}
}