{
  "type": "Feature",
  "properties": {
    "iso:country":"CH",
    "sg:address":"Entfelderstrasse 1 5000 Aarau. Postfach",
    "sg:city":"Aarau",
    "sg:orig_category":"Wirtschaftspr\u00fcfung, Steuerberatung U Treuhand",
    "sg:phone":"+41 62 824 44 42",
    "sg:postcode":"5001",
    "sg:province":"Aargau",
    "wof:name":"Veritas Treuhand Ag",
    "wof:placetype":"venue"
},
  "geometry": {"coordinates":[8.0483398438,47.3891067505],"type":"Point"}
}