{
  "type": "Feature",
  "properties": {
    "iso:country":"CH",
    "sg:address":"Ackerweg 6",
    "sg:city":"Wettswil",
    "sg:orig_category":"Non-Classified Establishments",
    "sg:postcode":"8907",
    "sg:province":"Z\u00fcrich",
    "wof:name":"Toplabel Gmbh",
    "wof:placetype":"venue"
},
  "geometry": {"coordinates":[8.4787139893,47.3380813599],"type":"Point"}
}