{
  "type": "Feature",
  "properties": {
    "iso:country":"CH",
    "sg:address":"Bahnhofstrasse 30",
    "sg:city":"Zug",
    "sg:orig_category":"Unclassifiable Establishments",
    "sg:postcode":"6300",
    "sg:province":"Zug",
    "wof:name":"It Wing Gmbh",
    "wof:placetype":"venue"
},
  "geometry": {"coordinates":[8.8288326263,47.2294769287],"type":"Point"}
}