{
  "type": "Feature",
  "properties": {
    "iso:country":"CH",
    "sg:address":"Vanoni Via 10",
    "sg:city":"Lugano",
    "sg:orig_category":"Institutionen des Sozialwesens ohne Beherbergung",
    "sg:postcode":"6900",
    "sg:province":"Ticino",
    "wof:name":"Associazione Mons. Eugenio Corecco Per La Famiglia",
    "wof:placetype":"venue"
},
  "geometry": {"coordinates":[8.9526634216,46.0114936829],"type":"Point"}
}