{
  "type": "Feature",
  "properties": {
    "iso:country":"CH",
    "sg:address":"Rofenbergstrasse 120",
    "sg:city":"Eschen",
    "sg:classifiers":[
        {
            "category":"Restaurant",
            "type":"Food & Drink"
        }
    ],
    "sg:postcode":"9492",
    "wof:name":"Gasthaus Hirschen",
    "wof:placetype":"venue"
},
  "geometry": {"coordinates":[9.5181503296,47.2152290344],"type":"Point"}
}