{
  "type": "Feature",
  "properties": {
    "iso:country":"CH",
    "sg:address":"Ringstrasse 29 4106 Therwil. Postfach 360",
    "sg:city":"Therwil",
    "sg:orig_category":"Herstellung von Medikamenten U sonstigen pharmazeutischen Erzeugnissen Herstellung von pharmazeutisc",
    "sg:phone":"+41 61 721 60 77",
    "sg:postcode":"4106",
    "sg:province":"Basel-Landschaft",
    "wof:name":"Permamed Ag",
    "wof:placetype":"venue"
},
  "geometry": {"coordinates":[7.5554099083,47.5047874451],"type":"Point"}
}