{
  "type": "Feature",
  "properties": {
    "iso:country":"CH",
    "sg:address":"Buechstrasse 1",
    "sg:city":"Eggenwil",
    "sg:orig_category":"Detailhandel mit Waren verschiedener Art, Hauptrichtung Nahrungsmittel",
    "sg:phone":"+41 52 264 26 16",
    "sg:postcode":"5445",
    "sg:province":"Aargau",
    "wof:name":"Volg Detailhandels Ag",
    "wof:placetype":"venue"
},
  "geometry": {"coordinates":[8.3416786194,47.3694458008],"type":"Point"}
}