{
  "type": "Feature",
  "properties": {
    "iso:country":"CH",
    "sg:address":"Oberdettigenstrasse 10",
    "sg:city":"Uettligen",
    "sg:orig_category":"Datenverarbeitungsdienste",
    "sg:phone":"+41 31 829 42 42",
    "sg:postcode":"3043",
    "sg:province":"Bern",
    "wof:name":"Christian Schlachter Didata",
    "wof:placetype":"venue"
},
  "geometry": {"coordinates":[7.385908,46.985504],"type":"Point"}
}