{
  "type": "Feature",
  "properties": {
    "iso:country":"CH",
    "sg:address":"Rue Des Somm\u00eatres 1a 2350 Saignel\u00e9gier. Postfach",
    "sg:city":"Saignel\u00e9gier",
    "sg:orig_category":"Datenverarbeitungsdienste",
    "sg:postcode":"2350",
    "sg:province":"Jura",
    "wof:name":"Tnt Logistics Switzerland Ag Logistik-dienstleistungen Usw",
    "wof:placetype":"venue"
},
  "geometry": {"coordinates":[8.069544,47.393307],"type":"Point"}
}