{
  "type": "Feature",
  "properties": {
    "addr:full":"Rue Des Noyers 11 Neuch\u00e2tel Neuch\u00e2tel 2000",
    "addr:housenumber":"11",
    "addr:postcode":"2000",
    "addr:street":"Rue Des Noyers",
    "iso:country":"CH",
    "sg:address":"Rue Des Noyers 11",
    "sg:city":"Neuch\u00e2tel",
    "sg:orig_category":"Bauschreinerei Herstellung von M\u00f6beln verschiedener Art",
    "sg:phone":"+41 32 730 12 85",
    "sg:postcode":"2000",
    "sg:province":"Neuch\u00e2tel",
    "wof:name":"Jean-michel Schaer Menuiserie & \u00e9b\u00e9nisterie",
    "wof:placetype":"venue"
},
  "geometry": {"coordinates":[6.898531,46.984573],"type":"Point"}
}