{
  "type": "Feature",
  "properties": {
    "iso:country":"CH",
    "sg:address":"Route De Certoux 13d",
    "sg:city":"Perly",
    "sg:orig_category":"Fahrschulen, Flugschulen",
    "sg:phone":"+41 79 624 79 95",
    "sg:postcode":"1258",
    "sg:province":"Gen\u00e8ve",
    "wof:name":"G\u00e9rald Clerc Auto-\u00e9cole",
    "wof:placetype":"venue"
},
  "geometry": {"coordinates":[6.0971589088,46.1579246521],"type":"Point"}
}