{
  "type": "Feature",
  "properties": {
    "iso:country":"CH",
    "sg:address":"Oberhofstrasse 7 6020 Emmenbr\u00fccke. Postfach",
    "sg:city":"Emmenbr\u00fccke",
    "sg:orig_category":"Allgemeinbildende weiterf\u00fchrende Schulen",
    "sg:postcode":"6020",
    "sg:province":"Luzern",
    "wof:name":"Kai-ru Ruedi Kaiser",
    "wof:placetype":"venue"
},
  "geometry": {"coordinates":[8.284094,47.072964],"type":"Point"}
}