{
  "type": "Feature",
  "properties": {
    "iso:country":"CH",
    "sg:address":"Luzernstrasse 17",
    "sg:city":"Neuenkirch",
    "sg:orig_category":"Detailhandel mit Beleuchtungs U Haushaltsgegenst\u00e4nden Detailhandel mit Textilien",
    "sg:phone":"+41 41 460 15 25",
    "sg:postcode":"6206",
    "sg:province":"Luzern",
    "wof:name":"Emma Huser Vorh\u00e4nge-aussteuern",
    "wof:placetype":"venue"
},
  "geometry": {"coordinates":[8.205962,47.098331],"type":"Point"}
}