{
  "type": "Feature",
  "properties": {
    "iso:country":"CH",
    "sg:address":"Hauptstrasse 1",
    "sg:city":"G\u00e4chliwil",
    "sg:orig_category":"Bastel- and Hobbyartikel Detailhandel Erwachsenenbildung U Unterricht",
    "sg:phone":"+41 32 351 23 30",
    "sg:postcode":"4584",
    "sg:province":"Solothurn",
    "wof:name":"Anna-katharina Wehrle Bastelbedarf Les Id\u00e9es",
    "wof:placetype":"venue"
},
  "geometry": {"coordinates":[7.44658,47.130501],"type":"Point"}
}