{
  "type": "Feature",
  "properties": {
    "iso:country":"CH",
    "sg:address":"Laupenackerstrasse 32c",
    "sg:city":"Moosseedorf",
    "sg:orig_category":"Grosshandel mit Datenverarbeitungsger\u00e4ten",
    "sg:phone":"+41 22 798 05 50",
    "sg:postcode":"3302",
    "sg:province":"Bern",
    "wof:name":"Magic-pixel S\u00e0rl Supports Informatiques",
    "wof:placetype":"venue"
},
  "geometry": {"coordinates":[6.118159771,46.2299690247],"type":"Point"}
}