{
  "type": "Feature",
  "properties": {
    "iso:country":"CH",
    "sg:address":"Schwerzbachstrasse",
    "sg:city":"Giswil",
    "sg:orig_category":"Pipe Cleaning Plants",
    "sg:phone":"+41 81 854 24 40",
    "sg:postcode":"6074",
    "sg:province":"Obwalden",
    "wof:name":"Obag Pontresina Ag",
    "wof:placetype":"venue"
},
  "geometry": {"coordinates":[9.922369957,46.57862854],"type":"Point"}
}