{
  "type": "Feature",
  "properties": {
    "addr:full":"Bildstrasse 3 Abtwil St. Gallen 9030",
    "addr:housenumber":"3",
    "addr:postcode":"9030",
    "addr:street":"Bildstrasse",
    "iso:country":"CH",
    "sg:address":"Bildstrasse 3",
    "sg:city":"Abtwil",
    "sg:classifiers":[
        {
            "category":"Autos & Motor Vehicles",
            "subcategory":"Auto Supplies",
            "type":"Retail Goods"
        }
    ],
    "sg:phone":"+41 71 313 68 68",
    "sg:postcode":"9030",
    "sg:province":"St. Gallen",
    "sg:tags":[
        "automobile",
        "painting"
    ],
    "wof:name":"Stratos Automobile Ag",
    "wof:placetype":"venue"
},
  "geometry": {"coordinates":[9.312679,47.417068],"type":"Point"}
}