{
  "type": "Feature",
  "properties": {
    "iso:country":"CH",
    "sg:address":"Niederfeldstrasse 24",
    "sg:city":"Wiesendangen",
    "sg:orig_category":"Vorschulen, Kinderg\u00e4rten",
    "sg:phone":"+41 52 337 10 15",
    "sg:postcode":"8542",
    "sg:province":"Z\u00fcrich",
    "wof:name":"Kindergarten Leingr\u00fcebler",
    "wof:placetype":"venue"
},
  "geometry": {"coordinates":[8.7821941376,47.5245895386],"type":"Point"}
}