{
  "type": "Feature",
  "properties": {
    "iso:country":"CH",
    "sg:address":"St. Gallerstrasse 15/17",
    "sg:city":"Arbon",
    "sg:orig_category":"Drogerien Sonstiger Fachdetailhandel mit Nahrungsmitteln, Getr\u00e4nken U Tabak in Verkaufsr\u00e4umen",
    "sg:phone":"+41 71 446 27 42",
    "sg:postcode":"9320",
    "sg:province":"Thurgau",
    "wof:name":"Dropa-drogerie Parf\u00fcmerie Reformhaus",
    "wof:placetype":"venue"
},
  "geometry": {"coordinates":[9.4306173325,47.511592865],"type":"Point"}
}