{
  "type": "Feature",
  "properties": {
    "iso:country":"CH",
    "sg:address":"Am Stausee 27",
    "sg:city":"Birsfelden",
    "sg:orig_category":"Fahrschulen, Flugschulen",
    "sg:phone":"+41 61 312 22 21",
    "sg:postcode":"4127",
    "sg:province":"Basel-Landschaft",
    "wof:name":"Erich Emmenegger Autofahrschule",
    "wof:placetype":"venue"
},
  "geometry": {"coordinates":[7.6314821243,47.5557174683],"type":"Point"}
}