{
  "type": "Feature",
  "properties": {
    "iso:country":"CH",
    "sg:address":"L\u00fctzelfl\u00fchstrasse 11",
    "sg:city":"R\u00fcegsauschachen",
    "sg:orig_category":"Sanit\u00e4r U Heizungsinstallation Sanit\u00e4r, Heizungs U L\u00fcftungsinstallation",
    "sg:phone":"+41 34 461 15 58",
    "sg:postcode":"3415",
    "sg:province":"Bern",
    "wof:name":"Werner Frank Service Ag",
    "wof:placetype":"venue"
},
  "geometry": {"coordinates":[7.6598100662,47.0163955688],"type":"Point"}
}