{
  "type": "Feature",
  "properties": {
    "iso:country":"CH",
    "sg:address":"6703",
    "sg:city":"Osogna",
    "sg:orig_category":"Granit",
    "sg:phone":"+41 91 863 11 08",
    "sg:postcode":"6703",
    "sg:province":"Ticino",
    "wof:name":"Maggia Graniti Sa, Osogna",
    "wof:placetype":"venue"
},
  "geometry": {"coordinates":[8.9886751175,46.3087654114],"type":"Point"}
}