{
  "type": "Feature",
  "properties": {
    "iso:country":"CH",
    "sg:address":"St\u00f6ckackerstrasse 30",
    "sg:city":"M\u00fcnchenstein",
    "sg:orig_category":"Non-Classified Establishments",
    "sg:phone":"+41 81 833 78 41",
    "sg:postcode":"4142",
    "sg:province":"Basel-Landschaft",
    "wof:name":"Activities By Malu Gmbh Freizeit U. Sportaktivit\u00e4ten; F\u00fchrung, Organisation, Planung",
    "wof:placetype":"venue"
},
  "geometry": {"coordinates":[9.8381910324,46.4970664978],"type":"Point"}
}