{
  "type": "Feature",
  "properties": {
    "iso:country":"CH",
    "sg:address":"Beethovenstrasse 5",
    "sg:city":"Z\u00fcrich",
    "sg:orig_category":"Vermietung U Verpachtung von eigenen Immobilien Vermittlung von Immobilien",
    "sg:phone":"+41 32 724 77 40",
    "sg:postcode":"8002",
    "sg:province":"Z\u00fcrich",
    "wof:name":"Herzog Services",
    "wof:placetype":"venue"
},
  "geometry": {"coordinates":[6.9277582169,46.9970054626],"type":"Point"}
}