{
  "type": "Feature",
  "properties": {
    "iso:country":"CH",
    "sg:address":"B\u00fcgl Pitschen 7557 Vn\u00e0. Postfach",
    "sg:city":"Vn\u00e0",
    "sg:orig_category":"M\u00f6belschreinereien",
    "sg:postcode":"7557",
    "sg:province":"Graubunden",
    "wof:name":"Schreinerei Andrea Pua",
    "wof:placetype":"venue"
},
  "geometry": {"coordinates":[10.3622779846,46.8435668945],"type":"Point"}
}