{
  "type": "Feature",
  "properties": {
    "iso:country":"CH",
    "sg:address":"Igelweid 5",
    "sg:city":"Aarau",
    "sg:orig_category":"P\u00e9dicure",
    "sg:phone":"+41 62 822 10 65",
    "sg:postcode":"5000",
    "sg:province":"Aargau",
    "wof:name":"Beat Ruf P\u00e9dicure",
    "wof:placetype":"venue"
},
  "geometry": {"coordinates":[8.0460443497,47.3919715881],"type":"Point"}
}