{
  "type": "Feature",
  "properties": {
    "addr:full":"Baselstrasse 17 4203 Grellingen. Postfach Grellingen Basel-Landschaft 4203",
    "addr:housenumber":"17",
    "addr:postcode":"4203 grellingen. postfach;4203",
    "addr:street":"Baselstrasse",
    "iso:country":"CH",
    "sg:address":"Baselstrasse 17 4203 Grellingen. Postfach",
    "sg:city":"Grellingen",
    "sg:orig_category":"Dachdeckerei",
    "sg:phone":"+41 61 741 16 61",
    "sg:postcode":"4203",
    "sg:province":"Basel-Landschaft",
    "wof:name":"Ernst Schlub Dachdecker-& Kaminbaugesch\u00e4ft",
    "wof:placetype":"venue"
},
  "geometry": {"coordinates":[7.590126,47.442722],"type":"Point"}
}