{
  "type": "Feature",
  "properties": {
    "iso:country":"CH",
    "sg:address":"Arinstrasse 2",
    "sg:city":"Sevelen",
    "sg:classifiers":[
        {
            "category":"Insurance",
            "subcategory":"Insurance Agent",
            "type":"Services"
        }
    ],
    "sg:phone":"+41 31 921 25 22",
    "sg:postcode":"9475",
    "sg:province":"St. Gallen",
    "sg:tags":[
        "versicherungsagenturen",
        "-broker"
    ],
    "wof:name":"Winterthur-versicherungen Agentur Stettlen-vechigen",
    "wof:placetype":"venue"
},
  "geometry": {"coordinates":[7.5142989159,46.9577255249],"type":"Point"}
}