{
  "type": "Feature",
  "properties": {
    "iso:country":"CH",
    "sg:address":"Au Coinat 40",
    "sg:city":"Bure",
    "sg:orig_category":"Vorschulen, Kinderg\u00e4rten",
    "sg:phone":"+41 22 343 68 43",
    "sg:postcode":"2915",
    "sg:province":"Jura",
    "wof:name":"Ecole Enfantine",
    "wof:placetype":"venue"
},
  "geometry": {"coordinates":[6.1478271484,46.1843490601],"type":"Point"}
}