{
  "type": "Feature",
  "properties": {
    "iso:country":"CH",
    "sg:address":"Place Saint-fran\u00e7ois 6 1003 Lausanne Case Postale",
    "sg:city":"Lausanne",
    "sg:orig_category":"Detailhandel mit Radio U Fernsehger\u00e4ten Detailhandel mit elektrischen Haushalts-,Radio U Fernsehger\u00e4",
    "sg:phone":"+41 71 633 21 31",
    "sg:postcode":"1002",
    "sg:province":"Vaud",
    "wof:name":"Sch\u00f6nholzer Ren\u00e9 Radio-tv-hifi-video Gmbh",
    "wof:placetype":"venue"
},
  "geometry": {"coordinates":[9.1527681351,47.552116394],"type":"Point"}
}