{
  "type": "Feature",
  "properties": {
    "iso:country":"CH",
    "sg:address":"Hauptstrasse 118",
    "sg:city":"M\u00f6hlin",
    "sg:orig_category":"Instandhaltung U Reparatur von Automobilen",
    "sg:phone":"+41 61 851 25 63",
    "sg:postcode":"4313",
    "sg:province":"Aargau",
    "wof:name":"Paul Stocker",
    "wof:placetype":"venue"
},
  "geometry": {"coordinates":[7.8515548706,47.5531044006],"type":"Point"}
}