{
  "type": "Feature",
  "properties": {
    "iso:country":"CH",
    "sg:address":"Schaufelweg 29",
    "sg:city":"K\u00f6niz",
    "sg:orig_category":"Sonstige mit der Informatik verbundene T\u00e4tigkeiten",
    "sg:postcode":"3098",
    "sg:province":"Bern",
    "wof:name":"Merz Asc",
    "wof:placetype":"venue"
},
  "geometry": {"coordinates":[7.4149951935,46.910030365],"type":"Point"}
}