{
  "type": "Feature",
  "properties": {
    "iso:country":"CH",
    "sg:address":"Lettenstrasse 8",
    "sg:city":"Rotkreuz",
    "sg:classifiers":[
        {
            "category":"Government",
            "subcategory":"Post Office",
            "type":"Public Place"
        }
    ],
    "sg:phone":"+41 22 312 20 95",
    "sg:postcode":"6343",
    "sg:province":"Zug",
    "sg:tags":[
        "caf\u00e9s",
        "tea-rooms"
    ],
    "wof:name":"Caf\u00e9teria Migros",
    "wof:placetype":"venue"
},
  "geometry": {"coordinates":[6.1512880325,46.2027778625],"type":"Point"}
}