{
  "type": "Feature",
  "properties": {
    "addr:full":"Quellenstrasse 27 Z\u00fcrich Z\u00fcrich 8005",
    "addr:housenumber":"27",
    "addr:postcode":"8005",
    "addr:street":"Quellenstrasse",
    "iso:country":"CH",
    "sg:address":"Quellenstrasse 27",
    "sg:city":"Z\u00fcrich",
    "sg:orig_category":"Architekturb\u00fcros",
    "sg:phone":"+41 12733090",
    "sg:postcode":"8005",
    "sg:province":"Z\u00fcrich",
    "wof:name":"Olivier De Perrot Architekturb\u00fcro",
    "wof:placetype":"venue"
},
  "geometry": {"coordinates":[8.527808,47.384998],"type":"Point"}
}