{
  "type": "Feature",
  "properties": {
    "iso:country":"CH",
    "sg:address":"Pilatusstr. 1",
    "sg:city":"Luzern",
    "sg:classifiers":[
        {
            "category":"Home & Garden",
            "subcategory":"Furniture",
            "type":"Retail Goods"
        }
    ],
    "sg:phone":"+41 41 226 11 30",
    "sg:postcode":"6002",
    "sg:province":"Luzern",
    "sg:tags":[
        "wood"
    ],
    "wof:name":"Linsi Ag",
    "wof:placetype":"venue"
},
  "geometry": {"coordinates":[8.3089599609,47.0499572754],"type":"Point"}
}