{
  "type": "Feature",
  "properties": {
    "iso:country":"CH",
    "sg:address":"Les Baumes",
    "sg:city":"Villarepos",
    "sg:orig_category":"Sonstiger spezialisierter Hoch U Tiefbau",
    "sg:postcode":"1583",
    "sg:province":"Fribourg",
    "wof:name":"Kamsa, B. Kuhn",
    "wof:placetype":"venue"
},
  "geometry": {"coordinates":[7.0888881683,46.8818206787],"type":"Point"}
}