{
  "type": "Feature",
  "properties": {
    "iso:country":"CH",
    "sg:address":"Ankergasse 3 8942 Oberrieden. Postfach",
    "sg:city":"Oberrieden",
    "sg:orig_category":"Maler U Glasergewerbe",
    "sg:phone":"+41 17203500",
    "sg:postcode":"8942",
    "sg:province":"Z\u00fcrich",
    "wof:name":"Fausch & Co, Malerwerkstatt",
    "wof:placetype":"venue"
},
  "geometry": {"coordinates":[8.5790662766,47.2816390991],"type":"Point"}
}