{
  "type": "Feature",
  "properties": {
    "iso:country":"CH",
    "sg:address":"Winkelstrasse 2",
    "sg:city":"Riniken",
    "sg:orig_category":"Unclassifiable Establishments",
    "sg:phone":"+41 56 442 54 50",
    "sg:postcode":"5223",
    "sg:province":"Aargau",
    "wof:name":"Reding Othmar Gartenbau, Gartenpflege",
    "wof:placetype":"venue"
},
  "geometry": {"coordinates":[8.1896629333,47.4952507019],"type":"Point"}
}