{
  "type": "Feature",
  "properties": {
    "addr:full":"Chemin Des Clochetons 20 Lausanne Vaud 1004",
    "addr:housenumber":"20",
    "addr:postcode":"1004",
    "addr:street":"Chemin Des Clochetons",
    "iso:country":"CH",
    "sg:address":"Chemin Des Clochetons 20",
    "sg:city":"Lausanne",
    "sg:orig_category":"Betrieb von Taxis",
    "sg:phone":"+41 21 624 23 63",
    "sg:postcode":"1004",
    "sg:province":"Vaud",
    "wof:name":"Alfred Mer\u00e7ay Taxis",
    "wof:placetype":"venue"
},
  "geometry": {"coordinates":[6.616948,46.526684],"type":"Point"}
}