{
  "type": "Feature",
  "properties": {
    "iso:country":"CH",
    "sg:address":"Meisenrain 39 8600 D\u00fcbendorf. Postfach",
    "sg:city":"Gockhausen",
    "sg:orig_category":"Pensionskassen",
    "sg:postcode":"8044",
    "sg:province":"Z\u00fcrich",
    "wof:name":"Personalf\u00fcrsorge-stiftung Der Advico Young & Rubicam Ag Und Der Ihr Angeschlossenen Firmen",
    "wof:placetype":"venue"
},
  "geometry": {"coordinates":[8.5974884033,47.3882865906],"type":"Point"}
}