{
  "type": "Feature",
  "properties": {
    "iso:country":"CH",
    "sg:address":"Route De La Chapelle 19",
    "sg:city":"Collombey",
    "sg:orig_category":"G\u00fcterbef\u00f6rderung im Strassenverkehr",
    "sg:phone":"+41 24 472 26 87",
    "sg:postcode":"1868",
    "sg:province":"Valais",
    "wof:name":"Pascal Perret-gentil",
    "wof:placetype":"venue"
},
  "geometry": {"coordinates":[6.9458708763,46.2813110352],"type":"Point"}
}