{
  "type": "Feature",
  "properties": {
    "iso:country":"CH",
    "sg:address":"Eschenring 3 6300 Zug. Postfach 2407",
    "sg:city":"Zug",
    "sg:orig_category":"Unternehmensberatung",
    "sg:phone":"+41 41 729 30 60",
    "sg:postcode":"6302",
    "sg:province":"Zug",
    "wof:name":"Martar Ag",
    "wof:placetype":"venue"
},
  "geometry": {"coordinates":[8.517950058,47.1814498901],"type":"Point"}
}