{
  "type": "Feature",
  "properties": {
    "iso:country":"CH",
    "sg:address":"6780",
    "sg:city":"Airolo",
    "sg:orig_category":"Detailhandel mit Uhren U Schmuck Reparatur von Uhren U Schmuck",
    "sg:phone":"+41 34 445 23 66",
    "sg:postcode":"6780",
    "sg:province":"Ticino",
    "wof:name":"Greiter Ag",
    "wof:placetype":"venue"
},
  "geometry": {"coordinates":[9.5577793121,47.3789405823],"type":"Point"}
}