{
  "type": "Feature",
  "properties": {
    "iso:country":"CH",
    "sg:address":"St. Alban-anlage 37",
    "sg:city":"Basel",
    "sg:orig_category":"Unclassifiable Establishments",
    "sg:postcode":"4052",
    "sg:province":"Basel-Stadt",
    "wof:name":"Concertagency.com Gmbh",
    "wof:placetype":"venue"
},
  "geometry": {"coordinates":[7.6004562378,47.5527305603],"type":"Point"}
}