{
  "type": "Feature",
  "properties": {
    "addr:full":"Am Saumweg 10 6370 Stans. Postfach 936 Stans Nidwalden 6371",
    "addr:housenumber":"10;936",
    "addr:postcode":"6370 stans.;6371",
    "addr:street":"Am Saumweg;Postfach",
    "iso:country":"CH",
    "sg:address":"Am Saumweg 10 6370 Stans. Postfach 936",
    "sg:city":"Stans",
    "sg:orig_category":"Architektur U Ingenieurb\u00fcros Architekturb\u00fcros",
    "sg:phone":"+41 41 610 61 01",
    "sg:postcode":"6371",
    "sg:province":"Nidwalden",
    "wof:name":"Reinhard Architekten Gmbh",
    "wof:placetype":"venue"
},
  "geometry": {"coordinates":[8.366084,46.961094],"type":"Point"}
}