{
  "type": "Feature",
  "properties": {
    "iso:country":"CH",
    "sg:address":"Golattenmattgasse 2",
    "sg:city":"Aarau",
    "sg:orig_category":"Tanzschulen, Tanzlehrer",
    "sg:phone":"+41 56 622 59 00",
    "sg:postcode":"5000",
    "sg:province":"Aargau",
    "wof:name":"Tanzschule Babs Gattlen Gmbh",
    "wof:placetype":"venue"
},
  "geometry": {"coordinates":[8.0442790985,47.3920898438],"type":"Point"}
}