{
  "type": "Feature",
  "properties": {
    "iso:country":"CH",
    "sg:address":"Le Parchet",
    "sg:city":"Puidoux",
    "sg:orig_category":"Verarbeitung von Milch Verwertung von Milch",
    "sg:postcode":"1070",
    "sg:province":"Vaud",
    "wof:name":"Soci\u00e9t\u00e9 De Laiterie De L'epesse-puidoux",
    "wof:placetype":"venue"
},
  "geometry": {"coordinates":[6.7830471992,46.5209617615],"type":"Point"}
}