{
  "type": "Feature",
  "properties": {
    "iso:country":"CH",
    "sg:address":"Viktoriaplatz 2",
    "sg:city":"Bern",
    "sg:orig_category":"Technische B\u00fcros Elektro",
    "sg:phone":"+41 31 331 16 32",
    "sg:postcode":"3013",
    "sg:province":"Bern",
    "wof:name":"Em Electrocontrol Ag",
    "wof:placetype":"venue"
},
  "geometry": {"coordinates":[7.4508781433,46.9550361633],"type":"Point"}
}