{
  "type": "Feature",
  "properties": {
    "addr:full":"Hauptstrasse Ramsen Schaffhausen 8262",
    "addr:postcode":"8262",
    "addr:street":"Hauptstrasse",
    "iso:country":"CH",
    "sg:address":"Hauptstrasse",
    "sg:city":"Ramsen",
    "sg:orig_category":"Arztpraxen",
    "sg:phone":"+41 52 743 16 36",
    "sg:postcode":"8262",
    "sg:province":"Schaffhausen",
    "wof:name":"Dr.med. Budak Demiral Arzt F\u00fcr Allgemeine Medizin",
    "wof:placetype":"venue"
},
  "geometry": {"coordinates":[8.80968,47.707905],"type":"Point"}
}