{
  "type": "Feature",
  "properties": {
    "iso:country":"CH",
    "sg:address":"Chesa Muntanella 7527 Brail. Postfach",
    "sg:city":"Brail",
    "sg:orig_category":"Allgemeiner Hoch U Tiefbau",
    "sg:postcode":"7527",
    "sg:province":"Graubunden",
    "wof:name":"Hohenegger Ren\u00e9 Sarl, Impraisa Da Fabrica",
    "wof:placetype":"venue"
},
  "geometry": {"coordinates":[10.034632,46.655556],"type":"Point"}
}