{
  "type": "Feature",
  "properties": {
    "iso:country":"CH",
    "sg:address":"Luganetto Via 4",
    "sg:city":"Viganello",
    "sg:orig_category":"Unclassifiable Establishments",
    "sg:postcode":"6962",
    "sg:province":"Ticino",
    "wof:name":"Kaper Sa",
    "wof:placetype":"venue"
},
  "geometry": {"coordinates":[8.9605922699,46.0109214783],"type":"Point"}
}