{
  "type": "Feature",
  "properties": {
    "iso:country":"CH",
    "sg:address":"Hammerstrasse 81 8032 Z\u00fcrich. Postfach 1331 8032 Z\u00fcrich",
    "sg:city":"Zust",
    "sg:orig_category":"Verlagsgewerbe Werbung",
    "sg:phone":"+41 13875770",
    "sg:postcode":"32",
    "wof:name":"Travel Media Ag",
    "wof:placetype":"venue"
},
  "geometry": {"coordinates":[8.5644578934,47.3601341248],"type":"Point"}
}