{
  "type": "Feature",
  "properties": {
    "iso:country":"CH",
    "sg:address":"Via Roncaccio 13",
    "sg:city":"Savosa",
    "sg:orig_category":"Approved Service Centres Standard Software",
    "sg:phone":"+41 71 230 13 13",
    "sg:postcode":"6942",
    "sg:province":"Ticino",
    "wof:name":"Customize Ag",
    "wof:placetype":"venue"
},
  "geometry": {"coordinates":[9.370397,47.424709],"type":"Point"}
}