{
  "type": "Feature",
  "properties": {
    "iso:country":"CH",
    "sg:address":"Rheinstrasse 11",
    "sg:city":"Sargans",
    "sg:orig_category":"Organisationen des Gesundheitswesen",
    "sg:phone":"+41 81 723 12 73",
    "sg:postcode":"7320",
    "sg:province":"St. Gallen",
    "wof:name":"Samariterverein Sargans",
    "wof:placetype":"venue"
},
  "geometry": {"coordinates":[9.4425258636,47.0487747192],"type":"Point"}
}