{
  "type": "Feature",
  "properties": {
    "iso:country":"CH",
    "sg:address":"1642",
    "sg:city":"Sorens",
    "sg:orig_category":"Landesverteidigung, Sozialversicherung \u00d6ffentliche Verwaltung",
    "sg:phone":"+41 26 915 23 95",
    "sg:postcode":"1642",
    "sg:province":"Fribourg",
    "wof:name":"Centre De Protection Civile",
    "wof:placetype":"venue"
},
  "geometry": {"coordinates":[7.0537500381,46.6693954468],"type":"Point"}
}