{
  "type": "Feature",
  "properties": {
    "iso:country":"CH",
    "sg:address":"Via Vallemaggia 67 6600 Solduno. Postfach",
    "sg:city":"Locarno",
    "sg:orig_category":"Zahntechnische Laboratorien",
    "sg:phone":"+41 91 751 29 09",
    "sg:postcode":"6604",
    "sg:province":"Ticino",
    "wof:name":"Vito Buzzini Laboratorio D'odontotecnico",
    "wof:placetype":"venue"
},
  "geometry": {"coordinates":[8.7803554535,46.1695861816],"type":"Point"}
}