{
  "type": "Feature",
  "properties": {
    "addr:full":"L\u00e4ndlistrasse 8 Wiesendangen Z\u00fcrich 8542",
    "addr:housenumber":"8",
    "addr:postcode":"8542",
    "addr:street":"Laendlistrasse",
    "iso:country":"CH",
    "sg:address":"L\u00e4ndlistrasse 8",
    "sg:city":"Wiesendangen",
    "sg:orig_category":"Datenverarbeitungsdienste Sonstige mit der Informatik verbundene T\u00e4tigkeiten",
    "sg:phone":"+41 52 337 37 74",
    "sg:postcode":"8542",
    "sg:province":"Z\u00fcrich",
    "wof:name":"Acla-informatik Clal\u00fcna Edv-dienstleistungen",
    "wof:placetype":"venue"
},
  "geometry": {"coordinates":[8.779847,47.527191],"type":"Point"}
}