{
  "type": "Feature",
  "properties": {
    "iso:country":"CH",
    "sg:address":"Plaun Rueun 7165 Breil/brigels. Postfach",
    "sg:city":"Breil/brigels",
    "sg:orig_category":"Sonstige mit Sport verbundene T\u00e4tigkeiten",
    "sg:phone":"+41 81 941 12 70",
    "sg:postcode":"7165",
    "sg:province":"Graubunden",
    "wof:name":"Schweiz.ski-& Snowboardschule Brigels-waltensburg-andiast",
    "wof:placetype":"venue"
},
  "geometry": {"coordinates":[9.0621614456,46.7695846558],"type":"Point"}
}