{
  "type": "Feature",
  "properties": {
    "iso:country":"CH",
    "sg:address":"M\u00fclhauserstrasse 57",
    "sg:city":"Basel",
    "sg:orig_category":"RESTAURANTS: TEA-ROOMS",
    "sg:phone":"+41 21 944 94 04",
    "sg:postcode":"4056",
    "sg:province":"Basel-Stadt",
    "wof:name":"Pizza Riviera S\u00e0rl",
    "wof:placetype":"venue"
},
  "geometry": {"coordinates":[6.8604550362,46.4553833008],"type":"Point"}
}