{
  "type": "Feature",
  "properties": {
    "iso:country":"CH",
    "sg:address":"Joderlicka 3818 Grindelwald. Postfach",
    "sg:city":"Grindelwald",
    "sg:orig_category":"Betrieb von Sportanlagen",
    "sg:postcode":"3818",
    "sg:province":"Bern",
    "wof:name":"Glacier Bungy Grindelwald Gmbh Bungy-anlagen; Installation U. Betrieb. Sportaktivit\u00e4ten Usw",
    "wof:placetype":"venue"
},
  "geometry": {"coordinates":[8.034633,46.624371],"type":"Point"}
}