{
  "type": "Feature",
  "properties": {
    "iso:country":"CH",
    "sg:address":"In Den Ziegelh\u00f6fen 53 4000 Basel. Postfach",
    "sg:city":"Basel",
    "sg:orig_category":"Gesundheitswesen",
    "sg:phone":"+41 71 888 33 50",
    "sg:postcode":"4051",
    "sg:province":"Basel-Stadt",
    "wof:name":"Ergosystem Ag",
    "wof:placetype":"venue"
},
  "geometry": {"coordinates":[9.6398096085,47.4346199036],"type":"Point"}
}