{
  "type": "Feature",
  "properties": {
    "iso:country":"CH",
    "sg:address":"Talstrasse 47",
    "sg:city":"Arlesheim",
    "sg:orig_category":"G\u00fcterbef\u00f6rderung im Strassenverkehr",
    "sg:phone":"+41 61 701 57 61",
    "sg:postcode":"4144",
    "sg:province":"Basel-Landschaft",
    "wof:name":"Vincenzo D'ercole Transporte",
    "wof:placetype":"venue"
},
  "geometry": {"coordinates":[7.6088137627,47.4988174438],"type":"Point"}
}