{
  "type": "Feature",
  "properties": {
    "iso:country":"CH",
    "sg:address":"Dorfstrasse 69 8706 Meilen. Postfach",
    "sg:city":"Meilen",
    "sg:orig_category":"Detailhandel mit Bekleidung Detailhandel mit Damenbekleidung",
    "sg:phone":"+41 71 333 32 77",
    "sg:postcode":"8706",
    "sg:province":"Z\u00fcrich",
    "wof:name":"Westarp-diener Susanna, Boutique Sanna",
    "wof:placetype":"venue"
},
  "geometry": {"coordinates":[9.386981,47.389774],"type":"Point"}
}