{
  "type": "Feature",
  "properties": {
    "addr:full":"Lindenallee 40 3800 Interlaken. Postfach 104 Interlaken Bern 3800",
    "addr:housenumber":"40;104",
    "addr:postcode":"3800;3800",
    "addr:street":"Lindenallee;Postfach",
    "iso:country":"CH",
    "sg:address":"Lindenallee 40 3800 Interlaken. Postfach 104",
    "sg:city":"Interlaken",
    "sg:orig_category":"Architekturb\u00fcros",
    "sg:phone":"+41 22 342 75 40",
    "sg:postcode":"3800",
    "sg:province":"Bern",
    "wof:name":"Grand Praplan & Associ\u00e9s Architectes Sa",
    "wof:placetype":"venue"
},
  "geometry": {"coordinates":[6.129615,46.18132],"type":"Point"}
}