{
  "type": "Feature",
  "properties": {
    "iso:country":"CH",
    "sg:address":"2900",
    "sg:city":"Pruntrut",
    "sg:orig_category":"Herstellung von Getr\u00e4nken Herstellung von Spirituosen",
    "sg:phone":"+41 21 781 20 05",
    "sg:postcode":"2900",
    "sg:province":"Jura",
    "wof:name":"Distillerie Paul Perroud S\u00e0rl",
    "wof:placetype":"venue"
},
  "geometry": {"coordinates":[6.771586895,46.5445823669],"type":"Point"}
}