{
  "type": "Feature",
  "properties": {
    "iso:country":"CH",
    "sg:address":"Bahnhofstrasse 70",
    "sg:city":"Wettingen",
    "sg:orig_category":"Herstellung von Elektromotoren, Generatoren U Transformatoren",
    "sg:postcode":"5430",
    "sg:province":"Aargau",
    "wof:name":"Hans Leutwyler Ag",
    "wof:placetype":"venue"
},
  "geometry": {"coordinates":[8.3268260956,47.4623794556],"type":"Point"}
}