{
  "type": "Feature",
  "properties": {
    "iso:country":"CH",
    "sg:address":"Kanalstrasse 13",
    "sg:city":"Vaduz",
    "sg:orig_category":"Grosshandel mit festen Brennstoffen U Mineral\u00f6lerzeugnissen",
    "sg:phone":"+423 232 11 51",
    "sg:postcode":"9490",
    "wof:name":"Liechtensteinische Oelvertriebsgesellschaft Mbh",
    "wof:placetype":"venue"
},
  "geometry": {"coordinates":[9.5215673447,47.1249198914],"type":"Point"}
}