{
  "type": "Feature",
  "properties": {
    "iso:country":"CH",
    "sg:address":"De-normandie Chemin 14 1206 Gen\u00e8ve. Postfach",
    "sg:city":"Gen\u00e8ve",
    "sg:orig_category":"Berufsbildende weiterf\u00fchrende Schulen",
    "sg:phone":"+41 22 342 79 94",
    "sg:postcode":"1206",
    "sg:province":"Gen\u00e8ve",
    "wof:name":"Christiane Bordeau Ecole Esth\u00e9tique & Cosmetol.",
    "wof:placetype":"venue"
},
  "geometry": {"coordinates":[6.139123,46.181736],"type":"Point"}
}