{
  "type": "Feature",
  "properties": {
    "iso:country":"CH",
    "sg:address":"Allenbergstrasse 65",
    "sg:city":"St\u00e4fa",
    "sg:orig_category":"Sanit\u00e4r U Heizungsinstallation",
    "sg:phone":"+41 19261517",
    "sg:postcode":"8712",
    "sg:province":"Z\u00fcrich",
    "wof:name":"Max E. M\u00e4chler Heizungen & Kaminbau",
    "wof:placetype":"venue"
},
  "geometry": {"coordinates":[8.7203912735,47.2491455078],"type":"Point"}
}