{
  "type": "Feature",
  "properties": {
    "iso:country":"CH",
    "sg:address":"Scheideggstrasse 10a",
    "sg:city":"Winterthur",
    "sg:orig_category":"Kinderkrippen U horte",
    "sg:phone":"+41 52 233 31 49",
    "sg:postcode":"8400",
    "sg:province":"Z\u00fcrich",
    "wof:name":"Frauenbund Winterthur Kinderkrippe Schn\u00e4ggehuus",
    "wof:placetype":"venue"
},
  "geometry": {"coordinates":[8.7500619888,47.4917678833],"type":"Point"}
}