{
  "type": "Feature",
  "properties": {
    "iso:country":"CH",
    "sg:address":"B\u00fcndtenstrasse 8",
    "sg:city":"Oftringen",
    "sg:orig_category":"Unternehmensberatung",
    "sg:phone":"+41 62 797 87 27",
    "sg:postcode":"4665",
    "sg:province":"Aargau",
    "wof:name":"Ernst Z\u00fcrcher Beratungsauftr\u00e4ge",
    "wof:placetype":"venue"
},
  "geometry": {"coordinates":[7.9408478737,47.2949371338],"type":"Point"}
}