{
  "type": "Feature",
  "properties": {
    "iso:country":"CH",
    "sg:address":"Bahnhofstrasse 19",
    "sg:city":"Dotzigen",
    "sg:orig_category":"Nationale Postdienste",
    "sg:phone":"+41 32 351 17 05",
    "sg:postcode":"3293",
    "sg:province":"Bern",
    "wof:name":"Die Schweizerische Post",
    "wof:placetype":"venue"
},
  "geometry": {"coordinates":[7.340086937,47.1177902222],"type":"Point"}
}