{
  "type": "Feature",
  "properties": {
    "iso:country":"CH",
    "sg:address":"Hauptstrasse 26",
    "sg:city":"Hunzenschwil",
    "sg:orig_category":"Detailhandel mit Waren verschiedener Art, Hauptrichtung Nahrungsmittel Tankstellen",
    "sg:phone":"+41 62 897 03 69",
    "sg:postcode":"5502",
    "sg:province":"Aargau",
    "wof:name":"Coop Tankstelle",
    "wof:placetype":"venue"
},
  "geometry": {"coordinates":[8.1268186569,47.3867683411],"type":"Point"}
}