{
  "type": "Feature",
  "properties": {
    "iso:country":"CH",
    "sg:address":"Grand-rue 74",
    "sg:city":"Ch\u00e2tel-st-denis",
    "sg:orig_category":"Detailhandel mit Waren verschiedener Art, Hauptrichtung Nahrungsmittel",
    "sg:phone":"+41 21 948 70 53",
    "sg:postcode":"1618",
    "sg:province":"Fribourg",
    "wof:name":"Cercle D'agriculture",
    "wof:placetype":"venue"
},
  "geometry": {"coordinates":[6.9026870728,46.5286598206],"type":"Point"}
}