{
  "type": "Feature",
  "properties": {
    "iso:country":"CH",
    "sg:address":"Chamerstrasse 12c",
    "sg:city":"Zug",
    "sg:orig_category":"Softwareentwicklung U beratung",
    "sg:phone":"+41 41 712 38 10",
    "sg:postcode":"6300",
    "sg:province":"Zug",
    "wof:name":"Swisowa Gmbh",
    "wof:placetype":"venue"
},
  "geometry": {"coordinates":[8.5116653442,47.1717948914],"type":"Point"}
}