{
  "type": "Feature",
  "properties": {
    "addr:full":"2552 Orpund Bern 2552",
    "addr:housenumber":"2552",
    "addr:postcode":"2552",
    "addr:street":"Orpund Bern",
    "iso:country":"CH",
    "sg:address":"2552",
    "sg:city":"Orpund",
    "sg:orig_category":"Bezirks, Sekundar, Realschulen, Oberstufe der Primarschulen",
    "sg:phone":"+41 31 301 67 66",
    "sg:postcode":"2552",
    "sg:province":"Bern",
    "wof:name":"Sekundarschule",
    "wof:placetype":"venue"
},
  "geometry": {"coordinates":[7.43596,46.978142],"type":"Point"}
}