{
  "type": "Feature",
  "properties": {
    "iso:country":"CH",
    "sg:address":"Aarauerstrasse 180 4600 Olten. Postfach 720",
    "sg:city":"Olten",
    "sg:orig_category":"Kauf U Verkauf von Immobilien auf eigene Rechnung Vermittlung von Immobilien",
    "sg:phone":"+41 62 296 22 35",
    "sg:postcode":"4603",
    "sg:province":"Solothurn",
    "wof:name":"Meba Verwaltungen, B\u00e4ttig H. R.",
    "wof:placetype":"venue"
},
  "geometry": {"coordinates":[7.9195299149,47.3501358032],"type":"Point"}
}