{
  "type": "Feature",
  "properties": {
    "iso:country":"CH",
    "sg:address":"Route De Saint-julien 264",
    "sg:city":"Perly",
    "sg:orig_category":"Instandhaltung U Reparatur von Automobilen",
    "sg:phone":"+41 22 771 39 19",
    "sg:postcode":"1258",
    "sg:province":"Gen\u00e8ve",
    "wof:name":"Garage Des Rois Sa",
    "wof:placetype":"venue"
},
  "geometry": {"coordinates":[6.0963640213,46.1570205688],"type":"Point"}
}