{
  "type": "Feature",
  "properties": {
    "iso:country":"CH",
    "sg:address":"Dorfstrasse 24 3715 Adelboden. Postfach 224",
    "sg:city":"Adelboden",
    "sg:classifiers":[
        {
            "category":"Insurance",
            "subcategory":"Insurance Agent",
            "type":"Services"
        }
    ],
    "sg:phone":"+41 8006731604",
    "sg:postcode":"3715",
    "sg:province":"Bern",
    "sg:tags":[
        "versicherungsagenturen",
        "-broker"
    ],
    "wof:name":"Z\u00fcrich Versicherung Agentur",
    "wof:placetype":"venue"
},
  "geometry": {"coordinates":[7.5582580566,46.4922866821],"type":"Point"}
}