{
  "type": "Feature",
  "properties": {
    "iso:country":"CH",
    "sg:address":"Route De Prilly 9",
    "sg:city":"Crissier",
    "sg:orig_category":"Autogaragen",
    "sg:phone":"+41 24 471 26 63",
    "sg:postcode":"1023",
    "sg:province":"Vaud",
    "wof:name":"F\u00e9lix Udriot Garage Bel-air",
    "wof:placetype":"venue"
},
  "geometry": {"coordinates":[6.945607,46.257854],"type":"Point"}
}