{
  "type": "Feature",
  "properties": {
    "iso:country":"CH",
    "sg:address":"Talstrasse 4",
    "sg:city":"Ennetmoos",
    "sg:classifiers":[
        {
            "category":"Transit Center",
            "subcategory":"Freight",
            "type":"Transportation"
        }
    ],
    "sg:phone":"+41 41 610 21 61",
    "sg:postcode":"6372",
    "sg:province":"Nidwalden",
    "sg:tags":[
        "forwarding",
        "agency"
    ],
    "wof:name":"Wyrsch Automobile Ag",
    "wof:placetype":"venue"
},
  "geometry": {"coordinates":[8.3346214294,46.9555778503],"type":"Point"}
}