{
  "type": "Feature",
  "properties": {
    "iso:country":"CH",
    "sg:address":"7463",
    "sg:city":"Riom",
    "sg:orig_category":"Gemeindeverwaltungen",
    "sg:phone":"+41 81 684 26 96",
    "sg:postcode":"7463",
    "sg:province":"Graubunden",
    "wof:name":"Gemeindeverwaltung Riom-parsonz",
    "wof:placetype":"venue"
},
  "geometry": {"coordinates":[9.5828199387,46.6049118042],"type":"Point"}
}