{
  "type": "Feature",
  "properties": {
    "iso:country":"CH",
    "sg:address":"5502",
    "sg:city":"Hunzenschwil",
    "sg:orig_category":"Bezirks, Sekundar, Realschulen, Oberstufe der Primarschulen",
    "sg:phone":"+41 62 897 27 00",
    "sg:postcode":"5502",
    "sg:province":"Aargau",
    "wof:name":"Oberstufenschule",
    "wof:placetype":"venue"
},
  "geometry": {"coordinates":[8.11629,47.38274],"type":"Point"}
}