{
  "type": "Feature",
  "properties": {
    "iso:country":"CH",
    "sg:address":"Hirzlistrasse 8 8722 Kaltbrunn. Postfach",
    "sg:city":"Kaltbrunn",
    "sg:orig_category":"Verwaltung von Immobilien",
    "sg:postcode":"8722",
    "sg:province":"St. Gallen",
    "wof:name":"Unterm\u00fchle Kaltbrunn Gmbh Immobilien Usw.",
    "wof:placetype":"venue"
},
  "geometry": {"coordinates":[9.0203380585,47.2127723694],"type":"Point"}
}