{
  "type": "Feature",
  "properties": {
    "iso:country":"CH",
    "sg:address":"Badenerstrasse 89",
    "sg:city":"Z\u00fcrich",
    "sg:orig_category":"Detailhandel mit Schuhen Detailhandel mit Schuhen U Lederwaren",
    "sg:phone":"+41 55 210 10 40",
    "sg:postcode":"8004",
    "sg:province":"Z\u00fcrich",
    "wof:name":"Schuh-morger",
    "wof:placetype":"venue"
},
  "geometry": {"coordinates":[8.8183994293,47.2271957397],"type":"Point"}
}