{
  "type": "Feature",
  "properties": {
    "iso:country":"CH",
    "sg:address":"Via San Gottardo 16 6600 Muralto Casella Postale 535",
    "sg:city":"Muralto",
    "sg:orig_category":"Grosshandel mit medizinischen U orthop\u00e4dischen Artikeln Herstellung von medizinischen U chirurgische",
    "sg:phone":"+41 91 743 80 33",
    "sg:postcode":"6600",
    "sg:province":"Ticino",
    "wof:name":"Mediplan Sa",
    "wof:placetype":"venue"
},
  "geometry": {"coordinates":[8.8003940582,46.1705741882],"type":"Point"}
}