{
  "type": "Feature",
  "properties": {
    "iso:country":"CH",
    "sg:address":"Schulstrasse 15",
    "sg:city":"Neftenbach",
    "sg:orig_category":"Detailhandel mit Waren verschiedener Art, Hauptrichtung Nahrungsmittel",
    "sg:postcode":"8413",
    "sg:province":"Z\u00fcrich",
    "wof:name":"Landw. Konsumgenossenschaft Neftenbach Und Umgebung",
    "wof:placetype":"venue"
},
  "geometry": {"coordinates":[8.6641407013,47.5256958008],"type":"Point"}
}