{
  "type": "Feature",
  "properties": {
    "iso:country":"CH",
    "sg:address":"Hochstrasse 11",
    "sg:city":"Schaffhausen",
    "sg:orig_category":"Instandhaltung U Reparatur von Automobilen",
    "sg:postcode":"8200",
    "sg:province":"Schaffhausen",
    "wof:name":"Garage D'andrea",
    "wof:placetype":"venue"
},
  "geometry": {"coordinates":[8.6344804764,47.7008934021],"type":"Point"}
}