{
  "type": "Feature",
  "properties": {
    "addr:full":"Hinterthal Muotathal Schwyz 6436",
    "addr:postcode":"6436",
    "iso:country":"CH",
    "sg:address":"Hinterthal",
    "sg:city":"Muotathal",
    "sg:orig_category":"Detailhandel mit Brot, Back U S\u00fcsswaren Sonstige Kurierdienste",
    "sg:phone":"+41 21 845 44 77",
    "sg:postcode":"6436",
    "sg:province":"Schwyz",
    "wof:name":"Express Matin, Baumgartner Marc & Olivier",
    "wof:placetype":"venue"
},
  "geometry": {"coordinates":[6.28231,46.647835],"type":"Point"}
}