{
  "type": "Feature",
  "properties": {
    "iso:country":"CH",
    "sg:address":"Gartenstr. 13",
    "sg:city":"Widnau",
    "sg:classifiers":[
        {
            "category":"Shopping",
            "subcategory":"Clothing, Apparel, & Fashions",
            "type":"Retail Goods"
        }
    ],
    "sg:phone":"+41 71 722 84 72",
    "sg:postcode":"9443",
    "sg:province":"St. Gallen",
    "sg:tags":[
        "textile",
        "clothing",
        "clothes"
    ],
    "wof:name":"Selana Gmbh",
    "wof:placetype":"venue"
},
  "geometry": {"coordinates":[9.641323,47.402267],"type":"Point"}
}