{
  "type": "Feature",
  "properties": {
    "iso:country":"CH",
    "sg:address":"Chemin De Pr\u00e9-cosson 3",
    "sg:city":"Troinex",
    "sg:orig_category":"Herstellung von sonstigen Produkten aus nichtmetallischen Mineralien",
    "sg:phone":"+41 22 899 18 30",
    "sg:postcode":"1256",
    "sg:province":"Gen\u00e8ve",
    "wof:name":"Rocnat Sa",
    "wof:placetype":"venue"
},
  "geometry": {"coordinates":[6.1566238403,46.1529655457],"type":"Point"}
}