{
  "type": "Feature",
  "properties": {
    "iso:country":"CH",
    "sg:address":"Hauptstr. 48",
    "sg:city":"Bretzwil",
    "sg:classifiers":[
        {
            "category":"Travel",
            "subcategory":"Hotels & Motels",
            "type":"Entertainment"
        }
    ],
    "sg:postcode":"4207",
    "sg:province":"Basel-Landschaft",
    "sg:tags":[
        "hotels",
        "mit",
        "restaurant"
    ],
    "wof:name":"Affolter-hasler R. + Affolter L.",
    "wof:placetype":"venue"
},
  "geometry": {"coordinates":[7.6526899338,47.3976211548],"type":"Point"}
}