{
  "type": "Feature",
  "properties": {
    "iso:country":"CH",
    "sg:address":"Flughofstrasse 55",
    "sg:city":"Glattbrugg",
    "sg:orig_category":"Herstellung von Metallerzeugnissen ohne Maschinenbau Maschinen-Fabrikation",
    "sg:phone":"+41 61 851 23 70",
    "sg:postcode":"8152",
    "sg:province":"Z\u00fcrich",
    "wof:name":"Comes Maschinenbau Ag",
    "wof:placetype":"venue"
},
  "geometry": {"coordinates":[7.8460769653,47.5692367554],"type":"Point"}
}