{
  "type": "Feature",
  "properties": {
    "iso:country":"CH",
    "sg:address":"Hofstettstrasse 11 9303 Wittenbach. Postfach",
    "sg:city":"Kronb\u00fchl",
    "sg:orig_category":"Dachdeckerei Zimmerei, Dachdeckerei, Bauspenglerei U Abdichtung",
    "sg:phone":"+41 71 298 41 28",
    "sg:postcode":"9302",
    "wof:name":"Sp\u00f6rri R. Ag",
    "wof:placetype":"venue"
},
  "geometry": {"coordinates":[9.393462,47.465],"type":"Point"}
}