{
  "type": "Feature",
  "properties": {
    "iso:country":"CH",
    "sg:address":"Sonnenbergstrasse 5",
    "sg:city":"Ennetbaden",
    "sg:orig_category":"RESTAURANTS: TEA-ROOMS",
    "sg:phone":"+41 56 221 14 32",
    "sg:postcode":"5408",
    "sg:province":"Aargau",
    "wof:name":"Restaurant / Pizzeria Engel, Gunti Chantal",
    "wof:placetype":"venue"
},
  "geometry": {"coordinates":[8.3138170242,47.4786834717],"type":"Point"}
}