{
  "type": "Feature",
  "properties": {
    "iso:country":"CH",
    "sg:address":"Prince Rue Du 10 1204 Gen\u00e8ve. Postfach",
    "sg:city":"Gen\u00e8ve",
    "sg:orig_category":"Herstellung von Oberbekleidung",
    "sg:postcode":"1201",
    "sg:province":"Gen\u00e8ve",
    "wof:name":"Tdz Ag",
    "wof:placetype":"venue"
},
  "geometry": {"coordinates":[8.8199501038,47.2357559204],"type":"Point"}
}