{
  "type": "Feature",
  "properties": {
    "iso:country":"CH",
    "sg:address":"Seewenstrasse 50",
    "sg:city":"Himmelried",
    "sg:orig_category":"RESTAURANTS: TEA-ROOMS",
    "sg:phone":"+41 61 741 12 75",
    "sg:postcode":"4204",
    "sg:province":"Solothurn",
    "wof:name":"Br\u00fcgger Reto Restaurant Pflug",
    "wof:placetype":"venue"
},
  "geometry": {"coordinates":[7.6007242203,47.4221687317],"type":"Point"}
}