{
  "type": "Feature",
  "properties": {
    "iso:country":"CH",
    "sg:address":"Obstbaumstrasse 4",
    "sg:city":"Dietikon",
    "sg:orig_category":"Kauf U Verkauf von Immobilien auf eigene Rechnung",
    "sg:postcode":"8953",
    "sg:province":"Z\u00fcrich",
    "wof:name":"Kloter Hans",
    "wof:placetype":"venue"
},
  "geometry": {"coordinates":[8.3986549377,47.4065856934],"type":"Point"}
}