{
  "type": "Feature",
  "properties": {
    "iso:country":"CH",
    "sg:address":"Beim Goldenen L\u00f6wen 12 4052 Basel. Postfach",
    "sg:city":"Basel",
    "sg:orig_category":"Markt U Meinungsforschung Unternehmensberatung",
    "sg:phone":"+41 61 312 88 88",
    "sg:postcode":"4028",
    "wof:name":"Mapag Marketing Pool Ag",
    "wof:placetype":"venue"
},
  "geometry": {"coordinates":[7.5968999863,47.5545005798],"type":"Point"}
}