{
  "type": "Feature",
  "properties": {
    "iso:country":"CH",
    "sg:address":"Rosengartenstrasse 80 8037 Z\u00fcrich. Postfach",
    "sg:city":"Z\u00fcrich",
    "sg:orig_category":"Reinigungsgewerbe",
    "sg:phone":"+41 31 981 00 44",
    "sg:postcode":"8037",
    "sg:province":"Z\u00fcrich",
    "wof:name":"Lisa Reinigungen-r\u00e4umungen Haldemann E.",
    "wof:placetype":"venue"
},
  "geometry": {"coordinates":[7.414276123,46.9228744507],"type":"Point"}
}