{
  "type": "Feature",
  "properties": {
    "iso:country":"CH",
    "sg:address":"Z\u00fcrichstrasse 108",
    "sg:city":"Ebmatingen",
    "sg:orig_category":"Sonstige mit der Informatik verbundene T\u00e4tigkeiten",
    "sg:postcode":"8123",
    "sg:province":"Z\u00fcrich",
    "wof:name":"Swisscode A. Gerber",
    "wof:placetype":"venue"
},
  "geometry": {"coordinates":[8.6430721283,47.3508720398],"type":"Point"}
}