{
  "type": "Feature",
  "properties": {
    "iso:country":"CH",
    "sg:address":"Rennweg 34 4052 Basel. Postfach",
    "sg:city":"Basel",
    "sg:orig_category":"Pensionskassen",
    "sg:phone":"+41 81 755 77 77",
    "sg:postcode":"4051",
    "sg:province":"Basel-Stadt",
    "wof:name":"F\u00fcrsorgestiftung Der Vetsch Ag, Internationale Transporte",
    "wof:placetype":"venue"
},
  "geometry": {"coordinates":[9.47665,47.169823],"type":"Point"}
}