{
  "type": "Feature",
  "properties": {
    "iso:country":"CH",
    "sg:address":"Grand-rue 43 1337 Vallorbe. Postfach",
    "sg:city":"Vallorbe",
    "sg:classifiers":[
        {
            "category":"Bars & Pubs",
            "type":"Food & Drink"
        }
    ],
    "sg:postcode":"1337",
    "sg:province":"Vaud",
    "wof:name":"Bogoljub Mijic",
    "wof:placetype":"venue"
},
  "geometry": {"coordinates":[6.376113,46.711678],"type":"Point"}
}