{
  "type": "Feature",
  "properties": {
    "iso:country":"CH",
    "sg:address":"Maad 9473 Gams. Postfach",
    "sg:city":"Gams",
    "sg:orig_category":"Herstellung von Landwirtschaftstraktoren",
    "sg:phone":"+41 31 839 10 83",
    "sg:postcode":"9473",
    "sg:province":"St. Gallen",
    "wof:name":"Fl\u00fcckiger Hans Traktoren, Landmaschinen, Nutzfahrzeuge",
    "wof:placetype":"venue"
},
  "geometry": {"coordinates":[7.5567212105,46.9359092712],"type":"Point"}
}