{
  "type": "Feature",
  "properties": {
    "iso:country":"CH",
    "sg:address":"Langstrasse 4 8001 Z\u00fcrich. Postfach 3",
    "sg:city":"Z\u00fcrich",
    "sg:orig_category":"Pensionskassen",
    "sg:postcode":"8001",
    "sg:province":"Z\u00fcrich",
    "wof:name":"Riposa Personalf\u00fcrsorgestiftung",
    "wof:placetype":"venue"
},
  "geometry": {"coordinates":[8.5243501663,47.3743743896],"type":"Point"}
}