{
  "type": "Feature",
  "properties": {
    "iso:country":"CH",
    "sg:address":"Grundstrasse 30 6430 Schwyz. Postfach 336",
    "sg:city":"Schwyz",
    "sg:orig_category":"Maler U Glasergewerbe Malerei",
    "sg:phone":"+41 19110513",
    "sg:postcode":"6431",
    "sg:province":"Schwyz",
    "wof:name":"Niederoest & Brunner, Malergesch\u00e4ft",
    "wof:placetype":"venue"
},
  "geometry": {"coordinates":[8.6057271957,47.3267784119],"type":"Point"}
}