{
  "type": "Feature",
  "properties": {
    "iso:country":"CH",
    "sg:address":"Shopping Center 11",
    "sg:city":"Spreitenbach",
    "sg:orig_category":"Unternehmensberatung Wirtschaftspr\u00fcfung, Steuerberatung U Treuhand",
    "sg:phone":"+41 56 401 24 64",
    "sg:postcode":"8957",
    "sg:province":"Aargau",
    "wof:name":"Bsr Treuhand Ag",
    "wof:placetype":"venue"
},
  "geometry": {"coordinates":[8.3701953888,47.4209098816],"type":"Point"}
}