{
  "type": "Feature",
  "properties": {
    "addr:full":"Pfistergasse 38 Zofingen Aargau 4800",
    "addr:housenumber":"38",
    "addr:postcode":"4800",
    "addr:street":"Pfistergasse",
    "iso:country":"CH",
    "sg:address":"Pfistergasse 38",
    "sg:city":"Zofingen",
    "sg:orig_category":"Dachdeckerei Herstellung von sonstigen Metallwaren",
    "sg:phone":"+41 41 850 65 25",
    "sg:postcode":"4800",
    "sg:province":"Aargau",
    "wof:name":"Sch\u00e4fer Stammbach Partner Ag",
    "wof:placetype":"venue"
},
  "geometry": {"coordinates":[8.441568,47.081211],"type":"Point"}
}