{
  "type": "Feature",
  "properties": {
    "iso:country":"CH",
    "sg:address":"Schwarzenburgstrasse 112",
    "sg:city":"Liebefeld",
    "sg:orig_category":"Tankstellen",
    "sg:phone":"+41 31 971 70 75",
    "sg:postcode":"3097",
    "sg:province":"Bern",
    "wof:name":"Tamoil Service Station, Jansen + B\u00e4rtschi",
    "wof:placetype":"venue"
},
  "geometry": {"coordinates":[7.4225759506,46.9332275391],"type":"Point"}
}