{
  "type": "Feature",
  "properties": {
    "iso:country":"CH",
    "sg:address":"Champ-des-bois Chemin Du 10 1234 Vessy. Postfach",
    "sg:city":"Vessy",
    "sg:orig_category":"Erbringung von Dienstleistungen f\u00fcr Unternehmen",
    "sg:phone":"+41 22 784 42 04",
    "sg:postcode":"1234",
    "sg:province":"Gen\u00e8ve",
    "wof:name":"Axel Prod, Barro Alexandre & Cie",
    "wof:placetype":"venue"
},
  "geometry": {"coordinates":[6.1556649208,46.1674842834],"type":"Point"}
}