{
  "type": "Feature",
  "properties": {
    "iso:country":"CH",
    "sg:address":"Zeughausgasse 12",
    "sg:city":"Bern",
    "sg:classifiers":[
        {
            "category":"Bars & Pubs",
            "type":"Food & Drink"
        }
    ],
    "sg:phone":"+41 31 311 24 28",
    "sg:postcode":"3011",
    "sg:province":"Bern",
    "sg:tags":[
        "restaurant"
    ],
    "wof:name":"Road House American Restaurant & Bar",
    "wof:placetype":"venue"
},
  "geometry": {"coordinates":[7.445525,46.949017],"type":"Point"}
}