{
  "type": "Feature",
  "properties": {
    "iso:country":"CH",
    "sg:address":"Rte Du Moulin 2",
    "sg:city":"Cudrefin",
    "sg:classifiers":[
        {
            "category":"Home & Garden",
            "subcategory":"Furniture",
            "type":"Retail Goods"
        }
    ],
    "sg:phone":"+41 26 677 14 26",
    "sg:postcode":"1588",
    "sg:province":"Vaud",
    "sg:tags":[
        "wood"
    ],
    "wof:name":"Baumann Charpentes Sa",
    "wof:placetype":"venue"
},
  "geometry": {"coordinates":[7.0205922127,46.9511260986],"type":"Point"}
}