{
  "type": "Feature",
  "properties": {
    "iso:country":"CH",
    "sg:address":"Bahnhofstrasse 15",
    "sg:city":"Sursee",
    "sg:orig_category":"Handelsvermittlung U Grosshandel",
    "sg:phone":"+41 21 946 25 12",
    "sg:postcode":"6210",
    "sg:province":"Luzern",
    "wof:name":"Dmd Sa Fourn.mat\u00e9riel Pr D\u00e9m\u00e9nageurs",
    "wof:placetype":"venue"
},
  "geometry": {"coordinates":[5.4990701675,45.4233818054],"type":"Point"}
}