{
  "type": "Feature",
  "properties": {
    "iso:country":"CH",
    "sg:address":"Windenboden 6",
    "sg:city":"Neuheim",
    "sg:orig_category":"Grosshandel mit Erzen U Metallen Sonstiger Grosshandel",
    "sg:phone":"+41 41 755 32 35",
    "sg:postcode":"6345",
    "sg:province":"Zug",
    "wof:name":"Pekari Ag",
    "wof:placetype":"venue"
},
  "geometry": {"coordinates":[8.5785779953,47.2066574097],"type":"Point"}
}