{
  "type": "Feature",
  "properties": {
    "iso:country":"CH",
    "sg:address":"Bergstrasse 67",
    "sg:city":"Dietikon",
    "sg:orig_category":"Herstellung von Ger\u00e4ten der Elektrizit\u00e4tserzeugung, -verteilung u.\u00e4. -Herstellung von sonstigen elek",
    "sg:phone":"+41 17411436",
    "sg:postcode":"8953",
    "sg:province":"Z\u00fcrich",
    "wof:name":"Prom Ag",
    "wof:placetype":"venue"
},
  "geometry": {"coordinates":[8.3949127197,47.4009017944],"type":"Point"}
}