{
  "type": "Feature",
  "properties": {
    "iso:country":"CH",
    "sg:address":"1936",
    "sg:city":"Verbier",
    "sg:classifiers":[
        {
            "category":"Restaurant",
            "type":"Food & Drink"
        }
    ],
    "sg:phone":"+41 27 771 21 48",
    "sg:postcode":"1936",
    "sg:province":"Valais",
    "wof:name":"Restaurant Les Touristes",
    "wof:placetype":"venue"
},
  "geometry": {"coordinates":[7.2229599953,46.0967216492],"type":"Point"}
}