{
  "type": "Feature",
  "properties": {
    "iso:country":"CH",
    "sg:address":"H\u00e4ngelenstrasse 3 Hettiswil B. Hindelbank",
    "sg:city":"Krauchthal",
    "sg:orig_category":"Grosshandel mit H\u00e4uten, Fellen U Leder Sonstige k\u00fcnstlerische U schriftstellerische T\u00e4tigkeiten U Da",
    "sg:phone":"+41 34 411 01 02",
    "sg:postcode":"3326",
    "sg:province":"Bern",
    "wof:name":"Hutmacher & Co. Leder-kunsthandwerk Hettiswil Ch",
    "wof:placetype":"venue"
},
  "geometry": {"coordinates":[7.5657777786,47.0091896057],"type":"Point"}
}