{
  "type": "Feature",
  "properties": {
    "addr:full":"Rue Du Centre 21 Crissier Vaud 1023",
    "addr:housenumber":"21",
    "addr:postcode":"1023",
    "addr:street":"Rue Du Centre",
    "iso:country":"CH",
    "sg:address":"Rue Du Centre 21",
    "sg:city":"Crissier",
    "sg:classifiers":[
        {
            "category":"Education",
            "subcategory":"Library",
            "type":"Public Place"
        }
    ],
    "sg:phone":"+41 21 631 96 89",
    "sg:postcode":"1023",
    "sg:province":"Vaud",
    "sg:tags":[
        "u",
        "bibliotheken",
        "archive"
    ],
    "wof:name":"Biblioth\u00e8que Communale",
    "wof:placetype":"venue"
},
  "geometry": {"coordinates":[6.578504,46.551994],"type":"Point"}
}