{
  "type": "Feature",
  "properties": {
    "iso:country":"CH",
    "sg:address":"Wasserturmplatz 2",
    "sg:city":"Liestal",
    "sg:orig_category":"Solarien",
    "sg:phone":"+41 71 245 20 01",
    "sg:postcode":"4410",
    "sg:province":"Basel-Landschaft",
    "wof:name":"Harry Furrer Solarium Golden Sun",
    "wof:placetype":"venue"
},
  "geometry": {"coordinates":[9.3885097504,47.4377861023],"type":"Point"}
}