{
  "type": "Feature",
  "properties": {
    "iso:country":"CH",
    "sg:address":"Route D'estivage",
    "sg:city":"Avenches",
    "sg:orig_category":"Autogaragen Autospenglereien",
    "sg:phone":"+41 79 230 76 50",
    "sg:postcode":"1580",
    "sg:province":"Vaud",
    "wof:name":"Carrosserie W.n\u00e4f Sa",
    "wof:placetype":"venue"
},
  "geometry": {"coordinates":[7.04494,46.887409],"type":"Point"}
}