{
  "type": "Feature",
  "properties": {
    "iso:country":"CH",
    "sg:address":"Zugerstrasse 25a",
    "sg:city":"Richterswil",
    "sg:orig_category":"Informatikschulen",
    "sg:phone":"+41 17842866",
    "sg:postcode":"8805",
    "sg:province":"Z\u00fcrich",
    "wof:name":"Sfd Comp-soft Computerschule",
    "wof:placetype":"venue"
},
  "geometry": {"coordinates":[8.7033720016,47.2045631409],"type":"Point"}
}