{
  "type": "Feature",
  "properties": {
    "iso:country":"CH",
    "sg:address":"St. Gallerstrasse 29",
    "sg:city":"Jona",
    "sg:orig_category":"W\u00e4scherei U chemische Reinigung",
    "sg:phone":"+41 55 212 10 53",
    "sg:postcode":"8645",
    "sg:province":"St. Gallen",
    "wof:name":"Drynette Josef Acar Textilreinigung",
    "wof:placetype":"venue"
},
  "geometry": {"coordinates":[8.8363399506,47.2300224304],"type":"Point"}
}