{
  "type": "Feature",
  "properties": {
    "iso:country":"CH",
    "sg:address":"Bahnhofstrasse 11",
    "sg:city":"Baar",
    "sg:orig_category":"Sonstige mit der Informatik verbundene T\u00e4tigkeiten",
    "sg:postcode":"6340",
    "sg:province":"Zug",
    "wof:name":"Obe Gmbh",
    "wof:placetype":"venue"
},
  "geometry": {"coordinates":[7.4862298965,46.9344024658],"type":"Point"}
}