{
  "type": "Feature",
  "properties": {
    "iso:country":"CH",
    "sg:address":"Rue Des Bourguignons 8",
    "sg:city":"Monthey",
    "sg:orig_category":"Architektur U Ingenieurb\u00fcros",
    "sg:phone":"+41 24 472 20 90",
    "sg:postcode":"1870",
    "sg:province":"Valais",
    "wof:name":"Imagina Sarl",
    "wof:placetype":"venue"
},
  "geometry": {"coordinates":[6.948442,46.251961],"type":"Point"}
}