{
  "type": "Feature",
  "properties": {
    "iso:country":"CH",
    "sg:address":"Arabienstrasse 16 4059 Basel. Postfach",
    "sg:city":"Basel",
    "sg:orig_category":"Wirtschaftspr\u00fcfung, Steuerberatung U Treuhand",
    "sg:phone":"+41 61 261 58 40",
    "sg:postcode":"4051",
    "sg:province":"Basel-Stadt",
    "wof:name":"Dr. Silvio Bianchi Treuhandb\u00fcro U. Steuerberatungen",
    "wof:placetype":"venue"
},
  "geometry": {"coordinates":[7.5891571045,47.5319442749],"type":"Point"}
}