{
  "type": "Feature",
  "properties": {
    "iso:country":"CH",
    "sg:address":"Breitibachstrasse 37",
    "sg:city":"D\u00fcbendorf",
    "sg:orig_category":"Sonstige mit der Informatik verbundene T\u00e4tigkeiten",
    "sg:phone":"+41 18201293",
    "sg:postcode":"8600",
    "sg:province":"Z\u00fcrich",
    "wof:name":"Covis Gmbh",
    "wof:placetype":"venue"
},
  "geometry": {"coordinates":[8.6072940826,47.393245697],"type":"Point"}
}