{
  "type": "Feature",
  "properties": {
    "iso:country":"CH",
    "sg:address":"Kohlrutistrasse 7",
    "sg:city":"Leuzigen",
    "sg:orig_category":"Instandhaltung U Reparatur von Automobilen",
    "sg:postcode":"3297",
    "sg:province":"Bern",
    "wof:name":"Garage Affolter B.",
    "wof:placetype":"venue"
},
  "geometry": {"coordinates":[7.4748930931,47.1746253967],"type":"Point"}
}