{
  "type": "Feature",
  "properties": {
    "iso:country":"CH",
    "sg:address":"Wiesenstrasse 9",
    "sg:city":"Schwerzenbach",
    "sg:orig_category":"Massagestudios",
    "sg:phone":"+41 71 891 57 71",
    "sg:postcode":"8603",
    "sg:province":"Z\u00fcrich",
    "wof:name":"Prosana Massagen",
    "wof:placetype":"venue"
},
  "geometry": {"coordinates":[9.5062351227,47.4447250366],"type":"Point"}
}