{
  "type": "Feature",
  "properties": {
    "iso:country":"CH",
    "sg:address":"Sonnenmatt 3",
    "sg:city":"Gattikon",
    "sg:orig_category":"Grosshandel mit Textilien",
    "sg:postcode":"8136",
    "sg:province":"Z\u00fcrich",
    "wof:name":"Sch\u00f6nenberger Textilien En Gros.",
    "wof:placetype":"venue"
},
  "geometry": {"coordinates":[8.5453748703,47.2838592529],"type":"Point"}
}