{
  "type": "Feature",
  "properties": {
    "iso:country":"CH",
    "sg:address":"Carrosserie Rue De La 2",
    "sg:city":"Crans-pr\u00e8s-c\u00e9ligny",
    "sg:orig_category":"Schreib U \u00dcbersetzungsb\u00fcros",
    "sg:phone":"+41 71 288 50 20",
    "sg:postcode":"1299",
    "sg:province":"Vaud",
    "wof:name":"Admicron Luggen",
    "wof:placetype":"venue"
},
  "geometry": {"coordinates":[9.4186763763,47.4420318604],"type":"Point"}
}