{
  "type": "Feature",
  "properties": {
    "iso:country":"CH",
    "sg:address":"Br\u00fchlgasse 28",
    "sg:city":"St.gallen",
    "sg:orig_category":"Detailhandel mit Blumen U Pflanzen Herstellung von Werkzeugen",
    "sg:phone":"+41 71 222 55 11",
    "sg:postcode":"9000",
    "sg:province":"St. Gallen",
    "wof:name":"Blumen Und Puppen Gmbh",
    "wof:placetype":"venue"
},
  "geometry": {"coordinates":[9.378371,47.425209],"type":"Point"}
}