{
  "type": "Feature",
  "properties": {
    "iso:country":"CH",
    "sg:address":"St. Urbangasse 5",
    "sg:city":"Solothurn",
    "sg:classifiers":[
        {
            "category":"Restaurant",
            "type":"Food & Drink"
        }
    ],
    "sg:phone":"+41 32 622 29 49",
    "sg:postcode":"4500",
    "sg:province":"Solothurn",
    "wof:name":"Restaurant Bieltor",
    "wof:placetype":"venue"
},
  "geometry": {"coordinates":[7.534842968,47.2083053589],"type":"Point"}
}