{
  "type": "Feature",
  "properties": {
    "iso:country":"CH",
    "sg:address":"Unterdorf 16",
    "sg:city":"Sch\u00fcpfheim",
    "sg:orig_category":"Werbegrafikateliers",
    "sg:phone":"+41 41 484 29 29",
    "sg:postcode":"6170",
    "sg:province":"Luzern",
    "wof:name":"Paul Thum Grafikstudio",
    "wof:placetype":"venue"
},
  "geometry": {"coordinates":[8.0189838409,46.9560127258],"type":"Point"}
}