{
  "type": "Feature",
  "properties": {
    "iso:country":"CH",
    "sg:address":"Knonauerstrasse 15",
    "sg:city":"Cham",
    "sg:orig_category":"Maler U Glasergewerbe Malerei",
    "sg:phone":"+41 41 780 72 77",
    "sg:postcode":"6330",
    "sg:province":"Zug",
    "wof:name":"Ernst Rast Malergesch\u00e4ft",
    "wof:placetype":"venue"
},
  "geometry": {"coordinates":[8.4605617523,47.1825294495],"type":"Point"}
}