{
  "type": "Feature",
  "properties": {
    "iso:country":"CH",
    "sg:address":"Hauptstrasse 102",
    "sg:city":"Bubendorf",
    "sg:orig_category":"Herstellung von Elektrizit\u00e4tsverteilungs U schalteinrichtungen Herstellung von industriellen Prozess",
    "sg:phone":"+41 61 931 36 44",
    "sg:postcode":"4416",
    "sg:province":"Basel-Landschaft",
    "wof:name":"Vtron Gmbh Elektr.steuerungen",
    "wof:placetype":"venue"
},
  "geometry": {"coordinates":[7.735490799,47.4465255737],"type":"Point"}
}