{
  "type": "Feature",
  "properties": {
    "iso:country":"CH",
    "sg:address":"Schaffhauserstrasse 520",
    "sg:city":"Z\u00fcrich",
    "sg:classifiers":[
        {
            "category":"Travel",
            "subcategory":"Hotels & Motels",
            "type":"Entertainment"
        }
    ],
    "sg:phone":"+41 27 979 11 38",
    "sg:postcode":"8052",
    "sg:province":"Z\u00fcrich",
    "sg:tags":[
        "hotels",
        "mit",
        "restaurant"
    ],
    "wof:name":"Hotel Fletschhorn",
    "wof:placetype":"venue"
},
  "geometry": {"coordinates":[8.0723695755,46.1851615906],"type":"Point"}
}