{
  "type": "Feature",
  "properties": {
    "addr:full":"B\u00fcelstrasse 77 Galgenen Schwyz 8854",
    "addr:housenumber":"77",
    "addr:postcode":"8854",
    "addr:street":"Bueelstrasse;Schwyz",
    "iso:country":"CH",
    "sg:address":"B\u00fcelstrasse 77",
    "sg:city":"Galgenen",
    "sg:orig_category":"Aktivit\u00e4ten der Generalunternehmen im Baugewerbe Architektur U Ingenieurb\u00fcros",
    "sg:phone":"+41 55 460 35 35",
    "sg:postcode":"8854",
    "sg:province":"Schwyz",
    "wof:name":"Weber Baurealisationen Gmbh",
    "wof:placetype":"venue"
},
  "geometry": {"coordinates":[8.8805,47.174187],"type":"Point"}
}