{
  "type": "Feature",
  "properties": {
    "iso:country":"CH",
    "sg:address":"Bahnhofstrasse 30 8240 Thayngen. Postfach",
    "sg:city":"Thayngen",
    "sg:orig_category":"Unternehmensberatung",
    "sg:phone":"+41 71 220 91 44",
    "sg:postcode":"8240",
    "sg:province":"Schaffhausen",
    "wof:name":"Eccoss Ag",
    "wof:placetype":"venue"
},
  "geometry": {"coordinates":[9.3828020096,47.4406471252],"type":"Point"}
}