{
  "type": "Feature",
  "properties": {
    "iso:country":"CH",
    "sg:address":"Neugass 30 9442 Berneck. Postfach",
    "sg:city":"Berneck",
    "sg:orig_category":"RESTAURANTS: TEA-ROOMS",
    "sg:phone":"+41 71 744 90 23",
    "sg:postcode":"9442",
    "sg:province":"St. Gallen",
    "wof:name":"Restaurant R\u00f6ssli, F. Eugster",
    "wof:placetype":"venue"
},
  "geometry": {"coordinates":[9.6132192612,47.4254264832],"type":"Point"}
}