{
  "type": "Feature",
  "properties": {
    "iso:country":"CH",
    "sg:address":"Rue De Gen\u00e8ve 144",
    "sg:city":"Th\u00f4nex",
    "sg:orig_category":"Grosshandel mit Maschinen U Ausr\u00fcstungen",
    "sg:postcode":"1226",
    "sg:province":"Gen\u00e8ve",
    "wof:name":"Hoval Herzog Sa",
    "wof:placetype":"venue"
},
  "geometry": {"coordinates":[6.204873085,46.192276001],"type":"Point"}
}