{
  "type": "Feature",
  "properties": {
    "iso:country":"CH",
    "sg:address":"Rue De Chantepoulet 1-3 1200 Gen\u00e8ve. Postfach",
    "sg:city":"Gen\u00e8ve",
    "sg:orig_category":"Grosshandel mit festen Brennstoffen U Mineral\u00f6lerzeugnissen",
    "sg:postcode":"1201",
    "sg:province":"Gen\u00e8ve",
    "wof:name":"M\u00e4chler Mineral\u00f6l Gmbh",
    "wof:placetype":"venue"
},
  "geometry": {"coordinates":[8.8608798981,47.1895332336],"type":"Point"}
}