{
  "type": "Feature",
  "properties": {
    "iso:country":"CH",
    "sg:address":"Boulevard Des P\u00e9rolles 18 1700 Fribourg Case Postale 86",
    "sg:city":"Fribourg",
    "sg:orig_category":"Allgemeiner Hochbau Strassenbau",
    "sg:phone":"+41 26 322 25 05",
    "sg:postcode":"1701",
    "sg:province":"Fribourg",
    "wof:name":"Walo Bertschinger Ag Bauunternehmung",
    "wof:placetype":"venue"
},
  "geometry": {"coordinates":[7.152433,46.800606],"type":"Point"}
}