{
  "type": "Feature",
  "properties": {
    "iso:country":"CH",
    "sg:address":"K\u00e4mmoos",
    "sg:city":"Bubikon",
    "sg:orig_category":"Golfpl\u00e4tze",
    "sg:phone":"+41 55 243 34 80",
    "sg:postcode":"8608",
    "sg:province":"Z\u00fcrich",
    "wof:name":"Public Golf Center Herrn Walter K\u00fcnzi",
    "wof:placetype":"venue"
},
  "geometry": {"coordinates":[8.8300924301,47.2613220215],"type":"Point"}
}