{
  "type": "Feature",
  "properties": {
    "iso:country":"CH",
    "sg:address":"Gewerbestrasse 30 4123 Allschwil. Postfach",
    "sg:city":"Allschwil",
    "sg:orig_category":"RESTAURANTS: TEA-ROOMS",
    "sg:postcode":"4123",
    "sg:province":"Basel-Landschaft",
    "wof:name":"Restaurant Fun-kulinarium, Murri S.",
    "wof:placetype":"venue"
},
  "geometry": {"coordinates":[7.5468349457,47.5591964722],"type":"Point"}
}