{
  "type": "Feature",
  "properties": {
    "iso:country":"CH",
    "sg:address":"Sandstrasse 33",
    "sg:city":"Meiringen",
    "sg:orig_category":"Fuhrhaltereien",
    "sg:phone":"+41 33 971 26 37",
    "sg:postcode":"3860",
    "sg:province":"Bern",
    "wof:name":"Hans Glarner Fuhrhalterei",
    "wof:placetype":"venue"
},
  "geometry": {"coordinates":[8.1951398849,46.723110199],"type":"Point"}
}