{
  "type": "Feature",
  "properties": {
    "iso:country":"CH",
    "sg:address":"Moosaffoltern",
    "sg:city":"Dieterswil",
    "sg:orig_category":"Primarschulen",
    "sg:phone":"+41 31 879 15 71",
    "sg:postcode":"3256",
    "sg:province":"Bern",
    "wof:name":"Primarschule",
    "wof:placetype":"venue"
},
  "geometry": {"coordinates":[7.4488401413,47.0557098389],"type":"Point"}
}