{
  "type": "Feature",
  "properties": {
    "iso:country":"CH",
    "sg:address":"Saschela 9479 Oberschan. Postfach",
    "sg:city":"Oberschan",
    "sg:orig_category":"Interessenvertretungen",
    "sg:phone":"+41 81 785 35 73",
    "sg:postcode":"9479",
    "sg:province":"St. Gallen",
    "wof:name":"Artillerie-fort-verein Magletsch (afom)",
    "wof:placetype":"venue"
},
  "geometry": {"coordinates":[9.4745159149,47.0961761475],"type":"Point"}
}