{
  "type": "Feature",
  "properties": {
    "iso:country":"CH",
    "sg:address":"Rte De Courroux 6 Case Postale 553",
    "sg:city":"Del\u00e9mont",
    "sg:classifiers":[
        {
            "category":"Professional",
            "subcategory":"Printing & Photocopies",
            "type":"Services"
        }
    ],
    "sg:phone":"+41 32 421 18 18",
    "sg:postcode":"2800",
    "sg:province":"Jura",
    "sg:tags":[
        "publishing"
    ],
    "wof:name":"Imprimerie Du D\u00c9mocrate Sa",
    "wof:placetype":"venue"
},
  "geometry": {"coordinates":[7.3750600815,47.3617286682],"type":"Point"}
}