{
  "type": "Feature",
  "properties": {
    "iso:country":"CH",
    "sg:address":"Tannegger Strasse 2",
    "sg:city":"Dussnang",
    "sg:classifiers":[
        {
            "category":"Restaurant",
            "type":"Food & Drink"
        }
    ],
    "sg:phone":"+41 71 977 13 41",
    "sg:postcode":"8374",
    "sg:province":"Thurgau",
    "wof:name":"Restaurant Tannegg",
    "wof:placetype":"venue"
},
  "geometry": {"coordinates":[8.9570388794,47.4306526184],"type":"Point"}
}