{
  "type": "Feature",
  "properties": {
    "iso:country":"CH",
    "sg:address":"Gemeindeweid 21 C",
    "sg:city":"Reisiswil",
    "sg:orig_category":"Non-Classified Establishments",
    "sg:postcode":"4919",
    "sg:province":"Bern",
    "wof:name":"Forstunternehmen Schneider + Panzica",
    "wof:placetype":"venue"
},
  "geometry": {"coordinates":[7.8328881264,47.1600723267],"type":"Point"}
}