{
  "type": "Feature",
  "properties": {
    "iso:country":"CH",
    "sg:address":"Oberkirchstrasse 37",
    "sg:city":"Frauenfeld",
    "sg:orig_category":"Softwareentwicklung U beratung",
    "sg:phone":"+41 56 641 04 61",
    "sg:postcode":"8500",
    "sg:province":"Thurgau",
    "wof:name":"Wintsch Erich, Bi-consulting",
    "wof:placetype":"venue"
},
  "geometry": {"coordinates":[8.3885850906,47.3377571106],"type":"Point"}
}