{
  "type": "Feature",
  "properties": {
    "iso:country":"CH",
    "sg:address":"Eggmattweg 24",
    "sg:city":"Magden",
    "sg:orig_category":"Elektroinstallation",
    "sg:phone":"+41 61 841 10 05",
    "sg:postcode":"4312",
    "sg:province":"Aargau",
    "wof:name":"Elektro Leutenegger",
    "wof:placetype":"venue"
},
  "geometry": {"coordinates":[7.8117051125,47.5326881409],"type":"Point"}
}