{
  "type": "Feature",
  "properties": {
    "addr:full":"Picardiestrasse 25 5040 Sch\u00f6ftland. Postfach Sch\u00f6ftland Aargau 5040",
    "addr:housenumber":"25",
    "addr:postcode":"5040;5040",
    "addr:street":"Picardiestrasse;Postfach Schoeftland",
    "iso:country":"CH",
    "sg:address":"Picardiestrasse 25 5040 Sch\u00f6ftland. Postfach",
    "sg:city":"Sch\u00f6ftland",
    "sg:orig_category":"Bauschreinerei Innenausbau",
    "sg:phone":"+41 62 721 17 77",
    "sg:postcode":"5040",
    "sg:province":"Aargau",
    "wof:name":"Willi M\u00fcller Ag, M\u00f6belwerkst\u00e4tte, Antike M\u00f6bel, Restaurationen",
    "wof:placetype":"venue"
},
  "geometry": {"coordinates":[8.041167,47.302708],"type":"Point"}
}