{
  "type": "Feature",
  "properties": {
    "iso:country":"CH",
    "sg:address":"Montchoisi Avenue De 21",
    "sg:city":"Lausanne",
    "sg:orig_category":"Pensionskassen",
    "sg:postcode":"1006",
    "sg:province":"Vaud",
    "wof:name":"Fonds De Pr\u00e9voyance Urbaplan Et Bureaux Affili\u00e9s",
    "wof:placetype":"venue"
},
  "geometry": {"coordinates":[6.6337418556,46.5133209229],"type":"Point"}
}