{
  "type": "Feature",
  "properties": {
    "iso:country":"CH",
    "sg:address":"Gehrenstrasse 36",
    "sg:city":"Affeltrangen",
    "sg:orig_category":"Sportvereine Sch\u00fctzen Armbrust",
    "sg:postcode":"9556",
    "sg:province":"Thurgau",
    "wof:name":"Armbrustsch\u00fctzengesell.wil",
    "wof:placetype":"venue"
},
  "geometry": {"coordinates":[9.0330905914,47.5233764648],"type":"Point"}
}