{
  "type": "Feature",
  "properties": {
    "iso:country":"CH",
    "sg:address":"Rue Des Fahys 9",
    "sg:city":"Neuch\u00e2tel",
    "sg:orig_category":"Geb\u00e4ude, Wohnungsreinigung Reinigungsgewerbe",
    "sg:phone":"+41 21 635 55 03",
    "sg:postcode":"2000",
    "sg:province":"Neuch\u00e2tel",
    "wof:name":"Entreprise Fedele Nettoyages",
    "wof:placetype":"venue"
},
  "geometry": {"coordinates":[6.5821371078,46.530254364],"type":"Point"}
}