{
  "type": "Feature",
  "properties": {
    "iso:country":"CH",
    "sg:address":"Via Concordia 12 6900 Lugano Casella Postale",
    "sg:city":"Calprino",
    "sg:orig_category":"Herstellung von Teppichen",
    "sg:postcode":"6900",
    "sg:province":"Ticino",
    "wof:name":"Spesol, Gailloud Claude",
    "wof:placetype":"venue"
},
  "geometry": {"coordinates":[6.8706459999,46.4708023071],"type":"Point"}
}