{
  "type": "Feature",
  "properties": {
    "iso:country":"CH",
    "sg:address":"Wettsteinallee 42 4058 Basel. Postfach",
    "sg:city":"Basel",
    "sg:orig_category":"Gesundheitswesen",
    "sg:phone":"+41 61 681 90 93",
    "sg:postcode":"4051",
    "sg:province":"Basel-Stadt",
    "wof:name":"Besuchsdienst Basel, Verein F\u00fcr Psychosoziale Eingliederung Rehabilitation, F\u00f6rderung, Betreuung V. Psych. Behinderten Dch Ausbildung In D. Betagten- U. Behindertenhilfe Usw",
    "wof:placetype":"venue"
},
  "geometry": {"coordinates":[7.6013140678,47.560382843],"type":"Point"}
}