{
  "type": "Feature",
  "properties": {
    "iso:country":"CH",
    "sg:address":"L\u00e4ttichstrasse 4a",
    "sg:city":"Baar",
    "sg:orig_category":"Herstellung von sonstigen Maschinen f\u00fcr bestimmte Verwendung",
    "sg:postcode":"6340",
    "sg:province":"Zug",
    "wof:name":"A Visual Graphic Design Gmbh Graphische Konzepte; Erstellung, Vertrieb Tr\u00e4germaterialien-erstellung Usw",
    "wof:placetype":"venue"
},
  "geometry": {"coordinates":[8.837884903,47.2992172241],"type":"Point"}
}