{
  "type": "Feature",
  "properties": {
    "iso:country":"CH",
    "sg:address":"Badweg 35",
    "sg:city":"Sch\u00f6ftland",
    "sg:orig_category":"Kosmetikinstitute",
    "sg:phone":"+41 62 721 61 80",
    "sg:postcode":"5040",
    "sg:province":"Aargau",
    "wof:name":"Barbara Richiusa Kosmetikinstitut Barbara",
    "wof:placetype":"venue"
},
  "geometry": {"coordinates":[8.0478363037,47.3004341125],"type":"Point"}
}