{
  "type": "Feature",
  "properties": {
    "iso:country":"CH",
    "sg:address":"Alte Poststrasse 16",
    "sg:city":"T\u00e4gerig",
    "sg:orig_category":"Autotransporte Tiefk\u00fchl",
    "sg:phone":"+41 56 491 21 87",
    "sg:postcode":"5522",
    "sg:province":"Aargau",
    "wof:name":"Anton Jurt K\u00fchltransporte",
    "wof:placetype":"venue"
},
  "geometry": {"coordinates":[8.27687,47.402782],"type":"Point"}
}