{
  "type": "Feature",
  "properties": {
    "addr:full":"Oelbergstrasse 23 Menziken Aargau 5737",
    "addr:housenumber":"23",
    "addr:postcode":"5737",
    "addr:street":"Oelbergstrasse",
    "iso:country":"CH",
    "sg:address":"Oelbergstrasse 23",
    "sg:city":"Menziken",
    "sg:orig_category":"Bauschreinerei Innenausbau",
    "sg:phone":"+41 62 771 16 65",
    "sg:postcode":"5737",
    "sg:province":"Aargau",
    "wof:name":"Erismann S\u00f6hne Inh.a.erismann M\u00f6belwerkst\u00e4tte Innenausbau",
    "wof:placetype":"venue"
},
  "geometry": {"coordinates":[8.184781,47.24398],"type":"Point"}
}