{
  "type": "Feature",
  "properties": {
    "iso:country":"CH",
    "sg:address":"Aarauerstrasse 14 4600 Olten. Postfach",
    "sg:city":"Olten",
    "sg:orig_category":"Zahntechnische Laboratorien",
    "sg:phone":"+41 62 296 38 10",
    "sg:postcode":"4601",
    "sg:province":"Solothurn",
    "wof:name":"Hans-rudolf Kuratli Dental-labor",
    "wof:placetype":"venue"
},
  "geometry": {"coordinates":[7.9086709023,47.3487930298],"type":"Point"}
}