{
  "type": "Feature",
  "properties": {
    "iso:country":"CH",
    "sg:address":"Landstrasse 54",
    "sg:city":"Gipf-oberfrick",
    "sg:orig_category":"Unternehmensberatung Wirtschaftspr\u00fcfung, Steuerberatung U Treuhand",
    "sg:phone":"+41 62 871 08 50",
    "sg:postcode":"5073",
    "sg:province":"Aargau",
    "wof:name":"Acc Audit Consultants Sa Treuhand & Unternehmensber.",
    "wof:placetype":"venue"
},
  "geometry": {"coordinates":[8.0005912781,47.4964065552],"type":"Point"}
}