{
  "type": "Feature",
  "properties": {
    "iso:country":"CH",
    "sg:address":"Harschwendi Ost 961",
    "sg:city":"Waldstatt",
    "sg:orig_category":"Herstellung von Arbeits U Berufsbekleidung Sonstiger Grosshandel",
    "sg:phone":"+41 71 351 49 81",
    "sg:postcode":"9104",
    "sg:province":"Appenzell Ausserrhoden",
    "wof:name":"Asg Technik Ramsauer Hans-peter",
    "wof:placetype":"venue"
},
  "geometry": {"coordinates":[9.2761182785,47.3556632996],"type":"Point"}
}