{
  "type": "Feature",
  "properties": {
    "iso:country":"CH",
    "sg:address":"Les Iles",
    "sg:city":"Martigny",
    "sg:orig_category":"Haltung von Gefl\u00fcgel",
    "sg:phone":"+41 27 722 13 49",
    "sg:postcode":"1920",
    "sg:province":"Valais",
    "wof:name":"Optigal Sa Parc Avicole",
    "wof:placetype":"venue"
},
  "geometry": {"coordinates":[7.0593352318,46.1238212585],"type":"Point"}
}