{
  "type": "Feature",
  "properties": {
    "iso:country":"CH",
    "sg:address":"Cossonay-gare",
    "sg:city":"Penthalaz",
    "sg:orig_category":"Vorschulen, Kinderg\u00e4rten",
    "sg:postcode":"1305",
    "sg:province":"Vaud",
    "wof:name":"Ecole Enfantine",
    "wof:placetype":"venue"
},
  "geometry": {"coordinates":[6.5224499702,46.6066017151],"type":"Point"}
}