{
  "type": "Feature",
  "properties": {
    "iso:country":"CH",
    "sg:address":"Morgartenstrasse 22",
    "sg:city":"Z\u00fcrich",
    "sg:orig_category":"Detailhandel mit B\u00fcchern Detailhandel mit B\u00fcchern, Zeitungen, Schreib U Papeteriewaren",
    "sg:phone":"+41 12411312",
    "sg:postcode":"8004",
    "sg:province":"Z\u00fcrich",
    "wof:name":"Andy's Motorbooks, Andreas Meyer",
    "wof:placetype":"venue"
},
  "geometry": {"coordinates":[8.528445,47.371445],"type":"Point"}
}