{
  "type": "Feature",
  "properties": {
    "iso:country":"CH",
    "sg:address":"Hauptstrasse 135",
    "sg:city":"Nidau",
    "sg:orig_category":"Fachdetailhandel in Verkaufsr\u00e4umen",
    "sg:phone":"+41 32 331 97 88",
    "sg:postcode":"2560",
    "sg:province":"Bern",
    "wof:name":"Aare-handelsgesellschaft Habegger & Co",
    "wof:placetype":"venue"
},
  "geometry": {"coordinates":[7.242743969,47.119846344],"type":"Point"}
}