{
  "type": "Feature",
  "properties": {
    "iso:country":"CH",
    "sg:address":"Avenue Pictet-de-rochemont 17",
    "sg:city":"Gen\u00e8ve",
    "sg:orig_category":"Fachdetailhandel in Verkaufsr\u00e4umen Verlagsgewerbe",
    "sg:phone":"+41 22 736 96 03",
    "sg:postcode":"1207",
    "sg:province":"Gen\u00e8ve",
    "wof:name":"Editart Mme D. Blanco",
    "wof:placetype":"venue"
},
  "geometry": {"coordinates":[6.1610121727,46.2010498047],"type":"Point"}
}