{
  "type": "Feature",
  "properties": {
    "iso:country":"CH",
    "sg:address":"M\u00fchledorfstrasse 47",
    "sg:city":"Tscheppach",
    "sg:orig_category":"Herstellung von Reiseartikeln, Leder U Sattlerwaren Innendekorationsateliers",
    "sg:phone":"+41 32 661 11 75",
    "sg:postcode":"4576",
    "sg:province":"Solothurn",
    "wof:name":"Fritz Sch\u00e4r Sattler-tapezierergesch\u00e4ft",
    "wof:placetype":"venue"
},
  "geometry": {"coordinates":[7.4786529541,47.145904541],"type":"Point"}
}