{
  "type": "Feature",
  "properties": {
    "iso:country":"CH",
    "sg:address":"M\u00fchlemattstrasse 13",
    "sg:city":"Liestal",
    "sg:orig_category":"Organisationen des Gesundheitswesen",
    "sg:phone":"+41 61 921 06 08",
    "sg:postcode":"4410",
    "sg:province":"Basel-Landschaft",
    "wof:name":"Spitex Liestal",
    "wof:placetype":"venue"
},
  "geometry": {"coordinates":[7.7309541702,47.4894065857],"type":"Point"}
}