{
  "type": "Feature",
  "properties": {
    "iso:country":"CH",
    "sg:address":"Via San Gottardo 164",
    "sg:city":"Minusio",
    "sg:orig_category":"Zimmerei, Dachdeckerei, Bauspenglerei U Abdichtung",
    "sg:phone":"+41 91 743 20 02",
    "sg:postcode":"6648",
    "sg:province":"Ticino",
    "wof:name":"Gaiardelli Chalet Sagl",
    "wof:placetype":"venue"
},
  "geometry": {"coordinates":[8.8218994141,46.1786880493],"type":"Point"}
}