{
  "type": "Feature",
  "properties": {
    "iso:country":"CH",
    "sg:address":"Presa Alta",
    "sg:city":"Brusio",
    "sg:orig_category":"RESTAURANTS: TEA-ROOMS",
    "sg:postcode":"7743",
    "sg:province":"Graubunden",
    "wof:name":"Lidia Kohler",
    "wof:placetype":"venue"
},
  "geometry": {"coordinates":[10.120303154,46.2692222595],"type":"Point"}
}