{
  "type": "Feature",
  "properties": {
    "iso:country":"CH",
    "sg:address":"Kastanienbaumstrasse 79",
    "sg:city":"Horw",
    "sg:orig_category":"Malerei",
    "sg:phone":"+41 41 340 22 31",
    "sg:postcode":"6048",
    "sg:province":"Luzern",
    "wof:name":"Walter Huber Malergesch\u00e4ft",
    "wof:placetype":"venue"
},
  "geometry": {"coordinates":[8.3095397949,47.0235137939],"type":"Point"}
}