{
  "type": "Feature",
  "properties": {
    "iso:country":"CH",
    "sg:address":"Alte Zentrale Lonza 3945 Gampel. Postfach 79",
    "sg:city":"Gampel",
    "sg:orig_category":"Herstellung von Verpackungen aus Kunststoff R\u00fcckgewinnung U Vorbereitung f\u00fcr die Wiederverwertung Re",
    "sg:phone":"+41 91 648 33 33",
    "sg:postcode":"3945",
    "sg:province":"Valais",
    "wof:name":"Ecopacking Sa",
    "wof:placetype":"venue"
},
  "geometry": {"coordinates":[8.9712247849,45.9057006836],"type":"Point"}
}