{
  "type": "Feature",
  "properties": {
    "iso:country":"CH",
    "sg:address":"Bahnhofstrasse 2",
    "sg:city":"Bellach",
    "sg:orig_category":"Handel mit Automobilen",
    "sg:phone":"+41 32 618 39 49",
    "sg:postcode":"4512",
    "sg:province":"Solothurn",
    "wof:name":"Allcar Sa",
    "wof:placetype":"venue"
},
  "geometry": {"coordinates":[7.4954710007,47.2094535828],"type":"Point"}
}