{
  "type": "Feature",
  "properties": {
    "iso:country":"CH",
    "sg:address":"Hauptstrasse 36",
    "sg:city":"M\u00fchlethurnen",
    "sg:orig_category":"Herstellung von Reiseartikeln, Leder U Sattlerwaren",
    "sg:phone":"+41 31 809 02 35",
    "sg:postcode":"3127",
    "sg:province":"Bern",
    "wof:name":"Weber H. U. & Co",
    "wof:placetype":"venue"
},
  "geometry": {"coordinates":[7.5090250969,46.8111495972],"type":"Point"}
}