{
  "type": "Feature",
  "properties": {
    "iso:country":"CH",
    "sg:address":"Bahnhofplatz 3 8001 Z\u00fcrich. Postfach",
    "sg:city":"Z\u00fcrich",
    "sg:orig_category":"Reiseb\u00fcros U Reiseveranstalter",
    "sg:phone":"+41 41 830 28 45",
    "sg:postcode":"8001",
    "sg:province":"Z\u00fcrich",
    "wof:name":"Erlebniswelt Muotathal Gmbh",
    "wof:placetype":"venue"
},
  "geometry": {"coordinates":[8.7111854553,46.9896850586],"type":"Point"}
}