{
  "type": "Feature",
  "properties": {
    "iso:country":"CH",
    "sg:address":"Parkstrasse 2",
    "sg:city":"Oftringen",
    "sg:orig_category":"Detailhandel mit Zeitungen U Zeitschriften Kioske",
    "sg:phone":"+41 62 797 08 65",
    "sg:postcode":"4665",
    "sg:province":"Aargau",
    "wof:name":"Ines Frey Kiosk",
    "wof:placetype":"venue"
},
  "geometry": {"coordinates":[7.9228758812,47.3117103577],"type":"Point"}
}