{
  "type": "Feature",
  "properties": {
    "iso:country":"CH",
    "sg:address":"Via Municipio 4 6616 Losone. Postfach Caselle Postale 378",
    "sg:city":"Losone",
    "sg:orig_category":"Elektroinstallation",
    "sg:postcode":"6616",
    "sg:province":"Ticino",
    "wof:name":"Fournier, D\u00e9pannage, \u00e9lectricit\u00e9, \u00e9lectrom\u00e9nager Entreprise D'\u00e9lectricit\u00e9 Et De T\u00e9l\u00e9phone",
    "wof:placetype":"venue"
},
  "geometry": {"coordinates":[7.3364691734,46.1857719421],"type":"Point"}
}