{
  "type": "Feature",
  "properties": {
    "iso:country":"CH",
    "sg:address":"Tannenberg",
    "sg:city":"Waldkirch",
    "sg:classifiers":[
        {
            "category":"Retail",
            "subcategory":"Auto Repair",
            "type":"Services"
        }
    ],
    "sg:phone":"+41 71 430 03 03",
    "sg:postcode":"9205",
    "sg:province":"St. Gallen",
    "sg:tags":[
        "engine",
        "overhaul"
    ],
    "wof:name":"Ubm Urs Bischofsberger Motoren",
    "wof:placetype":"venue"
},
  "geometry": {"coordinates":[9.308588028,47.4548034668],"type":"Point"}
}