{
  "type": "Feature",
  "properties": {
    "iso:country":"CH",
    "sg:address":"Z\u00fcrcherstrasse 161",
    "sg:city":"Frauenfeld",
    "sg:orig_category":"Detailhandel mit Geschenkartikeln U Souvenirs Detailhandel mit M\u00f6beln",
    "sg:phone":"+41 52 721 53 79",
    "sg:postcode":"8500",
    "sg:province":"Thurgau",
    "wof:name":"Finnshop A.breitenmoser",
    "wof:placetype":"venue"
},
  "geometry": {"coordinates":[8.8971233368,47.5560722351],"type":"Point"}
}