{
  "type": "Feature",
  "properties": {
    "iso:country":"CH",
    "sg:address":"G\u00f6sgerstrasse 102",
    "sg:city":"Niedererlinsbach",
    "sg:orig_category":"Gewinnung von Kies U Sand Herstellung von Betonerzeugnissen f\u00fcr den Bau",
    "sg:phone":"+41 62 844 10 15",
    "sg:postcode":"5015",
    "sg:province":"Solothurn",
    "wof:name":"Belser Ag",
    "wof:placetype":"venue"
},
  "geometry": {"coordinates":[8.0051851273,47.3882293701],"type":"Point"}
}