{
  "type": "Feature",
  "properties": {
    "iso:country":"CH",
    "sg:address":"Industriestrasse 1",
    "sg:city":"Embrach",
    "sg:orig_category":"Hardwareberatung",
    "sg:phone":"+41 32 968 95 20",
    "sg:postcode":"8424",
    "sg:province":"Z\u00fcrich",
    "wof:name":"Chronofiable Sa",
    "wof:placetype":"venue"
},
  "geometry": {"coordinates":[6.8263468742,47.1074409485],"type":"Point"}
}