{
  "type": "Feature",
  "properties": {
    "iso:country":"CH",
    "sg:address":"Schulstrasse 15 7302 Landquart. Postfach",
    "sg:city":"Landquart",
    "sg:orig_category":"Fachdetailhandel in Verkaufsr\u00e4umen Herstellung von keramischen Haushaltswaren U Ziergegenst\u00e4nden",
    "sg:phone":"+41 81 322 82 83",
    "sg:postcode":"7302",
    "sg:province":"Graubunden",
    "wof:name":"Gerda's Creativ-geschenke + T\u00f6pfertreff, Kofler",
    "wof:placetype":"venue"
},
  "geometry": {"coordinates":[9.5584249496,46.9659004211],"type":"Point"}
}