{
  "type": "Feature",
  "properties": {
    "iso:country":"CH",
    "sg:address":"Willikon 48 8618 Oetwil Am See. Postfach",
    "sg:city":"Feldbach",
    "sg:orig_category":"Instandhaltung U Reparatur von Automobilen",
    "sg:postcode":"8714",
    "sg:province":"Z\u00fcrich",
    "wof:name":"Carrosserie Maurer",
    "wof:placetype":"venue"
},
  "geometry": {"coordinates":[8.7270078659,47.2673301697],"type":"Point"}
}