{
  "type": "Feature",
  "properties": {
    "iso:country":"CH",
    "sg:address":"Chemin De Delay 9",
    "sg:city":"Vernier",
    "sg:orig_category":"Autogaragen",
    "sg:phone":"+41 22 341 30 10",
    "sg:postcode":"1214",
    "sg:province":"Gen\u00e8ve",
    "wof:name":"Mirek Kubicek Garage",
    "wof:placetype":"venue"
},
  "geometry": {"coordinates":[6.077503,46.218781],"type":"Point"}
}