{
  "type": "Feature",
  "properties": {
    "iso:country":"CH",
    "sg:address":"1854 Leysin. Postfach 14",
    "sg:city":"Leysin",
    "sg:orig_category":"Sportvereine Ballsport Fussball",
    "sg:postcode":"1854",
    "sg:province":"Vaud",
    "wof:name":"Fc Liddes",
    "wof:placetype":"venue"
},
  "geometry": {"coordinates":[7.1808519363,46.0040893555],"type":"Point"}
}