{
  "type": "Feature",
  "properties": {
    "iso:country":"CH",
    "sg:address":"Chemin Des Hutins 33",
    "sg:city":"Confignon",
    "sg:orig_category":"Grosshandel mit sonstigen Maschinen U Ausr\u00fcstungen f\u00fcr Industrie, Handel U Schiffahrt",
    "sg:postcode":"1232",
    "sg:province":"Gen\u00e8ve",
    "wof:name":"Tli Mansson, Tli Mme Monique M.-a. Mansson-steinmetz Succ.",
    "wof:placetype":"venue"
},
  "geometry": {"coordinates":[6.0825648308,46.1755332947],"type":"Point"}
}