{
  "type": "Feature",
  "properties": {
    "iso:country":"CH",
    "sg:address":"Hauptstrasse",
    "sg:city":"Leuggelbach",
    "sg:orig_category":"Detailhandel mit Brot, Back U S\u00fcsswaren",
    "sg:phone":"+41 71 385 12 54",
    "sg:postcode":"8772",
    "sg:province":"Glarus",
    "wof:name":"B\u00e4ckerei-konditorei Str\u00e4ssle",
    "wof:placetype":"venue"
},
  "geometry": {"coordinates":[9.252797,47.416599],"type":"Point"}
}