{
  "type": "Feature",
  "properties": {
    "addr:full":"Musterplatz 762 Gontenschwil Aargau 5728",
    "addr:housenumber":"762",
    "addr:postcode":"5728",
    "addr:street":"Musterplatz",
    "iso:country":"CH",
    "sg:address":"Musterplatz 762",
    "sg:city":"Gontenschwil",
    "sg:orig_category":"Allgemeiner Hoch U Tiefbau Innendekorationsateliers",
    "sg:phone":"+41 62 773 21 73",
    "sg:postcode":"5728",
    "sg:province":"Aargau",
    "wof:name":"Leuenberger K. & Co",
    "wof:placetype":"venue"
},
  "geometry": {"coordinates":[8.146804,47.275257],"type":"Point"}
}