{
  "type": "Feature",
  "properties": {
    "iso:country":"CH",
    "sg:address":"Mitteldorfstrasse 31",
    "sg:city":"Villmergen",
    "sg:orig_category":"Detailhandel mit Radio U Fernsehger\u00e4ten",
    "sg:phone":"+41 56 622 11 11",
    "sg:postcode":"5612",
    "sg:province":"Aargau",
    "wof:name":"Baur Tv Radio/tv & Video",
    "wof:placetype":"venue"
},
  "geometry": {"coordinates":[8.2448530197,47.3456535339],"type":"Point"}
}