{
  "type": "Feature",
  "properties": {
    "iso:country":"CH",
    "sg:address":"Ischlag",
    "sg:city":"Kandersteg",
    "sg:orig_category":"Sonstiger Fachdetailhandel in Verkaufsr\u00e4umen",
    "sg:phone":"+41 33 675 14 63",
    "sg:postcode":"3718",
    "sg:province":"Bern",
    "wof:name":"Erwin Walther Waffen & Munition",
    "wof:placetype":"venue"
},
  "geometry": {"coordinates":[7.6730470657,46.4949836731],"type":"Point"}
}