{
  "type": "Feature",
  "properties": {
    "iso:country":"CH",
    "sg:address":"Krauchtalstrasse 36",
    "sg:city":"Oberburg",
    "sg:orig_category":"Detailhandel mit Brot, Back U S\u00fcsswaren",
    "sg:phone":"+41 34 422 10 83",
    "sg:postcode":"3414",
    "sg:province":"Bern",
    "wof:name":"Beat Friedli B\u00e4ckerei-konditorei",
    "wof:placetype":"venue"
},
  "geometry": {"coordinates":[7.621356,47.038261],"type":"Point"}
}