{
  "type": "Feature",
  "properties": {
    "iso:country":"CH",
    "sg:address":"Rietstrasse 57",
    "sg:city":"Widnau",
    "sg:orig_category":"Non-Classified Establishments",
    "sg:phone":"+41 71 727 09 20",
    "sg:postcode":"9443",
    "sg:province":"St. Gallen",
    "wof:name":"K\u00f6ppel Natursteine Ag",
    "wof:placetype":"venue"
},
  "geometry": {"coordinates":[9.6289978027,47.400062561],"type":"Point"}
}