{
  "type": "Feature",
  "properties": {
    "iso:country":"CH",
    "sg:address":"Pilatusstrasse 18",
    "sg:city":"Luzern",
    "sg:orig_category":"Detailhandel mit Beleuchtungs U Haushaltsgegenst\u00e4nden Grosshandel mit keramischen Erzeugnissen,Glasw",
    "sg:phone":"+41 91 857 05 53",
    "sg:postcode":"6003",
    "sg:province":"Luzern",
    "wof:name":"Sovrana Sagl Articoli Casalinghi",
    "wof:placetype":"venue"
},
  "geometry": {"coordinates":[8.995528,46.187714],"type":"Point"}
}