{
  "type": "Feature",
  "properties": {
    "iso:country":"CH",
    "sg:address":"Kindergartenstrasse 3",
    "sg:city":"Montlingen",
    "sg:orig_category":"Grosshandel mit Holz U Baustoffen Herstellung von Konstruktionsteilen, Fertigbauteilen U Ausbaueleme",
    "sg:phone":"+41 79 437 54 10",
    "sg:postcode":"9462",
    "sg:province":"St. Gallen",
    "wof:name":"T\u00fcrex-import Benz August",
    "wof:placetype":"venue"
},
  "geometry": {"coordinates":[9.5887908936,47.3338165283],"type":"Point"}
}