{
  "type": "Feature",
  "properties": {
    "addr:full":"Rue De Lausanne 6 Sion Valais 1950",
    "addr:housenumber":"6",
    "addr:postcode":"1950",
    "addr:street":"Rue De Lausanne",
    "iso:country":"CH",
    "sg:address":"Rue De Lausanne 6",
    "sg:city":"Sion",
    "sg:orig_category":"Advokaturb\u00fcros Notariate",
    "sg:phone":"+41 27 322 79 36",
    "sg:postcode":"1950",
    "sg:province":"Valais",
    "wof:name":"Jean-j\u00e9r\u00f4me Crittin Etude D'avocat & Notaire",
    "wof:placetype":"venue"
},
  "geometry": {"coordinates":[7.359739,46.23288],"type":"Point"}
}