{
  "type": "Feature",
  "properties": {
    "iso:country":"CH",
    "sg:address":"Stradun",
    "sg:city":"Scuol",
    "sg:orig_category":"Parf\u00fcmerien U sonstiger Detailhandel mit kosmetischen Artikeln U K\u00f6rperpflegemitteln",
    "sg:phone":"+41 81 864 12 75",
    "sg:postcode":"7550",
    "sg:province":"Graubunden",
    "wof:name":"Astrid Casura",
    "wof:placetype":"venue"
},
  "geometry": {"coordinates":[10.2936811447,46.7949409485],"type":"Point"}
}