{
  "type": "Feature",
  "properties": {
    "iso:country":"CH",
    "sg:address":"Haldenstrasse 44",
    "sg:city":"Langenthal",
    "sg:orig_category":"Unternehmensberatung",
    "sg:phone":"+41 22 362 24 55",
    "sg:postcode":"4900",
    "sg:province":"Bern",
    "wof:name":"Affentranger Rudolf S\u00e0rl",
    "wof:placetype":"venue"
},
  "geometry": {"coordinates":[6.2182898521,46.4542808533],"type":"Point"}
}