{
  "type": "Feature",
  "properties": {
    "iso:country":"CH",
    "sg:address":"Hauptstrasse 144 4450 Sissach. Postfach",
    "sg:city":"Sissach",
    "sg:orig_category":"Ingenieurb\u00fcros Maschinenbau Maschinen-Fabrikation",
    "sg:phone":"+41 61 973 18 80",
    "sg:postcode":"4450",
    "sg:province":"Basel-Landschaft",
    "wof:name":"Engineering Zumbrunn",
    "wof:placetype":"venue"
},
  "geometry": {"coordinates":[7.8006029129,47.4660186768],"type":"Point"}
}