{
  "type": "Feature",
  "properties": {
    "iso:country":"CH",
    "sg:address":"Rothstrasse 48 8057 Z\u00fcrich. Postfach",
    "sg:city":"Z\u00fcrich",
    "sg:orig_category":"Unternehmensberatung",
    "sg:phone":"+41 13629570",
    "sg:postcode":"8033",
    "sg:province":"Z\u00fcrich",
    "wof:name":"Kogrere Ag",
    "wof:placetype":"venue"
},
  "geometry": {"coordinates":[8.5381288528,47.3935089111],"type":"Point"}
}