{
  "type": "Feature",
  "properties": {
    "iso:country":"CH",
    "sg:address":"Schmittenbrugg 4",
    "sg:city":"Gipf-oberfrick",
    "sg:orig_category":"Tierarztpraxis",
    "sg:phone":"+41 62 865 60 40",
    "sg:postcode":"5073",
    "sg:province":"Aargau",
    "wof:name":"Dr. Med. Vet. Rolf Reimann Tierarzt",
    "wof:placetype":"venue"
},
  "geometry": {"coordinates":[8.0069770813,47.5018119812],"type":"Point"}
}