{
  "type": "Feature",
  "properties": {
    "iso:country":"CH",
    "sg:address":"Ochsengasse 109",
    "sg:city":"Hellikon",
    "sg:orig_category":"Herstellung von Mess U Kontrollinstrumenten U vorrichtungen Herstellung von sonstigen elektrischen A",
    "sg:phone":"+41 61 871 02 00",
    "sg:postcode":"4316",
    "sg:province":"Aargau",
    "wof:name":"Mbs Sicherheit + Technik Ag",
    "wof:placetype":"venue"
},
  "geometry": {"coordinates":[7.9251389503,47.5098686218],"type":"Point"}
}