{
  "type": "Feature",
  "properties": {
    "iso:country":"CH",
    "sg:address":"W\u00fcrzenbachstrasse 53",
    "sg:city":"Luzern",
    "sg:orig_category":"Non-Classified Establishments",
    "sg:postcode":"6006",
    "sg:province":"Luzern",
    "wof:name":"Transport Bjelobrk",
    "wof:placetype":"venue"
},
  "geometry": {"coordinates":[8.3491640091,47.0561599731],"type":"Point"}
}