{
  "type": "Feature",
  "properties": {
    "iso:country":"CH",
    "sg:address":"Olgiati Via C. 17 6512 Giubiasco. Postfach",
    "sg:city":"Giubiasco",
    "sg:orig_category":"Architektur U Ingenieurb\u00fcros",
    "sg:postcode":"6512",
    "sg:province":"Ticino",
    "wof:name":"Studio Di Architettura Giussani Berther E Associati Sagl",
    "wof:placetype":"venue"
},
  "geometry": {"coordinates":[9.010825,46.17308],"type":"Point"}
}