{
  "type": "Feature",
  "properties": {
    "iso:country":"CH",
    "sg:address":"Via Ciseri 2 6900 Lugano. Postfach",
    "sg:city":"Lugano",
    "sg:orig_category":"Detailhandel mit elektrischen Haushalts-,Radio U Fernsehger\u00e4ten sowie Musikinstrumenten",
    "sg:postcode":"6900",
    "sg:province":"Ticino",
    "wof:name":"Albertoni Radio Tv Elettronica",
    "wof:placetype":"venue"
},
  "geometry": {"coordinates":[8.9533157349,46.0101509094],"type":"Point"}
}