{
  "type": "Feature",
  "properties": {
    "iso:country":"CH",
    "sg:address":"6577",
    "sg:city":"Ranzo",
    "sg:orig_category":"Unclassifiable Establishments",
    "sg:postcode":"6577",
    "sg:province":"Ticino",
    "wof:name":"Re-we/vto Di Vontobel Monika",
    "wof:placetype":"venue"
},
  "geometry": {"coordinates":[8.7681398392,46.1104888916],"type":"Point"}
}