{
  "type": "Feature",
  "properties": {
    "iso:country":"CH",
    "sg:address":"3925",
    "sg:city":"Gr\u00e4chen",
    "sg:orig_category":"Erbringung von sonstigen Dienstleistungen f\u00fcr Unterhaltung, Erholung U Freizeit",
    "sg:postcode":"3925",
    "sg:province":"Valais",
    "wof:name":"Musiker + Artistenagentur Perren Charles",
    "wof:placetype":"venue"
},
  "geometry": {"coordinates":[7.8392400742,46.1961631775],"type":"Point"}
}