{
  "type": "Feature",
  "properties": {
    "iso:country":"CH",
    "sg:address":"1986 Arolla. Postfach",
    "sg:city":"Arolla",
    "sg:classifiers":[
        {
            "category":"Travel",
            "subcategory":"Hotels & Motels",
            "type":"Entertainment"
        }
    ],
    "sg:phone":"+41 27 283 16 26",
    "sg:postcode":"1986",
    "sg:province":"Valais",
    "sg:tags":[
        "hotels",
        "mit",
        "restaurant"
    ],
    "wof:name":"Anz\u00e9vui Vincent",
    "wof:placetype":"venue"
},
  "geometry": {"coordinates":[7.4876799583,46.0387115479],"type":"Point"}
}