{
  "type": "Feature",
  "properties": {
    "iso:country":"CH",
    "sg:address":"Mattenhofstrasse 36",
    "sg:city":"Bern",
    "sg:orig_category":"Detailhandel mit Milcherzeugnissen U Eiern",
    "sg:phone":"+41 31 381 83 39",
    "sg:postcode":"3007",
    "sg:province":"Bern",
    "wof:name":"Fritz Freiburghaus Milchprodukte",
    "wof:placetype":"venue"
},
  "geometry": {"coordinates":[7.4283871651,46.9439697266],"type":"Point"}
}