{
  "type": "Feature",
  "properties": {
    "iso:country":"CH",
    "sg:address":"Alte Distelbergstrasse 1 5035 Unterentfelden. Postfach 69",
    "sg:city":"Oberentfelden",
    "sg:orig_category":"Herstellung von Gummi U Kunststoffwaren",
    "sg:phone":"+41 62 723 76 77",
    "sg:postcode":"5036",
    "sg:province":"Aargau",
    "wof:name":"Saka Ag",
    "wof:placetype":"venue"
},
  "geometry": {"coordinates":[8.0471000671,47.3728790283],"type":"Point"}
}