{
  "type": "Feature",
  "properties": {
    "iso:country":"CH",
    "sg:address":"Casa Cumin 7130 Ilanz. Postfach",
    "sg:city":"Ilanz",
    "sg:orig_category":"Unclassifiable Establishments",
    "sg:postcode":"7130",
    "sg:province":"Graubunden",
    "wof:name":"Gemeindewerke Strom, Gas-& Wasserversorgung",
    "wof:placetype":"venue"
},
  "geometry": {"coordinates":[8.5872621536,47.3172569275],"type":"Point"}
}