{
  "type": "Feature",
  "properties": {
    "iso:country":"CH",
    "sg:address":"Alte Landstrasse 108-114 8800 Thalwil. Postfach 1531",
    "sg:city":"Thalwil",
    "sg:orig_category":"Polizei",
    "sg:phone":"+41 17232390",
    "sg:postcode":"8800",
    "sg:province":"Z\u00fcrich",
    "wof:name":"Gemeindepolizei",
    "wof:placetype":"venue"
},
  "geometry": {"coordinates":[8.5651626587,47.2920036316],"type":"Point"}
}