{
  "type": "Feature",
  "properties": {
    "iso:country":"CH",
    "sg:address":"Oberdorfstrasse 95",
    "sg:city":"Herisau",
    "sg:orig_category":"Elektroinstallation",
    "sg:phone":"+41 71 351 63 35",
    "sg:postcode":"9100",
    "sg:province":"Appenzell Ausserrhoden",
    "wof:name":"Jakob Zuberb\u00fchler, Elektr. Anlagen",
    "wof:placetype":"venue"
},
  "geometry": {"coordinates":[9.2874860764,47.3874359131],"type":"Point"}
}