{
  "type": "Feature",
  "properties": {
    "iso:country":"CH",
    "sg:address":"Seeli",
    "sg:city":"Richterswil",
    "sg:orig_category":"Herstellung von Konstruktionsteilen, Fertigbauteilen U Ausbauelementen aus Holz",
    "sg:postcode":"8805",
    "sg:province":"Z\u00fcrich",
    "wof:name":"K\u00e4lin-l\u00fc\u00f6nd Josef, Schreinerei",
    "wof:placetype":"venue"
},
  "geometry": {"coordinates":[8.6740646362,47.1861991882],"type":"Point"}
}