{
  "type": "Feature",
  "properties": {
    "iso:country":"CH",
    "sg:address":"Kirchgasse 12",
    "sg:city":"Kloten",
    "sg:orig_category":"Detailhandel mit Geschenkartikeln U Souvenirs",
    "sg:phone":"+41 18133514",
    "sg:postcode":"8302",
    "sg:province":"Z\u00fcrich",
    "wof:name":"Monika's Eggli Monika Specker",
    "wof:placetype":"venue"
},
  "geometry": {"coordinates":[8.5828542709,47.4506988525],"type":"Point"}
}