{
  "type": "Feature",
  "properties": {
    "iso:country":"CH",
    "sg:address":"Kellerweg 32 8055 Z\u00fcrich. Postfach 812",
    "sg:city":"Z\u00fcrich",
    "sg:orig_category":"Hoch U Tiefbau",
    "sg:phone":"+41 17503538",
    "sg:postcode":"8055",
    "sg:province":"Z\u00fcrich",
    "wof:name":"Lanfranconi Bauunternehmung",
    "wof:placetype":"venue"
},
  "geometry": {"coordinates":[8.4375896454,47.4166145325],"type":"Point"}
}