{
  "type": "Feature",
  "properties": {
    "iso:country":"CH",
    "sg:address":"Im Horben 7",
    "sg:city":"K\u00fcnten",
    "sg:orig_category":"Unclassifiable Establishments",
    "sg:postcode":"5444",
    "sg:province":"Aargau",
    "wof:name":"Korfitsen",
    "wof:placetype":"venue"
},
  "geometry": {"coordinates":[8.3348312378,47.3888435364],"type":"Point"}
}