{
  "type": "Feature",
  "properties": {
    "addr:full":"Bodenackerstrasse 2 Bottmingen Basel-Landschaft 4103",
    "addr:housenumber":"2",
    "addr:postcode":"4103",
    "addr:street":"Bodenackerstrasse",
    "iso:country":"CH",
    "sg:address":"Bodenackerstrasse 2",
    "sg:city":"Bottmingen",
    "sg:orig_category":"Architekturb\u00fcros",
    "sg:phone":"+41 61 421 70 54",
    "sg:postcode":"4103",
    "sg:province":"Basel-Landschaft",
    "wof:name":"Eigen Haus P. Aeschlimann Architekturb\u00fcro",
    "wof:placetype":"venue"
},
  "geometry": {"coordinates":[7.58518,47.526421],"type":"Point"}
}