{
  "type": "Feature",
  "properties": {
    "iso:country":"CH",
    "sg:address":"Hauptstrasse 31",
    "sg:city":"Erlen",
    "sg:orig_category":"Arztpraxen",
    "sg:phone":"+41 71 646 00 60",
    "sg:postcode":"8586",
    "sg:province":"Thurgau",
    "wof:name":"Dres Med.m. Oettli & U. Beerli Aerzte F\u00fcr Allg.medizin Fmh",
    "wof:placetype":"venue"
},
  "geometry": {"coordinates":[9.233645,47.54797],"type":"Point"}
}