{
  "type": "Feature",
  "properties": {
    "iso:country":"CH",
    "sg:address":"Kantonsstrasse 6 3930 Visp. Postfach",
    "sg:city":"Visp",
    "sg:orig_category":"Kantonalbanken",
    "sg:phone":"+41 12712230",
    "sg:postcode":"3930",
    "sg:province":"Valais",
    "wof:name":"Banque Cantonale Du Valais",
    "wof:placetype":"venue"
},
  "geometry": {"coordinates":[7.8804740906,46.2921714783],"type":"Point"}
}