{
  "type": "Feature",
  "properties": {
    "addr:full":"Ufbruchstrasse 3 W\u00e4ngi Thurgau 9545",
    "addr:housenumber":"3",
    "addr:postcode":"9545",
    "addr:street":"Ufbruchstrasse;Thurgau",
    "iso:country":"CH",
    "sg:address":"Ufbruchstrasse 3",
    "sg:city":"W\u00e4ngi",
    "sg:orig_category":"Bauschreinerei Zimmerei, Dachdeckerei, Bauspenglerei U Abdichtung",
    "sg:phone":"+41 52 378 22 13",
    "sg:postcode":"9545",
    "sg:province":"Thurgau",
    "wof:name":"Rudolf Isenring Ag Zimmerei & Bauschreinerei",
    "wof:placetype":"venue"
},
  "geometry": {"coordinates":[8.939518,47.503292],"type":"Point"}
}