{
  "type": "Feature",
  "properties": {
    "iso:country":"CH",
    "sg:address":"Harschwendi",
    "sg:city":"Waldstatt",
    "sg:orig_category":"Fuhrhaltereien",
    "sg:phone":"+41 55 644 29 41",
    "sg:postcode":"9104",
    "sg:province":"Appenzell Ausserrhoden",
    "wof:name":"Kaspar H\u00f6sli Fuhrhalterei",
    "wof:placetype":"venue"
},
  "geometry": {"coordinates":[9.0640926361,46.9853286743],"type":"Point"}
}