{
  "type": "Feature",
  "properties": {
    "iso:country":"CH",
    "sg:address":"Sch\u00f6neggstrasse 6",
    "sg:city":"Horw",
    "sg:orig_category":"Zahnarztpraxen",
    "sg:phone":"+41 19100475",
    "sg:postcode":"6048",
    "sg:province":"Luzern",
    "wof:name":"Dr.med.dent.lorenz Hugentobler Zahnarzt",
    "wof:placetype":"venue"
},
  "geometry": {"coordinates":[8.5799007416,47.3171730042],"type":"Point"}
}