{
  "type": "Feature",
  "properties": {
    "iso:country":"CH",
    "sg:address":"Bachelin Avenue 11",
    "sg:city":"St-blaise",
    "sg:orig_category":"Wirtschaftspr\u00fcfung, Steuerberatung U Treuhand",
    "sg:phone":"+41 32 756 60 40",
    "sg:postcode":"2072",
    "sg:province":"Neuch\u00e2tel",
    "wof:name":"Jansen + Partners Sa",
    "wof:placetype":"venue"
},
  "geometry": {"coordinates":[6.9860172272,47.0127449036],"type":"Point"}
}