{
  "type": "Feature",
  "properties": {
    "iso:country":"CH",
    "sg:address":"Morgartenstrasse 10",
    "sg:city":"Z\u00fcrich",
    "sg:orig_category":"Druck ohne Zeitungsdruck",
    "sg:phone":"+41 12415527",
    "sg:postcode":"8004",
    "sg:province":"Z\u00fcrich",
    "wof:name":"Verso Ag Schule Und Vereine Auf Reisen",
    "wof:placetype":"venue"
},
  "geometry": {"coordinates":[8.5289974213,47.3714332581],"type":"Point"}
}