{
  "type": "Feature",
  "properties": {
    "iso:country":"CH",
    "sg:address":"Planaweg 1",
    "sg:city":"Sevelen",
    "sg:orig_category":"RESTAURANTS: TEA-ROOMS",
    "sg:phone":"+41 79 672 18 68",
    "sg:postcode":"9475",
    "sg:province":"St. Gallen",
    "wof:name":"Gastroratio Gmbh",
    "wof:placetype":"venue"
},
  "geometry": {"coordinates":[9.4851541519,47.123336792],"type":"Point"}
}