{
  "type": "Feature",
  "properties": {
    "addr:full":"Hintermatt Walchwil Zug 6318",
    "addr:postcode":"6318",
    "addr:street":"Hintermatt;Zug",
    "iso:country":"CH",
    "sg:address":"Hintermatt",
    "sg:city":"Walchwil",
    "sg:orig_category":"Allgemeiner Hoch U Tiefbau",
    "sg:postcode":"6318",
    "sg:province":"Zug",
    "wof:name":"Wiss Oswald",
    "wof:placetype":"venue"
},
  "geometry": {"coordinates":[8.52098,47.102352],"type":"Point"}
}