{
  "type": "Feature",
  "properties": {
    "iso:country":"CH",
    "sg:address":"Vi 316",
    "sg:city":"Scuol",
    "sg:orig_category":"Non-Classified Establishments",
    "sg:postcode":"7550",
    "sg:province":"Graubunden",
    "wof:name":"Cd-net Gmbh",
    "wof:placetype":"venue"
},
  "geometry": {"coordinates":[10.3000488281,46.7978096008],"type":"Point"}
}