{
  "type": "Feature",
  "properties": {
    "iso:country":"CH",
    "sg:address":"Landstrasse 10",
    "sg:city":"Turgi",
    "sg:orig_category":"Erbringung von Dienstleistungen f\u00fcr Unternehmen Grosshandel mit sonstigen Maschinen U Ausr\u00fcstungen f",
    "sg:phone":"+41 81 756 22 80",
    "sg:postcode":"5300",
    "sg:province":"Aargau",
    "wof:name":"Modella Ag",
    "wof:placetype":"venue"
},
  "geometry": {"coordinates":[9.4711065292,47.1621131897],"type":"Point"}
}