{
  "type": "Feature",
  "properties": {
    "iso:country":"CH",
    "sg:address":"4464",
    "sg:city":"Maisprach",
    "sg:orig_category":"Sportvereine Turnen",
    "sg:phone":"+41 71 777 22 14",
    "sg:postcode":"4464",
    "sg:province":"Basel-Landschaft",
    "wof:name":"Turnverein Marbach",
    "wof:placetype":"venue"
},
  "geometry": {"coordinates":[9.5790300369,47.3841705322],"type":"Point"}
}