{
  "type": "Feature",
  "properties": {
    "iso:country":"CH",
    "sg:address":"Dorfstrasse 51",
    "sg:city":"Hasle-r\u00fcegsau",
    "sg:orig_category":"Mechanik Schlossereien",
    "sg:phone":"+41 32 351 10 71",
    "sg:postcode":"3415",
    "sg:province":"Bern",
    "wof:name":"Schwab Walter",
    "wof:placetype":"venue"
},
  "geometry": {"coordinates":[7.3669238091,47.1384391785],"type":"Point"}
}