{
  "type": "Feature",
  "properties": {
    "iso:country":"CH",
    "sg:address":"Rousseaustrasse 23",
    "sg:city":"Z\u00fcrich",
    "sg:orig_category":"Erbringung von sonstigen Dienstleistungen f\u00fcr Unternehmen",
    "sg:phone":"+41 12517735",
    "sg:postcode":"8037",
    "sg:province":"Z\u00fcrich",
    "wof:name":"Peter Vogelsang Modellbau",
    "wof:placetype":"venue"
},
  "geometry": {"coordinates":[8.5340137482,47.3879356384],"type":"Point"}
}