{
  "type": "Feature",
  "properties": {
    "iso:country":"CH",
    "sg:address":"Saint-fran\u00e7ois Place 11 1003 Lausanne. Postfach",
    "sg:city":"Lausanne",
    "sg:orig_category":"Interessenvertretungen",
    "sg:postcode":"1003",
    "sg:province":"Vaud",
    "wof:name":"Fondation Perrin L\u00e9on",
    "wof:placetype":"venue"
},
  "geometry": {"coordinates":[6.9500641823,47.021446228],"type":"Point"}
}