{
  "type": "Feature",
  "properties": {
    "iso:country":"CH",
    "sg:address":"4629",
    "sg:city":"Fulenbach",
    "sg:orig_category":"Bau\u00e4mter",
    "sg:phone":"+41 52 649 24 01",
    "sg:postcode":"4629",
    "sg:province":"Solothurn",
    "wof:name":"Baureferat Der Gemeinde Lohn",
    "wof:placetype":"venue"
},
  "geometry": {"coordinates":[8.67099,47.75605],"type":"Point"}
}