{
  "type": "Feature",
  "properties": {
    "iso:country":"CH",
    "sg:address":"Bienenweg 10",
    "sg:city":"Frauenfeld",
    "sg:orig_category":"Sonstige Kultur U Unterhaltungseinrichtungen Tanzschulen, Tanzlehrer",
    "sg:phone":"+41 62 824 67 01",
    "sg:postcode":"8500",
    "sg:province":"Thurgau",
    "wof:name":"Ballettschule Ariane, H\u00e4nni Renate.",
    "wof:placetype":"venue"
},
  "geometry": {"coordinates":[8.0736427307,47.3938331604],"type":"Point"}
}