{
  "type": "Feature",
  "properties": {
    "iso:country":"CH",
    "sg:address":"Via Muraccio 62",
    "sg:city":"Ascona",
    "sg:orig_category":"Reparatur von Uhren U Schmuck",
    "sg:phone":"+41 91 791 25 60",
    "sg:postcode":"6612",
    "sg:province":"Ticino",
    "wof:name":"Giovanni Mordasini Orologiaio",
    "wof:placetype":"venue"
},
  "geometry": {"coordinates":[8.7805347443,46.1536941528],"type":"Point"}
}