{
  "type": "Feature",
  "properties": {
    "iso:country":"CH",
    "sg:address":"Kellerhofstrasse 16",
    "sg:city":"Elgg",
    "sg:orig_category":"Grosshandel mit chemischen Erzeugnissen Herstellung von Seifen, Wasch U Reinigungsmitteln",
    "sg:phone":"+41 62 212 44 15",
    "sg:postcode":"8353",
    "sg:province":"Z\u00fcrich",
    "wof:name":"Christ P., Wasch Und Reinigungsmittel",
    "wof:placetype":"venue"
},
  "geometry": {"coordinates":[7.8627910614,47.3479881287],"type":"Point"}
}