{
  "type": "Feature",
  "properties": {
    "iso:country":"CH",
    "sg:address":"Alpes Avenue Des 9",
    "sg:city":"Sierre",
    "sg:orig_category":"Handel mit Motorr\u00e4dern, Teilen U Zubeh\u00f6r Instandhaltung U Reparatur von Motorr\u00e4dern",
    "sg:phone":"+41 27 455 16 78",
    "sg:postcode":"3960",
    "sg:province":"Valais",
    "wof:name":"Vuistiner Danielle",
    "wof:placetype":"venue"
},
  "geometry": {"coordinates":[7.5306549072,46.2924041748],"type":"Point"}
}