{
  "type": "Feature",
  "properties": {
    "iso:country":"CH",
    "sg:address":"Chemin De Chafalet 15",
    "sg:city":"Dardagny",
    "sg:orig_category":"Unclassifiable Establishments",
    "sg:postcode":"1282",
    "wof:name":"D\u00f6rig",
    "wof:placetype":"venue"
},
  "geometry": {"coordinates":[5.9883022308,46.2049980164],"type":"Point"}
}