{
  "type": "Feature",
  "properties": {
    "iso:country":"CH",
    "sg:address":"Ch\u00e2teau De Grandson",
    "sg:city":"Grandson",
    "sg:orig_category":"Interessenvertretungen",
    "sg:postcode":"1422",
    "sg:province":"Vaud",
    "wof:name":"Fondation Du Ch\u00e2teau De Grandson",
    "wof:placetype":"venue"
},
  "geometry": {"coordinates":[6.6470799446,46.8095703125],"type":"Point"}
}