{
  "type": "Feature",
  "properties": {
    "iso:country":"CH",
    "sg:address":"Chesa Alpina 7516 Maloja. Postfach",
    "sg:city":"Maloja",
    "sg:orig_category":"RESTAURANTS: TEA-ROOMS",
    "sg:phone":"+41 81 407 12 23",
    "sg:postcode":"7516",
    "sg:province":"Graubunden",
    "wof:name":"Chesa Alpina Maloja Gmbh Gastgewerbe, Bes. Restaurant Chesa Alpina",
    "wof:placetype":"venue"
},
  "geometry": {"coordinates":[9.6952791214,46.401008606],"type":"Point"}
}