{
  "type": "Feature",
  "properties": {
    "addr:full":"R\u00f6schibachstrasse 52 Z\u00fcrich Z\u00fcrich 8037",
    "addr:housenumber":"52",
    "addr:postcode":"8037",
    "addr:street":"Roeschibachstrasse",
    "iso:country":"CH",
    "sg:address":"R\u00f6schibachstrasse 52",
    "sg:city":"Z\u00fcrich",
    "sg:orig_category":"Bau U Wohngenossenschaften",
    "sg:postcode":"8037",
    "sg:province":"Z\u00fcrich",
    "wof:name":"Baugenossenschaft Kyburg",
    "wof:placetype":"venue"
},
  "geometry": {"coordinates":[8.526516,47.393364],"type":"Point"}
}