{
  "type": "Feature",
  "properties": {
    "iso:country":"CH",
    "sg:address":"Schwerzenbachstrasse 28",
    "sg:city":"F\u00e4llanden",
    "sg:orig_category":"Reinigungsgewerbe",
    "sg:postcode":"8117",
    "sg:province":"Z\u00fcrich",
    "wof:name":"Clean & Proper Wissmann Reinigungen",
    "wof:placetype":"venue"
},
  "geometry": {"coordinates":[8.6422166824,47.3731079102],"type":"Point"}
}