{
  "type": "Feature",
  "properties": {
    "iso:country":"CH",
    "sg:address":"Wiesentalstrasse 84",
    "sg:city":"Chur",
    "sg:orig_category":"Detailhandel mit Waren verschiedener Art, Hauptrichtung Nahrungsmittel",
    "sg:phone":"+41 81 356 02 18",
    "sg:postcode":"7000",
    "sg:province":"Graubunden",
    "wof:name":"Kneub\u00fchler-cazin & Co.",
    "wof:placetype":"venue"
},
  "geometry": {"coordinates":[9.531126976,46.8604927063],"type":"Point"}
}