{
  "type": "Feature",
  "properties": {
    "iso:country":"CH",
    "sg:address":"Chemin Du Champ-des-filles 19",
    "sg:city":"Plan-les-ouates",
    "sg:orig_category":"Elektroinstallation Verlagsgewerbe",
    "sg:phone":"+41 22 794 83 60",
    "sg:postcode":"1228",
    "sg:province":"Gen\u00e8ve",
    "wof:name":"Imsat Sa",
    "wof:placetype":"venue"
},
  "geometry": {"coordinates":[6.1067352295,46.1658859253],"type":"Point"}
}