{
  "type": "Feature",
  "properties": {
    "iso:country":"CH",
    "sg:address":"Z\u00e4hringerstrasse 43",
    "sg:city":"Z\u00fcrich",
    "sg:orig_category":"HOTELS: OHNE RESTAURANT",
    "sg:phone":"+41 12515426",
    "sg:postcode":"8001",
    "sg:province":"Z\u00fcrich",
    "wof:name":"Hotel Garni R\u00fctli",
    "wof:placetype":"venue"
},
  "geometry": {"coordinates":[8.5443410873,47.3761558533],"type":"Point"}
}