{
  "type": "Feature",
  "properties": {
    "iso:country":"CH",
    "sg:address":"Heulenlochweg 4",
    "sg:city":"Pratteln",
    "sg:orig_category":"Wirtschaftspr\u00fcfung, Steuerberatung U Treuhand",
    "sg:phone":"+41 61 823 03 73",
    "sg:postcode":"4133",
    "sg:province":"Basel-Landschaft",
    "wof:name":"Regio Treuhand D\u00fcrrenberger B. + Brunner M.",
    "wof:placetype":"venue"
},
  "geometry": {"coordinates":[7.6837329865,47.5133056641],"type":"Point"}
}