{
  "type": "Feature",
  "properties": {
    "iso:country":"CH",
    "sg:address":"Bergstrasse 10",
    "sg:city":"Luzern",
    "sg:orig_category":"G\u00fcterbef\u00f6rderung im Strassenverkehr",
    "sg:phone":"+41 41 420 25 11",
    "sg:postcode":"6004",
    "sg:province":"Luzern",
    "wof:name":"Dominus Vukicevic",
    "wof:placetype":"venue"
},
  "geometry": {"coordinates":[8.307636261,47.0597839355],"type":"Point"}
}