{
  "type": "Feature",
  "properties": {
    "addr:full":"Blumenfeldstrasse 30 8046 Z\u00fcrich. Postfach Z\u00fcrich Z\u00fcrich 8046",
    "addr:housenumber":"30",
    "addr:postcode":"8046 zuerich. postfach;8046",
    "addr:street":"Blumenfeldstrasse",
    "iso:country":"CH",
    "sg:address":"Blumenfeldstrasse 30 8046 Z\u00fcrich. Postfach",
    "sg:city":"Z\u00fcrich",
    "sg:orig_category":"Allgemeiner Hochbau Sonstiger spezialisierter Hoch U Tiefbau",
    "sg:phone":"+41 13716968",
    "sg:postcode":"8046",
    "sg:province":"Z\u00fcrich",
    "wof:name":"Meier & Ritter Ag",
    "wof:placetype":"venue"
},
  "geometry": {"coordinates":[8.504081,47.423134],"type":"Point"}
}