{
  "type": "Feature",
  "properties": {
    "addr:full":"Eschenmoosweg 11 W\u00e4ngi Thurgau 9545",
    "addr:housenumber":"11",
    "addr:postcode":"9545",
    "addr:street":"Eschenmoosweg;Thurgau",
    "iso:country":"CH",
    "sg:address":"Eschenmoosweg 11",
    "sg:city":"W\u00e4ngi",
    "sg:orig_category":"Arztpraxen",
    "sg:phone":"+41 52 378 23 71",
    "sg:postcode":"9545",
    "sg:province":"Thurgau",
    "wof:name":"Dr.med.karl Frehner Arzt F.allgemeine Medizin Fmh",
    "wof:placetype":"venue"
},
  "geometry": {"coordinates":[8.959161,47.500202],"type":"Point"}
}