{
  "type": "Feature",
  "properties": {
    "iso:country":"CH",
    "sg:address":"Aeschengraben 26",
    "sg:city":"Basel",
    "sg:orig_category":"Sonstige pers\u00f6nliche Dienstleistungen",
    "sg:postcode":"4051",
    "sg:province":"Basel-Stadt",
    "wof:name":"Bws Bnp Paibas World Services Ag",
    "wof:placetype":"venue"
},
  "geometry": {"coordinates":[7.5929698944,47.5503311157],"type":"Point"}
}