{
  "type": "Feature",
  "properties": {
    "iso:country":"CH",
    "sg:address":"Z\u00fcrcherstrasse 143",
    "sg:city":"Basel",
    "sg:orig_category":"Alters U Pflegeheime Interessenvertretungen",
    "sg:phone":"+41 41 449 95 00",
    "sg:postcode":"4052",
    "sg:province":"Basel-Stadt",
    "wof:name":"Stiftung Betagtenzentrum D\u00f6sselen",
    "wof:placetype":"venue"
},
  "geometry": {"coordinates":[8.317884,47.132027],"type":"Point"}
}