{
  "type": "Feature",
  "properties": {
    "iso:country":"CH",
    "sg:address":"Felsenhofstrasse 14",
    "sg:city":"Hinwil",
    "sg:orig_category":"Fahrschulen, Flugschulen",
    "sg:phone":"+41 19372969",
    "sg:postcode":"8340",
    "sg:province":"Z\u00fcrich",
    "wof:name":"Hanspeter M\u00fcnger Autofahrschule",
    "wof:placetype":"venue"
},
  "geometry": {"coordinates":[8.8487358093,47.3011131287],"type":"Point"}
}