{
  "type": "Feature",
  "properties": {
    "iso:country":"CH",
    "sg:address":"Route Andr\u00e9 Piller 33a",
    "sg:city":"Givisiez",
    "sg:orig_category":"Architektur U Ingenieurb\u00fcros Architekturb\u00fcros",
    "sg:phone":"+41 26 466 73 63",
    "sg:postcode":"1762",
    "sg:province":"Fribourg",
    "wof:name":"Atelier 52 Sa",
    "wof:placetype":"venue"
},
  "geometry": {"coordinates":[7.117129,46.811794],"type":"Point"}
}