{
  "type": "Feature",
  "properties": {
    "iso:country":"CH",
    "sg:address":"Soodstrasse 44",
    "sg:city":"Adliswil",
    "sg:orig_category":"Non-Classified Establishments",
    "sg:postcode":"8134",
    "sg:province":"Z\u00fcrich",
    "wof:name":"Students Gmbh",
    "wof:placetype":"venue"
},
  "geometry": {"coordinates":[8.5207300186,47.3199310303],"type":"Point"}
}