{
  "type": "Feature",
  "properties": {
    "iso:country":"CH",
    "sg:address":"Route Sous-riette 29 1023 Crissier Case Postale",
    "sg:city":"Crissier",
    "sg:orig_category":"Grosshandel mit chemischen Erzeugnissen Herstellung von sonstigen Metallwaren",
    "sg:phone":"+41 21 631 41 11",
    "sg:postcode":"1023",
    "sg:province":"Vaud",
    "wof:name":"Busak + Shamban Sa",
    "wof:placetype":"venue"
},
  "geometry": {"coordinates":[6.5744318962,46.5536460876],"type":"Point"}
}