{
  "type": "Feature",
  "properties": {
    "addr:full":"Kreuzb\u00fchlstrasse 15 Z\u00fcrich Z\u00fcrich 8008",
    "addr:housenumber":"15",
    "addr:postcode":"8008",
    "addr:street":"Kreuzbuehlstrasse",
    "iso:country":"CH",
    "sg:address":"Kreuzb\u00fchlstrasse 15",
    "sg:city":"Z\u00fcrich",
    "sg:orig_category":"Advokaturb\u00fcros",
    "sg:phone":"+41 12518801",
    "sg:postcode":"8008",
    "sg:province":"Z\u00fcrich",
    "wof:name":"Dr.konrad H. Butz Advokaturb\u00fcro",
    "wof:placetype":"venue"
},
  "geometry": {"coordinates":[8.551668,47.365765],"type":"Point"}
}