{
  "type": "Feature",
  "properties": {
    "iso:country":"CH",
    "sg:address":"Rue Du Stand 33",
    "sg:city":"Gen\u00e8ve",
    "sg:orig_category":"Bauschreinerei Herstellung von M\u00f6beln verschiedener Art",
    "sg:phone":"+41 22 329 63 06",
    "sg:postcode":"1204",
    "sg:province":"Gen\u00e8ve",
    "wof:name":"Carlo Nespolo",
    "wof:placetype":"venue"
},
  "geometry": {"coordinates":[6.137958,46.203514],"type":"Point"}
}