{
  "type": "Feature",
  "properties": {
    "iso:country":"CH",
    "sg:address":"Luzernstrasse 84",
    "sg:city":"Huttwil",
    "sg:classifiers":[
        {
            "category":"Utilities",
            "subcategory":"Electric",
            "type":"Services"
        }
    ],
    "sg:phone":"+41 62 962 09 40",
    "sg:postcode":"4950",
    "sg:province":"Bern",
    "sg:tags":[
        "programmable",
        "controller",
        "software",
        "plc",
        "logic"
    ],
    "wof:name":"Aisoft",
    "wof:placetype":"venue"
},
  "geometry": {"coordinates":[7.8670830727,47.1167449951],"type":"Point"}
}