{
  "type": "Feature",
  "properties": {
    "iso:country":"CH",
    "sg:address":"Neutrottenstrasse 75 8207 Schaffhausen. Postfach",
    "sg:city":"Schaffhausen",
    "sg:orig_category":"Elektroinstallation Herstellung von Elektromotoren, Generatoren U Transformatoren",
    "sg:phone":"+41 52 640 19 19",
    "sg:postcode":"8207",
    "sg:province":"Schaffhausen",
    "wof:name":"Von Gunten Elektro Ag",
    "wof:placetype":"venue"
},
  "geometry": {"coordinates":[8.6564092636,47.7223091125],"type":"Point"}
}