{
  "type": "Feature",
  "properties": {
    "addr:full":"Trollstrasse 16 Postfach 276 Winterthur Z\u00fcrich 8402",
    "addr:housenumber":"16;276",
    "addr:postcode":"8402",
    "addr:street":"Trollstrasse;Postfach",
    "iso:country":"CH",
    "sg:address":"Trollstrasse 16 Postfach 276",
    "sg:city":"Winterthur",
    "sg:classifiers":[
        {
            "category":"Shopping",
            "subcategory":"Computers & Home Electronics",
            "type":"Retail Goods"
        }
    ],
    "sg:phone":"+41 32 926 72 74",
    "sg:postcode":"8402",
    "sg:province":"Z\u00fcrich",
    "sg:tags":[
        "electric",
        "electricity",
        "component",
        "equipment",
        "electrical",
        "electronic"
    ],
    "wof:name":"F Baillod Sa",
    "wof:placetype":"venue"
},
  "geometry": {"coordinates":[6.810464,47.094398],"type":"Point"}
}