{
  "type": "Feature",
  "properties": {
    "iso:country":"CH",
    "sg:address":"Chemin Du Vieux-pont 6",
    "sg:city":"Ch\u00eane-bougeries",
    "sg:orig_category":"Arztpraxen",
    "sg:phone":"+41 22 348 70 14",
    "sg:postcode":"1224",
    "sg:province":"Gen\u00e8ve",
    "wof:name":"Dr M\u00e9d. Jacques Arpin M\u00e9decin Sp\u00e9cialiste",
    "wof:placetype":"venue"
},
  "geometry": {"coordinates":[6.190756,46.195534],"type":"Point"}
}