{
  "type": "Feature",
  "properties": {
    "iso:country":"CH",
    "sg:address":"Place De La Gare 1",
    "sg:city":"Nyon",
    "sg:orig_category":"Drogerien",
    "sg:phone":"+41 22 361 32 92",
    "sg:postcode":"1260",
    "sg:province":"Vaud",
    "wof:name":"Roberto Leverone Droguerie Du Jura",
    "wof:placetype":"venue"
},
  "geometry": {"coordinates":[6.2359409332,46.3837890625],"type":"Point"}
}