{
  "type": "Feature",
  "properties": {
    "iso:country":"CH",
    "sg:address":"Via Campagna 6",
    "sg:city":"Giubiasco",
    "sg:orig_category":"Instandhaltung U Reparatur von Automobilen",
    "sg:postcode":"6512",
    "sg:province":"Ticino",
    "wof:name":"Di Martino Salvatore, Garage.",
    "wof:placetype":"venue"
},
  "geometry": {"coordinates":[8.8553771973,47.256187439],"type":"Point"}
}