{
  "type": "Feature",
  "properties": {
    "iso:country":"CH",
    "sg:address":"3920 Zermatt. Postfach 252",
    "sg:city":"Zermatt",
    "sg:classifiers":[
        {
            "category":"Travel",
            "subcategory":"Hotels & Motels",
            "type":"Entertainment"
        }
    ],
    "sg:phone":"+41 27 966 76 16",
    "sg:postcode":"3920",
    "sg:province":"Valais",
    "sg:tags":[
        "hotels",
        "mit",
        "restaurant"
    ],
    "wof:name":"Hotel Orion",
    "wof:placetype":"venue"
},
  "geometry": {"coordinates":[7.7484002113,46.024143219],"type":"Point"}
}