{
  "type": "Feature",
  "properties": {
    "iso:country":"CH",
    "sg:address":"3942",
    "sg:city":"Raron",
    "sg:orig_category":"Allgemeiner Hoch U Tiefbau",
    "sg:phone":"+41 27 932 38 19",
    "sg:postcode":"3942",
    "sg:province":"Valais",
    "wof:name":"Losinger Sion Sa Succursale De Niedergesteln",
    "wof:placetype":"venue"
},
  "geometry": {"coordinates":[7.800095,46.309719],"type":"Point"}
}