{
  "type": "Feature",
  "properties": {
    "iso:country":"CH",
    "sg:address":"Hauptplatz 6017 Ruswil. Postfach 71",
    "sg:city":"Ruswil",
    "sg:orig_category":"Reiseb\u00fcros",
    "sg:phone":"+41 41 495 26 26",
    "sg:postcode":"6017",
    "sg:province":"Luzern",
    "wof:name":"Reiseb\u00fcro Rottal Rottal Auto Ag",
    "wof:placetype":"venue"
},
  "geometry": {"coordinates":[8.1267251968,47.0840606689],"type":"Point"}
}