{
  "type": "Feature",
  "properties": {
    "iso:country":"CH",
    "sg:address":"Pfaffenrainstrasse 7",
    "sg:city":"Bottmingen",
    "sg:orig_category":"Handelsvermittlung U Grosshandel",
    "sg:phone":"+41 61 421 23 82",
    "sg:postcode":"4103",
    "sg:province":"Basel-Landschaft",
    "wof:name":"Sol\u00e8r Asset Management Ag",
    "wof:placetype":"venue"
},
  "geometry": {"coordinates":[7.575671196,47.5231552124],"type":"Point"}
}