{
  "type": "Feature",
  "properties": {
    "iso:country":"CH",
    "sg:address":"Birrfeldstrasse 12",
    "sg:city":"M\u00fclligen",
    "sg:orig_category":"Wirtschaftspr\u00fcfung, Steuerberatung U Treuhand",
    "sg:phone":"+41 56 225 27 27",
    "sg:postcode":"5243",
    "sg:province":"Aargau",
    "wof:name":"Ars Consulting Zurlinden P.",
    "wof:placetype":"venue"
},
  "geometry": {"coordinates":[8.2393426895,47.4561882019],"type":"Point"}
}