{
  "type": "Feature",
  "properties": {
    "iso:country":"CH",
    "sg:address":"Bahnhofstrasse 27",
    "sg:city":"Zug",
    "sg:orig_category":"Unclassifiable Establishments",
    "sg:postcode":"6300",
    "sg:province":"Zug",
    "wof:name":"Metacom Gmbh",
    "wof:placetype":"venue"
},
  "geometry": {"coordinates":[8.5156202316,47.1702880859],"type":"Point"}
}