{
  "type": "Feature",
  "properties": {
    "iso:country":"CH",
    "sg:address":"Rue Carlo-hemmerling 9",
    "sg:city":"Corseaux",
    "sg:orig_category":"Innendekorationsateliers",
    "sg:phone":"+41 21 921 89 67",
    "sg:postcode":"1802",
    "sg:province":"Vaud",
    "wof:name":"G\u00e9rard Corminboef Tapissier-d\u00e9corateur",
    "wof:placetype":"venue"
},
  "geometry": {"coordinates":[6.8422970772,46.471496582],"type":"Point"}
}