{
  "type": "Feature",
  "properties": {
    "iso:country":"CH",
    "sg:address":"Weststrasse 131 8408 Winterthur. Postfach",
    "sg:city":"Winterthur",
    "sg:orig_category":"Detektivb\u00fcros U \u00dcberwachung",
    "sg:postcode":"8408",
    "sg:province":"Z\u00fcrich",
    "wof:name":"Protector Sicherheits Und Wachdienst De Maio",
    "wof:placetype":"venue"
},
  "geometry": {"coordinates":[9.2506113052,47.4103240967],"type":"Point"}
}