{
  "type": "Feature",
  "properties": {
    "iso:country":"CH",
    "sg:address":"Friedmattstrasse 1",
    "sg:city":"Reiden",
    "sg:orig_category":"Maler U Glasergewerbe Malerei",
    "sg:phone":"+41 62 758 20 69",
    "sg:postcode":"6260",
    "sg:province":"Luzern",
    "wof:name":"Stefan Wey Malergesch\u00e4ft",
    "wof:placetype":"venue"
},
  "geometry": {"coordinates":[7.9689059258,47.2417144775],"type":"Point"}
}