{
  "type": "Feature",
  "properties": {
    "iso:country":"CH",
    "sg:address":"3186",
    "sg:city":"D\u00fcdingen",
    "sg:orig_category":"Detailhandel mit Waren verschiedener Art, Hauptrichtung Nahrungsmittel",
    "sg:phone":"+41 26 493 30 33",
    "sg:postcode":"3186",
    "sg:province":"Fribourg",
    "wof:name":"Coop Center Bahnhofzentrum",
    "wof:placetype":"venue"
},
  "geometry": {"coordinates":[7.1900749207,46.8504104614],"type":"Point"}
}