{
  "type": "Feature",
  "properties": {
    "iso:country":"CH",
    "sg:address":"Ahornweg 3 3012 Bern. Postfach",
    "sg:city":"Bern",
    "sg:orig_category":"Fachdetailhandel in Verkaufsr\u00e4umen",
    "sg:postcode":"3005",
    "sg:province":"Bern",
    "wof:name":"M. Brudermann Patienten- U Rekonvaleszenten-handarbeiten, Rheumaw\u00e4sche; Handel",
    "wof:placetype":"venue"
},
  "geometry": {"coordinates":[7.4351520538,46.9538383484],"type":"Point"}
}