{
  "type": "Feature",
  "properties": {
    "iso:country":"CH",
    "sg:address":"Neubr\u00fcckstrasse 166",
    "sg:city":"Bern",
    "sg:classifiers":[
        {
            "category":"Government",
            "subcategory":"Post Office",
            "type":"Public Place"
        }
    ],
    "sg:phone":"+41 31 302 38 42",
    "sg:postcode":"3012",
    "sg:province":"Bern",
    "sg:tags":[
        "caf\u00e9s",
        "tea-rooms"
    ],
    "wof:name":"Caf\u00e9 Park & Ride Neufeld",
    "wof:placetype":"venue"
},
  "geometry": {"coordinates":[7.4315829277,46.963508606],"type":"Point"}
}