{
  "type": "Feature",
  "properties": {
    "iso:country":"CH",
    "sg:address":"Chemin Grand-record 8 1030 Bussigny-lausanne Case Postale 75",
    "sg:city":"Bussigny-lausanne",
    "sg:orig_category":"Mechanische Werkst\u00e4tten",
    "sg:phone":"+41 21 701 09 38",
    "sg:postcode":"1030",
    "sg:province":"Vaud",
    "wof:name":"Electro M\u00e9cano Service Reynald Epitaux",
    "wof:placetype":"venue"
},
  "geometry": {"coordinates":[6.5517649651,46.5488891602],"type":"Point"}
}