{
  "type": "Feature",
  "properties": {
    "iso:country":"CH",
    "sg:address":"Hardturmstrasse 90",
    "sg:city":"Z\u00fcrich",
    "sg:orig_category":"Sonstiger Grosshandel",
    "sg:phone":"+41 12728566",
    "sg:postcode":"8005",
    "sg:province":"Z\u00fcrich",
    "wof:name":"Non Plus Ultra Gmbh",
    "wof:placetype":"venue"
},
  "geometry": {"coordinates":[8.5169315338,47.3924255371],"type":"Point"}
}