{
  "type": "Feature",
  "properties": {
    "iso:country":"CH",
    "sg:address":"Chenil Du Grand Blettay",
    "sg:city":"Fully",
    "sg:classifiers":[
        {
            "category":"Travel",
            "subcategory":"Hotels & Motels",
            "type":"Entertainment"
        }
    ],
    "sg:postcode":"1926",
    "sg:province":"Valais",
    "sg:tags":[
        "hotels",
        "mit",
        "restaurant"
    ],
    "wof:name":"Pension-elevage Du Grand Blettay S\u00e0rl",
    "wof:placetype":"venue"
},
  "geometry": {"coordinates":[7.119784832,46.1373138428],"type":"Point"}
}