{
  "type": "Feature",
  "properties": {
    "iso:country":"CH",
    "sg:address":"Diethelmstrasse 40",
    "sg:city":"F\u00fcrigen",
    "sg:orig_category":"Grosshandel mit Lederwaren U Reiseartikeln Herstellung von sonstigen chemischen Erzeugnissen",
    "sg:phone":"+41 41 260 41 70",
    "sg:postcode":"6363",
    "sg:province":"Nidwalden",
    "wof:name":"As-produkte Arthur Studach Chem.-techn.produkte Engros",
    "wof:placetype":"venue"
},
  "geometry": {"coordinates":[8.3518981934,46.9805831909],"type":"Point"}
}