{
  "type": "Feature",
  "properties": {
    "iso:country":"CH",
    "sg:address":"Mahrenstrasse 5",
    "sg:city":"Lostorf",
    "sg:orig_category":"Sonstiger spezialisierter Hoch U Tiefbau Strassenbau",
    "sg:phone":"+41 62 298 16 87",
    "sg:postcode":"4654",
    "sg:province":"Solothurn",
    "wof:name":"Paul Gerber Gmbh",
    "wof:placetype":"venue"
},
  "geometry": {"coordinates":[7.9460067749,47.3835716248],"type":"Point"}
}