{
  "type": "Feature",
  "properties": {
    "iso:country":"CH",
    "sg:address":"Rebgasse 23",
    "sg:city":"Binningen",
    "sg:orig_category":"Architektur U Ingenieurb\u00fcros",
    "sg:phone":"+41 61 421 46 70",
    "sg:postcode":"4102",
    "sg:province":"Basel-Landschaft",
    "wof:name":"M\u00fcller Rudolf",
    "wof:placetype":"venue"
},
  "geometry": {"coordinates":[7.568428,47.541119],"type":"Point"}
}