{
  "type": "Feature",
  "properties": {
    "iso:country":"CH",
    "sg:address":"Bahnhofstrasse 9",
    "sg:city":"Neuenkirch",
    "sg:orig_category":"Banken sonstige",
    "sg:phone":"+41 41 469 70 20",
    "sg:postcode":"6206",
    "sg:province":"Luzern",
    "wof:name":"Triba Partner Bank, Niederlassung Neuenkirch",
    "wof:placetype":"venue"
},
  "geometry": {"coordinates":[8.195508,47.116375],"type":"Point"}
}