{
  "type": "Feature",
  "properties": {
    "iso:country":"CH",
    "sg:address":"Rathausplatz 4 3000 Bern. Postfach",
    "sg:city":"Bern",
    "sg:orig_category":"Sonstiger Grosshandel",
    "sg:postcode":"3005",
    "sg:province":"Bern",
    "wof:name":"Pipes & More Gmbh",
    "wof:placetype":"venue"
},
  "geometry": {"coordinates":[7.45225811,46.9484214783],"type":"Point"}
}