{
  "type": "Feature",
  "properties": {
    "iso:country":"CH",
    "sg:address":"Route De Suisse 95bis",
    "sg:city":"Versoix",
    "sg:orig_category":"Saunas, Solarien, Fitnesszentren U \u00e4hnliches",
    "sg:postcode":"1290",
    "sg:province":"Gen\u00e8ve",
    "wof:name":"Sauna De Versoix, Stettler Ulrich.",
    "wof:placetype":"venue"
},
  "geometry": {"coordinates":[6.165640831,46.284614563],"type":"Point"}
}