{
  "type": "Feature",
  "properties": {
    "iso:country":"CH",
    "sg:address":"Parkterrasse 14/16",
    "sg:city":"Bern",
    "sg:orig_category":"Detailhandel mit Computern U Software Sonstige mit der Informatik verbundene T\u00e4tigkeiten",
    "sg:phone":"+41 32 320 17 00",
    "sg:postcode":"3012",
    "sg:province":"Bern",
    "wof:name":"Mtf Feusi Informatikschule Ag Hard- U. Softwareprodukte; Handel U. Dienstleistungen Usw",
    "wof:placetype":"venue"
},
  "geometry": {"coordinates":[7.4385,46.949863],"type":"Point"}
}