{
  "type": "Feature",
  "properties": {
    "iso:country":"CH",
    "sg:address":"Centrale Avenue",
    "sg:city":"Villars-sur-ollon",
    "sg:orig_category":"Unclassifiable Establishments",
    "sg:phone":"+41 26 927 18 70",
    "sg:postcode":"1884",
    "sg:province":"Vaud",
    "wof:name":"Si Les Epervi\u00e8res",
    "wof:placetype":"venue"
},
  "geometry": {"coordinates":[7.167386055,46.6153526306],"type":"Point"}
}