{
  "type": "Feature",
  "properties": {
    "iso:country":"CH",
    "sg:address":"Bergstrasse 5 7012 Felsberg. Postfach",
    "sg:city":"Felsberg",
    "sg:orig_category":"Unclassifiable Establishments",
    "sg:phone":"+41 81 252 35 86",
    "sg:postcode":"7012",
    "sg:province":"Graubunden",
    "wof:name":"Gartenbau Huber",
    "wof:placetype":"venue"
},
  "geometry": {"coordinates":[9.4799480438,46.8487281799],"type":"Point"}
}