{
  "type": "Feature",
  "properties": {
    "iso:country":"CH",
    "sg:address":"Ungarb\u00fchlstrasse 86 8200 Schaffhausen. Postfach",
    "sg:city":"Schaffhausen",
    "sg:orig_category":"Fotografisches Gewerbe U fotografische Laboratorien",
    "sg:postcode":"8202",
    "sg:province":"Schaffhausen",
    "wof:name":"Sonnenlicht Fotob\u00fcro Strehler Benjamin",
    "wof:placetype":"venue"
},
  "geometry": {"coordinates":[8.6434688568,47.7037086487],"type":"Point"}
}