{
  "type": "Feature",
  "properties": {
    "iso:country":"CH",
    "sg:address":"Els\u00e4sserstrasse 201 4056 Basel. Postfach 64",
    "sg:city":"Basel",
    "sg:orig_category":"Detailhandel mit Getr\u00e4nken Grosshandel mit Wein U Spirituosen",
    "sg:phone":"+41 62 212 10 62",
    "sg:postcode":"4013",
    "sg:province":"Basel-Stadt",
    "wof:name":"Hofer Charles Sa",
    "wof:placetype":"venue"
},
  "geometry": {"coordinates":[7.8636851311,47.3448562622],"type":"Point"}
}