{
  "type": "Feature",
  "properties": {
    "iso:country":"CH",
    "sg:address":"Via Stazione 66 6987 Caslano. Postfach Caselle Postale 139",
    "sg:city":"Caslano",
    "sg:orig_category":"Sonstige Aktivit\u00e4ten der nicht-\u00e4rztlichen Medizinalberufe",
    "sg:phone":"+41 91 606 12 75",
    "sg:postcode":"6987",
    "sg:province":"Ticino",
    "wof:name":"Therese Dellea Kinesiologia",
    "wof:placetype":"venue"
},
  "geometry": {"coordinates":[8.8775110245,45.9760437012],"type":"Point"}
}