{
  "type": "Feature",
  "properties": {
    "iso:country":"CH",
    "sg:address":"Immeuble Scandia",
    "sg:city":"Crans-sur-sierre",
    "sg:orig_category":"Verkehrs- and Tourismusb\u00fcros",
    "sg:phone":"+41 27 485 08 00",
    "sg:postcode":"3963",
    "sg:province":"Valais",
    "wof:name":"Office Du Tourisme",
    "wof:placetype":"venue"
},
  "geometry": {"coordinates":[7.4691519737,46.3059539795],"type":"Point"}
}