{
  "type": "Feature",
  "properties": {
    "iso:country":"CH",
    "sg:address":"Grundstrasse 12",
    "sg:city":"Rotkreuz",
    "sg:orig_category":"Geb\u00e4ude, Wohnungsreinigung",
    "sg:phone":"+41 41 790 26 28",
    "sg:postcode":"6343",
    "sg:province":"Zug",
    "wof:name":"B\u00f6sch H.",
    "wof:placetype":"venue"
},
  "geometry": {"coordinates":[8.4302759171,47.145690918],"type":"Point"}
}