{
  "type": "Feature",
  "properties": {
    "iso:country":"CH",
    "sg:address":"Rue De La Plaine 67",
    "sg:city":"Yverdon-les-bains",
    "sg:orig_category":"Diskotheken, Dancings, Night Clubs",
    "sg:phone":"+41 24 425 39 17",
    "sg:postcode":"1400",
    "sg:province":"Vaud",
    "wof:name":"Dancing Lido",
    "wof:placetype":"venue"
},
  "geometry": {"coordinates":[6.6468582153,46.7767601013],"type":"Point"}
}