{
  "type": "Feature",
  "properties": {
    "iso:country":"CH",
    "sg:address":"Oberstrasse 127",
    "sg:city":"St.gallen",
    "sg:orig_category":"Herstellung von Metallkonstruktionen Wirtschaftspr\u00fcfung, Steuerberatung U Treuhand",
    "sg:phone":"+41 61 811 15 50",
    "sg:postcode":"9000",
    "sg:province":"St. Gallen",
    "wof:name":"Holenstein & Co",
    "wof:placetype":"venue"
},
  "geometry": {"coordinates":[7.7233090401,47.5318832397],"type":"Point"}
}