{
  "type": "Feature",
  "properties": {
    "iso:country":"CH",
    "sg:address":"B\u00fcel 304",
    "sg:city":"Mittellunden",
    "sg:orig_category":"Herstellung von Hebezeugen U F\u00f6rdermitteln",
    "sg:phone":"+41 81 328 18 18",
    "sg:postcode":"7222",
    "sg:province":"Graubunden",
    "wof:name":"Wesa-montagen Wellenzohn & Savio",
    "wof:placetype":"venue"
},
  "geometry": {"coordinates":[9.7130346298,46.9441108704],"type":"Point"}
}