{
  "type": "Feature",
  "properties": {
    "iso:country":"CH",
    "sg:address":"Hintergasse 55",
    "sg:city":"Diessenhofen",
    "sg:orig_category":"Unclassifiable Establishments",
    "sg:phone":"+41 79 405 78 77",
    "sg:postcode":"8253",
    "sg:province":"Thurgau",
    "wof:name":"Rauber Baumpflege Gmbh",
    "wof:placetype":"venue"
},
  "geometry": {"coordinates":[8.7524785995,47.6896743774],"type":"Point"}
}