{
  "type": "Feature",
  "properties": {
    "iso:country":"CH",
    "sg:address":"Schmiedgasse 26",
    "sg:city":"Volketswil",
    "sg:orig_category":"Herstellung von Metallerzeugnissen ohne Maschinenbau",
    "sg:phone":"+41 19455416",
    "sg:postcode":"8604",
    "sg:province":"Z\u00fcrich",
    "wof:name":"Albert Schneider Formenbau",
    "wof:placetype":"venue"
},
  "geometry": {"coordinates":[8.6930236816,47.3871955872],"type":"Point"}
}