{
  "type": "Feature",
  "properties": {
    "iso:country":"CH",
    "sg:address":"Rathausgasse 3",
    "sg:city":"Aarau",
    "sg:orig_category":"Vermietung U Verpachtung von eigenen Immobilien",
    "sg:postcode":"5000",
    "sg:province":"Aargau",
    "wof:name":"Immobilien Rathausgasse 3 In Aarau Ag",
    "wof:placetype":"venue"
},
  "geometry": {"coordinates":[8.0434646606,47.3932113647],"type":"Point"}
}