{
  "type": "Feature",
  "properties": {
    "iso:country":"CH",
    "sg:address":"Schweizerhofstrasse 7",
    "sg:city":"Glarus",
    "sg:orig_category":"Detailhandel mit Waren verschiedener Art, Hauptrichtung Nahrungsmittel Grosshandel mit Nahrungsmitte",
    "sg:phone":"+41 55 640 72 32",
    "sg:postcode":"8750",
    "sg:province":"Glarus",
    "wof:name":"Reto Suter",
    "wof:placetype":"venue"
},
  "geometry": {"coordinates":[9.0705623627,47.040397644],"type":"Point"}
}