{
  "type": "Feature",
  "properties": {
    "iso:country":"CH",
    "sg:address":"Gandon Rue Adolphe- 18",
    "sg:city":"Courgenay",
    "sg:orig_category":"Non-Classified Establishments",
    "sg:postcode":"2950",
    "sg:province":"Jura",
    "wof:name":"Ak Holding Ag",
    "wof:placetype":"venue"
},
  "geometry": {"coordinates":[7.1263999939,47.4060211182],"type":"Point"}
}