{
  "type": "Feature",
  "properties": {
    "addr:full":"Avenue De France 12 Lausanne Vaud 1004",
    "addr:housenumber":"12",
    "addr:postcode":"1004",
    "addr:street":"Avenue De France",
    "iso:country":"CH",
    "sg:address":"Avenue De France 12",
    "sg:city":"Lausanne",
    "sg:orig_category":"Detailhandel mit Antiquit\u00e4ten Kunsthandel",
    "sg:phone":"+41 21 624 15 77",
    "sg:postcode":"1004",
    "sg:province":"Vaud",
    "wof:name":"Angela Morf Antiquit\u00e9s Chez Angela",
    "wof:placetype":"venue"
},
  "geometry": {"coordinates":[6.624038,46.524387],"type":"Point"}
}