{
  "type": "Feature",
  "properties": {
    "iso:country":"CH",
    "sg:address":"Motorenstrasse 14 8000 Z\u00fcrich. Postfach",
    "sg:city":"Z\u00fcrich",
    "sg:orig_category":"Sonstige mit der Informatik verbundene T\u00e4tigkeiten",
    "sg:postcode":"8001",
    "sg:province":"Z\u00fcrich",
    "wof:name":"Softwarelaboratorium M\u00e4hly Martin",
    "wof:placetype":"venue"
},
  "geometry": {"coordinates":[8.5286817551,47.3850326538],"type":"Point"}
}