{
  "type": "Feature",
  "properties": {
    "iso:country":"CH",
    "sg:address":"Achereggstrasse 5a",
    "sg:city":"Stansstad",
    "sg:orig_category":"Unclassifiable Establishments",
    "sg:postcode":"6362",
    "sg:province":"Nidwalden",
    "wof:name":"Sense4you Gmbh",
    "wof:placetype":"venue"
},
  "geometry": {"coordinates":[8.3360538483,46.9789428711],"type":"Point"}
}