{
  "type": "Feature",
  "properties": {
    "addr:full":"Amerbachstrasse 109 4057 Basel. Postfach Basel Basel-Stadt 4051",
    "addr:housenumber":"109",
    "addr:postcode":"4057;4051",
    "addr:street":"Amerbachstrasse;Postfach",
    "iso:country":"CH",
    "sg:address":"Amerbachstrasse 109 4057 Basel. Postfach",
    "sg:city":"Basel",
    "sg:orig_category":"Abbruch U Sprenggewerbe, Erdbewegungsarbeiten",
    "sg:phone":"+41 61 692 61 63",
    "sg:postcode":"4051",
    "sg:province":"Basel-Stadt",
    "wof:name":"Wolf & B\u00fcrgin, Inh. H. Wolf Aushub, Abbruch U. Warentransporte",
    "wof:placetype":"venue"
},
  "geometry": {"coordinates":[7.5975,47.569515],"type":"Point"}
}