{
  "type": "Feature",
  "properties": {
    "iso:country":"CH",
    "sg:address":"Dorfplatz 4",
    "sg:city":"Cham",
    "sg:orig_category":"Pensionskassen",
    "sg:phone":"+41 41 785 68 68",
    "sg:postcode":"6330",
    "sg:province":"Zug",
    "wof:name":"Personalf\u00fcrsorgestiftung Ims Ag",
    "wof:placetype":"venue"
},
  "geometry": {"coordinates":[8.4592695236,47.1807556152],"type":"Point"}
}