{
  "type": "Feature",
  "properties": {
    "iso:country":"CH",
    "sg:address":"Jonch\u00e8res 44",
    "sg:city":"St-imier",
    "sg:orig_category":"Sonstiger Fachdetailhandel mit Nahrungsmitteln, Getr\u00e4nken U Tabak in Verkaufsr\u00e4umen",
    "sg:phone":"+41 39412111",
    "sg:postcode":"2610",
    "sg:province":"Bern",
    "wof:name":"Laiterie K\u00e4mpf Florian",
    "wof:placetype":"venue"
},
  "geometry": {"coordinates":[6.9958810806,47.1509132385],"type":"Point"}
}