{
  "type": "Feature",
  "properties": {
    "iso:country":"CH",
    "sg:address":"Sandgrube 2",
    "sg:city":"Appenzell",
    "sg:orig_category":"Herstellung von \u00d6fen U Brennern",
    "sg:postcode":"9050",
    "sg:province":"Appenzell Innerhoden",
    "wof:name":"Guldener Ofen Und Chemin\u00e9ebau Gmbh",
    "wof:placetype":"venue"
},
  "geometry": {"coordinates":[8.7314949036,47.2748985291],"type":"Point"}
}