{
  "type": "Feature",
  "properties": {
    "iso:country":"CH",
    "sg:address":"Rheinklingen",
    "sg:city":"Kaltenbach",
    "sg:orig_category":"Primarschulen",
    "sg:phone":"+41 52 741 18 95",
    "sg:postcode":"8259",
    "sg:province":"Thurgau",
    "wof:name":"Primarschule",
    "wof:placetype":"venue"
},
  "geometry": {"coordinates":[8.8517379761,47.6583518982],"type":"Point"}
}