{
  "type": "Feature",
  "properties": {
    "iso:country":"CH",
    "sg:address":"Dornacherstrasse 192 4053 Basel. Postfach",
    "sg:city":"Basel",
    "sg:orig_category":"Herstellung von Pumpen U Kompressoren",
    "sg:phone":"+41 61 335 35 35",
    "sg:postcode":"4053",
    "sg:province":"Basel-Stadt",
    "wof:name":"Greenfield Ag Hochdruck-kompressoren, Systeme; Entw., Konstr., Herst., Vertrieb",
    "wof:placetype":"venue"
},
  "geometry": {"coordinates":[7.5926961899,47.5413360596],"type":"Point"}
}