{
  "type": "Feature",
  "properties": {
    "iso:country":"CH",
    "sg:address":"Bernstrasse 113",
    "sg:city":"Rothrist",
    "sg:orig_category":"Detailhandel mit Bekleidung",
    "sg:phone":"+41 62 794 12 44",
    "sg:postcode":"4852",
    "sg:province":"Aargau",
    "wof:name":"Max B\u00e4r Textilgesch\u00e4ft",
    "wof:placetype":"venue"
},
  "geometry": {"coordinates":[7.890526,47.305389],"type":"Point"}
}