{
  "type": "Feature",
  "properties": {
    "iso:country":"CH",
    "sg:address":"Marktgasse 20",
    "sg:city":"Sumiswald",
    "sg:orig_category":"Selbst\u00e4ndige bildende K\u00fcnstler",
    "sg:phone":"+41 71 911 04 57",
    "sg:postcode":"3454",
    "sg:province":"Bern",
    "wof:name":"Rudolf Gruber Holzbildhauer",
    "wof:placetype":"venue"
},
  "geometry": {"coordinates":[9.0481052399,47.4643821716],"type":"Point"}
}