{
  "type": "Feature",
  "properties": {
    "iso:country":"CH",
    "sg:address":"Hauptstr. 403 Pf 61",
    "sg:city":"Rohrbach",
    "sg:classifiers":[
        {
            "category":"Home & Garden",
            "subcategory":"Furniture",
            "type":"Retail Goods"
        }
    ],
    "sg:phone":"+41 62 965 24 24",
    "sg:postcode":"4938",
    "sg:province":"Bern",
    "sg:tags":[
        "wood"
    ],
    "wof:name":"Lanz Ag Furnier U S\u00c4gewerke",
    "wof:placetype":"venue"
},
  "geometry": {"coordinates":[7.8123750687,47.1359062195],"type":"Point"}
}