{
  "type": "Feature",
  "properties": {
    "iso:country":"CH",
    "sg:address":"Neumatt 12",
    "sg:city":"Laufen",
    "sg:orig_category":"Mechanische Werkst\u00e4tten Schlossereien",
    "sg:phone":"+41 61 763 15 20",
    "sg:postcode":"4242",
    "sg:province":"Basel-Landschaft",
    "wof:name":"Erwin B\u00e4rtschi Moweb Mobile Werkstatt",
    "wof:placetype":"venue"
},
  "geometry": {"coordinates":[7.5109820366,47.4238319397],"type":"Point"}
}