{
  "type": "Feature",
  "properties": {
    "iso:country":"CH",
    "sg:address":"L\u00f6wenweg 17",
    "sg:city":"Obfelden",
    "sg:orig_category":"Fachdetailhandel in Verkaufsr\u00e4umen",
    "sg:phone":"+41 31473768",
    "sg:postcode":"8912",
    "sg:province":"Z\u00fcrich",
    "wof:name":"Mader W. Registrierkassen",
    "wof:placetype":"venue"
},
  "geometry": {"coordinates":[7.2401781082,46.9093856812],"type":"Point"}
}