{
  "type": "Feature",
  "properties": {
    "iso:country":"CH",
    "sg:address":"R\u00fcckimattweg 3",
    "sg:city":"Fraubrunnen",
    "sg:orig_category":"Non-Classified Establishments",
    "sg:postcode":"3312",
    "sg:province":"Bern",
    "wof:name":"Zdravko Valentino Lukacic Edv Dienstleitungen",
    "wof:placetype":"venue"
},
  "geometry": {"coordinates":[7.5248022079,47.0864219666],"type":"Point"}
}