{
  "type": "Feature",
  "properties": {
    "iso:country":"CH",
    "sg:address":"Achilles Bischoff-strasse 2",
    "sg:city":"Basel",
    "sg:orig_category":"Non-Classified Establishments",
    "sg:postcode":"4053",
    "sg:province":"Basel-Stadt",
    "wof:name":"Quartierladen 2002, K. Pehlivan",
    "wof:placetype":"venue"
},
  "geometry": {"coordinates":[7.5938510895,47.5402030945],"type":"Point"}
}