{
  "type": "Feature",
  "properties": {
    "iso:country":"CH",
    "sg:address":"Moosstrasse 14",
    "sg:city":"Cham",
    "sg:orig_category":"Kinderkrippen U horte",
    "sg:phone":"+41 41 780 85 44",
    "sg:postcode":"6330",
    "sg:province":"Zug",
    "wof:name":"Kinderspielgruppe Chasperli",
    "wof:placetype":"venue"
},
  "geometry": {"coordinates":[8.4668636322,47.1853637695],"type":"Point"}
}