{
  "type": "Feature",
  "properties": {
    "iso:country":"CH",
    "sg:address":"Armes Place D' 4",
    "sg:city":"Cully",
    "sg:orig_category":"Betrieb U technische Hilfsdienste des Kultur U Unterhaltungswesens",
    "sg:postcode":"1096",
    "sg:province":"Vaud",
    "wof:name":"Association Culture Jazz",
    "wof:placetype":"venue"
},
  "geometry": {"coordinates":[6.730992,46.487686],"type":"Point"}
}