{
  "type": "Feature",
  "properties": {
    "iso:country":"CH",
    "sg:address":"Residenza Tiglio 17",
    "sg:city":"Pambio-noranco",
    "sg:orig_category":"Non-Classified Establishments",
    "sg:postcode":"6915",
    "sg:province":"Ticino",
    "wof:name":"Dama-arredamenti Di Candida Mammoliti",
    "wof:placetype":"venue"
},
  "geometry": {"coordinates":[8.9336853027,45.9883117676],"type":"Point"}
}