{
  "type": "Feature",
  "properties": {
    "iso:country":"CH",
    "sg:address":"Zugerstrasse 17",
    "sg:city":"Cham",
    "sg:orig_category":"Unternehmensberatung",
    "sg:phone":"+41 41 780 85 38",
    "sg:postcode":"6330",
    "sg:province":"Zug",
    "wof:name":"Karisch E., Betriebswirtschaftliche Beratung Und Organisation",
    "wof:placetype":"venue"
},
  "geometry": {"coordinates":[8.4618453979,47.1817092896],"type":"Point"}
}