{
  "type": "Feature",
  "properties": {
    "iso:country":"CH",
    "sg:address":"5612 Villmergen. Postfach 41",
    "sg:city":"Villmergen",
    "sg:orig_category":"Sportvereine Ballsport Tennis",
    "sg:postcode":"5612",
    "sg:province":"Aargau",
    "wof:name":"Tennisclub Vira Gambarogno",
    "wof:placetype":"venue"
},
  "geometry": {"coordinates":[8.8414697647,46.1437950134],"type":"Point"}
}