{
  "type": "Feature",
  "properties": {
    "iso:country":"CH",
    "sg:address":"Rue St-l\u00e9ger 8",
    "sg:city":"Gen\u00e8ve",
    "sg:orig_category":"Zahnarztpraxen",
    "sg:phone":"+41 22 310 50 68",
    "sg:postcode":"1205",
    "sg:province":"Gen\u00e8ve",
    "wof:name":"Dr M\u00e9d.dent. Valsangiacomo M\u00e9decin-dentiste",
    "wof:placetype":"venue"
},
  "geometry": {"coordinates":[6.1462478638,46.19764328],"type":"Point"}
}