{
  "type": "Feature",
  "properties": {
    "iso:country":"CH",
    "sg:address":"Primore Via 11",
    "sg:city":"Losone",
    "sg:orig_category":"Herstellung von Speiseeis U Sorbets",
    "sg:postcode":"6616",
    "sg:province":"Ticino",
    "wof:name":"Ti-gel Sagl",
    "wof:placetype":"venue"
},
  "geometry": {"coordinates":[8.7642450333,46.1679458618],"type":"Point"}
}