{
  "type": "Feature",
  "properties": {
    "iso:country":"CH",
    "sg:address":"Gravelone 50b",
    "sg:city":"Sion",
    "sg:orig_category":"Unternehmensberatung",
    "sg:postcode":"1950",
    "sg:province":"Valais",
    "wof:name":"Les Rives Lointaines Sa",
    "wof:placetype":"venue"
},
  "geometry": {"coordinates":[7.3526940346,46.235080719],"type":"Point"}
}