{
  "type": "Feature",
  "properties": {
    "iso:country":"CH",
    "sg:address":"Chemin Du Calvaire 1",
    "sg:city":"Lausanne",
    "sg:orig_category":"Grosshandel mit Baumaschinen Herstellung von Bergwerks U Baumaschinen",
    "sg:phone":"+41 79 312 89 18",
    "sg:postcode":"1005",
    "sg:province":"Vaud",
    "wof:name":"Bamaco Sa",
    "wof:placetype":"venue"
},
  "geometry": {"coordinates":[6.6380748749,46.5255241394],"type":"Point"}
}