{
  "type": "Feature",
  "properties": {
    "iso:country":"CH",
    "sg:address":"Waldstrasse 10",
    "sg:city":"Hubersdorf",
    "sg:orig_category":"Grosshandel mit elektrischen Haushaltsger\u00e4ten",
    "sg:phone":"+41 32 637 01 65",
    "sg:postcode":"4535",
    "sg:province":"Solothurn",
    "wof:name":"Sycatec Gmbh Kassensysteme F.gastronomie",
    "wof:placetype":"venue"
},
  "geometry": {"coordinates":[7.5854868889,47.2407035828],"type":"Point"}
}