{
  "type": "Feature",
  "properties": {
    "iso:country":"CH",
    "sg:address":"Under Brugg 13",
    "sg:city":"Berom\u00fcnster",
    "sg:orig_category":"Sanit\u00e4r, Heizungs U L\u00fcftungsinstallation Sanit\u00e4rinstallation",
    "sg:phone":"+41 41 930 15 25",
    "sg:postcode":"6215",
    "sg:province":"Luzern",
    "wof:name":"Wey Sanit\u00e4r/heizungs Ag",
    "wof:placetype":"venue"
},
  "geometry": {"coordinates":[8.1939268112,47.206413269],"type":"Point"}
}