{
  "type": "Feature",
  "properties": {
    "iso:country":"CH",
    "sg:address":"1892",
    "sg:city":"Lavey-village",
    "sg:orig_category":"Erschliessung von Grundst\u00fccken",
    "sg:postcode":"1892",
    "sg:province":"Vaud",
    "wof:name":"Soci\u00e9t\u00e9 Coop\u00e9rative Le Pacot Lavey-village",
    "wof:placetype":"venue"
},
  "geometry": {"coordinates":[7.017250061,46.219909668],"type":"Point"}
}