{
  "type": "Feature",
  "properties": {
    "iso:country":"CH",
    "sg:address":"Neugasse 1",
    "sg:city":"Zug",
    "sg:orig_category":"Effektenvermittlung Broker",
    "sg:phone":"+41 55 415 99 77",
    "sg:postcode":"6300",
    "sg:province":"Zug",
    "wof:name":"Dynamic Group Ltd",
    "wof:placetype":"venue"
},
  "geometry": {"coordinates":[8.7900953293,47.2021484375],"type":"Point"}
}