{
  "type": "Feature",
  "properties": {
    "iso:country":"CH",
    "sg:address":"Auring 19",
    "sg:city":"Vaduz",
    "sg:orig_category":"Rechtsberatung Verwaltung von Immobilien",
    "sg:phone":"+41 19701355",
    "sg:postcode":"9490",
    "wof:name":"Dieter Geiser Rechtsberatung & Treuhand",
    "wof:placetype":"venue"
},
  "geometry": {"coordinates":[8.7984800339,47.3245201111],"type":"Point"}
}