{
  "type": "Feature",
  "properties": {
    "iso:country":"CH",
    "sg:address":"Gewerbestrasse 11",
    "sg:city":"Cham",
    "sg:classifiers":[
        {
            "category":"Retail",
            "subcategory":"Repair Shop",
            "type":"Services"
        }
    ],
    "sg:phone":"+41 41 749 40 90",
    "sg:postcode":"6330",
    "sg:province":"Zug",
    "sg:tags":[
        "duct",
        "ducts",
        "ventilation",
        "air conditioning"
    ],
    "wof:name":"Air-on Ag",
    "wof:placetype":"venue"
},
  "geometry": {"coordinates":[8.472043,47.188694],"type":"Point"}
}