{
  "type": "Feature",
  "properties": {
    "addr:full":"Bahnhofstrasse 5 3629 Kiesen. Postfach Kiesen Bern 3629",
    "addr:housenumber":"5",
    "addr:postcode":"3629 kiesen. postfach;3629",
    "addr:street":"Bahnhofstrasse",
    "iso:country":"CH",
    "sg:address":"Bahnhofstrasse 5 3629 Kiesen. Postfach",
    "sg:city":"Kiesen",
    "sg:orig_category":"Architektur U Ingenieurb\u00fcros Innenarchitekturb\u00fcros",
    "sg:phone":"+41 31 781 00 01",
    "sg:postcode":"3629",
    "sg:province":"Bern",
    "wof:name":"Wehrli Edgar Innenarchitektur Und Design Ag",
    "wof:placetype":"venue"
},
  "geometry": {"coordinates":[7.586005,46.819332],"type":"Point"}
}