{
  "type": "Feature",
  "properties": {
    "iso:country":"CH",
    "sg:address":"Galeries St-laurent",
    "sg:city":"Saillon",
    "sg:orig_category":"Detailhandel mit Fleisch U Fleischwaren Detailhandel mit Waren verschiedener Art, Hauptrichtung Nahr",
    "sg:phone":"+41 27 744 41 51",
    "sg:postcode":"1913",
    "sg:province":"Valais",
    "wof:name":"Boucherie Souvel Sa",
    "wof:placetype":"venue"
},
  "geometry": {"coordinates":[7.1877098083,46.1712989807],"type":"Point"}
}