{
  "type": "Feature",
  "properties": {
    "iso:country":"CH",
    "sg:address":"Hauptstrasse 38",
    "sg:city":"Niederg\u00f6sgen",
    "sg:orig_category":"Detailhandel mit fotografischen Artikeln",
    "sg:phone":"+41 71 911 33 37",
    "sg:postcode":"5013",
    "sg:province":"Solothurn",
    "wof:name":"Hans Mayer Ag Foto Video",
    "wof:placetype":"venue"
},
  "geometry": {"coordinates":[9.0423936844,47.4646148682],"type":"Point"}
}