{
  "type": "Feature",
  "properties": {
    "iso:country":"CH",
    "sg:address":"Bahnhofplatz 5",
    "sg:city":"Winterthur",
    "sg:orig_category":"Zahntechnische Laboratorien",
    "sg:phone":"+41 71 385 93 13",
    "sg:postcode":"8400",
    "sg:province":"Z\u00fcrich",
    "wof:name":"Rolf Held Zahntechnisches Labor",
    "wof:placetype":"venue"
},
  "geometry": {"coordinates":[9.2548408508,47.4173278809],"type":"Point"}
}