{
  "type": "Feature",
  "properties": {
    "iso:country":"CH",
    "sg:address":"Hohstrasse 4 8302 Kloten. Postfach",
    "sg:city":"Kloten",
    "sg:orig_category":"Grosshandel mit Geschenkartikeln U Souvenirs Sonstiger Grosshandel",
    "sg:phone":"+41 18583282",
    "sg:postcode":"8302",
    "sg:province":"Z\u00fcrich",
    "wof:name":"Novidarte Special Promotions Gmbh",
    "wof:placetype":"venue"
},
  "geometry": {"coordinates":[8.4164104462,47.5659255981],"type":"Point"}
}