{
  "type": "Feature",
  "properties": {
    "iso:country":"CH",
    "sg:address":"Vicolo Nassetta 2",
    "sg:city":"Lugano",
    "sg:orig_category":"Vermietung U Verpachtung von eigenen Immobilien",
    "sg:postcode":"6900",
    "sg:province":"Ticino",
    "wof:name":"Herzog Rudolf",
    "wof:placetype":"venue"
},
  "geometry": {"coordinates":[9.3903656006,47.4357185364],"type":"Point"}
}