{
  "type": "Feature",
  "properties": {
    "iso:country":"CH",
    "sg:address":"Oeschstrasse 33",
    "sg:city":"Halten",
    "sg:orig_category":"Verlegen von Fliesen U Platten",
    "sg:phone":"+41 79 406 01 73",
    "sg:postcode":"4566",
    "sg:province":"Solothurn",
    "wof:name":"Beat Stampfli Keram.wand-& Bodenbel\u00e4ge",
    "wof:placetype":"venue"
},
  "geometry": {"coordinates":[7.6030302048,47.1673469543],"type":"Point"}
}