{
  "type": "Feature",
  "properties": {
    "iso:country":"CH",
    "sg:address":"Bundkofen 508",
    "sg:city":"Sch\u00fcpfen",
    "sg:orig_category":"RESTAURANTS: TEA-ROOMS",
    "sg:phone":"+41 31 879 01 61",
    "sg:postcode":"3054",
    "sg:province":"Bern",
    "wof:name":"Restaurant Br\u00fccke",
    "wof:placetype":"venue"
},
  "geometry": {"coordinates":[7.3659801483,47.0456123352],"type":"Point"}
}