{
  "type": "Feature",
  "properties": {
    "iso:country":"CH",
    "sg:address":"Badstrasse 39",
    "sg:city":"Dietikon",
    "sg:orig_category":"Sportvereine Behindertensport",
    "sg:phone":"+41 17409563",
    "sg:postcode":"8953",
    "sg:province":"Z\u00fcrich",
    "wof:name":"Svbs Amt & Limmattal",
    "wof:placetype":"venue"
},
  "geometry": {"coordinates":[8.3897752762,47.4050292969],"type":"Point"}
}