{
  "type": "Feature",
  "properties": {
    "addr:full":"Langackerstrasse 126 Herrliberg Z\u00fcrich 8704",
    "addr:housenumber":"126",
    "addr:postcode":"8704",
    "addr:street":"Langackerstrasse",
    "iso:country":"CH",
    "sg:address":"Langackerstrasse 126",
    "sg:city":"Herrliberg",
    "sg:orig_category":"Detailhandel mit Blumen U Pflanzen",
    "sg:phone":"+41 19152776",
    "sg:postcode":"8704",
    "sg:province":"Z\u00fcrich",
    "wof:name":"Heidi's Efeuh\u00fcsli Kreatives Mit Blumen",
    "wof:placetype":"venue"
},
  "geometry": {"coordinates":[8.616421,47.290607],"type":"Point"}
}