{
  "type": "Feature",
  "properties": {
    "iso:country":"CH",
    "sg:address":"Hauptstrasse 19 3186 D\u00fcdingen. Postfach",
    "sg:city":"D\u00fcdingen",
    "sg:orig_category":"Detailhandel mit Brot, Back U S\u00fcsswaren",
    "sg:phone":"+41 26 492 03 08",
    "sg:postcode":"3186",
    "sg:province":"Fribourg",
    "wof:name":"Sturny Daniel B\u00e4ckerei, Tea-room",
    "wof:placetype":"venue"
},
  "geometry": {"coordinates":[7.190266,46.847885],"type":"Point"}
}