{
  "type": "Feature",
  "properties": {
    "iso:country":"CH",
    "sg:address":"W\u00e4gitalstrasse 35",
    "sg:city":"Vorderthal",
    "sg:orig_category":"Strassenbau",
    "sg:phone":"+41 55 446 12 49",
    "sg:postcode":"8857",
    "sg:province":"Schwyz",
    "wof:name":"Arnold Schnyder Tiefbau",
    "wof:placetype":"venue"
},
  "geometry": {"coordinates":[8.8955564499,47.1264381409],"type":"Point"}
}