{
  "type": "Feature",
  "properties": {
    "iso:country":"CH",
    "sg:address":"3616",
    "sg:city":"Schwarzenegg",
    "sg:orig_category":"Institutionen f\u00fcr Behinderte Wohnheime f\u00fcr Kinder U Jugendliche",
    "sg:phone":"+41 79 208 34 01",
    "sg:postcode":"3616",
    "sg:province":"Bern",
    "wof:name":"Wohnheim H\u00f6chmatt",
    "wof:placetype":"venue"
},
  "geometry": {"coordinates":[7.7183098793,46.7949790955],"type":"Point"}
}