{
  "type": "Feature",
  "properties": {
    "iso:country":"CH",
    "sg:address":"F\u00f6hneneichstrasse 8",
    "sg:city":"Brunnen",
    "sg:orig_category":"Physiotherapie",
    "sg:phone":"+41 41 820 52 62",
    "sg:postcode":"6440",
    "sg:province":"Schwyz",
    "wof:name":"Raoul Schepens Physiotherapie & Akupunktur",
    "wof:placetype":"venue"
},
  "geometry": {"coordinates":[8.6050767899,46.9968414307],"type":"Point"}
}