{
  "type": "Feature",
  "properties": {
    "iso:country":"CH",
    "sg:address":"Chropfacher 4",
    "sg:city":"Schwerzenbach",
    "sg:orig_category":"Grosshandel mit B\u00fcromaschinen Grosshandel mit Datenverarbeitungsger\u00e4ten",
    "sg:phone":"+41 56 441 71 76",
    "sg:postcode":"8603",
    "sg:province":"Z\u00fcrich",
    "wof:name":"Humm Computer Engineering Ag",
    "wof:placetype":"venue"
},
  "geometry": {"coordinates":[8.1847200394,47.4678344727],"type":"Point"}
}