{
  "type": "Feature",
  "properties": {
    "iso:country":"CH",
    "sg:address":"Bahnhofstrasse 1",
    "sg:city":"Wattwil",
    "sg:orig_category":"Elektrizit\u00e4tsversorgung Wasserversorgung",
    "sg:phone":"+41 71 988 19 33",
    "sg:postcode":"9630",
    "sg:province":"St. Gallen",
    "wof:name":"Dorfkorporation Wasser & Elektrizit\u00e4t",
    "wof:placetype":"venue"
},
  "geometry": {"coordinates":[9.0862951279,47.3014984131],"type":"Point"}
}