{
  "type": "Feature",
  "properties": {
    "iso:country":"CH",
    "sg:address":"Industriestrasse 17 5507 Mellingen. Postfach",
    "sg:city":"Mellingen",
    "sg:orig_category":"Grosshandel mit elektrischen Haushaltsger\u00e4ten, Radio U Fernsehger\u00e4ten Herstellung von sonstigen elek",
    "sg:phone":"+41 56 481 81 41",
    "sg:postcode":"5507",
    "sg:province":"Aargau",
    "wof:name":"M. Sch\u00f6nenberger Ag",
    "wof:placetype":"venue"
},
  "geometry": {"coordinates":[8.2761802673,47.4104690552],"type":"Point"}
}