{
  "type": "Feature",
  "properties": {
    "iso:country":"CH",
    "sg:address":"Route Des Plaines-du-loup 78",
    "sg:city":"Lausanne",
    "sg:classifiers":[
        {
            "category":"Restaurant",
            "type":"Food & Drink"
        }
    ],
    "sg:phone":"+41 21 646 39 26",
    "sg:postcode":"1018",
    "sg:province":"Vaud",
    "wof:name":"Chalet De La Bl\u00e9cherette Caf\u00e9-restaurant",
    "wof:placetype":"venue"
},
  "geometry": {"coordinates":[6.6204681396,46.5410003662],"type":"Point"}
}