{
  "type": "Feature",
  "properties": {
    "iso:country":"CH",
    "sg:address":"Ahornweg 4",
    "sg:city":"Niederlenz",
    "sg:orig_category":"Unternehmensberatung",
    "sg:phone":"+41 62 892 27 00",
    "sg:postcode":"5702",
    "sg:province":"Aargau",
    "wof:name":"Paroste Gmbh",
    "wof:placetype":"venue"
},
  "geometry": {"coordinates":[8.1814222336,47.3984642029],"type":"Point"}
}