{
  "type": "Feature",
  "properties": {
    "addr:full":"Rathausplatz 1 Sch\u00e4nis St. Gallen 8718",
    "addr:housenumber":"1;st.",
    "addr:postcode":"8718",
    "addr:street":"Rathausplatz",
    "iso:country":"CH",
    "sg:address":"Rathausplatz 1",
    "sg:city":"Sch\u00e4nis",
    "sg:orig_category":"Aktivit\u00e4ten der Krankenschwestern U Hebammen, Hauspflege",
    "sg:phone":"+41 55 615 16 12",
    "sg:postcode":"8718",
    "sg:province":"St. Gallen",
    "wof:name":"Spitex-dienste Sch\u00e4nis",
    "wof:placetype":"venue"
},
  "geometry": {"coordinates":[9.045762,47.159779],"type":"Point"}
}