{
  "type": "Feature",
  "properties": {
    "iso:country":"CH",
    "sg:address":"Nufenenstrasse",
    "sg:city":"Ulrichen",
    "sg:orig_category":"Instandhaltung U Reparatur von Automobilen Tankstellen",
    "sg:phone":"+41 27 973 11 26",
    "sg:postcode":"3988",
    "sg:province":"Valais",
    "wof:name":"Garage Nufenen, Walther Stefan",
    "wof:placetype":"venue"
},
  "geometry": {"coordinates":[8.3201341629,46.501449585],"type":"Point"}
}