{
  "type": "Feature",
  "properties": {
    "iso:country":"CH",
    "sg:address":"Bienenstrasse 1",
    "sg:city":"Z\u00fcrich",
    "sg:orig_category":"Sonstige pers\u00f6nliche Dienstleistungen",
    "sg:postcode":"8004",
    "sg:province":"Z\u00fcrich",
    "wof:name":"First Business Service Gmbh",
    "wof:placetype":"venue"
},
  "geometry": {"coordinates":[8.5077934265,47.3807983398],"type":"Point"}
}