{
  "type": "Feature",
  "properties": {
    "iso:country":"CH",
    "sg:address":"Amthausplatz 1 4500 Solothurn. Postfach",
    "sg:city":"Solothurn",
    "sg:classifiers":[
        {
            "category":"Education",
            "subcategory":"Library",
            "type":"Public Place"
        }
    ],
    "sg:postcode":"4502",
    "sg:province":"Solothurn",
    "sg:tags":[
        "u",
        "bibliotheken",
        "archive"
    ],
    "wof:name":"Bibliothek Des Obergerichts",
    "wof:placetype":"venue"
},
  "geometry": {"coordinates":[7.534026,47.208229],"type":"Point"}
}