{
  "type": "Feature",
  "properties": {
    "iso:country":"CH",
    "sg:address":"Derri\u00e8re-les-remparts 5",
    "sg:city":"Fribourg",
    "sg:orig_category":"RESTAURANTS: TEA-ROOMS",
    "sg:postcode":"1700",
    "sg:province":"Fribourg",
    "wof:name":"Roulin Michel.",
    "wof:placetype":"venue"
},
  "geometry": {"coordinates":[7.1565990448,46.8087081909],"type":"Point"}
}