{
  "type": "Feature",
  "properties": {
    "addr:full":"R\u00f6telbachstrasse 23 4702 Oensingen. Postfach Oensingen Solothurn 4702",
    "addr:housenumber":"23",
    "addr:postcode":"4702 oensingen. postfach;4702",
    "addr:street":"Roetelbachstrasse",
    "iso:country":"CH",
    "sg:address":"R\u00f6telbachstrasse 23 4702 Oensingen. Postfach",
    "sg:city":"Oensingen",
    "sg:orig_category":"Bauschreinerei Zimmerei, Dachdeckerei, Bauspenglerei U Abdichtung",
    "sg:phone":"+41 26 418 21 23",
    "sg:postcode":"4702",
    "sg:province":"Solothurn",
    "wof:name":"Kanis & Nicole Br\u00fclhart Zimmerei-schreinerei",
    "wof:placetype":"venue"
},
  "geometry": {"coordinates":[7.233874,46.732281],"type":"Point"}
}