{
  "type": "Feature",
  "properties": {
    "iso:country":"CH",
    "sg:address":"Avenue Nestl\u00e9 39",
    "sg:city":"Montreux",
    "sg:classifiers":[
        {
            "category":"Government",
            "subcategory":"Post Office",
            "type":"Public Place"
        }
    ],
    "sg:phone":"+41 21 963 00 62",
    "sg:postcode":"1820",
    "sg:province":"Vaud",
    "sg:tags":[
        "caf\u00e9s",
        "tea-rooms"
    ],
    "wof:name":"Caf\u00e9 Baccara",
    "wof:placetype":"venue"
},
  "geometry": {"coordinates":[6.9133548737,46.4290924072],"type":"Point"}
}