{
  "type": "Feature",
  "properties": {
    "iso:country":"CH",
    "sg:address":"Kreuzstrasse 4 8712 St\u00e4fa. Postfach 469",
    "sg:city":"St\u00e4fa",
    "sg:orig_category":"Handelsvermittlung U Grosshandel Herstellung von Metallkonstruktionen",
    "sg:phone":"+41 19261258",
    "sg:postcode":"8712",
    "sg:province":"Z\u00fcrich",
    "wof:name":"Huber Lagertechnik Ag",
    "wof:placetype":"venue"
},
  "geometry": {"coordinates":[8.7258710861,47.2395248413],"type":"Point"}
}