{
  "type": "Feature",
  "properties": {
    "iso:country":"CH",
    "sg:address":"Finkenweg 17 3110 M\u00fcnsingen. Postfach",
    "sg:city":"M\u00fcnsingen",
    "sg:orig_category":"Non-Classified Establishments",
    "sg:phone":"+41 31 721 46 72",
    "sg:postcode":"3110",
    "sg:province":"Bern",
    "wof:name":"Asw Holding Ag",
    "wof:placetype":"venue"
},
  "geometry": {"coordinates":[7.5708250999,46.8725318909],"type":"Point"}
}