{
  "type": "Feature",
  "properties": {
    "iso:country":"CH",
    "sg:address":"Schwanengasse 5/7 3011 Bern. Postfach 8523",
    "sg:city":"Bern",
    "sg:orig_category":"Lagerung",
    "sg:phone":"+41 81 756 14 46",
    "sg:postcode":"3001",
    "sg:province":"Bern",
    "wof:name":"Lagerhausverwaltung Sbb",
    "wof:placetype":"venue"
},
  "geometry": {"coordinates":[9.4501104355,47.1685714722],"type":"Point"}
}