{
  "type": "Feature",
  "properties": {
    "iso:country":"CH",
    "sg:address":"Avenue Du Mont-blanc 38 1196 Gland. Postfach",
    "sg:city":"Gland",
    "sg:orig_category":"RESTAURANTS: TEA-ROOMS",
    "sg:postcode":"1196",
    "sg:province":"Vaud",
    "wof:name":"Bn Management Sa",
    "wof:placetype":"venue"
},
  "geometry": {"coordinates":[6.2730379105,46.4142951965],"type":"Point"}
}