{
  "type": "Feature",
  "properties": {
    "iso:country":"CH",
    "sg:address":"Schmiedstrasse 21 4717 M\u00fcmliswil. Postfach 7",
    "sg:city":"M\u00fcmliswil",
    "sg:orig_category":"Detailhandel mit Damenbekleidung",
    "sg:phone":"+41 62 391 00 66",
    "sg:postcode":"4717",
    "sg:province":"Solothurn",
    "wof:name":"Mode Silvia S.& P.bader",
    "wof:placetype":"venue"
},
  "geometry": {"coordinates":[7.702435,47.341427],"type":"Point"}
}