{
  "type": "Feature",
  "properties": {
    "iso:country":"CH",
    "sg:address":"Byfangweg 1a",
    "sg:city":"Basel",
    "sg:orig_category":"Markt U Meinungsforschung",
    "sg:phone":"+41 61 206 98 76",
    "sg:postcode":"4051",
    "sg:province":"Basel-Stadt",
    "wof:name":"Planconsult W + B Ag Unternehmensberatung, Betriebsplanung Usw",
    "wof:placetype":"venue"
},
  "geometry": {"coordinates":[7.5832700729,47.5527534485],"type":"Point"}
}