{
  "type": "Feature",
  "properties": {
    "iso:country":"CH",
    "sg:address":"Contrada Di Sassello 2",
    "sg:city":"Lugano",
    "sg:orig_category":"Zahntechnische Laboratorien",
    "sg:phone":"+41 41 360 11 62",
    "sg:postcode":"6900",
    "sg:province":"Ticino",
    "wof:name":"Hans Grob Zahntechnisches Laboratorium",
    "wof:placetype":"venue"
},
  "geometry": {"coordinates":[8.317861557,47.0421295166],"type":"Point"}
}