{
  "type": "Feature",
  "properties": {
    "iso:country":"CH",
    "sg:address":"Dornacherstrasse 277 4053 Basel. Postfach",
    "sg:city":"Basel",
    "sg:orig_category":"Handel mit Motorr\u00e4dern, Teilen U Zubeh\u00f6r Instandhaltung U Reparatur von Motorr\u00e4dern",
    "sg:phone":"+41 81 413 39 09",
    "sg:postcode":"4053",
    "sg:province":"Basel-Stadt",
    "wof:name":"Ivan's Velo-sport, Fausch Fahrr\u00e4der Usw.; Verkauf, Reparaturen",
    "wof:placetype":"venue"
},
  "geometry": {"coordinates":[9.8236074448,46.7939071655],"type":"Point"}
}