{
  "type": "Feature",
  "properties": {
    "iso:country":"CH",
    "sg:address":"H\u00f6henweg 27",
    "sg:city":"Uetendorf",
    "sg:orig_category":"Vorschulen, Kinderg\u00e4rten",
    "sg:phone":"+41 33 345 42 62",
    "sg:postcode":"3661",
    "sg:province":"Bern",
    "wof:name":"Kindergarten Riedern",
    "wof:placetype":"venue"
},
  "geometry": {"coordinates":[7.5725231171,46.7726173401],"type":"Point"}
}