{
  "type": "Feature",
  "properties": {
    "iso:country":"CH",
    "sg:address":"Rue De La P\u00e9lisserie 18",
    "sg:city":"Gen\u00e8ve",
    "sg:orig_category":"Aktivit\u00e4t der Bankinstitute",
    "sg:phone":"+41 22 311 19 01",
    "sg:postcode":"1204",
    "sg:province":"Gen\u00e8ve",
    "wof:name":"Investec Bank (switzerland) Ag",
    "wof:placetype":"venue"
},
  "geometry": {"coordinates":[6.145906,46.202297],"type":"Point"}
}