{
  "type": "Feature",
  "properties": {
    "iso:country":"CH",
    "sg:address":"R\u00e4tusstrasse 22",
    "sg:city":"Chur",
    "sg:orig_category":"Erschliessung von Grundst\u00fccken Vermittlung von Immobilien",
    "sg:phone":"+41 81 257 15 30",
    "sg:postcode":"7000",
    "sg:province":"Graubunden",
    "wof:name":"Allod Verwaltungs-ag Chur",
    "wof:placetype":"venue"
},
  "geometry": {"coordinates":[9.523235321,46.8488502502],"type":"Point"}
}