{
  "type": "Feature",
  "properties": {
    "iso:country":"CH",
    "sg:address":"Seestrasse 187",
    "sg:city":"Steckborn",
    "sg:orig_category":"RESTAURANTS: TEA-ROOMS",
    "sg:postcode":"8266",
    "sg:province":"Thurgau",
    "wof:name":"Keller Gottfried",
    "wof:placetype":"venue"
},
  "geometry": {"coordinates":[8.9711399078,47.6587982178],"type":"Point"}
}