{
  "type": "Feature",
  "properties": {
    "iso:country":"CH",
    "sg:address":"In Der Schappe 8 4144 Arlesheim. Postfach",
    "sg:city":"Arlesheim",
    "sg:orig_category":"Satzherstellung U Reproduktion",
    "sg:phone":"+41 32 914 34 14",
    "sg:postcode":"4144",
    "sg:province":"Basel-Landschaft",
    "wof:name":"L'imagerie-litho S\u00e0rl",
    "wof:placetype":"venue"
},
  "geometry": {"coordinates":[6.8218688965,47.0982589722],"type":"Point"}
}