{
  "type": "Feature",
  "properties": {
    "iso:country":"CH",
    "sg:address":"Rue Saint-pierre 3 1003 Lausanne Case Postale",
    "sg:city":"Lausanne",
    "sg:orig_category":"Vermietung U Verpachtung von eigenen Immobilien Vermittlung von Immobilien",
    "sg:phone":"+41 21 310 25 25",
    "sg:postcode":"1002",
    "sg:province":"Vaud",
    "wof:name":"Fontatrez Holding Sa",
    "wof:placetype":"venue"
},
  "geometry": {"coordinates":[6.6372241974,46.5196113586],"type":"Point"}
}