{
  "type": "Feature",
  "properties": {
    "iso:country":"CH",
    "sg:address":"Duggelistrasse 28",
    "sg:city":"Cham",
    "sg:orig_category":"Innendekorationsateliers",
    "sg:phone":"+41 41 781 12 33",
    "sg:postcode":"6330",
    "sg:province":"Zug",
    "wof:name":"Atelier Pally Eslbeth Wiese Vorhangatelier",
    "wof:placetype":"venue"
},
  "geometry": {"coordinates":[8.4696073532,47.185459137],"type":"Point"}
}