{
  "type": "Feature",
  "properties": {
    "iso:country":"CH",
    "sg:address":"Piazza Alighieri Dante 8",
    "sg:city":"Lugano",
    "sg:orig_category":"Unternehmensberatung",
    "sg:phone":"+41 91 921 11 66",
    "sg:postcode":"6900",
    "sg:province":"Ticino",
    "wof:name":"Mizzau & Associati Sa",
    "wof:placetype":"venue"
},
  "geometry": {"coordinates":[8.951086998,46.0051116943],"type":"Point"}
}