{
  "type": "Feature",
  "properties": {
    "iso:country":"CH",
    "sg:address":"Vallemaggia Via",
    "sg:city":"Locarno",
    "sg:orig_category":"Interessenvertretungen",
    "sg:postcode":"6600",
    "sg:province":"Ticino",
    "wof:name":"Associazione Padroni Pittori Di Locarno E Dintroni.",
    "wof:placetype":"venue"
},
  "geometry": {"coordinates":[8.7890300751,46.169708252],"type":"Point"}
}