{
  "type": "Feature",
  "properties": {
    "iso:country":"CH",
    "sg:address":"Grabackerstrasse 2",
    "sg:city":"Kaltbrunn",
    "sg:orig_category":"Sanit\u00e4rinstallation Schlossereien",
    "sg:phone":"+41 55 283 23 65",
    "sg:postcode":"8722",
    "sg:province":"St. Gallen",
    "wof:name":"Peter F\u00e4h Schlosserei Sanit\u00e4r",
    "wof:placetype":"venue"
},
  "geometry": {"coordinates":[9.0126276016,47.2158660889],"type":"Point"}
}