{
  "type": "Feature",
  "properties": {
    "iso:country":"CH",
    "sg:address":"Zentrum Meierwis 8606 Greifensee. Postfach 65",
    "sg:city":"Greifensee",
    "sg:orig_category":"Detailhandel mit Brillen U anderen Sehhilfen Fachdetailhandel in Verkaufsr\u00e4umen",
    "sg:phone":"+41 32 913 37 55",
    "sg:postcode":"8606",
    "sg:province":"Z\u00fcrich",
    "wof:name":"Optigare, Pauli C. Et Kohler K.",
    "wof:placetype":"venue"
},
  "geometry": {"coordinates":[6.825169,47.099125],"type":"Point"}
}