{
  "type": "Feature",
  "properties": {
    "iso:country":"CH",
    "sg:address":"Aufhofen 27",
    "sg:city":"Thundorf",
    "sg:orig_category":"Architektur U Ingenieurb\u00fcros",
    "sg:phone":"+41 22 342 68 40",
    "sg:postcode":"8512",
    "sg:province":"Thurgau",
    "wof:name":"Erbeia P. Et J-l. Bouchardy, Ing\u00e9nieurs Civils Epfl-sia",
    "wof:placetype":"venue"
},
  "geometry": {"coordinates":[6.142601,46.185574],"type":"Point"}
}