{
  "type": "Feature",
  "properties": {
    "iso:country":"CH",
    "sg:address":"Corso San Gottardo 32",
    "sg:city":"Chiasso",
    "sg:orig_category":"Kunststoff-Produkte",
    "sg:phone":"+41 19110430",
    "sg:postcode":"6830",
    "sg:province":"Ticino",
    "wof:name":"Aluplast, Roger Gampp",
    "wof:placetype":"venue"
},
  "geometry": {"coordinates":[8.584944725,47.3223686218],"type":"Point"}
}