{
  "type": "Feature",
  "properties": {
    "iso:country":"CH",
    "sg:address":"Dorfplatz 3",
    "sg:city":"Sarnen",
    "sg:orig_category":"Rechtsberatung",
    "sg:postcode":"6060",
    "sg:province":"Obwalden",
    "wof:name":"Bike-parking-systems Ag",
    "wof:placetype":"venue"
},
  "geometry": {"coordinates":[8.2457389832,46.8957366943],"type":"Point"}
}