{
  "type": "Feature",
  "properties": {
    "iso:country":"CH",
    "sg:address":"Neunbrunnenstr. 55",
    "sg:city":"Z\u00fcrich",
    "sg:classifiers":[
        {
            "category":"Professional",
            "subcategory":"Engineering",
            "type":"Services"
        }
    ],
    "sg:phone":"+41 22 794 34 00",
    "sg:postcode":"8050",
    "sg:province":"Z\u00fcrich",
    "sg:tags":[
        "information",
        "electric",
        "technology",
        "component",
        "equipment",
        "electrical",
        "softwa",
        "electronic"
    ],
    "wof:name":"Gespac Sa",
    "wof:placetype":"venue"
},
  "geometry": {"coordinates":[6.104391098,46.1676483154],"type":"Point"}
}