{
  "type": "Feature",
  "properties": {
    "iso:country":"CH",
    "sg:address":"Rue Des Tertres 2a",
    "sg:city":"Marin-epagnier",
    "sg:orig_category":"Politische Parteien SP",
    "sg:phone":"+41 32 861 29 67",
    "sg:postcode":"2074",
    "sg:province":"Neuch\u00e2tel",
    "wof:name":"Parti Socialiste M\u00f4tiers",
    "wof:placetype":"venue"
},
  "geometry": {"coordinates":[6.6080970764,46.9087142944],"type":"Point"}
}