{
  "type": "Feature",
  "properties": {
    "iso:country":"CH",
    "sg:address":"Seetalstrasse 840 5503 Schafisheim. Postfach",
    "sg:city":"Schafisheim",
    "sg:orig_category":"Instandhaltung U Reparatur von Automobilen",
    "sg:postcode":"5503",
    "sg:province":"Aargau",
    "wof:name":"Seetal Carrosserie Basler Roland Auto-carrosserie Werkstatt",
    "wof:placetype":"venue"
},
  "geometry": {"coordinates":[8.1430482864,47.3740921021],"type":"Point"}
}