{
  "type": "Feature",
  "properties": {
    "iso:country":"CH",
    "sg:address":"Via Pezzolo 6",
    "sg:city":"Canobbio",
    "sg:orig_category":"Detailhandel mit Musikinstrumenten",
    "sg:phone":"+41 91 941 50 86",
    "sg:postcode":"6952",
    "sg:province":"Ticino",
    "wof:name":"Ugo Schwaller Fisarmoniche",
    "wof:placetype":"venue"
},
  "geometry": {"coordinates":[8.9648180008,46.035030365],"type":"Point"}
}