{
  "type": "Feature",
  "properties": {
    "iso:country":"CH",
    "sg:address":"Fontanastrasse 5",
    "sg:city":"St.gallen",
    "sg:orig_category":"Herstellung von Metallkonstruktionen Stahl U Leichtmetallbau",
    "sg:phone":"+41 71 277 32 64",
    "sg:postcode":"9000",
    "sg:province":"St. Gallen",
    "wof:name":"Metallbau M\u00fcller Ag St. Gallen",
    "wof:placetype":"venue"
},
  "geometry": {"coordinates":[9.3522558212,47.4178581238],"type":"Point"}
}