{
  "type": "Feature",
  "properties": {
    "iso:country":"CH",
    "sg:address":"Hauptstrasse 9",
    "sg:city":"Metzerlen",
    "sg:orig_category":"Instandhaltung U Reparatur von Automobilen",
    "sg:phone":"+41 61 731 31 94",
    "sg:postcode":"4116",
    "sg:province":"Solothurn",
    "wof:name":"Weber Roland, Garage",
    "wof:placetype":"venue"
},
  "geometry": {"coordinates":[7.4661440849,47.4666175842],"type":"Point"}
}