{
  "type": "Feature",
  "properties": {
    "iso:country":"CH",
    "sg:address":"Calame Rue Henri- 8",
    "sg:city":"Cernier",
    "sg:orig_category":"Gesundheitswesen",
    "sg:postcode":"2053",
    "sg:province":"Neuch\u00e2tel",
    "wof:name":"Fondation D'aide Et De Soins \u00e0 Domicile Du Val-de-ruz",
    "wof:placetype":"venue"
},
  "geometry": {"coordinates":[6.9010667801,47.0601348877],"type":"Point"}
}