{
  "type": "Feature",
  "properties": {
    "iso:country":"CH",
    "sg:address":"Hauptstrasse 95",
    "sg:city":"B\u00f6zen",
    "sg:orig_category":"Sanit\u00e4rinstallation",
    "sg:phone":"+41 62 876 18 53",
    "sg:postcode":"5076",
    "sg:province":"Aargau",
    "wof:name":"Roland Gaschen Sanit.installationen",
    "wof:placetype":"venue"
},
  "geometry": {"coordinates":[8.0794010162,47.4964981079],"type":"Point"}
}