{
  "type": "Feature",
  "properties": {
    "iso:country":"CH",
    "sg:address":"Weinbergstrasse 17",
    "sg:city":"Wettingen",
    "sg:orig_category":"Gem\u00fcsebau",
    "sg:phone":"+41 56 430 22 77",
    "sg:postcode":"5430",
    "sg:province":"Aargau",
    "wof:name":"Altermatt B\u00fchnenbild & Messebau Gmbh",
    "wof:placetype":"venue"
},
  "geometry": {"coordinates":[8.3223361969,47.471408844],"type":"Point"}
}