{
  "type": "Feature",
  "properties": {
    "iso:country":"CH",
    "sg:address":"Fulenbacherstr. 163.",
    "sg:city":"Boningen",
    "sg:orig_category":"Stukkateurgewerbe, Gipserei U Verputzerei",
    "sg:phone":"+41 81 413 77 78",
    "sg:postcode":"4618",
    "sg:province":"Solothurn",
    "wof:name":"K. Melliger & S\u00f6hne Ag Gipsergesch\u00e4ft",
    "wof:placetype":"venue"
},
  "geometry": {"coordinates":[9.8235492706,46.7945747375],"type":"Point"}
}