{
  "type": "Feature",
  "properties": {
    "iso:country":"CH",
    "sg:address":"Fliederweg 10",
    "sg:city":"Suhr",
    "sg:orig_category":"Gesundheitswesen",
    "sg:postcode":"5034",
    "sg:province":"Aargau",
    "wof:name":"Feldenkrais Praxis Brigitte Lackner M\u00e4rki Und Severin M\u00e4rki-lackner",
    "wof:placetype":"venue"
},
  "geometry": {"coordinates":[8.0634679794,47.3837242126],"type":"Point"}
}