{
  "type": "Feature",
  "properties": {
    "iso:country":"CH",
    "sg:address":"Aarauerstrasse 55",
    "sg:city":"Olten",
    "sg:classifiers":[
        {
            "category":"Insurance",
            "subcategory":"Insurance Agent",
            "type":"Services"
        }
    ],
    "sg:phone":"+41 84888016",
    "sg:postcode":"4600",
    "sg:province":"Solothurn",
    "sg:tags":[
        "versicherungsagenturen",
        "-broker"
    ],
    "wof:name":"Generali Versicherungen Agentur",
    "wof:placetype":"venue"
},
  "geometry": {"coordinates":[7.9107170105,47.3486404419],"type":"Point"}
}