{
  "type": "Feature",
  "properties": {
    "iso:country":"CH",
    "sg:address":"Route De Beurnev\u00e9sin",
    "sg:city":"Bonfol",
    "sg:orig_category":"Darlehenskassen U Raiffeisenbanken",
    "sg:phone":"+41 32 474 48 07",
    "sg:postcode":"2944",
    "sg:province":"Jura",
    "wof:name":"Banque Raiffeisen De Bonfol-beurnev\u00e9sin",
    "wof:placetype":"venue"
},
  "geometry": {"coordinates":[7.149694,47.478134],"type":"Point"}
}