{
  "type": "Feature",
  "properties": {
    "iso:country":"CH",
    "sg:address":"Cour Avenue De 38a 1007 Lausanne. Postfach",
    "sg:city":"Lausanne",
    "sg:orig_category":"Betrieb U technische Hilfsdienste des Kultur U Unterhaltungswesens",
    "sg:postcode":"1003",
    "sg:province":"Vaud",
    "wof:name":"Spevent Creation S\u00e0rl Organisation D'\u00e9v\u00e8nements, Manifestation Etc",
    "wof:placetype":"venue"
},
  "geometry": {"coordinates":[6.632335,46.519596],"type":"Point"}
}