{
  "type": "Feature",
  "properties": {
    "iso:country":"CH",
    "sg:address":"Zollhausstrasse 28",
    "sg:city":"Glarus",
    "sg:orig_category":"Herstellung von Heizk\u00f6rpern U kesseln f\u00fcr die Zentralheizung Herstellung von \u00d6fen U Brennern",
    "sg:phone":"+41 55 640 28 49",
    "sg:postcode":"8750",
    "sg:province":"Glarus",
    "wof:name":"Oertli Service Ag",
    "wof:placetype":"venue"
},
  "geometry": {"coordinates":[9.0639753342,47.0429725647],"type":"Point"}
}