{
  "type": "Feature",
  "properties": {
    "iso:country":"CH",
    "sg:address":"Rue Ami-girard 4a",
    "sg:city":"Ch\u00e9zard-st-martin",
    "sg:orig_category":"Maurerarbeiten Sonstiger spezialisierter Hoch U Tiefbau",
    "sg:phone":"+41 32 853 22 29",
    "sg:postcode":"2054",
    "sg:province":"Neuch\u00e2tel",
    "wof:name":"Jean-fran\u00e7ois Barizzi Ma\u00e7onnerie & Carrelage",
    "wof:placetype":"venue"
},
  "geometry": {"coordinates":[6.9324178696,47.0668411255],"type":"Point"}
}