{
  "type": "Feature",
  "properties": {
    "iso:country":"CH",
    "sg:address":"Bahnhofstrasse 4",
    "sg:city":"Fehraltorf",
    "sg:orig_category":"Detailhandel mit Fleisch U Fleischwaren",
    "sg:phone":"+41 19541681",
    "sg:postcode":"8320",
    "sg:province":"Z\u00fcrich",
    "wof:name":"Urs D\u00f6nni Dorfmetzg",
    "wof:placetype":"venue"
},
  "geometry": {"coordinates":[8.7531547546,47.3868942261],"type":"Point"}
}