{
  "type": "Feature",
  "properties": {
    "iso:country":"CH",
    "sg:address":"F\u00f6hrenstrasse 6",
    "sg:city":"Arbon",
    "sg:orig_category":"Herstellung von konfektionierten Textilwaren ohne Bekleidung",
    "sg:postcode":"9320",
    "sg:province":"Thurgau",
    "wof:name":"Sergio Wohnen",
    "wof:placetype":"venue"
},
  "geometry": {"coordinates":[9.4191398621,47.5096893311],"type":"Point"}
}