{
  "type": "Feature",
  "properties": {
    "iso:country":"CH",
    "sg:address":"Zurlindeninsel 1 5000 Aarau. Postfach 3030",
    "sg:city":"Aarau",
    "sg:orig_category":"Unclassifiable Establishments",
    "sg:postcode":"5001",
    "sg:province":"Aargau",
    "wof:name":"Jurada Sa",
    "wof:placetype":"venue"
},
  "geometry": {"coordinates":[9.1283597946,46.2375984192],"type":"Point"}
}