{
  "type": "Feature",
  "properties": {
    "iso:country":"CH",
    "sg:address":"7435",
    "sg:city":"Spl\u00fcgen",
    "sg:orig_category":"Kalb U Schweine-M\u00e4sterei U Zucht",
    "sg:postcode":"7435",
    "sg:province":"Graubunden",
    "wof:name":"Schweinestallgenossenschaft Spl\u00fcgen",
    "wof:placetype":"venue"
},
  "geometry": {"coordinates":[9.3233728409,46.5529594421],"type":"Point"}
}