{
  "type": "Feature",
  "properties": {
    "iso:country":"CH",
    "sg:address":"Chemin De La Lissole 30",
    "sg:city":"Perly",
    "sg:orig_category":"Gem\u00fcsebau",
    "sg:phone":"+41 79 435 25 09",
    "sg:postcode":"1258",
    "sg:province":"Gen\u00e8ve",
    "wof:name":"Jean Baussand Maraicher",
    "wof:placetype":"venue"
},
  "geometry": {"coordinates":[6.0950298309,46.1592559814],"type":"Point"}
}