{
  "type": "Feature",
  "properties": {
    "iso:country":"CH",
    "sg:address":"Lerchensangstrasse 11",
    "sg:city":"Felben-wellhausen",
    "sg:classifiers":[
        {
            "category":"Wholesale",
            "subcategory":"Scrap",
            "type":"Manufacturing & Wholesale Goods"
        }
    ],
    "sg:phone":"+41 52 765 26 11",
    "sg:postcode":"8552",
    "sg:province":"Thurgau",
    "sg:tags":[
        "metal"
    ],
    "wof:name":"Ren\u00e9 Giger Gmbh",
    "wof:placetype":"venue"
},
  "geometry": {"coordinates":[8.945936203,47.5808372498],"type":"Point"}
}