{
  "type": "Feature",
  "properties": {
    "iso:country":"CH",
    "sg:address":"Pilatusstrasse 18",
    "sg:city":"Ettiswil",
    "sg:orig_category":"Interessenvertretungen",
    "sg:phone":"+41 41 980 10 22",
    "sg:postcode":"6218",
    "sg:province":"Luzern",
    "wof:name":"Stiftung Schloss Wyher",
    "wof:placetype":"venue"
},
  "geometry": {"coordinates":[8.017583847,47.147808075],"type":"Point"}
}