{
  "type": "Feature",
  "properties": {
    "addr:full":"Landstrasse 16 Rothenthurm Schwyz 6418",
    "addr:housenumber":"16",
    "addr:postcode":"6418",
    "addr:street":"Landstrasse;Schwyz",
    "iso:country":"CH",
    "sg:address":"Landstrasse 16",
    "sg:city":"Rothenthurm",
    "sg:orig_category":"Allgemeiner Hoch U Tiefbau ohne ausgepr\u00e4gten Schwerpunkt",
    "sg:phone":"+41 41 839 03 90",
    "sg:postcode":"6418",
    "sg:province":"Schwyz",
    "wof:name":"Othmar Sp\u00e4ni Baugesch\u00e4ft",
    "wof:placetype":"venue"
},
  "geometry": {"coordinates":[8.67112,47.097492],"type":"Point"}
}