{
  "type": "Feature",
  "properties": {
    "iso:country":"CH",
    "sg:address":"Bitziring 7",
    "sg:city":"Bischofszell",
    "sg:classifiers":[
        {
            "category":"Insurance",
            "subcategory":"Insurance Agent",
            "type":"Services"
        }
    ],
    "sg:phone":"+41 81 750 54 54",
    "sg:postcode":"9220",
    "sg:province":"Thurgau",
    "sg:tags":[
        "versicherungsagenturen",
        "-broker"
    ],
    "wof:name":"Alpina Versicherungen Agentur",
    "wof:placetype":"venue"
},
  "geometry": {"coordinates":[9.4766569138,47.1597976685],"type":"Point"}
}