{
  "type": "Feature",
  "properties": {
    "iso:country":"CH",
    "sg:address":"Haus Tell 6365 Kehrsiten. Postfach",
    "sg:city":"Kehrsiten",
    "sg:orig_category":"Sonstiger Grosshandel",
    "sg:phone":"+41 22 731 74 00",
    "sg:postcode":"6365",
    "sg:province":"Nidwalden",
    "wof:name":"Parking Grands Magasins La Placette",
    "wof:placetype":"venue"
},
  "geometry": {"coordinates":[6.1423740387,46.2072792053],"type":"Point"}
}