{
  "type": "Feature",
  "properties": {
    "iso:country":"CH",
    "sg:address":"Feuerwerkerstrasse 39",
    "sg:city":"Thun",
    "sg:orig_category":"Anti-Burglary Equipment, Mechanical, For Doors, Windows, Roller Shutters , Shafts",
    "sg:phone":"+41 33 228 30 66",
    "sg:postcode":"3603",
    "sg:province":"Bern",
    "wof:name":"Fasif Schweizerische Fachstelle F\u00fcr Sicherungsfragen",
    "wof:placetype":"venue"
},
  "geometry": {"coordinates":[7.597535,46.761906],"type":"Point"}
}