{
  "type": "Feature",
  "properties": {
    "iso:country":"CH",
    "sg:address":"Rue Du Plandodin",
    "sg:city":"Savi\u00e8se",
    "sg:orig_category":"Detailhandel mit M\u00f6beln Verlegen von Fussboden",
    "sg:phone":"+41 79 230 62 09",
    "sg:postcode":"1965",
    "sg:province":"Valais",
    "wof:name":"H\u00e9ritier Meubles-tapis",
    "wof:placetype":"venue"
},
  "geometry": {"coordinates":[7.3511247635,46.2515602112],"type":"Point"}
}