{
  "type": "Feature",
  "properties": {
    "iso:country":"CH",
    "sg:address":"Rue Saint-pierre 18 1700 Freiburg. Postfach",
    "sg:city":"Fribourg",
    "sg:orig_category":"Non-Classified Establishments",
    "sg:postcode":"1702",
    "sg:province":"Fribourg",
    "wof:name":"Dataloggistics International Sa",
    "wof:placetype":"venue"
},
  "geometry": {"coordinates":[7.1558661461,46.8040313721],"type":"Point"}
}