{
  "type": "Feature",
  "properties": {
    "iso:country":"CH",
    "sg:address":"Bodenmatt",
    "sg:city":"Entlebuch",
    "sg:orig_category":"Organisationen des Gesundheitswesen",
    "sg:phone":"+41 41 488 22 12",
    "sg:postcode":"6162",
    "sg:province":"Luzern",
    "wof:name":"Ambulante Krankenpflege Fl\u00fchli-s\u00f6renberg",
    "wof:placetype":"venue"
},
  "geometry": {"coordinates":[8.0140657425,46.8850288391],"type":"Point"}
}