{
  "type": "Feature",
  "properties": {
    "iso:country":"CH",
    "sg:address":"Unterdorfstrasse 6",
    "sg:city":"Sch\u00f6tz",
    "sg:orig_category":"Verarbeitung von Milch Verwertung von Milch",
    "sg:postcode":"6247",
    "sg:province":"Luzern",
    "wof:name":"K\u00e4sereigenossenschaft Sch\u00f6tz",
    "wof:placetype":"venue"
},
  "geometry": {"coordinates":[7.9866380692,47.1712303162],"type":"Point"}
}