{
  "type": "Feature",
  "properties": {
    "iso:country":"CH",
    "sg:address":"Casinoplatz 5",
    "sg:city":"Chur",
    "sg:orig_category":"W\u00e4scherei U chemische Reinigung",
    "sg:phone":"+41 81 252 88 10",
    "sg:postcode":"7000",
    "sg:province":"Graubunden",
    "wof:name":"Express Kleiderpflege Cahenzli Jolanda",
    "wof:placetype":"venue"
},
  "geometry": {"coordinates":[9.5318603516,46.8488616943],"type":"Point"}
}