{
  "type": "Feature",
  "properties": {
    "iso:country":"CH",
    "sg:address":"Frauenfelderstrasse 18",
    "sg:city":"Eschenz",
    "sg:orig_category":"Bau\u00e4mter",
    "sg:phone":"+41 52 741 51 50",
    "sg:postcode":"8264",
    "sg:province":"Thurgau",
    "wof:name":"Bauamt & Werkhof",
    "wof:placetype":"venue"
},
  "geometry": {"coordinates":[8.874733,47.645679],"type":"Point"}
}