{
  "type": "Feature",
  "properties": {
    "iso:country":"CH",
    "sg:address":"Hauptstrasse 23",
    "sg:city":"Seltisberg",
    "sg:orig_category":"Primarschulen",
    "sg:phone":"+41 61 911 94 70",
    "sg:postcode":"4411",
    "sg:province":"Basel-Landschaft",
    "wof:name":"Primarschule",
    "wof:placetype":"venue"
},
  "geometry": {"coordinates":[7.7185878754,47.4610061646],"type":"Point"}
}