{
  "type": "Feature",
  "properties": {
    "iso:country":"CH",
    "sg:address":"Bergstrasse 203",
    "sg:city":"M\u00e4nnedorf",
    "sg:orig_category":"Wirtschaftspr\u00fcfung, Steuerberatung U Treuhand",
    "sg:phone":"+41 17902307",
    "sg:postcode":"8708",
    "sg:province":"Z\u00fcrich",
    "wof:name":"Zwick K\u00fcnzler Treuhand",
    "wof:placetype":"venue"
},
  "geometry": {"coordinates":[8.7034702301,47.2590408325],"type":"Point"}
}