{
  "type": "Feature",
  "properties": {
    "iso:country":"CH",
    "sg:address":"Dietlikonerstrasse 16 8000 Z\u00fcrich. Postfach",
    "sg:city":"Z\u00fcrich",
    "sg:orig_category":"Finanzierungsinstitutionen",
    "sg:phone":"+41 13117270",
    "sg:postcode":"8000",
    "sg:province":"Z\u00fcrich",
    "wof:name":"Ferber Christian Ag",
    "wof:placetype":"venue"
},
  "geometry": {"coordinates":[8.4809503555,47.3614616394],"type":"Point"}
}