{
  "type": "Feature",
  "properties": {
    "iso:country":"CH",
    "sg:address":"Br\u00fcggstrasse 115a",
    "sg:city":"Biel/bienne",
    "sg:orig_category":"Fussboden, Fliesen U Plattenlegerei, Tapeziererei Verlegen von Fussboden",
    "sg:postcode":"2503",
    "sg:province":"Bern",
    "wof:name":"Kocher Robert",
    "wof:placetype":"venue"
},
  "geometry": {"coordinates":[7.258436203,47.1280097961],"type":"Point"}
}