{
  "type": "Feature",
  "properties": {
    "iso:country":"CH",
    "sg:address":"5707",
    "sg:city":"Seengen",
    "sg:orig_category":"Vorschulen, Kinderg\u00e4rten",
    "sg:phone":"+41 62 777 30 44",
    "sg:postcode":"5707",
    "sg:province":"Aargau",
    "wof:name":"Kindergarten Rotes Haus",
    "wof:placetype":"venue"
},
  "geometry": {"coordinates":[8.2041797638,47.3263511658],"type":"Point"}
}