{
  "type": "Feature",
  "properties": {
    "iso:country":"CH",
    "sg:address":"1665",
    "sg:city":"Estavannens",
    "sg:orig_category":"Non-Classified Establishments",
    "sg:postcode":"1665",
    "sg:province":"Fribourg",
    "wof:name":"Syndicat De Drainage D'estavannens",
    "wof:placetype":"venue"
},
  "geometry": {"coordinates":[7.1029200554,46.5643806458],"type":"Point"}
}