{
  "type": "Feature",
  "properties": {
    "iso:country":"CH",
    "sg:address":"Chemin De Sous-le-cr\u00eat 7",
    "sg:city":"Troinex",
    "sg:orig_category":"Gem\u00fcsebau",
    "sg:phone":"+41 22 784 20 60",
    "sg:postcode":"1256",
    "sg:province":"Gen\u00e8ve",
    "wof:name":"L\u00e9one Pittet Maraich\u00e8re",
    "wof:placetype":"venue"
},
  "geometry": {"coordinates":[6.1493701935,46.1649284363],"type":"Point"}
}