{
  "type": "Feature",
  "properties": {
    "iso:country":"CH",
    "sg:address":"Route Des Avouillons 30",
    "sg:city":"Gland",
    "sg:orig_category":"Berufliche Weiterbildung, Erwachsenenbildung HOTELS: MIT RESTAURANT",
    "sg:phone":"+41 19107306",
    "sg:postcode":"1196",
    "sg:province":"Vaud",
    "wof:name":"Mediasec Ag Fachtagungen",
    "wof:placetype":"venue"
},
  "geometry": {"coordinates":[8.598677,47.312656],"type":"Point"}
}