{
  "type": "Feature",
  "properties": {
    "iso:country":"CH",
    "sg:address":"Brauereistrasse",
    "sg:city":"B\u00fctschwil",
    "sg:orig_category":"Grosshandel mit Getr\u00e4nken",
    "sg:postcode":"9606",
    "sg:province":"St. Gallen",
    "wof:name":"Bierdepot B\u00e4rlocher R.",
    "wof:placetype":"venue"
},
  "geometry": {"coordinates":[9.0724220276,47.3585510254],"type":"Point"}
}