{
  "type": "Feature",
  "properties": {
    "iso:country":"CH",
    "sg:address":"Kirchenfeldstrasse 39",
    "sg:city":"Bern",
    "sg:orig_category":"Markt U Meinungsforschung",
    "sg:postcode":"3005",
    "sg:province":"Bern",
    "wof:name":"Bozic",
    "wof:placetype":"venue"
},
  "geometry": {"coordinates":[7.451895237,46.9407157898],"type":"Point"}
}