{
  "type": "Feature",
  "properties": {
    "iso:country":"CH",
    "sg:address":"H\u00f4tel Richemont 1837 Ch\u00e2teau-d'oex. Postfach",
    "sg:city":"Ch\u00e2teau-d'oex",
    "sg:classifiers":[
        {
            "category":"Travel",
            "subcategory":"Hotels & Motels",
            "type":"Entertainment"
        }
    ],
    "sg:postcode":"1837",
    "sg:tags":[
        "hotels",
        "mit",
        "restaurant"
    ],
    "wof:name":"J.p. Lang-felder",
    "wof:placetype":"venue"
},
  "geometry": {"coordinates":[7.7188200951,47.5356903076],"type":"Point"}
}