{
  "type": "Feature",
  "properties": {
    "iso:country":"CH",
    "sg:address":"Rue Des Vuarennes",
    "sg:city":"Granges-marnand",
    "sg:orig_category":"Architektur U Ingenieurb\u00fcros Grosshandel mit Datenverarbeitungsger\u00e4ten",
    "sg:phone":"+41 26 668 92 22",
    "sg:postcode":"1523",
    "sg:province":"Vaud",
    "wof:name":"Pouly Ing\u00e9nieurs Civils Sa",
    "wof:placetype":"venue"
},
  "geometry": {"coordinates":[6.887525,46.76358],"type":"Point"}
}