{
  "type": "Feature",
  "properties": {
    "iso:country":"CH",
    "sg:address":"Rue Du Vallon 27",
    "sg:city":"St-imier",
    "sg:orig_category":"Bauschreinerei Herstellung von M\u00f6beln verschiedener Art",
    "sg:phone":"+41 32 941 45 03",
    "sg:postcode":"2610",
    "sg:province":"Bern",
    "wof:name":"Oppliger Willy",
    "wof:placetype":"venue"
},
  "geometry": {"coordinates":[6.997339,47.151222],"type":"Point"}
}