{
  "type": "Feature",
  "properties": {
    "iso:country":"CH",
    "sg:address":"Keltenweg 32",
    "sg:city":"Steinhausen",
    "sg:orig_category":"Vereine Gesang",
    "sg:phone":"+41 41 741 18 55",
    "sg:postcode":"6312",
    "sg:province":"Zug",
    "wof:name":"M\u00e4nnerchor Zug",
    "wof:placetype":"venue"
},
  "geometry": {"coordinates":[8.479596138,47.1984672546],"type":"Point"}
}