{
  "type": "Feature",
  "properties": {
    "addr:full":"Dorfstrasse 6 M\u00fchlethal Aargau 4812",
    "addr:housenumber":"6",
    "addr:postcode":"4812",
    "addr:street":"Dorfstrasse",
    "iso:country":"CH",
    "sg:address":"Dorfstrasse 6",
    "sg:city":"M\u00fchlethal",
    "sg:orig_category":"Bauschreinerei",
    "sg:phone":"+41 62 751 69 37",
    "sg:postcode":"4812",
    "sg:province":"Aargau",
    "wof:name":"Peraj - Schreiner Montagen",
    "wof:placetype":"venue"
},
  "geometry": {"coordinates":[7.978829,47.301552],"type":"Point"}
}