{
  "type": "Feature",
  "properties": {
    "iso:country":"CH",
    "sg:address":"Unterdorf",
    "sg:city":"Goldingen",
    "sg:orig_category":"Verarbeitung von Milch Verwertung von Milch",
    "sg:postcode":"8638",
    "sg:province":"St. Gallen",
    "wof:name":"Alois Pfister",
    "wof:placetype":"venue"
},
  "geometry": {"coordinates":[8.9639005661,47.2631149292],"type":"Point"}
}