{
  "type": "Feature",
  "properties": {
    "iso:country":"CH",
    "sg:address":"Hauptstrasse 17",
    "sg:city":"Derendingen",
    "sg:orig_category":"Non-Classified Establishments",
    "sg:postcode":"4552",
    "sg:province":"Solothurn",
    "wof:name":"Deniz Pizza Kebab Gmbh",
    "wof:placetype":"venue"
},
  "geometry": {"coordinates":[7.5839300156,47.1979293823],"type":"Point"}
}