{
  "type": "Feature",
  "properties": {
    "iso:country":"CH",
    "sg:address":"Paradieslistrasse 4",
    "sg:city":"Aarburg",
    "sg:orig_category":"Grosshandel mit Software Softwareentwicklung U beratung",
    "sg:phone":"+41 62 791 06 40",
    "sg:postcode":"4663",
    "sg:province":"Aargau",
    "wof:name":"Prime Vision Ag",
    "wof:placetype":"venue"
},
  "geometry": {"coordinates":[7.8987607956,47.3167419434],"type":"Point"}
}