{
  "type": "Feature",
  "properties": {
    "iso:country":"CH",
    "sg:address":"Rue De Pierre-pertuis 44 2710 Tavannes. Postfach",
    "sg:city":"Tavannes",
    "sg:orig_category":"Handelsvermittlung U Grosshandel mit Automobilen Instandhaltung U Reparatur von Automobilen",
    "sg:phone":"+41 32 481 22 66",
    "sg:postcode":"2710",
    "sg:province":"Bern",
    "wof:name":"Codi V\u00e9hicules Sa V\u00e9hicules Utilitaires",
    "wof:placetype":"venue"
},
  "geometry": {"coordinates":[7.193002224,47.2152748108],"type":"Point"}
}