{
  "type": "Feature",
  "properties": {
    "iso:country":"CH",
    "sg:address":"Via S. Anna 1",
    "sg:city":"Sorengo",
    "sg:orig_category":"Arztpraxen",
    "sg:phone":"+41 91 630 92 40",
    "sg:postcode":"6924",
    "sg:province":"Ticino",
    "wof:name":"Dott.med.gianluigi Marini Specialista Fmh",
    "wof:placetype":"venue"
},
  "geometry": {"coordinates":[8.938936,46.000523],"type":"Point"}
}