{
  "type": "Feature",
  "properties": {
    "iso:country":"CH",
    "sg:address":"Spitzackerstrasse 4",
    "sg:city":"Liestal",
    "sg:orig_category":"Herstellung von k\u00e4lte U lufttechnischen Erzeugnissen f\u00fcr gewerbliche Zwecke",
    "sg:phone":"+41 61 921 46 91",
    "sg:postcode":"4410",
    "sg:province":"Basel-Landschaft",
    "wof:name":"Solbau Gmbh",
    "wof:placetype":"venue"
},
  "geometry": {"coordinates":[7.7381057739,47.4792747498],"type":"Point"}
}