{
  "type": "Feature",
  "properties": {
    "iso:country":"CH",
    "sg:address":"Urdorfer Str.",
    "sg:city":"Birmensdorf",
    "sg:classifiers":[
        {
            "category":"Banks & Credit Unions",
            "subcategory":"Investment Brokerage",
            "type":"Services"
        }
    ],
    "sg:phone":"+41 4117391466",
    "sg:postcode":"8903",
    "sg:province":"Z\u00fcrich",
    "sg:tags":[
        "-",
        "transport",
        "related"
    ],
    "wof:name":"Hastag Holding",
    "wof:placetype":"venue"
},
  "geometry": {"coordinates":[8.4296674728,47.3664169312],"type":"Point"}
}