{
  "type": "Feature",
  "properties": {
    "iso:country":"CH",
    "sg:address":"8722",
    "sg:city":"Kaltbrunn",
    "sg:orig_category":"Landw. Genossenschaften Viehzucht",
    "sg:postcode":"8722",
    "sg:province":"St. Gallen",
    "wof:name":"Viehzuchtgenossenschaft",
    "wof:placetype":"venue"
},
  "geometry": {"coordinates":[9.0725097656,46.9936103821],"type":"Point"}
}