{
  "type": "Feature",
  "properties": {
    "iso:country":"CH",
    "sg:address":"Laufenstrasse 623",
    "sg:city":"Kleinl\u00fctzel",
    "sg:orig_category":"Nationale Postdienste",
    "sg:phone":"+41 61 771 06 26",
    "sg:postcode":"4245",
    "sg:province":"Solothurn",
    "wof:name":"Die Schweizerische Post",
    "wof:placetype":"venue"
},
  "geometry": {"coordinates":[7.4158940315,47.4257125854],"type":"Point"}
}