{
  "type": "Feature",
  "properties": {
    "iso:country":"CH",
    "sg:address":"L\u00e4ttenstrasse 2 8952 Schlieren. Postfach",
    "sg:city":"Schlieren",
    "sg:orig_category":"Unclassifiable Establishments",
    "sg:phone":"+41 17304663",
    "sg:postcode":"8952",
    "sg:province":"Z\u00fcrich",
    "wof:name":"Haus + Tech-service Gmbh Liegenschaften-unterhaltsunternehmen",
    "wof:placetype":"venue"
},
  "geometry": {"coordinates":[8.444029808,47.4029960632],"type":"Point"}
}