{
  "type": "Feature",
  "properties": {
    "iso:country":"CH",
    "sg:address":"Feierabendstrasse 43",
    "sg:city":"Basel",
    "sg:orig_category":"Dienstleistungen im Gartenbau Malerei",
    "sg:postcode":"4051",
    "sg:province":"Basel-Stadt",
    "wof:name":"Dominik Eichenberger Wohnsinn/liegensch'betreuung",
    "wof:placetype":"venue"
},
  "geometry": {"coordinates":[7.5805630684,47.5525093079],"type":"Point"}
}