{
  "type": "Feature",
  "properties": {
    "iso:country":"CH",
    "sg:address":"Route De La Praly 33",
    "sg:city":"Ros\u00e9",
    "sg:orig_category":"Handelsvermittlung U Grosshandel Sonstiger Grosshandel",
    "sg:phone":"+41 26 470 28 10",
    "sg:postcode":"1754",
    "sg:province":"Fribourg",
    "wof:name":"Jcv Verdon Import-export",
    "wof:placetype":"venue"
},
  "geometry": {"coordinates":[7.0666351318,46.7830810547],"type":"Point"}
}