{
  "type": "Feature",
  "properties": {
    "iso:country":"CH",
    "sg:address":"6661",
    "sg:city":"Loco",
    "sg:orig_category":"Grosshandel mit lebenden Tieren",
    "sg:phone":"+41 41 811 40 04",
    "sg:postcode":"6661",
    "sg:province":"Ticino",
    "wof:name":"Dominik Reichmuth Viehhandel",
    "wof:placetype":"venue"
},
  "geometry": {"coordinates":[8.6323652267,47.026550293],"type":"Point"}
}