{
  "type": "Feature",
  "properties": {
    "iso:country":"CH",
    "sg:address":"Chemin Du Grand-puits 38 1217 Meyrin. Postfach",
    "sg:city":"Meyrin",
    "sg:orig_category":"Sonstige mit der Informatik verbundene T\u00e4tigkeiten",
    "sg:postcode":"1217",
    "sg:province":"Gen\u00e8ve",
    "wof:name":"Astron Associates Sa",
    "wof:placetype":"venue"
},
  "geometry": {"coordinates":[6.0751681328,46.2254486084],"type":"Point"}
}