{
  "type": "Feature",
  "properties": {
    "addr:full":"Torlenstrasse 1 St\u00e4fa Z\u00fcrich 8712",
    "addr:housenumber":"1",
    "addr:postcode":"8712",
    "addr:street":"Torlenstrasse;Zuerich",
    "iso:country":"CH",
    "sg:address":"Torlenstrasse 1",
    "sg:city":"St\u00e4fa",
    "sg:orig_category":"Architektur U Ingenieurb\u00fcros",
    "sg:phone":"+41 19265400",
    "sg:postcode":"8712",
    "sg:province":"Z\u00fcrich",
    "wof:name":"Deger Design + Dynamik Gmbh",
    "wof:placetype":"venue"
},
  "geometry": {"coordinates":[8.740455,47.241177],"type":"Point"}
}