{
  "type": "Feature",
  "properties": {
    "iso:country":"CH",
    "sg:address":"Waldeggstrasse 82",
    "sg:city":"Interlaken",
    "sg:orig_category":"Herstellung von Metallerzeugnissen ohne Maschinenbau",
    "sg:phone":"+41 79 334 41 73",
    "sg:postcode":"3800",
    "sg:province":"Bern",
    "wof:name":"Wladyslaw Jarmicki Metallwarenfabrikation",
    "wof:placetype":"venue"
},
  "geometry": {"coordinates":[7.8588747978,46.682674408],"type":"Point"}
}