{
  "type": "Feature",
  "properties": {
    "iso:country":"CH",
    "sg:address":"Rue De Corcelles 44 1616 Attalens. Postfach",
    "sg:city":"Attalens",
    "sg:orig_category":"Herstellung von Metallkonstruktionen Herstellung von elektronischen Bauelementen",
    "sg:phone":"+41 21 947 54 81",
    "sg:postcode":"1616",
    "sg:province":"Fribourg",
    "wof:name":"Sabitec, H\u00fcgli Andr\u00e9 Commerce De Mat\u00e9riel \u00e9lectronique Pour Industries, Laboratoires Etc",
    "wof:placetype":"venue"
},
  "geometry": {"coordinates":[6.8503050804,46.5124168396],"type":"Point"}
}