{
  "type": "Feature",
  "properties": {
    "iso:country":"CH",
    "sg:address":"Rue De La Poste 1936 Verbier. Postfach",
    "sg:city":"Verbier",
    "sg:orig_category":"Non-Classified Establishments",
    "sg:phone":"+41 21 921 21 96",
    "sg:postcode":"1936",
    "sg:province":"Valais",
    "wof:name":"Restodancing Sa",
    "wof:placetype":"venue"
},
  "geometry": {"coordinates":[7.2247400284,46.0970802307],"type":"Point"}
}