{
  "type": "Feature",
  "properties": {
    "iso:country":"CH",
    "sg:address":"3924",
    "sg:city":"Gasenried",
    "sg:orig_category":"RESTAURANTS: TEA-ROOMS",
    "sg:phone":"+41 19200265",
    "sg:postcode":"3924",
    "sg:province":"Valais",
    "wof:name":"Restaurant Riedsteg",
    "wof:placetype":"venue"
},
  "geometry": {"coordinates":[8.6775617599,47.2634506226],"type":"Point"}
}