{
  "type": "Feature",
  "properties": {
    "iso:country":"CH",
    "sg:address":"Cornouillerstrasse 4",
    "sg:city":"Biel/bienne",
    "sg:orig_category":"Architektur U Ingenieurb\u00fcros",
    "sg:phone":"+41 32 341 77 17",
    "sg:postcode":"2502",
    "sg:province":"Bern",
    "wof:name":"Detra Sa Consulting \u00e9lectrom\u00e9canique",
    "wof:placetype":"venue"
},
  "geometry": {"coordinates":[7.257114,47.145882],"type":"Point"}
}