{
  "type": "Feature",
  "properties": {
    "iso:country":"CH",
    "sg:address":"Rue De La M\u00e8bre 13",
    "sg:city":"Cheseaux-lausanne",
    "sg:orig_category":"Arztpraxen",
    "sg:phone":"+41 21 731 92 00",
    "sg:postcode":"1033",
    "sg:province":"Vaud",
    "wof:name":"Dr M\u00e9d. Michel Rohrer M\u00e9decin G\u00e9n\u00e9raliste Fmh",
    "wof:placetype":"venue"
},
  "geometry": {"coordinates":[6.607729,46.581699],"type":"Point"}
}