{
  "type": "Feature",
  "properties": {
    "iso:country":"CH",
    "sg:address":"Place Centrale 1936 Verbier. Postfach",
    "sg:city":"Verbier",
    "sg:orig_category":"Interessenvertretungen",
    "sg:postcode":"1936",
    "sg:province":"Valais",
    "wof:name":"Fondation De L'orchestre De Verbier Promouvoir La Vie Et La Cr\u00e9ation Culturelle, Artistique Et Musicale Etc",
    "wof:placetype":"venue"
},
  "geometry": {"coordinates":[7.2288060188,46.0959701538],"type":"Point"}
}