{
  "type": "Feature",
  "properties": {
    "iso:country":"CH",
    "sg:address":"Termerstrasse 74a",
    "sg:city":"Termen",
    "sg:orig_category":"Aktivit\u00e4ten der Generalunternehmen im Baugewerbe Allgemeiner Hoch U Tiefbau",
    "sg:phone":"+41 27 924 99 11",
    "sg:postcode":"3912",
    "sg:province":"Valais",
    "wof:name":"Gasser/kuonen Ag Generalunternehmung",
    "wof:placetype":"venue"
},
  "geometry": {"coordinates":[8.017137,46.322102],"type":"Point"}
}