{
  "type": "Feature",
  "properties": {
    "iso:country":"CH",
    "sg:address":"Via Gaggiolo 56",
    "sg:city":"Stabio",
    "sg:orig_category":"G\u00fcterbef\u00f6rderung im Strassenverkehr",
    "sg:phone":"+41 91 647 36 27",
    "sg:postcode":"6855",
    "sg:province":"Ticino",
    "wof:name":"Carugati Sa Trasporti Internazionali",
    "wof:placetype":"venue"
},
  "geometry": {"coordinates":[8.9180202484,45.8424415588],"type":"Point"}
}