{
  "type": "Feature",
  "properties": {
    "iso:country":"CH",
    "sg:address":"Le Torrent B",
    "sg:city":"Ch\u00e2teau-d'oex",
    "sg:orig_category":"Grosshandel mit Bekleidung Grosshandel mit Nahrungsmitteln, Getr\u00e4nken U Tabakwaren",
    "sg:phone":"+41 26 924 49 89",
    "sg:postcode":"1837",
    "wof:name":"Siee Ody & Hamon",
    "wof:placetype":"venue"
},
  "geometry": {"coordinates":[-83.6629104614,37.7164306641],"type":"Point"}
}