{
  "type": "Feature",
  "properties": {
    "iso:country":"CH",
    "sg:address":"Dornhaldestrasse 28",
    "sg:city":"Heimberg",
    "sg:orig_category":"Stukkateurgewerbe, Gipserei U Verputzerei",
    "sg:phone":"+41 33 437 36 28",
    "sg:postcode":"3627",
    "sg:province":"Bern",
    "wof:name":"Alessio G.",
    "wof:placetype":"venue"
},
  "geometry": {"coordinates":[7.6052980423,46.7948913574],"type":"Point"}
}