{
  "type": "Feature",
  "properties": {
    "iso:country":"CH",
    "sg:address":"Hauptgasse 64 4500 Solothurn. Postfach",
    "sg:city":"Solothurn",
    "sg:orig_category":"Vereine Lions",
    "sg:postcode":"4502",
    "sg:province":"Solothurn",
    "wof:name":"Lions Club Solothurn C/o Hotel Krone",
    "wof:placetype":"venue"
},
  "geometry": {"coordinates":[7.5384101868,47.2079086304],"type":"Point"}
}