{
  "type": "Feature",
  "properties": {
    "iso:country":"CH",
    "sg:address":"Scheftenau",
    "sg:city":"Wattwil",
    "sg:orig_category":"Landw. Genossenschaften Alpgenossenschaften",
    "sg:postcode":"9630",
    "sg:province":"St. Gallen",
    "wof:name":"Toggenburgische Alpen- Genossenschaft Engelschwand",
    "wof:placetype":"venue"
},
  "geometry": {"coordinates":[9.0982265472,47.2782440186],"type":"Point"}
}