{
  "type": "Feature",
  "properties": {
    "iso:country":"CH",
    "sg:address":"Zone Industrielle Case Postale",
    "sg:city":"Lucens",
    "sg:classifiers":[
        {
            "category":"Farming",
            "subcategory":"Farm & Veterinary Services",
            "type":"Manufacturing & Wholesale Goods"
        }
    ],
    "sg:phone":"+41 71 388 72 72",
    "sg:postcode":"1522",
    "sg:province":"Vaud",
    "sg:tags":[
        "food",
        "product",
        "breeding",
        "animal",
        "related"
    ],
    "wof:name":"Provimi Kliba Ag",
    "wof:placetype":"venue"
},
  "geometry": {"coordinates":[9.254929,47.412361],"type":"Point"}
}