{
  "type": "Feature",
  "properties": {
    "iso:country":"CH",
    "sg:address":"Schlossstrasse 41",
    "sg:city":"Oensingen",
    "sg:orig_category":"Arztpraxen",
    "sg:phone":"+41 62 396 16 24",
    "sg:postcode":"4702",
    "sg:province":"Solothurn",
    "wof:name":"Dr.med.christian Rohrmann Arzt F.allgemeine Medizin Fmh",
    "wof:placetype":"venue"
},
  "geometry": {"coordinates":[7.716853,47.292999],"type":"Point"}
}