{
  "type": "Feature",
  "properties": {
    "iso:country":"CH",
    "sg:address":"Oestliche Bergstrasse 8",
    "sg:city":"Littau",
    "sg:orig_category":"G\u00fcterbef\u00f6rderung im Strassenverkehr R\u00fcckgewinnung U Vorbereitung f\u00fcr die Wiederverwertung Recycling ",
    "sg:phone":"+41 41 250 24 82",
    "sg:postcode":"6014",
    "sg:province":"Luzern",
    "wof:name":"Hanspeter Lipp Transporte & Alteisen, Metalle",
    "wof:placetype":"venue"
},
  "geometry": {"coordinates":[8.2529363632,47.0548782349],"type":"Point"}
}