{
  "type": "Feature",
  "properties": {
    "iso:country":"CH",
    "sg:address":"Kindhauserstrasse 1 8604 Volketswil. Postfach",
    "sg:city":"Volketswil",
    "sg:orig_category":"Detailhandel mit Brot, Back U S\u00fcsswaren",
    "sg:phone":"+41 31 300 20 22",
    "sg:postcode":"8604",
    "sg:province":"Z\u00fcrich",
    "wof:name":"Beck Glatz Confiseur Ag",
    "wof:placetype":"venue"
},
  "geometry": {"coordinates":[7.494973,47.0173],"type":"Point"}
}