{
  "type": "Feature",
  "properties": {
    "iso:country":"CH",
    "sg:address":"Langgasse 40",
    "sg:city":"Baar",
    "sg:orig_category":"Unclassifiable Establishments",
    "sg:phone":"+41 41 760 13 13",
    "sg:postcode":"6340",
    "sg:province":"Zug",
    "wof:name":"Bw & M Holding Ag",
    "wof:placetype":"venue"
},
  "geometry": {"coordinates":[8.5370063782,47.1965637207],"type":"Point"}
}