{
  "type": "Feature",
  "properties": {
    "iso:country":"CH",
    "sg:address":"Belpbergstrasse 1b 3123 Belp. Postfach",
    "sg:city":"Belp",
    "sg:orig_category":"Unternehmensberatung",
    "sg:phone":"+41 19512120",
    "sg:postcode":"3123",
    "sg:province":"Bern",
    "wof:name":"Michael John Hirsiger Abs-dienstleistungen",
    "wof:placetype":"venue"
},
  "geometry": {"coordinates":[8.7938051224,47.3604431152],"type":"Point"}
}