{
  "type": "Feature",
  "properties": {
    "iso:country":"CH",
    "sg:address":"Reifferg\u00e4ssli 3 6300 Zug. Postfach",
    "sg:city":"Zug",
    "sg:orig_category":"RESTAURANTS: TEA-ROOMS",
    "sg:postcode":"6300",
    "sg:province":"Zug",
    "wof:name":"Finelli & Partner Ag Restaurationsbetrieben. T\u00e4tigkeiten In Der Gastronomiebranche",
    "wof:placetype":"venue"
},
  "geometry": {"coordinates":[8.5150337219,47.1696090698],"type":"Point"}
}