{
  "type": "Feature",
  "properties": {
    "iso:country":"CH",
    "sg:address":"Maderno Via Carlo 5",
    "sg:city":"Bellinzona",
    "sg:orig_category":"Sonstige pers\u00f6nliche Dienstleistungen",
    "sg:postcode":"6500",
    "sg:province":"Ticino",
    "wof:name":"Giro Service Di Rossi Giorgio",
    "wof:placetype":"venue"
},
  "geometry": {"coordinates":[9.0144720078,46.1844863892],"type":"Point"}
}