{
  "type": "Feature",
  "properties": {
    "iso:country":"CH",
    "sg:address":"M\u00e4ttenwil 343",
    "sg:city":"Brittnau",
    "sg:orig_category":"Verarbeitung von Milch Verwertung von Milch",
    "sg:postcode":"4805",
    "sg:province":"Aargau",
    "wof:name":"K\u00e4sereigenossenschaft Aesch",
    "wof:placetype":"venue"
},
  "geometry": {"coordinates":[8.2392454147,47.261920929],"type":"Point"}
}