{
  "type": "Feature",
  "properties": {
    "iso:country":"CH",
    "sg:address":"Chemin Des Pervenches 16",
    "sg:city":"Bassins",
    "sg:orig_category":"Herstellung von Oberbekleidung",
    "sg:postcode":"1269",
    "sg:province":"Vaud",
    "wof:name":"Bestinclass, Linther Tiberghien Maya",
    "wof:placetype":"venue"
},
  "geometry": {"coordinates":[6.2272801399,46.4714698792],"type":"Point"}
}