{
  "type": "Feature",
  "properties": {
    "iso:country":"CH",
    "sg:address":"Avenue Dumas 20 1206 Gen\u00e8ve. Postfach",
    "sg:city":"Gen\u00e8ve",
    "sg:orig_category":"Grosshandel mit sonstigen Gebrauchs U Verbrauchsg\u00fctern Handelsvermittlung von Brennstoffen, Erzen, M",
    "sg:phone":"+41 22 702 07 00",
    "sg:postcode":"1201",
    "sg:province":"Gen\u00e8ve",
    "wof:name":"Earneast Sa",
    "wof:placetype":"venue"
},
  "geometry": {"coordinates":[6.156662941,46.1911964417],"type":"Point"}
}