{
  "type": "Feature",
  "properties": {
    "iso:country":"CH",
    "sg:address":"St\u00f6cklen 36",
    "sg:city":"Meierskappel",
    "sg:orig_category":"Softwareentwicklung U beratung",
    "sg:phone":"+41 41 790 72 50",
    "sg:postcode":"6344",
    "sg:province":"Luzern",
    "wof:name":"Elektronik Und Netzwerk Sch\u00f6ni Daniel, Ingenieurb\u00fcro",
    "wof:placetype":"venue"
},
  "geometry": {"coordinates":[8.4387817383,47.1212921143],"type":"Point"}
}