{
  "type": "Feature",
  "properties": {
    "iso:country":"CH",
    "sg:address":"Ciseri Via Antonio 23",
    "sg:city":"Locarno",
    "sg:orig_category":"Verwaltung von Immobilien",
    "sg:phone":"+41 31 971 53 02",
    "sg:postcode":"6600",
    "sg:province":"Ticino",
    "wof:name":"Begreso Ag",
    "wof:placetype":"venue"
},
  "geometry": {"coordinates":[7.4381527901,46.9262199402],"type":"Point"}
}