{
  "type": "Feature",
  "properties": {
    "iso:country":"CH",
    "sg:address":"Lauetstrasse 13",
    "sg:city":"Otelfingen",
    "sg:classifiers":[
        {
            "category":"Professional",
            "subcategory":"Detective & Security Services",
            "type":"Services"
        }
    ],
    "sg:phone":"+41 18442550",
    "sg:postcode":"8112",
    "sg:province":"Z\u00fcrich",
    "sg:tags":[
        "abrasion",
        "protection"
    ],
    "wof:name":"B\u00fchrer Ag",
    "wof:placetype":"venue"
},
  "geometry": {"coordinates":[8.405808,47.457127],"type":"Point"}
}