{
  "type": "Feature",
  "properties": {
    "addr:full":"Bielstrasse 11 Bellach Solothurn 4512",
    "addr:housenumber":"11",
    "addr:postcode":"4512",
    "addr:street":"Bielstrasse",
    "iso:country":"CH",
    "sg:address":"Bielstrasse 11",
    "sg:city":"Bellach",
    "sg:classifiers":[
        {
            "category":"Manufacturing",
            "subcategory":"Rubber & Plastics",
            "type":"Manufacturing & Wholesale Goods"
        }
    ],
    "sg:phone":"+41 32 618 21 77",
    "sg:postcode":"4512",
    "sg:province":"Solothurn",
    "sg:tags":[
        "part",
        "cnc",
        "milled"
    ],
    "wof:name":"Kurt Bl\u00e4si",
    "wof:placetype":"venue"
},
  "geometry": {"coordinates":[7.50131,47.210533],"type":"Point"}
}