{
  "type": "Feature",
  "properties": {
    "iso:country":"CH",
    "sg:address":"Oltnerstrasse",
    "sg:city":"Egerkingen",
    "sg:orig_category":"Allgemeiner Hoch U Tiefbau Herstellung von Konstruktionsteilen, Fertigbauteilen U Ausbauelementen au",
    "sg:phone":"+41 62 398 21 41",
    "sg:postcode":"4622",
    "sg:province":"Solothurn",
    "wof:name":"Okal Haus Ag",
    "wof:placetype":"venue"
},
  "geometry": {"coordinates":[7.805119,47.323364],"type":"Point"}
}