{
  "type": "Feature",
  "properties": {
    "iso:country":"CH",
    "sg:address":"Gordemo Via 15",
    "sg:city":"Gordola",
    "sg:orig_category":"G\u00fcterbef\u00f6rderung im Strassenverkehr",
    "sg:postcode":"6596",
    "sg:province":"Ticino",
    "wof:name":"Sommer Trasporti Sagl",
    "wof:placetype":"venue"
},
  "geometry": {"coordinates":[8.8604202271,46.180934906],"type":"Point"}
}