{
  "type": "Feature",
  "properties": {
    "iso:country":"CH",
    "sg:address":"Via Cattori 5",
    "sg:city":"Locarno",
    "sg:orig_category":"Allgemeiner Hoch U Tiefbau Hoch U Tiefbau",
    "sg:phone":"+41 91 751 44 22",
    "sg:postcode":"6600",
    "sg:province":"Ticino",
    "wof:name":"Luigi Roncoroni Impresa Costruzioni",
    "wof:placetype":"venue"
},
  "geometry": {"coordinates":[8.800154,46.167923],"type":"Point"}
}