{
  "type": "Feature",
  "properties": {
    "iso:country":"CH",
    "sg:address":"Albisriederstrasse 390",
    "sg:city":"Z\u00fcrich",
    "sg:orig_category":"Autogaragen",
    "sg:phone":"+41 14319019",
    "sg:postcode":"8047",
    "sg:province":"Z\u00fcrich",
    "wof:name":"Riccardo Scanferla Garage Europabr\u00fccke",
    "wof:placetype":"venue"
},
  "geometry": {"coordinates":[8.483015,47.374565],"type":"Point"}
}