{
  "type": "Feature",
  "properties": {
    "iso:country":"CH",
    "sg:address":"Ennetb\u00fchlstrasse 3",
    "sg:city":"Horgen",
    "sg:orig_category":"Sportvereine Ballsport Handball",
    "sg:postcode":"8810",
    "sg:province":"Z\u00fcrich",
    "wof:name":"Spose Kilchberg",
    "wof:placetype":"venue"
},
  "geometry": {"coordinates":[8.5522918701,47.3188400269],"type":"Point"}
}