{
  "type": "Feature",
  "properties": {
    "iso:country":"CH",
    "sg:address":"Neugasse 169",
    "sg:city":"Berlingen",
    "sg:orig_category":"Sportvereine Turnen",
    "sg:phone":"+41 52 761 17 79",
    "sg:postcode":"8267",
    "sg:province":"Thurgau",
    "wof:name":"Turnverein Stv Berlingen",
    "wof:placetype":"venue"
},
  "geometry": {"coordinates":[9.0197257996,47.6736221313],"type":"Point"}
}