{
  "type": "Feature",
  "properties": {
    "iso:country":"CH",
    "sg:address":"6675",
    "sg:city":"Cevio",
    "sg:orig_category":"Erbringung von Dienstleistungen f\u00fcr Unternehmen",
    "sg:phone":"+41 91 754 18 24",
    "sg:postcode":"6675",
    "sg:province":"Ticino",
    "wof:name":"Oberholzer Sabina - Tagli Renato - Knobel Ray",
    "wof:placetype":"venue"
},
  "geometry": {"coordinates":[8.602025032,46.3169059753],"type":"Point"}
}