{
  "type": "Feature",
  "properties": {
    "iso:country":"CH",
    "sg:address":"Seftigenstrasse 212",
    "sg:city":"Wabern",
    "sg:orig_category":"Detailhandel mit Spielwaren",
    "sg:phone":"+41 31 961 26 36",
    "sg:postcode":"3084",
    "sg:province":"Bern",
    "wof:name":"Matthias Kupferschmid Modelleisenbahnen",
    "wof:placetype":"venue"
},
  "geometry": {"coordinates":[7.4485402107,46.9298171997],"type":"Point"}
}