{
  "type": "Feature",
  "properties": {
    "iso:country":"CH",
    "sg:address":"Corraterie Rue De La 11 1204 Gen\u00e8ve. Postfach",
    "sg:city":"Gen\u00e8ve",
    "sg:orig_category":"Pensionskassen",
    "sg:postcode":"1204",
    "sg:province":"Gen\u00e8ve",
    "wof:name":"Fonds Compl\u00e9mentaire Suisse Des Ouvriers Nestl\u00e9",
    "wof:placetype":"venue"
},
  "geometry": {"coordinates":[6.8568601608,46.4530181885],"type":"Point"}
}