{
  "type": "Feature",
  "properties": {
    "iso:country":"CH",
    "sg:address":"Wolfhaldenweg 4",
    "sg:city":"Br\u00fcttisellen",
    "sg:orig_category":"Baugewerbe",
    "sg:phone":"+41 18336252",
    "sg:postcode":"8306",
    "sg:province":"Z\u00fcrich",
    "wof:name":"Alexander Michel Heizungsdemontagen",
    "wof:placetype":"venue"
},
  "geometry": {"coordinates":[8.632319,47.419254],"type":"Point"}
}