{
  "type": "Feature",
  "properties": {
    "iso:country":"CH",
    "sg:address":"Tellistrasse 66",
    "sg:city":"Aarau",
    "sg:orig_category":"Non-Classified Establishments",
    "sg:postcode":"5000",
    "sg:province":"Aargau",
    "wof:name":"Spuntino, Uzgur + Co.",
    "wof:placetype":"venue"
},
  "geometry": {"coordinates":[8.0581693649,47.3975334167],"type":"Point"}
}