{
  "type": "Feature",
  "properties": {
    "iso:country":"CH",
    "sg:address":"Feldstrasse 103 4123 Allschwil. Postfach",
    "sg:city":"Allschwil",
    "sg:orig_category":"S\u00e4ge, Hobel U Holzimpr\u00e4gnierwerke",
    "sg:postcode":"4123",
    "sg:province":"Basel-Landschaft",
    "wof:name":"Holkon Sch\u00f6neck Marco Holzkonversierung, Holzsch\u00e4dlingsbek\u00e4mpfung, Geb\u00e4udeisolation Usw",
    "wof:placetype":"venue"
},
  "geometry": {"coordinates":[7.5535559654,47.5490226746],"type":"Point"}
}