{
  "type": "Feature",
  "properties": {
    "iso:country":"CH",
    "sg:address":"Leimenstrasse 49",
    "sg:city":"Basel",
    "sg:orig_category":"Grosshandel mit Geschenkartikeln U Souvenirs Herstellung von sonstigen Erzeugnissen",
    "sg:phone":"+41 62 822 04 66",
    "sg:postcode":"4051",
    "sg:province":"Basel-Stadt",
    "wof:name":"A & L Products Ag",
    "wof:placetype":"venue"
},
  "geometry": {"coordinates":[8.0694160461,47.390625],"type":"Point"}
}