{
  "type": "Feature",
  "properties": {
    "iso:country":"CH",
    "sg:address":"Grundstrasse",
    "sg:city":"Fehraltorf",
    "sg:orig_category":"Vermietung U Verpachtung von eigenen Immobilien Vermittlung von Immobilien",
    "sg:phone":"+41 55 210 68 78",
    "sg:postcode":"8320",
    "sg:province":"Z\u00fcrich",
    "wof:name":"Sedes Immobilien Ag",
    "wof:placetype":"venue"
},
  "geometry": {"coordinates":[8.8174009323,47.2270698547],"type":"Point"}
}