{
  "type": "Feature",
  "properties": {
    "iso:country":"CH",
    "sg:address":"1807 Blonay. Postfach",
    "sg:city":"Blonay",
    "sg:orig_category":"Detailhandel mit B\u00fcchern, Zeitungen, Schreib U Papeteriewaren",
    "sg:postcode":"1807",
    "sg:province":"Vaud",
    "wof:name":"Sarbach F.",
    "wof:placetype":"venue"
},
  "geometry": {"coordinates":[6.894983,46.46513],"type":"Point"}
}