{
  "type": "Feature",
  "properties": {
    "iso:country":"CH",
    "sg:address":"Ruessenstrasse 5",
    "sg:city":"Baar",
    "sg:classifiers":[
        {
            "category":"Manufacturing",
            "subcategory":"Glass & Minerals",
            "type":"Manufacturing & Wholesale Goods"
        }
    ],
    "sg:phone":"+41 41 761 71 65",
    "sg:postcode":"6340",
    "sg:province":"Zug",
    "sg:tags":[
        "fire-proof"
    ],
    "wof:name":"Allglas Technik Gmbh",
    "wof:placetype":"venue"
},
  "geometry": {"coordinates":[8.5635023117,47.2124977112],"type":"Point"}
}