{
  "type": "Feature",
  "properties": {
    "iso:country":"CH",
    "sg:address":"Wylihof",
    "sg:city":"Luterbach",
    "sg:orig_category":"Unclassifiable Establishments",
    "sg:postcode":"4542",
    "sg:province":"Solothurn",
    "wof:name":"Coninvest Deitingen S.\u00e0.r.l",
    "wof:placetype":"venue"
},
  "geometry": {"coordinates":[7.5899610519,47.2242546082],"type":"Point"}
}