{
  "type": "Feature",
  "properties": {
    "iso:country":"CH",
    "sg:address":"Susann-m\u00fcller-strasse 6",
    "sg:city":"Wattwil",
    "sg:orig_category":"Detailhandel mit Antiquit\u00e4ten U Gebrauchtwaren in Verkaufsr\u00e4umen",
    "sg:phone":"+41 71 988 60 39",
    "sg:postcode":"9630",
    "sg:province":"St. Gallen",
    "wof:name":"Gerehbab Ag",
    "wof:placetype":"venue"
},
  "geometry": {"coordinates":[9.085453,47.301479],"type":"Point"}
}