{
  "type": "Feature",
  "properties": {
    "iso:country":"CH",
    "sg:address":"1977",
    "sg:city":"Icogne",
    "sg:orig_category":"Haltung von Gefl\u00fcgel",
    "sg:phone":"+41 27 483 24 46",
    "sg:postcode":"1977",
    "sg:province":"Valais",
    "wof:name":"Oscar Mayor Parc Avicole",
    "wof:placetype":"venue"
},
  "geometry": {"coordinates":[7.438272953,46.2908935547],"type":"Point"}
}