{
  "type": "Feature",
  "properties": {
    "addr:full":"Aarburgerstrasse 176 Olten Solothurn 4600",
    "addr:housenumber":"176",
    "addr:postcode":"4600",
    "addr:street":"Aarburgerstrasse",
    "iso:country":"CH",
    "sg:address":"Aarburgerstrasse 176",
    "sg:city":"Olten",
    "sg:classifiers":[
        {
            "category":"Professional",
            "subcategory":"Engineering",
            "type":"Services"
        }
    ],
    "sg:phone":"+41 62 296 48 12",
    "sg:postcode":"4600",
    "sg:province":"Solothurn",
    "sg:tags":[
        "civil",
        "underground"
    ],
    "wof:name":"Gebr\u00fcder Meier Ag",
    "wof:placetype":"venue"
},
  "geometry": {"coordinates":[7.907701,47.343056],"type":"Point"}
}