{
  "type": "Feature",
  "properties": {
    "iso:country":"CH",
    "sg:address":"Avenue De Chailly 59 1000 Lausanne. Postfach",
    "sg:city":"Lausanne",
    "sg:orig_category":"RESTAURANTS: TEA-ROOMS",
    "sg:postcode":"1002",
    "sg:province":"Vaud",
    "wof:name":"Cottet Claudine",
    "wof:placetype":"venue"
},
  "geometry": {"coordinates":[6.6558909416,46.5230979919],"type":"Point"}
}