{
  "type": "Feature",
  "properties": {
    "iso:country":"CH",
    "sg:address":"Rathausplatz 3",
    "sg:city":"Stans",
    "sg:orig_category":"Verwaltung der Rechtspflege, Gerichte",
    "sg:phone":"+41 41 618 42 60",
    "sg:postcode":"6370",
    "sg:province":"Nidwalden",
    "wof:name":"Staatsanwaltschaft Des Kantons Nidwalden",
    "wof:placetype":"venue"
},
  "geometry": {"coordinates":[8.3666067123,46.9560012817],"type":"Point"}
}