{
  "type": "Feature",
  "properties": {
    "iso:country":"CH",
    "sg:address":"Rebenweg 2",
    "sg:city":"Laufen",
    "sg:orig_category":"Unclassifiable Establishments",
    "sg:postcode":"4242",
    "sg:province":"Basel-Landschaft",
    "wof:name":"Schneider Jos. Ag",
    "wof:placetype":"venue"
},
  "geometry": {"coordinates":[7.4991679192,47.4235458374],"type":"Point"}
}