{
  "type": "Feature",
  "properties": {
    "iso:country":"CH",
    "sg:address":"Friedlisbergstrasse 20",
    "sg:city":"Rudolfstetten",
    "sg:orig_category":"Haltung von Rindern",
    "sg:postcode":"8964",
    "sg:province":"Aargau",
    "wof:name":"Weidgenossenschaft Rudolfstetten",
    "wof:placetype":"venue"
},
  "geometry": {"coordinates":[8.3816747665,47.3675231934],"type":"Point"}
}