{
  "type": "Feature",
  "properties": {
    "addr:full":"T\u00f6sstalstrasse 84 Turbenthal Z\u00fcrich 8488",
    "addr:housenumber":"84",
    "addr:postcode":"8488",
    "addr:street":"Toesstalstrasse",
    "iso:country":"CH",
    "sg:address":"T\u00f6sstalstrasse 84",
    "sg:city":"Turbenthal",
    "sg:orig_category":"Aktivit\u00e4ten der Generalunternehmen im Baugewerbe Allgemeiner Hoch U Tiefbau",
    "sg:phone":"+41 27 207 11 15",
    "sg:postcode":"8488",
    "sg:province":"Z\u00fcrich",
    "wof:name":"Arcidea, Dussex Et Fournier Construction G\u00e9n\u00e9rale",
    "wof:placetype":"venue"
},
  "geometry": {"coordinates":[7.338803,46.195984],"type":"Point"}
}