{
  "type": "Feature",
  "properties": {
    "iso:country":"CH",
    "sg:address":"Stockerstrasse 44 8002 Z\u00fcrich. Postfach",
    "sg:city":"Z\u00fcrich",
    "sg:orig_category":"Wirtschaftspr\u00fcfung, Steuerberatung U Treuhand",
    "sg:phone":"+41 12810221",
    "sg:postcode":"8002",
    "sg:province":"Z\u00fcrich",
    "wof:name":"H\u00fcsser + Gm\u00fcr Ag Treuhand Und Revisionsgesellschaft",
    "wof:placetype":"venue"
},
  "geometry": {"coordinates":[8.5346040726,47.3680343628],"type":"Point"}
}