{
  "type": "Feature",
  "properties": {
    "iso:country":"CH",
    "sg:address":"Blumenstrasse 11",
    "sg:city":"Goldach",
    "sg:orig_category":"Detailhandel mit Boden U Wandbel\u00e4gen ohne Teppiche Detailhandel mit Teppichen",
    "sg:phone":"+41 71 841 08 87",
    "sg:postcode":"9403",
    "sg:province":"St. Gallen",
    "wof:name":"B\u00fcrki Ag Spannteppiche & Bodenbel\u00e4ge",
    "wof:placetype":"venue"
},
  "geometry": {"coordinates":[9.467617,47.475544],"type":"Point"}
}