{
  "type": "Feature",
  "properties": {
    "addr:full":"Mollis Glarus 8753",
    "addr:postcode":"8753",
    "addr:street":"Glarus",
    "iso:country":"CH",
    "sg:city":"Mollis",
    "sg:orig_category":"Immobilien U Baugewerbe, Bauhandwerk",
    "sg:postcode":"8753",
    "sg:province":"Glarus",
    "wof:name":"L\u00e4derach H\u00e4mmerli K\u00fchlanlagen",
    "wof:placetype":"venue"
},
  "geometry": {"coordinates":[9.074525,47.091438],"type":"Point"}
}