{
  "type": "Feature",
  "properties": {
    "addr:full":"Bahnhofstrasse 13 Visp Valais 3930",
    "addr:housenumber":"13",
    "addr:postcode":"3930",
    "addr:street":"Bahnhofstrasse",
    "iso:country":"CH",
    "sg:address":"Bahnhofstrasse 13",
    "sg:city":"Visp",
    "sg:orig_category":"Detailhandel mit B\u00fcchern, Zeitungen, Schreib U Papeteriewaren Detailhandel mit Zeitungen U Zeitschri",
    "sg:phone":"+41 27 946 53 04",
    "sg:postcode":"3930",
    "sg:province":"Valais",
    "wof:name":"Kiosk, Pfaffen-theler Erika",
    "wof:placetype":"venue"
},
  "geometry": {"coordinates":[7.881687,46.292767],"type":"Point"}
}