{
  "type": "Feature",
  "properties": {
    "iso:country":"CH",
    "sg:address":"Hauptstrasse 76f",
    "sg:city":"Jenaz",
    "sg:classifiers":[
        {
            "category":"Building & Trades",
            "subcategory":"Electrical",
            "type":"Services"
        }
    ],
    "sg:phone":"+41 81 332 15 51",
    "sg:postcode":"7233",
    "sg:province":"Graubunden",
    "sg:tags":[
        "installation"
    ],
    "wof:name":"Hans Gantenbein Ag",
    "wof:placetype":"venue"
},
  "geometry": {"coordinates":[9.711807251,46.9337348938],"type":"Point"}
}