{
  "type": "Feature",
  "properties": {
    "iso:country":"CH",
    "sg:address":"Klosterhof 6390 Engelberg. Postfach",
    "sg:city":"Engelberg",
    "sg:orig_category":"Verwertung von Milch",
    "sg:postcode":"6390",
    "sg:province":"Obwalden",
    "wof:name":"Schauk\u00e4serei Fam. Odermatt Gmbh",
    "wof:placetype":"venue"
},
  "geometry": {"coordinates":[8.4081554413,46.819770813],"type":"Point"}
}