{
  "type": "Feature",
  "properties": {
    "iso:country":"CH",
    "sg:address":"Ringstrasse 43",
    "sg:city":"Z\u00fcrich",
    "sg:orig_category":"Unternehmensberatung",
    "sg:phone":"+41 12620690",
    "sg:postcode":"8057",
    "sg:province":"Z\u00fcrich",
    "wof:name":"Dr.hellmut Hungerb\u00fchler Steuer-& Wirtschaftsberatung",
    "wof:placetype":"venue"
},
  "geometry": {"coordinates":[8.5418233871,47.4031105042],"type":"Point"}
}