{
  "type": "Feature",
  "properties": {
    "iso:country":"CH",
    "sg:address":"En Clarens",
    "sg:city":"Gland",
    "sg:orig_category":"Autogaragen",
    "sg:phone":"+41 22 364 10 30",
    "sg:postcode":"1196",
    "sg:province":"Vaud",
    "wof:name":"Roger Wulliamoz Garage Citro\u00ebn",
    "wof:placetype":"venue"
},
  "geometry": {"coordinates":[6.26145,46.422401],"type":"Point"}
}