{
  "type": "Feature",
  "properties": {
    "iso:country":"CH",
    "sg:address":"Seeblickstrasse 26",
    "sg:city":"T\u00fcbach",
    "sg:orig_category":"Kauf U Verkauf von Immobilien auf eigene Rechnung Vermietung U Verpachtung von eigenen Immobilien",
    "sg:phone":"+41 71 845 50 08",
    "sg:postcode":"9327",
    "sg:province":"St. Gallen",
    "wof:name":"Inka Seeblick Gmbh",
    "wof:placetype":"venue"
},
  "geometry": {"coordinates":[9.447218895,47.4877281189],"type":"Point"}
}