{
  "type": "Feature",
  "properties": {
    "iso:country":"CH",
    "sg:address":"Bachtelstrasse 6 Effretikon 8308 Horben B. Illnau. Postfach",
    "sg:city":"Tagelswangen",
    "sg:orig_category":"Allgemeiner Hoch U Tiefbau",
    "sg:postcode":"8317",
    "sg:province":"Z\u00fcrich",
    "wof:name":"Bernsteiner & Trachsler Gmbh",
    "wof:placetype":"venue"
},
  "geometry": {"coordinates":[8.723925,47.407471],"type":"Point"}
}