{
  "type": "Feature",
  "properties": {
    "iso:country":"CH",
    "sg:address":"Pasteur Via Luigi 1",
    "sg:city":"Chiasso",
    "sg:orig_category":"RESTAURANTS: TEA-ROOMS",
    "sg:postcode":"6830",
    "sg:province":"Ticino",
    "wof:name":"Andy's Fine Food Gmbh",
    "wof:placetype":"venue"
},
  "geometry": {"coordinates":[8.8453989029,47.4204826355],"type":"Point"}
}