{
  "type": "Feature",
  "properties": {
    "iso:country":"CH",
    "sg:address":"Avenue De La D\u00f4le 2 1000 Lausanne. Postfach",
    "sg:city":"Lausanne",
    "sg:orig_category":"Detailhandel mit Waren verschiedener Art, Hauptrichtung Nahrungsmittel",
    "sg:postcode":"1003",
    "sg:province":"Vaud",
    "wof:name":"Mayor & Partenaire",
    "wof:placetype":"venue"
},
  "geometry": {"coordinates":[6.6454339027,46.5214424133],"type":"Point"}
}