{
  "type": "Feature",
  "properties": {
    "addr:full":"Pelikanweg 8 Basel Basel-Stadt 4054",
    "addr:housenumber":"8",
    "addr:postcode":"4054",
    "addr:street":"Pelikanweg",
    "iso:country":"CH",
    "sg:address":"Pelikanweg 8",
    "sg:city":"Basel",
    "sg:orig_category":"Allgemeiner Hoch U Tiefbau",
    "sg:phone":"+41 79 243 79 89",
    "sg:postcode":"4054",
    "sg:province":"Basel-Stadt",
    "wof:name":"Dimba Immler Dieter",
    "wof:placetype":"venue"
},
  "geometry": {"coordinates":[7.58113,47.5499],"type":"Point"}
}