{
  "type": "Feature",
  "properties": {
    "iso:country":"CH",
    "sg:address":"Vogt Bvd Carl- 93 1205 Gen\u00e8ve. Postfach",
    "sg:city":"Gen\u00e8ve",
    "sg:orig_category":"Detektivb\u00fcros U \u00dcberwachung",
    "sg:postcode":"1205",
    "sg:province":"Gen\u00e8ve",
    "wof:name":"Capitol Guard Group, Selinger + H\u00e4mmerle",
    "wof:placetype":"venue"
},
  "geometry": {"coordinates":[9.8381910324,46.4970664978],"type":"Point"}
}