{
  "type": "Feature",
  "properties": {
    "iso:country":"CH",
    "sg:address":"Rainstrasse",
    "sg:city":"Jona",
    "sg:orig_category":"Bezirks, Sekundar, Realschulen, Oberstufe der Primarschulen",
    "sg:phone":"+41 55 212 56 51",
    "sg:postcode":"8645",
    "sg:province":"St. Gallen",
    "wof:name":"Realschule Rain",
    "wof:placetype":"venue"
},
  "geometry": {"coordinates":[8.842101,47.233234],"type":"Point"}
}