{
  "type": "Feature",
  "properties": {
    "iso:country":"CH",
    "sg:address":"Signalweg 2",
    "sg:city":"Romanshorn",
    "sg:classifiers":[
        {
            "category":"Restaurant",
            "type":"Food & Drink"
        }
    ],
    "sg:phone":"+41 81 833 11 38",
    "sg:postcode":"8590",
    "sg:province":"Thurgau",
    "wof:name":"Restaurant Signalst\u00fcbli",
    "wof:placetype":"venue"
},
  "geometry": {"coordinates":[9.8381900787,46.4970588684],"type":"Point"}
}