{
  "type": "Feature",
  "properties": {
    "iso:country":"CH",
    "sg:address":"D\u00f6rflistrasse 10",
    "sg:city":"Z\u00fcrich",
    "sg:orig_category":"Finanzierungsinstitutionen",
    "sg:phone":"+41 13130560",
    "sg:postcode":"8057",
    "sg:province":"Z\u00fcrich",
    "wof:name":"Eutex-finanz Ag",
    "wof:placetype":"venue"
},
  "geometry": {"coordinates":[8.5493278503,47.4041442871],"type":"Point"}
}