{
  "type": "Feature",
  "properties": {
    "iso:country":"CH",
    "sg:address":"1418",
    "sg:city":"Vuarrens",
    "sg:orig_category":"Haltung von Rindern",
    "sg:postcode":"1418",
    "sg:province":"Vaud",
    "wof:name":"Syndicat D'\u00e9levage Bovin De Vuarrens",
    "wof:placetype":"venue"
},
  "geometry": {"coordinates":[6.6476688385,46.6862792969],"type":"Point"}
}