{
  "type": "Feature",
  "properties": {
    "iso:country":"CH",
    "sg:address":"Peter Merian-strasse 48",
    "sg:city":"Basel",
    "sg:classifiers":[
        {
            "category":"Professional",
            "subcategory":"Business Services",
            "type":"Services"
        }
    ],
    "sg:phone":"+41 61 284 74 74",
    "sg:postcode":"4002",
    "sg:province":"Basel-Stadt",
    "sg:tags":[
        "consulting",
        "export"
    ],
    "wof:name":"Lamprecht Transport Ag",
    "wof:placetype":"venue"
},
  "geometry": {"coordinates":[7.5946059227,47.5476036072],"type":"Point"}
}