{
  "type": "Feature",
  "properties": {
    "iso:country":"CH",
    "sg:address":"Uraniastrasse 35 8001 Z\u00fcrich. Postfach",
    "sg:city":"Z\u00fcrich",
    "sg:orig_category":"Reiseb\u00fcros U Reiseveranstalter",
    "sg:phone":"+41 12111150",
    "sg:postcode":"8021",
    "sg:province":"Z\u00fcrich",
    "wof:name":"Reiseb\u00fcro Leibacher Ag",
    "wof:placetype":"venue"
},
  "geometry": {"coordinates":[8.5354251862,47.3731193542],"type":"Point"}
}