{
  "type": "Feature",
  "properties": {
    "iso:country":"CH",
    "sg:address":"Route De Lausanne 87",
    "sg:city":"Mont-sur-lausanne",
    "sg:orig_category":"Grosshandel mit Wein U Spirituosen",
    "sg:phone":"+41 14615237",
    "sg:postcode":"1052",
    "sg:province":"Vaud",
    "wof:name":"Tre Mulini Ag",
    "wof:placetype":"venue"
},
  "geometry": {"coordinates":[7.9634141922,47.5426521301],"type":"Point"}
}