{
  "type": "Feature",
  "properties": {
    "addr:full":"Paradiesgasse 19 Chur Graubunden 7000",
    "addr:housenumber":"19",
    "addr:postcode":"7000",
    "addr:street":"Paradiesgasse",
    "iso:country":"CH",
    "sg:address":"Paradiesgasse 19",
    "sg:city":"Chur",
    "sg:orig_category":"Arztpraxen",
    "sg:phone":"+41 81 413 11 50",
    "sg:postcode":"7000",
    "sg:province":"Graubunden",
    "wof:name":"Dr.med.gian-andrea Giovanoli Spezialarzt Fmh",
    "wof:placetype":"venue"
},
  "geometry": {"coordinates":[9.829301,46.802574],"type":"Point"}
}