{
  "type": "Feature",
  "properties": {
    "iso:country":"CH",
    "sg:address":"Industriestrasse 6",
    "sg:city":"Dietlikon",
    "sg:orig_category":"Grosshandel mit Radio U Fernsehger\u00e4ten",
    "sg:postcode":"8305",
    "sg:province":"Z\u00fcrich",
    "wof:name":"Ep Electronicpartner Ag Waren Der Unterhaltungselektronik, Telekommunikation Usw.; Kauf, Vermittlung, Verkauf",
    "wof:placetype":"venue"
},
  "geometry": {"coordinates":[8.6252803802,47.4160118103],"type":"Point"}
}