{
  "type": "Feature",
  "properties": {
    "addr:full":"Place De La Fusterie 7 Gen\u00e8ve Gen\u00e8ve 1204",
    "addr:housenumber":"7",
    "addr:postcode":"1204",
    "addr:street":"Place De La Fusterie",
    "iso:country":"CH",
    "sg:address":"Place De La Fusterie 7",
    "sg:city":"Gen\u00e8ve",
    "sg:orig_category":"Advokaturb\u00fcros",
    "sg:phone":"+41 22 310 30 64",
    "sg:postcode":"1204",
    "sg:province":"Gen\u00e8ve",
    "wof:name":"Olivier Weber-caflisch Etude D'avocat",
    "wof:placetype":"venue"
},
  "geometry": {"coordinates":[6.146242,46.203869],"type":"Point"}
}