{
  "type": "Feature",
  "properties": {
    "iso:country":"CH",
    "sg:address":"Lausanne Rue De 30",
    "sg:city":"Sion",
    "sg:orig_category":"Herstellung von D\u00fcngemitteln U Stickstoffverbindungen",
    "sg:phone":"+41 61 421 62 69",
    "sg:postcode":"1950",
    "sg:province":"Valais",
    "wof:name":"Orgater Ag",
    "wof:placetype":"venue"
},
  "geometry": {"coordinates":[7.577173233,47.5409622192],"type":"Point"}
}