{
  "type": "Feature",
  "properties": {
    "iso:country":"CH",
    "sg:address":"Zentralstrasse 54a",
    "sg:city":"Biel/bienne",
    "sg:orig_category":"Maler U Glasergewerbe Malerei",
    "sg:postcode":"2502",
    "sg:province":"Bern",
    "wof:name":"Sch\u00fctz Gmbh",
    "wof:placetype":"venue"
},
  "geometry": {"coordinates":[7.2463879585,47.1369400024],"type":"Point"}
}