{
  "type": "Feature",
  "properties": {
    "iso:country":"CH",
    "sg:address":"Im Steinhof 7",
    "sg:city":"B\u00fclach",
    "sg:orig_category":"Massagestudios",
    "sg:phone":"+41 19305976",
    "sg:postcode":"8180",
    "sg:province":"Z\u00fcrich",
    "wof:name":"Carsten Lizio Massagen",
    "wof:placetype":"venue"
},
  "geometry": {"coordinates":[8.8119430542,47.3283843994],"type":"Point"}
}