{
  "type": "Feature",
  "properties": {
    "iso:country":"CH",
    "sg:address":"Haus 38c",
    "sg:city":"Zernez",
    "sg:orig_category":"Sanit\u00e4r, Heizungs U L\u00fcftungsinstallation",
    "sg:phone":"+41 81 856 11 16",
    "sg:postcode":"7530",
    "sg:province":"Graubunden",
    "wof:name":"Issler & Gross Ag Heizung Sanit\u00e4r 24h Service",
    "wof:placetype":"venue"
},
  "geometry": {"coordinates":[10.0946302414,46.7002983093],"type":"Point"}
}