{
  "type": "Feature",
  "properties": {
    "iso:country":"CH",
    "sg:address":"Route De St-nicolas-de-fl\u00fce 30",
    "sg:city":"Fribourg",
    "sg:classifiers":[
        {
            "category":"Social Services",
            "subcategory":"Retirement Home",
            "type":"Services"
        }
    ],
    "sg:phone":"+41 71 966 26 16",
    "sg:postcode":"1700",
    "sg:province":"Fribourg",
    "sg:tags":[
        "pflegeheime",
        "u",
        "alters"
    ],
    "wof:name":"Villa F.betreuungsbed\u00fcrftige \u00e4ltere Menschen",
    "wof:placetype":"venue"
},
  "geometry": {"coordinates":[8.995559,47.479946],"type":"Point"}
}