{
  "type": "Feature",
  "properties": {
    "addr:full":"Post D\u00fcrren\u00e4sch Aargau 5724",
    "addr:postcode":"5724",
    "iso:country":"CH",
    "sg:address":"Post",
    "sg:city":"D\u00fcrren\u00e4sch",
    "sg:classifiers":[
        {
            "category":"Banks & Credit Unions",
            "subcategory":"Bank",
            "type":"Services"
        }
    ],
    "sg:phone":"+41 4164541526",
    "sg:postcode":"5724",
    "sg:province":"Aargau",
    "wof:name":"Hypothekarbank Lenzburg",
    "wof:placetype":"venue"
},
  "geometry": {"coordinates":[8.157849,47.32122],"type":"Point"}
}