{
  "type": "Feature",
  "properties": {
    "iso:country":"CH",
    "sg:address":"Stationsstrasse 5 6373 Ennetb\u00fcrgen. Postfach 22",
    "sg:city":"Ennetb\u00fcrgen",
    "sg:orig_category":"Detailhandel mit M\u00f6beln U Haushaltsgegenst\u00e4nden Innendekorationsateliers",
    "sg:phone":"+41 19101278",
    "sg:postcode":"6373",
    "sg:province":"Nidwalden",
    "wof:name":"Wyder Herbert Raumgestaltung",
    "wof:placetype":"venue"
},
  "geometry": {"coordinates":[8.5885152817,47.3071060181],"type":"Point"}
}