{
  "type": "Feature",
  "properties": {
    "iso:country":"CH",
    "sg:address":"7550",
    "sg:city":"Scuol",
    "sg:orig_category":"Reiseb\u00fcros U Reiseveranstalter",
    "sg:phone":"+41 55 210 84 94",
    "sg:postcode":"7550",
    "sg:province":"Graubunden",
    "wof:name":"Turgut Oezel Reisevermittlung",
    "wof:placetype":"venue"
},
  "geometry": {"coordinates":[8.8212537766,47.2291069031],"type":"Point"}
}