{
  "type": "Feature",
  "properties": {
    "iso:country":"CH",
    "sg:address":"Baslerstrasse 91",
    "sg:city":"Trimbach",
    "sg:orig_category":"Nationale Postdienste",
    "sg:phone":"+41 62 293 40 10",
    "sg:postcode":"4632",
    "sg:province":"Solothurn",
    "wof:name":"Die Schweizerische Post",
    "wof:placetype":"venue"
},
  "geometry": {"coordinates":[7.8991398811,47.3616104126],"type":"Point"}
}