{
  "type": "Feature",
  "properties": {
    "iso:country":"CH",
    "sg:address":"Rue De Gruy\u00e8res 5",
    "sg:city":"Bulle",
    "sg:orig_category":"RESTAURANTS: TEA-ROOMS",
    "sg:phone":"+41 26 912 77 31",
    "sg:postcode":"1630",
    "sg:province":"Fribourg",
    "wof:name":"Caf\u00e9 Des Xiii-cantons",
    "wof:placetype":"venue"
},
  "geometry": {"coordinates":[7.0572919846,46.6170349121],"type":"Point"}
}