{
  "type": "Feature",
  "properties": {
    "iso:country":"CH",
    "sg:address":"Maderno Via Carlo 52",
    "sg:city":"Mendrisio",
    "sg:orig_category":"Vermietung U Verpachtung von eigenen Immobilien",
    "sg:postcode":"6850",
    "sg:province":"Ticino",
    "wof:name":"Camado Sa",
    "wof:placetype":"venue"
},
  "geometry": {"coordinates":[8.980099678,45.8877792358],"type":"Point"}
}