{
  "type": "Feature",
  "properties": {
    "addr:full":"St. Josefen-strasse 34 St.gallen St. Gallen 9000",
    "addr:housenumber":"34;st.",
    "addr:postcode":"9000",
    "addr:street":"St.Gallen",
    "iso:country":"CH",
    "sg:address":"St. Josefen-strasse 34",
    "sg:city":"St.gallen",
    "sg:orig_category":"Architektur U Ingenieurb\u00fcros",
    "sg:postcode":"9000",
    "sg:province":"St. Gallen",
    "wof:name":"Ab Atelier F\u00fcr Baumanagement Gmbh",
    "wof:placetype":"venue"
},
  "geometry": {"coordinates":[9.346902,47.422634],"type":"Point"}
}