{
  "type": "Feature",
  "properties": {
    "iso:country":"CH",
    "sg:address":"Morgartenstrasse 19",
    "sg:city":"Luzern",
    "sg:orig_category":"Interessenvertretungen",
    "sg:phone":"+41 41 210 00 66",
    "sg:postcode":"6003",
    "sg:province":"Luzern",
    "wof:name":"Stiftung Caritas-hus",
    "wof:placetype":"venue"
},
  "geometry": {"coordinates":[8.3092689514,47.047996521],"type":"Point"}
}