{
  "type": "Feature",
  "properties": {
    "iso:country":"CH",
    "sg:address":"Seestrasse 33",
    "sg:city":"Goldach",
    "sg:orig_category":"Einbau von Schreinerwaren",
    "sg:phone":"+41 71 841 08 59",
    "sg:postcode":"9403",
    "sg:province":"St. Gallen",
    "wof:name":"Ingobert Reis Schreinerei-montagen",
    "wof:placetype":"venue"
},
  "geometry": {"coordinates":[9.4779806137,47.4831695557],"type":"Point"}
}