{
  "type": "Feature",
  "properties": {
    "iso:country":"CH",
    "sg:address":"Fennernstrasse 21",
    "sg:city":"Brittnau",
    "sg:orig_category":"Erbringung von Dienstleistungen f\u00fcr Unternehmen",
    "sg:phone":"+41 62 752 56 66",
    "sg:postcode":"4805",
    "sg:province":"Aargau",
    "wof:name":"Indeko Styline Gmbh",
    "wof:placetype":"venue"
},
  "geometry": {"coordinates":[7.9331030846,47.2621803284],"type":"Point"}
}