{
  "type": "Feature",
  "properties": {
    "iso:country":"CH",
    "sg:address":"Im Zinggen 1",
    "sg:city":"Ossingen",
    "sg:orig_category":"Arztpraxen",
    "sg:phone":"+41 52 317 32 11",
    "sg:postcode":"8475",
    "sg:province":"Z\u00fcrich",
    "wof:name":"Dres Med. J. & S. Zollikofer Aerzte F\u00fcr Allg.medizin Fmh",
    "wof:placetype":"venue"
},
  "geometry": {"coordinates":[8.722736,47.609238],"type":"Point"}
}