{
  "type": "Feature",
  "properties": {
    "iso:country":"CH",
    "sg:address":"Kempttalstrasse 89",
    "sg:city":"Illnau",
    "sg:classifiers":[
        {
            "category":"Home & Garden",
            "subcategory":"Hardware",
            "type":"Retail Goods"
        }
    ],
    "sg:phone":"+41 52 346 14 84",
    "sg:postcode":"8308",
    "sg:province":"Z\u00fcrich",
    "sg:tags":[
        "steel",
        "banister"
    ],
    "wof:name":"Glauser Metallbau Ag",
    "wof:placetype":"venue"
},
  "geometry": {"coordinates":[8.722508,47.412693],"type":"Point"}
}