{
  "type": "Feature",
  "properties": {
    "iso:country":"CH",
    "sg:address":"S\u00fcdstrasse 15",
    "sg:city":"M\u00fcnsingen",
    "sg:orig_category":"Herstellung von Metallerzeugnissen ohne Maschinenbau Herstellung von Platten, Folien, Schl\u00e4uchen U P",
    "sg:phone":"+41 31 818 81 11",
    "sg:postcode":"3110",
    "sg:province":"Bern",
    "wof:name":"Arburg Ag",
    "wof:placetype":"venue"
},
  "geometry": {"coordinates":[7.5637488365,46.8666687012],"type":"Point"}
}