{
  "type": "Feature",
  "properties": {
    "iso:country":"CH",
    "sg:address":"Seestrasse 124",
    "sg:city":"Steckborn",
    "sg:orig_category":"RESTAURANTS: TEA-ROOMS",
    "sg:phone":"+41 52 761 11 29",
    "sg:postcode":"8266",
    "sg:province":"Thurgau",
    "wof:name":"W\u00fcger Willi.",
    "wof:placetype":"venue"
},
  "geometry": {"coordinates":[8.9812383652,47.667175293],"type":"Point"}
}