{
  "type": "Feature",
  "properties": {
    "iso:country":"CH",
    "sg:address":"L\u00e4ngfeldweg 29",
    "sg:city":"Biel/bienne",
    "sg:orig_category":"Detailhandel mit Gebrauchtwaren in Verkaufsr\u00e4umen",
    "sg:phone":"+41 32 341 14 13",
    "sg:postcode":"2504",
    "sg:province":"Bern",
    "wof:name":"Brockenstube Der Heilsarmee",
    "wof:placetype":"venue"
},
  "geometry": {"coordinates":[7.2751159668,47.148311615],"type":"Point"}
}