{
  "type": "Feature",
  "properties": {
    "addr:full":"Lochbachweg 1 Wila Z\u00fcrich 8492",
    "addr:housenumber":"1",
    "addr:postcode":"8492",
    "addr:street":"Lochbachweg",
    "iso:country":"CH",
    "sg:address":"Lochbachweg 1",
    "sg:city":"Wila",
    "sg:orig_category":"Architektur U Ingenieurb\u00fcros",
    "sg:phone":"+41 52 385 48 28",
    "sg:postcode":"8492",
    "sg:province":"Z\u00fcrich",
    "wof:name":"Htb Horsfjord Technisches B\u00fcro",
    "wof:placetype":"venue"
},
  "geometry": {"coordinates":[8.844427,47.420322],"type":"Point"}
}