{
  "type": "Feature",
  "properties": {
    "iso:country":"CH",
    "sg:address":"Bergstrasse 34",
    "sg:city":"Urdorf",
    "sg:orig_category":"Drogerien",
    "sg:phone":"+41 17341171",
    "sg:postcode":"8902",
    "sg:province":"Z\u00fcrich",
    "wof:name":"L\u00fcdi Frau Ruth",
    "wof:placetype":"venue"
},
  "geometry": {"coordinates":[8.4317722321,47.3898849487],"type":"Point"}
}