{
  "type": "Feature",
  "properties": {
    "iso:country":"CH",
    "sg:address":"Marzilistrasse 32",
    "sg:city":"Bern",
    "sg:orig_category":"Grosshandel mit Datenverarbeitungsger\u00e4ten Herstellung von sonstigen elektrischen Ausr\u00fcstungen",
    "sg:phone":"+41 31 311 10 15",
    "sg:postcode":"3005",
    "sg:province":"Bern",
    "wof:name":"Arco Interelectronic Gmbh",
    "wof:placetype":"venue"
},
  "geometry": {"coordinates":[7.443374157,46.942905426],"type":"Point"}
}