{
  "type": "Feature",
  "properties": {
    "iso:country":"CH",
    "sg:address":"Wald 6034 Inwil. Postfach",
    "sg:city":"Inwil",
    "sg:orig_category":"Verwertung von Milch",
    "sg:postcode":"6034",
    "sg:province":"Luzern",
    "wof:name":"K\u00e4sereigenossenschaft Wald-d\u00fcnkel",
    "wof:placetype":"venue"
},
  "geometry": {"coordinates":[8.3602247238,47.1234436035],"type":"Point"}
}