{
  "type": "Feature",
  "properties": {
    "iso:country":"CH",
    "sg:address":"Route D'orpond 48 2500 Biel/bienne. Postfach",
    "sg:city":"Biel/bienne",
    "sg:orig_category":"Fachdetailhandel in Verkaufsr\u00e4umen",
    "sg:postcode":"2504",
    "sg:province":"Bern",
    "wof:name":"Garcia F.",
    "wof:placetype":"venue"
},
  "geometry": {"coordinates":[7.2601060867,47.1253814697],"type":"Point"}
}