{
  "type": "Feature",
  "properties": {
    "iso:country":"CH",
    "sg:address":"Langnaustrasse 109",
    "sg:city":"Zollbr\u00fcck",
    "sg:orig_category":"Sanit\u00e4r, Heizungs U L\u00fcftungsinstallation",
    "sg:phone":"+41 34 496 75 04",
    "sg:postcode":"3436",
    "sg:province":"Bern",
    "wof:name":"H\u00e4nni Haustechnik Gmbh",
    "wof:placetype":"venue"
},
  "geometry": {"coordinates":[7.7523541451,46.964969635],"type":"Point"}
}