{
  "type": "Feature",
  "properties": {
    "iso:country":"CH",
    "sg:address":"Schachenweidstrasse 60",
    "sg:city":"Ebikon",
    "sg:orig_category":"Detailhandel mit Radio U Fernsehger\u00e4ten Herstellung von Radio U Fernsehger\u00e4ten sowie phono U videote",
    "sg:phone":"+41 41 422 19 19",
    "sg:postcode":"6030",
    "sg:province":"Luzern",
    "wof:name":"Acr Car Und Home Hifi Ag",
    "wof:placetype":"venue"
},
  "geometry": {"coordinates":[8.3252229691,47.0716972351],"type":"Point"}
}