{
  "type": "Feature",
  "properties": {
    "iso:country":"CH",
    "sg:address":"Rue Du Temple 5 1700 Fribourg. Postfach",
    "sg:city":"Fribourg",
    "sg:orig_category":"RESTAURANTS: TEA-ROOMS",
    "sg:phone":"+41 26 322 88 22",
    "sg:postcode":"1701",
    "sg:province":"Fribourg",
    "wof:name":"Restaurant Pans'ami B\u00fcrgy Christoph",
    "wof:placetype":"venue"
},
  "geometry": {"coordinates":[7.1536178589,46.8047180176],"type":"Point"}
}