{
  "type": "Feature",
  "properties": {
    "iso:country":"CH",
    "sg:address":"Progressastrasse 25",
    "sg:city":"Oberburg",
    "sg:orig_category":"Wohnheime",
    "sg:phone":"+41 32 322 64 88",
    "sg:postcode":"3414",
    "sg:province":"Bern",
    "wof:name":"Wohnheim Schl\u00f6ssli",
    "wof:placetype":"venue"
},
  "geometry": {"coordinates":[7.6301159859,47.0374069214],"type":"Point"}
}