{
  "type": "Feature",
  "properties": {
    "iso:country":"CH",
    "sg:address":"Route De Ch\u00eane 36 1200 Genf. Postfach",
    "sg:city":"Gen\u00e8ve",
    "sg:orig_category":"Erschliessung von Grundst\u00fccken",
    "sg:postcode":"1204",
    "sg:province":"Gen\u00e8ve",
    "wof:name":"Association Les Vernets D'arve",
    "wof:placetype":"venue"
},
  "geometry": {"coordinates":[6.168970108,46.1997413635],"type":"Point"}
}