{
  "type": "Feature",
  "properties": {
    "iso:country":"CH",
    "sg:address":"Frank-buchser-strasse 1",
    "sg:city":"Feldbrunnen",
    "sg:orig_category":"Finanzierungsinstitutionen",
    "sg:phone":"+41 32 622 05 75",
    "sg:postcode":"4532",
    "sg:province":"Solothurn",
    "wof:name":"Letras Gmbh",
    "wof:placetype":"venue"
},
  "geometry": {"coordinates":[7.5551371574,47.2196273804],"type":"Point"}
}