{
  "type": "Feature",
  "properties": {
    "iso:country":"CH",
    "sg:address":"Solothurnerstrasse 22 4710 Balsthal. Postfach",
    "sg:city":"Balsthal",
    "sg:orig_category":"RESTAURANTS: TEA-ROOMS",
    "sg:postcode":"4710",
    "sg:province":"Solothurn",
    "wof:name":"G\u00f6kpinar E.",
    "wof:placetype":"venue"
},
  "geometry": {"coordinates":[7.6888799667,47.3074913025],"type":"Point"}
}