{
  "type": "Feature",
  "properties": {
    "iso:country":"CH",
    "sg:address":"Eintrachtstrasse 25",
    "sg:city":"W\u00e4denswil",
    "sg:orig_category":"Detailhandel mit Fleisch U Fleischwaren",
    "sg:phone":"+41 17804110",
    "sg:postcode":"8820",
    "sg:province":"Z\u00fcrich",
    "wof:name":"Ernst Gerber Metzgerei-wursterei",
    "wof:placetype":"venue"
},
  "geometry": {"coordinates":[8.6719655991,47.2263450623],"type":"Point"}
}