{
  "type": "Feature",
  "properties": {
    "iso:country":"CH",
    "sg:address":"Neub\u00fchl",
    "sg:city":"Gonten",
    "sg:orig_category":"Sonstiger Grosshandel",
    "sg:phone":"+41 71 794 16 20",
    "sg:postcode":"9108",
    "sg:province":"Appenzell Innerhoden",
    "wof:name":"Rafag",
    "wof:placetype":"venue"
},
  "geometry": {"coordinates":[9.3437042236,47.3260803223],"type":"Point"}
}