{
  "type": "Feature",
  "properties": {
    "iso:country":"CH",
    "sg:address":"1902",
    "sg:city":"Evionnaz",
    "sg:orig_category":"Organisationen der Wohlfahrtspflege",
    "sg:phone":"+41 32 926 77 35",
    "sg:postcode":"1902",
    "sg:province":"Valais",
    "wof:name":"Pro Juventute Secr\u00e9tariat",
    "wof:placetype":"venue"
},
  "geometry": {"coordinates":[6.8075671196,47.0921478271],"type":"Point"}
}