{
  "type": "Feature",
  "properties": {
    "iso:country":"CH",
    "sg:address":"Via Henri Guisan",
    "sg:city":"Bellinzona",
    "sg:orig_category":"Primarschulen",
    "sg:postcode":"6500",
    "sg:province":"Ticino",
    "wof:name":"Scuola Elementare Palazzo Nord",
    "wof:placetype":"venue"
},
  "geometry": {"coordinates":[9.0245485306,46.1948852539],"type":"Point"}
}