{
  "type": "Feature",
  "properties": {
    "addr:full":"Vordergasse 9 Neunkirch Schaffhausen 8213",
    "addr:housenumber":"9",
    "addr:postcode":"8213",
    "addr:street":"Vordergasse",
    "iso:country":"CH",
    "sg:address":"Vordergasse 9",
    "sg:city":"Neunkirch",
    "sg:orig_category":"Detailhandel mit Computern U Software",
    "sg:phone":"+41 52 682 25 35",
    "sg:postcode":"8213",
    "sg:province":"Schaffhausen",
    "wof:name":"Andreas Hunziker Webcom 2000",
    "wof:placetype":"venue"
},
  "geometry": {"coordinates":[8.500237,47.690174],"type":"Point"}
}