{
  "type": "Feature",
  "properties": {
    "iso:country":"CH",
    "sg:address":"Chemin Des Flombards 6",
    "sg:city":"Ch\u00eane-bougeries",
    "sg:orig_category":"Elektroinstallation Herstellung von nachrichtentechnischen Ger\u00e4ten U Einrichtungen",
    "sg:phone":"+41 22 348 56 06",
    "sg:postcode":"1224",
    "sg:province":"Gen\u00e8ve",
    "wof:name":"Del Bon Pierre Sa",
    "wof:placetype":"venue"
},
  "geometry": {"coordinates":[6.1910858154,46.1989021301],"type":"Point"}
}