{
  "type": "Feature",
  "properties": {
    "iso:country":"CH",
    "sg:address":"Oerlikonerstrasse 7 8000 Z\u00fcrich. Postfach",
    "sg:city":"Z\u00fcrich",
    "sg:orig_category":"Unternehmensberatung",
    "sg:phone":"+41 71 244 93 33",
    "sg:postcode":"8057",
    "sg:province":"Z\u00fcrich",
    "wof:name":"Contool St. Gallen Ag",
    "wof:placetype":"venue"
},
  "geometry": {"coordinates":[9.3786077499,47.4381408691],"type":"Point"}
}