{
  "type": "Feature",
  "properties": {
    "iso:country":"CH",
    "sg:address":"Seegrabe 3",
    "sg:city":"Marthalen",
    "sg:orig_category":"Kaminfeger",
    "sg:phone":"+41 71 744 47 38",
    "sg:postcode":"8460",
    "sg:province":"Z\u00fcrich",
    "wof:name":"Peter Rosenkranz Kaminfegermeister",
    "wof:placetype":"venue"
},
  "geometry": {"coordinates":[9.6316413879,47.4540061951],"type":"Point"}
}