{
  "type": "Feature",
  "properties": {
    "iso:country":"CH",
    "sg:address":"Avenue De La Gare 1",
    "sg:city":"Lausanne",
    "sg:orig_category":"Fachdetailhandel mit pharmazeutischen Produkten",
    "sg:phone":"+41 21 312 86 61",
    "sg:postcode":"1003",
    "sg:province":"Vaud",
    "wof:name":"Pharmacie Cornaz Elyane.",
    "wof:placetype":"venue"
},
  "geometry": {"coordinates":[6.6372947693,46.5166702271],"type":"Point"}
}