{
  "type": "Feature",
  "properties": {
    "iso:country":"CH",
    "sg:address":"Bahnhofstrasse 11",
    "sg:city":"Sursee",
    "sg:orig_category":"Markt U Meinungsforschung Werbeberatung",
    "sg:phone":"+41 52 318 24 46",
    "sg:postcode":"6210",
    "sg:province":"Luzern",
    "wof:name":"Medexsa, Marianne Allenspach",
    "wof:placetype":"venue"
},
  "geometry": {"coordinates":[8.6166610718,47.5589294434],"type":"Point"}
}