{
  "type": "Feature",
  "properties": {
    "iso:country":"CH",
    "sg:address":"Dorfstrasse 8",
    "sg:city":"Lommiswil",
    "sg:orig_category":"Oberfl\u00e4chenveredlung U W\u00e4rmebehandlung Stahl U Leichtmetallbau",
    "sg:phone":"+41 32 641 15 81",
    "sg:postcode":"4514",
    "sg:province":"Solothurn",
    "wof:name":"B\u00e4hler + Staub Metallwerkstatt",
    "wof:placetype":"venue"
},
  "geometry": {"coordinates":[7.4725089073,47.2250709534],"type":"Point"}
}