{
  "type": "Feature",
  "properties": {
    "iso:country":"CH",
    "sg:address":"P\u00fcntstrasse 22",
    "sg:city":"Z\u00fcrich",
    "sg:orig_category":"Softwareentwicklung U beratung",
    "sg:phone":"+41 32 373 24 47",
    "sg:postcode":"8047",
    "sg:province":"Z\u00fcrich",
    "wof:name":"Informatik Schrag Gmbh",
    "wof:placetype":"venue"
},
  "geometry": {"coordinates":[7.2689628601,47.1265258789],"type":"Point"}
}