{
  "type": "Feature",
  "properties": {
    "iso:country":"CH",
    "sg:address":"Nonnenweg 36",
    "sg:city":"Basel",
    "sg:orig_category":"K\u00fcnstlerische U schriftstellerische T\u00e4tigkeiten U Darbietungen",
    "sg:phone":"+41 61 261 63 73",
    "sg:postcode":"4055",
    "sg:province":"Basel-Stadt",
    "wof:name":"Atelier Marti-pichard Audrey",
    "wof:placetype":"venue"
},
  "geometry": {"coordinates":[7.5761342049,47.5583877563],"type":"Point"}
}