{
  "type": "Feature",
  "properties": {
    "iso:country":"CH",
    "sg:address":"Rehweid 9",
    "sg:city":"Russikon",
    "sg:orig_category":"Elektrizit\u00e4tsversorgung",
    "sg:postcode":"8332",
    "sg:province":"Z\u00fcrich",
    "wof:name":"Solarus Genossenschaft F\u00fcr Sonnenenergie",
    "wof:placetype":"venue"
},
  "geometry": {"coordinates":[8.7938165665,47.4146881104],"type":"Point"}
}