{
  "type": "Feature",
  "properties": {
    "iso:country":"CH",
    "sg:address":"Viale Stazione 1",
    "sg:city":"Giubiasco",
    "sg:orig_category":"Herstellung von Metallkonstruktionen",
    "sg:phone":"+41 91 857 51 83",
    "sg:postcode":"6512",
    "sg:province":"Ticino",
    "wof:name":"Plattner Costruzioni Metalliche Sa",
    "wof:placetype":"venue"
},
  "geometry": {"coordinates":[9.0090332031,46.1726760864],"type":"Point"}
}