{
  "type": "Feature",
  "properties": {
    "iso:country":"CH",
    "sg:address":"Viale Stazione 2",
    "sg:city":"Bellinzona",
    "sg:orig_category":"Arztpraxen",
    "sg:phone":"+41 91 825 18 13",
    "sg:postcode":"6500",
    "sg:province":"Ticino",
    "wof:name":"Dott.med.renato Luchessa Medico Generico Fmh",
    "wof:placetype":"venue"
},
  "geometry": {"coordinates":[9.023623,46.191738],"type":"Point"}
}