{
  "type": "Feature",
  "properties": {
    "iso:country":"CH",
    "sg:address":"Haus Alpina",
    "sg:city":"Tenna",
    "sg:orig_category":"Gemeindeverwaltungen",
    "sg:phone":"+41 81 645 12 50",
    "sg:postcode":"7106",
    "sg:province":"Graubunden",
    "wof:name":"Gemeindeverwaltung Tenna",
    "wof:placetype":"venue"
},
  "geometry": {"coordinates":[9.3394060135,46.746723175],"type":"Point"}
}