{
  "type": "Feature",
  "properties": {
    "iso:country":"CH",
    "sg:address":"Les Louyes 7 1746 Prez-vers-nor\u00e9az. Postfach",
    "sg:city":"Prez-vers-nor\u00e9az",
    "sg:orig_category":"Hardwareberatung",
    "sg:postcode":"1746",
    "sg:province":"Fribourg",
    "wof:name":"Vinylnews Perroud Disques Par Internet; Vente",
    "wof:placetype":"venue"
},
  "geometry": {"coordinates":[7.0161938667,46.7823410034],"type":"Point"}
}