{
  "type": "Feature",
  "properties": {
    "iso:country":"CH",
    "sg:address":"Stadtturmstrasse 19",
    "sg:city":"Baden",
    "sg:orig_category":"Erschliessung von Grundst\u00fccken",
    "sg:postcode":"5400",
    "sg:province":"Aargau",
    "wof:name":"Baugenossenschaft Leematten",
    "wof:placetype":"venue"
},
  "geometry": {"coordinates":[8.3055353165,47.4757881165],"type":"Point"}
}