{
  "type": "Feature",
  "properties": {
    "iso:country":"CH",
    "sg:address":"Talackerstrasse 7",
    "sg:city":"Uster",
    "sg:classifiers":[
        {
            "category":"Restaurant",
            "type":"Food & Drink"
        }
    ],
    "sg:phone":"+41 19401850",
    "sg:postcode":"8610",
    "sg:province":"Z\u00fcrich",
    "wof:name":"Restaurant Talgarten",
    "wof:placetype":"venue"
},
  "geometry": {"coordinates":[8.716255188,47.3450469971],"type":"Point"}
}