{
  "type": "Feature",
  "properties": {
    "addr:full":"Place St.-fran\u00e7ois 6 1003 Lausanne. Postfach Lausanne Vaud 1002",
    "addr:housenumber":"6",
    "addr:postcode":"1003;postfach;1002",
    "addr:street":"Place St.-Franc\u0327Ois",
    "iso:country":"CH",
    "sg:address":"Place St.-fran\u00e7ois 6 1003 Lausanne. Postfach",
    "sg:city":"Lausanne",
    "sg:orig_category":"Autotransporte international",
    "sg:phone":"+41 21 320 72 01",
    "sg:postcode":"1002",
    "sg:province":"Vaud",
    "wof:name":"Wagons-lits Tourisme Transports Internationaux",
    "wof:placetype":"venue"
},
  "geometry": {"coordinates":[6.633069,46.52013],"type":"Point"}
}