{
  "type": "Feature",
  "properties": {
    "iso:country":"CH",
    "sg:address":"R\u00fctihofstrasse 53 8049 Z\u00fcrich. Postfach",
    "sg:city":"Z\u00fcrich",
    "sg:orig_category":"Softwareentwicklung U beratung",
    "sg:phone":"+41 13414214",
    "sg:postcode":"8049",
    "sg:province":"Z\u00fcrich",
    "wof:name":"Mostajelien It-consulting Hard, Software; Handel. Beratungs, Supportdienstleistungen Im Bereich Der Informationstechnologien",
    "wof:placetype":"venue"
},
  "geometry": {"coordinates":[8.4767360687,47.4132957458],"type":"Point"}
}