{
  "type": "Feature",
  "properties": {
    "iso:country":"CH",
    "sg:address":"Schauenseestrasse 8",
    "sg:city":"Kriens",
    "sg:orig_category":"Geb\u00e4ude, Wohnungsreinigung",
    "sg:phone":"+41 41 320 01 83",
    "sg:postcode":"6010",
    "sg:province":"Luzern",
    "wof:name":"In\u00e9s Niederberger In-reinigung",
    "wof:placetype":"venue"
},
  "geometry": {"coordinates":[8.2752599716,47.0308761597],"type":"Point"}
}