{
  "type": "Feature",
  "properties": {
    "iso:country":"CH",
    "sg:address":"Buechstrasse 19",
    "sg:city":"Jona",
    "sg:orig_category":"Instandhaltung U Reparatur von Automobilen Vermietung von Automobilen",
    "sg:phone":"+41 55 212 34 44",
    "sg:postcode":"8645",
    "sg:province":"St. Gallen",
    "wof:name":"Garage Schweizer Gmbh",
    "wof:placetype":"venue"
},
  "geometry": {"coordinates":[8.8662624359,47.2272377014],"type":"Point"}
}