{
  "type": "Feature",
  "properties": {
    "iso:country":"CH",
    "sg:address":"Hubrainstrasse 8",
    "sg:city":"Maur",
    "sg:orig_category":"Finanzierungsinstitutionen",
    "sg:postcode":"8124",
    "sg:province":"Z\u00fcrich",
    "wof:name":"Mennel Consulting",
    "wof:placetype":"venue"
},
  "geometry": {"coordinates":[8.6657352448,47.3398742676],"type":"Point"}
}