{
  "type": "Feature",
  "properties": {
    "iso:country":"CH",
    "sg:address":"Dorfstrasse",
    "sg:city":"Aathal-seegr\u00e4ben",
    "sg:classifiers":[
        {
            "category":"Restaurant",
            "type":"Food & Drink"
        }
    ],
    "sg:phone":"+41 19321320",
    "sg:postcode":"8607",
    "sg:province":"Z\u00fcrich",
    "wof:name":"Restaurant Linde",
    "wof:placetype":"venue"
},
  "geometry": {"coordinates":[8.7684850693,47.3358840942],"type":"Point"}
}