{
  "type": "Feature",
  "properties": {
    "iso:country":"CH",
    "sg:address":"Kublihoschet 39",
    "sg:city":"Netstal",
    "sg:orig_category":"Herstellung von sonstigen M\u00f6beln",
    "sg:postcode":"8754",
    "sg:province":"Glarus",
    "wof:name":"Fuentes J.c. Stilm\u00f6bel-rustica",
    "wof:placetype":"venue"
},
  "geometry": {"coordinates":[9.057053566,47.0566482544],"type":"Point"}
}