{
  "type": "Feature",
  "properties": {
    "iso:country":"CH",
    "sg:address":"Jensstrasse 3",
    "sg:city":"Worben",
    "sg:orig_category":"Vereine Vogel-& Naturschutz",
    "sg:phone":"+41 32 384 29 64",
    "sg:postcode":"3252",
    "sg:province":"Bern",
    "wof:name":"Verein F.vogelzucht & Pflege",
    "wof:placetype":"venue"
},
  "geometry": {"coordinates":[7.2930588722,47.1062583923],"type":"Point"}
}