{
  "type": "Feature",
  "properties": {
    "iso:country":"CH",
    "sg:address":"Hauptstrasse 50",
    "sg:city":"Hausen",
    "sg:classifiers":[
        {
            "category":"Professional",
            "subcategory":"Management & Consulting",
            "type":"Services"
        }
    ],
    "sg:phone":"+41 41 852 05 00",
    "sg:postcode":"5212",
    "sg:province":"Aargau",
    "sg:tags":[
        "consultancy"
    ],
    "wof:name":"Germann Marketing",
    "wof:placetype":"venue"
},
  "geometry": {"coordinates":[8.4408140182,47.0863380432],"type":"Point"}
}