{
  "type": "Feature",
  "properties": {
    "iso:country":"CH",
    "sg:address":"St\u00f6berstrasse 6",
    "sg:city":"Basel",
    "sg:orig_category":"Herstellung von keramischen Wand U Bodenfliesen U platten Verlegen von Fliesen U Platten",
    "sg:phone":"+41 61 382 52 81",
    "sg:postcode":"4055",
    "sg:province":"Basel-Stadt",
    "wof:name":"Pezzot Pietro",
    "wof:placetype":"venue"
},
  "geometry": {"coordinates":[7.5723662376,47.5595436096],"type":"Point"}
}