{
  "type": "Feature",
  "properties": {
    "iso:country":"CH",
    "sg:address":"Allmend 4",
    "sg:city":"Rottenschwil",
    "sg:orig_category":"Herstellung von sonstigen Maschinen f\u00fcr bestimmte Verwendung",
    "sg:phone":"+41 56 634 40 12",
    "sg:postcode":"8919",
    "sg:province":"Aargau",
    "wof:name":"Walker J\u00fcrg Gmbh",
    "wof:placetype":"venue"
},
  "geometry": {"coordinates":[8.3694581985,47.3199996948],"type":"Point"}
}