{
  "type": "Feature",
  "properties": {
    "iso:country":"CH",
    "sg:address":"Bodmerstrasse 14 8027 Z\u00fcrich. Postfach",
    "sg:city":"Z\u00fcrich",
    "sg:orig_category":"Sonstiger Grosshandel",
    "sg:phone":"+41 12810011",
    "sg:postcode":"8027",
    "sg:province":"Z\u00fcrich",
    "wof:name":"Asp Ag",
    "wof:placetype":"venue"
},
  "geometry": {"coordinates":[8.5327739716,47.365398407],"type":"Point"}
}