{
  "type": "Feature",
  "properties": {
    "iso:country":"CH",
    "sg:address":"Rebgasse 4",
    "sg:city":"Liestal",
    "sg:orig_category":"Non-Classified Establishments",
    "sg:postcode":"4410",
    "sg:province":"Basel-Landschaft",
    "wof:name":"Sanavit Lehrinstitut Pl\u00fcss",
    "wof:placetype":"venue"
},
  "geometry": {"coordinates":[7.7339758873,47.4859046936],"type":"Point"}
}