{
  "type": "Feature",
  "properties": {
    "iso:country":"CH",
    "sg:address":"Chemin Des Fins 2 - Po Box 172 -",
    "sg:city":"Geneva",
    "sg:classifiers":[
        {
            "category":"Professional",
            "subcategory":"Art Services",
            "type":"Services"
        }
    ],
    "sg:phone":"+41 22 799 91 00",
    "sg:postcode":"1211",
    "sg:province":"Gen\u00e8ve",
    "sg:tags":[
        "export-import"
    ],
    "wof:name":"Australia General Consulate",
    "wof:placetype":"venue"
},
  "geometry": {"coordinates":[6.13993,46.203819],"type":"Point"}
}