{
  "type": "Feature",
  "properties": {
    "iso:country":"CH",
    "sg:address":"Obere Hauptstrasse",
    "sg:city":"Oftringen",
    "sg:orig_category":"Vermietung U Verpachtung von eigenen Immobilien",
    "sg:postcode":"4665",
    "sg:province":"Aargau",
    "wof:name":"Eichmatt Wohnbau Ag",
    "wof:placetype":"venue"
},
  "geometry": {"coordinates":[7.937473774,47.3112869263],"type":"Point"}
}