{
  "type": "Feature",
  "properties": {
    "iso:country":"CH",
    "sg:address":"Plattenbach 30",
    "sg:city":"Balzers",
    "sg:orig_category":"Rechtsberatung Verwaltung von Immobilien",
    "sg:phone":"+41 75 388 23 05",
    "sg:postcode":"9496",
    "wof:name":"Adcom Sa",
    "wof:placetype":"venue"
},
  "geometry": {"coordinates":[9.5036811829,47.0671844482],"type":"Point"}
}