{
  "type": "Feature",
  "properties": {
    "iso:country":"CH",
    "sg:address":"Montbenon Avenue De 2 1003 Lausanne Case Postale",
    "sg:city":"Lausanne",
    "sg:orig_category":"Detailhandel mit elektrischen Haushalts-,Radio U Fernsehger\u00e4ten sowie Musikinstrumenten",
    "sg:postcode":"1003",
    "sg:province":"Vaud",
    "wof:name":"Bewlay Bros S\u00e0rl. Toute Activit\u00e9 Industr. Et Commerciale Relative \u00e0 La Reproduct. Sonique Sous Quelque Forme Que Ce Soit, Etc.",
    "wof:placetype":"venue"
},
  "geometry": {"coordinates":[6.6289958954,46.5207748413],"type":"Point"}
}