{
  "type": "Feature",
  "properties": {
    "iso:country":"CH",
    "sg:address":"Soguel Rue Fr\u00e9d\u00e9ric- 20 A",
    "sg:city":"Cernier",
    "sg:orig_category":"Softwareentwicklung U beratung",
    "sg:phone":"+41 32 853 12 05",
    "sg:postcode":"2053",
    "sg:province":"Neuch\u00e2tel",
    "wof:name":"Plugin, Antenen J.-f.",
    "wof:placetype":"venue"
},
  "geometry": {"coordinates":[6.9030089378,47.0593338013],"type":"Point"}
}