{
  "type": "Feature",
  "properties": {
    "iso:country":"CH",
    "sg:address":"Birmensdorferstrasse 138 8902 Urdorf. Postfach",
    "sg:city":"Urdorf",
    "sg:orig_category":"Instandhaltung U Reparatur von Automobilen",
    "sg:postcode":"8902",
    "sg:province":"Z\u00fcrich",
    "wof:name":"Morocar, Hefele Garage. Metallbau-konstruktionen",
    "wof:placetype":"venue"
},
  "geometry": {"coordinates":[8.4229545593,47.3795928955],"type":"Point"}
}