{
  "type": "Feature",
  "properties": {
    "iso:country":"CH",
    "sg:address":"Oberm\u00fchlestrasse 8722 Kaltbrunn. Postfach 196",
    "sg:city":"Kaltbrunn",
    "sg:orig_category":"Herstellung von Schrauben, Nieten, Ketten U Federn",
    "sg:phone":"+41 55 293 20 20",
    "sg:postcode":"8722",
    "sg:province":"St. Gallen",
    "wof:name":"Federnfabrik Und Apparatebau Ag, Kaltbrunn",
    "wof:placetype":"venue"
},
  "geometry": {"coordinates":[9.0298805237,47.2175827026],"type":"Point"}
}