{
  "type": "Feature",
  "properties": {
    "iso:country":"CH",
    "sg:address":"Asylstrasse 58 8032 Z\u00fcrich. Postfach",
    "sg:city":"Z\u00fcrich",
    "sg:orig_category":"Fachdetailhandel mit pharmazeutischen Produkten",
    "sg:phone":"+41 61 461 25 25",
    "sg:postcode":"8030",
    "wof:name":"R\u00f6ssli-apotheke Frau Dr. Rolli-erb Elisabeth",
    "wof:placetype":"venue"
},
  "geometry": {"coordinates":[7.6470170021,47.5255622864],"type":"Point"}
}