{
  "type": "Feature",
  "properties": {
    "iso:country":"CH",
    "sg:address":"Am Schr\u00e4gen Weg 12",
    "sg:city":"Vaduz",
    "sg:orig_category":"Handelsvermittlung U Grosshandel Softwareentwicklung U beratung",
    "sg:phone":"+41 71 912 16 11",
    "sg:postcode":"9490",
    "wof:name":"Gh-solution Guido H\u00fcttenmoser",
    "wof:placetype":"venue"
},
  "geometry": {"coordinates":[9.028585434,47.4591903687],"type":"Point"}
}