{
  "type": "Feature",
  "properties": {
    "iso:country":"CH",
    "sg:address":"Grand-rue 48 1454 L'auberson. Postfach",
    "sg:city":"L'auberson",
    "sg:orig_category":"Detailhandel mit Brot, Back U S\u00fcsswaren",
    "sg:postcode":"1454",
    "sg:province":"Vaud",
    "wof:name":"Chez Taggi, Tagini & Tagini Boulangerie-p\u00e2tisserie Et Tea-room",
    "wof:placetype":"venue"
},
  "geometry": {"coordinates":[6.469717,46.819717],"type":"Point"}
}