{
  "type": "Feature",
  "properties": {
    "iso:country":"CH",
    "sg:address":"Route De Suisse 35",
    "sg:city":"Gland",
    "sg:orig_category":"Tankstellen",
    "sg:phone":"+41 22 364 00 30",
    "sg:postcode":"1196",
    "sg:province":"Vaud",
    "wof:name":"Kurz Rudolf",
    "wof:placetype":"venue"
},
  "geometry": {"coordinates":[6.2801961899,46.4164428711],"type":"Point"}
}