{
  "type": "Feature",
  "properties": {
    "iso:country":"CH",
    "sg:address":"Rte Andr\u00e9 Piller 21",
    "sg:city":"Fribourg",
    "sg:classifiers":[
        {
            "category":"Health Services",
            "subcategory":"Medical Lab",
            "type":"Services"
        }
    ],
    "sg:phone":"+41 26 466 51 26",
    "sg:postcode":"1701",
    "sg:province":"Fribourg",
    "sg:tags":[
        "chemical",
        "pharmaceutical",
        "pharmacy"
    ],
    "wof:name":"Interdelta Sa",
    "wof:placetype":"venue"
},
  "geometry": {"coordinates":[7.153683,46.803745],"type":"Point"}
}