{
  "type": "Feature",
  "properties": {
    "addr:full":"Dorfstrasse 17/19 6340 Baar. Postfach 262 Baar Zug 6341",
    "addr:housenumber":"17 / 19;262",
    "addr:postcode":"6340 baar.;6341",
    "addr:street":"Dorfstrasse;Postfach;Zug",
    "iso:country":"CH",
    "sg:address":"Dorfstrasse 17/19 6340 Baar. Postfach 262",
    "sg:city":"Baar",
    "sg:orig_category":"Detailhandel mit Beleuchtungs U Haushaltsgegenst\u00e4nden",
    "sg:phone":"+41 79 339 23 94",
    "sg:postcode":"6341",
    "sg:province":"Zug",
    "wof:name":"Gebr. Gysi Ag Eisenwaren Haushalt",
    "wof:placetype":"venue"
},
  "geometry": {"coordinates":[8.524923,47.193935],"type":"Point"}
}