{
  "type": "Feature",
  "properties": {
    "iso:country":"CH",
    "sg:address":"La Pran 1",
    "sg:city":"Vicques",
    "sg:orig_category":"Detailhandel mit Sportartikeln",
    "sg:phone":"+41 32 435 68 06",
    "sg:postcode":"2824",
    "sg:province":"Jura",
    "wof:name":"La Cabane Des Sportifs",
    "wof:placetype":"venue"
},
  "geometry": {"coordinates":[7.4165830612,47.3486289978],"type":"Point"}
}