{
  "type": "Feature",
  "properties": {
    "iso:country":"CH",
    "sg:address":"D\u00e9barcad\u00e8re Rue Du 15",
    "sg:city":"St-aubin-sauges",
    "sg:orig_category":"Detailhandel mit M\u00f6beln U Haushaltsgegenst\u00e4nden",
    "sg:postcode":"2024",
    "sg:province":"Neuch\u00e2tel",
    "wof:name":"Un Souffle D'ailleurs S\u00e0rl",
    "wof:placetype":"venue"
},
  "geometry": {"coordinates":[6.7632799149,46.8871154785],"type":"Point"}
}