{
  "type": "Feature",
  "properties": {
    "iso:country":"CH",
    "sg:address":"Aareweg",
    "sg:city":"Auenstein",
    "sg:orig_category":"Detailhandel mit B\u00fcromaschinen U einrichtungen",
    "sg:phone":"+41 62 893 25 88",
    "sg:postcode":"5105",
    "sg:province":"Aargau",
    "wof:name":"Silvio K\u00f6beli B\u00fcroeinrichtungen",
    "wof:placetype":"venue"
},
  "geometry": {"coordinates":[8.134981,47.416702],"type":"Point"}
}