{
  "type": "Feature",
  "properties": {
    "iso:country":"CH",
    "sg:address":"Paradiso Riva 7 6900 Paradiso. Postfach",
    "sg:city":"Paradiso",
    "sg:classifiers":[
        {
            "category":"Travel",
            "subcategory":"Hotels & Motels",
            "type":"Entertainment"
        }
    ],
    "sg:postcode":"6900",
    "sg:province":"Ticino",
    "sg:tags":[
        "hotels",
        "mit",
        "restaurant"
    ],
    "wof:name":"Lanfranchi Donato",
    "wof:placetype":"venue"
},
  "geometry": {"coordinates":[8.9534635544,45.989364624],"type":"Point"}
}