{
  "type": "Feature",
  "properties": {
    "iso:country":"CH",
    "sg:address":"Stansstaderstrasse 20 6370 Stans. Postfach 943",
    "sg:city":"Stans",
    "sg:orig_category":"Detailhandel mit fotografischen Artikeln Fotografische Ateliers",
    "sg:phone":"+41 41 610 21 06",
    "sg:postcode":"6371",
    "sg:province":"Nidwalden",
    "wof:name":"Foto Prest",
    "wof:placetype":"venue"
},
  "geometry": {"coordinates":[8.3641519547,46.9587249756],"type":"Point"}
}