{
  "type": "Feature",
  "properties": {
    "iso:country":"CH",
    "sg:address":"Sunnehof",
    "sg:city":"Hornussen",
    "sg:orig_category":"Haltung von Rindern",
    "sg:postcode":"5075",
    "sg:province":"Aargau",
    "wof:name":"Schwarzfleckviehzucht- Genossenschaft Fricktal",
    "wof:placetype":"venue"
},
  "geometry": {"coordinates":[8.0667695999,47.5069465637],"type":"Point"}
}