{
  "type": "Feature",
  "properties": {
    "iso:country":"CH",
    "sg:address":"Zugerstrasse 170",
    "sg:city":"Neu\u00e4geri",
    "sg:orig_category":"Grosshandel mit lebenden Tieren",
    "sg:phone":"+41 41 480 20 06",
    "sg:postcode":"6314",
    "sg:province":"Zug",
    "wof:name":"Duss Viehhandlung Gmbh",
    "wof:placetype":"venue"
},
  "geometry": {"coordinates":[8.0499076843,46.9801826477],"type":"Point"}
}