{
  "type": "Feature",
  "properties": {
    "iso:country":"CH",
    "sg:address":"Landstrasse 79 4313 M\u00f6hlin. Postfach",
    "sg:city":"M\u00f6hlin",
    "sg:orig_category":"Ausbaugewerbe",
    "sg:postcode":"4313",
    "sg:province":"Aargau",
    "wof:name":"Chemin\u00e9es Kachel\u00f6fen Plattenbel\u00e4ge, Guthauser Irene Projektieren Von Chemin\u00e9es, Kachel\u00f6fen U. Plattenbel\u00e4gen",
    "wof:placetype":"venue"
},
  "geometry": {"coordinates":[7.852824,47.55341],"type":"Point"}
}