{
  "type": "Feature",
  "properties": {
    "iso:country":"CH",
    "sg:address":"Au Village",
    "sg:city":"Gumefens",
    "sg:orig_category":"Detailhandel mit Waren verschiedener Art, Hauptrichtung Nahrungsmittel Grosshandel mit Nahrungsmitte",
    "sg:phone":"+41 26 915 14 59",
    "sg:postcode":"1643",
    "sg:province":"Fribourg",
    "wof:name":"Alimentation Vis-\u00e2-vis Steve & Ariane Rolle",
    "wof:placetype":"venue"
},
  "geometry": {"coordinates":[7.0767998695,46.6768531799],"type":"Point"}
}