{
  "type": "Feature",
  "properties": {
    "iso:country":"CH",
    "sg:address":"Rue De La Borde 3bis 1018 Lausanne. Postfach",
    "sg:city":"Lausanne",
    "sg:classifiers":[
        {
            "category":"Restaurant",
            "type":"Food & Drink"
        }
    ],
    "sg:phone":"+41 21 320 35 20",
    "sg:postcode":"1018",
    "sg:province":"Vaud",
    "sg:tags":[
        "tea-rooms",
        "restaurants"
    ],
    "wof:name":"Houston Caf\u00e9 S\u00e0rl Caf\u00e9s-restaurants Etc",
    "wof:placetype":"venue"
},
  "geometry": {"coordinates":[6.6329798698,46.5277709961],"type":"Point"}
}