{
  "type": "Feature",
  "properties": {
    "iso:country":"CH",
    "sg:address":"Pierrapartiaz 10",
    "sg:city":"Grimisuat",
    "sg:orig_category":"Dauerkulturbau",
    "sg:phone":"+41 27 398 32 22",
    "sg:postcode":"1971",
    "sg:province":"Valais",
    "wof:name":"Vuignier No\u00ebl",
    "wof:placetype":"venue"
},
  "geometry": {"coordinates":[7.393926,46.258495],"type":"Point"}
}