{
  "type": "Feature",
  "properties": {
    "iso:country":"CH",
    "sg:address":"Gotthardstrasse 43",
    "sg:city":"Fl\u00fcelen",
    "sg:orig_category":"Architektur U Ingenieurb\u00fcros",
    "sg:phone":"+41 41 870 37 71",
    "sg:postcode":"6454",
    "sg:province":"Uri",
    "wof:name":"Vinzenz Epp Ingenieurb\u00fcro",
    "wof:placetype":"venue"
},
  "geometry": {"coordinates":[8.625722,46.897617],"type":"Point"}
}