{
  "type": "Feature",
  "properties": {
    "iso:country":"CH",
    "sg:address":"Kirchstrasse 3a",
    "sg:city":"Altenrhein",
    "sg:orig_category":"Sanit\u00e4rinstallation Schlossereien",
    "sg:phone":"+41 71 855 44 61",
    "sg:postcode":"9423",
    "sg:province":"St. Gallen",
    "wof:name":"Edmund Hinnen Schlosserei & Sanit\u00e4r",
    "wof:placetype":"venue"
},
  "geometry": {"coordinates":[9.5507364273,47.4905090332],"type":"Point"}
}