{
  "type": "Feature",
  "properties": {
    "iso:country":"CH",
    "sg:address":"Hausmattstrasse 15",
    "sg:city":"Egerkingen",
    "sg:orig_category":"Machine Bases",
    "sg:phone":"+41 32 858 28 58",
    "sg:postcode":"4622",
    "sg:province":"Solothurn",
    "wof:name":"Patric M\u00e9tal S.a.",
    "wof:placetype":"venue"
},
  "geometry": {"coordinates":[6.850592,47.011406],"type":"Point"}
}