{
  "type": "Feature",
  "properties": {
    "iso:country":"CH",
    "sg:address":"Kanderstegstrasse 20 3714 Frutigen. Postfach 41",
    "sg:city":"Frutigen",
    "sg:orig_category":"Drogerien Sonstiger Fachdetailhandel mit Nahrungsmitteln, Getr\u00e4nken U Tabak in Verkaufsr\u00e4umen",
    "sg:phone":"+41 33 671 10 57",
    "sg:postcode":"3714",
    "sg:province":"Bern",
    "wof:name":"Drogerie & Reform, Z\u00fcrcher Markus",
    "wof:placetype":"venue"
},
  "geometry": {"coordinates":[7.6464691162,46.586933136],"type":"Point"}
}