{
  "type": "Feature",
  "properties": {
    "iso:country":"CH",
    "sg:address":"Sch\u00f6ngr\u00fcnstrasse 20",
    "sg:city":"Solothurn",
    "sg:orig_category":"Architekturb\u00fcros",
    "sg:phone":"+41 32 621 37 22",
    "sg:postcode":"4500",
    "sg:province":"Solothurn",
    "wof:name":"J\u00fcrg G. Sch\u00e4delin Architekturb\u00fcro",
    "wof:placetype":"venue"
},
  "geometry": {"coordinates":[7.538498,47.20182],"type":"Point"}
}