{
  "type": "Feature",
  "properties": {
    "iso:country":"CH",
    "sg:address":"Grand-rue 23",
    "sg:city":"Peseux",
    "sg:orig_category":"RESTAURANTS: TEA-ROOMS",
    "sg:postcode":"2034",
    "sg:province":"Neuch\u00e2tel",
    "wof:name":"Jeanneret Eug\u00e8ne Albert Et Cie",
    "wof:placetype":"venue"
},
  "geometry": {"coordinates":[6.8893518448,46.987575531],"type":"Point"}
}