{
  "type": "Feature",
  "properties": {
    "iso:country":"CH",
    "sg:address":"Wiggenhalde 12",
    "sg:city":"Kriens",
    "sg:orig_category":"Selbst\u00e4ndige bildende K\u00fcnstler",
    "sg:phone":"+41 41 310 24 91",
    "sg:postcode":"6010",
    "sg:province":"Luzern",
    "wof:name":"Josef & Erika Schnyder Holzbildhauerei",
    "wof:placetype":"venue"
},
  "geometry": {"coordinates":[8.2921075821,47.0217323303],"type":"Point"}
}