{
  "type": "Feature",
  "properties": {
    "iso:country":"CH",
    "sg:address":"Place De La Fontaine 4 2034 Peseux. Postfach",
    "sg:city":"Peseux",
    "sg:orig_category":"Fachdetailhandel mit pharmazeutischen Produkten",
    "sg:phone":"+41 32 731 11 31",
    "sg:postcode":"2034",
    "sg:province":"Neuch\u00e2tel",
    "wof:name":"Pharmacie Gauchat, Successeur Nussbaumer Patrick Pharmacien Et Licenci\u00e9 En Droit",
    "wof:placetype":"venue"
},
  "geometry": {"coordinates":[6.8898029327,46.9866447449],"type":"Point"}
}