{
  "type": "Feature",
  "properties": {
    "iso:country":"CH",
    "sg:address":"Lerchenstrasse 2",
    "sg:city":"Wolfwil",
    "sg:orig_category":"Grosshandel mit Holz U Baustoffen",
    "sg:postcode":"4628",
    "sg:province":"Solothurn",
    "wof:name":"Lakonita - Ausseruniversit\u00e4re Forschungsgemeinschaft Gmbh",
    "wof:placetype":"venue"
},
  "geometry": {"coordinates":[7.787820816,47.2684020996],"type":"Point"}
}