{
  "type": "Feature",
  "properties": {
    "iso:country":"CH",
    "sg:address":"Lindenstrasse 8",
    "sg:city":"Rheinfelden",
    "sg:orig_category":"Kauf U Verkauf von Immobilien auf eigene Rechnung",
    "sg:postcode":"4310",
    "sg:province":"Aargau",
    "wof:name":"Immo-score Ag",
    "wof:placetype":"venue"
},
  "geometry": {"coordinates":[9.8379974365,46.807258606],"type":"Point"}
}