{
  "type": "Feature",
  "properties": {
    "iso:country":"CH",
    "sg:address":"Fluhstrasse 14",
    "sg:city":"R\u00f6schenz",
    "sg:orig_category":"Selbst\u00e4ndige bildende K\u00fcnstler",
    "sg:phone":"+41 32 730 32 30",
    "sg:postcode":"4244",
    "sg:province":"Basel-Landschaft",
    "wof:name":"Oudin & Cie",
    "wof:placetype":"venue"
},
  "geometry": {"coordinates":[6.9070978165,46.9878883362],"type":"Point"}
}