{
  "type": "Feature",
  "properties": {
    "iso:country":"CH",
    "sg:address":"Bahnhofstrasse 4 3150 Schwarzenburg. Postfach 114",
    "sg:city":"Schwarzenburg",
    "sg:orig_category":"Grosshandel mit Nahrungsmitteln, Getr\u00e4nken U Tabakwaren Grosshandel mit Nahrungsmitteln, Getr\u00e4nken U",
    "sg:phone":"+41 31 731 26 66",
    "sg:postcode":"3150",
    "sg:province":"Bern",
    "wof:name":"Cuisine Spring Ag",
    "wof:placetype":"venue"
},
  "geometry": {"coordinates":[7.342045784,46.8186035156],"type":"Point"}
}