{
  "type": "Feature",
  "properties": {
    "iso:country":"CH",
    "sg:address":"Oberdorfstrasse 6",
    "sg:city":"Wigoltingen",
    "sg:orig_category":"Werbeberatung Werbung",
    "sg:phone":"+41 52 770 04 30",
    "sg:postcode":"8556",
    "sg:province":"Thurgau",
    "wof:name":"Hebe Werbung & Design Ag",
    "wof:placetype":"venue"
},
  "geometry": {"coordinates":[9.0321063995,47.5958213806],"type":"Point"}
}