{
  "type": "Feature",
  "properties": {
    "iso:country":"CH",
    "sg:address":"Guglerstrasse 7",
    "sg:city":"Nidau",
    "sg:orig_category":"Herstellung von Elektromotoren, Generatoren U Transformatoren",
    "sg:phone":"+41 56 621 92 92",
    "sg:postcode":"2560",
    "sg:province":"Bern",
    "wof:name":"Nse Gmbh",
    "wof:placetype":"venue"
},
  "geometry": {"coordinates":[8.2910175323,47.3471755981],"type":"Point"}
}