{
  "type": "Feature",
  "properties": {
    "iso:country":"CH",
    "sg:address":"Pr\u00e9-bois Route De 20 1216 Cointrin. Postfach",
    "sg:city":"Cointrin",
    "sg:orig_category":"Grosshandel mit sonstigen Gebrauchs U Verbrauchsg\u00fctern",
    "sg:phone":"+41 22 700 70 83",
    "sg:postcode":"1216",
    "sg:province":"Gen\u00e8ve",
    "wof:name":"Luxor Global Trading S\u00e0rl",
    "wof:placetype":"venue"
},
  "geometry": {"coordinates":[6.1084361076,46.2241477966],"type":"Point"}
}