{
  "type": "Feature",
  "properties": {
    "iso:country":"CH",
    "sg:address":"Arbonerstrasse 28",
    "sg:city":"Romanshorn",
    "sg:orig_category":"Personal U Stellenvermittlung Unternehmensberatung",
    "sg:phone":"+41 71 463 70 60",
    "sg:postcode":"8590",
    "sg:province":"Thurgau",
    "wof:name":"M\u00e4der & Partner Ag Wirtschaftsberatung",
    "wof:placetype":"venue"
},
  "geometry": {"coordinates":[9.3670463562,47.5623397827],"type":"Point"}
}