{
  "type": "Feature",
  "properties": {
    "iso:country":"CH",
    "sg:address":"Kirchstrasse 9",
    "sg:city":"Oberrieden",
    "sg:orig_category":"Tierarztpraxis",
    "sg:phone":"+41 79 688 44 66",
    "sg:postcode":"8942",
    "sg:province":"Z\u00fcrich",
    "wof:name":"Dr. Med. Vet. Esther Burri Tier\u00e4rztin",
    "wof:placetype":"venue"
},
  "geometry": {"coordinates":[8.5773439407,47.2761688232],"type":"Point"}
}