{
  "type": "Feature",
  "properties": {
    "iso:country":"CH",
    "sg:address":"Arova-areal",
    "sg:city":"Flurlingen",
    "sg:orig_category":"Architekturb\u00fcros",
    "sg:phone":"+41 71 223 40 40",
    "sg:postcode":"8247",
    "sg:province":"Z\u00fcrich",
    "wof:name":"Kaderli & Wehrli Architekten",
    "wof:placetype":"venue"
},
  "geometry": {"coordinates":[9.370527,47.42223],"type":"Point"}
}