{
  "type": "Feature",
  "properties": {
    "iso:country":"CH",
    "sg:address":"Pantera Via 21 6500 Bellinzona. Postfach",
    "sg:city":"Fiesso",
    "sg:orig_category":"Unclassifiable Establishments",
    "sg:postcode":"6772",
    "sg:province":"Ticino",
    "wof:name":"Gaillard Terribilini Stefania Vendita Articoli In Fibra Naturale Per Arredo Casa",
    "wof:placetype":"venue"
},
  "geometry": {"coordinates":[9.034611702,46.1996879578],"type":"Point"}
}