{
  "type": "Feature",
  "properties": {
    "iso:country":"CH",
    "sg:address":"Friesstrasse 19 8050 Z\u00fcrich. Postfach 8329 8050 Z\u00fcrich",
    "sg:city":"Zust",
    "sg:orig_category":"Elektroinstallation Grosshandel mit sonstigen Maschinen U Ausr\u00fcstungen f\u00fcr Industrie, Handel U Schif",
    "sg:phone":"+41 13023348",
    "sg:postcode":"50",
    "wof:name":"Elektrohammer Ag",
    "wof:placetype":"venue"
},
  "geometry": {"coordinates":[8.5465049744,47.4147033691],"type":"Point"}
}