{
  "type": "Feature",
  "properties": {
    "iso:country":"CH",
    "sg:address":"Laveggio Via 21",
    "sg:city":"Mendrisio",
    "sg:orig_category":"Herstellung von sonstigen elektrischen Ausr\u00fcstungen",
    "sg:phone":"+41 91 647 06 88",
    "sg:postcode":"6850",
    "sg:province":"Ticino",
    "wof:name":"Elettroforniture Sagl",
    "wof:placetype":"venue"
},
  "geometry": {"coordinates":[8.9780750275,45.8785362244],"type":"Point"}
}