{
  "type": "Feature",
  "properties": {
    "addr:full":"G\u00e4ssli 17 3232 Ins. Postfach Ins Bern 3232",
    "addr:housenumber":"17",
    "addr:postcode":"3232 ins. postfach ins;3232",
    "addr:street":"Gaessli;Bern",
    "iso:country":"CH",
    "sg:address":"G\u00e4ssli 17 3232 Ins. Postfach",
    "sg:city":"Ins",
    "sg:orig_category":"Architekturb\u00fcros",
    "sg:phone":"+41 32 313 26 80",
    "sg:postcode":"3232",
    "sg:province":"Bern",
    "wof:name":"Markus Rudin Architekturb\u00fcro",
    "wof:placetype":"venue"
},
  "geometry": {"coordinates":[7.104748,47.003887],"type":"Point"}
}