{
  "type": "Feature",
  "properties": {
    "iso:country":"CH",
    "sg:address":"8852",
    "sg:city":"Altendorf",
    "sg:orig_category":"Vorschulen, Kinderg\u00e4rten",
    "sg:phone":"+41 55 442 13 13",
    "sg:postcode":"8852",
    "sg:province":"Schwyz",
    "wof:name":"Kindergarten Hinterfeld",
    "wof:placetype":"venue"
},
  "geometry": {"coordinates":[8.8292293549,47.1925735474],"type":"Point"}
}