{
  "type": "Feature",
  "properties": {
    "iso:country":"CH",
    "sg:address":"Hauptstrasse 13",
    "sg:city":"Anwil",
    "sg:classifiers":[
        {
            "category":"Restaurant",
            "type":"Food & Drink"
        }
    ],
    "sg:phone":"+41 61 991 06 18",
    "sg:postcode":"4469",
    "sg:province":"Basel-Landschaft",
    "wof:name":"Restaurant J\u00e4gerst\u00fcbli",
    "wof:placetype":"venue"
},
  "geometry": {"coordinates":[7.9392781258,47.449508667],"type":"Point"}
}