{
  "type": "Feature",
  "properties": {
    "iso:country":"CH",
    "sg:address":"Haldenstrasse 87",
    "sg:city":"Z\u00fcrich",
    "sg:orig_category":"Druckweiterverarbeitung",
    "sg:phone":"+41 14623970",
    "sg:postcode":"8045",
    "sg:province":"Z\u00fcrich",
    "wof:name":"Buchbinderei Und Buchstudio Renfer",
    "wof:placetype":"venue"
},
  "geometry": {"coordinates":[8.5157403946,47.3661003113],"type":"Point"}
}