{
  "type": "Feature",
  "properties": {
    "iso:country":"CH",
    "sg:address":"Rue Des Bourguillards 6",
    "sg:city":"St-blaise",
    "sg:orig_category":"Interessenvertretungen",
    "sg:postcode":"2072",
    "sg:province":"Neuch\u00e2tel",
    "wof:name":"Fondation Elisa Junier",
    "wof:placetype":"venue"
},
  "geometry": {"coordinates":[6.9864630699,47.0146827698],"type":"Point"}
}