{
  "type": "Feature",
  "properties": {
    "iso:country":"CH",
    "sg:address":"Girenhaldenweg 15",
    "sg:city":"Bettingen",
    "sg:orig_category":"Herstellung von Werkzeugen Technische, physikalische U chemische Untersuchung",
    "sg:phone":"+41 61 601 71 11",
    "sg:postcode":"4126",
    "sg:province":"Basel-Stadt",
    "wof:name":"Ablg Bio-rat Ag",
    "wof:placetype":"venue"
},
  "geometry": {"coordinates":[7.6614818573,47.5690422058],"type":"Point"}
}