{
  "type": "Feature",
  "properties": {
    "iso:country":"CH",
    "sg:address":"Le Brue 2",
    "sg:city":"Vicques",
    "sg:classifiers":[
        {
            "category":"Insurance",
            "subcategory":"Insurance Agent",
            "type":"Services"
        }
    ],
    "sg:phone":"+41 32 435 66 57",
    "sg:postcode":"2824",
    "sg:province":"Jura",
    "sg:tags":[
        "versicherungsagenturen",
        "-broker"
    ],
    "wof:name":"Winterthur-assurances Agence",
    "wof:placetype":"venue"
},
  "geometry": {"coordinates":[7.4098978043,47.3465805054],"type":"Point"}
}