{
  "type": "Feature",
  "properties": {
    "iso:country":"CH",
    "sg:address":"Rte De France 17",
    "sg:city":"Boncourt",
    "sg:classifiers":[
        {
            "category":"Shopping",
            "subcategory":"Gifts & Souvenirs",
            "type":"Retail Goods"
        }
    ],
    "sg:phone":"+41 32 475 05 05",
    "sg:postcode":"2926",
    "sg:province":"Jura",
    "sg:tags":[
        "product",
        "miscellaneous"
    ],
    "wof:name":"British American Tobacco",
    "wof:placetype":"venue"
},
  "geometry": {"coordinates":[7.0157160759,47.5000686646],"type":"Point"}
}