{
  "type": "Feature",
  "properties": {
    "iso:country":"CH",
    "sg:address":"Luftmattstrasse 15",
    "sg:city":"Basel",
    "sg:orig_category":"Zahnarztpraxen",
    "sg:phone":"+41 61 312 22 19",
    "sg:postcode":"4052",
    "sg:province":"Basel-Stadt",
    "wof:name":"Dr.med.dent.anne-g. Imobersteg Zahn\u00e4rztin",
    "wof:placetype":"venue"
},
  "geometry": {"coordinates":[7.6025118828,47.5478553772],"type":"Point"}
}