{
  "type": "Feature",
  "properties": {
    "iso:country":"CH",
    "sg:address":"Talweg 123",
    "sg:city":"Uster",
    "sg:orig_category":"Herstellung von Armaturen",
    "sg:phone":"+41 17250778",
    "sg:postcode":"8610",
    "sg:province":"Z\u00fcrich",
    "wof:name":"Tsch\u00e4pp\u00e4t Ag",
    "wof:placetype":"venue"
},
  "geometry": {"coordinates":[8.7309598923,47.3481903076],"type":"Point"}
}