{
  "type": "Feature",
  "properties": {
    "iso:country":"CH",
    "sg:address":"Gallaria Milo",
    "sg:city":"Sent",
    "sg:orig_category":"Datenverarbeitungsdienste Softwareentwicklung U beratung",
    "sg:phone":"+41 81 860 00 33",
    "sg:postcode":"7554",
    "sg:province":"Graubunden",
    "wof:name":"Informatica Schmidt",
    "wof:placetype":"venue"
},
  "geometry": {"coordinates":[10.337835,46.816792],"type":"Point"}
}