{
  "type": "Feature",
  "properties": {
    "iso:country":"CH",
    "sg:address":"Ruelle De L'ecluse 10",
    "sg:city":"Del\u00e9mont",
    "sg:orig_category":"Politische Vereinigungen",
    "sg:postcode":"2800",
    "sg:province":"Jura",
    "wof:name":"Rassemblement Jurassien.",
    "wof:placetype":"venue"
},
  "geometry": {"coordinates":[7.3506422043,47.3633956909],"type":"Point"}
}