{
  "type": "Feature",
  "properties": {
    "iso:country":"CH",
    "sg:address":"Vogelherdstrasse",
    "sg:city":"Solothurn",
    "sg:orig_category":"Herstellung von Mess U Kontrollinstrumenten U vorrichtungen",
    "sg:phone":"+41 32 626 36 60",
    "sg:postcode":"4500",
    "sg:province":"Solothurn",
    "wof:name":"Infotech Ag",
    "wof:placetype":"venue"
},
  "geometry": {"coordinates":[7.5187001228,47.2145767212],"type":"Point"}
}