{
  "type": "Feature",
  "properties": {
    "iso:country":"CH",
    "sg:address":"Chemin De La Provence 3",
    "sg:city":"Ardon",
    "sg:orig_category":"Berufsbildende weiterf\u00fchrende Schulen",
    "sg:phone":"+41 27 306 72 86",
    "sg:postcode":"1957",
    "sg:province":"Valais",
    "wof:name":"Ecole Profess.de Massages Paramediform Diffusion S\u00e0rl",
    "wof:placetype":"venue"
},
  "geometry": {"coordinates":[7.258151,46.204899],"type":"Point"}
}