{
  "type": "Feature",
  "properties": {
    "iso:country":"CH",
    "sg:address":"Chemin Des Boveresses 155 1066 Epalinges Case Postale 34",
    "sg:city":"Epalinges",
    "sg:orig_category":"Medizinische Labors",
    "sg:phone":"+41 21 692 59 66",
    "sg:postcode":"1066",
    "sg:province":"Vaud",
    "wof:name":"Institut Ludwig De Recherche Sur Le Cancer",
    "wof:placetype":"venue"
},
  "geometry": {"coordinates":[6.6628470421,46.54271698],"type":"Point"}
}