{
  "type": "Feature",
  "properties": {
    "iso:country":"CH",
    "sg:address":"Hauptstr. 84.",
    "sg:city":"Muotathal",
    "sg:orig_category":"Detailhandel mit M\u00f6beln U Haushaltsgegenst\u00e4nden",
    "sg:phone":"+41 41 831 00 31",
    "sg:postcode":"6436",
    "sg:province":"Schwyz",
    "wof:name":"Inderbitzin R\u00f6sly.",
    "wof:placetype":"venue"
},
  "geometry": {"coordinates":[8.7625627518,46.9725608826],"type":"Point"}
}