{
  "type": "Feature",
  "properties": {
    "iso:country":"CH",
    "sg:address":"Fahrweidstrasse 46",
    "sg:city":"Geroldswil",
    "sg:orig_category":"Saunas, Solarien, Fitnesszentren U \u00e4hnliches",
    "sg:postcode":"8954",
    "sg:province":"Z\u00fcrich",
    "wof:name":"Isler & Partner",
    "wof:placetype":"venue"
},
  "geometry": {"coordinates":[8.4157247543,47.4184761047],"type":"Point"}
}