{
  "type": "Feature",
  "properties": {
    "iso:country":"CH",
    "sg:address":"Br\u00fchlstrasse 2a 9320 Arbon. Postfach 237",
    "sg:city":"Arbon",
    "sg:orig_category":"Architektur U Ingenieurb\u00fcros",
    "sg:phone":"+41 71 447 89 40",
    "sg:postcode":"9320",
    "sg:province":"Thurgau",
    "wof:name":"Ingenieurb\u00fcro W\u00e4lli Ag",
    "wof:placetype":"venue"
},
  "geometry": {"coordinates":[9.431589,47.51297],"type":"Point"}
}