{
  "type": "Feature",
  "properties": {
    "iso:country":"CH",
    "sg:address":"Bahnweg 3c",
    "sg:city":"H\u00e4gendorf",
    "sg:orig_category":"Abwasserreinigung, Abfallbeseitigung U sonstige Entsorgung",
    "sg:phone":"+41 62 216 28 79",
    "sg:postcode":"4614",
    "sg:province":"Solothurn",
    "wof:name":"Rohrreinigungsdienst Gmbh Loriol + Rufer",
    "wof:placetype":"venue"
},
  "geometry": {"coordinates":[7.842974,47.33062],"type":"Point"}
}