{
  "type": "Feature",
  "properties": {
    "iso:country":"CH",
    "sg:address":"Marktgasse 9 3011 Bern. Postfach",
    "sg:city":"Bern",
    "sg:orig_category":"Detailhandel mit Bekleidung",
    "sg:postcode":"3005",
    "sg:province":"Bern",
    "wof:name":"L'uomo M\u00fchlethaler Liane. Herrenmode; Verkauf.",
    "wof:placetype":"venue"
},
  "geometry": {"coordinates":[7.446896,46.9478],"type":"Point"}
}