{
  "type": "Feature",
  "properties": {
    "iso:country":"CH",
    "sg:address":"1636 Broc. Postfach",
    "sg:city":"Broc",
    "sg:orig_category":"Non-Classified Establishments",
    "sg:postcode":"1636",
    "sg:province":"Fribourg",
    "wof:name":"Si Centre-broc",
    "wof:placetype":"venue"
},
  "geometry": {"coordinates":[7.1003518105,46.6031494141],"type":"Point"}
}