{
  "type": "Feature",
  "properties": {
    "iso:country":"CH",
    "sg:address":"Waisenhausstrasse 2",
    "sg:city":"Thun",
    "sg:orig_category":"M\u00f6belschreinereien",
    "sg:postcode":"3600",
    "sg:province":"Bern",
    "wof:name":"Aebischer Christian Menuiserie S\u00e0rl",
    "wof:placetype":"venue"
},
  "geometry": {"coordinates":[6.8533539772,46.5883216858],"type":"Point"}
}