{
  "type": "Feature",
  "properties": {
    "iso:country":"CH",
    "sg:address":"Poststrasse 3 8001 Z\u00fcrich. Postfach",
    "sg:city":"Z\u00fcrich",
    "sg:orig_category":"Effektenverwaltung Privatbanken",
    "sg:phone":"+41 31 329 31 11",
    "sg:postcode":"8001",
    "sg:province":"Z\u00fcrich",
    "wof:name":"Von Graffenried Ag Privatbank",
    "wof:placetype":"venue"
},
  "geometry": {"coordinates":[7.4462900162,46.947479248],"type":"Point"}
}