{
  "type": "Feature",
  "properties": {
    "iso:country":"CH",
    "sg:address":"Seefeldstrasse 134",
    "sg:city":"Z\u00fcrich",
    "sg:orig_category":"Softwareentwicklung U beratung",
    "sg:phone":"+41 13802221",
    "sg:postcode":"8008",
    "sg:province":"Z\u00fcrich",
    "wof:name":"Newcon, Hersener Ralph",
    "wof:placetype":"venue"
},
  "geometry": {"coordinates":[8.5544471741,47.3574676514],"type":"Point"}
}