{
  "type": "Feature",
  "properties": {
    "iso:country":"CH",
    "sg:address":"Rue Du Grand-pont 6 1003 Lausanne Case Postale 240",
    "sg:city":"Lausanne",
    "sg:orig_category":"Grossbanken",
    "sg:phone":"+41 21 340 11 11",
    "sg:postcode":"1001",
    "sg:province":"Vaud",
    "wof:name":"Credit Suisse Succursale",
    "wof:placetype":"venue"
},
  "geometry": {"coordinates":[6.6306300163,46.5213737488],"type":"Point"}
}