{
  "type": "Feature",
  "properties": {
    "iso:country":"CH",
    "sg:address":"Vuarpilli\u00e8re Ch. De La 31 1260 Nyon. Postfach",
    "sg:city":"Z\u00fcrich",
    "sg:orig_category":"Fernmeldedienste",
    "sg:phone":"+41 12851111",
    "sg:postcode":"8001",
    "sg:province":"Z\u00fcrich",
    "wof:name":"Callahan Broadband Wireless Schweiz Gmbh Dienstleistungen Im Bereich Telekommunikation",
    "wof:placetype":"venue"
},
  "geometry": {"coordinates":[6.2390799522,46.3823661804],"type":"Point"}
}