{
  "type": "Feature",
  "properties": {
    "iso:country":"CH",
    "sg:address":"Bernstrasse 108",
    "sg:city":"Rothrist",
    "sg:orig_category":"Elektrizit\u00e4tsversorgung",
    "sg:phone":"+41 55 246 13 76",
    "sg:postcode":"4852",
    "sg:province":"Aargau",
    "wof:name":"Ew Wald Ag Elektrische Energie; Beschaffung, Verkauf, Verteilung. Elektroanlagen Usw.; Planung, Installation, Handel",
    "wof:placetype":"venue"
},
  "geometry": {"coordinates":[8.9413003922,47.2884101868],"type":"Point"}
}