{
  "type": "Feature",
  "properties": {
    "iso:country":"CH",
    "sg:address":"R\u00e9sidence Mila",
    "sg:city":"Champ\u00e9ry",
    "sg:orig_category":"Sonstiger Grosshandel",
    "sg:postcode":"1874",
    "sg:province":"Valais",
    "wof:name":"Carpatrans Ltd, \u00e0 Londres, Succursale De Champ\u00e9ry",
    "wof:placetype":"venue"
},
  "geometry": {"coordinates":[6.8706860542,46.1794052124],"type":"Point"}
}