{
  "type": "Feature",
  "properties": {
    "iso:country":"CH",
    "sg:address":"Baselstrasse 99",
    "sg:city":"Luzern",
    "sg:orig_category":"Detailhandel mit M\u00f6beln",
    "sg:phone":"+41 41 240 84 15",
    "sg:postcode":"6003",
    "sg:province":"Luzern",
    "wof:name":"Otto Bruggmann M\u00f6bel",
    "wof:placetype":"venue"
},
  "geometry": {"coordinates":[8.2884922028,47.0549316406],"type":"Point"}
}