{
  "type": "Feature",
  "properties": {
    "iso:country":"CH",
    "sg:address":"Buchmattstrasse 52 3400 Burgdorf. Postfach",
    "sg:city":"Burgdorf",
    "sg:orig_category":"Herstellung von Metallkonstruktionen Schlossereien",
    "sg:phone":"+41 34 422 47 22",
    "sg:postcode":"3401",
    "sg:province":"Bern",
    "wof:name":"Diethelm Ag Metallbau",
    "wof:placetype":"venue"
},
  "geometry": {"coordinates":[7.6058068275,47.0637779236],"type":"Point"}
}