{
  "type": "Feature",
  "properties": {
    "iso:country":"CH",
    "sg:address":"Grand-rue 59 1196 Gland. Postfach",
    "sg:city":"Gland",
    "sg:orig_category":"Vermietung U Verpachtung von eigenen Immobilien",
    "sg:postcode":"1196",
    "sg:province":"Vaud",
    "wof:name":"M\u00fcller Fran\u00e7ois Immeubles Etc",
    "wof:placetype":"venue"
},
  "geometry": {"coordinates":[6.2650990486,46.4239273071],"type":"Point"}
}