{
  "type": "Feature",
  "properties": {
    "iso:country":"CH",
    "sg:address":"Ouchy Avenue De 27 1000 Lausanne. Postfach",
    "sg:city":"Lausanne",
    "sg:orig_category":"Interessenvertretungen",
    "sg:phone":"+41 21 601 95 55",
    "sg:postcode":"1000",
    "sg:province":"Vaud",
    "wof:name":"La Voie Lactee S\u00e0rl Agence Culturelle Et Voyage",
    "wof:placetype":"venue"
},
  "geometry": {"coordinates":[6.6947751045,46.5545883179],"type":"Point"}
}