{
  "type": "Feature",
  "properties": {
    "iso:country":"CH",
    "sg:address":"Grand'rue 7 2108 Couvet Case Postale 249",
    "sg:city":"Couvet",
    "sg:orig_category":"Advokaturb\u00fcros",
    "sg:phone":"+41 32 863 21 71",
    "sg:postcode":"2108",
    "sg:province":"Neuch\u00e2tel",
    "wof:name":"Walder-de Montmollin & Klauser Etude D'avocat",
    "wof:placetype":"venue"
},
  "geometry": {"coordinates":[6.630678,46.926178],"type":"Point"}
}