{
  "type": "Feature",
  "properties": {
    "iso:country":"CH",
    "sg:address":"Chemin De Pr\u00e9-marquis 7d 1241 Puplinge. Postfach",
    "sg:city":"Gen\u00e8ve",
    "sg:orig_category":"Grosshandel mit Holz U Bauelementen aus Holz Grosshandel mit Holz U Baustoffen",
    "sg:phone":"+41 22 700 17 43",
    "sg:postcode":"1207",
    "sg:province":"Gen\u00e8ve",
    "wof:name":"Ceresxo Trading Sarl Bois Etc.; Importation, Exportation, Commercialisation",
    "wof:placetype":"venue"
},
  "geometry": {"coordinates":[6.2326841354,46.2129745483],"type":"Point"}
}