{
  "type": "Feature",
  "properties": {
    "iso:country":"CH",
    "sg:address":"B\u00f6smattweg 3",
    "sg:city":"Bellikon",
    "sg:orig_category":"Sonstige mit der Informatik verbundene T\u00e4tigkeiten",
    "sg:postcode":"5454",
    "sg:province":"Aargau",
    "wof:name":"B-in-motion Ag",
    "wof:placetype":"venue"
},
  "geometry": {"coordinates":[9.3690042496,47.4252624512],"type":"Point"}
}