{
  "type": "Feature",
  "properties": {
    "iso:country":"CH",
    "sg:address":"Wiesenstrasse 9",
    "sg:city":"Thal",
    "sg:orig_category":"Grosshandel mit Obst U Gem\u00fcse",
    "sg:phone":"+41 71 888 61 78",
    "sg:postcode":"9425",
    "sg:province":"St. Gallen",
    "wof:name":"Eberle Und Eberle",
    "wof:placetype":"venue"
},
  "geometry": {"coordinates":[9.5620145798,47.4648361206],"type":"Point"}
}