{
  "type": "Feature",
  "properties": {
    "iso:country":"CH",
    "sg:address":"Route De Lutry 17",
    "sg:city":"Savigny",
    "sg:orig_category":"Mit Sport verbundene T\u00e4tigkeiten",
    "sg:phone":"+41 21 781 19 04",
    "sg:postcode":"1073",
    "sg:province":"Vaud",
    "wof:name":"Man\u00e8ge De La Lutrive",
    "wof:placetype":"venue"
},
  "geometry": {"coordinates":[6.7255148888,46.5280838013],"type":"Point"}
}