{
  "type": "Feature",
  "properties": {
    "iso:country":"CH",
    "sg:address":"Via Della Pace 5",
    "sg:city":"Locarno",
    "sg:orig_category":"Herstellung von Reiseartikeln, Leder U Sattlerwaren",
    "sg:phone":"+41 32 968 13 81",
    "sg:postcode":"6600",
    "sg:province":"Ticino",
    "wof:name":"Rodal Fabrication De Bracelets Cuir",
    "wof:placetype":"venue"
},
  "geometry": {"coordinates":[6.8261990547,47.1065483093],"type":"Point"}
}