{
  "type": "Feature",
  "properties": {
    "iso:country":"CH",
    "sg:address":"Le N\u00e9zot",
    "sg:city":"Gr\u00f4ne",
    "sg:orig_category":"Einbau von Schreinerwaren",
    "sg:phone":"+41 27 458 26 64",
    "sg:postcode":"3979",
    "sg:province":"Valais",
    "wof:name":"Charly Ballestraz Agencement De Cuisines",
    "wof:placetype":"venue"
},
  "geometry": {"coordinates":[7.458398819,46.2508621216],"type":"Point"}
}