{
  "type": "Feature",
  "properties": {
    "iso:country":"CH",
    "sg:address":"Stanserstrasse 109",
    "sg:city":"Kerns",
    "sg:orig_category":"Finanzierungsinstitutionen",
    "sg:phone":"+41 41 660 42 21",
    "sg:postcode":"6064",
    "sg:province":"Obwalden",
    "wof:name":"Wiko Finanz Ag",
    "wof:placetype":"venue"
},
  "geometry": {"coordinates":[8.279299736,46.903339386],"type":"Point"}
}