{
  "type": "Feature",
  "properties": {
    "iso:country":"CH",
    "sg:address":"Wassbergstr. 11",
    "sg:city":"Maur",
    "sg:orig_category":"Maler U Glasergewerbe",
    "sg:postcode":"8124",
    "sg:province":"Z\u00fcrich",
    "wof:name":"Gfeller Malergesch\u00c4ft",
    "wof:placetype":"venue"
},
  "geometry": {"coordinates":[7.5389900208,46.8218536377],"type":"Point"}
}