{
  "type": "Feature",
  "properties": {
    "iso:country":"CH",
    "sg:address":"3995",
    "sg:city":"Ausserbinn",
    "sg:classifiers":[
        {
            "category":"Restaurant",
            "type":"Food & Drink"
        }
    ],
    "sg:phone":"+41 27 971 11 31",
    "sg:postcode":"3995",
    "sg:province":"Valais",
    "wof:name":"Restaurant J\u00e4gerheim",
    "wof:placetype":"venue"
},
  "geometry": {"coordinates":[8.1467695236,46.382270813],"type":"Point"}
}