{
  "type": "Feature",
  "properties": {
    "iso:country":"CH",
    "sg:address":"Route Du Village 14 1872 Troistorrents. Postfach",
    "sg:city":"Troistorrents",
    "sg:orig_category":"Non-Classified Establishments",
    "sg:postcode":"1872",
    "sg:province":"Valais",
    "wof:name":"Perle De Beaut\u00e9 - Cannistra Virginie",
    "wof:placetype":"venue"
},
  "geometry": {"coordinates":[6.9136400223,46.2265701294],"type":"Point"}
}