{
  "type": "Feature",
  "properties": {
    "addr:full":"Bahnhofstrasse 23 B\u00e4tterkinden Bern 3315",
    "addr:housenumber":"23",
    "addr:postcode":"3315",
    "addr:street":"Bahnhofstrasse",
    "iso:country":"CH",
    "sg:address":"Bahnhofstrasse 23",
    "sg:city":"B\u00e4tterkinden",
    "sg:orig_category":"Detailhandel mit Blumen U Pflanzen",
    "sg:phone":"+41 79 631 56 93",
    "sg:postcode":"3315",
    "sg:province":"Bern",
    "wof:name":"Bigler Samen Ag",
    "wof:placetype":"venue"
},
  "geometry": {"coordinates":[7.533734,47.129276],"type":"Point"}
}