{
  "type": "Feature",
  "properties": {
    "iso:country":"CH",
    "sg:address":"Schmidhusen 19",
    "sg:city":"Herisau",
    "sg:orig_category":"Unternehmensberatung",
    "sg:phone":"+41 71 350 16 00",
    "sg:postcode":"9100",
    "sg:province":"Appenzell Ausserrhoden",
    "wof:name":"Knellwolf Consulting",
    "wof:placetype":"venue"
},
  "geometry": {"coordinates":[9.2619905472,47.3793487549],"type":"Point"}
}