{
  "type": "Feature",
  "properties": {
    "iso:country":"CH",
    "sg:address":"Bleichestrasse 32",
    "sg:city":"Winterthur",
    "sg:orig_category":"Minigolfpl\u00e4tze",
    "sg:phone":"+41 52 223 10 10",
    "sg:postcode":"8400",
    "sg:province":"Z\u00fcrich",
    "wof:name":"Golf In Minigolf",
    "wof:placetype":"venue"
},
  "geometry": {"coordinates":[8.7190685272,47.5051612854],"type":"Point"}
}