{
  "type": "Feature",
  "properties": {
    "iso:country":"CH",
    "sg:address":"Liebewilstrasse 40",
    "sg:city":"Th\u00f6rishaus",
    "sg:orig_category":"Haltung von Gefl\u00fcgel",
    "sg:phone":"+41 31 889 01 52",
    "sg:postcode":"3174",
    "sg:province":"Bern",
    "wof:name":"H. & R. Pulfer, Gefl\u00fcgelfarm Ag",
    "wof:placetype":"venue"
},
  "geometry": {"coordinates":[7.3580861092,46.9036521912],"type":"Point"}
}