{
  "type": "Feature",
  "properties": {
    "iso:country":"CH",
    "sg:address":"Hegistrasse 1a",
    "sg:city":"Thal",
    "sg:orig_category":"Handel mit Motorr\u00e4dern, Teilen U Zubeh\u00f6r Instandhaltung U Reparatur von Motorr\u00e4dern",
    "sg:phone":"+41 62 822 31 81",
    "sg:postcode":"9425",
    "sg:province":"St. Gallen",
    "wof:name":"Biker Mike Zweiradshop, Keusch M.",
    "wof:placetype":"venue"
},
  "geometry": {"coordinates":[8.0766773224,47.3878097534],"type":"Point"}
}