{
  "type": "Feature",
  "properties": {
    "iso:country":"CH",
    "sg:address":"Centralstrasse 43",
    "sg:city":"Sursee",
    "sg:orig_category":"Kochherd and -apparate Herstelllung Treibhaus- and Wintergartenbau",
    "sg:phone":"+41 21 926 66 39",
    "sg:postcode":"6210",
    "sg:province":"Luzern",
    "wof:name":"Radiamon Sa Prod.de Syst\u00e8mes Thermiques",
    "wof:placetype":"venue"
},
  "geometry": {"coordinates":[5.4990701675,45.4233818054],"type":"Point"}
}