{
  "type": "Feature",
  "properties": {
    "iso:country":"CH",
    "sg:address":"Hauptstrasse 83",
    "sg:city":"Sissach",
    "sg:orig_category":"Pensionskassen",
    "sg:postcode":"4450",
    "sg:province":"Basel-Landschaft",
    "wof:name":"Personalvorsorgestiftung Der Firma Hotel-restaurant Zur Sonne Agsissach",
    "wof:placetype":"venue"
},
  "geometry": {"coordinates":[7.8101348877,47.464389801],"type":"Point"}
}