{
  "type": "Feature",
  "properties": {
    "addr:full":"6017 Ruswil. Postfach 313 Ruswil Luzern 6017",
    "addr:housenumber":"313",
    "addr:postcode":"6017;6017",
    "addr:street":"Ruswil. Postfach",
    "iso:country":"CH",
    "sg:address":"6017 Ruswil. Postfach 313",
    "sg:city":"Ruswil",
    "sg:classifiers":[
        {
            "category":"Social Services",
            "subcategory":"Retirement Home",
            "type":"Services"
        }
    ],
    "sg:phone":"+41 17614017",
    "sg:postcode":"6017",
    "sg:province":"Luzern",
    "sg:tags":[
        "pflegeheime",
        "u",
        "alters"
    ],
    "wof:name":"Alterswohnheim Seewadel Verwaltung",
    "wof:placetype":"venue"
},
  "geometry": {"coordinates":[8.44651,47.278179],"type":"Point"}
}