{
  "type": "Feature",
  "properties": {
    "iso:country":"CH",
    "sg:address":"Hauptstrasse 90",
    "sg:city":"Arisdorf",
    "sg:orig_category":"Schlossereien Stahl U Leichtmetallbau",
    "sg:phone":"+41 61 811 68 66",
    "sg:postcode":"4422",
    "sg:province":"Basel-Landschaft",
    "wof:name":"Walter Gunti Metallbau/schlosserei",
    "wof:placetype":"venue"
},
  "geometry": {"coordinates":[7.765376091,47.5082855225],"type":"Point"}
}