{
  "type": "Feature",
  "properties": {
    "iso:country":"CH",
    "sg:address":"Bachstrasse 1",
    "sg:city":"Bussnang",
    "sg:orig_category":"Herstellung von Metallkonstruktionen",
    "sg:phone":"+41 71 622 71 48",
    "sg:postcode":"9565",
    "sg:province":"Thurgau",
    "wof:name":"Franco Vigna Schlosserei & Metallbau",
    "wof:placetype":"venue"
},
  "geometry": {"coordinates":[9.0819349289,47.5562133789],"type":"Point"}
}