{
  "type": "Feature",
  "properties": {
    "iso:country":"CH",
    "sg:address":"Risi 7",
    "sg:city":"Gr\u00e4nichen",
    "sg:orig_category":"Vereine Lions",
    "sg:phone":"+41 41 870 13 17",
    "sg:postcode":"5722",
    "sg:province":"Aargau",
    "wof:name":"Lions Club Altdorf",
    "wof:placetype":"venue"
},
  "geometry": {"coordinates":[8.6348772049,46.8773612976],"type":"Point"}
}