{
  "type": "Feature",
  "properties": {
    "iso:country":"CH",
    "sg:address":"Rue De L'eglise",
    "sg:city":"Fully",
    "sg:orig_category":"Zimmerei, Dachdeckerei, Bauspenglerei U Abdichtung",
    "sg:postcode":"1926",
    "sg:province":"Valais",
    "wof:name":"Pasquier Roland",
    "wof:placetype":"venue"
},
  "geometry": {"coordinates":[7.1151638031,46.1387557983],"type":"Point"}
}