{
  "type": "Feature",
  "properties": {
    "iso:country":"CH",
    "sg:address":"Unterseestrasse 65 8280 Kreuzlingen. Postfach 863",
    "sg:city":"Kreuzlingen",
    "sg:orig_category":"Pensionskassen",
    "sg:postcode":"8280",
    "sg:province":"Thurgau",
    "wof:name":"Personalvorsorgestiftung Der Muco Se Muldenbau Ag",
    "wof:placetype":"venue"
},
  "geometry": {"coordinates":[9.4907827377,47.2058181763],"type":"Point"}
}