{
  "type": "Feature",
  "properties": {
    "iso:country":"CH",
    "sg:address":"Salisstrasse 25",
    "sg:city":"St.gallen",
    "sg:orig_category":"Detailhandel mit Sportartikeln Fachdetailhandel in Verkaufsr\u00e4umen",
    "sg:phone":"+41 79 437 14 64",
    "sg:postcode":"9000",
    "sg:province":"St. Gallen",
    "wof:name":"Red Star Sport Gmbh",
    "wof:placetype":"venue"
},
  "geometry": {"coordinates":[9.3546733856,47.4193382263],"type":"Point"}
}