{
  "type": "Feature",
  "properties": {
    "iso:country":"CH",
    "sg:address":"Bohnackerstrasse 5",
    "sg:city":"Dietikon",
    "sg:orig_category":"Kinderkrippen U horte",
    "sg:phone":"+41 17404160",
    "sg:postcode":"8953",
    "sg:province":"Z\u00fcrich",
    "wof:name":"Tageshort Fondli",
    "wof:placetype":"venue"
},
  "geometry": {"coordinates":[8.387008667,47.4081993103],"type":"Point"}
}