{
  "type": "Feature",
  "properties": {
    "iso:country":"CH",
    "sg:address":"2828",
    "sg:city":"Montsevelier",
    "sg:orig_category":"Gemeindeverwaltungen",
    "sg:phone":"+41 26 660 37 84",
    "sg:postcode":"2828",
    "sg:province":"Jura",
    "wof:name":"Administration Communale De Morens Fr",
    "wof:placetype":"venue"
},
  "geometry": {"coordinates":[6.9066200256,46.8436813354],"type":"Point"}
}