{
  "type": "Feature",
  "properties": {
    "iso:country":"CH",
    "sg:address":"Allmendweg 1",
    "sg:city":"Kappelen",
    "sg:orig_category":"Instandhaltung U Reparatur von Automobilen",
    "sg:phone":"+41 79 634 65 38",
    "sg:postcode":"3273",
    "sg:province":"Bern",
    "wof:name":"Garage Mollard",
    "wof:placetype":"venue"
},
  "geometry": {"coordinates":[6.8103551865,46.8257484436],"type":"Point"}
}