{
  "type": "Feature",
  "properties": {
    "iso:country":"CH",
    "sg:address":"Br\u00fcderhofweg 29",
    "sg:city":"Z\u00fcrich",
    "sg:orig_category":"Pers\u00f6nliche Dienstleistungen",
    "sg:phone":"+41 56 282 00 16",
    "sg:postcode":"8057",
    "sg:province":"Z\u00fcrich",
    "wof:name":"Translawyer Gmbh \u00dcbersetzung, Lektorat Juristischer U. Wirtschaftlicher Fachtexte",
    "wof:placetype":"venue"
},
  "geometry": {"coordinates":[8.2894554138,47.4870452881],"type":"Point"}
}