{
  "type": "Feature",
  "properties": {
    "iso:country":"CH",
    "sg:address":"Murg 8877 Murg. Postfach",
    "sg:city":"Murg",
    "sg:orig_category":"Sonstiger Grosshandel",
    "sg:postcode":"8877",
    "sg:province":"St. Gallen",
    "wof:name":"Stonerock Gmbh",
    "wof:placetype":"venue"
},
  "geometry": {"coordinates":[9.2179203033,47.1106796265],"type":"Point"}
}