{
  "type": "Feature",
  "properties": {
    "iso:country":"CH",
    "sg:address":"Kleinstalden",
    "sg:city":"Alberswil",
    "sg:orig_category":"Maler U Glasergewerbe Malerei",
    "sg:phone":"+41 41 970 37 73",
    "sg:postcode":"6248",
    "sg:province":"Luzern",
    "wof:name":"Malergesch\u00e4ft Amrein",
    "wof:placetype":"venue"
},
  "geometry": {"coordinates":[7.9914059639,47.1384811401],"type":"Point"}
}