{
  "type": "Feature",
  "properties": {
    "iso:country":"CH",
    "sg:address":"Oberneuhofstrasse 1",
    "sg:city":"Baar",
    "sg:orig_category":"Handels-H\u00e4user U Gesellschaften",
    "sg:phone":"+41 41 761 05 38",
    "sg:postcode":"6340",
    "sg:province":"Zug",
    "wof:name":"Ap Auto-pool Ag",
    "wof:placetype":"venue"
},
  "geometry": {"coordinates":[8.5149316788,47.1888237],"type":"Point"}
}