{
  "type": "Feature",
  "properties": {
    "iso:country":"CH",
    "sg:address":"Mattenstrasse 9 3800 Matten B. Interl. Postfach",
    "sg:city":"Interlaken",
    "sg:orig_category":"Grosshandel mit Getr\u00e4nken Grosshandel mit Wein U Spirituosen",
    "sg:phone":"+41 33 822 55 55",
    "sg:postcode":"3800",
    "sg:province":"Bern",
    "wof:name":"Vin Di Vin Wein Und Getr\u00e4nkehandel Gmbh",
    "wof:placetype":"venue"
},
  "geometry": {"coordinates":[7.8666501045,46.6771202087],"type":"Point"}
}