{
  "type": "Feature",
  "properties": {
    "iso:country":"CH",
    "sg:address":"Alte Spitalgasse 4 3770 Zweisimmen. Postfach 207",
    "sg:city":"Zweisimmen",
    "sg:orig_category":"Drogerien Sonstiger Fachdetailhandel mit Nahrungsmitteln, Getr\u00e4nken U Tabak in Verkaufsr\u00e4umen",
    "sg:phone":"+41 33 437 16 00",
    "sg:postcode":"3770",
    "sg:province":"Bern",
    "wof:name":"Fritz Moser Pedro-drogerie Moser",
    "wof:placetype":"venue"
},
  "geometry": {"coordinates":[7.3729338646,46.5532722473],"type":"Point"}
}