{
  "type": "Feature",
  "properties": {
    "iso:country":"CH",
    "sg:address":"Kappelergasse 14",
    "sg:city":"Z\u00fcrich",
    "sg:orig_category":"Unclassifiable Establishments",
    "sg:phone":"+41 12110933",
    "sg:postcode":"8001",
    "sg:province":"Z\u00fcrich",
    "wof:name":"Meisterkoepfe Ag",
    "wof:placetype":"venue"
},
  "geometry": {"coordinates":[8.5403757095,47.3690261841],"type":"Point"}
}