{
  "type": "Feature",
  "properties": {
    "iso:country":"CH",
    "sg:address":"Hauptgasse 6",
    "sg:city":"Willisau",
    "sg:orig_category":"Detailhandel mit Getr\u00e4nken",
    "sg:phone":"+41 41 970 30 50",
    "sg:postcode":"6130",
    "sg:province":"Luzern",
    "wof:name":"Kellerei St. Gerog Weine & Getr\u00e4nke",
    "wof:placetype":"venue"
},
  "geometry": {"coordinates":[7.9916439056,47.1209831238],"type":"Point"}
}