{
  "type": "Feature",
  "properties": {
    "iso:country":"CH",
    "sg:address":"L\u00e4rchenweg 7",
    "sg:city":"K\u00fcssnacht",
    "sg:classifiers":[
        {
            "category":"Professional",
            "subcategory":"Computer Services",
            "type":"Services"
        }
    ],
    "sg:postcode":"6403",
    "sg:tags":[
        "collaboration",
        "communication",
        "appliance",
        "software-development",
        "project"
    ],
    "sg:website":"http://www.oriact.com",
    "wof:name":"Oriact",
    "wof:placetype":"venue"
},
  "geometry": {"coordinates":[8.4371634,47.0882193],"type":"Point"}
}