{
  "type": "Feature",
  "properties": {
    "iso:country":"CH",
    "sg:address":"Avenue De Rumine 9 1005 Lausanne Case Postale 4113",
    "sg:city":"Lausanne",
    "sg:orig_category":"Reiseb\u00fcros",
    "sg:phone":"+41 21 312 60 47",
    "sg:postcode":"1002",
    "sg:province":"Vaud",
    "wof:name":"Voyages El Cid",
    "wof:placetype":"venue"
},
  "geometry": {"coordinates":[6.6270709038,46.5230903625],"type":"Point"}
}