{
  "type": "Feature",
  "properties": {
    "iso:country":"CH",
    "sg:address":"Kirchgasse 3",
    "sg:city":"Olten",
    "sg:orig_category":"Detailhandel mit Herrenbekleidung",
    "sg:phone":"+41 62 212 02 82",
    "sg:postcode":"4600",
    "sg:province":"Solothurn",
    "wof:name":"Herren Globus Ag",
    "wof:placetype":"venue"
},
  "geometry": {"coordinates":[7.9021930695,47.3498268127],"type":"Point"}
}