{
  "type": "Feature",
  "properties": {
    "iso:country":"CH",
    "sg:address":"Kirchberstr. 18",
    "sg:city":"Hindelbank",
    "sg:classifiers":[
        {
            "category":"Autos & Motor Vehicles",
            "subcategory":"Automobile Sales",
            "type":"Retail Goods"
        }
    ],
    "sg:phone":"+41 34 411 90 90",
    "sg:postcode":"3324",
    "sg:province":"Bern",
    "sg:tags":[
        "equipment",
        "motor-cars",
        "transport"
    ],
    "wof:name":"Bantam Camping",
    "wof:placetype":"venue"
},
  "geometry": {"coordinates":[7.5484871864,47.0509376526],"type":"Point"}
}