{
  "type": "Feature",
  "properties": {
    "iso:country":"CH",
    "sg:address":"Sunnentalstrasse 14",
    "sg:city":"Wolfhausen",
    "sg:orig_category":"Architektur U Ingenieurb\u00fcros",
    "sg:phone":"+41 55 243 26 88",
    "sg:postcode":"8633",
    "sg:province":"Z\u00fcrich",
    "wof:name":"Marc Ganahl Technisches B\u00fcro",
    "wof:placetype":"venue"
},
  "geometry": {"coordinates":[8.805559,47.254246],"type":"Point"}
}