{
  "type": "Feature",
  "properties": {
    "iso:country":"CH",
    "sg:address":"4536",
    "sg:city":"Attiswil",
    "sg:orig_category":"Landw. Genossenschaften Pferdezucht Landw. Genossenschaften Viehzucht",
    "sg:postcode":"4536",
    "sg:province":"Bern",
    "wof:name":"Pferdezuchtgenossenschaft Des Oberaargaus",
    "wof:placetype":"venue"
},
  "geometry": {"coordinates":[7.6126790047,47.246887207],"type":"Point"}
}