{
  "type": "Feature",
  "properties": {
    "iso:country":"CH",
    "sg:address":"Kaysersbergerstrasse 55",
    "sg:city":"Basel",
    "sg:orig_category":"Erschliessung von Grundst\u00fccken",
    "sg:postcode":"4055",
    "sg:province":"Basel-Stadt",
    "wof:name":"Wohngenossenschaft Kayserbergstrasse",
    "wof:placetype":"venue"
},
  "geometry": {"coordinates":[7.5614290237,47.5652198792],"type":"Point"}
}