{
  "type": "Feature",
  "properties": {
    "iso:country":"CH",
    "sg:address":"Gloriastrasse 35",
    "sg:city":"Z\u00fcrich",
    "sg:orig_category":"Interessenvertretungen",
    "sg:postcode":"8006",
    "sg:province":"Z\u00fcrich",
    "wof:name":"Arbeitsgemeinschaft Prof. Hugel Agph",
    "wof:placetype":"venue"
},
  "geometry": {"coordinates":[8.5528774261,47.3772697449],"type":"Point"}
}