{
  "type": "Feature",
  "properties": {
    "iso:country":"CH",
    "sg:address":"Basse Rue 6 2502 Biel/bienne. Postfach",
    "sg:city":"Biel/bienne",
    "sg:orig_category":"Detailhandel mit elektrischen Haushalts-,Radio U Fernsehger\u00e4ten sowie Musikinstrumenten",
    "sg:phone":"+41 32 323 28 02",
    "sg:postcode":"2502",
    "sg:province":"Bern",
    "wof:name":"Imer Alain Magasin De Disques",
    "wof:placetype":"venue"
},
  "geometry": {"coordinates":[7.2469592094,47.1410255432],"type":"Point"}
}