{
  "type": "Feature",
  "properties": {
    "iso:country":"CH",
    "sg:address":"Grabenstrasse 15",
    "sg:city":"Chur",
    "sg:orig_category":"Detailhandel mit elektrischen Haushalts-,Radio U Fernsehger\u00e4ten sowie Musikinstrumenten Handelsvermi",
    "sg:phone":"+41 79 239 96 14",
    "sg:postcode":"7000",
    "sg:province":"Graubunden",
    "wof:name":"Almyra W\u00fcrgler Walter",
    "wof:placetype":"venue"
},
  "geometry": {"coordinates":[9.3800859451,47.4394989014],"type":"Point"}
}