{
  "type": "Feature",
  "properties": {
    "iso:country":"CH",
    "sg:address":"6781",
    "sg:city":"Bedretto",
    "sg:orig_category":"Sessellifte and Skilifte",
    "sg:phone":"+41 91 869 21 88",
    "sg:postcode":"6781",
    "sg:province":"Ticino",
    "wof:name":"Impianti Turistici Cioss Prato Sa",
    "wof:placetype":"venue"
},
  "geometry": {"coordinates":[8.5122346878,46.5061454773],"type":"Point"}
}