{
  "type": "Feature",
  "properties": {
    "iso:country":"CH",
    "sg:address":"Vorstadt 17",
    "sg:city":"Schaffhausen",
    "sg:orig_category":"Fussreflexzonenmassage P\u00e9dicure",
    "sg:phone":"+41 52 625 98 05",
    "sg:postcode":"8200",
    "sg:province":"Schaffhausen",
    "wof:name":"Louis Joos",
    "wof:placetype":"venue"
},
  "geometry": {"coordinates":[8.6339073181,47.6980285645],"type":"Point"}
}