{
  "type": "Feature",
  "properties": {
    "iso:country":"CH",
    "sg:address":"Wannenstrasse 37",
    "sg:city":"Wiesendangen",
    "sg:orig_category":"Gartenbau",
    "sg:phone":"+41 52 337 14 58",
    "sg:postcode":"8542",
    "sg:province":"Z\u00fcrich",
    "wof:name":"Bruno Theiler Gartenbau & G\u00e4rtnerei",
    "wof:placetype":"venue"
},
  "geometry": {"coordinates":[8.780626297,47.5273208618],"type":"Point"}
}