{
  "type": "Feature",
  "properties": {
    "iso:country":"CH",
    "sg:address":"Unterbiberiststrasse 7",
    "sg:city":"Biberist",
    "sg:orig_category":"Herstellung von industriellen Prozesssteuerungsanlagen",
    "sg:postcode":"4562",
    "sg:province":"Solothurn",
    "wof:name":"Kaiser El.installationen-schaltanlagen",
    "wof:placetype":"venue"
},
  "geometry": {"coordinates":[7.560988903,47.183757782],"type":"Point"}
}