{
  "type": "Feature",
  "properties": {
    "iso:country":"CH",
    "sg:address":"Marktgasse 31 3011 Bern. Postfach",
    "sg:city":"Bern",
    "sg:orig_category":"Institutionen des Sozialwesens ohne Beherbergung",
    "sg:postcode":"3005",
    "sg:province":"Bern",
    "wof:name":"Fonds De D\u00e9veloppement \u00e9conomique Et Social En Ha\u00efti (fides Ha\u00efti) Sammeln V Geldern F Basisorganisationen Zur Unterst\u00fctzung Eigener Entwicklungsbestreben Usw",
    "wof:placetype":"venue"
},
  "geometry": {"coordinates":[7.4457421303,46.9479026794],"type":"Point"}
}