{
  "type": "Feature",
  "properties": {
    "iso:country":"CH",
    "sg:address":"Fbg. Du Lac 6 2500 Biel/bienne. Postfach",
    "sg:city":"Biel/bienne",
    "sg:orig_category":"Kauf U Verkauf von Immobilien auf eigene Rechnung",
    "sg:phone":"+41 32 343 68 11",
    "sg:postcode":"2500",
    "sg:province":"Bern",
    "wof:name":"Maeder-leschot Sa",
    "wof:placetype":"venue"
},
  "geometry": {"coordinates":[7.2369041443,47.1353759766],"type":"Point"}
}