{
  "type": "Feature",
  "properties": {
    "iso:country":"CH",
    "sg:address":"Sandgarten 22 4312 Magden. Postfach",
    "sg:city":"Magden",
    "sg:orig_category":"Unternehmensberatung",
    "sg:phone":"+41 61 843 00 60",
    "sg:postcode":"4312",
    "sg:province":"Aargau",
    "wof:name":"Bubendorf Logistics Consulting",
    "wof:placetype":"venue"
},
  "geometry": {"coordinates":[7.8204321861,47.5278816223],"type":"Point"}
}