{
  "type": "Feature",
  "properties": {
    "iso:country":"CH",
    "sg:address":"Lufingerstrasse 9",
    "sg:city":"Winkel",
    "sg:orig_category":"Bauschreinerei",
    "sg:phone":"+41 31 809 07 17",
    "sg:postcode":"8185",
    "sg:province":"Z\u00fcrich",
    "wof:name":"Fritz Kohler Schreinerei",
    "wof:placetype":"venue"
},
  "geometry": {"coordinates":[7.44063,46.782749],"type":"Point"}
}