{
  "type": "Feature",
  "properties": {
    "iso:country":"CH",
    "sg:address":"Hauptstrasse 64 4313 M\u00f6hlin. Postfach",
    "sg:city":"M\u00f6hlin",
    "sg:orig_category":"Fachdetailhandel mit pharmazeutischen Produkten",
    "sg:phone":"+41 800 300 001",
    "sg:postcode":"4313",
    "sg:province":"Aargau",
    "wof:name":"Apotheke M\u00f6hlin Beatrice Weidmann",
    "wof:placetype":"venue"
},
  "geometry": {"coordinates":[7.8432087898,47.5582923889],"type":"Point"}
}