{
  "type": "Feature",
  "properties": {
    "iso:country":"CH",
    "sg:address":"Pumpwerkstrasse 35 4142 M\u00fcnchenstein. Postfach",
    "sg:city":"M\u00fcnchenstein",
    "sg:orig_category":"Unclassifiable Establishments",
    "sg:postcode":"4142",
    "sg:province":"Basel-Landschaft",
    "wof:name":"Sei Sport Events International Brunner K.",
    "wof:placetype":"venue"
},
  "geometry": {"coordinates":[7.6132998466,47.5146217346],"type":"Point"}
}