{
  "type": "Feature",
  "properties": {
    "iso:country":"CH",
    "sg:address":"M\u00f6sliweg 35",
    "sg:city":"K\u00f6niz",
    "sg:orig_category":"Personal U Stellenvermittlung Unternehmensberatung",
    "sg:phone":"+41 31 971 42 42",
    "sg:postcode":"3098",
    "sg:province":"Bern",
    "wof:name":"Shehzad Brainselect Consulting",
    "wof:placetype":"venue"
},
  "geometry": {"coordinates":[7.4061169624,46.922328949],"type":"Point"}
}