{
  "type": "Feature",
  "properties": {
    "iso:country":"CH",
    "sg:address":"Obsthaldenstrasse 82",
    "sg:city":"Z\u00fcrich",
    "sg:orig_category":"Detailhandel mit B\u00fcchern, Zeitungen, Schreib U Papeteriewaren",
    "sg:postcode":"8046",
    "sg:province":"Z\u00fcrich",
    "wof:name":"Hefele Gmbh",
    "wof:placetype":"venue"
},
  "geometry": {"coordinates":[8.8179,47.22757],"type":"Point"}
}