{
  "type": "Feature",
  "properties": {
    "iso:country":"CH",
    "sg:address":"Rainstrasse 46",
    "sg:city":"Safnern",
    "sg:classifiers":[
        {
            "category":"Professional",
            "subcategory":"Credit Reporting & Collection",
            "type":"Services"
        }
    ],
    "sg:phone":"+41 32 962 50 50",
    "sg:postcode":"2553",
    "sg:province":"Bern",
    "sg:tags":[
        "dial"
    ],
    "wof:name":"Les Fils D'arnold Linder S.a.",
    "wof:placetype":"venue"
},
  "geometry": {"coordinates":[6.904610157,47.1760635376],"type":"Point"}
}