{
  "type": "Feature",
  "properties": {
    "iso:country":"CH",
    "sg:address":"Rue St-s\u00e9bastien 28",
    "sg:city":"Del\u00e9mont",
    "sg:orig_category":"Instandhaltung U Reparatur von Automobilen",
    "sg:phone":"+41 79 251 22 83",
    "sg:postcode":"2800",
    "sg:province":"Jura",
    "wof:name":"Auto Marea S\u00e0rl",
    "wof:placetype":"venue"
},
  "geometry": {"coordinates":[7.3446831703,47.3522872925],"type":"Point"}
}