{
  "type": "Feature",
  "properties": {
    "iso:country":"CH",
    "sg:address":"Industriestrasse 17",
    "sg:city":"Thunstetten",
    "sg:orig_category":"Lagerh\u00e4user, G\u00fcterumschlag, Verteilzentren",
    "sg:phone":"+41 62 958 88 88",
    "sg:postcode":"4922",
    "sg:province":"Bern",
    "wof:name":"Alifet Ag",
    "wof:placetype":"venue"
},
  "geometry": {"coordinates":[7.7561440468,47.2139892578],"type":"Point"}
}