{
  "type": "Feature",
  "properties": {
    "iso:country":"CH",
    "sg:address":"Tobelr\u00fctistrasse 3 8426 Lufingen. Postfach",
    "sg:city":"Glattbrugg",
    "sg:orig_category":"Non-Classified Establishments",
    "sg:postcode":"8152",
    "sg:province":"Z\u00fcrich",
    "wof:name":"Transport Service Th. Schlotterbeck",
    "wof:placetype":"venue"
},
  "geometry": {"coordinates":[8.5910968781,47.4906387329],"type":"Point"}
}