{
  "type": "Feature",
  "properties": {
    "iso:country":"CH",
    "sg:address":"Englischviertelstrasse 7 8032 Z\u00fcrich",
    "sg:city":"Zust",
    "sg:orig_category":"Erzeugung U Erstbearbeitung von Aluminium",
    "sg:postcode":"32",
    "wof:name":"Krd Sammlerladen, Schneider B.",
    "wof:placetype":"venue"
},
  "geometry": {"coordinates":[9.3191003799,47.4219245911],"type":"Point"}
}