{
  "type": "Feature",
  "properties": {
    "iso:country":"CH",
    "sg:address":"D\u00e9vens Les",
    "sg:city":"Bex",
    "sg:orig_category":"Gartenbau",
    "sg:phone":"+41 37524252",
    "sg:postcode":"1880",
    "sg:province":"Vaud",
    "wof:name":"P\u00e9pini\u00e8re Waeber Fr\u00e9d\u00e9ric",
    "wof:placetype":"venue"
},
  "geometry": {"coordinates":[6.914659977,46.6908187866],"type":"Point"}
}