{
  "type": "Feature",
  "properties": {
    "iso:country":"CH",
    "sg:address":"Hinterdorfstrasse 2",
    "sg:city":"D\u00fcrnten",
    "sg:orig_category":"Detailhandel mit Textilien",
    "sg:phone":"+41 55 240 24 81",
    "sg:postcode":"8635",
    "sg:province":"Z\u00fcrich",
    "wof:name":"Elsa Schoch Wolle-mercerie-bonneterie",
    "wof:placetype":"venue"
},
  "geometry": {"coordinates":[8.8423233032,47.2781410217],"type":"Point"}
}