{
  "type": "Feature",
  "properties": {
    "iso:country":"CH",
    "sg:address":"Alte Neuburgstrasse 40",
    "sg:city":"Winterthur",
    "sg:orig_category":"Sportvereine Turnen Vereine Damen",
    "sg:phone":"+41 31 331 15 51",
    "sg:postcode":"8408",
    "sg:province":"Z\u00fcrich",
    "wof:name":"Frauenr.lorraine-breitenrain",
    "wof:placetype":"venue"
},
  "geometry": {"coordinates":[7.4490318298,46.9687995911],"type":"Point"}
}