{
  "type": "Feature",
  "properties": {
    "iso:country":"CH",
    "sg:address":"Bergellerstrasse 20",
    "sg:city":"Z\u00fcrich",
    "sg:orig_category":"Schreib U \u00dcbersetzungsb\u00fcros",
    "sg:postcode":"8049",
    "sg:province":"Z\u00fcrich",
    "wof:name":"Schnider Frau Irma. Schreibb\u00fcro, Lektorieren V. Dokumentationen In Deutsch, Franz\u00f6sisch U. Englisch.",
    "wof:placetype":"venue"
},
  "geometry": {"coordinates":[8.4941110611,47.4060211182],"type":"Point"}
}