{
  "type": "Feature",
  "properties": {
    "iso:country":"CH",
    "sg:address":"Burgfelderstrasse 190",
    "sg:city":"Basel",
    "sg:classifiers":[
        {
            "category":"Social Services",
            "subcategory":"Retirement Home",
            "type":"Services"
        }
    ],
    "sg:phone":"+41 61 271 07 17",
    "sg:postcode":"4055",
    "sg:province":"Basel-Stadt",
    "sg:tags":[
        "pflegeheime",
        "u",
        "alters"
    ],
    "wof:name":"Altersheim Des B\u00fcrgerspitals",
    "wof:placetype":"venue"
},
  "geometry": {"coordinates":[7.573825,47.562038],"type":"Point"}
}