{
  "type": "Feature",
  "properties": {
    "iso:country":"CH",
    "sg:address":"Route De Gr\u00f4ne",
    "sg:city":"R\u00e9chy",
    "sg:classifiers":[
        {
            "category":"Government",
            "subcategory":"Post Office",
            "type":"Public Place"
        }
    ],
    "sg:phone":"+41 27 458 22 58",
    "sg:postcode":"3966",
    "sg:province":"Valais",
    "sg:tags":[
        "caf\u00e9s",
        "tea-rooms"
    ],
    "wof:name":"Tea-room La Cascade",
    "wof:placetype":"venue"
},
  "geometry": {"coordinates":[7.4901418686,46.2604293823],"type":"Point"}
}