{
  "type": "Feature",
  "properties": {
    "iso:country":"CH",
    "sg:address":"3929",
    "sg:city":"T\u00e4sch",
    "sg:orig_category":"Betrieb von Taxis Tankstellen",
    "sg:phone":"+41 27 967 35 35",
    "sg:postcode":"3929",
    "sg:province":"Valais",
    "wof:name":"Marcel Imboden Garage Christophe & Taxi",
    "wof:placetype":"venue"
},
  "geometry": {"coordinates":[7.776325,46.069695],"type":"Point"}
}