{
  "type": "Feature",
  "properties": {
    "iso:country":"CH",
    "sg:address":"Hauptstrasse 44 4450 Sissach. Postfach",
    "sg:city":"Sissach",
    "sg:orig_category":"Detailhandel mit Bekleidung",
    "sg:phone":"+41 61 973 24 44",
    "sg:postcode":"4450",
    "sg:province":"Basel-Landschaft",
    "wof:name":"Fortyfour 44 Men & Women Store Gmbh Kleider-boutique",
    "wof:placetype":"venue"
},
  "geometry": {"coordinates":[7.81441,47.463303],"type":"Point"}
}