{
  "type": "Feature",
  "properties": {
    "iso:country":"CH",
    "sg:address":"Liebestrasse 3",
    "sg:city":"Winterthur",
    "sg:orig_category":"Vereine Gesang",
    "sg:postcode":"8400",
    "sg:province":"Z\u00fcrich",
    "wof:name":"Evangelischer Kirchenchor",
    "wof:placetype":"venue"
},
  "geometry": {"coordinates":[8.7296733856,47.5021209717],"type":"Point"}
}