{
  "type": "Feature",
  "properties": {
    "iso:country":"CH",
    "sg:address":"Sparrenbergstrasse 1",
    "sg:city":"Unterengstringen",
    "sg:classifiers":[
        {
            "category":"Social Services",
            "subcategory":"Job Training",
            "type":"Services"
        }
    ],
    "sg:phone":"+41 17336033",
    "sg:postcode":"8103",
    "sg:province":"Z\u00fcrich",
    "sg:tags":[
        "control",
        "noise",
        "solution"
    ],
    "wof:name":"Emfa Schallschutz Ag",
    "wof:placetype":"venue"
},
  "geometry": {"coordinates":[8.4560213089,47.4161987305],"type":"Point"}
}