{
  "type": "Feature",
  "properties": {
    "iso:country":"CH",
    "sg:address":"1950",
    "sg:city":"Sitten",
    "sg:orig_category":"Werbung",
    "sg:phone":"+41 27 322 20 02",
    "sg:postcode":"1950",
    "sg:province":"Valais",
    "wof:name":"Treize Etoiles.",
    "wof:placetype":"venue"
},
  "geometry": {"coordinates":[7.3633999825,46.2366981506],"type":"Point"}
}