{
  "type": "Feature",
  "properties": {
    "iso:country":"CH",
    "sg:address":"Z\u00fcrcherstrasse 135",
    "sg:city":"Basel",
    "sg:orig_category":"Detailhandel mit Blumen U Pflanzen Fachdetailhandel in Verkaufsr\u00e4umen",
    "sg:phone":"+41 61 311 73 67",
    "sg:postcode":"4052",
    "sg:province":"Basel-Stadt",
    "wof:name":"Blumenhaus K\u00f6pfer",
    "wof:placetype":"venue"
},
  "geometry": {"coordinates":[7.613474,47.55545],"type":"Point"}
}