{
  "type": "Feature",
  "properties": {
    "iso:country":"CH",
    "sg:address":"Rue De La Justice 3",
    "sg:city":"Cully",
    "sg:orig_category":"Bauschreinerei Erbringung von Dienstleistungen f\u00fcr Unternehmen",
    "sg:phone":"+41 21 799 25 87",
    "sg:postcode":"1096",
    "sg:province":"Vaud",
    "wof:name":"Fondation Latreille",
    "wof:placetype":"venue"
},
  "geometry": {"coordinates":[6.730071,46.488983],"type":"Point"}
}