{
  "type": "Feature",
  "properties": {
    "addr:full":"Rue Du Mol\u00e9son 1 Bulle Fribourg 1630",
    "addr:housenumber":"1",
    "addr:postcode":"1630",
    "addr:street":"Rue Du Mole\u0301Son",
    "iso:country":"CH",
    "sg:address":"Rue Du Mol\u00e9son 1",
    "sg:city":"Bulle",
    "sg:classifiers":[
        {
            "category":"Social Services",
            "subcategory":"Retirement Home",
            "type":"Services"
        }
    ],
    "sg:phone":"+41 26 912 55 40",
    "sg:postcode":"1630",
    "sg:province":"Fribourg",
    "sg:tags":[
        "pflegeheime",
        "u",
        "alters"
    ],
    "wof:name":"Fondation Du Foyer Gruy\u00e9rien Pour Personnes \u00e2g\u00e9es",
    "wof:placetype":"venue"
},
  "geometry": {"coordinates":[7.056648,46.61507],"type":"Point"}
}