{
  "type": "Feature",
  "properties": {
    "iso:country":"CH",
    "sg:address":"Praz-recoulaz",
    "sg:city":"Crans-sur-sierre",
    "sg:orig_category":"Malerei",
    "sg:phone":"+41 91 864 24 93",
    "sg:postcode":"3963",
    "sg:province":"Valais",
    "wof:name":"Narciso Lanza Impresa Di Pittura",
    "wof:placetype":"venue"
},
  "geometry": {"coordinates":[8.9068098068,46.3802680969],"type":"Point"}
}