{
  "type": "Feature",
  "properties": {
    "iso:country":"CH",
    "sg:address":"Ottikerstr. 24",
    "sg:city":"Z\u00fcrich",
    "sg:classifiers":[
        {
            "category":"Professional",
            "subcategory":"Advertising",
            "type":"Services"
        }
    ],
    "sg:phone":"+41 22 343 52 00",
    "sg:postcode":"8006",
    "sg:province":"Z\u00fcrich",
    "sg:tags":[
        "communication",
        "medium"
    ],
    "wof:name":"Trimedia Communication Et Relations Publiques Sa",
    "wof:placetype":"venue"
},
  "geometry": {"coordinates":[6.142332,46.191296],"type":"Point"}
}