{
  "type": "Feature",
  "properties": {
    "iso:country":"CH",
    "sg:address":"Flurhofstrasse 30 8572 Andhausen. Postfach",
    "sg:city":"Andhausen",
    "sg:orig_category":"Interessenvertretungen",
    "sg:postcode":"8572",
    "sg:province":"Thurgau",
    "wof:name":"Winterhilfe Thurgau",
    "wof:placetype":"venue"
},
  "geometry": {"coordinates":[9.1784420013,47.5786514282],"type":"Point"}
}