{
  "type": "Feature",
  "properties": {
    "iso:country":"CH",
    "sg:address":"Shopping Center",
    "sg:city":"Spreitenbach",
    "sg:orig_category":"Fachdetailhandel in Verkaufsr\u00e4umen",
    "sg:postcode":"8957",
    "sg:province":"Aargau",
    "wof:name":"Albrecht & Co, Flair Blumen",
    "wof:placetype":"venue"
},
  "geometry": {"coordinates":[8.3702945709,47.4206886292],"type":"Point"}
}