{
  "type": "Feature",
  "properties": {
    "iso:country":"CH",
    "sg:address":"Industriestrasse 16",
    "sg:city":"Kestenholz",
    "sg:orig_category":"Bauingenieurb\u00fcros Heizung L\u00fcftung Klima",
    "sg:phone":"+41 71 223 89 49",
    "sg:postcode":"4703",
    "sg:province":"Solothurn",
    "wof:name":"Waldhauser Haustechnik Ingenieurb\u00fcro Ag",
    "wof:placetype":"venue"
},
  "geometry": {"coordinates":[9.369556,47.420574],"type":"Point"}
}