{
  "type": "Feature",
  "properties": {
    "iso:country":"CH",
    "sg:address":"Terreaux Rue Des 1",
    "sg:city":"Neuch\u00e2tel",
    "sg:orig_category":"Interessenvertretungen",
    "sg:phone":"+41 32 718 39 20",
    "sg:postcode":"2000",
    "sg:province":"Neuch\u00e2tel",
    "wof:name":"Fondation Forum Suisse Pour L'etude Des Migrations",
    "wof:placetype":"venue"
},
  "geometry": {"coordinates":[6.9306302071,46.9920692444],"type":"Point"}
}