{
  "type": "Feature",
  "properties": {
    "iso:country":"CH",
    "sg:address":"Grand-rue 19",
    "sg:city":"Morges",
    "sg:orig_category":"Detailhandel mit Geschenkartikeln U Souvenirs",
    "sg:phone":"+41 17619310",
    "sg:postcode":"1110",
    "sg:province":"Vaud",
    "wof:name":"Pia Stehrenberger Boutique Calimba",
    "wof:placetype":"venue"
},
  "geometry": {"coordinates":[8.45399189,47.2778968811],"type":"Point"}
}