{
  "type": "Feature",
  "properties": {
    "iso:country":"CH",
    "sg:address":"Reusseggstrasse 17",
    "sg:city":"Emmenbr\u00fccke",
    "sg:orig_category":"Elektrizit\u00e4tsversorgung R\u00fcckgewinnung U Vorbereitung f\u00fcr die Wiederverwertung Recycling",
    "sg:phone":"+41 41 420 77 33",
    "sg:postcode":"6020",
    "sg:province":"Luzern",
    "wof:name":"Sibag Entsorgung Und Recycling Ag",
    "wof:placetype":"venue"
},
  "geometry": {"coordinates":[8.2827596664,47.0684165955],"type":"Point"}
}