{
  "type": "Feature",
  "properties": {
    "iso:country":"CH",
    "sg:address":"Rue Des Tilleuls 3",
    "sg:city":"Grandson",
    "sg:orig_category":"Arztpraxen",
    "sg:phone":"+41 24 445 14 13",
    "sg:postcode":"1422",
    "sg:province":"Vaud",
    "wof:name":"Dr M\u00e9d. Jean-blaise Jaccard M\u00e9decin G\u00e9n\u00e9raliste Fmh",
    "wof:placetype":"venue"
},
  "geometry": {"coordinates":[6.62738,46.798817],"type":"Point"}
}