{
  "type": "Feature",
  "properties": {
    "iso:country":"CH",
    "sg:address":"L\u00f6wenmattweg 39",
    "sg:city":"M\u00fcnsingen",
    "sg:orig_category":"Herstellung von Konstruktionsteilen, Fertigbauteilen U Ausbauelementen aus Holz",
    "sg:postcode":"3110",
    "sg:province":"Bern",
    "wof:name":"Gautschi Hans, Schreinerei Und Montage",
    "wof:placetype":"venue"
},
  "geometry": {"coordinates":[7.559363842,46.881111145],"type":"Point"}
}