{
  "type": "Feature",
  "properties": {
    "iso:country":"CH",
    "sg:address":"Bahnhofstrasse 28",
    "sg:city":"Laufen",
    "sg:orig_category":"Detailhandel mit Waren verschiedener Art, Hauptrichtung Nahrungsmittel",
    "sg:phone":"+41 61 761 29 26",
    "sg:postcode":"4242",
    "sg:province":"Basel-Landschaft",
    "wof:name":"Coop Super Center",
    "wof:placetype":"venue"
},
  "geometry": {"coordinates":[7.5019512177,47.418800354],"type":"Point"}
}