{
  "type": "Feature",
  "properties": {
    "iso:country":"CH",
    "sg:address":"Route De Meinier 145",
    "sg:city":"Meinier",
    "sg:orig_category":"G\u00fcterbef\u00f6rderung im Strassenverkehr Lagerung",
    "sg:phone":"+41 22 750 11 55",
    "sg:postcode":"1252",
    "sg:province":"Gen\u00e8ve",
    "wof:name":"Daniel Baer Transports-garde-meubles",
    "wof:placetype":"venue"
},
  "geometry": {"coordinates":[6.2165617943,46.2358627319],"type":"Point"}
}