{
  "type": "Feature",
  "properties": {
    "iso:country":"CH",
    "sg:address":"Uettlingenstr. 5 3038 Kirchlindach. Postfach",
    "sg:city":"Herrenschwanden",
    "sg:orig_category":"Instandhaltung U Reparatur von Automobilen",
    "sg:postcode":"3037",
    "sg:province":"Bern",
    "wof:name":"Garage Leibundgut",
    "wof:placetype":"venue"
},
  "geometry": {"coordinates":[7.4158201218,47.0001220703],"type":"Point"}
}