{
  "type": "Feature",
  "properties": {
    "iso:country":"CH",
    "sg:address":"Weierwis 2",
    "sg:city":"Hauptwil",
    "sg:orig_category":"Kosmetikinstitute",
    "sg:phone":"+41 79 336 27 69",
    "sg:postcode":"9213",
    "sg:province":"Thurgau",
    "wof:name":"Elsbeth Stucki Kosmetik-praxis",
    "wof:placetype":"venue"
},
  "geometry": {"coordinates":[9.2573871613,47.4843406677],"type":"Point"}
}