{
  "type": "Feature",
  "properties": {
    "iso:country":"CH",
    "sg:address":"Romanshornerstrasse 4",
    "sg:city":"Arbon",
    "sg:orig_category":"Herstellung von Papier, Karton U Pappe",
    "sg:postcode":"9320",
    "sg:province":"Thurgau",
    "wof:name":"Arnold, Raschle, Partner Ag",
    "wof:placetype":"venue"
},
  "geometry": {"coordinates":[9.0437936783,47.4658126831],"type":"Point"}
}