{
  "type": "Feature",
  "properties": {
    "iso:country":"CH",
    "sg:address":"Hammerstrasse 14",
    "sg:city":"Basel",
    "sg:orig_category":"Detailhandel mit Schuhen Detailhandel mit medizinischen U orthop\u00e4dischen Artikeln",
    "sg:phone":"+41 61 691 00 66",
    "sg:postcode":"4058",
    "sg:province":"Basel-Stadt",
    "wof:name":"Winkler P., Eidg. Dipl. Orthop\u00e4die-schuhmacher",
    "wof:placetype":"venue"
},
  "geometry": {"coordinates":[7.5982818604,47.560005188],"type":"Point"}
}