{
  "type": "Feature",
  "properties": {
    "iso:country":"CH",
    "sg:address":"Dorfstrasse 23",
    "sg:city":"Seftigen",
    "sg:orig_category":"Selbst\u00e4ndige bildende K\u00fcnstler",
    "sg:phone":"+41 33 345 43 14",
    "sg:postcode":"3662",
    "sg:province":"Bern",
    "wof:name":"Kislig + Wenger Grabmalatelier Gmbh",
    "wof:placetype":"venue"
},
  "geometry": {"coordinates":[7.538875103,46.7870254517],"type":"Point"}
}