{
  "type": "Feature",
  "properties": {
    "iso:country":"CH",
    "sg:address":"Binningerstrasse 110",
    "sg:city":"Allschwil",
    "sg:orig_category":"Detailhandel mit Waren verschiedener Art in Verkaufsr\u00e4umen Fachdetailhandel mit Nahrungsmitteln, Get",
    "sg:phone":"+41 61 482 12 52",
    "sg:postcode":"4123",
    "sg:province":"Basel-Landschaft",
    "wof:name":"Otto's Warenposten Ag",
    "wof:placetype":"venue"
},
  "geometry": {"coordinates":[7.5505027771,47.5470237732],"type":"Point"}
}