{
  "type": "Feature",
  "properties": {
    "iso:country":"CH",
    "sg:address":"Fr\u00f6schweid 11",
    "sg:city":"Rheinfelden",
    "sg:orig_category":"Maler U Glasergewerbe",
    "sg:phone":"+41 71 222 26 65",
    "sg:postcode":"4310",
    "sg:province":"Aargau",
    "wof:name":"Malerbetrieb Brot Gmbh",
    "wof:placetype":"venue"
},
  "geometry": {"coordinates":[9.3842105865,47.4230232239],"type":"Point"}
}