{
  "type": "Feature",
  "properties": {
    "iso:country":"CH",
    "sg:address":"Fronwagplatz 1",
    "sg:city":"Schaffhausen",
    "sg:orig_category":"Detailhandel mit Waren verschiedener Art, Hauptrichtung Nahrungsmittel",
    "sg:phone":"+41 52 630 09 30",
    "sg:postcode":"8200",
    "sg:province":"Schaffhausen",
    "wof:name":"Coop Super Center Fronwagplatz",
    "wof:placetype":"venue"
},
  "geometry": {"coordinates":[8.6334571838,47.696472168],"type":"Point"}
}