{
  "type": "Feature",
  "properties": {
    "iso:country":"CH",
    "sg:address":"Gewerbestrasse 2",
    "sg:city":"Egolzwil",
    "sg:orig_category":"Sanit\u00e4r, Heizungs U L\u00fcftungsinstallation Sanit\u00e4rinstallation",
    "sg:phone":"+41 41 980 30 20",
    "sg:postcode":"6243",
    "sg:province":"Luzern",
    "wof:name":"Alt Ag Sanit\u00e4re Anlagen & Heizungen",
    "wof:placetype":"venue"
},
  "geometry": {"coordinates":[8.0059766769,47.1831626892],"type":"Point"}
}