{
  "type": "Feature",
  "properties": {
    "iso:country":"CH",
    "sg:address":"Hauptstrasse",
    "sg:city":"Kleindietwil",
    "sg:orig_category":"Grosshandel mit Nahrungsmitteln, Getr\u00e4nken U Tabakwaren ohne ausgepr\u00e4gten Schwerpunkt",
    "sg:phone":"+41 62 965 34 44",
    "sg:postcode":"4936",
    "sg:province":"Bern",
    "wof:name":"Lebensmittel Derendinger Niko",
    "wof:placetype":"venue"
},
  "geometry": {"coordinates":[7.7899851799,47.1464042664],"type":"Point"}
}