{
  "type": "Feature",
  "properties": {
    "iso:country":"CH",
    "sg:address":"Dorfstrasse 9 8805 Richterswil. Postfach",
    "sg:city":"Richterswil",
    "sg:classifiers":[
        {
            "category":"Education",
            "subcategory":"Library",
            "type":"Public Place"
        }
    ],
    "sg:postcode":"8805",
    "sg:province":"Z\u00fcrich",
    "sg:tags":[
        "u",
        "bibliotheken",
        "archive"
    ],
    "wof:name":"Farbdia-archiv E. Van Hoorick.",
    "wof:placetype":"venue"
},
  "geometry": {"coordinates":[8.706383,47.206318],"type":"Point"}
}