{
  "type": "Feature",
  "properties": {
    "iso:country":"CH",
    "sg:address":"Rue De La Gare 64",
    "sg:city":"Sonceboz-sombeval",
    "sg:classifiers":[
        {
            "category":"Restaurant",
            "type":"Food & Drink"
        }
    ],
    "sg:phone":"+41 32 489 29 71",
    "sg:postcode":"2605",
    "sg:province":"Bern",
    "wof:name":"Restaurant De La Clef",
    "wof:placetype":"venue"
},
  "geometry": {"coordinates":[7.162375927,47.197971344],"type":"Point"}
}