{
  "type": "Feature",
  "properties": {
    "addr:full":"W\u00fcrzenbachstrasse 56 Luzern Luzern 6006",
    "addr:housenumber":"56",
    "addr:postcode":"6006",
    "addr:street":"Wuerzenbachstrasse",
    "iso:country":"CH",
    "sg:address":"W\u00fcrzenbachstrasse 56",
    "sg:city":"Luzern",
    "sg:orig_category":"Architektur U Ingenieurb\u00fcros",
    "sg:phone":"+41 41 375 00 75",
    "sg:postcode":"6006",
    "sg:province":"Luzern",
    "wof:name":"Aicher, De Martin, Zweng Ag Ingenieurb\u00fcro F. Heizungs, L\u00fcftungs, Klimaanlagen Usw; Beteiligungen",
    "wof:placetype":"venue"
},
  "geometry": {"coordinates":[8.351119,47.057121],"type":"Point"}
}