{
  "type": "Feature",
  "properties": {
    "iso:country":"CH",
    "sg:address":"Kupferschmiedeweg 45 7000 Chur. Postfach",
    "sg:city":"Chur",
    "sg:orig_category":"Dienstleistungen im Gartenbau Gartenbau",
    "sg:phone":"+41 81 353 28 41",
    "sg:postcode":"7000",
    "sg:province":"Graubunden",
    "wof:name":"Gartenblitz Chur Gmbh Gartenbau- U. Tiefbauarbeiten Usw",
    "wof:placetype":"venue"
},
  "geometry": {"coordinates":[9.5423307419,46.84167099],"type":"Point"}
}