{
  "type": "Feature",
  "properties": {
    "iso:country":"CH",
    "sg:address":"Grugnay",
    "sg:city":"Chamoson",
    "sg:orig_category":"Interessenvertretungen",
    "sg:postcode":"1955",
    "sg:province":"Valais",
    "wof:name":"La Gaillarde Scoop",
    "wof:placetype":"venue"
},
  "geometry": {"coordinates":[7.2198901176,46.2065582275],"type":"Point"}
}