{
  "type": "Feature",
  "properties": {
    "iso:country":"CH",
    "sg:address":"Route De Geneve 26",
    "sg:city":"Commugny",
    "sg:orig_category":"Softwareentwicklung U beratung",
    "sg:phone":"+41 22 776 43 82",
    "sg:postcode":"1291",
    "sg:province":"Vaud",
    "wof:name":"Mas Services, Zysset Roland",
    "wof:placetype":"venue"
},
  "geometry": {"coordinates":[6.1734871864,46.314414978],"type":"Point"}
}