{
  "type": "Feature",
  "properties": {
    "iso:country":"CH",
    "sg:address":"Avenue Haldimand 39",
    "sg:city":"Yverdon-les-bains",
    "sg:orig_category":"Wirtschaftspr\u00fcfung, Steuerberatung U Treuhand",
    "sg:phone":"+41 22 732 88 03",
    "sg:postcode":"1400",
    "sg:province":"Vaud",
    "wof:name":"Allied Services Compagnie Fiduciaire Sa",
    "wof:placetype":"venue"
},
  "geometry": {"coordinates":[6.147772789,46.2083892822],"type":"Point"}
}