{
  "type": "Feature",
  "properties": {
    "iso:country":"CH",
    "sg:address":"Bahnhofstrasse 3",
    "sg:city":"Fl\u00fcelen",
    "sg:orig_category":"Detailhandel mit Getr\u00e4nken Grosshandel mit Getr\u00e4nken",
    "sg:phone":"+41 41 871 10 91",
    "sg:postcode":"6454",
    "sg:province":"Uri",
    "wof:name":"Filoni Weinhandlung",
    "wof:placetype":"venue"
},
  "geometry": {"coordinates":[8.6241121292,46.9006843567],"type":"Point"}
}