{
  "type": "Feature",
  "properties": {
    "iso:country":"CH",
    "sg:address":"H\u00f6lli 21",
    "sg:city":"Othmarsingen",
    "sg:orig_category":"Verarbeitung von Milch Verwertung von Milch",
    "sg:postcode":"5504",
    "sg:province":"Aargau",
    "wof:name":"K\u00e4serei-genossenschaft Riken",
    "wof:placetype":"venue"
},
  "geometry": {"coordinates":[7.8371567726,47.2683372498],"type":"Point"}
}