{
  "type": "Feature",
  "properties": {
    "iso:country":"CH",
    "sg:address":"Glarnerstrasse 80",
    "sg:city":"Siebnen",
    "sg:orig_category":"Maler U Glasergewerbe Malerei",
    "sg:phone":"+41 55 440 14 77",
    "sg:postcode":"8854",
    "sg:province":"Schwyz",
    "wof:name":"Mayer Manfred",
    "wof:placetype":"venue"
},
  "geometry": {"coordinates":[8.909658432,47.1758613586],"type":"Point"}
}