{
  "type": "Feature",
  "properties": {
    "iso:country":"CH",
    "sg:address":"Affolternstrasse 100",
    "sg:city":"Z\u00fcrich",
    "sg:orig_category":"Maler U Glasergewerbe Malerei",
    "sg:phone":"+41 79 611 03 04",
    "sg:postcode":"8050",
    "sg:province":"Z\u00fcrich",
    "wof:name":"Vogel Otto-leo",
    "wof:placetype":"venue"
},
  "geometry": {"coordinates":[9.8188638687,46.7890396118],"type":"Point"}
}