{
  "type": "Feature",
  "properties": {
    "iso:country":"CH",
    "sg:address":"Edlibachstr. 40 6345 Neuheim. Postfach",
    "sg:city":"Neuheim",
    "sg:orig_category":"Sanit\u00e4r, Heizungs U L\u00fcftungsinstallation",
    "sg:phone":"+41 41 755 28 48",
    "sg:postcode":"6345",
    "sg:province":"Zug",
    "wof:name":"Obrist Karl Ag",
    "wof:placetype":"venue"
},
  "geometry": {"coordinates":[8.5685415268,47.1895332336],"type":"Point"}
}