{
  "type": "Feature",
  "properties": {
    "iso:country":"CH",
    "sg:address":"Via Bartolomeo Varenna 2",
    "sg:city":"Locarno",
    "sg:orig_category":"Non-Classified Establishments",
    "sg:phone":"+41 91 751 43 36",
    "sg:postcode":"6600",
    "sg:province":"Ticino",
    "wof:name":"Corona Holding S.a.",
    "wof:placetype":"venue"
},
  "geometry": {"coordinates":[8.7898111343,46.1679916382],"type":"Point"}
}