{
  "type": "Feature",
  "properties": {
    "iso:country":"CH",
    "sg:address":"Austrasse 10",
    "sg:city":"Wagen",
    "sg:orig_category":"Detailhandel an Verkaufsst\u00e4nden U auf M\u00e4rkten Sonstiger Grosshandel",
    "sg:phone":"+41 55 212 29 69",
    "sg:postcode":"8646",
    "sg:province":"St. Gallen",
    "wof:name":"Helbling Robert, Marktfahrer",
    "wof:placetype":"venue"
},
  "geometry": {"coordinates":[8.882972,47.23085],"type":"Point"}
}