{
  "type": "Feature",
  "properties": {
    "addr:full":"St\u00f6ckackerstrasse 89 Bern Bern 3018",
    "addr:housenumber":"89",
    "addr:postcode":"3018",
    "addr:street":"Stoeckackerstrasse",
    "iso:country":"CH",
    "sg:address":"St\u00f6ckackerstrasse 89",
    "sg:city":"Bern",
    "sg:orig_category":"Betrieb von Taxis",
    "sg:phone":"+41 31 994 26 66",
    "sg:postcode":"3018",
    "sg:province":"Bern",
    "wof:name":"Alao Enterprises",
    "wof:placetype":"venue"
},
  "geometry": {"coordinates":[7.400319,46.944221],"type":"Point"}
}