{
  "type": "Feature",
  "properties": {
    "iso:country":"CH",
    "sg:address":"Eichenstrasse 23",
    "sg:city":"Arbon",
    "sg:orig_category":"Herstellung von Metallkonstruktionen",
    "sg:postcode":"9320",
    "sg:province":"Thurgau",
    "wof:name":"Stahl Tech Arbon Gmbh",
    "wof:placetype":"venue"
},
  "geometry": {"coordinates":[9.4280195236,47.5128860474],"type":"Point"}
}