{
  "type": "Feature",
  "properties": {
    "iso:country":"CH",
    "sg:address":"Baarerstrasse 27 6300 Zug. Postfach 4447",
    "sg:city":"Zug",
    "sg:orig_category":"Detailhandel mit elektrischen Haushalts-,Radio U Fernsehger\u00e4ten sowie Musikinstrumenten Grosshandel ",
    "sg:phone":"+41 22 343 66 38",
    "sg:postcode":"6304",
    "sg:province":"Zug",
    "wof:name":"Peyer Sa",
    "wof:placetype":"venue"
},
  "geometry": {"coordinates":[6.1443538666,46.1844673157],"type":"Point"}
}