{
  "type": "Feature",
  "properties": {
    "iso:country":"CH",
    "sg:address":"Via Fola 13",
    "sg:city":"Pregassona",
    "sg:orig_category":"Instandhaltung U Reparatur von Automobilen",
    "sg:phone":"+41 91 972 58 63",
    "sg:postcode":"6963",
    "sg:province":"Ticino",
    "wof:name":"Franco Foti Garage Stazio",
    "wof:placetype":"venue"
},
  "geometry": {"coordinates":[8.9628305435,46.0170097351],"type":"Point"}
}