{
  "type": "Feature",
  "properties": {
    "iso:country":"CH",
    "sg:address":"Alpenstrasse 1 6300 Zug. Postfach",
    "sg:city":"Zug",
    "sg:orig_category":"Sonstige pers\u00f6nliche Dienstleistungen",
    "sg:phone":"+41 32 968 67 92",
    "sg:postcode":"6300",
    "sg:province":"Zug",
    "wof:name":"Xydec, Rouiller Atelier De D\u00e9colletage",
    "wof:placetype":"venue"
},
  "geometry": {"coordinates":[6.8299050331,47.102809906],"type":"Point"}
}