{
  "type": "Feature",
  "properties": {
    "iso:country":"CH",
    "sg:address":"1304",
    "sg:city":"Cossonay-ville",
    "sg:orig_category":"Maler U Glasergewerbe Stukkateurgewerbe, Gipserei U Verputzerei",
    "sg:phone":"+41 21 861 01 73",
    "sg:postcode":"1304",
    "sg:province":"Vaud",
    "wof:name":"Pommaz Pierre",
    "wof:placetype":"venue"
},
  "geometry": {"coordinates":[6.50770998,46.6138191223],"type":"Point"}
}