{
  "type": "Feature",
  "properties": {
    "iso:country":"CH",
    "sg:address":"Schnetzletb\u00fchlstrasse 14",
    "sg:city":"Hinwil",
    "sg:orig_category":"Sportvereine Minigolf",
    "sg:phone":"+41 56 622 46 71",
    "sg:postcode":"8340",
    "sg:province":"Z\u00fcrich",
    "wof:name":"Mc Wohlen",
    "wof:placetype":"venue"
},
  "geometry": {"coordinates":[8.2809085846,47.3434104919],"type":"Point"}
}