{
  "type": "Feature",
  "properties": {
    "iso:country":"CH",
    "sg:address":"Via Buonamano 7",
    "sg:city":"Ascona",
    "sg:classifiers":[
        {
            "category":"Travel",
            "subcategory":"Hotels & Motels",
            "type":"Entertainment"
        }
    ],
    "sg:phone":"+41 91 791 44 21",
    "sg:postcode":"6612",
    "sg:province":"Ticino",
    "sg:tags":[
        "hotels",
        "mit",
        "restaurant"
    ],
    "wof:name":"Albergo Polo",
    "wof:placetype":"venue"
},
  "geometry": {"coordinates":[8.7724275589,46.1563224792],"type":"Point"}
}