{
  "type": "Feature",
  "properties": {
    "iso:country":"CH",
    "sg:address":"M\u00fchlethalstrasse 26",
    "sg:city":"Zofingen",
    "sg:orig_category":"Vermietung U Verpachtung von eigenen Immobilien Vermittlung von Immobilien",
    "sg:phone":"+41 79 332 98 41",
    "sg:postcode":"4800",
    "sg:province":"Aargau",
    "wof:name":"Kneub\u00fchler Ag Immobilien",
    "wof:placetype":"venue"
},
  "geometry": {"coordinates":[7.9470911026,47.2945709229],"type":"Point"}
}