{
  "type": "Feature",
  "properties": {
    "addr:full":"Via Chiasso 7 Biasca Ticino 6710",
    "addr:housenumber":"7",
    "addr:postcode":"6710",
    "addr:street":"Via Chiasso",
    "iso:country":"CH",
    "sg:address":"Via Chiasso 7",
    "sg:city":"Biasca",
    "sg:orig_category":"Bauspenglerei Mechanische Werkst\u00e4tten",
    "sg:phone":"+41 91 862 18 22",
    "sg:postcode":"6710",
    "sg:province":"Ticino",
    "wof:name":"Thermonord Biasca Sa",
    "wof:placetype":"venue"
},
  "geometry": {"coordinates":[8.975598,46.346485],"type":"Point"}
}