{
  "type": "Feature",
  "properties": {
    "iso:country":"CH",
    "sg:address":"S\u00fcdstrasse 29",
    "sg:city":"Z\u00fcrich",
    "sg:orig_category":"Herstellung von medizinischen U chirurgischen Ger\u00e4ten sowie orthop\u00e4dischen Vorrichtungen Zahntechnis",
    "sg:phone":"+41 13832041",
    "sg:postcode":"8008",
    "sg:province":"Z\u00fcrich",
    "wof:name":"Camin & Hari Zahntechnik",
    "wof:placetype":"venue"
},
  "geometry": {"coordinates":[8.5637731552,47.3540878296],"type":"Point"}
}