{
  "type": "Feature",
  "properties": {
    "iso:country":"CH",
    "sg:address":"Ettingerstrasse 12",
    "sg:city":"Witterswil",
    "sg:orig_category":"Chemin\u00e9e- and Ofenbau Hafner",
    "sg:phone":"+41 61 721 67 37",
    "sg:postcode":"4108",
    "sg:province":"Solothurn",
    "wof:name":"Hanspeter H\u00fcgin Hafnerei",
    "wof:placetype":"venue"
},
  "geometry": {"coordinates":[7.523797,47.484715],"type":"Point"}
}