{
  "type": "Feature",
  "properties": {
    "iso:country":"CH",
    "sg:address":"Rte Des Acacias 47",
    "sg:city":"Gen\u00e8ve",
    "sg:orig_category":"Erbringung von sonstigen Dienstleistungen f\u00fcr Unterhaltung, Erholung U Freizeit",
    "sg:postcode":"1200",
    "sg:province":"Gen\u00e8ve",
    "wof:name":"Beverley Sa",
    "wof:placetype":"venue"
},
  "geometry": {"coordinates":[6.1294522285,46.1883735657],"type":"Point"}
}