{
  "type": "Feature",
  "properties": {
    "addr:full":"Gerechtigkeitsgasse 49 Bern Bern 3011",
    "addr:housenumber":"49",
    "addr:postcode":"3011",
    "addr:street":"Gerechtigkeitsgasse",
    "iso:country":"CH",
    "sg:address":"Gerechtigkeitsgasse 49",
    "sg:city":"Bern",
    "sg:orig_category":"Detailhandel mit Damenbekleidung",
    "sg:phone":"+41 31 311 01 06",
    "sg:postcode":"3011",
    "sg:province":"Bern",
    "wof:name":"Couture & Styling Marianne Milani",
    "wof:placetype":"venue"
},
  "geometry": {"coordinates":[7.453563,46.948029],"type":"Point"}
}