{
  "type": "Feature",
  "properties": {
    "iso:country":"CH",
    "sg:address":"Waldheimstrasse 6 3072 Ostermundigen. Postfach 305",
    "sg:city":"Ostermundigen",
    "sg:orig_category":"Sportvereine Turnen",
    "sg:phone":"+41 31 932 06 28",
    "sg:postcode":"3072",
    "sg:province":"Bern",
    "wof:name":"Turnverein Stv Ostermundigen",
    "wof:placetype":"venue"
},
  "geometry": {"coordinates":[7.4861049652,46.9508018494],"type":"Point"}
}