{
  "type": "Feature",
  "properties": {
    "iso:country":"CH",
    "sg:address":"Bissau 1173",
    "sg:city":"Heiden",
    "sg:orig_category":"Elektroinstallation",
    "sg:phone":"+41 71 891 21 90",
    "sg:postcode":"9410",
    "sg:province":"Appenzell Ausserrhoden",
    "wof:name":"Elektro-z\u00fcst & Co",
    "wof:placetype":"venue"
},
  "geometry": {"coordinates":[9.5373487473,47.4326782227],"type":"Point"}
}