{
  "type": "Feature",
  "properties": {
    "iso:country":"CH",
    "sg:address":"Postfach 88",
    "sg:city":"Plaffeien",
    "sg:classifiers":[
        {
            "category":"Home & Garden",
            "subcategory":"Furniture",
            "type":"Retail Goods"
        }
    ],
    "sg:phone":"+41 71 388 58 00",
    "sg:postcode":"1716",
    "sg:province":"Fribourg",
    "sg:tags":[
        "wood"
    ],
    "wof:name":"Holzwerk Lehmann Ag",
    "wof:placetype":"venue"
},
  "geometry": {"coordinates":[9.2549495697,47.4144134521],"type":"Point"}
}