{
  "type": "Feature",
  "properties": {
    "iso:country":"CH",
    "sg:address":"Sumpfstrasse 32",
    "sg:city":"Zug",
    "sg:orig_category":"Sonstige mit der Informatik verbundene T\u00e4tigkeiten",
    "sg:phone":"+41 41 748 22 88",
    "sg:postcode":"6300",
    "sg:province":"Zug",
    "wof:name":"Itarco Ag",
    "wof:placetype":"venue"
},
  "geometry": {"coordinates":[8.4851512909,47.1778526306],"type":"Point"}
}