{
  "type": "Feature",
  "properties": {
    "iso:country":"CH",
    "sg:address":"Forchstrasse 1001",
    "sg:city":"Hinteregg",
    "sg:orig_category":"Instandhaltung U Reparatur von Automobilen",
    "sg:phone":"+41 19841432",
    "sg:postcode":"8132",
    "sg:province":"Z\u00fcrich",
    "wof:name":"Garage Und Carosserie Schweizer & Co",
    "wof:placetype":"venue"
},
  "geometry": {"coordinates":[8.6781253815,47.3105239868],"type":"Point"}
}