{
  "type": "Feature",
  "properties": {
    "iso:country":"CH",
    "sg:address":"Seetalstrasse 31",
    "sg:city":"Schafisheim",
    "sg:orig_category":"Detailhandel mit Beleuchtungs U Haushaltsgegenst\u00e4nden Detailhandel mit Spielwaren",
    "sg:phone":"+41 62 891 34 27",
    "sg:postcode":"5503",
    "sg:province":"Aargau",
    "wof:name":"Lotti Wildi Haushaltboutique Spielwaren",
    "wof:placetype":"venue"
},
  "geometry": {"coordinates":[8.141935,47.379524],"type":"Point"}
}