{
  "type": "Feature",
  "properties": {
    "iso:country":"CH",
    "sg:address":"Baarerstr. 47 6300 Zug. Postfach",
    "sg:city":"Zug",
    "sg:orig_category":"Elektroinstallation",
    "sg:postcode":"6301",
    "sg:province":"Zug",
    "wof:name":"Buob & Co., Leo",
    "wof:placetype":"venue"
},
  "geometry": {"coordinates":[8.5168762207,47.1742706299],"type":"Point"}
}