{
  "type": "Feature",
  "properties": {
    "addr:full":"Petite Corniche Route De 1 1091 Grandvaux. Postfach Grandvaux Vaud 1091",
    "addr:housenumber":"1",
    "addr:postcode":"1091 grandvaux. postfach grandvaux;1091",
    "addr:street":"Petite Corniche Route De",
    "iso:country":"CH",
    "sg:address":"Petite Corniche Route De 1 1091 Grandvaux. Postfach",
    "sg:city":"Grandvaux",
    "sg:orig_category":"Architektur U Ingenieurb\u00fcros",
    "sg:phone":"+41 21 799 31 80",
    "sg:postcode":"1091",
    "sg:province":"Vaud",
    "wof:name":"Megawat Sa",
    "wof:placetype":"venue"
},
  "geometry": {"coordinates":[6.71613,46.49358],"type":"Point"}
}