{
  "type": "Feature",
  "properties": {
    "iso:country":"CH",
    "sg:address":"Mettstrasse 98",
    "sg:city":"Biel/bienne",
    "sg:orig_category":"Maler U Glasergewerbe Malerei",
    "sg:phone":"+41 32 365 01 62",
    "sg:postcode":"2504",
    "sg:province":"Bern",
    "wof:name":"Schwertfeger Markus",
    "wof:placetype":"venue"
},
  "geometry": {"coordinates":[7.2673540115,47.1411361694],"type":"Point"}
}