{
  "type": "Feature",
  "properties": {
    "iso:country":"CH",
    "sg:address":"Dorfstrasse 2",
    "sg:city":"Oberkulm",
    "sg:classifiers":[
        {
            "category":"Restaurant",
            "type":"Food & Drink"
        }
    ],
    "sg:phone":"+41 62 776 12 14",
    "sg:postcode":"5727",
    "sg:province":"Aargau",
    "wof:name":"Restaurant Huberst\u00fcbli",
    "wof:placetype":"venue"
},
  "geometry": {"coordinates":[8.1193914413,47.2990837097],"type":"Point"}
}