{
  "type": "Feature",
  "properties": {
    "iso:country":"CH",
    "sg:address":"Dorfstrasse 45",
    "sg:city":"Richterswil",
    "sg:classifiers":[
        {
            "category":"Bars & Pubs",
            "type":"Food & Drink"
        }
    ],
    "sg:phone":"+41 17848186",
    "sg:postcode":"8805",
    "sg:province":"Z\u00fcrich",
    "wof:name":"Green Cat Bar",
    "wof:placetype":"venue"
},
  "geometry": {"coordinates":[8.704865,47.207829],"type":"Point"}
}