{
  "type": "Feature",
  "properties": {
    "iso:country":"CH",
    "sg:address":"Baltzerstrasse 1",
    "sg:city":"Bern",
    "sg:orig_category":"Universit\u00e4ten, Hochschulen",
    "sg:phone":"+41 71 224 25 60",
    "sg:postcode":"3012",
    "sg:province":"Bern",
    "wof:name":"Hochschule St.gallen Kulturwissenschaftl.abteilung",
    "wof:placetype":"venue"
},
  "geometry": {"coordinates":[9.3731222153,47.4318122864],"type":"Point"}
}