{
  "type": "Feature",
  "properties": {
    "iso:country":"CH",
    "sg:address":"Dorf",
    "sg:city":"Blumenstein",
    "sg:orig_category":"Detailhandel mit elektrischen Haushalts-,Radio U Fernsehger\u00e4ten sowie Musikinstrumenten",
    "sg:phone":"+41 33 356 20 55",
    "sg:postcode":"3638",
    "sg:province":"Bern",
    "wof:name":"Haus + Agro, Stauffer R.",
    "wof:placetype":"venue"
},
  "geometry": {"coordinates":[7.5206098557,46.7410163879],"type":"Point"}
}