{
  "type": "Feature",
  "properties": {
    "iso:country":"CH",
    "sg:address":"Via Rinaldo Simen 1",
    "sg:city":"Locarno",
    "sg:orig_category":"Stukkateurgewerbe, Gipserei U Verputzerei",
    "sg:postcode":"6600",
    "sg:province":"Ticino",
    "wof:name":"Gimag - Mordasini Gian-luigi",
    "wof:placetype":"venue"
},
  "geometry": {"coordinates":[8.7917766571,46.1667938232],"type":"Point"}
}