{
  "type": "Feature",
  "properties": {
    "iso:country":"CH",
    "sg:address":"N\u00f6llenstrasse 13",
    "sg:city":"Widnau",
    "sg:orig_category":"Datenverarbeitungsdienste Herstellung von pharmazeutischen Grundstoffen",
    "sg:phone":"+41 71 727 25 25",
    "sg:postcode":"9443",
    "sg:province":"St. Gallen",
    "wof:name":"Pharmapool-logistic Ag",
    "wof:placetype":"venue"
},
  "geometry": {"coordinates":[9.637908,47.414562],"type":"Point"}
}