{
  "type": "Feature",
  "properties": {
    "iso:country":"CH",
    "sg:address":"Aarburgerstrasse 29",
    "sg:city":"Zofingen",
    "sg:orig_category":"G\u00fcterbef\u00f6rderung im Strassenverkehr",
    "sg:phone":"+41 62 752 11 66",
    "sg:postcode":"4800",
    "sg:province":"Aargau",
    "wof:name":"Gloor Transport Ag",
    "wof:placetype":"venue"
},
  "geometry": {"coordinates":[7.9375491142,47.2949371338],"type":"Point"}
}