{
  "type": "Feature",
  "properties": {
    "iso:country":"CH",
    "sg:address":"P\u00fcntstrasse 12",
    "sg:city":"Wila",
    "sg:orig_category":"Ger\u00fcstbau Malerei",
    "sg:phone":"+41 52 385 28 30",
    "sg:postcode":"8492",
    "sg:province":"Z\u00fcrich",
    "wof:name":"Graf Heinz Malergesch\u00e4ft/ger\u00fcstbau Malergesch\u00e4ft. Ger\u00fcste; Vermietung, Aufbau, Abbruch",
    "wof:placetype":"venue"
},
  "geometry": {"coordinates":[8.8442277908,47.4235992432],"type":"Point"}
}