{
  "type": "Feature",
  "properties": {
    "iso:country":"CH",
    "sg:address":"Hagenbachstrasse 7",
    "sg:city":"Basel",
    "sg:orig_category":"Sonstige pers\u00f6nliche Dienstleistungen",
    "sg:phone":"+41 61 313 77 74",
    "sg:postcode":"4052",
    "sg:province":"Basel-Stadt",
    "wof:name":"Unterwegs Zum Du Partnervermittlung",
    "wof:placetype":"venue"
},
  "geometry": {"coordinates":[7.6001467705,47.547958374],"type":"Point"}
}