{
  "type": "Feature",
  "properties": {
    "iso:country":"CH",
    "sg:address":"Via San Carlo 34",
    "sg:city":"Barbengo",
    "sg:classifiers":[
        {
            "category":"Manufacturing",
            "subcategory":"Motor Vehicles & Parts",
            "type":"Manufacturing & Wholesale Goods"
        }
    ],
    "sg:phone":"+41 91 995 14 12",
    "sg:postcode":"6917",
    "sg:province":"Ticino",
    "sg:tags":[
        "bolts",
        "shaped",
        "component",
        "nuts",
        "dy",
        "carbide",
        "rivets"
    ],
    "wof:name":"Bitiess Microtecnica Sa",
    "wof:placetype":"venue"
},
  "geometry": {"coordinates":[8.925066,45.966976],"type":"Point"}
}