{
  "type": "Feature",
  "properties": {
    "iso:country":"CH",
    "sg:address":"Z\u00fcrcherstrasse 107a",
    "sg:city":"Oberengstringen",
    "sg:orig_category":"Detektivb\u00fcros U \u00dcberwachung",
    "sg:postcode":"8102",
    "sg:province":"Z\u00fcrich",
    "wof:name":"Sia, Schwendimann Jean-pierre",
    "wof:placetype":"venue"
},
  "geometry": {"coordinates":[6.8579797745,46.9656105042],"type":"Point"}
}