{
  "type": "Feature",
  "properties": {
    "iso:country":"CH",
    "sg:address":"Kirchbergstrasse 35",
    "sg:city":"Burgdorf",
    "sg:orig_category":"Detailhandel mit Zeitungen U Zeitschriften Kioske",
    "sg:phone":"+41 71 966 28 92",
    "sg:postcode":"3400",
    "sg:province":"Bern",
    "wof:name":"Kiosk Am Bahnhof Hans-rudolf M\u00fcller",
    "wof:placetype":"venue"
},
  "geometry": {"coordinates":[8.9989452362,47.4769439697],"type":"Point"}
}