{
  "type": "Feature",
  "properties": {
    "iso:country":"CH",
    "sg:address":"Sternenbachmatte 5",
    "sg:city":"Wahlendorf",
    "sg:orig_category":"Elektroinstallation",
    "sg:phone":"+41 31 931 12 22",
    "sg:postcode":"3046",
    "sg:province":"Bern",
    "wof:name":"Beat Jordi Ag, Elektro Und Telefonunternehmen",
    "wof:placetype":"venue"
},
  "geometry": {"coordinates":[7.4792408943,46.9572601318],"type":"Point"}
}