{
  "type": "Feature",
  "properties": {
    "iso:country":"CH",
    "sg:address":"Avenue De Cour 80",
    "sg:city":"Lausanne",
    "sg:orig_category":"Detailhandel mit Fleisch U Fleischwaren",
    "sg:phone":"+41 21 616 58 40",
    "sg:postcode":"1007",
    "sg:province":"Vaud",
    "wof:name":"Antonio Carboni Boucherie Chevaline",
    "wof:placetype":"venue"
},
  "geometry": {"coordinates":[6.6136741638,46.5162315369],"type":"Point"}
}