{
  "type": "Feature",
  "properties": {
    "iso:country":"CH",
    "sg:address":"La Petite-camargue 80 1897 Bouveret. Postfach",
    "sg:city":"Bouveret",
    "sg:orig_category":"Herstellung von Teppichen",
    "sg:phone":"+41 24 481 29 39",
    "sg:postcode":"1897",
    "sg:province":"Valais",
    "wof:name":"Visinand Ren\u00e9",
    "wof:placetype":"venue"
},
  "geometry": {"coordinates":[6.866590023,46.3802833557],"type":"Point"}
}