{
  "type": "Feature",
  "properties": {
    "iso:country":"CH",
    "sg:address":"Barf\u00fcssergasse 2",
    "sg:city":"Solothurn",
    "sg:orig_category":"Herstellung von Oberbekleidung",
    "sg:postcode":"4500",
    "sg:province":"Solothurn",
    "wof:name":"Framode Sa",
    "wof:placetype":"venue"
},
  "geometry": {"coordinates":[7.5373430252,47.2080841064],"type":"Point"}
}