{
  "type": "Feature",
  "properties": {
    "iso:country":"CH",
    "sg:address":"Badenerstrasse 9-11",
    "sg:city":"Fislisbach",
    "sg:orig_category":"Handelsvermittlung U Grosshandel mit Automobilteilen U Zubeh\u00f6r Herstellung von Bereifungen",
    "sg:phone":"+41 56 493 25 25",
    "sg:postcode":"5442",
    "sg:province":"Aargau",
    "wof:name":"Pneu Treier",
    "wof:placetype":"venue"
},
  "geometry": {"coordinates":[8.2900400162,47.4362030029],"type":"Point"}
}