{
  "type": "Feature",
  "properties": {
    "iso:country":"CH",
    "sg:address":"Finkenweg 5",
    "sg:city":"M\u00fcnsingen",
    "sg:orig_category":"Grosshandel mit Baumaterialien Herstellung von Bergwerks U Baumaschinen",
    "sg:phone":"+41 79 671 96 61",
    "sg:postcode":"3110",
    "sg:province":"Bern",
    "wof:name":"Wenker Bau Und Schalungsbedarf",
    "wof:placetype":"venue"
},
  "geometry": {"coordinates":[7.5724029541,46.8733291626],"type":"Point"}
}