{
  "type": "Feature",
  "properties": {
    "iso:country":"CH",
    "sg:address":"Zielstrasse 38",
    "sg:city":"Appenzell",
    "sg:orig_category":"Pensionskassen",
    "sg:phone":"+41 33 222 61 73",
    "sg:postcode":"9050",
    "sg:province":"Appenzell Innerhoden",
    "wof:name":"Pensionskasse Der Alba-gruppe",
    "wof:placetype":"venue"
},
  "geometry": {"coordinates":[9.4077110291,47.3339538574],"type":"Point"}
}