{
  "type": "Feature",
  "properties": {
    "iso:country":"CH",
    "sg:address":"Avenue De La Concorde 16",
    "sg:city":"Chavannes-renens",
    "sg:orig_category":"Gewinnung von Natursteinen f\u00fcr den Bau Sonstiger Grosshandel",
    "sg:phone":"+41 21 671 15 70",
    "sg:postcode":"1022",
    "sg:province":"Vaud",
    "wof:name":"Gemmes-tech Sa",
    "wof:placetype":"venue"
},
  "geometry": {"coordinates":[6.5739898682,46.5328102112],"type":"Point"}
}