{
  "type": "Feature",
  "properties": {
    "iso:country":"CH",
    "sg:address":"8632",
    "sg:city":"Tann",
    "sg:orig_category":"Primarschulen",
    "sg:postcode":"8632",
    "sg:province":"Z\u00fcrich",
    "wof:name":"Primarschule Tannenb\u00fchl",
    "wof:placetype":"venue"
},
  "geometry": {"coordinates":[8.8530702591,47.2672195435],"type":"Point"}
}