{
  "type": "Feature",
  "properties": {
    "iso:country":"CH",
    "sg:address":"Grand-place Ouest Crans",
    "sg:city":"Lens",
    "sg:orig_category":"Verarbeitung von Tee U Kaffee",
    "sg:phone":"+41 32 926 44 88",
    "sg:postcode":"1978",
    "sg:province":"Valais",
    "wof:name":"La Semeuse Torr\u00e9faction De Caf\u00e9",
    "wof:placetype":"venue"
},
  "geometry": {"coordinates":[6.813123,47.087154],"type":"Point"}
}