{
  "type": "Feature",
  "properties": {
    "iso:country":"CH",
    "sg:address":"Gr\u00e4tzlistrasse 51",
    "sg:city":"Opfikon",
    "sg:orig_category":"Maler U Glasergewerbe Tapeziererei",
    "sg:phone":"+41 18105023",
    "sg:postcode":"8152",
    "sg:province":"Z\u00fcrich",
    "wof:name":"Sch\u00e4r + Friedrich Ag",
    "wof:placetype":"venue"
},
  "geometry": {"coordinates":[8.5825366974,47.4242630005],"type":"Point"}
}