{
  "type": "Feature",
  "properties": {
    "iso:country":"CH",
    "sg:address":"Hauptstrasse 16",
    "sg:city":"Villnachern",
    "sg:orig_category":"Nationale Postdienste",
    "sg:phone":"+41 56 441 14 53",
    "sg:postcode":"5213",
    "sg:province":"Aargau",
    "wof:name":"Die Schweizerische Post",
    "wof:placetype":"venue"
},
  "geometry": {"coordinates":[8.1635560989,47.4699783325],"type":"Point"}
}