{
  "type": "Feature",
  "properties": {
    "addr:full":"Loostrasse 11 Oerlingen Z\u00fcrich 8461",
    "addr:housenumber":"11",
    "addr:postcode":"8461",
    "addr:street":"Loostrasse;Zuerich",
    "iso:country":"CH",
    "sg:address":"Loostrasse 11",
    "sg:city":"Oerlingen",
    "sg:orig_category":"Herstellung von Werkzeugen",
    "sg:phone":"+41 32 913 48 38",
    "sg:postcode":"8461",
    "sg:province":"Z\u00fcrich",
    "wof:name":"Sparconic Sa",
    "wof:placetype":"venue"
},
  "geometry": {"coordinates":[6.817694,47.101341],"type":"Point"}
}