{
  "type": "Feature",
  "properties": {
    "iso:country":"CH",
    "sg:address":"Glattalstrasse 516",
    "sg:city":"R\u00fcmlang",
    "sg:classifiers":[
        {
            "category":"Mining & Drilling",
            "type":"Manufacturing & Wholesale Goods"
        }
    ],
    "sg:phone":"+41 18179200",
    "sg:postcode":"8153",
    "sg:province":"Z\u00fcrich",
    "sg:tags":[
        "facing",
        "boring",
        "tool"
    ],
    "wof:name":"Heinz Kaiser Ag",
    "wof:placetype":"venue"
},
  "geometry": {"coordinates":[8.5414361954,47.4344749451],"type":"Point"}
}