{
  "type": "Feature",
  "properties": {
    "iso:country":"CH",
    "sg:address":"Schiltstrasse 29",
    "sg:city":"Glarus",
    "sg:orig_category":"Herstellung von Papier, Karton U Pappe",
    "sg:postcode":"8750",
    "sg:province":"Glarus",
    "wof:name":"Inledag",
    "wof:placetype":"venue"
},
  "geometry": {"coordinates":[9.0615243912,47.0380172729],"type":"Point"}
}