{
  "type": "Feature",
  "properties": {
    "iso:country":"CH",
    "sg:address":"Platanen 12",
    "sg:city":"Olten",
    "sg:orig_category":"Non-Classified Establishments",
    "sg:postcode":"4600",
    "sg:province":"Solothurn",
    "wof:name":"Trisolver Ag",
    "wof:placetype":"venue"
},
  "geometry": {"coordinates":[7.9029669762,47.3444786072],"type":"Point"}
}