{
  "type": "Feature",
  "properties": {
    "iso:country":"CH",
    "sg:address":"Breitistrasse",
    "sg:city":"M\u00f6hlin",
    "sg:orig_category":"Vorschulen, Kinderg\u00e4rten",
    "sg:phone":"+41 61 851 34 44",
    "sg:postcode":"4313",
    "sg:province":"Aargau",
    "wof:name":"Kindergarten Breiti",
    "wof:placetype":"venue"
},
  "geometry": {"coordinates":[7.8375558853,47.5620613098],"type":"Point"}
}