{
  "type": "Feature",
  "properties": {
    "iso:country":"CH",
    "sg:address":"Mezikonerstrasse 9",
    "sg:city":"M\u00fcnchwilen",
    "sg:classifiers":[
        {
            "category":"Real Estate",
            "subcategory":"Architect",
            "type":"Services"
        }
    ],
    "sg:phone":"+41 71 969 35 90",
    "sg:postcode":"9542",
    "sg:province":"Thurgau",
    "sg:tags":[
        "work",
        "developing"
    ],
    "wof:name":"Schmid Engineering Ag",
    "wof:placetype":"venue"
},
  "geometry": {"coordinates":[8.9937772751,47.4868659973],"type":"Point"}
}