{
  "type": "Feature",
  "properties": {
    "iso:country":"CH",
    "sg:address":"Schulhausstrasse",
    "sg:city":"Gampel",
    "sg:orig_category":"Fussboden, Fliesen U Plattenlegerei, Tapeziererei",
    "sg:postcode":"3945",
    "sg:province":"Valais",
    "wof:name":"Eidt Urs, Plattenlegergesch\u00e4ft",
    "wof:placetype":"venue"
},
  "geometry": {"coordinates":[7.742205143,46.3146820068],"type":"Point"}
}