{
  "type": "Feature",
  "properties": {
    "iso:country":"CH",
    "sg:address":"F\u00f6hneneichstrasse 56",
    "sg:city":"Brunnen",
    "sg:orig_category":"Chemische Reinigung W\u00e4schereien",
    "sg:postcode":"6440",
    "sg:province":"Schwyz",
    "wof:name":"Kley Textilreinigung & W\u00e4scherei",
    "wof:placetype":"venue"
},
  "geometry": {"coordinates":[8.644156,46.882042],"type":"Point"}
}