{
  "type": "Feature",
  "properties": {
    "iso:country":"CH",
    "sg:address":"Riedgutschstrasse 9",
    "sg:city":"Wollerau",
    "sg:orig_category":"Datenverarbeitungsdienste",
    "sg:phone":"+41 81 416 59 58",
    "sg:postcode":"8832",
    "sg:province":"Schwyz",
    "wof:name":"J\u00f6rg Pajarola Edv-dienstleistungsb\u00fcro",
    "wof:placetype":"venue"
},
  "geometry": {"coordinates":[9.842875,46.802467],"type":"Point"}
}