{
  "type": "Feature",
  "properties": {
    "iso:country":"CH",
    "sg:address":"Quellenstrasse 2a",
    "sg:city":"M\u00f6rschwil",
    "sg:orig_category":"Maler U Glasergewerbe Malerei",
    "sg:phone":"+41 71 866 15 94",
    "sg:postcode":"9402",
    "sg:province":"St. Gallen",
    "wof:name":"Lanzmaier Walter, Malergesch\u00e4ft.",
    "wof:placetype":"venue"
},
  "geometry": {"coordinates":[9.4208526611,47.4635658264],"type":"Point"}
}