{
  "type": "Feature",
  "properties": {
    "iso:country":"CH",
    "sg:address":"R\u00fctligasse 2 6003 Luzern. Postfach",
    "sg:city":"Luzern",
    "sg:orig_category":"RESTAURANTS: TEA-ROOMS",
    "sg:postcode":"6003",
    "sg:province":"Luzern",
    "wof:name":"Sebastian's Gmbh Restaurants",
    "wof:placetype":"venue"
},
  "geometry": {"coordinates":[8.3023786545,47.0503807068],"type":"Point"}
}