{
  "type": "Feature",
  "properties": {
    "iso:country":"CH",
    "sg:address":"Uitikonerstrasse 23",
    "sg:city":"Schlieren",
    "sg:orig_category":"Sportvereine Flug Aero-Club",
    "sg:phone":"+41 17301228",
    "sg:postcode":"8952",
    "sg:province":"Z\u00fcrich",
    "wof:name":"Ae.c.s.segelfluggruppe Z\u00fcrich",
    "wof:placetype":"venue"
},
  "geometry": {"coordinates":[8.4483880997,47.3956031799],"type":"Point"}
}