{
  "type": "Feature",
  "properties": {
    "iso:country":"CH",
    "sg:address":"Neuhauserstrasse 4",
    "sg:city":"Flurlingen",
    "sg:orig_category":"Institutionen des Sozialwesens ohne Beherbergung",
    "sg:postcode":"8247",
    "sg:province":"Z\u00fcrich",
    "wof:name":"Sigg-ergo-stiftung Willy Und Marguerite",
    "wof:placetype":"venue"
},
  "geometry": {"coordinates":[8.6286849976,47.6827163696],"type":"Point"}
}