{
  "type": "Feature",
  "properties": {
    "iso:country":"CH",
    "sg:address":"Alpenstrasse 15 6300 Zug. Postfach",
    "sg:city":"Zug",
    "sg:orig_category":"Dienstleistungen von Beteiligungsgesellschaften",
    "sg:postcode":"6300",
    "sg:province":"Zug",
    "wof:name":"Trivox S.\u00e0.r.l., Luxemburg, Zweigniederlassung Zug Gr\u00fcndung, Verwaltung, Finanzierung Von Unternehmen Und Gesellschaften",
    "wof:placetype":"venue"
},
  "geometry": {"coordinates":[8.5148057938,47.172958374],"type":"Point"}
}