{
  "type": "Feature",
  "properties": {
    "iso:country":"CH",
    "sg:address":"Dufourstrasse 56 8008 Z\u00fcrich. Postfach",
    "sg:city":"Z\u00fcrich",
    "sg:orig_category":"Fernmeldedienste",
    "sg:phone":"+41 56 618 44 44",
    "sg:postcode":"8001",
    "sg:province":"Z\u00fcrich",
    "wof:name":"Telcomtech Gmbh",
    "wof:placetype":"venue"
},
  "geometry": {"coordinates":[8.276684761,47.3516616821],"type":"Point"}
}