{
  "type": "Feature",
  "properties": {
    "iso:country":"CH",
    "sg:address":"2108",
    "sg:city":"Couvet",
    "sg:orig_category":"Vereine Gesang",
    "sg:postcode":"2108",
    "sg:province":"Neuch\u00e2tel",
    "wof:name":"Choeur Mixte De L'\u00e9glise Nationale De Couvet",
    "wof:placetype":"venue"
},
  "geometry": {"coordinates":[6.6301870346,46.9247665405],"type":"Point"}
}