{
  "type": "Feature",
  "properties": {
    "iso:country":"CH",
    "sg:address":"Kleinm\u00e4ttji 3923 T\u00f6rbel. Postfach",
    "sg:city":"T\u00f6rbel",
    "sg:orig_category":"Betrieb U technische Hilfsdienste des Kultur U Unterhaltungswesens",
    "sg:postcode":"3923",
    "sg:province":"Valais",
    "wof:name":"Verein Sonne F\u00fcr Behinderte Kinder Entlastungsm\u00f6glichkeiten, Ferien, Freizeitgestaltung F\u00fcr Behinderte Kinder Usw.; Unterst\u00fctzung, F\u00f6rderung",
    "wof:placetype":"venue"
},
  "geometry": {"coordinates":[7.846852,46.237865],"type":"Point"}
}