{
  "type": "Feature",
  "properties": {
    "iso:country":"CH",
    "sg:address":"Kestenholzstrasse 16 4702 Oensingen. Postfach",
    "sg:city":"Oensingen",
    "sg:orig_category":"Handel mit Automobilen",
    "sg:phone":"+41 79 432 62 70",
    "sg:postcode":"4702",
    "sg:province":"Solothurn",
    "wof:name":"Bohnenblust Martin, Autohandel",
    "wof:placetype":"venue"
},
  "geometry": {"coordinates":[7.724946022,47.2895545959],"type":"Point"}
}