{
  "type": "Feature",
  "properties": {
    "iso:country":"CH",
    "sg:address":"St. Gallerstrasse 10",
    "sg:city":"Kronb\u00fchl",
    "sg:orig_category":"Bau U Wohngenossenschaften Erschliessung von Grundst\u00fccken",
    "sg:phone":"+41 71 292 20 50",
    "sg:postcode":"9302",
    "wof:name":"Gsw Gen.f.seniorenwohnungen C/o Raiffeisenbank",
    "wof:placetype":"venue"
},
  "geometry": {"coordinates":[9.396523,47.457474],"type":"Point"}
}