{
  "type": "Feature",
  "properties": {
    "iso:country":"CH",
    "sg:address":"Feldstrasse 1",
    "sg:city":"Grasswil",
    "sg:classifiers":[
        {
            "category":"Restaurant",
            "type":"Food & Drink"
        }
    ],
    "sg:phone":"+41 55 240 12 22",
    "sg:postcode":"3365",
    "sg:province":"Bern",
    "wof:name":"Restaurant B\u00e4ren",
    "wof:placetype":"venue"
},
  "geometry": {"coordinates":[8.8527879715,47.2580986023],"type":"Point"}
}