{
  "type": "Feature",
  "properties": {
    "iso:country":"CH",
    "sg:address":"Pulverm\u00fchleweg 12",
    "sg:city":"Kriens",
    "sg:orig_category":"Architektur U Ingenieurb\u00fcros Innenarchitekturb\u00fcros",
    "sg:phone":"+41 41 320 19 10",
    "sg:postcode":"6010",
    "sg:province":"Luzern",
    "wof:name":"M\u00fcller Beat Und Patrick, Architekturb\u00fcro",
    "wof:placetype":"venue"
},
  "geometry": {"coordinates":[8.269846,47.034821],"type":"Point"}
}