{
  "type": "Feature",
  "properties": {
    "addr:full":"Oberstufenzentrum Flums St. Gallen 8890",
    "addr:postcode":"8890",
    "iso:country":"CH",
    "sg:address":"Oberstufenzentrum",
    "sg:city":"Flums",
    "sg:orig_category":"Bezirks, Sekundar, Realschulen, Oberstufe der Primarschulen",
    "sg:postcode":"8890",
    "sg:province":"St. Gallen",
    "wof:name":"Sekundarschule Fl\u00fchli",
    "wof:placetype":"venue"
},
  "geometry": {"coordinates":[8.016077,46.883495],"type":"Point"}
}