{
  "type": "Feature",
  "properties": {
    "iso:country":"CH",
    "sg:address":"Rauracherweg 3",
    "sg:city":"Muttenz",
    "sg:classifiers":[
        {
            "category":"Banks & Credit Unions",
            "subcategory":"Bureau De Change",
            "type":"Services"
        }
    ],
    "sg:phone":"+41 61 313 60 27",
    "sg:postcode":"4132",
    "sg:province":"Basel-Landschaft",
    "sg:tags":[
        "leak",
        "detector"
    ],
    "wof:name":"Marag Flow & Gastech Ag",
    "wof:placetype":"venue"
},
  "geometry": {"coordinates":[7.630698204,47.5359992981],"type":"Point"}
}