{
  "type": "Feature",
  "properties": {
    "iso:country":"CH",
    "sg:address":"1063",
    "sg:city":"Chapelle-s-moudon",
    "sg:orig_category":"Verwertung von Milch",
    "sg:postcode":"1063",
    "sg:province":"Vaud",
    "wof:name":"Soci\u00e9t\u00e9 De Laiterie De Chapelle-martherenges",
    "wof:placetype":"venue"
},
  "geometry": {"coordinates":[6.737195015,46.6686592102],"type":"Point"}
}