{
  "type": "Feature",
  "properties": {
    "iso:country":"CH",
    "sg:address":"Riedpark",
    "sg:city":"Landquart",
    "sg:orig_category":"Detailhandel mit Fleisch U Fleischwaren",
    "sg:phone":"+41 81 300 60 88",
    "sg:postcode":"7302",
    "sg:province":"Graubunden",
    "wof:name":"Carna Grischa Ag",
    "wof:placetype":"venue"
},
  "geometry": {"coordinates":[9.5598402023,46.9604034424],"type":"Point"}
}