{
  "type": "Feature",
  "properties": {
    "iso:country":"CH",
    "sg:address":"Im Zogg 9",
    "sg:city":"Maienfeld",
    "sg:orig_category":"Herstellung von Elektromotoren, Generatoren U Transformatoren Ingenieurb\u00fcros Maschinenbau",
    "sg:phone":"+41 81 330 17 85",
    "sg:postcode":"7304",
    "sg:province":"Graubunden",
    "wof:name":"Powercondens Ag",
    "wof:placetype":"venue"
},
  "geometry": {"coordinates":[9.5382986069,47.0046386719],"type":"Point"}
}