{
  "type": "Feature",
  "properties": {
    "iso:country":"CH",
    "sg:address":"Sch\u00fcrbergstrasse 16",
    "sg:city":"Gr\u00e4nichen",
    "sg:orig_category":"Herstellung von Futtermitteln f\u00fcr Nutztiere",
    "sg:postcode":"5722",
    "sg:province":"Aargau",
    "wof:name":"Grastrocknungsgenossenschaft Amt Entlebuch",
    "wof:placetype":"venue"
},
  "geometry": {"coordinates":[8.0420398712,46.9739456177],"type":"Point"}
}