{
  "type": "Feature",
  "properties": {
    "iso:country":"CH",
    "sg:address":"S\u00e4ntisstr. 25 8132 Egg B. Z\u00fcrich. Postfach",
    "sg:city":"Esslingen",
    "sg:orig_category":"Reiseb\u00fcros U Reiseveranstalter",
    "sg:postcode":"8133",
    "sg:province":"Z\u00fcrich",
    "wof:name":"Farrag Kameltours",
    "wof:placetype":"venue"
},
  "geometry": {"coordinates":[8.6900548935,47.3005561829],"type":"Point"}
}