{
  "type": "Feature",
  "properties": {
    "iso:country":"CH",
    "sg:address":"Rue De L'ancien-stand 19 1820 Montreux. Postfach",
    "sg:city":"Brent",
    "sg:orig_category":"Reiseb\u00fcros U Reiseveranstalter",
    "sg:phone":"+41 21 961 15 05",
    "sg:postcode":"1817",
    "sg:province":"Vaud",
    "wof:name":"Lithos \u00ac Talon Ch.",
    "wof:placetype":"venue"
},
  "geometry": {"coordinates":[6.9114770889,46.4391555786],"type":"Point"}
}