{
  "type": "Feature",
  "properties": {
    "iso:country":"CH",
    "sg:address":"Malixerstrasse 71",
    "sg:city":"Chur",
    "sg:classifiers":[
        {
            "category":"Manufacturing",
            "subcategory":"Metals",
            "type":"Manufacturing & Wholesale Goods"
        }
    ],
    "sg:phone":"+41 81 253 58 57",
    "sg:postcode":"7000",
    "sg:province":"Graubunden",
    "sg:tags":[
        "u",
        "leichtmetallbau",
        "stahl"
    ],
    "wof:name":"Soder Metallbautechnik Ag",
    "wof:placetype":"venue"
},
  "geometry": {"coordinates":[9.530872345,46.8447647095],"type":"Point"}
}