{
  "type": "Feature",
  "properties": {
    "iso:country":"CH",
    "sg:address":"Bahnhofstrasse 9",
    "sg:city":"Baar",
    "sg:orig_category":"Public-Relations-Agenturen Unternehmensberatung",
    "sg:phone":"+41 41 760 77 19",
    "sg:postcode":"6340",
    "sg:province":"Zug",
    "wof:name":"Its Trade Service Ag",
    "wof:placetype":"venue"
},
  "geometry": {"coordinates":[8.5244979858,47.1954307556],"type":"Point"}
}