{
  "type": "Feature",
  "properties": {
    "iso:country":"CH",
    "sg:address":"Rue De L'eglise 1926 Fully Case Postale 62",
    "sg:city":"Fully",
    "sg:orig_category":"Non-Classified Establishments",
    "sg:phone":"+41 27 746 33 47",
    "sg:postcode":"1926",
    "sg:province":"Valais",
    "wof:name":"Agribort Sa",
    "wof:placetype":"venue"
},
  "geometry": {"coordinates":[7.1151638031,46.1387557983],"type":"Point"}
}