{
  "type": "Feature",
  "properties": {
    "iso:country":"CH",
    "sg:address":"1408",
    "sg:city":"Prahins",
    "sg:orig_category":"Detailhandel mit Waren verschiedener Art, Hauptrichtung Nahrungsmittel",
    "sg:postcode":"1408",
    "sg:province":"Vaud",
    "wof:name":"Coop\u00e9rative Agricole D'utilisation De Machines De Prahins",
    "wof:placetype":"venue"
},
  "geometry": {"coordinates":[6.7345299721,46.7364807129],"type":"Point"}
}