{
  "type": "Feature",
  "properties": {
    "iso:country":"CH",
    "sg:address":"Zentrumsplatz 10",
    "sg:city":"Sch\u00f6nb\u00fchl-urtenen",
    "sg:orig_category":"Detailhandel mit B\u00fcchern, Zeitungen, Schreib U Papeteriewaren Detailhandel mit Zeitungen U Zeitschri",
    "sg:phone":"+41 31 859 36 86",
    "sg:postcode":"3322",
    "sg:province":"Bern",
    "wof:name":"Kiosk Im Dorfzentrum, Waser Katharina",
    "wof:placetype":"venue"
},
  "geometry": {"coordinates":[7.498298,47.020767],"type":"Point"}
}