{
  "type": "Feature",
  "properties": {
    "iso:country":"CH",
    "sg:address":"6929",
    "sg:city":"Gravesano",
    "sg:orig_category":"Politische Parteien Gr\u00fcne Partei",
    "sg:phone":"+41 91 605 33 44",
    "sg:postcode":"6929",
    "sg:province":"Ticino",
    "wof:name":"I Verdi Ticino",
    "wof:placetype":"venue"
},
  "geometry": {"coordinates":[8.9184398651,46.0415916443],"type":"Point"}
}