{
  "type": "Feature",
  "properties": {
    "iso:country":"CH",
    "sg:address":"Haltingerstrasse 97",
    "sg:city":"Basel",
    "sg:orig_category":"Kinderkrippen U horte",
    "sg:phone":"+41 61 693 38 38",
    "sg:postcode":"4057",
    "sg:province":"Basel-Stadt",
    "wof:name":"Spielgruppe Yseb\u00e4hnli",
    "wof:placetype":"venue"
},
  "geometry": {"coordinates":[7.5973381996,47.5666809082],"type":"Point"}
}