{
  "type": "Feature",
  "properties": {
    "iso:country":"CH",
    "sg:address":"Constant Place Benjamin- 2",
    "sg:city":"Lausanne",
    "sg:orig_category":"Vermietung U Verpachtung von eigenen Immobilien",
    "sg:postcode":"1003",
    "sg:province":"Vaud",
    "wof:name":"Patrimoine Foncier Et Financier Pff Sa",
    "wof:placetype":"venue"
},
  "geometry": {"coordinates":[6.1399769783,46.185333252],"type":"Point"}
}