{
  "type": "Feature",
  "properties": {
    "iso:country":"CH",
    "sg:address":"Fronhofweg 51",
    "sg:city":"Hallau",
    "sg:orig_category":"Detailhandel mit M\u00f6beln Detailhandel mit M\u00f6beln U Haushaltsgegenst\u00e4nden",
    "sg:phone":"+41 79 629 12 35",
    "sg:postcode":"8215",
    "sg:province":"Schaffhausen",
    "wof:name":"Schnetzler Kurt",
    "wof:placetype":"venue"
},
  "geometry": {"coordinates":[8.4566698074,47.6958198547],"type":"Point"}
}