{
  "type": "Feature",
  "properties": {
    "iso:country":"CH",
    "sg:address":"Hauptstrasse 101",
    "sg:city":"Zetzwil",
    "sg:orig_category":"Detailhandel mit M\u00f6beln",
    "sg:phone":"+41 62 773 23 85",
    "sg:postcode":"5732",
    "sg:province":"Aargau",
    "wof:name":"M\u00f6bel Hunziker Ag",
    "wof:placetype":"venue"
},
  "geometry": {"coordinates":[8.1529092789,47.283744812],"type":"Point"}
}