{
  "type": "Feature",
  "properties": {
    "iso:country":"CH",
    "sg:address":"Haltengut 8753 Mollis. Postfach 131",
    "sg:city":"Mollis",
    "sg:orig_category":"Gesundheitswesen Luftfahrt",
    "sg:phone":"+41 55 612 33 33",
    "sg:postcode":"8753",
    "sg:province":"Glarus",
    "wof:name":"Heli-linth Ag",
    "wof:placetype":"venue"
},
  "geometry": {"coordinates":[9.0745248795,47.0914382935],"type":"Point"}
}