{
  "type": "Feature",
  "properties": {
    "iso:country":"CH",
    "sg:address":"Avenue De La Gare 30",
    "sg:city":"Sion",
    "sg:orig_category":"Fussreflexzonenmassage",
    "sg:phone":"+41 22 771 17 02",
    "sg:postcode":"1950",
    "sg:province":"Valais",
    "wof:name":"Marie-france Binggeli Massage & R\u00e9flexologie",
    "wof:placetype":"venue"
},
  "geometry": {"coordinates":[6.1364598274,46.145401001],"type":"Point"}
}