{
  "type": "Feature",
  "properties": {
    "iso:country":"CH",
    "sg:address":"Pedra Grossa 5",
    "sg:city":"Lenzerheide/lai",
    "sg:orig_category":"Sonstige mit Sport verbundene T\u00e4tigkeiten",
    "sg:postcode":"7078",
    "sg:province":"Graubunden",
    "wof:name":"Romo Egger Rolf Motorsportpromotion Sa",
    "wof:placetype":"venue"
},
  "geometry": {"coordinates":[7.0395359993,46.7534675598],"type":"Point"}
}