{
  "type": "Feature",
  "properties": {
    "iso:country":"CH",
    "sg:address":"Niesenstrasse 16",
    "sg:city":"Konolfingen",
    "sg:orig_category":"Werbung",
    "sg:phone":"+41 31 791 25 29",
    "sg:postcode":"3510",
    "sg:province":"Bern",
    "wof:name":"Wp Werbeplanung Ag",
    "wof:placetype":"venue"
},
  "geometry": {"coordinates":[7.6173219681,46.8779754639],"type":"Point"}
}