{
  "type": "Feature",
  "properties": {
    "addr:full":"Bl\u00e4siring 158 4000 Basel. Postfach Basel Basel-Stadt 4051",
    "addr:housenumber":"158",
    "addr:postcode":"4000;4051",
    "addr:street":"Postfach",
    "iso:country":"CH",
    "sg:address":"Bl\u00e4siring 158 4000 Basel. Postfach",
    "sg:city":"Basel",
    "sg:orig_category":"Allgemeiner Hoch U Tiefbau",
    "sg:postcode":"4051",
    "sg:province":"Basel-Stadt",
    "wof:name":"Wunderle Gmbh",
    "wof:placetype":"venue"
},
  "geometry": {"coordinates":[7.595883,47.568661],"type":"Point"}
}