{
  "type": "Feature",
  "properties": {
    "iso:country":"CH",
    "sg:address":"Dorfstr. 8",
    "sg:city":"Pfaffnau",
    "sg:classifiers":[
        {
            "category":"Shopping",
            "subcategory":"Clothing, Apparel, & Fashions",
            "type":"Retail Goods"
        }
    ],
    "sg:phone":"+41 62 754 12 64",
    "sg:postcode":"6264",
    "sg:province":"Luzern",
    "sg:tags":[
        "textile",
        "clothing",
        "clothes"
    ],
    "wof:name":"Atelier Buettiker",
    "wof:placetype":"venue"
},
  "geometry": {"coordinates":[7.90053,47.230217],"type":"Point"}
}