{
  "type": "Feature",
  "properties": {
    "iso:country":"CH",
    "sg:address":"Berghaus Gurli 1716 Plaffeien. Postfach",
    "sg:city":"Plaffeien",
    "sg:classifiers":[
        {
            "category":"Travel",
            "subcategory":"Hotels & Motels",
            "type":"Entertainment"
        }
    ],
    "sg:phone":"+41 37391913",
    "sg:postcode":"1716",
    "sg:province":"Fribourg",
    "sg:tags":[
        "hotels",
        "mit",
        "restaurant"
    ],
    "wof:name":"Maire Hanni Berghaus Gurli",
    "wof:placetype":"venue"
},
  "geometry": {"coordinates":[7.2868709564,46.7410163879],"type":"Point"}
}