{
  "type": "Feature",
  "properties": {
    "addr:full":"Vo\u00ebte Chemin De La 30 Vallorbe Vaud 1337",
    "addr:housenumber":"30",
    "addr:postcode":"1337",
    "addr:street":"Chemin De La",
    "iso:country":"CH",
    "sg:address":"Vo\u00ebte Chemin De La 30",
    "sg:city":"Vallorbe",
    "sg:orig_category":"Betrieb von Sportanlagen",
    "sg:phone":"+41 21 843 00 70",
    "sg:postcode":"1337",
    "sg:province":"Vaud",
    "wof:name":"Soci\u00e9t\u00e9 De La Patinoire Des 3 Vallons",
    "wof:placetype":"venue"
},
  "geometry": {"coordinates":[6.379095,46.71196],"type":"Point"}
}