{
  "type": "Feature",
  "properties": {
    "iso:country":"CH",
    "sg:address":"6855",
    "sg:city":"Stabio",
    "sg:orig_category":"Herstellung von Maschinen f\u00fcr die Textil, Bekleidungsherstellung U die Lederverarbeitung",
    "sg:postcode":"6855",
    "sg:province":"Ticino",
    "wof:name":"Itex Wil Ag",
    "wof:placetype":"venue"
},
  "geometry": {"coordinates":[9.0328617096,47.4650878906],"type":"Point"}
}