{
  "type": "Feature",
  "properties": {
    "iso:country":"CH",
    "sg:address":"B\u00fcmplizstrasse 153",
    "sg:city":"Bern",
    "sg:orig_category":"Elektroinstallation",
    "sg:phone":"+41 31 992 44 73",
    "sg:postcode":"3018",
    "sg:province":"Bern",
    "wof:name":"Peter W\u00e4lti Ag",
    "wof:placetype":"venue"
},
  "geometry": {"coordinates":[7.3920021057,46.9396934509],"type":"Point"}
}