{
  "type": "Feature",
  "properties": {
    "iso:country":"CH",
    "sg:address":"Pictet Avenue Ernest- 19",
    "sg:city":"Gen\u00e8ve",
    "sg:orig_category":"Handels-H\u00e4user U Gesellschaften",
    "sg:postcode":"1203",
    "sg:province":"Gen\u00e8ve",
    "wof:name":"Aeos Consulting Bonjour S\u00e9bastien",
    "wof:placetype":"venue"
},
  "geometry": {"coordinates":[6.1255288124,46.2120857239],"type":"Point"}
}