{
  "type": "Feature",
  "properties": {
    "iso:country":"CH",
    "sg:address":"Neuweilerstrasse 60",
    "sg:city":"Basel",
    "sg:orig_category":"Sonstige Aktivit\u00e4ten der nicht-\u00e4rztlichen Medizinalberufe",
    "sg:phone":"+41 61 261 38 03",
    "sg:postcode":"4054",
    "sg:province":"Basel-Stadt",
    "wof:name":"Esther Schwald M\u00e4der Atemtherapie & Massagen",
    "wof:placetype":"venue"
},
  "geometry": {"coordinates":[7.5610737801,47.546459198],"type":"Point"}
}