{
  "type": "Feature",
  "properties": {
    "iso:country":"CH",
    "sg:address":"Rue Du Vieux M\u00f4tier",
    "sg:city":"Courfaivre",
    "sg:orig_category":"Detailhandel mit elektrischen Haushaltsger\u00e4ten",
    "sg:phone":"+41 32 426 73 23",
    "sg:postcode":"2853",
    "sg:province":"Jura",
    "wof:name":"Marcel Berset Machines \u00e0 Coudre",
    "wof:placetype":"venue"
},
  "geometry": {"coordinates":[7.2911300659,47.3330802917],"type":"Point"}
}