{
  "type": "Feature",
  "properties": {
    "iso:country":"CH",
    "sg:address":"Neustadtstrasse 40",
    "sg:city":"Luzern",
    "sg:orig_category":"Non-Classified Establishments",
    "sg:postcode":"6003",
    "sg:province":"Luzern",
    "wof:name":"Netform Gmbh",
    "wof:placetype":"venue"
},
  "geometry": {"coordinates":[8.3078527451,47.0417098999],"type":"Point"}
}