{
  "type": "Feature",
  "properties": {
    "iso:country":"CH",
    "sg:address":"Monbijoustrasse 11 3007 Bern. Postfach",
    "sg:city":"Bern",
    "sg:orig_category":"Elektrizit\u00e4tsversorgung",
    "sg:phone":"+41 31 321 31 11",
    "sg:postcode":"3001",
    "sg:province":"Bern",
    "wof:name":"Elektrizit\u00e4tswerk Der Stadt Bern",
    "wof:placetype":"venue"
},
  "geometry": {"coordinates":[7.4359998703,46.9412727356],"type":"Point"}
}