{
  "type": "Feature",
  "properties": {
    "iso:country":"CH",
    "sg:address":"Lengnaustr. 6 Pf 436",
    "sg:city":"Lengnau",
    "sg:classifiers":[
        {
            "category":"Wholesale",
            "subcategory":"Machinery & Supplies",
            "type":"Manufacturing & Wholesale Goods"
        }
    ],
    "sg:phone":"+41 32 653 04 44",
    "sg:postcode":"2543",
    "sg:province":"Bern",
    "sg:tags":[
        "handling",
        "material",
        "-",
        "machine",
        "equipment",
        "engineering",
        "mechanical"
    ],
    "wof:name":"Polyservice Ag",
    "wof:placetype":"venue"
},
  "geometry": {"coordinates":[7.3662519455,47.1823883057],"type":"Point"}
}