{
  "type": "Feature",
  "properties": {
    "iso:country":"CH",
    "sg:address":"Waldweg 5 6018 Buttisholz. Postfach 160",
    "sg:city":"Buttisholz",
    "sg:orig_category":"Herstellung von k\u00e4lte U lufttechnischen Erzeugnissen f\u00fcr gewerbliche Zwecke Installation von Heizung",
    "sg:phone":"+41 41 928 07 08",
    "sg:postcode":"6018",
    "sg:province":"Luzern",
    "wof:name":"Liwing Ag",
    "wof:placetype":"venue"
},
  "geometry": {"coordinates":[8.1046943665,47.1168899536],"type":"Point"}
}