{
  "type": "Feature",
  "properties": {
    "iso:country":"CH",
    "sg:address":"Avenue De Frontenex 16 -",
    "sg:city":"Geneva",
    "sg:classifiers":[
        {
            "category":"Professional",
            "subcategory":"Art Services",
            "type":"Services"
        }
    ],
    "sg:phone":"+41 22 735 04 05",
    "sg:postcode":"1207",
    "sg:province":"Gen\u00e8ve",
    "sg:tags":[
        "export-import"
    ],
    "wof:name":"Hungary Consulate",
    "wof:placetype":"venue"
},
  "geometry": {"coordinates":[6.157654,46.201641],"type":"Point"}
}