{
  "type": "Feature",
  "properties": {
    "iso:country":"CH",
    "sg:address":"Hauptstrasse 56",
    "sg:city":"Muttenz",
    "sg:orig_category":"Verm\u00f6gensverwaltung Versicherungen Generalagenturen",
    "sg:postcode":"4132",
    "sg:province":"Basel-Landschaft",
    "wof:name":"Jean-pierre Ceccon Finanzberatung Rentenanstalt/ Swiss Life",
    "wof:placetype":"venue"
},
  "geometry": {"coordinates":[7.6470937729,47.5256462097],"type":"Point"}
}