{
  "type": "Feature",
  "properties": {
    "iso:country":"CH",
    "sg:address":"Via Gian Battista Mal\u00e8 5 6600 Solduno. Postfach",
    "sg:city":"Locarno",
    "sg:orig_category":"Grafikateliers, Design",
    "sg:phone":"+41 91 751 69 71",
    "sg:postcode":"6604",
    "sg:province":"Ticino",
    "wof:name":"Flaviano Piffero Insegne",
    "wof:placetype":"venue"
},
  "geometry": {"coordinates":[8.779337883,46.1705093384],"type":"Point"}
}