{
  "type": "Feature",
  "properties": {
    "iso:country":"CH",
    "sg:address":"Thaler Strasse 62",
    "sg:city":"Rheineck",
    "sg:orig_category":"Stukkateurgewerbe, Gipserei U Verputzerei",
    "sg:phone":"+41 79 468 06 23",
    "sg:postcode":"9424",
    "sg:province":"St. Gallen",
    "wof:name":"Gebr\u00fcder Badali Gmbh",
    "wof:placetype":"venue"
},
  "geometry": {"coordinates":[9.5813083649,47.4667129517],"type":"Point"}
}