{
  "type": "Feature",
  "properties": {
    "iso:country":"CH",
    "sg:address":"Freibachstrasse 26",
    "sg:city":"Rheineck",
    "sg:orig_category":"Kauf U Verkauf von Immobilien auf eigene Rechnung",
    "sg:postcode":"9424",
    "sg:province":"St. Gallen",
    "wof:name":"Flurag",
    "wof:placetype":"venue"
},
  "geometry": {"coordinates":[9.5821771622,47.4685211182],"type":"Point"}
}