{
  "type": "Feature",
  "properties": {
    "iso:country":"CH",
    "sg:address":"Landstrasse 53 8197 Rafz. Postfach Posfach 58",
    "sg:city":"Rafz",
    "sg:orig_category":"Informatikdienste Sonstige mit der Informatik verbundene T\u00e4tigkeiten",
    "sg:phone":"+41 18692189",
    "sg:postcode":"8197",
    "sg:province":"Z\u00fcrich",
    "wof:name":"Universweb Web-net-hosting-service",
    "wof:placetype":"venue"
},
  "geometry": {"coordinates":[8.5474748611,47.6137542725],"type":"Point"}
}