{
  "type": "Feature",
  "properties": {
    "iso:country":"CH",
    "sg:address":"Coulouvreni\u00e8re Rue De La 19",
    "sg:city":"Gen\u00e8ve",
    "sg:orig_category":"Handel mit Automobilen",
    "sg:postcode":"1204",
    "sg:province":"Gen\u00e8ve",
    "wof:name":"Cougan Sa",
    "wof:placetype":"venue"
},
  "geometry": {"coordinates":[6.1373538971,46.2040061951],"type":"Point"}
}