{
  "type": "Feature",
  "properties": {
    "iso:country":"CH",
    "sg:address":"Tannenbachstrasse 14 8942 Oberrieden. Postfach",
    "sg:city":"Oberrieden",
    "sg:orig_category":"Unternehmensberatung",
    "sg:phone":"+41 17200162",
    "sg:postcode":"8942",
    "sg:province":"Z\u00fcrich",
    "wof:name":"Ts Consulting M.feuerstein",
    "wof:placetype":"venue"
},
  "geometry": {"coordinates":[8.5803823471,47.2691078186],"type":"Point"}
}