{
  "type": "Feature",
  "properties": {
    "iso:country":"CH",
    "sg:address":"Thurgauerstrasse 33",
    "sg:city":"Rorschach",
    "sg:orig_category":"Detailhandel mit Teppichen Verlegen von Fussboden",
    "sg:phone":"+41 71 841 87 88",
    "sg:postcode":"9400",
    "sg:province":"St. Gallen",
    "wof:name":"Hans Niederer Teppiche & Bodenbel\u00e4ge",
    "wof:placetype":"venue"
},
  "geometry": {"coordinates":[9.4856386185,47.4796257019],"type":"Point"}
}