{
  "type": "Feature",
  "properties": {
    "iso:country":"CH",
    "sg:address":"Luzernerstrasse 68",
    "sg:city":"Neudorf",
    "sg:orig_category":"Grosshandel mit landwirtschaftlichen Maschinen U Ger\u00e4ten",
    "sg:phone":"+41 41 930 10 55",
    "sg:postcode":"6025",
    "sg:province":"Luzern",
    "wof:name":"Chappuis Ag",
    "wof:placetype":"venue"
},
  "geometry": {"coordinates":[8.2104043961,47.1748161316],"type":"Point"}
}