{
  "type": "Feature",
  "properties": {
    "iso:country":"CH",
    "sg:address":"Zweierstrasse 182",
    "sg:city":"Z\u00fcrich",
    "sg:orig_category":"Sonstiger Grosshandel",
    "sg:postcode":"8003",
    "sg:province":"Z\u00fcrich",
    "wof:name":"Biafori & Co",
    "wof:placetype":"venue"
},
  "geometry": {"coordinates":[8.517334938,47.3696098328],"type":"Point"}
}