{
  "type": "Feature",
  "properties": {
    "iso:country":"CH",
    "sg:address":"Knubelacker 17",
    "sg:city":"Zollbr\u00fcck",
    "sg:orig_category":"Grosshandel mit Milch, Milcherzeugnissen, Eiern, Speise\u00f6len U Nahrungsfetten Sonstiger Fachdetailhan",
    "sg:phone":"+41 34 402 13 22",
    "sg:postcode":"3436",
    "sg:province":"Bern",
    "wof:name":"Probst & Co Ag",
    "wof:placetype":"venue"
},
  "geometry": {"coordinates":[7.7478561401,46.9762458801],"type":"Point"}
}