{
  "type": "Feature",
  "properties": {
    "iso:country":"CH",
    "sg:address":"Route De France 23",
    "sg:city":"Soyhi\u00e8res",
    "sg:orig_category":"Sprachschulen",
    "sg:phone":"+41 32 422 01 24",
    "sg:postcode":"2805",
    "sg:province":"Jura",
    "wof:name":"Maison Chappuis Pensionnat De Jeunes Filles",
    "wof:placetype":"venue"
},
  "geometry": {"coordinates":[7.3694219589,47.3911819458],"type":"Point"}
}