{
  "type": "Feature",
  "properties": {
    "iso:country":"CH",
    "sg:address":"Jupiterstrasse 49",
    "sg:city":"Z\u00fcrich",
    "sg:orig_category":"Internationale Organisationen mit Beh\u00f6rdecharakter",
    "sg:phone":"+41 14223839",
    "sg:postcode":"8032",
    "sg:province":"Z\u00fcrich",
    "wof:name":"Verband Intern.de Philat\u00e9lie Fip",
    "wof:placetype":"venue"
},
  "geometry": {"coordinates":[8.5653867722,47.3657798767],"type":"Point"}
}