{
  "type": "Feature",
  "properties": {
    "iso:country":"CH",
    "sg:address":"Avenue Du Lac 71",
    "sg:city":"Avenue Du Lac 71",
    "sg:orig_category":"Fachdetailhandel in Verkaufsr\u00e4umen",
    "sg:postcode":"2026",
    "wof:name":"Rosen Waibel Gmbh",
    "wof:placetype":"venue"
},
  "geometry": {"coordinates":[9.5376768112,47.378780365],"type":"Point"}
}