{
  "type": "Feature",
  "properties": {
    "iso:country":"CH",
    "sg:address":"Ancienne-poste",
    "sg:city":"F\u00e9chy",
    "sg:orig_category":"Rebbau",
    "sg:phone":"+41 21 808 50 06",
    "sg:postcode":"1173",
    "sg:province":"Vaud",
    "wof:name":"Ren\u00e9 Barbay Viticulteur",
    "wof:placetype":"venue"
},
  "geometry": {"coordinates":[6.3719658852,46.4802742004],"type":"Point"}
}