{
  "type": "Feature",
  "properties": {
    "iso:country":"CH",
    "sg:address":"Bernstrasse 101",
    "sg:city":"M\u00fcnchenbuchsee",
    "sg:orig_category":"Lagerung Verpackungsgewerbe",
    "sg:phone":"+41 31 869 37 38",
    "sg:postcode":"3053",
    "sg:province":"Bern",
    "wof:name":"Gittersberger Erich Ag",
    "wof:placetype":"venue"
},
  "geometry": {"coordinates":[7.4602007866,47.0115737915],"type":"Point"}
}