{
  "type": "Feature",
  "properties": {
    "iso:country":"CH",
    "sg:address":"K\u00fcrbergstrasse 20",
    "sg:city":"Z\u00fcrich",
    "sg:orig_category":"Sonstige Institutionen des Sozialwesens ohne Beherbergung",
    "sg:phone":"+41 13420914",
    "sg:postcode":"8049",
    "sg:province":"Z\u00fcrich",
    "wof:name":"Ruth Stucki M\u00fctterberatung H\u00f6ngg Riedhof",
    "wof:placetype":"venue"
},
  "geometry": {"coordinates":[8.5070123672,47.3995933533],"type":"Point"}
}