{
  "type": "Feature",
  "properties": {
    "iso:country":"CH",
    "sg:address":"Bramenstrasse 11",
    "sg:city":"Bachenb\u00fclach",
    "sg:orig_category":"Vermietung U Verpachtung von eigenen Immobilien",
    "sg:postcode":"8184",
    "sg:province":"Z\u00fcrich",
    "wof:name":"Immobilien Moor Ag",
    "wof:placetype":"venue"
},
  "geometry": {"coordinates":[8.5380506516,47.5030937195],"type":"Point"}
}