{
  "type": "Feature",
  "properties": {
    "iso:country":"CH",
    "sg:address":"4600",
    "sg:city":"Olten",
    "sg:classifiers":[
        {
            "category":"Insurance",
            "subcategory":"Life Insurance",
            "type":"Services"
        }
    ],
    "sg:phone":"+41 62 212 10 51",
    "sg:postcode":"4600",
    "sg:province":"Solothurn",
    "sg:tags":[
        "felt",
        "hat"
    ],
    "wof:name":"Redes-import",
    "wof:placetype":"venue"
},
  "geometry": {"coordinates":[7.902009964,47.3510093689],"type":"Point"}
}