{
  "type": "Feature",
  "properties": {
    "iso:country":"CH",
    "sg:address":"Dorfzentrum",
    "sg:city":"Murg",
    "sg:orig_category":"Allgemeiner Hochbau Strassenbau",
    "sg:phone":"+41 81 723 25 64",
    "sg:postcode":"8877",
    "sg:province":"St. Gallen",
    "wof:name":"Giger Ag Hoch-& Tiefbau",
    "wof:placetype":"venue"
},
  "geometry": {"coordinates":[9.216112,47.113022],"type":"Point"}
}