{
  "type": "Feature",
  "properties": {
    "iso:country":"CH",
    "sg:address":"Schaffhauserstrasse 126",
    "sg:city":"Kloten",
    "sg:orig_category":"Unternehmensberatung",
    "sg:postcode":"8302",
    "sg:province":"Z\u00fcrich",
    "wof:name":"Sts Marketing Systeme Ag",
    "wof:placetype":"venue"
},
  "geometry": {"coordinates":[8.581454277,47.4510154724],"type":"Point"}
}