{
  "type": "Feature",
  "properties": {
    "iso:country":"CH",
    "sg:address":"Via Gaggiolo 54",
    "sg:city":"Stabio",
    "sg:classifiers":[
        {
            "category":"Bars & Pubs",
            "type":"Food & Drink"
        }
    ],
    "sg:phone":"+41 91 647 32 97",
    "sg:postcode":"6855",
    "sg:province":"Ticino",
    "wof:name":"Bar Dogana",
    "wof:placetype":"venue"
},
  "geometry": {"coordinates":[8.91802,45.842442],"type":"Point"}
}