{
  "type": "Feature",
  "properties": {
    "iso:country":"CH",
    "sg:address":"Wiesstrasse 15",
    "sg:city":"Oberegg",
    "sg:orig_category":"Detailhandel mit elektrischen Haushalts-,Radio U Fernsehger\u00e4ten sowie Musikinstrumenten",
    "sg:phone":"+41 71 891 45 11",
    "sg:postcode":"9413",
    "sg:province":"Appenzell Innerhoden",
    "wof:name":"Axel's Records Gmbh",
    "wof:placetype":"venue"
},
  "geometry": {"coordinates":[9.5510387421,47.4251403809],"type":"Point"}
}