{
  "type": "Feature",
  "properties": {
    "iso:country":"CH",
    "sg:address":"Hofwiesweg 5",
    "sg:city":"Appenzell",
    "sg:orig_category":"Zahnarztpraxen",
    "sg:phone":"+41 71 787 13 57",
    "sg:postcode":"9050",
    "sg:province":"Appenzell Innerhoden",
    "wof:name":"Dr. Med. Dent. Balz H\u00e4fliger Zahnarzt",
    "wof:placetype":"venue"
},
  "geometry": {"coordinates":[9.4036417007,47.3307228088],"type":"Point"}
}