{
  "type": "Feature",
  "properties": {
    "iso:country":"CH",
    "sg:address":"Granois",
    "sg:city":"Savi\u00e8se",
    "sg:orig_category":"Rebbau",
    "sg:phone":"+41 26 673 15 55",
    "sg:postcode":"1965",
    "sg:province":"Valais",
    "wof:name":"Gilbert Chautems Viticulteur",
    "wof:placetype":"venue"
},
  "geometry": {"coordinates":[7.0819420815,46.9478416443],"type":"Point"}
}