{
  "type": "Feature",
  "properties": {
    "iso:country":"CH",
    "sg:address":"Orpundstrasse 77 2504 Biel/bienne Case Postale 1080",
    "sg:city":"Biel/bienne",
    "sg:orig_category":"Handel mit Automobilen",
    "sg:phone":"+41 32 342 54 54",
    "sg:postcode":"2501",
    "sg:province":"Bern",
    "wof:name":"Orpundgarage Biel Ag Automobile, -bestandteile, Zubeh\u00f6r; Handel, Reparatur Usw",
    "wof:placetype":"venue"
},
  "geometry": {"coordinates":[7.2839708328,47.1425094604],"type":"Point"}
}