{
  "type": "Feature",
  "properties": {
    "iso:country":"CH",
    "sg:address":"Wartstrasse 24",
    "sg:city":"Winterthur",
    "sg:classifiers":[
        {
            "category":"Restaurant",
            "type":"Food & Drink"
        }
    ],
    "sg:phone":"+41 52 212 15 18",
    "sg:postcode":"8400",
    "sg:province":"Z\u00fcrich",
    "wof:name":"Restaurant Warteck",
    "wof:placetype":"venue"
},
  "geometry": {"coordinates":[8.7213983536,47.5012969971],"type":"Point"}
}