{
  "type": "Feature",
  "properties": {
    "addr:full":"Alte Steinhauserstrasse 19 Cham Zug 6330",
    "addr:housenumber":"19",
    "addr:postcode":"6330",
    "addr:street":"Alte Steinhauserstrasse;Zug",
    "iso:country":"CH",
    "sg:address":"Alte Steinhauserstrasse 19",
    "sg:city":"Cham",
    "sg:orig_category":"Datenverarbeitungsdienste Wirtschaftspr\u00fcfung, Steuerberatung U Treuhand",
    "sg:postcode":"6330",
    "sg:province":"Zug",
    "wof:name":"Calfid Ag Treuhandgesellschaft",
    "wof:placetype":"venue"
},
  "geometry": {"coordinates":[8.852437,47.261463],"type":"Point"}
}