{
  "type": "Feature",
  "properties": {
    "iso:country":"CH",
    "sg:address":"Hindelbankstrasse 10",
    "sg:city":"Sch\u00f6nb\u00fchl-urtenen",
    "sg:orig_category":"Geschenk- and Werbeartikel Grosshandel",
    "sg:phone":"+41 31 331 37 38",
    "sg:postcode":"3322",
    "sg:province":"Bern",
    "wof:name":"Pin's Factory Pin's & Werbeartikel",
    "wof:placetype":"venue"
},
  "geometry": {"coordinates":[7.4515480995,46.9568443298],"type":"Point"}
}