{
  "type": "Feature",
  "properties": {
    "iso:country":"CH",
    "sg:address":"Bielstrasse 10",
    "sg:city":"Aegerten",
    "sg:orig_category":"Vereine Harmonika and Akkordeon",
    "sg:phone":"+41 32 331 72 54",
    "sg:postcode":"2558",
    "sg:province":"Bern",
    "wof:name":"Akkordeon-orchester Blau-weiss",
    "wof:placetype":"venue"
},
  "geometry": {"coordinates":[7.287209034,47.1221847534],"type":"Point"}
}