{
  "type": "Feature",
  "properties": {
    "iso:country":"CH",
    "sg:address":"Oberdorfstrasse 13 6340 Baar. Postfach 2458",
    "sg:city":"Baar",
    "sg:orig_category":"Herstellung von sonstigen elektrischen Ausr\u00fcstungen",
    "sg:phone":"+41 41 760 30 40",
    "sg:postcode":"6342",
    "sg:province":"Zug",
    "wof:name":"Knobel Urs Ag",
    "wof:placetype":"venue"
},
  "geometry": {"coordinates":[8.5304355621,47.1960144043],"type":"Point"}
}