{
  "type": "Feature",
  "properties": {
    "iso:country":"CH",
    "sg:address":"Alte Steinhauserstrasse 29",
    "sg:city":"Cham",
    "sg:orig_category":"Grosshandel mit Geschenkartikeln U Souvenirs Grosshandel mit elektrischen Haushaltsger\u00e4ten, Radio U ",
    "sg:phone":"+41 41 748 50 10",
    "sg:postcode":"6330",
    "sg:province":"Zug",
    "wof:name":"Sir Heian Ag",
    "wof:placetype":"venue"
},
  "geometry": {"coordinates":[8.4746589661,47.1902122498],"type":"Point"}
}