{
  "type": "Feature",
  "properties": {
    "iso:country":"CH",
    "sg:address":"8580",
    "sg:city":"Amriswil",
    "sg:orig_category":"Zimmerei, Dachdeckerei, Bauspenglerei U Abdichtung",
    "sg:phone":"+41 71 411 39 57",
    "sg:postcode":"8580",
    "sg:province":"Thurgau",
    "wof:name":"Gubler Hans",
    "wof:placetype":"venue"
},
  "geometry": {"coordinates":[9.2995681763,47.54504776],"type":"Point"}
}