{
  "type": "Feature",
  "properties": {
    "iso:country":"CH",
    "sg:address":"Finkenweg 30",
    "sg:city":"Niederbipp",
    "sg:orig_category":"Einbau von Schreinerwaren Herstellung von K\u00fcchenm\u00f6beln",
    "sg:postcode":"4704",
    "sg:province":"Bern",
    "wof:name":"Martin Dolder",
    "wof:placetype":"venue"
},
  "geometry": {"coordinates":[7.6890678406,47.26820755],"type":"Point"}
}