{
  "type": "Feature",
  "properties": {
    "iso:country":"CH",
    "sg:address":"Schulstrasse 101e",
    "sg:city":"Rizenbach",
    "sg:orig_category":"Herstellung von Metallkonstruktionen Stahl U Leichtmetallbau",
    "sg:phone":"+41 32 365 32 32",
    "sg:postcode":"3206",
    "sg:province":"Bern",
    "wof:name":"Vallo Sa",
    "wof:placetype":"venue"
},
  "geometry": {"coordinates":[7.2603640556,47.1212997437],"type":"Point"}
}