{
  "type": "Feature",
  "properties": {
    "iso:country":"CH",
    "sg:address":"Chemin Des Sources 1",
    "sg:city":"Marly",
    "sg:orig_category":"Sanit\u00e4rinstallation",
    "sg:phone":"+41 32 968 71 38",
    "sg:postcode":"1723",
    "sg:province":"Fribourg",
    "wof:name":"Joao Luis Sousa Dos Santos Installation Sanitaire",
    "wof:placetype":"venue"
},
  "geometry": {"coordinates":[6.8270559311,47.1100845337],"type":"Point"}
}