{
  "type": "Feature",
  "properties": {
    "iso:country":"CH",
    "sg:address":"Seestrasse 70",
    "sg:city":"R\u00fcschlikon",
    "sg:orig_category":"Maler U Glasergewerbe Malerei",
    "sg:phone":"+41 18306040",
    "sg:postcode":"8803",
    "sg:province":"Z\u00fcrich",
    "wof:name":"Gehringer & Dillschneider",
    "wof:placetype":"venue"
},
  "geometry": {"coordinates":[8.7607221603,47.4835586548],"type":"Point"}
}