{
  "type": "Feature",
  "properties": {
    "iso:country":"CH",
    "sg:address":"Nordstrasse 18",
    "sg:city":"Z\u00fcrich",
    "sg:orig_category":"Unclassifiable Establishments",
    "sg:postcode":"8006",
    "sg:province":"Z\u00fcrich",
    "wof:name":"Weltrade Gmbh",
    "wof:placetype":"venue"
},
  "geometry": {"coordinates":[8.5390233994,47.3848838806],"type":"Point"}
}