{
  "type": "Feature",
  "properties": {
    "iso:country":"CH",
    "sg:address":"Bernstrasse 332",
    "sg:city":"Dietikon",
    "sg:orig_category":"Allgemeiner Hoch U Tiefbau",
    "sg:postcode":"8953",
    "sg:province":"Z\u00fcrich",
    "wof:name":"Gaiardelli Ag",
    "wof:placetype":"venue"
},
  "geometry": {"coordinates":[8.402835,47.393486],"type":"Point"}
}