{
  "type": "Feature",
  "properties": {
    "iso:country":"CH",
    "sg:address":"6558",
    "sg:city":"Lostallo",
    "sg:orig_category":"Schulpflegen",
    "sg:postcode":"6558",
    "sg:province":"Graubunden",
    "wof:name":"Delegazione Scolastica Del Comune Di Lostallo",
    "wof:placetype":"venue"
},
  "geometry": {"coordinates":[9.1959848404,46.3131256104],"type":"Point"}
}