{
  "type": "Feature",
  "properties": {
    "iso:country":"CH",
    "sg:address":"Speichergasse 5 3005 Bern. Postfach",
    "sg:city":"Bern",
    "sg:orig_category":"Verwaltung von Immobilien",
    "sg:postcode":"3005",
    "sg:province":"Bern",
    "wof:name":"Imag Bauinvest Ag Immobilien, Bes. An Der Scheibenstrasse Usw",
    "wof:placetype":"venue"
},
  "geometry": {"coordinates":[7.4439201355,46.949836731],"type":"Point"}
}