{
  "type": "Feature",
  "properties": {
    "iso:country":"CH",
    "sg:address":"Mattstrasse 18",
    "sg:city":"Netstal",
    "sg:orig_category":"Elektro- and elektronische Maschinen Grosshandel Herstellung von elektronischen Bauelementen",
    "sg:phone":"+41 55 280 52 60",
    "sg:postcode":"8754",
    "sg:province":"Glarus",
    "wof:name":"Mep Marogg Electronic Performance Gmbh",
    "wof:placetype":"venue"
},
  "geometry": {"coordinates":[9.058426857,47.0602226257],"type":"Point"}
}