{
  "type": "Feature",
  "properties": {
    "iso:country":"CH",
    "sg:address":"Hauptstrasse 45",
    "sg:city":"Holziken",
    "sg:orig_category":"G\u00fcterbef\u00f6rderung im Strassenverkehr",
    "sg:phone":"+41 79 415 18 66",
    "sg:postcode":"5043",
    "sg:province":"Aargau",
    "wof:name":"Roland R\u00fcegger Holztransporte",
    "wof:placetype":"venue"
},
  "geometry": {"coordinates":[8.0333070755,47.3226661682],"type":"Point"}
}