{
  "type": "Feature",
  "properties": {
    "iso:country":"CH",
    "sg:address":"Stebligerweg 2",
    "sg:city":"Sissach",
    "sg:orig_category":"Shiatsu-Therapie",
    "sg:phone":"+41 61 971 63 17",
    "sg:postcode":"4450",
    "sg:province":"Basel-Landschaft",
    "wof:name":"Hanspeter Fluri Massagen & Shiatsu",
    "wof:placetype":"venue"
},
  "geometry": {"coordinates":[7.8064141273,47.4695358276],"type":"Point"}
}