{
  "type": "Feature",
  "properties": {
    "iso:country":"CH",
    "sg:address":"In Der Mettlen 3",
    "sg:city":"B\u00e4retswil",
    "sg:orig_category":"Autogaragen",
    "sg:phone":"+41 19391872",
    "sg:postcode":"8344",
    "sg:province":"Z\u00fcrich",
    "wof:name":"Heinz Stern Ag Garage",
    "wof:placetype":"venue"
},
  "geometry": {"coordinates":[8.858981,47.338428],"type":"Point"}
}