{
  "type": "Feature",
  "properties": {
    "iso:country":"CH",
    "sg:address":"Z\u00fcrcher Strasse 202 9014 St. Gallen. Postfach 9014 St. Gallen",
    "sg:city":"Zust",
    "sg:orig_category":"Unternehmensberatung",
    "sg:phone":"+41 71 272 23 13",
    "sg:postcode":"14",
    "wof:name":"Management Intelligence Gmbh",
    "wof:placetype":"venue"
},
  "geometry": {"coordinates":[9.3368339539,47.4125785828],"type":"Point"}
}