{
  "type": "Feature",
  "properties": {
    "iso:country":"CH",
    "sg:address":"Grand-bureau Rue Du 22 1200 Gen\u00e8ve. Postfach",
    "sg:city":"Gen\u00e8ve",
    "sg:orig_category":"Maler U Glasergewerbe",
    "sg:phone":"+41 18503306",
    "sg:postcode":"1200",
    "sg:province":"Gen\u00e8ve",
    "wof:name":"H\u00e4berling Ren\u00e9, Jun.",
    "wof:placetype":"venue"
},
  "geometry": {"coordinates":[8.5039148331,47.4934272766],"type":"Point"}
}