{
  "type": "Feature",
  "properties": {
    "iso:country":"CH",
    "sg:address":"Pestalozziweg 1",
    "sg:city":"Bremgarten",
    "sg:classifiers":[
        {
            "category":"Utilities",
            "subcategory":"Cable",
            "type":"Services"
        }
    ],
    "sg:phone":"+41 31 300 33 33",
    "sg:postcode":"3047",
    "sg:province":"Bern",
    "sg:tags":[
        "sector-specific",
        "solution",
        "software"
    ],
    "wof:name":"Data Dynamic Informatic Ag",
    "wof:placetype":"venue"
},
  "geometry": {"coordinates":[7.4390850067,46.9770736694],"type":"Point"}
}