{
  "type": "Feature",
  "properties": {
    "iso:country":"CH",
    "sg:address":"Binzikonerstrasse",
    "sg:city":"Gr\u00fcningen",
    "sg:orig_category":"Herstellung von sonstigen Fahrzeugen",
    "sg:phone":"+41 19351564",
    "sg:postcode":"8627",
    "sg:province":"Z\u00fcrich",
    "wof:name":"Emil Leemann Holzbau & Wagnerei",
    "wof:placetype":"venue"
},
  "geometry": {"coordinates":[8.759554863,47.2783813477],"type":"Point"}
}