{
  "type": "Feature",
  "properties": {
    "iso:country":"CH",
    "sg:address":"Bahnhofstrasse 11",
    "sg:city":"Sursee",
    "sg:orig_category":"Markt U Meinungsforschung Werbeberatung",
    "sg:phone":"+41 19221827",
    "sg:postcode":"6210",
    "sg:province":"Luzern",
    "wof:name":"Marketing Factory/bachofner Rainer",
    "wof:placetype":"venue"
},
  "geometry": {"coordinates":[8.0991439819,47.1701202393],"type":"Point"}
}