{
  "type": "Feature",
  "properties": {
    "iso:country":"CH",
    "sg:address":"Quellenweg 11",
    "sg:city":"Aarwangen",
    "sg:orig_category":"Sportvereine Wassersport Schwimmen",
    "sg:phone":"+41 62 922 70 04",
    "sg:postcode":"4912",
    "sg:province":"Bern",
    "wof:name":"Schwimmclub Aarwangen",
    "wof:placetype":"venue"
},
  "geometry": {"coordinates":[7.7688379288,47.2379302979],"type":"Point"}
}