{
  "type": "Feature",
  "properties": {
    "iso:country":"CH",
    "sg:address":"Niederb\u00fcrerstrasse 8",
    "sg:city":"Bischofszell",
    "sg:orig_category":"G\u00fcterbef\u00f6rderung im Strassenverkehr",
    "sg:postcode":"9220",
    "sg:province":"Thurgau",
    "wof:name":"Mettler Transporte",
    "wof:placetype":"venue"
},
  "geometry": {"coordinates":[8.4379940033,47.0760955811],"type":"Point"}
}