{
  "type": "Feature",
  "properties": {
    "iso:country":"CH",
    "sg:address":"Bundesstrasse 13",
    "sg:city":"Luzern",
    "sg:classifiers":[
        {
            "category":"Government",
            "subcategory":"Court House",
            "type":"Public Place"
        }
    ],
    "sg:phone":"+41 41 210 68 00",
    "sg:postcode":"6003",
    "sg:province":"Luzern",
    "sg:tags":[
        "player",
        "cd"
    ],
    "wof:name":"Electronova Luzern Gmbh",
    "wof:placetype":"venue"
},
  "geometry": {"coordinates":[8.305539,47.044613],"type":"Point"}
}