{
  "type": "Feature",
  "properties": {
    "iso:country":"CH",
    "sg:address":"Postweg 3",
    "sg:city":"Sch\u00f6nenwerd",
    "sg:orig_category":"Detailhandel mit fotografischen Artikeln Fotografisches Gewerbe U fotografische Laboratorien",
    "sg:phone":"+41 62 849 19 67",
    "sg:postcode":"5012",
    "sg:province":"Solothurn",
    "wof:name":"Foto-color-studio Simon",
    "wof:placetype":"venue"
},
  "geometry": {"coordinates":[8.0025205612,47.3730773926],"type":"Point"}
}