{
  "type": "Feature",
  "properties": {
    "iso:country":"CH",
    "sg:address":"T\u00fcfiwis 26 8332 Russikon. Postfach",
    "sg:city":"Russikon",
    "sg:orig_category":"Herstellung von industriellen Prozesssteuerungsanlagen Maschinen-Fabrikation",
    "sg:phone":"+41 19562000",
    "sg:postcode":"8332",
    "sg:province":"Z\u00fcrich",
    "wof:name":"Indel Ag Industrielle Elektronik",
    "wof:placetype":"venue"
},
  "geometry": {"coordinates":[8.7726097107,47.3912200928],"type":"Point"}
}