{
  "type": "Feature",
  "properties": {
    "iso:country":"CH",
    "sg:address":"Bleikenweg 2",
    "sg:city":"B\u00f6singen",
    "sg:orig_category":"Herstellung von Metallerzeugnissen ohne Maschinenbau Sonstiger spezialisierter Hoch U Tiefbau",
    "sg:phone":"+41 31 747 80 14",
    "sg:postcode":"3178",
    "sg:province":"Fribourg",
    "wof:name":"Perrottet Und Piller Ag",
    "wof:placetype":"venue"
},
  "geometry": {"coordinates":[7.2279667854,46.8925971985],"type":"Point"}
}