{
  "type": "Feature",
  "properties": {
    "iso:country":"CH",
    "sg:address":"Gruy\u00e8res Rue De 26 1630 Bulle. Postfach",
    "sg:city":"Bulle",
    "sg:orig_category":"RESTAURANTS: TEA-ROOMS",
    "sg:postcode":"1630",
    "sg:province":"Fribourg",
    "wof:name":"Caf\u00e9 Iguana, Morand Karine Et Fassi Maurizio",
    "wof:placetype":"venue"
},
  "geometry": {"coordinates":[7.0570378304,46.6161613464],"type":"Point"}
}