{
  "type": "Feature",
  "properties": {
    "iso:country":"CH",
    "sg:address":"Schumacherweg 24",
    "sg:city":"Z\u00fcrich",
    "sg:orig_category":"Sonstiger Grosshandel",
    "sg:phone":"+41 13721612",
    "sg:postcode":"8046",
    "sg:province":"Z\u00fcrich",
    "wof:name":"D. Nikolic - Export-import",
    "wof:placetype":"venue"
},
  "geometry": {"coordinates":[8.5140743256,47.4131507874],"type":"Point"}
}