{
  "type": "Feature",
  "properties": {
    "iso:country":"CH",
    "sg:address":"Kirchgasse 7",
    "sg:city":"B\u00fctschwil",
    "sg:orig_category":"Physiotherapie",
    "sg:phone":"+41 71 983 17 78",
    "sg:postcode":"9606",
    "sg:province":"St. Gallen",
    "wof:name":"Andrea Brunner Physiotherapie",
    "wof:placetype":"venue"
},
  "geometry": {"coordinates":[9.0719890594,47.3593063354],"type":"Point"}
}