{
  "type": "Feature",
  "properties": {
    "iso:country":"CH",
    "sg:address":"T\u00e4germatt",
    "sg:city":"M\u00fcnsingen",
    "sg:orig_category":"Landwirtschaft, Jagd U damit verbundene Dienstleistungen",
    "sg:phone":"+41 31 721 12 46",
    "sg:postcode":"3110",
    "sg:province":"Bern",
    "wof:name":"Bernhard Hauswirth Gutsbetrieb",
    "wof:placetype":"venue"
},
  "geometry": {"coordinates":[7.5494308472,46.8828392029],"type":"Point"}
}