{
  "type": "Feature",
  "properties": {
    "iso:country":"CH",
    "sg:address":"Bahnhofstrasse 72 4574 L\u00fcsslingen. Postfach 207",
    "sg:city":"Nennigkofen",
    "sg:orig_category":"Herstellung von Schrauben, Nieten, Ketten U Federn",
    "sg:phone":"+41 32 622 56 55",
    "sg:postcode":"4574",
    "sg:province":"Solothurn",
    "wof:name":"Pr\u00e9vis Ag",
    "wof:placetype":"venue"
},
  "geometry": {"coordinates":[7.4983167648,47.1926422119],"type":"Point"}
}