{
  "type": "Feature",
  "properties": {
    "iso:country":"CH",
    "sg:address":"Contra 6646 Contra. Postfach",
    "sg:city":"Contra",
    "sg:orig_category":"Architektur U Ingenieurb\u00fcros",
    "sg:postcode":"6646",
    "sg:province":"Ticino",
    "wof:name":"Pmc Sa",
    "wof:placetype":"venue"
},
  "geometry": {"coordinates":[8.83944,46.188564],"type":"Point"}
}