{
  "type": "Feature",
  "properties": {
    "addr:full":"Contrada Di Sassello 4 Lugano Ticino 6900",
    "addr:housenumber":"4",
    "addr:postcode":"6900",
    "addr:street":"Contrada Di Sassello",
    "iso:country":"CH",
    "sg:address":"Contrada Di Sassello 4",
    "sg:city":"Lugano",
    "sg:orig_category":"Detailhandel mit Brillen U anderen Sehhilfen Fachdetailhandel in Verkaufsr\u00e4umen",
    "sg:phone":"+41 91 922 72 44",
    "sg:postcode":"6900",
    "sg:province":"Ticino",
    "wof:name":"Cocchi & Brughera Ottica",
    "wof:placetype":"venue"
},
  "geometry": {"coordinates":[8.950099,46.003609],"type":"Point"}
}