{
  "type": "Feature",
  "properties": {
    "iso:country":"CH",
    "sg:address":"4222",
    "sg:city":"Zwingen",
    "sg:orig_category":"Non-Classified Establishments",
    "sg:phone":"+41 61 971 24 55",
    "sg:postcode":"4222",
    "sg:province":"Basel-Landschaft",
    "wof:name":"Architekturb\u00fcro Sia Quartier Und Gesamtplanung.",
    "wof:placetype":"venue"
},
  "geometry": {"coordinates":[7.5277500153,47.4357681274],"type":"Point"}
}