{
  "type": "Feature",
  "properties": {
    "iso:country":"CH",
    "sg:address":"Centre Commercial",
    "sg:city":"Givisiez",
    "sg:orig_category":"Fachdetailhandel in Verkaufsr\u00e4umen",
    "sg:postcode":"1762",
    "sg:province":"Fribourg",
    "wof:name":"Schwab Sandra",
    "wof:placetype":"venue"
},
  "geometry": {"coordinates":[7.131072998,46.8139228821],"type":"Point"}
}