{
  "type": "Feature",
  "properties": {
    "iso:country":"CH",
    "sg:address":"Wangserstrasse 51",
    "sg:city":"Mels",
    "sg:orig_category":"Architekturb\u00fcros",
    "sg:phone":"+41 81 720 44 44",
    "sg:postcode":"8887",
    "sg:province":"St. Gallen",
    "wof:name":"Filippi & Partner Architektur Und Bauleitungs- Ag",
    "wof:placetype":"venue"
},
  "geometry": {"coordinates":[9.424736,47.044239],"type":"Point"}
}