{
  "type": "Feature",
  "properties": {
    "iso:country":"CH",
    "sg:address":"Steckbornstrasse 33",
    "sg:city":"Pfyn",
    "sg:orig_category":"Ger\u00fcstbau Herstellung von Metallkonstruktionen",
    "sg:phone":"+41 52 765 25 22",
    "sg:postcode":"8505",
    "sg:province":"Thurgau",
    "wof:name":"Finger Roland",
    "wof:placetype":"venue"
},
  "geometry": {"coordinates":[8.9509277344,47.5989341736],"type":"Point"}
}