{
  "type": "Feature",
  "properties": {
    "iso:country":"CH",
    "sg:address":"Nidaugasse 18 2500 Biel/bienne. Postfach",
    "sg:city":"Biel/bienne",
    "sg:orig_category":"Detailhandel mit Brot, Back U S\u00fcsswaren",
    "sg:phone":"+41 32 322 35 83",
    "sg:postcode":"2501",
    "sg:province":"Bern",
    "wof:name":"Knuchel-fankhauser R.",
    "wof:placetype":"venue"
},
  "geometry": {"coordinates":[7.28998,47.14674],"type":"Point"}
}