{
  "type": "Feature",
  "properties": {
    "iso:country":"CH",
    "sg:address":"Bahnhofstrasse 7",
    "sg:city":"Biberist",
    "sg:orig_category":"Fachdetailhandel in Verkaufsr\u00e4umen",
    "sg:phone":"+41 32 672 27 60",
    "sg:postcode":"4562",
    "sg:province":"Solothurn",
    "wof:name":"Pytargo Gmbh",
    "wof:placetype":"venue"
},
  "geometry": {"coordinates":[7.5554938316,47.1825294495],"type":"Point"}
}