{
  "type": "Feature",
  "properties": {
    "iso:country":"CH",
    "sg:address":"Bahnhofstrasse 18",
    "sg:city":"Zug",
    "sg:orig_category":"Handelsvermittlung von Brennstoffen, Erzen, Metallen U Chemikalien Sonstiger Grosshandel",
    "sg:phone":"+41 41 710 33 12",
    "sg:postcode":"6300",
    "sg:province":"Zug",
    "wof:name":"Iscar Ag",
    "wof:placetype":"venue"
},
  "geometry": {"coordinates":[8.5158376694,47.1692504883],"type":"Point"}
}