{
  "type": "Feature",
  "properties": {
    "iso:country":"CH",
    "sg:address":"Bielstrasse",
    "sg:city":"Aegerten",
    "sg:orig_category":"Bauschreinerei Herstellung von Konstruktionsteilen, Fertigbauteilen U Ausbauelementen aus Holz",
    "sg:phone":"+41 32 372 17 72",
    "sg:postcode":"2558",
    "sg:province":"Bern",
    "wof:name":"H\u00fcbscher Serviceschreinerei Gmbh",
    "wof:placetype":"venue"
},
  "geometry": {"coordinates":[7.288069,47.121758],"type":"Point"}
}