{
  "type": "Feature",
  "properties": {
    "iso:country":"CH",
    "sg:address":"R\u00fctistrasse 12d",
    "sg:city":"Adliswil",
    "sg:orig_category":"Sonstiger Grosshandel",
    "sg:postcode":"8134",
    "sg:province":"Z\u00fcrich",
    "wof:name":"Janusz Smolinski",
    "wof:placetype":"venue"
},
  "geometry": {"coordinates":[8.527132988,47.3058509827],"type":"Point"}
}