{
  "type": "Feature",
  "properties": {
    "iso:country":"CH",
    "sg:address":"Im Schossacher 12",
    "sg:city":"D\u00fcbendorf",
    "sg:orig_category":"Mit dem Versicherungsgewerbe verbundene T\u00e4tigkeiten",
    "sg:phone":"+41 21 620 75 00",
    "sg:postcode":"8600",
    "sg:province":"Z\u00fcrich",
    "wof:name":"Tradiconsult Sa",
    "wof:placetype":"venue"
},
  "geometry": {"coordinates":[6.6113052368,46.5230331421],"type":"Point"}
}