{
  "type": "Feature",
  "properties": {
    "iso:country":"CH",
    "sg:address":"T\u00f6distrasse 21",
    "sg:city":"Wettingen",
    "sg:orig_category":"Finanzierungsinstitutionen",
    "sg:postcode":"5430",
    "sg:province":"Aargau",
    "wof:name":"Vogt-b\u00fcsser Gmbh",
    "wof:placetype":"venue"
},
  "geometry": {"coordinates":[8.3282299042,47.4599533081],"type":"Point"}
}