{
  "type": "Feature",
  "properties": {
    "iso:country":"CH",
    "sg:address":"Bellariastrasse 64",
    "sg:city":"Z\u00fcrich",
    "sg:orig_category":"Wirtschaftspr\u00fcfung, Steuerberatung U Treuhand",
    "sg:phone":"+41 14824289",
    "sg:postcode":"8038",
    "sg:province":"Z\u00fcrich",
    "wof:name":"Jak Buchhaltung & Beratung Jost A.kummer",
    "wof:placetype":"venue"
},
  "geometry": {"coordinates":[8.5290307999,47.3487892151],"type":"Point"}
}