{
  "type": "Feature",
  "properties": {
    "iso:country":"CH",
    "sg:address":"Simmentalstrasse 17",
    "sg:city":"Spiez",
    "sg:orig_category":"Herstellung von Metallkonstruktionen",
    "sg:phone":"+41 33 654 18 32",
    "sg:postcode":"3700",
    "sg:province":"Bern",
    "wof:name":"Ulrich Jaggi",
    "wof:placetype":"venue"
},
  "geometry": {"coordinates":[7.6600761414,46.6848754883],"type":"Point"}
}