{
  "type": "Feature",
  "properties": {
    "iso:country":"CH",
    "sg:address":"Chemin Des Corneilles 13",
    "sg:city":"Th\u00f4nex",
    "sg:orig_category":"Allgemeiner Gartenbau Landschaftsplanungsb\u00fcros U Gartenarchitekturb\u00fcros",
    "sg:phone":"+41 79 606 38 40",
    "sg:postcode":"1226",
    "sg:province":"Gen\u00e8ve",
    "wof:name":"Cretier Daniel",
    "wof:placetype":"venue"
},
  "geometry": {"coordinates":[6.219639,46.201851],"type":"Point"}
}