{
  "type": "Feature",
  "properties": {
    "iso:country":"CH",
    "sg:address":"6611",
    "sg:city":"Gresso",
    "sg:orig_category":"Sportvereine Ballsport Fussball",
    "sg:postcode":"6611",
    "sg:province":"Ticino",
    "wof:name":"Football Club Gresso",
    "wof:placetype":"venue"
},
  "geometry": {"coordinates":[8.6161623001,46.2246170044],"type":"Point"}
}