{
  "type": "Feature",
  "properties": {
    "iso:country":"CH",
    "sg:address":"Seyon Rue Du 32",
    "sg:city":"Neuch\u00e2tel",
    "sg:orig_category":"Fotografisches Gewerbe U fotografische Laboratorien",
    "sg:phone":"+41 32 724 97 36",
    "sg:postcode":"2000",
    "sg:province":"Neuch\u00e2tel",
    "wof:name":"Photo Num\u00e9rique Service, Fl\u00fcckiger Claude-alain",
    "wof:placetype":"venue"
},
  "geometry": {"coordinates":[6.9310851097,46.9903335571],"type":"Point"}
}