{
  "type": "Feature",
  "properties": {
    "iso:country":"CH",
    "sg:address":"Rue De Neuch\u00e2tel 1",
    "sg:city":"Gen\u00e8ve",
    "sg:orig_category":"Zahntechnische Laboratorien",
    "sg:phone":"+41 22 732 41 69",
    "sg:postcode":"1201",
    "sg:province":"Gen\u00e8ve",
    "wof:name":"Fran\u00e7ois Marmoud Labor.de Proth\u00e8ses Dentaires",
    "wof:placetype":"venue"
},
  "geometry": {"coordinates":[6.1450548172,46.2102546692],"type":"Point"}
}