{
  "type": "Feature",
  "properties": {
    "iso:country":"CH",
    "sg:address":"Langholzstrasse 26 6331 H\u00fcnenberg. Postfach",
    "sg:city":"H\u00fcnenberg",
    "sg:orig_category":"Grosshandel mit Erzen U Metallen",
    "sg:postcode":"6331",
    "sg:province":"Zug",
    "wof:name":"R&r Commodities Ag",
    "wof:placetype":"venue"
},
  "geometry": {"coordinates":[8.4422340393,47.1706390381],"type":"Point"}
}