{
  "type": "Feature",
  "properties": {
    "iso:country":"CH",
    "sg:address":"Klybeckstrasse 249",
    "sg:city":"Basel",
    "sg:orig_category":"Herstellung von Ger\u00e4ten der Elektrizit\u00e4tserzeugung, -verteilung u.\u00e4. -Herstellung von elektronischen",
    "sg:phone":"+41 61 631 12 68",
    "sg:postcode":"4057",
    "sg:province":"Basel-Stadt",
    "wof:name":"M. Sz\u00e9kely Momo Elektronik",
    "wof:placetype":"venue"
},
  "geometry": {"coordinates":[7.588075161,47.5760955811],"type":"Point"}
}