{
  "type": "Feature",
  "properties": {
    "iso:country":"CH",
    "sg:address":"St. Johanns-vorstadt 22",
    "sg:city":"Basel",
    "sg:orig_category":"Grosshandel mit sonstigen Gebrauchs U Verbrauchsg\u00fctern",
    "sg:postcode":"4056",
    "sg:province":"Basel-Stadt",
    "wof:name":"Zoomax Advertising Gmbh",
    "wof:placetype":"venue"
},
  "geometry": {"coordinates":[7.5849618912,47.5631942749],"type":"Point"}
}