{
  "type": "Feature",
  "properties": {
    "iso:country":"CH",
    "sg:address":"Route De Montimbert",
    "sg:city":"Ch\u00e2tel-st-denis",
    "sg:orig_category":"Holzplattenwerke",
    "sg:postcode":"1618",
    "sg:province":"Fribourg",
    "wof:name":"Tornare Robert",
    "wof:placetype":"venue"
},
  "geometry": {"coordinates":[6.8925881386,46.5231132507],"type":"Point"}
}