{
  "type": "Feature",
  "properties": {
    "iso:country":"CH",
    "sg:address":"Industriestr. 21b Im Eisenwerk 8500 Frauenfeld. Postfach",
    "sg:city":"Frauenfeld",
    "sg:orig_category":"Druck ohne Zeitungsdruck",
    "sg:phone":"+41 52 728 89 66",
    "sg:postcode":"8500",
    "sg:province":"Thurgau",
    "wof:name":"Baumann Gebr.",
    "wof:placetype":"venue"
},
  "geometry": {"coordinates":[8.8972301483,47.5554885864],"type":"Point"}
}