{
  "type": "Feature",
  "properties": {
    "iso:country":"CH",
    "sg:address":"Neudorfstrasse 11",
    "sg:city":"Z\u00fcrich",
    "sg:orig_category":"Grosshandel mit sonstigen Gebrauchs U Verbrauchsg\u00fctern Herstellung von Sprengstoffen",
    "sg:phone":"+41 13125516",
    "sg:postcode":"8050",
    "sg:province":"Z\u00fcrich",
    "wof:name":"Alfa Werbe-service Ag",
    "wof:placetype":"venue"
},
  "geometry": {"coordinates":[8.5476331711,47.4112434387],"type":"Point"}
}