{
  "type": "Feature",
  "properties": {
    "iso:country":"CH",
    "sg:address":"St. Jakobs-strasse 222",
    "sg:city":"Basel",
    "sg:classifiers":[
        {
            "category":"Restaurant",
            "type":"Food & Drink"
        }
    ],
    "sg:phone":"+41 21 801 23 39",
    "sg:postcode":"4052",
    "sg:province":"Basel-Stadt",
    "wof:name":"Restaurant Union",
    "wof:placetype":"venue"
},
  "geometry": {"coordinates":[6.4640598297,46.5057106018],"type":"Point"}
}