{
  "type": "Feature",
  "properties": {
    "iso:country":"CH",
    "sg:address":"B\u00fcnishoferstrasse 174",
    "sg:city":"Feldmeilen",
    "sg:orig_category":"Institutionen des Sozialwesens ohne Beherbergung",
    "sg:postcode":"8706",
    "sg:province":"Z\u00fcrich",
    "wof:name":"Otto K\u00e4ppeler Stiftung",
    "wof:placetype":"venue"
},
  "geometry": {"coordinates":[8.6211023331,47.2816238403],"type":"Point"}
}