{
  "type": "Feature",
  "properties": {
    "iso:country":"CH",
    "sg:address":"H\u00e4rdlistrasse 15",
    "sg:city":"Spreitenbach",
    "sg:orig_category":"Erbringung von Dienstleistungen f\u00fcr Unternehmen Verlagsgewerbe",
    "sg:phone":"+41 56 418 40 30",
    "sg:postcode":"8957",
    "sg:province":"Aargau",
    "wof:name":"S & K Gmbh",
    "wof:placetype":"venue"
},
  "geometry": {"coordinates":[8.3679733276,47.4311828613],"type":"Point"}
}