{
  "type": "Feature",
  "properties": {
    "iso:country":"CH",
    "sg:address":"Seebacherstrasse 69 8052 Z\u00fcrich. Postfach",
    "sg:city":"Z\u00fcrich",
    "sg:orig_category":"Instandhaltung U Reparatur von Automobilen",
    "sg:phone":"+41 13022566",
    "sg:postcode":"8052",
    "sg:province":"Z\u00fcrich",
    "wof:name":"Autogarage Vogt J.p.",
    "wof:placetype":"venue"
},
  "geometry": {"coordinates":[8.5412969589,47.4226951599],"type":"Point"}
}