{
  "type": "Feature",
  "properties": {
    "iso:country":"CH",
    "sg:address":"Le Ruz",
    "sg:city":"Hauteville",
    "sg:classifiers":[
        {
            "category":"Restaurant",
            "type":"Food & Drink"
        }
    ],
    "sg:phone":"+41 26 915 15 51",
    "sg:postcode":"1648",
    "sg:province":"Fribourg",
    "wof:name":"Auberge Du Lion D'or",
    "wof:placetype":"venue"
},
  "geometry": {"coordinates":[7.1184802055,46.6770935059],"type":"Point"}
}