{
  "type": "Feature",
  "properties": {
    "iso:country":"CH",
    "sg:address":"Grienstrasse 26",
    "sg:city":"Basel",
    "sg:classifiers":[
        {
            "category":"Personal",
            "subcategory":"Piercing",
            "type":"Services"
        }
    ],
    "sg:phone":"+41 61 322 48 90",
    "sg:postcode":"4055",
    "sg:province":"Basel-Stadt",
    "sg:tags":[
        "tattoo"
    ],
    "wof:name":"Rattattoo T\u00e4towierungen",
    "wof:placetype":"venue"
},
  "geometry": {"coordinates":[7.5644750595,47.5633087158],"type":"Point"}
}