{
  "type": "Feature",
  "properties": {
    "iso:country":"CH",
    "sg:address":"Furthof",
    "sg:city":"W\u00e4denswil",
    "sg:classifiers":[
        {
            "category":"Communications",
            "subcategory":"Television Station",
            "type":"Services"
        }
    ],
    "sg:phone":"+41 16803606",
    "sg:postcode":"8820",
    "sg:province":"Z\u00fcrich",
    "sg:tags":[
        "avionics"
    ],
    "wof:name":"Erik Detering",
    "wof:placetype":"venue"
},
  "geometry": {"coordinates":[8.660573,47.221828],"type":"Point"}
}