{
  "type": "Feature",
  "properties": {
    "iso:country":"CH",
    "sg:address":"Wiedingstrasse 78 8045 Z\u00fcrich. Postfach",
    "sg:city":"Z\u00fcrich",
    "sg:orig_category":"Organisationen der Wohlfahrtspflege",
    "sg:phone":"+41 41 210 49 36",
    "sg:postcode":"8036",
    "sg:province":"Z\u00fcrich",
    "wof:name":"Schweizerischer Katholischer Frauenbund Skf",
    "wof:placetype":"venue"
},
  "geometry": {"coordinates":[8.3028726578,47.0501403809],"type":"Point"}
}