{
  "type": "Feature",
  "properties": {
    "iso:country":"CH",
    "sg:address":"Weiermatt 7",
    "sg:city":"L\u00e4ngenb\u00fchl",
    "sg:orig_category":"Grosshandel mit lebenden Tieren",
    "sg:phone":"+41 79 656 87 68",
    "sg:postcode":"3636",
    "sg:province":"Bern",
    "wof:name":"Martin Wenger Viehhandlung",
    "wof:placetype":"venue"
},
  "geometry": {"coordinates":[7.5483298302,46.7568054199],"type":"Point"}
}