{
  "type": "Feature",
  "properties": {
    "iso:country":"CH",
    "sg:address":"Freilagerstrasse 47",
    "sg:city":"Z\u00fcrich",
    "sg:orig_category":"Detailhandel mit M\u00f6beln U Haushaltsgegenst\u00e4nden Grosshandel mit M\u00f6beln, Wohnbedarf, Teppichen U Bode",
    "sg:phone":"+41 91 946 41 06",
    "sg:postcode":"8043",
    "sg:province":"Z\u00fcrich",
    "wof:name":"Bc Diffusion Sa",
    "wof:placetype":"venue"
},
  "geometry": {"coordinates":[8.927479744,46.0982551575],"type":"Point"}
}