{
  "type": "Feature",
  "properties": {
    "iso:country":"CH",
    "sg:address":"Wieslergasse 10",
    "sg:city":"Z\u00fcrich",
    "sg:orig_category":"Verwaltung der Rechtspflege, Gerichte",
    "sg:phone":"+41 13415455",
    "sg:postcode":"8049",
    "sg:province":"Z\u00fcrich",
    "wof:name":"Notariat Grundbuch-& Konkursamt H\u00f6ngg-z\u00fcrich",
    "wof:placetype":"venue"
},
  "geometry": {"coordinates":[8.4962091446,47.4029273987],"type":"Point"}
}