{
  "type": "Feature",
  "properties": {
    "iso:country":"CH",
    "sg:address":"Route De Sion 69",
    "sg:city":"Sierre",
    "sg:orig_category":"Sonstiger spezialisierter Hoch U Tiefbau",
    "sg:phone":"+41 27 455 44 40",
    "sg:postcode":"3960",
    "sg:province":"Valais",
    "wof:name":"Diamcoupe Sa Forage & Sciage De B\u00e9ton",
    "wof:placetype":"venue"
},
  "geometry": {"coordinates":[7.5185818672,46.2859039307],"type":"Point"}
}