{
  "type": "Feature",
  "properties": {
    "iso:country":"CH",
    "sg:address":"Schulstrasse 160 8413 Neftenbach. Postfach",
    "sg:city":"Neftenbach",
    "sg:orig_category":"Unclassifiable Establishments",
    "sg:postcode":"8413",
    "sg:province":"Z\u00fcrich",
    "wof:name":"Wolfweb B\u00e4chi Gabriela Dienstleistungen In Den Bereichen Administration Und Informatik, Bes. Web-design",
    "wof:placetype":"venue"
},
  "geometry": {"coordinates":[8.6598119736,47.5235404968],"type":"Point"}
}