{
  "type": "Feature",
  "properties": {
    "iso:country":"CH",
    "sg:address":"Marktplatz 1",
    "sg:city":"Lyss",
    "sg:orig_category":"Zahnarztpraxen",
    "sg:phone":"+41 32 384 44 10",
    "sg:postcode":"3250",
    "sg:province":"Bern",
    "wof:name":"Dr. Med. Dent. Rudolf M\u00f6sch Zahnarzt",
    "wof:placetype":"venue"
},
  "geometry": {"coordinates":[7.3063831329,47.0736045837],"type":"Point"}
}