{
  "type": "Feature",
  "properties": {
    "iso:country":"CH",
    "sg:address":"Heliosstrasse 25",
    "sg:city":"Z\u00fcrich",
    "sg:orig_category":"Sonstige Aktivit\u00e4ten der nicht-\u00e4rztlichen Medizinalberufe",
    "sg:phone":"+41 13818141",
    "sg:postcode":"8032",
    "sg:province":"Z\u00fcrich",
    "wof:name":"Dorothea Furrer Kinesiologie & Atemtherapie",
    "wof:placetype":"venue"
},
  "geometry": {"coordinates":[8.5607004166,47.3628501892],"type":"Point"}
}