{
  "type": "Feature",
  "properties": {
    "iso:country":"CH",
    "sg:address":"Manessestrasse 88",
    "sg:city":"Z\u00fcrich",
    "sg:orig_category":"Detailhandel mit Fleisch U Fleischwaren",
    "sg:phone":"+41 14620090",
    "sg:postcode":"8045",
    "sg:province":"Z\u00fcrich",
    "wof:name":"Metzgerei Keller Ag",
    "wof:placetype":"venue"
},
  "geometry": {"coordinates":[8.5217103958,47.3650016785],"type":"Point"}
}