{
  "type": "Feature",
  "properties": {
    "iso:country":"CH",
    "sg:address":"Vordergasse 60 8200 Schaffhausen. Postfach",
    "sg:city":"Schaffhausen",
    "sg:orig_category":"Massagestudios Schlankheitsinstitute",
    "sg:phone":"+41 52 625 78 01",
    "sg:postcode":"8200",
    "sg:province":"Schaffhausen",
    "wof:name":"Formola Form & Leichtigkeit Mohler Brigitta Wellness",
    "wof:placetype":"venue"
},
  "geometry": {"coordinates":[8.6350822449,47.6964225769],"type":"Point"}
}