{
  "type": "Feature",
  "properties": {
    "iso:country":"CH",
    "sg:address":"Rue De La Gare 5",
    "sg:city":"Villeret",
    "sg:orig_category":"Allgemeinbildende weiterf\u00fchrende Schulen",
    "sg:phone":"+41 32 941 50 40",
    "sg:postcode":"2613",
    "sg:province":"Bern",
    "wof:name":"Centre De Cours Villeret Zbinden Reto H.",
    "wof:placetype":"venue"
},
  "geometry": {"coordinates":[7.018202,47.158825],"type":"Point"}
}