{
  "type": "Feature",
  "properties": {
    "iso:country":"CH",
    "sg:address":"Rue Du Milieu 4",
    "sg:city":"Alle",
    "sg:orig_category":"Sportvereine Turnen",
    "sg:phone":"+41 32 471 16 72",
    "sg:postcode":"2942",
    "sg:province":"Jura",
    "wof:name":"St\u00e9 De Gymnastique D'alle",
    "wof:placetype":"venue"
},
  "geometry": {"coordinates":[7.1293969154,47.4252815247],"type":"Point"}
}