{
  "type": "Feature",
  "properties": {
    "iso:country":"CH",
    "sg:address":"Lindenb\u00fchl 243",
    "sg:city":"Trogen",
    "sg:orig_category":"Zimmerei, Ingenieurholzbau",
    "sg:phone":"+41 79 350 83 03",
    "sg:postcode":"9043",
    "sg:province":"Appenzell Ausserrhoden",
    "wof:name":"Ulrich Zbinden Holzbau",
    "wof:placetype":"venue"
},
  "geometry": {"coordinates":[7.4069471359,46.7818603516],"type":"Point"}
}