{
  "type": "Feature",
  "properties": {
    "iso:country":"CH",
    "sg:address":"Sch\u00fctzenmattstrasse 44",
    "sg:city":"Basel",
    "sg:orig_category":"Arztpraxen",
    "sg:phone":"+41 62 771 09 17",
    "sg:postcode":"4051",
    "sg:province":"Basel-Stadt",
    "wof:name":"Dr.med.daniel Urech Spezialarzt Fmh",
    "wof:placetype":"venue"
},
  "geometry": {"coordinates":[8.184031,47.25071],"type":"Point"}
}