{
  "type": "Feature",
  "properties": {
    "iso:country":"CH",
    "sg:address":"Bernstrasse 98",
    "sg:city":"Stettlen",
    "sg:orig_category":"Drogerien Sonstiger Fachdetailhandel mit Nahrungsmitteln, Getr\u00e4nken U Tabak in Verkaufsr\u00e4umen",
    "sg:phone":"+41 31 931 41 55",
    "sg:postcode":"3066",
    "sg:province":"Bern",
    "wof:name":"Beat & Therese Liechti Drogerie Parfumerie Reformhaus",
    "wof:placetype":"venue"
},
  "geometry": {"coordinates":[7.5243740082,46.9584007263],"type":"Point"}
}