{
  "type": "Feature",
  "properties": {
    "iso:country":"CH",
    "sg:address":"Kreuzackerweg 7",
    "sg:city":"Bottmingen",
    "sg:orig_category":"Geb\u00e4ude, Wohnungsreinigung Reinigungsgewerbe",
    "sg:phone":"+41 61 422 04 44",
    "sg:postcode":"4103",
    "sg:province":"Basel-Landschaft",
    "wof:name":"Sch\u00e4fer Reinigungen Gmbh",
    "wof:placetype":"venue"
},
  "geometry": {"coordinates":[7.567150116,47.5259666443],"type":"Point"}
}