{
  "type": "Feature",
  "properties": {
    "iso:country":"CH",
    "sg:address":"Oberr\u00fctelistrasse 13",
    "sg:city":"Mollis",
    "sg:orig_category":"Unclassifiable Establishments",
    "sg:postcode":"8753",
    "sg:province":"Glarus",
    "wof:name":"Wenet Textilien Ag",
    "wof:placetype":"venue"
},
  "geometry": {"coordinates":[9.0696020126,47.0913581848],"type":"Point"}
}