{
  "type": "Feature",
  "properties": {
    "iso:country":"CH",
    "sg:address":"Reussgasse 12",
    "sg:city":"Seon",
    "sg:orig_category":"Zimmerei, Dachdeckerei, Bauspenglerei U Abdichtung",
    "sg:postcode":"5703",
    "sg:province":"Aargau",
    "wof:name":"Gebr. Sommerhalder Ag, Zimmerei & Schreinerei",
    "wof:placetype":"venue"
},
  "geometry": {"coordinates":[8.161611557,47.3452033997],"type":"Point"}
}