{
  "type": "Feature",
  "properties": {
    "iso:country":"CH",
    "sg:address":"Hirschengraben 19",
    "sg:city":"Luzern",
    "sg:orig_category":"Schl\u00fcsselservice",
    "sg:phone":"+41 41 210 89 84",
    "sg:postcode":"6003",
    "sg:province":"Luzern",
    "wof:name":"Zaugg & Co Schl\u00fcssel-service",
    "wof:placetype":"venue"
},
  "geometry": {"coordinates":[8.3028335571,47.0488433838],"type":"Point"}
}