{
  "type": "Feature",
  "properties": {
    "iso:country":"CH",
    "sg:address":"St. Gallerstrasse 31 9400 Rorschach. Postfach",
    "sg:city":"Heerbrugg",
    "sg:orig_category":"RESTAURANTS: TEA-ROOMS",
    "sg:postcode":"9435",
    "sg:province":"St. Gallen",
    "wof:name":"Pizzeria Don Camillo Bulun",
    "wof:placetype":"venue"
},
  "geometry": {"coordinates":[9.484172821,47.4781913757],"type":"Point"}
}