{
  "type": "Feature",
  "properties": {
    "iso:country":"CH",
    "sg:address":"Zofingerstrasse 3",
    "sg:city":"Strengelbach",
    "sg:classifiers":[
        {
            "category":"Government",
            "subcategory":"Post Office",
            "type":"Public Place"
        }
    ],
    "sg:phone":"+41 41 375 70 50",
    "sg:postcode":"4802",
    "sg:province":"Aargau",
    "sg:tags":[
        "caf\u00e9s",
        "tea-rooms"
    ],
    "wof:name":"Tea-room Kreyenb\u00fchl",
    "wof:placetype":"venue"
},
  "geometry": {"coordinates":[8.3446512222,47.0547943115],"type":"Point"}
}