{
  "type": "Feature",
  "properties": {
    "addr:full":"Zone Industrielle Les Graveys Daillens Vaud 1306",
    "addr:postcode":"1306",
    "addr:street":"Zone Industrielle Les Graveys",
    "iso:country":"CH",
    "sg:address":"Zone Industrielle Les Graveys",
    "sg:city":"Daillens",
    "sg:orig_category":"Datenverarbeitungsdienste",
    "sg:phone":"+41 21 862 25 25",
    "sg:postcode":"1306",
    "sg:province":"Vaud",
    "wof:name":"Fiege Goth Romandie Sa",
    "wof:placetype":"venue"
},
  "geometry": {"coordinates":[6.548685,46.620605],"type":"Point"}
}