{
  "type": "Feature",
  "properties": {
    "iso:country":"CH",
    "sg:address":"Via Pugnetti",
    "sg:city":"Tesserete",
    "sg:orig_category":"Elektroinstallation",
    "sg:phone":"+41 91 943 22 23",
    "sg:postcode":"6950",
    "sg:province":"Ticino",
    "wof:name":"Bruno Benagli",
    "wof:placetype":"venue"
},
  "geometry": {"coordinates":[8.9659252167,46.0682296753],"type":"Point"}
}