{
  "type": "Feature",
  "properties": {
    "addr:full":"Hauptstrasse 23 Kreuzlingen Thurgau 8280",
    "addr:housenumber":"23",
    "addr:postcode":"8280",
    "addr:street":"Hauptstrasse",
    "iso:country":"CH",
    "sg:address":"Hauptstrasse 23",
    "sg:city":"Kreuzlingen",
    "sg:classifiers":[
        {
            "category":"Bars & Pubs",
            "type":"Food & Drink"
        }
    ],
    "sg:phone":"+41 71 672 76 91",
    "sg:postcode":"8280",
    "sg:province":"Thurgau",
    "wof:name":"Sababar",
    "wof:placetype":"venue"
},
  "geometry": {"coordinates":[9.173964,47.652657],"type":"Point"}
}