{
  "type": "Feature",
  "properties": {
    "iso:country":"CH",
    "sg:address":"6014",
    "sg:city":"Littau",
    "sg:classifiers":[
        {
            "category":"Travel",
            "subcategory":"Hotels & Motels",
            "type":"Entertainment"
        }
    ],
    "sg:phone":"+41 61 751 17 72",
    "sg:postcode":"6014",
    "sg:province":"Luzern",
    "sg:tags":[
        "hotels",
        "mit",
        "restaurant"
    ],
    "wof:name":"Achermann, Margrith",
    "wof:placetype":"venue"
},
  "geometry": {"coordinates":[7.5978980064,47.466594696],"type":"Point"}
}