{
  "type": "Feature",
  "properties": {
    "iso:country":"CH",
    "sg:address":"La Coudre",
    "sg:city":"Mont-la-ville",
    "sg:orig_category":"Tierarztpraxis",
    "sg:phone":"+41 21 697 07 15",
    "sg:postcode":"1328",
    "wof:name":"Dr M\u00e9d. V\u00e9t. Pierre Nidegger M\u00e9decin V\u00e9t\u00e9rinaire",
    "wof:placetype":"venue"
},
  "geometry": {"coordinates":[6.5552539825,46.5081481934],"type":"Point"}
}