{
  "type": "Feature",
  "properties": {
    "iso:country":"CH",
    "sg:address":"Seestrasse 2 6373 Ennetb\u00fcrgen. Postfach 260",
    "sg:city":"Ennetb\u00fcrgen",
    "sg:orig_category":"Schiffsbau ohne Boots U Yachtbau",
    "sg:phone":"+41 41 620 15 71",
    "sg:postcode":"6373",
    "sg:province":"Nidwalden",
    "wof:name":"Infanger Propeller Ag",
    "wof:placetype":"venue"
},
  "geometry": {"coordinates":[8.4172925949,46.986782074],"type":"Point"}
}