{
  "type": "Feature",
  "properties": {
    "iso:country":"CH",
    "sg:address":"Faggi Via 8",
    "sg:city":"Lugano",
    "sg:orig_category":"Interessenvertretungen",
    "sg:phone":"+41 91 971 26 62",
    "sg:postcode":"6900",
    "sg:province":"Ticino",
    "wof:name":"Associazione Alzheimer Svizzera, Sezione Ticino",
    "wof:placetype":"venue"
},
  "geometry": {"coordinates":[8.9513053894,46.0029754639],"type":"Point"}
}