{
  "type": "Feature",
  "properties": {
    "iso:country":"CH",
    "sg:address":"Unterdorf 6",
    "sg:city":"Gretzenbach",
    "sg:orig_category":"Instandhaltung U Reparatur von Automobilen",
    "sg:postcode":"5014",
    "sg:province":"Solothurn",
    "wof:name":"Garage Kirchhofer",
    "wof:placetype":"venue"
},
  "geometry": {"coordinates":[7.992623806,47.3597297668],"type":"Point"}
}