{
  "type": "Feature",
  "properties": {
    "iso:country":"CH",
    "sg:address":"St\u00e4dtli",
    "sg:city":"Churwalden",
    "sg:orig_category":"Verarbeitung von Milch Verwertung von Milch",
    "sg:postcode":"7075",
    "sg:province":"Graubunden",
    "wof:name":"Milchgenossenschaft Churwalden-parpan",
    "wof:placetype":"venue"
},
  "geometry": {"coordinates":[9.5535573959,46.7707824707],"type":"Point"}
}