{
  "type": "Feature",
  "properties": {
    "iso:country":"CH",
    "sg:address":"Grand'rue 12",
    "sg:city":"Lucens",
    "sg:orig_category":"Detailhandel mit Waren verschiedener Art, Hauptrichtung Nahrungsmittel",
    "sg:phone":"+41 21 906 92 57",
    "sg:postcode":"1522",
    "sg:province":"Vaud",
    "wof:name":"Raoul Vorlet Denner-satellite",
    "wof:placetype":"venue"
},
  "geometry": {"coordinates":[6.8399448395,46.709236145],"type":"Point"}
}