{
  "type": "Feature",
  "properties": {
    "iso:country":"CH",
    "sg:address":"M\u00f6etscheweg 1",
    "sg:city":"Marthalen",
    "sg:orig_category":"Zimmerei, Dachdeckerei, Bauspenglerei U Abdichtung",
    "sg:postcode":"8460",
    "sg:province":"Z\u00fcrich",
    "wof:name":"Keller Werner Zimmerei",
    "wof:placetype":"venue"
},
  "geometry": {"coordinates":[8.6536626816,47.6262359619],"type":"Point"}
}