{
  "type": "Feature",
  "properties": {
    "iso:country":"CH",
    "sg:address":"Rossackerstrasse 124 8047 Z\u00fcrich. Postfach",
    "sg:city":"Z\u00fcrich",
    "sg:orig_category":"Elektroinstallation",
    "sg:postcode":"8047",
    "sg:province":"Z\u00fcrich",
    "wof:name":"Bugini Und Niedermann, Renovacom",
    "wof:placetype":"venue"
},
  "geometry": {"coordinates":[8.4882717133,47.370174408],"type":"Point"}
}