{
  "type": "Feature",
  "properties": {
    "iso:country":"CH",
    "sg:address":"Rue De L'ancienne Poste 4",
    "sg:city":"Yverdon-les-bains",
    "sg:orig_category":"Herstellung von medizinischen U chirurgischen Ger\u00e4ten sowie orthop\u00e4dischen Vorrichtungen Zahntechnis",
    "sg:phone":"+41 24 425 52 21",
    "sg:postcode":"1400",
    "sg:province":"Vaud",
    "wof:name":"Thierry Roland",
    "wof:placetype":"venue"
},
  "geometry": {"coordinates":[6.6390161514,46.7801094055],"type":"Point"}
}