{
  "type": "Feature",
  "properties": {
    "iso:country":"CH",
    "sg:address":"Gartenweg 2",
    "sg:city":"K\u00fcnten",
    "sg:classifiers":[
        {
            "category":"Banks & Credit Unions",
            "subcategory":"Investment Brokerage",
            "type":"Services"
        }
    ],
    "sg:phone":"+41 56 496 38 33",
    "sg:postcode":"5444",
    "sg:province":"Aargau",
    "sg:tags":[
        "absorption",
        "refrigerator"
    ],
    "wof:name":"Reap Ag",
    "wof:placetype":"venue"
},
  "geometry": {"coordinates":[8.334267,47.390087],"type":"Point"}
}