{
  "type": "Feature",
  "properties": {
    "iso:country":"CH",
    "sg:address":"1417",
    "sg:city":"Essertines-yverdon",
    "sg:orig_category":"Instandhaltung U Reparatur von Automobilen",
    "sg:phone":"+41 71 945 80 18",
    "sg:postcode":"1417",
    "sg:province":"Vaud",
    "wof:name":"Pcz Pneu Center Gmbh",
    "wof:placetype":"venue"
},
  "geometry": {"coordinates":[9.1147146225,47.4718780518],"type":"Point"}
}