{
  "type": "Feature",
  "properties": {
    "iso:country":"CH",
    "sg:address":"Schwarzbachstr. 18",
    "sg:city":"St\u00e4fa",
    "sg:orig_category":"Werbung",
    "sg:postcode":"8712",
    "sg:province":"Z\u00fcrich",
    "wof:name":"Sigrist Martin",
    "wof:placetype":"venue"
},
  "geometry": {"coordinates":[8.759396553,47.2396888733],"type":"Point"}
}