{
  "type": "Feature",
  "properties": {
    "iso:country":"CH",
    "sg:address":"Seefeldstrasse 199",
    "sg:city":"Z\u00fcrich",
    "sg:orig_category":"Unclassifiable Establishments",
    "sg:postcode":"8008",
    "sg:province":"Z\u00fcrich",
    "wof:name":"Coop Z\u00fcrich",
    "wof:placetype":"venue"
},
  "geometry": {"coordinates":[8.5588235855,47.3533554077],"type":"Point"}
}