{
  "type": "Feature",
  "properties": {
    "iso:country":"CH",
    "sg:address":"B\u00fcndtenweg 24",
    "sg:city":"Hersberg",
    "sg:orig_category":"Grosshandel mit Getr\u00e4nken",
    "sg:phone":"+41 61 923 21 31",
    "sg:postcode":"4423",
    "sg:province":"Basel-Landschaft",
    "wof:name":"Liptay & Partner Gmbh",
    "wof:placetype":"venue"
},
  "geometry": {"coordinates":[7.7851371765,47.4939041138],"type":"Point"}
}