{
  "type": "Feature",
  "properties": {
    "iso:country":"CH",
    "sg:address":"H\u00e4ngeli 261",
    "sg:city":"Uetendorf",
    "sg:orig_category":"Detailhandel mit Teppichen Verlegen von Fussboden",
    "sg:phone":"+41 33 345 22 78",
    "sg:postcode":"3661",
    "sg:province":"Bern",
    "wof:name":"Fritz Stalder Teppiche & Bodenbel\u00e4ge",
    "wof:placetype":"venue"
},
  "geometry": {"coordinates":[7.5654602051,46.7768440247],"type":"Point"}
}