{
  "type": "Feature",
  "properties": {
    "iso:country":"CH",
    "sg:address":"1967 Bramois Case Postale 48",
    "sg:city":"Bramois",
    "sg:orig_category":"Bauschreinerei Zimmerei, Ingenieurholzbau",
    "sg:phone":"+41 26 495 15 78",
    "sg:postcode":"1967",
    "sg:province":"Valais",
    "wof:name":"August Br\u00fcgger Chaletbau & K\u00fcchenbau",
    "wof:placetype":"venue"
},
  "geometry": {"coordinates":[7.257298,46.822872],"type":"Point"}
}