{
  "type": "Feature",
  "properties": {
    "iso:country":"CH",
    "sg:address":"Route Du Rawyl",
    "sg:city":"Montana-vermala",
    "sg:orig_category":"Detailhandel mit Beleuchtungs U Haushaltsgegenst\u00e4nden Detailhandel mit elektrischen Haushalts, Radio",
    "sg:phone":"+41 27 481 56 38",
    "sg:postcode":"3962",
    "wof:name":"Jean-daniel Rey Magasin Electro-m\u00e9nager",
    "wof:placetype":"venue"
},
  "geometry": {"coordinates":[7.492434,46.314419],"type":"Point"}
}