{
  "type": "Feature",
  "properties": {
    "iso:country":"CH",
    "sg:address":"Route De Lausanne 25",
    "sg:city":"Yverdon-les-bains",
    "sg:classifiers":[
        {
            "category":"Manufacturing",
            "subcategory":"Motor Vehicles & Parts",
            "type":"Manufacturing & Wholesale Goods"
        }
    ],
    "sg:phone":"+41 24 425 01 46",
    "sg:postcode":"1400",
    "sg:province":"Vaud",
    "sg:tags":[
        "precision",
        "mechanic"
    ],
    "wof:name":"Socodim S.a.",
    "wof:placetype":"venue"
},
  "geometry": {"coordinates":[6.647914,46.762287],"type":"Point"}
}