{
  "type": "Feature",
  "properties": {
    "iso:country":"CH",
    "sg:address":"Bleicherweg 20 8002 Z\u00fcrich. Postfach",
    "sg:city":"Z\u00fcrich",
    "sg:orig_category":"Wohnheime",
    "sg:postcode":"8001",
    "sg:province":"Z\u00fcrich",
    "wof:name":"Jaeger-stiftung Fritz Finanz. Unterst\u00fctzung K\u00f6rperlich U. Geistig Behinderter Kinder",
    "wof:placetype":"venue"
},
  "geometry": {"coordinates":[8.5362796783,47.3683013916],"type":"Point"}
}