{
  "type": "Feature",
  "properties": {
    "iso:country":"CH",
    "sg:address":"Wiesenstrasse 17 4900 Langenthal. Postfach",
    "sg:city":"Langenthal",
    "sg:orig_category":"Herstellung von elektrischen Lampen U Leuchten",
    "sg:postcode":"4900",
    "sg:province":"Bern",
    "wof:name":"X-light & Sound Veranstaltungstechnik Gmbh Beleuchtungs, Beschallungs- U. B\u00fchnentechnik; Vermietung, Verkauf. Fixinstallationen In Clubs Usw",
    "wof:placetype":"venue"
},
  "geometry": {"coordinates":[7.786506176,47.2121658325],"type":"Point"}
}