{
  "type": "Feature",
  "properties": {
    "iso:country":"CH",
    "sg:address":"Dorfstrasse 57",
    "sg:city":"G\u00fcmligen",
    "sg:orig_category":"Grosshandel mit chemischen Erzeugnissen Herstellung von Arbeits U Berufsbekleidung",
    "sg:phone":"+41 31 952 76 86",
    "sg:postcode":"3073",
    "sg:province":"Bern",
    "wof:name":"Inter-cb Gmbh",
    "wof:placetype":"venue"
},
  "geometry": {"coordinates":[7.5098390579,46.9353294373],"type":"Point"}
}