{
  "type": "Feature",
  "properties": {
    "iso:country":"CH",
    "sg:address":"Bahnhofstrasse 7",
    "sg:city":"Kilchberg",
    "sg:classifiers":[
        {
            "category":"Banks & Credit Unions",
            "subcategory":"Bank",
            "type":"Services"
        }
    ],
    "sg:phone":"+41 17155177",
    "sg:postcode":"8802",
    "sg:province":"Z\u00fcrich",
    "wof:name":"Sparkasse Des Wahlkreises Thalwil",
    "wof:placetype":"venue"
},
  "geometry": {"coordinates":[8.54876,47.323471],"type":"Point"}
}