{
  "type": "Feature",
  "properties": {
    "iso:country":"CH",
    "sg:address":"Neustadt 67",
    "sg:city":"Schaffhausen",
    "sg:orig_category":"Bastel- and Hobbyartikel Detailhandel",
    "sg:phone":"+41 52 624 96 94",
    "sg:postcode":"8200",
    "sg:province":"Schaffhausen",
    "wof:name":"Catharina Jost Quilt-& Patchworkladen",
    "wof:placetype":"venue"
},
  "geometry": {"coordinates":[8.632098,47.695679],"type":"Point"}
}