{
  "type": "Feature",
  "properties": {
    "iso:country":"CH",
    "sg:address":"Schaffhauserstrasse 352",
    "sg:city":"Z\u00fcrich",
    "sg:orig_category":"Rechtsberatung Wirtschaftspr\u00fcfung, Steuerberatung U Treuhand",
    "sg:phone":"+41 13126323",
    "sg:postcode":"8050",
    "sg:province":"Z\u00fcrich",
    "wof:name":"Borsoi Suter Weck & Partner Steuern Recht Treuhand Ag",
    "wof:placetype":"venue"
},
  "geometry": {"coordinates":[8.5464477539,47.4096717834],"type":"Point"}
}