{
  "type": "Feature",
  "properties": {
    "iso:country":"CH",
    "sg:address":"Riedstrasse 9",
    "sg:city":"Cham",
    "sg:orig_category":"Grosshandel mit Maschinen U Ausr\u00fcstungen Herstellung von Werkzeugmaschinen",
    "sg:phone":"+41 17372191",
    "sg:postcode":"6330",
    "sg:province":"Zug",
    "wof:name":"Schwab Paul, Peco-schweisstechnik",
    "wof:placetype":"venue"
},
  "geometry": {"coordinates":[8.4337415695,47.3576278687],"type":"Point"}
}