{
  "type": "Feature",
  "properties": {
    "iso:country":"CH",
    "sg:address":"Route De Denges 6 1027 Lonay Case Postale",
    "sg:city":"Lonay",
    "sg:orig_category":"Grosshandel mit Eisenwaren sowie Installationsbedarf f\u00fcr Gas, Wasser U Heizung Grosshandel mit elekt",
    "sg:phone":"+41 22 809 10 90",
    "sg:postcode":"1027",
    "sg:province":"Vaud",
    "wof:name":"K\u00fcleg Sa",
    "wof:placetype":"venue"
},
  "geometry": {"coordinates":[6.1425008774,46.1933517456],"type":"Point"}
}