{
  "type": "Feature",
  "properties": {
    "iso:country":"CH",
    "sg:address":"Dorfstrasse 69",
    "sg:city":"Altavilla",
    "sg:orig_category":"Sonstige Aktivit\u00e4ten der nicht-\u00e4rztlichen Medizinalberufe",
    "sg:phone":"+41 26 670 37 17",
    "sg:postcode":"3280",
    "sg:province":"Fribourg",
    "wof:name":"Katharina Aebersold Kinesiologie & Massagen",
    "wof:placetype":"venue"
},
  "geometry": {"coordinates":[7.1191439629,46.9292831421],"type":"Point"}
}