{
  "type": "Feature",
  "properties": {
    "iso:country":"CH",
    "sg:address":"Aarb\u00fchlstrasse 19",
    "sg:city":"Wabern",
    "sg:orig_category":"Allgemeiner Hochbau Strassenbau",
    "sg:phone":"+41 31 961 12 76",
    "sg:postcode":"3084",
    "sg:province":"Bern",
    "wof:name":"Werner Schmid Ag Bauunternehmung",
    "wof:placetype":"venue"
},
  "geometry": {"coordinates":[7.45084,46.929035],"type":"Point"}
}