{
  "type": "Feature",
  "properties": {
    "iso:country":"CH",
    "sg:address":"Alpenstrasse 30a",
    "sg:city":"Grenchen",
    "sg:orig_category":"Herstellung von Uhren",
    "sg:postcode":"2540",
    "sg:province":"Solothurn",
    "wof:name":"Termina Ag",
    "wof:placetype":"venue"
},
  "geometry": {"coordinates":[7.3970160484,47.1987953186],"type":"Point"}
}