{
  "type": "Feature",
  "properties": {
    "iso:country":"CH",
    "sg:address":"Avenue Bergi\u00e8res 22",
    "sg:city":"Lausanne",
    "sg:orig_category":"Detailhandel mit Radio U Fernsehger\u00e4ten Instandhaltung U Reparatur von Automobilen",
    "sg:phone":"+41 79 449 18 19",
    "sg:postcode":"1004",
    "sg:province":"Vaud",
    "wof:name":"Jean-marie Monnet",
    "wof:placetype":"venue"
},
  "geometry": {"coordinates":[6.621175766,46.5293807983],"type":"Point"}
}