{
  "type": "Feature",
  "properties": {
    "iso:country":"CH",
    "sg:address":"Suot Chesas Via 6 7512 Champf\u00e8r. Postfach",
    "sg:city":"Champf\u00e8r",
    "sg:orig_category":"Non-Classified Establishments",
    "sg:phone":"+41 81 833 77 14",
    "sg:postcode":"7512",
    "sg:province":"Graubunden",
    "wof:name":"The St. Moritz Experience Ag",
    "wof:placetype":"venue"
},
  "geometry": {"coordinates":[9.8130102158,46.4789237976],"type":"Point"}
}