{
  "type": "Feature",
  "properties": {
    "iso:country":"CH",
    "sg:address":"2027",
    "sg:city":"Montalchez",
    "sg:orig_category":"Detailhandel mit Milcherzeugnissen U Eiern Verarbeitung von Milch",
    "sg:postcode":"2027",
    "sg:province":"Neuch\u00e2tel",
    "wof:name":"Soci\u00e9t\u00e9 De Laiterie",
    "wof:placetype":"venue"
},
  "geometry": {"coordinates":[6.7449741364,46.897354126],"type":"Point"}
}