{
  "type": "Feature",
  "properties": {
    "iso:country":"CH",
    "sg:address":"Vorstadtstrasse 23",
    "sg:city":"Gr\u00e4nichen",
    "sg:orig_category":"Detailhandel mit Blumen U Pflanzen",
    "sg:phone":"+41 62 842 26 85",
    "sg:postcode":"5722",
    "sg:province":"Aargau",
    "wof:name":"Createam Barth & Co Dekorationen Blumen",
    "wof:placetype":"venue"
},
  "geometry": {"coordinates":[8.099311,47.36264],"type":"Point"}
}