{
  "type": "Feature",
  "properties": {
    "iso:country":"CH",
    "sg:address":"Rue Des Cond\u00e9mines 19-21",
    "sg:city":"Yverdon-les-bains",
    "sg:classifiers":[
        {
            "category":"Home & Garden",
            "subcategory":"Mobile Homes",
            "type":"Retail Goods"
        }
    ],
    "sg:phone":"+41 24 426 21 21",
    "sg:postcode":"1400",
    "sg:province":"Vaud",
    "sg:tags":[
        "awning",
        "outdoor",
        "marquee"
    ],
    "wof:name":"Independservice",
    "wof:placetype":"venue"
},
  "geometry": {"coordinates":[6.6523928642,46.766960144],"type":"Point"}
}