{
  "type": "Feature",
  "properties": {
    "iso:country":"CH",
    "sg:address":"Marktplatz 10",
    "sg:city":"Lyss",
    "sg:orig_category":"Finanzierungsinstitutionen",
    "sg:phone":"+41 32 385 15 22",
    "sg:postcode":"3250",
    "sg:province":"Bern",
    "wof:name":"Bgv Beratungsservice F\u00fcr Geld Und Versicherungsfragen, Erwin L\u00fcthi",
    "wof:placetype":"venue"
},
  "geometry": {"coordinates":[7.3054118156,47.0734863281],"type":"Point"}
}