{
  "type": "Feature",
  "properties": {
    "iso:country":"CH",
    "sg:address":"General Guisan-strasse 10",
    "sg:city":"Zofingen",
    "sg:orig_category":"Jugendherbergen U H\u00fctten",
    "sg:phone":"+41 62 751 64 98",
    "sg:postcode":"4800",
    "sg:province":"Aargau",
    "wof:name":"Jugendherberge Sjh",
    "wof:placetype":"venue"
},
  "geometry": {"coordinates":[7.9483847618,47.2879066467],"type":"Point"}
}