{
  "type": "Feature",
  "properties": {
    "iso:country":"CH",
    "sg:address":"Passh\u00f6he Hulftegg",
    "sg:city":"M\u00fchlr\u00fcti",
    "sg:classifiers":[
        {
            "category":"Restaurant",
            "type":"Food & Drink"
        }
    ],
    "sg:phone":"+41 33 681 14 81",
    "sg:postcode":"9613",
    "sg:province":"St. Gallen",
    "wof:name":"Panoramarestaurant Stockhorn",
    "wof:placetype":"venue"
},
  "geometry": {"coordinates":[7.8617801666,49.1125106812],"type":"Point"}
}