{
  "type": "Feature",
  "properties": {
    "iso:country":"CH",
    "sg:address":"Claridenweg 10",
    "sg:city":"Volketswil",
    "sg:orig_category":"Reiseb\u00fcros U Reiseveranstalter",
    "sg:phone":"+41 13460634",
    "sg:postcode":"8604",
    "sg:province":"Z\u00fcrich",
    "wof:name":"Efes Reisen Sansal Caglar",
    "wof:placetype":"venue"
},
  "geometry": {"coordinates":[8.6767177582,47.3903694153],"type":"Point"}
}