{
  "type": "Feature",
  "properties": {
    "iso:country":"CH",
    "sg:address":"Les Condemennes",
    "sg:city":"Rebeuvelier",
    "sg:orig_category":"Unclassifiable Establishments",
    "sg:postcode":"2832",
    "sg:province":"Jura",
    "wof:name":"Accin S\u00e0rl",
    "wof:placetype":"venue"
},
  "geometry": {"coordinates":[7.41685009,47.3270111084],"type":"Point"}
}