{
  "type": "Feature",
  "properties": {
    "iso:country":"CH",
    "sg:address":"Sch\u00f6neggrain 18 2540 Grenchen. Postfach 21",
    "sg:city":"Grenchen",
    "sg:orig_category":"Kauf U Verkauf von Immobilien auf eigene Rechnung",
    "sg:phone":"+41 32 652 70 60",
    "sg:postcode":"2540",
    "sg:province":"Solothurn",
    "wof:name":"Wikim Ag",
    "wof:placetype":"venue"
},
  "geometry": {"coordinates":[7.394906044,47.2007369995],"type":"Point"}
}