{
  "type": "Feature",
  "properties": {
    "iso:country":"CH",
    "sg:address":"Rue Charles-clos Olsommer",
    "sg:city":"Veyras",
    "sg:orig_category":"Landesverteidigung, Sozialversicherung \u00d6ffentliche Verwaltung",
    "sg:phone":"+41 27 455 21 16",
    "sg:postcode":"3968",
    "sg:province":"Valais",
    "wof:name":"Centre De Protection Civile",
    "wof:placetype":"venue"
},
  "geometry": {"coordinates":[7.5368747711,46.3019371033],"type":"Point"}
}