{
  "type": "Feature",
  "properties": {
    "iso:country":"CH",
    "sg:address":"Zuchwilerstrasse 41",
    "sg:city":"Solothurn",
    "sg:orig_category":"Detailhandel mit Waren verschiedener Art, Hauptrichtung Nahrungsmittel",
    "sg:phone":"+41 81 844 13 93",
    "sg:postcode":"4500",
    "sg:province":"Solothurn",
    "wof:name":"Dina Giumelli Coloniali",
    "wof:placetype":"venue"
},
  "geometry": {"coordinates":[10.0723896027,46.3089790344],"type":"Point"}
}