{
  "type": "Feature",
  "properties": {
    "iso:country":"CH",
    "sg:address":"Dorfstrasse 49",
    "sg:city":"Oberengstringen",
    "sg:classifiers":[
        {
            "category":"Restaurant",
            "type":"Food & Drink"
        }
    ],
    "sg:phone":"+41 17504009",
    "sg:postcode":"8102",
    "sg:province":"Z\u00fcrich",
    "wof:name":"Restaurant Freihof",
    "wof:placetype":"venue"
},
  "geometry": {"coordinates":[8.4605979919,47.4085845947],"type":"Point"}
}