{
  "type": "Feature",
  "properties": {
    "iso:country":"CH",
    "sg:address":"Birsmattstrasse 30",
    "sg:city":"Therwil",
    "sg:orig_category":"Aktivit\u00e4ten der Krankenschwestern U Hebammen, Hauspflege Organisationen des Gesundheitswesen",
    "sg:phone":"+41 71 766 15 87",
    "sg:postcode":"4106",
    "sg:province":"Basel-Landschaft",
    "wof:name":"Spitex Krankenpflege Frau Claudia Hanimann",
    "wof:placetype":"venue"
},
  "geometry": {"coordinates":[9.517035,47.27721],"type":"Point"}
}