{
  "type": "Feature",
  "properties": {
    "iso:country":"CH",
    "sg:address":"6594",
    "sg:city":"Contone",
    "sg:orig_category":"Sportvereine Renn-& Reitsport",
    "sg:postcode":"6594",
    "sg:province":"Ticino",
    "wof:name":"Freizeitreiter-verein Thurgau",
    "wof:placetype":"venue"
},
  "geometry": {"coordinates":[8.6150074005,47.5579376221],"type":"Point"}
}