{
  "type": "Feature",
  "properties": {
    "iso:country":"CH",
    "sg:address":"7317",
    "sg:city":"Balen-gassaura",
    "sg:orig_category":"Sportvereine Sch\u00fctzen",
    "sg:phone":"+41 19543213",
    "sg:postcode":"7317",
    "sg:province":"St. Gallen",
    "wof:name":"Sch\u00fctzenverein",
    "wof:placetype":"venue"
},
  "geometry": {"coordinates":[9.482919693,46.9835891724],"type":"Point"}
}