{
  "type": "Feature",
  "properties": {
    "iso:country":"CH",
    "sg:address":"Schlossgasse 14 8003 Z\u00fcrich. Postfach 632",
    "sg:city":"Z\u00fcrich",
    "sg:orig_category":"Detektivb\u00fcros U \u00dcberwachung",
    "sg:phone":"+41 12015959",
    "sg:postcode":"8027",
    "sg:province":"Z\u00fcrich",
    "wof:name":"Berufsdetektei Vetter/ondiek Gmbh",
    "wof:placetype":"venue"
},
  "geometry": {"coordinates":[8.5197038651,47.3691062927],"type":"Point"}
}