{
  "type": "Feature",
  "properties": {
    "iso:country":"CH",
    "sg:address":"L\u00e9ch\u00e8re Rue De La 1630 Bulle Case Postale 642",
    "sg:city":"Bulle",
    "sg:orig_category":"Pulvermetallurgie Schmieden, Pressen, Stanzen U Profilwalzen von Metallen",
    "sg:phone":"+41 26 912 71 20",
    "sg:postcode":"1630",
    "sg:province":"Fribourg",
    "wof:name":"Ateliers Firmann Sa, Bulle Atelier De D\u00e9coupage, D'emboutissage Et De Construction M\u00e9tallique",
    "wof:placetype":"venue"
},
  "geometry": {"coordinates":[7.0573811531,46.6186027527],"type":"Point"}
}