{
  "type": "Feature",
  "properties": {
    "iso:country":"CH",
    "sg:address":"Maulbeerstrasse 13",
    "sg:city":"Basel",
    "sg:orig_category":"Herstellung von sonstigen elektrischen Ausr\u00fcstungen",
    "sg:phone":"+41 19502744",
    "sg:postcode":"4058",
    "sg:province":"Basel-Stadt",
    "wof:name":"Sematic Ag",
    "wof:placetype":"venue"
},
  "geometry": {"coordinates":[8.7798719406,47.3684272766],"type":"Point"}
}