{
  "type": "Feature",
  "properties": {
    "iso:country":"CH",
    "sg:address":"Bual",
    "sg:city":"Vella",
    "sg:orig_category":"Sonstige mit der Informatik verbundene T\u00e4tigkeiten",
    "sg:postcode":"7144",
    "sg:province":"Graubunden",
    "wof:name":"Cmc Caviezel Management & Consulting",
    "wof:placetype":"venue"
},
  "geometry": {"coordinates":[9.1706008911,46.7152099609],"type":"Point"}
}