{
  "type": "Feature",
  "properties": {
    "iso:country":"CH",
    "sg:address":"Paradiesstrasse 5",
    "sg:city":"Brugg",
    "sg:classifiers":[
        {
            "category":"Structure",
            "subcategory":"Bridge",
            "type":"Public Place"
        }
    ],
    "sg:phone":"+41 56 460 02 20",
    "sg:postcode":"5200",
    "sg:province":"Aargau",
    "sg:tags":[
        "construction"
    ],
    "wof:name":"Gebr. Meier Ag",
    "wof:placetype":"venue"
},
  "geometry": {"coordinates":[8.208595,47.483421],"type":"Point"}
}