{
  "type": "Feature",
  "properties": {
    "iso:country":"CH",
    "sg:address":"Kreuzbergstrasse 3",
    "sg:city":"Bichelsee",
    "sg:orig_category":"Softwareentwicklung U beratung",
    "sg:phone":"+41 71 971 23 02",
    "sg:postcode":"8363",
    "sg:province":"Thurgau",
    "wof:name":"Schicker R.",
    "wof:placetype":"venue"
},
  "geometry": {"coordinates":[8.9225149155,47.4480514526],"type":"Point"}
}