{
  "type": "Feature",
  "properties": {
    "iso:country":"CH",
    "sg:address":"Schanzm\u00e4ttelistrasse 5 5000 Aarau. Postfach",
    "sg:city":"Aarau",
    "sg:orig_category":"Herstellung von medizinischen U chirurgischen Ger\u00e4ten sowie orthop\u00e4dischen Vorrichtungen",
    "sg:phone":"+41 78 632 08 15",
    "sg:postcode":"5000",
    "sg:province":"Aargau",
    "wof:name":"Ruf Hans Dental-labor Gmbh",
    "wof:placetype":"venue"
},
  "geometry": {"coordinates":[8.0432300568,47.3890304565],"type":"Point"}
}