{
  "type": "Feature",
  "properties": {
    "iso:country":"CH",
    "sg:address":"Bachmatt 5",
    "sg:city":"Fahrwangen",
    "sg:orig_category":"Sonstige mit der Informatik verbundene T\u00e4tigkeiten Unternehmensberatung",
    "sg:phone":"+41 19912055",
    "sg:postcode":"5615",
    "sg:province":"Aargau",
    "wof:name":"Maxtronics Ag",
    "wof:placetype":"venue"
},
  "geometry": {"coordinates":[8.606762886,47.3087615967],"type":"Point"}
}