{
  "type": "Feature",
  "properties": {
    "iso:country":"CH",
    "sg:address":"Neum\u00fchlestrasse 42 8406 Winterthur. Postfach",
    "sg:city":"Winterthur",
    "sg:orig_category":"Elektroinstallation Herstellung von Radio U Fernsehger\u00e4ten sowie phono U videotechnischen Ger\u00e4ten",
    "sg:phone":"+41 32 652 31 13",
    "sg:postcode":"8406",
    "sg:province":"Z\u00fcrich",
    "wof:name":"Bratschi Ag",
    "wof:placetype":"venue"
},
  "geometry": {"coordinates":[7.3660998344,47.1816177368],"type":"Point"}
}