{
  "type": "Feature",
  "properties": {
    "iso:country":"CH",
    "sg:address":"Erlenstrasse 4a 6343 Rotkreuz. Postfach",
    "sg:city":"Rotkreuz",
    "sg:orig_category":"Erwachsenenbildung U Unterricht",
    "sg:postcode":"6343",
    "sg:province":"Zug",
    "wof:name":"Top Training Management Gmbh Schulungs, Beratungs- U. Ausbildungsdienstleistungen Usw",
    "wof:placetype":"venue"
},
  "geometry": {"coordinates":[8.430431366,47.1490135193],"type":"Point"}
}