{
  "type": "Feature",
  "properties": {
    "iso:country":"CH",
    "sg:address":"Jensgasse 8",
    "sg:city":"Bellmund",
    "sg:orig_category":"Cnc-Milled Parts",
    "sg:phone":"+41 32 331 62 27",
    "sg:postcode":"2564",
    "sg:province":"Bern",
    "wof:name":"Bruno Poletti Ag",
    "wof:placetype":"venue"
},
  "geometry": {"coordinates":[7.247722,47.107594],"type":"Point"}
}