{
  "type": "Feature",
  "properties": {
    "iso:country":"CH",
    "sg:address":"Freiestrasse 34",
    "sg:city":"Interlaken",
    "sg:orig_category":"Fahrschulen, Flugschulen",
    "sg:phone":"+41 79 407 66 66",
    "sg:postcode":"3800",
    "sg:province":"Bern",
    "wof:name":"Albrik Schibli Autofahrschule",
    "wof:placetype":"venue"
},
  "geometry": {"coordinates":[9.0373411179,47.4647369385],"type":"Point"}
}