{
  "type": "Feature",
  "properties": {
    "iso:country":"CH",
    "sg:address":"Steinenvorstadt 79",
    "sg:city":"Basel",
    "sg:orig_category":"Kosmetikinstitute",
    "sg:phone":"+41 61 281 73 74",
    "sg:postcode":"4051",
    "sg:province":"Basel-Stadt",
    "wof:name":"Manuela M\u00fcller Parallele Kosmetik",
    "wof:placetype":"venue"
},
  "geometry": {"coordinates":[7.5872402191,47.5512084961],"type":"Point"}
}