{
  "type": "Feature",
  "properties": {
    "iso:country":"CH",
    "sg:address":"H\u00fcbelweg 7",
    "sg:city":"Dittingen",
    "sg:orig_category":"Sportvereine Turnen",
    "sg:phone":"+41 61 311 72 28",
    "sg:postcode":"4243",
    "sg:province":"Basel-Landschaft",
    "wof:name":"Turnverein Stv Dornach",
    "wof:placetype":"venue"
},
  "geometry": {"coordinates":[7.6123270988,47.4797515869],"type":"Point"}
}