{
  "type": "Feature",
  "properties": {
    "iso:country":"CH",
    "sg:address":"Aeschweg 20",
    "sg:city":"Moosseedorf",
    "sg:orig_category":"Sonstiger Grosshandel",
    "sg:phone":"+41 31 859 75 43",
    "sg:postcode":"3302",
    "sg:province":"Bern",
    "wof:name":"Kilchenmann Th. & Krieg M.",
    "wof:placetype":"venue"
},
  "geometry": {"coordinates":[7.4861531258,47.0109634399],"type":"Point"}
}