{
  "type": "Feature",
  "properties": {
    "iso:country":"CH",
    "sg:address":"Baselstrasse 57",
    "sg:city":"Sch\u00f6nenbuch",
    "sg:orig_category":"Herstellung von sonstigen landwirtschaftlichen Maschinen",
    "sg:postcode":"4124",
    "sg:province":"Basel-Landschaft",
    "wof:name":"Zwick Daniel",
    "wof:placetype":"venue"
},
  "geometry": {"coordinates":[7.5084338188,47.540851593],"type":"Point"}
}