{
  "type": "Feature",
  "properties": {
    "iso:country":"CH",
    "sg:address":"Munimattstrasse 6",
    "sg:city":"Menziken",
    "sg:orig_category":"Herstellung von k\u00e4lte U lufttechnischen Erzeugnissen f\u00fcr gewerbliche Zwecke",
    "sg:phone":"+41 62 771 82 50",
    "sg:postcode":"5737",
    "sg:province":"Aargau",
    "wof:name":"Propair L\u00fcftung-klima Montageunternehmen Eginme Mehmet",
    "wof:placetype":"venue"
},
  "geometry": {"coordinates":[8.1913547516,47.2470588684],"type":"Point"}
}