{
  "type": "Feature",
  "properties": {
    "iso:country":"CH",
    "sg:address":"Hostattstrasse 4",
    "sg:city":"Sarnen",
    "sg:orig_category":"Interessenvertretungen",
    "sg:postcode":"6060",
    "sg:province":"Obwalden",
    "wof:name":"Strassengenossenschaft Hostatt",
    "wof:placetype":"venue"
},
  "geometry": {"coordinates":[8.2500543594,46.8951911926],"type":"Point"}
}