{
  "type": "Feature",
  "properties": {
    "iso:country":"CH",
    "sg:address":"Rue Oscar-huguenin 22",
    "sg:city":"Boudry",
    "sg:orig_category":"Vermietung U Verpachtung von eigenen Immobilien",
    "sg:postcode":"2017",
    "sg:province":"Neuch\u00e2tel",
    "wof:name":"Les Buchilles Sa",
    "wof:placetype":"venue"
},
  "geometry": {"coordinates":[6.8369951248,46.9499473572],"type":"Point"}
}