{
  "type": "Feature",
  "properties": {
    "addr:full":"Lokdepot Lindstrasse 35 Winterthur Z\u00fcrich 8400",
    "addr:housenumber":"35",
    "addr:postcode":"8400",
    "addr:street":"Lindstrasse",
    "iso:country":"CH",
    "sg:address":"Lokdepot Lindstrasse 35",
    "sg:city":"Winterthur",
    "sg:orig_category":"Detailhandel mit B\u00fcchern, Zeitungen, Schreib U Papeteriewaren",
    "sg:phone":"+41 52 214 09 80",
    "sg:postcode":"8400",
    "sg:province":"Z\u00fcrich",
    "wof:name":"Lais Peter Eisenbahnb\u00fccher",
    "wof:placetype":"venue"
},
  "geometry": {"coordinates":[8.73299,47.498531],"type":"Point"}
}