{
  "type": "Feature",
  "properties": {
    "iso:country":"CH",
    "sg:address":"Haldenweg 1",
    "sg:city":"Jegenstorf",
    "sg:orig_category":"Handelsvermittlung U Grosshandel",
    "sg:phone":"+41 61 701 70 00",
    "sg:postcode":"3303",
    "sg:province":"Bern",
    "wof:name":"Suscawa Vertriebs-gmbh",
    "wof:placetype":"venue"
},
  "geometry": {"coordinates":[7.6215720177,47.4794540405],"type":"Point"}
}