{
  "type": "Feature",
  "properties": {
    "iso:country":"CH",
    "sg:address":"Florastrasse 44",
    "sg:city":"Olten",
    "sg:classifiers":[
        {
            "category":"Professional",
            "subcategory":"Employment Agencies",
            "type":"Services"
        }
    ],
    "sg:phone":"+41 31 326 48 48",
    "sg:postcode":"4600",
    "sg:province":"Solothurn",
    "sg:tags":[
        "personal",
        "u",
        "stellenvermittlung"
    ],
    "wof:name":"Xs Stellen Ag Tempor\u00e4rb\u00fcro Usw",
    "wof:placetype":"venue"
},
  "geometry": {"coordinates":[7.4473648071,46.9481048584],"type":"Point"}
}