{
  "type": "Feature",
  "properties": {
    "iso:country":"CH",
    "sg:address":"Jeandin Avenue Adrien- 4 1226 Th\u00f4nex. Postfach",
    "sg:city":"Th\u00f4nex",
    "sg:orig_category":"Druck ohne Zeitungsdruck",
    "sg:postcode":"1226",
    "sg:province":"Gen\u00e8ve",
    "wof:name":"Renia Nathalie Imprimerie",
    "wof:placetype":"venue"
},
  "geometry": {"coordinates":[6.2021870613,46.1922416687],"type":"Point"}
}