{
  "type": "Feature",
  "properties": {
    "iso:country":"CH",
    "sg:address":"Galterstrasse 12",
    "sg:city":"Gansingen",
    "sg:orig_category":"Detailhandel mit Metallwaren, Anstrichmitteln, Glaswaren, Bau U Heimwerkerbedarf",
    "sg:phone":"+41 62 875 10 22",
    "sg:postcode":"5272",
    "sg:province":"Aargau",
    "wof:name":"Sch\u00f6n Heinz Anlagentechnik",
    "wof:placetype":"venue"
},
  "geometry": {"coordinates":[8.1322050095,47.5429000854],"type":"Point"}
}