{
  "type": "Feature",
  "properties": {
    "iso:country":"CH",
    "sg:address":"Aarefeldstrasse 3",
    "sg:city":"Thun",
    "sg:orig_category":"Arztpraxen",
    "sg:phone":"+41 33 222 40 30",
    "sg:postcode":"3600",
    "sg:province":"Bern",
    "wof:name":"Dr.med.peter Schafroth Spezialarzt Fmh",
    "wof:placetype":"venue"
},
  "geometry": {"coordinates":[7.631849,46.756027],"type":"Point"}
}