{
  "type": "Feature",
  "properties": {
    "iso:country":"CH",
    "sg:address":"Kronengarten 2",
    "sg:city":"Appenzell",
    "sg:classifiers":[
        {
            "category":"Restaurant",
            "type":"Food & Drink"
        }
    ],
    "sg:phone":"+41 71 787 12 04",
    "sg:postcode":"9050",
    "sg:province":"Appenzell Innerhoden",
    "wof:name":"Restaurant Marktplatz",
    "wof:placetype":"venue"
},
  "geometry": {"coordinates":[9.4067287445,47.3312911987],"type":"Point"}
}