{
  "type": "Feature",
  "properties": {
    "iso:country":"CH",
    "sg:address":"Parkstrasse 16b 5012 Sch\u00f6nenwerd. Postfach",
    "sg:city":"Lenzburg",
    "sg:orig_category":"Erbringung von Dienstleistungen f\u00fcr Unternehmen",
    "sg:postcode":"5600",
    "sg:province":"Aargau",
    "wof:name":"Spinform Ag",
    "wof:placetype":"venue"
},
  "geometry": {"coordinates":[7.9979748726,47.3702011108],"type":"Point"}
}