{
  "type": "Feature",
  "properties": {
    "iso:country":"CH",
    "sg:address":"Neckerstrasse 11",
    "sg:city":"Oberhelfenschwil",
    "sg:orig_category":"Allgemeiner Hochbau Strassenbau",
    "sg:phone":"+41 71 374 16 38",
    "sg:postcode":"9621",
    "sg:province":"St. Gallen",
    "wof:name":"Dahinden Ag Bauunternehmung",
    "wof:placetype":"venue"
},
  "geometry": {"coordinates":[9.116124,47.353752],"type":"Point"}
}