{
  "type": "Feature",
  "properties": {
    "iso:country":"CH",
    "sg:address":"Digue De La Morge 41 1962 Pont-de-la-morge Case Postale 54",
    "sg:city":"Pont-de-la-morge",
    "sg:orig_category":"Institutionen f\u00fcr Behinderte Tagesheime f\u00fcr Behinderte, gesch\u00fctzte Werkst\u00e4tten",
    "sg:phone":"+41 32 913 20 15",
    "sg:postcode":"1962",
    "sg:province":"Valais",
    "wof:name":"Centre Professionnel Les Perce-neige",
    "wof:placetype":"venue"
},
  "geometry": {"coordinates":[6.8351559639,47.1019172668],"type":"Point"}
}