{
  "type": "Feature",
  "properties": {
    "iso:country":"CH",
    "sg:address":"Obere Bisr\u00fctistrasse 30 9220 Bischofszell. Postfach",
    "sg:city":"T\u00e4gerschen",
    "sg:orig_category":"Herstellung von Metallkonstruktionen",
    "sg:postcode":"9554",
    "sg:province":"Thurgau",
    "wof:name":"Eugster Markus Montage Und Reparaturdienstleistungen Maschinen, Bes. Druckgussmaschinen; Montage, Reparatur Usw",
    "wof:placetype":"venue"
},
  "geometry": {"coordinates":[9.25086689,47.4930152893],"type":"Point"}
}