{
  "type": "Feature",
  "properties": {
    "iso:country":"CH",
    "sg:address":"Riedmatt 29",
    "sg:city":"Zug",
    "sg:orig_category":"Konsumentenorganisationen",
    "sg:phone":"+41 31 951 25 25",
    "sg:postcode":"6300",
    "sg:province":"Zug",
    "wof:name":"Liselotte Steffen Konsumentinnenforum Sekt.bern",
    "wof:placetype":"venue"
},
  "geometry": {"coordinates":[7.4870638847,46.9323997498],"type":"Point"}
}