{
  "type": "Feature",
  "properties": {
    "iso:country":"CH",
    "sg:address":"Grand'rue 96",
    "sg:city":"Rolle",
    "sg:orig_category":"Bauspenglerei Zimmerei, Dachdeckerei, Bauspenglerei U Abdichtung",
    "sg:phone":"+41 21 825 15 29",
    "sg:postcode":"1180",
    "sg:province":"Vaud",
    "wof:name":"Mischler, Reynald",
    "wof:placetype":"venue"
},
  "geometry": {"coordinates":[6.338232,46.457516],"type":"Point"}
}