{
  "type": "Feature",
  "properties": {
    "iso:country":"CH",
    "sg:address":"Hauptstrasse 45 8363 Bichelsee. Postfach",
    "sg:city":"Bichelsee",
    "sg:orig_category":"Herstellung von Kunststoff in Prim\u00e4rformen Herstellung von Kunststoffwaren",
    "sg:phone":"+41 71 971 34 33",
    "sg:postcode":"8363",
    "sg:province":"Thurgau",
    "wof:name":"Winkler Kunststoffwerk Ag",
    "wof:placetype":"venue"
},
  "geometry": {"coordinates":[8.918419838,47.4498710632],"type":"Point"}
}