{
  "type": "Feature",
  "properties": {
    "iso:country":"CH",
    "sg:address":"Culmannstrasse 36 8050 Z\u00fcrich 50 Zust. Postfach 8839",
    "sg:city":"Z\u00fcrich",
    "sg:orig_category":"Herstellung von Schmuck, Gold U Silberschmiedwaren",
    "sg:phone":"+41 13130227",
    "sg:postcode":"8050",
    "sg:province":"Z\u00fcrich",
    "wof:name":"Nat Arie",
    "wof:placetype":"venue"
},
  "geometry": {"coordinates":[8.5494403839,47.413520813],"type":"Point"}
}