{
  "type": "Feature",
  "properties": {
    "iso:country":"CH",
    "sg:address":"Langackerweg 27",
    "sg:city":"Niederhasli",
    "sg:orig_category":"Verlegen von Fliesen U Platten",
    "sg:phone":"+41 56 622 44 60",
    "sg:postcode":"8155",
    "sg:province":"Z\u00fcrich",
    "wof:name":"Willi Strasser Keramische Wand-& Bodenbel\u00e4ge",
    "wof:placetype":"venue"
},
  "geometry": {"coordinates":[8.2929754257,47.345085144],"type":"Point"}
}