{
  "type": "Feature",
  "properties": {
    "iso:country":"CH",
    "sg:address":"Kanzleistrasse 127",
    "sg:city":"Z\u00fcrich",
    "sg:orig_category":"Architektur U Ingenieurb\u00fcros Architekturb\u00fcros",
    "sg:phone":"+41 12913700",
    "sg:postcode":"8004",
    "sg:province":"Z\u00fcrich",
    "wof:name":"Archidee Stettler + Reiner Architekturb\u00fcro Htl",
    "wof:placetype":"venue"
},
  "geometry": {"coordinates":[8.520171,47.376907],"type":"Point"}
}