{
  "type": "Feature",
  "properties": {
    "iso:country":"CH",
    "sg:address":"Alte Landstrasse 82",
    "sg:city":"Mitl\u00f6di",
    "sg:orig_category":"Unclassifiable Establishments",
    "sg:postcode":"8756",
    "sg:province":"Glarus",
    "wof:name":"Giant Catering Gmbh",
    "wof:placetype":"venue"
},
  "geometry": {"coordinates":[7.4788808823,46.9300804138],"type":"Point"}
}