{
  "type": "Feature",
  "properties": {
    "iso:country":"CH",
    "sg:address":"Looslistrasse 29a",
    "sg:city":"Bern",
    "sg:orig_category":"Einzelhandel mit Automobilteilen U Zubeh\u00f6r Herstellung von Teilen U Zubeh\u00f6r f\u00fcr Automobile",
    "sg:phone":"+41 79 432 08 82",
    "sg:postcode":"3027",
    "sg:province":"Bern",
    "wof:name":"Lor\u00e9tan Ag",
    "wof:placetype":"venue"
},
  "geometry": {"coordinates":[7.3977499008,46.9480018616],"type":"Point"}
}