{
  "type": "Feature",
  "properties": {
    "iso:country":"CH",
    "sg:address":"Hagenholzstrasse 85",
    "sg:city":"Z\u00fcrich",
    "sg:orig_category":"Unclassifiable Establishments",
    "sg:postcode":"8050",
    "sg:province":"Z\u00fcrich",
    "wof:name":"Holcim Group Support (zurich) Ltd",
    "wof:placetype":"venue"
},
  "geometry": {"coordinates":[8.5601816177,47.4147644043],"type":"Point"}
}