{
  "type": "Feature",
  "properties": {
    "iso:country":"CH",
    "sg:address":"Gygerweg 31",
    "sg:city":"Spiez",
    "sg:orig_category":"Softwareentwicklung U beratung",
    "sg:phone":"+41 33 654 40 75",
    "sg:postcode":"3700",
    "sg:province":"Bern",
    "wof:name":"Lang Informatik Gmbh",
    "wof:placetype":"venue"
},
  "geometry": {"coordinates":[7.6650657654,46.685005188],"type":"Point"}
}