{
  "type": "Feature",
  "properties": {
    "iso:country":"CH",
    "sg:address":"Ankerstrasse 3",
    "sg:city":"Z\u00fcrich",
    "sg:orig_category":"Architekturb\u00fcros",
    "sg:phone":"+41 12400909",
    "sg:postcode":"8004",
    "sg:province":"Z\u00fcrich",
    "wof:name":"Martin Schneider Architekturb\u00fcro",
    "wof:placetype":"venue"
},
  "geometry": {"coordinates":[8.523774,47.372471],"type":"Point"}
}