{
  "type": "Feature",
  "properties": {
    "iso:country":"CH",
    "sg:address":"Benedikt-hugi-strasse 16",
    "sg:city":"Solothurn",
    "sg:orig_category":"Detailhandel mit Fahrr\u00e4dern Handel mit Motorr\u00e4dern, Teilen U Zubeh\u00f6r Instandhaltung U Reparatur von ",
    "sg:phone":"+41 32 623 44 22",
    "sg:postcode":"4500",
    "sg:province":"Solothurn",
    "wof:name":"Radsport Friedli",
    "wof:placetype":"venue"
},
  "geometry": {"coordinates":[7.5166940689,47.2094078064],"type":"Point"}
}