{
  "type": "Feature",
  "properties": {
    "iso:country":"CH",
    "sg:address":"Feldstrasse 1 6022 Grosswangen. Postfach",
    "sg:city":"Grosswangen",
    "sg:orig_category":"Allgemeiner Hoch U Tiefbau Architekturb\u00fcros",
    "sg:phone":"+41 41 980 31 71",
    "sg:postcode":"6022",
    "sg:province":"Luzern",
    "wof:name":"Hunkeler J. + E. Ag",
    "wof:placetype":"venue"
},
  "geometry": {"coordinates":[8.047662,47.133484],"type":"Point"}
}