{
  "type": "Feature",
  "properties": {
    "iso:country":"CH",
    "sg:address":"Sinserstr. 11",
    "sg:city":"Auw",
    "sg:orig_category":"RESTAURANTS: TEA-ROOMS",
    "sg:postcode":"5644",
    "sg:province":"Aargau",
    "wof:name":"Frey Alfred Gasthof Linde",
    "wof:placetype":"venue"
},
  "geometry": {"coordinates":[8.3665113449,47.2106895447],"type":"Point"}
}