{
  "type": "Feature",
  "properties": {
    "iso:country":"CH",
    "sg:address":"9052",
    "sg:city":"Niederteufen",
    "sg:orig_category":"Verwaltung der Strafvollzuganstalten Wohnheime",
    "sg:phone":"+41 71 335 09 40",
    "sg:postcode":"9052",
    "sg:province":"Appenzell Ausserrhoden",
    "wof:name":"Kant. Strafanstalt Gm\u00fcnden",
    "wof:placetype":"venue"
},
  "geometry": {"coordinates":[9.3625898361,47.3931999207],"type":"Point"}
}