{
  "type": "Feature",
  "properties": {
    "iso:country":"CH",
    "sg:address":"Sitzberg",
    "sg:city":"Schmidr\u00fcti",
    "sg:orig_category":"Sportvereine Flug Delta",
    "sg:phone":"+41 19304958",
    "sg:postcode":"8495",
    "sg:province":"Z\u00fcrich",
    "wof:name":"Gs-club Wald Zh-oberland",
    "wof:placetype":"venue"
},
  "geometry": {"coordinates":[8.8114118576,47.3339881897],"type":"Point"}
}