{
  "type": "Feature",
  "properties": {
    "iso:country":"CH",
    "sg:address":"Reiserstrasse 112",
    "sg:city":"Olten",
    "sg:orig_category":"Grosshandel mit Eisenwaren sowie Installationsbedarf f\u00fcr Gas, Wasser U Heizung Grosshandel mit Werkz",
    "sg:phone":"+41 79 240 54 65",
    "sg:postcode":"4600",
    "sg:province":"Solothurn",
    "wof:name":"Singer Pr\u00e9cision Sa",
    "wof:placetype":"venue"
},
  "geometry": {"coordinates":[6.9374527931,46.9935340881],"type":"Point"}
}