{
  "type": "Feature",
  "properties": {
    "addr:full":"Rue Scheffer 6 Courfaivre Jura 2853",
    "addr:housenumber":"6",
    "addr:postcode":"2853",
    "addr:street":"Rue Scheffer;Jura",
    "iso:country":"CH",
    "sg:address":"Rue Scheffer 6",
    "sg:city":"Courfaivre",
    "sg:classifiers":[
        {
            "category":"Professional",
            "subcategory":"Business Services",
            "type":"Services"
        }
    ],
    "sg:phone":"+41 32 427 01 01",
    "sg:postcode":"2853",
    "sg:province":"Jura",
    "sg:tags":[
        "high-precision",
        "mechanic"
    ],
    "wof:name":"Condor S.a.",
    "wof:placetype":"venue"
},
  "geometry": {"coordinates":[7.291266,47.334801],"type":"Point"}
}