{
  "type": "Feature",
  "properties": {
    "iso:country":"CH",
    "sg:address":"1528",
    "sg:city":"Surpierre",
    "sg:orig_category":"Detailhandel mit Antiquit\u00e4ten U Gebrauchtwaren in Verkaufsr\u00e4umen",
    "sg:postcode":"1528",
    "sg:province":"Fribourg",
    "wof:name":"Cl\u00e9ment Line.",
    "wof:placetype":"venue"
},
  "geometry": {"coordinates":[6.571775,46.574234],"type":"Point"}
}