{
  "type": "Feature",
  "properties": {
    "iso:country":"CH",
    "sg:address":"Neuzelgweg 10",
    "sg:city":"Villigen",
    "sg:orig_category":"Unclassifiable Establishments",
    "sg:postcode":"5234",
    "sg:province":"Aargau",
    "wof:name":"Finsterwald Elektrounternehmung Gmbh",
    "wof:placetype":"venue"
},
  "geometry": {"coordinates":[8.2171611786,47.5202636719],"type":"Point"}
}