{
  "type": "Feature",
  "properties": {
    "iso:country":"CH",
    "sg:address":"Rue De L'ile Falcon",
    "sg:city":"Sierre",
    "sg:orig_category":"Detailhandel mit Teppichen Verlegen von Fussboden",
    "sg:phone":"+41 27 455 01 58",
    "sg:postcode":"3960",
    "sg:province":"Valais",
    "wof:name":"Fernand M\u00e9trailler Tapis Linos Parquets",
    "wof:placetype":"venue"
},
  "geometry": {"coordinates":[7.550339222,46.2863006592],"type":"Point"}
}