{
  "type": "Feature",
  "properties": {
    "iso:country":"CH",
    "sg:address":"Industriestrasse 65 3052 Zollikofen. Postfach",
    "sg:city":"Zollikofen",
    "sg:orig_category":"Sonstige mit Sport verbundene T\u00e4tigkeiten",
    "sg:postcode":"3052",
    "sg:province":"Bern",
    "wof:name":"Davos Leistungssport (stiftung)",
    "wof:placetype":"venue"
},
  "geometry": {"coordinates":[9.8158302307,46.7902336121],"type":"Point"}
}