{
  "type": "Feature",
  "properties": {
    "iso:country":"CH",
    "sg:address":"Zone Industrielle En Charri\u00e8re",
    "sg:city":"Vuiteboeuf",
    "sg:classifiers":[
        {
            "category":"Utilities",
            "subcategory":"Recycling",
            "type":"Services"
        }
    ],
    "sg:phone":"+41 24 459 25 75",
    "sg:postcode":"1445",
    "sg:province":"Vaud",
    "sg:tags":[
        "metal"
    ],
    "wof:name":"Laurent Bader",
    "wof:placetype":"venue"
},
  "geometry": {"coordinates":[6.5488681793,46.8069915771],"type":"Point"}
}