{
  "type": "Feature",
  "properties": {
    "addr:full":"Morissen Graubunden 7143",
    "addr:postcode":"7143",
    "iso:country":"CH",
    "sg:city":"Morissen",
    "sg:classifiers":[
        {
            "category":"Banks & Credit Unions",
            "subcategory":"Bank",
            "type":"Services"
        }
    ],
    "sg:phone":"+41 81 931 22 21",
    "sg:postcode":"7143",
    "sg:province":"Graubunden",
    "wof:name":"Raiffeisenbank",
    "wof:placetype":"venue"
},
  "geometry": {"coordinates":[9.181076,46.73016],"type":"Point"}
}