{
  "type": "Feature",
  "properties": {
    "iso:country":"CH",
    "sg:address":"Pace Via Della 6",
    "sg:city":"Locarno",
    "sg:orig_category":"Pensionskassen",
    "sg:postcode":"6600",
    "sg:province":"Ticino",
    "wof:name":"Cassa Decessi Della Sezione Ticino Della Federazione Svizzera Dei Funzionari Di Polizia",
    "wof:placetype":"venue"
},
  "geometry": {"coordinates":[8.7984743118,46.1681365967],"type":"Point"}
}