{
  "type": "Feature",
  "properties": {
    "iso:country":"CH",
    "sg:address":"Hauptgasse 9",
    "sg:city":"Mellingen",
    "sg:orig_category":"Detailhandel mit Uhren U Schmuck Fachdetailhandel in Verkaufsr\u00e4umen",
    "sg:phone":"+41 56 491 32 67",
    "sg:postcode":"5507",
    "sg:province":"Aargau",
    "wof:name":"Liechti",
    "wof:placetype":"venue"
},
  "geometry": {"coordinates":[8.2733030319,47.418510437],"type":"Point"}
}