{
  "type": "Feature",
  "properties": {
    "iso:country":"CH",
    "sg:address":"Rue Du Pont 3",
    "sg:city":"Tramelan",
    "sg:orig_category":"Herstellung von sonstigen landwirtschaftlichen Maschinen",
    "sg:phone":"+41 32 487 65 35",
    "sg:postcode":"2720",
    "sg:province":"Bern",
    "wof:name":"Gottfried B\u00fchler Machines Agricoles & Garage",
    "wof:placetype":"venue"
},
  "geometry": {"coordinates":[7.1123080254,47.2226600647],"type":"Point"}
}