{
  "type": "Feature",
  "properties": {
    "iso:country":"CH",
    "sg:address":"Neudorf",
    "sg:city":"L\u00fctisburg",
    "sg:orig_category":"Elektroinstallation",
    "sg:postcode":"9604",
    "sg:province":"St. Gallen",
    "wof:name":"Ew Elektro Widmer Ag",
    "wof:placetype":"venue"
},
  "geometry": {"coordinates":[9.0820589066,47.39686203],"type":"Point"}
}