{
  "type": "Feature",
  "properties": {
    "iso:country":"CH",
    "sg:address":"7415",
    "sg:city":"Pratval",
    "sg:orig_category":"Landesverteidigung, Sozialversicherung \u00d6ffentliche Verwaltung",
    "sg:phone":"+41 81 655 10 20",
    "sg:postcode":"7415",
    "sg:province":"Graubunden",
    "wof:name":"Zivilschutzstelle Pratval",
    "wof:placetype":"venue"
},
  "geometry": {"coordinates":[9.4460220337,46.7313308716],"type":"Point"}
}