{
  "type": "Feature",
  "properties": {
    "iso:country":"CH",
    "sg:address":"Oey",
    "sg:city":"Saanen",
    "sg:orig_category":"RESTAURANTS: TEA-ROOMS",
    "sg:phone":"+41 33 744 60 99",
    "sg:postcode":"3792",
    "sg:province":"Bern",
    "wof:name":"Flugplatzbeizli, Blum Walter",
    "wof:placetype":"venue"
},
  "geometry": {"coordinates":[7.2574400902,46.4894638062],"type":"Point"}
}