{
  "type": "Feature",
  "properties": {
    "iso:country":"CH",
    "sg:address":"Obstgartenweg 11 8136 Gattikon. Postfach",
    "sg:city":"Gattikon",
    "sg:orig_category":"G\u00fcterbef\u00f6rderung im Strassenverkehr",
    "sg:postcode":"8136",
    "sg:province":"Z\u00fcrich",
    "wof:name":"A. Siegfried + Co Transporte + Umz\u00fcge",
    "wof:placetype":"venue"
},
  "geometry": {"coordinates":[8.5489635468,47.2837715149],"type":"Point"}
}