{
  "type": "Feature",
  "properties": {
    "iso:country":"CH",
    "sg:address":"Keltenweg 1",
    "sg:city":"Gelterkinden",
    "sg:orig_category":"Instandhaltung U Reparatur von Automobilen",
    "sg:phone":"+41 61 981 36 06",
    "sg:postcode":"4460",
    "sg:province":"Basel-Landschaft",
    "wof:name":"H\u00e4uselmann H. Autoelectric",
    "wof:placetype":"venue"
},
  "geometry": {"coordinates":[7.8584499359,47.4599914551],"type":"Point"}
}