{
  "type": "Feature",
  "properties": {
    "iso:country":"CH",
    "sg:address":"Rue Des Courtils 8a",
    "sg:city":"Corcelles",
    "sg:classifiers":[
        {
            "category":"Manufacturing",
            "subcategory":"Motor Vehicles & Parts",
            "type":"Manufacturing & Wholesale Goods"
        }
    ],
    "sg:phone":"+41 32 732 99 99",
    "sg:postcode":"2035",
    "sg:province":"Neuch\u00e2tel",
    "sg:tags":[
        "electronic",
        "assembling",
        "component"
    ],
    "wof:name":"Forelec Sa",
    "wof:placetype":"venue"
},
  "geometry": {"coordinates":[6.88047,46.983746],"type":"Point"}
}