{
  "type": "Feature",
  "properties": {
    "iso:country":"CH",
    "sg:address":"Oberwiesenstrasse 75",
    "sg:city":"Frauenfeld",
    "sg:orig_category":"Herstellung von Erzeugnissen aus Beton, Gips U Zement Herstellung von sonstigen elektrischen Ausr\u00fcst",
    "sg:phone":"+41 52 720 88 22",
    "sg:postcode":"8500",
    "sg:province":"Thurgau",
    "wof:name":"Sibatron Ag",
    "wof:placetype":"venue"
},
  "geometry": {"coordinates":[8.8798093796,47.5567703247],"type":"Point"}
}