{
  "type": "Feature",
  "properties": {
    "iso:country":"CH",
    "sg:address":"1040",
    "sg:city":"Echallens",
    "sg:orig_category":"Grosshandel mit Getreide, Saatgut U Futtermitteln",
    "sg:phone":"+41 79 237 50 11",
    "sg:postcode":"1040",
    "sg:province":"Vaud",
    "wof:name":"Coretti Gian",
    "wof:placetype":"venue"
},
  "geometry": {"coordinates":[9.7641716003,46.4287643433],"type":"Point"}
}