{
  "type": "Feature",
  "properties": {
    "iso:country":"CH",
    "sg:address":"6036",
    "sg:city":"Dierikon",
    "sg:orig_category":"Gemeindeverwaltungen",
    "sg:phone":"+41 55 653 61 61",
    "sg:postcode":"6036",
    "sg:province":"Luzern",
    "wof:name":"Gemeindeverwaltung Diesbach",
    "wof:placetype":"venue"
},
  "geometry": {"coordinates":[9.0313501358,46.9512786865],"type":"Point"}
}