{
  "type": "Feature",
  "properties": {
    "iso:country":"CH",
    "sg:address":"Via Pioda 8",
    "sg:city":"Lugano",
    "sg:orig_category":"Vermietung U Verpachtung von eigenen Immobilien Vermittlung von Immobilien",
    "sg:phone":"+41 41 410 67 67",
    "sg:postcode":"6900",
    "sg:province":"Ticino",
    "wof:name":"Dormen Ag",
    "wof:placetype":"venue"
},
  "geometry": {"coordinates":[8.301202774,47.0527076721],"type":"Point"}
}