{
  "type": "Feature",
  "properties": {
    "iso:country":"CH",
    "sg:address":"M\u00fchlegasse 3 8001 Z\u00fcrich. Postfach",
    "sg:city":"Z\u00fcrich",
    "sg:classifiers":[
        {
            "category":"Bars & Pubs",
            "type":"Food & Drink"
        }
    ],
    "sg:phone":"+41 12514110",
    "sg:postcode":"8025",
    "wof:name":"Haifisch-bar",
    "wof:placetype":"venue"
},
  "geometry": {"coordinates":[8.543189,47.374428],"type":"Point"}
}