{
  "type": "Feature",
  "properties": {
    "iso:country":"CH",
    "sg:address":"Winzenbachstrasse 2",
    "sg:city":"Neuheim",
    "sg:orig_category":"Detailhandel mit Teppichen Verlegen von Fussboden",
    "sg:phone":"+41 41 755 25 58",
    "sg:postcode":"6345",
    "sg:province":"Zug",
    "wof:name":"Heinz Horlacher Teppiche & Bodenbel\u00e4ge",
    "wof:placetype":"venue"
},
  "geometry": {"coordinates":[8.5830087662,47.2027435303],"type":"Point"}
}