{
  "type": "Feature",
  "properties": {
    "addr:full":"Avry Route D' 4 Matran Fribourg 1753",
    "addr:housenumber":"avry;4",
    "addr:postcode":"1753",
    "addr:street":"Route D '",
    "iso:country":"CH",
    "sg:address":"Avry Route D' 4",
    "sg:city":"Matran",
    "sg:orig_category":"Architektur U Ingenieurb\u00fcros",
    "sg:phone":"+41 26 402 93 85",
    "sg:postcode":"1753",
    "sg:province":"Fribourg",
    "wof:name":"Dorthe G\u00e9rard, Bureau Technique",
    "wof:placetype":"venue"
},
  "geometry": {"coordinates":[7.076083,46.787098],"type":"Point"}
}