{
  "type": "Feature",
  "properties": {
    "iso:country":"CH",
    "sg:address":"Herdernstrasse 63 8004 Z\u00fcrich. Postfach",
    "sg:city":"Z\u00fcrich",
    "sg:orig_category":"Berufsorganisationen",
    "sg:phone":"+41 14921215",
    "sg:postcode":"8004",
    "sg:province":"Z\u00fcrich",
    "wof:name":"Genossenschaft Metzgermeisterverein Z\u00fcrich",
    "wof:placetype":"venue"
},
  "geometry": {"coordinates":[8.50687,47.384064],"type":"Point"}
}