{
  "type": "Feature",
  "properties": {
    "iso:country":"CH",
    "sg:address":"Avenue De La Vallombreuse 97 1008 Prilly Case Postale 181",
    "sg:city":"Prilly",
    "sg:orig_category":"Maler U Glasergewerbe Stukkateurgewerbe, Gipserei U Verputzerei",
    "sg:phone":"+41 79 310 77 65",
    "sg:postcode":"1008",
    "sg:province":"Vaud",
    "wof:name":"Interd\u00e9cor A.& A.lezzi Entreprise De Peinture",
    "wof:placetype":"venue"
},
  "geometry": {"coordinates":[6.6098251343,46.5396385193],"type":"Point"}
}