{
  "type": "Feature",
  "properties": {
    "iso:country":"CH",
    "sg:address":"Avenue De La Gare",
    "sg:city":"Rolle",
    "sg:orig_category":"Fachdetailhandel mit pharmazeutischen Produkten Sonstiger Fachdetailhandel mit Nahrungsmitteln, Getr",
    "sg:phone":"+41 21 826 03 44",
    "sg:postcode":"1180",
    "sg:province":"Vaud",
    "wof:name":"Sun Store Sa",
    "wof:placetype":"venue"
},
  "geometry": {"coordinates":[6.3373608589,46.4628181458],"type":"Point"}
}