{
  "type": "Feature",
  "properties": {
    "addr:full":"Josefstrasse 20 Z\u00fcrich Z\u00fcrich 8005",
    "addr:housenumber":"20",
    "addr:postcode":"8005",
    "addr:street":"Josefstrasse",
    "iso:country":"CH",
    "sg:address":"Josefstrasse 20",
    "sg:city":"Z\u00fcrich",
    "sg:orig_category":"Architektur U Ingenieurb\u00fcros",
    "sg:phone":"+41 14404255",
    "sg:postcode":"8005",
    "sg:province":"Z\u00fcrich",
    "wof:name":"Raumlichtdetail Meierhofer Peter",
    "wof:placetype":"venue"
},
  "geometry": {"coordinates":[8.533944,47.380909],"type":"Point"}
}