{
  "type": "Feature",
  "properties": {
    "iso:country":"CH",
    "sg:address":"Spielhof 7 8750 Glarus. Postfach",
    "sg:city":"Glarus",
    "sg:orig_category":"Unternehmensberatung",
    "sg:postcode":"8750",
    "sg:province":"Glarus",
    "wof:name":"Fischli & W\u00fcrmli Beratung Und Coaching In Entwicklungsprozessen In Organisationen",
    "wof:placetype":"venue"
},
  "geometry": {"coordinates":[9.0662679672,47.0419464111],"type":"Point"}
}