{
  "type": "Feature",
  "properties": {
    "iso:country":"CH",
    "sg:address":"Untere Rebgasse 8",
    "sg:city":"Basel",
    "sg:orig_category":"Aktivit\u00e4t der Bankinstitute",
    "sg:phone":"+41 61 681 27 77",
    "sg:postcode":"4058",
    "sg:province":"Basel-Stadt",
    "wof:name":"Migrosbank",
    "wof:placetype":"venue"
},
  "geometry": {"coordinates":[7.592787,47.562195],"type":"Point"}
}