{
  "type": "Feature",
  "properties": {
    "iso:country":"CH",
    "sg:address":"G\u00fcterstrasse 22",
    "sg:city":"Neuenhof",
    "sg:orig_category":"Elektrizit\u00e4tsversorgung",
    "sg:phone":"+41 56 406 31 41",
    "sg:postcode":"5432",
    "sg:province":"Aargau",
    "wof:name":"W. Pfeiffer, Lic. Oec, Hsg, B\u00fcro F\u00fcr Energiewirtschaft",
    "wof:placetype":"venue"
},
  "geometry": {"coordinates":[8.3324718475,47.4434967041],"type":"Point"}
}