{
  "type": "Feature",
  "properties": {
    "iso:country":"CH",
    "sg:address":"Marktgasse 23",
    "sg:city":"Langenthal",
    "sg:orig_category":"Einbau von Schreinerwaren Herstellung von K\u00fcchenm\u00f6beln",
    "sg:phone":"+41 62 923 22 10",
    "sg:postcode":"4900",
    "sg:province":"Bern",
    "wof:name":"Oester Ruedi K\u00fcchen",
    "wof:placetype":"venue"
},
  "geometry": {"coordinates":[7.7888011932,47.2114181519],"type":"Point"}
}