{
  "type": "Feature",
  "properties": {
    "iso:country":"CH",
    "sg:address":"Avenue Louis-ruchonnet 18",
    "sg:city":"Lausanne",
    "sg:orig_category":"Architektur U Ingenieurb\u00fcros",
    "sg:phone":"+41 21 310 20 30",
    "sg:postcode":"1003",
    "sg:province":"Vaud",
    "wof:name":"Atelier D'architecture Perret Architecte Epfl-sia",
    "wof:placetype":"venue"
},
  "geometry": {"coordinates":[6.625113,46.519077],"type":"Point"}
}