{
  "type": "Feature",
  "properties": {
    "iso:country":"CH",
    "sg:address":"M\u00fchlethalstrasse 25",
    "sg:city":"Zofingen",
    "sg:orig_category":"Arztpraxen",
    "sg:phone":"+41 62 752 08 88",
    "sg:postcode":"4800",
    "sg:province":"Aargau",
    "wof:name":"Dr.med. Jean Pf\u00e4ndler Spezialarzt Fmh",
    "wof:placetype":"venue"
},
  "geometry": {"coordinates":[7.946288,47.294308],"type":"Point"}
}