{
  "type": "Feature",
  "properties": {
    "iso:country":"CH",
    "sg:address":"Chemin De La Moraine 8",
    "sg:city":"Prilly",
    "sg:orig_category":"Malerei Stukkateurgewerbe, Gipserei U Verputzerei",
    "sg:phone":"+41 21 946 11 40",
    "sg:postcode":"1008",
    "sg:province":"Vaud",
    "wof:name":"Aldo Zoppi Pl\u00e2trerie & Peinture",
    "wof:placetype":"venue"
},
  "geometry": {"coordinates":[-105.31991577150001,35.3930015564],"type":"Point"}
}