{
  "type": "Feature",
  "properties": {
    "iso:country":"CH",
    "sg:address":"Winkelstrasse 23",
    "sg:city":"Oftringen",
    "sg:orig_category":"Unclassifiable Establishments",
    "sg:postcode":"4665",
    "sg:province":"Aargau",
    "wof:name":"Pama Truck-supplies Gmbh",
    "wof:placetype":"venue"
},
  "geometry": {"coordinates":[7.9323067665,47.299747467],"type":"Point"}
}