{
  "type": "Feature",
  "properties": {
    "iso:country":"CH",
    "sg:address":"Dorfplatz",
    "sg:city":"Leukerbad",
    "sg:orig_category":"HOTELS: MIT RESTAURANT Kongress- and Tagungshotels mit Restaurant",
    "sg:phone":"+41 27 957 10 01",
    "sg:postcode":"3954",
    "sg:province":"Valais",
    "wof:name":"Metropol Grand Hotel",
    "wof:placetype":"venue"
},
  "geometry": {"coordinates":[7.933672905,46.1117172241],"type":"Point"}
}