{
  "type": "Feature",
  "properties": {
    "iso:country":"CH",
    "sg:address":"Gibelhalde 18",
    "sg:city":"Herisau",
    "sg:orig_category":"Unternehmensberatung",
    "sg:postcode":"9100",
    "sg:province":"Appenzell Ausserrhoden",
    "wof:name":"Camaca Consult Ag",
    "wof:placetype":"venue"
},
  "geometry": {"coordinates":[9.2958345413,47.3902359009],"type":"Point"}
}