{
  "type": "Feature",
  "properties": {
    "iso:country":"CH",
    "sg:address":"Oberoppikon",
    "sg:city":"Oppikon",
    "sg:orig_category":"Detailhandel mit Milcherzeugnissen U Eiern Verarbeitung von Milch",
    "sg:phone":"+41 71 651 11 41",
    "sg:postcode":"9565",
    "sg:province":"Thurgau",
    "wof:name":"Edwin Iseli K\u00e4serei",
    "wof:placetype":"venue"
},
  "geometry": {"coordinates":[9.0787296295,47.5577392578],"type":"Point"}
}