{
  "type": "Feature",
  "properties": {
    "iso:country":"CH",
    "sg:address":"Parkstr. 14",
    "sg:city":"Matten",
    "sg:orig_category":"Medien, Zeitungen and Zeitschriften",
    "sg:phone":"+41 33",
    "sg:postcode":"3800",
    "sg:province":"Bern",
    "wof:name":"Ganzheitlich Leben Im Wassermann-zeitalter",
    "wof:placetype":"venue"
},
  "geometry": {"coordinates":[7.861696,46.682346],"type":"Point"}
}