{
  "type": "Feature",
  "properties": {
    "iso:country":"CH",
    "sg:address":"Sonneggstrasse 25 6410 Goldau. Postfach",
    "sg:city":"Goldau",
    "sg:orig_category":"Herstellung von konfektionierten Textilwaren ohne Bekleidung",
    "sg:phone":"+41 41 629 70 76",
    "sg:postcode":"6410",
    "sg:province":"Schwyz",
    "wof:name":"Clean Factory Gmbh",
    "wof:placetype":"venue"
},
  "geometry": {"coordinates":[8.5491867065,47.0457496643],"type":"Point"}
}