{
  "type": "Feature",
  "properties": {
    "iso:country":"CH",
    "sg:address":"Route De Denges 20",
    "sg:city":"Lonay",
    "sg:orig_category":"Detailhandel mit Waren verschiedener Art, Hauptrichtung Nahrungsmittel Wein Detailhandel",
    "sg:postcode":"1027",
    "sg:province":"Vaud",
    "wof:name":"Jos\u00e9 Vaz Alimentation La Grotte",
    "wof:placetype":"venue"
},
  "geometry": {"coordinates":[6.5250511169,46.5262451172],"type":"Point"}
}