{
  "type": "Feature",
  "properties": {
    "iso:country":"CH",
    "sg:address":"Coll\u00e8ge Rue Du 10",
    "sg:city":"Avenches",
    "sg:orig_category":"Bibliotheken U Archive Haltung von Schafen, Ziegen, Pferden U Eseln",
    "sg:phone":"+41 26 676 61 11",
    "sg:postcode":"1580",
    "sg:province":"Vaud",
    "wof:name":"Association National Du Cheval Avenches Anca",
    "wof:placetype":"venue"
},
  "geometry": {"coordinates":[7.040785,46.880058],"type":"Point"}
}