{
  "type": "Feature",
  "properties": {
    "iso:country":"CH",
    "sg:address":"Kirchb\u00fcndtstrasse 46",
    "sg:city":"Ettingen",
    "sg:orig_category":"Unclassifiable Establishments",
    "sg:phone":"+41 61 722 14 79",
    "sg:postcode":"4107",
    "sg:province":"Basel-Landschaft",
    "wof:name":"Steinen Handwerker Zentrale, Paul Benjamin",
    "wof:placetype":"venue"
},
  "geometry": {"coordinates":[7.5504999161,47.4793891907],"type":"Point"}
}