{
  "type": "Feature",
  "properties": {
    "iso:country":"CH",
    "sg:address":"Bahnhofplatz 4",
    "sg:city":"M\u00fchlethurnen",
    "sg:orig_category":"Sanit\u00e4r, Heizungs U L\u00fcftungsinstallation Sanit\u00e4rinstallation U Spenglerei",
    "sg:phone":"+41 24 472 52 19",
    "sg:postcode":"3127",
    "sg:province":"Bern",
    "wof:name":"Gippa Sa, Succcursale De Muraz",
    "wof:placetype":"venue"
},
  "geometry": {"coordinates":[6.9349308014,46.276386261],"type":"Point"}
}