{
  "type": "Feature",
  "properties": {
    "addr:full":"Bahnhofstrasse 20 Ostermundigen Bern 3072",
    "addr:housenumber":"20",
    "addr:postcode":"3072",
    "addr:street":"Bahnhofstrasse",
    "iso:country":"CH",
    "sg:address":"Bahnhofstrasse 20",
    "sg:city":"Ostermundigen",
    "sg:orig_category":"Arbeitnehmerverb\u00e4nde",
    "sg:phone":"+41 31 931 60 61",
    "sg:postcode":"3072",
    "sg:province":"Bern",
    "wof:name":"Personalverband Der Allgem. Bundesverwaltung Pvb",
    "wof:placetype":"venue"
},
  "geometry": {"coordinates":[7.486395,46.954414],"type":"Point"}
}