{
  "type": "Feature",
  "properties": {
    "iso:country":"CH",
    "sg:address":"Lyssachstrasse 27",
    "sg:city":"Burgdorf",
    "sg:classifiers":[
        {
            "category":"Banks & Credit Unions",
            "subcategory":"Bank",
            "type":"Services"
        }
    ],
    "sg:phone":"+41 34231523",
    "sg:postcode":"3400",
    "sg:province":"Bern",
    "wof:name":"Neue Emme Bank",
    "wof:placetype":"venue"
},
  "geometry": {"coordinates":[7.620855,47.059368],"type":"Point"}
}