{
  "type": "Feature",
  "properties": {
    "iso:country":"CH",
    "sg:address":"Am Schanzengraben",
    "sg:city":"Z\u00fcrich",
    "sg:orig_category":"Berufsorganisationen",
    "sg:postcode":"8002",
    "sg:province":"Z\u00fcrich",
    "wof:name":"Verein Bauberater",
    "wof:placetype":"venue"
},
  "geometry": {"coordinates":[8.53497,47.369186],"type":"Point"}
}