{
  "type": "Feature",
  "properties": {
    "iso:country":"CH",
    "sg:address":"Dorfstrasse 2 6064 Kerns. Postfach 142",
    "sg:city":"Kerns",
    "sg:orig_category":"Zahnarztpraxen",
    "sg:phone":"+41 71 766 26 60",
    "sg:postcode":"6064",
    "sg:province":"Obwalden",
    "wof:name":"Dr. Med. Dent. Sami Fawzi Zahnarzt",
    "wof:placetype":"venue"
},
  "geometry": {"coordinates":[9.5383329391,47.2926864624],"type":"Point"}
}