{
  "type": "Feature",
  "properties": {
    "iso:country":"CH",
    "sg:address":"Heinrich Stutz-strasse 23",
    "sg:city":"Urdorf",
    "sg:orig_category":"Non-Classified Establishments",
    "sg:postcode":"8902",
    "sg:province":"Z\u00fcrich",
    "wof:name":"Pulsimmo Ag",
    "wof:placetype":"venue"
},
  "geometry": {"coordinates":[7.5961751938,47.4769973755],"type":"Point"}
}