{
  "type": "Feature",
  "properties": {
    "addr:full":"Biberiststrasse 21 Derendingen Solothurn 4552",
    "addr:housenumber":"21",
    "addr:postcode":"4552",
    "addr:street":"Biberiststrasse",
    "iso:country":"CH",
    "sg:address":"Biberiststrasse 21",
    "sg:city":"Derendingen",
    "sg:orig_category":"Allgemeiner Hoch U Tiefbau",
    "sg:postcode":"4552",
    "sg:province":"Solothurn",
    "wof:name":"Freni Bau Ag",
    "wof:placetype":"venue"
},
  "geometry": {"coordinates":[7.58224,47.186279],"type":"Point"}
}