{
  "type": "Feature",
  "properties": {
    "iso:country":"CH",
    "sg:address":"Quartiergasse 29 3013 Bern. Postfach",
    "sg:city":"Bern",
    "sg:orig_category":"Sonstige mit der Informatik verbundene T\u00e4tigkeiten",
    "sg:phone":"+41 31 331 74 56",
    "sg:postcode":"3005",
    "sg:province":"Bern",
    "wof:name":"Do Van Khoa Software; Beratung U. Entwicklung",
    "wof:placetype":"venue"
},
  "geometry": {"coordinates":[7.4450387955,46.957901001],"type":"Point"}
}