{
  "type": "Feature",
  "properties": {
    "iso:country":"CH",
    "sg:address":"M\u00fchlebachstrasse 70 8008 Z\u00fcrich. Postfach 331",
    "sg:city":"Z\u00fcrich",
    "sg:orig_category":"Aktivit\u00e4t der Bankinstitute",
    "sg:phone":"+41 12505656",
    "sg:postcode":"8034",
    "sg:province":"Z\u00fcrich",
    "wof:name":"Slb Commercial Bank",
    "wof:placetype":"venue"
},
  "geometry": {"coordinates":[8.552531,47.362648],"type":"Point"}
}