{
  "type": "Feature",
  "properties": {
    "iso:country":"CH",
    "sg:address":"Bossons Rue Des 20",
    "sg:city":"Onex",
    "sg:orig_category":"Unclassifiable Establishments",
    "sg:postcode":"1213",
    "sg:province":"Gen\u00e8ve",
    "wof:name":"Promarco Sa",
    "wof:placetype":"venue"
},
  "geometry": {"coordinates":[6.1030621529,46.1861991882],"type":"Point"}
}