{
  "type": "Feature",
  "properties": {
    "iso:country":"CH",
    "sg:address":"Eichenweg 30",
    "sg:city":"Jeuss",
    "sg:orig_category":"Malerei",
    "sg:phone":"+41 26 674 15 20",
    "sg:postcode":"1793",
    "sg:province":"Fribourg",
    "wof:name":"David Schiess Malergesch\u00e4ft",
    "wof:placetype":"venue"
},
  "geometry": {"coordinates":[7.1706027985,46.9008903503],"type":"Point"}
}