{
  "type": "Feature",
  "properties": {
    "iso:country":"CH",
    "sg:address":"7304",
    "sg:city":"Maienfeld",
    "sg:orig_category":"Museen",
    "sg:phone":"+41 81 302 36 26",
    "sg:postcode":"7304",
    "sg:province":"Graubunden",
    "wof:name":"Heididorf Original Heidihausmuseum",
    "wof:placetype":"venue"
},
  "geometry": {"coordinates":[9.531504631,47.0071144104],"type":"Point"}
}