{
  "type": "Feature",
  "properties": {
    "iso:country":"CH",
    "sg:address":"N\u00e4hseydi 6",
    "sg:city":"Buochs",
    "sg:orig_category":"Detailhandel mit Brot, Back U S\u00fcsswaren",
    "sg:phone":"+41 41 620 02 34",
    "sg:postcode":"6374",
    "sg:province":"Nidwalden",
    "wof:name":"B\u00e4ckerei-konditorei Bergamin",
    "wof:placetype":"venue"
},
  "geometry": {"coordinates":[8.41831,46.97871],"type":"Point"}
}