{
  "type": "Feature",
  "properties": {
    "iso:country":"CH",
    "sg:address":"Via Simone Da Locarno 4 6600 Locarno. Postfach",
    "sg:city":"Locarno",
    "sg:orig_category":"Sonstige Vermietung U Verpachtung von eigenen Immobilien Verwaltung von Immobilien",
    "sg:phone":"+41 91 751 22 21",
    "sg:postcode":"6600",
    "sg:province":"Ticino",
    "wof:name":"Amministrazione Sl Immobiliare Di Lappe Stefano",
    "wof:placetype":"venue"
},
  "geometry": {"coordinates":[8.8007354736,46.1676635742],"type":"Point"}
}