{
  "type": "Feature",
  "properties": {
    "iso:country":"CH",
    "sg:address":"Rte De Baumaroche 28 Le Mont-p\u00e9lerin",
    "sg:city":"Chardonne",
    "sg:orig_category":"Grosshandel mit Nahrungsmitteln, Getr\u00e4nken U Tabakwaren ohne ausgepr\u00e4gten Schwerpunkt",
    "sg:postcode":"1803",
    "sg:province":"Vaud",
    "wof:name":"Dupraz-neyroud Andr\u00e9 Et Marl\u00e8ne",
    "wof:placetype":"venue"
},
  "geometry": {"coordinates":[6.8272252083,46.4760360718],"type":"Point"}
}