{
  "type": "Feature",
  "properties": {
    "iso:country":"CH",
    "sg:address":"Route Du Vanel 21",
    "sg:city":"Geneveys-coffrane",
    "sg:orig_category":"Wohnheime",
    "sg:postcode":"2206",
    "sg:province":"Neuch\u00e2tel",
    "wof:name":"Le Pivert, Kerboull Elisabeth",
    "wof:placetype":"venue"
},
  "geometry": {"coordinates":[6.8520288467,47.0180435181],"type":"Point"}
}