{
  "type": "Feature",
  "properties": {
    "iso:country":"CH",
    "sg:address":"Niesenweg 4",
    "sg:city":"Bern",
    "sg:orig_category":"\u00dcbersetzungsb\u00fcros",
    "sg:phone":"+41 31 301 11 78",
    "sg:postcode":"3012",
    "sg:province":"Bern",
    "wof:name":"Traducta Sa",
    "wof:placetype":"venue"
},
  "geometry": {"coordinates":[7.4294271469,46.9493408203],"type":"Point"}
}