{
  "type": "Feature",
  "properties": {
    "iso:country":"CH",
    "sg:address":"Mettlenbachstrasse 17 8617 M\u00f6nchaltorf. Postfach",
    "sg:city":"M\u00f6nchaltorf",
    "sg:orig_category":"Herstellung von Konstruktionsteilen, Fertigbauteilen U Ausbauelementen aus Holz Innenausbau",
    "sg:phone":"+41 19482460",
    "sg:postcode":"8617",
    "sg:province":"Z\u00fcrich",
    "wof:name":"Schreinerei Koch Anton Holzarbeiten, Bes. Im Bereich Des Innenausbaus U. M\u00f6belbaus",
    "wof:placetype":"venue"
},
  "geometry": {"coordinates":[8.7211742401,47.3031272888],"type":"Point"}
}