{
  "type": "Feature",
  "properties": {
    "iso:country":"CH",
    "sg:address":"Rue Du Midi 14",
    "sg:city":"Moutier",
    "sg:orig_category":"Detailhandel mit Radio U Fernsehger\u00e4ten Fernmeldedienste",
    "sg:phone":"+41 32 494 60 90",
    "sg:postcode":"2740",
    "sg:province":"Bern",
    "wof:name":"Ross\u00e9 T\u00e9l\u00e9communications Sa",
    "wof:placetype":"venue"
},
  "geometry": {"coordinates":[7.3747239113,47.2783699036],"type":"Point"}
}