{
  "type": "Feature",
  "properties": {
    "iso:country":"CH",
    "sg:address":"1405",
    "sg:city":"Pomy",
    "sg:orig_category":"Zimmerei, Dachdeckerei, Bauspenglerei U Abdichtung Zimmerei, Ingenieurholzbau",
    "sg:phone":"+41 24 425 51 50",
    "sg:postcode":"1405",
    "sg:province":"Vaud",
    "wof:name":"Favre Sa Charpente-couverture",
    "wof:placetype":"venue"
},
  "geometry": {"coordinates":[6.6688499451,46.7578010559],"type":"Point"}
}