{
  "type": "Feature",
  "properties": {
    "iso:country":"CH",
    "sg:address":"Rothausstrasse 15",
    "sg:city":"Muttenz",
    "sg:orig_category":"Kauf U Verkauf von Immobilien auf eigene Rechnung",
    "sg:postcode":"4132",
    "sg:province":"Basel-Landschaft",
    "wof:name":"Im Gstr\u00fcpf Ag",
    "wof:placetype":"venue"
},
  "geometry": {"coordinates":[7.6561441422,47.5257797241],"type":"Point"}
}