{
  "type": "Feature",
  "properties": {
    "iso:country":"CH",
    "sg:address":"Kirchbergstrasse 207",
    "sg:city":"Burgdorf",
    "sg:orig_category":"Detailhandel mit B\u00fcromaschinen U einrichtungen Grosshandel mit B\u00fcromaschinen U einrichtungen",
    "sg:phone":"+41 34 422 01 59",
    "sg:postcode":"3400",
    "sg:province":"Bern",
    "wof:name":"B\u00fcrom\u00f6bel Buchmatt Helga Fankhauser",
    "wof:placetype":"venue"
},
  "geometry": {"coordinates":[7.605241,47.066917],"type":"Point"}
}