{
  "type": "Feature",
  "properties": {
    "iso:country":"CH",
    "sg:address":"K\u00f6schenr\u00fctistrasse 17",
    "sg:city":"Z\u00fcrich",
    "sg:orig_category":"Sportvereine Ski",
    "sg:postcode":"8052",
    "sg:province":"Z\u00fcrich",
    "wof:name":"Ski-& Bergclub Tv Seebach",
    "wof:placetype":"venue"
},
  "geometry": {"coordinates":[8.5377521515,47.4238357544],"type":"Point"}
}