{
  "type": "Feature",
  "properties": {
    "iso:country":"CH",
    "sg:address":"Neuhofstrasse 4",
    "sg:city":"Baar",
    "sg:orig_category":"Detailhandel mit Waren verschiedener Art, Hauptrichtung Nahrungsmittel",
    "sg:phone":"+41 41 768 77 33",
    "sg:postcode":"6340",
    "sg:province":"Zug",
    "wof:name":"L\u00fcn Ag",
    "wof:placetype":"venue"
},
  "geometry": {"coordinates":[8.5136909485,47.1903457642],"type":"Point"}
}