{
  "type": "Feature",
  "properties": {
    "iso:country":"CH",
    "sg:address":"Haute-nendaz",
    "sg:city":"Haute-nendaz",
    "sg:orig_category":"RESTAURANTS: TEA-ROOMS",
    "sg:phone":"+41 27 288 10 14",
    "sg:postcode":"1997",
    "sg:province":"Valais",
    "wof:name":"Fournier Jean-paul",
    "wof:placetype":"venue"
},
  "geometry": {"coordinates":[7.3364601135,46.1857681274],"type":"Point"}
}