{
  "type": "Feature",
  "properties": {
    "iso:country":"CH",
    "sg:address":"Baarerstrasse 69 6300 Zug. Postfach 2070",
    "sg:city":"Zug",
    "sg:orig_category":"Grosshandel mit Nahrungsmitteln, Getr\u00e4nken U Tabakwaren Sonstiger Grosshandel",
    "sg:phone":"+41 41 710 36 07",
    "sg:postcode":"6302",
    "sg:province":"Zug",
    "wof:name":"Vegoil Trading Company Ltd",
    "wof:placetype":"venue"
},
  "geometry": {"coordinates":[8.5175647736,47.1766815186],"type":"Point"}
}