{
  "type": "Feature",
  "properties": {
    "iso:country":"CH",
    "sg:address":"Limmatstrasse 285 8005 Z\u00fcrich. Postfach 561",
    "sg:city":"Z\u00fcrich",
    "sg:orig_category":"Mechanik Mechanische Werkst\u00e4tten",
    "sg:phone":"+41 12710244",
    "sg:postcode":"8037",
    "sg:province":"Z\u00fcrich",
    "wof:name":"Culatti Ag",
    "wof:placetype":"venue"
},
  "geometry": {"coordinates":[8.5247125626,47.3890380859],"type":"Point"}
}