{
  "type": "Feature",
  "properties": {
    "iso:country":"CH",
    "sg:address":"Schaubernstrasse 2",
    "sg:city":"Geuensee",
    "sg:orig_category":"Grosshandel mit Fleisch U Fleischwaren Grosshandel mit sonstigen Nahrungsmitteln",
    "sg:phone":"+41 41 926 37 37",
    "sg:postcode":"6232",
    "sg:province":"Luzern",
    "wof:name":"Viaca Ag Fleisch-& Wurstwaren Engros",
    "wof:placetype":"venue"
},
  "geometry": {"coordinates":[8.1041202545,47.195110321],"type":"Point"}
}