{
  "type": "Feature",
  "properties": {
    "addr:full":"Villnachern Villnachern Aargau 5213",
    "addr:postcode":"5213",
    "iso:country":"CH",
    "sg:address":"Villnachern",
    "sg:city":"Villnachern",
    "sg:classifiers":[
        {
            "category":"Banks & Credit Unions",
            "subcategory":"Bank",
            "type":"Services"
        }
    ],
    "sg:phone":"+41 56411452",
    "sg:postcode":"5213",
    "sg:province":"Aargau",
    "wof:name":"Neue Aargauer Bank",
    "wof:placetype":"venue"
},
  "geometry": {"coordinates":[8.16285,47.470081],"type":"Point"}
}