{
  "type": "Feature",
  "properties": {
    "iso:country":"CH",
    "sg:address":"Ueberlandstrasse 289",
    "sg:city":"Z\u00fcrich",
    "sg:orig_category":"Aktivit\u00e4ten der Generalunternehmen im Baugewerbe Allgemeiner Hoch U Tiefbau",
    "sg:phone":"+41 13213044",
    "sg:postcode":"8051",
    "sg:province":"Z\u00fcrich",
    "wof:name":"Petra Planung Ag",
    "wof:placetype":"venue"
},
  "geometry": {"coordinates":[8.577196,47.40955],"type":"Point"}
}