{
  "type": "Feature",
  "properties": {
    "iso:country":"CH",
    "sg:address":"Steinstrasse 21",
    "sg:city":"Z\u00fcrich",
    "sg:orig_category":"Non-Classified Establishments",
    "sg:phone":"+41 12624222",
    "sg:postcode":"8003",
    "sg:province":"Z\u00fcrich",
    "wof:name":"Catpics Ag",
    "wof:placetype":"venue"
},
  "geometry": {"coordinates":[8.5198450089,47.3681640625],"type":"Point"}
}