{
  "type": "Feature",
  "properties": {
    "iso:country":"CH",
    "sg:address":"Gottardo Via San 134",
    "sg:city":"Balerna",
    "sg:orig_category":"Non-Classified Establishments",
    "sg:postcode":"6828",
    "sg:province":"Ticino",
    "wof:name":"Fritma Sa",
    "wof:placetype":"venue"
},
  "geometry": {"coordinates":[9.0037345886,45.8518981934],"type":"Point"}
}