{
  "type": "Feature",
  "properties": {
    "iso:country":"CH",
    "sg:address":"Rue De L'industrie 129",
    "sg:city":"Courtaman",
    "sg:orig_category":"Einzelhandel mit Automobilteilen U Zubeh\u00f6r Herstellung von Tanks U Sammelbeh\u00e4ltern aus Metall",
    "sg:phone":"+41 26 684 80 80",
    "sg:postcode":"1791",
    "sg:province":"Fribourg",
    "wof:name":"Migrol St\u00e9 Coop\u00e9rative",
    "wof:placetype":"venue"
},
  "geometry": {"coordinates":[7.1273441315,46.8725852966],"type":"Point"}
}