{
  "type": "Feature",
  "properties": {
    "iso:country":"CH",
    "sg:address":"Heuerweg 1",
    "sg:city":"Dottikon",
    "sg:orig_category":"Herstellung von sonstigen elektrischen Ausr\u00fcstungen",
    "sg:postcode":"5605",
    "sg:province":"Aargau",
    "wof:name":"Mero, R\u00fctimann R.",
    "wof:placetype":"venue"
},
  "geometry": {"coordinates":[8.2385463715,47.3806228638],"type":"Point"}
}