{
  "type": "Feature",
  "properties": {
    "iso:country":"CH",
    "sg:address":"Grand-rue 68",
    "sg:city":"Montreux",
    "sg:orig_category":"Detailhandel mit Schuhen",
    "sg:phone":"+41 21 963 39 39",
    "sg:postcode":"1820",
    "sg:province":"Vaud",
    "wof:name":"Bally Schuhfabriken Ag",
    "wof:placetype":"venue"
},
  "geometry": {"coordinates":[6.9096441269,46.4357414246],"type":"Point"}
}