{
  "type": "Feature",
  "properties": {
    "iso:country":"CH",
    "sg:address":"Eichwaldstrasse 13 6005 Luzern. Postfach",
    "sg:city":"Luzern",
    "sg:classifiers":[
        {
            "category":"Education",
            "subcategory":"Library",
            "type":"Public Place"
        }
    ],
    "sg:phone":"+41 41 320 51 67",
    "sg:postcode":"6002",
    "sg:province":"Luzern",
    "sg:tags":[
        "u",
        "bibliotheken",
        "archive"
    ],
    "wof:name":"Bibliothek D.gewerbeverbandes Des Kantons Luzern",
    "wof:placetype":"venue"
},
  "geometry": {"coordinates":[8.300905,47.038277],"type":"Point"}
}