{
  "type": "Feature",
  "properties": {
    "iso:country":"CH",
    "sg:address":"Stadtturmstrasse 10 5400 Baden. Postfach",
    "sg:city":"Baden",
    "sg:orig_category":"Versicherungen Generalagenturen",
    "sg:phone":"+41 56 203 75 75",
    "sg:postcode":"5401",
    "sg:province":"Aargau",
    "wof:name":"Basler Versicherungen Generalagentur",
    "wof:placetype":"venue"
},
  "geometry": {"coordinates":[8.3057947159,47.4759101868],"type":"Point"}
}