{
  "type": "Feature",
  "properties": {
    "iso:country":"CH",
    "sg:address":"M\u00fchlestrasse 15",
    "sg:city":"Thierachern",
    "sg:orig_category":"G\u00fcterbef\u00f6rderung im Strassenverkehr",
    "sg:phone":"+41 33 345 33 58",
    "sg:postcode":"3634",
    "sg:province":"Bern",
    "wof:name":"Josef Matzinger Fuhrhalterei & Tiertransporte",
    "wof:placetype":"venue"
},
  "geometry": {"coordinates":[7.5768461227,46.7526016235],"type":"Point"}
}