{
  "type": "Feature",
  "properties": {
    "iso:country":"CH",
    "sg:address":"Binenweg 2",
    "sg:city":"Naters",
    "sg:orig_category":"Fachdetailhandel in Verkaufsr\u00e4umen",
    "sg:phone":"+41 26 927 28 44",
    "sg:postcode":"3904",
    "sg:province":"Valais",
    "wof:name":"Golf Services & Technologies Fa Sa",
    "wof:placetype":"venue"
},
  "geometry": {"coordinates":[7.1595897675,46.6244392395],"type":"Point"}
}