{
  "type": "Feature",
  "properties": {
    "iso:country":"CH",
    "sg:address":"Rheinstrasse 81",
    "sg:city":"Chur",
    "sg:orig_category":"Mechanische Werkst\u00e4tten",
    "sg:phone":"+41 81 284 62 24",
    "sg:postcode":"7000",
    "sg:province":"Graubunden",
    "wof:name":"Guido Mazzetta Elektromechanische Werkstatt",
    "wof:placetype":"venue"
},
  "geometry": {"coordinates":[9.5204982758,46.8558387756],"type":"Point"}
}