{
  "type": "Feature",
  "properties": {
    "iso:country":"CH",
    "sg:address":"Bollstrasse 3076 Bangerten B. Worb. Postfach",
    "sg:city":"Worb",
    "sg:orig_category":"Wohnheime",
    "sg:postcode":"3076",
    "sg:province":"Bern",
    "wof:name":"Familienheimgenossenschaft Worb",
    "wof:placetype":"venue"
},
  "geometry": {"coordinates":[7.5580430031,46.9397926331],"type":"Point"}
}