{
  "type": "Feature",
  "properties": {
    "iso:country":"CH",
    "sg:address":"Fort-barreau Rue Du 29 1201 Gen\u00e8ve. Postfach",
    "sg:city":"Gen\u00e8ve",
    "sg:orig_category":"Reinigungsgewerbe",
    "sg:postcode":"1201",
    "sg:province":"Gen\u00e8ve",
    "wof:name":"Mn Nettoyages Sarl",
    "wof:placetype":"venue"
},
  "geometry": {"coordinates":[6.138625145,46.2118606567],"type":"Point"}
}