{
  "type": "Feature",
  "properties": {
    "iso:country":"CH",
    "sg:address":"Pavillonweg 3",
    "sg:city":"Bern",
    "sg:orig_category":"Interessenvertretungen U sonstige Vereinigungen",
    "sg:phone":"+41 31 301 43 43",
    "sg:postcode":"3012",
    "sg:province":"Bern",
    "wof:name":"Schweizer Unterwassersport- Verband Susv",
    "wof:placetype":"venue"
},
  "geometry": {"coordinates":[7.4340209961,46.9491195679],"type":"Point"}
}