{
  "type": "Feature",
  "properties": {
    "iso:country":"CH",
    "sg:address":"Unterbach 175",
    "sg:city":"Trogen",
    "sg:orig_category":"Vereine Musik/Blasmusik",
    "sg:phone":"+41 71 344 35 11",
    "sg:postcode":"9043",
    "sg:province":"Appenzell Ausserrhoden",
    "wof:name":"Musikgesellschaft Trogen",
    "wof:placetype":"venue"
},
  "geometry": {"coordinates":[9.4544363022,47.4016227722],"type":"Point"}
}