{
  "type": "Feature",
  "properties": {
    "addr:full":"Oberer Steisteg 6 6430 Schwyz. Postfach 356 Schwyz Schwyz 6431",
    "addr:housenumber":"6;356",
    "addr:postcode":"6430;6431",
    "addr:street":"Oberer Steisteg;Postfach",
    "iso:country":"CH",
    "sg:address":"Oberer Steisteg 6 6430 Schwyz. Postfach 356",
    "sg:city":"Schwyz",
    "sg:orig_category":"Detailhandel mit Brillen U anderen Sehhilfen Fachdetailhandel in Verkaufsr\u00e4umen",
    "sg:phone":"+41 32 912 56 56",
    "sg:postcode":"6431",
    "sg:province":"Schwyz",
    "wof:name":"Oberli Opticiens J.-l.gonzalez S\u00e0rl",
    "wof:placetype":"venue"
},
  "geometry": {"coordinates":[6.830017,47.102558],"type":"Point"}
}