{
  "type": "Feature",
  "properties": {
    "iso:country":"CH",
    "sg:address":"Bahnhofstrasse 1 8001 Z\u00fcrich. Postfach 4639",
    "sg:city":"Z\u00fcrich",
    "sg:orig_category":"Unclassifiable Establishments",
    "sg:phone":"+41 22 819 21 11",
    "sg:postcode":"8022",
    "sg:province":"Z\u00fcrich",
    "wof:name":"Union Bancaire Privee, Ubp",
    "wof:placetype":"venue"
},
  "geometry": {"coordinates":[6.1515679359,46.2032203674],"type":"Point"}
}