{
  "type": "Feature",
  "properties": {
    "iso:country":"CH",
    "sg:address":"Bielstrasse 11 3250 Lyss. Postfach",
    "sg:city":"Lyss",
    "sg:orig_category":"Detailhandel mit Bekleidung Detailhandel mit Damenbekleidung",
    "sg:phone":"+41 32 384 11 75",
    "sg:postcode":"3250",
    "sg:province":"Bern",
    "wof:name":"Mode B\u00fcchler, Lyss",
    "wof:placetype":"venue"
},
  "geometry": {"coordinates":[7.305532,47.074993],"type":"Point"}
}