{
  "type": "Feature",
  "properties": {
    "addr:full":"Rue De Crissier 9 Renens Vaud 1020",
    "addr:housenumber":"9",
    "addr:postcode":"1020",
    "addr:street":"Rue De Crissier",
    "iso:country":"CH",
    "sg:address":"Rue De Crissier 9",
    "sg:city":"Renens",
    "sg:classifiers":[
        {
            "category":"Building & Trades",
            "subcategory":"Construction",
            "type":"Services"
        }
    ],
    "sg:phone":"+41 21 634 37 91",
    "sg:postcode":"1020",
    "sg:province":"Vaud",
    "sg:tags":[
        "industry",
        "air-conditioning",
        "system"
    ],
    "wof:name":"Climatec Renens Sa",
    "wof:placetype":"venue"
},
  "geometry": {"coordinates":[6.579232,46.538818],"type":"Point"}
}