{
  "type": "Feature",
  "properties": {
    "iso:country":"CH",
    "sg:address":"Route Du Nant-d'avril 12",
    "sg:city":"Vernier",
    "sg:orig_category":"Bauschreinerei Herstellung von M\u00f6beln verschiedener Art",
    "sg:phone":"+41 21 845 58 92",
    "sg:postcode":"1214",
    "sg:province":"Gen\u00e8ve",
    "wof:name":"Meylan Pierre",
    "wof:placetype":"venue"
},
  "geometry": {"coordinates":[6.231002,46.605251],"type":"Point"}
}