{
  "type": "Feature",
  "properties": {
    "iso:country":"CH",
    "sg:address":"6373 Ennetb\u00fcrgen. Postfach",
    "sg:city":"Ennetb\u00fcrgen",
    "sg:orig_category":"Pensionskassen",
    "sg:postcode":"6373",
    "sg:province":"Nidwalden",
    "wof:name":"Personalstiftung Der Firma Dr. Sigrist Ag Messger\u00e4tebau",
    "wof:placetype":"venue"
},
  "geometry": {"coordinates":[8.4138898849,46.9846916199],"type":"Point"}
}