{
  "type": "Feature",
  "properties": {
    "iso:country":"CH",
    "sg:address":"Rue Des Evaux 5 1213 Onex. Postfach",
    "sg:city":"Onex",
    "sg:orig_category":"Sanit\u00e4r, Heizungs U L\u00fcftungsinstallation",
    "sg:postcode":"1213",
    "sg:province":"Gen\u00e8ve",
    "wof:name":"Suriano Roberto",
    "wof:placetype":"venue"
},
  "geometry": {"coordinates":[6.1010007858,46.1896743774],"type":"Point"}
}