{
  "type": "Feature",
  "properties": {
    "iso:country":"CH",
    "sg:address":"Hinterdorfstrasse 26",
    "sg:city":"Dintikon",
    "sg:orig_category":"Instandhaltung U Reparatur von Automobilen",
    "sg:phone":"+41 18501030",
    "sg:postcode":"5606",
    "sg:province":"Aargau",
    "wof:name":"Meier Eugen",
    "wof:placetype":"venue"
},
  "geometry": {"coordinates":[8.5043497086,47.4799613953],"type":"Point"}
}