{
  "type": "Feature",
  "properties": {
    "iso:country":"CH",
    "sg:address":"Hangstrasse 9",
    "sg:city":"Lengnau",
    "sg:classifiers":[
        {
            "category":"Banks & Credit Unions",
            "subcategory":"Investment Brokerage",
            "type":"Services"
        }
    ],
    "sg:phone":"+41 56 241 16 72",
    "sg:postcode":"5426",
    "sg:province":"Aargau",
    "sg:tags":[
        "batteries",
        "primary",
        "secondary"
    ],
    "wof:name":"Elektro-technik Anselm Lorenzi",
    "wof:placetype":"venue"
},
  "geometry": {"coordinates":[8.326768,47.518078],"type":"Point"}
}