{
  "type": "Feature",
  "properties": {
    "iso:country":"CH",
    "sg:address":"Rue Du Temple 7 2105 Travers Case Postale 71",
    "sg:city":"Travers",
    "sg:orig_category":"Vorschulen, Kinderg\u00e4rten",
    "sg:postcode":"2105",
    "sg:province":"Neuch\u00e2tel",
    "wof:name":"Jardin D'enfants Les Marmouzets",
    "wof:placetype":"venue"
},
  "geometry": {"coordinates":[6.6739897728,46.9401092529],"type":"Point"}
}