{
  "type": "Feature",
  "properties": {
    "iso:country":"CH",
    "sg:address":"Rue St-s\u00e9bastien 4",
    "sg:city":"Del\u00e9mont",
    "sg:orig_category":"Einzelhandel mit Automobilen Instandhaltung U Reparatur von Automobilen",
    "sg:phone":"+41 32 423 11 10",
    "sg:postcode":"2800",
    "sg:province":"Jura",
    "wof:name":"Garage Et Carrosserie Du Rallye Sa",
    "wof:placetype":"venue"
},
  "geometry": {"coordinates":[7.3415389061,47.3546028137],"type":"Point"}
}