{
  "type": "Feature",
  "properties": {
    "iso:country":"CH",
    "sg:address":"Furtbachweg 54",
    "sg:city":"Wallisellen",
    "sg:orig_category":"Fussreflexzonenmassage",
    "sg:phone":"+41 71 244 18 40",
    "sg:postcode":"8304",
    "sg:province":"Z\u00fcrich",
    "wof:name":"Theodora Mis Fussreflexzonen-massage",
    "wof:placetype":"venue"
},
  "geometry": {"coordinates":[9.3962001801,47.4477081299],"type":"Point"}
}