{
  "type": "Feature",
  "properties": {
    "iso:country":"CH",
    "sg:address":"En Novallette",
    "sg:city":"Noville",
    "sg:orig_category":"Instandhaltung U Reparatur von Automobilen",
    "sg:phone":"+41 21 960 33 15",
    "sg:postcode":"1845",
    "sg:province":"Vaud",
    "wof:name":"Garage Fontannaz Manuel",
    "wof:placetype":"venue"
},
  "geometry": {"coordinates":[6.9005651474,46.3829689026],"type":"Point"}
}