{
  "type": "Feature",
  "properties": {
    "iso:country":"CH",
    "sg:address":"Sch\u00fctzenweg 22 3014 Bern. Postfach",
    "sg:city":"Bern",
    "sg:orig_category":"Maler U Glasergewerbe Stukkateurgewerbe, Gipserei U Verputzerei",
    "sg:phone":"+41 31 332 95 11",
    "sg:postcode":"3005",
    "sg:province":"Bern",
    "wof:name":"Malerei Lauper Urs Ag Maler- U. Gipserarbeiten Usw.",
    "wof:placetype":"venue"
},
  "geometry": {"coordinates":[7.4502887726,46.9591712952],"type":"Point"}
}