{
  "type": "Feature",
  "properties": {
    "iso:country":"CH",
    "sg:address":"Ch. De Burquenet 1095 Ch\u00e2telard-lutry. Postfach",
    "sg:city":"Lutry",
    "sg:orig_category":"Non-Classified Establishments",
    "sg:postcode":"1095",
    "sg:province":"Vaud",
    "wof:name":"Si Les Foug\u00e8res Ayent",
    "wof:placetype":"venue"
},
  "geometry": {"coordinates":[7.4068250656,46.2767829895],"type":"Point"}
}