{
  "type": "Feature",
  "properties": {
    "iso:country":"CH",
    "sg:address":"Riefersh\u00e4usernstrasse 18 3415 Hasle B. Burgdorf. Postfach",
    "sg:city":"Hasle-r\u00fcegsau",
    "sg:orig_category":"Fachdetailhandel in Verkaufsr\u00e4umen",
    "sg:phone":"+41 34 461 57 25",
    "sg:postcode":"3415",
    "sg:province":"Bern",
    "wof:name":"Carrer",
    "wof:placetype":"venue"
},
  "geometry": {"coordinates":[7.6589021683,47.012134552],"type":"Point"}
}