{
  "type": "Feature",
  "properties": {
    "iso:country":"CH",
    "sg:address":"Hauptstrasse Unterterzen 8883 Quarten. Postfach",
    "sg:city":"Unterterzen",
    "sg:orig_category":"Handel mit Automobilen",
    "sg:postcode":"8882",
    "sg:province":"St. Gallen",
    "wof:name":"Gubser Martin Garage-spenglerei Ag",
    "wof:placetype":"venue"
},
  "geometry": {"coordinates":[9.2411851883,47.1078948975],"type":"Point"}
}