{
  "type": "Feature",
  "properties": {
    "iso:country":"CH",
    "sg:address":"Obachstr. 10",
    "sg:city":"Solothurn",
    "sg:classifiers":[
        {
            "category":"Building & Trades",
            "subcategory":"Construction",
            "type":"Services"
        }
    ],
    "sg:phone":"+41 32 622 89 12",
    "sg:postcode":"4502",
    "sg:province":"Solothurn",
    "sg:tags":[
        "work",
        "public"
    ],
    "wof:name":"Astrada Ag",
    "wof:placetype":"venue"
},
  "geometry": {"coordinates":[7.53235,47.205379],"type":"Point"}
}