{
  "type": "Feature",
  "properties": {
    "addr:full":"Bruchstrasse 2 Luzern Luzern 6003",
    "addr:housenumber":"2",
    "addr:postcode":"6003",
    "addr:street":"Bruchstrasse",
    "iso:country":"CH",
    "sg:address":"Bruchstrasse 2",
    "sg:city":"Luzern",
    "sg:classifiers":[
        {
            "category":"Utilities",
            "subcategory":"Cable",
            "type":"Services"
        }
    ],
    "sg:phone":"+41 41 240 61 78",
    "sg:postcode":"6003",
    "sg:province":"Luzern",
    "sg:tags":[
        "tv",
        "medien",
        "u",
        "radio"
    ],
    "wof:name":"Etcetera Verlag",
    "wof:placetype":"venue"
},
  "geometry": {"coordinates":[8.298729,47.051586],"type":"Point"}
}