{
  "type": "Feature",
  "properties": {
    "iso:country":"CH",
    "sg:address":"Baumgartenstrasse 13",
    "sg:city":"Urdorf",
    "sg:orig_category":"Kosmetikinstitute",
    "sg:phone":"+41 17351500",
    "sg:postcode":"8902",
    "sg:province":"Z\u00fcrich",
    "wof:name":"Veronique Rosselet Kosmetikinstitut",
    "wof:placetype":"venue"
},
  "geometry": {"coordinates":[8.4214744568,47.3798332214],"type":"Point"}
}