{
  "type": "Feature",
  "properties": {
    "iso:country":"CH",
    "sg:address":"Balconi Via Dei 2",
    "sg:city":"Barbengo",
    "sg:orig_category":"Handel mit Automobilen",
    "sg:postcode":"6917",
    "sg:province":"Ticino",
    "wof:name":"Gysi-automobile Ag",
    "wof:placetype":"venue"
},
  "geometry": {"coordinates":[8.3115491867,46.9846305847],"type":"Point"}
}