{
  "type": "Feature",
  "properties": {
    "iso:country":"CH",
    "sg:address":"Schleitheimerstrasse 21",
    "sg:city":"Beringen",
    "sg:orig_category":"Sportvereine Turnen",
    "sg:phone":"+41 52 685 37 53",
    "sg:postcode":"8222",
    "sg:province":"Schaffhausen",
    "wof:name":"Turnverein Stv Beringen",
    "wof:placetype":"venue"
},
  "geometry": {"coordinates":[8.5712785721,47.6976966858],"type":"Point"}
}