{
  "type": "Feature",
  "properties": {
    "addr:full":"Erlenweg 2 Baden Aargau 5400",
    "addr:housenumber":"2",
    "addr:postcode":"5400",
    "addr:street":"Erlenweg",
    "iso:country":"CH",
    "sg:address":"Erlenweg 2",
    "sg:city":"Baden",
    "sg:orig_category":"Bau U Wohngenossenschaften Erschliessung von Grundst\u00fccken",
    "sg:postcode":"5400",
    "sg:province":"Aargau",
    "wof:name":"Genoss.f\u00fcr Stadtwohnungen Baden",
    "wof:placetype":"venue"
},
  "geometry": {"coordinates":[8.29177,47.47366],"type":"Point"}
}