{
  "type": "Feature",
  "properties": {
    "iso:country":"CH",
    "sg:address":"Dorfstrasse 37",
    "sg:city":"Gebenstorf",
    "sg:orig_category":"Mechanik",
    "sg:postcode":"5412",
    "sg:province":"Aargau",
    "wof:name":"Heinrich Killer Ag",
    "wof:placetype":"venue"
},
  "geometry": {"coordinates":[8.2473783493,47.4779891968],"type":"Point"}
}