{
  "type": "Feature",
  "properties": {
    "iso:country":"CH",
    "sg:address":"Shopping Center Emmen",
    "sg:city":"Emmenbr\u00fccke",
    "sg:orig_category":"Detailhandel mit B\u00fcchern",
    "sg:phone":"+41 41 260 28 27",
    "sg:postcode":"6020",
    "sg:province":"Luzern",
    "wof:name":"Buch Shopping Ag",
    "wof:placetype":"venue"
},
  "geometry": {"coordinates":[8.275493,47.078087],"type":"Point"}
}