{
  "type": "Feature",
  "properties": {
    "iso:country":"CH",
    "sg:address":"Br\u00fcggliacher 8",
    "sg:city":"Oberrohrdorf",
    "sg:orig_category":"Erschliessung von Grundst\u00fccken",
    "sg:postcode":"5452",
    "sg:province":"Aargau",
    "wof:name":"Wogea",
    "wof:placetype":"venue"
},
  "geometry": {"coordinates":[8.3130331039,47.4213867188],"type":"Point"}
}