{
  "type": "Feature",
  "properties": {
    "iso:country":"CH",
    "sg:address":"Chemin Du Clo\u00eetre-de-l\u00e0 26-28",
    "sg:city":"Aigle",
    "sg:orig_category":"Detailhandel mit Computern U Software Softwareentwicklung U beratung",
    "sg:phone":"+41 71 912 34 80",
    "sg:postcode":"1860",
    "sg:province":"Vaud",
    "wof:name":"Autesca Informatik",
    "wof:placetype":"venue"
},
  "geometry": {"coordinates":[9.046934,47.465443],"type":"Point"}
}