{
  "type": "Feature",
  "properties": {
    "iso:country":"CH",
    "sg:address":"1926",
    "sg:city":"Fully",
    "sg:orig_category":"Sanit\u00e4r, Heizungs U L\u00fcftungsinstallation",
    "sg:phone":"+41 27 746 12 32",
    "sg:postcode":"1926",
    "sg:province":"Valais",
    "wof:name":"Carron-lugon-chauffage-sanitaire Sa",
    "wof:placetype":"venue"
},
  "geometry": {"coordinates":[7.119784832,46.1373138428],"type":"Point"}
}