{
  "type": "Feature",
  "properties": {
    "iso:country":"CH",
    "sg:address":"Chemin Byron 15",
    "sg:city":"Presinge",
    "sg:classifiers":[
        {
            "category":"Travel",
            "subcategory":"Hotels & Motels",
            "type":"Entertainment"
        }
    ],
    "sg:phone":"+41 22 759 21 19",
    "sg:postcode":"1243",
    "sg:province":"Gen\u00e8ve",
    "sg:tags":[
        "hotels",
        "mit",
        "restaurant"
    ],
    "wof:name":"Montagrin Liliane",
    "wof:placetype":"venue"
},
  "geometry": {"coordinates":[6.2551198006,46.2195396423],"type":"Point"}
}