{
  "type": "Feature",
  "properties": {
    "iso:country":"CH",
    "sg:address":"Burghofstrasse 40",
    "sg:city":"Dielsdorf",
    "sg:orig_category":"Gartenbau Geb\u00e4ude, Wohnungsreinigung",
    "sg:phone":"+41 17413938",
    "sg:postcode":"8157",
    "sg:province":"Z\u00fcrich",
    "wof:name":"Abc Team Ag",
    "wof:placetype":"venue"
},
  "geometry": {"coordinates":[8.444026947,47.4714431763],"type":"Point"}
}