{
  "type": "Feature",
  "properties": {
    "iso:country":"CH",
    "sg:address":"Calas Avenue 20 1206 Gen\u00e8ve. Postfach",
    "sg:city":"Gen\u00e8ve",
    "sg:orig_category":"Grosshandel mit sonstigen Gebrauchs U Verbrauchsg\u00fctern",
    "sg:postcode":"1206",
    "sg:province":"Gen\u00e8ve",
    "wof:name":"Herrera Fr\u00e8res S\u00e0rl",
    "wof:placetype":"venue"
},
  "geometry": {"coordinates":[6.1543979645,46.1891403198],"type":"Point"}
}