{
  "type": "Feature",
  "properties": {
    "iso:country":"CH",
    "sg:address":"Rue Abb\u00e9-monnin 24",
    "sg:city":"Bassecourt",
    "sg:orig_category":"Detailhandel mit Zeitungen U Zeitschriften Kioske",
    "sg:phone":"+41 32 426 52 15",
    "sg:postcode":"2854",
    "sg:province":"Jura",
    "wof:name":"Kiosque Central",
    "wof:placetype":"venue"
},
  "geometry": {"coordinates":[7.2464752197,47.3372383118],"type":"Point"}
}