{
  "type": "Feature",
  "properties": {
    "addr:full":"Ifangstrasse 12 8603 Schwerzenbach. Postfach Schwerzenbach Z\u00fcrich 8603",
    "addr:housenumber":"12",
    "addr:postcode":"8603 schwerzenbach. postfach;8603",
    "addr:street":"Ifangstrasse",
    "iso:country":"CH",
    "sg:address":"Ifangstrasse 12 8603 Schwerzenbach. Postfach",
    "sg:city":"Schwerzenbach",
    "sg:orig_category":"Autogaragen Autospenglereien",
    "sg:phone":"+41 18255129",
    "sg:postcode":"8603",
    "sg:province":"Z\u00fcrich",
    "wof:name":"Guido Stirnemann Garage & Spenglerei",
    "wof:placetype":"venue"
},
  "geometry": {"coordinates":[8.663134,47.383125],"type":"Point"}
}