{
  "type": "Feature",
  "properties": {
    "iso:country":"CH",
    "sg:address":"L\u00f6wenstrasse 16",
    "sg:city":"Kreuzlingen",
    "sg:orig_category":"Spring Contact Pins For Testing Printed Circuits Boards",
    "sg:phone":"+41 71 672 58 92",
    "sg:postcode":"8280",
    "sg:province":"Thurgau",
    "wof:name":"Ingun Ag",
    "wof:placetype":"venue"
},
  "geometry": {"coordinates":[9.171790123,47.6478843689],"type":"Point"}
}