{
  "type": "Feature",
  "properties": {
    "iso:country":"CH",
    "sg:address":"Via Adamini 20",
    "sg:city":"Lugano",
    "sg:orig_category":"Detailhandel mit elektrischen Haushalts-,Radio U Fernsehger\u00e4ten sowie Musikinstrumenten",
    "sg:postcode":"6900",
    "sg:province":"Ticino",
    "wof:name":"Swelen Sa.",
    "wof:placetype":"venue"
},
  "geometry": {"coordinates":[8.9446401596,45.9980697632],"type":"Point"}
}