{
  "type": "Feature",
  "properties": {
    "iso:country":"CH",
    "sg:address":"Constant Galeries B.- 1 1003 Lausanne. Postfach",
    "sg:city":"Lausanne",
    "sg:orig_category":"Sonstige pers\u00f6nliche Dienstleistungen",
    "sg:phone":"+41 55 415 68 88",
    "sg:postcode":"1003",
    "sg:province":"Vaud",
    "wof:name":"Syntrade Ag",
    "wof:placetype":"venue"
},
  "geometry": {"coordinates":[8.7755222321,47.2052307129],"type":"Point"}
}