{
  "type": "Feature",
  "properties": {
    "addr:full":"Unterbiel 66 Reigoldswil Basel-Landschaft 4418",
    "addr:housenumber":"66",
    "addr:postcode":"4418",
    "addr:street":"Unterbiel",
    "iso:country":"CH",
    "sg:address":"Unterbiel 66",
    "sg:city":"Reigoldswil",
    "sg:classifiers":[
        {
            "category":"Government",
            "subcategory":"Post Office",
            "type":"Public Place"
        }
    ],
    "sg:phone":"+41 61 941 16 22",
    "sg:postcode":"4418",
    "sg:province":"Basel-Landschaft",
    "sg:tags":[
        "blade",
        "saw",
        "circular"
    ],
    "wof:name":"Rigold Werkzeugsch\u00e4rferei & Werkzeu Ghandel",
    "wof:placetype":"venue"
},
  "geometry": {"coordinates":[7.691036,47.40163],"type":"Point"}
}