{
  "type": "Feature",
  "properties": {
    "iso:country":"CH",
    "sg:address":"Tschachenstrasse 9",
    "sg:city":"Bilten",
    "sg:classifiers":[
        {
            "category":"Structure",
            "subcategory":"Bridge",
            "type":"Public Place"
        }
    ],
    "sg:phone":"+41 55 619 60 90",
    "sg:postcode":"8865",
    "sg:province":"Glarus",
    "sg:tags":[
        "construction"
    ],
    "wof:name":"Toneatti Ag",
    "wof:placetype":"venue"
},
  "geometry": {"coordinates":[9.029232,47.15324],"type":"Point"}
}