{
  "type": "Feature",
  "properties": {
    "iso:country":"CH",
    "sg:address":"Hauptstrasse 1151",
    "sg:city":"Wildhaus",
    "sg:orig_category":"Detailhandel mit Textilien Verlegen von Fussboden",
    "sg:phone":"+41 71 994 21 55",
    "sg:postcode":"9658",
    "sg:province":"St. Gallen",
    "wof:name":"Ferdi Berlinger Innenausstattung",
    "wof:placetype":"venue"
},
  "geometry": {"coordinates":[9.3415031433,47.2019233704],"type":"Point"}
}