{
  "type": "Feature",
  "properties": {
    "iso:country":"CH",
    "sg:address":"Hanfrose 16",
    "sg:city":"Z\u00fcrich",
    "sg:orig_category":"Herstellung von sonstigen elektrischen Ausr\u00fcstungen",
    "sg:postcode":"8055",
    "sg:province":"Z\u00fcrich",
    "wof:name":"Soltech Kaeser Elektron. Sicherungs- U. Versorgungstechnik; Entwicklung U. Verkauf",
    "wof:placetype":"venue"
},
  "geometry": {"coordinates":[8.5094251633,47.3673248291],"type":"Point"}
}