{
  "type": "Feature",
  "properties": {
    "iso:country":"CH",
    "sg:address":"Hochgasse 1",
    "sg:city":"Trimbach",
    "sg:orig_category":"G\u00fcterbef\u00f6rderung im Strassenverkehr",
    "sg:postcode":"4632",
    "sg:province":"Solothurn",
    "wof:name":"Risch Muldenservice",
    "wof:placetype":"venue"
},
  "geometry": {"coordinates":[9.4626941681,47.169380188],"type":"Point"}
}