{
  "type": "Feature",
  "properties": {
    "addr:full":"Zugerbergstr. 46 Zug Zug 6300",
    "addr:housenumber":"46",
    "addr:postcode":"6300",
    "addr:street":"Zugerbergstr.;Zug",
    "iso:country":"CH",
    "sg:address":"Zugerbergstr. 46",
    "sg:city":"Zug",
    "sg:classifiers":[
        {
            "category":"Travel",
            "subcategory":"Hotels & Motels",
            "type":"Entertainment"
        }
    ],
    "sg:phone":"+41 41 711 28 21",
    "sg:postcode":"6300",
    "sg:province":"Zug",
    "sg:tags":[
        "hotels",
        "business",
        "restaurant"
    ],
    "wof:name":"Hotel-restaurant Guggital",
    "wof:placetype":"venue"
},
  "geometry": {"coordinates":[8.518867,47.156971],"type":"Point"}
}