{
  "type": "Feature",
  "properties": {
    "iso:country":"CH",
    "sg:address":"Zopfgasse 17 5603 Staufen. Postfach 49",
    "sg:city":"Staufen",
    "sg:orig_category":"Herstellung von Betonerzeugnissen f\u00fcr den Bau Herstellung von sonstigen Produkten aus nichtmetallisc",
    "sg:phone":"+41 62 891 20 35",
    "sg:postcode":"5603",
    "sg:province":"Aargau",
    "wof:name":"Beat Zuckschwerdt Kunststeinwerk",
    "wof:placetype":"venue"
},
  "geometry": {"coordinates":[8.169131279,47.3802185059],"type":"Point"}
}