{
  "type": "Feature",
  "properties": {
    "iso:country":"CH",
    "sg:address":"Roosstrasse 40",
    "sg:city":"Regensdorf",
    "sg:classifiers":[
        {
            "category":"Restaurant",
            "type":"Food & Drink"
        }
    ],
    "sg:phone":"+41 18405407",
    "sg:postcode":"8105",
    "sg:province":"Z\u00fcrich",
    "wof:name":"Freizeitanlage Regensdorf Restaurant",
    "wof:placetype":"venue"
},
  "geometry": {"coordinates":[8.4714717865,47.4315071106],"type":"Point"}
}