{
  "type": "Feature",
  "properties": {
    "iso:country":"CH",
    "sg:address":"Tschalun 8",
    "sg:city":"Schwyz",
    "sg:orig_category":"Detailhandel mit Musikinstrumenten",
    "sg:phone":"+41 55 240 82 32",
    "sg:postcode":"6430",
    "sg:province":"Schwyz",
    "wof:name":"Martin Rettenmund Musikhaus",
    "wof:placetype":"venue"
},
  "geometry": {"coordinates":[8.8425273895,47.2597694397],"type":"Point"}
}