{
  "type": "Feature",
  "properties": {
    "iso:country":"CH",
    "sg:address":"Hauptstrasse 30",
    "sg:city":"Rorschach",
    "sg:orig_category":"Arztpraxen",
    "sg:phone":"+41 71 841 59 16",
    "sg:postcode":"9400",
    "sg:province":"St. Gallen",
    "wof:name":"Dr.med.manoutch Nakhostin Spezialarzt Fmh",
    "wof:placetype":"venue"
},
  "geometry": {"coordinates":[9.495236,47.47802],"type":"Point"}
}