{
  "type": "Feature",
  "properties": {
    "iso:country":"CH",
    "sg:address":"Chemin Du Boisy 3",
    "sg:city":"Lausanne",
    "sg:orig_category":"Vermietung U Verpachtung von eigenen Immobilien Vermittlung von Immobilien",
    "sg:phone":"+41 21 648 18 09",
    "sg:postcode":"1004",
    "sg:province":"Vaud",
    "wof:name":"Home-valeur, Ruben L.l. Monti",
    "wof:placetype":"venue"
},
  "geometry": {"coordinates":[6.6175398827,46.5325241089],"type":"Point"}
}