{
  "type": "Feature",
  "properties": {
    "iso:country":"CH",
    "sg:address":"Chemin Du Ch\u00eane 5",
    "sg:city":"Nyon",
    "sg:orig_category":"Elektroinstallation",
    "sg:phone":"+41 22 361 07 39",
    "sg:postcode":"1260",
    "sg:province":"Vaud",
    "wof:name":"Perrin & Spaeth Bureau D'ing\u00e9nieurs \u00e9lectriciens Sa, Succursale De Nyon",
    "wof:placetype":"venue"
},
  "geometry": {"coordinates":[6.2279410362,46.3941421509],"type":"Point"}
}