{
  "type": "Feature",
  "properties": {
    "addr:full":"Rue Granges-st-martin 8 Orbe Vaud 1350",
    "addr:housenumber":"8",
    "addr:postcode":"1350",
    "addr:street":"Rue Granges-St-Martin",
    "iso:country":"CH",
    "sg:address":"Rue Granges-st-martin 8",
    "sg:city":"Orbe",
    "sg:orig_category":"Bauspenglerei Sanit\u00e4rinstallation",
    "sg:phone":"+41 24 441 12 63",
    "sg:postcode":"1350",
    "sg:province":"Vaud",
    "wof:name":"Philippe Beney Ltd Installations Sanitaires",
    "wof:placetype":"venue"
},
  "geometry": {"coordinates":[6.53537,46.720631],"type":"Point"}
}