{
  "type": "Feature",
  "properties": {
    "iso:country":"CH",
    "sg:address":"Hallenweg",
    "sg:city":"Muttenz",
    "sg:orig_category":"Interessenvertretungen",
    "sg:phone":"+41 61 461 13 61",
    "sg:postcode":"4132",
    "sg:province":"Basel-Landschaft",
    "wof:name":"Rapp-stiftung Ruth Und Hans-joachim",
    "wof:placetype":"venue"
},
  "geometry": {"coordinates":[7.648856163,47.5213699341],"type":"Point"}
}