{
  "type": "Feature",
  "properties": {
    "iso:country":"CH",
    "sg:address":"Alte Churerstrasse 18",
    "sg:city":"Balzers",
    "sg:orig_category":"Hoch U Tiefbau",
    "sg:phone":"+423 384 11 76",
    "sg:postcode":"9496",
    "wof:name":"David Vogt Baugesch\u00e4ft",
    "wof:placetype":"venue"
},
  "geometry": {"coordinates":[9.5091485977,47.0651702881],"type":"Point"}
}