{
  "type": "Feature",
  "properties": {
    "iso:country":"CH",
    "sg:address":"M\u00fcnchackerstr. 20",
    "sg:city":"Pratteln",
    "sg:orig_category":"Primarschulen",
    "sg:phone":"+41 61 821 57 44",
    "sg:postcode":"4133",
    "sg:province":"Basel-Landschaft",
    "wof:name":"Primarschule M\u00fcnchacker",
    "wof:placetype":"venue"
},
  "geometry": {"coordinates":[7.6973700523,47.5237503052],"type":"Point"}
}