{
  "type": "Feature",
  "properties": {
    "iso:country":"CH",
    "sg:address":"Route Cantonale 99",
    "sg:city":"V\u00e9troz",
    "sg:classifiers":[
        {
            "category":"Banks & Credit Unions",
            "subcategory":"Bank",
            "type":"Services"
        }
    ],
    "sg:phone":"+41 27364606",
    "sg:postcode":"1963",
    "sg:province":"Valais",
    "wof:name":"Credit Suisse",
    "wof:placetype":"venue"
},
  "geometry": {"coordinates":[7.281771,46.225628],"type":"Point"}
}