{
  "type": "Feature",
  "properties": {
    "iso:country":"CH",
    "sg:address":"Sonnenwiesenstrasse 13",
    "sg:city":"Kreuzlingen",
    "sg:orig_category":"Handel mit Motorr\u00e4dern, Teilen U Zubeh\u00f6r Instandhaltung U Reparatur von Motorr\u00e4dern Sonstiger Grossh",
    "sg:phone":"+41 71 688 64 60",
    "sg:postcode":"8280",
    "sg:province":"Thurgau",
    "wof:name":"Yokobo Ag",
    "wof:placetype":"venue"
},
  "geometry": {"coordinates":[9.1921930313,47.644733429],"type":"Point"}
}