{
  "type": "Feature",
  "properties": {
    "iso:country":"CH",
    "sg:address":"B\u00fcrgelistr. 225",
    "sg:city":"Schwaderloch",
    "sg:orig_category":"Allgemeiner Hoch U Tiefbau",
    "sg:postcode":"5326",
    "sg:province":"Aargau",
    "wof:name":"W + G Raihalde Gmbh",
    "wof:placetype":"venue"
},
  "geometry": {"coordinates":[8.14637,47.588593],"type":"Point"}
}