{
  "type": "Feature",
  "properties": {
    "iso:country":"CH",
    "sg:address":"Seestrasse 113",
    "sg:city":"Thalwil",
    "sg:orig_category":"Mechanische Werkst\u00e4tten",
    "sg:phone":"+41 21 791 61 00",
    "sg:postcode":"8800",
    "sg:province":"Z\u00fcrich",
    "wof:name":"Bricoservice Mani Jacques",
    "wof:placetype":"venue"
},
  "geometry": {"coordinates":[6.6774148941,46.5133132935],"type":"Point"}
}