{
  "type": "Feature",
  "properties": {
    "iso:country":"CH",
    "sg:address":"M\u00fchlegasse 30",
    "sg:city":"Baar",
    "sg:orig_category":"Organisationen des Gesundheitswesen",
    "sg:phone":"+41 41 620 69 42",
    "sg:postcode":"6340",
    "sg:province":"Zug",
    "wof:name":"Samariterverein Baar",
    "wof:placetype":"venue"
},
  "geometry": {"coordinates":[8.5252084732,47.1997871399],"type":"Point"}
}