{
  "type": "Feature",
  "properties": {
    "iso:country":"CH",
    "sg:address":"Gellertstrasse 18 4052 Basel. Postfach",
    "sg:city":"Basel",
    "sg:orig_category":"Non-Classified Establishments",
    "sg:phone":"+41 61 312 54 54",
    "sg:postcode":"4051",
    "sg:province":"Basel-Stadt",
    "wof:name":"Beihold Finanz Ag Finanzierungen, Beiteiligungen Usw",
    "wof:placetype":"venue"
},
  "geometry": {"coordinates":[7.6072192192,47.5520019531],"type":"Point"}
}