{
  "type": "Feature",
  "properties": {
    "iso:country":"CH",
    "sg:address":"Kirchplatz 5",
    "sg:city":"Heiden",
    "sg:orig_category":"Nationale Postdienste",
    "sg:phone":"+41 71 891 11 24",
    "sg:postcode":"9410",
    "sg:province":"Appenzell Ausserrhoden",
    "wof:name":"Die Schweizerische Post",
    "wof:placetype":"venue"
},
  "geometry": {"coordinates":[9.5347890854,47.4445381165],"type":"Point"}
}