{
  "type": "Feature",
  "properties": {
    "iso:country":"CH",
    "sg:address":"Chemin De Vuichardaz 11",
    "sg:city":"Bussigny-lausanne",
    "sg:orig_category":"Kosmetikinstitute",
    "sg:phone":"+41 21 701 45 49",
    "sg:postcode":"1030",
    "sg:province":"Vaud",
    "wof:name":"H\u00e9l\u00e8ne Bruckert Institut De Beaut\u00e9",
    "wof:placetype":"venue"
},
  "geometry": {"coordinates":[6.5550279617,46.5504264832],"type":"Point"}
}