{
  "type": "Feature",
  "properties": {
    "addr:full":"Pl St-fran\u00e7ois 2 Lausanne Vaud 1002",
    "addr:housenumber":"2",
    "addr:postcode":"1002",
    "addr:street":"Pl St-Franc\u0327Ois",
    "iso:country":"CH",
    "sg:address":"Pl St-fran\u00e7ois 2",
    "sg:city":"Lausanne",
    "sg:classifiers":[
        {
            "category":"Travel",
            "subcategory":"Hotels & Motels",
            "type":"Entertainment"
        }
    ],
    "sg:phone":"+41 21 311 14 25",
    "sg:postcode":"1002",
    "sg:province":"Vaud",
    "sg:tags":[
        "hotels",
        "business",
        "restaurant"
    ],
    "wof:name":"Pizza Hut",
    "wof:placetype":"venue"
},
  "geometry": {"coordinates":[6.632491,46.519878],"type":"Point"}
}