{
  "type": "Feature",
  "properties": {
    "iso:country":"CH",
    "sg:address":"Winterthurerstrasse",
    "sg:city":"Flurlingen",
    "sg:classifiers":[
        {
            "category":"Utilities",
            "subcategory":"Sewage",
            "type":"Services"
        }
    ],
    "sg:phone":"+41 41 921 07 17",
    "sg:postcode":"8247",
    "sg:province":"Z\u00fcrich",
    "sg:tags":[
        "cladding",
        "welding"
    ],
    "wof:name":"Leuko Motorsportteile",
    "wof:placetype":"venue"
},
  "geometry": {"coordinates":[8.07447,47.182919],"type":"Point"}
}