{
  "type": "Feature",
  "properties": {
    "iso:country":"CH",
    "sg:address":"Aspermontstrasse 17",
    "sg:city":"Chur",
    "sg:orig_category":"Sonstige Kultur U Unterhaltungseinrichtungen",
    "sg:phone":"+41 31 311 87 35",
    "sg:postcode":"7000",
    "sg:province":"Graubunden",
    "wof:name":"Freizeitcenter Der Coop",
    "wof:placetype":"venue"
},
  "geometry": {"coordinates":[7.4422111511,46.9496002197],"type":"Point"}
}