{
  "type": "Feature",
  "properties": {
    "iso:country":"CH",
    "sg:address":"Gewerbehallenstrasse 4",
    "sg:city":"Wallisellen",
    "sg:orig_category":"Herstellung von Karosserien U Anh\u00e4ngern",
    "sg:phone":"+41 18306060",
    "sg:postcode":"8304",
    "sg:province":"Z\u00fcrich",
    "wof:name":"Carrosserie Hauser Ag",
    "wof:placetype":"venue"
},
  "geometry": {"coordinates":[8.574886322,47.4147644043],"type":"Point"}
}