{
  "type": "Feature",
  "properties": {
    "iso:country":"CH",
    "sg:address":"Pfistergasse 25 6000 Luzern. Postfach",
    "sg:city":"Luzern",
    "sg:orig_category":"Fachdetailhandel in Verkaufsr\u00e4umen",
    "sg:postcode":"6003",
    "sg:province":"Luzern",
    "wof:name":"Sportboutique Number One Gmbh",
    "wof:placetype":"venue"
},
  "geometry": {"coordinates":[8.3016147614,47.0510787964],"type":"Point"}
}