{
  "type": "Feature",
  "properties": {
    "addr:full":"Piazzetta Della Posta Lugano Ticino 6900",
    "addr:postcode":"6900",
    "addr:street":"Piazzetta Della Posta",
    "iso:country":"CH",
    "sg:address":"Piazzetta Della Posta",
    "sg:city":"Lugano",
    "sg:classifiers":[
        {
            "category":"Banks & Credit Unions",
            "subcategory":"Bank",
            "type":"Services"
        }
    ],
    "sg:phone":"+41 4191218484",
    "sg:postcode":"6900",
    "sg:province":"Ticino",
    "wof:name":"Union Bank Of Switzerland",
    "wof:placetype":"venue"
},
  "geometry": {"coordinates":[8.952505,46.005226],"type":"Point"}
}