{
  "type": "Feature",
  "properties": {
    "iso:country":"CH",
    "sg:address":"Avenue De La Gare",
    "sg:city":"Montana-vermala",
    "sg:orig_category":"Detailhandel mit Zeitungen U Zeitschriften Kioske",
    "sg:phone":"+41 27 481 89 89",
    "sg:postcode":"3962",
    "wof:name":"Kiosque Ali-baba",
    "wof:placetype":"venue"
},
  "geometry": {"coordinates":[7.483520031,46.3125],"type":"Point"}
}