{
  "type": "Feature",
  "properties": {
    "iso:country":"CH",
    "sg:address":"Grand-rue 72",
    "sg:city":"St-maurice",
    "sg:classifiers":[
        {
            "category":"Restaurant",
            "type":"Food & Drink"
        }
    ],
    "sg:phone":"+41 24 485 10 20",
    "sg:postcode":"1890",
    "sg:province":"Valais",
    "wof:name":"Caf\u00e9 De La Place",
    "wof:placetype":"venue"
},
  "geometry": {"coordinates":[7.0047140121,46.2198486328],"type":"Point"}
}