{
  "type": "Feature",
  "properties": {
    "iso:country":"CH",
    "sg:address":"Eggrainstrasse 3",
    "sg:city":"Wigoltingen",
    "sg:orig_category":"Hardwareberatung",
    "sg:postcode":"8556",
    "sg:province":"Thurgau",
    "wof:name":"Hypercant Baumann Computer, Hard, Und Software Usw.; Handel, Verkauf, Reparatur, Wartung",
    "wof:placetype":"venue"
},
  "geometry": {"coordinates":[8.5317974091,47.2824821472],"type":"Point"}
}