{
  "type": "Feature",
  "properties": {
    "iso:country":"CH",
    "sg:address":"Rohracker",
    "sg:city":"Langrickenbach",
    "sg:orig_category":"Allgemeiner Hoch U Tiefbau",
    "sg:phone":"+41 71 411 42 40",
    "sg:postcode":"8585",
    "sg:province":"Thurgau",
    "wof:name":"Hofstetter Bau Ag",
    "wof:placetype":"venue"
},
  "geometry": {"coordinates":[9.247656,47.592941],"type":"Point"}
}