{
  "type": "Feature",
  "properties": {
    "iso:country":"CH",
    "sg:address":"Kreuzstrasse 34",
    "sg:city":"Kriens",
    "sg:orig_category":"Grosshandel mit sonstigen Gebrauchs U Verbrauchsg\u00fctern",
    "sg:postcode":"6010",
    "sg:province":"Luzern",
    "wof:name":"General Dynamics Ots Gmbh",
    "wof:placetype":"venue"
},
  "geometry": {"coordinates":[8.299328804,47.0199012756],"type":"Point"}
}