{
  "type": "Feature",
  "properties": {
    "iso:country":"CH",
    "sg:address":"Route De Bourdigny 80",
    "sg:city":"Satigny",
    "sg:orig_category":"Rebbau",
    "sg:phone":"+41 22 753 15 16",
    "sg:postcode":"1242",
    "sg:province":"Gen\u00e8ve",
    "wof:name":"Jean-michel Gros Viticulteur",
    "wof:placetype":"venue"
},
  "geometry": {"coordinates":[6.0327649117,46.2339057922],"type":"Point"}
}