{
  "type": "Feature",
  "properties": {
    "iso:country":"CH",
    "sg:address":"Chemin De La Cr\u00e9taux 1196 Gland Case Postale 227",
    "sg:city":"Gland",
    "sg:orig_category":"Verarbeitung von Tee U Kaffee",
    "sg:phone":"+41 22 995 05 00",
    "sg:postcode":"1196",
    "sg:province":"Vaud",
    "wof:name":"Caf\u00e9 Espresso-club Sa",
    "wof:placetype":"venue"
},
  "geometry": {"coordinates":[6.2683949471,46.4182548523],"type":"Point"}
}