{
  "type": "Feature",
  "properties": {
    "iso:country":"CH",
    "sg:address":"Avenue Ch\u00e2teau De La Cour 4 3960 Sierre Case Postale 621",
    "sg:city":"Sierre",
    "sg:orig_category":"Versicherungen Generalagenturen",
    "sg:phone":"+41 27 455 11 30",
    "sg:postcode":"3960",
    "sg:province":"Valais",
    "wof:name":"Winterthur Assurances Agence G\u00e9n\u00e9rale",
    "wof:placetype":"venue"
},
  "geometry": {"coordinates":[7.5339560509,46.2937049866],"type":"Point"}
}