{
  "type": "Feature",
  "properties": {
    "iso:country":"CH",
    "sg:address":"Motta Via Giuseppe 10",
    "sg:city":"Chiasso",
    "sg:orig_category":"Grosshandel mit Erzen U Metallen",
    "sg:phone":"+41 32 373 50 55",
    "sg:postcode":"6830",
    "sg:province":"Ticino",
    "wof:name":"Metaltec Ag Blankstahlvertrieb",
    "wof:placetype":"venue"
},
  "geometry": {"coordinates":[7.3147788048,47.1114120483],"type":"Point"}
}