{
  "type": "Feature",
  "properties": {
    "iso:country":"CH",
    "sg:address":"Sandstrasse 29",
    "sg:city":"Gebenstorf",
    "sg:orig_category":"Sonstige pers\u00f6nliche Dienstleistungen",
    "sg:postcode":"5412",
    "sg:province":"Aargau",
    "wof:name":"Claudia Salzmann Beratung Und Dienstleistung",
    "wof:placetype":"venue"
},
  "geometry": {"coordinates":[8.2444286346,47.4854736328],"type":"Point"}
}