{
  "type": "Feature",
  "properties": {
    "iso:country":"CH",
    "sg:address":"Viale Alessandro Volta 10",
    "sg:city":"Chiasso",
    "sg:orig_category":"Zahnarztpraxen",
    "sg:phone":"+41 91 682 40 44",
    "sg:postcode":"6830",
    "sg:province":"Ticino",
    "wof:name":"Dott.med.dent.maurizio Dotto Dentista",
    "wof:placetype":"venue"
},
  "geometry": {"coordinates":[9.0331907272,45.8348083496],"type":"Point"}
}