{
  "type": "Feature",
  "properties": {
    "iso:country":"CH",
    "sg:address":"Chemin Du Praz-riond",
    "sg:city":"Penthaz",
    "sg:orig_category":"Detailhandel mit Fleisch U Fleischwaren Fleischverarbeitung",
    "sg:phone":"+41 21 862 71 16",
    "sg:postcode":"1303",
    "sg:province":"Vaud",
    "wof:name":"Prario Sa",
    "wof:placetype":"venue"
},
  "geometry": {"coordinates":[6.5411820412,46.5997924805],"type":"Point"}
}