{
  "type": "Feature",
  "properties": {
    "iso:country":"CH",
    "sg:address":"Burgholz",
    "sg:city":"Oey",
    "sg:orig_category":"Autogaragen Lastwagen and Nutzfahrzeuge",
    "sg:phone":"+41 33 681 27 58",
    "sg:postcode":"3753",
    "sg:province":"Bern",
    "wof:name":"Ernst Ledermann Lastwagenreparaturwerkst\u00e4tte",
    "wof:placetype":"venue"
},
  "geometry": {"coordinates":[7.57717,46.659599],"type":"Point"}
}