{
  "type": "Feature",
  "properties": {
    "iso:country":"CH",
    "sg:address":"Petite-rue",
    "sg:city":"Allaman",
    "sg:orig_category":"Architektur U Ingenieurb\u00fcros Architekturb\u00fcros",
    "sg:phone":"+41 21 808 82 80",
    "sg:postcode":"1165",
    "sg:province":"Vaud",
    "wof:name":"Keller Pascal",
    "wof:placetype":"venue"
},
  "geometry": {"coordinates":[6.396875,46.471149],"type":"Point"}
}