{
  "type": "Feature",
  "properties": {
    "iso:country":"CH",
    "sg:address":"Parkstrasse 6",
    "sg:city":"Goldau",
    "sg:orig_category":"Reiseb\u00fcros U Reiseveranstalter",
    "sg:postcode":"6410",
    "sg:province":"Schwyz",
    "wof:name":"Reiseb\u00fcro Art Travel, Kaufmann Martin",
    "wof:placetype":"venue"
},
  "geometry": {"coordinates":[8.5485095978,47.0498733521],"type":"Point"}
}