{
  "type": "Feature",
  "properties": {
    "iso:country":"CH",
    "sg:address":"Jordil Rue Georges- 4",
    "sg:city":"Fribourg",
    "sg:orig_category":"Detailhandel mit Waren verschiedener Art, Hauptrichtung Nahrungsmittel",
    "sg:postcode":"1700",
    "sg:province":"Fribourg",
    "wof:name":"Crosa Sa",
    "wof:placetype":"venue"
},
  "geometry": {"coordinates":[7.1539797783,46.7996177673],"type":"Point"}
}