{
  "type": "Feature",
  "properties": {
    "iso:country":"CH",
    "sg:address":"Hardstrasse 104 5432 Neuenhof. Postfach",
    "sg:city":"Neuenhof",
    "sg:orig_category":"Verarbeitung von Tee U Kaffee",
    "sg:phone":"+41 55 464 19 00",
    "sg:postcode":"5432",
    "sg:province":"Aargau",
    "wof:name":"Ansaro Gmbh Kaffeer\u00f6sterei",
    "wof:placetype":"venue"
},
  "geometry": {"coordinates":[8.9527902603,47.1751785278],"type":"Point"}
}