{
  "type": "Feature",
  "properties": {
    "iso:country":"CH",
    "sg:address":"Via Entadavos",
    "sg:city":"Ruschein",
    "sg:orig_category":"Zimmerei, Ingenieurholzbau",
    "sg:phone":"+41 81 925 61 71",
    "sg:postcode":"7154",
    "sg:province":"Graubunden",
    "wof:name":"Daniel Coray Holzbau",
    "wof:placetype":"venue"
},
  "geometry": {"coordinates":[9.1933546066,46.784740448],"type":"Point"}
}