{
  "type": "Feature",
  "properties": {
    "addr:full":"L\u00f6wenstrasse 13 Z\u00fcrich Z\u00fcrich 8001",
    "addr:housenumber":"13",
    "addr:postcode":"8001",
    "addr:street":"Loewenstrasse",
    "iso:country":"CH",
    "sg:address":"L\u00f6wenstrasse 13",
    "sg:city":"Z\u00fcrich",
    "sg:orig_category":"Architektur U Ingenieurb\u00fcros Unternehmensberatung",
    "sg:phone":"+41 12115400",
    "sg:postcode":"8001",
    "sg:province":"Z\u00fcrich",
    "wof:name":"Sec Schmid Engineering Consulting Ag",
    "wof:placetype":"venue"
},
  "geometry": {"coordinates":[8.53484,47.373726],"type":"Point"}
}