{
  "type": "Feature",
  "properties": {
    "iso:country":"CH",
    "sg:address":"Ober Hinterfeld",
    "sg:city":"Rothenburg",
    "sg:classifiers":[
        {
            "category":"Banks & Credit Unions",
            "subcategory":"Bank",
            "type":"Services"
        }
    ],
    "sg:phone":"+41 4141536437",
    "sg:postcode":"6023",
    "sg:province":"Luzern",
    "wof:name":"Rentenanstalt Swiss Life",
    "wof:placetype":"venue"
},
  "geometry": {"coordinates":[8.244144,47.118244],"type":"Point"}
}