{
  "type": "Feature",
  "properties": {
    "iso:country":"CH",
    "sg:address":"6760",
    "sg:city":"Faido",
    "sg:orig_category":"Advokaturb\u00fcros Notariate",
    "sg:phone":"+41 91 866 12 09",
    "sg:postcode":"6760",
    "sg:province":"Ticino",
    "wof:name":"Alberto Stefani Studio Legale & Notarile",
    "wof:placetype":"venue"
},
  "geometry": {"coordinates":[8.82089,46.489632],"type":"Point"}
}