{
  "type": "Feature",
  "properties": {
    "iso:country":"CH",
    "sg:address":"Bachwiesenstrasse 1 5436 W\u00fcrenlos. Postfach 71",
    "sg:city":"W\u00fcrenlos",
    "sg:orig_category":"Werbeagenturen Werbegrafikateliers",
    "sg:phone":"+41 56 424 36 74",
    "sg:postcode":"5436",
    "sg:province":"Aargau",
    "wof:name":"Bruno Waldmeier Werbung Grafik-konzepte",
    "wof:placetype":"venue"
},
  "geometry": {"coordinates":[8.3628168106,47.4418067932],"type":"Point"}
}