{
  "type": "Feature",
  "properties": {
    "iso:country":"CH",
    "sg:address":"Neuhofstrasse 8",
    "sg:city":"Baar",
    "sg:orig_category":"Logistikberatung Werbeberatung",
    "sg:phone":"+41 62 771 31 00",
    "sg:postcode":"6340",
    "sg:province":"Zug",
    "wof:name":"Dr. Ing. Ranjit Basu Mazumder Eth Consulting Engineer",
    "wof:placetype":"venue"
},
  "geometry": {"coordinates":[8.1967611313,47.2738685608],"type":"Point"}
}