{
  "type": "Feature",
  "properties": {
    "iso:country":"CH",
    "sg:address":"Vollandes Rue Des 40",
    "sg:city":"Gen\u00e8ve",
    "sg:orig_category":"Fachdetailhandel in Verkaufsr\u00e4umen",
    "sg:postcode":"1207",
    "sg:province":"Gen\u00e8ve",
    "wof:name":"L\u00e9man Tradition Sarl",
    "wof:placetype":"venue"
},
  "geometry": {"coordinates":[6.1620931625,46.2033424377],"type":"Point"}
}