{
  "type": "Feature",
  "properties": {
    "addr:full":"B\u00f6sch 5 H\u00fcnenberg Zug 6331",
    "addr:housenumber":"5",
    "addr:postcode":"6331",
    "addr:street":"Boesch;Huenenberg Zug",
    "iso:country":"CH",
    "sg:address":"B\u00f6sch 5",
    "sg:city":"H\u00fcnenberg",
    "sg:classifiers":[
        {
            "category":"Coffee & Tea",
            "type":"Food & Drink"
        }
    ],
    "sg:phone":"+41 41 780 65 55",
    "sg:postcode":"6331",
    "sg:province":"Zug",
    "sg:tags":[
        "aquavit"
    ],
    "wof:name":"Landtwing R\u00fctter Ag",
    "wof:placetype":"venue"
},
  "geometry": {"coordinates":[8.437399,47.160572],"type":"Point"}
}