{
  "type": "Feature",
  "properties": {
    "iso:country":"CH",
    "sg:address":"Uraniastrasse 9",
    "sg:city":"Z\u00fcrich",
    "sg:classifiers":[
        {
            "category":"Banks & Credit Unions",
            "subcategory":"Bank",
            "type":"Services"
        }
    ],
    "sg:phone":"+41 13334050",
    "sg:postcode":"8070",
    "sg:province":"Z\u00fcrich",
    "wof:name":"Credis International Fund Holding Ag",
    "wof:placetype":"venue"
},
  "geometry": {"coordinates":[8.539636,47.374378],"type":"Point"}
}