{
  "type": "Feature",
  "properties": {
    "iso:country":"CH",
    "sg:address":"St. Gallerstrasse 15",
    "sg:city":"Rorschach",
    "sg:orig_category":"Bauspenglerei Zimmerei, Dachdeckerei, Bauspenglerei U Abdichtung",
    "sg:phone":"+41 79 658 55 22",
    "sg:postcode":"9400",
    "sg:province":"St. Gallen",
    "wof:name":"Mayer Walter",
    "wof:placetype":"venue"
},
  "geometry": {"coordinates":[9.487188,47.478634],"type":"Point"}
}