{
  "type": "Feature",
  "properties": {
    "iso:country":"CH",
    "sg:address":"Hochbergerstrasse 15 4057 Basel. Postfach",
    "sg:city":"Basel",
    "sg:orig_category":"Zeitungsverlag",
    "sg:postcode":"4051",
    "sg:province":"Basel-Stadt",
    "wof:name":"Finanz-zeitung Ag Schweiz. Finanz-zeitung Usw; Herausgabe",
    "wof:placetype":"venue"
},
  "geometry": {"coordinates":[7.5975160599,47.5763092041],"type":"Point"}
}