{
  "type": "Feature",
  "properties": {
    "iso:country":"CH",
    "sg:address":"B\u00e4lliz 25 3600 Thun. Postfach",
    "sg:city":"Thun",
    "sg:orig_category":"Sonstige pers\u00f6nliche Dienstleistungen",
    "sg:postcode":"3600",
    "sg:province":"Bern",
    "wof:name":"L\u00e4derach Pi Ar Ag",
    "wof:placetype":"venue"
},
  "geometry": {"coordinates":[7.6272478104,46.7590370178],"type":"Point"}
}