{
  "type": "Feature",
  "properties": {
    "iso:country":"CH",
    "sg:address":"Aarauerstrasse 27",
    "sg:city":"Olten",
    "sg:classifiers":[
        {
            "category":"Professional",
            "subcategory":"Employment Agencies",
            "type":"Services"
        }
    ],
    "sg:phone":"+41 19411811",
    "sg:postcode":"4600",
    "sg:province":"Solothurn",
    "sg:tags":[
        "personal",
        "u",
        "stellenvermittlung"
    ],
    "wof:name":"Kappeler & Partner Ag",
    "wof:placetype":"venue"
},
  "geometry": {"coordinates":[8.6008930206,47.3279571533],"type":"Point"}
}