{
  "type": "Feature",
  "properties": {
    "iso:country":"CH",
    "sg:address":"Avenue Du Casino 53",
    "sg:city":"Montreux",
    "sg:orig_category":"Fachdetailhandel mit pharmazeutischen Produkten Parf\u00fcmerien U sonstiger Detailhandel mit kosmetische",
    "sg:phone":"+41 32 373 16 71",
    "sg:postcode":"1820",
    "sg:province":"Vaud",
    "wof:name":"Pharmacie-parfumerie Br\u00fcggmoos Gmbh",
    "wof:placetype":"venue"
},
  "geometry": {"coordinates":[7.2666568756,47.1203079224],"type":"Point"}
}