{
  "type": "Feature",
  "properties": {
    "iso:country":"CH",
    "sg:address":"D\u00f6rfli",
    "sg:city":"Engi",
    "sg:orig_category":"Unclassifiable Establishments",
    "sg:postcode":"8765",
    "sg:province":"Glarus",
    "wof:name":"Rosi's Dorfladen Rosmarie B\u00e4bler",
    "wof:placetype":"venue"
},
  "geometry": {"coordinates":[9.1541223526,46.9818992615],"type":"Point"}
}