{
  "type": "Feature",
  "properties": {
    "iso:country":"CH",
    "sg:address":"Liotard Rue 11 1202 Gen\u00e8ve. Postfach",
    "sg:city":"Gen\u00e8ve",
    "sg:orig_category":"Sonstiger Grosshandel",
    "sg:postcode":"1202",
    "sg:province":"Gen\u00e8ve",
    "wof:name":"Dollar Import-export Sa.",
    "wof:placetype":"venue"
},
  "geometry": {"coordinates":[6.1335091591,46.2095794678],"type":"Point"}
}