{
  "type": "Feature",
  "properties": {
    "iso:country":"CH",
    "sg:address":"Place St-fran\u00e7ois 1 1000 Lausanne. Postfach",
    "sg:city":"Lausanne",
    "sg:orig_category":"Unclassifiable Establishments",
    "sg:postcode":"1003",
    "sg:province":"Vaud",
    "wof:name":"Si Avenue Des Alpes 111, La Tour-de-peilz",
    "wof:placetype":"venue"
},
  "geometry": {"coordinates":[6.8568668365,46.4530258179],"type":"Point"}
}