{
  "type": "Feature",
  "properties": {
    "iso:country":"CH",
    "sg:address":"Engehaldenstrasse 12",
    "sg:city":"Bern",
    "sg:classifiers":[
        {
            "category":"Professional",
            "subcategory":"Computer Services",
            "type":"Services"
        }
    ],
    "sg:phone":"+41 31 633 21 21",
    "sg:postcode":"3012",
    "sg:province":"Bern",
    "sg:tags":[
        "administration",
        "software"
    ],
    "wof:name":"Bedag Informatik Ag",
    "wof:placetype":"venue"
},
  "geometry": {"coordinates":[7.439716,46.954399],"type":"Point"}
}