{
  "type": "Feature",
  "properties": {
    "iso:country":"CH",
    "sg:address":"Gemeindeverwaltung 3935 B\u00fcrchen. Postfach 3",
    "sg:city":"B\u00fcrchen",
    "sg:orig_category":"Wasserversorgung",
    "sg:postcode":"3935",
    "sg:province":"Valais",
    "wof:name":"Wasserversorgung",
    "wof:placetype":"venue"
},
  "geometry": {"coordinates":[7.8239197731,46.2781448364],"type":"Point"}
}