{
  "type": "Feature",
  "properties": {
    "iso:country":"CH",
    "sg:address":"1567 Delley. Postfach",
    "sg:city":"Delley",
    "sg:orig_category":"Grosshandel mit Getreide, Saatgut U Futtermitteln",
    "sg:phone":"+41 26 677 40 50",
    "sg:postcode":"1567",
    "sg:province":"Fribourg",
    "wof:name":"Sspv-asps Schweizerischer Saatgutproduzentenverband",
    "wof:placetype":"venue"
},
  "geometry": {"coordinates":[6.9719600677,46.9128189087],"type":"Point"}
}