{
  "type": "Feature",
  "properties": {
    "iso:country":"CH",
    "sg:address":"H\u00f6nggerstrasse 118",
    "sg:city":"Z\u00fcrich",
    "sg:classifiers":[
        {
            "category":"Professional",
            "subcategory":"Employment Agencies",
            "type":"Services"
        }
    ],
    "sg:phone":"+41 14474447",
    "sg:postcode":"8037",
    "sg:province":"Z\u00fcrich",
    "sg:tags":[
        "personal",
        "u",
        "stellenvermittlung"
    ],
    "wof:name":"Markan Personalmanagement Ag",
    "wof:placetype":"venue"
},
  "geometry": {"coordinates":[8.5187520981,47.3955917358],"type":"Point"}
}