{
  "type": "Feature",
  "properties": {
    "iso:country":"CH",
    "sg:address":"Oberm\u00fclistrasse 57",
    "sg:city":"Fehraltorf",
    "sg:orig_category":"Grosshandel mit sonstigen Maschinen U Ausr\u00fcstungen f\u00fcr Industrie, Handel U Schiffahrt Herstellung vo",
    "sg:phone":"+41 31 721 98 22",
    "sg:postcode":"8320",
    "sg:province":"Z\u00fcrich",
    "wof:name":"Friedrich Schaub, Technischer Handel",
    "wof:placetype":"venue"
},
  "geometry": {"coordinates":[7.5257778168,46.9317855835],"type":"Point"}
}