{
  "type": "Feature",
  "properties": {
    "iso:country":"CH",
    "sg:address":"Guillimann Rue Fran\u00e7ois- 14",
    "sg:city":"Fribourg",
    "sg:orig_category":"Gesundheitswesen",
    "sg:phone":"+41 26 323 34 23",
    "sg:postcode":"1700",
    "sg:province":"Fribourg",
    "wof:name":"Formul'sant\u00e9 Bien-\u00eatre, Winiger Myriam - Sallin Fran\u00e7ois",
    "wof:placetype":"venue"
},
  "geometry": {"coordinates":[7.150747776,46.7983093262],"type":"Point"}
}