{
  "type": "Feature",
  "properties": {
    "iso:country":"CH",
    "sg:address":"Casa Magnolia V.ponte Vecchio",
    "sg:city":"Agno",
    "sg:orig_category":"Malerei",
    "sg:phone":"+41 91 605 22 65",
    "sg:postcode":"6982",
    "sg:province":"Ticino",
    "wof:name":"Michele Diasio Impresa Di Pittura",
    "wof:placetype":"venue"
},
  "geometry": {"coordinates":[8.8993301392,45.9967536926],"type":"Point"}
}