{
  "type": "Feature",
  "properties": {
    "iso:country":"CH",
    "sg:address":"Eigerweg 44",
    "sg:city":"Kehrsatz",
    "sg:orig_category":"Sonstige mit der Informatik verbundene T\u00e4tigkeiten",
    "sg:phone":"+41 31 348 14 56",
    "sg:postcode":"3122",
    "sg:province":"Bern",
    "wof:name":"Ra Ii System-solutions Avramovic Rafael S.",
    "wof:placetype":"venue"
},
  "geometry": {"coordinates":[7.470954895,46.9170227051],"type":"Point"}
}