{
  "type": "Feature",
  "properties": {
    "iso:country":"CH",
    "sg:address":"3800",
    "sg:city":"Unterseen",
    "sg:orig_category":"Vereine Musik/Blasmusik",
    "sg:phone":"+41 19405562",
    "sg:postcode":"3800",
    "sg:province":"Bern",
    "wof:name":"Stadtmusik Uster",
    "wof:placetype":"venue"
},
  "geometry": {"coordinates":[8.7172937393,47.3500556946],"type":"Point"}
}