{
  "type": "Feature",
  "properties": {
    "iso:country":"CH",
    "sg:address":"Weingartenweg 11",
    "sg:city":"Oensingen",
    "sg:orig_category":"Sportvereine Velo Rad-& Motorfahrer-Bund SRB",
    "sg:phone":"+41 62 396 22 16",
    "sg:postcode":"4702",
    "sg:province":"Solothurn",
    "wof:name":"Veloclub Oensingen",
    "wof:placetype":"venue"
},
  "geometry": {"coordinates":[7.7157239914,47.2918701172],"type":"Point"}
}