{
  "type": "Feature",
  "properties": {
    "iso:country":"CH",
    "sg:address":"Dolderstrasse 24",
    "sg:city":"Z\u00fcrich",
    "sg:classifiers":[
        {
            "category":"Professional",
            "subcategory":"Employment Agencies",
            "type":"Services"
        }
    ],
    "sg:phone":"+41 12612627",
    "sg:postcode":"8032",
    "sg:province":"Z\u00fcrich",
    "sg:tags":[
        "personal",
        "u",
        "stellenvermittlung"
    ],
    "wof:name":"Geiger Karin Personalberatung",
    "wof:placetype":"venue"
},
  "geometry": {"coordinates":[8.5585632324,47.3704795837],"type":"Point"}
}