{
  "type": "Feature",
  "properties": {
    "iso:country":"CH",
    "sg:address":"Route De Taillepied 89",
    "sg:city":"Ch\u00e2telard-lutry",
    "sg:orig_category":"Hoch U Tiefbau Stukkateurgewerbe, Gipserei U Verputzerei",
    "sg:phone":"+41 71 385 71 71",
    "sg:postcode":"1095",
    "sg:province":"Vaud",
    "wof:name":"Una Gips Ag",
    "wof:placetype":"venue"
},
  "geometry": {"coordinates":[9.2734594345,47.415145874],"type":"Point"}
}