{
  "type": "Feature",
  "properties": {
    "iso:country":"CH",
    "sg:address":"Baarerstrasse 95",
    "sg:city":"Zug",
    "sg:orig_category":"Aktivit\u00e4ten der Generalunternehmen im Baugewerbe Architektur U Ingenieurb\u00fcros",
    "sg:phone":"+41 41 761 62 88",
    "sg:postcode":"6300",
    "sg:province":"Zug",
    "wof:name":"Bader-sachse Ag Architektur & Generaluntern.",
    "wof:placetype":"venue"
},
  "geometry": {"coordinates":[8.52418,47.173309],"type":"Point"}
}