{
  "type": "Feature",
  "properties": {
    "iso:country":"CH",
    "sg:address":"Rue De Montbrillant 88 1200 Gen\u00e8ve. Postfach",
    "sg:city":"Gen\u00e8ve",
    "sg:orig_category":"Interessenvertretungen",
    "sg:postcode":"1202",
    "sg:province":"Gen\u00e8ve",
    "wof:name":"Club Charter Fly 2 Cf",
    "wof:placetype":"venue"
},
  "geometry": {"coordinates":[6.1408371925,46.2202529907],"type":"Point"}
}