{
  "type": "Feature",
  "properties": {
    "iso:country":"CH",
    "sg:address":"Oberer Graben 6 8400 Winterthur. Postfach 560",
    "sg:city":"Winterthur",
    "sg:orig_category":"Kinos",
    "sg:phone":"+41 19327250",
    "sg:postcode":"8402",
    "sg:province":"Z\u00fcrich",
    "wof:name":"Lichtspiele Ag",
    "wof:placetype":"venue"
},
  "geometry": {"coordinates":[8.7973403931,47.321975708],"type":"Point"}
}