{
  "type": "Feature",
  "properties": {
    "iso:country":"CH",
    "sg:address":"7435",
    "sg:city":"Spl\u00fcgen",
    "sg:orig_category":"Verwaltung der Rechtspflege, Gerichte",
    "sg:phone":"+41 81 664 11 28",
    "sg:postcode":"7435",
    "sg:province":"Graubunden",
    "wof:name":"Grundbuchamt",
    "wof:placetype":"venue"
},
  "geometry": {"coordinates":[9.3233728409,46.5529594421],"type":"Point"}
}