{
  "type": "Feature",
  "properties": {
    "iso:country":"CH",
    "sg:address":"Kastellstrasse 11",
    "sg:city":"Kaiseraugst",
    "sg:orig_category":"Physiotherapie",
    "sg:phone":"+41 61 811 53 33",
    "sg:postcode":"4303",
    "sg:province":"Aargau",
    "wof:name":"Physiotherapie Kuny",
    "wof:placetype":"venue"
},
  "geometry": {"coordinates":[7.7239141464,47.5395851135],"type":"Point"}
}