{
  "type": "Feature",
  "properties": {
    "iso:country":"CH",
    "sg:address":"Moosstrasse 5",
    "sg:city":"Menzingen",
    "sg:orig_category":"Elektroinstallation",
    "sg:postcode":"6313",
    "sg:province":"Zug",
    "wof:name":"Hegglin A., Elektroplanungen",
    "wof:placetype":"venue"
},
  "geometry": {"coordinates":[8.6004447937,47.174282074],"type":"Point"}
}