{
  "type": "Feature",
  "properties": {
    "iso:country":"CH",
    "sg:address":"Z\u00fcrcherstrasse 300",
    "sg:city":"Frauenfeld",
    "sg:orig_category":"Kauf U Verkauf von Immobilien auf eigene Rechnung Vermietung U Verpachtung von eigenen Immobilien",
    "sg:phone":"+41 27 458 46 38",
    "sg:postcode":"8500",
    "sg:province":"Thurgau",
    "wof:name":"Courtactif Sa",
    "wof:placetype":"venue"
},
  "geometry": {"coordinates":[7.4636449814,46.2584381104],"type":"Point"}
}