{
  "type": "Feature",
  "properties": {
    "iso:country":"CH",
    "sg:address":"Hauptstrasse 30",
    "sg:city":"Einsiedeln",
    "sg:classifiers":[
        {
            "category":"Home & Garden",
            "subcategory":"Kitchen Supply",
            "type":"Retail Goods"
        }
    ],
    "sg:phone":"+41 55 422 22 00",
    "sg:postcode":"8840",
    "sg:province":"Schwyz",
    "sg:tags":[
        "fitted"
    ],
    "wof:name":"Chuchi Trend Ag",
    "wof:placetype":"venue"
},
  "geometry": {"coordinates":[8.7462787628,47.1271705627],"type":"Point"}
}