{
  "type": "Feature",
  "properties": {
    "iso:country":"CH",
    "sg:address":"Wehntalerstrasse 586 A 8000 Z\u00fcrich. Postfach",
    "sg:city":"Z\u00fcrich",
    "sg:orig_category":"Zimmerei, Dachdeckerei, Bauspenglerei U Abdichtung",
    "sg:postcode":"8046",
    "sg:province":"Z\u00fcrich",
    "wof:name":"Woodbau Gmbh",
    "wof:placetype":"venue"
},
  "geometry": {"coordinates":[8.5031642914,47.4205665588],"type":"Point"}
}