{
  "type": "Feature",
  "properties": {
    "addr:full":"J.v.-widmann-strasse 4 Thun Bern 3600",
    "addr:housenumber":"4",
    "addr:postcode":"3600",
    "addr:street":"J.V.-Widmann-Strasse;Bern",
    "iso:country":"CH",
    "sg:address":"J.v.-widmann-strasse 4",
    "sg:city":"Thun",
    "sg:orig_category":"Architekturb\u00fcros",
    "sg:phone":"+41 33 222 72 79",
    "sg:postcode":"3600",
    "sg:province":"Bern",
    "wof:name":"Claude Aebersold Architekturb\u00fcro",
    "wof:placetype":"venue"
},
  "geometry": {"coordinates":[7.625404,46.750561],"type":"Point"}
}