{
  "type": "Feature",
  "properties": {
    "iso:country":"CH",
    "sg:address":"Schwamendingerstrasse 55",
    "sg:city":"Z\u00fcrich",
    "sg:orig_category":"Religi\u00f6se Vereinigungen divers",
    "sg:postcode":"8050",
    "sg:province":"Z\u00fcrich",
    "wof:name":"Kath.arbeitnehmerbewegung Der Pfarrei Herz-jesu Schw'dingen",
    "wof:placetype":"venue"
},
  "geometry": {"coordinates":[8.5513429642,47.4067878723],"type":"Point"}
}