{
  "type": "Feature",
  "properties": {
    "iso:country":"CH",
    "sg:address":"Plantaud Avenue 14b",
    "sg:city":"Monthey",
    "sg:orig_category":"Erbringung von sonstigen Dienstleistungen f\u00fcr Unterhaltung, Erholung U Freizeit",
    "sg:postcode":"1870",
    "sg:province":"Valais",
    "wof:name":"Mk Power, Lenweiter, Rosaire Et D\u00e9nervaud",
    "wof:placetype":"venue"
},
  "geometry": {"coordinates":[6.9511351585,46.2508544922],"type":"Point"}
}