{
  "type": "Feature",
  "properties": {
    "iso:country":"CH",
    "sg:address":"Gemeindehausplatz 5 6048 Horw. Postfach",
    "sg:city":"Horw",
    "sg:orig_category":"Detailhandel mit Damenbekleidung Detailhandel mit Herrenbekleidung",
    "sg:phone":"+41 41 870 81 71",
    "sg:postcode":"6048",
    "sg:province":"Luzern",
    "wof:name":"Charles V\u00f6gele Mode Ag",
    "wof:placetype":"venue"
},
  "geometry": {"coordinates":[8.6508302689,46.8718147278],"type":"Point"}
}