{
  "type": "Feature",
  "properties": {
    "iso:country":"CH",
    "sg:address":"Gygerweg 18",
    "sg:city":"Spiezwiler",
    "sg:orig_category":"Wein Detailhandel",
    "sg:phone":"+41 33 654 70 50",
    "sg:postcode":"3700",
    "sg:province":"Bern",
    "wof:name":"Weinkiste St. Jakob",
    "wof:placetype":"venue"
},
  "geometry": {"coordinates":[7.6654000282,46.6838722229],"type":"Point"}
}