{
  "type": "Feature",
  "properties": {
    "iso:country":"CH",
    "sg:address":"St. Jakobs-strasse 110",
    "sg:city":"Basel",
    "sg:orig_category":"Sonstiger Fachdetailhandel mit Nahrungsmitteln, Getr\u00e4nken U Tabak in Verkaufsr\u00e4umen",
    "sg:postcode":"4052",
    "sg:province":"Basel-Stadt",
    "wof:name":"Gourmets-events Tschudin Stephan",
    "wof:placetype":"venue"
},
  "geometry": {"coordinates":[7.6016550064,47.5458984375],"type":"Point"}
}