{
  "type": "Feature",
  "properties": {
    "iso:country":"CH",
    "sg:address":"Via Giulia",
    "sg:city":"Stabio",
    "sg:orig_category":"Grosshandel mit Textilien",
    "sg:postcode":"6855",
    "sg:province":"Ticino",
    "wof:name":"Fidler Charly Pelze Ltd",
    "wof:placetype":"venue"
},
  "geometry": {"coordinates":[8.543381691,47.3293838501],"type":"Point"}
}