{
  "type": "Feature",
  "properties": {
    "iso:country":"CH",
    "sg:address":"Route De St-cergue 63",
    "sg:city":"Nyon",
    "sg:orig_category":"Herstellung von sonstigen elektrischen Ausr\u00fcstungen",
    "sg:phone":"+41 22 361 35 79",
    "sg:postcode":"1260",
    "sg:province":"Vaud",
    "wof:name":"Equey Robert",
    "wof:placetype":"venue"
},
  "geometry": {"coordinates":[6.2323060036,46.3914833069],"type":"Point"}
}