{
  "type": "Feature",
  "properties": {
    "iso:country":"CH",
    "sg:address":"Aarestrasse 30 A",
    "sg:city":"Thun",
    "sg:orig_category":"Fachdetailhandel mit Nahrungsmitteln, Getr\u00e4nken U Tabakwaren in Verkaufsr\u00e4umen",
    "sg:phone":"+41 33 221 42 88",
    "sg:postcode":"3600",
    "sg:province":"Bern",
    "wof:name":"Spar Supermarkt",
    "wof:placetype":"venue"
},
  "geometry": {"coordinates":[7.6272549629,46.757270813],"type":"Point"}
}