{
  "type": "Feature",
  "properties": {
    "iso:country":"CH",
    "sg:address":"Aarhaldenstrasse 6",
    "sg:city":"Wabern",
    "sg:orig_category":"Gartenbau",
    "sg:phone":"+41 79 651 13 07",
    "sg:postcode":"3084",
    "sg:province":"Bern",
    "wof:name":"Friedrich Backe Gartenbau",
    "wof:placetype":"venue"
},
  "geometry": {"coordinates":[7.4508399963,46.9290351868],"type":"Point"}
}