{
  "type": "Feature",
  "properties": {
    "iso:country":"CH",
    "sg:address":"Runatsch",
    "sg:city":"Zernez",
    "sg:orig_category":"G\u00fcterbef\u00f6rderung im Strassenverkehr",
    "sg:postcode":"7530",
    "sg:province":"Graubunden",
    "wof:name":"Hunger Anton, Transporte",
    "wof:placetype":"venue"
},
  "geometry": {"coordinates":[9.3146314621,46.6814079285],"type":"Point"}
}