{
  "type": "Feature",
  "properties": {
    "iso:country":"CH",
    "sg:address":"Grand-rue 14",
    "sg:city":"Peseux",
    "sg:orig_category":"Detailhandel mit Tabakwaren Reparatur von Uhren U Schmuck",
    "sg:phone":"+41 32 731 30 44",
    "sg:postcode":"2034",
    "sg:province":"Neuch\u00e2tel",
    "wof:name":"Danielle Gay Tabacs Horlogerie",
    "wof:placetype":"venue"
},
  "geometry": {"coordinates":[6.8885850906,46.9868431091],"type":"Point"}
}