{
  "type": "Feature",
  "properties": {
    "iso:country":"CH",
    "sg:address":"Seefeldstrasse 202",
    "sg:city":"Z\u00fcrich",
    "sg:classifiers":[
        {
            "category":"Communications",
            "subcategory":"Film & Video Production",
            "type":"Services"
        }
    ],
    "sg:phone":"+41 62 205 90 50",
    "sg:postcode":"8008",
    "sg:province":"Z\u00fcrich",
    "sg:tags":[
        "videofilmherstellung",
        "u"
    ],
    "wof:name":"Alphavision Ag Tv-& Video-produktionen",
    "wof:placetype":"venue"
},
  "geometry": {"coordinates":[7.867699,47.344456],"type":"Point"}
}