{
  "type": "Feature",
  "properties": {
    "iso:country":"CH",
    "sg:address":"Goldackerweg 6",
    "sg:city":"Seuzach",
    "sg:orig_category":"Wirtschafts- and Arbeitgeberverb\u00e4nde",
    "sg:phone":"+41 52 335 45 15",
    "sg:postcode":"8472",
    "sg:province":"Z\u00fcrich",
    "wof:name":"Verband Schweizerischer Privatradios Vsp",
    "wof:placetype":"venue"
},
  "geometry": {"coordinates":[8.7446641922,47.5360717773],"type":"Point"}
}