{
  "type": "Feature",
  "properties": {
    "iso:country":"CH",
    "sg:address":"Scheienhaus",
    "sg:city":"B\u00fchler",
    "sg:orig_category":"Politische Parteien FDP",
    "sg:phone":"+41 71 793 18 69",
    "sg:postcode":"9055",
    "sg:province":"Appenzell Ausserrhoden",
    "wof:name":"Fdp Ortspartei B\u00fchler",
    "wof:placetype":"venue"
},
  "geometry": {"coordinates":[9.4177865982,47.3744659424],"type":"Point"}
}