{
  "type": "Feature",
  "properties": {
    "iso:country":"CH",
    "sg:address":"Madretschstrasse 126 2500 Biel/bienne. Postfach",
    "sg:city":"Biel/bienne",
    "sg:orig_category":"Museen",
    "sg:postcode":"2503",
    "sg:province":"Bern",
    "wof:name":"Galerie Florian, Akhbari A.",
    "wof:placetype":"venue"
},
  "geometry": {"coordinates":[7.2586479187,47.1367835999],"type":"Point"}
}