{
  "type": "Feature",
  "properties": {
    "iso:country":"CH",
    "sg:address":"Avenue Des Sports 48",
    "sg:city":"Yverdon-les-bains",
    "sg:orig_category":"Grosshandel mit Getreide, Saatgut U Futtermitteln",
    "sg:phone":"+41 24 425 31 58",
    "sg:postcode":"1400",
    "sg:province":"Vaud",
    "wof:name":"Centre Collecteur Du Nord Vaudois",
    "wof:placetype":"venue"
},
  "geometry": {"coordinates":[6.6539912224,46.7797241211],"type":"Point"}
}