{
  "type": "Feature",
  "properties": {
    "iso:country":"CH",
    "sg:address":"Rue De L'industrie 59 1030 Bussigny-lausanne Case Postale 447",
    "sg:city":"Bussigny-lausanne",
    "sg:orig_category":"Herstellung von sonstigen Maschinen f\u00fcr unspezifische Verwendung Mechanische Werkst\u00e4tten",
    "sg:phone":"+41 22 701 28 11",
    "sg:postcode":"1030",
    "sg:province":"Vaud",
    "wof:name":"Voltec Sa",
    "wof:placetype":"venue"
},
  "geometry": {"coordinates":[6.5594801903,46.5455665588],"type":"Point"}
}