{
  "type": "Feature",
  "properties": {
    "iso:country":"CH",
    "sg:address":"6543",
    "sg:city":"Arvigo",
    "sg:orig_category":"Allgemeiner Hoch U Tiefbau",
    "sg:phone":"+41 91 828 15 45",
    "sg:postcode":"6543",
    "sg:province":"Graubunden",
    "wof:name":"Impresa Bogana Francesco Sagl",
    "wof:placetype":"venue"
},
  "geometry": {"coordinates":[9.114112,46.302986],"type":"Point"}
}