{
  "type": "Feature",
  "properties": {
    "iso:country":"CH",
    "sg:address":"Panoramastrasse 14",
    "sg:city":"Ebikon",
    "sg:orig_category":"Grosshandel mit Getr\u00e4nken",
    "sg:postcode":"6030",
    "sg:province":"Luzern",
    "wof:name":"Berger Weinhandel",
    "wof:placetype":"venue"
},
  "geometry": {"coordinates":[8.3414163589,47.0755157471],"type":"Point"}
}