{
  "type": "Feature",
  "properties": {
    "iso:country":"CH",
    "sg:address":"Ruessenstrasse 5",
    "sg:city":"Baar",
    "sg:orig_category":"Unternehmensberatung",
    "sg:postcode":"6340",
    "sg:province":"Zug",
    "wof:name":"J + B Barbalux Consulting Gmbh",
    "wof:placetype":"venue"
},
  "geometry": {"coordinates":[8.5635023117,47.2124977112],"type":"Point"}
}