{
  "type": "Feature",
  "properties": {
    "iso:country":"CH",
    "sg:address":"1407",
    "sg:city":"Donneloye",
    "sg:classifiers":[
        {
            "category":"Restaurant",
            "type":"Food & Drink"
        }
    ],
    "sg:phone":"+41 32 968 34 14",
    "sg:postcode":"1407",
    "sg:province":"Vaud",
    "wof:name":"Restaurant Des Combettes",
    "wof:placetype":"venue"
},
  "geometry": {"coordinates":[6.8331198692,47.1170272827],"type":"Point"}
}