{
  "type": "Feature",
  "properties": {
    "iso:country":"CH",
    "sg:address":"Plattenstrasse 18",
    "sg:city":"B\u00fctschwil",
    "sg:orig_category":"Gartenbau Landschaftsplanungsb\u00fcros U Gartenarchitekturb\u00fcros",
    "sg:phone":"+41 71 913 96 50",
    "sg:postcode":"9606",
    "sg:province":"St. Gallen",
    "wof:name":"Engeler Freiraumplanung Ag",
    "wof:placetype":"venue"
},
  "geometry": {"coordinates":[9.0781593323,47.3590965271],"type":"Point"}
}