{
  "type": "Feature",
  "properties": {
    "iso:country":"CH",
    "sg:address":"3126",
    "sg:city":"Gelterfingen",
    "sg:orig_category":"Herstellung von Schreinerwaren ohne ausgepr\u00e4gten Schwerpunkt Herstellung von sonstigen Fahrzeugen",
    "sg:phone":"+41 31 819 09 69",
    "sg:postcode":"3126",
    "sg:province":"Bern",
    "wof:name":"Fritz Keller Schreinerei-wagnerei",
    "wof:placetype":"venue"
},
  "geometry": {"coordinates":[7.5065898895,46.8429718018],"type":"Point"}
}