{
  "type": "Feature",
  "properties": {
    "iso:country":"CH",
    "sg:address":"Leuchen 9428 Walzenhausen. Postfach",
    "sg:city":"Platz",
    "sg:orig_category":"Bauschreinerei Hobel U Holzimpr\u00e4gnierwerke",
    "sg:phone":"+41 71 888 28 90",
    "sg:postcode":"9428",
    "sg:province":"Appenzell Ausserrhoden",
    "wof:name":"Sagu Ag Walzenhausen",
    "wof:placetype":"venue"
},
  "geometry": {"coordinates":[9.628474,47.439911],"type":"Point"}
}