{
  "type": "Feature",
  "properties": {
    "iso:country":"CH",
    "sg:address":"Bubentalstrasse 6",
    "sg:city":"Wallisellen",
    "sg:orig_category":"Grosshandel mit B\u00fcromaschinen Grosshandel mit Datenverarbeitungsger\u00e4ten",
    "sg:phone":"+41 18312208",
    "sg:postcode":"8304",
    "sg:province":"Z\u00fcrich",
    "wof:name":"Giorgio Guzzi Edv-beratung",
    "wof:placetype":"venue"
},
  "geometry": {"coordinates":[8.6007461548,47.4135856628],"type":"Point"}
}