{
  "type": "Feature",
  "properties": {
    "iso:country":"CH",
    "sg:address":"Spitalgasse 18",
    "sg:city":"Bern",
    "sg:orig_category":"Grosshandel mit Bekleidung",
    "sg:phone":"+41 31 311 57 18",
    "sg:postcode":"3011",
    "sg:province":"Bern",
    "wof:name":"Ferri's, Gayret F. Jun. Bekleidungsartikel; Handel.",
    "wof:placetype":"venue"
},
  "geometry": {"coordinates":[7.4425492287,46.9481430054],"type":"Point"}
}