{
  "type": "Feature",
  "properties": {
    "iso:country":"CH",
    "sg:address":"Im Zentrum 1",
    "sg:city":"Oberengstringen",
    "sg:orig_category":"Fachdetailhandel mit pharmazeutischen Produkten",
    "sg:phone":"+41 17505050",
    "sg:postcode":"8102",
    "sg:province":"Z\u00fcrich",
    "wof:name":"Apotheke Hardegger Dr. Ag",
    "wof:placetype":"venue"
},
  "geometry": {"coordinates":[8.4608974457,47.4086151123],"type":"Point"}
}