{
  "type": "Feature",
  "properties": {
    "iso:country":"CH",
    "sg:address":"Wahlenstrasse 18",
    "sg:city":"B\u00fcsserach",
    "sg:orig_category":"Sanit\u00e4rinstallation",
    "sg:phone":"+41 91 791 19 10",
    "sg:postcode":"4227",
    "sg:province":"Solothurn",
    "wof:name":"Olivio Materni Impianti Sanitari",
    "wof:placetype":"venue"
},
  "geometry": {"coordinates":[8.7370166779,46.1500396729],"type":"Point"}
}