{
  "type": "Feature",
  "properties": {
    "iso:country":"CH",
    "sg:address":"Junkermattstrasse 10",
    "sg:city":"Muttenz",
    "sg:orig_category":"Herstellung von Armaturen",
    "sg:phone":"+41 61 462 40 00",
    "sg:postcode":"4132",
    "sg:province":"Basel-Landschaft",
    "wof:name":"Aran Ag",
    "wof:placetype":"venue"
},
  "geometry": {"coordinates":[7.6507668495,47.5318107605],"type":"Point"}
}