{
  "type": "Feature",
  "properties": {
    "iso:country":"CH",
    "sg:address":"Bahnhofstrasse 32",
    "sg:city":"Boswil",
    "sg:classifiers":[
        {
            "category":"Home & Garden",
            "subcategory":"Carpets & Floor Coverings",
            "type":"Retail Goods"
        }
    ],
    "sg:phone":"+41 56 666 23 23",
    "sg:postcode":"5623",
    "sg:province":"Aargau",
    "sg:tags":[
        "houses",
        "shed"
    ],
    "wof:name":"Eko Holz Ag",
    "wof:placetype":"venue"
},
  "geometry": {"coordinates":[8.3175563812,47.3057327271],"type":"Point"}
}