{
  "type": "Feature",
  "properties": {
    "iso:country":"CH",
    "sg:address":"Tanneggstrasse 3",
    "sg:city":"Arbon",
    "sg:orig_category":"Reiseb\u00fcros U Reiseveranstalter",
    "sg:phone":"+41 71 446 55 19",
    "sg:postcode":"9320",
    "sg:province":"Thurgau",
    "wof:name":"Franz K\u00e4fer Carreisen",
    "wof:placetype":"venue"
},
  "geometry": {"coordinates":[9.4215250015,47.5103187561],"type":"Point"}
}