{
  "type": "Feature",
  "properties": {
    "iso:country":"CH",
    "sg:address":"Zeughausstrasse 15",
    "sg:city":"Burgdorf",
    "sg:orig_category":"Kinderkrippen U horte",
    "sg:phone":"+41 34 422 28 17",
    "sg:postcode":"3400",
    "sg:province":"Bern",
    "wof:name":"Sch\u00fclerhorte D.stadt Burgdorf",
    "wof:placetype":"venue"
},
  "geometry": {"coordinates":[7.6150569916,47.064453125],"type":"Point"}
}