{
  "type": "Feature",
  "properties": {
    "iso:country":"CH",
    "sg:address":"Rh\u00f4ne Rue Du 78",
    "sg:city":"Gen\u00e8ve",
    "sg:orig_category":"Non-Classified Establishments",
    "sg:postcode":"1204",
    "sg:province":"Gen\u00e8ve",
    "wof:name":"Reno Pelli Gmbh",
    "wof:placetype":"venue"
},
  "geometry": {"coordinates":[9.0352497101,47.4610061646],"type":"Point"}
}