{
  "type": "Feature",
  "properties": {
    "iso:country":"CH",
    "sg:address":"Im Hasen 73",
    "sg:city":"Lauerz",
    "sg:orig_category":"Softwareentwicklung U beratung",
    "sg:postcode":"6424",
    "sg:province":"Schwyz",
    "wof:name":"Mccom Mcwilliams & Co",
    "wof:placetype":"venue"
},
  "geometry": {"coordinates":[8.5890169144,47.0304069519],"type":"Point"}
}