{
  "type": "Feature",
  "properties": {
    "iso:country":"CH",
    "sg:address":"Fr\u00fchacker 8573 Alterswilen. Postfach",
    "sg:city":"Altishausen",
    "sg:orig_category":"Fachdetailhandel in Verkaufsr\u00e4umen",
    "sg:postcode":"8573",
    "sg:province":"Thurgau",
    "wof:name":"Btw Sport + Design Gmbh",
    "wof:placetype":"venue"
},
  "geometry": {"coordinates":[9.1679496765,47.6103401184],"type":"Point"}
}