{
  "type": "Feature",
  "properties": {
    "iso:country":"CH",
    "sg:address":"L\u00e4rchenweg. 9514 Wuppenau. Postfach",
    "sg:city":"Wuppenau",
    "sg:orig_category":"Allgemeiner Hoch U Tiefbau",
    "sg:postcode":"9514",
    "sg:province":"Thurgau",
    "wof:name":"Burri Max, Generalunternehmer.",
    "wof:placetype":"venue"
},
  "geometry": {"coordinates":[9.109355,47.4963],"type":"Point"}
}