{
  "type": "Feature",
  "properties": {
    "iso:country":"CH",
    "sg:address":"Bahnhofstrasse 20",
    "sg:city":"Weinfelden",
    "sg:orig_category":"Detailhandel mit Beleuchtungs U Haushaltsgegenst\u00e4nden Detailhandel mit Geschenkartikeln U Souvenirs",
    "sg:phone":"+41 71 622 15 20",
    "sg:postcode":"8570",
    "sg:province":"Thurgau",
    "wof:name":"Pro-table Urs Wehrle Porzellan & Haushaltartikel",
    "wof:placetype":"venue"
},
  "geometry": {"coordinates":[9.106817,47.568352],"type":"Point"}
}