{
  "type": "Feature",
  "properties": {
    "iso:country":"CH",
    "sg:address":"Dorfstrasse 27",
    "sg:city":"Einigen",
    "sg:orig_category":"Maschinen and Apparate divers Grosshandel",
    "sg:phone":"+41 33 650 91 20",
    "sg:postcode":"3646",
    "sg:province":"Bern",
    "wof:name":"Beku Automaten Ag",
    "wof:placetype":"venue"
},
  "geometry": {"coordinates":[7.6474108696,46.7087593079],"type":"Point"}
}