{
  "type": "Feature",
  "properties": {
    "iso:country":"CH",
    "sg:address":"Malvaux Chemin De 10",
    "sg:city":"Evilard",
    "sg:orig_category":"K\u00fcnstlerische U schriftstellerische T\u00e4tigkeiten U Darbietungen",
    "sg:phone":"+41 32 323 43 48",
    "sg:postcode":"2533",
    "sg:province":"Bern",
    "wof:name":"4u Productions Music & Events Walther Dominique",
    "wof:placetype":"venue"
},
  "geometry": {"coordinates":[7.2369737625,47.149307251],"type":"Point"}
}