{
  "type": "Feature",
  "properties": {
    "addr:full":"Vogt Bvd Carl- 47 1205 Gen\u00e8ve. Postfach Gen\u00e8ve Gen\u00e8ve 1205",
    "addr:postcode":"1205;postfach;1205",
    "addr:street":"Bvd Carl 47",
    "iso:country":"CH",
    "sg:address":"Vogt Bvd Carl- 47 1205 Gen\u00e8ve. Postfach",
    "sg:city":"Gen\u00e8ve",
    "sg:orig_category":"Allgemeiner Hoch U Tiefbau",
    "sg:postcode":"1205",
    "sg:province":"Gen\u00e8ve",
    "wof:name":"Bissig Hans, Baugesch\u00e4ft",
    "wof:placetype":"venue"
},
  "geometry": {"coordinates":[8.615389,46.879524],"type":"Point"}
}