{
  "type": "Feature",
  "properties": {
    "iso:country":"CH",
    "sg:address":"Bahnhofstrasse 29 8810 Horgen. Postfach 629",
    "sg:city":"Horgen",
    "sg:orig_category":"Herstellung von Elektrizit\u00e4tsverteilungs U schalteinrichtungen",
    "sg:phone":"+41 17276700",
    "sg:postcode":"8810",
    "sg:province":"Z\u00fcrich",
    "wof:name":"H\u00fcni Ag Process Controls",
    "wof:placetype":"venue"
},
  "geometry": {"coordinates":[8.599935,47.260963],"type":"Point"}
}