{
  "type": "Feature",
  "properties": {
    "iso:country":"CH",
    "sg:address":"8957",
    "sg:city":"Spreitenbach",
    "sg:orig_category":"Bezirks, Sekundar, Realschulen, Oberstufe der Primarschulen",
    "sg:phone":"+41 56 401 47 51",
    "sg:postcode":"8957",
    "sg:province":"Aargau",
    "wof:name":"Sekundarschule",
    "wof:placetype":"venue"
},
  "geometry": {"coordinates":[8.365684,47.418045],"type":"Point"}
}