{
  "type": "Feature",
  "properties": {
    "iso:country":"CH",
    "sg:address":"Strengelbacherstrasse 24",
    "sg:city":"Zofingen",
    "sg:orig_category":"Detailhandel mit S\u00e4uglings U Kinderbekleidung Sonstiger Fachdetailhandel in Verkaufsr\u00e4umen",
    "sg:phone":"+41 62 752 38 00",
    "sg:postcode":"4800",
    "sg:province":"Aargau",
    "wof:name":"K\u00e4thi Fehr Baby Shop",
    "wof:placetype":"venue"
},
  "geometry": {"coordinates":[7.9381580353,47.2828674316],"type":"Point"}
}