{
  "type": "Feature",
  "properties": {
    "iso:country":"CH",
    "sg:address":"4053 Basel. Postfach 1",
    "sg:city":"Basel",
    "sg:orig_category":"Lagerung",
    "sg:phone":"+41 61 338 96 96",
    "sg:postcode":"4023",
    "sg:province":"Basel-Landschaft",
    "wof:name":"Basler Freilager Ag",
    "wof:placetype":"venue"
},
  "geometry": {"coordinates":[7.5971298218,47.5378684998],"type":"Point"}
}