{
  "type": "Feature",
  "properties": {
    "iso:country":"CH",
    "sg:address":"Britternmatte Rinderbach",
    "sg:city":"R\u00fcegsbach",
    "sg:orig_category":"Detailhandel mit Waren verschiedener Art, Hauptrichtung Nahrungsmittel",
    "sg:phone":"+41 52 264 26 16",
    "sg:postcode":"3418",
    "sg:province":"Bern",
    "wof:name":"Hans Uehlingr Brigitt's-dorflade",
    "wof:placetype":"venue"
},
  "geometry": {"coordinates":[7.9711937904,47.3276634216],"type":"Point"}
}