{
  "type": "Feature",
  "properties": {
    "iso:country":"CH",
    "sg:address":"Wichlernstrasse",
    "sg:city":"Kriens",
    "sg:orig_category":"Softwareentwicklung U beratung",
    "sg:phone":"+41 41 320 82 84",
    "sg:postcode":"6010",
    "sg:province":"Luzern",
    "wof:name":"Bossart-soft",
    "wof:placetype":"venue"
},
  "geometry": {"coordinates":[8.2731151581,47.0332565308],"type":"Point"}
}