{
  "type": "Feature",
  "properties": {
    "iso:country":"CH",
    "sg:address":"Wattstrasse 1",
    "sg:city":"Uzwil",
    "sg:orig_category":"Reiseb\u00fcros",
    "sg:phone":"+41 71 955 99 99",
    "sg:postcode":"9240",
    "sg:province":"St. Gallen",
    "wof:name":"Helvetic Tours Coop Super Center",
    "wof:placetype":"venue"
},
  "geometry": {"coordinates":[9.1390571594,47.4356079102],"type":"Point"}
}