{
  "type": "Feature",
  "properties": {
    "iso:country":"CH",
    "sg:address":"Hauptstrasse 3 4563 Gerlafingen. Postfach",
    "sg:city":"Gerlafingen",
    "sg:orig_category":"Fachdetailhandel mit pharmazeutischen Produkten",
    "sg:phone":"+41 32 675 22 88",
    "sg:postcode":"4563",
    "sg:province":"Solothurn",
    "wof:name":"Apotheke Und Drogerie Dr. S. Scheurer",
    "wof:placetype":"venue"
},
  "geometry": {"coordinates":[7.5726590157,47.1708145142],"type":"Point"}
}