{
  "type": "Feature",
  "properties": {
    "iso:country":"CH",
    "sg:address":"S\u00e4getstrasse 130",
    "sg:city":"Strengelbach",
    "sg:orig_category":"Detailhandel mit Waren verschiedener Art, Hauptrichtung Nahrungsmittel",
    "sg:phone":"+41 62 756 24 74",
    "sg:postcode":"4802",
    "sg:province":"Aargau",
    "wof:name":"Rosa Widmer",
    "wof:placetype":"venue"
},
  "geometry": {"coordinates":[7.9230780602,47.2944259644],"type":"Point"}
}