{
  "type": "Feature",
  "properties": {
    "iso:country":"CH",
    "sg:address":"R\u00fcttenenweg 65",
    "sg:city":"M\u00f6hlin",
    "sg:orig_category":"Unclassifiable Establishments",
    "sg:postcode":"4313",
    "sg:province":"Aargau",
    "wof:name":"Huna & Co",
    "wof:placetype":"venue"
},
  "geometry": {"coordinates":[7.8396430016,47.5651893616],"type":"Point"}
}