{
  "type": "Feature",
  "properties": {
    "iso:country":"CH",
    "sg:address":"Bundesplatz 2",
    "sg:city":"Zug",
    "sg:orig_category":"Architektur U Ingenieurb\u00fcros",
    "sg:phone":"+41 41 410 83 30",
    "sg:postcode":"6300",
    "sg:province":"Zug",
    "wof:name":"G & A Baufocus Ag",
    "wof:placetype":"venue"
},
  "geometry": {"coordinates":[8.515556,47.171333],"type":"Point"}
}