{
  "type": "Feature",
  "properties": {
    "iso:country":"CH",
    "sg:address":"Route De Mervelier 2e",
    "sg:city":"Corban",
    "sg:orig_category":"Herstellung von Tanks U Sammelbeh\u00e4ltern aus Metall Herstellung von Verpackungsmittelnaus Holz",
    "sg:phone":"+41 32 438 86 53",
    "sg:postcode":"2826",
    "sg:province":"Jura",
    "wof:name":"Steullet Jean-louis Sa",
    "wof:placetype":"venue"
},
  "geometry": {"coordinates":[7.4760251045,47.3463859558],"type":"Point"}
}