{
  "type": "Feature",
  "properties": {
    "iso:country":"CH",
    "sg:address":"B\u00e4lliz 10",
    "sg:city":"Thun",
    "sg:orig_category":"Unclassifiable Establishments",
    "sg:postcode":"3600",
    "sg:province":"Bern",
    "wof:name":"Han Thun Ag",
    "wof:placetype":"venue"
},
  "geometry": {"coordinates":[7.6262178421,46.759853363],"type":"Point"}
}