{
  "type": "Feature",
  "properties": {
    "iso:country":"CH",
    "sg:address":"Chemin De La Fin Dessus 1",
    "sg:city":"Mies",
    "sg:orig_category":"Sonstiger Grosshandel",
    "sg:phone":"+41 22 776 33 15",
    "sg:postcode":"1295",
    "sg:province":"Vaud",
    "wof:name":"Soci\u00e9t\u00e9 Datco S\u00e0rl.",
    "wof:placetype":"venue"
},
  "geometry": {"coordinates":[6.1760988235,46.3089599609],"type":"Point"}
}