{
  "type": "Feature",
  "properties": {
    "iso:country":"CH",
    "sg:address":"Flugbrunnenstrasse 2 3065 Bolligen. Postfach 218",
    "sg:city":"Bolligen",
    "sg:orig_category":"Rechtsberatung",
    "sg:phone":"+41 31 921 00 14",
    "sg:postcode":"3065",
    "sg:province":"Bern",
    "wof:name":"Luginb\u00fchl U. & Degiorgi D.",
    "wof:placetype":"venue"
},
  "geometry": {"coordinates":[7.4975948334,46.9750328064],"type":"Point"}
}