{
  "type": "Feature",
  "properties": {
    "iso:country":"CH",
    "sg:address":"Rue Des Glacis-de-rive 21 1200 Genf. Postfach",
    "sg:city":"Gen\u00e8ve",
    "sg:orig_category":"Interessenvertretungen",
    "sg:postcode":"1207",
    "sg:province":"Gen\u00e8ve",
    "wof:name":"Fondation Guang Ming",
    "wof:placetype":"venue"
},
  "geometry": {"coordinates":[6.1548662186,46.1996612549],"type":"Point"}
}