{
  "type": "Feature",
  "properties": {
    "addr:full":"Steinentorberg 3 Basel Basel-Stadt 4051",
    "addr:housenumber":"3",
    "addr:postcode":"4051",
    "addr:street":"Steinentorberg",
    "iso:country":"CH",
    "sg:address":"Steinentorberg 3",
    "sg:city":"Basel",
    "sg:orig_category":"Betrieb von Taxis",
    "sg:phone":"+41 61 281 90 77",
    "sg:postcode":"4051",
    "sg:province":"Basel-Stadt",
    "wof:name":"Limotion Gmbh",
    "wof:placetype":"venue"
},
  "geometry": {"coordinates":[7.587569,47.550556],"type":"Point"}
}