{
  "type": "Feature",
  "properties": {
    "iso:country":"CH",
    "sg:address":"Ringstrasse 8 4600 Olten. Postfach",
    "sg:city":"Olten",
    "sg:orig_category":"Zahnarztpraxen",
    "sg:phone":"+41 18504811",
    "sg:postcode":"4603",
    "sg:province":"Solothurn",
    "wof:name":"Dr.med.dent.l. Takacs Grossen Zahn\u00e4rztin",
    "wof:placetype":"venue"
},
  "geometry": {"coordinates":[8.4968957901,47.4924125671],"type":"Point"}
}