{
  "type": "Feature",
  "properties": {
    "iso:country":"CH",
    "sg:address":"Kurvenstrasse 9",
    "sg:city":"Lustm\u00fchle",
    "sg:orig_category":"Zahnarztpraxen",
    "sg:phone":"+41 71 333 39 92",
    "sg:postcode":"9062",
    "sg:province":"Appenzell Ausserrhoden",
    "wof:name":"Dr. Med. Dent. Helga Hitz Zahn\u00e4rztin",
    "wof:placetype":"venue"
},
  "geometry": {"coordinates":[9.3581924438,47.3978157043],"type":"Point"}
}