{
  "type": "Feature",
  "properties": {
    "iso:country":"CH",
    "sg:address":"B\u00fcelgasse 6",
    "sg:city":"Wangen",
    "sg:classifiers":[
        {
            "category":"Building & Trades",
            "subcategory":"Construction",
            "type":"Services"
        }
    ],
    "sg:phone":"+41 55 440 13 68",
    "sg:postcode":"8855",
    "sg:province":"Schwyz",
    "sg:tags":[
        "machine"
    ],
    "wof:name":"Bruhin & Diethelm Ag Maschinenbau",
    "wof:placetype":"venue"
},
  "geometry": {"coordinates":[8.8953371048,47.1952171326],"type":"Point"}
}