{
  "type": "Feature",
  "properties": {
    "iso:country":"CH",
    "sg:address":"Lindenstrasse 2",
    "sg:city":"Sarnen",
    "sg:orig_category":"Unclassifiable Establishments",
    "sg:postcode":"6060",
    "sg:province":"Obwalden",
    "wof:name":"Gravitas Treuhand + Revisions Ag",
    "wof:placetype":"venue"
},
  "geometry": {"coordinates":[8.2466259003,46.8971214294],"type":"Point"}
}