{
  "type": "Feature",
  "properties": {
    "iso:country":"CH",
    "sg:address":"Oberplattenstrasse 8",
    "sg:city":"Lichtensteig",
    "sg:orig_category":"Schreib U \u00dcbersetzungsb\u00fcros",
    "sg:postcode":"9620",
    "sg:province":"St. Gallen",
    "wof:name":"Sallauka Translations",
    "wof:placetype":"venue"
},
  "geometry": {"coordinates":[9.086432457,47.3322181702],"type":"Point"}
}