{
  "type": "Feature",
  "properties": {
    "iso:country":"CH",
    "sg:address":"Bitzistrasse 12",
    "sg:city":"Siebnen",
    "sg:orig_category":"Glaserei Herstellung von Konstruktionsteilen, Fertigbauteilen U Ausbauelementen aus Holz",
    "sg:phone":"+41 55 440 24 44",
    "sg:postcode":"8854",
    "sg:province":"Schwyz",
    "wof:name":"Aros Ag",
    "wof:placetype":"venue"
},
  "geometry": {"coordinates":[8.9032144547,47.1771125793],"type":"Point"}
}