{
  "type": "Feature",
  "properties": {
    "iso:country":"CH",
    "sg:address":"Hauptstrasse 23 9400 Rorschach. Postfach 326",
    "sg:city":"Rorschach",
    "sg:orig_category":"Fachdetailhandel in Verkaufsr\u00e4umen Handel mit Motorr\u00e4dern, Teilen U Zubeh\u00f6r Instandhaltung U Reparat",
    "sg:phone":"+41 71 841 25 89",
    "sg:postcode":"9401",
    "sg:province":"St. Gallen",
    "wof:name":"Giger Alb., Velos Motos",
    "wof:placetype":"venue"
},
  "geometry": {"coordinates":[9.4958772659,47.477684021],"type":"Point"}
}