{
  "type": "Feature",
  "properties": {
    "iso:country":"CH",
    "sg:address":"Schwarztorstrasse 61 3007 Bern. Postfach",
    "sg:city":"Bern",
    "sg:orig_category":"Rechtsberatung",
    "sg:postcode":"3050",
    "sg:province":"Bern",
    "wof:name":"Swisscom Mobile Ag",
    "wof:placetype":"venue"
},
  "geometry": {"coordinates":[7.429997921,46.9445228577],"type":"Point"}
}