{
  "type": "Feature",
  "properties": {
    "iso:country":"CH",
    "sg:address":"Manoir Ruelle Du 1",
    "sg:city":"Sierre",
    "sg:orig_category":"Grosshandel mit Nahrungsmitteln, Getr\u00e4nken U Tabakwaren ohne ausgepr\u00e4gten Schwerpunkt",
    "sg:postcode":"3960",
    "sg:province":"Valais",
    "wof:name":"Alimentation Kummer Et Cie",
    "wof:placetype":"venue"
},
  "geometry": {"coordinates":[7.5306549072,46.2924041748],"type":"Point"}
}