{
  "type": "Feature",
  "properties": {
    "iso:country":"CH",
    "sg:address":"Gare Avenue De La",
    "sg:city":"Martigny",
    "sg:orig_category":"Herstellung von M\u00fcnzen U Medaillen",
    "sg:postcode":"1920",
    "sg:province":"Valais",
    "wof:name":"Pari Louis.",
    "wof:placetype":"venue"
},
  "geometry": {"coordinates":[6.5820469856,46.534122467],"type":"Point"}
}