{
  "type": "Feature",
  "properties": {
    "addr:full":"Rennweg 57 8001 Z\u00fcrich. Postfach Z\u00fcrich Z\u00fcrich 8001",
    "addr:housenumber":"57",
    "addr:postcode":"8001 zuerich. postfach;8001",
    "addr:street":"Rennweg",
    "iso:country":"CH",
    "sg:address":"Rennweg 57 8001 Z\u00fcrich. Postfach",
    "sg:city":"Z\u00fcrich",
    "sg:orig_category":"Banken sonstige",
    "sg:phone":"+41 800 811 820",
    "sg:postcode":"8001",
    "sg:province":"Z\u00fcrich",
    "wof:name":"Banque Migros",
    "wof:placetype":"venue"
},
  "geometry": {"coordinates":[6.843275,46.462135],"type":"Point"}
}