{
  "type": "Feature",
  "properties": {
    "iso:country":"CH",
    "sg:address":"Chote 2",
    "sg:city":"Ligerz",
    "sg:orig_category":"Architektur U Ingenieurb\u00fcros",
    "sg:phone":"+41 32 315 31 31",
    "sg:postcode":"2514",
    "sg:province":"Bern",
    "wof:name":"Andry F.",
    "wof:placetype":"venue"
},
  "geometry": {"coordinates":[7.142425,47.090881],"type":"Point"}
}