{
  "type": "Feature",
  "properties": {
    "iso:country":"CH",
    "sg:address":"Au Village",
    "sg:city":"Borex",
    "sg:orig_category":"Detailhandel mit Fisch U Meeresfr\u00fcchten Detailhandel mit Fleisch U Fleischwaren",
    "sg:phone":"+41 22 367 12 18",
    "sg:postcode":"1277",
    "sg:province":"Vaud",
    "wof:name":"Jean-bernard Crottet Borex Poisson",
    "wof:placetype":"venue"
},
  "geometry": {"coordinates":[6.1780738831,46.3789787292],"type":"Point"}
}