{
  "type": "Feature",
  "properties": {
    "iso:country":"CH",
    "sg:address":"Largo Libero Olgiati 77",
    "sg:city":"Giubiasco",
    "sg:classifiers":[
        {
            "category":"Insurance",
            "subcategory":"Insurance Agent",
            "type":"Services"
        }
    ],
    "sg:phone":"+41 91 857 67 55",
    "sg:postcode":"6512",
    "sg:province":"Ticino",
    "sg:tags":[
        "versicherungsagenturen",
        "-broker"
    ],
    "wof:name":"Winterthur-assicurazioni Agenzia Rodolfo Pedroia",
    "wof:placetype":"venue"
},
  "geometry": {"coordinates":[9.0099182129,46.1726913452],"type":"Point"}
}