{
  "type": "Feature",
  "properties": {
    "iso:country":"CH",
    "sg:address":"Spitzberglistrasse 6",
    "sg:city":"Horw",
    "sg:orig_category":"Detailhandel mit M\u00f6beln U Haushaltsgegenst\u00e4nden",
    "sg:phone":"+41 41 340 33 04",
    "sg:postcode":"6048",
    "sg:province":"Luzern",
    "wof:name":"Sharzad Shafighi Damensalon",
    "wof:placetype":"venue"
},
  "geometry": {"coordinates":[8.3018169403,47.0124855042],"type":"Point"}
}