{
  "type": "Feature",
  "properties": {
    "addr:full":"Vitznau Luzern 6354",
    "addr:postcode":"6354",
    "iso:country":"CH",
    "sg:city":"Vitznau",
    "sg:orig_category":"Reisen, Reiseveranstalter",
    "sg:phone":"+41 41 399 87 87",
    "sg:postcode":"6354",
    "sg:province":"Luzern",
    "wof:name":"Rigi - Bahnen",
    "wof:placetype":"venue"
},
  "geometry": {"coordinates":[8.48331,47.010342],"type":"Point"}
}