{
  "type": "Feature",
  "properties": {
    "iso:country":"CH",
    "sg:address":"Stelzenstrasse 6",
    "sg:city":"Glattbrugg",
    "sg:orig_category":"Grosshandel mit Blumen U Pflanzen Zimmerei, Dachdeckerei, Bauspenglerei U Abdichtung",
    "sg:phone":"+41 31 939 31 91",
    "sg:postcode":"8152",
    "sg:province":"Z\u00fcrich",
    "wof:name":"Zinco Ag Dachbegr\u00fcnungssysteme",
    "wof:placetype":"venue"
},
  "geometry": {"coordinates":[7.5571708679,47.5114479065],"type":"Point"}
}