{
  "type": "Feature",
  "properties": {
    "addr:full":"Tuls. Sent Graubunden 7554",
    "addr:housenumber":"7554",
    "iso:country":"CH",
    "sg:address":"Tuls.",
    "sg:city":"Sent",
    "sg:orig_category":"Bauschreinerei Herstellung von M\u00f6beln verschiedener Art",
    "sg:phone":"+41 81 864 01 22",
    "sg:postcode":"7554",
    "sg:province":"Graubunden",
    "wof:name":"Taverna Johann Otto & Andri.",
    "wof:placetype":"venue"
},
  "geometry": {"coordinates":[10.341373,46.818535],"type":"Point"}
}