{
  "type": "Feature",
  "properties": {
    "iso:country":"CH",
    "sg:address":"Kasernenstrasse 46 8180 B\u00fclach. Postfach",
    "sg:city":"B\u00fclach",
    "sg:orig_category":"Non-Classified Establishments",
    "sg:postcode":"8180",
    "sg:province":"Z\u00fcrich",
    "wof:name":"Re.com Elektroanlagen Ag Beratung, Erstellung, Planung, Organisation U. \u00dcberwachung Von Projekten Im Bereich Der Digitalen Medien Usw",
    "wof:placetype":"venue"
},
  "geometry": {"coordinates":[8.5335054398,47.5169448853],"type":"Point"}
}