{
  "type": "Feature",
  "properties": {
    "iso:country":"CH",
    "sg:address":"Segantinistrasse 49",
    "sg:city":"Z\u00fcrich",
    "sg:orig_category":"G\u00fcterbef\u00f6rderung im Strassenverkehr",
    "sg:phone":"+41 13410968",
    "sg:postcode":"8049",
    "sg:province":"Z\u00fcrich",
    "wof:name":"Pagava Beglar",
    "wof:placetype":"venue"
},
  "geometry": {"coordinates":[8.4995708466,47.4052200317],"type":"Point"}
}