{
  "type": "Feature",
  "properties": {
    "iso:country":"CH",
    "sg:address":"Holbeinstrasse 20",
    "sg:city":"Z\u00fcrich",
    "sg:orig_category":"Architektur U Ingenieurb\u00fcros Architekturb\u00fcros",
    "sg:phone":"+41 12510541",
    "sg:postcode":"8008",
    "sg:province":"Z\u00fcrich",
    "wof:name":"Planungsgruppe 11, Architektur-atelier, H. F. Reimann",
    "wof:placetype":"venue"
},
  "geometry": {"coordinates":[8.549318,47.36388],"type":"Point"}
}