{
  "type": "Feature",
  "properties": {
    "iso:country":"CH",
    "sg:address":"Badenerstrasse 249",
    "sg:city":"Z\u00fcrich",
    "sg:orig_category":"Detailhandel mit B\u00fcchern, Zeitungen, Schreib U Papeteriewaren",
    "sg:postcode":"8003",
    "sg:province":"Z\u00fcrich",
    "wof:name":"Kiosk Sihlfeld, Dudu Dana-g\u00f6kg\u00f6z",
    "wof:placetype":"venue"
},
  "geometry": {"coordinates":[8.51628,47.375648],"type":"Point"}
}