{
  "type": "Feature",
  "properties": {
    "iso:country":"CH",
    "sg:address":"Im G\u00e4ssli 1",
    "sg:city":"Winterthur",
    "sg:orig_category":"Arztpraxen",
    "sg:phone":"+41 52 232 99 07",
    "sg:postcode":"8405",
    "sg:province":"Z\u00fcrich",
    "wof:name":"Dr.med.alfred R\u00f6sli Arzt F.allgemeine Medizin Fmh",
    "wof:placetype":"venue"
},
  "geometry": {"coordinates":[8.761972,47.484406],"type":"Point"}
}