{
  "type": "Feature",
  "properties": {
    "iso:country":"CH",
    "sg:address":"Bovon Route De 38 1302 Vufflens-la-ville. Postfach",
    "sg:city":"Vufflens-la-ville",
    "sg:orig_category":"Grosshandel mit Textilien",
    "sg:phone":"+41 21 702 35 00",
    "sg:postcode":"1302",
    "sg:province":"Vaud",
    "wof:name":"Ns New Shop Sa Commerce De Textiles Et Accessoires",
    "wof:placetype":"venue"
},
  "geometry": {"coordinates":[6.5393657684,46.5778503418],"type":"Point"}
}