{
  "type": "Feature",
  "properties": {
    "iso:country":"CH",
    "sg:address":"Kirchstrasse 42",
    "sg:city":"Freienbach",
    "sg:orig_category":"Sonstige mit der Informatik verbundene T\u00e4tigkeiten",
    "sg:phone":"+41 61 711 50 84",
    "sg:postcode":"8807",
    "sg:province":"Schwyz",
    "wof:name":"Ecosoft.net Schweiz Gmbh Informatik-dienstleistungen. Management-auftr\u00e4ge Usw",
    "wof:placetype":"venue"
},
  "geometry": {"coordinates":[7.5911569595,47.4862174988],"type":"Point"}
}