{
  "type": "Feature",
  "properties": {
    "iso:country":"CH",
    "sg:address":"Allmendstrasse 1",
    "sg:city":"Huttwil",
    "sg:orig_category":"Maler U Glasergewerbe Tapeziererei",
    "sg:phone":"+41 62 962 17 42",
    "sg:postcode":"4950",
    "sg:province":"Bern",
    "wof:name":"Paul Fl\u00fcckiger",
    "wof:placetype":"venue"
},
  "geometry": {"coordinates":[7.8511772156,47.1146774292],"type":"Point"}
}