{
  "type": "Feature",
  "properties": {
    "iso:country":"CH",
    "sg:address":"Schmittenbach",
    "sg:city":"Fischenthal",
    "sg:orig_category":"Bauingenieurb\u00fcros Hochbau Bauingenieurb\u00fcros allgemein",
    "sg:phone":"+41 62 771 09 88",
    "sg:postcode":"8497",
    "sg:province":"Z\u00fcrich",
    "wof:name":"Franz Bitterli Ag Ingenieurb\u00fcro",
    "wof:placetype":"venue"
},
  "geometry": {"coordinates":[8.184031,47.25071],"type":"Point"}
}