{
  "type": "Feature",
  "properties": {
    "iso:country":"CH",
    "sg:address":"Eisselmatt 496 3155 Helgisried. Postfach",
    "sg:city":"Helgisried",
    "sg:orig_category":"Stukkateurgewerbe, Gipserei U Verputzerei",
    "sg:postcode":"3155",
    "sg:province":"Bern",
    "wof:name":"Krebs Markus, Gipsergesch\u00e4ft",
    "wof:placetype":"venue"
},
  "geometry": {"coordinates":[7.4310312271,46.8167877197],"type":"Point"}
}