{
  "type": "Feature",
  "properties": {
    "iso:country":"CH",
    "sg:address":"Grand-ch\u00eane Rue Du 2 1003 Lausanne. Postfach",
    "sg:city":"Lausanne",
    "sg:orig_category":"Vermietung U Verpachtung von eigenen Immobilien",
    "sg:phone":"+41 56 441 60 84",
    "sg:postcode":"1003",
    "sg:province":"Vaud",
    "wof:name":"Savaris Immobilien Ag",
    "wof:placetype":"venue"
},
  "geometry": {"coordinates":[8.2014408112,47.4823226929],"type":"Point"}
}