{
  "type": "Feature",
  "properties": {
    "iso:country":"CH",
    "sg:address":"Via Municipio 11",
    "sg:city":"Muralto",
    "sg:orig_category":"Herstellung von keramischen Haushaltswaren U Ziergegenst\u00e4nden",
    "sg:phone":"+41 91 743 36 65",
    "sg:postcode":"6600",
    "sg:province":"Ticino",
    "wof:name":"Federico Masa Ars-ceramica & Artigianato",
    "wof:placetype":"venue"
},
  "geometry": {"coordinates":[8.8068552017,46.1731414795],"type":"Point"}
}