{
  "type": "Feature",
  "properties": {
    "iso:country":"CH",
    "sg:address":"Bernstrasse 217",
    "sg:city":"Zollikofen",
    "sg:orig_category":"Lettershops and Versandservice",
    "sg:phone":"+41 61 401 16 21",
    "sg:postcode":"3052",
    "sg:province":"Bern",
    "wof:name":"Kurt Stricker Brief-postbearbeitungs-service",
    "wof:placetype":"venue"
},
  "geometry": {"coordinates":[7.5624527931,47.5164489746],"type":"Point"}
}