{
  "type": "Feature",
  "properties": {
    "iso:country":"CH",
    "sg:address":"Scheuchzerstrasse 14",
    "sg:city":"Z\u00fcrich",
    "sg:orig_category":"Unclassifiable Establishments",
    "sg:postcode":"8006",
    "sg:province":"Z\u00fcrich",
    "wof:name":"Institut F\u00fcr Systemische Beratung Messmer",
    "wof:placetype":"venue"
},
  "geometry": {"coordinates":[8.5454273224,47.3831253052],"type":"Point"}
}