{
  "type": "Feature",
  "properties": {
    "iso:country":"CH",
    "sg:address":"Maison Rouge",
    "sg:city":"Burtigny",
    "sg:orig_category":"Architekturb\u00fcros",
    "sg:phone":"+41 22 366 28 88",
    "sg:postcode":"1261",
    "sg:province":"Vaud",
    "wof:name":"Daniel Redard Bureau D'architecture",
    "wof:placetype":"venue"
},
  "geometry": {"coordinates":[6.272745,46.475723],"type":"Point"}
}