{
  "type": "Feature",
  "properties": {
    "iso:country":"CH",
    "sg:address":"Moosstrasse 15 6003 Luzern. Postfach",
    "sg:city":"Luzern",
    "sg:orig_category":"Herstellung von medizinischen U chirurgischen Ger\u00e4ten sowie orthop\u00e4dischen Vorrichtungen",
    "sg:phone":"+41 41 210 84 24",
    "sg:postcode":"6003",
    "sg:province":"Luzern",
    "wof:name":"Dental Labor Faes G. Dental-labor",
    "wof:placetype":"venue"
},
  "geometry": {"coordinates":[8.3061056137,47.0457420349],"type":"Point"}
}