{
  "type": "Feature",
  "properties": {
    "addr:full":"Buchbergweg 7 Oberburg Bern 3414",
    "addr:housenumber":"7",
    "addr:postcode":"3414",
    "addr:street":"Buchbergweg",
    "iso:country":"CH",
    "sg:address":"Buchbergweg 7",
    "sg:city":"Oberburg",
    "sg:orig_category":"Arztpraxen",
    "sg:phone":"+41 34 422 62 13",
    "sg:postcode":"3414",
    "sg:province":"Bern",
    "wof:name":"Dr.med.paul Wittwer Arzt F.allgemeine Medizin Fmh",
    "wof:placetype":"venue"
},
  "geometry": {"coordinates":[7.619127,47.038414],"type":"Point"}
}