{
  "type": "Feature",
  "properties": {
    "iso:country":"CH",
    "sg:address":"Seestrasse 25",
    "sg:city":"Gersau",
    "sg:orig_category":"RESTAURANTS: TEA-ROOMS",
    "sg:phone":"+41 41 828 12 14",
    "sg:postcode":"6442",
    "sg:province":"Schwyz",
    "wof:name":"Camenzind-nigg Marlies Und Otto",
    "wof:placetype":"venue"
},
  "geometry": {"coordinates":[8.5267019272,46.9906845093],"type":"Point"}
}