{
  "type": "Feature",
  "properties": {
    "iso:country":"CH",
    "sg:address":"Boulevard De P\u00e9rolles 37 1700 Fribourg. Postfach",
    "sg:city":"Fribourg",
    "sg:orig_category":"Architekturb\u00fcros",
    "sg:phone":"+41 26 424 51 21",
    "sg:postcode":"1701",
    "sg:province":"Fribourg",
    "wof:name":"Jean-denis Collaud Bureau D'architecture",
    "wof:placetype":"venue"
},
  "geometry": {"coordinates":[7.15385,46.797455],"type":"Point"}
}