{
  "type": "Feature",
  "properties": {
    "iso:country":"CH",
    "sg:address":"Chemin Du Ch\u00eane 3 2615 Montagne-sonvilier Case Postale 13",
    "sg:city":"Montagne-sonvilier",
    "sg:orig_category":"Herstellung von M\u00f6beln",
    "sg:phone":"+41 32 941 11 60",
    "sg:postcode":"2615",
    "sg:province":"Bern",
    "wof:name":"Ameublement Tanner Sa",
    "wof:placetype":"venue"
},
  "geometry": {"coordinates":[6.9661917686,47.1391410828],"type":"Point"}
}