{
  "type": "Feature",
  "properties": {
    "iso:country":"CH",
    "sg:address":"Egerta 53 9496 Balzers. Postfach 148",
    "sg:city":"Balzers",
    "sg:orig_category":"Verwaltung von Immobilien",
    "sg:phone":"+423 388 02 02",
    "sg:postcode":"9496",
    "wof:name":"Fiduciana Verwaltungsanstalt",
    "wof:placetype":"venue"
},
  "geometry": {"coordinates":[9.5077943802,47.07213974],"type":"Point"}
}