{
  "type": "Feature",
  "properties": {
    "iso:country":"CH",
    "sg:address":"Hasenrainstrasse 59",
    "sg:city":"Binningen",
    "sg:classifiers":[
        {
            "category":"Restaurant",
            "type":"Food & Drink"
        }
    ],
    "sg:phone":"+41 61 421 24 30",
    "sg:postcode":"4102",
    "sg:province":"Basel-Landschaft",
    "wof:name":"Restaurant The Castle",
    "wof:placetype":"venue"
},
  "geometry": {"coordinates":[7.569560051,47.5439147949],"type":"Point"}
}