{
  "type": "Feature",
  "properties": {
    "iso:country":"CH",
    "sg:address":"Zugerstrasse 6340 Baar. Postfach",
    "sg:city":"Baar",
    "sg:orig_category":"Unclassifiable Establishments",
    "sg:phone":"+41 61 976 55 55",
    "sg:postcode":"6340",
    "sg:province":"Zug",
    "wof:name":"Gysin Ag",
    "wof:placetype":"venue"
},
  "geometry": {"coordinates":[7.7473831177,47.3935241699],"type":"Point"}
}