{
  "type": "Feature",
  "properties": {
    "iso:country":"CH",
    "sg:address":"7205",
    "sg:city":"Zizers",
    "sg:orig_category":"Non-Classified Establishments",
    "sg:postcode":"7205",
    "sg:province":"Graubunden",
    "wof:name":"K. G\u00e4mperli, Sportcenter F\u00fcnf D\u00f6rfer",
    "wof:placetype":"venue"
},
  "geometry": {"coordinates":[9.5652751923,46.9360046387],"type":"Point"}
}