{
  "type": "Feature",
  "properties": {
    "iso:country":"CH",
    "sg:address":"Loestrasse 54",
    "sg:city":"Chur",
    "sg:orig_category":"Betrieb U technische Hilfsdienste des Kultur U Unterhaltungswesens",
    "sg:postcode":"7000",
    "sg:province":"Graubunden",
    "wof:name":"Neue Theatergenossenschaft Chur Ntg",
    "wof:placetype":"venue"
},
  "geometry": {"coordinates":[9.537837,46.857304],"type":"Point"}
}