{
  "type": "Feature",
  "properties": {
    "iso:country":"CH",
    "sg:address":"Breiten",
    "sg:city":"Lohnstorf",
    "sg:classifiers":[
        {
            "category":"Insurance",
            "subcategory":"Insurance Agent",
            "type":"Services"
        }
    ],
    "sg:phone":"+41 31 809 10 20",
    "sg:postcode":"3127",
    "sg:province":"Bern",
    "sg:tags":[
        "versicherungsagenturen",
        "-broker"
    ],
    "wof:name":"Emmentalische Mobiliarversich. Agentur Thurnen U.haslebacher",
    "wof:placetype":"venue"
},
  "geometry": {"coordinates":[7.5088820457,46.8062438965],"type":"Point"}
}