{
  "type": "Feature",
  "properties": {
    "iso:country":"CH",
    "sg:address":"Burgackerweg 11",
    "sg:city":"Zeiningen",
    "sg:orig_category":"Politische Parteien SVP",
    "sg:phone":"+41 61 851 23 06",
    "sg:postcode":"4314",
    "sg:province":"Aargau",
    "wof:name":"Svp Ortspartei Zeiningen",
    "wof:placetype":"venue"
},
  "geometry": {"coordinates":[7.8771290779,47.5442886353],"type":"Point"}
}