{
  "type": "Feature",
  "properties": {
    "iso:country":"CH",
    "sg:address":"S\u00fcri",
    "sg:city":"Rossh\u00e4usern",
    "sg:orig_category":"Gartenbau",
    "sg:phone":"+41 33 733 13 47",
    "sg:postcode":"3204",
    "sg:province":"Bern",
    "wof:name":"Ernst Marggi Gartenbau",
    "wof:placetype":"venue"
},
  "geometry": {"coordinates":[7.4355912209,46.4722595215],"type":"Point"}
}