{
  "type": "Feature",
  "properties": {
    "iso:country":"CH",
    "sg:address":"Ernst M\u00fcller-strasse 8 8200 Schaffhausen. Postfach",
    "sg:city":"Schaffhausen",
    "sg:orig_category":"Sanit\u00e4r, Heizungs U L\u00fcftungsinstallation",
    "sg:postcode":"8207",
    "sg:province":"Schaffhausen",
    "wof:name":"Sanhag",
    "wof:placetype":"venue"
},
  "geometry": {"coordinates":[8.6425094604,47.7072372437],"type":"Point"}
}