{
  "type": "Feature",
  "properties": {
    "iso:country":"CH",
    "sg:address":"3206",
    "sg:city":"Rizenbach",
    "sg:orig_category":"Selbst\u00e4ndige bildende K\u00fcnstler",
    "sg:phone":"+41 31 751 09 40",
    "sg:postcode":"3206",
    "sg:province":"Bern",
    "wof:name":"Ernst Scheidegger Glasmalerei",
    "wof:placetype":"venue"
},
  "geometry": {"coordinates":[7.2261400223,46.9422798157],"type":"Point"}
}