{
  "type": "Feature",
  "properties": {
    "iso:country":"CH",
    "sg:address":"Rehhagstrasse 37 3018 Bern. Postfach",
    "sg:city":"Bern",
    "sg:orig_category":"Herstellung von Teppichen",
    "sg:postcode":"3018",
    "sg:province":"Bern",
    "wof:name":"Stern Bodenbel\u00e4ge Gmbh Dienstl. Im Baugewerbe, Bes. Erst. V. Bodenbel\u00e4gen Usw",
    "wof:placetype":"venue"
},
  "geometry": {"coordinates":[7.3875927925,46.9373664856],"type":"Point"}
}