{
  "type": "Feature",
  "properties": {
    "iso:country":"CH",
    "sg:address":"R\u00fcmikerstrasse 56 8352 R\u00e4terschen. Postfach",
    "sg:city":"R\u00e4terschen",
    "sg:orig_category":"Betrieb von Sportanlagen",
    "sg:postcode":"8352",
    "sg:province":"Z\u00fcrich",
    "wof:name":"Tennisarena, Waldenberger B. + H. Tenniscenter",
    "wof:placetype":"venue"
},
  "geometry": {"coordinates":[8.78213,47.504791],"type":"Point"}
}