{
  "type": "Feature",
  "properties": {
    "iso:country":"CH",
    "sg:address":"Route Des Marais 12",
    "sg:city":"Marin-epagnier",
    "sg:orig_category":"File Dressing Machines",
    "sg:phone":"+41 32 753 62 35",
    "sg:postcode":"2074",
    "sg:province":"Neuch\u00e2tel",
    "wof:name":"Kuhn Service",
    "wof:placetype":"venue"
},
  "geometry": {"coordinates":[7.0208501816,47.0075645447],"type":"Point"}
}