{
  "type": "Feature",
  "properties": {
    "iso:country":"CH",
    "sg:address":"Ringstrasse 19",
    "sg:city":"Zunzgen",
    "sg:orig_category":"Fahrschulen, Flugschulen",
    "sg:phone":"+41 79 645 71 21",
    "sg:postcode":"4455",
    "sg:province":"Basel-Landschaft",
    "wof:name":"Ren\u00e9 Zumbrunn Autofahrschule",
    "wof:placetype":"venue"
},
  "geometry": {"coordinates":[7.8045902252,47.4530334473],"type":"Point"}
}