{
  "type": "Feature",
  "properties": {
    "iso:country":"CH",
    "sg:address":"En M\u00e9r\u00e9naz",
    "sg:city":"Poliez-le-grand",
    "sg:orig_category":"Sanit\u00e4r, Heizungs U L\u00fcftungsinstallation",
    "sg:phone":"+41 21 882 11 56",
    "sg:postcode":"1041",
    "sg:province":"Vaud",
    "wof:name":"Gaudard Patrice",
    "wof:placetype":"venue"
},
  "geometry": {"coordinates":[6.6657547951,46.6367492676],"type":"Point"}
}