{
  "type": "Feature",
  "properties": {
    "iso:country":"CH",
    "sg:address":"Route Du Ch\u00e2teau D'affry 6",
    "sg:city":"Givisiez",
    "sg:orig_category":"Sanit\u00e4r U Heizungsinstallation",
    "sg:phone":"+41 26 912 46 96",
    "sg:postcode":"1762",
    "sg:province":"Fribourg",
    "wof:name":"Elcotherm Ag",
    "wof:placetype":"venue"
},
  "geometry": {"coordinates":[1.5530380011,49.2477798462],"type":"Point"}
}