{
  "type": "Feature",
  "properties": {
    "iso:country":"CH",
    "sg:address":"Industriestrasse 4a 8604 Volketswil. Postfach",
    "sg:city":"Volketswil",
    "sg:orig_category":"Maschinen-Fabrikation",
    "sg:phone":"+41 19136611",
    "sg:postcode":"8604",
    "sg:province":"Z\u00fcrich",
    "wof:name":"Maag Gebr\u00fcder, Maschinenfabrik Ag",
    "wof:placetype":"venue"
},
  "geometry": {"coordinates":[8.5857868195,47.3129196167],"type":"Point"}
}