{
  "type": "Feature",
  "properties": {
    "iso:country":"CH",
    "sg:address":"Waldstrasse 15",
    "sg:city":"Biberist",
    "sg:classifiers":[
        {
            "category":"Professional",
            "subcategory":"Employment Agencies",
            "type":"Services"
        }
    ],
    "sg:phone":"+41 32 672 38 72",
    "sg:postcode":"4562",
    "sg:province":"Solothurn",
    "sg:tags":[
        "personal",
        "u",
        "stellenvermittlung"
    ],
    "wof:name":"Pr\u00e9tat Consulting",
    "wof:placetype":"venue"
},
  "geometry": {"coordinates":[7.5548448563,47.1877365112],"type":"Point"}
}