{
  "type": "Feature",
  "properties": {
    "iso:country":"CH",
    "sg:address":"3979",
    "sg:city":"Gr\u00f4ne",
    "sg:orig_category":"G\u00fcterbef\u00f6rderung im Strassenverkehr",
    "sg:phone":"+41 27 458 21 51",
    "sg:postcode":"3979",
    "sg:province":"Valais",
    "wof:name":"Ballestraz Ren\u00e9 Et Fils Transports Sa",
    "wof:placetype":"venue"
},
  "geometry": {"coordinates":[7.4571409225,46.2511062622],"type":"Point"}
}