{
  "type": "Feature",
  "properties": {
    "iso:country":"CH",
    "sg:address":"Rougemont Rue Denis-de- 20",
    "sg:city":"Neuenburg",
    "sg:orig_category":"Non-Classified Establishments",
    "sg:phone":"+41 32 721 42 68",
    "sg:postcode":"2000",
    "sg:province":"Neuch\u00e2tel",
    "wof:name":"Aba Taxi - Pola",
    "wof:placetype":"venue"
},
  "geometry": {"coordinates":[6.917470932,47.0009689331],"type":"Point"}
}