{
  "type": "Feature",
  "properties": {
    "iso:country":"CH",
    "sg:address":"Grand'rue 52 1373 Chavornay. Postfach",
    "sg:city":"Chavornay",
    "sg:orig_category":"Werbung",
    "sg:phone":"+41 71 877 37 77",
    "sg:postcode":"1373",
    "sg:province":"Vaud",
    "wof:name":"Easy Scan.buff Christian Druckvorstufe, Werbung, High-end-scans Usw.; Herstellung, Beratung",
    "wof:placetype":"venue"
},
  "geometry": {"coordinates":[9.4905567169,47.415512085],"type":"Point"}
}