{
  "type": "Feature",
  "properties": {
    "iso:country":"CH",
    "sg:address":"Batteriestrasse 2",
    "sg:city":"Bottmingen",
    "sg:orig_category":"Physiotherapie",
    "sg:phone":"+41 61 422 03 36",
    "sg:postcode":"4103",
    "sg:province":"Basel-Landschaft",
    "wof:name":"Physiotherapie Wuhrmatt",
    "wof:placetype":"venue"
},
  "geometry": {"coordinates":[7.574652195,47.5276870728],"type":"Point"}
}