{
  "type": "Feature",
  "properties": {
    "iso:country":"CH",
    "sg:address":"Glarnerstrasse 14",
    "sg:city":"Siebnen",
    "sg:orig_category":"Fachdetailhandel in Verkaufsr\u00e4umen",
    "sg:postcode":"8854",
    "sg:province":"Schwyz",
    "wof:name":"Seiler Alice, Uhren, Bijouterie, Optik",
    "wof:placetype":"venue"
},
  "geometry": {"coordinates":[8.898434639,47.1746444702],"type":"Point"}
}