{
  "type": "Feature",
  "properties": {
    "iso:country":"CH",
    "sg:address":"Dufourstrasse 40",
    "sg:city":"St.gallen",
    "sg:orig_category":"Unclassifiable Establishments",
    "sg:phone":"+41 71 493 51 11",
    "sg:postcode":"9000",
    "sg:province":"St. Gallen",
    "wof:name":"Helvetia Patria Holding",
    "wof:placetype":"venue"
},
  "geometry": {"coordinates":[9.3772001266,47.4321632385],"type":"Point"}
}