{
  "type": "Feature",
  "properties": {
    "iso:country":"CH",
    "sg:address":"Valmont Avenue De 15",
    "sg:city":"Lausanne",
    "sg:orig_category":"Stukkateurgewerbe, Gipserei U Verputzerei",
    "sg:postcode":"1010",
    "sg:province":"Vaud",
    "wof:name":"Fernando Miguel Gypserie & Peinture",
    "wof:placetype":"venue"
},
  "geometry": {"coordinates":[6.998696804,47.2085762024],"type":"Point"}
}