{
  "type": "Feature",
  "properties": {
    "iso:country":"CH",
    "sg:address":"Solothurnstrasse 30",
    "sg:city":"Grenchen",
    "sg:orig_category":"Betrieb U technische Hilfsdienste des Kultur U Unterhaltungswesens",
    "sg:phone":"+41 32 652 21 58",
    "sg:postcode":"2540",
    "sg:province":"Solothurn",
    "wof:name":"Swifresa Gmbh",
    "wof:placetype":"venue"
},
  "geometry": {"coordinates":[7.397895,47.192493],"type":"Point"}
}