{
  "type": "Feature",
  "properties": {
    "addr:full":"Speicherweg 6 Steffisburg Bern 3612",
    "addr:housenumber":"6",
    "addr:postcode":"3612",
    "addr:street":"Speicherweg;Bern",
    "iso:country":"CH",
    "sg:address":"Speicherweg 6",
    "sg:city":"Steffisburg",
    "sg:orig_category":"Allgemeiner Hoch U Tiefbau",
    "sg:phone":"+41 62 873 00 70",
    "sg:postcode":"3612",
    "sg:province":"Bern",
    "wof:name":"M. Eugster Anlagenmonteur",
    "wof:placetype":"venue"
},
  "geometry": {"coordinates":[7.954649,47.544052],"type":"Point"}
}