{
  "type": "Feature",
  "properties": {
    "iso:country":"CH",
    "sg:address":"Fauquez Route Aloys- 50 1018 Lausanne. Postfach",
    "sg:city":"Lausanne",
    "sg:orig_category":"Pensionskassen",
    "sg:phone":"+41 21 312 55 81",
    "sg:postcode":"1018",
    "sg:province":"Vaud",
    "wof:name":"Fondation Georges T. Sickel En Faveur Du Personnel De La Maison Sickel Sa",
    "wof:placetype":"venue"
},
  "geometry": {"coordinates":[6.6335787773,46.5341262817],"type":"Point"}
}