{
  "type": "Feature",
  "properties": {
    "addr:full":"Aargauerstrasse 3 Mellingen Aargau 5507",
    "addr:housenumber":"3",
    "addr:postcode":"5507",
    "addr:street":"Aargauerstrasse",
    "iso:country":"CH",
    "sg:address":"Aargauerstrasse 3",
    "sg:city":"Mellingen",
    "sg:classifiers":[
        {
            "category":"Manufacturing",
            "subcategory":"Printing",
            "type":"Manufacturing & Wholesale Goods"
        }
    ],
    "sg:phone":"+41 56 470 66 66",
    "sg:postcode":"5507",
    "sg:province":"Aargau",
    "sg:tags":[
        "house",
        "book"
    ],
    "wof:name":"Druckerei Patrick Rohr",
    "wof:placetype":"venue"
},
  "geometry": {"coordinates":[8.268421,47.419407],"type":"Point"}
}