{
  "type": "Feature",
  "properties": {
    "iso:country":"CH",
    "sg:address":"Hauptstrasse 47",
    "sg:city":"D\u00f6ttingen",
    "sg:classifiers":[
        {
            "category":"Restaurant",
            "type":"Food & Drink"
        }
    ],
    "sg:phone":"+41 56 245 14 70",
    "sg:postcode":"5312",
    "sg:province":"Aargau",
    "wof:name":"Restaurant Salmen",
    "wof:placetype":"venue"
},
  "geometry": {"coordinates":[8.2564754486,47.5706977844],"type":"Point"}
}