{
  "type": "Feature",
  "properties": {
    "iso:country":"CH",
    "sg:address":"Dorfstrasse 45",
    "sg:city":"Kemptthal",
    "sg:orig_category":"Bauschreinerei Innenausbau",
    "sg:phone":"+41 56 443 10 27",
    "sg:postcode":"8310",
    "sg:province":"Z\u00fcrich",
    "wof:name":"Konecek Roland",
    "wof:placetype":"venue"
},
  "geometry": {"coordinates":[8.157682,47.435722],"type":"Point"}
}