{
  "type": "Feature",
  "properties": {
    "iso:country":"CH",
    "sg:address":"Unter Altstadt 17",
    "sg:city":"Zug",
    "sg:orig_category":"Detailhandel mit Haustieren U zoologischem Bedarf",
    "sg:phone":"+41 41 711 60 70",
    "sg:postcode":"6300",
    "sg:province":"Zug",
    "wof:name":"Elisabeth Gisiger Zoo-boutique",
    "wof:placetype":"venue"
},
  "geometry": {"coordinates":[8.5144147873,47.1654624939],"type":"Point"}
}