{
  "type": "Feature",
  "properties": {
    "iso:country":"CH",
    "sg:address":"Ahornweg 6",
    "sg:city":"Inkwil",
    "sg:orig_category":"Zimmerei, Dachdeckerei, Bauspenglerei U Abdichtung",
    "sg:phone":"+41 62 961 37 01",
    "sg:postcode":"3375",
    "sg:province":"Bern",
    "wof:name":"Stalder Holzbauplanung Gmbh",
    "wof:placetype":"venue"
},
  "geometry": {"coordinates":[7.6729049683,47.1977729797],"type":"Point"}
}