{
  "type": "Feature",
  "properties": {
    "iso:country":"CH",
    "sg:address":"Altenburgstrasse 30",
    "sg:city":"Wettingen",
    "sg:orig_category":"Architektur U Ingenieurb\u00fcros",
    "sg:phone":"+41 21 728 23 94",
    "sg:postcode":"5430",
    "sg:province":"Aargau",
    "wof:name":"Alberti Ing\u00e9nieurs Sa",
    "wof:placetype":"venue"
},
  "geometry": {"coordinates":[6.644933,46.514832],"type":"Point"}
}