{
  "type": "Feature",
  "properties": {
    "addr:full":"Oberdorfstrasse 20 Flawil St. Gallen 9230",
    "addr:housenumber":"20",
    "addr:postcode":"9230",
    "addr:street":"Oberdorfstrasse",
    "iso:country":"CH",
    "sg:address":"Oberdorfstrasse 20",
    "sg:city":"Flawil",
    "sg:orig_category":"Detailhandel mit Brot, Back U S\u00fcsswaren",
    "sg:phone":"+41 71 393 16 24",
    "sg:postcode":"9230",
    "sg:province":"St. Gallen",
    "wof:name":"Peter Lichtensteiger B\u00e4ckerei-konditorei",
    "wof:placetype":"venue"
},
  "geometry": {"coordinates":[9.187604,47.415718],"type":"Point"}
}