{
  "type": "Feature",
  "properties": {
    "iso:country":"CH",
    "sg:address":"Zugerstrasse 25 8820 W\u00e4denswil. Postfach 265",
    "sg:city":"W\u00e4denswil",
    "sg:orig_category":"Detailhandel mit Uhren U Schmuck Reparatur von Uhren U Schmuck",
    "sg:phone":"+41 17802919",
    "sg:postcode":"8820",
    "sg:province":"Z\u00fcrich",
    "wof:name":"Guelbert Gmbh Uhrenatelier, Bijouterie",
    "wof:placetype":"venue"
},
  "geometry": {"coordinates":[8.6698894501,47.2295799255],"type":"Point"}
}