{
  "type": "Feature",
  "properties": {
    "iso:country":"CH",
    "sg:address":"Botzet Rue Du 9",
    "sg:city":"Fribourg",
    "sg:orig_category":"Interessenvertretungen",
    "sg:postcode":"1700",
    "sg:province":"Fribourg",
    "wof:name":"Projet De Paix, Pr\u00e9vention Des Conflits",
    "wof:placetype":"venue"
},
  "geometry": {"coordinates":[7.1569709778,46.7968406677],"type":"Point"}
}