{
  "type": "Feature",
  "properties": {
    "iso:country":"CH",
    "sg:address":"Rue De La Gare 7",
    "sg:city":"Tramelan",
    "sg:classifiers":[
        {
            "category":"Wholesale",
            "subcategory":"Machinery & Supplies",
            "type":"Manufacturing & Wholesale Goods"
        }
    ],
    "sg:phone":"+41 22 707 31 31",
    "sg:postcode":"2720",
    "sg:province":"Bern",
    "sg:tags":[
        "equipment",
        "equipement",
        "precision",
        "timekeeping"
    ],
    "wof:name":"Baume & Mercier Sa Branch Of Richmont International",
    "wof:placetype":"venue"
},
  "geometry": {"coordinates":[6.1738739014,46.1999130249],"type":"Point"}
}