{
  "type": "Feature",
  "properties": {
    "iso:country":"CH",
    "sg:address":"Via Magazzini Generali 7",
    "sg:city":"Balerna",
    "sg:orig_category":"Non-Classified Establishments",
    "sg:postcode":"6828",
    "sg:province":"Ticino",
    "wof:name":"Coduri & Gilardi Sa",
    "wof:placetype":"venue"
},
  "geometry": {"coordinates":[9.0171222687,45.8392181396],"type":"Point"}
}