{
  "type": "Feature",
  "properties": {
    "addr:full":"Seestrasse 11 Z\u00fcrich Z\u00fcrich 8002",
    "addr:housenumber":"11",
    "addr:postcode":"8002",
    "addr:street":"Seestrasse",
    "iso:country":"CH",
    "sg:address":"Seestrasse 11",
    "sg:city":"Z\u00fcrich",
    "sg:orig_category":"Architektur U Ingenieurb\u00fcros",
    "sg:postcode":"8002",
    "sg:province":"Z\u00fcrich",
    "wof:name":"Lazar Thomas, Dipl. Architekt Eth",
    "wof:placetype":"venue"
},
  "geometry": {"coordinates":[8.531676,47.365063],"type":"Point"}
}