{
  "type": "Feature",
  "properties": {
    "iso:country":"CH",
    "sg:address":"Lagerstrasse 95",
    "sg:city":"Z\u00fcrich",
    "sg:orig_category":"Reiseb\u00fcros U Reiseveranstalter",
    "sg:phone":"+41 41 418 50 60",
    "sg:postcode":"8004",
    "sg:province":"Z\u00fcrich",
    "wof:name":"Travel Tours Agency Ag",
    "wof:placetype":"venue"
},
  "geometry": {"coordinates":[8.3109292984,47.0576553345],"type":"Point"}
}