{
  "type": "Feature",
  "properties": {
    "iso:country":"CH",
    "sg:address":"Pringy 1663 Gruy\u00e8res. Postfach",
    "sg:city":"Pringy",
    "sg:orig_category":"Herstellung von Teppichen",
    "sg:postcode":"1662",
    "wof:name":"Wicky Michel",
    "wof:placetype":"venue"
},
  "geometry": {"coordinates":[7.0800499916,46.5818710327],"type":"Point"}
}