{
  "type": "Feature",
  "properties": {
    "iso:country":"CH",
    "sg:address":"Schrennengasse 22 8003 Z\u00fcrich. Postfach",
    "sg:city":"Z\u00fcrich",
    "sg:orig_category":"Bestattungswesen",
    "sg:postcode":"8003",
    "sg:province":"Z\u00fcrich",
    "wof:name":"Colic Olgica Bestattungsunternehmen, Transporte U. \u00dcberf\u00fchrungen. Erledigung Aller Formalit\u00e4ten Mit \u00c4mtern Usw",
    "wof:placetype":"venue"
},
  "geometry": {"coordinates":[8.515387,47.369991],"type":"Point"}
}