{
  "type": "Feature",
  "properties": {
    "iso:country":"CH",
    "sg:address":"Dufourstrasse 147",
    "sg:city":"Z\u00fcrich",
    "sg:orig_category":"Sonstige mit der Informatik verbundene T\u00e4tigkeiten",
    "sg:postcode":"8008",
    "sg:province":"Z\u00fcrich",
    "wof:name":"H\u00d6ft & Wessel Ag",
    "wof:placetype":"venue"
},
  "geometry": {"coordinates":[8.5539855957,47.3560905457],"type":"Point"}
}