{
  "type": "Feature",
  "properties": {
    "addr:full":"Hofackerstrasse 216a Wilchingen Schaffhausen 8217",
    "addr:housenumber":"216a",
    "addr:postcode":"8217",
    "addr:street":"Hofackerstrasse",
    "iso:country":"CH",
    "sg:address":"Hofackerstrasse 216a",
    "sg:city":"Wilchingen",
    "sg:classifiers":[
        {
            "category":"Social Services",
            "subcategory":"Retirement Home",
            "type":"Services"
        }
    ],
    "sg:phone":"+41 52 681 48 68",
    "sg:postcode":"8217",
    "sg:province":"Schaffhausen",
    "sg:tags":[
        "pflegeheime",
        "u",
        "alters"
    ],
    "wof:name":"Alters-& Pflegeheim Altershaamet",
    "wof:placetype":"venue"
},
  "geometry": {"coordinates":[8.467798,47.670143],"type":"Point"}
}