{
  "type": "Feature",
  "properties": {
    "iso:country":"CH",
    "sg:address":"Leimern 3638 Blumenstein. Postfach 20",
    "sg:city":"Blumenstein",
    "sg:orig_category":"Herstellung von Konstruktionsteilen, Fertigbauteilen U Ausbauelementen aus Holz",
    "sg:phone":"+41 91 646 89 36",
    "sg:postcode":"3638",
    "sg:province":"Bern",
    "wof:name":"A. Cereghetti & G. Capitanio Fabbrica Mobili & Serramenti",
    "wof:placetype":"venue"
},
  "geometry": {"coordinates":[9.0076999664,45.8654785156],"type":"Point"}
}