{
  "type": "Feature",
  "properties": {
    "iso:country":"CH",
    "sg:address":"Chemin Des Guidoux",
    "sg:city":"Saxon",
    "sg:classifiers":[
        {
            "category":"Utilities",
            "subcategory":"Water",
            "type":"Services"
        }
    ],
    "sg:phone":"+41 27 743 20 60",
    "sg:postcode":"1907",
    "sg:province":"Valais",
    "sg:tags":[
        "waters",
        "natural",
        "mineral"
    ],
    "wof:name":"Alpwater S.a.",
    "wof:placetype":"venue"
},
  "geometry": {"coordinates":[7.1664199829,46.1516304016],"type":"Point"}
}