{
  "type": "Feature",
  "properties": {
    "iso:country":"CH",
    "sg:address":"Rue De Bourg 33 1000 Lausanne. Postfach",
    "sg:city":"Lausanne",
    "sg:orig_category":"Allgemeiner Hoch U Tiefbau",
    "sg:phone":"+41 21 312 27 90",
    "sg:postcode":"1003",
    "sg:province":"Vaud",
    "wof:name":"Entreprise G\u00e9n\u00e9rale Piko T.",
    "wof:placetype":"venue"
},
  "geometry": {"coordinates":[6.635711,46.520088],"type":"Point"}
}