{
  "type": "Feature",
  "properties": {
    "iso:country":"CH",
    "sg:address":"Klusi 12",
    "sg:city":"Grindelwald",
    "sg:orig_category":"S\u00e4gewerke",
    "sg:phone":"+41 79 335 96 81",
    "sg:postcode":"3818",
    "sg:province":"Bern",
    "wof:name":"Peter Bohren S\u00e4gerei",
    "wof:placetype":"venue"
},
  "geometry": {"coordinates":[8.051738739,46.6310691833],"type":"Point"}
}