{
  "type": "Feature",
  "properties": {
    "iso:country":"CH",
    "sg:address":"Molkereistrasse 3",
    "sg:city":"Jona",
    "sg:orig_category":"Kauf U Verkauf von Immobilien auf eigene Rechnung Vermittlung von Immobilien",
    "sg:phone":"+41 55 225 37 70",
    "sg:postcode":"8645",
    "sg:province":"St. Gallen",
    "wof:name":"Isag Kb Immoservice Ag",
    "wof:placetype":"venue"
},
  "geometry": {"coordinates":[8.8373451233,47.2313804626],"type":"Point"}
}