{
  "type": "Feature",
  "properties": {
    "iso:country":"CH",
    "sg:address":"D\u00e4hlenstrasse 4",
    "sg:city":"Grenchen",
    "sg:classifiers":[
        {
            "category":"Education",
            "subcategory":"Library",
            "type":"Public Place"
        }
    ],
    "sg:phone":"+41 32 621 51 66",
    "sg:postcode":"2540",
    "sg:province":"Solothurn",
    "sg:tags":[
        "u",
        "bibliotheken",
        "archive"
    ],
    "wof:name":"Christkath.pfarrbibliothek",
    "wof:placetype":"venue"
},
  "geometry": {"coordinates":[7.388019,47.19141],"type":"Point"}
}