{
  "type": "Feature",
  "properties": {
    "iso:country":"CH",
    "sg:address":"Bernstrasse 83a",
    "sg:city":"Kehrsatz",
    "sg:orig_category":"Bauspenglerei Sanit\u00e4rinstallation U Spenglerei",
    "sg:phone":"+41 31 961 78 56",
    "sg:postcode":"3122",
    "sg:province":"Bern",
    "wof:name":"Probst Metallbau Spenglerei",
    "wof:placetype":"venue"
},
  "geometry": {"coordinates":[7.467539,46.914593],"type":"Point"}
}