{
  "type": "Feature",
  "properties": {
    "iso:country":"CH",
    "sg:address":"9105",
    "sg:city":"Sch\u00f6nengrund",
    "sg:orig_category":"Landw. Genossenschaften Viehzucht",
    "sg:postcode":"9105",
    "sg:province":"Appenzell Ausserrhoden",
    "wof:name":"Braunviehzuchtgenossenschaft Sch\u00f6nengrund & Umgebung",
    "wof:placetype":"venue"
},
  "geometry": {"coordinates":[9.2251300812,47.3255081177],"type":"Point"}
}