{
  "type": "Feature",
  "properties": {
    "iso:country":"CH",
    "sg:address":"Gl\u00e4rnischstrasse 17",
    "sg:city":"Horgen",
    "sg:orig_category":"Zimmerei, Dachdeckerei, Bauspenglerei U Abdichtung",
    "sg:phone":"+41 17671457",
    "sg:postcode":"8810",
    "sg:province":"Z\u00fcrich",
    "wof:name":"Waser Zimmerei, Innenausbau, Renovationen",
    "wof:placetype":"venue"
},
  "geometry": {"coordinates":[8.6034584045,47.2566680908],"type":"Point"}
}