{
  "type": "Feature",
  "properties": {
    "iso:country":"CH",
    "sg:address":"Im Geren 1",
    "sg:city":"Urdorf",
    "sg:orig_category":"Ingenieurb\u00fcros Maschinenbau",
    "sg:phone":"+41 52 383 19 48",
    "sg:postcode":"8902",
    "sg:province":"Z\u00fcrich",
    "wof:name":"J. Anderegg Ag Ingenieurb\u00fcro",
    "wof:placetype":"venue"
},
  "geometry": {"coordinates":[8.8130607605,47.4580345154],"type":"Point"}
}