{
  "type": "Feature",
  "properties": {
    "iso:country":"CH",
    "sg:address":"Luzernstrasse 3",
    "sg:city":"Subingen",
    "sg:orig_category":"Pensionskassen",
    "sg:postcode":"4553",
    "sg:province":"Solothurn",
    "wof:name":"Personalf\u00fcrsorgestiftung Der Firma J. Suter & Cie Ag",
    "wof:placetype":"venue"
},
  "geometry": {"coordinates":[8.8409557343,47.2989654541],"type":"Point"}
}