{
  "type": "Feature",
  "properties": {
    "iso:country":"CH",
    "sg:address":"Kronenstrasse 4",
    "sg:city":"Adliswil",
    "sg:classifiers":[
        {
            "category":"Restaurant",
            "type":"Food & Drink"
        }
    ],
    "sg:phone":"+41 17090545",
    "sg:postcode":"8134",
    "sg:province":"Z\u00fcrich",
    "wof:name":"Ristorante-pizzeria Al Ponte",
    "wof:placetype":"venue"
},
  "geometry": {"coordinates":[8.5269737244,47.3120727539],"type":"Point"}
}