{
  "type": "Feature",
  "properties": {
    "addr:full":"Place Du Midi 48 1950 Sion. Postfach Sion Valais 1951",
    "addr:housenumber":"48",
    "addr:postcode":"1950;postfach;1951",
    "addr:street":"Place Du Midi",
    "iso:country":"CH",
    "sg:address":"Place Du Midi 48 1950 Sion. Postfach",
    "sg:city":"Sion",
    "sg:orig_category":"Architekturb\u00fcros",
    "sg:phone":"+41 27 322 09 82",
    "sg:postcode":"1951",
    "sg:province":"Valais",
    "wof:name":"Bernard Ogier Bureau D'architecture",
    "wof:placetype":"venue"
},
  "geometry": {"coordinates":[7.362253,46.231972],"type":"Point"}
}