{
  "type": "Feature",
  "properties": {
    "iso:country":"CH",
    "sg:address":"Sertelstrasse 8",
    "sg:city":"Reiden",
    "sg:orig_category":"Gartenbau",
    "sg:phone":"+41 62 758 25 59",
    "sg:postcode":"6260",
    "sg:province":"Luzern",
    "wof:name":"Maurer Gartenbau Ag",
    "wof:placetype":"venue"
},
  "geometry": {"coordinates":[7.9769291878,47.2424125671],"type":"Point"}
}