{
  "type": "Feature",
  "properties": {
    "iso:country":"CH",
    "sg:address":"Rathausplatz 10",
    "sg:city":"Arth",
    "sg:orig_category":"Detailhandel mit M\u00f6beln U Haushaltsgegenst\u00e4nden",
    "sg:postcode":"6415",
    "sg:province":"Schwyz",
    "wof:name":"Rulo-teppiche, Loser R.",
    "wof:placetype":"venue"
},
  "geometry": {"coordinates":[8.5233669281,47.0629043579],"type":"Point"}
}