{
  "type": "Feature",
  "properties": {
    "iso:country":"CH",
    "sg:address":"L\u00e4ngweg 9",
    "sg:city":"Feldbrunnen",
    "sg:orig_category":"Werbung",
    "sg:phone":"+41 32 623 67 06",
    "sg:postcode":"4532",
    "sg:province":"Solothurn",
    "wof:name":"Nma New Media Agency B\u00f6ke & Partner",
    "wof:placetype":"venue"
},
  "geometry": {"coordinates":[7.5517301559,47.2201461792],"type":"Point"}
}