{
  "type": "Feature",
  "properties": {
    "iso:country":"CH",
    "sg:address":"Brambergstrasse 18 A",
    "sg:city":"Neuenegg",
    "sg:orig_category":"Elektrizit\u00e4tsversorgung",
    "sg:phone":"+41 33 821 00 44",
    "sg:postcode":"3176",
    "sg:province":"Bern",
    "wof:name":"Visconsil Ag",
    "wof:placetype":"venue"
},
  "geometry": {"coordinates":[7.2797431946,46.9071464539],"type":"Point"}
}