{
  "type": "Feature",
  "properties": {
    "iso:country":"CH",
    "sg:address":"Neugutstrasse 25",
    "sg:city":"Oberengstringen",
    "sg:orig_category":"Zimmerei, Dachdeckerei, Bauspenglerei U Abdichtung",
    "sg:phone":"+41 17718077",
    "sg:postcode":"8102",
    "sg:province":"Z\u00fcrich",
    "wof:name":"Weiss Zimmerei & Blockbau",
    "wof:placetype":"venue"
},
  "geometry": {"coordinates":[8.5321273804,47.2877120972],"type":"Point"}
}