{
  "type": "Feature",
  "properties": {
    "iso:country":"CH",
    "sg:address":"Hohle 6",
    "sg:city":"Subingen",
    "sg:orig_category":"P\u00e9dicure Saunas",
    "sg:phone":"+41 79 211 70 54",
    "sg:postcode":"4553",
    "sg:province":"Solothurn",
    "wof:name":"Esther Horisberger",
    "wof:placetype":"venue"
},
  "geometry": {"coordinates":[7.435505867,46.9275856018],"type":"Point"}
}