{
  "type": "Feature",
  "properties": {
    "iso:country":"CH",
    "sg:address":"Bernstrasse 4",
    "sg:city":"Wynau",
    "sg:orig_category":"Gasth\u00f6fe/Gasth\u00e4user mit Restaurant Kongress- and Tagungshotels mit Restaurant",
    "sg:phone":"+41 62 929 22 32",
    "sg:postcode":"4923",
    "sg:province":"Bern",
    "wof:name":"Landgasthof Zur Traube",
    "wof:placetype":"venue"
},
  "geometry": {"coordinates":[7.8173937798,47.2540206909],"type":"Point"}
}