{
  "type": "Feature",
  "properties": {
    "iso:country":"CH",
    "sg:address":"Heimetweg 9",
    "sg:city":"Emmen",
    "sg:orig_category":"Sanit\u00e4r, Heizungs U L\u00fcftungsinstallation Sanit\u00e4rinstallation",
    "sg:phone":"+41 41 280 16 94",
    "sg:postcode":"6032",
    "sg:province":"Luzern",
    "wof:name":"Studer Alfons, Nachfolger Studer Roland",
    "wof:placetype":"venue"
},
  "geometry": {"coordinates":[8.2840862274,47.0832099915],"type":"Point"}
}