{
  "type": "Feature",
  "properties": {
    "iso:country":"CH",
    "sg:address":"Forchstrasse 95 8032 Z\u00fcrich. Postfach",
    "sg:city":"Z\u00fcrich",
    "sg:orig_category":"Unternehmensberatung",
    "sg:phone":"+41 13878711",
    "sg:postcode":"8032",
    "sg:province":"Z\u00fcrich",
    "wof:name":"Kessler & Co Ag Versicherungsbroker",
    "wof:placetype":"venue"
},
  "geometry": {"coordinates":[8.5602445602,47.3620223999],"type":"Point"}
}