{
  "type": "Feature",
  "properties": {
    "iso:country":"CH",
    "sg:address":"Schwarzenbach",
    "sg:city":"Huttwil",
    "sg:orig_category":"Sonstiger spezialisierter Hoch U Tiefbau",
    "sg:phone":"+41 62 962 19 08",
    "sg:postcode":"4950",
    "sg:province":"Bern",
    "wof:name":"Scheidegger Peter",
    "wof:placetype":"venue"
},
  "geometry": {"coordinates":[7.8184762001,47.1050224304],"type":"Point"}
}