{
  "type": "Feature",
  "properties": {
    "iso:country":"CH",
    "sg:address":"Avenue De Beaumont 4 1700 Fribourg. Postfach",
    "sg:city":"Freiburg",
    "sg:orig_category":"Vermietung U Verpachtung von eigenen Immobilien",
    "sg:postcode":"1700",
    "sg:province":"Fribourg",
    "wof:name":"Beaumont Sa Ii",
    "wof:placetype":"venue"
},
  "geometry": {"coordinates":[7.1447172165,46.7961044312],"type":"Point"}
}