{
  "type": "Feature",
  "properties": {
    "iso:country":"CH",
    "sg:address":"Aathalstrasse 84 8610 Uster. Postfach",
    "sg:city":"Uster",
    "sg:orig_category":"Sonstige mit der Informatik verbundene T\u00e4tigkeiten",
    "sg:postcode":"8610",
    "sg:province":"Z\u00fcrich",
    "wof:name":"Itx Consulting Gmbh Beratungen, Dienstleistungen Im Informatik-bereich. Informatik-material; Handel",
    "wof:placetype":"venue"
},
  "geometry": {"coordinates":[8.7405052185,47.3456192017],"type":"Point"}
}