{
  "type": "Feature",
  "properties": {
    "addr:full":"Worbstrasse 306 G\u00fcmligen Bern 3073",
    "addr:housenumber":"306",
    "addr:postcode":"3073",
    "addr:street":"Worbstrasse",
    "iso:country":"CH",
    "sg:address":"Worbstrasse 306",
    "sg:city":"G\u00fcmligen",
    "sg:orig_category":"Architekturb\u00fcros",
    "sg:phone":"+41 24 499 10 18",
    "sg:postcode":"3073",
    "sg:province":"Bern",
    "wof:name":"Berrut & Hirschi Bureau D'architecture",
    "wof:placetype":"venue"
},
  "geometry": {"coordinates":[6.990439,46.29808],"type":"Point"}
}