{
  "type": "Feature",
  "properties": {
    "iso:country":"CH",
    "sg:address":"Rue Des Pr\u00e9s 126 2500 Biel/bienne. Postfach",
    "sg:city":"Biel/bienne",
    "sg:orig_category":"Detailhandel mit Waren verschiedener Art, Hauptrichtung Nahrungsmittel",
    "sg:postcode":"2503",
    "sg:province":"Bern",
    "wof:name":"Brigante Matteo",
    "wof:placetype":"venue"
},
  "geometry": {"coordinates":[7.2547998428,47.1364860535],"type":"Point"}
}