{
  "type": "Feature",
  "properties": {
    "iso:country":"CH",
    "sg:address":"8841",
    "sg:city":"Gross",
    "sg:orig_category":"Vereine Musik/Blasmusik",
    "sg:postcode":"8841",
    "sg:province":"Schwyz",
    "wof:name":"Feldmusik",
    "wof:placetype":"venue"
},
  "geometry": {"coordinates":[8.7752199173,47.1189918518],"type":"Point"}
}