{
  "type": "Feature",
  "properties": {
    "addr:full":"Ulrichstrasse 20 Z\u00fcrich Z\u00fcrich 8032",
    "addr:housenumber":"20",
    "addr:postcode":"8032",
    "addr:street":"Ulrichstrasse",
    "iso:country":"CH",
    "sg:address":"Ulrichstrasse 20",
    "sg:city":"Z\u00fcrich",
    "sg:orig_category":"Advokaturb\u00fcros",
    "sg:phone":"+41 14222956",
    "sg:postcode":"8032",
    "sg:province":"Z\u00fcrich",
    "wof:name":"Christoph Sautter Advokaturb\u00fcro",
    "wof:placetype":"venue"
},
  "geometry": {"coordinates":[8.563383,47.361843],"type":"Point"}
}