{
  "type": "Feature",
  "properties": {
    "iso:country":"CH",
    "sg:address":"Rathausg\u00e4ssli",
    "sg:city":"Quarten",
    "sg:orig_category":"Interessenvertretungen",
    "sg:postcode":"8883",
    "sg:province":"St. Gallen",
    "wof:name":"Stiftung Pro Quinten",
    "wof:placetype":"venue"
},
  "geometry": {"coordinates":[9.2411851883,47.1078948975],"type":"Point"}
}