{
  "type": "Feature",
  "properties": {
    "addr:full":"Rue Mont Sujet 18 Pr\u00eales Bern 2515",
    "addr:housenumber":"18",
    "addr:postcode":"2515",
    "addr:street":"Rue Mont Sujet",
    "iso:country":"CH",
    "sg:address":"Rue Mont Sujet 18",
    "sg:city":"Pr\u00eales",
    "sg:classifiers":[
        {
            "category":"Professional",
            "subcategory":"Art Services",
            "type":"Services"
        }
    ],
    "sg:phone":"+41 32 315 21 51",
    "sg:postcode":"2515",
    "sg:province":"Bern",
    "sg:tags":[
        "design"
    ],
    "wof:name":"Hot's Design & Communication",
    "wof:placetype":"venue"
},
  "geometry": {"coordinates":[7.127409,47.094463],"type":"Point"}
}