{
  "type": "Feature",
  "properties": {
    "iso:country":"CH",
    "sg:address":"Im Lindenfeld 3",
    "sg:city":"Pfyn",
    "sg:classifiers":[
        {
            "category":"Insurance",
            "subcategory":"Insurance Agent",
            "type":"Services"
        }
    ],
    "sg:phone":"+41 52 765 17 50",
    "sg:postcode":"8505",
    "sg:province":"Thurgau",
    "sg:tags":[
        "versicherungsagenturen",
        "-broker"
    ],
    "wof:name":"Z\u00fcrich-versicherungen Agentur",
    "wof:placetype":"venue"
},
  "geometry": {"coordinates":[8.959277153,47.5960617065],"type":"Point"}
}