{
  "type": "Feature",
  "properties": {
    "iso:country":"CH",
    "sg:address":"Bellacherstr. 3 2545 Selzach. Postfach",
    "sg:city":"Selzach",
    "sg:orig_category":"Grosshandel mit festen Brennstoffen U Mineral\u00f6lerzeugnissen",
    "sg:phone":"+41 32 641 10 83",
    "sg:postcode":"2545",
    "sg:province":"Solothurn",
    "wof:name":"Flury Eduard, Brennstoffe",
    "wof:placetype":"venue"
},
  "geometry": {"coordinates":[7.4582247734,47.2045326233],"type":"Point"}
}