{
  "type": "Feature",
  "properties": {
    "iso:country":"CH",
    "sg:address":"Staldenhof 2",
    "sg:city":"Littau",
    "sg:orig_category":"Detailhandel mit B\u00fcromaschinen U einrichtungen Informatikdienste",
    "sg:phone":"+41 41 250 01 11",
    "sg:postcode":"6014",
    "sg:province":"Luzern",
    "wof:name":"L\u00f6tscher B\u00fcrocenter Ag",
    "wof:placetype":"venue"
},
  "geometry": {"coordinates":[8.269304,47.064903],"type":"Point"}
}