{
  "type": "Feature",
  "properties": {
    "iso:country":"CH",
    "sg:address":"Novalles & Environs",
    "sg:city":"Grandson",
    "sg:orig_category":"Schulpflegen",
    "sg:phone":"+41 24 445 11 51",
    "sg:postcode":"1422",
    "sg:province":"Vaud",
    "wof:name":"Commission Scolaire Des \u00e9coles Primaires De Fontaines-",
    "wof:placetype":"venue"
},
  "geometry": {"coordinates":[6.6459798813,46.8093681335],"type":"Point"}
}