{
  "type": "Feature",
  "properties": {
    "iso:country":"CH",
    "sg:address":"Zentralstrasse 19",
    "sg:city":"Uster",
    "sg:orig_category":"Detailhandel mit Uhren U Schmuck Herstellung von Schmuck, Gold U Silberschmiedwaren",
    "sg:phone":"+41 18250474",
    "sg:postcode":"8610",
    "sg:province":"Z\u00fcrich",
    "wof:name":"Michels Alberto",
    "wof:placetype":"venue"
},
  "geometry": {"coordinates":[8.7177820206,47.3468666077],"type":"Point"}
}