{
  "type": "Feature",
  "properties": {
    "iso:country":"CH",
    "sg:address":"Stampfstrasse 35",
    "sg:city":"Jona",
    "sg:orig_category":"HERSTELLUNG VON GER\u00c4TEN DER ELEKTRIZIT\u00c4TSERZEUGUNG, -VERTEILUNG U.\u00c4 Herstellung von Elektrizit\u00e4tsver",
    "sg:phone":"+41 55 212 55 02",
    "sg:postcode":"8645",
    "sg:province":"St. Gallen",
    "wof:name":"Technoservice Siegrist Harry",
    "wof:placetype":"venue"
},
  "geometry": {"coordinates":[8.8464870453,47.2249488831],"type":"Point"}
}