{
  "type": "Feature",
  "properties": {
    "iso:country":"CH",
    "sg:address":"Blumenweg 10",
    "sg:city":"Ermatingen",
    "sg:orig_category":"Unclassifiable Establishments",
    "sg:phone":"+41 71 664 38 34",
    "sg:postcode":"8272",
    "sg:province":"Thurgau",
    "wof:name":"Untersee Gartenbau Vaterlaus Ag",
    "wof:placetype":"venue"
},
  "geometry": {"coordinates":[9.0823659897,47.668510437],"type":"Point"}
}