{
  "type": "Feature",
  "properties": {
    "iso:country":"CH",
    "sg:address":"Buchserstrasse 14",
    "sg:city":"D\u00e4llikon",
    "sg:orig_category":"Allgemeiner Hoch U Tiefbau Allgemeiner Hochbau",
    "sg:postcode":"8108",
    "sg:province":"Z\u00fcrich",
    "wof:name":"Furtbach Bau Ag D\u00e4llikon",
    "wof:placetype":"venue"
},
  "geometry": {"coordinates":[8.439044,47.44408],"type":"Point"}
}