{
  "type": "Feature",
  "properties": {
    "addr:full":"Erlenstrasse 5 Liestal Basel-Landschaft 4410",
    "addr:housenumber":"5",
    "addr:postcode":"4410",
    "addr:street":"Erlenstrasse",
    "iso:country":"CH",
    "sg:address":"Erlenstrasse 5",
    "sg:city":"Liestal",
    "sg:orig_category":"Buchf\u00fchrung Wirtschaftspr\u00fcfung, Steuerberatung U Treuhand",
    "sg:phone":"+41 32 351 35 33",
    "sg:postcode":"4410",
    "sg:province":"Basel-Landschaft",
    "wof:name":"Buchhaltungsb\u00fcro W\u00e4lti Elisabeth",
    "wof:placetype":"venue"
},
  "geometry": {"coordinates":[7.364701,47.137428],"type":"Point"}
}