{
  "type": "Feature",
  "properties": {
    "iso:country":"CH",
    "sg:address":"M\u00fchlethalstr. 71",
    "sg:city":"Zofingen",
    "sg:classifiers":[
        {
            "category":"Transit Center",
            "subcategory":"Freight",
            "type":"Transportation"
        }
    ],
    "sg:phone":"+41 62 746 07 77",
    "sg:postcode":"4800",
    "sg:province":"Aargau",
    "sg:tags":[
        "metallurgy",
        "pipe",
        "metalworking",
        "sheet"
    ],
    "wof:name":"Abt Blechtechnik Ag",
    "wof:placetype":"venue"
},
  "geometry": {"coordinates":[7.9570379257,47.2973976135],"type":"Point"}
}