{
  "type": "Feature",
  "properties": {
    "iso:country":"CH",
    "sg:address":"I Runch Da Vigana 10",
    "sg:city":"Camorino",
    "sg:orig_category":"Vermietung U Verpachtung von eigenen Immobilien",
    "sg:postcode":"6528",
    "sg:province":"Ticino",
    "wof:name":"Postim Sa",
    "wof:placetype":"venue"
},
  "geometry": {"coordinates":[8.9989442825,46.1558380127],"type":"Point"}
}