{
  "type": "Feature",
  "properties": {
    "iso:country":"CH",
    "sg:address":"Via Quatorta",
    "sg:city":"Lumino",
    "sg:orig_category":"Autospenglereien Handel mit Automobilen",
    "sg:postcode":"6533",
    "sg:province":"Ticino",
    "wof:name":"Carozzeria New Line Sagl",
    "wof:placetype":"venue"
},
  "geometry": {"coordinates":[9.05341,46.225151],"type":"Point"}
}