{
  "type": "Feature",
  "properties": {
    "iso:country":"CH",
    "sg:address":"Jurastrasse 11",
    "sg:city":"Attiswil",
    "sg:orig_category":"Sanit\u00e4r, Heizungs U L\u00fcftungsinstallation Sanit\u00e4rinstallation",
    "sg:phone":"+41 32 637 32 37",
    "sg:postcode":"4536",
    "sg:province":"Bern",
    "wof:name":"Jakob Brudermann Sanit\u00e4r-service",
    "wof:placetype":"venue"
},
  "geometry": {"coordinates":[7.6047759056,47.247253418],"type":"Point"}
}