{
  "type": "Feature",
  "properties": {
    "iso:country":"CH",
    "sg:address":"G\u00e4chlingerstr. 337",
    "sg:city":"Neunkirch",
    "sg:orig_category":"Herstellung von \u00d6fen U Brennern",
    "sg:phone":"+41 52 681 30 34",
    "sg:postcode":"8213",
    "sg:province":"Schaffhausen",
    "wof:name":"Schmid Ofenbau Inhaber Meyer Thomas",
    "wof:placetype":"venue"
},
  "geometry": {"coordinates":[8.5000905991,47.6967163086],"type":"Point"}
}