{
  "type": "Feature",
  "properties": {
    "iso:country":"CH",
    "sg:address":"Fellenbergweg 9",
    "sg:city":"Z\u00fcrich",
    "sg:orig_category":"Unternehmensberatung",
    "sg:phone":"+41 55 462 27 18",
    "sg:postcode":"8047",
    "sg:province":"Z\u00fcrich",
    "wof:name":"Bzw Ag",
    "wof:placetype":"venue"
},
  "geometry": {"coordinates":[8.7937135696,47.2006072998],"type":"Point"}
}