{
  "type": "Feature",
  "properties": {
    "iso:country":"CH",
    "sg:address":"Route Du Jorat 6",
    "sg:city":"Mollie-margot",
    "sg:orig_category":"Gartenbau Landschaftsplanungsb\u00fcros U Gartenarchitekturb\u00fcros",
    "sg:phone":"+41 21 781 10 96",
    "sg:postcode":"1074",
    "wof:name":"Jean-claude Parisod Paysagiste",
    "wof:placetype":"venue"
},
  "geometry": {"coordinates":[6.7504901886,46.5567893982],"type":"Point"}
}