{
  "type": "Feature",
  "properties": {
    "iso:country":"CH",
    "sg:address":"Via Alpsu 51",
    "sg:city":"Sedrun",
    "sg:orig_category":"Mechanik Schmieden",
    "sg:phone":"+41 81 949 13 70",
    "sg:postcode":"7188",
    "sg:province":"Graubunden",
    "wof:name":"Berther E.",
    "wof:placetype":"venue"
},
  "geometry": {"coordinates":[8.7767982483,46.6811752319],"type":"Point"}
}