{
  "type": "Feature",
  "properties": {
    "iso:country":"CH",
    "sg:address":"Buchrainweg 11",
    "sg:city":"Zollikofen",
    "sg:orig_category":"Detailhandel mit Bekleidung Grosshandel mit Textilien",
    "sg:postcode":"3052",
    "sg:province":"Bern",
    "wof:name":"Fritz Fl\u00fcckiger",
    "wof:placetype":"venue"
},
  "geometry": {"coordinates":[7.451515,46.997059],"type":"Point"}
}