{
  "type": "Feature",
  "properties": {
    "iso:country":"CH",
    "sg:address":"Sprungstrasse 1d",
    "sg:city":"Unter\u00e4geri",
    "sg:orig_category":"Druckguss-Werke",
    "sg:phone":"+41 21 906 83 62",
    "sg:postcode":"6314",
    "sg:province":"Zug",
    "wof:name":"Givag, Zweigniederlassung Der Fonderies De Moudon Sa",
    "wof:placetype":"venue"
},
  "geometry": {"coordinates":[9.0384082794,47.408367157],"type":"Point"}
}