{
  "type": "Feature",
  "properties": {
    "iso:country":"CH",
    "sg:address":"B\u00fchlstrasse 2",
    "sg:city":"Weggis",
    "sg:orig_category":"Zimmerei, Dachdeckerei, Bauspenglerei U Abdichtung Zimmerei, Ingenieurholzbau",
    "sg:phone":"+41 79 341 59 10",
    "sg:postcode":"6353",
    "sg:province":"Luzern",
    "wof:name":"K\u00fcttel Erwin Zimmerei Ag",
    "wof:placetype":"venue"
},
  "geometry": {"coordinates":[8.4387598038,47.0324668884],"type":"Point"}
}