{
  "type": "Feature",
  "properties": {
    "iso:country":"CH",
    "sg:address":"H\u00fcttenweg 2",
    "sg:city":"Unterlunkhofen",
    "sg:orig_category":"Sanit\u00e4r, Heizungs U L\u00fcftungsinstallation Sanit\u00e4rinstallation",
    "sg:phone":"+41 56 634 40 30",
    "sg:postcode":"8918",
    "sg:province":"Aargau",
    "wof:name":"Eiga Ag",
    "wof:placetype":"venue"
},
  "geometry": {"coordinates":[8.3807973862,47.3209037781],"type":"Point"}
}