{
  "type": "Feature",
  "properties": {
    "iso:country":"CH",
    "sg:address":"Parkstrasse 37",
    "sg:city":"Weggis",
    "sg:orig_category":"Massagestudios",
    "sg:phone":"+41 79 340 80 60",
    "sg:postcode":"6353",
    "sg:province":"Luzern",
    "wof:name":"Toni K\u00fcnzle Massagen",
    "wof:placetype":"venue"
},
  "geometry": {"coordinates":[8.4263696671,47.0334701538],"type":"Point"}
}