{
  "type": "Feature",
  "properties": {
    "iso:country":"CH",
    "sg:address":"Im Bergd\u00f6rfli 8",
    "sg:city":"Z\u00fcrich",
    "sg:orig_category":"Erschliessung von Grundst\u00fccken",
    "sg:phone":"+41 14817105",
    "sg:postcode":"8038",
    "sg:province":"Z\u00fcrich",
    "wof:name":"Baugenossenschaft Entlisberg",
    "wof:placetype":"venue"
},
  "geometry": {"coordinates":[8.5240697861,47.3383026123],"type":"Point"}
}