{
  "type": "Feature",
  "properties": {
    "iso:country":"CH",
    "sg:address":"Centrale Rue 13 1450 Ste-croix Case Postale 170",
    "sg:city":"Ste-croix",
    "sg:orig_category":"Grosshandel mit Getr\u00e4nken",
    "sg:phone":"+41 24 454 21 64",
    "sg:postcode":"1450",
    "sg:province":"Vaud",
    "wof:name":"Cam\u00fc S\u00e0rl",
    "wof:placetype":"venue"
},
  "geometry": {"coordinates":[6.5010499954,46.8242111206],"type":"Point"}
}