{
  "type": "Feature",
  "properties": {
    "iso:country":"CH",
    "sg:address":"Blumenweg 3 4143 Dornach. Postfach",
    "sg:city":"Dornach",
    "sg:orig_category":"Herstellung von Konstruktionsteilen, Fertigbauteilen U Ausbauelementen aus Holz",
    "sg:phone":"+41 71 971 29 71",
    "sg:postcode":"4143",
    "sg:province":"Solothurn",
    "wof:name":"Tr\u00fcb H. + Co",
    "wof:placetype":"venue"
},
  "geometry": {"coordinates":[8.9700908661,47.4650726318],"type":"Point"}
}