{
  "type": "Feature",
  "properties": {
    "iso:country":"CH",
    "sg:address":"Via Lucino 8 6932 Breganzona. Postfach Caselle Postale 35",
    "sg:city":"Breganzona",
    "sg:orig_category":"Kaminfeger Reinigungsgewerbe",
    "sg:phone":"+41 91 966 24 36",
    "sg:postcode":"6932",
    "sg:province":"Ticino",
    "wof:name":"Giovanni Kauz Sa Impresa Di Spazzacamino",
    "wof:placetype":"venue"
},
  "geometry": {"coordinates":[8.9352378845,46.0095024109],"type":"Point"}
}