{
  "type": "Feature",
  "properties": {
    "iso:country":"CH",
    "sg:address":"Spalentorweg 62",
    "sg:city":"Basel",
    "sg:classifiers":[
        {
            "category":"Wholesale",
            "subcategory":"Drugs",
            "type":"Manufacturing & Wholesale Goods"
        }
    ],
    "sg:phone":"+41 61 272 39 24",
    "sg:postcode":"4003",
    "sg:province":"Basel-Stadt",
    "sg:tags":[
        "chemical",
        "pharmaceutical"
    ],
    "wof:name":"P H Stehelin & Cie Ag",
    "wof:placetype":"venue"
},
  "geometry": {"coordinates":[7.5785,47.554981],"type":"Point"}
}