{
  "type": "Feature",
  "properties": {
    "iso:country":"CH",
    "sg:address":"Obere Hauptgasse 64",
    "sg:city":"Thun",
    "sg:orig_category":"Herstellung von Schneidwaren U Bestecken Schmieden",
    "sg:phone":"+41 33 222 23 03",
    "sg:postcode":"3600",
    "sg:province":"Bern",
    "wof:name":"Schoder M.",
    "wof:placetype":"venue"
},
  "geometry": {"coordinates":[7.6307849884,46.758102417],"type":"Point"}
}