{
  "type": "Feature",
  "properties": {
    "iso:country":"CH",
    "sg:address":"Schaivel 14b",
    "sg:city":"M\u00fcstair",
    "sg:orig_category":"Herstellung von sonstigen Maschinen f\u00fcr unspezifische Verwendung",
    "sg:phone":"+41 81 858 52 62",
    "sg:postcode":"7537",
    "sg:province":"Graubunden",
    "wof:name":"Gasph Gmbh",
    "wof:placetype":"venue"
},
  "geometry": {"coordinates":[10.4544382095,46.6314659119],"type":"Point"}
}