{
  "type": "Feature",
  "properties": {
    "iso:country":"CH",
    "sg:address":"Rue Du Voisinand 16",
    "sg:city":"Ch\u00e2telard-lutry",
    "sg:orig_category":"G\u00fcterbef\u00f6rderung im Strassenverkehr",
    "sg:phone":"+41 21 791 16 38",
    "sg:postcode":"1095",
    "sg:province":"Vaud",
    "wof:name":"Dumas Alois Et Fils, Successeur Dumas Roland",
    "wof:placetype":"venue"
},
  "geometry": {"coordinates":[6.687060833,46.5039710999],"type":"Point"}
}