{
  "type": "Feature",
  "properties": {
    "iso:country":"CH",
    "sg:address":"Sportplatzweg 34",
    "sg:city":"Naters",
    "sg:orig_category":"Reiseb\u00fcros U Reiseveranstalter",
    "sg:phone":"+1 27923123",
    "sg:postcode":"3904",
    "sg:province":"Valais",
    "wof:name":"Skate & Fun, L\u00f6wenthal Schmid Sabine",
    "wof:placetype":"venue"
},
  "geometry": {"coordinates":[8.0005760193,46.3250465393],"type":"Point"}
}