{
  "type": "Feature",
  "properties": {
    "iso:country":"CH",
    "sg:address":"Hauserstrasse 34",
    "sg:city":"Windisch",
    "sg:orig_category":"Detailhandel mit Textilien",
    "sg:phone":"+41 56 441 43 89",
    "sg:postcode":"5210",
    "sg:province":"Aargau",
    "wof:name":"Heidi Br\u00fcgger Boutique Schatzch\u00e4schtli",
    "wof:placetype":"venue"
},
  "geometry": {"coordinates":[8.210439682,47.4710044861],"type":"Point"}
}