{
  "type": "Feature",
  "properties": {
    "addr:full":"Gibelinstrasse 25 4500 Solothurn. Postfach 227 Solothurn Solothurn 4502",
    "addr:housenumber":"25;227",
    "addr:postcode":"4500 solothurn.;4502",
    "addr:street":"Gibelinstrasse;Postfach",
    "iso:country":"CH",
    "sg:address":"Gibelinstrasse 25 4500 Solothurn. Postfach 227",
    "sg:city":"Solothurn",
    "sg:orig_category":"Architektur U Ingenieurb\u00fcros",
    "sg:phone":"+41 32 625 81 81",
    "sg:postcode":"4502",
    "sg:province":"Solothurn",
    "wof:name":"Scherler Ag, Solothurn, Beratende Ingenieure",
    "wof:placetype":"venue"
},
  "geometry": {"coordinates":[7.525746,47.208527],"type":"Point"}
}