{
  "type": "Feature",
  "properties": {
    "iso:country":"CH",
    "sg:address":"3971",
    "sg:city":"Chermignon",
    "sg:orig_category":"Herstellung von Karosserien U Anh\u00e4ngern",
    "sg:phone":"+41 27 483 28 72",
    "sg:postcode":"3971",
    "sg:province":"Valais",
    "wof:name":"Bonvin Adrien",
    "wof:placetype":"venue"
},
  "geometry": {"coordinates":[7.4784898758,46.2839508057],"type":"Point"}
}