{
  "type": "Feature",
  "properties": {
    "addr:full":"Rain 44 Aarau Aargau 5000",
    "addr:housenumber":"44",
    "addr:postcode":"5000",
    "addr:street":"Rain",
    "iso:country":"CH",
    "sg:address":"Rain 44",
    "sg:city":"Aarau",
    "sg:classifiers":[
        {
            "category":"Shopping Center",
            "type":"Public Place"
        }
    ],
    "sg:phone":"+41 62 824 43 43",
    "sg:postcode":"5000",
    "sg:province":"Aargau",
    "sg:tags":[
        "aluminium",
        "casting"
    ],
    "wof:name":"H. R\u00fcetschi Ag Glocken- Und Kunstgiesserei",
    "wof:placetype":"venue"
},
  "geometry": {"coordinates":[8.043321,47.389919],"type":"Point"}
}