{
  "type": "Feature",
  "properties": {
    "iso:country":"CH",
    "sg:address":"Baarerstrasse 95 6300 Zug. Postfach 1260",
    "sg:city":"Zug",
    "sg:orig_category":"Wirtschaftspr\u00fcfung, Steuerberatung U Treuhand",
    "sg:phone":"+41 41 769 78 00",
    "sg:postcode":"6301",
    "sg:province":"Zug",
    "wof:name":"Von Fl\u00fce Treuhand Ag",
    "wof:placetype":"venue"
},
  "geometry": {"coordinates":[8.5241804123,47.1733093262],"type":"Point"}
}