{
  "type": "Feature",
  "properties": {
    "iso:country":"CH",
    "sg:address":"Am Schilfgraben 1 9423 Altenrhein. Postfach",
    "sg:city":"Altenrhein",
    "sg:orig_category":"Grosshandel mit Textilien",
    "sg:postcode":"9423",
    "sg:province":"St. Gallen",
    "wof:name":"Atelier Z\u00fcnd",
    "wof:placetype":"venue"
},
  "geometry": {"coordinates":[9.5517377853,47.4903907776],"type":"Point"}
}