{
  "type": "Feature",
  "properties": {
    "iso:country":"CH",
    "sg:address":"Gr\u00fczenstrasse 15",
    "sg:city":"D\u00fcbendorf",
    "sg:orig_category":"Bau U Wohngenossenschaften",
    "sg:postcode":"8600",
    "sg:province":"Z\u00fcrich",
    "wof:name":"Siedlungs-& Baugen.d\u00fcbendorf",
    "wof:placetype":"venue"
},
  "geometry": {"coordinates":[8.620673,47.393791],"type":"Point"}
}