{
  "type": "Feature",
  "properties": {
    "iso:country":"CH",
    "sg:address":"Hauptstrasse 16",
    "sg:city":"L\u00e4ufelfingen",
    "sg:orig_category":"Detailhandel mit Fleisch U Fleischwaren",
    "sg:phone":"+41 91 864 13 57",
    "sg:postcode":"4448",
    "sg:province":"Basel-Landschaft",
    "wof:name":"Mauri Piergiorgio",
    "wof:placetype":"venue"
},
  "geometry": {"coordinates":[8.9068098068,46.3802680969],"type":"Point"}
}