{
  "type": "Feature",
  "properties": {
    "iso:country":"CH",
    "sg:address":"Hupperg\u00e4ssli 6",
    "sg:city":"Lengnau",
    "sg:classifiers":[
        {
            "category":"Banks & Credit Unions",
            "subcategory":"Bank",
            "type":"Services"
        }
    ],
    "sg:phone":"+41 4165524149",
    "sg:postcode":"2543",
    "sg:province":"Bern",
    "wof:name":"Schweiz. Mobiliar",
    "wof:placetype":"venue"
},
  "geometry": {"coordinates":[7.3694162369,47.1859741211],"type":"Point"}
}