{
  "type": "Feature",
  "properties": {
    "iso:country":"CH",
    "sg:address":"Statthalterstrasse 101",
    "sg:city":"Bern",
    "sg:orig_category":"Autotransporte international Sonstige Verkehrsvermittlung",
    "sg:postcode":"3018",
    "sg:province":"Bern",
    "wof:name":"Kipfer Internationale Transport Ag",
    "wof:placetype":"venue"
},
  "geometry": {"coordinates":[7.392647,46.937164],"type":"Point"}
}