{
  "type": "Feature",
  "properties": {
    "iso:country":"CH",
    "sg:address":"Chlenglerweg 79",
    "sg:city":"Thayngen",
    "sg:orig_category":"Herstellung von k\u00e4lte U lufttechnischen Erzeugnissen f\u00fcr gewerbliche Zwecke Ingenieurb\u00fcros Umwelttec",
    "sg:phone":"+41 32 467 13 25",
    "sg:postcode":"8240",
    "sg:province":"Schaffhausen",
    "wof:name":"Air M'etudes S\u00e0rl",
    "wof:placetype":"venue"
},
  "geometry": {"coordinates":[7.0729169846,47.418838501],"type":"Point"}
}