{
  "type": "Feature",
  "properties": {
    "iso:country":"CH",
    "sg:address":"Grand-rue 29 2034 Peseux. Postfach",
    "sg:city":"Peseux",
    "sg:classifiers":[
        {
            "category":"Restaurant",
            "type":"Food & Drink"
        }
    ],
    "sg:phone":"+41 32 731 11 44",
    "sg:postcode":"2034",
    "sg:province":"Neuch\u00e2tel",
    "sg:tags":[
        "tea-rooms",
        "restaurants"
    ],
    "wof:name":"Simonet Caf\u00e9 Restaurant Chez Nina",
    "wof:placetype":"venue"
},
  "geometry": {"coordinates":[6.8895921707,46.9876861572],"type":"Point"}
}