{
  "type": "Feature",
  "properties": {
    "iso:country":"CH",
    "sg:address":"Via San Salvatore 13",
    "sg:city":"Paradiso",
    "sg:orig_category":"Datenverarbeitungsdienste Softwareentwicklung U beratung",
    "sg:phone":"+41 17518939",
    "sg:postcode":"6900",
    "sg:province":"Ticino",
    "wof:name":"Chip-in Ag",
    "wof:placetype":"venue"
},
  "geometry": {"coordinates":[8.437495,47.419029],"type":"Point"}
}