{
  "type": "Feature",
  "properties": {
    "iso:country":"CH",
    "sg:address":"Schaffhauserstrasse 26",
    "sg:city":"Thayngen",
    "sg:orig_category":"Elektroinstallation",
    "sg:phone":"+41 52 649 46 40",
    "sg:postcode":"8240",
    "sg:province":"Schaffhausen",
    "wof:name":"Elektro Rinaldi",
    "wof:placetype":"venue"
},
  "geometry": {"coordinates":[8.6996488571,47.7476844788],"type":"Point"}
}