{
  "type": "Feature",
  "properties": {
    "iso:country":"CH",
    "sg:address":"Kantonsstrasse 18",
    "sg:city":"Freienbach",
    "sg:orig_category":"RESTAURANTS: TEA-ROOMS",
    "sg:phone":"+41 31 859 01 83",
    "sg:postcode":"8807",
    "sg:province":"Schwyz",
    "wof:name":"Seiler-bachmann Hans-peter",
    "wof:placetype":"venue"
},
  "geometry": {"coordinates":[7.5276780128,47.0192718506],"type":"Point"}
}