{
  "type": "Feature",
  "properties": {
    "iso:country":"CH",
    "sg:address":"M\u00fchlemattstrasse 61",
    "sg:city":"Bern",
    "sg:orig_category":"Arztpraxen",
    "sg:phone":"+41 31 372 43 43",
    "sg:postcode":"3007",
    "sg:province":"Bern",
    "wof:name":"Dr.med. Hans Albrecht Arzt F.allgemeine Medizin Fmh",
    "wof:placetype":"venue"
},
  "geometry": {"coordinates":[7.431791,46.941376],"type":"Point"}
}