{
  "type": "Feature",
  "properties": {
    "iso:country":"CH",
    "sg:address":"Via Angelo Maspoli 2",
    "sg:city":"Mendrisio",
    "sg:classifiers":[
        {
            "category":"Education",
            "subcategory":"Kindergarten",
            "type":"Public Place"
        }
    ],
    "sg:phone":"+41 21 841 15 51",
    "sg:postcode":"6850",
    "sg:province":"Ticino",
    "sg:tags":[
        "movement",
        "clock"
    ],
    "wof:name":"Dubois & D\u00e9praz S.a.",
    "wof:placetype":"venue"
},
  "geometry": {"coordinates":[6.28143,46.647022],"type":"Point"}
}