{
  "type": "Feature",
  "properties": {
    "iso:country":"CH",
    "sg:address":"Rebhaldenstrasse 15",
    "sg:city":"Freienbach",
    "sg:orig_category":"Bezirks, Sekundar, Realschulen, Oberstufe der Primarschulen",
    "sg:phone":"+41 55 410 24 28",
    "sg:postcode":"8807",
    "sg:province":"Schwyz",
    "wof:name":"Sekundarschule",
    "wof:placetype":"venue"
},
  "geometry": {"coordinates":[8.75424,47.203739],"type":"Point"}
}