{
  "type": "Feature",
  "properties": {
    "iso:country":"CH",
    "sg:address":"Hauptstrasse 35 4434 H\u00f6lstein. Postfach 209",
    "sg:city":"H\u00f6lstein",
    "sg:orig_category":"Autogaragen",
    "sg:phone":"+41 61 951 10 73",
    "sg:postcode":"4434",
    "sg:province":"Basel-Landschaft",
    "wof:name":"A. & F. Schweizer Touring-garage",
    "wof:placetype":"venue"
},
  "geometry": {"coordinates":[7.77051,47.42635],"type":"Point"}
}