{
  "type": "Feature",
  "properties": {
    "addr:full":"M\u00fcnchensteinerstrasse 41 Basel Basel-Stadt 4052",
    "addr:housenumber":"41",
    "addr:postcode":"4052",
    "addr:street":"Muenchensteinerstrasse",
    "iso:country":"CH",
    "sg:address":"M\u00fcnchensteinerstrasse 41",
    "sg:city":"Basel",
    "sg:classifiers":[
        {
            "category":"Shopping",
            "subcategory":"Clothing, Apparel, & Fashions",
            "type":"Retail Goods"
        }
    ],
    "sg:phone":"+41 61 377 74 74",
    "sg:postcode":"4052",
    "sg:province":"Basel-Stadt",
    "sg:tags":[
        "children's",
        "clothing"
    ],
    "wof:name":"Corporate Fashion International Ltd",
    "wof:placetype":"venue"
},
  "geometry": {"coordinates":[7.598782,47.546097],"type":"Point"}
}