{
  "type": "Feature",
  "properties": {
    "iso:country":"CH",
    "sg:address":"Xxxi-d\u00e9cembre Rue Du 48",
    "sg:city":"Gen\u00e8ve",
    "sg:orig_category":"Unclassifiable Establishments",
    "sg:postcode":"1207",
    "sg:province":"Gen\u00e8ve",
    "wof:name":"Hardsteelconsulting Ltd Beteiligungen, Bes. Der Stahlbranche Usw",
    "wof:placetype":"venue"
},
  "geometry": {"coordinates":[9.374461174,47.4244728088],"type":"Point"}
}