{
  "type": "Feature",
  "properties": {
    "iso:country":"CH",
    "sg:address":"Lautengartenstrasse 23 4000 Basel. Postfach",
    "sg:city":"Basel",
    "sg:orig_category":"Non-Classified Establishments",
    "sg:postcode":"4051",
    "sg:province":"Basel-Stadt",
    "wof:name":"Extratel Teamconsult Gmbh",
    "wof:placetype":"venue"
},
  "geometry": {"coordinates":[-105.89307403559999,39.3157958984],"type":"Point"}
}