{
  "type": "Feature",
  "properties": {
    "iso:country":"CH",
    "sg:address":"Bernstrasse 30",
    "sg:city":"M\u00fcnsingen",
    "sg:orig_category":"Handel mit Motorr\u00e4dern, Teilen U Zubeh\u00f6r Instandhaltung U Reparatur von Motorr\u00e4dern",
    "sg:phone":"+41 31 721 41 91",
    "sg:postcode":"3110",
    "sg:province":"Bern",
    "wof:name":"Am-shop Alois Monn Motorradbekleidung & Zubeh\u00f6r",
    "wof:placetype":"venue"
},
  "geometry": {"coordinates":[7.5603079796,46.8797950745],"type":"Point"}
}