{
  "type": "Feature",
  "properties": {
    "iso:country":"CH",
    "sg:address":"Route Des Ecoles 32",
    "sg:city":"Marly",
    "sg:orig_category":"Primarschulen",
    "sg:phone":"+41 26 436 34 31",
    "sg:postcode":"1723",
    "sg:province":"Fribourg",
    "wof:name":"Ecole Primaire Marly-grand-pr\u00e9",
    "wof:placetype":"venue"
},
  "geometry": {"coordinates":[7.1465039253,46.7829055786],"type":"Point"}
}