{
  "type": "Feature",
  "properties": {
    "iso:country":"CH",
    "sg:address":"Sternmattstrasse 10a",
    "sg:city":"Emmen",
    "sg:classifiers":[
        {
            "category":"Government",
            "subcategory":"Department Of Motor Vehicles",
            "type":"Public Place"
        }
    ],
    "sg:phone":"+41 41 260 13 13",
    "sg:postcode":"6032",
    "sg:province":"Luzern",
    "sg:tags":[
        "car",
        "rental",
        "brokerage"
    ],
    "wof:name":"Sonderegger Solutions Gmbh",
    "wof:placetype":"venue"
},
  "geometry": {"coordinates":[8.303399,47.077305],"type":"Point"}
}