{
  "type": "Feature",
  "properties": {
    "iso:country":"CH",
    "sg:address":"Dorfstrasse 30",
    "sg:city":"Einigen",
    "sg:orig_category":"Unclassifiable Establishments",
    "sg:postcode":"3646",
    "sg:province":"Bern",
    "wof:name":"Donath Thoma Communication & Consulting",
    "wof:placetype":"venue"
},
  "geometry": {"coordinates":[7.6471500397,46.7090454102],"type":"Point"}
}