{
  "type": "Feature",
  "properties": {
    "iso:country":"CH",
    "sg:address":"Route D'ambilly 38",
    "sg:city":"Th\u00f4nex",
    "sg:orig_category":"Tankstellen",
    "sg:phone":"+41 22 348 51 06",
    "sg:postcode":"1226",
    "sg:province":"Gen\u00e8ve",
    "wof:name":"Gis\u00e8le Ferrante",
    "wof:placetype":"venue"
},
  "geometry": {"coordinates":[6.2055101395,46.1978683472],"type":"Point"}
}