{
  "type": "Feature",
  "properties": {
    "iso:country":"CH",
    "sg:address":"Bahnhofstrasse 34 8702 Zollikon. Postfach 45",
    "sg:city":"Zollikon",
    "sg:orig_category":"Maschinen-Fabrikation",
    "sg:phone":"+41 13918816",
    "sg:postcode":"8702",
    "sg:province":"Z\u00fcrich",
    "wof:name":"Coatec Holding Ag",
    "wof:placetype":"venue"
},
  "geometry": {"coordinates":[8.5710964203,47.3380508423],"type":"Point"}
}