{
  "type": "Feature",
  "properties": {
    "iso:country":"CH",
    "sg:address":"Belpbergstrasse 5",
    "sg:city":"Toffen",
    "sg:orig_category":"Instandhaltung U Reparatur von Automobilen",
    "sg:phone":"+41 41 497 23 67",
    "sg:postcode":"3125",
    "sg:province":"Bern",
    "wof:name":"Marbacher Hans",
    "wof:placetype":"venue"
},
  "geometry": {"coordinates":[8.1349363327,47.0414581299],"type":"Point"}
}