{
  "type": "Feature",
  "properties": {
    "iso:country":"CH",
    "sg:address":"Kirchdorfstrasse 28",
    "sg:city":"Jaberg",
    "sg:orig_category":"Einrahmungen",
    "sg:phone":"+41 31 781 08 22",
    "sg:postcode":"3629",
    "sg:province":"Bern",
    "wof:name":"Hans Wiedmann Einrahmungen",
    "wof:placetype":"venue"
},
  "geometry": {"coordinates":[7.5684652328,46.8179321289],"type":"Point"}
}