{
  "type": "Feature",
  "properties": {
    "iso:country":"CH",
    "sg:address":"Rive Rue De 52",
    "sg:city":"Nyon",
    "sg:orig_category":"Fachdetailhandel in Verkaufsr\u00e4umen",
    "sg:postcode":"1260",
    "sg:province":"Vaud",
    "wof:name":"Maguette Sculpture S\u00e0rl",
    "wof:placetype":"venue"
},
  "geometry": {"coordinates":[6.2390799522,46.3823661804],"type":"Point"}
}