{
  "type": "Feature",
  "properties": {
    "iso:country":"CH",
    "sg:address":"Via Venoi 6",
    "sg:city":"Canobbio",
    "sg:orig_category":"Druckweiterverarbeitung",
    "sg:postcode":"6952",
    "sg:province":"Ticino",
    "wof:name":"Printest Sagl",
    "wof:placetype":"venue"
},
  "geometry": {"coordinates":[8.964222908,46.0354309082],"type":"Point"}
}