{
  "type": "Feature",
  "properties": {
    "iso:country":"CH",
    "sg:address":"Winkelb\u00fcelhof 4",
    "sg:city":"Adligenswil",
    "sg:orig_category":"Vorschulen, Kinderg\u00e4rten",
    "sg:postcode":"6043",
    "sg:province":"Luzern",
    "wof:name":"Kindergarten Montessori",
    "wof:placetype":"venue"
},
  "geometry": {"coordinates":[8.3773736954,47.0716247559],"type":"Point"}
}