{
  "type": "Feature",
  "properties": {
    "iso:country":"CH",
    "sg:address":"Rue Albert-rieter 6",
    "sg:city":"Bulle",
    "sg:orig_category":"Institutionen f\u00fcr Behinderte Sonderschulen",
    "sg:phone":"+41 26 652 30 60",
    "sg:postcode":"1630",
    "sg:province":"Fribourg",
    "wof:name":"Ecole Services Auxiliaires Scolaires",
    "wof:placetype":"venue"
},
  "geometry": {"coordinates":[6.9188599586,46.6953582764],"type":"Point"}
}