{
  "type": "Feature",
  "properties": {
    "iso:country":"CH",
    "sg:address":"Speerweg 12",
    "sg:city":"B\u00fctschwil",
    "sg:orig_category":"Sportvereine Ballsport Tennis",
    "sg:phone":"+41 71 983 13 23",
    "sg:postcode":"9606",
    "sg:province":"St. Gallen",
    "wof:name":"Tc B\u00fctschwil",
    "wof:placetype":"venue"
},
  "geometry": {"coordinates":[9.0697107315,47.3567314148],"type":"Point"}
}