{
  "type": "Feature",
  "properties": {
    "iso:country":"CH",
    "sg:address":"Grand'rue 10 1162 St-prex. Postfach",
    "sg:city":"St-prex",
    "sg:orig_category":"RESTAURANTS: TEA-ROOMS",
    "sg:postcode":"1162",
    "sg:province":"Vaud",
    "wof:name":"Ioconte Ag Gastgewerbebetriebe-f\u00fchrung",
    "wof:placetype":"venue"
},
  "geometry": {"coordinates":[7.6206588745,46.7194862366],"type":"Point"}
}