{
  "type": "Feature",
  "properties": {
    "iso:country":"CH",
    "sg:address":"Landstrasse 54 8868 Oberurnen. Postfach",
    "sg:city":"Oberurnen",
    "sg:orig_category":"Herstellung von Elektromotoren, Generatoren U Transformatoren",
    "sg:phone":"+41 55 610 11 06",
    "sg:postcode":"8868",
    "sg:province":"Glarus",
    "wof:name":"Witzig Antriebe Ag Elektromotoren, Maschinen, Werkzeuge; Konstruktion, Herstellung Usw",
    "wof:placetype":"venue"
},
  "geometry": {"coordinates":[9.0613613129,47.1114997864],"type":"Point"}
}