{
  "type": "Feature",
  "properties": {
    "iso:country":"CH",
    "sg:address":"Muristrasse 21a",
    "sg:city":"Bern",
    "sg:orig_category":"Eisbahnen and Eissportpl\u00e4tze",
    "sg:phone":"+41 31 352 88 00",
    "sg:postcode":"3006",
    "sg:province":"Bern",
    "wof:name":"Eisbahn Egelm\u00f6sli Schosshalden Ostring-murifeld-leist",
    "wof:placetype":"venue"
},
  "geometry": {"coordinates":[7.4635038376,46.9436836243],"type":"Point"}
}