{
  "type": "Feature",
  "properties": {
    "iso:country":"CH",
    "sg:address":"H\u00f6henstr. 4",
    "sg:city":"Ramlinsburg",
    "sg:orig_category":"Institutionen des Sozialwesens ohne Beherbergung",
    "sg:postcode":"4433",
    "sg:province":"Basel-Landschaft",
    "wof:name":"Stiftung Wendepunkt",
    "wof:placetype":"venue"
},
  "geometry": {"coordinates":[7.7666230202,47.4490585327],"type":"Point"}
}