{
  "type": "Feature",
  "properties": {
    "iso:country":"CH",
    "sg:address":"Bahnhofstrasse 50",
    "sg:city":"Aarburg",
    "sg:orig_category":"RESTAURANTS: TEA-ROOMS",
    "sg:postcode":"4663",
    "sg:province":"Aargau",
    "wof:name":"Moonwalker Entertainment Gmbh",
    "wof:placetype":"venue"
},
  "geometry": {"coordinates":[7.9069862366,47.3202934265],"type":"Point"}
}