{
  "type": "Feature",
  "properties": {
    "iso:country":"CH",
    "sg:address":"Marktstrasse 1",
    "sg:city":"Heerbrugg",
    "sg:orig_category":"Versicherungen Hauptagenturen",
    "sg:phone":"+41 52 741 12 42",
    "sg:postcode":"9435",
    "sg:province":"St. Gallen",
    "wof:name":"Winterthur-versicherungen Hauptagentur",
    "wof:placetype":"venue"
},
  "geometry": {"coordinates":[8.8604602814,47.6593589783],"type":"Point"}
}