{
  "type": "Feature",
  "properties": {
    "iso:country":"CH",
    "sg:address":"Vicolo Centrale 1 6900 Massagno. Postfach 192",
    "sg:city":"Massagno",
    "sg:orig_category":"Vermietung U Verpachtung von eigenen Immobilien Vermittlung von Immobilien",
    "sg:phone":"+41 91 967 28 27",
    "sg:postcode":"6900",
    "sg:province":"Ticino",
    "wof:name":"Vesa Sa",
    "wof:placetype":"venue"
},
  "geometry": {"coordinates":[8.9458608627,46.0105628967],"type":"Point"}
}