{
  "type": "Feature",
  "properties": {
    "iso:country":"CH",
    "sg:address":"Grabenstrasse 4",
    "sg:city":"Zollikofen",
    "sg:orig_category":"RESTAURANTS: TEA-ROOMS",
    "sg:postcode":"3052",
    "sg:province":"Bern",
    "wof:name":"Rentsch Gastro Ag",
    "wof:placetype":"venue"
},
  "geometry": {"coordinates":[7.4398460388,46.9980964661],"type":"Point"}
}