{
  "type": "Feature",
  "properties": {
    "addr:full":"Hagentalerstrasse 57 Basel Basel-Stadt 4055",
    "addr:housenumber":"57",
    "addr:postcode":"4055",
    "addr:street":"Hagentalerstrasse",
    "iso:country":"CH",
    "sg:address":"Hagentalerstrasse 57",
    "sg:city":"Basel",
    "sg:orig_category":"Bauingenieurb\u00fcros allgemein",
    "sg:phone":"+41 31 952 76 76",
    "sg:postcode":"4055",
    "sg:province":"Basel-Stadt",
    "wof:name":"Bau & Plan Ingenieurb\u00fcro",
    "wof:placetype":"venue"
},
  "geometry": {"coordinates":[7.486851,46.93074],"type":"Point"}
}