{
  "type": "Feature",
  "properties": {
    "iso:country":"CH",
    "sg:address":"Tuechstrasse 26",
    "sg:city":"Flaach",
    "sg:orig_category":"Reiseb\u00fcros U Reiseveranstalter Sanit\u00e4r U Heizungsinstallation",
    "sg:phone":"+41 52 318 22 42",
    "sg:postcode":"8416",
    "sg:province":"Z\u00fcrich",
    "wof:name":"N. Kohl W\u00e4rmetechnik",
    "wof:placetype":"venue"
},
  "geometry": {"coordinates":[8.5978937149,47.5725212097],"type":"Point"}
}