{
  "type": "Feature",
  "properties": {
    "iso:country":"CH",
    "sg:address":"Rorschacher Strasse 59",
    "sg:city":"St.gallen",
    "sg:orig_category":"W\u00e4schereien",
    "sg:phone":"+41 71 951 91 33",
    "sg:postcode":"9000",
    "sg:province":"St. Gallen",
    "wof:name":"Quick-wash Beat & Verena B\u00f6ni",
    "wof:placetype":"venue"
},
  "geometry": {"coordinates":[9.3835287094,47.4273605347],"type":"Point"}
}