{
  "type": "Feature",
  "properties": {
    "iso:country":"CH",
    "sg:address":"Saint-joseph Rue 37 1630 Bulle. Postfach",
    "sg:city":"Bulle",
    "sg:orig_category":"Sonstiger spezialisierter Hoch U Tiefbau",
    "sg:postcode":"1630",
    "sg:province":"Fribourg",
    "wof:name":"Moret M. & Fils",
    "wof:placetype":"venue"
},
  "geometry": {"coordinates":[6.4834461212,46.9046783447],"type":"Point"}
}