{
  "type": "Feature",
  "properties": {
    "iso:country":"CH",
    "sg:address":"Wegenstetterstrasse 260 4325 Schupfart. Postfach",
    "sg:city":"Schupfart",
    "sg:orig_category":"Herstellung von keramischen Wand U Bodenfliesen U platten",
    "sg:postcode":"4325",
    "sg:province":"Aargau",
    "wof:name":"Keramische Wand Und Bodenbel\u00e4ge M\u00fcller",
    "wof:placetype":"venue"
},
  "geometry": {"coordinates":[7.9635949135,47.5113220215],"type":"Point"}
}