{
  "type": "Feature",
  "properties": {
    "iso:country":"CH",
    "sg:city":"R\u00fcmikon",
    "sg:classifiers":[
        {
            "category":"Banks & Credit Unions",
            "subcategory":"Bank",
            "type":"Services"
        }
    ],
    "sg:phone":"+41 4156531286",
    "sg:postcode":"8439",
    "wof:name":"Raiffeisenkasse",
    "wof:placetype":"venue"
},
  "geometry": {"coordinates":[6.33707,52.903881],"type":"Point"}
}