{
  "type": "Feature",
  "properties": {
    "iso:country":"CH",
    "sg:address":"Hegenheimerstrasse 128",
    "sg:city":"Basel",
    "sg:orig_category":"Detailhandel mit Waren verschiedener Art, Hauptrichtung Nahrungsmittel Herstellung von sonstigen Nah",
    "sg:phone":"+41 61 381 49 17",
    "sg:postcode":"4055",
    "sg:province":"Basel-Stadt",
    "wof:name":"Paste Ines, Pfefferli Albert",
    "wof:placetype":"venue"
},
  "geometry": {"coordinates":[7.5666799545,47.5628738403],"type":"Point"}
}