{
  "type": "Feature",
  "properties": {
    "iso:country":"CH",
    "sg:address":"Alte Bernstrasse 146a 3613 Steffisburg. Postfach 56",
    "sg:city":"Steffisburg",
    "sg:orig_category":"Herstellung von Werkzeugen Herstellung von Werkzeugmaschinen f\u00fcr die Metallbearbeitung",
    "sg:phone":"+41 33 439 05 05",
    "sg:postcode":"3613",
    "sg:province":"Bern",
    "wof:name":"Maschinenfabrik Meyer & Burger Ag",
    "wof:placetype":"venue"
},
  "geometry": {"coordinates":[7.617576,46.775444],"type":"Point"}
}