{
  "type": "Feature",
  "properties": {
    "iso:country":"CH",
    "sg:address":"Heiterstalden",
    "sg:city":"Menzingen",
    "sg:orig_category":"Herstellung von Baubedarfsartikeln aus Kunststoff",
    "sg:phone":"+41 41 755 26 09",
    "sg:postcode":"6313",
    "sg:province":"Zug",
    "wof:name":"Traunsteiner Flachsilos, Ab\u00e4cherli Franz",
    "wof:placetype":"venue"
},
  "geometry": {"coordinates":[8.569817543,47.1608657837],"type":"Point"}
}