{
  "type": "Feature",
  "properties": {
    "iso:country":"CH",
    "sg:address":"Dorf 14b",
    "sg:city":"R\u00fceggisberg",
    "sg:orig_category":"Elektroinstallation",
    "sg:phone":"+41 31 809 30 80",
    "sg:postcode":"3088",
    "sg:province":"Bern",
    "wof:name":"Staub & Zbinden Elektro Gmbh",
    "wof:placetype":"venue"
},
  "geometry": {"coordinates":[7.4401707649,46.8224143982],"type":"Point"}
}