{
  "type": "Feature",
  "properties": {
    "addr:full":"M\u00fcnchhaldenstrasse 15 Z\u00fcrich Z\u00fcrich 8008",
    "addr:housenumber":"15",
    "addr:postcode":"8008",
    "addr:street":"Muenchhaldenstrasse",
    "iso:country":"CH",
    "sg:address":"M\u00fcnchhaldenstrasse 15",
    "sg:city":"Z\u00fcrich",
    "sg:orig_category":"Architektur U Ingenieurb\u00fcros",
    "sg:phone":"+41 12015279",
    "sg:postcode":"8008",
    "sg:province":"Z\u00fcrich",
    "wof:name":"Monica R\u00fcdlinger Grafik",
    "wof:placetype":"venue"
},
  "geometry": {"coordinates":[8.557562,47.35429],"type":"Point"}
}