{
  "type": "Feature",
  "properties": {
    "iso:country":"CH",
    "sg:address":"Taiada Via 22",
    "sg:city":"Arbedo",
    "sg:orig_category":"G\u00fcterbef\u00f6rderung im Strassenverkehr",
    "sg:postcode":"6517",
    "sg:province":"Ticino",
    "wof:name":"S.d.r. Di Rocca P. Servizio Distribuzioni Rapide",
    "wof:placetype":"venue"
},
  "geometry": {"coordinates":[9.04342556,46.2145881653],"type":"Point"}
}