{
  "type": "Feature",
  "properties": {
    "iso:country":"CH",
    "sg:address":"Inkwilerstrasse 1",
    "sg:city":"Subingen",
    "sg:orig_category":"Mechanik Schlossereien",
    "sg:phone":"+41 32 614 11 44",
    "sg:postcode":"4553",
    "sg:province":"Solothurn",
    "wof:name":"Sch\u00e4r Hansruedi Schmiede",
    "wof:placetype":"venue"
},
  "geometry": {"coordinates":[7.6187319756,47.1989707947],"type":"Point"}
}