{
  "type": "Feature",
  "properties": {
    "addr:full":"Scharnagelnstrasse 8 Niederbipp Bern 4704",
    "addr:housenumber":"8",
    "addr:postcode":"4704",
    "addr:street":"Scharnagelnstrasse",
    "iso:country":"CH",
    "sg:address":"Scharnagelnstrasse 8",
    "sg:city":"Niederbipp",
    "sg:orig_category":"Allgemeiner Hoch U Tiefbau Allgemeiner Hochbau",
    "sg:phone":"+41 32 633 11 15",
    "sg:postcode":"4704",
    "sg:province":"Bern",
    "wof:name":"Gebr. Born Ag",
    "wof:placetype":"venue"
},
  "geometry": {"coordinates":[7.699674,47.264053],"type":"Point"}
}