{
  "type": "Feature",
  "properties": {
    "iso:country":"CH",
    "sg:address":"Talstrasse 28",
    "sg:city":"Langenthal",
    "sg:orig_category":"Informatikschulen",
    "sg:phone":"+41 62 919 82 70",
    "sg:postcode":"4900",
    "sg:province":"Bern",
    "wof:name":"Kaufm.berufsschule Langenthal",
    "wof:placetype":"venue"
},
  "geometry": {"coordinates":[7.7856359482,47.210647583],"type":"Point"}
}