{
  "type": "Feature",
  "properties": {
    "addr:full":"Br\u00fcckenstrasse 8a Huttwil Bern 4950",
    "addr:housenumber":"8a",
    "addr:postcode":"4950",
    "addr:street":"Brueckenstrasse",
    "iso:country":"CH",
    "sg:address":"Br\u00fcckenstrasse 8a",
    "sg:city":"Huttwil",
    "sg:orig_category":"Bauspenglerei Sanit\u00e4r, Heizungs U L\u00fcftungsinstallation",
    "sg:phone":"+41 62 959 80 20",
    "sg:postcode":"4950",
    "sg:province":"Bern",
    "wof:name":"Leuenberger Peter",
    "wof:placetype":"venue"
},
  "geometry": {"coordinates":[7.864002,47.115753],"type":"Point"}
}