{
  "type": "Feature",
  "properties": {
    "addr:full":"Riedtenacker 2 3474 R\u00fcedisbach. Postfach 5 Wynigen Bern 3472",
    "addr:housenumber":"2;5",
    "addr:postcode":"3474;3472",
    "addr:street":"Riedtenacker;Postfach",
    "iso:country":"CH",
    "sg:address":"Riedtenacker 2 3474 R\u00fcedisbach. Postfach 5",
    "sg:city":"Wynigen",
    "sg:orig_category":"Bauschreinerei Herstellung von Konstruktionsteilen, Fertigbauteilen U Ausbauelementen aus Holz",
    "sg:phone":"+41 34 415 19 78",
    "sg:postcode":"3472",
    "sg:province":"Bern",
    "wof:name":"Minder Schreinerei/zimmerei Ag",
    "wof:placetype":"venue"
},
  "geometry": {"coordinates":[7.702974,47.119553],"type":"Point"}
}