{
  "type": "Feature",
  "properties": {
    "iso:country":"CH",
    "sg:address":"Rathausstrasse 35",
    "sg:city":"Weinfelden",
    "sg:orig_category":"Detailhandel mit Brillen U anderen Sehhilfen Fachdetailhandel in Verkaufsr\u00e4umen",
    "sg:phone":"+41 71 622 58 05",
    "sg:postcode":"8570",
    "sg:province":"Thurgau",
    "wof:name":"W\u00fcthrich Optik",
    "wof:placetype":"venue"
},
  "geometry": {"coordinates":[9.108633,47.566475],"type":"Point"}
}