{
  "type": "Feature",
  "properties": {
    "iso:country":"CH",
    "sg:address":"Chemin De La Prairie 19",
    "sg:city":"Corminboeuf",
    "sg:orig_category":"Sonstige mit der Informatik verbundene T\u00e4tigkeiten",
    "sg:postcode":"1720",
    "sg:province":"Fribourg",
    "wof:name":"Npmx S\u00e0rl",
    "wof:placetype":"venue"
},
  "geometry": {"coordinates":[7.1020140648,46.8135108948],"type":"Point"}
}