{
  "type": "Feature",
  "properties": {
    "iso:country":"CH",
    "sg:address":"Rive Cours De 16",
    "sg:city":"Gen\u00e8ve",
    "sg:orig_category":"Zahnarztpraxen",
    "sg:postcode":"1204",
    "sg:province":"Gen\u00e8ve",
    "wof:name":"Consultadent Ag",
    "wof:placetype":"venue"
},
  "geometry": {"coordinates":[8.3107662201,46.9867362976],"type":"Point"}
}