{
  "type": "Feature",
  "properties": {
    "iso:country":"CH",
    "sg:address":"Seetalstrasse 156 5705 Hallwil. Postfach 10",
    "sg:city":"Hallwil",
    "sg:orig_category":"Instandhaltung U Reparatur von Automobilen",
    "sg:phone":"+41 81 413 62 48",
    "sg:postcode":"5705",
    "sg:province":"Aargau",
    "wof:name":"Heiss Gmbh Reparatur- U. Dienstleistungsbetrieb, Bes. Reparatur Von U. Handel Mit Fahrzeugen Usw",
    "wof:placetype":"venue"
},
  "geometry": {"coordinates":[9.8171081543,46.7915420532],"type":"Point"}
}