{
  "type": "Feature",
  "properties": {
    "iso:country":"CH",
    "sg:address":"Le Villards",
    "sg:city":"Vex",
    "sg:orig_category":"G\u00fcterbef\u00f6rderung im Strassenverkehr",
    "sg:phone":"+41 27 207 24 44",
    "sg:postcode":"1981",
    "sg:province":"Valais",
    "wof:name":"Seppey Jean-claude",
    "wof:placetype":"venue"
},
  "geometry": {"coordinates":[7.3985052109,46.2118530273],"type":"Point"}
}