{
  "type": "Feature",
  "properties": {
    "iso:country":"CH",
    "sg:address":"Zugerstrasse 76 6340 Baar. Postfach",
    "sg:city":"Zug",
    "sg:orig_category":"Grosshandel mit chemischen Erzeugnissen Handelsvermittlung von landwirtschaftlichen Grundstoffen, le",
    "sg:phone":"+41 41 768 20 30",
    "sg:postcode":"6300",
    "sg:province":"Zug",
    "wof:name":"Navinon Ag Chemikalien Usw.; Im, Export",
    "wof:placetype":"venue"
},
  "geometry": {"coordinates":[8.519613266,47.1831130981],"type":"Point"}
}