{
  "type": "Feature",
  "properties": {
    "iso:country":"CH",
    "sg:address":"De-candolle Rue 26 1205 Gen\u00e8ve. Postfach",
    "sg:city":"Gen\u00e8ve",
    "sg:orig_category":"Institutionen des Sozialwesens ohne Beherbergung",
    "sg:postcode":"1201",
    "sg:province":"Gen\u00e8ve",
    "wof:name":"Fondation D'aide Aux Victimes De Mines Antipersonnel",
    "wof:placetype":"venue"
},
  "geometry": {"coordinates":[6.1455988884,46.1975822449],"type":"Point"}
}