{
  "type": "Feature",
  "properties": {
    "iso:country":"CH",
    "sg:address":"Aegertenstrasse 19",
    "sg:city":"Biel/bienne",
    "sg:orig_category":"Detailhandel mit Ton U Bildtr\u00e4gern Videotheken",
    "sg:phone":"+41 52 233 27 55",
    "sg:postcode":"2503",
    "sg:province":"Bern",
    "wof:name":"Movie House/erotic World",
    "wof:placetype":"venue"
},
  "geometry": {"coordinates":[8.7607221603,47.4835586548],"type":"Point"}
}