{
  "type": "Feature",
  "properties": {
    "iso:country":"CH",
    "sg:address":"Telmoos 6 1716 Plaffeien. Postfach",
    "sg:city":"Plaffeien",
    "sg:orig_category":"Herstellung von Metallkonstruktionen",
    "sg:postcode":"1716",
    "sg:province":"Fribourg",
    "wof:name":"Riesen Montagen",
    "wof:placetype":"venue"
},
  "geometry": {"coordinates":[7.2919020653,46.7383651733],"type":"Point"}
}