{
  "type": "Feature",
  "properties": {
    "iso:country":"CH",
    "sg:address":"Via Cantonale",
    "sg:city":"Verscio",
    "sg:orig_category":"Autogaragen",
    "sg:phone":"+41 91 796 26 87",
    "sg:postcode":"6653",
    "sg:province":"Ticino",
    "wof:name":"G. Pirro & L.badasci Garage Pedemonte",
    "wof:placetype":"venue"
},
  "geometry": {"coordinates":[8.736475,46.186432],"type":"Point"}
}