{
  "type": "Feature",
  "properties": {
    "iso:country":"CH",
    "sg:address":"St. Niklausstrasse 1",
    "sg:city":"Solothurn",
    "sg:classifiers":[
        {
            "category":"Manufacturing",
            "subcategory":"Chemicals & Compounds",
            "type":"Manufacturing & Wholesale Goods"
        }
    ],
    "sg:phone":"+41 32 626 55 00",
    "sg:postcode":"4500",
    "sg:province":"Solothurn",
    "sg:tags":[
        "industry",
        "containers",
        "tanks",
        "boiler",
        "apparatus"
    ],
    "wof:name":"Ec Chem Ag",
    "wof:placetype":"venue"
},
  "geometry": {"coordinates":[7.539312,47.211491],"type":"Point"}
}