{
  "type": "Feature",
  "properties": {
    "iso:country":"CH",
    "sg:address":"Place Camoletti 6",
    "sg:city":"Gen\u00e8ve",
    "sg:orig_category":"Finanzierungsinstitutionen",
    "sg:phone":"+41 22 786 02 59",
    "sg:postcode":"1207",
    "sg:province":"Gen\u00e8ve",
    "wof:name":"Le Roux G\u00e9rard",
    "wof:placetype":"venue"
},
  "geometry": {"coordinates":[6.1555161476,46.2030067444],"type":"Point"}
}