{
  "type": "Feature",
  "properties": {
    "addr:full":"Straubenzellstrasse 19 St.gallen St. Gallen 9014",
    "addr:housenumber":"19",
    "addr:postcode":"9014",
    "addr:street":"Straubenzellstrasse",
    "iso:country":"CH",
    "sg:address":"Straubenzellstrasse 19",
    "sg:city":"St.gallen",
    "sg:orig_category":"Reisen, Unterk\u00fcnfte",
    "sg:phone":"+41 71 277 13 12",
    "sg:postcode":"9014",
    "sg:province":"St. Gallen",
    "wof:name":"Hotel Sporting In Ch-st.gallen In Der Ostschweiz",
    "wof:placetype":"venue"
},
  "geometry": {"coordinates":[9.333414,47.409035],"type":"Point"}
}