{
  "type": "Feature",
  "properties": {
    "iso:country":"CH",
    "sg:address":"Schulstrasse 11 8413 Neftenbach. Postfach 222",
    "sg:city":"Neftenbach",
    "sg:orig_category":"Detailhandel mit Milcherzeugnissen U Eiern Verarbeitung von Milch",
    "sg:phone":"+41 52 315 15 38",
    "sg:postcode":"8413",
    "sg:province":"Z\u00fcrich",
    "wof:name":"Hans Elsener Milchzentrale",
    "wof:placetype":"venue"
},
  "geometry": {"coordinates":[8.6655664444,47.526222229],"type":"Point"}
}