{
  "type": "Feature",
  "properties": {
    "iso:country":"CH",
    "sg:address":"Impasse Du Siau 5 1462 Yvonand. Postfach",
    "sg:city":"Yvonand",
    "sg:orig_category":"Mechanik Schl\u00fcsselservice",
    "sg:phone":"+41 24 430 23 76",
    "sg:postcode":"1462",
    "sg:province":"Vaud",
    "wof:name":"Illicoservice S\u00e0rl Travaux De Serrurerie Etc",
    "wof:placetype":"venue"
},
  "geometry": {"coordinates":[6.7532029152,46.7961044312],"type":"Point"}
}