{
  "type": "Feature",
  "properties": {
    "iso:country":"CH",
    "sg:address":"Dorfstrasse 111",
    "sg:city":"Planken",
    "sg:orig_category":"G\u00fcterbef\u00f6rderung im Strassenverkehr",
    "sg:phone":"+41 79 419 00 81",
    "sg:postcode":"9498",
    "wof:name":"Kurt Gantner Autotransporte",
    "wof:placetype":"venue"
},
  "geometry": {"coordinates":[9.5469121933,47.1860542297],"type":"Point"}
}