{
  "type": "Feature",
  "properties": {
    "iso:country":"CH",
    "sg:address":"Route De Bellegarde 63",
    "sg:city":"Chancy",
    "sg:orig_category":"Herstellung von Karosserien U Anh\u00e4ngern",
    "sg:phone":"+41 22 756 11 66",
    "sg:postcode":"1284",
    "sg:province":"Gen\u00e8ve",
    "wof:name":"Carrosserie Hubert Preisig",
    "wof:placetype":"venue"
},
  "geometry": {"coordinates":[5.9720239639,46.1497650146],"type":"Point"}
}