{
  "type": "Feature",
  "properties": {
    "addr:full":"Hofstrasse 71 K\u00f6lliken Aargau 5742",
    "addr:housenumber":"71",
    "addr:postcode":"5742",
    "addr:street":"Hofstrasse",
    "iso:country":"CH",
    "sg:address":"Hofstrasse 71",
    "sg:city":"K\u00f6lliken",
    "sg:classifiers":[
        {
            "category":"Manufacturing",
            "subcategory":"Tools & Machinery",
            "type":"Manufacturing & Wholesale Goods"
        }
    ],
    "sg:phone":"+41 62 723 99 77",
    "sg:postcode":"5742",
    "sg:province":"Aargau",
    "sg:tags":[
        "construction",
        "container",
        "apparatus"
    ],
    "wof:name":"Zimmerli Apparatebau Ag",
    "wof:placetype":"venue"
},
  "geometry": {"coordinates":[8.007585,47.324776],"type":"Point"}
}