{
  "type": "Feature",
  "properties": {
    "addr:full":"Untere Bahnhofstrasse 16 8932 Mettmenstetten. Postfach Mettmenstetten Z\u00fcrich 8932",
    "addr:housenumber":"16",
    "addr:postcode":"8932 mettmenstetten. postfach;8932",
    "addr:street":"Untere Bahnhofstrasse",
    "iso:country":"CH",
    "sg:address":"Untere Bahnhofstrasse 16 8932 Mettmenstetten. Postfach",
    "sg:city":"Mettmenstetten",
    "sg:orig_category":"Allgemeiner Hoch U Tiefbau",
    "sg:phone":"+41 61 726 64 00",
    "sg:postcode":"8932",
    "sg:province":"Z\u00fcrich",
    "wof:name":"Aquaform Ag",
    "wof:placetype":"venue"
},
  "geometry": {"coordinates":[7.52535,47.505211],"type":"Point"}
}