{
  "type": "Feature",
  "properties": {
    "iso:country":"CH",
    "sg:address":"Hofwilstrasse 138",
    "sg:city":"M\u00fcnchenbuchsee",
    "sg:orig_category":"Maler U Glasergewerbe",
    "sg:phone":"+41 31692175",
    "sg:postcode":"3053",
    "sg:province":"Bern",
    "wof:name":"Dubach Walter, Malerei",
    "wof:placetype":"venue"
},
  "geometry": {"coordinates":[7.4567680359,47.0159111023],"type":"Point"}
}