{
  "type": "Feature",
  "properties": {
    "iso:country":"CH",
    "sg:address":"Oberdorf 7",
    "sg:city":"Obermumpf",
    "sg:orig_category":"Grosshandel mit Getreide, Saatgut U Futtermitteln",
    "sg:phone":"+41 62 873 13 07",
    "sg:postcode":"4324",
    "sg:province":"Aargau",
    "wof:name":"Anton Vogel Heuhandel",
    "wof:placetype":"venue"
},
  "geometry": {"coordinates":[7.9376649857,47.5303459167],"type":"Point"}
}