{
  "type": "Feature",
  "properties": {
    "addr:full":"Otelfingerstrasse 67 Wettingen Aargau 5430",
    "addr:housenumber":"67",
    "addr:postcode":"5430",
    "addr:street":"Otelfingerstrasse",
    "iso:country":"CH",
    "sg:address":"Otelfingerstrasse 67",
    "sg:city":"Wettingen",
    "sg:orig_category":"Allgemeiner Hoch U Tiefbau Malerei",
    "sg:phone":"+41 56 426 44 74",
    "sg:postcode":"5430",
    "sg:province":"Aargau",
    "wof:name":"Fritz Brunner Fassadenrenovationen",
    "wof:placetype":"venue"
},
  "geometry": {"coordinates":[8.350725,47.458061],"type":"Point"}
}