{
  "type": "Feature",
  "properties": {
    "iso:country":"CH",
    "sg:address":"Feldstrasse 31",
    "sg:city":"Winterthur",
    "sg:orig_category":"Werbung",
    "sg:phone":"+41 52 223 29 20",
    "sg:postcode":"8400",
    "sg:province":"Z\u00fcrich",
    "wof:name":"Transforum Witzig",
    "wof:placetype":"venue"
},
  "geometry": {"coordinates":[8.7190723419,47.5068092346],"type":"Point"}
}