{
  "type": "Feature",
  "properties": {
    "iso:country":"CH",
    "sg:address":"L\u00e4ngfeldstrasse 16",
    "sg:city":"Ittigen",
    "sg:orig_category":"Sportvereine Turnen",
    "sg:phone":"+41 31 922 21 76",
    "sg:postcode":"3063",
    "sg:province":"Bern",
    "wof:name":"Kath.turnverein St.marien",
    "wof:placetype":"venue"
},
  "geometry": {"coordinates":[7.4784722328,46.9839134216],"type":"Point"}
}