{
  "type": "Feature",
  "properties": {
    "iso:country":"CH",
    "sg:address":"Obere Turmatt 4 6370 Stans. Postfach 1141",
    "sg:city":"Stans",
    "sg:orig_category":"Bauingenieurb\u00fcros Heizung L\u00fcftung Klima Bauingenieurb\u00fcros Sanit\u00e4r",
    "sg:phone":"+41 31 331 07 09",
    "sg:postcode":"6371",
    "sg:province":"Nidwalden",
    "wof:name":"Galletti + Bachmann Ag",
    "wof:placetype":"venue"
},
  "geometry": {"coordinates":[7.468921,46.955505],"type":"Point"}
}