{
  "type": "Feature",
  "properties": {
    "iso:country":"CH",
    "sg:address":"Schweizerhausstrasse 14",
    "sg:city":"Engelberg",
    "sg:orig_category":"Architekturb\u00fcros",
    "sg:phone":"+41 41 637 45 89",
    "sg:postcode":"6390",
    "sg:province":"Obwalden",
    "wof:name":"Roland Schacher Architekturb\u00fcro",
    "wof:placetype":"venue"
},
  "geometry": {"coordinates":[8.421191,46.818844],"type":"Point"}
}