{
  "type": "Feature",
  "properties": {
    "iso:country":"CH",
    "sg:address":"L\u00e4gernweg 8",
    "sg:city":"Endingen",
    "sg:orig_category":"Datenverarbeitungsdienste Sonstige mit der Informatik verbundene T\u00e4tigkeiten",
    "sg:phone":"+41 56 242 19 92",
    "sg:postcode":"5304",
    "sg:province":"Aargau",
    "wof:name":"K & B Modeler",
    "wof:placetype":"venue"
},
  "geometry": {"coordinates":[8.294426,47.537037],"type":"Point"}
}