{
  "type": "Feature",
  "properties": {
    "iso:country":"CH",
    "sg:address":"Hard 6 8408 Winterthur. Postfach",
    "sg:city":"Winterthur",
    "sg:orig_category":"Erbringung von Dienstleistungen f\u00fcr Unternehmen",
    "sg:postcode":"8408",
    "sg:province":"Z\u00fcrich",
    "wof:name":"Hajnoczky Peter Konzeption Gestaltung Kommunikation Bearbeitung Von Grafischen Aufgaben Im Bereich Der Visuellen Kommunikation",
    "wof:placetype":"venue"
},
  "geometry": {"coordinates":[8.6764793396,47.5175476074],"type":"Point"}
}