{
  "type": "Feature",
  "properties": {
    "iso:country":"CH",
    "sg:address":"Gottardo Via San 137",
    "sg:city":"Savosa",
    "sg:orig_category":"Reiseb\u00fcros U Reiseveranstalter",
    "sg:phone":"+41 91 967 35 60",
    "sg:postcode":"6942",
    "sg:province":"Ticino",
    "wof:name":"Goes Travel Sa",
    "wof:placetype":"venue"
},
  "geometry": {"coordinates":[8.9505434036,46.0234375],"type":"Point"}
}