{
  "type": "Feature",
  "properties": {
    "iso:country":"CH",
    "sg:address":"Bachtelenrain 23",
    "sg:city":"Grenchen",
    "sg:orig_category":"Luft U Raumfahrzeugbau",
    "sg:postcode":"2540",
    "sg:province":"Solothurn",
    "wof:name":"Grenavia Luftfahrtdienstleistungen Gmbh",
    "wof:placetype":"venue"
},
  "geometry": {"coordinates":[7.3806180954,47.1942901611],"type":"Point"}
}