{
  "type": "Feature",
  "properties": {
    "iso:country":"CH",
    "sg:address":"Seestrasse",
    "sg:city":"Steckborn",
    "sg:orig_category":"Innenarchitekturb\u00fcros",
    "sg:phone":"+41 55 240 61 20",
    "sg:postcode":"8266",
    "sg:province":"Thurgau",
    "wof:name":"J\u00fcrgen Rosinski Innenarchitektur",
    "wof:placetype":"venue"
},
  "geometry": {"coordinates":[8.842455864,47.2557411194],"type":"Point"}
}