{
  "type": "Feature",
  "properties": {
    "iso:country":"CH",
    "sg:address":"Mittelstrasse 17 2500 Biel/bienne. Postfach",
    "sg:city":"Biel/bienne",
    "sg:orig_category":"Non-Classified Establishments",
    "sg:postcode":"2502",
    "sg:province":"Bern",
    "wof:name":"Savic Zoran, Malerbetrieb",
    "wof:placetype":"venue"
},
  "geometry": {"coordinates":[9.1993598938,47.2241897583],"type":"Point"}
}