{
  "type": "Feature",
  "properties": {
    "iso:country":"CH",
    "sg:address":"Sch\u00f6nburgstrasse 48 3013 Bern. Postfach",
    "sg:city":"Bern",
    "sg:orig_category":"Architektur U Ingenieurb\u00fcros",
    "sg:phone":"+41 31 331 36 86",
    "sg:postcode":"3005",
    "sg:province":"Bern",
    "wof:name":"4 D Landschaftsarchitektur Keller + Sch\u00f6ni + Schifferli",
    "wof:placetype":"venue"
},
  "geometry": {"coordinates":[7.457683,46.954933],"type":"Point"}
}