{
  "type": "Feature",
  "properties": {
    "iso:country":"CH",
    "sg:address":"Signalstrasse 12",
    "sg:city":"Rorschach",
    "sg:orig_category":"Wohnheime",
    "sg:phone":"+41 71 845 59 40",
    "sg:postcode":"9400",
    "sg:province":"St. Gallen",
    "wof:name":"Hpv-verein F\u00fcr Regionale Behindertenhilfe",
    "wof:placetype":"venue"
},
  "geometry": {"coordinates":[9.4917392731,47.477432251],"type":"Point"}
}