{
  "type": "Feature",
  "properties": {
    "iso:country":"CH",
    "sg:address":"6344",
    "sg:city":"Meierskappel",
    "sg:orig_category":"Vorschulen, Kinderg\u00e4rten",
    "sg:phone":"+41 41 790 56 06",
    "sg:postcode":"6344",
    "sg:province":"Luzern",
    "wof:name":"Kindergarten Schulhaus",
    "wof:placetype":"venue"
},
  "geometry": {"coordinates":[8.44328022,47.1246833801],"type":"Point"}
}