{
  "type": "Feature",
  "properties": {
    "iso:country":"CH",
    "sg:address":"Klewenalp",
    "sg:city":"Beckenried",
    "sg:orig_category":"Unclassifiable Establishments",
    "sg:phone":"+41 41 620 29 22",
    "sg:postcode":"6375",
    "sg:province":"Nidwalden",
    "wof:name":"Hotel Panorama",
    "wof:placetype":"venue"
},
  "geometry": {"coordinates":[8.475060463,46.9384307861],"type":"Point"}
}