{
  "type": "Feature",
  "properties": {
    "iso:country":"CH",
    "sg:address":"Chemin De Chamblandes 42",
    "sg:city":"Pully",
    "sg:orig_category":"Finanzierungsinstitutionen Unternehmensberatung",
    "sg:phone":"+41 21 729 71 85",
    "sg:postcode":"1009",
    "sg:province":"Vaud",
    "wof:name":"Lms Leverage Management Services S\u00e0rl",
    "wof:placetype":"venue"
},
  "geometry": {"coordinates":[6.6467990875,46.5079536438],"type":"Point"}
}