{
  "type": "Feature",
  "properties": {
    "iso:country":"CH",
    "sg:address":"Rue Des C\u00e8dres 3 1950 Sion Case Postale 950",
    "sg:city":"Sion",
    "sg:orig_category":"Reiseb\u00fcros Verkehrsverb\u00e4nde",
    "sg:phone":"+41 27 329 28 20",
    "sg:postcode":"1951",
    "sg:province":"Valais",
    "wof:name":"Touring-club Suisse Tcs Office & Agence De Voyages",
    "wof:placetype":"venue"
},
  "geometry": {"coordinates":[7.358602047,46.2300262451],"type":"Point"}
}