{
  "type": "Feature",
  "properties": {
    "iso:country":"CH",
    "sg:address":"Euelstrasse 53 8400 Winterthur. Postfach",
    "sg:city":"Winterthur",
    "sg:orig_category":"Herstellung von Schl\u00f6ssern U Beschl\u00e4gen",
    "sg:postcode":"8408",
    "sg:province":"Z\u00fcrich",
    "wof:name":"Schl\u00fcsselfund-service Ruflin",
    "wof:placetype":"venue"
},
  "geometry": {"coordinates":[8.6809244156,47.5103874207],"type":"Point"}
}