{
  "type": "Feature",
  "properties": {
    "iso:country":"CH",
    "sg:address":"Oberdorfstrasse 14 4244 R\u00f6schenz. Postfach",
    "sg:city":"R\u00f6schenz",
    "sg:orig_category":"Detailhandel mit Brot, Back U S\u00fcsswaren",
    "sg:phone":"+41 61 761 64 62",
    "sg:postcode":"4244",
    "sg:province":"Basel-Landschaft",
    "wof:name":"B\u00e4ckerei-konditorei Karrer-cueni",
    "wof:placetype":"venue"
},
  "geometry": {"coordinates":[7.475149,47.425392],"type":"Point"}
}