{
  "type": "Feature",
  "properties": {
    "iso:country":"CH",
    "sg:address":"1718",
    "sg:city":"Rechthalten",
    "sg:orig_category":"Schulpflegen",
    "sg:phone":"+41 27 973 25 72",
    "sg:postcode":"1718",
    "sg:province":"Fribourg",
    "wof:name":"Schulkommission Der Gemeinde Reckingen",
    "wof:placetype":"venue"
},
  "geometry": {"coordinates":[8.2414398193,46.4691390991],"type":"Point"}
}