{
  "type": "Feature",
  "properties": {
    "iso:country":"CH",
    "sg:address":"Ebmattstrasse 11",
    "sg:city":"Bubikon",
    "sg:orig_category":"Vermietung U Verpachtung von eigenen Immobilien",
    "sg:postcode":"8608",
    "sg:province":"Z\u00fcrich",
    "wof:name":"Alpropria H Immobilien Ag",
    "wof:placetype":"venue"
},
  "geometry": {"coordinates":[8.8231477737,47.2684211731],"type":"Point"}
}