{
  "type": "Feature",
  "properties": {
    "iso:country":"CH",
    "sg:address":"Bachtobelstrasse 3",
    "sg:city":"Horgen",
    "sg:orig_category":"Fachdetailhandel in Verkaufsr\u00e4umen Grosshandel mit Schmuck",
    "sg:phone":"+41 31 371 37 38",
    "sg:postcode":"8810",
    "sg:province":"Z\u00fcrich",
    "wof:name":"Tr\u00f6hler Ueli",
    "wof:placetype":"venue"
},
  "geometry": {"coordinates":[7.4329061508,46.9420394897],"type":"Point"}
}