{
  "type": "Feature",
  "properties": {
    "iso:country":"CH",
    "sg:address":"Centralbahnplatz 13",
    "sg:city":"Basel",
    "sg:orig_category":"Fachdetailhandel mit pharmazeutischen Produkten Parf\u00fcmerien U sonstiger Detailhandel mit kosmetische",
    "sg:phone":"+41 61 271 29 99",
    "sg:postcode":"4051",
    "sg:province":"Basel-Stadt",
    "wof:name":"Central-apotheke",
    "wof:placetype":"venue"
},
  "geometry": {"coordinates":[7.5900540352,47.5485534668],"type":"Point"}
}