{
  "type": "Feature",
  "properties": {
    "iso:country":"CH",
    "sg:address":"Hartbergstrasse 9",
    "sg:city":"Chur",
    "sg:orig_category":"Vermietung U Verpachtung von eigenen Immobilien Vermittlung von Immobilien",
    "sg:postcode":"7000",
    "sg:province":"Graubunden",
    "wof:name":"Linus Steiger Treuhand",
    "wof:placetype":"venue"
},
  "geometry": {"coordinates":[9.532201767,46.8532371521],"type":"Point"}
}