{
  "type": "Feature",
  "properties": {
    "iso:country":"CH",
    "sg:address":"7404",
    "sg:city":"Feldis/veulden",
    "sg:classifiers":[
        {
            "category":"Travel",
            "subcategory":"Hotels & Motels",
            "type":"Entertainment"
        }
    ],
    "sg:phone":"+41 81 630 10 80",
    "sg:postcode":"7404",
    "sg:province":"Graubunden",
    "sg:tags":[
        "hotels",
        "mit",
        "restaurant"
    ],
    "wof:name":"Hotel Mira-t\u00f6di",
    "wof:placetype":"venue"
},
  "geometry": {"coordinates":[9.4579896927,46.7896499634],"type":"Point"}
}