{
  "type": "Feature",
  "properties": {
    "iso:country":"CH",
    "sg:address":"Via Stazione 11",
    "sg:city":"Muralto",
    "sg:orig_category":"Detailhandel mit Bekleidung Fischzucht, Teichwirtschaft",
    "sg:phone":"+41 32 751 26 69",
    "sg:postcode":"6600",
    "sg:province":"Ticino",
    "wof:name":"R\u00e9mi Rossel Commerce De Textiles",
    "wof:placetype":"venue"
},
  "geometry": {"coordinates":[7.076169,47.061966],"type":"Point"}
}