{
  "type": "Feature",
  "properties": {
    "iso:country":"CH",
    "sg:address":"Bottenwilerstrasse 142",
    "sg:city":"Staffelbach",
    "sg:orig_category":"Verwertung von Milch",
    "sg:postcode":"5053",
    "sg:province":"Aargau",
    "wof:name":"Milchgenossenschaft Wittwil",
    "wof:placetype":"venue"
},
  "geometry": {"coordinates":[8.0367803574,47.2894325256],"type":"Point"}
}