{
  "type": "Feature",
  "properties": {
    "iso:country":"CH",
    "sg:address":"Alderstrasse 41",
    "sg:city":"Z\u00fcrich",
    "sg:orig_category":"Softwareentwicklung U beratung",
    "sg:phone":"+41 14223261",
    "sg:postcode":"8008",
    "sg:province":"Z\u00fcrich",
    "wof:name":"Upcode Applications Sch\u00e4fer Martin",
    "wof:placetype":"venue"
},
  "geometry": {"coordinates":[8.5541009903,47.3567314148],"type":"Point"}
}