{
  "type": "Feature",
  "properties": {
    "iso:country":"CH",
    "sg:address":"Im Hof 31 5424 Unterehrendingen. Postfach",
    "sg:city":"Unterehrendingen",
    "sg:orig_category":"Herstellung von Duft U K\u00f6rperpflegemitteln",
    "sg:postcode":"5424",
    "wof:name":"Schuler M. Gmbh Praxis F\u00fcr Fusspflege Usw",
    "wof:placetype":"venue"
},
  "geometry": {"coordinates":[8.3467407227,47.5035362244],"type":"Point"}
}