{
  "type": "Feature",
  "properties": {
    "iso:country":"CH",
    "sg:address":"Hauptstrasse 75 5737 Menziken. Postfach",
    "sg:city":"Menziken",
    "sg:orig_category":"Grosshandel mit Nahrungsmitteln, Getr\u00e4nken U Tabakwaren ohne ausgepr\u00e4gten Schwerpunkt",
    "sg:postcode":"5737",
    "sg:province":"Aargau",
    "wof:name":"Schok-schai Thai Shop Gmbh",
    "wof:placetype":"venue"
},
  "geometry": {"coordinates":[8.1899337769,47.2387237549],"type":"Point"}
}