{
  "type": "Feature",
  "properties": {
    "iso:country":"CH",
    "sg:address":"Grabenstrasse 12",
    "sg:city":"Schlieren",
    "sg:orig_category":"Sonstiger Grosshandel",
    "sg:phone":"+41 17312128",
    "sg:postcode":"8952",
    "sg:province":"Z\u00fcrich",
    "wof:name":"Tsp Schweiz Gmbh",
    "wof:placetype":"venue"
},
  "geometry": {"coordinates":[8.4500522614,47.3981933594],"type":"Point"}
}