{
  "type": "Feature",
  "properties": {
    "iso:country":"CH",
    "sg:address":"Bahnhofstrasse 66",
    "sg:city":"Aarburg",
    "sg:orig_category":"Unclassifiable Establishments",
    "sg:phone":"+41 62 791 60 77",
    "sg:postcode":"4663",
    "sg:province":"Aargau",
    "wof:name":"Bms Schmitt Ren\u00e9",
    "wof:placetype":"venue"
},
  "geometry": {"coordinates":[7.9089097977,47.3192367554],"type":"Point"}
}