{
  "type": "Feature",
  "properties": {
    "iso:country":"CH",
    "sg:address":"Gewerbestrasse 13",
    "sg:city":"M\u00e4nnedorf",
    "sg:orig_category":"Elektroinstallation",
    "sg:phone":"+41 19221272",
    "sg:postcode":"8708",
    "sg:province":"Z\u00fcrich",
    "wof:name":"Elektro Fierz Ag",
    "wof:placetype":"venue"
},
  "geometry": {"coordinates":[8.7010097504,47.259021759],"type":"Point"}
}