{
  "type": "Feature",
  "properties": {
    "iso:country":"CH",
    "sg:address":"Gewerbestrasse 18b",
    "sg:city":"Thalwil",
    "sg:orig_category":"Fachdetailhandel in Verkaufsr\u00e4umen",
    "sg:postcode":"8800",
    "sg:province":"Z\u00fcrich",
    "wof:name":"Sw-ski Vertrieb, W. Z\u00fcrcher + Co.",
    "wof:placetype":"venue"
},
  "geometry": {"coordinates":[8.5658521652,47.2859382629],"type":"Point"}
}