{
  "type": "Feature",
  "properties": {
    "iso:country":"CH",
    "sg:address":"Gasthaus Krone",
    "sg:city":"Gonten",
    "sg:orig_category":"Handelsvermittlung U Grosshandel",
    "sg:phone":"+41 71 794 11 61",
    "sg:postcode":"9108",
    "sg:province":"Appenzell Innerhoden",
    "wof:name":"Richard Wettmer Landesprodukte",
    "wof:placetype":"venue"
},
  "geometry": {"coordinates":[9.3437042236,47.3260803223],"type":"Point"}
}