{
  "type": "Feature",
  "properties": {
    "iso:country":"CH",
    "sg:address":"Hardstrasse 74 5430 Wettingen. Postfach 252",
    "sg:city":"Wettingen",
    "sg:orig_category":"Pensionskassen",
    "sg:phone":"+41 56 437 34 34",
    "sg:postcode":"5430",
    "sg:province":"Aargau",
    "wof:name":"F\u00fcrsorgestiftung Der Gutor Electronic Ag",
    "wof:placetype":"venue"
},
  "geometry": {"coordinates":[8.3375053406,47.4568481445],"type":"Point"}
}