{
  "type": "Feature",
  "properties": {
    "iso:country":"CH",
    "sg:address":"Uetlibergstrasse 246",
    "sg:city":"Z\u00fcrich",
    "sg:orig_category":"Druck ohne Zeitungsdruck Satzherstellung U Reproduktion",
    "sg:phone":"+41 14516751",
    "sg:postcode":"8045",
    "sg:province":"Z\u00fcrich",
    "wof:name":"Bg-pack Gmbh Vorstufe F\u00fcr Verpackungsdruck",
    "wof:placetype":"venue"
},
  "geometry": {"coordinates":[8.5126037598,47.3558006287],"type":"Point"}
}