{
  "type": "Feature",
  "properties": {
    "iso:country":"CH",
    "sg:address":"Obere Gasse 53 7000 Chur. Postfach",
    "sg:city":"Chur",
    "sg:orig_category":"Drogerien Herstellung von Anstrichmitteln, Druckfarben U Kitten",
    "sg:phone":"+41 81 252 17 21",
    "sg:postcode":"7001",
    "sg:province":"Graubunden",
    "wof:name":"Ullius & Co., Hs.",
    "wof:placetype":"venue"
},
  "geometry": {"coordinates":[9.5298070908,46.848110199],"type":"Point"}
}