{
  "type": "Feature",
  "properties": {
    "iso:country":"CH",
    "sg:address":"Im Feld 9",
    "sg:city":"Hermetschwil-staff",
    "sg:orig_category":"Sonstiger Grosshandel",
    "sg:phone":"+41 31 951 52 09",
    "sg:postcode":"5626",
    "sg:province":"Aargau",
    "wof:name":"Hadiscom Gmbh",
    "wof:placetype":"venue"
},
  "geometry": {"coordinates":[7.4838709831,46.9332084656],"type":"Point"}
}