{
  "type": "Feature",
  "properties": {
    "iso:country":"CH",
    "sg:address":"Ue Montsalvens 11",
    "sg:city":"Broc",
    "sg:classifiers":[
        {
            "category":"Banks & Credit Unions",
            "subcategory":"Bank",
            "type":"Services"
        }
    ],
    "sg:phone":"+41 2961222",
    "sg:postcode":"1636",
    "sg:province":"Fribourg",
    "wof:name":"Union Bank Of Switzerland",
    "wof:placetype":"venue"
},
  "geometry": {"coordinates":[7.101285,46.602856],"type":"Point"}
}