{
  "type": "Feature",
  "properties": {
    "iso:country":"CH",
    "sg:address":"Cordiers Rue Des 19 A 1207 Gen\u00e8ve. Postfach",
    "sg:city":"Gen\u00e8ve",
    "sg:orig_category":"Erbringung von Dienstleistungen f\u00fcr Unternehmen",
    "sg:postcode":"1207",
    "sg:province":"Gen\u00e8ve",
    "wof:name":"Style Int\u00e9rieur Von Ballmoos Et Berberat S\u00e0rl",
    "wof:placetype":"venue"
},
  "geometry": {"coordinates":[6.8285098076,47.1050643921],"type":"Point"}
}