{
  "type": "Feature",
  "properties": {
    "iso:country":"CH",
    "sg:address":"Bischofg\u00e4ssli 5",
    "sg:city":"Jegenstorf",
    "sg:classifiers":[
        {
            "category":"Government",
            "subcategory":"Post Office",
            "type":"Public Place"
        }
    ],
    "sg:phone":"+41 31 761 03 07",
    "sg:postcode":"3303",
    "sg:province":"Bern",
    "sg:tags":[
        "caf\u00e9s",
        "tea-rooms"
    ],
    "wof:name":"Tea-room Jegi",
    "wof:placetype":"venue"
},
  "geometry": {"coordinates":[7.5063939095,47.0475158691],"type":"Point"}
}