{
  "type": "Feature",
  "properties": {
    "iso:country":"CH",
    "sg:address":"Langackerstrasse 3",
    "sg:city":"M\u00fcnchenstein",
    "sg:orig_category":"Physiotherapie",
    "sg:phone":"+41 61 411 12 32",
    "sg:postcode":"4142",
    "sg:province":"Basel-Landschaft",
    "wof:name":"Marianne Ruckstuhl Physiotherapie",
    "wof:placetype":"venue"
},
  "geometry": {"coordinates":[7.6166758537,47.5230560303],"type":"Point"}
}