{
  "type": "Feature",
  "properties": {
    "iso:country":"CH",
    "sg:address":"Bahnhofstrasse 10",
    "sg:city":"Rheinfelden",
    "sg:orig_category":"Detailhandel mit Bekleidung Detailhandel mit Textilien",
    "sg:phone":"+41 61 831 48 13",
    "sg:postcode":"4310",
    "sg:province":"Aargau",
    "wof:name":"Nitaya Hinnen Seiden-laden",
    "wof:placetype":"venue"
},
  "geometry": {"coordinates":[7.791944,47.554482],"type":"Point"}
}