{
  "type": "Feature",
  "properties": {
    "iso:country":"CH",
    "sg:address":"B\u00e4lliz 69 3600 Thun. Postfach",
    "sg:city":"Thun",
    "sg:orig_category":"RESTAURANTS: TEA-ROOMS",
    "sg:postcode":"3600",
    "sg:province":"Bern",
    "wof:name":"Kernen W., Wirtschaft Zum Steinbock",
    "wof:placetype":"venue"
},
  "geometry": {"coordinates":[7.6298937798,46.7574081421],"type":"Point"}
}