{
  "type": "Feature",
  "properties": {
    "iso:country":"CH",
    "sg:address":"Zelgstr. 1",
    "sg:city":"Kreuzlingen",
    "sg:classifiers":[
        {
            "category":"Professional",
            "subcategory":"Printing & Photocopies",
            "type":"Services"
        }
    ],
    "sg:phone":"+41 71 686 52 52",
    "sg:postcode":"8280",
    "sg:province":"Thurgau",
    "sg:tags":[
        "publishing"
    ],
    "wof:name":"Bodan Ag Druckerei Und Verlag",
    "wof:placetype":"venue"
},
  "geometry": {"coordinates":[9.2010583878,47.6411972046],"type":"Point"}
}