{
  "type": "Feature",
  "properties": {
    "iso:country":"CH",
    "sg:address":"Rue De Bourg 39",
    "sg:city":"Lausanne",
    "sg:orig_category":"RESTAURANTS: TEA-ROOMS",
    "sg:postcode":"1000",
    "sg:province":"Vaud",
    "wof:name":"Manuel Daniel",
    "wof:placetype":"venue"
},
  "geometry": {"coordinates":[6.6360449791,46.5201454163],"type":"Point"}
}