{
  "type": "Feature",
  "properties": {
    "iso:country":"CH",
    "sg:address":"Patriotenweg 9",
    "sg:city":"Solothurn",
    "sg:orig_category":"Arbeitnehmerverb\u00e4nde",
    "sg:phone":"+41 32 621 53 23",
    "sg:postcode":"4500",
    "sg:province":"Solothurn",
    "wof:name":"Verband Lehrerinnen & Lehrer Solothurn",
    "wof:placetype":"venue"
},
  "geometry": {"coordinates":[7.537341,47.205387],"type":"Point"}
}