{
  "type": "Feature",
  "properties": {
    "addr:full":"Gotthardstrasse 49 Andermatt Uri 6490",
    "addr:housenumber":"49",
    "addr:postcode":"6490",
    "addr:street":"Gotthardstrasse;Uri",
    "iso:country":"CH",
    "sg:address":"Gotthardstrasse 49",
    "sg:city":"Andermatt",
    "sg:orig_category":"B\u00e4ckereien Konditoreien",
    "sg:postcode":"6490",
    "sg:province":"Uri",
    "wof:name":"Eduard Baumann B\u00e4ckerei-konditorei",
    "wof:placetype":"venue"
},
  "geometry": {"coordinates":[8.596521,46.634579],"type":"Point"}
}