{
  "type": "Feature",
  "properties": {
    "iso:country":"CH",
    "sg:address":"Morand Rue Marc 22",
    "sg:city":"Martigny",
    "sg:orig_category":"Unclassifiable Establishments",
    "sg:postcode":"1920",
    "sg:province":"Valais",
    "wof:name":"Fondation La Pluie Du Matin R\u00e9jouit Le P\u00e8lerin",
    "wof:placetype":"venue"
},
  "geometry": {"coordinates":[7.0713381767,46.1046218872],"type":"Point"}
}