{
  "type": "Feature",
  "properties": {
    "iso:country":"CH",
    "sg:address":"Allmeind 22",
    "sg:city":"Glarus",
    "sg:orig_category":"Unternehmensberatung",
    "sg:postcode":"8750",
    "sg:province":"Glarus",
    "wof:name":"St\u00fcssi Fritz, Projekte + Consulting",
    "wof:placetype":"venue"
},
  "geometry": {"coordinates":[9.0697460175,47.038608551],"type":"Point"}
}