{
  "type": "Feature",
  "properties": {
    "iso:country":"CH",
    "sg:address":"Bahnhofstrasse 2 2502 Biel/bienne. Postfach",
    "sg:city":"Biel/bienne",
    "sg:orig_category":"Advokaturb\u00fcros",
    "sg:phone":"+41 12662170",
    "sg:postcode":"2501",
    "sg:province":"Bern",
    "wof:name":"Wenger Plattner Advokaturb\u00fcro",
    "wof:placetype":"venue"
},
  "geometry": {"coordinates":[8.574125,47.327305],"type":"Point"}
}