{
  "type": "Feature",
  "properties": {
    "iso:country":"CH",
    "sg:address":"Seminarstrasse 86 8057 Z\u00fcrich. Postfach",
    "sg:city":"Z\u00fcrich",
    "sg:orig_category":"Herstellung von sonstigen Maschinen f\u00fcr bestimmte Verwendung",
    "sg:postcode":"8057",
    "sg:province":"Z\u00fcrich",
    "wof:name":"E.ch.o. Polistirolo Sa",
    "wof:placetype":"venue"
},
  "geometry": {"coordinates":[9.0934152603,46.2361106873],"type":"Point"}
}