{
  "type": "Feature",
  "properties": {
    "iso:country":"CH",
    "sg:address":"Chemin Des Bains 1040 Echallens Case Postale",
    "sg:city":"Echallens",
    "sg:orig_category":"Kauf U Verkauf von Immobilien auf eigene Rechnung Vermietung U Verpachtung von eigenen Immobilien",
    "sg:phone":"+41 14919123",
    "sg:postcode":"1040",
    "sg:province":"Vaud",
    "wof:name":"Ilemoc-immobilien Ag",
    "wof:placetype":"venue"
},
  "geometry": {"coordinates":[8.4735498428,47.3593673706],"type":"Point"}
}