{
  "type": "Feature",
  "properties": {
    "iso:country":"CH",
    "sg:address":"9000",
    "sg:city":"St.gallen",
    "sg:orig_category":"Detailhandel mit M\u00f6beln Fachdetailhandel in Verkaufsr\u00e4umen",
    "sg:phone":"+41 79 344 25 73",
    "sg:postcode":"9000",
    "sg:province":"St. Gallen",
    "wof:name":"Galleria Verde Pflanzen M\u00f6bel",
    "wof:placetype":"venue"
},
  "geometry": {"coordinates":[9.3780097961,47.4236297607],"type":"Point"}
}