{
  "type": "Feature",
  "properties": {
    "iso:country":"CH",
    "sg:address":"Dornacherstrasse 27 4053 Basel. Postfach",
    "sg:city":"Basel",
    "sg:orig_category":"Grosshandel mit B\u00fcromaschinen",
    "sg:phone":"+41 71 245 44 31",
    "sg:postcode":"4008",
    "sg:province":"Basel-Stadt",
    "wof:name":"Fritz Schumacher Ag Offset-& Kopiermaschinen",
    "wof:placetype":"venue"
},
  "geometry": {"coordinates":[9.3827676773,47.4268531799],"type":"Point"}
}