{
  "type": "Feature",
  "properties": {
    "iso:country":"CH",
    "sg:address":"Route De Beaumont 20 1700 Fribourg Case Postale 1057",
    "sg:city":"Fribourg",
    "sg:orig_category":"Detailhandel mit B\u00fcchern",
    "sg:phone":"+41 26 425 85 95",
    "sg:postcode":"1701",
    "sg:province":"Fribourg",
    "wof:name":"Albert Le Grand Sa Librairie",
    "wof:placetype":"venue"
},
  "geometry": {"coordinates":[7.140626,46.796673],"type":"Point"}
}