{
  "type": "Feature",
  "properties": {
    "iso:country":"CH",
    "sg:address":"Zugerstrasse 23",
    "sg:city":"W\u00e4denswil",
    "sg:classifiers":[
        {
            "category":"Government",
            "subcategory":"Post Office",
            "type":"Public Place"
        }
    ],
    "sg:phone":"+41 17807438",
    "sg:postcode":"8820",
    "sg:province":"Z\u00fcrich",
    "sg:tags":[
        "caf\u00e9s",
        "tea-rooms"
    ],
    "wof:name":"Caf\u00e9 City",
    "wof:placetype":"venue"
},
  "geometry": {"coordinates":[8.6701726913,47.2295761108],"type":"Point"}
}