{
  "type": "Feature",
  "properties": {
    "iso:country":"CH",
    "sg:address":"R\u00fceggisingerstrasse 29",
    "sg:city":"Emmenbr\u00fccke",
    "sg:orig_category":"Gymnastik U Fitnesszentren Saunas, Solarien, Fitnesszentren U \u00e4hnliches",
    "sg:phone":"+41 41 260 85 22",
    "sg:postcode":"6020",
    "sg:province":"Luzern",
    "wof:name":"Dynamic Fitness-center Gmbh",
    "wof:placetype":"venue"
},
  "geometry": {"coordinates":[8.2775802612,47.0785865784],"type":"Point"}
}