{
  "type": "Feature",
  "properties": {
    "iso:country":"CH",
    "sg:address":"B\u00e4umlimatt 1",
    "sg:city":"Wildegg",
    "sg:orig_category":"Herstellung von sonstigen Produkten aus nichtmetallischen Mineralien Instandhaltung U Reparatur von ",
    "sg:phone":"+41 21 903 27 27",
    "sg:postcode":"5103",
    "sg:province":"Aargau",
    "wof:name":"Frisba Ag",
    "wof:placetype":"venue"
},
  "geometry": {"coordinates":[6.7711448669,46.5909996033],"type":"Point"}
}