{
  "type": "Feature",
  "properties": {
    "iso:country":"CH",
    "sg:address":"2713",
    "sg:city":"Bellelay",
    "sg:orig_category":"Sportvereine Eissport Eishockey",
    "sg:postcode":"2713",
    "sg:province":"Bern",
    "wof:name":"Hockey-club Le Locle",
    "wof:placetype":"venue"
},
  "geometry": {"coordinates":[6.7467451096,47.056476593],"type":"Point"}
}