{
  "type": "Feature",
  "properties": {
    "iso:country":"CH",
    "sg:address":"Aemmenmattstrasse 5/36",
    "sg:city":"Belp",
    "sg:classifiers":[
        {
            "category":"Insurance",
            "subcategory":"Insurance Agent",
            "type":"Services"
        }
    ],
    "sg:phone":"+41 17811070",
    "sg:postcode":"3123",
    "sg:province":"Bern",
    "sg:tags":[
        "versicherungsagenturen",
        "-broker"
    ],
    "wof:name":"Allianz Versicherung",
    "wof:placetype":"venue"
},
  "geometry": {"coordinates":[8.641462326,47.2400283813],"type":"Point"}
}