{
  "type": "Feature",
  "properties": {
    "iso:country":"CH",
    "sg:address":"Capannone Zucchetti",
    "sg:city":"Bironico",
    "sg:orig_category":"Technische, physikalische U chemische Untersuchung",
    "sg:phone":"+41 71 622 75 55",
    "sg:postcode":"6804",
    "sg:province":"Ticino",
    "wof:name":"Genossenschaft Clarowwf",
    "wof:placetype":"venue"
},
  "geometry": {"coordinates":[9.1381845474,47.5666694641],"type":"Point"}
}