{
  "type": "Feature",
  "properties": {
    "iso:country":"CH",
    "sg:address":"Kasernenstrasse 103",
    "sg:city":"Chur",
    "sg:orig_category":"Herstellung von Teppichen",
    "sg:phone":"+41 81 756 51 52",
    "sg:postcode":"7000",
    "sg:province":"Graubunden",
    "wof:name":"Tsv - Top Service Gmbh",
    "wof:placetype":"venue"
},
  "geometry": {"coordinates":[9.4750080109,47.166305542],"type":"Point"}
}