{
  "type": "Feature",
  "properties": {
    "iso:country":"CH",
    "sg:address":"Bhofstrasse 21",
    "sg:city":"Russikon",
    "sg:orig_category":"Sonstige pers\u00f6nliche Dienstleistungen",
    "sg:postcode":"8332",
    "sg:province":"Z\u00fcrich",
    "wof:name":"Morel Consulting Gmbh",
    "wof:placetype":"venue"
},
  "geometry": {"coordinates":[8.7790489197,47.3942756653],"type":"Point"}
}