{
  "type": "Feature",
  "properties": {
    "iso:country":"CH",
    "sg:address":"Unterer Sandb\u00fchl",
    "sg:city":"Stettfurt",
    "sg:orig_category":"Schwimmb\u00e4der",
    "sg:phone":"+41 52 376 10 71",
    "sg:postcode":"9507",
    "sg:province":"Thurgau",
    "wof:name":"Schwimmbad Am Sonnenberg",
    "wof:placetype":"venue"
},
  "geometry": {"coordinates":[8.9552621841,47.5240783691],"type":"Point"}
}