{
  "type": "Feature",
  "properties": {
    "iso:country":"CH",
    "sg:address":"Boulevard De Grancy 12",
    "sg:city":"Lausanne",
    "sg:orig_category":"Grosshandel mit Sportartikeln Grosshandel mit chemischen Erzeugnissen",
    "sg:phone":"+41 79 607 88 82",
    "sg:postcode":"1006",
    "sg:province":"Vaud",
    "wof:name":"Piscines-fitness S\u00e0rl Articles De Sport, Notamm. De Piscines Et Pour Le Traitement De L'eau; Commerce",
    "wof:placetype":"venue"
},
  "geometry": {"coordinates":[6.5581297874,46.5123977661],"type":"Point"}
}