{
  "type": "Feature",
  "properties": {
    "iso:country":"CH",
    "sg:address":"Impasse De La Grangette 15",
    "sg:city":"Villars-sur-gl\u00e2ne",
    "sg:orig_category":"Malerei",
    "sg:phone":"+41 26 402 19 40",
    "sg:postcode":"1752",
    "sg:province":"Fribourg",
    "wof:name":"Andr\u00e9 Rody Entreprise De Peinture",
    "wof:placetype":"venue"
},
  "geometry": {"coordinates":[7.1384921074,46.7895088196],"type":"Point"}
}