{
  "type": "Feature",
  "properties": {
    "iso:country":"CH",
    "sg:address":"Bahnhofstrasse 3",
    "sg:city":"Biel/bienne",
    "sg:orig_category":"Unclassifiable Establishments",
    "sg:postcode":"2502",
    "sg:province":"Bern",
    "wof:name":"Goldhaus Wildi",
    "wof:placetype":"venue"
},
  "geometry": {"coordinates":[7.2421541214,47.1339607239],"type":"Point"}
}