{
  "type": "Feature",
  "properties": {
    "iso:country":"CH",
    "sg:address":"Buzibachstrasse 25",
    "sg:city":"Rothenburg",
    "sg:orig_category":"Detailhandel mit elektrischen Haushalts-,Radio U Fernsehger\u00e4ten sowie Musikinstrumenten Reparatur vo",
    "sg:phone":"+41 41 282 07 42",
    "sg:postcode":"6023",
    "sg:province":"Luzern",
    "wof:name":"Ottiger Shop Kaffeemaschinen",
    "wof:placetype":"venue"
},
  "geometry": {"coordinates":[8.2580308914,47.0927047729],"type":"Point"}
}