{
  "type": "Feature",
  "properties": {
    "iso:country":"CH",
    "sg:address":"Dammstrasse 21 4500 Solothurn. Postfach",
    "sg:city":"Solothurn",
    "sg:orig_category":"Verwaltung von Immobilien Wirtschaftspr\u00fcfung, Steuerberatung U Treuhand",
    "sg:phone":"+41 79 422 64 64",
    "sg:postcode":"4502",
    "sg:province":"Solothurn",
    "wof:name":"Ig Treuhand Und Revisions Ag Reinach",
    "wof:placetype":"venue"
},
  "geometry": {"coordinates":[8.1746788025,47.2570381165],"type":"Point"}
}