{
  "type": "Feature",
  "properties": {
    "iso:country":"CH",
    "sg:address":"Zwirnerstrasse 70",
    "sg:city":"Z\u00fcrich",
    "sg:orig_category":"Non-Classified Establishments",
    "sg:phone":"+41 844 804 010",
    "sg:postcode":"8041",
    "sg:province":"Z\u00fcrich",
    "wof:name":"Cablecom Gmbh Winerthur",
    "wof:placetype":"venue"
},
  "geometry": {"coordinates":[8.5161151886,47.3383407593],"type":"Point"}
}