{
  "type": "Feature",
  "properties": {
    "iso:country":"CH",
    "sg:address":"Wolleraustrasse 53",
    "sg:city":"Freienbach",
    "sg:orig_category":"Pensionskassen",
    "sg:postcode":"8807",
    "sg:province":"Schwyz",
    "wof:name":"Wohlfahrtsstiftung Der Difag Ag, Freienbach.",
    "wof:placetype":"venue"
},
  "geometry": {"coordinates":[8.7545871735,47.2020874023],"type":"Point"}
}