{
  "type": "Feature",
  "properties": {
    "iso:country":"CH",
    "sg:address":"Remorino Via 4",
    "sg:city":"Minusio",
    "sg:orig_category":"Schreib U \u00dcbersetzungsb\u00fcros",
    "sg:phone":"+41 91 743 73 75",
    "sg:postcode":"6648",
    "sg:province":"Ticino",
    "wof:name":"Crt - Radczuweit Claudia Traduzioni",
    "wof:placetype":"venue"
},
  "geometry": {"coordinates":[8.8179149628,46.1779403687],"type":"Point"}
}