{
  "type": "Feature",
  "properties": {
    "iso:country":"CH",
    "sg:address":"Hartbertstrasse 11 7000 Chur. Postfach",
    "sg:city":"Chur",
    "sg:orig_category":"Arbeitnehmerverb\u00e4nde",
    "sg:phone":"+41 32 422 19 59",
    "sg:postcode":"7000",
    "sg:province":"Graubunden",
    "wof:name":"Syna Synd.interprofessionnel Section Artisanat",
    "wof:placetype":"venue"
},
  "geometry": {"coordinates":[7.350325,47.362839],"type":"Point"}
}