{
  "type": "Feature",
  "properties": {
    "iso:country":"CH",
    "sg:address":"Schaalgasse 5",
    "sg:city":"Solothurn",
    "sg:orig_category":"Reparatur von Schuhen U Lederwaren",
    "sg:phone":"+41 32 623 21 79",
    "sg:postcode":"4500",
    "sg:province":"Solothurn",
    "wof:name":"Antonio Sturzo Schuhmacherei",
    "wof:placetype":"venue"
},
  "geometry": {"coordinates":[7.5372362137,47.2069168091],"type":"Point"}
}