{
  "type": "Feature",
  "properties": {
    "iso:country":"CH",
    "sg:address":"Chemin De La Jaque 50",
    "sg:city":"Ch\u00e2telard-lutry",
    "sg:orig_category":"Unclassifiable Establishments",
    "sg:postcode":"1095",
    "sg:province":"Vaud",
    "wof:name":"Fondation Claude Latour",
    "wof:placetype":"venue"
},
  "geometry": {"coordinates":[6.6805691719,46.5153579712],"type":"Point"}
}