{
  "type": "Feature",
  "properties": {
    "iso:country":"CH",
    "sg:address":"Rue Du Bas-du-ru",
    "sg:city":"Granges-marnand",
    "sg:orig_category":"Elektroinstallation Fernmeldedienste",
    "sg:phone":"+41 26 668 02 12",
    "sg:postcode":"1523",
    "sg:province":"Vaud",
    "wof:name":"Cdg Electricit\u00e9 & Telecom S\u00e0rl",
    "wof:placetype":"venue"
},
  "geometry": {"coordinates":[6.8863401413,46.763343811],"type":"Point"}
}