{
  "type": "Feature",
  "properties": {
    "iso:country":"CH",
    "sg:address":"Rue Du Cardinal-journet 57",
    "sg:city":"Meyrin",
    "sg:orig_category":"Herstellung von Konstruktionsteilen, Fertigbauteilen U Ausbauelementen aus Holz",
    "sg:postcode":"1217",
    "sg:province":"Gen\u00e8ve",
    "wof:name":"Costa Roland.",
    "wof:placetype":"venue"
},
  "geometry": {"coordinates":[6.0795221329,46.2257804871],"type":"Point"}
}