{
  "type": "Feature",
  "properties": {
    "iso:country":"CH",
    "sg:address":"Rainackerweg 1",
    "sg:city":"St\u00fcsslingen",
    "sg:orig_category":"Erdbewegungsarbeiten",
    "sg:phone":"+41 62 298 17 19",
    "sg:postcode":"4655",
    "sg:province":"Solothurn",
    "wof:name":"Josef Wittmer",
    "wof:placetype":"venue"
},
  "geometry": {"coordinates":[7.9759497643,47.3955345154],"type":"Point"}
}