{
  "type": "Feature",
  "properties": {
    "iso:country":"CH",
    "sg:address":"Birrfeldstrasse 7",
    "sg:city":"Mellingen",
    "sg:orig_category":"Nationale Postdienste",
    "sg:phone":"+41 56 491 10 20",
    "sg:postcode":"5507",
    "sg:province":"Aargau",
    "wof:name":"Die Schweizerische Post",
    "wof:placetype":"venue"
},
  "geometry": {"coordinates":[8.2715244293,47.4182090759],"type":"Point"}
}