{
  "type": "Feature",
  "properties": {
    "iso:country":"CH",
    "sg:address":"R\u00fcttistrasse 1",
    "sg:city":"Zollikofen",
    "sg:orig_category":"Unclassifiable Establishments",
    "sg:phone":"+41 31 911 16 94",
    "sg:postcode":"3052",
    "sg:province":"Bern",
    "wof:name":"Bridge Network Solutions",
    "wof:placetype":"venue"
},
  "geometry": {"coordinates":[7.4598889351,46.9958648682],"type":"Point"}
}