{
  "type": "Feature",
  "properties": {
    "iso:country":"CH",
    "sg:address":"Bachtobelstrasse 4",
    "sg:city":"Horgen",
    "sg:orig_category":"Grosshandel mit chemischen Erzeugnissen",
    "sg:postcode":"8810",
    "sg:province":"Z\u00fcrich",
    "wof:name":"Duclean, Duriaux E. & G.",
    "wof:placetype":"venue"
},
  "geometry": {"coordinates":[6.7878599167,46.5902786255],"type":"Point"}
}