{
  "type": "Feature",
  "properties": {
    "iso:country":"CH",
    "sg:address":"Rives-de-la-morges 7",
    "sg:city":"Morges",
    "sg:orig_category":"Arztpraxen",
    "sg:phone":"+41 32 913 72 73",
    "sg:postcode":"1110",
    "sg:province":"Vaud",
    "wof:name":"Dr M\u00e9d. Claude-andr\u00e9 Moser M\u00e9decin Sp\u00e9cialiste Fmh",
    "wof:placetype":"venue"
},
  "geometry": {"coordinates":[6.824681,47.101959],"type":"Point"}
}