{
  "type": "Feature",
  "properties": {
    "iso:country":"CH",
    "sg:address":"Juraweg 14",
    "sg:city":"Vordemwald",
    "sg:orig_category":"Handel mit Motorr\u00e4dern, Teilen U Zubeh\u00f6r Instandhaltung U Reparatur von Motorr\u00e4dern",
    "sg:postcode":"4803",
    "sg:province":"Aargau",
    "wof:name":"Wolf T.",
    "wof:placetype":"venue"
},
  "geometry": {"coordinates":[7.9045300484,47.274181366],"type":"Point"}
}