{
  "type": "Feature",
  "properties": {
    "iso:country":"CH",
    "sg:address":"Route De Rolle 48",
    "sg:city":"St-prex",
    "sg:orig_category":"Herstellung von M\u00f6beln Innenausbau",
    "sg:phone":"+41 41 672 99 11",
    "sg:postcode":"1162",
    "sg:province":"Vaud",
    "wof:name":"Alpnach Norm-schrankelemente Ag",
    "wof:placetype":"venue"
},
  "geometry": {"coordinates":[8.2706480026,46.9377784729],"type":"Point"}
}