{
  "type": "Feature",
  "properties": {
    "iso:country":"CH",
    "sg:address":"Via Besso 43",
    "sg:city":"Lugano",
    "sg:orig_category":"Verwaltung von Immobilien",
    "sg:phone":"+41 91 967 45 00",
    "sg:postcode":"6900",
    "sg:province":"Ticino",
    "wof:name":"Gusto Antico Pizzeria Al Trancio",
    "wof:placetype":"venue"
},
  "geometry": {"coordinates":[8.9393587112,46.0092391968],"type":"Point"}
}