{
  "type": "Feature",
  "properties": {
    "iso:country":"CH",
    "sg:address":"Fahrstrasse 6",
    "sg:city":"Wolfwil",
    "sg:orig_category":"Detailhandel mit medizinischen U orthop\u00e4dischen Artikeln Reparatur von Schuhen U Lederwaren",
    "sg:phone":"+41 62 926 25 65",
    "sg:postcode":"4628",
    "sg:province":"Solothurn",
    "wof:name":"Gregor Wyss",
    "wof:placetype":"venue"
},
  "geometry": {"coordinates":[7.7975430489,47.2678260803],"type":"Point"}
}