{
  "type": "Feature",
  "properties": {
    "iso:country":"CH",
    "sg:address":"Spalenring 136",
    "sg:city":"Basel",
    "sg:classifiers":[
        {
            "category":"Professional",
            "subcategory":"Employment Agencies",
            "type":"Services"
        }
    ],
    "sg:phone":"+41 61 301 36 00",
    "sg:postcode":"4055",
    "sg:province":"Basel-Stadt",
    "sg:tags":[
        "personal",
        "u",
        "stellenvermittlung"
    ],
    "wof:name":"A-jobs Ag Personalvermittlung Usw",
    "wof:placetype":"venue"
},
  "geometry": {"coordinates":[7.5756411552,47.5553817749],"type":"Point"}
}