{
  "type": "Feature",
  "properties": {
    "iso:country":"CH",
    "sg:address":"Aubodenstrasse 20",
    "sg:city":"Seuzach",
    "sg:orig_category":"Gartenbau",
    "sg:phone":"+41 52 335 15 66",
    "sg:postcode":"8472",
    "sg:province":"Z\u00fcrich",
    "wof:name":"Maraffino Gartenbau Ag",
    "wof:placetype":"venue"
},
  "geometry": {"coordinates":[8.7159385681,47.5255889893],"type":"Point"}
}