{
  "type": "Feature",
  "properties": {
    "iso:country":"CH",
    "sg:address":"Place Pury 2",
    "sg:city":"Neuch\u00e2tel",
    "sg:orig_category":"Detailhandel mit Damenbekleidung Kleiderboutiquen",
    "sg:phone":"+41 17618844",
    "sg:postcode":"2000",
    "sg:province":"Neuch\u00e2tel",
    "wof:name":"Chicor\u00e9e Mode Ag",
    "wof:placetype":"venue"
},
  "geometry": {"coordinates":[8.4524431229,47.278263092],"type":"Point"}
}