{
  "type": "Feature",
  "properties": {
    "iso:country":"CH",
    "sg:address":"Avenue Louis-ruchonnet 3",
    "sg:city":"Lausanne",
    "sg:classifiers":[
        {
            "category":"Professional",
            "subcategory":"Engineering",
            "type":"Services"
        }
    ],
    "sg:phone":"+41 21 312 33 23",
    "sg:postcode":"1003",
    "sg:province":"Vaud",
    "wof:name":"Glass Industry Services Ltd.",
    "wof:placetype":"venue"
},
  "geometry": {"coordinates":[6.627273,46.517822],"type":"Point"}
}