{
  "type": "Feature",
  "properties": {
    "iso:country":"CH",
    "sg:address":"Rue Des Longschamps 10",
    "sg:city":"Hauterive",
    "sg:orig_category":"Primarschulen",
    "sg:phone":"+41 32 756 97 43",
    "sg:postcode":"2068",
    "sg:province":"Neuch\u00e2tel",
    "wof:name":"Ecole Primaire Centre Scolaire",
    "wof:placetype":"venue"
},
  "geometry": {"coordinates":[6.9715008736,47.0121994019],"type":"Point"}
}