{
  "type": "Feature",
  "properties": {
    "iso:country":"CH",
    "sg:address":"G\u00fcterstrasse 4",
    "sg:city":"Neuenhof",
    "sg:orig_category":"Sonstiger Grosshandel",
    "sg:postcode":"5432",
    "sg:province":"Aargau",
    "wof:name":"Jasna Ognjanovic Z.",
    "wof:placetype":"venue"
},
  "geometry": {"coordinates":[8.3303394318,47.4453201294],"type":"Point"}
}