{
  "type": "Feature",
  "properties": {
    "iso:country":"CH",
    "sg:address":"St. Gallerstrasse 60 9400 Rorschach. Postfach 143",
    "sg:city":"Rorschach",
    "sg:orig_category":"Vermittlung von Immobilien Wirtschaftspr\u00fcfung, Steuerberatung U Treuhand",
    "sg:phone":"+41 71 845 31 31",
    "sg:postcode":"9401",
    "sg:province":"St. Gallen",
    "wof:name":"Hafner-buchhaltungs Ag",
    "wof:placetype":"venue"
},
  "geometry": {"coordinates":[9.4812459946,47.4785881042],"type":"Point"}
}