{
  "type": "Feature",
  "properties": {
    "iso:country":"CH",
    "sg:address":"Pr\u00e9s Rue Des 51",
    "sg:city":"Tramelan",
    "sg:orig_category":"Erschliessung von Grundst\u00fccken",
    "sg:postcode":"2720",
    "sg:province":"Bern",
    "wof:name":"Coop\u00e9rative D'habitation Les C\u00e8dres",
    "wof:placetype":"venue"
},
  "geometry": {"coordinates":[7.1003022194,47.2231445312],"type":"Point"}
}