{
  "type": "Feature",
  "properties": {
    "iso:country":"CH",
    "sg:address":"Z\u00fcrcherstrasse 1",
    "sg:city":"Baden",
    "sg:orig_category":"Detailhandel mit Damenbekleidung Detailhandel mit Herrenbekleidung",
    "sg:phone":"+41 56 210 05 21",
    "sg:postcode":"5400",
    "sg:province":"Aargau",
    "wof:name":"Spengler Ag Count-down Mode-discount",
    "wof:placetype":"venue"
},
  "geometry": {"coordinates":[8.3060407639,47.4708518982],"type":"Point"}
}