{
  "type": "Feature",
  "properties": {
    "iso:country":"CH",
    "sg:address":"Bahnweg 7",
    "sg:city":"H\u00e4gendorf",
    "sg:orig_category":"P\u00e9dicure",
    "sg:phone":"+41 62 216 36 06",
    "sg:postcode":"4614",
    "sg:province":"Solothurn",
    "wof:name":"Marie-theres Merz Kosmetik & P\u00e9dicure",
    "wof:placetype":"venue"
},
  "geometry": {"coordinates":[7.8418278694,47.3315925598],"type":"Point"}
}