{
  "type": "Feature",
  "properties": {
    "iso:country":"CH",
    "sg:address":"Turenmattenstrasse 6",
    "sg:city":"Meiringen",
    "sg:orig_category":"Vermittlung von Immobilien Wirtschaftspr\u00fcfung, Steuerberatung U Treuhand",
    "sg:phone":"+41 33 822 73 79",
    "sg:postcode":"3860",
    "sg:province":"Bern",
    "wof:name":"Anderegg Treuhand",
    "wof:placetype":"venue"
},
  "geometry": {"coordinates":[8.185090065,46.7257003784],"type":"Point"}
}