{
  "type": "Feature",
  "properties": {
    "iso:country":"CH",
    "sg:address":"Dorfstrasse 70",
    "sg:city":"Giffers",
    "sg:orig_category":"Herstellung von Konstruktionsteilen, Fertigbauteilen U Ausbauelementen aus Holz Zimmerei, Ingenieurh",
    "sg:phone":"+41 26 418 16 15",
    "sg:postcode":"1735",
    "sg:province":"Fribourg",
    "wof:name":"Bapst Bruno.",
    "wof:placetype":"venue"
},
  "geometry": {"coordinates":[7.2030057907,46.7652626038],"type":"Point"}
}