{
  "type": "Feature",
  "properties": {
    "iso:country":"CH",
    "sg:address":"La Rapille",
    "sg:city":"Villars-ste-croix",
    "sg:orig_category":"Detailhandel mit Metallwaren, Anstrichmitteln, Glaswaren, Bau U Heimwerkerbedarf Installation von He",
    "sg:phone":"+41 21 701 49 70",
    "sg:postcode":"1029",
    "sg:province":"Vaud",
    "wof:name":"As Technique, Sousa J.",
    "wof:placetype":"venue"
},
  "geometry": {"coordinates":[6.561191082,46.5639953613],"type":"Point"}
}