{
  "type": "Feature",
  "properties": {
    "iso:country":"CH",
    "sg:address":"Sch\u00f6nhaldenstrasse 21 8272 Ermatingen. Postfach",
    "sg:city":"Ermatingen",
    "sg:classifiers":[
        {
            "category":"Restaurant",
            "type":"Food & Drink"
        }
    ],
    "sg:phone":"+41 71 660 08 80",
    "sg:postcode":"8272",
    "sg:province":"Thurgau",
    "wof:name":"Restaurant Sch\u00f6nhalde",
    "wof:placetype":"venue"
},
  "geometry": {"coordinates":[9.0866060257,47.6660194397],"type":"Point"}
}