{
  "type": "Feature",
  "properties": {
    "iso:country":"CH",
    "sg:address":"Aire La Ville Route D' 24",
    "sg:city":"Bernex",
    "sg:orig_category":"RESTAURANTS: TEA-ROOMS",
    "sg:phone":"+41 81 833 32 65",
    "sg:postcode":"1233",
    "sg:province":"Gen\u00e8ve",
    "wof:name":"Melcher Arthur.",
    "wof:placetype":"venue"
},
  "geometry": {"coordinates":[9.838965416,46.4982147217],"type":"Point"}
}