{
  "type": "Feature",
  "properties": {
    "iso:country":"CH",
    "sg:address":"Via Ramogna 3",
    "sg:city":"Locarno",
    "sg:orig_category":"HOTELS: OHNE RESTAURANT",
    "sg:phone":"+41 91 751 29 21",
    "sg:postcode":"6600",
    "sg:province":"Ticino",
    "wof:name":"Albergo Du Lac",
    "wof:placetype":"venue"
},
  "geometry": {"coordinates":[8.7992010117,46.170425415],"type":"Point"}
}