{
  "type": "Feature",
  "properties": {
    "iso:country":"CH",
    "sg:address":"Baarerstrasse 75 6300 Zug. Postfach",
    "sg:city":"Zug",
    "sg:orig_category":"Detailhandel mit Metallwaren, Anstrichmitteln, Glaswaren, Bau U Heimwerkerbedarf",
    "sg:postcode":"6300",
    "sg:province":"Zug",
    "wof:name":"Tamona Ag",
    "wof:placetype":"venue"
},
  "geometry": {"coordinates":[8.517616272,47.1769981384],"type":"Point"}
}