{
  "type": "Feature",
  "properties": {
    "iso:country":"CH",
    "sg:address":"Hauentalstrasse 50",
    "sg:city":"Schaffhausen",
    "sg:classifiers":[
        {
            "category":"Restaurant",
            "type":"Food & Drink"
        }
    ],
    "sg:phone":"+41 71 223 28 96",
    "sg:postcode":"8200",
    "sg:province":"Schaffhausen",
    "wof:name":"Restaurant Playboy",
    "wof:placetype":"venue"
},
  "geometry": {"coordinates":[9.3786716461,47.4240684509],"type":"Point"}
}