{
  "type": "Feature",
  "properties": {
    "iso:country":"CH",
    "sg:address":"Zollrain 10",
    "sg:city":"Aarau",
    "sg:orig_category":"Detailhandel mit Fleisch U Fleischwaren",
    "sg:phone":"+41 62 822 37 48",
    "sg:postcode":"5000",
    "sg:province":"Aargau",
    "wof:name":"A. Speck Metzgerei Und Restaurant",
    "wof:placetype":"venue"
},
  "geometry": {"coordinates":[8.0433740616,47.3936843872],"type":"Point"}
}