{
  "type": "Feature",
  "properties": {
    "iso:country":"CH",
    "sg:address":"Rue De Lausanne 42 1530 Payerne Case Postale 254",
    "sg:city":"Payerne",
    "sg:orig_category":"Detailhandel mit Textilien Herstellung von konfektionierten Textilwaren ohne Bekleidung",
    "sg:phone":"+41 26 660 46 14",
    "sg:postcode":"1530",
    "sg:province":"Vaud",
    "wof:name":"Jean Crausaz Rally Literie Meubles",
    "wof:placetype":"venue"
},
  "geometry": {"coordinates":[6.9367527962,46.8192749023],"type":"Point"}
}