{
  "type": "Feature",
  "properties": {
    "iso:country":"CH",
    "sg:address":"Nassa Via 60",
    "sg:city":"Lugano",
    "sg:orig_category":"Unclassifiable Establishments",
    "sg:postcode":"6900",
    "sg:province":"Ticino",
    "wof:name":"Tisvi Sa",
    "wof:placetype":"venue"
},
  "geometry": {"coordinates":[8.9493074417,46.0011444092],"type":"Point"}
}