{
  "type": "Feature",
  "properties": {
    "iso:country":"CH",
    "sg:address":"Stampfenbrunnenstrasse 1",
    "sg:city":"Z\u00fcrich",
    "sg:orig_category":"Unclassifiable Establishments",
    "sg:postcode":"8048",
    "sg:province":"Z\u00fcrich",
    "wof:name":"Giahi - Ilardo & Turki",
    "wof:placetype":"venue"
},
  "geometry": {"coordinates":[8.4804077148,47.3882637024],"type":"Point"}
}