{
  "type": "Feature",
  "properties": {
    "iso:country":"CH",
    "sg:address":"Emmentalstrasse 73c 3510 Konolfingen. Postfach 140",
    "sg:city":"Konolfingen",
    "sg:orig_category":"Allgemeiner Hochbau Bau von Strassen, Sportanlagen U Bahnverkehrsstrecken",
    "sg:phone":"+41 31 791 05 34",
    "sg:postcode":"3510",
    "sg:province":"Bern",
    "wof:name":"Batigroup Ag Emmental",
    "wof:placetype":"venue"
},
  "geometry": {"coordinates":[7.633507,46.885609],"type":"Point"}
}