{
  "type": "Feature",
  "properties": {
    "iso:country":"CH",
    "sg:address":"Spalenring 44 4055 Basel. Postfach 306",
    "sg:city":"Basel",
    "sg:orig_category":"Wirtschaftspr\u00fcfung, Steuerberatung U Treuhand",
    "sg:postcode":"4009",
    "sg:province":"Basel-Stadt",
    "wof:name":"Treuhandb\u00fcro Schaub",
    "wof:placetype":"venue"
},
  "geometry": {"coordinates":[7.9917340279,47.5545425415],"type":"Point"}
}