{
  "type": "Feature",
  "properties": {
    "iso:country":"CH",
    "sg:address":"Zypressenstrasse 3",
    "sg:city":"Winterthur",
    "sg:orig_category":"Non-Classified Establishments",
    "sg:postcode":"8408",
    "sg:province":"Z\u00fcrich",
    "wof:name":"Tang Fricker, Ren-chinesische Schule F\u00fcr Sprache Und Kultur",
    "wof:placetype":"venue"
},
  "geometry": {"coordinates":[8.689412117,47.510219574],"type":"Point"}
}