{
  "type": "Feature",
  "properties": {
    "iso:country":"CH",
    "sg:address":"1646",
    "sg:city":"Echarlens",
    "sg:orig_category":"Grosshandel mit Holz U Bauelementen aus Holz S\u00e4gewerke",
    "sg:phone":"+41 26 915 16 24",
    "sg:postcode":"1646",
    "sg:province":"Fribourg",
    "wof:name":"Rapha\u00ebl Gremaud Scierie-commerce De Bois",
    "wof:placetype":"venue"
},
  "geometry": {"coordinates":[7.0820398331,46.6472587585],"type":"Point"}
}