{
  "type": "Feature",
  "properties": {
    "iso:country":"CH",
    "sg:address":"Rychgass 1",
    "sg:city":"Basadingen",
    "sg:orig_category":"Sonstiger Grosshandel",
    "sg:postcode":"8254",
    "sg:province":"Thurgau",
    "wof:name":"Grajcevci Elmi",
    "wof:placetype":"venue"
},
  "geometry": {"coordinates":[8.7477750778,47.6687355042],"type":"Point"}
}