{
  "type": "Feature",
  "properties": {
    "iso:country":"CH",
    "sg:address":"Unterdorfstrasse 19",
    "sg:city":"Watt",
    "sg:orig_category":"Unternehmensberatung",
    "sg:phone":"+41 61 401 17 86",
    "sg:postcode":"8105",
    "sg:province":"Z\u00fcrich",
    "wof:name":"Abgottspon Markus",
    "wof:placetype":"venue"
},
  "geometry": {"coordinates":[7.5503649712,47.5122642517],"type":"Point"}
}