{
  "type": "Feature",
  "properties": {
    "iso:country":"CH",
    "sg:address":"Rue De Gen\u00e8ve 101",
    "sg:city":"Th\u00f4nex",
    "sg:orig_category":"Detailhandel mit Tabakwaren",
    "sg:phone":"+41 22 349 23 77",
    "sg:postcode":"1226",
    "sg:province":"Gen\u00e8ve",
    "wof:name":"Claude Perret Tabac",
    "wof:placetype":"venue"
},
  "geometry": {"coordinates":[6.200761795,46.1934623718],"type":"Point"}
}