{
  "type": "Feature",
  "properties": {
    "iso:country":"CH",
    "sg:address":"Johanniterstrasse 11",
    "sg:city":"Basel",
    "sg:orig_category":"Grosshandel mit sonstigen Gebrauchs U Verbrauchsg\u00fctern",
    "sg:phone":"+41 61 322 55 33",
    "sg:postcode":"4056",
    "sg:province":"Basel-Stadt",
    "wof:name":"Meier Ren\u00e9",
    "wof:placetype":"venue"
},
  "geometry": {"coordinates":[7.5820579529,47.5650062561],"type":"Point"}
}