{
  "type": "Feature",
  "properties": {
    "iso:country":"CH",
    "sg:address":"Tschachenstrasse 4",
    "sg:city":"Bilten",
    "sg:orig_category":"Handel mit Automobilen",
    "sg:phone":"+41 55 615 24 61",
    "sg:postcode":"8865",
    "sg:province":"Glarus",
    "wof:name":"Schmid Hans",
    "wof:placetype":"venue"
},
  "geometry": {"coordinates":[9.0305223465,47.1530761719],"type":"Point"}
}