{
  "type": "Feature",
  "properties": {
    "iso:country":"CH",
    "sg:address":"Route De Rolle 2a",
    "sg:city":"St-prex",
    "sg:orig_category":"Elektroinstallation Fernmeldedienste",
    "sg:phone":"+41 21 806 44 86",
    "sg:postcode":"1162",
    "sg:province":"Vaud",
    "wof:name":"Weibel Francis Institut De Beaut\u00e9 Katia",
    "wof:placetype":"venue"
},
  "geometry": {"coordinates":[6.4570188522,46.4811096191],"type":"Point"}
}