{
  "type": "Feature",
  "properties": {
    "iso:country":"CH",
    "sg:address":"Z\u00fcrichstrasse 151",
    "sg:city":"Aathal-seegr\u00e4ben",
    "sg:orig_category":"Non-Classified Establishments",
    "sg:postcode":"8607",
    "sg:province":"Z\u00fcrich",
    "wof:name":"Colibri Holding Ag",
    "wof:placetype":"venue"
},
  "geometry": {"coordinates":[8.3094043732,46.9828605652],"type":"Point"}
}