{
  "type": "Feature",
  "properties": {
    "iso:country":"CH",
    "sg:address":"4202",
    "sg:city":"Duggingen",
    "sg:orig_category":"Schulpflegen",
    "sg:phone":"+41 61 751 60 95",
    "sg:postcode":"4202",
    "sg:province":"Basel-Landschaft",
    "wof:name":"Primarschulkommission Der Gemeinde Duggingen",
    "wof:placetype":"venue"
},
  "geometry": {"coordinates":[7.6079897881,47.4483108521],"type":"Point"}
}