{
  "type": "Feature",
  "properties": {
    "iso:country":"CH",
    "sg:address":"Schulhausstrasse",
    "sg:city":"Lalden",
    "sg:orig_category":"Verlegen von Fliesen U Platten",
    "sg:phone":"+41 79 629 17 19",
    "sg:postcode":"3931",
    "sg:province":"Valais",
    "wof:name":"J\u00f6rg Pfammatter Plattengesch\u00e4ft",
    "wof:placetype":"venue"
},
  "geometry": {"coordinates":[7.9043002129,46.2983894348],"type":"Point"}
}