{
  "type": "Feature",
  "properties": {
    "iso:country":"CH",
    "sg:address":"Kreuzb\u00fchlstrasse 40",
    "sg:city":"Netstal",
    "sg:classifiers":[
        {
            "category":"Restaurant",
            "type":"Food & Drink"
        }
    ],
    "sg:phone":"+41 55 640 18 22",
    "sg:postcode":"8754",
    "sg:province":"Glarus",
    "wof:name":"Restaurant Salmen",
    "wof:placetype":"venue"
},
  "geometry": {"coordinates":[9.0562257767,47.0626869202],"type":"Point"}
}