{
  "type": "Feature",
  "properties": {
    "addr:full":"Rue De L'h\u00f4pital 2 Neuch\u00e2tel Neuch\u00e2tel 2000",
    "addr:housenumber":"2",
    "addr:postcode":"2000",
    "addr:street":"Rue De L'Ho \u0302Pital",
    "iso:country":"CH",
    "sg:address":"Rue De L'h\u00f4pital 2",
    "sg:city":"Neuch\u00e2tel",
    "sg:orig_category":"Arztpraxen",
    "sg:phone":"+41 24 492 30 41",
    "sg:postcode":"2000",
    "sg:province":"Neuch\u00e2tel",
    "wof:name":"Dr M\u00e9d. Pascal Gertsch M\u00e9decin G\u00e9n\u00e9raliste Fmh",
    "wof:placetype":"venue"
},
  "geometry": {"coordinates":[7.158712,46.35004],"type":"Point"}
}