{
  "type": "Feature",
  "properties": {
    "iso:country":"CH",
    "sg:address":"Le Moulin-de-gressy 1432 Belmont-yverdon Case Postale",
    "sg:city":"Valeyres-ursins",
    "sg:orig_category":"Haltung von Gefl\u00fcgel",
    "sg:phone":"+41 24 435 14 94",
    "sg:postcode":"1412",
    "sg:province":"Vaud",
    "wof:name":"Lepitre Jacques Sa",
    "wof:placetype":"venue"
},
  "geometry": {"coordinates":[6.6356348991,46.7486228943],"type":"Point"}
}