{
  "type": "Feature",
  "properties": {
    "iso:country":"CH",
    "sg:address":"Im Guet 6",
    "sg:city":"Langwiesen",
    "sg:orig_category":"Verlegen von Fliesen U Platten",
    "sg:phone":"+41 52 659 41 75",
    "sg:postcode":"8246",
    "sg:province":"Z\u00fcrich",
    "wof:name":"Patrick Bienz Keramische Wand-& Bodenbel\u00e4ge",
    "wof:placetype":"venue"
},
  "geometry": {"coordinates":[8.6626825333,47.6844444275],"type":"Point"}
}