{
  "type": "Feature",
  "properties": {
    "iso:country":"CH",
    "sg:address":"Bahnhofplatz 1",
    "sg:city":"Baden",
    "sg:orig_category":"Wirtschaftspr\u00fcfung, Steuerberatung U Treuhand",
    "sg:phone":"+41 56 222 80 51",
    "sg:postcode":"5400",
    "sg:province":"Aargau",
    "wof:name":"Pabo Gmbh",
    "wof:placetype":"venue"
},
  "geometry": {"coordinates":[8.3086118698,47.4764671326],"type":"Point"}
}