{
  "type": "Feature",
  "properties": {
    "iso:country":"CH",
    "sg:address":"Sch\u00fctzenstrasse 18",
    "sg:city":"Rorschacherberg",
    "sg:orig_category":"Sportvereine Behindertensport",
    "sg:phone":"+41 71 855 73 23",
    "sg:postcode":"9404",
    "sg:province":"St. Gallen",
    "wof:name":"Svbs Rorschach",
    "wof:placetype":"venue"
},
  "geometry": {"coordinates":[9.4918699265,47.4706802368],"type":"Point"}
}