{
  "type": "Feature",
  "properties": {
    "iso:country":"CH",
    "sg:address":"Emdwiesenstrasse 29 8240 Thayngen. Postfach 171",
    "sg:city":"Thayngen",
    "sg:orig_category":"Sonstiger Grosshandel",
    "sg:phone":"+41 52 645 07 07",
    "sg:postcode":"8240",
    "sg:province":"Schaffhausen",
    "wof:name":"Wunder-baum Ag",
    "wof:placetype":"venue"
},
  "geometry": {"coordinates":[8.7110214233,47.7420158386],"type":"Point"}
}