{
  "type": "Feature",
  "properties": {
    "iso:country":"CH",
    "sg:address":"Steinm\u00fcristrasse 2 8123 Ebmatingen. Postfach",
    "sg:city":"Ebmatingen",
    "sg:orig_category":"Fachdetailhandel in Verkaufsr\u00e4umen",
    "sg:phone":"+41 19805820",
    "sg:postcode":"8123",
    "sg:province":"Z\u00fcrich",
    "wof:name":"Grab Rad-sport-technik Grab Harald Fahrr\u00e4der, Zubeh\u00f6r; Handel, Herstellung Und Reparatur",
    "wof:placetype":"venue"
},
  "geometry": {"coordinates":[8.642156601,47.3499336243],"type":"Point"}
}