{
  "type": "Feature",
  "properties": {
    "iso:country":"CH",
    "sg:address":"M\u00fcrtschenstrasse 20",
    "sg:city":"Z\u00fcrich",
    "sg:orig_category":"Kauf U Verkauf von Immobilien auf eigene Rechnung",
    "sg:postcode":"8048",
    "sg:province":"Z\u00fcrich",
    "wof:name":"M\u00fcller Beat, Liegenschaften Und Treuhand Ag, Z\u00fcrich",
    "wof:placetype":"venue"
},
  "geometry": {"coordinates":[8.4972295761,47.3874092102],"type":"Point"}
}