{
  "type": "Feature",
  "properties": {
    "addr:full":"Bahnhofstrasse 3 Fl\u00fcelen Uri 6454",
    "addr:housenumber":"3",
    "addr:postcode":"6454",
    "addr:street":"Bahnhofstrasse;Uri",
    "iso:country":"CH",
    "sg:address":"Bahnhofstrasse 3",
    "sg:city":"Fl\u00fcelen",
    "sg:orig_category":"Anticorrosives",
    "sg:phone":"+41 41 871 26 28",
    "sg:postcode":"6454",
    "sg:province":"Uri",
    "wof:name":"Teko Oberfl\u00e4chentechnik Und Farbenzentrum Gmbh",
    "wof:placetype":"venue"
},
  "geometry": {"coordinates":[8.624112,46.900684],"type":"Point"}
}