{
  "type": "Feature",
  "properties": {
    "iso:country":"CH",
    "sg:address":"Rue Saint-henri 2 2800 Delsberg. Postfach",
    "sg:city":"Delsberg",
    "sg:orig_category":"Herstellung von Bergwerks U Baumaschinen",
    "sg:postcode":"2800",
    "sg:province":"Jura",
    "wof:name":"Dela (suisse) Sa",
    "wof:placetype":"venue"
},
  "geometry": {"coordinates":[7.3385868073,47.3525466919],"type":"Point"}
}