{
  "type": "Feature",
  "properties": {
    "iso:country":"CH",
    "sg:address":"3113",
    "sg:city":"Rubigen",
    "sg:orig_category":"Landw. Genossenschaften Viehzucht",
    "sg:postcode":"3113",
    "sg:province":"Bern",
    "wof:name":"Viehzuchtgenossenschaft",
    "wof:placetype":"venue"
},
  "geometry": {"coordinates":[7.5441198349,46.8983802795],"type":"Point"}
}