{
  "type": "Feature",
  "properties": {
    "iso:country":"CH",
    "sg:address":"Temple Rue Du 3 1096 Cully. Postfach",
    "sg:city":"Cully",
    "sg:orig_category":"Grosshandel mit Tabakwaren",
    "sg:phone":"+41 21 799 16 50",
    "sg:postcode":"1096",
    "sg:province":"Vaud",
    "wof:name":"Le Minaret, Wait & Ommeniello Magasin De Tabacs, Journaux Etc",
    "wof:placetype":"venue"
},
  "geometry": {"coordinates":[6.7302689552,46.4886474609],"type":"Point"}
}