{
  "type": "Feature",
  "properties": {
    "iso:country":"CH",
    "sg:address":"Rte Jo Siffert 36",
    "sg:city":"Givisiez",
    "sg:classifiers":[
        {
            "category":"Manufacturing",
            "subcategory":"Rubber & Plastics",
            "type":"Manufacturing & Wholesale Goods"
        }
    ],
    "sg:phone":"+41 26 467 71 11",
    "sg:postcode":"1762",
    "sg:province":"Fribourg",
    "wof:name":"Michelin Sa",
    "wof:placetype":"venue"
},
  "geometry": {"coordinates":[7.117588,46.81411],"type":"Point"}
}