{
  "type": "Feature",
  "properties": {
    "iso:country":"CH",
    "sg:address":"Bachfeldstrasse 13 9403 Goldach. Postfach",
    "sg:city":"Goldach",
    "sg:orig_category":"Fernmeldedienste",
    "sg:postcode":"9403",
    "sg:province":"St. Gallen",
    "wof:name":"D-projects Lazzarini Fabio",
    "wof:placetype":"venue"
},
  "geometry": {"coordinates":[9.4746522903,47.4802093506],"type":"Point"}
}