{
  "type": "Feature",
  "properties": {
    "iso:country":"CH",
    "sg:address":"Ausserdorf 10a 8322 Madetswil. Postfach",
    "sg:city":"Madetswil",
    "sg:orig_category":"Sonstige mit der Informatik verbundene T\u00e4tigkeiten",
    "sg:phone":"+41 19956353",
    "sg:postcode":"8322",
    "sg:province":"Z\u00fcrich",
    "wof:name":"Interware Gmbh",
    "wof:placetype":"venue"
},
  "geometry": {"coordinates":[8.7904605865,47.4095497131],"type":"Point"}
}