{
  "type": "Feature",
  "properties": {
    "iso:country":"CH",
    "sg:address":"Bahnhofstrasse 11",
    "sg:city":"R\u00fcschlikon",
    "sg:orig_category":"Detailhandel mit Getr\u00e4nken Grosshandel mit Getr\u00e4nken",
    "sg:postcode":"8803",
    "sg:province":"Z\u00fcrich",
    "wof:name":"Getr\u00e4nkehandel Lang Gmbh",
    "wof:placetype":"venue"
},
  "geometry": {"coordinates":[8.1480493546,47.4470710754],"type":"Point"}
}