{
  "type": "Feature",
  "properties": {
    "iso:country":"CH",
    "sg:address":"Willenhofstrasse 29",
    "sg:city":"Hochfelden",
    "sg:orig_category":"Sonstiger Grosshandel",
    "sg:phone":"+41 18606416",
    "sg:postcode":"8182",
    "sg:province":"Z\u00fcrich",
    "wof:name":"Gemperli Peter",
    "wof:placetype":"venue"
},
  "geometry": {"coordinates":[8.5142688751,47.5169258118],"type":"Point"}
}