{
  "type": "Feature",
  "properties": {
    "iso:country":"CH",
    "sg:address":"Vy-d'etra 50",
    "sg:city":"Neuenburg",
    "sg:orig_category":"Non-Classified Establishments",
    "sg:postcode":"2000",
    "sg:province":"Neuch\u00e2tel",
    "wof:name":"Fs-distribution, Fahrni S\u00e9bastien",
    "wof:placetype":"venue"
},
  "geometry": {"coordinates":[6.941450119,46.9826812744],"type":"Point"}
}