{
  "type": "Feature",
  "properties": {
    "iso:country":"CH",
    "sg:address":"6410",
    "sg:city":"Goldau",
    "sg:classifiers":[
        {
            "category":"Travel",
            "subcategory":"Hotels & Motels",
            "type":"Entertainment"
        }
    ],
    "sg:phone":"+41 41 850 10 02",
    "sg:postcode":"6410",
    "sg:province":"Schwyz",
    "sg:tags":[
        "hotels",
        "mit",
        "restaurant"
    ],
    "wof:name":"Hotel Rigi-seebodenalp",
    "wof:placetype":"venue"
},
  "geometry": {"coordinates":[8.4430551529,47.0825958252],"type":"Point"}
}