{
  "type": "Feature",
  "properties": {
    "iso:country":"CH",
    "sg:address":"Rue Du March\u00e9 12-14 1200 Genf. Postfach",
    "sg:city":"Gen\u00e8ve",
    "sg:orig_category":"Detailhandel mit Bekleidung",
    "sg:postcode":"1204",
    "sg:province":"Gen\u00e8ve",
    "wof:name":"Andr\u00e9 Gilles Cohen",
    "wof:placetype":"venue"
},
  "geometry": {"coordinates":[6.145956,46.203335],"type":"Point"}
}