{
  "type": "Feature",
  "properties": {
    "addr:full":"Lindenweg 6 R\u00fcmlang Z\u00fcrich 8153",
    "addr:housenumber":"6",
    "addr:postcode":"8153",
    "addr:street":"Lindenweg;Zuerich",
    "iso:country":"CH",
    "sg:address":"Lindenweg 6",
    "sg:city":"R\u00fcmlang",
    "sg:orig_category":"Architektur U Ingenieurb\u00fcros",
    "sg:phone":"+41 19372767",
    "sg:postcode":"8153",
    "sg:province":"Z\u00fcrich",
    "wof:name":"W\u00e4fler E. Ingenieurb\u00fcro",
    "wof:placetype":"venue"
},
  "geometry": {"coordinates":[8.85844,47.287884],"type":"Point"}
}