{
  "type": "Feature",
  "properties": {
    "iso:country":"CH",
    "sg:address":"Hagenbuch 243",
    "sg:city":"Sch\u00f6nholzerswilen",
    "sg:orig_category":"Verwertung von Milch",
    "sg:postcode":"8577",
    "sg:province":"Thurgau",
    "wof:name":"Peter Wittwer",
    "wof:placetype":"venue"
},
  "geometry": {"coordinates":[9.1184196472,47.5199890137],"type":"Point"}
}