{
  "type": "Feature",
  "properties": {
    "iso:country":"CH",
    "sg:address":"Gerbistrasse 3",
    "sg:city":"Ennenda",
    "sg:orig_category":"W\u00e4scherei U chemische Reinigung",
    "sg:phone":"+41 55 640 16 24",
    "sg:postcode":"8755",
    "sg:province":"Glarus",
    "wof:name":"Noser Erwin, Textilreinigung",
    "wof:placetype":"venue"
},
  "geometry": {"coordinates":[9.0705842972,47.0446281433],"type":"Point"}
}