{
  "type": "Feature",
  "properties": {
    "iso:country":"CH",
    "sg:address":"La Foge-dessus",
    "sg:city":"Marchissy",
    "sg:orig_category":"S\u00e4gewerke",
    "sg:phone":"+41 55 284 10 60",
    "sg:postcode":"1261",
    "sg:province":"Vaud",
    "wof:name":"Pius Eicher S\u00e4gerei",
    "wof:placetype":"venue"
},
  "geometry": {"coordinates":[9.0695314407,47.2788391113],"type":"Point"}
}