{
  "type": "Feature",
  "properties": {
    "iso:country":"CH",
    "sg:address":"B\u00fcchelrain 7",
    "sg:city":"Adliswil",
    "sg:orig_category":"Sportvereine Eissport Curling",
    "sg:phone":"+41 17090789",
    "sg:postcode":"8134",
    "sg:province":"Z\u00fcrich",
    "wof:name":"Dolder Curlingbahnen Verein",
    "wof:placetype":"venue"
},
  "geometry": {"coordinates":[8.5199222565,47.3012962341],"type":"Point"}
}