{
  "type": "Feature",
  "properties": {
    "iso:country":"CH",
    "sg:address":"Avenue Des Platanes 13 3960 Sierre Case Postale 848",
    "sg:city":"Sierre",
    "sg:orig_category":"Detektivb\u00fcros U \u00dcberwachung",
    "sg:phone":"+41 800 808 590",
    "sg:postcode":"3960",
    "sg:province":"Valais",
    "wof:name":"Securitas Ag Schweiz. Bewachungsgesellschaft",
    "wof:placetype":"venue"
},
  "geometry": {"coordinates":[7.5296649933,46.2896728516],"type":"Point"}
}