{
  "type": "Feature",
  "properties": {
    "iso:country":"CH",
    "sg:address":"Dorfstrasse 29",
    "sg:city":"Engelberg",
    "sg:classifiers":[
        {
            "category":"Government",
            "subcategory":"Post Office",
            "type":"Public Place"
        }
    ],
    "sg:phone":"+41 41 637 25 24",
    "sg:postcode":"6390",
    "sg:province":"Obwalden",
    "sg:tags":[
        "caf\u00e9s",
        "tea-rooms"
    ],
    "wof:name":"Caf\u00e9 Zur Alten Post",
    "wof:placetype":"venue"
},
  "geometry": {"coordinates":[8.4045152664,46.8210792542],"type":"Point"}
}