{
  "type": "Feature",
  "properties": {
    "iso:country":"CH",
    "sg:address":"L\u00f6wenstrasse 4",
    "sg:city":"Kreuzlingen",
    "sg:orig_category":"Herstellung von Kakao, Schokoladeerzeugnissen U Zuckerwaren",
    "sg:postcode":"8280",
    "sg:province":"Thurgau",
    "wof:name":"Peter Elmer, City Caf\u00e9-confiserie",
    "wof:placetype":"venue"
},
  "geometry": {"coordinates":[9.1745462418,47.6478652954],"type":"Point"}
}