{
  "type": "Feature",
  "properties": {
    "addr:full":"D\u00fcrren\u00e4scherstrasse 106 Hallwil Aargau 5705",
    "addr:housenumber":"106",
    "addr:postcode":"5705",
    "addr:street":"Duerrenaescherstrasse",
    "iso:country":"CH",
    "sg:address":"D\u00fcrren\u00e4scherstrasse 106",
    "sg:city":"Hallwil",
    "sg:classifiers":[
        {
            "category":"Home & Garden",
            "subcategory":"Building Materials",
            "type":"Retail Goods"
        }
    ],
    "sg:phone":"+41 62 777 26 28",
    "sg:postcode":"5705",
    "sg:province":"Aargau",
    "sg:tags":[
        "central",
        "heating",
        "boiler"
    ],
    "wof:name":"Max Boesch",
    "wof:placetype":"venue"
},
  "geometry": {"coordinates":[8.174736,47.329273],"type":"Point"}
}