{
  "type": "Feature",
  "properties": {
    "iso:country":"CH",
    "sg:address":"1264",
    "sg:city":"St-cergue",
    "sg:orig_category":"Detailhandel mit Brot, Back U S\u00fcsswaren",
    "sg:phone":"+41 22 360 13 74",
    "sg:postcode":"1264",
    "sg:province":"Vaud",
    "wof:name":"Hesse Rolf.",
    "wof:placetype":"venue"
},
  "geometry": {"coordinates":[6.157581,46.446419],"type":"Point"}
}