{
  "type": "Feature",
  "properties": {
    "iso:country":"CH",
    "sg:address":"Luggenackerstrasse 6",
    "sg:city":"Scherzingen",
    "sg:orig_category":"Non-Classified Establishments",
    "sg:postcode":"8596",
    "sg:province":"Thurgau",
    "wof:name":"Sp United Holding Ag",
    "wof:placetype":"venue"
},
  "geometry": {"coordinates":[9.2265520096,47.6321220398],"type":"Point"}
}