{
  "type": "Feature",
  "properties": {
    "iso:country":"CH",
    "sg:address":"Bleicherweg 10",
    "sg:city":"Z\u00fcrich",
    "sg:orig_category":"Detailhandel mit Damenbekleidung Herstellung von Strumpfwaren",
    "sg:phone":"+41 12012183",
    "sg:postcode":"8002",
    "sg:province":"Z\u00fcrich",
    "wof:name":"Fogal Ag",
    "wof:placetype":"venue"
},
  "geometry": {"coordinates":[8.5368833542,47.3685417175],"type":"Point"}
}