{
  "type": "Feature",
  "properties": {
    "iso:country":"CH",
    "sg:address":"Th\u00e9\u00e2tre Avenue Du 8",
    "sg:city":"Lausanne",
    "sg:orig_category":"Non-Classified Establishments",
    "sg:phone":"+41 13202911",
    "sg:postcode":"1005",
    "sg:province":"Vaud",
    "wof:name":"Si Du Pavillon Sa",
    "wof:placetype":"venue"
},
  "geometry": {"coordinates":[6.632335186,46.5195960999],"type":"Point"}
}