{
  "type": "Feature",
  "properties": {
    "iso:country":"CH",
    "sg:address":"Haldenweg 35",
    "sg:city":"Gelterkinden",
    "sg:orig_category":"Grosshandel mit Textilien",
    "sg:phone":"+41 61 274 16 90",
    "sg:postcode":"4460",
    "sg:province":"Basel-Landschaft",
    "wof:name":"T-shirt Factory Gmbh",
    "wof:placetype":"venue"
},
  "geometry": {"coordinates":[7.849960804,47.4679946899],"type":"Point"}
}