{
  "type": "Feature",
  "properties": {
    "addr:full":"Aegerten Rue D' 28 2500 Biel/bienne. Postfach Biel/bienne Bern 2500",
    "addr:housenumber":"28",
    "addr:postcode":"2500;postfach;2500",
    "addr:street":"Rue D '",
    "iso:country":"CH",
    "sg:address":"Aegerten Rue D' 28 2500 Biel/bienne. Postfach",
    "sg:city":"Biel/bienne",
    "sg:orig_category":"Datenverarbeitungsdienste",
    "sg:phone":"+41 32 365 16 57",
    "sg:postcode":"2500",
    "sg:province":"Bern",
    "wof:name":"Sigest Besan\u00e7on Florian D\u00e9veloppement De Logiciels",
    "wof:placetype":"venue"
},
  "geometry": {"coordinates":[7.252662,47.125404],"type":"Point"}
}