{
  "type": "Feature",
  "properties": {
    "addr:full":"Bernstr. 110 Rapperswil Bern 3255",
    "addr:housenumber":"110",
    "addr:postcode":"3255",
    "addr:street":"Rapperswil Bern",
    "iso:country":"CH",
    "sg:address":"Bernstr. 110",
    "sg:city":"Rapperswil",
    "sg:classifiers":[
        {
            "category":"Banks & Credit Unions",
            "subcategory":"Bank",
            "type":"Services"
        }
    ],
    "sg:phone":"+41 31 879 12 22",
    "sg:postcode":"3255",
    "sg:province":"Bern",
    "wof:name":"Berner Kantonalbank",
    "wof:placetype":"venue"
},
  "geometry": {"coordinates":[7.41534,47.058842],"type":"Point"}
}