{
  "type": "Feature",
  "properties": {
    "iso:country":"CH",
    "sg:address":"Z\u00fcrcherstrasse 191 8500 Frauenfeld. Postfach",
    "sg:city":"Frauenfeld",
    "sg:orig_category":"Detailhandel mit elektrischen Haushalts-,Radio U Fernsehger\u00e4ten sowie Musikinstrumenten Elektroinsta",
    "sg:phone":"+41 52 721 45 72",
    "sg:postcode":"8500",
    "sg:province":"Thurgau",
    "wof:name":"Radio Keiser, Marolf + Schefer Ag",
    "wof:placetype":"venue"
},
  "geometry": {"coordinates":[8.8990573883,47.5577468872],"type":"Point"}
}