{
  "type": "Feature",
  "properties": {
    "iso:country":"CH",
    "sg:address":"Rue Le-corbusier 20",
    "sg:city":"Gen\u00e8ve",
    "sg:orig_category":"Fahrschulen, Flugschulen",
    "sg:phone":"+41 79 413 06 00",
    "sg:postcode":"1208",
    "sg:province":"Gen\u00e8ve",
    "wof:name":"Elmar Stieger Autofahrschule",
    "wof:placetype":"venue"
},
  "geometry": {"coordinates":[9.5644330978,47.3204345703],"type":"Point"}
}