{
  "type": "Feature",
  "properties": {
    "iso:country":"CH",
    "sg:address":"Ch. Champ-colomb 13",
    "sg:city":"Ecublens",
    "sg:classifiers":[
        {
            "category":"Professional",
            "subcategory":"Advertising",
            "type":"Services"
        }
    ],
    "sg:phone":"+41 21 637 24 00",
    "sg:postcode":"1024",
    "sg:province":"Vaud",
    "sg:tags":[
        "display",
        "displays"
    ],
    "wof:name":"Afiro (ass.)",
    "wof:placetype":"venue"
},
  "geometry": {"coordinates":[6.5727257729,46.5379867554],"type":"Point"}
}