{
  "type": "Feature",
  "properties": {
    "iso:country":"CH",
    "sg:address":"Alte Dorfstrasse 65",
    "sg:city":"Herrliberg",
    "sg:orig_category":"Maler U Glasergewerbe Malerei",
    "sg:phone":"+41 19151147",
    "sg:postcode":"8704",
    "sg:province":"Z\u00fcrich",
    "wof:name":"Hintermann Ag",
    "wof:placetype":"venue"
},
  "geometry": {"coordinates":[8.6151018143,47.2863235474],"type":"Point"}
}