{
  "type": "Feature",
  "properties": {
    "iso:country":"CH",
    "sg:address":"1782",
    "sg:city":"Belfaux",
    "sg:orig_category":"Herstellung von Konstruktionsteilen, Fertigbauteilen U Ausbauelementen aus Holz",
    "sg:postcode":"1782",
    "sg:province":"Fribourg",
    "wof:name":"Tinguely G\u00e9rard.",
    "wof:placetype":"venue"
},
  "geometry": {"coordinates":[7.1060299873,46.8202896118],"type":"Point"}
}