{
  "type": "Feature",
  "properties": {
    "iso:country":"CH",
    "sg:address":"L\u00e4nggassstrasse 76",
    "sg:city":"Bern",
    "sg:orig_category":"Pensionskassen",
    "sg:phone":"+41 31 300 45 00",
    "sg:postcode":"3012",
    "sg:province":"Bern",
    "wof:name":"Personalvorsorge-stiftung Der Huber Hans Ag",
    "wof:placetype":"venue"
},
  "geometry": {"coordinates":[7.4277710915,46.9555702209],"type":"Point"}
}