{
  "type": "Feature",
  "properties": {
    "iso:country":"CH",
    "sg:address":"Pioppi Via Carrale Dei 27 6514 Sementina. Postfach",
    "sg:city":"Sementina",
    "sg:orig_category":"Unclassifiable Establishments",
    "sg:postcode":"6514",
    "sg:province":"Ticino",
    "wof:name":"Econ Star Sa Impianti Civili, Militari Ed Industriali Di Ristorazione; Progettaz., Realizzaz. Ecc",
    "wof:placetype":"venue"
},
  "geometry": {"coordinates":[8.9970397949,46.1790008545],"type":"Point"}
}