{
  "type": "Feature",
  "properties": {
    "iso:country":"CH",
    "sg:address":"Chemin Neuf 5",
    "sg:city":"Gen\u00e8ve",
    "sg:orig_category":"Architekturb\u00fcros",
    "sg:phone":"+41 22 786 47 66",
    "sg:postcode":"1207",
    "sg:province":"Gen\u00e8ve",
    "wof:name":"Jacques Sch\u00e4r Bureau D'architecture",
    "wof:placetype":"venue"
},
  "geometry": {"coordinates":[6.159468,46.202999],"type":"Point"}
}