{
  "type": "Feature",
  "properties": {
    "iso:country":"CH",
    "sg:address":"Rue Louis-bourguet 1",
    "sg:city":"Neuch\u00e2tel",
    "sg:orig_category":"Malerei Stukkateurgewerbe, Gipserei U Verputzerei",
    "sg:phone":"+41 32 721 47 63",
    "sg:postcode":"2000",
    "sg:province":"Neuch\u00e2tel",
    "wof:name":"Mario Rusconi Gypserie & Peinture",
    "wof:placetype":"venue"
},
  "geometry": {"coordinates":[6.9531707764,47.0037918091],"type":"Point"}
}