{
  "type": "Feature",
  "properties": {
    "iso:country":"CH",
    "sg:address":"8264",
    "sg:city":"Eschenz",
    "sg:orig_category":"Schulpflegen",
    "sg:phone":"+41 79 217 68 31",
    "sg:postcode":"8264",
    "sg:province":"Thurgau",
    "wof:name":"Primarschulkommission Der Gemeinde Eschlikon",
    "wof:placetype":"venue"
},
  "geometry": {"coordinates":[8.9705295563,47.4648590088],"type":"Point"}
}