{
  "type": "Feature",
  "properties": {
    "iso:country":"CH",
    "sg:address":"Bergstrasse 277",
    "sg:city":"Meilen",
    "sg:orig_category":"G\u00fcterbef\u00f6rderung im Strassenverkehr",
    "sg:phone":"+41 19231468",
    "sg:postcode":"8706",
    "sg:province":"Z\u00fcrich",
    "wof:name":"Blattmann Fredi + Kurt",
    "wof:placetype":"venue"
},
  "geometry": {"coordinates":[8.6665077209,47.2704811096],"type":"Point"}
}