{
  "type": "Feature",
  "properties": {
    "iso:country":"CH",
    "sg:address":"Soodstrasse 59",
    "sg:city":"Adliswil",
    "sg:orig_category":"Allgemeiner Hoch U Tiefbau",
    "sg:postcode":"8134",
    "sg:province":"Z\u00fcrich",
    "wof:name":"Albis Bau Und Sanierungs Ag Adliswil",
    "wof:placetype":"venue"
},
  "geometry": {"coordinates":[8.522394,47.319298],"type":"Point"}
}