{
  "type": "Feature",
  "properties": {
    "addr:full":"Via Besso 43 6900 Lugano. Postfach Casa Postale Lugano Ticino 6900",
    "addr:housenumber":"43",
    "addr:postcode":"6900;6900",
    "addr:street":"Via Besso;Postfach",
    "iso:country":"CH",
    "sg:address":"Via Besso 43 6900 Lugano. Postfach Casa Postale",
    "sg:city":"Lugano",
    "sg:orig_category":"Detailhandel mit B\u00fcchern, Zeitungen, Schreib U Papeteriewaren",
    "sg:postcode":"6900",
    "sg:province":"Ticino",
    "wof:name":"Redazioni Estate Di Maria Brughera Compra E Vendita Di Libri",
    "wof:placetype":"venue"
},
  "geometry": {"coordinates":[8.939359,46.009239],"type":"Point"}
}