{
  "type": "Feature",
  "properties": {
    "iso:country":"CH",
    "sg:address":"Effingerstrasse 37",
    "sg:city":"Bern",
    "sg:orig_category":"Herstellung von medizinischen U chirurgischen Ger\u00e4ten sowie orthop\u00e4dischen Vorrichtungen Herstellung",
    "sg:phone":"+41 31 382 31 83",
    "sg:postcode":"3000",
    "sg:province":"Bern",
    "wof:name":"Ortho-team Ag Orthop\u00e4die Und Rehatechnik",
    "wof:placetype":"venue"
},
  "geometry": {"coordinates":[7.4314341545,46.9458236694],"type":"Point"}
}