{
  "type": "Feature",
  "properties": {
    "iso:country":"CH",
    "sg:address":"Bahnhofstrasse 12",
    "sg:city":"Mellingen",
    "sg:orig_category":"Detailhandel mit Waren verschiedener Art, Hauptrichtung Nahrungsmittel",
    "sg:phone":"+41 56 491 13 15",
    "sg:postcode":"5507",
    "sg:province":"Aargau",
    "wof:name":"Hans Sieber Lebensmittel",
    "wof:placetype":"venue"
},
  "geometry": {"coordinates":[8.2742671967,47.4205589294],"type":"Point"}
}