{
  "type": "Feature",
  "properties": {
    "iso:country":"CH",
    "sg:address":"Dufourstrasse 26",
    "sg:city":"Aarau",
    "sg:orig_category":"Fussreflexzonenmassage",
    "sg:phone":"+41 71 223 58 32",
    "sg:postcode":"5000",
    "sg:province":"Aargau",
    "wof:name":"Marianne Weber Fussreflexzonen-massage",
    "wof:placetype":"venue"
},
  "geometry": {"coordinates":[9.3760004044,47.4212379456],"type":"Point"}
}