{
  "type": "Feature",
  "properties": {
    "iso:country":"CH",
    "sg:address":"Landskronstrasse 28 4053 Basel. Postfach 343",
    "sg:city":"Basel",
    "sg:orig_category":"Unclassifiable Establishments",
    "sg:phone":"+41 61 321 10 50",
    "sg:postcode":"4053",
    "sg:province":"Basel-Stadt",
    "wof:name":"M + S Mauerwerke Und Schalungen Ag",
    "wof:placetype":"venue"
},
  "geometry": {"coordinates":[7.5775790215,47.5688819885],"type":"Point"}
}