{
  "type": "Feature",
  "properties": {
    "iso:country":"CH",
    "sg:address":"Rue Ernest-sch\u00fcler 22 2500 Biel/bienne. Postfach",
    "sg:city":"Biel/bienne",
    "sg:orig_category":"RESTAURANTS: TEA-ROOMS",
    "sg:postcode":"2500",
    "sg:province":"Bern",
    "wof:name":"P\u00f6schtli Gmbh",
    "wof:placetype":"venue"
},
  "geometry": {"coordinates":[7.558839798,47.5137062073],"type":"Point"}
}