{
  "type": "Feature",
  "properties": {
    "iso:country":"CH",
    "sg:address":"Rue De La V\u00e9l\u00e9 12",
    "sg:city":"Court",
    "sg:orig_category":"Blumen U Zierpflanzenbau Landschaftsplanungsb\u00fcros U Gartenarchitekturb\u00fcros",
    "sg:phone":"+41 32 497 94 04",
    "sg:postcode":"2738",
    "sg:province":"Bern",
    "wof:name":"Buchser Fr\u00e9d\u00e9ric",
    "wof:placetype":"venue"
},
  "geometry": {"coordinates":[7.324708,47.241409],"type":"Point"}
}