{
  "type": "Feature",
  "properties": {
    "iso:country":"CH",
    "sg:address":"Dorfstrasse 39",
    "sg:city":"Ersigen",
    "sg:orig_category":"Unternehmensberatung",
    "sg:postcode":"3423",
    "sg:province":"Bern",
    "wof:name":"Kmoch Consulting",
    "wof:placetype":"venue"
},
  "geometry": {"coordinates":[7.5955200195,47.0938987732],"type":"Point"}
}