{
  "type": "Feature",
  "properties": {
    "addr:full":"Lavaterstr. 57 Z\u00fcrich Z\u00fcrich 8002",
    "addr:housenumber":"57",
    "addr:postcode":"8002",
    "addr:street":"Lavaterstr.",
    "iso:country":"CH",
    "sg:address":"Lavaterstr. 57",
    "sg:city":"Z\u00fcrich",
    "sg:classifiers":[
        {
            "category":"Manufacturing",
            "subcategory":"Chemicals & Compounds",
            "type":"Manufacturing & Wholesale Goods"
        }
    ],
    "sg:phone":"+41 4112016150",
    "sg:postcode":"8002",
    "sg:province":"Z\u00fcrich",
    "sg:tags":[
        "pharmaceutical",
        "chemistry"
    ],
    "wof:name":"Krebs & Co Ag",
    "wof:placetype":"venue"
},
  "geometry": {"coordinates":[8.532895,47.361729],"type":"Point"}
}