{
  "type": "Feature",
  "properties": {
    "iso:country":"CH",
    "sg:address":"Bruggerstrasse 67 5330 Zurzach. Postfach",
    "sg:city":"Zurzach",
    "sg:orig_category":"Schnelldruck U Kopierservice Sonstiges Druckgewerbe",
    "sg:phone":"+41 56 249 49 01",
    "sg:postcode":"5330",
    "sg:province":"Aargau",
    "wof:name":"Terra-copy Gmbh Dienstl., Bes. Im Bereich Herst. V. Kopien, Drucksachen",
    "wof:placetype":"venue"
},
  "geometry": {"coordinates":[8.2913532257,47.5831947327],"type":"Point"}
}