{
  "type": "Feature",
  "properties": {
    "iso:country":"CH",
    "sg:address":"Biberlinstrasse 8 8032 Z\u00fcrich. Postfach 186",
    "sg:city":"Z\u00fcrich",
    "sg:orig_category":"Grosshandel mit Nahrungsmitteln, Getr\u00e4nken U Tabakwaren Herstellung von homogenisierten U di\u00e4tetisch",
    "sg:phone":"+41 14222030",
    "sg:postcode":"8030",
    "wof:name":"Sanguisan Ag",
    "wof:placetype":"venue"
},
  "geometry": {"coordinates":[8.5690383911,47.3625526428],"type":"Point"}
}