{
  "type": "Feature",
  "properties": {
    "iso:country":"CH",
    "sg:address":"Gewerbering",
    "sg:city":"Schachen",
    "sg:classifiers":[
        {
            "category":"Banks & Credit Unions",
            "subcategory":"Investment Brokerage",
            "type":"Services"
        }
    ],
    "sg:phone":"+41 41 499 70 40",
    "sg:postcode":"6105",
    "sg:province":"Luzern",
    "sg:tags":[
        "switch",
        "float"
    ],
    "wof:name":"Reed Electronics Ag",
    "wof:placetype":"venue"
},
  "geometry": {"coordinates":[8.1402702332,47.0386657715],"type":"Point"}
}