{
  "type": "Feature",
  "properties": {
    "iso:country":"CH",
    "sg:address":"1564",
    "sg:city":"Domdidier",
    "sg:orig_category":"Wirtschaftspr\u00fcfung, Steuerberatung U Treuhand",
    "sg:phone":"+41 22 321 08 09",
    "sg:postcode":"1564",
    "sg:province":"Fribourg",
    "wof:name":"Fiducap Soci\u00e9t\u00e9 Fiduciaire Sa",
    "wof:placetype":"venue"
},
  "geometry": {"coordinates":[6.1397452354,46.2012138367],"type":"Point"}
}