{
  "type": "Feature",
  "properties": {
    "iso:country":"CH",
    "sg:address":"Samstagernstrasse 83",
    "sg:city":"Wollerau",
    "sg:orig_category":"Detailhandel mit Milcherzeugnissen U Eiern Verarbeitung von Milch",
    "sg:phone":"+41 71 633 15 33",
    "sg:postcode":"8832",
    "sg:province":"Schwyz",
    "wof:name":"Swiss Dairy Food Ag Weichk\u00e4serei B\u00fcrglen",
    "wof:placetype":"venue"
},
  "geometry": {"coordinates":[9.1479263306,47.5491828918],"type":"Point"}
}