{
  "type": "Feature",
  "properties": {
    "iso:country":"CH",
    "sg:address":"Nutenwil 9602 Bazenheid. Postfach",
    "sg:city":"Bazenheid",
    "sg:orig_category":"Verwertung von Milch",
    "sg:postcode":"9602",
    "sg:province":"St. Gallen",
    "wof:name":"Thalmann Herbert",
    "wof:placetype":"venue"
},
  "geometry": {"coordinates":[9.053440094,47.4077033997],"type":"Point"}
}