{
  "type": "Feature",
  "properties": {
    "iso:country":"CH",
    "sg:address":"Hohenrainring 21 4133 Pratteln. Postfach",
    "sg:city":"Pratteln",
    "sg:classifiers":[
        {
            "category":"Professional",
            "subcategory":"Employment Agencies",
            "type":"Services"
        }
    ],
    "sg:postcode":"4133",
    "sg:province":"Basel-Landschaft",
    "sg:tags":[
        "personal",
        "u",
        "stellenvermittlung"
    ],
    "wof:name":"Diesl Consulting",
    "wof:placetype":"venue"
},
  "geometry": {"coordinates":[9.3810987473,47.4334907532],"type":"Point"}
}