{
  "type": "Feature",
  "properties": {
    "iso:country":"CH",
    "sg:address":"Unterriedenstrasse 29",
    "sg:city":"Gebenstorf",
    "sg:orig_category":"Wirtschaftspr\u00fcfung, Steuerberatung U Treuhand",
    "sg:postcode":"5412",
    "sg:province":"Aargau",
    "wof:name":"Revicoma Ag \u00dcbernahme U. Besorgung Aller Auftr\u00e4ge, Die Zum T\u00e4tigkeitsbereich Einer Kontroll- U. Revisionsstelle Geh\u00f6ren. Edv-beratung Usw",
    "wof:placetype":"venue"
},
  "geometry": {"coordinates":[9.3952035904,47.3884010315],"type":"Point"}
}