{
  "type": "Feature",
  "properties": {
    "iso:country":"CH",
    "sg:address":"Steinbruchstrasse 2 7000 Chur. Postfach",
    "sg:city":"Chur",
    "sg:classifiers":[
        {
            "category":"Restaurant",
            "type":"Food & Drink"
        }
    ],
    "sg:phone":"+41 27 455 12 91",
    "sg:postcode":"7002",
    "sg:province":"Graubunden",
    "wof:name":"Restaurant Contr\u00e9e",
    "wof:placetype":"venue"
},
  "geometry": {"coordinates":[7.5277199745,46.2974700928],"type":"Point"}
}