{
  "type": "Feature",
  "properties": {
    "iso:country":"CH",
    "sg:address":"Im Wiesengrund 20",
    "sg:city":"Wallisellen",
    "sg:orig_category":"Hoch U Tiefbau",
    "sg:phone":"+41 18303021",
    "sg:postcode":"8304",
    "sg:province":"Z\u00fcrich",
    "wof:name":"Eduard Gasser Baugesch\u00e4ft",
    "wof:placetype":"venue"
},
  "geometry": {"coordinates":[8.597369194,47.4144744873],"type":"Point"}
}