{
  "type": "Feature",
  "properties": {
    "iso:country":"CH",
    "sg:address":"Rheinstrasse 53",
    "sg:city":"Chur",
    "sg:orig_category":"Verwaltung von Immobilien",
    "sg:postcode":"7000",
    "sg:province":"Graubunden",
    "wof:name":"Knightsbridge Immobilien Ag",
    "wof:placetype":"venue"
},
  "geometry": {"coordinates":[9.5222702026,46.8543281555],"type":"Point"}
}