{
  "type": "Feature",
  "properties": {
    "iso:country":"CH",
    "sg:address":"Dufourstrasse 27",
    "sg:city":"Z\u00fcrich",
    "sg:orig_category":"Direktwerbeagenturen Werbeagenturen",
    "sg:phone":"+41 12596458",
    "sg:postcode":"8008",
    "sg:province":"Z\u00fcrich",
    "wof:name":"Ringier Direct",
    "wof:placetype":"venue"
},
  "geometry": {"coordinates":[8.5479640961,47.3637657166],"type":"Point"}
}