{
  "type": "Feature",
  "properties": {
    "iso:country":"CH",
    "sg:address":"Riedgasse 5 4912 Aarwangen. Postfach",
    "sg:city":"Aarwangen",
    "sg:orig_category":"Landwirtschaftliche Genossenschaften",
    "sg:phone":"+41 71 977 15 91",
    "sg:postcode":"4912",
    "sg:province":"Bern",
    "wof:name":"Landw.genossenschaft Au",
    "wof:placetype":"venue"
},
  "geometry": {"coordinates":[8.9690742493,47.4147911072],"type":"Point"}
}