{
  "type": "Feature",
  "properties": {
    "iso:country":"CH",
    "sg:address":"8807 Freienbach. Postfach",
    "sg:city":"Freienbach",
    "sg:orig_category":"Sportvereine Ballsport Fussball Vereine Damen",
    "sg:phone":"+41 17844168",
    "sg:postcode":"8807",
    "sg:province":"Schwyz",
    "wof:name":"Fc Freienbach Abt.damen",
    "wof:placetype":"venue"
},
  "geometry": {"coordinates":[8.7595396042,47.2016296387],"type":"Point"}
}