{
  "type": "Feature",
  "properties": {
    "iso:country":"CH",
    "sg:address":"Allmeindstrasse 17",
    "sg:city":"Einsiedeln",
    "sg:orig_category":"Non-Classified Establishments",
    "sg:postcode":"8840",
    "sg:province":"Schwyz",
    "wof:name":"Askaro Alberti + Spiess",
    "wof:placetype":"venue"
},
  "geometry": {"coordinates":[141.7017364502,39.0775184631],"type":"Point"}
}