{
  "type": "Feature",
  "properties": {
    "iso:country":"CH",
    "sg:address":"Montelly",
    "sg:city":"Perroy",
    "sg:orig_category":"Obstbau",
    "sg:phone":"+41 21 825 16 92",
    "sg:postcode":"1166",
    "sg:province":"Vaud",
    "wof:name":"Jean-pierre Gallay Cultures Fruiti\u00e8res",
    "wof:placetype":"venue"
},
  "geometry": {"coordinates":[6.3564929962,46.4673118591],"type":"Point"}
}