{
  "type": "Feature",
  "properties": {
    "iso:country":"CH",
    "sg:address":"6331 H\u00fcnenberg. Postfach 914",
    "sg:city":"H\u00fcnenberg",
    "sg:orig_category":"Sportvereine Sch\u00fctzen",
    "sg:postcode":"6331",
    "sg:province":"Zug",
    "wof:name":"Sch\u00fctzengesellschaft H\u00fcnenberg Sgh",
    "wof:placetype":"venue"
},
  "geometry": {"coordinates":[8.427069664,47.1758384705],"type":"Point"}
}