{
  "type": "Feature",
  "properties": {
    "iso:country":"CH",
    "sg:address":"Sch\u00f6neggstrasse 3",
    "sg:city":"Dietikon",
    "sg:orig_category":"Ingenieurb\u00fcros Umwelttechnik and \u00d6kologie",
    "sg:phone":"+41 17404378",
    "sg:postcode":"8953",
    "sg:province":"Z\u00fcrich",
    "wof:name":"Umweltberatung Gilbert",
    "wof:placetype":"venue"
},
  "geometry": {"coordinates":[8.4015216827,47.4024848938],"type":"Point"}
}