{
  "type": "Feature",
  "properties": {
    "iso:country":"CH",
    "sg:address":"Ruchweid 24",
    "sg:city":"Oberlunkhofen",
    "sg:orig_category":"Sportvereine",
    "sg:phone":"+41 56 634 16 63",
    "sg:postcode":"8917",
    "sg:province":"Aargau",
    "wof:name":"Altersturnen Arni",
    "wof:placetype":"venue"
},
  "geometry": {"coordinates":[8.4010801315,47.3124847412],"type":"Point"}
}