{
  "type": "Feature",
  "properties": {
    "iso:country":"CH",
    "sg:address":"Route De Saint-cergue 303",
    "sg:city":"Nyon",
    "sg:orig_category":"Sonstige pers\u00f6nliche Dienstleistungen",
    "sg:postcode":"1260",
    "sg:province":"Vaud",
    "wof:name":"Kites Kemp & Co International Transfers & Entertainment Services",
    "wof:placetype":"venue"
},
  "geometry": {"coordinates":[6.2258281708,46.3964614868],"type":"Point"}
}