{
  "type": "Feature",
  "properties": {
    "iso:country":"CH",
    "sg:address":"Plaz",
    "sg:city":"Sent",
    "sg:orig_category":"Interessenvertretungen",
    "sg:phone":"+41 81 864 92 04",
    "sg:postcode":"7554",
    "sg:province":"Graubunden",
    "wof:name":"Sgabuz",
    "wof:placetype":"venue"
},
  "geometry": {"coordinates":[10.3381700516,46.8173599243],"type":"Point"}
}