{
  "type": "Feature",
  "properties": {
    "iso:country":"CH",
    "sg:address":"Weiacherstrasse 4",
    "sg:city":"Rorbas",
    "sg:orig_category":"Bauspenglerei Sanit\u00e4rinstallation U Spenglerei",
    "sg:phone":"+41 18650383",
    "sg:postcode":"8427",
    "sg:province":"Z\u00fcrich",
    "wof:name":"Karl Meier Spenglerei",
    "wof:placetype":"venue"
},
  "geometry": {"coordinates":[8.578888,47.525852],"type":"Point"}
}