{
  "type": "Feature",
  "properties": {
    "iso:country":"CH",
    "sg:address":"Hinterbissaustr. 28 Postfach 44",
    "sg:city":"Heiden",
    "sg:classifiers":[
        {
            "category":"Manufacturing",
            "subcategory":"Printing",
            "type":"Manufacturing & Wholesale Goods"
        }
    ],
    "sg:phone":"+41 56 622 80 00",
    "sg:postcode":"9410",
    "sg:province":"Appenzell Ausserrhoden",
    "sg:tags":[
        "publishing"
    ],
    "wof:name":"Hutter Siebdruck Ag",
    "wof:placetype":"venue"
},
  "geometry": {"coordinates":[8.2700939178,47.3547363281],"type":"Point"}
}