{
  "type": "Feature",
  "properties": {
    "addr:full":"Berntorstrasse 16 Solothurn Solothurn 4500",
    "addr:housenumber":"16",
    "addr:postcode":"4500",
    "addr:street":"Berntorstrasse",
    "iso:country":"CH",
    "sg:address":"Berntorstrasse 16",
    "sg:city":"Solothurn",
    "sg:classifiers":[
        {
            "category":"Bars & Pubs",
            "type":"Food & Drink"
        }
    ],
    "sg:phone":"+41 32 622 40 10",
    "sg:postcode":"4500",
    "sg:province":"Solothurn",
    "wof:name":"Capitol Barock Caf\u00e9",
    "wof:placetype":"venue"
},
  "geometry": {"coordinates":[7.536413,47.204498],"type":"Point"}
}