{
  "type": "Feature",
  "properties": {
    "iso:country":"CH",
    "sg:address":"Huebwiesenstrasse 22",
    "sg:city":"Geroldswil",
    "sg:orig_category":"Unclassifiable Establishments",
    "sg:phone":"+41 17482752",
    "sg:postcode":"8954",
    "sg:province":"Z\u00fcrich",
    "wof:name":"Videostudio Aravideo R\u00e4ss Albert",
    "wof:placetype":"venue"
},
  "geometry": {"coordinates":[8.4122476578,47.4210090637],"type":"Point"}
}