{
  "type": "Feature",
  "properties": {
    "iso:country":"CH",
    "sg:address":"Valle Via Ponte Di 7",
    "sg:city":"Davesco-soragno",
    "sg:orig_category":"Grosshandel mit Holz U Baustoffen",
    "sg:phone":"+41 91 994 44 33",
    "sg:postcode":"6964",
    "sg:province":"Ticino",
    "wof:name":"Geo-polieco Sa",
    "wof:placetype":"venue"
},
  "geometry": {"coordinates":[8.9895296097,46.0325584412],"type":"Point"}
}