{
  "type": "Feature",
  "properties": {
    "iso:country":"CH",
    "sg:address":"Br\u00fcttelengasse 40",
    "sg:city":"Ins",
    "sg:orig_category":"S\u00e4gewerke",
    "sg:phone":"+41 32 313 14 25",
    "sg:postcode":"3232",
    "sg:province":"Bern",
    "wof:name":"Rudolf Jenni S\u00e4gerei",
    "wof:placetype":"venue"
},
  "geometry": {"coordinates":[7.1084470749,47.0101585388],"type":"Point"}
}