{
  "type": "Feature",
  "properties": {
    "iso:country":"CH",
    "sg:address":"Rue Verdaine 7",
    "sg:city":"Gen\u00e8ve",
    "sg:orig_category":"Detailhandel mit Damenbekleidung Herstellung von Oberbekleidung",
    "sg:phone":"+41 22 311 60 80",
    "sg:postcode":"1204",
    "sg:province":"Gen\u00e8ve",
    "wof:name":"Hirzel Paul Et Ren\u00e9e",
    "wof:placetype":"venue"
},
  "geometry": {"coordinates":[6.1506109238,46.2015113831],"type":"Point"}
}