{
  "type": "Feature",
  "properties": {
    "iso:country":"CH",
    "sg:address":"Im H\u00e4feler 6a",
    "sg:city":"Frauenfeld",
    "sg:orig_category":"Mit Sport verbundene T\u00e4tigkeiten",
    "sg:phone":"+41 52 720 71 93",
    "sg:postcode":"8500",
    "sg:province":"Thurgau",
    "wof:name":"Reitschule Maiholz",
    "wof:placetype":"venue"
},
  "geometry": {"coordinates":[8.8802814484,47.5653152466],"type":"Point"}
}