{
  "type": "Feature",
  "properties": {
    "iso:country":"CH",
    "sg:address":"Grand Rue 2b",
    "sg:city":"Montreux",
    "sg:orig_category":"Detailhandel mit Schuhen",
    "sg:phone":"+41 21 961 27 78",
    "sg:postcode":"1820",
    "sg:province":"Vaud",
    "wof:name":"Boutique Florence Jean-paul Ch\u00e2telain",
    "wof:placetype":"venue"
},
  "geometry": {"coordinates":[6.910736084,46.4315681458],"type":"Point"}
}