{
  "type": "Feature",
  "properties": {
    "iso:country":"CH",
    "sg:address":"Buchenweg 2",
    "sg:city":"Benzenschwil",
    "sg:orig_category":"Herstellung von Konstruktionsteilen, Fertigbauteilen U Ausbauelementen aus Holz",
    "sg:phone":"+41 56 668 21 10",
    "sg:postcode":"5636",
    "sg:province":"Aargau",
    "wof:name":"Bauschreinerei Thaler G. & Sohn",
    "wof:placetype":"venue"
},
  "geometry": {"coordinates":[8.3675136566,47.2474861145],"type":"Point"}
}