{
  "type": "Feature",
  "properties": {
    "iso:country":"CH",
    "sg:address":"Bodenackerstrasse 52",
    "sg:city":"Otelfingen",
    "sg:orig_category":"Vereine Gesang",
    "sg:phone":"+41 17381050",
    "sg:postcode":"8112",
    "sg:province":"Z\u00fcrich",
    "wof:name":"M\u00e4nnerchor Otelfingen",
    "wof:placetype":"venue"
},
  "geometry": {"coordinates":[8.3930778503,47.4604263306],"type":"Point"}
}