{
  "type": "Feature",
  "properties": {
    "iso:country":"CH",
    "sg:address":"Via Della Posta 6",
    "sg:city":"Gordevio",
    "sg:orig_category":"Nationale Postdienste",
    "sg:phone":"+41 91 753 11 52",
    "sg:postcode":"6672",
    "sg:province":"Ticino",
    "wof:name":"La Posta Svizzera",
    "wof:placetype":"venue"
},
  "geometry": {"coordinates":[8.7437801361,46.2255134583],"type":"Point"}
}