{
  "type": "Feature",
  "properties": {
    "iso:country":"CH",
    "sg:address":"Weideliguet 24",
    "sg:city":"Bottighofen",
    "sg:orig_category":"Hardwareberatung",
    "sg:phone":"+41 79 636 20 50",
    "sg:postcode":"8598",
    "sg:province":"Thurgau",
    "wof:name":"Cecchin Informatik",
    "wof:placetype":"venue"
},
  "geometry": {"coordinates":[9.2064418793,47.6425590515],"type":"Point"}
}