{
  "type": "Feature",
  "properties": {
    "iso:country":"CH",
    "sg:address":"5275",
    "sg:city":"Etzgen",
    "sg:orig_category":"Pensionskassen",
    "sg:phone":"+41 62 875 11 21",
    "sg:postcode":"5275",
    "sg:province":"Aargau",
    "wof:name":"Personalf\u00fcrsorgestiftung Der Cesare Perlini Ag Etzgen",
    "wof:placetype":"venue"
},
  "geometry": {"coordinates":[8.115240097,47.5717582703],"type":"Point"}
}