{
  "type": "Feature",
  "properties": {
    "iso:country":"CH",
    "sg:address":"Via Trevano 49",
    "sg:city":"Lugano",
    "sg:orig_category":"Advokaturb\u00fcros Notariate",
    "sg:phone":"+41 91 943 20 65",
    "sg:postcode":"6900",
    "sg:province":"Ticino",
    "wof:name":"Giovanni Colombo Studio Legale & Notarile",
    "wof:placetype":"venue"
},
  "geometry": {"coordinates":[8.955908,46.016945],"type":"Point"}
}