{
  "type": "Feature",
  "properties": {
    "iso:country":"CH",
    "sg:address":"Lindenweg 17",
    "sg:city":"Pfaffhausen",
    "sg:orig_category":"Rechtsberatung Wirtschaftspr\u00fcfung, Steuerberatung U Treuhand",
    "sg:phone":"+41 18261991",
    "sg:postcode":"8118",
    "sg:province":"Z\u00fcrich",
    "wof:name":"Beerli Irina, Beratung Treuhand Uebersetzungen",
    "wof:placetype":"venue"
},
  "geometry": {"coordinates":[8.6264572144,47.3683586121],"type":"Point"}
}