{
  "type": "Feature",
  "properties": {
    "iso:country":"CH",
    "sg:address":"Rheinstrasse 24",
    "sg:city":"F\u00fcllinsdorf",
    "sg:orig_category":"Detailhandel mit M\u00f6beln Gartenbau",
    "sg:phone":"+41 61 811 65 82",
    "sg:postcode":"4414",
    "sg:province":"Basel-Landschaft",
    "wof:name":"Daniel Krumm Holz Im Garten/gartenm\u00f6bel",
    "wof:placetype":"venue"
},
  "geometry": {"coordinates":[7.721529007,47.5053367615],"type":"Point"}
}