{
  "type": "Feature",
  "properties": {
    "iso:country":"CH",
    "sg:address":"Georges Route De Saint- 47 1212 Grand-lancy. Postfach",
    "sg:city":"Gen\u00e8ve",
    "sg:orig_category":"Pensionskassen",
    "sg:postcode":"1202",
    "sg:province":"Gen\u00e8ve",
    "wof:name":"Fondation En Faveur Du Personnel Des Soci\u00e9t\u00e9s Sa Ancienne Fabrique Piaget Georges & Cie Et Complications Sa",
    "wof:placetype":"venue"
},
  "geometry": {"coordinates":[6.4908499718,46.8687477112],"type":"Point"}
}