{
  "type": "Feature",
  "properties": {
    "iso:country":"CH",
    "sg:address":"Alpenquai 14/12",
    "sg:city":"Luzern",
    "sg:orig_category":"Hochschulen U h\u00f6here Ausbildung",
    "sg:postcode":"6005",
    "sg:province":"Luzern",
    "wof:name":"System Balance Gmbh",
    "wof:placetype":"venue"
},
  "geometry": {"coordinates":[8.3176755905,47.0465354919],"type":"Point"}
}