{
  "type": "Feature",
  "properties": {
    "iso:country":"CH",
    "sg:address":"Rue De Grimisuat 8",
    "sg:city":"Martigny",
    "sg:orig_category":"Kantinen",
    "sg:phone":"+41 27 723 36 88",
    "sg:postcode":"1920",
    "sg:province":"Valais",
    "wof:name":"Woltz St\u00e9phane Et B\u00e9n\u00e9dicte",
    "wof:placetype":"venue"
},
  "geometry": {"coordinates":[7.0850849152,46.104434967],"type":"Point"}
}