{
  "type": "Feature",
  "properties": {
    "iso:country":"CH",
    "sg:address":"Weingasse 10",
    "sg:city":"Villmergen",
    "sg:orig_category":"Elektroinstallation",
    "sg:phone":"+41 26 652 36 46",
    "sg:postcode":"5612",
    "sg:province":"Aargau",
    "wof:name":"Electro-tel Sa",
    "wof:placetype":"venue"
},
  "geometry": {"coordinates":[6.9096050262,46.6983528137],"type":"Point"}
}