{
  "type": "Feature",
  "properties": {
    "iso:country":"CH",
    "sg:address":"Spitalstrasse 12",
    "sg:city":"Grabs",
    "sg:orig_category":"Detailhandel mit Getr\u00e4nken Grosshandel mit Getr\u00e4nken",
    "sg:phone":"+41 81 771 30 54",
    "sg:postcode":"9472",
    "sg:province":"St. Gallen",
    "wof:name":"Getr\u00e4nke Baumgartner Markus",
    "wof:placetype":"venue"
},
  "geometry": {"coordinates":[9.4443340302,47.1801986694],"type":"Point"}
}