{
  "type": "Feature",
  "properties": {
    "iso:country":"CH",
    "sg:address":"Hauptstrasse 19",
    "sg:city":"Magden",
    "sg:orig_category":"Detailhandel mit Fleisch U Fleischwaren Grosshandel mit lebenden Tieren",
    "sg:phone":"+41 61 841 11 29",
    "sg:postcode":"4312",
    "sg:province":"Aargau",
    "wof:name":"Tschannen Ag",
    "wof:placetype":"venue"
},
  "geometry": {"coordinates":[7.8130168915,47.5271034241],"type":"Point"}
}