{
  "type": "Feature",
  "properties": {
    "iso:country":"CH",
    "sg:address":"Wiesenstrasse 1",
    "sg:city":"Z\u00fcrich",
    "sg:orig_category":"Herstellung von Elektrizit\u00e4tsverteilungs U schalteinrichtungen",
    "sg:phone":"+41 14225100",
    "sg:postcode":"8008",
    "sg:province":"Z\u00fcrich",
    "wof:name":"Flight Test Consultants Ag",
    "wof:placetype":"venue"
},
  "geometry": {"coordinates":[8.5508918762,47.3620529175],"type":"Point"}
}