{
  "type": "Feature",
  "properties": {
    "iso:country":"CH",
    "sg:address":"4665 Oftringen. Postfach",
    "sg:city":"Oftringen",
    "sg:orig_category":"Pensionskassen",
    "sg:postcode":"4665",
    "sg:province":"Aargau",
    "wof:name":"Personalf\u00fcrsorgestiftung Der Heinz Senn Ag Oftringen",
    "wof:placetype":"venue"
},
  "geometry": {"coordinates":[7.9209251404,47.3165397644],"type":"Point"}
}