{
  "type": "Feature",
  "properties": {
    "iso:country":"CH",
    "sg:address":"Chipf 10",
    "sg:city":"Oberburg",
    "sg:orig_category":"Herstellung von Werkzeugen",
    "sg:phone":"+41 16871551",
    "sg:postcode":"3414",
    "sg:province":"Bern",
    "wof:name":"Feusi + Spadaro Vorrichtungen Und Werkzeugbau",
    "wof:placetype":"venue"
},
  "geometry": {"coordinates":[8.7341480255,47.1973953247],"type":"Point"}
}