{
  "type": "Feature",
  "properties": {
    "addr:full":"Castaletweg 1 Igis Graubunden 7206",
    "addr:housenumber":"1",
    "addr:postcode":"7206",
    "addr:street":"Castaletweg",
    "iso:country":"CH",
    "sg:address":"Castaletweg 1",
    "sg:city":"Igis",
    "sg:orig_category":"Arztpraxen",
    "sg:phone":"+41 81 322 50 30",
    "sg:postcode":"7206",
    "sg:province":"Graubunden",
    "wof:name":"Dr.med.hans B\u00f6sch Arzt F\u00fcr Allgemeine Medizin",
    "wof:placetype":"venue"
},
  "geometry": {"coordinates":[9.568365,46.947647],"type":"Point"}
}