{
  "type": "Feature",
  "properties": {
    "iso:country":"CH",
    "sg:address":"Stadtgartenweg 10 7000 Chur. Postfach",
    "sg:city":"Chur",
    "sg:orig_category":"Finanzierungsinstitutionen",
    "sg:phone":"+41 81 256 93 34",
    "sg:postcode":"7000",
    "sg:province":"Graubunden",
    "wof:name":"Landwirtschaftliche Kreditgenossenschaft Graub\u00fcnden",
    "wof:placetype":"venue"
},
  "geometry": {"coordinates":[9.5296611786,46.8502540588],"type":"Point"}
}