{
  "type": "Feature",
  "properties": {
    "iso:country":"CH",
    "sg:address":"M\u00fclhauserstrasse 30 4056 Basel. Postfach",
    "sg:city":"Basel",
    "sg:orig_category":"Detailhandel mit M\u00f6beln U Haushaltsgegenst\u00e4nden Innendekorationsateliers",
    "sg:phone":"+41 61 321 47 47",
    "sg:postcode":"4013",
    "sg:province":"Basel-Stadt",
    "wof:name":"Gardina Ag",
    "wof:placetype":"venue"
},
  "geometry": {"coordinates":[7.581510067,47.5692710876],"type":"Point"}
}