{
  "type": "Feature",
  "properties": {
    "iso:country":"CH",
    "sg:address":"Seestrasse 89",
    "sg:city":"Horn",
    "sg:orig_category":"Non-Classified Establishments",
    "sg:postcode":"9326",
    "sg:province":"Thurgau",
    "wof:name":"Haga Vertriebs Gmbh",
    "wof:placetype":"venue"
},
  "geometry": {"coordinates":[9.4620742798,47.4959030151],"type":"Point"}
}