{
  "type": "Feature",
  "properties": {
    "iso:country":"CH",
    "sg:address":"H\u00fcrdweg 10",
    "sg:city":"Galgenen",
    "sg:orig_category":"Herstellung von Seifen, Wasch U Reinigungsmitteln",
    "sg:phone":"+41 56 618 80 00",
    "sg:postcode":"8854",
    "sg:province":"Schwyz",
    "wof:name":"Sole.ch Gmbh Artikel D. K\u00f6rper- U. Haushaltpflege Pfanzlicher Herkunft Usw.; Handel",
    "wof:placetype":"venue"
},
  "geometry": {"coordinates":[8.2758016586,47.3540153503],"type":"Point"}
}