{
  "type": "Feature",
  "properties": {
    "iso:country":"CH",
    "sg:address":"Gewerbezentrum Egelsee",
    "sg:city":"Kaltenbach",
    "sg:orig_category":"Grosshandel mit sonstigen Halbwaren Herstellung von Verpackungen aus Kunststoff",
    "sg:phone":"+41 56 664 41 51",
    "sg:postcode":"8259",
    "sg:province":"Thurgau",
    "wof:name":"Fps Kunststoff-verpackungen Ag",
    "wof:placetype":"venue"
},
  "geometry": {"coordinates":[8.3174819946,47.2825775146],"type":"Point"}
}