{
  "type": "Feature",
  "properties": {
    "iso:country":"CH",
    "sg:address":"Im Rietacker 14 9494 Schaan. Postfach 135",
    "sg:city":"Schaan",
    "sg:orig_category":"Bauspenglerei Dachdeckerei",
    "sg:phone":"+423 232 45 73",
    "sg:postcode":"9494",
    "wof:name":"Eberle Ag Spenglerei Flachbedachungen Blitzschutz",
    "wof:placetype":"venue"
},
  "geometry": {"coordinates":[9.510331,47.175251],"type":"Point"}
}