{
  "type": "Feature",
  "properties": {
    "iso:country":"CH",
    "sg:address":"R\u00f6hrliberg 4",
    "sg:city":"Cham",
    "sg:orig_category":"Unternehmensberatung",
    "sg:phone":"+41 41 780 77 93",
    "sg:postcode":"6330",
    "sg:province":"Zug",
    "wof:name":"Hrt Unternehmensberatung, Dr. E. Wullschleger",
    "wof:placetype":"venue"
},
  "geometry": {"coordinates":[8.4546079636,47.1848983765],"type":"Point"}
}