{
  "type": "Feature",
  "properties": {
    "iso:country":"CH",
    "sg:address":"Rathausgasse 4 8180 B\u00fclach. Postfach",
    "sg:city":"B\u00fclach",
    "sg:orig_category":"Sonstige Institutionen des Sozialwesens ohne Beherbergung",
    "sg:phone":"+41 548957",
    "sg:postcode":"8180",
    "sg:province":"Z\u00fcrich",
    "wof:name":"M\u00fctterberatung Des Bezirks Pf\u00e4ffikon",
    "wof:placetype":"venue"
},
  "geometry": {"coordinates":[8.7831945419,47.3666534424],"type":"Point"}
}