{
  "type": "Feature",
  "properties": {
    "addr:full":"Place Du March\u00e9 2 Nyon Vaud 1260",
    "addr:housenumber":"2",
    "addr:postcode":"1260",
    "addr:street":"Place Du Marche\u0301",
    "iso:country":"CH",
    "sg:address":"Place Du March\u00e9 2",
    "sg:city":"Nyon",
    "sg:orig_category":"Bauingenieurb\u00fcros allgemein",
    "sg:phone":"+41 22 361 20 61",
    "sg:postcode":"1260",
    "sg:province":"Vaud",
    "wof:name":"Cevey & Grossenbacher Bureau D'ingenieurs",
    "wof:placetype":"venue"
},
  "geometry": {"coordinates":[6.23869,46.381927],"type":"Point"}
}