{
  "type": "Feature",
  "properties": {
    "iso:country":"CH",
    "sg:address":"Rue Du Moulinet 39",
    "sg:city":"Orbe",
    "sg:orig_category":"Mechanische Werkst\u00e4tten",
    "sg:phone":"+41 21 625 32 05",
    "sg:postcode":"1350",
    "sg:province":"Vaud",
    "wof:name":"Julien Cherubini M\u00e9canique De Pr\u00e9cision",
    "wof:placetype":"venue"
},
  "geometry": {"coordinates":[6.5327858925,46.7207145691],"type":"Point"}
}