{
  "type": "Feature",
  "properties": {
    "iso:country":"CH",
    "sg:address":"Hauptstrasse 81",
    "sg:city":"Buckten",
    "sg:orig_category":"Instandhaltung U Reparatur von Automobilen",
    "sg:phone":"+41 62 299 16 39",
    "sg:postcode":"4446",
    "sg:province":"Basel-Landschaft",
    "wof:name":"Garage Salfinger",
    "wof:placetype":"venue"
},
  "geometry": {"coordinates":[7.845252037,47.4077301025],"type":"Point"}
}