{
  "type": "Feature",
  "properties": {
    "addr:full":"Steindlerstrasse 60 Unterseen Bern 3800",
    "addr:housenumber":"60",
    "addr:postcode":"3800",
    "addr:street":"Steindlerstrasse",
    "iso:country":"CH",
    "sg:address":"Steindlerstrasse 60",
    "sg:city":"Unterseen",
    "sg:orig_category":"Campingpl\u00e4tze Detailhandel mit Zeitungen U Zeitschriften Kioske",
    "sg:phone":"+41 33 822 44 14",
    "sg:postcode":"3800",
    "sg:province":"Bern",
    "wof:name":"Campingplatz Jungfraublick 7",
    "wof:placetype":"venue"
},
  "geometry": {"coordinates":[7.866433,46.673466],"type":"Point"}
}