{
  "type": "Feature",
  "properties": {
    "iso:country":"CH",
    "sg:address":"Piazza Collegiata 9",
    "sg:city":"Bellinzona",
    "sg:orig_category":"Versicherungen Generalagenturen",
    "sg:phone":"+41 91 822 00 50",
    "sg:postcode":"6500",
    "sg:province":"Ticino",
    "wof:name":"Vodese Assicurazioni Agenzia Generale",
    "wof:placetype":"venue"
},
  "geometry": {"coordinates":[9.0231609344,46.1916923523],"type":"Point"}
}