{
  "type": "Feature",
  "properties": {
    "iso:country":"CH",
    "sg:address":"Grand'rue 10",
    "sg:city":"St-blaise",
    "sg:orig_category":"RESTAURANTS: TEA-ROOMS",
    "sg:phone":"+41 27 722 81 64",
    "sg:postcode":"2072",
    "sg:province":"Neuch\u00e2tel",
    "wof:name":"Vuilleumier Urs",
    "wof:placetype":"venue"
},
  "geometry": {"coordinates":[7.1693601608,46.0871124268],"type":"Point"}
}