{
  "type": "Feature",
  "properties": {
    "iso:country":"CH",
    "sg:address":"Dattenmattstrasse 11",
    "sg:city":"Kriens",
    "sg:orig_category":"Autospenglereien",
    "sg:phone":"+41 41 340 85 82",
    "sg:postcode":"6010",
    "sg:province":"Luzern",
    "wof:name":"Rudolf Fallegger Autospenglerei",
    "wof:placetype":"venue"
},
  "geometry": {"coordinates":[8.301022,47.019333],"type":"Point"}
}