{
  "type": "Feature",
  "properties": {
    "iso:country":"CH",
    "sg:address":"Kantonsstrasse 320",
    "sg:city":"Gamsen",
    "sg:orig_category":"Detailhandel mit Computern U Software Hardwareberatung",
    "sg:phone":"+41 31 307 17 17",
    "sg:postcode":"3900",
    "sg:province":"Valais",
    "wof:name":"Mega-shop Pc-direkt Ag",
    "wof:placetype":"venue"
},
  "geometry": {"coordinates":[7.433411,46.952358],"type":"Point"}
}