{
  "type": "Feature",
  "properties": {
    "iso:country":"CH",
    "sg:address":"Maupas Rue Du 2",
    "sg:city":"Lausanne",
    "sg:orig_category":"Non-Classified Establishments",
    "sg:postcode":"1004",
    "sg:province":"Vaud",
    "wof:name":"Si Des Pr\u00e9s D'amens Sa",
    "wof:placetype":"venue"
},
  "geometry": {"coordinates":[6.7473778725,47.0568122864],"type":"Point"}
}