{
  "type": "Feature",
  "properties": {
    "iso:country":"CH",
    "sg:address":"Chemin De Sorecot 9",
    "sg:city":"Cheseaux-lausanne",
    "sg:orig_category":"Zahntechnische Laboratorien",
    "sg:phone":"+41 21 731 18 49",
    "sg:postcode":"1033",
    "sg:province":"Vaud",
    "wof:name":"Philippe Burli Labor.de Proth\u00e8ses Dentaires",
    "wof:placetype":"venue"
},
  "geometry": {"coordinates":[6.597992897,46.58411026],"type":"Point"}
}