{
  "type": "Feature",
  "properties": {
    "addr:full":"Grundstrasse 5 Zumikon Z\u00fcrich 8126",
    "addr:housenumber":"5",
    "addr:postcode":"8126",
    "addr:street":"Grundstrasse",
    "iso:country":"CH",
    "sg:address":"Grundstrasse 5",
    "sg:city":"Zumikon",
    "sg:orig_category":"Arztpraxen",
    "sg:phone":"+41 19190400",
    "sg:postcode":"8126",
    "sg:province":"Z\u00fcrich",
    "wof:name":"Dr.med.tobias Niggli Arzt F.allgemeine Medizin Fmh",
    "wof:placetype":"venue"
},
  "geometry": {"coordinates":[8.623822,47.329742],"type":"Point"}
}