{
  "type": "Feature",
  "properties": {
    "iso:country":"CH",
    "sg:address":"Route D'oron 77",
    "sg:city":"Lausanne",
    "sg:orig_category":"Allgemeinbildende weiterf\u00fchrende Schulen Maturit\u00e4tsschulen, Lehrerseminarien",
    "sg:phone":"+41 21 652 17 66",
    "sg:postcode":"1010",
    "sg:province":"Vaud",
    "wof:name":"Ecole Le Cap Sa",
    "wof:placetype":"venue"
},
  "geometry": {"coordinates":[6.666006,46.506939],"type":"Point"}
}