{
  "type": "Feature",
  "properties": {
    "iso:country":"CH",
    "sg:address":"Bachmattstrasse 53",
    "sg:city":"Z\u00fcrich",
    "sg:orig_category":"Markt U Meinungsforschung Wirtschaftspr\u00fcfung, Steuerberatung U Treuhand",
    "sg:phone":"+41 41 743 06 05",
    "sg:postcode":"8048",
    "sg:province":"Z\u00fcrich",
    "wof:name":"Content Marketing & Services Gmbh",
    "wof:placetype":"venue"
},
  "geometry": {"coordinates":[8.347869873,47.3581504822],"type":"Point"}
}