{
  "type": "Feature",
  "properties": {
    "iso:country":"CH",
    "sg:address":"Obere Dorfstrasse 38",
    "sg:city":"Bettingen",
    "sg:orig_category":"Verkehrs- and Tourismusb\u00fcros",
    "sg:phone":"+41 61 601 08 89",
    "sg:postcode":"4126",
    "sg:province":"Basel-Stadt",
    "wof:name":"Verkehrsverein Herrn Hanspeter Kiefer",
    "wof:placetype":"venue"
},
  "geometry": {"coordinates":[7.6659750938,47.5706443787],"type":"Point"}
}