{
  "type": "Feature",
  "properties": {
    "iso:country":"CH",
    "sg:address":"6030",
    "sg:city":"Ebikon",
    "sg:orig_category":"Sportvereine Ballsport Badminton",
    "sg:phone":"+41 26 496 26 89",
    "sg:postcode":"6030",
    "sg:province":"Luzern",
    "wof:name":"Badminton-club Schmitten",
    "wof:placetype":"venue"
},
  "geometry": {"coordinates":[7.2530660629,46.8643913269],"type":"Point"}
}