{
  "type": "Feature",
  "properties": {
    "iso:country":"CH",
    "sg:address":"Hasenb\u00fchlstrasse 5",
    "sg:city":"Uster",
    "sg:orig_category":"Fotografische Ateliers",
    "sg:phone":"+41 19407473",
    "sg:postcode":"8610",
    "sg:province":"Z\u00fcrich",
    "wof:name":"Heidi Wettstein Fotoreportagen",
    "wof:placetype":"venue"
},
  "geometry": {"coordinates":[8.7225942612,47.3541793823],"type":"Point"}
}