{
  "type": "Feature",
  "properties": {
    "iso:country":"CH",
    "sg:address":"Vignettaz Route De La 57-59",
    "sg:city":"Fribourg",
    "sg:orig_category":"Religi\u00f6se Vereinigungen",
    "sg:phone":"+41 26 424 19 77",
    "sg:postcode":"1702",
    "sg:province":"Fribourg",
    "wof:name":"Institut Lavigerie",
    "wof:placetype":"venue"
},
  "geometry": {"coordinates":[7.1536831856,46.8037452698],"type":"Point"}
}