{
  "type": "Feature",
  "properties": {
    "iso:country":"CH",
    "sg:address":"Stationsstrasse 11",
    "sg:city":"Bonstetten",
    "sg:orig_category":"Fussboden, Fliesen U Plattenlegerei, Tapeziererei",
    "sg:phone":"+41 17003533",
    "sg:postcode":"8906",
    "sg:province":"Z\u00fcrich",
    "wof:name":"Meier G. Ag",
    "wof:placetype":"venue"
},
  "geometry": {"coordinates":[8.4680728912,47.316822052],"type":"Point"}
}