{
  "type": "Feature",
  "properties": {
    "iso:country":"CH",
    "sg:address":"Bahnhofstrasse 20",
    "sg:city":"Herisau",
    "sg:orig_category":"Zahnarztpraxen",
    "sg:phone":"+41 71 351 67 32",
    "sg:postcode":"9100",
    "sg:province":"Appenzell Ausserrhoden",
    "wof:name":"Dr. Med. Dent. Heinz Gregorin Zahnarzt",
    "wof:placetype":"venue"
},
  "geometry": {"coordinates":[9.2766771317,47.3884429932],"type":"Point"}
}