{
  "type": "Feature",
  "properties": {
    "iso:country":"CH",
    "sg:address":"Surbtalstrasse 22",
    "sg:city":"D\u00f6ttingen",
    "sg:orig_category":"Manicure P\u00e9dicure",
    "sg:phone":"+41 56 633 08 33",
    "sg:postcode":"5312",
    "sg:province":"Aargau",
    "wof:name":"Diana Roos",
    "wof:placetype":"venue"
},
  "geometry": {"coordinates":[8.350110054,47.3493309021],"type":"Point"}
}