{
  "type": "Feature",
  "properties": {
    "iso:country":"CH",
    "sg:address":"Richtersmattweg 6a",
    "sg:city":"Sch\u00fcpfen",
    "sg:orig_category":"Herstellung von Armaturen Herstellung von Metallerzeugnissen ohne Maschinenbau",
    "sg:phone":"+41 81 302 76 76",
    "sg:postcode":"3054",
    "sg:province":"Bern",
    "wof:name":"Strawa Ag",
    "wof:placetype":"venue"
},
  "geometry": {"coordinates":[9.5029401779,47.0111198425],"type":"Point"}
}