{
  "type": "Feature",
  "properties": {
    "iso:country":"CH",
    "sg:address":"Ob Dem Dorf 11",
    "sg:city":"Titterten",
    "sg:orig_category":"Wirtschaftspr\u00fcfung, Steuerberatung U Treuhand",
    "sg:phone":"+41 61 943 10 10",
    "sg:postcode":"4425",
    "sg:province":"Basel-Landschaft",
    "wof:name":"Stw Sch\u00fcrmann Treuhand Ag",
    "wof:placetype":"venue"
},
  "geometry": {"coordinates":[7.7174711227,47.4016456604],"type":"Point"}
}