{
  "type": "Feature",
  "properties": {
    "iso:country":"CH",
    "sg:address":"Watterstrasse 17",
    "sg:city":"Regensdorf",
    "sg:classifiers":[
        {
            "category":"Education",
            "subcategory":"Library",
            "type":"Public Place"
        }
    ],
    "sg:phone":"+41 18401461",
    "sg:postcode":"8105",
    "sg:province":"Z\u00fcrich",
    "sg:tags":[
        "u",
        "bibliotheken",
        "archive"
    ],
    "wof:name":"Gemeindebibliothek",
    "wof:placetype":"venue"
},
  "geometry": {"coordinates":[8.465747,47.430485],"type":"Point"}
}