{
  "type": "Feature",
  "properties": {
    "iso:country":"CH",
    "sg:address":"Immeuble Rond-point",
    "sg:city":"Montana-vermala",
    "sg:orig_category":"Reiseb\u00fcros",
    "sg:phone":"+41 27 481 88 61",
    "sg:postcode":"3962",
    "wof:name":"Prestige Vacances Sa",
    "wof:placetype":"venue"
},
  "geometry": {"coordinates":[7.4924340248,46.3144187927],"type":"Point"}
}