{
  "type": "Feature",
  "properties": {
    "iso:country":"CH",
    "sg:address":"4000 Basel. Postfach",
    "sg:city":"Basel",
    "sg:orig_category":"Unclassifiable Establishments",
    "sg:postcode":"4000",
    "sg:province":"Basel-Stadt",
    "wof:name":"Graphic-papiers.com S\u00e0rl",
    "wof:placetype":"venue"
},
  "geometry": {"coordinates":[7.3472747803,46.2116165161],"type":"Point"}
}