{
  "type": "Feature",
  "properties": {
    "iso:country":"CH",
    "sg:address":"1872",
    "sg:city":"Troistorrents",
    "sg:orig_category":"Herstellung von Teppichen Verlegen von Fliesen U Platten",
    "sg:phone":"+41 24 477 15 42",
    "sg:postcode":"1872",
    "sg:province":"Valais",
    "wof:name":"Dubosson Alexandre",
    "wof:placetype":"venue"
},
  "geometry": {"coordinates":[6.9183092117,46.2293548584],"type":"Point"}
}