{
  "type": "Feature",
  "properties": {
    "iso:country":"CH",
    "sg:address":"Gehristrasse 5",
    "sg:city":"Kriens",
    "sg:orig_category":"Grosshandel mit Nahrungsmitteln, Getr\u00e4nken U Tabakwaren ohne ausgepr\u00e4gten Schwerpunkt",
    "sg:postcode":"6010",
    "sg:province":"Luzern",
    "wof:name":"Longariello Schl\u00f6sslilade",
    "wof:placetype":"venue"
},
  "geometry": {"coordinates":[8.2774019241,47.0301017761],"type":"Point"}
}