{
  "type": "Feature",
  "properties": {
    "iso:country":"CH",
    "sg:address":"Bahnhofstrasse 14",
    "sg:city":"Toffen",
    "sg:orig_category":"Nationale Postdienste",
    "sg:phone":"+41 32 384 22 05",
    "sg:postcode":"3125",
    "sg:province":"Bern",
    "wof:name":"Die Schweizerische Post",
    "wof:placetype":"venue"
},
  "geometry": {"coordinates":[7.3216218948,47.099357605],"type":"Point"}
}