{
  "type": "Feature",
  "properties": {
    "iso:country":"CH",
    "sg:address":"Oberneuhofstrasse 6 6340 Baar. Postfach 564",
    "sg:city":"Baar",
    "sg:orig_category":"Detailhandel mit elektrischen Haushalts-,Radio U Fernsehger\u00e4ten sowie Musikinstrumenten Grosshandel ",
    "sg:phone":"+41 41 767 47 00",
    "sg:postcode":"6341",
    "sg:province":"Zug",
    "wof:name":"Sony Music Entertainment Ag",
    "wof:placetype":"venue"
},
  "geometry": {"coordinates":[8.5157575607,47.1882553101],"type":"Point"}
}