{
  "type": "Feature",
  "properties": {
    "addr:full":"Industriestrasse 1 Schlieren Z\u00fcrich 8952",
    "addr:housenumber":"1",
    "addr:postcode":"8952",
    "addr:street":"Industriestrasse",
    "iso:country":"CH",
    "sg:address":"Industriestrasse 1",
    "sg:city":"Schlieren",
    "sg:classifiers":[
        {
            "category":"Professional",
            "subcategory":"Advertising",
            "type":"Services"
        }
    ],
    "sg:phone":"+41 71 313 99 11",
    "sg:postcode":"8952",
    "sg:province":"Z\u00fcrich",
    "sg:tags":[
        "poster"
    ],
    "wof:name":"Kaiser Print & Display Gmbh",
    "wof:placetype":"venue"
},
  "geometry": {"coordinates":[9.292616,47.405018],"type":"Point"}
}