{
  "type": "Feature",
  "properties": {
    "iso:country":"CH",
    "sg:address":"Rue Ferdinand-hodler 19 1200 Genf. Postfach",
    "sg:city":"Gen\u00e8ve",
    "sg:orig_category":"Fachdetailhandel in Verkaufsr\u00e4umen",
    "sg:phone":"+41 22 311 30 26",
    "sg:postcode":"1201",
    "sg:province":"Gen\u00e8ve",
    "wof:name":"Sugar Stefan",
    "wof:placetype":"venue"
},
  "geometry": {"coordinates":[6.1552357674,46.1992073059],"type":"Point"}
}