{
  "type": "Feature",
  "properties": {
    "iso:country":"CH",
    "sg:address":"R\u00fcttistrasse 12",
    "sg:city":"Eiken",
    "sg:orig_category":"Massagestudios",
    "sg:phone":"+41 17600555",
    "sg:postcode":"5074",
    "sg:province":"Aargau",
    "wof:name":"Hansueli R\u00fcfenacht Massage-praxis",
    "wof:placetype":"venue"
},
  "geometry": {"coordinates":[8.4508810043,47.2711868286],"type":"Point"}
}