{
  "type": "Feature",
  "properties": {
    "iso:country":"CH",
    "sg:address":"Via P. Marconi 13 6710 Biasca. Postfach",
    "sg:city":"Biasca",
    "sg:orig_category":"Herstellung von sonstigen landwirtschaftlichen Maschinen Sonstiger Grosshandel",
    "sg:phone":"+41 91 880 04 04",
    "sg:postcode":"6710",
    "sg:province":"Ticino",
    "wof:name":"Massera Ivano, Delaval Servizio Ticino Prodotti; Vendita, Assistenza Tecnica",
    "wof:placetype":"venue"
},
  "geometry": {"coordinates":[8.9693183899,46.3620147705],"type":"Point"}
}