{
  "type": "Feature",
  "properties": {
    "iso:country":"CH",
    "sg:address":"Steinrieselnstrasse 80 9100 Herisau. Postfach",
    "sg:city":"Herisau",
    "sg:orig_category":"Wirtschaftspr\u00fcfung, Steuerberatung U Treuhand",
    "sg:postcode":"9100",
    "sg:province":"Appenzell Ausserrhoden",
    "wof:name":"Baumer Treuhand",
    "wof:placetype":"venue"
},
  "geometry": {"coordinates":[9.2890939713,47.3857421875],"type":"Point"}
}