{
  "type": "Feature",
  "properties": {
    "iso:country":"CH",
    "sg:address":"Vordergasse 21",
    "sg:city":"Schaffhausen",
    "sg:orig_category":"Kosmetikinstitute",
    "sg:phone":"+41 55 210 00 05",
    "sg:postcode":"8200",
    "sg:province":"Schaffhausen",
    "wof:name":"Perle De Beaut\u00e9, Meierhofer Christina",
    "wof:placetype":"venue"
},
  "geometry": {"coordinates":[8.8163328171,47.227016449],"type":"Point"}
}