{
  "type": "Feature",
  "properties": {
    "iso:country":"CH",
    "sg:address":"8617 M\u00f6nchaltorf. Postfach 164",
    "sg:city":"M\u00f6nchaltorf",
    "sg:orig_category":"Sonstige mit der Informatik verbundene T\u00e4tigkeiten",
    "sg:postcode":"8617",
    "sg:province":"Z\u00fcrich",
    "wof:name":"Pbkomm Informatik & Beratung, Bauer P. Edv; Support, Beratung, Schulung, Installation",
    "wof:placetype":"venue"
},
  "geometry": {"coordinates":[8.3546152115,47.1746406555],"type":"Point"}
}