{
  "type": "Feature",
  "properties": {
    "iso:country":"CH",
    "sg:address":"Centralstrasse 14",
    "sg:city":"Berom\u00fcnster",
    "sg:orig_category":"Detailhandel mit fotografischen Artikeln",
    "sg:phone":"+41 41 931 02 92",
    "sg:postcode":"6215",
    "sg:province":"Luzern",
    "wof:name":"Fotolade R\u00f6ssli Foto-& Filmfachgesch\u00e4ft",
    "wof:placetype":"venue"
},
  "geometry": {"coordinates":[8.190404892,47.2067604065],"type":"Point"}
}