{
  "type": "Feature",
  "properties": {
    "iso:country":"CH",
    "sg:address":"Konstanzerstrasse 55",
    "sg:city":"Kreuzlingen",
    "sg:classifiers":[
        {
            "category":"Home & Garden",
            "subcategory":"Building Materials",
            "type":"Retail Goods"
        }
    ],
    "sg:phone":"+41 71 672 55 72",
    "sg:postcode":"8280",
    "sg:province":"Thurgau",
    "sg:tags":[
        "central",
        "heating",
        "boiler"
    ],
    "wof:name":"Burkart + Sohn Ag",
    "wof:placetype":"venue"
},
  "geometry": {"coordinates":[9.16375,47.64901],"type":"Point"}
}