{
  "type": "Feature",
  "properties": {
    "iso:country":"CH",
    "sg:address":"Dorfstr. 94",
    "sg:city":"Amsoldingen",
    "sg:orig_category":"Erschliessung von Grundst\u00fccken",
    "sg:postcode":"3633",
    "sg:province":"Bern",
    "wof:name":"Wohnbaugenossenschaft Galgacher, Amsoldingen",
    "wof:placetype":"venue"
},
  "geometry": {"coordinates":[7.5798602104,46.7271614075],"type":"Point"}
}