{
  "type": "Feature",
  "properties": {
    "iso:country":"CH",
    "sg:address":"Principale 80 2533 Evilard Case Postale",
    "sg:city":"Evilard",
    "sg:orig_category":"Sonstiger spezialisierter Hoch U Tiefbau",
    "sg:phone":"+41 32 322 30 60",
    "sg:postcode":"2533",
    "sg:province":"Bern",
    "wof:name":"Aqua Projekt Ag Bew\u00e4sserungsanlagen; Planung Usw",
    "wof:placetype":"venue"
},
  "geometry": {"coordinates":[7.2325921059,47.1497344971],"type":"Point"}
}