{
  "type": "Feature",
  "properties": {
    "iso:country":"CH",
    "sg:address":"7189",
    "sg:city":"Rueras",
    "sg:classifiers":[
        {
            "category":"Restaurant",
            "type":"Food & Drink"
        }
    ],
    "sg:phone":"+41 81 949 11 58",
    "sg:postcode":"7189",
    "sg:province":"Graubunden",
    "wof:name":"Ustria D'alp Planatsch",
    "wof:placetype":"venue"
},
  "geometry": {"coordinates":[8.7533197403,46.6759796143],"type":"Point"}
}