{
  "type": "Feature",
  "properties": {
    "iso:country":"CH",
    "sg:address":"Birkenweg 2",
    "sg:city":"Ober\u00f6nz",
    "sg:classifiers":[
        {
            "category":"Transit Center",
            "subcategory":"Freight",
            "type":"Transportation"
        }
    ],
    "sg:phone":"+41 62 956 22 22",
    "sg:postcode":"3363",
    "sg:province":"Bern",
    "sg:tags":[
        "spindle",
        "air-bearing"
    ],
    "wof:name":"Fischer Ag Pr\u00e4zisionsspindeln",
    "wof:placetype":"venue"
},
  "geometry": {"coordinates":[7.698513,47.183369],"type":"Point"}
}