{
  "type": "Feature",
  "properties": {
    "iso:country":"CH",
    "sg:address":"3296",
    "sg:city":"Arch",
    "sg:orig_category":"Vereine Gesang",
    "sg:postcode":"3296",
    "sg:province":"Bern",
    "wof:name":"M\u00e4nnerchor Arion Solothurn",
    "wof:placetype":"venue"
},
  "geometry": {"coordinates":[7.4961671829,47.2346038818],"type":"Point"}
}