{
  "type": "Feature",
  "properties": {
    "iso:country":"CH",
    "sg:address":"Kantonsstrasse 3900 Gamsen. Postfach",
    "sg:city":"Gamsen",
    "sg:orig_category":"Herstellung von konfektionierten Textilwaren ohne Bekleidung",
    "sg:postcode":"3900",
    "sg:province":"Valais",
    "wof:name":"Lettermann Furger & Seematter Fahnen; Erstellen, Beschriften Usw",
    "wof:placetype":"venue"
},
  "geometry": {"coordinates":[7.9593667984,46.3058013916],"type":"Point"}
}