{
  "type": "Feature",
  "properties": {
    "iso:country":"CH",
    "sg:address":"Kublihoschet 12",
    "sg:city":"Netstal",
    "sg:orig_category":"Grosshandel mit Getr\u00e4nken",
    "sg:postcode":"8754",
    "sg:province":"Glarus",
    "wof:name":"Seiler Walter Ag",
    "wof:placetype":"venue"
},
  "geometry": {"coordinates":[9.0580978394,47.0573005676],"type":"Point"}
}