{
  "type": "Feature",
  "properties": {
    "addr:full":"Altenbergstrasse 57 Bern Bern 3013",
    "addr:housenumber":"57",
    "addr:postcode":"3013",
    "addr:street":"Altenbergstrasse",
    "iso:country":"CH",
    "sg:address":"Altenbergstrasse 57",
    "sg:city":"Bern",
    "sg:orig_category":"Bauschreinerei",
    "sg:phone":"+41 31 332 30 41",
    "sg:postcode":"3013",
    "sg:province":"Bern",
    "wof:name":"Ulrich Wyttenbach Altenberg-schreinerei",
    "wof:placetype":"venue"
},
  "geometry": {"coordinates":[7.450046,46.95042],"type":"Point"}
}