{
  "type": "Feature",
  "properties": {
    "iso:country":"CH",
    "sg:address":"Tilleuls Rue Des 9",
    "sg:city":"Geneveys-coffrane",
    "sg:orig_category":"Fachdetailhandel in Verkaufsr\u00e4umen",
    "sg:postcode":"2206",
    "sg:province":"Neuch\u00e2tel",
    "wof:name":"Mom Cr\u00e9ation Sa",
    "wof:placetype":"venue"
},
  "geometry": {"coordinates":[6.8518447876,47.0164413452],"type":"Point"}
}