{
  "type": "Feature",
  "properties": {
    "iso:country":"CH",
    "sg:address":"B\u00fcrgstrasse 36",
    "sg:city":"Spiez",
    "sg:orig_category":"Softwareentwicklung U beratung",
    "sg:phone":"+41 33 654 80 44",
    "sg:postcode":"3700",
    "sg:province":"Bern",
    "wof:name":"Rola Mvs Gmbh",
    "wof:placetype":"venue"
},
  "geometry": {"coordinates":[7.6967368126,46.6842041016],"type":"Point"}
}