{
  "type": "Feature",
  "properties": {
    "iso:country":"CH",
    "sg:address":"Winkel 21 9496 Balzers. Postfach 418",
    "sg:city":"Balzers",
    "sg:orig_category":"Bauschreinerei",
    "sg:phone":"+43 841 553",
    "sg:postcode":"9496",
    "wof:name":"Anton Vogt Ag Schreinerei",
    "wof:placetype":"venue"
},
  "geometry": {"coordinates":[9.50629,47.067989],"type":"Point"}
}