{
  "type": "Feature",
  "properties": {
    "addr:full":"Quai De La Thi\u00e8le 3 1400 Yverdon-les-bains. Postfach Yverdon Vaud 1401",
    "addr:housenumber":"3",
    "addr:postcode":"1400;postfach;1401",
    "addr:street":"Quai De La Thie\u0300Le",
    "iso:country":"CH",
    "sg:address":"Quai De La Thi\u00e8le 3 1400 Yverdon-les-bains. Postfach",
    "sg:city":"Yverdon",
    "sg:orig_category":"Arbeitnehmerverb\u00e4nde",
    "sg:phone":"+41 24 425 06 76",
    "sg:postcode":"1401",
    "sg:province":"Vaud",
    "wof:name":"Syndicat Industrie & B\u00e2timent",
    "wof:placetype":"venue"
},
  "geometry": {"coordinates":[6.637148,46.781006],"type":"Point"}
}