{
  "type": "Feature",
  "properties": {
    "iso:country":"CH",
    "sg:address":"Hochstrasse 113 4053 Basel. Postfach",
    "sg:city":"Basel",
    "sg:orig_category":"Public-Relations-Agenturen Werbeagenturen",
    "sg:phone":"+41 41 660 96 19",
    "sg:postcode":"4018",
    "sg:province":"Basel-Stadt",
    "wof:name":"Kommunikationswerkstatt Gmbh",
    "wof:placetype":"venue"
},
  "geometry": {"coordinates":[8.2105798721,46.8866882324],"type":"Point"}
}