{
  "type": "Feature",
  "properties": {
    "iso:country":"CH",
    "sg:address":"Holzgasse 6490 Andermatt. Postfach",
    "sg:city":"Andermatt",
    "sg:orig_category":"Pensionskassen",
    "sg:phone":"+41 56 618 73 73",
    "sg:postcode":"6490",
    "sg:province":"Uri",
    "wof:name":"Wohlfahrtsfonds Der Belux Ag",
    "wof:placetype":"venue"
},
  "geometry": {"coordinates":[8.2953500748,47.3473014832],"type":"Point"}
}