{
  "type": "Feature",
  "properties": {
    "iso:country":"CH",
    "sg:address":"Etang Chemin De L' 48 1219 Ch\u00e2telaine. Postfach",
    "sg:city":"Ch\u00e2telaine",
    "sg:orig_category":"Handel mit Automobilen",
    "sg:postcode":"1219",
    "sg:province":"Gen\u00e8ve",
    "wof:name":"J.b. Autos S\u00e0rl",
    "wof:placetype":"venue"
},
  "geometry": {"coordinates":[4.2666201591,46.8350372314],"type":"Point"}
}