{
  "type": "Feature",
  "properties": {
    "iso:country":"CH",
    "sg:address":"Z\u00fcrcherstrasse 17",
    "sg:city":"Neerach",
    "sg:orig_category":"Telefonmarketingagenturen",
    "sg:phone":"+41 62 867 20 57",
    "sg:postcode":"8173",
    "sg:province":"Z\u00fcrich",
    "wof:name":"Adelheid Kroese Icc Industrial Call Center",
    "wof:placetype":"venue"
},
  "geometry": {"coordinates":[8.1552801132,47.5617485046],"type":"Point"}
}