{
  "type": "Feature",
  "properties": {
    "iso:country":"CH",
    "sg:address":"Schneckenmannstrasse 27",
    "sg:city":"Z\u00fcrich",
    "sg:orig_category":"Interessenvertretungen",
    "sg:postcode":"8044",
    "sg:province":"Z\u00fcrich",
    "wof:name":"Pro Zurituutsch",
    "wof:placetype":"venue"
},
  "geometry": {"coordinates":[8.5633049011,47.3756790161],"type":"Point"}
}