{
  "type": "Feature",
  "properties": {
    "iso:country":"CH",
    "sg:address":"Quatre-vents Rue Des 5",
    "sg:city":"Boncourt",
    "sg:orig_category":"Allgemeiner Hoch U Tiefbau",
    "sg:phone":"+41 32 475 55 24",
    "sg:postcode":"2926",
    "sg:province":"Jura",
    "wof:name":"Lachat Damien",
    "wof:placetype":"venue"
},
  "geometry": {"coordinates":[7.005309,47.499489],"type":"Point"}
}