{
  "type": "Feature",
  "properties": {
    "iso:country":"CH",
    "sg:address":"Sablons Rue Des 45",
    "sg:city":"Neuch\u00e2tel",
    "sg:orig_category":"Interessenvertretungen",
    "sg:postcode":"2000",
    "sg:province":"Neuch\u00e2tel",
    "wof:name":"Fondation Du Cinquantenaire De L'ecole Sup\u00e9rieure De Commerce De Neuch\u00e2tel",
    "wof:placetype":"venue"
},
  "geometry": {"coordinates":[6.9316082001,46.99609375],"type":"Point"}
}