{
  "type": "Feature",
  "properties": {
    "iso:country":"CH",
    "sg:address":"Dornacherstrasse 404 4053 Basel. Postfach",
    "sg:city":"Basel",
    "sg:orig_category":"Non-Classified Establishments",
    "sg:phone":"+41 61 383 27 44",
    "sg:postcode":"4053",
    "sg:province":"Basel-Stadt",
    "wof:name":"Ixotic Ag",
    "wof:placetype":"venue"
},
  "geometry": {"coordinates":[7.6076340675,47.5375823975],"type":"Point"}
}