{
  "type": "Feature",
  "properties": {
    "iso:country":"CH",
    "sg:address":"Fayards Chemin Des 2",
    "sg:city":"Romanel-s-lausanne",
    "sg:orig_category":"Grosshandel mit sonstigen Maschinen U Ausr\u00fcstungen f\u00fcr Industrie, Handel U Schiffahrt",
    "sg:postcode":"1032",
    "sg:province":"Vaud",
    "wof:name":"Jauslin Plexacryl Sa",
    "wof:placetype":"venue"
},
  "geometry": {"coordinates":[6.6038780212,46.5632209778],"type":"Point"}
}