{
  "type": "Feature",
  "properties": {
    "iso:country":"CH",
    "sg:address":"Im Leib\u00fcel 3",
    "sg:city":"Elgg",
    "sg:orig_category":"Sportvereine Ballsport Tennis",
    "sg:phone":"+41 52 364 23 97",
    "sg:postcode":"8353",
    "sg:province":"Z\u00fcrich",
    "wof:name":"Tc Elgg",
    "wof:placetype":"venue"
},
  "geometry": {"coordinates":[8.8636636734,47.4918861389],"type":"Point"}
}