{
  "type": "Feature",
  "properties": {
    "iso:country":"CH",
    "sg:address":"Via Balestra 9",
    "sg:city":"Lugano",
    "sg:orig_category":"Wirtschaftspr\u00fcfung, Steuerberatung U Treuhand",
    "sg:postcode":"6900",
    "sg:province":"Ticino",
    "wof:name":"Studio Fiduciario Rag. Righini Giordano.",
    "wof:placetype":"venue"
},
  "geometry": {"coordinates":[8.9541625977,46.0081062317],"type":"Point"}
}