{
  "type": "Feature",
  "properties": {
    "iso:country":"CH",
    "sg:address":"Boulevard De P\u00e9rolles 7",
    "sg:city":"Fribourg",
    "sg:orig_category":"Markt U Meinungsforschung",
    "sg:postcode":"1700",
    "sg:province":"Fribourg",
    "wof:name":"Mb Marketing Sa",
    "wof:placetype":"venue"
},
  "geometry": {"coordinates":[7.1517372131,46.801235199],"type":"Point"}
}