{
  "type": "Feature",
  "properties": {
    "iso:country":"CH",
    "sg:address":"G\u00fcterstrasse 8",
    "sg:city":"Feuerthalen",
    "sg:orig_category":"Herstellung von Spielwaren",
    "sg:phone":"+41 56 282 58 82",
    "sg:postcode":"8245",
    "sg:province":"Z\u00fcrich",
    "wof:name":"Schreier Beat, Modell & Art",
    "wof:placetype":"venue"
},
  "geometry": {"coordinates":[8.2980823517,47.4858665466],"type":"Point"}
}