{
  "type": "Feature",
  "properties": {
    "iso:country":"CH",
    "sg:address":"Rue Du Pr\u00e9-j\u00e9r\u00f4me 5 1200 Genf. Postfach",
    "sg:city":"Gen\u00e8ve",
    "sg:orig_category":"Betrieb U technische Hilfsdienste des Kultur U Unterhaltungswesens",
    "sg:postcode":"1205",
    "sg:province":"Gen\u00e8ve",
    "wof:name":"Ressources Scoutes Internationales",
    "wof:placetype":"venue"
},
  "geometry": {"coordinates":[6.144504,46.193123],"type":"Point"}
}