{
  "type": "Feature",
  "properties": {
    "iso:country":"CH",
    "sg:address":"Rebhaldenstrasse 37",
    "sg:city":"Neerach",
    "sg:orig_category":"Abdichtung Allgemeiner Hoch U Tiefbau",
    "sg:phone":"+41 22 788 51 23",
    "sg:postcode":"8173",
    "sg:province":"Z\u00fcrich",
    "wof:name":"Gypseco S\u00e0rl",
    "wof:placetype":"venue"
},
  "geometry": {"coordinates":[6.125625,46.235344],"type":"Point"}
}