{
  "type": "Feature",
  "properties": {
    "iso:country":"CH",
    "sg:address":"Murtenstrasse 11",
    "sg:city":"Aarberg",
    "sg:orig_category":"Werbeagenturen Werbegrafikateliers",
    "sg:phone":"+41 32 392 19 91",
    "sg:postcode":"3270",
    "sg:province":"Bern",
    "wof:name":"Bernhard Barraud Grafik & Werbung",
    "wof:placetype":"venue"
},
  "geometry": {"coordinates":[7.2721347809,47.0427818298],"type":"Point"}
}