{
  "type": "Feature",
  "properties": {
    "iso:country":"CH",
    "sg:address":"Au Clos-\u00e0-galley",
    "sg:city":"Chessel",
    "sg:orig_category":"Herstellung von k\u00e4lte U lufttechnischen Erzeugnissen f\u00fcr gewerbliche Zwecke Sanit\u00e4r U Heizungsinstal",
    "sg:phone":"+41 24 481 12 85",
    "sg:postcode":"1846",
    "sg:province":"Vaud",
    "wof:name":"Ruch E. Climat Service Sa",
    "wof:placetype":"venue"
},
  "geometry": {"coordinates":[6.8959531784,46.3521347046],"type":"Point"}
}