{
  "type": "Feature",
  "properties": {
    "iso:country":"CH",
    "sg:address":"Oltnerstrasse 7",
    "sg:city":"Niederg\u00f6sgen",
    "sg:orig_category":"P\u00e9dicure",
    "sg:phone":"+41 62 849 30 30",
    "sg:postcode":"5013",
    "sg:province":"Solothurn",
    "wof:name":"Anne Leuner P\u00e9dicure",
    "wof:placetype":"venue"
},
  "geometry": {"coordinates":[7.9856038094,47.3714828491],"type":"Point"}
}