{
  "type": "Feature",
  "properties": {
    "iso:country":"CH",
    "sg:address":"7000",
    "sg:city":"Chur",
    "sg:orig_category":"Friedhofs- and Stadtg\u00e4rtnereien",
    "sg:phone":"+41 71 224 51 21",
    "sg:postcode":"7000",
    "sg:province":"Graubunden",
    "wof:name":"Gartenbauamt Der Stadt St.gallen",
    "wof:placetype":"venue"
},
  "geometry": {"coordinates":[9.3760881424,47.4254989624],"type":"Point"}
}