{
  "type": "Feature",
  "properties": {
    "iso:country":"CH",
    "sg:address":"Dorfstrasse 6",
    "sg:city":"Altenrhein",
    "sg:orig_category":"Architektur U Ingenieurb\u00fcros Architekturb\u00fcros",
    "sg:phone":"+41 71 855 33 73",
    "sg:postcode":"9423",
    "sg:province":"St. Gallen",
    "wof:name":"Camenisch Rolf Architekturb\u00fcro Ag",
    "wof:placetype":"venue"
},
  "geometry": {"coordinates":[9.551407,47.489433],"type":"Point"}
}