{
  "type": "Feature",
  "properties": {
    "iso:country":"CH",
    "sg:address":"Avenue De La Gare 44",
    "sg:city":"Martigny",
    "sg:classifiers":[
        {
            "category":"Restaurant",
            "type":"Food & Drink"
        }
    ],
    "sg:phone":"+41 27 722 88 33",
    "sg:postcode":"1920",
    "sg:province":"Valais",
    "wof:name":"Cr\u00eaperie Rustique",
    "wof:placetype":"venue"
},
  "geometry": {"coordinates":[7.0772490501,46.1043930054],"type":"Point"}
}