{
  "type": "Feature",
  "properties": {
    "iso:country":"CH",
    "sg:address":"Breitistrasse 18",
    "sg:city":"Kloten",
    "sg:orig_category":"Gesundheitswesen Physiotherapie",
    "sg:phone":"+41 61 711 87 80",
    "sg:postcode":"8302",
    "sg:province":"Z\u00fcrich",
    "wof:name":"Physiotherapie Kern",
    "wof:placetype":"venue"
},
  "geometry": {"coordinates":[7.5885667801,47.4937705994],"type":"Point"}
}