{
  "type": "Feature",
  "properties": {
    "iso:country":"CH",
    "sg:address":"Rue Peillonnex 2",
    "sg:city":"Ch\u00eane-bourg",
    "sg:orig_category":"Grosshandel mit Parf\u00fcmerieartikeln U K\u00f6rperpflegemitteln Grosshandel mit medizinischen U orthop\u00e4disc",
    "sg:phone":"+41 22 349 37 37",
    "sg:postcode":"1225",
    "sg:province":"Gen\u00e8ve",
    "wof:name":"Pharmacie Populaire Trois-chene",
    "wof:placetype":"venue"
},
  "geometry": {"coordinates":[6.1955561638,46.1943244934],"type":"Point"}
}