{
  "type": "Feature",
  "properties": {
    "iso:country":"CH",
    "sg:address":"L\u00e4ttenwiesenstrasse 23",
    "sg:city":"Opfikon",
    "sg:orig_category":"Detailhandel mit M\u00f6beln U Haushaltsgegenst\u00e4nden",
    "sg:postcode":"8152",
    "sg:province":"Z\u00fcrich",
    "wof:name":"H\u00fcsler Xaver, M\u00f6bel Und Teppiche",
    "wof:placetype":"venue"
},
  "geometry": {"coordinates":[8.5640535355,47.4261512756],"type":"Point"}
}