{
  "type": "Feature",
  "properties": {
    "iso:country":"CH",
    "sg:address":"Zentralstrasse 56",
    "sg:city":"Neuhausen",
    "sg:orig_category":"Detailhandel mit Brot, Back U S\u00fcsswaren",
    "sg:phone":"+41 52 625 73 33",
    "sg:postcode":"8212",
    "sg:province":"Schaffhausen",
    "wof:name":"B\u00e4ckerei Zur Tanne Gmbh",
    "wof:placetype":"venue"
},
  "geometry": {"coordinates":[8.620391,47.681992],"type":"Point"}
}