{
  "type": "Feature",
  "properties": {
    "iso:country":"CH",
    "sg:address":"Bahnhofstrasse 63",
    "sg:city":"Riehen",
    "sg:classifiers":[
        {
            "category":"Travel",
            "subcategory":"Hotels & Motels",
            "type":"Entertainment"
        }
    ],
    "sg:phone":"+41 61 641 64 85",
    "sg:postcode":"4125",
    "sg:province":"Basel-Stadt",
    "sg:tags":[
        "hotels",
        "mit",
        "restaurant"
    ],
    "wof:name":"Perspectiva - Gesellschaft F\u00fcr Pers\u00f6nlichkeitsentwicklung Gmbh",
    "wof:placetype":"venue"
},
  "geometry": {"coordinates":[7.6505451202,47.5821380615],"type":"Point"}
}