{
  "type": "Feature",
  "properties": {
    "iso:country":"CH",
    "sg:address":"Pury Place",
    "sg:city":"Neuch\u00e2tel",
    "sg:orig_category":"Nahrungsmittel-Industrie: Rohstoffe",
    "sg:postcode":"2000",
    "sg:province":"Neuch\u00e2tel",
    "wof:name":"Munzur, G\u00dcnd\u00dcz Mustafa",
    "wof:placetype":"venue"
},
  "geometry": {"coordinates":[6.9290499687,46.9895744324],"type":"Point"}
}