{
  "type": "Feature",
  "properties": {
    "iso:country":"CH",
    "sg:address":"Fabrikstrasse 31 3012 Bern. Postfach",
    "sg:city":"Bern",
    "sg:orig_category":"Kinderg\u00e4rten, Vor U Grundschulen Unternehmensberatung",
    "sg:phone":"+41 31 372 05 31",
    "sg:postcode":"3012",
    "sg:province":"Bern",
    "wof:name":"Krips Gmbh Kindertagesst\u00e4tte",
    "wof:placetype":"venue"
},
  "geometry": {"coordinates":[7.4250102043,46.9544906616],"type":"Point"}
}