{
  "type": "Feature",
  "properties": {
    "iso:country":"CH",
    "sg:address":"Burgstrasse 70",
    "sg:city":"Weinfelden",
    "sg:classifiers":[
        {
            "category":"Professional",
            "subcategory":"Detective & Security Services",
            "type":"Services"
        }
    ],
    "sg:phone":"+41 71 622 52 10",
    "sg:postcode":"8570",
    "sg:province":"Thurgau",
    "sg:tags":[
        "flasher",
        "alarm",
        "lamp"
    ],
    "wof:name":"Wunderli Electronics Ag",
    "wof:placetype":"venue"
},
  "geometry": {"coordinates":[9.130716,47.571686],"type":"Point"}
}