{
  "type": "Feature",
  "properties": {
    "addr:full":"Ebnaterstrasse 45a 9630 Wattwil. Postfach Wattwil St. Gallen 9630",
    "addr:housenumber":"45a",
    "addr:postcode":"9630 wattwil. postfach wattwil;9630",
    "addr:street":"Ebnaterstrasse",
    "iso:country":"CH",
    "sg:address":"Ebnaterstrasse 45a 9630 Wattwil. Postfach",
    "sg:city":"Wattwil",
    "sg:orig_category":"Architektur U Ingenieurb\u00fcros",
    "sg:phone":"+41 55 211 23 33",
    "sg:postcode":"9630",
    "sg:province":"St. Gallen",
    "wof:name":"Hochuli & Partner Gmbh, B\u00fcro F\u00fcr Architektur Und Landschaftsarchitektur",
    "wof:placetype":"venue"
},
  "geometry": {"coordinates":[8.799535,47.213333],"type":"Point"}
}