{
  "type": "Feature",
  "properties": {
    "addr:full":"Bodenacherstrasse 58 Benglen Z\u00fcrich 8121",
    "addr:housenumber":"58",
    "addr:postcode":"8121",
    "addr:street":"Bodenacherstrasse",
    "iso:country":"CH",
    "sg:address":"Bodenacherstrasse 58",
    "sg:city":"Benglen",
    "sg:orig_category":"Betrieb von Taxis G\u00fcterbef\u00f6rderung im Strassenverkehr",
    "sg:phone":"+41 18251647",
    "sg:postcode":"8121",
    "sg:province":"Z\u00fcrich",
    "wof:name":"Wetter Reto Limousine Service",
    "wof:placetype":"venue"
},
  "geometry": {"coordinates":[8.638617,47.360779],"type":"Point"}
}