{
  "type": "Feature",
  "properties": {
    "iso:country":"CH",
    "sg:address":"Blatten",
    "sg:city":"Iseltwald",
    "sg:orig_category":"Abwasserreinigung",
    "sg:phone":"+41 33 845 13 73",
    "sg:postcode":"3807",
    "sg:province":"Bern",
    "wof:name":"Abwasserreinigungsanlage",
    "wof:placetype":"venue"
},
  "geometry": {"coordinates":[7.958244,46.707668],"type":"Point"}
}