{
  "type": "Feature",
  "properties": {
    "iso:country":"CH",
    "sg:address":"Oberwilerstrasse 5",
    "sg:city":"Hettlingen",
    "sg:orig_category":"HERSTELLUNG VON GER\u00c4TEN DER ELEKTRIZIT\u00c4TSERZEUGUNG, -VERTEILUNG U.\u00c4",
    "sg:phone":"+41 55 282 34 00",
    "sg:postcode":"8442",
    "sg:province":"Z\u00fcrich",
    "wof:name":"K\u00e4lin & Fischer Ag Elektrotechnische Bauteile",
    "wof:placetype":"venue"
},
  "geometry": {"coordinates":[8.9213428497,47.2407341003],"type":"Point"}
}