{
  "type": "Feature",
  "properties": {
    "addr:full":"Route Des Cernys 3 Ballaigues Vaud 1338",
    "addr:housenumber":"3",
    "addr:postcode":"1338",
    "addr:street":"Route Des Cernys",
    "iso:country":"CH",
    "sg:address":"Route Des Cernys 3",
    "sg:city":"Ballaigues",
    "sg:classifiers":[
        {
            "category":"Real Estate",
            "subcategory":"Architect",
            "type":"Services"
        }
    ],
    "sg:phone":"+41 32 924 50 10",
    "sg:postcode":"1338",
    "sg:province":"Vaud",
    "sg:tags":[
        "dial",
        "made",
        "watch",
        "stone",
        "clock-faces",
        "precious"
    ],
    "wof:name":"Fehr & Cie S.a.",
    "wof:placetype":"venue"
},
  "geometry": {"coordinates":[6.823983,47.093418],"type":"Point"}
}