{
  "type": "Feature",
  "properties": {
    "iso:country":"CH",
    "sg:address":"Kirschbaumweg 8",
    "sg:city":"Ipsach",
    "sg:orig_category":"Grosshandel mit Textilien",
    "sg:phone":"+41 32 331 93 82",
    "sg:postcode":"2563",
    "sg:province":"Bern",
    "wof:name":"Fran\u00e7ois E.",
    "wof:placetype":"venue"
},
  "geometry": {"coordinates":[7.239590168,47.1174125671],"type":"Point"}
}