{
  "type": "Feature",
  "properties": {
    "iso:country":"CH",
    "sg:address":"Z\u00fcrcherstr. 61 8840 Einsiedeln. Postfach 25",
    "sg:city":"Einsiedeln",
    "sg:orig_category":"Pensionskassen",
    "sg:postcode":"8840",
    "sg:province":"Schwyz",
    "wof:name":"Personalvorsorgestiftung Indermaur Ingrid",
    "wof:placetype":"venue"
},
  "geometry": {"coordinates":[8.7460803986,47.1273155212],"type":"Point"}
}