{
  "type": "Feature",
  "properties": {
    "iso:country":"CH",
    "sg:address":"Via San Gottardo",
    "sg:city":"Airolo",
    "sg:orig_category":"Fahrschulen, Flugschulen",
    "sg:phone":"+41 79 421 92 92",
    "sg:postcode":"6780",
    "sg:province":"Ticino",
    "wof:name":"Augusto Beffa Autoscuola",
    "wof:placetype":"venue"
},
  "geometry": {"coordinates":[8.6045045853,46.5296478271],"type":"Point"}
}