{
  "type": "Feature",
  "properties": {
    "iso:country":"CH",
    "sg:address":"Route Gravi\u00e8re",
    "sg:city":"Penthaz",
    "sg:orig_category":"Detailhandel mit M\u00f6beln Innenarchitekturb\u00fcros",
    "sg:phone":"+41 21 862 72 34",
    "sg:postcode":"1303",
    "sg:province":"Vaud",
    "wof:name":"Objets & Fonctions Sa",
    "wof:placetype":"venue"
},
  "geometry": {"coordinates":[6.5383901596,46.5959358215],"type":"Point"}
}