{
  "type": "Feature",
  "properties": {
    "iso:country":"CH",
    "sg:address":"Konsumstrasse 4",
    "sg:city":"B\u00fctschwil",
    "sg:orig_category":"Elektrizit\u00e4tsversorgung",
    "sg:phone":"+41 71 980 06 40",
    "sg:postcode":"9606",
    "sg:province":"St. Gallen",
    "wof:name":"Elektrizit\u00e4ts-& Wasserversorgung B\u00fctschwil",
    "wof:placetype":"venue"
},
  "geometry": {"coordinates":[9.0719823837,47.358997345],"type":"Point"}
}