{
  "type": "Feature",
  "properties": {
    "iso:country":"CH",
    "sg:address":"Chavannes Route De 55 1007 Lausanne. Postfach",
    "sg:city":"Lausanne",
    "sg:orig_category":"Reinigungsgewerbe",
    "sg:phone":"+41 21 625 99 30",
    "sg:postcode":"1003",
    "sg:province":"Vaud",
    "wof:name":"Ammann Pierre. Comm., R\u00e9paration Et Entretien De Distributeurs De Carburants.",
    "wof:placetype":"venue"
},
  "geometry": {"coordinates":[6.5931048393,46.522819519],"type":"Point"}
}