{
  "type": "Feature",
  "properties": {
    "iso:country":"CH",
    "sg:address":"Langackerstrasse 4",
    "sg:city":"Hettlingen",
    "sg:orig_category":"Geb\u00e4ude, Wohnungsreinigung",
    "sg:phone":"+41 52 316 19 22",
    "sg:postcode":"8442",
    "sg:province":"Z\u00fcrich",
    "wof:name":"Ren\u00e9 Kr\u00fcsi Reinigungsunternehmen",
    "wof:placetype":"venue"
},
  "geometry": {"coordinates":[8.698969841,47.5454216003],"type":"Point"}
}