{
  "type": "Feature",
  "properties": {
    "iso:country":"CH",
    "sg:address":"Kirchweg 18",
    "sg:city":"Glarus",
    "sg:orig_category":"Non-Classified Establishments",
    "sg:postcode":"8750",
    "sg:province":"Glarus",
    "wof:name":"Hotel Freihof, Aepli",
    "wof:placetype":"venue"
},
  "geometry": {"coordinates":[9.0702733994,47.0388031006],"type":"Point"}
}