{
  "type": "Feature",
  "properties": {
    "iso:country":"CH",
    "sg:address":"Breiti",
    "sg:city":"G\u00f6schenen",
    "sg:orig_category":"Erschliessung von Grundst\u00fccken",
    "sg:postcode":"6487",
    "sg:province":"Uri",
    "wof:name":"Baugenossenschaft Dammablick",
    "wof:placetype":"venue"
},
  "geometry": {"coordinates":[8.5863666534,46.6689224243],"type":"Point"}
}