{
  "type": "Feature",
  "properties": {
    "addr:full":"Chemin Du Rieu 18 Gen\u00e8ve Gen\u00e8ve 1208",
    "addr:housenumber":"18",
    "addr:postcode":"1208",
    "addr:street":"Chemin Du Rieu",
    "iso:country":"CH",
    "sg:address":"Chemin Du Rieu 18",
    "sg:city":"Gen\u00e8ve",
    "sg:orig_category":"Alters U Hinterlassenenversicherung AHV, Invalidenversicherung IV, Arbeitslosenversicherung ALV",
    "sg:phone":"+41 22 347 63 33",
    "sg:postcode":"1208",
    "sg:province":"Gen\u00e8ve",
    "wof:name":"Caisse D'allocation Familiales Des Boulangers",
    "wof:placetype":"venue"
},
  "geometry": {"coordinates":[6.165257,46.195267],"type":"Point"}
}