{
  "type": "Feature",
  "properties": {
    "iso:country":"CH",
    "sg:address":"Weissbadstrasse 26",
    "sg:city":"Appenzell",
    "sg:orig_category":"Handel mit Motorr\u00e4dern, Teilen U Zubeh\u00f6r Instandhaltung U Reparatur von Automobilen Instandhaltung U",
    "sg:phone":"+41 71 787 12 89",
    "sg:postcode":"9050",
    "sg:province":"Appenzell Innerhoden",
    "wof:name":"Streule & D\u00f6rig",
    "wof:placetype":"venue"
},
  "geometry": {"coordinates":[9.412115097,47.3291473389],"type":"Point"}
}