{
  "type": "Feature",
  "properties": {
    "iso:country":"CH",
    "sg:address":"Schmiedhof 4",
    "sg:city":"Ebikon",
    "sg:orig_category":"Verlegen von Fliesen U Platten",
    "sg:phone":"+41 41 440 84 34",
    "sg:postcode":"6030",
    "sg:province":"Luzern",
    "wof:name":"Urs K\u00fcnzle Plattengesch\u00e4ft & Chemin\u00e9ebau",
    "wof:placetype":"venue"
},
  "geometry": {"coordinates":[8.3332529068,47.0757675171],"type":"Point"}
}