{
  "type": "Feature",
  "properties": {
    "iso:country":"CH",
    "sg:address":"Schulhausstrasse 27",
    "sg:city":"D\u00fcbendorf",
    "sg:orig_category":"Interessenvertretungen",
    "sg:postcode":"8600",
    "sg:province":"Z\u00fcrich",
    "wof:name":"Genossenschaft Oberheimet D\u00fcbendorf",
    "wof:placetype":"venue"
},
  "geometry": {"coordinates":[8.6223096848,47.3954353333],"type":"Point"}
}