{
  "type": "Feature",
  "properties": {
    "iso:country":"CH",
    "sg:address":"Neubadstrasse 81",
    "sg:city":"Basel",
    "sg:orig_category":"Kauf U Verkauf von Immobilien auf eigene Rechnung Verwaltung von Immobilien",
    "sg:phone":"+41 61 331 62 68",
    "sg:postcode":"4000",
    "sg:province":"Basel-Stadt",
    "wof:name":"Pfeiffer Verwaltungen Gmbh",
    "wof:placetype":"venue"
},
  "geometry": {"coordinates":[7.5697832108,47.5488586426],"type":"Point"}
}