{
  "type": "Feature",
  "properties": {
    "iso:country":"CH",
    "sg:address":"Im L\u00e4deli Chalet Campanula 3778 Sch\u00f6nried. Postfach",
    "sg:city":"Sch\u00f6nried",
    "sg:orig_category":"Interessenvertretungen",
    "sg:postcode":"3778",
    "sg:province":"Bern",
    "wof:name":"Weggenossenschaft Innere Bleiken, Lenk I.s.",
    "wof:placetype":"venue"
},
  "geometry": {"coordinates":[7.46434021,46.4307403564],"type":"Point"}
}