{
  "type": "Feature",
  "properties": {
    "iso:country":"CH",
    "sg:address":"Dorfstrasse 79 8906 Bonstetten. Postfach",
    "sg:city":"Bonstetten",
    "sg:orig_category":"Gesundheitswesen",
    "sg:phone":"+41 19351981",
    "sg:postcode":"8906",
    "sg:province":"Z\u00fcrich",
    "wof:name":"Priv\u00c9 Organisation F\u00fcr Gesundheits Und Krankenpflege, Ferrazzini E.",
    "wof:placetype":"venue"
},
  "geometry": {"coordinates":[8.7556886673,47.3044166565],"type":"Point"}
}