{
  "type": "Feature",
  "properties": {
    "iso:country":"CH",
    "sg:address":"Marktgasse 11",
    "sg:city":"Baar",
    "sg:classifiers":[
        {
            "category":"Banks & Credit Unions",
            "subcategory":"Bank",
            "type":"Services"
        }
    ],
    "sg:phone":"+41 61 761 34 20",
    "sg:postcode":"6340",
    "sg:province":"Zug",
    "wof:name":"Raiffeisenbank Baerschwil",
    "wof:placetype":"venue"
},
  "geometry": {"coordinates":[7.536927,47.210541],"type":"Point"}
}