{
  "type": "Feature",
  "properties": {
    "iso:country":"CH",
    "sg:address":"Rue Du Maupas 42",
    "sg:city":"Lausanne",
    "sg:orig_category":"Detailhandel mit Geschenkartikeln U Souvenirs",
    "sg:phone":"+41 55 210 75 25",
    "sg:postcode":"1004",
    "sg:province":"Vaud",
    "wof:name":"Trudi Henggeler Delfin Kunstgewerbe",
    "wof:placetype":"venue"
},
  "geometry": {"coordinates":[8.8179550171,47.2277030945],"type":"Point"}
}