{
  "type": "Feature",
  "properties": {
    "iso:country":"CH",
    "sg:address":"R\u00fctihof",
    "sg:city":"Herrliberg",
    "sg:orig_category":"Mit Sport verbundene T\u00e4tigkeiten",
    "sg:phone":"+41 19152165",
    "sg:postcode":"8704",
    "sg:province":"Z\u00fcrich",
    "wof:name":"Hugo Schmutz Reitschule",
    "wof:placetype":"venue"
},
  "geometry": {"coordinates":[8.6038742065,47.2923088074],"type":"Point"}
}