{
  "type": "Feature",
  "properties": {
    "iso:country":"CH",
    "sg:address":"Haldenstrasse 61 8708 M\u00e4nnedorf. Postfach",
    "sg:city":"M\u00e4nnedorf",
    "sg:orig_category":"Unclassifiable Establishments",
    "sg:postcode":"8708",
    "sg:province":"Z\u00fcrich",
    "wof:name":"Marktpirat Guglielmetti + Co",
    "wof:placetype":"venue"
},
  "geometry": {"coordinates":[8.7012748718,47.2552032471],"type":"Point"}
}