{
  "type": "Feature",
  "properties": {
    "iso:country":"CH",
    "sg:address":"Fin Chemin De La 2",
    "sg:city":"Mies-tannay",
    "sg:orig_category":"Korrespondenz U Nachrichtenb\u00fcros, selbst\u00e4ndige Journalisten",
    "sg:phone":"+41 79 455 83 66",
    "sg:postcode":"1295",
    "sg:province":"Vaud",
    "wof:name":"Objectif Medias, Koehn Odile",
    "wof:placetype":"venue"
},
  "geometry": {"coordinates":[6.1724500656,46.3060684204],"type":"Point"}
}