{
  "type": "Feature",
  "properties": {
    "iso:country":"CH",
    "sg:address":"Village Rue Du 38",
    "sg:city":"Corseaux",
    "sg:orig_category":"Reiseb\u00fcros U Reiseveranstalter",
    "sg:phone":"+41 21 923 67 41",
    "sg:postcode":"1802",
    "sg:province":"Vaud",
    "wof:name":"B & B Switzerland, Neyroud-detraz Nicole",
    "wof:placetype":"venue"
},
  "geometry": {"coordinates":[6.8311800957,46.4719734192],"type":"Point"}
}