{
  "type": "Feature",
  "properties": {
    "addr:full":"Boniweg 12 Pratteln Basel-Landschaft 4133",
    "addr:housenumber":"12",
    "addr:postcode":"4133",
    "addr:street":"Boniweg",
    "iso:country":"CH",
    "sg:address":"Boniweg 12",
    "sg:city":"Pratteln",
    "sg:orig_category":"Detailhandel mit Beleuchtungs U Haushaltsgegenst\u00e4nden Detailhandel mit elektrischen Haushalts-,Radio",
    "sg:phone":"+41 79 658 03 69",
    "sg:postcode":"4133",
    "sg:province":"Basel-Landschaft",
    "wof:name":"Bhs Bernhard Haushaltapparate Service",
    "wof:placetype":"venue"
},
  "geometry": {"coordinates":[7.713983,47.517334],"type":"Point"}
}