{
  "type": "Feature",
  "properties": {
    "iso:country":"CH",
    "sg:address":"Alpli",
    "sg:city":"R\u00fceterswil",
    "sg:orig_category":"Abbruch U Sprenggewerbe, Erdbewegungsarbeiten Erdbewegungsarbeiten",
    "sg:phone":"+41 27 398 35 66",
    "sg:postcode":"8735",
    "sg:province":"St. Gallen",
    "wof:name":"Jean Christian",
    "wof:placetype":"venue"
},
  "geometry": {"coordinates":[7.406825,46.276783],"type":"Point"}
}