{
  "type": "Feature",
  "properties": {
    "iso:country":"CH",
    "sg:address":"Via Motta 14",
    "sg:city":"Biasca",
    "sg:orig_category":"Grosshandel mit Bekleidung Herstellung von Sportger\u00e4ten",
    "sg:phone":"+41 81 410 23 00",
    "sg:postcode":"6710",
    "sg:province":"Ticino",
    "wof:name":"K2 Sports Ag Snowboard In-line Skates",
    "wof:placetype":"venue"
},
  "geometry": {"coordinates":[9.8754816055,46.8837432861],"type":"Point"}
}