{
  "type": "Feature",
  "properties": {
    "iso:country":"CH",
    "sg:address":"Sonnmattstrasse 16",
    "sg:city":"Neuenkirch",
    "sg:orig_category":"Non-Classified Establishments",
    "sg:postcode":"6206",
    "sg:province":"Luzern",
    "wof:name":"Elt-swiss Gmbh",
    "wof:placetype":"venue"
},
  "geometry": {"coordinates":[8.2208967209,47.0966262817],"type":"Point"}
}