{
  "type": "Feature",
  "properties": {
    "iso:country":"CH",
    "sg:address":"Via Enrico Dunant 2",
    "sg:city":"Chiasso",
    "sg:orig_category":"Landesverteidigung, Sozialversicherung \u00d6ffentliche Verwaltung",
    "sg:phone":"+41 91 695 09 62",
    "sg:postcode":"6830",
    "sg:province":"Ticino",
    "wof:name":"Centro Di Protezione Civile Di Chiasso",
    "wof:placetype":"venue"
},
  "geometry": {"coordinates":[9.028008461,45.8347206116],"type":"Point"}
}