{
  "type": "Feature",
  "properties": {
    "iso:country":"CH",
    "sg:address":"Ohringerstrasse 111",
    "sg:city":"Seuzach",
    "sg:orig_category":"Herstellung von \u00d6fen U Brennern Verlegen von Fliesen U Platten",
    "sg:phone":"+41 52 335 30 23",
    "sg:postcode":"8472",
    "sg:province":"Z\u00fcrich",
    "wof:name":"Bula Emil, Ofen Und Chemin\u00e9ebau, Plattenbel\u00e4ge.",
    "wof:placetype":"venue"
},
  "geometry": {"coordinates":[8.7210016251,47.5353355408],"type":"Point"}
}