{
  "type": "Feature",
  "properties": {
    "iso:country":"CH",
    "sg:address":"Milieu Rue Du 20",
    "sg:city":"Biel/bienne",
    "sg:orig_category":"Sonstiger Grosshandel",
    "sg:phone":"+41 12014090",
    "sg:postcode":"2502",
    "sg:province":"Bern",
    "wof:name":"Ts Trend Ag",
    "wof:placetype":"venue"
},
  "geometry": {"coordinates":[7.2503871918,47.1416397095],"type":"Point"}
}