{
  "type": "Feature",
  "properties": {
    "iso:country":"CH",
    "sg:address":"Rietstrasse 44 8702 Zollikon. Postfach",
    "sg:city":"Zollikon",
    "sg:orig_category":"Bau U Wohngenossenschaften",
    "sg:phone":"+41 55 241 21 27",
    "sg:postcode":"8702",
    "sg:province":"Z\u00fcrich",
    "wof:name":"Neue Baugenossenschaft R\u00fcti",
    "wof:placetype":"venue"
},
  "geometry": {"coordinates":[8.869015,47.254108],"type":"Point"}
}