{
  "type": "Feature",
  "properties": {
    "iso:country":"CH",
    "sg:address":"Sternenhaldenstr. 13",
    "sg:city":"St\u00e4fa",
    "sg:classifiers":[
        {
            "category":"Banks & Credit Unions",
            "subcategory":"Bank",
            "type":"Services"
        }
    ],
    "sg:phone":"+41 19263550",
    "sg:postcode":"8712",
    "sg:province":"Z\u00fcrich",
    "wof:name":"Rentenanstalt Swiss Life",
    "wof:placetype":"venue"
},
  "geometry": {"coordinates":[8.737337,47.236069],"type":"Point"}
}