{
  "type": "Feature",
  "properties": {
    "iso:country":"CH",
    "sg:address":"Route De Rolle 38 1162 St-prex Case Postale 45",
    "sg:city":"St-prex",
    "sg:orig_category":"Detailhandel mit Blumen U Pflanzen Gartenbau",
    "sg:phone":"+41 21 806 10 86",
    "sg:postcode":"1162",
    "sg:province":"Vaud",
    "wof:name":"Marzoli Josette, Fleurs",
    "wof:placetype":"venue"
},
  "geometry": {"coordinates":[6.449126,46.478542],"type":"Point"}
}