{
  "type": "Feature",
  "properties": {
    "iso:country":"CH",
    "sg:address":"Les Briesses 3971 Chermignon. Postfach",
    "sg:city":"Lens",
    "sg:orig_category":"Stukkateurgewerbe, Gipserei U Verputzerei",
    "sg:postcode":"1978",
    "sg:province":"Valais",
    "wof:name":"Savoy Michel",
    "wof:placetype":"venue"
},
  "geometry": {"coordinates":[7.4752230644,46.2944602966],"type":"Point"}
}