{
  "type": "Feature",
  "properties": {
    "iso:country":"CH",
    "sg:address":"Rue De Gruy\u00e8res 28",
    "sg:city":"Bulle",
    "sg:orig_category":"Drogerien Parf\u00fcmerien U sonstiger Detailhandel mit kosmetischen Artikeln U K\u00f6rperpflegemitteln",
    "sg:phone":"+41 26 912 71 77",
    "sg:postcode":"1630",
    "sg:province":"Fribourg",
    "wof:name":"Droguerie Gougler Y.",
    "wof:placetype":"venue"
},
  "geometry": {"coordinates":[7.0571260452,46.616065979],"type":"Point"}
}