{
  "type": "Feature",
  "properties": {
    "addr:full":"Ruelle Du Couchant 9 Gen\u00e8ve Gen\u00e8ve 1207",
    "addr:housenumber":"9",
    "addr:postcode":"1207",
    "addr:street":"Ruelle Du Couchant",
    "iso:country":"CH",
    "sg:address":"Ruelle Du Couchant 9",
    "sg:city":"Gen\u00e8ve",
    "sg:orig_category":"Arztpraxen",
    "sg:phone":"+41 22 786 60 56",
    "sg:postcode":"1207",
    "sg:province":"Gen\u00e8ve",
    "wof:name":"Dr M\u00e9d. Christine Boccard M\u00e9decin Sp\u00e9cialiste Fmh",
    "wof:placetype":"venue"
},
  "geometry": {"coordinates":[6.156944,46.200008],"type":"Point"}
}