{
  "type": "Feature",
  "properties": {
    "iso:country":"CH",
    "sg:address":"Dorfstrasse 56",
    "sg:city":"Dintikon",
    "sg:orig_category":"Autogaragen",
    "sg:phone":"+41 56 624 28 68",
    "sg:postcode":"5606",
    "sg:province":"Aargau",
    "wof:name":"Hans Russer Garage",
    "wof:placetype":"venue"
},
  "geometry": {"coordinates":[8.230261,47.367878],"type":"Point"}
}