{
  "type": "Feature",
  "properties": {
    "iso:country":"CH",
    "sg:address":"Seefeldstrasse 4",
    "sg:city":"Kreuzlingen",
    "sg:orig_category":"Grosshandel mit Holz U Baustoffen",
    "sg:phone":"+41 62 772 09 71",
    "sg:postcode":"8280",
    "sg:province":"Thurgau",
    "wof:name":"Bauland Abholmarkt Gmbh",
    "wof:placetype":"venue"
},
  "geometry": {"coordinates":[8.180018425,47.2642021179],"type":"Point"}
}