{
  "type": "Feature",
  "properties": {
    "iso:country":"CH",
    "sg:address":"Badenerstrasse 694 8048 Z\u00fcrich. Postfach 1900",
    "sg:city":"Z\u00fcrich",
    "sg:orig_category":"Versicherungen Generalagenturen",
    "sg:phone":"+41 41 249 99 50",
    "sg:postcode":"8048",
    "sg:province":"Z\u00fcrich",
    "wof:name":"Elvia Versicherungen Schadenzentrum Innerschweiz",
    "wof:placetype":"venue"
},
  "geometry": {"coordinates":[8.3036851883,47.0447731018],"type":"Point"}
}