{
  "type": "Feature",
  "properties": {
    "iso:country":"CH",
    "sg:address":"Wellhauserweg 33",
    "sg:city":"Frauenfeld",
    "sg:orig_category":"Detektivb\u00fcros U \u00dcberwachung",
    "sg:phone":"+41 52 721 30 74",
    "sg:postcode":"8500",
    "sg:province":"Thurgau",
    "wof:name":"Atlas Security Gmbh",
    "wof:placetype":"venue"
},
  "geometry": {"coordinates":[8.9156799316,47.5650482178],"type":"Point"}
}