{
  "type": "Feature",
  "properties": {
    "iso:country":"CH",
    "sg:address":"Hagenholzstrasse 113 8050 Z\u00fcrich. Postfach",
    "sg:city":"Z\u00fcrich",
    "sg:orig_category":"Herstellung von Frischmilchprodukten Verarbeitung von Milch",
    "sg:phone":"+41 18097979",
    "sg:postcode":"8050",
    "sg:province":"Z\u00fcrich",
    "wof:name":"Bischofberger Ag",
    "wof:placetype":"venue"
},
  "geometry": {"coordinates":[8.5623598099,47.4153175354],"type":"Point"}
}