{
  "type": "Feature",
  "properties": {
    "iso:country":"CH",
    "sg:address":"Untere Gasse 2",
    "sg:city":"Interlaken",
    "sg:orig_category":"RESTAURANTS: TEA-ROOMS",
    "sg:phone":"+41 33 822 86 89",
    "sg:postcode":"3800",
    "sg:province":"Bern",
    "wof:name":"Jordi-gertsch Hanspeter",
    "wof:placetype":"venue"
},
  "geometry": {"coordinates":[7.8669848442,46.6898155212],"type":"Point"}
}