{
  "type": "Feature",
  "properties": {
    "iso:country":"CH",
    "sg:address":"Rte De Beaumont 1700 Fribourg Case Postale 952",
    "sg:city":"Freiburg",
    "sg:orig_category":"Vermietung U Verpachtung von eigenen Immobilien",
    "sg:postcode":"1700",
    "sg:province":"Fribourg",
    "wof:name":"Mardel Sa.",
    "wof:placetype":"venue"
},
  "geometry": {"coordinates":[7.1440691948,46.7960510254],"type":"Point"}
}