{
  "type": "Feature",
  "properties": {
    "addr:full":"Rue Centrale Dor\u00e9naz Valais 1905",
    "addr:postcode":"1905",
    "addr:street":"Rue Centrale",
    "iso:country":"CH",
    "sg:address":"Rue Centrale",
    "sg:city":"Dor\u00e9naz",
    "sg:orig_category":"Detailhandel mit Blumen U Pflanzen",
    "sg:postcode":"1905",
    "sg:province":"Valais",
    "wof:name":"Anne-chantal Biollay Mag.de Fleurs Jardin De L'ille",
    "wof:placetype":"venue"
},
  "geometry": {"coordinates":[7.04229,46.1488],"type":"Point"}
}