{
  "type": "Feature",
  "properties": {
    "iso:country":"CH",
    "sg:address":"Zimmergasse 17 8008 Z\u00fcrich. Postfach",
    "sg:city":"Z\u00fcrich",
    "sg:orig_category":"Interessenvertretungen",
    "sg:postcode":"8001",
    "sg:province":"Z\u00fcrich",
    "wof:name":"Swicomp Verband Der Edv-generalunternehmen",
    "wof:placetype":"venue"
},
  "geometry": {"coordinates":[8.3402223587,47.3441047668],"type":"Point"}
}