{
  "type": "Feature",
  "properties": {
    "iso:country":"CH",
    "sg:address":"Rue Du Bois-du-lan 8",
    "sg:city":"Meyrin",
    "sg:orig_category":"Datenverarbeitungsdienste Softwareentwicklung U beratung",
    "sg:phone":"+41 22 785 16 11",
    "sg:postcode":"1217",
    "sg:province":"Gen\u00e8ve",
    "wof:name":"Kaelin Beno",
    "wof:placetype":"venue"
},
  "geometry": {"coordinates":[6.077138,46.22559],"type":"Point"}
}