{
  "type": "Feature",
  "properties": {
    "iso:country":"CH",
    "sg:address":"Place Du Petit-mont 2",
    "sg:city":"Mont-sur-lausanne",
    "sg:orig_category":"Vermittlung von Immobilien Verwaltung von Immobilien",
    "sg:phone":"+41 21 653 16 16",
    "sg:postcode":"1052",
    "sg:province":"Vaud",
    "wof:name":"Schmalz Andr\u00e9, G\u00e9rance & Courtage",
    "wof:placetype":"venue"
},
  "geometry": {"coordinates":[6.636428833,46.5532035828],"type":"Point"}
}