{
  "type": "Feature",
  "properties": {
    "iso:country":"CH",
    "sg:address":"Lorrainestrasse 4",
    "sg:city":"Bern",
    "sg:orig_category":"Sonstige k\u00fcnstlerische U schriftstellerische T\u00e4tigkeiten U Darbietungen",
    "sg:phone":"+41 31 333 10 62",
    "sg:postcode":"3013",
    "sg:province":"Bern",
    "wof:name":"Hans Christian Mathys Restaurierungen",
    "wof:placetype":"venue"
},
  "geometry": {"coordinates":[7.4455499649,46.954864502],"type":"Point"}
}