{
  "type": "Feature",
  "properties": {
    "iso:country":"CH",
    "sg:address":"Rasch\u00e4renstrasse 30",
    "sg:city":"Chur",
    "sg:orig_category":"Betrieb von Sportanlagen Handelsvermittlung U Grosshandel",
    "sg:phone":"+41 55 251 56 00",
    "sg:postcode":"7000",
    "sg:province":"Graubunden",
    "wof:name":"Bms Bowling Marketing Service Ag",
    "wof:placetype":"venue"
},
  "geometry": {"coordinates":[8.8529729843,47.2523727417],"type":"Point"}
}