{
  "type": "Feature",
  "properties": {
    "iso:country":"CH",
    "sg:address":"Talacker 41",
    "sg:city":"Z\u00fcrich",
    "sg:orig_category":"Banks:Trust Companies",
    "sg:phone":"+41 4112121515",
    "sg:postcode":"8039",
    "wof:name":"Mitsubishi Trust, And Banking",
    "wof:placetype":"venue"
},
  "geometry": {"coordinates":[8.534548,47.37236],"type":"Point"}
}