{
  "type": "Feature",
  "properties": {
    "iso:country":"CH",
    "sg:address":"Dapples Avenue 9",
    "sg:city":"Lausanne",
    "sg:orig_category":"Dienstleistungen von Beteiligungsgesellschaften",
    "sg:phone":"+41 32 757 13 43",
    "sg:postcode":"1006",
    "sg:province":"Vaud",
    "wof:name":"Lcd Gestion, Clottu Raymond",
    "wof:placetype":"venue"
},
  "geometry": {"coordinates":[7.0167741776,47.0387878418],"type":"Point"}
}