{
  "type": "Feature",
  "properties": {
    "iso:country":"CH",
    "sg:address":"Theiligerstrasse 60",
    "sg:city":"Weisslingen",
    "sg:orig_category":"Sonstiger Grosshandel",
    "sg:postcode":"8484",
    "sg:province":"Z\u00fcrich",
    "wof:name":"Peter Caprez",
    "wof:placetype":"venue"
},
  "geometry": {"coordinates":[8.7674856186,47.4199981689],"type":"Point"}
}