{
  "type": "Feature",
  "properties": {
    "addr:full":"Im Leeacher 20 Hinteregg Z\u00fcrich 8132",
    "addr:housenumber":"20",
    "addr:postcode":"8132",
    "addr:street":"Im Leeacher",
    "iso:country":"CH",
    "sg:address":"Im Leeacher 20",
    "sg:city":"Hinteregg",
    "sg:orig_category":"Allgemeiner Hoch U Tiefbau Hoch U Tiefbau",
    "sg:phone":"+41 19842594",
    "sg:postcode":"8132",
    "sg:province":"Z\u00fcrich",
    "wof:name":"Baugesch\u00e4ft Meier Ag",
    "wof:placetype":"venue"
},
  "geometry": {"coordinates":[8.681862,47.306435],"type":"Point"}
}