{
  "type": "Feature",
  "properties": {
    "iso:country":"CH",
    "sg:address":"Eichenweg 1",
    "sg:city":"Liestal",
    "sg:orig_category":"Herstellung von Metallerzeugnissen ohne Maschinenbau Herstellung von sonstigen Maschinen f\u00fcr unspezi",
    "sg:phone":"+41 61 901 87 47",
    "sg:postcode":"4410",
    "sg:province":"Basel-Landschaft",
    "wof:name":"Greub + Co Ag",
    "wof:placetype":"venue"
},
  "geometry": {"coordinates":[7.7274799347,47.4909362793],"type":"Point"}
}