{
  "type": "Feature",
  "properties": {
    "addr:full":"Etraz Rue 3 1003 Lausanne. Postfach Lausanne Vaud 1003",
    "addr:housenumber":"3",
    "addr:postcode":"1003;postfach;1003",
    "addr:street":"Rue",
    "iso:country":"CH",
    "sg:address":"Etraz Rue 3 1003 Lausanne. Postfach",
    "sg:city":"Lausanne",
    "sg:orig_category":"Detailhandel mit Antiquit\u00e4ten U Gebrauchtwaren in Verkaufsr\u00e4umen",
    "sg:postcode":"1003",
    "sg:province":"Vaud",
    "wof:name":"Au Petit Versailles, Haab Ruth Antiquit\u00e9s, Objets D'art, Bijoux Anciens, Etc.; Comm.",
    "wof:placetype":"venue"
},
  "geometry": {"coordinates":[6.638299,46.519527],"type":"Point"}
}