{
  "type": "Feature",
  "properties": {
    "iso:country":"CH",
    "sg:address":"Chesa Diavolezza",
    "sg:city":"Pontresina",
    "sg:orig_category":"Bauschreinerei Herstellung von Konstruktionsteilen, Fertigbauteilen U Ausbauelementen aus Holz",
    "sg:phone":"+41 81 842 65 05",
    "sg:postcode":"7504",
    "sg:province":"Graubunden",
    "wof:name":"Conradin Schwab Bau-& M\u00f6belschreinerei",
    "wof:placetype":"venue"
},
  "geometry": {"coordinates":[9.90466,46.489014],"type":"Point"}
}