{
  "type": "Feature",
  "properties": {
    "iso:country":"CH",
    "sg:address":"Friedenstrasse 2",
    "sg:city":"Luzern",
    "sg:classifiers":[
        {
            "category":"Restaurant",
            "type":"Food & Drink"
        }
    ],
    "sg:phone":"+41 41 410 33 20",
    "sg:postcode":"6004",
    "sg:province":"Luzern",
    "sg:tags":[
        "tea-rooms",
        "restaurants"
    ],
    "wof:name":"Sps Restaurant Und Reisen Ag",
    "wof:placetype":"venue"
},
  "geometry": {"coordinates":[8.3107566833,47.0562782288],"type":"Point"}
}