{
  "type": "Feature",
  "properties": {
    "iso:country":"CH",
    "sg:address":"Rue Des Pinsons 8",
    "sg:city":"Gorgier",
    "sg:orig_category":"Non-Classified Establishments",
    "sg:phone":"+41 32 730 37 87",
    "sg:postcode":"2023",
    "sg:province":"Neuch\u00e2tel",
    "wof:name":"Crefinex Sa",
    "wof:placetype":"venue"
},
  "geometry": {"coordinates":[6.7789988518,46.9015159607],"type":"Point"}
}