{
  "type": "Feature",
  "properties": {
    "iso:country":"CH",
    "sg:address":"Le Ch\u00eane 357",
    "sg:city":"Marsens",
    "sg:orig_category":"Berufsbildende weiterf\u00fchrende Schulen",
    "sg:phone":"+41 26 915 38 29",
    "sg:postcode":"1633",
    "sg:province":"Fribourg",
    "wof:name":"Ecole De Mannequins Unic",
    "wof:placetype":"venue"
},
  "geometry": {"coordinates":[7.06,46.65749],"type":"Point"}
}