{
  "type": "Feature",
  "properties": {
    "iso:country":"CH",
    "sg:address":"Lorzenweidstr. 105 6330 Cham. Postfach",
    "sg:city":"Hagendorn",
    "sg:orig_category":"RESTAURANTS: TEA-ROOMS",
    "sg:phone":"+41 34 402 49 19",
    "sg:postcode":"6332",
    "sg:province":"Zug",
    "wof:name":"Ramseier B.",
    "wof:placetype":"venue"
},
  "geometry": {"coordinates":[7.757589817,46.9491271973],"type":"Point"}
}