{
  "type": "Feature",
  "properties": {
    "iso:country":"CH",
    "sg:address":"Kantonsstrasse 63 3930 Visp Case Postale 326",
    "sg:city":"Visp",
    "sg:orig_category":"Herstellung von Uhren",
    "sg:phone":"+41 61 913 06 10",
    "sg:postcode":"3930",
    "sg:province":"Valais",
    "wof:name":"Acol Gmbh",
    "wof:placetype":"venue"
},
  "geometry": {"coordinates":[7.8703250885,47.3448562622],"type":"Point"}
}