{
  "type": "Feature",
  "properties": {
    "iso:country":"CH",
    "sg:address":"1772",
    "sg:city":"Grolley",
    "sg:orig_category":"Vereine Musik/Blasmusik",
    "sg:phone":"+41 27 776 23 77",
    "sg:postcode":"1772",
    "sg:province":"Fribourg",
    "wof:name":"St\u00e9 De Musique L'avenir",
    "wof:placetype":"venue"
},
  "geometry": {"coordinates":[7.0707321167,46.8333053589],"type":"Point"}
}