{
  "type": "Feature",
  "properties": {
    "iso:country":"CH",
    "sg:address":"Via Bocarello",
    "sg:city":"Arbedo",
    "sg:orig_category":"Herstellung von Metallkonstruktionen",
    "sg:phone":"+41 91 683 52 03",
    "sg:postcode":"6517",
    "sg:province":"Ticino",
    "wof:name":"Clelio Nessi Costruzioni In Ferro",
    "wof:placetype":"venue"
},
  "geometry": {"coordinates":[9.021905899,45.8488769531],"type":"Point"}
}