{
  "type": "Feature",
  "properties": {
    "iso:country":"CH",
    "sg:address":"Chesa St. Georg",
    "sg:city":"Pontresina",
    "sg:orig_category":"Kauf U Verkauf von Immobilien auf eigene Rechnung",
    "sg:phone":"+41 81 842 82 92",
    "sg:postcode":"7504",
    "sg:province":"Graubunden",
    "wof:name":"Astras Sa",
    "wof:placetype":"venue"
},
  "geometry": {"coordinates":[9.9037094116,46.4937591553],"type":"Point"}
}