{
  "type": "Feature",
  "properties": {
    "iso:country":"CH",
    "sg:address":"Zurigo Via 12",
    "sg:city":"Lugano",
    "sg:orig_category":"Herstellung von sonstigen elektrischen Ausr\u00fcstungen",
    "sg:postcode":"6900",
    "sg:province":"Ticino",
    "wof:name":"R.s. Robotic Suisse Sa",
    "wof:placetype":"venue"
},
  "geometry": {"coordinates":[8.9539909363,46.0120162964],"type":"Point"}
}