{
  "type": "Feature",
  "properties": {
    "iso:country":"CH",
    "sg:address":"Stationsstrasse 1",
    "sg:city":"Samstagern",
    "sg:orig_category":"Detailhandel mit M\u00f6beln M\u00f6belveredelung U restaurierung",
    "sg:phone":"+41 17847318",
    "sg:postcode":"8833",
    "sg:province":"Z\u00fcrich",
    "wof:name":"Jos\u00e9 Garcia Antikschreinerei",
    "wof:placetype":"venue"
},
  "geometry": {"coordinates":[8.6762542725,47.1925354004],"type":"Point"}
}