{
  "type": "Feature",
  "properties": {
    "iso:country":"CH",
    "sg:address":"Le Petit-pr\u00e9",
    "sg:city":"Ch\u00e2teau-d'oex",
    "sg:orig_category":"Allgemeiner Hoch U Tiefbau Innenausbau",
    "sg:phone":"+41 26 924 61 68",
    "sg:postcode":"1837",
    "wof:name":"Chabloz Laurent",
    "wof:placetype":"venue"
},
  "geometry": {"coordinates":[1.570581,45.677967],"type":"Point"}
}