{
  "type": "Feature",
  "properties": {
    "iso:country":"CH",
    "sg:address":"Winzerstrasse 5",
    "sg:city":"Z\u00fcrich",
    "sg:orig_category":"Vermittlung von Immobilien Verwaltung von Immobilien",
    "sg:phone":"+41 71 388 80 50",
    "sg:postcode":"8049",
    "sg:province":"Z\u00fcrich",
    "wof:name":"Mauchle Treuhand Ag",
    "wof:placetype":"venue"
},
  "geometry": {"coordinates":[9.2503061295,47.4162902832],"type":"Point"}
}