{
  "type": "Feature",
  "properties": {
    "iso:country":"CH",
    "sg:address":"Grundstrasse 5",
    "sg:city":"Rotkreuz",
    "sg:orig_category":"Elektrizit\u00e4tsversorgung",
    "sg:phone":"+41 41 790 13 77",
    "sg:postcode":"6343",
    "sg:province":"Zug",
    "wof:name":"St\u00f6ckli Bau\u00fcberwachungen",
    "wof:placetype":"venue"
},
  "geometry": {"coordinates":[8.4295015335,47.1452255249],"type":"Point"}
}