{
  "type": "Feature",
  "properties": {
    "iso:country":"CH",
    "sg:address":"Rue Sainte-marguerite 17",
    "sg:city":"Sion",
    "sg:orig_category":"Detailhandel mit Bekleidung Detailhandel mit Textilien",
    "sg:phone":"+41 27 322 48 42",
    "sg:postcode":"1950",
    "sg:province":"Valais",
    "wof:name":"Walliser Tuch-& Deckenfabrik Ag Fabrikladen",
    "wof:placetype":"venue"
},
  "geometry": {"coordinates":[7.366433,46.229836],"type":"Point"}
}