{
  "type": "Feature",
  "properties": {
    "iso:country":"CH",
    "sg:address":"St. Galler-strasse 79",
    "sg:city":"Winterthur",
    "sg:orig_category":"Geb\u00e4ude, Wohnungsreinigung Reinigungsgewerbe",
    "sg:phone":"+41 52 213 64 76",
    "sg:postcode":"8400",
    "sg:province":"Z\u00fcrich",
    "wof:name":"Gjyke Hykasmoni Reinigungen",
    "wof:placetype":"venue"
},
  "geometry": {"coordinates":[8.7441043854,47.4983444214],"type":"Point"}
}