{
  "type": "Feature",
  "properties": {
    "iso:country":"CH",
    "sg:address":"Quadras",
    "sg:city":"Scuol",
    "sg:orig_category":"Erschliessung von Grundst\u00fccken",
    "sg:postcode":"7550",
    "sg:province":"Graubunden",
    "wof:name":"Wohnbaugenossenschaft Quadras, Scuol",
    "wof:placetype":"venue"
},
  "geometry": {"coordinates":[10.3034067154,46.7971572876],"type":"Point"}
}