{
  "type": "Feature",
  "properties": {
    "iso:country":"CH",
    "sg:address":"Bachd\u00f6rfli 1",
    "sg:city":"N\u00e4fels",
    "sg:orig_category":"Kauf U Verkauf von Immobilien auf eigene Rechnung",
    "sg:phone":"+41 26 660 40 04",
    "sg:postcode":"8752",
    "sg:province":"Glarus",
    "wof:name":"Clos De La Gare Sa",
    "wof:placetype":"venue"
},
  "geometry": {"coordinates":[6.8926100731,46.8147010803],"type":"Point"}
}