{
  "type": "Feature",
  "properties": {
    "iso:country":"CH",
    "sg:address":"Gemeindeverwaltung",
    "sg:city":"R\u00fcderswil",
    "sg:orig_category":"Wasserversorgung",
    "sg:phone":"+41 34 496 73 88",
    "sg:postcode":"3437",
    "sg:province":"Bern",
    "wof:name":"Kanalisationskommission R\u00fcderswil",
    "wof:placetype":"venue"
},
  "geometry": {"coordinates":[7.7185168266,46.98412323],"type":"Point"}
}