{
  "type": "Feature",
  "properties": {
    "iso:country":"CH",
    "sg:address":"Allmendstrasse 148",
    "sg:city":"Rohrbach",
    "sg:orig_category":"Herstellung von Konstruktionsteilen, Fertigbauteilen U Ausbauelementen aus Holz",
    "sg:phone":"+41 79 222 34 78",
    "sg:postcode":"4938",
    "sg:province":"Bern",
    "wof:name":"Hirschi Schreinerei Gmbh",
    "wof:placetype":"venue"
},
  "geometry": {"coordinates":[7.818821907,47.1345062256],"type":"Point"}
}