{
  "type": "Feature",
  "properties": {
    "iso:country":"CH",
    "sg:address":"Adlergartenstrasse 2 6467 Schattdorf. Postfach",
    "sg:city":"Schattdorf",
    "sg:orig_category":"Detailhandel mit Fleisch U Fleischwaren",
    "sg:phone":"+41 41 870 11 40",
    "sg:postcode":"6467",
    "sg:province":"Uri",
    "wof:name":"Erwin Stadler Metzgerei",
    "wof:placetype":"venue"
},
  "geometry": {"coordinates":[8.6547842026,46.8648490906],"type":"Point"}
}