{
  "type": "Feature",
  "properties": {
    "iso:country":"CH",
    "sg:address":"Schrabachstrasse 95b",
    "sg:city":"Schiers",
    "sg:orig_category":"Reiseb\u00fcros U Reiseveranstalter",
    "sg:phone":"+41 81 325 24 44",
    "sg:postcode":"7220",
    "sg:province":"Graubunden",
    "wof:name":"R\u00e4tikon Adventure R. Pingeon",
    "wof:placetype":"venue"
},
  "geometry": {"coordinates":[9.689207077,46.9660949707],"type":"Point"}
}