{
  "type": "Feature",
  "properties": {
    "iso:country":"CH",
    "sg:address":"Planaterrastrasse 8 7000 Chur. Postfach",
    "sg:city":"Chur",
    "sg:orig_category":"G\u00fcterbef\u00f6rderung im Strassenverkehr Reinigungsgewerbe",
    "sg:postcode":"7000",
    "sg:province":"Graubunden",
    "wof:name":"Mani Oeko Reinigung Und Transporte Gmbh Geb\u00e4udereinigungen, Unterhaltsservice Usw",
    "wof:placetype":"venue"
},
  "geometry": {"coordinates":[9.5344047546,46.8504524231],"type":"Point"}
}