{
  "type": "Feature",
  "properties": {
    "iso:country":"CH",
    "sg:address":"Ennetb\u00fcrgerstrasse 53 6374 Buochs. Postfach 420",
    "sg:city":"Buochs",
    "sg:orig_category":"Geb\u00e4ude, Wohnungsreinigung Reinigungsgewerbe",
    "sg:phone":"+41 41 620 72 09",
    "sg:postcode":"6374",
    "sg:province":"Nidwalden",
    "wof:name":"Titlis-reinigung Ag",
    "wof:placetype":"venue"
},
  "geometry": {"coordinates":[8.4152936935,46.9785614014],"type":"Point"}
}