{
  "type": "Feature",
  "properties": {
    "iso:country":"CH",
    "sg:address":"Romanshornerstrasse 30 9302 Kronb\u00fchl. Postfach 176",
    "sg:city":"Kronb\u00fchl",
    "sg:orig_category":"Drogerien",
    "sg:phone":"+41 71 298 40 04",
    "sg:postcode":"9302",
    "wof:name":"Drogerie Martin",
    "wof:placetype":"venue"
},
  "geometry": {"coordinates":[9.3924627304,47.4595413208],"type":"Point"}
}