{
  "type": "Feature",
  "properties": {
    "iso:country":"CH",
    "sg:address":"Alpes Avenue Des 15 1820 Montreux. Postfach",
    "sg:city":"Montreux",
    "sg:classifiers":[
        {
            "category":"Travel",
            "subcategory":"Hotels & Motels",
            "type":"Entertainment"
        }
    ],
    "sg:phone":"+41 21 966 46 46",
    "sg:postcode":"1820",
    "sg:province":"Vaud",
    "sg:tags":[
        "hotels",
        "mit",
        "restaurant"
    ],
    "wof:name":"H\u00f4tel De L'europe Sa",
    "wof:placetype":"venue"
},
  "geometry": {"coordinates":[6.9105057716,46.4316940308],"type":"Point"}
}