{
  "type": "Feature",
  "properties": {
    "iso:country":"CH",
    "sg:address":"Lerberstrasse 33",
    "sg:city":"Bern",
    "sg:orig_category":"Grosshandel mit Nahrungsmitteln, Getr\u00e4nken U Tabakwaren ohne ausgepr\u00e4gten Schwerpunkt",
    "sg:phone":"+41 31 398 24 72",
    "sg:postcode":"3013",
    "sg:province":"Bern",
    "wof:name":"Art & Vita Gmbh",
    "wof:placetype":"venue"
},
  "geometry": {"coordinates":[7.4572257996,46.9513893127],"type":"Point"}
}