{
  "type": "Feature",
  "properties": {
    "iso:country":"CH",
    "sg:address":"Chlusbode",
    "sg:city":"Sch\u00fcpfheim",
    "sg:orig_category":"Gartenbau Landschaftsplanungsb\u00fcros U Gartenarchitekturb\u00fcros",
    "sg:phone":"+41 41 484 16 18",
    "sg:postcode":"6170",
    "sg:province":"Luzern",
    "wof:name":"Bieri, Felder & Co Gartenbau & Landschaftsarch.",
    "wof:placetype":"venue"
},
  "geometry": {"coordinates":[8.0194749832,46.9536094666],"type":"Point"}
}