{
  "type": "Feature",
  "properties": {
    "iso:country":"CH",
    "sg:address":"Monbijoustrasse 39",
    "sg:city":"Bern",
    "sg:orig_category":"Arztpraxen",
    "sg:phone":"+41 31 381 53 53",
    "sg:postcode":"3011",
    "sg:province":"Bern",
    "wof:name":"Dr.med.hans Kr\u00e4uchi Spezialarzt Fmh",
    "wof:placetype":"venue"
},
  "geometry": {"coordinates":[7.436097,46.943207],"type":"Point"}
}