{
  "type": "Feature",
  "properties": {
    "iso:country":"CH",
    "sg:address":"R\u00fctistrasse 6",
    "sg:city":"Zumikon",
    "sg:orig_category":"Handel mit Automobilen Vermietung von Automobilen",
    "sg:phone":"+41 71 223 12 44",
    "sg:postcode":"8126",
    "sg:province":"Z\u00fcrich",
    "wof:name":"Stadtgarage Ag",
    "wof:placetype":"venue"
},
  "geometry": {"coordinates":[9.3715496063,47.4207344055],"type":"Point"}
}