{
  "type": "Feature",
  "properties": {
    "iso:country":"CH",
    "sg:address":"S\u00e4geweg 5",
    "sg:city":"Oberuzwil",
    "sg:orig_category":"Sonstige mit der Informatik verbundene T\u00e4tigkeiten",
    "sg:phone":"+41 71 952 72 11",
    "sg:postcode":"9242",
    "sg:province":"St. Gallen",
    "wof:name":"Mmc M\u00fcller Consulting Gmbh",
    "wof:placetype":"venue"
},
  "geometry": {"coordinates":[9.1215791702,47.4284362793],"type":"Point"}
}