{
  "type": "Feature",
  "properties": {
    "iso:country":"CH",
    "sg:address":"Kerzersstrasse 4",
    "sg:city":"M\u00fcntschemier",
    "sg:orig_category":"Arztpraxen",
    "sg:phone":"+41 32 313 20 77",
    "sg:postcode":"3225",
    "sg:province":"Bern",
    "wof:name":"Dr.med.hans-werner Leibundgut Arzt F.allgemeine Medizin Fmh",
    "wof:placetype":"venue"
},
  "geometry": {"coordinates":[7.147186,46.99551],"type":"Point"}
}