{
  "type": "Feature",
  "properties": {
    "iso:country":"CH",
    "sg:address":"Rietli 181",
    "sg:city":"Triesenberg",
    "sg:orig_category":"Bauschreinerei Innenausbau",
    "sg:phone":"+41 52 319 13 36",
    "sg:postcode":"9497",
    "wof:name":"Werner & Nadine Keller Schreinerei & Innenausbau",
    "wof:placetype":"venue"
},
  "geometry": {"coordinates":[8.656145,47.653748],"type":"Point"}
}