{
  "type": "Feature",
  "properties": {
    "iso:country":"CH",
    "sg:address":"Chilegasse 4",
    "sg:city":"Willisau",
    "sg:orig_category":"Reiseb\u00fcros U Reiseveranstalter",
    "sg:phone":"+41 41 970 11 81",
    "sg:postcode":"6130",
    "sg:province":"Luzern",
    "wof:name":"Noli Reisen + Kredite Qollaku",
    "wof:placetype":"venue"
},
  "geometry": {"coordinates":[7.9916348457,47.1204223633],"type":"Point"}
}