{
  "type": "Feature",
  "properties": {
    "iso:country":"CH",
    "sg:address":"Hauptstrasse 47",
    "sg:city":"Seltisberg",
    "sg:classifiers":[
        {
            "category":"Restaurant",
            "type":"Food & Drink"
        }
    ],
    "sg:phone":"+41 61 911 00 28",
    "sg:postcode":"4411",
    "sg:province":"Basel-Landschaft",
    "wof:name":"Restaurant Sch\u00fctzen",
    "wof:placetype":"venue"
},
  "geometry": {"coordinates":[7.7164912224,47.4592475891],"type":"Point"}
}