{
  "type": "Feature",
  "properties": {
    "iso:country":"CH",
    "sg:address":"Scheidwegstrasse 20",
    "sg:city":"St.gallen",
    "sg:orig_category":"Maler U Glasergewerbe Malerei",
    "sg:phone":"+41 71 245 02 05",
    "sg:postcode":"9000",
    "sg:province":"St. Gallen",
    "wof:name":"Gmeiner Robert",
    "wof:placetype":"venue"
},
  "geometry": {"coordinates":[9.4024333954,47.4344291687],"type":"Point"}
}