{
  "type": "Feature",
  "properties": {
    "iso:country":"CH",
    "sg:address":"Rue Carteret 19",
    "sg:city":"Gen\u00e8ve",
    "sg:orig_category":"Forschung U Entwicklung Patentverwertung",
    "sg:phone":"+41 22 733 73 89",
    "sg:postcode":"1202",
    "sg:province":"Gen\u00e8ve",
    "wof:name":"Innovatech S\u00e0rl Recherche Et D\u00e9velopppement",
    "wof:placetype":"venue"
},
  "geometry": {"coordinates":[6.1333899498,46.2125396729],"type":"Point"}
}