{
  "type": "Feature",
  "properties": {
    "addr:full":"Gerberngasse 5 Bern Bern 3011",
    "addr:housenumber":"5",
    "addr:postcode":"3011",
    "addr:street":"Gerberngasse",
    "iso:country":"CH",
    "sg:address":"Gerberngasse 5",
    "sg:city":"Bern",
    "sg:orig_category":"Detailhandel mit Bekleidung",
    "sg:phone":"+41 31 311 73 11",
    "sg:postcode":"3011",
    "sg:province":"Bern",
    "wof:name":"Mano A Mano Mode Design Boutique",
    "wof:placetype":"venue"
},
  "geometry": {"coordinates":[7.457761,46.948208],"type":"Point"}
}