{
  "type": "Feature",
  "properties": {
    "iso:country":"CH",
    "sg:address":"Place Du Midi 27",
    "sg:city":"Sion",
    "sg:orig_category":"Fussreflexzonenmassage",
    "sg:postcode":"1950",
    "sg:province":"Valais",
    "wof:name":"Atelier La Chrysalide R\u00e9flexologie",
    "wof:placetype":"venue"
},
  "geometry": {"coordinates":[7.3611841202,46.2315940857],"type":"Point"}
}