{
  "type": "Feature",
  "properties": {
    "iso:country":"CH",
    "sg:address":"Birmensdorferstrasse 174 8003 Z\u00fcrich. Postfach",
    "sg:city":"Z\u00fcrich",
    "sg:orig_category":"Reinigungsgewerbe",
    "sg:postcode":"8001",
    "sg:province":"Z\u00fcrich",
    "wof:name":"Da Costa Oliveira A., Geb\u00e4udereinigung",
    "wof:placetype":"venue"
},
  "geometry": {"coordinates":[8.5177755356,47.370639801],"type":"Point"}
}