{
  "type": "Feature",
  "properties": {
    "iso:country":"CH",
    "sg:address":"Schorenstrasse 54",
    "sg:city":"Gwatt",
    "sg:orig_category":"Apparatus, Containers, Tanks, Vessels, And Boilers Of Stainless Steel",
    "sg:phone":"+41 33 336 72 72",
    "sg:postcode":"3645",
    "sg:province":"Bern",
    "wof:name":"Ist-edelstahl-anlagenbau Ag",
    "wof:placetype":"venue"
},
  "geometry": {"coordinates":[7.619981,46.731636],"type":"Point"}
}