{
  "type": "Feature",
  "properties": {
    "iso:country":"CH",
    "sg:address":"Bernhauser Str. 5",
    "sg:city":"Zihlschlacht",
    "sg:classifiers":[
        {
            "category":"Banks & Credit Unions",
            "subcategory":"Bank",
            "type":"Services"
        }
    ],
    "sg:phone":"+41 71 424 29 29",
    "sg:postcode":"8588",
    "sg:province":"Thurgau",
    "wof:name":"Raiffeisenbank",
    "wof:placetype":"venue"
},
  "geometry": {"coordinates":[9.258041,47.521744],"type":"Point"}
}