{
  "type": "Feature",
  "properties": {
    "iso:country":"CH",
    "sg:address":"Milchh\u00fcslistrasse 231",
    "sg:city":"M\u00f6nthal",
    "sg:orig_category":"Wirtschaftspr\u00fcfung, Steuerberatung U Treuhand",
    "sg:phone":"+41 56 290 20 91",
    "sg:postcode":"5237",
    "sg:province":"Aargau",
    "wof:name":"Finoptima, M. Jaderosa",
    "wof:placetype":"venue"
},
  "geometry": {"coordinates":[8.1434335709,47.5186767578],"type":"Point"}
}