{
  "type": "Feature",
  "properties": {
    "iso:country":"CH",
    "sg:address":"Haus Vanello 7250 Klosters. Postfach",
    "sg:city":"Klosters",
    "sg:orig_category":"Reiseb\u00fcros U Reiseveranstalter",
    "sg:postcode":"7250",
    "sg:province":"Graubunden",
    "wof:name":"Ferienwohnungen Pia A. Wunderlin",
    "wof:placetype":"venue"
},
  "geometry": {"coordinates":[9.8801698685,46.8800468445],"type":"Point"}
}