{
  "type": "Feature",
  "properties": {
    "iso:country":"CH",
    "sg:address":"Rive Rue De 8 1200 Genf. Postfach",
    "sg:city":"Gen\u00e8ve",
    "sg:orig_category":"Reiseb\u00fcros U Reiseveranstalter",
    "sg:phone":"+41 79 210 35 50",
    "sg:postcode":"1201",
    "sg:province":"Gen\u00e8ve",
    "wof:name":"Aubert Voyages Sa",
    "wof:placetype":"venue"
},
  "geometry": {"coordinates":[6.2310299873,46.6077919006],"type":"Point"}
}