{
  "type": "Feature",
  "properties": {
    "iso:country":"CH",
    "sg:address":"Seewjinenstrasse 4",
    "sg:city":"Visp",
    "sg:orig_category":"Fahrschulen, Flugschulen",
    "sg:phone":"+41 79 628 73 03",
    "sg:postcode":"3930",
    "sg:province":"Valais",
    "wof:name":"Harry Studer Autofahrschule",
    "wof:placetype":"venue"
},
  "geometry": {"coordinates":[7.8883509636,46.2925415039],"type":"Point"}
}