{
  "type": "Feature",
  "properties": {
    "iso:country":"CH",
    "sg:address":"Am Bach 92",
    "sg:city":"Gondiswil",
    "sg:orig_category":"Baugewerbe",
    "sg:phone":"+41 79 340 16 00",
    "sg:postcode":"4955",
    "sg:province":"Bern",
    "wof:name":"Fredy Meyer Baumontagen",
    "wof:placetype":"venue"
},
  "geometry": {"coordinates":[7.868482,47.144936],"type":"Point"}
}