{
  "type": "Feature",
  "properties": {
    "iso:country":"CH",
    "sg:address":"Milit\u00e4rstrasse 89 8000 Z\u00fcrich. Postfach",
    "sg:city":"Z\u00fcrich",
    "sg:orig_category":"Detailhandel mit Bekleidung",
    "sg:postcode":"8001",
    "sg:province":"Z\u00fcrich",
    "wof:name":"R\u00fcegger Mirquella",
    "wof:placetype":"venue"
},
  "geometry": {"coordinates":[8.529564,47.378887],"type":"Point"}
}