{
  "type": "Feature",
  "properties": {
    "iso:country":"CH",
    "sg:address":"Hombergstrasse 46",
    "sg:city":"Steffisburg",
    "sg:orig_category":"Sportvereine Triathlon Laufen, Schwimmen, Velo",
    "sg:phone":"+41 33 438 36 87",
    "sg:postcode":"3612",
    "sg:province":"Bern",
    "wof:name":"Tri-team Steffisburg",
    "wof:placetype":"venue"
},
  "geometry": {"coordinates":[7.6394619942,46.7717475891],"type":"Point"}
}