{
  "type": "Feature",
  "properties": {
    "iso:country":"CH",
    "sg:address":"Peiden Bad",
    "sg:city":"Duvin",
    "sg:classifiers":[
        {
            "category":"Restaurant",
            "type":"Food & Drink"
        }
    ],
    "sg:phone":"+41 81 931 11 80",
    "sg:postcode":"7112",
    "sg:province":"Graubunden",
    "wof:name":"Ustria Peiden Bogn",
    "wof:placetype":"venue"
},
  "geometry": {"coordinates":[9.1962795258,46.7199707031],"type":"Point"}
}