{
  "type": "Feature",
  "properties": {
    "iso:country":"CH",
    "sg:address":"Avenue Juste-olivier 16",
    "sg:city":"Lausanne",
    "sg:orig_category":"Physiotherapie",
    "sg:phone":"+41 21 311 53 89",
    "sg:postcode":"1006",
    "sg:province":"Vaud",
    "wof:name":"Rosanna Scipione Physioth\u00e9rapie",
    "wof:placetype":"venue"
},
  "geometry": {"coordinates":[6.6366758347,46.515296936],"type":"Point"}
}