{
  "type": "Feature",
  "properties": {
    "iso:country":"CH",
    "sg:address":"Rue Du Pont 5 1003 Lausanne. Postfach",
    "sg:city":"Lausanne",
    "sg:orig_category":"Restaurants Warenh\u00e4user",
    "sg:phone":"+41 21 342 99 88",
    "sg:postcode":"1002",
    "sg:province":"Vaud",
    "wof:name":"Globus Warenhaus Ag",
    "wof:placetype":"venue"
},
  "geometry": {"coordinates":[6.6335811615,46.5211486816],"type":"Point"}
}