{
  "type": "Feature",
  "properties": {
    "iso:country":"CH",
    "sg:address":"La Bicoque",
    "sg:city":"St-saphorin-lavaux",
    "sg:orig_category":"Sanit\u00e4r, Heizungs U L\u00fcftungsinstallation",
    "sg:phone":"+41 21 922 76 76",
    "sg:postcode":"1813",
    "wof:name":"Fuentes Jos\u00e9",
    "wof:placetype":"venue"
},
  "geometry": {"coordinates":[6.7959570885,46.4733009338],"type":"Point"}
}