{
  "type": "Feature",
  "properties": {
    "iso:country":"CH",
    "sg:address":"Stiefelstrasse 13",
    "sg:city":"Zufikon",
    "sg:orig_category":"Innenausbau Zimmerei, Ingenieurholzbau",
    "sg:phone":"+41 56 633 93 17",
    "sg:postcode":"5621",
    "sg:province":"Aargau",
    "wof:name":"Ewald Wendel Holzbau & Zimmerei",
    "wof:placetype":"venue"
},
  "geometry": {"coordinates":[8.3560361862,47.3518218994],"type":"Point"}
}