{
  "type": "Feature",
  "properties": {
    "iso:country":"CH",
    "sg:address":"Kornfeldstrasse 19",
    "sg:city":"Riehen",
    "sg:orig_category":"Werbegrafikateliers",
    "sg:phone":"+41 79 356 71 17",
    "sg:postcode":"4125",
    "sg:province":"Basel-Stadt",
    "wof:name":"Wegm\u00fcller Graphik & Design",
    "wof:placetype":"venue"
},
  "geometry": {"coordinates":[7.6460800171,47.5771636963],"type":"Point"}
}