{
  "type": "Feature",
  "properties": {
    "iso:country":"CH",
    "sg:address":"Wespenstrasse 15",
    "sg:city":"Frauenfeld",
    "sg:orig_category":"Grosshandel mit Datenverarbeitungsger\u00e4ten",
    "sg:phone":"+41 21 792 15 60",
    "sg:postcode":"8500",
    "sg:province":"Thurgau",
    "wof:name":"Philippe Froidevaux Cadgeo Informatique",
    "wof:placetype":"venue"
},
  "geometry": {"coordinates":[6.6777420044,46.5129203796],"type":"Point"}
}