{
  "type": "Feature",
  "properties": {
    "iso:country":"CH",
    "sg:address":"1747",
    "sg:city":"Corserey",
    "sg:classifiers":[
        {
            "category":"Travel",
            "subcategory":"Hotels & Motels",
            "type":"Entertainment"
        }
    ],
    "sg:postcode":"1747",
    "sg:province":"Fribourg",
    "sg:tags":[
        "hotels",
        "mit",
        "restaurant"
    ],
    "wof:name":"Brouwer Elisabeth.",
    "wof:placetype":"venue"
},
  "geometry": {"coordinates":[6.9889202118,46.7712287903],"type":"Point"}
}