{
  "type": "Feature",
  "properties": {
    "iso:country":"CH",
    "sg:address":"8000 Z\u00fcrich. Postfach",
    "sg:city":"Z\u00fcrich",
    "sg:orig_category":"Unclassifiable Establishments",
    "sg:postcode":"8051",
    "sg:province":"Z\u00fcrich",
    "wof:name":"Jb - Vision Jasminka Brcina",
    "wof:placetype":"venue"
},
  "geometry": {"coordinates":[8.0762910843,47.3871803284],"type":"Point"}
}