{
  "type": "Feature",
  "properties": {
    "iso:country":"CH",
    "sg:address":"Route De Vevey 8 1096 Cully Case Postale",
    "sg:city":"Cully",
    "sg:orig_category":"Geometerb\u00fcros",
    "sg:phone":"+41 21 646 49 78",
    "sg:postcode":"1096",
    "sg:province":"Vaud",
    "wof:name":"Jacques Vautier Bureau De G\u00e9om\u00e8tre",
    "wof:placetype":"venue"
},
  "geometry": {"coordinates":[6.7318959236,46.4887046814],"type":"Point"}
}