{
  "type": "Feature",
  "properties": {
    "iso:country":"CH",
    "sg:address":"Route De Porrentruy 72",
    "sg:city":"Del\u00e9mont",
    "sg:orig_category":"Tankstellen",
    "sg:phone":"+41 32 422 43 41",
    "sg:postcode":"2800",
    "sg:province":"Jura",
    "wof:name":"Jeannin Jean-claude",
    "wof:placetype":"venue"
},
  "geometry": {"coordinates":[7.3355631828,47.360660553],"type":"Point"}
}