{
  "type": "Feature",
  "properties": {
    "iso:country":"CH",
    "sg:address":"R\u00f6ssligasse 19",
    "sg:city":"Riehen",
    "sg:classifiers":[
        {
            "category":"Restaurant",
            "type":"Food & Drink"
        }
    ],
    "sg:phone":"+41 61 643 13 30",
    "sg:postcode":"4125",
    "sg:province":"Basel-Stadt",
    "wof:name":"Caf\u00e9 Aksu",
    "wof:placetype":"venue"
},
  "geometry": {"coordinates":[7.6516342163,47.5857009888],"type":"Point"}
}