{
  "type": "Feature",
  "properties": {
    "iso:country":"CH",
    "sg:address":"Adam-friedrich-molz-gasse 10",
    "sg:city":"Biel/bienne",
    "sg:orig_category":"Detailhandel mit Getr\u00e4nken Grosshandel mit Getr\u00e4nken",
    "sg:phone":"+41 32 322 88 48",
    "sg:postcode":"2502",
    "sg:province":"Bern",
    "wof:name":"Le Vin, Biedermann H.r.",
    "wof:placetype":"venue"
},
  "geometry": {"coordinates":[7.2451710701,47.1393890381],"type":"Point"}
}