{
  "type": "Feature",
  "properties": {
    "iso:country":"CH",
    "sg:address":"Junkholzweg 1",
    "sg:city":"Kaiseraugst",
    "sg:orig_category":"Detailhandel mit Beleuchtungs U Haushaltsgegenst\u00e4nden Detailhandel mit elektrischen Haushalts, Radio",
    "sg:phone":"+41 61 401 21 00",
    "sg:postcode":"4303",
    "sg:province":"Aargau",
    "wof:name":"Fust Ag Elektroapparate",
    "wof:placetype":"venue"
},
  "geometry": {"coordinates":[7.554483,47.507725],"type":"Point"}
}