{
  "type": "Feature",
  "properties": {
    "iso:country":"CH",
    "sg:address":"Rue Plantour 10 1860 Aigle. Postfach",
    "sg:city":"Aigle",
    "sg:orig_category":"Allgemeiner Hoch U Tiefbau Stukkateurgewerbe, Gipserei U Verputzerei",
    "sg:phone":"+41 24 466 20 90",
    "sg:postcode":"1860",
    "sg:province":"Vaud",
    "wof:name":"D\u00e9caillet S\u00e0rl",
    "wof:placetype":"venue"
},
  "geometry": {"coordinates":[6.969105,46.316963],"type":"Point"}
}