{
  "type": "Feature",
  "properties": {
    "iso:country":"CH",
    "sg:address":"Kleindorfstrasse 12a 8707 Uetikon Am See. Postfach",
    "sg:city":"Feldmeilen",
    "sg:orig_category":"Handelsvermittlung U Grosshandel",
    "sg:phone":"+41 55 283 17 27",
    "sg:postcode":"8706",
    "sg:province":"Z\u00fcrich",
    "wof:name":"Heinz R\u00fcegg K.e.w.reinigungstechnik",
    "wof:placetype":"venue"
},
  "geometry": {"coordinates":[9.0168457031,47.1889648438],"type":"Point"}
}