{
  "type": "Feature",
  "properties": {
    "iso:country":"CH",
    "sg:address":"Alpenweg 28",
    "sg:city":"D\u00fcdingen",
    "sg:orig_category":"P\u00e9dicure",
    "sg:phone":"+41 19354293",
    "sg:postcode":"3186",
    "sg:province":"Fribourg",
    "wof:name":"Heidi Graf P\u00e9dicure",
    "wof:placetype":"venue"
},
  "geometry": {"coordinates":[8.7652597427,47.3030357361],"type":"Point"}
}