{
  "type": "Feature",
  "properties": {
    "iso:country":"CH",
    "sg:address":"Rue De La Chapelle 7",
    "sg:city":"Aigle",
    "sg:orig_category":"Sanit\u00e4rinstallation",
    "sg:phone":"+41 24 466 40 29",
    "sg:postcode":"1860",
    "sg:province":"Vaud",
    "wof:name":"Michel Longchamp Installations Sanitaires",
    "wof:placetype":"venue"
},
  "geometry": {"coordinates":[6.9676599503,46.3148994446],"type":"Point"}
}