{
  "type": "Feature",
  "properties": {
    "iso:country":"CH",
    "sg:address":"An Der Halde 41",
    "sg:city":"Triesen",
    "sg:orig_category":"Vermittlung von Immobilien Verwaltung von Immobilien",
    "sg:phone":"+423 392 24 14",
    "sg:postcode":"9495",
    "wof:name":"Risch & Partner Architektur Ag",
    "wof:placetype":"venue"
},
  "geometry": {"coordinates":[9.5253019333,47.1119422913],"type":"Point"}
}