{
  "type": "Feature",
  "properties": {
    "iso:country":"CH",
    "sg:address":"Vietta Saluver",
    "sg:city":"Celerina",
    "sg:orig_category":"Vermietung U Verpachtung von eigenen Immobilien",
    "sg:phone":"+41 81 834 83 86",
    "sg:postcode":"7505",
    "sg:province":"Graubunden",
    "wof:name":"Engadiner Haus Ag",
    "wof:placetype":"venue"
},
  "geometry": {"coordinates":[9.8381910324,46.4970664978],"type":"Point"}
}