{
  "type": "Feature",
  "properties": {
    "iso:country":"CH",
    "sg:address":"Brunnenstrasse 16",
    "sg:city":"Bassersdorf",
    "sg:orig_category":"Unternehmensberatung",
    "sg:phone":"+41 18366927",
    "sg:postcode":"8303",
    "sg:province":"Z\u00fcrich",
    "wof:name":"Schweizer Max, Bau Und Unternehmensberatung.",
    "wof:placetype":"venue"
},
  "geometry": {"coordinates":[8.6371107101,47.4397926331],"type":"Point"}
}