{
  "type": "Feature",
  "properties": {
    "iso:country":"CH",
    "sg:address":"L\u00e4uferberg 15",
    "sg:city":"N\u00e4fels",
    "sg:orig_category":"Interessenvertretungen",
    "sg:postcode":"8752",
    "sg:province":"Glarus",
    "wof:name":"Igl Interessengemeinschaft L\u00c4uferberg",
    "wof:placetype":"venue"
},
  "geometry": {"coordinates":[9.0343790054,47.1014633179],"type":"Point"}
}