{
  "type": "Feature",
  "properties": {
    "iso:country":"CH",
    "sg:address":"Sieberstrasse 5 8055 Z\u00fcrich. Postfach",
    "sg:city":"Z\u00fcrich",
    "sg:orig_category":"Softwareentwicklung U beratung",
    "sg:phone":"+41 14637488",
    "sg:postcode":"8055",
    "sg:province":"Z\u00fcrich",
    "wof:name":"Br\u00e4ndle, Missura & Partner Informatik Ag",
    "wof:placetype":"venue"
},
  "geometry": {"coordinates":[8.5101938248,47.3658218384],"type":"Point"}
}