{
  "type": "Feature",
  "properties": {
    "iso:country":"CH",
    "sg:address":"Dachslernstrasse 84",
    "sg:city":"Z\u00fcrich",
    "sg:orig_category":"Reinigungsgewerbe",
    "sg:phone":"+41 14314645",
    "sg:postcode":"8048",
    "sg:province":"Z\u00fcrich",
    "wof:name":"Domestica Liegenschaftenunterhalt Vito Antonio Turco",
    "wof:placetype":"venue"
},
  "geometry": {"coordinates":[8.4737195969,47.3912658691],"type":"Point"}
}