{
  "type": "Feature",
  "properties": {
    "iso:country":"CH",
    "sg:address":"Boulevard De P\u00e9rolles 83",
    "sg:city":"Fribourg",
    "sg:orig_category":"Sportvereine Unihockey",
    "sg:phone":"+41 26 424 50 44",
    "sg:postcode":"1700",
    "sg:province":"Fribourg",
    "wof:name":"Uhc Grolley",
    "wof:placetype":"venue"
},
  "geometry": {"coordinates":[7.1565318108,46.7950553894],"type":"Point"}
}