{
  "type": "Feature",
  "properties": {
    "iso:country":"CH",
    "sg:address":"Johann-renfer-strasse 51-55",
    "sg:city":"Biel/bienne",
    "sg:classifiers":[
        {
            "category":"Building & Trades",
            "subcategory":"Construction",
            "type":"Services"
        }
    ],
    "sg:phone":"+41 32 344 45 00",
    "sg:postcode":"2504",
    "sg:province":"Bern",
    "sg:tags":[
        "machine"
    ],
    "wof:name":"Swiss Metal Casting Ag",
    "wof:placetype":"venue"
},
  "geometry": {"coordinates":[7.2877287865,47.1575431824],"type":"Point"}
}