{
  "type": "Feature",
  "properties": {
    "addr:full":"Boriodaz Chemin 50 Montreux Vaud 1820",
    "addr:postcode":"1820",
    "addr:street":"Chemin 50",
    "iso:country":"CH",
    "sg:address":"Boriodaz Chemin 50",
    "sg:city":"Montreux",
    "sg:orig_category":"Architektur U Ingenieurb\u00fcros",
    "sg:postcode":"1820",
    "sg:province":"Vaud",
    "wof:name":"Cogesco Commercialisation, Gestion Et Consulting S\u00e0rl",
    "wof:placetype":"venue"
},
  "geometry": {"coordinates":[6.91712,46.435658],"type":"Point"}
}