{
  "type": "Feature",
  "properties": {
    "iso:country":"CH",
    "sg:address":"Langacherstrasse 10",
    "sg:city":"Untersiggenthal",
    "sg:orig_category":"Allgemeiner Hoch U Tiefbau",
    "sg:postcode":"5417",
    "sg:province":"Aargau",
    "wof:name":"J. Benk\u00f6, Umbau Und Renovationen",
    "wof:placetype":"venue"
},
  "geometry": {"coordinates":[8.257163,47.503441],"type":"Point"}
}