{
  "type": "Feature",
  "properties": {
    "iso:country":"CH",
    "sg:address":"Avenue De La Gare 11",
    "sg:city":"Chavannes-renens",
    "sg:orig_category":"Detailhandel mit Beleuchtungs U Haushaltsgegenst\u00e4nden Detailhandel mit elektrischen Haushalts-,Radio",
    "sg:phone":"+41 21 635 21 67",
    "sg:postcode":"1022",
    "sg:province":"Vaud",
    "wof:name":"Far, Alvarin-fernandez Rosa",
    "wof:placetype":"venue"
},
  "geometry": {"coordinates":[6.578162,46.534916],"type":"Point"}
}