{
  "type": "Feature",
  "properties": {
    "iso:country":"CH",
    "sg:address":"Limmatstrasse 2",
    "sg:city":"Spreitenbach",
    "sg:orig_category":"Grosshandel mit Eisenwaren sowie Installationsbedarf f\u00fcr Gas, Wasser U Heizung Grosshandel mit Erzen",
    "sg:phone":"+41 56 417 90 00",
    "sg:postcode":"8957",
    "sg:province":"Aargau",
    "wof:name":"Bahco Belzer Gmbh Filiale Spreitenbach",
    "wof:placetype":"venue"
},
  "geometry": {"coordinates":[8.3709888458,47.4295272827],"type":"Point"}
}