{
  "type": "Feature",
  "properties": {
    "iso:country":"CH",
    "sg:address":"Feithierenstrasse",
    "sg:city":"Susten",
    "sg:orig_category":"Maler U Glasergewerbe Malerei",
    "sg:phone":"+41 52 672 37 61",
    "sg:postcode":"3952",
    "sg:province":"Valais",
    "wof:name":"Malergesch\u00e4ft Simunovic",
    "wof:placetype":"venue"
},
  "geometry": {"coordinates":[8.6174097061,47.6810340881],"type":"Point"}
}