{
  "type": "Feature",
  "properties": {
    "iso:country":"CH",
    "sg:address":"L\u00e4nggassstrasse 122",
    "sg:city":"Bern",
    "sg:orig_category":"Universit\u00e4ten, Hochschulen",
    "sg:phone":"+41 31 631 21 11",
    "sg:postcode":"3012",
    "sg:province":"Bern",
    "wof:name":"Veterin\u00e4r-medizin.fakult\u00e4t",
    "wof:placetype":"venue"
},
  "geometry": {"coordinates":[7.4256281853,46.9562683105],"type":"Point"}
}