{
  "type": "Feature",
  "properties": {
    "iso:country":"CH",
    "sg:address":"J\u00f6ndliweg 13",
    "sg:city":"Strengelbach",
    "sg:orig_category":"Herstellung von k\u00e4lte U lufttechnischen Erzeugnissen f\u00fcr gewerbliche Zwecke",
    "sg:phone":"+41 62 751 32 36",
    "sg:postcode":"4802",
    "sg:province":"Aargau",
    "wof:name":"Planungsb\u00fcro Heizung Siegrist Werner H.",
    "wof:placetype":"venue"
},
  "geometry": {"coordinates":[7.92979002,47.2783660889],"type":"Point"}
}