{
  "type": "Feature",
  "properties": {
    "iso:country":"CH",
    "sg:address":"Luganetto Via 4",
    "sg:city":"Viganello",
    "sg:orig_category":"Chemische Fabriken",
    "sg:postcode":"6962",
    "sg:province":"Ticino",
    "wof:name":"Kalichem Sagl",
    "wof:placetype":"venue"
},
  "geometry": {"coordinates":[8.960592,46.010921],"type":"Point"}
}