{
  "type": "Feature",
  "properties": {
    "iso:country":"CH",
    "sg:address":"Rue Des C\u00e8dres 13",
    "sg:city":"Sion",
    "sg:orig_category":"Arztpraxen",
    "sg:phone":"+41 27 323 56 32",
    "sg:postcode":"1950",
    "sg:province":"Valais",
    "wof:name":"Dr M\u00e9d. Rosario Granges M\u00e9decin Sp\u00e9cialiste Fmh",
    "wof:placetype":"venue"
},
  "geometry": {"coordinates":[7.361273,46.230598],"type":"Point"}
}