{
  "type": "Feature",
  "properties": {
    "iso:country":"CH",
    "sg:address":"Witellikerstrasse 40",
    "sg:city":"Z\u00fcrich",
    "sg:orig_category":"Gesundheitswesen",
    "sg:phone":"+41 13873011",
    "sg:postcode":"8008",
    "sg:province":"Z\u00fcrich",
    "wof:name":"Zentrum F\u00fcr Schlafmedizin Hirslanden Z\u00fcrich",
    "wof:placetype":"venue"
},
  "geometry": {"coordinates":[8.5767393112,47.3510780334],"type":"Point"}
}