{
  "type": "Feature",
  "properties": {
    "iso:country":"CH",
    "sg:address":"Z\u00fcrcherstrasse 73",
    "sg:city":"Siebnen",
    "sg:orig_category":"Handelsvermittlung U Grosshandel mit Automobilteilen U Zubeh\u00f6r Herstellung von Bereifungen",
    "sg:phone":"+41 55 440 79 45",
    "sg:postcode":"8854",
    "sg:province":"Schwyz",
    "wof:name":"Pneuhandel Sch\u00e4tti",
    "wof:placetype":"venue"
},
  "geometry": {"coordinates":[8.8876695633,47.1780395508],"type":"Point"}
}