{
  "type": "Feature",
  "properties": {
    "iso:country":"CH",
    "sg:address":"Via Castausio 20",
    "sg:city":"Lugano",
    "sg:orig_category":"Architektur U Ingenieurb\u00fcros",
    "sg:phone":"+41 91 971 16 62",
    "sg:postcode":"6900",
    "sg:province":"Ticino",
    "wof:name":"Verzeri Plinio.",
    "wof:placetype":"venue"
},
  "geometry": {"coordinates":[8.952812,46.015259],"type":"Point"}
}