{
  "type": "Feature",
  "properties": {
    "iso:country":"CH",
    "sg:address":"Hauptstrasse 57",
    "sg:city":"Sevelen",
    "sg:orig_category":"Detailhandel mit S\u00e4uglings U Kinderbekleidung",
    "sg:postcode":"9475",
    "sg:province":"St. Gallen",
    "wof:name":"Bambola Katrin Murezzan Kinderkleider & Secondhand",
    "wof:placetype":"venue"
},
  "geometry": {"coordinates":[9.4870052338,47.1215591431],"type":"Point"}
}