{
  "type": "Feature",
  "properties": {
    "iso:country":"CH",
    "sg:address":"3960 Sierre Case Postale 585",
    "sg:city":"Sierre",
    "sg:orig_category":"Sportvereine Ballsport Tennis",
    "sg:phone":"+41 56 249 24 56",
    "sg:postcode":"3960",
    "sg:province":"Valais",
    "wof:name":"Tennisclub Solvay Ag",
    "wof:placetype":"venue"
},
  "geometry": {"coordinates":[8.3176641464,47.570526123],"type":"Point"}
}