{
  "type": "Feature",
  "properties": {
    "iso:country":"CH",
    "sg:address":"Bahnhofstr. 17 6300 Zug. Postfach",
    "sg:city":"Zug",
    "sg:orig_category":"Interessenvertretungen",
    "sg:postcode":"6301",
    "sg:province":"Zug",
    "wof:name":"W.a. Mozart-stiftung.",
    "wof:placetype":"venue"
},
  "geometry": {"coordinates":[8.5156183243,47.1694488525],"type":"Point"}
}