{
  "type": "Feature",
  "properties": {
    "iso:country":"CH",
    "sg:address":"Wilerstrasse 3",
    "sg:city":"Flawil",
    "sg:orig_category":"Arztpraxen",
    "sg:phone":"+41 71 393 44 88",
    "sg:postcode":"9230",
    "sg:province":"St. Gallen",
    "wof:name":"Dr.med.eva Bures Spezial\u00e4rztin",
    "wof:placetype":"venue"
},
  "geometry": {"coordinates":[9.186769,47.413364],"type":"Point"}
}