{
  "type": "Feature",
  "properties": {
    "iso:country":"CH",
    "sg:address":"Hauptstrasse 47",
    "sg:city":"Lausen",
    "sg:orig_category":"Malerei",
    "sg:phone":"+41 61 921 68 48",
    "sg:postcode":"4415",
    "sg:province":"Basel-Landschaft",
    "wof:name":"Karl Tschopp Malergesch\u00e4ft",
    "wof:placetype":"venue"
},
  "geometry": {"coordinates":[7.7566761971,47.4726524353],"type":"Point"}
}