{
  "type": "Feature",
  "properties": {
    "iso:country":"CH",
    "sg:address":"Pischastrasse",
    "sg:city":"Zizers",
    "sg:orig_category":"Politische Parteien SVP",
    "sg:phone":"+41 81 322 71 44",
    "sg:postcode":"7205",
    "sg:province":"Graubunden",
    "wof:name":"Svp Kreis F\u00fcnf D\u00f6rfer",
    "wof:placetype":"venue"
},
  "geometry": {"coordinates":[9.5692501068,46.9354362488],"type":"Point"}
}