{
  "type": "Feature",
  "properties": {
    "iso:country":"CH",
    "sg:address":"Chemin De Mongevon 9",
    "sg:city":"Crissier",
    "sg:orig_category":"Bimetal Thermometers",
    "sg:phone":"+41 21 637 32 32",
    "sg:postcode":"1023",
    "sg:province":"Vaud",
    "wof:name":"R\u00fceger S.a.",
    "wof:placetype":"venue"
},
  "geometry": {"coordinates":[6.574415,46.547642],"type":"Point"}
}