{
  "type": "Feature",
  "properties": {
    "iso:country":"CH",
    "sg:address":"Rotachstrasse 36",
    "sg:city":"Z\u00fcrich",
    "sg:orig_category":"Herstellung von Damen U M\u00e4dchenoberbekleidung Herstellung von Herren U Knabenoberbekleidung",
    "sg:phone":"+41 14510400",
    "sg:postcode":"8003",
    "sg:province":"Z\u00fcrich",
    "wof:name":"Bloomer Staub Christine",
    "wof:placetype":"venue"
},
  "geometry": {"coordinates":[8.5145454407,47.3713760376],"type":"Point"}
}