{
  "type": "Feature",
  "properties": {
    "iso:country":"CH",
    "sg:address":"Winkel",
    "sg:city":"Maienfeld",
    "sg:orig_category":"Organisationen des Gesundheitswesen",
    "sg:phone":"+41 81 322 13 08",
    "sg:postcode":"7304",
    "sg:province":"Graubunden",
    "wof:name":"Samariterverein Malans",
    "wof:placetype":"venue"
},
  "geometry": {"coordinates":[9.5757646561,46.9795951843],"type":"Point"}
}