{
  "type": "Feature",
  "properties": {
    "iso:country":"CH",
    "sg:address":"Neuwiesenstrasse 31",
    "sg:city":"Volketswil",
    "sg:classifiers":[
        {
            "category":"Insurance",
            "subcategory":"Insurance Agent",
            "type":"Services"
        }
    ],
    "sg:phone":"+41 19453703",
    "sg:postcode":"8604",
    "sg:province":"Z\u00fcrich",
    "sg:tags":[
        "versicherungsagenturen",
        "-broker"
    ],
    "wof:name":"Helvetia Patria Versicherungen Agentur",
    "wof:placetype":"venue"
},
  "geometry": {"coordinates":[8.6891651154,47.387424469],"type":"Point"}
}