{
  "type": "Feature",
  "properties": {
    "iso:country":"CH",
    "sg:address":"Pierre Rue Saint- 3",
    "sg:city":"Fribourg",
    "sg:orig_category":"Finanzierungsinstitutionen",
    "sg:phone":"+41 26 425 83 40",
    "sg:postcode":"1700",
    "sg:province":"Fribourg",
    "wof:name":"Fidex Consulting Sa",
    "wof:placetype":"venue"
},
  "geometry": {"coordinates":[7.1546449661,46.8038215637],"type":"Point"}
}