{
  "type": "Feature",
  "properties": {
    "iso:country":"CH",
    "sg:address":"Linth-escher-strasse 13",
    "sg:city":"Bilten",
    "sg:orig_category":"Instandhaltung U Reparatur von Automobilen",
    "sg:phone":"+41 55 615 21 15",
    "sg:postcode":"8865",
    "sg:province":"Glarus",
    "wof:name":"Auto Gasser Bilten",
    "wof:placetype":"venue"
},
  "geometry": {"coordinates":[9.0276479721,47.152015686],"type":"Point"}
}