{
  "type": "Feature",
  "properties": {
    "iso:country":"CH",
    "sg:address":"Hauptstrasse 1a 4563 Gerlafingen. Postfach 204",
    "sg:city":"Gerlafingen",
    "sg:orig_category":"Detailhandel mit Computern U Software Siebdruck",
    "sg:phone":"+41 32 675 68 80",
    "sg:postcode":"4563",
    "sg:province":"Solothurn",
    "wof:name":"Hasan Uenl\u00fc Hb Graphics & Computer",
    "wof:placetype":"venue"
},
  "geometry": {"coordinates":[7.572768,47.170681],"type":"Point"}
}