{
  "type": "Feature",
  "properties": {
    "iso:country":"CH",
    "sg:address":"Glattstegweg 4 8051 Z\u00fcrich. Postfach",
    "sg:city":"Z\u00fcrich",
    "sg:orig_category":"Fussboden, Fliesen U Plattenlegerei, Tapeziererei",
    "sg:phone":"+41 13227273",
    "sg:postcode":"8051",
    "sg:province":"Z\u00fcrich",
    "wof:name":"Greco, Makripodis Chr. Plattenlegergesch\u00e4ft. Keramikplatten, Marmor; Verlegen",
    "wof:placetype":"venue"
},
  "geometry": {"coordinates":[8.573636055,47.4063262939],"type":"Point"}
}