{
  "type": "Feature",
  "properties": {
    "iso:country":"CH",
    "sg:address":"Alte Bahnhofstrasse 3",
    "sg:city":"Herisau",
    "sg:orig_category":"Interessenvertretungen",
    "sg:postcode":"9102",
    "sg:province":"Appenzell Ausserrhoden",
    "wof:name":"Hans Z'graggen-stiftung",
    "wof:placetype":"venue"
},
  "geometry": {"coordinates":[14.651049614,48.4240493774],"type":"Point"}
}