{
  "type": "Feature",
  "properties": {
    "iso:country":"CH",
    "sg:address":"Bachwilstrasse",
    "sg:city":"Entlebuch",
    "sg:orig_category":"Sonstige Personenbef\u00f6rderung im Landverkehr",
    "sg:postcode":"6162",
    "sg:province":"Luzern",
    "wof:name":"Huber Reisen",
    "wof:placetype":"venue"
},
  "geometry": {"coordinates":[8.1154699326,47.157661438],"type":"Point"}
}