{
  "type": "Feature",
  "properties": {
    "iso:country":"CH",
    "sg:address":"4543 Deitingen. Postfach 3",
    "sg:city":"Deitingen",
    "sg:orig_category":"Sportvereine Ballsport Fussball",
    "sg:postcode":"4543",
    "sg:province":"Solothurn",
    "wof:name":"Fc Deitingen",
    "wof:placetype":"venue"
},
  "geometry": {"coordinates":[7.6207699776,47.2136154175],"type":"Point"}
}