{
  "type": "Feature",
  "properties": {
    "iso:country":"CH",
    "sg:address":"Obergasse 15 8400 Winterthur. Postfach",
    "sg:city":"Winterthur",
    "sg:orig_category":"Detailhandel mit B\u00fcchern, Zeitungen, Schreib U Papeteriewaren",
    "sg:postcode":"8400",
    "sg:province":"Z\u00fcrich",
    "wof:name":"Zebra Geschenke B\u00fccher Musik Gmbh",
    "wof:placetype":"venue"
},
  "geometry": {"coordinates":[8.860254,47.659081],"type":"Point"}
}