{
  "type": "Feature",
  "properties": {
    "iso:country":"CH",
    "sg:address":"Rheinstrasse 16 4410 Liestal. Postfach",
    "sg:city":"Liestal",
    "sg:orig_category":"Aktivit\u00e4ten der Generalunternehmen im Baugewerbe Vermittlung von Immobilien",
    "sg:phone":"+41 61 927 92 00",
    "sg:postcode":"4410",
    "sg:province":"Basel-Landschaft",
    "wof:name":"Gribi Theurillat Ag",
    "wof:placetype":"venue"
},
  "geometry": {"coordinates":[7.732315,47.486214],"type":"Point"}
}