{
  "type": "Feature",
  "properties": {
    "iso:country":"CH",
    "sg:address":"Violetta Via 9 6976 Castagnola. Postfach",
    "sg:city":"Castagnola",
    "sg:orig_category":"Detailhandel mit elektrischen Haushalts-,Radio U Fernsehger\u00e4ten sowie Musikinstrumenten",
    "sg:phone":"+41 22 340 05 70",
    "sg:postcode":"6976",
    "sg:province":"Ticino",
    "wof:name":"Zap Sa Sonorisation",
    "wof:placetype":"venue"
},
  "geometry": {"coordinates":[6.1215481758,46.2094192505],"type":"Point"}
}