{
  "type": "Feature",
  "properties": {
    "addr:full":"Reuebergstrasse 16 Grossaffoltern Bern 3257",
    "addr:housenumber":"16",
    "addr:postcode":"3257",
    "addr:street":"Reuebergstrasse",
    "iso:country":"CH",
    "sg:address":"Reuebergstrasse 16",
    "sg:city":"Grossaffoltern",
    "sg:orig_category":"Datenverarbeitungsdienste",
    "sg:phone":"+41 32 389 51 70",
    "sg:postcode":"3257",
    "sg:province":"Bern",
    "wof:name":"Air Info Ag Informatik-l\u00f6sungen",
    "wof:placetype":"venue"
},
  "geometry": {"coordinates":[7.353234,47.066086],"type":"Point"}
}