{
  "type": "Feature",
  "properties": {
    "iso:country":"CH",
    "sg:address":"\u00dcberlandstrasse 180 8000 Z\u00fcrich. Postfach",
    "sg:city":"Z\u00fcrich",
    "sg:orig_category":"Grosshandel mit Nahrungsmitteln, Getr\u00e4nken U Tabakwaren ohne ausgepr\u00e4gten Schwerpunkt",
    "sg:postcode":"8001",
    "sg:province":"Z\u00fcrich",
    "wof:name":"N\u00c4geli Quick Chicken Ag",
    "wof:placetype":"venue"
},
  "geometry": {"coordinates":[8.5676307678,47.4081459045],"type":"Point"}
}