{
  "type": "Feature",
  "properties": {
    "iso:country":"CH",
    "sg:address":"Simplonstrasse 55",
    "sg:city":"Ried-brig",
    "sg:orig_category":"Detailhandel mit M\u00f6beln U Haushaltsgegenst\u00e4nden Selbst\u00e4ndige bildende K\u00fcnstler",
    "sg:phone":"+41 27 923 44 54",
    "sg:postcode":"3911",
    "sg:province":"Valais",
    "wof:name":"Josef Zenklusen Ag Schnitzerei & Giesserei",
    "wof:placetype":"venue"
},
  "geometry": {"coordinates":[8.0170984268,46.3167381287],"type":"Point"}
}