{
  "type": "Feature",
  "properties": {
    "iso:country":"CH",
    "sg:address":"Via Simone Da Locarno 4 6600 Locarno. Postfach",
    "sg:city":"Locarno",
    "sg:orig_category":"Sonstige Vermietung U Verpachtung von eigenen Immobilien Verwaltung von Immobilien",
    "sg:phone":"+41 71 277 78 76",
    "sg:postcode":"6600",
    "sg:province":"Ticino",
    "wof:name":"Bks Bauberatung Gmbh",
    "wof:placetype":"venue"
},
  "geometry": {"coordinates":[9.3283252716,47.4078140259],"type":"Point"}
}