{
  "type": "Feature",
  "properties": {
    "iso:country":"CH",
    "sg:address":"Webergasse 7",
    "sg:city":"Basel",
    "sg:orig_category":"RESTAURANTS: TEA-ROOMS",
    "sg:phone":"+41 61 681 13 03",
    "sg:postcode":"4058",
    "sg:province":"Basel-Stadt",
    "wof:name":"Roter Kater Ag",
    "wof:placetype":"venue"
},
  "geometry": {"coordinates":[7.5905790329,47.5617828369],"type":"Point"}
}