{
  "type": "Feature",
  "properties": {
    "iso:country":"CH",
    "sg:address":"2615",
    "sg:city":"Montagne-sonvilier",
    "sg:orig_category":"Sanit\u00e4r, Heizungs U L\u00fcftungsinstallation",
    "sg:postcode":"2615",
    "sg:province":"Bern",
    "wof:name":"Pellegrini Vincenzo",
    "wof:placetype":"venue"
},
  "geometry": {"coordinates":[6.9643440247,47.1388969421],"type":"Point"}
}