{
  "type": "Feature",
  "properties": {
    "iso:country":"CH",
    "sg:address":"Dreieggli",
    "sg:city":"Hemberg",
    "sg:orig_category":"Pensionen mit Restaurant",
    "sg:phone":"+41 31 331 79 24",
    "sg:postcode":"9633",
    "sg:province":"St. Gallen",
    "wof:name":"Pension Hiltbrand",
    "wof:placetype":"venue"
},
  "geometry": {"coordinates":[7.4549069405,46.9619407654],"type":"Point"}
}