{
  "type": "Feature",
  "properties": {
    "addr:full":"Ponte Piazza 9 6850 Mendrisio. Postfach Mendrisio Ticino 6850",
    "addr:postcode":"6850 mendrisio. postfach;6850",
    "addr:street":"Piazza 9",
    "iso:country":"CH",
    "sg:address":"Ponte Piazza 9 6850 Mendrisio. Postfach",
    "sg:city":"Mendrisio",
    "sg:orig_category":"Detailhandel mit Bekleidung",
    "sg:postcode":"6850",
    "sg:province":"Ticino",
    "wof:name":"New Gallery, Hofmann Natalie",
    "wof:placetype":"venue"
},
  "geometry": {"coordinates":[8.438524,47.322857],"type":"Point"}
}