{
  "type": "Feature",
  "properties": {
    "iso:country":"CH",
    "sg:address":"Route Du Mar\u00e9cot 24",
    "sg:city":"Cho\u00ebx",
    "sg:orig_category":"Architektur U Ingenieurb\u00fcros Mechanische Werkst\u00e4tten",
    "sg:phone":"+41 24 471 27 60",
    "sg:postcode":"1871",
    "sg:province":"Valais",
    "wof:name":"Wisatec - Wisard Ren\u00e9",
    "wof:placetype":"venue"
},
  "geometry": {"coordinates":[6.941928,46.243439],"type":"Point"}
}