{
  "type": "Feature",
  "properties": {
    "iso:country":"CH",
    "sg:address":"Stockerstrasse 11 8002 Z\u00fcrich. Postfach",
    "sg:city":"Z\u00fcrich",
    "sg:orig_category":"Interessenvertretungen",
    "sg:postcode":"8001",
    "sg:province":"Z\u00fcrich",
    "wof:name":"Supras Verst\u00e4ndniss F. Kulturelle, Soziale Aspekte Weltweiter Entw.prozesse In Forschung, Bes. Verbindung Zw. D. Ethnolog. Wissen U. D. Entw.praxis Usw; F\u00f6rderung",
    "wof:placetype":"venue"
},
  "geometry": {"coordinates":[8.5363740921,47.365146637],"type":"Point"}
}