{
  "type": "Feature",
  "properties": {
    "iso:country":"CH",
    "sg:address":"Bahnhofstrasse 9",
    "sg:city":"Emmen",
    "sg:orig_category":"Interessenvertretungen",
    "sg:postcode":"6032",
    "sg:province":"Luzern",
    "wof:name":"Interessengemeinschaft Des Sch\u00f6nstattwerkes Der Schweiz (isws)",
    "wof:placetype":"venue"
},
  "geometry": {"coordinates":[8.2820110321,47.0705833435],"type":"Point"}
}