{
  "type": "Feature",
  "properties": {
    "iso:country":"CH",
    "sg:address":"Kehr 22 9056 Gais. Postfach",
    "sg:city":"Gais",
    "sg:orig_category":"Bauschreinerei",
    "sg:phone":"+41 41 497 39 14",
    "sg:postcode":"9056",
    "sg:province":"Appenzell Ausserrhoden",
    "wof:name":"Beat Bucheli Schreinerei",
    "wof:placetype":"venue"
},
  "geometry": {"coordinates":[8.138225,47.038979],"type":"Point"}
}