{
  "type": "Feature",
  "properties": {
    "iso:country":"CH",
    "sg:address":"Letzigraben 43",
    "sg:city":"Z\u00fcrich",
    "sg:orig_category":"Sonstige pers\u00f6nliche Dienstleistungen",
    "sg:postcode":"8001",
    "sg:province":"Z\u00fcrich",
    "wof:name":"Aramis Gastro Management Gmbh",
    "wof:placetype":"venue"
},
  "geometry": {"coordinates":[8.5015258789,47.379737854],"type":"Point"}
}