{
  "type": "Feature",
  "properties": {
    "iso:country":"CH",
    "sg:address":"Dorfstrasse 8",
    "sg:city":"Birrhard",
    "sg:orig_category":"Kauf U Verkauf von Immobilien auf eigene Rechnung",
    "sg:phone":"+41 56 225 26 53",
    "sg:postcode":"5244",
    "sg:province":"Aargau",
    "wof:name":"Reusshalden Ag",
    "wof:placetype":"venue"
},
  "geometry": {"coordinates":[8.2425508499,47.4313468933],"type":"Point"}
}