{
  "type": "Feature",
  "properties": {
    "iso:country":"CH",
    "sg:address":"Giessh\u00fcbelstrasse 119 8045 Z\u00fcrich. Postfach",
    "sg:city":"Z\u00fcrich",
    "sg:orig_category":"Fotografische Ateliers",
    "sg:phone":"+41 81 322 50 66",
    "sg:postcode":"8045",
    "sg:province":"Z\u00fcrich",
    "wof:name":"Fortunat Anhorn Fotografie & Grafik",
    "wof:placetype":"venue"
},
  "geometry": {"coordinates":[9.5754261017,46.982963562],"type":"Point"}
}