{
  "type": "Feature",
  "properties": {
    "iso:country":"CH",
    "sg:address":"Grabenstrasse 11 8500 Frauenfeld. Postfach",
    "sg:city":"Frauenfeld",
    "sg:orig_category":"Polizei",
    "sg:phone":"+41 52 722 18 33",
    "sg:postcode":"8501",
    "sg:province":"Thurgau",
    "wof:name":"Kantonale Polizei",
    "wof:placetype":"venue"
},
  "geometry": {"coordinates":[8.897105217,47.5569801331],"type":"Point"}
}