{
  "type": "Feature",
  "properties": {
    "iso:country":"CH",
    "sg:address":"Hegenheimerstrasse 30",
    "sg:city":"Allschwil",
    "sg:orig_category":"Sanit\u00e4r, Heizungs U L\u00fcftungsinstallation Sanit\u00e4rinstallation",
    "sg:phone":"+41 61 483 83 00",
    "sg:postcode":"4123",
    "sg:province":"Basel-Landschaft",
    "wof:name":"Heimgartner & Partner Ag Sanit\u00e4re Anlagen",
    "wof:placetype":"venue"
},
  "geometry": {"coordinates":[7.5377898216,47.5524139404],"type":"Point"}
}