{
  "type": "Feature",
  "properties": {
    "iso:country":"CH",
    "sg:address":"4574",
    "sg:city":"Nennigkofen",
    "sg:orig_category":"Sportvereine Sch\u00fctzen",
    "sg:phone":"+41 56 622 86 32",
    "sg:postcode":"4574",
    "sg:province":"Solothurn",
    "wof:name":"Sch\u00fctzengesellschaft",
    "wof:placetype":"venue"
},
  "geometry": {"coordinates":[7.8687829971,47.3428268433],"type":"Point"}
}