{
  "type": "Feature",
  "properties": {
    "iso:country":"CH",
    "sg:address":"Sentib\u00fchlh\u00f6he 3",
    "sg:city":"Meggen",
    "sg:orig_category":"Datenverarbeitungsdienste Unternehmensberatung",
    "sg:phone":"+41 21 923 75 71",
    "sg:postcode":"6045",
    "sg:province":"Luzern",
    "wof:name":"Osima, Wicky Michel",
    "wof:placetype":"venue"
},
  "geometry": {"coordinates":[5.18087,45.897339],"type":"Point"}
}