{
  "type": "Feature",
  "properties": {
    "iso:country":"CH",
    "sg:address":"Tribschenstrasse 78a",
    "sg:city":"Luzern",
    "sg:classifiers":[
        {
            "category":"Government",
            "subcategory":"Post Office",
            "type":"Public Place"
        }
    ],
    "sg:phone":"+41 41 360 36 33",
    "sg:postcode":"6005",
    "sg:province":"Luzern",
    "sg:tags":[
        "caf\u00e9s",
        "tea-rooms"
    ],
    "wof:name":"Caf\u00e9 Pavillon",
    "wof:placetype":"venue"
},
  "geometry": {"coordinates":[8.3186941147,47.0416946411],"type":"Point"}
}