{
  "type": "Feature",
  "properties": {
    "iso:country":"CH",
    "sg:address":"Pfarrg\u00e4ssli 1",
    "sg:city":"Sumiswald",
    "sg:orig_category":"Detailhandel mit Blumen U Pflanzen",
    "sg:phone":"+41 34 431 27 67",
    "sg:postcode":"3454",
    "sg:province":"Bern",
    "wof:name":"Urs R\u00fcegg Blumen R\u00fcegg",
    "wof:placetype":"venue"
},
  "geometry": {"coordinates":[7.74557,47.028118],"type":"Point"}
}