{
  "type": "Feature",
  "properties": {
    "iso:country":"CH",
    "sg:address":"Kr\u00e4hb\u00fchlstrasse 76",
    "sg:city":"Z\u00fcrich",
    "sg:orig_category":"Softwareentwicklung U beratung Sonstige mit der Informatik verbundene T\u00e4tigkeiten",
    "sg:phone":"+41 12531600",
    "sg:postcode":"8044",
    "sg:province":"Z\u00fcrich",
    "wof:name":"Wolf Informatik",
    "wof:placetype":"venue"
},
  "geometry": {"coordinates":[8.5673742294,47.3783531189],"type":"Point"}
}