{
  "type": "Feature",
  "properties": {
    "iso:country":"CH",
    "sg:address":"Aemtlerstrasse 82a",
    "sg:city":"Z\u00fcrich",
    "sg:orig_category":"Sanit\u00e4rinstallation",
    "sg:phone":"+41 61 461 91 58",
    "sg:postcode":"8003",
    "sg:province":"Z\u00fcrich",
    "wof:name":"Thomas Baumgartner Sanibad",
    "wof:placetype":"venue"
},
  "geometry": {"coordinates":[7.7086219788,47.5347824097],"type":"Point"}
}