{
  "type": "Feature",
  "properties": {
    "iso:country":"CH",
    "sg:address":"Rotonda Via Alla 5 6517 Arbedo. Postfach",
    "sg:city":"Arbedo",
    "sg:orig_category":"Sonstiger Grosshandel",
    "sg:phone":"+41 79 240 12 80",
    "sg:postcode":"6517",
    "sg:province":"Ticino",
    "wof:name":"Sergio Nembrini Pneumatici Ricostruiti Import-export Di Articoli, Alimentari Ecc",
    "wof:placetype":"venue"
},
  "geometry": {"coordinates":[9.0411462784,46.2121315002],"type":"Point"}
}