{
  "type": "Feature",
  "properties": {
    "iso:country":"CH",
    "sg:address":"4943",
    "sg:city":"Oeschenbach",
    "sg:orig_category":"Detailhandel mit Milcherzeugnissen U Eiern Verarbeitung von Milch",
    "sg:phone":"+41 62 965 21 79",
    "sg:postcode":"4943",
    "sg:province":"Bern",
    "wof:name":"Peter Haslebacher K\u00e4serei",
    "wof:placetype":"venue"
},
  "geometry": {"coordinates":[7.7433300018,47.1128997803],"type":"Point"}
}