{
  "type": "Feature",
  "properties": {
    "iso:country":"CH",
    "sg:address":"Boiron Route Du 1",
    "sg:city":"Nyon",
    "sg:orig_category":"Fachdetailhandel in Verkaufsr\u00e4umen",
    "sg:phone":"+41 22 361 67 23",
    "sg:postcode":"1260",
    "sg:province":"Vaud",
    "wof:name":"Carol Dog Wash, Kursner Carol",
    "wof:placetype":"venue"
},
  "geometry": {"coordinates":[6.2390799522,46.3823661804],"type":"Point"}
}