{
  "type": "Feature",
  "properties": {
    "iso:country":"CH",
    "sg:address":"Rosswiesstrasse 27",
    "sg:city":"Bubikon",
    "sg:orig_category":"Herstellung von nachrichtentechnischen Ger\u00e4ten U Einrichtungen Herstellung von sonstigen elektrische",
    "sg:phone":"+41 55 253 40 50",
    "sg:postcode":"8608",
    "sg:province":"Z\u00fcrich",
    "wof:name":"R&m Robot Ag",
    "wof:placetype":"venue"
},
  "geometry": {"coordinates":[8.8255386353,47.2704048157],"type":"Point"}
}