{
  "type": "Feature",
  "properties": {
    "iso:country":"CH",
    "sg:address":"Route De Choulex 155",
    "sg:city":"Choulex",
    "sg:orig_category":"Maurerarbeiten",
    "sg:phone":"+41 22 750 24 61",
    "sg:postcode":"1244",
    "sg:province":"Gen\u00e8ve",
    "wof:name":"Olivier Cencioni Entreprise De Ma\u00e7onnerie",
    "wof:placetype":"venue"
},
  "geometry": {"coordinates":[6.2253570557,46.2246894836],"type":"Point"}
}