{
  "type": "Feature",
  "properties": {
    "iso:country":"CH",
    "sg:address":"7153",
    "sg:city":"Falera",
    "sg:orig_category":"Verkehrs- and Tourismusb\u00fcros",
    "sg:phone":"+41 71 368 50 50",
    "sg:postcode":"7153",
    "sg:province":"Graubunden",
    "wof:name":"Appenzellerland Tourismus",
    "wof:placetype":"venue"
},
  "geometry": {"coordinates":[9.3433551788,47.3754196167],"type":"Point"}
}