{
  "type": "Feature",
  "properties": {
    "iso:country":"CH",
    "sg:address":"Villa Negroni",
    "sg:city":"Vezia",
    "sg:classifiers":[
        {
            "category":"Banks & Credit Unions",
            "subcategory":"Bank",
            "type":"Services"
        }
    ],
    "sg:phone":"+41 4191560569",
    "sg:postcode":"6943",
    "sg:province":"Ticino",
    "wof:name":"Bancaria Ticinese",
    "wof:placetype":"venue"
},
  "geometry": {"coordinates":[8.937485,46.023643],"type":"Point"}
}