{
  "type": "Feature",
  "properties": {
    "iso:country":"CH",
    "sg:address":"Landstrasse 54 5430 Wettingen. Postfach 61",
    "sg:city":"Wettingen",
    "sg:orig_category":"Druck ohne Zeitungsdruck",
    "sg:phone":"+41 56 437 88 88",
    "sg:postcode":"5430",
    "sg:province":"Aargau",
    "wof:name":"H\u00e4fliger Druck Ag",
    "wof:placetype":"venue"
},
  "geometry": {"coordinates":[8.3224582672,47.4675788879],"type":"Point"}
}