{
  "type": "Feature",
  "properties": {
    "iso:country":"CH",
    "sg:address":"Rue De Lyon 16 1200 Genf. Postfach",
    "sg:city":"Gen\u00e8ve",
    "sg:classifiers":[
        {
            "category":"Bars & Pubs",
            "type":"Food & Drink"
        }
    ],
    "sg:postcode":"1201",
    "sg:province":"Gen\u00e8ve",
    "wof:name":"Mcf Concept S\u00e0rl",
    "wof:placetype":"venue"
},
  "geometry": {"coordinates":[6.136579,46.208866],"type":"Point"}
}