{
  "type": "Feature",
  "properties": {
    "iso:country":"CH",
    "sg:address":"Hauptstrasse 9",
    "sg:city":"Ober\u00e4geri",
    "sg:orig_category":"Detailhandel mit Geschenkartikeln U Souvenirs",
    "sg:phone":"+41 41 752 14 20",
    "sg:postcode":"6315",
    "sg:province":"Zug",
    "wof:name":"S'l\u00e4deli Geschenk-boutique",
    "wof:placetype":"venue"
},
  "geometry": {"coordinates":[8.6133480072,47.1348953247],"type":"Point"}
}