{
  "type": "Feature",
  "properties": {
    "iso:country":"CH",
    "sg:address":"Route De Bruy\u00e8re",
    "sg:city":"Domdidier",
    "sg:orig_category":"Zimmerei, Dachdeckerei, Bauspenglerei U Abdichtung Zimmerei, Ingenieurholzbau",
    "sg:phone":"+41 26 675 12 24",
    "sg:postcode":"1564",
    "sg:province":"Fribourg",
    "wof:name":"Stauffacher Charpentes Sa",
    "wof:placetype":"venue"
},
  "geometry": {"coordinates":[7.0105419159,46.8584022522],"type":"Point"}
}