{
  "type": "Feature",
  "properties": {
    "iso:country":"CH",
    "sg:address":"Zentralstrasse 38a",
    "sg:city":"Luzern",
    "sg:orig_category":"Architektur U Ingenieurb\u00fcros Architekturb\u00fcros",
    "sg:phone":"+41 41 226 36 66",
    "sg:postcode":"6003",
    "sg:province":"Luzern",
    "wof:name":"Tgs Partner Architekten T\u00fcfer P., Gr\u00fcter M., Moser A.",
    "wof:placetype":"venue"
},
  "geometry": {"coordinates":[8.309679,47.046852],"type":"Point"}
}