{
  "type": "Feature",
  "properties": {
    "iso:country":"CH",
    "sg:address":"J.c. Fischer-strasse 7",
    "sg:city":"Schaffhausen",
    "sg:orig_category":"Unternehmensberatung Werbeberatung",
    "sg:phone":"+41 52 624 63 13",
    "sg:postcode":"8200",
    "sg:province":"Schaffhausen",
    "wof:name":"Wem Gmbh",
    "wof:placetype":"venue"
},
  "geometry": {"coordinates":[8.6316728592,47.7026786804],"type":"Point"}
}