{
  "type": "Feature",
  "properties": {
    "iso:country":"CH",
    "sg:address":"Route De Thonon 72",
    "sg:city":"Collonge-bellerive",
    "sg:orig_category":"Sonstiger Grosshandel",
    "sg:phone":"+41 22 752 58 60",
    "sg:postcode":"1245",
    "sg:province":"Gen\u00e8ve",
    "wof:name":"Jean-luc Frey Import-export",
    "wof:placetype":"venue"
},
  "geometry": {"coordinates":[6.2131848335,46.246963501],"type":"Point"}
}