{
  "type": "Feature",
  "properties": {
    "iso:country":"CH",
    "sg:address":"Aspermontstrasse 4 7000 Chur. Postfach",
    "sg:city":"Chur",
    "sg:orig_category":"Finanzierungsinstitutionen",
    "sg:postcode":"7000",
    "sg:province":"Graubunden",
    "wof:name":"Arcom Ag.",
    "wof:placetype":"venue"
},
  "geometry": {"coordinates":[9.5292005539,46.8603210449],"type":"Point"}
}