{
  "type": "Feature",
  "properties": {
    "iso:country":"CH",
    "sg:address":"Vouvry-centre",
    "sg:city":"Vouvry",
    "sg:classifiers":[
        {
            "category":"Insurance",
            "subcategory":"Insurance Agent",
            "type":"Services"
        }
    ],
    "sg:phone":"+41 24 481 32 89",
    "sg:postcode":"1896",
    "sg:province":"Valais",
    "sg:tags":[
        "versicherungsagenturen",
        "-broker"
    ],
    "wof:name":"Winterthur Assurances Agence",
    "wof:placetype":"venue"
},
  "geometry": {"coordinates":[6.8908228874,46.3360748291],"type":"Point"}
}