{
  "type": "Feature",
  "properties": {
    "iso:country":"CH",
    "sg:address":"Place Du Pas",
    "sg:city":"Vernayaz",
    "sg:orig_category":"Detailhandel mit Computern U Software Unternehmensberatung",
    "sg:phone":"+41 27 764 30 60",
    "sg:postcode":"1904",
    "sg:province":"Valais",
    "wof:name":"Linsoft Sarl",
    "wof:placetype":"venue"
},
  "geometry": {"coordinates":[7.043753,46.134968],"type":"Point"}
}