{
  "type": "Feature",
  "properties": {
    "iso:country":"CH",
    "sg:address":"St. Gallerstrasse 5",
    "sg:city":"Rorschach",
    "sg:orig_category":"Sonstiger spezialisierter Hoch U Tiefbau Strassenbau",
    "sg:phone":"+41 71 841 45 11",
    "sg:postcode":"9400",
    "sg:province":"St. Gallen",
    "wof:name":"Passeri Ag",
    "wof:placetype":"venue"
},
  "geometry": {"coordinates":[9.4881448746,47.4788131714],"type":"Point"}
}