{
  "type": "Feature",
  "properties": {
    "iso:country":"CH",
    "sg:address":"Route De Massongex",
    "sg:city":"Bex",
    "sg:orig_category":"Instandhaltung U Reparatur von Automobilen",
    "sg:phone":"+41 24 463 17 73",
    "sg:postcode":"1880",
    "sg:province":"Vaud",
    "wof:name":"Carrosserie Nino - Iannalfo L.",
    "wof:placetype":"venue"
},
  "geometry": {"coordinates":[7.0030260086,46.246837616],"type":"Point"}
}