{
  "type": "Feature",
  "properties": {
    "iso:country":"CH",
    "sg:address":"Im Fahr 7 6035 Perlen. Postfach",
    "sg:city":"Perlen",
    "sg:orig_category":"Sonstige mit der Informatik verbundene T\u00e4tigkeiten",
    "sg:postcode":"6035",
    "sg:province":"Luzern",
    "wof:name":"Baroni Interactive Dienstleistungen Im Multimedia-bereich. Edv-hard- U. Software; Handel U. Support",
    "wof:placetype":"venue"
},
  "geometry": {"coordinates":[8.3514375687,47.1046142578],"type":"Point"}
}