{
  "type": "Feature",
  "properties": {
    "iso:country":"CH",
    "sg:address":"Schl\u00f6ssliweg 2",
    "sg:city":"Rorschacherberg",
    "sg:orig_category":"Vereine Briefmarkensammler",
    "sg:phone":"+41 71 855 25 76",
    "sg:postcode":"9404",
    "sg:province":"St. Gallen",
    "wof:name":"Philatelistencl.reg.rorschach",
    "wof:placetype":"venue"
},
  "geometry": {"coordinates":[9.5111217499,47.4766273499],"type":"Point"}
}