{
  "type": "Feature",
  "properties": {
    "iso:country":"CH",
    "sg:address":"Im Gwidem 29",
    "sg:city":"Pfeffingen",
    "sg:classifiers":[
        {
            "category":"Communications",
            "subcategory":"Radio Station",
            "type":"Services"
        }
    ],
    "sg:phone":"+41 61 753 07 07",
    "sg:postcode":"4148",
    "sg:province":"Basel-Landschaft",
    "sg:tags":[
        "fernsehanstalten",
        "u"
    ],
    "wof:name":"Benny Fasnacht Visual Communication",
    "wof:placetype":"venue"
},
  "geometry": {"coordinates":[7.5870752335,47.4619636536],"type":"Point"}
}