{
  "type": "Feature",
  "properties": {
    "iso:country":"CH",
    "sg:address":"Mettlenstrasse 33b",
    "sg:city":"Eglisau",
    "sg:classifiers":[
        {
            "category":"Shopping",
            "subcategory":"Computers & Home Electronics",
            "type":"Retail Goods"
        }
    ],
    "sg:phone":"+41 18670049",
    "sg:postcode":"8193",
    "sg:province":"Z\u00fcrich",
    "sg:tags":[
        "device",
        "alarm"
    ],
    "wof:name":"Girsberger Elektronik Ag",
    "wof:placetype":"venue"
},
  "geometry": {"coordinates":[8.518415,47.574123],"type":"Point"}
}