{
  "type": "Feature",
  "properties": {
    "iso:country":"CH",
    "sg:address":"Sack 247",
    "sg:city":"Aathal-seegr\u00e4ben",
    "sg:orig_category":"Wirtschaftsverb\u00e4nde Gewerbeverb\u00e4nde/-vereine",
    "sg:phone":"+41 71 310 16 16",
    "sg:postcode":"8607",
    "sg:province":"Z\u00fcrich",
    "wof:name":"Gewerbeverein Abtwil-engelburg",
    "wof:placetype":"venue"
},
  "geometry": {"coordinates":[9.3277330399,47.4249954224],"type":"Point"}
}