{
  "type": "Feature",
  "properties": {
    "iso:country":"CH",
    "sg:address":"Bahnhofplatz 9-11",
    "sg:city":"Liestal",
    "sg:orig_category":"Handelsvermittlung U Grosshandel Herstellung von k\u00e4lte U lufttechnischen Erzeugnissen f\u00fcr gewerblich",
    "sg:phone":"+41 61 921 27 80",
    "sg:postcode":"4410",
    "sg:province":"Basel-Landschaft",
    "wof:name":"Ltb Ag Lufttechn. Bauelemente",
    "wof:placetype":"venue"
},
  "geometry": {"coordinates":[7.7308058739,47.4851913452],"type":"Point"}
}