{
  "type": "Feature",
  "properties": {
    "addr:full":"Chilestieg 26 8153 R\u00fcmlang. Postfach 270 R\u00fcmlang Z\u00fcrich 8153",
    "addr:housenumber":"26;270",
    "addr:postcode":"8153;8153",
    "addr:street":"Chilestieg;Postfach;Zuerich",
    "iso:country":"CH",
    "sg:address":"Chilestieg 26 8153 R\u00fcmlang. Postfach 270",
    "sg:city":"R\u00fcmlang",
    "sg:orig_category":"Architektur U Ingenieurb\u00fcros Innenarchitekturb\u00fcros",
    "sg:phone":"+41 18180267",
    "sg:postcode":"8153",
    "sg:province":"Z\u00fcrich",
    "wof:name":"Peter Cvetko Technisches B\u00fcro",
    "wof:placetype":"venue"
},
  "geometry": {"coordinates":[8.526539,47.447735],"type":"Point"}
}