{
  "type": "Feature",
  "properties": {
    "iso:country":"CH",
    "sg:address":"Dufourstrasse 1",
    "sg:city":"Lenzburg",
    "sg:orig_category":"Fahrschulen, Flugschulen",
    "sg:phone":"+41 62 891 50 70",
    "sg:postcode":"5600",
    "sg:province":"Aargau",
    "wof:name":"Hans-peter Proff Autofahrschule",
    "wof:placetype":"venue"
},
  "geometry": {"coordinates":[8.1588144302,47.3886451721],"type":"Point"}
}