{
  "type": "Feature",
  "properties": {
    "iso:country":"CH",
    "sg:address":"Via Galbisio 75d",
    "sg:city":"Bellinzona",
    "sg:orig_category":"Rolladen- and Storenmontage",
    "sg:phone":"+41 91 826 13 41",
    "sg:postcode":"6503",
    "sg:province":"Ticino",
    "wof:name":"Wolf Profilierwerk Sa",
    "wof:placetype":"venue"
},
  "geometry": {"coordinates":[9.030667305,46.2116851807],"type":"Point"}
}