{
  "type": "Feature",
  "properties": {
    "iso:country":"CH",
    "sg:address":"Unterwiesenstrasse 16",
    "sg:city":"Aadorf",
    "sg:orig_category":"Sportvereine Turnen",
    "sg:postcode":"8355",
    "sg:province":"Thurgau",
    "wof:name":"Athletik-sport-club Aadorf",
    "wof:placetype":"venue"
},
  "geometry": {"coordinates":[8.9073791504,47.4951324463],"type":"Point"}
}