{
  "type": "Feature",
  "properties": {
    "iso:country":"CH",
    "sg:address":"Gyrenstrasse 11",
    "sg:city":"Widen",
    "sg:orig_category":"Non-Classified Establishments",
    "sg:postcode":"8967",
    "sg:province":"Aargau",
    "wof:name":"Hightec-shop Gmbh",
    "wof:placetype":"venue"
},
  "geometry": {"coordinates":[8.3549633026,47.366973877],"type":"Point"}
}