{
  "type": "Feature",
  "properties": {
    "iso:country":"CH",
    "sg:address":"Neugasse 6 9400 Rorschach. Postfach",
    "sg:city":"Rorschach",
    "sg:orig_category":"Fachdetailhandel in Verkaufsr\u00e4umen",
    "sg:postcode":"9400",
    "sg:province":"St. Gallen",
    "wof:name":"Blumenhof Schoch Christian",
    "wof:placetype":"venue"
},
  "geometry": {"coordinates":[9.4919204712,47.4784812927],"type":"Point"}
}