{
  "type": "Feature",
  "properties": {
    "iso:country":"CH",
    "sg:address":"Gestenrietstrasse 2 8307 Effretikon. Postfach 298",
    "sg:city":"Effretikon",
    "sg:orig_category":"Detailhandel mit Haustieren U zoologischem Bedarf Fachdetailhandel in Verkaufsr\u00e4umen",
    "sg:phone":"+41 52 343 76 30",
    "sg:postcode":"8307",
    "sg:province":"Z\u00fcrich",
    "wof:name":"Animal-love Nazzareno Mancini",
    "wof:placetype":"venue"
},
  "geometry": {"coordinates":[8.6850128174,47.429069519],"type":"Point"}
}