{
  "type": "Feature",
  "properties": {
    "iso:country":"CH",
    "sg:address":"Industriezone Hintere R\u00fcti",
    "sg:city":"W\u00e4denswil",
    "sg:orig_category":"Betrieb von Sportanlagen",
    "sg:phone":"+41 17811015",
    "sg:postcode":"8820",
    "sg:province":"Z\u00fcrich",
    "wof:name":"Tennishalle Neub\u00fchl W\u00e4denswil Ag",
    "wof:placetype":"venue"
},
  "geometry": {"coordinates":[8.636277,47.234348],"type":"Point"}
}