{
  "type": "Feature",
  "properties": {
    "iso:country":"CH",
    "sg:address":"Rue De Riant-coteau 11",
    "sg:city":"Gland",
    "sg:orig_category":"Herstellung von K\u00fcchenm\u00f6beln",
    "sg:phone":"+41 22 995 02 12",
    "sg:postcode":"1196",
    "sg:province":"Vaud",
    "wof:name":"Anc S\u00e0rl",
    "wof:placetype":"venue"
},
  "geometry": {"coordinates":[6.2829709053,46.4196014404],"type":"Point"}
}