{
  "type": "Feature",
  "properties": {
    "iso:country":"CH",
    "sg:address":"Bachtobelstrasse 10 8045 Z\u00fcrich. Postfach",
    "sg:city":"Z\u00fcrich",
    "sg:orig_category":"Elektroinstallation",
    "sg:phone":"+41 79 226 74 08",
    "sg:postcode":"8045",
    "sg:province":"Z\u00fcrich",
    "wof:name":"Elektra Z\u00fcrich Ag F\u00fcr Elektrotechnische Anlagen Elektr. Installationen. Elektr. Apparate; Handel Usw",
    "wof:placetype":"venue"
},
  "geometry": {"coordinates":[8.51674366,47.3613739014],"type":"Point"}
}