{
  "type": "Feature",
  "properties": {
    "iso:country":"CH",
    "sg:address":"Molkereistrasse 1",
    "sg:city":"Jona",
    "sg:classifiers":[
        {
            "category":"Restaurant",
            "type":"Food & Drink"
        }
    ],
    "sg:phone":"+41 55 212 65 60",
    "sg:postcode":"8645",
    "sg:province":"St. Gallen",
    "wof:name":"Wirtschaft Zum Stadttor",
    "wof:placetype":"venue"
},
  "geometry": {"coordinates":[8.8371505737,47.2309494019],"type":"Point"}
}