{
  "type": "Feature",
  "properties": {
    "iso:country":"CH",
    "sg:address":"2853",
    "sg:city":"Courfaivre",
    "sg:orig_category":"Detailhandel mit Brot, Back U S\u00fcsswaren",
    "sg:phone":"+41 32 426 89 66",
    "sg:postcode":"2853",
    "sg:province":"Jura",
    "wof:name":"Marcel Jubin Boulangerie",
    "wof:placetype":"venue"
},
  "geometry": {"coordinates":[7.280702,47.334412],"type":"Point"}
}