{
  "type": "Feature",
  "properties": {
    "iso:country":"CH",
    "sg:address":"Hauptstrasse 203",
    "sg:city":"Oberbuchsiten",
    "sg:orig_category":"Gesundheitswesen",
    "sg:postcode":"4625",
    "sg:province":"Solothurn",
    "wof:name":"Coaching K\u00fcnzle Franziska",
    "wof:placetype":"venue"
},
  "geometry": {"coordinates":[7.7656259537,47.3093490601],"type":"Point"}
}