{
  "type": "Feature",
  "properties": {
    "iso:country":"CH",
    "sg:address":"Plaz Da Posta",
    "sg:city":"Andeer",
    "sg:orig_category":"Physiotherapie",
    "sg:phone":"+41 81 661 16 54",
    "sg:postcode":"7440",
    "sg:province":"Graubunden",
    "wof:name":"Edwin Koelman Physiotherapie",
    "wof:placetype":"venue"
},
  "geometry": {"coordinates":[9.4274578094,46.6025886536],"type":"Point"}
}