{
  "type": "Feature",
  "properties": {
    "iso:country":"CH",
    "sg:address":"Els\u00e4sserstrasse 1",
    "sg:city":"Basel",
    "sg:orig_category":"RESTAURANTS: TEA-ROOMS",
    "sg:postcode":"4056",
    "sg:province":"Basel-Stadt",
    "wof:name":"Giovanni Parrino",
    "wof:placetype":"venue"
},
  "geometry": {"coordinates":[7.5814189911,47.5666847229],"type":"Point"}
}