{
  "type": "Feature",
  "properties": {
    "iso:country":"CH",
    "sg:address":"Stedtligass 16",
    "sg:city":"Gr\u00fcningen",
    "sg:classifiers":[
        {
            "category":"Restaurant",
            "type":"Food & Drink"
        }
    ],
    "sg:phone":"+41 19351165",
    "sg:postcode":"8627",
    "sg:province":"Z\u00fcrich",
    "wof:name":"Restaurant Hirschen",
    "wof:placetype":"venue"
},
  "geometry": {"coordinates":[8.7637252808,47.2843933105],"type":"Point"}
}