{
  "type": "Feature",
  "properties": {
    "iso:country":"CH",
    "sg:address":"Strohackerstrasse 22",
    "sg:city":"Niederg\u00f6sgen",
    "sg:orig_category":"Sonstige pers\u00f6nliche Dienstleistungen",
    "sg:phone":"+41 62 849 57 26",
    "sg:postcode":"5013",
    "sg:province":"Solothurn",
    "wof:name":"Elen Buda V.",
    "wof:placetype":"venue"
},
  "geometry": {"coordinates":[7.9884371758,47.3696250916],"type":"Point"}
}