{
  "type": "Feature",
  "properties": {
    "iso:country":"CH",
    "sg:address":"Jurastrasse 4",
    "sg:city":"Wettingen",
    "sg:orig_category":"Grosshandel mit Holz U Bauelementen aus Holz Grosshandel mit Holz U Baustoffen",
    "sg:phone":"+41 56 426 65 29",
    "sg:postcode":"5430",
    "sg:province":"Aargau",
    "wof:name":"August Berz, Holzhandel, Lagervermietung",
    "wof:placetype":"venue"
},
  "geometry": {"coordinates":[8.3316516876,47.4624328613],"type":"Point"}
}