{
  "type": "Feature",
  "properties": {
    "iso:country":"CH",
    "sg:address":"6802 Rivera. Postfach",
    "sg:city":"Rivera",
    "sg:orig_category":"Herstellung von Metallkonstruktionen",
    "sg:phone":"+41 81 756 45 86",
    "sg:postcode":"6802",
    "sg:province":"Ticino",
    "wof:name":"Power Job Ag",
    "wof:placetype":"venue"
},
  "geometry": {"coordinates":[9.478020668,47.1672058105],"type":"Point"}
}