{
  "type": "Feature",
  "properties": {
    "iso:country":"CH",
    "sg:address":"Chemin Des Collines 41",
    "sg:city":"Sion",
    "sg:orig_category":"Stukkateurgewerbe, Gipserei U Verputzerei",
    "sg:phone":"+41 27 322 28 02",
    "sg:postcode":"1950",
    "sg:province":"Valais",
    "wof:name":"Blanc & Duc Sa",
    "wof:placetype":"venue"
},
  "geometry": {"coordinates":[7.3510141373,46.2309570312],"type":"Point"}
}