{
  "type": "Feature",
  "properties": {
    "iso:country":"CH",
    "sg:address":"Brunnenwiesenstrasse 11",
    "sg:city":"Dietlikon",
    "sg:orig_category":"P\u00e9dicure",
    "sg:phone":"+41 26 496 22 84",
    "sg:postcode":"8305",
    "sg:province":"Z\u00fcrich",
    "wof:name":"Verena Tamani Fuss-studio Vreni",
    "wof:placetype":"venue"
},
  "geometry": {"coordinates":[7.2413711548,46.850818634],"type":"Point"}
}