{
  "type": "Feature",
  "properties": {
    "iso:country":"CH",
    "sg:address":"Geisshaldenweg 24 5242 Birr-lupfig. Postfach",
    "sg:city":"Birr-lupfig",
    "sg:orig_category":"Grosshandel mit Textilien",
    "sg:phone":"+41 56 444 89 14",
    "sg:postcode":"5242",
    "sg:province":"Aargau",
    "wof:name":"Stebler Fashion Gmbh Textilhandelsunternehmen Usw",
    "wof:placetype":"venue"
},
  "geometry": {"coordinates":[8.2027254105,47.4361724854],"type":"Point"}
}