{
  "type": "Feature",
  "properties": {
    "iso:country":"CH",
    "sg:address":"Dorfstrasse 1",
    "sg:city":"Trub",
    "sg:orig_category":"Gewinnung von Kies U Sand",
    "sg:postcode":"3556",
    "sg:province":"Bern",
    "wof:name":"Sch\u00e4chli Kies + Beton Ag",
    "wof:placetype":"venue"
},
  "geometry": {"coordinates":[7.8769898415,46.9407691956],"type":"Point"}
}