{
  "type": "Feature",
  "properties": {
    "iso:country":"CH",
    "sg:address":"Kieselgasse 9 8000 Z\u00fcrich. Postfach",
    "sg:city":"Z\u00fcrich",
    "sg:orig_category":"Sonstige pers\u00f6nliche Dienstleistungen",
    "sg:postcode":"8008",
    "sg:province":"Z\u00fcrich",
    "wof:name":"Life Imaging Services Gmbh",
    "wof:placetype":"venue"
},
  "geometry": {"coordinates":[7.6003937721,47.4883308411],"type":"Point"}
}