{
  "type": "Feature",
  "properties": {
    "addr:full":"Ritterstrasse 18 3951 Agarn. Postfach Littau Luzern 6014",
    "addr:housenumber":"18",
    "addr:postcode":"3951;6014",
    "addr:street":"Ritterstrasse;Postfach",
    "iso:country":"CH",
    "sg:address":"Ritterstrasse 18 3951 Agarn. Postfach",
    "sg:city":"Littau",
    "sg:orig_category":"Allgemeiner Hochbau Strassenbau",
    "sg:phone":"+41 41 250 32 57",
    "sg:postcode":"6014",
    "sg:province":"Luzern",
    "wof:name":"L\u00f6tscher Tiefbau Ag",
    "wof:placetype":"venue"
},
  "geometry": {"coordinates":[7.663592,46.296951],"type":"Point"}
}