{
  "type": "Feature",
  "properties": {
    "iso:country":"CH",
    "sg:address":"Trevano Via 38 6900 Calprino. Postfach 6906 Lugano",
    "sg:city":"Caselle",
    "sg:orig_category":"Unternehmensberatung",
    "sg:postcode":"6",
    "wof:name":"National & International Developments Ltd, Dublino, Succursale Di Lugano Consulenza, Progettazione, Intermediazione Nel Sett. Industriale, Turistico Ecc",
    "wof:placetype":"venue"
},
  "geometry": {"coordinates":[8.9513053894,46.0029754639],"type":"Point"}
}