{
  "type": "Feature",
  "properties": {
    "iso:country":"CH",
    "sg:address":"Schacheng\u00e4ssli 96",
    "sg:city":"Aefligen",
    "sg:orig_category":"Detailhandel mit Waren verschiedener Art, Hauptrichtung Nahrungsmittel",
    "sg:phone":"+41 34 445 21 73",
    "sg:postcode":"3426",
    "sg:province":"Bern",
    "wof:name":"Coop Bern/biel",
    "wof:placetype":"venue"
},
  "geometry": {"coordinates":[7.5620598793,47.0937614441],"type":"Point"}
}