{
  "type": "Feature",
  "properties": {
    "iso:country":"CH",
    "sg:address":"Neumattstrasse 24",
    "sg:city":"Dietikon",
    "sg:orig_category":"Verwaltung von Immobilien",
    "sg:postcode":"8953",
    "sg:province":"Z\u00fcrich",
    "wof:name":"Ernst Hofer Immocom Gmbh",
    "wof:placetype":"venue"
},
  "geometry": {"coordinates":[8.4033203125,47.4068107605],"type":"Point"}
}