{
  "type": "Feature",
  "properties": {
    "iso:country":"CH",
    "sg:address":"Gloten",
    "sg:city":"Sirnach",
    "sg:orig_category":"Handel mit Automobilen",
    "sg:phone":"+41 71 966 52 70",
    "sg:postcode":"8370",
    "sg:province":"Thurgau",
    "wof:name":"Surber Automobile Ag Garage",
    "wof:placetype":"venue"
},
  "geometry": {"coordinates":[9.0218801498,47.4632797241],"type":"Point"}
}