{
  "type": "Feature",
  "properties": {
    "iso:country":"CH",
    "sg:address":"Harlachenstrasse 9",
    "sg:city":"Fislisbach",
    "sg:orig_category":"Non-Classified Establishments",
    "sg:postcode":"5442",
    "sg:province":"Aargau",
    "wof:name":"Aerbet Ag",
    "wof:placetype":"venue"
},
  "geometry": {"coordinates":[8.2899122238,47.4333686829],"type":"Point"}
}