{
  "type": "Feature",
  "properties": {
    "addr:full":"Hinterdorfstrasse 36 Oeschgen 5263",
    "addr:housenumber":"36",
    "addr:postcode":"5263",
    "addr:street":"Hinterdorfstrasse",
    "iso:country":"CH",
    "sg:address":"Hinterdorfstrasse 36",
    "sg:city":"Oeschgen",
    "sg:classifiers":[
        {
            "category":"Banks & Credit Unions",
            "subcategory":"Bank",
            "type":"Services"
        }
    ],
    "sg:phone":"+41 4164613249",
    "sg:postcode":"5263",
    "wof:name":"Schweiz. Mobiliar",
    "wof:placetype":"venue"
},
  "geometry": {"coordinates":[8.019833,47.516434],"type":"Point"}
}