{
  "type": "Feature",
  "properties": {
    "iso:country":"CH",
    "sg:address":"Micheli-du-crest Rue 16 1200 Genf. Postfach",
    "sg:city":"Gen\u00e8ve",
    "sg:orig_category":"RESTAURANTS: TEA-ROOMS",
    "sg:postcode":"1205",
    "sg:province":"Gen\u00e8ve",
    "wof:name":"Ferreira Antonella",
    "wof:placetype":"venue"
},
  "geometry": {"coordinates":[6.1474881172,46.1946411133],"type":"Point"}
}