{
  "type": "Feature",
  "properties": {
    "iso:country":"CH",
    "sg:address":"Neubadstrasse 83 4054 Basel. Postfach",
    "sg:city":"Basel",
    "sg:orig_category":"Pensionskassen",
    "sg:postcode":"4051",
    "sg:province":"Basel-Stadt",
    "wof:name":"Stiftung Des Vereins F\u00fcr Hauspflege St. Leonhard-paulus-stephanus, Basel Ehemalige O. Aktive Mitarbeiter, In Ausnahmef\u00e4llen Beduerftige Patient En D. Vereins; Unterst\u00fctzung Usw",
    "wof:placetype":"venue"
},
  "geometry": {"coordinates":[7.5696630478,47.5487594604],"type":"Point"}
}