{
  "type": "Feature",
  "properties": {
    "iso:country":"CH",
    "sg:address":"Dohlenweg 6",
    "sg:city":"Z\u00fcrich",
    "sg:orig_category":"Detailhandel mit Teppichen",
    "sg:phone":"+41 13020729",
    "sg:postcode":"8050",
    "sg:province":"Z\u00fcrich",
    "wof:name":"Matthias Anton Camenisch Aca-teppich-center",
    "wof:placetype":"venue"
},
  "geometry": {"coordinates":[8.5470542908,47.4162445068],"type":"Point"}
}