{
  "type": "Feature",
  "properties": {
    "iso:country":"CH",
    "sg:address":"Avenue Du Grand-pont 26 1095 Ch\u00e2telard-lutry Case Postale 286",
    "sg:city":"Ch\u00e2telard-lutry",
    "sg:orig_category":"Bauspenglerei Sanit\u00e4r, Heizungs U L\u00fcftungsinstallation",
    "sg:phone":"+41 21 624 14 81",
    "sg:postcode":"1095",
    "sg:province":"Vaud",
    "wof:name":"Brauchli Sa",
    "wof:placetype":"venue"
},
  "geometry": {"coordinates":[6.617887,46.52544],"type":"Point"}
}