{
  "type": "Feature",
  "properties": {
    "iso:country":"CH",
    "sg:address":"Grand-rue 2",
    "sg:city":"Peseux",
    "sg:orig_category":"Stukkateurgewerbe, Gipserei U Verputzerei",
    "sg:phone":"+41 32 731 71 47",
    "sg:postcode":"2034",
    "sg:province":"Neuch\u00e2tel",
    "wof:name":"Matthey Denis",
    "wof:placetype":"venue"
},
  "geometry": {"coordinates":[6.8872408867,46.9863548279],"type":"Point"}
}