{
  "type": "Feature",
  "properties": {
    "iso:country":"CH",
    "sg:address":"Hintere Gasse 23",
    "sg:city":"Meinisberg",
    "sg:orig_category":"Organisationen des Gesundheitswesen",
    "sg:phone":"+41 32372248",
    "sg:postcode":"2554",
    "sg:province":"Bern",
    "wof:name":"Samariterverein Meinisberg",
    "wof:placetype":"venue"
},
  "geometry": {"coordinates":[7.3470859528,47.1592330933],"type":"Point"}
}