{
  "type": "Feature",
  "properties": {
    "iso:country":"CH",
    "sg:city":"Rodi Fiesso",
    "sg:classifiers":[
        {
            "category":"Banks & Credit Unions",
            "subcategory":"Bank",
            "type":"Services"
        }
    ],
    "sg:phone":"+41 91 881 10 00",
    "sg:postcode":"6772",
    "sg:province":"Ticino",
    "wof:name":"Raiffeisen Leventina",
    "wof:placetype":"venue"
},
  "geometry": {"coordinates":[8.737402,46.490257],"type":"Point"}
}