{
  "type": "Feature",
  "properties": {
    "iso:country":"CH",
    "sg:address":"Grand-rue 122",
    "sg:city":"Tramelan",
    "sg:classifiers":[
        {
            "category":"Travel",
            "subcategory":"Hotels & Motels",
            "type":"Entertainment"
        }
    ],
    "sg:phone":"+41 26 477 10 05",
    "sg:postcode":"2720",
    "sg:province":"Bern",
    "sg:tags":[
        "hotels",
        "mit",
        "restaurant"
    ],
    "wof:name":"H\u00f4tel La Chaumi\u00e8re",
    "wof:placetype":"venue"
},
  "geometry": {"coordinates":[7.0701651573,46.7708892822],"type":"Point"}
}