{
  "type": "Feature",
  "properties": {
    "iso:country":"CH",
    "sg:address":"Gl\u00e4rnischstrasse",
    "sg:city":"M\u00e4nnedorf",
    "sg:orig_category":"Kinderkrippen U horte",
    "sg:phone":"+41 19211904",
    "sg:postcode":"8708",
    "sg:province":"Z\u00fcrich",
    "wof:name":"Kinderhort Schulhaus Hasenacker Ii",
    "wof:placetype":"venue"
},
  "geometry": {"coordinates":[8.6997060776,47.2540740967],"type":"Point"}
}