{
  "type": "Feature",
  "properties": {
    "iso:country":"CH",
    "sg:address":"Schnabelsberg 25",
    "sg:city":"Bennau",
    "sg:orig_category":"RESTAURANTS: TEA-ROOMS",
    "sg:postcode":"8836",
    "sg:province":"Schwyz",
    "wof:name":"Reiner-catillaz Max",
    "wof:placetype":"venue"
},
  "geometry": {"coordinates":[8.6694488525,47.7550163269],"type":"Point"}
}