{
  "type": "Feature",
  "properties": {
    "iso:country":"CH",
    "sg:address":"Hauptstrasse 116a 6436 Muotathal. Postfach",
    "sg:city":"Muotathal",
    "sg:orig_category":"Detailhandel mit Waren verschiedener Art, Hauptrichtung Nahrungsmittel Grosshandel mit Nahrungsmitte",
    "sg:phone":"+41 41 830 22 91",
    "sg:postcode":"6436",
    "sg:province":"Schwyz",
    "wof:name":"Epa Superdiscount, Betschart-f\u00f6hn R. Und I. Lebensmittel; Verkauf",
    "wof:placetype":"venue"
},
  "geometry": {"coordinates":[8.7663125992,46.9722938538],"type":"Point"}
}