{
  "type": "Feature",
  "properties": {
    "iso:country":"CH",
    "sg:address":"Feldstrasse 14 8580 Amriswil. Postfach 1673",
    "sg:city":"Amriswil",
    "sg:orig_category":"Verwaltung von Immobilien Wirtschaftspr\u00fcfung, Steuerberatung U Treuhand",
    "sg:phone":"+41 55 644 31 53",
    "sg:postcode":"8580",
    "sg:province":"Thurgau",
    "wof:name":"D\u00fcrig Urs Treuhand Gmbh",
    "wof:placetype":"venue"
},
  "geometry": {"coordinates":[9.0702581406,46.9948196411],"type":"Point"}
}