{
  "type": "Feature",
  "properties": {
    "iso:country":"CH",
    "sg:address":"Rathausgasse 21 5000 Aarau. Postfach",
    "sg:city":"Aarau",
    "sg:orig_category":"\u00dcbersetzungsb\u00fcros",
    "sg:phone":"+41 62 822 24 02",
    "sg:postcode":"5000",
    "sg:province":"Aargau",
    "wof:name":"Eva Frauenfelder Intra Uebersetzungsb\u00fcro",
    "wof:placetype":"venue"
},
  "geometry": {"coordinates":[8.0440816879,47.3926620483],"type":"Point"}
}