{
  "type": "Feature",
  "properties": {
    "iso:country":"CH",
    "sg:address":"8360",
    "sg:city":"Wallenwil",
    "sg:orig_category":"Sportvereine Sch\u00fctzen",
    "sg:postcode":"8360",
    "sg:province":"Thurgau",
    "wof:name":"Feldsch\u00fctzenges.wolfwil",
    "wof:placetype":"venue"
},
  "geometry": {"coordinates":[7.8550000191,47.3246002197],"type":"Point"}
}