{
  "type": "Feature",
  "properties": {
    "iso:country":"CH",
    "sg:address":"Scheidweg",
    "sg:city":"Hofstetten",
    "sg:classifiers":[
        {
            "category":"Banks & Credit Unions",
            "subcategory":"Bank",
            "type":"Services"
        }
    ],
    "sg:phone":"+41 36511603",
    "sg:postcode":"3858",
    "sg:province":"Bern",
    "wof:name":"Raiffeisenkasse",
    "wof:placetype":"venue"
},
  "geometry": {"coordinates":[8.074505,46.753723],"type":"Point"}
}