{
  "type": "Feature",
  "properties": {
    "iso:country":"CH",
    "sg:address":"Menznauerstrasse 7",
    "sg:city":"Wolhusen",
    "sg:orig_category":"Herstellung von \u00d6fen U Brennern",
    "sg:phone":"+41 41 490 12 37",
    "sg:postcode":"6110",
    "sg:province":"Luzern",
    "wof:name":"Aeschbach Ofen- & Chemin\u00e9ebau",
    "wof:placetype":"venue"
},
  "geometry": {"coordinates":[8.0729398727,47.0590744019],"type":"Point"}
}