{
  "type": "Feature",
  "properties": {
    "iso:country":"CH",
    "sg:address":"8926",
    "sg:city":"Hauptikon",
    "sg:orig_category":"Wasserversorgung",
    "sg:phone":"+41 41 917 14 29",
    "sg:postcode":"8926",
    "sg:province":"Z\u00fcrich",
    "wof:name":"Wasserversorgungs-genossensch. Josef Kretz",
    "wof:placetype":"venue"
},
  "geometry": {"coordinates":[8.238735199,47.2555046082],"type":"Point"}
}