{
  "type": "Feature",
  "properties": {
    "iso:country":"CH",
    "sg:address":"Andreasplatz 7",
    "sg:city":"Basel",
    "sg:orig_category":"Grosshandel mit Textilien",
    "sg:phone":"+41 61 261 59 09",
    "sg:postcode":"4051",
    "sg:province":"Basel-Stadt",
    "wof:name":"Kangaroo Gmbh",
    "wof:placetype":"venue"
},
  "geometry": {"coordinates":[7.5864810944,47.5580406189],"type":"Point"}
}