{
  "type": "Feature",
  "properties": {
    "iso:country":"CH",
    "sg:address":"Pierrefleur Chemin De 32",
    "sg:city":"Lausanne",
    "sg:orig_category":"Allgemeiner Hoch U Tiefbau",
    "sg:postcode":"1004",
    "sg:province":"Vaud",
    "wof:name":"Marche Pierrefleur S\u00e0rl",
    "wof:placetype":"venue"
},
  "geometry": {"coordinates":[6.6165,46.535091],"type":"Point"}
}