{
  "type": "Feature",
  "properties": {
    "iso:country":"CH",
    "sg:address":"Hofmattstrasse 20 3920 Zermatt. Postfach 219",
    "sg:city":"Zermatt",
    "sg:classifiers":[
        {
            "category":"Travel",
            "subcategory":"Hotels & Motels",
            "type":"Entertainment"
        }
    ],
    "sg:phone":"+41 27 967 11 31",
    "sg:postcode":"3920",
    "sg:province":"Valais",
    "sg:tags":[
        "hotels",
        "mit",
        "restaurant"
    ],
    "wof:name":"Hotel Mischabel",
    "wof:placetype":"venue"
},
  "geometry": {"coordinates":[7.7486009598,46.021282196],"type":"Point"}
}