{
  "type": "Feature",
  "properties": {
    "iso:country":"CH",
    "sg:address":"6353",
    "sg:city":"Weggis",
    "sg:classifiers":[
        {
            "category":"Education",
            "subcategory":"Vocational School",
            "type":"Public Place"
        }
    ],
    "sg:postcode":"6353",
    "sg:province":"Luzern",
    "sg:tags":[
        "koch-",
        "haushaltschulen"
    ],
    "wof:name":"Hauswirtschaftliche Kurse Des M\u00fcttervereins Weggis",
    "wof:placetype":"venue"
},
  "geometry": {"coordinates":[8.4343938828,47.0322952271],"type":"Point"}
}