{
  "type": "Feature",
  "properties": {
    "iso:country":"CH",
    "sg:address":"Ried",
    "sg:city":"Ueberstorf",
    "sg:orig_category":"Blumen U Zierpflanzenbau",
    "sg:phone":"+41 31 741 05 08",
    "sg:postcode":"3182",
    "sg:province":"Fribourg",
    "wof:name":"Christian & Barbara Komminoth Schnittblumeng\u00e4rtnerei",
    "wof:placetype":"venue"
},
  "geometry": {"coordinates":[7.348598,46.886147],"type":"Point"}
}