{
  "type": "Feature",
  "properties": {
    "iso:country":"CH",
    "sg:address":"Hirschelenstrasse",
    "sg:city":"Rebstein",
    "sg:orig_category":"Organisationen des Gesundheitswesen",
    "sg:phone":"+41 62 771 67 60",
    "sg:postcode":"9445",
    "sg:province":"St. Gallen",
    "wof:name":"Samariterverein Reinach & Umg.",
    "wof:placetype":"venue"
},
  "geometry": {"coordinates":[8.1893186569,47.2512245178],"type":"Point"}
}