{
  "type": "Feature",
  "properties": {
    "iso:country":"CH",
    "sg:address":"Friedheimstrasse 39",
    "sg:city":"Z\u00fcrich",
    "sg:orig_category":"Architekturb\u00fcros",
    "sg:phone":"+41 13120944",
    "sg:postcode":"8057",
    "sg:province":"Z\u00fcrich",
    "wof:name":"Hans Sch\u00fcpbach Architekturb\u00fcro",
    "wof:placetype":"venue"
},
  "geometry": {"coordinates":[8.553711,47.404236],"type":"Point"}
}