{
  "type": "Feature",
  "properties": {
    "iso:country":"CH",
    "sg:address":"Neuensteinerstrasse 21",
    "sg:city":"Basel",
    "sg:orig_category":"Unclassifiable Establishments",
    "sg:phone":"+41 61 333 90 10",
    "sg:postcode":"4053",
    "sg:province":"Basel-Stadt",
    "wof:name":"Sunvision Ideenfabrik Gmbh",
    "wof:placetype":"venue"
},
  "geometry": {"coordinates":[7.6012539864,47.5403404236],"type":"Point"}
}