{
  "type": "Feature",
  "properties": {
    "iso:country":"CH",
    "sg:address":"Hauptstrasse 160 5044 Schlossrued. Postfach",
    "sg:city":"Schlossrued",
    "sg:orig_category":"Handel mit Automobilen",
    "sg:postcode":"5044",
    "sg:province":"Aargau",
    "wof:name":"Perfect-car Gmbh",
    "wof:placetype":"venue"
},
  "geometry": {"coordinates":[8.0868377686,47.291683197],"type":"Point"}
}