{
  "type": "Feature",
  "properties": {
    "iso:country":"CH",
    "sg:address":"Via Al Forte 10",
    "sg:city":"Lugano",
    "sg:orig_category":"Detailhandel mit medizinischen U orthop\u00e4dischen Artikeln Drogerien",
    "sg:phone":"+41 91 923 62 56",
    "sg:postcode":"6900",
    "sg:province":"Ticino",
    "wof:name":"Drogheria Belotti Sa",
    "wof:placetype":"venue"
},
  "geometry": {"coordinates":[8.9536867142,46.005645752],"type":"Point"}
}