{
  "type": "Feature",
  "properties": {
    "addr:full":"Route De Corni\u00e8re 70 Puplinge Gen\u00e8ve 1241",
    "addr:housenumber":"70",
    "addr:postcode":"1241",
    "addr:street":"Route De Cornie\u0300Re",
    "iso:country":"CH",
    "sg:address":"Route De Corni\u00e8re 70",
    "sg:city":"Puplinge",
    "sg:orig_category":"Architektur U Ingenieurb\u00fcros Gartenbau",
    "sg:phone":"+41 19843303",
    "sg:postcode":"1241",
    "sg:province":"Gen\u00e8ve",
    "wof:name":"Dardelet Gmbh",
    "wof:placetype":"venue"
},
  "geometry": {"coordinates":[8.690055,47.300556],"type":"Point"}
}