{
  "type": "Feature",
  "properties": {
    "addr:full":"M\u00fclimattring 22 Halten Solothurn 4566",
    "addr:housenumber":"22",
    "addr:postcode":"4566",
    "addr:street":"Muelimattring",
    "iso:country":"CH",
    "sg:address":"M\u00fclimattring 22",
    "sg:city":"Halten",
    "sg:orig_category":"Architekturb\u00fcros",
    "sg:phone":"+41 79 222 78 83",
    "sg:postcode":"4566",
    "sg:province":"Solothurn",
    "wof:name":"Heinz Stalder Architekturb\u00fcro",
    "wof:placetype":"venue"
},
  "geometry": {"coordinates":[7.598728,47.172474],"type":"Point"}
}