{
  "type": "Feature",
  "properties": {
    "iso:country":"CH",
    "sg:address":"Bahnhofstrasse 32",
    "sg:city":"Chur",
    "sg:orig_category":"Detailhandel mit Uhren U Schmuck Reparatur von Uhren U Schmuck",
    "sg:phone":"+41 81 756 03 56",
    "sg:postcode":"7000",
    "sg:province":"Graubunden",
    "wof:name":"Christ Uhren & Schmuck Ag",
    "wof:placetype":"venue"
},
  "geometry": {"coordinates":[9.4732599258,47.1659355164],"type":"Point"}
}