{
  "type": "Feature",
  "properties": {
    "iso:country":"CH",
    "sg:address":"Davoserweg 365c 7302 Landquart. Postfach",
    "sg:city":"Landquart",
    "sg:orig_category":"Stukkateurgewerbe, Gipserei U Verputzerei",
    "sg:postcode":"7302",
    "sg:province":"Graubunden",
    "wof:name":"Adler, Jean-jacques",
    "wof:placetype":"venue"
},
  "geometry": {"coordinates":[6.9953799248,46.2966117859],"type":"Point"}
}