{
  "type": "Feature",
  "properties": {
    "iso:country":"CH",
    "sg:address":"Dienerstrasse 15",
    "sg:city":"Z\u00fcrich",
    "sg:orig_category":"Informatikdienste",
    "sg:phone":"+41 12979111",
    "sg:postcode":"8004",
    "sg:province":"Z\u00fcrich",
    "wof:name":"Npocom Ag Informatik-services",
    "wof:placetype":"venue"
},
  "geometry": {"coordinates":[8.5285406113,47.377620697],"type":"Point"}
}