{
  "type": "Feature",
  "properties": {
    "iso:country":"CH",
    "sg:address":"L\u00f6bernstrasse 16c 6330 Cham. Postfach",
    "sg:city":"Cham",
    "sg:orig_category":"Wirtschaftspr\u00fcfung, Steuerberatung U Treuhand",
    "sg:phone":"+41 56 631 68 05",
    "sg:postcode":"6330",
    "sg:province":"Zug",
    "wof:name":"Kuhn G. Rechtsberatung Treuhand Gmbh",
    "wof:placetype":"venue"
},
  "geometry": {"coordinates":[8.3479719162,47.3558578491],"type":"Point"}
}