{
  "type": "Feature",
  "properties": {
    "iso:country":"CH",
    "sg:address":"Waldmannstrasse 10 8001 Z\u00fcrich. Postfach",
    "sg:city":"Z\u00fcrich",
    "sg:orig_category":"Advokaturb\u00fcros",
    "sg:phone":"+41 71 243 20 00",
    "sg:postcode":"8024",
    "sg:province":"Z\u00fcrich",
    "wof:name":"Nabholz & Oberholzer Advokaturb\u00fcro",
    "wof:placetype":"venue"
},
  "geometry": {"coordinates":[9.379711,47.428444],"type":"Point"}
}