{
  "type": "Feature",
  "properties": {
    "iso:country":"CH",
    "sg:address":"Via Bassone 7",
    "sg:city":"Aldesago",
    "sg:orig_category":"Unclassifiable Establishments",
    "sg:postcode":"6974",
    "sg:province":"Ticino",
    "wof:name":"Hotel Colibr\u00ec Aldesago Sa",
    "wof:placetype":"venue"
},
  "geometry": {"coordinates":[8.9791126251,46.0078735352],"type":"Point"}
}