{
  "type": "Feature",
  "properties": {
    "iso:country":"CH",
    "sg:address":"Spiegelgutstrasse 9",
    "sg:city":"Schaffhausen",
    "sg:orig_category":"Handelsvermittlung U Grosshandel R\u00fcckgewinnung U Vorbereitung f\u00fcr die Wiederverwertung Recycling",
    "sg:phone":"+41 52 643 15 10",
    "sg:postcode":"8200",
    "sg:province":"Schaffhausen",
    "wof:name":"Niklaus Sch\u00f6pfer Alteisen & Altmetalle",
    "wof:placetype":"venue"
},
  "geometry": {"coordinates":[8.6480951309,47.717414856],"type":"Point"}
}