{
  "type": "Feature",
  "properties": {
    "iso:country":"CH",
    "sg:address":"Kirchlindachstrasse 49",
    "sg:city":"Zollikofen",
    "sg:orig_category":"Sonderschulen Wohnheime",
    "sg:phone":"+41 31 911 25 16",
    "sg:postcode":"3052",
    "sg:province":"Bern",
    "wof:name":"Stiftung F\u00fcr Blinde Und Sehbehinderte Kinder Und Jugendliche Zollikofen",
    "wof:placetype":"venue"
},
  "geometry": {"coordinates":[7.4545621872,47.0013961792],"type":"Point"}
}