{
  "type": "Feature",
  "properties": {
    "iso:country":"CH",
    "sg:address":"Oberdorfstrasse 8",
    "sg:city":"Dietikon",
    "sg:orig_category":"Elektroinstallation",
    "sg:phone":"+41 79 404 28 61",
    "sg:postcode":"8953",
    "sg:province":"Z\u00fcrich",
    "wof:name":"Leipert M. Elektroplanung Und Bauleitung",
    "wof:placetype":"venue"
},
  "geometry": {"coordinates":[8.4006919861,47.4027137756],"type":"Point"}
}