{
  "type": "Feature",
  "properties": {
    "iso:country":"CH",
    "sg:address":"Via San Gottardo 60",
    "sg:city":"Minusio",
    "sg:orig_category":"Gemeindeverwaltungen",
    "sg:phone":"+41 91 735 81 81",
    "sg:postcode":"6648",
    "sg:province":"Ticino",
    "wof:name":"Amministrazione Comunale Di Minusio",
    "wof:placetype":"venue"
},
  "geometry": {"coordinates":[8.8123502731,46.1758880615],"type":"Point"}
}