{
  "type": "Feature",
  "properties": {
    "iso:country":"CH",
    "sg:address":"Rue Peillonnex 39",
    "sg:city":"Ch\u00eane-bourg",
    "sg:orig_category":"Grosshandel mit Uhren Herstellung von Phantasieschmuck",
    "sg:postcode":"1225",
    "sg:province":"Gen\u00e8ve",
    "wof:name":"Jacoby-bender Ag",
    "wof:placetype":"venue"
},
  "geometry": {"coordinates":[6.9325761795,46.9949569702],"type":"Point"}
}