{
  "type": "Feature",
  "properties": {
    "iso:country":"CH",
    "sg:address":"Ferdinand Hodler-strasse 11",
    "sg:city":"Z\u00fcrich",
    "sg:orig_category":"Detailhandel mit Schuhen U Lederwaren",
    "sg:phone":"+41 13412907",
    "sg:postcode":"8049",
    "sg:province":"Z\u00fcrich",
    "wof:name":"Rietmann Edwin Lederwarenbeschl\u00e4ge; Import",
    "wof:placetype":"venue"
},
  "geometry": {"coordinates":[8.5012149811,47.4038085938],"type":"Point"}
}