{
  "type": "Feature",
  "properties": {
    "iso:country":"CH",
    "sg:address":"Chemin De Val\u00e9rie 55 1292 Pregny. Postfach",
    "sg:city":"Chamb\u00e9sy",
    "sg:orig_category":"Interessenvertretungen",
    "sg:postcode":"1292",
    "sg:province":"Gen\u00e8ve",
    "wof:name":"Association Pour L'int\u00e9gration Des Expatri\u00e9s \u00e0 Gen\u00e8ve Et En France Voisine (aiegefv)",
    "wof:placetype":"venue"
},
  "geometry": {"coordinates":[6.14149189,46.2377471924],"type":"Point"}
}