{
  "type": "Feature",
  "properties": {
    "iso:country":"CH",
    "sg:address":"Mahrenstrasse 100a",
    "sg:city":"Lostorf",
    "sg:orig_category":"Gartenbau",
    "sg:phone":"+41 62 298 20 44",
    "sg:postcode":"4654",
    "sg:province":"Solothurn",
    "wof:name":"Buechehof Landwirtschaft & G\u00e4rtnerei",
    "wof:placetype":"venue"
},
  "geometry": {"coordinates":[7.9321908951,47.3833503723],"type":"Point"}
}