{
  "type": "Feature",
  "properties": {
    "iso:country":"CH",
    "sg:address":"Chemin Des Champs 4",
    "sg:city":"Ch\u00e2telard-lutry",
    "sg:orig_category":"Allgemeiner Hoch U Tiefbau Unterhalt U Reparatur im Hoch U Tiefbau",
    "sg:phone":"+41 21 312 37 10",
    "sg:postcode":"1095",
    "sg:province":"Vaud",
    "wof:name":"Renovit Sa Succursale De Lutry",
    "wof:placetype":"venue"
},
  "geometry": {"coordinates":[6.686539,46.504768],"type":"Point"}
}