{
  "type": "Feature",
  "properties": {
    "iso:country":"CH",
    "sg:address":"6809",
    "sg:city":"Medeglia",
    "sg:orig_category":"Darlehenskassen U Raiffeisenbanken",
    "sg:phone":"+41 91 683 55 25",
    "sg:postcode":"6809",
    "sg:province":"Ticino",
    "wof:name":"Banca Raiffeisen",
    "wof:placetype":"venue"
},
  "geometry": {"coordinates":[9.05037,45.870098],"type":"Point"}
}