{
  "type": "Feature",
  "properties": {
    "iso:country":"CH",
    "sg:address":"Baslerstrasse 60",
    "sg:city":"Olten",
    "sg:orig_category":"Detailhandel mit elektrischen Haushalts-,Radio U Fernsehger\u00e4ten sowie Musikinstrumenten Detailhandel",
    "sg:postcode":"4600",
    "sg:province":"Solothurn",
    "wof:name":"Torcivia G.",
    "wof:placetype":"venue"
},
  "geometry": {"coordinates":[6.8262062073,47.100353241],"type":"Point"}
}