{
  "type": "Feature",
  "properties": {
    "iso:country":"CH",
    "sg:address":"Ramuz Avenue C.-f.- 66",
    "sg:city":"Pully",
    "sg:orig_category":"Herstellung von medizinischen U chirurgischen Ger\u00e4ten sowie orthop\u00e4dischen Vorrichtungen",
    "sg:phone":"+41 21 729 31 32",
    "sg:postcode":"1009",
    "sg:province":"Vaud",
    "wof:name":"Health Body S\u00e0rl",
    "wof:placetype":"venue"
},
  "geometry": {"coordinates":[6.6598000526,46.5102577209],"type":"Point"}
}