{
  "type": "Feature",
  "properties": {
    "iso:country":"CH",
    "sg:address":"Rue Du Maupas 23 Ter",
    "sg:city":"Lausanne",
    "sg:orig_category":"Herstellung von Teppichen",
    "sg:phone":"+41 21 648 11 73",
    "sg:postcode":"1004",
    "sg:province":"Vaud",
    "wof:name":"Tisch-reymond W. Sa",
    "wof:placetype":"venue"
},
  "geometry": {"coordinates":[6.625453949,46.5249519348],"type":"Point"}
}