{
  "type": "Feature",
  "properties": {
    "iso:country":"CH",
    "sg:address":"Reidenbach",
    "sg:city":"Boltigen",
    "sg:orig_category":"Haltung von Rindern",
    "sg:postcode":"3766",
    "sg:province":"Bern",
    "wof:name":"Viehzuchtgenossenschaft Boltigen Ii",
    "wof:placetype":"venue"
},
  "geometry": {"coordinates":[7.3752808571,46.6199417114],"type":"Point"}
}