{
  "type": "Feature",
  "properties": {
    "iso:country":"CH",
    "sg:address":"Hauptstrasse 35",
    "sg:city":"Zurzach",
    "sg:orig_category":"Detailhandel mit Fleisch U Fleischwaren",
    "sg:phone":"+41 56 249 12 21",
    "sg:postcode":"5330",
    "sg:province":"Aargau",
    "wof:name":"Mathias Arnold Metzgerei",
    "wof:placetype":"venue"
},
  "geometry": {"coordinates":[8.2921924591,47.5867652893],"type":"Point"}
}