{
  "type": "Feature",
  "properties": {
    "iso:country":"CH",
    "sg:address":"Steinenbachstrasse",
    "sg:city":"Ebnat-kappel",
    "sg:orig_category":"Bauspenglerei Dachdeckerei",
    "sg:phone":"+41 61 756 96 96",
    "sg:postcode":"9642",
    "sg:province":"St. Gallen",
    "wof:name":"Hummel & Meyer Ag",
    "wof:placetype":"venue"
},
  "geometry": {"coordinates":[7.590342,47.477123],"type":"Point"}
}