{
  "type": "Feature",
  "properties": {
    "iso:country":"CH",
    "sg:address":"Petit-ch\u00e9zard 5",
    "sg:city":"Ch\u00e9zard-st-martin",
    "sg:orig_category":"Grosshandel mit sonstigen Halbwaren",
    "sg:phone":"+41 32 853 34 54",
    "sg:postcode":"2054",
    "sg:province":"Neuch\u00e2tel",
    "wof:name":"Autopack Silvio Butscher",
    "wof:placetype":"venue"
},
  "geometry": {"coordinates":[6.9201140404,47.0651016235],"type":"Point"}
}