{
  "type": "Feature",
  "properties": {
    "iso:country":"CH",
    "sg:address":"Burgweg 1",
    "sg:city":"Konolfingen",
    "sg:orig_category":"Arztpraxen",
    "sg:phone":"+41 31 791 16 46",
    "sg:postcode":"3510",
    "sg:province":"Bern",
    "wof:name":"Dr.med.sebastian Birrer Arzt F.allgemeine Medizin Fmh",
    "wof:placetype":"venue"
},
  "geometry": {"coordinates":[7.622807,46.881954],"type":"Point"}
}