{
  "type": "Feature",
  "properties": {
    "iso:country":"CH",
    "sg:address":"Kleinberg",
    "sg:city":"Portels",
    "sg:orig_category":"Sportvereine Sch\u00fctzen",
    "sg:phone":"+41 81 733 30 09",
    "sg:postcode":"8895",
    "sg:province":"St. Gallen",
    "wof:name":"Sch\u00fctzengesellschaft",
    "wof:placetype":"venue"
},
  "geometry": {"coordinates":[9.3344802856,47.0827217102],"type":"Point"}
}