{
  "type": "Feature",
  "properties": {
    "iso:country":"CH",
    "sg:address":"H\u00f6fli",
    "sg:city":"Greppen",
    "sg:orig_category":"Sonstiger Fachdetailhandel mit Nahrungsmitteln, Getr\u00e4nken U Tabak in Verkaufsr\u00e4umen Verarbeitung von",
    "sg:phone":"+41 71 622 10 44",
    "sg:postcode":"6404",
    "sg:province":"Luzern",
    "wof:name":"F\u00e4ssler Albert",
    "wof:placetype":"venue"
},
  "geometry": {"coordinates":[9.1381845474,47.5666694641],"type":"Point"}
}