{
  "type": "Feature",
  "properties": {
    "iso:country":"CH",
    "sg:address":"Chemin Du Raffort 5",
    "sg:city":"M\u00e9zi\u00e8res",
    "sg:classifiers":[
        {
            "category":"Shopping",
            "subcategory":"Computers & Home Electronics",
            "type":"Retail Goods"
        }
    ],
    "sg:phone":"+41 21 903 21 14",
    "sg:postcode":"1083",
    "sg:province":"Vaud",
    "sg:tags":[
        "instrument",
        "electronic",
        "measurement"
    ],
    "wof:name":"Metra Instruments S.a.",
    "wof:placetype":"venue"
},
  "geometry": {"coordinates":[6.7678399086,46.5961914062],"type":"Point"}
}