{
  "type": "Feature",
  "properties": {
    "iso:country":"CH",
    "sg:address":"B\u00e4chi",
    "sg:city":"Ellighausen",
    "sg:orig_category":"Herstellung von Maschinen f\u00fcr die Nahrungsmittel, Getr\u00e4nkeherstellung U die Tabakverarbeitung",
    "sg:phone":"+41 71 664 14 93",
    "sg:postcode":"8566",
    "sg:province":"Thurgau",
    "wof:name":"Trocknungsgenossenschaft Kemmental",
    "wof:placetype":"venue"
},
  "geometry": {"coordinates":[9.1353902817,47.6129188538],"type":"Point"}
}