{
  "type": "Feature",
  "properties": {
    "addr:full":"Rue St-pierre-canisius 1 1700 Fribourg. Postfach Fribourg Fribourg 1701",
    "addr:housenumber":"1",
    "addr:postcode":"1700;postfach;1701",
    "addr:street":"Rue St-Pierre-Canisius",
    "iso:country":"CH",
    "sg:address":"Rue St-pierre-canisius 1 1700 Fribourg. Postfach",
    "sg:city":"Fribourg",
    "sg:orig_category":"Advokaturb\u00fcros",
    "sg:phone":"+41 26 322 39 49",
    "sg:postcode":"1701",
    "sg:province":"Fribourg",
    "wof:name":"Alain Ribordy Etude D'avocat",
    "wof:placetype":"venue"
},
  "geometry": {"coordinates":[7.157465,46.80579],"type":"Point"}
}