{
  "type": "Feature",
  "properties": {
    "iso:country":"CH",
    "sg:address":"Schulstrasse 3",
    "sg:city":"Tuggen",
    "sg:orig_category":"Unclassifiable Establishments",
    "sg:phone":"+41 55 445 16 64",
    "sg:postcode":"8856",
    "sg:province":"Schwyz",
    "wof:name":"Hipag Hydraulik Ag",
    "wof:placetype":"venue"
},
  "geometry": {"coordinates":[8.9452867508,47.2019004822],"type":"Point"}
}