{
  "type": "Feature",
  "properties": {
    "addr:full":"Chesa Prad\u00e8 Samedan Graubunden 7503",
    "addr:postcode":"7503",
    "addr:street":"Graubunden",
    "iso:country":"CH",
    "sg:address":"Chesa Prad\u00e8",
    "sg:city":"Samedan",
    "sg:orig_category":"Allgemeiner Hoch U Tiefbau",
    "sg:postcode":"7503",
    "sg:province":"Graubunden",
    "wof:name":"Hirschi Hans",
    "wof:placetype":"venue"
},
  "geometry": {"coordinates":[9.872837,46.535358],"type":"Point"}
}