{
  "type": "Feature",
  "properties": {
    "iso:country":"CH",
    "sg:address":"In Huebwiesen 9",
    "sg:city":"D\u00fcbendorf",
    "sg:orig_category":"Handelsvermittlung U Grosshandel Handelsvermittlung U Grosshandel mit Automobilteilen U Zubeh\u00f6r",
    "sg:phone":"+41 18202004",
    "sg:postcode":"8600",
    "sg:province":"Z\u00fcrich",
    "wof:name":"Schaad Gmbh Garage",
    "wof:placetype":"venue"
},
  "geometry": {"coordinates":[8.6155261993,47.4009094238],"type":"Point"}
}