{
  "type": "Feature",
  "properties": {
    "iso:country":"CH",
    "sg:address":"7482",
    "sg:city":"Berg\u00fcn/bravuogn",
    "sg:orig_category":"Fahrschulen, Flugschulen",
    "sg:phone":"+41 81 407 21 65",
    "sg:postcode":"7482",
    "sg:province":"Graubunden",
    "wof:name":"J\u00fcrg & Karin Fasser Autofahrschule",
    "wof:placetype":"venue"
},
  "geometry": {"coordinates":[9.7946901321,46.621471405],"type":"Point"}
}