{
  "type": "Feature",
  "properties": {
    "iso:country":"CH",
    "sg:address":"Rue Lamartine 22",
    "sg:city":"Gen\u00e8ve",
    "sg:orig_category":"Elektroinstallation",
    "sg:phone":"+41 22 345 12 68",
    "sg:postcode":"1203",
    "sg:province":"Gen\u00e8ve",
    "wof:name":"Cg Integra S\u00e0rl Installateurs Electriciens",
    "wof:placetype":"venue"
},
  "geometry": {"coordinates":[6.128839016,46.2110176086],"type":"Point"}
}