{
  "type": "Feature",
  "properties": {
    "iso:country":"CH",
    "sg:address":"Selnaustrasse 3",
    "sg:city":"Z\u00fcrich",
    "sg:classifiers":[
        {
            "category":"Travel",
            "subcategory":"Hotels & Motels",
            "type":"Entertainment"
        }
    ],
    "sg:postcode":"8002",
    "sg:province":"Z\u00fcrich",
    "sg:tags":[
        "hotels",
        "mit",
        "restaurant"
    ],
    "wof:name":"Oekotel",
    "wof:placetype":"venue"
},
  "geometry": {"coordinates":[8.5333414078,47.3696594238],"type":"Point"}
}