{
  "type": "Feature",
  "properties": {
    "iso:country":"CH",
    "sg:address":"Seestrasse 40",
    "sg:city":"Spiez",
    "sg:orig_category":"Detailhandel mit Brot, Back U S\u00fcsswaren",
    "sg:postcode":"3700",
    "sg:province":"Bern",
    "wof:name":"Bircher Alain",
    "wof:placetype":"venue"
},
  "geometry": {"coordinates":[7.212448,46.08046],"type":"Point"}
}