{
  "type": "Feature",
  "properties": {
    "iso:country":"CH",
    "sg:address":"Gandr\u00fctti 47",
    "sg:city":"Schattdorf",
    "sg:orig_category":"Berufliche Weiterbildung, Erwachsenenbildung",
    "sg:phone":"+41 79 659 03 33",
    "sg:postcode":"6467",
    "sg:province":"Uri",
    "wof:name":"Dale Carnegie Training",
    "wof:placetype":"venue"
},
  "geometry": {"coordinates":[8.644816,46.860695],"type":"Point"}
}