{
  "type": "Feature",
  "properties": {
    "iso:country":"CH",
    "sg:address":"Korbackerweg 19 5502 Hunzenschwil. Postfach",
    "sg:city":"Hunzenschwil",
    "sg:orig_category":"Herstellung von medizinischen U chirurgischen Ger\u00e4ten sowie orthop\u00e4dischen Vorrichtungen",
    "sg:postcode":"5502",
    "sg:province":"Aargau",
    "wof:name":"Idea Nova Rico K\u00f6beli",
    "wof:placetype":"venue"
},
  "geometry": {"coordinates":[8.1313381195,47.3859062195],"type":"Point"}
}