{
  "type": "Feature",
  "properties": {
    "iso:country":"CH",
    "sg:address":"Rue Du Bourg De L'auge 1",
    "sg:city":"Broc",
    "sg:orig_category":"Detailhandel mit Radio U Fernsehger\u00e4ten Detailhandel mit elektrischen Haushalts-,Radio U Fernsehger\u00e4",
    "sg:phone":"+41 26 921 39 00",
    "sg:postcode":"1636",
    "sg:province":"Fribourg",
    "wof:name":"Fragni\u00e8re Jacques",
    "wof:placetype":"venue"
},
  "geometry": {"coordinates":[5.2456002235,46.191444397],"type":"Point"}
}