{
  "type": "Feature",
  "properties": {
    "iso:country":"CH",
    "sg:address":"L\u00f6wenstrasse 22",
    "sg:city":"Z\u00fcrich",
    "sg:orig_category":"Reiseb\u00fcros U Reiseveranstalter",
    "sg:postcode":"8001",
    "sg:province":"Z\u00fcrich",
    "wof:name":"Croisance R\u00e9sidence",
    "wof:placetype":"venue"
},
  "geometry": {"coordinates":[7.5717401505,46.7205696106],"type":"Point"}
}