{
  "type": "Feature",
  "properties": {
    "iso:country":"CH",
    "sg:address":"Gr\u00e4flib\u00fchlstrasse 7",
    "sg:city":"Rebstein",
    "sg:orig_category":"Sportvereine Turnen",
    "sg:phone":"+41 71 777 25 84",
    "sg:postcode":"9445",
    "sg:province":"St. Gallen",
    "wof:name":"Katholischer Turnverein Ktv",
    "wof:placetype":"venue"
},
  "geometry": {"coordinates":[9.5870485306,47.3991165161],"type":"Point"}
}