{
  "type": "Feature",
  "properties": {
    "iso:country":"CH",
    "sg:address":"Rue St-honor\u00e9 3 2000 Neuch\u00e2tel. Postfach",
    "sg:city":"Neuenburg",
    "sg:orig_category":"Finanzierungsinstitutionen Softwareentwicklung U beratung",
    "sg:phone":"+41 32 724 88 20",
    "sg:postcode":"2000",
    "sg:province":"Neuch\u00e2tel",
    "wof:name":"Genicorp S\u00e0rl Conseils, De Services Dans Le Dom. De L'informatique, Gestion D'entreprise Et Financi\u00e8re",
    "wof:placetype":"venue"
},
  "geometry": {"coordinates":[6.9312009811,46.9907722473],"type":"Point"}
}