{
  "type": "Feature",
  "properties": {
    "iso:country":"CH",
    "sg:address":"Aspstrasse 15",
    "sg:city":"Seuzach",
    "sg:orig_category":"Maler U Glasergewerbe Malerei",
    "sg:phone":"+41 52 320 06 06",
    "sg:postcode":"8472",
    "sg:province":"Z\u00fcrich",
    "wof:name":"Malerwerkst\u00e4tten Schmid Heinrich Ag",
    "wof:placetype":"venue"
},
  "geometry": {"coordinates":[8.7057237625,47.527053833],"type":"Point"}
}