{
  "type": "Feature",
  "properties": {
    "iso:country":"CH",
    "sg:address":"Moosmattstrasse 25a 6005 Luzern. Postfach",
    "sg:city":"Luzern",
    "sg:orig_category":"Elektroinstallation Handelsvermittlung U Grosshandel",
    "sg:phone":"+41 41 312 11 90",
    "sg:postcode":"6002",
    "sg:province":"Luzern",
    "wof:name":"Auto-flor Gmbh Waren; Handel, Verarbeitung Usw",
    "wof:placetype":"venue"
},
  "geometry": {"coordinates":[8.3043870926,47.0392837524],"type":"Point"}
}