{
  "type": "Feature",
  "properties": {
    "iso:country":"CH",
    "sg:address":"Lutherstrasse 2",
    "sg:city":"Z\u00fcrich",
    "sg:orig_category":"Gesundheitswesen",
    "sg:postcode":"8004",
    "sg:province":"Z\u00fcrich",
    "wof:name":"Zentrum F\u00fcr Essst\u00f6rungen, Frei S.",
    "wof:placetype":"venue"
},
  "geometry": {"coordinates":[8.5297040939,47.3737487793],"type":"Point"}
}