{
  "type": "Feature",
  "properties": {
    "iso:country":"CH",
    "sg:address":"Schloss",
    "sg:city":"Blankenburg",
    "sg:orig_category":"Verwaltung der Rechtspflege, Gerichte",
    "sg:phone":"+41 33 729 85 85",
    "sg:postcode":"3771",
    "sg:province":"Bern",
    "wof:name":"Kreisgrundbuchamt Obersimmental-saanen",
    "wof:placetype":"venue"
},
  "geometry": {"coordinates":[7.3879241943,46.5396461487],"type":"Point"}
}