{
  "type": "Feature",
  "properties": {
    "iso:country":"CH",
    "sg:address":"Hauptstrasse 51",
    "sg:city":"B\u00f6ckten",
    "sg:orig_category":"RESTAURANTS: TEA-ROOMS",
    "sg:postcode":"4461",
    "sg:province":"Basel-Landschaft",
    "wof:name":"Chan + Co.",
    "wof:placetype":"venue"
},
  "geometry": {"coordinates":[7.835670948,47.4623985291],"type":"Point"}
}