{
  "type": "Feature",
  "properties": {
    "iso:country":"CH",
    "sg:address":"Bellevuestrasse 8 8800 Thalwil. Postfach",
    "sg:city":"Thalwil",
    "sg:orig_category":"Instandhaltung U Reparatur von Automobilen",
    "sg:postcode":"8800",
    "sg:province":"Z\u00fcrich",
    "wof:name":"Timtec Gmbh Motorfahrzeuge, Waren; Import, Export U. Reparatur",
    "wof:placetype":"venue"
},
  "geometry": {"coordinates":[8.5707349777,47.2886238098],"type":"Point"}
}