{
  "type": "Feature",
  "properties": {
    "iso:country":"CH",
    "sg:address":"Hauptstrasse 23 8280 Kreuzlingen. Postfach 811",
    "sg:city":"Kreuzlingen",
    "sg:orig_category":"Strassenbau",
    "sg:phone":"+41 71 672 22 56",
    "sg:postcode":"8280",
    "sg:province":"Thurgau",
    "wof:name":"Pflastrabau Gmbh",
    "wof:placetype":"venue"
},
  "geometry": {"coordinates":[9.1739635468,47.6526565552],"type":"Point"}
}