{
  "type": "Feature",
  "properties": {
    "addr:full":"Via Al Chioso 28 Lugano Ticino 6900",
    "addr:housenumber":"28",
    "addr:postcode":"6900",
    "addr:street":"Via Al Chioso",
    "iso:country":"CH",
    "sg:address":"Via Al Chioso 28",
    "sg:city":"Lugano",
    "sg:orig_category":"Architekturb\u00fcros",
    "sg:phone":"+41 91 972 34 61",
    "sg:postcode":"6900",
    "sg:province":"Ticino",
    "wof:name":"G\u00e9rald Walther Studio D'architettura",
    "wof:placetype":"venue"
},
  "geometry": {"coordinates":[8.963536,46.009109],"type":"Point"}
}