{
  "type": "Feature",
  "properties": {
    "iso:country":"CH",
    "sg:address":"Erlenstrasse 50",
    "sg:city":"Basel",
    "sg:orig_category":"Kosmetikinstitute",
    "sg:phone":"+41 32 372 70 77",
    "sg:postcode":"4058",
    "sg:province":"Basel-Stadt",
    "wof:name":"Epi Med Gmbh",
    "wof:placetype":"venue"
},
  "geometry": {"coordinates":[7.3147788048,47.1114120483],"type":"Point"}
}