{
  "type": "Feature",
  "properties": {
    "iso:country":"CH",
    "sg:address":"Verenastrasse 9",
    "sg:city":"Z\u00fcrich",
    "sg:orig_category":"Geb\u00e4ude, Wohnungsreinigung",
    "sg:phone":"+41 61 712 01 01",
    "sg:postcode":"8038",
    "sg:province":"Z\u00fcrich",
    "wof:name":"M M Cleaning Service M.meier",
    "wof:placetype":"venue"
},
  "geometry": {"coordinates":[7.5773119926,47.4939613342],"type":"Point"}
}