{
  "type": "Feature",
  "properties": {
    "iso:country":"CH",
    "sg:address":"Albisstrasse 15 6340 Baar. Postfach 144",
    "sg:city":"Baar",
    "sg:orig_category":"Institutionen f\u00fcr Finanzierungsleasing",
    "sg:phone":"+41 41 769 30 51",
    "sg:postcode":"6341",
    "sg:province":"Zug",
    "wof:name":"Colm Leasing Ag",
    "wof:placetype":"venue"
},
  "geometry": {"coordinates":[8.5249700546,47.198425293],"type":"Point"}
}