{
  "type": "Feature",
  "properties": {
    "iso:country":"CH",
    "sg:address":"Rahn G\u00e4tziberg 2",
    "sg:city":"Altst\u00e4tten",
    "sg:classifiers":[
        {
            "category":"Banks & Credit Unions",
            "subcategory":"Investment Brokerage",
            "type":"Services"
        }
    ],
    "sg:phone":"+41 71 352 41 41",
    "sg:postcode":"9450",
    "sg:province":"St. Gallen",
    "sg:tags":[
        "processing",
        "data",
        "system"
    ],
    "wof:name":"Dataland Informatik Ag",
    "wof:placetype":"venue"
},
  "geometry": {"coordinates":[9.507077,47.368214],"type":"Point"}
}