{
  "type": "Feature",
  "properties": {
    "addr:full":"Weinbergstrasse 164 Z\u00fcrich Z\u00fcrich 8006",
    "addr:housenumber":"164",
    "addr:postcode":"8006",
    "addr:street":"Weinbergstrasse",
    "iso:country":"CH",
    "sg:address":"Weinbergstrasse 164",
    "sg:city":"Z\u00fcrich",
    "sg:orig_category":"Chiropraktik",
    "sg:phone":"+41 13624900",
    "sg:postcode":"8006",
    "sg:province":"Z\u00fcrich",
    "wof:name":"Dr.bernhard Anklin Chiropraktor",
    "wof:placetype":"venue"
},
  "geometry": {"coordinates":[8.539525,47.391121],"type":"Point"}
}