{
  "type": "Feature",
  "properties": {
    "iso:country":"CH",
    "sg:address":"8401 Winterthur. Postfach 414",
    "sg:city":"Winterthur",
    "sg:orig_category":"Sportvereine Ballsport Fussball",
    "sg:phone":"+41 91 683 00 78",
    "sg:postcode":"8401",
    "sg:province":"Z\u00fcrich",
    "wof:name":"Fc Superiore 72",
    "wof:placetype":"venue"
},
  "geometry": {"coordinates":[9.0503702164,45.870098114],"type":"Point"}
}