{
  "type": "Feature",
  "properties": {
    "iso:country":"CH",
    "sg:address":"Richtersmattweg 6a",
    "sg:city":"Sch\u00fcpfen",
    "sg:orig_category":"Mechanik",
    "sg:postcode":"3054",
    "sg:province":"Bern",
    "wof:name":"Wehrli-weber A.",
    "wof:placetype":"venue"
},
  "geometry": {"coordinates":[9.8064022064,46.9110946655],"type":"Point"}
}