{
  "type": "Feature",
  "properties": {
    "iso:country":"CH",
    "sg:address":"Via Franchino Rusca 1",
    "sg:city":"Locarno",
    "sg:orig_category":"Schulpflegen",
    "sg:postcode":"6600",
    "sg:province":"Ticino",
    "wof:name":"Delegazione Scolastica Del Comune Di Locarno",
    "wof:placetype":"venue"
},
  "geometry": {"coordinates":[8.7943334579,46.1679611206],"type":"Point"}
}