{
  "type": "Feature",
  "properties": {
    "iso:country":"CH",
    "sg:address":"Dorfstrasse 36",
    "sg:city":"Wettingen",
    "sg:orig_category":"RESTAURANTS: TEA-ROOMS",
    "sg:phone":"+41 56 427 44 80",
    "sg:postcode":"5430",
    "sg:province":"Aargau",
    "wof:name":"Kasino Wettingen Gmbh",
    "wof:placetype":"venue"
},
  "geometry": {"coordinates":[8.3334407806,47.4666366577],"type":"Point"}
}