{
  "type": "Feature",
  "properties": {
    "iso:country":"CH",
    "sg:address":"Route D'etraz 172",
    "sg:city":"Versoix",
    "sg:orig_category":"Herstellung von Tanks U Sammelbeh\u00e4ltern aus Metall",
    "sg:phone":"+41 22 755 20 91",
    "sg:postcode":"1290",
    "sg:province":"Gen\u00e8ve",
    "wof:name":"Cuhat Sa R\u00e9vision De Citernes",
    "wof:placetype":"venue"
},
  "geometry": {"coordinates":[6.154692173,46.292804718],"type":"Point"}
}