{
  "type": "Feature",
  "properties": {
    "iso:country":"CH",
    "sg:address":"Jeandin Avenue Adrien- 31",
    "sg:city":"Th\u00f4nex",
    "sg:orig_category":"Architektur U Ingenieurb\u00fcros",
    "sg:phone":"+41 22 349 89 48",
    "sg:postcode":"1226",
    "sg:province":"Gen\u00e8ve",
    "wof:name":"Ott B. Et Uldry C. S\u00e0rl",
    "wof:placetype":"venue"
},
  "geometry": {"coordinates":[6.201223,46.189922],"type":"Point"}
}