{
  "type": "Feature",
  "properties": {
    "addr:full":"3966 R\u00e9chy Valais 3966",
    "addr:housenumber":"3966",
    "addr:postcode":"3966",
    "iso:country":"CH",
    "sg:address":"3966",
    "sg:city":"R\u00e9chy",
    "sg:orig_category":"Bauspenglerei Sanit\u00e4r, Heizungs U L\u00fcftungsinstallation",
    "sg:phone":"+41 27 458 32 92",
    "sg:postcode":"3966",
    "sg:province":"Valais",
    "wof:name":"Gaudin Serge",
    "wof:placetype":"venue"
},
  "geometry": {"coordinates":[7.495225,46.261307],"type":"Point"}
}