{
  "type": "Feature",
  "properties": {
    "iso:country":"CH",
    "sg:address":"Via Ronco 8",
    "sg:city":"Arcegno",
    "sg:orig_category":"Architekturb\u00fcros",
    "sg:phone":"+41 91 791 14 66",
    "sg:postcode":"6618",
    "sg:province":"Ticino",
    "wof:name":"Rodolfo Frank Studio D'architettura",
    "wof:placetype":"venue"
},
  "geometry": {"coordinates":[8.742036,46.161476],"type":"Point"}
}