{
  "type": "Feature",
  "properties": {
    "iso:country":"CH",
    "sg:address":"Wyssmattstr. 3",
    "sg:city":"Kriens",
    "sg:classifiers":[
        {
            "category":"Shopping",
            "type":"Retail Goods"
        }
    ],
    "sg:phone":"+41 41 310 85 60",
    "sg:postcode":"6010",
    "sg:province":"Luzern",
    "sg:tags":[
        "metallurgy",
        "finished",
        "-",
        "metalworking",
        "metallic"
    ],
    "wof:name":"Robert Baumann",
    "wof:placetype":"venue"
},
  "geometry": {"coordinates":[8.2925481796,47.030254364],"type":"Point"}
}