{
  "type": "Feature",
  "properties": {
    "iso:country":"CH",
    "sg:address":"Von Roll-strasse 2",
    "sg:city":"Oensingen",
    "sg:orig_category":"Vermittlung von Immobilien Verwaltung von Immobilien",
    "sg:phone":"+41 62 396 34 36",
    "sg:postcode":"4702",
    "sg:province":"Solothurn",
    "wof:name":"Monika Allemann Immobilien-treuhand",
    "wof:placetype":"venue"
},
  "geometry": {"coordinates":[7.7093467712,47.2856864929],"type":"Point"}
}