{
  "type": "Feature",
  "properties": {
    "iso:country":"CH",
    "sg:address":"Place D`armes 3 2000 Neuch\u00e2tel Case Postale 502",
    "sg:city":"Neuenburg",
    "sg:orig_category":"Architektur U Ingenieurb\u00fcros Architekturb\u00fcros",
    "sg:phone":"+41 71 311 36 36",
    "sg:postcode":"2000",
    "sg:province":"Neuch\u00e2tel",
    "wof:name":"Georg B\u00fchler Architekturb\u00fcro Ag",
    "wof:placetype":"venue"
},
  "geometry": {"coordinates":[9.326026,47.425903],"type":"Point"}
}