{
  "type": "Feature",
  "properties": {
    "iso:country":"CH",
    "sg:address":"Via Ai Molini 1",
    "sg:city":"Losone",
    "sg:orig_category":"Vermittlung von Immobilien Wirtschaftspr\u00fcfung, Steuerberatung U Treuhand",
    "sg:phone":"+41 91 791 39 58",
    "sg:postcode":"6616",
    "sg:province":"Ticino",
    "wof:name":"Studio Fiduciario E Immobiliare Piozzini Armando E Marco",
    "wof:placetype":"venue"
},
  "geometry": {"coordinates":[8.760219574,46.1646003723],"type":"Point"}
}