{
  "type": "Feature",
  "properties": {
    "addr:full":"Pfeffingerstrasse 27 4053 Basel. Postfach Basel Basel-Stadt 4051",
    "addr:housenumber":"27",
    "addr:postcode":"4053;4051",
    "addr:street":"Pfeffingerstrasse;Postfach",
    "iso:country":"CH",
    "sg:address":"Pfeffingerstrasse 27 4053 Basel. Postfach",
    "sg:city":"Basel",
    "sg:orig_category":"Architektur U Ingenieurb\u00fcros",
    "sg:postcode":"4051",
    "sg:province":"Basel-Stadt",
    "wof:name":"Vogel Dr. H. B\u00fcro F\u00fcr Bodenforschung",
    "wof:placetype":"venue"
},
  "geometry": {"coordinates":[7.591749,47.544685],"type":"Point"}
}