{
  "type": "Feature",
  "properties": {
    "iso:country":"CH",
    "sg:address":"Forgerons Rue Des 21",
    "sg:city":"Grand-savagnier",
    "sg:orig_category":"Unclassifiable Establishments",
    "sg:postcode":"2065",
    "sg:province":"Neuch\u00e2tel",
    "wof:name":"Ebel Jardins",
    "wof:placetype":"venue"
},
  "geometry": {"coordinates":[6.9550199509,47.0474662781],"type":"Point"}
}