{
  "type": "Feature",
  "properties": {
    "iso:country":"CH",
    "sg:address":"Chemin De La Montagne 112 1224 Ch\u00eane-bougeries. Postfach",
    "sg:city":"Ch\u00eane-bougeries",
    "sg:orig_category":"Softwareentwicklung U beratung",
    "sg:postcode":"1224",
    "sg:province":"Gen\u00e8ve",
    "wof:name":"Burki Info S\u00e0rl",
    "wof:placetype":"venue"
},
  "geometry": {"coordinates":[6.198969841,46.2042617798],"type":"Point"}
}