{
  "type": "Feature",
  "properties": {
    "iso:country":"CH",
    "sg:address":"Obere Gasse 35",
    "sg:city":"Chur",
    "sg:orig_category":"Druck ohne Zeitungsdruck",
    "sg:postcode":"7000",
    "sg:province":"Graubunden",
    "wof:name":"Darwa, W. Zogg.",
    "wof:placetype":"venue"
},
  "geometry": {"coordinates":[9.5304136276,46.8478813171],"type":"Point"}
}