{
  "type": "Feature",
  "properties": {
    "iso:country":"CH",
    "sg:address":"Epautheyres",
    "sg:city":"Essertines-yverdon",
    "sg:orig_category":"Gartenbau Landschaftsplanungsb\u00fcros U Gartenarchitekturb\u00fcros",
    "sg:phone":"+41 22 342 90 97",
    "sg:postcode":"1417",
    "sg:province":"Vaud",
    "wof:name":"Gonzalez, Jardinier-paysagiste.",
    "wof:placetype":"venue"
},
  "geometry": {"coordinates":[6.1454339027,46.1841506958],"type":"Point"}
}