{
  "type": "Feature",
  "properties": {
    "addr:full":"Poststrasse 6 Uster Z\u00fcrich 8610",
    "addr:housenumber":"6",
    "addr:postcode":"8610",
    "addr:street":"Poststrasse",
    "iso:country":"CH",
    "sg:address":"Poststrasse 6",
    "sg:city":"Uster",
    "sg:orig_category":"Buchf\u00fchrung Verwaltung von Immobilien",
    "sg:phone":"+41 19943860",
    "sg:postcode":"8610",
    "sg:province":"Z\u00fcrich",
    "wof:name":"Roger Ziegenhagen Accounting Service",
    "wof:placetype":"venue"
},
  "geometry": {"coordinates":[8.717903,47.349918],"type":"Point"}
}