{
  "type": "Feature",
  "properties": {
    "iso:country":"CH",
    "sg:address":"Zona Industriale 2",
    "sg:city":"Bioggio",
    "sg:orig_category":"Bauschreinerei Herstellung von Konstruktionsteilen, Fertigbauteilen U Ausbauelementen aus Holz",
    "sg:phone":"+41 91 605 54 51",
    "sg:postcode":"6934",
    "sg:province":"Ticino",
    "wof:name":"Binda Sa",
    "wof:placetype":"venue"
},
  "geometry": {"coordinates":[8.9086551666,46.0143966675],"type":"Point"}
}