{
  "type": "Feature",
  "properties": {
    "iso:country":"CH",
    "sg:address":"Bahnhofstrasse 25",
    "sg:city":"Wangs",
    "sg:orig_category":"Elektrischer Leitungsbau",
    "sg:phone":"+41 81 710 56 53",
    "sg:postcode":"7323",
    "sg:province":"St. Gallen",
    "wof:name":"Cablecom Engineering Ag",
    "wof:placetype":"venue"
},
  "geometry": {"coordinates":[9.4335107803,47.0361824036],"type":"Point"}
}