{
  "type": "Feature",
  "properties": {
    "iso:country":"CH",
    "sg:address":"B\u00fcttenring 10 6006 Luzern. Postfach",
    "sg:city":"Luzern",
    "sg:orig_category":"Maschinen-Fabrikation",
    "sg:postcode":"6003",
    "sg:province":"Luzern",
    "wof:name":"Cad Construct Gmbh Maschinenbauteile; Entwicklung, Herstellung Usw",
    "wof:placetype":"venue"
},
  "geometry": {"coordinates":[8.3547306061,47.0548171997],"type":"Point"}
}