{
  "type": "Feature",
  "properties": {
    "iso:country":"CH",
    "sg:address":"Hofmattstrasse 12",
    "sg:city":"Huttwil",
    "sg:orig_category":"Elektroinstallation",
    "sg:phone":"+41 62 962 20 22",
    "sg:postcode":"4950",
    "sg:province":"Bern",
    "wof:name":"Paul R\u00fceger Elektrische Anlagen",
    "wof:placetype":"venue"
},
  "geometry": {"coordinates":[7.8472619057,47.1132278442],"type":"Point"}
}