{
  "type": "Feature",
  "properties": {
    "iso:country":"CH",
    "sg:address":"R\u00f6telirainstrasse 22",
    "sg:city":"Menziken",
    "sg:orig_category":"D\u00e4mmung gegen K\u00e4lte, W\u00e4rme, Schall U Ersch\u00fctterung Herstellung von sonstigen Metallwaren",
    "sg:phone":"+41 62 771 67 82",
    "sg:postcode":"5737",
    "sg:province":"Aargau",
    "wof:name":"Hans-werner Maurer Bautenschutz Abdichtungen",
    "wof:placetype":"venue"
},
  "geometry": {"coordinates":[8.1952228546,47.2397155762],"type":"Point"}
}