{
  "type": "Feature",
  "properties": {
    "iso:country":"CH",
    "sg:address":"Gerechtigkeitsgasse 9 3011 Bern. Postfach",
    "sg:city":"Bern",
    "sg:orig_category":"RESTAURANTS: TEA-ROOMS",
    "sg:phone":"+41 31 312 41 12",
    "sg:postcode":"3005",
    "sg:province":"Bern",
    "wof:name":"Imbiss-kurier, Ferencz G. Verkauf V Menus Im Fast-food-bereich",
    "wof:placetype":"venue"
},
  "geometry": {"coordinates":[7.4553890228,46.9484481812],"type":"Point"}
}