{
  "type": "Feature",
  "properties": {
    "iso:country":"CH",
    "sg:address":"General Guisan-strasse 103",
    "sg:city":"Basel",
    "sg:orig_category":"Bauingenieurb\u00fcros Hochbau Bauingenieurb\u00fcros allgemein",
    "sg:phone":"+41 61 302 06 06",
    "sg:postcode":"4054",
    "sg:province":"Basel-Stadt",
    "wof:name":"Stephan Renz Ingenieurb\u00fcro",
    "wof:placetype":"venue"
},
  "geometry": {"coordinates":[7.565174,47.54948],"type":"Point"}
}