{
  "type": "Feature",
  "properties": {
    "iso:country":"CH",
    "sg:address":"Avenue Des Gittaz 4",
    "sg:city":"Ste-croix",
    "sg:orig_category":"Architektur U Ingenieurb\u00fcros",
    "sg:phone":"+41 21 731 38 78",
    "sg:postcode":"1450",
    "sg:province":"Vaud",
    "wof:name":"Delatechnique Sa",
    "wof:placetype":"venue"
},
  "geometry": {"coordinates":[7.164905,46.746414],"type":"Point"}
}