{
  "type": "Feature",
  "properties": {
    "iso:country":"CH",
    "sg:address":"Via Pazzalino 15",
    "sg:city":"Viganello",
    "sg:orig_category":"RESTAURANTS: TEA-ROOMS",
    "sg:phone":"+41 91 971 71 40",
    "sg:postcode":"6962",
    "sg:province":"Ticino",
    "wof:name":"Osteria-pizzeria La Bettola",
    "wof:placetype":"venue"
},
  "geometry": {"coordinates":[8.970290184,46.0151138306],"type":"Point"}
}