{
  "type": "Feature",
  "properties": {
    "iso:country":"CH",
    "sg:address":"Treycovagnes Chauss\u00e9e De 7 1400 Yverdon-les-bains Case Postale",
    "sg:city":"Yverdon-les-bains",
    "sg:orig_category":"Handel mit Automobilen",
    "sg:phone":"+41 24 445 63 24",
    "sg:postcode":"1400",
    "sg:province":"Vaud",
    "wof:name":"Auto-fila Sa",
    "wof:placetype":"venue"
},
  "geometry": {"coordinates":[6.6248512268,46.778377533],"type":"Point"}
}