{
  "type": "Feature",
  "properties": {
    "iso:country":"CH",
    "sg:address":"Grand-rue 2 1530 Payerne Case Postale 412",
    "sg:city":"Payerne",
    "sg:orig_category":"Versicherungen Generalagenturen",
    "sg:phone":"+41 26 662 40 40",
    "sg:postcode":"1530",
    "sg:province":"Vaud",
    "wof:name":"Vaudoise Assurances Agence G\u00e9n\u00e9rale",
    "wof:placetype":"venue"
},
  "geometry": {"coordinates":[6.9400320053,46.821975708],"type":"Point"}
}