{
  "type": "Feature",
  "properties": {
    "addr:full":"Museggstrasse 35 Luzern Luzern 6004",
    "addr:housenumber":"35",
    "addr:postcode":"6004",
    "addr:street":"Museggstrasse",
    "iso:country":"CH",
    "sg:address":"Museggstrasse 35",
    "sg:city":"Luzern",
    "sg:orig_category":"Architekturb\u00fcros",
    "sg:phone":"+41 41 410 23 73",
    "sg:postcode":"6004",
    "sg:province":"Luzern",
    "wof:name":"Gotthard Erni Architekturb\u00fcro",
    "wof:placetype":"venue"
},
  "geometry": {"coordinates":[8.30288,47.053238],"type":"Point"}
}