{
  "type": "Feature",
  "properties": {
    "iso:country":"CH",
    "sg:address":"Oron Route D' 39",
    "sg:city":"Lausanne",
    "sg:orig_category":"Instandhaltung U Reparatur von Automobilen",
    "sg:phone":"+41 21 652 91 48",
    "sg:postcode":"1010",
    "sg:province":"Vaud",
    "wof:name":"Centre Widas Von Allmen W. Sa Lausanne",
    "wof:placetype":"venue"
},
  "geometry": {"coordinates":[6.8081388474,46.56665802],"type":"Point"}
}