{
  "type": "Feature",
  "properties": {
    "iso:country":"CH",
    "sg:address":"Route De La Belle-croix 24",
    "sg:city":"Haute-nendaz",
    "sg:classifiers":[
        {
            "category":"Restaurant",
            "type":"Food & Drink"
        }
    ],
    "sg:phone":"+41 71 222 69 38",
    "sg:postcode":"1997",
    "sg:province":"Valais",
    "sg:tags":[
        "tea-rooms",
        "restaurants"
    ],
    "wof:name":"Barcelona Gastro Gmbh",
    "wof:placetype":"venue"
},
  "geometry": {"coordinates":[9.3752717972,47.4234199524],"type":"Point"}
}