{
  "type": "Feature",
  "properties": {
    "iso:country":"CH",
    "sg:address":"Chemin Des Falquets 49",
    "sg:city":"Cologny",
    "sg:orig_category":"Sportvereine Ski",
    "sg:postcode":"1223",
    "sg:province":"Gen\u00e8ve",
    "wof:name":"Ski-club Amis Montagnards",
    "wof:placetype":"venue"
},
  "geometry": {"coordinates":[6.190955162,46.2096366882],"type":"Point"}
}