{
  "type": "Feature",
  "properties": {
    "iso:country":"CH",
    "sg:address":"Via Angelo Baroffio 6 6900 Lugano. Postfach",
    "sg:city":"Lugano",
    "sg:orig_category":"Non-Classified Establishments",
    "sg:postcode":"6900",
    "sg:province":"Ticino",
    "wof:name":"Shironeko.com Di Crudo Davide",
    "wof:placetype":"venue"
},
  "geometry": {"coordinates":[8.9474363327,46.0064888],"type":"Point"}
}