{
  "type": "Feature",
  "properties": {
    "iso:country":"CH",
    "sg:address":"Karl-schenk-passage 4",
    "sg:city":"Bern",
    "sg:orig_category":"Detailhandel mit Schuhen U Lederwaren",
    "sg:postcode":"3000",
    "sg:province":"Bern",
    "wof:name":"Chaussures Michelle Ag",
    "wof:placetype":"venue"
},
  "geometry": {"coordinates":[7.4430389404,46.9484825134],"type":"Point"}
}