{
  "type": "Feature",
  "properties": {
    "iso:country":"CH",
    "sg:address":"Baselstrasse 22",
    "sg:city":"Arlesheim",
    "sg:orig_category":"Architektur U Ingenieurb\u00fcros Unternehmensberatung",
    "sg:phone":"+41 61 706 96 28",
    "sg:postcode":"4144",
    "sg:province":"Basel-Landschaft",
    "wof:name":"Gutag Ag",
    "wof:placetype":"venue"
},
  "geometry": {"coordinates":[7.620337,47.497589],"type":"Point"}
}