{
  "type": "Feature",
  "properties": {
    "iso:country":"CH",
    "sg:address":"2824 Vicques Case Postale 102",
    "sg:city":"Vicques",
    "sg:orig_category":"Sportvereine Ballsport Fussball",
    "sg:phone":"+41 32 435 69 91",
    "sg:postcode":"2824",
    "sg:province":"Jura",
    "wof:name":"Fc Vicques",
    "wof:placetype":"venue"
},
  "geometry": {"coordinates":[7.4162049294,47.3487281799],"type":"Point"}
}