{
  "type": "Feature",
  "properties": {
    "iso:country":"CH",
    "sg:address":"Elisried 3152 Mamishaus. Postfach",
    "sg:city":"Mamishaus",
    "sg:orig_category":"Grosshandel mit Getr\u00e4nken",
    "sg:postcode":"3152",
    "sg:province":"Bern",
    "wof:name":"Gurtner's Beerenkulturen & Weingrotte Fruchtweine, Fruchtschaumweine Usw.; Handel",
    "wof:placetype":"venue"
},
  "geometry": {"coordinates":[7.3641462326,46.8205718994],"type":"Point"}
}