{
  "type": "Feature",
  "properties": {
    "iso:country":"CH",
    "sg:address":"1055",
    "sg:city":"Froideville",
    "sg:orig_category":"Vorschulen, Kinderg\u00e4rten",
    "sg:postcode":"1055",
    "sg:province":"Vaud",
    "wof:name":"Ecole Enfantine",
    "wof:placetype":"venue"
},
  "geometry": {"coordinates":[6.6880102158,46.5993614197],"type":"Point"}
}