{
  "type": "Feature",
  "properties": {
    "iso:country":"CH",
    "sg:address":"Grundstrasse 12",
    "sg:city":"Rotkreuz",
    "sg:orig_category":"Mixing Desks",
    "sg:phone":"+41 21 651 01 01",
    "sg:postcode":"6343",
    "sg:province":"Zug",
    "wof:name":"Sonosax Sas Sa",
    "wof:placetype":"venue"
},
  "geometry": {"coordinates":[6.6192541122,46.5631065369],"type":"Point"}
}