{
  "type": "Feature",
  "properties": {
    "iso:country":"CH",
    "sg:address":"Route Du Tir F\u00e9d\u00e9ral 18 1762 Givisiez Case Postale 518",
    "sg:city":"Basel",
    "sg:orig_category":"Detailhandel mit Waren verschiedener Art, Hauptrichtung Nahrungsmittel",
    "sg:phone":"+41 21 633 41 11",
    "sg:postcode":"4053",
    "sg:province":"Basel-Stadt",
    "wof:name":"Coop Direction",
    "wof:placetype":"venue"
},
  "geometry": {"coordinates":[7.131799221,46.8185424805],"type":"Point"}
}