{
  "type": "Feature",
  "properties": {
    "iso:country":"CH",
    "sg:address":"Schwimmbadstrasse 11 8353 Elgg. Postfach 115",
    "sg:city":"Elgg",
    "sg:orig_category":"Verlagsgewerbe Zeitungsverlag",
    "sg:phone":"+41 21 646 22 02",
    "sg:postcode":"8353",
    "sg:province":"Z\u00fcrich",
    "wof:name":"Export-edition Sa",
    "wof:placetype":"venue"
},
  "geometry": {"coordinates":[6.6239891052,46.5260353088],"type":"Point"}
}