{
  "type": "Feature",
  "properties": {
    "iso:country":"CH",
    "sg:address":"Dorfstrasse 717",
    "sg:city":"Gontenschwil",
    "sg:orig_category":"Schlossereien Schmieden",
    "sg:phone":"+41 62 773 25 50",
    "sg:postcode":"5728",
    "sg:province":"Aargau",
    "wof:name":"Fritz Gautschi Schmiede & Schlosserei",
    "wof:placetype":"venue"
},
  "geometry": {"coordinates":[8.144862175,47.276348114],"type":"Point"}
}