{
  "type": "Feature",
  "properties": {
    "iso:country":"CH",
    "sg:address":"Via Cantonale.",
    "sg:city":"Orselina",
    "sg:orig_category":"Detailhandel mit Brot, Back U S\u00fcsswaren",
    "sg:postcode":"6644",
    "sg:province":"Ticino",
    "wof:name":"Cecchettin.",
    "wof:placetype":"venue"
},
  "geometry": {"coordinates":[8.798625,46.178726],"type":"Point"}
}