{
  "type": "Feature",
  "properties": {
    "iso:country":"CH",
    "sg:address":"Rue Du Faubourg 10",
    "sg:city":"Savagnier",
    "sg:orig_category":"Gem\u00fcsebau",
    "sg:phone":"+41 32 853 67 95",
    "sg:postcode":"2065",
    "sg:province":"Neuch\u00e2tel",
    "wof:name":"Marc Challandes Maraicher",
    "wof:placetype":"venue"
},
  "geometry": {"coordinates":[6.9564452171,47.0504837036],"type":"Point"}
}