{
  "type": "Feature",
  "properties": {
    "iso:country":"CH",
    "sg:address":"Place De La T\u00e9l\u00e9cabine",
    "sg:city":"Haute-nendaz",
    "sg:orig_category":"Diskotheken, Dancings, Night Clubs",
    "sg:phone":"+41 27 288 23 14",
    "sg:postcode":"1997",
    "sg:province":"Valais",
    "wof:name":"Dancing Le Feeling",
    "wof:placetype":"venue"
},
  "geometry": {"coordinates":[7.2953381538,46.1824874878],"type":"Point"}
}