{
  "type": "Feature",
  "properties": {
    "iso:country":"CH",
    "sg:address":"Z\u00fcrcherstrasse 51",
    "sg:city":"Baden",
    "sg:orig_category":"RESTAURANTS: TEA-ROOMS",
    "sg:phone":"+41 56 222 42 71",
    "sg:postcode":"5400",
    "sg:province":"Aargau",
    "wof:name":"Restaurant Kreuzliberg",
    "wof:placetype":"venue"
},
  "geometry": {"coordinates":[8.3063077927,47.4664993286],"type":"Point"}
}