{
  "type": "Feature",
  "properties": {
    "addr:full":"Spitzackerstrasse 7 N\u00fcrensdorf Z\u00fcrich 8309",
    "addr:housenumber":"7",
    "addr:postcode":"8309",
    "addr:street":"Spitzackerstrasse",
    "iso:country":"CH",
    "sg:address":"Spitzackerstrasse 7",
    "sg:city":"N\u00fcrensdorf",
    "sg:orig_category":"Detailhandel mit Beleuchtungs U Haushaltsgegenst\u00e4nden Detailhandel mit Geschenkartikeln U Souvenirs",
    "sg:phone":"+41 71 222 33 93",
    "sg:postcode":"8309",
    "sg:province":"Z\u00fcrich",
    "wof:name":"Ursi Rupf Tip's F\u00fcr K\u00fcche & Tisch",
    "wof:placetype":"venue"
},
  "geometry": {"coordinates":[9.375952,47.423908],"type":"Point"}
}