{
  "type": "Feature",
  "properties": {
    "iso:country":"CH",
    "sg:address":"Via Grumo 24",
    "sg:city":"Gravesano",
    "sg:classifiers":[
        {
            "category":"Bars & Pubs",
            "type":"Food & Drink"
        }
    ],
    "sg:phone":"+41 91 604 63 95",
    "sg:postcode":"6929",
    "sg:province":"Ticino",
    "wof:name":"Reno Bar",
    "wof:placetype":"venue"
},
  "geometry": {"coordinates":[8.923723,46.039246],"type":"Point"}
}