{
  "type": "Feature",
  "properties": {
    "iso:country":"CH",
    "sg:address":"W\u00fclflingerstrasse 230",
    "sg:city":"Winterthur",
    "sg:orig_category":"Nationale Postdienste",
    "sg:phone":"+41 31 839 21 02",
    "sg:postcode":"8408",
    "sg:province":"Z\u00fcrich",
    "wof:name":"Die Schweizerische Post Worb 1",
    "wof:placetype":"venue"
},
  "geometry": {"coordinates":[7.5631980896,46.9302368164],"type":"Point"}
}