{
  "type": "Feature",
  "properties": {
    "iso:country":"CH",
    "sg:address":"Schlossgasse 23",
    "sg:city":"Lenzburg",
    "sg:orig_category":"Museen",
    "sg:phone":"+41 62 891 66 70",
    "sg:postcode":"5600",
    "sg:province":"Aargau",
    "wof:name":"Museum Burghalde",
    "wof:placetype":"venue"
},
  "geometry": {"coordinates":[8.1831912994,47.3855628967],"type":"Point"}
}