{
  "type": "Feature",
  "properties": {
    "iso:country":"CH",
    "sg:address":"Schulhausstrasse 4",
    "sg:city":"Oberdiessbach",
    "sg:orig_category":"Allgemeiner Hoch U Tiefbau Hoch U Tiefbau",
    "sg:phone":"+41 31 770 77 77",
    "sg:postcode":"3672",
    "sg:province":"Bern",
    "wof:name":"Hirschi Bauunternehmung Ag",
    "wof:placetype":"venue"
},
  "geometry": {"coordinates":[7.621374,46.839588],"type":"Point"}
}