{
  "type": "Feature",
  "properties": {
    "iso:country":"CH",
    "sg:address":"Via Del Tiglio 11 6900 Lugano. Postfach 6906 Lugano",
    "sg:city":"Caselle",
    "sg:orig_category":"Vermietung U Verpachtung von eigenen Immobilien",
    "sg:postcode":"6",
    "wof:name":"Tanystropheus Sa",
    "wof:placetype":"venue"
},
  "geometry": {"coordinates":[8.962387085,46.0076026917],"type":"Point"}
}