{
  "type": "Feature",
  "properties": {
    "iso:country":"CH",
    "sg:address":"Hohstrasse 1 8302 Kloten. Postfach 535",
    "sg:city":"Kloten",
    "sg:orig_category":"Grosshandel mit B\u00fcromaschinen Grosshandel mit Datenverarbeitungsger\u00e4ten",
    "sg:phone":"+41 18047474",
    "sg:postcode":"8302",
    "sg:province":"Z\u00fcrich",
    "wof:name":"Cabtronix Gmbh",
    "wof:placetype":"venue"
},
  "geometry": {"coordinates":[8.5957994461,47.4507980347],"type":"Point"}
}