{
  "type": "Feature",
  "properties": {
    "iso:country":"CH",
    "sg:address":"W\u00fclflingerstrasse 2 8400 Winterthur. Postfach 606",
    "sg:city":"Winterthur",
    "sg:orig_category":"Public-Relations-Agenturen",
    "sg:phone":"+41 52 213 12 32",
    "sg:postcode":"8401",
    "sg:province":"Z\u00fcrich",
    "wof:name":"P-art Bachmann Public Relations",
    "wof:placetype":"venue"
},
  "geometry": {"coordinates":[8.7242336273,47.5028533936],"type":"Point"}
}