{
  "type": "Feature",
  "properties": {
    "iso:country":"CH",
    "sg:address":"Bifangstrasse 9",
    "sg:city":"Zofingen",
    "sg:orig_category":"Bauschreinerei",
    "sg:phone":"+41 62 751 32 32",
    "sg:postcode":"4800",
    "sg:province":"Aargau",
    "wof:name":"Robert Willisegger Schreinerei",
    "wof:placetype":"venue"
},
  "geometry": {"coordinates":[7.946361,47.292316],"type":"Point"}
}