{
  "type": "Feature",
  "properties": {
    "iso:country":"CH",
    "sg:address":"Rte De Corcelles 112",
    "sg:city":"Cr\u00e9mines",
    "sg:classifiers":[
        {
            "category":"Banks & Credit Unions",
            "subcategory":"Bank",
            "type":"Services"
        }
    ],
    "sg:phone":"+41 32 499 90 88",
    "sg:postcode":"2746",
    "sg:province":"Bern",
    "wof:name":"Raiffeisen",
    "wof:placetype":"venue"
},
  "geometry": {"coordinates":[7.442824,47.283726],"type":"Point"}
}