{
  "type": "Feature",
  "properties": {
    "iso:country":"CH",
    "sg:address":"Echallens Avenue D' 6 1004 Lausanne. Postfach",
    "sg:city":"Lausanne",
    "sg:orig_category":"Herstellung von Duft U K\u00f6rperpflegemitteln",
    "sg:postcode":"1003",
    "sg:province":"Vaud",
    "wof:name":"Roos Christiane Articles Cosm\u00e9tiques; Vente",
    "wof:placetype":"venue"
},
  "geometry": {"coordinates":[6.6187300682,46.5334892273],"type":"Point"}
}