{
  "type": "Feature",
  "properties": {
    "iso:country":"CH",
    "sg:address":"L\u00e4ttenwiesenstrasse 3",
    "sg:city":"Glattbrugg",
    "sg:orig_category":"Unternehmensberatung",
    "sg:postcode":"8152",
    "sg:province":"Z\u00fcrich",
    "wof:name":"Osc Ag Consulting Management Communication",
    "wof:placetype":"venue"
},
  "geometry": {"coordinates":[8.5666475296,47.4275932312],"type":"Point"}
}