{
  "type": "Feature",
  "properties": {
    "addr:full":"Domaine Les Carroz Vucherens 1086",
    "addr:postcode":"1086",
    "addr:street":"Vucherens",
    "iso:country":"CH",
    "sg:address":"Domaine Les Carroz",
    "sg:city":"Vucherens",
    "sg:orig_category":"Haltung von Gefl\u00fcgel",
    "sg:phone":"+41 21 903 03 55",
    "sg:postcode":"1086",
    "wof:name":"Stettler Produits Alimentaires Sa,parc Avicole Du Jorat",
    "wof:placetype":"venue"
},
  "geometry": {"coordinates":[6.781355,46.624836],"type":"Point"}
}