{
  "type": "Feature",
  "properties": {
    "iso:country":"CH",
    "sg:address":"Heinrichstrasse 125",
    "sg:city":"Z\u00fcrich",
    "sg:orig_category":"Arztpraxen",
    "sg:phone":"+41 61 402 08 68",
    "sg:postcode":"8005",
    "sg:province":"Z\u00fcrich",
    "wof:name":"Dr.med.werner Jelk Spezialarzt Fmh",
    "wof:placetype":"venue"
},
  "geometry": {"coordinates":[7.554929,47.509212],"type":"Point"}
}