{
  "type": "Feature",
  "properties": {
    "iso:country":"CH",
    "sg:address":"B\u00fchlstr. 3",
    "sg:city":"Boppelsen",
    "sg:orig_category":"Vermietung U Verpachtung von eigenen Immobilien",
    "sg:phone":"+41 31 951 11 74",
    "sg:postcode":"8113",
    "sg:province":"Z\u00fcrich",
    "wof:name":"Rindlisbacher Immobilien-treuhand",
    "wof:placetype":"venue"
},
  "geometry": {"coordinates":[7.4836640358,46.9304695129],"type":"Point"}
}