{
  "type": "Feature",
  "properties": {
    "addr:full":"Chemin De La Fontaine 8 Ch\u00eane-bougeries Gen\u00e8ve 1224",
    "addr:housenumber":"8",
    "addr:postcode":"1224",
    "addr:street":"Chemin De La Fontaine",
    "iso:country":"CH",
    "sg:address":"Chemin De La Fontaine 8",
    "sg:city":"Ch\u00eane-bougeries",
    "sg:orig_category":"Detailhandel mit Brillen U anderen Sehhilfen Fachdetailhandel in Verkaufsr\u00e4umen",
    "sg:phone":"+41 22 348 07 28",
    "sg:postcode":"1224",
    "sg:province":"Gen\u00e8ve",
    "wof:name":"New Optique, Pradervand Laurent",
    "wof:placetype":"venue"
},
  "geometry": {"coordinates":[6.19089,46.19685],"type":"Point"}
}