{
  "type": "Feature",
  "properties": {
    "iso:country":"CH",
    "sg:address":"Freilagerstrasse 47",
    "sg:city":"Z\u00fcrich",
    "sg:orig_category":"Sonstige Verkehrsvermittlung",
    "sg:phone":"+41 14056262",
    "sg:postcode":"8043",
    "sg:province":"Z\u00fcrich",
    "wof:name":"Z\u00fcrcher Freilager Ag",
    "wof:placetype":"venue"
},
  "geometry": {"coordinates":[8.4902496338,47.3798408508],"type":"Point"}
}