{
  "type": "Feature",
  "properties": {
    "iso:country":"CH",
    "sg:address":"Huebstrasse 1",
    "sg:city":"Zurzach",
    "sg:orig_category":"Arztpraxen",
    "sg:phone":"+41 56 249 27 77",
    "sg:postcode":"5330",
    "sg:province":"Aargau",
    "wof:name":"Dr.med.martin Dubler Arzt F.allgemeine Medizin Fmh",
    "wof:placetype":"venue"
},
  "geometry": {"coordinates":[8.291622,47.584095],"type":"Point"}
}