{
  "type": "Feature",
  "properties": {
    "iso:country":"CH",
    "sg:address":"Rosenbergstrasse 4",
    "sg:city":"Luzern",
    "sg:orig_category":"Aktivit\u00e4ten der Krankenschwestern U Hebammen, Hauspflege Gesundheits U Sozialwesen",
    "sg:phone":"+41 41 429 30 70",
    "sg:postcode":"6004",
    "sg:province":"Luzern",
    "wof:name":"Spitex Luzern",
    "wof:placetype":"venue"
},
  "geometry": {"coordinates":[8.305451,47.061169],"type":"Point"}
}