{
  "type": "Feature",
  "properties": {
    "iso:country":"CH",
    "sg:address":"St-cergue Route De 23",
    "sg:city":"Nyon",
    "sg:orig_category":"Herstellung von homogenisierten U di\u00e4tetischen Nahrungsmitteln",
    "sg:postcode":"1260",
    "sg:province":"Vaud",
    "wof:name":"Di\u00e9t\u00e9tique Import-export, Arzouni Soumeire Christiane",
    "wof:placetype":"venue"
},
  "geometry": {"coordinates":[6.2603201866,46.5135612488],"type":"Point"}
}