{
  "type": "Feature",
  "properties": {
    "iso:country":"CH",
    "sg:address":"Via Cantone",
    "sg:city":"Rancate",
    "sg:orig_category":"Instandhaltung U Reparatur von Automobilen",
    "sg:phone":"+41 91 646 24 41",
    "sg:postcode":"6862",
    "sg:province":"Ticino",
    "wof:name":"Gandini Fratelli",
    "wof:placetype":"venue"
},
  "geometry": {"coordinates":[8.9707164764,45.881061554],"type":"Point"}
}