{
  "type": "Feature",
  "properties": {
    "iso:country":"CH",
    "sg:address":"Sonnhalde 1",
    "sg:city":"Flamatt",
    "sg:orig_category":"Non-Classified Establishments",
    "sg:phone":"+41 31 741 02 88",
    "sg:postcode":"3175",
    "sg:province":"Fribourg",
    "wof:name":"Karl Leder Opaho Holzanz\u00fcnder",
    "wof:placetype":"venue"
},
  "geometry": {"coordinates":[7.3084349632,46.8884162903],"type":"Point"}
}