{
  "type": "Feature",
  "properties": {
    "iso:country":"CH",
    "sg:address":"Route De Moudon 8 1522 Lucens Case Postale 142",
    "sg:city":"Lucens",
    "sg:orig_category":"Herstellung von sonstigen Produkten aus nichtmetallischen Mineralien",
    "sg:phone":"+41 21 995 55 55",
    "sg:postcode":"1522",
    "sg:province":"Vaud",
    "wof:name":"Reymond & Co Sa",
    "wof:placetype":"venue"
},
  "geometry": {"coordinates":[6.837882,46.707325],"type":"Point"}
}