{
  "type": "Feature",
  "properties": {
    "iso:country":"CH",
    "sg:address":"Baslerstrasse 355",
    "sg:city":"Allschwil",
    "sg:orig_category":"RESTAURANTS: TEA-ROOMS",
    "sg:phone":"+41 61 302 12 20",
    "sg:postcode":"4123",
    "sg:province":"Basel-Landschaft",
    "wof:name":"Restaurant Zic-zac Rockgarden",
    "wof:placetype":"venue"
},
  "geometry": {"coordinates":[7.5641908646,47.5572242737],"type":"Point"}
}