{
  "type": "Feature",
  "properties": {
    "iso:country":"CH",
    "sg:address":"Wildenhof 3",
    "sg:city":"Neuhausen",
    "sg:orig_category":"Fachdetailhandel in Verkaufsr\u00e4umen",
    "sg:phone":"+41 17613460",
    "sg:postcode":"8212",
    "sg:province":"Schaffhausen",
    "wof:name":"Topp Optik Gmbh",
    "wof:placetype":"venue"
},
  "geometry": {"coordinates":[8.4542570114,47.2805480957],"type":"Point"}
}