{
  "type": "Feature",
  "properties": {
    "iso:country":"CH",
    "sg:address":"Rorschacher Strasse 22",
    "sg:city":"Steinach",
    "sg:classifiers":[
        {
            "category":"Restaurant",
            "type":"Food & Drink"
        }
    ],
    "sg:phone":"+41 71 446 14 34",
    "sg:postcode":"9323",
    "sg:province":"St. Gallen",
    "wof:name":"Restaurant Krone",
    "wof:placetype":"venue"
},
  "geometry": {"coordinates":[9.4371175766,47.4917678833],"type":"Point"}
}