{
  "type": "Feature",
  "properties": {
    "iso:country":"CH",
    "sg:address":"Dorfstr. 12",
    "sg:city":"Grossaffoltern",
    "sg:classifiers":[
        {
            "category":"Farming",
            "subcategory":"Farm",
            "type":"Manufacturing & Wholesale Goods"
        }
    ],
    "sg:phone":"+41 32 389 10 10",
    "sg:postcode":"3257",
    "sg:province":"Bern",
    "sg:tags":[
        "horticulture",
        "agriculture",
        "livestock"
    ],
    "wof:name":"Hauert & Co",
    "wof:placetype":"venue"
},
  "geometry": {"coordinates":[7.359168,47.065498],"type":"Point"}
}