{
  "type": "Feature",
  "properties": {
    "iso:country":"CH",
    "sg:address":"Dorfstrasse 30a 5430 Wettingen. Postfach",
    "sg:city":"Wettingen",
    "sg:orig_category":"Unclassifiable Establishments",
    "sg:phone":"+41 56 426 15 16",
    "sg:postcode":"5430",
    "sg:province":"Aargau",
    "wof:name":"Zetef Kommunikation Z. Fristensky",
    "wof:placetype":"venue"
},
  "geometry": {"coordinates":[8.3320102692,47.4669837952],"type":"Point"}
}