{
  "type": "Feature",
  "properties": {
    "iso:country":"CH",
    "sg:address":"Kantonsstrasse",
    "sg:city":"Entlebuch",
    "sg:classifiers":[
        {
            "category":"Travel",
            "subcategory":"Hotels & Motels",
            "type":"Entertainment"
        }
    ],
    "sg:phone":"+41 79 415 61 85",
    "sg:postcode":"6162",
    "sg:province":"Luzern",
    "sg:tags":[
        "hotels",
        "mit",
        "restaurant"
    ],
    "wof:name":"Hotel Meienrisli",
    "wof:placetype":"venue"
},
  "geometry": {"coordinates":[8.0649986267,46.9928016663],"type":"Point"}
}