{
  "type": "Feature",
  "properties": {
    "iso:country":"CH",
    "sg:address":"Wolfberg",
    "sg:city":"Kallnach",
    "sg:orig_category":"Detailhandel mit Tabakwaren",
    "sg:postcode":"3283",
    "sg:province":"Bern",
    "wof:name":"Sch\u00fcrch Tobaccos Gmbh",
    "wof:placetype":"venue"
},
  "geometry": {"coordinates":[7.2405958176,47.0279426575],"type":"Point"}
}