{
  "type": "Feature",
  "properties": {
    "iso:country":"CH",
    "sg:address":"Zi Vannel C",
    "sg:city":"Bex",
    "sg:orig_category":"Detailhandel mit Bekleidung",
    "sg:postcode":"1880",
    "sg:province":"Vaud",
    "wof:name":"Taleb Sa",
    "wof:placetype":"venue"
},
  "geometry": {"coordinates":[7.015681,46.250259],"type":"Point"}
}