{
  "type": "Feature",
  "properties": {
    "iso:country":"CH",
    "sg:address":"Theaterstrasse 1",
    "sg:city":"Luzern",
    "sg:orig_category":"Bestattungswesen",
    "sg:phone":"+41 41 240 31 30",
    "sg:postcode":"6003",
    "sg:province":"Luzern",
    "wof:name":"Luzerner Feuerbestattung",
    "wof:placetype":"venue"
},
  "geometry": {"coordinates":[8.306592,47.050735],"type":"Point"}
}