{
  "type": "Feature",
  "properties": {
    "iso:country":"CH",
    "sg:address":"Via Stazio 10",
    "sg:city":"Massagno",
    "sg:orig_category":"Unclassifiable Establishments",
    "sg:postcode":"6900",
    "sg:province":"Ticino",
    "wof:name":"Giannicola Sa",
    "wof:placetype":"venue"
},
  "geometry": {"coordinates":[8.9460878372,46.0110740662],"type":"Point"}
}