{
  "type": "Feature",
  "properties": {
    "iso:country":"CH",
    "sg:address":"Gare Place De La",
    "sg:city":"Nyon",
    "sg:orig_category":"RESTAURANTS: TEA-ROOMS",
    "sg:postcode":"1260",
    "sg:province":"Vaud",
    "wof:name":"Buffet De La Gare, Strassberger Doris",
    "wof:placetype":"venue"
},
  "geometry": {"coordinates":[6.2390799522,46.3823661804],"type":"Point"}
}