{
  "type": "Feature",
  "properties": {
    "iso:country":"CH",
    "sg:address":"Weierstrasse 55",
    "sg:city":"Klingnau",
    "sg:orig_category":"Herstellung von Bergwerks U Baumaschinen",
    "sg:phone":"+41 56 245 76 06",
    "sg:postcode":"5313",
    "sg:province":"Aargau",
    "wof:name":"Sonik Ag",
    "wof:placetype":"venue"
},
  "geometry": {"coordinates":[8.2519025803,47.5797996521],"type":"Point"}
}