{
  "type": "Feature",
  "properties": {
    "addr:full":"Grand-pr\u00e9 Rue Du 4 1202 Gen\u00e8ve. Postfach Gen\u00e8ve Gen\u00e8ve 1202",
    "addr:postcode":"1202;postfach;1202",
    "addr:street":"Rue Du 4",
    "iso:country":"CH",
    "sg:address":"Grand-pr\u00e9 Rue Du 4 1202 Gen\u00e8ve. Postfach",
    "sg:city":"Gen\u00e8ve",
    "sg:orig_category":"Architektur U Ingenieurb\u00fcros",
    "sg:phone":"+41 22 734 48 69",
    "sg:postcode":"1202",
    "sg:province":"Gen\u00e8ve",
    "wof:name":"Dessin Assist\u00e9 Computer, Dac, Canetta Daniel A.",
    "wof:placetype":"venue"
},
  "geometry": {"coordinates":[6.138109,46.212868],"type":"Point"}
}