{
  "type": "Feature",
  "properties": {
    "iso:country":"CH",
    "sg:address":"Cap\u00e4ls",
    "sg:city":"K\u00fcblis",
    "sg:orig_category":"Grosshandel mit Baumaterialien",
    "sg:phone":"+41 81 330 55 66",
    "sg:postcode":"7240",
    "sg:province":"Graubunden",
    "wof:name":"Barit Baubedarf Ag",
    "wof:placetype":"venue"
},
  "geometry": {"coordinates":[9.7861118317,46.9125976562],"type":"Point"}
}