{
  "type": "Feature",
  "properties": {
    "iso:country":"CH",
    "sg:address":"Usteristrasse 17",
    "sg:city":"Z\u00fcrich",
    "sg:orig_category":"Detailhandel mit Uhren U Schmuck",
    "sg:phone":"+41 12113822",
    "sg:postcode":"8001",
    "sg:province":"Z\u00fcrich",
    "wof:name":"Edgar Stickel Goldschmied",
    "wof:placetype":"venue"
},
  "geometry": {"coordinates":[8.5367164612,47.3756866455],"type":"Point"}
}