{
  "type": "Feature",
  "properties": {
    "addr:full":"Brunnenwiesenstrasse 10 D\u00e4llikon Z\u00fcrich 8108",
    "addr:housenumber":"10",
    "addr:postcode":"8108",
    "addr:street":"Brunnenwiesenstrasse;Zuerich",
    "iso:country":"CH",
    "sg:address":"Brunnenwiesenstrasse 10",
    "sg:city":"D\u00e4llikon",
    "sg:orig_category":"Assembling, Disassembling",
    "sg:phone":"+41 18497070",
    "sg:postcode":"8108",
    "sg:province":"Z\u00fcrich",
    "wof:name":"Holder Huber Ag",
    "wof:placetype":"venue"
},
  "geometry": {"coordinates":[8.441121,47.44305],"type":"Point"}
}