{
  "type": "Feature",
  "properties": {
    "iso:country":"CH",
    "sg:address":"Obermattenstrasse 15",
    "sg:city":"K\u00f6lliken",
    "sg:orig_category":"Instandhaltung U Reparatur von Automobilen",
    "sg:postcode":"5742",
    "sg:province":"Aargau",
    "wof:name":"Garage Raja Krist",
    "wof:placetype":"venue"
},
  "geometry": {"coordinates":[8.0147819519,47.3229255676],"type":"Point"}
}