{
  "type": "Feature",
  "properties": {
    "iso:country":"CH",
    "sg:address":"Fehlhalde",
    "sg:city":"Eschenz",
    "sg:orig_category":"Vereine Gesang",
    "sg:phone":"+41 52 741 15 81",
    "sg:postcode":"8264",
    "sg:province":"Thurgau",
    "wof:name":"M\u00e4nnerchor Eschenz",
    "wof:placetype":"venue"
},
  "geometry": {"coordinates":[8.870051384,47.6487541199],"type":"Point"}
}