{
  "type": "Feature",
  "properties": {
    "iso:country":"CH",
    "sg:address":"B\u00f6sch 65 6331 H\u00fcnenberg. Postfach",
    "sg:city":"H\u00fcnenberg",
    "sg:orig_category":"Sonstige mit der Informatik verbundene T\u00e4tigkeiten",
    "sg:postcode":"6331",
    "sg:province":"Zug",
    "wof:name":"Stc Informatik Steiner Dominik Informatik-dienstleistungen",
    "wof:placetype":"venue"
},
  "geometry": {"coordinates":[8.4385118484,47.1624031067],"type":"Point"}
}