{
  "type": "Feature",
  "properties": {
    "iso:country":"CH",
    "sg:address":"Bernstrasse 6",
    "sg:city":"Thun",
    "sg:orig_category":"Arztpraxen",
    "sg:phone":"+41 55 442 34 24",
    "sg:postcode":"3600",
    "sg:province":"Bern",
    "wof:name":"Dr.med.richard Schibli Spezialarzt Fmh",
    "wof:placetype":"venue"
},
  "geometry": {"coordinates":[8.859257,47.195488],"type":"Point"}
}