{
  "type": "Feature",
  "properties": {
    "iso:country":"CH",
    "sg:address":"Contrada Di Sassello 5 6900 Lugano. Postfach",
    "sg:city":"Lugano",
    "sg:orig_category":"Reiseb\u00fcros",
    "sg:phone":"+41 79 221 62 93",
    "sg:postcode":"6901",
    "sg:province":"Ticino",
    "wof:name":"Kuoni Viaggi Sa",
    "wof:placetype":"venue"
},
  "geometry": {"coordinates":[8.9498071671,46.0033798218],"type":"Point"}
}