{
  "type": "Feature",
  "properties": {
    "iso:country":"CH",
    "sg:address":"Rosenweg 9",
    "sg:city":"Unterkulm",
    "sg:orig_category":"Wirtschaftspr\u00fcfung, Steuerberatung U Treuhand",
    "sg:phone":"+41 62 776 11 46",
    "sg:postcode":"5726",
    "sg:province":"Aargau",
    "wof:name":"Tc Treuhand & Consulting Ag",
    "wof:placetype":"venue"
},
  "geometry": {"coordinates":[8.1170663834,47.3094863892],"type":"Point"}
}