{
  "type": "Feature",
  "properties": {
    "iso:country":"CH",
    "sg:address":"Schillerstrasse 6",
    "sg:city":"St.gallen",
    "sg:orig_category":"Herstellung von W\u00e4sche",
    "sg:phone":"+41 71 278 33 39",
    "sg:postcode":"9000",
    "sg:province":"St. Gallen",
    "wof:name":"Gallus Kinderbekleidung Ag",
    "wof:placetype":"venue"
},
  "geometry": {"coordinates":[9.3573303223,47.4177703857],"type":"Point"}
}