{
  "type": "Feature",
  "properties": {
    "iso:country":"CH",
    "sg:address":"Po Box 2923",
    "sg:city":"Geneva",
    "sg:classifiers":[
        {
            "category":"Banks & Credit Unions",
            "subcategory":"Bank",
            "type":"Services"
        }
    ],
    "sg:postcode":"1211",
    "sg:province":"Gen\u00e8ve",
    "wof:name":"Sgk Management Ag",
    "wof:placetype":"venue"
},
  "geometry": {"coordinates":[8.53955,47.37706],"type":"Point"}
}