{
  "type": "Feature",
  "properties": {
    "iso:country":"CH",
    "sg:address":"Schweizergasse 21 8001 Z\u00fcrich. Postfach",
    "sg:city":"Z\u00fcrich",
    "sg:orig_category":"Grosshandel mit Fleisch U Fleischwaren Grosshandel mit Wein U Spirituosen",
    "sg:phone":"+41 12115720",
    "sg:postcode":"8023",
    "sg:province":"Z\u00fcrich",
    "wof:name":"Bonizzi Alberto Ag Lebensmittel; Imp., Exp. Handel Usw",
    "wof:placetype":"venue"
},
  "geometry": {"coordinates":[8.5370893478,47.3761863708],"type":"Point"}
}