{
  "type": "Feature",
  "properties": {
    "iso:country":"CH",
    "sg:address":"Gyrenstrasse 25",
    "sg:city":"Widen",
    "sg:orig_category":"Architektur U Ingenieurb\u00fcros",
    "sg:phone":"+41 56 633 89 04",
    "sg:postcode":"8967",
    "sg:province":"Aargau",
    "wof:name":"R. Iten",
    "wof:placetype":"venue"
},
  "geometry": {"coordinates":[8.354034,47.367851],"type":"Point"}
}