{
  "type": "Feature",
  "properties": {
    "iso:country":"CH",
    "sg:address":"Gotthardstrasse 81",
    "sg:city":"Weggis",
    "sg:orig_category":"Konkurs- and Betreibungs\u00e4mter",
    "sg:phone":"+41 41 390 16 22",
    "sg:postcode":"6353",
    "sg:province":"Luzern",
    "wof:name":"Betreibungsamt",
    "wof:placetype":"venue"
},
  "geometry": {"coordinates":[8.4445543289,47.0305290222],"type":"Point"}
}