{
  "type": "Feature",
  "properties": {
    "iso:country":"CH",
    "sg:address":"8302",
    "sg:city":"Kloten",
    "sg:orig_category":"Vereine Gesang",
    "sg:phone":"+41 18043040",
    "sg:postcode":"8302",
    "sg:province":"Z\u00fcrich",
    "wof:name":"M\u00e4nnerchor Kloten",
    "wof:placetype":"venue"
},
  "geometry": {"coordinates":[8.5806808472,47.4521408081],"type":"Point"}
}