{
  "type": "Feature",
  "properties": {
    "iso:country":"CH",
    "sg:address":"Via Rodari 16",
    "sg:city":"Lugano",
    "sg:orig_category":"Datenverarbeitungsdienste Softwareentwicklung U beratung",
    "sg:phone":"+41 21 691 47 56",
    "sg:postcode":"6900",
    "sg:province":"Ticino",
    "wof:name":"Teleinvest Sa",
    "wof:placetype":"venue"
},
  "geometry": {"coordinates":[6.55915,46.512447],"type":"Point"}
}