{
  "type": "Feature",
  "properties": {
    "iso:country":"CH",
    "sg:address":"Hardturmstrasse 120",
    "sg:city":"Z\u00fcrich",
    "sg:orig_category":"Grosshandel mit B\u00fcromaschinen Grosshandel mit Datenverarbeitungsger\u00e4ten",
    "sg:phone":"+41 12784730",
    "sg:postcode":"8005",
    "sg:province":"Z\u00fcrich",
    "wof:name":"Common Switzerland Ibm Users Association",
    "wof:placetype":"venue"
},
  "geometry": {"coordinates":[8.5154333115,47.3932113647],"type":"Point"}
}