{
  "type": "Feature",
  "properties": {
    "iso:country":"CH",
    "sg:address":"2053",
    "sg:city":"Cernier",
    "sg:orig_category":"Bezirks, Sekundar, Realschulen, Oberstufe der Primarschulen",
    "sg:postcode":"2053",
    "sg:province":"Neuch\u00e2tel",
    "wof:name":"Ecole Secondaire Coll\u00e8ge De La Fontenelle",
    "wof:placetype":"venue"
},
  "geometry": {"coordinates":[6.90526,47.057339],"type":"Point"}
}