{
  "type": "Feature",
  "properties": {
    "iso:country":"CH",
    "sg:address":"Rue De La Dixence 8",
    "sg:city":"Sion",
    "sg:orig_category":"Arztpraxen",
    "sg:phone":"+41 32 913 04 33",
    "sg:postcode":"1950",
    "sg:province":"Valais",
    "wof:name":"Dr M\u00e9d. Freddy C\u00e9spedes M\u00e9decin Sp\u00e9cialiste Fmh",
    "wof:placetype":"venue"
},
  "geometry": {"coordinates":[6.819039,47.096584],"type":"Point"}
}