{
  "type": "Feature",
  "properties": {
    "iso:country":"CH",
    "sg:address":"Murtenstrasse 123 3008 Bern. Postfach 6962",
    "sg:city":"Bern",
    "sg:orig_category":"Benzin, Heiz\u00f6l and Mineral\u00f6lprodukte Grosshandel Detailhandel mit Brennstoffen U Heizmaterial",
    "sg:phone":"+41 31 384 84 84",
    "sg:postcode":"3001",
    "sg:province":"Bern",
    "wof:name":"Flamol Mineral\u00f6l Ag",
    "wof:placetype":"venue"
},
  "geometry": {"coordinates":[7.411885,46.949802],"type":"Point"}
}