{
  "type": "Feature",
  "properties": {
    "iso:country":"CH",
    "sg:address":"St. Antonsgasse 4a",
    "sg:city":"Zug",
    "sg:orig_category":"Wirtschaftspr\u00fcfung, Steuerberatung U Treuhand",
    "sg:phone":"+41 41 711 55 21",
    "sg:postcode":"6300",
    "sg:province":"Zug",
    "wof:name":"Fidinam (trustees) Ag",
    "wof:placetype":"venue"
},
  "geometry": {"coordinates":[8.5165901184,47.1672706604],"type":"Point"}
}