{
  "type": "Feature",
  "properties": {
    "iso:country":"CH",
    "sg:address":"Unterdorf 1",
    "sg:city":"Sch\u00fcpfheim",
    "sg:orig_category":"Blumen U Zierpflanzenbau Detailhandel mit Blumen U Pflanzen",
    "sg:phone":"+41 41 484 21 40",
    "sg:postcode":"6170",
    "sg:province":"Luzern",
    "wof:name":"Ulrich Finsterwald",
    "wof:placetype":"venue"
},
  "geometry": {"coordinates":[8.018578,46.953983],"type":"Point"}
}