{
  "type": "Feature",
  "properties": {
    "iso:country":"CH",
    "sg:address":"Rue De Rive 38",
    "sg:city":"Nyon",
    "sg:orig_category":"Detailhandel mit Waren verschiedener Art, Hauptrichtung Nahrungsmittel Sonstiger Fachdetailhandel mi",
    "sg:phone":"+41 22 361 21 15",
    "sg:postcode":"1260",
    "sg:province":"Vaud",
    "wof:name":"Hardy G\u00e9rard, Au Plateau De Fromages & Laiterie De Rive",
    "wof:placetype":"venue"
},
  "geometry": {"coordinates":[6.2427539825,46.3824615479],"type":"Point"}
}