{
  "type": "Feature",
  "properties": {
    "iso:country":"CH",
    "sg:address":"8506",
    "sg:city":"Lanzenneunforn",
    "sg:orig_category":"Primarschulen",
    "sg:phone":"+41 52 747 14 54",
    "sg:postcode":"8506",
    "sg:province":"Thurgau",
    "wof:name":"Primarschule",
    "wof:placetype":"venue"
},
  "geometry": {"coordinates":[8.938949585,47.6226005554],"type":"Point"}
}