{
  "type": "Feature",
  "properties": {
    "iso:country":"CH",
    "sg:address":"Fortunagasse 11",
    "sg:city":"Z\u00fcrich",
    "sg:orig_category":"Grosshandel mit sonstigen Gebrauchs U Verbrauchsg\u00fctern Herstellung von sonstigen Erzeugnissen",
    "sg:phone":"+41 12211085",
    "sg:postcode":"8001",
    "sg:province":"Z\u00fcrich",
    "wof:name":"Flor & Decor, R. Thomann",
    "wof:placetype":"venue"
},
  "geometry": {"coordinates":[8.5399188995,47.3730735779],"type":"Point"}
}