{
  "type": "Feature",
  "properties": {
    "iso:country":"CH",
    "sg:address":"Rainacher 198",
    "sg:city":"Fr\u00e4schels",
    "sg:orig_category":"Museen",
    "sg:postcode":"3284",
    "sg:province":"Fribourg",
    "wof:name":"Hurn M. Et Mme.",
    "wof:placetype":"venue"
},
  "geometry": {"coordinates":[6.82873106,46.5241355896],"type":"Point"}
}