{
  "type": "Feature",
  "properties": {
    "iso:country":"CH",
    "sg:address":"Ziegelried 374",
    "sg:city":"Sch\u00fcpfen",
    "sg:orig_category":"Forschung U Entwicklung im Bereich der Naturwissenschaften",
    "sg:phone":"+41 31 879 26 41",
    "sg:postcode":"3054",
    "sg:province":"Bern",
    "wof:name":"Wildvet Projects Giacometti",
    "wof:placetype":"venue"
},
  "geometry": {"coordinates":[7.3684420586,47.0403633118],"type":"Point"}
}