{
  "type": "Feature",
  "properties": {
    "iso:country":"CH",
    "sg:address":"Wunderklingen 472",
    "sg:city":"Hallau",
    "sg:orig_category":"S\u00e4gewerke",
    "sg:phone":"+41 31 701 06 14",
    "sg:postcode":"8215",
    "sg:province":"Schaffhausen",
    "wof:name":"Peter Z\u00fcrcher S\u00e4gerei",
    "wof:placetype":"venue"
},
  "geometry": {"coordinates":[7.647110939,46.9343948364],"type":"Point"}
}