{
  "type": "Feature",
  "properties": {
    "iso:country":"CH",
    "sg:address":"3928",
    "sg:city":"Randa",
    "sg:orig_category":"Maler U Glasergewerbe",
    "sg:phone":"+41 27 967 56 73",
    "sg:postcode":"3928",
    "sg:province":"Valais",
    "wof:name":"Malergesch\u00e4ft Summermatter Renato",
    "wof:placetype":"venue"
},
  "geometry": {"coordinates":[7.7803549767,46.0985984802],"type":"Point"}
}