{
  "type": "Feature",
  "properties": {
    "iso:country":"CH",
    "sg:address":"Edelweiss",
    "sg:city":"Luthern",
    "sg:orig_category":"Bauspenglerei Dachdeckerei",
    "sg:phone":"+41 41 978 13 44",
    "sg:postcode":"6156",
    "sg:province":"Luzern",
    "wof:name":"Franz Christen Dachdeckergesch\u00e4ft Spenglerei",
    "wof:placetype":"venue"
},
  "geometry": {"coordinates":[7.90804,47.058319],"type":"Point"}
}