{
  "type": "Feature",
  "properties": {
    "iso:country":"CH",
    "sg:address":"Riedtlistrasse 1 8000 Z\u00fcrich. Postfach",
    "sg:city":"Z\u00fcrich",
    "sg:orig_category":"Non-Classified Establishments",
    "sg:postcode":"8001",
    "sg:province":"Z\u00fcrich",
    "wof:name":"Zentner J.",
    "wof:placetype":"venue"
},
  "geometry": {"coordinates":[8.5400381088,47.390499115],"type":"Point"}
}