{
  "type": "Feature",
  "properties": {
    "iso:country":"CH",
    "sg:address":"Aadorferstrasse 16",
    "sg:city":"Matzingen",
    "sg:classifiers":[
        {
            "category":"Government",
            "subcategory":"Post Office",
            "type":"Public Place"
        }
    ],
    "sg:phone":"+41 52 369 67 67",
    "sg:postcode":"9548",
    "sg:province":"Thurgau",
    "sg:tags":[
        "heater",
        "electric",
        "space"
    ],
    "wof:name":"Heim Elektroheizungen Gmbh",
    "wof:placetype":"venue"
},
  "geometry": {"coordinates":[8.9298439026,47.5197753906],"type":"Point"}
}