{
  "type": "Feature",
  "properties": {
    "iso:country":"CH",
    "sg:address":"Vordere Hauptgasse 10",
    "sg:city":"Zofingen",
    "sg:orig_category":"Detailhandel mit Damenbekleidung",
    "sg:phone":"+41 62 751 59 22",
    "sg:postcode":"4800",
    "sg:province":"Aargau",
    "wof:name":"Blackout Ag",
    "wof:placetype":"venue"
},
  "geometry": {"coordinates":[7.944,47.290218],"type":"Point"}
}