{
  "type": "Feature",
  "properties": {
    "iso:country":"CH",
    "sg:address":"Witellikerstrasse 50",
    "sg:city":"Zollikon",
    "sg:orig_category":"Unternehmensberatung",
    "sg:phone":"+41 13917232",
    "sg:postcode":"8702",
    "sg:province":"Z\u00fcrich",
    "wof:name":"Lundberg F. Management Ag",
    "wof:placetype":"venue"
},
  "geometry": {"coordinates":[8.5817747116,47.3444328308],"type":"Point"}
}