{
  "type": "Feature",
  "properties": {
    "iso:country":"CH",
    "sg:address":"Schaubhus 11",
    "sg:city":"Emmenbr\u00fccke",
    "sg:orig_category":"Sportvereine Turnen Vereine Damen",
    "sg:phone":"+41 71 477 21 82",
    "sg:postcode":"6020",
    "sg:province":"Luzern",
    "wof:name":"Damenturnverein Neukirch",
    "wof:placetype":"venue"
},
  "geometry": {"coordinates":[9.3692731857,47.5288887024],"type":"Point"}
}