{
  "type": "Feature",
  "properties": {
    "iso:country":"CH",
    "sg:address":"Corso San Gottardo 103",
    "sg:city":"Chiasso",
    "sg:orig_category":"RESTAURANTS: TEA-ROOMS",
    "sg:postcode":"6830",
    "sg:province":"Ticino",
    "wof:name":"Lembo Anna Maria",
    "wof:placetype":"venue"
},
  "geometry": {"coordinates":[9.0244731903,45.8366851807],"type":"Point"}
}