{
  "type": "Feature",
  "properties": {
    "iso:country":"CH",
    "sg:address":"Hauptstrasse 15",
    "sg:city":"Weesen",
    "sg:orig_category":"Nationale Postdienste",
    "sg:phone":"+41 55 616 11 05",
    "sg:postcode":"8872",
    "sg:province":"St. Gallen",
    "wof:name":"Die Schweizerische Post",
    "wof:placetype":"venue"
},
  "geometry": {"coordinates":[9.0969467163,47.1344566345],"type":"Point"}
}