{
  "type": "Feature",
  "properties": {
    "addr:full":"Vall\u00e9e Vals Graubunden 7132",
    "addr:postcode":"7132",
    "addr:street":"Valle\u0301E;Graubunden",
    "iso:country":"CH",
    "sg:address":"Vall\u00e9e",
    "sg:city":"Vals",
    "sg:orig_category":"Allgemeiner Hoch U Tiefbau Hoch U Tiefbau",
    "sg:phone":"+41 81 925 22 72",
    "sg:postcode":"7132",
    "sg:province":"Graubunden",
    "wof:name":"Schmid Richard Ag",
    "wof:placetype":"venue"
},
  "geometry": {"coordinates":[9.180222,46.617252],"type":"Point"}
}