{
  "type": "Feature",
  "properties": {
    "iso:country":"CH",
    "sg:address":"Les Brits Syens",
    "sg:city":"Moudon",
    "sg:orig_category":"Malerei Stukkateurgewerbe, Gipserei U Verputzerei",
    "sg:phone":"+41 21 905 66 34",
    "sg:postcode":"1510",
    "sg:province":"Vaud",
    "wof:name":"Paul Galifier Entreprise De Peinture",
    "wof:placetype":"venue"
},
  "geometry": {"coordinates":[6.8003668785,46.6674957275],"type":"Point"}
}