{
  "type": "Feature",
  "properties": {
    "iso:country":"CH",
    "sg:address":"Talackerstrasse 17 8152 Glattbrugg. Postfach",
    "sg:city":"Z\u00fcrich",
    "sg:orig_category":"Grosshandel mit Textilien Grosshandel mit sonstigen Konsumg\u00fctern",
    "sg:phone":"+41 56 493 02 88",
    "sg:postcode":"8065",
    "sg:province":"Z\u00fcrich",
    "wof:name":"Sosta Gmbh",
    "wof:placetype":"venue"
},
  "geometry": {"coordinates":[8.4143533707,47.3648796082],"type":"Point"}
}