{
  "type": "Feature",
  "properties": {
    "iso:country":"CH",
    "sg:address":"Bundtstrasse 8",
    "sg:city":"Forch",
    "sg:orig_category":"Betrieb von Taxis",
    "sg:postcode":"8127",
    "sg:province":"Z\u00fcrich",
    "wof:name":"Gees E. Dienstleistungen & Transporte Aller Art Personentransporte, Dienstleistungen Im Transportgewerbe",
    "wof:placetype":"venue"
},
  "geometry": {"coordinates":[8.773604,47.198448],"type":"Point"}
}