{
  "type": "Feature",
  "properties": {
    "iso:country":"CH",
    "sg:address":"Seestrasse 89",
    "sg:city":"M\u00e4nnedorf",
    "sg:orig_category":"Sonstige pers\u00f6nliche Dienstleistungen",
    "sg:phone":"+41 19200096",
    "sg:postcode":"8708",
    "sg:province":"Z\u00fcrich",
    "wof:name":"Success Sa",
    "wof:placetype":"venue"
},
  "geometry": {"coordinates":[8.6837787628,47.2568092346],"type":"Point"}
}