{
  "type": "Feature",
  "properties": {
    "iso:country":"CH",
    "sg:address":"Murackerstrasse 6",
    "sg:city":"Lenzburg",
    "sg:orig_category":"Versicherungen Generalagenturen",
    "sg:phone":"+41 31 747 27 27",
    "sg:postcode":"5600",
    "sg:province":"Aargau",
    "wof:name":"Die Mobiliar Versicherungen & Vorsorge",
    "wof:placetype":"venue"
},
  "geometry": {"coordinates":[7.2380309105,46.9036941528],"type":"Point"}
}