{
  "type": "Feature",
  "properties": {
    "iso:country":"CH",
    "sg:address":"Frutigenstrasse 25",
    "sg:city":"Thun",
    "sg:orig_category":"Vermietung U Verpachtung von eigenen Immobilien",
    "sg:postcode":"3600",
    "sg:province":"Bern",
    "wof:name":"Matter Fritz Immobilien Ag",
    "wof:placetype":"venue"
},
  "geometry": {"coordinates":[8.4485788345,47.2728118896],"type":"Point"}
}