{
  "type": "Feature",
  "properties": {
    "iso:country":"CH",
    "sg:address":"Rebhaldenweg 2",
    "sg:city":"Ennetbaden",
    "sg:orig_category":"Non-Classified Establishments",
    "sg:postcode":"5408",
    "sg:province":"Aargau",
    "wof:name":"L. H. C. Consulting Lulay",
    "wof:placetype":"venue"
},
  "geometry": {"coordinates":[8.320848465,47.4821472168],"type":"Point"}
}