{
  "type": "Feature",
  "properties": {
    "iso:country":"CH",
    "sg:address":"La Poussaz",
    "sg:city":"Moudon",
    "sg:orig_category":"Blumen U Zierpflanzenbau",
    "sg:phone":"+41 21 905 37 87",
    "sg:postcode":"1510",
    "sg:province":"Vaud",
    "wof:name":"Butty Jardins S\u00e0rl Am\u00e9nagement Et Entretien De Jardins Etc",
    "wof:placetype":"venue"
},
  "geometry": {"coordinates":[6.792474,46.657475],"type":"Point"}
}