{
  "type": "Feature",
  "properties": {
    "iso:country":"CH",
    "sg:address":"Peney Route De 133 1242 Satigny. Postfach",
    "sg:city":"Satigny",
    "sg:orig_category":"Herstellung von sonstigen Fahrzeugen",
    "sg:phone":"+41 22 341 08 74",
    "sg:postcode":"1242",
    "sg:province":"Gen\u00e8ve",
    "wof:name":"Autos & Energies S\u00e0rl R\u00e9paration Dans Le Dom. De L'\u00e9lectricit\u00e9, L'\u00e9lectronique Automobile Etc",
    "wof:placetype":"venue"
},
  "geometry": {"coordinates":[6.0330247879,46.2154884338],"type":"Point"}
}