{
  "type": "Feature",
  "properties": {
    "iso:country":"CH",
    "sg:address":"Waldst\u00e4tterstrasse 12",
    "sg:city":"Luzern",
    "sg:orig_category":"Architekturb\u00fcros",
    "sg:phone":"+41 27 322 53 06",
    "sg:postcode":"6003",
    "sg:province":"Luzern",
    "wof:name":"Beat Plattner Sa Bureau D'architecture",
    "wof:placetype":"venue"
},
  "geometry": {"coordinates":[7.361331,46.234535],"type":"Point"}
}