{
  "type": "Feature",
  "properties": {
    "iso:country":"CH",
    "sg:address":"Chemin Sur-rang 9 Pinchat",
    "sg:city":"Vessy",
    "sg:orig_category":"Unclassifiable Establishments",
    "sg:postcode":"1234",
    "sg:province":"Gen\u00e8ve",
    "wof:name":"Fran\u00e7ois Gisel Naturopathe",
    "wof:placetype":"venue"
},
  "geometry": {"coordinates":[6.1582798958,46.1719741821],"type":"Point"}
}