{
  "type": "Feature",
  "properties": {
    "iso:country":"CH",
    "sg:address":"Zi",
    "sg:city":"St-pierre-de-clages",
    "sg:classifiers":[
        {
            "category":"Home & Garden",
            "subcategory":"Furniture",
            "type":"Retail Goods"
        }
    ],
    "sg:phone":"+41 27 306 31 65",
    "sg:postcode":"1956",
    "sg:tags":[
        "household",
        "wood"
    ],
    "wof:name":"Prodival Sa",
    "wof:placetype":"venue"
},
  "geometry": {"coordinates":[7.2365617752,46.1922073364],"type":"Point"}
}