{
  "type": "Feature",
  "properties": {
    "iso:country":"CH",
    "sg:address":"Alpenblick 5",
    "sg:city":"Cham",
    "sg:orig_category":"Politische Parteien SP",
    "sg:phone":"+41 41 780 45 19",
    "sg:postcode":"6330",
    "sg:province":"Zug",
    "wof:name":"Sps Ortspartei Cham",
    "wof:placetype":"venue"
},
  "geometry": {"coordinates":[8.4740467072,47.183921814],"type":"Point"}
}