{
  "type": "Feature",
  "properties": {
    "iso:country":"CH",
    "sg:address":"Weberm\u00fchle 23",
    "sg:city":"Neuenhof",
    "sg:orig_category":"Detailhandel mit Teppichen",
    "sg:phone":"+41 71 925 26 60",
    "sg:postcode":"5432",
    "sg:province":"Aargau",
    "wof:name":"Peter M. Gm\u00fcr Ag Orientteppiche",
    "wof:placetype":"venue"
},
  "geometry": {"coordinates":[9.0534296036,47.4628791809],"type":"Point"}
}