{
  "type": "Feature",
  "properties": {
    "iso:country":"CH",
    "sg:address":"T\u00e4schmattstrasse 10 6015 Reussb\u00fchl. Postfach",
    "sg:city":"Reussb\u00fchl",
    "sg:orig_category":"Herstellung von k\u00e4lte U lufttechnischen Erzeugnissen f\u00fcr gewerbliche Zwecke",
    "sg:phone":"+41 41 261 05 05",
    "sg:postcode":"6015",
    "sg:province":"Luzern",
    "wof:name":"Lk Luftqualit\u00e4t Ag",
    "wof:placetype":"venue"
},
  "geometry": {"coordinates":[8.2785797119,47.0647850037],"type":"Point"}
}