{
  "type": "Feature",
  "properties": {
    "iso:country":"CH",
    "sg:address":"Samstagernstrasse 44m",
    "sg:city":"Wollerau",
    "sg:orig_category":"Herstellung von k\u00e4lte U lufttechnischen Erzeugnissen f\u00fcr gewerbliche Zwecke Sanit\u00e4r U Heizungsinstal",
    "sg:phone":"+41 17864035",
    "sg:postcode":"8832",
    "sg:province":"Schwyz",
    "wof:name":"Pfiffner Ag",
    "wof:placetype":"venue"
},
  "geometry": {"coordinates":[8.7077064514,47.1902618408],"type":"Point"}
}