{
  "type": "Feature",
  "properties": {
    "iso:country":"CH",
    "sg:address":"1700",
    "sg:city":"Fribourg",
    "sg:classifiers":[
        {
            "category":"Travel",
            "subcategory":"Hotels & Motels",
            "type":"Entertainment"
        }
    ],
    "sg:postcode":"1700",
    "sg:province":"Fribourg",
    "sg:tags":[
        "hotels",
        "mit",
        "restaurant"
    ],
    "wof:name":"Neuhaus Eug\u00e8ne",
    "wof:placetype":"venue"
},
  "geometry": {"coordinates":[7.1746201515,46.8062400818],"type":"Point"}
}