{
  "type": "Feature",
  "properties": {
    "iso:country":"CH",
    "sg:address":"Schlagstrasse 59",
    "sg:city":"Schwyz",
    "sg:orig_category":"Fachdetailhandel in Verkaufsr\u00e4umen",
    "sg:postcode":"6430",
    "sg:province":"Schwyz",
    "wof:name":"Art-in Ag",
    "wof:placetype":"venue"
},
  "geometry": {"coordinates":[8.6456451416,47.4106559753],"type":"Point"}
}