{
  "type": "Feature",
  "properties": {
    "iso:country":"CH",
    "sg:address":"Route De St-cergue 305",
    "sg:city":"Nyon",
    "sg:orig_category":"Grosshandel mit B\u00fcromaschinen Grosshandel mit Datenverarbeitungsger\u00e4ten",
    "sg:phone":"+41 22 365 75 10",
    "sg:postcode":"1260",
    "sg:province":"Vaud",
    "wof:name":"Proactive Partners Ag Informatique",
    "wof:placetype":"venue"
},
  "geometry": {"coordinates":[6.2258281708,46.3964614868],"type":"Point"}
}