{
  "type": "Feature",
  "properties": {
    "iso:country":"CH",
    "sg:address":"Chapelle Rue De La 17",
    "sg:city":"Peseux",
    "sg:orig_category":"Unclassifiable Establishments",
    "sg:postcode":"2034",
    "sg:province":"Neuch\u00e2tel",
    "wof:name":"Biohealth Sa",
    "wof:placetype":"venue"
},
  "geometry": {"coordinates":[6.8898267746,46.9876365662],"type":"Point"}
}