{
  "type": "Feature",
  "properties": {
    "iso:country":"CH",
    "sg:address":"Rue Du Pr\u00e9-du-march\u00e9 34",
    "sg:city":"Lausanne",
    "sg:orig_category":"Detailhandel mit Brot, Back U S\u00fcsswaren",
    "sg:phone":"+41 21 312 55 31",
    "sg:postcode":"1004",
    "sg:province":"Vaud",
    "wof:name":"Genoux R.",
    "wof:placetype":"venue"
},
  "geometry": {"coordinates":[6.630021,46.52409],"type":"Point"}
}