{
  "type": "Feature",
  "properties": {
    "iso:country":"CH",
    "sg:address":"Pl. Bel-air 4 1260 Nyon Case Postale 252",
    "sg:city":"Nyon",
    "sg:orig_category":"Detailhandel mit Spielwaren Fachdetailhandel in Verkaufsr\u00e4umen",
    "sg:phone":"+41 22 361 34 40",
    "sg:postcode":"1260",
    "sg:province":"Vaud",
    "wof:name":"Wagnon Jean-blaise",
    "wof:placetype":"venue"
},
  "geometry": {"coordinates":[6.2385139465,46.3826522827],"type":"Point"}
}