{
  "type": "Feature",
  "properties": {
    "iso:country":"CH",
    "sg:address":"Im Ror 17",
    "sg:city":"Hinwil",
    "sg:orig_category":"Grosshandel mit sonstigen Maschinen U Ausr\u00fcstungen f\u00fcr Industrie, Handel U Schiffahrt",
    "sg:phone":"+41 19374273",
    "sg:postcode":"8340",
    "sg:province":"Z\u00fcrich",
    "wof:name":"Aconsult Ag Industriebedarf",
    "wof:placetype":"venue"
},
  "geometry": {"coordinates":[8.8547019958,47.2864646912],"type":"Point"}
}