{
  "type": "Feature",
  "properties": {
    "iso:country":"CH",
    "sg:address":"1355",
    "sg:city":"Sergey",
    "sg:orig_category":"Gemeindeverwaltungen",
    "sg:phone":"+41 24 441 01 58",
    "sg:postcode":"1355",
    "sg:province":"Vaud",
    "wof:name":"Administration Communale De Sergey",
    "wof:placetype":"venue"
},
  "geometry": {"coordinates":[6.4996700287,46.7504882812],"type":"Point"}
}