{
  "type": "Feature",
  "properties": {
    "iso:country":"CH",
    "sg:address":"Giessh\u00fcbelstrasse 62 8045 Z\u00fcrich. Postfach 646",
    "sg:city":"Z\u00fcrich",
    "sg:orig_category":"G\u00fcterbef\u00f6rderung im Strassenverkehr Lagerung",
    "sg:phone":"+41 14544854",
    "sg:postcode":"8027",
    "sg:province":"Z\u00fcrich",
    "wof:name":"Z\u00fcrcher Lagerhaus Ag",
    "wof:placetype":"venue"
},
  "geometry": {"coordinates":[8.518945694,47.3594932556],"type":"Point"}
}