{
  "type": "Feature",
  "properties": {
    "iso:country":"CH",
    "sg:address":"Praz-de-plan",
    "sg:city":"Ch\u00e2tel-st-denis",
    "sg:orig_category":"Fotografische Ateliers Fotografisches Gewerbe U fotografische Laboratorien",
    "sg:phone":"+41 71 244 74 71",
    "sg:postcode":"1618",
    "sg:province":"Fribourg",
    "wof:name":"Carsten Seltrecht Fotografisches Atelier",
    "wof:placetype":"venue"
},
  "geometry": {"coordinates":[9.3789348602,47.4267272949],"type":"Point"}
}