{
  "type": "Feature",
  "properties": {
    "iso:country":"CH",
    "sg:address":"Petite Corniche 11",
    "sg:city":"Lutry",
    "sg:classifiers":[
        {
            "category":"Banks & Credit Unions",
            "subcategory":"Investment Brokerage",
            "type":"Services"
        }
    ],
    "sg:phone":"+41 21 635 06 12",
    "sg:postcode":"1095",
    "sg:province":"Vaud",
    "sg:tags":[
        "business",
        "advice",
        "appliance",
        "equipment",
        "electrical",
        "electronic",
        "household"
    ],
    "wof:name":"Schick Electronic Sa",
    "wof:placetype":"venue"
},
  "geometry": {"coordinates":[6.586171,46.544666],"type":"Point"}
}