{
  "type": "Feature",
  "properties": {
    "iso:country":"CH",
    "sg:address":"Restelbergstrasse 49",
    "sg:city":"Z\u00fcrich",
    "sg:classifiers":[
        {
            "category":"Professional",
            "subcategory":"Management & Consulting",
            "type":"Services"
        }
    ],
    "sg:phone":"+41 71 228 00 95",
    "sg:postcode":"8044",
    "sg:province":"Z\u00fcrich",
    "sg:tags":[
        "consultancy"
    ],
    "wof:name":"Interpares Gmbh",
    "wof:placetype":"venue"
},
  "geometry": {"coordinates":[9.3625078201,47.4188270569],"type":"Point"}
}