{
  "type": "Feature",
  "properties": {
    "iso:country":"CH",
    "sg:address":"Rue Le-corbusier 14",
    "sg:city":"Gen\u00e8ve",
    "sg:orig_category":"Wirtschaftspr\u00fcfung, Steuerberatung U Treuhand",
    "sg:phone":"+41 22 347 99 67",
    "sg:postcode":"1208",
    "sg:province":"Gen\u00e8ve",
    "wof:name":"Fiduciaire Tardivelle Sa Expertise Fiscale, Contr\u00f4le Et R\u00e9vision De Comptabilit\u00e9s Etc",
    "wof:placetype":"venue"
},
  "geometry": {"coordinates":[6.1681427956,46.194152832],"type":"Point"}
}