{
  "type": "Feature",
  "properties": {
    "iso:country":"CH",
    "sg:address":"Schellenberg 5",
    "sg:city":"Herdern",
    "sg:orig_category":"Unternehmensberatung",
    "sg:phone":"+41 52 747 28 28",
    "sg:postcode":"8535",
    "sg:province":"Thurgau",
    "wof:name":"Felix Wiggli Unternehmensberatung",
    "wof:placetype":"venue"
},
  "geometry": {"coordinates":[8.9080972672,47.60704422],"type":"Point"}
}