{
  "type": "Feature",
  "properties": {
    "iso:country":"CH",
    "sg:address":"R\u00f6merweg 17",
    "sg:city":"Kloten",
    "sg:orig_category":"Reinigungsgewerbe",
    "sg:phone":"+41 79 622 29 64",
    "sg:postcode":"8302",
    "sg:province":"Z\u00fcrich",
    "wof:name":"Cg Nettoyages Di Natale",
    "wof:placetype":"venue"
},
  "geometry": {"coordinates":[6.5615501404,46.5296096802],"type":"Point"}
}