{
  "type": "Feature",
  "properties": {
    "iso:country":"CH",
    "sg:address":"Route De Sion 80",
    "sg:city":"Sierre",
    "sg:orig_category":"Mechanik",
    "sg:phone":"+41 27 455 84 04",
    "sg:postcode":"3960",
    "sg:province":"Valais",
    "wof:name":"Bms, Bulloni M\u00e9canique G\u00e9n\u00e9rale Et Serrurerie",
    "wof:placetype":"venue"
},
  "geometry": {"coordinates":[7.5148029327,46.2841835022],"type":"Point"}
}