{
  "type": "Feature",
  "properties": {
    "iso:country":"CH",
    "sg:address":"Industriestrasse 9",
    "sg:city":"Zug",
    "sg:orig_category":"Betrieb U technische Hilfsdienste des Kultur U Unterhaltungswesens",
    "sg:postcode":"6300",
    "sg:province":"Zug",
    "wof:name":"Habegger Veranstaltungstechnik Ag",
    "wof:placetype":"venue"
},
  "geometry": {"coordinates":[8.517642,47.171043],"type":"Point"}
}