{
  "type": "Feature",
  "properties": {
    "iso:country":"CH",
    "sg:address":"Mattenstrasse 20c 3600 Thun. Postfach",
    "sg:city":"Thun",
    "sg:orig_category":"Grosshandel mit Erzen U Metallen",
    "sg:postcode":"3601",
    "sg:province":"Bern",
    "wof:name":"Hebera.com Gmbh",
    "wof:placetype":"venue"
},
  "geometry": {"coordinates":[8.7577753067,47.2063064575],"type":"Point"}
}