{
  "type": "Feature",
  "properties": {
    "iso:country":"CH",
    "sg:address":"3942 Raron. Postfach 35",
    "sg:city":"Raron",
    "sg:orig_category":"Mechanik Schlossereien",
    "sg:phone":"+41 71 744 24 55",
    "sg:postcode":"3942",
    "sg:province":"Valais",
    "wof:name":"Schlosserei Strub Ag",
    "wof:placetype":"venue"
},
  "geometry": {"coordinates":[9.6351919174,47.4310073853],"type":"Point"}
}