{
  "type": "Feature",
  "properties": {
    "iso:country":"CH",
    "sg:address":"Aeschenplatz 13 4052 Basel. Postfach",
    "sg:city":"Basel",
    "sg:orig_category":"Finanzierungsinstitutionen",
    "sg:phone":"+41 61 277 64 89",
    "sg:postcode":"4052",
    "sg:province":"Basel-Stadt",
    "wof:name":"Pax-anlage Ag Kapitalanlagen, Immobiliengesch\u00e4fte, Finanzdienstleistungen Usw",
    "wof:placetype":"venue"
},
  "geometry": {"coordinates":[7.5955729485,47.5518379211],"type":"Point"}
}