{
  "type": "Feature",
  "properties": {
    "iso:country":"CH",
    "sg:address":"Hatzenb\u00fchlstrasse 56",
    "sg:city":"N\u00fcrensdorf",
    "sg:orig_category":"Herstellung von Metallkonstruktionen",
    "sg:phone":"+41 79 644 96 79",
    "sg:postcode":"8309",
    "sg:province":"Z\u00fcrich",
    "wof:name":"Max Helbling Storen Winterg\u00e4rten",
    "wof:placetype":"venue"
},
  "geometry": {"coordinates":[8.6515760422,47.4517822266],"type":"Point"}
}