{
  "type": "Feature",
  "properties": {
    "iso:country":"CH",
    "sg:address":"Rue De La Manufacture 4 1967 Bramois. Postfach",
    "sg:city":"Bramois",
    "sg:orig_category":"Sonstige pers\u00f6nliche Dienstleistungen",
    "sg:postcode":"1967",
    "sg:province":"Valais",
    "wof:name":"Favre Bruno Propri\u00e9taire-encaveur",
    "wof:placetype":"venue"
},
  "geometry": {"coordinates":[7.4021129608,46.229309082],"type":"Point"}
}