{
  "type": "Feature",
  "properties": {
    "addr:full":"Bahnhofstrasse 18 M\u00fchlethurnen Bern 3127",
    "addr:housenumber":"18",
    "addr:postcode":"3127",
    "addr:street":"Bahnhofstrasse",
    "iso:country":"CH",
    "sg:address":"Bahnhofstrasse 18",
    "sg:city":"M\u00fchlethurnen",
    "sg:orig_category":"Arztpraxen",
    "sg:phone":"+41 31 809 04 88",
    "sg:postcode":"3127",
    "sg:province":"Bern",
    "wof:name":"Dr.med. Daniel Beutler Arzt F.allgemeine Medizin Fmh",
    "wof:placetype":"venue"
},
  "geometry": {"coordinates":[7.510073,46.813416],"type":"Point"}
}