{
  "type": "Feature",
  "properties": {
    "iso:country":"CH",
    "sg:address":"Rue Du March\u00e9 12",
    "sg:city":"Gen\u00e8ve",
    "sg:orig_category":"Detailhandel mit Uhren U Schmuck Grosshandel mit sonstigen Gebrauchs U Verbrauchsg\u00fctern",
    "sg:phone":"+41 22 311 74 58",
    "sg:postcode":"1204",
    "sg:province":"Gen\u00e8ve",
    "wof:name":"Chaya Gil Sa.",
    "wof:placetype":"venue"
},
  "geometry": {"coordinates":[6.1459560394,46.2033348083],"type":"Point"}
}