{
  "type": "Feature",
  "properties": {
    "iso:country":"CH",
    "sg:address":"Engstringerstrasse 5 8952 Schlieren. Postfach",
    "sg:city":"Schlieren",
    "sg:orig_category":"Herstellung von Klebstoffen U Gelatinen",
    "sg:phone":"+41 19200191",
    "sg:postcode":"8952",
    "sg:province":"Z\u00fcrich",
    "wof:name":"Giv Gerling Industrie-vertretungen Gmbh Vertretung Von Industriefirmen. Klebe, Folientechnik; Beratung Usw",
    "wof:placetype":"venue"
},
  "geometry": {"coordinates":[8.6859560013,47.268409729],"type":"Point"}
}