{
  "type": "Feature",
  "properties": {
    "addr:full":"8010 Z\u00fcrich-m\u00fclligen Z\u00fcrich 8010",
    "addr:housenumber":"8010",
    "addr:postcode":"8010",
    "addr:street":"Zuerich-Muelligen Zuerich",
    "iso:country":"CH",
    "sg:address":"8010",
    "sg:city":"Z\u00fcrich-m\u00fclligen",
    "sg:orig_category":"Betrieb U technische Hilfsdienste des Kultur U Unterhaltungswesens",
    "sg:postcode":"8010",
    "sg:province":"Z\u00fcrich",
    "wof:name":"Sm-inter Studio Und Tontechnik Meyer Serge E.h.",
    "wof:placetype":"venue"
},
  "geometry": {"coordinates":[8.53801,47.369091],"type":"Point"}
}