{
  "type": "Feature",
  "properties": {
    "iso:country":"CH",
    "sg:address":"Rufenen",
    "sg:city":"Plaffeien",
    "sg:orig_category":"Kosmetikinstitute",
    "sg:phone":"+41 22 342 16 66",
    "sg:postcode":"1716",
    "sg:province":"Fribourg",
    "wof:name":"Brigitte Galvin Institut De Beaut\u00e9 Amandine",
    "wof:placetype":"venue"
},
  "geometry": {"coordinates":[6.1405658722,46.184879303],"type":"Point"}
}