{
  "type": "Feature",
  "properties": {
    "iso:country":"CH",
    "sg:address":"Rue Du V\u00e9l\u00e9 10",
    "sg:city":"Court",
    "sg:orig_category":"Herstellung von sonstigen landwirtschaftlichen Maschinen",
    "sg:phone":"+41 79 235 90 78",
    "sg:postcode":"2738",
    "sg:province":"Bern",
    "wof:name":"Ross\u00e9 Maurice.",
    "wof:placetype":"venue"
},
  "geometry": {"coordinates":[7.325510025,47.2411804199],"type":"Point"}
}