{
  "type": "Feature",
  "properties": {
    "iso:country":"CH",
    "sg:address":"Wintergasse 12",
    "sg:city":"Basel",
    "sg:orig_category":"Erbringung von Dienstleistungen f\u00fcr Unternehmen",
    "sg:phone":"+41 61 381 98 38",
    "sg:postcode":"4056",
    "sg:province":"Basel-Stadt",
    "wof:name":"Modellshop, M\u00fcller Peter L.",
    "wof:placetype":"venue"
},
  "geometry": {"coordinates":[7.5738530159,47.5646896362],"type":"Point"}
}