{
  "type": "Feature",
  "properties": {
    "iso:country":"CH",
    "sg:address":"Rue Des Rangiers 3",
    "sg:city":"Saignel\u00e9gier",
    "sg:orig_category":"Detailhandel mit Milcherzeugnissen U Eiern Verwertung von Milch",
    "sg:phone":"+41 32 751 21 95",
    "sg:postcode":"2350",
    "sg:province":"Jura",
    "wof:name":"Andr\u00e9 Reuse Laiterie Des Fontaines",
    "wof:placetype":"venue"
},
  "geometry": {"coordinates":[7.0927929878,47.0633888245],"type":"Point"}
}