{
  "type": "Feature",
  "properties": {
    "iso:country":"CH",
    "sg:address":"Nordstrasse 124",
    "sg:city":"Z\u00fcrich",
    "sg:orig_category":"Autogaragen",
    "sg:phone":"+41 13620806",
    "sg:postcode":"8037",
    "sg:province":"Z\u00fcrich",
    "wof:name":"Hansueli Eugster Garage",
    "wof:placetype":"venue"
},
  "geometry": {"coordinates":[8.534376,47.389927],"type":"Point"}
}