{
  "type": "Feature",
  "properties": {
    "iso:country":"CH",
    "sg:address":"Loestrasse 37 7000 Chur. Postfach",
    "sg:city":"Chur",
    "sg:orig_category":"Jugend- and Sport\u00e4mter",
    "sg:phone":"+41 81 257 27 55",
    "sg:postcode":"7001",
    "sg:province":"Graubunden",
    "wof:name":"Kant. Sportamt Graub\u00fcnden",
    "wof:placetype":"venue"
},
  "geometry": {"coordinates":[9.5380430222,46.8547592163],"type":"Point"}
}