{
  "type": "Feature",
  "properties": {
    "addr:full":"Vogesenstrasse 551 Basel Basel-Stadt 4056",
    "addr:housenumber":"551",
    "addr:postcode":"4056",
    "addr:street":"Vogesenstrasse",
    "iso:country":"CH",
    "sg:address":"Vogesenstrasse 551",
    "sg:city":"Basel",
    "sg:classifiers":[
        {
            "category":"Manufacturing",
            "subcategory":"Furniture",
            "type":"Manufacturing & Wholesale Goods"
        }
    ],
    "sg:phone":"+41 61 386 95 55",
    "sg:postcode":"4056",
    "sg:province":"Basel-Stadt",
    "sg:tags":[
        "customized"
    ],
    "wof:name":"Hofstetter Ag",
    "wof:placetype":"venue"
},
  "geometry": {"coordinates":[7.57354,47.570049],"type":"Point"}
}