{
  "type": "Feature",
  "properties": {
    "iso:country":"CH",
    "sg:address":"Pont-butin Route 62 1213 Petit-lancy. Postfach",
    "sg:city":"Lancy",
    "sg:orig_category":"Herstellung von sonstigen Maschinen f\u00fcr unspezifische Verwendung",
    "sg:postcode":"1213",
    "sg:province":"Gen\u00e8ve",
    "wof:name":"Ormond, Titulaire Viola F. Mat\u00e9riel Servant \u00e0 Lutter Contre Le Feu, Notamm. Extincteur Etc.; Import., Export., Vente",
    "wof:placetype":"venue"
},
  "geometry": {"coordinates":[6.1151189804,46.1873168945],"type":"Point"}
}