{
  "type": "Feature",
  "properties": {
    "iso:country":"CH",
    "sg:address":"Rue Du Simplon 28",
    "sg:city":"Martigny",
    "sg:orig_category":"Sonstiges Versicherungsgewerbe",
    "sg:phone":"+41 27 722 34 56",
    "sg:postcode":"1920",
    "sg:province":"Valais",
    "wof:name":"Sayard Francis",
    "wof:placetype":"venue"
},
  "geometry": {"coordinates":[7.0796041489,46.1034812927],"type":"Point"}
}