{
  "type": "Feature",
  "properties": {
    "iso:country":"CH",
    "sg:address":"Dorfstrasse 39",
    "sg:city":"Henggart",
    "sg:orig_category":"Vorschulen, Kinderg\u00e4rten",
    "sg:phone":"+41 52 316 16 48",
    "sg:postcode":"8444",
    "sg:province":"Z\u00fcrich",
    "wof:name":"Kindergarten Altes Schulhaus",
    "wof:placetype":"venue"
},
  "geometry": {"coordinates":[8.6822090149,47.5607223511],"type":"Point"}
}