{
  "type": "Feature",
  "properties": {
    "iso:country":"CH",
    "sg:address":"6780",
    "sg:city":"Airolo",
    "sg:classifiers":[
        {
            "category":"Travel",
            "subcategory":"Hotels & Motels",
            "type":"Entertainment"
        }
    ],
    "sg:postcode":"6780",
    "sg:province":"Ticino",
    "sg:tags":[
        "hotels",
        "mit",
        "restaurant"
    ],
    "wof:name":"Albergo Motta Sa",
    "wof:placetype":"venue"
},
  "geometry": {"coordinates":[8.6094970703,46.5278015137],"type":"Point"}
}