{
  "type": "Feature",
  "properties": {
    "iso:country":"CH",
    "sg:address":"Gare Avenue De La 28",
    "sg:city":"Sion",
    "sg:orig_category":"Gesundheitswesen",
    "sg:postcode":"1950",
    "sg:province":"Valais",
    "wof:name":"Physichem Laboratoire Dr. Groh Margrit",
    "wof:placetype":"venue"
},
  "geometry": {"coordinates":[7.1649050713,46.7464141846],"type":"Point"}
}