{
  "type": "Feature",
  "properties": {
    "addr:full":"Marktgasse 41 Olten Solothurn 4600",
    "addr:housenumber":"41",
    "addr:postcode":"4600",
    "addr:street":"Marktgasse",
    "iso:country":"CH",
    "sg:address":"Marktgasse 41",
    "sg:city":"Olten",
    "sg:orig_category":"Detailhandel mit Beleuchtungs U Haushaltsgegenst\u00e4nden Fachdetailhandel in Verkaufsr\u00e4umen",
    "sg:phone":"+41 32 725 12 14",
    "sg:postcode":"4600",
    "sg:province":"Solothurn",
    "wof:name":"Schinz Sa",
    "wof:placetype":"venue"
},
  "geometry": {"coordinates":[6.930255,46.991573],"type":"Point"}
}