{
  "type": "Feature",
  "properties": {
    "iso:country":"CH",
    "sg:address":"4324",
    "sg:city":"Obermumpf",
    "sg:orig_category":"Primarschulen",
    "sg:phone":"+41 62 873 55 51",
    "sg:postcode":"4324",
    "sg:province":"Aargau",
    "wof:name":"Primarschule Neumatt",
    "wof:placetype":"venue"
},
  "geometry": {"coordinates":[7.9365301132,47.5286712646],"type":"Point"}
}