{
  "type": "Feature",
  "properties": {
    "iso:country":"CH",
    "sg:address":"Lindenhofrain 8 8708 M\u00e4nnedorf. Postfach",
    "sg:city":"M\u00e4nnedorf",
    "sg:orig_category":"Fernmeldedienste",
    "sg:postcode":"8708",
    "sg:province":"Z\u00fcrich",
    "wof:name":"Eco (expert Consultancy Option) Gmbh Beratung Von Fest Und Mobilnetzbetreibern",
    "wof:placetype":"venue"
},
  "geometry": {"coordinates":[8.6824769974,47.2590332031],"type":"Point"}
}