{
  "type": "Feature",
  "properties": {
    "iso:country":"CH",
    "sg:address":"Badenerstrasse 678",
    "sg:city":"Z\u00fcrich",
    "sg:orig_category":"Arztpraxen",
    "sg:phone":"+41 14389090",
    "sg:postcode":"8048",
    "sg:province":"Z\u00fcrich",
    "wof:name":"Dres Med.a. Gadient & S. Basak Spezial\u00e4rzte Fmh",
    "wof:placetype":"venue"
},
  "geometry": {"coordinates":[8.485661,47.388115],"type":"Point"}
}