{
  "type": "Feature",
  "properties": {
    "addr:full":"Bellariastrasse 56 Z\u00fcrich Z\u00fcrich 8038",
    "addr:housenumber":"56",
    "addr:postcode":"8038",
    "addr:street":"Bellariastrasse",
    "iso:country":"CH",
    "sg:address":"Bellariastrasse 56",
    "sg:city":"Z\u00fcrich",
    "sg:orig_category":"Architekturb\u00fcros Innenarchitekturb\u00fcros",
    "sg:phone":"+41 14824344",
    "sg:postcode":"8038",
    "sg:province":"Z\u00fcrich",
    "wof:name":"Bernard San",
    "wof:placetype":"venue"
},
  "geometry": {"coordinates":[8.529295,47.349419],"type":"Point"}
}