{
  "type": "Feature",
  "properties": {
    "iso:country":"CH",
    "sg:address":"Saumweg 6 6370 Stans. Postfach",
    "sg:city":"Stans",
    "sg:orig_category":"Sonstiger spezialisierter Hoch U Tiefbau",
    "sg:phone":"+41 41 610 05 45",
    "sg:postcode":"6370",
    "sg:province":"Nidwalden",
    "wof:name":"Imboden Roland, Kundenmaurer Maurer, Gipser Und Plattenarbeiten, Chemin\u00e9ebau",
    "wof:placetype":"venue"
},
  "geometry": {"coordinates":[8.3658218384,46.9607582092],"type":"Point"}
}