{
  "type": "Feature",
  "properties": {
    "iso:country":"CH",
    "sg:address":"B\u00fctzberg 4922 Thunstetten. Postfach",
    "sg:city":"B\u00fctzberg",
    "sg:orig_category":"Pensionskassen",
    "sg:postcode":"4922",
    "sg:province":"Bern",
    "wof:name":"Personalf\u00fcrsorgestiftung Der Firma Girsberger Ag",
    "wof:placetype":"venue"
},
  "geometry": {"coordinates":[7.7463102341,47.2157897949],"type":"Point"}
}