{
  "type": "Feature",
  "properties": {
    "iso:country":"CH",
    "sg:address":"Hottingerstrasse 27",
    "sg:city":"Z\u00fcrich",
    "sg:orig_category":"RESTAURANTS: TEA-ROOMS",
    "sg:phone":"+41 12524880",
    "sg:postcode":"8032",
    "sg:province":"Z\u00fcrich",
    "wof:name":"Cafeteria Steinwies, Doris Gwerder B\u00fchler",
    "wof:placetype":"venue"
},
  "geometry": {"coordinates":[8.5530004501,47.3698310852],"type":"Point"}
}