{
  "type": "Feature",
  "properties": {
    "iso:country":"CH",
    "sg:address":"Bahnhofstr. 10 8708 M\u00e4nnedorf. Postfach",
    "sg:city":"M\u00e4nnedorf",
    "sg:orig_category":"Wohnheime",
    "sg:postcode":"8708",
    "sg:province":"Z\u00fcrich",
    "wof:name":"Stiftung Alterswohnungen M\u00e4nnedorf",
    "wof:placetype":"venue"
},
  "geometry": {"coordinates":[8.691403389,47.2536315918],"type":"Point"}
}