{
  "type": "Feature",
  "properties": {
    "iso:country":"CH",
    "sg:address":"Stationsstrasse 3",
    "sg:city":"Winterthur",
    "sg:classifiers":[
        {
            "category":"Government",
            "subcategory":"Post Office",
            "type":"Public Place"
        }
    ],
    "sg:phone":"+41 81 858 51 16",
    "sg:postcode":"8406",
    "sg:province":"Z\u00fcrich",
    "sg:tags":[
        "caf\u00e9s",
        "tea-rooms"
    ],
    "wof:name":"Caf\u00e9 Fuschina",
    "wof:placetype":"venue"
},
  "geometry": {"coordinates":[10.423620224,46.6011390686],"type":"Point"}
}