{
  "type": "Feature",
  "properties": {
    "iso:country":"CH",
    "sg:address":"Weinfelderstr. 4 8580 Amriswil. Postfach",
    "sg:city":"Amriswil",
    "sg:orig_category":"Grosshandel mit keramischen Erzeugnissen, Glaswaren U Reinigungsmitteln",
    "sg:phone":"+41 71 411 12 42",
    "sg:postcode":"8580",
    "sg:province":"Thurgau",
    "wof:name":"Tapetenservice Forsthuber Anton",
    "wof:placetype":"venue"
},
  "geometry": {"coordinates":[9.2981262207,47.5452919006],"type":"Point"}
}