{
  "type": "Feature",
  "properties": {
    "addr:full":"Oberdorf 228 Gais Appenzell Ausserrhoden 9056",
    "addr:housenumber":"228",
    "addr:postcode":"9056",
    "addr:street":"Oberdorf;Appenzell Ausserrhoden",
    "iso:country":"CH",
    "sg:address":"Oberdorf 228",
    "sg:city":"Gais",
    "sg:orig_category":"Allgemeiner Hoch U Tiefbau",
    "sg:postcode":"9056",
    "sg:province":"Appenzell Ausserrhoden",
    "wof:name":"Emil H\u00f6rler Ag",
    "wof:placetype":"venue"
},
  "geometry": {"coordinates":[9.45352,47.364079],"type":"Point"}
}