{
  "type": "Feature",
  "properties": {
    "iso:country":"CH",
    "sg:address":"Chemin Du Vuasset 4",
    "sg:city":"Pr\u00e9verenges",
    "sg:orig_category":"Elektroinstallation Fernmeldedienste",
    "sg:phone":"+41 21 804 53 53",
    "sg:postcode":"1028",
    "sg:province":"Vaud",
    "wof:name":"Ip Worldcom",
    "wof:placetype":"venue"
},
  "geometry": {"coordinates":[6.5165891647,46.5187797546],"type":"Point"}
}