{
  "type": "Feature",
  "properties": {
    "iso:country":"CH",
    "sg:address":"Kirchgasse",
    "sg:city":"Saanen",
    "sg:orig_category":"Detailhandel mit Spielwaren Herstellung von Spielwaren",
    "sg:phone":"+41 33 744 41 00",
    "sg:postcode":"3792",
    "sg:province":"Bern",
    "wof:name":"Reparatur-service & Modellbahnen, R. Trachsel",
    "wof:placetype":"venue"
},
  "geometry": {"coordinates":[7.2592830658,46.4906654358],"type":"Point"}
}