{
  "type": "Feature",
  "properties": {
    "iso:country":"CH",
    "sg:address":"1623 Semsales. Postfach 2",
    "sg:city":"Semsales",
    "sg:orig_category":"Sportvereine Ballsport Fussball",
    "sg:phone":"+41 26 918 56 56",
    "sg:postcode":"1623",
    "sg:province":"Fribourg",
    "wof:name":"Fc Semsales",
    "wof:placetype":"venue"
},
  "geometry": {"coordinates":[6.9270949364,46.5727844238],"type":"Point"}
}