{
  "type": "Feature",
  "properties": {
    "iso:country":"CH",
    "sg:address":"Marktgasse 30 4310 Rheinfelden. Postfach",
    "sg:city":"Rheinfelden",
    "sg:orig_category":"Detailhandel mit Geschenkartikeln U Souvenirs Herstellung von sonstigen keramischen Erzeugnissen",
    "sg:phone":"+41 61 831 11 21",
    "sg:postcode":"4310",
    "sg:province":"Aargau",
    "wof:name":"Rh Rheinfelder Keramik Ag",
    "wof:placetype":"venue"
},
  "geometry": {"coordinates":[7.7925992012,47.555316925],"type":"Point"}
}