{
  "type": "Feature",
  "properties": {
    "iso:country":"CH",
    "sg:address":"Albulastrasse 55 8048 Z\u00fcrich. Postfach",
    "sg:city":"Z\u00fcrich",
    "sg:orig_category":"Unclassifiable Establishments",
    "sg:postcode":"8048",
    "sg:province":"Z\u00fcrich",
    "wof:name":"Arifi & Elezi Gartenbau",
    "wof:placetype":"venue"
},
  "geometry": {"coordinates":[8.5917062759,47.303276062],"type":"Point"}
}