{
  "type": "Feature",
  "properties": {
    "addr:full":"Wydackerstrasse 1 Zollikofen Bern 3052",
    "addr:housenumber":"1",
    "addr:postcode":"3052",
    "addr:street":"Wydackerstrasse",
    "iso:country":"CH",
    "sg:address":"Wydackerstrasse 1",
    "sg:city":"Zollikofen",
    "sg:orig_category":"Arztpraxen",
    "sg:phone":"+41 17613262",
    "sg:postcode":"3052",
    "sg:province":"Bern",
    "wof:name":"Dr.med.anton Caprez Arzt F.allgemeine Medizin Fmh",
    "wof:placetype":"venue"
},
  "geometry": {"coordinates":[8.455333,47.27779],"type":"Point"}
}