{
  "type": "Feature",
  "properties": {
    "iso:country":"CH",
    "sg:address":"1813",
    "sg:city":"St-saphorin-lavaux",
    "sg:orig_category":"Autospenglereien",
    "sg:phone":"+41 21 921 70 09",
    "sg:postcode":"1813",
    "wof:name":"Marcel Blanc Carrosserie",
    "wof:placetype":"venue"
},
  "geometry": {"coordinates":[6.795957,46.473301],"type":"Point"}
}