{
  "type": "Feature",
  "properties": {
    "iso:country":"CH",
    "sg:address":"Lindehofweg 1",
    "sg:city":"Marthalen",
    "sg:orig_category":"Sonstiger Grosshandel",
    "sg:phone":"+41 52 319 27 24",
    "sg:postcode":"8460",
    "sg:province":"Z\u00fcrich",
    "wof:name":"Stc Globestore Gmbh",
    "wof:placetype":"venue"
},
  "geometry": {"coordinates":[8.6488208771,47.6233787537],"type":"Point"}
}