{
  "type": "Feature",
  "properties": {
    "addr:full":"Casa Mengoni Magadino Ticino 6573",
    "addr:housenumber":"6573",
    "iso:country":"CH",
    "sg:address":"Casa Mengoni",
    "sg:city":"Magadino",
    "sg:orig_category":"Betrieb von Taxis",
    "sg:postcode":"6573",
    "sg:province":"Ticino",
    "wof:name":"Bonanza Viaggi Sa",
    "wof:placetype":"venue"
},
  "geometry": {"coordinates":[8.85611,46.148571],"type":"Point"}
}