{
  "type": "Feature",
  "properties": {
    "iso:country":"CH",
    "sg:address":"Etterlinstrasse 14",
    "sg:city":"Luzern",
    "sg:orig_category":"Arbeitnehmerverb\u00e4nde",
    "sg:postcode":"6004",
    "sg:province":"Luzern",
    "wof:name":"Verein St\u00e4dtischer Beamter & Angest.,herrn J\u00f6rg Kaufmann",
    "wof:placetype":"venue"
},
  "geometry": {"coordinates":[8.289021,47.056904],"type":"Point"}
}