{
  "type": "Feature",
  "properties": {
    "iso:country":"CH",
    "sg:address":"Avenue De La Harpe 17",
    "sg:city":"Lausanne",
    "sg:orig_category":"Detailhandel mit Waren verschiedener Art, Hauptrichtung Nahrungsmittel",
    "sg:phone":"+41 21 616 31 93",
    "sg:postcode":"1007",
    "sg:province":"Vaud",
    "wof:name":"Migros Harpe",
    "wof:placetype":"venue"
},
  "geometry": {"coordinates":[6.625893116,46.5123405457],"type":"Point"}
}