{
  "type": "Feature",
  "properties": {
    "addr:full":"Kirchstrasse 58 Grenchen Solothurn 2540",
    "addr:housenumber":"58",
    "addr:postcode":"2540",
    "addr:street":"Kirchstrasse",
    "iso:country":"CH",
    "sg:address":"Kirchstrasse 58",
    "sg:city":"Grenchen",
    "sg:orig_category":"Autogaragen",
    "sg:phone":"+41 21 968 22 22",
    "sg:postcode":"2540",
    "sg:province":"Solothurn",
    "wof:name":"J. Heiniger Sa Garage",
    "wof:placetype":"venue"
},
  "geometry": {"coordinates":[6.923517,46.396656],"type":"Point"}
}