{
  "type": "Feature",
  "properties": {
    "iso:country":"CH",
    "sg:address":"Seestrasse 357",
    "sg:city":"Z\u00fcrich",
    "sg:orig_category":"Haltung von Gefl\u00fcgel",
    "sg:postcode":"8038",
    "sg:province":"Z\u00fcrich",
    "wof:name":"Ibahandels Ag",
    "wof:placetype":"venue"
},
  "geometry": {"coordinates":[8.5335197449,47.3455924988],"type":"Point"}
}