{
  "type": "Feature",
  "properties": {
    "iso:country":"CH",
    "sg:address":"Studerswiler Strasse 4a",
    "sg:city":"Kronb\u00fchl",
    "sg:orig_category":"Detailhandel mit Boden U Wandbel\u00e4gen ohne Teppiche Verlegen von Fussboden",
    "sg:phone":"+41 32 351 45 48",
    "sg:postcode":"9302",
    "wof:name":"Daniel B\u00e4hler Laminat-b\u00f6den",
    "wof:placetype":"venue"
},
  "geometry": {"coordinates":[7.40428,47.149673],"type":"Point"}
}