{
  "type": "Feature",
  "properties": {
    "iso:country":"CH",
    "sg:address":"Technikumstrasse 1 8400 Winterthur. Postfach",
    "sg:city":"Winterthur",
    "sg:orig_category":"Organisationen der Wohlfahrtspflege",
    "sg:phone":"+41 52 267 66 10",
    "sg:postcode":"8402",
    "sg:province":"Z\u00fcrich",
    "wof:name":"Winterthurer Fachstelle F\u00fcr Alkoholprobleme Wfa",
    "wof:placetype":"venue"
},
  "geometry": {"coordinates":[8.7324905396,47.4977302551],"type":"Point"}
}