{
  "type": "Feature",
  "properties": {
    "addr:full":"Bodenacker 27 Bolligen Bern 3065",
    "addr:housenumber":"27",
    "addr:postcode":"3065",
    "addr:street":"Bodenacker",
    "iso:country":"CH",
    "sg:address":"Bodenacker 27",
    "sg:city":"Bolligen",
    "sg:orig_category":"Arbeitnehmerverb\u00e4nde",
    "sg:phone":"+41 31 921 56 01",
    "sg:postcode":"3065",
    "sg:province":"Bern",
    "wof:name":"Schweizerischer Arbeits- Lehrerinnen-verein",
    "wof:placetype":"venue"
},
  "geometry": {"coordinates":[7.498608,46.980572],"type":"Point"}
}