{
  "type": "Feature",
  "properties": {
    "addr:full":"Esslingerstrasse 20 M\u00f6nchaltorf Z\u00fcrich 8617",
    "addr:housenumber":"20",
    "addr:postcode":"8617",
    "addr:street":"Esslingerstrasse;Zuerich",
    "iso:country":"CH",
    "sg:address":"Esslingerstrasse 20",
    "sg:city":"M\u00f6nchaltorf",
    "sg:orig_category":"Bauschreinerei Herstellung von M\u00f6beln verschiedener Art",
    "sg:phone":"+41 19480245",
    "sg:postcode":"8617",
    "sg:province":"Z\u00fcrich",
    "wof:name":"Oertli Gebr\u00fcder Ag",
    "wof:placetype":"venue"
},
  "geometry": {"coordinates":[8.720813,47.305996],"type":"Point"}
}