{
  "type": "Feature",
  "properties": {
    "iso:country":"CH",
    "sg:address":"Grindelstrasse 6",
    "sg:city":"Bassersdorf",
    "sg:orig_category":"Grosshandel mit medizinischen U orthop\u00e4dischen Artikeln",
    "sg:phone":"+41 81 771 64 54",
    "sg:postcode":"8303",
    "sg:province":"Z\u00fcrich",
    "wof:name":"Dentatech Handels Ag Dentalhandel",
    "wof:placetype":"venue"
},
  "geometry": {"coordinates":[9.4688119888,47.1664924622],"type":"Point"}
}