{
  "type": "Feature",
  "properties": {
    "iso:country":"CH",
    "sg:address":"Aareweg 5",
    "sg:city":"Bettlach",
    "sg:orig_category":"Herstellung von Radio U Fernsehger\u00e4ten sowie phono U videotechnischen Ger\u00e4ten",
    "sg:phone":"+41 32 653 73 40",
    "sg:postcode":"2544",
    "sg:province":"Solothurn",
    "wof:name":"Immocom Hauskommunikations-systeme Gmbh",
    "wof:placetype":"venue"
},
  "geometry": {"coordinates":[7.427590847,47.1936912537],"type":"Point"}
}