{
  "type": "Feature",
  "properties": {
    "iso:country":"CH",
    "sg:address":"Wohlerstrasse",
    "sg:city":"Waltenschwil",
    "sg:orig_category":"Herstellung von Kakao, Schokoladeerzeugnissen U Zuckerwaren",
    "sg:phone":"+41 56 622 76 88",
    "sg:postcode":"5622",
    "sg:province":"Aargau",
    "wof:name":"Robert Dubler Jun. Autogarage",
    "wof:placetype":"venue"
},
  "geometry": {"coordinates":[8.3002901077,47.3347511292],"type":"Point"}
}