{
  "type": "Feature",
  "properties": {
    "iso:country":"CH",
    "sg:address":"Berninastrasse 11",
    "sg:city":"Z\u00fcrich",
    "sg:orig_category":"Unternehmensberatung",
    "sg:postcode":"8057",
    "sg:province":"Z\u00fcrich",
    "wof:name":"Ts Schnadt Thomas Unternehmensberatung Betriebswirtschaftl. Beratung I. Sachen Qualit\u00e4t, Rationalisierung Usw",
    "wof:placetype":"venue"
},
  "geometry": {"coordinates":[8.5520181656,47.402545929],"type":"Point"}
}