{
  "type": "Feature",
  "properties": {
    "iso:country":"CH",
    "sg:address":"Route D'yverdon 15",
    "sg:city":"Echallens",
    "sg:orig_category":"Architektur U Ingenieurb\u00fcros",
    "sg:phone":"+41 21 648 73 73",
    "sg:postcode":"1040",
    "sg:province":"Vaud",
    "wof:name":"Polyconseils Sa Bureau Technique",
    "wof:placetype":"venue"
},
  "geometry": {"coordinates":[6.621596,46.527393],"type":"Point"}
}