{
  "type": "Feature",
  "properties": {
    "addr:full":"Schulhausstrasse 14 Zollikofen Bern 3052",
    "addr:housenumber":"14",
    "addr:postcode":"3052",
    "addr:street":"Schulhausstrasse",
    "iso:country":"CH",
    "sg:address":"Schulhausstrasse 14",
    "sg:city":"Zollikofen",
    "sg:orig_category":"Bauspenglerei Sanit\u00e4r, Heizungs U L\u00fcftungsinstallation",
    "sg:phone":"+41 31 911 00 88",
    "sg:postcode":"3052",
    "sg:province":"Bern",
    "wof:name":"W. Ruchti & Sohn Inh.r.ruchti San.installationen Spenglerei",
    "wof:placetype":"venue"
},
  "geometry": {"coordinates":[7.45634,46.998074],"type":"Point"}
}