{
  "type": "Feature",
  "properties": {
    "iso:country":"CH",
    "sg:address":"Henauerstrasse 31",
    "sg:city":"Niederuzwil",
    "sg:orig_category":"Detailhandel mit Waren verschiedener Art, Hauptrichtung Nahrungsmittel",
    "sg:phone":"+41 71 951 52 36",
    "sg:postcode":"9244",
    "sg:province":"St. Gallen",
    "wof:name":"Kurt Egger Lebensmittelgesch\u00e4ft",
    "wof:placetype":"venue"
},
  "geometry": {"coordinates":[9.1376209259,47.4459266663],"type":"Point"}
}