{
  "type": "Feature",
  "properties": {
    "addr:full":"Landstrasse 90 3715 Adelboden. Postfach 227 Adelboden Bern 3715",
    "addr:housenumber":"90;227",
    "addr:postcode":"3715 adelboden.;3715",
    "addr:street":"Landstrasse;Postfach",
    "iso:country":"CH",
    "sg:address":"Landstrasse 90 3715 Adelboden. Postfach 227",
    "sg:city":"Adelboden",
    "sg:orig_category":"Autogaragen",
    "sg:phone":"+41 33 673 31 88",
    "sg:postcode":"3715",
    "sg:province":"Bern",
    "wof:name":"Fritz K\u00fcnzi Allround-garage",
    "wof:placetype":"venue"
},
  "geometry": {"coordinates":[7.569046,46.493904],"type":"Point"}
}