{
  "type": "Feature",
  "properties": {
    "iso:country":"CH",
    "sg:address":"3826",
    "sg:city":"Gimmelwald",
    "sg:orig_category":"Non-Classified Establishments",
    "sg:phone":"+41 33 855 17 30",
    "sg:postcode":"3826",
    "sg:province":"Bern",
    "wof:name":"Pension Gimmelwald",
    "wof:placetype":"venue"
},
  "geometry": {"coordinates":[7.8921198845,46.5465888977],"type":"Point"}
}