{
  "type": "Feature",
  "properties": {
    "iso:country":"CH",
    "sg:address":"Grabenackerstrasse 32",
    "sg:city":"Steinhausen",
    "sg:orig_category":"Grosshandel mit pharmazeutischen Erzeugnissen",
    "sg:phone":"+41 41 741 14 76",
    "sg:postcode":"6312",
    "sg:province":"Zug",
    "wof:name":"Ecr Pharma Ag",
    "wof:placetype":"venue"
},
  "geometry": {"coordinates":[8.4804496765,47.2000427246],"type":"Point"}
}