{
  "type": "Feature",
  "properties": {
    "iso:country":"CH",
    "sg:address":"Oberrickenbach",
    "sg:city":"Wolfenschiessen",
    "sg:orig_category":"RESTAURANTS: TEA-ROOMS",
    "sg:phone":"+41 41 628 13 48",
    "sg:postcode":"6386",
    "sg:province":"Nidwalden",
    "wof:name":"Christen Roland",
    "wof:placetype":"venue"
},
  "geometry": {"coordinates":[8.3971099854,46.9084701538],"type":"Point"}
}