{
  "type": "Feature",
  "properties": {
    "iso:country":"CH",
    "sg:address":"Weihermattstrasse 20",
    "sg:city":"Birr",
    "sg:orig_category":"Baugewerbe Herstellung von Metallkonstruktionen",
    "sg:phone":"+41 56 444 86 54",
    "sg:postcode":"5242",
    "sg:province":"Aargau",
    "wof:name":"Schneider + Co",
    "wof:placetype":"venue"
},
  "geometry": {"coordinates":[8.198934,47.433487],"type":"Point"}
}