{
  "type": "Feature",
  "properties": {
    "addr:full":"Schiggstrasse 21 Wangs St. Gallen 7323",
    "addr:housenumber":"21",
    "addr:postcode":"7323",
    "addr:street":"Schiggstrasse",
    "iso:country":"CH",
    "sg:address":"Schiggstrasse 21",
    "sg:city":"Wangs",
    "sg:orig_category":"Aktivit\u00e4ten der Krankenschwestern U Hebammen, Hauspflege Organisationen des Gesundheitswesen",
    "sg:phone":"+41 81 723 49 22",
    "sg:postcode":"7323",
    "sg:province":"St. Gallen",
    "wof:name":"Krankenpflege Vilters-wangs Spitex St\u00fctzpunkt",
    "wof:placetype":"venue"
},
  "geometry": {"coordinates":[9.432825,47.030006],"type":"Point"}
}