{
  "type": "Feature",
  "properties": {
    "iso:country":"CH",
    "sg:address":"Staffelstrasse 3 A",
    "sg:city":"Jegenstorf",
    "sg:orig_category":"Unclassifiable Establishments",
    "sg:postcode":"3303",
    "sg:province":"Bern",
    "wof:name":"Vukadin Transporte",
    "wof:placetype":"venue"
},
  "geometry": {"coordinates":[7.5098829269,47.0527458191],"type":"Point"}
}