{
  "type": "Feature",
  "properties": {
    "iso:country":"CH",
    "sg:address":"Seedorfstrasse 1",
    "sg:city":"Landschlacht",
    "sg:orig_category":"Instandhaltung U Reparatur von Automobilen",
    "sg:postcode":"8597",
    "sg:province":"Thurgau",
    "wof:name":"Garage Viktor Inhaber Viktor Mulaj",
    "wof:placetype":"venue"
},
  "geometry": {"coordinates":[9.2460002899,47.6287689209],"type":"Point"}
}