{
  "type": "Feature",
  "properties": {
    "iso:country":"CH",
    "sg:address":"Frohe Aussicht",
    "sg:city":"H\u00fctten",
    "sg:orig_category":"Zimmerei, Dachdeckerei, Bauspenglerei U Abdichtung",
    "sg:phone":"+41 17881028",
    "sg:postcode":"8825",
    "sg:province":"Z\u00fcrich",
    "wof:name":"Bachmann Und Partner Rolls-rohr, Inh. A. Bachmann",
    "wof:placetype":"venue"
},
  "geometry": {"coordinates":[8.6740980148,47.1783981323],"type":"Point"}
}