{
  "type": "Feature",
  "properties": {
    "iso:country":"CH",
    "sg:address":"Maunoir Rue 5",
    "sg:city":"Gen\u00e8ve",
    "sg:orig_category":"Sonstige Kurierdienste",
    "sg:postcode":"1207",
    "sg:province":"Gen\u00e8ve",
    "wof:name":"Gheldman Herv\u00e9",
    "wof:placetype":"venue"
},
  "geometry": {"coordinates":[6.1599268913,46.2042961121],"type":"Point"}
}