{
  "type": "Feature",
  "properties": {
    "iso:country":"CH",
    "sg:address":"Hauptstrasse 13 1716 Plaffeien. Postfach 2",
    "sg:city":"Plaffeien",
    "sg:orig_category":"Sanit\u00e4r, Heizungs U L\u00fcftungsinstallation Sanit\u00e4rinstallation",
    "sg:phone":"+41 26 419 23 32",
    "sg:postcode":"1716",
    "sg:province":"Fribourg",
    "wof:name":"Hyko Ag",
    "wof:placetype":"venue"
},
  "geometry": {"coordinates":[7.2878818512,46.7411956787],"type":"Point"}
}