{
  "type": "Feature",
  "properties": {
    "iso:country":"CH",
    "sg:address":"Wannefeld 428",
    "sg:city":"Birrwil",
    "sg:orig_category":"Aktivit\u00e4ten der Generalunternehmen im Baugewerbe Allgemeiner Hoch U Tiefbau",
    "sg:phone":"+41 62 772 12 32",
    "sg:postcode":"5708",
    "sg:province":"Aargau",
    "wof:name":"Wilfried Merz Immobilien & Generaluntern.",
    "wof:placetype":"venue"
},
  "geometry": {"coordinates":[8.197252,47.28714],"type":"Point"}
}