{
  "type": "Feature",
  "properties": {
    "iso:country":"CH",
    "sg:address":"Hauptstrasse 11",
    "sg:city":"Tann",
    "sg:orig_category":"Detailhandel mit Textilien Verlegen von Fussboden",
    "sg:phone":"+41 55 240 42 45",
    "sg:postcode":"8632",
    "sg:province":"Z\u00fcrich",
    "wof:name":"Mich\u00e8le M\u00fcller Innendekoration",
    "wof:placetype":"venue"
},
  "geometry": {"coordinates":[8.851436615,47.2614059448],"type":"Point"}
}