{
  "type": "Feature",
  "properties": {
    "iso:country":"CH",
    "sg:address":"Gundeldingerstrasse 197",
    "sg:city":"Basel",
    "sg:orig_category":"Architektur U Ingenieurb\u00fcros Architekturb\u00fcros",
    "sg:phone":"+41 32 968 92 82",
    "sg:postcode":"4053",
    "sg:province":"Basel-Stadt",
    "wof:name":"Gaudenzi Pierre Bureau D'architecture",
    "wof:placetype":"venue"
},
  "geometry": {"coordinates":[6.830802,47.107838],"type":"Point"}
}