{
  "type": "Feature",
  "properties": {
    "iso:country":"CH",
    "sg:address":"Sulzbachstrasse 21a 9400 Rorschach. Postfach",
    "sg:city":"Rorschach",
    "sg:orig_category":"Zahntechnische Laboratorien",
    "sg:phone":"+41 71 855 40 45",
    "sg:postcode":"9401",
    "sg:province":"St. Gallen",
    "wof:name":"Walter Hertach Dental-labor",
    "wof:placetype":"venue"
},
  "geometry": {"coordinates":[9.4952001572,47.4779396057],"type":"Point"}
}