{
  "type": "Feature",
  "properties": {
    "iso:country":"CH",
    "sg:address":"Bensol",
    "sg:city":"Oberegg",
    "sg:orig_category":"Grosshandel mit lebenden Tieren",
    "sg:phone":"+41 71 911 17 38",
    "sg:postcode":"9413",
    "sg:province":"Appenzell Innerhoden",
    "wof:name":"Jakob Notter Schweinehandel",
    "wof:placetype":"venue"
},
  "geometry": {"coordinates":[9.0580759048,47.4678993225],"type":"Point"}
}