{
  "type": "Feature",
  "properties": {
    "iso:country":"CH",
    "sg:address":"Stand Rue Du 3 1204 Gen\u00e8ve. Postfach",
    "sg:city":"Gen\u00e8ve",
    "sg:orig_category":"Interessenvertretungen",
    "sg:postcode":"1204",
    "sg:province":"Gen\u00e8ve",
    "wof:name":"Fondation Did\u00e9 (dignit\u00e9 En D\u00e9tention) Oeuvrer Pour Le Respect De La Dignit\u00e9 De La Personne Priv\u00e9e De Libert\u00e9",
    "wof:placetype":"venue"
},
  "geometry": {"coordinates":[6.1450362206,46.202419281],"type":"Point"}
}