{
  "type": "Feature",
  "properties": {
    "iso:country":"CH",
    "sg:address":"Wurmsbach",
    "sg:city":"Bollingen",
    "sg:orig_category":"Bauschreinerei Herstellung von Konstruktionsteilen, Fertigbauteilen U Ausbauelementen aus Holz",
    "sg:phone":"+41 55 212 22 92",
    "sg:postcode":"8715",
    "sg:province":"St. Gallen",
    "wof:name":"H\u00f6fliger Und Thoma, M\u00f6bel Und Innenausbau",
    "wof:placetype":"venue"
},
  "geometry": {"coordinates":[8.895041,47.219345],"type":"Point"}
}