{
  "type": "Feature",
  "properties": {
    "iso:country":"CH",
    "sg:address":"Place Des Halles 11",
    "sg:city":"Neuch\u00e2tel",
    "sg:classifiers":[
        {
            "category":"Restaurant",
            "type":"Food & Drink"
        }
    ],
    "sg:phone":"+41 71 911 21 66",
    "sg:postcode":"2000",
    "sg:province":"Neuch\u00e2tel",
    "wof:name":"Trattoria Frohburg",
    "wof:placetype":"venue"
},
  "geometry": {"coordinates":[9.0382442474,47.4641571045],"type":"Point"}
}