{
  "type": "Feature",
  "properties": {
    "iso:country":"CH",
    "sg:address":"Gheidgraben 10 4600 Olten. Postfach",
    "sg:city":"Olten",
    "sg:orig_category":"Gewinnung von Kies U Sand",
    "sg:phone":"+41 62 212 13 25",
    "sg:postcode":"4600",
    "sg:province":"Solothurn",
    "wof:name":"Vogt Kies Ag",
    "wof:placetype":"venue"
},
  "geometry": {"coordinates":[7.8922839165,47.3412513733],"type":"Point"}
}