{
  "type": "Feature",
  "properties": {
    "iso:country":"CH",
    "sg:address":"Rue Des Saars 115",
    "sg:city":"Neuch\u00e2tel",
    "sg:orig_category":"Kinesiologie",
    "sg:phone":"+41 32 721 10 67",
    "sg:postcode":"2000",
    "sg:province":"Neuch\u00e2tel",
    "wof:name":"Mierta Chevroulet Centre De Bien-\u00eatre",
    "wof:placetype":"venue"
},
  "geometry": {"coordinates":[6.956348896,47.001285553],"type":"Point"}
}