{
  "type": "Feature",
  "properties": {
    "iso:country":"CH",
    "sg:address":"Route De Malagnou 48",
    "sg:city":"Gen\u00e8ve",
    "sg:orig_category":"Kosmetikinstitute",
    "sg:phone":"+41 22 786 35 34",
    "sg:postcode":"1208",
    "sg:province":"Gen\u00e8ve",
    "wof:name":"Marie-fran\u00e7oise Cadoux Jardin De La Beaut\u00e9",
    "wof:placetype":"venue"
},
  "geometry": {"coordinates":[6.1624879837,46.1967658997],"type":"Point"}
}