{
  "type": "Feature",
  "properties": {
    "iso:country":"CH",
    "sg:address":"Cantonale Via",
    "sg:city":"Vernate",
    "sg:orig_category":"Interessenvertretungen",
    "sg:phone":"+41 91 604 66 42",
    "sg:postcode":"6992",
    "sg:province":"Ticino",
    "wof:name":"Estival Productions Di Andreas Wyden",
    "wof:placetype":"venue"
},
  "geometry": {"coordinates":[8.8846321106,45.9948158264],"type":"Point"}
}