{
  "type": "Feature",
  "properties": {
    "iso:country":"CH",
    "sg:address":"Chemin De Tivoli 6",
    "sg:city":"Petit-lancy",
    "sg:orig_category":"Sanit\u00e4r, Heizungs U L\u00fcftungsinstallation",
    "sg:phone":"+41 79 434 95 93",
    "sg:postcode":"1213",
    "sg:province":"Gen\u00e8ve",
    "wof:name":"A.f. Chauffage S\u00e0rl",
    "wof:placetype":"venue"
},
  "geometry": {"coordinates":[6.1248512268,46.1945762634],"type":"Point"}
}