{
  "type": "Feature",
  "properties": {
    "iso:country":"CH",
    "sg:address":"3983",
    "sg:city":"M\u00f6rel",
    "sg:orig_category":"Handel mit Motorr\u00e4dern, Teilen U Zubeh\u00f6r Instandhaltung U Reparatur von Motorr\u00e4dern",
    "sg:postcode":"3983",
    "sg:province":"Valais",
    "wof:name":"Sch\u00e4rli-sport R.",
    "wof:placetype":"venue"
},
  "geometry": {"coordinates":[7.5895690918,47.4900245667],"type":"Point"}
}