{
  "type": "Feature",
  "properties": {
    "iso:country":"CH",
    "sg:address":"Dorfbachweg 3 5035 Unterentfelden. Postfach 99",
    "sg:city":"Unterentfelden",
    "sg:orig_category":"Herstellung von Hebezeugen U F\u00f6rdermitteln",
    "sg:phone":"+41 62 737 04 04",
    "sg:postcode":"5035",
    "sg:province":"Aargau",
    "wof:name":"Fta Fahrzeugtechnik Ag R\u00e4der Rollen Transportger\u00e4te",
    "wof:placetype":"venue"
},
  "geometry": {"coordinates":[8.0452651978,47.3654670715],"type":"Point"}
}