{
  "type": "Feature",
  "properties": {
    "iso:country":"CH",
    "sg:address":"Boulevard James-fazy 3",
    "sg:city":"Gen\u00e8ve",
    "sg:orig_category":"Fahrschulen, Flugschulen",
    "sg:phone":"+41 71 245 94 25",
    "sg:postcode":"1201",
    "sg:province":"Gen\u00e8ve",
    "wof:name":"Afg Auto-fahrlehrer-gemeinschaft",
    "wof:placetype":"venue"
},
  "geometry": {"coordinates":[9.378950119,47.426448822],"type":"Point"}
}