{
  "type": "Feature",
  "properties": {
    "iso:country":"CH",
    "sg:address":"3962",
    "sg:city":"Montana",
    "sg:orig_category":"Non-Classified Establishments",
    "sg:phone":"+41 27 485 02 00",
    "sg:postcode":"3962",
    "wof:name":"H\u00f4tel Villa Notre Dame Maison De Repos",
    "wof:placetype":"venue"
},
  "geometry": {"coordinates":[-122.67961120610001,45.5516166687],"type":"Point"}
}