{
  "type": "Feature",
  "properties": {
    "iso:country":"CH",
    "sg:address":"Rue D'orbe 77",
    "sg:city":"Yverdon-les-bains",
    "sg:orig_category":"Detailhandel mit Waren verschiedener Art, Hauptrichtung Nahrungsmittel",
    "sg:phone":"+41 24 425 14 24",
    "sg:postcode":"1400",
    "sg:province":"Vaud",
    "wof:name":"Eduardo Prezioso Epicerie-primeurs",
    "wof:placetype":"venue"
},
  "geometry": {"coordinates":[6.6414198875,46.778629303],"type":"Point"}
}