{
  "type": "Feature",
  "properties": {
    "iso:country":"CH",
    "sg:address":"Spitalstrasse 11",
    "sg:city":"Grabs",
    "sg:orig_category":"Wirtschaftspr\u00fcfung, Steuerberatung U Treuhand",
    "sg:phone":"+41 56 622 98 00",
    "sg:postcode":"9472",
    "sg:province":"St. Gallen",
    "wof:name":"Dentakont Ag",
    "wof:placetype":"venue"
},
  "geometry": {"coordinates":[8.2727031708,47.3498497009],"type":"Point"}
}