{
  "type": "Feature",
  "properties": {
    "iso:country":"CH",
    "sg:address":"Poststrase 5",
    "sg:city":"Lenzburg",
    "sg:classifiers":[
        {
            "category":"Professional",
            "subcategory":"Employment Agencies",
            "type":"Services"
        }
    ],
    "sg:postcode":"5600",
    "sg:province":"Aargau",
    "sg:tags":[
        "personal",
        "u",
        "stellenvermittlung"
    ],
    "wof:name":"Dmc-plus Gmbh",
    "wof:placetype":"venue"
},
  "geometry": {"coordinates":[8.1787652969,47.3874588013],"type":"Point"}
}