{
  "type": "Feature",
  "properties": {
    "iso:country":"CH",
    "sg:address":"Melchiorstrasse 23/71 3027 Bern. Postfach",
    "sg:city":"Bern",
    "sg:orig_category":"Interessenvertretungen",
    "sg:postcode":"3018",
    "sg:province":"Bern",
    "wof:name":"Familiengarten-genossenschaft Jorden",
    "wof:placetype":"venue"
},
  "geometry": {"coordinates":[7.3883337975,46.9514541626],"type":"Point"}
}