{
  "type": "Feature",
  "properties": {
    "iso:country":"CH",
    "sg:address":"Avenue De Florimont 1",
    "sg:city":"Lausanne",
    "sg:orig_category":"Interessenvertretungen U sonstige Vereinigungen",
    "sg:phone":"+41 21 343 21 15",
    "sg:postcode":"1006",
    "sg:province":"Vaud",
    "wof:name":"Viscom Direction Suisse Romande",
    "wof:placetype":"venue"
},
  "geometry": {"coordinates":[6.6380681992,46.5164527893],"type":"Point"}
}