{
  "type": "Feature",
  "properties": {
    "iso:country":"CH",
    "sg:address":"Chemin Louis-hubert 2",
    "sg:city":"Grand-lancy",
    "sg:orig_category":"Herstellung von Hebezeugen U F\u00f6rdermitteln",
    "sg:postcode":"1212",
    "sg:province":"Gen\u00e8ve",
    "wof:name":"Otis",
    "wof:placetype":"venue"
},
  "geometry": {"coordinates":[6.1138401031,46.1806945801],"type":"Point"}
}