{
  "type": "Feature",
  "properties": {
    "iso:country":"CH",
    "sg:address":"St. Wolfgangstrasse 30",
    "sg:city":"Triesen",
    "sg:orig_category":"Solarien",
    "sg:phone":"+423 392 16 59",
    "sg:postcode":"9495",
    "wof:name":"Silvia Gerster Solarium Studio Blue Sun",
    "wof:placetype":"venue"
},
  "geometry": {"coordinates":[9.5262269974,47.1190299988],"type":"Point"}
}