{
  "type": "Feature",
  "properties": {
    "iso:country":"CH",
    "sg:address":"Im H\u00f6fli 92",
    "sg:city":"Regensberg",
    "sg:orig_category":"Herstellung von keramischen Wand U Bodenfliesen U platten",
    "sg:phone":"+41 18854050",
    "sg:postcode":"8158",
    "sg:province":"Z\u00fcrich",
    "wof:name":"Keramus Ag",
    "wof:placetype":"venue"
},
  "geometry": {"coordinates":[8.4363718033,47.4825248718],"type":"Point"}
}