{
  "type": "Feature",
  "properties": {
    "addr:full":"Seestrasse 395 8038 Z\u00fcrich. Postfach Z\u00fcrich Z\u00fcrich 8038",
    "addr:housenumber":"395",
    "addr:postcode":"8038 zuerich. postfach;8038",
    "addr:street":"Seestrasse",
    "iso:country":"CH",
    "sg:address":"Seestrasse 395 8038 Z\u00fcrich. Postfach",
    "sg:city":"Z\u00fcrich",
    "sg:orig_category":"Betrieb U technische Hilfsdienste des Kultur U Unterhaltungswesens",
    "sg:phone":"+41 52 762 77 77",
    "sg:postcode":"8038",
    "sg:province":"Z\u00fcrich",
    "wof:name":"Schaffner Freizeit Ag",
    "wof:placetype":"venue"
},
  "geometry": {"coordinates":[8.989792,47.597939],"type":"Point"}
}