{
  "type": "Feature",
  "properties": {
    "iso:country":"CH",
    "sg:address":"Winkfeld 396",
    "sg:city":"Waldstatt",
    "sg:classifiers":[
        {
            "category":"Restaurant",
            "type":"Food & Drink"
        }
    ],
    "sg:phone":"+41 18440540",
    "sg:postcode":"9104",
    "sg:province":"Appenzell Ausserrhoden",
    "wof:name":"Restaurant Frohsinn",
    "wof:placetype":"venue"
},
  "geometry": {"coordinates":[8.439034462,47.4580001831],"type":"Point"}
}