{
  "type": "Feature",
  "properties": {
    "iso:country":"CH",
    "sg:address":"Langacher",
    "sg:city":"Attinghausen",
    "sg:orig_category":"Verwertung von Milch",
    "sg:postcode":"6468",
    "sg:province":"Uri",
    "wof:name":"Milchverwertungsgenossenschaft Attinghausen",
    "wof:placetype":"venue"
},
  "geometry": {"coordinates":[8.6276626587,46.8578643799],"type":"Point"}
}