{
  "type": "Feature",
  "properties": {
    "iso:country":"CH",
    "sg:address":"Im Zwinggarten 12",
    "sg:city":"D\u00fcbendorf",
    "sg:orig_category":"Non-Classified Establishments",
    "sg:postcode":"8600",
    "sg:province":"Z\u00fcrich",
    "wof:name":"Kohnle Sicherheitstechnik",
    "wof:placetype":"venue"
},
  "geometry": {"coordinates":[8.6178340912,47.4031181335],"type":"Point"}
}