{
  "type": "Feature",
  "properties": {
    "iso:country":"CH",
    "sg:address":"Rebbergstrasse 8255 Schlattingen. Postfach",
    "sg:city":"Schlattingen",
    "sg:orig_category":"Erwachsenenbildung U Unterricht",
    "sg:postcode":"8255",
    "sg:province":"Thurgau",
    "wof:name":"Imhof Klaus",
    "wof:placetype":"venue"
},
  "geometry": {"coordinates":[8.7698097229,47.6652259827],"type":"Point"}
}