{
  "type": "Feature",
  "properties": {
    "iso:country":"CH",
    "sg:address":"Chantemerle Chemin De 11 1010 Lausanne. Postfach",
    "sg:city":"Lausanne",
    "sg:orig_category":"Detailhandel mit elektrischen Haushalts-,Radio U Fernsehger\u00e4ten sowie Musikinstrumenten",
    "sg:postcode":"1010",
    "sg:province":"Vaud",
    "wof:name":"Jolis Import, Liskiewicz Jozefa Articles, Notam. Appareils M\u00e9nagers; Comm.",
    "wof:placetype":"venue"
},
  "geometry": {"coordinates":[6.6488418579,46.5352249146],"type":"Point"}
}