{
  "type": "Feature",
  "properties": {
    "iso:country":"CH",
    "sg:address":"Via S. Gottardo 71",
    "sg:city":"Lugano",
    "sg:orig_category":"Grosshandel mit keramischen Erzeugnissen, Glaswaren U Reinigungsmitteln",
    "sg:phone":"+41 91 968 19 75",
    "sg:postcode":"6900",
    "sg:province":"Ticino",
    "wof:name":"Rostami-zarrabi-furutani Parvin",
    "wof:placetype":"venue"
},
  "geometry": {"coordinates":[8.9464731216,46.0083084106],"type":"Point"}
}