{
  "type": "Feature",
  "properties": {
    "iso:country":"CH",
    "sg:address":"Gewerbezone 80",
    "sg:city":"Buttisholz",
    "sg:orig_category":"Rechtsberatung",
    "sg:postcode":"6018",
    "sg:province":"Luzern",
    "wof:name":"Tn-3 Gmbh",
    "wof:placetype":"venue"
},
  "geometry": {"coordinates":[8.0809268951,47.112991333],"type":"Point"}
}