{
  "type": "Feature",
  "properties": {
    "addr:full":"Hauptstrasse 37 Unterkulm Aargau 5726",
    "addr:housenumber":"37",
    "addr:postcode":"5726",
    "addr:street":"Hauptstrasse",
    "iso:country":"CH",
    "sg:address":"Hauptstrasse 37",
    "sg:city":"Unterkulm",
    "sg:orig_category":"Chemische Reinigung",
    "sg:phone":"+41 62 776 30 04",
    "sg:postcode":"5726",
    "sg:province":"Aargau",
    "wof:name":"Sevinc Textilreinigung",
    "wof:placetype":"venue"
},
  "geometry": {"coordinates":[8.113961,47.311684],"type":"Point"}
}