{
  "type": "Feature",
  "properties": {
    "iso:country":"CH",
    "sg:address":"6830",
    "sg:city":"Chiasso",
    "sg:orig_category":"Zoll- and Grenzb\u00fcros",
    "sg:phone":"+41 91 695 55 20",
    "sg:postcode":"6830",
    "sg:province":"Ticino",
    "wof:name":"Dogana Svizzera Chiasso Punto Franco",
    "wof:placetype":"venue"
},
  "geometry": {"coordinates":[9.0249595642,45.8330001831],"type":"Point"}
}