{
  "type": "Feature",
  "properties": {
    "iso:country":"CH",
    "sg:address":"Via Ferri 21",
    "sg:city":"Lugano",
    "sg:orig_category":"Vorschulen, Kinderg\u00e4rten",
    "sg:phone":"+41 91 971 24 31",
    "sg:postcode":"6900",
    "sg:province":"Ticino",
    "wof:name":"Scuola Materna Molino Nuovo I-vi",
    "wof:placetype":"venue"
},
  "geometry": {"coordinates":[8.9587841034,46.0143470764],"type":"Point"}
}