{
  "type": "Feature",
  "properties": {
    "iso:country":"CH",
    "sg:address":"Stadtplatz 1-3 3270 Aarberg. Postfach",
    "sg:city":"Aarberg",
    "sg:orig_category":"Detailhandel mit Beleuchtungs U Haushaltsgegenst\u00e4nden Grosshandel mit Eisenwaren sowie Installations",
    "sg:phone":"+41 32 392 11 24",
    "sg:postcode":"3270",
    "sg:province":"Bern",
    "wof:name":"Adam P. + B.",
    "wof:placetype":"venue"
},
  "geometry": {"coordinates":[7.27667,47.044811],"type":"Point"}
}