{
  "type": "Feature",
  "properties": {
    "iso:country":"CH",
    "sg:address":"Edlischwil",
    "sg:city":"Waldkirch",
    "sg:orig_category":"Herstellung von Konstruktionsteilen, Fertigbauteilen U Ausbauelementen aus Holz Zimmerei, Ingenieurh",
    "sg:phone":"+41 71 433 20 32",
    "sg:postcode":"9205",
    "sg:province":"St. Gallen",
    "wof:name":"Scherrer Gebr. Holzbau Ag",
    "wof:placetype":"venue"
},
  "geometry": {"coordinates":[9.3056201935,47.4738502502],"type":"Point"}
}