{
  "type": "Feature",
  "properties": {
    "iso:country":"CH",
    "sg:address":"Dorfstrasse 9 6340 Baar. Postfach",
    "sg:city":"Baar",
    "sg:orig_category":"Erbringung von Dienstleistungen f\u00fcr Unternehmen",
    "sg:postcode":"6340",
    "sg:province":"Zug",
    "wof:name":"4d Wohnraum Gmbh Dienstleistungen Im Innendekorationsbereich",
    "wof:placetype":"venue"
},
  "geometry": {"coordinates":[8.5256357193,47.1942214966],"type":"Point"}
}