{
  "type": "Feature",
  "properties": {
    "iso:country":"CH",
    "sg:address":"Heinrich Bosshard-strasse 2 8405 Seen. Postfach",
    "sg:city":"Winterthur",
    "sg:orig_category":"Interessenvertretungen",
    "sg:postcode":"8405",
    "sg:province":"Z\u00fcrich",
    "wof:name":"Peru-mission",
    "wof:placetype":"venue"
},
  "geometry": {"coordinates":[8.7559013367,47.4864120483],"type":"Point"}
}