{
  "type": "Feature",
  "properties": {
    "iso:country":"CH",
    "sg:address":"Route De La Piscine 10 1950 Sion Case Postale 1433",
    "sg:city":"Sion",
    "sg:orig_category":"Wirtschaftspr\u00fcfung, Steuerberatung U Treuhand",
    "sg:postcode":"1951",
    "sg:province":"Valais",
    "wof:name":"Soci\u00e9t\u00e9 Fiduciaire Valgestion V & D Sa",
    "wof:placetype":"venue"
},
  "geometry": {"coordinates":[6.5580701828,46.5100784302],"type":"Point"}
}