{
  "type": "Feature",
  "properties": {
    "iso:country":"CH",
    "sg:address":"Oberdorfstrasse 38",
    "sg:city":"Sch\u00fcpfen",
    "sg:orig_category":"Unclassifiable Establishments",
    "sg:phone":"+41 31 879 01 69",
    "sg:postcode":"3054",
    "sg:province":"Bern",
    "wof:name":"Lauclair Ag",
    "wof:placetype":"venue"
},
  "geometry": {"coordinates":[7.376139164,47.0341949463],"type":"Point"}
}