{
  "type": "Feature",
  "properties": {
    "iso:country":"CH",
    "sg:address":"Industriestrasse",
    "sg:city":"Menzingen",
    "sg:orig_category":"Betrieb von Sportanlagen",
    "sg:phone":"+41 41 755 18 33",
    "sg:postcode":"6313",
    "sg:province":"Zug",
    "wof:name":"Teme Tennis Menzingen Ag",
    "wof:placetype":"venue"
},
  "geometry": {"coordinates":[8.601415,47.173435],"type":"Point"}
}