{
  "type": "Feature",
  "properties": {
    "iso:country":"CH",
    "sg:address":"Euelstrasse 21 8408 Winterthur. Postfach",
    "sg:city":"Winterthur",
    "sg:orig_category":"Werbung",
    "sg:phone":"+41 52 223 21 17",
    "sg:postcode":"8408",
    "sg:province":"Z\u00fcrich",
    "wof:name":"Werbung Und Pr Agentur Monje",
    "wof:placetype":"venue"
},
  "geometry": {"coordinates":[8.6825008392,47.5080833435],"type":"Point"}
}