{
  "type": "Feature",
  "properties": {
    "addr:full":"Kirchg\u00e4ssli 14 Rheinfelden Aargau 4310",
    "addr:housenumber":"14",
    "addr:postcode":"4310",
    "addr:street":"Kirchgaessli",
    "iso:country":"CH",
    "sg:address":"Kirchg\u00e4ssli 14",
    "sg:city":"Rheinfelden",
    "sg:orig_category":"Datenverarbeitungsdienste Hardwareberatung",
    "sg:phone":"+41 61 716 96 16",
    "sg:postcode":"4310",
    "sg:province":"Aargau",
    "wof:name":"Initec Ag",
    "wof:placetype":"venue"
},
  "geometry": {"coordinates":[7.600713,47.486187],"type":"Point"}
}