{
  "type": "Feature",
  "properties": {
    "addr:full":"Dohlenzelgstrasse 23 Windisch Aargau 5210",
    "addr:housenumber":"23",
    "addr:postcode":"5210",
    "addr:street":"Dohlenzelgstrasse",
    "iso:country":"CH",
    "sg:address":"Dohlenzelgstrasse 23",
    "sg:city":"Windisch",
    "sg:orig_category":"Arztpraxen",
    "sg:phone":"+41 71 222 96 62",
    "sg:postcode":"5210",
    "sg:province":"Aargau",
    "wof:name":"Dr.med.alice Vetterli Spezial\u00e4rztin Fmh",
    "wof:placetype":"venue"
},
  "geometry": {"coordinates":[9.373674,47.421867],"type":"Point"}
}