{
  "type": "Feature",
  "properties": {
    "iso:country":"CH",
    "sg:address":"Beim Flugplatz",
    "sg:city":"Mollis",
    "sg:orig_category":"Gewinnung von Kies U Sand Gewinnung von Natursteinen f\u00fcr den Bau",
    "sg:phone":"+41 55 612 17 94",
    "sg:postcode":"8753",
    "sg:province":"Glarus",
    "wof:name":"Hartschotterwerk Haltengut Ag Mollis",
    "wof:placetype":"venue"
},
  "geometry": {"coordinates":[9.0745248795,47.0914382935],"type":"Point"}
}