{
  "type": "Feature",
  "properties": {
    "iso:country":"CH",
    "sg:address":"Quadratscha 1",
    "sg:city":"Samedan",
    "sg:orig_category":"Verwaltung der Rechtspflege, Gerichte",
    "sg:phone":"+41 55 451 22 21",
    "sg:postcode":"7503",
    "sg:province":"Graubunden",
    "wof:name":"Bezirksgericht March",
    "wof:placetype":"venue"
},
  "geometry": {"coordinates":[8.8531122208,47.1904411316],"type":"Point"}
}