{
  "type": "Feature",
  "properties": {
    "iso:country":"CH",
    "sg:address":"Eggstrasse 7",
    "sg:city":"Zweisimmen",
    "sg:orig_category":"Fahrschulen, Flugschulen",
    "sg:phone":"+41 33 722 21 22",
    "sg:postcode":"3770",
    "sg:province":"Bern",
    "wof:name":"Hans Kohli Autofahrschule",
    "wof:placetype":"venue"
},
  "geometry": {"coordinates":[7.3824601173,46.5610313416],"type":"Point"}
}