{
  "type": "Feature",
  "properties": {
    "iso:country":"CH",
    "sg:address":"Haselweg 4",
    "sg:city":"Schaffhausen",
    "sg:orig_category":"Malerei",
    "sg:phone":"+41 52 624 48 52",
    "sg:postcode":"8200",
    "sg:province":"Schaffhausen",
    "wof:name":"Andreas Meier Malerarbeiten",
    "wof:placetype":"venue"
},
  "geometry": {"coordinates":[8.6204414368,47.7029876709],"type":"Point"}
}