{
  "type": "Feature",
  "properties": {
    "iso:country":"CH",
    "sg:address":"Via Capelascia 10",
    "sg:city":"Lamone",
    "sg:classifiers":[
        {
            "category":"Retail",
            "subcategory":"Driving School",
            "type":"Services"
        }
    ],
    "sg:phone":"+41 91 961 80 10",
    "sg:postcode":"6814",
    "sg:province":"Ticino",
    "sg:tags":[
        "awning",
        "drive"
    ],
    "wof:name":"Bredo Bau S.a.",
    "wof:placetype":"venue"
},
  "geometry": {"coordinates":[8.9306650162,46.0396537781],"type":"Point"}
}