{
  "type": "Feature",
  "properties": {
    "iso:country":"CH",
    "sg:address":"Brodlaube 2 4310 Rheinfelden. Postfach",
    "sg:city":"Rheinfelden",
    "sg:orig_category":"Herstellung von konfektionierten Textilwaren ohne Bekleidung",
    "sg:phone":"+41 61 831 50 70",
    "sg:postcode":"4310",
    "sg:province":"Aargau",
    "wof:name":"Couture Atratus Eichholzer J. Damen U. Herren Massschneideratelier",
    "wof:placetype":"venue"
},
  "geometry": {"coordinates":[7.7937641144,47.5551834106],"type":"Point"}
}