{
  "type": "Feature",
  "properties": {
    "iso:country":"CH",
    "sg:address":"Langenhagstrasse 40",
    "sg:city":"Birsfelden",
    "sg:orig_category":"Grosshandel mit festen Brennstoffen U Mineral\u00f6lerzeugnissen Mineral\u00f6lverarbeitung",
    "sg:phone":"+41 61 311 85 00",
    "sg:postcode":"4127",
    "sg:province":"Basel-Landschaft",
    "wof:name":"Gm\u00fcr Brennstoffe",
    "wof:placetype":"venue"
},
  "geometry": {"coordinates":[7.6398730278,47.5521888733],"type":"Point"}
}