{
  "type": "Feature",
  "properties": {
    "iso:country":"CH",
    "sg:address":"Hofstrasse 31",
    "sg:city":"Romanshorn",
    "sg:orig_category":"Grosshandel mit Textilien",
    "sg:postcode":"8590",
    "sg:province":"Thurgau",
    "wof:name":"Textrachem Ag",
    "wof:placetype":"venue"
},
  "geometry": {"coordinates":[9.3679962158,47.5581855774],"type":"Point"}
}