{
  "type": "Feature",
  "properties": {
    "iso:country":"CH",
    "sg:address":"Thunstrasse 108 3113 Rubigen. Postfach",
    "sg:city":"Rubigen",
    "sg:orig_category":"Zimmerei, Dachdeckerei, Bauspenglerei U Abdichtung",
    "sg:postcode":"3113",
    "sg:province":"Bern",
    "wof:name":"Happy Work Gmbh",
    "wof:placetype":"venue"
},
  "geometry": {"coordinates":[7.5503621101,46.8915786743],"type":"Point"}
}