{
  "type": "Feature",
  "properties": {
    "iso:country":"CH",
    "sg:address":"Oristalstrasse 16",
    "sg:city":"Nuglar",
    "sg:orig_category":"Herstellung von Radio U Fernsehger\u00e4ten sowie phono U videotechnischen Ger\u00e4ten",
    "sg:phone":"+41 61 911 91 95",
    "sg:postcode":"4412",
    "sg:province":"Solothurn",
    "wof:name":"Lehmann Videosysteme Gmbh",
    "wof:placetype":"venue"
},
  "geometry": {"coordinates":[7.7080321312,47.4698028564],"type":"Point"}
}