{
  "type": "Feature",
  "properties": {
    "iso:country":"CH",
    "sg:address":"Feldmoosstrasse 8 8853 Lachen Sz. Postfach 230",
    "sg:city":"Altendorf",
    "sg:orig_category":"Handelsvermittlung U Grosshandel Sonstige pers\u00f6nliche Dienstleistungen",
    "sg:phone":"+41 55 451 50 20",
    "sg:postcode":"8852",
    "sg:province":"Schwyz",
    "wof:name":"Factotum Handelshaus Ag",
    "wof:placetype":"venue"
},
  "geometry": {"coordinates":[8.8627977371,47.189289093],"type":"Point"}
}