{
  "type": "Feature",
  "properties": {
    "iso:country":"CH",
    "sg:address":"Grand Rue",
    "sg:city":"Montreux",
    "sg:orig_category":"Pensionskassen",
    "sg:postcode":"1820",
    "sg:province":"Vaud",
    "wof:name":"Caisse De Retraite En Faveur Du Personnel De La Soci\u00e9t\u00e9 Montreux-palace Sa",
    "wof:placetype":"venue"
},
  "geometry": {"coordinates":[6.905151844,46.4393043518],"type":"Point"}
}