{
  "type": "Feature",
  "properties": {
    "iso:country":"CH",
    "sg:address":"Feldg\u00fcetliweg 144",
    "sg:city":"Feldmeilen",
    "sg:orig_category":"Bauschreinerei Herstellung von Konstruktionsteilen, Fertigbauteilen U Ausbauelementen aus Holz",
    "sg:phone":"+41 71 245 40 15",
    "sg:postcode":"8706",
    "sg:province":"Z\u00fcrich",
    "wof:name":"Peter Vogler Ag",
    "wof:placetype":"venue"
},
  "geometry": {"coordinates":[9.387953,47.43605],"type":"Point"}
}