{
  "type": "Feature",
  "properties": {
    "iso:country":"CH",
    "sg:address":"Dorfstrasse 21",
    "sg:city":"Mogelsberg",
    "sg:orig_category":"Detailhandel mit Waren verschiedener Art, Hauptrichtung Nahrungsmittel Sonstiger Grosshandel",
    "sg:phone":"+41 71 374 23 81",
    "sg:postcode":"9122",
    "sg:province":"St. Gallen",
    "wof:name":"Sch\u00f6b-broger R.",
    "wof:placetype":"venue"
},
  "geometry": {"coordinates":[9.1355991364,47.3627738953],"type":"Point"}
}