{
  "type": "Feature",
  "properties": {
    "addr:full":"Kirchweg 1 Oberehrendingen 5422",
    "addr:housenumber":"1",
    "addr:postcode":"5422",
    "addr:street":"Kirchweg;Oberehrendingen",
    "iso:country":"CH",
    "sg:address":"Kirchweg 1",
    "sg:city":"Oberehrendingen",
    "sg:orig_category":"Architektur U Ingenieurb\u00fcros Architekturb\u00fcros",
    "sg:phone":"+41 56 222 38 80",
    "sg:postcode":"5422",
    "wof:name":"Thomsen + Ludwig Architekturb\u00fcro",
    "wof:placetype":"venue"
},
  "geometry": {"coordinates":[8.342151,47.495941],"type":"Point"}
}