{
  "type": "Feature",
  "properties": {
    "iso:country":"CH",
    "sg:address":"Dorf",
    "sg:city":"Bristen",
    "sg:orig_category":"G\u00fcterbef\u00f6rderung im Strassenverkehr",
    "sg:phone":"+41 79 217 67 47",
    "sg:postcode":"6475",
    "sg:province":"Uri",
    "wof:name":"Johann Ritzinger Transporte",
    "wof:placetype":"venue"
},
  "geometry": {"coordinates":[8.2186841965,47.4890823364],"type":"Point"}
}