{
  "type": "Feature",
  "properties": {
    "iso:country":"CH",
    "sg:address":"Walther-hauser-strasse 3 8820 W\u00e4denswil. Postfach 704",
    "sg:city":"W\u00e4denswil",
    "sg:orig_category":"Gartenbau",
    "sg:phone":"+41 17808562",
    "sg:postcode":"8820",
    "sg:province":"Z\u00fcrich",
    "wof:name":"Gebr. Zellweger & Co Gartenbau",
    "wof:placetype":"venue"
},
  "geometry": {"coordinates":[8.6749296188,47.2182502747],"type":"Point"}
}