{
  "type": "Feature",
  "properties": {
    "iso:country":"CH",
    "sg:address":"Dorfstrasse 8",
    "sg:city":"Schleinikon",
    "sg:orig_category":"Sonstiges Gesundheitswesen",
    "sg:phone":"+41 18561920",
    "sg:postcode":"8165",
    "sg:province":"Z\u00fcrich",
    "wof:name":"Spitex Wehntal Krankenmobilien-magazin",
    "wof:placetype":"venue"
},
  "geometry": {"coordinates":[8.3981571198,47.4967803955],"type":"Point"}
}