{
  "type": "Feature",
  "properties": {
    "iso:country":"CH",
    "sg:address":"Wasterkingerweg",
    "sg:city":"Eglisau",
    "sg:classifiers":[
        {
            "category":"Social Services",
            "subcategory":"Job Training",
            "type":"Services"
        }
    ],
    "sg:phone":"+41 18683033",
    "sg:postcode":"8193",
    "sg:province":"Z\u00fcrich",
    "sg:tags":[
        "adhesive",
        "industry",
        "electrical",
        "tape"
    ],
    "wof:name":"Alvico P. Vils & Co",
    "wof:placetype":"venue"
},
  "geometry": {"coordinates":[8.51114,47.581104],"type":"Point"}
}