{
  "type": "Feature",
  "properties": {
    "iso:country":"CH",
    "sg:address":"M\u00fchlegasse 18",
    "sg:city":"Baar",
    "sg:orig_category":"Technische B\u00fcros Elektro",
    "sg:phone":"+41 41 760 22 88",
    "sg:postcode":"6340",
    "sg:province":"Zug",
    "wof:name":"Ft Digitec Ag Planungsb\u00fcro F.elektrotechnik",
    "wof:placetype":"venue"
},
  "geometry": {"coordinates":[8.5264730453,47.1992111206],"type":"Point"}
}