{
  "type": "Feature",
  "properties": {
    "iso:country":"CH",
    "sg:address":"Postgasse 6 8708 M\u00e4nnedorf. Postfach",
    "sg:city":"M\u00e4nnedorf",
    "sg:orig_category":"Non-Classified Establishments",
    "sg:phone":"+41 19221333",
    "sg:postcode":"8708",
    "sg:province":"Z\u00fcrich",
    "wof:name":"Marti + Dietschweiler Ag",
    "wof:placetype":"venue"
},
  "geometry": {"coordinates":[8.6905498505,47.2530555725],"type":"Point"}
}