{
  "type": "Feature",
  "properties": {
    "iso:country":"CH",
    "sg:address":"Via Cantonale",
    "sg:city":"Barbengo",
    "sg:orig_category":"Informatikdienste Sonstige mit der Informatik verbundene T\u00e4tigkeiten",
    "sg:phone":"+41 55 240 90 90",
    "sg:postcode":"6917",
    "sg:province":"Ticino",
    "wof:name":"Webrise.ch Homepage Internet Web Design",
    "wof:placetype":"venue"
},
  "geometry": {"coordinates":[8.8392601013,47.2569160461],"type":"Point"}
}