{
  "type": "Feature",
  "properties": {
    "iso:country":"CH",
    "sg:address":"Beundenfeldstrasse 27 3013 Bern. Postfach",
    "sg:city":"Bern",
    "sg:orig_category":"Markt U Meinungsforschung",
    "sg:postcode":"3005",
    "sg:province":"Bern",
    "wof:name":"Fischer Manuel B\u00fcro F\u00fcr Verkauf Und Koordination Konzepte Bes. I. Ber. Verkaufsplanung, Werbung Usw; Planung, Realisat.",
    "wof:placetype":"venue"
},
  "geometry": {"coordinates":[7.4543409348,46.9565505981],"type":"Point"}
}