{
  "type": "Feature",
  "properties": {
    "iso:country":"CH",
    "sg:address":"1816",
    "sg:city":"Chailly-montreux",
    "sg:orig_category":"Detailhandel mit Milcherzeugnissen U Eiern",
    "sg:phone":"+41 41 921 86 00",
    "sg:postcode":"1816",
    "sg:province":"Vaud",
    "wof:name":"Robert Ruch Ch\u00e4si-lade",
    "wof:placetype":"venue"
},
  "geometry": {"coordinates":[8.0744695663,47.1829185486],"type":"Point"}
}