{
  "type": "Feature",
  "properties": {
    "iso:country":"CH",
    "sg:address":"Rue Du Ch\u00e2teau-d'en-bas 15 1630 Bulle Case Postale 149",
    "sg:city":"Bulle",
    "sg:orig_category":"Detailhandel mit Fahrr\u00e4dern Handel mit Motorr\u00e4dern, Teilen U Zubeh\u00f6r Instandhaltung U Reparatur von ",
    "sg:phone":"+41 26 912 35 22",
    "sg:postcode":"1630",
    "sg:province":"Fribourg",
    "wof:name":"Pythoud Cycles Sa",
    "wof:placetype":"venue"
},
  "geometry": {"coordinates":[7.0823850632,46.5843086243],"type":"Point"}
}