{
  "type": "Feature",
  "properties": {
    "addr:full":"Spitalstrasse 27 Bern Bern 3011",
    "addr:housenumber":"27",
    "addr:postcode":"3011",
    "addr:street":"Spitalstrasse",
    "iso:country":"CH",
    "sg:address":"Spitalstrasse 27",
    "sg:city":"Bern",
    "sg:orig_category":"Advokaturb\u00fcros",
    "sg:phone":"+41 31 311 81 81",
    "sg:postcode":"3011",
    "sg:province":"Bern",
    "wof:name":"Dr. Jur. Rolf Messerli Advokaturb\u00fcro F\u00fcrsprecher",
    "wof:placetype":"venue"
},
  "geometry": {"coordinates":[7.442146,46.947948],"type":"Point"}
}