{
  "type": "Feature",
  "properties": {
    "iso:country":"CH",
    "sg:address":"Gewerbestrasse 11",
    "sg:city":"Cham",
    "sg:orig_category":"Wirtschaftspr\u00fcfung, Steuerberatung U Treuhand",
    "sg:phone":"+41 81 921 65 60",
    "sg:postcode":"6330",
    "sg:province":"Zug",
    "wof:name":"Steiner Treuhand",
    "wof:placetype":"venue"
},
  "geometry": {"coordinates":[9.255616188,46.8012237549],"type":"Point"}
}