{
  "type": "Feature",
  "properties": {
    "iso:country":"CH",
    "sg:address":"Mettlenweg 23 2500 Biel/bienne. Postfach",
    "sg:city":"Biel/bienne",
    "sg:orig_category":"Architektur U Ingenieurb\u00fcros",
    "sg:postcode":"2504",
    "sg:province":"Bern",
    "wof:name":"Haller Hans-rudolf",
    "wof:placetype":"venue"
},
  "geometry": {"coordinates":[7.277707,47.148129],"type":"Point"}
}