{
  "type": "Feature",
  "properties": {
    "iso:country":"CH",
    "sg:address":"Spitalackerstrasse 67",
    "sg:city":"Bern",
    "sg:orig_category":"Arztpraxen",
    "sg:phone":"+41 31 331 31 81",
    "sg:postcode":"3013",
    "sg:province":"Bern",
    "wof:name":"Dr.med.claude Rui Spezialarzt Fmh",
    "wof:placetype":"venue"
},
  "geometry": {"coordinates":[7.451244,46.957047],"type":"Point"}
}