{
  "type": "Feature",
  "properties": {
    "iso:country":"CH",
    "sg:address":"Sch\u00f6nenbergstrasse 6",
    "sg:city":"W\u00e4denswil",
    "sg:orig_category":"Unclassifiable Establishments",
    "sg:phone":"+41 17808270",
    "sg:postcode":"8820",
    "sg:province":"Z\u00fcrich",
    "wof:name":"Dmp Digital Multi Print Ag",
    "wof:placetype":"venue"
},
  "geometry": {"coordinates":[8.6714000702,47.228729248],"type":"Point"}
}