{
  "type": "Feature",
  "properties": {
    "iso:country":"CH",
    "sg:address":"B\u00f6sch 83a",
    "sg:city":"H\u00fcnenberg",
    "sg:orig_category":"Mechanische Werkst\u00e4tten",
    "sg:phone":"+41 41 780 62 10",
    "sg:postcode":"6331",
    "sg:province":"Zug",
    "wof:name":"Rolf K\u00e4ppeli Schweisstechnik",
    "wof:placetype":"venue"
},
  "geometry": {"coordinates":[8.4346780777,47.1624794006],"type":"Point"}
}