{
  "type": "Feature",
  "properties": {
    "iso:country":"CH",
    "sg:address":"Rue De Pain-blanc 19",
    "sg:city":"Neuenburg",
    "sg:orig_category":"Non-Classified Establishments",
    "sg:postcode":"2000",
    "sg:province":"Neuch\u00e2tel",
    "wof:name":"Olivier Rieser - Photographie-edition",
    "wof:placetype":"venue"
},
  "geometry": {"coordinates":[6.8986477852,46.9820709229],"type":"Point"}
}