{
  "type": "Feature",
  "properties": {
    "iso:country":"CH",
    "sg:address":"Rickenstrasse 28",
    "sg:city":"Wagen",
    "sg:orig_category":"Unclassifiable Establishments",
    "sg:postcode":"8646",
    "sg:province":"St. Gallen",
    "wof:name":"Hrc Uebelmann - Richtcenter",
    "wof:placetype":"venue"
},
  "geometry": {"coordinates":[8.1788911819,47.4681015015],"type":"Point"}
}