{
  "type": "Feature",
  "properties": {
    "iso:country":"CH",
    "sg:address":"Z\u00fcrcherstrasse 232a",
    "sg:city":"Dietikon",
    "sg:orig_category":"Instandhaltung U Reparatur von Automobilen",
    "sg:phone":"+41 17405151",
    "sg:postcode":"8953",
    "sg:province":"Z\u00fcrich",
    "wof:name":"Garage Egger Ag",
    "wof:placetype":"venue"
},
  "geometry": {"coordinates":[8.4241104126,47.3970947266],"type":"Point"}
}