{
  "type": "Feature",
  "properties": {
    "iso:country":"CH",
    "sg:address":"2905 Courtedoux Case Postale 8",
    "sg:city":"Courtedoux",
    "sg:orig_category":"Sportvereine Ballsport Fussball",
    "sg:postcode":"2905",
    "sg:province":"Jura",
    "wof:name":"Fc Courtedoux",
    "wof:placetype":"venue"
},
  "geometry": {"coordinates":[7.042069912,47.4065055847],"type":"Point"}
}