{
  "type": "Feature",
  "properties": {
    "iso:country":"CH",
    "sg:address":"Rue De La Plaine 84",
    "sg:city":"Yverdon-les-bains",
    "sg:classifiers":[
        {
            "category":"Restaurant",
            "type":"Food & Drink"
        }
    ],
    "sg:phone":"+41 24 426 14 61",
    "sg:postcode":"1400",
    "sg:province":"Vaud",
    "wof:name":"Caf\u00e9 Le Poivrier",
    "wof:placetype":"venue"
},
  "geometry": {"coordinates":[6.6464319229,46.7766571045],"type":"Point"}
}