{
  "type": "Feature",
  "properties": {
    "iso:country":"CH",
    "sg:address":"Binningerstrasse 89",
    "sg:city":"Allschwil",
    "sg:orig_category":"RESTAURANTS: TEA-ROOMS",
    "sg:phone":"+41 61 481 21 10",
    "sg:postcode":"4123",
    "sg:province":"Basel-Landschaft",
    "wof:name":"Sylvia Hug",
    "wof:placetype":"venue"
},
  "geometry": {"coordinates":[7.5460219383,47.5484275818],"type":"Point"}
}