{
  "type": "Feature",
  "properties": {
    "iso:country":"CH",
    "sg:address":"Rue Du Four 24",
    "sg:city":"Yverdon-les-bains",
    "sg:orig_category":"Detailhandel mit Ton U Bildtr\u00e4gern",
    "sg:phone":"+41 24 425 70 77",
    "sg:postcode":"1400",
    "sg:province":"Vaud",
    "wof:name":"Ren\u00e9 Kaeser Cd Box",
    "wof:placetype":"venue"
},
  "geometry": {"coordinates":[6.6393451691,46.7786865234],"type":"Point"}
}