{
  "type": "Feature",
  "properties": {
    "iso:country":"CH",
    "sg:address":"Grand-rue 89",
    "sg:city":"Morges",
    "sg:orig_category":"Advokaturb\u00fcros",
    "sg:phone":"+41 21 803 34 71",
    "sg:postcode":"1110",
    "sg:province":"Vaud",
    "wof:name":"Jean-emmanuel Rossel Etude D'avocat",
    "wof:placetype":"venue"
},
  "geometry": {"coordinates":[6.49739,46.508015],"type":"Point"}
}