{
  "type": "Feature",
  "properties": {
    "iso:country":"CH",
    "sg:address":"Avenue Du Midi 8 1950 Sion. Postfach",
    "sg:city":"Sion",
    "sg:orig_category":"Fachdetailhandel mit pharmazeutischen Produkten",
    "sg:phone":"+41 27 322 42 35",
    "sg:postcode":"1951",
    "sg:province":"Valais",
    "wof:name":"Rapha\u00ebl Berger Pharmacie Berger",
    "wof:placetype":"venue"
},
  "geometry": {"coordinates":[7.3589577675,46.2306518555],"type":"Point"}
}