{
  "type": "Feature",
  "properties": {
    "addr:full":"M\u00fcnstergasse 30 Schaffhausen Schaffhausen 8200",
    "addr:housenumber":"30",
    "addr:postcode":"8200",
    "addr:street":"Muenstergasse",
    "iso:country":"CH",
    "sg:address":"M\u00fcnstergasse 30",
    "sg:city":"Schaffhausen",
    "sg:orig_category":"Bau\u00e4mter",
    "sg:phone":"+41 52 632 51 11",
    "sg:postcode":"8200",
    "sg:province":"Schaffhausen",
    "wof:name":"St\u00e4dtisches Hochbauamt",
    "wof:placetype":"venue"
},
  "geometry": {"coordinates":[8.63483,47.696274],"type":"Point"}
}