{
  "type": "Feature",
  "properties": {
    "iso:country":"CH",
    "sg:address":"Rue De La Mairie 33",
    "sg:city":"Gen\u00e8ve",
    "sg:orig_category":"Einrahmungen Glaserei",
    "sg:phone":"+41 22 735 56 60",
    "sg:postcode":"1207",
    "sg:province":"Gen\u00e8ve",
    "wof:name":"Bativer Sa Vitrerie & Encadrements",
    "wof:placetype":"venue"
},
  "geometry": {"coordinates":[6.1592059135,46.2020263672],"type":"Point"}
}