{
  "type": "Feature",
  "properties": {
    "iso:country":"CH",
    "sg:address":"Moulin Du Choc",
    "sg:city":"Romanel-sur-morges",
    "sg:orig_category":"Herstellung von sonstigen Nahrungsmitteln",
    "sg:postcode":"1122",
    "sg:province":"Vaud",
    "wof:name":"Grin Jean-claude",
    "wof:placetype":"venue"
},
  "geometry": {"coordinates":[6.5264410973,46.561340332],"type":"Point"}
}