{
  "type": "Feature",
  "properties": {
    "iso:country":"CH",
    "sg:address":"Neugr\u00fcttstrasse 9",
    "sg:city":"Balgach",
    "sg:orig_category":"Vermietung U Verpachtung von eigenen Immobilien",
    "sg:postcode":"9436",
    "sg:province":"St. Gallen",
    "wof:name":"Heitos Ag",
    "wof:placetype":"venue"
},
  "geometry": {"coordinates":[9.0692996979,46.9964408875],"type":"Point"}
}