{
  "type": "Feature",
  "properties": {
    "iso:country":"CH",
    "sg:address":"Leoncavallo Via",
    "sg:city":"Brissago",
    "sg:orig_category":"Tankstellen",
    "sg:phone":"+41 61 726 97 10",
    "sg:postcode":"6614",
    "sg:province":"Ticino",
    "wof:name":"Leu Carrosserie Und Spritzwerk Ag",
    "wof:placetype":"venue"
},
  "geometry": {"coordinates":[7.5330200195,47.5077781677],"type":"Point"}
}