{
  "type": "Feature",
  "properties": {
    "iso:country":"CH",
    "sg:address":"Sous-la-ville",
    "sg:city":"Puidoux",
    "sg:orig_category":"Herstellung von Duft U K\u00f6rperpflegemitteln",
    "sg:postcode":"1070",
    "sg:province":"Vaud",
    "wof:name":"Eb S\u00e0rl",
    "wof:placetype":"venue"
},
  "geometry": {"coordinates":[6.7703652382,46.4883651733],"type":"Point"}
}