{
  "type": "Feature",
  "properties": {
    "iso:country":"CH",
    "sg:address":"Rorschacher Strasse 19",
    "sg:city":"St.gallen",
    "sg:orig_category":"Gesundheitswesen",
    "sg:phone":"+41 71 243 59 47",
    "sg:postcode":"9000",
    "sg:province":"St. Gallen",
    "wof:name":"Fritz Sprenger Ag",
    "wof:placetype":"venue"
},
  "geometry": {"coordinates":[9.3803091049,47.4264755249],"type":"Point"}
}