{
  "type": "Feature",
  "properties": {
    "iso:country":"CH",
    "sg:address":"Seestrasse 412",
    "sg:city":"Z\u00fcrich",
    "sg:orig_category":"Non-Classified Establishments",
    "sg:postcode":"8038",
    "sg:province":"Z\u00fcrich",
    "wof:name":"Alpwood Gmbh",
    "wof:placetype":"venue"
},
  "geometry": {"coordinates":[8.536110878,47.3423995972],"type":"Point"}
}