{
  "type": "Feature",
  "properties": {
    "iso:country":"CH",
    "sg:address":"Soodstrasse 38",
    "sg:city":"Adliswil",
    "sg:orig_category":"Detailhandel Handel mit Motorr\u00e4dern, Teilen U Zubeh\u00f6r Instandhaltung U Reparatur von Motorr\u00e4dern Rep",
    "sg:phone":"+41 17103784",
    "sg:postcode":"8134",
    "sg:province":"Z\u00fcrich",
    "wof:name":"Andr\u00e9 Gonella Motos",
    "wof:placetype":"venue"
},
  "geometry": {"coordinates":[8.5242738724,47.3180732727],"type":"Point"}
}