{
  "type": "Feature",
  "properties": {
    "iso:country":"CH",
    "sg:address":"6715",
    "sg:city":"Dongio",
    "sg:orig_category":"Fachdetailhandel mit pharmazeutischen Produkten",
    "sg:phone":"+41 91 871 18 18",
    "sg:postcode":"6715",
    "sg:province":"Ticino",
    "wof:name":"Farmacia Martinoli Sa",
    "wof:placetype":"venue"
},
  "geometry": {"coordinates":[8.9522600174,46.4397087097],"type":"Point"}
}