{
  "type": "Feature",
  "properties": {
    "iso:country":"CH",
    "sg:address":"Winkel",
    "sg:city":"Obersteckholz",
    "sg:orig_category":"Herstellung von Konstruktionsteilen, Fertigbauteilen U Ausbauelementen aus Holz",
    "sg:phone":"+41 62 922 69 39",
    "sg:postcode":"4924",
    "sg:province":"Bern",
    "wof:name":"Hertig Erich",
    "wof:placetype":"venue"
},
  "geometry": {"coordinates":[7.8198251724,47.1980400085],"type":"Point"}
}