{
  "type": "Feature",
  "properties": {
    "iso:country":"CH",
    "sg:address":"6048",
    "sg:city":"Horw",
    "sg:orig_category":"Bezirks, Sekundar, Realschulen, Oberstufe der Primarschulen",
    "sg:phone":"+41 41 340 63 18",
    "sg:postcode":"6048",
    "sg:province":"Luzern",
    "wof:name":"Sekundarschule Oberstufenschulhaus",
    "wof:placetype":"venue"
},
  "geometry": {"coordinates":[8.311521,47.019157],"type":"Point"}
}