{
  "type": "Feature",
  "properties": {
    "iso:country":"CH",
    "sg:address":"Chemin Frank-thomas 44",
    "sg:city":"Cologny",
    "sg:orig_category":"Softwareentwicklung U beratung",
    "sg:postcode":"1223",
    "sg:province":"Gen\u00e8ve",
    "wof:name":"Agribu Sa",
    "wof:placetype":"venue"
},
  "geometry": {"coordinates":[6.1747598648,46.2039108276],"type":"Point"}
}