{
  "type": "Feature",
  "properties": {
    "iso:country":"CH",
    "sg:address":"Oberwilerstrasse 73 4102 Binningen. Postfach",
    "sg:city":"Binningen",
    "sg:orig_category":"Herstellung von Seifen, Wasch U Reinigungsmitteln",
    "sg:postcode":"4102",
    "sg:province":"Basel-Landschaft",
    "wof:name":"Kelly's Car-shine-produkte, Kellerhals Heinz",
    "wof:placetype":"venue"
},
  "geometry": {"coordinates":[7.5698161125,47.5320510864],"type":"Point"}
}