{
  "type": "Feature",
  "properties": {
    "iso:country":"CH",
    "sg:address":"Pfeilstrasse 7",
    "sg:city":"Derendingen",
    "sg:orig_category":"Advokaturb\u00fcros",
    "sg:phone":"+41 12244929",
    "sg:postcode":"4552",
    "sg:province":"Solothurn",
    "wof:name":"J.martin Pulver Advokaturb\u00fcro",
    "wof:placetype":"venue"
},
  "geometry": {"coordinates":[8.776873,47.201431],"type":"Point"}
}