{
  "type": "Feature",
  "properties": {
    "addr:full":"Schwaderloh 19 Neuwilen Thurgau 8566",
    "addr:housenumber":"19",
    "addr:postcode":"8566",
    "addr:street":"Schwaderloh;Thurgau",
    "iso:country":"CH",
    "sg:address":"Schwaderloh 19",
    "sg:city":"Neuwilen",
    "sg:orig_category":"Blumen U Zierpflanzenbau",
    "sg:phone":"+41 79 416 64 91",
    "sg:postcode":"8566",
    "sg:province":"Thurgau",
    "wof:name":"Manfred & Regine Felsberg Friedhofsg\u00e4rtnerei",
    "wof:placetype":"venue"
},
  "geometry": {"coordinates":[9.134541,47.621853],"type":"Point"}
}