{
  "type": "Feature",
  "properties": {
    "iso:country":"CH",
    "sg:address":"Landstrasse 92",
    "sg:city":"W\u00fcrenlos",
    "sg:orig_category":"Detailhandel mit Fahrr\u00e4dern",
    "sg:phone":"+41 56 424 37 47",
    "sg:postcode":"5436",
    "sg:province":"Aargau",
    "wof:name":"Martin Kaiser Bike Corner",
    "wof:placetype":"venue"
},
  "geometry": {"coordinates":[8.3646268845,47.4406738281],"type":"Point"}
}