{
  "type": "Feature",
  "properties": {
    "addr:full":"Bernstrasse 13 Radelfingen Bern 3271",
    "addr:housenumber":"13",
    "addr:postcode":"3271",
    "addr:street":"Bernstrasse",
    "iso:country":"CH",
    "sg:address":"Bernstrasse 13",
    "sg:city":"Radelfingen",
    "sg:orig_category":"Bauschreinerei Herstellung von Konstruktionsteilen, Fertigbauteilen U Ausbauelementen aus Holz",
    "sg:postcode":"3271",
    "sg:province":"Bern",
    "wof:name":"Grundner Ruedi",
    "wof:placetype":"venue"
},
  "geometry": {"coordinates":[9.385499,47.434677],"type":"Point"}
}