{
  "type": "Feature",
  "properties": {
    "iso:country":"CH",
    "sg:address":"Grand'rue 10",
    "sg:city":"Rolle",
    "sg:orig_category":"Detailhandel mit B\u00fcchern, Zeitungen, Schreib U Papeteriewaren",
    "sg:phone":"+41 33 243 22 85",
    "sg:postcode":"1180",
    "sg:province":"Vaud",
    "wof:name":"H. C. Maeder Ag",
    "wof:placetype":"venue"
},
  "geometry": {"coordinates":[8.0339612961,46.7541313171],"type":"Point"}
}