{
  "type": "Feature",
  "properties": {
    "iso:country":"CH",
    "sg:address":"Maienweg 2a",
    "sg:city":"Schlieren",
    "sg:orig_category":"Sonstige pers\u00f6nliche Dienstleistungen",
    "sg:postcode":"8952",
    "sg:province":"Z\u00fcrich",
    "wof:name":"Ustina Ursula G\u00fctlin-pl\u00fcer",
    "wof:placetype":"venue"
},
  "geometry": {"coordinates":[8.4475650787,47.4044799805],"type":"Point"}
}