{
  "type": "Feature",
  "properties": {
    "iso:country":"CH",
    "sg:address":"Sch\u00fctzengraben 35 4051 Basel. Postfach 306",
    "sg:city":"Basel",
    "sg:orig_category":"Grosshandel mit Fleisch U Fleischwaren",
    "sg:phone":"+41 61 264 50 50",
    "sg:postcode":"4003",
    "sg:province":"Basel-Stadt",
    "wof:name":"Gvfi International Ag",
    "wof:placetype":"venue"
},
  "geometry": {"coordinates":[7.5809102058,47.556640625],"type":"Point"}
}