{
  "type": "Feature",
  "properties": {
    "iso:country":"CH",
    "sg:address":"Kaufplatz 5 3930 Visp. Postfach",
    "sg:city":"Visp",
    "sg:orig_category":"RESTAURANTS: TEA-ROOMS",
    "sg:phone":"+41 27 946 22 37",
    "sg:postcode":"3930",
    "sg:province":"Valais",
    "wof:name":"Restaurant National, Kalbermatter Esther",
    "wof:placetype":"venue"
},
  "geometry": {"coordinates":[7.8816342354,46.2908630371],"type":"Point"}
}