{
  "type": "Feature",
  "properties": {
    "iso:country":"CH",
    "sg:address":"5300 Turgi. Postfach 192",
    "sg:city":"Turgi",
    "sg:orig_category":"Unclassifiable Establishments",
    "sg:phone":"+41 56 210 25 58",
    "sg:postcode":"5300",
    "sg:province":"Aargau",
    "wof:name":"Kokaunivers Umzuege-reinigungen",
    "wof:placetype":"venue"
},
  "geometry": {"coordinates":[8.2524995804,47.4925689697],"type":"Point"}
}