{
  "type": "Feature",
  "properties": {
    "addr:full":"Chesa Joumana Madulain Graubunden 7523",
    "addr:housenumber":"7523",
    "iso:country":"CH",
    "sg:address":"Chesa Joumana",
    "sg:city":"Madulain",
    "sg:orig_category":"Architektur U Ingenieurb\u00fcros",
    "sg:phone":"+41 81 852 35 88",
    "sg:postcode":"7523",
    "sg:province":"Graubunden",
    "wof:name":"Niederegger & Z\u00fcger Ingenieurb\u00fcro",
    "wof:placetype":"venue"
},
  "geometry": {"coordinates":[9.94032,46.589111],"type":"Point"}
}