{
  "type": "Feature",
  "properties": {
    "iso:country":"CH",
    "sg:address":"Brittnauerstrasse 30",
    "sg:city":"Strengelbach",
    "sg:orig_category":"Instandhaltung U Reparatur von Automobilen",
    "sg:phone":"+41 79 330 26 19",
    "sg:postcode":"4802",
    "sg:province":"Aargau",
    "wof:name":"Fischer M. Parts 4x4 British & Us Spez.",
    "wof:placetype":"venue"
},
  "geometry": {"coordinates":[7.9319791794,47.2755279541],"type":"Point"}
}