{
  "type": "Feature",
  "properties": {
    "iso:country":"CH",
    "sg:address":"Hauptstrasse 21 9424 Rheineck. Postfach",
    "sg:city":"Rheineck",
    "sg:orig_category":"Verwaltung der Rechtspflege, Gerichte",
    "sg:phone":"+41 71 886 40 24",
    "sg:postcode":"9424",
    "sg:province":"St. Gallen",
    "wof:name":"Grundbuchamt",
    "wof:placetype":"venue"
},
  "geometry": {"coordinates":[9.5903244019,47.4663391113],"type":"Point"}
}