{
  "type": "Feature",
  "properties": {
    "iso:country":"CH",
    "sg:address":"Grafenb\u00fchl",
    "sg:city":"Linden",
    "sg:orig_category":"Holzplattenwerke",
    "sg:postcode":"3673",
    "sg:province":"Bern",
    "wof:name":"Holzverwertungsgenossenschaft Linden",
    "wof:placetype":"venue"
},
  "geometry": {"coordinates":[7.6723070145,46.8430747986],"type":"Point"}
}