{
  "type": "Feature",
  "properties": {
    "iso:country":"CH",
    "sg:address":"Hintere Vorstadt 16",
    "sg:city":"Aarau",
    "sg:orig_category":"Zahnarztpraxen",
    "sg:phone":"+41 62 822 28 47",
    "sg:postcode":"5000",
    "sg:province":"Aargau",
    "wof:name":"Dr. Med. Dent. Ewald Thenisch Zahnarzt",
    "wof:placetype":"venue"
},
  "geometry": {"coordinates":[8.045290947,47.3913269043],"type":"Point"}
}