{
  "type": "Feature",
  "properties": {
    "iso:country":"CH",
    "sg:address":"Sternenstrasse 15",
    "sg:city":"Z\u00fcrich",
    "sg:orig_category":"Internet Provider Softwareentwicklung U beratung",
    "sg:phone":"+41 43 344 41 41",
    "sg:postcode":"8002",
    "sg:province":"Z\u00fcrich",
    "wof:name":"Innofair Ag",
    "wof:placetype":"venue"
},
  "geometry": {"coordinates":[8.533539772,47.3600196838],"type":"Point"}
}