{
  "type": "Feature",
  "properties": {
    "iso:country":"CH",
    "sg:address":"Bahnhofstrasse 18 3860 Meiringen. Postfach 297",
    "sg:city":"Meiringen",
    "sg:orig_category":"Detailhandel mit Brot, Back U S\u00fcsswaren",
    "sg:phone":"+41 33 971 18 21",
    "sg:postcode":"3860",
    "sg:province":"Bern",
    "wof:name":"Andreas Frutiger B\u00e4ckerei-konditorei",
    "wof:placetype":"venue"
},
  "geometry": {"coordinates":[8.186483,46.727638],"type":"Point"}
}