{
  "type": "Feature",
  "properties": {
    "iso:country":"CH",
    "sg:address":"Soleil Rue Du",
    "sg:city":"Champvent",
    "sg:orig_category":"Sonstiger Grosshandel",
    "sg:phone":"+41 41 850 59 89",
    "sg:postcode":"1443",
    "sg:province":"Vaud",
    "wof:name":"Macom Kellenberger M.",
    "wof:placetype":"venue"
},
  "geometry": {"coordinates":[8.4368896484,47.0871276855],"type":"Point"}
}