{
  "type": "Feature",
  "properties": {
    "iso:country":"CH",
    "sg:address":"Zugerstrasse 58e 6330 Cham. Postfach",
    "sg:city":"Cham",
    "sg:orig_category":"Sonstige pers\u00f6nliche Dienstleistungen",
    "sg:phone":"+41 41 781 48 00",
    "sg:postcode":"6330",
    "sg:province":"Zug",
    "wof:name":"Swex Ag Dienstl. Im Bereiche D. Schadensermittlung, -regulierung Usw",
    "wof:placetype":"venue"
},
  "geometry": {"coordinates":[8.4682750702,47.1819343567],"type":"Point"}
}