{
  "type": "Feature",
  "properties": {
    "iso:country":"CH",
    "sg:address":"Fin Route De La 21 1871 Cho\u00ebx Case Postale 235",
    "sg:city":"Cho\u00ebx",
    "sg:orig_category":"Unternehmensberatung",
    "sg:phone":"+41 24 471 65 72",
    "sg:postcode":"1871",
    "sg:province":"Valais",
    "wof:name":"Valgest S\u00e0rl",
    "wof:placetype":"venue"
},
  "geometry": {"coordinates":[6.9547939301,46.2385025024],"type":"Point"}
}