{
  "type": "Feature",
  "properties": {
    "iso:country":"CH",
    "sg:address":"Rue Des Rettes 33",
    "sg:city":"Noiraigue",
    "sg:orig_category":"Bauspenglerei Herstellung von Gummi U Kunststoffwaren",
    "sg:phone":"+41 32 863 48 63",
    "sg:postcode":"2103",
    "sg:province":"Neuch\u00e2tel",
    "wof:name":"G\u00e9rald Erard Construction De Piscines",
    "wof:placetype":"venue"
},
  "geometry": {"coordinates":[6.721137,46.955986],"type":"Point"}
}