{
  "type": "Feature",
  "properties": {
    "iso:country":"CH",
    "sg:address":"Chemin De La R\u00e9che 76",
    "sg:city":"Bulle",
    "sg:orig_category":"Detailhandel mit Sportartikeln",
    "sg:phone":"+41 71 845 44 60",
    "sg:postcode":"1630",
    "sg:province":"Fribourg",
    "wof:name":"Christian Ulrich Windsurfshop",
    "wof:placetype":"venue"
},
  "geometry": {"coordinates":[9.5395460129,47.4820175171],"type":"Point"}
}