{
  "type": "Feature",
  "properties": {
    "iso:country":"CH",
    "sg:address":"Rue Louis-favre 54",
    "sg:city":"Boudry",
    "sg:orig_category":"Detailhandel mit Fahrr\u00e4dern Handel mit Motorr\u00e4dern, Teilen U Zubeh\u00f6r Instandhaltung U Reparatur von ",
    "sg:phone":"+41 32 842 10 12",
    "sg:postcode":"2017",
    "sg:province":"Neuch\u00e2tel",
    "wof:name":"Mouraux, M. Achat, Vente Et R\u00e9parat. De Cycles Et Motos",
    "wof:placetype":"venue"
},
  "geometry": {"coordinates":[6.835187912,46.9489364624],"type":"Point"}
}