{
  "type": "Feature",
  "properties": {
    "iso:country":"CH",
    "sg:address":"Eichholzstrasse 23",
    "sg:city":"Wabern",
    "sg:orig_category":"Vorschulen, Kinderg\u00e4rten",
    "sg:phone":"+41 31 961 11 78",
    "sg:postcode":"3084",
    "sg:province":"Bern",
    "wof:name":"Kindergarten Wabern",
    "wof:placetype":"venue"
},
  "geometry": {"coordinates":[7.4522089958,46.9299087524],"type":"Point"}
}