{
  "type": "Feature",
  "properties": {
    "iso:country":"CH",
    "sg:address":"Bahnhofstrasse 22",
    "sg:city":"St\u00e4fa",
    "sg:orig_category":"Detailhandel mit Brot, Back U S\u00fcsswaren",
    "sg:phone":"+41 32 631 18 63",
    "sg:postcode":"8712",
    "sg:province":"Z\u00fcrich",
    "wof:name":"Verena Walther B\u00e4ckerei-konditorei",
    "wof:placetype":"venue"
},
  "geometry": {"coordinates":[7.654681,47.235832],"type":"Point"}
}