{
  "type": "Feature",
  "properties": {
    "iso:country":"CH",
    "sg:address":"Aeussere Lange Heid 18 4142 M\u00fcnchenstein. Postfach",
    "sg:city":"M\u00fcnchenstein",
    "sg:orig_category":"Elektroinstallation",
    "sg:phone":"+41 61 411 87 72",
    "sg:postcode":"4142",
    "sg:province":"Basel-Landschaft",
    "wof:name":"Ses-snebl Elektro Service Elektroservicearbeiten",
    "wof:placetype":"venue"
},
  "geometry": {"coordinates":[7.6062412262,47.5237693787],"type":"Point"}
}