{
  "type": "Feature",
  "properties": {
    "iso:country":"CH",
    "sg:address":"Hufg.10",
    "sg:city":"Z\u00fcrich",
    "sg:classifiers":[
        {
            "category":"Professional",
            "subcategory":"Advertising",
            "type":"Services"
        }
    ],
    "sg:phone":"+41 4116317777",
    "sg:postcode":"8008",
    "sg:province":"Z\u00fcrich",
    "sg:tags":[
        "information",
        "medium",
        "communication"
    ],
    "wof:name":"Reuters Sa",
    "wof:placetype":"venue"
},
  "geometry": {"coordinates":[8.53955,47.37706],"type":"Point"}
}