{
  "type": "Feature",
  "properties": {
    "iso:country":"CH",
    "sg:address":"Waldweg 20",
    "sg:city":"Magden",
    "sg:orig_category":"Sportvereine Turnen",
    "sg:phone":"+41 81 322 95 93",
    "sg:postcode":"4312",
    "sg:province":"Aargau",
    "wof:name":"Turnverein Stv Malans",
    "wof:placetype":"venue"
},
  "geometry": {"coordinates":[9.5767631531,46.9852981567],"type":"Point"}
}