{
  "type": "Feature",
  "properties": {
    "iso:country":"CH",
    "sg:address":"Bachstrasse 13",
    "sg:city":"Thal",
    "sg:orig_category":"Detailhandel mit Antiquit\u00e4ten",
    "sg:phone":"+41 71 888 18 03",
    "sg:postcode":"9425",
    "sg:province":"St. Gallen",
    "wof:name":"Lili Selina Breu Antiquit\u00e4ten",
    "wof:placetype":"venue"
},
  "geometry": {"coordinates":[9.567951,47.467182],"type":"Point"}
}