{
  "type": "Feature",
  "properties": {
    "iso:country":"CH",
    "sg:address":"Heusser-staub-strasse 18",
    "sg:city":"Uster",
    "sg:orig_category":"Wirtschaftspr\u00fcfung, Steuerberatung U Treuhand",
    "sg:postcode":"8610",
    "sg:province":"Z\u00fcrich",
    "wof:name":"Luag Ag F\u00fcr Land Und Nutzungsumlegung",
    "wof:placetype":"venue"
},
  "geometry": {"coordinates":[8.7204256058,47.3418159485],"type":"Point"}
}