{
  "type": "Feature",
  "properties": {
    "iso:country":"CH",
    "sg:address":"Hauptstrasse 14",
    "sg:city":"Muttenz",
    "sg:orig_category":"Detailhandel mit Fleisch U Fleischwaren",
    "sg:phone":"+41 61 461 11 88",
    "sg:postcode":"4132",
    "sg:province":"Basel-Landschaft",
    "wof:name":"Tebewe Beckmann Und Co",
    "wof:placetype":"venue"
},
  "geometry": {"coordinates":[7.6456727982,47.5231704712],"type":"Point"}
}