{
  "type": "Feature",
  "properties": {
    "iso:country":"CH",
    "sg:address":"Place De La Gare 10 1003 Lausanne Case Postale 1115",
    "sg:city":"Lausanne",
    "sg:orig_category":"Grosshandel mit chemischen Erzeugnissen Grosshandel mit pharmazeutischen Erzeugnissen",
    "sg:phone":"+41 21 323 47 33",
    "sg:postcode":"1001",
    "sg:province":"Vaud",
    "wof:name":"Landmark Chemicals Sa",
    "wof:placetype":"venue"
},
  "geometry": {"coordinates":[6.6287441254,46.5175514221],"type":"Point"}
}