{
  "type": "Feature",
  "properties": {
    "iso:country":"CH",
    "sg:address":"Avenue Saint-fran\u00e7ois 3",
    "sg:city":"Sion",
    "sg:orig_category":"Religi\u00f6se Vereinigungen",
    "sg:postcode":"1950",
    "sg:province":"Valais",
    "wof:name":"Foi Chr\u00e9tienne Et Soci\u00e9t\u00e9.",
    "wof:placetype":"venue"
},
  "geometry": {"coordinates":[7.3582830429,46.2365646362],"type":"Point"}
}