{
  "type": "Feature",
  "properties": {
    "iso:country":"CH",
    "sg:address":"Holzh\u00e4usernstr. 1",
    "sg:city":"Rotkreuz",
    "sg:orig_category":"Herstellung von Akkumulatoren U Batterien",
    "sg:postcode":"6343",
    "sg:province":"Zug",
    "wof:name":"Powac Gmbh",
    "wof:placetype":"venue"
},
  "geometry": {"coordinates":[8.4660310745,47.1341400146],"type":"Point"}
}