{
  "type": "Feature",
  "properties": {
    "iso:country":"CH",
    "sg:address":"Rathausgasse 11",
    "sg:city":"Aarau",
    "sg:orig_category":"Detailhandel mit Bekleidung Detailhandel mit Sportartikeln",
    "sg:phone":"+41 62 825 07 14",
    "sg:postcode":"5000",
    "sg:province":"Aargau",
    "wof:name":"Wittmer & Zwahlen Sport-& Freizeitshop",
    "wof:placetype":"venue"
},
  "geometry": {"coordinates":[8.043707,47.392994],"type":"Point"}
}