{
  "type": "Feature",
  "properties": {
    "iso:country":"CH",
    "sg:address":"Bugnon Route Du 40",
    "sg:city":"Villars-sur-gl\u00e2ne",
    "sg:orig_category":"Sanit\u00e4r, Heizungs U L\u00fcftungsinstallation",
    "sg:postcode":"1752",
    "sg:province":"Fribourg",
    "wof:name":"Jean-pierre Neyroud, A. L\u00f6tscher Successeur",
    "wof:placetype":"venue"
},
  "geometry": {"coordinates":[5.1808700562,45.8973388672],"type":"Point"}
}