{
  "type": "Feature",
  "properties": {
    "iso:country":"CH",
    "sg:address":"Selnaustrasse 3 8002 Z\u00fcrich. Postfach",
    "sg:city":"Z\u00fcrich",
    "sg:orig_category":"Detailhandel mit B\u00fcchern, Zeitungen, Schreib U Papeteriewaren",
    "sg:postcode":"8001",
    "sg:province":"Z\u00fcrich",
    "wof:name":"Oekos-buchhandlung Und Heimatliches Kunsthandwerk Ag",
    "wof:placetype":"venue"
},
  "geometry": {"coordinates":[8.533341,47.369659],"type":"Point"}
}