{
  "type": "Feature",
  "properties": {
    "iso:country":"CH",
    "sg:address":"La Petite-joux",
    "sg:city":"Petit-martel",
    "sg:classifiers":[
        {
            "category":"Restaurant",
            "type":"Food & Drink"
        }
    ],
    "sg:phone":"+41 32 937 17 75",
    "sg:postcode":"2315",
    "wof:name":"Pinte De La Petite-joux",
    "wof:placetype":"venue"
},
  "geometry": {"coordinates":[6.7594099045,47.0115585327],"type":"Point"}
}