{
  "type": "Feature",
  "properties": {
    "iso:country":"CH",
    "sg:address":"Arsenaux Route Des 9 1700 Fribourg. Postfach",
    "sg:city":"Fribourg",
    "sg:orig_category":"Herstellung von Armaturen",
    "sg:phone":"+41 26 321 26 04",
    "sg:postcode":"1700",
    "sg:province":"Fribourg",
    "wof:name":"Alpa Plus S\u00e0rl Armatures; Pose D' Etc.",
    "wof:placetype":"venue"
},
  "geometry": {"coordinates":[7.1536831856,46.8037452698],"type":"Point"}
}