{
  "type": "Feature",
  "properties": {
    "iso:country":"CH",
    "sg:address":"Buobenmatt 2",
    "sg:city":"Luzern",
    "sg:classifiers":[
        {
            "category":"Restaurant",
            "type":"Food & Drink"
        }
    ],
    "sg:phone":"+41 41 210 83 77",
    "sg:postcode":"6003",
    "sg:province":"Luzern",
    "wof:name":"Wirtschaft Zur Ente",
    "wof:placetype":"venue"
},
  "geometry": {"coordinates":[8.3062953949,47.0499839783],"type":"Point"}
}