{
  "type": "Feature",
  "properties": {
    "iso:country":"CH",
    "sg:address":"Mayenfelserstrasse 56",
    "sg:city":"Pratteln",
    "sg:classifiers":[
        {
            "category":"Home & Garden",
            "subcategory":"Hardware",
            "type":"Retail Goods"
        }
    ],
    "sg:phone":"+41 91 943 38 31",
    "sg:postcode":"4133",
    "sg:province":"Basel-Landschaft",
    "sg:tags":[
        "equipment"
    ],
    "wof:name":"Davide - Giardini Sagl",
    "wof:placetype":"venue"
},
  "geometry": {"coordinates":[8.9564619064,46.0654716492],"type":"Point"}
}