{
  "type": "Feature",
  "properties": {
    "iso:country":"CH",
    "sg:address":"Rue Des Deux Fontaines 9",
    "sg:city":"Chernex",
    "sg:classifiers":[
        {
            "category":"Manufacturing",
            "subcategory":"Motor Vehicles & Parts",
            "type":"Manufacturing & Wholesale Goods"
        }
    ],
    "sg:phone":"+41 21 964 27 04",
    "sg:postcode":"1822",
    "sg:province":"Vaud",
    "sg:tags":[
        "electronic",
        "assembling",
        "component"
    ],
    "wof:name":"Briod Sa",
    "wof:placetype":"venue"
},
  "geometry": {"coordinates":[6.911131,46.443787],"type":"Point"}
}