{
  "type": "Feature",
  "properties": {
    "iso:country":"CH",
    "sg:address":"P\u00fcntstrasse 38",
    "sg:city":"Volketswil",
    "sg:orig_category":"Non-Classified Establishments",
    "sg:postcode":"8604",
    "sg:province":"Z\u00fcrich",
    "wof:name":"Apm Bundi Gmbh",
    "wof:placetype":"venue"
},
  "geometry": {"coordinates":[8.6847286224,47.4062232971],"type":"Point"}
}