{
  "type": "Feature",
  "properties": {
    "iso:country":"CH",
    "sg:address":"4436",
    "sg:city":"Liedertswil",
    "sg:orig_category":"Landesverteidigung, Sozialversicherung \u00d6ffentliche Verwaltung",
    "sg:phone":"+41 61 961 92 02",
    "sg:postcode":"4436",
    "sg:province":"Basel-Landschaft",
    "wof:name":"Zivilschutzstelle Liedertswil",
    "wof:placetype":"venue"
},
  "geometry": {"coordinates":[7.7193031311,47.391910553],"type":"Point"}
}