{
  "type": "Feature",
  "properties": {
    "addr:full":"Buchholzstrasse 74e 3604 Thun. Postfach 352 Thun 3606",
    "addr:housenumber":"74e;352",
    "addr:postcode":"3604 thun.;3606",
    "addr:street":"Buchholzstrasse;Postfach",
    "iso:country":"CH",
    "sg:address":"Buchholzstrasse 74e 3604 Thun. Postfach 352",
    "sg:city":"Thun",
    "sg:orig_category":"Ausbaugewerbe Bauinstallation",
    "sg:phone":"+41 33 335 80 80",
    "sg:postcode":"3606",
    "wof:name":"Sieber Verticaltec Spezialmontagen",
    "wof:placetype":"venue"
},
  "geometry": {"coordinates":[7.611185,46.735771],"type":"Point"}
}