{
  "type": "Feature",
  "properties": {
    "addr:full":"Alte Aarburgerstrasse 41 Rothrist Aargau 4852",
    "addr:housenumber":"41",
    "addr:postcode":"4852",
    "addr:street":"Alte Aarburgerstrasse",
    "iso:country":"CH",
    "sg:address":"Alte Aarburgerstrasse 41",
    "sg:city":"Rothrist",
    "sg:classifiers":[
        {
            "category":"Landmark",
            "subcategory":"Unesco World Heritage Site",
            "type":"Public Place"
        }
    ],
    "sg:phone":"+41 62 794 24 80",
    "sg:postcode":"4852",
    "sg:province":"Aargau",
    "sg:tags":[
        "programming",
        "database"
    ],
    "wof:name":"Nesto-software Ag",
    "wof:placetype":"venue"
},
  "geometry": {"coordinates":[7.883104,47.308235],"type":"Point"}
}