{
  "type": "Feature",
  "properties": {
    "iso:country":"CH",
    "sg:address":"Wassergrabe 6",
    "sg:city":"Sursee",
    "sg:orig_category":"Versicherungen Generalagenturen",
    "sg:phone":"+41 41 922 13 33",
    "sg:postcode":"6210",
    "sg:province":"Luzern",
    "wof:name":"Ms Makler Service Ag Selbst\u00e4ndige Generalagentur",
    "wof:placetype":"venue"
},
  "geometry": {"coordinates":[8.1088123322,47.1839179993],"type":"Point"}
}