{
  "type": "Feature",
  "properties": {
    "iso:country":"CH",
    "sg:address":"Pratifori Avenue De 8",
    "sg:city":"Sion",
    "sg:orig_category":"Vermietung U Verpachtung von eigenen Immobilien",
    "sg:postcode":"1950",
    "sg:province":"Valais",
    "wof:name":"Fidinvest Sa",
    "wof:placetype":"venue"
},
  "geometry": {"coordinates":[7.3572969437,46.2313117981],"type":"Point"}
}