{
  "type": "Feature",
  "properties": {
    "iso:country":"CH",
    "sg:address":"Monruz Rue De 36",
    "sg:city":"Neuch\u00e2tel",
    "sg:orig_category":"Herstellung von Spielwaren",
    "sg:phone":"+41 32 724 32 60",
    "sg:postcode":"2000",
    "sg:province":"Neuch\u00e2tel",
    "wof:name":"Lucsaj, Eliane Shaibi & Yoel Gat",
    "wof:placetype":"venue"
},
  "geometry": {"coordinates":[6.9617810249,47.0047187805],"type":"Point"}
}