{
  "type": "Feature",
  "properties": {
    "iso:country":"CH",
    "sg:address":"K\u00fcfergasse 2",
    "sg:city":"H\u00fcntwangen",
    "sg:orig_category":"Detailhandel mit Brot, Back U S\u00fcsswaren",
    "sg:phone":"+41 18690330",
    "sg:postcode":"8194",
    "sg:province":"Z\u00fcrich",
    "wof:name":"Paride Loffredo B\u00e4ckerei-konditorei",
    "wof:placetype":"venue"
},
  "geometry": {"coordinates":[8.491175,47.595654],"type":"Point"}
}