{
  "type": "Feature",
  "properties": {
    "iso:country":"CH",
    "sg:address":"Seestrasse 38 6442 Gersau. Postfach 142",
    "sg:city":"Gersau",
    "sg:classifiers":[
        {
            "category":"Restaurant",
            "type":"Food & Drink"
        }
    ],
    "sg:phone":"+41 41 828 15 15",
    "sg:postcode":"6442",
    "sg:province":"Schwyz",
    "wof:name":"Restaurant Wehri",
    "wof:placetype":"venue"
},
  "geometry": {"coordinates":[8.5231590271,46.9927558899],"type":"Point"}
}