{
  "type": "Feature",
  "properties": {
    "iso:country":"CH",
    "sg:address":"Dorfstrasse 29",
    "sg:city":"Asp",
    "sg:orig_category":"Vereine Milit\u00e4r",
    "sg:phone":"+41 62 878 18 88",
    "sg:postcode":"5025",
    "sg:province":"Aargau",
    "wof:name":"Uov Bezirk Lenzburg",
    "wof:placetype":"venue"
},
  "geometry": {"coordinates":[8.0499782562,47.4439544678],"type":"Point"}
}