{
  "type": "Feature",
  "properties": {
    "iso:country":"CH",
    "sg:address":"Falkenweg 15",
    "sg:city":"Baar",
    "sg:orig_category":"Physiotherapie",
    "sg:phone":"+41 41 761 76 66",
    "sg:postcode":"6340",
    "sg:province":"Zug",
    "wof:name":"Physiotherapie Oberdorf",
    "wof:placetype":"venue"
},
  "geometry": {"coordinates":[8.5277385712,47.1964759827],"type":"Point"}
}