{
  "type": "Feature",
  "properties": {
    "iso:country":"CH",
    "sg:address":"Glattalstrasse 198",
    "sg:city":"R\u00fcmlang",
    "sg:orig_category":"Elektroinstallation",
    "sg:phone":"+41 18172106",
    "sg:postcode":"8153",
    "sg:province":"Z\u00fcrich",
    "wof:name":"V\u00f6geli Elektro Ag",
    "wof:placetype":"venue"
},
  "geometry": {"coordinates":[8.5296363831,47.4499588013],"type":"Point"}
}