{
  "type": "Feature",
  "properties": {
    "iso:country":"CH",
    "sg:address":"Bahnhofstrasse 15 6362 Stansstad. Postfach 154",
    "sg:city":"Stansstad",
    "sg:orig_category":"Vermittlung von Immobilien Wirtschaftspr\u00fcfung, Steuerberatung U Treuhand",
    "sg:phone":"+41 41 610 71 62",
    "sg:postcode":"6362",
    "sg:province":"Nidwalden",
    "wof:name":"Verfina Immobilien Treuhand Ag",
    "wof:placetype":"venue"
},
  "geometry": {"coordinates":[8.337521553,46.9776954651],"type":"Point"}
}