{
  "type": "Feature",
  "properties": {
    "iso:country":"CH",
    "sg:address":"H\u00fcnikerstrasse 23 5425 Schneisingen. Postfach",
    "sg:city":"Unterehrendingen",
    "sg:orig_category":"Herstellung von Metallkonstruktionen",
    "sg:postcode":"5424",
    "wof:name":"Montani Metallbau & Schweisskonstruktion",
    "wof:placetype":"venue"
},
  "geometry": {"coordinates":[8.3685445786,47.5168533325],"type":"Point"}
}