{
  "type": "Feature",
  "properties": {
    "iso:country":"CH",
    "sg:address":"David Hessweg 12",
    "sg:city":"Z\u00fcrich",
    "sg:orig_category":"Erbringung von sonstigen Dienstleistungen f\u00fcr Unternehmen",
    "sg:phone":"+41 14826854",
    "sg:postcode":"8038",
    "sg:province":"Z\u00fcrich",
    "wof:name":"Roger Koch-consulting Koch Roger",
    "wof:placetype":"venue"
},
  "geometry": {"coordinates":[8.531206131,47.3342132568],"type":"Point"}
}