{
  "type": "Feature",
  "properties": {
    "iso:country":"CH",
    "sg:address":"St-julien Route De 78 1212 Grand-lancy. Postfach",
    "sg:city":"Cointrin",
    "sg:orig_category":"Sonstiger Grosshandel",
    "sg:postcode":"1216",
    "sg:province":"Gen\u00e8ve",
    "wof:name":"Autos Evasion S\u00e0rl",
    "wof:placetype":"venue"
},
  "geometry": {"coordinates":[6.1266708374,46.1729812622],"type":"Point"}
}