{
  "type": "Feature",
  "properties": {
    "iso:country":"CH",
    "sg:address":"1185",
    "sg:city":"Mont-sur-rolle",
    "sg:orig_category":"Dauerkulturbau Rebbau",
    "sg:phone":"+41 21 825 14 19",
    "sg:postcode":"1185",
    "sg:province":"Vaud",
    "wof:name":"Soci\u00e9t\u00e9 Des Caves De Producteurs Mont-f\u00e9chy",
    "wof:placetype":"venue"
},
  "geometry": {"coordinates":[6.33798,46.47279],"type":"Point"}
}