{
  "type": "Feature",
  "properties": {
    "addr:full":"Luzernerstrasse 2 Dornach Solothurn 4143",
    "addr:housenumber":"2",
    "addr:postcode":"4143",
    "addr:street":"Luzernerstrasse",
    "iso:country":"CH",
    "sg:address":"Luzernerstrasse 2",
    "sg:city":"Dornach",
    "sg:orig_category":"Architekturb\u00fcros",
    "sg:phone":"+41 61 701 71 65",
    "sg:postcode":"4143",
    "sg:province":"Solothurn",
    "wof:name":"Hans Georg Braun Architekturb\u00fcro",
    "wof:placetype":"venue"
},
  "geometry": {"coordinates":[7.624174,47.480476],"type":"Point"}
}