{
  "type": "Feature",
  "properties": {
    "iso:country":"CH",
    "sg:address":"Kirchstrasse 6",
    "sg:city":"Freienbach",
    "sg:orig_category":"Non-Classified Establishments",
    "sg:postcode":"8807",
    "sg:province":"Schwyz",
    "wof:name":"Ace Medien Ag",
    "wof:placetype":"venue"
},
  "geometry": {"coordinates":[8.7264680862,47.1954345703],"type":"Point"}
}