{
  "type": "Feature",
  "properties": {
    "iso:country":"CH",
    "sg:address":"Gerliswilstrasse 66",
    "sg:city":"Emmenbr\u00fccke",
    "sg:orig_category":"Non-Classified Establishments",
    "sg:postcode":"6020",
    "sg:province":"Luzern",
    "wof:name":"Agm Malergesch\u00e4ft A. Gotadoro",
    "wof:placetype":"venue"
},
  "geometry": {"coordinates":[9.3848800659,47.4170227051],"type":"Point"}
}