{
  "type": "Feature",
  "properties": {
    "iso:country":"CH",
    "sg:address":"Obere Milken Sangernboden 3158 Guggisberg. Postfach",
    "sg:city":"Guggisberg",
    "sg:orig_category":"Architektur U Ingenieurb\u00fcros",
    "sg:phone":"+41 26 419 32 90",
    "sg:postcode":"3158",
    "sg:province":"Bern",
    "wof:name":"Ingenieurb\u00fcro Und Unternehmungsberatungs Gmbh",
    "wof:placetype":"venue"
},
  "geometry": {"coordinates":[7.341563,46.715553],"type":"Point"}
}