{
  "type": "Feature",
  "properties": {
    "iso:country":"CH",
    "sg:address":"Burenb\u00fcel 16",
    "sg:city":"Fehraltorf",
    "sg:orig_category":"Kauf U Verkauf von Immobilien auf eigene Rechnung",
    "sg:postcode":"8320",
    "sg:province":"Z\u00fcrich",
    "wof:name":"Klemenz, Immobilien-treuhand & -beratung",
    "wof:placetype":"venue"
},
  "geometry": {"coordinates":[8.7595262527,47.3839530945],"type":"Point"}
}