{
  "type": "Feature",
  "properties": {
    "iso:country":"CH",
    "sg:address":"L\u00f6wenburg",
    "sg:city":"Ederswiler",
    "sg:orig_category":"Landwirtschaft, Jagd U damit verbundene Dienstleistungen",
    "sg:phone":"+41 32 431 12 20",
    "sg:postcode":"2813",
    "sg:province":"Jura",
    "wof:name":"Christoph Merian Stiftung Gutsbetrieb",
    "wof:placetype":"venue"
},
  "geometry": {"coordinates":[7.3326449394,47.4250259399],"type":"Point"}
}