{
  "type": "Feature",
  "properties": {
    "iso:country":"CH",
    "sg:address":"Wehntalerstrasse 197d",
    "sg:city":"Z\u00fcrich",
    "sg:orig_category":"Sonstiger Grosshandel",
    "sg:postcode":"8057",
    "sg:province":"Z\u00fcrich",
    "wof:name":"Folini H. Warenhandel, Autoreinigungsarbeiten",
    "wof:placetype":"venue"
},
  "geometry": {"coordinates":[8.5313577652,47.4065666199],"type":"Point"}
}