{
  "type": "Feature",
  "properties": {
    "iso:country":"CH",
    "sg:address":"Rue De La Palud 4a 1955 Chamoson. Postfach",
    "sg:city":"Chamoson",
    "sg:orig_category":"Non-Classified Establishments",
    "sg:postcode":"1955",
    "sg:province":"Valais",
    "wof:name":"Putallaz Serge",
    "wof:placetype":"venue"
},
  "geometry": {"coordinates":[7.2235321999,46.1992530823],"type":"Point"}
}