{
  "type": "Feature",
  "properties": {
    "iso:country":"CH",
    "sg:address":"Baarerstrasse 63 6300 Zug. Postfach",
    "sg:city":"Zug",
    "sg:orig_category":"Markt U Meinungsforschung",
    "sg:postcode":"6300",
    "sg:province":"Zug",
    "wof:name":"Northern Seafood Gmbh Beratungsdienstleistungen Im Ber. Marketing, Bes. F\u00fcr Seafood Usw",
    "wof:placetype":"venue"
},
  "geometry": {"coordinates":[8.5173740387,47.1761703491],"type":"Point"}
}