{
  "type": "Feature",
  "properties": {
    "iso:country":"CH",
    "sg:address":"Hauptstr. 21",
    "sg:city":"Glarus",
    "sg:classifiers":[
        {
            "category":"Banks & Credit Unions",
            "subcategory":"Bank",
            "type":"Services"
        }
    ],
    "sg:phone":"+41 55 646 71 11",
    "sg:postcode":"8750",
    "sg:province":"Glarus",
    "wof:name":"Glarner Kantonalbank",
    "wof:placetype":"venue"
},
  "geometry": {"coordinates":[9.068344,47.039185],"type":"Point"}
}