{
  "type": "Feature",
  "properties": {
    "iso:country":"CH",
    "sg:address":"Hauptstrasse 48 6260 Reiden. Postfach",
    "sg:city":"Reiden",
    "sg:orig_category":"Kantonalbanken",
    "sg:phone":"+41 62 749 55 55",
    "sg:postcode":"6260",
    "sg:province":"Luzern",
    "wof:name":"Luzerner Kantonalbank",
    "wof:placetype":"venue"
},
  "geometry": {"coordinates":[7.9714989662,47.2475547791],"type":"Point"}
}