{
  "type": "Feature",
  "properties": {
    "iso:country":"CH",
    "sg:address":"Tulpenweg 26",
    "sg:city":"Biel/bienne",
    "sg:orig_category":"Detailhandel mit Musikinstrumenten",
    "sg:phone":"+41 32 365 40 91",
    "sg:postcode":"2503",
    "sg:province":"Bern",
    "wof:name":"Samuel Andres Klavierfachgesch\u00e4ft",
    "wof:placetype":"venue"
},
  "geometry": {"coordinates":[7.2587909698,47.1365966797],"type":"Point"}
}