{
  "type": "Feature",
  "properties": {
    "iso:country":"CH",
    "sg:address":"Stockmatt",
    "sg:city":"R\u00fcschegg",
    "sg:classifiers":[
        {
            "category":"Banks & Credit Unions",
            "subcategory":"Bank",
            "type":"Services"
        }
    ],
    "sg:phone":"+41 33 453 12 21",
    "sg:postcode":"3154",
    "sg:province":"Bern",
    "wof:name":"Raiffeisenbank Schwarzenegg",
    "wof:placetype":"venue"
},
  "geometry": {"coordinates":[7.71831,46.794979],"type":"Point"}
}