{
  "type": "Feature",
  "properties": {
    "iso:country":"CH",
    "sg:address":"Dorfstrasse 21",
    "sg:city":"Urdorf",
    "sg:orig_category":"Architektur U Ingenieurb\u00fcros",
    "sg:postcode":"8902",
    "sg:province":"Z\u00fcrich",
    "wof:name":"Ingenieurb\u00fcro Rhyner",
    "wof:placetype":"venue"
},
  "geometry": {"coordinates":[8.415915,47.389965],"type":"Point"}
}