{
  "type": "Feature",
  "properties": {
    "iso:country":"CH",
    "sg:address":"Cit\u00e9-derri\u00e8re Rue 12",
    "sg:city":"Lausanne",
    "sg:orig_category":"Schreib U \u00dcbersetzungsb\u00fcros",
    "sg:phone":"+41 21 320 82 03",
    "sg:postcode":"1005",
    "sg:province":"Vaud",
    "wof:name":"Van Bogaert Olivier",
    "wof:placetype":"venue"
},
  "geometry": {"coordinates":[6.6360940933,46.5232582092],"type":"Point"}
}