{
  "type": "Feature",
  "properties": {
    "iso:country":"CH",
    "sg:address":"Seestrasse 49",
    "sg:city":"Z\u00fcrich",
    "sg:orig_category":"Arztpraxen",
    "sg:phone":"+41 12862020",
    "sg:postcode":"8002",
    "sg:province":"Z\u00fcrich",
    "wof:name":"Dres Med. Stoffel & Muller Spezial\u00e4rzte Fmh",
    "wof:placetype":"venue"
},
  "geometry": {"coordinates":[8.531501,47.362202],"type":"Point"}
}