{
  "type": "Feature",
  "properties": {
    "iso:country":"CH",
    "sg:address":"Balmhofmatte",
    "sg:city":"Brienzwiler",
    "sg:orig_category":"Instandhaltung U Reparatur von Automobilen",
    "sg:phone":"+41 33 951 11 20",
    "sg:postcode":"3856",
    "sg:province":"Bern",
    "wof:name":"Daniel Homberger",
    "wof:placetype":"venue"
},
  "geometry": {"coordinates":[8.0902853012,46.7459335327],"type":"Point"}
}