{
  "type": "Feature",
  "properties": {
    "iso:country":"CH",
    "sg:address":"Burgstrasse 26",
    "sg:city":"Glarus",
    "sg:orig_category":"Unclassifiable Establishments",
    "sg:postcode":"8750",
    "sg:province":"Glarus",
    "wof:name":"Hetflejs Dog Tools",
    "wof:placetype":"venue"
},
  "geometry": {"coordinates":[8.7928409576,47.5513687134],"type":"Point"}
}