{
  "type": "Feature",
  "properties": {
    "iso:country":"CH",
    "sg:address":"Gerbergasse 26 4001 Basel. Postfach",
    "sg:city":"Basel",
    "sg:orig_category":"Interessenvertretungen",
    "sg:phone":"+41 61 261 45 45",
    "sg:postcode":"4001",
    "sg:province":"Basel-Stadt",
    "wof:name":"Pro Scientia F\u00f6rderung V. Wissenschaftl. Studien, Stipendien An Studenten U. Privatdozenten D. Basler Universit\u00e4t",
    "wof:placetype":"venue"
},
  "geometry": {"coordinates":[7.5882058144,47.5568313599],"type":"Point"}
}