{
  "type": "Feature",
  "properties": {
    "iso:country":"CH",
    "sg:address":"Rue Du Casino 1",
    "sg:city":"Yverdon-les-bains",
    "sg:orig_category":"Sonstige k\u00fcnstlerische U schriftstellerische T\u00e4tigkeiten U Darbietungen",
    "sg:phone":"+41 26 413 44 42",
    "sg:postcode":"1400",
    "sg:province":"Vaud",
    "wof:name":"Pots Fink Topf Peter Fink",
    "wof:placetype":"venue"
},
  "geometry": {"coordinates":[7.1448669434,46.7549171448],"type":"Point"}
}