{
  "type": "Feature",
  "properties": {
    "iso:country":"CH",
    "sg:address":"Egelseestrasse 4",
    "sg:city":"Dietikon",
    "sg:orig_category":"Architektur U Ingenieurb\u00fcros",
    "sg:postcode":"8953",
    "sg:province":"Z\u00fcrich",
    "wof:name":"Stefan M\u00fcller, Ingenieurb\u00fcro F\u00fcr Unix Und Informatik",
    "wof:placetype":"venue"
},
  "geometry": {"coordinates":[8.388091,47.400242],"type":"Point"}
}