{
  "type": "Feature",
  "properties": {
    "iso:country":"CH",
    "sg:address":"Zehntenstrasse 20",
    "sg:city":"Pratteln",
    "sg:orig_category":"Grosshandel mit Nahrungsmitteln, Getr\u00e4nken U Tabakwaren ohne ausgepr\u00e4gten Schwerpunkt",
    "sg:postcode":"4133",
    "sg:province":"Basel-Landschaft",
    "wof:name":"Kraft Foods Schweiz Ag, Zweigniederlassung Pratteln",
    "wof:placetype":"venue"
},
  "geometry": {"coordinates":[7.6948032379,47.5226211548],"type":"Point"}
}