{
  "type": "Feature",
  "properties": {
    "iso:country":"CH",
    "sg:address":"Bachserstrasse",
    "sg:city":"Stadel",
    "sg:orig_category":"Bauschreinerei Innenausbau",
    "sg:phone":"+41 18582147",
    "sg:postcode":"8174",
    "sg:province":"Z\u00fcrich",
    "wof:name":"Albert Frei Schreinerei & Innenausbau",
    "wof:placetype":"venue"
},
  "geometry": {"coordinates":[8.451872,47.525394],"type":"Point"}
}