{
  "type": "Feature",
  "properties": {
    "iso:country":"CH",
    "sg:address":"Zugerstrasse 4",
    "sg:city":"Steinhausen",
    "sg:orig_category":"Herstellung von k\u00e4lte U lufttechnischen Erzeugnissen f\u00fcr gewerbliche Zwecke",
    "sg:phone":"+41 19414457",
    "sg:postcode":"6312",
    "sg:province":"Zug",
    "wof:name":"Airtag Engineering Ag Drucklufttechnik, Kompressoren",
    "wof:placetype":"venue"
},
  "geometry": {"coordinates":[8.7102203369,47.3563613892],"type":"Point"}
}