{
  "type": "Feature",
  "properties": {
    "addr:full":"Allwegmatte 4 Ennetmoos Nidwalden 6372",
    "addr:housenumber":"4",
    "addr:postcode":"6372",
    "addr:street":"Allwegmatte",
    "iso:country":"CH",
    "sg:address":"Allwegmatte 4",
    "sg:city":"Ennetmoos",
    "sg:orig_category":"Bau von Strassen, Sportanlagen U Bahnverkehrsstrecken",
    "sg:postcode":"6372",
    "sg:province":"Nidwalden",
    "wof:name":"Strassengenossenschaft Allwegmatte",
    "wof:placetype":"venue"
},
  "geometry": {"coordinates":[8.335554,46.95723],"type":"Point"}
}