{
  "type": "Feature",
  "properties": {
    "iso:country":"CH",
    "sg:address":"Laubbergstrasse 6",
    "sg:city":"Glattfelden",
    "sg:orig_category":"Detailhandel mit Fahrr\u00e4dern Handel mit Motorr\u00e4dern, Teilen U Zubeh\u00f6r Instandhaltung U Reparatur von ",
    "sg:phone":"+41 71 744 12 18",
    "sg:postcode":"8192",
    "sg:province":"Z\u00fcrich",
    "wof:name":"Robert Keller Velos Motos",
    "wof:placetype":"venue"
},
  "geometry": {"coordinates":[9.630572319,47.453666687],"type":"Point"}
}