{
  "type": "Feature",
  "properties": {
    "iso:country":"CH",
    "sg:address":"Balgacherstrasse 22",
    "sg:city":"Heerbrugg",
    "sg:orig_category":"G\u00fcterbef\u00f6rderung im Strassenverkehr",
    "sg:phone":"+41 71 722 10 35",
    "sg:postcode":"9435",
    "sg:province":"St. Gallen",
    "wof:name":"Arnold Schmidheiny Transportunternehmung",
    "wof:placetype":"venue"
},
  "geometry": {"coordinates":[9.6255702972,47.4110412598],"type":"Point"}
}