{
  "type": "Feature",
  "properties": {
    "iso:country":"CH",
    "sg:address":"Badenerstrasse 116 8952 Schlieren. Postfach",
    "sg:city":"Schlieren",
    "sg:orig_category":"Handelsvermittlung U Grosshandel Pharmazeutische Industrie",
    "sg:phone":"+41 17554070",
    "sg:postcode":"8952",
    "sg:province":"Z\u00fcrich",
    "wof:name":"Marbert Ag, D\u00fcsseldorf, Zweigniederlassung Schlieren Zweigniederlassung Schlieren",
    "wof:placetype":"venue"
},
  "geometry": {"coordinates":[8.4306726456,47.3973083496],"type":"Point"}
}