{
  "type": "Feature",
  "properties": {
    "iso:country":"CH",
    "sg:address":"Aarburgerstrasse 84 4600 Olten. Postfach",
    "sg:city":"Olten",
    "sg:orig_category":"Detektivb\u00fcros U \u00dcberwachung",
    "sg:phone":"+41 62 286 64 64",
    "sg:postcode":"4601",
    "sg:province":"Solothurn",
    "wof:name":"Securitas Ag Schweizerische Bewachungsgesellschaft, Filiale Olten",
    "wof:placetype":"venue"
},
  "geometry": {"coordinates":[7.9065899849,47.3458786011],"type":"Point"}
}