{
  "type": "Feature",
  "properties": {
    "iso:country":"CH",
    "sg:address":"Blumenrain 8 4051 Basel. Postfach",
    "sg:city":"Basel",
    "sg:classifiers":[
        {
            "category":"Travel",
            "subcategory":"Hotels & Motels",
            "type":"Entertainment"
        }
    ],
    "sg:phone":"+41 61 260 50 50",
    "sg:postcode":"4001",
    "sg:province":"Basel-Stadt",
    "sg:tags":[
        "hotels",
        "mit",
        "restaurant"
    ],
    "wof:name":"Hotel Drei K\u00f6nige Am Rhein",
    "wof:placetype":"venue"
},
  "geometry": {"coordinates":[7.587532,47.560509],"type":"Point"}
}