{
  "type": "Feature",
  "properties": {
    "iso:country":"CH",
    "sg:address":"Im Kirchbrunnen 4",
    "sg:city":"R\u00fcmlang",
    "sg:orig_category":"Reiseb\u00fcros U Reiseveranstalter",
    "sg:postcode":"8153",
    "sg:province":"Z\u00fcrich",
    "wof:name":"Montair, Bienz-sabljic Reisen, Ferien; Vermittlung",
    "wof:placetype":"venue"
},
  "geometry": {"coordinates":[8.2779712677,46.9444618225],"type":"Point"}
}