{
  "type": "Feature",
  "properties": {
    "iso:country":"CH",
    "sg:address":"Via Luganetto 2",
    "sg:city":"Viganello",
    "sg:orig_category":"Fernmeldedienste",
    "sg:postcode":"6962",
    "sg:province":"Ticino",
    "wof:name":"Audiofon Gesellschaft F\u00fcr Professionelle Audiotex-anwendungen Mbh Direktmarketing-dienstl. Bes. Call-center-dienstl. Usw",
    "wof:placetype":"venue"
},
  "geometry": {"coordinates":[9.6406002045,47.4368247986],"type":"Point"}
}