{
  "type": "Feature",
  "properties": {
    "iso:country":"CH",
    "sg:address":"Uetlibergstrasse 54 8045 Z\u00fcrich. Postfach",
    "sg:city":"Z\u00fcrich",
    "sg:orig_category":"Finanzierungsinstitutionen",
    "sg:phone":"+41 14625000",
    "sg:postcode":"8045",
    "sg:province":"Z\u00fcrich",
    "wof:name":"Term Finanz Ag Finanzgesch\u00e4fte Usw",
    "wof:placetype":"venue"
},
  "geometry": {"coordinates":[8.518995285,47.3629379272],"type":"Point"}
}