{
  "type": "Feature",
  "properties": {
    "iso:country":"CH",
    "sg:address":"Pisciculture Route De La 6",
    "sg:city":"Fribourg",
    "sg:orig_category":"Korrespondenz U Nachrichtenb\u00fcros, selbst\u00e4ndige Journalisten",
    "sg:phone":"+41 79 206 44 09",
    "sg:postcode":"1700",
    "sg:province":"Fribourg",
    "wof:name":"Photographica - Vullo M.",
    "wof:placetype":"venue"
},
  "geometry": {"coordinates":[7.1591668129,46.7862052917],"type":"Point"}
}