{
  "type": "Feature",
  "properties": {
    "iso:country":"CH",
    "sg:address":"Boissonnet Chemin De 33",
    "sg:city":"Lausanne",
    "sg:orig_category":"Werbung",
    "sg:postcode":"1010",
    "sg:province":"Vaud",
    "wof:name":"Propaganda, D'amico Ignazia",
    "wof:placetype":"venue"
},
  "geometry": {"coordinates":[6.6459021568,46.5378494263],"type":"Point"}
}