{
  "type": "Feature",
  "properties": {
    "iso:country":"CH",
    "sg:address":"Zentralstrasse 94",
    "sg:city":"Neuhausen",
    "sg:orig_category":"Kosmetikinstitute",
    "sg:phone":"+41 52 672 51 85",
    "sg:postcode":"8212",
    "sg:province":"Schaffhausen",
    "wof:name":"Giorgio & Rosmarie Angelini Kosmetikinstitut",
    "wof:placetype":"venue"
},
  "geometry": {"coordinates":[8.62159729,47.6833877563],"type":"Point"}
}