{
  "type": "Feature",
  "properties": {
    "iso:country":"CH",
    "sg:address":"Kirchgasse 7",
    "sg:city":"Kloten",
    "sg:orig_category":"K\u00fcnstlerische Schulen",
    "sg:phone":"+41 18151274",
    "sg:postcode":"8302",
    "sg:province":"Z\u00fcrich",
    "wof:name":"Musikschule Bassersdorf-kloten Sekretariat",
    "wof:placetype":"venue"
},
  "geometry": {"coordinates":[8.5826120377,47.4510650635],"type":"Point"}
}