{
  "type": "Feature",
  "properties": {
    "iso:country":"CH",
    "sg:address":"Hafenstr. 120",
    "sg:city":"Birsfelden",
    "sg:classifiers":[
        {
            "category":"Manufacturing",
            "subcategory":"Rubber & Plastics",
            "type":"Manufacturing & Wholesale Goods"
        }
    ],
    "sg:phone":"+41 61 315 77 88",
    "sg:postcode":"4127",
    "sg:province":"Basel-Landschaft",
    "sg:tags":[
        "packaging",
        "material",
        "-",
        "paper",
        "cardboard"
    ],
    "wof:name":"Migros Betriebe Birsfelden Ag",
    "wof:placetype":"venue"
},
  "geometry": {"coordinates":[7.6348347664,47.5576286316],"type":"Point"}
}