{
  "type": "Feature",
  "properties": {
    "iso:country":"CH",
    "sg:address":"Chemin Des Bluets 5",
    "sg:city":"Pully",
    "sg:orig_category":"Sonstiger Grosshandel",
    "sg:phone":"+41 21 729 66 80",
    "sg:postcode":"1009",
    "sg:province":"Vaud",
    "wof:name":"Euramsud Promotions-services S\u00e0rl",
    "wof:placetype":"venue"
},
  "geometry": {"coordinates":[6.663588047,46.522983551],"type":"Point"}
}