{
  "type": "Feature",
  "properties": {
    "iso:country":"CH",
    "sg:address":"Besso Via 7",
    "sg:city":"Lugano",
    "sg:orig_category":"Allgemeiner Hoch U Tiefbau",
    "sg:phone":"+41 91 967 69 33",
    "sg:postcode":"6900",
    "sg:province":"Ticino",
    "wof:name":"Sicim Spa, Busseto (i), Succursale Di Lugano",
    "wof:placetype":"venue"
},
  "geometry": {"coordinates":[8.943768,46.005856],"type":"Point"}
}