{
  "type": "Feature",
  "properties": {
    "addr:full":"Br\u00fcckenstrasse 5d Kreuzlingen Thurgau 8280",
    "addr:housenumber":"5d",
    "addr:postcode":"8280",
    "addr:street":"Brueckenstrasse",
    "iso:country":"CH",
    "sg:address":"Br\u00fcckenstrasse 5d",
    "sg:city":"Kreuzlingen",
    "sg:orig_category":"Architektur U Ingenieurb\u00fcros",
    "sg:phone":"+41 71 672 81 61",
    "sg:postcode":"8280",
    "sg:province":"Thurgau",
    "wof:name":"Rickenbach Engineering",
    "wof:placetype":"venue"
},
  "geometry": {"coordinates":[9.171757,47.654213],"type":"Point"}
}