{
  "type": "Feature",
  "properties": {
    "iso:country":"CH",
    "sg:address":"Avenue Wendt 56",
    "sg:city":"Gen\u00e8ve",
    "sg:orig_category":"Textilveredlung",
    "sg:postcode":"1203",
    "sg:province":"Gen\u00e8ve",
    "wof:name":"S. Ortelli",
    "wof:placetype":"venue"
},
  "geometry": {"coordinates":[6.1283340454,46.2124328613],"type":"Point"}
}