{
  "type": "Feature",
  "properties": {
    "iso:country":"CH",
    "sg:address":"Helvetiaplatz 5 3005 Bern. Postfach",
    "sg:city":"Bern",
    "sg:orig_category":"Museen",
    "sg:postcode":"3005",
    "sg:province":"Bern",
    "wof:name":"Orientalische Sammlung Henri Moser, Charlottenfels, Im Bernischen Historischen Museum",
    "wof:placetype":"venue"
},
  "geometry": {"coordinates":[7.4490981102,46.9435005188],"type":"Point"}
}