{
  "type": "Feature",
  "properties": {
    "iso:country":"CH",
    "sg:address":"Gr\u00fcttmoos",
    "sg:city":"H\u00e4usernmoos",
    "sg:orig_category":"Non-Classified Establishments",
    "sg:postcode":"3463",
    "sg:province":"Bern",
    "wof:name":"Christen Gmbh Leitern Und Zaunfabrikation",
    "wof:placetype":"venue"
},
  "geometry": {"coordinates":[7.7493782043,47.0795173645],"type":"Point"}
}