{
  "type": "Feature",
  "properties": {
    "iso:country":"CH",
    "sg:address":"Fichtenstrasse 25 6020 Emmenbr\u00fccke. Postfach",
    "sg:city":"Emmenbr\u00fccke",
    "sg:orig_category":"Elektroinstallation",
    "sg:postcode":"6020",
    "sg:province":"Luzern",
    "wof:name":"Elroh Gmbh",
    "wof:placetype":"venue"
},
  "geometry": {"coordinates":[8.2914896011,47.0712814331],"type":"Point"}
}