{
  "type": "Feature",
  "properties": {
    "iso:country":"CH",
    "sg:address":"M\u00fchlenplatz 12",
    "sg:city":"Luzern",
    "sg:classifiers":[
        {
            "category":"Restaurant",
            "type":"Food & Drink"
        }
    ],
    "sg:phone":"+41 41 410 17 91",
    "sg:postcode":"6004",
    "sg:province":"Luzern",
    "wof:name":"Restaurant Mama Leone",
    "wof:placetype":"venue"
},
  "geometry": {"coordinates":[8.3032226562,47.052116394],"type":"Point"}
}