{
  "type": "Feature",
  "properties": {
    "iso:country":"CH",
    "sg:address":"Romanshornstrasse 17",
    "sg:city":"Sulgen",
    "sg:orig_category":"Non-Classified Establishments",
    "sg:postcode":"8583",
    "sg:province":"Thurgau",
    "wof:name":"Erich Keller Pro Communication",
    "wof:placetype":"venue"
},
  "geometry": {"coordinates":[9.1536808014,47.5668830872],"type":"Point"}
}