{
  "type": "Feature",
  "properties": {
    "iso:country":"CH",
    "sg:address":"Feldstrasse 27 5436 W\u00fcrenlos. Postfach 222",
    "sg:city":"Z\u00fcrich",
    "sg:orig_category":"Sportvereine",
    "sg:phone":"+41 56 424 14 86",
    "sg:postcode":"8049",
    "sg:province":"Z\u00fcrich",
    "wof:name":"Sportverein H\u00f6ngg Svh",
    "wof:placetype":"venue"
},
  "geometry": {"coordinates":[8.3687782288,47.4403686523],"type":"Point"}
}