{
  "type": "Feature",
  "properties": {
    "iso:country":"CH",
    "sg:address":"Rue De La Calle 42",
    "sg:city":"Onex",
    "sg:orig_category":"Sonstige Kultur U Unterhaltungseinrichtungen",
    "sg:phone":"+41 22 793 72 72",
    "sg:postcode":"1213",
    "sg:province":"Gen\u00e8ve",
    "wof:name":"Caf\u00e9 Le Danseur",
    "wof:placetype":"venue"
},
  "geometry": {"coordinates":[6.1046738625,46.1919212341],"type":"Point"}
}