{
  "type": "Feature",
  "properties": {
    "iso:country":"CH",
    "sg:address":"Spyrweg 3",
    "sg:city":"Ruswil",
    "sg:orig_category":"Erschliessung von Grundst\u00fccken",
    "sg:postcode":"6017",
    "sg:province":"Luzern",
    "wof:name":"Genossenschaft F\u00fcr Sozialen Wohnungsbau Ruswil",
    "wof:placetype":"venue"
},
  "geometry": {"coordinates":[8.1268129349,47.0825195312],"type":"Point"}
}