{
  "type": "Feature",
  "properties": {
    "iso:country":"CH",
    "sg:address":"Fontaines 2",
    "sg:city":"Boudevilliers",
    "sg:orig_category":"G\u00fcterbef\u00f6rderung im Strassenverkehr",
    "sg:phone":"+41 79 637 10 29",
    "sg:postcode":"2043",
    "sg:province":"Neuch\u00e2tel",
    "wof:name":"Christian Delley Transports",
    "wof:placetype":"venue"
},
  "geometry": {"coordinates":[6.8900980949,47.0291137695],"type":"Point"}
}