{
  "type": "Feature",
  "properties": {
    "iso:country":"CH",
    "sg:address":"Spitalstrasse 1 7430 Thusis. Postfach",
    "sg:city":"Thusis",
    "sg:orig_category":"Arztpraxen",
    "sg:phone":"+41 81 651 51 61",
    "sg:postcode":"7430",
    "sg:province":"Graubunden",
    "wof:name":"Dr.med.trifone Ingellis Spezialarzt Fmh",
    "wof:placetype":"venue"
},
  "geometry": {"coordinates":[9.438399,46.696877],"type":"Point"}
}