{
  "type": "Feature",
  "properties": {
    "iso:country":"CH",
    "sg:address":"1934 Villette Case Postale 1781",
    "sg:city":"Villette",
    "sg:orig_category":"Architekturb\u00fcros",
    "sg:phone":"+41 27 776 18 18",
    "sg:postcode":"1934",
    "sg:province":"Valais",
    "wof:name":"Jean-fran\u00e7ois Besse Bureau D'architecture",
    "wof:placetype":"venue"
},
  "geometry": {"coordinates":[7.21441,46.081188],"type":"Point"}
}