{
  "type": "Feature",
  "properties": {
    "iso:country":"CH",
    "sg:address":"Rue Des Oches 4",
    "sg:city":"Blonay",
    "sg:classifiers":[
        {
            "category":"Personal",
            "subcategory":"Nail Salon",
            "type":"Services"
        }
    ],
    "sg:phone":"+41 21 921 84 56",
    "sg:postcode":"1807",
    "sg:province":"Vaud",
    "sg:tags":[
        "manicure"
    ],
    "wof:name":"Marie-paule Hunziker Institut Creative Nails",
    "wof:placetype":"venue"
},
  "geometry": {"coordinates":[6.8949651718,46.465511322],"type":"Point"}
}