{
  "type": "Feature",
  "properties": {
    "iso:country":"CH",
    "sg:address":"Rue Des Maraichers 5",
    "sg:city":"Gen\u00e8ve",
    "sg:orig_category":"Instandhaltung U Reparatur von Automobilen",
    "sg:phone":"+41 22 321 56 30",
    "sg:postcode":"1205",
    "sg:province":"Gen\u00e8ve",
    "wof:name":"Garage Des Mara\u00eechers, Bochud Damien",
    "wof:placetype":"venue"
},
  "geometry": {"coordinates":[6.1345829964,46.1997756958],"type":"Point"}
}