{
  "type": "Feature",
  "properties": {
    "iso:country":"CH",
    "sg:address":"Unterm Schellenberg 146",
    "sg:city":"Riehen",
    "sg:classifiers":[
        {
            "category":"Professional",
            "subcategory":"Employment Agencies",
            "type":"Services"
        }
    ],
    "sg:phone":"+41 61 601 87 66",
    "sg:postcode":"4125",
    "sg:province":"Basel-Stadt",
    "sg:tags":[
        "personal",
        "u",
        "stellenvermittlung"
    ],
    "wof:name":"Bl\u00e4ttler Alfred Consulting",
    "wof:placetype":"venue"
},
  "geometry": {"coordinates":[7.6467618942,47.5723075867],"type":"Point"}
}