{
  "type": "Feature",
  "properties": {
    "addr:full":"Im H\u00f6fli 2 Oberstammheim Z\u00fcrich 8477",
    "addr:housenumber":"2",
    "addr:postcode":"8477",
    "addr:street":"Im Hoefli",
    "iso:country":"CH",
    "sg:address":"Im H\u00f6fli 2",
    "sg:city":"Oberstammheim",
    "sg:orig_category":"Chemin\u00e9e- and Ofenbau",
    "sg:phone":"+41 52 745 18 14",
    "sg:postcode":"8477",
    "sg:province":"Z\u00fcrich",
    "wof:name":"Fritz H\u00fcbscher Chemin\u00e9e-& Ofenbau",
    "wof:placetype":"venue"
},
  "geometry": {"coordinates":[8.798726,47.63274],"type":"Point"}
}