{
  "type": "Feature",
  "properties": {
    "addr:full":"Spalenvorstadt 8 4051 Basel. Postfach Basel Basel-Stadt 4003",
    "addr:housenumber":"8",
    "addr:postcode":"4051;4003",
    "addr:street":"Spalenvorstadt;Postfach",
    "iso:country":"CH",
    "sg:address":"Spalenvorstadt 8 4051 Basel. Postfach",
    "sg:city":"Basel",
    "sg:orig_category":"Architekturb\u00fcros",
    "sg:phone":"+41 61 264 92 92",
    "sg:postcode":"4003",
    "sg:province":"Basel-Stadt",
    "wof:name":"Fran\u00e7ois Fasnacht Architekturb\u00fcro",
    "wof:placetype":"venue"
},
  "geometry": {"coordinates":[7.583552,47.55735],"type":"Point"}
}