{
  "type": "Feature",
  "properties": {
    "iso:country":"CH",
    "sg:address":"Gfell 3860 Meiringen. Postfach",
    "sg:city":"Meiringen",
    "sg:orig_category":"Sportvereine Ski",
    "sg:phone":"+41 33 971 57 56",
    "sg:postcode":"3860",
    "sg:province":"Bern",
    "wof:name":"Skiclub Innertkirchen",
    "wof:placetype":"venue"
},
  "geometry": {"coordinates":[8.1928100586,46.7282218933],"type":"Point"}
}