{
  "type": "Feature",
  "properties": {
    "iso:country":"CH",
    "sg:address":"Via Luvini",
    "sg:city":"Lugano",
    "sg:orig_category":"Fachdetailhandel in Verkaufsr\u00e4umen",
    "sg:postcode":"6900",
    "sg:province":"Ticino",
    "wof:name":"Boatcenter Saladin",
    "wof:placetype":"venue"
},
  "geometry": {"coordinates":[8.9511098862,46.0047035217],"type":"Point"}
}