{
  "type": "Feature",
  "properties": {
    "addr:full":"Hochhausstrasse 14 Grabs St. Gallen 9472",
    "addr:housenumber":"14",
    "addr:postcode":"9472",
    "addr:street":"Hochhausstrasse",
    "iso:country":"CH",
    "sg:address":"Hochhausstrasse 14",
    "sg:city":"Grabs",
    "sg:orig_category":"Allgemeiner Hoch U Tiefbau",
    "sg:phone":"+41 81 771 31 32",
    "sg:postcode":"9472",
    "sg:province":"St. Gallen",
    "wof:name":"Vetsch Peter Baudienstleistungen Im Hochbau",
    "wof:placetype":"venue"
},
  "geometry": {"coordinates":[9.447842,47.17683],"type":"Point"}
}