{
  "type": "Feature",
  "properties": {
    "iso:country":"CH",
    "sg:address":"Ringstrasse 11 4614 H\u00e4gendorf. Postfach",
    "sg:city":"H\u00e4gendorf",
    "sg:orig_category":"Maler U Glasergewerbe",
    "sg:phone":"+41 62 216 11 30",
    "sg:postcode":"4614",
    "sg:province":"Solothurn",
    "wof:name":"Rupp Hansruedi, Malergesch\u00e4ft",
    "wof:placetype":"venue"
},
  "geometry": {"coordinates":[7.8434791565,47.330581665],"type":"Point"}
}