{
  "type": "Feature",
  "properties": {
    "iso:country":"CH",
    "sg:address":"Parkstrasse 5 6410 Goldau. Postfach 226",
    "sg:city":"Goldau",
    "sg:orig_category":"Fussreflexzonenmassage Solarien",
    "sg:phone":"+41 32 381 10 23",
    "sg:postcode":"6410",
    "sg:province":"Schwyz",
    "wof:name":"Ruth Kuentz",
    "wof:placetype":"venue"
},
  "geometry": {"coordinates":[7.2438988686,47.0813140869],"type":"Point"}
}