{
  "type": "Feature",
  "properties": {
    "iso:country":"CH",
    "sg:address":"Weidstrasse 25 6300 Zug. Postfach",
    "sg:city":"Zug",
    "sg:orig_category":"Architektur U Ingenieurb\u00fcros",
    "sg:postcode":"6300",
    "sg:province":"Zug",
    "wof:name":"Stocker + Stocker Architektur Und Fotografie Gmbh",
    "wof:placetype":"venue"
},
  "geometry": {"coordinates":[8.52909,47.169609],"type":"Point"}
}