{
  "type": "Feature",
  "properties": {
    "iso:country":"CH",
    "sg:address":"Les P\u00e2les 2",
    "sg:city":"Alle",
    "sg:orig_category":"HERSTELLUNG VON GER\u00c4TEN DER ELEKTRIZIT\u00c4TSERZEUGUNG, -VERTEILUNG U.\u00c4 Herstellung von Metallerzeugniss",
    "sg:phone":"+41 32 471 18 58",
    "sg:postcode":"2942",
    "sg:province":"Jura",
    "wof:name":"Philippe Saner Terminage De Horlogerie",
    "wof:placetype":"venue"
},
  "geometry": {"coordinates":[7.1248149872,47.4275093079],"type":"Point"}
}