{
  "type": "Feature",
  "properties": {
    "iso:country":"CH",
    "sg:address":"Hauptstrasse 32",
    "sg:city":"Waldenburg",
    "sg:orig_category":"Nationale Postdienste",
    "sg:phone":"+41 61 961 00 00",
    "sg:postcode":"4437",
    "sg:province":"Basel-Landschaft",
    "wof:name":"Die Schweizerische Post",
    "wof:placetype":"venue"
},
  "geometry": {"coordinates":[7.7488431931,47.3838233948],"type":"Point"}
}