{
  "type": "Feature",
  "properties": {
    "iso:country":"CH",
    "sg:address":"Via Lucino 12",
    "sg:city":"Breganzona",
    "sg:orig_category":"Detailhandel mit Radio U Fernsehger\u00e4ten",
    "sg:phone":"+41 91 966 66 06",
    "sg:postcode":"6932",
    "sg:province":"Ticino",
    "wof:name":"Tele Studio Di Antonio Gengaro",
    "wof:placetype":"venue"
},
  "geometry": {"coordinates":[8.9349527359,46.0092277527],"type":"Point"}
}