{
  "type": "Feature",
  "properties": {
    "iso:country":"CH",
    "sg:address":"Lerchenweg 4",
    "sg:city":"Burgdorf",
    "sg:orig_category":"Berufsberatungen",
    "sg:phone":"+41 34 422 00 55",
    "sg:postcode":"3400",
    "sg:province":"Bern",
    "wof:name":"Dr.rudolf Ramseyer Berufsberatung",
    "wof:placetype":"venue"
},
  "geometry": {"coordinates":[7.612562,47.059284],"type":"Point"}
}