{
  "type": "Feature",
  "properties": {
    "iso:country":"CH",
    "sg:address":"Dorfstrasse 20",
    "sg:city":"Belp",
    "sg:orig_category":"Kantonalbanken",
    "sg:phone":"+41 31 812 45 40",
    "sg:postcode":"3123",
    "sg:province":"Bern",
    "wof:name":"Berner Kantonalbank Bekb/bcbe",
    "wof:placetype":"venue"
},
  "geometry": {"coordinates":[7.4984478951,46.8921279907],"type":"Point"}
}