{
  "type": "Feature",
  "properties": {
    "iso:country":"CH",
    "sg:address":"Ch. Des Platti\u00e8res 10",
    "sg:city":"Chancy",
    "sg:classifiers":[
        {
            "category":"Utilities",
            "subcategory":"Electric",
            "type":"Services"
        }
    ],
    "sg:phone":"+41 22 756 96 00",
    "sg:postcode":"1284",
    "sg:province":"Gen\u00e8ve",
    "sg:tags":[
        "electricity",
        "raw",
        "energy",
        "material"
    ],
    "wof:name":"Soci\u00c9t\u00c9 Forces Mortrices De Chancy-pougny",
    "wof:placetype":"venue"
},
  "geometry": {"coordinates":[5.9726748466,46.1494407654],"type":"Point"}
}