{
  "type": "Feature",
  "properties": {
    "iso:country":"CH",
    "sg:address":"Chemin De Saule 57",
    "sg:city":"Bernex",
    "sg:orig_category":"Herstellung von sonstigen Erzeugnissen",
    "sg:postcode":"1233",
    "sg:province":"Gen\u00e8ve",
    "wof:name":"Guillot Jacqueline",
    "wof:placetype":"venue"
},
  "geometry": {"coordinates":[6.0691981316,46.1754226685],"type":"Point"}
}