{
  "type": "Feature",
  "properties": {
    "iso:country":"CH",
    "sg:address":"Chlotengasse 12",
    "sg:city":"Tagelswangen",
    "sg:orig_category":"G\u00fcterbef\u00f6rderung im Strassenverkehr",
    "sg:phone":"+41 62 776 14 30",
    "sg:postcode":"8317",
    "sg:province":"Z\u00fcrich",
    "wof:name":"Heidi Hunziker Transporte",
    "wof:placetype":"venue"
},
  "geometry": {"coordinates":[8.1144113541,47.3312530518],"type":"Point"}
}