{
  "type": "Feature",
  "properties": {
    "iso:country":"CH",
    "sg:address":"Seestrasse 25",
    "sg:city":"Uster",
    "sg:orig_category":"Unclassifiable Establishments",
    "sg:postcode":"8610",
    "sg:province":"Z\u00fcrich",
    "wof:name":"Ren\u00e9 Brack Bildhauerei",
    "wof:placetype":"venue"
},
  "geometry": {"coordinates":[8.7126264572,47.346321106],"type":"Point"}
}