{
  "type": "Feature",
  "properties": {
    "iso:country":"CH",
    "sg:address":"Gutstrasse 3",
    "sg:city":"Z\u00fcrich",
    "sg:orig_category":"Pensionskassen",
    "sg:phone":"+41 14639936",
    "sg:postcode":"8055",
    "sg:province":"Z\u00fcrich",
    "wof:name":"Wohlfahrts-stiftung Der Ruckstuhl Ernst Ag In Z\u00fcrich",
    "wof:placetype":"venue"
},
  "geometry": {"coordinates":[8.5099897385,47.3699531555],"type":"Point"}
}