{
  "type": "Feature",
  "properties": {
    "iso:country":"CH",
    "sg:address":"Staldenstrasse 4",
    "sg:city":"Zermatt",
    "sg:orig_category":"Kosmetikinstitute",
    "sg:phone":"+41 27 967 25 45",
    "sg:postcode":"3920",
    "sg:province":"Valais",
    "wof:name":"Chantal Perren Kosmetikinstitut Chantal",
    "wof:placetype":"venue"
},
  "geometry": {"coordinates":[7.7463550568,46.0164604187],"type":"Point"}
}