{
  "type": "Feature",
  "properties": {
    "iso:country":"CH",
    "sg:address":"Gersauerstrasse 100",
    "sg:city":"Brunnen",
    "sg:classifiers":[
        {
            "category":"Restaurant",
            "type":"Food & Drink"
        }
    ],
    "sg:phone":"+41 41 820 14 47",
    "sg:postcode":"6440",
    "sg:province":"Schwyz",
    "wof:name":"Restaurant Eichwald",
    "wof:placetype":"venue"
},
  "geometry": {"coordinates":[8.5954198837,46.9993286133],"type":"Point"}
}