{
  "type": "Feature",
  "properties": {
    "addr:full":"M\u00e8re Voie Chemin De La 27 1228 Plan-les-ouates. Postfach Plan-les-ouates Gen\u00e8ve 1228",
    "addr:housenumber":"27",
    "addr:postcode":"1228;postfach;1228",
    "addr:street":"Me\u0300Re Voie Chemin De La",
    "iso:country":"CH",
    "sg:address":"M\u00e8re Voie Chemin De La 27 1228 Plan-les-ouates. Postfach",
    "sg:city":"Plan-les-ouates",
    "sg:orig_category":"Allgemeiner Hoch U Tiefbau",
    "sg:postcode":"1228",
    "sg:province":"Gen\u00e8ve",
    "wof:name":"Plafisol S\u00e0rl",
    "wof:placetype":"venue"
},
  "geometry": {"coordinates":[6.1174,46.168209],"type":"Point"}
}