{
  "type": "Feature",
  "properties": {
    "iso:country":"CH",
    "sg:address":"Hauptstrasse 76",
    "sg:city":"R\u00fcttenen",
    "sg:classifiers":[
        {
            "category":"Restaurant",
            "type":"Food & Drink"
        }
    ],
    "sg:phone":"+41 32 622 33 71",
    "sg:postcode":"4522",
    "sg:province":"Solothurn",
    "wof:name":"Restaurant Zur Post",
    "wof:placetype":"venue"
},
  "geometry": {"coordinates":[7.5332598686,47.2323722839],"type":"Point"}
}