{
  "type": "Feature",
  "properties": {
    "iso:country":"CH",
    "sg:address":"Hubelrain 5 6206 Neuenkirch. Postfach",
    "sg:city":"Neuenkirch",
    "sg:classifiers":[
        {
            "category":"Insurance",
            "subcategory":"Insurance Agent",
            "type":"Services"
        }
    ],
    "sg:phone":"+41 41 467 18 94",
    "sg:postcode":"6206",
    "sg:province":"Luzern",
    "sg:tags":[
        "versicherungsagenturen",
        "-broker"
    ],
    "wof:name":"Basler Versicherungen Agentur",
    "wof:placetype":"venue"
},
  "geometry": {"coordinates":[8.1961097717,47.1047439575],"type":"Point"}
}