{
  "type": "Feature",
  "properties": {
    "iso:country":"CH",
    "sg:address":"Zentralstrasse 38",
    "sg:city":"Luzern",
    "sg:orig_category":"Sonstige Finanzierungsinstitutionen Unternehmensberatung",
    "sg:phone":"+41 41 210 04 77",
    "sg:postcode":"6003",
    "sg:province":"Luzern",
    "wof:name":"Zentronica Ag",
    "wof:placetype":"venue"
},
  "geometry": {"coordinates":[8.3096790314,47.0468521118],"type":"Point"}
}