{
  "type": "Feature",
  "properties": {
    "iso:country":"CH",
    "sg:address":"Schmidhusen 35 9100 Herisau. Postfach",
    "sg:city":"Herisau",
    "sg:orig_category":"Erbringung von Dienstleistungen f\u00fcr Unternehmen",
    "sg:phone":"+41 32 653 11 04",
    "sg:postcode":"9100",
    "sg:province":"Appenzell Ausserrhoden",
    "wof:name":"Modelltechnik Renfer",
    "wof:placetype":"venue"
},
  "geometry": {"coordinates":[7.370112896,47.1862983704],"type":"Point"}
}