{
  "type": "Feature",
  "properties": {
    "iso:country":"CH",
    "sg:address":"Hauptstrasse 69",
    "sg:city":"Nidau",
    "sg:classifiers":[
        {
            "category":"Restaurant",
            "type":"Food & Drink"
        }
    ],
    "sg:phone":"+41 32 331 56 21",
    "sg:postcode":"2560",
    "sg:province":"Bern",
    "wof:name":"Restaurant L\u00f6wen",
    "wof:placetype":"venue"
},
  "geometry": {"coordinates":[7.2411088943,47.1245994568],"type":"Point"}
}