{
  "type": "Feature",
  "properties": {
    "iso:country":"CH",
    "sg:address":"Grundstrasse 16",
    "sg:city":"St\u00e4fa",
    "sg:orig_category":"Herstellung von Werkzeugen Herstellung von Werkzeugmaschinen",
    "sg:phone":"+41 71 626 77 66",
    "sg:postcode":"8712",
    "sg:province":"Z\u00fcrich",
    "wof:name":"Inoflex Ag",
    "wof:placetype":"venue"
},
  "geometry": {"coordinates":[9.1381845474,47.5666694641],"type":"Point"}
}