{
  "type": "Feature",
  "properties": {
    "iso:country":"CH",
    "sg:address":"Ottenhub",
    "sg:city":"Wila",
    "sg:orig_category":"Dachdeckerei",
    "sg:phone":"+41 52 385 15 14",
    "sg:postcode":"8492",
    "sg:province":"Z\u00fcrich",
    "wof:name":"August Schneider Dachdeckergesch\u00e4ft",
    "wof:placetype":"venue"
},
  "geometry": {"coordinates":[8.88019,47.403912],"type":"Point"}
}