{
  "type": "Feature",
  "properties": {
    "iso:country":"CH",
    "sg:address":"Rank 5",
    "sg:city":"Obermumpf",
    "sg:classifiers":[
        {
            "category":"Education",
            "subcategory":"Library",
            "type":"Public Place"
        }
    ],
    "sg:phone":"+41 62 873 17 61",
    "sg:postcode":"4324",
    "sg:province":"Aargau",
    "sg:tags":[
        "u",
        "bibliotheken",
        "archive"
    ],
    "wof:name":"Katholische Pfarrbibliothek",
    "wof:placetype":"venue"
},
  "geometry": {"coordinates":[7.93218,47.531773],"type":"Point"}
}