{
  "type": "Feature",
  "properties": {
    "iso:country":"CH",
    "sg:address":"Melchnaustrasse 40",
    "sg:city":"Madiswil",
    "sg:orig_category":"RESTAURANTS: TEA-ROOMS",
    "sg:phone":"+41 62 965 26 31",
    "sg:postcode":"4934",
    "sg:province":"Bern",
    "wof:name":"Schreiber Andr\u00e9",
    "wof:placetype":"venue"
},
  "geometry": {"coordinates":[7.8159031868,47.1756019592],"type":"Point"}
}