{
  "type": "Feature",
  "properties": {
    "iso:country":"CH",
    "sg:address":"Sonnackerweg 8",
    "sg:city":"Konolfingen",
    "sg:orig_category":"Offsetdruck",
    "sg:phone":"+41 31 791 10 44",
    "sg:postcode":"3510",
    "sg:province":"Bern",
    "wof:name":"Johann Koch Offsetdruckerei",
    "wof:placetype":"venue"
},
  "geometry": {"coordinates":[7.6328949928,46.889919281],"type":"Point"}
}