{
  "type": "Feature",
  "properties": {
    "iso:country":"CH",
    "sg:address":"Hausimollstrasse 1",
    "sg:city":"Egerkingen",
    "sg:orig_category":"Reiseb\u00fcros U Reiseveranstalter",
    "sg:phone":"+41 62 212 41 50",
    "sg:postcode":"4622",
    "sg:province":"Solothurn",
    "wof:name":"Reiserama Gmbh",
    "wof:placetype":"venue"
},
  "geometry": {"coordinates":[7.8011898994,47.3178443909],"type":"Point"}
}