{
  "type": "Feature",
  "properties": {
    "iso:country":"CH",
    "sg:address":"Fraum\u00fcnsterstrasse 29",
    "sg:city":"Z\u00fcrich",
    "sg:orig_category":"Interessenvertretungen",
    "sg:postcode":"8001",
    "sg:province":"Z\u00fcrich",
    "wof:name":"Cinp Collegium Internationale Neuro-psychopharmacologicum",
    "wof:placetype":"venue"
},
  "geometry": {"coordinates":[8.5404977798,47.3696174622],"type":"Point"}
}