{
  "type": "Feature",
  "properties": {
    "addr:full":"Im Langacher Greifensee Z\u00fcrich 8606",
    "addr:postcode":"8606",
    "addr:street":"Im Langacher",
    "iso:country":"CH",
    "sg:address":"Im Langacher",
    "sg:city":"Greifensee",
    "sg:classifiers":[
        {
            "category":"Professional",
            "subcategory":"Testing Lab",
            "type":"Services"
        }
    ],
    "sg:phone":"+41 19444545",
    "sg:postcode":"8606",
    "sg:province":"Z\u00fcrich",
    "sg:tags":[
        "analytical",
        "laboratory",
        "balance"
    ],
    "wof:name":"Mettler-toledo (schweiz) Ag",
    "wof:placetype":"venue"
},
  "geometry": {"coordinates":[8.686167,47.366161],"type":"Point"}
}