{
  "type": "Feature",
  "properties": {
    "iso:country":"CH",
    "sg:address":"Chemin De Saule 104",
    "sg:city":"Bernex",
    "sg:orig_category":"G\u00fcterbef\u00f6rderung im Strassenverkehr",
    "sg:phone":"+41 18440515",
    "sg:postcode":"1233",
    "sg:province":"Gen\u00e8ve",
    "wof:name":"Fritz Helfenberger Transporte",
    "wof:placetype":"venue"
},
  "geometry": {"coordinates":[8.4315481186,47.4590263367],"type":"Point"}
}