{
  "type": "Feature",
  "properties": {
    "iso:country":"CH",
    "sg:address":"Rue Principale 21",
    "sg:city":"Vermes",
    "sg:orig_category":"Non-Classified Establishments",
    "sg:phone":"+41 32 438 87 77",
    "sg:postcode":"2829",
    "sg:province":"Jura",
    "wof:name":"Auberge De La Gabiare",
    "wof:placetype":"venue"
},
  "geometry": {"coordinates":[7.4748091698,47.3291854858],"type":"Point"}
}