{
  "type": "Feature",
  "properties": {
    "addr:full":"Im Ochsengarten 1 4223 Blauen. Postfach Blauen Basel-Landschaft 4223",
    "addr:housenumber":"1",
    "addr:postcode":"4223 blauen. postfach;4223",
    "addr:street":"Im Ochsengarten",
    "iso:country":"CH",
    "sg:address":"Im Ochsengarten 1 4223 Blauen. Postfach",
    "sg:city":"Blauen",
    "sg:orig_category":"Detailhandel mit Antiquit\u00e4ten U Gebrauchtwaren in Verkaufsr\u00e4umen",
    "sg:phone":"+41 61 761 78 23",
    "sg:postcode":"4223",
    "sg:province":"Basel-Landschaft",
    "wof:name":"Antik Style Saladin Antiquit\u00e4tenzubeh\u00f6r Wie M\u00f6belbeschl\u00e4ge, Holzteile U. Behandlungsmittel; Handel",
    "wof:placetype":"venue"
},
  "geometry": {"coordinates":[7.518243,47.449936],"type":"Point"}
}