{
  "type": "Feature",
  "properties": {
    "iso:country":"CH",
    "sg:address":"Rosenwg 3 6330 Cham. Postfach",
    "sg:city":"Cham",
    "sg:orig_category":"Herstellung von rohen \u00d6len U Fetten",
    "sg:postcode":"6330",
    "sg:province":"Zug",
    "wof:name":"Castelli Salvatore Seisefett U. -oel; Handel",
    "wof:placetype":"venue"
},
  "geometry": {"coordinates":[8.4537687302,47.1787071228],"type":"Point"}
}