{
  "type": "Feature",
  "properties": {
    "iso:country":"CH",
    "sg:address":"Fischingerstrasse",
    "sg:city":"Sirnach",
    "sg:orig_category":"Grosshandel mit Getr\u00e4nken",
    "sg:postcode":"8370",
    "sg:province":"Thurgau",
    "wof:name":"Enoteca Leonardo Inhaberin Soru Priska",
    "wof:placetype":"venue"
},
  "geometry": {"coordinates":[8.9956302643,47.4603652954],"type":"Point"}
}