{
  "type": "Feature",
  "properties": {
    "iso:country":"CH",
    "sg:address":"Im Lenz 112a",
    "sg:city":"Hinwil",
    "sg:orig_category":"Fahrschulen, Flugschulen",
    "sg:phone":"+41 19380880",
    "sg:postcode":"8340",
    "sg:province":"Z\u00fcrich",
    "wof:name":"Stefano Martino Autofahrschule",
    "wof:placetype":"venue"
},
  "geometry": {"coordinates":[8.8431787491,47.2966384888],"type":"Point"}
}