{
  "type": "Feature",
  "properties": {
    "iso:country":"CH",
    "sg:address":"Chappelistrasse 1 8604 Volketswil. Postfach",
    "sg:city":"Volketswil",
    "sg:orig_category":"Wirtschaftspr\u00fcfung, Steuerberatung U Treuhand",
    "sg:phone":"+41 19452121",
    "sg:postcode":"8604",
    "sg:province":"Z\u00fcrich",
    "wof:name":"Dubler Treuhand Ag",
    "wof:placetype":"venue"
},
  "geometry": {"coordinates":[8.6737508774,47.3893318176],"type":"Point"}
}