{
  "type": "Feature",
  "properties": {
    "iso:country":"CH",
    "sg:address":"Untermatt 6 8902 Urdorf. Postfach",
    "sg:city":"Urdorf",
    "sg:orig_category":"Sonstige mit der Informatik verbundene T\u00e4tigkeiten",
    "sg:postcode":"8902",
    "sg:province":"Z\u00fcrich",
    "wof:name":"Hehr It",
    "wof:placetype":"venue"
},
  "geometry": {"coordinates":[8.4165334702,47.3905715942],"type":"Point"}
}