{
  "type": "Feature",
  "properties": {
    "iso:country":"CH",
    "sg:address":"Place De La Gare 51 2900 Porrentruy Case Postale 175",
    "sg:city":"Porrentruy",
    "sg:orig_category":"Finanzierungsinstitutionen Unternehmensberatung",
    "sg:phone":"+41 13855656",
    "sg:postcode":"2900",
    "sg:province":"Jura",
    "wof:name":"Commcept Ag",
    "wof:placetype":"venue"
},
  "geometry": {"coordinates":[8.3335599899,47.0247917175],"type":"Point"}
}