{
  "type": "Feature",
  "properties": {
    "iso:country":"CH",
    "sg:address":"Stockenweg 35 8906 Bonstetten. Postfach",
    "sg:city":"Bonstetten",
    "sg:orig_category":"Gartenbau",
    "sg:phone":"+41 17001369",
    "sg:postcode":"8906",
    "sg:province":"Z\u00fcrich",
    "wof:name":"Fuchs & Co.",
    "wof:placetype":"venue"
},
  "geometry": {"coordinates":[8.4526023865,47.3165740967],"type":"Point"}
}