{
  "type": "Feature",
  "properties": {
    "iso:country":"CH",
    "sg:address":"La Pelouse",
    "sg:city":"Payerne",
    "sg:orig_category":"Zeitungsverlag",
    "sg:postcode":"1530",
    "sg:province":"Vaud",
    "wof:name":"Soci\u00e9t\u00e9 Typographique Payernoise",
    "wof:placetype":"venue"
},
  "geometry": {"coordinates":[6.9400901794,46.8218994141],"type":"Point"}
}