{
  "type": "Feature",
  "properties": {
    "iso:country":"CH",
    "sg:address":"Chalet Ermina 1854 Leysin. Postfach",
    "sg:city":"Leysin",
    "sg:orig_category":"Vermittlungen Wohnungs-Agenturen,",
    "sg:phone":"+41 24 494 12 61",
    "sg:postcode":"1854",
    "sg:province":"Vaud",
    "wof:name":"Ermina S\u00e0rl Location De Chambres D'h\u00f4tes Etc",
    "wof:placetype":"venue"
},
  "geometry": {"coordinates":[7.0123200417,46.3469238281],"type":"Point"}
}