{
  "type": "Feature",
  "properties": {
    "iso:country":"CH",
    "sg:address":"6197",
    "sg:city":"Bumbach",
    "sg:orig_category":"Detailhandel mit Waren verschiedener Art, Hauptrichtung Nahrungsmittel",
    "sg:phone":"+41 32 392 14 78",
    "sg:postcode":"6197",
    "sg:province":"Bern",
    "wof:name":"Gottfried Meer Handlung",
    "wof:placetype":"venue"
},
  "geometry": {"coordinates":[7.3157100677,47.0305595398],"type":"Point"}
}