{
  "type": "Feature",
  "properties": {
    "iso:country":"CH",
    "sg:address":"Z\u00fcrcherstrasse 43",
    "sg:city":"Feuerthalen",
    "sg:orig_category":"Sonstiger Grosshandel",
    "sg:phone":"+41 52 670 03 16",
    "sg:postcode":"8245",
    "sg:province":"Z\u00fcrich",
    "wof:name":"Meda Organisation Und Informationsverarbeitung Ag",
    "wof:placetype":"venue"
},
  "geometry": {"coordinates":[8.6420726776,47.6920814514],"type":"Point"}
}