{
  "type": "Feature",
  "properties": {
    "iso:country":"CH",
    "sg:address":"Gare Rue De La",
    "sg:city":"Pal\u00e9zieux-gare",
    "sg:orig_category":"Instandhaltung U Reparatur von Automobilen",
    "sg:phone":"+41 21 907 81 68",
    "sg:postcode":"1607",
    "sg:province":"Vaud",
    "wof:name":"Pousaz H. & Fils Sa",
    "wof:placetype":"venue"
},
  "geometry": {"coordinates":[6.8111100197,46.5389404297],"type":"Point"}
}