{
  "type": "Feature",
  "properties": {
    "iso:country":"CH",
    "sg:address":"Rickenstrasse 9",
    "sg:city":"Gebertingen",
    "sg:orig_category":"RESTAURANTS: TEA-ROOMS",
    "sg:phone":"+41 55 284 22 33",
    "sg:postcode":"8725",
    "sg:province":"St. Gallen",
    "wof:name":"Restaurant Frohe Aussicht",
    "wof:placetype":"venue"
},
  "geometry": {"coordinates":[9.0025520325,47.2525863647],"type":"Point"}
}