{
  "type": "Feature",
  "properties": {
    "iso:country":"CH",
    "sg:address":"Glaserbergstrasse 41 4056 Basel. Postfach",
    "sg:city":"Basel",
    "sg:orig_category":"Wirtschaftspr\u00fcfung, Steuerberatung U Treuhand",
    "sg:phone":"+41 61 321 47 95",
    "sg:postcode":"4051",
    "sg:province":"Basel-Stadt",
    "wof:name":"D\u00f6rffler Heinz, Dipl. B\u00fccherexperte Revisions- U. Treuhandb\u00fcro",
    "wof:placetype":"venue"
},
  "geometry": {"coordinates":[7.5687761307,47.5663337708],"type":"Point"}
}