{
  "type": "Feature",
  "properties": {
    "iso:country":"CH",
    "sg:address":"Binzikerstrasse 80",
    "sg:city":"Gr\u00fcningen",
    "sg:orig_category":"Gasth\u00f6fe/Gasth\u00e4user mit Restaurant",
    "sg:phone":"+41 19351154",
    "sg:postcode":"8627",
    "sg:province":"Z\u00fcrich",
    "wof:name":"Landgasthof Adler",
    "wof:placetype":"venue"
},
  "geometry": {"coordinates":[8.7596101761,47.2784614563],"type":"Point"}
}