{
  "type": "Feature",
  "properties": {
    "iso:country":"CH",
    "sg:address":"Bahnhofstrasse 12",
    "sg:city":"Fehraltorf",
    "sg:orig_category":"Fahrschulen, Flugschulen",
    "sg:phone":"+41 32 373 66 44",
    "sg:postcode":"8320",
    "sg:province":"Z\u00fcrich",
    "wof:name":"Thomas Leibacher Autofahrschule",
    "wof:placetype":"venue"
},
  "geometry": {"coordinates":[7.3006091118,47.107837677],"type":"Point"}
}