{
  "type": "Feature",
  "properties": {
    "iso:country":"CH",
    "sg:address":"Esterlistrasse 20",
    "sg:city":"Pratteln",
    "sg:orig_category":"Sportvereine Velo Rad-& Motorfahrer-Bund SRB",
    "sg:phone":"+41 61 821 30 66",
    "sg:postcode":"4133",
    "sg:province":"Basel-Landschaft",
    "wof:name":"Veloclub Rollers Wolhusen",
    "wof:placetype":"venue"
},
  "geometry": {"coordinates":[7.6875238419,47.5194244385],"type":"Point"}
}