{
  "type": "Feature",
  "properties": {
    "iso:country":"CH",
    "sg:address":"P\u00e9rolles Boulevard De 34 1700 Fribourg. Postfach",
    "sg:city":"Freiburg",
    "sg:orig_category":"Vermietung U Verpachtung von eigenen Immobilien",
    "sg:phone":"+41 21 697 07 80",
    "sg:postcode":"1700",
    "sg:province":"Fribourg",
    "wof:name":"Jadinvest S\u00e0rl",
    "wof:placetype":"venue"
},
  "geometry": {"coordinates":[6.5580701828,46.5100784302],"type":"Point"}
}