{
  "type": "Feature",
  "properties": {
    "iso:country":"CH",
    "sg:address":"Bachweg 21",
    "sg:city":"Altnau",
    "sg:orig_category":"Sportschulen Wassersport",
    "sg:phone":"+41 71 695 25 35",
    "sg:postcode":"8595",
    "sg:province":"Thurgau",
    "wof:name":"Charly B\u00f6hler Segel-& Motorbootschule",
    "wof:placetype":"venue"
},
  "geometry": {"coordinates":[9.2640867233,47.6113853455],"type":"Point"}
}