{
  "type": "Feature",
  "properties": {
    "iso:country":"CH",
    "sg:address":"Schallenberg 305",
    "sg:city":"Liebistorf",
    "sg:orig_category":"Advokaturb\u00fcros",
    "sg:phone":"+41 26 674 36 12",
    "sg:postcode":"3213",
    "sg:province":"Fribourg",
    "wof:name":"Daniela B\u00f6sch Advokaturb\u00fcro",
    "wof:placetype":"venue"
},
  "geometry": {"coordinates":[7.18774,46.90593],"type":"Point"}
}