{
  "type": "Feature",
  "properties": {
    "iso:country":"CH",
    "sg:address":"Corso San Gottardo 48",
    "sg:city":"Chiasso",
    "sg:orig_category":"Betrieb von Taxis",
    "sg:phone":"+41 91 682 57 54",
    "sg:postcode":"6830",
    "sg:province":"Ticino",
    "wof:name":"Oreste Garetto Tassi Internazionale",
    "wof:placetype":"venue"
},
  "geometry": {"coordinates":[9.029016,45.834743],"type":"Point"}
}