{
  "type": "Feature",
  "properties": {
    "iso:country":"CH",
    "sg:address":"Via Trisnera 42b",
    "sg:city":"Losone",
    "sg:orig_category":"Hoch U Tiefbau",
    "sg:phone":"+41 91 791 31 54",
    "sg:postcode":"6616",
    "sg:province":"Ticino",
    "wof:name":"Eros Battaglia Impresa Costruzioni",
    "wof:placetype":"venue"
},
  "geometry": {"coordinates":[8.7592144012,46.1730766296],"type":"Point"}
}