{
  "type": "Feature",
  "properties": {
    "iso:country":"CH",
    "sg:address":"Pf\u00e4ffikerstrasse 462",
    "sg:city":"Hittnau",
    "sg:classifiers":[
        {
            "category":"Bars & Pubs",
            "type":"Food & Drink"
        }
    ],
    "sg:phone":"+41 41 467 20 24",
    "sg:postcode":"8335",
    "sg:province":"Z\u00fcrich",
    "sg:tags":[
        "restaurant"
    ],
    "wof:name":"Restaurant-pub Max",
    "wof:placetype":"venue"
},
  "geometry": {"coordinates":[8.194031,47.115257],"type":"Point"}
}