{
  "type": "Feature",
  "properties": {
    "iso:country":"CH",
    "sg:address":"Unterb\u00e4chen",
    "sg:city":"Boltigen",
    "sg:orig_category":"Elektroinstallation",
    "sg:phone":"+41 33 822 25 73",
    "sg:postcode":"3766",
    "sg:province":"Bern",
    "wof:name":"Feuz, Elektroinstallationen Und Rtv",
    "wof:placetype":"venue"
},
  "geometry": {"coordinates":[7.894329071,46.701084137],"type":"Point"}
}