{
  "type": "Feature",
  "properties": {
    "iso:country":"CH",
    "sg:address":"Oltnerstrasse 16",
    "sg:city":"Sch\u00f6nenwerd",
    "sg:orig_category":"HOTELS: MIT RESTAURANT Kongress- and Tagungshotels mit Restaurant",
    "sg:phone":"+41 34 445 23 10",
    "sg:postcode":"5012",
    "sg:province":"Solothurn",
    "wof:name":"Hotel Sunnehof",
    "wof:placetype":"venue"
},
  "geometry": {"coordinates":[7.5844712257,47.0853385925],"type":"Point"}
}