{
  "type": "Feature",
  "properties": {
    "iso:country":"CH",
    "sg:address":"Boulevard De La Cluse 9",
    "sg:city":"Gen\u00e8ve",
    "sg:orig_category":"Herstellung von Elektromotoren, Generatoren U Transformatoren",
    "sg:phone":"+41 22 320 78 68",
    "sg:postcode":"1205",
    "sg:province":"Gen\u00e8ve",
    "wof:name":"Kohler & Cie Fabr.de Transformateurs",
    "wof:placetype":"venue"
},
  "geometry": {"coordinates":[6.1442298889,46.1882667542],"type":"Point"}
}