{
  "type": "Feature",
  "properties": {
    "iso:country":"CH",
    "sg:address":"Rossweid 3 8405 Seen. Postfach",
    "sg:city":"Winterthur",
    "sg:orig_category":"Unternehmensberatung",
    "sg:phone":"+41 52 233 40 36",
    "sg:postcode":"8405",
    "sg:province":"Z\u00fcrich",
    "wof:name":"Oscot Osterwalder Consulting And Trading",
    "wof:placetype":"venue"
},
  "geometry": {"coordinates":[8.7754468918,47.4822235107],"type":"Point"}
}