{
  "type": "Feature",
  "properties": {
    "iso:country":"CH",
    "sg:address":"Hauptstrasse 12",
    "sg:city":"Hunzenschwil",
    "sg:orig_category":"Tankstellen",
    "sg:postcode":"5502",
    "sg:province":"Aargau",
    "wof:name":"Rudolf Rohr Ag",
    "wof:placetype":"venue"
},
  "geometry": {"coordinates":[8.1315450668,47.3868370056],"type":"Point"}
}