{
  "type": "Feature",
  "properties": {
    "iso:country":"CH",
    "sg:address":"Andlauerstrasse 34",
    "sg:city":"Muttenz",
    "sg:orig_category":"Decoration Displays",
    "sg:phone":"+41 61 467 99 00",
    "sg:postcode":"4132",
    "sg:province":"Basel-Landschaft",
    "wof:name":"Aces Vertrieb Von Designprodukten Gmbh",
    "wof:placetype":"venue"
},
  "geometry": {"coordinates":[7.642307,47.528008],"type":"Point"}
}