{
  "type": "Feature",
  "properties": {
    "addr:full":"Alte Badenerstrasse 34 Neerach Z\u00fcrich 8173",
    "addr:housenumber":"34",
    "addr:postcode":"8173",
    "addr:street":"Alte Badenerstrasse",
    "iso:country":"CH",
    "sg:address":"Alte Badenerstrasse 34",
    "sg:city":"Neerach",
    "sg:orig_category":"Allgemeiner Hoch U Tiefbau Hoch U Tiefbau",
    "sg:phone":"+41 18582850",
    "sg:postcode":"8173",
    "sg:province":"Z\u00fcrich",
    "wof:name":"Ok Bau Bauunternehmung, D. Okle",
    "wof:placetype":"venue"
},
  "geometry": {"coordinates":[8.464905,47.50967],"type":"Point"}
}