{
  "type": "Feature",
  "properties": {
    "iso:country":"CH",
    "sg:address":"Bahnhofstrasse 26 9443 Widnau. Postfach",
    "sg:city":"Widnau",
    "sg:orig_category":"RESTAURANTS: TEA-ROOMS",
    "sg:postcode":"9443",
    "sg:province":"St. Gallen",
    "wof:name":"Metropolis Chitas E. Restaurant",
    "wof:placetype":"venue"
},
  "geometry": {"coordinates":[9.6340513229,47.4059638977],"type":"Point"}
}