{
  "type": "Feature",
  "properties": {
    "iso:country":"CH",
    "sg:address":"Schwanenstrasse 5",
    "sg:city":"Einsiedeln",
    "sg:orig_category":"Detailhandel mit Textilien",
    "sg:phone":"+41 55 412 26 10",
    "sg:postcode":"8840",
    "sg:province":"Schwyz",
    "wof:name":"Restenhalle, Antoinette Hungerb\u00fchler",
    "wof:placetype":"venue"
},
  "geometry": {"coordinates":[8.7465496063,47.1270217896],"type":"Point"}
}