{
  "type": "Feature",
  "properties": {
    "iso:country":"CH",
    "sg:address":"Obstgartenweg 16",
    "sg:city":"M\u00e4nnedorf",
    "sg:orig_category":"Fahrschulen, Flugschulen",
    "sg:phone":"+41 71 761 36 61",
    "sg:postcode":"8708",
    "sg:province":"Z\u00fcrich",
    "wof:name":"Fahrschule Mattle Lukas",
    "wof:placetype":"venue"
},
  "geometry": {"coordinates":[9.5728178024,47.3281860352],"type":"Point"}
}