{
  "type": "Feature",
  "properties": {
    "iso:country":"CH",
    "sg:address":"Strassburgerallee 105 4000 Basel. Postfach",
    "sg:city":"Basel",
    "sg:orig_category":"Sonstiger Grosshandel",
    "sg:phone":"+41 91 943 32 12",
    "sg:postcode":"4051",
    "sg:province":"Basel-Stadt",
    "wof:name":"Gaspare Pia",
    "wof:placetype":"venue"
},
  "geometry": {"coordinates":[8.991985321,46.0526733398],"type":"Point"}
}