{
  "type": "Feature",
  "properties": {
    "iso:country":"CH",
    "sg:address":"Quaistrasse 41",
    "sg:city":"Trimbach",
    "sg:orig_category":"Detailhandel mit Metallwaren, Anstrichmitteln, Glaswaren, Bau U Heimwerkerbedarf Handelsvermittlung ",
    "sg:phone":"+41 71 278 68 05",
    "sg:postcode":"4632",
    "sg:province":"Solothurn",
    "wof:name":"C-norm Ag",
    "wof:placetype":"venue"
},
  "geometry": {"coordinates":[9.3582420349,47.4177284241],"type":"Point"}
}