{
  "type": "Feature",
  "properties": {
    "iso:country":"CH",
    "sg:address":"Kreuzbuchstrasse 63",
    "sg:city":"Meggen",
    "sg:orig_category":"Erbringung von Dienstleistungen f\u00fcr Unternehmen",
    "sg:phone":"+41 32 342 25 05",
    "sg:postcode":"6045",
    "sg:province":"Luzern",
    "wof:name":"Zweiter Stock S\u00fcd, Netthoevel & Gaberth\u00fcel",
    "wof:placetype":"venue"
},
  "geometry": {"coordinates":[7.255338192,47.1463470459],"type":"Point"}
}