{
  "type": "Feature",
  "properties": {
    "iso:country":"CH",
    "sg:address":"Rue Centrale 46 1580 Avenches. Postfach",
    "sg:city":"Avenches",
    "sg:orig_category":"Detailhandel mit Beleuchtungs U Haushaltsgegenst\u00e4nden Detailhandel mit Radio U Fernsehger\u00e4ten",
    "sg:phone":"+41 26 675 20 20",
    "sg:postcode":"1580",
    "sg:province":"Vaud",
    "wof:name":"Tv Etter S\u00e0rl Radio \u00e9lectrom\u00e9nager",
    "wof:placetype":"venue"
},
  "geometry": {"coordinates":[7.039397,46.879414],"type":"Point"}
}