{
  "type": "Feature",
  "properties": {
    "iso:country":"CH",
    "sg:address":"Rossweidstrasse 14",
    "sg:city":"Zufikon",
    "sg:orig_category":"Vereine Gesang",
    "sg:phone":"+41 56 633 72 86",
    "sg:postcode":"5621",
    "sg:province":"Aargau",
    "wof:name":"Kirchenchor Zufikon",
    "wof:placetype":"venue"
},
  "geometry": {"coordinates":[8.3541250229,47.3453140259],"type":"Point"}
}