{
  "type": "Feature",
  "properties": {
    "iso:country":"CH",
    "sg:address":"Maulbeerstrasse 34 4058 Basel. Postfach",
    "sg:city":"Basel",
    "sg:orig_category":"RESTAURANTS: TEA-ROOMS",
    "sg:phone":"+41 61 691 93 33",
    "sg:postcode":"4051",
    "sg:province":"Basel-Stadt",
    "wof:name":"Restaurant Latino, Cicek D.",
    "wof:placetype":"venue"
},
  "geometry": {"coordinates":[7.6008548737,47.5669593811],"type":"Point"}
}