{
  "type": "Feature",
  "properties": {
    "iso:country":"CH",
    "sg:address":"Hirsackerstrasse",
    "sg:city":"Horgen",
    "sg:orig_category":"Sonstige mit Sport verbundene T\u00e4tigkeiten",
    "sg:postcode":"8810",
    "sg:province":"Z\u00fcrich",
    "wof:name":"Genossenschaft Segler-clubhaus Horgen",
    "wof:placetype":"venue"
},
  "geometry": {"coordinates":[8.6078853607,47.2579154968],"type":"Point"}
}