{
  "type": "Feature",
  "properties": {
    "iso:country":"CH",
    "sg:address":"Buckhauserstrasse 28",
    "sg:city":"Z\u00fcrich",
    "sg:orig_category":"G\u00fcterbef\u00f6rderung im Strassenverkehr",
    "sg:phone":"+41 14924413",
    "sg:postcode":"8048",
    "sg:province":"Z\u00fcrich",
    "wof:name":"M\u00fcrset Ag",
    "wof:placetype":"venue"
},
  "geometry": {"coordinates":[8.4927148819,47.3843688965],"type":"Point"}
}