{
  "type": "Feature",
  "properties": {
    "iso:country":"CH",
    "sg:address":"Gydisdorf",
    "sg:city":"Grindelwald",
    "sg:orig_category":"Sanit\u00e4r, Heizungs U L\u00fcftungsinstallation",
    "sg:postcode":"3818",
    "sg:province":"Bern",
    "wof:name":"U. Studer Ag, Grindelwald",
    "wof:placetype":"venue"
},
  "geometry": {"coordinates":[8.0409498215,46.6241416931],"type":"Point"}
}