{
  "type": "Feature",
  "properties": {
    "iso:country":"CH",
    "sg:address":"6362 Stansstad. Postfach 457",
    "sg:city":"Stansstad",
    "sg:orig_category":"Eisenbahnverkehr",
    "sg:phone":"+41 41 618 85 85",
    "sg:postcode":"6362",
    "sg:province":"Nidwalden",
    "wof:name":"Luzern-stans-engelberg-bahn (lse)",
    "wof:placetype":"venue"
},
  "geometry": {"coordinates":[8.3291397095,46.972328186],"type":"Point"}
}