{
  "type": "Feature",
  "properties": {
    "iso:country":"CH",
    "sg:address":"Gartenstrasse 36 4528 Zuchwil. Postfach 360",
    "sg:city":"Zuchwil",
    "sg:orig_category":"RESTAURANTS: TEA-ROOMS",
    "sg:phone":"+41 71 766 11 07",
    "sg:postcode":"4528",
    "sg:province":"Solothurn",
    "wof:name":"Restaurant Blumenhalde",
    "wof:placetype":"venue"
},
  "geometry": {"coordinates":[9.5170345306,47.2772102356],"type":"Point"}
}