{
  "type": "Feature",
  "properties": {
    "iso:country":"CH",
    "sg:address":"Kasernenstrasse 43",
    "sg:city":"B\u00fclach",
    "sg:orig_category":"Kinos",
    "sg:phone":"+41 71 223 12 73",
    "sg:postcode":"8180",
    "sg:province":"Z\u00fcrich",
    "wof:name":"Storchen-cin\u00e9ma",
    "wof:placetype":"venue"
},
  "geometry": {"coordinates":[9.3759641647,47.4271621704],"type":"Point"}
}