{
  "type": "Feature",
  "properties": {
    "iso:country":"CH",
    "sg:address":"Bahnhofstrasse 3770 Zweisimmen. Postfach 448",
    "sg:city":"Zweisimmen",
    "sg:orig_category":"Detailhandel mit Bekleidung Detailhandel mit Sportartikeln",
    "sg:phone":"+41 33 722 18 39",
    "sg:postcode":"3770",
    "sg:province":"Bern",
    "wof:name":"Sporthaus Wittwer",
    "wof:placetype":"venue"
},
  "geometry": {"coordinates":[7.372545,46.553699],"type":"Point"}
}