{
  "type": "Feature",
  "properties": {
    "iso:country":"CH",
    "sg:address":"Sunnengartenstrasse 12",
    "sg:city":"Richterswil",
    "sg:orig_category":"Erschliessung von Grundst\u00fccken",
    "sg:phone":"+41 71 912 40 91",
    "sg:postcode":"8805",
    "sg:province":"Z\u00fcrich",
    "wof:name":"Baugenossenschaft Sunneschyn, Wil Sg",
    "wof:placetype":"venue"
},
  "geometry": {"coordinates":[9.0351228714,47.4611091614],"type":"Point"}
}