{
  "type": "Feature",
  "properties": {
    "iso:country":"CH",
    "sg:address":"Lyon Rue De 12 1201 Gen\u00e8ve. Postfach",
    "sg:city":"Gen\u00e8ve",
    "sg:orig_category":"Herstellung von Armaturen",
    "sg:postcode":"1201",
    "sg:province":"Gen\u00e8ve",
    "wof:name":"Fernandez Vaamonde Pose D'armatures En B\u00e9ton Arm\u00e9",
    "wof:placetype":"venue"
},
  "geometry": {"coordinates":[6.1395998001,46.1839904785],"type":"Point"}
}