{
  "type": "Feature",
  "properties": {
    "iso:country":"CH",
    "sg:address":"Kommetsr\u00fcti 51 6110 Wolhusen. Postfach 343",
    "sg:city":"Wolhusen",
    "sg:orig_category":"Stukkateurgewerbe, Gipserei U Verputzerei",
    "sg:phone":"+41 41 490 19 87",
    "sg:postcode":"6110",
    "sg:province":"Luzern",
    "wof:name":"Wicki Josef, Gipsergesch\u00e4ft Ag",
    "wof:placetype":"venue"
},
  "geometry": {"coordinates":[8.0683498383,47.0544891357],"type":"Point"}
}