{
  "type": "Feature",
  "properties": {
    "iso:country":"CH",
    "sg:address":"Ruelle Du Temple 3",
    "sg:city":"Orbe",
    "sg:classifiers":[
        {
            "category":"Government",
            "subcategory":"Post Office",
            "type":"Public Place"
        }
    ],
    "sg:phone":"+41 24 441 83 03",
    "sg:postcode":"1350",
    "sg:province":"Vaud",
    "sg:tags":[
        "caf\u00e9s",
        "tea-rooms"
    ],
    "wof:name":"Tea-room Le City",
    "wof:placetype":"venue"
},
  "geometry": {"coordinates":[6.5323882103,46.7247962952],"type":"Point"}
}