{
  "type": "Feature",
  "properties": {
    "iso:country":"CH",
    "sg:address":"J.-c.-heer-strasse 25",
    "sg:city":"D\u00fcrnten",
    "sg:orig_category":"Handelsvermittlung U Grosshandel",
    "sg:phone":"+41 55 240 76 54",
    "sg:postcode":"8635",
    "sg:province":"Z\u00fcrich",
    "wof:name":"Hombi Trading Ltd.liab.co Import/export Australien",
    "wof:placetype":"venue"
},
  "geometry": {"coordinates":[8.8743000031,47.2758865356],"type":"Point"}
}