{
  "type": "Feature",
  "properties": {
    "iso:country":"CH",
    "sg:address":"Florastrasse 28 8008 Z\u00fcrich. Postfach",
    "sg:city":"Z\u00fcrich",
    "sg:orig_category":"Pensionskassen",
    "sg:phone":"+41 14212010",
    "sg:postcode":"8001",
    "sg:province":"Z\u00fcrich",
    "wof:name":"Personalstiftung Der Inter-unitek Ag Bvg",
    "wof:placetype":"venue"
},
  "geometry": {"coordinates":[8.5504846573,47.3611068726],"type":"Point"}
}