{
  "type": "Feature",
  "properties": {
    "iso:country":"CH",
    "sg:address":"Hauptstrasse 75",
    "sg:city":"Ermatingen",
    "sg:orig_category":"Fachdetailhandel in Verkaufsr\u00e4umen",
    "sg:postcode":"8272",
    "sg:province":"Thurgau",
    "wof:name":"S'dr\u00dcckli Behr Ursula",
    "wof:placetype":"venue"
},
  "geometry": {"coordinates":[9.0783662796,47.6694488525],"type":"Point"}
}