{
  "type": "Feature",
  "properties": {
    "iso:country":"CH",
    "sg:address":"Rue Des Vernes 11",
    "sg:city":"Payerne",
    "sg:orig_category":"Verlegen von Fliesen U Platten",
    "sg:phone":"+41 56 622 54 72",
    "sg:postcode":"1530",
    "sg:province":"Vaud",
    "wof:name":"Roland Walser Plattenbel\u00e4ge Gmbh",
    "wof:placetype":"venue"
},
  "geometry": {"coordinates":[8.2865018845,47.3515739441],"type":"Point"}
}