{
  "type": "Feature",
  "properties": {
    "addr:full":"Dorfstr. 28 Dintikon Aargau 5606",
    "addr:housenumber":"28",
    "addr:postcode":"5606",
    "addr:street":"Dorfstr.",
    "iso:country":"CH",
    "sg:address":"Dorfstr. 28",
    "sg:city":"Dintikon",
    "sg:classifiers":[
        {
            "category":"Banks & Credit Unions",
            "subcategory":"Bank",
            "type":"Services"
        }
    ],
    "sg:phone":"+41 56 624 11 78",
    "sg:postcode":"5606",
    "sg:province":"Aargau",
    "wof:name":"Raiffeisenbank",
    "wof:placetype":"venue"
},
  "geometry": {"coordinates":[8.229086,47.365734],"type":"Point"}
}