{
  "type": "Feature",
  "properties": {
    "iso:country":"CH",
    "sg:address":"Rue De Gen\u00e8ve 150 1226 Th\u00f4nex Case Postale 111",
    "sg:city":"Th\u00f4nex",
    "sg:orig_category":"Architektur U Ingenieurb\u00fcros",
    "sg:phone":"+41 22 349 11 95",
    "sg:postcode":"1226",
    "sg:province":"Gen\u00e8ve",
    "wof:name":"Setri Sa Bureau Technique",
    "wof:placetype":"venue"
},
  "geometry": {"coordinates":[6.20593,46.192089],"type":"Point"}
}