{
  "type": "Feature",
  "properties": {
    "iso:country":"CH",
    "sg:address":"4803",
    "sg:city":"Vordemwald",
    "sg:orig_category":"Organisationen des Gesundheitswesen",
    "sg:phone":"+41 62 751 98 75",
    "sg:postcode":"4803",
    "sg:province":"Aargau",
    "wof:name":"Samariterverein Vordemwald",
    "wof:placetype":"venue"
},
  "geometry": {"coordinates":[7.9015169144,47.2758522034],"type":"Point"}
}