{
  "type": "Feature",
  "properties": {
    "iso:country":"CH",
    "sg:address":"Christoph-schnyder-strasse 1c 6210 Sursee. Postfach 52",
    "sg:city":"Sursee",
    "sg:orig_category":"Vermittlung von Immobilien Verwaltung von Immobilien",
    "sg:phone":"+41 41 921 61 61",
    "sg:postcode":"6210",
    "sg:province":"Luzern",
    "wof:name":"Bdo Visura",
    "wof:placetype":"venue"
},
  "geometry": {"coordinates":[8.1021928787,47.1717567444],"type":"Point"}
}