{
  "type": "Feature",
  "properties": {
    "iso:country":"CH",
    "sg:address":"Apfelbaumstrasse 39",
    "sg:city":"Z\u00fcrich",
    "sg:orig_category":"Herstellung von Ger\u00e4ten der Elektrizit\u00e4tserzeugung, -verteilung u.\u00e4. -Herstellung von elektronischen",
    "sg:phone":"+41 13086644",
    "sg:postcode":"8050",
    "sg:province":"Z\u00fcrich",
    "wof:name":"Marti-systemtechnik",
    "wof:placetype":"venue"
},
  "geometry": {"coordinates":[8.5562791824,47.4072189331],"type":"Point"}
}