{
  "type": "Feature",
  "properties": {
    "iso:country":"CH",
    "sg:address":"Birchrainstrasse 3",
    "sg:city":"Lufingen",
    "sg:orig_category":"Hilfs U Nebent\u00e4tigkeiten f\u00fcr den Verkehr Personal U Stellenvermittlung Reiseb\u00fcros",
    "sg:postcode":"8426",
    "sg:province":"Z\u00fcrich",
    "wof:name":"Rufus Greenhalgh Operations Officer",
    "wof:placetype":"venue"
},
  "geometry": {"coordinates":[8.5917139053,47.4866027832],"type":"Point"}
}