{
  "type": "Feature",
  "properties": {
    "iso:country":"CH",
    "sg:address":"Via Cereda",
    "sg:city":"Novazzano",
    "sg:orig_category":"Gartenbau",
    "sg:phone":"+41 79 350 60 15",
    "sg:postcode":"6883",
    "sg:province":"Ticino",
    "wof:name":"Giuseppe Gigliotti Manutenzione Giardini",
    "wof:placetype":"venue"
},
  "geometry": {"coordinates":[8.9968709946,45.8445854187],"type":"Point"}
}