{
  "type": "Feature",
  "properties": {
    "iso:country":"CH",
    "sg:address":"Zentralstrasse 45 2502 Biel/bienne Case Postale 1117",
    "sg:city":"Biel/bienne",
    "sg:classifiers":[
        {
            "category":"Professional",
            "subcategory":"Employment Agencies",
            "type":"Services"
        }
    ],
    "sg:phone":"+41 32 322 55 22",
    "sg:postcode":"2501",
    "sg:province":"Bern",
    "sg:tags":[
        "personal",
        "u",
        "stellenvermittlung"
    ],
    "wof:name":"Adecco Ressources Humaines Sa",
    "wof:placetype":"venue"
},
  "geometry": {"coordinates":[7.2462539673,47.1374435425],"type":"Point"}
}