{
  "type": "Feature",
  "properties": {
    "iso:country":"CH",
    "sg:address":"Rue De La Corraterie 10 1200 Genf. Postfach",
    "sg:city":"Gen\u00e8ve",
    "sg:orig_category":"Interessenvertretungen",
    "sg:postcode":"1204",
    "sg:province":"Gen\u00e8ve",
    "wof:name":"Fondation Finance",
    "wof:placetype":"venue"
},
  "geometry": {"coordinates":[6.1428990364,46.2032966614],"type":"Point"}
}