{
  "type": "Feature",
  "properties": {
    "iso:country":"CH",
    "sg:address":"M\u00f6slistrasse",
    "sg:city":"Heinrichswil",
    "sg:orig_category":"Politische Parteien FDP",
    "sg:postcode":"4558",
    "sg:province":"Solothurn",
    "wof:name":"Fdp Ortspartei Heinrichswil",
    "wof:placetype":"venue"
},
  "geometry": {"coordinates":[7.6406869888,47.1599731445],"type":"Point"}
}