{
  "type": "Feature",
  "properties": {
    "iso:country":"CH",
    "sg:address":"Sonnmattstrasse 10a",
    "sg:city":"Hasle-r\u00fcegsau",
    "sg:orig_category":"Unclassifiable Establishments",
    "sg:phone":"+41 34 461 39 31",
    "sg:postcode":"3415",
    "sg:province":"Bern",
    "wof:name":"Chalilow Consulting",
    "wof:placetype":"venue"
},
  "geometry": {"coordinates":[7.6564340591,47.0159950256],"type":"Point"}
}