{
  "type": "Feature",
  "properties": {
    "iso:country":"CH",
    "sg:address":"Unterfeldstrasse 35",
    "sg:city":"L\u00fcterkofen-ichert",
    "sg:orig_category":"Saunas Solarien",
    "sg:phone":"+41 32 677 14 35",
    "sg:postcode":"4571",
    "sg:province":"Solothurn",
    "wof:name":"Ernst Robert & Livia Mattiello Sauna Solarium Massage",
    "wof:placetype":"venue"
},
  "geometry": {"coordinates":[7.5184202194,47.1613693237],"type":"Point"}
}