{
  "type": "Feature",
  "properties": {
    "iso:country":"CH",
    "sg:address":"Engelgasse 7",
    "sg:city":"Zofingen",
    "sg:classifiers":[
        {
            "category":"Restaurant",
            "type":"Food & Drink"
        }
    ],
    "sg:phone":"+41 62 751 10 86",
    "sg:postcode":"4800",
    "sg:province":"Aargau",
    "wof:name":"Restaurant J\u00e4gerst\u00fcbli",
    "wof:placetype":"venue"
},
  "geometry": {"coordinates":[7.9459581375,47.2880554199],"type":"Point"}
}