{
  "type": "Feature",
  "properties": {
    "iso:country":"CH",
    "sg:address":"S\u00e4ntisstrasse 20",
    "sg:city":"Dietlikon",
    "sg:orig_category":"Sonstige mit der Informatik verbundene T\u00e4tigkeiten",
    "sg:postcode":"8305",
    "sg:province":"Z\u00fcrich",
    "wof:name":"Charles Elber Edv Schulung + Programmierung",
    "wof:placetype":"venue"
},
  "geometry": {"coordinates":[8.6198654175,47.4235916138],"type":"Point"}
}