{
  "type": "Feature",
  "properties": {
    "iso:country":"CH",
    "sg:address":"Ueberlandstrasse 295",
    "sg:city":"Z\u00fcrich",
    "sg:orig_category":"Sonstiger Grosshandel",
    "sg:phone":"+41 13225040",
    "sg:postcode":"8051",
    "sg:province":"Z\u00fcrich",
    "wof:name":"Ukz Handels Ag",
    "wof:placetype":"venue"
},
  "geometry": {"coordinates":[8.5776090622,47.4095802307],"type":"Point"}
}