{
  "type": "Feature",
  "properties": {
    "iso:country":"CH",
    "sg:address":"Kantonsstrasse 5",
    "sg:city":"Visp",
    "sg:orig_category":"Herstellung von medizinischen U chirurgischen Ger\u00e4ten sowie orthop\u00e4dischen Vorrichtungen",
    "sg:postcode":"3930",
    "sg:province":"Valais",
    "wof:name":"Locher Orthop\u00e4die.",
    "wof:placetype":"venue"
},
  "geometry": {"coordinates":[7.8804960251,46.2924385071],"type":"Point"}
}