{
  "type": "Feature",
  "properties": {
    "iso:country":"CH",
    "sg:address":"Tr\u00e9velin Rue De 2",
    "sg:city":"Aubonne",
    "sg:orig_category":"Unclassifiable Establishments",
    "sg:postcode":"1170",
    "sg:province":"Vaud",
    "wof:name":"Boutique Tee Time, Dominique Chabloz",
    "wof:placetype":"venue"
},
  "geometry": {"coordinates":[6.3915920258,46.4948806763],"type":"Point"}
}