{
  "type": "Feature",
  "properties": {
    "iso:country":"CH",
    "sg:address":"Coin D'en-haut 4",
    "sg:city":"Belmont-lausanne",
    "sg:classifiers":[
        {
            "category":"Restaurant",
            "type":"Food & Drink"
        }
    ],
    "sg:phone":"+41 21 728 09 03",
    "sg:postcode":"1092",
    "sg:province":"Vaud",
    "wof:name":"Auberge Communale",
    "wof:placetype":"venue"
},
  "geometry": {"coordinates":[6.6801738739,46.5198783875],"type":"Point"}
}