{
  "type": "Feature",
  "properties": {
    "iso:country":"CH",
    "sg:address":"Oberstadtstrasse 4",
    "sg:city":"Frauenfeld",
    "sg:orig_category":"Wirtschaftspr\u00fcfung, Steuerberatung U Treuhand",
    "sg:phone":"+41 71 242 00 60",
    "sg:postcode":"8500",
    "sg:province":"Thurgau",
    "wof:name":"Obtg Ostschweizerische B\u00fcrgschafts Und Treuhandgenossenschaft F\u00f6rderung Von Klein Und Mittelbetrieben Usw",
    "wof:placetype":"venue"
},
  "geometry": {"coordinates":[9.3951749802,47.4311218262],"type":"Point"}
}