{
  "type": "Feature",
  "properties": {
    "iso:country":"CH",
    "sg:address":"Kembergstrasse 24",
    "sg:city":"Cham",
    "sg:orig_category":"Unternehmensberatung",
    "sg:phone":"+41 41 780 05 50",
    "sg:postcode":"6330",
    "sg:province":"Zug",
    "wof:name":"Buijs Consulting",
    "wof:placetype":"venue"
},
  "geometry": {"coordinates":[8.4444351196,47.1742744446],"type":"Point"}
}