{
  "type": "Feature",
  "properties": {
    "iso:country":"CH",
    "sg:address":"Heimstrasse 10",
    "sg:city":"Diepoldsau",
    "sg:classifiers":[
        {
            "category":"Social Services",
            "subcategory":"Retirement Home",
            "type":"Services"
        }
    ],
    "sg:phone":"+41 71 999 11 34",
    "sg:postcode":"9444",
    "sg:province":"St. Gallen",
    "sg:tags":[
        "pflegeheime",
        "u",
        "alters"
    ],
    "wof:name":"Altersheim",
    "wof:placetype":"venue"
},
  "geometry": {"coordinates":[9.28492,47.193584],"type":"Point"}
}