{
  "type": "Feature",
  "properties": {
    "iso:country":"CH",
    "sg:address":"Pilgerweg 13",
    "sg:city":"Richterswil",
    "sg:orig_category":"Architektur U Ingenieurb\u00fcros",
    "sg:phone":"+41 41 870 46 66",
    "sg:postcode":"8805",
    "sg:province":"Z\u00fcrich",
    "wof:name":"Ingenieurb\u00fcro Duwaplan Gmbh",
    "wof:placetype":"venue"
},
  "geometry": {"coordinates":[8.641665,46.882793],"type":"Point"}
}