{
  "type": "Feature",
  "properties": {
    "iso:country":"CH",
    "sg:address":"H\u00f6henweg 21",
    "sg:city":"M\u00f6rigen",
    "sg:orig_category":"Sportvereine Flug Aero-Club",
    "sg:phone":"+41 32 397 16 27",
    "sg:postcode":"2572",
    "sg:province":"Bern",
    "wof:name":"Ae.c.s.segelfluggruppe Biel",
    "wof:placetype":"venue"
},
  "geometry": {"coordinates":[7.2120008469,47.0800933838],"type":"Point"}
}