{
  "type": "Feature",
  "properties": {
    "iso:country":"CH",
    "sg:address":"1813",
    "sg:city":"St-saphorin-lavaux",
    "sg:orig_category":"Rebbau",
    "sg:phone":"+41 21 921 29 74",
    "sg:postcode":"1813",
    "wof:name":"Etat De Fribourg Domaine Viticole Des Faverges",
    "wof:placetype":"venue"
},
  "geometry": {"coordinates":[6.7959570885,46.4733009338],"type":"Point"}
}