{
  "type": "Feature",
  "properties": {
    "iso:country":"CH",
    "sg:address":"Guggerstr. 41",
    "sg:city":"Zollikon",
    "sg:orig_category":"Sonstiger Grosshandel",
    "sg:postcode":"8702",
    "sg:province":"Z\u00fcrich",
    "wof:name":"De Haas, Import-export",
    "wof:placetype":"venue"
},
  "geometry": {"coordinates":[8.5735282898,47.332572937],"type":"Point"}
}