{
  "type": "Feature",
  "properties": {
    "iso:country":"CH",
    "sg:address":"Emmenhofstrasse 4",
    "sg:city":"Derendingen",
    "sg:orig_category":"Vermittlung von Immobilien Verwaltung von Immobilien",
    "sg:phone":"+41 32 682 43 29",
    "sg:postcode":"4552",
    "sg:province":"Solothurn",
    "wof:name":"Emmenhof Immobilien Ag",
    "wof:placetype":"venue"
},
  "geometry": {"coordinates":[7.5832080841,47.1952476501],"type":"Point"}
}