{
  "type": "Feature",
  "properties": {
    "iso:country":"CH",
    "sg:address":"Kanalstrasse 12",
    "sg:city":"Baden",
    "sg:orig_category":"Sportvereine Ballsport Handball",
    "sg:phone":"+41 71 385 69 41",
    "sg:postcode":"5400",
    "sg:province":"Aargau",
    "wof:name":"Tsv Fortitudo Gossau",
    "wof:placetype":"venue"
},
  "geometry": {"coordinates":[9.2548904419,47.4220199585],"type":"Point"}
}