{
  "type": "Feature",
  "properties": {
    "iso:country":"CH",
    "sg:address":"6636",
    "sg:city":"Frasco",
    "sg:classifiers":[
        {
            "category":"Restaurant",
            "type":"Food & Drink"
        }
    ],
    "sg:phone":"+41 91 746 11 72",
    "sg:postcode":"6636",
    "sg:province":"Ticino",
    "wof:name":"Ristorante Efra",
    "wof:placetype":"venue"
},
  "geometry": {"coordinates":[8.8020801544,46.3401947021],"type":"Point"}
}