{
  "type": "Feature",
  "properties": {
    "iso:country":"CH",
    "sg:address":"Baumgartenstrasse 14",
    "sg:city":"M\u00e4genwil",
    "sg:orig_category":"Grosshandel mit Erzen U Metallen",
    "sg:phone":"+41 62 887 41 00",
    "sg:postcode":"5506",
    "sg:province":"Aargau",
    "wof:name":"Dynamic Steel Ag",
    "wof:placetype":"venue"
},
  "geometry": {"coordinates":[8.2291517258,47.4126281738],"type":"Point"}
}