{
  "type": "Feature",
  "properties": {
    "addr:full":"Alpsteinstrasse 4 Eggersriet St. Gallen 9034",
    "addr:housenumber":"4",
    "addr:postcode":"9034",
    "addr:street":"Alpsteinstrasse",
    "iso:country":"CH",
    "sg:address":"Alpsteinstrasse 4",
    "sg:city":"Eggersriet",
    "sg:orig_category":"Architektur U Ingenieurb\u00fcros",
    "sg:phone":"+41 71 877 14 11",
    "sg:postcode":"9034",
    "sg:province":"St. Gallen",
    "wof:name":"Peter Bretscher Ingenieurb\u00fcro F\u00fcr Wirtschaftsentwicklung",
    "wof:placetype":"venue"
},
  "geometry": {"coordinates":[9.47718,47.441628],"type":"Point"}
}