{
  "type": "Feature",
  "properties": {
    "iso:country":"CH",
    "sg:address":"Ebnifeld 2 9523 Z\u00fcberwangen. Postfach",
    "sg:city":"Z\u00fcberwangen",
    "sg:orig_category":"Softwareentwicklung U beratung",
    "sg:postcode":"9523",
    "sg:province":"St. Gallen",
    "wof:name":"Mc Control Gmbh",
    "wof:placetype":"venue"
},
  "geometry": {"coordinates":[9.0829000473,47.4670562744],"type":"Point"}
}