{
  "type": "Feature",
  "properties": {
    "iso:country":"CH",
    "sg:address":"Rangiers Rue Des 1 2350 Saignel\u00e9gier. Postfach",
    "sg:city":"Saignel\u00e9gier",
    "sg:orig_category":"Detailhandel mit Fleisch U Fleischwaren",
    "sg:postcode":"2350",
    "sg:province":"Jura",
    "wof:name":"Paratte Romain Boucherie-charcuterie",
    "wof:placetype":"venue"
},
  "geometry": {"coordinates":[6.9971299171,47.256061554],"type":"Point"}
}