{
  "type": "Feature",
  "properties": {
    "iso:country":"CH",
    "sg:address":"Gr\u00fcttstrasse 9",
    "sg:city":"Derendingen",
    "sg:orig_category":"Tierheime",
    "sg:phone":"+41 32 682 23 91",
    "sg:postcode":"4552",
    "sg:province":"Solothurn",
    "wof:name":"Marlies Stuber Tierheim",
    "wof:placetype":"venue"
},
  "geometry": {"coordinates":[7.5787529945,47.1840362549],"type":"Point"}
}