{
  "type": "Feature",
  "properties": {
    "iso:country":"CH",
    "sg:address":"Weinsteig 69",
    "sg:city":"Schaffhausen",
    "sg:orig_category":"Detailhandel mit Waren verschiedener Art, Hauptrichtung Nahrungsmittel",
    "sg:phone":"+41 52 624 19 80",
    "sg:postcode":"8200",
    "sg:province":"Schaffhausen",
    "wof:name":"Hans Ruedi Sommer Geissberg Lebensmittel",
    "wof:placetype":"venue"
},
  "geometry": {"coordinates":[8.6323471069,47.7037162781],"type":"Point"}
}