{
  "type": "Feature",
  "properties": {
    "iso:country":"CH",
    "sg:address":"Brunnmattstrasse 10",
    "sg:city":"R\u00fcegsauschachen",
    "sg:orig_category":"Versicherungsagenturen and -broker -Verm\u00f6gensverwaltung",
    "sg:phone":"+41 34 461 29 09",
    "sg:postcode":"3415",
    "sg:province":"Bern",
    "wof:name":"Toni Niederhauser Versicherungen",
    "wof:placetype":"venue"
},
  "geometry": {"coordinates":[7.6620459557,47.014289856],"type":"Point"}
}