{
  "type": "Feature",
  "properties": {
    "iso:country":"CH",
    "sg:address":"Schwyzerstrasse 30 8805 Richterswil. Postfach",
    "sg:city":"Richterswil",
    "sg:orig_category":"Kauf U Verkauf von Immobilien auf eigene Rechnung",
    "sg:postcode":"8805",
    "sg:province":"Z\u00fcrich",
    "wof:name":"Faessler W. A. Ag",
    "wof:placetype":"venue"
},
  "geometry": {"coordinates":[9.3855466843,47.4420814514],"type":"Point"}
}