{
  "type": "Feature",
  "properties": {
    "iso:country":"CH",
    "sg:address":"Reussstrasse 7",
    "sg:city":"M\u00fchlau",
    "sg:orig_category":"D\u00e4mmung gegen K\u00e4lte, W\u00e4rme, Schall U Ersch\u00fctterung",
    "sg:phone":"+41 56 668 10 19",
    "sg:postcode":"5642",
    "sg:province":"Aargau",
    "wof:name":"Olivier Nicoulaz Isolierungen",
    "wof:placetype":"venue"
},
  "geometry": {"coordinates":[8.3939266205,47.2259216309],"type":"Point"}
}