{
  "type": "Feature",
  "properties": {
    "iso:country":"CH",
    "sg:address":"Bahnhofplatz 10 3011 Bern. Postfach",
    "sg:city":"Basel",
    "sg:orig_category":"Linienflugverkehr",
    "sg:phone":"+41 61 325 25 25",
    "sg:postcode":"4051",
    "sg:province":"Basel-Stadt",
    "wof:name":"Crossair Ag",
    "wof:placetype":"venue"
},
  "geometry": {"coordinates":[7.4402651787,46.9489097595],"type":"Point"}
}