{
  "type": "Feature",
  "properties": {
    "iso:country":"CH",
    "sg:address":"Luzernstrasse 177",
    "sg:city":"Etziken",
    "sg:orig_category":"Pensionskassen",
    "sg:postcode":"4554",
    "sg:province":"Solothurn",
    "wof:name":"Personalf\u00fcrsorgestiftung Der Firma Urben & Kyburz Ag, Optik Und Mechanik.",
    "wof:placetype":"venue"
},
  "geometry": {"coordinates":[7.6557202339,47.18516922],"type":"Point"}
}