{
  "type": "Feature",
  "properties": {
    "iso:country":"CH",
    "sg:address":"Metzgergasse 4",
    "sg:city":"Arbon",
    "sg:orig_category":"Sonstiger Fachdetailhandel mit Nahrungsmitteln, Getr\u00e4nken U Tabak in Verkaufsr\u00e4umen Verarbeitung von",
    "sg:phone":"+41 71 446 12 23",
    "sg:postcode":"9320",
    "sg:province":"Thurgau",
    "wof:name":"Leibacher Hans.",
    "wof:placetype":"venue"
},
  "geometry": {"coordinates":[9.4352769852,47.5154876709],"type":"Point"}
}