{
  "type": "Feature",
  "properties": {
    "iso:country":"CH",
    "sg:address":"Nicolas Glasson Rue 7 1630 Bulle. Postfach",
    "sg:city":"Bulle",
    "sg:orig_category":"Vermietung U Verpachtung von eigenen Immobilien",
    "sg:postcode":"1630",
    "sg:province":"Fribourg",
    "wof:name":"Groupe Geco Sa, Succursale De Bulle Immeubles Etc",
    "wof:placetype":"venue"
},
  "geometry": {"coordinates":[7.0555849075,46.6173324585],"type":"Point"}
}