{
  "type": "Feature",
  "properties": {
    "iso:country":"CH",
    "sg:address":"Zopfmatt 1",
    "sg:city":"Willisau",
    "sg:orig_category":"Sonstiges Gesundheitswesen",
    "sg:phone":"+41 41 970 16 50",
    "sg:postcode":"6130",
    "sg:province":"Luzern",
    "wof:name":"Krankenmobilienmagazin Frau Lydia Mehr",
    "wof:placetype":"venue"
},
  "geometry": {"coordinates":[7.980535984,47.1189651489],"type":"Point"}
}