{
  "type": "Feature",
  "properties": {
    "iso:country":"CH",
    "sg:address":"Hintergoldingerstrasse 78",
    "sg:city":"Goldingen",
    "sg:orig_category":"Herstellung von sonstigen landwirtschaftlichen Maschinen",
    "sg:phone":"+41 55 284 14 76",
    "sg:postcode":"8638",
    "sg:province":"St. Gallen",
    "wof:name":"Bl\u00f6chlinger Franz",
    "wof:placetype":"venue"
},
  "geometry": {"coordinates":[8.9728899002,47.2744598389],"type":"Point"}
}