{
  "type": "Feature",
  "properties": {
    "iso:country":"CH",
    "sg:address":"3154 R\u00fcschegg Graben. Postfach",
    "sg:city":"Hirschhorn",
    "sg:orig_category":"Zimmerei, Dachdeckerei, Bauspenglerei U Abdichtung",
    "sg:phone":"+41 31 738 81 44",
    "sg:postcode":"3153",
    "sg:province":"Bern",
    "wof:name":"Hans Rohrbach",
    "wof:placetype":"venue"
},
  "geometry": {"coordinates":[7.4180898666,46.7700996399],"type":"Point"}
}