{
  "type": "Feature",
  "properties": {
    "iso:country":"CH",
    "sg:address":"Aarbergstrasse 66 2503 Biel/bienne. Postfach",
    "sg:city":"Biel/bienne",
    "sg:orig_category":"Architektur U Ingenieurb\u00fcros",
    "sg:phone":"+41 32 325 43 40",
    "sg:postcode":"2503",
    "sg:province":"Bern",
    "wof:name":"Arteplage Biel Gmbh",
    "wof:placetype":"venue"
},
  "geometry": {"coordinates":[7.23976,47.131119],"type":"Point"}
}