{
  "type": "Feature",
  "properties": {
    "iso:country":"CH",
    "sg:address":"Untere Laubegg",
    "sg:city":"H\u00fctten",
    "sg:orig_category":"Datenverarbeitungsdienste",
    "sg:postcode":"8825",
    "sg:province":"Z\u00fcrich",
    "wof:name":"Agro-pc",
    "wof:placetype":"venue"
},
  "geometry": {"coordinates":[7.92799,47.154179],"type":"Point"}
}