{
  "type": "Feature",
  "properties": {
    "iso:country":"CH",
    "sg:address":"Chemin De Ros\u00e9az 6",
    "sg:city":"Bussigny-lausanne",
    "sg:orig_category":"Herstellung von Seifen, Wasch U Reinigungsmitteln",
    "sg:postcode":"1030",
    "sg:province":"Vaud",
    "wof:name":"Maison Vaprosa, Pierre-andr\u00e9 Joss.",
    "wof:placetype":"venue"
},
  "geometry": {"coordinates":[6.5542621613,46.5489463806],"type":"Point"}
}