{
  "type": "Feature",
  "properties": {
    "iso:country":"CH",
    "sg:address":"Wilemattsrasse 30",
    "sg:city":"Sursee",
    "sg:orig_category":"G\u00fcterbef\u00f6rderung im Strassenverkehr",
    "sg:phone":"+41 41 921 38 38",
    "sg:postcode":"6210",
    "sg:province":"Luzern",
    "wof:name":"Hunkeler Transport Ag",
    "wof:placetype":"venue"
},
  "geometry": {"coordinates":[8.1103200912,47.1689186096],"type":"Point"}
}