{
  "type": "Feature",
  "properties": {
    "iso:country":"CH",
    "sg:address":"Ganzenbreitestrasse 2",
    "sg:city":"Hochfelden",
    "sg:orig_category":"Finanzierungsinstitutionen",
    "sg:postcode":"8182",
    "sg:province":"Z\u00fcrich",
    "wof:name":"Suprima Gmbh",
    "wof:placetype":"venue"
},
  "geometry": {"coordinates":[8.5146856308,47.5212402344],"type":"Point"}
}