{
  "type": "Feature",
  "properties": {
    "iso:country":"CH",
    "sg:address":"St. Jakob-strasse 37",
    "sg:city":"St.gallen",
    "sg:orig_category":"Pensionskassen",
    "sg:phone":"+41 71 243 43 44",
    "sg:postcode":"9000",
    "sg:province":"St. Gallen",
    "wof:name":"Patronale F\u00fcrsorgestiftung Der Brauerei Sch\u00fctzengarten Ag",
    "wof:placetype":"venue"
},
  "geometry": {"coordinates":[8.4765996933,48.0781707764],"type":"Point"}
}