{
  "type": "Feature",
  "properties": {
    "iso:country":"CH",
    "sg:address":"Rue Cantonale 92",
    "sg:city":"V\u00e9troz",
    "sg:orig_category":"Nationale Postdienste",
    "sg:phone":"+41 27 346 13 40",
    "sg:postcode":"1963",
    "sg:province":"Valais",
    "wof:name":"La Poste Suisse",
    "wof:placetype":"venue"
},
  "geometry": {"coordinates":[7.2800102234,46.2256355286],"type":"Point"}
}