{
  "type": "Feature",
  "properties": {
    "iso:country":"CH",
    "sg:address":"H\u00f6schgasse 52 8008 Z\u00fcrich. Postfach",
    "sg:city":"Z\u00fcrich",
    "sg:orig_category":"Vermietung von Gebrauchsg\u00fctern",
    "sg:postcode":"8001",
    "sg:province":"Z\u00fcrich",
    "wof:name":"Tabesh Video-verleih",
    "wof:placetype":"venue"
},
  "geometry": {"coordinates":[8.554816246,47.3577041626],"type":"Point"}
}