{
  "type": "Feature",
  "properties": {
    "addr:full":"Eyhalde 18 Aarwangen Bern 4912",
    "addr:housenumber":"18",
    "addr:postcode":"4912",
    "addr:street":"Eyhalde",
    "iso:country":"CH",
    "sg:address":"Eyhalde 18",
    "sg:city":"Aarwangen",
    "sg:orig_category":"Autolackierereien",
    "sg:phone":"+41 62 922 63 83",
    "sg:postcode":"4912",
    "sg:province":"Bern",
    "wof:name":"J\u00fcrg B\u00e4rtschi Automalerei",
    "wof:placetype":"venue"
},
  "geometry": {"coordinates":[7.764074,47.244789],"type":"Point"}
}