{
  "type": "Feature",
  "properties": {
    "addr:full":"Rue De Vevey 18 Bulle Fribourg 1630",
    "addr:housenumber":"18",
    "addr:postcode":"1630",
    "addr:street":"Rue De Vevey",
    "iso:country":"CH",
    "sg:address":"Rue De Vevey 18",
    "sg:city":"Bulle",
    "sg:classifiers":[
        {
            "category":"Manufacturing",
            "subcategory":"Glass & Minerals",
            "type":"Manufacturing & Wholesale Goods"
        }
    ],
    "sg:phone":"+41 32 913 68 33",
    "sg:postcode":"1630",
    "sg:province":"Fribourg",
    "sg:tags":[
        "cleaning",
        "agent"
    ],
    "wof:name":"Dick Optique",
    "wof:placetype":"venue"
},
  "geometry": {"coordinates":[6.824386,47.099751],"type":"Point"}
}