{
  "type": "Feature",
  "properties": {
    "iso:country":"CH",
    "sg:address":"4814",
    "sg:city":"Bottenwil",
    "sg:orig_category":"Sportvereine Sch\u00fctzen",
    "sg:phone":"+41 56 666 23 42",
    "sg:postcode":"4814",
    "sg:province":"Aargau",
    "wof:name":"Sch\u00fctzengesellschaft",
    "wof:placetype":"venue"
},
  "geometry": {"coordinates":[7.9994702339,47.2817802429],"type":"Point"}
}