{
  "type": "Feature",
  "properties": {
    "iso:country":"CH",
    "sg:address":"Heinrich Gujer-strasse 5",
    "sg:city":"Bauma",
    "sg:orig_category":"Detailhandel mit Radio U Fernsehger\u00e4ten Elektroinstallation",
    "sg:phone":"+41 52 386 13 66",
    "sg:postcode":"8494",
    "sg:province":"Z\u00fcrich",
    "wof:name":"Brizzi-elektro Ag",
    "wof:placetype":"venue"
},
  "geometry": {"coordinates":[8.8770914078,47.3684120178],"type":"Point"}
}