{
  "type": "Feature",
  "properties": {
    "iso:country":"CH",
    "sg:address":"Ceresio Via 41 6963 Pregassona. Postfach",
    "sg:city":"Pregassona",
    "sg:orig_category":"Unclassifiable Establishments",
    "sg:phone":"+41 81 756 00 56",
    "sg:postcode":"6963",
    "sg:province":"Ticino",
    "wof:name":"Biosk, B\u00e4rtschi Oskar",
    "wof:placetype":"venue"
},
  "geometry": {"coordinates":[9.4626941681,47.169380188],"type":"Point"}
}