{
  "type": "Feature",
  "properties": {
    "iso:country":"CH",
    "sg:address":"Winterthurerstrasse 660",
    "sg:city":"Z\u00fcrich",
    "sg:orig_category":"Arztpraxen",
    "sg:phone":"+41 13222068",
    "sg:postcode":"8051",
    "sg:province":"Z\u00fcrich",
    "wof:name":"Dr.med.robert Koch Arzt F\u00fcr Allgemeine Medizin",
    "wof:placetype":"venue"
},
  "geometry": {"coordinates":[8.581361,47.405834],"type":"Point"}
}