{
  "type": "Feature",
  "properties": {
    "iso:country":"CH",
    "sg:address":"Geissensteinring 12-14",
    "sg:city":"Luzern",
    "sg:orig_category":"Bauschreinerei Innenausbau",
    "sg:phone":"+41 41 360 28 33",
    "sg:postcode":"6005",
    "sg:province":"Luzern",
    "wof:name":"Franz Stocker Gmbh",
    "wof:placetype":"venue"
},
  "geometry": {"coordinates":[8.310081,47.039932],"type":"Point"}
}