{
  "type": "Feature",
  "properties": {
    "iso:country":"CH",
    "sg:address":"8522",
    "sg:city":"H\u00e4uslenen",
    "sg:orig_category":"Vorschulen, Kinderg\u00e4rten",
    "sg:phone":"+41 52 721 34 71",
    "sg:postcode":"8522",
    "sg:province":"Thurgau",
    "wof:name":"Kindergarten Altes Schulhaus",
    "wof:placetype":"venue"
},
  "geometry": {"coordinates":[8.9001302719,47.5204582214],"type":"Point"}
}