{
  "type": "Feature",
  "properties": {
    "iso:country":"CH",
    "sg:address":"Friedenstrasse 10",
    "sg:city":"Arbon",
    "sg:orig_category":"Sportvereine Ballsport Badminton",
    "sg:phone":"+41 71 446 82 20",
    "sg:postcode":"9320",
    "sg:province":"Thurgau",
    "wof:name":"Badminton-club Arbon",
    "wof:placetype":"venue"
},
  "geometry": {"coordinates":[9.4324769974,47.5152778625],"type":"Point"}
}