{
  "type": "Feature",
  "properties": {
    "iso:country":"CH",
    "sg:address":"Hauptstrasse 2",
    "sg:city":"Eiken",
    "sg:orig_category":"Sanit\u00e4r, Heizungs U L\u00fcftungsinstallation Sanit\u00e4rinstallation",
    "sg:phone":"+41 62 871 27 44",
    "sg:postcode":"5074",
    "sg:province":"Aargau",
    "wof:name":"A. Spaar",
    "wof:placetype":"venue"
},
  "geometry": {"coordinates":[7.9826450348,47.5350761414],"type":"Point"}
}