{
  "type": "Feature",
  "properties": {
    "iso:country":"CH",
    "sg:address":"Via Balestra 31/33",
    "sg:city":"Lugano",
    "sg:orig_category":"Public-Relations-Agenturen Unternehmensberatung",
    "sg:phone":"+41 62 824 86 77",
    "sg:postcode":"6900",
    "sg:province":"Ticino",
    "wof:name":"Inter-toicoma Gmbh",
    "wof:placetype":"venue"
},
  "geometry": {"coordinates":[8.0915975571,47.4052238464],"type":"Point"}
}