{
  "type": "Feature",
  "properties": {
    "iso:country":"CH",
    "sg:address":"Hauptstrasse 19 2560 Nidau. Postfach 500",
    "sg:city":"Nidau",
    "sg:orig_category":"Detailhandel mit Fleisch U Fleischwaren",
    "sg:phone":"+41 32 331 05 15",
    "sg:postcode":"2560",
    "sg:province":"Bern",
    "wof:name":"Peter Ziemer Metzgerei",
    "wof:placetype":"venue"
},
  "geometry": {"coordinates":[7.2404727936,47.1260566711],"type":"Point"}
}