{
  "type": "Feature",
  "properties": {
    "iso:country":"CH",
    "sg:address":"Br\u00fcckenweg 1",
    "sg:city":"Visp",
    "sg:orig_category":"Allgemeiner Hoch U Tiefbau Herstellung von Konstruktionsteilen, Fertigbauteilen U Ausbauelementen au",
    "sg:phone":"+41 27 945 13 35",
    "sg:postcode":"3930",
    "sg:province":"Valais",
    "wof:name":"Vitahaus Holzsystem Ag",
    "wof:placetype":"venue"
},
  "geometry": {"coordinates":[7.878356,46.294983],"type":"Point"}
}