{
  "type": "Feature",
  "properties": {
    "iso:country":"CH",
    "sg:address":"Badenerstrasse 172 8004 Z\u00fcrich. Postfach",
    "sg:city":"Z\u00fcrich",
    "sg:orig_category":"Informatikdienste",
    "sg:phone":"+41 22 920 29 30",
    "sg:postcode":"8036",
    "sg:province":"Z\u00fcrich",
    "wof:name":"Fides Information Services",
    "wof:placetype":"venue"
},
  "geometry": {"coordinates":[6.1256251335,46.2353439331],"type":"Point"}
}