{
  "type": "Feature",
  "properties": {
    "iso:country":"CH",
    "sg:address":"Brunnersmoosstrasse 13",
    "sg:city":"Balsthal",
    "sg:orig_category":"Autogaragen",
    "sg:phone":"+41 62 391 20 00",
    "sg:postcode":"4710",
    "sg:province":"Solothurn",
    "wof:name":"Garage Steiner & Schneeberger Gmbh",
    "wof:placetype":"venue"
},
  "geometry": {"coordinates":[7.67735,47.30817],"type":"Point"}
}