{
  "type": "Feature",
  "properties": {
    "iso:country":"CH",
    "sg:address":"Honegg",
    "sg:city":"Oberegg",
    "sg:orig_category":"RESTAURANTS: TEA-ROOMS",
    "sg:phone":"+41 71 755 13 91",
    "sg:postcode":"9413",
    "sg:province":"Appenzell Innerhoden",
    "wof:name":"Looser Melchior",
    "wof:placetype":"venue"
},
  "geometry": {"coordinates":[9.5503931046,47.4226455688],"type":"Point"}
}