{
  "type": "Feature",
  "properties": {
    "iso:country":"CH",
    "sg:address":"Wilstrasse 16",
    "sg:city":"D\u00fcbendorf",
    "sg:orig_category":"Detailhandel mit Beleuchtungs U Haushaltsgegenst\u00e4nden Detailhandel mit elektrischen Haushalts-,Radio",
    "sg:phone":"+41 18203133",
    "sg:postcode":"8600",
    "sg:province":"Z\u00fcrich",
    "wof:name":"Cdm Commercial Direct Marketing, Bichsel Erika",
    "wof:placetype":"venue"
},
  "geometry": {"coordinates":[8.61683,47.396343],"type":"Point"}
}