{
  "type": "Feature",
  "properties": {
    "iso:country":"CH",
    "sg:address":"1772 Grolley Case Postale 37",
    "sg:city":"Grolley",
    "sg:orig_category":"Detailhandel mit elektrischen Haushalts-,Radio U Fernsehger\u00e4ten sowie Musikinstrumenten",
    "sg:phone":"+41 26 475 16 57",
    "sg:postcode":"1772",
    "sg:province":"Fribourg",
    "wof:name":"Olivier Marius",
    "wof:placetype":"venue"
},
  "geometry": {"coordinates":[7.0707321167,46.8333053589],"type":"Point"}
}