{
  "type": "Feature",
  "properties": {
    "addr:full":"Aarbergergasse 20-22 3011 Bern. Postfach Bern Bern 3001",
    "addr:housenumber":"20-22",
    "addr:postcode":"3011;postfach;3001",
    "addr:street":"Aarbergergasse",
    "iso:country":"CH",
    "sg:address":"Aarbergergasse 20-22 3011 Bern. Postfach",
    "sg:city":"Bern",
    "sg:orig_category":"Aktivit\u00e4t der Bankinstitute",
    "sg:phone":"+41 8003203811",
    "sg:postcode":"3001",
    "sg:province":"Bern",
    "wof:name":"Migrosbank",
    "wof:placetype":"venue"
},
  "geometry": {"coordinates":[7.44315,46.949619],"type":"Point"}
}