{
  "type": "Feature",
  "properties": {
    "iso:country":"CH",
    "sg:address":"Eschenweg 5b 2542 Pieterlen. Postfach 228",
    "sg:city":"Pieterlen",
    "sg:orig_category":"Herstellung von Elektromotoren, Generatoren U Transformatoren Herstellung von Werkzeugen",
    "sg:phone":"+41 32 377 12 93",
    "sg:postcode":"2542",
    "sg:province":"Bern",
    "wof:name":"Big Ag F\u00fcr Elektromotoren Und Elektrowerkzeuge, Pieterlen (schweiz)",
    "wof:placetype":"venue"
},
  "geometry": {"coordinates":[7.3377280235,47.1730003357],"type":"Point"}
}