{
  "type": "Feature",
  "properties": {
    "iso:country":"CH",
    "sg:address":"Oberfeldstrasse 13",
    "sg:city":"Biglen",
    "sg:orig_category":"Sportvereine Turnen Vereine Damen",
    "sg:postcode":"3507",
    "sg:province":"Bern",
    "wof:name":"Frauenturnverein Stv Brienz",
    "wof:placetype":"venue"
},
  "geometry": {"coordinates":[8.036860466,46.7545585632],"type":"Point"}
}