{
  "type": "Feature",
  "properties": {
    "addr:full":"Brunaustrasse 22 Adetswil Z\u00fcrich 8345",
    "addr:housenumber":"22",
    "addr:postcode":"8345",
    "addr:street":"Brunaustrasse",
    "iso:country":"CH",
    "sg:address":"Brunaustrasse 22",
    "sg:city":"Adetswil",
    "sg:orig_category":"Architektur U Ingenieurb\u00fcros",
    "sg:phone":"+41 19391772",
    "sg:postcode":"8345",
    "sg:province":"Z\u00fcrich",
    "wof:name":"Protech-consulting Gmbh Ingenieurb\u00fcro",
    "wof:placetype":"venue"
},
  "geometry": {"coordinates":[8.844681,47.337746],"type":"Point"}
}