{
  "type": "Feature",
  "properties": {
    "iso:country":"CH",
    "sg:address":"Freudenbergstrasse 2 9242 Oberuzwil. Postfach",
    "sg:city":"Oberuzwil",
    "sg:orig_category":"Herstellung von Strumpfwaren",
    "sg:phone":"+41 71 951 56 03",
    "sg:postcode":"9242",
    "sg:province":"St. Gallen",
    "wof:name":"Strumpffabrik Rosengarten Ag",
    "wof:placetype":"venue"
},
  "geometry": {"coordinates":[9.1228666306,47.4316482544],"type":"Point"}
}