{
  "type": "Feature",
  "properties": {
    "iso:country":"CH",
    "sg:address":"Marschalkenstrasse 9",
    "sg:city":"Muttenz",
    "sg:orig_category":"Detailhandel mit Metallwaren, Anstrichmitteln, Glaswaren, Bau U Heimwerkerbedarf Glaserei",
    "sg:phone":"+41 79 447 14 19",
    "sg:postcode":"4132",
    "sg:province":"Basel-Landschaft",
    "wof:name":"Howald Glaserei Ag",
    "wof:placetype":"venue"
},
  "geometry": {"coordinates":[7.6503767967,47.530796051],"type":"Point"}
}