{
  "type": "Feature",
  "properties": {
    "iso:country":"CH",
    "sg:address":"Gerliswilerstr. 20 6032 Emmen. Postfach",
    "sg:city":"Emmenbr\u00fccke",
    "sg:orig_category":"Grosshandel mit Nahrungsmitteln, Getr\u00e4nken U Tabakwaren ohne ausgepr\u00e4gten Schwerpunkt",
    "sg:postcode":"6020",
    "sg:province":"Luzern",
    "wof:name":"Bouchaut & Cie La Petite Case \u00e0 Rhum Punchs Antillais",
    "wof:placetype":"venue"
},
  "geometry": {"coordinates":[70.93533325200001,20.7149791718],"type":"Point"}
}