{
  "type": "Feature",
  "properties": {
    "iso:country":"CH",
    "sg:address":"Les Bourguillards 7",
    "sg:city":"St-blaise",
    "sg:orig_category":"Nationale Postdienste",
    "sg:phone":"+41 27 761 12 68",
    "sg:postcode":"2072",
    "sg:province":"Neuch\u00e2tel",
    "wof:name":"La Poste Suisse",
    "wof:placetype":"venue"
},
  "geometry": {"coordinates":[6.3947701454,48.0577583313],"type":"Point"}
}