{
  "type": "Feature",
  "properties": {
    "iso:country":"CH",
    "sg:address":"Centralstrasse 14 2540 Grenchen. Postfach",
    "sg:city":"Grenchen",
    "sg:orig_category":"Fachdetailhandel mit pharmazeutischen Produkten",
    "sg:phone":"+41 32 652 72 72",
    "sg:postcode":"2540",
    "sg:province":"Solothurn",
    "wof:name":"Post-apotheke Marti",
    "wof:placetype":"venue"
},
  "geometry": {"coordinates":[7.3958530426,47.1933250427],"type":"Point"}
}