{
  "type": "Feature",
  "properties": {
    "iso:country":"CH",
    "sg:address":"Buholzstr. 14 6017 Ruswil. Postfach",
    "sg:city":"R\u00fcediswil",
    "sg:orig_category":"Instandhaltung U Reparatur von Automobilen",
    "sg:postcode":"6017",
    "sg:province":"Luzern",
    "wof:name":"Autohaus Frei W.",
    "wof:placetype":"venue"
},
  "geometry": {"coordinates":[8.0894899368,47.0600585938],"type":"Point"}
}