{
  "type": "Feature",
  "properties": {
    "iso:country":"CH",
    "sg:address":"Furtbachstrasse 5",
    "sg:city":"Buchs",
    "sg:orig_category":"Expert's Reports On Industrial Floors",
    "sg:phone":"+41 18445044",
    "sg:postcode":"8107",
    "sg:province":"Z\u00fcrich",
    "wof:name":"Texolit Ag",
    "wof:placetype":"venue"
},
  "geometry": {"coordinates":[8.4317331314,47.4512634277],"type":"Point"}
}