{
  "type": "Feature",
  "properties": {
    "iso:country":"CH",
    "sg:address":"Hauptstrasse 42 Islikon 8547 Gachnang. Postfach",
    "sg:city":"Islikon",
    "sg:orig_category":"Detailhandel mit Antiquit\u00e4ten U Gebrauchtwaren in Verkaufsr\u00e4umen Detailhandel mit Bekleidung",
    "sg:phone":"+41 52 375 25 52",
    "sg:postcode":"8546",
    "sg:province":"Thurgau",
    "wof:name":"Boulanger J. Bo Visage",
    "wof:placetype":"venue"
},
  "geometry": {"coordinates":[8.852095,47.537888],"type":"Point"}
}