{
  "type": "Feature",
  "properties": {
    "iso:country":"CH",
    "sg:address":"Enselweg 36c",
    "sg:city":"Schwadernau",
    "sg:orig_category":"Gem\u00fcsebau",
    "sg:phone":"+41 79 208 57 71",
    "sg:postcode":"2556",
    "sg:province":"Bern",
    "wof:name":"Alfred Gutknecht Gem\u00fcsebau",
    "wof:placetype":"venue"
},
  "geometry": {"coordinates":[7.3089489937,47.1186065674],"type":"Point"}
}