{
  "type": "Feature",
  "properties": {
    "addr:full":"Erlenweg 5 Neuenegg Bern 3176",
    "addr:housenumber":"5",
    "addr:postcode":"3176",
    "addr:street":"Erlenweg;Bern",
    "iso:country":"CH",
    "sg:address":"Erlenweg 5",
    "sg:city":"Neuenegg",
    "sg:orig_category":"Bauspenglerei Sanit\u00e4rinstallation",
    "sg:phone":"+41 31 741 01 74",
    "sg:postcode":"3176",
    "sg:province":"Bern",
    "wof:name":"Werner Gr\u00fctter Sanit\u00e4re Anlagen & Spenglerei",
    "wof:placetype":"venue"
},
  "geometry": {"coordinates":[7.306924,46.894768],"type":"Point"}
}