{
  "type": "Feature",
  "properties": {
    "iso:country":"CH",
    "sg:address":"Calvenweg 2 7304 Maienfeld. Postfach",
    "sg:city":"Chur",
    "sg:orig_category":"Sonstige pers\u00f6nliche Dienstleistungen",
    "sg:postcode":"7000",
    "sg:province":"Graubunden",
    "wof:name":"Tim International Gmbh",
    "wof:placetype":"venue"
},
  "geometry": {"coordinates":[8.4536466599,47.2786026001],"type":"Point"}
}