{
  "type": "Feature",
  "properties": {
    "iso:country":"CH",
    "sg:address":"Gibelhalde 10a",
    "sg:city":"Herisau",
    "sg:orig_category":"Sanit\u00e4r, Heizungs U L\u00fcftungsinstallation",
    "sg:phone":"+41 71 352 50 53",
    "sg:postcode":"9100",
    "sg:province":"Appenzell Ausserrhoden",
    "wof:name":"Ren\u00e9 Zwicker Sanit\u00e4r-akkord",
    "wof:placetype":"venue"
},
  "geometry": {"coordinates":[9.2945985794,47.3898010254],"type":"Point"}
}