{
  "type": "Feature",
  "properties": {
    "iso:country":"CH",
    "sg:address":"3512",
    "sg:city":"Walkringen",
    "sg:orig_category":"Organisationen des Gesundheitswesen",
    "sg:phone":"+41 55 440 55 87",
    "sg:postcode":"3512",
    "sg:province":"Bern",
    "wof:name":"Samariterverein Wangen",
    "wof:placetype":"venue"
},
  "geometry": {"coordinates":[8.8926000595,47.191368103],"type":"Point"}
}