{
  "type": "Feature",
  "properties": {
    "iso:country":"CH",
    "sg:address":"Im Ifang 7",
    "sg:city":"Effretikon",
    "sg:orig_category":"Gartenbau",
    "sg:phone":"+41 55 283 13 33",
    "sg:postcode":"8307",
    "sg:province":"Z\u00fcrich",
    "wof:name":"Ralph Frei Gartenbau",
    "wof:placetype":"venue"
},
  "geometry": {"coordinates":[9.0551662445,47.2227134705],"type":"Point"}
}