{
  "type": "Feature",
  "properties": {
    "iso:country":"CH",
    "sg:address":"Industriestrasse 10",
    "sg:city":"Zug",
    "sg:orig_category":"Detailhandel mit Getr\u00e4nken",
    "sg:phone":"+41 41 760 09 03",
    "sg:postcode":"6300",
    "sg:province":"Zug",
    "wof:name":"Weber-vonesch Ag Getr\u00e4nke Abholmarkt G\u00f6bli",
    "wof:placetype":"venue"
},
  "geometry": {"coordinates":[8.5182533264,47.1713447571],"type":"Point"}
}