{
  "type": "Feature",
  "properties": {
    "iso:country":"CH",
    "sg:address":"Via Vela 1",
    "sg:city":"Bellinzona",
    "sg:orig_category":"Versicherungen Hauptagenturen",
    "sg:phone":"+41 91 825 64 12",
    "sg:postcode":"6500",
    "sg:province":"Ticino",
    "wof:name":"Militare Ufficio Fed.dell' Assicurazione Militare Circ.",
    "wof:placetype":"venue"
},
  "geometry": {"coordinates":[9.0232048035,46.1943016052],"type":"Point"}
}