{
  "type": "Feature",
  "properties": {
    "iso:country":"CH",
    "sg:address":"Meierwiesenstrasse 4",
    "sg:city":"Z\u00fcrich",
    "sg:orig_category":"Grosshandel mit pharmazeutischen Erzeugnissen, medizinischen U orthop\u00e4dischen Artikeln",
    "sg:phone":"+41 14311946",
    "sg:postcode":"8064",
    "sg:province":"Z\u00fcrich",
    "wof:name":"Medicenter Khan Enterprise",
    "wof:placetype":"venue"
},
  "geometry": {"coordinates":[8.4944953918,47.398109436],"type":"Point"}
}