{
  "type": "Feature",
  "properties": {
    "iso:country":"CH",
    "sg:address":"M\u00fchlebachweg 5",
    "sg:city":"Grossh\u00f6chstetten",
    "sg:orig_category":"Vermittlung von Immobilien Verwaltung von Immobilien",
    "sg:phone":"+41 31 380 69 79",
    "sg:postcode":"3506",
    "sg:province":"Bern",
    "wof:name":"Revag Immobilien Ag",
    "wof:placetype":"venue"
},
  "geometry": {"coordinates":[7.4302968979,46.9436187744],"type":"Point"}
}