{
  "type": "Feature",
  "properties": {
    "iso:country":"CH",
    "sg:address":"Via Bresce 1 6854 S. Pietro Casella Postale 1",
    "sg:city":"Stabio",
    "sg:orig_category":"Handel mit Motorr\u00e4dern, Teilen U Zubeh\u00f6r Instandhaltung U Reparatur von Motorr\u00e4dern",
    "sg:phone":"+41 91 647 39 71",
    "sg:postcode":"6855",
    "sg:province":"Ticino",
    "wof:name":"Assos Ag",
    "wof:placetype":"venue"
},
  "geometry": {"coordinates":[8.9393825531,45.8523521423],"type":"Point"}
}