{
  "type": "Feature",
  "properties": {
    "iso:country":"CH",
    "sg:address":"Adam-friedrich Molz Gasse 2",
    "sg:city":"Biel/bienne",
    "sg:classifiers":[
        {
            "category":"Restaurant",
            "type":"Food & Drink"
        }
    ],
    "sg:phone":"+41 32 325 20 27",
    "sg:postcode":"2502",
    "sg:province":"Bern",
    "wof:name":"Restaurant La Koutoubia",
    "wof:placetype":"venue"
},
  "geometry": {"coordinates":[7.2447838783,47.1401519775],"type":"Point"}
}