{
  "type": "Feature",
  "properties": {
    "iso:country":"CH",
    "sg:address":"Quellenstrasse 9",
    "sg:city":"Uzwil",
    "sg:orig_category":"Fachdetailhandel in Verkaufsr\u00e4umen",
    "sg:phone":"+41 71 951 21 80",
    "sg:postcode":"9240",
    "sg:province":"St. Gallen",
    "wof:name":"Hezeh Beratung Und Vertrieb, Zehnder Heidi",
    "wof:placetype":"venue"
},
  "geometry": {"coordinates":[9.1188926697,47.4428710938],"type":"Point"}
}