{
  "type": "Feature",
  "properties": {
    "iso:country":"CH",
    "sg:address":"Badstrasse 17 5400 Baden. Postfach",
    "sg:city":"Baden",
    "sg:orig_category":"Rechtsberatung",
    "sg:phone":"+41 56 204 33 66",
    "sg:postcode":"5401",
    "sg:province":"Aargau",
    "wof:name":"Dr. Iur. Jakob Notter",
    "wof:placetype":"venue"
},
  "geometry": {"coordinates":[8.3081865311,47.4749450684],"type":"Point"}
}