{
  "type": "Feature",
  "properties": {
    "iso:country":"CH",
    "sg:address":"Kunkels",
    "sg:city":"V\u00e4ttis",
    "sg:classifiers":[
        {
            "category":"Restaurant",
            "type":"Food & Drink"
        }
    ],
    "sg:phone":"+41 34 493 32 66",
    "sg:postcode":"7315",
    "sg:province":"St. Gallen",
    "wof:name":"Bergrestaurant Eigerblick",
    "wof:placetype":"venue"
},
  "geometry": {"coordinates":[7.8967900276,46.8511390686],"type":"Point"}
}