{
  "type": "Feature",
  "properties": {
    "iso:country":"CH",
    "sg:address":"Schipfe 2",
    "sg:city":"Z\u00fcrich",
    "sg:orig_category":"Sonstiges Versicherungsgewerbe",
    "sg:phone":"+41 32 842 30 31",
    "sg:postcode":"8001",
    "sg:province":"Z\u00fcrich",
    "wof:name":"Iceberg Finance S\u00e0rl",
    "wof:placetype":"venue"
},
  "geometry": {"coordinates":[6.857986927,46.9656143188],"type":"Point"}
}