{
  "type": "Feature",
  "properties": {
    "iso:country":"CH",
    "sg:address":"Kirchstrasse 42 8807 Freienbach. Postfach",
    "sg:city":"Freienbach",
    "sg:orig_category":"Fachdetailhandel in Verkaufsr\u00e4umen",
    "sg:postcode":"8807",
    "sg:province":"Schwyz",
    "wof:name":"Inartra Gmbh Kunsthandel, Dienstleistungen",
    "wof:placetype":"venue"
},
  "geometry": {"coordinates":[8.7593593597,47.2054176331],"type":"Point"}
}