{
  "type": "Feature",
  "properties": {
    "iso:country":"CH",
    "sg:address":"Weidli 21",
    "sg:city":"Melchtal",
    "sg:orig_category":"Baugewerbe",
    "sg:phone":"+41 41 669 11 54",
    "sg:postcode":"6067",
    "sg:province":"Obwalden",
    "wof:name":"Paul H\u00fcrlimann Ph-service",
    "wof:placetype":"venue"
},
  "geometry": {"coordinates":[8.278651,46.802223],"type":"Point"}
}