{
  "type": "Feature",
  "properties": {
    "iso:country":"CH",
    "sg:address":"Rue Paul-bouchet 5",
    "sg:city":"Gen\u00e8ve",
    "sg:classifiers":[
        {
            "category":"Travel",
            "subcategory":"Hotels & Motels",
            "type":"Entertainment"
        }
    ],
    "sg:phone":"+41 22 731 47 20",
    "sg:postcode":"1201",
    "sg:province":"Gen\u00e8ve",
    "sg:tags":[
        "hotels",
        "mit",
        "restaurant"
    ],
    "wof:name":"H\u00f4tel Rhodania",
    "wof:placetype":"venue"
},
  "geometry": {"coordinates":[6.1435799599,46.2081184387],"type":"Point"}
}