{
  "type": "Feature",
  "properties": {
    "addr:full":"Scheuergraben 93 Heitenried Fribourg 1714",
    "addr:housenumber":"93",
    "addr:postcode":"1714",
    "addr:street":"Scheuergraben",
    "iso:country":"CH",
    "sg:address":"Scheuergraben 93",
    "sg:city":"Heitenried",
    "sg:orig_category":"Bauschreinerei Herstellung von Konstruktionsteilen, Fertigbauteilen U Ausbauelementen aus Holz",
    "sg:phone":"+41 26 495 14 82",
    "sg:postcode":"1714",
    "sg:province":"Fribourg",
    "wof:name":"Hirschi Holzbau Gmbh",
    "wof:placetype":"venue"
},
  "geometry": {"coordinates":[7.279591,46.846722],"type":"Point"}
}