{
  "type": "Feature",
  "properties": {
    "iso:country":"CH",
    "sg:address":"Weinmarkt 20",
    "sg:city":"Luzern",
    "sg:classifiers":[
        {
            "category":"Military Area",
            "subcategory":"Air Force Base",
            "type":"Public Place"
        }
    ],
    "sg:phone":"+41 56 463 63 33",
    "sg:postcode":"6004",
    "sg:province":"Luzern",
    "sg:tags":[
        "sink",
        "kitchen"
    ],
    "wof:name":"Suter Sp\u00fcltischwerk Gmbh",
    "wof:placetype":"venue"
},
  "geometry": {"coordinates":[8.1671009064,47.4475822449],"type":"Point"}
}