{
  "type": "Feature",
  "properties": {
    "iso:country":"CH",
    "sg:address":"Morgartenstrasse 6 8004 Z\u00fcrich. Postfach",
    "sg:city":"Z\u00fcrich",
    "sg:orig_category":"Finanzierungsinstitutionen",
    "sg:phone":"+41 12411551",
    "sg:postcode":"8023",
    "sg:province":"Z\u00fcrich",
    "wof:name":"Finanzhaus B\u00fcrkle & Co, Nachfolger Horch Dr. G. & Co",
    "wof:placetype":"venue"
},
  "geometry": {"coordinates":[8.5293092728,47.3714065552],"type":"Point"}
}