{
  "type": "Feature",
  "properties": {
    "iso:country":"CH",
    "sg:address":"Dorfstrasse 144",
    "sg:city":"Meilen",
    "sg:orig_category":"Zahnarztpraxen",
    "sg:phone":"+41 19302115",
    "sg:postcode":"8706",
    "sg:province":"Z\u00fcrich",
    "wof:name":"Dr. Med. Dent. Keiko Koch Zahn\u00e4rztin",
    "wof:placetype":"venue"
},
  "geometry": {"coordinates":[8.7994213104,47.3266601562],"type":"Point"}
}