{
  "type": "Feature",
  "properties": {
    "iso:country":"CH",
    "sg:address":"Bielstrasse 12",
    "sg:city":"M\u00fcnchenbuchsee",
    "sg:orig_category":"Radar Warning Devices",
    "sg:phone":"+41 31 868 71 11",
    "sg:postcode":"3053",
    "sg:province":"Bern",
    "wof:name":"Sprintel Communications Ag",
    "wof:placetype":"venue"
},
  "geometry": {"coordinates":[7.4466238022,47.025138855],"type":"Point"}
}