{
  "type": "Feature",
  "properties": {
    "iso:country":"CH",
    "sg:address":"Cart Rue Jean-jacques- 2 1006 Lausanne. Postfach",
    "sg:city":"Lausanne",
    "sg:classifiers":[
        {
            "category":"Professional",
            "subcategory":"Employment Agencies",
            "type":"Services"
        }
    ],
    "sg:phone":"+41 21 616 27 74",
    "sg:postcode":"1003",
    "sg:province":"Vaud",
    "sg:tags":[
        "personal",
        "u",
        "stellenvermittlung"
    ],
    "wof:name":"Bolla Mme L. Bureau De Placement Priv\u00e9, Etc.",
    "wof:placetype":"venue"
},
  "geometry": {"coordinates":[6.6269798279,46.5139884949],"type":"Point"}
}