{
  "type": "Feature",
  "properties": {
    "iso:country":"CH",
    "sg:address":"Via Martignoni 6900 Massagno. Postfach",
    "sg:city":"Massagno",
    "sg:orig_category":"Einzelhandel mit Automobilen Instandhaltung U Reparatur von Automobilen",
    "sg:phone":"+41 91 966 92 13",
    "sg:postcode":"6900",
    "sg:province":"Ticino",
    "wof:name":"Garage Besomi & Morsanti Riparazione E Vendita Di Autoveicoli",
    "wof:placetype":"venue"
},
  "geometry": {"coordinates":[8.9390554428,46.013874054],"type":"Point"}
}