{
  "type": "Feature",
  "properties": {
    "iso:country":"CH",
    "sg:address":"Reussblick 2 6331 H\u00fcnenberg. Postfach 195",
    "sg:city":"Cham",
    "sg:orig_category":"Handelsvermittlung U Grosshandel",
    "sg:phone":"+41 41 780 50 27",
    "sg:postcode":"6330",
    "sg:province":"Zug",
    "wof:name":"Telba Ag Umwelttechnik",
    "wof:placetype":"venue"
},
  "geometry": {"coordinates":[8.4216556549,47.1782722473],"type":"Point"}
}