{
  "type": "Feature",
  "properties": {
    "iso:country":"CH",
    "sg:address":"Alpbachstrasse 2",
    "sg:city":"Meiringen",
    "sg:orig_category":"Detailhandel mit Waren verschiedener Art, Hauptrichtung Nahrungsmittel",
    "sg:phone":"+41 33 971 11 44",
    "sg:postcode":"3860",
    "sg:province":"Bern",
    "wof:name":"Hanspeter Amacher Lebensmittel",
    "wof:placetype":"venue"
},
  "geometry": {"coordinates":[8.1898899078,46.725769043],"type":"Point"}
}