{
  "type": "Feature",
  "properties": {
    "iso:country":"CH",
    "sg:address":"Z\u00fcrichstrasse 59 8840 Einsiedeln. Postfach 25",
    "sg:city":"Einsiedeln",
    "sg:orig_category":"Unclassifiable Establishments",
    "sg:phone":"+41 55 418 75 60",
    "sg:postcode":"8840",
    "sg:province":"Schwyz",
    "wof:name":"Astorplast Inter Ag",
    "wof:placetype":"venue"
},
  "geometry": {"coordinates":[8.7449531555,47.1349601746],"type":"Point"}
}