{
  "type": "Feature",
  "properties": {
    "iso:country":"CH",
    "sg:address":"Bohlstrasse 12",
    "sg:city":"Thayngen",
    "sg:orig_category":"Grosshandel mit Holz U Baustoffen Herstellung von Baubedarfsartikeln aus Kunststoff",
    "sg:phone":"+41 52 649 27 49",
    "sg:postcode":"8240",
    "sg:province":"Schaffhausen",
    "wof:name":"Cabina Ag",
    "wof:placetype":"venue"
},
  "geometry": {"coordinates":[8.7032194138,47.7442321777],"type":"Point"}
}