{
  "type": "Feature",
  "properties": {
    "iso:country":"CH",
    "sg:address":"Schmittenstrasse 15",
    "sg:city":"Kreuzlingen",
    "sg:orig_category":"Grosshandel mit B\u00fcromaschinen Grosshandel mit Datenverarbeitungsger\u00e4ten",
    "sg:phone":"+41 76 316 43 43",
    "sg:postcode":"8280",
    "sg:province":"Thurgau",
    "wof:name":"Highpower Gmbh",
    "wof:placetype":"venue"
},
  "geometry": {"coordinates":[9.0022296906,47.4901809692],"type":"Point"}
}