{
  "type": "Feature",
  "properties": {
    "iso:country":"CH",
    "sg:address":"Goldacherstrasse 67 9404 Rorschacherberg. Postfach",
    "sg:city":"Rorschacherberg",
    "sg:orig_category":"Konkurs- and Betreibungs\u00e4mter",
    "sg:phone":"+41 55 251 32 50",
    "sg:postcode":"9404",
    "sg:province":"St. Gallen",
    "wof:name":"Betreibungsamt R\u00fcti",
    "wof:placetype":"venue"
},
  "geometry": {"coordinates":[8.8503112793,47.2565078735],"type":"Point"}
}