{
  "type": "Feature",
  "properties": {
    "addr:full":"Rossauerstrasse 10 Mettmenstetten Z\u00fcrich 8932",
    "addr:housenumber":"10",
    "addr:postcode":"8932",
    "addr:street":"Rossauerstrasse",
    "iso:country":"CH",
    "sg:address":"Rossauerstrasse 10",
    "sg:city":"Mettmenstetten",
    "sg:orig_category":"Architektur U Ingenieurb\u00fcros",
    "sg:phone":"+41 79 601 77 17",
    "sg:postcode":"8932",
    "sg:province":"Z\u00fcrich",
    "wof:name":"Architekturb\u00fcro Ag H\u00e4chler Markus",
    "wof:placetype":"venue"
},
  "geometry": {"coordinates":[8.464522,47.241806],"type":"Point"}
}