{
  "type": "Feature",
  "properties": {
    "iso:country":"CH",
    "sg:address":"5432",
    "sg:city":"Neuenhof",
    "sg:orig_category":"Sportvereine Turnen Vereine Damen",
    "sg:phone":"+41 56 406 19 45",
    "sg:postcode":"5432",
    "sg:province":"Aargau",
    "wof:name":"Damenriege Etv",
    "wof:placetype":"venue"
},
  "geometry": {"coordinates":[8.3268165588,47.4499435425],"type":"Point"}
}