{
  "type": "Feature",
  "properties": {
    "iso:country":"CH",
    "sg:address":"B\u00fcrlisb\u00fcel",
    "sg:city":"Sevelen",
    "sg:orig_category":"Herstellung von Seifen, Wasch U Reinigungsmitteln",
    "sg:phone":"+41 81 785 14 70",
    "sg:postcode":"9475",
    "sg:province":"St. Gallen",
    "wof:name":"Cleanstar Wyler",
    "wof:placetype":"venue"
},
  "geometry": {"coordinates":[9.4822540283,47.1234169006],"type":"Point"}
}