{
  "type": "Feature",
  "properties": {
    "iso:country":"CH",
    "sg:address":"Mundsch\u00f6pfiweg 11",
    "sg:city":"Walchwil",
    "sg:orig_category":"Handelsvermittlung U Grosshandel Herstellung von sonstigen Holzwaren",
    "sg:phone":"+41 41 758 13 86",
    "sg:postcode":"6318",
    "sg:province":"Zug",
    "wof:name":"Woram Ag",
    "wof:placetype":"venue"
},
  "geometry": {"coordinates":[8.5128335953,47.1052856445],"type":"Point"}
}