{
  "type": "Feature",
  "properties": {
    "iso:country":"CH",
    "sg:address":"Industriestrasse",
    "sg:city":"Reiden",
    "sg:classifiers":[
        {
            "category":"Manufacturing",
            "subcategory":"Wood Products",
            "type":"Manufacturing & Wholesale Goods"
        }
    ],
    "sg:phone":"+41 62 749 22 22",
    "sg:postcode":"6260",
    "sg:province":"Luzern",
    "sg:tags":[
        "gate",
        "made",
        "door"
    ],
    "wof:name":"Sorex Baumarkt Produkte Ag",
    "wof:placetype":"venue"
},
  "geometry": {"coordinates":[7.9653100967,47.2532463074],"type":"Point"}
}