{
  "type": "Feature",
  "properties": {
    "iso:country":"CH",
    "sg:address":"Endingerstrasse 33",
    "sg:city":"W\u00fcrenlingen",
    "sg:orig_category":"Non-Classified Establishments",
    "sg:phone":"+41 13026555",
    "sg:postcode":"5303",
    "sg:province":"Aargau",
    "wof:name":"Gastrolux Gmbh",
    "wof:placetype":"venue"
},
  "geometry": {"coordinates":[8.2597799301,47.5304489136],"type":"Point"}
}