{
  "type": "Feature",
  "properties": {
    "iso:country":"CH",
    "sg:address":"Rehb\u00fchlstrasse 2",
    "sg:city":"Uster",
    "sg:orig_category":"Bezirks, Sekundar, Realschulen, Oberstufe der Primarschulen",
    "sg:phone":"+41 19404030",
    "sg:postcode":"8610",
    "sg:province":"Z\u00fcrich",
    "wof:name":"Berufswahlschule Uster",
    "wof:placetype":"venue"
},
  "geometry": {"coordinates":[8.726827,47.355953],"type":"Point"}
}