{
  "type": "Feature",
  "properties": {
    "iso:country":"CH",
    "sg:address":"Eduard Huberstrasse 1",
    "sg:city":"Grosswangen",
    "sg:orig_category":"Arztpraxen",
    "sg:phone":"+41 41 980 17 57",
    "sg:postcode":"6022",
    "sg:province":"Luzern",
    "wof:name":"Dr.med.albert Pf\u00e4ffli Arzt F.allgemeine Medizin Fmh",
    "wof:placetype":"venue"
},
  "geometry": {"coordinates":[8.051444,47.132805],"type":"Point"}
}