{
  "type": "Feature",
  "properties": {
    "iso:country":"CH",
    "sg:address":"Bielstrasse 26",
    "sg:city":"Kappelen",
    "sg:orig_category":"Handel mit Automobilteilen U Zubeh\u00f6r",
    "sg:phone":"+41 32 384 03 68",
    "sg:postcode":"3273",
    "sg:province":"Bern",
    "wof:name":"Amstutz Andreas",
    "wof:placetype":"venue"
},
  "geometry": {"coordinates":[7.2625079155,47.0545120239],"type":"Point"}
}