{
  "type": "Feature",
  "properties": {
    "iso:country":"CH",
    "sg:address":"Schachenstrasse 4b",
    "sg:city":"Emmenbr\u00fccke",
    "sg:classifiers":[
        {
            "category":"Structure",
            "subcategory":"Building",
            "type":"Public Place"
        }
    ],
    "sg:phone":"+41 41 268 81 37",
    "sg:postcode":"6020",
    "sg:province":"Luzern",
    "sg:tags":[
        "attic",
        "insulation",
        "system"
    ],
    "wof:name":"Bautrend Baustoffe Ag",
    "wof:placetype":"venue"
},
  "geometry": {"coordinates":[8.286419,47.068127],"type":"Point"}
}