{
  "type": "Feature",
  "properties": {
    "iso:country":"CH",
    "sg:address":"Kreuzkapellenweg 2",
    "sg:city":"Wettingen",
    "sg:orig_category":"Datenverarbeitungsdienste Softwareentwicklung U beratung",
    "sg:phone":"+41 56 426 56 57",
    "sg:postcode":"5430",
    "sg:province":"Aargau",
    "wof:name":"Prosystem Canzani Ag",
    "wof:placetype":"venue"
},
  "geometry": {"coordinates":[8.340497,47.460419],"type":"Point"}
}