{
  "type": "Feature",
  "properties": {
    "iso:country":"CH",
    "sg:address":"Tobel\u00e4ckerstrasse 7",
    "sg:city":"Neuhausen",
    "sg:orig_category":"Mechanik Stahl U Leichtmetallbau",
    "sg:phone":"+41 52 670 04 50",
    "sg:postcode":"8212",
    "sg:province":"Schaffhausen",
    "wof:name":"Kofel Ag Schlosserei-metallbau",
    "wof:placetype":"venue"
},
  "geometry": {"coordinates":[8.6034860611,47.6762046814],"type":"Point"}
}