{
  "type": "Feature",
  "properties": {
    "iso:country":"CH",
    "sg:address":"Werkhofstrasse 29d",
    "sg:city":"Solothurn",
    "sg:orig_category":"Detailhandel mit Waren verschiedener Art, Hauptrichtung Nahrungsmittel Fachdetailhandel mit Nahrungs",
    "sg:phone":"+41 32 625 81 40",
    "sg:postcode":"4500",
    "sg:province":"Solothurn",
    "wof:name":"Solo-supermarkt",
    "wof:placetype":"venue"
},
  "geometry": {"coordinates":[7.5367388725,47.2106323242],"type":"Point"}
}