{
  "type": "Feature",
  "properties": {
    "iso:country":"CH",
    "sg:address":"Champ-cochet 2",
    "sg:city":"Courtelary",
    "sg:orig_category":"G\u00fcterbef\u00f6rderung im Strassenverkehr",
    "sg:phone":"+41 32 944 14 40",
    "sg:postcode":"2608",
    "sg:province":"Bern",
    "wof:name":"Robert Gindrat Camionnage Officiel",
    "wof:placetype":"venue"
},
  "geometry": {"coordinates":[7.0675911903,47.1782913208],"type":"Point"}
}