{
  "type": "Feature",
  "properties": {
    "addr:full":"Universit\u00e4tstrasse 81 Z\u00fcrich Z\u00fcrich 8006",
    "addr:housenumber":"81",
    "addr:postcode":"8006",
    "addr:street":"Universitaetstrasse",
    "iso:country":"CH",
    "sg:address":"Universit\u00e4tstrasse 81",
    "sg:city":"Z\u00fcrich",
    "sg:orig_category":"Detailhandel mit Damenbekleidung",
    "sg:phone":"+41 13026586",
    "sg:postcode":"8006",
    "sg:province":"Z\u00fcrich",
    "wof:name":"Elli Ascari Braut-& Abendkleider",
    "wof:placetype":"venue"
},
  "geometry": {"coordinates":[8.547986,47.382862],"type":"Point"}
}