{
  "type": "Feature",
  "properties": {
    "iso:country":"CH",
    "sg:address":"Sch\u00f6naustrasse 58 4058 Basel. Postfach",
    "sg:city":"Basel",
    "sg:orig_category":"Sonstiger Grosshandel",
    "sg:postcode":"4058",
    "sg:province":"Basel-Stadt",
    "wof:name":"Singh Impex Import Export Waren; Import, Export",
    "wof:placetype":"venue"
},
  "geometry": {"coordinates":[7.6029977798,47.5682411194],"type":"Point"}
}