{
  "type": "Feature",
  "properties": {
    "iso:country":"CH",
    "sg:address":"Unterer Kanalweg 5",
    "sg:city":"Nidau",
    "sg:orig_category":"Malerei",
    "sg:phone":"+41 32 331 00 55",
    "sg:postcode":"2560",
    "sg:province":"Bern",
    "wof:name":"Hans Stolz Malergesch\u00e4ft",
    "wof:placetype":"venue"
},
  "geometry": {"coordinates":[7.2430539131,47.1221199036],"type":"Point"}
}