{
  "type": "Feature",
  "properties": {
    "iso:country":"CH",
    "sg:address":"Spychergasse 3a",
    "sg:city":"Felben",
    "sg:orig_category":"M\u00f6belschreinereien",
    "sg:phone":"+41 79 413 09 51",
    "sg:postcode":"8552",
    "sg:province":"Thurgau",
    "wof:name":"Design-m\u00f6bel Schreinerei Bolli Markus",
    "wof:placetype":"venue"
},
  "geometry": {"coordinates":[8.9425401688,47.5796318054],"type":"Point"}
}