{
  "type": "Feature",
  "properties": {
    "iso:country":"CH",
    "sg:address":"Distern",
    "sg:city":"Ausserberg",
    "sg:orig_category":"Unclassifiable Establishments",
    "sg:postcode":"3938",
    "sg:province":"Valais",
    "wof:name":"Werlen Christof, Spenglerei",
    "wof:placetype":"venue"
},
  "geometry": {"coordinates":[7.8491530418,46.3131256104],"type":"Point"}
}