{
  "type": "Feature",
  "properties": {
    "iso:country":"CH",
    "sg:address":"Via Peri 18",
    "sg:city":"Lugano",
    "sg:orig_category":"Massagestudios",
    "sg:phone":"+41 91 924 92 92",
    "sg:postcode":"6900",
    "sg:province":"Ticino",
    "wof:name":"Baldi Alessandro Sagl",
    "wof:placetype":"venue"
},
  "geometry": {"coordinates":[8.9507894516,46.0062904358],"type":"Point"}
}