{
  "type": "Feature",
  "properties": {
    "iso:country":"CH",
    "sg:address":"1487",
    "sg:classifiers":[
        {
            "category":"Restaurant",
            "type":"Food & Drink"
        }
    ],
    "sg:phone":"+41 26 402 32 25",
    "sg:postcode":"1487",
    "wof:name":"Caf\u00e9 De La Gl\u00e2ne",
    "wof:placetype":"venue"
},
  "geometry": {"coordinates":[7.1274709702,46.7862129211],"type":"Point"}
}