{
  "type": "Feature",
  "properties": {
    "iso:country":"CH",
    "sg:address":"Ey 5a",
    "sg:city":"Ittigen",
    "sg:orig_category":"Instandhaltung U Reparatur von Automobilen",
    "sg:postcode":"3063",
    "sg:province":"Bern",
    "wof:name":"Vali Garage",
    "wof:placetype":"venue"
},
  "geometry": {"coordinates":[9.455499649,47.2063102722],"type":"Point"}
}