{
  "type": "Feature",
  "properties": {
    "iso:country":"CH",
    "sg:address":"Bettlachstrasse 149",
    "sg:city":"Grenchen",
    "sg:orig_category":"Sportvereine Velo Rad-& Motorfahrer-Bund SRB",
    "sg:phone":"+41 32 653 09 35",
    "sg:postcode":"2540",
    "sg:province":"Solothurn",
    "wof:name":"Kunst-& Reigenfahrer Atb",
    "wof:placetype":"venue"
},
  "geometry": {"coordinates":[7.4046578407,47.1968650818],"type":"Point"}
}