{
  "type": "Feature",
  "properties": {
    "iso:country":"CH",
    "sg:address":"Isenacher 2.",
    "sg:city":"St\u00e4fa",
    "sg:orig_category":"Unternehmensberatung",
    "sg:phone":"+41 19263742",
    "sg:postcode":"8712",
    "sg:province":"Z\u00fcrich",
    "wof:name":"Straub Oskar, Unternehmensberatung",
    "wof:placetype":"venue"
},
  "geometry": {"coordinates":[8.7161540985,47.250087738],"type":"Point"}
}