{
  "type": "Feature",
  "properties": {
    "iso:country":"CH",
    "sg:address":"Castels",
    "sg:city":"Ascharina",
    "sg:orig_category":"Personenbef\u00f6rderung im Linienverkehr zu Land",
    "sg:postcode":"7245",
    "sg:province":"Graubunden",
    "wof:name":"Skilift Junker Ag",
    "wof:placetype":"venue"
},
  "geometry": {"coordinates":[9.8019504547,46.9529800415],"type":"Point"}
}