{
  "type": "Feature",
  "properties": {
    "iso:country":"CH",
    "sg:address":"Lagerstrasse 1",
    "sg:city":"Neuenhof",
    "sg:orig_category":"Bauschreinerei Glaserei",
    "sg:phone":"+41 56 406 29 01",
    "sg:postcode":"5432",
    "sg:province":"Aargau",
    "wof:name":"Kurt Voser Schreinerei & Glaserei",
    "wof:placetype":"venue"
},
  "geometry": {"coordinates":[8.326915,47.448772],"type":"Point"}
}