{
  "type": "Feature",
  "properties": {
    "addr:full":"Dorfgasse 106 Twann Bern 2513",
    "addr:housenumber":"106",
    "addr:postcode":"2513",
    "addr:street":"Dorfgasse",
    "iso:country":"CH",
    "sg:address":"Dorfgasse 106",
    "sg:city":"Twann",
    "sg:orig_category":"Architektur U Ingenieurb\u00fcros Hoch U Tiefbau",
    "sg:phone":"+41 32 315 52 52",
    "sg:postcode":"2513",
    "sg:province":"Bern",
    "wof:name":"Beka Bauforum Gmbh",
    "wof:placetype":"venue"
},
  "geometry": {"coordinates":[7.157351,47.095024],"type":"Point"}
}