{
  "type": "Feature",
  "properties": {
    "iso:country":"CH",
    "sg:address":"Thonon Route De 85",
    "sg:city":"Collonge-bellerive",
    "sg:orig_category":"Dienstleistungen von Beteiligungsgesellschaften",
    "sg:postcode":"1245",
    "sg:province":"Gen\u00e8ve",
    "wof:name":"Olivier Jacques Glauser",
    "wof:placetype":"venue"
},
  "geometry": {"coordinates":[6.2042441368,46.2535629272],"type":"Point"}
}