{
  "type": "Feature",
  "properties": {
    "iso:country":"CH",
    "sg:address":"Unterdorf",
    "sg:city":"Rohrbach",
    "sg:orig_category":"Maler U Glasergewerbe Malerei",
    "sg:phone":"+41 62 965 29 56",
    "sg:postcode":"4938",
    "sg:province":"Bern",
    "wof:name":"W\u00fcrgler, Malergesch\u00e4ft",
    "wof:placetype":"venue"
},
  "geometry": {"coordinates":[7.8095221519,47.1362953186],"type":"Point"}
}