{
  "type": "Feature",
  "properties": {
    "iso:country":"CH",
    "sg:address":"Obergasse 47",
    "sg:city":"Schmerikon",
    "sg:orig_category":"Kosmetikinstitute",
    "sg:phone":"+41 55 282 44 40",
    "sg:postcode":"8716",
    "sg:province":"St. Gallen",
    "wof:name":"Erika Zimmermann Kosmetikinstitut",
    "wof:placetype":"venue"
},
  "geometry": {"coordinates":[8.9411611557,47.2262840271],"type":"Point"}
}