{
  "type": "Feature",
  "properties": {
    "iso:country":"CH",
    "sg:address":"Hammerstrasse 35",
    "sg:city":"Liestal",
    "sg:orig_category":"Non-Classified Establishments",
    "sg:phone":"+41 61 905 81 11",
    "sg:postcode":"4410",
    "sg:province":"Basel-Landschaft",
    "wof:name":"First Promotion Ag",
    "wof:placetype":"venue"
},
  "geometry": {"coordinates":[7.7248659134,47.4994277954],"type":"Point"}
}