{
  "type": "Feature",
  "properties": {
    "iso:country":"CH",
    "sg:address":"Forchstr. 185.",
    "sg:city":"Maur",
    "sg:orig_category":"Herstellung von Metallkonstruktionen",
    "sg:postcode":"8124",
    "sg:province":"Z\u00fcrich",
    "wof:name":"Alubau Ag.",
    "wof:placetype":"venue"
},
  "geometry": {"coordinates":[8.6676130295,47.3403167725],"type":"Point"}
}