{
  "type": "Feature",
  "properties": {
    "iso:country":"CH",
    "sg:address":"L\u00f6ser 19 7413 F\u00fcrstenaubruck. Postfach",
    "sg:city":"F\u00fcrstenaubruck",
    "sg:orig_category":"Sonstiger Grosshandel",
    "sg:postcode":"7413",
    "sg:province":"Graubunden",
    "wof:name":"Rever Ag",
    "wof:placetype":"venue"
},
  "geometry": {"coordinates":[9.540555954,47.3782348633],"type":"Point"}
}