{
  "type": "Feature",
  "properties": {
    "iso:country":"CH",
    "sg:address":"F\u00f6hrenweg 11",
    "sg:city":"Lenggenwil",
    "sg:orig_category":"Grosshandel mit Sportartikeln",
    "sg:phone":"+41 79 286 98 72",
    "sg:postcode":"9525",
    "sg:province":"St. Gallen",
    "wof:name":"Werner Nef Campingbedarf",
    "wof:placetype":"venue"
},
  "geometry": {"coordinates":[9.1526422501,47.4757575989],"type":"Point"}
}