{
  "type": "Feature",
  "properties": {
    "iso:country":"CH",
    "sg:address":"Poststrasse 30",
    "sg:city":"Zug",
    "sg:orig_category":"Handelsvermittlung U Grosshandel mit Automobilen Instandhaltung U Reparatur von Automobilen",
    "sg:phone":"+41 41 630 36 61",
    "sg:postcode":"6300",
    "sg:province":"Zug",
    "wof:name":"Ic Handels Ag",
    "wof:placetype":"venue"
},
  "geometry": {"coordinates":[8.3105592728,46.983253479],"type":"Point"}
}