{
  "type": "Feature",
  "properties": {
    "iso:country":"CH",
    "sg:address":"1689",
    "sg:city":"Ch\u00e2telard-p-romont",
    "sg:orig_category":"Gemeindeverwaltungen",
    "sg:phone":"+41 21 841 11 20",
    "sg:postcode":"1689",
    "sg:province":"Fribourg",
    "wof:name":"Administration Communale De Le Lieu",
    "wof:placetype":"venue"
},
  "geometry": {"coordinates":[6.282310009,46.6478347778],"type":"Point"}
}