{
  "type": "Feature",
  "properties": {
    "iso:country":"CH",
    "sg:address":"4913",
    "sg:city":"Bannwil",
    "sg:orig_category":"Vereine Musik/Blasmusik",
    "sg:postcode":"4913",
    "sg:province":"Bern",
    "wof:name":"Musikgesellschaft",
    "wof:placetype":"venue"
},
  "geometry": {"coordinates":[7.7337398529,47.2378005981],"type":"Point"}
}