{
  "type": "Feature",
  "properties": {
    "iso:country":"CH",
    "sg:address":"Chemin Des Plaines 13",
    "sg:city":"St-blaise",
    "sg:orig_category":"Sonstige mit der Informatik verbundene T\u00e4tigkeiten",
    "sg:phone":"+41 32 753 52 75",
    "sg:postcode":"2072",
    "sg:province":"Neuch\u00e2tel",
    "wof:name":"Max R\u00fcedi Servtech",
    "wof:placetype":"venue"
},
  "geometry": {"coordinates":[6.9869618416,47.0193519592],"type":"Point"}
}