{
  "type": "Feature",
  "properties": {
    "iso:country":"CH",
    "sg:address":"Dorfstrasse 8",
    "sg:city":"Wettingen",
    "sg:orig_category":"Architektur U Ingenieurb\u00fcros",
    "sg:phone":"+41 56 426 79 48",
    "sg:postcode":"5430",
    "sg:province":"Aargau",
    "wof:name":"Planungsb\u00fcro Loos",
    "wof:placetype":"venue"
},
  "geometry": {"coordinates":[8.329363,47.466419],"type":"Point"}
}