{
  "type": "Feature",
  "properties": {
    "iso:country":"CH",
    "sg:address":"4587",
    "sg:city":"Aetingen",
    "sg:orig_category":"Primarschulen",
    "sg:phone":"+41 32 614 27 67",
    "sg:postcode":"4587",
    "sg:province":"Solothurn",
    "wof:name":"Primarschule",
    "wof:placetype":"venue"
},
  "geometry": {"coordinates":[7.5000100136,47.1271591187],"type":"Point"}
}