{
  "type": "Feature",
  "properties": {
    "iso:country":"CH",
    "sg:address":"Zurigo Via 5 6900 Lugano. Postfach",
    "sg:city":"Lugano",
    "sg:orig_category":"Herstellung von sonstigen elektrischen Ausr\u00fcstungen",
    "sg:postcode":"6900",
    "sg:province":"Ticino",
    "wof:name":"Saleco Ag",
    "wof:placetype":"venue"
},
  "geometry": {"coordinates":[7.3763251305,46.923915863],"type":"Point"}
}