{
  "type": "Feature",
  "properties": {
    "iso:country":"CH",
    "sg:address":"Steineggstr. 18",
    "sg:city":"Lachen",
    "sg:classifiers":[
        {
            "category":"Manufacturing",
            "subcategory":"Textiles",
            "type":"Manufacturing & Wholesale Goods"
        }
    ],
    "sg:phone":"+41 55 442 31 23",
    "sg:postcode":"8853",
    "sg:province":"Schwyz",
    "sg:tags":[
        "linen",
        "clothing",
        "fabric"
    ],
    "wof:name":"Modellana Ag",
    "wof:placetype":"venue"
},
  "geometry": {"coordinates":[8.8562498093,47.1854133606],"type":"Point"}
}