{
  "type": "Feature",
  "properties": {
    "iso:country":"CH",
    "sg:address":"Bahnhofplatz 4",
    "sg:city":"Luzern",
    "sg:orig_category":"Nationale Postdienste",
    "sg:phone":"+41 41 370 23 21",
    "sg:postcode":"6003",
    "sg:province":"Luzern",
    "wof:name":"Die Schweizerische Post Luzern 15 W\u00fcrzenbach",
    "wof:placetype":"venue"
},
  "geometry": {"coordinates":[8.3417778015,47.052116394],"type":"Point"}
}