{
  "type": "Feature",
  "properties": {
    "iso:country":"CH",
    "sg:address":"B\u00fchlstrasse 19 8000 Z\u00fcrich. Postfach",
    "sg:city":"Z\u00fcrich",
    "sg:orig_category":"Kinderg\u00e4rten, Vor U Grundschulen Kinderkrippen U horte",
    "sg:phone":"+41 79 353 85 23",
    "sg:postcode":"8000",
    "sg:province":"Z\u00fcrich",
    "wof:name":"L'ilotr\u00e9sor, Fl\u00fcckiger Jocelyne",
    "wof:placetype":"venue"
},
  "geometry": {"coordinates":[6.5750727654,46.5186653137],"type":"Point"}
}