{
  "type": "Feature",
  "properties": {
    "iso:country":"CH",
    "sg:address":"Grebelackerstrasse 32",
    "sg:city":"Z\u00fcrich",
    "sg:orig_category":"Allgemeiner Hoch U Tiefbau Hoch U Tiefbau",
    "sg:phone":"+41 13631581",
    "sg:postcode":"8057",
    "sg:province":"Z\u00fcrich",
    "wof:name":"Bauunternehmung Paul B\u00fcchler Ag",
    "wof:placetype":"venue"
},
  "geometry": {"coordinates":[8.535976,47.398701],"type":"Point"}
}