{
  "type": "Feature",
  "properties": {
    "iso:country":"CH",
    "sg:address":"Hauptstrasse 22 4204 Himmelried. Postfach",
    "sg:city":"Himmelried",
    "sg:orig_category":"RESTAURANTS: TEA-ROOMS",
    "sg:phone":"+41 79 408 14 63",
    "sg:postcode":"4204",
    "sg:province":"Solothurn",
    "wof:name":"Mutsuaki Yoshioka Restaurant Frohsinn",
    "wof:placetype":"venue"
},
  "geometry": {"coordinates":[7.5972471237,47.4219093323],"type":"Point"}
}