{
  "type": "Feature",
  "properties": {
    "iso:country":"CH",
    "sg:address":"H\u00f6henstrasse 4b",
    "sg:city":"Geroldswil",
    "sg:orig_category":"Maschinen and Apparate divers Grosshandel",
    "sg:phone":"+41 81 416 57 28",
    "sg:postcode":"8954",
    "sg:province":"Z\u00fcrich",
    "wof:name":"Hanspeter Ebener K\u00fchlanlagen",
    "wof:placetype":"venue"
},
  "geometry": {"coordinates":[9.8345108032,46.8012657166],"type":"Point"}
}