{
  "type": "Feature",
  "properties": {
    "iso:country":"CH",
    "sg:address":"Wabernstrasse 58",
    "sg:city":"Bern",
    "sg:orig_category":"Grosshandel mit Foto U Kinoger\u00e4ten, feinmechanischen U optischen Erzeugnissen",
    "sg:phone":"+41 31 371 33 11",
    "sg:postcode":"3007",
    "sg:province":"Bern",
    "wof:name":"Kuhny Instrumentenoptik",
    "wof:placetype":"venue"
},
  "geometry": {"coordinates":[7.4391040802,46.9372444153],"type":"Point"}
}