{
  "type": "Feature",
  "properties": {
    "iso:country":"CH",
    "sg:address":"Sonnhaldeweg 5",
    "sg:city":"Dornach",
    "sg:orig_category":"Grosshandel mit Textilien",
    "sg:phone":"+41 61 701 43 48",
    "sg:postcode":"4143",
    "sg:province":"Solothurn",
    "wof:name":"Chronos Ag",
    "wof:placetype":"venue"
},
  "geometry": {"coordinates":[7.6147451401,47.4876747131],"type":"Point"}
}