{
  "type": "Feature",
  "properties": {
    "iso:country":"CH",
    "sg:address":"Waldheimstrasse 35 6300 Zug. Postfach",
    "sg:city":"Cham",
    "sg:orig_category":"Erwachsenenbildung U Unterricht",
    "sg:postcode":"6330",
    "sg:province":"Zug",
    "wof:name":"Management By Media Gmbh",
    "wof:placetype":"venue"
},
  "geometry": {"coordinates":[8.5215501785,47.1592521667],"type":"Point"}
}