{
  "type": "Feature",
  "properties": {
    "iso:country":"CH",
    "sg:address":"Baumgartenweg 1",
    "sg:city":"Oberentfelden",
    "sg:orig_category":"Notariate",
    "sg:phone":"+41 62 723 04 00",
    "sg:postcode":"5036",
    "sg:province":"Aargau",
    "wof:name":"K\u00fcnzli & K\u00fcmin Notariatsb\u00fcro",
    "wof:placetype":"venue"
},
  "geometry": {"coordinates":[8.0465946198,47.3586082458],"type":"Point"}
}