{
  "type": "Feature",
  "properties": {
    "iso:country":"CH",
    "sg:address":"Stabile Torretta",
    "sg:city":"Bellinzona",
    "sg:orig_category":"Finanz\u00e4mter",
    "sg:phone":"+41 91 804 35 02",
    "sg:postcode":"6500",
    "sg:province":"Ticino",
    "wof:name":"Dipartimento Cantonale Delle Finanze",
    "wof:placetype":"venue"
},
  "geometry": {"coordinates":[9.0241193771,46.1944618225],"type":"Point"}
}