{
  "type": "Feature",
  "properties": {
    "addr:full":"Chiss 7 Samedan Graubunden 7503",
    "addr:housenumber":"7",
    "addr:postcode":"7503",
    "addr:street":"Chiss;Graubunden",
    "iso:country":"CH",
    "sg:address":"Chiss 7",
    "sg:city":"Samedan",
    "sg:orig_category":"Architektur U Ingenieurb\u00fcros Fernmeldedienste",
    "sg:phone":"+41 81 850 09 99",
    "sg:postcode":"7503",
    "sg:province":"Graubunden",
    "wof:name":"Metelcom Ag",
    "wof:placetype":"venue"
},
  "geometry": {"coordinates":[9.869471,46.535011],"type":"Point"}
}