{
  "type": "Feature",
  "properties": {
    "iso:country":"CH",
    "sg:address":"Rue Du Quartier 18 2882 St-ursanne Case Postale 91",
    "sg:city":"St-ursanne",
    "sg:orig_category":"Verkehrs- and Tourismusb\u00fcros Wirtschaftsverb\u00e4nde Verkehrswesen, Tourismus",
    "sg:phone":"+41 32 461 37 16",
    "sg:postcode":"2882",
    "sg:province":"Jura",
    "wof:name":"Jura-tourisme St-ursanne & Clos-du-doubs",
    "wof:placetype":"venue"
},
  "geometry": {"coordinates":[7.1536641121,47.3640937805],"type":"Point"}
}