{
  "type": "Feature",
  "properties": {
    "iso:country":"CH",
    "sg:address":"Wolfacker 442",
    "sg:city":"D\u00fcrren\u00e4sch",
    "sg:orig_category":"Betrieb U technische Hilfsdienste des Kultur U Unterhaltungswesens",
    "sg:postcode":"5724",
    "sg:province":"Aargau",
    "wof:name":"S.a.d.o. Gmbh Party- U. Konzertveranstaltungen Usw.",
    "wof:placetype":"venue"
},
  "geometry": {"coordinates":[9.360816,47.415768],"type":"Point"}
}