{
  "type": "Feature",
  "properties": {
    "addr:full":"Schulhausstr. 4 Selzach Solothurn 2545",
    "addr:housenumber":"4",
    "addr:postcode":"2545",
    "addr:street":"Schulhausstr.",
    "iso:country":"CH",
    "sg:address":"Schulhausstr. 4",
    "sg:city":"Selzach",
    "sg:classifiers":[
        {
            "category":"Banks & Credit Unions",
            "subcategory":"Bank",
            "type":"Services"
        }
    ],
    "sg:phone":"+41 32 641 22 26",
    "sg:postcode":"2545",
    "sg:province":"Solothurn",
    "wof:name":"Raiffeisenbank Wandflue",
    "wof:placetype":"venue"
},
  "geometry": {"coordinates":[7.456293,47.205036],"type":"Point"}
}