{
  "type": "Feature",
  "properties": {
    "iso:country":"CH",
    "sg:address":"Via San Gottardo 72",
    "sg:city":"Massagno",
    "sg:orig_category":"Detailhandel mit Fleisch U Fleischwaren Detailhandel mit Waren verschiedener Art, Hauptrichtung Nahr",
    "sg:phone":"+41 91 966 10 56",
    "sg:postcode":"6900",
    "sg:province":"Ticino",
    "wof:name":"Rezzonico Carlo.",
    "wof:placetype":"venue"
},
  "geometry": {"coordinates":[8.9467468262,46.0107536316],"type":"Point"}
}