{
  "type": "Feature",
  "properties": {
    "iso:country":"CH",
    "sg:address":"Chemin De La Chenaillettaz 1 1110 Morges. Postfach",
    "sg:city":"Morges",
    "sg:orig_category":"Druckweiterverarbeitung",
    "sg:postcode":"1110",
    "sg:province":"Vaud",
    "wof:name":"Brossardesign S\u00e0rl Graphique Multim\u00e9dia; Cr\u00e9ation Et R\u00e9alisation",
    "wof:placetype":"venue"
},
  "geometry": {"coordinates":[6.5005431175,46.5175666809],"type":"Point"}
}