{
  "type": "Feature",
  "properties": {
    "iso:country":"CH",
    "sg:address":"5611",
    "sg:city":"Anglikon",
    "sg:orig_category":"Sportvereine Turnen",
    "sg:phone":"+41 56 634 44 86",
    "sg:postcode":"5611",
    "sg:province":"Aargau",
    "wof:name":"Turnverein Arni",
    "wof:placetype":"venue"
},
  "geometry": {"coordinates":[8.4385242462,47.3228569031],"type":"Point"}
}