{
  "type": "Feature",
  "properties": {
    "iso:country":"CH",
    "sg:address":"Kirchgasse 25",
    "sg:city":"Olten",
    "sg:orig_category":"Non-Classified Establishments",
    "sg:phone":"+41 62 296 74 05",
    "sg:postcode":"4600",
    "sg:province":"Solothurn",
    "wof:name":"Schneider Daniel Landschaftsarchitekten Bsla",
    "wof:placetype":"venue"
},
  "geometry": {"coordinates":[7.900993824,47.3496017456],"type":"Point"}
}