{
  "type": "Feature",
  "properties": {
    "iso:country":"CH",
    "sg:address":"Ottenweg 33",
    "sg:city":"Z\u00fcrich",
    "sg:orig_category":"Reparatur von Schuhen U Lederwaren",
    "sg:phone":"+41 12616850",
    "sg:postcode":"8008",
    "sg:province":"Z\u00fcrich",
    "wof:name":"Walter Hess Schuhreparatur-service",
    "wof:placetype":"venue"
},
  "geometry": {"coordinates":[8.5540132523,47.364276886],"type":"Point"}
}