{
  "type": "Feature",
  "properties": {
    "iso:country":"CH",
    "sg:address":"Spitzwaldstrasse 199",
    "sg:city":"Allschwil",
    "sg:orig_category":"Allgemeiner Hoch U Tiefbau Malerei",
    "sg:phone":"+41 61 481 20 78",
    "sg:postcode":"4123",
    "sg:province":"Basel-Landschaft",
    "wof:name":"Hohl Rolf Malergesch\u00e4ft Renovationsbetrieb, Malergesch\u00e4ft, Fassadenrenovationen",
    "wof:placetype":"venue"
},
  "geometry": {"coordinates":[7.55355,47.548199],"type":"Point"}
}