{
  "type": "Feature",
  "properties": {
    "iso:country":"CH",
    "sg:address":"Cours De Rive 5",
    "sg:city":"Gen\u00e8ve",
    "sg:orig_category":"Arztpraxen",
    "sg:phone":"+41 22 311 44 55",
    "sg:postcode":"1204",
    "sg:province":"Gen\u00e8ve",
    "wof:name":"Dr M\u00e9d. Roger Vallet M\u00e9decin Sp\u00e9cialiste Fmh",
    "wof:placetype":"venue"
},
  "geometry": {"coordinates":[6.152892,46.20192],"type":"Point"}
}