{
  "type": "Feature",
  "properties": {
    "iso:country":"CH",
    "sg:address":"Hutgasse 4 4000 Basel. Postfach",
    "sg:city":"Basel",
    "sg:orig_category":"Fachdetailhandel in Verkaufsr\u00e4umen",
    "sg:postcode":"4001",
    "sg:province":"Basel-Stadt",
    "wof:name":"X-time Ag",
    "wof:placetype":"venue"
},
  "geometry": {"coordinates":[7.5874700546,47.5576972961],"type":"Point"}
}