{
  "type": "Feature",
  "properties": {
    "iso:country":"CH",
    "sg:address":"Schaffhauserstrasse 7 8006 Z\u00fcrich. Postfach",
    "sg:city":"Z\u00fcrich",
    "sg:orig_category":"Interessenvertretungen U sonstige Vereinigungen Organisationen der Wohlfahrtspflege",
    "sg:phone":"+41 31 311 45 11",
    "sg:postcode":"8042",
    "sg:province":"Z\u00fcrich",
    "wof:name":"Caritas Bern",
    "wof:placetype":"venue"
},
  "geometry": {"coordinates":[7.4314570427,46.9408226013],"type":"Point"}
}