{
  "type": "Feature",
  "properties": {
    "iso:country":"CH",
    "sg:address":"Place De Cornavin 2",
    "sg:city":"Gen\u00e8ve",
    "sg:orig_category":"Fotografische Ateliers Fotografisches Gewerbe U fotografische Laboratorien",
    "sg:phone":"+41 21 635 61 31",
    "sg:postcode":"1201",
    "sg:province":"Gen\u00e8ve",
    "wof:name":"Studio Photo Page & Cie",
    "wof:placetype":"venue"
},
  "geometry": {"coordinates":[6.5865068436,46.5445671082],"type":"Point"}
}