{
  "type": "Feature",
  "properties": {
    "iso:country":"CH",
    "sg:address":"Rue Du Contrat-social 1",
    "sg:city":"Gen\u00e8ve",
    "sg:classifiers":[
        {
            "category":"Restaurant",
            "type":"Food & Drink"
        }
    ],
    "sg:phone":"+41 22 345 12 98",
    "sg:postcode":"1203",
    "sg:province":"Gen\u00e8ve",
    "wof:name":"Caf\u00e9-restaurant Paradisio",
    "wof:placetype":"venue"
},
  "geometry": {"coordinates":[6.1242480278,46.2042350769],"type":"Point"}
}