{
  "type": "Feature",
  "properties": {
    "iso:country":"CH",
    "sg:address":"Bp Tankstelle A4",
    "sg:city":"Adlikon",
    "sg:orig_category":"Detailhandel mit Bekleidung Einzelhandel mit Automobilteilen U Zubeh\u00f6r",
    "sg:phone":"+41 52 301 20 19",
    "sg:postcode":"8452",
    "sg:province":"Z\u00fcrich",
    "wof:name":"Trucker Shop & Western Store Inh.romy Linder",
    "wof:placetype":"venue"
},
  "geometry": {"coordinates":[8.6925,47.582672],"type":"Point"}
}