{
  "type": "Feature",
  "properties": {
    "iso:country":"CH",
    "sg:address":"Bahnhofstrasse 10",
    "sg:city":"Herisau",
    "sg:orig_category":"Sonstige Aktivit\u00e4ten der nicht-\u00e4rztlichen Medizinalberufe",
    "sg:phone":"+41 71 351 34 34",
    "sg:postcode":"9100",
    "sg:province":"Appenzell Ausserrhoden",
    "wof:name":"Henri Sangue Akupunkteur & Naturheilarzt",
    "wof:placetype":"venue"
},
  "geometry": {"coordinates":[9.2782993317,47.3870735168],"type":"Point"}
}