{
  "type": "Feature",
  "properties": {
    "iso:country":"CH",
    "sg:address":"Chemin De La Charrue 18",
    "sg:city":"Del\u00e9mont",
    "sg:orig_category":"Reiseb\u00fcros",
    "sg:phone":"+41 32 422 62 32",
    "sg:postcode":"2800",
    "sg:province":"Jura",
    "wof:name":"Blue Wave Agence De Voyages",
    "wof:placetype":"venue"
},
  "geometry": {"coordinates":[7.3632788658,47.3612747192],"type":"Point"}
}