{
  "type": "Feature",
  "properties": {
    "iso:country":"CH",
    "sg:address":"Schreinerei",
    "sg:city":"Feldis/veulden",
    "sg:orig_category":"Sportvereine Ski",
    "sg:phone":"+41 81 655 22 80",
    "sg:postcode":"7404",
    "sg:province":"Graubunden",
    "wof:name":"Skiclub Cresta Feldis",
    "wof:placetype":"venue"
},
  "geometry": {"coordinates":[9.4311380386,46.79454422],"type":"Point"}
}