{
  "type": "Feature",
  "properties": {
    "addr:full":"Geissweidli 6 Willerzell Schwyz 8846",
    "addr:housenumber":"6",
    "addr:postcode":"8846",
    "addr:street":"Geissweidli;Schwyz",
    "iso:country":"CH",
    "sg:address":"Geissweidli 6",
    "sg:city":"Willerzell",
    "sg:orig_category":"Bauschreinerei Herstellung von Konstruktionsteilen, Fertigbauteilen U Ausbauelementen aus Holz",
    "sg:phone":"+41 55 412 55 94",
    "sg:postcode":"8846",
    "sg:province":"Schwyz",
    "wof:name":"Pero Schreinermontagen Gmbh",
    "wof:placetype":"venue"
},
  "geometry": {"coordinates":[8.797541,47.12748],"type":"Point"}
}