{
  "type": "Feature",
  "properties": {
    "iso:country":"CH",
    "sg:address":"Fahrweg 10",
    "sg:city":"Fulenbach",
    "sg:orig_category":"Schlossereien Schmieden",
    "sg:phone":"+41 62 926 29 40",
    "sg:postcode":"4629",
    "sg:province":"Solothurn",
    "wof:name":"Theodor Wyss Schmiede & Schlosserei",
    "wof:placetype":"venue"
},
  "geometry": {"coordinates":[7.8303251266,47.2694282532],"type":"Point"}
}