{
  "type": "Feature",
  "properties": {
    "iso:country":"CH",
    "sg:address":"Cours De Rive 10",
    "sg:city":"Gen\u00e8ve",
    "sg:orig_category":"Personal U Stellenvermittlung Unternehmensberatung",
    "sg:phone":"+41 18218000",
    "sg:postcode":"1204",
    "sg:province":"Gen\u00e8ve",
    "wof:name":"Ziwalig Personaltreuhand Ag D\u00fcbendorf Unternehmensberatung, Personalvermittlung, Dienstleistungen Im Bereich Der Personaladministration Usw",
    "wof:placetype":"venue"
},
  "geometry": {"coordinates":[8.8514051437,47.2599372864],"type":"Point"}
}