{
  "type": "Feature",
  "properties": {
    "iso:country":"CH",
    "sg:address":"Z\u00fcrcherstrasse 22",
    "sg:city":"Schlieren",
    "sg:orig_category":"Mit dem Versicherungsgewerbe verbundene T\u00e4tigkeiten",
    "sg:phone":"+41 32 384 14 07",
    "sg:postcode":"8952",
    "sg:province":"Z\u00fcrich",
    "wof:name":"Gril Oswald, Unabh\u00e4ngige Neutrale Verischerungsberatung Unvb",
    "wof:placetype":"venue"
},
  "geometry": {"coordinates":[7.3032488823,47.1077919006],"type":"Point"}
}