{
  "type": "Feature",
  "properties": {
    "iso:country":"CH",
    "sg:address":"Al Pascolett",
    "sg:city":"Grono",
    "sg:classifiers":[
        {
            "category":"Building & Trades",
            "subcategory":"Construction",
            "type":"Services"
        }
    ],
    "sg:phone":"+41 91 827 27 39",
    "sg:postcode":"6537",
    "sg:province":"Graubunden",
    "sg:tags":[
        "track"
    ],
    "wof:name":"Fratelli Censi Sa",
    "wof:placetype":"venue"
},
  "geometry": {"coordinates":[9.1554775238,46.2497520447],"type":"Point"}
}