{
  "type": "Feature",
  "properties": {
    "iso:country":"CH",
    "sg:address":"Rue Du Temple 21",
    "sg:city":"Cartigny",
    "sg:orig_category":"Erbringung von sonstigen Dienstleistungen f\u00fcr Unterhaltung, Erholung U Freizeit",
    "sg:phone":"+41 22 756 12 10",
    "sg:postcode":"1236",
    "sg:province":"Gen\u00e8ve",
    "wof:name":"Fondation De Gestion Du Centre De Rencontres De Cartigny",
    "wof:placetype":"venue"
},
  "geometry": {"coordinates":[6.0172700882,46.1740226746],"type":"Point"}
}