{
  "type": "Feature",
  "properties": {
    "iso:country":"CH",
    "sg:address":"Schauplatzgasse 26",
    "sg:city":"Bern",
    "sg:orig_category":"Zahnarztpraxen",
    "sg:phone":"+41 31 311 16 18",
    "sg:postcode":"3011",
    "sg:province":"Bern",
    "wof:name":"Dr. Med. Dent. J\u00fcrg Keller Zahnarzt",
    "wof:placetype":"venue"
},
  "geometry": {"coordinates":[7.4417481422,46.9474639893],"type":"Point"}
}