{
  "type": "Feature",
  "properties": {
    "iso:country":"CH",
    "sg:address":"Obere Sihleggstrasse 6",
    "sg:city":"Schindellegi",
    "sg:orig_category":"Offsetdruck",
    "sg:phone":"+41 17845763",
    "sg:postcode":"8834",
    "sg:province":"Schwyz",
    "wof:name":"Paul-rob. & Roger Leuenberger Druckerei",
    "wof:placetype":"venue"
},
  "geometry": {"coordinates":[8.7107954025,47.182308197],"type":"Point"}
}