{
  "type": "Feature",
  "properties": {
    "iso:country":"CH",
    "sg:address":"Reppischtalstrasse 62",
    "sg:city":"Stallikon",
    "sg:orig_category":"RESTAURANTS: TEA-ROOMS",
    "sg:phone":"+41 81 413 38 95",
    "sg:postcode":"8143",
    "sg:province":"Z\u00fcrich",
    "wof:name":"Restaurant Pizzeria Padrino, Inhaber Antonio Legrottaglie",
    "wof:placetype":"venue"
},
  "geometry": {"coordinates":[9.8229255676,46.7933616638],"type":"Point"}
}