{
  "type": "Feature",
  "properties": {
    "iso:country":"CH",
    "sg:address":"Ch. De La Sapini\u00e8re 11",
    "sg:city":"Vandoeuvres",
    "sg:orig_category":"Unclassifiable Establishments",
    "sg:postcode":"1253",
    "sg:province":"Gen\u00e8ve",
    "wof:name":"Si La Brume-nord",
    "wof:placetype":"venue"
},
  "geometry": {"coordinates":[6.2017698288,46.2142448425],"type":"Point"}
}