{
  "type": "Feature",
  "properties": {
    "iso:country":"CH",
    "sg:address":"Lossy 1783 Pensier. Postfach",
    "sg:city":"Lossy-formangueire",
    "sg:orig_category":"Verwertung von Milch",
    "sg:postcode":"1782",
    "sg:province":"Fribourg",
    "wof:name":"Soci\u00e9t\u00e9 De Laiterie De La Forclaz.",
    "wof:placetype":"venue"
},
  "geometry": {"coordinates":[7.0534849167,46.3616447449],"type":"Point"}
}