{
  "type": "Feature",
  "properties": {
    "iso:country":"CH",
    "sg:address":"Route De Bellegarde 50",
    "sg:city":"Chancy",
    "sg:orig_category":"Sanit\u00e4r U Heizungsinstallation",
    "sg:phone":"+41 79 457 30 13",
    "sg:postcode":"1284",
    "sg:province":"Gen\u00e8ve",
    "wof:name":"Henri Gautschi Installation De Chauffages",
    "wof:placetype":"venue"
},
  "geometry": {"coordinates":[5.9727430344,46.1495628357],"type":"Point"}
}