{
  "type": "Feature",
  "properties": {
    "addr:full":"Rue De La Plaine 50 Yverdon-les-bains Vaud 1400",
    "addr:housenumber":"50",
    "addr:postcode":"1400",
    "addr:street":"Rue De La Plaine",
    "iso:country":"CH",
    "sg:address":"Rue De La Plaine 50",
    "sg:city":"Yverdon-les-bains",
    "sg:orig_category":"Detailhandel mit Blumen U Pflanzen Fachdetailhandel in Verkaufsr\u00e4umen",
    "sg:phone":"+41 24 424 15 24",
    "sg:postcode":"1400",
    "sg:province":"Vaud",
    "wof:name":"Flendrich Fleurs",
    "wof:placetype":"venue"
},
  "geometry": {"coordinates":[6.644269,46.777046],"type":"Point"}
}