{
  "type": "Feature",
  "properties": {
    "iso:country":"CH",
    "sg:address":"Luzernerstrasse 17",
    "sg:city":"Sins",
    "sg:orig_category":"Detailhandel mit Waren verschiedener Art, Hauptrichtung Nahrungsmittel Herstellung von sonstigen Fah",
    "sg:phone":"+41 34 437 17 86",
    "sg:postcode":"5643",
    "sg:province":"Aargau",
    "wof:name":"Markus Sommer Wagnerei & Handlung",
    "wof:placetype":"venue"
},
  "geometry": {"coordinates":[7.7976908684,47.0417785645],"type":"Point"}
}