{
  "type": "Feature",
  "properties": {
    "iso:country":"CH",
    "sg:address":"Kanalweg 8",
    "sg:city":"Sch\u00f6nb\u00fchl-urtenen",
    "sg:orig_category":"Grosshandel mit Textilien Textilgewerbe",
    "sg:postcode":"3322",
    "sg:province":"Bern",
    "wof:name":"Sl Swiss-lein Ag",
    "wof:placetype":"venue"
},
  "geometry": {"coordinates":[7.491271019,47.0203094482],"type":"Point"}
}