{
  "type": "Feature",
  "properties": {
    "iso:country":"CH",
    "sg:address":"Dassier Rue Jean- 20",
    "sg:city":"Gen\u00e8ve",
    "sg:orig_category":"Reiseb\u00fcros U Reiseveranstalter",
    "sg:phone":"+41 22 788 42 16",
    "sg:postcode":"1201",
    "sg:province":"Gen\u00e8ve",
    "wof:name":"Saugy",
    "wof:placetype":"venue"
},
  "geometry": {"coordinates":[6.1394991875,46.2089538574],"type":"Point"}
}