{
  "type": "Feature",
  "properties": {
    "iso:country":"CH",
    "sg:address":"Buenstrasse 75 8600 D\u00fcbendorf. Postfach",
    "sg:city":"D\u00fcbendorf",
    "sg:orig_category":"Non-Classified Establishments",
    "sg:postcode":"8600",
    "sg:province":"Z\u00fcrich",
    "wof:name":"M\u00fcller Talbach Carrosserie Ag",
    "wof:placetype":"venue"
},
  "geometry": {"coordinates":[7.9438538551,47.1364974976],"type":"Point"}
}