{
  "type": "Feature",
  "properties": {
    "iso:country":"CH",
    "sg:address":"Esterliweg 1",
    "sg:city":"Staufen",
    "sg:orig_category":"Detailhandel mit Fahrr\u00e4dern Handel mit Motorr\u00e4dern, Teilen U Zubeh\u00f6r Instandhaltung U Reparatur von ",
    "sg:phone":"+41 62 891 79 79",
    "sg:postcode":"5603",
    "sg:province":"Aargau",
    "wof:name":"Franz Staubmann Velos Motos",
    "wof:placetype":"venue"
},
  "geometry": {"coordinates":[8.1622200012,47.3858451843],"type":"Point"}
}