{
  "type": "Feature",
  "properties": {
    "iso:country":"CH",
    "sg:address":"Avenue Des Cerisiers 5",
    "sg:city":"Crissier",
    "sg:orig_category":"Grosshandel mit sonstigen Maschinen U Ausr\u00fcstungen f\u00fcr Industrie, Handel U Schiffahrt",
    "sg:postcode":"1023",
    "sg:province":"Vaud",
    "wof:name":"Barriendos Eugenio.",
    "wof:placetype":"venue"
},
  "geometry": {"coordinates":[6.5784711838,46.5400695801],"type":"Point"}
}