{
  "type": "Feature",
  "properties": {
    "iso:country":"CH",
    "sg:address":"Dessus",
    "sg:city":"Vallamand",
    "sg:orig_category":"Zimmerei, Dachdeckerei, Bauspenglerei U Abdichtung",
    "sg:postcode":"1586",
    "sg:province":"Vaud",
    "wof:name":"T.e.c. Transformations-entretien-construction S\u00e0rl",
    "wof:placetype":"venue"
},
  "geometry": {"coordinates":[7.0382351875,46.9266242981],"type":"Point"}
}