{
  "type": "Feature",
  "properties": {
    "iso:country":"CH",
    "sg:address":"Seestrasse 47 3600 Thun. Postfach 129",
    "sg:city":"Thun",
    "sg:orig_category":"Kauf U Verkauf von Immobilien auf eigene Rechnung",
    "sg:phone":"+41 33 226 12 12",
    "sg:postcode":"3602",
    "sg:province":"Bern",
    "wof:name":"Hotel Seepark Ag",
    "wof:placetype":"venue"
},
  "geometry": {"coordinates":[7.6343278885,46.745174408],"type":"Point"}
}