{
  "type": "Feature",
  "properties": {
    "iso:country":"CH",
    "sg:address":"Kunibergstrasse",
    "sg:city":"Leukerbad",
    "sg:classifiers":[
        {
            "category":"Government",
            "subcategory":"Post Office",
            "type":"Public Place"
        }
    ],
    "sg:phone":"+41 27 470 40 96",
    "sg:postcode":"3954",
    "sg:province":"Valais",
    "sg:tags":[
        "caf\u00e9s",
        "tea-rooms"
    ],
    "wof:name":"Tea-room Primo-snack",
    "wof:placetype":"venue"
},
  "geometry": {"coordinates":[7.6278572083,46.3820228577],"type":"Point"}
}