{
  "type": "Feature",
  "properties": {
    "iso:country":"CH",
    "sg:address":"Churerstrasse 26",
    "sg:city":"Rorschach",
    "sg:orig_category":"Unclassifiable Establishments",
    "sg:postcode":"9400",
    "sg:province":"St. Gallen",
    "wof:name":"Goldst\u00fcck Gmbh",
    "wof:placetype":"venue"
},
  "geometry": {"coordinates":[9.5016040802,47.4781188965],"type":"Point"}
}