{
  "type": "Feature",
  "properties": {
    "iso:country":"CH",
    "sg:address":"Unterm\u00fcli 7",
    "sg:city":"Zug",
    "sg:orig_category":"Herstellung von Pumpen U Kompressoren",
    "sg:phone":"+41 56 611 04 05",
    "sg:postcode":"6300",
    "sg:province":"Zug",
    "wof:name":"Schurer Consulting",
    "wof:placetype":"venue"
},
  "geometry": {"coordinates":[8.2781887054,47.3421058655],"type":"Point"}
}