{
  "type": "Feature",
  "properties": {
    "iso:country":"CH",
    "sg:address":"Langgr\u00fctstrasse 161",
    "sg:city":"Z\u00fcrich",
    "sg:orig_category":"Sonstiger Grosshandel",
    "sg:postcode":"8047",
    "sg:province":"Z\u00fcrich",
    "wof:name":"Amuzu Export",
    "wof:placetype":"venue"
},
  "geometry": {"coordinates":[8.4904241562,47.3742599487],"type":"Point"}
}