{
  "type": "Feature",
  "properties": {
    "iso:country":"CH",
    "sg:address":"Rue Des Deux-march\u00e9s 15",
    "sg:city":"Vevey",
    "sg:orig_category":"Detailhandel mit Bekleidung Detailhandel mit Pelzwaren",
    "sg:phone":"+41 21 921 88 50",
    "sg:postcode":"1800",
    "sg:province":"Vaud",
    "wof:name":"Au Tigre Royal Vevey S\u00e0rl Gonella-camenisch M. Et Mme.",
    "wof:placetype":"venue"
},
  "geometry": {"coordinates":[6.843789,46.459953],"type":"Point"}
}