{
  "type": "Feature",
  "properties": {
    "iso:country":"CH",
    "sg:address":"Eichholz",
    "sg:city":"Sevelen",
    "sg:orig_category":"Haltung von Rindern",
    "sg:postcode":"9475",
    "sg:province":"St. Gallen",
    "wof:name":"Viehzuchtgenossenschaft Sevelen.",
    "wof:placetype":"venue"
},
  "geometry": {"coordinates":[9.4939899445,47.1311454773],"type":"Point"}
}