{
  "type": "Feature",
  "properties": {
    "iso:country":"CH",
    "sg:address":"Les Savagni\u00e8res 54a",
    "sg:city":"St-imier",
    "sg:orig_category":"RESTAURANTS: TEA-ROOMS",
    "sg:phone":"+41 32 941 45 60",
    "sg:postcode":"2610",
    "sg:province":"Bern",
    "wof:name":"Desboeufs Sylviane",
    "wof:placetype":"venue"
},
  "geometry": {"coordinates":[7.0084819794,47.126750946],"type":"Point"}
}