{
  "type": "Feature",
  "properties": {
    "addr:full":"Davos Baselgia 62b Rueun Graubunden 7156",
    "addr:housenumber":"62b",
    "addr:postcode":"7156",
    "addr:street":"Baselgia;Graubunden",
    "iso:country":"CH",
    "sg:address":"Davos Baselgia 62b",
    "sg:city":"Rueun",
    "sg:orig_category":"Bauspenglerei Zimmerei, Dachdeckerei, Bauspenglerei U Abdichtung",
    "sg:phone":"+41 79 406 70 15",
    "sg:postcode":"7156",
    "sg:province":"Graubunden",
    "wof:name":"Dermont Luis.",
    "wof:placetype":"venue"
},
  "geometry": {"coordinates":[9.152542,46.778606],"type":"Point"}
}