{
  "type": "Feature",
  "properties": {
    "iso:country":"CH",
    "sg:address":"Freilagerstrasse 2",
    "sg:city":"M\u00fcnchenstein",
    "sg:orig_category":"Lagerung",
    "sg:phone":"+41 61 331 36 30",
    "sg:postcode":"4142",
    "sg:province":"Basel-Landschaft",
    "wof:name":"General Transport Ag",
    "wof:placetype":"venue"
},
  "geometry": {"coordinates":[7.6105399132,47.5333137512],"type":"Point"}
}