{
  "type": "Feature",
  "properties": {
    "iso:country":"CH",
    "sg:address":"Isenrietstrasse 25",
    "sg:city":"M\u00f6nchaltorf",
    "sg:orig_category":"Sonstiger Grosshandel",
    "sg:phone":"+41 34 445 05 65",
    "sg:postcode":"8617",
    "sg:province":"Z\u00fcrich",
    "wof:name":"Baumann Peter Waren; Import, Export, Handel. Dienstleistungen Im Versicherungs- U. Verm\u00f6gensbereich",
    "wof:placetype":"venue"
},
  "geometry": {"coordinates":[7.587583065,47.0867996216],"type":"Point"}
}