{
  "type": "Feature",
  "properties": {
    "iso:country":"CH",
    "sg:address":"Unterbort 3792 Saanen. Postfach 94",
    "sg:city":"Saanen",
    "sg:orig_category":"Unclassifiable Establishments",
    "sg:phone":"+41 33 744 47 91",
    "sg:postcode":"3792",
    "sg:province":"Bern",
    "wof:name":"Zingre Chalet-bau Ag",
    "wof:placetype":"venue"
},
  "geometry": {"coordinates":[7.2525620461,46.4943580627],"type":"Point"}
}