{
  "type": "Feature",
  "properties": {
    "iso:country":"CH",
    "sg:address":"Im Seewadel 1",
    "sg:city":"R\u00fcschlikon",
    "sg:orig_category":"Datenverarbeitungsdienste",
    "sg:phone":"+41 17728411",
    "sg:postcode":"8803",
    "sg:province":"Z\u00fcrich",
    "wof:name":"Edv Beratung Wiesendanger",
    "wof:placetype":"venue"
},
  "geometry": {"coordinates":[8.55375,47.301003],"type":"Point"}
}