{
  "type": "Feature",
  "properties": {
    "iso:country":"CH",
    "sg:address":"I. & G. Park",
    "sg:city":"Altenrhein",
    "sg:classifiers":[
        {
            "category":"Manufacturing",
            "subcategory":"Tools & Machinery",
            "type":"Manufacturing & Wholesale Goods"
        }
    ],
    "sg:phone":"+41 71 858 46 20",
    "sg:postcode":"9423",
    "sg:province":"St. Gallen",
    "sg:tags":[
        "machine",
        "part",
        "component"
    ],
    "wof:name":"Sta Strukturwerkstoffe Altenrhein Ag",
    "wof:placetype":"venue"
},
  "geometry": {"coordinates":[9.5517301559,47.4903907776],"type":"Point"}
}