{
  "type": "Feature",
  "properties": {
    "iso:country":"CH",
    "sg:address":"Rue Du Perset 1",
    "sg:city":"P\u00e9ry",
    "sg:orig_category":"Mechanische Werkst\u00e4tten",
    "sg:phone":"+41 32 485 15 91",
    "sg:postcode":"2603",
    "sg:province":"Bern",
    "wof:name":"Pierre Allemann Atelier M\u00e9canique",
    "wof:placetype":"venue"
},
  "geometry": {"coordinates":[7.2428741455,47.1925163269],"type":"Point"}
}