{
  "type": "Feature",
  "properties": {
    "addr:full":"Le Cerf D'or Leysin Vaud 1854",
    "addr:postcode":"1854",
    "iso:country":"CH",
    "sg:address":"Le Cerf D'or",
    "sg:city":"Leysin",
    "sg:orig_category":"Ausbaugewerbe",
    "sg:postcode":"1854",
    "sg:province":"Vaud",
    "wof:name":"Hohl Jean Walter",
    "wof:placetype":"venue"
},
  "geometry": {"coordinates":[7.038961,46.366241],"type":"Point"}
}