{
  "type": "Feature",
  "properties": {
    "iso:country":"CH",
    "sg:address":"Corso Enrico Pestalozzi 10",
    "sg:city":"Lugano",
    "sg:orig_category":"RESTAURANTS: TEA-ROOMS",
    "sg:postcode":"6900",
    "sg:province":"Ticino",
    "wof:name":"Plas Andrea",
    "wof:placetype":"venue"
},
  "geometry": {"coordinates":[8.954035759,46.0055732727],"type":"Point"}
}