{
  "type": "Feature",
  "properties": {
    "iso:country":"CH",
    "sg:address":"Via Arbigo 78 6616 Losone. Postfach Caselle Postale 7001",
    "sg:city":"Losone",
    "sg:orig_category":"Herstellung von Karosserien U Anh\u00e4ngern",
    "sg:phone":"+41 79 685 58 75",
    "sg:postcode":"6616",
    "sg:province":"Ticino",
    "wof:name":"Carozzeria Carrara",
    "wof:placetype":"venue"
},
  "geometry": {"coordinates":[8.7545318604,46.1726264954],"type":"Point"}
}