{
  "type": "Feature",
  "properties": {
    "iso:country":"CH",
    "sg:address":"Brent Route De 24",
    "sg:city":"Blonay",
    "sg:orig_category":"Vermietung U Verpachtung von eigenen Immobilien",
    "sg:phone":"+41 21 943 23 57",
    "sg:postcode":"1807",
    "sg:province":"Vaud",
    "wof:name":"Guethary Sa",
    "wof:placetype":"venue"
},
  "geometry": {"coordinates":[6.8949828148,46.4651298523],"type":"Point"}
}