{
  "type": "Feature",
  "properties": {
    "iso:country":"CH",
    "sg:address":"Kolinplatz 2",
    "sg:city":"Zug",
    "sg:orig_category":"Architektur U Ingenieurb\u00fcros",
    "sg:postcode":"6300",
    "sg:province":"Zug",
    "wof:name":"Marbart Engineering Ag",
    "wof:placetype":"venue"
},
  "geometry": {"coordinates":[8.515376,47.166386],"type":"Point"}
}