{
  "type": "Feature",
  "properties": {
    "iso:country":"CH",
    "sg:address":"Seestrasse 121",
    "sg:city":"Zollikon",
    "sg:orig_category":"Allgemeiner Hochbau Zimmerei, Dachdeckerei, Bauspenglerei U Abdichtung",
    "sg:phone":"+41 79 340 53 81",
    "sg:postcode":"8702",
    "sg:province":"Z\u00fcrich",
    "wof:name":"Dach + Wand Gmbh",
    "wof:placetype":"venue"
},
  "geometry": {"coordinates":[8.636346,46.877911],"type":"Point"}
}