{
  "type": "Feature",
  "properties": {
    "iso:country":"CH",
    "sg:address":"Torri Via Alle 19 6503 Bellinzona. Postfach",
    "sg:city":"Bellinzona",
    "sg:orig_category":"RESTAURANTS: TEA-ROOMS",
    "sg:postcode":"6503",
    "sg:province":"Ticino",
    "wof:name":"Ebocan Sagl Ristorante Alla Taverna",
    "wof:placetype":"venue"
},
  "geometry": {"coordinates":[9.015879631,46.2039718628],"type":"Point"}
}