{
  "type": "Feature",
  "properties": {
    "iso:country":"CH",
    "sg:address":"Bahnhofplatz 6 8854 Siebnen. Postfach",
    "sg:city":"Siebnen",
    "sg:orig_category":"Hardwareberatung",
    "sg:postcode":"8854",
    "sg:province":"Schwyz",
    "wof:name":"Fendata (schweiz) Gmbh",
    "wof:placetype":"venue"
},
  "geometry": {"coordinates":[8.900683403,47.1822814941],"type":"Point"}
}