{
  "type": "Feature",
  "properties": {
    "iso:country":"CH",
    "sg:address":"Fabrikstrasse 36",
    "sg:city":"Bern",
    "sg:orig_category":"Interessenvertretungen",
    "sg:postcode":"3012",
    "sg:province":"Bern",
    "wof:name":"Bashkimi I Intelektualeve Shqiptar Ne Zvicer (bishz)",
    "wof:placetype":"venue"
},
  "geometry": {"coordinates":[7.4251699448,46.9549980164],"type":"Point"}
}