{
  "type": "Feature",
  "properties": {
    "iso:country":"CH",
    "sg:address":"Hauptstrasse 20",
    "sg:city":"Malix",
    "sg:orig_category":"Detailhandel mit Waren verschiedener Art, Hauptrichtung Nahrungsmittel Grosshandel mit Nahrungsmitte",
    "sg:phone":"+41 81 252 19 07",
    "sg:postcode":"7074",
    "sg:province":"Graubunden",
    "wof:name":"Matth\u00e4us Hermann Volg-partner",
    "wof:placetype":"venue"
},
  "geometry": {"coordinates":[9.5326595306,46.8128852844],"type":"Point"}
}