{
  "type": "Feature",
  "properties": {
    "iso:country":"CH",
    "sg:address":"Wehntalerstrasse 284",
    "sg:city":"Z\u00fcrich",
    "sg:orig_category":"Zimmerei, Dachdeckerei, Bauspenglerei U Abdichtung",
    "sg:postcode":"8046",
    "sg:province":"Z\u00fcrich",
    "wof:name":"Pfister Robert & Co Spenglerei Und Sanit\u00e4re Anlagen",
    "wof:placetype":"venue"
},
  "geometry": {"coordinates":[8.5258922577,47.4113922119],"type":"Point"}
}