{
  "type": "Feature",
  "properties": {
    "iso:country":"CH",
    "sg:address":"Schilfweg 9",
    "sg:city":"Egnach",
    "sg:orig_category":"Non-Classified Establishments",
    "sg:postcode":"9322",
    "sg:province":"Thurgau",
    "wof:name":"Trend Haus 2000 Ag",
    "wof:placetype":"venue"
},
  "geometry": {"coordinates":[9.385008812,47.5460929871],"type":"Point"}
}