{
  "type": "Feature",
  "properties": {
    "iso:country":"CH",
    "sg:address":"Eichstrasse 15a 6330 Cham. Postfach",
    "sg:city":"Cham",
    "sg:orig_category":"Maurerarbeiten Sonstiger spezialisierter Hoch U Tiefbau",
    "sg:phone":"+41 41 781 23 39",
    "sg:postcode":"6330",
    "sg:province":"Zug",
    "wof:name":"Cosi Bau Gmbh Maurerarbeiten",
    "wof:placetype":"venue"
},
  "geometry": {"coordinates":[8.4692373276,47.1826286316],"type":"Point"}
}