{
  "type": "Feature",
  "properties": {
    "iso:country":"CH",
    "sg:address":"Avenue Des P\u00e2quiers 1",
    "sg:city":"St-blaise",
    "sg:orig_category":"Herstellung von Brot U Backwaren Herstellung von Dauerbackwaren",
    "sg:phone":"+41 21 691 29 11",
    "sg:postcode":"2072",
    "sg:province":"Neuch\u00e2tel",
    "wof:name":"Jowa Sa",
    "wof:placetype":"venue"
},
  "geometry": {"coordinates":[6.5598988533,46.5390434265],"type":"Point"}
}