{
  "type": "Feature",
  "properties": {
    "iso:country":"CH",
    "sg:address":"Caf\u00e9 Du Centre",
    "sg:city":"Mi\u00e8ge",
    "sg:orig_category":"Unclassifiable Establishments",
    "sg:postcode":"3972",
    "sg:province":"Valais",
    "wof:name":"Oertel Anna & Cie, 'caf\u00e9 Du Centre'",
    "wof:placetype":"venue"
},
  "geometry": {"coordinates":[7.5477252007,46.3121948242],"type":"Point"}
}