{
  "type": "Feature",
  "properties": {
    "iso:country":"CH",
    "sg:address":"Sportplatz Emmig",
    "sg:city":"Steckborn",
    "sg:orig_category":"Sportvereine Ballsport Fussball",
    "sg:phone":"+41 17133653",
    "sg:postcode":"8266",
    "sg:province":"Thurgau",
    "wof:name":"Fussballclub Langnau Am Albis",
    "wof:placetype":"venue"
},
  "geometry": {"coordinates":[8.5343046188,47.2828598022],"type":"Point"}
}