{
  "type": "Feature",
  "properties": {
    "iso:country":"CH",
    "sg:address":"Via Collina D'oro 65",
    "sg:city":"Montagnola",
    "sg:orig_category":"Fachdetailhandel in Verkaufsr\u00e4umen Grosshandel mit sonstigen Gebrauchs U Verbrauchsg\u00fctern",
    "sg:phone":"+41 79 621 40 87",
    "sg:postcode":"6926",
    "sg:province":"Ticino",
    "wof:name":"Silva Fiori Sagl",
    "wof:placetype":"venue"
},
  "geometry": {"coordinates":[8.9171819687,45.982673645],"type":"Point"}
}