{
  "type": "Feature",
  "properties": {
    "iso:country":"CH",
    "sg:address":"Route Cantonale 139 Ecuvillens",
    "sg:city":"Ecuvillens",
    "sg:orig_category":"Detailhandel mit Radio U Fernsehger\u00e4ten Detailhandel mit elektrischen Haushalts-,Radio U Fernsehger\u00e4",
    "sg:postcode":"1730",
    "sg:province":"Fribourg",
    "wof:name":"Gilbert Goetschmann",
    "wof:placetype":"venue"
},
  "geometry": {"coordinates":[7.0892109871,46.7579231262],"type":"Point"}
}