{
  "type": "Feature",
  "properties": {
    "iso:country":"CH",
    "sg:address":"Dungele",
    "sg:city":"Winikon",
    "sg:orig_category":"Baugewerbe",
    "sg:phone":"+41 41 933 09 19",
    "sg:postcode":"6235",
    "sg:province":"Luzern",
    "wof:name":"Ueli L\u00fctolf Ag Baumontagen",
    "wof:placetype":"venue"
},
  "geometry": {"coordinates":[8.038376,47.234943],"type":"Point"}
}