{
  "type": "Feature",
  "properties": {
    "iso:country":"CH",
    "sg:address":"Godet Quai Phillipe- 18",
    "sg:city":"Neuch\u00e2tel",
    "sg:orig_category":"Sanit\u00e4r, Heizungs U L\u00fcftungsinstallation",
    "sg:phone":"+41 91 683 40 16",
    "sg:postcode":"2000",
    "sg:province":"Neuch\u00e2tel",
    "wof:name":"Lurati Angelo",
    "wof:placetype":"venue"
},
  "geometry": {"coordinates":[9.0503702164,45.870098114],"type":"Point"}
}