{
  "type": "Feature",
  "properties": {
    "iso:country":"CH",
    "sg:address":"Alte Bruggerstrasse 10 5605 Dottikon. Postfach 46",
    "sg:city":"Dottikon",
    "sg:orig_category":"Architektur U Ingenieurb\u00fcros",
    "sg:phone":"+41 56 624 38 80",
    "sg:postcode":"5605",
    "sg:province":"Aargau",
    "wof:name":"Widmer Ag Architekturb\u00fcro",
    "wof:placetype":"venue"
},
  "geometry": {"coordinates":[8.235124,47.374561],"type":"Point"}
}