{
  "type": "Feature",
  "properties": {
    "addr:full":"Le Dally 14 Vuadens Fribourg 1628",
    "addr:housenumber":"14",
    "addr:postcode":"1628",
    "iso:country":"CH",
    "sg:address":"Le Dally 14",
    "sg:city":"Vuadens",
    "sg:orig_category":"Architektur U Ingenieurb\u00fcros",
    "sg:phone":"+41 79 230 56 06",
    "sg:postcode":"1628",
    "sg:province":"Fribourg",
    "wof:name":"Serge Philipona Ing. Ets",
    "wof:placetype":"venue"
},
  "geometry": {"coordinates":[7.030512,46.614796],"type":"Point"}
}