{
  "type": "Feature",
  "properties": {
    "iso:country":"CH",
    "sg:address":"Route Des Creux",
    "sg:city":"Verbier",
    "sg:orig_category":"Detailhandel mit S\u00e4uglings U Kinderbekleidung",
    "sg:phone":"+41 41 850 27 33",
    "sg:postcode":"1936",
    "sg:province":"Valais",
    "wof:name":"Moby's Kinderboutique",
    "wof:placetype":"venue"
},
  "geometry": {"coordinates":[8.4415683746,47.0812110901],"type":"Point"}
}