{
  "type": "Feature",
  "properties": {
    "iso:country":"CH",
    "sg:address":"Sonneggstrasse 76",
    "sg:city":"Z\u00fcrich",
    "sg:orig_category":"Grafikateliers, Design",
    "sg:phone":"+41 22 342 33 77",
    "sg:postcode":"8006",
    "sg:province":"Z\u00fcrich",
    "wof:name":"Lettra Syst\u00e8me Sa",
    "wof:placetype":"venue"
},
  "geometry": {"coordinates":[6.1285629272,46.1871337891],"type":"Point"}
}