{
  "type": "Feature",
  "properties": {
    "iso:country":"CH",
    "sg:address":"St-loup",
    "sg:city":"Pompaples",
    "sg:orig_category":"Interessenvertretungen",
    "sg:phone":"+41 21 866 60 93",
    "sg:postcode":"1318",
    "sg:province":"Vaud",
    "wof:name":"Institution Des Diaconesses",
    "wof:placetype":"venue"
},
  "geometry": {"coordinates":[6.5050301552,46.6662788391],"type":"Point"}
}