{
  "type": "Feature",
  "properties": {
    "iso:country":"CH",
    "sg:address":"Repfergasse 32",
    "sg:city":"Schaffhausen",
    "sg:orig_category":"Detailhandel mit Sportartikeln Vermietung von Gebrauchsg\u00fctern",
    "sg:phone":"+41 27 957 31 61",
    "sg:postcode":"8200",
    "sg:province":"Schaffhausen",
    "wof:name":"Martina Burgener Burgener Sport",
    "wof:placetype":"venue"
},
  "geometry": {"coordinates":[7.9367241859,46.1232452393],"type":"Point"}
}