{
  "type": "Feature",
  "properties": {
    "iso:country":"CH",
    "sg:address":"Oberdorfstrasse 13",
    "sg:city":"Steffisburg",
    "sg:orig_category":"Detailhandel mit Blumen U Pflanzen Fachdetailhandel in Verkaufsr\u00e4umen",
    "sg:phone":"+41 33 437 88 14",
    "sg:postcode":"3612",
    "sg:province":"Bern",
    "wof:name":"Blumenboutique Goldschmid Ursula",
    "wof:placetype":"venue"
},
  "geometry": {"coordinates":[7.633895,46.77948],"type":"Point"}
}