{
  "type": "Feature",
  "properties": {
    "iso:country":"CH",
    "sg:address":"Ankerstrasse 119",
    "sg:city":"Z\u00fcrich",
    "sg:orig_category":"Sonstiger Grosshandel",
    "sg:postcode":"8004",
    "sg:province":"Z\u00fcrich",
    "wof:name":"Smach Fundgrube",
    "wof:placetype":"venue"
},
  "geometry": {"coordinates":[8.5282154083,47.3765945435],"type":"Point"}
}