{
  "type": "Feature",
  "properties": {
    "iso:country":"CH",
    "sg:address":"Holzstrasse 1",
    "sg:city":"Muotathal",
    "sg:orig_category":"S\u00e4gewerke Zimmerei, Dachdeckerei, Bauspenglerei U Abdichtung",
    "sg:phone":"+41 41 830 14 80",
    "sg:postcode":"6436",
    "sg:province":"Schwyz",
    "wof:name":"Suter Josef & Co",
    "wof:placetype":"venue"
},
  "geometry": {"coordinates":[8.758895874,46.9739608765],"type":"Point"}
}