{
  "type": "Feature",
  "properties": {
    "iso:country":"CH",
    "sg:address":"Treytorrens",
    "sg:city":"Cully",
    "sg:orig_category":"Rebbau",
    "sg:phone":"+41 21 799 13 00",
    "sg:postcode":"1096",
    "sg:province":"Vaud",
    "wof:name":"Jean-claude Chevalley & Fils Viticulteur-p\u00e9pini\u00e9riste",
    "wof:placetype":"venue"
},
  "geometry": {"coordinates":[6.7545599937,46.4846916199],"type":"Point"}
}