{
  "type": "Feature",
  "properties": {
    "iso:country":"CH",
    "sg:address":"1525",
    "sg:city":"Henniez",
    "sg:classifiers":[
        {
            "category":"Food Court",
            "type":"Food & Drink"
        }
    ],
    "sg:phone":"+41 71 314 64 74",
    "sg:postcode":"1525",
    "sg:province":"Vaud",
    "sg:tags":[
        "product",
        "related"
    ],
    "wof:name":"Supro-n\u00c4hrmittel Ag",
    "wof:placetype":"venue"
},
  "geometry": {"coordinates":[7.08604002,51.2439613342],"type":"Point"}
}