{
  "type": "Feature",
  "properties": {
    "iso:country":"CH",
    "sg:address":"B\u00fchlstrasse 8a",
    "sg:city":"Balgach",
    "sg:orig_category":"Vorschulen, Kinderg\u00e4rten",
    "sg:phone":"+41 71 722 45 80",
    "sg:postcode":"9436",
    "sg:province":"St. Gallen",
    "wof:name":"Kindergarten Horst",
    "wof:placetype":"venue"
},
  "geometry": {"coordinates":[9.6092262268,47.407459259],"type":"Point"}
}