{
  "type": "Feature",
  "properties": {
    "iso:country":"CH",
    "sg:address":"Ancien-port Rue De L' 13 1201 Gen\u00e8ve. Postfach",
    "sg:city":"Gen\u00e8ve",
    "sg:orig_category":"Betrieb U technische Hilfsdienste des Kultur U Unterhaltungswesens",
    "sg:postcode":"1201",
    "sg:province":"Gen\u00e8ve",
    "wof:name":"Association The Mood Lamalgam",
    "wof:placetype":"venue"
},
  "geometry": {"coordinates":[6.155522,46.199749],"type":"Point"}
}