{
  "type": "Feature",
  "properties": {
    "iso:country":"CH",
    "sg:address":"Bahnhofstrasse 7 6300 Zug. Postfach 1225",
    "sg:city":"Zug",
    "sg:orig_category":"Rechtsberatung",
    "sg:postcode":"6301",
    "sg:province":"Zug",
    "wof:name":"W\u00e4lti Richard, Rechtsberatung",
    "wof:placetype":"venue"
},
  "geometry": {"coordinates":[8.7197780609,47.2726097107],"type":"Point"}
}