{
  "type": "Feature",
  "properties": {
    "iso:country":"CH",
    "sg:address":"Rue Fleury 12",
    "sg:city":"Neuch\u00e2tel",
    "sg:orig_category":"Detailhandel mit Fleisch U Fleischwaren Detailhandel mit Waren verschiedener Art, Hauptrichtung Nahr",
    "sg:phone":"+41 32 725 22 30",
    "sg:postcode":"2000",
    "sg:province":"Neuch\u00e2tel",
    "wof:name":"Carnasec Sa Boucherie",
    "wof:placetype":"venue"
},
  "geometry": {"coordinates":[6.9282250404,46.9912757874],"type":"Point"}
}