{
  "type": "Feature",
  "properties": {
    "iso:country":"CH",
    "sg:address":"Fesciano Via",
    "sg:city":"Cadro",
    "sg:orig_category":"Softwareentwicklung U beratung",
    "sg:postcode":"6965",
    "sg:province":"Ticino",
    "wof:name":"High Power Solutions Di Pellegrini & Stefanini",
    "wof:placetype":"venue"
},
  "geometry": {"coordinates":[8.9852170944,46.0418891907],"type":"Point"}
}