{
  "type": "Feature",
  "properties": {
    "iso:country":"CH",
    "sg:address":"Grand-rue 37",
    "sg:city":"Vallorbe",
    "sg:orig_category":"Fachdetailhandel mit pharmazeutischen Produkten",
    "sg:phone":"+41 21 843 10 25",
    "sg:postcode":"1337",
    "sg:province":"Vaud",
    "wof:name":"Pharmacie Du Sapin, Mourey Mme Claude",
    "wof:placetype":"venue"
},
  "geometry": {"coordinates":[6.3768072128,46.7115745544],"type":"Point"}
}