{
  "type": "Feature",
  "properties": {
    "iso:country":"CH",
    "sg:address":"Hauptstrasse",
    "sg:city":"Maloja",
    "sg:classifiers":[
        {
            "category":"Travel",
            "subcategory":"Hotels & Motels",
            "type":"Entertainment"
        }
    ],
    "sg:phone":"+41 81 416 34 44",
    "sg:postcode":"7516",
    "sg:province":"Graubunden",
    "sg:tags":[
        "hotels",
        "mit",
        "restaurant"
    ],
    "wof:name":"Sporthotel Montana, Christoffel Hans",
    "wof:placetype":"venue"
},
  "geometry": {"coordinates":[9.8407659531,46.8088722229],"type":"Point"}
}