{
  "type": "Feature",
  "properties": {
    "iso:country":"CH",
    "sg:address":"Im Moos 2",
    "sg:city":"L\u00fcchingen",
    "sg:orig_category":"Instandhaltung U Reparatur von Automobilen",
    "sg:phone":"+41 71 755 38 10",
    "sg:postcode":"9450",
    "sg:province":"St. Gallen",
    "wof:name":"Untersee Fredy",
    "wof:placetype":"venue"
},
  "geometry": {"coordinates":[9.5556592941,47.3843078613],"type":"Point"}
}