{
  "type": "Feature",
  "properties": {
    "iso:country":"CH",
    "sg:address":"Thunstrasse 40 3005 Bern. Postfach",
    "sg:city":"Bern",
    "sg:orig_category":"Herstellung von Seifen, Wasch U Reinigungsmitteln",
    "sg:postcode":"3005",
    "sg:province":"Bern",
    "wof:name":"Georges K\u00fcbli Putzartikel-handel.",
    "wof:placetype":"venue"
},
  "geometry": {"coordinates":[7.456548214,46.9410018921],"type":"Point"}
}