{
  "type": "Feature",
  "properties": {
    "iso:country":"CH",
    "sg:address":"Via Curti 5",
    "sg:city":"Lugano",
    "sg:orig_category":"Institutionen f\u00fcr Finanzierungsleasing",
    "sg:postcode":"6900",
    "sg:province":"Ticino",
    "wof:name":"Dubuis Data Finance",
    "wof:placetype":"venue"
},
  "geometry": {"coordinates":[6.9261350632,46.39818573],"type":"Point"}
}