{
  "type": "Feature",
  "properties": {
    "iso:country":"CH",
    "sg:address":"Roseaux Chemin Des 5c",
    "sg:city":"Hauterive",
    "sg:orig_category":"Instandhaltung U Reparatur von Automobilen",
    "sg:phone":"+41 32 724 96 99",
    "sg:postcode":"2068",
    "sg:province":"Neuch\u00e2tel",
    "wof:name":"A.a.f. Assistance Auto Fiorucci",
    "wof:placetype":"venue"
},
  "geometry": {"coordinates":[6.9710087776,47.0127906799],"type":"Point"}
}