{
  "type": "Feature",
  "properties": {
    "iso:country":"CH",
    "sg:address":"Dorfstrasse 63b",
    "sg:city":"Untersiggenthal",
    "sg:orig_category":"Arztpraxen",
    "sg:phone":"+41 56 288 25 27",
    "sg:postcode":"5417",
    "sg:province":"Aargau",
    "wof:name":"Dr.med.beat Marbach Arzt F.allgemeine Medizin Fmh",
    "wof:placetype":"venue"
},
  "geometry": {"coordinates":[8.254433,47.501724],"type":"Point"}
}