{
  "type": "Feature",
  "properties": {
    "iso:country":"CH",
    "sg:address":"Ziegelbr\u00fcckestr. 71 8867 Niederurnen. Postfach",
    "sg:city":"Ziegelbr\u00fccke",
    "sg:orig_category":"Herstellung von Metallkonstruktionen",
    "sg:postcode":"8866",
    "sg:province":"Glarus",
    "wof:name":"Betschart Peter, Montagebau",
    "wof:placetype":"venue"
},
  "geometry": {"coordinates":[9.0590229034,47.1318702698],"type":"Point"}
}