{
  "type": "Feature",
  "properties": {
    "iso:country":"CH",
    "sg:address":"8573 Alterswilen. Postfach",
    "sg:city":"Siegershausen",
    "sg:orig_category":"Fotografisches Gewerbe U fotografische Laboratorien",
    "sg:postcode":"8573",
    "sg:province":"Thurgau",
    "wof:name":"Bommer-weiher Studio Ag",
    "wof:placetype":"venue"
},
  "geometry": {"coordinates":[9.1542901993,47.609413147],"type":"Point"}
}