{
  "type": "Feature",
  "properties": {
    "iso:country":"CH",
    "sg:address":"In Bichwil Ausserdorf.",
    "sg:city":"Oberuzwil",
    "sg:orig_category":"Zimmerei, Dachdeckerei, Bauspenglerei U Abdichtung",
    "sg:postcode":"9242",
    "sg:province":"St. Gallen",
    "wof:name":"B\u00fchler & Co.",
    "wof:placetype":"venue"
},
  "geometry": {"coordinates":[9.1233797073,47.4295463562],"type":"Point"}
}