{
  "type": "Feature",
  "properties": {
    "iso:country":"CH",
    "sg:address":"Strehlgasse 29",
    "sg:city":"Z\u00fcrich",
    "sg:orig_category":"Wirtschaftspr\u00fcfung, Steuerberatung U Treuhand",
    "sg:phone":"+41 19292670",
    "sg:postcode":"8001",
    "sg:province":"Z\u00fcrich",
    "wof:name":"Walser-treuhand",
    "wof:placetype":"venue"
},
  "geometry": {"coordinates":[8.7246389389,47.2663269043],"type":"Point"}
}