{
  "type": "Feature",
  "properties": {
    "iso:country":"CH",
    "sg:address":"Altwiesenstrasse 16",
    "sg:city":"W\u00fcrenlos",
    "sg:orig_category":"Non-Classified Establishments",
    "sg:postcode":"5436",
    "sg:province":"Aargau",
    "wof:name":"Roth Relations . Public & Investor Relations Consulting",
    "wof:placetype":"venue"
},
  "geometry": {"coordinates":[8.3621912003,47.4356803894],"type":"Point"}
}