{
  "type": "Feature",
  "properties": {
    "addr:full":"Polenl\u00f6serweg 850 Untervaz Graubunden 7204",
    "addr:housenumber":"850;7204",
    "addr:street":"Untervaz Graubunden",
    "iso:country":"CH",
    "sg:address":"Polenl\u00f6serweg 850",
    "sg:city":"Untervaz",
    "sg:orig_category":"Bau von Strassen, Sportanlagen U Bahnverkehrsstrecken Strassenbau",
    "sg:phone":"+41 81 322 35 89",
    "sg:postcode":"7204",
    "sg:province":"Graubunden",
    "wof:name":"Palatini Ag Strassenbau",
    "wof:placetype":"venue"
},
  "geometry": {"coordinates":[9.553674,46.915627],"type":"Point"}
}