{
  "type": "Feature",
  "properties": {
    "iso:country":"CH",
    "sg:address":"Reggenschwilerstrasse 14",
    "sg:city":"M\u00f6rschwil",
    "sg:orig_category":"Wirtschaftspr\u00fcfung, Steuerberatung U Treuhand",
    "sg:phone":"+41 71 866 16 46",
    "sg:postcode":"9402",
    "sg:province":"St. Gallen",
    "wof:name":"Gm\u00fcnder Josef Versicherungs-treuhand",
    "wof:placetype":"venue"
},
  "geometry": {"coordinates":[9.414182663,47.466632843],"type":"Point"}
}