{
  "type": "Feature",
  "properties": {
    "iso:country":"CH",
    "sg:address":"In Der Rehweid 7",
    "sg:city":"Wettswil",
    "sg:orig_category":"Kauf U Verkauf von Immobilien auf eigene Rechnung",
    "sg:postcode":"8907",
    "sg:province":"Z\u00fcrich",
    "wof:name":"Mabaro Ag",
    "wof:placetype":"venue"
},
  "geometry": {"coordinates":[8.4693346024,47.3451309204],"type":"Point"}
}