{
  "type": "Feature",
  "properties": {
    "iso:country":"CH",
    "sg:address":"Langenacker 4",
    "sg:city":"Gais",
    "sg:orig_category":"Architektur U Ingenieurb\u00fcros",
    "sg:postcode":"9056",
    "sg:province":"Appenzell Ausserrhoden",
    "wof:name":"Kocian Zbynek, Industrieberatung",
    "wof:placetype":"venue"
},
  "geometry": {"coordinates":[8.807577,47.324055],"type":"Point"}
}