{
  "type": "Feature",
  "properties": {
    "iso:country":"CH",
    "sg:address":"Tschamerie 22",
    "sg:city":"Hasle-r\u00fcegsau",
    "sg:orig_category":"Detailhandel mit Waren verschiedener Art, Hauptrichtung Nahrungsmittel",
    "sg:phone":"+41 34 461 12 63",
    "sg:postcode":"3415",
    "sg:province":"Bern",
    "wof:name":"Hans Mosimann Handlung",
    "wof:placetype":"venue"
},
  "geometry": {"coordinates":[7.6392588615,47.0234336853],"type":"Point"}
}