{
  "type": "Feature",
  "properties": {
    "iso:country":"CH",
    "sg:address":"M\u00f6nchsbergerstrasse 2 4053 Basel. Postfach",
    "sg:city":"Basel",
    "sg:orig_category":"Satzherstellung U Reproduktion",
    "sg:postcode":"4051",
    "sg:province":"Basel-Stadt",
    "wof:name":"Diginetal Bo Basel Gmbh",
    "wof:placetype":"venue"
},
  "geometry": {"coordinates":[7.5990028381,47.5381774902],"type":"Point"}
}