{
  "type": "Feature",
  "properties": {
    "iso:country":"CH",
    "sg:address":"Grabengasse 11",
    "sg:city":"B\u00fclach",
    "sg:orig_category":"Detailhandel mit Beleuchtungs U Haushaltsgegenst\u00e4nden",
    "sg:phone":"+41 31 972 42 40",
    "sg:postcode":"8180",
    "sg:province":"Z\u00fcrich",
    "wof:name":"Willi Meier Haushaltapparate",
    "wof:placetype":"venue"
},
  "geometry": {"coordinates":[7.433887,46.926018],"type":"Point"}
}