{
  "type": "Feature",
  "properties": {
    "iso:country":"CH",
    "sg:address":"Puits-godet Rue Du 10 A",
    "sg:city":"Neuch\u00e2tel",
    "sg:orig_category":"RESTAURANTS: TEA-ROOMS",
    "sg:phone":"+41 32 724 26 10",
    "sg:postcode":"2000",
    "sg:province":"Neuch\u00e2tel",
    "wof:name":"Restaurant Du Puits, Duvoisin Et Cie",
    "wof:placetype":"venue"
},
  "geometry": {"coordinates":[6.9133257866,46.9985961914],"type":"Point"}
}