{
  "type": "Feature",
  "properties": {
    "iso:country":"CH",
    "sg:address":"G\u00fcrtelstrasse 65 7000 Chur. Postfach 131",
    "sg:city":"Chur",
    "sg:orig_category":"Zahntechnische Laboratorien",
    "sg:phone":"+41 81 353 72 08",
    "sg:postcode":"7002",
    "sg:province":"Graubunden",
    "wof:name":"Andres Dentaltechnik",
    "wof:placetype":"venue"
},
  "geometry": {"coordinates":[9.5298748016,46.8557434082],"type":"Point"}
}