{
  "type": "Feature",
  "properties": {
    "iso:country":"CH",
    "sg:address":"Lerberstrasse 18",
    "sg:city":"Bern",
    "sg:orig_category":"Kunsthandel",
    "sg:phone":"+41 31 333 12 20",
    "sg:postcode":"3013",
    "sg:province":"Bern",
    "wof:name":"Harri Lehmann Blue Steel Art Kunsthandel",
    "wof:placetype":"venue"
},
  "geometry": {"coordinates":[7.4591031075,46.9510803223],"type":"Point"}
}