{
  "type": "Feature",
  "properties": {
    "iso:country":"CH",
    "sg:address":"Freiestrasse 21",
    "sg:city":"Uster",
    "sg:classifiers":[
        {
            "category":"Restaurant",
            "type":"Food & Drink"
        }
    ],
    "sg:phone":"+41 71 223 26 02",
    "sg:postcode":"8610",
    "sg:province":"Z\u00fcrich",
    "wof:name":"Restaurant Steingr\u00fcbli",
    "wof:placetype":"venue"
},
  "geometry": {"coordinates":[9.3907136917,47.4148864746],"type":"Point"}
}