{
  "type": "Feature",
  "properties": {
    "iso:country":"CH",
    "sg:address":"Rue De St-jean 92",
    "sg:city":"Perly",
    "sg:orig_category":"Grosshandel mit pharmazeutischen Erzeugnissen, medizinischen U orthop\u00e4dischen Artikeln",
    "sg:postcode":"1258",
    "sg:province":"Gen\u00e8ve",
    "wof:name":"Bodan Pharma, Todt Sylvia Halspastillen Usw; Import U. Engroshandel.",
    "wof:placetype":"venue"
},
  "geometry": {"coordinates":[9.3655843735,47.4101676941],"type":"Point"}
}