{
  "type": "Feature",
  "properties": {
    "iso:country":"CH",
    "sg:address":"Aegetli 3",
    "sg:city":"Thal",
    "sg:orig_category":"Herstellung von Metallkonstruktionen Reparatur von sonstigen Gebrauchsg\u00fctern",
    "sg:phone":"+41 18445927",
    "sg:postcode":"9425",
    "sg:province":"St. Gallen",
    "wof:name":"Tinner System-montagen & Storenbau",
    "wof:placetype":"venue"
},
  "geometry": {"coordinates":[8.4048643112,47.446647644],"type":"Point"}
}