{
  "type": "Feature",
  "properties": {
    "iso:country":"CH",
    "sg:address":"Ruchholzstrasse 25",
    "sg:city":"Bottmingen",
    "sg:orig_category":"Vorschulen, Kinderg\u00e4rten",
    "sg:phone":"+41 61 421 81 01",
    "sg:postcode":"4103",
    "sg:province":"Basel-Landschaft",
    "wof:name":"Kindergarten",
    "wof:placetype":"venue"
},
  "geometry": {"coordinates":[7.5747151375,47.5252952576],"type":"Point"}
}