{
  "type": "Feature",
  "properties": {
    "iso:country":"CH",
    "sg:address":"Av. Eug\u00e8ne-lance 50",
    "sg:city":"Grand-lancy",
    "sg:orig_category":"Einbau von Schreinerwaren",
    "sg:phone":"+41 22 880 06 60",
    "sg:postcode":"1212",
    "sg:province":"Gen\u00e8ve",
    "wof:name":"Sch\u00fcller Rudolf",
    "wof:placetype":"venue"
},
  "geometry": {"coordinates":[6.1242699623,46.1766014099],"type":"Point"}
}