{
  "type": "Feature",
  "properties": {
    "iso:country":"CH",
    "sg:address":"Hauptstrasse 27",
    "sg:city":"Brunegg",
    "sg:orig_category":"Instandhaltung U Reparatur von Automobilen",
    "sg:phone":"+41 22 342 55 10",
    "sg:postcode":"5505",
    "sg:province":"Aargau",
    "wof:name":"Sporting Garage, Chatelanat Gabriel",
    "wof:placetype":"venue"
},
  "geometry": {"coordinates":[6.1414251328,46.1833114624],"type":"Point"}
}