{
  "type": "Feature",
  "properties": {
    "iso:country":"CH",
    "sg:address":"Luggwegstrasse 118",
    "sg:city":"Z\u00fcrich",
    "sg:orig_category":"Vorschulen, Kinderg\u00e4rten",
    "sg:phone":"+41 14322949",
    "sg:postcode":"8048",
    "sg:province":"Z\u00fcrich",
    "wof:name":"Luggweg-chindsgi Privatkindergarten",
    "wof:placetype":"venue"
},
  "geometry": {"coordinates":[8.4883756638,47.3832359314],"type":"Point"}
}