{
  "type": "Feature",
  "properties": {
    "iso:country":"CH",
    "sg:address":"Kernstrasse 60",
    "sg:city":"Z\u00fcrich",
    "sg:classifiers":[
        {
            "category":"Restaurant",
            "type":"Food & Drink"
        }
    ],
    "sg:phone":"+41 62 216 13 19",
    "sg:postcode":"8004",
    "sg:province":"Z\u00fcrich",
    "sg:tags":[
        "tea-rooms",
        "restaurants"
    ],
    "wof:name":"Restaurant Kreuz Von D\u00e4niken S.",
    "wof:placetype":"venue"
},
  "geometry": {"coordinates":[7.8560471535,47.3400115967],"type":"Point"}
}