{
  "type": "Feature",
  "properties": {
    "iso:country":"CH",
    "sg:address":"Schwanden",
    "sg:city":"Vitznau",
    "sg:orig_category":"Sonstige mit der Informatik verbundene T\u00e4tigkeiten",
    "sg:postcode":"6354",
    "sg:province":"Luzern",
    "wof:name":"Material Phases Data System Mpds Villars",
    "wof:placetype":"venue"
},
  "geometry": {"coordinates":[8.4833097458,47.0103416443],"type":"Point"}
}