{
  "type": "Feature",
  "properties": {
    "addr:full":"Bahnhofstrasse 61 Burgdorf Bern 3400",
    "addr:housenumber":"61",
    "addr:postcode":"3400",
    "addr:street":"Bahnhofstrasse",
    "iso:country":"CH",
    "sg:address":"Bahnhofstrasse 61",
    "sg:city":"Burgdorf",
    "sg:orig_category":"Chiropraktik",
    "sg:phone":"+41 34 422 86 87",
    "sg:postcode":"3400",
    "sg:province":"Bern",
    "wof:name":"Dr.bendicht Beglinger Chiropraktor",
    "wof:placetype":"venue"
},
  "geometry": {"coordinates":[7.62164,47.0597],"type":"Point"}
}