{
  "type": "Feature",
  "properties": {
    "iso:country":"CH",
    "sg:address":"Hauptstrasse 78",
    "sg:city":"B\u00f6zen",
    "sg:orig_category":"Organisationen des Gesundheitswesen",
    "sg:phone":"+41 62 876 10 57",
    "sg:postcode":"5076",
    "sg:province":"Aargau",
    "wof:name":"Samariterverein Hornussen",
    "wof:placetype":"venue"
},
  "geometry": {"coordinates":[8.0818099976,47.4950752258],"type":"Point"}
}