{
  "type": "Feature",
  "properties": {
    "iso:country":"CH",
    "sg:address":"G\u00e4belbachstrasse 37",
    "sg:city":"Bern",
    "sg:orig_category":"Sonstiger Grosshandel",
    "sg:postcode":"3027",
    "sg:province":"Bern",
    "wof:name":"Imex Abdeen",
    "wof:placetype":"venue"
},
  "geometry": {"coordinates":[7.3764829636,46.9489898682],"type":"Point"}
}