{
  "type": "Feature",
  "properties": {
    "iso:country":"CH",
    "sg:address":"L\u00fcsselmattweg 3",
    "sg:city":"Zwingen",
    "sg:orig_category":"Non-Classified Establishments",
    "sg:phone":"+41 61 761 13 13",
    "sg:postcode":"4222",
    "sg:province":"Basel-Landschaft",
    "wof:name":"F. Studer Ag",
    "wof:placetype":"venue"
},
  "geometry": {"coordinates":[7.5305409431,47.4308853149],"type":"Point"}
}