{
  "type": "Feature",
  "properties": {
    "addr:full":"Unterdorf 13 Speicher Appenzell Ausserrhoden 9042",
    "addr:housenumber":"13",
    "addr:postcode":"9042",
    "addr:street":"Unterdorf;Ausserrhoden",
    "iso:country":"CH",
    "sg:address":"Unterdorf 13",
    "sg:city":"Speicher",
    "sg:orig_category":"Advokaturb\u00fcros",
    "sg:phone":"+41 71 222 10 77",
    "sg:postcode":"9042",
    "sg:province":"Appenzell Ausserrhoden",
    "wof:name":"Pietro Donati Advokaturb\u00fcro",
    "wof:placetype":"venue"
},
  "geometry": {"coordinates":[9.44565,47.413059],"type":"Point"}
}