{
  "type": "Feature",
  "properties": {
    "iso:country":"CH",
    "sg:address":"Rue Des Moulins 31",
    "sg:city":"Neuenburg",
    "sg:orig_category":"Unternehmensberatung",
    "sg:phone":"+41 32 725 00 07",
    "sg:postcode":"2000",
    "sg:province":"Neuch\u00e2tel",
    "wof:name":"Interconcept Jcm, Monachon Jean-claude",
    "wof:placetype":"venue"
},
  "geometry": {"coordinates":[6.9278922081,46.9926528931],"type":"Point"}
}