{
  "type": "Feature",
  "properties": {
    "iso:country":"CH",
    "sg:address":"Bahnhofstrasse 28 6300 Zug. Postfach 1358",
    "sg:city":"Zug",
    "sg:orig_category":"Reiseb\u00fcros U Reiseveranstalter",
    "sg:phone":"+41 41 711 97 79",
    "sg:postcode":"6301",
    "sg:province":"Zug",
    "wof:name":"Arcatour Sa",
    "wof:placetype":"venue"
},
  "geometry": {"coordinates":[8.5159921646,47.1701126099],"type":"Point"}
}