{
  "type": "Feature",
  "properties": {
    "iso:country":"CH",
    "sg:address":"Rotmattstrasse 13",
    "sg:city":"Meggen",
    "sg:orig_category":"Vermietung U Verpachtung von eigenen Immobilien",
    "sg:phone":"+41 17616244",
    "sg:postcode":"6045",
    "sg:province":"Luzern",
    "wof:name":"Dinz Immobilien Ag",
    "wof:placetype":"venue"
},
  "geometry": {"coordinates":[8.4448890686,47.2796478271],"type":"Point"}
}