{
  "type": "Feature",
  "properties": {
    "addr:full":"St-loup Pompaples Vaud 1318",
    "addr:postcode":"1318",
    "iso:country":"CH",
    "sg:address":"St-loup",
    "sg:city":"Pompaples",
    "sg:classifiers":[
        {
            "category":"Education",
            "subcategory":"Library",
            "type":"Public Place"
        }
    ],
    "sg:phone":"+41 21 866 51 11",
    "sg:postcode":"1318",
    "sg:province":"Vaud",
    "sg:tags":[
        "u",
        "bibliotheken",
        "archive"
    ],
    "wof:name":"R\u00e9seau De Soins Hospitaliers St-loup-orbe-la Vall\u00e9e",
    "wof:placetype":"venue"
},
  "geometry": {"coordinates":[6.50503,46.666279],"type":"Point"}
}