{
  "type": "Feature",
  "properties": {
    "iso:country":"CH",
    "sg:address":"Obere Goldey 42",
    "sg:city":"Unterseen",
    "sg:orig_category":"Ger\u00fcstbau Herstellung von Bergwerks U Baumaschinen",
    "sg:phone":"+41 33 822 91 04",
    "sg:postcode":"3800",
    "sg:province":"Bern",
    "wof:name":"Scheidegger Ger\u00fcstebau Ag.",
    "wof:placetype":"venue"
},
  "geometry": {"coordinates":[7.8523049355,46.6889419556],"type":"Point"}
}