{
  "type": "Feature",
  "properties": {
    "iso:country":"CH",
    "sg:address":"Chemin De L'etang 10",
    "sg:city":"Paudex",
    "sg:orig_category":"Herstellung von Konstruktionsteilen, Fertigbauteilen U Ausbauelementen aus Holz",
    "sg:phone":"+41 21 791 34 86",
    "sg:postcode":"1094",
    "sg:province":"Vaud",
    "wof:name":"Fontannaz Roland",
    "wof:placetype":"venue"
},
  "geometry": {"coordinates":[6.670156002,46.506855011],"type":"Point"}
}