{
  "type": "Feature",
  "properties": {
    "iso:country":"CH",
    "sg:address":"Kantonsstrasse 70 7205 Zizers. Postfach 90",
    "sg:city":"Zizers",
    "sg:orig_category":"Drogerien",
    "sg:phone":"+41 81 322 27 64",
    "sg:postcode":"7205",
    "sg:province":"Graubunden",
    "wof:name":"Mazenauer P.",
    "wof:placetype":"venue"
},
  "geometry": {"coordinates":[9.5651254654,46.9361038208],"type":"Point"}
}