{
  "type": "Feature",
  "properties": {
    "iso:country":"CH",
    "sg:address":"Alte Rheinstrasse 50 9451 Kriessern. Postfach",
    "sg:city":"Kriessern",
    "sg:orig_category":"Unclassifiable Establishments",
    "sg:postcode":"9451",
    "sg:province":"St. Gallen",
    "wof:name":"Vk Industrie Holding Ag",
    "wof:placetype":"venue"
},
  "geometry": {"coordinates":[9.6115846634,47.360458374],"type":"Point"}
}