{
  "type": "Feature",
  "properties": {
    "iso:country":"CH",
    "sg:address":"Champs-montants 16a 2074 Marin-centre Case Postale 179",
    "sg:city":"Marin-centre",
    "sg:classifiers":[
        {
            "category":"Communications",
            "subcategory":"Radio Station",
            "type":"Services"
        }
    ],
    "sg:phone":"+41 32 756 01 10",
    "sg:postcode":"2074",
    "sg:province":"Neuch\u00e2tel",
    "sg:tags":[
        "fernsehanstalten",
        "u"
    ],
    "wof:name":"Rtn-2001 Sa",
    "wof:placetype":"venue"
},
  "geometry": {"coordinates":[6.9998049736,47.0116462708],"type":"Point"}
}