{
  "type": "Feature",
  "properties": {
    "iso:country":"CH",
    "sg:address":"Weiherwald 4 9213 Hauptwil. Postfach",
    "sg:city":"Hauptwil",
    "sg:classifiers":[
        {
            "category":"Professional",
            "subcategory":"Employment Agencies",
            "type":"Services"
        }
    ],
    "sg:phone":"+41 71 422 68 43",
    "sg:postcode":"9213",
    "sg:province":"Thurgau",
    "sg:tags":[
        "personal",
        "u",
        "stellenvermittlung"
    ],
    "wof:name":"Vip Gastro Gmbh",
    "wof:placetype":"venue"
},
  "geometry": {"coordinates":[9.256067276,47.478477478],"type":"Point"}
}