{
  "type": "Feature",
  "properties": {
    "iso:country":"CH",
    "sg:address":"Buecheneggstrasse 5a",
    "sg:city":"Bonstetten",
    "sg:orig_category":"Sportvereine Eissport Bob, Schlitteln and Skeleton",
    "sg:phone":"+41 17000814",
    "sg:postcode":"8906",
    "sg:province":"Z\u00fcrich",
    "wof:name":"Skeleton Club S\u00e4uliamt",
    "wof:placetype":"venue"
},
  "geometry": {"coordinates":[8.4739551544,47.3128433228],"type":"Point"}
}