{
  "type": "Feature",
  "properties": {
    "iso:country":"CH",
    "sg:address":"Alpenstrasse 1 6280 Hochdorf. Postfach",
    "sg:city":"Hochdorf",
    "sg:orig_category":"Herstellung von Metallkonstruktionen",
    "sg:postcode":"6280",
    "sg:province":"Luzern",
    "wof:name":"Staub Time Work Archiv- U. Lagereinrichtungen; Montage",
    "wof:placetype":"venue"
},
  "geometry": {"coordinates":[8.2900075912,47.170135498],"type":"Point"}
}