{
  "type": "Feature",
  "properties": {
    "iso:country":"CH",
    "sg:address":"Grosser Letten 1",
    "sg:city":"Neunkirch",
    "sg:orig_category":"D\u00e4mmung gegen K\u00e4lte, W\u00e4rme, Schall U Ersch\u00fctterung Stukkateurgewerbe, Gipserei U Verputzerei",
    "sg:phone":"+41 52 681 28 60",
    "sg:postcode":"8213",
    "sg:province":"Schaffhausen",
    "wof:name":"Victor Brunner Maler-& Gipsergesch\u00e4ft",
    "wof:placetype":"venue"
},
  "geometry": {"coordinates":[8.5004024506,47.6886825562],"type":"Point"}
}