{
  "type": "Feature",
  "properties": {
    "iso:country":"CH",
    "sg:address":"Schulstrasse 196",
    "sg:city":"Birrhard",
    "sg:orig_category":"Primarschulen",
    "sg:phone":"+41 56 225 21 82",
    "sg:postcode":"5244",
    "sg:province":"Aargau",
    "wof:name":"Primarschule",
    "wof:placetype":"venue"
},
  "geometry": {"coordinates":[8.2473897934,47.4358177185],"type":"Point"}
}