{
  "type": "Feature",
  "properties": {
    "addr:full":"Stegackerstrasse 15 Muttenz Basel-Landschaft 4132",
    "addr:housenumber":"15",
    "addr:postcode":"4132",
    "addr:street":"Stegackerstrasse",
    "iso:country":"CH",
    "sg:address":"Stegackerstrasse 15",
    "sg:city":"Muttenz",
    "sg:orig_category":"Berufliche Weiterbildung, Erwachsenenbildung",
    "sg:phone":"+41 61 461 46 50",
    "sg:postcode":"4132",
    "sg:province":"Basel-Landschaft",
    "wof:name":"Ausbildungszentrum Des Schweiz.autogewerbe-verbandes",
    "wof:placetype":"venue"
},
  "geometry": {"coordinates":[7.634939,47.536812],"type":"Point"}
}