{
  "type": "Feature",
  "properties": {
    "iso:country":"CH",
    "sg:address":"3113 Rubigen. Postfach 209",
    "sg:city":"Rubigen",
    "sg:orig_category":"Sportvereine Ballsport Fussball",
    "sg:phone":"+41 31 372 43 55",
    "sg:postcode":"3113",
    "sg:province":"Bern",
    "wof:name":"Fc Rubigen",
    "wof:placetype":"venue"
},
  "geometry": {"coordinates":[7.5441198349,46.8983802795],"type":"Point"}
}