{
  "type": "Feature",
  "properties": {
    "iso:country":"CH",
    "sg:address":"Bahnhofstrasse 1",
    "sg:city":"Wolfenschiessen",
    "sg:orig_category":"Kreditinstitute ohne Spezialkreditinstitute Unternehmensberatung",
    "sg:phone":"+41 41 629 09 40",
    "sg:postcode":"6386",
    "sg:province":"Nidwalden",
    "wof:name":"General Consulting Ag",
    "wof:placetype":"venue"
},
  "geometry": {"coordinates":[8.3952283859,46.9076080322],"type":"Point"}
}