{
  "type": "Feature",
  "properties": {
    "iso:country":"CH",
    "sg:address":"H\u00f6lzle",
    "sg:city":"Herisau",
    "sg:orig_category":"Textilveredlung",
    "sg:phone":"+41 71 351 20 31",
    "sg:postcode":"9100",
    "sg:province":"Appenzell Ausserrhoden",
    "wof:name":"Signer & Co Ag Herisau Textilveredlung",
    "wof:placetype":"venue"
},
  "geometry": {"coordinates":[9.2639665604,47.3906402588],"type":"Point"}
}