{
  "type": "Feature",
  "properties": {
    "iso:country":"CH",
    "sg:address":"6951 Bogno. Postfach",
    "sg:city":"Bogno",
    "sg:orig_category":"RESTAURANTS: TEA-ROOMS",
    "sg:postcode":"6951",
    "sg:province":"Ticino",
    "wof:name":"Bottinelli, Edgardo Ed Erica.",
    "wof:placetype":"venue"
},
  "geometry": {"coordinates":[9.0641136169,46.0894584656],"type":"Point"}
}