{
  "type": "Feature",
  "properties": {
    "iso:country":"CH",
    "sg:address":"Chaunt Da Luf 93",
    "sg:city":"Zuoz",
    "sg:orig_category":"Dachdeckerei Zimmerei, Dachdeckerei, Bauspenglerei U Abdichtung",
    "sg:phone":"+41 81 854 13 95",
    "sg:postcode":"7524",
    "sg:province":"Graubunden",
    "wof:name":"R\u00fcegg Tolaria Installaziuns Gmbh",
    "wof:placetype":"venue"
},
  "geometry": {"coordinates":[9.957982,46.601677],"type":"Point"}
}