{
  "type": "Feature",
  "properties": {
    "iso:country":"CH",
    "sg:address":"Hauptstrasse 62 5070 Frick. Postfach 77",
    "sg:city":"Frick",
    "sg:orig_category":"Elektroinstallation Herstellung von sonstigen elektrischen Ausr\u00fcstungen",
    "sg:phone":"+41 62 871 13 20",
    "sg:postcode":"5070",
    "sg:province":"Aargau",
    "wof:name":"Venhoda Ag Elektrische Installationen",
    "wof:placetype":"venue"
},
  "geometry": {"coordinates":[8.0212888718,47.5069122314],"type":"Point"}
}