{
  "type": "Feature",
  "properties": {
    "iso:country":"CH",
    "sg:address":"Ausserfeld 2",
    "sg:city":"B\u00fctschwil",
    "sg:orig_category":"S\u00e4gewerke Zimmerei, Dachdeckerei, Bauspenglerei U Abdichtung",
    "sg:phone":"+41 71 983 15 23",
    "sg:postcode":"9606",
    "sg:province":"St. Gallen",
    "wof:name":"Scherrer Gebr\u00fcder Holz Und Fensterbau Ag",
    "wof:placetype":"venue"
},
  "geometry": {"coordinates":[9.0753955841,47.3519554138],"type":"Point"}
}