{
  "type": "Feature",
  "properties": {
    "iso:country":"CH",
    "sg:address":"Route Claie-aux-moines 7",
    "sg:city":"Savigny",
    "sg:orig_category":"G\u00fcterbef\u00f6rderung im Strassenverkehr",
    "sg:phone":"+41 21 781 26 21",
    "sg:postcode":"1073",
    "sg:province":"Vaud",
    "wof:name":"Blanc Transports Sa",
    "wof:placetype":"venue"
},
  "geometry": {"coordinates":[6.7300329208,46.5385017395],"type":"Point"}
}