{
  "type": "Feature",
  "properties": {
    "iso:country":"CH",
    "sg:address":"6579 Piazzogna. Postfach",
    "sg:city":"Piazzogna",
    "sg:orig_category":"Maler U Glasergewerbe",
    "sg:postcode":"6579",
    "sg:province":"Ticino",
    "wof:name":"Barcella Marcello",
    "wof:placetype":"venue"
},
  "geometry": {"coordinates":[8.8294000626,46.1273612976],"type":"Point"}
}