{
  "type": "Feature",
  "properties": {
    "iso:country":"CH",
    "sg:address":"Schulhausstrasse 37",
    "sg:city":"Herrliberg",
    "sg:orig_category":"Bezirks, Sekundar, Realschulen, Oberstufe der Primarschulen",
    "sg:phone":"+41 19158126",
    "sg:postcode":"8704",
    "sg:province":"Z\u00fcrich",
    "wof:name":"Oberstufenschule Breiti",
    "wof:placetype":"venue"
},
  "geometry": {"coordinates":[8.613031,47.288509],"type":"Point"}
}