{
  "type": "Feature",
  "properties": {
    "iso:country":"CH",
    "sg:address":"Huggerwaldstrasse 324",
    "sg:city":"Kleinl\u00fctzel",
    "sg:orig_category":"Detailhandel mit Textilien Instandhaltung U Reparatur von Automobilen",
    "sg:phone":"+41 61 771 05 45",
    "sg:postcode":"4245",
    "sg:province":"Solothurn",
    "wof:name":"Agatha Schott Mercerie",
    "wof:placetype":"venue"
},
  "geometry": {"coordinates":[7.4188461304,47.4251022339],"type":"Point"}
}