{
  "type": "Feature",
  "properties": {
    "iso:country":"CH",
    "sg:address":"Strassburgerallee 31 4055 Basel. Postfach",
    "sg:city":"Basel",
    "sg:classifiers":[
        {
            "category":"Government",
            "subcategory":"Post Office",
            "type":"Public Place"
        }
    ],
    "sg:phone":"+41 61 381 18 54",
    "sg:postcode":"4012",
    "sg:province":"Basel-Stadt",
    "sg:tags":[
        "caf\u00e9s",
        "tea-rooms"
    ],
    "wof:name":"Caf\u00e9 Beau-site",
    "wof:placetype":"venue"
},
  "geometry": {"coordinates":[7.5705609322,47.562789917],"type":"Point"}
}