{
  "type": "Feature",
  "properties": {
    "iso:country":"CH",
    "sg:address":"Freiestrasse 5",
    "sg:city":"Liebefeld",
    "sg:orig_category":"Wirtschafts- and Arbeitgeberverb\u00e4nde",
    "sg:phone":"+41 56 282 56 85",
    "sg:postcode":"3097",
    "sg:province":"Bern",
    "wof:name":"Hans Keller Aarg. S\u00e4gereiverband",
    "wof:placetype":"venue"
},
  "geometry": {"coordinates":[8.2757005692,47.4942817688],"type":"Point"}
}