{
  "type": "Feature",
  "properties": {
    "iso:country":"CH",
    "sg:address":"Sonnenstrasse 14",
    "sg:city":"Widnau",
    "sg:orig_category":"Grosshandel mit Textilien Stickerei",
    "sg:phone":"+41 71 722 23 28",
    "sg:postcode":"9443",
    "sg:province":"St. Gallen",
    "wof:name":"Scherlerei Strasser",
    "wof:placetype":"venue"
},
  "geometry": {"coordinates":[9.6336107254,47.4013595581],"type":"Point"}
}