{
  "type": "Feature",
  "properties": {
    "iso:country":"CH",
    "sg:address":"Eschliweg",
    "sg:city":"Sarnen",
    "sg:orig_category":"Grosshandel mit lebenden Tieren",
    "sg:phone":"+41 41 660 10 49",
    "sg:postcode":"6060",
    "sg:province":"Obwalden",
    "wof:name":"Paul Furrer Viehhandel",
    "wof:placetype":"venue"
},
  "geometry": {"coordinates":[8.2469902039,46.9073104858],"type":"Point"}
}