{
  "type": "Feature",
  "properties": {
    "iso:country":"CH",
    "sg:address":"Oltnerstrasse 17",
    "sg:city":"Sch\u00f6nenwerd",
    "sg:orig_category":"Detailhandel mit Waren verschiedener Art, Hauptrichtung Nahrungsmittel",
    "sg:phone":"+41 62 858 60 10",
    "sg:postcode":"5012",
    "sg:province":"Solothurn",
    "wof:name":"Coop Center",
    "wof:placetype":"venue"
},
  "geometry": {"coordinates":[8.0026445389,47.3706092834],"type":"Point"}
}