{
  "type": "Feature",
  "properties": {
    "iso:country":"CH",
    "sg:address":"Araschgerstrasse 6",
    "sg:city":"Passugg-araschgen",
    "sg:orig_category":"Tanzschulen, Tanzlehrer",
    "sg:phone":"+41 81 253 92 75",
    "sg:postcode":"7062",
    "sg:province":"Graubunden",
    "wof:name":"Nausikaa B\u00fcsch Tanzschule Modern Dance",
    "wof:placetype":"venue"
},
  "geometry": {"coordinates":[9.5470342636,46.8301811218],"type":"Point"}
}