{
  "type": "Feature",
  "properties": {
    "iso:country":"CH",
    "sg:address":"Hauptstrasse 23",
    "sg:city":"Oberstammheim",
    "sg:orig_category":"Allgemeiner Hoch U Tiefbau",
    "sg:phone":"+41 52 745 21 81",
    "sg:postcode":"8477",
    "sg:province":"Z\u00fcrich",
    "wof:name":"Messmer Bauunternehmung Gmbh",
    "wof:placetype":"venue"
},
  "geometry": {"coordinates":[8.797318,47.633457],"type":"Point"}
}