{
  "type": "Feature",
  "properties": {
    "iso:country":"CH",
    "sg:address":"Chemin Des Eterpeys 12",
    "sg:city":"Lausanne",
    "sg:classifiers":[
        {
            "category":"Government",
            "subcategory":"Post Office",
            "type":"Public Place"
        }
    ],
    "sg:phone":"+41 21 652 22 06",
    "sg:postcode":"1010",
    "sg:province":"Vaud",
    "sg:tags":[
        "caf\u00e9s",
        "tea-rooms"
    ],
    "wof:name":"Tea-room La Grangette",
    "wof:placetype":"venue"
},
  "geometry": {"coordinates":[6.6621079445,46.5366668701],"type":"Point"}
}