{
  "type": "Feature",
  "properties": {
    "iso:country":"CH",
    "sg:address":"Stauffacherstrasse 102",
    "sg:city":"Z\u00fcrich",
    "sg:orig_category":"Non-Classified Establishments",
    "sg:phone":"+41 41 671 00 10",
    "sg:postcode":"8004",
    "sg:province":"Z\u00fcrich",
    "wof:name":"Bioniwa Ag",
    "wof:placetype":"venue"
},
  "geometry": {"coordinates":[8.2758054733,46.9366340637],"type":"Point"}
}