{
  "type": "Feature",
  "properties": {
    "iso:country":"CH",
    "sg:address":"Rheinaustrasse 8",
    "sg:city":"Sargans",
    "sg:classifiers":[
        {
            "category":"Food & Beverages",
            "subcategory":"Specialty",
            "type":"Retail Goods"
        }
    ],
    "sg:phone":"+41 17601800",
    "sg:postcode":"7320",
    "sg:province":"St. Gallen",
    "sg:tags":[
        "caterer"
    ],
    "wof:name":"Pizza-kurier Fulmine Gmbh",
    "wof:placetype":"venue"
},
  "geometry": {"coordinates":[8.440435,47.272778],"type":"Point"}
}