{
  "type": "Feature",
  "properties": {
    "iso:country":"CH",
    "sg:address":"Rue De La Blancherie 29",
    "sg:city":"Chavannes-renens",
    "sg:orig_category":"Fussboden, Fliesen U Plattenlegerei, Tapeziererei Verlegen von Fliesen U Platten",
    "sg:phone":"+41 21 635 89 57",
    "sg:postcode":"1022",
    "sg:province":"Vaud",
    "wof:name":"B\u00fcschi Ren\u00e9",
    "wof:placetype":"venue"
},
  "geometry": {"coordinates":[6.5773630142,46.5319633484],"type":"Point"}
}