{
  "type": "Feature",
  "properties": {
    "addr:full":"Avenue Gare-des-eaux-vives 10 Gen\u00e8ve Gen\u00e8ve 1207",
    "addr:housenumber":"10",
    "addr:postcode":"1207",
    "addr:street":"Avenue Gare-Des-Eaux-Vives",
    "iso:country":"CH",
    "sg:address":"Avenue Gare-des-eaux-vives 10",
    "sg:city":"Gen\u00e8ve",
    "sg:orig_category":"Advokaturb\u00fcros",
    "sg:phone":"+41 22 786 62 00",
    "sg:postcode":"1207",
    "sg:province":"Gen\u00e8ve",
    "wof:name":"Rosa Delia Maillart Etude D'avocat",
    "wof:placetype":"venue"
},
  "geometry": {"coordinates":[6.16677,46.200706],"type":"Point"}
}