{
  "type": "Feature",
  "properties": {
    "iso:country":"CH",
    "sg:address":"Chemin De Villard",
    "sg:city":"Blonay",
    "sg:orig_category":"Grosshandel mit Getreide, Saatgut U Futtermitteln",
    "sg:phone":"+41 21 944 19 57",
    "sg:postcode":"1807",
    "sg:province":"Vaud",
    "wof:name":"Grefo Paille, Fourrage, Produits Du Sol, George A. Oggier",
    "wof:placetype":"venue"
},
  "geometry": {"coordinates":[6.8745222092,46.463432312],"type":"Point"}
}