{
  "type": "Feature",
  "properties": {
    "iso:country":"CH",
    "sg:address":"Bremgarterstrasse 12",
    "sg:city":"Widen",
    "sg:orig_category":"Nationale Postdienste",
    "sg:phone":"+41 56 225 11 14",
    "sg:postcode":"8967",
    "sg:province":"Aargau",
    "wof:name":"Die Schweizerische Post",
    "wof:placetype":"venue"
},
  "geometry": {"coordinates":[8.2459583282,47.4607810974],"type":"Point"}
}