{
  "type": "Feature",
  "properties": {
    "addr:full":"Rue Des Murs 8 Coppet Vaud 1296",
    "addr:housenumber":"8",
    "addr:postcode":"1296",
    "addr:street":"Rue Des Murs",
    "iso:country":"CH",
    "sg:address":"Rue Des Murs 8",
    "sg:city":"Coppet",
    "sg:orig_category":"Detailhandel mit Blumen U Pflanzen",
    "sg:phone":"+41 22 776 81 55",
    "sg:postcode":"1296",
    "sg:province":"Vaud",
    "wof:name":"Floral Fantasia Rachel Hauser Magasin De Fleurs",
    "wof:placetype":"venue"
},
  "geometry": {"coordinates":[6.192025,46.316284],"type":"Point"}
}