{
  "type": "Feature",
  "properties": {
    "iso:country":"CH",
    "sg:address":"P\u00e9cheurs Rue Des 8 1400 Yverdon-les-bains. Postfach",
    "sg:city":"Cheseaux-nor\u00e9az",
    "sg:orig_category":"RESTAURANTS: TEA-ROOMS",
    "sg:postcode":"1400",
    "sg:province":"Vaud",
    "wof:name":"Restaurant St-roch",
    "wof:placetype":"venue"
},
  "geometry": {"coordinates":[6.6447529793,46.7814865112],"type":"Point"}
}