{
  "type": "Feature",
  "properties": {
    "iso:country":"CH",
    "sg:address":"Fistez",
    "sg:city":"Castrisch",
    "sg:orig_category":"Fachdetailhandel in Verkaufsr\u00e4umen",
    "sg:phone":"+41 81 925 41 31",
    "sg:postcode":"7126",
    "sg:province":"Graubunden",
    "wof:name":"Fontan Art, Patricia Fontana",
    "wof:placetype":"venue"
},
  "geometry": {"coordinates":[9.2291049957,46.7754516602],"type":"Point"}
}