{
  "type": "Feature",
  "properties": {
    "iso:country":"CH",
    "sg:address":"Werkstrasse 4",
    "sg:city":"Jona",
    "sg:orig_category":"Reiseb\u00fcros U Reiseveranstalter",
    "sg:phone":"+41 55 212 66 08",
    "sg:postcode":"8645",
    "sg:province":"St. Gallen",
    "wof:name":"Power Of Spirit Ag",
    "wof:placetype":"venue"
},
  "geometry": {"coordinates":[8.8359069824,47.2321205139],"type":"Point"}
}