{
  "type": "Feature",
  "properties": {
    "iso:country":"CH",
    "sg:address":"La Voie-creuse 7b",
    "sg:city":"Gen\u00e8ve",
    "sg:orig_category":"Kosmetikinstitute",
    "sg:phone":"+41 71 855 76 70",
    "sg:postcode":"1202",
    "sg:province":"Gen\u00e8ve",
    "wof:name":"Monica H\u00fcttenmoser Salon Beaut\u00e9 Monique",
    "wof:placetype":"venue"
},
  "geometry": {"coordinates":[9.5313978195,47.4803886414],"type":"Point"}
}