{
  "type": "Feature",
  "properties": {
    "addr:full":"Birkenweg 44 St-ours Fribourg 1717",
    "addr:housenumber":"44",
    "addr:postcode":"1717",
    "addr:street":"Birkenweg;Fribourg",
    "iso:country":"CH",
    "sg:address":"Birkenweg 44",
    "sg:city":"St-ours",
    "sg:orig_category":"Detailhandel mit Bekleidung Detailhandel mit Textilien",
    "sg:phone":"+41 26 494 22 77",
    "sg:postcode":"1717",
    "sg:province":"Fribourg",
    "wof:name":"Aebischer Textil",
    "wof:placetype":"venue"
},
  "geometry": {"coordinates":[7.219515,46.789238],"type":"Point"}
}