{
  "type": "Feature",
  "properties": {
    "iso:country":"CH",
    "sg:address":"Neum\u00fcnsterallee 6",
    "sg:city":"Z\u00fcrich",
    "sg:orig_category":"Unclassifiable Establishments",
    "sg:phone":"+41 56 402 07 28",
    "sg:postcode":"8008",
    "sg:province":"Z\u00fcrich",
    "wof:name":"Ecofin Management Ag",
    "wof:placetype":"venue"
},
  "geometry": {"coordinates":[8.5563879013,47.3625831604],"type":"Point"}
}