{
  "type": "Feature",
  "properties": {
    "iso:country":"CH",
    "sg:address":"Pace Via Della 1",
    "sg:city":"Locarno",
    "sg:orig_category":"Detailhandel mit Bekleidung",
    "sg:postcode":"6600",
    "sg:province":"Ticino",
    "wof:name":"Portmann Marianne",
    "wof:placetype":"venue"
},
  "geometry": {"coordinates":[6.857987,46.965614],"type":"Point"}
}