{
  "type": "Feature",
  "properties": {
    "iso:country":"CH",
    "sg:address":"Mont-goulin Avenue De 21",
    "sg:city":"Prilly",
    "sg:orig_category":"Fachdetailhandel mit pharmazeutischen Produkten",
    "sg:phone":"+41 21 647 77 33",
    "sg:postcode":"1008",
    "sg:province":"Vaud",
    "wof:name":"Pharmacie De La Vallombreuse, Troxler M.-c. & Grivat S.",
    "wof:placetype":"venue"
},
  "geometry": {"coordinates":[6.6105289459,46.5378913879],"type":"Point"}
}