{
  "type": "Feature",
  "properties": {
    "iso:country":"CH",
    "sg:address":"Boulevard De P\u00e9rolles 24",
    "sg:city":"Fribourg",
    "sg:orig_category":"Detailhandel mit Geschenkartikeln U Souvenirs Herstellung von sonstigen Metallwaren",
    "sg:phone":"+41 31 371 58 24",
    "sg:postcode":"1700",
    "sg:province":"Fribourg",
    "wof:name":"Marcel Kaderli",
    "wof:placetype":"venue"
},
  "geometry": {"coordinates":[7.4317917824,46.9434738159],"type":"Point"}
}