{
  "type": "Feature",
  "properties": {
    "iso:country":"CH",
    "sg:address":"7127",
    "sg:city":"Sevgein",
    "sg:orig_category":"Sportvereine Sch\u00fctzen",
    "sg:postcode":"7127",
    "sg:province":"Graubunden",
    "wof:name":"Societad De Tir",
    "wof:placetype":"venue"
},
  "geometry": {"coordinates":[9.2274198532,46.7528915405],"type":"Point"}
}