{
  "type": "Feature",
  "properties": {
    "iso:country":"CH",
    "sg:address":"B\u00f6smattweg 9",
    "sg:city":"Bellikon",
    "sg:orig_category":"Vereine Harmonika and Akkordeon",
    "sg:phone":"+41 56 470 14 61",
    "sg:postcode":"5454",
    "sg:province":"Aargau",
    "wof:name":"Akkordeon-& Gitarren-orchester",
    "wof:placetype":"venue"
},
  "geometry": {"coordinates":[8.3463506699,47.3918228149],"type":"Point"}
}