{
  "type": "Feature",
  "properties": {
    "iso:country":"CH",
    "sg:address":"Alte-bernstrasse 56",
    "sg:city":"Solothurn",
    "sg:orig_category":"Interessenvertretungen",
    "sg:postcode":"4500",
    "sg:province":"Solothurn",
    "wof:name":"Borrer-stiftung Walter",
    "wof:placetype":"venue"
},
  "geometry": {"coordinates":[7.5347309113,47.1992073059],"type":"Point"}
}