{
  "type": "Feature",
  "properties": {
    "iso:country":"CH",
    "sg:address":"Hauptstrasse 84",
    "sg:city":"Murgenthal",
    "sg:orig_category":"Nationale Postdienste",
    "sg:phone":"+41 62 926 10 80",
    "sg:postcode":"4853",
    "sg:province":"Aargau",
    "wof:name":"Die Schweizerische Post",
    "wof:placetype":"venue"
},
  "geometry": {"coordinates":[7.8311061859,47.2654724121],"type":"Point"}
}