{
  "type": "Feature",
  "properties": {
    "iso:country":"CH",
    "sg:address":"Monbijoustrasse 71 3007 Bern. Postfach",
    "sg:city":"Bern",
    "sg:orig_category":"Nahrungsmittel-Industrie: Rohstoffe",
    "sg:phone":"+41 55 442 35 69",
    "sg:postcode":"3005",
    "sg:province":"Bern",
    "wof:name":"Deric Dusan",
    "wof:placetype":"venue"
},
  "geometry": {"coordinates":[8.8517942429,47.1921844482],"type":"Point"}
}