{
  "type": "Feature",
  "properties": {
    "addr:full":"8840 Einsiedeln. Postfach 161 Einsiedeln Schwyz 8840",
    "addr:housenumber":"161",
    "addr:postcode":"8840;8840",
    "addr:street":"Postfach;Schwyz",
    "iso:country":"CH",
    "sg:address":"8840 Einsiedeln. Postfach 161",
    "sg:city":"Einsiedeln",
    "sg:orig_category":"Bau\u00e4mter",
    "sg:phone":"+41 41 854 01 81",
    "sg:postcode":"8840",
    "sg:province":"Schwyz",
    "wof:name":"Bauamt Des Bezirks K\u00fcssnacht Am Rigi",
    "wof:placetype":"venue"
},
  "geometry": {"coordinates":[8.439315,47.079952],"type":"Point"}
}