{
  "type": "Feature",
  "properties": {
    "iso:country":"CH",
    "sg:address":"Via San Gottardo 58 A",
    "sg:city":"Bellinzona",
    "sg:orig_category":"Architektur U Ingenieurb\u00fcros",
    "sg:phone":"+41 91 825 65 81",
    "sg:postcode":"6500",
    "sg:province":"Ticino",
    "wof:name":"Mario Sartori Studio Tecnico",
    "wof:placetype":"venue"
},
  "geometry": {"coordinates":[9.033408,46.201649],"type":"Point"}
}