{
  "type": "Feature",
  "properties": {
    "iso:country":"CH",
    "sg:address":"9125",
    "sg:city":"Brunnadern",
    "sg:orig_category":"Vereine Musik/Blasmusik",
    "sg:phone":"+41 71 385 63 65",
    "sg:postcode":"9125",
    "sg:province":"St. Gallen",
    "wof:name":"Musikgesellschaft",
    "wof:placetype":"venue"
},
  "geometry": {"coordinates":[9.2762403488,47.4391708374],"type":"Point"}
}