{
  "type": "Feature",
  "properties": {
    "iso:country":"CH",
    "sg:address":"Weststrasse 169",
    "sg:city":"Z\u00fcrich",
    "sg:orig_category":"Wirtschaftspr\u00fcfung, Steuerberatung U Treuhand",
    "sg:phone":"+41 14510585",
    "sg:postcode":"8003",
    "sg:province":"Z\u00fcrich",
    "wof:name":"Roger Laubacher, Rolag Treuhand Und Buchhaltungsservice",
    "wof:placetype":"venue"
},
  "geometry": {"coordinates":[8.5179805756,47.3739089966],"type":"Point"}
}