{
  "type": "Feature",
  "properties": {
    "iso:country":"CH",
    "sg:address":"Via Baselga 2",
    "sg:city":"Rh\u00e4z\u00fcns",
    "sg:orig_category":"Kantonalbanken",
    "sg:phone":"+41 81 837 02 70",
    "sg:postcode":"7403",
    "sg:province":"Graubunden",
    "wof:name":"Graub\u00fcndner Kantonalbank",
    "wof:placetype":"venue"
},
  "geometry": {"coordinates":[9.8357152939,46.488368988],"type":"Point"}
}