{
  "type": "Feature",
  "properties": {
    "iso:country":"CH",
    "sg:address":"Thurhof",
    "sg:city":"Adlikon",
    "sg:orig_category":"Getreide Grosshandel",
    "sg:phone":"+41 17155685",
    "sg:postcode":"8452",
    "sg:province":"Z\u00fcrich",
    "wof:name":"Erwin Liebmann Getreide-agentur",
    "wof:placetype":"venue"
},
  "geometry": {"coordinates":[8.5406847,47.3268852234],"type":"Point"}
}