{
  "type": "Feature",
  "properties": {
    "iso:country":"CH",
    "sg:address":"Schwarzenburgstr. 586",
    "sg:city":"Gasel",
    "sg:classifiers":[
        {
            "category":"Shopping",
            "subcategory":"Hobbies, Toys, & Games",
            "type":"Retail Goods"
        }
    ],
    "sg:phone":"+41 31 848 10 30",
    "sg:postcode":"3144",
    "sg:province":"Bern",
    "sg:tags":[
        "product",
        "miscellaneous",
        "entertainment"
    ],
    "wof:name":"Rex Metall Ag Bern",
    "wof:placetype":"venue"
},
  "geometry": {"coordinates":[7.4016718864,46.8998985291],"type":"Point"}
}