{
  "type": "Feature",
  "properties": {
    "iso:country":"CH",
    "sg:address":"Via Pasture Genovesi 35",
    "sg:city":"Comano",
    "sg:orig_category":"Naturheil\u00e4rzte and Heilpraktiker Shiatsu-Therapie",
    "sg:postcode":"6949",
    "sg:province":"Ticino",
    "wof:name":"Scuola Quo Shiatsu E Medicina Naturale",
    "wof:placetype":"venue"
},
  "geometry": {"coordinates":[8.9543199539,46.0432014465],"type":"Point"}
}