{
  "type": "Feature",
  "properties": {
    "iso:country":"CH",
    "sg:address":"Via Peri 5",
    "sg:city":"Lugano",
    "sg:orig_category":"Unclassifiable Establishments",
    "sg:postcode":"6900",
    "sg:province":"Ticino",
    "wof:name":"Trustland Sa.",
    "wof:placetype":"venue"
},
  "geometry": {"coordinates":[8.950594902,46.0053253174],"type":"Point"}
}