{
  "type": "Feature",
  "properties": {
    "iso:country":"CH",
    "sg:address":"Habsburgerstrasse 12",
    "sg:city":"Luzern",
    "sg:orig_category":"Sonstiger Fachdetailhandel mit Nahrungsmitteln, Getr\u00e4nken U Tabak in Verkaufsr\u00e4umen",
    "sg:postcode":"6003",
    "sg:province":"Luzern",
    "wof:name":"Schafer & Co, K\u00e4se Und Milchprodukte",
    "wof:placetype":"venue"
},
  "geometry": {"coordinates":[7.140021801,46.8987121582],"type":"Point"}
}