{
  "type": "Feature",
  "properties": {
    "iso:country":"CH",
    "sg:address":"Via S. Margherita 3a 6855 Stabio Casella Postale",
    "sg:city":"Stabio",
    "sg:orig_category":"Herstellung von Bekleidung U Pelzwaren Textilgewerbe",
    "sg:phone":"+41 91 794 15 75",
    "sg:postcode":"6855",
    "sg:province":"Ticino",
    "wof:name":"Rubella Sa",
    "wof:placetype":"venue"
},
  "geometry": {"coordinates":[8.9393825531,45.8523521423],"type":"Point"}
}