{
  "type": "Feature",
  "properties": {
    "iso:country":"CH",
    "sg:address":"Le Point Du Jour",
    "sg:city":"Essertines-rolle",
    "sg:orig_category":"Tierheime",
    "sg:phone":"+41 21 828 38 14",
    "sg:postcode":"1186",
    "sg:province":"Vaud",
    "wof:name":"Alain Zwygart Pension Pour Animaux",
    "wof:placetype":"venue"
},
  "geometry": {"coordinates":[6.3187551498,46.4923286438],"type":"Point"}
}