{
  "type": "Feature",
  "properties": {
    "iso:country":"CH",
    "sg:address":"Centre Commercial",
    "sg:city":"Haute-nendaz",
    "sg:orig_category":"RESTAURANTS: TEA-ROOMS",
    "sg:phone":"+41 27 288 42 19",
    "sg:postcode":"1997",
    "sg:province":"Valais",
    "wof:name":"Fournier Marie-pierre",
    "wof:placetype":"venue"
},
  "geometry": {"coordinates":[7.2981119156,46.1841583252],"type":"Point"}
}