{
  "type": "Feature",
  "properties": {
    "iso:country":"CH",
    "sg:address":"Lohstampfestrasse 11 8274 T\u00e4gerwilen. Postfach",
    "sg:city":"T\u00e4gerwilen",
    "sg:orig_category":"Herstellung von k\u00e4lte U lufttechnischen Erzeugnissen f\u00fcr gewerbliche Zwecke Installation von Heizung",
    "sg:phone":"+41 71 669 28 82",
    "sg:postcode":"8274",
    "sg:province":"Thurgau",
    "wof:name":"Innotherm Ag",
    "wof:placetype":"venue"
},
  "geometry": {"coordinates":[9.1292333603,47.659740448],"type":"Point"}
}