{
  "type": "Feature",
  "properties": {
    "iso:country":"CH",
    "sg:address":"Benkenstrasse 82",
    "sg:city":"Basel",
    "sg:orig_category":"Fotografische Ateliers",
    "sg:phone":"+41 61 281 38 60",
    "sg:postcode":"4054",
    "sg:province":"Basel-Stadt",
    "wof:name":"Peter Schnetz Fotograf",
    "wof:placetype":"venue"
},
  "geometry": {"coordinates":[7.5758662224,47.5471763611],"type":"Point"}
}