{
  "type": "Feature",
  "properties": {
    "iso:country":"CH",
    "sg:address":"6482",
    "sg:city":"Gurtnellen",
    "sg:classifiers":[
        {
            "category":"Travel",
            "subcategory":"Hotels & Motels",
            "type":"Entertainment"
        }
    ],
    "sg:postcode":"6482",
    "sg:province":"Uri",
    "sg:tags":[
        "hotels",
        "mit",
        "restaurant"
    ],
    "wof:name":"Dittli Astrid Gathaus Bergheim",
    "wof:placetype":"venue"
},
  "geometry": {"coordinates":[8.6214704514,46.7278785706],"type":"Point"}
}