{
  "type": "Feature",
  "properties": {
    "iso:country":"CH",
    "sg:address":"Linth-escherstrasse 5",
    "sg:city":"Bilten",
    "sg:orig_category":"Herstellung von Reiseartikeln, Leder U Sattlerwaren Verlegen von Fussboden",
    "sg:phone":"+41 17640545",
    "sg:postcode":"8865",
    "sg:province":"Glarus",
    "wof:name":"Andreas Kolbe Polsterm\u00f6bel Bodenbel\u00e4ge",
    "wof:placetype":"venue"
},
  "geometry": {"coordinates":[8.5371580124,47.2401351929],"type":"Point"}
}