{
  "type": "Feature",
  "properties": {
    "iso:country":"CH",
    "sg:address":"Schulhaus",
    "sg:city":"Buus",
    "sg:orig_category":"Primarschulen",
    "sg:phone":"+41 61 971 41 69",
    "sg:postcode":"4463",
    "sg:province":"Basel-Landschaft",
    "wof:name":"Primarschule",
    "wof:placetype":"venue"
},
  "geometry": {"coordinates":[7.8598370552,47.5081520081],"type":"Point"}
}