{
  "type": "Feature",
  "properties": {
    "addr:full":"Via Lisano 4 Massagno Ticino 6900",
    "addr:housenumber":"4",
    "addr:postcode":"6900",
    "addr:street":"Via Lisano",
    "iso:country":"CH",
    "sg:address":"Via Lisano 4",
    "sg:city":"Massagno",
    "sg:orig_category":"Architektur U Ingenieurb\u00fcros Architekturb\u00fcros",
    "sg:phone":"+41 91 967 37 30",
    "sg:postcode":"6900",
    "sg:province":"Ticino",
    "wof:name":"Luca Gallmann Studio D'architettura",
    "wof:placetype":"venue"
},
  "geometry": {"coordinates":[8.942465,46.009327],"type":"Point"}
}