{
  "type": "Feature",
  "properties": {
    "iso:country":"CH",
    "sg:address":"D\u00e9lices Rue Des 12bis 1203 Gen\u00e8ve. Postfach",
    "sg:city":"Gen\u00e8ve",
    "sg:orig_category":"Wirtschaftspr\u00fcfung, Steuerberatung U Treuhand",
    "sg:postcode":"1203",
    "sg:province":"Gen\u00e8ve",
    "wof:name":"Charles Winzenried",
    "wof:placetype":"venue"
},
  "geometry": {"coordinates":[6.943915844,46.5225067139],"type":"Point"}
}