{
  "type": "Feature",
  "properties": {
    "iso:country":"CH",
    "sg:address":"8593",
    "sg:city":"Kesswil",
    "sg:orig_category":"Schulpflegen",
    "sg:postcode":"8593",
    "sg:province":"Thurgau",
    "wof:name":"Primarschulkommission Der Gemeinde Kesswil",
    "wof:placetype":"venue"
},
  "geometry": {"coordinates":[9.3160495758,47.5903892517],"type":"Point"}
}