{
  "type": "Feature",
  "properties": {
    "iso:country":"CH",
    "sg:address":"Sommeristrasse 28",
    "sg:city":"Amriswil",
    "sg:orig_category":"Zimmerei, Dachdeckerei, Bauspenglerei U Abdichtung",
    "sg:phone":"+41 71 414 01 51",
    "sg:postcode":"8580",
    "sg:province":"Thurgau",
    "wof:name":"Krattiger Holzbau Ag",
    "wof:placetype":"venue"
},
  "geometry": {"coordinates":[9.2939977646,47.5557632446],"type":"Point"}
}