{
  "type": "Feature",
  "properties": {
    "iso:country":"CH",
    "sg:address":"Etzelstrasse 6 8634 Hombrechtikon. Postfach",
    "sg:city":"Hombrechtikon",
    "sg:orig_category":"Pensionskassen",
    "sg:postcode":"8634",
    "sg:province":"Z\u00fcrich",
    "wof:name":"Gemeinschaftsstiftung F\u00fcr Soziale Vorsorge",
    "wof:placetype":"venue"
},
  "geometry": {"coordinates":[8.778752327,47.2528915405],"type":"Point"}
}