{
  "type": "Feature",
  "properties": {
    "iso:country":"CH",
    "sg:address":"Dufourstrasse 22",
    "sg:city":"Z\u00fcrich",
    "sg:orig_category":"Sonstiger Grosshandel",
    "sg:postcode":"8008",
    "sg:province":"Z\u00fcrich",
    "wof:name":"D'agostini Gmbh",
    "wof:placetype":"venue"
},
  "geometry": {"coordinates":[8.7937135696,47.2006072998],"type":"Point"}
}