{
  "type": "Feature",
  "properties": {
    "iso:country":"CH",
    "sg:address":"K\u00e4ppelimattweg 16",
    "sg:city":"Brislach",
    "sg:orig_category":"Sanit\u00e4r, Heizungs U L\u00fcftungsinstallation Sanit\u00e4rinstallation",
    "sg:phone":"+41 81 868 53 43",
    "sg:postcode":"4225",
    "sg:province":"Basel-Landschaft",
    "wof:name":"Heis H.p.",
    "wof:placetype":"venue"
},
  "geometry": {"coordinates":[10.3613004684,46.9444885254],"type":"Point"}
}