{
  "type": "Feature",
  "properties": {
    "iso:country":"CH",
    "sg:address":"Schwenden",
    "sg:city":"Diemtigen",
    "sg:orig_category":"G\u00fcterbef\u00f6rderung im Strassenverkehr",
    "sg:postcode":"3754",
    "sg:province":"Bern",
    "wof:name":"A. Spring",
    "wof:placetype":"venue"
},
  "geometry": {"coordinates":[7.4914069176,46.5693664551],"type":"Point"}
}