{
  "type": "Feature",
  "properties": {
    "addr:full":"Largo Zorzi 6600 Locarno. Postfach Locarno Ticino 6601",
    "addr:postcode":"6600 locarno. postfach;6601",
    "addr:street":"Largo Zorzi",
    "iso:country":"CH",
    "sg:address":"Largo Zorzi 6600 Locarno. Postfach",
    "sg:city":"Locarno",
    "sg:orig_category":"Bijouterien Reparatur von Uhren U Schmuck",
    "sg:phone":"+41 91 751 05 92",
    "sg:postcode":"6601",
    "sg:province":"Ticino",
    "wof:name":"Christ Uhren & Schmuck Ag Warenhaus Globus",
    "wof:placetype":"venue"
},
  "geometry": {"coordinates":[8.798319,46.169823],"type":"Point"}
}