{
  "type": "Feature",
  "properties": {
    "iso:country":"CH",
    "sg:address":"Grosszelgstrasse 24",
    "sg:city":"W\u00fcrenlos",
    "sg:orig_category":"Sonstige mit der Informatik verbundene T\u00e4tigkeiten",
    "sg:phone":"+41 56 424 30 70",
    "sg:postcode":"5436",
    "sg:province":"Aargau",
    "wof:name":"M\u00fchlethaler Informatik Gmbh",
    "wof:placetype":"venue"
},
  "geometry": {"coordinates":[8.3554391861,47.4445648193],"type":"Point"}
}