{
  "type": "Feature",
  "properties": {
    "iso:country":"CH",
    "sg:address":"L\u00f6wenplatz 5",
    "sg:city":"Zwingen",
    "sg:orig_category":"Erwachsenenbildung U Unterricht",
    "sg:postcode":"4222",
    "sg:province":"Basel-Landschaft",
    "wof:name":"Chavanne Michel, Immobilien Bewirtschaftungs Ag",
    "wof:placetype":"venue"
},
  "geometry": {"coordinates":[7.5301060677,47.4382858276],"type":"Point"}
}