{
  "type": "Feature",
  "properties": {
    "iso:country":"CH",
    "sg:address":"Unter Dem Birg 3715 Adelboden. Postfach 147",
    "sg:city":"Adelboden",
    "sg:orig_category":"RESTAURANTS: TEA-ROOMS",
    "sg:phone":"+41 33 673 16 26",
    "sg:postcode":"3715",
    "sg:province":"Bern",
    "wof:name":"Br\u00fcgger-feller A. & M. Restaurant Steinbock.",
    "wof:placetype":"venue"
},
  "geometry": {"coordinates":[7.5641260147,46.4597053528],"type":"Point"}
}