{
  "type": "Feature",
  "properties": {
    "iso:country":"CH",
    "sg:address":"Rue Saint-paul 7",
    "sg:city":"Fribourg",
    "sg:orig_category":"Psychotherapie",
    "sg:phone":"+41 26 323 24 42",
    "sg:postcode":"1700",
    "sg:province":"Fribourg",
    "wof:name":"Elizabeth Dreyer Psychoth\u00e9rapie",
    "wof:placetype":"venue"
},
  "geometry": {"coordinates":[7.1516690254,46.7988395691],"type":"Point"}
}