{
  "type": "Feature",
  "properties": {
    "iso:country":"CH",
    "sg:address":"Chemin Mo\u00efse-duboule 29 1200 Gen\u00e8ve. Postfach",
    "sg:city":"Gen\u00e8ve",
    "sg:orig_category":"Finanzierungsinstitutionen",
    "sg:phone":"+41 22 798 91 16",
    "sg:postcode":"1209",
    "sg:province":"Gen\u00e8ve",
    "wof:name":"Wicki Invest",
    "wof:placetype":"venue"
},
  "geometry": {"coordinates":[6.1256761551,46.2247695923],"type":"Point"}
}