{
  "type": "Feature",
  "properties": {
    "iso:country":"CH",
    "sg:address":"Saurerareal Werk 2 9320 Arbon. Postfach 43",
    "sg:city":"Arbon",
    "sg:orig_category":"Sonstiger spezialisierter Hoch U Tiefbau",
    "sg:phone":"+41 71 455 22 50",
    "sg:postcode":"9320",
    "sg:province":"Thurgau",
    "wof:name":"Carlo Bianchi Ger\u00fcstbau Ag",
    "wof:placetype":"venue"
},
  "geometry": {"coordinates":[9.4349451065,47.5160446167],"type":"Point"}
}