{
  "type": "Feature",
  "properties": {
    "iso:country":"CH",
    "sg:address":"Via Ghiringhelli 47",
    "sg:city":"Bellinzona",
    "sg:orig_category":"Ger\u00fcstbau Sonstiger spezialisierter Hoch U Tiefbau",
    "sg:phone":"+41 91 826 11 66",
    "sg:postcode":"6500",
    "sg:province":"Ticino",
    "wof:name":"Pamo Ponteggi Sa",
    "wof:placetype":"venue"
},
  "geometry": {"coordinates":[9.0148458481,46.1847305298],"type":"Point"}
}