{
  "type": "Feature",
  "properties": {
    "iso:country":"CH",
    "sg:address":"Hauptstrasse 76 3473 Alchenstorf. Postfach",
    "sg:city":"Alchenstorf",
    "sg:orig_category":"Sanit\u00e4r, Heizungs U L\u00fcftungsinstallation",
    "sg:postcode":"3473",
    "sg:province":"Bern",
    "wof:name":"Bill Th. Gmbh",
    "wof:placetype":"venue"
},
  "geometry": {"coordinates":[7.6393771172,47.1248703003],"type":"Point"}
}