{
  "type": "Feature",
  "properties": {
    "iso:country":"CH",
    "sg:address":"Concordia Vicolo 1",
    "sg:city":"Breganzona",
    "sg:orig_category":"Technische, physikalische U chemische Untersuchung",
    "sg:postcode":"6932",
    "sg:province":"Ticino",
    "wof:name":"Planatur Ag",
    "wof:placetype":"venue"
},
  "geometry": {"coordinates":[7.8325619698,47.2352867126],"type":"Point"}
}