{
  "type": "Feature",
  "properties": {
    "iso:country":"CH",
    "sg:address":"Haus Am Platz",
    "sg:city":"Langwies",
    "sg:orig_category":"Verkehrs- and Tourismusb\u00fcros",
    "sg:phone":"+41 81 374 22 55",
    "sg:postcode":"7057",
    "sg:province":"Graubunden",
    "wof:name":"Verkehrsverein",
    "wof:placetype":"venue"
},
  "geometry": {"coordinates":[9.7126750946,46.8205833435],"type":"Point"}
}