{
  "type": "Feature",
  "properties": {
    "iso:country":"CH",
    "sg:address":"Seidenweg 26 3012 Bern. Postfach",
    "sg:city":"Bern",
    "sg:orig_category":"Grosshandel mit lebenden Tieren",
    "sg:phone":"+41 55 246 29 31",
    "sg:postcode":"3005",
    "sg:province":"Bern",
    "wof:name":"Luminati Albin",
    "wof:placetype":"venue"
},
  "geometry": {"coordinates":[8.9413003922,47.2884101868],"type":"Point"}
}