{
  "type": "Feature",
  "properties": {
    "iso:country":"CH",
    "sg:address":"S\u00e4genboden",
    "sg:city":"Wildhaus",
    "sg:orig_category":"S\u00e4gewerke",
    "sg:phone":"+41 71 999 12 47",
    "sg:postcode":"9658",
    "sg:province":"St. Gallen",
    "wof:name":"Karl Forrer S\u00e4gerei",
    "wof:placetype":"venue"
},
  "geometry": {"coordinates":[9.369972229,47.198890686],"type":"Point"}
}