{
  "type": "Feature",
  "properties": {
    "iso:country":"CH",
    "sg:address":"Ennetriederweg 11",
    "sg:city":"Sarnen",
    "sg:orig_category":"Kauf U Verkauf von Immobilien auf eigene Rechnung",
    "sg:phone":"+41 26 496 00 23",
    "sg:postcode":"6060",
    "sg:province":"Obwalden",
    "wof:name":"Vonlanthen J., Die Erben",
    "wof:placetype":"venue"
},
  "geometry": {"coordinates":[7.2271509171,46.8408927917],"type":"Point"}
}