{
  "type": "Feature",
  "properties": {
    "iso:country":"CH",
    "sg:address":"Schulstrasse 15",
    "sg:city":"Zufikon",
    "sg:orig_category":"Forst\u00e4mter",
    "sg:phone":"+41 56 631 66 24",
    "sg:postcode":"5621",
    "sg:province":"Aargau",
    "wof:name":"Forstamt Zufikon/oberlunkhofen",
    "wof:placetype":"venue"
},
  "geometry": {"coordinates":[8.3578567505,47.3483085632],"type":"Point"}
}