{
  "type": "Feature",
  "properties": {
    "iso:country":"CH",
    "sg:address":"Aarauerstrasse 55",
    "sg:city":"Olten",
    "sg:orig_category":"Arztpraxen",
    "sg:phone":"+41 62 296 50 55",
    "sg:postcode":"4600",
    "sg:province":"Solothurn",
    "wof:name":"Dr.med. Jacqueline Binswanger Spezial\u00e4rztin",
    "wof:placetype":"venue"
},
  "geometry": {"coordinates":[7.910717,47.34864],"type":"Point"}
}