{
  "type": "Feature",
  "properties": {
    "iso:country":"CH",
    "sg:address":"Amlehnstrasse 54",
    "sg:city":"Kriens",
    "sg:orig_category":"Parf\u00fcmerien U sonstiger Detailhandel mit kosmetischen Artikeln U K\u00f6rperpflegemitteln",
    "sg:phone":"+41 41 310 05 41",
    "sg:postcode":"6010",
    "sg:province":"Luzern",
    "wof:name":"Daniel Moll Coiffure Damen & Herren",
    "wof:placetype":"venue"
},
  "geometry": {"coordinates":[8.2914533615,47.03698349],"type":"Point"}
}