{
  "type": "Feature",
  "properties": {
    "iso:country":"CH",
    "sg:address":"6430",
    "sg:city":"Schwyz",
    "sg:orig_category":"Primarschulen",
    "sg:phone":"+41 41 811 30 43",
    "sg:postcode":"6430",
    "sg:province":"Schwyz",
    "wof:name":"Primarschule Herrengasse",
    "wof:placetype":"venue"
},
  "geometry": {"coordinates":[8.6672801971,47.0384216309],"type":"Point"}
}