{
  "type": "Feature",
  "properties": {
    "iso:country":"CH",
    "sg:address":"Br\u00fcel 4",
    "sg:city":"Balzers",
    "sg:orig_category":"Detailhandel mit Spielwaren",
    "sg:phone":"+41 61 272 86 49",
    "sg:postcode":"9496",
    "wof:name":"Marcel Unger Fachgesch\u00e4ft F\u00fcr Modellbau",
    "wof:placetype":"venue"
},
  "geometry": {"coordinates":[7.7121338844,47.5365943909],"type":"Point"}
}