{
  "type": "Feature",
  "properties": {
    "iso:country":"CH",
    "sg:address":"Fluhmattstrasse 40",
    "sg:city":"Luzern",
    "sg:orig_category":"Architektur U Ingenieurb\u00fcros",
    "sg:phone":"+41 55 225 35 00",
    "sg:postcode":"6004",
    "sg:province":"Luzern",
    "wof:name":"Ammeraal Beltech Ag Antriebs-& F\u00f6rdertechnik",
    "wof:placetype":"venue"
},
  "geometry": {"coordinates":[8.869781,47.22776],"type":"Point"}
}