{
  "type": "Feature",
  "properties": {
    "addr:full":"Bollenfeldstrasse 1 Oberg\u00f6sgen Solothurn 4653",
    "addr:housenumber":"1",
    "addr:postcode":"4653",
    "addr:street":"Bollenfeldstrasse",
    "iso:country":"CH",
    "sg:address":"Bollenfeldstrasse 1",
    "sg:city":"Oberg\u00f6sgen",
    "sg:orig_category":"Architektur U Ingenieurb\u00fcros Architekturb\u00fcros",
    "sg:phone":"+41 62 295 25 55",
    "sg:postcode":"4653",
    "sg:province":"Solothurn",
    "wof:name":"Schmidig Ungerer Architektur & Generaluntern.",
    "wof:placetype":"venue"
},
  "geometry": {"coordinates":[7.954048,47.364857],"type":"Point"}
}