{
  "type": "Feature",
  "properties": {
    "iso:country":"CH",
    "sg:address":"6330",
    "sg:city":"Cham",
    "sg:orig_category":"Schwimmb\u00e4der",
    "sg:phone":"+41 81 416 15 05",
    "sg:postcode":"6330",
    "sg:province":"Zug",
    "wof:name":"Strandbad Davos",
    "wof:placetype":"venue"
},
  "geometry": {"coordinates":[9.8443841934,46.8125228882],"type":"Point"}
}