{
  "type": "Feature",
  "properties": {
    "addr:full":"Hauptstrasse 52 Zetzwil Aargau 5732",
    "addr:housenumber":"52",
    "addr:postcode":"5732",
    "addr:street":"Hauptstrasse",
    "iso:country":"CH",
    "sg:address":"Hauptstrasse 52",
    "sg:city":"Zetzwil",
    "sg:orig_category":"Detailhandel mit Brot, Back U S\u00fcsswaren",
    "sg:phone":"+41 62 773 12 70",
    "sg:postcode":"5732",
    "sg:province":"Aargau",
    "wof:name":"Gysi-lutz R. B\u00e4ckerei-konditorei",
    "wof:placetype":"venue"
},
  "geometry": {"coordinates":[8.152049,47.285011],"type":"Point"}
}