{
  "type": "Feature",
  "properties": {
    "iso:country":"CH",
    "sg:address":"Ch\u00e2telard Route Du 54 B",
    "sg:city":"Lausanne",
    "sg:orig_category":"Sonstige pers\u00f6nliche Dienstleistungen",
    "sg:phone":"+41 21 647 07 60",
    "sg:postcode":"1018",
    "sg:province":"Vaud",
    "wof:name":"Amorsta S\u00e0rl",
    "wof:placetype":"venue"
},
  "geometry": {"coordinates":[6.6241240501,46.543712616],"type":"Point"}
}