{
  "type": "Feature",
  "properties": {
    "iso:country":"CH",
    "sg:address":"Kirchweg 1",
    "sg:city":"Gunzgen",
    "sg:classifiers":[
        {
            "category":"Insurance",
            "subcategory":"Insurance Agent",
            "type":"Services"
        }
    ],
    "sg:phone":"+41 62 216 16 42",
    "sg:postcode":"4617",
    "sg:province":"Solothurn",
    "sg:tags":[
        "versicherungsagenturen",
        "-broker"
    ],
    "wof:name":"La Suisse Versicherungen Agentur Heinrich Kamber",
    "wof:placetype":"venue"
},
  "geometry": {"coordinates":[7.8292570114,47.3151473999],"type":"Point"}
}