{
  "type": "Feature",
  "properties": {
    "iso:country":"CH",
    "sg:address":"Rue Du Th\u00e9\u00e2tre 9",
    "sg:city":"Montreux",
    "sg:orig_category":"Kinos",
    "sg:phone":"+41 56 622 35 04",
    "sg:postcode":"1820",
    "sg:province":"Vaud",
    "wof:name":"Cin\u00e9vision Gmbh",
    "wof:placetype":"venue"
},
  "geometry": {"coordinates":[8.2718276978,47.3504295349],"type":"Point"}
}