{
  "type": "Feature",
  "properties": {
    "iso:country":"CH",
    "sg:address":"Landstrasse 25",
    "sg:city":"Altnau",
    "sg:orig_category":"Tankstellen",
    "sg:postcode":"8595",
    "sg:province":"Thurgau",
    "wof:name":"Seeblick Altnau Gmbh",
    "wof:placetype":"venue"
},
  "geometry": {"coordinates":[9.2678947449,47.6181411743],"type":"Point"}
}