{
  "type": "Feature",
  "properties": {
    "iso:country":"CH",
    "sg:address":"Im D\u00f6rfli",
    "sg:city":"Filzbach",
    "sg:classifiers":[
        {
            "category":"Restaurant",
            "type":"Food & Drink"
        }
    ],
    "sg:phone":"+41 55 614 13 35",
    "sg:postcode":"8757",
    "sg:province":"Glarus",
    "wof:name":"Restaurant L\u00f6wen",
    "wof:placetype":"venue"
},
  "geometry": {"coordinates":[9.1314992905,47.1209602356],"type":"Point"}
}