{
  "type": "Feature",
  "properties": {
    "iso:country":"CH",
    "sg:address":"Avenue De La Gare 18",
    "sg:city":"Sion",
    "sg:orig_category":"Detailhandel mit Getr\u00e4nken Grosshandel mit Getr\u00e4nken",
    "sg:phone":"+41 27 322 55 55",
    "sg:postcode":"1950",
    "sg:province":"Valais",
    "wof:name":"Vinoth\u00e8que Nobilis Sa",
    "wof:placetype":"venue"
},
  "geometry": {"coordinates":[7.3586778641,46.2297134399],"type":"Point"}
}