{
  "type": "Feature",
  "properties": {
    "addr:full":"W\u00e4sserwies 12 St\u00e4fa Z\u00fcrich 8712",
    "addr:housenumber":"12",
    "addr:postcode":"8712",
    "addr:street":"Waesserwies;Zuerich",
    "iso:country":"CH",
    "sg:address":"W\u00e4sserwies 12",
    "sg:city":"St\u00e4fa",
    "sg:orig_category":"Datenverarbeitungsdienste Sonstige mit der Informatik verbundene T\u00e4tigkeiten",
    "sg:phone":"+41 19265540",
    "sg:postcode":"8712",
    "sg:province":"Z\u00fcrich",
    "wof:name":"Cim-beratung Pfund J\u00fcrg",
    "wof:placetype":"venue"
},
  "geometry": {"coordinates":[8.726039,47.243542],"type":"Point"}
}