{
  "type": "Feature",
  "properties": {
    "iso:country":"CH",
    "sg:address":"L\u00f6weng\u00e4sschen 2",
    "sg:city":"Schaffhausen",
    "sg:orig_category":"Parf\u00fcmerien U sonstiger Detailhandel mit kosmetischen Artikeln U K\u00f6rperpflegemitteln",
    "sg:phone":"+41 52 620 03 65",
    "sg:postcode":"8200",
    "sg:province":"Schaffhausen",
    "wof:name":"The Body Shop Levy Ag",
    "wof:placetype":"venue"
},
  "geometry": {"coordinates":[8.6341924667,47.6984024048],"type":"Point"}
}