{
  "type": "Feature",
  "properties": {
    "iso:country":"CH",
    "sg:address":"Schnabelgasse 2",
    "sg:city":"Basel",
    "sg:orig_category":"RESTAURANTS: TEA-ROOMS",
    "sg:phone":"+41 61 261 99 34",
    "sg:postcode":"4000",
    "sg:province":"Basel-Stadt",
    "wof:name":"Restaurant Spalenburg, Schneider Max",
    "wof:placetype":"venue"
},
  "geometry": {"coordinates":[7.5863261223,47.5569229126],"type":"Point"}
}