{
  "type": "Feature",
  "properties": {
    "iso:country":"CH",
    "sg:address":"St. Martinsplatz 8 7000 Chur. Postfach",
    "sg:city":"Chur",
    "sg:orig_category":"Finanzierungsinstitutionen",
    "sg:phone":"+41 81 257 00 77",
    "sg:postcode":"7000",
    "sg:province":"Graubunden",
    "wof:name":"Liag Ag Chur",
    "wof:placetype":"venue"
},
  "geometry": {"coordinates":[9.5323343277,46.8481216431],"type":"Point"}
}