{
  "type": "Feature",
  "properties": {
    "iso:country":"CH",
    "sg:address":"Bernstrasse Ost 49",
    "sg:city":"Suhr",
    "sg:orig_category":"Detailhandel mit Sportartikeln Fachdetailhandel in Verkaufsr\u00e4umen",
    "sg:phone":"+41 41 785 60 30",
    "sg:postcode":"5034",
    "sg:province":"Aargau",
    "wof:name":"Athleticum Sportmarkets Ag",
    "wof:placetype":"venue"
},
  "geometry": {"coordinates":[8.0845899582,47.3741378784],"type":"Point"}
}