{
  "type": "Feature",
  "properties": {
    "iso:country":"CH",
    "sg:address":"Rheinstrasse 43",
    "sg:city":"Liestal",
    "sg:orig_category":"Institutionen f\u00fcr Behinderte",
    "sg:phone":"+41 61 927 76 20",
    "sg:postcode":"4410",
    "sg:province":"Basel-Landschaft",
    "wof:name":"Windspiel Wohnheim F\u00fcr Geistig Behinderte",
    "wof:placetype":"venue"
},
  "geometry": {"coordinates":[7.7270069122,47.4901123047],"type":"Point"}
}