{
  "type": "Feature",
  "properties": {
    "iso:country":"CH",
    "sg:address":"Via Giovan Battist Pioda 8",
    "sg:city":"Lugano",
    "sg:orig_category":"Vermietung U Verpachtung von eigenen Immobilien",
    "sg:postcode":"6900",
    "sg:province":"Ticino",
    "wof:name":"Immobiliare Galbion Sa",
    "wof:placetype":"venue"
},
  "geometry": {"coordinates":[8.9541282654,46.0066757202],"type":"Point"}
}