{
  "type": "Feature",
  "properties": {
    "iso:country":"CH",
    "sg:address":"Schlossmatten 9",
    "sg:city":"Schwarzenburg",
    "sg:orig_category":"Detailhandel mit Damenbekleidung",
    "sg:phone":"+41 71 755 59 78",
    "sg:postcode":"3150",
    "sg:province":"Bern",
    "wof:name":"Anny Beusch Modes Beusch",
    "wof:placetype":"venue"
},
  "geometry": {"coordinates":[9.540912,47.378601],"type":"Point"}
}