{
  "type": "Feature",
  "properties": {
    "iso:country":"CH",
    "sg:address":"Gupfe 43",
    "sg:city":"Buchberg",
    "sg:orig_category":"G\u00fcterbef\u00f6rderung im Strassenverkehr",
    "sg:postcode":"8454",
    "sg:province":"Schaffhausen",
    "wof:name":"Sch\u00fcpbach D. Transporte",
    "wof:placetype":"venue"
},
  "geometry": {"coordinates":[8.5576601028,47.5718994141],"type":"Point"}
}