{
  "type": "Feature",
  "properties": {
    "iso:country":"CH",
    "sg:address":"Birgistrasse 7",
    "sg:city":"Wallisellen",
    "sg:orig_category":"Architektur U Ingenieurb\u00fcros",
    "sg:phone":"+41 18305060",
    "sg:postcode":"8304",
    "sg:province":"Z\u00fcrich",
    "wof:name":"Peter Sch\u00f6nenberger Ingenieurb\u00fcro",
    "wof:placetype":"venue"
},
  "geometry": {"coordinates":[8.580461,47.414841],"type":"Point"}
}