{
  "type": "Feature",
  "properties": {
    "iso:country":"CH",
    "sg:address":"Wildeggerstrasse 1",
    "sg:city":"Niederlenz",
    "sg:orig_category":"Grosshandel mit Erzen U Metallen Herstellung von Metallerzeugnissen ohne Maschinenbau",
    "sg:phone":"+41 62 891 27 53",
    "sg:postcode":"5702",
    "sg:province":"Aargau",
    "wof:name":"Stawo Ag",
    "wof:placetype":"venue"
},
  "geometry": {"coordinates":[8.1749687195,47.4044837952],"type":"Point"}
}