{
  "type": "Feature",
  "properties": {
    "iso:country":"CH",
    "sg:address":"Seewadelstrasse 14",
    "sg:city":"Henggart",
    "sg:orig_category":"Herstellung von Radio U Fernsehger\u00e4ten sowie phono U videotechnischen Ger\u00e4ten",
    "sg:phone":"+41 71 280 01 81",
    "sg:postcode":"8444",
    "sg:province":"Z\u00fcrich",
    "wof:name":"Partel Com Ag",
    "wof:placetype":"venue"
},
  "geometry": {"coordinates":[9.3511571884,47.4127693176],"type":"Point"}
}