{
  "type": "Feature",
  "properties": {
    "iso:country":"CH",
    "sg:address":"Chemin De La Gravi\u00e8re 8 1200 Genf. Postfach",
    "sg:city":"Gen\u00e8ve",
    "sg:orig_category":"Werbung",
    "sg:postcode":"1207",
    "sg:province":"Gen\u00e8ve",
    "wof:name":"Thrac\u00e9 Cr\u00e9ation, Sudan",
    "wof:placetype":"venue"
},
  "geometry": {"coordinates":[6.1305270195,46.1971588135],"type":"Point"}
}