{
  "type": "Feature",
  "properties": {
    "iso:country":"CH",
    "sg:address":"Obstgartenstrasse 11 8136 Gattikon. Postfach",
    "sg:city":"Gattikon",
    "sg:orig_category":"Herstellung von Konstruktionsteilen, Fertigbauteilen U Ausbauelementen aus Holz",
    "sg:postcode":"8136",
    "sg:province":"Z\u00fcrich",
    "wof:name":"A. Schlagintweit Ag",
    "wof:placetype":"venue"
},
  "geometry": {"coordinates":[8.5489635468,47.2837715149],"type":"Point"}
}