{
  "type": "Feature",
  "properties": {
    "iso:country":"CH",
    "sg:address":"3771",
    "sg:city":"Blankenburg",
    "sg:orig_category":"Landw. Genossenschaften Alpgenossenschaften",
    "sg:phone":"+41 33 722 32 82",
    "sg:postcode":"3771",
    "sg:province":"Bern",
    "wof:name":"Alpkorporation Frohmatt Arnold Rohrbach",
    "wof:placetype":"venue"
},
  "geometry": {"coordinates":[7.3881897926,46.5409088135],"type":"Point"}
}