{
  "type": "Feature",
  "properties": {
    "iso:country":"CH",
    "sg:address":"Sch\u00fctzenmattstrasse 1171",
    "sg:city":"B\u00fclach",
    "sg:orig_category":"G\u00fcterbef\u00f6rderung im Strassenverkehr",
    "sg:phone":"+41 18607961",
    "sg:postcode":"8180",
    "sg:province":"Z\u00fcrich",
    "wof:name":"Fredi Burgstaller Autotransporte",
    "wof:placetype":"venue"
},
  "geometry": {"coordinates":[8.5331268311,47.5279045105],"type":"Point"}
}