{
  "type": "Feature",
  "properties": {
    "iso:country":"CH",
    "sg:address":"Bahnhofstrasse 20",
    "sg:city":"Ermatingen",
    "sg:classifiers":[
        {
            "category":"Autos & Motor Vehicles",
            "subcategory":"Recreational Vehicle Sales",
            "type":"Retail Goods"
        }
    ],
    "sg:phone":"+41 71 664 28 20",
    "sg:postcode":"8272",
    "sg:province":"Thurgau",
    "sg:tags":[
        "machine",
        "equipment",
        "tool",
        "automation"
    ],
    "wof:name":"Ass Engeler",
    "wof:placetype":"venue"
},
  "geometry": {"coordinates":[9.0873212814,47.668888092],"type":"Point"}
}