{
  "type": "Feature",
  "properties": {
    "iso:country":"CH",
    "sg:address":"Les Cluds",
    "sg:city":"Bullet",
    "sg:orig_category":"RESTAURANTS: TEA-ROOMS",
    "sg:postcode":"1453",
    "sg:province":"Vaud",
    "wof:name":"Chablaix Olivier",
    "wof:placetype":"venue"
},
  "geometry": {"coordinates":[6.5607199669,46.8430900574],"type":"Point"}
}