{
  "type": "Feature",
  "properties": {
    "iso:country":"CH",
    "sg:address":"Bahnhofstrasse 8",
    "sg:city":"Klosters",
    "sg:orig_category":"Arztpraxen",
    "sg:phone":"+41 71 245 03 82",
    "sg:postcode":"7250",
    "sg:province":"Graubunden",
    "wof:name":"Dr.med.reto Andreas Bon Spezialarzt Fmh",
    "wof:placetype":"venue"
},
  "geometry": {"coordinates":[9.249401,47.411228],"type":"Point"}
}