{
  "type": "Feature",
  "properties": {
    "iso:country":"CH",
    "sg:address":"Hofstatt 4 3400 Burgdorf. Postfach",
    "sg:city":"Burgdorf",
    "sg:classifiers":[
        {
            "category":"Restaurant",
            "type":"Food & Drink"
        }
    ],
    "sg:phone":"+41 34 422 26 88",
    "sg:postcode":"3402",
    "sg:province":"Bern",
    "wof:name":"Restaurant Bistro",
    "wof:placetype":"venue"
},
  "geometry": {"coordinates":[7.6265091896,47.055557251],"type":"Point"}
}