{
  "type": "Feature",
  "properties": {
    "iso:country":"CH",
    "sg:address":"Bahnhofstrasse 6 8810 Horgen. Postfach",
    "sg:city":"Horgen",
    "sg:orig_category":"Wirtschaftspr\u00fcfung, Steuerberatung U Treuhand",
    "sg:postcode":"8810",
    "sg:province":"Z\u00fcrich",
    "wof:name":"Treuhandb\u00fcro Scheiwiller W., B\u00fccherexperte",
    "wof:placetype":"venue"
},
  "geometry": {"coordinates":[8.596578598,47.2612724304],"type":"Point"}
}