{
  "type": "Feature",
  "properties": {
    "iso:country":"CH",
    "sg:address":"Speicherstrasse 16",
    "sg:city":"St.gallen",
    "sg:orig_category":"Gesundheitswesen",
    "sg:phone":"+41 79 412 24 38",
    "sg:postcode":"9000",
    "sg:province":"St. Gallen",
    "wof:name":"Pasche Marie-christine Espace De Bien-\u00eatre, R\u00e9flexologie Etc",
    "wof:placetype":"venue"
},
  "geometry": {"coordinates":[6.8195672035,47.0968971252],"type":"Point"}
}