{
  "type": "Feature",
  "properties": {
    "iso:country":"CH",
    "sg:address":"Rue De La Prairie 7",
    "sg:city":"Gen\u00e8ve",
    "sg:orig_category":"Herstellung von Metallkonstruktionen Schlossereien",
    "sg:phone":"+41 22 344 85 25",
    "sg:postcode":"1202",
    "sg:province":"Gen\u00e8ve",
    "wof:name":"Cl\u00e9s-express",
    "wof:placetype":"venue"
},
  "geometry": {"coordinates":[6.1349229813,46.2090263367],"type":"Point"}
}