{
  "type": "Feature",
  "properties": {
    "iso:country":"CH",
    "sg:address":"Avenue Des Boveresses 42",
    "sg:city":"Lausanne",
    "sg:classifiers":[
        {
            "category":"Professional",
            "subcategory":"Business Services",
            "type":"Services"
        }
    ],
    "sg:phone":"+41 21 646 75 35",
    "sg:postcode":"1010",
    "sg:province":"Vaud",
    "sg:tags":[
        "data"
    ],
    "wof:name":"Ardel Sa",
    "wof:placetype":"venue"
},
  "geometry": {"coordinates":[6.621664,46.541409],"type":"Point"}
}