{
  "type": "Feature",
  "properties": {
    "iso:country":"CH",
    "sg:address":"Rue De L'eglise 3",
    "sg:city":"P\u00e9ry",
    "sg:classifiers":[
        {
            "category":"Restaurant",
            "type":"Food & Drink"
        }
    ],
    "sg:phone":"+41 21 946 11 26",
    "sg:postcode":"2603",
    "sg:province":"Bern",
    "wof:name":"Restaurant Du Lac De Bret",
    "wof:placetype":"venue"
},
  "geometry": {"coordinates":[7.1420798302,46.9222106934],"type":"Point"}
}