{
  "type": "Feature",
  "properties": {
    "iso:country":"CH",
    "sg:address":"Gen\u00e8ve Rue De 14",
    "sg:city":"Ch\u00eane-bourg",
    "sg:orig_category":"Non-Classified Establishments",
    "sg:phone":"+41 24 472 79 80",
    "sg:postcode":"1225",
    "sg:province":"Gen\u00e8ve",
    "wof:name":"Alain Bressoud Marbrerie Des Plavaux",
    "wof:placetype":"venue"
},
  "geometry": {"coordinates":[6.9337849617,46.2804336548],"type":"Point"}
}