{
  "type": "Feature",
  "properties": {
    "iso:country":"CH",
    "sg:address":"Buechstrasse",
    "sg:city":"Jona",
    "sg:orig_category":"Diskotheken, Dancings, Night Clubs",
    "sg:phone":"+41 55 212 15 28",
    "sg:postcode":"8645",
    "sg:province":"St. Gallen",
    "wof:name":"Dancing-discothek Magic",
    "wof:placetype":"venue"
},
  "geometry": {"coordinates":[8.8659944534,47.2257270813],"type":"Point"}
}