{
  "type": "Feature",
  "properties": {
    "iso:country":"CH",
    "sg:address":"Unterdorfstrasse 50",
    "sg:city":"Wigoltingen",
    "sg:orig_category":"Oberfl\u00e4chenveredlung U W\u00e4rmebehandlung",
    "sg:postcode":"8556",
    "sg:province":"Thurgau",
    "wof:name":"W. & E. Engeli Sandstrahl Gmbh",
    "wof:placetype":"venue"
},
  "geometry": {"coordinates":[9.0317182541,47.6020278931],"type":"Point"}
}