{
  "type": "Feature",
  "properties": {
    "iso:country":"CH",
    "sg:address":"Rue De La Poterie 22",
    "sg:city":"Gen\u00e8ve",
    "sg:orig_category":"Detailhandel mit Waren verschiedener Art, Hauptrichtung Nahrungsmittel",
    "sg:phone":"+41 22 734 44 59",
    "sg:postcode":"1202",
    "sg:province":"Gen\u00e8ve",
    "wof:name":"Roland Filliettaz Primeurs",
    "wof:placetype":"venue"
},
  "geometry": {"coordinates":[6.1339268684,46.2104377747],"type":"Point"}
}