{
  "type": "Feature",
  "properties": {
    "iso:country":"CH",
    "sg:address":"7505",
    "sg:city":"Schlarigna",
    "sg:orig_category":"Detailhandel mit Geschenkartikeln U Souvenirs",
    "sg:phone":"+41 81 833 44 74",
    "sg:postcode":"7505",
    "sg:province":"Graubunden",
    "wof:name":"Rosmarie Lisignoli Boutique Romy Kunstgewerbe",
    "wof:placetype":"venue"
},
  "geometry": {"coordinates":[9.8600702286,46.5126800537],"type":"Point"}
}