{
  "type": "Feature",
  "properties": {
    "iso:country":"CH",
    "sg:address":"Rue Bel-air 20 2350 Saignel\u00e9gier. Postfach",
    "sg:city":"Saignel\u00e9gier",
    "sg:orig_category":"Aktivit\u00e4ten der Generalunternehmen im Baugewerbe Allgemeiner Hoch U Tiefbau",
    "sg:phone":"+41 32 951 35 45",
    "sg:postcode":"2350",
    "sg:province":"Jura",
    "wof:name":"Pbst Construction S\u00e0rl Entreprise G\u00e9n\u00e9rale De Construction, De G\u00e9nie Civil Etc",
    "wof:placetype":"venue"
},
  "geometry": {"coordinates":[6.991841,47.254612],"type":"Point"}
}