{
  "type": "Feature",
  "properties": {
    "iso:country":"CH",
    "sg:address":"Villa L'emeraude",
    "sg:city":"L'abbaye",
    "sg:orig_category":"Pulvermetallurgie Schmieden, Pressen, Stanzen U Profilwalzen von Metallen",
    "sg:phone":"+41 21 841 16 81",
    "sg:postcode":"1344",
    "sg:province":"Vaud",
    "wof:name":"Donald Rochat Constr.d'\u00e9tampes",
    "wof:placetype":"venue"
},
  "geometry": {"coordinates":[-79.83000183110001,37.0555992126],"type":"Point"}
}