{
  "type": "Feature",
  "properties": {
    "iso:country":"CH",
    "sg:address":"Route Du Stand 41",
    "sg:city":"Nyon",
    "sg:orig_category":"Dachdeckerei Zimmerei, Dachdeckerei, Bauspenglerei U Abdichtung",
    "sg:phone":"+41 22 361 50 31",
    "sg:postcode":"1260",
    "sg:province":"Vaud",
    "wof:name":"Jaquinet Robert Sa",
    "wof:placetype":"venue"
},
  "geometry": {"coordinates":[6.219574,46.381668],"type":"Point"}
}