{
  "type": "Feature",
  "properties": {
    "addr:full":"Kantonsstrasse 6 Visp Valais 3930",
    "addr:housenumber":"6",
    "addr:postcode":"3930",
    "addr:street":"Kantonsstrasse",
    "iso:country":"CH",
    "sg:address":"Kantonsstrasse 6",
    "sg:city":"Visp",
    "sg:orig_category":"Detailhandel mit Brillen U anderen Sehhilfen Detailhandel mit medizinischen U orthop\u00e4dischen Artikel",
    "sg:phone":"+41 27 924 54 54",
    "sg:postcode":"3930",
    "sg:province":"Valais",
    "wof:name":"Auditis Tharin Sa",
    "wof:placetype":"venue"
},
  "geometry": {"coordinates":[7.880474,46.292171],"type":"Point"}
}