{
  "type": "Feature",
  "properties": {
    "iso:country":"CH",
    "sg:address":"Wilen",
    "sg:city":"Kaltbrunn",
    "sg:orig_category":"Pensionskassen",
    "sg:phone":"+41 55 293 30 00",
    "sg:postcode":"8722",
    "sg:province":"St. Gallen",
    "wof:name":"Vorsorgestiftung Destra",
    "wof:placetype":"venue"
},
  "geometry": {"coordinates":[9.0375299454,47.2095413208],"type":"Point"}
}