{
  "type": "Feature",
  "properties": {
    "iso:country":"CH",
    "sg:address":"Lake-placid",
    "sg:city":"Haute-nendaz",
    "sg:orig_category":"Detailhandel mit Schreib U Papeteriewaren Detailhandel mit Zeitungen U Zeitschriften Kioske",
    "sg:phone":"+41 41 420 70 02",
    "sg:postcode":"1997",
    "sg:province":"Valais",
    "wof:name":"Papeterie Kiosk Maihof",
    "wof:placetype":"venue"
},
  "geometry": {"coordinates":[8.3110456467,47.0645141602],"type":"Point"}
}