{
  "type": "Feature",
  "properties": {
    "iso:country":"CH",
    "sg:address":"Riedstrasse 8 8953 Dietikon. Postfach",
    "sg:city":"Dietikon",
    "sg:orig_category":"Herstellung von Radio U Fernsehger\u00e4ten sowie phono U videotechnischen Ger\u00e4ten",
    "sg:phone":"+41 17421849",
    "sg:postcode":"8953",
    "sg:province":"Z\u00fcrich",
    "wof:name":"Ton Total Optical Networks Ag Fernmeldetechnische Produkte; Lieferung. Telekommunikations-dienstleistungen",
    "wof:placetype":"venue"
},
  "geometry": {"coordinates":[8.3944854736,47.4198493958],"type":"Point"}
}