{
  "type": "Feature",
  "properties": {
    "iso:country":"CH",
    "sg:address":"Via Casa Del Frate 21 6616 Losone. Postfach Caselle Postale 7011",
    "sg:city":"Losone",
    "sg:classifiers":[
        {
            "category":"Insurance",
            "subcategory":"Insurance Agent",
            "type":"Services"
        }
    ],
    "sg:phone":"+41 91 791 17 26",
    "sg:postcode":"6616",
    "sg:province":"Ticino",
    "sg:tags":[
        "versicherungsagenturen",
        "-broker"
    ],
    "wof:name":"Alfredo Maggetti Assicurazioni",
    "wof:placetype":"venue"
},
  "geometry": {"coordinates":[8.7562885284,46.1748924255],"type":"Point"}
}