{
  "type": "Feature",
  "properties": {
    "iso:country":"CH",
    "sg:address":"Gliserallee 47",
    "sg:city":"Glis",
    "sg:orig_category":"Gartenbau",
    "sg:postcode":"3902",
    "sg:province":"Valais",
    "wof:name":"Leo Kressibucher-gerber",
    "wof:placetype":"venue"
},
  "geometry": {"coordinates":[9.1819200516,47.5958404541],"type":"Point"}
}