{
  "type": "Feature",
  "properties": {
    "iso:country":"CH",
    "sg:address":"1304",
    "sg:city":"Cossonay-ville",
    "sg:orig_category":"Verarbeitung von Milch Verwertung von Milch",
    "sg:postcode":"1304",
    "sg:province":"Vaud",
    "wof:name":"Soci\u00e9t\u00e9 De Laiterie De Cossonay",
    "wof:placetype":"venue"
},
  "geometry": {"coordinates":[6.50770998,46.6138191223],"type":"Point"}
}