{
  "type": "Feature",
  "properties": {
    "iso:country":"CH",
    "sg:address":"Seefeldstrasse 116",
    "sg:city":"Z\u00fcrich",
    "sg:orig_category":"Advokaturb\u00fcros",
    "sg:phone":"+41 19702050",
    "sg:postcode":"8008",
    "sg:province":"Z\u00fcrich",
    "wof:name":"Gisler & Haltiner",
    "wof:placetype":"venue"
},
  "geometry": {"coordinates":[8.800628,47.326641],"type":"Point"}
}