{
  "type": "Feature",
  "properties": {
    "addr:full":"Via San Gottardo 31 Gordola Ticino 6596",
    "addr:housenumber":"31",
    "addr:postcode":"6596",
    "addr:street":"Via San Gottardo",
    "iso:country":"CH",
    "sg:address":"Via San Gottardo 31",
    "sg:city":"Gordola",
    "sg:classifiers":[
        {
            "category":"Shopping",
            "subcategory":"Discount & Variety Stores",
            "type":"Retail Goods"
        }
    ],
    "sg:phone":"+41 91 745 44 89",
    "sg:postcode":"6596",
    "sg:province":"Ticino",
    "sg:tags":[
        "shop",
        "locksmith's"
    ],
    "wof:name":"Giovanni Pezzolla & Ernst G\u00fcnter",
    "wof:placetype":"venue"
},
  "geometry": {"coordinates":[8.857764,46.182056],"type":"Point"}
}