{
  "type": "Feature",
  "properties": {
    "iso:country":"CH",
    "sg:address":"Waidhalde 11 8493 Saland. Postfach",
    "sg:city":"Z\u00fcrich",
    "sg:orig_category":"Erbringung von Dienstleistungen f\u00fcr Unternehmen",
    "sg:postcode":"8001",
    "sg:province":"Z\u00fcrich",
    "wof:name":"Ib - G\u00d6ssler Industriebeschriftungen Im Elektrotechnischen Bereich",
    "wof:placetype":"venue"
},
  "geometry": {"coordinates":[8.8541097641,47.3906326294],"type":"Point"}
}