{
  "type": "Feature",
  "properties": {
    "iso:country":"CH",
    "sg:address":"Route De Riddes",
    "sg:city":"Leytron",
    "sg:orig_category":"Tankstellen",
    "sg:phone":"+41 27 306 29 17",
    "sg:postcode":"1912",
    "sg:province":"Valais",
    "wof:name":"Claudine Devayes Station-service",
    "wof:placetype":"venue"
},
  "geometry": {"coordinates":[7.2115449905,46.1848564148],"type":"Point"}
}