{
  "type": "Feature",
  "properties": {
    "iso:country":"CH",
    "sg:address":"Bahnw\u00e4chterh\u00e4uschen 7122 Valendas. Postfach",
    "sg:city":"Valendas",
    "sg:orig_category":"Herstellung von Mess U Kontrollinstrumenten U vorrichtungen",
    "sg:postcode":"7122",
    "sg:province":"Graubunden",
    "wof:name":"Bernasconi High Voltage Ag",
    "wof:placetype":"venue"
},
  "geometry": {"coordinates":[9.2821350098,46.7875747681],"type":"Point"}
}