{
  "type": "Feature",
  "properties": {
    "iso:country":"CH",
    "sg:address":"Ebenaustrasse",
    "sg:city":"Horw",
    "sg:orig_category":"Verwaltung von Immobilien",
    "sg:postcode":"6048",
    "sg:province":"Luzern",
    "wof:name":"Steinibach-immobilien Ag",
    "wof:placetype":"venue"
},
  "geometry": {"coordinates":[8.308344841,47.0144844055],"type":"Point"}
}