{
  "type": "Feature",
  "properties": {
    "iso:country":"CH",
    "sg:address":"Kasernenstrasse 120",
    "sg:city":"B\u00fclach",
    "sg:classifiers":[
        {
            "category":"Restaurant",
            "type":"Food & Drink"
        }
    ],
    "sg:phone":"+41 18606434",
    "sg:postcode":"8180",
    "sg:province":"Z\u00fcrich",
    "wof:name":"Restaurant Frieden",
    "wof:placetype":"venue"
},
  "geometry": {"coordinates":[8.524813652,47.5127944946],"type":"Point"}
}