{
  "type": "Feature",
  "properties": {
    "iso:country":"CH",
    "sg:address":"Marschalkenstrasse 119",
    "sg:city":"Basel",
    "sg:orig_category":"Grosshandel mit medizinischen U orthop\u00e4dischen Artikeln Herstellung von medizinischen U chirurgische",
    "sg:phone":"+41 61 302 42 02",
    "sg:postcode":"4000",
    "sg:province":"Basel-Stadt",
    "wof:name":"Science Products Spt",
    "wof:placetype":"venue"
},
  "geometry": {"coordinates":[7.5701289177,47.5465660095],"type":"Point"}
}