{
  "type": "Feature",
  "properties": {
    "iso:country":"CH",
    "sg:address":"Rue Du March\u00e9 28",
    "sg:city":"Gen\u00e8ve",
    "sg:orig_category":"Softwareentwicklung U beratung Sonstiger Grosshandel",
    "sg:phone":"+41 22 817 37 67",
    "sg:postcode":"1204",
    "sg:province":"Gen\u00e8ve",
    "wof:name":"Sellys S\u00e0rl",
    "wof:placetype":"venue"
},
  "geometry": {"coordinates":[6.1472101212,46.2029571533],"type":"Point"}
}