{
  "type": "Feature",
  "properties": {
    "iso:country":"CH",
    "sg:address":"Feldmattstrasse 13",
    "sg:city":"Emmen",
    "sg:orig_category":"Grosshandel mit Eisenwaren sowie Installationsbedarf f\u00fcr Gas, Wasser U Heizung Sanit\u00e4r, Heizungs U L",
    "sg:phone":"+41 71 777 18 33",
    "sg:postcode":"6032",
    "sg:province":"Luzern",
    "wof:name":"Sanit\u00e4r-baur Handels Ag",
    "wof:placetype":"venue"
},
  "geometry": {"coordinates":[9.5688352585,47.3884544373],"type":"Point"}
}