{
  "type": "Feature",
  "properties": {
    "iso:country":"CH",
    "sg:address":"Stutzstr. 7 3700 Spiez. Postfach",
    "sg:city":"Hondrich",
    "sg:orig_category":"Werbung",
    "sg:postcode":"3702",
    "sg:province":"Bern",
    "wof:name":"Agentur F\u00fcr Marketing Und Werbung Friedli Fritz",
    "wof:placetype":"venue"
},
  "geometry": {"coordinates":[7.5633950233,46.9277572632],"type":"Point"}
}