{
  "type": "Feature",
  "properties": {
    "iso:country":"CH",
    "sg:address":"Rue Sismondi 16",
    "sg:city":"Gen\u00e8ve",
    "sg:orig_category":"Detailhandel mit Waren verschiedener Art, Hauptrichtung Nahrungsmittel",
    "sg:phone":"+41 22 731 36 12",
    "sg:postcode":"1201",
    "sg:province":"Gen\u00e8ve",
    "wof:name":"Kibangu & Nkodia Malambu Afrika Food Produits Tropicaux",
    "wof:placetype":"venue"
},
  "geometry": {"coordinates":[6.1466751099,46.2103729248],"type":"Point"}
}