{
  "type": "Feature",
  "properties": {
    "iso:country":"CH",
    "sg:address":"Rue Du Coll\u00e8ge 11",
    "sg:city":"Yverdon-les-bains",
    "sg:orig_category":"Detailhandel mit Brillen U anderen Sehhilfen Fachdetailhandel in Verkaufsr\u00e4umen",
    "sg:phone":"+41 24 426 43 58",
    "sg:postcode":"1400",
    "sg:province":"Vaud",
    "wof:name":"Boiziau Opticien S\u00e0rl",
    "wof:placetype":"venue"
},
  "geometry": {"coordinates":[6.638073,46.779266],"type":"Point"}
}