{
  "type": "Feature",
  "properties": {
    "iso:country":"CH",
    "sg:address":"Eichenweg 2 3052 Zollikofen. Postfach",
    "sg:city":"Zollikofen",
    "sg:orig_category":"Innenarchitekturb\u00fcros",
    "sg:phone":"+41 31 911 61 23",
    "sg:postcode":"3052",
    "sg:province":"Bern",
    "wof:name":"Experience Artdesign Interieur",
    "wof:placetype":"venue"
},
  "geometry": {"coordinates":[7.463080883,46.9965553284],"type":"Point"}
}