{
  "type": "Feature",
  "properties": {
    "iso:country":"CH",
    "sg:address":"Klausstrasse 49",
    "sg:city":"Z\u00fcrich",
    "sg:orig_category":"Erbringung von sonstigen Dienstleistungen f\u00fcr Unterhaltung, Erholung U Freizeit",
    "sg:phone":"+41 79 436 35 57",
    "sg:postcode":"8008",
    "sg:province":"Z\u00fcrich",
    "wof:name":"L\u00f6hmann Peter",
    "wof:placetype":"venue"
},
  "geometry": {"coordinates":[9.8381910324,46.4970664978],"type":"Point"}
}