{
  "type": "Feature",
  "properties": {
    "iso:country":"CH",
    "sg:address":"Gempenring 96",
    "sg:city":"Dornach",
    "sg:orig_category":"Sonstiger spezialisierter Hoch U Tiefbau",
    "sg:phone":"+41 61 701 57 87",
    "sg:postcode":"4143",
    "sg:province":"Solothurn",
    "wof:name":"Th\u00fcring Hanspeter, Kundenmaurer",
    "wof:placetype":"venue"
},
  "geometry": {"coordinates":[7.6123118401,47.4767456055],"type":"Point"}
}