{
  "type": "Feature",
  "properties": {
    "addr:full":"Ador Quai Gustave- 12 1207 Gen\u00e8ve. Postfach Gen\u00e8ve Gen\u00e8ve 1207",
    "addr:housenumber":"ador;12",
    "addr:postcode":"1207;postfach;1207",
    "addr:street":"Quai Gustave",
    "iso:country":"CH",
    "sg:address":"Ador Quai Gustave- 12 1207 Gen\u00e8ve. Postfach",
    "sg:city":"Gen\u00e8ve",
    "sg:orig_category":"Betrieb von Taxis",
    "sg:postcode":"1207",
    "sg:province":"Gen\u00e8ve",
    "wof:name":"Limospeed Service Taxi, Carmine Capo",
    "wof:placetype":"venue"
},
  "geometry": {"coordinates":[6.156371,46.205055],"type":"Point"}
}