{
  "type": "Feature",
  "properties": {
    "iso:country":"CH",
    "sg:address":"Via Gismonda 17",
    "sg:city":"Mendrisio",
    "sg:orig_category":"Physiotherapie",
    "sg:phone":"+41 91 646 45 66",
    "sg:postcode":"6850",
    "sg:province":"Ticino",
    "wof:name":"Sigrid Kempf Fisioterapia",
    "wof:placetype":"venue"
},
  "geometry": {"coordinates":[8.9859676361,45.8691215515],"type":"Point"}
}