{
  "type": "Feature",
  "properties": {
    "iso:country":"CH",
    "sg:address":"Seestrasse 39",
    "sg:city":"Uster",
    "sg:orig_category":"Non-Classified Establishments",
    "sg:postcode":"8610",
    "sg:province":"Z\u00fcrich",
    "wof:name":"B\u00e4ckerei-konditorei Vuaillat",
    "wof:placetype":"venue"
},
  "geometry": {"coordinates":[8.7111816406,47.3457183838],"type":"Point"}
}