{
  "type": "Feature",
  "properties": {
    "iso:country":"CH",
    "sg:address":"Bergstrasse 4",
    "sg:city":"Z\u00fcrich",
    "sg:orig_category":"Institutionen f\u00fcr Behinderte Institutionen f\u00fcr psychosoziale F\u00e4lle",
    "sg:phone":"+41 12622499",
    "sg:postcode":"8044",
    "sg:province":"Z\u00fcrich",
    "wof:name":"Beth Chana Heim F\u00fcr Behinderte",
    "wof:placetype":"venue"
},
  "geometry": {"coordinates":[8.5598516464,47.3754882812],"type":"Point"}
}