{
  "type": "Feature",
  "properties": {
    "iso:country":"CH",
    "sg:address":"Dreinepperstrasse 17",
    "sg:city":"M\u00e4nnedorf",
    "sg:orig_category":"Bauspenglerei Sanit\u00e4rinstallation",
    "sg:phone":"+41 19200366",
    "sg:postcode":"8708",
    "sg:province":"Z\u00fcrich",
    "wof:name":"J\u00fcrg H\u00e4ckel Sanit\u00e4re Anlagen & Spenglerei",
    "wof:placetype":"venue"
},
  "geometry": {"coordinates":[8.689173,47.257351],"type":"Point"}
}