{
  "type": "Feature",
  "properties": {
    "iso:country":"CH",
    "sg:address":"Rue Barth\u00e9lemy-menn 5",
    "sg:city":"Gen\u00e8ve",
    "sg:orig_category":"Instandhaltung U Reparatur von Automobilen Mechanische Werkst\u00e4tten",
    "sg:phone":"+41 22 320 48 10",
    "sg:postcode":"1205",
    "sg:province":"Gen\u00e8ve",
    "wof:name":"Jp M\u00e9canique, J & J Presas",
    "wof:placetype":"venue"
},
  "geometry": {"coordinates":[6.1450600624,46.1906509399],"type":"Point"}
}