{
  "type": "Feature",
  "properties": {
    "iso:country":"CH",
    "sg:address":"Via Pretorio 5",
    "sg:city":"Lugano",
    "sg:orig_category":"Zahnarztpraxen",
    "sg:phone":"+41 91 923 47 30",
    "sg:postcode":"6900",
    "sg:province":"Ticino",
    "wof:name":"Dottori Med.dent. Moor Dentisti",
    "wof:placetype":"venue"
},
  "geometry": {"coordinates":[8.9513759613,46.0055351257],"type":"Point"}
}