{
  "type": "Feature",
  "properties": {
    "iso:country":"CH",
    "sg:address":"Schleumen",
    "sg:city":"Hindelbank",
    "sg:orig_category":"RESTAURANTS: TEA-ROOMS",
    "sg:phone":"+41 34229549",
    "sg:postcode":"3324",
    "sg:province":"Bern",
    "wof:name":"Stucki Christian.",
    "wof:placetype":"venue"
},
  "geometry": {"coordinates":[7.5406918526,47.0429344177],"type":"Point"}
}