{
  "type": "Feature",
  "properties": {
    "iso:country":"CH",
    "sg:address":"Stockenerstrasse 3",
    "sg:city":"Bischofszell",
    "sg:orig_category":"Bildung and Forschung, Bildungsmedien",
    "sg:phone":"+41 71 420 03 61",
    "sg:postcode":"9220",
    "sg:province":"Thurgau",
    "wof:name":"Techedition",
    "wof:placetype":"venue"
},
  "geometry": {"coordinates":[9.250544,47.496262],"type":"Point"}
}