{
  "type": "Feature",
  "properties": {
    "iso:country":"CH",
    "sg:address":"Aarwangenstrasse 43",
    "sg:city":"Langenthal",
    "sg:orig_category":"Architektur U Ingenieurb\u00fcros",
    "sg:phone":"+41 62 922 35 52",
    "sg:postcode":"4900",
    "sg:province":"Bern",
    "wof:name":"Scheidegger Ag, Ingenieurb\u00fcro F\u00fcr Hoch Und Tiefbau",
    "wof:placetype":"venue"
},
  "geometry": {"coordinates":[7.78433,47.21909],"type":"Point"}
}