{
  "type": "Feature",
  "properties": {
    "iso:country":"CH",
    "sg:address":"Langmattstrasse 3 4415 Lausen. Postfach",
    "sg:city":"Lausen",
    "sg:orig_category":"Non-Classified Establishments",
    "sg:postcode":"4415",
    "sg:province":"Basel-Landschaft",
    "wof:name":"Paramount Ltd Beteiligungen",
    "wof:placetype":"venue"
},
  "geometry": {"coordinates":[7.7717638016,47.468711853],"type":"Point"}
}