{
  "type": "Feature",
  "properties": {
    "iso:country":"CH",
    "sg:address":"Grundstrasse 16",
    "sg:city":"Rotkreuz",
    "sg:orig_category":"Markt U Meinungsforschung",
    "sg:phone":"+41 41 790 53 53",
    "sg:postcode":"6343",
    "sg:province":"Zug",
    "wof:name":"Degra Ag",
    "wof:placetype":"venue"
},
  "geometry": {"coordinates":[8.4307823181,47.1460037231],"type":"Point"}
}