{
  "type": "Feature",
  "properties": {
    "iso:country":"CH",
    "sg:address":"Wehntalerstrasse 84",
    "sg:city":"Dielsdorf",
    "sg:orig_category":"Herstellung von Teppichen",
    "sg:postcode":"8157",
    "sg:province":"Z\u00fcrich",
    "wof:name":"Maksuti Bodenbel\u00e4ge Gmbh",
    "wof:placetype":"venue"
},
  "geometry": {"coordinates":[8.4545183182,47.4754066467],"type":"Point"}
}