{
  "type": "Feature",
  "properties": {
    "iso:country":"CH",
    "sg:address":"Stockertstrasse 26",
    "sg:city":"Muttenz",
    "sg:orig_category":"G\u00fcterbef\u00f6rderung im Strassenverkehr",
    "sg:phone":"+41 71 311 35 35",
    "sg:postcode":"4132",
    "sg:province":"Basel-Landschaft",
    "wof:name":"Sprenger Transporte",
    "wof:placetype":"venue"
},
  "geometry": {"coordinates":[9.2996959686,47.405040741],"type":"Point"}
}