{
  "type": "Feature",
  "properties": {
    "iso:country":"CH",
    "sg:address":"Blattenweg 1",
    "sg:city":"Lohn",
    "sg:classifiers":[
        {
            "category":"Wholesale",
            "subcategory":"Medical Equipment & Supplies",
            "type":"Manufacturing & Wholesale Goods"
        }
    ],
    "sg:phone":"+41 52 649 40 80",
    "sg:postcode":"8235",
    "sg:province":"Schaffhausen",
    "sg:tags":[
        "instrument",
        "surgical"
    ],
    "wof:name":"Amidia Ag",
    "wof:placetype":"venue"
},
  "geometry": {"coordinates":[8.673541069,47.7542953491],"type":"Point"}
}