{
  "type": "Feature",
  "properties": {
    "iso:country":"CH",
    "sg:address":"Binzstrasse 7 8045 Z\u00fcrich",
    "sg:city":"Zust",
    "sg:orig_category":"Fernmeldedienste",
    "sg:phone":"+41 41 810 17 78",
    "sg:postcode":"45",
    "wof:name":"Gc Pan European Crossing Switzerland Gmbh",
    "wof:placetype":"venue"
},
  "geometry": {"coordinates":[8.6376781464,47.0244865417],"type":"Point"}
}