{
  "type": "Feature",
  "properties": {
    "iso:country":"CH",
    "sg:address":"Urdorferstrasse 9",
    "sg:city":"Dietikon",
    "sg:orig_category":"Herstellung von Papier, Karton U Pappe",
    "sg:postcode":"8953",
    "sg:province":"Z\u00fcrich",
    "wof:name":"Technogramme Ag",
    "wof:placetype":"venue"
},
  "geometry": {"coordinates":[8.413143158,47.3991928101],"type":"Point"}
}