{
  "type": "Feature",
  "properties": {
    "iso:country":"CH",
    "sg:address":"Route P\u00e9nesson 6",
    "sg:city":"Aubonne",
    "sg:orig_category":"Gartenbau Landschaftsplanungsb\u00fcros U Gartenarchitekturb\u00fcros",
    "sg:phone":"+41 21 808 70 91",
    "sg:postcode":"1170",
    "sg:province":"Vaud",
    "wof:name":"Albert Hirt Jardinier-paysagiste",
    "wof:placetype":"venue"
},
  "geometry": {"coordinates":[6.386341095,46.4919242859],"type":"Point"}
}