{
  "type": "Feature",
  "properties": {
    "iso:country":"CH",
    "sg:address":"Wampflenstrasse 78 8706 Meilen. Postfach",
    "sg:city":"Meilen",
    "sg:orig_category":"Non-Classified Establishments",
    "sg:postcode":"8706",
    "sg:province":"Z\u00fcrich",
    "wof:name":"Health & More Gmbh Naturprodukte, Bes. Kosmetikartikel, Kleider, Nat\u00fcrliche Lebensmittel Usw.; Beratung, Verkauf, Vertrieb",
    "wof:placetype":"venue"
},
  "geometry": {"coordinates":[8.6418533325,47.2747573853],"type":"Point"}
}