{
  "type": "Feature",
  "properties": {
    "iso:country":"CH",
    "sg:address":"Sonnenh\u00fcgel 11",
    "sg:city":"T\u00e4gerschen",
    "sg:orig_category":"Non-Classified Establishments",
    "sg:postcode":"9554",
    "sg:province":"Thurgau",
    "wof:name":"Aar Baumontagen Gmbh",
    "wof:placetype":"venue"
},
  "geometry": {"coordinates":[9.03262043,47.5107765198],"type":"Point"}
}