{
  "type": "Feature",
  "properties": {
    "iso:country":"CH",
    "sg:address":"Z\u00fcrichbergstrasse 201",
    "sg:city":"Z\u00fcrich",
    "sg:orig_category":"Elektroinstallation",
    "sg:phone":"+41 14503090",
    "sg:postcode":"8044",
    "sg:province":"Z\u00fcrich",
    "wof:name":"Dudli Elektro Gmbh",
    "wof:placetype":"venue"
},
  "geometry": {"coordinates":[8.5741100311,47.3839111328],"type":"Point"}
}