{
  "type": "Feature",
  "properties": {
    "iso:country":"CH",
    "sg:address":"Bachstrasse 31",
    "sg:city":"Lenzburg",
    "sg:orig_category":"Organisationen der Wohlfahrtspflege",
    "sg:phone":"+41 2577884",
    "sg:postcode":"5600",
    "sg:province":"Aargau",
    "wof:name":"Pro Senectute",
    "wof:placetype":"venue"
},
  "geometry": {"coordinates":[8.8018665314,47.3273506165],"type":"Point"}
}