{
  "type": "Feature",
  "properties": {
    "iso:country":"CH",
    "sg:address":"Engenb\u00fchl 333 5705 Hallwil. Postfach",
    "sg:city":"Hallwil",
    "sg:orig_category":"Detailhandel mit M\u00f6beln U Haushaltsgegenst\u00e4nden",
    "sg:postcode":"5705",
    "sg:province":"Aargau",
    "wof:name":"Scala Habitat Gmbh",
    "wof:placetype":"venue"
},
  "geometry": {"coordinates":[8.1748332977,47.3291168213],"type":"Point"}
}