{
  "type": "Feature",
  "properties": {
    "iso:country":"CH",
    "sg:address":"Chemin De Chemarin 3",
    "sg:city":"Ligni\u00e8res",
    "sg:orig_category":"Mechanische Werkst\u00e4tten Technische B\u00fcros Feinmechanik",
    "sg:phone":"+41 32 751 20 80",
    "sg:postcode":"2523",
    "sg:province":"Neuch\u00e2tel",
    "wof:name":"Eveline Fatton Crs Solutions",
    "wof:placetype":"venue"
},
  "geometry": {"coordinates":[7.0653781891,47.0791893005],"type":"Point"}
}