{
  "type": "Feature",
  "properties": {
    "iso:country":"CH",
    "sg:address":"Chemin De Palud",
    "sg:city":"Perroy",
    "sg:orig_category":"Reinigungsgewerbe",
    "sg:postcode":"1166",
    "sg:province":"Vaud",
    "wof:name":"Adeler Egle Gisela",
    "wof:placetype":"venue"
},
  "geometry": {"coordinates":[9.1993598938,47.2241897583],"type":"Point"}
}