{
  "type": "Feature",
  "properties": {
    "iso:country":"CH",
    "sg:address":"Kasernenstrasse 1 9100 Herisau. Postfach",
    "sg:city":"Herisau",
    "sg:orig_category":"Zahnarztpraxen",
    "sg:phone":"+41 71 944 24 28",
    "sg:postcode":"9102",
    "sg:province":"Appenzell Ausserrhoden",
    "wof:name":"Dr. Med. Dent. J\u00fcrg Scherrer Zahnarzt",
    "wof:placetype":"venue"
},
  "geometry": {"coordinates":[9.1109209061,47.474571228],"type":"Point"}
}