{
  "type": "Feature",
  "properties": {
    "iso:country":"CH",
    "sg:address":"Etzelstrasse 44 A",
    "sg:city":"W\u00e4denswil",
    "sg:orig_category":"Unclassifiable Establishments",
    "sg:postcode":"8820",
    "sg:province":"Z\u00fcrich",
    "wof:name":"Meier Hans-rudolf Kommunikationsberatung",
    "wof:placetype":"venue"
},
  "geometry": {"coordinates":[8.6798906326,47.2225570679],"type":"Point"}
}