{
  "type": "Feature",
  "properties": {
    "addr:full":"1323 Romainm\u00f4tier Vaud 1323",
    "addr:postcode":"1323;1323",
    "iso:country":"CH",
    "sg:address":"1323",
    "sg:city":"Romainm\u00f4tier",
    "sg:orig_category":"Detailhandel mit Antiquit\u00e4ten",
    "sg:phone":"+41 79 448 41 93",
    "sg:postcode":"1323",
    "sg:province":"Vaud",
    "wof:name":"Th\u00e9odore Surer Au Lieutenant Baillival Antiq.",
    "wof:placetype":"venue"
},
  "geometry": {"coordinates":[6.460725,46.693455],"type":"Point"}
}