{
  "type": "Feature",
  "properties": {
    "iso:country":"CH",
    "sg:address":"Via Industria 14a",
    "sg:city":"Lamone",
    "sg:classifiers":[
        {
            "category":"Restaurant",
            "type":"Food & Drink"
        }
    ],
    "sg:phone":"+41 91 864 16 04",
    "sg:postcode":"6814",
    "sg:province":"Ticino",
    "wof:name":"Ristorante Pinocchio",
    "wof:placetype":"venue"
},
  "geometry": {"coordinates":[8.9068098068,46.3802680969],"type":"Point"}
}