{
  "type": "Feature",
  "properties": {
    "iso:country":"CH",
    "sg:address":"Neumarkt 15",
    "sg:city":"Z\u00fcrich",
    "sg:orig_category":"Arbeitnehmerverb\u00e4nde",
    "sg:phone":"+41 12529295",
    "sg:postcode":"8001",
    "sg:province":"Z\u00fcrich",
    "wof:name":"Architektur Forum Z\u00fcrich",
    "wof:placetype":"venue"
},
  "geometry": {"coordinates":[8.546093,47.37291],"type":"Point"}
}