{
  "type": "Feature",
  "properties": {
    "iso:country":"CH",
    "sg:address":"Rue Du Grand-ch\u00eane 6",
    "sg:city":"Lausanne",
    "sg:orig_category":"Effekten U Warenterminb\u00f6rsen Finanzierungsinstitutionen",
    "sg:phone":"+41 21 317 58 00",
    "sg:postcode":"1003",
    "sg:province":"Vaud",
    "wof:name":"Upturn One Sa Sponsoring",
    "wof:placetype":"venue"
},
  "geometry": {"coordinates":[6.6308717728,46.5198402405],"type":"Point"}
}