{
  "type": "Feature",
  "properties": {
    "addr:full":"Untersteckholz Bern 4916",
    "addr:postcode":"4916",
    "iso:country":"CH",
    "sg:city":"Untersteckholz",
    "sg:classifiers":[
        {
            "category":"Banks & Credit Unions",
            "subcategory":"Bank",
            "type":"Services"
        }
    ],
    "sg:phone":"+41 4163220460",
    "sg:postcode":"4916",
    "sg:province":"Bern",
    "wof:name":"Ersparniskasse, Des Amtsbezirkes Aarwangen",
    "wof:placetype":"venue"
},
  "geometry": {"coordinates":[7.845878,47.199795],"type":"Point"}
}