{
  "type": "Feature",
  "properties": {
    "iso:country":"CH",
    "sg:address":"K\u00fcfergasse 17",
    "sg:city":"K\u00f6lliken",
    "sg:orig_category":"G\u00fcterbef\u00f6rderung im Strassenverkehr",
    "sg:phone":"+41 62 723 36 60",
    "sg:postcode":"5742",
    "sg:province":"Aargau",
    "wof:name":"Steiner Hans & Sohn, Transporte",
    "wof:placetype":"venue"
},
  "geometry": {"coordinates":[8.0200471878,47.3291702271],"type":"Point"}
}