{
  "type": "Feature",
  "properties": {
    "iso:country":"CH",
    "sg:address":"Rondi",
    "sg:city":"Gampelen",
    "sg:orig_category":"Sportvereine Sch\u00fctzen Bogen",
    "sg:phone":"+41 32 313 32 97",
    "sg:postcode":"3236",
    "sg:province":"Bern",
    "wof:name":"Tell-club Neuch\u00e2tel",
    "wof:placetype":"venue"
},
  "geometry": {"coordinates":[7.0584812164,47.0145874023],"type":"Point"}
}