{
  "type": "Feature",
  "properties": {
    "iso:country":"CH",
    "sg:address":"Weinbergstrasse 102",
    "sg:city":"Z\u00fcrich",
    "sg:orig_category":"Detailhandel mit elektrischen Haushalts-,Radio U Fernsehger\u00e4ten sowie Musikinstrumenten",
    "sg:phone":"+41 13629770",
    "sg:postcode":"8006",
    "sg:province":"Z\u00fcrich",
    "wof:name":"Somara Ag",
    "wof:placetype":"venue"
},
  "geometry": {"coordinates":[8.5426101685,47.3853721619],"type":"Point"}
}