{
  "type": "Feature",
  "properties": {
    "iso:country":"CH",
    "sg:address":"Renferstrasse 17 2500 Biel/bienne. Postfach",
    "sg:city":"Biel/bienne",
    "sg:orig_category":"Herstellung von Werkzeugmaschinen",
    "sg:postcode":"2500",
    "sg:province":"Bern",
    "wof:name":"Jet Grinding Systems Ag Statische Umformer: Entwicklung, Vertrieb U. Handel. Elektrowerkzeuge; Reparatur",
    "wof:placetype":"venue"
},
  "geometry": {"coordinates":[7.2679200172,47.1530570984],"type":"Point"}
}