{
  "type": "Feature",
  "properties": {
    "iso:country":"CH",
    "sg:address":"Hauptstrasse 1",
    "sg:city":"Schmerikon",
    "sg:orig_category":"Non-Classified Establishments",
    "sg:postcode":"8716",
    "sg:province":"St. Gallen",
    "wof:name":"Josal Holding Ag",
    "wof:placetype":"venue"
},
  "geometry": {"coordinates":[8.9408426285,47.2252693176],"type":"Point"}
}