{
  "type": "Feature",
  "properties": {
    "iso:country":"CH",
    "sg:address":"Hauptstrasse 41",
    "sg:city":"K\u00f6lliken",
    "sg:orig_category":"Spielsalons",
    "sg:phone":"+41 62 723 12 23",
    "sg:postcode":"5742",
    "sg:province":"Aargau",
    "wof:name":"Caf\u00e9 Kolibri",
    "wof:placetype":"venue"
},
  "geometry": {"coordinates":[8.0245141983,47.3346366882],"type":"Point"}
}