{
  "type": "Feature",
  "properties": {
    "addr:full":"Chalet Bramad Saanen Bern 3792",
    "addr:postcode":"3792",
    "iso:country":"CH",
    "sg:address":"Chalet Bramad",
    "sg:city":"Saanen",
    "sg:orig_category":"Betrieb von Taxis",
    "sg:phone":"+41 33 744 44 55",
    "sg:postcode":"3792",
    "sg:province":"Bern",
    "wof:name":"Ronald Schopfer Taxi",
    "wof:placetype":"venue"
},
  "geometry": {"coordinates":[7.259921,46.489792],"type":"Point"}
}