{
  "type": "Feature",
  "properties": {
    "iso:country":"CH",
    "sg:address":"Rebweg 10",
    "sg:city":"Scherzingen",
    "sg:orig_category":"Sonstige mit der Informatik verbundene T\u00e4tigkeiten",
    "sg:postcode":"8596",
    "sg:province":"Thurgau",
    "wof:name":"Evoltec Ag",
    "wof:placetype":"venue"
},
  "geometry": {"coordinates":[8.2879657745,47.4520759583],"type":"Point"}
}