{
  "type": "Feature",
  "properties": {
    "iso:country":"CH",
    "sg:address":"Strada Cantonale 6802 Rivera Casella Postale",
    "sg:city":"Rivera",
    "sg:orig_category":"Herstellung von sonstigen elektrischen Ausr\u00fcstungen",
    "sg:phone":"+41 41 910 43 32",
    "sg:postcode":"6802",
    "sg:province":"Ticino",
    "wof:name":"Pentatron Ag",
    "wof:placetype":"venue"
},
  "geometry": {"coordinates":[8.2449445724,47.1694908142],"type":"Point"}
}