{
  "type": "Feature",
  "properties": {
    "iso:country":"CH",
    "sg:address":"La Fin-d'en-haut",
    "sg:city":"Bassins",
    "sg:orig_category":"Reiseb\u00fcros Reiseb\u00fcros U Reiseveranstalter",
    "sg:phone":"+41 71 220 32 20",
    "sg:postcode":"1269",
    "sg:province":"Vaud",
    "wof:name":"Apollo Tours Arvanitidis Apostolos",
    "wof:placetype":"venue"
},
  "geometry": {"coordinates":[9.3797826767,47.4248008728],"type":"Point"}
}