{
  "type": "Feature",
  "properties": {
    "iso:country":"CH",
    "sg:address":"Wiggispark",
    "sg:city":"Netstal",
    "sg:orig_category":"Architektur U Ingenieurb\u00fcros Architekturb\u00fcros",
    "sg:phone":"+41 31 326 70 70",
    "sg:postcode":"8754",
    "sg:province":"Glarus",
    "wof:name":"Hausammann M. + Y. Architekten Ag",
    "wof:placetype":"venue"
},
  "geometry": {"coordinates":[7.457129,46.947227],"type":"Point"}
}