{
  "type": "Feature",
  "properties": {
    "iso:country":"CH",
    "sg:address":"Chamerstrasse 117",
    "sg:city":"Zug",
    "sg:orig_category":"Geb\u00e4ude, Wohnungsreinigung Reinigungsgewerbe",
    "sg:postcode":"6300",
    "sg:province":"Zug",
    "wof:name":"Reina Reinigungsservice, Kasza",
    "wof:placetype":"venue"
},
  "geometry": {"coordinates":[8.4925498962,47.1786193848],"type":"Point"}
}