{
  "type": "Feature",
  "properties": {
    "iso:country":"CH",
    "sg:address":"Augustin Kellerstrasse 12$",
    "sg:city":"Lenzburg",
    "sg:orig_category":"Herstellung von Radio U Fernsehger\u00e4ten sowie phono U videotechnischen Ger\u00e4ten",
    "sg:phone":"+41 79 602 05 10",
    "sg:postcode":"5600",
    "sg:province":"Aargau",
    "wof:name":"Soundwave Godo Laszlo",
    "wof:placetype":"venue"
},
  "geometry": {"coordinates":[8.4484939575,47.0816307068],"type":"Point"}
}