{
  "type": "Feature",
  "properties": {
    "iso:country":"CH",
    "sg:address":"Hofwiesenstrasse 96",
    "sg:city":"Regensdorf",
    "sg:orig_category":"Sonderschulen Wohnheime f\u00fcr Kinder U Jugendliche",
    "sg:phone":"+41 18401340",
    "sg:postcode":"8105",
    "sg:province":"Z\u00fcrich",
    "wof:name":"Sprachheilschule",
    "wof:placetype":"venue"
},
  "geometry": {"coordinates":[8.4730997086,47.4285697937],"type":"Point"}
}