{
  "type": "Feature",
  "properties": {
    "iso:country":"CH",
    "sg:address":"Deichstrasse 72",
    "sg:city":"Therwil",
    "sg:classifiers":[
        {
            "category":"Arena",
            "subcategory":"Sports Club",
            "type":"Entertainment"
        }
    ],
    "sg:phone":"+41 61 721 31 75",
    "sg:postcode":"4106",
    "sg:province":"Basel-Landschaft",
    "sg:tags":[
        "karate",
        "judo",
        "sportvereine"
    ],
    "wof:name":"Jc Do-yu-kan Basel",
    "wof:placetype":"venue"
},
  "geometry": {"coordinates":[7.5566749573,47.4990844727],"type":"Point"}
}