{
  "type": "Feature",
  "properties": {
    "iso:country":"CH",
    "sg:address":"1902",
    "sg:city":"Evionnaz",
    "sg:orig_category":"Interessenvertretungen",
    "sg:postcode":"1902",
    "sg:province":"Valais",
    "wof:name":"Fondation Pour La Mise \u00e0 Disposition De Terrains Industriels Dans Le Bas-valais-fibav",
    "wof:placetype":"venue"
},
  "geometry": {"coordinates":[7.0232758522,46.1770515442],"type":"Point"}
}