{
  "type": "Feature",
  "properties": {
    "iso:country":"CH",
    "sg:address":"Herrenweg 11",
    "sg:city":"Solothurn",
    "sg:orig_category":"Sonstige mit der Informatik verbundene T\u00e4tigkeiten",
    "sg:phone":"+41 32 685 61 91",
    "sg:postcode":"4500",
    "sg:province":"Solothurn",
    "wof:name":"Systemhaus F\u00fcr Integration Gmbh",
    "wof:placetype":"venue"
},
  "geometry": {"coordinates":[7.5349488258,47.214805603],"type":"Point"}
}