{
  "type": "Feature",
  "properties": {
    "iso:country":"CH",
    "sg:address":"Chasseralstrasse 156",
    "sg:city":"Spiegel",
    "sg:classifiers":[
        {
            "category":"Banks & Credit Unions",
            "subcategory":"Bank",
            "type":"Services"
        }
    ],
    "sg:phone":"+41 31 971 91 22",
    "sg:postcode":"3095",
    "sg:province":"Bern",
    "wof:name":"Schweiz. Bankgesellschaft",
    "wof:placetype":"venue"
},
  "geometry": {"coordinates":[7.433615,46.926495],"type":"Point"}
}