{
  "type": "Feature",
  "properties": {
    "iso:country":"CH",
    "sg:address":"Caratti Via 2",
    "sg:city":"Bellinzona",
    "sg:orig_category":"Herstellung von Schmuck, Gold U Silberschmiedwaren",
    "sg:postcode":"6500",
    "sg:province":"Ticino",
    "wof:name":"Rovelli Giuseppe",
    "wof:placetype":"venue"
},
  "geometry": {"coordinates":[9.0241193771,46.1944618225],"type":"Point"}
}