{
  "type": "Feature",
  "properties": {
    "iso:country":"CH",
    "sg:address":"Bollerweg 50",
    "sg:city":"W\u00e4denswil",
    "sg:orig_category":"Innendekorationsateliers",
    "sg:phone":"+41 17803206",
    "sg:postcode":"8820",
    "sg:province":"Z\u00fcrich",
    "wof:name":"Atelier Giardino Wohninspirationen",
    "wof:placetype":"venue"
},
  "geometry": {"coordinates":[8.6832370758,47.2219848633],"type":"Point"}
}