{
  "type": "Feature",
  "properties": {
    "iso:country":"CH",
    "sg:address":"B\u00e4rmattweg 8",
    "sg:city":"Hindelbank",
    "sg:orig_category":"Satzherstellung U Reproduktion",
    "sg:phone":"+41 34 411 00 77",
    "sg:postcode":"3324",
    "sg:province":"Bern",
    "wof:name":"L\u00e4derach Repro Ag",
    "wof:placetype":"venue"
},
  "geometry": {"coordinates":[7.5430397987,47.0504760742],"type":"Point"}
}