{
  "type": "Feature",
  "properties": {
    "iso:country":"CH",
    "sg:address":"Adlikerstrasse 236 8105 Regensdorf. Postfach",
    "sg:city":"Regensdorf",
    "sg:orig_category":"HERSTELLUNG VON GER\u00c4TEN DER ELEKTRIZIT\u00c4TSERZEUGUNG, -VERTEILUNG U.\u00c4 Herstellung von Mess U Kontrolli",
    "sg:phone":"+41 18712500",
    "sg:postcode":"8105",
    "sg:province":"Z\u00fcrich",
    "wof:name":"Berthold Technologies (schweiz) Gmbh Wissenschaftlich-technische Mess, Pr\u00fcf, Hilfsger\u00e4te, Bes. Wissenschaftliche Instrumente F\u00fcr Physikalische Forschung Usw.; Vertrieb",
    "wof:placetype":"venue"
},
  "geometry": {"coordinates":[8.4645957947,47.4415473938],"type":"Point"}
}