{
  "type": "Feature",
  "properties": {
    "iso:country":"CH",
    "sg:address":"Langackerstrasse 8",
    "sg:city":"M\u00e4nnedorf",
    "sg:classifiers":[
        {
            "category":"Restaurant",
            "type":"Food & Drink"
        }
    ],
    "sg:phone":"+41 19204591",
    "sg:postcode":"8708",
    "sg:province":"Z\u00fcrich",
    "wof:name":"Restaurant Neugut",
    "wof:placetype":"venue"
},
  "geometry": {"coordinates":[8.688533783,47.2553977966],"type":"Point"}
}