{
  "type": "Feature",
  "properties": {
    "iso:country":"CH",
    "sg:address":"Rue Du Cardinal-journet 5",
    "sg:city":"Meyrin",
    "sg:orig_category":"Detailhandel mit elektrischen Haushalts-,Radio U Fernsehger\u00e4ten sowie Musikinstrumenten Grosshandel ",
    "sg:phone":"+41 22 782 02 25",
    "sg:postcode":"1217",
    "sg:province":"Gen\u00e8ve",
    "wof:name":"Avisys Audio-visual System Sa",
    "wof:placetype":"venue"
},
  "geometry": {"coordinates":[6.084126,46.223408],"type":"Point"}
}