{
  "type": "Feature",
  "properties": {
    "iso:country":"CH",
    "sg:address":"Adlibogenstrasse 16 8155 Niederhasli. Postfach",
    "sg:city":"Niederhasli",
    "sg:orig_category":"Handelsvermittlung U Grosshandel Sonstiger Grosshandel",
    "sg:phone":"+41 18504121",
    "sg:postcode":"8155",
    "sg:province":"Z\u00fcrich",
    "wof:name":"We\u00acwe Intertrade Sa",
    "wof:placetype":"venue"
},
  "geometry": {"coordinates":[8.4945497513,47.4802932739],"type":"Point"}
}