{
  "type": "Feature",
  "properties": {
    "iso:country":"CH",
    "sg:address":"Wettsteinallee 42 4058 Basel. Postfach",
    "sg:city":"Basel",
    "sg:orig_category":"Gesundheitswesen",
    "sg:postcode":"4051",
    "sg:province":"Basel-Stadt",
    "wof:name":"Betagten Und Krankenbetreuung Loosen",
    "wof:placetype":"venue"
},
  "geometry": {"coordinates":[7.5639939308,46.9336929321],"type":"Point"}
}