{
  "type": "Feature",
  "properties": {
    "iso:country":"CH",
    "sg:address":"Oelegasse 1",
    "sg:city":"Kerzers",
    "sg:orig_category":"Gartenbau",
    "sg:phone":"+41 31 755 58 55",
    "sg:postcode":"3210",
    "sg:province":"Fribourg",
    "wof:name":"Bernhard Meyer Gartengestaltung",
    "wof:placetype":"venue"
},
  "geometry": {"coordinates":[7.201529026,46.9738349915],"type":"Point"}
}