{
  "type": "Feature",
  "properties": {
    "iso:country":"CH",
    "sg:address":"Rue Du Village",
    "sg:city":"Bramois",
    "sg:classifiers":[
        {
            "category":"Restaurant",
            "type":"Food & Drink"
        }
    ],
    "sg:phone":"+41 27 203 12 95",
    "sg:postcode":"1967",
    "sg:province":"Valais",
    "wof:name":"Caf\u00e9 Avenue",
    "wof:placetype":"venue"
},
  "geometry": {"coordinates":[7.4049649239,46.2329978943],"type":"Point"}
}