{
  "type": "Feature",
  "properties": {
    "iso:country":"CH",
    "sg:address":"Loco Via 2",
    "sg:city":"Pregassona",
    "sg:orig_category":"Unclassifiable Establishments",
    "sg:postcode":"6963",
    "sg:province":"Ticino",
    "wof:name":"Restauredil Sa",
    "wof:placetype":"venue"
},
  "geometry": {"coordinates":[8.9726696014,46.022518158],"type":"Point"}
}