{
  "type": "Feature",
  "properties": {
    "iso:country":"CH",
    "sg:address":"Ruchstuckstrasse 14",
    "sg:city":"Br\u00fcttisellen",
    "sg:orig_category":"Geb\u00e4ude, Wohnungsreinigung Sonstige mit der Informatik verbundene T\u00e4tigkeiten",
    "sg:phone":"+41 79 631 19 17",
    "sg:postcode":"8306",
    "sg:province":"Z\u00fcrich",
    "wof:name":"Acc Arn Computer Clean Service",
    "wof:placetype":"venue"
},
  "geometry": {"coordinates":[7.5546331406,47.2522277832],"type":"Point"}
}