{
  "type": "Feature",
  "properties": {
    "iso:country":"CH",
    "sg:address":"Gartenstrasse 118 4052 Basel. Postfach",
    "sg:city":"Basel",
    "sg:orig_category":"Detailhandel mit M\u00f6beln",
    "sg:phone":"+41 22 361 21 29",
    "sg:postcode":"4002",
    "sg:province":"Basel-Stadt",
    "wof:name":"Luthi Sa Meubles",
    "wof:placetype":"venue"
},
  "geometry": {"coordinates":[6.2376308441,46.3835067749],"type":"Point"}
}