{
  "type": "Feature",
  "properties": {
    "iso:country":"CH",
    "sg:address":"Schlossstrasse 5 4133 Pratteln. Postfach",
    "sg:city":"Pratteln",
    "sg:orig_category":"Herstellung von sonstigen Nahrungsmitteln",
    "sg:phone":"+41 61 821 31 65",
    "sg:postcode":"4133",
    "sg:province":"Basel-Landschaft",
    "wof:name":"Charles Hartmann Aktiengesellschaft",
    "wof:placetype":"venue"
},
  "geometry": {"coordinates":[7.6945171356,47.5221443176],"type":"Point"}
}