{
  "type": "Feature",
  "properties": {
    "iso:country":"CH",
    "sg:address":"Grand-rue 51",
    "sg:city":"Courtelary",
    "sg:orig_category":"Verwertung von Milch",
    "sg:postcode":"2608",
    "sg:province":"Bern",
    "wof:name":"K\u00e4mpf Harald",
    "wof:placetype":"venue"
},
  "geometry": {"coordinates":[7.0721039772,47.1780853271],"type":"Point"}
}