{
  "type": "Feature",
  "properties": {
    "iso:country":"CH",
    "sg:address":"Chemin De Prahys 24 1091 Grandvaux. Postfach",
    "sg:city":"Grandvaux",
    "sg:orig_category":"Sonstige mit der Informatik verbundene T\u00e4tigkeiten",
    "sg:postcode":"1091",
    "sg:province":"Vaud",
    "wof:name":"Cryptme S\u00e0rl",
    "wof:placetype":"venue"
},
  "geometry": {"coordinates":[6.7193598747,46.4979553223],"type":"Point"}
}