{
  "type": "Feature",
  "properties": {
    "iso:country":"CH",
    "sg:address":"Baselstrasse 151",
    "sg:city":"Muttenz",
    "sg:orig_category":"Sonstiger Grosshandel",
    "sg:phone":"+41 79 415 81 00",
    "sg:postcode":"4132",
    "sg:province":"Basel-Landschaft",
    "wof:name":"Mencora K\u00e4mpfer",
    "wof:placetype":"venue"
},
  "geometry": {"coordinates":[7.6336989403,47.530040741],"type":"Point"}
}