{
  "type": "Feature",
  "properties": {
    "iso:country":"CH",
    "sg:address":"Saumacherstrasse 16",
    "sg:city":"Effretikon",
    "sg:orig_category":"Betrieb von Taxis",
    "sg:phone":"+41 52 343 43 43",
    "sg:postcode":"8307",
    "sg:province":"Z\u00fcrich",
    "wof:name":"Effi-taxi T. & V. Dinkel",
    "wof:placetype":"venue"
},
  "geometry": {"coordinates":[8.682977,47.425789],"type":"Point"}
}