{
  "type": "Feature",
  "properties": {
    "iso:country":"CH",
    "sg:address":"Via Madonnetta 17",
    "sg:city":"Lugano",
    "sg:orig_category":"Architekturb\u00fcros",
    "sg:phone":"+41 91 923 41 44",
    "sg:postcode":"6900",
    "sg:province":"Ticino",
    "wof:name":"Alvaro B\u00fchring Studio D'architettura",
    "wof:placetype":"venue"
},
  "geometry": {"coordinates":[8.957611,46.011684],"type":"Point"}
}