{
  "type": "Feature",
  "properties": {
    "addr:full":"Weidweg 1 Rothrist Aargau 4852",
    "addr:housenumber":"1",
    "addr:postcode":"4852",
    "addr:street":"Weidweg",
    "iso:country":"CH",
    "sg:address":"Weidweg 1",
    "sg:city":"Rothrist",
    "sg:orig_category":"Blumen U Zierpflanzenbau",
    "sg:phone":"+41 62 794 10 33",
    "sg:postcode":"4852",
    "sg:province":"Aargau",
    "wof:name":"Werner B\u00fchler Friedhofg\u00e4rtnerei",
    "wof:placetype":"venue"
},
  "geometry": {"coordinates":[7.891723,47.301952],"type":"Point"}
}