{
  "type": "Feature",
  "properties": {
    "iso:country":"CH",
    "sg:address":"Geissr\u00fcttiweg 20",
    "sg:city":"Oberburg",
    "sg:orig_category":"Non-Classified Establishments",
    "sg:postcode":"3414",
    "sg:province":"Bern",
    "wof:name":"Kundenmaurer Und Pl\u00e4ttlileger Walter Jost",
    "wof:placetype":"venue"
},
  "geometry": {"coordinates":[7.6321258545,47.0381851196],"type":"Point"}
}