{
  "type": "Feature",
  "properties": {
    "iso:country":"CH",
    "sg:city":"Z\u00fcrich",
    "sg:orig_category":"Immobilien U Baugewerbe, Architektur U Design",
    "sg:postcode":"8046",
    "sg:province":"Z\u00fcrich",
    "wof:name":"Architekten Virtual-home",
    "wof:placetype":"venue"
},
  "geometry": {"coordinates":[8.50973,47.419498],"type":"Point"}
}