{
  "type": "Feature",
  "properties": {
    "iso:country":"CH",
    "sg:address":"Gewerbestrasse 4 3532 Z\u00e4ziwil. Postfach",
    "sg:city":"Z\u00e4ziwil",
    "sg:orig_category":"Maler U Glasergewerbe Stukkateurgewerbe, Gipserei U Verputzerei",
    "sg:phone":"+41 79 415 22 14",
    "sg:postcode":"3532",
    "sg:province":"Bern",
    "wof:name":"Hans K\u00fcenzi",
    "wof:placetype":"venue"
},
  "geometry": {"coordinates":[7.6592531204,46.8966217041],"type":"Point"}
}