{
  "type": "Feature",
  "properties": {
    "iso:country":"CH",
    "sg:address":"Wingreis",
    "sg:city":"Twann",
    "sg:orig_category":"Interessenvertretungen",
    "sg:phone":"+41 32 315 22 91",
    "sg:postcode":"2513",
    "sg:province":"Bern",
    "wof:name":"Stiftung Rebhaus Wingreis",
    "wof:placetype":"venue"
},
  "geometry": {"coordinates":[7.1769728661,47.1025657654],"type":"Point"}
}