{
  "type": "Feature",
  "properties": {
    "iso:country":"CH",
    "sg:address":"Obergasse 12",
    "sg:city":"Bischofszell",
    "sg:orig_category":"Detailhandel mit elektrischen Haushalts, Radio U Fernsehger\u00e4ten ohne ausgepr\u00e4gten Schwerpunkt Elektr",
    "sg:phone":"+41 71 422 12 73",
    "sg:postcode":"9220",
    "sg:province":"Thurgau",
    "wof:name":"Elektro Engeler",
    "wof:placetype":"venue"
},
  "geometry": {"coordinates":[9.2423038483,47.4938774109],"type":"Point"}
}