{
  "type": "Feature",
  "properties": {
    "iso:country":"CH",
    "sg:address":"Rue Louis-favre 21 1200 Gen\u00e8ve. Postfach",
    "sg:city":"Gen\u00e8ve",
    "sg:orig_category":"Fussboden, Fliesen U Plattenlegerei, Tapeziererei",
    "sg:postcode":"1201",
    "sg:province":"Gen\u00e8ve",
    "wof:name":"Entreprise De Parquet Et De Nettoyage Gende",
    "wof:placetype":"venue"
},
  "geometry": {"coordinates":[6.1373729706,46.2112617493],"type":"Point"}
}