{
  "type": "Feature",
  "properties": {
    "iso:country":"CH",
    "sg:address":"Hauptstr. 148",
    "sg:city":"Ormalingen",
    "sg:orig_category":"RESTAURANTS: TEA-ROOMS",
    "sg:postcode":"4466",
    "sg:province":"Basel-Landschaft",
    "wof:name":"B\u00fcrgin-b\u00f6hmer Ingrid",
    "wof:placetype":"venue"
},
  "geometry": {"coordinates":[7.8758997917,47.4686775208],"type":"Point"}
}