{
  "type": "Feature",
  "properties": {
    "iso:country":"CH",
    "sg:address":"1618",
    "sg:city":"Ch\u00e2tel-st-denis",
    "sg:orig_category":"Architektur U Ingenieurb\u00fcros",
    "sg:postcode":"1618",
    "sg:province":"Fribourg",
    "wof:name":"Volveton Management Ltd Wilmington, Succursale De Ch\u00e2tel-st-denis",
    "wof:placetype":"venue"
},
  "geometry": {"coordinates":[6.90154,46.527534],"type":"Point"}
}