{
  "type": "Feature",
  "properties": {
    "iso:country":"CH",
    "sg:address":"Bettingerstrasse 3",
    "sg:city":"Riehen",
    "sg:orig_category":"Architekturb\u00fcros",
    "sg:phone":"+41 61 641 39 33",
    "sg:postcode":"4125",
    "sg:province":"Basel-Stadt",
    "wof:name":"Rolf Br\u00fcderlin Dipl.architekt Sia",
    "wof:placetype":"venue"
},
  "geometry": {"coordinates":[7.648051,47.58268],"type":"Point"}
}