{
  "type": "Feature",
  "properties": {
    "iso:country":"CH",
    "sg:address":"Industrie Rue De L' 44",
    "sg:city":"Sion",
    "sg:orig_category":"Herstellung von Anstrichmitteln, Druckfarben U Kitten",
    "sg:phone":"+41 27 323 46 82",
    "sg:postcode":"1950",
    "sg:province":"Valais",
    "wof:name":"Commerce De Peinture Amoval S\u00e0rl Couleurs - Vernis",
    "wof:placetype":"venue"
},
  "geometry": {"coordinates":[7.3685722351,46.2284126282],"type":"Point"}
}