{
  "type": "Feature",
  "properties": {
    "iso:country":"CH",
    "sg:address":"Piazza Teatro",
    "sg:city":"Bellinzona",
    "sg:orig_category":"Fachdetailhandel mit pharmazeutischen Produkten",
    "sg:phone":"+41 91 825 81 01",
    "sg:postcode":"6500",
    "sg:province":"Ticino",
    "wof:name":"Farmacia Teatro Di Montalbetti Flavio",
    "wof:placetype":"venue"
},
  "geometry": {"coordinates":[9.0220098495,46.1910552979],"type":"Point"}
}