{
  "type": "Feature",
  "properties": {
    "iso:country":"CH",
    "sg:address":"Birmannsgasse 12",
    "sg:city":"Basel",
    "sg:orig_category":"Vermittlung von Immobilien Verwaltung von Immobilien",
    "sg:phone":"+41 41 422 08 00",
    "sg:postcode":"4055",
    "sg:province":"Basel-Stadt",
    "wof:name":"W\u00e4smeli Treuhand Robert Zoller Ag Steuer, Betriebs- U. Unternehmerberatung",
    "wof:placetype":"venue"
},
  "geometry": {"coordinates":[8.3194522858,47.0635986328],"type":"Point"}
}