{
  "type": "Feature",
  "properties": {
    "iso:country":"CH",
    "sg:address":"Saumackerstrasse 12",
    "sg:city":"Z\u00fcrich",
    "sg:orig_category":"Anticorrosives",
    "sg:phone":"+41 14312150",
    "sg:postcode":"8048",
    "sg:province":"Z\u00fcrich",
    "wof:name":"Ks Korrosionsschutz Ag",
    "wof:placetype":"venue"
},
  "geometry": {"coordinates":[8.489219,47.390045],"type":"Point"}
}