{
  "type": "Feature",
  "properties": {
    "iso:country":"CH",
    "sg:address":"Sauverny Rte De 6",
    "sg:city":"Versoix",
    "sg:orig_category":"Betrieb U technische Hilfsdienste des Kultur U Unterhaltungswesens",
    "sg:postcode":"1290",
    "sg:province":"Gen\u00e8ve",
    "wof:name":"Meca Business Sa",
    "wof:placetype":"venue"
},
  "geometry": {"coordinates":[6.1648240089,46.2838439941],"type":"Point"}
}