{
  "type": "Feature",
  "properties": {
    "iso:country":"CH",
    "sg:address":"Im Stadelacker 3",
    "sg:city":"Arnegg",
    "sg:orig_category":"Detailhandel mit M\u00f6beln U Haushaltsgegenst\u00e4nden Handelsvermittlung von M\u00f6beln, Einrichtungs U Hausha",
    "sg:phone":"+41 71 383 29 00",
    "sg:postcode":"9212",
    "sg:province":"St. Gallen",
    "wof:name":"Arco-vertretungen Gmbh",
    "wof:placetype":"venue"
},
  "geometry": {"coordinates":[9.2569656372,47.4404411316],"type":"Point"}
}