{
  "type": "Feature",
  "properties": {
    "iso:country":"CH",
    "sg:address":"Arnold Baumgartner-strasse 9",
    "sg:city":"Grenchen",
    "sg:orig_category":"Detailhandel mit elektrischen Haushalts-,Radio U Fernsehger\u00e4ten sowie Musikinstrumenten Verlag von b",
    "sg:phone":"+41 18882606",
    "sg:postcode":"2540",
    "sg:province":"Solothurn",
    "wof:name":"Viteka Music Ag",
    "wof:placetype":"venue"
},
  "geometry": {"coordinates":[8.6437921524,47.4144477844],"type":"Point"}
}