{
  "type": "Feature",
  "properties": {
    "iso:country":"CH",
    "sg:address":"Brunnenhofstr. 6",
    "sg:city":"Bolligen",
    "sg:orig_category":"Detailhandel mit elektrischen Haushalts-,Radio U Fernsehger\u00e4ten sowie Musikinstrumenten",
    "sg:phone":"+41 81721808",
    "sg:postcode":"3065",
    "sg:province":"Bern",
    "wof:name":"Kollegger Beat",
    "wof:placetype":"venue"
},
  "geometry": {"coordinates":[9.646695137,46.6786651611],"type":"Point"}
}