{
  "type": "Feature",
  "properties": {
    "iso:country":"CH",
    "sg:address":"Weinplatz 7",
    "sg:city":"Z\u00fcrich",
    "sg:orig_category":"Detailhandel mit Uhren U Schmuck",
    "sg:phone":"+41 12110704",
    "sg:postcode":"8001",
    "sg:province":"Z\u00fcrich",
    "wof:name":"Spitzbarth Am Weinplatz",
    "wof:placetype":"venue"
},
  "geometry": {"coordinates":[8.5415887833,47.3715400696],"type":"Point"}
}