{
  "type": "Feature",
  "properties": {
    "iso:country":"CH",
    "sg:address":"Hauptstrasse 12",
    "sg:city":"Lyss",
    "sg:orig_category":"B\u00e4ckereien Konditoreien",
    "sg:phone":"+41 32 384 13 59",
    "sg:postcode":"3250",
    "sg:province":"Bern",
    "wof:name":"Fam. Burkhard B\u00e4ckerei-konditorei",
    "wof:placetype":"venue"
},
  "geometry": {"coordinates":[7.306896,47.073318],"type":"Point"}
}