{
  "type": "Feature",
  "properties": {
    "addr:full":"S\u00e4gereistrasse 25 Glattbrugg Z\u00fcrich 8152",
    "addr:housenumber":"25",
    "addr:postcode":"8152",
    "addr:street":"Saegereistrasse",
    "iso:country":"CH",
    "sg:address":"S\u00e4gereistrasse 25",
    "sg:city":"Glattbrugg",
    "sg:orig_category":"Buchverlag Verlagsgewerbe",
    "sg:phone":"+41 18093111",
    "sg:postcode":"8152",
    "sg:province":"Z\u00fcrich",
    "wof:name":"Verlagsgesellschaft Pro Ag",
    "wof:placetype":"venue"
},
  "geometry": {"coordinates":[8.55925,47.432011],"type":"Point"}
}