{
  "type": "Feature",
  "properties": {
    "addr:full":"B\u00fcglgrond Scuol Graubunden 7550",
    "addr:postcode":"7550",
    "addr:street":"Bueglgrond;Graubunden",
    "iso:country":"CH",
    "sg:address":"B\u00fcglgrond",
    "sg:city":"Scuol",
    "sg:orig_category":"Architektur U Ingenieurb\u00fcros",
    "sg:postcode":"7550",
    "sg:province":"Graubunden",
    "wof:name":"Design, Architectura, Gastronomia Rauch J.a. Rauch & Co",
    "wof:placetype":"venue"
},
  "geometry": {"coordinates":[10.29817,46.795601],"type":"Point"}
}