{
  "type": "Feature",
  "properties": {
    "iso:country":"CH",
    "sg:address":"Rue Du Centre 10",
    "sg:city":"Crissier",
    "sg:orig_category":"Grosshandel mit lebenden Tieren",
    "sg:phone":"+41 21 634 05 34",
    "sg:postcode":"1023",
    "sg:province":"Vaud",
    "wof:name":"L\u00e9vy Pierre.",
    "wof:placetype":"venue"
},
  "geometry": {"coordinates":[6.5772600174,46.5531921387],"type":"Point"}
}