{
  "type": "Feature",
  "properties": {
    "iso:country":"CH",
    "sg:address":"Via Mario J\u00e4ggli 1",
    "sg:city":"Bellinzona",
    "sg:orig_category":"Herstellung von Tanks U Sammelbeh\u00e4ltern aus Metall",
    "sg:phone":"+41 91 825 64 87",
    "sg:postcode":"6500",
    "sg:province":"Ticino",
    "wof:name":"Giuseppe Tramontana Revisione Cisterne",
    "wof:placetype":"venue"
},
  "geometry": {"coordinates":[9.0257806778,46.2045974731],"type":"Point"}
}