{
  "type": "Feature",
  "properties": {
    "iso:country":"CH",
    "sg:address":"Schiffenen Route De 9a",
    "sg:city":"Freiburg",
    "sg:orig_category":"Softwareentwicklung U beratung",
    "sg:postcode":"1700",
    "sg:province":"Fribourg",
    "wof:name":"Alcoda S\u00e0rl",
    "wof:placetype":"venue"
},
  "geometry": {"coordinates":[7.1733179092,46.8156356812],"type":"Point"}
}