{
  "type": "Feature",
  "properties": {
    "iso:country":"CH",
    "sg:address":"2545",
    "sg:city":"Selzach",
    "sg:orig_category":"Verwertung von Milch",
    "sg:postcode":"2545",
    "sg:province":"Solothurn",
    "wof:name":"Milchgenossenschaft Altreu.",
    "wof:placetype":"venue"
},
  "geometry": {"coordinates":[7.4574799538,47.2030410767],"type":"Point"}
}