{
  "type": "Feature",
  "properties": {
    "addr:full":"Europastrasse 15 Reinach Aargau 5734",
    "addr:housenumber":"15",
    "addr:postcode":"5734",
    "addr:street":"Europastrasse",
    "iso:country":"CH",
    "sg:address":"Europastrasse 15",
    "sg:city":"Reinach",
    "sg:orig_category":"Basic Ingredients For Marinades",
    "sg:phone":"+41 62 765 42 42",
    "sg:postcode":"5734",
    "sg:province":"Aargau",
    "wof:name":"I.f.f. (schweiz) Ag",
    "wof:placetype":"venue"
},
  "geometry": {"coordinates":[8.177127,47.263592],"type":"Point"}
}