{
  "type": "Feature",
  "properties": {
    "iso:country":"CH",
    "sg:address":"Knospenweg 7",
    "sg:city":"Gerolfingen",
    "sg:orig_category":"Sonstige mit der Informatik verbundene T\u00e4tigkeiten",
    "sg:phone":"+41 32 396 31 25",
    "sg:postcode":"2575",
    "sg:province":"Bern",
    "wof:name":"Kuich Edv-consulting Gmbh",
    "wof:placetype":"venue"
},
  "geometry": {"coordinates":[7.1982970238,47.0727081299],"type":"Point"}
}