{
  "type": "Feature",
  "properties": {
    "iso:country":"CH",
    "sg:address":"1662",
    "sg:city":"Mol\u00e9son-village",
    "sg:orig_category":"Sonstige Kultur U Unterhaltungseinrichtungen",
    "sg:phone":"+41 26 921 32 97",
    "sg:postcode":"1662",
    "wof:name":"Centre Sportif Tennis Minigolf Bob Luge",
    "wof:placetype":"venue"
},
  "geometry": {"coordinates":[7.0377101898,46.5613098145],"type":"Point"}
}