{
  "type": "Feature",
  "properties": {
    "iso:country":"CH",
    "sg:address":"Chemin Du Ch\u00e2teau-sec 6 1510 Moudon. Postfach",
    "sg:city":"Moudon",
    "sg:orig_category":"Allgemeiner Hoch U Tiefbau Allgemeiner Hochbau",
    "sg:phone":"+41 21 905 15 88",
    "sg:postcode":"1510",
    "sg:province":"Vaud",
    "wof:name":"Gabarits Construction S\u00e0rl Travaux D'implantation De B\u00e2timents, De Construction, D'achat Etc",
    "wof:placetype":"venue"
},
  "geometry": {"coordinates":[6.794663,46.666718],"type":"Point"}
}