{
  "type": "Feature",
  "properties": {
    "iso:country":"CH",
    "sg:address":"Alpsteinstrasse 68",
    "sg:city":"Herisau",
    "sg:orig_category":"Bauschreinerei Sonstiger Detailhandel mit Metallwaren, Anstrichmitteln, Glaswaren, Bau U Heimwerkerb",
    "sg:phone":"+41 34 445 34 60",
    "sg:postcode":"9100",
    "sg:province":"Appenzell Ausserrhoden",
    "wof:name":"Hans M\u00fchlemann Schreinerei",
    "wof:placetype":"venue"
},
  "geometry": {"coordinates":[7.58658,47.086334],"type":"Point"}
}