{
  "type": "Feature",
  "properties": {
    "iso:country":"CH",
    "sg:address":"3437 R\u00fcderswil. Postfach",
    "sg:city":"Zollbr\u00fcck",
    "sg:orig_category":"Pensionskassen",
    "sg:postcode":"3436",
    "sg:province":"Bern",
    "wof:name":"Personalf\u00fcrsorgestiftung Der Firma Maeder Ag, Landesprodukte Zollbr\u00fcck",
    "wof:placetype":"venue"
},
  "geometry": {"coordinates":[7.7137498856,46.9802093506],"type":"Point"}
}