{
  "type": "Feature",
  "properties": {
    "iso:country":"CH",
    "sg:address":"Route De Riddes",
    "sg:city":"Sion",
    "sg:orig_category":"Handelsvermittlung U Grosshandel",
    "sg:phone":"+41 27 203 30 41",
    "sg:postcode":"1950",
    "sg:province":"Valais",
    "wof:name":"K\u00e4ssbohrer Gel\u00e4ndefahrzeug Ag",
    "wof:placetype":"venue"
},
  "geometry": {"coordinates":[7.3662347794,46.222076416],"type":"Point"}
}