{
  "type": "Feature",
  "properties": {
    "iso:country":"CH",
    "sg:address":"Gide Chemin Charles- 2 1006 Lausanne. Postfach",
    "sg:city":"Lausanne",
    "sg:orig_category":"Softwareentwicklung U beratung",
    "sg:postcode":"1003",
    "sg:province":"Vaud",
    "wof:name":"Dekyd, Trabelsi Khedidher",
    "wof:placetype":"venue"
},
  "geometry": {"coordinates":[6.6383509636,46.5114212036],"type":"Point"}
}