{
  "type": "Feature",
  "properties": {
    "iso:country":"CH",
    "sg:address":"Alpenstrasse 14",
    "sg:city":"Zug",
    "sg:orig_category":"Non-Classified Establishments",
    "sg:postcode":"6300",
    "sg:province":"Zug",
    "wof:name":"Seer Gmbh Dichtungstechnik",
    "wof:placetype":"venue"
},
  "geometry": {"coordinates":[8.2003889084,47.4743995667],"type":"Point"}
}