{
  "type": "Feature",
  "properties": {
    "iso:country":"CH",
    "sg:address":"3804",
    "sg:city":"Habkern",
    "sg:classifiers":[
        {
            "category":"Restaurant",
            "type":"Food & Drink"
        }
    ],
    "sg:phone":"+41 27 957 31 21",
    "sg:postcode":"3804",
    "sg:province":"Bern",
    "wof:name":"Restaurant Alpenblick",
    "wof:placetype":"venue"
},
  "geometry": {"coordinates":[7.933672905,46.1117172241],"type":"Point"}
}