{
  "type": "Feature",
  "properties": {
    "iso:country":"CH",
    "sg:address":"Bankstrasse 9 8610 Uster. Postfach",
    "sg:city":"Uster",
    "sg:orig_category":"Erbringung von Dienstleistungen f\u00fcr Unternehmen",
    "sg:phone":"+41 19354648",
    "sg:postcode":"8610",
    "sg:province":"Z\u00fcrich",
    "wof:name":"Ehrsam Rolf Einrichtungs-design",
    "wof:placetype":"venue"
},
  "geometry": {"coordinates":[8.7605133057,47.3102149963],"type":"Point"}
}