{
  "type": "Feature",
  "properties": {
    "iso:country":"CH",
    "sg:address":"Via Magoria",
    "sg:city":"Bellinzona",
    "sg:orig_category":"Massagestudios Solarien",
    "sg:phone":"+41 62 771 85 71",
    "sg:postcode":"6500",
    "sg:province":"Ticino",
    "wof:name":"Sun House Sauna Solarium & Masseur",
    "wof:placetype":"venue"
},
  "geometry": {"coordinates":[8.2070322037,47.2640304565],"type":"Point"}
}