{
  "type": "Feature",
  "properties": {
    "iso:country":"CH",
    "sg:address":"Tannackerstrasse 14",
    "sg:city":"D\u00fcrnten",
    "sg:orig_category":"Erschliessung von Grundst\u00fccken",
    "sg:postcode":"8635",
    "sg:province":"Z\u00fcrich",
    "wof:name":"Wohngenossenschaft Tannacker, Tann-d\u00fcrnten",
    "wof:placetype":"venue"
},
  "geometry": {"coordinates":[8.8508558273,47.2683792114],"type":"Point"}
}