{
  "type": "Feature",
  "properties": {
    "iso:country":"CH",
    "sg:address":"Moosgasse 7",
    "sg:city":"M\u00fcntschemier",
    "sg:orig_category":"Detailhandel mit Schuhen Reparatur von Schuhen U Lederwaren",
    "sg:phone":"+41 32 313 18 35",
    "sg:postcode":"3225",
    "sg:province":"Bern",
    "wof:name":"Hans Siegfried",
    "wof:placetype":"venue"
},
  "geometry": {"coordinates":[7.146613121,46.9944267273],"type":"Point"}
}