{
  "type": "Feature",
  "properties": {
    "iso:country":"CH",
    "sg:address":"Laupenstrasse 5 3008 Bern. Postfach 6575",
    "sg:city":"Bern",
    "sg:orig_category":"Interessenvertretungen U sonstige Vereinigungen Organisationen der Wohlfahrtspflege",
    "sg:phone":"+41 41 410 91 39",
    "sg:postcode":"3001",
    "sg:province":"Bern",
    "wof:name":"Kolping-stiftung",
    "wof:placetype":"venue"
},
  "geometry": {"coordinates":[8.2998981476,47.0531806946],"type":"Point"}
}