{
  "type": "Feature",
  "properties": {
    "addr:full":"W\u00f6lferstrasse 18 F\u00fcllinsdorf Basel-Landschaft 4414",
    "addr:housenumber":"18",
    "addr:postcode":"4414",
    "addr:street":"Woelferstrasse",
    "iso:country":"CH",
    "sg:address":"W\u00f6lferstrasse 18",
    "sg:city":"F\u00fcllinsdorf",
    "sg:orig_category":"Architekturb\u00fcros",
    "sg:phone":"+41 61 836 85 85",
    "sg:postcode":"4414",
    "sg:province":"Basel-Landschaft",
    "wof:name":"Walter Winter Architekturb\u00fcro",
    "wof:placetype":"venue"
},
  "geometry": {"coordinates":[7.967735,47.539661],"type":"Point"}
}