{
  "type": "Feature",
  "properties": {
    "iso:country":"CH",
    "sg:address":"Via San Gottardo",
    "sg:city":"Muralto",
    "sg:orig_category":"Reiseb\u00fcros U Reiseveranstalter",
    "sg:phone":"+41 91 743 37 55",
    "sg:postcode":"6600",
    "sg:province":"Ticino",
    "wof:name":"Elvistours Di Hartmann Ghezzi Petra",
    "wof:placetype":"venue"
},
  "geometry": {"coordinates":[8.8092098236,46.1749000549],"type":"Point"}
}