{
  "type": "Feature",
  "properties": {
    "iso:country":"CH",
    "sg:address":"Lerzenstrasse 5b",
    "sg:city":"Dietikon",
    "sg:orig_category":"Autolackierereien",
    "sg:phone":"+41 17408805",
    "sg:postcode":"8953",
    "sg:province":"Z\u00fcrich",
    "wof:name":"Enea Foletti Autospritzwerk",
    "wof:placetype":"venue"
},
  "geometry": {"coordinates":[8.399095,47.415119],"type":"Point"}
}