{
  "type": "Feature",
  "properties": {
    "iso:country":"CH",
    "sg:address":"Dornacherstrasse 270",
    "sg:city":"Basel",
    "sg:orig_category":"Non-Classified Establishments",
    "sg:postcode":"4053",
    "sg:province":"Basel-Stadt",
    "wof:name":"Golf & Country Club De La Largue Holding Ag",
    "wof:placetype":"venue"
},
  "geometry": {"coordinates":[7.5985131264,47.540145874],"type":"Point"}
}