{
  "type": "Feature",
  "properties": {
    "iso:country":"CH",
    "sg:address":"Via Delle Querce 23",
    "sg:city":"Ascona",
    "sg:orig_category":"Sportvereine Ballsport Tennis",
    "sg:phone":"+41 91 791 24 49",
    "sg:postcode":"6612",
    "sg:province":"Ticino",
    "wof:name":"Tennisclub Castello Del Sole",
    "wof:placetype":"venue"
},
  "geometry": {"coordinates":[8.7840328217,46.1562309265],"type":"Point"}
}