{
  "type": "Feature",
  "properties": {
    "iso:country":"CH",
    "sg:address":"D\u00fcnnernstrasse 32",
    "sg:city":"Oensingen",
    "sg:orig_category":"Instandhaltung U Reparatur von Automobilen",
    "sg:phone":"+41 21 963 40 96",
    "sg:postcode":"4702",
    "sg:province":"Solothurn",
    "wof:name":"Auto-trade Evolution S\u00e0rl",
    "wof:placetype":"venue"
},
  "geometry": {"coordinates":[6.9295902252,46.3618087769],"type":"Point"}
}