{
  "type": "Feature",
  "properties": {
    "iso:country":"CH",
    "sg:address":"5443",
    "sg:city":"Niederrohrdorf",
    "sg:orig_category":"Primarschulen",
    "sg:phone":"+41 56 496 17 37",
    "sg:postcode":"5443",
    "sg:province":"Aargau",
    "wof:name":"Primarschule H\u00fcslerberg",
    "wof:placetype":"venue"
},
  "geometry": {"coordinates":[8.3019599915,47.4214401245],"type":"Point"}
}