{
  "type": "Feature",
  "properties": {
    "iso:country":"CH",
    "sg:city":"Fiesch",
    "sg:classifiers":[
        {
            "category":"Banks & Credit Unions",
            "subcategory":"Bank",
            "type":"Services"
        }
    ],
    "sg:phone":"+41 27 971 27 22",
    "sg:postcode":"3984",
    "sg:province":"Valais",
    "wof:name":"Walliser Kantonalbank",
    "wof:placetype":"venue"
},
  "geometry": {"coordinates":[8.135188,46.403774],"type":"Point"}
}