{
  "type": "Feature",
  "properties": {
    "iso:country":"CH",
    "sg:address":"Chemin Ritter 8",
    "sg:city":"Biel/bienne",
    "sg:classifiers":[
        {
            "category":"Building & Trades",
            "subcategory":"Construction",
            "type":"Services"
        }
    ],
    "sg:phone":"+41 32 342 52 67",
    "sg:postcode":"2502",
    "sg:province":"Bern",
    "sg:tags":[
        "prototype"
    ],
    "wof:name":"Synergies Horlog\u00e8res Sa",
    "wof:placetype":"venue"
},
  "geometry": {"coordinates":[7.252204895,47.1398124695],"type":"Point"}
}