{
  "type": "Feature",
  "properties": {
    "iso:country":"CH",
    "sg:address":"Chemin De Mochettaz 2-4",
    "sg:city":"Bussigny-pr\u00e8s-lausanne",
    "sg:classifiers":[
        {
            "category":"Manufacturing",
            "subcategory":"Metals",
            "type":"Manufacturing & Wholesale Goods"
        }
    ],
    "sg:phone":"+41 71 227 29 00",
    "sg:postcode":"1030",
    "sg:province":"Vaud",
    "sg:tags":[
        "metallurgy",
        "steel",
        "metalworking"
    ],
    "wof:name":"D & A Management Und Beratung Ag",
    "wof:placetype":"venue"
},
  "geometry": {"coordinates":[9.3754863739,47.4248199463],"type":"Point"}
}