{
  "type": "Feature",
  "properties": {
    "addr:full":"Kirchweg 20 H\u00e4gendorf Solothurn 4614",
    "addr:housenumber":"20",
    "addr:postcode":"4614",
    "addr:street":"Kirchweg;Solothurn",
    "iso:country":"CH",
    "sg:address":"Kirchweg 20",
    "sg:city":"H\u00e4gendorf",
    "sg:orig_category":"Architektur U Ingenieurb\u00fcros",
    "sg:postcode":"4614",
    "sg:province":"Solothurn",
    "wof:name":"Sunline Ag",
    "wof:placetype":"venue"
},
  "geometry": {"coordinates":[7.848124,47.338169],"type":"Point"}
}