{
  "type": "Feature",
  "properties": {
    "iso:country":"CH",
    "sg:address":"6390 Engelberg. Postfach",
    "sg:city":"Engelberg",
    "sg:orig_category":"Sportvereine Eissport Eishockey",
    "sg:postcode":"6390",
    "sg:province":"Obwalden",
    "wof:name":"Eishockey-club Fletschhorn Saas-grund-allm.",
    "wof:placetype":"venue"
},
  "geometry": {"coordinates":[7.9367241859,46.1232452393],"type":"Point"}
}