{
  "type": "Feature",
  "properties": {
    "iso:country":"CH",
    "sg:address":"Route De Penau 35",
    "sg:city":"Mont-sur-lausanne",
    "sg:orig_category":"Sanit\u00e4rinstallation",
    "sg:phone":"+41 33 336 19 42",
    "sg:postcode":"1052",
    "sg:province":"Vaud",
    "wof:name":"Peter Michel Sanit\u00e4re Anlagen",
    "wof:placetype":"venue"
},
  "geometry": {"coordinates":[7.6268639565,46.7273178101],"type":"Point"}
}