{
  "type": "Feature",
  "properties": {
    "addr:full":"Dorfstrasse 17 Oberegg Appenzell Innerhoden 9413",
    "addr:housenumber":"17",
    "addr:postcode":"9413",
    "addr:street":"Dorfstrasse",
    "iso:country":"CH",
    "sg:address":"Dorfstrasse 17",
    "sg:city":"Oberegg",
    "sg:orig_category":"Arztpraxen",
    "sg:phone":"+41 79 404 44 22",
    "sg:postcode":"9413",
    "sg:province":"Appenzell Innerhoden",
    "wof:name":"Dr.med.margrith Breu Aerztin F\u00fcr Allg.medizin Fmh",
    "wof:placetype":"venue"
},
  "geometry": {"coordinates":[9.552389,47.422283],"type":"Point"}
}