{
  "type": "Feature",
  "properties": {
    "iso:country":"CH",
    "sg:address":"Am Dorfplatz 5",
    "sg:city":"Meggen",
    "sg:orig_category":"Detailhandel mit Waren verschiedener Art, Hauptrichtung Nahrungsmittel",
    "sg:phone":"+41 41 377 46 36",
    "sg:postcode":"6045",
    "sg:province":"Luzern",
    "wof:name":"Coop Center",
    "wof:placetype":"venue"
},
  "geometry": {"coordinates":[8.3734951019,47.0465087891],"type":"Point"}
}