{
  "type": "Feature",
  "properties": {
    "iso:country":"CH",
    "sg:address":"Grand-rue 86",
    "sg:city":"Thielle-wavre",
    "sg:orig_category":"Handelsvermittlung U Grosshandel Herstellung von sonstigen elektrischen Ausr\u00fcstungen",
    "sg:phone":"+41 19840440",
    "sg:postcode":"2075",
    "sg:province":"Neuch\u00e2tel",
    "wof:name":"Fritz Rindlisbacher Metalldetektoren-handel",
    "wof:placetype":"venue"
},
  "geometry": {"coordinates":[8.6900548935,47.3005561829],"type":"Point"}
}