{
  "type": "Feature",
  "properties": {
    "iso:country":"CH",
    "sg:address":"Dorfplatz 3 5026 Densb\u00fcren. Postfach",
    "sg:city":"Densb\u00fcren",
    "sg:orig_category":"Museen",
    "sg:phone":"+41 62 878 16 30",
    "sg:postcode":"5026",
    "sg:province":"Aargau",
    "wof:name":"Steiner Walo Kunstdruckatelier + Galerie",
    "wof:placetype":"venue"
},
  "geometry": {"coordinates":[8.0540771484,47.4541053772],"type":"Point"}
}