{
  "type": "Feature",
  "properties": {
    "iso:country":"CH",
    "sg:address":"Maienstr. 9",
    "sg:city":"Grenchen",
    "sg:classifiers":[
        {
            "category":"Manufacturing",
            "subcategory":"Metals",
            "type":"Manufacturing & Wholesale Goods"
        }
    ],
    "sg:phone":"+41 32 652 25 22",
    "sg:postcode":"2540",
    "sg:province":"Solothurn",
    "sg:tags":[
        "-",
        "machine",
        "equipment",
        "engineering",
        "machinery",
        "mechanical"
    ],
    "wof:name":"Tschudin",
    "wof:placetype":"venue"
},
  "geometry": {"coordinates":[7.4048957825,47.190738678],"type":"Point"}
}