{
  "type": "Feature",
  "properties": {
    "iso:country":"CH",
    "sg:address":"H\u00fchnerhubelstrasse 59 3123 Belp. Postfach",
    "sg:city":"Belp",
    "sg:orig_category":"Grosshandel mit medizinischen U orthop\u00e4dischen Artikeln Grosshandel mit pharmazeutischen Erzeugnisse",
    "sg:phone":"+41 31 819 00 93",
    "sg:postcode":"3123",
    "sg:province":"Bern",
    "wof:name":"Gribi Ag Belp",
    "wof:placetype":"venue"
},
  "geometry": {"coordinates":[7.4955239296,46.9038925171],"type":"Point"}
}