{
  "type": "Feature",
  "properties": {
    "iso:country":"CH",
    "sg:address":"Via San Martino 6 C",
    "sg:city":"Vacallo",
    "sg:orig_category":"Allgemeiner Hoch U Tiefbau Hoch U Tiefbau",
    "sg:phone":"+41 71 755 12 06",
    "sg:postcode":"6833",
    "sg:province":"Ticino",
    "wof:name":"Pinardi's C. Erben",
    "wof:placetype":"venue"
},
  "geometry": {"coordinates":[9.549698,47.375202],"type":"Point"}
}