{
  "type": "Feature",
  "properties": {
    "iso:country":"CH",
    "sg:address":"Unterer Quai 44",
    "sg:city":"Biel/bienne",
    "sg:orig_category":"Arztpraxen",
    "sg:phone":"+41 32 322 25 35",
    "sg:postcode":"2502",
    "sg:province":"Bern",
    "wof:name":"Dr.med.peter Blaser Spezialarzt Fmh",
    "wof:placetype":"venue"
},
  "geometry": {"coordinates":[7.240385,47.134212],"type":"Point"}
}