{
  "type": "Feature",
  "properties": {
    "iso:country":"CH",
    "sg:address":"Winkelriedstrasse 42 8200 Schaffhausen. Postfach",
    "sg:city":"Schaffhausen",
    "sg:orig_category":"Erbringung von sonstigen Dienstleistungen f\u00fcr Unterhaltung, Erholung U Freizeit",
    "sg:phone":"+41 52 624 74 15",
    "sg:postcode":"8203",
    "sg:province":"Schaffhausen",
    "wof:name":"Art 2000 Wahl & Co",
    "wof:placetype":"venue"
},
  "geometry": {"coordinates":[8.656083107,47.6999168396],"type":"Point"}
}