{
  "type": "Feature",
  "properties": {
    "iso:country":"CH",
    "sg:address":"Dorf",
    "sg:city":"Wattenwil",
    "sg:orig_category":"Vereine Vogel-& Naturschutz",
    "sg:phone":"+41 52 345 11 50",
    "sg:postcode":"3665",
    "sg:province":"Bern",
    "wof:name":"Ornithol.verein Effretikon",
    "wof:placetype":"venue"
},
  "geometry": {"coordinates":[8.7162685394,47.4353561401],"type":"Point"}
}