{
  "type": "Feature",
  "properties": {
    "iso:country":"CH",
    "sg:address":"Klybeckstrasse 74 4057 Basel. Postfach",
    "sg:city":"Basel",
    "sg:orig_category":"RESTAURANTS: TEA-ROOMS",
    "sg:phone":"+41 62 390 15 60",
    "sg:postcode":"4051",
    "sg:province":"Basel-Stadt",
    "wof:name":"Gastro Eintracht Gmbh",
    "wof:placetype":"venue"
},
  "geometry": {"coordinates":[7.753385067,47.3328437805],"type":"Point"}
}