{
  "type": "Feature",
  "properties": {
    "iso:country":"CH",
    "sg:address":"7440",
    "sg:city":"Andeer",
    "sg:orig_category":"Sportvereine Sch\u00fctzen",
    "sg:phone":"+41 81 661 17 54",
    "sg:postcode":"7440",
    "sg:province":"Graubunden",
    "wof:name":"Schiessverein",
    "wof:placetype":"venue"
},
  "geometry": {"coordinates":[9.4262599945,46.6029052734],"type":"Point"}
}