{
  "type": "Feature",
  "properties": {
    "iso:country":"CH",
    "sg:address":"H\u00f6heweg 82 2502 Biel/bienne Case Postale 1153",
    "sg:city":"Biel/bienne",
    "sg:orig_category":"HERSTELLUNG VON GER\u00c4TEN DER ELEKTRIZIT\u00c4TSERZEUGUNG, -VERTEILUNG U.\u00c4 Herstellung von Werkzeugen",
    "sg:phone":"+41 27 203 20 20",
    "sg:postcode":"2501",
    "sg:province":"Bern",
    "wof:name":"Mecotec Sa",
    "wof:placetype":"venue"
},
  "geometry": {"coordinates":[7.372150898,46.2232894897],"type":"Point"}
}