{
  "type": "Feature",
  "properties": {
    "iso:country":"CH",
    "sg:address":"Bahnhofstrasse 54",
    "sg:city":"Landquart",
    "sg:orig_category":"Unclassifiable Establishments",
    "sg:postcode":"7302",
    "sg:province":"Graubunden",
    "wof:name":"Provalor Ag",
    "wof:placetype":"venue"
},
  "geometry": {"coordinates":[9.5619878769,46.9679985046],"type":"Point"}
}