{
  "type": "Feature",
  "properties": {
    "iso:country":"CH",
    "sg:address":"Holzackerstrasse 14",
    "sg:city":"Belp",
    "sg:orig_category":"Vereine Abstinenten",
    "sg:phone":"+41 71 278 36 07",
    "sg:postcode":"3123",
    "sg:province":"Bern",
    "wof:name":"Blaukreuzverein Centrum",
    "wof:placetype":"venue"
},
  "geometry": {"coordinates":[9.3626384735,47.4231491089],"type":"Point"}
}