{
  "type": "Feature",
  "properties": {
    "addr:full":"Auf Der Fuhren Lauterbrunnen Bern 3822",
    "addr:postcode":"3822",
    "addr:street":"Auf Der Fuhren",
    "iso:country":"CH",
    "sg:address":"Auf Der Fuhren",
    "sg:city":"Lauterbrunnen",
    "sg:orig_category":"Bauschreinerei Herstellung von Konstruktionsteilen, Fertigbauteilen U Ausbauelementen aus Holz",
    "sg:phone":"+41 33 855 38 44",
    "sg:postcode":"3822",
    "sg:province":"Bern",
    "wof:name":"Raffainer Ag",
    "wof:placetype":"venue"
},
  "geometry": {"coordinates":[7.894355,46.544815],"type":"Point"}
}