{
  "type": "Feature",
  "properties": {
    "iso:country":"CH",
    "sg:address":"Moosbergstrasse 9",
    "sg:city":"Aarwangen",
    "sg:orig_category":"Kaminfeger",
    "sg:phone":"+41 79 422 01 80",
    "sg:postcode":"4912",
    "sg:province":"Bern",
    "wof:name":"Alois Buschor Kaminfegergesch\u00e4ft",
    "wof:placetype":"venue"
},
  "geometry": {"coordinates":[9.6327590942,47.4275016785],"type":"Point"}
}