{
  "type": "Feature",
  "properties": {
    "iso:country":"CH",
    "sg:address":"Krongasse 12",
    "sg:city":"Luzern",
    "sg:orig_category":"Detailhandel mit Herrenbekleidung Herstellung von konfektionierten Textilwaren ohne Bekleidung",
    "sg:phone":"+41 41 210 35 00",
    "sg:postcode":"6003",
    "sg:province":"Luzern",
    "wof:name":"Federer Sonja - Mann Oh Mio",
    "wof:placetype":"venue"
},
  "geometry": {"coordinates":[8.3037290573,47.0505065918],"type":"Point"}
}