{
  "type": "Feature",
  "properties": {
    "iso:country":"CH",
    "sg:address":"Solothurnstrassee 111",
    "sg:city":"Kr\u00e4iligen",
    "sg:orig_category":"Vereine Gesang",
    "sg:postcode":"3315",
    "sg:province":"Bern",
    "wof:name":"Gesangvereine B\u00e4tterkinden",
    "wof:placetype":"venue"
},
  "geometry": {"coordinates":[7.5333709717,47.1476783752],"type":"Point"}
}