{
  "type": "Feature",
  "properties": {
    "iso:country":"CH",
    "sg:address":"K\u00e4ppeliweg 23",
    "sg:city":"Muttenz",
    "sg:orig_category":"Vereine Fasnacht",
    "sg:phone":"+41 61 461 02 06",
    "sg:postcode":"4132",
    "sg:province":"Basel-Landschaft",
    "wof:name":"Die Ainsame",
    "wof:placetype":"venue"
},
  "geometry": {"coordinates":[7.6267471313,47.5339241028],"type":"Point"}
}