{
  "type": "Feature",
  "properties": {
    "addr:full":"Murtenstrasse 13 3210 Kerzers. Postfach Kerzers Fribourg 3210",
    "addr:housenumber":"13",
    "addr:postcode":"3210;3210",
    "addr:street":"Murtenstrasse",
    "iso:country":"CH",
    "sg:address":"Murtenstrasse 13 3210 Kerzers. Postfach",
    "sg:city":"Kerzers",
    "sg:orig_category":"Architektur U Ingenieurb\u00fcros Architekturb\u00fcros",
    "sg:phone":"+41 31 750 51 11",
    "sg:postcode":"3210",
    "sg:province":"Fribourg",
    "wof:name":"3-d Architekten Sa",
    "wof:placetype":"venue"
},
  "geometry": {"coordinates":[7.194524,46.974239],"type":"Point"}
}