{
  "type": "Feature",
  "properties": {
    "iso:country":"CH",
    "sg:address":"Aeschstrasse 112",
    "sg:city":"Ebmatingen",
    "sg:orig_category":"Sportvereine Ski",
    "sg:phone":"+41 19802675",
    "sg:postcode":"8123",
    "sg:province":"Z\u00fcrich",
    "wof:name":"Skiclub Ebmatingen",
    "wof:placetype":"venue"
},
  "geometry": {"coordinates":[8.6430683136,47.3495941162],"type":"Point"}
}