{
  "type": "Feature",
  "properties": {
    "iso:country":"CH",
    "sg:address":"Brunnenstrasse 20",
    "sg:city":"Heiden",
    "sg:orig_category":"Unclassifiable Establishments",
    "sg:postcode":"9410",
    "sg:province":"Appenzell Ausserrhoden",
    "wof:name":"Bernhard Nessensohn Naturheilpraxis",
    "wof:placetype":"venue"
},
  "geometry": {"coordinates":[9.5266189575,47.4391746521],"type":"Point"}
}