{
  "type": "Feature",
  "properties": {
    "iso:country":"CH",
    "sg:address":"Florissant Route De 55 1206 Gen\u00e8ve. Postfach",
    "sg:city":"Gen\u00e8ve",
    "sg:orig_category":"Fachdetailhandel in Verkaufsr\u00e4umen",
    "sg:postcode":"1206",
    "sg:province":"Gen\u00e8ve",
    "wof:name":"Isaflor Sa",
    "wof:placetype":"venue"
},
  "geometry": {"coordinates":[6.6091198921,46.7431411743],"type":"Point"}
}