{
  "type": "Feature",
  "properties": {
    "iso:country":"CH",
    "sg:address":"Vechigenstrasse 3 3076 Bangerten B. Worb. Postfach",
    "sg:city":"Worb",
    "sg:orig_category":"Zimmerei, Dachdeckerei, Bauspenglerei U Abdichtung",
    "sg:phone":"+41 19291255",
    "sg:postcode":"3076",
    "sg:province":"Bern",
    "wof:name":"K\u00fcbler & Humm Holzbau Ag",
    "wof:placetype":"venue"
},
  "geometry": {"coordinates":[8.7258205414,47.2776451111],"type":"Point"}
}