{
  "type": "Feature",
  "properties": {
    "iso:country":"CH",
    "sg:address":"Grosszelgstrasse 21",
    "sg:city":"W\u00fcrenlos",
    "sg:orig_category":"Herstellung von Hebezeugen U F\u00f6rdermitteln",
    "sg:postcode":"5436",
    "sg:province":"Aargau",
    "wof:name":"Niklaus Kiser",
    "wof:placetype":"venue"
},
  "geometry": {"coordinates":[8.3559417725,47.4444541931],"type":"Point"}
}