{
  "type": "Feature",
  "properties": {
    "iso:country":"CH",
    "sg:address":"Rue De Bourg 10",
    "sg:city":"Lausanne",
    "sg:orig_category":"Detailhandel mit Geschenkartikeln U Souvenirs Kunsthandel",
    "sg:phone":"+41 21 312 55 60",
    "sg:postcode":"1003",
    "sg:province":"Vaud",
    "wof:name":"Cardas, Boyer",
    "wof:placetype":"venue"
},
  "geometry": {"coordinates":[6.6353340149,46.5198936462],"type":"Point"}
}