{
  "type": "Feature",
  "properties": {
    "iso:country":"CH",
    "sg:address":"D\u00fcbendorfstrasse 5",
    "sg:city":"F\u00e4llanden",
    "sg:orig_category":"Autogaragen",
    "sg:phone":"+41 18253206",
    "sg:postcode":"8117",
    "sg:province":"Z\u00fcrich",
    "wof:name":"Paul Bl\u00e4ttler Garage",
    "wof:placetype":"venue"
},
  "geometry": {"coordinates":[8.637489,47.371281],"type":"Point"}
}