{
  "type": "Feature",
  "properties": {
    "iso:country":"CH",
    "sg:address":"Geren 10",
    "sg:city":"Tagelswangen",
    "sg:orig_category":"Grosshandel mit B\u00fcromaschinen Softwareentwicklung U beratung",
    "sg:phone":"+41 17221083",
    "sg:postcode":"8317",
    "sg:province":"Z\u00fcrich",
    "wof:name":"Symex Ag",
    "wof:placetype":"venue"
},
  "geometry": {"coordinates":[8.6666736603,47.4323425293],"type":"Point"}
}