{
  "type": "Feature",
  "properties": {
    "iso:country":"CH",
    "sg:address":"Frobenstrasse 75 4053 Basel. Postfach",
    "sg:city":"Basel",
    "sg:orig_category":"Detailhandel mit Metallwaren, Anstrichmitteln, Glaswaren, Bau U Heimwerkerbedarf Handelsvermittlung ",
    "sg:phone":"+41 71 244 32 40",
    "sg:postcode":"4008",
    "sg:province":"Basel-Stadt",
    "wof:name":"Muhl-vertrieb",
    "wof:placetype":"venue"
},
  "geometry": {"coordinates":[9.3828678131,47.4384613037],"type":"Point"}
}