{
  "type": "Feature",
  "properties": {
    "iso:country":"CH",
    "sg:address":"M\u00fcnzgasse 3 4125 Riehen. Postfach",
    "sg:city":"Basel",
    "sg:orig_category":"Unternehmensberatung",
    "sg:postcode":"4001",
    "sg:province":"Basel-Stadt",
    "wof:name":"Au Kaderberatung Beat Altherr",
    "wof:placetype":"venue"
},
  "geometry": {"coordinates":[7.6494550705,47.5844192505],"type":"Point"}
}