{
  "type": "Feature",
  "properties": {
    "iso:country":"CH",
    "sg:address":"Z\u00fcrcherstrasse 244 8500 Frauenfeld. Postfach",
    "sg:city":"Arbon",
    "sg:orig_category":"Grosshandel mit Datenverarbeitungsger\u00e4ten Sonstige mit der Informatik verbundene T\u00e4tigkeiten",
    "sg:phone":"+41 71 446 38 50",
    "sg:postcode":"9320",
    "sg:province":"Thurgau",
    "wof:name":"Data Trend Systeme Gmbh Edv-dienstleistungen Usw",
    "wof:placetype":"venue"
},
  "geometry": {"coordinates":[8.9026155472,47.5601959229],"type":"Point"}
}