{
  "type": "Feature",
  "properties": {
    "iso:country":"CH",
    "sg:address":"Rue De Lausanne 52 1200 Gen\u00e8ve. Postfach",
    "sg:city":"Gen\u00e8ve",
    "sg:orig_category":"Detailhandel mit B\u00fcchern, Zeitungen, Schreib U Papeteriewaren",
    "sg:phone":"+41 22 732 78 59",
    "sg:postcode":"1201",
    "sg:province":"Gen\u00e8ve",
    "wof:name":"Afsar T.",
    "wof:placetype":"venue"
},
  "geometry": {"coordinates":[6.1465420723,46.2144508362],"type":"Point"}
}