{
  "type": "Feature",
  "properties": {
    "iso:country":"CH",
    "sg:address":"Plessurquai 49",
    "sg:city":"Chur",
    "sg:orig_category":"Sportvereine Turnen",
    "sg:phone":"+41 81 252 70 49",
    "sg:postcode":"7000",
    "sg:province":"Graubunden",
    "wof:name":"Turnverein Der Kantonssch\u00fcler",
    "wof:placetype":"venue"
},
  "geometry": {"coordinates":[9.5338478088,46.8469772339],"type":"Point"}
}