{
  "type": "Feature",
  "properties": {
    "iso:country":"CH",
    "sg:address":"Chemin Du Bochat 25",
    "sg:city":"Paudex",
    "sg:orig_category":"Bauingenieurb\u00fcros Heizung L\u00fcftung Klima Bauingenieurb\u00fcros allgemein",
    "sg:phone":"+41 21 791 60 00",
    "sg:postcode":"1094",
    "sg:province":"Vaud",
    "wof:name":"Fernand Grandjean Bureau D'ing\u00e9nieur",
    "wof:placetype":"venue"
},
  "geometry": {"coordinates":[6.6747918129,46.5075454712],"type":"Point"}
}