{
  "type": "Feature",
  "properties": {
    "iso:country":"CH",
    "sg:address":"Eugen Huber-strasse 3",
    "sg:city":"Z\u00fcrich",
    "sg:orig_category":"Werbegrafikateliers",
    "sg:phone":"+41 13622367",
    "sg:postcode":"8048",
    "sg:province":"Z\u00fcrich",
    "wof:name":"Gion-christ Rostetter Grafisches Atelier",
    "wof:placetype":"venue"
},
  "geometry": {"coordinates":[8.4867630005,47.3843803406],"type":"Point"}
}