{
  "type": "Feature",
  "properties": {
    "iso:country":"CH",
    "sg:address":"Schulstrasse 8",
    "sg:city":"Sch\u00fcpfen",
    "sg:orig_category":"Detailhandel mit Brot, Back U S\u00fcsswaren",
    "sg:phone":"+41 31 879 04 63",
    "sg:postcode":"3054",
    "sg:province":"Bern",
    "wof:name":"Hans-ulrich Scheuner B\u00e4ckerei-konditorei",
    "wof:placetype":"venue"
},
  "geometry": {"coordinates":[7.377557,47.037643],"type":"Point"}
}