{
  "type": "Feature",
  "properties": {
    "iso:country":"CH",
    "sg:address":"Kantonsstrasse 64a 3930 Visp. Postfach",
    "sg:city":"Visp",
    "sg:orig_category":"Herstellung von Werkzeugmaschinen f\u00fcr die Metallbearbeitung Maschinen-Fabrikation",
    "sg:phone":"+41 27 945 18 70",
    "sg:postcode":"3930",
    "sg:province":"Valais",
    "wof:name":"Zema Ag Produktion Von Maschinen, Waren Usw",
    "wof:placetype":"venue"
},
  "geometry": {"coordinates":[7.8965392113,46.2930679321],"type":"Point"}
}