{
  "type": "Feature",
  "properties": {
    "iso:country":"CH",
    "sg:address":"Tischenlooweg 10",
    "sg:city":"Thalwil",
    "sg:orig_category":"Unclassifiable Establishments",
    "sg:postcode":"8800",
    "sg:province":"Z\u00fcrich",
    "wof:name":"Hauswartungen Willi Jaisli Liegenschaften Und Unterhalt",
    "wof:placetype":"venue"
},
  "geometry": {"coordinates":[8.5775871277,47.2821426392],"type":"Point"}
}