{
  "type": "Feature",
  "properties": {
    "iso:country":"CH",
    "sg:address":"Voa Tgameltger 4 Valbella 7082 Vaz/obervaz. Postfach",
    "sg:city":"Valbella",
    "sg:orig_category":"Detailhandel mit elektrischen Haushalts-,Radio U Fernsehger\u00e4ten sowie Musikinstrumenten",
    "sg:postcode":"7077",
    "sg:province":"Graubunden",
    "wof:name":"Wiesendanger Audiovision",
    "wof:placetype":"venue"
},
  "geometry": {"coordinates":[9.5320854187,46.6989746094],"type":"Point"}
}