{
  "type": "Feature",
  "properties": {
    "iso:country":"CH",
    "sg:address":"Baarerstrasse 10 6300 Zug. Postfach",
    "sg:city":"Zug",
    "sg:orig_category":"Reiseb\u00fcros U Reiseveranstalter",
    "sg:phone":"+41 41 729 13 33",
    "sg:postcode":"6300",
    "sg:province":"Zug",
    "wof:name":"Golden Arch Hotels Suisse Sa Dienstleistungen Im Zusammenhang Mit Beherbergung, Verpflegung, Tourismus Usw",
    "wof:placetype":"venue"
},
  "geometry": {"coordinates":[8.5164327621,47.1715621948],"type":"Point"}
}