{
  "type": "Feature",
  "properties": {
    "iso:country":"CH",
    "sg:address":"Delfterstrasse",
    "sg:city":"Aarau",
    "sg:orig_category":"Tankstellen",
    "sg:phone":"+41 62 212 96 16",
    "sg:postcode":"5000",
    "sg:province":"Aargau",
    "wof:name":"Coop Tankstelle",
    "wof:placetype":"venue"
},
  "geometry": {"coordinates":[7.8642292023,47.3420677185],"type":"Point"}
}