{
  "type": "Feature",
  "properties": {
    "iso:country":"CH",
    "sg:address":"Lohwisstrasse 36",
    "sg:city":"Ebmatingen",
    "sg:orig_category":"Herstellung von konfektionierten Textilwaren ohne Bekleidung",
    "sg:postcode":"8123",
    "sg:province":"Z\u00fcrich",
    "wof:name":"Storenbau Bernik",
    "wof:placetype":"venue"
},
  "geometry": {"coordinates":[8.889547348,47.520942688],"type":"Point"}
}