{
  "type": "Feature",
  "properties": {
    "iso:country":"CH",
    "sg:address":"B\u00f6sch 72",
    "sg:city":"H\u00fcnenberg",
    "sg:orig_category":"Grosshandel mit Getreide, Saatgut U Futtermitteln",
    "sg:phone":"+41 41 711 25 05",
    "sg:postcode":"6331",
    "sg:province":"Zug",
    "wof:name":"Tanecco Ag",
    "wof:placetype":"venue"
},
  "geometry": {"coordinates":[8.435002327,47.1618156433],"type":"Point"}
}