{
  "type": "Feature",
  "properties": {
    "iso:country":"CH",
    "sg:address":"Alpenstrasse 14 6300 Zug. Postfach 4306",
    "sg:city":"Zug",
    "sg:orig_category":"Finanzierungsinstitutionen Wirtschaftspr\u00fcfung, Steuerberatung U Treuhand",
    "sg:phone":"+41 41 720 09 69",
    "sg:postcode":"6304",
    "sg:province":"Zug",
    "wof:name":"Gecko Consulting Ag",
    "wof:placetype":"venue"
},
  "geometry": {"coordinates":[8.5150566101,47.1726837158],"type":"Point"}
}