{
  "type": "Feature",
  "properties": {
    "addr:full":"Flachsacherstrasse 3 Birr-lupfig Aargau 5242",
    "addr:housenumber":"3",
    "addr:postcode":"5242",
    "addr:street":"Flachsacherstrasse",
    "iso:country":"CH",
    "sg:address":"Flachsacherstrasse 3",
    "sg:city":"Birr-lupfig",
    "sg:orig_category":"Detailhandel mit Blumen U Pflanzen",
    "sg:phone":"+41 56 444 75 59",
    "sg:postcode":"5242",
    "sg:province":"Aargau",
    "wof:name":"Karl R\u00e4mi Blueme Kari",
    "wof:placetype":"venue"
},
  "geometry": {"coordinates":[8.202725,47.436172],"type":"Point"}
}