{
  "type": "Feature",
  "properties": {
    "iso:country":"CH",
    "sg:address":"5102 Rupperswil. Postfach 49",
    "sg:city":"Rupperswil",
    "sg:orig_category":"Sportvereine Ballsport Fussball",
    "sg:postcode":"5102",
    "sg:province":"Aargau",
    "wof:name":"Fc Rupperswil",
    "wof:placetype":"venue"
},
  "geometry": {"coordinates":[8.1292772293,47.4022331238],"type":"Point"}
}