{
  "type": "Feature",
  "properties": {
    "iso:country":"CH",
    "sg:address":"6276",
    "sg:city":"Hohenrain",
    "sg:orig_category":"Institutionen f\u00fcr Behinderte Sonderschulen",
    "sg:phone":"+41 61 641 47 67",
    "sg:postcode":"6276",
    "sg:province":"Luzern",
    "wof:name":"Kantonales Sonderschulheim Zur Hoffnung",
    "wof:placetype":"venue"
},
  "geometry": {"coordinates":[7.6525530815,47.5805358887],"type":"Point"}
}