{
  "type": "Feature",
  "properties": {
    "iso:country":"CH",
    "sg:address":"Florastrasse 5",
    "sg:city":"Unter\u00e4geri",
    "sg:orig_category":"Grosshandel mit Textilien",
    "sg:phone":"+41 41 750 12 56",
    "sg:postcode":"6314",
    "sg:province":"Zug",
    "wof:name":"Textile Managers Inc",
    "wof:placetype":"venue"
},
  "geometry": {"coordinates":[8.5874347687,47.1387329102],"type":"Point"}
}