{
  "type": "Feature",
  "properties": {
    "iso:country":"CH",
    "sg:address":"Eichweg 4 6300 Zug. Postfach 2003",
    "sg:city":"Zug",
    "sg:orig_category":"Handelsvermittlung U Grosshandel Sonstiger Grosshandel",
    "sg:phone":"+41 55 225 42 20",
    "sg:postcode":"6302",
    "sg:province":"Zug",
    "wof:name":"Airgom Ag",
    "wof:placetype":"venue"
},
  "geometry": {"coordinates":[9.1500082016,47.5490837097],"type":"Point"}
}