{
  "type": "Feature",
  "properties": {
    "iso:country":"CH",
    "sg:address":"Hintereggstrasse 4",
    "sg:city":"Achseten",
    "sg:orig_category":"Bauspenglerei Sanit\u00e4rinstallation U Spenglerei",
    "sg:phone":"+41 33 671 44 20",
    "sg:postcode":"3725",
    "sg:province":"Bern",
    "wof:name":"Ernst Trachsel Spenglerei",
    "wof:placetype":"venue"
},
  "geometry": {"coordinates":[7.597219,46.527805],"type":"Point"}
}