{
  "type": "Feature",
  "properties": {
    "iso:country":"CH",
    "sg:address":"Ohne Domizil 6300 Zug. Postfach",
    "sg:city":"Zug",
    "sg:orig_category":"Sanit\u00e4rinstallation U Spenglerei",
    "sg:phone":"+41 61 467 92 22",
    "sg:postcode":"6301",
    "sg:province":"Zug",
    "wof:name":"Benone Ag",
    "wof:placetype":"venue"
},
  "geometry": {"coordinates":[7.6575517654,47.5289077759],"type":"Point"}
}