{
  "type": "Feature",
  "properties": {
    "iso:country":"CH",
    "sg:address":"Laufenstr. 4",
    "sg:city":"Breitenbach",
    "sg:classifiers":[
        {
            "category":"Banks & Credit Unions",
            "subcategory":"Bank",
            "type":"Services"
        }
    ],
    "sg:phone":"+41 61 766 55 66",
    "sg:postcode":"4226",
    "sg:province":"Solothurn",
    "wof:name":"Swiss Bank Corp.",
    "wof:placetype":"venue"
},
  "geometry": {"coordinates":[7.542829,47.408154],"type":"Point"}
}