{
  "type": "Feature",
  "properties": {
    "iso:country":"CH",
    "sg:address":"Restaurant Spitzmeilenblick",
    "sg:city":"Flums",
    "sg:orig_category":"Unclassifiable Establishments",
    "sg:postcode":"8890",
    "sg:province":"St. Gallen",
    "wof:name":"Restaurant Spitzmeilenblick, Widmer Hansj\u00f6rg",
    "wof:placetype":"venue"
},
  "geometry": {"coordinates":[9.3425388336,47.0917549133],"type":"Point"}
}