{
  "type": "Feature",
  "properties": {
    "iso:country":"CH",
    "sg:address":"Via Vallemaggia 1",
    "sg:city":"Locarno",
    "sg:orig_category":"Detailhandel mit Zeitungen U Zeitschriften Kioske",
    "sg:phone":"+41 91 752 15 91",
    "sg:postcode":"6600",
    "sg:province":"Ticino",
    "wof:name":"Edicola Nuova Cantoreggi Patricia",
    "wof:placetype":"venue"
},
  "geometry": {"coordinates":[8.7901315689,46.1696624756],"type":"Point"}
}