{
  "type": "Feature",
  "properties": {
    "iso:country":"CH",
    "sg:address":"Bernstrasse 145a",
    "sg:city":"Ostermundigen",
    "sg:orig_category":"Reinigungsgewerbe",
    "sg:postcode":"3072",
    "sg:province":"Bern",
    "wof:name":"Pavlin Josef",
    "wof:placetype":"venue"
},
  "geometry": {"coordinates":[7.5000338554,46.9599456787],"type":"Point"}
}