{
  "type": "Feature",
  "properties": {
    "iso:country":"CH",
    "sg:address":"Kirchstrasse 75 2540 Grenchen. Postfach 742",
    "sg:city":"Grenchen",
    "sg:orig_category":"Herstellung von Schrauben, Nieten, Ketten U Federn Herstellung von Uhren",
    "sg:phone":"+41 32 652 82 44",
    "sg:postcode":"2540",
    "sg:province":"Solothurn",
    "wof:name":"Meyer & Co Ag",
    "wof:placetype":"venue"
},
  "geometry": {"coordinates":[7.3923110962,47.195640564],"type":"Point"}
}