{
  "type": "Feature",
  "properties": {
    "iso:country":"CH",
    "sg:address":"Route De Morat 1",
    "sg:city":"Courtepin",
    "sg:orig_category":"Massagestudios",
    "sg:phone":"+41 26 684 34 02",
    "sg:postcode":"1784",
    "sg:province":"Fribourg",
    "wof:name":"Massant\u00e9 S\u00e0rl Massage De Sant\u00e9 Et De Sport",
    "wof:placetype":"venue"
},
  "geometry": {"coordinates":[7.1222229004,46.8689689636],"type":"Point"}
}