{
  "type": "Feature",
  "properties": {
    "iso:country":"CH",
    "sg:address":"Thermenstrasse 11",
    "sg:city":"Rheinfelden",
    "sg:orig_category":"Architektur U Ingenieurb\u00fcros Ingenieurb\u00fcros Datenverarbeitung",
    "sg:phone":"+41 61 836 82 00",
    "sg:postcode":"4310",
    "sg:province":"Aargau",
    "wof:name":"Ibitech Ag Ingenieurb\u00fcro F\u00fcr Informationstechnologie",
    "wof:placetype":"venue"
},
  "geometry": {"coordinates":[7.802077,47.549664],"type":"Point"}
}