{
  "type": "Feature",
  "properties": {
    "iso:country":"CH",
    "sg:address":"Kernstrasse 57",
    "sg:city":"Z\u00fcrich",
    "sg:classifiers":[
        {
            "category":"Personal",
            "subcategory":"Sauna",
            "type":"Services"
        }
    ],
    "sg:phone":"+41 12916362",
    "sg:postcode":"8004",
    "sg:province":"Z\u00fcrich",
    "wof:name":"Reno's Relax Club Sauna",
    "wof:placetype":"venue"
},
  "geometry": {"coordinates":[8.5258321762,47.3779907227],"type":"Point"}
}