{
  "type": "Feature",
  "properties": {
    "iso:country":"CH",
    "sg:address":"Eichhofweg 3",
    "sg:city":"Eich",
    "sg:orig_category":"Unternehmensberatung",
    "sg:phone":"+41 41 461 06 75",
    "sg:postcode":"6205",
    "sg:province":"Luzern",
    "wof:name":"Vertrieb & Management-support (v & M) Bachmann Joe",
    "wof:placetype":"venue"
},
  "geometry": {"coordinates":[8.1659984589,47.1550521851],"type":"Point"}
}