{
  "type": "Feature",
  "properties": {
    "iso:country":"CH",
    "sg:address":"Rue Des Uttins 36",
    "sg:city":"Yverdon-les-bains",
    "sg:orig_category":"Herstellung von Anstrichmitteln, Druckfarben U Kitten Herstellung von sonstigen chemischen Erzeugnis",
    "sg:phone":"+41 24 445 42 42",
    "sg:postcode":"1400",
    "sg:province":"Vaud",
    "wof:name":"Siegfried Keller Sa Couleurs & Vernis",
    "wof:placetype":"venue"
},
  "geometry": {"coordinates":[6.6239128113,46.7837905884],"type":"Point"}
}