{
  "type": "Feature",
  "properties": {
    "iso:country":"CH",
    "sg:address":"Bruggweg 6",
    "sg:city":"Dornach",
    "sg:classifiers":[
        {
            "category":"Restaurant",
            "type":"Food & Drink"
        }
    ],
    "sg:phone":"+41 61 701 19 24",
    "sg:postcode":"4143",
    "sg:province":"Solothurn",
    "wof:name":"Restaurant Dibi-d\u00e4bi",
    "wof:placetype":"venue"
},
  "geometry": {"coordinates":[7.6093010902,47.4879646301],"type":"Point"}
}