{
  "type": "Feature",
  "properties": {
    "iso:country":"CH",
    "sg:address":"Luzernerring 76",
    "sg:city":"Basel",
    "sg:orig_category":"Religi\u00f6se Vereinigungen",
    "sg:postcode":"4056",
    "sg:province":"Basel-Stadt",
    "wof:name":"Mission \u00e9vang\u00e9lique",
    "wof:placetype":"venue"
},
  "geometry": {"coordinates":[7.5678601265,47.5687599182],"type":"Point"}
}