{
  "type": "Feature",
  "properties": {
    "iso:country":"CH",
    "sg:address":"La Ruelle 9",
    "sg:city":"Vernier",
    "sg:orig_category":"Physiotherapie",
    "sg:phone":"+41 22 341 45 58",
    "sg:postcode":"1214",
    "sg:province":"Gen\u00e8ve",
    "wof:name":"Eric Gagnaux Physioth\u00e9rapie",
    "wof:placetype":"venue"
},
  "geometry": {"coordinates":[6.0822458267,46.213142395],"type":"Point"}
}