{
  "type": "Feature",
  "properties": {
    "iso:country":"CH",
    "sg:address":"Alfred Strebel-weg 6",
    "sg:city":"Z\u00fcrich",
    "sg:classifiers":[
        {
            "category":"Communications",
            "subcategory":"Radio Station",
            "type":"Services"
        }
    ],
    "sg:phone":"+41 14927177",
    "sg:postcode":"8047",
    "sg:province":"Z\u00fcrich",
    "sg:tags":[
        "fernsehanstalten",
        "u"
    ],
    "wof:name":"Biweco Ag Digital, Ton, Bildinformationen; Erzeugung, Vervielf\u00e4ltigung, Auswertung Usw",
    "wof:placetype":"venue"
},
  "geometry": {"coordinates":[8.4938697815,47.3714408875],"type":"Point"}
}