{
  "type": "Feature",
  "properties": {
    "iso:country":"CH",
    "sg:address":"\u00dcberlandstrasse 360",
    "sg:city":"Z\u00fcrich",
    "sg:orig_category":"Non-Classified Establishments",
    "sg:postcode":"8000",
    "sg:province":"Z\u00fcrich",
    "wof:name":"Kuoni Reisen Ag, Zweigniederlassung Incoming Services",
    "wof:placetype":"venue"
},
  "geometry": {"coordinates":[8.5828561783,47.40782547],"type":"Point"}
}