{
  "type": "Feature",
  "properties": {
    "iso:country":"CH",
    "sg:address":"Route Du Ch\u00e2telet 8",
    "sg:city":"Marly",
    "sg:orig_category":"Allgemeiner Hoch U Tiefbau Hoch U Tiefbau",
    "sg:phone":"+41 71 722 18 71",
    "sg:postcode":"1723",
    "sg:province":"Fribourg",
    "wof:name":"Carnier Ag",
    "wof:placetype":"venue"
},
  "geometry": {"coordinates":[9.628298,47.411697],"type":"Point"}
}