{
  "type": "Feature",
  "properties": {
    "iso:country":"CH",
    "sg:address":"Scheuchzerstrasse 35",
    "sg:city":"Z\u00fcrich",
    "sg:orig_category":"Bezirks, Sekundar, Realschulen, Oberstufe der Primarschulen Primarschulen",
    "sg:phone":"+41 13622730",
    "sg:postcode":"8006",
    "sg:province":"Z\u00fcrich",
    "wof:name":"Montessori-schule Z\u00fcrich C/o Frau Claudine Baumann",
    "wof:placetype":"venue"
},
  "geometry": {"coordinates":[8.544681,47.384808],"type":"Point"}
}