{
  "type": "Feature",
  "properties": {
    "iso:country":"CH",
    "sg:address":"9424",
    "sg:city":"Rheineck",
    "sg:orig_category":"Vereine Abstinenten",
    "sg:postcode":"9424",
    "sg:province":"St. Gallen",
    "wof:name":"Blaues Kreuz",
    "wof:placetype":"venue"
},
  "geometry": {"coordinates":[9.549697876,47.375202179],"type":"Point"}
}