{
  "type": "Feature",
  "properties": {
    "iso:country":"CH",
    "sg:address":"Ponte No\u00ebl 6917 Barbengo. Postfach",
    "sg:city":"Agra",
    "sg:orig_category":"Sonstiges Textilgewerbe",
    "sg:phone":"+41 91 995 10 33",
    "sg:postcode":"6927",
    "sg:province":"Ticino",
    "wof:name":"Ariete Di Mani Heinz",
    "wof:placetype":"venue"
},
  "geometry": {"coordinates":[8.9250659943,45.9669761658],"type":"Point"}
}