{
  "type": "Feature",
  "properties": {
    "iso:country":"CH",
    "sg:address":"1312",
    "sg:city":"Ecl\u00e9pens",
    "sg:orig_category":"Sportvereine Sch\u00fctzen",
    "sg:postcode":"1312",
    "sg:province":"Vaud",
    "wof:name":"St\u00e9 De Tir Armes De Guerre",
    "wof:placetype":"venue"
},
  "geometry": {"coordinates":[6.544479847,46.6521987915],"type":"Point"}
}