{
  "type": "Feature",
  "properties": {
    "iso:country":"CH",
    "sg:address":"2717",
    "sg:city":"Fornet-dessous",
    "sg:classifiers":[
        {
            "category":"Travel",
            "subcategory":"Hotels & Motels",
            "type":"Entertainment"
        }
    ],
    "sg:phone":"+41 32 484 91 19",
    "sg:postcode":"2717",
    "sg:province":"Bern",
    "sg:tags":[
        "hotels",
        "mit",
        "restaurant"
    ],
    "wof:name":"H\u00f4tel Du Sapin",
    "wof:placetype":"venue"
},
  "geometry": {"coordinates":[7.1733298302,47.2802696228],"type":"Point"}
}