{
  "type": "Feature",
  "properties": {
    "iso:country":"CH",
    "sg:address":"Place Des Bennelats 1",
    "sg:city":"Porrentruy",
    "sg:orig_category":"Detailhandel mit B\u00fcchern, Zeitungen, Schreib U Papeteriewaren Detailhandel mit Zeitungen U Zeitschri",
    "sg:phone":"+41 24 425 11 81",
    "sg:postcode":"2900",
    "sg:province":"Jura",
    "wof:name":"Chapuis Michel",
    "wof:placetype":"venue"
},
  "geometry": {"coordinates":[6.638433,46.779888],"type":"Point"}
}