{
  "type": "Feature",
  "properties": {
    "iso:country":"CH",
    "sg:address":"Burgunderstrasse 42a",
    "sg:city":"Basel",
    "sg:orig_category":"Vermittlung von Immobilien Verwaltung von Immobilien",
    "sg:phone":"+41 61 271 52 55",
    "sg:postcode":"4051",
    "sg:province":"Basel-Stadt",
    "wof:name":"Paul Ulli & Co.",
    "wof:placetype":"venue"
},
  "geometry": {"coordinates":[7.5784511566,47.5526847839],"type":"Point"}
}