{
  "type": "Feature",
  "properties": {
    "iso:country":"CH",
    "sg:address":"Rte De Develier 171.",
    "sg:city":"Courfaivre",
    "sg:orig_category":"Herstellung von Sportger\u00e4ten",
    "sg:phone":"+41 32 426 89 16",
    "sg:postcode":"2853",
    "sg:province":"Jura",
    "wof:name":"Veya Madame Simone.",
    "wof:placetype":"venue"
},
  "geometry": {"coordinates":[7.2840099335,47.3363609314],"type":"Point"}
}