{
  "type": "Feature",
  "properties": {
    "iso:country":"CH",
    "sg:address":"Hauptbahnhofstrasse 2 4500 Solothurn. Postfach",
    "sg:city":"Solothurn",
    "sg:orig_category":"Fachdetailhandel mit pharmazeutischen Produkten",
    "sg:phone":"+41 32 622 19 19",
    "sg:postcode":"4500",
    "sg:province":"Solothurn",
    "wof:name":"Bahnhof Apotheke Solothurn Ag Apotheke. Pharmazeutische Produkte; Handel",
    "wof:placetype":"venue"
},
  "geometry": {"coordinates":[7.5405421257,47.2050971985],"type":"Point"}
}