{
  "type": "Feature",
  "properties": {
    "iso:country":"CH",
    "sg:address":"1892",
    "sg:city":"Lavey-les-bains",
    "sg:orig_category":"Physiotherapie Sanatorien",
    "sg:phone":"+41 24 486 15 30",
    "sg:postcode":"1892",
    "sg:province":"Vaud",
    "wof:name":"Centre M\u00e9dical De Lavey-les-bains Sa",
    "wof:placetype":"venue"
},
  "geometry": {"coordinates":[7.0191202164,46.2037391663],"type":"Point"}
}