{
  "type": "Feature",
  "properties": {
    "iso:country":"CH",
    "sg:address":"Aarbergstrasse 87",
    "sg:city":"Lyss",
    "sg:orig_category":"Tankstellen",
    "sg:phone":"+41 32 384 38 10",
    "sg:postcode":"3250",
    "sg:province":"Bern",
    "wof:name":"Shell-service-station, Hans-ulrich M\u00f6ri",
    "wof:placetype":"venue"
},
  "geometry": {"coordinates":[7.3002810478,47.0640945435],"type":"Point"}
}