{
  "type": "Feature",
  "properties": {
    "iso:country":"CH",
    "sg:address":"Hermetschloostrasse 10 8048 Z\u00fcrich. Postfach",
    "sg:city":"Z\u00fcrich",
    "sg:orig_category":"Autotransporte international",
    "sg:phone":"+41 14386222",
    "sg:postcode":"8048",
    "sg:province":"Z\u00fcrich",
    "wof:name":"Airsped Ag",
    "wof:placetype":"venue"
},
  "geometry": {"coordinates":[8.481763,47.392063],"type":"Point"}
}