{
  "type": "Feature",
  "properties": {
    "iso:country":"CH",
    "sg:address":"Winterthurerstrasse 3",
    "sg:city":"Eschlikon",
    "sg:classifiers":[
        {
            "category":"Manufacturing",
            "subcategory":"Wood Products",
            "type":"Manufacturing & Wholesale Goods"
        }
    ],
    "sg:phone":"+41 71 971 17 17",
    "sg:postcode":"8360",
    "sg:province":"Thurgau",
    "sg:tags":[
        "lumber"
    ],
    "wof:name":"Paul Dreyer S\u00e4gewerk",
    "wof:placetype":"venue"
},
  "geometry": {"coordinates":[8.9550609589,47.4620399475],"type":"Point"}
}