{
  "type": "Feature",
  "properties": {
    "iso:country":"CH",
    "sg:address":"Eptingerstrasse 3 4448 L\u00e4ufelfingen. Postfach 28",
    "sg:city":"L\u00e4ufelfingen",
    "sg:orig_category":"Fachdetailhandel in Verkaufsr\u00e4umen",
    "sg:phone":"+41 62 299 25 70",
    "sg:postcode":"4448",
    "sg:province":"Basel-Landschaft",
    "wof:name":"Homburg Optik E. K\u00fcng M\u00fcller",
    "wof:placetype":"venue"
},
  "geometry": {"coordinates":[7.8558769226,47.3920021057],"type":"Point"}
}