{
  "type": "Feature",
  "properties": {
    "iso:country":"CH",
    "sg:address":"Mythencenterstrasse 18",
    "sg:city":"Ibach",
    "sg:orig_category":"Detailhandel mit Waren verschiedener Art, Hauptrichtung Nahrungsmittel",
    "sg:phone":"+41 41 811 54 85",
    "sg:postcode":"6438",
    "sg:province":"Schwyz",
    "wof:name":"Denner Top Superdiscount",
    "wof:placetype":"venue"
},
  "geometry": {"coordinates":[8.6458873749,47.0148544312],"type":"Point"}
}