{
  "type": "Feature",
  "properties": {
    "iso:country":"CH",
    "sg:address":"Balmat Rue Jacques- 5 1204 Gen\u00e8ve. Postfach",
    "sg:city":"Gen\u00e8ve",
    "sg:orig_category":"Non-Classified Establishments",
    "sg:postcode":"1201",
    "sg:province":"Gen\u00e8ve",
    "wof:name":"Montana Holding Altdorf Beteiligungen Usw",
    "wof:placetype":"venue"
},
  "geometry": {"coordinates":[8.6430692673,46.8819656372],"type":"Point"}
}