{
  "type": "Feature",
  "properties": {
    "iso:country":"CH",
    "sg:address":"Chemin De Machefer 45",
    "sg:city":"Versoix",
    "sg:orig_category":"Autolackierereien Autospenglereien",
    "sg:phone":"+41 22 755 59 91",
    "sg:postcode":"1290",
    "sg:province":"Gen\u00e8ve",
    "wof:name":"Claudio Bacci Carrosserie",
    "wof:placetype":"venue"
},
  "geometry": {"coordinates":[6.140756,46.274921],"type":"Point"}
}