{
  "type": "Feature",
  "properties": {
    "iso:country":"CH",
    "sg:address":"Z\u00fcrcherstrasse 145",
    "sg:city":"Jona",
    "sg:orig_category":"Revision Unternehmensberatung",
    "sg:phone":"+41 55 210 14 57",
    "sg:postcode":"8645",
    "sg:province":"St. Gallen",
    "wof:name":"Emmanuel S\u00e9quin",
    "wof:placetype":"venue"
},
  "geometry": {"coordinates":[8.814450264,47.2372932434],"type":"Point"}
}