{
  "type": "Feature",
  "properties": {
    "iso:country":"CH",
    "sg:address":"Weidstrasse 6a",
    "sg:city":"Zug",
    "sg:orig_category":"Non-Classified Establishments",
    "sg:postcode":"6300",
    "sg:province":"Zug",
    "wof:name":"Development & Investments Ag",
    "wof:placetype":"venue"
},
  "geometry": {"coordinates":[8.525932312,47.1671333313],"type":"Point"}
}