{
  "type": "Feature",
  "properties": {
    "iso:country":"CH",
    "sg:address":"Verschnalsweg 8",
    "sg:city":"Igis",
    "sg:orig_category":"Reiseb\u00fcros U Reiseveranstalter",
    "sg:phone":"+41 62 956 56 56",
    "sg:postcode":"7206",
    "sg:province":"Graubunden",
    "wof:name":"Verkehrsclub Der Schweiz Vcs St.gallen/appenzell",
    "wof:placetype":"venue"
},
  "geometry": {"coordinates":[9.3733558655,47.4241333008],"type":"Point"}
}