{
  "type": "Feature",
  "properties": {
    "iso:country":"CH",
    "sg:address":"K\u00e4ppeligarten 2",
    "sg:city":"R\u00f6schenz",
    "sg:orig_category":"Softwareentwicklung U beratung",
    "sg:phone":"+41 61 763 06 90",
    "sg:postcode":"4244",
    "sg:province":"Basel-Landschaft",
    "wof:name":"Scherrer Werner + Partner",
    "wof:placetype":"venue"
},
  "geometry": {"coordinates":[7.4784841537,47.4250869751],"type":"Point"}
}