{
  "type": "Feature",
  "properties": {
    "iso:country":"CH",
    "sg:address":"Balfrinstrasse 15d",
    "sg:city":"Visp",
    "sg:orig_category":"Detailhandel mit Blumen U Pflanzen",
    "sg:phone":"+41 27 946 30 38",
    "sg:postcode":"3930",
    "sg:province":"Valais",
    "wof:name":"Bl\u00fcemuparadies Rinaldo Weissen",
    "wof:placetype":"venue"
},
  "geometry": {"coordinates":[7.882314,46.291462],"type":"Point"}
}