{
  "type": "Feature",
  "properties": {
    "iso:country":"CH",
    "sg:address":"Platz 4 3904 Naters. Postfach",
    "sg:city":"Naters",
    "sg:orig_category":"Allgemeiner Hoch U Tiefbau",
    "sg:postcode":"3904",
    "sg:province":"Valais",
    "wof:name":"Ar-architekten Gmbh",
    "wof:placetype":"venue"
},
  "geometry": {"coordinates":[7.988106,46.326813],"type":"Point"}
}