{
  "type": "Feature",
  "properties": {
    "iso:country":"CH",
    "sg:address":"Via Vignola 17",
    "sg:city":"Lugano",
    "sg:orig_category":"Elektroinstallation",
    "sg:phone":"+41 22 771 16 97",
    "sg:postcode":"6900",
    "sg:province":"Ticino",
    "wof:name":"C. Giacobino",
    "wof:placetype":"venue"
},
  "geometry": {"coordinates":[6.1042528152,46.1490287781],"type":"Point"}
}