{
  "type": "Feature",
  "properties": {
    "iso:country":"CH",
    "sg:address":"Rue De L'h\u00f4tel De Ville 11",
    "sg:city":"Estavayer-le-lac",
    "sg:orig_category":"Gemeindeverwaltungen",
    "sg:phone":"+41 26 652 15 17",
    "sg:postcode":"1470",
    "sg:province":"Fribourg",
    "wof:name":"Administration Communale De Est\u00e9venens",
    "wof:placetype":"venue"
},
  "geometry": {"coordinates":[6.9318900108,46.6349906921],"type":"Point"}
}