{
  "type": "Feature",
  "properties": {
    "iso:country":"CH",
    "sg:address":"Tramstrasse 19 9444 Diepoldsau. Postfach 441",
    "sg:city":"Diepoldsau",
    "sg:orig_category":"Instandhaltung U Reparatur von Automobilen",
    "sg:phone":"+41 71 733 18 42",
    "sg:postcode":"9444",
    "sg:province":"St. Gallen",
    "wof:name":"Garage Thurnheer Ag",
    "wof:placetype":"venue"
},
  "geometry": {"coordinates":[9.6512727737,47.3887023926],"type":"Point"}
}