{
  "type": "Feature",
  "properties": {
    "iso:country":"CH",
    "sg:address":"Feldstrasse 6",
    "sg:city":"Urdorf",
    "sg:orig_category":"Detailhandel mit Radio U Fernsehger\u00e4ten Reparatur von elektrischen Haushaltsger\u00e4ten",
    "sg:phone":"+41 52 741 41 66",
    "sg:postcode":"8902",
    "sg:province":"Z\u00fcrich",
    "wof:name":"Josef Hagen Service Partner Hagen",
    "wof:placetype":"venue"
},
  "geometry": {"coordinates":[8.8605594635,47.6586151123],"type":"Point"}
}