{
  "type": "Feature",
  "properties": {
    "iso:country":"CH",
    "sg:address":"Unterdorfstr. 11",
    "sg:city":"Madiswil",
    "sg:orig_category":"Erschliessung von Grundst\u00fccken",
    "sg:phone":"+41 31 740 52 18",
    "sg:postcode":"4934",
    "sg:province":"Bern",
    "wof:name":"Liberale Baugenossenschaft Habitat",
    "wof:placetype":"venue"
},
  "geometry": {"coordinates":[7.2390007973,46.9028816223],"type":"Point"}
}