{
  "type": "Feature",
  "properties": {
    "addr:full":"Hauptstrasse 21 Zumholz Fribourg 1719",
    "addr:housenumber":"21",
    "addr:postcode":"1719",
    "addr:street":"Hauptstrasse",
    "iso:country":"CH",
    "sg:address":"Hauptstrasse 21",
    "sg:city":"Zumholz",
    "sg:orig_category":"Autolackierereien",
    "sg:phone":"+41 26 419 14 92",
    "sg:postcode":"1719",
    "sg:province":"Fribourg",
    "wof:name":"Kanis Zbinden Automalerei",
    "wof:placetype":"venue"
},
  "geometry": {"coordinates":[7.290423,46.754398],"type":"Point"}
}