{
  "type": "Feature",
  "properties": {
    "iso:country":"CH",
    "sg:address":"Kantonstrasse 14",
    "sg:city":"Sch\u00fcbelbach",
    "sg:orig_category":"Handel mit Motorr\u00e4dern, Teilen U Zubeh\u00f6r Instandhaltung U Reparatur von Motorr\u00e4dern",
    "sg:phone":"+41 55 440 36 35",
    "sg:postcode":"8862",
    "sg:province":"Schwyz",
    "wof:name":"Eichmann",
    "wof:placetype":"venue"
},
  "geometry": {"coordinates":[8.9304885864,47.1732978821],"type":"Point"}
}