{
  "type": "Feature",
  "properties": {
    "iso:country":"CH",
    "sg:address":"Via Balestra 27",
    "sg:city":"Lugano",
    "sg:orig_category":"Advokaturb\u00fcros",
    "sg:phone":"+41 91 922 05 55",
    "sg:postcode":"6900",
    "sg:province":"Ticino",
    "wof:name":"Yves Fl\u00fcckiger Studio Legale",
    "wof:placetype":"venue"
},
  "geometry": {"coordinates":[8.957789,46.00795],"type":"Point"}
}