{
  "type": "Feature",
  "properties": {
    "iso:country":"CH",
    "sg:address":"St.galler Strasse 117",
    "sg:city":"Arbon",
    "sg:orig_category":"Sportvereine Boccia",
    "sg:phone":"+41 71 446 64 90",
    "sg:postcode":"9320",
    "sg:province":"Thurgau",
    "wof:name":"Boccia-club Arbon",
    "wof:placetype":"venue"
},
  "geometry": {"coordinates":[9.4247303009,47.5101318359],"type":"Point"}
}