{
  "type": "Feature",
  "properties": {
    "iso:country":"CH",
    "sg:address":"Messeplatz 1 4058 Basel. Postfach",
    "sg:city":"Basel",
    "sg:orig_category":"RESTAURANTS: TEA-ROOMS",
    "sg:phone":"+41 61 686 38 20",
    "sg:postcode":"4051",
    "sg:province":"Basel-Stadt",
    "wof:name":"Megastro Ag Gastst\u00e4tten; Betrieb",
    "wof:placetype":"venue"
},
  "geometry": {"coordinates":[7.5995140076,47.5636901855],"type":"Point"}
}