{
  "type": "Feature",
  "properties": {
    "iso:country":"CH",
    "sg:address":"Pictet-de-rochemont Av. 6 1207 Gen\u00e8ve. Postfach",
    "sg:city":"Gen\u00e8ve",
    "sg:orig_category":"Detailhandel mit Brot, Back U S\u00fcsswaren",
    "sg:postcode":"1207",
    "sg:province":"Gen\u00e8ve",
    "wof:name":"P\u00e2tisserie R. Berger",
    "wof:placetype":"venue"
},
  "geometry": {"coordinates":[6.157445,46.202236],"type":"Point"}
}