{
  "type": "Feature",
  "properties": {
    "iso:country":"CH",
    "sg:address":"Bahnhofstrasse 31",
    "sg:city":"Wangs",
    "sg:classifiers":[
        {
            "category":"Travel",
            "subcategory":"Hotels & Motels",
            "type":"Entertainment"
        }
    ],
    "sg:phone":"+41 81 723 48 18",
    "sg:postcode":"7323",
    "sg:province":"St. Gallen",
    "sg:tags":[
        "hotels",
        "mit",
        "restaurant"
    ],
    "wof:name":"Park-hotel Pizol",
    "wof:placetype":"venue"
},
  "geometry": {"coordinates":[9.4341125488,47.0368614197],"type":"Point"}
}