{
  "type": "Feature",
  "properties": {
    "iso:country":"CH",
    "sg:address":"1747",
    "sg:city":"Corserey",
    "sg:orig_category":"Landesverteidigung, Sozialversicherung \u00d6ffentliche Verwaltung",
    "sg:phone":"+41 26 470 17 22",
    "sg:postcode":"1747",
    "sg:province":"Fribourg",
    "wof:name":"Centre De Protection Civile",
    "wof:placetype":"venue"
},
  "geometry": {"coordinates":[6.9889202118,46.7712287903],"type":"Point"}
}