{
  "type": "Feature",
  "properties": {
    "iso:country":"CH",
    "sg:address":"Kirchrain 11",
    "sg:city":"Sutz",
    "sg:orig_category":"Grosshandel mit Nahrungsmitteln, Getr\u00e4nken U Tabakwaren ohne ausgepr\u00e4gten Schwerpunkt",
    "sg:phone":"+41 32 397 10 05",
    "sg:postcode":"2572",
    "sg:province":"Bern",
    "wof:name":"Camping L\u00e4deli Am See, Maffei Karin",
    "wof:placetype":"venue"
},
  "geometry": {"coordinates":[7.2183728218,47.1072349548],"type":"Point"}
}