{
  "type": "Feature",
  "properties": {
    "iso:country":"CH",
    "sg:address":"Avenue De Lucens 12",
    "sg:city":"Moudon",
    "sg:orig_category":"Handel mit Motorr\u00e4dern, Teilen U Zubeh\u00f6r Instandhaltung U Reparatur von Motorr\u00e4dern",
    "sg:phone":"+41 79 649 25 39",
    "sg:postcode":"1510",
    "sg:province":"Vaud",
    "wof:name":"Renzo Lovisetto Cycles Motos",
    "wof:placetype":"venue"
},
  "geometry": {"coordinates":[6.8038020134,46.6718826294],"type":"Point"}
}