{
  "type": "Feature",
  "properties": {
    "iso:country":"CH",
    "sg:address":"Bernstrasse 11",
    "sg:city":"Konolfingen",
    "sg:orig_category":"Detailhandel mit Fahrr\u00e4dern Detailhandel mit Sportartikeln",
    "sg:phone":"+41 31 791 15 16",
    "sg:postcode":"3510",
    "sg:province":"Bern",
    "wof:name":"Mr. Feelgood Matthias Liechti Velo-bike & Snowboard",
    "wof:placetype":"venue"
},
  "geometry": {"coordinates":[7.6171278954,46.8787269592],"type":"Point"}
}