{
  "type": "Feature",
  "properties": {
    "iso:country":"CH",
    "sg:address":"Chemin Louis-dunant 15",
    "sg:city":"Meyrin",
    "sg:orig_category":"Pensionskassen",
    "sg:phone":"+41 22 989 89 89",
    "sg:postcode":"1217",
    "sg:province":"Gen\u00e8ve",
    "wof:name":"Fondation De Pr\u00e9voyance En Faveur Du Personnel De Praxair Surface Technologies (europe) Sa",
    "wof:placetype":"venue"
},
  "geometry": {"coordinates":[6.0722160339,46.2284431458],"type":"Point"}
}