{
  "type": "Feature",
  "properties": {
    "iso:country":"CH",
    "sg:address":"Homburgerstrasse 24 4132 Muttenz. Postfach 1",
    "sg:city":"Muttenz",
    "sg:orig_category":"Bauschreinerei Detailhandel mit M\u00f6beln U Haushaltsgegenst\u00e4nden",
    "sg:phone":"+41 61 461 44 40",
    "sg:postcode":"4132",
    "sg:province":"Basel-Landschaft",
    "wof:name":"Domino M\u00f6bel Ag",
    "wof:placetype":"venue"
},
  "geometry": {"coordinates":[7.65159,47.531452],"type":"Point"}
}