{
  "type": "Feature",
  "properties": {
    "iso:country":"CH",
    "sg:address":"6877",
    "sg:city":"Coldrerio",
    "sg:orig_category":"Elektroinstallation",
    "sg:phone":"+41 91 646 37 51",
    "sg:postcode":"6877",
    "sg:province":"Ticino",
    "wof:name":"Osvaldo Bianchi Impianti Elettrici",
    "wof:placetype":"venue"
},
  "geometry": {"coordinates":[8.9850301743,45.8534698486],"type":"Point"}
}