{
  "type": "Feature",
  "properties": {
    "iso:country":"CH",
    "sg:address":"6802",
    "sg:city":"Rivera",
    "sg:orig_category":"Sanit\u00e4r, Heizungs U L\u00fcftungsinstallation",
    "sg:postcode":"6802",
    "sg:province":"Ticino",
    "wof:name":"Candusso, Matter & Vaucher S\u00e0rl",
    "wof:placetype":"venue"
},
  "geometry": {"coordinates":[6.9310851097,46.9903335571],"type":"Point"}
}