{
  "type": "Feature",
  "properties": {
    "iso:country":"CH",
    "sg:address":"Neue Badstrasse 4654 Lostorf. Postfach 124",
    "sg:city":"Lostorf",
    "sg:orig_category":"Verm\u00f6gensverwaltung",
    "sg:phone":"+41 62 298 27 84",
    "sg:postcode":"4654",
    "sg:province":"Solothurn",
    "wof:name":"Schiess Portfolio Management",
    "wof:placetype":"venue"
},
  "geometry": {"coordinates":[7.9366488457,47.3937835693],"type":"Point"}
}