{
  "type": "Feature",
  "properties": {
    "addr:full":"H\u00fcnenbergerstrasse 12 Cham Zug 6330",
    "addr:housenumber":"12",
    "addr:postcode":"6330",
    "addr:street":"Huenenbergerstrasse;Zug",
    "iso:country":"CH",
    "sg:address":"H\u00fcnenbergerstrasse 12",
    "sg:city":"Cham",
    "sg:orig_category":"Detailhandel mit Beleuchtungs U Haushaltsgegenst\u00e4nden Herstellung von sonstigen elektrischen Ausr\u00fcst",
    "sg:phone":"+41 41 780 15 55",
    "sg:postcode":"6330",
    "sg:province":"Zug",
    "wof:name":"Ertle Audio Video Ag Radio/tv & Haushaltapparate",
    "wof:placetype":"venue"
},
  "geometry": {"coordinates":[8.456959,47.179752],"type":"Point"}
}