{
  "type": "Feature",
  "properties": {
    "iso:country":"CH",
    "sg:address":"Obere Dattenbergstrasse 49",
    "sg:city":"Kriens",
    "sg:orig_category":"Architekturb\u00fcros",
    "sg:phone":"+41 61 711 76 49",
    "sg:postcode":"6010",
    "sg:province":"Luzern",
    "wof:name":"Urs Uebelhart Architekturb\u00fcro",
    "wof:placetype":"venue"
},
  "geometry": {"coordinates":[7.591639,47.493679],"type":"Point"}
}