{
  "type": "Feature",
  "properties": {
    "iso:country":"CH",
    "sg:address":"Blattenstrasse 12 8603 Schwerzenbach. Postfach",
    "sg:city":"Schwerzenbach",
    "sg:orig_category":"Herstellung von sonstigen elektrischen Ausr\u00fcstungen",
    "sg:postcode":"8609",
    "sg:province":"Z\u00fcrich",
    "wof:name":"Reich Sicherheit",
    "wof:placetype":"venue"
},
  "geometry": {"coordinates":[8.6508350372,47.3843536377],"type":"Point"}
}