{
  "type": "Feature",
  "properties": {
    "iso:country":"CH",
    "sg:address":"L\u00f6wenstrasse 65 /67",
    "sg:city":"Z\u00fcrich",
    "sg:orig_category":"Zahnarztpraxen",
    "sg:postcode":"8001",
    "sg:province":"Z\u00fcrich",
    "wof:name":"Shandy S\u00e0rl",
    "wof:placetype":"venue"
},
  "geometry": {"coordinates":[1.9467660189,50.2957191467],"type":"Point"}
}