{
  "type": "Feature",
  "properties": {
    "iso:country":"CH",
    "sg:address":"Haldimand Rue 1",
    "sg:city":"Lausanne",
    "sg:orig_category":"Wirtschaftspr\u00fcfung, Steuerberatung U Treuhand",
    "sg:phone":"+41 31 982 04 04",
    "sg:postcode":"1003",
    "sg:province":"Vaud",
    "wof:name":"Figas Autogewerbe-treuhand Der Schweiz",
    "wof:placetype":"venue"
},
  "geometry": {"coordinates":[7.3616409302,46.9164810181],"type":"Point"}
}