{
  "type": "Feature",
  "properties": {
    "iso:country":"CH",
    "sg:address":"Dorfstrasse 73 8706 Meilen. Postfach",
    "sg:city":"Meilen",
    "sg:orig_category":"Nationale Postdienste",
    "sg:phone":"+41 19250151",
    "sg:postcode":"8706",
    "sg:province":"Z\u00fcrich",
    "wof:name":"Die Schweizerische Post",
    "wof:placetype":"venue"
},
  "geometry": {"coordinates":[8.6423330307,47.2699661255],"type":"Point"}
}