{
  "type": "Feature",
  "properties": {
    "iso:country":"CH",
    "sg:address":"M\u00fchlestrasse 6",
    "sg:city":"Reichenburg",
    "sg:orig_category":"G\u00fcterbef\u00f6rderung im Strassenverkehr",
    "sg:phone":"+41 55 444 17 32",
    "sg:postcode":"8864",
    "sg:province":"Schwyz",
    "wof:name":"Weber A., Transporte",
    "wof:placetype":"venue"
},
  "geometry": {"coordinates":[8.9747495651,47.1729927063],"type":"Point"}
}