{
  "type": "Feature",
  "properties": {
    "addr:full":"Chlupfgasse 17 Bassersdorf Z\u00fcrich 8303",
    "addr:housenumber":"17",
    "addr:postcode":"8303",
    "addr:street":"Chlupfgasse",
    "iso:country":"CH",
    "sg:address":"Chlupfgasse 17",
    "sg:city":"Bassersdorf",
    "sg:orig_category":"Allgemeiner Hoch U Tiefbau",
    "sg:postcode":"8303",
    "sg:province":"Z\u00fcrich",
    "wof:name":"Oehri-schweizer Ag",
    "wof:placetype":"venue"
},
  "geometry": {"coordinates":[8.623218,47.443588],"type":"Point"}
}