{
  "type": "Feature",
  "properties": {
    "iso:country":"CH",
    "sg:address":"Birkenweg 11 6072 Sachseln. Postfach",
    "sg:city":"Sachseln",
    "sg:orig_category":"Elektroinstallation",
    "sg:phone":"+41 71 930 03 00",
    "sg:postcode":"6072",
    "sg:province":"Obwalden",
    "wof:name":"Elbaz-elektrofachgesch\u00e4ft Ag, Bazenheid",
    "wof:placetype":"venue"
},
  "geometry": {"coordinates":[9.0401592255,47.41065979],"type":"Point"}
}