{
  "type": "Feature",
  "properties": {
    "iso:country":"CH",
    "sg:address":"Rue Des Indiennes 13a",
    "sg:city":"Marin-centre",
    "sg:orig_category":"Herstellung U Veredlung von sonstigem Glas Herstellung von Kunststoffwaren",
    "sg:phone":"+41 32 753 33 61",
    "sg:postcode":"2074",
    "sg:province":"Neuch\u00e2tel",
    "wof:name":"Kyburz Et Cie Sa",
    "wof:placetype":"venue"
},
  "geometry": {"coordinates":[6.9968938828,47.0112075806],"type":"Point"}
}