{
  "type": "Feature",
  "properties": {
    "iso:country":"CH",
    "sg:address":"Bodackerstrasse 14",
    "sg:city":"Dietikon",
    "sg:orig_category":"Instandhaltung U Reparatur von Automobilen",
    "sg:phone":"+41 17404000",
    "sg:postcode":"8953",
    "sg:province":"Z\u00fcrich",
    "wof:name":"Garage Micar Ag",
    "wof:placetype":"venue"
},
  "geometry": {"coordinates":[8.3863143921,47.4123382568],"type":"Point"}
}