{
  "type": "Feature",
  "properties": {
    "iso:country":"CH",
    "sg:address":"Steistegstrasse 11 6430 Schwyz. Postfach 54",
    "sg:city":"Schwyz",
    "sg:orig_category":"Erwachsenenbildung U Unterricht Unternehmensberatung",
    "sg:phone":"+41 71 278 60 80",
    "sg:postcode":"6431",
    "sg:province":"Schwyz",
    "wof:name":"Ibs Institut Dr. B\u00fcrkle & Partner Gmbh St. Gallen",
    "wof:placetype":"venue"
},
  "geometry": {"coordinates":[9.3368339539,47.4125785828],"type":"Point"}
}