{
  "type": "Feature",
  "properties": {
    "iso:country":"CH",
    "sg:address":"Domaine Du Paradau",
    "sg:city":"Gland",
    "sg:orig_category":"Obstbau",
    "sg:phone":"+41 22 364 13 07",
    "sg:postcode":"1196",
    "sg:province":"Vaud",
    "wof:name":"Jean-pierre Bruch Arboriculteur",
    "wof:placetype":"venue"
},
  "geometry": {"coordinates":[6.2744989395,46.4093666077],"type":"Point"}
}