{
  "type": "Feature",
  "properties": {
    "iso:country":"CH",
    "sg:address":"Buechstrasse 27",
    "sg:city":"Jona",
    "sg:classifiers":[
        {
            "category":"Home & Garden",
            "subcategory":"Furniture",
            "type":"Retail Goods"
        }
    ],
    "sg:phone":"+41 55 225 50 50",
    "sg:postcode":"8645",
    "sg:province":"St. Gallen",
    "sg:tags":[
        "accessory"
    ],
    "wof:name":"Eggenschwiler Ag",
    "wof:placetype":"venue"
},
  "geometry": {"coordinates":[8.8668851852,47.2274932861],"type":"Point"}
}