{
  "type": "Feature",
  "properties": {
    "iso:country":"CH",
    "sg:address":"Schlossgutweg 3a 3073 G\u00fcmligen. Postfach",
    "sg:city":"G\u00fcmligen",
    "sg:classifiers":[
        {
            "category":"Professional",
            "subcategory":"Employment Agencies",
            "type":"Services"
        }
    ],
    "sg:phone":"+41 31 954 11 89",
    "sg:postcode":"3073",
    "sg:province":"Bern",
    "sg:tags":[
        "personal",
        "u",
        "stellenvermittlung"
    ],
    "wof:name":"Schmid Telecomsulting",
    "wof:placetype":"venue"
},
  "geometry": {"coordinates":[7.5150580406,46.9352149963],"type":"Point"}
}