{
  "type": "Feature",
  "properties": {
    "iso:country":"CH",
    "sg:address":"Kaufplatz 10",
    "sg:city":"Visp",
    "sg:orig_category":"Fachdetailhandel in Verkaufsr\u00e4umen",
    "sg:postcode":"3930",
    "sg:province":"Valais",
    "wof:name":"Fl\u00fcckiger Lara",
    "wof:placetype":"venue"
},
  "geometry": {"coordinates":[7.8813848495,46.2908935547],"type":"Point"}
}