{
  "type": "Feature",
  "properties": {
    "iso:country":"CH",
    "sg:address":"Oberebenestrasse 63",
    "sg:city":"Bremgarten",
    "sg:classifiers":[
        {
            "category":"Utilities",
            "subcategory":"Natural Gas",
            "type":"Services"
        }
    ],
    "sg:phone":"+41 56 631 95 80",
    "sg:postcode":"5620",
    "sg:province":"Aargau",
    "sg:tags":[
        "equipment",
        "heating",
        "system",
        "air"
    ],
    "wof:name":"Babcock Wanson Ag",
    "wof:placetype":"venue"
},
  "geometry": {"coordinates":[8.327843,47.352978],"type":"Point"}
}