{
  "type": "Feature",
  "properties": {
    "iso:country":"CH",
    "sg:address":"Wiesenstrasse 5 8008 Z\u00fcrich. Postfach",
    "sg:city":"Z\u00fcrich",
    "sg:orig_category":"Architektur U Ingenieurb\u00fcros",
    "sg:postcode":"8001",
    "sg:province":"Z\u00fcrich",
    "wof:name":"Anywey, Dr. Hubert M. Wey Ingenieurb\u00fcro, Warenhandel Usw",
    "wof:placetype":"venue"
},
  "geometry": {"coordinates":[8.551332,47.36216],"type":"Point"}
}