{
  "type": "Feature",
  "properties": {
    "iso:country":"CH",
    "sg:address":"Rue Des Murs",
    "sg:city":"Coppet",
    "sg:orig_category":"Physiotherapie",
    "sg:phone":"+41 22 776 27 27",
    "sg:postcode":"1296",
    "sg:province":"Vaud",
    "wof:name":"Physio-centre De Coppet",
    "wof:placetype":"venue"
},
  "geometry": {"coordinates":[6.1919307709,46.3161392212],"type":"Point"}
}