{
  "type": "Feature",
  "properties": {
    "iso:country":"CH",
    "sg:address":"Seestrasse 49",
    "sg:city":"Thun",
    "sg:orig_category":"Sportvereine",
    "sg:postcode":"3604",
    "sg:province":"Bern",
    "wof:name":"Panathlon-club Berner Oberland",
    "wof:placetype":"venue"
},
  "geometry": {"coordinates":[7.6330227852,46.7447738647],"type":"Point"}
}