{
  "type": "Feature",
  "properties": {
    "iso:country":"CH",
    "sg:address":"Grenchenstr. 14",
    "sg:city":"Solothurn",
    "sg:classifiers":[
        {
            "category":"Manufacturing",
            "subcategory":"Metals",
            "type":"Manufacturing & Wholesale Goods"
        }
    ],
    "sg:phone":"+41 32 623 27 23",
    "sg:postcode":"4503",
    "sg:province":"Solothurn",
    "sg:tags":[
        "-",
        "machine",
        "equipment",
        "engineering",
        "machinery",
        "mechanical"
    ],
    "wof:name":"Simonet Ag",
    "wof:placetype":"venue"
},
  "geometry": {"coordinates":[7.5294909477,47.2132301331],"type":"Point"}
}