{
  "type": "Feature",
  "properties": {
    "iso:country":"CH",
    "sg:address":"Harschwendi",
    "sg:city":"Waldstatt",
    "sg:orig_category":"Organisationen des Gesundheitswesen",
    "sg:postcode":"9104",
    "sg:province":"Appenzell Ausserrhoden",
    "wof:name":"Samariterverein Waldstatt",
    "wof:placetype":"venue"
},
  "geometry": {"coordinates":[9.2741651535,47.3528938293],"type":"Point"}
}