{
  "type": "Feature",
  "properties": {
    "iso:country":"CH",
    "sg:address":"Schnydermatt 1",
    "sg:city":"Sursee",
    "sg:orig_category":"G\u00fcterbef\u00f6rderung im Strassenverkehr",
    "sg:phone":"+41 41 921 20 19",
    "sg:postcode":"6210",
    "sg:province":"Luzern",
    "wof:name":"Paul Huwyler Offiz.camionnage",
    "wof:placetype":"venue"
},
  "geometry": {"coordinates":[8.1017637253,47.1709747314],"type":"Point"}
}