{
  "type": "Feature",
  "properties": {
    "iso:country":"CH",
    "sg:address":"Bardella",
    "sg:city":"Maienfeld",
    "sg:orig_category":"Herstellung von sonstigen Maschinen f\u00fcr unspezifische Verwendung R\u00fcckgewinnung U Vorbereitung f\u00fcr di",
    "sg:phone":"+41 81 302 22 03",
    "sg:postcode":"7304",
    "sg:province":"Graubunden",
    "wof:name":"Abe Gmbh Abfallbewirtschaftung & Entsorgung",
    "wof:placetype":"venue"
},
  "geometry": {"coordinates":[9.5343360901,47.0041847229],"type":"Point"}
}