{
  "type": "Feature",
  "properties": {
    "iso:country":"CH",
    "sg:address":"Winterthurstrasse 1",
    "sg:city":"Neftenbach",
    "sg:orig_category":"Eisenwaren Detailhandel",
    "sg:phone":"+41 52 315 12 05",
    "sg:postcode":"8413",
    "sg:province":"Z\u00fcrich",
    "wof:name":"Ulrich Hug Eisenwaren",
    "wof:placetype":"venue"
},
  "geometry": {"coordinates":[8.6684045792,47.5281982422],"type":"Point"}
}