{
  "type": "Feature",
  "properties": {
    "iso:country":"CH",
    "sg:address":"Place De La Navigation 10",
    "sg:city":"Lausanne",
    "sg:orig_category":"Kinderkrippen U horte",
    "sg:phone":"+41 21 616 28 27",
    "sg:postcode":"1006",
    "sg:province":"Vaud",
    "wof:name":"Garderie D'enfants Le Petit Prince",
    "wof:placetype":"venue"
},
  "geometry": {"coordinates":[6.6260061264,46.5072822571],"type":"Point"}
}