{
  "type": "Feature",
  "properties": {
    "iso:country":"CH",
    "sg:address":"Kalkbreitestrasse 69 8003 Z\u00fcrich. Postfach",
    "sg:city":"Z\u00fcrich",
    "sg:orig_category":"Erwachsenenbildung U Unterricht",
    "sg:phone":"+41 14501045",
    "sg:postcode":"8003",
    "sg:province":"Z\u00fcrich",
    "wof:name":"Cotras Coaching - Training - Assessment",
    "wof:placetype":"venue"
},
  "geometry": {"coordinates":[8.5179481506,47.3725700378],"type":"Point"}
}