{
  "type": "Feature",
  "properties": {
    "iso:country":"CH",
    "sg:address":"Gubelstrasse 22",
    "sg:city":"Zug",
    "sg:orig_category":"Herstellung von Platten, Folien, Schl\u00e4uchen U Profilen aus Kunststoff",
    "sg:postcode":"6300",
    "sg:province":"Zug",
    "wof:name":"Kurz Leonhard Gmbh & Co., F\u00fcrth (d), Zweigniederlassung Zug",
    "wof:placetype":"venue"
},
  "geometry": {"coordinates":[8.515376091,47.1746673584],"type":"Point"}
}