{
  "type": "Feature",
  "properties": {
    "iso:country":"CH",
    "sg:address":"Fahrweidstrasse 26",
    "sg:city":"Fahrweid",
    "sg:orig_category":"Herstellung von sonstigen Metallwaren Werbegrafikateliers",
    "sg:phone":"+41 17470980",
    "sg:postcode":"8951",
    "sg:province":"Z\u00fcrich",
    "wof:name":"Riccardo Navetta",
    "wof:placetype":"venue"
},
  "geometry": {"coordinates":[8.4143638611,47.409942627],"type":"Point"}
}