{
  "type": "Feature",
  "properties": {
    "iso:country":"CH",
    "sg:address":"Uznabergstrasse 18",
    "sg:city":"Uznach",
    "sg:orig_category":"Sanit\u00e4r U Heizungsinstallation",
    "sg:phone":"+41 18444481",
    "sg:postcode":"8730",
    "sg:province":"St. Gallen",
    "wof:name":"Guido Sigrist Zentralheizungen",
    "wof:placetype":"venue"
},
  "geometry": {"coordinates":[8.4036283493,47.4478263855],"type":"Point"}
}