{
  "type": "Feature",
  "properties": {
    "iso:country":"CH",
    "sg:address":"Uraniastrasse 28 8001 Z\u00fcrich. Postfach 2132",
    "sg:city":"Z\u00fcrich",
    "sg:orig_category":"Aktivit\u00e4t der Bankinstitute",
    "sg:phone":"+41 71 228 02 28",
    "sg:postcode":"8022",
    "sg:province":"Z\u00fcrich",
    "wof:name":"Bank Thorbecke Ag",
    "wof:placetype":"venue"
},
  "geometry": {"coordinates":[9.373757,47.425121],"type":"Point"}
}