{
  "type": "Feature",
  "properties": {
    "iso:country":"CH",
    "sg:address":"Thurgauerstrasse 54 8050 Z\u00fcrich. Postfach",
    "sg:city":"Z\u00fcrich",
    "sg:orig_category":"Privatbanken",
    "sg:phone":"+41 13068511",
    "sg:postcode":"8050",
    "sg:province":"Z\u00fcrich",
    "wof:name":"Abb Export Bank",
    "wof:placetype":"venue"
},
  "geometry": {"coordinates":[8.5526027679,47.41563797],"type":"Point"}
}