{
  "type": "Feature",
  "properties": {
    "iso:country":"CH",
    "sg:address":"Pestalozzistrasse 11",
    "sg:city":"Rorschach",
    "sg:orig_category":"Herstellung von Metallerzeugnissen ohne Maschinenbau Maschinenbau",
    "sg:phone":"+41 22 906 46 00",
    "sg:postcode":"9400",
    "sg:province":"St. Gallen",
    "wof:name":"Speno International Sa",
    "wof:placetype":"venue"
},
  "geometry": {"coordinates":[6.148713,46.218231],"type":"Point"}
}