{
  "type": "Feature",
  "properties": {
    "iso:country":"CH",
    "sg:address":"Erlenstr\u00e4sschen 62",
    "sg:city":"Riehen",
    "sg:orig_category":"Datenverarbeitungsdienste",
    "sg:phone":"+41 61 645 95 55",
    "sg:postcode":"4125",
    "sg:province":"Basel-Stadt",
    "wof:name":"Universal Consulting Bureau Ag",
    "wof:placetype":"venue"
},
  "geometry": {"coordinates":[7.645925,47.585373],"type":"Point"}
}