{
  "type": "Feature",
  "properties": {
    "iso:country":"CH",
    "sg:address":"Simplon Route Du 5",
    "sg:city":"Mayens-de-saxon",
    "sg:classifiers":[
        {
            "category":"Education",
            "subcategory":"Library",
            "type":"Public Place"
        }
    ],
    "sg:postcode":"1907",
    "sg:province":"Valais",
    "sg:tags":[
        "u",
        "bibliotheken",
        "archive"
    ],
    "wof:name":"Librairie Lardanchet, Chemineau-lardanchet Jean-pierre",
    "wof:placetype":"venue"
},
  "geometry": {"coordinates":[7.1736750603,46.148891449],"type":"Point"}
}