{
  "type": "Feature",
  "properties": {
    "iso:country":"CH",
    "sg:address":"1034",
    "sg:city":"Boussens",
    "sg:orig_category":"Vorschulen, Kinderg\u00e4rten",
    "sg:postcode":"1034",
    "sg:province":"Vaud",
    "wof:name":"Ecole Enfantine",
    "wof:placetype":"venue"
},
  "geometry": {"coordinates":[6.5845799446,46.6043014526],"type":"Point"}
}