{
  "type": "Feature",
  "properties": {
    "iso:country":"CH",
    "sg:address":"R\u00fceggisingerstrasse 5",
    "sg:city":"Emmenbr\u00fccke",
    "sg:orig_category":"Chemische Reinigung",
    "sg:phone":"+41 41 260 72 55",
    "sg:postcode":"6020",
    "sg:province":"Luzern",
    "wof:name":"Max Huber Textilreinigung Exacta",
    "wof:placetype":"venue"
},
  "geometry": {"coordinates":[8.277155,47.075275],"type":"Point"}
}