{
  "type": "Feature",
  "properties": {
    "iso:country":"CH",
    "sg:address":"Belforterstrasse 135",
    "sg:city":"Basel",
    "sg:orig_category":"RESTAURANTS: TEA-ROOMS",
    "sg:phone":"+41 61 381 43 33",
    "sg:postcode":"4055",
    "sg:province":"Basel-Stadt",
    "wof:name":"Gartenbad Bachgraben",
    "wof:placetype":"venue"
},
  "geometry": {"coordinates":[7.557390213,47.5633049011],"type":"Point"}
}