{
  "type": "Feature",
  "properties": {
    "iso:country":"CH",
    "sg:address":"Kapuzinerstrasse 29 3902 Glis. Postfach",
    "sg:city":"Glis",
    "sg:orig_category":"Unternehmensberatung",
    "sg:phone":"+41 27 922 11 33",
    "sg:postcode":"3902",
    "sg:province":"Valais",
    "wof:name":"Sitora Unternehmungsberatung Ag",
    "wof:placetype":"venue"
},
  "geometry": {"coordinates":[7.987724781,46.3143463135],"type":"Point"}
}