{
  "type": "Feature",
  "properties": {
    "iso:country":"CH",
    "sg:address":"Gempenstrasse 56",
    "sg:city":"Basel",
    "sg:orig_category":"Psychotherapie",
    "sg:phone":"+41 61 272 13 22",
    "sg:postcode":"4053",
    "sg:province":"Basel-Stadt",
    "wof:name":"Franziska Steiger Polarity-therapeutin",
    "wof:placetype":"venue"
},
  "geometry": {"coordinates":[7.5864009857,47.5440368652],"type":"Point"}
}