{
  "type": "Feature",
  "properties": {
    "iso:country":"CH",
    "sg:address":"Gewerbestrasse 11",
    "sg:city":"Cham",
    "sg:orig_category":"Bau von Strassen, Sportanlagen U Bahnverkehrsstrecken",
    "sg:phone":"+41 41 740 20 05",
    "sg:postcode":"6330",
    "sg:province":"Zug",
    "wof:name":"H\u00fcppi Ag",
    "wof:placetype":"venue"
},
  "geometry": {"coordinates":[8.472043,47.188694],"type":"Point"}
}