{
  "type": "Feature",
  "properties": {
    "iso:country":"CH",
    "sg:address":"Hummelbergstrasse 25",
    "sg:city":"Jona",
    "sg:orig_category":"Vermietung U Verpachtung von eigenen Immobilien",
    "sg:postcode":"8645",
    "sg:province":"St. Gallen",
    "wof:name":"Centrum Immobilien Ag",
    "wof:placetype":"venue"
},
  "geometry": {"coordinates":[8.8533143997,47.2315788269],"type":"Point"}
}