{
  "type": "Feature",
  "properties": {
    "iso:country":"CH",
    "sg:address":"Unterlachenstrasse 17",
    "sg:city":"Luzern",
    "sg:orig_category":"Elektrizit\u00e4tsversorgung Herstellung von Metallerzeugnissen ohne Maschinenbau",
    "sg:phone":"+41 41 361 13 20",
    "sg:postcode":"6005",
    "sg:province":"Luzern",
    "wof:name":"Jaduro Ag",
    "wof:placetype":"venue"
},
  "geometry": {"coordinates":[8.3130569458,47.0421676636],"type":"Point"}
}