{
  "type": "Feature",
  "properties": {
    "iso:country":"CH",
    "sg:address":"Seetalstr. 302",
    "sg:city":"Birrwil",
    "sg:classifiers":[
        {
            "category":"Professional",
            "subcategory":"Engineering",
            "type":"Services"
        }
    ],
    "sg:phone":"+41 62 772 15 60",
    "sg:postcode":"5708",
    "sg:province":"Aargau",
    "sg:tags":[
        "machine",
        "-",
        "mechanical"
    ],
    "wof:name":"Kurt W\u00dcst Ag",
    "wof:placetype":"venue"
},
  "geometry": {"coordinates":[8.1987266541,47.2901573181],"type":"Point"}
}