{
  "type": "Feature",
  "properties": {
    "iso:country":"CH",
    "sg:address":"Juchgasse 14",
    "sg:city":"Zeiningen",
    "sg:orig_category":"Schiffsbau ohne Boots U Yachtbau",
    "sg:postcode":"4314",
    "sg:province":"Aargau",
    "wof:name":"H\u00e4nggi Ren\u00e9 Schiffbau + Seefahrt",
    "wof:placetype":"venue"
},
  "geometry": {"coordinates":[7.8729290962,47.5451812744],"type":"Point"}
}