{
  "type": "Feature",
  "properties": {
    "iso:country":"CH",
    "sg:address":"Gerbestrasse 5",
    "sg:city":"Einsiedeln",
    "sg:classifiers":[
        {
            "category":"Social Services",
            "subcategory":"Retirement Home",
            "type":"Services"
        }
    ],
    "sg:phone":"+41 55 412 25 15",
    "sg:postcode":"8840",
    "sg:province":"Schwyz",
    "sg:tags":[
        "pflegeheime",
        "u",
        "alters"
    ],
    "wof:name":"Altersheim Gerbe",
    "wof:placetype":"venue"
},
  "geometry": {"coordinates":[8.750023,47.132645],"type":"Point"}
}