{
  "type": "Feature",
  "properties": {
    "iso:country":"CH",
    "sg:address":"Frauwisstrasse 2 8493 Saland. Postfach",
    "sg:city":"Saland",
    "sg:orig_category":"RESTAURANTS: TEA-ROOMS",
    "sg:postcode":"8493",
    "sg:province":"Z\u00fcrich",
    "wof:name":"M\u00fcller-potterat Gmbh",
    "wof:placetype":"venue"
},
  "geometry": {"coordinates":[8.8541412354,47.3929214478],"type":"Point"}
}