{
  "type": "Feature",
  "properties": {
    "iso:country":"CH",
    "sg:address":"Unterdorf 139",
    "sg:city":"Ursenbach",
    "sg:classifiers":[
        {
            "category":"Structure",
            "subcategory":"Restrooms",
            "type":"Public Place"
        }
    ],
    "sg:phone":"+41 62 965 26 25",
    "sg:postcode":"4937",
    "sg:province":"Bern",
    "sg:tags":[
        "equipment",
        "bath"
    ],
    "wof:name":"Begert Gmbh",
    "wof:placetype":"venue"
},
  "geometry": {"coordinates":[7.776273,47.140923],"type":"Point"}
}