{
  "type": "Feature",
  "properties": {
    "iso:country":"CH",
    "sg:address":"Aegetli 7",
    "sg:city":"Thal",
    "sg:orig_category":"Mechanik Mechanische Werkst\u00e4tten",
    "sg:phone":"+41 79 354 90 91",
    "sg:postcode":"9425",
    "sg:province":"St. Gallen",
    "wof:name":"Moto Nautica Stelvio Calcinotto",
    "wof:placetype":"venue"
},
  "geometry": {"coordinates":[9.5810890198,47.4780273438],"type":"Point"}
}