{
  "type": "Feature",
  "properties": {
    "iso:country":"CH",
    "sg:address":"Fliederweg 2",
    "sg:city":"Grossh\u00f6chstetten",
    "sg:orig_category":"Maler U Glasergewerbe",
    "sg:postcode":"3506",
    "sg:province":"Bern",
    "wof:name":"Industriemalerei Zanin",
    "wof:placetype":"venue"
},
  "geometry": {"coordinates":[7.6407051086,46.9022789001],"type":"Point"}
}