{
  "type": "Feature",
  "properties": {
    "iso:country":"CH",
    "sg:address":"Kaysersbergstrasse 33",
    "sg:city":"Basel",
    "sg:orig_category":"Sportschulen Fern\u00f6stliche Kampfsportarten Sportvereine Judo and Karate",
    "sg:phone":"+41 61 321 82 50",
    "sg:postcode":"4055",
    "sg:province":"Basel-Stadt",
    "wof:name":"Karate-kai Basel",
    "wof:placetype":"venue"
},
  "geometry": {"coordinates":[7.5619602203,47.5659103394],"type":"Point"}
}