{
  "type": "Feature",
  "properties": {
    "iso:country":"CH",
    "sg:address":"Gontenstrasse 17",
    "sg:city":"Appenzell",
    "sg:orig_category":"Fernmeldedienste",
    "sg:postcode":"9050",
    "sg:province":"Appenzell Innerhoden",
    "wof:name":"Planetwerks Ag",
    "wof:placetype":"venue"
},
  "geometry": {"coordinates":[8.4357042313,47.4219360352],"type":"Point"}
}