{
  "type": "Feature",
  "properties": {
    "iso:country":"CH",
    "sg:address":"Baarerstrasse",
    "sg:city":"Zug",
    "sg:orig_category":"Architektur U Ingenieurb\u00fcros",
    "sg:postcode":"6300",
    "sg:province":"Zug",
    "wof:name":"Paznova Ag",
    "wof:placetype":"venue"
},
  "geometry": {"coordinates":[8.519565,47.182434],"type":"Point"}
}