{
  "type": "Feature",
  "properties": {
    "iso:country":"CH",
    "sg:address":"Werdstr. 327a",
    "sg:city":"Neuendorf",
    "sg:orig_category":"G\u00fcterbef\u00f6rderung im Strassenverkehr",
    "sg:postcode":"4623",
    "sg:province":"Solothurn",
    "wof:name":"Transporte K\u00fcng-zwischenberger",
    "wof:placetype":"venue"
},
  "geometry": {"coordinates":[7.8000431061,47.304233551],"type":"Point"}
}