{
  "type": "Feature",
  "properties": {
    "iso:country":"CH",
    "sg:address":"1173",
    "sg:city":"F\u00e9chy",
    "sg:orig_category":"Primarschulen",
    "sg:phone":"+41 26 660 81 12",
    "sg:postcode":"1173",
    "sg:province":"Vaud",
    "wof:name":"Ecole Primaire",
    "wof:placetype":"venue"
},
  "geometry": {"coordinates":[6.3741102219,46.4814109802],"type":"Point"}
}