{
  "type": "Feature",
  "properties": {
    "iso:country":"CH",
    "sg:address":"Dorfgasse 81 2513 Twann. Postfach",
    "sg:city":"Twann",
    "sg:orig_category":"RESTAURANTS: TEA-ROOMS",
    "sg:postcode":"2513",
    "sg:province":"Bern",
    "wof:name":"Taverna Romana, Meola",
    "wof:placetype":"venue"
},
  "geometry": {"coordinates":[7.1574869156,47.0953674316],"type":"Point"}
}