{
  "type": "Feature",
  "properties": {
    "iso:country":"CH",
    "sg:address":"Stei\u00e4cher",
    "sg:city":"Leuggern",
    "sg:orig_category":"Herstellung von Metallkonstruktionen Stahl U Leichtmetallbau",
    "sg:phone":"+41 56 268 00 20",
    "sg:postcode":"5316",
    "sg:province":"Aargau",
    "wof:name":"Erne H. Metallbau Ag",
    "wof:placetype":"venue"
},
  "geometry": {"coordinates":[8.221570015,47.5790786743],"type":"Point"}
}