{
  "type": "Feature",
  "properties": {
    "iso:country":"CH",
    "sg:address":"Z\u00fcrichweg 5",
    "sg:city":"R\u00fcmlang",
    "sg:orig_category":"Technische, physikalische U chemische Untersuchung Unternehmensberatung",
    "sg:phone":"+41 18180232",
    "sg:postcode":"8153",
    "sg:province":"Z\u00fcrich",
    "wof:name":"Sponsolim Umweltconsulting Binderheim Evi",
    "wof:placetype":"venue"
},
  "geometry": {"coordinates":[8.5279970169,47.4479637146],"type":"Point"}
}