{
  "type": "Feature",
  "properties": {
    "iso:country":"CH",
    "sg:address":"F\u00fcrfelderstrasse 81",
    "sg:city":"Riehen",
    "sg:orig_category":"Sportvereine Turnen",
    "sg:phone":"+41 61 601 50 09",
    "sg:postcode":"4125",
    "sg:province":"Basel-Stadt",
    "wof:name":"Kath.turn-& Sportverband Basel",
    "wof:placetype":"venue"
},
  "geometry": {"coordinates":[7.6362018585,47.5736579895],"type":"Point"}
}