{
  "type": "Feature",
  "properties": {
    "iso:country":"CH",
    "sg:address":"Br\u00fcckenstrasse 128",
    "sg:city":"Murgenthal",
    "sg:orig_category":"Mechanik",
    "sg:postcode":"4853",
    "sg:province":"Aargau",
    "wof:name":"Meister Ch. + M. Schweissarbeiten",
    "wof:placetype":"venue"
},
  "geometry": {"coordinates":[7.8325200081,47.2664527893],"type":"Point"}
}