{
  "type": "Feature",
  "properties": {
    "iso:country":"CH",
    "sg:address":"Gr\u00fcnauring 15",
    "sg:city":"Z\u00fcrich",
    "sg:orig_category":"Sportvereine Sch\u00fctzen",
    "sg:postcode":"8064",
    "sg:province":"Z\u00fcrich",
    "wof:name":"Schiessektion Der Uog",
    "wof:placetype":"venue"
},
  "geometry": {"coordinates":[8.489027977,47.3956336975],"type":"Point"}
}