{
  "type": "Feature",
  "properties": {
    "iso:country":"CH",
    "sg:address":"Rainweg 1",
    "sg:city":"Adelboden",
    "sg:orig_category":"Softwareentwicklung U beratung",
    "sg:phone":"+41 33 673 21 28",
    "sg:postcode":"3715",
    "sg:province":"Bern",
    "wof:name":"Fenas Software Ag",
    "wof:placetype":"venue"
},
  "geometry": {"coordinates":[7.5723347664,46.5037345886],"type":"Point"}
}