{
  "type": "Feature",
  "properties": {
    "iso:country":"CH",
    "sg:address":"Bernstr. 59",
    "sg:city":"Jegenstorf",
    "sg:classifiers":[
        {
            "category":"Manufacturing",
            "subcategory":"Tools & Machinery",
            "type":"Manufacturing & Wholesale Goods"
        }
    ],
    "sg:phone":"+41 31 764 99 11",
    "sg:postcode":"3303",
    "sg:province":"Bern",
    "sg:tags":[
        "equipment",
        "measurement",
        "-",
        "precision",
        "instrument"
    ],
    "wof:name":"Bourdon-hanni Ag",
    "wof:placetype":"venue"
},
  "geometry": {"coordinates":[7.504287,47.043015],"type":"Point"}
}