{
  "type": "Feature",
  "properties": {
    "iso:country":"CH",
    "sg:address":"Rue Dr-schwab 9",
    "sg:city":"St-imier",
    "sg:orig_category":"Detailhandel mit elektrischen Haushalts-,Radio U Fernsehger\u00e4ten sowie Musikinstrumenten",
    "sg:phone":"+41 14911709",
    "sg:postcode":"2610",
    "sg:province":"Bern",
    "wof:name":"Gac-trading Ag",
    "wof:placetype":"venue"
},
  "geometry": {"coordinates":[8.4458284378,47.3754997253],"type":"Point"}
}