{
  "type": "Feature",
  "properties": {
    "iso:country":"CH",
    "sg:address":"Chemin De La Cocuaz 46",
    "sg:city":"Vandoeuvres",
    "sg:orig_category":"Erbringung von Dienstleistungen f\u00fcr Unternehmen",
    "sg:postcode":"1253",
    "sg:province":"Gen\u00e8ve",
    "wof:name":"Rsvp Mosimann-connelly Karen",
    "wof:placetype":"venue"
},
  "geometry": {"coordinates":[6.2027797699,46.2158126831],"type":"Point"}
}