{
  "type": "Feature",
  "properties": {
    "iso:country":"CH",
    "sg:address":"Via Nassa 30",
    "sg:city":"Lugano",
    "sg:orig_category":"Detailhandel mit Damenbekleidung",
    "sg:phone":"+41 71 755 66 08",
    "sg:postcode":"6900",
    "sg:province":"Ticino",
    "wof:name":"Teresa Rosolia Boutique Fellini",
    "wof:placetype":"venue"
},
  "geometry": {"coordinates":[9.539274,47.377621],"type":"Point"}
}