{
  "type": "Feature",
  "properties": {
    "iso:country":"CH",
    "sg:address":"Schw\u00e4ndtenmos 15",
    "sg:city":"Zumikon",
    "sg:orig_category":"Grosshandel mit Getr\u00e4nken Grosshandel mit Wein U Spirituosen",
    "sg:phone":"+41 19843804",
    "sg:postcode":"8126",
    "sg:province":"Z\u00fcrich",
    "wof:name":"Vinaria Gmbh Weinprodukte; Im, Export, Handel",
    "wof:placetype":"venue"
},
  "geometry": {"coordinates":[8.6900548935,47.3005561829],"type":"Point"}
}