{
  "type": "Feature",
  "properties": {
    "iso:country":"CH",
    "sg:address":"Talacker 35",
    "sg:city":"Z\u00fcrich",
    "sg:orig_category":"Kosmetikinstitute",
    "sg:phone":"+41 61 711 05 03",
    "sg:postcode":"8001",
    "sg:province":"Z\u00fcrich",
    "wof:name":"Rosemarie Steiner Kosmetikinstitut",
    "wof:placetype":"venue"
},
  "geometry": {"coordinates":[7.5933899879,47.4937438965],"type":"Point"}
}