{
  "type": "Feature",
  "properties": {
    "iso:country":"CH",
    "sg:address":"Buchenrain 243.",
    "sg:city":"G\u00fcnsberg",
    "sg:orig_category":"Mechanik",
    "sg:postcode":"4524",
    "sg:province":"Solothurn",
    "wof:name":"Kampinex-technik Gmbh",
    "wof:placetype":"venue"
},
  "geometry": {"coordinates":[9.2546901703,47.4133110046],"type":"Point"}
}