{
  "type": "Feature",
  "properties": {
    "iso:country":"CH",
    "sg:address":"Stollenrain 12",
    "sg:city":"Arlesheim",
    "sg:orig_category":"Unclassifiable Establishments",
    "sg:postcode":"4144",
    "sg:province":"Basel-Landschaft",
    "wof:name":"'sunnegarte', Stiftung F\u00fcr Familienerg\u00e4nzende Kinderbetreuung",
    "wof:placetype":"venue"
},
  "geometry": {"coordinates":[7.6139740944,47.4929428101],"type":"Point"}
}