{
  "type": "Feature",
  "properties": {
    "iso:country":"CH",
    "sg:address":"Bernstrasse 61",
    "sg:city":"Schnottwil",
    "sg:orig_category":"Detailhandel mit Waren verschiedener Art, Hauptrichtung Nahrungsmittel",
    "sg:phone":"+41 32 351 24 38",
    "sg:postcode":"3253",
    "sg:province":"Solothurn",
    "wof:name":"Werner Suter Eisen-& Spezereihandlung",
    "wof:placetype":"venue"
},
  "geometry": {"coordinates":[7.3897800446,47.11743927],"type":"Point"}
}