{
  "type": "Feature",
  "properties": {
    "iso:country":"CH",
    "sg:address":"Bourguillon. 1700 Fribourg. Postfach",
    "sg:city":"Fribourg",
    "sg:orig_category":"Herstellung von sonstigen Produkten aus nichtmetallischen Mineralien",
    "sg:postcode":"1701",
    "sg:province":"Fribourg",
    "wof:name":"Baeriswyl Jules Enrobit",
    "wof:placetype":"venue"
},
  "geometry": {"coordinates":[7.1683549881,46.8073310852],"type":"Point"}
}