{
  "type": "Feature",
  "properties": {
    "addr:full":"Marktgasse 16-18 9220 Bischofszell. Postfach Bischofszell Thurgau 9220",
    "addr:housenumber":"16-18",
    "addr:postcode":"9220 bischofszell. postfach;9220",
    "addr:street":"Marktgasse",
    "iso:country":"CH",
    "sg:address":"Marktgasse 16-18 9220 Bischofszell. Postfach",
    "sg:city":"Bischofszell",
    "sg:orig_category":"Detailhandel mit Beleuchtungs U Haushaltsgegenst\u00e4nden",
    "sg:phone":"+41 71 422 18 23",
    "sg:postcode":"9220",
    "sg:province":"Thurgau",
    "wof:name":"Etter & Co Ag Eisenwaren Haushalt",
    "wof:placetype":"venue"
},
  "geometry": {"coordinates":[9.240322,47.493954],"type":"Point"}
}