{
  "type": "Feature",
  "properties": {
    "iso:country":"CH",
    "sg:address":"Grand-rue 14",
    "sg:city":"Begnins",
    "sg:orig_category":"Detailhandel mit Brot, Back U S\u00fcsswaren Detailhandel mit Waren verschiedener Art, Hauptrichtung Nahr",
    "sg:phone":"+41 22 366 13 25",
    "sg:postcode":"1268",
    "sg:province":"Vaud",
    "wof:name":"Bleuler W. Fils",
    "wof:placetype":"venue"
},
  "geometry": {"coordinates":[6.249005,46.440887],"type":"Point"}
}