{
  "type": "Feature",
  "properties": {
    "iso:country":"CH",
    "sg:address":"Route Outre-vi\u00e8ze",
    "sg:city":"Cho\u00ebx",
    "sg:orig_category":"Vereine Gesang",
    "sg:postcode":"1871",
    "sg:province":"Valais",
    "wof:name":"Chorale De Monthey",
    "wof:placetype":"venue"
},
  "geometry": {"coordinates":[6.9480500221,46.2422523499],"type":"Point"}
}