{
  "type": "Feature",
  "properties": {
    "iso:country":"CH",
    "sg:address":"Bergstrasse 90 5430 Wettingen. Postfach",
    "sg:city":"Wettingen",
    "sg:orig_category":"Gesundheitswesen",
    "sg:postcode":"5430",
    "sg:province":"Aargau",
    "wof:name":"Tamarind Gmbh Akupunktur, Kr\u00e4uterbehandlungen Im Bereich D. Tradition. Chines. Medizin; Schulungen, Veranstaltungen",
    "wof:placetype":"venue"
},
  "geometry": {"coordinates":[8.3434343338,47.4714393616],"type":"Point"}
}