{
  "type": "Feature",
  "properties": {
    "iso:country":"CH",
    "sg:address":"Postgasse 3",
    "sg:city":"Vorderthal",
    "sg:orig_category":"Gemeindeverwaltungen",
    "sg:phone":"+41 56 418 85 11",
    "sg:postcode":"8857",
    "sg:province":"Schwyz",
    "wof:name":"Gemeindeverwaltung Vorderthal",
    "wof:placetype":"venue"
},
  "geometry": {"coordinates":[8.8972492218,47.1225891113],"type":"Point"}
}