{
  "type": "Feature",
  "properties": {
    "addr:full":"Corso Italia 31 Campione Ticino 6911",
    "addr:housenumber":"31",
    "addr:postcode":"6911",
    "addr:street":"Corso Italia",
    "iso:country":"CH",
    "sg:address":"Corso Italia 31",
    "sg:city":"Campione",
    "sg:classifiers":[
        {
            "category":"Bars & Pubs",
            "type":"Food & Drink"
        }
    ],
    "sg:phone":"+41 91 649 42 96",
    "sg:postcode":"6911",
    "sg:province":"Ticino",
    "wof:name":"Bar Mafalda",
    "wof:placetype":"venue"
},
  "geometry": {"coordinates":[10.821231,45.080364],"type":"Point"}
}