{
  "type": "Feature",
  "properties": {
    "iso:country":"CH",
    "sg:address":"Baumgartenstrasse 7",
    "sg:city":"Dietikon",
    "sg:orig_category":"Sanit\u00e4r, Heizungs U L\u00fcftungsinstallation Sanit\u00e4rinstallation",
    "sg:phone":"+41 31 738 87 53",
    "sg:postcode":"8953",
    "sg:province":"Z\u00fcrich",
    "wof:name":"Harry Hirsbrunner Sanit\u00e4re Anlagen & Heizungen",
    "wof:placetype":"venue"
},
  "geometry": {"coordinates":[7.4039468765,46.7815322876],"type":"Point"}
}