{
  "type": "Feature",
  "properties": {
    "iso:country":"CH",
    "sg:address":"Bodenackerstrasse 5",
    "sg:city":"Obfelden",
    "sg:orig_category":"Offsetdruck",
    "sg:phone":"+41 17619158",
    "sg:postcode":"8912",
    "sg:province":"Z\u00fcrich",
    "wof:name":"Mantegani & Co Buch-& Offsetdruck",
    "wof:placetype":"venue"
},
  "geometry": {"coordinates":[8.4291172028,47.2647094727],"type":"Point"}
}