{
  "type": "Feature",
  "properties": {
    "iso:country":"CH",
    "sg:address":"Parkstr. 34 6415 Arth. Postfach",
    "sg:city":"Goldau",
    "sg:orig_category":"Herstellung von Konstruktionsteilen, Fertigbauteilen U Ausbauelementen aus Holz",
    "sg:phone":"+41 41 855 12 20",
    "sg:postcode":"6410",
    "sg:province":"Schwyz",
    "wof:name":"K\u00e4lin Fredi.",
    "wof:placetype":"venue"
},
  "geometry": {"coordinates":[8.5528316498,47.0512962341],"type":"Point"}
}