{
  "type": "Feature",
  "properties": {
    "iso:country":"CH",
    "sg:address":"Bergwerkstrasse 24 5027 Herznach. Postfach 246",
    "sg:city":"Frick",
    "sg:orig_category":"Sportvereine Ballsport Tischtennis",
    "sg:phone":"+41 62 878 12 66",
    "sg:postcode":"5070",
    "sg:province":"Aargau",
    "wof:name":"Ttc Frick",
    "wof:placetype":"venue"
},
  "geometry": {"coordinates":[8.0453643799,47.4736061096],"type":"Point"}
}