{
  "type": "Feature",
  "properties": {
    "iso:country":"CH",
    "sg:address":"Route De Rolle 52",
    "sg:city":"St-prex",
    "sg:orig_category":"Instandhaltung U Reparatur von Automobilen",
    "sg:phone":"+41 21 806 25 77",
    "sg:postcode":"1162",
    "sg:province":"Vaud",
    "wof:name":"Garage De La Fleur De Lys S\u00e0rl",
    "wof:placetype":"venue"
},
  "geometry": {"coordinates":[6.4422659874,46.4765472412],"type":"Point"}
}