{
  "type": "Feature",
  "properties": {
    "iso:country":"CH",
    "sg:address":"Aarauerstrasse 74",
    "sg:city":"Olten",
    "sg:orig_category":"Fachdetailhandel in Verkaufsr\u00e4umen Sonstiger Fachdetailhandel in Verkaufsr\u00e4umen",
    "sg:phone":"+41 62 296 50 65",
    "sg:postcode":"4600",
    "sg:province":"Solothurn",
    "wof:name":"Kloos G\u00fcnter",
    "wof:placetype":"venue"
},
  "geometry": {"coordinates":[7.9119558334,47.3486289978],"type":"Point"}
}