{
  "type": "Feature",
  "properties": {
    "iso:country":"CH",
    "sg:address":"Hardstrasse 6",
    "sg:city":"Lenzburg",
    "sg:orig_category":"Festh\u00fctten- and Zeltvermietung",
    "sg:phone":"+41 62 892 08 52",
    "sg:postcode":"5600",
    "sg:province":"Aargau",
    "wof:name":"Rent A Tent Gmbh Festhallenvermietung",
    "wof:placetype":"venue"
},
  "geometry": {"coordinates":[8.1696796417,47.395942688],"type":"Point"}
}