{
  "type": "Feature",
  "properties": {
    "iso:country":"CH",
    "sg:address":"Rue Oscar-huguenin 6",
    "sg:city":"Boudry",
    "sg:orig_category":"Kosmetikinstitute",
    "sg:phone":"+41 61 711 65 35",
    "sg:postcode":"2017",
    "sg:province":"Neuch\u00e2tel",
    "wof:name":"Nicole R\u00f6thlisberger Coiffure & Beaut\u00e9",
    "wof:placetype":"venue"
},
  "geometry": {"coordinates":[7.5891551971,47.4925384521],"type":"Point"}
}