{
  "type": "Feature",
  "properties": {
    "iso:country":"CH",
    "sg:address":"Piazzetta Di Capitani 8",
    "sg:city":"Locarno",
    "sg:orig_category":"Detailhandel mit Schuhen Detailhandel mit Schuhen U Lederwaren",
    "sg:phone":"+41 91 751 47 88",
    "sg:postcode":"6600",
    "sg:province":"Ticino",
    "wof:name":"Barbara Roncaroni Neg.calzature Piccoli Passi",
    "wof:placetype":"venue"
},
  "geometry": {"coordinates":[8.7946519852,46.1700592041],"type":"Point"}
}