{
  "type": "Feature",
  "properties": {
    "addr:full":"Rue Des Etuves 16-18 Gen\u00e8ve Gen\u00e8ve 1201",
    "addr:postcode":"16-18;1201",
    "addr:street":"Rue Des Etuves",
    "iso:country":"CH",
    "sg:address":"Rue Des Etuves 16-18",
    "sg:city":"Gen\u00e8ve",
    "sg:orig_category":"Detailhandel mit Antiquit\u00e4ten Detailhandel mit Uhren U Schmuck",
    "sg:phone":"+41 22 738 34 60",
    "sg:postcode":"1201",
    "sg:province":"Gen\u00e8ve",
    "wof:name":"L'autre Sa",
    "wof:placetype":"venue"
},
  "geometry": {"coordinates":[6.143877,46.206364],"type":"Point"}
}