{
  "type": "Feature",
  "properties": {
    "iso:country":"CH",
    "sg:address":"Sandmattstrasse 12",
    "sg:city":"Solothurn",
    "sg:orig_category":"Technische, physikalische U chemische Untersuchung",
    "sg:phone":"+41 32 623 59 43",
    "sg:postcode":"4500",
    "sg:province":"Solothurn",
    "wof:name":"Ziegler Christoph",
    "wof:placetype":"venue"
},
  "geometry": {"coordinates":[7.5409059525,47.2014923096],"type":"Point"}
}