{
  "type": "Feature",
  "properties": {
    "iso:country":"CH",
    "sg:address":"Rue Centrale 11",
    "sg:city":"Ste-croix",
    "sg:orig_category":"Detailhandel mit Fleisch U Fleischwaren",
    "sg:phone":"+41 24 454 21 85",
    "sg:postcode":"1450",
    "sg:province":"Vaud",
    "wof:name":"Junod Louis, Boucherie Centrale",
    "wof:placetype":"venue"
},
  "geometry": {"coordinates":[6.5023789406,46.8230056763],"type":"Point"}
}