{
  "type": "Feature",
  "properties": {
    "iso:country":"CH",
    "sg:address":"Wiesenstrasse 2 5432 Neuenhof. Postfach",
    "sg:city":"Neuenhof",
    "sg:orig_category":"Detailhandel mit elektrischen Haushalts-,Radio U Fernsehger\u00e4ten sowie Musikinstrumenten",
    "sg:phone":"+41 56 406 06 60",
    "sg:postcode":"5432",
    "sg:province":"Aargau",
    "wof:name":"Show Supply Gmbh Waren, Bes. Produkte Aus Dem Bereich Professioneller Audio- U. Event-technik; Handel",
    "wof:placetype":"venue"
},
  "geometry": {"coordinates":[8.323931694,47.4525413513],"type":"Point"}
}