{
  "type": "Feature",
  "properties": {
    "iso:country":"CH",
    "sg:address":"Avenue Des Planches 2",
    "sg:city":"Montreux",
    "sg:orig_category":"Unclassifiable Establishments",
    "sg:phone":"+41 21 963 55 77",
    "sg:postcode":"1820",
    "sg:province":"Vaud",
    "wof:name":"Association De La Coupe Des Nations",
    "wof:placetype":"venue"
},
  "geometry": {"coordinates":[6.9154100418,46.4318084717],"type":"Point"}
}