{
  "type": "Feature",
  "properties": {
    "iso:country":"CH",
    "sg:address":"Rue Des Granges 14",
    "sg:city":"Payerne",
    "sg:orig_category":"Architektur U Ingenieurb\u00fcros",
    "sg:phone":"+41 26 660 31 77",
    "sg:postcode":"1530",
    "sg:province":"Vaud",
    "wof:name":"K\u00fcng Et Associ\u00e9s Sa",
    "wof:placetype":"venue"
},
  "geometry": {"coordinates":[6.938127,46.819447],"type":"Point"}
}