{
  "type": "Feature",
  "properties": {
    "iso:country":"CH",
    "sg:address":"Leonhardsstrasse 8",
    "sg:city":"Basel",
    "sg:orig_category":"Museen",
    "sg:phone":"+41 61 261 69 45",
    "sg:postcode":"4051",
    "sg:province":"Basel-Stadt",
    "wof:name":"Musikinstrumenten-sammlung Des Historischen Museums Basel",
    "wof:placetype":"venue"
},
  "geometry": {"coordinates":[7.5863189697,47.5547676086],"type":"Point"}
}