{
  "type": "Feature",
  "properties": {
    "iso:country":"CH",
    "sg:address":"Reichsgasse 61",
    "sg:city":"Chur",
    "sg:orig_category":"Grosshandel mit sonstigen Gebrauchs U Verbrauchsg\u00fctern",
    "sg:phone":"+41 81 254 38 42",
    "sg:postcode":"7000",
    "sg:province":"Graubunden",
    "wof:name":"Vincor Sa",
    "wof:placetype":"venue"
},
  "geometry": {"coordinates":[9.5329761505,46.8490409851],"type":"Point"}
}