{
  "type": "Feature",
  "properties": {
    "iso:country":"CH",
    "sg:address":"Breitenrainstrasse 41",
    "sg:city":"Bern",
    "sg:orig_category":"Non-Classified Establishments",
    "sg:postcode":"3013",
    "sg:province":"Bern",
    "wof:name":"Lacraz Sa Entreprise De Nettoyages",
    "wof:placetype":"venue"
},
  "geometry": {"coordinates":[6.1418061256,46.1833534241],"type":"Point"}
}