{
  "type": "Feature",
  "properties": {
    "addr:full":"Bleierlis Appenzell Appenzell Innerhoden 9050",
    "addr:postcode":"9050",
    "iso:country":"CH",
    "sg:address":"Bleierlis",
    "sg:city":"Appenzell",
    "sg:orig_category":"Architektur U Ingenieurb\u00fcros Technische B\u00fcros",
    "sg:phone":"+41 71 787 89 83",
    "sg:postcode":"9050",
    "sg:province":"Appenzell Innerhoden",
    "wof:name":"Lange Roland Konstruktionsb\u00fcro",
    "wof:placetype":"venue"
},
  "geometry": {"coordinates":[9.407683,47.331436],"type":"Point"}
}