{
  "type": "Feature",
  "properties": {
    "addr:full":"Bahnhofstrasse 31 Sursee Luzern 6210",
    "addr:housenumber":"31",
    "addr:postcode":"6210",
    "addr:street":"Bahnhofstrasse",
    "iso:country":"CH",
    "sg:address":"Bahnhofstrasse 31",
    "sg:city":"Sursee",
    "sg:classifiers":[
        {
            "category":"Banks & Credit Unions",
            "subcategory":"Bank",
            "type":"Services"
        }
    ],
    "sg:phone":"+41 4145217155",
    "sg:postcode":"6210",
    "sg:province":"Luzern",
    "wof:name":"Schweiz. Bankgesellschaft",
    "wof:placetype":"venue"
},
  "geometry": {"coordinates":[8.102288,47.172264],"type":"Point"}
}