{
  "type": "Feature",
  "properties": {
    "iso:country":"CH",
    "sg:address":"Albrechts-platz 3",
    "sg:city":"Rheinfelden",
    "sg:classifiers":[
        {
            "category":"Professional",
            "subcategory":"Advertising",
            "type":"Services"
        }
    ],
    "sg:phone":"+41 61 835 00 00",
    "sg:postcode":"4310",
    "sg:province":"Aargau",
    "sg:tags":[
        "poster"
    ],
    "wof:name":"Herzog Medien Ag",
    "wof:placetype":"venue"
},
  "geometry": {"coordinates":[7.794306,47.555416],"type":"Point"}
}