{
  "type": "Feature",
  "properties": {
    "iso:country":"CH",
    "sg:address":"Obere Bahnhofstrasse 13 5507 Mellingen. Postfach",
    "sg:city":"Mellingen",
    "sg:orig_category":"Non-Classified Establishments",
    "sg:postcode":"5507",
    "sg:province":"Aargau",
    "wof:name":"Meifa Gmbh Haus- U. Industrietechnik; Projekt-planung, Betreuung, Ausf\u00fchrung. Hard- U. Software Entwicklung Usw.",
    "wof:placetype":"venue"
},
  "geometry": {"coordinates":[7.3570599556,46.9729194641],"type":"Point"}
}