{
  "type": "Feature",
  "properties": {
    "iso:country":"CH",
    "sg:address":"Place De L'eglise",
    "sg:city":"Lussy-sur-morges",
    "sg:orig_category":"Kauf U Verkauf von Immobilien auf eigene Rechnung Vermittlung von Immobilien",
    "sg:phone":"+41 21 802 64 66",
    "sg:postcode":"1133",
    "wof:name":"Ics Grohe",
    "wof:placetype":"venue"
},
  "geometry": {"coordinates":[6.4505200386,46.5040588379],"type":"Point"}
}