{
  "type": "Feature",
  "properties": {
    "iso:country":"CH",
    "sg:address":"M\u00fchlestiegstrasse 29 4125 Riehen. Postfach",
    "sg:city":"Riehen",
    "sg:orig_category":"Gesundheitswesen",
    "sg:phone":"+41 61 641 06 83",
    "sg:postcode":"4125",
    "sg:province":"Basel-Stadt",
    "wof:name":"L\u00fcscher-diagnostik, Inbaberin Hennes Ulrike Produkte Zur Farbdiagnostik; Vertrieb, Verkauf",
    "wof:placetype":"venue"
},
  "geometry": {"coordinates":[7.6473269463,47.5782852173],"type":"Point"}
}