{
  "type": "Feature",
  "properties": {
    "iso:country":"CH",
    "sg:address":"Via Peri 2",
    "sg:city":"Lugano",
    "sg:orig_category":"Vermittlung von Immobilien Verwaltung von Immobilien",
    "sg:phone":"+41 56 622 88 66",
    "sg:postcode":"6900",
    "sg:province":"Ticino",
    "wof:name":"Exacta Treuhand Ag",
    "wof:placetype":"venue"
},
  "geometry": {"coordinates":[8.2772769928,47.3475189209],"type":"Point"}
}