{
  "type": "Feature",
  "properties": {
    "iso:country":"CH",
    "sg:address":"Opfikonerstrasse 18",
    "sg:city":"Wallisellen",
    "sg:orig_category":"Elektroinstallation",
    "sg:phone":"+41 18302619",
    "sg:postcode":"8304",
    "sg:province":"Z\u00fcrich",
    "wof:name":"Elektro-schmid, Wallisellen",
    "wof:placetype":"venue"
},
  "geometry": {"coordinates":[8.5876560211,47.4162216187],"type":"Point"}
}