{
  "type": "Feature",
  "properties": {
    "iso:country":"CH",
    "sg:address":"Chemin De Mochettaz 8 1030 Bussigny-lausanne Case Postale 80",
    "sg:city":"Lausanne",
    "sg:orig_category":"Druck ohne Zeitungsdruck Offsetdruck",
    "sg:phone":"+41 21 349 45 00",
    "sg:postcode":"1003",
    "sg:province":"Vaud",
    "wof:name":"Cie Centre D'impression Edipresse Lausanne Sa",
    "wof:placetype":"venue"
},
  "geometry": {"coordinates":[6.5483751297,46.5473442078],"type":"Point"}
}