{
  "type": "Feature",
  "properties": {
    "iso:country":"CH",
    "sg:address":"Rue De La Borde 17 1018 Lausanne Case Postale",
    "sg:city":"Lausanne",
    "sg:orig_category":"Detailhandel mit Teppichen Verlegen von Fussboden",
    "sg:phone":"+41 21 641 75 75",
    "sg:postcode":"1000",
    "sg:province":"Vaud",
    "wof:name":"Blanc & Cie Sa",
    "wof:placetype":"venue"
},
  "geometry": {"coordinates":[6.6324062347,46.5283546448],"type":"Point"}
}