{
  "type": "Feature",
  "properties": {
    "iso:country":"CH",
    "sg:address":"Dreik\u00f6nigstrasse 31a 8002 Z\u00fcrich. Postfach",
    "sg:city":"Z\u00fcrich",
    "sg:orig_category":"Fernmeldedienste",
    "sg:postcode":"8002",
    "sg:province":"Z\u00fcrich",
    "wof:name":"3u Telecom Ag Verbindungsnetzbetreiber. Dienstleistungen Im Telekommunikationsbereich Usw",
    "wof:placetype":"venue"
},
  "geometry": {"coordinates":[8.5351734161,47.3664855957],"type":"Point"}
}