{
  "type": "Feature",
  "properties": {
    "iso:country":"CH",
    "sg:city":"Birsfelden",
    "sg:orig_category":"Shopping U Fachgesch\u00e4fte, Kosmetik U K\u00f6rperpflege",
    "sg:postcode":"4127",
    "sg:province":"Basel-Landschaft",
    "wof:name":"Lipofluid Kosmetik",
    "wof:placetype":"venue"
},
  "geometry": {"coordinates":[7.620073,47.55407],"type":"Point"}
}