{
  "type": "Feature",
  "properties": {
    "iso:country":"CH",
    "sg:address":"Unterer Einschlag 2544 Bettlach. Postfach 148",
    "sg:city":"Bettlach",
    "sg:orig_category":"Herstellung von Werkzeugen Herstellung von sonstigen Metallwaren",
    "sg:phone":"+41 32 644 33 11",
    "sg:postcode":"2544",
    "sg:province":"Solothurn",
    "wof:name":"Heinz H\u00e4nggi Ag Stanztechnik",
    "wof:placetype":"venue"
},
  "geometry": {"coordinates":[7.42634,47.195065],"type":"Point"}
}