{
  "type": "Feature",
  "properties": {
    "iso:country":"CH",
    "sg:address":"Feldbergstrasse 55",
    "sg:city":"Basel",
    "sg:orig_category":"Interessenvertretungen Organisationen der Wohlfahrtspflege",
    "sg:phone":"+41 61 691 35 04",
    "sg:postcode":"4057",
    "sg:province":"Basel-Stadt",
    "wof:name":"Stiftung Hinterhuus",
    "wof:placetype":"venue"
},
  "geometry": {"coordinates":[7.5916118622,47.5665130615],"type":"Point"}
}