{
  "type": "Feature",
  "properties": {
    "iso:country":"CH",
    "sg:address":"4624",
    "sg:city":"H\u00e4rkingen",
    "sg:orig_category":"Landw. Genossenschaften Viehzucht",
    "sg:postcode":"4624",
    "sg:province":"Solothurn",
    "wof:name":"Viehzuchtgenossenschaft",
    "wof:placetype":"venue"
},
  "geometry": {"coordinates":[7.8196401596,47.3040084839],"type":"Point"}
}