{
  "type": "Feature",
  "properties": {
    "iso:country":"CH",
    "sg:address":"Buchlistrasse",
    "sg:city":"Niederbipp",
    "sg:orig_category":"Detailhandel Reparatur von Gebrauchsg\u00fctern Vermietung von Gebrauchsg\u00fctern",
    "sg:phone":"+41 32 633 15 25",
    "sg:postcode":"4704",
    "sg:province":"Bern",
    "wof:name":"Mediathek L\u00f6wen, A. Christen",
    "wof:placetype":"venue"
},
  "geometry": {"coordinates":[7.6853971481,47.2678756714],"type":"Point"}
}