{
  "type": "Feature",
  "properties": {
    "iso:country":"CH",
    "sg:address":"Grand-rue 25",
    "sg:city":"Fleurier",
    "sg:orig_category":"Sportvereine Ski",
    "sg:phone":"+41 81 733 47 24",
    "sg:postcode":"2114",
    "sg:province":"Neuch\u00e2tel",
    "wof:name":"Ski-club Flums",
    "wof:placetype":"venue"
},
  "geometry": {"coordinates":[9.3718099594,47.0840492249],"type":"Point"}
}