{
  "type": "Feature",
  "properties": {
    "iso:country":"CH",
    "sg:address":"Sch\u00fctzengraben 28",
    "sg:city":"Schaffhausen",
    "sg:orig_category":"Finanzierungsinstitutionen",
    "sg:postcode":"8200",
    "sg:province":"Schaffhausen",
    "wof:name":"Mrs Magnetresonanz Schaffhausen Ag",
    "wof:placetype":"venue"
},
  "geometry": {"coordinates":[8.6352815628,47.6990814209],"type":"Point"}
}