{
  "type": "Feature",
  "properties": {
    "iso:country":"CH",
    "sg:address":"Z\u00fcrcher Strasse 36",
    "sg:city":"St.gallen",
    "sg:orig_category":"Grosshandel mit Holz U Baustoffen",
    "sg:phone":"+41 21 864 58 59",
    "sg:postcode":"9000",
    "sg:province":"St. Gallen",
    "wof:name":"Chemirev Sa",
    "wof:placetype":"venue"
},
  "geometry": {"coordinates":[6.4546599388,46.5740318298],"type":"Point"}
}