{
  "type": "Feature",
  "properties": {
    "iso:country":"CH",
    "sg:address":"Favre Rue Louis- 23 1201 Gen\u00e8ve. Postfach",
    "sg:city":"Gen\u00e8ve",
    "sg:orig_category":"Sonstige pers\u00f6nliche Dienstleistungen",
    "sg:postcode":"1201",
    "sg:province":"Gen\u00e8ve",
    "wof:name":"Lpc Lavore Papa Cristoforo Pon\u00e7age, Polissage De Marbre Etc",
    "wof:placetype":"venue"
},
  "geometry": {"coordinates":[6.1373639107,46.2113113403],"type":"Point"}
}