{
  "type": "Feature",
  "properties": {
    "iso:country":"CH",
    "sg:address":"6677",
    "sg:city":"Aurigeno",
    "sg:classifiers":[
        {
            "category":"Bars & Pubs",
            "type":"Food & Drink"
        }
    ],
    "sg:phone":"+41 91 753 22 25",
    "sg:postcode":"6677",
    "sg:province":"Ticino",
    "sg:tags":[
        "restaurant"
    ],
    "wof:name":"Grotto & Bar Ai Ronchini",
    "wof:placetype":"venue"
},
  "geometry": {"coordinates":[8.7122,46.231049],"type":"Point"}
}