{
  "type": "Feature",
  "properties": {
    "iso:country":"CH",
    "sg:address":"Driangelgasse 2",
    "sg:city":"Lungern",
    "sg:orig_category":"Detailhandel mit Milcherzeugnissen U Eiern Verarbeitung von Milch",
    "sg:phone":"+41 41 678 12 15",
    "sg:postcode":"6078",
    "sg:province":"Obwalden",
    "wof:name":"Arnold Gasser Sennerei",
    "wof:placetype":"venue"
},
  "geometry": {"coordinates":[8.1523981094,46.7825431824],"type":"Point"}
}