{
  "type": "Feature",
  "properties": {
    "iso:country":"CH",
    "sg:address":"R\u00fctiweg 23",
    "sg:city":"Uster",
    "sg:orig_category":"Sonstige pers\u00f6nliche Dienstleistungen",
    "sg:phone":"+41 19406666",
    "sg:postcode":"8610",
    "sg:province":"Z\u00fcrich",
    "wof:name":"Beratungsstelle Wettstein P. Bssi",
    "wof:placetype":"venue"
},
  "geometry": {"coordinates":[8.703379631,47.3525695801],"type":"Point"}
}