{
  "type": "Feature",
  "properties": {
    "iso:country":"CH",
    "sg:address":"Route De Florissant 25",
    "sg:city":"Gen\u00e8ve",
    "sg:orig_category":"Kosmetikinstitute",
    "sg:phone":"+41 22 346 11 23",
    "sg:postcode":"1206",
    "sg:province":"Gen\u00e8ve",
    "wof:name":"Elys\u00e9s Beaut\u00e9 Jeanine Savoy",
    "wof:placetype":"venue"
},
  "geometry": {"coordinates":[6.1575789452,46.1954269409],"type":"Point"}
}