{
  "type": "Feature",
  "properties": {
    "iso:country":"CH",
    "sg:address":"Dorfstrasse 24",
    "sg:city":"Frutigen",
    "sg:orig_category":"Wirtschaftspr\u00fcfung, Steuerberatung U Treuhand",
    "sg:phone":"+41 33 671 25 23",
    "sg:postcode":"3714",
    "sg:province":"Bern",
    "wof:name":"Frautschi Otto",
    "wof:placetype":"venue"
},
  "geometry": {"coordinates":[7.6461992264,46.5888328552],"type":"Point"}
}