{
  "type": "Feature",
  "properties": {
    "addr:full":"Haltenstrasse 37 Obfelden Z\u00fcrich 8912",
    "addr:housenumber":"37",
    "addr:postcode":"8912",
    "addr:street":"Haltenstrasse",
    "iso:country":"CH",
    "sg:address":"Haltenstrasse 37",
    "sg:city":"Obfelden",
    "sg:orig_category":"Bauspenglerei Sanit\u00e4rinstallation U Spenglerei",
    "sg:phone":"+41 22 756 11 32",
    "sg:postcode":"8912",
    "sg:province":"Z\u00fcrich",
    "wof:name":"Hubert Guichon Ferblanterie",
    "wof:placetype":"venue"
},
  "geometry": {"coordinates":[6.008,46.15593],"type":"Point"}
}