{
  "type": "Feature",
  "properties": {
    "iso:country":"CH",
    "sg:address":"Vonmattstrasse 24a",
    "sg:city":"Luzern",
    "sg:orig_category":"Erbringung von Dienstleistungen f\u00fcr Unternehmen",
    "sg:postcode":"6003",
    "sg:province":"Luzern",
    "wof:name":"Seghizzi Alessa Jewelry",
    "wof:placetype":"venue"
},
  "geometry": {"coordinates":[8.2997255325,47.0475196838],"type":"Point"}
}