{
  "type": "Feature",
  "properties": {
    "iso:country":"CH",
    "sg:address":"Bahnhofstrasse 8 8212 Neuhausen. Postfach",
    "sg:city":"Neuhausen",
    "sg:orig_category":"Sonstige mit der Informatik verbundene T\u00e4tigkeiten",
    "sg:postcode":"8212",
    "sg:province":"Schaffhausen",
    "wof:name":"Kei Kabil Engineering & Innovation Edv-dienstleistungen, Elektroplanung Usw",
    "wof:placetype":"venue"
},
  "geometry": {"coordinates":[8.6221418381,47.6825218201],"type":"Point"}
}