{
  "type": "Feature",
  "properties": {
    "iso:country":"CH",
    "sg:address":"Seebleichestrasse 61 9404 Rorschacherberg. Postfach 82",
    "sg:city":"Rorschach",
    "sg:orig_category":"Herstellung von Werkzeugen Herstellung von sonstigen Werkzeugmaschinen",
    "sg:phone":"+41 71 858 81 11",
    "sg:postcode":"9401",
    "sg:province":"St. Gallen",
    "wof:name":"Starrag-heckert Holding Ag",
    "wof:placetype":"venue"
},
  "geometry": {"coordinates":[9.5182113647,47.4781265259],"type":"Point"}
}