{
  "type": "Feature",
  "properties": {
    "iso:country":"CH",
    "sg:address":"Avenue Du G\u00e9n\u00e9ral Guisan 16 3960 Sierre Case Postale 624",
    "sg:city":"Sierre",
    "sg:orig_category":"Detailhandel mit Zeitungen U Zeitschriften Kioske",
    "sg:phone":"+41 27 455 07 07",
    "sg:postcode":"3960",
    "sg:province":"Valais",
    "wof:name":"Martin M\u00fcller Kiosque",
    "wof:placetype":"venue"
},
  "geometry": {"coordinates":[7.5311999321,46.2925605774],"type":"Point"}
}