{
  "type": "Feature",
  "properties": {
    "iso:country":"CH",
    "sg:address":"Av. Du G\u00e9n\u00e9ral Guisan 30",
    "sg:city":"Sierre",
    "sg:orig_category":"RESTAURANTS: TEA-ROOMS",
    "sg:postcode":"3960",
    "sg:province":"Valais",
    "wof:name":"Zufferey Nadine",
    "wof:placetype":"venue"
},
  "geometry": {"coordinates":[7.6151399612,46.1528205872],"type":"Point"}
}