{
  "type": "Feature",
  "properties": {
    "iso:country":"CH",
    "sg:address":"Route De Corbaroche 28",
    "sg:city":"Marly",
    "sg:orig_category":"Herstellung von Teppichen",
    "sg:postcode":"1723",
    "sg:province":"Fribourg",
    "wof:name":"Chambettaz J.-c., Carrelage Et Rev\u00eatement.",
    "wof:placetype":"venue"
},
  "geometry": {"coordinates":[7.163421154,46.770488739],"type":"Point"}
}