{
  "type": "Feature",
  "properties": {
    "iso:country":"CH",
    "sg:address":"Bungertweg 2",
    "sg:city":"Winterthur",
    "sg:orig_category":"Vermietung U Verpachtung von eigenen Immobilien",
    "sg:postcode":"8400",
    "sg:province":"Z\u00fcrich",
    "wof:name":"Zurlinda Ag.",
    "wof:placetype":"venue"
},
  "geometry": {"coordinates":[8.7501564026,47.5063018799],"type":"Point"}
}