{
  "type": "Feature",
  "properties": {
    "iso:country":"CH",
    "sg:address":"Rue De La Gare 26",
    "sg:city":"Nyon",
    "sg:orig_category":"Kosmetikinstitute",
    "sg:phone":"+41 22 361 10 90",
    "sg:postcode":"1260",
    "sg:province":"Vaud",
    "wof:name":"Manuela Ferro Institut De Beaut\u00e9 Manuela",
    "wof:placetype":"venue"
},
  "geometry": {"coordinates":[6.2367591858,46.3828964233],"type":"Point"}
}