{
  "type": "Feature",
  "properties": {
    "iso:country":"CH",
    "sg:address":"Chemin Gilbert-trolliet 4",
    "sg:city":"Gen\u00e8ve",
    "sg:classifiers":[
        {
            "category":"Restaurant",
            "type":"Food & Drink"
        }
    ],
    "sg:phone":"+41 22 740 37 30",
    "sg:postcode":"1209",
    "sg:province":"Gen\u00e8ve",
    "wof:name":"Vinoth\u00e8que Taverna Toscana",
    "wof:placetype":"venue"
},
  "geometry": {"coordinates":[6.1233620644,46.2193069458],"type":"Point"}
}