{
  "type": "Feature",
  "properties": {
    "iso:country":"CH",
    "sg:address":"Hinterdorfstrasse 1",
    "sg:city":"D\u00fcrnten",
    "sg:orig_category":"Grosshandel mit Nahrungsmitteln, Getr\u00e4nken U Tabakwaren Sonstiger Grosshandel",
    "sg:phone":"+41 55 240 43 65",
    "sg:postcode":"8635",
    "sg:province":"Z\u00fcrich",
    "wof:name":"Mpv Mineralstoff-produkte-vertrieb Dieter Kaltenbach",
    "wof:placetype":"venue"
},
  "geometry": {"coordinates":[8.8424034119,47.2779045105],"type":"Point"}
}