{
  "type": "Feature",
  "properties": {
    "iso:country":"CH",
    "sg:address":"Bahnhofstrasse 29 8560 M\u00e4rstetten. Postfach",
    "sg:city":"M\u00e4rstetten",
    "sg:orig_category":"Kauf U Verkauf von Immobilien auf eigene Rechnung",
    "sg:phone":"+41 79 438 87 74",
    "sg:postcode":"8560",
    "sg:province":"Thurgau",
    "wof:name":"Rt Immofid Gmbh",
    "wof:placetype":"venue"
},
  "geometry": {"coordinates":[9.0635204315,47.5884094238],"type":"Point"}
}