{
  "type": "Feature",
  "properties": {
    "iso:country":"CH",
    "sg:address":"Peter Rot-strasse 113",
    "sg:city":"Basel",
    "sg:orig_category":"Tanzschulen, Tanzlehrer",
    "sg:phone":"+41 61 691 17 23",
    "sg:postcode":"4058",
    "sg:province":"Basel-Stadt",
    "wof:name":"Ecole De Ballet Frau Michiko Ichida",
    "wof:placetype":"venue"
},
  "geometry": {"coordinates":[7.6037712097,47.5625114441],"type":"Point"}
}