{
  "type": "Feature",
  "properties": {
    "iso:country":"CH",
    "sg:address":"Chemin De Grand-donzel 36",
    "sg:city":"Vessy",
    "sg:orig_category":"Tanzschulen, Tanzlehrer",
    "sg:phone":"+41 59 450 54 40",
    "sg:postcode":"1234",
    "sg:province":"Gen\u00e8ve",
    "wof:name":"Ecole Genevoise D'alpinisme Monsieur Raphael Cuman",
    "wof:placetype":"venue"
},
  "geometry": {"coordinates":[6.1667299271,46.1681137085],"type":"Point"}
}