{
  "type": "Feature",
  "properties": {
    "iso:country":"CH",
    "sg:address":"Stadtplatz 20",
    "sg:city":"Aarberg",
    "sg:classifiers":[
        {
            "category":"Restaurant",
            "type":"Food & Drink"
        }
    ],
    "sg:phone":"+41 56 441 14 96",
    "sg:postcode":"3270",
    "sg:province":"Bern",
    "wof:name":"Restaurant Commercio",
    "wof:placetype":"venue"
},
  "geometry": {"coordinates":[8.2071123123,47.485874176],"type":"Point"}
}