{
  "type": "Feature",
  "properties": {
    "iso:country":"CH",
    "sg:address":"Les Cheseaux",
    "sg:city":"St-cergue",
    "sg:orig_category":"Non-Classified Establishments",
    "sg:postcode":"1264",
    "sg:province":"Vaud",
    "wof:name":"Equiranch, N. Tschopp",
    "wof:placetype":"venue"
},
  "geometry": {"coordinates":[6.1545948982,46.450088501],"type":"Point"}
}