{
  "type": "Feature",
  "properties": {
    "iso:country":"CH",
    "sg:address":"Alte Landstrasse 56",
    "sg:city":"R\u00fcschlikon",
    "sg:orig_category":"Fachdetailhandel in Verkaufsr\u00e4umen",
    "sg:phone":"+41 55 280 28 85",
    "sg:postcode":"8803",
    "sg:province":"Z\u00fcrich",
    "wof:name":"Ski-center Uznach, Trinkner Fritz & Valeria",
    "wof:placetype":"venue"
},
  "geometry": {"coordinates":[8.5524406433,47.3080291748],"type":"Point"}
}