{
  "type": "Feature",
  "properties": {
    "iso:country":"CH",
    "sg:address":"B\u00fcrglenstrasse B\u00fcrglen",
    "sg:city":"Lungern",
    "sg:orig_category":"Herstellung von sonstigen elektrischen Ausr\u00fcstungen",
    "sg:postcode":"6078",
    "sg:province":"Obwalden",
    "wof:name":"Elektro Service Gasser Niklaus",
    "wof:placetype":"venue"
},
  "geometry": {"coordinates":[8.1595687866,46.7853965759],"type":"Point"}
}