{
  "type": "Feature",
  "properties": {
    "iso:country":"CH",
    "sg:address":"Eiche 7",
    "sg:city":"Wiedlisbach",
    "sg:orig_category":"Erschliessung von Grundst\u00fccken",
    "sg:postcode":"4537",
    "sg:province":"Bern",
    "wof:name":"\u00abbaugenossenschaft Otit\u00bb",
    "wof:placetype":"venue"
},
  "geometry": {"coordinates":[7.646545887,47.2491874695],"type":"Point"}
}