{
  "type": "Feature",
  "properties": {
    "iso:country":"CH",
    "sg:address":"Route Cantonale",
    "sg:city":"Riddes",
    "sg:orig_category":"Sanit\u00e4r, Heizungs U L\u00fcftungsinstallation Sanit\u00e4rinstallation",
    "sg:phone":"+41 27 306 61 70",
    "sg:postcode":"1908",
    "sg:province":"Valais",
    "wof:name":"Favre Fernand",
    "wof:placetype":"venue"
},
  "geometry": {"coordinates":[7.2157649994,46.1690216064],"type":"Point"}
}