{
  "type": "Feature",
  "properties": {
    "iso:country":"CH",
    "sg:address":"Edletenstrasse 18 H 4415 Lausen. Postfach",
    "sg:city":"Lausen",
    "sg:orig_category":"Architektur U Ingenieurb\u00fcros",
    "sg:postcode":"4415",
    "sg:province":"Basel-Landschaft",
    "wof:name":"Inel Industrie-elektrik Ag",
    "wof:placetype":"venue"
},
  "geometry": {"coordinates":[9.501995,47.012779],"type":"Point"}
}