{
  "type": "Feature",
  "properties": {
    "iso:country":"CH",
    "sg:address":"Gemeindekanzlei",
    "sg:city":"Ardez",
    "sg:orig_category":"Museen",
    "sg:postcode":"7546",
    "sg:province":"Graubunden",
    "wof:name":"Stiftung Pro Ardez",
    "wof:placetype":"venue"
},
  "geometry": {"coordinates":[10.2019052505,46.7752609253],"type":"Point"}
}