{
  "type": "Feature",
  "properties": {
    "iso:country":"CH",
    "sg:address":"Rue De L'eglise Catholique 12",
    "sg:city":"Montreux",
    "sg:orig_category":"B\u00e4ckereien Konditoreien",
    "sg:phone":"+41 21 963 23 03",
    "sg:postcode":"1820",
    "sg:province":"Vaud",
    "wof:name":"Emilio Spina & Fils Boulangerie Du Casino",
    "wof:placetype":"venue"
},
  "geometry": {"coordinates":[6.91208,46.430977],"type":"Point"}
}