{
  "type": "Feature",
  "properties": {
    "iso:country":"CH",
    "sg:address":"Dorfstrasse 9",
    "sg:city":"Oberegg",
    "sg:orig_category":"Detailhandel mit Bekleidung",
    "sg:phone":"+41 21 323 17 17",
    "sg:postcode":"9413",
    "sg:province":"Appenzell Innerhoden",
    "wof:name":"Pkz Burger-kehl & Co Ag V\u00eatements Pour Messieurs Et Jeunes Gens, Tissus Etc; Fabr, Vente",
    "wof:placetype":"venue"
},
  "geometry": {"coordinates":[6.679629,46.538723],"type":"Point"}
}