{
  "type": "Feature",
  "properties": {
    "iso:country":"CH",
    "sg:address":"6866",
    "sg:city":"Meride",
    "sg:classifiers":[
        {
            "category":"Restaurant",
            "type":"Food & Drink"
        }
    ],
    "sg:phone":"+41 91 646 56 06",
    "sg:postcode":"6866",
    "sg:province":"Ticino",
    "wof:name":"Grotto Antico",
    "wof:placetype":"venue"
},
  "geometry": {"coordinates":[8.955031395,45.8902359009],"type":"Point"}
}