{
  "type": "Feature",
  "properties": {
    "iso:country":"CH",
    "sg:address":"1983",
    "sg:city":"Evol\u00e8ne",
    "sg:classifiers":[
        {
            "category":"Restaurant",
            "type":"Food & Drink"
        }
    ],
    "sg:phone":"+41 27 283 13 79",
    "sg:postcode":"1983",
    "sg:province":"Valais",
    "wof:name":"Caf\u00e9 Paix",
    "wof:placetype":"venue"
},
  "geometry": {"coordinates":[7.4961590767,46.1144752502],"type":"Point"}
}