{
  "type": "Feature",
  "properties": {
    "iso:country":"CH",
    "sg:address":"Rte Du Vignoble 27 Case Postale 23",
    "sg:city":"Boudry",
    "sg:classifiers":[
        {
            "category":"Food Court",
            "type":"Food & Drink"
        }
    ],
    "sg:phone":"+41 32 843 02 60",
    "sg:postcode":"2017",
    "sg:province":"Neuch\u00e2tel",
    "sg:tags":[
        "product",
        "related"
    ],
    "wof:name":"Cave Des Coteaux",
    "wof:placetype":"venue"
},
  "geometry": {"coordinates":[104.4981307983,15.0814800262],"type":"Point"}
}