{
  "type": "Feature",
  "properties": {
    "iso:country":"CH",
    "sg:address":"Sonnenwiesenstrasse 21",
    "sg:city":"Kreuzlingen",
    "sg:orig_category":"Herstellung von Oberbekleidung",
    "sg:phone":"+41 71 686 33 33",
    "sg:postcode":"8280",
    "sg:province":"Thurgau",
    "wof:name":"Lenox Ag",
    "wof:placetype":"venue"
},
  "geometry": {"coordinates":[9.1968402863,47.6445198059],"type":"Point"}
}