{
  "type": "Feature",
  "properties": {
    "iso:country":"CH",
    "sg:address":"Holbeinstrasse 93",
    "sg:city":"Basel",
    "sg:orig_category":"Interessenvertretungen",
    "sg:phone":"+41 61 281 61 63",
    "sg:postcode":"4051",
    "sg:province":"Basel-Stadt",
    "wof:name":"Chorschule Basel, Eine Stiftung Der Basler Liedertafel",
    "wof:placetype":"venue"
},
  "geometry": {"coordinates":[7.581761837,47.5506591797],"type":"Point"}
}