{
  "type": "Feature",
  "properties": {
    "iso:country":"CH",
    "sg:address":"Neuengasse 20 3011 Bern. Postfach 6335",
    "sg:city":"Bern",
    "sg:classifiers":[
        {
            "category":"Education",
            "subcategory":"Library",
            "type":"Public Place"
        }
    ],
    "sg:phone":"+41 31 310 11 12",
    "sg:postcode":"3001",
    "sg:province":"Bern",
    "sg:tags":[
        "u",
        "bibliotheken",
        "archive"
    ],
    "wof:name":"Bibliothek Des Handwerker-& Gewerbeverbands Der Stadt Bern",
    "wof:placetype":"venue"
},
  "geometry": {"coordinates":[7.442575,46.94899],"type":"Point"}
}