{
  "type": "Feature",
  "properties": {
    "iso:country":"CH",
    "sg:address":"Baumstrasse 30",
    "sg:city":"Sch\u00f6nenwerd",
    "sg:orig_category":"Bauspenglerei Sanit\u00e4rinstallation",
    "sg:phone":"+41 62 849 15 06",
    "sg:postcode":"5012",
    "sg:province":"Solothurn",
    "wof:name":"Max Hofer Spenglerei Sanit\u00e4r Heizungen",
    "wof:placetype":"venue"
},
  "geometry": {"coordinates":[8.00404,47.376762],"type":"Point"}
}