{
  "type": "Feature",
  "properties": {
    "iso:country":"CH",
    "sg:address":"Dorfstrasse 29",
    "sg:city":"Besenb\u00fcren",
    "sg:orig_category":"Technische B\u00fcros Hoch-& Tiefbau",
    "sg:phone":"+41 56 666 20 42",
    "sg:postcode":"5627",
    "sg:province":"Aargau",
    "wof:name":"Orlando Christian Roth Bau",
    "wof:placetype":"venue"
},
  "geometry": {"coordinates":[8.3396453857,47.3150558472],"type":"Point"}
}