{
  "type": "Feature",
  "properties": {
    "iso:country":"CH",
    "sg:address":"Gerbestrasse 30",
    "sg:city":"Ostermundigen",
    "sg:orig_category":"Detailhandel mit Schuhen U Lederwaren",
    "sg:postcode":"3072",
    "sg:province":"Bern",
    "wof:name":"Boutique Hotland Schmidiger",
    "wof:placetype":"venue"
},
  "geometry": {"coordinates":[7.4835062027,46.951877594],"type":"Point"}
}