{
  "type": "Feature",
  "properties": {
    "iso:country":"CH",
    "sg:address":"Hofwiesenstrasse 16 8136 Gattikon. Postfach",
    "sg:city":"Gattikon",
    "sg:orig_category":"Reinigungsgewerbe",
    "sg:postcode":"8136",
    "sg:province":"Z\u00fcrich",
    "wof:name":"P. Kovac Geb\u00e4udereinigung",
    "wof:placetype":"venue"
},
  "geometry": {"coordinates":[8.5492963791,47.2853927612],"type":"Point"}
}