{
  "type": "Feature",
  "properties": {
    "iso:country":"CH",
    "sg:address":"Rue De Sous-ville",
    "sg:city":"Riddes",
    "sg:orig_category":"Arztpraxen",
    "sg:phone":"+41 27 305 25 05",
    "sg:postcode":"1908",
    "sg:province":"Valais",
    "wof:name":"Drs M\u00e9d. Quinodoz & Haenni M\u00e9decins G\u00e9n\u00e9ralistes Fmh",
    "wof:placetype":"venue"
},
  "geometry": {"coordinates":[7.22322,46.175121],"type":"Point"}
}