{
  "type": "Feature",
  "properties": {
    "iso:country":"CH",
    "sg:address":"Mauverney Rue 20b 1196 Gland Case Postale 613",
    "sg:city":"Gland",
    "sg:orig_category":"Sonstige pers\u00f6nliche Dienstleistungen",
    "sg:postcode":"1196",
    "sg:province":"Vaud",
    "wof:name":"Contacts Steckler Partnervermittlung Usw",
    "wof:placetype":"venue"
},
  "geometry": {"coordinates":[7.555352211,47.5109443665],"type":"Point"}
}