{
  "type": "Feature",
  "properties": {
    "iso:country":"CH",
    "sg:address":"Giessenstrasse 41",
    "sg:city":"Feusisberg",
    "sg:orig_category":"Technische B\u00fcros Heizung, L\u00fcftung, Klima",
    "sg:phone":"+41 16877939",
    "sg:postcode":"8835",
    "sg:province":"Schwyz",
    "wof:name":"M. M\u00fcllhaupt & E. Schn\u00f6ller Planungsb\u00fcro Klima & L\u00fcftung",
    "wof:placetype":"venue"
},
  "geometry": {"coordinates":[8.7436132431,47.1871032715],"type":"Point"}
}