{
  "type": "Feature",
  "properties": {
    "iso:country":"CH",
    "sg:address":"Kirchstrasse 194",
    "sg:city":"Wabern",
    "sg:orig_category":"Maler U Glasergewerbe Stukkateurgewerbe, Gipserei U Verputzerei",
    "sg:phone":"+41 79 651 58 57",
    "sg:postcode":"3084",
    "sg:province":"Bern",
    "wof:name":"Mosimann Martin",
    "wof:placetype":"venue"
},
  "geometry": {"coordinates":[7.4476499557,46.9294624329],"type":"Point"}
}