{
  "type": "Feature",
  "properties": {
    "iso:country":"CH",
    "sg:address":"Blumenweg 10",
    "sg:city":"Recherswil",
    "sg:orig_category":"Detailhandel mit Damenbekleidung",
    "sg:phone":"+41 32 675 38 49",
    "sg:postcode":"4565",
    "sg:province":"Solothurn",
    "wof:name":"Alexandra J\u00e4ggi Couture",
    "wof:placetype":"venue"
},
  "geometry": {"coordinates":[7.595738,47.159328],"type":"Point"}
}