{
  "type": "Feature",
  "properties": {
    "iso:country":"CH",
    "sg:address":"Chlotengasse 10",
    "sg:city":"Tagelswangen",
    "sg:orig_category":"Instandhaltung U Reparatur von Automobilen",
    "sg:phone":"+41 52 343 67 14",
    "sg:postcode":"8317",
    "sg:province":"Z\u00fcrich",
    "wof:name":"Feldmann Fritz Dorf-garage",
    "wof:placetype":"venue"
},
  "geometry": {"coordinates":[8.6703042984,47.4307174683],"type":"Point"}
}