{
  "type": "Feature",
  "properties": {
    "iso:country":"CH",
    "sg:address":"K\u00f6nizstrasse 161",
    "sg:city":"Liebefeld",
    "sg:orig_category":"Bastel- and Hobbyartikel Detailhandel Herstellung von sonstigen elektrischen Ausr\u00fcstungen",
    "sg:phone":"+41 31 971 05 33",
    "sg:postcode":"3097",
    "sg:province":"Bern",
    "wof:name":"Elko Elektrowerkzeuge Kovacevic",
    "wof:placetype":"venue"
},
  "geometry": {"coordinates":[7.416476,46.935604],"type":"Point"}
}