{
  "type": "Feature",
  "properties": {
    "iso:country":"CH",
    "sg:address":"Kirchgasse 6",
    "sg:city":"Chur",
    "sg:orig_category":"Druck ohne Zeitungsdruck",
    "sg:postcode":"7000",
    "sg:province":"Graubunden",
    "wof:name":"Telrecht Ag",
    "wof:placetype":"venue"
},
  "geometry": {"coordinates":[9.5327777863,46.8478622437],"type":"Point"}
}