{
  "type": "Feature",
  "properties": {
    "iso:country":"CH",
    "sg:address":"Luzernstrasse 76 4950 Huttwil. Postfach",
    "sg:city":"Huttwil",
    "sg:orig_category":"RESTAURANTS: TEA-ROOMS",
    "sg:postcode":"4950",
    "sg:province":"Bern",
    "wof:name":"Take-away, Kartal & Co",
    "wof:placetype":"venue"
},
  "geometry": {"coordinates":[7.8652448654,47.1146850586],"type":"Point"}
}