{
  "type": "Feature",
  "properties": {
    "iso:country":"CH",
    "sg:address":"Rue Des Terreaux 14",
    "sg:city":"Neuch\u00e2tel",
    "sg:orig_category":"Museen",
    "sg:phone":"+41 32 931 16 80",
    "sg:postcode":"2000",
    "sg:province":"Neuch\u00e2tel",
    "wof:name":"Mus\u00e9e D'horlogerie Ch\u00e2teau Des Monts",
    "wof:placetype":"venue"
},
  "geometry": {"coordinates":[6.750082016,47.0628318787],"type":"Point"}
}