{
  "type": "Feature",
  "properties": {
    "iso:country":"CH",
    "sg:address":"Felsenstrasse 14",
    "sg:city":"Z\u00fcrich",
    "sg:orig_category":"G\u00fcterbef\u00f6rderung im Strassenverkehr",
    "sg:phone":"+41 13821443",
    "sg:postcode":"8008",
    "sg:province":"Z\u00fcrich",
    "wof:name":"Art In Motion Fine Art Voyaging Service, Gschwind Samuel",
    "wof:placetype":"venue"
},
  "geometry": {"coordinates":[8.5611982346,47.3600349426],"type":"Point"}
}