{
  "type": "Feature",
  "properties": {
    "iso:country":"CH",
    "sg:address":"Heulenhof 4116 Metzerlen. Postfach",
    "sg:city":"Mariastein",
    "sg:orig_category":"Sonstige mit Sport verbundene T\u00e4tigkeiten",
    "sg:postcode":"4115",
    "sg:province":"Solothurn",
    "wof:name":"Bosshard Doris",
    "wof:placetype":"venue"
},
  "geometry": {"coordinates":[7.4650549889,47.4659118652],"type":"Point"}
}