{
  "type": "Feature",
  "properties": {
    "iso:country":"CH",
    "sg:address":"Bernstrasse 8",
    "sg:city":"Thun",
    "sg:orig_category":"Sportvereine Sch\u00fctzen",
    "sg:phone":"+41 33 438 25 55",
    "sg:postcode":"3600",
    "sg:province":"Bern",
    "wof:name":"Infanteriesch\u00fctzen",
    "wof:placetype":"venue"
},
  "geometry": {"coordinates":[7.699090004,46.7197189331],"type":"Point"}
}