{
  "type": "Feature",
  "properties": {
    "iso:country":"CH",
    "sg:address":"Via Giuseppe Cattori 9",
    "sg:city":"Paradiso",
    "sg:orig_category":"Hundesalons",
    "sg:phone":"+41 91 994 39 72",
    "sg:postcode":"6900",
    "sg:province":"Ticino",
    "wof:name":"Patrizia Pigazzini Tutto Per Il Cane",
    "wof:placetype":"venue"
},
  "geometry": {"coordinates":[8.9441509247,45.9922828674],"type":"Point"}
}