{
  "type": "Feature",
  "properties": {
    "iso:country":"CH",
    "sg:address":"Zweierstrasse 185",
    "sg:city":"Z\u00fcrich",
    "sg:orig_category":"Sportvereine Ballsport Badminton",
    "sg:phone":"+41 12899191",
    "sg:postcode":"8003",
    "sg:province":"Z\u00fcrich",
    "wof:name":"Badminton-club Irchel",
    "wof:placetype":"venue"
},
  "geometry": {"coordinates":[8.517329216,47.3691177368],"type":"Point"}
}