{
  "type": "Feature",
  "properties": {
    "iso:country":"CH",
    "sg:address":"Dorfstr. 214",
    "sg:city":"Gr\u00fcningen",
    "sg:orig_category":"Pensionskassen",
    "sg:postcode":"8627",
    "sg:province":"Z\u00fcrich",
    "wof:name":"Pensionskasse Der Vetsch Ag, Internationale Transporte",
    "wof:placetype":"venue"
},
  "geometry": {"coordinates":[9.476650238,47.1698226929],"type":"Point"}
}