{
  "type": "Feature",
  "properties": {
    "iso:country":"CH",
    "sg:address":"Alte Gfennstrasse 57",
    "sg:city":"D\u00fcbendorf",
    "sg:orig_category":"Non-Classified Establishments",
    "sg:phone":"+41 18203602",
    "sg:postcode":"8600",
    "sg:province":"Z\u00fcrich",
    "wof:name":"J. Pristas, Haustechnische Installationen",
    "wof:placetype":"venue"
},
  "geometry": {"coordinates":[8.6299772263,47.3931770325],"type":"Point"}
}