{
  "type": "Feature",
  "properties": {
    "iso:country":"CH",
    "sg:address":"Quai Wilson 35",
    "sg:city":"Gen\u00e8ve",
    "sg:orig_category":"Arztpraxen",
    "sg:phone":"+41 21 946 10 32",
    "sg:postcode":"1201",
    "sg:province":"Gen\u00e8ve",
    "wof:name":"Dr M\u00e9d. Jacques Court M\u00e9decin G\u00e9n\u00e9raliste",
    "wof:placetype":"venue"
},
  "geometry": {"coordinates":[104.498131,15.08148],"type":"Point"}
}