{
  "type": "Feature",
  "properties": {
    "addr:full":"Quai Wilson 35 Gen\u00e8ve Gen\u00e8ve 1201",
    "addr:housenumber":"35",
    "addr:postcode":"1201",
    "addr:street":"Quai Wilson",
    "iso:country":"CH",
    "sg:address":"Quai Wilson 35",
    "sg:city":"Gen\u00e8ve",
    "sg:orig_category":"Arztpraxen",
    "sg:phone":"+41 21 946 10 32",
    "sg:postcode":"1201",
    "sg:province":"Gen\u00e8ve",
    "wof:name":"Dr M\u00e9d. Jacques Court M\u00e9decin G\u00e9n\u00e9raliste",
    "wof:placetype":"venue"
},
  "geometry": {"coordinates":[104.498131,15.08148],"type":"Point"}
}