{
  "type": "Feature",
  "properties": {
    "addr:full":"Schulhausstrasse 21 Herrliberg Z\u00fcrich 8704",
    "addr:housenumber":"21",
    "addr:postcode":"8704",
    "addr:street":"Schulhausstrasse",
    "iso:country":"CH",
    "sg:address":"Schulhausstrasse 21",
    "sg:city":"Herrliberg",
    "sg:orig_category":"Allgemeinbildende weiterf\u00fchrende Schulen Sonderschulen",
    "sg:phone":"+41 19150515",
    "sg:postcode":"8704",
    "sg:province":"Z\u00fcrich",
    "wof:name":"Schule Zum Kleinen Christoffel",
    "wof:placetype":"venue"
},
  "geometry": {"coordinates":[8.614424,47.287514],"type":"Point"}
}