{
  "type": "Feature",
  "properties": {
    "iso:country":"CH",
    "sg:address":"Quartier De La Verrerie 12",
    "sg:city":"Montagne-moutier",
    "sg:orig_category":"Instandhaltung U Reparatur von Automobilen",
    "sg:phone":"+41 32 483 12 33",
    "sg:postcode":"2740",
    "sg:province":"Bern",
    "wof:name":"Garage Bebert Girardin Bertrand",
    "wof:placetype":"venue"
},
  "geometry": {"coordinates":[7.3591179848,47.2671127319],"type":"Point"}
}