{
  "type": "Feature",
  "properties": {
    "iso:country":"CH",
    "sg:address":"Rue De Lausanne 3.",
    "sg:city":"Sion",
    "sg:orig_category":"Detailhandel mit Parf\u00fcmerieartikeln U K\u00f6rperpflegemitteln",
    "sg:postcode":"1950",
    "sg:province":"Valais",
    "wof:name":"Revaz Marie-louise Mme.",
    "wof:placetype":"venue"
},
  "geometry": {"coordinates":[7.3602228165,46.2329368591],"type":"Point"}
}