{
  "type": "Feature",
  "properties": {
    "iso:country":"CH",
    "sg:address":"Schlossstrasse 23",
    "sg:city":"Steffisburg",
    "sg:orig_category":"Sportvereine Motorrad",
    "sg:phone":"+41 33 437 01 04",
    "sg:postcode":"3613",
    "sg:province":"Bern",
    "wof:name":"Vespa-club Thun",
    "wof:placetype":"venue"
},
  "geometry": {"coordinates":[7.6247777939,46.7644577026],"type":"Point"}
}