{
  "type": "Feature",
  "properties": {
    "iso:country":"CH",
    "sg:address":"Selnaustrasse 1 8002 Z\u00fcrich. Postfach",
    "sg:city":"Z\u00fcrich",
    "sg:orig_category":"Fachdetailhandel mit pharmazeutischen Produkten",
    "sg:postcode":"8039",
    "wof:name":"Sempf J\u00fcrg",
    "wof:placetype":"venue"
},
  "geometry": {"coordinates":[8.0517930984,46.7506103516],"type":"Point"}
}