{
  "type": "Feature",
  "properties": {
    "iso:country":"CH",
    "sg:address":"Waldeckstrasse 2",
    "sg:city":"Zollikofen",
    "sg:orig_category":"Bauschreinerei Innenausbau",
    "sg:phone":"+41 31 911 68 88",
    "sg:postcode":"3052",
    "sg:province":"Bern",
    "wof:name":"Ren\u00e9 Geissb\u00fchler Schreinerei & Innenausbau",
    "wof:placetype":"venue"
},
  "geometry": {"coordinates":[7.436668,46.996632],"type":"Point"}
}