{
  "type": "Feature",
  "properties": {
    "iso:country":"CH",
    "sg:address":"Dorf",
    "sg:city":"Entlebuch",
    "sg:orig_category":"Schmieden",
    "sg:phone":"+41 41 480 12 02",
    "sg:postcode":"6162",
    "sg:province":"Luzern",
    "wof:name":"Josef Bieri Schmiede",
    "wof:placetype":"venue"
},
  "geometry": {"coordinates":[8.0651550293,46.9935340881],"type":"Point"}
}