{
  "type": "Feature",
  "properties": {
    "iso:country":"CH",
    "sg:address":"Lochbruggstrasse 41",
    "sg:city":"Laufen",
    "sg:orig_category":"Institutionen f\u00fcr Behinderte Tagesheime f\u00fcr Behinderte, gesch\u00fctzte Werkst\u00e4tten",
    "sg:phone":"+41 61 761 42 41",
    "sg:postcode":"4242",
    "sg:province":"Basel-Landschaft",
    "wof:name":"Besch\u00e4ftigungsst\u00e4tte F\u00fcr Behinderte",
    "wof:placetype":"venue"
},
  "geometry": {"coordinates":[7.5058221817,47.4255485535],"type":"Point"}
}