{
  "type": "Feature",
  "properties": {
    "iso:country":"CH",
    "sg:address":"Bahnhofstrasse 13",
    "sg:city":"Derendingen",
    "sg:orig_category":"Detailhandel mit Bekleidung Detailhandel mit Damenbekleidung",
    "sg:phone":"+41 32 682 20 25",
    "sg:postcode":"4552",
    "sg:province":"Solothurn",
    "wof:name":"Levy-picard Ag",
    "wof:placetype":"venue"
},
  "geometry": {"coordinates":[7.581117,47.201096],"type":"Point"}
}