{
  "type": "Feature",
  "properties": {
    "iso:country":"CH",
    "sg:address":"Avenue Eug\u00e8ne-pittard 13",
    "sg:city":"Gen\u00e8ve",
    "sg:orig_category":"Unternehmensberatung",
    "sg:phone":"+41 22 346 88 77",
    "sg:postcode":"1206",
    "sg:province":"Gen\u00e8ve",
    "wof:name":"Aksa Sa",
    "wof:placetype":"venue"
},
  "geometry": {"coordinates":[6.1624350548,46.1916618347],"type":"Point"}
}