{
  "type": "Feature",
  "properties": {
    "iso:country":"CH",
    "sg:address":"Rue Des Terreaux 30",
    "sg:city":"Orbe",
    "sg:orig_category":"Physiotherapie",
    "sg:phone":"+41 24 441 13 23",
    "sg:postcode":"1350",
    "sg:province":"Vaud",
    "wof:name":"Olivier & Sally Majeur Physioth\u00e9rapie & Massage",
    "wof:placetype":"venue"
},
  "geometry": {"coordinates":[6.5310788155,46.7244338989],"type":"Point"}
}