{
  "type": "Feature",
  "properties": {
    "iso:country":"CH",
    "sg:address":"Chemin Des P\u00e9toleyres 7",
    "sg:city":"Morges",
    "sg:orig_category":"Elektroinstallation",
    "sg:phone":"+41 21 321 44 55",
    "sg:postcode":"1110",
    "sg:province":"Vaud",
    "wof:name":"Monnet R. Et Cie Sa",
    "wof:placetype":"venue"
},
  "geometry": {"coordinates":[6.6310310364,46.5228118896],"type":"Point"}
}