{
  "type": "Feature",
  "properties": {
    "iso:country":"CH",
    "sg:address":"Wilgasse 3 6370 Oberdorf Nw. Postfach",
    "sg:city":"Stans",
    "sg:orig_category":"Elektrizit\u00e4tsversorgung",
    "sg:phone":"+41 41 611 01 41",
    "sg:postcode":"6371",
    "sg:province":"Nidwalden",
    "wof:name":"Kantonales Elektrizit\u00e4tswerk Nidwalden",
    "wof:placetype":"venue"
},
  "geometry": {"coordinates":[8.3892087936,46.9601325989],"type":"Point"}
}