{
  "type": "Feature",
  "properties": {
    "iso:country":"CH",
    "sg:address":"Neumarkt 6",
    "sg:city":"Z\u00fcrich",
    "sg:classifiers":[
        {
            "category":"Home & Garden",
            "subcategory":"Home Furnishings",
            "type":"Retail Goods"
        }
    ],
    "sg:phone":"+41 12619650",
    "sg:postcode":"8001",
    "sg:province":"Z\u00fcrich",
    "sg:tags":[
        "desk"
    ],
    "wof:name":"J\u00fcrg Bally Partner Ag",
    "wof:placetype":"venue"
},
  "geometry": {"coordinates":[8.545888,47.372486],"type":"Point"}
}