{
  "type": "Feature",
  "properties": {
    "iso:country":"CH",
    "sg:address":"Sternenhofstrasse 15a",
    "sg:city":"Reinach",
    "sg:classifiers":[
        {
            "category":"Autos & Motor Vehicles",
            "subcategory":"Automobile Sales",
            "type":"Retail Goods"
        }
    ],
    "sg:phone":"+41 61 711 87 22",
    "sg:postcode":"4153",
    "sg:province":"Basel-Landschaft",
    "sg:tags":[
        "varnish",
        "lacquers"
    ],
    "wof:name":"Elaax Ag",
    "wof:placetype":"venue"
},
  "geometry": {"coordinates":[7.59609,47.489349],"type":"Point"}
}