{
  "type": "Feature",
  "properties": {
    "iso:country":"CH",
    "sg:address":"Lodrino",
    "sg:city":"Lodrino",
    "sg:classifiers":[
        {
            "category":"Banks & Credit Unions",
            "subcategory":"Bank",
            "type":"Services"
        }
    ],
    "sg:phone":"+41 4192662216",
    "sg:postcode":"6527",
    "sg:province":"Ticino",
    "wof:name":"Banca Raiffeisen, Di Lodrino-prosito",
    "wof:placetype":"venue"
},
  "geometry": {"coordinates":[8.981131,46.299667],"type":"Point"}
}