{
  "type": "Feature",
  "properties": {
    "iso:country":"CH",
    "sg:address":"Sihlweidstrasse 64",
    "sg:city":"Z\u00fcrich",
    "sg:orig_category":"Finanzierungsinstitutionen",
    "sg:postcode":"8041",
    "sg:province":"Z\u00fcrich",
    "wof:name":"Trevicontrol Sa",
    "wof:placetype":"venue"
},
  "geometry": {"coordinates":[8.5180130005,47.3273582458],"type":"Point"}
}