{
  "type": "Feature",
  "properties": {
    "iso:country":"CH",
    "sg:address":"Uttenbergstr. 3",
    "sg:city":"Knonau",
    "sg:orig_category":"Stukkateurgewerbe, Gipserei U Verputzerei",
    "sg:phone":"+41 17682145",
    "sg:postcode":"8934",
    "sg:province":"Z\u00fcrich",
    "wof:name":"Claude Rochat, Gipserarbeiten",
    "wof:placetype":"venue"
},
  "geometry": {"coordinates":[8.4621276855,47.2233772278],"type":"Point"}
}