{
  "type": "Feature",
  "properties": {
    "iso:country":"CH",
    "sg:address":"Grand-rue 20",
    "sg:city":"St-maurice",
    "sg:orig_category":"Detailhandel mit Fleisch U Fleischwaren",
    "sg:phone":"+41 24 485 13 92",
    "sg:postcode":"1890",
    "sg:province":"Valais",
    "wof:name":"Franz Lochmann Boucherie Agaunoise",
    "wof:placetype":"venue"
},
  "geometry": {"coordinates":[7.0047550201,46.2181091309],"type":"Point"}
}