{
  "type": "Feature",
  "properties": {
    "iso:country":"CH",
    "sg:address":"Werftstrasse 15 9323 Steinach. Postfach 42",
    "sg:city":"Steinach",
    "sg:orig_category":"Herstellung von Gummi U Kunststoffwaren",
    "sg:phone":"+41 55 246 19 31",
    "sg:postcode":"9323",
    "sg:province":"St. Gallen",
    "wof:name":"Z\u00fcger Erich Ag",
    "wof:placetype":"venue"
},
  "geometry": {"coordinates":[8.9279069901,47.2645988464],"type":"Point"}
}