{
  "type": "Feature",
  "properties": {
    "iso:country":"CH",
    "sg:address":"D\u00e4hlh\u00f6lzliweg 18",
    "sg:city":"Bern",
    "sg:orig_category":"Softwareentwicklung U beratung",
    "sg:phone":"+41 31 974 02 05",
    "sg:postcode":"3005",
    "sg:province":"Bern",
    "wof:name":"Netstyle.ch Gmbh",
    "wof:placetype":"venue"
},
  "geometry": {"coordinates":[7.4548802376,46.940574646],"type":"Point"}
}