{
  "type": "Feature",
  "properties": {
    "iso:country":"CH",
    "sg:address":"Hagenholzstr. 71",
    "sg:city":"Z\u00fcrich",
    "sg:classifiers":[
        {
            "category":"Manufacturing",
            "subcategory":"Printing",
            "type":"Manufacturing & Wholesale Goods"
        }
    ],
    "sg:phone":"+41 4113088411",
    "sg:postcode":"8050",
    "sg:province":"Z\u00fcrich",
    "sg:tags":[
        "publishing"
    ],
    "wof:name":"Karl Schwegler Ag",
    "wof:placetype":"venue"
},
  "geometry": {"coordinates":[8.556189537,47.4146690369],"type":"Point"}
}