{
  "type": "Feature",
  "properties": {
    "iso:country":"CH",
    "sg:address":"Baselstrasse 13",
    "sg:city":"Solothurn",
    "sg:orig_category":"Wirtschafts- and Arbeitgeberverb\u00e4nde",
    "sg:phone":"+41 32 622 80 03",
    "sg:postcode":"4500",
    "sg:province":"Solothurn",
    "wof:name":"Verband Der Museen Der Schweiz",
    "wof:placetype":"venue"
},
  "geometry": {"coordinates":[7.5419249535,47.2100563049],"type":"Point"}
}