{
  "type": "Feature",
  "properties": {
    "iso:country":"CH",
    "sg:address":"Berghalde 8",
    "sg:city":"Russikon",
    "sg:orig_category":"Fachdetailhandel in Verkaufsr\u00e4umen",
    "sg:postcode":"8332",
    "sg:province":"Z\u00fcrich",
    "wof:name":"Bilderverlag Veritatis Margrit M. Belser Gallmann",
    "wof:placetype":"venue"
},
  "geometry": {"coordinates":[8.7748737335,47.398525238],"type":"Point"}
}