{
  "type": "Feature",
  "properties": {
    "iso:country":"CH",
    "sg:address":"Obergerlafingenstrasse 8",
    "sg:city":"Gerlafingen",
    "sg:orig_category":"M\u00f6belschreinereien",
    "sg:phone":"+41 32 675 66 92",
    "sg:postcode":"4563",
    "sg:province":"Solothurn",
    "wof:name":"Flury Peter.",
    "wof:placetype":"venue"
},
  "geometry": {"coordinates":[7.5729298592,47.1702537537],"type":"Point"}
}