{
  "type": "Feature",
  "properties": {
    "iso:country":"CH",
    "sg:address":"Via Davos Must\u00e9r 737",
    "sg:city":"Disentis/must\u00e9r",
    "sg:orig_category":"Finanzierungsinstitutionen Unternehmensberatung",
    "sg:phone":"+41 81 947 59 59",
    "sg:postcode":"7180",
    "sg:province":"Graubunden",
    "wof:name":"Secunda Grischa Sa",
    "wof:placetype":"venue"
},
  "geometry": {"coordinates":[8.8592195511,46.70703125],"type":"Point"}
}