{
  "type": "Feature",
  "properties": {
    "iso:country":"CH",
    "sg:address":"1585",
    "sg:city":"Salavaux",
    "sg:orig_category":"Verwaltung von Immobilien",
    "sg:postcode":"1585",
    "sg:province":"Vaud",
    "wof:name":"Cecom Salavaux Sa",
    "wof:placetype":"venue"
},
  "geometry": {"coordinates":[7.0223398209,46.9181594849],"type":"Point"}
}