{
  "type": "Feature",
  "properties": {
    "iso:country":"CH",
    "sg:address":"Opfikonerstrasse 45 8304 Wallisellen. Postfach",
    "sg:city":"Z\u00fcrich",
    "sg:orig_category":"Effektenvermittlung Broker Finanzierungsinstitutionen",
    "sg:phone":"+41 18312255",
    "sg:postcode":"8001",
    "sg:province":"Z\u00fcrich",
    "wof:name":"Aabc Alternative Asset Broker Co Ltd Beteiligungen Usw",
    "wof:placetype":"venue"
},
  "geometry": {"coordinates":[8.5825548172,47.4180755615],"type":"Point"}
}