{
  "type": "Feature",
  "properties": {
    "iso:country":"CH",
    "sg:address":"Riedstrasse 7 6330 Cham. Postfach 5264",
    "sg:city":"Cham",
    "sg:orig_category":"Grosshandel mit sonstigen Halbwaren Sonstiger Grosshandel",
    "sg:phone":"+41 41 748 19 19",
    "sg:postcode":"6330",
    "sg:province":"Zug",
    "wof:name":"Pergo Ag",
    "wof:placetype":"venue"
},
  "geometry": {"coordinates":[8.4766769409,47.1891326904],"type":"Point"}
}