{
  "type": "Feature",
  "properties": {
    "iso:country":"CH",
    "sg:address":"Goetz-monin Rue 24 1200 Genf. Postfach",
    "sg:city":"Gen\u00e8ve",
    "sg:orig_category":"Sonstige mit Sport verbundene T\u00e4tigkeiten",
    "sg:phone":"+41 22 321 20 03",
    "sg:postcode":"1201",
    "sg:province":"Gen\u00e8ve",
    "wof:name":"Judo Jiu-jitsu Institut Sarl",
    "wof:placetype":"venue"
},
  "geometry": {"coordinates":[6.1472578049,46.1940231323],"type":"Point"}
}