{
  "type": "Feature",
  "properties": {
    "iso:country":"CH",
    "sg:address":"Kronengasse 7",
    "sg:city":"Selzach",
    "sg:orig_category":"Detailhandel mit M\u00f6beln U Haushaltsgegenst\u00e4nden",
    "sg:phone":"+41 62 391 36 33",
    "sg:postcode":"2545",
    "sg:province":"Solothurn",
    "wof:name":"Steiner Hanny, Hanny's Bsteckh\u00fcsli",
    "wof:placetype":"venue"
},
  "geometry": {"coordinates":[7.4525651932,47.2073745728],"type":"Point"}
}