{
  "type": "Feature",
  "properties": {
    "iso:country":"CH",
    "sg:address":"6690",
    "sg:city":"Cavergno",
    "sg:orig_category":"Zimmerei, Dachdeckerei, Bauspenglerei U Abdichtung",
    "sg:phone":"+41 91 754 11 62",
    "sg:postcode":"6690",
    "sg:province":"Ticino",
    "wof:name":"Zanini Felice",
    "wof:placetype":"venue"
},
  "geometry": {"coordinates":[8.6107501984,46.3444099426],"type":"Point"}
}