{
  "type": "Feature",
  "properties": {
    "iso:country":"CH",
    "sg:address":"Baselstrasse 8",
    "sg:city":"Feldbrunnen",
    "sg:orig_category":"Grosshandel mit Geschenkartikeln U Souvenirs Grosshandel mit keramischen Erzeugnissen,Glaswaren U Ta",
    "sg:phone":"+41 62 873 15 28",
    "sg:postcode":"4532",
    "sg:province":"Solothurn",
    "wof:name":"Fantasia Geschenke Gmbh",
    "wof:placetype":"venue"
},
  "geometry": {"coordinates":[7.9516158104,47.5460395813],"type":"Point"}
}