{
  "type": "Feature",
  "properties": {
    "iso:country":"CH",
    "sg:address":"Kirchstrasse 32",
    "sg:city":"Fl\u00fcelen",
    "sg:classifiers":[
        {
            "category":"Personal",
            "subcategory":"Sauna",
            "type":"Services"
        }
    ],
    "sg:phone":"+41 41 870 68 52",
    "sg:postcode":"6454",
    "sg:province":"Uri",
    "wof:name":"Hermann Aregger Sauna",
    "wof:placetype":"venue"
},
  "geometry": {"coordinates":[8.6269083023,46.9050292969],"type":"Point"}
}