{
  "type": "Feature",
  "properties": {
    "iso:country":"CH",
    "sg:address":"Schloss Klingelburg",
    "sg:city":"Rheineck",
    "sg:orig_category":"Aktivit\u00e4ten der Generalunternehmen im Baugewerbe Allgemeiner Hoch U Tiefbau",
    "sg:phone":"+41 56 443 28 43",
    "sg:postcode":"9424",
    "sg:province":"St. Gallen",
    "wof:name":"Keller Rudolf Generalunternehmung Ag",
    "wof:placetype":"venue"
},
  "geometry": {"coordinates":[8.169972,47.452297],"type":"Point"}
}