{
  "type": "Feature",
  "properties": {
    "iso:country":"CH",
    "sg:address":"Rue Arnold Winkelried 4",
    "sg:city":"Gen\u00e8ve",
    "sg:orig_category":"Detailhandel mit Uhren U Schmuck Reparatur von Uhren U Schmuck",
    "sg:phone":"+41 22 738 60 11",
    "sg:postcode":"1201",
    "sg:province":"Gen\u00e8ve",
    "wof:name":"Time Gallery Montres & Bijoux",
    "wof:placetype":"venue"
},
  "geometry": {"coordinates":[6.1463279724,46.2071723938],"type":"Point"}
}