{
  "type": "Feature",
  "properties": {
    "iso:country":"CH",
    "sg:address":"Industriestrasse 14",
    "sg:city":"Egerkingen",
    "sg:orig_category":"Herstellung von Industriegasen Herstellung von sonstigen Maschinen f\u00fcr unspezifische Verwendung",
    "sg:phone":"+41 62 387 84 84",
    "sg:postcode":"4622",
    "sg:province":"Solothurn",
    "wof:name":"Pangas Technische & Medizinische Gase Acetylenwerk Egerkingen",
    "wof:placetype":"venue"
},
  "geometry": {"coordinates":[7.7924971581,47.3154144287],"type":"Point"}
}