{
  "type": "Feature",
  "properties": {
    "iso:country":"CH",
    "sg:address":"Gempenstrasse 10 3415 R\u00fcegsauschachen. Postfach",
    "sg:city":"R\u00fcegsauschachen",
    "sg:orig_category":"Herstellung von Duft U K\u00f6rperpflegemitteln",
    "sg:phone":"+41 31 818 54 55",
    "sg:postcode":"3415",
    "sg:province":"Bern",
    "wof:name":"Bcm-care Ag",
    "wof:placetype":"venue"
},
  "geometry": {"coordinates":[8.8368453979,47.3006668091],"type":"Point"}
}