{
  "type": "Feature",
  "properties": {
    "iso:country":"CH",
    "sg:address":"Baumgartenweg 12",
    "sg:city":"M\u00fcnchenstein",
    "sg:orig_category":"Aktivit\u00e4ten der Generalunternehmen im Baugewerbe Allgemeiner Hoch U Tiefbau",
    "sg:phone":"+41 61 411 11 56",
    "sg:postcode":"4142",
    "sg:province":"Basel-Landschaft",
    "wof:name":"Bgu Bau Und Generalunternehmung Ag",
    "wof:placetype":"venue"
},
  "geometry": {"coordinates":[7.621143,47.509247],"type":"Point"}
}