{
  "type": "Feature",
  "properties": {
    "iso:country":"CH",
    "sg:address":"Recordon Avenue 30 1004 Lausanne. Postfach",
    "sg:city":"Lausanne",
    "sg:orig_category":"Herstellung von Konstruktionsteilen, Fertigbauteilen U Ausbauelementen aus Holz",
    "sg:postcode":"1003",
    "sg:province":"Vaud",
    "wof:name":"Menuiserie Joe Baudois",
    "wof:placetype":"venue"
},
  "geometry": {"coordinates":[6.8084278107,46.609588623],"type":"Point"}
}