{
  "type": "Feature",
  "properties": {
    "iso:country":"CH",
    "sg:address":"Tieftalweg 2",
    "sg:city":"Immensee",
    "sg:classifiers":[
        {
            "category":"Restaurant",
            "type":"Food & Drink"
        }
    ],
    "sg:phone":"+41 41 850 48 14",
    "sg:postcode":"6405",
    "sg:province":"Schwyz",
    "wof:name":"Restaurant Zum Schl\u00fcssel",
    "wof:placetype":"venue"
},
  "geometry": {"coordinates":[8.4637451172,47.0968856812],"type":"Point"}
}