{
  "type": "Feature",
  "properties": {
    "iso:country":"CH",
    "sg:address":"Rivo Paradiso 2 /4",
    "sg:city":"Paradiso",
    "sg:orig_category":"Detailhandel mit Tabakwaren",
    "sg:phone":"+41 91 994 16 26",
    "sg:postcode":"6900",
    "sg:province":"Ticino",
    "wof:name":"Elcigarroo Sa Tabac Center",
    "wof:placetype":"venue"
},
  "geometry": {"coordinates":[8.9470481873,45.9920501709],"type":"Point"}
}