{
  "type": "Feature",
  "properties": {
    "iso:country":"CH",
    "sg:address":"Rue Marterey 2",
    "sg:city":"Lausanne",
    "sg:orig_category":"Fahrschulen, Flugschulen",
    "sg:phone":"+41 79 250 20 22",
    "sg:postcode":"1005",
    "sg:province":"Vaud",
    "wof:name":"Marie-christine Graf Moto & Auto-\u00e9cole",
    "wof:placetype":"venue"
},
  "geometry": {"coordinates":[6.6378250122,46.5197296143],"type":"Point"}
}