{
  "type": "Feature",
  "properties": {
    "iso:country":"CH",
    "sg:address":"Gasthaus B\u00e4ren",
    "sg:city":"Vorderthal",
    "sg:orig_category":"RESTAURANTS: TEA-ROOMS",
    "sg:postcode":"8857",
    "sg:province":"Schwyz",
    "wof:name":"Ziltener Paul",
    "wof:placetype":"venue"
},
  "geometry": {"coordinates":[8.9013547897,47.1198883057],"type":"Point"}
}