{
  "type": "Feature",
  "properties": {
    "iso:country":"CH",
    "sg:address":"Les Jaccolats",
    "sg:city":"Yvorne",
    "sg:orig_category":"Landwirtschaftliche Maschinen Wartung and Reparatur Mechanische Werkst\u00e4tten",
    "sg:phone":"+41 24 466 13 83",
    "sg:postcode":"1853",
    "sg:province":"Vaud",
    "wof:name":"Gigandet Sa Atelier M\u00e9canique Et Viticoles",
    "wof:placetype":"venue"
},
  "geometry": {"coordinates":[6.9504160881,46.3307723999],"type":"Point"}
}