{
  "type": "Feature",
  "properties": {
    "iso:country":"CH",
    "sg:address":"Route Du Crochet 9",
    "sg:city":"Givisiez",
    "sg:orig_category":"Elektro- and elektronische Maschinen Grosshandel Sonstiger Grosshandel",
    "sg:phone":"+41 26 426 55 55",
    "sg:postcode":"1762",
    "sg:province":"Fribourg",
    "wof:name":"Atmel S\u00e0rl",
    "wof:placetype":"venue"
},
  "geometry": {"coordinates":[7.1341252327,46.816192627],"type":"Point"}
}