{
  "type": "Feature",
  "properties": {
    "iso:country":"CH",
    "sg:address":"Sahlimatte 200",
    "sg:city":"Detligen",
    "sg:orig_category":"Tankstellen",
    "sg:phone":"+41 31 825 62 45",
    "sg:postcode":"3036",
    "sg:province":"Bern",
    "wof:name":"Erwin Bill Ag Garage & Tankstelle",
    "wof:placetype":"venue"
},
  "geometry": {"coordinates":[7.2732839584,47.0015716553],"type":"Point"}
}