{
  "type": "Feature",
  "properties": {
    "iso:country":"CH",
    "sg:address":"Niederfeldstrasse 10 8932 Mettmenstetten. Postfach",
    "sg:city":"Mettmenstetten",
    "sg:orig_category":"Zimmerei, Dachdeckerei, Bauspenglerei U Abdichtung",
    "sg:phone":"+41 55 240 87 00",
    "sg:postcode":"8932",
    "sg:province":"Z\u00fcrich",
    "wof:name":"K\u00fcndig Ag Holzbau",
    "wof:placetype":"venue"
},
  "geometry": {"coordinates":[8.8664484024,47.2666053772],"type":"Point"}
}