{
  "type": "Feature",
  "properties": {
    "iso:country":"CH",
    "sg:address":"Or\u00e9e Chemin De L' 21 1293 Bellevue. Postfach",
    "sg:city":"Bellevue",
    "sg:orig_category":"Allgemeiner Hoch U Tiefbau",
    "sg:phone":"+41 22 774 45 66",
    "sg:postcode":"1293",
    "sg:province":"Gen\u00e8ve",
    "wof:name":"Ridelco, Richoz Daniel Entreprise Du B\u00e2timent",
    "wof:placetype":"venue"
},
  "geometry": {"coordinates":[-4.279354,48.451893],"type":"Point"}
}