{
  "type": "Feature",
  "properties": {
    "iso:country":"CH",
    "sg:address":"Aewilerstrasse 11",
    "sg:city":"Ganterschwil",
    "sg:orig_category":"Fussboden, Fliesen U Plattenlegerei, Tapeziererei",
    "sg:postcode":"9608",
    "sg:province":"St. Gallen",
    "wof:name":"M\u00fcller Paul.",
    "wof:placetype":"venue"
},
  "geometry": {"coordinates":[7.2517352104,46.7967453003],"type":"Point"}
}