{
  "type": "Feature",
  "properties": {
    "iso:country":"CH",
    "sg:address":"Erzgrubenweg 1",
    "sg:city":"Aarau",
    "sg:orig_category":"Fast-Foodrestaurants - nicht eigenst\u00e4ndig -Caterer",
    "sg:phone":"+41 62 824 77 77",
    "sg:postcode":"5000",
    "sg:province":"Aargau",
    "wof:name":"Pizza Kurier Il Mulino",
    "wof:placetype":"venue"
},
  "geometry": {"coordinates":[8.0404176712,47.4009475708],"type":"Point"}
}