{
  "type": "Feature",
  "properties": {
    "iso:country":"CH",
    "sg:address":"Lausanne Rue De 65",
    "sg:city":"Pr\u00e9verenges",
    "sg:orig_category":"Unclassifiable Establishments",
    "sg:postcode":"1028",
    "sg:province":"Vaud",
    "wof:name":"Is Staff Holding S\u00e0rl",
    "wof:placetype":"venue"
},
  "geometry": {"coordinates":[6.5305070877,46.517124176],"type":"Point"}
}