{
  "type": "Feature",
  "properties": {
    "iso:country":"CH",
    "sg:address":"Sur La Place 92a",
    "sg:city":"Bonfol",
    "sg:orig_category":"Galvanische Betriebe",
    "sg:phone":"+41 32 474 50 20",
    "sg:postcode":"2944",
    "sg:province":"Jura",
    "wof:name":"Maurice Girardin Polissage Or & Acier",
    "wof:placetype":"venue"
},
  "geometry": {"coordinates":[7.1502361298,47.4787330627],"type":"Point"}
}