{
  "type": "Feature",
  "properties": {
    "iso:country":"CH",
    "sg:address":"B\u00e4umlihofstrasse 68",
    "sg:city":"Basel",
    "sg:orig_category":"Fotografische Ateliers",
    "sg:phone":"+41 19324481",
    "sg:postcode":"4058",
    "sg:province":"Basel-Stadt",
    "wof:name":"Ren\u00e9 Kappeler Fotografisches Atelier",
    "wof:placetype":"venue"
},
  "geometry": {"coordinates":[8.7951393127,47.3207168579],"type":"Point"}
}