{
  "type": "Feature",
  "properties": {
    "iso:country":"CH",
    "sg:address":"Bernstr.",
    "sg:city":"Schwarzenburg",
    "sg:orig_category":"Instandhaltung U Reparatur von Automobilen",
    "sg:postcode":"3150",
    "sg:province":"Bern",
    "wof:name":"Fryberg M.",
    "wof:placetype":"venue"
},
  "geometry": {"coordinates":[7.3411660194,46.8191223145],"type":"Point"}
}