{
  "type": "Feature",
  "properties": {
    "iso:country":"CH",
    "sg:address":"Route Des Gouttes-d'or 17",
    "sg:city":"Neuch\u00e2tel",
    "sg:orig_category":"Elektroinstallation",
    "sg:phone":"+41 32 729 70 10",
    "sg:postcode":"2000",
    "sg:province":"Neuch\u00e2tel",
    "wof:name":"Connectcom",
    "wof:placetype":"venue"
},
  "geometry": {"coordinates":[6.817855835,47.4077529907],"type":"Point"}
}