{
  "type": "Feature",
  "properties": {
    "iso:country":"CH",
    "sg:address":"Lettenweg 114",
    "sg:city":"Allschwil",
    "sg:classifiers":[
        {
            "category":"Wholesale",
            "subcategory":"Machinery & Supplies",
            "type":"Manufacturing & Wholesale Goods"
        }
    ],
    "sg:phone":"+41 61 482 22 62",
    "sg:postcode":"4123",
    "sg:province":"Basel-Landschaft",
    "sg:tags":[
        "equipment",
        "-",
        "precision",
        "glass",
        "optical",
        "health",
        "instrument"
    ],
    "wof:name":"Holzer Optik Ag",
    "wof:placetype":"venue"
},
  "geometry": {"coordinates":[7.5506381989,47.5483322144],"type":"Point"}
}