{
  "type": "Feature",
  "properties": {
    "iso:country":"CH",
    "sg:address":"Dorfstrasse 164 5512 Wohlenschwil. Postfach",
    "sg:city":"Wohlenschwil",
    "sg:orig_category":"Instandhaltung U Reparatur von Automobilen",
    "sg:phone":"+41 56 491 23 05",
    "sg:postcode":"5512",
    "sg:province":"Aargau",
    "wof:name":"Carrosserie Saxer Ag",
    "wof:placetype":"venue"
},
  "geometry": {"coordinates":[8.2605791092,47.4208831787],"type":"Point"}
}