{
  "type": "Feature",
  "properties": {
    "addr:full":"Soodstrasse 6 Adliswil Z\u00fcrich 8134",
    "addr:housenumber":"6",
    "addr:postcode":"8134",
    "addr:street":"Soodstrasse",
    "iso:country":"CH",
    "sg:address":"Soodstrasse 6",
    "sg:city":"Adliswil",
    "sg:orig_category":"Arztpraxen",
    "sg:phone":"+41 17103322",
    "sg:postcode":"8134",
    "sg:province":"Z\u00fcrich",
    "wof:name":"Dr.med.robert Kurmann Spezialarzt Fmh",
    "wof:placetype":"venue"
},
  "geometry": {"coordinates":[8.526142,47.315029],"type":"Point"}
}