{
  "type": "Feature",
  "properties": {
    "iso:country":"CH",
    "sg:address":"Mura",
    "sg:city":"Vals",
    "sg:orig_category":"Allgemeiner Hoch U Tiefbau Hoch U Tiefbau",
    "sg:phone":"+41 79 621 95 54",
    "sg:postcode":"7132",
    "sg:province":"Graubunden",
    "wof:name":"Berni Bau Ag",
    "wof:placetype":"venue"
},
  "geometry": {"coordinates":[9.179589,46.615059],"type":"Point"}
}