{
  "type": "Feature",
  "properties": {
    "iso:country":"CH",
    "sg:address":"Z\u00fcrcherstrasse 125",
    "sg:city":"Frauenfeld",
    "sg:orig_category":"Detailhandel mit B\u00fcchern, Zeitungen, Schreib U Papeteriewaren",
    "sg:postcode":"8500",
    "sg:province":"Thurgau",
    "wof:name":"Ertl Gisela",
    "wof:placetype":"venue"
},
  "geometry": {"coordinates":[8.893856,47.554001],"type":"Point"}
}