{
  "type": "Feature",
  "properties": {
    "iso:country":"CH",
    "sg:address":"Blattengasse",
    "sg:city":"M\u00e4nnedorf",
    "sg:orig_category":"Vorschulen, Kinderg\u00e4rten",
    "sg:phone":"+41 19202872",
    "sg:postcode":"8708",
    "sg:province":"Z\u00fcrich",
    "wof:name":"Kindergarten Blatten",
    "wof:placetype":"venue"
},
  "geometry": {"coordinates":[8.6966934204,47.2547492981],"type":"Point"}
}