{
  "type": "Feature",
  "properties": {
    "iso:country":"CH",
    "sg:address":"Claragraben 157",
    "sg:city":"Basel",
    "sg:orig_category":"Maler U Glasergewerbe Malerei",
    "sg:phone":"+41 79 205 99 33",
    "sg:postcode":"4057",
    "sg:province":"Basel-Stadt",
    "wof:name":"L. Kugel Ag",
    "wof:placetype":"venue"
},
  "geometry": {"coordinates":[7.5917811394,47.5659980774],"type":"Point"}
}