{
  "type": "Feature",
  "properties": {
    "iso:country":"CH",
    "sg:address":"R\u00f6merstrasse 34",
    "sg:city":"Baden",
    "sg:orig_category":"Softwareentwicklung U beratung",
    "sg:phone":"+41 56 222 94 78",
    "sg:postcode":"5400",
    "sg:province":"Aargau",
    "wof:name":"Asist G. Novak",
    "wof:placetype":"venue"
},
  "geometry": {"coordinates":[8.3055429459,47.4812850952],"type":"Point"}
}