{
  "type": "Feature",
  "properties": {
    "iso:country":"CH",
    "sg:address":"Simplon Rue Du 8 1207 Gen\u00e8ve. Postfach",
    "sg:city":"Gen\u00e8ve",
    "sg:orig_category":"RESTAURANTS: TEA-ROOMS",
    "sg:postcode":"1207",
    "sg:province":"Gen\u00e8ve",
    "wof:name":"Chaieb Taoufik",
    "wof:placetype":"venue"
},
  "geometry": {"coordinates":[6.1581830978,46.2045135498],"type":"Point"}
}