{
  "type": "Feature",
  "properties": {
    "iso:country":"CH",
    "sg:address":"Waldeggweg 4b",
    "sg:city":"Kloten",
    "sg:orig_category":"Instandhaltung U Reparatur von Automobilen",
    "sg:phone":"+41 18137300",
    "sg:postcode":"8302",
    "sg:province":"Z\u00fcrich",
    "wof:name":"Alpine Atelier, Garage Isliker, Kloten",
    "wof:placetype":"venue"
},
  "geometry": {"coordinates":[8.576915741,47.4410896301],"type":"Point"}
}