{
  "type": "Feature",
  "properties": {
    "iso:country":"CH",
    "sg:address":"Oberdorf 42",
    "sg:city":"Schnottwil",
    "sg:orig_category":"Zimmerei, Dachdeckerei, Bauspenglerei U Abdichtung",
    "sg:phone":"+41 32 351 36 37",
    "sg:postcode":"3253",
    "sg:province":"Solothurn",
    "wof:name":"Fahrer Erich",
    "wof:placetype":"venue"
},
  "geometry": {"coordinates":[7.3928499222,47.1117401123],"type":"Point"}
}