{
  "type": "Feature",
  "properties": {
    "iso:country":"CH",
    "sg:address":"Chesa Jann",
    "sg:city":"Schlarigna",
    "sg:orig_category":"Architekturb\u00fcros",
    "sg:phone":"+41 81 833 83 12",
    "sg:postcode":"7505",
    "sg:province":"Graubunden",
    "wof:name":"Fernando & Erica Fanconi Architekturb\u00fcro",
    "wof:placetype":"venue"
},
  "geometry": {"coordinates":[9.860075,46.51268],"type":"Point"}
}