{
  "type": "Feature",
  "properties": {
    "iso:country":"CH",
    "sg:address":"Thunstrasse 37 3005 Bern. Postfach",
    "sg:city":"Bern",
    "sg:orig_category":"Gesundheitswesen",
    "sg:postcode":"3005",
    "sg:province":"Bern",
    "wof:name":"Stiftung Des Vereins F\u00fcr Das Alter Sektion Bern-stadt Die Stiftung Bezweckt, D. Wohl Betagter Menschen Zu Erhalten, Zu Heben Usw",
    "wof:placetype":"venue"
},
  "geometry": {"coordinates":[7.4552211761,46.9417266846],"type":"Point"}
}