{
  "type": "Feature",
  "properties": {
    "iso:country":"CH",
    "sg:address":"Selnaustrasse 15",
    "sg:city":"Z\u00fcrich",
    "sg:orig_category":"Non-Classified Establishments",
    "sg:phone":"+41 21312315",
    "sg:postcode":"8002",
    "sg:province":"Z\u00fcrich",
    "wof:name":"Ccc Centre Commercial De Cugy Sa",
    "wof:placetype":"venue"
},
  "geometry": {"coordinates":[6.6639499664,46.5902061462],"type":"Point"}
}