{
  "type": "Feature",
  "properties": {
    "iso:country":"CH",
    "sg:address":"Weidenweg 13",
    "sg:city":"Frenkendorf",
    "sg:orig_category":"Reiseb\u00fcros U Reiseveranstalter",
    "sg:phone":"+41 61 903 21 15",
    "sg:postcode":"4402",
    "sg:province":"Basel-Landschaft",
    "wof:name":"Prestige Golf Tours Gmbh",
    "wof:placetype":"venue"
},
  "geometry": {"coordinates":[7.7145199776,47.5000305176],"type":"Point"}
}