{
  "type": "Feature",
  "properties": {
    "iso:country":"CH",
    "sg:address":"Stanserstrasse 3 6362 Stansstad. Postfach 418",
    "sg:city":"Stansstad",
    "sg:orig_category":"Detailhandel mit Radio U Fernsehger\u00e4ten Detailhandel mit elektrischen Haushalts-,Radio U Fernsehger\u00e4",
    "sg:phone":"+41 41 610 36 66",
    "sg:postcode":"6362",
    "sg:province":"Nidwalden",
    "wof:name":"Huber Othmar Ag",
    "wof:placetype":"venue"
},
  "geometry": {"coordinates":[8.3360319138,46.9781341553],"type":"Point"}
}