{
  "type": "Feature",
  "properties": {
    "iso:country":"CH",
    "sg:address":"Schulstrasse 36",
    "sg:city":"Urdorf",
    "sg:orig_category":"Finanzierungsinstitutionen",
    "sg:phone":"+41 17340595",
    "sg:postcode":"8902",
    "sg:province":"Z\u00fcrich",
    "wof:name":"Farr\u00e9r H. Allgemeiner Beratungsservice",
    "wof:placetype":"venue"
},
  "geometry": {"coordinates":[8.4269771576,47.3873901367],"type":"Point"}
}