{
  "type": "Feature",
  "properties": {
    "iso:country":"CH",
    "sg:address":"Simplon Rue Du 6",
    "sg:city":"Lausanne",
    "sg:orig_category":"Detailhandel mit Waren verschiedener Art, Hauptrichtung Nahrungsmittel",
    "sg:postcode":"1006",
    "sg:province":"Vaud",
    "wof:name":"Syed Shah Indian Shop",
    "wof:placetype":"venue"
},
  "geometry": {"coordinates":[6.6318850517,46.5156440735],"type":"Point"}
}