{
  "type": "Feature",
  "properties": {
    "iso:country":"CH",
    "sg:address":"Wesemlinstrasse 2",
    "sg:city":"Luzern",
    "sg:orig_category":"Sonstiger Grosshandel",
    "sg:phone":"+41 41 420 74 13",
    "sg:postcode":"6006",
    "sg:province":"Luzern",
    "wof:name":"Transport Mijajlovic",
    "wof:placetype":"venue"
},
  "geometry": {"coordinates":[8.3093938828,47.0602226257],"type":"Point"}
}