{
  "type": "Feature",
  "properties": {
    "iso:country":"CH",
    "sg:address":"6772 Rodi-fiesso. Postfach",
    "sg:city":"Rodi-fiesso",
    "sg:orig_category":"Unclassifiable Establishments",
    "sg:phone":"+41 91 867 12 12",
    "sg:postcode":"6772",
    "sg:province":"Ticino",
    "wof:name":"Elmaga Di Mario Galbusera",
    "wof:placetype":"venue"
},
  "geometry": {"coordinates":[8.7374019623,46.4902572632],"type":"Point"}
}