{
  "type": "Feature",
  "properties": {
    "iso:country":"CH",
    "sg:address":"Grand-rue 162",
    "sg:city":"Ste-croix",
    "sg:orig_category":"Detailhandel mit Brot, Back U S\u00fcsswaren",
    "sg:postcode":"1450",
    "sg:province":"Vaud",
    "wof:name":"Dos Santos Anacleto",
    "wof:placetype":"venue"
},
  "geometry": {"coordinates":[6.457727,46.818153],"type":"Point"}
}