{
  "type": "Feature",
  "properties": {
    "iso:country":"CH",
    "sg:address":"Im Weidli 151",
    "sg:city":"Rizenbach",
    "sg:orig_category":"Herstellung von Radio U Fernsehger\u00e4ten sowie phono U videotechnischen Ger\u00e4ten",
    "sg:phone":"+41 31 751 11 09",
    "sg:postcode":"3206",
    "sg:province":"Bern",
    "wof:name":"Ar Electronic, Roger Aeschbacher",
    "wof:placetype":"venue"
},
  "geometry": {"coordinates":[7.2101960182,46.9493179321],"type":"Point"}
}