{
  "type": "Feature",
  "properties": {
    "iso:country":"CH",
    "sg:address":"Schlossstrasse 87",
    "sg:city":"Schaffhausen",
    "sg:orig_category":"Geb\u00e4ude, Wohnungsreinigung",
    "sg:phone":"+41 52 643 55 33",
    "sg:postcode":"8207",
    "sg:province":"Schaffhausen",
    "wof:name":"Janet & Hans-urs Hubmann Geb\u00e4ude-& Wohnungsreinigung",
    "wof:placetype":"venue"
},
  "geometry": {"coordinates":[8.6609897614,47.7290878296],"type":"Point"}
}