{
  "type": "Feature",
  "properties": {
    "iso:country":"CH",
    "sg:address":"Pilatusstrasse 22",
    "sg:city":"Luzern",
    "sg:classifiers":[
        {
            "category":"Banks & Credit Unions",
            "subcategory":"Bank",
            "type":"Services"
        }
    ],
    "sg:postcode":"6003",
    "sg:province":"Luzern",
    "wof:name":"Luzerner Landbank Ag",
    "wof:placetype":"venue"
},
  "geometry": {"coordinates":[8.30824,47.045658],"type":"Point"}
}