{
  "type": "Feature",
  "properties": {
    "iso:country":"CH",
    "sg:address":"Geissenbergstrasse 59",
    "sg:city":"Kreuzlingen",
    "sg:orig_category":"Herstellung von Bereifungen",
    "sg:phone":"+41 62 772 35 00",
    "sg:postcode":"8280",
    "sg:province":"Thurgau",
    "wof:name":"B + Z, Berchtold P. & Zaugg P.",
    "wof:placetype":"venue"
},
  "geometry": {"coordinates":[8.2008571625,47.2762947083],"type":"Point"}
}