{
  "type": "Feature",
  "properties": {
    "iso:country":"CH",
    "sg:address":"Br\u00fcnigstrasse 87",
    "sg:city":"Sachseln",
    "sg:orig_category":"Hobel U Holzimpr\u00e4gnierwerke",
    "sg:phone":"+41 21 944 53 60",
    "sg:postcode":"6072",
    "sg:province":"Obwalden",
    "wof:name":"Joseph-marie Grau Top-bois",
    "wof:placetype":"venue"
},
  "geometry": {"coordinates":[6.8670420647,46.4554595947],"type":"Point"}
}