{
  "type": "Feature",
  "properties": {
    "iso:country":"CH",
    "sg:address":"Grossmatt",
    "sg:city":"R\u00fcderswil",
    "sg:orig_category":"Elektroinstallation",
    "sg:phone":"+41 34 496 87 55",
    "sg:postcode":"3437",
    "sg:province":"Bern",
    "wof:name":"Allemann Elektro Ag Aeg-service",
    "wof:placetype":"venue"
},
  "geometry": {"coordinates":[7.7301511765,46.9808197021],"type":"Point"}
}