{
  "type": "Feature",
  "properties": {
    "addr:full":"Chemin Du Bouzenet 2 Cheseaux-lausanne Vaud 1033",
    "addr:housenumber":"2",
    "addr:postcode":"1033",
    "addr:street":"Chemin Du Bouzenet",
    "iso:country":"CH",
    "sg:address":"Chemin Du Bouzenet 2",
    "sg:city":"Cheseaux-lausanne",
    "sg:orig_category":"Blumen U Zierpflanzenbau Gem\u00fcsebau",
    "sg:phone":"+41 79 213 71 27",
    "sg:postcode":"1033",
    "sg:province":"Vaud",
    "wof:name":"Pierre H\u00e4mmerli",
    "wof:placetype":"venue"
},
  "geometry": {"coordinates":[6.608288,46.581554],"type":"Point"}
}