{
  "type": "Feature",
  "properties": {
    "iso:country":"CH",
    "sg:address":"Reibestrasse 6",
    "sg:city":"Uster",
    "sg:orig_category":"Fussreflexzonenmassage P\u00e9dicure",
    "sg:phone":"+41 19404700",
    "sg:postcode":"8610",
    "sg:province":"Z\u00fcrich",
    "wof:name":"Rosalia Glesti",
    "wof:placetype":"venue"
},
  "geometry": {"coordinates":[8.7199344635,47.3473815918],"type":"Point"}
}