{
  "type": "Feature",
  "properties": {
    "iso:country":"CH",
    "sg:address":"Dufourstrasse 9a 9400 Rorschach. Postfach",
    "sg:city":"Rorschach",
    "sg:orig_category":"Detailhandel mit elektrischen Haushalts-,Radio U Fernsehger\u00e4ten sowie Musikinstrumenten Grosshandel ",
    "sg:phone":"+41 71 841 95 64",
    "sg:postcode":"9401",
    "sg:province":"St. Gallen",
    "wof:name":"Norbert Kronenberg Haushalt-& Gewerbeger\u00e4te",
    "wof:placetype":"venue"
},
  "geometry": {"coordinates":[9.4873275757,47.4751853943],"type":"Point"}
}