{
  "type": "Feature",
  "properties": {
    "iso:country":"CH",
    "sg:address":"Baarerstrasse 63 6300 Zug. Postfach",
    "sg:city":"Zug",
    "sg:orig_category":"Advokaturb\u00fcros",
    "sg:phone":"+41 71 912 30 50",
    "sg:postcode":"6301",
    "sg:province":"Zug",
    "wof:name":"Joseph B. Koch Advokaturb\u00fcro",
    "wof:placetype":"venue"
},
  "geometry": {"coordinates":[9.0429,47.464626],"type":"Point"}
}