{
  "type": "Feature",
  "properties": {
    "iso:country":"CH",
    "sg:address":"Winterthurerstrasse 625",
    "sg:city":"Z\u00fcrich",
    "sg:orig_category":"Handel mit Motorr\u00e4dern, Teilen U Zubeh\u00f6r Instandhaltung U Reparatur von Motorr\u00e4dern",
    "sg:phone":"+41 13222617",
    "sg:postcode":"8051",
    "sg:province":"Z\u00fcrich",
    "wof:name":"Minder Zweirad-shop Ag",
    "wof:placetype":"venue"
},
  "geometry": {"coordinates":[8.5772771835,47.4051589966],"type":"Point"}
}