{
  "type": "Feature",
  "properties": {
    "iso:country":"CH",
    "sg:address":"Kirchb\u00fchl 10",
    "sg:city":"Burgdorf",
    "sg:orig_category":"Detailhandel mit Uhren U Schmuck Herstellung von Schmuck, Gold U Silberschmiedwaren",
    "sg:phone":"+41 34 423 26 27",
    "sg:postcode":"3400",
    "sg:province":"Bern",
    "wof:name":"Aebi Alain",
    "wof:placetype":"venue"
},
  "geometry": {"coordinates":[7.6261138916,47.0564422607],"type":"Point"}
}