{
  "type": "Feature",
  "properties": {
    "iso:country":"CH",
    "sg:address":"Br\u00e4ndelistalweg 1",
    "sg:city":"Bottmingen",
    "sg:orig_category":"Gesundheitswesen",
    "sg:phone":"+41 61 422 10 77",
    "sg:postcode":"4103",
    "sg:province":"Basel-Landschaft",
    "wof:name":"Outicare Pflege Und Betreuung Zu Hause Gmbh",
    "wof:placetype":"venue"
},
  "geometry": {"coordinates":[7.5822701454,47.5219497681],"type":"Point"}
}