{
  "type": "Feature",
  "properties": {
    "iso:country":"CH",
    "sg:address":"Rietstrasse 1 8103 Unterengstringen. Postfach",
    "sg:city":"Basel",
    "sg:orig_category":"Sonstiges Druckgewerbe Versicherungsagenturen and -broker",
    "sg:phone":"+41 61 273 71 11",
    "sg:postcode":"4051",
    "sg:province":"Basel-Stadt",
    "wof:name":"Scc Swiss Copy Center Gmbh Hard, Software; Beratung, Vermietung, Vetrieb Usw.",
    "wof:placetype":"venue"
},
  "geometry": {"coordinates":[8.4490156174,47.4140586853],"type":"Point"}
}