{
  "type": "Feature",
  "properties": {
    "addr:full":"Bundesplatz 10 6300 Zug. Postfach 4463 Zug Zug 6304",
    "addr:housenumber":"10",
    "addr:postcode":"6300;4463;6304",
    "addr:street":"Bundesplatz;Postfach;Zug",
    "iso:country":"CH",
    "sg:address":"Bundesplatz 10 6300 Zug. Postfach 4463",
    "sg:city":"Zug",
    "sg:orig_category":"Buchverlag Verlagsgewerbe",
    "sg:phone":"+41 41 710 30 46",
    "sg:postcode":"6304",
    "sg:province":"Zug",
    "wof:name":"Edition Pacis Ag",
    "wof:placetype":"venue"
},
  "geometry": {"coordinates":[8.515194,47.171696],"type":"Point"}
}