{
  "type": "Feature",
  "properties": {
    "iso:country":"CH",
    "sg:address":"Rankstrasse 14",
    "sg:city":"Neftenbach",
    "sg:orig_category":"Architektur U Ingenieurb\u00fcros",
    "sg:phone":"+41 52 315 34 15",
    "sg:postcode":"8413",
    "sg:province":"Z\u00fcrich",
    "wof:name":"Wiesmann Hansj\u00f6rg Architekt",
    "wof:placetype":"venue"
},
  "geometry": {"coordinates":[8.657631,47.518372],"type":"Point"}
}