{
  "type": "Feature",
  "properties": {
    "iso:country":"CH",
    "sg:address":"Stalden 306",
    "sg:city":"Biembach",
    "sg:orig_category":"Dachdeckerei Zimmerei, Dachdeckerei, Bauspenglerei U Abdichtung",
    "sg:phone":"+41 34 461 21 62",
    "sg:postcode":"3419",
    "sg:province":"Bern",
    "wof:name":"Grossenbacher Bedachungs Ag",
    "wof:placetype":"venue"
},
  "geometry": {"coordinates":[7.628309,47.002251],"type":"Point"}
}