{
  "type": "Feature",
  "properties": {
    "addr:full":"Grab\u00e4ckerstrasse 27 8957 Spreitenbach. Postfach Bern Bern 3007",
    "addr:housenumber":"27",
    "addr:postcode":"8957 spreitenbach. postfach bern;3007",
    "addr:street":"Grabaeckerstrasse",
    "iso:country":"CH",
    "sg:address":"Grab\u00e4ckerstrasse 27 8957 Spreitenbach. Postfach",
    "sg:city":"Bern",
    "sg:orig_category":"Aktivit\u00e4ten der Generalunternehmen im Baugewerbe Allgemeiner Hoch U Tiefbau",
    "sg:phone":"+41 17517751",
    "sg:postcode":"3007",
    "sg:province":"Bern",
    "wof:name":"Confida Generalunternehmung Ag",
    "wof:placetype":"venue"
},
  "geometry": {"coordinates":[8.37305,47.41951],"type":"Point"}
}