{
  "type": "Feature",
  "properties": {
    "iso:country":"CH",
    "sg:address":"Balmbr\u00fccke 3860 Meiringen. Postfach",
    "sg:city":"Meiringen",
    "sg:orig_category":"Zimmerei, Dachdeckerei, Bauspenglerei U Abdichtung",
    "sg:phone":"+41 79 432 97 80",
    "sg:postcode":"3860",
    "sg:province":"Bern",
    "wof:name":"Michel Installationen Ag",
    "wof:placetype":"venue"
},
  "geometry": {"coordinates":[8.1557178497,46.7290420532],"type":"Point"}
}