{
  "type": "Feature",
  "properties": {
    "iso:country":"CH",
    "sg:address":"Rue Du Petit-ch\u00eane 17",
    "sg:city":"Lausanne",
    "sg:orig_category":"Grosshandel mit sonstigen Konsumg\u00fctern",
    "sg:phone":"+41 71 636 22 47",
    "sg:postcode":"1003",
    "sg:province":"Vaud",
    "wof:name":"Com-tel Cosyflor Gmbh Handels-gesellschaft",
    "wof:placetype":"venue"
},
  "geometry": {"coordinates":[9.1676063538,47.5748329163],"type":"Point"}
}