{
  "type": "Feature",
  "properties": {
    "iso:country":"CH",
    "sg:address":"Blumenweg 3",
    "sg:city":"Adelboden",
    "sg:orig_category":"Wohnheime",
    "sg:phone":"+41 71 777 27 37",
    "sg:postcode":"3715",
    "sg:province":"Bern",
    "wof:name":"Wohngruppe Lebhag Sozialtherap.wohngruppe",
    "wof:placetype":"venue"
},
  "geometry": {"coordinates":[9.567407608,47.3922233582],"type":"Point"}
}