{
  "type": "Feature",
  "properties": {
    "iso:country":"CH",
    "sg:address":"Via Industrie",
    "sg:city":"Bioggio",
    "sg:orig_category":"Unternehmensberatung",
    "sg:phone":"+41 91 611 58 58",
    "sg:postcode":"6934",
    "sg:province":"Ticino",
    "wof:name":"Planzer Transport Ag Trasporti, Magazzinaggi, Incarichi Logistici",
    "wof:placetype":"venue"
},
  "geometry": {"coordinates":[8.9177484512,46.0171966553],"type":"Point"}
}