{
  "type": "Feature",
  "properties": {
    "addr:full":"Ringstrasse Zuzwil St. Gallen 9524",
    "addr:postcode":"9524",
    "addr:street":"Ringstrasse",
    "iso:country":"CH",
    "sg:address":"Ringstrasse",
    "sg:city":"Zuzwil",
    "sg:classifiers":[
        {
            "category":"Building & Trades",
            "subcategory":"Construction",
            "type":"Services"
        }
    ],
    "sg:phone":"+41 71 940 01 14",
    "sg:postcode":"9524",
    "sg:province":"St. Gallen",
    "sg:tags":[
        "saw",
        "circular"
    ],
    "wof:name":"Kasto Maschinenbau Gmbh & Co Kg",
    "wof:placetype":"venue"
},
  "geometry": {"coordinates":[9.105308,47.46904],"type":"Point"}
}