{
  "type": "Feature",
  "properties": {
    "iso:country":"CH",
    "sg:address":"Aubrigstrasse 9",
    "sg:city":"Horgen",
    "sg:orig_category":"Hardwareberatung",
    "sg:postcode":"8810",
    "sg:province":"Z\u00fcrich",
    "wof:name":"Carnevale & Partner (it Technology)",
    "wof:placetype":"venue"
},
  "geometry": {"coordinates":[8.8552646637,47.2523498535],"type":"Point"}
}