{
  "type": "Feature",
  "properties": {
    "iso:country":"CH",
    "sg:address":"Obergerlafingenstrasse 15 4566 Kriegstetten. Postfach",
    "sg:city":"Kriegstetten",
    "sg:orig_category":"Herstellung von Konstruktionsteilen, Fertigbauteilen U Ausbauelementen aus Holz",
    "sg:phone":"+41 32 675 43 25",
    "sg:postcode":"4566",
    "sg:province":"Solothurn",
    "wof:name":"Schreinerei Hess",
    "wof:placetype":"venue"
},
  "geometry": {"coordinates":[7.5970568657,47.1721572876],"type":"Point"}
}