{
  "type": "Feature",
  "properties": {
    "iso:country":"CH",
    "sg:address":"Steini 3862 Innertkirchen. Postfach",
    "sg:city":"Innertkirchen",
    "sg:orig_category":"G\u00fcterbef\u00f6rderung im Strassenverkehr",
    "sg:postcode":"3862",
    "sg:province":"Bern",
    "wof:name":"Hans Bodmer",
    "wof:placetype":"venue"
},
  "geometry": {"coordinates":[8.2325668335,46.7025985718],"type":"Point"}
}