{
  "type": "Feature",
  "properties": {
    "addr:full":"Alter Z\u00fcrichweg 14/a Schlieren Z\u00fcrich 8952",
    "addr:housenumber":"14 / a",
    "addr:postcode":"8952",
    "iso:country":"CH",
    "sg:address":"Alter Z\u00fcrichweg 14/a",
    "sg:city":"Schlieren",
    "sg:orig_category":"Architektur U Ingenieurb\u00fcros",
    "sg:phone":"+41 55 246 19 21",
    "sg:postcode":"8952",
    "sg:province":"Z\u00fcrich",
    "wof:name":"Asp Advanced Solar Products Ag",
    "wof:placetype":"venue"
},
  "geometry": {"coordinates":[8.927907,47.264599],"type":"Point"}
}