{
  "type": "Feature",
  "properties": {
    "iso:country":"CH",
    "sg:address":"8304 Wallisellen. Postfach 441",
    "sg:city":"Wallisellen",
    "sg:orig_category":"Vereine Musik/Blasmusik",
    "sg:phone":"+41 56 631 63 33",
    "sg:postcode":"8304",
    "sg:province":"Z\u00fcrich",
    "wof:name":"Jungmusik Oberwil-lieli",
    "wof:placetype":"venue"
},
  "geometry": {"coordinates":[8.3849716187,47.3332023621],"type":"Point"}
}