{
  "type": "Feature",
  "properties": {
    "iso:country":"CH",
    "sg:address":"Staadstrasse 38 2540 Grenchen. Postfach 576",
    "sg:city":"Grenchen",
    "sg:orig_category":"Grafikateliers, Design Linoleum Detailhandel",
    "sg:phone":"+41 32 653 17 71",
    "sg:postcode":"2540",
    "sg:province":"Solothurn",
    "wof:name":"Atelier Heer Messebau Bodenbel\u00e4ge",
    "wof:placetype":"venue"
},
  "geometry": {"coordinates":[7.4003448486,47.1844978333],"type":"Point"}
}