{
  "type": "Feature",
  "properties": {
    "iso:country":"CH",
    "sg:address":"7448",
    "sg:city":"Juf",
    "sg:orig_category":"Detailhandel mit Geschenkartikeln U Souvenirs Detailhandel mit Zeitungen U Zeitschriften Kioske",
    "sg:phone":"+41 81 667 12 59",
    "sg:postcode":"7448",
    "sg:province":"Graubunden",
    "wof:name":"Markus Menn Kiosk Andenken",
    "wof:placetype":"venue"
},
  "geometry": {"coordinates":[9.5797901154,46.4454193115],"type":"Point"}
}