{
  "type": "Feature",
  "properties": {
    "iso:country":"CH",
    "sg:address":"Via Borgo 1",
    "sg:city":"Ascona",
    "sg:orig_category":"Nationale Postdienste",
    "sg:phone":"+41 91 791 20 21",
    "sg:postcode":"6612",
    "sg:province":"Ticino",
    "wof:name":"La Posta Svizzera",
    "wof:placetype":"venue"
},
  "geometry": {"coordinates":[8.7692670822,46.1566925049],"type":"Point"}
}