{
  "type": "Feature",
  "properties": {
    "iso:country":"CH",
    "sg:address":"Gr\u00fcnhaldenstrasse 1",
    "sg:city":"Sch\u00fcbelbach",
    "sg:orig_category":"Innenausbau Vermietung U Verpachtung von eigenen Immobilien",
    "sg:phone":"+41 33 672 80 85",
    "sg:postcode":"8862",
    "sg:province":"Schwyz",
    "wof:name":"Peter Allenbach",
    "wof:placetype":"venue"
},
  "geometry": {"coordinates":[7.6635007858,46.6079711914],"type":"Point"}
}