{
  "type": "Feature",
  "properties": {
    "iso:country":"CH",
    "sg:address":"Oberdorf 35",
    "sg:city":"Trogen",
    "sg:orig_category":"Detailhandel mit Fleisch U Fleischwaren",
    "sg:phone":"+41 71 344 13 89",
    "sg:postcode":"9043",
    "sg:province":"Appenzell Ausserrhoden",
    "wof:name":"Metzgerei Locher",
    "wof:placetype":"venue"
},
  "geometry": {"coordinates":[9.4638442993,47.407989502],"type":"Point"}
}