{
  "type": "Feature",
  "properties": {
    "iso:country":"CH",
    "sg:address":"Weystrasse 20",
    "sg:city":"Luzern",
    "sg:classifiers":[
        {
            "category":"Wholesale",
            "subcategory":"Drugs",
            "type":"Manufacturing & Wholesale Goods"
        }
    ],
    "sg:phone":"+41 41 368 49 49",
    "sg:postcode":"6006",
    "sg:province":"Luzern",
    "sg:tags":[
        "antibiotic"
    ],
    "wof:name":"Essex Chemie Ag",
    "wof:placetype":"venue"
},
  "geometry": {"coordinates":[8.312469,47.056812],"type":"Point"}
}