{
  "type": "Feature",
  "properties": {
    "iso:country":"CH",
    "sg:address":"Route De Bussigny 21-23",
    "sg:city":"Crissier",
    "sg:orig_category":"Herstellung von sonstigen chemischen Erzeugnissen",
    "sg:phone":"+41 21 634 27 25",
    "sg:postcode":"1023",
    "sg:province":"Vaud",
    "wof:name":"Alunni Sa Atelier De Chromage Dur",
    "wof:placetype":"venue"
},
  "geometry": {"coordinates":[6.5745768547,46.5401039124],"type":"Point"}
}