{
  "type": "Feature",
  "properties": {
    "iso:country":"CH",
    "sg:address":"Unter Der Halde 166",
    "sg:city":"Wallbach",
    "sg:orig_category":"Pensionskassen",
    "sg:postcode":"4323",
    "sg:province":"Aargau",
    "wof:name":"Personalf\u00fcrsorgestiftung Der Novoplast Ag",
    "wof:placetype":"venue"
},
  "geometry": {"coordinates":[7.9057660103,47.5572624207],"type":"Point"}
}