{
  "type": "Feature",
  "properties": {
    "iso:country":"CH",
    "sg:address":"Gemeindeweid 21",
    "sg:city":"Reisiswil",
    "sg:classifiers":[
        {
            "category":"Professional",
            "type":"Services"
        }
    ],
    "sg:phone":"+41 62 965 30 66",
    "sg:postcode":"4919",
    "sg:province":"Bern",
    "sg:tags":[
        "transport"
    ],
    "wof:name":"Meyer Vertriebs Gmbh",
    "wof:placetype":"venue"
},
  "geometry": {"coordinates":[7.8328881264,47.1600723267],"type":"Point"}
}