{
  "type": "Feature",
  "properties": {
    "iso:country":"CH",
    "sg:address":"Jakob-st\u00e4mpfli-strasse 2",
    "sg:city":"Biel/bienne",
    "sg:classifiers":[
        {
            "category":"Government",
            "subcategory":"Post Office",
            "type":"Public Place"
        }
    ],
    "sg:phone":"+41 32 342 02 01",
    "sg:postcode":"2502",
    "sg:province":"Bern",
    "sg:tags":[
        "caf\u00e9s",
        "tea-rooms"
    ],
    "wof:name":"Caf\u00e9 Pino",
    "wof:placetype":"venue"
},
  "geometry": {"coordinates":[7.2570199966,47.1426887512],"type":"Point"}
}