{
  "type": "Feature",
  "properties": {
    "iso:country":"CH",
    "sg:address":"Dorfstrasse 34",
    "sg:city":"Fl\u00fcelen",
    "sg:orig_category":"Non-Classified Establishments",
    "sg:phone":"+41 41 870 12 56",
    "sg:postcode":"6454",
    "sg:province":"Uri",
    "wof:name":"Restaurant Rose",
    "wof:placetype":"venue"
},
  "geometry": {"coordinates":[8.6255636215,46.9013328552],"type":"Point"}
}