{
  "type": "Feature",
  "properties": {
    "iso:country":"CH",
    "sg:address":"Eigenstrasse 1033",
    "sg:city":"Hallau",
    "sg:orig_category":"Rebbau Vermietung U Verpachtung von eigenen Immobilien",
    "sg:phone":"+41 52 681 38 03",
    "sg:postcode":"8215",
    "sg:province":"Schaffhausen",
    "wof:name":"Gasser H. + P. Ag.",
    "wof:placetype":"venue"
},
  "geometry": {"coordinates":[8.4639186859,47.6972045898],"type":"Point"}
}