{
  "type": "Feature",
  "properties": {
    "iso:country":"CH",
    "sg:address":"Riedenweg 2 4208 Nunningen. Postfach",
    "sg:city":"Nunningen",
    "sg:orig_category":"Mechanik Schmieden",
    "sg:phone":"+41 61 791 03 18",
    "sg:postcode":"4208",
    "sg:province":"Solothurn",
    "wof:name":"Gasser Josef",
    "wof:placetype":"venue"
},
  "geometry": {"coordinates":[7.6189742088,47.3946533203],"type":"Point"}
}