{
  "type": "Feature",
  "properties": {
    "iso:country":"CH",
    "sg:address":"Boulevard De P\u00e9rolles 10",
    "sg:city":"Fribourg",
    "sg:classifiers":[
        {
            "category":"Government",
            "subcategory":"Post Office",
            "type":"Public Place"
        }
    ],
    "sg:phone":"+41 26 322 65 25",
    "sg:postcode":"1700",
    "sg:province":"Fribourg",
    "sg:tags":[
        "caf\u00e9s",
        "tea-rooms"
    ],
    "wof:name":"Tea-room Cintra",
    "wof:placetype":"venue"
},
  "geometry": {"coordinates":[7.151966095,46.8016242981],"type":"Point"}
}