{
  "type": "Feature",
  "properties": {
    "iso:country":"CH",
    "sg:address":"3818",
    "sg:city":"Grindelwald",
    "sg:orig_category":"Campingpl\u00e4tze",
    "sg:phone":"+41 33 853 42 27",
    "sg:postcode":"3818",
    "sg:province":"Bern",
    "wof:name":"Campingplatz Eigernordwand",
    "wof:placetype":"venue"
},
  "geometry": {"coordinates":[8.034633,46.624371],"type":"Point"}
}