{
  "type": "Feature",
  "properties": {
    "iso:country":"CH",
    "sg:address":"Gliserallee 63 3902 Glis. Postfach",
    "sg:city":"Glis",
    "sg:orig_category":"Grosshandel mit sonstigen Maschinen U Ausr\u00fcstungen f\u00fcr Industrie, Handel U Schiffahrt Maschinen and ",
    "sg:postcode":"3902",
    "sg:province":"Valais",
    "wof:name":"Resys-reinigungssysteme Gmbh Reinigungsanlagen Und Ger\u00e4te; Import, Vertrieb Usw",
    "wof:placetype":"venue"
},
  "geometry": {"coordinates":[7.9846138954,46.3141784668],"type":"Point"}
}