{
  "type": "Feature",
  "properties": {
    "iso:country":"CH",
    "sg:address":"Belvedere Via 12a",
    "sg:city":"Balerna",
    "sg:orig_category":"RESTAURANTS: TEA-ROOMS",
    "sg:phone":"+41 91 649 75 21",
    "sg:postcode":"6828",
    "sg:province":"Ticino",
    "wof:name":"Romantic Place Sa",
    "wof:placetype":"venue"
},
  "geometry": {"coordinates":[9.0087938309,45.8515510559],"type":"Point"}
}