{
  "type": "Feature",
  "properties": {
    "iso:country":"CH",
    "sg:address":"Eustrasse 2",
    "sg:city":"Menzingen",
    "sg:orig_category":"Handelsvermittlung U Grosshandel",
    "sg:phone":"+41 56 621 18 24",
    "sg:postcode":"6313",
    "sg:province":"Zug",
    "wof:name":"Meier Arbeitssicherheit",
    "wof:placetype":"venue"
},
  "geometry": {"coordinates":[8.2739601135,47.3457107544],"type":"Point"}
}