{
  "type": "Feature",
  "properties": {
    "iso:country":"CH",
    "sg:address":"1720 Corminboeuf. Postfach",
    "sg:city":"Corminboeuf",
    "sg:orig_category":"Sportvereine Ballsport Badminton",
    "sg:phone":"+41 26 411 34 66",
    "sg:postcode":"1720",
    "sg:province":"Fribourg",
    "wof:name":"Badminton-club Corminboeuf",
    "wof:placetype":"venue"
},
  "geometry": {"coordinates":[7.1015400887,46.8071708679],"type":"Point"}
}