{
  "type": "Feature",
  "properties": {
    "iso:country":"CH",
    "sg:address":"Huebwiesenstrasse 14",
    "sg:city":"Geroldswil",
    "sg:orig_category":"Herstellung von medizinischen U chirurgischen Ger\u00e4ten sowie orthop\u00e4dischen Vorrichtungen",
    "sg:postcode":"8954",
    "sg:province":"Z\u00fcrich",
    "wof:name":"Dentaltechnik Keramik-labor, Milisavljevic-schmid Sonja",
    "wof:placetype":"venue"
},
  "geometry": {"coordinates":[8.4129581451,47.4204750061],"type":"Point"}
}