{
  "type": "Feature",
  "properties": {
    "iso:country":"CH",
    "sg:address":"Poststrasse 2/4 3400 Burgdorf. Postfach",
    "sg:city":"Burgdorf",
    "sg:orig_category":"Instandhaltung U Reparatur von Automobilen",
    "sg:postcode":"3402",
    "sg:province":"Bern",
    "wof:name":"Bahnhof Garage Ag Burgdorf",
    "wof:placetype":"venue"
},
  "geometry": {"coordinates":[7.6253118515,47.0601997375],"type":"Point"}
}