{
  "type": "Feature",
  "properties": {
    "iso:country":"CH",
    "sg:address":"Avenue Juste-olivier 7",
    "sg:city":"Lausanne",
    "sg:orig_category":"Detailhandel mit Fleisch U Fleischwaren",
    "sg:phone":"+41 34 431 15 75",
    "sg:postcode":"1006",
    "sg:province":"Vaud",
    "wof:name":"Sicaro Fleischhandels Ag",
    "wof:placetype":"venue"
},
  "geometry": {"coordinates":[7.6671600342,46.9350700378],"type":"Point"}
}