{
  "type": "Feature",
  "properties": {
    "iso:country":"CH",
    "sg:address":"Carr\u00e0 Dei Nasi 8",
    "sg:city":"Ascona",
    "sg:orig_category":"Kunsthandel",
    "sg:phone":"+41 71 223 50 58",
    "sg:postcode":"6612",
    "sg:province":"Ticino",
    "wof:name":"Maria Palatini Galerie Zum Strauss",
    "wof:placetype":"venue"
},
  "geometry": {"coordinates":[9.3751831055,47.4227142334],"type":"Point"}
}