{
  "type": "Feature",
  "properties": {
    "iso:country":"CH",
    "sg:address":"Grand-rue",
    "sg:city":"Vernayaz",
    "sg:orig_category":"RESTAURANTS: TEA-ROOMS",
    "sg:postcode":"1904",
    "sg:province":"Valais",
    "wof:name":"Chappuis Genevi\u00e8ve",
    "wof:placetype":"venue"
},
  "geometry": {"coordinates":[7.038626194,46.1372070312],"type":"Point"}
}