{
  "type": "Feature",
  "properties": {
    "iso:country":"CH",
    "sg:address":"Br\u00fcelgasse 7",
    "sg:city":"Br\u00fctten",
    "sg:classifiers":[
        {
            "category":"Education",
            "subcategory":"Library",
            "type":"Public Place"
        }
    ],
    "sg:phone":"+41 61 711 12 68",
    "sg:postcode":"8311",
    "sg:province":"Z\u00fcrich",
    "sg:tags":[
        "u",
        "bibliotheken",
        "archive"
    ],
    "wof:name":"Gemeindebibliothek Egerten-pavillon",
    "wof:placetype":"venue"
},
  "geometry": {"coordinates":[7.591723,47.496693],"type":"Point"}
}