{
  "type": "Feature",
  "properties": {
    "iso:country":"CH",
    "sg:address":"Tobel 9302 Kronb\u00fchl. Postfach",
    "sg:city":"Kronb\u00fchl",
    "sg:orig_category":"Kalb U Schweine-M\u00e4sterei U Zucht",
    "sg:phone":"+41 71 477 10 22",
    "sg:postcode":"9302",
    "wof:name":"Wirth Fridolin",
    "wof:placetype":"venue"
},
  "geometry": {"coordinates":[9.3818778992,47.5442619324],"type":"Point"}
}