{
  "type": "Feature",
  "properties": {
    "iso:country":"CH",
    "sg:address":"Bahnhofstrassse 21",
    "sg:city":"Toffen",
    "sg:orig_category":"Erschliessung von Grundst\u00fccken",
    "sg:postcode":"3125",
    "sg:province":"Bern",
    "wof:name":"Liberale Baugen.toffen",
    "wof:placetype":"venue"
},
  "geometry": {"coordinates":[7.4910049438,46.8586387634],"type":"Point"}
}