{
  "type": "Feature",
  "properties": {
    "iso:country":"CH",
    "sg:address":"Kirchgasse 1",
    "sg:city":"Russikon",
    "sg:orig_category":"Werbung",
    "sg:phone":"+41 52 345 02 50",
    "sg:postcode":"8332",
    "sg:province":"Z\u00fcrich",
    "wof:name":"Ritschard Vasalli Angelika Tpc The Professional Crew",
    "wof:placetype":"venue"
},
  "geometry": {"coordinates":[8.7171001434,47.4365730286],"type":"Point"}
}