{
  "type": "Feature",
  "properties": {
    "iso:country":"CH",
    "sg:address":"Ankerstrasse 3",
    "sg:city":"Z\u00fcrich",
    "sg:orig_category":"Grosshandel mit sonstigen Konsumg\u00fctern",
    "sg:phone":"+41 12411400",
    "sg:postcode":"8004",
    "sg:province":"Z\u00fcrich",
    "wof:name":"Rose-marie Hofmann Textilagentur",
    "wof:placetype":"venue"
},
  "geometry": {"coordinates":[8.523774147,47.3724708557],"type":"Point"}
}