{
  "type": "Feature",
  "properties": {
    "iso:country":"CH",
    "sg:address":"Via Sporz 19a",
    "sg:city":"Lenzerheide",
    "sg:classifiers":[
        {
            "category":"Banks & Credit Unions",
            "subcategory":"Bank",
            "type":"Services"
        }
    ],
    "sg:phone":"+41 4181341950",
    "sg:postcode":"7078",
    "sg:province":"Graubunden",
    "wof:name":"Raiffeisenbank, Lenzerheide-valbella",
    "wof:placetype":"venue"
},
  "geometry": {"coordinates":[9.553463,46.728096],"type":"Point"}
}