{
  "type": "Feature",
  "properties": {
    "iso:country":"CH",
    "sg:address":"Route De Courgenay 37",
    "sg:city":"Porrentruy",
    "sg:orig_category":"Autogaragen Instandhaltung U Reparatur von Automobilen",
    "sg:phone":"+41 32 466 19 13",
    "sg:postcode":"2900",
    "sg:province":"Jura",
    "wof:name":"Garage Michel Philippe Garage. V\u00e9hicules; R\u00e9paration, Vente Etc",
    "wof:placetype":"venue"
},
  "geometry": {"coordinates":[7.083644,47.416027],"type":"Point"}
}