{
  "type": "Feature",
  "properties": {
    "iso:country":"CH",
    "sg:address":"Biglenstrasse 712",
    "sg:city":"Enggistein",
    "sg:orig_category":"Non-Classified Establishments",
    "sg:postcode":"3077",
    "sg:province":"Bern",
    "wof:name":"Ebi Trocknungs Ag",
    "wof:placetype":"venue"
},
  "geometry": {"coordinates":[7.5988698006,46.9318733215],"type":"Point"}
}