{
  "type": "Feature",
  "properties": {
    "iso:country":"CH",
    "sg:address":"Rue De La Boverie 26",
    "sg:city":"Payerne",
    "sg:orig_category":"Grosshandel mit Tabakwaren",
    "sg:phone":"+41 26 322 90 68",
    "sg:postcode":"1530",
    "sg:province":"Vaud",
    "wof:name":"Sota Soci\u00e9t\u00e9 Coop\u00e9rative Pour L'achat Du Tabac Indig\u00e8ne",
    "wof:placetype":"venue"
},
  "geometry": {"coordinates":[6.9345889091,46.8173484802],"type":"Point"}
}