{
  "type": "Feature",
  "properties": {
    "iso:country":"CH",
    "sg:address":"Rue De Lausanne 76",
    "sg:city":"Gen\u00e8ve",
    "sg:orig_category":"Grosshandel mit Foto U Kinoger\u00e4ten, feinmechanischen U optischen Erzeugnissen",
    "sg:phone":"+41 19136111",
    "sg:postcode":"1202",
    "sg:province":"Gen\u00e8ve",
    "wof:name":"Nikon Ag",
    "wof:placetype":"venue"
},
  "geometry": {"coordinates":[8.5810031891,47.3152961731],"type":"Point"}
}