{
  "type": "Feature",
  "properties": {
    "iso:country":"CH",
    "sg:address":"Rue Centrale 57",
    "sg:city":"Avenches",
    "sg:orig_category":"Detailhandel mit Blumen U Pflanzen",
    "sg:phone":"+41 26 675 27 38",
    "sg:postcode":"1580",
    "sg:province":"Vaud",
    "wof:name":"Hans Rudolf Moser Boutique De Fleurs",
    "wof:placetype":"venue"
},
  "geometry": {"coordinates":[7.039878,46.879372],"type":"Point"}
}