{
  "type": "Feature",
  "properties": {
    "iso:country":"CH",
    "sg:address":"Enzenb\u00fchlstrasse 72",
    "sg:city":"Z\u00fcrich",
    "sg:orig_category":"Vereine Gesang",
    "sg:phone":"+41 19503118",
    "sg:postcode":"8008",
    "sg:province":"Z\u00fcrich",
    "wof:name":"Kastellchor Pf\u00e4ffikon",
    "wof:placetype":"venue"
},
  "geometry": {"coordinates":[8.7945671082,47.3645629883],"type":"Point"}
}