{
  "type": "Feature",
  "properties": {
    "iso:country":"CH",
    "sg:address":"Hauptstrasse 410",
    "sg:city":"Zuzgen",
    "sg:orig_category":"Erbringung von Dienstleistungen f\u00fcr Unternehmen",
    "sg:phone":"+41 61 871 06 86",
    "sg:postcode":"4315",
    "sg:province":"Aargau",
    "wof:name":"Architekturmodellbau Ludger J\u00fctte",
    "wof:placetype":"venue"
},
  "geometry": {"coordinates":[7.8988351822,47.5255241394],"type":"Point"}
}