{
  "type": "Feature",
  "properties": {
    "iso:country":"CH",
    "sg:address":"Lettenstrasse 7 Rotkreuz 6343 Risch. Postfach",
    "sg:city":"Rotkreuz",
    "sg:orig_category":"Handels-H\u00e4user U Gesellschaften",
    "sg:postcode":"6343",
    "sg:province":"Zug",
    "wof:name":"Atoz Gmbh",
    "wof:placetype":"venue"
},
  "geometry": {"coordinates":[8.4660310745,47.1341400146],"type":"Point"}
}