{
  "type": "Feature",
  "properties": {
    "iso:country":"CH",
    "sg:address":"Avenue De Cour 45",
    "sg:city":"Lausanne",
    "sg:orig_category":"Maturit\u00e4tsschulen, Lehrerseminarien",
    "sg:phone":"+41 32 717 87 00",
    "sg:postcode":"1007",
    "sg:province":"Vaud",
    "wof:name":"Ecole Sup\u00e9rieure Numa-droz",
    "wof:placetype":"venue"
},
  "geometry": {"coordinates":[6.9312200546,46.9902572632],"type":"Point"}
}