{
  "type": "Feature",
  "properties": {
    "iso:country":"CH",
    "sg:address":"Rosenweg 3",
    "sg:city":"Kerzers",
    "sg:orig_category":"Maler U Glasergewerbe Stukkateurgewerbe, Gipserei U Verputzerei",
    "sg:phone":"+41 31 755 52 32",
    "sg:postcode":"3210",
    "sg:province":"Fribourg",
    "wof:name":"Maler Richard Ag",
    "wof:placetype":"venue"
},
  "geometry": {"coordinates":[7.1944088936,46.9770545959],"type":"Point"}
}