{
  "type": "Feature",
  "properties": {
    "iso:country":"CH",
    "sg:address":"Ile Quai De L' 15 1204 Gen\u00e8ve. Postfach",
    "sg:city":"Gen\u00e8ve",
    "sg:orig_category":"Non-Classified Establishments",
    "sg:postcode":"1204",
    "sg:province":"Gen\u00e8ve",
    "wof:name":"Soci\u00e9t\u00e9 Immobili\u00e8re La Fougeraie B",
    "wof:placetype":"venue"
},
  "geometry": {"coordinates":[6.1515002251,46.2049484253],"type":"Point"}
}