{
  "type": "Feature",
  "properties": {
    "iso:country":"CH",
    "sg:address":"Herrenberg 9",
    "sg:city":"Ermensee",
    "sg:orig_category":"Gartenbau",
    "sg:phone":"+41 41 917 19 42",
    "sg:postcode":"6294",
    "sg:province":"Luzern",
    "wof:name":"S\u00fcess A. Gartenbau Ag Gartenbau & Gartenpflege",
    "wof:placetype":"venue"
},
  "geometry": {"coordinates":[8.2405357361,47.2225799561],"type":"Point"}
}