{
  "type": "Feature",
  "properties": {
    "iso:country":"CH",
    "sg:address":"Lindenweg 50",
    "sg:city":"Wabern",
    "sg:classifiers":[
        {
            "category":"Education",
            "subcategory":"Library",
            "type":"Public Place"
        }
    ],
    "sg:postcode":"3084",
    "sg:province":"Bern",
    "sg:tags":[
        "u",
        "bibliotheken",
        "archive"
    ],
    "wof:name":"Amt F\u00fcr Mass & Gewicht Bibliothek",
    "wof:placetype":"venue"
},
  "geometry": {"coordinates":[7.45084,46.929035],"type":"Point"}
}