{
  "type": "Feature",
  "properties": {
    "iso:country":"CH",
    "sg:address":"La Corne",
    "sg:city":"Dor\u00e9naz",
    "sg:orig_category":"Maurerarbeiten",
    "sg:phone":"+41 79 214 22 27",
    "sg:postcode":"1905",
    "sg:province":"Valais",
    "wof:name":"Mario Esteves Ma\u00e7onnerie",
    "wof:placetype":"venue"
},
  "geometry": {"coordinates":[7.0441660881,46.1511993408],"type":"Point"}
}