{
  "type": "Feature",
  "properties": {
    "iso:country":"CH",
    "sg:address":"Vers-chez-savary",
    "sg:city":"Vers-chez-perrin",
    "sg:orig_category":"Bauschreinerei Herstellung von Konstruktionsteilen, Fertigbauteilen U Ausbauelementen aus Holz",
    "sg:phone":"+41 26 660 33 93",
    "sg:postcode":"1551",
    "sg:province":"Vaud",
    "wof:name":"Jean-pierre Vonnez Eb\u00e9nisterie",
    "wof:placetype":"venue"
},
  "geometry": {"coordinates":[6.941987,46.797447],"type":"Point"}
}