{
  "type": "Feature",
  "properties": {
    "iso:country":"CH",
    "sg:address":"B\u00fcrgistrasse 15",
    "sg:city":"Lichtensteig",
    "sg:orig_category":"Zimmerei, Dachdeckerei, Bauspenglerei U Abdichtung",
    "sg:phone":"+41 71 988 16 70",
    "sg:postcode":"9620",
    "sg:province":"St. Gallen",
    "wof:name":"Bischof Holzbau Ag",
    "wof:placetype":"venue"
},
  "geometry": {"coordinates":[9.0917282104,47.3243484497],"type":"Point"}
}