{
  "type": "Feature",
  "properties": {
    "iso:country":"CH",
    "sg:address":"Gentenwisstrasse 4",
    "sg:city":"Russikon",
    "sg:orig_category":"Unternehmensberatung",
    "sg:phone":"+41 19543976",
    "sg:postcode":"8332",
    "sg:province":"Z\u00fcrich",
    "wof:name":"Urs Marbacher Marbacher Engineering",
    "wof:placetype":"venue"
},
  "geometry": {"coordinates":[8.7808322906,47.3862571716],"type":"Point"}
}