{
  "type": "Feature",
  "properties": {
    "addr:full":"Via Stazione 32 6828 Balerna. Postfach Caselle Postale 46 Balerna Ticino 6828",
    "addr:housenumber":"32",
    "addr:postcode":"6828 balerna. postfach caselle postale 46;6828",
    "addr:street":"Via Stazione",
    "iso:country":"CH",
    "sg:address":"Via Stazione 32 6828 Balerna. Postfach Caselle Postale 46",
    "sg:city":"Balerna",
    "sg:orig_category":"Detailhandel mit Brennstoffen U Heizmaterial Herstellung von Tanks U Sammelbeh\u00e4ltern aus Metall",
    "sg:phone":"+41 71 244 77 55",
    "sg:postcode":"6828",
    "sg:province":"Ticino",
    "wof:name":"Gottlieb Fr\u00fch",
    "wof:placetype":"venue"
},
  "geometry": {"coordinates":[9.393655,47.440735],"type":"Point"}
}