{
  "type": "Feature",
  "properties": {
    "iso:country":"CH",
    "sg:address":"Dorfstrasse 2",
    "sg:city":"Russikon",
    "sg:orig_category":"Sonstiger Fachdetailhandel mit Nahrungsmitteln, Getr\u00e4nken U Tabak in Verkaufsr\u00e4umen",
    "sg:phone":"+41 19542875",
    "sg:postcode":"8332",
    "sg:province":"Z\u00fcrich",
    "wof:name":"K\u00e4se-import, Roberto Bergamin",
    "wof:placetype":"venue"
},
  "geometry": {"coordinates":[8.7762537003,47.3941116333],"type":"Point"}
}