{
  "type": "Feature",
  "properties": {
    "iso:country":"CH",
    "sg:address":"1675",
    "sg:city":"Vauderens",
    "sg:orig_category":"Gartenbau Landschaftsplanungsb\u00fcros U Gartenarchitekturb\u00fcros",
    "sg:phone":"+41 21 691 68 52",
    "sg:postcode":"1675",
    "sg:province":"Fribourg",
    "wof:name":"D. Burkhard Sa Cr\u00e9ation De Parcs & Jardins",
    "wof:placetype":"venue"
},
  "geometry": {"coordinates":[6.5581297874,46.5123977661],"type":"Point"}
}