{
  "type": "Feature",
  "properties": {
    "addr:full":"Staldenhof 2 Littau Luzern 6014",
    "addr:housenumber":"2",
    "addr:postcode":"6014",
    "addr:street":"Staldenhof",
    "iso:country":"CH",
    "sg:address":"Staldenhof 2",
    "sg:city":"Littau",
    "sg:classifiers":[
        {
            "category":"Building & Trades",
            "subcategory":"Construction",
            "type":"Services"
        }
    ],
    "sg:phone":"+41 41 259 00 50",
    "sg:postcode":"6014",
    "sg:province":"Luzern",
    "sg:tags":[
        "installation",
        "air-conditioning",
        "system"
    ],
    "wof:name":"Air Rep Ag",
    "wof:placetype":"venue"
},
  "geometry": {"coordinates":[8.269304,47.064903],"type":"Point"}
}