{
  "type": "Feature",
  "properties": {
    "iso:country":"CH",
    "sg:address":"Hofstrasse 1a",
    "sg:city":"Zug",
    "sg:orig_category":"Sonstiger Grosshandel",
    "sg:phone":"+41 18442558",
    "sg:postcode":"6300",
    "sg:province":"Zug",
    "wof:name":"Sigrist Guido",
    "wof:placetype":"venue"
},
  "geometry": {"coordinates":[8.4410219193,47.4595108032],"type":"Point"}
}