{
  "type": "Feature",
  "properties": {
    "iso:country":"CH",
    "sg:address":"1983",
    "sg:city":"Evol\u00e8ne",
    "sg:orig_category":"Sessellifte and Skilifte",
    "sg:phone":"+41 27 283 10 80",
    "sg:postcode":"1983",
    "sg:province":"Valais",
    "wof:name":"T\u00e9l\u00e9-evol\u00e8ne Sa Remont\u00e9es M\u00e9caniques",
    "wof:placetype":"venue"
},
  "geometry": {"coordinates":[7.4961590767,46.1144752502],"type":"Point"}
}