{
  "type": "Feature",
  "properties": {
    "iso:country":"CH",
    "sg:address":"Ch\u00e9salles Route De 18",
    "sg:city":"Marly",
    "sg:orig_category":"Grosshandel mit Obst U Gem\u00fcse",
    "sg:phone":"+41 26 436 21 35",
    "sg:postcode":"1723",
    "sg:province":"Fribourg",
    "wof:name":"Berger Sa Sp\u00e9cialit\u00e9s Fra\u00eeches Et Surgel\u00e9es",
    "wof:placetype":"venue"
},
  "geometry": {"coordinates":[7.1579470634,46.7725105286],"type":"Point"}
}