{
  "type": "Feature",
  "properties": {
    "iso:country":"CH",
    "sg:address":"Route Du Signal 40",
    "sg:city":"Lausanne",
    "sg:orig_category":"Diskotheken, Dancings, Night Clubs",
    "sg:phone":"+41 33 744 24 51",
    "sg:postcode":"1018",
    "sg:province":"Vaud",
    "wof:name":"Restaurant Chesery & Pianobar",
    "wof:placetype":"venue"
},
  "geometry": {"coordinates":[7.2964911461,46.467414856],"type":"Point"}
}