{
  "type": "Feature",
  "properties": {
    "iso:country":"CH",
    "sg:address":"Talstr. 42",
    "sg:city":"Etzgen",
    "sg:orig_category":"RESTAURANTS: TEA-ROOMS",
    "sg:phone":"+41 62 875 11 06",
    "sg:postcode":"5275",
    "sg:province":"Aargau",
    "wof:name":"Sonja St\u00e4ger",
    "wof:placetype":"venue"
},
  "geometry": {"coordinates":[8.1109628677,47.5694351196],"type":"Point"}
}