{
  "type": "Feature",
  "properties": {
    "iso:country":"CH",
    "sg:address":"8201",
    "sg:city":"Schaffhausen",
    "sg:orig_category":"Wirtschafts- and Arbeitgeberverb\u00e4nde",
    "sg:postcode":"8201",
    "sg:province":"Schaffhausen",
    "wof:name":"Schweizerischer Wirteverband Sektion Schaffhausen",
    "wof:placetype":"venue"
},
  "geometry": {"coordinates":[8.632229805,47.6974716187],"type":"Point"}
}