{
  "type": "Feature",
  "properties": {
    "iso:country":"CH",
    "sg:address":"Nauengasse 14",
    "sg:city":"Rorbas",
    "sg:orig_category":"Grosshandel mit B\u00fcromaschinen Grosshandel mit Datenverarbeitungsger\u00e4ten",
    "sg:phone":"+41 22 827 15 70",
    "sg:postcode":"8427",
    "sg:province":"Z\u00fcrich",
    "wof:name":"Icon Informatique & Conseils Fischer & Girardin",
    "wof:placetype":"venue"
},
  "geometry": {"coordinates":[6.12774086,46.1870918274],"type":"Point"}
}