{
  "type": "Feature",
  "properties": {
    "iso:country":"CH",
    "sg:address":"3250",
    "sg:city":"Lyss",
    "sg:orig_category":"Primarschulen",
    "sg:phone":"+41 32 384 15 15",
    "sg:postcode":"3250",
    "sg:province":"Bern",
    "wof:name":"Primarschule Kirchenfeld",
    "wof:placetype":"venue"
},
  "geometry": {"coordinates":[7.3079900742,47.0719146729],"type":"Point"}
}