{
  "type": "Feature",
  "properties": {
    "iso:country":"CH",
    "sg:address":"Z\u00fcrcherstrasse 7",
    "sg:city":"Fehraltorf",
    "sg:orig_category":"Bauschreinerei",
    "sg:phone":"+41 19540154",
    "sg:postcode":"8320",
    "sg:province":"Z\u00fcrich",
    "wof:name":"Marcel Gerzner Schreinerei",
    "wof:placetype":"venue"
},
  "geometry": {"coordinates":[8.74677,47.389709],"type":"Point"}
}