{
  "type": "Feature",
  "properties": {
    "iso:country":"CH",
    "sg:address":"Schwarzackerstrasse 12 8304 Wallisellen. Postfach",
    "sg:city":"Wallisellen",
    "sg:classifiers":[
        {
            "category":"Insurance",
            "subcategory":"Insurance Agent",
            "type":"Services"
        }
    ],
    "sg:phone":"+41 18302573",
    "sg:postcode":"8304",
    "sg:province":"Z\u00fcrich",
    "sg:tags":[
        "versicherungsagenturen",
        "-broker"
    ],
    "wof:name":"Carlo Sbampato Versicherungsagentur",
    "wof:placetype":"venue"
},
  "geometry": {"coordinates":[8.5897026062,47.4135437012],"type":"Point"}
}