{
  "type": "Feature",
  "properties": {
    "iso:country":"CH",
    "sg:address":"Schwerrihof",
    "sg:city":"Grosswangen",
    "sg:orig_category":"Sportvereine Turnen",
    "sg:phone":"+41 71 891 23 08",
    "sg:postcode":"6022",
    "sg:province":"Luzern",
    "wof:name":"Turnverein Stv Grub",
    "wof:placetype":"venue"
},
  "geometry": {"coordinates":[9.5031204224,47.4540405273],"type":"Point"}
}