{
  "type": "Feature",
  "properties": {
    "iso:country":"CH",
    "sg:address":"Anglikerstrasse 87 5612 Villmergen. Postfach",
    "sg:city":"Villmergen",
    "sg:orig_category":"RESTAURANTS: TEA-ROOMS",
    "sg:postcode":"5612",
    "sg:province":"Aargau",
    "wof:name":"Rohr's Imbiss-bude",
    "wof:placetype":"venue"
},
  "geometry": {"coordinates":[8.2540464401,47.3534889221],"type":"Point"}
}