{
  "type": "Feature",
  "properties": {
    "addr:full":"Steinhaldenstrasse 22 Geroldswil Z\u00fcrich 8954",
    "addr:housenumber":"22",
    "addr:postcode":"8954",
    "addr:street":"Steinhaldenstrasse",
    "iso:country":"CH",
    "sg:address":"Steinhaldenstrasse 22",
    "sg:city":"Geroldswil",
    "sg:classifiers":[
        {
            "category":"Museum",
            "subcategory":"Art Museum",
            "type":"Entertainment"
        }
    ],
    "sg:phone":"+41 17478540",
    "sg:postcode":"8954",
    "sg:province":"Z\u00fcrich",
    "sg:tags":[
        "artwork"
    ],
    "wof:name":"Colorlith Ag",
    "wof:placetype":"venue"
},
  "geometry": {"coordinates":[8.4116,47.419609],"type":"Point"}
}