{
  "type": "Feature",
  "properties": {
    "iso:country":"CH",
    "sg:address":"Rue De La Pierre-\u00e0-mazel 53",
    "sg:city":"Neuenburg",
    "sg:orig_category":"RESTAURANTS: TEA-ROOMS",
    "sg:phone":"+41 32 724 61 33",
    "sg:postcode":"2000",
    "sg:province":"Neuch\u00e2tel",
    "wof:name":"Caf\u00e9-restaurant Du Littoral, Fourcade Vincent",
    "wof:placetype":"venue"
},
  "geometry": {"coordinates":[6.9490818977,46.9970321655],"type":"Point"}
}