{
  "type": "Feature",
  "properties": {
    "iso:country":"CH",
    "sg:address":"Aeschenvorstadt 16",
    "sg:city":"Basel",
    "sg:classifiers":[
        {
            "category":"Banks & Credit Unions",
            "subcategory":"Bank",
            "type":"Services"
        }
    ],
    "sg:phone":"+41 61 286 66 66",
    "sg:postcode":"4002",
    "sg:province":"Basel-Stadt",
    "wof:name":"Les Fils Dreyfus & Cie Sa",
    "wof:placetype":"venue"
},
  "geometry": {"coordinates":[7.592475,47.553123],"type":"Point"}
}