{
  "type": "Feature",
  "properties": {
    "iso:country":"CH",
    "sg:address":"Rainstrasse 2 8143 Stallikon. Postfach",
    "sg:city":"Stallikon",
    "sg:orig_category":"Druck ohne Zeitungsdruck Offsetdruck",
    "sg:phone":"+41 17001803",
    "sg:postcode":"8143",
    "sg:province":"Z\u00fcrich",
    "wof:name":"Stegmann Rudolf, Buch, Offset, Pr\u00e4gedruck Und Graphik Ag",
    "wof:placetype":"venue"
},
  "geometry": {"coordinates":[8.4772205353,47.3480987549],"type":"Point"}
}