{
  "type": "Feature",
  "properties": {
    "iso:country":"CH",
    "sg:address":"R\u00f6tistrasse 2a",
    "sg:city":"Feldbrunnen",
    "sg:orig_category":"Architektur U Ingenieurb\u00fcros",
    "sg:phone":"+41 32 622 70 53",
    "sg:postcode":"4532",
    "sg:province":"Solothurn",
    "wof:name":"Smk Bauingenieur Und Planungsfirma Studer R.",
    "wof:placetype":"venue"
},
  "geometry": {"coordinates":[7.555692,47.220322],"type":"Point"}
}