{
  "type": "Feature",
  "properties": {
    "iso:country":"CH",
    "sg:address":"Neustadt 1",
    "sg:city":"Schaffhausen",
    "sg:orig_category":"Unternehmensberatung",
    "sg:phone":"+41 52 624 42 68",
    "sg:postcode":"8200",
    "sg:province":"Schaffhausen",
    "wof:name":"Hans Kaufmann Der Gastroberater",
    "wof:placetype":"venue"
},
  "geometry": {"coordinates":[8.6320743561,47.6938819885],"type":"Point"}
}