{
  "type": "Feature",
  "properties": {
    "addr:full":"Gartenstrasse 19 Zurich 8039",
    "addr:housenumber":"19",
    "addr:postcode":"8039",
    "addr:street":"Gartenstrasse;Zurich",
    "iso:country":"CH",
    "sg:address":"Gartenstrasse 19",
    "sg:city":"Zurich",
    "sg:classifiers":[
        {
            "category":"Banks & Credit Unions",
            "subcategory":"Financial Services",
            "type":"Services"
        }
    ],
    "sg:phone":"+41 4112026333",
    "sg:postcode":"8039",
    "sg:tags":[
        "banking",
        "finance",
        "insurance"
    ],
    "wof:name":"Berenberg Finance Ltd",
    "wof:placetype":"venue"
},
  "geometry": {"coordinates":[8.53345,47.368179],"type":"Point"}
}