{
  "type": "Feature",
  "properties": {
    "iso:country":"CH",
    "sg:address":"Bernstrasse 114",
    "sg:city":"Rudolfstetten",
    "sg:orig_category":"Sanit\u00e4r, Heizungs U L\u00fcftungsinstallation Sanit\u00e4rinstallation",
    "sg:postcode":"8964",
    "sg:province":"Aargau",
    "wof:name":"D\u00e4hler Samuel.",
    "wof:placetype":"venue"
},
  "geometry": {"coordinates":[7.0426301956,47.0200386047],"type":"Point"}
}