{
  "type": "Feature",
  "properties": {
    "iso:country":"CH",
    "sg:address":"H\u00e4ftlibach",
    "sg:city":"M\u00f6rschwil",
    "sg:orig_category":"Vorschulen, Kinderg\u00e4rten",
    "sg:phone":"+41 71 866 18 58",
    "sg:postcode":"9402",
    "sg:province":"St. Gallen",
    "wof:name":"Kindergarten",
    "wof:placetype":"venue"
},
  "geometry": {"coordinates":[9.4230098724,47.467880249],"type":"Point"}
}