{
  "type": "Feature",
  "properties": {
    "addr:full":"Avenue De La Gare 66 Conthey Valais 1964",
    "addr:housenumber":"66",
    "addr:postcode":"1964",
    "addr:street":"Avenue De La Gare",
    "iso:country":"CH",
    "sg:address":"Avenue De La Gare 66",
    "sg:city":"Conthey",
    "sg:orig_category":"Ausbaugewerbe",
    "sg:phone":"+41 27 346 19 44",
    "sg:postcode":"1964",
    "sg:province":"Valais",
    "wof:name":"Charles Rapillard Entreprise De Chemin\u00e9es",
    "wof:placetype":"venue"
},
  "geometry": {"coordinates":[7.303414,46.229446],"type":"Point"}
}