{
  "type": "Feature",
  "properties": {
    "iso:country":"CH",
    "sg:address":"Sullens",
    "sg:city":"Sullens",
    "sg:classifiers":[
        {
            "category":"Banks & Credit Unions",
            "subcategory":"Bank",
            "type":"Services"
        }
    ],
    "sg:postcode":"1036",
    "sg:province":"Vaud",
    "wof:name":"Caisse D'\u00c9pargne Et De Cr\u00e9dit",
    "wof:placetype":"venue"
},
  "geometry": {"coordinates":[6.63274,46.52084],"type":"Point"}
}