{
  "type": "Feature",
  "properties": {
    "iso:country":"CH",
    "sg:address":"Hubelweg 7",
    "sg:city":"Steffisburg",
    "sg:orig_category":"Sonstige pers\u00f6nliche Dienstleistungen",
    "sg:phone":"+41 33 438 80 05",
    "sg:postcode":"3612",
    "sg:province":"Bern",
    "wof:name":"Senox Ag",
    "wof:placetype":"venue"
},
  "geometry": {"coordinates":[7.6343970299,46.7833023071],"type":"Point"}
}