{
  "type": "Feature",
  "properties": {
    "iso:country":"CH",
    "sg:address":"K\u00e4mmoosstrasse 4",
    "sg:city":"Bubikon",
    "sg:orig_category":"Finanzierungsinstitutionen",
    "sg:phone":"+41 81 254 38 65",
    "sg:postcode":"8608",
    "sg:province":"Z\u00fcrich",
    "wof:name":"Honegger Jacques",
    "wof:placetype":"venue"
},
  "geometry": {"coordinates":[8.8196773529,47.2678184509],"type":"Point"}
}