{
  "type": "Feature",
  "properties": {
    "addr:full":"Rue De L'orangerie 2 Neuch\u00e2tel Neuch\u00e2tel 2000",
    "addr:housenumber":"2",
    "addr:postcode":"2000",
    "addr:street":"Rue De L'Orangerie",
    "iso:country":"CH",
    "sg:address":"Rue De L'orangerie 2",
    "sg:city":"Neuch\u00e2tel",
    "sg:orig_category":"Detailhandel mit Brot, Back U S\u00fcsswaren",
    "sg:phone":"+41 32 725 23 44",
    "sg:postcode":"2000",
    "sg:province":"Neuch\u00e2tel",
    "wof:name":"Boulangerie De L'orangerie, Lemoine Michel",
    "wof:placetype":"venue"
},
  "geometry": {"coordinates":[6.935063,46.992779],"type":"Point"}
}