{
  "type": "Feature",
  "properties": {
    "iso:country":"CH",
    "sg:address":"3917",
    "sg:city":"Kippel",
    "sg:classifiers":[
        {
            "category":"Social Services",
            "subcategory":"Retirement Home",
            "type":"Services"
        }
    ],
    "sg:phone":"+41 27 939 19 29",
    "sg:postcode":"3917",
    "sg:province":"Valais",
    "sg:tags":[
        "pflegeheime",
        "u",
        "alters"
    ],
    "wof:name":"Altersheim St.barbara",
    "wof:placetype":"venue"
},
  "geometry": {"coordinates":[7.77261,46.399551],"type":"Point"}
}