{
  "type": "Feature",
  "properties": {
    "iso:country":"CH",
    "sg:address":"Chemin Du Ch\u00e2telard 23",
    "sg:city":"Aigle",
    "sg:classifiers":[
        {
            "category":"Restaurant",
            "type":"Food & Drink"
        }
    ],
    "sg:phone":"+41 24 466 34 68",
    "sg:postcode":"1860",
    "sg:province":"Vaud",
    "wof:name":"Restaurant-pizzeria San Remo",
    "wof:placetype":"venue"
},
  "geometry": {"coordinates":[6.9585428238,46.3135223389],"type":"Point"}
}