{
  "type": "Feature",
  "properties": {
    "iso:country":"CH",
    "sg:address":"Grand-rue 30 1204 Gen\u00e8ve. Postfach",
    "sg:city":"Gen\u00e8ve",
    "sg:orig_category":"Detailhandel mit M\u00f6beln U Haushaltsgegenst\u00e4nden",
    "sg:postcode":"1204",
    "sg:province":"Gen\u00e8ve",
    "wof:name":"Asia-africa Museum H\u00e9l\u00e8ne Nguyen Tan-phuoc",
    "wof:placetype":"venue"
},
  "geometry": {"coordinates":[6.1462450027,46.201461792],"type":"Point"}
}