{
  "type": "Feature",
  "properties": {
    "iso:country":"CH",
    "sg:address":"Oberredstrasse 9",
    "sg:city":"Niedererlinsbach",
    "sg:orig_category":"Detailhandel mit Sportartikeln Grosshandel mit Sportartikeln",
    "sg:phone":"+41 32 721 21 22",
    "sg:postcode":"5015",
    "sg:province":"Solothurn",
    "wof:name":"Lambelet Diffusion",
    "wof:placetype":"venue"
},
  "geometry": {"coordinates":[6.8602528572,46.9589805603],"type":"Point"}
}