{
  "type": "Feature",
  "properties": {
    "iso:country":"CH",
    "sg:address":"Via Borgo 55",
    "sg:city":"Ascona",
    "sg:orig_category":"Zahnarztpraxen",
    "sg:phone":"+41 91 792 25 26",
    "sg:postcode":"6612",
    "sg:province":"Ticino",
    "wof:name":"Dottori Montanari & Leonardi Dentisti",
    "wof:placetype":"venue"
},
  "geometry": {"coordinates":[8.7668514252,46.1550331116],"type":"Point"}
}