{
  "type": "Feature",
  "properties": {
    "iso:country":"CH",
    "sg:address":"Industriestrasse 6b",
    "sg:city":"Bronschhofen",
    "sg:orig_category":"Unclassifiable Establishments",
    "sg:phone":"+41 71 913 98 88",
    "sg:postcode":"9552",
    "sg:province":"St. Gallen",
    "wof:name":"Telsonic Holding Ag",
    "wof:placetype":"venue"
},
  "geometry": {"coordinates":[9.0342998505,47.473323822],"type":"Point"}
}