{
  "type": "Feature",
  "properties": {
    "iso:country":"CH",
    "sg:address":"Therwilerstrasse 2",
    "sg:city":"Bottmingen",
    "sg:orig_category":"Detailhandel mit Milcherzeugnissen U Eiern Verarbeitung von Milch",
    "sg:phone":"+41 61 421 13 08",
    "sg:postcode":"4103",
    "sg:province":"Basel-Landschaft",
    "wof:name":"Mibo Sa",
    "wof:placetype":"venue"
},
  "geometry": {"coordinates":[7.5716371536,47.5233840942],"type":"Point"}
}