{
  "type": "Feature",
  "properties": {
    "iso:country":"CH",
    "sg:address":"H\u00f6schgasse 53",
    "sg:city":"Z\u00fcrich",
    "sg:orig_category":"Sonstige Aktivit\u00e4ten der nicht-\u00e4rztlichen Medizinalberufe",
    "sg:phone":"+41 79 327 33 51",
    "sg:postcode":"8008",
    "sg:province":"Z\u00fcrich",
    "wof:name":"Liselotte H\u00e4berli Kinesiologie",
    "wof:placetype":"venue"
},
  "geometry": {"coordinates":[8.5540676117,47.3577728271],"type":"Point"}
}