{
  "type": "Feature",
  "properties": {
    "iso:country":"CH",
    "sg:address":"Raing\u00e4ssli 14",
    "sg:city":"Meilen",
    "sg:orig_category":"Effektenvermittlung Broker Finanzierungsinstitutionen",
    "sg:phone":"+41 22 738 00 20",
    "sg:postcode":"8706",
    "sg:province":"Z\u00fcrich",
    "wof:name":"Trigone Capital Finance Sa",
    "wof:placetype":"venue"
},
  "geometry": {"coordinates":[6.147591114,46.2094612122],"type":"Point"}
}