{
  "type": "Feature",
  "properties": {
    "iso:country":"CH",
    "sg:address":"Staatsstrasse 149",
    "sg:city":"H\u00fcnibach",
    "sg:orig_category":"Kantonalbanken",
    "sg:phone":"+41 33 243 05 30",
    "sg:postcode":"3626",
    "sg:province":"Bern",
    "wof:name":"Berner Kantonalbank Bekb/bcbe",
    "wof:placetype":"venue"
},
  "geometry": {"coordinates":[7.6438231468,46.7455291748],"type":"Point"}
}