{
  "type": "Feature",
  "properties": {
    "iso:country":"CH",
    "sg:address":"Muristrasse 94",
    "sg:city":"Bern",
    "sg:orig_category":"Unclassifiable Establishments",
    "sg:phone":"+41 31 351 79 22",
    "sg:postcode":"3006",
    "sg:province":"Bern",
    "wof:name":"Inkoform Gmbh",
    "wof:placetype":"venue"
},
  "geometry": {"coordinates":[7.4694261551,46.9397544861],"type":"Point"}
}