{
  "type": "Feature",
  "properties": {
    "iso:country":"CH",
    "sg:address":"Usterstrasse 9",
    "sg:city":"M\u00f6nchaltorf",
    "sg:orig_category":"Detailhandel mit Waren verschiedener Art, Hauptrichtung Nahrungsmittel",
    "sg:phone":"+41 19480149",
    "sg:postcode":"8617",
    "sg:province":"Z\u00fcrich",
    "wof:name":"Max Hofmann Lebensmittel",
    "wof:placetype":"venue"
},
  "geometry": {"coordinates":[8.7212190628,47.3101921082],"type":"Point"}
}