{
  "type": "Feature",
  "properties": {
    "iso:country":"CH",
    "sg:address":"Fritz K\u00e4ser-strasse 2a",
    "sg:city":"Biberist",
    "sg:orig_category":"Physiotherapie",
    "sg:phone":"+41 32 672 10 80",
    "sg:postcode":"4562",
    "sg:province":"Solothurn",
    "wof:name":"Physiotherapie Neumatt-zentrum",
    "wof:placetype":"venue"
},
  "geometry": {"coordinates":[7.5629768372,47.1836509705],"type":"Point"}
}