{
  "type": "Feature",
  "properties": {
    "iso:country":"CH",
    "sg:address":"Galgenfeldweg 7",
    "sg:city":"Bern",
    "sg:orig_category":"Heat-Resistant Insulated Lines",
    "sg:phone":"+41 31 332 14 41",
    "sg:postcode":"3006",
    "sg:province":"Bern",
    "wof:name":"Armasol Ag",
    "wof:placetype":"venue"
},
  "geometry": {"coordinates":[7.4709591866,46.9539794922],"type":"Point"}
}