{
  "type": "Feature",
  "properties": {
    "iso:country":"CH",
    "sg:address":"Kleinb\u00e4retswil 8344 B\u00e4retswil. Postfach",
    "sg:city":"B\u00e4retswil",
    "sg:orig_category":"Wasserversorgung",
    "sg:postcode":"8344",
    "sg:province":"Z\u00fcrich",
    "wof:name":"Wasserversorgungsgenossenschaft Allmann",
    "wof:placetype":"venue"
},
  "geometry": {"coordinates":[8.856669426,47.3358688354],"type":"Point"}
}