{
  "type": "Feature",
  "properties": {
    "iso:country":"CH",
    "sg:address":"Solothurnstrasse 16",
    "sg:city":"B\u00e4tterkinden",
    "sg:orig_category":"Maler U Glasergewerbe Verlegen von Fussboden",
    "sg:postcode":"3315",
    "sg:province":"Bern",
    "wof:name":"Fritz Joggi",
    "wof:placetype":"venue"
},
  "geometry": {"coordinates":[7.5387029648,47.1324806213],"type":"Point"}
}