{
  "type": "Feature",
  "properties": {
    "iso:country":"CH",
    "sg:address":"Route De Veyrier 272",
    "sg:city":"Veyrier",
    "sg:classifiers":[
        {
            "category":"Banks & Credit Unions",
            "subcategory":"Bank",
            "type":"Services"
        }
    ],
    "sg:phone":"+41 24 430 03 03",
    "sg:postcode":"1255",
    "sg:province":"Gen\u00e8ve",
    "wof:name":"Banque Raiffeisen Yvonand",
    "wof:placetype":"venue"
},
  "geometry": {"coordinates":[6.74507,46.799728],"type":"Point"}
}