{
  "type": "Feature",
  "properties": {
    "iso:country":"CH",
    "sg:address":"Libellenrain 17 6004 Luzern. Postfach 4634",
    "sg:city":"Luzern",
    "sg:orig_category":"Herstellung von Bekleidung U Pelzwaren Textilgewerbe",
    "sg:phone":"+41 41 420 08 70",
    "sg:postcode":"6002",
    "sg:province":"Luzern",
    "wof:name":"Kleiderfabrik Am Rotsee Ag",
    "wof:placetype":"venue"
},
  "geometry": {"coordinates":[8.3046541214,47.0638504028],"type":"Point"}
}