{
  "type": "Feature",
  "properties": {
    "iso:country":"CH",
    "sg:address":"Allmendweg 1",
    "sg:city":"Zufikon",
    "sg:orig_category":"Gymnastik U Fitnesszentren Saunas, Solarien, Fitnesszentren U \u00e4hnliches",
    "sg:phone":"+41 41 670 08 70",
    "sg:postcode":"5621",
    "sg:province":"Aargau",
    "wof:name":"Condor Fitness- & Gesundheits-studio Gmbh",
    "wof:placetype":"venue"
},
  "geometry": {"coordinates":[8.2784233093,46.9417533875],"type":"Point"}
}