{
  "type": "Feature",
  "properties": {
    "iso:country":"CH",
    "sg:address":"St. Galler Strasse 45",
    "sg:city":"Kronb\u00fchl",
    "sg:orig_category":"Herstellung von Bereifungen Pneus Detailhandel",
    "sg:phone":"+41 71 298 38 83",
    "sg:postcode":"9302",
    "wof:name":"Pneu Kr\u00fcsi Autobestandteile - Alu Und Stahlfelgen",
    "wof:placetype":"venue"
},
  "geometry": {"coordinates":[9.3984603882,47.4556388855],"type":"Point"}
}