{
  "type": "Feature",
  "properties": {
    "iso:country":"CH",
    "sg:address":"9658",
    "sg:city":"Wildhaus",
    "sg:orig_category":"Sportvereine Sch\u00fctzen",
    "sg:phone":"+41 71 923 63 59",
    "sg:postcode":"9658",
    "sg:province":"St. Gallen",
    "wof:name":"Milit\u00e4rsch\u00fctzenverein",
    "wof:placetype":"venue"
},
  "geometry": {"coordinates":[9.3509206772,47.2028656006],"type":"Point"}
}