{
  "type": "Feature",
  "properties": {
    "iso:country":"CH",
    "sg:address":"Steinberggasse 21",
    "sg:city":"Winterthur",
    "sg:orig_category":"Detailhandel mit Antiquit\u00e4ten U Gebrauchtwaren in Verkaufsr\u00e4umen Detailhandel mit B\u00fcchern",
    "sg:phone":"+41 52 212 44 46",
    "sg:postcode":"8400",
    "sg:province":"Z\u00fcrich",
    "wof:name":"B\u00fcecherbrocki & Antiquartiat C.rufener",
    "wof:placetype":"venue"
},
  "geometry": {"coordinates":[8.729417,47.498234],"type":"Point"}
}