{
  "type": "Feature",
  "properties": {
    "iso:country":"CH",
    "sg:address":"Stotzhalten",
    "sg:city":"Grindelwald",
    "sg:orig_category":"HOTELS: OHNE RESTAURANT",
    "sg:phone":"+41 71 223 60 80",
    "sg:postcode":"3818",
    "sg:province":"Bern",
    "wof:name":"Hotel Vadian Garni",
    "wof:placetype":"venue"
},
  "geometry": {"coordinates":[9.3755378723,47.4221496582],"type":"Point"}
}