{
  "type": "Feature",
  "properties": {
    "addr:full":"Laupenstrasse 6 Bern Bern 3008",
    "addr:housenumber":"6",
    "addr:postcode":"3008",
    "addr:street":"Laupenstrasse",
    "iso:country":"CH",
    "sg:address":"Laupenstrasse 6",
    "sg:city":"Bern",
    "sg:orig_category":"Arztpraxen",
    "sg:phone":"+41 31 331 60 31",
    "sg:postcode":"3008",
    "sg:province":"Bern",
    "wof:name":"Dr.med.jasna Aljinovic Spezial\u00e4rztin Fmh",
    "wof:placetype":"venue"
},
  "geometry": {"coordinates":[7.43671,46.947384],"type":"Point"}
}