{
  "type": "Feature",
  "properties": {
    "iso:country":"CH",
    "sg:address":"Hauptstr. 142 5072 Oeschgen. Postfach",
    "sg:city":"Oeschgen",
    "sg:orig_category":"Pensionskassen",
    "sg:postcode":"5072",
    "sg:province":"Aargau",
    "wof:name":"Personalvorsorgestiftung Der Werner Keigel Ag",
    "wof:placetype":"venue"
},
  "geometry": {"coordinates":[8.0107088089,47.5183563232],"type":"Point"}
}