{
  "type": "Feature",
  "properties": {
    "iso:country":"CH",
    "sg:address":"Stationsstrasse 3",
    "sg:city":"Brenzikofen",
    "sg:orig_category":"Detailhandel Reparatur von Gebrauchsg\u00fctern",
    "sg:phone":"+41 31 771 03 82",
    "sg:postcode":"3671",
    "sg:province":"Bern",
    "wof:name":"Landw.genossenschaft Herbligen Brenzikofen",
    "wof:placetype":"venue"
},
  "geometry": {"coordinates":[7.6128058434,46.8171234131],"type":"Point"}
}