{
  "type": "Feature",
  "properties": {
    "iso:country":"CH",
    "sg:address":"Marienruh Ried",
    "sg:city":"Giswil",
    "sg:orig_category":"Grosshandel mit lebenden Tieren",
    "sg:phone":"+41 79 669 77 80",
    "sg:postcode":"6074",
    "sg:province":"Obwalden",
    "wof:name":"Josef Von Ah Viehhandel",
    "wof:placetype":"venue"
},
  "geometry": {"coordinates":[8.1849498749,46.8343658447],"type":"Point"}
}