{
  "type": "Feature",
  "properties": {
    "iso:country":"CH",
    "sg:address":"6517",
    "sg:city":"Arbedo",
    "sg:orig_category":"Organisationen des Gesundheitswesen",
    "sg:postcode":"6517",
    "sg:province":"Ticino",
    "wof:name":"Societ\u00e0 Dei Samaritani",
    "wof:placetype":"venue"
},
  "geometry": {"coordinates":[9.0421895981,46.2133483887],"type":"Point"}
}