{
  "type": "Feature",
  "properties": {
    "iso:country":"CH",
    "sg:address":"Chantepoulet Rue De 1-3 1201 Gen\u00e8ve. Postfach",
    "sg:city":"Gen\u00e8ve",
    "sg:orig_category":"Unclassifiable Establishments",
    "sg:postcode":"1201",
    "sg:province":"Gen\u00e8ve",
    "wof:name":"Enderli Werner Und Albrecht Margrit, Pro Due Partnervermittlung",
    "wof:placetype":"venue"
},
  "geometry": {"coordinates":[12.5818796158,47.8608703613],"type":"Point"}
}