{
  "type": "Feature",
  "properties": {
    "iso:country":"CH",
    "sg:address":"Rue De La Piscine 10",
    "sg:city":"Sion",
    "sg:orig_category":"Vermietung U Verpachtung von eigenen Immobilien",
    "sg:postcode":"1950",
    "sg:province":"Valais",
    "wof:name":"Pilier 4 Sa",
    "wof:placetype":"venue"
},
  "geometry": {"coordinates":[7.3547649384,46.2249145508],"type":"Point"}
}