{
  "type": "Feature",
  "properties": {
    "iso:country":"CH",
    "sg:address":"L\u00e4nggasse 47",
    "sg:city":"Selzach",
    "sg:orig_category":"G\u00fcterbef\u00f6rderung im Strassenverkehr",
    "sg:phone":"+41 61 713 04 56",
    "sg:postcode":"2545",
    "sg:province":"Solothurn",
    "wof:name":"Portmann Hermann",
    "wof:placetype":"venue"
},
  "geometry": {"coordinates":[7.587952137,47.4936141968],"type":"Point"}
}