{
  "type": "Feature",
  "properties": {
    "addr:full":"Morgartenstrasse 6 Z\u00fcrich Z\u00fcrich 8004",
    "addr:housenumber":"6",
    "addr:postcode":"8004",
    "addr:street":"Morgartenstrasse",
    "iso:country":"CH",
    "sg:address":"Morgartenstrasse 6",
    "sg:city":"Z\u00fcrich",
    "sg:orig_category":"Architektur U Ingenieurb\u00fcros",
    "sg:postcode":"8004",
    "sg:province":"Z\u00fcrich",
    "wof:name":"Bcp Biotech Consulting Partners Gmbh",
    "wof:placetype":"venue"
},
  "geometry": {"coordinates":[8.529309,47.371407],"type":"Point"}
}