{
  "type": "Feature",
  "properties": {
    "iso:country":"CH",
    "sg:address":"Aarwangenstrasse 9",
    "sg:city":"Langenthal",
    "sg:orig_category":"Organisationen der Wohlfahrtspflege",
    "sg:phone":"+41 62 922 50 52",
    "sg:postcode":"4900",
    "sg:province":"Bern",
    "wof:name":"Pro Juventute Bezirkssekretariat Aarwangen",
    "wof:placetype":"venue"
},
  "geometry": {"coordinates":[7.7880129814,47.214176178],"type":"Point"}
}