{
  "type": "Feature",
  "properties": {
    "iso:country":"CH",
    "sg:address":"Alpenstrasse 16",
    "sg:city":"Zug",
    "sg:orig_category":"Architektur U Ingenieurb\u00fcros Ingenieurb\u00fcros Geologie",
    "sg:phone":"+41 41 720 07 02",
    "sg:postcode":"6300",
    "sg:province":"Zug",
    "wof:name":"Muttoni & Beffa Sa",
    "wof:placetype":"venue"
},
  "geometry": {"coordinates":[8.515163,47.172855],"type":"Point"}
}