{
  "type": "Feature",
  "properties": {
    "iso:country":"CH",
    "sg:address":"6533 Lumino. Postfach",
    "sg:city":"Lumino",
    "sg:orig_category":"Hardwareberatung",
    "sg:phone":"+41 91 829 04 79",
    "sg:postcode":"6533",
    "sg:province":"Ticino",
    "wof:name":"Deac Sagl Impianti N. Ambito D. Domotica, Telemisura Ecc.; Progettazione, Consulenza, Installazione",
    "wof:placetype":"venue"
},
  "geometry": {"coordinates":[9.065369606,46.23072052],"type":"Point"}
}