{
  "type": "Feature",
  "properties": {
    "iso:country":"CH",
    "sg:address":"Silostr. 1",
    "sg:city":"Dintikon",
    "sg:classifiers":[
        {
            "category":"Home & Garden",
            "subcategory":"Furniture",
            "type":"Retail Goods"
        }
    ],
    "sg:phone":"+41 56 616 60 70",
    "sg:postcode":"5606",
    "sg:province":"Aargau",
    "sg:tags":[
        "household",
        "wood"
    ],
    "wof:name":"Botanic-haus Plastiflor Ag",
    "wof:placetype":"venue"
},
  "geometry": {"coordinates":[8.2252492905,47.3752861023],"type":"Point"}
}