{
  "type": "Feature",
  "properties": {
    "iso:country":"CH",
    "sg:address":"Holzgasse 1",
    "sg:city":"Sch\u00f6nb\u00fchl-urtenen",
    "sg:orig_category":"Architektur U Ingenieurb\u00fcros",
    "sg:phone":"+41 71 910 11 12",
    "sg:postcode":"3322",
    "sg:province":"Bern",
    "wof:name":"Ingenieurb\u00fcro Merz",
    "wof:placetype":"venue"
},
  "geometry": {"coordinates":[9.044128,47.470627],"type":"Point"}
}