{
  "type": "Feature",
  "properties": {
    "addr:full":"Oberhaus 371 Gais Appenzell Ausserrhoden 9056",
    "addr:housenumber":"371",
    "addr:postcode":"9056",
    "addr:street":"Oberhaus;Appenzell Ausserrhoden",
    "iso:country":"CH",
    "sg:address":"Oberhaus 371",
    "sg:city":"Gais",
    "sg:orig_category":"Aktivit\u00e4t der Bankinstitute",
    "sg:phone":"+41 91 695 49 11",
    "sg:postcode":"9056",
    "sg:province":"Appenzell Ausserrhoden",
    "wof:name":"Abn Amro Bank (schweiz)",
    "wof:placetype":"venue"
},
  "geometry": {"coordinates":[9.014679,45.847984],"type":"Point"}
}