{
  "type": "Feature",
  "properties": {
    "iso:country":"CH",
    "sg:address":"Via Vignole",
    "sg:city":"Manno",
    "sg:orig_category":"Verwaltung von Immobilien",
    "sg:phone":"+41 21 971 14 04",
    "sg:postcode":"6928",
    "sg:province":"Ticino",
    "wof:name":"Gendre & Emonet, G\u00e9rance Et Fiduciaire Sa Immeubles; G\u00e9rance, Courtage, Administration Etc",
    "wof:placetype":"venue"
},
  "geometry": {"coordinates":[6.8569989204,46.4531364441],"type":"Point"}
}