{
  "type": "Feature",
  "properties": {
    "iso:country":"CH",
    "sg:address":"Forchstrasse 420 8702 Zollikon. Postfach",
    "sg:city":"Zollikon",
    "sg:orig_category":"Rechtsberatung",
    "sg:postcode":"8702",
    "sg:province":"Z\u00fcrich",
    "wof:name":"Frei Patentanwaltsb\u00fcro Ag",
    "wof:placetype":"venue"
},
  "geometry": {"coordinates":[8.584227562,47.3503265381],"type":"Point"}
}