{
  "type": "Feature",
  "properties": {
    "iso:country":"CH",
    "sg:address":"1996",
    "sg:city":"Basse-nendaz",
    "sg:orig_category":"Tankstellen",
    "sg:phone":"+41 27 288 23 46",
    "sg:postcode":"1996",
    "sg:province":"Valais",
    "wof:name":"Georges Bornet Carrosserie & Station Bp",
    "wof:placetype":"venue"
},
  "geometry": {"coordinates":[7.3121800423,46.190158844],"type":"Point"}
}