{
  "type": "Feature",
  "properties": {
    "iso:country":"CH",
    "sg:address":"3305",
    "sg:city":"Iffwil",
    "sg:orig_category":"Primarschulen",
    "sg:phone":"+41 31 761 36 51",
    "sg:postcode":"3305",
    "sg:province":"Bern",
    "wof:name":"Primarschule",
    "wof:placetype":"venue"
},
  "geometry": {"coordinates":[7.4820280075,47.0620880127],"type":"Point"}
}