{
  "type": "Feature",
  "properties": {
    "iso:country":"CH",
    "sg:address":"Z\u00fcrcherstrasse 330 8500 Frauenfeld. Postfach",
    "sg:city":"Frauenfeld",
    "sg:orig_category":"Instandhaltung U Reparatur von Automobilen",
    "sg:phone":"+41 52 722 45 22",
    "sg:postcode":"8503",
    "sg:province":"Thurgau",
    "wof:name":"Autokosmetik Uebigau",
    "wof:placetype":"venue"
},
  "geometry": {"coordinates":[8.913066864,47.5660934448],"type":"Point"}
}