{
  "type": "Feature",
  "properties": {
    "iso:country":"CH",
    "sg:address":"Rheinstrasse 65",
    "sg:city":"Chur",
    "sg:orig_category":"RESTAURANTS: TEA-ROOMS",
    "sg:postcode":"7000",
    "sg:province":"Graubunden",
    "wof:name":"Cabernard Gmbh",
    "wof:placetype":"venue"
},
  "geometry": {"coordinates":[9.5216426849,46.8546981812],"type":"Point"}
}