{
  "type": "Feature",
  "properties": {
    "iso:country":"CH",
    "sg:address":"Ligusterweg 7",
    "sg:city":"Bonstetten",
    "sg:orig_category":"Herstellung von Reiseartikeln, Leder U Sattlerwaren Textilgewerbe",
    "sg:phone":"+41 17779685",
    "sg:postcode":"8906",
    "sg:province":"Z\u00fcrich",
    "wof:name":"Thaler L. Gmbh",
    "wof:placetype":"venue"
},
  "geometry": {"coordinates":[8.4712810516,47.3265762329],"type":"Point"}
}