{
  "type": "Feature",
  "properties": {
    "iso:country":"CH",
    "sg:address":"Litternaring 2 3930 Visp. Postfach 281",
    "sg:city":"Visp",
    "sg:orig_category":"Elektrizit\u00e4tsversorgung Unternehmensberatung",
    "sg:phone":"+41 27 948 61 88",
    "sg:postcode":"3930",
    "sg:province":"Valais",
    "wof:name":"Lonza Energie Ag Konzerngesellschaft. Anlagen; Koordination, \u00dcberwachung, Forschung Usw",
    "wof:placetype":"venue"
},
  "geometry": {"coordinates":[7.8859620094,46.2934608459],"type":"Point"}
}