{
  "type": "Feature",
  "properties": {
    "iso:country":"CH",
    "sg:address":"Buholz",
    "sg:city":"Ruswil",
    "sg:orig_category":"Fussreflexzonenmassage",
    "sg:phone":"+41 62 291 13 57",
    "sg:postcode":"6017",
    "sg:province":"Luzern",
    "wof:name":"Romy Kiser Fussreflexzonen-massage",
    "wof:placetype":"venue"
},
  "geometry": {"coordinates":[7.9845910072,47.3544540405],"type":"Point"}
}