{
  "type": "Feature",
  "properties": {
    "iso:country":"CH",
    "sg:address":"St.-johannes-strasse 6",
    "sg:city":"Zug",
    "sg:orig_category":"Softwareentwicklung U beratung",
    "sg:phone":"+41 41 741 83 71",
    "sg:postcode":"6300",
    "sg:province":"Zug",
    "wof:name":"Ilic Software Engineering",
    "wof:placetype":"venue"
},
  "geometry": {"coordinates":[8.5064287186,47.179523468],"type":"Point"}
}