{
  "type": "Feature",
  "properties": {
    "iso:country":"CH",
    "sg:address":"Stettenstrasse Postfach",
    "sg:city":"Henau",
    "sg:orig_category":"Miscellaneous Products",
    "sg:phone":"+41 21 345 82 11",
    "sg:postcode":"9247",
    "sg:province":"St. Gallen",
    "wof:name":"Codefine Sa",
    "wof:placetype":"venue"
},
  "geometry": {"coordinates":[6.644411087,46.5169410706],"type":"Point"}
}