{
  "type": "Feature",
  "properties": {
    "addr:full":"Luegetenstrasse 16 Einsiedeln Schwyz 8840",
    "addr:housenumber":"16",
    "addr:postcode":"8840",
    "addr:street":"Luegetenstrasse;Schwyz",
    "iso:country":"CH",
    "sg:address":"Luegetenstrasse 16",
    "sg:city":"Einsiedeln",
    "sg:orig_category":"Detailhandel mit Antiquit\u00e4ten U Gebrauchtwaren in Verkaufsr\u00e4umen Sonstiger Fachdetailhandel in Verka",
    "sg:phone":"+41 71 747 65 00",
    "sg:postcode":"8840",
    "sg:province":"Schwyz",
    "wof:name":"Interbond Ag F\u00fcr Historische Wertpapiere",
    "wof:placetype":"venue"
},
  "geometry": {"coordinates":[9.6406,47.436825],"type":"Point"}
}