{
  "type": "Feature",
  "properties": {
    "iso:country":"CH",
    "sg:address":"Postgasse 35",
    "sg:city":"Interlaken",
    "sg:orig_category":"Vorschulen, Kinderg\u00e4rten",
    "sg:postcode":"3800",
    "sg:province":"Bern",
    "wof:name":"Kindergarten",
    "wof:placetype":"venue"
},
  "geometry": {"coordinates":[7.8527960777,46.6873931885],"type":"Point"}
}