{
  "type": "Feature",
  "properties": {
    "iso:country":"CH",
    "sg:address":"Avry-bourg",
    "sg:city":"Avry-sur-matran",
    "sg:orig_category":"Abbruch U Sprenggewerbe, Erdbewegungsarbeiten",
    "sg:postcode":"1754",
    "sg:province":"Fribourg",
    "wof:name":"Abp Assechement S.\u00e0.r.l.",
    "wof:placetype":"venue"
},
  "geometry": {"coordinates":[7.078503,46.784973],"type":"Point"}
}