{
  "type": "Feature",
  "properties": {
    "iso:country":"CH",
    "sg:address":"Rosenbergstrasse 56",
    "sg:city":"St.gallen",
    "sg:orig_category":"Detailhandel mit B\u00fcromaschinen U einrichtungen Detailhandel mit Computern U Software",
    "sg:phone":"+41 71 223 60 02",
    "sg:postcode":"9000",
    "sg:province":"St. Gallen",
    "wof:name":"Schober Hans.",
    "wof:placetype":"venue"
},
  "geometry": {"coordinates":[9.368012,47.423622],"type":"Point"}
}