{
  "type": "Feature",
  "properties": {
    "iso:country":"CH",
    "sg:address":"Brienzstrasse",
    "sg:city":"Goldswil",
    "sg:classifiers":[
        {
            "category":"Travel",
            "subcategory":"Hotels & Motels",
            "type":"Entertainment"
        }
    ],
    "sg:phone":"+41 33 822 15 43",
    "sg:postcode":"3805",
    "sg:province":"Bern",
    "sg:tags":[
        "hotels",
        "mit",
        "restaurant"
    ],
    "wof:name":"Hotel Sch\u00f6negg",
    "wof:placetype":"venue"
},
  "geometry": {"coordinates":[7.8765048981,46.6964454651],"type":"Point"}
}