{
  "type": "Feature",
  "properties": {
    "iso:country":"CH",
    "sg:address":"Blickensdorferstrasse 5",
    "sg:city":"Steinhausen",
    "sg:orig_category":"Grosshandel mit Getr\u00e4nken Grosshandel mit Wein U Spirituosen",
    "sg:phone":"+41 41 743 12 15",
    "sg:postcode":"6312",
    "sg:province":"Zug",
    "wof:name":"Sp\u00f6rri Paul Swiss Panorama",
    "wof:placetype":"venue"
},
  "geometry": {"coordinates":[8.4855155945,47.1971130371],"type":"Point"}
}