{
  "type": "Feature",
  "properties": {
    "iso:country":"CH",
    "sg:address":"Mulino Di Neggio",
    "sg:city":"Magliaso",
    "sg:orig_category":"Bestattungswesen",
    "sg:phone":"+41 91 606 23 53",
    "sg:postcode":"6983",
    "sg:province":"Ticino",
    "wof:name":"Roberto Monti Onoranze Funebri",
    "wof:placetype":"venue"
},
  "geometry": {"coordinates":[8.879485,45.982204],"type":"Point"}
}