{
  "type": "Feature",
  "properties": {
    "iso:country":"CH",
    "sg:address":"Vorheidestrasse 1",
    "sg:city":"Aadorf",
    "sg:orig_category":"Blumen U Zierpflanzenbau Grosshandel mit Blumen U Pflanzen",
    "sg:phone":"+41 52 365 12 06",
    "sg:postcode":"8355",
    "sg:province":"Thurgau",
    "wof:name":"K\u00fcnzli & Co",
    "wof:placetype":"venue"
},
  "geometry": {"coordinates":[8.906679,47.498821],"type":"Point"}
}