{
  "type": "Feature",
  "properties": {
    "iso:country":"CH",
    "sg:address":"Feldstrasse 76",
    "sg:city":"B\u00fclach",
    "sg:orig_category":"Instandhaltung U Reparatur von Automobilen",
    "sg:phone":"+41 18604816",
    "sg:postcode":"8180",
    "sg:province":"Z\u00fcrich",
    "wof:name":"Gebr\u00fcder Santoli Carrosserie & Garage",
    "wof:placetype":"venue"
},
  "geometry": {"coordinates":[8.5384578705,47.5097312927],"type":"Point"}
}