{
  "type": "Feature",
  "properties": {
    "iso:country":"CH",
    "sg:address":"Waldweg 10",
    "sg:city":"Buchrain",
    "sg:orig_category":"Unclassifiable Establishments",
    "sg:postcode":"6033",
    "sg:province":"Luzern",
    "wof:name":"A-z Lager Gmbh",
    "wof:placetype":"venue"
},
  "geometry": {"coordinates":[8.3420753479,47.0931625366],"type":"Point"}
}