{
  "type": "Feature",
  "properties": {
    "iso:country":"CH",
    "sg:address":"Dettenried 19",
    "sg:city":"Neschwil",
    "sg:orig_category":"Bauspenglerei Sanit\u00e4rinstallation U Spenglerei",
    "sg:phone":"+41 52 345 18 10",
    "sg:postcode":"8484",
    "sg:province":"Z\u00fcrich",
    "wof:name":"Werner Wyss Spenglerei",
    "wof:placetype":"venue"
},
  "geometry": {"coordinates":[8.763714,47.431526],"type":"Point"}
}