{
  "type": "Feature",
  "properties": {
    "iso:country":"CH",
    "sg:address":"Weid 1",
    "sg:city":"Muotathal",
    "sg:orig_category":"Malerei",
    "sg:phone":"+41 79 408 21 04",
    "sg:postcode":"6436",
    "sg:province":"Schwyz",
    "wof:name":"Pirmin Rickenbacher Malergesch\u00e4ft",
    "wof:placetype":"venue"
},
  "geometry": {"coordinates":[8.7504682541,46.9758529663],"type":"Point"}
}