{
  "type": "Feature",
  "properties": {
    "iso:country":"CH",
    "sg:address":"Rona 7454 Rona. Postfach",
    "sg:city":"Rona",
    "sg:orig_category":"Instandhaltung U Reparatur von Automobilen",
    "sg:postcode":"7454",
    "sg:province":"Graubunden",
    "wof:name":"Jovanovic Zivojin",
    "wof:placetype":"venue"
},
  "geometry": {"coordinates":[-114.0970916748,47.5284233093],"type":"Point"}
}