{
  "type": "Feature",
  "properties": {
    "addr:full":"Lehenmattstrasse 248 Basel Basel-Stadt 4052",
    "addr:housenumber":"248",
    "addr:postcode":"4052",
    "addr:street":"Lehenmattstrasse",
    "iso:country":"CH",
    "sg:address":"Lehenmattstrasse 248",
    "sg:city":"Basel",
    "sg:orig_category":"Arztpraxen",
    "sg:phone":"+41 61 311 17 66",
    "sg:postcode":"4052",
    "sg:province":"Basel-Stadt",
    "wof:name":"Dr.med.louis Litschgi Arzt F\u00fcr Allgemeine Medizin",
    "wof:placetype":"venue"
},
  "geometry": {"coordinates":[7.620921,47.54813],"type":"Point"}
}