{
  "type": "Feature",
  "properties": {
    "iso:country":"CH",
    "sg:address":"Bruggenmattweg 1",
    "sg:city":"Bonstetten",
    "sg:orig_category":"Wirtschaftspr\u00fcfung, Steuerberatung U Treuhand",
    "sg:postcode":"8906",
    "sg:province":"Z\u00fcrich",
    "wof:name":"Maurer Rosmarie, Buchhaltungsmandate",
    "wof:placetype":"venue"
},
  "geometry": {"coordinates":[8.4745874405,47.3263893127],"type":"Point"}
}