{
  "type": "Feature",
  "properties": {
    "iso:country":"CH",
    "sg:address":"Hofwiesenstrasse 207",
    "sg:city":"Z\u00fcrich",
    "sg:orig_category":"Geb\u00e4ude, Wohnungsreinigung Reinigungsgewerbe",
    "sg:phone":"+41 13641919",
    "sg:postcode":"8057",
    "sg:province":"Z\u00fcrich",
    "wof:name":"Pua Reinigungs Ag",
    "wof:placetype":"venue"
},
  "geometry": {"coordinates":[8.535654068,47.4028320312],"type":"Point"}
}