{
  "type": "Feature",
  "properties": {
    "iso:country":"CH",
    "sg:address":"Scheurenstrasse 16",
    "sg:city":"Dotzigen",
    "sg:orig_category":"Grosshandel mit Software Vermietung U Verpachtung von eigenen Immobilien",
    "sg:phone":"+41 79 332 93 46",
    "sg:postcode":"3293",
    "sg:province":"Bern",
    "wof:name":"Evioris Gmbh",
    "wof:placetype":"venue"
},
  "geometry": {"coordinates":[7.3349900246,47.1208152771],"type":"Point"}
}