{
  "type": "Feature",
  "properties": {
    "addr:full":"Hauptstrasse 32 Ettingen Basel-Landschaft 4107",
    "addr:housenumber":"32",
    "addr:postcode":"4107",
    "addr:street":"Hauptstrasse",
    "iso:country":"CH",
    "sg:address":"Hauptstrasse 32",
    "sg:city":"Ettingen",
    "sg:orig_category":"Alkoholbrennerei Rebbau",
    "sg:phone":"+41 61 751 45 45",
    "sg:postcode":"4107",
    "sg:province":"Basel-Landschaft",
    "wof:name":"Domaine Nussbaumer Ag Weine & Spirituosen",
    "wof:placetype":"venue"
},
  "geometry": {"coordinates":[7.577164,47.466084],"type":"Point"}
}