{
  "type": "Feature",
  "properties": {
    "iso:country":"CH",
    "sg:address":"Geisswaldweg 27",
    "sg:city":"Pratteln",
    "sg:orig_category":"Zimmerei, Dachdeckerei, Bauspenglerei U Abdichtung",
    "sg:phone":"+41 61 821 91 11",
    "sg:postcode":"4133",
    "sg:province":"Basel-Landschaft",
    "wof:name":"B\u00fcrgisser Spenglertechnik Ag",
    "wof:placetype":"venue"
},
  "geometry": {"coordinates":[7.701294899,47.5141372681],"type":"Point"}
}