{
  "type": "Feature",
  "properties": {
    "iso:country":"CH",
    "sg:address":"Pichard Rue 13 1003 Lausanne. Postfach",
    "sg:city":"Lausanne",
    "sg:orig_category":"Herstellung von sonstiger Bekleidung U Bekleidungszubeh\u00f6r",
    "sg:postcode":"1003",
    "sg:province":"Vaud",
    "wof:name":"Au Paradis De L'enfant, Mmes Martinez Et Perez Meubles, V\u00eatements, Jouets Etc Pour Enfants; Commerce",
    "wof:placetype":"venue"
},
  "geometry": {"coordinates":[6.632335186,46.5195960999],"type":"Point"}
}