{
  "type": "Feature",
  "properties": {
    "iso:country":"CH",
    "sg:address":"Via Colorine 12",
    "sg:city":"Stabio",
    "sg:orig_category":"Landwirtschaft, Jagd U damit verbundene Dienstleistungen",
    "sg:phone":"+41 91 647 19 40",
    "sg:postcode":"6855",
    "sg:province":"Ticino",
    "wof:name":"A. Christen Sa Azienda Agricola",
    "wof:placetype":"venue"
},
  "geometry": {"coordinates":[8.944688797,45.8440284729],"type":"Point"}
}