{
  "type": "Feature",
  "properties": {
    "iso:country":"CH",
    "sg:address":"4944",
    "sg:city":"Auswil",
    "sg:orig_category":"Schulpflegen",
    "sg:postcode":"4944",
    "sg:province":"Bern",
    "wof:name":"Primarschulkommission Der Gemeinde Baggwil",
    "wof:placetype":"venue"
},
  "geometry": {"coordinates":[7.3157100677,47.0305595398],"type":"Point"}
}