{
  "type": "Feature",
  "properties": {
    "iso:country":"CH",
    "sg:address":"Kirchgasse 4",
    "sg:city":"Arlesheim",
    "sg:orig_category":"RESTAURANTS: TEA-ROOMS",
    "sg:phone":"+41 61 701 99 05",
    "sg:postcode":"4144",
    "sg:province":"Basel-Landschaft",
    "wof:name":"Giuseppe Gatti, Restaurant Domst\u00fcbli",
    "wof:placetype":"venue"
},
  "geometry": {"coordinates":[7.6215500832,47.492149353],"type":"Point"}
}