{
  "type": "Feature",
  "properties": {
    "iso:country":"CH",
    "sg:address":"Moosmatt",
    "sg:city":"Murgenthal",
    "sg:orig_category":"Organisationen des Gesundheitswesen",
    "sg:phone":"+41 62 926 00 55",
    "sg:postcode":"4853",
    "sg:province":"Aargau",
    "wof:name":"Gemeindekrankenpflege",
    "wof:placetype":"venue"
},
  "geometry": {"coordinates":[7.8435850143,47.2740516663],"type":"Point"}
}