{
  "type": "Feature",
  "properties": {
    "iso:country":"CH",
    "sg:address":"1618",
    "sg:city":"Ch\u00e2tel-st-denis",
    "sg:classifiers":[
        {
            "category":"Education",
            "subcategory":"Vocational School",
            "type":"Public Place"
        }
    ],
    "sg:postcode":"1618",
    "sg:province":"Fribourg",
    "sg:tags":[
        "koch-",
        "haushaltschulen"
    ],
    "wof:name":"Ecole M\u00e9nag\u00e8re",
    "wof:placetype":"venue"
},
  "geometry": {"coordinates":[6.8579797745,46.9656105042],"type":"Point"}
}