{
  "type": "Feature",
  "properties": {
    "iso:country":"CH",
    "sg:address":"Burgstrasse 18",
    "sg:city":"Thun",
    "sg:orig_category":"Allgemeiner Hoch U Tiefbau",
    "sg:phone":"+41 81 756 70 13",
    "sg:postcode":"3600",
    "sg:province":"Bern",
    "wof:name":"Bauindustrie Multi-service, Paul Mazur",
    "wof:placetype":"venue"
},
  "geometry": {"coordinates":[9.474725,47.162006],"type":"Point"}
}