{
  "type": "Feature",
  "properties": {
    "iso:country":"CH",
    "sg:address":"Rinkenbach 12",
    "sg:city":"Appenzell",
    "sg:orig_category":"Handels-H\u00e4user U Gesellschaften",
    "sg:phone":"+41 41 711 60 79",
    "sg:postcode":"9050",
    "sg:province":"Appenzell Innerhoden",
    "wof:name":"Bacotex Handels Ag",
    "wof:placetype":"venue"
},
  "geometry": {"coordinates":[8.5081262589,47.1486358643],"type":"Point"}
}