{
  "type": "Feature",
  "properties": {
    "iso:country":"CH",
    "sg:address":"Idaplatz 2",
    "sg:city":"Z\u00fcrich",
    "sg:orig_category":"Grosshandel mit Foto U Kinoger\u00e4ten, feinmechanischen U optischen Erzeugnissen",
    "sg:phone":"+41 18410540",
    "sg:postcode":"8003",
    "sg:province":"Z\u00fcrich",
    "wof:name":"Eugen Aeppli Astro Optik & Instrumente",
    "wof:placetype":"venue"
},
  "geometry": {"coordinates":[8.4613513947,47.4537887573],"type":"Point"}
}