{
  "type": "Feature",
  "properties": {
    "iso:country":"CH",
    "sg:address":"Spitzackerstrasse 3",
    "sg:city":"Wallisellen",
    "sg:orig_category":"Softwareentwicklung U beratung",
    "sg:postcode":"8304",
    "sg:province":"Z\u00fcrich",
    "wof:name":"Db Consulting Gmbh",
    "wof:placetype":"venue"
},
  "geometry": {"coordinates":[8.6058826447,47.4112091064],"type":"Point"}
}