{
  "type": "Feature",
  "properties": {
    "iso:country":"CH",
    "sg:address":"Lindenstrasse 20",
    "sg:city":"Kloten",
    "sg:orig_category":"Unternehmensberatung",
    "sg:postcode":"8302",
    "sg:province":"Z\u00fcrich",
    "wof:name":"Keller Matthias, Lic. Oec. Hsg, Wirtschaftsberater",
    "wof:placetype":"venue"
},
  "geometry": {"coordinates":[8.5844049454,47.4489479065],"type":"Point"}
}