{
  "type": "Feature",
  "properties": {
    "iso:country":"CH",
    "sg:address":"Rue Des Moulins 11",
    "sg:city":"Vevey",
    "sg:orig_category":"Sprachschulen",
    "sg:phone":"+41 32 911 10 00",
    "sg:postcode":"1800",
    "sg:province":"Vaud",
    "wof:name":"Ecole-club Migros",
    "wof:placetype":"venue"
},
  "geometry": {"coordinates":[6.8300409317,47.1017684937],"type":"Point"}
}