{
  "type": "Feature",
  "properties": {
    "iso:country":"CH",
    "sg:address":"St\u00e4dtchen 1 8730 Uznach. Postfach",
    "sg:city":"Uznach",
    "sg:orig_category":"RESTAURANTS: TEA-ROOMS",
    "sg:postcode":"8730",
    "sg:province":"St. Gallen",
    "wof:name":"S&w Gastronomica Gmbh",
    "wof:placetype":"venue"
},
  "geometry": {"coordinates":[8.8964147568,47.1912956238],"type":"Point"}
}