{
  "type": "Feature",
  "properties": {
    "iso:country":"CH",
    "sg:address":"Frohburgstrasse 132 8057 Z\u00fcrich. Postfach",
    "sg:city":"Z\u00fcrich",
    "sg:orig_category":"Allgemeiner Hochbau Dachdeckerei",
    "sg:phone":"+41 13617660",
    "sg:postcode":"8057",
    "sg:province":"Z\u00fcrich",
    "wof:name":"Am Dach-& Fassaden Ag",
    "wof:placetype":"venue"
},
  "geometry": {"coordinates":[8.55172,47.394932],"type":"Point"}
}