{
  "type": "Feature",
  "properties": {
    "iso:country":"CH",
    "sg:address":"Baselstrasse 16",
    "sg:city":"Feldbrunnen",
    "sg:orig_category":"Unternehmensberatung",
    "sg:phone":"+41 32 621 81 88",
    "sg:postcode":"4532",
    "sg:province":"Solothurn",
    "wof:name":"Bwh Unternehmensberatung",
    "wof:placetype":"venue"
},
  "geometry": {"coordinates":[7.555106163,47.2201652527],"type":"Point"}
}