{
  "type": "Feature",
  "properties": {
    "iso:country":"CH",
    "sg:address":"1782",
    "sg:city":"Belfaux",
    "sg:orig_category":"Verwertung von Milch",
    "sg:postcode":"1782",
    "sg:province":"Fribourg",
    "wof:name":"Soci\u00e9t\u00e9 De Laiterie De Belfaux",
    "wof:placetype":"venue"
},
  "geometry": {"coordinates":[7.1060299873,46.8202896118],"type":"Point"}
}