{
  "type": "Feature",
  "properties": {
    "iso:country":"CH",
    "sg:address":"Sandreutenen 1 3110 M\u00fcnsingen. Postfach 1303",
    "sg:city":"M\u00fcnsingen",
    "sg:orig_category":"Sportvereine Ballsport Tennis",
    "sg:phone":"+41 41 370 14 04",
    "sg:postcode":"3110",
    "sg:province":"Bern",
    "wof:name":"Hallentennisclub Smash Luzern",
    "wof:placetype":"venue"
},
  "geometry": {"coordinates":[8.3337202072,47.0521507263],"type":"Point"}
}