{
  "type": "Feature",
  "properties": {
    "iso:country":"CH",
    "sg:address":"Deusstr. 3",
    "sg:city":"D\u00fcdingen",
    "sg:orig_category":"Instandhaltung U Reparatur von Automobilen",
    "sg:phone":"+41 55 440 18 25",
    "sg:postcode":"3186",
    "sg:province":"Fribourg",
    "wof:name":"Kuriger-pfister",
    "wof:placetype":"venue"
},
  "geometry": {"coordinates":[8.895190239,47.1914482117],"type":"Point"}
}