{
  "type": "Feature",
  "properties": {
    "iso:country":"CH",
    "sg:address":"3647",
    "sg:city":"Reutigen",
    "sg:orig_category":"Sportvereine Eissport Eishockey",
    "sg:postcode":"3647",
    "sg:province":"Bern",
    "wof:name":"Hockey-club Riviera Aslpn",
    "wof:placetype":"venue"
},
  "geometry": {"coordinates":[6.8568668365,46.4530258179],"type":"Point"}
}