{
  "type": "Feature",
  "properties": {
    "iso:country":"CH",
    "sg:address":"Schulweg 6 A",
    "sg:city":"Ittigen",
    "sg:orig_category":"Druck ohne Zeitungsdruck",
    "sg:phone":"+41 31 992 13 05",
    "sg:postcode":"3063",
    "sg:province":"Bern",
    "wof:name":"Gspurning Ren\u00e9",
    "wof:placetype":"venue"
},
  "geometry": {"coordinates":[7.4791908264,46.9750900269],"type":"Point"}
}