{
  "type": "Feature",
  "properties": {
    "iso:country":"CH",
    "sg:address":"Rosenweg 25",
    "sg:city":"Bern",
    "sg:orig_category":"Hardwareberatung Softwareentwicklung U beratung",
    "sg:postcode":"3007",
    "sg:province":"Bern",
    "wof:name":"Brainsys Brainstorm Systems Ag Edv Hard- & Software, Schulung",
    "wof:placetype":"venue"
},
  "geometry": {"coordinates":[7.434431076,46.9360809326],"type":"Point"}
}