{
  "type": "Feature",
  "properties": {
    "iso:country":"CH",
    "sg:address":"Weinbergstrasse 42",
    "sg:city":"Aarau",
    "sg:orig_category":"Kauf U Verkauf von Immobilien auf eigene Rechnung",
    "sg:phone":"+41 62 824 77 14",
    "sg:postcode":"5000",
    "sg:province":"Aargau",
    "wof:name":"Rietmann Kurt, Immobilienberatung, Aarau",
    "wof:placetype":"venue"
},
  "geometry": {"coordinates":[8.035733223,47.3964958191],"type":"Point"}
}