{
  "type": "Feature",
  "properties": {
    "iso:country":"CH",
    "sg:address":"Route De Fontenais 46",
    "sg:city":"Porrentruy",
    "sg:orig_category":"Druck ohne Zeitungsdruck",
    "sg:phone":"+41 32 466 71 79",
    "sg:postcode":"2900",
    "sg:province":"Jura",
    "wof:name":"Imprimerie Jaune D'encre, Girard Michel",
    "wof:placetype":"venue"
},
  "geometry": {"coordinates":[7.0774350166,47.4117660522],"type":"Point"}
}