{
  "type": "Feature",
  "properties": {
    "iso:country":"CH",
    "sg:address":"Unterdorfstrasse 23",
    "sg:city":"Dornach",
    "sg:orig_category":"Fussboden, Fliesen U Plattenlegerei, Tapeziererei",
    "sg:phone":"+41 79 651 67 76",
    "sg:postcode":"4143",
    "sg:province":"Solothurn",
    "wof:name":"Werner Gerber Fix Parkett",
    "wof:placetype":"venue"
},
  "geometry": {"coordinates":[7.5241189003,47.0206184387],"type":"Point"}
}