{
  "type": "Feature",
  "properties": {
    "iso:country":"CH",
    "sg:address":"Poststrasse 7050 Arosa. Postfach",
    "sg:city":"Arosa",
    "sg:orig_category":"Grossbanken",
    "sg:phone":"+41 52 741 17 26",
    "sg:postcode":"7050",
    "sg:province":"Graubunden",
    "wof:name":"Credit Suisse",
    "wof:placetype":"venue"
},
  "geometry": {"coordinates":[8.8590927124,47.6595993042],"type":"Point"}
}