{
  "type": "Feature",
  "properties": {
    "iso:country":"CH",
    "sg:address":"Gotthardstrasse 137",
    "sg:city":"Andermatt",
    "sg:classifiers":[
        {
            "category":"Restaurant",
            "type":"Food & Drink"
        }
    ],
    "sg:phone":"+41 41 887 10 30",
    "sg:postcode":"6490",
    "sg:province":"Uri",
    "wof:name":"Restaurant Schwarzer B\u00e4ren",
    "wof:placetype":"venue"
},
  "geometry": {"coordinates":[8.5945653915,46.6328659058],"type":"Point"}
}