{
  "type": "Feature",
  "properties": {
    "iso:country":"CH",
    "sg:address":"Rue Des Eaux-vives 20",
    "sg:city":"Gen\u00e8ve",
    "sg:orig_category":"Detailhandel mit B\u00fcchern Detailhandel mit B\u00fcchern, Zeitungen, Schreib U Papeteriewaren",
    "sg:phone":"+41 22 736 27 26",
    "sg:postcode":"1207",
    "sg:province":"Gen\u00e8ve",
    "wof:name":"Librairie Le Parnasse, Marco Dogliotti Et Boris Mabillard",
    "wof:placetype":"venue"
},
  "geometry": {"coordinates":[6.158601,46.204109],"type":"Point"}
}