{
  "type": "Feature",
  "properties": {
    "iso:country":"CH",
    "sg:address":"Breitenrainstrasse 17 3013 Bern. Postfach",
    "sg:city":"Bern",
    "sg:orig_category":"Pensionskassen",
    "sg:phone":"+41 31 331 58 22",
    "sg:postcode":"3005",
    "sg:province":"Bern",
    "wof:name":"Personalf\u00fcrsorgefonds Der Firma Schenker Druck Ag",
    "wof:placetype":"venue"
},
  "geometry": {"coordinates":[7.45221,46.957859],"type":"Point"}
}