{
  "type": "Feature",
  "properties": {
    "iso:country":"CH",
    "sg:address":"Brunnmattstrasse 50 4528 Zuchwil. Postfach",
    "sg:city":"Zuchwil",
    "sg:orig_category":"Herstellung von Teppichen",
    "sg:postcode":"4528",
    "sg:province":"Solothurn",
    "wof:name":"Schori Patrick",
    "wof:placetype":"venue"
},
  "geometry": {"coordinates":[7.5627498627,47.2008628845],"type":"Point"}
}