{
  "type": "Feature",
  "properties": {
    "iso:country":"CH",
    "sg:address":"Feldbergstrasse 45 4057 Basel. Postfach",
    "sg:city":"Basel",
    "sg:orig_category":"Detailhandel mit B\u00fcchern, Zeitungen, Schreib U Papeteriewaren",
    "sg:phone":"+41 61 692 16 55",
    "sg:postcode":"4051",
    "sg:province":"Basel-Stadt",
    "wof:name":"K\u00e4mpf-hajdu Sarolta Papeteriewaren; Handel",
    "wof:placetype":"venue"
},
  "geometry": {"coordinates":[7.590637,47.566345],"type":"Point"}
}