{
  "type": "Feature",
  "properties": {
    "iso:country":"CH",
    "sg:address":"Rathausstrasse 24/26",
    "sg:city":"Liestal",
    "sg:orig_category":"Detailhandel mit Damenbekleidung Detailhandel mit Herrenbekleidung",
    "sg:phone":"+41 61 921 68 87",
    "sg:postcode":"4410",
    "sg:province":"Basel-Landschaft",
    "wof:name":"Charles V\u00f6gele Mode Ag",
    "wof:placetype":"venue"
},
  "geometry": {"coordinates":[7.7345762253,47.4844017029],"type":"Point"}
}