{
  "type": "Feature",
  "properties": {
    "iso:country":"CH",
    "sg:address":"Choiseul Avenue 21a 1290 Versoix. Postfach",
    "sg:city":"Versoix",
    "sg:classifiers":[
        {
            "category":"Professional",
            "subcategory":"Employment Agencies",
            "type":"Services"
        }
    ],
    "sg:phone":"+41 19306622",
    "sg:postcode":"1290",
    "sg:province":"Gen\u00e8ve",
    "sg:tags":[
        "personal",
        "u",
        "stellenvermittlung"
    ],
    "wof:name":"Itta Ag",
    "wof:placetype":"venue"
},
  "geometry": {"coordinates":[8.8031492233,47.3282279968],"type":"Point"}
}