{
  "type": "Feature",
  "properties": {
    "iso:country":"CH",
    "sg:address":"Rue De La Cond\u00e9mine",
    "sg:city":"Bulle",
    "sg:orig_category":"Vorschulen, Kinderg\u00e4rten",
    "sg:phone":"+41 26 919 81 60",
    "sg:postcode":"1630",
    "sg:province":"Fribourg",
    "wof:name":"Ecole Enfantine I-iv",
    "wof:placetype":"venue"
},
  "geometry": {"coordinates":[7.0595607758,46.6176338196],"type":"Point"}
}