{
  "type": "Feature",
  "properties": {
    "iso:country":"CH",
    "sg:address":"G\u00fcterstrasse 137 4053 Basel. Postfach",
    "sg:city":"Basel",
    "sg:orig_category":"Unternehmensberatung",
    "sg:phone":"+41 61 366 86 30",
    "sg:postcode":"4008",
    "sg:province":"Basel-Stadt",
    "wof:name":"Inscope Ag",
    "wof:placetype":"venue"
},
  "geometry": {"coordinates":[7.5895819664,47.5448875427],"type":"Point"}
}