{
  "type": "Feature",
  "properties": {
    "iso:country":"CH",
    "sg:address":"Biberstrasse 50",
    "sg:city":"Thayngen",
    "sg:orig_category":"Fachdetailhandel in Verkaufsr\u00e4umen",
    "sg:postcode":"8240",
    "sg:province":"Schaffhausen",
    "wof:name":"Navig-plaisance B\u00fcsser Werner",
    "wof:placetype":"venue"
},
  "geometry": {"coordinates":[8.7052774429,47.750415802],"type":"Point"}
}