{
  "type": "Feature",
  "properties": {
    "iso:country":"CH",
    "sg:address":"Birkenhof 485",
    "sg:city":"Gipf-oberfrick",
    "sg:orig_category":"Haltung von Gefl\u00fcgel",
    "sg:phone":"+41 62 871 12 64",
    "sg:postcode":"5073",
    "sg:province":"Aargau",
    "wof:name":"Benedikt Schmid Gefl\u00fcgelfarm",
    "wof:placetype":"venue"
},
  "geometry": {"coordinates":[8.005399704,47.4999046326],"type":"Point"}
}