{
  "type": "Feature",
  "properties": {
    "iso:country":"CH",
    "sg:address":"Fuchsb\u00fchlstrasse 8",
    "sg:city":"Amriswil",
    "sg:orig_category":"Mechanik Stahl U Leichtmetallbau",
    "sg:phone":"+41 71 411 74 64",
    "sg:postcode":"8580",
    "sg:province":"Thurgau",
    "wof:name":"Zweifel Bruno Metallverarbeitung Ag",
    "wof:placetype":"venue"
},
  "geometry": {"coordinates":[9.2727432251,47.5461769104],"type":"Point"}
}