{
  "type": "Feature",
  "properties": {
    "iso:country":"CH",
    "sg:address":"Wehntalerstrasse 20",
    "sg:city":"Sch\u00f6fflisdorf",
    "sg:orig_category":"Unclassifiable Establishments",
    "sg:postcode":"8165",
    "sg:province":"Z\u00fcrich",
    "wof:name":"Haag Marianne",
    "wof:placetype":"venue"
},
  "geometry": {"coordinates":[7.4548568726,47.1454620361],"type":"Point"}
}