{
  "type": "Feature",
  "properties": {
    "iso:country":"CH",
    "sg:address":"B\u00e4derstrasse 15",
    "sg:city":"Baden",
    "sg:orig_category":"RESTAURANTS: TEA-ROOMS",
    "sg:phone":"+41 56 222 32 09",
    "sg:postcode":"5400",
    "sg:province":"Aargau",
    "wof:name":"Restaurant Chalet K. Nagy",
    "wof:placetype":"venue"
},
  "geometry": {"coordinates":[8.3123941422,47.4795799255],"type":"Point"}
}