{
  "type": "Feature",
  "properties": {
    "iso:country":"CH",
    "sg:address":"Hohle Gasse 38. 3210 Kerzers. Postfach",
    "sg:city":"Kerzers",
    "sg:orig_category":"Non-Classified Establishments",
    "sg:phone":"+41 31 755 73 14",
    "sg:postcode":"3210",
    "sg:province":"Fribourg",
    "wof:name":"Meyer B.",
    "wof:placetype":"venue"
},
  "geometry": {"coordinates":[7.1988449097,46.9724197388],"type":"Point"}
}