{
  "type": "Feature",
  "properties": {
    "iso:country":"CH",
    "sg:address":"Talgutzentrum 38",
    "sg:city":"Ittigen",
    "sg:orig_category":"Institutionen des Sozialwesens ohne Beherbergung",
    "sg:phone":"+41 31 922 18 02",
    "sg:postcode":"3063",
    "sg:province":"Bern",
    "wof:name":"Kinderhilfswerk Adoption International",
    "wof:placetype":"venue"
},
  "geometry": {"coordinates":[7.4822731018,46.9745178223],"type":"Point"}
}