{
  "type": "Feature",
  "properties": {
    "iso:country":"CH",
    "sg:address":"Josefstrasse 146",
    "sg:city":"Z\u00fcrich",
    "sg:classifiers":[
        {
            "category":"Restaurant",
            "type":"Food & Drink"
        }
    ],
    "sg:phone":"+41 12713860",
    "sg:postcode":"8005",
    "sg:province":"Z\u00fcrich",
    "wof:name":"Restaurant Dammburg",
    "wof:placetype":"venue"
},
  "geometry": {"coordinates":[8.5277118683,47.3847465515],"type":"Point"}
}