{
  "type": "Feature",
  "properties": {
    "iso:country":"CH",
    "sg:address":"1187",
    "sg:city":"St-oyens",
    "sg:orig_category":"Landesverteidigung, Sozialversicherung \u00d6ffentliche Verwaltung",
    "sg:phone":"+41 21 828 30 59",
    "sg:postcode":"1187",
    "sg:province":"Vaud",
    "wof:name":"Centre De Protection Civile",
    "wof:placetype":"venue"
},
  "geometry": {"coordinates":[6.296790123,46.4940414429],"type":"Point"}
}