{
  "type": "Feature",
  "properties": {
    "iso:country":"CH",
    "sg:address":"Zielstrasse 38",
    "sg:city":"Appenzell",
    "sg:orig_category":"Cloth Calendars",
    "sg:phone":"+41 71 788 91 11",
    "sg:postcode":"9050",
    "sg:province":"Appenzell Innerhoden",
    "wof:name":"Alba Albin Breitenmoser Ag",
    "wof:placetype":"venue"
},
  "geometry": {"coordinates":[9.407711,47.333954],"type":"Point"}
}