{
  "type": "Feature",
  "properties": {
    "iso:country":"CH",
    "sg:address":"Rue Principale 35",
    "sg:city":"B\u00e9vilard",
    "sg:orig_category":"D\u00e9colletagen and Schrauben Herstellung",
    "sg:phone":"+41 32 968 52 92",
    "sg:postcode":"2735",
    "sg:province":"Bern",
    "wof:name":"Gilbert Bilat & Fils Atelier De D\u00e9colletages",
    "wof:placetype":"venue"
},
  "geometry": {"coordinates":[6.83555,47.115505],"type":"Point"}
}