{
  "type": "Feature",
  "properties": {
    "iso:country":"CH",
    "sg:address":"Wartstrasse 61",
    "sg:city":"Winterthur",
    "sg:orig_category":"Sanit\u00e4r, Heizungs U L\u00fcftungsinstallation",
    "sg:postcode":"8400",
    "sg:province":"Z\u00fcrich",
    "wof:name":"Staub H. Ag",
    "wof:placetype":"venue"
},
  "geometry": {"coordinates":[8.7147006989,47.5032501221],"type":"Point"}
}