{
  "type": "Feature",
  "properties": {
    "iso:country":"CH",
    "sg:address":"Strangstal 301",
    "sg:city":"Linden",
    "sg:orig_category":"Softwareentwicklung U beratung",
    "sg:phone":"+41 31 771 13 81",
    "sg:postcode":"3673",
    "sg:province":"Bern",
    "wof:name":"Andreas Wittwer Buco Support",
    "wof:placetype":"venue"
},
  "geometry": {"coordinates":[7.6660499573,46.851184845],"type":"Point"}
}