{
  "type": "Feature",
  "properties": {
    "iso:country":"CH",
    "sg:address":"Steinstrasse 50 8003 Z\u00fcrich. Postfach",
    "sg:city":"Z\u00fcrich",
    "sg:orig_category":"Non-Classified Establishments",
    "sg:phone":"+41 14621018",
    "sg:postcode":"8001",
    "sg:province":"Z\u00fcrich",
    "wof:name":"Willi M\u00fcller, Mediadienstleistungen",
    "wof:placetype":"venue"
},
  "geometry": {"coordinates":[8.5201272964,47.3668403625],"type":"Point"}
}