{
  "type": "Feature",
  "properties": {
    "addr:full":"Industriestrasse 25 Liestal Basel-Landschaft 4410",
    "addr:housenumber":"25",
    "addr:postcode":"4410",
    "addr:street":"Industriestrasse",
    "iso:country":"CH",
    "sg:address":"Industriestrasse 25",
    "sg:city":"Liestal",
    "sg:orig_category":"Autogaragen",
    "sg:phone":"+41 61 901 33 11",
    "sg:postcode":"4410",
    "sg:province":"Basel-Landschaft",
    "wof:name":"Hans Ehrsam Garage",
    "wof:placetype":"venue"
},
  "geometry": {"coordinates":[7.719817,47.496098],"type":"Point"}
}