{
  "type": "Feature",
  "properties": {
    "iso:country":"CH",
    "sg:address":"Route Du Chaluet 3",
    "sg:city":"Court",
    "sg:classifiers":[
        {
            "category":"Professional",
            "subcategory":"Employment Agencies",
            "type":"Services"
        }
    ],
    "sg:postcode":"2738",
    "sg:province":"Bern",
    "sg:tags":[
        "personal",
        "u",
        "stellenvermittlung"
    ],
    "wof:name":"Icea Service Sa.",
    "wof:placetype":"venue"
},
  "geometry": {"coordinates":[7.3916978836,47.2442054749],"type":"Point"}
}