{
  "type": "Feature",
  "properties": {
    "iso:country":"CH",
    "sg:address":"Waldhof Dachlissen",
    "sg:city":"Mettmenstetten",
    "sg:orig_category":"Finanzierungsinstitutionen",
    "sg:postcode":"8932",
    "sg:province":"Z\u00fcrich",
    "wof:name":"B\u00e4rtsch Arthur, Finanzen & Handel",
    "wof:placetype":"venue"
},
  "geometry": {"coordinates":[8.8171329498,47.2266998291],"type":"Point"}
}