{
  "type": "Feature",
  "properties": {
    "iso:country":"CH",
    "sg:address":"M\u00fchlebachstrasse 51b",
    "sg:city":"Thalwil",
    "sg:orig_category":"Vorschulen, Kinderg\u00e4rten",
    "sg:phone":"+41 17207477",
    "sg:postcode":"8800",
    "sg:province":"Z\u00fcrich",
    "wof:name":"Kindergarten Jennyschloss",
    "wof:placetype":"venue"
},
  "geometry": {"coordinates":[8.565955162,47.2917442322],"type":"Point"}
}