{
  "type": "Feature",
  "properties": {
    "iso:country":"CH",
    "sg:address":"Raggent\u00f6rli 2 6210 Sursee. Postfach",
    "sg:city":"Sursee",
    "sg:orig_category":"Werbevermittlung Werbung",
    "sg:phone":"+41 41 921 51 44",
    "sg:postcode":"6210",
    "sg:province":"Luzern",
    "wof:name":"Werbe-team Ag",
    "wof:placetype":"venue"
},
  "geometry": {"coordinates":[8.1103754044,47.1725883484],"type":"Point"}
}