{
  "type": "Feature",
  "properties": {
    "iso:country":"CH",
    "sg:address":"Steindlerstrasse 44 3800 Unterseen. Postfach Postfach",
    "sg:city":"Interlaken",
    "sg:orig_category":"Kauf U Verkauf von Immobilien auf eigene Rechnung Verwaltung von Immobilien",
    "sg:phone":"+41 33 826 11 11",
    "sg:postcode":"3800",
    "sg:province":"Bern",
    "wof:name":"Regez Ag",
    "wof:placetype":"venue"
},
  "geometry": {"coordinates":[7.8354258537,46.6864929199],"type":"Point"}
}