{
  "type": "Feature",
  "properties": {
    "iso:country":"CH",
    "sg:address":"Route De Pregny 43",
    "sg:city":"Chamb\u00e9sy",
    "sg:orig_category":"Kinderkrippen U horte",
    "sg:phone":"+41 22 758 11 43",
    "sg:postcode":"1292",
    "sg:province":"Gen\u00e8ve",
    "wof:name":"Garderie D'enfants Pitchounets",
    "wof:placetype":"venue"
},
  "geometry": {"coordinates":[6.1436700821,46.2417793274],"type":"Point"}
}