{
  "type": "Feature",
  "properties": {
    "iso:country":"CH",
    "sg:address":"Neugasse 21",
    "sg:city":"Zug",
    "sg:orig_category":"Detailhandel mit Pelzwaren Zurichtung U F\u00e4rben von Fellen, Herstellung von Pelzwaren",
    "sg:phone":"+41 41 711 18 65",
    "sg:postcode":"6300",
    "sg:province":"Zug",
    "wof:name":"Weber August",
    "wof:placetype":"venue"
},
  "geometry": {"coordinates":[8.5157117844,47.1666145325],"type":"Point"}
}