{
  "type": "Feature",
  "properties": {
    "iso:country":"CH",
    "sg:address":"Neuhusweg 2",
    "sg:city":"Richterswil",
    "sg:orig_category":"Unternehmensberatung",
    "sg:phone":"+41 17861207",
    "sg:postcode":"8805",
    "sg:province":"Z\u00fcrich",
    "wof:name":"Management Beratung, Ingo Rothb\u00f6ck",
    "wof:placetype":"venue"
},
  "geometry": {"coordinates":[8.7018671036,47.2057876587],"type":"Point"}
}