{
  "type": "Feature",
  "properties": {
    "iso:country":"CH",
    "sg:address":"Eystrasse 10",
    "sg:city":"Gr\u00fcnen",
    "sg:orig_category":"Druck ohne Zeitungsdruck Offsetdruck",
    "sg:phone":"+41 34 431 19 19",
    "sg:postcode":"3455",
    "sg:province":"Bern",
    "wof:name":"Buch Und Offsetdruck Bo Ag",
    "wof:placetype":"venue"
},
  "geometry": {"coordinates":[7.7440800667,47.0250778198],"type":"Point"}
}