{
  "type": "Feature",
  "properties": {
    "iso:country":"CH",
    "sg:address":"1096 Cully Case Postale 50",
    "sg:city":"Cully",
    "sg:orig_category":"Sportvereine Wassersport Segeln",
    "sg:phone":"+41 21 799 19 17",
    "sg:postcode":"1096",
    "sg:province":"Vaud",
    "wof:name":"Cercle De La Voile Cvmc",
    "wof:placetype":"venue"
},
  "geometry": {"coordinates":[6.7303199768,46.4881858826],"type":"Point"}
}