{
  "type": "Feature",
  "properties": {
    "iso:country":"CH",
    "sg:address":"Ringstrasse 14",
    "sg:city":"Neuenhof",
    "sg:orig_category":"Assembling, Disassembling",
    "sg:phone":"+41 18701014",
    "sg:postcode":"5432",
    "sg:province":"Aargau",
    "wof:name":"Mfs Montagen Ag",
    "wof:placetype":"venue"
},
  "geometry": {"coordinates":[8.330055,47.453495],"type":"Point"}
}