{
  "type": "Feature",
  "properties": {
    "iso:country":"CH",
    "sg:address":"Sonnenhofstrasse 9 8953 Dietikon. Postfach",
    "sg:city":"Dietikon",
    "sg:orig_category":"Informatikschulen Unternehmensberatung",
    "sg:phone":"+41 17406391",
    "sg:postcode":"8953",
    "sg:province":"Z\u00fcrich",
    "wof:name":"Arcara Consulting Gmbh",
    "wof:placetype":"venue"
},
  "geometry": {"coordinates":[8.3958940506,47.4037322998],"type":"Point"}
}