{
  "type": "Feature",
  "properties": {
    "iso:country":"CH",
    "sg:address":"Allmendweg 8 Postfach 6",
    "sg:city":"Zuchwil",
    "sg:classifiers":[
        {
            "category":"Professional",
            "subcategory":"Engineering",
            "type":"Services"
        }
    ],
    "sg:phone":"+41 32 686 11 11",
    "sg:postcode":"4528",
    "sg:province":"Solothurn",
    "sg:tags":[
        "machine",
        "-",
        "mechanical"
    ],
    "wof:name":"Selltex Ag",
    "wof:placetype":"venue"
},
  "geometry": {"coordinates":[-6.2731690407,53.3594474792],"type":"Point"}
}