{
  "type": "Feature",
  "properties": {
    "iso:country":"CH",
    "sg:address":"Oetenbachgasse 13",
    "sg:city":"Z\u00fcrich",
    "sg:orig_category":"Grosshandel mit sonstigen Gebrauchs U Verbrauchsg\u00fctern",
    "sg:phone":"+41 55 266 19 11",
    "sg:postcode":"8001",
    "sg:province":"Z\u00fcrich",
    "wof:name":"Wytor Ag Glenor Kr & Meeresalgen",
    "wof:placetype":"venue"
},
  "geometry": {"coordinates":[8.9390354156,47.2693862915],"type":"Point"}
}