{
  "type": "Feature",
  "properties": {
    "iso:country":"CH",
    "sg:address":"Route De Montcherand",
    "sg:city":"Orbe",
    "sg:orig_category":"Detailhandel mit Bekleidung Detailhandel mit Damenbekleidung",
    "sg:phone":"+41 21 441 84 42",
    "sg:postcode":"1350",
    "sg:province":"Vaud",
    "wof:name":"Besson Mode S\u00e0rl",
    "wof:placetype":"venue"
},
  "geometry": {"coordinates":[6.523019,46.729511],"type":"Point"}
}