{
  "type": "Feature",
  "properties": {
    "iso:country":"CH",
    "sg:address":"Haldenstrasse 5 6340 Baar. Postfach",
    "sg:city":"Baar",
    "sg:orig_category":"Handelsvermittlung von Brennstoffen, Erzen, Metallen U Chemikalien Handelsvermittlung von landwirtsc",
    "sg:phone":"+41 41 768 01 30",
    "sg:postcode":"6340",
    "sg:province":"Zug",
    "wof:name":"Bs Metex Overseas Ltd Rohstoffe; Handel",
    "wof:placetype":"venue"
},
  "geometry": {"coordinates":[8.5383815765,47.1966171265],"type":"Point"}
}