{
  "type": "Feature",
  "properties": {
    "iso:country":"CH",
    "sg:address":"S\u00e4ntisstrasse 10",
    "sg:city":"Flawil",
    "sg:orig_category":"Sportvereine Velo Rad-& Motorfahrer-Bund SRB",
    "sg:phone":"+41 41 660 26 10",
    "sg:postcode":"9230",
    "sg:province":"St. Gallen",
    "wof:name":"Velo-moto-club Alpnach",
    "wof:placetype":"venue"
},
  "geometry": {"coordinates":[8.2790460587,46.9436836243],"type":"Point"}
}