{
  "type": "Feature",
  "properties": {
    "iso:country":"CH",
    "sg:address":"R\u00fctschelengasse 13",
    "sg:city":"Burgdorf",
    "sg:orig_category":"Sportvereine Renn-& Reitsport",
    "sg:phone":"+41 34 413 10 00",
    "sg:postcode":"3400",
    "sg:province":"Bern",
    "wof:name":"Reitverein An Der Unteren Emme",
    "wof:placetype":"venue"
},
  "geometry": {"coordinates":[7.6274180412,47.0555305481],"type":"Point"}
}