{
  "type": "Feature",
  "properties": {
    "iso:country":"CH",
    "sg:address":"Oberer Kanalweg 8",
    "sg:city":"Nidau",
    "sg:orig_category":"Interessenvertretungen",
    "sg:postcode":"2560",
    "sg:province":"Bern",
    "wof:name":"Schweizer Ergosom Verein",
    "wof:placetype":"venue"
},
  "geometry": {"coordinates":[7.235558033,47.1235198975],"type":"Point"}
}