{
  "type": "Feature",
  "properties": {
    "iso:country":"CH",
    "sg:address":"Rue De La Combe-gr\u00e8de 34",
    "sg:city":"Villeret",
    "sg:orig_category":"Erschliessung von Grundst\u00fccken",
    "sg:postcode":"2613",
    "sg:province":"Bern",
    "wof:name":"Les 4 Maisons",
    "wof:placetype":"venue"
},
  "geometry": {"coordinates":[7.0212059021,47.156791687],"type":"Point"}
}