{
  "type": "Feature",
  "properties": {
    "iso:country":"CH",
    "sg:address":"1064 St-cierges. Postfach",
    "sg:city":"Corren\u00e7on",
    "sg:orig_category":"RESTAURANTS: TEA-ROOMS",
    "sg:phone":"+41 21 905 31 26",
    "sg:postcode":"1064",
    "wof:name":"Immordino Michele Caf\u00e9-restaurant Auberge Du Cheval Blanc",
    "wof:placetype":"venue"
},
  "geometry": {"coordinates":[6.7349619865,46.6901321411],"type":"Point"}
}