{
  "type": "Feature",
  "properties": {
    "iso:country":"CH",
    "sg:address":"Zelglistrasse 4",
    "sg:city":"Fehraltorf",
    "sg:orig_category":"Erbringung von Dienstleistungen f\u00fcr Unternehmen",
    "sg:postcode":"8320",
    "sg:province":"Z\u00fcrich",
    "wof:name":"Werbe-service Gmbh Najbr",
    "wof:placetype":"venue"
},
  "geometry": {"coordinates":[8.7564926147,47.3930778503],"type":"Point"}
}