{
  "type": "Feature",
  "properties": {
    "iso:country":"CH",
    "sg:address":"Route De La Gl\u00e2ne 134",
    "sg:city":"Villars-sur-gl\u00e2ne",
    "sg:orig_category":"Instandhaltung U Reparatur von Automobilen",
    "sg:phone":"+41 26 402 20 00",
    "sg:postcode":"1752",
    "sg:province":"Fribourg",
    "wof:name":"Carrosserie Des Daillettes Sa",
    "wof:placetype":"venue"
},
  "geometry": {"coordinates":[7.1362600327,46.7897720337],"type":"Point"}
}