{
  "type": "Feature",
  "properties": {
    "iso:country":"CH",
    "sg:address":"Dorfstrasse 33 8916 Jonen. Postfach",
    "sg:city":"Jonen",
    "sg:orig_category":"Architektur U Ingenieurb\u00fcros",
    "sg:phone":"+41 56 640 20 00",
    "sg:postcode":"8916",
    "sg:province":"Aargau",
    "wof:name":"R\u00dcttimann Architektur",
    "wof:placetype":"venue"
},
  "geometry": {"coordinates":[8.391576,47.295742],"type":"Point"}
}