{
  "type": "Feature",
  "properties": {
    "iso:country":"CH",
    "sg:address":"Spitalstrasse 21",
    "sg:city":"Luzern",
    "sg:classifiers":[
        {
            "category":"Government",
            "subcategory":"Post Office",
            "type":"Public Place"
        }
    ],
    "sg:phone":"+41 55 442 81 61",
    "sg:postcode":"6004",
    "sg:province":"Luzern",
    "sg:tags":[
        "caf\u00e9s",
        "tea-rooms"
    ],
    "wof:name":"Caf\u00e9 Melanie",
    "wof:placetype":"venue"
},
  "geometry": {"coordinates":[8.8507814407,47.1905555725],"type":"Point"}
}