{
  "type": "Feature",
  "properties": {
    "iso:country":"CH",
    "sg:address":"Rue De La Dixence 21",
    "sg:city":"Sion",
    "sg:orig_category":"Elektroinstallation",
    "sg:postcode":"1950",
    "sg:province":"Valais",
    "wof:name":"T\u00e9l\u00e9contact, Weber Claude",
    "wof:placetype":"venue"
},
  "geometry": {"coordinates":[7.3638181686,46.2305030823],"type":"Point"}
}