{
  "type": "Feature",
  "properties": {
    "addr:full":"Rue De Lausanne 8 Morges Vaud 1110",
    "addr:housenumber":"8",
    "addr:postcode":"1110",
    "addr:street":"Rue De Lausanne",
    "iso:country":"CH",
    "sg:address":"Rue De Lausanne 8",
    "sg:city":"Morges",
    "sg:orig_category":"Arztpraxen",
    "sg:phone":"+41 32 913 22 03",
    "sg:postcode":"1110",
    "sg:province":"Vaud",
    "wof:name":"Dr M\u00e9d. Luc Magnanelli M\u00e9decin Sp\u00e9cialiste",
    "wof:placetype":"venue"
},
  "geometry": {"coordinates":[6.82185,47.103214],"type":"Point"}
}