{
  "type": "Feature",
  "properties": {
    "iso:country":"CH",
    "sg:address":"Haus Sch\u00f6negg",
    "sg:city":"Leukerbad",
    "sg:orig_category":"Erbringung von Dienstleistungen f\u00fcr Unternehmen",
    "sg:postcode":"3954",
    "sg:province":"Valais",
    "wof:name":"Jaggy Schriften",
    "wof:placetype":"venue"
},
  "geometry": {"coordinates":[7.6253261566,46.3759307861],"type":"Point"}
}