{
  "type": "Feature",
  "properties": {
    "iso:country":"CH",
    "sg:address":"Carlo Piazzetta San 2",
    "sg:city":"Lugano",
    "sg:orig_category":"Interessenvertretungen",
    "sg:postcode":"6900",
    "sg:province":"Ticino",
    "wof:name":"Fondazione Per I Bambini Del Polo Nord",
    "wof:placetype":"venue"
},
  "geometry": {"coordinates":[8.9586811066,46.0056304932],"type":"Point"}
}