{
  "type": "Feature",
  "properties": {
    "iso:country":"CH",
    "sg:address":"6760",
    "sg:city":"Faido",
    "sg:orig_category":"Reiseb\u00fcros U Reiseveranstalter",
    "sg:phone":"+41 21 960 20 72",
    "sg:postcode":"6760",
    "sg:province":"Ticino",
    "wof:name":"Angeloz Voyages-excursions Sa",
    "wof:placetype":"venue"
},
  "geometry": {"coordinates":[6.9346351624,46.3913116455],"type":"Point"}
}