{
  "type": "Feature",
  "properties": {
    "iso:country":"CH",
    "sg:address":"Wahlackerstrasse 1",
    "sg:city":"Zollikofen",
    "sg:orig_category":"Detailhandel mit Spielwaren Herstellung von Spielwaren",
    "sg:phone":"+41 31 829 05 68",
    "sg:postcode":"3052",
    "sg:province":"Bern",
    "wof:name":"Baur Flugmodelle Gmbh",
    "wof:placetype":"venue"
},
  "geometry": {"coordinates":[7.4563999176,46.9926719666],"type":"Point"}
}