{
  "type": "Feature",
  "properties": {
    "iso:country":"CH",
    "sg:address":"Sonnhaldenstrasse 49",
    "sg:city":"Uster",
    "sg:orig_category":"Grosshandel mit sonstigen Gebrauchs U Verbrauchsg\u00fctern Grosshandel mit sonstigen Maschinen U Ausr\u00fcst",
    "sg:phone":"+41 18215572",
    "sg:postcode":"8610",
    "sg:province":"Z\u00fcrich",
    "wof:name":"Siku-magic Ag",
    "wof:placetype":"venue"
},
  "geometry": {"coordinates":[8.7341842651,47.3406105042],"type":"Point"}
}