{
  "type": "Feature",
  "properties": {
    "iso:country":"CH",
    "sg:address":"Rue Du Lac 12",
    "sg:city":"Gen\u00e8ve",
    "sg:orig_category":"Architektur U Ingenieurb\u00fcros Innenarchitekturb\u00fcros",
    "sg:phone":"+41 22 700 66 33",
    "sg:postcode":"1207",
    "sg:province":"Gen\u00e8ve",
    "wof:name":"Chazalon Oscar S\u00e0rl",
    "wof:placetype":"venue"
},
  "geometry": {"coordinates":[6.157486,46.20396],"type":"Point"}
}