{
  "type": "Feature",
  "properties": {
    "iso:country":"CH",
    "sg:address":"2875",
    "sg:city":"Montfaucon",
    "sg:orig_category":"Architektur U Ingenieurb\u00fcros",
    "sg:phone":"+41 71 757 11 55",
    "sg:postcode":"2875",
    "sg:province":"Jura",
    "wof:name":"G\u00f6ldi + Eggenberger Ag",
    "wof:placetype":"venue"
},
  "geometry": {"coordinates":[9.559074,47.368954],"type":"Point"}
}