{
  "type": "Feature",
  "properties": {
    "iso:country":"CH",
    "sg:address":"Rohrerstrasse 100",
    "sg:city":"Aarau",
    "sg:orig_category":"Gesundheitswesen G\u00fcterbef\u00f6rderung im Strassenverkehr",
    "sg:phone":"+41 41 811 29 46",
    "sg:postcode":"5000",
    "sg:province":"Aargau",
    "wof:name":"Eichhorn Transportdienste Ag Bestattungsinstitut",
    "wof:placetype":"venue"
},
  "geometry": {"coordinates":[8.6360750198,47.0247001648],"type":"Point"}
}