{
  "type": "Feature",
  "properties": {
    "iso:country":"CH",
    "sg:address":"Riehenstrasse 125",
    "sg:city":"Basel",
    "sg:orig_category":"Unternehmensberatung",
    "sg:phone":"+41 61 683 23 15",
    "sg:postcode":"4058",
    "sg:province":"Basel-Stadt",
    "wof:name":"Bilanx Gmbh",
    "wof:placetype":"venue"
},
  "geometry": {"coordinates":[7.6041069031,47.5641746521],"type":"Point"}
}