{
  "type": "Feature",
  "properties": {
    "iso:country":"CH",
    "sg:address":"B\u00fc\u00f6lstrasse 14 6440 Brunnen. Postfach 425",
    "sg:city":"Brunnen",
    "sg:orig_category":"Maler U Glasergewerbe Malerei",
    "sg:phone":"+41 41 820 15 05",
    "sg:postcode":"6440",
    "sg:province":"Schwyz",
    "wof:name":"Norbert Micheletto Malergesch\u00e4ft",
    "wof:placetype":"venue"
},
  "geometry": {"coordinates":[8.6030235291,46.9978752136],"type":"Point"}
}