{
  "type": "Feature",
  "properties": {
    "iso:country":"CH",
    "sg:address":"Steinb\u00e4renstrasse 2 6234 Triengen. Postfach 433",
    "sg:city":"Triengen",
    "sg:orig_category":"Tabakverarbeitung",
    "sg:phone":"+41 79 632 92 82",
    "sg:postcode":"6234",
    "sg:province":"Luzern",
    "wof:name":"F. Fischer Ag Zigarrenfabrik",
    "wof:placetype":"venue"
},
  "geometry": {"coordinates":[8.0763225555,47.2387428284],"type":"Point"}
}