{
  "type": "Feature",
  "properties": {
    "iso:country":"CH",
    "sg:address":"Route Du Burenoz 37",
    "sg:city":"Belmont-lausanne",
    "sg:orig_category":"Kinderkrippen U horte",
    "sg:phone":"+41 21 729 56 33",
    "sg:postcode":"1092",
    "sg:province":"Vaud",
    "wof:name":"Garderies D'enfants Les Guignols",
    "wof:placetype":"venue"
},
  "geometry": {"coordinates":[6.6730031967,46.5208091736],"type":"Point"}
}