{
  "type": "Feature",
  "properties": {
    "iso:country":"CH",
    "sg:address":"Route Des Charmilles 30 1963 V\u00e9troz. Postfach",
    "sg:city":"V\u00e9troz",
    "sg:orig_category":"Blumen U Zierpflanzenbau Detailhandel mit Blumen U Pflanzen",
    "sg:phone":"+41 27 346 15 14",
    "sg:postcode":"1963",
    "sg:province":"Valais",
    "wof:name":"Bruno Terrettaz",
    "wof:placetype":"venue"
},
  "geometry": {"coordinates":[7.289328,46.219223],"type":"Point"}
}