{
  "type": "Feature",
  "properties": {
    "iso:country":"CH",
    "sg:address":"Keltenweg 10",
    "sg:city":"Steinhausen",
    "sg:orig_category":"Vermittlung von Immobilien",
    "sg:phone":"+41 41 741 12 75",
    "sg:postcode":"6312",
    "sg:province":"Zug",
    "wof:name":"Eduard Baumann Immobilien",
    "wof:placetype":"venue"
},
  "geometry": {"coordinates":[8.4796733856,47.1984863281],"type":"Point"}
}