{
  "type": "Feature",
  "properties": {
    "iso:country":"CH",
    "sg:address":"Stauffacherstrasse 19",
    "sg:city":"Schaffhausen",
    "sg:orig_category":"Malerei",
    "sg:phone":"+41 32 353 73 67",
    "sg:postcode":"8200",
    "sg:province":"Schaffhausen",
    "wof:name":"Urs Winist\u00f6rfer Malerei",
    "wof:placetype":"venue"
},
  "geometry": {"coordinates":[7.4066982269,47.1518630981],"type":"Point"}
}