{
  "type": "Feature",
  "properties": {
    "iso:country":"CH",
    "sg:address":"Bielstrasse 40a",
    "sg:city":"Aarberg",
    "sg:orig_category":"Grosshandel mit festen Brennstoffen U Mineral\u00f6lerzeugnissen",
    "sg:phone":"+41 32 392 62 17",
    "sg:postcode":"3270",
    "sg:province":"Bern",
    "wof:name":"K\u00f6nig Andr\u00e9",
    "wof:placetype":"venue"
},
  "geometry": {"coordinates":[7.2678332329,47.0477333069],"type":"Point"}
}