{
  "type": "Feature",
  "properties": {
    "iso:country":"CH",
    "sg:address":"H\u00f6heweg 2",
    "sg:city":"Interlaken",
    "sg:classifiers":[
        {
            "category":"Insurance",
            "subcategory":"Insurance Agent",
            "type":"Services"
        }
    ],
    "sg:phone":"+41 91 647 38 88",
    "sg:postcode":"3800",
    "sg:province":"Bern",
    "sg:tags":[
        "versicherungsagenturen",
        "-broker"
    ],
    "wof:name":"Nazionale Svizzera Assicuraz. Agenzia Antonio Sanguin",
    "wof:placetype":"venue"
},
  "geometry": {"coordinates":[8.9354667664,45.8560752869],"type":"Point"}
}