{
  "type": "Feature",
  "properties": {
    "iso:country":"CH",
    "sg:address":"Stadtturmstrasse 18",
    "sg:city":"Baden",
    "sg:orig_category":"Softwareentwicklung U beratung",
    "sg:phone":"+41 71 244 12 51",
    "sg:postcode":"5400",
    "sg:province":"Aargau",
    "wof:name":"Samac Software-produkte Ag Software; Herst, Vermarktung, Vertrieb",
    "wof:placetype":"venue"
},
  "geometry": {"coordinates":[9.3865833282,47.4341926575],"type":"Point"}
}