{
  "type": "Feature",
  "properties": {
    "iso:country":"CH",
    "sg:address":"Zentrum 8",
    "sg:city":"Hombrechtikon",
    "sg:orig_category":"Grosshandel mit Nahrungsmitteln, Getr\u00e4nken U Tabakwaren ohne ausgepr\u00e4gten Schwerpunkt",
    "sg:phone":"+41 55 210 55 17",
    "sg:postcode":"8634",
    "sg:province":"Z\u00fcrich",
    "wof:name":"Denner Satellit, S. Eugster & Co",
    "wof:placetype":"venue"
},
  "geometry": {"coordinates":[8.7686328888,47.2520141602],"type":"Point"}
}