{
  "type": "Feature",
  "properties": {
    "iso:country":"CH",
    "sg:address":"Garnmarkt 1",
    "sg:city":"Winterthur",
    "sg:orig_category":"Detailhandel mit Bekleidung Detailhandel mit Damenbekleidung",
    "sg:phone":"+41 52 212 24 23",
    "sg:postcode":"8400",
    "sg:province":"Z\u00fcrich",
    "wof:name":"Boutique Metzggasse 16 Mode & Geschenke",
    "wof:placetype":"venue"
},
  "geometry": {"coordinates":[8.728013,47.498806],"type":"Point"}
}