{
  "type": "Feature",
  "properties": {
    "iso:country":"CH",
    "sg:address":"Bahnhofstrasse 2 4322 Mumpf. Postfach 20",
    "sg:city":"Mumpf",
    "sg:orig_category":"Instandhaltung U Reparatur von Automobilen",
    "sg:phone":"+41 56 664 21 24",
    "sg:postcode":"4322",
    "sg:province":"Aargau",
    "wof:name":"Garage Werner Iten Ag",
    "wof:placetype":"venue"
},
  "geometry": {"coordinates":[8.3174819946,47.2825775146],"type":"Point"}
}