{
  "type": "Feature",
  "properties": {
    "addr:full":"Winkelriedstrasse 19 Schaffhausen Schaffhausen 8200",
    "addr:housenumber":"19",
    "addr:postcode":"8200",
    "addr:street":"Winkelriedstrasse",
    "iso:country":"CH",
    "sg:address":"Winkelriedstrasse 19",
    "sg:city":"Schaffhausen",
    "sg:orig_category":"Arbeitnehmerverb\u00e4nde",
    "sg:phone":"+41 56 622 60 69",
    "sg:postcode":"8200",
    "sg:province":"Schaffhausen",
    "wof:name":"Schweiz.typograph.vereinigung Sektion Aarau,herrn Nic Keel",
    "wof:placetype":"venue"
},
  "geometry": {"coordinates":[8.274423,47.350098],"type":"Point"}
}