{
  "type": "Feature",
  "properties": {
    "iso:country":"CH",
    "sg:address":"Rue Du Moulin 4",
    "sg:city":"Montagne-moutier",
    "sg:orig_category":"Fotografisches Gewerbe U fotografische Laboratorien",
    "sg:postcode":"2740",
    "sg:province":"Bern",
    "wof:name":"Crea Aldo.",
    "wof:placetype":"venue"
},
  "geometry": {"coordinates":[7.3702259064,47.2784347534],"type":"Point"}
}