{
  "type": "Feature",
  "properties": {
    "iso:country":"CH",
    "sg:address":"Avenue De France 6 1950 Sion. Postfach 148",
    "sg:city":"Sion",
    "sg:orig_category":"Zahnarztpraxen",
    "sg:phone":"+41 21 923 52 20",
    "sg:postcode":"1951",
    "sg:province":"Valais",
    "wof:name":"Drs M\u00e9d.dent. Briaux & Bischof M\u00e9decins-dentistes",
    "wof:placetype":"venue"
},
  "geometry": {"coordinates":[5.1808700562,45.8973388672],"type":"Point"}
}