{
  "type": "Feature",
  "properties": {
    "iso:country":"CH",
    "sg:address":"Route De Malagny 22 1294 Creux-de-genthod. Postfach",
    "sg:city":"Creux-de-genthod",
    "sg:orig_category":"Vermietung U Verpachtung von eigenen Immobilien",
    "sg:postcode":"1294",
    "sg:province":"Gen\u00e8ve",
    "wof:name":"Chrono Immobilier Sa Immeubles Etc",
    "wof:placetype":"venue"
},
  "geometry": {"coordinates":[6.1585488319,46.2686042786],"type":"Point"}
}