{
  "type": "Feature",
  "properties": {
    "iso:country":"CH",
    "sg:address":"4803",
    "sg:city":"Vordemwald",
    "sg:orig_category":"Schulpflegen",
    "sg:postcode":"4803",
    "sg:province":"Aargau",
    "wof:name":"Schulpflege Der Gemeinde Walde",
    "wof:placetype":"venue"
},
  "geometry": {"coordinates":[8.1105499268,47.2613601685],"type":"Point"}
}