{
  "type": "Feature",
  "properties": {
    "iso:country":"CH",
    "sg:address":"Tannenweg 17 3700 Spiez. Postfach",
    "sg:city":"Liebefeld",
    "sg:orig_category":"Softwareentwicklung U beratung",
    "sg:phone":"+41 31 971 41 30",
    "sg:postcode":"3097",
    "sg:province":"Bern",
    "wof:name":"Pro Informatik Organisations Ag",
    "wof:placetype":"venue"
},
  "geometry": {"coordinates":[7.6891851425,46.6859016418],"type":"Point"}
}