{
  "type": "Feature",
  "properties": {
    "iso:country":"CH",
    "sg:address":"Brandschenkestrasse 10",
    "sg:city":"Z\u00fcrich",
    "sg:orig_category":"Aktivit\u00e4t der Bankinstitute Kreditinstitute ohne Spezialkreditinstitute",
    "sg:phone":"+41 22 738 93 22",
    "sg:postcode":"8002",
    "sg:province":"Z\u00fcrich",
    "wof:name":"Banco Santander Central Hispano (suisse) Sa",
    "wof:placetype":"venue"
},
  "geometry": {"coordinates":[6.146119,46.208347],"type":"Point"}
}