{
  "type": "Feature",
  "properties": {
    "iso:country":"CH",
    "sg:address":"Route Du Bois De Finges 2c",
    "sg:city":"Sierre",
    "sg:classifiers":[
        {
            "category":"Insurance",
            "subcategory":"Insurance Agent",
            "type":"Services"
        }
    ],
    "sg:phone":"+41 27 455 35 85",
    "sg:postcode":"3960",
    "sg:province":"Valais",
    "sg:tags":[
        "versicherungsagenturen",
        "-broker"
    ],
    "wof:name":"Philippe Badoux Conseils En Assurances Fortuna",
    "wof:placetype":"venue"
},
  "geometry": {"coordinates":[7.5448031425,46.2963600159],"type":"Point"}
}