{
  "type": "Feature",
  "properties": {
    "iso:country":"CH",
    "sg:address":"Rengglochstrasse 29",
    "sg:city":"Obernau",
    "sg:orig_category":"Baugewerbe",
    "sg:phone":"+41 41 250 23 50",
    "sg:postcode":"6012",
    "sg:province":"Luzern",
    "wof:name":"Giger Montagen",
    "wof:placetype":"venue"
},
  "geometry": {"coordinates":[8.255031,47.033382],"type":"Point"}
}