{
  "type": "Feature",
  "properties": {
    "iso:country":"CH",
    "sg:address":"Hauptstrasse",
    "sg:city":"Kandersteg",
    "sg:orig_category":"Kantonalbanken",
    "sg:phone":"+41 33 675 15 48",
    "sg:postcode":"3718",
    "sg:province":"Bern",
    "wof:name":"Berner Kantonalbank Bekb/bcbe",
    "wof:placetype":"venue"
},
  "geometry": {"coordinates":[7.6641669273,46.4781723022],"type":"Point"}
}