{
  "type": "Feature",
  "properties": {
    "iso:country":"CH",
    "sg:address":"Ruelle Des Arcades 2. 1470 Estavayer-le-lac. Postfach",
    "sg:city":"Estavayer-le-lac",
    "sg:orig_category":"Pensionskassen",
    "sg:postcode":"1470",
    "sg:province":"Fribourg",
    "wof:name":"Fondation De Pr\u00e9voyance En Faveur Du Personnel De J.v. Chanez - R. Diserens Sa \u00e0 Estavayer-le-lac, R. Diserens - J.v. Chanez Sa \u00e0 Payerne, J.p. Crotti, R. Diserens & J.v. Chanez Sa \u00e0 Moudon.",
    "wof:placetype":"venue"
},
  "geometry": {"coordinates":[6.847661972,46.8500137329],"type":"Point"}
}