{
  "type": "Feature",
  "properties": {
    "iso:country":"CH",
    "sg:address":"B\u00fcntenmatt 15",
    "sg:city":"Sarnen",
    "sg:orig_category":"Arbeitnehmerverb\u00e4nde",
    "sg:phone":"+41 41 661 03 22",
    "sg:postcode":"6060",
    "sg:province":"Obwalden",
    "wof:name":"Schweiz.eisenbahn-& Verkehrs- Personal-verb.unterverb.arbeit",
    "wof:placetype":"venue"
},
  "geometry": {"coordinates":[8.252271,46.899349],"type":"Point"}
}