{
  "type": "Feature",
  "properties": {
    "iso:country":"CH",
    "sg:address":"Rue Des Platanes 9 1958 St-l\u00e9onard. Postfach",
    "sg:city":"St-l\u00e9onard",
    "sg:orig_category":"Stukkateurgewerbe, Gipserei U Verputzerei",
    "sg:postcode":"1958",
    "sg:province":"Valais",
    "wof:name":"Lathion Dominique",
    "wof:placetype":"venue"
},
  "geometry": {"coordinates":[7.41705513,46.2537384033],"type":"Point"}
}