{
  "type": "Feature",
  "properties": {
    "addr:full":"Route Du Faubourg 13 Avenches Vaud 1580",
    "addr:housenumber":"13",
    "addr:postcode":"1580",
    "addr:street":"Route Du Faubourg",
    "iso:country":"CH",
    "sg:address":"Route Du Faubourg 13",
    "sg:city":"Avenches",
    "sg:orig_category":"Benzin, Heiz\u00f6l and Mineral\u00f6lprodukte Grosshandel Tankstellen",
    "sg:phone":"+41 26 675 24 78",
    "sg:postcode":"1580",
    "sg:province":"Vaud",
    "wof:name":"Agip (suisse) Sa",
    "wof:placetype":"venue"
},
  "geometry": {"coordinates":[7.044045,46.879623],"type":"Point"}
}