{
  "type": "Feature",
  "properties": {
    "iso:country":"CH",
    "sg:address":"Via Pocobelli 8 6900 Lugano. Postfach Caselle Postale 10",
    "sg:city":"Lugano",
    "sg:orig_category":"Herstellung von sonstigen Metallwaren Mechanische Werkst\u00e4tten",
    "sg:phone":"+41 22 300 21 31",
    "sg:postcode":"6903",
    "sg:province":"Ticino",
    "wof:name":"Vaucher Pascal Vincent Sa",
    "wof:placetype":"venue"
},
  "geometry": {"coordinates":[6.1354060173,46.1796722412],"type":"Point"}
}