{
  "type": "Feature",
  "properties": {
    "iso:country":"CH",
    "sg:address":"R. Beauregard 5 Case Postale 92",
    "sg:city":"Peseux",
    "sg:classifiers":[
        {
            "category":"Wholesale",
            "subcategory":"Machinery & Supplies",
            "type":"Manufacturing & Wholesale Goods"
        }
    ],
    "sg:phone":"+41 32 486 90 00",
    "sg:postcode":"2034",
    "sg:province":"Neuch\u00e2tel",
    "sg:tags":[
        "equipment",
        "equipement",
        "precision",
        "timekeeping"
    ],
    "wof:name":"Soprod Sa",
    "wof:placetype":"venue"
},
  "geometry": {"coordinates":[7.08335495,47.2246208191],"type":"Point"}
}