{
  "type": "Feature",
  "properties": {
    "iso:country":"CH",
    "sg:address":"Pal. Darani 2 6760 Faido. Postfach",
    "sg:city":"Faido",
    "sg:orig_category":"Reiseb\u00fcros U Reiseveranstalter",
    "sg:postcode":"6760",
    "sg:province":"Ticino",
    "wof:name":"Hradec Sa",
    "wof:placetype":"venue"
},
  "geometry": {"coordinates":[7.1587119102,46.3500404358],"type":"Point"}
}