{
  "type": "Feature",
  "properties": {
    "iso:country":"CH",
    "sg:address":"Seestrasse",
    "sg:city":"St\u00e4fa",
    "sg:orig_category":"Detailhandel mit Zeitungen U Zeitschriften Kioske",
    "sg:phone":"+41 19262125",
    "sg:postcode":"8712",
    "sg:province":"Z\u00fcrich",
    "wof:name":"Strandbad Lattenberg",
    "wof:placetype":"venue"
},
  "geometry": {"coordinates":[8.719502449,47.2390480042],"type":"Point"}
}