{
  "type": "Feature",
  "properties": {
    "iso:country":"CH",
    "sg:address":"Rohrhaldenstrasse 18",
    "sg:city":"St\u00e4fa",
    "sg:orig_category":"Herstellung von Duft U K\u00f6rperpflegemitteln",
    "sg:phone":"+41 19268300",
    "sg:postcode":"8712",
    "sg:province":"Z\u00fcrich",
    "wof:name":"Extrabelle Meissner H.",
    "wof:placetype":"venue"
},
  "geometry": {"coordinates":[8.7395000458,47.2354011536],"type":"Point"}
}