{
  "type": "Feature",
  "properties": {
    "iso:country":"CH",
    "sg:address":"3904 Naters. Postfach",
    "sg:city":"Naters",
    "sg:orig_category":"Verwertung von Milch",
    "sg:postcode":"3904",
    "sg:province":"Valais",
    "wof:name":"Sennereigenossenschaft Auslikon/unter-balm",
    "wof:placetype":"venue"
},
  "geometry": {"coordinates":[8.7815437317,47.3674468994],"type":"Point"}
}