{
  "type": "Feature",
  "properties": {
    "iso:country":"CH",
    "sg:address":"Bachstrasse 2",
    "sg:city":"Lenzburg",
    "sg:orig_category":"Unclassifiable Establishments",
    "sg:postcode":"5600",
    "sg:province":"Aargau",
    "wof:name":"Immo Torfeld Ag",
    "wof:placetype":"venue"
},
  "geometry": {"coordinates":[8.1763782501,47.3879089355],"type":"Point"}
}