{
  "type": "Feature",
  "properties": {
    "iso:country":"CH",
    "sg:address":"Kernstrasse 8",
    "sg:city":"Z\u00fcrich",
    "sg:orig_category":"Advokaturb\u00fcros",
    "sg:phone":"+41 12410259",
    "sg:postcode":"8004",
    "sg:province":"Z\u00fcrich",
    "wof:name":"Adrian Bl\u00e4ttler Advokaturb\u00fcro",
    "wof:placetype":"venue"
},
  "geometry": {"coordinates":[8.523814,47.375088],"type":"Point"}
}