{
  "type": "Feature",
  "properties": {
    "iso:country":"CH",
    "sg:address":"Bammattenweg 15",
    "sg:city":"Naters",
    "sg:orig_category":"Architektur U Ingenieurb\u00fcros Architekturb\u00fcros",
    "sg:phone":"+41 27 923 84 18",
    "sg:postcode":"3904",
    "sg:province":"Valais",
    "wof:name":"Robert Baum Architekturb\u00fcro",
    "wof:placetype":"venue"
},
  "geometry": {"coordinates":[7.999325,46.328537],"type":"Point"}
}