{
  "type": "Feature",
  "properties": {
    "iso:country":"CH",
    "sg:address":"Aeussere Poststrasse 7050 Arosa. Postfach 84",
    "sg:city":"Arosa",
    "sg:orig_category":"Detailhandel mit Bekleidung Detailhandel mit Damenbekleidung",
    "sg:phone":"+41 81 377 25 26",
    "sg:postcode":"7050",
    "sg:province":"Graubunden",
    "wof:name":"Boutique Jelen Urs Ag",
    "wof:placetype":"venue"
},
  "geometry": {"coordinates":[9.683255,46.783165],"type":"Point"}
}