{
  "type": "Feature",
  "properties": {
    "iso:country":"CH",
    "sg:address":"Sch\u00fcrgistrasse 78 8000 Z\u00fcrich. Postfach",
    "sg:city":"Z\u00fcrich",
    "sg:orig_category":"Sonstiger Grosshandel",
    "sg:postcode":"8051",
    "sg:province":"Z\u00fcrich",
    "wof:name":"Fl\u00fcckiger Z. Export - Import",
    "wof:placetype":"venue"
},
  "geometry": {"coordinates":[8.5785140991,47.4085502625],"type":"Point"}
}