{
  "type": "Feature",
  "properties": {
    "iso:country":"CH",
    "sg:address":"Bodenacherstrasse 47",
    "sg:city":"Benglen",
    "sg:orig_category":"Vereine Gemeinn\u00fctzige",
    "sg:phone":"+41 18252655",
    "sg:postcode":"8121",
    "sg:province":"Z\u00fcrich",
    "wof:name":"Elterngemeinschaft F\u00e4llanden",
    "wof:placetype":"venue"
},
  "geometry": {"coordinates":[8.6373748779,47.3624076843],"type":"Point"}
}