{
  "type": "Feature",
  "properties": {
    "iso:country":"CH",
    "sg:address":"Chemin Du Taulard 18",
    "sg:city":"Romanel-s-lausanne",
    "sg:orig_category":"G\u00fcterbef\u00f6rderung im Strassenverkehr",
    "sg:phone":"+41 34 445 45 70",
    "sg:postcode":"1032",
    "sg:province":"Vaud",
    "wof:name":"Alfred Tanner Umz\u00fcge",
    "wof:placetype":"venue"
},
  "geometry": {"coordinates":[7.5774970055,47.0893592834],"type":"Point"}
}