{
  "type": "Feature",
  "properties": {
    "iso:country":"CH",
    "sg:address":"Ohne Domizil",
    "sg:city":"Baar",
    "sg:orig_category":"Sonstige Kultur U Unterhaltungseinrichtungen",
    "sg:phone":"+41 79 209 27 54",
    "sg:postcode":"6340",
    "sg:province":"Zug",
    "wof:name":"Verein F\u00fcr Jugendarbeit K\u00f6niz (vfjk)",
    "wof:placetype":"venue"
},
  "geometry": {"coordinates":[7.4159798622,46.9093437195],"type":"Point"}
}