{
  "type": "Feature",
  "properties": {
    "iso:country":"CH",
    "sg:address":"Kr\u00f6nleinstrasse 34",
    "sg:city":"Z\u00fcrich",
    "sg:orig_category":"Allgemeiner Hoch U Tiefbau",
    "sg:postcode":"8044",
    "sg:province":"Z\u00fcrich",
    "wof:name":"Steudler Werner",
    "wof:placetype":"venue"
},
  "geometry": {"coordinates":[8.20254,46.737251],"type":"Point"}
}