{
  "type": "Feature",
  "properties": {
    "iso:country":"CH",
    "sg:address":"Eierbachstrasse 1",
    "sg:city":"Niederhasli",
    "sg:orig_category":"Herstellung von Duft U K\u00f6rperpflegemitteln Technische, physikalische U chemische Untersuchung",
    "sg:phone":"+41 21 635 55 82",
    "sg:postcode":"8155",
    "sg:province":"Z\u00fcrich",
    "wof:name":"Laboratoire Sanoflore Sa",
    "wof:placetype":"venue"
},
  "geometry": {"coordinates":[6.5861711502,46.5446662903],"type":"Point"}
}