{
  "type": "Feature",
  "properties": {
    "addr:full":"Gasterstrasse 4 Sch\u00e4nis St. Gallen 8718",
    "addr:housenumber":"4;st.",
    "addr:postcode":"8718",
    "addr:street":"Gasterstrasse",
    "iso:country":"CH",
    "sg:address":"Gasterstrasse 4",
    "sg:city":"Sch\u00e4nis",
    "sg:orig_category":"Dachdeckerei Zimmerei, Dachdeckerei, Bauspenglerei U Abdichtung",
    "sg:phone":"+41 55 615 12 40",
    "sg:postcode":"8718",
    "sg:province":"St. Gallen",
    "wof:name":"Roth Ag, Bedachungen, Spenglerei",
    "wof:placetype":"venue"
},
  "geometry": {"coordinates":[9.049805,47.162418],"type":"Point"}
}