{
  "type": "Feature",
  "properties": {
    "iso:country":"CH",
    "sg:address":"B\u00fcrerweg 4 9245 Oberb\u00fcren. Postfach",
    "sg:city":"Oberb\u00fcren",
    "sg:orig_category":"Sonstiger spezialisierter Hoch U Tiefbau",
    "sg:postcode":"9245",
    "sg:province":"St. Gallen",
    "wof:name":"Roth Ger\u00fcste Ag",
    "wof:placetype":"venue"
},
  "geometry": {"coordinates":[9.1568565369,47.4477729797],"type":"Point"}
}