{
  "type": "Feature",
  "properties": {
    "iso:country":"CH",
    "sg:address":"R\u00f6merstrasse 195",
    "sg:city":"Stadel(winterthur)",
    "sg:orig_category":"Architektur U Ingenieurb\u00fcros",
    "sg:phone":"+41 52 243 17 16",
    "sg:postcode":"8404",
    "sg:province":"Z\u00fcrich",
    "wof:name":"Vogt & Partner",
    "wof:placetype":"venue"
},
  "geometry": {"coordinates":[8.758223,47.506569],"type":"Point"}
}