{
  "type": "Feature",
  "properties": {
    "addr:full":"Rue De Monthoux 8 Gen\u00e8ve Gen\u00e8ve 1201",
    "addr:housenumber":"8",
    "addr:postcode":"1201",
    "addr:street":"Rue De Monthoux",
    "iso:country":"CH",
    "sg:address":"Rue De Monthoux 8",
    "sg:city":"Gen\u00e8ve",
    "sg:classifiers":[
        {
            "category":"Bars & Pubs",
            "type":"Food & Drink"
        }
    ],
    "sg:phone":"+41 22 732 74 73",
    "sg:postcode":"1201",
    "sg:province":"Gen\u00e8ve",
    "wof:name":"Grand Duke Pub",
    "wof:placetype":"venue"
},
  "geometry": {"coordinates":[6.149463,46.21035],"type":"Point"}
}