{
  "type": "Feature",
  "properties": {
    "iso:country":"CH",
    "sg:address":"Aarbergergasse 29",
    "sg:city":"Bern",
    "sg:orig_category":"Sonstiges Versicherungsgewerbe",
    "sg:phone":"+41 31261313",
    "sg:postcode":"3011",
    "sg:province":"Bern",
    "wof:name":"Generalagentur Martin Bichsel Allianz Suisse",
    "wof:placetype":"venue"
},
  "geometry": {"coordinates":[7.4427080154,46.949546814],"type":"Point"}
}