{
  "type": "Feature",
  "properties": {
    "addr:full":"Ruchstuckstrasse 14 Br\u00fcttisellen Z\u00fcrich 8306",
    "addr:housenumber":"14",
    "addr:postcode":"8306",
    "addr:street":"Ruchstuckstrasse;Zuerich",
    "iso:country":"CH",
    "sg:address":"Ruchstuckstrasse 14",
    "sg:city":"Br\u00fcttisellen",
    "sg:orig_category":"Architektur U Ingenieurb\u00fcros",
    "sg:phone":"+41 18884110",
    "sg:postcode":"8306",
    "sg:province":"Z\u00fcrich",
    "wof:name":"Hirmann G., Institut F\u00fcr Digitalmechanik",
    "wof:placetype":"venue"
},
  "geometry": {"coordinates":[8.629735,47.418034],"type":"Point"}
}