{
  "type": "Feature",
  "properties": {
    "iso:country":"CH",
    "sg:address":"Ch. Des Cigales",
    "sg:city":"St-l\u00e9onard",
    "sg:orig_category":"Sanit\u00e4r, Heizungs U L\u00fcftungsinstallation",
    "sg:postcode":"1958",
    "sg:province":"Valais",
    "wof:name":"Energies Syst\u00e8mes, Delalay Bertrand",
    "wof:placetype":"venue"
},
  "geometry": {"coordinates":[7.4277591705,46.2549972534],"type":"Point"}
}