{
  "type": "Feature",
  "properties": {
    "iso:country":"CH",
    "sg:address":"Via Angelo Maspoli 18",
    "sg:city":"Mendrisio",
    "sg:orig_category":"Detailhandel mit Beleuchtungs U Haushaltsgegenst\u00e4nden Detailhandel mit Textilien",
    "sg:phone":"+41 91 646 84 46",
    "sg:postcode":"6850",
    "sg:province":"Ticino",
    "wof:name":"Glb Sagl Negozio Home Store",
    "wof:placetype":"venue"
},
  "geometry": {"coordinates":[8.978729,45.875259],"type":"Point"}
}