{
  "type": "Feature",
  "properties": {
    "iso:country":"CH",
    "sg:address":"Sonnenbergstrasse 4a",
    "sg:city":"Jona",
    "sg:orig_category":"Detektivb\u00fcros U \u00dcberwachung",
    "sg:postcode":"8645",
    "sg:province":"St. Gallen",
    "wof:name":"Schuler Mobile Security",
    "wof:placetype":"venue"
},
  "geometry": {"coordinates":[8.8208389282,47.2420692444],"type":"Point"}
}