{
  "type": "Feature",
  "properties": {
    "iso:country":"CH",
    "sg:address":"Poststrasse 3",
    "sg:city":"Humlikon",
    "sg:orig_category":"Architektur U Ingenieurb\u00fcros Herstellung von Wellpapier U pappe sowie von Verpackungsmitteln aus Pap",
    "sg:phone":"+41 17604386",
    "sg:postcode":"8457",
    "sg:province":"Z\u00fcrich",
    "wof:name":"Profena Ag",
    "wof:placetype":"venue"
},
  "geometry": {"coordinates":[8.444665,47.271519],"type":"Point"}
}