{
  "type": "Feature",
  "properties": {
    "iso:country":"CH",
    "sg:address":"Bachwiesenstrasse 1",
    "sg:city":"W\u00fcrenlos",
    "sg:classifiers":[
        {
            "category":"Utilities",
            "subcategory":"Natural Gas",
            "type":"Services"
        }
    ],
    "sg:phone":"+41 56 424 13 66",
    "sg:postcode":"5436",
    "sg:province":"Aargau",
    "sg:tags":[
        "fluorescent",
        "lamp",
        "illuminant"
    ],
    "wof:name":"Minilux Ag",
    "wof:placetype":"venue"
},
  "geometry": {"coordinates":[8.3628168106,47.4418067932],"type":"Point"}
}