{
  "type": "Feature",
  "properties": {
    "iso:country":"CH",
    "sg:address":"Rue Centrale 43 1880 Bex Case Postale 335",
    "sg:city":"Bex",
    "sg:orig_category":"Fachdetailhandel mit pharmazeutischen Produkten",
    "sg:phone":"+41 24 463 16 24",
    "sg:postcode":"1880",
    "sg:province":"Vaud",
    "wof:name":"Bulliard Eric",
    "wof:placetype":"venue"
},
  "geometry": {"coordinates":[7.0159568787,46.250202179],"type":"Point"}
}