{
  "type": "Feature",
  "properties": {
    "iso:country":"CH",
    "sg:address":"Au Praz 1695 Rueyres-st-laurent. Postfach",
    "sg:city":"Rueyres-st-laurent",
    "sg:orig_category":"Handels-H\u00e4user U Gesellschaften",
    "sg:postcode":"1695",
    "sg:province":"Fribourg",
    "wof:name":"Yelfind Limited, \u00e0 Dublin (irlande), Succursale De Villarsel-le-gibloux Articles; Production, Cr\u00e9ation, Importation, Exportation, Achat, Vente En Gros Et En D\u00e9tail Etc",
    "wof:placetype":"venue"
},
  "geometry": {"coordinates":[7.0330882072,46.7155151367],"type":"Point"}
}