{
  "type": "Feature",
  "properties": {
    "iso:country":"CH",
    "sg:address":"Marktgasse 46",
    "sg:city":"Langenthal",
    "sg:orig_category":"Zahntechnische Laboratorien",
    "sg:phone":"+41 62 922 06 68",
    "sg:postcode":"4900",
    "sg:province":"Bern",
    "wof:name":"Reto Stupan Zahntechnisches Labor",
    "wof:placetype":"venue"
},
  "geometry": {"coordinates":[7.7880511284,47.2106666565],"type":"Point"}
}