{
  "type": "Feature",
  "properties": {
    "iso:country":"CH",
    "sg:address":"Moudon Route De 1",
    "sg:city":"Echallens",
    "sg:orig_category":"Instandhaltung U Reparatur von Automobilen",
    "sg:phone":"+41 21 883 02 50",
    "sg:postcode":"1040",
    "sg:province":"Vaud",
    "wof:name":"D\u00e9pannages 2000 Plus, Hegi Pierre",
    "wof:placetype":"venue"
},
  "geometry": {"coordinates":[6.6343631744,46.6408653259],"type":"Point"}
}