{
  "type": "Feature",
  "properties": {
    "addr:full":"Gruy\u00e8re Route De La 8 Marly Fribourg 1723",
    "addr:housenumber":"8",
    "addr:postcode":"1723",
    "addr:street":"Route De La",
    "iso:country":"CH",
    "sg:address":"Gruy\u00e8re Route De La 8",
    "sg:city":"Marly",
    "sg:orig_category":"Allgemeiner Hoch U Tiefbau",
    "sg:postcode":"1723",
    "sg:province":"Fribourg",
    "wof:name":"H\u00fcppi Ag Zweigniederlassung Pf\u00e4ffikon Sz",
    "wof:placetype":"venue"
},
  "geometry": {"coordinates":[8.778135,47.201378],"type":"Point"}
}