{
  "type": "Feature",
  "properties": {
    "iso:country":"CH",
    "sg:address":"Hauptstrasse 13",
    "sg:city":"Oensingen",
    "sg:orig_category":"Wirtschaftsverb\u00e4nde Gewerbeverb\u00e4nde/-vereine",
    "sg:phone":"+41 19291667",
    "sg:postcode":"4702",
    "sg:province":"Solothurn",
    "wof:name":"Gewerbeverein Oetwil Am See Pr\u00e4s.herrn Ernst Pally",
    "wof:placetype":"venue"
},
  "geometry": {"coordinates":[8.7228803635,47.2736358643],"type":"Point"}
}