{
  "type": "Feature",
  "properties": {
    "iso:country":"CH",
    "sg:address":"Avenue De Plan 20",
    "sg:city":"Morges",
    "sg:orig_category":"Herstellung von sonstigen Nahrungsmitteln",
    "sg:postcode":"1110",
    "sg:province":"Vaud",
    "wof:name":"Fabrique De Fonds De P\u00e2tisserie",
    "wof:placetype":"venue"
},
  "geometry": {"coordinates":[6.5064058304,46.5180206299],"type":"Point"}
}