{
  "type": "Feature",
  "properties": {
    "iso:country":"CH",
    "sg:address":"Chemin De Poussy 4a",
    "sg:city":"Vernier",
    "sg:orig_category":"Akupunktur",
    "sg:phone":"+41 22 341 01 02",
    "sg:postcode":"1214",
    "sg:province":"Gen\u00e8ve",
    "wof:name":"Gilbert Russi Acupuncture",
    "wof:placetype":"venue"
},
  "geometry": {"coordinates":[6.094315,46.218468],"type":"Point"}
}