{
  "type": "Feature",
  "properties": {
    "iso:country":"CH",
    "sg:address":"Bahnhofstrasse 63",
    "sg:city":"D\u00fcbendorf",
    "sg:orig_category":"Vereine Vogel-& Naturschutz",
    "sg:phone":"+41 61 911 09 70",
    "sg:postcode":"8600",
    "sg:province":"Z\u00fcrich",
    "wof:name":"Ornitholog.verein Arlesheim",
    "wof:placetype":"venue"
},
  "geometry": {"coordinates":[7.6545372009,47.4353981018],"type":"Point"}
}