{
  "type": "Feature",
  "properties": {
    "iso:country":"CH",
    "sg:address":"Jungstrasse 50",
    "sg:city":"Basel",
    "sg:orig_category":"Kauf U Verkauf von Immobilien auf eigene Rechnung",
    "sg:phone":"+41 61 381 51 00",
    "sg:postcode":"4056",
    "sg:province":"Basel-Stadt",
    "wof:name":"H\u00e4ring & Partner Liegenschaftsverwaltung",
    "wof:placetype":"venue"
},
  "geometry": {"coordinates":[7.5777411461,47.5669059753],"type":"Point"}
}