{
  "type": "Feature",
  "properties": {
    "iso:country":"CH",
    "sg:address":"Schulhaus 65",
    "sg:city":"Bettwil",
    "sg:orig_category":"Film U Videofilmherstellung Sonstige Hilfsdienste des Kultur U Unterhaltungswesens",
    "sg:phone":"+41 41 360 98 44",
    "sg:postcode":"5618",
    "sg:province":"Aargau",
    "wof:name":"Soundville Recording Studios Ton- U. Bildaufzeichnungen Usw.; Herstellung",
    "wof:placetype":"venue"
},
  "geometry": {"coordinates":[8.3128328323,47.04296875],"type":"Point"}
}