{
  "type": "Feature",
  "properties": {
    "iso:country":"CH",
    "sg:address":"Waldh\u00f6heweg 30",
    "sg:city":"Bern",
    "sg:orig_category":"Personal U Stellenvermittlung Unternehmensberatung",
    "sg:phone":"+41 79 601 80 11",
    "sg:postcode":"3013",
    "sg:province":"Bern",
    "wof:name":"Bl\u00e4si G., Personal Und Unternehmensberatung",
    "wof:placetype":"venue"
},
  "geometry": {"coordinates":[8.4593896866,47.3529396057],"type":"Point"}
}