{
  "type": "Feature",
  "properties": {
    "iso:country":"CH",
    "sg:address":"Chemin Des Grands Champs 1bis",
    "sg:city":"Cheseaux-sur-lausanne",
    "sg:classifiers":[
        {
            "category":"Real Estate",
            "subcategory":"Architect",
            "type":"Services"
        }
    ],
    "sg:phone":"+41 21 731 03 10",
    "sg:postcode":"1033",
    "sg:province":"Vaud",
    "sg:tags":[
        "lighting",
        "neon",
        "accessory"
    ],
    "wof:name":"N\u00e9on Imsa S.a.",
    "wof:placetype":"venue"
},
  "geometry": {"coordinates":[6.6072797775,46.5827102661],"type":"Point"}
}