{
  "type": "Feature",
  "properties": {
    "iso:country":"CH",
    "sg:address":"Place De La Gare 10 1003 Lausanne. Postfach",
    "sg:city":"Lausanne",
    "sg:orig_category":"Advokaturb\u00fcros",
    "sg:phone":"+41 22 347 36 67",
    "sg:postcode":"1001",
    "sg:province":"Vaud",
    "wof:name":"Jean-pierre Carera Etude D'avocat",
    "wof:placetype":"venue"
},
  "geometry": {"coordinates":[6.153855,46.195335],"type":"Point"}
}