{
  "type": "Feature",
  "properties": {
    "iso:country":"CH",
    "sg:address":"Hubelweg 14",
    "sg:city":"K\u00f6niz",
    "sg:orig_category":"Allgemeiner Hoch U Tiefbau",
    "sg:phone":"+41 31 985 23 23",
    "sg:postcode":"3098",
    "sg:province":"Bern",
    "wof:name":"Weiss + Appetito Ag K\u00f6niz",
    "wof:placetype":"venue"
},
  "geometry": {"coordinates":[7.422218,46.925743],"type":"Point"}
}