{
  "type": "Feature",
  "properties": {
    "iso:country":"CH",
    "sg:address":"Altmannsteinstrasse 25",
    "sg:city":"H\u00f6ri",
    "sg:orig_category":"Non-Classified Establishments",
    "sg:phone":"+41 22 369 10 80",
    "sg:postcode":"8181",
    "sg:province":"Z\u00fcrich",
    "wof:name":"Kuirt Cuttat, Kbc - System Engineering",
    "wof:placetype":"venue"
},
  "geometry": {"coordinates":[6.2354798317,46.4775047302],"type":"Point"}
}