{
  "type": "Feature",
  "properties": {
    "addr:full":"Talacker 21 Z\u00fcrich Z\u00fcrich 8022",
    "addr:housenumber":"21",
    "addr:postcode":"8022",
    "addr:street":"Talacker",
    "iso:country":"CH",
    "sg:address":"Talacker 21",
    "sg:city":"Z\u00fcrich",
    "sg:classifiers":[
        {
            "category":"Banks & Credit Unions",
            "subcategory":"Bank",
            "type":"Services"
        }
    ],
    "sg:phone":"+41 12213035",
    "sg:postcode":"8022",
    "sg:province":"Z\u00fcrich",
    "wof:name":"Arab Bank Ltd.",
    "wof:placetype":"venue"
},
  "geometry": {"coordinates":[8.536843,47.37064],"type":"Point"}
}