{
  "type": "Feature",
  "properties": {
    "iso:country":"CH",
    "sg:address":"Via Nadro",
    "sg:city":"Biasca",
    "sg:orig_category":"Vorschulen, Kinderg\u00e4rten",
    "sg:phone":"+41 91 862 16 30",
    "sg:postcode":"6710",
    "sg:province":"Ticino",
    "wof:name":"Scuola Materna S.giuseppe",
    "wof:placetype":"venue"
},
  "geometry": {"coordinates":[8.9719982147,46.3591842651],"type":"Point"}
}