{
  "type": "Feature",
  "properties": {
    "iso:country":"CH",
    "sg:address":"M\u00fcrli",
    "sg:city":"Rechthalten",
    "sg:orig_category":"Herstellung von Konstruktionsteilen, Fertigbauteilen U Ausbauelementen aus Holz",
    "sg:postcode":"1718",
    "sg:province":"Fribourg",
    "wof:name":"Zargenmontage Chodak G.",
    "wof:placetype":"venue"
},
  "geometry": {"coordinates":[7.6032757759,47.5106620789],"type":"Point"}
}