{
  "type": "Feature",
  "properties": {
    "iso:country":"CH",
    "sg:address":"1994",
    "sg:city":"Aproz",
    "sg:classifiers":[
        {
            "category":"Insurance",
            "subcategory":"Insurance Agent",
            "type":"Services"
        }
    ],
    "sg:phone":"+41 27 346 61 16",
    "sg:postcode":"1994",
    "sg:province":"Valais",
    "sg:tags":[
        "versicherungsagenturen",
        "-broker"
    ],
    "wof:name":"Patrick Valli Agence Winterthur Assurances",
    "wof:placetype":"venue"
},
  "geometry": {"coordinates":[7.3139300346,46.2092781067],"type":"Point"}
}