{
  "type": "Feature",
  "properties": {
    "iso:country":"CH",
    "sg:address":"Siteberg 6170 Sch\u00fcpfheim. Postfach",
    "sg:city":"Sch\u00fcpfheim",
    "sg:orig_category":"Allgemeiner Hoch U Tiefbau",
    "sg:phone":"+41 41 484 26 85",
    "sg:postcode":"6170",
    "sg:province":"Luzern",
    "wof:name":"Stalder Erwin Baugesch\u00e4ft Ag Bauunternehmung Usw",
    "wof:placetype":"venue"
},
  "geometry": {"coordinates":[8.019475,46.953609],"type":"Point"}
}