{
  "type": "Feature",
  "properties": {
    "iso:country":"CH",
    "sg:address":"Affolternstrasse 18",
    "sg:city":"Regensdorf",
    "sg:orig_category":"Finanzierungsinstitutionen",
    "sg:postcode":"8105",
    "sg:province":"Z\u00fcrich",
    "wof:name":"R.u.n. Investment Ag",
    "wof:placetype":"venue"
},
  "geometry": {"coordinates":[8.4649372101,47.4297981262],"type":"Point"}
}