{
  "type": "Feature",
  "properties": {
    "iso:country":"CH",
    "sg:address":"Stelzenstrasse 6",
    "sg:city":"Glattbrugg",
    "sg:orig_category":"Handelsvermittlung von Textilien, Bekleidung, Schuhen U Lederwaren",
    "sg:postcode":"8152",
    "sg:province":"Z\u00fcrich",
    "wof:name":"Modeagentur, Pasinetti T.",
    "wof:placetype":"venue"
},
  "geometry": {"coordinates":[8.5591802597,47.4253120422],"type":"Point"}
}