{
  "type": "Feature",
  "properties": {
    "iso:country":"CH",
    "sg:address":"Grand'rue 29",
    "sg:city":"Rolle",
    "sg:orig_category":"Detailhandel mit Waren verschiedener Art, Hauptrichtung Nahrungsmittel",
    "sg:phone":"+41 21 825 15 76",
    "sg:postcode":"1180",
    "sg:province":"Vaud",
    "wof:name":"Coop Vaud Chablais Valaisan",
    "wof:placetype":"venue"
},
  "geometry": {"coordinates":[6.3382320404,46.4575157166],"type":"Point"}
}