{
  "type": "Feature",
  "properties": {
    "iso:country":"CH",
    "sg:address":"Rue Du 23-juin 38",
    "sg:city":"Courroux",
    "sg:classifiers":[
        {
            "category":"Travel",
            "subcategory":"Hotels & Motels",
            "type":"Entertainment"
        }
    ],
    "sg:phone":"+41 32 422 13 65",
    "sg:postcode":"2822",
    "sg:province":"Jura",
    "sg:tags":[
        "hotels",
        "mit",
        "restaurant"
    ],
    "wof:name":"H\u00f4tel De L'ours",
    "wof:placetype":"venue"
},
  "geometry": {"coordinates":[7.3741497993,47.3617477417],"type":"Point"}
}