{
  "type": "Feature",
  "properties": {
    "iso:country":"CH",
    "sg:address":"Brislachstrasse 5",
    "sg:city":"Laufen",
    "sg:orig_category":"Erbringung von Dienstleistungen f\u00fcr Unternehmen",
    "sg:phone":"+41 61 761 55 49",
    "sg:postcode":"4242",
    "sg:province":"Basel-Landschaft",
    "wof:name":"Gygi Hansj\u00f6rg, Grafik",
    "wof:placetype":"venue"
},
  "geometry": {"coordinates":[7.5043578148,47.4192657471],"type":"Point"}
}