{
  "type": "Feature",
  "properties": {
    "iso:country":"CH",
    "sg:address":"M\u00fchlenstrasse 50",
    "sg:city":"Schaffhausen",
    "sg:orig_category":"Herstellung von Ger\u00e4ten der Elektrizit\u00e4tserzeugung, -verteilung u.\u00e4. -Herstellung von sonstigen elek",
    "sg:phone":"+41 52 625 21 11",
    "sg:postcode":"8200",
    "sg:province":"Schaffhausen",
    "wof:name":"Relag Electric Gmbh",
    "wof:placetype":"venue"
},
  "geometry": {"coordinates":[8.6273698807,47.6932411194],"type":"Point"}
}