{
  "type": "Feature",
  "properties": {
    "iso:country":"CH",
    "sg:address":"Alter Z\u00fcrichweg 35",
    "sg:city":"Schlieren",
    "sg:orig_category":"Herstellung von sonstigen elektrischen Ausr\u00fcstungen Sonstiger Grosshandel",
    "sg:phone":"+41 17307818",
    "sg:postcode":"8952",
    "sg:province":"Z\u00fcrich",
    "wof:name":"Alatec Alarm-& Sicherheitstechnik Gmbh",
    "wof:placetype":"venue"
},
  "geometry": {"coordinates":[8.4540710449,47.3949203491],"type":"Point"}
}