{
  "type": "Feature",
  "properties": {
    "iso:country":"CH",
    "sg:address":"Ziegelbr\u00fcckstrasse 81",
    "sg:city":"Niederurnen",
    "sg:orig_category":"Fernmeldedienste",
    "sg:phone":"+41 18410770",
    "sg:postcode":"8867",
    "sg:province":"Glarus",
    "wof:name":"Cybercall Netservice Gmbh",
    "wof:placetype":"venue"
},
  "geometry": {"coordinates":[9.0602703094,47.1324996948],"type":"Point"}
}