{
  "type": "Feature",
  "properties": {
    "addr:full":"Hauptstrasse 26 Laufen Basel-Landschaft 4242",
    "addr:housenumber":"26",
    "addr:postcode":"4242",
    "addr:street":"Hauptstrasse",
    "iso:country":"CH",
    "sg:address":"Hauptstrasse 26",
    "sg:city":"Laufen",
    "sg:orig_category":"Detailhandel mit Brot, Back U S\u00fcsswaren",
    "sg:phone":"+41 61 761 62 01",
    "sg:postcode":"4242",
    "sg:province":"Basel-Landschaft",
    "wof:name":"Guido Kern",
    "wof:placetype":"venue"
},
  "geometry": {"coordinates":[7.500698,47.422039],"type":"Point"}
}