{
  "type": "Feature",
  "properties": {
    "iso:country":"CH",
    "sg:address":"Route Thonon 50",
    "sg:city":"V\u00e9senaz",
    "sg:classifiers":[
        {
            "category":"Restaurant",
            "type":"Food & Drink"
        }
    ],
    "sg:phone":"+41 22 752 11 10",
    "sg:postcode":"1222",
    "sg:province":"Gen\u00e8ve",
    "wof:name":"Caf\u00e9-restaurant Dancing Station",
    "wof:placetype":"venue"
},
  "geometry": {"coordinates":[6.1975951195,46.2392883301],"type":"Point"}
}