{
  "type": "Feature",
  "properties": {
    "iso:country":"CH",
    "sg:address":"Avenue D'echallens 61",
    "sg:city":"Lausanne",
    "sg:orig_category":"Zahnarztpraxen",
    "sg:phone":"+41 21 624 61 47",
    "sg:postcode":"1004",
    "sg:province":"Vaud",
    "wof:name":"Dr M\u00e9d. Dent. Domitien Emery M\u00e9decin-dentiste",
    "wof:placetype":"venue"
},
  "geometry": {"coordinates":[6.6187300682,46.5334892273],"type":"Point"}
}