{
  "type": "Feature",
  "properties": {
    "iso:country":"CH",
    "sg:address":"Zugerstr. 74",
    "sg:city":"Baar",
    "sg:classifiers":[
        {
            "category":"Shopping",
            "subcategory":"Bicycles & Sporting Goods",
            "type":"Retail Goods"
        }
    ],
    "sg:phone":"+41 61 911 80 70",
    "sg:postcode":"6340",
    "sg:province":"Zug",
    "sg:tags":[
        "product",
        "sport",
        "miscellaneous"
    ],
    "wof:name":"Mario Bulloni Spielzeug Ag",
    "wof:placetype":"venue"
},
  "geometry": {"coordinates":[7.6582689285,47.4374809265],"type":"Point"}
}