{
  "type": "Feature",
  "properties": {
    "addr:full":"Rue Du Grand-pont 8 Lausanne Vaud 1003",
    "addr:housenumber":"8",
    "addr:postcode":"1003",
    "addr:street":"Rue Du Grand-Pont",
    "iso:country":"CH",
    "sg:address":"Rue Du Grand-pont 8",
    "sg:city":"Lausanne",
    "sg:orig_category":"Arztpraxen",
    "sg:phone":"+41 21 320 79 60",
    "sg:postcode":"1003",
    "sg:province":"Vaud",
    "wof:name":"Dres Med. Ketterer & Rieckhoff M\u00e9decins Sp\u00e9cialistes Fmh",
    "wof:placetype":"venue"
},
  "geometry": {"coordinates":[6.630526,46.521469],"type":"Point"}
}