{
  "type": "Feature",
  "properties": {
    "iso:country":"CH",
    "sg:address":"Sch\u00fctzenstrasse 38 9100 Herisau. Postfach",
    "sg:city":"Herisau",
    "sg:orig_category":"Herstellung von Tanks U Sammelbeh\u00e4ltern aus Metall Reinigungsgewerbe",
    "sg:phone":"+41 71 351 13 51",
    "sg:postcode":"9101",
    "sg:province":"Appenzell Ausserrhoden",
    "wof:name":"Diener + Tobler Ag",
    "wof:placetype":"venue"
},
  "geometry": {"coordinates":[9.287229538,47.3930015564],"type":"Point"}
}