{
  "type": "Feature",
  "properties": {
    "addr:full":"Chilchgasse 133 G\u00e4chlingen Schaffhausen 8214",
    "addr:housenumber":"133",
    "addr:postcode":"8214",
    "addr:street":"Chilchgasse",
    "iso:country":"CH",
    "sg:address":"Chilchgasse 133",
    "sg:city":"G\u00e4chlingen",
    "sg:orig_category":"Autogaragen",
    "sg:phone":"+41 52 681 42 50",
    "sg:postcode":"8214",
    "sg:province":"Schaffhausen",
    "wof:name":"Ernst Gerber Autoreparaturwerkstatt",
    "wof:placetype":"venue"
},
  "geometry": {"coordinates":[8.50056,47.702881],"type":"Point"}
}