{
  "type": "Feature",
  "properties": {
    "iso:country":"CH",
    "sg:address":"Hauptstrasse",
    "sg:city":"Kienberg",
    "sg:classifiers":[
        {
            "category":"Restaurant",
            "type":"Food & Drink"
        }
    ],
    "sg:phone":"+41 62 844 24 01",
    "sg:postcode":"4468",
    "sg:province":"Solothurn",
    "wof:name":"Restaurant Forellenhof",
    "wof:placetype":"venue"
},
  "geometry": {"coordinates":[7.9668068886,47.439163208],"type":"Point"}
}