{
  "type": "Feature",
  "properties": {
    "iso:country":"CH",
    "sg:address":"Dreilindenstrasse 75a",
    "sg:city":"Luzern",
    "sg:orig_category":"Gesundheitswesen",
    "sg:postcode":"6006",
    "sg:province":"Luzern",
    "wof:name":"Frauchiger Martin Schulung + Beratung",
    "wof:placetype":"venue"
},
  "geometry": {"coordinates":[8.3185386658,47.0601959229],"type":"Point"}
}