{
  "type": "Feature",
  "properties": {
    "iso:country":"CH",
    "sg:address":"Saltinistrasse 1",
    "sg:city":"Trimmis",
    "sg:orig_category":"Sportvereine Ballsport Squash",
    "sg:postcode":"7203",
    "sg:province":"Graubunden",
    "wof:name":"Sportclub Cr\u00e9dit Suisse Squash",
    "wof:placetype":"venue"
},
  "geometry": {"coordinates":[8.5380096436,47.3690910339],"type":"Point"}
}