{
  "type": "Feature",
  "properties": {
    "iso:country":"CH",
    "sg:address":"Boulevard Des Tranch\u00e9es 44",
    "sg:city":"Gen\u00e8ve",
    "sg:orig_category":"Chiropraktik",
    "sg:phone":"+41 22 346 47 33",
    "sg:postcode":"1206",
    "sg:province":"Gen\u00e8ve",
    "wof:name":"Claude B. Illi Chiropraticien",
    "wof:placetype":"venue"
},
  "geometry": {"coordinates":[6.155139,46.197979],"type":"Point"}
}