{
  "type": "Feature",
  "properties": {
    "iso:country":"CH",
    "sg:address":"K\u00f6nizstrasse 161",
    "sg:city":"Liebefeld",
    "sg:orig_category":"Instandhaltung U Reparatur von Automobilen",
    "sg:phone":"+41 31 971 29 53",
    "sg:postcode":"3097",
    "sg:province":"Bern",
    "wof:name":"Garage L\u00fcthi T.",
    "wof:placetype":"venue"
},
  "geometry": {"coordinates":[7.4164757729,46.9356040955],"type":"Point"}
}