{
  "type": "Feature",
  "properties": {
    "iso:country":"CH",
    "sg:address":"Breitigasse 5 8610 Uster. Postfach",
    "sg:city":"Uster",
    "sg:orig_category":"Sonstige mit der Informatik verbundene T\u00e4tigkeiten",
    "sg:postcode":"8610",
    "sg:province":"Z\u00fcrich",
    "wof:name":"Reinhardt Peter Consulting",
    "wof:placetype":"venue"
},
  "geometry": {"coordinates":[8.7347278595,47.3441085815],"type":"Point"}
}