{
  "type": "Feature",
  "properties": {
    "iso:country":"CH",
    "sg:address":"Avenue Victor-ruffy 52",
    "sg:city":"Lausanne",
    "sg:orig_category":"Elektroinstallation",
    "sg:phone":"+41 21 653 63 63",
    "sg:postcode":"1012",
    "sg:province":"Vaud",
    "wof:name":"Adelec Aebischer & Derungs Sa",
    "wof:placetype":"venue"
},
  "geometry": {"coordinates":[6.6486859322,46.5289726257],"type":"Point"}
}