{
  "type": "Feature",
  "properties": {
    "iso:country":"CH",
    "sg:address":"Hohmoos 6",
    "sg:city":"Z\u00fcrich",
    "sg:orig_category":"Minigolfpl\u00e4tze",
    "sg:phone":"+41 13224687",
    "sg:postcode":"8051",
    "sg:province":"Z\u00fcrich",
    "wof:name":"Minigolf Z\u00fcrich Nord",
    "wof:placetype":"venue"
},
  "geometry": {"coordinates":[8.5908308029,47.3979377747],"type":"Point"}
}