{
  "type": "Feature",
  "properties": {
    "iso:country":"CH",
    "sg:address":"Bruchstrasse 54 6003 Luzern. Postfach",
    "sg:city":"Luzern",
    "sg:orig_category":"Unternehmensberatung Wirtschaftspr\u00fcfung, Steuerberatung U Treuhand",
    "sg:phone":"+41 79 341 72 19",
    "sg:postcode":"6002",
    "sg:province":"Luzern",
    "wof:name":"Widmer Treuhand Ag Luzern",
    "wof:placetype":"venue"
},
  "geometry": {"coordinates":[8.3013305664,47.0484313965],"type":"Point"}
}