{
  "type": "Feature",
  "properties": {
    "iso:country":"CH",
    "sg:address":"St.-antons-gasse 4a",
    "sg:city":"Zug",
    "sg:orig_category":"Buchf\u00fchrung Wirtschaftspr\u00fcfung, Steuerberatung U Treuhand",
    "sg:phone":"+41 71 740 09 41",
    "sg:postcode":"6300",
    "sg:province":"Zug",
    "wof:name":"Krt Treuhand R\u00fcegg Kurt",
    "wof:placetype":"venue"
},
  "geometry": {"coordinates":[9.637427,47.435043],"type":"Point"}
}