{
  "type": "Feature",
  "properties": {
    "iso:country":"CH",
    "sg:address":"Aeschstrasse 169 8123 Ebmatingen. Postfach",
    "sg:city":"Binz",
    "sg:orig_category":"Softwareentwicklung U beratung",
    "sg:postcode":"8122",
    "sg:province":"Z\u00fcrich",
    "wof:name":"Omico Gmbh",
    "wof:placetype":"venue"
},
  "geometry": {"coordinates":[8.644115448,47.3491477966],"type":"Point"}
}