{
  "type": "Feature",
  "properties": {
    "iso:country":"CH",
    "sg:address":"3995",
    "sg:city":"Ernen",
    "sg:orig_category":"Primarschulen",
    "sg:phone":"+41 27 971 11 51",
    "sg:postcode":"3995",
    "sg:province":"Valais",
    "wof:name":"Primarschule",
    "wof:placetype":"venue"
},
  "geometry": {"coordinates":[8.1464395523,46.39868927],"type":"Point"}
}