{
  "type": "Feature",
  "properties": {
    "iso:country":"CH",
    "sg:address":"Herdmattenstrasse 19 5636 Benzenschwil. Postfach",
    "sg:city":"Benzenschwil",
    "sg:orig_category":"Herstellung von konfektionierten Textilwaren ohne Bekleidung Rolladen- and Storenmontage",
    "sg:phone":"+41 79 655 11 01",
    "sg:postcode":"5636",
    "sg:province":"Aargau",
    "wof:name":"Frei\u00e4mter Storen-service Gmbh Storen U. Insektenschutzgitter; Handel, Montage, Reparatur",
    "wof:placetype":"venue"
},
  "geometry": {"coordinates":[8.3628339767,47.246295929],"type":"Point"}
}