{
  "type": "Feature",
  "properties": {
    "iso:country":"CH",
    "sg:address":"Palettes Chemin Des 25",
    "sg:city":"Grand-lancy",
    "sg:orig_category":"Fachdetailhandel in Verkaufsr\u00e4umen",
    "sg:phone":"+41 19504697",
    "sg:postcode":"1212",
    "sg:province":"Gen\u00e8ve",
    "wof:name":"Reveruzzi Goldschmuck",
    "wof:placetype":"venue"
},
  "geometry": {"coordinates":[8.7821655273,47.372844696],"type":"Point"}
}