{
  "type": "Feature",
  "properties": {
    "iso:country":"CH",
    "sg:address":"Rainweg 4",
    "sg:city":"Auenstein",
    "sg:orig_category":"Wirtschaftspr\u00fcfung, Steuerberatung U Treuhand",
    "sg:postcode":"5105",
    "sg:province":"Aargau",
    "wof:name":"Daro Treuhand Gmbh",
    "wof:placetype":"venue"
},
  "geometry": {"coordinates":[8.1339635849,47.4182281494],"type":"Point"}
}