{
  "type": "Feature",
  "properties": {
    "iso:country":"CH",
    "sg:address":"Guisan Av. Du G\u00e9n\u00e9ral 2b",
    "sg:city":"Sierre",
    "sg:orig_category":"RESTAURANTS: TEA-ROOMS",
    "sg:postcode":"3960",
    "sg:province":"Valais",
    "wof:name":"Caf\u00e9-restaurant \u00abau Petit Plus\u00bb Vioget Fabienne Et Corinne",
    "wof:placetype":"venue"
},
  "geometry": {"coordinates":[7.5321369171,46.2928543091],"type":"Point"}
}