{
  "type": "Feature",
  "properties": {
    "iso:country":"CH",
    "sg:address":"Talackerstrasse 3",
    "sg:city":"Uster",
    "sg:orig_category":"Fassadenbau Stukkateurgewerbe, Gipserei U Verputzerei",
    "sg:phone":"+41 19941153",
    "sg:postcode":"8610",
    "sg:province":"Z\u00fcrich",
    "wof:name":"Gibon Gmbh Gipser-& Fassadenarbeiten",
    "wof:placetype":"venue"
},
  "geometry": {"coordinates":[8.7161931992,47.3453369141],"type":"Point"}
}