{
  "type": "Feature",
  "properties": {
    "iso:country":"CH",
    "sg:address":"Chemin Du Daru 15",
    "sg:city":"Plan-les-ouates",
    "sg:classifiers":[
        {
            "category":"Bus Stop",
            "subcategory":"None",
            "type":"Transportation"
        }
    ],
    "sg:phone":"+41 22 771 12 23",
    "sg:postcode":"1228",
    "sg:province":"Gen\u00e8ve",
    "sg:tags":[
        "switch",
        "low-voltage"
    ],
    "wof:name":"Partenaire Rockwell Automation Sprecher & Schuh",
    "wof:placetype":"venue"
},
  "geometry": {"coordinates":[6.112944,46.165596],"type":"Point"}
}