{
  "type": "Feature",
  "properties": {
    "iso:country":"CH",
    "sg:address":"1274",
    "sg:city":"Grens",
    "sg:orig_category":"Gemeindeverwaltungen",
    "sg:phone":"+41 22 361 58 47",
    "sg:postcode":"1274",
    "sg:province":"Vaud",
    "wof:name":"Administration Communale De Grens",
    "wof:placetype":"venue"
},
  "geometry": {"coordinates":[6.1965398788,46.3957290649],"type":"Point"}
}