{
  "type": "Feature",
  "properties": {
    "iso:country":"CH",
    "sg:address":"Mittlerer Rainweg 8 4414 F\u00fcllinsdorf. Postfach",
    "sg:city":"F\u00fcllinsdorf",
    "sg:orig_category":"Softwareentwicklung U beratung Sonstige mit der Informatik verbundene T\u00e4tigkeiten",
    "sg:phone":"+41 61 903 09 09",
    "sg:postcode":"4414",
    "sg:province":"Basel-Landschaft",
    "wof:name":"Kilian Edv Gmbh Beratung - Support - Internet - Schulung",
    "wof:placetype":"venue"
},
  "geometry": {"coordinates":[7.733607769,47.5065460205],"type":"Point"}
}