{
  "type": "Feature",
  "properties": {
    "iso:country":"CH",
    "sg:address":"Zentralstrasse 2 8003 Z\u00fcrich. Postfach 9125",
    "sg:city":"Z\u00fcrich",
    "sg:orig_category":"Kauf U Verkauf von Immobilien auf eigene Rechnung Vermittlung von Immobilien",
    "sg:phone":"+41 14511111",
    "sg:postcode":"8036",
    "sg:province":"Z\u00fcrich",
    "wof:name":"K & P, Krummenacher & Partner, Immobilien-treuhand Ag",
    "wof:placetype":"venue"
},
  "geometry": {"coordinates":[8.5209360123,47.3702011108],"type":"Point"}
}