{
  "type": "Feature",
  "properties": {
    "iso:country":"CH",
    "sg:address":"Br\u00fcnnelistrasse 11",
    "sg:city":"Ermatingen",
    "sg:orig_category":"Unclassifiable Establishments",
    "sg:postcode":"8272",
    "sg:province":"Thurgau",
    "wof:name":"Adyna Gmbh",
    "wof:placetype":"venue"
},
  "geometry": {"coordinates":[9.0763015747,47.6676597595],"type":"Point"}
}