{
  "type": "Feature",
  "properties": {
    "iso:country":"CH",
    "sg:address":"Route Des Fournaises 1950 Sion. Postfach",
    "sg:city":"Sion",
    "sg:orig_category":"Detailhandel mit Brennstoffen U Heizmaterial",
    "sg:phone":"+41 27 203 36 14",
    "sg:postcode":"1951",
    "sg:province":"Valais",
    "wof:name":"Raf Sa Combustibles",
    "wof:placetype":"venue"
},
  "geometry": {"coordinates":[7.371855,46.223595],"type":"Point"}
}