{
  "type": "Feature",
  "properties": {
    "iso:country":"CH",
    "sg:address":"Via Baragge 56",
    "sg:city":"Ascona",
    "sg:orig_category":"Unclassifiable Establishments",
    "sg:postcode":"6612",
    "sg:province":"Ticino",
    "wof:name":"Scarabik Sa",
    "wof:placetype":"venue"
},
  "geometry": {"coordinates":[8.7745542526,46.1591682434],"type":"Point"}
}