{
  "type": "Feature",
  "properties": {
    "iso:country":"CH",
    "sg:address":"Longemalle Place De 13 1204 Gen\u00e8ve. Postfach",
    "sg:city":"Gen\u00e8ve",
    "sg:classifiers":[
        {
            "category":"Travel",
            "subcategory":"Hotels & Motels",
            "type":"Entertainment"
        }
    ],
    "sg:phone":"+41 22 818 62 62",
    "sg:postcode":"1204",
    "sg:province":"Gen\u00e8ve",
    "sg:tags":[
        "hotels",
        "mit",
        "restaurant"
    ],
    "wof:name":"H\u00f4tel Touring-balance",
    "wof:placetype":"venue"
},
  "geometry": {"coordinates":[6.150290966,46.2031784058],"type":"Point"}
}