{
  "type": "Feature",
  "properties": {
    "iso:country":"CH",
    "sg:address":"Route De Moudon 40",
    "sg:city":"Lucens",
    "sg:orig_category":"Softwareentwicklung U beratung",
    "sg:phone":"+41 21 906 89 16",
    "sg:postcode":"1522",
    "sg:province":"Vaud",
    "wof:name":"Lml - Logiciels Laborde, Luthi",
    "wof:placetype":"venue"
},
  "geometry": {"coordinates":[6.8337349892,46.7016410828],"type":"Point"}
}