{
  "type": "Feature",
  "properties": {
    "iso:country":"CH",
    "sg:address":"Postgasse 12",
    "sg:city":"Arbon",
    "sg:orig_category":"Markt U Meinungsforschung",
    "sg:postcode":"9320",
    "sg:province":"Thurgau",
    "wof:name":"Solo Io Ag",
    "wof:placetype":"venue"
},
  "geometry": {"coordinates":[9.4358320236,47.5150871277],"type":"Point"}
}