{
  "type": "Feature",
  "properties": {
    "iso:country":"CH",
    "sg:address":"Stadtplatz 6 3270 Aarberg. Postfach 39",
    "sg:city":"Aarberg",
    "sg:orig_category":"Mechanik Schmieden",
    "sg:phone":"+41 32 484 94 59",
    "sg:postcode":"3270",
    "sg:province":"Bern",
    "wof:name":"Crevoisier, Fr\u00e8res",
    "wof:placetype":"venue"
},
  "geometry": {"coordinates":[7.1378297806,47.2788200378],"type":"Point"}
}