{
  "type": "Feature",
  "properties": {
    "iso:country":"CH",
    "sg:address":"Obere Bahnhofstrasse 24",
    "sg:city":"Mellingen",
    "sg:classifiers":[
        {
            "category":"Restaurant",
            "type":"Food & Drink"
        }
    ],
    "sg:phone":"+41 18441750",
    "sg:postcode":"5507",
    "sg:province":"Aargau",
    "wof:name":"Restaurant Zum Bergwerk",
    "wof:placetype":"venue"
},
  "geometry": {"coordinates":[8.454126358,47.4578170776],"type":"Point"}
}