{
  "type": "Feature",
  "properties": {
    "iso:country":"CH",
    "sg:address":"Dornacherstrasse 404",
    "sg:city":"Basel",
    "sg:orig_category":"Wirtschaftspr\u00fcfung, Steuerberatung U Treuhand",
    "sg:postcode":"4053",
    "sg:province":"Basel-Stadt",
    "wof:name":"Kurt Rohrer",
    "wof:placetype":"venue"
},
  "geometry": {"coordinates":[8.5801410675,47.3188972473],"type":"Point"}
}