{
  "type": "Feature",
  "properties": {
    "iso:country":"CH",
    "sg:address":"Rue Du Tertre 30",
    "sg:city":"Neuch\u00e2tel",
    "sg:orig_category":"Bauspenglerei Zimmerei, Dachdeckerei, Bauspenglerei U Abdichtung",
    "sg:phone":"+41 19504363",
    "sg:postcode":"2000",
    "sg:province":"Neuch\u00e2tel",
    "wof:name":"Silligmann Ag",
    "wof:placetype":"venue"
},
  "geometry": {"coordinates":[8.781767,47.366665],"type":"Point"}
}