{
  "type": "Feature",
  "properties": {
    "iso:country":"CH",
    "sg:address":"Klarastrasse 3",
    "sg:city":"Z\u00fcrich",
    "sg:orig_category":"Erbringung von Dienstleistungen f\u00fcr Unternehmen",
    "sg:postcode":"8008",
    "sg:province":"Z\u00fcrich",
    "wof:name":"Christa Abt",
    "wof:placetype":"venue"
},
  "geometry": {"coordinates":[8.5503635406,47.3642654419],"type":"Point"}
}