{
  "type": "Feature",
  "properties": {
    "iso:country":"CH",
    "sg:address":"Weissensteinstrasse 41",
    "sg:city":"Bern",
    "sg:orig_category":"Primarschulen",
    "sg:postcode":"3007",
    "sg:province":"Bern",
    "wof:name":"Primarschule Pestalozzi",
    "wof:placetype":"venue"
},
  "geometry": {"coordinates":[7.4237961769,46.9399261475],"type":"Point"}
}