{
  "type": "Feature",
  "properties": {
    "iso:country":"CH",
    "sg:address":"Grand-rue 130",
    "sg:city":"Tramelan",
    "sg:orig_category":"Erbringung von Dienstleistungen f\u00fcr Unternehmen",
    "sg:phone":"+41 21 922 54 08",
    "sg:postcode":"2720",
    "sg:province":"Bern",
    "wof:name":"Boutique Int\u00e9rieurs, Monique Pugin-margot",
    "wof:placetype":"venue"
},
  "geometry": {"coordinates":[1.9467660189,50.2957191467],"type":"Point"}
}