{
  "type": "Feature",
  "properties": {
    "iso:country":"CH",
    "sg:address":"Dorf 3512 Walkringen. Postfach",
    "sg:city":"Bigenthal",
    "sg:orig_category":"Instandhaltung U Reparatur von Automobilen",
    "sg:postcode":"3513",
    "sg:province":"Bern",
    "wof:name":"Automalerei Tschanz.",
    "wof:placetype":"venue"
},
  "geometry": {"coordinates":[7.6227722168,46.9611701965],"type":"Point"}
}