{
  "type": "Feature",
  "properties": {
    "iso:country":"CH",
    "sg:address":"Rue De La Mercerie 24",
    "sg:city":"Lausanne",
    "sg:orig_category":"Maturit\u00e4tsschulen, Lehrerseminarien",
    "sg:phone":"+41 21 312 90 50",
    "sg:postcode":"1003",
    "sg:province":"Vaud",
    "wof:name":"Gymnase Du Soir",
    "wof:placetype":"venue"
},
  "geometry": {"coordinates":[6.6348528862,46.5213623047],"type":"Point"}
}