{
  "type": "Feature",
  "properties": {
    "iso:country":"CH",
    "sg:address":"Kalkofenstrasse 10 8810 Horgen. Postfach",
    "sg:city":"Horgen",
    "sg:orig_category":"Unclassifiable Establishments",
    "sg:postcode":"8812",
    "sg:province":"Z\u00fcrich",
    "wof:name":"Ramizi Transport Gmbh Transportunternehmen",
    "wof:placetype":"venue"
},
  "geometry": {"coordinates":[8.6092176437,47.2462539673],"type":"Point"}
}