{
  "type": "Feature",
  "properties": {
    "iso:country":"CH",
    "sg:address":"Bahnhofstrasse 15",
    "sg:city":"Koblenz",
    "sg:orig_category":"Instandhaltung U Reparatur von Automobilen Tankstellen",
    "sg:phone":"+41 56 246 11 61",
    "sg:postcode":"5322",
    "sg:province":"Aargau",
    "wof:name":"K. Nusser Ag",
    "wof:placetype":"venue"
},
  "geometry": {"coordinates":[8.2319431305,47.6061439514],"type":"Point"}
}