{
  "type": "Feature",
  "properties": {
    "iso:country":"CH",
    "sg:address":"Baslerstrasse 275",
    "sg:city":"Allschwil",
    "sg:orig_category":"Reiseb\u00fcros U Reiseveranstalter",
    "sg:phone":"+41 71 223 20 41",
    "sg:postcode":"4123",
    "sg:province":"Basel-Landschaft",
    "wof:name":"Asc Ferien Center Ag Reiseb\u00fcro",
    "wof:placetype":"venue"
},
  "geometry": {"coordinates":[9.3705568314,47.4207572937],"type":"Point"}
}