{
  "type": "Feature",
  "properties": {
    "iso:country":"CH",
    "sg:address":"Inkwilerstrasse 24",
    "sg:city":"Subingen",
    "sg:orig_category":"Softwareentwicklung U beratung",
    "sg:postcode":"4553",
    "sg:province":"Solothurn",
    "wof:name":"Avb Consulting Von B\u00fcren",
    "wof:placetype":"venue"
},
  "geometry": {"coordinates":[7.6226949692,47.1989974976],"type":"Point"}
}