{
  "type": "Feature",
  "properties": {
    "iso:country":"CH",
    "sg:address":"Bondastrasse 32",
    "sg:city":"Chur",
    "sg:orig_category":"Vermittlung von Immobilien Wirtschaftspr\u00fcfung, Steuerberatung U Treuhand",
    "sg:postcode":"7000",
    "sg:province":"Graubunden",
    "wof:name":"R\u00e9gie Du Croset Sa",
    "wof:placetype":"venue"
},
  "geometry": {"coordinates":[6.5647010803,46.5349006653],"type":"Point"}
}