{
  "type": "Feature",
  "properties": {
    "addr:full":"Route De Bramois Sion Valais 1950",
    "addr:postcode":"1950",
    "addr:street":"Route De Bramois",
    "iso:country":"CH",
    "sg:address":"Route De Bramois",
    "sg:city":"Sion",
    "sg:orig_category":"Architektur U Ingenieurb\u00fcros",
    "sg:phone":"+41 27 203 43 23",
    "sg:postcode":"1950",
    "sg:province":"Valais",
    "wof:name":"Rs Cr\u00e9ation Sch\u00f6pfer Roger",
    "wof:placetype":"venue"
},
  "geometry": {"coordinates":[7.389672,46.226425],"type":"Point"}
}