{
  "type": "Feature",
  "properties": {
    "iso:country":"CH",
    "sg:address":"Kilchbergstrasse 6a",
    "sg:city":"Adliswil",
    "sg:classifiers":[
        {
            "category":"Manufacturing",
            "subcategory":"Chemicals & Compounds",
            "type":"Manufacturing & Wholesale Goods"
        }
    ],
    "sg:phone":"+41 17091212",
    "sg:postcode":"8134",
    "sg:province":"Z\u00fcrich",
    "sg:tags":[
        "cosmetic"
    ],
    "wof:name":"Erson Ag",
    "wof:placetype":"venue"
},
  "geometry": {"coordinates":[8.52807,47.312157],"type":"Point"}
}