{
  "type": "Feature",
  "properties": {
    "iso:country":"CH",
    "sg:address":"Fl\u00e4cke",
    "sg:city":"Berom\u00fcnster",
    "sg:orig_category":"Detailhandel mit Brot, Back U S\u00fcsswaren",
    "sg:phone":"+41 41 930 24 48",
    "sg:postcode":"6215",
    "sg:province":"Luzern",
    "wof:name":"Kilian Fischer B\u00e4ckerei-konditorei",
    "wof:placetype":"venue"
},
  "geometry": {"coordinates":[8.192506,47.206577],"type":"Point"}
}