{
  "type": "Feature",
  "properties": {
    "iso:country":"CH",
    "sg:address":"Via Francesco Somaini 7",
    "sg:city":"Lugano",
    "sg:orig_category":"Zahnarztpraxen",
    "sg:phone":"+41 91 922 03 10",
    "sg:postcode":"6900",
    "sg:province":"Ticino",
    "wof:name":"Dott. Med. Dent. G. De-marchi Dentista",
    "wof:placetype":"venue"
},
  "geometry": {"coordinates":[8.9566669464,46.0073432922],"type":"Point"}
}