{
  "type": "Feature",
  "properties": {
    "iso:country":"CH",
    "sg:address":"Ancienne Route De Sierre",
    "sg:city":"Mi\u00e8ge",
    "sg:orig_category":"Detailhandel mit Metallwaren, Anstrichmitteln, Glaswaren, Bau U Heimwerkerbedarf Grosshandel mit Mas",
    "sg:phone":"+41 27 455 25 75",
    "sg:postcode":"3972",
    "sg:province":"Valais",
    "wof:name":"Skyline Sa",
    "wof:placetype":"venue"
},
  "geometry": {"coordinates":[7.5466499329,46.3091392517],"type":"Point"}
}