{
  "type": "Feature",
  "properties": {
    "iso:country":"CH",
    "sg:address":"Alte Brauerei",
    "sg:city":"Schlarigna",
    "sg:orig_category":"Elektroinstallation",
    "sg:phone":"+41 27 722 21 79",
    "sg:postcode":"7505",
    "sg:province":"Graubunden",
    "wof:name":"Mauerhofer Et Zuber, Entreprises Electriques, Sa, Succursale De Martigny",
    "wof:placetype":"venue"
},
  "geometry": {"coordinates":[7.0894808769,46.1131439209],"type":"Point"}
}