{
  "type": "Feature",
  "properties": {
    "iso:country":"CH",
    "sg:address":"Eisfeldstrasse 2",
    "sg:city":"Luzern",
    "sg:orig_category":"Sportschulen Tennis",
    "sg:phone":"+41 41 360 61 66",
    "sg:postcode":"6005",
    "sg:province":"Luzern",
    "wof:name":"Tennisschule Luzern",
    "wof:placetype":"venue"
},
  "geometry": {"coordinates":[8.3210906982,47.0411987305],"type":"Point"}
}