{
  "type": "Feature",
  "properties": {
    "iso:country":"CH",
    "sg:address":"Feldhofstrasse 4 8708 M\u00e4nnedorf. Postfach",
    "sg:city":"M\u00e4nnedorf",
    "sg:orig_category":"Werbung",
    "sg:postcode":"8708",
    "sg:province":"Z\u00fcrich",
    "wof:name":"Tonini Graphic Art Design",
    "wof:placetype":"venue"
},
  "geometry": {"coordinates":[8.7069568634,47.2495079041],"type":"Point"}
}