{
  "type": "Feature",
  "properties": {
    "addr:full":"Lausanne Rue De 72 1201 Gen\u00e8ve. Postfach Gen\u00e8ve Gen\u00e8ve 1201",
    "addr:housenumber":"72",
    "addr:postcode":"1201;postfach;1201",
    "addr:street":"Rue De",
    "iso:country":"CH",
    "sg:address":"Lausanne Rue De 72 1201 Gen\u00e8ve. Postfach",
    "sg:city":"Gen\u00e8ve",
    "sg:orig_category":"Allgemeinbildende weiterf\u00fchrende Schulen",
    "sg:postcode":"1201",
    "sg:province":"Gen\u00e8ve",
    "wof:name":"Global Trade Institute (gti) S\u00e0rl",
    "wof:placetype":"venue"
},
  "geometry": {"coordinates":[6.142701,46.208359],"type":"Point"}
}