{
  "type": "Feature",
  "properties": {
    "addr:full":"Mattenhof 123 Z\u00fcrich Z\u00fcrich 8051",
    "addr:housenumber":"123",
    "addr:postcode":"8051",
    "addr:street":"Mattenhof",
    "iso:country":"CH",
    "sg:address":"Mattenhof 123",
    "sg:city":"Z\u00fcrich",
    "sg:orig_category":"Datenverarbeitungsdienste Sonstige mit der Informatik verbundene T\u00e4tigkeiten",
    "sg:phone":"+41 13201701",
    "sg:postcode":"8051",
    "sg:province":"Z\u00fcrich",
    "wof:name":"Meili Data",
    "wof:placetype":"venue"
},
  "geometry": {"coordinates":[8.595078,47.39809],"type":"Point"}
}