{
  "type": "Feature",
  "properties": {
    "iso:country":"CH",
    "sg:address":"Goethestrasse 23",
    "sg:city":"St\u00e4fa",
    "sg:orig_category":"Wirtschafts- and Arbeitgeberverb\u00e4nde",
    "sg:phone":"+41 19266787",
    "sg:postcode":"8712",
    "sg:province":"Z\u00fcrich",
    "wof:name":"Schweiz.hafnermeisterverband Zh'see & Umg.,willi Str\u00e4ssler",
    "wof:placetype":"venue"
},
  "geometry": {"coordinates":[8.7244186401,47.2410926819],"type":"Point"}
}