{
  "type": "Feature",
  "properties": {
    "iso:country":"CH",
    "sg:address":"Oberdorfstrasse",
    "sg:city":"Steffisburg",
    "sg:orig_category":"Non-Classified Establishments",
    "sg:postcode":"3612",
    "sg:province":"Bern",
    "wof:name":"D\u00e4llenbach & Ewald Holding Ag",
    "wof:placetype":"venue"
},
  "geometry": {"coordinates":[7.6338729858,46.7801208496],"type":"Point"}
}