{
  "type": "Feature",
  "properties": {
    "iso:country":"CH",
    "sg:address":"1115",
    "sg:city":"Vullierens",
    "sg:orig_category":"Herstellung von Konstruktionsteilen, Fertigbauteilen U Ausbauelementen aus Holz",
    "sg:phone":"+41 21 869 91 66",
    "sg:postcode":"1115",
    "sg:province":"Vaud",
    "wof:name":"Andr\u00e9 Raymond",
    "wof:placetype":"venue"
},
  "geometry": {"coordinates":[6.482336998,46.5726203918],"type":"Point"}
}