{
  "type": "Feature",
  "properties": {
    "iso:country":"CH",
    "sg:address":"Obstgartenstrasse 15",
    "sg:city":"Kloten",
    "sg:orig_category":"Interessenvertretungen",
    "sg:postcode":"8302",
    "sg:province":"Z\u00fcrich",
    "wof:name":"Arts Communications Dr. David Meili",
    "wof:placetype":"venue"
},
  "geometry": {"coordinates":[8.5789804459,47.4501953125],"type":"Point"}
}