{
  "type": "Feature",
  "properties": {
    "iso:country":"CH",
    "sg:address":"Ch. Des Dents Du Midi 46",
    "sg:city":"Aigle",
    "sg:orig_category":"Fachdetailhandel in Verkaufsr\u00e4umen",
    "sg:postcode":"1860",
    "sg:province":"Vaud",
    "wof:name":"Crisan Alexandru",
    "wof:placetype":"venue"
},
  "geometry": {"coordinates":[6.9593930244,46.3128814697],"type":"Point"}
}