{
  "type": "Feature",
  "properties": {
    "addr:full":"Rue Du Petit-beaulieu 4 Lausanne Vaud 1004",
    "addr:housenumber":"4",
    "addr:postcode":"1004",
    "addr:street":"Rue Du Petit-Beaulieu",
    "iso:country":"CH",
    "sg:address":"Rue Du Petit-beaulieu 4",
    "sg:city":"Lausanne",
    "sg:orig_category":"Arztpraxen",
    "sg:phone":"+41 22 734 59 66",
    "sg:postcode":"1004",
    "sg:province":"Vaud",
    "wof:name":"Dr M\u00e9d. Bijan Farpour M\u00e9decin Sp\u00e9cialiste Fmh",
    "wof:placetype":"venue"
},
  "geometry": {"coordinates":[6.118818,46.23074],"type":"Point"}
}