{
  "type": "Feature",
  "properties": {
    "iso:country":"CH",
    "sg:address":"Mittlere Gasse 11",
    "sg:city":"Baden",
    "sg:orig_category":"Detailhandel mit Uhren U Schmuck",
    "sg:phone":"+41 56 222 00 40",
    "sg:postcode":"5400",
    "sg:province":"Aargau",
    "wof:name":"Andreas Barany Goldschmied",
    "wof:placetype":"venue"
},
  "geometry": {"coordinates":[8.3072214127,47.4726791382],"type":"Point"}
}