{
  "type": "Feature",
  "properties": {
    "iso:country":"CH",
    "sg:address":"Via Cantonale",
    "sg:city":"Riazzino",
    "sg:orig_category":"Unclassifiable Establishments",
    "sg:phone":"+41 91 859 14 22",
    "sg:postcode":"6595",
    "sg:province":"Ticino",
    "wof:name":"Albergo Riazzino",
    "wof:placetype":"venue"
},
  "geometry": {"coordinates":[8.9000196457,46.1742401123],"type":"Point"}
}