{
  "type": "Feature",
  "properties": {
    "iso:country":"CH",
    "sg:address":"Hugenalp",
    "sg:city":"Krinau",
    "sg:classifiers":[
        {
            "category":"Restaurant",
            "type":"Food & Drink"
        }
    ],
    "sg:phone":"+41 17610815",
    "sg:postcode":"9622",
    "sg:province":"St. Gallen",
    "wof:name":"Restaurant Aemtlerst\u00fcbli",
    "wof:placetype":"venue"
},
  "geometry": {"coordinates":[8.4510612488,47.2760238647],"type":"Point"}
}