{
  "type": "Feature",
  "properties": {
    "iso:country":"CH",
    "sg:address":"Im D\u00f6rfli 20",
    "sg:city":"Dietikon",
    "sg:orig_category":"Politische Parteien Evangelische Volkspartei",
    "sg:phone":"+41 19504400",
    "sg:postcode":"8953",
    "sg:province":"Z\u00fcrich",
    "wof:name":"Evp Bezirkspartei Pf\u00e4ffikon",
    "wof:placetype":"venue"
},
  "geometry": {"coordinates":[8.7918844223,47.3739852905],"type":"Point"}
}