{
  "type": "Feature",
  "properties": {
    "iso:country":"CH",
    "sg:address":"Haldenstrasse 23",
    "sg:city":"Willisau",
    "sg:orig_category":"Sportvereine Ballsport Tennis",
    "sg:phone":"+41 71 222 53 08",
    "sg:postcode":"6130",
    "sg:province":"Luzern",
    "wof:name":"Hallen-tennis-club St.gallen",
    "wof:placetype":"venue"
},
  "geometry": {"coordinates":[9.3727722168,47.4320259094],"type":"Point"}
}