{
  "type": "Feature",
  "properties": {
    "iso:country":"CH",
    "sg:address":"Rue Du Ch\u00e2let 18a",
    "sg:city":"Tramelan",
    "sg:orig_category":"Sportvereine Ballsport Tennis",
    "sg:phone":"+41 32 487 57 64",
    "sg:postcode":"2720",
    "sg:province":"Bern",
    "wof:name":"Tc Tramelan",
    "wof:placetype":"venue"
},
  "geometry": {"coordinates":[7.0950188637,47.2245635986],"type":"Point"}
}