{
  "type": "Feature",
  "properties": {
    "iso:country":"CH",
    "sg:address":"M\u00fclihaldenstrasse 24",
    "sg:city":"Rickenbach-attikon",
    "sg:orig_category":"Vermietung von Luftfahrzeugen",
    "sg:postcode":"8544",
    "sg:province":"Z\u00fcrich",
    "wof:name":"Aets Aviation Engineering And Technical Support Gmbh",
    "wof:placetype":"venue"
},
  "geometry": {"coordinates":[8.797454834,47.5358734131],"type":"Point"}
}