{
  "type": "Feature",
  "properties": {
    "iso:country":"CH",
    "sg:address":"Leberngasse 21",
    "sg:city":"Olten",
    "sg:orig_category":"Unternehmensberatung",
    "sg:postcode":"4600",
    "sg:province":"Solothurn",
    "wof:name":"Wasteba Ag",
    "wof:placetype":"venue"
},
  "geometry": {"coordinates":[7.901263237,47.3490104675],"type":"Point"}
}