{
  "type": "Feature",
  "properties": {
    "addr:full":"Hertistrasse 3 Wallisellen Z\u00fcrich 8304",
    "addr:housenumber":"3",
    "addr:postcode":"8304",
    "addr:street":"Hertistrasse",
    "iso:country":"CH",
    "sg:address":"Hertistrasse 3",
    "sg:city":"Wallisellen",
    "sg:orig_category":"Autogaragen",
    "sg:phone":"+41 18300555",
    "sg:postcode":"8304",
    "sg:province":"Z\u00fcrich",
    "wof:name":"Domenico Cesare Garage",
    "wof:placetype":"venue"
},
  "geometry": {"coordinates":[8.582381,47.41333],"type":"Point"}
}