{
  "type": "Feature",
  "properties": {
    "iso:country":"CH",
    "sg:address":"Industriestrasse 25",
    "sg:city":"Liestal",
    "sg:classifiers":[
        {
            "category":"Retail",
            "subcategory":"Repair Shop",
            "type":"Services"
        }
    ],
    "sg:phone":"+41 61 901 47 40",
    "sg:postcode":"4410",
    "sg:province":"Basel-Landschaft",
    "sg:tags":[
        "hardening"
    ],
    "wof:name":"Grag H\u00e4rterei & Apparatebau Ag",
    "wof:placetype":"venue"
},
  "geometry": {"coordinates":[7.719817,47.496098],"type":"Point"}
}