{
  "type": "Feature",
  "properties": {
    "iso:country":"CH",
    "sg:address":"Place Du Prieur\u00e9 2 A 1009 Pully. Postfach",
    "sg:city":"Pully",
    "sg:orig_category":"RESTAURANTS: TEA-ROOMS",
    "sg:postcode":"1009",
    "sg:province":"Vaud",
    "wof:name":"Restaurant Le Prieur\u00e9, Theux B\u00e9rucq Michel",
    "wof:placetype":"venue"
},
  "geometry": {"coordinates":[6.6615591049,46.5092391968],"type":"Point"}
}