{
  "type": "Feature",
  "properties": {
    "iso:country":"CH",
    "sg:address":"Sunnmatt 6b 6410 Goldau. Postfach 230",
    "sg:city":"Goldau",
    "sg:orig_category":"Verkehrs- and Tourismusb\u00fcros",
    "sg:phone":"+41 41 855 54 30",
    "sg:postcode":"6410",
    "sg:province":"Schwyz",
    "wof:name":"Verkehrs-& Einwohnerverein Goldau Am Rigi",
    "wof:placetype":"venue"
},
  "geometry": {"coordinates":[8.5512485504,47.0556945801],"type":"Point"}
}