{
  "type": "Feature",
  "properties": {
    "iso:country":"CH",
    "sg:address":"Hotel Saanerhof",
    "sg:city":"Saanen",
    "sg:orig_category":"Maler U Glasergewerbe Malerei",
    "sg:phone":"+41 19327379",
    "sg:postcode":"3792",
    "sg:province":"Bern",
    "wof:name":"Malergesch\u00e4ft Fiorenza & Spasari",
    "wof:placetype":"venue"
},
  "geometry": {"coordinates":[8.7792577744,47.3301315308],"type":"Point"}
}