{
  "type": "Feature",
  "properties": {
    "iso:country":"CH",
    "sg:address":"Gorgen",
    "sg:city":"Ballwil",
    "sg:orig_category":"Allgemeiner Hoch U Tiefbau",
    "sg:phone":"+41 41 448 38 07",
    "sg:postcode":"6275",
    "sg:province":"Luzern",
    "wof:name":"Wiederkehr Kurt Baugesch\u00e4ft",
    "wof:placetype":"venue"
},
  "geometry": {"coordinates":[8.333095,47.156971],"type":"Point"}
}