{
  "type": "Feature",
  "properties": {
    "iso:country":"CH",
    "sg:address":"H\u00f6he\u00e4cker",
    "sg:city":"Oberaach",
    "sg:orig_category":"Vorschulen, Kinderg\u00e4rten",
    "sg:phone":"+41 71 411 67 52",
    "sg:postcode":"8587",
    "sg:province":"Thurgau",
    "wof:name":"Kindergarten",
    "wof:placetype":"venue"
},
  "geometry": {"coordinates":[9.2671279907,47.5582466125],"type":"Point"}
}