{
  "type": "Feature",
  "properties": {
    "iso:country":"CH",
    "sg:address":"Zugerstrasse 51 6340 Baar. Postfach",
    "sg:city":"Baar",
    "sg:orig_category":"Reinigungsgewerbe",
    "sg:phone":"+41 71 244 70 20",
    "sg:postcode":"6340",
    "sg:province":"Zug",
    "wof:name":"Thomann M. Ag",
    "wof:placetype":"venue"
},
  "geometry": {"coordinates":[9.3830432892,47.4364051819],"type":"Point"}
}