{
  "type": "Feature",
  "properties": {
    "addr:full":"Grande-rue 36 Le Sentier Vaud 1347",
    "addr:housenumber":"36",
    "addr:postcode":"1347",
    "addr:street":"Grande-Rue",
    "iso:country":"CH",
    "sg:address":"Grande-rue 36",
    "sg:city":"Le Sentier",
    "sg:classifiers":[
        {
            "category":"Banks & Credit Unions",
            "subcategory":"Bank",
            "type":"Services"
        }
    ],
    "sg:phone":"+41 21 845 42 72",
    "sg:postcode":"1347",
    "sg:province":"Vaud",
    "wof:name":"Banque Cantonale Vaudoise",
    "wof:placetype":"venue"
},
  "geometry": {"coordinates":[6.230933,46.607468],"type":"Point"}
}