{
  "type": "Feature",
  "properties": {
    "iso:country":"CH",
    "sg:address":"Falkenstrasse 28",
    "sg:city":"Z\u00fcrich",
    "sg:classifiers":[
        {
            "category":"Banks & Credit Unions",
            "subcategory":"Financial Services",
            "type":"Services"
        }
    ],
    "sg:phone":"+41 22 809 34 56",
    "sg:postcode":"8008",
    "sg:province":"Z\u00fcrich",
    "sg:tags":[
        "banking",
        "finance",
        "insurance"
    ],
    "wof:name":"Banque Cantonale De Gen\u00c8ve",
    "wof:placetype":"venue"
},
  "geometry": {"coordinates":[6.13993,46.203819],"type":"Point"}
}