{
  "type": "Feature",
  "properties": {
    "iso:country":"CH",
    "sg:address":"Burgstrasse 32",
    "sg:city":"Meilen",
    "sg:orig_category":"Unclassifiable Establishments",
    "sg:postcode":"8706",
    "sg:province":"Z\u00fcrich",
    "wof:name":"Damenturnverein Melchnau",
    "wof:placetype":"venue"
},
  "geometry": {"coordinates":[7.8352608681,47.2321281433],"type":"Point"}
}