{
  "type": "Feature",
  "properties": {
    "iso:country":"CH",
    "sg:address":"Bahnhofstrasse 26",
    "sg:city":"Hitzkirch",
    "sg:orig_category":"Grosshandel mit Erzen U Metallen Herstellung von sonstigen Metallwaren",
    "sg:phone":"+41 41 917 31 17",
    "sg:postcode":"6285",
    "sg:province":"Luzern",
    "wof:name":"Alpha Ag Zinnwaren & Sportmedaillen",
    "wof:placetype":"venue"
},
  "geometry": {"coordinates":[8.2562789917,47.2236175537],"type":"Point"}
}