{
  "type": "Feature",
  "properties": {
    "iso:country":"CH",
    "sg:address":"Rue Jean-grimoux 6",
    "sg:city":"Fribourg",
    "sg:orig_category":"Grosshandel mit sonstigen Maschinen U Ausr\u00fcstungen f\u00fcr Industrie, Handel U Schiffahrt Handelsvermitt",
    "sg:phone":"+41 26 322 59 89",
    "sg:postcode":"1700",
    "sg:province":"Fribourg",
    "wof:name":"Benz Fr\u00e8res Sa Freins & Embrayages",
    "wof:placetype":"venue"
},
  "geometry": {"coordinates":[7.1556258202,46.807308197],"type":"Point"}
}