{
  "type": "Feature",
  "properties": {
    "iso:country":"CH",
    "sg:address":"T\u00f6ntschiweg 1",
    "sg:city":"Klosters",
    "sg:orig_category":"Zimmerei, Dachdeckerei, Bauspenglerei U Abdichtung",
    "sg:phone":"+41 81 422 23 90",
    "sg:postcode":"7250",
    "sg:province":"Graubunden",
    "wof:name":"Hobi Hansj\u00f6rg Und Urs, Kleinzimmerei-treppenbau",
    "wof:placetype":"venue"
},
  "geometry": {"coordinates":[9.8886098862,46.8690719604],"type":"Point"}
}