{
  "type": "Feature",
  "properties": {
    "iso:country":"CH",
    "sg:address":"Schlierbacherstrasse 8",
    "sg:city":"B\u00fcron",
    "sg:orig_category":"Maler U Glasergewerbe Malerei",
    "sg:phone":"+41 27 934 20 43",
    "sg:postcode":"6233",
    "sg:province":"Luzern",
    "wof:name":"Dirren Romeo, Malerei Und Sandstrahlerei",
    "wof:placetype":"venue"
},
  "geometry": {"coordinates":[7.8033881187,46.2830123901],"type":"Point"}
}