{
  "type": "Feature",
  "properties": {
    "iso:country":"CH",
    "sg:address":"Allmend 3212 Gurmels. Postfach 4",
    "sg:city":"Gurmels",
    "sg:orig_category":"Sanit\u00e4r, Heizungs U L\u00fcftungsinstallation Sanit\u00e4rinstallation",
    "sg:phone":"+41 79 310 10 78",
    "sg:postcode":"3212",
    "sg:province":"Fribourg",
    "wof:name":"Hesa Ag",
    "wof:placetype":"venue"
},
  "geometry": {"coordinates":[7.1740250587,46.8945503235],"type":"Point"}
}