{
  "type": "Feature",
  "properties": {
    "iso:country":"CH",
    "sg:address":"Hauptstrasse 64 4132 Muttenz. Postfach 243",
    "sg:city":"Muttenz",
    "sg:orig_category":"Unternehmensberatung",
    "sg:phone":"+41 61 462 09 57",
    "sg:postcode":"4132",
    "sg:province":"Basel-Landschaft",
    "wof:name":"Domus Consulting Ag Unternehmensberatung",
    "wof:placetype":"venue"
},
  "geometry": {"coordinates":[7.6472978592,47.526008606],"type":"Point"}
}