{
  "type": "Feature",
  "properties": {
    "iso:country":"CH",
    "sg:address":"Frauenfelderstrasse 104",
    "sg:city":"Winterthur",
    "sg:orig_category":"Detailhandel mit Brot, Back U S\u00fcsswaren",
    "sg:phone":"+41 52 232 50 37",
    "sg:postcode":"8404",
    "sg:province":"Z\u00fcrich",
    "wof:name":"Edwin Z\u00fcrcher B\u00e4ckerei-konditorei",
    "wof:placetype":"venue"
},
  "geometry": {"coordinates":[8.751248,47.503159],"type":"Point"}
}