{
  "type": "Feature",
  "properties": {
    "iso:country":"CH",
    "sg:address":"Rue Emile-bo\u00e9chat 30-32",
    "sg:city":"Del\u00e9mont",
    "sg:orig_category":"Mechanik Mechanische Werkst\u00e4tten",
    "sg:phone":"+41 32 422 80 47",
    "sg:postcode":"2800",
    "sg:province":"Jura",
    "wof:name":"Srs M\u00e9canique S\u00e0rl",
    "wof:placetype":"venue"
},
  "geometry": {"coordinates":[7.3497071266,47.360496521],"type":"Point"}
}