{
  "type": "Feature",
  "properties": {
    "iso:country":"CH",
    "sg:address":"Konservenstrasse 620",
    "sg:city":"Hallau",
    "sg:orig_category":"Herstellung von \u00d6fen U Brennern Verlegen von Fliesen U Platten",
    "sg:phone":"+41 81 302 13 37",
    "sg:postcode":"8215",
    "sg:province":"Schaffhausen",
    "wof:name":"Schneider Ag, Bad Ragaz",
    "wof:placetype":"venue"
},
  "geometry": {"coordinates":[9.5007143021,47.0138702393],"type":"Point"}
}