{
  "type": "Feature",
  "properties": {
    "iso:country":"CH",
    "sg:address":"Alte Landstrasse 4",
    "sg:city":"Dulliken",
    "sg:orig_category":"Druckweiterverarbeitung",
    "sg:phone":"+41 62 295 35 38",
    "sg:postcode":"4657",
    "sg:province":"Solothurn",
    "wof:name":"Martin Flury Buchbinderei & Einrahmungen",
    "wof:placetype":"venue"
},
  "geometry": {"coordinates":[7.9447851181,47.3499488831],"type":"Point"}
}