{
  "type": "Feature",
  "properties": {
    "iso:country":"CH",
    "sg:address":"6747",
    "sg:city":"Chironico",
    "sg:orig_category":"Interessenvertretungen",
    "sg:postcode":"6747",
    "sg:province":"Ticino",
    "wof:name":"Fondazione Barudoni Pietro",
    "wof:placetype":"venue"
},
  "geometry": {"coordinates":[8.8444948196,46.4236946106],"type":"Point"}
}