{
  "type": "Feature",
  "properties": {
    "iso:country":"CH",
    "sg:address":"Eichholzstrasse 7",
    "sg:city":"Derendingen",
    "sg:orig_category":"P\u00e9dicure",
    "sg:phone":"+41 32 682 32 86",
    "sg:postcode":"4552",
    "sg:province":"Solothurn",
    "wof:name":"Jeannette Scheidegger P\u00e9dicure",
    "wof:placetype":"venue"
},
  "geometry": {"coordinates":[7.5875678062,47.1857414246],"type":"Point"}
}