{
  "type": "Feature",
  "properties": {
    "iso:country":"CH",
    "sg:address":"Wylerstrasse 65",
    "sg:city":"Bern",
    "sg:orig_category":"Grosshandel mit sonstigen Maschinen U Ausr\u00fcstungen f\u00fcr Industrie, Handel U Schiffahrt",
    "sg:phone":"+41 31 333 88 86",
    "sg:postcode":"3014",
    "sg:province":"Bern",
    "wof:name":"Tibor Csicsak Industrievertriebsmanagement",
    "wof:placetype":"venue"
},
  "geometry": {"coordinates":[7.448071003,46.9608345032],"type":"Point"}
}