{
  "type": "Feature",
  "properties": {
    "iso:country":"CH",
    "sg:address":"Thungschneitweg 51 3627 Heimberg. Postfach",
    "sg:city":"Heimberg",
    "sg:orig_category":"G\u00fcterbef\u00f6rderung im Strassenverkehr",
    "sg:postcode":"3627",
    "sg:province":"Bern",
    "wof:name":"Reber Transporte",
    "wof:placetype":"venue"
},
  "geometry": {"coordinates":[7.5879898071,47.0856628418],"type":"Point"}
}