{
  "type": "Feature",
  "properties": {
    "iso:country":"CH",
    "sg:address":"Zeltweg 50 8032 Z\u00fcrich. Postfach 8032 Z\u00fcrich",
    "sg:city":"Zust",
    "sg:orig_category":"Vereine Trachten",
    "sg:phone":"+41 21 923 39 00",
    "sg:postcode":"32",
    "wof:name":"Assoc.cantonale Du Costume Vaudois,c/o H\u00f4tel Famille",
    "wof:placetype":"venue"
},
  "geometry": {"coordinates":[5.1808700562,45.8973388672],"type":"Point"}
}