{
  "type": "Feature",
  "properties": {
    "iso:country":"CH",
    "sg:address":"Sihlbruggstrasse 105",
    "sg:city":"Baar",
    "sg:classifiers":[
        {
            "category":"Professional",
            "subcategory":"Accounting & Tax Preparation",
            "type":"Services"
        }
    ],
    "sg:phone":"+41 41 766 40 80",
    "sg:postcode":"6340",
    "sg:province":"Zug",
    "sg:tags":[
        "book-keeping"
    ],
    "wof:name":"Gyseler Consulting",
    "wof:placetype":"venue"
},
  "geometry": {"coordinates":[8.539093,47.197777],"type":"Point"}
}