{
  "type": "Feature",
  "properties": {
    "iso:country":"CH",
    "sg:address":"Rebbergstrasse 25",
    "sg:city":"Adlikon",
    "sg:orig_category":"Grosshandel mit Blumen U Pflanzen",
    "sg:phone":"+41 22 307 02 10",
    "sg:postcode":"8452",
    "sg:province":"Z\u00fcrich",
    "wof:name":"Plantes Et Fleurs Sa",
    "wof:placetype":"venue"
},
  "geometry": {"coordinates":[6.1422162056,46.1742095947],"type":"Point"}
}