{
  "type": "Feature",
  "properties": {
    "iso:country":"CH",
    "sg:address":"Alte Basadingerstrasse 2",
    "sg:city":"Diessenhofen",
    "sg:classifiers":[
        {
            "category":"Education",
            "subcategory":"Library",
            "type":"Public Place"
        }
    ],
    "sg:postcode":"8253",
    "sg:province":"Thurgau",
    "sg:tags":[
        "u",
        "bibliotheken",
        "archive"
    ],
    "wof:name":"Reformierte Pfarrbibliothek",
    "wof:placetype":"venue"
},
  "geometry": {"coordinates":[8.748486,47.687485],"type":"Point"}
}