{
  "type": "Feature",
  "properties": {
    "iso:country":"CH",
    "sg:address":"Via Francesco Soave 9",
    "sg:city":"Lugano",
    "sg:orig_category":"Vermietung U Verpachtung von eigenen Immobilien",
    "sg:postcode":"6900",
    "sg:province":"Ticino",
    "wof:name":"Si Dosso Sa",
    "wof:placetype":"venue"
},
  "geometry": {"coordinates":[8.9502868652,46.0043449402],"type":"Point"}
}