{
  "type": "Feature",
  "properties": {
    "iso:country":"CH",
    "sg:address":"Via Serafino Balestra 12",
    "sg:city":"Lugano",
    "sg:orig_category":"Finanzierungsinstitutionen",
    "sg:phone":"+41 22 908 03 33",
    "sg:postcode":"6900",
    "sg:province":"Ticino",
    "wof:name":"Gutzwiller Sa Gen\u00e8ve",
    "wof:placetype":"venue"
},
  "geometry": {"coordinates":[6.1479511261,46.2083740234],"type":"Point"}
}