{
  "type": "Feature",
  "properties": {
    "iso:country":"CH",
    "sg:address":"M\u00fchlaustrasse 19 8730 Uznach. Postfach",
    "sg:city":"Uznach",
    "sg:orig_category":"Unclassifiable Establishments",
    "sg:postcode":"8730",
    "sg:province":"St. Gallen",
    "wof:name":"Hadorn Transport-service Gmbh",
    "wof:placetype":"venue"
},
  "geometry": {"coordinates":[8.9970474243,47.2205162048],"type":"Point"}
}