{
  "type": "Feature",
  "properties": {
    "iso:country":"CH",
    "sg:address":"Tissot Avenue 16 1003 Lausanne. Postfach",
    "sg:city":"Lausanne",
    "sg:orig_category":"Interessenvertretungen",
    "sg:postcode":"1003",
    "sg:province":"Vaud",
    "wof:name":"Fondation Reymond Ir\u00e8ne Attribuer Chaque Ann\u00e9e Deux Prix Et Une Aide \u00e0 Des Artistes Suisses Romands, Etc.",
    "wof:placetype":"venue"
},
  "geometry": {"coordinates":[6.6361231804,46.5150604248],"type":"Point"}
}