{
  "type": "Feature",
  "properties": {
    "iso:country":"CH",
    "sg:address":"Eidgenossenweg 5 4052 Basel. Postfach 2222",
    "sg:city":"Basel",
    "sg:orig_category":"Erschliessung von Grundst\u00fccken",
    "sg:phone":"+41 61 313 37 72",
    "sg:postcode":"4052",
    "sg:province":"Basel-Stadt",
    "wof:name":"Baugenossenschaft Des Bundespersonals Basels Preisg\u00fcnstige Wohnungen F.d. Mgl.",
    "wof:placetype":"venue"
},
  "geometry": {"coordinates":[7.6162447929,47.5413589478],"type":"Point"}
}