{
  "type": "Feature",
  "properties": {
    "iso:country":"CH",
    "sg:address":"Route De C\u00e9ligny 2",
    "sg:city":"Crans-pr\u00e8s-c\u00e9ligny",
    "sg:orig_category":"Primarschulen",
    "sg:phone":"+41 22 776 53 05",
    "sg:postcode":"1299",
    "sg:province":"Vaud",
    "wof:name":"Ecole Primaire Coll\u00e8ge",
    "wof:placetype":"venue"
},
  "geometry": {"coordinates":[6.2030568123,46.3569335938],"type":"Point"}
}