{
  "type": "Feature",
  "properties": {
    "iso:country":"CH",
    "sg:address":"Fl\u00fchgasse 33e",
    "sg:city":"Z\u00fcrich",
    "sg:orig_category":"Unclassifiable Establishments",
    "sg:postcode":"8008",
    "sg:province":"Z\u00fcrich",
    "wof:name":"Bhp Architekten Ag",
    "wof:placetype":"venue"
},
  "geometry": {"coordinates":[8.565448761,47.3499908447],"type":"Point"}
}