{
  "type": "Feature",
  "properties": {
    "iso:country":"CH",
    "sg:address":"Fabrikstrasse",
    "sg:city":"Grabs",
    "sg:orig_category":"Detailhandel mit Schuhen Detailhandel mit Schuhen U Lederwaren",
    "sg:phone":"+41 81 771 41 71",
    "sg:postcode":"9472",
    "sg:province":"St. Gallen",
    "wof:name":"H\u00e4lg Markenschuhe Ag",
    "wof:placetype":"venue"
},
  "geometry": {"coordinates":[9.4521150589,47.1794166565],"type":"Point"}
}