{
  "type": "Feature",
  "properties": {
    "addr:full":"Edisriederstrasse 61 Sachseln Obwalden 6072",
    "addr:housenumber":"61",
    "addr:postcode":"6072",
    "addr:street":"Edisriederstrasse",
    "iso:country":"CH",
    "sg:address":"Edisriederstrasse 61",
    "sg:city":"Sachseln",
    "sg:orig_category":"Bauschreinerei Detailhandel mit M\u00f6beln",
    "sg:phone":"+41 41 660 49 60",
    "sg:postcode":"6072",
    "sg:province":"Obwalden",
    "wof:name":"Othmar Rohrer",
    "wof:placetype":"venue"
},
  "geometry": {"coordinates":[8.233087,46.862537],"type":"Point"}
}