{
  "type": "Feature",
  "properties": {
    "iso:country":"CH",
    "sg:address":"R\u00fctistrasse 3",
    "sg:city":"D\u00fcrnten",
    "sg:orig_category":"Kantonalbanken",
    "sg:phone":"+41 55 241 39 39",
    "sg:postcode":"8635",
    "sg:province":"Z\u00fcrich",
    "wof:name":"Z\u00fcrcher Kantonalbank",
    "wof:placetype":"venue"
},
  "geometry": {"coordinates":[8.8425102234,47.2776451111],"type":"Point"}
}