{
  "type": "Feature",
  "properties": {
    "iso:country":"CH",
    "sg:address":"Neustrasse 350 4623 Neuendorf. Postfach 18",
    "sg:city":"Neuendorf",
    "sg:orig_category":"Lagerung",
    "sg:phone":"+41 62 388 71 11",
    "sg:postcode":"4623",
    "sg:province":"Solothurn",
    "wof:name":"Migros-verteilbetrieb Neuendorf Ag",
    "wof:placetype":"venue"
},
  "geometry": {"coordinates":[7.7920598984,47.3056411743],"type":"Point"}
}