{
  "type": "Feature",
  "properties": {
    "iso:country":"CH",
    "sg:address":"Chemin Des Grangettes 8",
    "sg:city":"Ch\u00eane-bougeries",
    "sg:orig_category":"Hochschulen U h\u00f6here Ausbildung",
    "sg:postcode":"1224",
    "sg:province":"Gen\u00e8ve",
    "wof:name":"Focussi, O. Dufour",
    "wof:placetype":"venue"
},
  "geometry": {"coordinates":[6.1823449135,46.1989555359],"type":"Point"}
}