{
  "type": "Feature",
  "properties": {
    "iso:country":"CH",
    "sg:address":"See\u00e4cherstrasse 11",
    "sg:city":"Zurzach",
    "sg:orig_category":"Druckweiterverarbeitung Grafikateliers, Design",
    "sg:phone":"+41 56 249 01 44",
    "sg:postcode":"5330",
    "sg:province":"Aargau",
    "wof:name":"Ansatz Werbung & Beschriftung Gmbh",
    "wof:placetype":"venue"
},
  "geometry": {"coordinates":[8.3082857132,47.5806312561],"type":"Point"}
}