{
  "type": "Feature",
  "properties": {
    "iso:country":"CH",
    "sg:address":"Weidenweg 2b",
    "sg:city":"Lengnau",
    "sg:classifiers":[
        {
            "category":"Home & Garden",
            "subcategory":"Carpets & Floor Coverings",
            "type":"Retail Goods"
        }
    ],
    "sg:phone":"+41 32 652 97 32",
    "sg:postcode":"2543",
    "sg:province":"Bern",
    "sg:tags":[
        "polishing",
        "abrasive",
        "paste"
    ],
    "wof:name":"Rolf Etter",
    "wof:placetype":"venue"
},
  "geometry": {"coordinates":[7.36271,47.177982],"type":"Point"}
}