{
  "type": "Feature",
  "properties": {
    "iso:country":"CH",
    "sg:address":"Rue Des Laurelles 6",
    "sg:city":"Cossonay-ville",
    "sg:orig_category":"Versicherungen Hauptagenturen",
    "sg:phone":"+41 32 912 55 60",
    "sg:postcode":"1304",
    "sg:province":"Vaud",
    "wof:name":"Vaudoise Assurances Agence Principale",
    "wof:placetype":"venue"
},
  "geometry": {"coordinates":[6.8235998154,47.1000022888],"type":"Point"}
}