{
  "type": "Feature",
  "properties": {
    "iso:country":"CH",
    "sg:address":"Rotfarbstrasse 2",
    "sg:city":"Zofingen",
    "sg:orig_category":"Gymnastikschulen",
    "sg:phone":"+41 71 245 21 48",
    "sg:postcode":"4800",
    "sg:province":"Aargau",
    "wof:name":"Callanetics Studio Gymnastik-studio",
    "wof:placetype":"venue"
},
  "geometry": {"coordinates":[9.3943710327,47.4311828613],"type":"Point"}
}