{
  "type": "Feature",
  "properties": {
    "iso:country":"CH",
    "sg:address":"P\u00e9pinet Place 1 1003 Lausanne. Postfach",
    "sg:city":"Lausanne",
    "sg:orig_category":"Vermietung U Verpachtung von eigenen Immobilien",
    "sg:postcode":"1003",
    "sg:province":"Vaud",
    "wof:name":"Si Les Combes-la Roche",
    "wof:placetype":"venue"
},
  "geometry": {"coordinates":[7.1380748749,46.6968002319],"type":"Point"}
}