{
  "type": "Feature",
  "properties": {
    "iso:country":"CH",
    "sg:address":"Wieshofstrasse 44",
    "sg:city":"Winterthur",
    "sg:classifiers":[
        {
            "category":"Restaurant",
            "type":"Food & Drink"
        }
    ],
    "sg:phone":"+41 52 222 19 57",
    "sg:postcode":"8408",
    "sg:province":"Z\u00fcrich",
    "wof:name":"Pizzeria Monte Civetta",
    "wof:placetype":"venue"
},
  "geometry": {"coordinates":[8.6755714417,47.5019989014],"type":"Point"}
}