{
  "type": "Feature",
  "properties": {
    "addr:full":"Schwanengasse 1 Bern Bern 3011",
    "addr:housenumber":"1",
    "addr:postcode":"3011",
    "addr:street":"Schwanengasse",
    "iso:country":"CH",
    "sg:address":"Schwanengasse 1",
    "sg:city":"Bern",
    "sg:classifiers":[
        {
            "category":"Professional",
            "subcategory":"Computer Services",
            "type":"Services"
        }
    ],
    "sg:phone":"+41 31 328 75 75",
    "sg:postcode":"3011",
    "sg:province":"Bern",
    "sg:tags":[
        "control",
        "machinery",
        "software"
    ],
    "wof:name":"Autork Ag",
    "wof:placetype":"venue"
},
  "geometry": {"coordinates":[7.439055,46.947163],"type":"Point"}
}