{
  "type": "Feature",
  "properties": {
    "iso:country":"CH",
    "sg:address":"7075",
    "sg:city":"Churwalden",
    "sg:classifiers":[
        {
            "category":"Social Services",
            "subcategory":"Retirement Home",
            "type":"Services"
        }
    ],
    "sg:phone":"+41 71 333 13 10",
    "sg:postcode":"7075",
    "sg:province":"Graubunden",
    "sg:tags":[
        "pflegeheime",
        "u",
        "alters"
    ],
    "wof:name":"Altersheim Lindenh\u00fcgel",
    "wof:placetype":"venue"
},
  "geometry": {"coordinates":[9.396793,47.389557],"type":"Point"}
}