{
  "type": "Feature",
  "properties": {
    "addr:full":"Glarnerstrasse 79 Siebnen Schwyz 8854",
    "addr:housenumber":"79",
    "addr:postcode":"8854",
    "addr:street":"Glarnerstrasse;Schwyz",
    "iso:country":"CH",
    "sg:address":"Glarnerstrasse 79",
    "sg:city":"Siebnen",
    "sg:classifiers":[
        {
            "category":"Food & Beverages",
            "subcategory":"Cheese",
            "type":"Retail Goods"
        }
    ],
    "sg:phone":"+41 55 440 12 65",
    "sg:postcode":"8854",
    "sg:province":"Schwyz",
    "sg:tags":[
        "making",
        "supply"
    ],
    "wof:name":"Hannes Bruhin & Co",
    "wof:placetype":"venue"
},
  "geometry": {"coordinates":[8.908293,47.176094],"type":"Point"}
}