{
  "type": "Feature",
  "properties": {
    "iso:country":"CH",
    "sg:address":"M\u00fchlegasse 12",
    "sg:city":"Z\u00fcrich",
    "sg:orig_category":"Fachdetailhandel in Verkaufsr\u00e4umen",
    "sg:phone":"+41 27 927 13 01",
    "sg:postcode":"8001",
    "sg:province":"Z\u00fcrich",
    "wof:name":"Mattig-sport.",
    "wof:placetype":"venue"
},
  "geometry": {"coordinates":[8.1907701492,46.4355049133],"type":"Point"}
}