{
  "type": "Feature",
  "properties": {
    "iso:country":"CH",
    "sg:address":"Route Du Bisse",
    "sg:city":"Vercorin",
    "sg:orig_category":"Detailhandel mit Bekleidung Grosshandel mit Bekleidung",
    "sg:phone":"+41 27 456 54 14",
    "sg:postcode":"3967",
    "sg:province":"Valais",
    "wof:name":"Seconde Nature S\u00e0rl V\u00eatements & Accessoires",
    "wof:placetype":"venue"
},
  "geometry": {"coordinates":[7.528665,46.253868],"type":"Point"}
}