{
  "type": "Feature",
  "properties": {
    "iso:country":"CH",
    "sg:address":"Gl\u00e4rnischstrasse 5 8633 Wolfhausen. Postfach",
    "sg:city":"Wolfhausen",
    "sg:orig_category":"Detailhandel mit Metallwaren, Anstrichmitteln, Glaswaren, Bau U Heimwerkerbedarf",
    "sg:phone":"+41 55 243 42 20",
    "sg:postcode":"8633",
    "sg:province":"Z\u00fcrich",
    "wof:name":"Elem Intertecnic Ag",
    "wof:placetype":"venue"
},
  "geometry": {"coordinates":[8.793129921,47.2594070435],"type":"Point"}
}