{
  "type": "Feature",
  "properties": {
    "iso:country":"CH",
    "sg:address":"Vattel Rue Emer-de- 13",
    "sg:city":"Couvet",
    "sg:orig_category":"RESTAURANTS: TEA-ROOMS",
    "sg:postcode":"2108",
    "sg:province":"Neuch\u00e2tel",
    "wof:name":"Pereira A. S\u00e0rl",
    "wof:placetype":"venue"
},
  "geometry": {"coordinates":[6.6318588257,46.9237785339],"type":"Point"}
}