{
  "type": "Feature",
  "properties": {
    "addr:full":"Rue Du Tunnel 1 Lausanne Vaud 1005",
    "addr:housenumber":"1",
    "addr:postcode":"1005",
    "addr:street":"Rue Du Tunnel",
    "iso:country":"CH",
    "sg:address":"Rue Du Tunnel 1",
    "sg:city":"Lausanne",
    "sg:orig_category":"Arztpraxen",
    "sg:phone":"+41 21 312 11 18",
    "sg:postcode":"1005",
    "sg:province":"Vaud",
    "wof:name":"Dr M\u00e9d. Mir Ahmad Hedjazi M\u00e9decin G\u00e9n\u00e9raliste",
    "wof:placetype":"venue"
},
  "geometry": {"coordinates":[6.6324,46.524307],"type":"Point"}
}