{
  "type": "Feature",
  "properties": {
    "iso:country":"CH",
    "sg:address":"Kreuzweg 7",
    "sg:city":"Tentlingen",
    "sg:orig_category":"Wirtschaftspr\u00fcfung, Steuerberatung U Treuhand",
    "sg:postcode":"1734",
    "sg:province":"Fribourg",
    "wof:name":"Multi Bureau, F. Marguet",
    "wof:placetype":"venue"
},
  "geometry": {"coordinates":[7.1984381676,46.7678642273],"type":"Point"}
}