{
  "type": "Feature",
  "properties": {
    "iso:country":"CH",
    "sg:address":"Oberdorf 45 4458 Eptingen. Postfach",
    "sg:city":"Eptingen",
    "sg:orig_category":"Unternehmensberatung",
    "sg:postcode":"4458",
    "sg:province":"Basel-Landschaft",
    "wof:name":"Apertis Consulting Gmbh Dienstleistungen Im Bereich Der Unternehmensberatung, Bes. Organisationsberatung U. Projektmanagement",
    "wof:placetype":"venue"
},
  "geometry": {"coordinates":[7.8210201263,47.3846282959],"type":"Point"}
}