{
  "type": "Feature",
  "properties": {
    "iso:country":"CH",
    "sg:address":"Wichlernweg 10",
    "sg:city":"Kriens",
    "sg:orig_category":"Allgemeiner Hoch U Tiefbau Strassenbau",
    "sg:phone":"+41 41 320 99 20",
    "sg:postcode":"6010",
    "sg:province":"Luzern",
    "wof:name":"Renggli Hans Bau Ag Malters, Filiale Kriens",
    "wof:placetype":"venue"
},
  "geometry": {"coordinates":[8.272988,47.031555],"type":"Point"}
}