{
  "type": "Feature",
  "properties": {
    "iso:country":"CH",
    "sg:address":"Rue De La Gare 8",
    "sg:city":"Marin-centre",
    "sg:orig_category":"Nationale Postdienste",
    "sg:phone":"+41 32 753 16 89",
    "sg:postcode":"2074",
    "sg:province":"Neuch\u00e2tel",
    "wof:name":"La Poste Suisse",
    "wof:placetype":"venue"
},
  "geometry": {"coordinates":[7.0043578148,47.0089416504],"type":"Point"}
}