{
  "type": "Feature",
  "properties": {
    "iso:country":"CH",
    "sg:address":"Blumenfeldstrasse 22",
    "sg:city":"Z\u00fcrich",
    "sg:orig_category":"Interessenvertretungen",
    "sg:postcode":"8046",
    "sg:province":"Z\u00fcrich",
    "wof:name":"Sterbekasse Des Wirtevereins Z\u00fcrich",
    "wof:placetype":"venue"
},
  "geometry": {"coordinates":[8.5041227341,47.4217834473],"type":"Point"}
}