{
  "type": "Feature",
  "properties": {
    "iso:country":"CH",
    "sg:address":"Birren 13",
    "sg:city":"Seon",
    "sg:orig_category":"Instandhaltung U Reparatur von Automobilen",
    "sg:phone":"+41 77394148",
    "sg:postcode":"5703",
    "sg:province":"Aargau",
    "wof:name":"Birrengarage Gmbh",
    "wof:placetype":"venue"
},
  "geometry": {"coordinates":[8.1690254211,47.3622207642],"type":"Point"}
}