{
  "type": "Feature",
  "properties": {
    "iso:country":"CH",
    "sg:address":"Dorfstr. 41",
    "sg:city":"Grossaffoltern",
    "sg:orig_category":"Unclassifiable Establishments",
    "sg:postcode":"3257",
    "sg:province":"Bern",
    "wof:name":"Schwarzenbach Gartenbau",
    "wof:placetype":"venue"
},
  "geometry": {"coordinates":[7.3610239029,47.0664405823],"type":"Point"}
}