{
  "type": "Feature",
  "properties": {
    "iso:country":"CH",
    "sg:address":"Gerstenstrasse 6",
    "sg:city":"Wettingen",
    "sg:orig_category":"Bauingenieurb\u00fcros allgemein",
    "sg:phone":"+41 56 426 35 55",
    "sg:postcode":"5430",
    "sg:province":"Aargau",
    "wof:name":"Jakob Hasler Ingenieurb\u00fcro",
    "wof:placetype":"venue"
},
  "geometry": {"coordinates":[8.320165,47.458282],"type":"Point"}
}