{
  "type": "Feature",
  "properties": {
    "iso:country":"CH",
    "sg:address":"6512 Giubiasco Casella Postale",
    "sg:city":"Giubiasco",
    "sg:orig_category":"Herstellung von Kunststoffwaren Herstellung von Teppichen",
    "sg:phone":"+41 91 850 01 11",
    "sg:postcode":"6512",
    "sg:province":"Ticino",
    "wof:name":"Forbo-giubiasco Sa",
    "wof:placetype":"venue"
},
  "geometry": {"coordinates":[9.0108251572,46.1730804443],"type":"Point"}
}