{
  "type": "Feature",
  "properties": {
    "iso:country":"CH",
    "sg:address":"Oetlingerstrasse 10",
    "sg:city":"Basel",
    "sg:orig_category":"Grosshandel mit chemischen Erzeugnissen Herstellung von Klebstoffen U Gelatinen",
    "sg:phone":"+41 61 692 00 70",
    "sg:postcode":"4057",
    "sg:province":"Basel-Stadt",
    "wof:name":"Stiletto International Gmbh",
    "wof:placetype":"venue"
},
  "geometry": {"coordinates":[7.5875558853,47.5672302246],"type":"Point"}
}