{
  "type": "Feature",
  "properties": {
    "iso:country":"CH",
    "sg:address":"Klotenerstrasse 8 8303 Bassersdorf. Postfach",
    "sg:city":"Bassersdorf",
    "sg:orig_category":"Unclassifiable Establishments",
    "sg:postcode":"8303",
    "sg:province":"Z\u00fcrich",
    "wof:name":"Face And Body Care Russo Kosmetiksalon. Kosmetikartikel; Verkauf",
    "wof:placetype":"venue"
},
  "geometry": {"coordinates":[8.6280784607,47.4436378479],"type":"Point"}
}