{
  "type": "Feature",
  "properties": {
    "iso:country":"CH",
    "sg:address":"1318",
    "sg:city":"Pompaples",
    "sg:orig_category":"RESTAURANTS: TEA-ROOMS",
    "sg:phone":"+41 21 866 11 43",
    "sg:postcode":"1318",
    "sg:province":"Vaud",
    "wof:name":"Guzzante",
    "wof:placetype":"venue"
},
  "geometry": {"coordinates":[6.5223398209,46.6762695312],"type":"Point"}
}