{
  "type": "Feature",
  "properties": {
    "iso:country":"CH",
    "sg:address":"Chilenholzstrasse 29",
    "sg:city":"Wettswil",
    "sg:orig_category":"\u00dcbersetzungsb\u00fcros",
    "sg:phone":"+41 17000717",
    "sg:postcode":"8907",
    "sg:province":"Z\u00fcrich",
    "wof:name":"Christine Reinprecht Uebersetzungsb\u00fcro",
    "wof:placetype":"venue"
},
  "geometry": {"coordinates":[8.479839325,47.3315429688],"type":"Point"}
}