{
  "type": "Feature",
  "properties": {
    "iso:country":"CH",
    "sg:address":"Seestrasse 5 6330 Cham. Postfach",
    "sg:city":"Bern",
    "sg:orig_category":"Herstellung von sonstigen elektrischen Ausr\u00fcstungen",
    "sg:postcode":"3005",
    "sg:province":"Bern",
    "wof:name":"Lantronix International Ag",
    "wof:placetype":"venue"
},
  "geometry": {"coordinates":[8.4603786469,47.1799736023],"type":"Point"}
}