{
  "type": "Feature",
  "properties": {
    "iso:country":"CH",
    "sg:address":"Rue Fleur-de-lys 26",
    "sg:city":"Marin-centre",
    "sg:orig_category":"Fachdetailhandel in Verkaufsr\u00e4umen",
    "sg:phone":"+41 32 753 61 22",
    "sg:postcode":"2074",
    "sg:province":"Neuch\u00e2tel",
    "wof:name":"De Warenghien Isabelle",
    "wof:placetype":"venue"
},
  "geometry": {"coordinates":[7.0062298775,47.0124397278],"type":"Point"}
}