{
  "type": "Feature",
  "properties": {
    "iso:country":"CH",
    "sg:address":"Claridenweg 2",
    "sg:city":"Hombrechtikon",
    "sg:orig_category":"Architektur U Ingenieurb\u00fcros",
    "sg:phone":"+41 55 244 21 23",
    "sg:postcode":"8634",
    "sg:province":"Z\u00fcrich",
    "wof:name":"Hans-ulrich Genzel Ingenieurb\u00fcro",
    "wof:placetype":"venue"
},
  "geometry": {"coordinates":[8.766009,47.256001],"type":"Point"}
}