{
  "type": "Feature",
  "properties": {
    "iso:country":"CH",
    "sg:address":"Hausmatt 6 6422 Steinen. Postfach",
    "sg:city":"Brunnen",
    "sg:orig_category":"Grosshandel mit Getr\u00e4nken",
    "sg:postcode":"6440",
    "sg:province":"Schwyz",
    "wof:name":"Tandara Emil Weinhandel",
    "wof:placetype":"venue"
},
  "geometry": {"coordinates":[8.614938736,47.047794342],"type":"Point"}
}