{
  "type": "Feature",
  "properties": {
    "iso:country":"CH",
    "sg:address":"Weidli",
    "sg:city":"Diegten",
    "sg:orig_category":"Wohnheime f\u00fcr Kinder U Jugendliche",
    "sg:phone":"+41 61 971 38 55",
    "sg:postcode":"4457",
    "sg:province":"Basel-Landschaft",
    "wof:name":"Pfadiheim St.martin",
    "wof:placetype":"venue"
},
  "geometry": {"coordinates":[7.8105559349,47.4056282043],"type":"Point"}
}