{
  "type": "Feature",
  "properties": {
    "addr:full":"Poststrasse 1 8303 Bassersdorf. Postfach Bassersdorf Z\u00fcrich 8303",
    "addr:housenumber":"1",
    "addr:postcode":"8303;postfach;8303",
    "addr:street":"Poststrasse",
    "iso:country":"CH",
    "sg:address":"Poststrasse 1 8303 Bassersdorf. Postfach",
    "sg:city":"Bassersdorf",
    "sg:orig_category":"Arztpraxen",
    "sg:phone":"+41 18367635",
    "sg:postcode":"8303",
    "sg:province":"Z\u00fcrich",
    "wof:name":"Dr.med.rudolf Hammer Arzt F.allgemeine Medizin Fmh",
    "wof:placetype":"venue"
},
  "geometry": {"coordinates":[8.631058,47.442986],"type":"Point"}
}