{
  "type": "Feature",
  "properties": {
    "iso:country":"CH",
    "sg:address":"Bahnhofstrasse 21 6300 Zug. Postfach",
    "sg:city":"Unter\u00e4geri",
    "sg:orig_category":"Werbung",
    "sg:postcode":"6314",
    "sg:province":"Zug",
    "wof:name":"Adnet/netpub, Maurice Favre",
    "wof:placetype":"venue"
},
  "geometry": {"coordinates":[6.5580701828,46.5100784302],"type":"Point"}
}