{
  "type": "Feature",
  "properties": {
    "addr:full":"Niesenstrasse 11 Interlaken Bern 3800",
    "addr:housenumber":"11",
    "addr:postcode":"3800",
    "addr:street":"Niesenstrasse",
    "iso:country":"CH",
    "sg:address":"Niesenstrasse 11",
    "sg:city":"Interlaken",
    "sg:classifiers":[
        {
            "category":"Banks & Credit Unions",
            "subcategory":"Bank",
            "type":"Services"
        }
    ],
    "sg:phone":"+41 36226827",
    "sg:postcode":"3800",
    "sg:province":"Bern",
    "wof:name":"Rentenanstalt Swiss Life",
    "wof:placetype":"venue"
},
  "geometry": {"coordinates":[7.854584,46.682602],"type":"Point"}
}