{
  "type": "Feature",
  "properties": {
    "iso:country":"CH",
    "sg:address":"Stationsstrasse 80",
    "sg:city":"Rothenburg",
    "sg:orig_category":"Grosshandel mit landwirtschaftlichen Maschinen U Ger\u00e4ten Herstellung von sonstigen landwirtschaftlic",
    "sg:phone":"+41 41 280 13 43",
    "sg:postcode":"6023",
    "sg:province":"Luzern",
    "wof:name":"Emag-landmaschinen Ag",
    "wof:placetype":"venue"
},
  "geometry": {"coordinates":[8.2546472549,47.0932312012],"type":"Point"}
}