{
  "type": "Feature",
  "properties": {
    "iso:country":"CH",
    "sg:address":"Churerstrasse 68",
    "sg:city":"Altendorf",
    "sg:orig_category":"Landwirtschaftliche Maschinen Wartung and Reparatur Mechanische Werkst\u00e4tten",
    "sg:phone":"+41 55 442 36 26",
    "sg:postcode":"8852",
    "sg:province":"Schwyz",
    "wof:name":"Bruno Oetiker Mech.werkstatt Landmaschinen",
    "wof:placetype":"venue"
},
  "geometry": {"coordinates":[8.8438205719,47.1899261475],"type":"Point"}
}