{
  "type": "Feature",
  "properties": {
    "iso:country":"CH",
    "sg:address":"Dorfstrasse 49",
    "sg:city":"Amden",
    "sg:classifiers":[
        {
            "category":"Travel",
            "subcategory":"Hotels & Motels",
            "type":"Entertainment"
        }
    ],
    "sg:phone":"+41 55 611 11 36",
    "sg:postcode":"8873",
    "sg:province":"St. Gallen",
    "sg:tags":[
        "hotels",
        "mit",
        "restaurant"
    ],
    "wof:name":"Hotel Sch\u00e4fli",
    "wof:placetype":"venue"
},
  "geometry": {"coordinates":[9.1482458115,47.149055481],"type":"Point"}
}