{
  "type": "Feature",
  "properties": {
    "iso:country":"CH",
    "sg:address":"Bahnhofstrasse",
    "sg:city":"Zermatt",
    "sg:orig_category":"Detailhandel mit Uhren U Schmuck Reparatur von Uhren U Schmuck",
    "sg:phone":"+41 27 967 53 53",
    "sg:postcode":"3920",
    "sg:province":"Valais",
    "wof:name":"Bucherer Ag Uhren-schmuck-juwelen",
    "wof:placetype":"venue"
},
  "geometry": {"coordinates":[7.746240139,46.0201454163],"type":"Point"}
}