{
  "type": "Feature",
  "properties": {
    "iso:country":"CH",
    "sg:address":"Hallerstrasse 4",
    "sg:city":"Bern",
    "sg:orig_category":"Arztpraxen",
    "sg:phone":"+41 31 302 35 35",
    "sg:postcode":"3012",
    "sg:province":"Bern",
    "wof:name":"Dr.med.marianne L\u00e9pine Spezial\u00e4rztin Fmh",
    "wof:placetype":"venue"
},
  "geometry": {"coordinates":[7.434882,46.951836],"type":"Point"}
}