{
  "type": "Feature",
  "properties": {
    "iso:country":"CH",
    "sg:address":"1743",
    "sg:city":"Estavayer-gibloux",
    "sg:orig_category":"Sportvereine Ballsport Fussball",
    "sg:phone":"+41 26 411 46 50",
    "sg:postcode":"1743",
    "wof:name":"Fc Estavayer-le-gibloux",
    "wof:placetype":"venue"
},
  "geometry": {"coordinates":[7.0249800682,46.7235298157],"type":"Point"}
}