{
  "type": "Feature",
  "properties": {
    "iso:country":"CH",
    "sg:address":"Birkenweg 8 4310 Rheinfelden. Postfach",
    "sg:city":"Rheinfelden",
    "sg:orig_category":"Mit dem Versicherungsgewerbe verbundene T\u00e4tigkeiten",
    "sg:postcode":"4310",
    "sg:province":"Aargau",
    "wof:name":"Peba Wirtschaftsberatung Peromingo Versicherungs- U. Finanzberatung. Hypothekardarlehen Usw",
    "wof:placetype":"venue"
},
  "geometry": {"coordinates":[7.7951087952,47.5487709045],"type":"Point"}
}