{
  "type": "Feature",
  "properties": {
    "addr:full":"Schulstrasse 3 Niederurnen Glarus 8867",
    "addr:housenumber":"3",
    "addr:postcode":"8867",
    "addr:street":"Schulstrasse",
    "iso:country":"CH",
    "sg:address":"Schulstrasse 3",
    "sg:city":"Niederurnen",
    "sg:orig_category":"B\u00e4ckereien Konditoreien",
    "sg:phone":"+41 55 610 12 27",
    "sg:postcode":"8867",
    "sg:province":"Glarus",
    "wof:name":"Beat Hug B\u00e4ckerei-konditorei",
    "wof:placetype":"venue"
},
  "geometry": {"coordinates":[9.052071,47.125664],"type":"Point"}
}