{
  "type": "Feature",
  "properties": {
    "iso:country":"CH",
    "sg:address":"Epautheyres",
    "sg:city":"Essertines-yverdon",
    "sg:orig_category":"Sonstiger Grosshandel",
    "sg:phone":"+41 24 435 18 17",
    "sg:postcode":"1417",
    "sg:province":"Vaud",
    "wof:name":"Viauc Sa",
    "wof:placetype":"venue"
},
  "geometry": {"coordinates":[6.6422400475,46.7385101318],"type":"Point"}
}