{
  "type": "Feature",
  "properties": {
    "iso:country":"CH",
    "sg:address":"Winznauerstrasse 10",
    "sg:city":"Trimbach",
    "sg:classifiers":[
        {
            "category":"Government",
            "subcategory":"Post Office",
            "type":"Public Place"
        }
    ],
    "sg:phone":"+41 62 293 24 23",
    "sg:postcode":"4632",
    "sg:province":"Solothurn",
    "sg:tags":[
        "caf\u00e9s",
        "tea-rooms"
    ],
    "wof:name":"Caf\u00e9 Mohana",
    "wof:placetype":"venue"
},
  "geometry": {"coordinates":[7.9009699821,47.3614234924],"type":"Point"}
}