{
  "type": "Feature",
  "properties": {
    "iso:country":"CH",
    "sg:address":"Sternengasse 18 4051 Basel. Postfach 3423",
    "sg:city":"Basel",
    "sg:orig_category":"Konsulate",
    "sg:phone":"+41 61 331 82 97",
    "sg:postcode":"4002",
    "sg:province":"Basel-Stadt",
    "wof:name":"Konsulat Der Rep.san Marino",
    "wof:placetype":"venue"
},
  "geometry": {"coordinates":[7.5925130844,47.551738739],"type":"Point"}
}