{
  "type": "Feature",
  "properties": {
    "iso:country":"CH",
    "sg:address":"Feldbergstrasse 86 4057 Basel. Postfach",
    "sg:city":"Basel",
    "sg:orig_category":"Schreib U \u00dcbersetzungsb\u00fcros",
    "sg:phone":"+41 61 693 15 00",
    "sg:postcode":"4051",
    "sg:province":"Basel-Stadt",
    "wof:name":"Atlas, Sayin \u00dcbersetzungen V. D. Deutschen U. Englischen Sprache In D. T\u00fcrkische",
    "wof:placetype":"venue"
},
  "geometry": {"coordinates":[7.5935320854,47.5666351318],"type":"Point"}
}