{
  "type": "Feature",
  "properties": {
    "iso:country":"CH",
    "sg:address":"Gessnerallee 42",
    "sg:city":"Z\u00fcrich",
    "sg:orig_category":"Schreib U \u00dcbersetzungsb\u00fcros",
    "sg:postcode":"8001",
    "sg:province":"Z\u00fcrich",
    "wof:name":"A & D Print, Fischer Yvonne & Co Adressverwaltung, Textverarbeitung, B\u00fcroserivearbeiten, Edv-projektmanagemente Usw.",
    "wof:placetype":"venue"
},
  "geometry": {"coordinates":[8.5372962952,47.3769683838],"type":"Point"}
}