{
  "type": "Feature",
  "properties": {
    "iso:country":"CH",
    "sg:address":"Pilatusweg 22",
    "sg:city":"Rothrist",
    "sg:orig_category":"Grosshandel mit Parf\u00fcmerieartikeln U K\u00f6rperpflegemitteln Handelsvermittlung U Grosshandel mit Automo",
    "sg:phone":"+41 62 794 29 31",
    "sg:postcode":"4852",
    "sg:province":"Aargau",
    "wof:name":"Elizabeth Hallwyler Royal Hall Ventures",
    "wof:placetype":"venue"
},
  "geometry": {"coordinates":[7.9038472176,47.3038825989],"type":"Point"}
}