{
  "type": "Feature",
  "properties": {
    "iso:country":"CH",
    "sg:address":"Badenerstrasse 69-71",
    "sg:city":"Z\u00fcrich",
    "sg:orig_category":"Arztpraxen",
    "sg:phone":"+41 12910300",
    "sg:postcode":"8004",
    "sg:province":"Z\u00fcrich",
    "wof:name":"Dr.med.frank A. Gassmann Spezialarzt Fmh",
    "wof:placetype":"venue"
},
  "geometry": {"coordinates":[8.527213,47.373363],"type":"Point"}
}