{
  "type": "Feature",
  "properties": {
    "iso:country":"CH",
    "sg:address":"Plong Muling 7013 Domat/ems. Postfach 118",
    "sg:city":"Domat/ems",
    "sg:orig_category":"Grosshandel mit Maschinen U Ausr\u00fcstungen Grosshandel mit chemischen Erzeugnissen",
    "sg:phone":"+41 41 917 42 52",
    "sg:postcode":"7013",
    "sg:province":"Graubunden",
    "wof:name":"Walco-lin Reinigungstechnik Bonnet Max",
    "wof:placetype":"venue"
},
  "geometry": {"coordinates":[8.2404928207,47.2581214905],"type":"Point"}
}