{
  "type": "Feature",
  "properties": {
    "iso:country":"CH",
    "sg:address":"Bissen",
    "sg:city":"Saanen",
    "sg:orig_category":"Reiseb\u00fcros U Reiseveranstalter",
    "sg:phone":"+41 41 410 51 10",
    "sg:postcode":"3792",
    "sg:province":"Bern",
    "wof:name":"Hurter-reisen Ag, Weggisgasse 31, Luzern",
    "wof:placetype":"venue"
},
  "geometry": {"coordinates":[8.3055124283,47.052570343],"type":"Point"}
}