{
  "type": "Feature",
  "properties": {
    "iso:country":"CH",
    "sg:address":"Hofrainstrasse 11",
    "sg:city":"Eich",
    "sg:orig_category":"Fotografische Ateliers Fotografische Laboratorien",
    "sg:phone":"+41 41 460 12 13",
    "sg:postcode":"6205",
    "sg:province":"Luzern",
    "wof:name":"Werner Polinelli",
    "wof:placetype":"venue"
},
  "geometry": {"coordinates":[8.1645841599,47.1560630798],"type":"Point"}
}