{
  "type": "Feature",
  "properties": {
    "iso:country":"CH",
    "sg:address":"Alte Strasse 281c",
    "sg:city":"Thusis",
    "sg:orig_category":"Zahnarztpraxen",
    "sg:phone":"+41 81 632 11 11",
    "sg:postcode":"7430",
    "sg:province":"Graubunden",
    "wof:name":"Dr. Med. Dent. Markus H\u00e4nny Zahnarzt",
    "wof:placetype":"venue"
},
  "geometry": {"coordinates":[9.4391698837,46.6994857788],"type":"Point"}
}