{
  "type": "Feature",
  "properties": {
    "iso:country":"CH",
    "sg:address":"Pr\u00e9-naville Rue Du 6 1207 Gen\u00e8ve. Postfach",
    "sg:city":"Gen\u00e8ve",
    "sg:orig_category":"Vermittlungen Wohnungs-Agenturen,",
    "sg:postcode":"1201",
    "sg:province":"Gen\u00e8ve",
    "wof:name":"Home Sweet Home, Grange Alexandra",
    "wof:placetype":"venue"
},
  "geometry": {"coordinates":[6.162984848,46.2063217163],"type":"Point"}
}