{
  "type": "Feature",
  "properties": {
    "addr:full":"Aarbergergasse 46 Bern Bern 3011",
    "addr:housenumber":"46",
    "addr:postcode":"3011",
    "addr:street":"Aarbergergasse",
    "iso:country":"CH",
    "sg:address":"Aarbergergasse 46",
    "sg:city":"Bern",
    "sg:orig_category":"Arztpraxen",
    "sg:phone":"+41 31 312 15 00",
    "sg:postcode":"3011",
    "sg:province":"Bern",
    "wof:name":"Dr.med.witold Lesniak Spezialarzt Fmh",
    "wof:placetype":"venue"
},
  "geometry": {"coordinates":[7.442091,46.949844],"type":"Point"}
}