{
  "type": "Feature",
  "properties": {
    "iso:country":"CH",
    "sg:address":"Lourtier 1948 Lourtier. Postfach",
    "sg:city":"Lourtier",
    "sg:orig_category":"Zimmerei, Dachdeckerei, Bauspenglerei U Abdichtung",
    "sg:phone":"+41 32 373 15 52",
    "sg:postcode":"1948",
    "sg:province":"Valais",
    "wof:name":"Bruderer Ag, Holzbau",
    "wof:placetype":"venue"
},
  "geometry": {"coordinates":[7.2799639702,47.1229667664],"type":"Point"}
}