{
  "type": "Feature",
  "properties": {
    "iso:country":"CH",
    "sg:address":"4208",
    "sg:city":"Nunningen",
    "sg:orig_category":"Abwasserreinigung",
    "sg:phone":"+41 61 791 92 16",
    "sg:postcode":"4208",
    "sg:province":"Solothurn",
    "wof:name":"Kl\u00e4ranlage",
    "wof:placetype":"venue"
},
  "geometry": {"coordinates":[7.621168,47.393654],"type":"Point"}
}