{
  "type": "Feature",
  "properties": {
    "addr:full":"Bubenbergplatz 8 Bern Bern 3011",
    "addr:housenumber":"8",
    "addr:postcode":"3011",
    "addr:street":"Bubenbergplatz;Bern",
    "iso:country":"CH",
    "sg:address":"Bubenbergplatz 8",
    "sg:city":"Bern",
    "sg:orig_category":"Detailhandel mit Computern U Software",
    "sg:phone":"+41 31 311 55 11",
    "sg:postcode":"3011",
    "sg:province":"Bern",
    "wof:name":"Pc Hai Ag Computer-shop",
    "wof:placetype":"venue"
},
  "geometry": {"coordinates":[7.438571,46.947453],"type":"Point"}
}