{
  "type": "Feature",
  "properties": {
    "iso:country":"CH",
    "sg:address":"Scharfrichtergasse 3",
    "sg:city":"Chur",
    "sg:classifiers":[
        {
            "category":"Restaurant",
            "type":"Food & Drink"
        }
    ],
    "sg:phone":"+41 81 252 26 40",
    "sg:postcode":"7000",
    "sg:province":"Graubunden",
    "wof:name":"Restaurant Der Baron",
    "wof:placetype":"venue"
},
  "geometry": {"coordinates":[9.533862114,46.8510665894],"type":"Point"}
}