{
  "type": "Feature",
  "properties": {
    "iso:country":"CH",
    "sg:address":"Espenstrasse 9",
    "sg:city":"Wattwil",
    "sg:orig_category":"Unternehmensberatung",
    "sg:phone":"+41 71 988 72 05",
    "sg:postcode":"9630",
    "sg:province":"St. Gallen",
    "wof:name":"Er-consulting, Ehrbar R.",
    "wof:placetype":"venue"
},
  "geometry": {"coordinates":[9.0966682434,47.2946166992],"type":"Point"}
}