{
  "type": "Feature",
  "properties": {
    "iso:country":"CH",
    "sg:address":"Grundhofstrasse 15",
    "sg:city":"Herrliberg",
    "sg:orig_category":"Handelsvermittlung von Brennstoffen, Erzen, Metallen U Chemikalien",
    "sg:postcode":"8704",
    "sg:province":"Z\u00fcrich",
    "wof:name":"Gehrig Hellas Trade Rohstoffe; Im, Export, Handel",
    "wof:placetype":"venue"
},
  "geometry": {"coordinates":[8.6201438904,47.2862167358],"type":"Point"}
}