{
  "type": "Feature",
  "properties": {
    "iso:country":"CH",
    "sg:address":"Rue Des Cygnes 26",
    "sg:city":"Yverdon-les-bains",
    "sg:orig_category":"Interessenvertretungen",
    "sg:postcode":"1400",
    "sg:province":"Vaud",
    "wof:name":"Association Du V\u00f4-vietnam",
    "wof:placetype":"venue"
},
  "geometry": {"coordinates":[6.6356701851,46.7858963013],"type":"Point"}
}