{
  "type": "Feature",
  "properties": {
    "addr:full":"Denkmalstrasse 39 Neuenegg Bern 3176",
    "addr:housenumber":"39",
    "addr:postcode":"3176",
    "addr:street":"Denkmalstrasse;Bern",
    "iso:country":"CH",
    "sg:address":"Denkmalstrasse 39",
    "sg:city":"Neuenegg",
    "sg:orig_category":"Architektur U Ingenieurb\u00fcros",
    "sg:phone":"+41 79 652 01 73",
    "sg:postcode":"3176",
    "sg:province":"Bern",
    "wof:name":"Jenni Markus",
    "wof:placetype":"venue"
},
  "geometry": {"coordinates":[7.308251,46.896877],"type":"Point"}
}