{
  "type": "Feature",
  "properties": {
    "iso:country":"CH",
    "sg:address":"Adlerfeldstrasse 1",
    "sg:city":"Frenkendorf",
    "sg:orig_category":"Architekturb\u00fcros",
    "sg:phone":"+41 79 644 02 66",
    "sg:postcode":"4402",
    "sg:province":"Basel-Landschaft",
    "wof:name":"Heinz Spring Architekturb\u00fcro",
    "wof:placetype":"venue"
},
  "geometry": {"coordinates":[7.713152,47.503326],"type":"Point"}
}