{
  "type": "Feature",
  "properties": {
    "iso:country":"CH",
    "sg:address":"Obere Steinegg",
    "sg:city":"Appenzell",
    "sg:orig_category":"Allgemeiner Hoch U Tiefbau Strassenbau",
    "sg:phone":"+41 71 787 28 41",
    "sg:postcode":"9050",
    "sg:province":"Appenzell Innerhoden",
    "wof:name":"Rusch Erdbewegungen Gmbh",
    "wof:placetype":"venue"
},
  "geometry": {"coordinates":[9.407683,47.331436],"type":"Point"}
}