{
  "type": "Feature",
  "properties": {
    "iso:country":"CH",
    "sg:address":"Place Du Parc 4",
    "sg:city":"Broc",
    "sg:orig_category":"Kantonalbanken",
    "sg:phone":"+41 26 919 24 00",
    "sg:postcode":"1636",
    "sg:province":"Fribourg",
    "wof:name":"Banque Cantonale De Fribourg",
    "wof:placetype":"venue"
},
  "geometry": {"coordinates":[7.1005778313,46.6038169861],"type":"Point"}
}