{
  "type": "Feature",
  "properties": {
    "iso:country":"CH",
    "sg:address":"Birren 1 5703 Seon. Postfach",
    "sg:city":"Seon",
    "sg:orig_category":"Pensionskassen",
    "sg:phone":"+41 62 775 22 59",
    "sg:postcode":"5703",
    "sg:province":"Aargau",
    "wof:name":"Personalf\u00fcrsorge-stiftung Der Firma W. Fehlmann Ag, Seon",
    "wof:placetype":"venue"
},
  "geometry": {"coordinates":[8.1652002335,47.3624305725],"type":"Point"}
}