{
  "type": "Feature",
  "properties": {
    "iso:country":"CH",
    "sg:address":"Churfirstenstrasse 17",
    "sg:city":"D\u00fcbendorf",
    "sg:orig_category":"Zimmerei, Dachdeckerei, Bauspenglerei U Abdichtung",
    "sg:phone":"+41 33 676 23 67",
    "sg:postcode":"8600",
    "sg:province":"Z\u00fcrich",
    "wof:name":"Lehmann Fritz",
    "wof:placetype":"venue"
},
  "geometry": {"coordinates":[7.7004852295,46.629989624],"type":"Point"}
}