{
  "type": "Feature",
  "properties": {
    "iso:country":"CH",
    "sg:address":"Rue Margencel 27",
    "sg:city":"Aigle",
    "sg:orig_category":"Physiotherapie",
    "sg:phone":"+41 24 466 46 11",
    "sg:postcode":"1860",
    "sg:province":"Vaud",
    "wof:name":"Claire Jalla Physioth\u00e9rapie",
    "wof:placetype":"venue"
},
  "geometry": {"coordinates":[6.9649782181,46.3180389404],"type":"Point"}
}