{
  "type": "Feature",
  "properties": {
    "iso:country":"CH",
    "sg:address":"Grand-rue 5-7",
    "sg:city":"Nyon",
    "sg:orig_category":"Interessenvertretungen",
    "sg:postcode":"1260",
    "sg:province":"Vaud",
    "wof:name":"Fondation I-with.org",
    "wof:placetype":"venue"
},
  "geometry": {"coordinates":[6.2390160561,46.3823852539],"type":"Point"}
}