{
  "type": "Feature",
  "properties": {
    "iso:country":"CH",
    "sg:address":"Breitmattboden 35",
    "sg:city":"Gipf-oberfrick",
    "sg:orig_category":"Physiotherapie",
    "sg:phone":"+41 52 365 31 59",
    "sg:postcode":"5073",
    "sg:province":"Aargau",
    "wof:name":"Agnes M\u00fcller Physiotherapie",
    "wof:placetype":"venue"
},
  "geometry": {"coordinates":[8.8987197876,47.4795341492],"type":"Point"}
}