{
  "type": "Feature",
  "properties": {
    "iso:country":"CH",
    "sg:address":"Fabrikstrasse 13",
    "sg:city":"Obfelden",
    "sg:orig_category":"Fahrschulen, Flugschulen",
    "sg:phone":"+41 17618822",
    "sg:postcode":"8912",
    "sg:province":"Z\u00fcrich",
    "wof:name":"Verkehrsinstitut Albis Ag",
    "wof:placetype":"venue"
},
  "geometry": {"coordinates":[8.4154863358,47.2629737854],"type":"Point"}
}