{
  "type": "Feature",
  "properties": {
    "iso:country":"CH",
    "sg:address":"Industriestrasse 8 8404 Stadel(winterthur). Postfach 1084",
    "sg:city":"Winterthur",
    "sg:orig_category":"Verlagsgewerbe Zeitungsdruck",
    "sg:phone":"+41 31 311 44 12",
    "sg:postcode":"8401",
    "sg:province":"Z\u00fcrich",
    "wof:name":"Finanz & Wirtschaft Redaktion Bern",
    "wof:placetype":"venue"
},
  "geometry": {"coordinates":[7.4451880455,46.9491004944],"type":"Point"}
}