{
  "type": "Feature",
  "properties": {
    "iso:country":"CH",
    "sg:address":"Champs-montants 16b Case Postale 36",
    "sg:city":"Marin-epagnier",
    "sg:classifiers":[
        {
            "category":"Wholesale",
            "subcategory":"Machinery & Supplies",
            "type":"Manufacturing & Wholesale Goods"
        }
    ],
    "sg:phone":"+41 32 756 75 00",
    "sg:postcode":"2074",
    "sg:province":"Neuch\u00e2tel",
    "sg:tags":[
        "equipment",
        "equipement",
        "precision",
        "timekeeping"
    ],
    "wof:name":"Bertolucci Sa",
    "wof:placetype":"venue"
},
  "geometry": {"coordinates":[5.6688599586,50.0393218994],"type":"Point"}
}