{
  "type": "Feature",
  "properties": {
    "iso:country":"CH",
    "sg:address":"Ursulaweg 22",
    "sg:city":"Winterthur",
    "sg:orig_category":"Sportvereine Ballsport Handball",
    "sg:phone":"+41 52 242 37 90",
    "sg:postcode":"8404",
    "sg:province":"Z\u00fcrich",
    "wof:name":"Athletic 57",
    "wof:placetype":"venue"
},
  "geometry": {"coordinates":[8.7617330551,47.5198478699],"type":"Point"}
}