{
  "type": "Feature",
  "properties": {
    "iso:country":"CH",
    "sg:address":"Amthausquai 33",
    "sg:city":"Olten",
    "sg:orig_category":"Arztpraxen",
    "sg:phone":"+41 62 212 11 41",
    "sg:postcode":"4600",
    "sg:province":"Solothurn",
    "wof:name":"Dr.med.klaus L\u00e4mmli Spezialarzt Fmh",
    "wof:placetype":"venue"
},
  "geometry": {"coordinates":[7.905448,47.35482],"type":"Point"}
}