{
  "type": "Feature",
  "properties": {
    "iso:country":"CH",
    "sg:address":"Beaumont Route De 2 1700 Freiburg. Postfach",
    "sg:city":"Fribourg",
    "sg:orig_category":"Pensionskassen",
    "sg:postcode":"1702",
    "sg:province":"Fribourg",
    "wof:name":"Fonds De Pr\u00e9voyance De La Fribourgeoise G\u00e9n\u00e9rale D'assurances Sa",
    "wof:placetype":"venue"
},
  "geometry": {"coordinates":[7.1451158524,46.7960395813],"type":"Point"}
}