{
  "type": "Feature",
  "properties": {
    "iso:country":"CH",
    "sg:address":"1891",
    "sg:city":"V\u00e9rossaz",
    "sg:orig_category":"Maler U Glasergewerbe Tapeziererei",
    "sg:phone":"+41 79 416 62 22",
    "sg:postcode":"1891",
    "sg:province":"Valais",
    "wof:name":"Gherardi Ren\u00e9",
    "wof:placetype":"venue"
},
  "geometry": {"coordinates":[8.8357276917,47.3056488037],"type":"Point"}
}