{
  "type": "Feature",
  "properties": {
    "iso:country":"CH",
    "sg:address":"8754",
    "sg:city":"Netstal",
    "sg:orig_category":"Pensionskassen",
    "sg:postcode":"8754",
    "sg:province":"Glarus",
    "wof:name":"Pensionsstiftung F\u00fcr Die Angestellten Und Arbeiter Der Vereinigten Papierfabriken Netstal Ag",
    "wof:placetype":"venue"
},
  "geometry": {"coordinates":[9.0356998444,47.0660896301],"type":"Point"}
}