{
  "type": "Feature",
  "properties": {
    "iso:country":"CH",
    "sg:address":"Gartenstrasse 3",
    "sg:city":"Zug",
    "sg:orig_category":"Non-Classified Establishments",
    "sg:postcode":"6300",
    "sg:province":"Zug",
    "wof:name":"Centratech Ag",
    "wof:placetype":"venue"
},
  "geometry": {"coordinates":[8.5148210526,47.1700744629],"type":"Point"}
}