{
  "type": "Feature",
  "properties": {
    "iso:country":"CH",
    "sg:address":"Obere Bahnhofstrasse 3714 Frutigen. Postfach",
    "sg:city":"Frutigen",
    "sg:orig_category":"RESTAURANTS: TEA-ROOMS",
    "sg:postcode":"3714",
    "sg:province":"Bern",
    "wof:name":"Confiserie Tea-room Zurcher & Cie",
    "wof:placetype":"venue"
},
  "geometry": {"coordinates":[6.857986927,46.9656143188],"type":"Point"}
}