{
  "type": "Feature",
  "properties": {
    "iso:country":"CH",
    "sg:address":"Chemin Du Fr\u00eane 11",
    "sg:city":"Lausanne",
    "sg:orig_category":"Kosmetikinstitute",
    "sg:phone":"+41 21 647 79 33",
    "sg:postcode":"1004",
    "sg:province":"Vaud",
    "wof:name":"Ir\u00e8ne Jaccard Institut De Beaut\u00e9 Genevi\u00e8ve",
    "wof:placetype":"venue"
},
  "geometry": {"coordinates":[6.6277837753,46.5254707336],"type":"Point"}
}