{
  "type": "Feature",
  "properties": {
    "iso:country":"CH",
    "sg:address":"1195",
    "sg:city":"Dully",
    "sg:orig_category":"Sonstige mit Sport verbundene T\u00e4tigkeiten",
    "sg:postcode":"1195",
    "sg:province":"Vaud",
    "wof:name":"Swiss Team For The America's Cup, Stac",
    "wof:placetype":"venue"
},
  "geometry": {"coordinates":[6.2956819534,46.4300880432],"type":"Point"}
}