{
  "type": "Feature",
  "properties": {
    "iso:country":"CH",
    "sg:address":"Geissacher",
    "sg:city":"Berschis",
    "sg:orig_category":"Non-Classified Establishments",
    "sg:postcode":"8892",
    "sg:province":"St. Gallen",
    "wof:name":"Jakob T\u00e4schler Buchhaltungen & Beratungen",
    "wof:placetype":"venue"
},
  "geometry": {"coordinates":[9.3441972733,47.1073684692],"type":"Point"}
}