{
  "type": "Feature",
  "properties": {
    "iso:country":"CH",
    "sg:address":"Studbachstrasse 15",
    "sg:city":"Hinwil",
    "sg:orig_category":"Grosshandel mit sonstigen Halbwaren Herstellung von Verpackungsmitteln aus Holz",
    "sg:phone":"+41 79 355 82 13",
    "sg:postcode":"8340",
    "sg:province":"Z\u00fcrich",
    "wof:name":"Nicola Fiore Gmbh",
    "wof:placetype":"venue"
},
  "geometry": {"coordinates":[8.8190374374,47.3039855957],"type":"Point"}
}