{
  "type": "Feature",
  "properties": {
    "iso:country":"CH",
    "sg:address":"Chemin Chenalettaz 7a",
    "sg:city":"Blonay",
    "sg:orig_category":"Autoelektro and -elektronik Werkst\u00e4tten -Einzelhandel mit Automobilteilen U Zubeh\u00f6r",
    "sg:phone":"+41 21 943 38 43",
    "sg:postcode":"1807",
    "sg:province":"Vaud",
    "wof:name":"Pierre Brunisholz Installation D'auto-radios",
    "wof:placetype":"venue"
},
  "geometry": {"coordinates":[6.887633,46.46833],"type":"Point"}
}