{
  "type": "Feature",
  "properties": {
    "iso:country":"CH",
    "sg:address":"B\u00fctzbergstrasse 2",
    "sg:city":"Aarwangen",
    "sg:orig_category":"Herstellung von keramischen Wand U Bodenfliesen U platten",
    "sg:postcode":"4912",
    "sg:province":"Bern",
    "wof:name":"Hebu-keramik, Burkhard Beat + Hegi Samuel",
    "wof:placetype":"venue"
},
  "geometry": {"coordinates":[7.7734050751,47.2344436646],"type":"Point"}
}