{
  "type": "Feature",
  "properties": {
    "iso:country":"CH",
    "sg:address":"6060",
    "sg:city":"Sarnen",
    "sg:orig_category":"Sportvereine Behindertensport",
    "sg:postcode":"6060",
    "sg:province":"Obwalden",
    "wof:name":"Behindertensportclub Wohlen-lenzburg",
    "wof:placetype":"venue"
},
  "geometry": {"coordinates":[8.2780704498,47.3505363464],"type":"Point"}
}