{
  "type": "Feature",
  "properties": {
    "addr:full":"Alleestrasse 50 Romanshorn Thurgau 8590",
    "addr:housenumber":"50",
    "addr:postcode":"8590",
    "addr:street":"Alleestrasse",
    "iso:country":"CH",
    "sg:address":"Alleestrasse 50",
    "sg:city":"Romanshorn",
    "sg:classifiers":[
        {
            "category":"Education",
            "subcategory":"Library",
            "type":"Public Place"
        }
    ],
    "sg:phone":"+41 71 463 60 44",
    "sg:postcode":"8590",
    "sg:province":"Thurgau",
    "sg:tags":[
        "u",
        "bibliotheken",
        "archive"
    ],
    "wof:name":"Gemeindebibliothek",
    "wof:placetype":"venue"
},
  "geometry": {"coordinates":[9.377952,47.563522],"type":"Point"}
}