{
  "type": "Feature",
  "properties": {
    "iso:country":"CH",
    "sg:address":"Innere Margarethenstrasse 9",
    "sg:city":"Basel",
    "sg:orig_category":"Kosmetikinstitute",
    "sg:phone":"+41 61 281 33 10",
    "sg:postcode":"4051",
    "sg:province":"Basel-Stadt",
    "wof:name":"Silvia Kramer Kosmetikinstitut & Solarium",
    "wof:placetype":"venue"
},
  "geometry": {"coordinates":[7.5870141983,47.5502891541],"type":"Point"}
}