{
  "type": "Feature",
  "properties": {
    "iso:country":"CH",
    "sg:address":"Rue Du Lac 18 1400 Yverdon-les-bains. Postfach",
    "sg:city":"Yverdon",
    "sg:orig_category":"Reiseb\u00fcros",
    "sg:phone":"+41 24 425 47 21",
    "sg:postcode":"1401",
    "sg:province":"Vaud",
    "wof:name":"Kuoni Voyages Sa",
    "wof:placetype":"venue"
},
  "geometry": {"coordinates":[6.640212059,46.779258728],"type":"Point"}
}