{
  "type": "Feature",
  "properties": {
    "iso:country":"CH",
    "sg:address":"Eisenwerkstrasse 20a 8500 Frauenfeld. Postfach",
    "sg:city":"Frauenfeld",
    "sg:orig_category":"Hardwareberatung",
    "sg:phone":"+41 52 722 20 45",
    "sg:postcode":"8500",
    "sg:province":"Thurgau",
    "wof:name":"Ttweb Gmbh Pc, Netzwerk, U. Kommunikationsl\u00f6sungen; Handel Usw",
    "wof:placetype":"venue"
},
  "geometry": {"coordinates":[8.8948326111,47.5609550476],"type":"Point"}
}