{
  "type": "Feature",
  "properties": {
    "iso:country":"CH",
    "sg:address":"R\u00fctihofstrasse 139",
    "sg:city":"Siglistorf",
    "sg:orig_category":"Softwareentwicklung U beratung",
    "sg:phone":"+41 56 243 16 74",
    "sg:postcode":"5462",
    "sg:province":"Aargau",
    "wof:name":"Martin Hochstrasser Sap-entwicklungen",
    "wof:placetype":"venue"
},
  "geometry": {"coordinates":[8.3845014572,47.5421867371],"type":"Point"}
}