{
  "type": "Feature",
  "properties": {
    "iso:country":"CH",
    "sg:address":"Zielstrasse 9",
    "sg:city":"Amriswil",
    "sg:orig_category":"Zahnarztpraxen",
    "sg:phone":"+41 71 411 41 81",
    "sg:postcode":"8580",
    "sg:province":"Thurgau",
    "wof:name":"Dr.med.dent.hans C. Wuhrmann Zahnarzt",
    "wof:placetype":"venue"
},
  "geometry": {"coordinates":[9.2981681824,47.5469970703],"type":"Point"}
}