{
  "type": "Feature",
  "properties": {
    "iso:country":"CH",
    "sg:address":"Bizenenstrasse 3 B",
    "sg:city":"Muttenz",
    "sg:orig_category":"Bauschreinerei Innenausbau",
    "sg:phone":"+41 61 467 94 68",
    "sg:postcode":"4132",
    "sg:province":"Basel-Landschaft",
    "wof:name":"Bauhaus Muttenz F. M\u00fcnch + R. Hochuli",
    "wof:placetype":"venue"
},
  "geometry": {"coordinates":[7.650881,47.528496],"type":"Point"}
}