{
  "type": "Feature",
  "properties": {
    "iso:country":"CH",
    "sg:address":"Lindenstrasse 73",
    "sg:city":"St.gallen",
    "sg:orig_category":"Herstellung von Konstruktionsteilen, Fertigbauteilen U Ausbauelementen aus Holz Innenausbau",
    "sg:phone":"+41 71 222 35 76",
    "sg:postcode":"9000",
    "sg:province":"St. Gallen",
    "wof:name":"U. Menzi",
    "wof:placetype":"venue"
},
  "geometry": {"coordinates":[9.3936929703,47.4332427979],"type":"Point"}
}