{
  "type": "Feature",
  "properties": {
    "iso:country":"CH",
    "sg:address":"Derendingenstrasse 12",
    "sg:city":"Deitingen",
    "sg:orig_category":"Herstellung von Frucht U Gem\u00fcses\u00e4ften Herstellung von Obst U Fruchtweinen",
    "sg:phone":"+41 32 614 23 02",
    "sg:postcode":"4543",
    "sg:province":"Solothurn",
    "wof:name":"Xaver Niggli Brennerei & Mosterei",
    "wof:placetype":"venue"
},
  "geometry": {"coordinates":[7.615447998,47.2095108032],"type":"Point"}
}