{
  "type": "Feature",
  "properties": {
    "iso:country":"CH",
    "sg:address":"G\u00fcterstrasse 20 4900 Langenthal. Postfach",
    "sg:city":"Langenthal",
    "sg:orig_category":"Bauschreinerei Zimmerei, Dachdeckerei, Bauspenglerei U Abdichtung",
    "sg:phone":"+41 62 919 07 07",
    "sg:postcode":"4900",
    "sg:province":"Bern",
    "wof:name":"Egger Hector Holzbau Ag",
    "wof:placetype":"venue"
},
  "geometry": {"coordinates":[7.782054,47.21666],"type":"Point"}
}