{
  "type": "Feature",
  "properties": {
    "iso:country":"CH",
    "sg:address":"Reitnauerstrasse",
    "sg:city":"Winikon",
    "sg:orig_category":"Sanit\u00e4rinstallation",
    "sg:phone":"+41 62 824 84 59",
    "sg:postcode":"6235",
    "sg:province":"Luzern",
    "wof:name":"Robert Gerber Sanit.anl. Boden-& Wandbel\u00e4ge",
    "wof:placetype":"venue"
},
  "geometry": {"coordinates":[8.0733680725,47.3913002014],"type":"Point"}
}