{
  "type": "Feature",
  "properties": {
    "iso:country":"CH",
    "sg:address":"Stockistrasse 28",
    "sg:city":"Glattfelden",
    "sg:orig_category":"Non-Classified Establishments",
    "sg:phone":"+41 18673809",
    "sg:postcode":"8192",
    "sg:province":"Z\u00fcrich",
    "wof:name":"Hauser Gartenpflege Gmbh",
    "wof:placetype":"venue"
},
  "geometry": {"coordinates":[8.5000972748,47.5565376282],"type":"Point"}
}