{
  "type": "Feature",
  "properties": {
    "iso:country":"CH",
    "sg:address":"Marcolet Route De 13 1023 Crissier. Postfach",
    "sg:city":"Crissier",
    "sg:orig_category":"Instandhaltung U Reparatur von Automobilen",
    "sg:phone":"+41 32 913 46 81",
    "sg:postcode":"1023",
    "sg:province":"Vaud",
    "wof:name":"Autodelta Sa Garage & Carrosserie",
    "wof:placetype":"venue"
},
  "geometry": {"coordinates":[6.8200130463,47.0976333618],"type":"Point"}
}