{
  "type": "Feature",
  "properties": {
    "iso:country":"CH",
    "sg:address":"Iles Falcon",
    "sg:city":"Sierre",
    "sg:orig_category":"Erzeugung U Erstbearbeitung von Aluminium Grosshandel mit Baumaterialien",
    "sg:phone":"+41 27 455 82 64",
    "sg:postcode":"3960",
    "sg:province":"Valais",
    "wof:name":"Pyrotek Sa",
    "wof:placetype":"venue"
},
  "geometry": {"coordinates":[7.5508790016,46.2876243591],"type":"Point"}
}