{
  "type": "Feature",
  "properties": {
    "iso:country":"CH",
    "sg:address":"Badstrasse 23 5400 Baden. Postfach",
    "sg:city":"Baden",
    "sg:orig_category":"Detailhandel mit B\u00fcchern Detailhandel mit B\u00fcchern, Zeitungen, Schreib U Papeteriewaren",
    "sg:phone":"+41 56 222 53 47",
    "sg:postcode":"5401",
    "sg:province":"Aargau",
    "wof:name":"B\u00fccher Doppler Ag Buchhandlung",
    "wof:placetype":"venue"
},
  "geometry": {"coordinates":[8.308359,47.475288],"type":"Point"}
}