{
  "type": "Feature",
  "properties": {
    "iso:country":"CH",
    "sg:address":"5012",
    "sg:city":"Sch\u00f6nenwerd",
    "sg:orig_category":"Bauspenglerei Dachdeckerei",
    "sg:phone":"+41 61 461 55 44",
    "sg:postcode":"5012",
    "sg:province":"Solothurn",
    "wof:name":"Fladag Ag",
    "wof:placetype":"venue"
},
  "geometry": {"coordinates":[7.654376,47.530235],"type":"Point"}
}