{
  "type": "Feature",
  "properties": {
    "iso:country":"CH",
    "sg:address":"Dr.max W\u00fcthrich-strasse 2",
    "sg:city":"Rheinfelden",
    "sg:orig_category":"Institutionen f\u00fcr Behinderte Sonderschulen",
    "sg:phone":"+41 61 831 69 95",
    "sg:postcode":"4310",
    "sg:province":"Aargau",
    "wof:name":"Heilp\u00e4dagogische Sonderschule",
    "wof:placetype":"venue"
},
  "geometry": {"coordinates":[7.7960162163,47.5459251404],"type":"Point"}
}