{
  "type": "Feature",
  "properties": {
    "addr:full":"Chemin De La C\u00f4te 1 Dardagny 1282",
    "addr:housenumber":"1;1282",
    "addr:street":"Chemin De La Co\u0302Te",
    "iso:country":"CH",
    "sg:address":"Chemin De La C\u00f4te 1",
    "sg:city":"Dardagny",
    "sg:orig_category":"Detailhandel mit B\u00fcchern",
    "sg:phone":"+41 22 754 12 31",
    "sg:postcode":"1282",
    "wof:name":"Dani\u00e8le Bagnoud Librairie Occassion",
    "wof:placetype":"venue"
},
  "geometry": {"coordinates":[5.994915,46.194874],"type":"Point"}
}