{
  "type": "Feature",
  "properties": {
    "iso:country":"CH",
    "sg:address":"Via Ai Ronchi 14 6952 Canobbio. Postfach",
    "sg:city":"Paradiso",
    "sg:orig_category":"Detailhandel mit Bekleidung",
    "sg:postcode":"6900",
    "sg:province":"Ticino",
    "wof:name":"Unifashion Sa Abbigliamento Civile E Uniformato; Fabbricazione E Commercio",
    "wof:placetype":"venue"
},
  "geometry": {"coordinates":[8.962658,46.037605],"type":"Point"}
}