{
  "type": "Feature",
  "properties": {
    "iso:country":"CH",
    "sg:address":"3207 Wileroltigen. Postfach",
    "sg:city":"Wileroltigen",
    "sg:orig_category":"Sportvereine Ballsport Fussball",
    "sg:phone":"+41 31 751 10 71",
    "sg:postcode":"3207",
    "sg:province":"Bern",
    "wof:name":"Sc Wileroltigen",
    "wof:placetype":"venue"
},
  "geometry": {"coordinates":[7.2387070656,46.9708595276],"type":"Point"}
}