{
  "type": "Feature",
  "properties": {
    "iso:country":"CH",
    "sg:address":"Klusstrasse 20",
    "sg:city":"St.gallen",
    "sg:orig_category":"Herstellung von Metallkonstruktionen",
    "sg:phone":"+41 71 277 88 73",
    "sg:postcode":"9000",
    "sg:province":"St. Gallen",
    "wof:name":"Werner Marxer, Schweisstechnik Und Montagen Im Anlagenbau Gmbh",
    "wof:placetype":"venue"
},
  "geometry": {"coordinates":[9.3770856857,47.418548584],"type":"Point"}
}