{
  "type": "Feature",
  "properties": {
    "iso:country":"CH",
    "sg:address":"Avenue Du Tribunal-f\u00e9d\u00e9ral 5",
    "sg:city":"Lausanne",
    "sg:orig_category":"Vermietung von Gebrauchsg\u00fctern",
    "sg:phone":"+41 21 311 02 67",
    "sg:postcode":"1003",
    "sg:province":"Vaud",
    "wof:name":"Mirna Pavone S\u00e0rl",
    "wof:placetype":"venue"
},
  "geometry": {"coordinates":[6.638384819,46.5198402405],"type":"Point"}
}