{
  "type": "Feature",
  "properties": {
    "iso:country":"CH",
    "sg:address":"Alemannenstrasse 5",
    "sg:city":"Therwil",
    "sg:orig_category":"\u00dcbersetzungsb\u00fcros",
    "sg:phone":"+41 61 721 49 42",
    "sg:postcode":"4106",
    "sg:province":"Basel-Landschaft",
    "wof:name":"Thomas Richers Uebersetzungen",
    "wof:placetype":"venue"
},
  "geometry": {"coordinates":[7.5503721237,47.5035972595],"type":"Point"}
}