{
  "type": "Feature",
  "properties": {
    "iso:country":"CH",
    "sg:address":"Rue Pierre Yerly",
    "sg:city":"Givisiez",
    "sg:orig_category":"Herstellung von K\u00fcchenm\u00f6beln",
    "sg:phone":"+41 32 927 30 70",
    "sg:postcode":"1762",
    "sg:province":"Fribourg",
    "wof:name":"Ispagencements S\u00e0rl",
    "wof:placetype":"venue"
},
  "geometry": {"coordinates":[6.8299050331,47.102809906],"type":"Point"}
}