{
  "type": "Feature",
  "properties": {
    "iso:country":"CH",
    "sg:address":"Waffenplatzstr. 85 8000 Z\u00fcrich. Postfach",
    "sg:city":"Z\u00fcrich",
    "sg:orig_category":"Sonstige pers\u00f6nliche Dienstleistungen",
    "sg:postcode":"8055",
    "sg:province":"Z\u00fcrich",
    "wof:name":"Pro Due Gmbh Stadt Zuerich West",
    "wof:placetype":"venue"
},
  "geometry": {"coordinates":[8.5271425247,47.3567276001],"type":"Point"}
}