{
  "type": "Feature",
  "properties": {
    "iso:country":"CH",
    "sg:address":"Nelkenweg 19 4500 Solothurn. Postfach",
    "sg:city":"Solothurn",
    "sg:orig_category":"Interessenvertretungen",
    "sg:postcode":"4502",
    "sg:province":"Solothurn",
    "wof:name":"Pro Aegrotis",
    "wof:placetype":"venue"
},
  "geometry": {"coordinates":[7.5357060432,47.2157821655],"type":"Point"}
}