{
  "type": "Feature",
  "properties": {
    "iso:country":"CH",
    "sg:address":"Piazza Grande 28",
    "sg:city":"Locarno",
    "sg:orig_category":"Detailhandel mit Waren verschiedener Art, Hauptrichtung Nahrungsmittel",
    "sg:phone":"+41 91 751 84 44",
    "sg:postcode":"6600",
    "sg:province":"Ticino",
    "wof:name":"Coop Centre",
    "wof:placetype":"venue"
},
  "geometry": {"coordinates":[8.7946834564,46.1692314148],"type":"Point"}
}