{
  "type": "Feature",
  "properties": {
    "iso:country":"CH",
    "sg:address":"Theaterplatz 4 5400 Baden. Postfach",
    "sg:city":"Baden",
    "sg:orig_category":"Versicherungen Generalagenturen",
    "sg:phone":"+41 71 228 39 39",
    "sg:postcode":"5401",
    "sg:province":"Aargau",
    "wof:name":"Winterthur Lebensversich.-ges. Generalagentur",
    "wof:placetype":"venue"
},
  "geometry": {"coordinates":[9.3702487946,47.4199562073],"type":"Point"}
}