{
  "type": "Feature",
  "properties": {
    "iso:country":"CH",
    "sg:address":"Brauerstrasse 102 8001 Z\u00fcrich. Postfach",
    "sg:city":"Z\u00fcrich",
    "sg:orig_category":"Herstellung von Konstruktionsteilen, Fertigbauteilen U Ausbauelementen aus Holz",
    "sg:postcode":"8001",
    "sg:province":"Z\u00fcrich",
    "wof:name":"Gabrieli Bruno Akustikplatten; Verkauf, Montage. Innenausbauarbeiten",
    "wof:placetype":"venue"
},
  "geometry": {"coordinates":[8.5235834122,47.3797836304],"type":"Point"}
}