{
  "type": "Feature",
  "properties": {
    "iso:country":"CH",
    "sg:address":"Usseramtstrasse 37",
    "sg:city":"N\u00fcrensdorf",
    "sg:orig_category":"Bau von Strassen, Sportanlagen U Bahnverkehrsstrecken Sonstige Entsorgung",
    "sg:phone":"+41 18371133",
    "sg:postcode":"8309",
    "sg:province":"Z\u00fcrich",
    "wof:name":"H\u00fcgli J\u00fcrg, Maschinelle Strassenreinigung",
    "wof:placetype":"venue"
},
  "geometry": {"coordinates":[8.66604,47.460163],"type":"Point"}
}