{
  "type": "Feature",
  "properties": {
    "iso:country":"CH",
    "sg:address":"St. Jakobs-strasse 140",
    "sg:city":"Muttenz",
    "sg:orig_category":"Detailhandel mit Geschenkartikeln U Souvenirs",
    "sg:phone":"+41 61 462 04 03",
    "sg:postcode":"4132",
    "sg:province":"Basel-Landschaft",
    "wof:name":"Insider Mode & Accessoires E.& S.haas",
    "wof:placetype":"venue"
},
  "geometry": {"coordinates":[7.6297001839,47.5338630676],"type":"Point"}
}