{
  "type": "Feature",
  "properties": {
    "iso:country":"CH",
    "sg:address":"Hopfenweg 13a",
    "sg:city":"Thun",
    "sg:orig_category":"Pensionskassen",
    "sg:phone":"+41 33 225 01 55",
    "sg:postcode":"3600",
    "sg:province":"Bern",
    "wof:name":"Personalvorsorgestiftung Der L\u00e4derach Weibel Ag",
    "wof:placetype":"venue"
},
  "geometry": {"coordinates":[7.6251602173,46.7558898926],"type":"Point"}
}