{
  "type": "Feature",
  "properties": {
    "iso:country":"CH",
    "sg:address":"Route De Meinier 12",
    "sg:city":"Vandoeuvres",
    "sg:orig_category":"Herstellung von Konstruktionsteilen, Fertigbauteilen U Ausbauelementen aus Holz",
    "sg:phone":"+41 79 217 02 16",
    "sg:postcode":"1253",
    "sg:province":"Gen\u00e8ve",
    "wof:name":"Leroux Albert",
    "wof:placetype":"venue"
},
  "geometry": {"coordinates":[6.2031669617,46.2222633362],"type":"Point"}
}