{
  "type": "Feature",
  "properties": {
    "iso:country":"CH",
    "sg:address":"Ludretikonerstrasse 18",
    "sg:city":"Thalwil",
    "sg:orig_category":"Siebdruck",
    "sg:phone":"+41 17206521",
    "sg:postcode":"8800",
    "sg:province":"Z\u00fcrich",
    "wof:name":"Anna Henke Siebdruckatelier",
    "wof:placetype":"venue"
},
  "geometry": {"coordinates":[8.5620355606,47.2997093201],"type":"Point"}
}