{
  "type": "Feature",
  "properties": {
    "iso:country":"CH",
    "sg:address":"Kirchgasse 38",
    "sg:city":"Z\u00fcrich",
    "sg:orig_category":"Werbung",
    "sg:phone":"+41 21 729 24 20",
    "sg:postcode":"8001",
    "sg:province":"Z\u00fcrich",
    "wof:name":"Lauffer & Frischknecht",
    "wof:placetype":"venue"
},
  "geometry": {"coordinates":[8.5459623337,47.3703727722],"type":"Point"}
}