{
  "type": "Feature",
  "properties": {
    "iso:country":"CH",
    "sg:address":"Werkstra\u00dfe 28",
    "sg:city":"Lyss",
    "sg:classifiers":[
        {
            "category":"Manufacturing",
            "subcategory":"Tools & Machinery",
            "type":"Manufacturing & Wholesale Goods"
        }
    ],
    "sg:phone":"+41 32 387 80 80",
    "sg:postcode":"3250",
    "sg:province":"Bern",
    "sg:tags":[
        "metallurgy",
        "metalworking"
    ],
    "wof:name":"Spt Roth Ag",
    "wof:placetype":"venue"
},
  "geometry": {"coordinates":[7.2945079803,47.0692176819],"type":"Point"}
}