{
  "type": "Feature",
  "properties": {
    "iso:country":"CH",
    "sg:address":"Lyssachstrasse 1",
    "sg:city":"Burgdorf",
    "sg:orig_category":"Herstellung von keramischen Haushaltswaren U Ziergegenst\u00e4nden",
    "sg:phone":"+41 34 423 15 55",
    "sg:postcode":"3400",
    "sg:province":"Bern",
    "wof:name":"Sue M\u00fcller T\u00f6pferei Cat",
    "wof:placetype":"venue"
},
  "geometry": {"coordinates":[7.6251502037,47.0580825806],"type":"Point"}
}