{
  "type": "Feature",
  "properties": {
    "iso:country":"CH",
    "sg:address":"St. Gallerstrasse 16a",
    "sg:city":"Rorschach",
    "sg:orig_category":"Fahrschulen, Flugschulen",
    "sg:phone":"+41 55 240 73 65",
    "sg:postcode":"9400",
    "sg:province":"St. Gallen",
    "wof:name":"Fritz Cavaleri Autofahrschule",
    "wof:placetype":"venue"
},
  "geometry": {"coordinates":[8.8564729691,47.2565040588],"type":"Point"}
}