{
  "type": "Feature",
  "properties": {
    "iso:country":"CH",
    "sg:address":"Via Trevano 80",
    "sg:city":"Lugano",
    "sg:orig_category":"Fotografische Ateliers Korrespondenz U Nachrichtenb\u00fcros",
    "sg:phone":"+41 32 968 44 53",
    "sg:postcode":"6900",
    "sg:province":"Ticino",
    "wof:name":"Marcel Gerber Photographe De Presse Rp",
    "wof:placetype":"venue"
},
  "geometry": {"coordinates":[6.8290500641,47.1069488525],"type":"Point"}
}