{
  "type": "Feature",
  "properties": {
    "iso:country":"CH",
    "sg:address":"Bergi\u00e8res Avenue 1004 Lausanne Case Postale 278",
    "sg:city":"Lausanne",
    "sg:orig_category":"Elektroinstallation",
    "sg:phone":"+41 21 643 70 00",
    "sg:postcode":"1004",
    "sg:province":"Vaud",
    "wof:name":"L\u00fcthi Et Schmied Sa",
    "wof:placetype":"venue"
},
  "geometry": {"coordinates":[6.6179900169,46.5310935974],"type":"Point"}
}