{
  "type": "Feature",
  "properties": {
    "iso:country":"CH",
    "sg:address":"Klingenweg 4",
    "sg:city":"Eschenz",
    "sg:orig_category":"Softwareentwicklung U beratung",
    "sg:phone":"+41 52 741 44 33",
    "sg:postcode":"8264",
    "sg:province":"Thurgau",
    "wof:name":"H. R. Erz",
    "wof:placetype":"venue"
},
  "geometry": {"coordinates":[8.8634643555,47.6528511047],"type":"Point"}
}