{
  "type": "Feature",
  "properties": {
    "iso:country":"CH",
    "sg:address":"Les Essertons",
    "sg:city":"S\u00e9vaz",
    "sg:orig_category":"Fahrschulen, Flugschulen",
    "sg:phone":"+41 79 413 42 87",
    "sg:postcode":"1541",
    "sg:province":"Fribourg",
    "wof:name":"Guido Trueb Auto-\u00e9cole",
    "wof:placetype":"venue"
},
  "geometry": {"coordinates":[6.8730897903,46.838924408],"type":"Point"}
}