{
  "type": "Feature",
  "properties": {
    "iso:country":"CH",
    "sg:address":"Ackeretstrasse 19",
    "sg:city":"Winterthur",
    "sg:orig_category":"Unternehmensberatung",
    "sg:phone":"+41 71 220 14 01",
    "sg:postcode":"8400",
    "sg:province":"Z\u00fcrich",
    "wof:name":"Esprit St.gallen Beratung Durch Studenten",
    "wof:placetype":"venue"
},
  "geometry": {"coordinates":[9.3731222153,47.4318122864],"type":"Point"}
}