{
  "type": "Feature",
  "properties": {
    "iso:country":"CH",
    "sg:address":"Gerbi 44",
    "sg:city":"N\u00e4fels",
    "sg:classifiers":[
        {
            "category":"Restaurant",
            "type":"Food & Drink"
        }
    ],
    "sg:phone":"+41 55 612 10 62",
    "sg:postcode":"8752",
    "sg:province":"Glarus",
    "wof:name":"Restaurant J\u00e4gerst\u00fcbli",
    "wof:placetype":"venue"
},
  "geometry": {"coordinates":[9.05991745,47.1001281738],"type":"Point"}
}