{
  "type": "Feature",
  "properties": {
    "iso:country":"CH",
    "sg:address":"8158",
    "sg:city":"Regensberg",
    "sg:orig_category":"Detailhandel mit Waren verschiedener Art, Hauptrichtung Nahrungsmittel",
    "sg:phone":"+41 71 891 38 92",
    "sg:postcode":"8158",
    "sg:province":"Z\u00fcrich",
    "wof:name":"Konsumgenossenschaft Reute Ar Und Umgebung",
    "wof:placetype":"venue"
},
  "geometry": {"coordinates":[9.5737476349,47.4198760986],"type":"Point"}
}