{
  "type": "Feature",
  "properties": {
    "iso:country":"CH",
    "sg:address":"Grand'rue 33",
    "sg:city":"Auvernier",
    "sg:orig_category":"Rebbau",
    "sg:phone":"+41 32 731 85 39",
    "sg:postcode":"2012",
    "sg:province":"Neuch\u00e2tel",
    "wof:name":"Jean-d. & Christine Perrochet Vigneron-encaveur",
    "wof:placetype":"venue"
},
  "geometry": {"coordinates":[6.8685297966,46.98046875],"type":"Point"}
}