{
  "type": "Feature",
  "properties": {
    "iso:country":"CH",
    "sg:address":"Chemin De Fontadel 29",
    "sg:city":"Prilly",
    "sg:orig_category":"Grosshandel mit B\u00fcromaschinen Grosshandel mit Datenverarbeitungsger\u00e4ten",
    "sg:phone":"+41 21 624 31 00",
    "sg:postcode":"1008",
    "sg:province":"Vaud",
    "wof:name":"Savoy Computer Service Sa",
    "wof:placetype":"venue"
},
  "geometry": {"coordinates":[6.6076550484,46.5377006531],"type":"Point"}
}