{
  "type": "Feature",
  "properties": {
    "addr:full":"1123 Aclens Vaud 1123",
    "addr:housenumber":"1123",
    "addr:postcode":"1123",
    "addr:street":"Aclens",
    "iso:country":"CH",
    "sg:address":"1123",
    "sg:city":"Aclens",
    "sg:orig_category":"Autogaragen Autospenglereien",
    "sg:phone":"+41 21 869 95 29",
    "sg:postcode":"1123",
    "sg:province":"Vaud",
    "wof:name":"Jean-claude Schopfer Garage & Carrosserie",
    "wof:placetype":"venue"
},
  "geometry": {"coordinates":[6.51096,46.5686],"type":"Point"}
}