{
  "type": "Feature",
  "properties": {
    "iso:country":"CH",
    "sg:address":"Talackerstrasse",
    "sg:city":"Waltenschwil",
    "sg:orig_category":"Politische Parteien CVP",
    "sg:phone":"+41 56 622 68 55",
    "sg:postcode":"5622",
    "sg:province":"Aargau",
    "wof:name":"Cvp Ortspartei Waltenschwil",
    "wof:placetype":"venue"
},
  "geometry": {"coordinates":[8.303730011,47.3384132385],"type":"Point"}
}