{
  "type": "Feature",
  "properties": {
    "addr:full":"Schl\u00fcchtern 20 Schwarzenburg Bern 3150",
    "addr:housenumber":"20",
    "addr:postcode":"3150",
    "addr:street":"Schluechtern;Bern",
    "iso:country":"CH",
    "sg:address":"Schl\u00fcchtern 20",
    "sg:city":"Schwarzenburg",
    "sg:orig_category":"Shopping U Fachgesch\u00e4fte, Kosmetik U K\u00f6rperpflege",
    "sg:phone":"+41 79 417 89 91",
    "sg:postcode":"3150",
    "sg:province":"Bern",
    "wof:name":"Inka-leder",
    "wof:placetype":"venue"
},
  "geometry": {"coordinates":[7.345438,46.822838],"type":"Point"}
}