{
  "type": "Feature",
  "properties": {
    "iso:country":"CH",
    "sg:address":"Kanzleistrasse 120 8004 Z\u00fcrich. Postfach",
    "sg:city":"Z\u00fcrich",
    "sg:orig_category":"Architektur U Ingenieurb\u00fcros",
    "sg:postcode":"8001",
    "sg:province":"Z\u00fcrich",
    "wof:name":"Ingenieurb\u00fcro Gambert Ingenieurb\u00fcro F. Luft, Klima- U. W\u00e4rmetechnik",
    "wof:placetype":"venue"
},
  "geometry": {"coordinates":[8.521017,47.376896],"type":"Point"}
}