{
  "type": "Feature",
  "properties": {
    "iso:country":"CH",
    "sg:address":"St. Dionysstrasse 31",
    "sg:city":"Jona",
    "sg:orig_category":"Sonstige mit der Informatik verbundene T\u00e4tigkeiten",
    "sg:phone":"+41 55 212 43 55",
    "sg:postcode":"8645",
    "sg:province":"St. Gallen",
    "wof:name":"Dionys-net Ag",
    "wof:placetype":"venue"
},
  "geometry": {"coordinates":[8.8641910553,47.2257270813],"type":"Point"}
}