{
  "type": "Feature",
  "properties": {
    "iso:country":"CH",
    "sg:address":"Gartenweg 2 4450 Sissach. Postfach 229",
    "sg:city":"Sissach",
    "sg:orig_category":"Sanit\u00e4r, Heizungs U L\u00fcftungsinstallation",
    "sg:phone":"+41 79 241 91 04",
    "sg:postcode":"4450",
    "sg:province":"Basel-Landschaft",
    "wof:name":"John Haustechnik Ag",
    "wof:placetype":"venue"
},
  "geometry": {"coordinates":[7.8124680519,47.4632720947],"type":"Point"}
}