{
  "type": "Feature",
  "properties": {
    "iso:country":"CH",
    "sg:address":"R\u00f6merstrasse 175 8404 Oberwinterthur. Postfach",
    "sg:city":"Winterthur",
    "sg:orig_category":"K\u00fcnstlerische U schriftstellerische T\u00e4tigkeiten U Darbietungen",
    "sg:phone":"+41 56 225 18 44",
    "sg:postcode":"8404",
    "sg:province":"Z\u00fcrich",
    "wof:name":"Keller Restauro Gmbh",
    "wof:placetype":"venue"
},
  "geometry": {"coordinates":[8.2445201874,47.4626045227],"type":"Point"}
}