{
  "type": "Feature",
  "properties": {
    "addr:full":"Schaffhauserstrasse 354 Z\u00fcrich Z\u00fcrich 8050",
    "addr:housenumber":"354",
    "addr:postcode":"8050",
    "addr:street":"Schaffhauserstrasse",
    "iso:country":"CH",
    "sg:address":"Schaffhauserstrasse 354",
    "sg:city":"Z\u00fcrich",
    "sg:orig_category":"Detailhandel mit Blumen U Pflanzen",
    "sg:phone":"+41 13114894",
    "sg:postcode":"8050",
    "sg:province":"Z\u00fcrich",
    "wof:name":"Blumen Oertig",
    "wof:placetype":"venue"
},
  "geometry": {"coordinates":[8.546372,47.409931],"type":"Point"}
}