{
  "type": "Feature",
  "properties": {
    "iso:country":"CH",
    "sg:address":"Alpbach-hofstatt 5",
    "sg:city":"Erstfeld",
    "sg:orig_category":"Sportvereine Schwingen",
    "sg:phone":"+41 41 880 02 77",
    "sg:postcode":"6472",
    "sg:province":"Uri",
    "wof:name":"Schwingklub Erstfeld",
    "wof:placetype":"venue"
},
  "geometry": {"coordinates":[8.6448478699,46.8195114136],"type":"Point"}
}