{
  "type": "Feature",
  "properties": {
    "iso:country":"CH",
    "sg:address":"Zeughausstrasse 3",
    "sg:city":"Lenzburg",
    "sg:orig_category":"Physiotherapie",
    "sg:phone":"+41 62 891 51 22",
    "sg:postcode":"5600",
    "sg:province":"Aargau",
    "wof:name":"Urs H\u00e4fliger Physiotherapie",
    "wof:placetype":"venue"
},
  "geometry": {"coordinates":[8.1701726913,47.389591217],"type":"Point"}
}