{
  "type": "Feature",
  "properties": {
    "iso:country":"CH",
    "sg:address":"Alte T\u00f6sstalstrasse 46",
    "sg:city":"R\u00e4mism\u00fchle",
    "sg:orig_category":"Non-Classified Establishments",
    "sg:postcode":"8487",
    "sg:province":"Z\u00fcrich",
    "wof:name":"Dudli Gmbh Montagen Schlosserei",
    "wof:placetype":"venue"
},
  "geometry": {"coordinates":[8.8244123459,47.4474182129],"type":"Point"}
}