{
  "type": "Feature",
  "properties": {
    "iso:country":"CH",
    "sg:address":"Bruggenmattweg 24",
    "sg:city":"Bonstetten",
    "sg:orig_category":"Grosshandel mit Eisenwaren sowie Installationsbedarf f\u00fcr Gas, Wasser U Heizung Herstellung von k\u00e4lte",
    "sg:phone":"+41 21 634 95 62",
    "sg:postcode":"8906",
    "sg:province":"Z\u00fcrich",
    "wof:name":"R\u00e9fry Sa",
    "wof:placetype":"venue"
},
  "geometry": {"coordinates":[6.5909309387,46.5329780579],"type":"Point"}
}