{
  "type": "Feature",
  "properties": {
    "iso:country":"CH",
    "sg:address":"Langwattstrasse 46",
    "sg:city":"Zollikerberg",
    "sg:orig_category":"Vorschulen, Kinderg\u00e4rten",
    "sg:phone":"+41 13919440",
    "sg:postcode":"8125",
    "sg:province":"Z\u00fcrich",
    "wof:name":"Kindergarten Langwatt",
    "wof:placetype":"venue"
},
  "geometry": {"coordinates":[8.6064405441,47.3409461975],"type":"Point"}
}