{
  "type": "Feature",
  "properties": {
    "iso:country":"CH",
    "sg:address":"Albisstrasse 5",
    "sg:city":"Zug",
    "sg:orig_category":"Unclassifiable Establishments",
    "sg:phone":"+41 71 245 48 68",
    "sg:postcode":"6300",
    "sg:province":"Zug",
    "wof:name":"Eoipso Ag",
    "wof:placetype":"venue"
},
  "geometry": {"coordinates":[9.3957004547,47.4312705994],"type":"Point"}
}