{
  "type": "Feature",
  "properties": {
    "iso:country":"CH",
    "sg:address":"Zweierstrasse 129",
    "sg:city":"Z\u00fcrich",
    "sg:orig_category":"Betrieb von Taxis",
    "sg:phone":"+41 79 438 76 56",
    "sg:postcode":"8003",
    "sg:province":"Z\u00fcrich",
    "wof:name":"Taxibetrieb Simonic Franc",
    "wof:placetype":"venue"
},
  "geometry": {"coordinates":[8.520223,47.371037],"type":"Point"}
}