{
  "type": "Feature",
  "properties": {
    "iso:country":"CH",
    "sg:address":"Blegistrasse 1",
    "sg:city":"Rotkreuz",
    "sg:orig_category":"Buchf\u00fchrung Dienstleistungen von Beteiligungsgesellschaften",
    "sg:phone":"+41 41 799 69 99",
    "sg:postcode":"6343",
    "sg:province":"Zug",
    "wof:name":"Doc Business Support Ag",
    "wof:placetype":"venue"
},
  "geometry": {"coordinates":[8.436128,47.14819],"type":"Point"}
}