{
  "type": "Feature",
  "properties": {
    "iso:country":"CH",
    "sg:address":"Dorfstrasse 44",
    "sg:city":"Wiesendangen",
    "sg:orig_category":"Detailhandel mit S\u00e4uglings U Kinderbekleidung Herstellung von W\u00e4sche",
    "sg:phone":"+41 19110368",
    "sg:postcode":"8542",
    "sg:province":"Z\u00fcrich",
    "wof:name":"Marija Fr\u00f6hlich Kinderboutique",
    "wof:placetype":"venue"
},
  "geometry": {"coordinates":[8.5809049606,47.3179359436],"type":"Point"}
}