{
  "type": "Feature",
  "properties": {
    "iso:country":"CH",
    "sg:address":"Heinzenbergstrasse",
    "sg:city":"Thusis",
    "sg:orig_category":"Vorschulen, Kinderg\u00e4rten",
    "sg:phone":"+41 81 651 32 03",
    "sg:postcode":"7430",
    "sg:province":"Graubunden",
    "wof:name":"Kindergarten",
    "wof:placetype":"venue"
},
  "geometry": {"coordinates":[9.435634613,46.6945648193],"type":"Point"}
}