{
  "type": "Feature",
  "properties": {
    "iso:country":"CH",
    "sg:address":"Eptingerstr. 20",
    "sg:city":"Basel",
    "sg:classifiers":[
        {
            "category":"Home & Garden",
            "subcategory":"Furniture",
            "type":"Retail Goods"
        }
    ],
    "sg:phone":"+41 61 312 55 35",
    "sg:postcode":"4052",
    "sg:province":"Basel-Stadt",
    "sg:tags":[
        "wood"
    ],
    "wof:name":"Carrom Holzwerkstatt",
    "wof:placetype":"venue"
},
  "geometry": {"coordinates":[7.607967,47.554737],"type":"Point"}
}