{
  "type": "Feature",
  "properties": {
    "iso:country":"CH",
    "sg:address":"Wiesenschanzweg 9",
    "sg:city":"Basel",
    "sg:orig_category":"Kinderkrippen U horte",
    "sg:phone":"+41 61 692 67 34",
    "sg:postcode":"4057",
    "sg:province":"Basel-Stadt",
    "wof:name":"Tagesheim & Kinderkrippe Des Basler Frauenvereins",
    "wof:placetype":"venue"
},
  "geometry": {"coordinates":[7.5952281952,47.5714645386],"type":"Point"}
}