{
  "type": "Feature",
  "properties": {
    "iso:country":"CH",
    "sg:address":"1748",
    "sg:city":"Torny-le-grand",
    "sg:classifiers":[
        {
            "category":"Travel",
            "subcategory":"Hotels & Motels",
            "type":"Entertainment"
        }
    ],
    "sg:postcode":"1748",
    "sg:province":"Fribourg",
    "sg:tags":[
        "hotels",
        "mit",
        "restaurant"
    ],
    "wof:name":"Curty Rapha\u00ebl.",
    "wof:placetype":"venue"
},
  "geometry": {"coordinates":[6.967979908,46.7694892883],"type":"Point"}
}