{
  "type": "Feature",
  "properties": {
    "iso:country":"CH",
    "sg:address":"Elisabethenstrasse 28 4051 Basel. Postfach 422",
    "sg:city":"Basel",
    "sg:orig_category":"Wirtschafts- and Arbeitgeberverb\u00e4nde",
    "sg:phone":"+41 61 261 30 06",
    "sg:postcode":"4010",
    "sg:province":"Basel-Stadt",
    "wof:name":"Verband Der Basler Lichtspieltheater",
    "wof:placetype":"venue"
},
  "geometry": {"coordinates":[7.5908617973,47.5512084961],"type":"Point"}
}