{
  "type": "Feature",
  "properties": {
    "iso:country":"CH",
    "sg:address":"Verwaltungsgeb\u00e4ude Tiefbauamt",
    "sg:city":"Frauenfeld",
    "sg:orig_category":"Architektur U Ingenieurb\u00fcros",
    "sg:postcode":"8500",
    "sg:province":"Thurgau",
    "wof:name":"J\u00fcrg Blaser Architektur Ag",
    "wof:placetype":"venue"
},
  "geometry": {"coordinates":[7.75759,46.949127],"type":"Point"}
}