{
  "type": "Feature",
  "properties": {
    "iso:country":"CH",
    "sg:address":"Neuhaltenring 1 6030 Ebikon. Postfach 363",
    "sg:city":"Ebikon",
    "sg:orig_category":"Grosshandel mit B\u00fcromaschinen Grosshandel mit Datenverarbeitungsger\u00e4ten",
    "sg:phone":"+41 41 440 70 22",
    "sg:postcode":"6031",
    "sg:province":"Luzern",
    "wof:name":"Up Distribution Sarl",
    "wof:placetype":"venue"
},
  "geometry": {"coordinates":[8.3435697556,47.0879020691],"type":"Point"}
}