{
  "type": "Feature",
  "properties": {
    "iso:country":"CH",
    "sg:address":"Edisriederstr. 106 Postfach 264",
    "sg:city":"Sachseln",
    "sg:classifiers":[
        {
            "category":"Manufacturing",
            "subcategory":"Rubber & Plastics",
            "type":"Manufacturing & Wholesale Goods"
        }
    ],
    "sg:phone":"+41 41 666 71 11",
    "sg:postcode":"6072",
    "sg:province":"Obwalden",
    "sg:tags":[
        "metallurgy",
        "tool",
        "metalworking"
    ],
    "wof:name":"Elfo Ag",
    "wof:placetype":"venue"
},
  "geometry": {"coordinates":[121.5388717651,25.0265293121],"type":"Point"}
}