{
  "type": "Feature",
  "properties": {
    "iso:country":"CH",
    "sg:address":"4144",
    "sg:city":"Arlesheim",
    "sg:orig_category":"Zahnkliniken",
    "sg:phone":"+41 41 260 26 88",
    "sg:postcode":"4144",
    "sg:province":"Basel-Landschaft",
    "wof:name":"Schulzahnpflege Schulhaus Gersag",
    "wof:placetype":"venue"
},
  "geometry": {"coordinates":[8.2789831161,47.0785331726],"type":"Point"}
}