{
  "type": "Feature",
  "properties": {
    "iso:country":"CH",
    "sg:address":"Bolacker",
    "sg:city":"Obergerlafingen",
    "sg:orig_category":"Erbringung von Dienstleistungen f\u00fcr Unternehmen",
    "sg:phone":"+41 32 675 51 13",
    "sg:postcode":"4564",
    "sg:province":"Bern",
    "wof:name":"Grafik, J\u00e4ggi Martin",
    "wof:placetype":"venue"
},
  "geometry": {"coordinates":[7.582007885,47.1596984863],"type":"Point"}
}