{
  "type": "Feature",
  "properties": {
    "iso:country":"CH",
    "sg:address":"S\u00e4ntisstrasse 3 8716 Schmerikon. Postfach",
    "sg:city":"Schmerikon",
    "sg:orig_category":"Sportvereine Wassersport Segeln",
    "sg:phone":"+41 55 282 20 34",
    "sg:postcode":"8716",
    "sg:province":"St. Gallen",
    "wof:name":"Segel-& Surfcl.schmerikon Sycs",
    "wof:placetype":"venue"
},
  "geometry": {"coordinates":[8.9541492462,47.225818634],"type":"Point"}
}