{
  "type": "Feature",
  "properties": {
    "iso:country":"CH",
    "sg:address":"Alte Steinhauserstrasse 19",
    "sg:city":"Cham",
    "sg:orig_category":"Herstellung von Elektrizit\u00e4tsverteilungs U schalteinrichtungen Herstellung von industriellen Prozess",
    "sg:phone":"+41 62 893 19 84",
    "sg:postcode":"6330",
    "sg:province":"Zug",
    "wof:name":"Kirchhofer Ag, Steuer, Mess Und Regelanlagen",
    "wof:placetype":"venue"
},
  "geometry": {"coordinates":[8.1759490967,47.4129104614],"type":"Point"}
}