{
  "type": "Feature",
  "properties": {
    "iso:country":"CH",
    "sg:address":"Lindenstrasse 14",
    "sg:city":"Baar",
    "sg:orig_category":"Non-Classified Establishments",
    "sg:postcode":"6340",
    "sg:province":"Zug",
    "wof:name":"Commercial Metals (international) Ag",
    "wof:placetype":"venue"
},
  "geometry": {"coordinates":[8.5181684494,47.183177948],"type":"Point"}
}