{
  "type": "Feature",
  "properties": {
    "iso:country":"CH",
    "sg:address":"Lenzburgerstrasse 6",
    "sg:city":"Niederlenz",
    "sg:orig_category":"Instandhaltung U Reparatur von Automobilen",
    "sg:phone":"+41 62 888 25 50",
    "sg:postcode":"5702",
    "sg:province":"Aargau",
    "wof:name":"Central-garage O. W\u00e4lty Ag",
    "wof:placetype":"venue"
},
  "geometry": {"coordinates":[8.1790657043,47.397277832],"type":"Point"}
}