{
  "type": "Feature",
  "properties": {
    "iso:country":"CH",
    "sg:address":"Birkenstrasse 3",
    "sg:city":"M\u00e4nnedorf",
    "sg:orig_category":"Arztpraxen",
    "sg:phone":"+41 19204141",
    "sg:postcode":"8708",
    "sg:province":"Z\u00fcrich",
    "wof:name":"Dr.med.andreas Jent Arzt F.allgemeine Medizin Fmh",
    "wof:placetype":"venue"
},
  "geometry": {"coordinates":[8.705229,47.256268],"type":"Point"}
}