{
  "type": "Feature",
  "properties": {
    "iso:country":"CH",
    "sg:address":"Bahnh\u00f6heweg 86 3018 Bern. Postfach 558",
    "sg:city":"Bern",
    "sg:orig_category":"Vermietung U Verpachtung von eigenen Immobilien",
    "sg:phone":"+41 22 798 31 71",
    "sg:postcode":"3018",
    "sg:province":"Bern",
    "wof:name":"Fabet Ag Immobilien, Beteiligungen",
    "wof:placetype":"venue"
},
  "geometry": {"coordinates":[7.3971347809,46.9388084412],"type":"Point"}
}