{
  "type": "Feature",
  "properties": {
    "iso:country":"CH",
    "sg:address":"Landstrasse 125",
    "sg:city":"Wettingen",
    "sg:orig_category":"Kosmetikinstitute",
    "sg:phone":"+41 56 633 75 50",
    "sg:postcode":"5430",
    "sg:province":"Aargau",
    "wof:name":"Jasmin Fausch Kosmetikinstitut",
    "wof:placetype":"venue"
},
  "geometry": {"coordinates":[8.3488235474,47.3519325256],"type":"Point"}
}