{
  "type": "Feature",
  "properties": {
    "iso:country":"CH",
    "sg:address":"Heideggweg 6",
    "sg:city":"Aarau",
    "sg:orig_category":"Architektur U Ingenieurb\u00fcros",
    "sg:phone":"+41 71 244 43 64",
    "sg:postcode":"5000",
    "sg:province":"Aargau",
    "wof:name":"Oscar Lanfranconi Ingenieurb\u00fcro",
    "wof:placetype":"venue"
},
  "geometry": {"coordinates":[9.37398,47.440163],"type":"Point"}
}