{
  "type": "Feature",
  "properties": {
    "addr:full":"Rue De Lausanne 3 Sion Valais 1950",
    "addr:housenumber":"3",
    "addr:postcode":"1950",
    "addr:street":"Rue De Lausanne",
    "iso:country":"CH",
    "sg:address":"Rue De Lausanne 3",
    "sg:city":"Sion",
    "sg:orig_category":"Detailhandel mit Bekleidung Detailhandel mit Schuhen",
    "sg:phone":"+41 31 311 30 40",
    "sg:postcode":"1950",
    "sg:province":"Valais",
    "wof:name":"Ballett Shop Bern Bekleidung Schuhe Accessoires",
    "wof:placetype":"venue"
},
  "geometry": {"coordinates":[7.449793,46.947594],"type":"Point"}
}