{
  "type": "Feature",
  "properties": {
    "iso:country":"CH",
    "sg:address":"W\u00e4gitalerstrasse 2",
    "sg:city":"Siebnen",
    "sg:orig_category":"Chemische Reinigung",
    "sg:phone":"+41 55 440 35 44",
    "sg:postcode":"8854",
    "sg:province":"Schwyz",
    "wof:name":"Erna Kessler Chemische Reinigung",
    "wof:placetype":"venue"
},
  "geometry": {"coordinates":[8.896656,47.174103],"type":"Point"}
}