{
  "type": "Feature",
  "properties": {
    "iso:country":"CH",
    "sg:address":"Rikonerstrasse 52 8307 Effretikon. Postfach",
    "sg:city":"Effretikon",
    "sg:orig_category":"Wirtschaftspr\u00fcfung, Steuerberatung U Treuhand",
    "sg:phone":"+41 71 222 95 53",
    "sg:postcode":"8307",
    "sg:province":"Z\u00fcrich",
    "wof:name":"W\u00fcrmli Werner. Buchhaltungs- U. Treuhandb\u00fcro.",
    "wof:placetype":"venue"
},
  "geometry": {"coordinates":[9.3848495483,47.4172058105],"type":"Point"}
}