{
  "type": "Feature",
  "properties": {
    "iso:country":"CH",
    "sg:address":"Hauptstrasse 58",
    "sg:city":"Muttenz",
    "sg:orig_category":"Drogerien Sonstiger Fachdetailhandel mit Nahrungsmitteln, Getr\u00e4nken U Tabak in Verkaufsr\u00e4umen",
    "sg:phone":"+41 61 461 66 40",
    "sg:postcode":"4132",
    "sg:province":"Basel-Landschaft",
    "wof:name":"Central Drogerie Erich Haller",
    "wof:placetype":"venue"
},
  "geometry": {"coordinates":[7.6471447945,47.5257377625],"type":"Point"}
}