{
  "type": "Feature",
  "properties": {
    "iso:country":"CH",
    "sg:address":"3270 Aarberg. Postfach",
    "sg:city":"Aarberg",
    "sg:orig_category":"Konkurs- and Betreibungs\u00e4mter",
    "sg:phone":"+41 32 392 54 24",
    "sg:postcode":"3270",
    "sg:province":"Bern",
    "wof:name":"Betreibungs-& Konkursamt Dienststelle Aarberg",
    "wof:placetype":"venue"
},
  "geometry": {"coordinates":[7.2756547928,47.0425682068],"type":"Point"}
}