{
  "type": "Feature",
  "properties": {
    "iso:country":"CH",
    "sg:address":"Grand-rue 82",
    "sg:city":"Morges",
    "sg:orig_category":"Pensionskassen",
    "sg:phone":"+41 21 802 13 43",
    "sg:postcode":"1110",
    "sg:province":"Vaud",
    "wof:name":"Caisse Paritaire De Pr\u00e9voyance De L'association Des Horticulteurs De La Suisse Romande",
    "wof:placetype":"venue"
},
  "geometry": {"coordinates":[6.4974579811,46.5084915161],"type":"Point"}
}