{
  "type": "Feature",
  "properties": {
    "iso:country":"CH",
    "sg:address":"M\u00e4ttenbach",
    "sg:city":"Madiswil",
    "sg:orig_category":"Grosshandel mit Kaffee, Tee, Kakao U Gew\u00fcrzen",
    "sg:postcode":"4934",
    "sg:province":"Bern",
    "wof:name":"Tee-spezialit\u00e4ten, Eduard Geiser",
    "wof:placetype":"venue"
},
  "geometry": {"coordinates":[7.8270120621,47.1602096558],"type":"Point"}
}