{
  "type": "Feature",
  "properties": {
    "iso:country":"CH",
    "sg:address":"Vorstadt 3",
    "sg:city":"Nebikon",
    "sg:orig_category":"Grosshandel mit Nahrungsmitteln, Getr\u00e4nken U Tabakwaren ohne ausgepr\u00e4gten Schwerpunkt",
    "sg:postcode":"6244",
    "sg:province":"Luzern",
    "wof:name":"Lebensmittelhandel Willi",
    "wof:placetype":"venue"
},
  "geometry": {"coordinates":[7.9738001823,47.1901664734],"type":"Point"}
}