{
  "type": "Feature",
  "properties": {
    "iso:country":"CH",
    "sg:address":"Kriegstettenstrasse 15 4563 Gerlafingen. Postfach 126",
    "sg:city":"Obergerlafingen",
    "sg:orig_category":"Detailhandel mit B\u00fcchern, Zeitungen, Schreib U Papeteriewaren",
    "sg:phone":"+41 79 206 00 58",
    "sg:postcode":"4564",
    "sg:province":"Bern",
    "wof:name":"Andy's Shop",
    "wof:placetype":"venue"
},
  "geometry": {"coordinates":[7.575029,47.170963],"type":"Point"}
}