{
  "type": "Feature",
  "properties": {
    "iso:country":"CH",
    "sg:address":"Route De Riaz 42",
    "sg:city":"Bulle",
    "sg:orig_category":"Detailhandel mit Schuhen",
    "sg:phone":"+41 26 912 08 54",
    "sg:postcode":"1630",
    "sg:province":"Fribourg",
    "wof:name":"Dosenbach Chaussures",
    "wof:placetype":"venue"
},
  "geometry": {"coordinates":[7.0593800545,46.6249732971],"type":"Point"}
}