{
  "type": "Feature",
  "properties": {
    "addr:full":"Route De B\u00e2le 2 Del\u00e9mont Jura 2800",
    "addr:housenumber":"2",
    "addr:postcode":"2800",
    "addr:street":"Route De Ba\u0302Le;Jura",
    "iso:country":"CH",
    "sg:address":"Route De B\u00e2le 2",
    "sg:city":"Del\u00e9mont",
    "sg:orig_category":"Architektur U Ingenieurb\u00fcros Architekturb\u00fcros",
    "sg:phone":"+41 32 422 33 31",
    "sg:postcode":"2800",
    "sg:province":"Jura",
    "wof:name":"Gobat Architectes Sa",
    "wof:placetype":"venue"
},
  "geometry": {"coordinates":[7.345704,47.365902],"type":"Point"}
}