{
  "type": "Feature",
  "properties": {
    "iso:country":"CH",
    "sg:address":"Sch\u00f6nb\u00fcelstrasse 6",
    "sg:city":"Engelburg",
    "sg:orig_category":"Sportvereine Motorrad",
    "sg:phone":"+41 71 277 68 13",
    "sg:postcode":"9032",
    "sg:province":"St. Gallen",
    "wof:name":"Motor-sport-club Msc Engelburg",
    "wof:placetype":"venue"
},
  "geometry": {"coordinates":[9.3400201797,47.4450111389],"type":"Point"}
}