{
  "type": "Feature",
  "properties": {
    "iso:country":"CH",
    "sg:address":"H\u00fcttenmoosstrasse",
    "sg:city":"Rorschacherberg",
    "sg:orig_category":"Elektroinstallation",
    "sg:phone":"+41 71 850 06 40",
    "sg:postcode":"9404",
    "sg:province":"St. Gallen",
    "wof:name":"Buob Elektro Elektroinstallationsgesch\u00e4ft",
    "wof:placetype":"venue"
},
  "geometry": {"coordinates":[9.5053873062,47.4673309326],"type":"Point"}
}