{
  "type": "Feature",
  "properties": {
    "iso:country":"CH",
    "sg:address":"Etzelstrasse 68",
    "sg:city":"W\u00e4denswil",
    "sg:orig_category":"Herstellung von k\u00e4lte U lufttechnischen Erzeugnissen f\u00fcr gewerbliche Zwecke",
    "sg:phone":"+41 62 771 93 75",
    "sg:postcode":"8820",
    "sg:province":"Z\u00fcrich",
    "wof:name":"Bintherm W\u00e4rmetechnik Gmbh",
    "wof:placetype":"venue"
},
  "geometry": {"coordinates":[8.204911232,47.2597084045],"type":"Point"}
}