{
  "type": "Feature",
  "properties": {
    "iso:country":"CH",
    "sg:address":"8117",
    "sg:city":"F\u00e4llanden",
    "sg:orig_category":"Vereine Dramatische and Theater",
    "sg:postcode":"8117",
    "sg:province":"Z\u00fcrich",
    "wof:name":"Theatergruppe Langnau",
    "wof:placetype":"venue"
},
  "geometry": {"coordinates":[8.5329093933,47.2841491699],"type":"Point"}
}