{
  "type": "Feature",
  "properties": {
    "iso:country":"CH",
    "sg:address":"Fuchsgasse 42",
    "sg:city":"Widnau",
    "sg:orig_category":"Webdesign",
    "sg:phone":"+41 71 722 70 07",
    "sg:postcode":"9443",
    "sg:province":"St. Gallen",
    "wof:name":"Henry Eduard Merkli Kreativ-web",
    "wof:placetype":"venue"
},
  "geometry": {"coordinates":[9.6421003342,47.4036445618],"type":"Point"}
}