{
  "type": "Feature",
  "properties": {
    "iso:country":"CH",
    "sg:address":"Lochg. 18",
    "sg:city":"Gr\u00e4nichen",
    "sg:classifiers":[
        {
            "category":"Home & Garden",
            "subcategory":"Furniture",
            "type":"Retail Goods"
        }
    ],
    "sg:phone":"+41 62 855 80 80",
    "sg:postcode":"5722",
    "sg:province":"Aargau",
    "sg:tags":[
        "household",
        "wood"
    ],
    "wof:name":"M\u00c4rki Ag",
    "wof:placetype":"venue"
},
  "geometry": {"coordinates":[8.0961351395,47.3603096008],"type":"Point"}
}