{
  "type": "Feature",
  "properties": {
    "iso:country":"CH",
    "sg:address":"Avenue Du Ch\u00eane 3",
    "sg:city":"Aubonne",
    "sg:orig_category":"Detailhandel mit Bekleidung Detailhandel mit Herrenbekleidung",
    "sg:phone":"+41 21 808 78 88",
    "sg:postcode":"1170",
    "sg:province":"Vaud",
    "wof:name":"Durand Mode Masculine Roger Durand",
    "wof:placetype":"venue"
},
  "geometry": {"coordinates":[6.393978,46.493988],"type":"Point"}
}