{
  "type": "Feature",
  "properties": {
    "iso:country":"CH",
    "sg:address":"Kr\u00e4mermatt 2",
    "sg:city":"Cham",
    "sg:orig_category":"Handelsvermittlung U Grosshandel Sonstiger Grosshandel",
    "sg:phone":"+41 41 785 07 41",
    "sg:postcode":"6330",
    "sg:province":"Zug",
    "wof:name":"Ecofu Ag",
    "wof:placetype":"venue"
},
  "geometry": {"coordinates":[8.450884819,47.1800613403],"type":"Point"}
}