{
  "type": "Feature",
  "properties": {
    "iso:country":"CH",
    "sg:address":"Impasse De La Cure",
    "sg:city":"Veyras",
    "sg:orig_category":"Detailhandel mit Geschenkartikeln U Souvenirs",
    "sg:phone":"+41 27 455 01 02",
    "sg:postcode":"3968",
    "sg:province":"Valais",
    "wof:name":"Technogravure Didier Zufferey",
    "wof:placetype":"venue"
},
  "geometry": {"coordinates":[7.5368208885,46.3013687134],"type":"Point"}
}