{
  "type": "Feature",
  "properties": {
    "iso:country":"CH",
    "sg:address":"Brunisberg 6",
    "sg:city":"Hombrechtikon",
    "sg:orig_category":"Detailhandel mit Milcherzeugnissen U Eiern Verarbeitung von Milch",
    "sg:phone":"+41 500380",
    "sg:postcode":"8634",
    "sg:province":"Z\u00fcrich",
    "wof:name":"Landw. Verein Pf\u00e4ffikon",
    "wof:placetype":"venue"
},
  "geometry": {"coordinates":[8.7839918137,47.3674468994],"type":"Point"}
}