{
  "type": "Feature",
  "properties": {
    "iso:country":"CH",
    "sg:address":"Castausio Via 4",
    "sg:city":"Lugano",
    "sg:orig_category":"Gewinnung von Kies U Sand",
    "sg:postcode":"6900",
    "sg:province":"Ticino",
    "wof:name":"Silvagni G. & C. Sa",
    "wof:placetype":"venue"
},
  "geometry": {"coordinates":[8.9541397095,46.013633728],"type":"Point"}
}