{
  "type": "Feature",
  "properties": {
    "iso:country":"CH",
    "sg:address":"Rue Du Village 26",
    "sg:city":"Vernier",
    "sg:orig_category":"Detailhandel mit Waren verschiedener Art, Hauptrichtung Nahrungsmittel",
    "sg:phone":"+41 22 341 36 40",
    "sg:postcode":"1214",
    "sg:province":"Gen\u00e8ve",
    "wof:name":"Coop Vernier",
    "wof:placetype":"venue"
},
  "geometry": {"coordinates":[6.0828537941,46.214302063],"type":"Point"}
}