{
  "type": "Feature",
  "properties": {
    "iso:country":"CH",
    "sg:address":"Petersgraben 4",
    "sg:city":"Basel",
    "sg:orig_category":"Interessenvertretungen",
    "sg:postcode":"4054",
    "sg:province":"Basel-Stadt",
    "wof:name":"Stiftung F\u00fcr H\u00f6henmedizinische Forschung Und Pr\u00e4ventiv-medizin",
    "wof:placetype":"venue"
},
  "geometry": {"coordinates":[9.8530454636,46.4981575012],"type":"Point"}
}