{
  "type": "Feature",
  "properties": {
    "iso:country":"CH",
    "sg:address":"Geroldstrasse 20",
    "sg:city":"Z\u00fcrich",
    "sg:orig_category":"Grosshandel mit Erzen U Metallen",
    "sg:phone":"+41 12731411",
    "sg:postcode":"8001",
    "sg:province":"Z\u00fcrich",
    "wof:name":"Usinor Aciers Suisse Sa",
    "wof:placetype":"venue"
},
  "geometry": {"coordinates":[8.5190887451,47.3861503601],"type":"Point"}
}