{
  "type": "Feature",
  "properties": {
    "iso:country":"CH",
    "sg:address":"Franscini Viale 16",
    "sg:city":"Lugano",
    "sg:orig_category":"Herstellung von sonstigen elektrischen Ausr\u00fcstungen",
    "sg:phone":"+41 52 630 47 37",
    "sg:postcode":"6900",
    "sg:province":"Ticino",
    "wof:name":"Cobra Automotive Technologies Sa, Lussemburgo, Succursale Di Lugano",
    "wof:placetype":"venue"
},
  "geometry": {"coordinates":[8.9538192749,46.0096817017],"type":"Point"}
}