{
  "type": "Feature",
  "properties": {
    "iso:country":"CH",
    "sg:address":"Dersbachstrasse 312a",
    "sg:city":"Cham",
    "sg:orig_category":"Datenverarbeitungsdienste Softwareentwicklung U beratung",
    "sg:postcode":"6330",
    "sg:province":"Zug",
    "wof:name":"Imsec Gmbh Informations- & Informatik",
    "wof:placetype":"venue"
},
  "geometry": {"coordinates":[8.450848,47.166615],"type":"Point"}
}