{
  "type": "Feature",
  "properties": {
    "addr:full":"Horw Luzern 6048",
    "addr:postcode":"6048",
    "iso:country":"CH",
    "sg:city":"Horw",
    "sg:orig_category":"Industrie, Maschinenbau",
    "sg:postcode":"6048",
    "sg:province":"Luzern",
    "wof:name":"Pohland Ag",
    "wof:placetype":"venue"
},
  "geometry": {"coordinates":[8.311521,47.019157],"type":"Point"}
}