{
  "type": "Feature",
  "properties": {
    "iso:country":"CH",
    "sg:address":"Unterm\u00fcli 7",
    "sg:city":"Zug",
    "sg:orig_category":"Detailhandel mit B\u00fcchern, Zeitungen, Schreib U Papeteriewaren",
    "sg:phone":"+41 41 769 10 25",
    "sg:postcode":"6300",
    "sg:province":"Zug",
    "wof:name":"Remed Verlags Ag",
    "wof:placetype":"venue"
},
  "geometry": {"coordinates":[8.517702,47.180416],"type":"Point"}
}