{
  "type": "Feature",
  "properties": {
    "iso:country":"CH",
    "sg:address":"Contrada Nuova 20",
    "sg:city":"Agno",
    "sg:orig_category":"Zahnarztpraxen",
    "sg:phone":"+41 91 605 24 16",
    "sg:postcode":"6982",
    "sg:province":"Ticino",
    "wof:name":"Dott. Med. Dent. Carlo Bottini Dentista",
    "wof:placetype":"venue"
},
  "geometry": {"coordinates":[8.901049614,45.9976768494],"type":"Point"}
}