{
  "type": "Feature",
  "properties": {
    "iso:country":"CH",
    "sg:address":"Ryfflig\u00e4sschen 6",
    "sg:city":"Bern",
    "sg:orig_category":"Detailhandel Kinos Reparatur von Gebrauchsg\u00fctern",
    "sg:phone":"+41 31 311 12 04",
    "sg:postcode":"3011",
    "sg:province":"Bern",
    "wof:name":"Kino Cin\u00e9 6 East Cin\u00e9mas Ag",
    "wof:placetype":"venue"
},
  "geometry": {"coordinates":[7.4420452118,46.9485054016],"type":"Point"}
}