{
  "type": "Feature",
  "properties": {
    "addr:full":"Oberdorfstrasse 13 M\u00fcnchenbuchsee Bern 3053",
    "addr:housenumber":"13",
    "addr:postcode":"3053",
    "addr:street":"Oberdorfstrasse",
    "iso:country":"CH",
    "sg:address":"Oberdorfstrasse 13",
    "sg:city":"M\u00fcnchenbuchsee",
    "sg:orig_category":"Detailhandel mit Brot, Back U S\u00fcsswaren",
    "sg:postcode":"3053",
    "sg:province":"Bern",
    "wof:name":"Krieger J.c.",
    "wof:placetype":"venue"
},
  "geometry": {"coordinates":[6.86265,46.465328],"type":"Point"}
}