{
  "type": "Feature",
  "properties": {
    "iso:country":"CH",
    "sg:address":"Bahnhofstrasse 9",
    "sg:city":"Wimmis",
    "sg:orig_category":"Verkehrs- and Tourismusb\u00fcros",
    "sg:phone":"+41 33 657 16 20",
    "sg:postcode":"3752",
    "sg:province":"Bern",
    "wof:name":"Verkehrsb\u00fcro",
    "wof:placetype":"venue"
},
  "geometry": {"coordinates":[7.6356248856,46.6756744385],"type":"Point"}
}