{
  "type": "Feature",
  "properties": {
    "addr:full":"In Der Mettlen 3 B\u00e4retswil Z\u00fcrich 8344",
    "addr:housenumber":"3",
    "addr:postcode":"8344",
    "addr:street":"In Der Mettlen;Zuerich",
    "iso:country":"CH",
    "sg:address":"In Der Mettlen 3",
    "sg:city":"B\u00e4retswil",
    "sg:orig_category":"Autogaragen",
    "sg:phone":"+41 62 291 15 05",
    "sg:postcode":"8344",
    "sg:province":"Z\u00fcrich",
    "wof:name":"Heinz Suter Autogarage",
    "wof:placetype":"venue"
},
  "geometry": {"coordinates":[7.979397,47.35516],"type":"Point"}
}