{
  "type": "Feature",
  "properties": {
    "iso:country":"CH",
    "sg:address":"Andhauserstrasse 64",
    "sg:city":"Berg",
    "sg:classifiers":[
        {
            "category":"Government",
            "subcategory":"Fire Station",
            "type":"Public Place"
        }
    ],
    "sg:phone":"+41 71 637 63 63",
    "sg:postcode":"8572",
    "sg:province":"Thurgau",
    "sg:tags":[
        "semiconductor",
        "chip",
        "power"
    ],
    "wof:name":"Alpha Sem Ag",
    "wof:placetype":"venue"
},
  "geometry": {"coordinates":[9.1704826355,47.5777664185],"type":"Point"}
}