{
  "type": "Feature",
  "properties": {
    "iso:country":"CH",
    "sg:address":"M\u00fchlibach 453",
    "sg:city":"Wilchingen",
    "sg:orig_category":"Non-Classified Establishments",
    "sg:phone":"+41 52 681 21 15",
    "sg:postcode":"8217",
    "sg:province":"Schaffhausen",
    "wof:name":"K & R Holding Ag",
    "wof:placetype":"venue"
},
  "geometry": {"coordinates":[8.4598121643,47.6768836975],"type":"Point"}
}