{
  "type": "Feature",
  "properties": {
    "iso:country":"CH",
    "sg:address":"Edlibachstrasse 4",
    "sg:city":"Neuheim",
    "sg:orig_category":"Instandhaltung U Reparatur von Automobilen",
    "sg:phone":"+41 41 755 32 34",
    "sg:postcode":"6345",
    "sg:province":"Zug",
    "wof:name":"Christian Schneitter Autospritzwerk",
    "wof:placetype":"venue"
},
  "geometry": {"coordinates":[8.5685415268,47.1895332336],"type":"Point"}
}