{
  "type": "Feature",
  "properties": {
    "iso:country":"CH",
    "sg:address":"F\u00e4hrstrasse 2",
    "sg:city":"Bern",
    "sg:classifiers":[
        {
            "category":"Restaurant",
            "type":"Food & Drink"
        }
    ],
    "sg:phone":"+41 79 300 38 54",
    "sg:postcode":"3004",
    "sg:province":"Bern",
    "wof:name":"Restaurant Felsenau",
    "wof:placetype":"venue"
},
  "geometry": {"coordinates":[7.4413380623,46.9728393555],"type":"Point"}
}