{
  "type": "Feature",
  "properties": {
    "iso:country":"CH",
    "sg:address":"Le P\u00e9cat 84",
    "sg:city":"Courfaivre",
    "sg:orig_category":"Detailhandel mit Fleisch U Fleischwaren",
    "sg:phone":"+41 32 426 55 39",
    "sg:postcode":"2853",
    "sg:province":"Jura",
    "wof:name":"Bruno Cortat Boucherie",
    "wof:placetype":"venue"
},
  "geometry": {"coordinates":[7.2798600197,47.3349685669],"type":"Point"}
}