{
  "type": "Feature",
  "properties": {
    "iso:country":"CH",
    "sg:address":"Hinterz\u00e4unen 90",
    "sg:city":"Unterlangenegg",
    "sg:orig_category":"Detailhandel mit Boden U Wandbel\u00e4gen ohne Teppiche Verlegen von Fussboden",
    "sg:phone":"+41 52 383 21 77",
    "sg:postcode":"3614",
    "sg:province":"Bern",
    "wof:name":"Gido Marcolin Bodenbel\u00e4ge",
    "wof:placetype":"venue"
},
  "geometry": {"coordinates":[8.794187,47.450596],"type":"Point"}
}