{
  "type": "Feature",
  "properties": {
    "iso:country":"CH",
    "sg:address":"Le Ch\u00e2telard",
    "sg:city":"Treycovagnes",
    "sg:classifiers":[
        {
            "category":"Restaurant",
            "type":"Food & Drink"
        }
    ],
    "sg:phone":"+41 24 445 26 28",
    "sg:postcode":"1436",
    "sg:province":"Vaud",
    "wof:name":"Caf\u00e9 Du Ch\u00e2telard",
    "wof:placetype":"venue"
},
  "geometry": {"coordinates":[6.6175489426,46.7785224915],"type":"Point"}
}