{
  "type": "Feature",
  "properties": {
    "iso:country":"CH",
    "sg:address":"Crans-sur-sierre",
    "sg:city":"Chermignon",
    "sg:orig_category":"Detailhandel mit B\u00fcchern, Zeitungen, Schreib U Papeteriewaren",
    "sg:postcode":"3971",
    "sg:province":"Valais",
    "wof:name":"Librairie De Crans, Rey Lucie",
    "wof:placetype":"venue"
},
  "geometry": {"coordinates":[7.47849,46.283951],"type":"Point"}
}