{
  "type": "Feature",
  "properties": {
    "iso:country":"CH",
    "sg:address":"Chemin Des Dailles 36",
    "sg:city":"Monthey",
    "sg:orig_category":"Sonstiger spezialisierter Hoch U Tiefbau",
    "sg:phone":"+41 24 472 71 75",
    "sg:postcode":"1870",
    "sg:province":"Valais",
    "wof:name":"Premand Joseph",
    "wof:placetype":"venue"
},
  "geometry": {"coordinates":[6.9485669136,46.2639274597],"type":"Point"}
}