{
  "type": "Feature",
  "properties": {
    "iso:country":"CH",
    "sg:address":"Thujastrasse 55",
    "sg:city":"Z\u00fcrich",
    "sg:orig_category":"Fotografische Ateliers",
    "sg:phone":"+41 14920909",
    "sg:postcode":"8038",
    "sg:province":"Z\u00fcrich",
    "wof:name":"Tres Camenzind Fotostudio",
    "wof:placetype":"venue"
},
  "geometry": {"coordinates":[8.524394989,47.347694397],"type":"Point"}
}