{
  "type": "Feature",
  "properties": {
    "iso:country":"CH",
    "sg:address":"Rue De La Gare 30 1260 Nyon. Postfach",
    "sg:city":"Nyon",
    "sg:orig_category":"Unclassifiable Establishments",
    "sg:postcode":"1260",
    "sg:province":"Vaud",
    "wof:name":"Kalicura Investment Ag",
    "wof:placetype":"venue"
},
  "geometry": {"coordinates":[9.1381845474,47.5666694641],"type":"Point"}
}