{
  "type": "Feature",
  "properties": {
    "iso:country":"CH",
    "sg:address":"Breiten 3",
    "sg:city":"Kaisten",
    "sg:orig_category":"Grosshandel mit Datenverarbeitungsger\u00e4ten Grosshandel mit Software",
    "sg:phone":"+41 62 874 28 09",
    "sg:postcode":"5082",
    "sg:province":"Aargau",
    "wof:name":"Buecomp Gmbh",
    "wof:placetype":"venue"
},
  "geometry": {"coordinates":[8.0478973389,47.5385475159],"type":"Point"}
}