{
  "type": "Feature",
  "properties": {
    "iso:country":"CH",
    "sg:address":"Rue Du Temple 2 2900 Pruntrut. Postfach",
    "sg:city":"Pruntrut",
    "sg:orig_category":"Reiseb\u00fcros U Reiseveranstalter",
    "sg:postcode":"2900",
    "sg:province":"Jura",
    "wof:name":"Evasions.com S\u00e0rl",
    "wof:placetype":"venue"
},
  "geometry": {"coordinates":[7.0735931396,47.4157485962],"type":"Point"}
}