{
  "type": "Feature",
  "properties": {
    "iso:country":"CH",
    "sg:address":"Wiesenstrasse 26",
    "sg:city":"Langenthal",
    "sg:orig_category":"Detailhandel mit Geschenkartikeln U Souvenirs",
    "sg:phone":"+41 81 416 46 42",
    "sg:postcode":"4900",
    "sg:province":"Bern",
    "wof:name":"Boutique (13) Claudia Bischof",
    "wof:placetype":"venue"
},
  "geometry": {"coordinates":[9.8338565826,46.8014411926],"type":"Point"}
}