{
  "type": "Feature",
  "properties": {
    "iso:country":"CH",
    "sg:address":"Gustav-kahlenbach-platz",
    "sg:city":"Rheinfelden",
    "sg:orig_category":"Vorschulen, Kinderg\u00e4rten",
    "sg:phone":"+41 81 756 08 74",
    "sg:postcode":"4310",
    "sg:province":"Aargau",
    "wof:name":"Kindergarten",
    "wof:placetype":"venue"
},
  "geometry": {"coordinates":[8.0736198425,47.3907279968],"type":"Point"}
}