{
  "type": "Feature",
  "properties": {
    "iso:country":"CH",
    "sg:address":"Rte Du Centre 11",
    "sg:city":"Grolley",
    "sg:orig_category":"Detailhandel mit Fleisch U Fleischwaren",
    "sg:phone":"+41 26 475 36 73",
    "sg:postcode":"1772",
    "sg:province":"Fribourg",
    "wof:name":"Boucherie Cl\u00e9ment Pascal",
    "wof:placetype":"venue"
},
  "geometry": {"coordinates":[7.0643677711,46.8319091797],"type":"Point"}
}