{
  "type": "Feature",
  "properties": {
    "iso:country":"CH",
    "sg:address":"Bahnhofstrasse 3",
    "sg:city":"D\u00fcdingen",
    "sg:orig_category":"Sportvereine Turnen",
    "sg:phone":"+41 71 298 40 88",
    "sg:postcode":"3186",
    "sg:province":"Fribourg",
    "wof:name":"Turnverein St.gallen-ost",
    "wof:placetype":"venue"
},
  "geometry": {"coordinates":[9.3956165314,47.4558448792],"type":"Point"}
}