{
  "type": "Feature",
  "properties": {
    "iso:country":"CH",
    "sg:address":"Rue Du Coq 6",
    "sg:city":"Montagne-sonvilier",
    "sg:orig_category":"Sportvereine Eissport Eishockey",
    "sg:phone":"+41 79 637 42 01",
    "sg:postcode":"2615",
    "sg:province":"Bern",
    "wof:name":"Hockey-club Sonvilie",
    "wof:placetype":"venue"
},
  "geometry": {"coordinates":[6.9674940109,47.1393623352],"type":"Point"}
}