{
  "type": "Feature",
  "properties": {
    "iso:country":"CH",
    "sg:address":"Stadthausgasse 6",
    "sg:city":"Schaffhausen",
    "sg:classifiers":[
        {
            "category":"Restaurant",
            "type":"Food & Drink"
        }
    ],
    "sg:phone":"+41 56 631 33 11",
    "sg:postcode":"8200",
    "sg:province":"Schaffhausen",
    "sg:tags":[
        "tea-rooms",
        "restaurants"
    ],
    "wof:name":"El Mosquito Restaurationsbetriebe Gmbh",
    "wof:placetype":"venue"
},
  "geometry": {"coordinates":[8.3400030136,47.3491363525],"type":"Point"}
}