{
  "type": "Feature",
  "properties": {
    "iso:country":"CH",
    "sg:address":"Witmattstrasse 51",
    "sg:city":"Grenchen",
    "sg:orig_category":"Electrosurgical Devices",
    "sg:phone":"+41 32 652 22 50",
    "sg:postcode":"2540",
    "sg:province":"Solothurn",
    "wof:name":"Zamelco",
    "wof:placetype":"venue"
},
  "geometry": {"coordinates":[7.3955841064,47.1857643127],"type":"Point"}
}