{
  "type": "Feature",
  "properties": {
    "iso:country":"CH",
    "sg:address":"B\u00e4chliackerweg 16",
    "sg:city":"Frenkendorf",
    "sg:orig_category":"Oberfl\u00e4chenveredlung U W\u00e4rmebehandlung",
    "sg:phone":"+41 61 901 18 72",
    "sg:postcode":"4402",
    "sg:province":"Basel-Landschaft",
    "wof:name":"Gebr. Thommen",
    "wof:placetype":"venue"
},
  "geometry": {"coordinates":[7.7162041664,47.4979705811],"type":"Point"}
}