{
  "type": "Feature",
  "properties": {
    "iso:country":"CH",
    "sg:address":"Bachstrasse 44",
    "sg:city":"Schaffhausen",
    "sg:orig_category":"Non-Classified Establishments",
    "sg:postcode":"8200",
    "sg:province":"Schaffhausen",
    "wof:name":"Behama Holding Ag",
    "wof:placetype":"venue"
},
  "geometry": {"coordinates":[8.6377372742,47.697769165],"type":"Point"}
}