{
  "type": "Feature",
  "properties": {
    "iso:country":"CH",
    "sg:address":"Oberdorfstrasse 19",
    "sg:city":"Dietikon",
    "sg:orig_category":"Unternehmensberatung",
    "sg:postcode":"8953",
    "sg:province":"Z\u00fcrich",
    "wof:name":"Klauser Edith, Consulting.",
    "wof:placetype":"venue"
},
  "geometry": {"coordinates":[8.3991794586,47.4018859863],"type":"Point"}
}