{
  "type": "Feature",
  "properties": {
    "iso:country":"CH",
    "sg:address":"2828",
    "sg:city":"Montsevelier",
    "sg:orig_category":"Vereine Musik/Blasmusik",
    "sg:postcode":"2828",
    "sg:province":"Jura",
    "wof:name":"St\u00e9 De Musique Concordia",
    "wof:placetype":"venue"
},
  "geometry": {"coordinates":[7.2124481201,46.0804595947],"type":"Point"}
}