{
  "type": "Feature",
  "properties": {
    "addr:full":"Piazzetta Achille Borella 4 Mendrisio Ticino 6850",
    "addr:housenumber":"4",
    "addr:postcode":"6850",
    "addr:street":"Piazzetta Achille Borella",
    "iso:country":"CH",
    "sg:address":"Piazzetta Achille Borella 4",
    "sg:city":"Mendrisio",
    "sg:orig_category":"Detailhandel mit Damenbekleidung",
    "sg:phone":"+41 91 646 34 61",
    "sg:postcode":"6850",
    "sg:province":"Ticino",
    "wof:name":"Eleonora Pesciolini Prontex-moda",
    "wof:placetype":"venue"
},
  "geometry": {"coordinates":[8.986297,45.869316],"type":"Point"}
}