{
  "type": "Feature",
  "properties": {
    "iso:country":"CH",
    "sg:address":"Rathausstrasse 66",
    "sg:city":"Liestal",
    "sg:orig_category":"Public-Relations-Agenturen",
    "sg:phone":"+41 61 923 05 15",
    "sg:postcode":"4410",
    "sg:province":"Basel-Landschaft",
    "wof:name":"Bea Rieder Public Relations",
    "wof:placetype":"venue"
},
  "geometry": {"coordinates":[7.7351517677,47.4834709167],"type":"Point"}
}