{
  "type": "Feature",
  "properties": {
    "iso:country":"CH",
    "sg:address":"Pf\u00e4ffikonerstrasse 8 8834 Schindellegi. Postfach",
    "sg:city":"Schindellegi",
    "sg:orig_category":"Herstellung von medizinischen U chirurgischen Ger\u00e4ten sowie orthop\u00e4dischen Vorrichtungen",
    "sg:postcode":"8834",
    "sg:province":"Schwyz",
    "wof:name":"Magno-sana, Tiefenthaler K.j.",
    "wof:placetype":"venue"
},
  "geometry": {"coordinates":[8.7134237289,47.1750030518],"type":"Point"}
}