{
  "type": "Feature",
  "properties": {
    "iso:country":"CH",
    "sg:address":"Schwandenstrasse 8",
    "sg:city":"Stallikon",
    "sg:classifiers":[
        {
            "category":"Wholesale",
            "subcategory":"Vending Machines",
            "type":"Manufacturing & Wholesale Goods"
        }
    ],
    "sg:phone":"+41 17000212",
    "sg:postcode":"8143",
    "sg:province":"Z\u00fcrich",
    "sg:tags":[
        "bag",
        "sealing"
    ],
    "wof:name":"Markus Sproll",
    "wof:placetype":"venue"
},
  "geometry": {"coordinates":[8.472659,47.351707],"type":"Point"}
}