{
  "type": "Feature",
  "properties": {
    "iso:country":"CH",
    "sg:address":"Zelglistrasse 41",
    "sg:city":"Fislisbach",
    "sg:orig_category":"Unclassifiable Establishments",
    "sg:postcode":"5442",
    "sg:province":"Aargau",
    "wof:name":"Rail4you.ch Bahntechnik Mechatronik Informatik Gmbh",
    "wof:placetype":"venue"
},
  "geometry": {"coordinates":[8.2927703857,47.4328765869],"type":"Point"}
}