{
  "type": "Feature",
  "properties": {
    "iso:country":"CH",
    "sg:address":"6563",
    "sg:city":"Mesocco",
    "sg:orig_category":"Allgemeiner Hoch U Tiefbau Allgemeiner Hochbau",
    "sg:phone":"+41 79 207 16 08",
    "sg:postcode":"6563",
    "sg:province":"Graubunden",
    "wof:name":"Barella Sa",
    "wof:placetype":"venue"
},
  "geometry": {"coordinates":[9.2329,46.391632],"type":"Point"}
}