{
  "type": "Feature",
  "properties": {
    "iso:country":"CH",
    "sg:address":"Aem\u00e4ttlihof 105",
    "sg:city":"Stans",
    "sg:orig_category":"Detailhandel mit Metallwaren, Anstrichmitteln, Glaswaren, Bau U Heimwerkerbedarf",
    "sg:phone":"+41 41 611 16 50",
    "sg:postcode":"6370",
    "sg:province":"Nidwalden",
    "wof:name":"Cdh Ag",
    "wof:placetype":"venue"
},
  "geometry": {"coordinates":[8.3572664261,46.9630851746],"type":"Point"}
}