{
  "type": "Feature",
  "properties": {
    "iso:country":"CH",
    "sg:address":"Belpbergstrasse 8",
    "sg:city":"Belp",
    "sg:orig_category":"Malerei Stukkateurgewerbe, Gipserei U Verputzerei",
    "sg:phone":"+41 32 931 55 88",
    "sg:postcode":"3123",
    "sg:province":"Bern",
    "wof:name":"Vuillemin Frank Pl\u00e2trerie-peinture",
    "wof:placetype":"venue"
},
  "geometry": {"coordinates":[6.6999487877,47.0671882629],"type":"Point"}
}