{
  "type": "Feature",
  "properties": {
    "iso:country":"CH",
    "sg:address":"Stadthausstrasse 8400 Winterthur. Postfach 689",
    "sg:city":"Winterthur",
    "sg:orig_category":"Verwaltung der Rechtspflege, Gerichte",
    "sg:phone":"+41 52 212 10 83",
    "sg:postcode":"8401",
    "sg:province":"Z\u00fcrich",
    "wof:name":"Notariat Grundbuch-& Konkursamt Oberwinterthur",
    "wof:placetype":"venue"
},
  "geometry": {"coordinates":[8.7322292328,47.5005187988],"type":"Point"}
}