{
  "type": "Feature",
  "properties": {
    "iso:country":"CH",
    "sg:address":"St. Klara-rain 1 6370 Stans. Postfach 1062",
    "sg:city":"Stans",
    "sg:orig_category":"Werbevermittlung Werbung",
    "sg:phone":"+41 21 647 12 31",
    "sg:postcode":"6371",
    "sg:province":"Nidwalden",
    "wof:name":"S3c Groupe De Communication Souham G\u00e9rard Sa",
    "wof:placetype":"venue"
},
  "geometry": {"coordinates":[6.6239891052,46.5260353088],"type":"Point"}
}