{
  "type": "Feature",
  "properties": {
    "iso:country":"CH",
    "sg:address":"Aebnitstr. 5",
    "sg:city":"Arch",
    "sg:orig_category":"Grosshandel mit sonstigen Gebrauchs U Verbrauchsg\u00fctern",
    "sg:phone":"+41 32 679 35 79",
    "sg:postcode":"3296",
    "sg:province":"Bern",
    "wof:name":"Kia Automaten, Supper Oliver",
    "wof:placetype":"venue"
},
  "geometry": {"coordinates":[7.4318771362,47.1671104431],"type":"Point"}
}