{
  "type": "Feature",
  "properties": {
    "addr:full":"Waldeggweg 3 Unterkulm Aargau 5726",
    "addr:housenumber":"3",
    "addr:postcode":"5726",
    "addr:street":"Waldeggweg",
    "iso:country":"CH",
    "sg:address":"Waldeggweg 3",
    "sg:city":"Unterkulm",
    "sg:orig_category":"Architektur U Ingenieurb\u00fcros",
    "sg:phone":"+41 62 776 19 38",
    "sg:postcode":"5726",
    "sg:province":"Aargau",
    "wof:name":"Peter Buchwalder Technisches B\u00fcro",
    "wof:placetype":"venue"
},
  "geometry": {"coordinates":[8.11578,47.31432],"type":"Point"}
}