{
  "type": "Feature",
  "properties": {
    "iso:country":"CH",
    "sg:address":"Eichstrasse 18",
    "sg:city":"Neuenhof",
    "sg:orig_category":"Herstellung von Ger\u00e4ten der Elektrizit\u00e4tserzeugung, -verteilung u.\u00e4. -Herstellung von sonstigen elek",
    "sg:phone":"+41 56 416 04 16",
    "sg:postcode":"5432",
    "sg:province":"Aargau",
    "wof:name":"Statron Ag",
    "wof:placetype":"venue"
},
  "geometry": {"coordinates":[8.3252658844,47.4503593445],"type":"Point"}
}