{
  "type": "Feature",
  "properties": {
    "iso:country":"CH",
    "sg:address":"Dorfstrasse",
    "sg:city":"Matten(st.stephan)",
    "sg:orig_category":"Detailhandel mit Getr\u00e4nken Detailhandel mit Waren verschiedener Art, Hauptrichtung Nahrungsmittel",
    "sg:phone":"+41 17500303",
    "sg:postcode":"3773",
    "sg:province":"Bern",
    "wof:name":"Roland Wyss Fisch-& Getr\u00e4nkehandlung",
    "wof:placetype":"venue"
},
  "geometry": {"coordinates":[8.4356536865,47.4189376831],"type":"Point"}
}