{
  "type": "Feature",
  "properties": {
    "iso:country":"CH",
    "sg:address":"Z\u00fcrichstrasse 106",
    "sg:city":"Adliswil",
    "sg:orig_category":"Unternehmensberatung",
    "sg:phone":"+41 41 410 34 03",
    "sg:postcode":"8134",
    "sg:province":"Z\u00fcrich",
    "wof:name":"M\u00fchlebach & Mitarbeiter Advokaturb\u00fcro",
    "wof:placetype":"venue"
},
  "geometry": {"coordinates":[8.3073883057,47.0535697937],"type":"Point"}
}