{
  "type": "Feature",
  "properties": {
    "iso:country":"CH",
    "sg:address":"G.-f.-heilmann-strasse 12",
    "sg:city":"Biel/bienne",
    "sg:orig_category":"Detailhandel mit Haustieren U zoologischem Bedarf",
    "sg:phone":"+41 32 323 58 22",
    "sg:postcode":"2502",
    "sg:province":"Bern",
    "wof:name":"Laslo Cseh Aquarium Piranha",
    "wof:placetype":"venue"
},
  "geometry": {"coordinates":[7.2499489784,47.1428947449],"type":"Point"}
}