{
  "type": "Feature",
  "properties": {
    "addr:full":"Aeschstrasse 2 Ettingen Basel-Landschaft 4107",
    "addr:housenumber":"2",
    "addr:postcode":"4107",
    "addr:street":"Aeschstrasse",
    "iso:country":"CH",
    "sg:address":"Aeschstrasse 2",
    "sg:city":"Ettingen",
    "sg:classifiers":[
        {
            "category":"Bars & Pubs",
            "type":"Food & Drink"
        }
    ],
    "sg:phone":"+41 61 721 11 72",
    "sg:postcode":"4107",
    "sg:province":"Basel-Landschaft",
    "wof:name":"Pub Zum Scharfe Egg",
    "wof:placetype":"venue"
},
  "geometry": {"coordinates":[7.544593,47.480747],"type":"Point"}
}