{
  "type": "Feature",
  "properties": {
    "addr:full":"Rue Du 31-d\u00e9cembre 47 Gen\u00e8ve Gen\u00e8ve 1207",
    "addr:housenumber":"47",
    "addr:postcode":"1207",
    "addr:street":"Rue Du 31-De \u0301Cembre",
    "iso:country":"CH",
    "sg:address":"Rue Du 31-d\u00e9cembre 47",
    "sg:city":"Gen\u00e8ve",
    "sg:orig_category":"Advokaturb\u00fcros",
    "sg:phone":"+41 22 849 60 40",
    "sg:postcode":"1207",
    "sg:province":"Gen\u00e8ve",
    "wof:name":"Fasel Bochatay & Tsimaratos Etude D'avocat",
    "wof:placetype":"venue"
},
  "geometry": {"coordinates":[6.161117,46.201935],"type":"Point"}
}