{
  "type": "Feature",
  "properties": {
    "iso:country":"CH",
    "sg:address":"Locarno Via 10",
    "sg:city":"Ascona",
    "sg:orig_category":"Finanzierungsinstitutionen",
    "sg:phone":"+41 91 791 14 11",
    "sg:postcode":"6612",
    "sg:province":"Ticino",
    "wof:name":"Im Invest Management Sa",
    "wof:placetype":"venue"
},
  "geometry": {"coordinates":[8.7696800232,46.1568946838],"type":"Point"}
}