{
  "type": "Feature",
  "properties": {
    "iso:country":"CH",
    "sg:address":"Brahaldenstrasse 8",
    "sg:city":"Neftenbach",
    "sg:orig_category":"Unclassifiable Establishments",
    "sg:postcode":"8413",
    "sg:province":"Z\u00fcrich",
    "wof:name":"Odz Systeme, W. J. Zweidler.",
    "wof:placetype":"venue"
},
  "geometry": {"coordinates":[8.6646995544,47.5595169067],"type":"Point"}
}