{
  "type": "Feature",
  "properties": {
    "iso:country":"CH",
    "sg:address":"Kirchstrasse 15",
    "sg:city":"Kreuzlingen",
    "sg:orig_category":"Detailhandel mit Musikinstrumenten Detailhandel mit elektrischen Haushalts-,Radio U Fernsehger\u00e4ten s",
    "sg:phone":"+41 71 672 27 15",
    "sg:postcode":"8280",
    "sg:province":"Thurgau",
    "wof:name":"Haag Musik Ag",
    "wof:placetype":"venue"
},
  "geometry": {"coordinates":[9.0477952957,47.4638252258],"type":"Point"}
}