{
  "type": "Feature",
  "properties": {
    "iso:country":"CH",
    "sg:address":"Rue Fr\u00e9d\u00e9ric Soguel 22",
    "sg:city":"Cernier",
    "sg:orig_category":"Arztpraxen",
    "sg:phone":"+41 32 853 22 77",
    "sg:postcode":"2053",
    "sg:province":"Neuch\u00e2tel",
    "wof:name":"Dr M\u00e9d. Raymond P\u00e9ter-contesse M\u00e9decin G\u00e9n\u00e9raliste Fmh",
    "wof:placetype":"venue"
},
  "geometry": {"coordinates":[6.903548,47.059475],"type":"Point"}
}