{
  "type": "Feature",
  "properties": {
    "iso:country":"CH",
    "sg:address":"Schweizerhofstrasse 6 8750 Glarus. Postfach 321",
    "sg:city":"Glarus",
    "sg:orig_category":"F\u00fcrsorge\u00e4mter",
    "sg:phone":"+41 55 640 47 25",
    "sg:postcode":"8750",
    "sg:province":"Glarus",
    "wof:name":"F\u00fcrsorgeamt Glarus-riedern",
    "wof:placetype":"venue"
},
  "geometry": {"coordinates":[9.0707101822,47.0407028198],"type":"Point"}
}