{
  "type": "Feature",
  "properties": {
    "iso:country":"CH",
    "sg:address":"Lochm\u00fchle",
    "sg:city":"Illighausen",
    "sg:orig_category":"Grosshandel mit Holz U Baustoffen",
    "sg:postcode":"8574",
    "sg:province":"Thurgau",
    "wof:name":"Walser's Be-fix",
    "wof:placetype":"venue"
},
  "geometry": {"coordinates":[8.841345787,47.2992858887],"type":"Point"}
}