{
  "type": "Feature",
  "properties": {
    "iso:country":"CH",
    "sg:address":"Bolleystrasse 7",
    "sg:city":"Z\u00fcrich",
    "sg:orig_category":"Detailhandel mit elektrischen Haushalts-,Radio U Fernsehger\u00e4ten sowie Musikinstrumenten",
    "sg:phone":"+41 91 648 24 70",
    "sg:postcode":"8006",
    "sg:province":"Z\u00fcrich",
    "wof:name":"S.i.a.v.a. Di Caputo Enrico",
    "wof:placetype":"venue"
},
  "geometry": {"coordinates":[8.9712247849,45.9057006836],"type":"Point"}
}