{
  "type": "Feature",
  "properties": {
    "iso:country":"CH",
    "sg:address":"Rebenstrasse 60",
    "sg:city":"Arbon",
    "sg:orig_category":"RESTAURANTS: TEA-ROOMS",
    "sg:postcode":"9320",
    "sg:province":"Thurgau",
    "wof:name":"Geugel Hans",
    "wof:placetype":"venue"
},
  "geometry": {"coordinates":[9.4235954285,47.514503479],"type":"Point"}
}