{
  "type": "Feature",
  "properties": {
    "iso:country":"CH",
    "sg:address":"Burgunderstrasse 69",
    "sg:city":"Bern",
    "sg:orig_category":"Erschliessung von Grundst\u00fccken",
    "sg:postcode":"3018",
    "sg:province":"Bern",
    "wof:name":"Iii. Baugenossenschaft Des Verwaltungspersonals In Bern, Siedlung Burgunderstrasse",
    "wof:placetype":"venue"
},
  "geometry": {"coordinates":[7.3977770805,46.9400024414],"type":"Point"}
}