{
  "type": "Feature",
  "properties": {
    "iso:country":"CH",
    "sg:address":"Bahnhofstrasse 41",
    "sg:city":"Amriswil",
    "sg:orig_category":"Detailhandel mit Fleisch U Fleischwaren",
    "sg:phone":"+41 71 411 07 70",
    "sg:postcode":"8580",
    "sg:province":"Thurgau",
    "wof:name":"Bernhard & Martin St\u00fcdli St\u00fcdli's Metzg-party Service",
    "wof:placetype":"venue"
},
  "geometry": {"coordinates":[9.303103447,47.5495452881],"type":"Point"}
}