{
  "type": "Feature",
  "properties": {
    "iso:country":"CH",
    "sg:address":"Rue Emile-bo\u00e9chat 119",
    "sg:city":"Del\u00e9mont",
    "sg:orig_category":"Grosshandel mit Baumaterialien",
    "sg:phone":"+41 32 423 55 50",
    "sg:postcode":"2800",
    "sg:province":"Jura",
    "wof:name":"Stratex Sa",
    "wof:placetype":"venue"
},
  "geometry": {"coordinates":[7.3600068092,47.3587875366],"type":"Point"}
}