{
  "type": "Feature",
  "properties": {
    "iso:country":"CH",
    "sg:address":"Ueberlandstrasse 5",
    "sg:city":"Z\u00fcrich",
    "sg:orig_category":"Sonstige mit der Informatik verbundene T\u00e4tigkeiten",
    "sg:postcode":"8000",
    "sg:province":"Z\u00fcrich",
    "wof:name":"Rothation, Peter Roth",
    "wof:placetype":"venue"
},
  "geometry": {"coordinates":[8.5557804108,47.4034118652],"type":"Point"}
}