{
  "type": "Feature",
  "properties": {
    "iso:country":"CH",
    "sg:address":"Marktgasse 37",
    "sg:city":"Langenthal",
    "sg:orig_category":"Arztpraxen",
    "sg:phone":"+41 71 923 44 23",
    "sg:postcode":"4900",
    "sg:province":"Bern",
    "wof:name":"Dr.med.franz L\u00fcthi Arzt F.allgemeine Medizin Fmh",
    "wof:placetype":"venue"
},
  "geometry": {"coordinates":[-77.133026,40.476929],"type":"Point"}
}