{
  "type": "Feature",
  "properties": {
    "iso:country":"CH",
    "sg:address":"Bahnhofstrasse 21 6300 Zug. Postfach",
    "sg:city":"Zug",
    "sg:orig_category":"Unclassifiable Establishments",
    "sg:postcode":"6300",
    "sg:province":"Zug",
    "wof:name":"Alkona Holding Ag",
    "wof:placetype":"venue"
},
  "geometry": {"coordinates":[9.2466087341,47.4197807312],"type":"Point"}
}