{
  "type": "Feature",
  "properties": {
    "iso:country":"CH",
    "sg:address":"M\u00fchlerain 14",
    "sg:city":"Meilen",
    "sg:orig_category":"Vermietung U Verpachtung von eigenen Immobilien",
    "sg:postcode":"8706",
    "sg:province":"Z\u00fcrich",
    "wof:name":"Alpropria G Immobilien Ag",
    "wof:placetype":"venue"
},
  "geometry": {"coordinates":[8.6669921875,47.2635688782],"type":"Point"}
}