{
  "type": "Feature",
  "properties": {
    "iso:country":"CH",
    "sg:address":"Rue Saint-joseph 25",
    "sg:city":"Bulle",
    "sg:classifiers":[
        {
            "category":"Military Area",
            "subcategory":"Army Base",
            "type":"Public Place"
        }
    ],
    "sg:phone":"+41 26 913 09 00",
    "sg:postcode":"1630",
    "sg:province":"Fribourg",
    "sg:tags":[
        "electrostatic",
        "coating",
        "powder"
    ],
    "wof:name":"Dupont Polymer Powders Switzerland S\u00e0rl",
    "wof:placetype":"venue"
},
  "geometry": {"coordinates":[7.044233799,46.6149711609],"type":"Point"}
}