{
  "type": "Feature",
  "properties": {
    "iso:country":"CH",
    "sg:address":"Hohlenbaumstrasse 71",
    "sg:city":"Schaffhausen",
    "sg:orig_category":"Detailhandel mit Fleisch U Fleischwaren",
    "sg:phone":"+41 52 625 77 72",
    "sg:postcode":"8200",
    "sg:province":"Schaffhausen",
    "wof:name":"Hauser Ren\u00e9 Metzgerei",
    "wof:placetype":"venue"
},
  "geometry": {"coordinates":[8.6191272736,47.7063217163],"type":"Point"}
}