{
  "type": "Feature",
  "properties": {
    "iso:country":"CH",
    "sg:address":"Innere G\u00fcterstrasse 4",
    "sg:city":"Zug",
    "sg:orig_category":"Vermietung U Verpachtung von eigenen Immobilien Vermittlung von Immobilien",
    "sg:phone":"+41 61 716 95 40",
    "sg:postcode":"6300",
    "sg:province":"Zug",
    "wof:name":"Poka Immobilien Ag",
    "wof:placetype":"venue"
},
  "geometry": {"coordinates":[7.5929059982,47.4923210144],"type":"Point"}
}