{
  "type": "Feature",
  "properties": {
    "iso:country":"CH",
    "sg:address":"Schaffhauserstrasse 279",
    "sg:city":"Z\u00fcrich",
    "sg:orig_category":"Sanit\u00e4r U Heizungsinstallation Sanit\u00e4r, Heizungs U L\u00fcftungsinstallation",
    "sg:phone":"+41 31 302 10 84",
    "sg:postcode":"8057",
    "sg:province":"Z\u00fcrich",
    "wof:name":"Gfeller Heizungsbau",
    "wof:placetype":"venue"
},
  "geometry": {"coordinates":[7.4244189262,46.9548454285],"type":"Point"}
}