{
  "type": "Feature",
  "properties": {
    "iso:country":"CH",
    "sg:address":"En Budron H 13",
    "sg:city":"Mont-sur-lausanne",
    "sg:orig_category":"Grosshandel mit sonstigen Maschinen U Ausr\u00fcstungen f\u00fcr Industrie, Handel U Schiffahrt",
    "sg:postcode":"1052",
    "sg:province":"Vaud",
    "wof:name":"Kba - Le Mont-sur-lausanne Sa",
    "wof:placetype":"venue"
},
  "geometry": {"coordinates":[6.6287908554,46.5716514587],"type":"Point"}
}