{
  "type": "Feature",
  "properties": {
    "iso:country":"CH",
    "sg:address":"Rue Du Mont-blanc 5",
    "sg:city":"Gen\u00e8ve",
    "sg:classifiers":[
        {
            "category":"Professional",
            "subcategory":"Employment Agencies",
            "type":"Services"
        }
    ],
    "sg:phone":"+41 22 731 96 44",
    "sg:postcode":"1201",
    "sg:province":"Gen\u00e8ve",
    "sg:tags":[
        "personal",
        "u",
        "stellenvermittlung"
    ],
    "wof:name":"Randstad (schweiz) Ag",
    "wof:placetype":"venue"
},
  "geometry": {"coordinates":[6.1465139389,46.2074241638],"type":"Point"}
}