{
  "type": "Feature",
  "properties": {
    "iso:country":"CH",
    "sg:address":"8052 Z\u00fcrich. Postfach 813",
    "sg:city":"Z\u00fcrich",
    "sg:orig_category":"Sportvereine Ballsport Fussball Vereine Damen",
    "sg:phone":"+41 18602336",
    "sg:postcode":"8052",
    "sg:province":"Z\u00fcrich",
    "wof:name":"Sv Seebach Zh Abt.damen",
    "wof:placetype":"venue"
},
  "geometry": {"coordinates":[8.5387096405,47.4295196533],"type":"Point"}
}