{
  "type": "Feature",
  "properties": {
    "iso:country":"CH",
    "sg:address":"Weissensteinstrasse 4",
    "sg:city":"Bern",
    "sg:orig_category":"Detailhandel mit Teppichen Verlegen von Fliesen U Platten",
    "sg:phone":"+41 31 385 28 30",
    "sg:postcode":"3008",
    "sg:province":"Bern",
    "wof:name":"Walter Lustenberger Ag Bodenbel\u00e4ge Teppiche",
    "wof:placetype":"venue"
},
  "geometry": {"coordinates":[7.4137558937,46.9418487549],"type":"Point"}
}