{
  "type": "Feature",
  "properties": {
    "iso:country":"CH",
    "sg:address":"Rugenparkstrasse 2 3800 Interlaken. Postfach",
    "sg:city":"Interlaken",
    "sg:orig_category":"Vermietung U Verpachtung von eigenen Immobilien",
    "sg:postcode":"3800",
    "sg:province":"Bern",
    "wof:name":"Walter Gerber-von Dach",
    "wof:placetype":"venue"
},
  "geometry": {"coordinates":[8.1821708679,47.4197998047],"type":"Point"}
}