{
  "type": "Feature",
  "properties": {
    "iso:country":"CH",
    "sg:address":"Neumatt 8",
    "sg:city":"Laufen",
    "sg:orig_category":"Grosshandel mit Eisenwaren sowie Installationsbedarf f\u00fcr Gas, Wasser U Heizung Sonstiger spezialisie",
    "sg:phone":"+41 61 763 06 60",
    "sg:postcode":"4242",
    "sg:province":"Basel-Landschaft",
    "wof:name":"Halkamin Gmbh",
    "wof:placetype":"venue"
},
  "geometry": {"coordinates":[7.5108571053,47.4234580994],"type":"Point"}
}