{
  "type": "Feature",
  "properties": {
    "iso:country":"CH",
    "sg:address":"Schachen 2746",
    "sg:city":"Schachen",
    "sg:classifiers":[
        {
            "category":"Manufacturing",
            "subcategory":"Wood Products",
            "type":"Manufacturing & Wholesale Goods"
        }
    ],
    "sg:phone":"+41 71 351 31 61",
    "sg:postcode":"9112",
    "sg:province":"Appenzell Ausserrhoden",
    "sg:tags":[
        "firewood"
    ],
    "wof:name":"St\u00fcdli Holz Ag",
    "wof:placetype":"venue"
},
  "geometry": {"coordinates":[8.4731397629,47.3268013],"type":"Point"}
}