{
  "type": "Feature",
  "properties": {
    "iso:country":"CH",
    "sg:address":"Ueberhengert",
    "sg:city":"M\u00f6rel",
    "sg:classifiers":[
        {
            "category":"Insurance",
            "subcategory":"Insurance Agent",
            "type":"Services"
        }
    ],
    "sg:phone":"+41 27 927 17 92",
    "sg:postcode":"3983",
    "sg:province":"Valais",
    "sg:tags":[
        "versicherungsagenturen",
        "-broker"
    ],
    "wof:name":"Basler Versicherungen Agentur",
    "wof:placetype":"venue"
},
  "geometry": {"coordinates":[8.0416326523,46.3543968201],"type":"Point"}
}