{
  "type": "Feature",
  "properties": {
    "iso:country":"CH",
    "sg:address":"Avenue De Gilamont 46",
    "sg:city":"Vevey",
    "sg:orig_category":"Tea, Theine-Free",
    "sg:phone":"+41 21 921 02 37",
    "sg:postcode":"1800",
    "sg:province":"Vaud",
    "wof:name":"Infr\u00e9 S.a.",
    "wof:placetype":"venue"
},
  "geometry": {"coordinates":[6.850479126,46.4700393677],"type":"Point"}
}