{
  "type": "Feature",
  "properties": {
    "iso:country":"CH",
    "sg:address":"Schaalweg 6",
    "sg:city":"M\u00fcnchenbuchsee",
    "sg:orig_category":"Herstellung von Duft U K\u00f6rperpflegemitteln",
    "sg:postcode":"3053",
    "sg:province":"Bern",
    "wof:name":"Balsiger Mc-cosmetics",
    "wof:placetype":"venue"
},
  "geometry": {"coordinates":[7.4534211159,47.0237083435],"type":"Point"}
}