{
  "type": "Feature",
  "properties": {
    "iso:country":"CH",
    "sg:address":"Rue Baptiste-savoye 16",
    "sg:city":"St-imier",
    "sg:orig_category":"Herstellung von Uhren",
    "sg:postcode":"2610",
    "sg:province":"Bern",
    "wof:name":"Fiorucci L\u00e9on",
    "wof:placetype":"venue"
},
  "geometry": {"coordinates":[6.9909567833,47.1495132446],"type":"Point"}
}