{
  "type": "Feature",
  "properties": {
    "iso:country":"CH",
    "sg:address":"Bungertweg 4 8600 D\u00fcbendorf. Postfach",
    "sg:city":"D\u00fcbendorf",
    "sg:orig_category":"Softwareentwicklung U beratung",
    "sg:postcode":"8600",
    "sg:province":"Z\u00fcrich",
    "wof:name":"Egger Informatik",
    "wof:placetype":"venue"
},
  "geometry": {"coordinates":[8.6161565781,47.393573761],"type":"Point"}
}