{
  "type": "Feature",
  "properties": {
    "iso:country":"CH",
    "sg:address":"Obermoos 4 6301 Zug. Postfach",
    "sg:city":"Zug",
    "sg:orig_category":"Filmverleih U Videoprogrammanbieter",
    "sg:postcode":"6301",
    "sg:province":"Zug",
    "wof:name":"First Floor Film Gmbh",
    "wof:placetype":"venue"
},
  "geometry": {"coordinates":[8.5162153244,47.1715087891],"type":"Point"}
}