{
  "type": "Feature",
  "properties": {
    "addr:full":"Pestalozzistrasse 9 Kreuzlingen Thurgau 8280",
    "addr:housenumber":"9",
    "addr:postcode":"8280",
    "addr:street":"Pestalozzistrasse",
    "iso:country":"CH",
    "sg:address":"Pestalozzistrasse 9",
    "sg:city":"Kreuzlingen",
    "sg:classifiers":[
        {
            "category":"Education",
            "subcategory":"Library",
            "type":"Public Place"
        }
    ],
    "sg:phone":"+41 71 670 06 71",
    "sg:postcode":"8280",
    "sg:province":"Thurgau",
    "sg:tags":[
        "u",
        "bibliotheken",
        "archive"
    ],
    "wof:name":"Bibliothek Der Kantonsschule",
    "wof:placetype":"venue"
},
  "geometry": {"coordinates":[9.179408,47.648403],"type":"Point"}
}