{
  "type": "Feature",
  "properties": {
    "iso:country":"CH",
    "sg:address":"Bremgarterstrasse 39",
    "sg:city":"Widen",
    "sg:orig_category":"Vereine Gartenbau",
    "sg:phone":"+41 56 633 38 07",
    "sg:postcode":"8967",
    "sg:province":"Aargau",
    "wof:name":"Gartenverein Widen",
    "wof:placetype":"venue"
},
  "geometry": {"coordinates":[8.3609189987,47.3661575317],"type":"Point"}
}