{
  "type": "Feature",
  "properties": {
    "iso:country":"CH",
    "sg:address":"Baslerstrasse 122",
    "sg:city":"Trimbach",
    "sg:orig_category":"Schulpflegen",
    "sg:phone":"+41 62 289 23 00",
    "sg:postcode":"4632",
    "sg:province":"Solothurn",
    "wof:name":"Schulkommission Schulsekretariat Gemeindehaus",
    "wof:placetype":"venue"
},
  "geometry": {"coordinates":[7.8958449364,47.3630828857],"type":"Point"}
}