{
  "type": "Feature",
  "properties": {
    "iso:country":"CH",
    "sg:address":"Vorstadt 12",
    "sg:city":"Schaffhausen",
    "sg:classifiers":[
        {
            "category":"Insurance",
            "subcategory":"Insurance Agent",
            "type":"Services"
        }
    ],
    "sg:phone":"+41 17260447",
    "sg:postcode":"8200",
    "sg:province":"Schaffhausen",
    "sg:tags":[
        "versicherungsagenturen",
        "-broker"
    ],
    "wof:name":"Schaniel Gmbh Versicherungsberatung",
    "wof:placetype":"venue"
},
  "geometry": {"coordinates":[8.5846643448,47.2603530884],"type":"Point"}
}