{
  "type": "Feature",
  "properties": {
    "iso:country":"CH",
    "sg:address":"Hertizentrum 10 6300 Zug. Postfach 3226",
    "sg:city":"Zug",
    "sg:orig_category":"RESTAURANTS: TEA-ROOMS",
    "sg:phone":"+41 41 711 47 77",
    "sg:postcode":"6303",
    "sg:province":"Zug",
    "wof:name":"Sandi Gastro Gmbh",
    "wof:placetype":"venue"
},
  "geometry": {"coordinates":[8.505613327,47.1769218445],"type":"Point"}
}