{
  "type": "Feature",
  "properties": {
    "addr:full":"Schwamendingenstrasse 54 Z\u00fcrich Z\u00fcrich 8050",
    "addr:housenumber":"54",
    "addr:postcode":"8050",
    "addr:street":"Schwamendingenstrasse",
    "iso:country":"CH",
    "sg:address":"Schwamendingenstrasse 54",
    "sg:city":"Z\u00fcrich",
    "sg:orig_category":"B\u00e4ckereien Konditoreien",
    "sg:phone":"+41 13118275",
    "sg:postcode":"8050",
    "sg:province":"Z\u00fcrich",
    "wof:name":"Josef Schreiner B\u00e4ckerei-konditorei",
    "wof:placetype":"venue"
},
  "geometry": {"coordinates":[8.551208,47.40657],"type":"Point"}
}