{
  "type": "Feature",
  "properties": {
    "iso:country":"CH",
    "sg:address":"6015 Reussb\u00fchl. Postfach",
    "sg:city":"Reussb\u00fchl",
    "sg:orig_category":"Sportvereine Turnen",
    "sg:phone":"+41 41 260 11 64",
    "sg:postcode":"6015",
    "sg:province":"Luzern",
    "wof:name":"Turnverein Etv Reussb\u00fchl",
    "wof:placetype":"venue"
},
  "geometry": {"coordinates":[8.2813596725,47.0650215149],"type":"Point"}
}