{
  "type": "Feature",
  "properties": {
    "iso:country":"CH",
    "sg:address":"Pictet-de-rochemont Av. 7 1207 Gen\u00e8ve. Postfach",
    "sg:city":"Gen\u00e8ve",
    "sg:orig_category":"Wirtschaftspr\u00fcfung, Steuerberatung U Treuhand",
    "sg:postcode":"1207",
    "sg:province":"Gen\u00e8ve",
    "wof:name":"Comins Sarl",
    "wof:placetype":"venue"
},
  "geometry": {"coordinates":[6.1577029228,46.2023925781],"type":"Point"}
}