{
  "type": "Feature",
  "properties": {
    "iso:country":"CH",
    "sg:address":"Klosbachstrasse 134",
    "sg:city":"Z\u00fcrich",
    "sg:orig_category":"Non-Classified Establishments",
    "sg:postcode":"8032",
    "sg:province":"Z\u00fcrich",
    "wof:name":"Katina Amstad Naturheilpraxis",
    "wof:placetype":"venue"
},
  "geometry": {"coordinates":[8.5631065369,47.3690261841],"type":"Point"}
}