{
  "type": "Feature",
  "properties": {
    "iso:country":"CH",
    "sg:address":"Parkweg 10 4144 Arlesheim. Postfach",
    "sg:city":"Arlesheim",
    "sg:orig_category":"Sportvereine Turnen",
    "sg:phone":"+41 61 702 20 37",
    "sg:postcode":"4144",
    "sg:province":"Basel-Landschaft",
    "wof:name":"Turnverein Stv Arlesheim",
    "wof:placetype":"venue"
},
  "geometry": {"coordinates":[7.6156702042,47.4894523621],"type":"Point"}
}