{
  "type": "Feature",
  "properties": {
    "iso:country":"CH",
    "sg:address":"Oskar - Pirlo Str. 5",
    "sg:city":"Kufstein",
    "sg:orig_category":"Dienstleistungen, Telekommunikation",
    "sg:phone":"+41 436763135934",
    "sg:postcode":"6330",
    "sg:province":"Zug",
    "wof:name":"Billiger Telefonieren - Online Tarifvergleich",
    "wof:placetype":"venue"
},
  "geometry": {"coordinates":[12.172359,47.587093],"type":"Point"}
}