{
  "type": "Feature",
  "properties": {
    "iso:country":"CH",
    "sg:address":"Alte Landstrasse 16",
    "sg:city":"Fischbach-g\u00f6slikon",
    "sg:orig_category":"Giessereiindustrie Herstellung von Metallerzeugnissen ohne Maschinenbau",
    "sg:phone":"+41 56 622 64 74",
    "sg:postcode":"5525",
    "sg:province":"Aargau",
    "wof:name":"Kurt Stutz Giesserei",
    "wof:placetype":"venue"
},
  "geometry": {"coordinates":[8.309671402,47.3707618713],"type":"Point"}
}