{
  "type": "Feature",
  "properties": {
    "iso:country":"CH",
    "sg:address":"Unterdorf. 7220 Schiers. Postfach",
    "sg:city":"Schiers",
    "sg:orig_category":"Maler U Glasergewerbe",
    "sg:phone":"+41 81 328 14 44",
    "sg:postcode":"7220",
    "sg:province":"Graubunden",
    "wof:name":"Widmaier W.",
    "wof:placetype":"venue"
},
  "geometry": {"coordinates":[9.6860246658,46.9698753357],"type":"Point"}
}