{
  "type": "Feature",
  "properties": {
    "iso:country":"CH",
    "sg:address":"Bilchenstrasse 5a",
    "sg:city":"Amriswil",
    "sg:orig_category":"Grosshandel mit keramischen Erzeugnissen,Glaswaren U Tapeten Grosshandel mit sonstigen Gebrauchs U V",
    "sg:phone":"+41 71 411 59 11",
    "sg:postcode":"8580",
    "sg:province":"Thurgau",
    "wof:name":"M & A Angehrn Gmbh",
    "wof:placetype":"venue"
},
  "geometry": {"coordinates":[9.3113822937,47.5385665894],"type":"Point"}
}