{
  "type": "Feature",
  "properties": {
    "iso:country":"CH",
    "sg:address":"Buochserstrasse 24b",
    "sg:city":"Ennetb\u00fcrgen",
    "sg:orig_category":"Einzelhandel mit Automobilteilen U Zubeh\u00f6r Instandhaltung U Reparatur von Automobilen",
    "sg:phone":"+41 41 620 27 07",
    "sg:postcode":"6373",
    "sg:province":"Nidwalden",
    "wof:name":"M & L Automusig",
    "wof:placetype":"venue"
},
  "geometry": {"coordinates":[8.4133615494,46.981464386],"type":"Point"}
}