{
  "type": "Feature",
  "properties": {
    "iso:country":"CH",
    "sg:address":"Rotzlochstrasse 6370 Stans. Postfach 139",
    "sg:city":"Stans",
    "sg:orig_category":"Druckweiterverarbeitung",
    "sg:phone":"+41 41 870 27 93",
    "sg:postcode":"6371",
    "sg:province":"Nidwalden",
    "wof:name":"B\u00e4r Offset Ag",
    "wof:placetype":"venue"
},
  "geometry": {"coordinates":[8.6480197906,46.8739624023],"type":"Point"}
}