{
  "type": "Feature",
  "properties": {
    "iso:country":"CH",
    "sg:address":"Baselstrasse 61",
    "sg:city":"Luzern",
    "sg:orig_category":"Berufsbildende weiterf\u00fchrende Schulen",
    "sg:phone":"+41 41 249 98 40",
    "sg:postcode":"6003",
    "sg:province":"Luzern",
    "wof:name":"Verein Ausbildungsst\u00e4tte Sanit\u00e4r Und Spenglerei Luzern",
    "wof:placetype":"venue"
},
  "geometry": {"coordinates":[8.29277,47.053177],"type":"Point"}
}