{
  "type": "Feature",
  "properties": {
    "iso:country":"CH",
    "sg:address":"Cassarinetta Via 10",
    "sg:city":"Lugano",
    "sg:orig_category":"Vermietung U Verpachtung von eigenen Immobilien",
    "sg:postcode":"6900",
    "sg:province":"Ticino",
    "wof:name":"Enfa Sa",
    "wof:placetype":"venue"
},
  "geometry": {"coordinates":[8.9564027786,46.0299224854],"type":"Point"}
}