{
  "type": "Feature",
  "properties": {
    "addr:full":"Pl. H\u00f4tel-de-ville 5 Chaux De Fonds Neuch\u00e2tel 2300",
    "addr:housenumber":"5",
    "addr:postcode":"2300",
    "addr:street":"Pl. Ho\u0302Tel-De-Ville;Chaux De Fonds Neucha\u0302Tel",
    "iso:country":"CH",
    "sg:address":"Pl. H\u00f4tel-de-ville 5",
    "sg:city":"Chaux De Fonds",
    "sg:classifiers":[
        {
            "category":"Banks & Credit Unions",
            "subcategory":"Bank",
            "type":"Services"
        }
    ],
    "sg:phone":"+41 32 968 19 20",
    "sg:postcode":"2300",
    "sg:province":"Neuch\u00e2tel",
    "wof:name":"Raiffeisen",
    "wof:placetype":"venue"
},
  "geometry": {"coordinates":[6.832759,47.1035],"type":"Point"}
}