{
  "type": "Feature",
  "properties": {
    "iso:country":"CH",
    "sg:address":"Haus Curver Unterdorf",
    "sg:city":"Rodels",
    "sg:orig_category":"Verwaltung der Rechtspflege, Gerichte",
    "sg:phone":"+41 81 655 12 28",
    "sg:postcode":"7415",
    "sg:province":"Graubunden",
    "wof:name":"Kreisnotariat Domleschg",
    "wof:placetype":"venue"
},
  "geometry": {"coordinates":[9.4447851181,46.7353668213],"type":"Point"}
}