{
  "type": "Feature",
  "properties": {
    "iso:country":"CH",
    "sg:address":"Wiesentalstrasse 81",
    "sg:city":"Chur",
    "sg:orig_category":"Wirtschaftspr\u00fcfung, Steuerberatung U Treuhand",
    "sg:phone":"+41 81 353 31 92",
    "sg:postcode":"7000",
    "sg:province":"Graubunden",
    "wof:name":"Steuerberatung Und Treuhandb\u00fcro Keller Walter",
    "wof:placetype":"venue"
},
  "geometry": {"coordinates":[9.5305776596,46.8600463867],"type":"Point"}
}