{
  "type": "Feature",
  "properties": {
    "iso:country":"CH",
    "sg:address":"Ch\u00e2teau De Vidy",
    "sg:city":"Lausanne",
    "sg:orig_category":"Interessenvertretungen",
    "sg:postcode":"1000",
    "sg:province":"Vaud",
    "wof:name":"Fondation Ompa, Organisme De Management Pour La Promotion Des Activit\u00e9s Professionnelles Et Intellectuelles",
    "wof:placetype":"venue"
},
  "geometry": {"coordinates":[6.8206748962,46.8364982605],"type":"Point"}
}