{
  "type": "Feature",
  "properties": {
    "iso:country":"CH",
    "sg:address":"Linth-park",
    "sg:city":"Uznach",
    "sg:orig_category":"Detailhandel mit Haustieren U zoologischem Bedarf Detailhandel mit Sportartikeln",
    "sg:phone":"+41 22 823 11 15",
    "sg:postcode":"8730",
    "sg:province":"St. Gallen",
    "wof:name":"Qualipet Ag Haustierbedarfs-center",
    "wof:placetype":"venue"
},
  "geometry": {"coordinates":[6.1467480659,46.1847000122],"type":"Point"}
}