{
  "type": "Feature",
  "properties": {
    "iso:country":"CH",
    "sg:address":"J\u00e4gerstrasse 23",
    "sg:city":"Schaffhausen",
    "sg:orig_category":"Gesundheitswesen",
    "sg:phone":"+41 52 643 44 40",
    "sg:postcode":"8200",
    "sg:province":"Schaffhausen",
    "wof:name":"Rita Walt Consulting Gmbh",
    "wof:placetype":"venue"
},
  "geometry": {"coordinates":[8.6446943283,47.7173118591],"type":"Point"}
}