{
  "type": "Feature",
  "properties": {
    "iso:country":"CH",
    "sg:address":"Ringstrasse 34",
    "sg:city":"Chur",
    "sg:orig_category":"G\u00fcterbef\u00f6rderung im Strassenverkehr",
    "sg:phone":"+41 81 302 66 12",
    "sg:postcode":"7000",
    "sg:province":"Graubunden",
    "wof:name":"Komgra Komminoth",
    "wof:placetype":"venue"
},
  "geometry": {"coordinates":[9.501115799,47.0015945435],"type":"Point"}
}