{
  "type": "Feature",
  "properties": {
    "iso:country":"CH",
    "sg:address":"R\u00f6merstrasse 20 5400 Baden. Postfach",
    "sg:city":"Baden",
    "sg:orig_category":"Advokaturb\u00fcros",
    "sg:phone":"+41 56 222 89 09",
    "sg:postcode":"5401",
    "sg:province":"Aargau",
    "wof:name":"Giuseppe Dell'olivo Advokaturb\u00fcro",
    "wof:placetype":"venue"
},
  "geometry": {"coordinates":[8.310308,47.480717],"type":"Point"}
}