{
  "type": "Feature",
  "properties": {
    "iso:country":"CH",
    "sg:address":"Rue Micheli-du-crest 2",
    "sg:city":"Gen\u00e8ve",
    "sg:orig_category":"Detailhandel mit Geschenkartikeln U Souvenirs",
    "sg:phone":"+41 22 372 91 92",
    "sg:postcode":"1205",
    "sg:province":"Gen\u00e8ve",
    "wof:name":"Isabella Aliberti Boutique Brodisa Broderie",
    "wof:placetype":"venue"
},
  "geometry": {"coordinates":[6.1457538605,46.1960639954],"type":"Point"}
}