{
  "type": "Feature",
  "properties": {
    "iso:country":"CH",
    "sg:address":"Via Nasora 7",
    "sg:city":"Comano",
    "sg:orig_category":"Effektenvermittlung Broker Wirtschaftspr\u00fcfung, Steuerberatung U Treuhand",
    "sg:phone":"+41 91 942 72 10",
    "sg:postcode":"6949",
    "sg:province":"Ticino",
    "wof:name":"Amfida Sa",
    "wof:placetype":"venue"
},
  "geometry": {"coordinates":[8.9579896927,46.0333518982],"type":"Point"}
}