{
  "type": "Feature",
  "properties": {
    "iso:country":"CH",
    "sg:address":"Seestrasse 755",
    "sg:city":"Meilen",
    "sg:orig_category":"Fachdetailhandel in Verkaufsr\u00e4umen Herstellung von optischen Instrumenten",
    "sg:phone":"+41 19232400",
    "sg:postcode":"8706",
    "sg:province":"Z\u00fcrich",
    "wof:name":"Gueissaz J.",
    "wof:placetype":"venue"
},
  "geometry": {"coordinates":[8.652130127,47.2653999329],"type":"Point"}
}