{
  "type": "Feature",
  "properties": {
    "iso:country":"CH",
    "sg:address":"Franklinstrasse 7 8050 Z\u00fcrich. Postfach 9238",
    "sg:city":"Z\u00fcrich",
    "sg:orig_category":"Interessenvertretungen U sonstige Vereinigungen",
    "sg:phone":"+41 13124171",
    "sg:postcode":"8050",
    "sg:province":"Z\u00fcrich",
    "wof:name":"Z\u00fcrcher Handballverband",
    "wof:placetype":"venue"
},
  "geometry": {"coordinates":[8.5456256866,47.4088020325],"type":"Point"}
}