{
  "type": "Feature",
  "properties": {
    "iso:country":"CH",
    "sg:address":"Via Alle Vigne 22",
    "sg:city":"Gordola",
    "sg:orig_category":"Finanzierungsinstitutionen",
    "sg:postcode":"6596",
    "sg:province":"Ticino",
    "wof:name":"Rosanna Bruno",
    "wof:placetype":"venue"
},
  "geometry": {"coordinates":[8.8752145767,46.1794128418],"type":"Point"}
}