{
  "type": "Feature",
  "properties": {
    "iso:country":"CH",
    "sg:address":"Steinstrasse 75 8003 Z\u00fcrich. Postfach 9222",
    "sg:city":"Z\u00fcrich",
    "sg:orig_category":"Advokaturb\u00fcros",
    "sg:phone":"+41 14506565",
    "sg:postcode":"8036",
    "sg:province":"Z\u00fcrich",
    "wof:name":"Robert H\u00e4berli Advokaturb\u00fcro",
    "wof:placetype":"venue"
},
  "geometry": {"coordinates":[8.521623,47.365913],"type":"Point"}
}