{
  "type": "Feature",
  "properties": {
    "iso:country":"CH",
    "sg:address":"Grotweg 1",
    "sg:city":"Lengnau",
    "sg:classifiers":[
        {
            "category":"Manufacturing",
            "subcategory":"Rubber & Plastics",
            "type":"Manufacturing & Wholesale Goods"
        }
    ],
    "sg:phone":"+41 32 653 23 07",
    "sg:postcode":"2543",
    "sg:province":"Bern",
    "sg:tags":[
        "case",
        "material",
        "made"
    ],
    "wof:name":"Antaram",
    "wof:placetype":"venue"
},
  "geometry": {"coordinates":[7.375067,47.186432],"type":"Point"}
}