{
  "type": "Feature",
  "properties": {
    "iso:country":"CH",
    "sg:address":"Piazza",
    "sg:city":"Mesocco",
    "sg:orig_category":"Non-Classified Establishments",
    "sg:postcode":"6563",
    "sg:province":"Graubunden",
    "wof:name":"Albim Sa",
    "wof:placetype":"venue"
},
  "geometry": {"coordinates":[9.2328996658,46.3916320801],"type":"Point"}
}