{
  "type": "Feature",
  "properties": {
    "iso:country":"CH",
    "sg:address":"Petit-schoenberg 106",
    "sg:city":"Fribourg",
    "sg:orig_category":"Massagestudios",
    "sg:phone":"+41 26 481 20 45",
    "sg:postcode":"1700",
    "sg:province":"Fribourg",
    "wof:name":"Institut D\u00e9couvertes Massage De Sant\u00e9",
    "wof:placetype":"venue"
},
  "geometry": {"coordinates":[7.1444897652,46.8025093079],"type":"Point"}
}