{
  "type": "Feature",
  "properties": {
    "iso:country":"CH",
    "sg:address":"Chemin Des Ecureuils 3",
    "sg:city":"Pully",
    "sg:orig_category":"Hochschulen U h\u00f6here Ausbildung",
    "sg:postcode":"1009",
    "sg:province":"Vaud",
    "wof:name":"Pollen Louis.",
    "wof:placetype":"venue"
},
  "geometry": {"coordinates":[6.6641778946,46.5214691162],"type":"Point"}
}