{
  "type": "Feature",
  "properties": {
    "iso:country":"CH",
    "sg:address":"Avenir Rue De L' 23",
    "sg:city":"Del\u00e9mont",
    "sg:orig_category":"Unclassifiable Establishments",
    "sg:postcode":"2800",
    "sg:province":"Jura",
    "wof:name":"Zollikofer It Gmbh",
    "wof:placetype":"venue"
},
  "geometry": {"coordinates":[9.4146776199,47.4431686401],"type":"Point"}
}