{
  "type": "Feature",
  "properties": {
    "iso:country":"CH",
    "sg:address":"Les Ilettes",
    "sg:city":"Monthey",
    "sg:classifiers":[
        {
            "category":"Restaurant",
            "type":"Food & Drink"
        }
    ],
    "sg:phone":"+41 24 471 22 32",
    "sg:postcode":"1870",
    "sg:province":"Valais",
    "wof:name":"Pizzeria Les Ilettes",
    "wof:placetype":"venue"
},
  "geometry": {"coordinates":[6.9609351158,46.2472343445],"type":"Point"}
}