{
  "type": "Feature",
  "properties": {
    "iso:country":"CH",
    "sg:address":"Rue Du Bruide 21",
    "sg:city":"Erde",
    "sg:orig_category":"Herstellung von Teppichen",
    "sg:phone":"+41 27 346 28 34",
    "sg:postcode":"1976",
    "sg:province":"Valais",
    "wof:name":"Edmond Germanier Sa Entreprise De Parquets",
    "wof:placetype":"venue"
},
  "geometry": {"coordinates":[7.2959799767,46.2425804138],"type":"Point"}
}