{
  "type": "Feature",
  "properties": {
    "iso:country":"CH",
    "sg:address":"1957",
    "sg:city":"Ardon",
    "sg:orig_category":"Sportvereine Turnen",
    "sg:postcode":"1957",
    "sg:province":"Valais",
    "wof:name":"St\u00e9 De Gymnastique",
    "wof:placetype":"venue"
},
  "geometry": {"coordinates":[6.8579797745,46.9656105042],"type":"Point"}
}