{
  "type": "Feature",
  "properties": {
    "iso:country":"CH",
    "sg:address":"B\u00fcnishoferstrasse 295",
    "sg:city":"Feldmeilen",
    "sg:orig_category":"Primarschulen Vorschulen, Kinderg\u00e4rten",
    "sg:phone":"+41 19242070",
    "sg:postcode":"8706",
    "sg:province":"Z\u00fcrich",
    "wof:name":"Heilp\u00e4dagogischer Verein Werkheim St\u00f6ckenweid",
    "wof:placetype":"venue"
},
  "geometry": {"coordinates":[8.6268596649,47.2828102112],"type":"Point"}
}