{
  "type": "Feature",
  "properties": {
    "iso:country":"CH",
    "sg:address":"Sorengo Via 8",
    "sg:city":"Lugano",
    "sg:orig_category":"Bestattungswesen",
    "sg:phone":"+41 91 682 10 10",
    "sg:postcode":"6900",
    "sg:province":"Ticino",
    "wof:name":"Onoranze Funebri Faccoli Angela Sa",
    "wof:placetype":"venue"
},
  "geometry": {"coordinates":[8.943449,46.00515],"type":"Point"}
}