{
  "type": "Feature",
  "properties": {
    "iso:country":"CH",
    "sg:address":"Binzm\u00fchlestrasse 1",
    "sg:city":"Neerach",
    "sg:orig_category":"Forschung U Entwicklung im Bereich der Naturwissenschaften",
    "sg:postcode":"8173",
    "sg:province":"Z\u00fcrich",
    "wof:name":"Mca Technologies Kaul Dr. Chem. Bansi",
    "wof:placetype":"venue"
},
  "geometry": {"coordinates":[7.5211372375,47.5040588379],"type":"Point"}
}