{
  "type": "Feature",
  "properties": {
    "addr:full":"Hauptstrasse 3 Birsfelden Basel-Landschaft 4127",
    "addr:housenumber":"3",
    "addr:postcode":"4127",
    "addr:street":"Hauptstrasse",
    "iso:country":"CH",
    "sg:address":"Hauptstrasse 3",
    "sg:city":"Birsfelden",
    "sg:orig_category":"Arztpraxen",
    "sg:phone":"+41 61 311 39 93",
    "sg:postcode":"4127",
    "sg:province":"Basel-Landschaft",
    "wof:name":"Dr.med.christine Planta Aerztin F.allgemeine Medizin",
    "wof:placetype":"venue"
},
  "geometry": {"coordinates":[7.61822,47.555042],"type":"Point"}
}