{
  "type": "Feature",
  "properties": {
    "iso:country":"CH",
    "sg:address":"Hauptstrasse 20",
    "sg:city":"Holziken",
    "sg:orig_category":"Schlossereien",
    "sg:phone":"+41 62 721 17 47",
    "sg:postcode":"5043",
    "sg:province":"Aargau",
    "wof:name":"Daniel L\u00fcthi Schlosserei",
    "wof:placetype":"venue"
},
  "geometry": {"coordinates":[8.0398330688,47.3210372925],"type":"Point"}
}