{
  "type": "Feature",
  "properties": {
    "iso:country":"CH",
    "sg:address":"Hauptstrasse 73",
    "sg:city":"Balgach",
    "sg:classifiers":[
        {
            "category":"Professional",
            "subcategory":"Employment Agencies",
            "type":"Services"
        }
    ],
    "sg:postcode":"9436",
    "sg:province":"St. Gallen",
    "sg:tags":[
        "personal",
        "u",
        "stellenvermittlung"
    ],
    "wof:name":"Showorx Gmbh",
    "wof:placetype":"venue"
},
  "geometry": {"coordinates":[9.6001691818,47.4033966064],"type":"Point"}
}