{
  "type": "Feature",
  "properties": {
    "iso:country":"CH",
    "sg:address":"8353 Elgg. Postfach 131",
    "sg:city":"Elgg",
    "sg:orig_category":"Bau\u00e4mter",
    "sg:phone":"+41 52 364 23 23",
    "sg:postcode":"8353",
    "sg:province":"Z\u00fcrich",
    "wof:name":"Bauamt Der Gemeinde Elgg",
    "wof:placetype":"venue"
},
  "geometry": {"coordinates":[8.869225,47.490253],"type":"Point"}
}