{
  "type": "Feature",
  "properties": {
    "iso:country":"CH",
    "sg:address":"Avenue De La Gare 1 1003 Lausanne Case Postale 820",
    "sg:city":"Lausanne",
    "sg:orig_category":"Versicherungen Generalagenturen",
    "sg:phone":"+41 21 341 47 11",
    "sg:postcode":"1001",
    "sg:province":"Vaud",
    "wof:name":"Helvetia Patria Assurances Agence G\u00e9n\u00e9rale",
    "wof:placetype":"venue"
},
  "geometry": {"coordinates":[6.6372947693,46.5166702271],"type":"Point"}
}