{
  "type": "Feature",
  "properties": {
    "iso:country":"CH",
    "sg:address":"Jomini Avenue 8",
    "sg:city":"Lausanne",
    "sg:classifiers":[
        {
            "category":"Professional",
            "subcategory":"Employment Agencies",
            "type":"Services"
        }
    ],
    "sg:phone":"+41 31 350 17 17",
    "sg:postcode":"1004",
    "sg:province":"Vaud",
    "sg:tags":[
        "personal",
        "u",
        "stellenvermittlung"
    ],
    "wof:name":"A Eins Personal Ag",
    "wof:placetype":"venue"
},
  "geometry": {"coordinates":[7.4572649002,46.9592323303],"type":"Point"}
}