{
  "type": "Feature",
  "properties": {
    "iso:country":"CH",
    "sg:address":"Chesa Seraina 7512 Champf\u00e8r. Postfach",
    "sg:city":"Champf\u00e8r",
    "sg:orig_category":"Sanit\u00e4r, Heizungs U L\u00fcftungsinstallation",
    "sg:postcode":"7512",
    "sg:province":"Graubunden",
    "wof:name":"Itall, Installationen, Bedachungen, Spenglerei, Heizungsanlagen U. \u00d6lbrennerservice, Andenmatten Hans",
    "wof:placetype":"venue"
},
  "geometry": {"coordinates":[7.9573631287,46.0964317322],"type":"Point"}
}