{
  "type": "Feature",
  "properties": {
    "iso:country":"CH",
    "sg:address":"Wasserfallstrasse 60 6390 Engelberg. Postfach",
    "sg:city":"Engelberg",
    "sg:orig_category":"Maler U Glasergewerbe Malerei",
    "sg:phone":"+41 79 434 31 22",
    "sg:postcode":"6391",
    "sg:province":"Obwalden",
    "wof:name":"Gr\u00e4ni Ag",
    "wof:placetype":"venue"
},
  "geometry": {"coordinates":[8.4173707962,46.8132362366],"type":"Point"}
}