{
  "type": "Feature",
  "properties": {
    "iso:country":"CH",
    "sg:address":"S\u00e4listrasse 61 4601 Olten. Postfach",
    "sg:city":"Olten",
    "sg:orig_category":"Handel mit Motorr\u00e4dern, Teilen U Zubeh\u00f6r Handelsvermittlung U Grosshandel mit Automobilteilen U Zube",
    "sg:phone":"+41 62 296 81 81",
    "sg:postcode":"4601",
    "sg:province":"Solothurn",
    "wof:name":"Arnold & Partner Parkier-& Bedachungssysteme",
    "wof:placetype":"venue"
},
  "geometry": {"coordinates":[7.9081048965,47.3460998535],"type":"Point"}
}