{
  "type": "Feature",
  "properties": {
    "iso:country":"CH",
    "sg:address":"Neuwiesenstrasse 15 8400 Winterthur. Postfach Postfach",
    "sg:city":"Winterthur",
    "sg:orig_category":"Datenverarbeitungsdienste Softwareentwicklung U beratung",
    "sg:phone":"+41 52 202 52 70",
    "sg:postcode":"8401",
    "sg:province":"Z\u00fcrich",
    "wof:name":"Apnet Altitoro & Pavic",
    "wof:placetype":"venue"
},
  "geometry": {"coordinates":[8.718534,47.499786],"type":"Point"}
}