{
  "type": "Feature",
  "properties": {
    "iso:country":"CH",
    "sg:address":"D\u00e4hlenstrasse 33",
    "sg:city":"Grenchen",
    "sg:orig_category":"Herstellung von Mess U Kontrollinstrumenten U vorrichtungen",
    "sg:postcode":"2540",
    "sg:province":"Solothurn",
    "wof:name":"Tecno Graf Ag",
    "wof:placetype":"venue"
},
  "geometry": {"coordinates":[7.3855051994,47.1934623718],"type":"Point"}
}