{
  "type": "Feature",
  "properties": {
    "iso:country":"CH",
    "sg:address":"4497",
    "sg:city":"R\u00fcnenberg",
    "sg:orig_category":"Primarschulen",
    "sg:postcode":"4497",
    "sg:province":"Basel-Landschaft",
    "wof:name":"Primarschule",
    "wof:placetype":"venue"
},
  "geometry": {"coordinates":[7.8806300163,47.4319610596],"type":"Point"}
}