{
  "type": "Feature",
  "properties": {
    "iso:country":"CH",
    "sg:address":"Hauptstrasse 35",
    "sg:city":"Pfyn",
    "sg:orig_category":"Landesverteidigung, Sozialversicherung \u00d6ffentliche Verwaltung",
    "sg:phone":"+41 52 765 29 29",
    "sg:postcode":"8505",
    "sg:province":"Thurgau",
    "wof:name":"Zivilschutzstelle Pfyn",
    "wof:placetype":"venue"
},
  "geometry": {"coordinates":[8.9561872482,47.5963745117],"type":"Point"}
}