{
  "type": "Feature",
  "properties": {
    "iso:country":"CH",
    "sg:address":"Binzenstrasse 2",
    "sg:city":"Gockhausen",
    "sg:orig_category":"Erbringung von Dienstleistungen f\u00fcr Unternehmen",
    "sg:phone":"+41 18202871",
    "sg:postcode":"8044",
    "sg:province":"Z\u00fcrich",
    "wof:name":"Atelier H\u00e4nni Stefan",
    "wof:placetype":"venue"
},
  "geometry": {"coordinates":[8.5981626511,47.3850059509],"type":"Point"}
}