{
  "type": "Feature",
  "properties": {
    "addr:full":"Grindelwald Bern 3818",
    "addr:postcode":"3818",
    "iso:country":"CH",
    "sg:city":"Grindelwald",
    "sg:orig_category":"Immobilien U Baugewerbe, Immobilienmarkt U Kleinanzeigen",
    "sg:phone":"+41 33 853 45 00",
    "sg:postcode":"3818",
    "sg:province":"Bern",
    "wof:name":"Griwaplan Ag",
    "wof:placetype":"venue"
},
  "geometry": {"coordinates":[8.034633,46.624371],"type":"Point"}
}