{
  "type": "Feature",
  "properties": {
    "iso:country":"CH",
    "sg:address":"Obere Br\u00fchlstrasse 4 4800 Zofingen. Postfach 770",
    "sg:city":"Zofingen",
    "sg:orig_category":"Herstellung von elektrischen Haushaltsger\u00e4ten Sanit\u00e4r, Heizungs U L\u00fcftungsinstallation",
    "sg:phone":"+41 62 745 30 30",
    "sg:postcode":"4800",
    "sg:province":"Aargau",
    "wof:name":"Lehmann 2000 Ag",
    "wof:placetype":"venue"
},
  "geometry": {"coordinates":[7.944021225,47.284538269],"type":"Point"}
}