{
  "type": "Feature",
  "properties": {
    "iso:country":"CH",
    "sg:address":"Jomen",
    "sg:city":"Gstaad",
    "sg:orig_category":"G\u00fcterbef\u00f6rderung im Strassenverkehr",
    "sg:phone":"+41 33 744 56 00",
    "sg:postcode":"3780",
    "sg:province":"Bern",
    "wof:name":"Sollberger & Sohn Transporte",
    "wof:placetype":"venue"
},
  "geometry": {"coordinates":[7.2929821014,46.4719276428],"type":"Point"}
}