{
  "type": "Feature",
  "properties": {
    "iso:country":"CH",
    "sg:address":"B\u00fcgl Da La Nina 19",
    "sg:city":"Samedan",
    "sg:orig_category":"Pensionen mit Restaurant",
    "sg:phone":"+41 81 852 52 22",
    "sg:postcode":"7503",
    "sg:province":"Graubunden",
    "wof:name":"Pension Giardin",
    "wof:placetype":"venue"
},
  "geometry": {"coordinates":[9.8687963486,46.5337524414],"type":"Point"}
}