{
  "type": "Feature",
  "properties": {
    "iso:country":"CH",
    "sg:address":"Via Rondonico 2",
    "sg:city":"Ascona",
    "sg:orig_category":"Wirtschaftspr\u00fcfung, Steuerberatung U Treuhand",
    "sg:phone":"+41 91 791 63 43",
    "sg:postcode":"6612",
    "sg:province":"Ticino",
    "wof:name":"Ris Urs R.",
    "wof:placetype":"venue"
},
  "geometry": {"coordinates":[8.7685031891,46.1564292908],"type":"Point"}
}