{
  "type": "Feature",
  "properties": {
    "addr:full":"Wintersingerstrasse 23 4312 Magden. Postfach 33 Magden Aargau 4312",
    "addr:housenumber":"23;33",
    "addr:postcode":"4312 magden.;4312",
    "addr:street":"Wintersingerstrasse;Postfach",
    "iso:country":"CH",
    "sg:address":"Wintersingerstrasse 23 4312 Magden. Postfach 33",
    "sg:city":"Magden",
    "sg:orig_category":"Architektur U Ingenieurb\u00fcros",
    "sg:phone":"+41 61 841 17 04",
    "sg:postcode":"4312",
    "sg:province":"Aargau",
    "wof:name":"Max Kaiser Technisches B\u00fcro",
    "wof:placetype":"venue"
},
  "geometry": {"coordinates":[7.814423,47.524471],"type":"Point"}
}