{
  "type": "Feature",
  "properties": {
    "iso:country":"CH",
    "sg:address":"Baumackerstrasse 24",
    "sg:city":"Z\u00fcrich",
    "sg:orig_category":"Event Agenturen Public-Relations-Agenturen",
    "sg:phone":"+41 13130805",
    "sg:postcode":"8050",
    "sg:province":"Z\u00fcrich",
    "wof:name":"Gian Andreossi Pga Presseb\u00fcro",
    "wof:placetype":"venue"
},
  "geometry": {"coordinates":[8.5448379517,47.4087257385],"type":"Point"}
}