{
  "type": "Feature",
  "properties": {
    "iso:country":"CH",
    "sg:address":"Chemin De Bourgogne 21",
    "sg:city":"Nyon",
    "sg:orig_category":"Dienstleistungen von Beteiligungsgesellschaften",
    "sg:phone":"+41 22 361 07 21",
    "sg:postcode":"1260",
    "sg:province":"Vaud",
    "wof:name":"Nypah Sa",
    "wof:placetype":"venue"
},
  "geometry": {"coordinates":[6.2266511917,46.3934135437],"type":"Point"}
}