{
  "type": "Feature",
  "properties": {
    "iso:country":"CH",
    "sg:address":"Hartbertstrasse 111 7000 Chur. Postfach",
    "sg:city":"Chur",
    "sg:orig_category":"Schiffsbau ohne Boots U Yachtbau",
    "sg:postcode":"7000",
    "sg:province":"Graubunden",
    "wof:name":"Oceana Shipping Ag",
    "wof:placetype":"venue"
},
  "geometry": {"coordinates":[9.5321674347,46.8541297913],"type":"Point"}
}