{
  "type": "Feature",
  "properties": {
    "iso:country":"CH",
    "sg:address":"6516",
    "sg:city":"Cugnasco",
    "sg:orig_category":"Grosshandel mit Holz U Bauelementen aus Holz Grosshandel mit Holz U Baustoffen",
    "sg:phone":"+41 91 859 23 58",
    "sg:postcode":"6516",
    "sg:province":"Ticino",
    "wof:name":"Nicoli Santo",
    "wof:placetype":"venue"
},
  "geometry": {"coordinates":[8.9177398682,46.1752510071],"type":"Point"}
}