{
  "type": "Feature",
  "properties": {
    "iso:country":"CH",
    "sg:address":"Gotthardstrasse 126 4054 Basel. Postfach",
    "sg:city":"Basel",
    "sg:orig_category":"Fachdetailhandel mit pharmazeutischen Produkten",
    "sg:phone":"+41 61 301 40 53",
    "sg:postcode":"4027",
    "wof:name":"Victoria-apotheke",
    "wof:placetype":"venue"
},
  "geometry": {"coordinates":[7.5615649223,47.5514144897],"type":"Point"}
}