{
  "type": "Feature",
  "properties": {
    "iso:country":"CH",
    "sg:address":"Obere Matt 39 8713 Uerikon. Postfach",
    "sg:city":"Uerikon",
    "sg:orig_category":"Fotografisches Gewerbe U fotografische Laboratorien",
    "sg:postcode":"8713",
    "sg:province":"Z\u00fcrich",
    "wof:name":"Hasler Landschaftsfoto Landschaftsfotos \u00fcbers Internet; Erstellen, Vertrieb",
    "wof:placetype":"venue"
},
  "geometry": {"coordinates":[8.7607803345,47.2373886108],"type":"Point"}
}