{
  "type": "Feature",
  "properties": {
    "iso:country":"CH",
    "sg:address":"Murtenstrasse 25 3186 D\u00fcdingen. Postfach 251",
    "sg:city":"D\u00fcdingen",
    "sg:orig_category":"Herstellung von Erzeugnissen aus Beton, Gips U Zement Herstellung von Zement",
    "sg:phone":"+41 26 492 94 50",
    "sg:postcode":"3186",
    "sg:province":"Fribourg",
    "wof:name":"Cewag D\u00fcdingen",
    "wof:placetype":"venue"
},
  "geometry": {"coordinates":[7.1983089447,46.8562889099],"type":"Point"}
}