{
  "type": "Feature",
  "properties": {
    "iso:country":"CH",
    "sg:address":"Baselstrasse 17",
    "sg:city":"Dagmersellen",
    "sg:orig_category":"Vereine Musik/Blasmusik",
    "sg:phone":"+41 62 756 34 76",
    "sg:postcode":"6252",
    "sg:province":"Luzern",
    "wof:name":"Musikgesellschaft Dagmersellen",
    "wof:placetype":"venue"
},
  "geometry": {"coordinates":[7.9870209694,47.214099884],"type":"Point"}
}