{
  "type": "Feature",
  "properties": {
    "iso:country":"CH",
    "sg:address":"Regensbergstrasse 242 8050 Z\u00fcrich. Postfach 9118",
    "sg:city":"Z\u00fcrich",
    "sg:orig_category":"Grosshandel mit M\u00f6beln, Wohnbedarf, Teppichen U Bodenbel\u00e4gen Herstellung von konfektionierten Textil",
    "sg:phone":"+41 13125900",
    "sg:postcode":"8050",
    "sg:province":"Z\u00fcrich",
    "wof:name":"Tebo Teppich Bock Ag",
    "wof:placetype":"venue"
},
  "geometry": {"coordinates":[8.530459404,47.4109725952],"type":"Point"}
}