{
  "type": "Feature",
  "properties": {
    "iso:country":"CH",
    "sg:address":"Chemin Des Hauts-cr\u00eats 35",
    "sg:city":"Cologny",
    "sg:orig_category":"Unternehmensberatung",
    "sg:postcode":"1223",
    "sg:province":"Gen\u00e8ve",
    "wof:name":"Copex, Le Luc B.",
    "wof:placetype":"venue"
},
  "geometry": {"coordinates":[6.1853671074,46.2157287598],"type":"Point"}
}