{
  "type": "Feature",
  "properties": {
    "iso:country":"CH",
    "sg:address":"Aarauerstrasse 7",
    "sg:city":"Lenzburg",
    "sg:orig_category":"Fernmeldedienste",
    "sg:phone":"+41 62 891 55 66",
    "sg:postcode":"5600",
    "sg:province":"Aargau",
    "wof:name":"Seicom Ag",
    "wof:placetype":"venue"
},
  "geometry": {"coordinates":[8.1721334457,47.386806488],"type":"Point"}
}