{
  "type": "Feature",
  "properties": {
    "iso:country":"CH",
    "sg:address":"Hauptstrasse 35",
    "sg:city":"Oberkulm",
    "sg:orig_category":"Instandhaltung U Reparatur von Automobilen",
    "sg:phone":"+41 71 944 10 28",
    "sg:postcode":"5727",
    "sg:province":"Aargau",
    "wof:name":"Elite Garage Zuzwil Ag",
    "wof:placetype":"venue"
},
  "geometry": {"coordinates":[9.1129798889,47.4723396301],"type":"Point"}
}