{
  "type": "Feature",
  "properties": {
    "iso:country":"CH",
    "sg:address":"Weinbergstrasse 47 5035 Unterentfelden. Postfach",
    "sg:city":"Unterentfelden",
    "sg:orig_category":"Interessenvertretungen",
    "sg:postcode":"5035",
    "sg:province":"Aargau",
    "wof:name":"The European Higher Engineering And Technical Professionals Association (eureta)",
    "wof:placetype":"venue"
},
  "geometry": {"coordinates":[8.0446243286,47.3672866821],"type":"Point"}
}