{
  "type": "Feature",
  "properties": {
    "iso:country":"CH",
    "sg:address":"Unterfeldstrasse 10",
    "sg:city":"Koblenz",
    "sg:orig_category":"Instandhaltung U Reparatur von Automobilen",
    "sg:postcode":"5322",
    "sg:province":"Aargau",
    "wof:name":"Carrosserie Tornamb\u00e9 P. Carrosseriespenglerei",
    "wof:placetype":"venue"
},
  "geometry": {"coordinates":[8.4652328491,47.4485778809],"type":"Point"}
}