{
  "type": "Feature",
  "properties": {
    "iso:country":"CH",
    "sg:address":"Orbe Rue D' 68",
    "sg:city":"Yverdon-les-bains",
    "sg:orig_category":"Unclassifiable Establishments",
    "sg:phone":"+41 24 425 69 52",
    "sg:postcode":"1400",
    "sg:province":"Vaud",
    "wof:name":"Nicola De Petra",
    "wof:placetype":"venue"
},
  "geometry": {"coordinates":[6.6289792061,46.7540664673],"type":"Point"}
}