{
  "type": "Feature",
  "properties": {
    "iso:country":"CH",
    "sg:address":"Marktgasse 46a",
    "sg:city":"Langenthal",
    "sg:orig_category":"Grosshandel mit Wein U Spirituosen Wein Detailhandel",
    "sg:phone":"+41 62 923 39 49",
    "sg:postcode":"4900",
    "sg:province":"Bern",
    "wof:name":"Eric Vuithier Terre & Vigne",
    "wof:placetype":"venue"
},
  "geometry": {"coordinates":[7.7880511284,47.2106666565],"type":"Point"}
}