{
  "type": "Feature",
  "properties": {
    "iso:country":"CH",
    "sg:address":"Hagenholzstrasse 70",
    "sg:city":"Z\u00fcrich",
    "sg:orig_category":"Grosshandel mit sonstigen Halbwaren",
    "sg:phone":"+41 56 633 74 18",
    "sg:postcode":"8050",
    "sg:province":"Z\u00fcrich",
    "wof:name":"Erme Ag Gebr.meyer",
    "wof:placetype":"venue"
},
  "geometry": {"coordinates":[8.3694620132,47.3625411987],"type":"Point"}
}