{
  "type": "Feature",
  "properties": {
    "iso:country":"CH",
    "sg:address":"Jurastrasse 92",
    "sg:city":"Bettlach",
    "sg:orig_category":"Politische Parteien FDP",
    "sg:phone":"+41 32 627 25 41",
    "sg:postcode":"2544",
    "sg:province":"Solothurn",
    "wof:name":"Fdp Ortspartei Bettlach",
    "wof:placetype":"venue"
},
  "geometry": {"coordinates":[7.4097747803,47.2002944946],"type":"Point"}
}