{
  "type": "Feature",
  "properties": {
    "iso:country":"CH",
    "sg:address":"Via Vallemaggia 71.",
    "sg:city":"Locarno",
    "sg:orig_category":"Interessenvertretungen",
    "sg:postcode":"6600",
    "sg:province":"Ticino",
    "wof:name":"Eneide 80.",
    "wof:placetype":"venue"
},
  "geometry": {"coordinates":[8.7891702652,46.169719696],"type":"Point"}
}