{
  "type": "Feature",
  "properties": {
    "iso:country":"CH",
    "sg:address":"Rue Du Vieux-moulin 9",
    "sg:city":"Onex",
    "sg:orig_category":"Betrieb von Taxis",
    "sg:phone":"+41 22 792 45 03",
    "sg:postcode":"1213",
    "sg:province":"Gen\u00e8ve",
    "wof:name":"Roger Borgeaud Taxis",
    "wof:placetype":"venue"
},
  "geometry": {"coordinates":[6.099493,46.188927],"type":"Point"}
}