{
  "type": "Feature",
  "properties": {
    "iso:country":"CH",
    "sg:address":"Rue De La Gare 12 B",
    "sg:city":"Bevaix",
    "sg:orig_category":"Elektroinstallation",
    "sg:phone":"+41 32 846 12 76",
    "sg:postcode":"2022",
    "sg:province":"Neuch\u00e2tel",
    "wof:name":"Cl\u00e9ment Fivaz Installation \u00e9lectrique",
    "wof:placetype":"venue"
},
  "geometry": {"coordinates":[6.8124961853,46.9299736023],"type":"Point"}
}