{
  "type": "Feature",
  "properties": {
    "iso:country":"CH",
    "sg:address":"Grand-rue 60",
    "sg:city":"Tavannes",
    "sg:orig_category":"Tankstellen",
    "sg:postcode":"2710",
    "sg:province":"Bern",
    "wof:name":"Criblez-de Cola Anna-marie Mme",
    "wof:placetype":"venue"
},
  "geometry": {"coordinates":[7.2036008835,47.223487854],"type":"Point"}
}