{
  "type": "Feature",
  "properties": {
    "iso:country":"CH",
    "sg:address":"Friedhofweg 4a",
    "sg:city":"Jegenstorf",
    "sg:orig_category":"Detailhandel mit Geschenkartikeln U Souvenirs",
    "sg:phone":"+41 31 761 38 58",
    "sg:postcode":"3303",
    "sg:province":"Bern",
    "wof:name":"Boutique New 4 You First & Secondhand",
    "wof:placetype":"venue"
},
  "geometry": {"coordinates":[7.5119009018,47.0529747009],"type":"Point"}
}