{
  "type": "Feature",
  "properties": {
    "iso:country":"CH",
    "sg:address":"Hauptstrasse 137 4313 M\u00f6hlin. Postfach",
    "sg:city":"M\u00f6hlin",
    "sg:orig_category":"Sanit\u00e4r, Heizungs U L\u00fcftungsinstallation",
    "sg:postcode":"4313",
    "sg:province":"Aargau",
    "wof:name":"Schlatter G. Gmbh Sanit\u00e4r-installationen, Spenglerei, Flachdach; Planungen, Arbeiten",
    "wof:placetype":"venue"
},
  "geometry": {"coordinates":[7.8515591621,47.5534095764],"type":"Point"}
}