{
  "type": "Feature",
  "properties": {
    "iso:country":"CH",
    "sg:address":"Hotel Grichting + Badnerhof",
    "sg:city":"Leukerbad",
    "sg:orig_category":"Unclassifiable Establishments",
    "sg:postcode":"3954",
    "sg:province":"Valais",
    "wof:name":"Bauer-grichting Und Co.",
    "wof:placetype":"venue"
},
  "geometry": {"coordinates":[7.6253261566,46.3759307861],"type":"Point"}
}