{
  "type": "Feature",
  "properties": {
    "iso:country":"CH",
    "sg:address":"Flossenmatt 11",
    "sg:city":"Meggen",
    "sg:orig_category":"Sportvereine Ballsport Tischtennis",
    "sg:phone":"+41 41 377 53 69",
    "sg:postcode":"6045",
    "sg:province":"Luzern",
    "wof:name":"Ttc Rapid Luzern",
    "wof:placetype":"venue"
},
  "geometry": {"coordinates":[8.3608837128,47.0441017151],"type":"Point"}
}