{
  "type": "Feature",
  "properties": {
    "iso:country":"CH",
    "sg:address":"Talackerstrasse 8152 Glattbrugg. Postfach",
    "sg:city":"Z\u00fcrich",
    "sg:orig_category":"Grosshandel mit sonstigen Konsumg\u00fctern",
    "sg:phone":"+41 18292877",
    "sg:postcode":"8065",
    "sg:province":"Z\u00fcrich",
    "wof:name":"Peter B\u00fchrer Textilagentur",
    "wof:placetype":"venue"
},
  "geometry": {"coordinates":[8.5654697418,47.430141449],"type":"Point"}
}