{
  "type": "Feature",
  "properties": {
    "iso:country":"CH",
    "sg:address":"Pulverturm",
    "sg:city":"Zofingen",
    "sg:orig_category":"Sportvereine Sch\u00fctzen",
    "sg:phone":"+41 62 751 76 00",
    "sg:postcode":"4800",
    "sg:province":"Aargau",
    "wof:name":"Artillerieverein Zofingen",
    "wof:placetype":"venue"
},
  "geometry": {"coordinates":[7.9463100433,47.2886199951],"type":"Point"}
}