{
  "type": "Feature",
  "properties": {
    "iso:country":"CH",
    "sg:address":"Dammstrasse 11",
    "sg:city":"Hochdorf",
    "sg:orig_category":"Architektur U Ingenieurb\u00fcros Architekturb\u00fcros",
    "sg:postcode":"6280",
    "sg:province":"Luzern",
    "wof:name":"Sigrist Und Partner Architekten Gmbh",
    "wof:placetype":"venue"
},
  "geometry": {"coordinates":[8.291778,47.164982],"type":"Point"}
}