{
  "type": "Feature",
  "properties": {
    "iso:country":"CH",
    "sg:address":"Talbachstrasse 9",
    "sg:city":"Altendorf",
    "sg:orig_category":"Instandhaltung U Reparatur von Automobilen",
    "sg:phone":"+41 55 462 27 27",
    "sg:postcode":"8852",
    "sg:province":"Schwyz",
    "wof:name":"Senn Peter Ag",
    "wof:placetype":"venue"
},
  "geometry": {"coordinates":[8.8088560104,47.1987991333],"type":"Point"}
}