{
  "type": "Feature",
  "properties": {
    "iso:country":"CH",
    "sg:address":"Bahnstrasse 80",
    "sg:city":"Bern",
    "sg:orig_category":"Erschliessung von Grundst\u00fccken",
    "sg:postcode":"3008",
    "sg:province":"Bern",
    "wof:name":"Baugenossenschaft Signal Bern",
    "wof:placetype":"venue"
},
  "geometry": {"coordinates":[7.4080071449,46.9443359375],"type":"Point"}
}