{
  "type": "Feature",
  "properties": {
    "iso:country":"CH",
    "sg:address":"Route De Praz-v\u00e9guey 14",
    "sg:city":"Chavannes-renens",
    "sg:classifiers":[
        {
            "category":"Government",
            "subcategory":"Post Office",
            "type":"Public Place"
        }
    ],
    "sg:phone":"+41 21 691 40 55",
    "sg:postcode":"1022",
    "sg:province":"Vaud",
    "sg:tags":[
        "caf\u00e9s",
        "tea-rooms"
    ],
    "wof:name":"Tea-room Le Dauphin",
    "wof:placetype":"venue"
},
  "geometry": {"coordinates":[6.5731511116,46.5264587402],"type":"Point"}
}