{
  "type": "Feature",
  "properties": {
    "iso:country":"CH",
    "sg:address":"Bundesplatz 2",
    "sg:city":"Zug",
    "sg:orig_category":"Grosshandel mit Nahrungsmitteln, Getr\u00e4nken U Tabakwaren",
    "sg:phone":"+41 41 710 19 30",
    "sg:postcode":"6300",
    "sg:province":"Zug",
    "wof:name":"Foodwell Vertiebs Gmbh",
    "wof:placetype":"venue"
},
  "geometry": {"coordinates":[8.5155563354,47.171333313],"type":"Point"}
}