{
  "type": "Feature",
  "properties": {
    "iso:country":"CH",
    "sg:address":"Landsgemeindeplatz 3 9050 Appenzell. Postfach",
    "sg:city":"Appenzell",
    "sg:classifiers":[
        {
            "category":"Travel",
            "subcategory":"Hotels & Motels",
            "type":"Entertainment"
        }
    ],
    "sg:postcode":"9050",
    "sg:province":"Appenzell Innerhoden",
    "sg:tags":[
        "hotels",
        "mit",
        "restaurant"
    ],
    "wof:name":"Hotel S\u00e4ntis Filadoro Basilio",
    "wof:placetype":"venue"
},
  "geometry": {"coordinates":[9.3942890167,47.3917427063],"type":"Point"}
}