{
  "type": "Feature",
  "properties": {
    "iso:country":"CH",
    "sg:address":"Ochsengasse 29",
    "sg:city":"Basel",
    "sg:orig_category":"Grosshandel mit Sportartikeln",
    "sg:phone":"+41 61 281 74 84",
    "sg:postcode":"4058",
    "sg:province":"Basel-Stadt",
    "wof:name":"Jumbo, D. Stalder Waren Usw; Handel",
    "wof:placetype":"venue"
},
  "geometry": {"coordinates":[7.5913009644,47.5620117188],"type":"Point"}
}