{
  "type": "Feature",
  "properties": {
    "iso:country":"CH",
    "sg:address":"Ausserbergstrasse 2",
    "sg:city":"Oensingen",
    "sg:orig_category":"Haltung von Rindern",
    "sg:postcode":"4702",
    "sg:province":"Solothurn",
    "wof:name":"Viehzuchtgenossenschaft Oensingen",
    "wof:placetype":"venue"
},
  "geometry": {"coordinates":[7.7264499664,47.2915916443],"type":"Point"}
}