{
  "type": "Feature",
  "properties": {
    "iso:country":"CH",
    "sg:address":"Spiss",
    "sg:city":"Zermatt",
    "sg:orig_category":"Campingpl\u00e4tze Detailhandel mit Zeitungen U Zeitschriften Kioske",
    "sg:phone":"+41 79 456 93 58",
    "sg:postcode":"3920",
    "sg:province":"Valais",
    "wof:name":"Campingplatz Matterhorn",
    "wof:placetype":"venue"
},
  "geometry": {"coordinates":[7.75243,46.025879],"type":"Point"}
}