{
  "type": "Feature",
  "properties": {
    "addr:full":"Rue De Gen\u00e8ve 40 Ch\u00eane-bourg Gen\u00e8ve 1225",
    "addr:housenumber":"40",
    "addr:postcode":"1225",
    "addr:street":"Rue De Gene\u0300Ve;Che\u0302Ne-Bourg",
    "iso:country":"CH",
    "sg:address":"Rue De Gen\u00e8ve 40",
    "sg:city":"Ch\u00eane-bourg",
    "sg:orig_category":"Architektur U Ingenieurb\u00fcros",
    "sg:phone":"+41 22 349 33 55",
    "sg:postcode":"1225",
    "sg:province":"Gen\u00e8ve",
    "wof:name":"Bureau Technique D\u00e9perraz Claude Et Kunz Philippe",
    "wof:placetype":"venue"
},
  "geometry": {"coordinates":[6.195853,46.193893],"type":"Point"}
}