{
  "type": "Feature",
  "properties": {
    "iso:country":"CH",
    "sg:address":"Oberstrasse 16",
    "sg:city":"Herzogenbuchsee",
    "sg:orig_category":"Elektroinstallation",
    "sg:postcode":"3360",
    "sg:province":"Bern",
    "wof:name":"Lnw Products Gmbh",
    "wof:placetype":"venue"
},
  "geometry": {"coordinates":[7.7018070221,47.1869430542],"type":"Point"}
}