{
  "type": "Feature",
  "properties": {
    "iso:country":"CH",
    "sg:address":"Aegertstrasse 737",
    "sg:city":"Dietlikon",
    "sg:orig_category":"Sportvereine Sch\u00fctzen Armbrust",
    "sg:phone":"+41 18332844",
    "sg:postcode":"8305",
    "sg:province":"Z\u00fcrich",
    "wof:name":"Armbrustsch\u00fctzen-bund Dietlikon",
    "wof:placetype":"venue"
},
  "geometry": {"coordinates":[8.6280698776,47.4120101929],"type":"Point"}
}