{
  "type": "Feature",
  "properties": {
    "iso:country":"CH",
    "sg:address":"Stelzenstrasse 42 8706 Meilen. Postfach",
    "sg:city":"Meilen",
    "sg:orig_category":"Grosshandel mit Nahrungsmitteln, Getr\u00e4nken U Tabakwaren ohne ausgepr\u00e4gten Schwerpunkt",
    "sg:postcode":"8706",
    "sg:province":"Z\u00fcrich",
    "wof:name":"Chickeria Gyros Gmbh",
    "wof:placetype":"venue"
},
  "geometry": {"coordinates":[8.6466598511,47.2695236206],"type":"Point"}
}