{
  "type": "Feature",
  "properties": {
    "iso:country":"CH",
    "sg:address":"Route De Beaumont 16",
    "sg:city":"Fribourg",
    "sg:orig_category":"Handelsvermittlung U Grosshandel Handelsvermittlung U Grosshandel mit Automobilteilen U Zubeh\u00f6r",
    "sg:phone":"+41 56 442 51 60",
    "sg:postcode":"1700",
    "sg:province":"Fribourg",
    "wof:name":"Fa-tech Ag",
    "wof:placetype":"venue"
},
  "geometry": {"coordinates":[8.2108316422,47.4685325623],"type":"Point"}
}