{
  "type": "Feature",
  "properties": {
    "iso:country":"CH",
    "sg:address":"Via Alla Romantica",
    "sg:city":"Arbedo",
    "sg:orig_category":"Allgemeiner Hoch U Tiefbau",
    "sg:postcode":"6517",
    "sg:province":"Ticino",
    "wof:name":"Monresa Sa",
    "wof:placetype":"venue"
},
  "geometry": {"coordinates":[9.04713,46.211918],"type":"Point"}
}