{
  "type": "Feature",
  "properties": {
    "iso:country":"CH",
    "sg:address":"Speiserstrasse 98",
    "sg:city":"Basel",
    "sg:orig_category":"Gartenbau",
    "sg:phone":"+41 19200192",
    "sg:postcode":"4052",
    "sg:province":"Basel-Stadt",
    "wof:name":"Fritz Peter G\u00e4rtnerei",
    "wof:placetype":"venue"
},
  "geometry": {"coordinates":[8.6708612442,47.2636871338],"type":"Point"}
}