{
  "type": "Feature",
  "properties": {
    "iso:country":"CH",
    "sg:address":"Gerliswilstrasse 6a",
    "sg:city":"Emmenbr\u00fccke",
    "sg:orig_category":"Arztpraxen",
    "sg:phone":"+41 41 260 04 40",
    "sg:postcode":"6020",
    "sg:province":"Luzern",
    "wof:name":"Dr.med.sophie Brunner Leupi Spezial\u00e4rztin Fmh",
    "wof:placetype":"venue"
},
  "geometry": {"coordinates":[8.281455,47.070358],"type":"Point"}
}