{
  "type": "Feature",
  "properties": {
    "iso:country":"CH",
    "sg:address":"Seestrasse 15",
    "sg:city":"Zug",
    "sg:orig_category":"Architekturb\u00fcros",
    "sg:phone":"+41 41 710 48 08",
    "sg:postcode":"6300",
    "sg:province":"Zug",
    "wof:name":"Hans-peter Ammann Architekturb\u00fcro",
    "wof:placetype":"venue"
},
  "geometry": {"coordinates":[8.514483,47.166538],"type":"Point"}
}