{
  "type": "Feature",
  "properties": {
    "iso:country":"CH",
    "sg:address":"Scex Place Du 11 1950 Sion Case Postale 388",
    "sg:city":"Sierre",
    "sg:orig_category":"Herstellung von k\u00e4lte U lufttechnischen Erzeugnissen f\u00fcr gewerbliche Zwecke Sanit\u00e4r, Heizungs U L\u00fcft",
    "sg:phone":"+41 27 455 65 81",
    "sg:postcode":"3960",
    "sg:province":"Valais",
    "wof:name":"Froid Romandie S\u00e0rl Mat\u00e9riel De Climatisation Et De Production De Froid; Achat, Vente, Installation Etc",
    "wof:placetype":"venue"
},
  "geometry": {"coordinates":[7.3588571548,46.2280921936],"type":"Point"}
}