{
  "type": "Feature",
  "properties": {
    "iso:country":"CH",
    "sg:address":"N\u00fcnenenweg 7",
    "sg:city":"Heimberg",
    "sg:orig_category":"Sanit\u00e4r, Heizungs U L\u00fcftungsinstallation",
    "sg:phone":"+41 33 437 81 47",
    "sg:postcode":"3627",
    "sg:province":"Bern",
    "wof:name":"Stucki Martin",
    "wof:placetype":"venue"
},
  "geometry": {"coordinates":[7.604268074,46.7845993042],"type":"Point"}
}