{
  "type": "Feature",
  "properties": {
    "iso:country":"CH",
    "sg:address":"Chemin De La B\u00e9goudaz",
    "sg:city":"Eysins",
    "sg:orig_category":"Aktivit\u00e4ten der Generalunternehmen im Baugewerbe Allgemeiner Hoch U Tiefbau",
    "sg:phone":"+41 22 990 04 41",
    "sg:postcode":"1262",
    "sg:province":"Vaud",
    "wof:name":"General Entreprise Amc Ltd, \u00e0 Londres, Succursale D'eysins",
    "wof:placetype":"venue"
},
  "geometry": {"coordinates":[6.206785,46.383179],"type":"Point"}
}