{
  "type": "Feature",
  "properties": {
    "iso:country":"CH",
    "sg:address":"Weiacherstrasse 80",
    "sg:city":"Rorbas",
    "sg:orig_category":"Herstellung von Bereifungen",
    "sg:phone":"+41 18817525",
    "sg:postcode":"8427",
    "sg:province":"Z\u00fcrich",
    "wof:name":"Pneu Sigi, R. Siegenthaler",
    "wof:placetype":"venue"
},
  "geometry": {"coordinates":[8.5721712112,47.5330467224],"type":"Point"}
}