{
  "type": "Feature",
  "properties": {
    "iso:country":"CH",
    "sg:address":"Dorfstrasse 58",
    "sg:city":"Osterfingen",
    "sg:orig_category":"Rebbau",
    "sg:phone":"+41 52 681 19 92",
    "sg:postcode":"8218",
    "sg:province":"Schaffhausen",
    "wof:name":"Arnold Deuber",
    "wof:placetype":"venue"
},
  "geometry": {"coordinates":[8.4890813828,47.6629333496],"type":"Point"}
}