{
  "type": "Feature",
  "properties": {
    "iso:country":"CH",
    "sg:address":"Gl\u00e2ne Route De La 197",
    "sg:city":"Villars-sur-gl\u00e2ne",
    "sg:orig_category":"Non-Classified Establishments",
    "sg:postcode":"1752",
    "sg:province":"Fribourg",
    "wof:name":"Bvs Bella Vista Sa",
    "wof:placetype":"venue"
},
  "geometry": {"coordinates":[7.130428791,46.7955818176],"type":"Point"}
}