{
  "type": "Feature",
  "properties": {
    "iso:country":"CH",
    "sg:address":"Bodmi",
    "sg:city":"Grindelwald",
    "sg:orig_category":"RESTAURANTS: TEA-ROOMS",
    "sg:phone":"+41 33 853 12 56",
    "sg:postcode":"3818",
    "sg:province":"Bern",
    "wof:name":"Brawand Samuel",
    "wof:placetype":"venue"
},
  "geometry": {"coordinates":[8.039899826,46.6294174194],"type":"Point"}
}