{
  "type": "Feature",
  "properties": {
    "iso:country":"CH",
    "sg:address":"Weihermattstrasse 23",
    "sg:city":"Oberrohrdorf",
    "sg:orig_category":"Kauf U Verkauf von Immobilien auf eigene Rechnung",
    "sg:phone":"+41 56 496 63 20",
    "sg:postcode":"5452",
    "sg:province":"Aargau",
    "wof:name":"Park Immobilien Ag",
    "wof:placetype":"venue"
},
  "geometry": {"coordinates":[8.3164024353,47.4228820801],"type":"Point"}
}