{
  "type": "Feature",
  "properties": {
    "iso:country":"CH",
    "sg:address":"Liebr\u00fctistrasse 42",
    "sg:city":"Kaiseraugst",
    "sg:orig_category":"Fahrschulen, Flugschulen",
    "sg:phone":"+41 79 419 54 60",
    "sg:postcode":"4303",
    "sg:province":"Aargau",
    "wof:name":"Roger Favre Autofahrschule",
    "wof:placetype":"venue"
},
  "geometry": {"coordinates":[8.5358057022,47.279914856],"type":"Point"}
}