{
  "type": "Feature",
  "properties": {
    "iso:country":"CH",
    "sg:address":"Vedeggi Via 37",
    "sg:city":"Magliaso",
    "sg:orig_category":"Betrieb von Taxis",
    "sg:phone":"+41 79 239 00 73",
    "sg:postcode":"6983",
    "sg:province":"Ticino",
    "wof:name":"Samdriver Sagl",
    "wof:placetype":"venue"
},
  "geometry": {"coordinates":[8.887455,45.978783],"type":"Point"}
}