{
  "type": "Feature",
  "properties": {
    "addr:full":"Baselstrasse 13 4533 Riedholz. Postfach Riedholz Solothurn 4533",
    "addr:housenumber":"13",
    "addr:postcode":"4533;4533",
    "addr:street":"Baselstrasse",
    "iso:country":"CH",
    "sg:address":"Baselstrasse 13 4533 Riedholz. Postfach",
    "sg:city":"Riedholz",
    "sg:orig_category":"Herstellung von Landwirtschaftstraktoren",
    "sg:phone":"+41 32 623 23 43",
    "sg:postcode":"4533",
    "sg:province":"Solothurn",
    "wof:name":"Protractor Gmbh 2000 Motorfahrzeuge, Bes. Traktoren, Motoren, Ersatzteile U. Zubeh\u00f6r; Import, Handel",
    "wof:placetype":"venue"
},
  "geometry": {"coordinates":[7.567896,47.229717],"type":"Point"}
}