{
  "type": "Feature",
  "properties": {
    "iso:country":"CH",
    "sg:address":"Bielstrasse 158",
    "sg:city":"Solothurn",
    "sg:orig_category":"Detailhandel mit Sportartikeln",
    "sg:phone":"+41 32 621 84 84",
    "sg:postcode":"4500",
    "sg:province":"Solothurn",
    "wof:name":"Golf-bird Reinhardt Brigitte",
    "wof:placetype":"venue"
},
  "geometry": {"coordinates":[7.5185399055,47.2124137878],"type":"Point"}
}