{
  "type": "Feature",
  "properties": {
    "iso:country":"CH",
    "sg:address":"Giglenstrasse 2",
    "sg:city":"Sarnen",
    "sg:classifiers":[
        {
            "category":"Travel",
            "subcategory":"Hotels & Motels",
            "type":"Entertainment"
        }
    ],
    "sg:phone":"+41 41 660 13 36",
    "sg:postcode":"6060",
    "sg:province":"Obwalden",
    "sg:tags":[
        "hotels",
        "mit",
        "restaurant"
    ],
    "wof:name":"Hotel M\u00fchle",
    "wof:placetype":"venue"
},
  "geometry": {"coordinates":[8.2378292084,46.8926849365],"type":"Point"}
}