{
  "type": "Feature",
  "properties": {
    "iso:country":"CH",
    "sg:address":"Romont Rue De 22 1700 Fribourg Case Postale 646",
    "sg:city":"Freiburg",
    "sg:orig_category":"Architektur U Ingenieurb\u00fcros",
    "sg:postcode":"1700",
    "sg:province":"Fribourg",
    "wof:name":"Isb Ag Beratung, Betreuung, Bearbeitung U. Ausf\u00fchrung Von Bauten Usw",
    "wof:placetype":"venue"
},
  "geometry": {"coordinates":[7.59945,47.48859],"type":"Point"}
}