{
  "type": "Feature",
  "properties": {
    "iso:country":"CH",
    "sg:address":"Hauptstrasse 78 4450 Sissach. Postfach",
    "sg:city":"Sissach",
    "sg:orig_category":"Elektroinstallation",
    "sg:phone":"+41 79 413 19 35",
    "sg:postcode":"4450",
    "sg:province":"Basel-Landschaft",
    "wof:name":"Elektro Lang D\u00f6lf Gmbh",
    "wof:placetype":"venue"
},
  "geometry": {"coordinates":[8.4500131607,47.2803497314],"type":"Point"}
}