{
  "type": "Feature",
  "properties": {
    "iso:country":"CH",
    "sg:address":"Z\u00fcrichstreasse 521",
    "sg:city":"Aathal-seegr\u00e4ben",
    "sg:orig_category":"Einzelhandel mit Automobilen Handel mit Automobilen",
    "sg:phone":"+41 13721859",
    "sg:postcode":"8607",
    "sg:province":"Z\u00fcrich",
    "wof:name":"Autoshow Aathal Ag",
    "wof:placetype":"venue"
},
  "geometry": {"coordinates":[8.7684850693,47.3358840942],"type":"Point"}
}