{
  "type": "Feature",
  "properties": {
    "iso:country":"CH",
    "sg:address":"Zentralstrasse 57 2500 Biel/bienne. Postfach",
    "sg:city":"Biel/bienne",
    "sg:classifiers":[
        {
            "category":"Travel",
            "subcategory":"Hotels & Motels",
            "type":"Entertainment"
        }
    ],
    "sg:phone":"+41 79 336 42 09",
    "sg:postcode":"2502",
    "sg:province":"Bern",
    "sg:tags":[
        "hotels",
        "mit",
        "restaurant"
    ],
    "wof:name":"Flury Reto",
    "wof:placetype":"venue"
},
  "geometry": {"coordinates":[9.8244037628,46.798286438],"type":"Point"}
}