{
  "type": "Feature",
  "properties": {
    "iso:country":"CH",
    "sg:address":"Bahnhofstrasse 9",
    "sg:city":"Eglisau",
    "sg:classifiers":[
        {
            "category":"Travel",
            "subcategory":"Hotels & Motels",
            "type":"Entertainment"
        }
    ],
    "sg:phone":"+41 18670105",
    "sg:postcode":"8193",
    "sg:province":"Z\u00fcrich",
    "sg:tags":[
        "hotels",
        "mit",
        "restaurant"
    ],
    "wof:name":"Hotel Bahnhof",
    "wof:placetype":"venue"
},
  "geometry": {"coordinates":[8.5163326263,47.5727272034],"type":"Point"}
}