{
  "type": "Feature",
  "properties": {
    "iso:country":"CH",
    "sg:address":"Via Avvocato Buetti 7",
    "sg:city":"Locarno",
    "sg:orig_category":"Herstellung von Uhren",
    "sg:phone":"+41 32 968 08 18",
    "sg:postcode":"6600",
    "sg:province":"Ticino",
    "wof:name":"Taratec Sa",
    "wof:placetype":"venue"
},
  "geometry": {"coordinates":[6.836979866,47.1053962708],"type":"Point"}
}