{
  "type": "Feature",
  "properties": {
    "iso:country":"CH",
    "sg:address":"Via Tinelle 4",
    "sg:city":"Pedrinate",
    "sg:orig_category":"Unclassifiable Establishments",
    "sg:postcode":"6832",
    "sg:province":"Ticino",
    "wof:name":"Alfredo Rey It And Consulting",
    "wof:placetype":"venue"
},
  "geometry": {"coordinates":[8.432179451,47.3561897278],"type":"Point"}
}