{
  "type": "Feature",
  "properties": {
    "iso:country":"CH",
    "sg:address":"Sorts Via 37",
    "sg:city":"Ilanz",
    "sg:orig_category":"Unternehmensberatung",
    "sg:phone":"+41 81 925 24 78",
    "sg:postcode":"7130",
    "sg:province":"Graubunden",
    "wof:name":"Flury Fashion Consult Ffc",
    "wof:placetype":"venue"
},
  "geometry": {"coordinates":[9.1985797882,46.7738494873],"type":"Point"}
}