{
  "type": "Feature",
  "properties": {
    "iso:country":"CH",
    "sg:address":"Zeughausstrasse 12",
    "sg:city":"Lenzburg",
    "sg:orig_category":"Zahnarztpraxen",
    "sg:phone":"+41 62 891 54 64",
    "sg:postcode":"5600",
    "sg:province":"Aargau",
    "wof:name":"Dr.med.dent.eugen Schildknecht Zahnarzt",
    "wof:placetype":"venue"
},
  "geometry": {"coordinates":[8.1690568924,47.3896789551],"type":"Point"}
}