{
  "type": "Feature",
  "properties": {
    "iso:country":"CH",
    "sg:address":"Hafenstrasse 9 4057 Basel. Postfach",
    "sg:city":"Basel",
    "sg:orig_category":"G\u00fcterbef\u00f6rderung im Strassenverkehr",
    "sg:phone":"+41 61 639 97 97",
    "sg:postcode":"4019",
    "sg:province":"Basel-Stadt",
    "wof:name":"Poltrans Int.transporte Ag",
    "wof:placetype":"venue"
},
  "geometry": {"coordinates":[7.590088,47.583538],"type":"Point"}
}