{
  "type": "Feature",
  "properties": {
    "iso:country":"CH",
    "sg:address":"Champs-montants 14 B",
    "sg:city":"Marin-centre",
    "sg:orig_category":"Reinigungsgewerbe",
    "sg:postcode":"2074",
    "sg:province":"Neuch\u00e2tel",
    "wof:name":"Hobi + Co, Geb\u00e4udereinigungen",
    "wof:placetype":"venue"
},
  "geometry": {"coordinates":[8.6900548935,47.3005561829],"type":"Point"}
}