{
  "type": "Feature",
  "properties": {
    "iso:country":"CH",
    "sg:address":"Lettengrund 1",
    "sg:city":"Sins",
    "sg:orig_category":"Unclassifiable Establishments",
    "sg:phone":"+41 41 787 01 02",
    "sg:postcode":"5643",
    "sg:province":"Aargau",
    "wof:name":"Hair 4 You Gmbh",
    "wof:placetype":"venue"
},
  "geometry": {"coordinates":[8.3951272964,47.1894378662],"type":"Point"}
}