{
  "type": "Feature",
  "properties": {
    "iso:country":"CH",
    "sg:address":"Chr.-schnyderstrasse 48",
    "sg:city":"Sursee",
    "sg:orig_category":"Institutionen f\u00fcr Behinderte Tagesheime f\u00fcr Behinderte, gesch\u00fctzte Werkst\u00e4tten",
    "sg:phone":"+41 41 925 61 61",
    "sg:postcode":"6210",
    "sg:province":"Luzern",
    "wof:name":"Awb Neubrugg Eingliederungs-werkst\u00e4tten",
    "wof:placetype":"venue"
},
  "geometry": {"coordinates":[8.1055107117,47.1657943726],"type":"Point"}
}