{
  "type": "Feature",
  "properties": {
    "iso:country":"CH",
    "sg:address":"Grindelstrasse 5 8304 Wallisellen. Postfach",
    "sg:city":"Wallisellen",
    "sg:orig_category":"Non-Classified Establishments",
    "sg:postcode":"8304",
    "sg:province":"Z\u00fcrich",
    "wof:name":"Webneuch M\u00fcller Alain",
    "wof:placetype":"venue"
},
  "geometry": {"coordinates":[6.7472929955,47.059173584],"type":"Point"}
}