{
  "type": "Feature",
  "properties": {
    "iso:country":"CH",
    "sg:address":"Haldenweg 7",
    "sg:city":"Burgdorf",
    "sg:orig_category":"Orchester, Ch\u00f6re, Musiker",
    "sg:phone":"+41 34 422 06 26",
    "sg:postcode":"3400",
    "sg:province":"Bern",
    "wof:name":"Caruso Top Sound Dancing Grosse U. Und Kleine Anl\u00e4sse Orchster Kapelle",
    "wof:placetype":"venue"
},
  "geometry": {"coordinates":[7.6281900406,47.0578308105],"type":"Point"}
}