{
  "type": "Feature",
  "properties": {
    "iso:country":"CH",
    "sg:address":"Grand-places 16",
    "sg:city":"Fribourg",
    "sg:classifiers":[
        {
            "category":"Government",
            "subcategory":"Post Office",
            "type":"Public Place"
        }
    ],
    "sg:phone":"+41 26 322 31 31",
    "sg:postcode":"1700",
    "sg:province":"Fribourg",
    "sg:tags":[
        "caf\u00e9s",
        "tea-rooms"
    ],
    "wof:name":"Tea-room Joye Fid\u00e8le",
    "wof:placetype":"venue"
},
  "geometry": {"coordinates":[7.1531581879,46.8028907776],"type":"Point"}
}