{
  "type": "Feature",
  "properties": {
    "iso:country":"CH",
    "sg:address":"H\u00f4tel Du Cheval-blanc",
    "sg:city":"Bulle",
    "sg:classifiers":[
        {
            "category":"Travel",
            "subcategory":"Hotels & Motels",
            "type":"Entertainment"
        }
    ],
    "sg:postcode":"1630",
    "sg:province":"Fribourg",
    "sg:tags":[
        "hotels",
        "mit",
        "restaurant"
    ],
    "wof:name":"Basler H. Gasthof Zum L\u00f6wen",
    "wof:placetype":"venue"
},
  "geometry": {"coordinates":[8.1618499756,47.247089386],"type":"Point"}
}