{
  "type": "Feature",
  "properties": {
    "iso:country":"CH",
    "sg:address":"Hostettweg 5",
    "sg:city":"Kerns",
    "sg:orig_category":"Herstellung von sonstiger Bekleidung U Bekleidungszubeh\u00f6r",
    "sg:phone":"+41 41 660 59 15",
    "sg:postcode":"6064",
    "sg:province":"Obwalden",
    "wof:name":"Popofix Gmbh",
    "wof:placetype":"venue"
},
  "geometry": {"coordinates":[8.277299881,46.9031562805],"type":"Point"}
}