{
  "type": "Feature",
  "properties": {
    "iso:country":"CH",
    "sg:address":"Rue Des Vieux-grenadiers 4 1200 Genf. Postfach",
    "sg:city":"Gen\u00e8ve",
    "sg:orig_category":"Herstellung von Teppichen",
    "sg:phone":"+41 71 288 07 29",
    "sg:postcode":"1201",
    "sg:province":"Gen\u00e8ve",
    "wof:name":"Dragojlovic Rade",
    "wof:placetype":"venue"
},
  "geometry": {"coordinates":[9.4121351242,47.4422836304],"type":"Point"}
}