{
  "type": "Feature",
  "properties": {
    "iso:country":"CH",
    "sg:address":"Ackersteinstrasse 142",
    "sg:city":"Z\u00fcrich",
    "sg:orig_category":"Sonstige Hilfs U Nebent\u00e4tigkeiten f\u00fcr die Luftfahrt",
    "sg:postcode":"8049",
    "sg:province":"Z\u00fcrich",
    "wof:name":"Pro-flite Ag",
    "wof:placetype":"venue"
},
  "geometry": {"coordinates":[8.5039901733,47.3991851807],"type":"Point"}
}