{
  "type": "Feature",
  "properties": {
    "iso:country":"CH",
    "sg:address":"Kindergartenstrasse 15",
    "sg:city":"Romanshorn",
    "sg:orig_category":"Handels-H\u00e4user U Gesellschaften",
    "sg:postcode":"8590",
    "sg:province":"Thurgau",
    "wof:name":"Eigenmann P. Uni-handelsagentur",
    "wof:placetype":"venue"
},
  "geometry": {"coordinates":[9.3716154099,47.5647010803],"type":"Point"}
}