{
  "type": "Feature",
  "properties": {
    "addr:full":"Rathausgasse 29 Aarau Aargau 5000",
    "addr:housenumber":"29",
    "addr:postcode":"5000",
    "addr:street":"Rathausgasse",
    "iso:country":"CH",
    "sg:address":"Rathausgasse 29",
    "sg:city":"Aarau",
    "sg:orig_category":"Arztpraxen",
    "sg:phone":"+41 62 822 22 62",
    "sg:postcode":"5000",
    "sg:province":"Aargau",
    "wof:name":"Dr.med.helmut Jundt Spezialarzt Fmh",
    "wof:placetype":"venue"
},
  "geometry": {"coordinates":[8.044198,47.392441],"type":"Point"}
}