{
  "type": "Feature",
  "properties": {
    "iso:country":"CH",
    "sg:address":"Zulgstrasse 109",
    "sg:city":"Steffisburg",
    "sg:orig_category":"Innenarchitekturb\u00fcros",
    "sg:phone":"+41 33 437 91 90",
    "sg:postcode":"3613",
    "sg:province":"Bern",
    "wof:name":"Klaus Tschan Innenarchitektur",
    "wof:placetype":"venue"
},
  "geometry": {"coordinates":[7.6200890541,46.7745056152],"type":"Point"}
}