{
  "type": "Feature",
  "properties": {
    "iso:country":"CH",
    "sg:address":"3986",
    "sg:city":"Ried-m\u00f6rel",
    "sg:orig_category":"Detailhandel mit Waren verschiedener Art, Hauptrichtung Nahrungsmittel",
    "sg:phone":"+41 27 927 32 22",
    "sg:postcode":"3986",
    "sg:province":"Valais",
    "wof:name":"Konsumgenossenschaft Ried-m\u00f6rel",
    "wof:placetype":"venue"
},
  "geometry": {"coordinates":[8.0320081711,46.3573417664],"type":"Point"}
}