{
  "type": "Feature",
  "properties": {
    "iso:country":"CH",
    "sg:address":"Industriestrasse 13b",
    "sg:city":"Zug",
    "sg:classifiers":[
        {
            "category":"Professional",
            "subcategory":"Engineering",
            "type":"Services"
        }
    ],
    "sg:phone":"+41 41 711 27 22",
    "sg:postcode":"6300",
    "sg:province":"Zug",
    "wof:name":"Bowas Ag",
    "wof:placetype":"venue"
},
  "geometry": {"coordinates":[8.5183839798,47.1725463867],"type":"Point"}
}