{
  "type": "Feature",
  "properties": {
    "iso:country":"CH",
    "sg:city":"Ittigen",
    "sg:orig_category":"Industrie, Metallindustrie",
    "sg:postcode":"3063",
    "sg:province":"Bern",
    "wof:name":"Gaeng Metallbau",
    "wof:placetype":"venue"
},
  "geometry": {"coordinates":[7.480955,46.977432],"type":"Point"}
}