{
  "type": "Feature",
  "properties": {
    "iso:country":"CH",
    "sg:address":"H\u00f6ngerstrasse 292",
    "sg:city":"Laupersdorf",
    "sg:orig_category":"Bezirks, Sekundar, Realschulen, Oberstufe der Primarschulen",
    "sg:phone":"+41 62 391 17 55",
    "sg:postcode":"4712",
    "sg:province":"Solothurn",
    "wof:name":"Oberstufenschule Schulhaus Sunnmatt",
    "wof:placetype":"venue"
},
  "geometry": {"coordinates":[7.652476,47.312759],"type":"Point"}
}