{
  "type": "Feature",
  "properties": {
    "iso:country":"CH",
    "sg:address":"Fuchshubelstrasse 7",
    "sg:city":"Ittigen",
    "sg:orig_category":"Gartenbau",
    "sg:phone":"+41 18410690",
    "sg:postcode":"3063",
    "sg:province":"Bern",
    "wof:name":"Walter Meier G\u00e4rtnerei",
    "wof:placetype":"venue"
},
  "geometry": {"coordinates":[8.4677600861,47.4507446289],"type":"Point"}
}