{
  "type": "Feature",
  "properties": {
    "iso:country":"CH",
    "sg:address":"Schaffhuserstrass 8 8460 Marthalen. Postfach 53",
    "sg:city":"Marthalen",
    "sg:orig_category":"Sonstige Spinnstoffaufbereitung U Spinnerei",
    "sg:phone":"+41 52 319 11 31",
    "sg:postcode":"8460",
    "sg:province":"Z\u00fcrich",
    "wof:name":"Toggenburger & Co Ag Rosshaarspinnerei",
    "wof:placetype":"venue"
},
  "geometry": {"coordinates":[8.6510562897,47.6272621155],"type":"Point"}
}