{
  "type": "Feature",
  "properties": {
    "iso:country":"CH",
    "sg:address":"Bernstrasse 382 8953 Dietikon. Postfach",
    "sg:city":"Dietikon",
    "sg:classifiers":[
        {
            "category":"Bars & Pubs",
            "type":"Food & Drink"
        }
    ],
    "sg:phone":"+41 61 401 46 55",
    "sg:postcode":"8953",
    "sg:province":"Z\u00fcrich",
    "wof:name":"Smuggler's Pub",
    "wof:placetype":"venue"
},
  "geometry": {"coordinates":[7.563351,47.515717],"type":"Point"}
}