{
  "type": "Feature",
  "properties": {
    "iso:country":"CH",
    "sg:address":"Gartenstrasse 21",
    "sg:city":"Rohr",
    "sg:classifiers":[
        {
            "category":"Autos & Motor Vehicles",
            "subcategory":"Auto Supplies",
            "type":"Retail Goods"
        }
    ],
    "sg:phone":"+41 62 823 94 74",
    "sg:postcode":"5032",
    "sg:province":"Aargau",
    "sg:tags":[
        "part",
        "spare",
        "motorcycle",
        "accessory"
    ],
    "wof:name":"Maurer Motos Ag",
    "wof:placetype":"venue"
},
  "geometry": {"coordinates":[8.0814828873,47.4015617371],"type":"Point"}
}