{
  "type": "Feature",
  "properties": {
    "iso:country":"CH",
    "sg:address":"Bachstrasse 12",
    "sg:city":"Oberweningen",
    "sg:orig_category":"Handelsvermittlung von Textilien, Bekleidung, Schuhen U Lederwaren",
    "sg:phone":"+41 18857585",
    "sg:postcode":"8165",
    "sg:province":"Z\u00fcrich",
    "wof:name":"Stotz Mode + Marketing",
    "wof:placetype":"venue"
},
  "geometry": {"coordinates":[8.4099302292,47.5019493103],"type":"Point"}
}