{
  "type": "Feature",
  "properties": {
    "iso:country":"CH",
    "sg:address":"Rue Joseph-piller 4",
    "sg:city":"Fribourg",
    "sg:orig_category":"Wohnheime f\u00fcr Kinder U Jugendliche",
    "sg:phone":"+41 26 322 82 22",
    "sg:postcode":"1700",
    "sg:province":"Fribourg",
    "wof:name":"Foyer Beau-sejour Pour Jeunes Filles",
    "wof:placetype":"venue"
},
  "geometry": {"coordinates":[7.1555628777,46.8066596985],"type":"Point"}
}