{
  "type": "Feature",
  "properties": {
    "iso:country":"CH",
    "sg:address":"Obgassweg 6",
    "sg:city":"Buochs",
    "sg:orig_category":"Fachdetailhandel in Verkaufsr\u00e4umen",
    "sg:postcode":"6374",
    "sg:province":"Nidwalden",
    "wof:name":"Glasses Impex Gmbh Im, Export U. Handel Von Waren, Bes. Auf Dem Gebiet Der Optik",
    "wof:placetype":"venue"
},
  "geometry": {"coordinates":[8.6896934509,47.2690429688],"type":"Point"}
}