{
  "type": "Feature",
  "properties": {
    "iso:country":"CH",
    "sg:address":"Seestrasse 151 8820 W\u00e4denswil. Postfach",
    "sg:city":"W\u00e4denswil",
    "sg:orig_category":"Dienstleistungen von Beteiligungsgesellschaften",
    "sg:postcode":"8820",
    "sg:province":"Z\u00fcrich",
    "wof:name":"Rw Liegenschaften Ag, W\u00e4denswil",
    "wof:placetype":"venue"
},
  "geometry": {"coordinates":[8.6700639725,47.232093811],"type":"Point"}
}