{
  "type": "Feature",
  "properties": {
    "iso:country":"CH",
    "sg:address":"Napoleonstrasse 116",
    "sg:city":"Glis",
    "sg:orig_category":"G\u00fcterbef\u00f6rderung im Strassenverkehr",
    "sg:phone":"+41 27 923 17 62",
    "sg:postcode":"3902",
    "sg:province":"Valais",
    "wof:name":"Albert Pfammatter Transporte",
    "wof:placetype":"venue"
},
  "geometry": {"coordinates":[7.9874892235,46.309337616],"type":"Point"}
}