{
  "type": "Feature",
  "properties": {
    "iso:country":"CH",
    "sg:address":"Freiburgstrasse 14",
    "sg:city":"Biel/bienne",
    "sg:orig_category":"Vermietung U Verpachtung von eigenen Immobilien",
    "sg:postcode":"2500",
    "sg:province":"Bern",
    "wof:name":"Lindt & Peter Immobilien",
    "wof:placetype":"venue"
},
  "geometry": {"coordinates":[7.2477898598,47.1316223145],"type":"Point"}
}