{
  "type": "Feature",
  "properties": {
    "iso:country":"CH",
    "sg:address":"Hauptstrasse 1",
    "sg:city":"M\u00e4genwil",
    "sg:orig_category":"Stukkateurgewerbe, Gipserei U Verputzerei",
    "sg:postcode":"5506",
    "sg:province":"Aargau",
    "wof:name":"Gr\u00fcter Beat",
    "wof:placetype":"venue"
},
  "geometry": {"coordinates":[8.2246484756,47.4102516174],"type":"Point"}
}