{
  "type": "Feature",
  "properties": {
    "iso:country":"CH",
    "sg:address":"Route De Sion 65",
    "sg:city":"Sierre",
    "sg:orig_category":"Detailhandel mit Brot, Back U S\u00fcsswaren",
    "sg:phone":"+41 27 456 13 12",
    "sg:postcode":"3960",
    "sg:province":"Valais",
    "wof:name":"Boulangerie De L'ouest Epars-epiney Erica",
    "wof:placetype":"venue"
},
  "geometry": {"coordinates":[7.519185,46.286224],"type":"Point"}
}