{
  "type": "Feature",
  "properties": {
    "iso:country":"CH",
    "sg:address":"Laufenstrasse 20",
    "sg:city":"Basel",
    "sg:orig_category":"Non-Classified Establishments",
    "sg:postcode":"4053",
    "sg:province":"Basel-Stadt",
    "wof:name":"Gd Gastro, G. Nibali + D. Busic",
    "wof:placetype":"venue"
},
  "geometry": {"coordinates":[7.5992860794,47.5420188904],"type":"Point"}
}