{
  "type": "Feature",
  "properties": {
    "iso:country":"CH",
    "sg:address":"Oberdorfstrasse 10",
    "sg:city":"Knonau",
    "sg:orig_category":"Hoch U Tiefbau",
    "sg:phone":"+41 17670373",
    "sg:postcode":"8934",
    "sg:province":"Z\u00fcrich",
    "wof:name":"Viktor Schrader Baugesch\u00e4ft",
    "wof:placetype":"venue"
},
  "geometry": {"coordinates":[8.4625720978,47.2249603271],"type":"Point"}
}