{
  "type": "Feature",
  "properties": {
    "iso:country":"CH",
    "sg:address":"8450",
    "sg:city":"Andelfingen",
    "sg:orig_category":"Vereine Frauen Vereine Gemeinn\u00fctzige",
    "sg:phone":"+41 52 317 15 89",
    "sg:postcode":"8450",
    "sg:province":"Z\u00fcrich",
    "wof:name":"Frauenverein Andelfingen",
    "wof:placetype":"venue"
},
  "geometry": {"coordinates":[8.6767053604,47.5952262878],"type":"Point"}
}