{
  "type": "Feature",
  "properties": {
    "iso:country":"CH",
    "sg:address":"Hauptgasse 41 9050 Appenzell. Postfach",
    "sg:city":"Appenzell",
    "sg:orig_category":"Herstellung von D\u00fcngemitteln U Stickstoffverbindungen",
    "sg:postcode":"9050",
    "sg:province":"Appenzell Innerhoden",
    "wof:name":"Stercus Ag Waren, Bes. D\u00fcngelmittel, Gasprodukte; Handel Usw",
    "wof:placetype":"venue"
},
  "geometry": {"coordinates":[9.406867981,47.3313827515],"type":"Point"}
}