{
  "type": "Feature",
  "properties": {
    "iso:country":"CH",
    "sg:address":"Schulhaus",
    "sg:city":"Arboldswil",
    "sg:orig_category":"Religi\u00f6se Vereinigungen divers",
    "sg:postcode":"4424",
    "sg:province":"Basel-Landschaft",
    "wof:name":"Cvjm",
    "wof:placetype":"venue"
},
  "geometry": {"coordinates":[7.7172021866,47.4155006409],"type":"Point"}
}