{
  "type": "Feature",
  "properties": {
    "iso:country":"CH",
    "sg:address":"Chalet Birke Bahnhofplatz 3777 Saanenm\u00f6ser. Postfach",
    "sg:city":"Saanenm\u00f6ser",
    "sg:orig_category":"Personenbef\u00f6rderung im Linienverkehr zu Land",
    "sg:phone":"+41 79 342 84 49",
    "sg:postcode":"3777",
    "sg:province":"Bern",
    "wof:name":"Bergbahnen Saas-almagell Ag",
    "wof:placetype":"venue"
},
  "geometry": {"coordinates":[7.9573631287,46.0964317322],"type":"Point"}
}