{
  "type": "Feature",
  "properties": {
    "iso:country":"CH",
    "sg:address":"Avenue Bois-de-la-chapelle 106",
    "sg:city":"Onex",
    "sg:orig_category":"Detailhandel mit Sportartikeln Fachdetailhandel in Verkaufsr\u00e4umen",
    "sg:phone":"+41 22 793 44 78",
    "sg:postcode":"1213",
    "sg:province":"Gen\u00e8ve",
    "wof:name":"Onex Sports, Spadavecchia N.",
    "wof:placetype":"venue"
},
  "geometry": {"coordinates":[6.1007041931,46.1852378845],"type":"Point"}
}