{
  "type": "Feature",
  "properties": {
    "iso:country":"CH",
    "sg:address":"Obere Lattenbergstrasse 17",
    "sg:city":"St\u00e4fa",
    "sg:orig_category":"Vorschulen, Kinderg\u00e4rten",
    "sg:phone":"+41 19262236",
    "sg:postcode":"8712",
    "sg:province":"Z\u00fcrich",
    "wof:name":"Kindergarten Uelikon",
    "wof:placetype":"venue"
},
  "geometry": {"coordinates":[8.7177457809,47.2481269836],"type":"Point"}
}