{
  "type": "Feature",
  "properties": {
    "iso:country":"CH",
    "sg:address":"Binzstrasse 18 8000 Z\u00fcrich. Postfach 8045 Z\u00fcrich",
    "sg:city":"Zust",
    "sg:orig_category":"Unclassifiable Establishments",
    "sg:postcode":"45",
    "wof:name":"Lecygne Conseils S\u00e0rl",
    "wof:placetype":"venue"
},
  "geometry": {"coordinates":[6.3737401962,46.4796485901],"type":"Point"}
}