{
  "type": "Feature",
  "properties": {
    "iso:country":"CH",
    "sg:address":"Landoltstrasse 16",
    "sg:city":"Z\u00fcrich",
    "sg:orig_category":"Arztpraxen",
    "sg:phone":"+41 13620451",
    "sg:postcode":"8006",
    "sg:province":"Z\u00fcrich",
    "wof:name":"Dr.med.rudolf Strehler Spezialarzt Fmh",
    "wof:placetype":"venue"
},
  "geometry": {"coordinates":[8.551416,47.382832],"type":"Point"}
}