{
  "type": "Feature",
  "properties": {
    "iso:country":"CH",
    "sg:address":"Steinerstrasse 4",
    "sg:city":"Ossingen",
    "sg:orig_category":"Massagestudios",
    "sg:phone":"+41 52 317 20 70",
    "sg:postcode":"8475",
    "sg:province":"Z\u00fcrich",
    "wof:name":"Elvira Hefti Massagen",
    "wof:placetype":"venue"
},
  "geometry": {"coordinates":[8.7264709473,47.6116142273],"type":"Point"}
}