{
  "type": "Feature",
  "properties": {
    "iso:country":"CH",
    "sg:address":"Im Hasli 6",
    "sg:city":"Glash\u00fctten",
    "sg:orig_category":"Softwareentwicklung U beratung",
    "sg:phone":"+41 56 631 70 20",
    "sg:postcode":"4856",
    "sg:province":"Aargau",
    "wof:name":"Learn2win Gmbh Informatik; Schulung, Beratung Usw",
    "wof:placetype":"venue"
},
  "geometry": {"coordinates":[8.344452858,47.3506698608],"type":"Point"}
}