{
  "type": "Feature",
  "properties": {
    "iso:country":"CH",
    "sg:address":"Bois D'amont 78",
    "sg:city":"Ferpicloz",
    "sg:orig_category":"Elektroinstallation",
    "sg:phone":"+41 31 961 33 20",
    "sg:postcode":"1724",
    "sg:province":"Fribourg",
    "wof:name":"Meuwly Consulting S\u00e0rl",
    "wof:placetype":"venue"
},
  "geometry": {"coordinates":[7.164899826,46.7464103699],"type":"Point"}
}