{
  "type": "Feature",
  "properties": {
    "iso:country":"CH",
    "sg:address":"Schiltstrasse 29 8750 Glarus. Postfach",
    "sg:city":"Glarus",
    "sg:orig_category":"Handels-H\u00e4user U Gesellschaften",
    "sg:postcode":"8750",
    "sg:province":"Glarus",
    "wof:name":"Oai Ag",
    "wof:placetype":"venue"
},
  "geometry": {"coordinates":[9.0615243912,47.0380172729],"type":"Point"}
}