{
  "type": "Feature",
  "properties": {
    "iso:country":"CH",
    "sg:address":"Via Stazione 7",
    "sg:city":"Caslano",
    "sg:orig_category":"Allgemeiner Hoch U Tiefbau Erdbewegungsarbeiten",
    "sg:phone":"+41 91 606 11 38",
    "sg:postcode":"6987",
    "sg:province":"Ticino",
    "wof:name":"Maspoli Sa, Impresa Costruzioni",
    "wof:placetype":"venue"
},
  "geometry": {"coordinates":[8.882002,45.971836],"type":"Point"}
}