{
  "type": "Feature",
  "properties": {
    "addr:full":"Centralstrasse 17 Interlaken Bern 3800",
    "addr:housenumber":"17",
    "addr:postcode":"3800",
    "addr:street":"Centralstrasse",
    "iso:country":"CH",
    "sg:address":"Centralstrasse 17",
    "sg:city":"Interlaken",
    "sg:classifiers":[
        {
            "category":"Ice Cream",
            "type":"Food & Drink"
        }
    ],
    "sg:phone":"+41 33 822 21 90",
    "sg:postcode":"3800",
    "sg:province":"Bern",
    "sg:tags":[
        "freezers",
        "chest",
        "deep",
        "freezer"
    ],
    "wof:name":"V\u00f6geli Ag",
    "wof:placetype":"venue"
},
  "geometry": {"coordinates":[7.855798,46.68446],"type":"Point"}
}