{
  "type": "Feature",
  "properties": {
    "iso:country":"CH",
    "sg:address":"Rue Du Ch\u00e2teau 2",
    "sg:city":"Peseux",
    "sg:orig_category":"Bau\u00e4mter",
    "sg:phone":"+41 32 737 11 78",
    "sg:postcode":"2034",
    "sg:province":"Neuch\u00e2tel",
    "wof:name":"Services Communaux Travaux Publics",
    "wof:placetype":"venue"
},
  "geometry": {"coordinates":[6.889281,46.98814],"type":"Point"}
}