{
  "type": "Feature",
  "properties": {
    "iso:country":"CH",
    "sg:address":"Brahmsstrasse 47",
    "sg:city":"Z\u00fcrich",
    "sg:orig_category":"Vorschulen, Kinderg\u00e4rten",
    "sg:postcode":"8003",
    "sg:province":"Z\u00fcrich",
    "wof:name":"St\u00e4dtischer Kindergarten",
    "wof:placetype":"venue"
},
  "geometry": {"coordinates":[8.5060539246,47.378490448],"type":"Point"}
}