{
  "type": "Feature",
  "properties": {
    "iso:country":"CH",
    "sg:address":"Krattigstr. 80",
    "sg:city":"Spiez",
    "sg:orig_category":"Markt U Meinungsforschung",
    "sg:phone":"+41 33 655 00 76",
    "sg:postcode":"3700",
    "sg:province":"Bern",
    "wof:name":"Betec Arthur Beck, Marketing Und Unternehmensberatung, Ausstellungs Und Messeorganisation",
    "wof:placetype":"venue"
},
  "geometry": {"coordinates":[7.6841239929,46.6802864075],"type":"Point"}
}