{
  "type": "Feature",
  "properties": {
    "iso:country":"CH",
    "sg:address":"Witikonerstrasse 416",
    "sg:city":"Z\u00fcrich",
    "sg:orig_category":"Instandhaltung U Reparatur von Automobilen",
    "sg:phone":"+41 79 413 77 46",
    "sg:postcode":"8053",
    "sg:province":"Z\u00fcrich",
    "wof:name":"Rossi Silvano",
    "wof:placetype":"venue"
},
  "geometry": {"coordinates":[8.9789495468,46.1534805298],"type":"Point"}
}