{
  "type": "Feature",
  "properties": {
    "iso:country":"CH",
    "sg:address":"Blumenrain 105",
    "sg:city":"Biel/bienne",
    "sg:orig_category":"Pensionskassen",
    "sg:phone":"+41 32 366 41 11",
    "sg:postcode":"2500",
    "sg:province":"Bern",
    "wof:name":"Personalf\u00fcrsorgestiftung Der Klinik Linde Biel",
    "wof:placetype":"venue"
},
  "geometry": {"coordinates":[7.2630238533,47.1326446533],"type":"Point"}
}