{
  "type": "Feature",
  "properties": {
    "addr:full":"Via Rondonico 9 Ascona Ticino 6612",
    "addr:housenumber":"9",
    "addr:postcode":"6612",
    "addr:street":"Via Rondonico",
    "iso:country":"CH",
    "sg:address":"Via Rondonico 9",
    "sg:city":"Ascona",
    "sg:orig_category":"Architekturb\u00fcros",
    "sg:phone":"+41 91 791 21 14",
    "sg:postcode":"6612",
    "sg:province":"Ticino",
    "wof:name":"Livio Fantoni Studio D'architettura",
    "wof:placetype":"venue"
},
  "geometry": {"coordinates":[8.768088,46.156487],"type":"Point"}
}