{
  "type": "Feature",
  "properties": {
    "iso:country":"CH",
    "sg:address":"Riedgrabenstrasse 15",
    "sg:city":"R\u00fcmlang",
    "sg:orig_category":"Abbruch U Sprenggewerbe Abbruch U Sprenggewerbe, Erdbewegungsarbeiten",
    "sg:phone":"+41 18173276",
    "sg:postcode":"8153",
    "sg:province":"Z\u00fcrich",
    "wof:name":"Kuster Hans-ulrich Ag, R\u00fcmlang, Abbruch Und Tiefbau",
    "wof:placetype":"venue"
},
  "geometry": {"coordinates":[8.519405,47.462425],"type":"Point"}
}