{
  "type": "Feature",
  "properties": {
    "iso:country":"CH",
    "sg:address":"Hofwisenstrasse 50 8153 R\u00fcmlang. Postfach",
    "sg:city":"R\u00fcmlang",
    "sg:orig_category":"Fernmeldedienste",
    "sg:postcode":"8153",
    "sg:province":"Z\u00fcrich",
    "wof:name":"Sunrise Internet Services Ag",
    "wof:placetype":"venue"
},
  "geometry": {"coordinates":[8.5399179459,47.4497146606],"type":"Point"}
}