{
  "type": "Feature",
  "properties": {
    "iso:country":"CH",
    "sg:address":"Tramstrasse 4",
    "sg:city":"Diepoldsau",
    "sg:orig_category":"Detailhandel mit Textilien",
    "sg:phone":"+41 71 733 12 81",
    "sg:postcode":"9444",
    "sg:province":"St. Gallen",
    "wof:name":"Johanna Weder Wollzentrale",
    "wof:placetype":"venue"
},
  "geometry": {"coordinates":[9.654417038,47.3865242004],"type":"Point"}
}