{
  "type": "Feature",
  "properties": {
    "iso:country":"CH",
    "sg:address":"Oberibergerstrasse 9 8842 Unteriberg. Postfach",
    "sg:city":"Unteriberg",
    "sg:orig_category":"RESTAURANTS: TEA-ROOMS",
    "sg:phone":"+41 81 756 15 85",
    "sg:postcode":"8842",
    "sg:province":"Schwyz",
    "wof:name":"Berghaus Malbun, Good Toni Bergrestaurant Mit Beherbungsm\u00f6glichkeiten",
    "wof:placetype":"venue"
},
  "geometry": {"coordinates":[9.4626941681,47.169380188],"type":"Point"}
}