{
  "type": "Feature",
  "properties": {
    "iso:country":"CH",
    "sg:address":"T\u00f6distrasse 17",
    "sg:city":"Z\u00fcrich",
    "sg:orig_category":"Interessenvertretungen",
    "sg:postcode":"8002",
    "sg:province":"Z\u00fcrich",
    "wof:name":"Fondation Internationale Pour La Promotion Et Le D\u00e9veloppement-finde.",
    "wof:placetype":"venue"
},
  "geometry": {"coordinates":[8.5351657867,47.3653030396],"type":"Point"}
}