{
  "type": "Feature",
  "properties": {
    "iso:country":"CH",
    "sg:address":"St. Gallerstrasse 53",
    "sg:city":"Herisau",
    "sg:orig_category":"Verwaltung von Immobilien",
    "sg:postcode":"9100",
    "sg:province":"Appenzell Ausserrhoden",
    "wof:name":"Wohnbaugenossenschaft Wangen A. A.",
    "wof:placetype":"venue"
},
  "geometry": {"coordinates":[7.6489210129,47.234161377],"type":"Point"}
}