{
  "type": "Feature",
  "properties": {
    "iso:country":"CH",
    "sg:address":"1670",
    "sg:city":"Ursy",
    "sg:orig_category":"Bauschreinerei Herstellung von Fenstern U T\u00fcren aus Holz",
    "sg:phone":"+41 21 909 41 22",
    "sg:postcode":"1670",
    "sg:province":"Fribourg",
    "wof:name":"D\u00e9nervaud Fr\u00e8res S\u00e0rl Fen\u00eatres Portes Escaliers",
    "wof:placetype":"venue"
},
  "geometry": {"coordinates":[6.84338,46.641811],"type":"Point"}
}