{
  "type": "Feature",
  "properties": {
    "iso:country":"CH",
    "sg:address":"Leingr\u00fceblerstrasse 1 A",
    "sg:city":"Wiesendangen",
    "sg:orig_category":"Wirtschaftspr\u00fcfung, Steuerberatung U Treuhand",
    "sg:postcode":"8542",
    "sg:province":"Z\u00fcrich",
    "wof:name":"Bsb-beat Streit Buchhaltungen",
    "wof:placetype":"venue"
},
  "geometry": {"coordinates":[8.780248642,47.5250053406],"type":"Point"}
}