{
  "type": "Feature",
  "properties": {
    "iso:country":"CH",
    "sg:address":"Chemin De La Damaz 84",
    "sg:city":"St-prex",
    "sg:orig_category":"Malerei Stukkateurgewerbe, Gipserei U Verputzerei",
    "sg:phone":"+41 21 806 11 10",
    "sg:postcode":"1162",
    "sg:province":"Vaud",
    "wof:name":"Jean-pierre Marsens Pl\u00e2trerie & Peinture",
    "wof:placetype":"venue"
},
  "geometry": {"coordinates":[6.4406638145,46.4791679382],"type":"Point"}
}