{
  "type": "Feature",
  "properties": {
    "iso:country":"CH",
    "sg:address":"Solothurnerstrasse 96",
    "sg:city":"Basel",
    "sg:orig_category":"Arztpraxen",
    "sg:phone":"+41 61 363 07 05",
    "sg:postcode":"4053",
    "sg:province":"Basel-Stadt",
    "wof:name":"Dr.med. Beatrice Gisin Spezial\u00e4rztin Fmh",
    "wof:placetype":"venue"
},
  "geometry": {"coordinates":[7.588209,47.541855],"type":"Point"}
}