{
  "type": "Feature",
  "properties": {
    "iso:country":"CH",
    "sg:address":"Sonnmattstrasse 31",
    "sg:city":"Adligenswil",
    "sg:orig_category":"Detailhandel mit M\u00f6beln U Haushaltsgegenst\u00e4nden Detailhandel mit Teppichen",
    "sg:phone":"+41 79 215 61 94",
    "sg:postcode":"6043",
    "sg:province":"Luzern",
    "wof:name":"Teppiche Perego",
    "wof:placetype":"venue"
},
  "geometry": {"coordinates":[8.37977314,47.075340271],"type":"Point"}
}