{
  "type": "Feature",
  "properties": {
    "iso:country":"CH",
    "sg:address":"Uttenbergstrasse 1",
    "sg:city":"Knonau",
    "sg:classifiers":[
        {
            "category":"Restaurant",
            "type":"Food & Drink"
        }
    ],
    "sg:phone":"+41 17670292",
    "sg:postcode":"8934",
    "sg:province":"Z\u00fcrich",
    "wof:name":"Restaurant H\u00f6rnli",
    "wof:placetype":"venue"
},
  "geometry": {"coordinates":[8.4625587463,47.2234153748],"type":"Point"}
}