{
  "type": "Feature",
  "properties": {
    "addr:full":"Winkelstrasse 3 Oftringen Aargau 4665",
    "addr:housenumber":"3",
    "addr:postcode":"4665",
    "addr:street":"Winkelstrasse",
    "iso:country":"CH",
    "sg:address":"Winkelstrasse 3",
    "sg:city":"Oftringen",
    "sg:orig_category":"Allgemeiner Gartenbau Dienstleistungen im Gartenbau",
    "sg:phone":"+41 31 984 07 00",
    "sg:postcode":"4665",
    "sg:province":"Aargau",
    "wof:name":"Erhard Riggenbach Gartenbau Liegenschaftsdienst",
    "wof:placetype":"venue"
},
  "geometry": {"coordinates":[7.361014,46.917126],"type":"Point"}
}