{
  "type": "Feature",
  "properties": {
    "iso:country":"CH",
    "sg:address":"In Der Gass 1 8627 Gr\u00fcningen. Postfach",
    "sg:city":"Gr\u00fcningen",
    "sg:orig_category":"Wirtschaftspr\u00fcfung, Steuerberatung U Treuhand",
    "sg:postcode":"8627",
    "sg:province":"Z\u00fcrich",
    "wof:name":"Von Allmen Verena, Treuhand",
    "wof:placetype":"venue"
},
  "geometry": {"coordinates":[8.7562704086,47.2798614502],"type":"Point"}
}