{
  "type": "Feature",
  "properties": {
    "iso:country":"CH",
    "sg:address":"Untere Schlossmatte",
    "sg:city":"Heitenried",
    "sg:orig_category":"Herstellung von sonstigen elektrischen Ausr\u00fcstungen",
    "sg:postcode":"1714",
    "sg:province":"Fribourg",
    "wof:name":"Wagner J. Ag",
    "wof:placetype":"venue"
},
  "geometry": {"coordinates":[9.5583677292,47.3812904358],"type":"Point"}
}