{
  "type": "Feature",
  "properties": {
    "iso:country":"CH",
    "sg:address":"Gl\u00e4rnischstrasse 10 8002 Z\u00fcrich. Postfach",
    "sg:city":"Z\u00fcrich",
    "sg:orig_category":"Diskotheken, Dancings, Night Clubs",
    "sg:phone":"+41 12012410",
    "sg:postcode":"8022",
    "sg:province":"Z\u00fcrich",
    "wof:name":"Discothek Club Diagonal",
    "wof:placetype":"venue"
},
  "geometry": {"coordinates":[8.5386190414,47.3668746948],"type":"Point"}
}