{
  "type": "Feature",
  "properties": {
    "addr:full":"H\u00fchnerhubelstrasse 37 3123 Belp. Postfach Belp Bern 3123",
    "addr:housenumber":"37",
    "addr:postcode":"3123 belp. postfach;3123",
    "addr:street":"Huehnerhubelstrasse",
    "iso:country":"CH",
    "sg:address":"H\u00fchnerhubelstrasse 37 3123 Belp. Postfach",
    "sg:city":"Belp",
    "sg:orig_category":"Betrieb U technische Hilfsdienste des Kultur U Unterhaltungswesens",
    "sg:postcode":"3123",
    "sg:province":"Bern",
    "wof:name":"Mob-hill Audio-recording Gmbh",
    "wof:placetype":"venue"
},
  "geometry": {"coordinates":[7.497007,46.901073],"type":"Point"}
}