{
  "type": "Feature",
  "properties": {
    "iso:country":"CH",
    "sg:address":"Via Giulio Pocobelli 16",
    "sg:city":"Melide",
    "sg:orig_category":"Nationale Postdienste",
    "sg:phone":"+41 91 649 73 13",
    "sg:postcode":"6815",
    "sg:province":"Ticino",
    "wof:name":"La Posta Svizzera",
    "wof:placetype":"venue"
},
  "geometry": {"coordinates":[8.943239212,45.9514160156],"type":"Point"}
}