{
  "type": "Feature",
  "properties": {
    "iso:country":"CH",
    "sg:address":"Bahnhofstrasse 122",
    "sg:city":"Schiers",
    "sg:orig_category":"Detailhandel mit Waren verschiedener Art, Hauptrichtung Nahrungsmittel Sonstiger Grosshandel",
    "sg:phone":"+41 81 328 13 23",
    "sg:postcode":"7220",
    "sg:province":"Graubunden",
    "wof:name":"Lagrischa Sa",
    "wof:placetype":"venue"
},
  "geometry": {"coordinates":[9.6886053085,46.9694213867],"type":"Point"}
}