{
  "type": "Feature",
  "properties": {
    "iso:country":"CH",
    "sg:address":"Route De Villars 21",
    "sg:city":"Fribourg",
    "sg:orig_category":"Detailhandel mit Fleisch U Fleischwaren",
    "sg:phone":"+41 26 660 40 08",
    "sg:postcode":"1700",
    "sg:province":"Fribourg",
    "wof:name":"Pury Eddy",
    "wof:placetype":"venue"
},
  "geometry": {"coordinates":[6.8926100731,46.8147010803],"type":"Point"}
}