{
  "type": "Feature",
  "properties": {
    "iso:country":"CH",
    "sg:address":"Bl\u00fcmlisalpstrasse 36",
    "sg:city":"Heimberg",
    "sg:orig_category":"Unclassifiable Establishments",
    "sg:phone":"+41 33 438 15 51",
    "sg:postcode":"3627",
    "sg:province":"Bern",
    "wof:name":"Mcdonald's Restaurant",
    "wof:placetype":"venue"
},
  "geometry": {"coordinates":[7.6067762375,46.7809677124],"type":"Point"}
}