{
  "type": "Feature",
  "properties": {
    "iso:country":"CH",
    "sg:address":"Dorfstrasse 19",
    "sg:city":"Gansingen",
    "sg:orig_category":"Detailhandel mit Waren verschiedener Art, Hauptrichtung Nahrungsmittel Grosshandel mit Nahrungsmitte",
    "sg:phone":"+41 32 351 37 73",
    "sg:postcode":"5272",
    "sg:province":"Aargau",
    "wof:name":"Denner Satellit, Seuret R.",
    "wof:placetype":"venue"
},
  "geometry": {"coordinates":[7.3660411835,47.1392250061],"type":"Point"}
}