{
  "type": "Feature",
  "properties": {
    "addr:full":"Benkenstrasse 51 K\u00fcttigen Aargau 5024",
    "addr:housenumber":"51",
    "addr:postcode":"5024",
    "addr:street":"Benkenstrasse",
    "iso:country":"CH",
    "sg:address":"Benkenstrasse 51",
    "sg:city":"K\u00fcttigen",
    "sg:orig_category":"Autogaragen Instandhaltung U Reparatur von Automobilen",
    "sg:phone":"+41 62 827 13 43",
    "sg:postcode":"5024",
    "sg:province":"Aargau",
    "wof:name":"Benkengarage Brechb\u00fchl + Klossner",
    "wof:placetype":"venue"
},
  "geometry": {"coordinates":[8.039557,47.421383],"type":"Point"}
}