{
  "type": "Feature",
  "properties": {
    "iso:country":"CH",
    "sg:address":"Soleil 2000",
    "sg:city":"Chandolin",
    "sg:orig_category":"Detailhandel mit Milcherzeugnissen U Eiern",
    "sg:phone":"+41 27 475 18 48",
    "sg:postcode":"3961",
    "sg:province":"Valais",
    "wof:name":"Valrh\u00f4ne Sa Primo Alimentation",
    "wof:placetype":"venue"
},
  "geometry": {"coordinates":[7.603741169,46.1775054932],"type":"Point"}
}