{
  "type": "Feature",
  "properties": {
    "addr:full":"L\u00e4nggassstr. 7 Bern Bern 3001",
    "addr:housenumber":"7",
    "addr:postcode":"3001",
    "addr:street":"Laenggassstr.",
    "iso:country":"CH",
    "sg:address":"L\u00e4nggassstr. 7",
    "sg:city":"Bern",
    "sg:classifiers":[
        {
            "category":"Professional",
            "subcategory":"Advertising",
            "type":"Services"
        }
    ],
    "sg:phone":"+41 31 309 33 33",
    "sg:postcode":"3001",
    "sg:province":"Bern",
    "sg:tags":[
        "information",
        "medium",
        "communication"
    ],
    "wof:name":"Schweizerische Depeschenagentur Ag",
    "wof:placetype":"venue"
},
  "geometry": {"coordinates":[7.434522,46.951561],"type":"Point"}
}