{
  "type": "Feature",
  "properties": {
    "iso:country":"CH",
    "sg:address":"Haltenstrasse 10",
    "sg:city":"Neftenbach",
    "sg:orig_category":"Fachdetailhandel in Verkaufsr\u00e4umen",
    "sg:phone":"+41 52 315 47 30",
    "sg:postcode":"8413",
    "sg:province":"Z\u00fcrich",
    "wof:name":"Friedman-scheiber Isabelle",
    "wof:placetype":"venue"
},
  "geometry": {"coordinates":[8.6693763733,47.5250511169],"type":"Point"}
}