{
  "type": "Feature",
  "properties": {
    "iso:country":"CH",
    "sg:address":"Hauptstrasse 63",
    "sg:city":"Ligerz",
    "sg:orig_category":"Rebbau Sonstiger Grosshandel",
    "sg:phone":"+41 27 306 50 56",
    "sg:postcode":"2514",
    "sg:province":"Bern",
    "wof:name":"Snc Lips Rolf & C\u00e9cile",
    "wof:placetype":"venue"
},
  "geometry": {"coordinates":[7.2086448669,46.1864585876],"type":"Point"}
}