{
  "type": "Feature",
  "properties": {
    "iso:country":"CH",
    "sg:address":"Tellistrasse 4",
    "sg:city":"Aarau",
    "sg:orig_category":"Informatikschulen",
    "sg:phone":"+41 81 413 75 17",
    "sg:postcode":"5000",
    "sg:province":"Aargau",
    "wof:name":"Berufsschule Der Landschaft Davos",
    "wof:placetype":"venue"
},
  "geometry": {"coordinates":[9.8196086884,46.791557312],"type":"Point"}
}