{
  "type": "Feature",
  "properties": {
    "addr:full":"Dorfstrasse 44 Adelboden Bern 3715",
    "addr:housenumber":"44",
    "addr:postcode":"3715",
    "addr:street":"Dorfstrasse",
    "iso:country":"CH",
    "sg:address":"Dorfstrasse 44",
    "sg:city":"Adelboden",
    "sg:orig_category":"Arztpraxen",
    "sg:phone":"+41 33 673 26 26",
    "sg:postcode":"3715",
    "sg:province":"Bern",
    "wof:name":"Dres Med.w. Schmid & E. Kempf Aerzte F\u00fcr Allg.medizin Fmh",
    "wof:placetype":"venue"
},
  "geometry": {"coordinates":[7.557286,46.491451],"type":"Point"}
}