{
  "type": "Feature",
  "properties": {
    "iso:country":"CH",
    "sg:address":"Sch\u00e4renmoosstrasse 105",
    "sg:city":"Z\u00fcrich",
    "sg:orig_category":"Werbeberatung",
    "sg:phone":"+41 13028069",
    "sg:postcode":"8052",
    "sg:province":"Z\u00fcrich",
    "wof:name":"Thomas Schwander Zentrale Text Konzept",
    "wof:placetype":"venue"
},
  "geometry": {"coordinates":[8.5588321686,47.4184799194],"type":"Point"}
}