{
  "type": "Feature",
  "properties": {
    "iso:country":"CH",
    "sg:address":"4657",
    "sg:city":"Dulliken",
    "sg:orig_category":"Sportvereine Sch\u00fctzen",
    "sg:phone":"+41 62 291 22 15",
    "sg:postcode":"4657",
    "sg:province":"Solothurn",
    "wof:name":"Sch\u00fctzengesellschaft",
    "wof:placetype":"venue"
},
  "geometry": {"coordinates":[7.9811601639,47.3500900269],"type":"Point"}
}