{
  "type": "Feature",
  "properties": {
    "iso:country":"CH",
    "sg:address":"Binzikerstrasse 49",
    "sg:city":"Gr\u00fcningen",
    "sg:classifiers":[
        {
            "category":"Exhibition Hall",
            "type":"Public Place"
        }
    ],
    "sg:phone":"+41 19353375",
    "sg:postcode":"8627",
    "sg:province":"Z\u00fcrich",
    "sg:tags":[
        "steel"
    ],
    "wof:name":"Heinrich Frauenfelder",
    "wof:placetype":"venue"
},
  "geometry": {"coordinates":[8.7596492767,47.2783508301],"type":"Point"}
}