{
  "type": "Feature",
  "properties": {
    "iso:country":"CH",
    "sg:address":"Stauffacherstrasse 5",
    "sg:city":"Bern",
    "sg:orig_category":"Elektroinstallation",
    "sg:phone":"+41 32 665 29 29",
    "sg:postcode":"3014",
    "sg:province":"Bern",
    "wof:name":"Alfred Ramseier Elektro Ramseier",
    "wof:placetype":"venue"
},
  "geometry": {"coordinates":[7.5588068962,47.1521186829],"type":"Point"}
}