{
  "type": "Feature",
  "properties": {
    "iso:country":"CH",
    "sg:address":"Thurtalstrasse 28",
    "sg:city":"Altikon",
    "sg:orig_category":"Sportvereine Turnen",
    "sg:phone":"+41 52 336 16 49",
    "sg:postcode":"8479",
    "sg:province":"Z\u00fcrich",
    "wof:name":"Turnverein Stv Altikon",
    "wof:placetype":"venue"
},
  "geometry": {"coordinates":[8.7816791534,47.5731620789],"type":"Point"}
}