{
  "type": "Feature",
  "properties": {
    "iso:country":"CH",
    "sg:address":"Riedstrasse 12 8953 Dietikon. Postfach",
    "sg:city":"Dietikon",
    "sg:orig_category":"Detailhandel mit elektrischen Haushalts-,Radio U Fernsehger\u00e4ten sowie Musikinstrumenten",
    "sg:postcode":"8953",
    "sg:province":"Z\u00fcrich",
    "wof:name":"Design Und Ton Ag",
    "wof:placetype":"venue"
},
  "geometry": {"coordinates":[8.3951148987,47.4202423096],"type":"Point"}
}