{
  "type": "Feature",
  "properties": {
    "iso:country":"CH",
    "sg:address":"M\u00f6\u00f6slimatten 17",
    "sg:city":"Ettiswil",
    "sg:orig_category":"G\u00fcterbef\u00f6rderung im Strassenverkehr",
    "sg:phone":"+41 32 757 17 90",
    "sg:postcode":"6218",
    "sg:province":"Luzern",
    "wof:name":"Thomi Henri",
    "wof:placetype":"venue"
},
  "geometry": {"coordinates":[7.0127072334,47.0351142883],"type":"Point"}
}