{
  "type": "Feature",
  "properties": {
    "iso:country":"CH",
    "sg:address":"Rue De La Terrassi\u00e8re 25 1200 Genf. Postfach",
    "sg:city":"Gen\u00e8ve",
    "sg:orig_category":"Detailhandel mit Tabakwaren",
    "sg:postcode":"1207",
    "sg:province":"Gen\u00e8ve",
    "wof:name":"M. Et Mme Renggli",
    "wof:placetype":"venue"
},
  "geometry": {"coordinates":[6.1584610939,46.2007446289],"type":"Point"}
}