{
  "type": "Feature",
  "properties": {
    "iso:country":"CH",
    "sg:address":"Hohlstrasse 610 8000 Z\u00fcrich. Postfach",
    "sg:city":"Z\u00fcrich",
    "sg:orig_category":"Vermietung U Verpachtung von eigenen Immobilien",
    "sg:phone":"+41 14326020",
    "sg:postcode":"8048",
    "sg:province":"Z\u00fcrich",
    "wof:name":"Gumar Treuhand- & Verwaltungs Ag",
    "wof:placetype":"venue"
},
  "geometry": {"coordinates":[8.4847230911,47.3919258118],"type":"Point"}
}