{
  "type": "Feature",
  "properties": {
    "iso:country":"CH",
    "sg:address":"Sunneweg 5 8820 W\u00e4denswil. Postfach",
    "sg:city":"W\u00e4denswil",
    "sg:orig_category":"Vermietung U Verpachtung von eigenen Immobilien",
    "sg:phone":"+41 71 385 27 27",
    "sg:postcode":"8820",
    "sg:province":"Z\u00fcrich",
    "wof:name":"Eisenring Immobilien Ag",
    "wof:placetype":"venue"
},
  "geometry": {"coordinates":[9.2438488007,47.4145889282],"type":"Point"}
}