{
  "type": "Feature",
  "properties": {
    "iso:country":"CH",
    "sg:address":"7141",
    "sg:city":"Luven",
    "sg:orig_category":"Grosshandel mit Spielwaren",
    "sg:phone":"+41 81 925 22 43",
    "sg:postcode":"7141",
    "sg:province":"Graubunden",
    "wof:name":"J. & Chr. Sommer Modellbauzubeh\u00f6r",
    "wof:placetype":"venue"
},
  "geometry": {"coordinates":[9.1987686157,46.7618560791],"type":"Point"}
}