{
  "type": "Feature",
  "properties": {
    "iso:country":"CH",
    "sg:address":"Obstgartenweg 1",
    "sg:city":"Freienstein",
    "sg:orig_category":"Herstellung von Mess U Kontrollinstrumenten U vorrichtungen Mechanische Werkst\u00e4tten",
    "sg:phone":"+41 32 931 30 17",
    "sg:postcode":"8427",
    "sg:province":"Z\u00fcrich",
    "wof:name":"Wyss Pierre",
    "wof:placetype":"venue"
},
  "geometry": {"coordinates":[6.7461872101,47.0432434082],"type":"Point"}
}