{
  "type": "Feature",
  "properties": {
    "iso:country":"CH",
    "sg:address":"Route De La Chassotte 3",
    "sg:city":"Givisiez",
    "sg:orig_category":"Detailhandel mit elektrischen Haushalts-,Radio U Fernsehger\u00e4ten sowie Musikinstrumenten",
    "sg:postcode":"1762",
    "sg:province":"Fribourg",
    "wof:name":"Clean Sound, Cotting & Cie",
    "wof:placetype":"venue"
},
  "geometry": {"coordinates":[7.1361589432,46.8119163513],"type":"Point"}
}