{
  "type": "Feature",
  "properties": {
    "iso:country":"CH",
    "sg:address":"Eggstrasse 4",
    "sg:city":"Zweisimmen",
    "sg:orig_category":"Kaminfeger",
    "sg:phone":"+41 33 722 22 44",
    "sg:postcode":"3770",
    "sg:province":"Bern",
    "wof:name":"Anton Roth Kaminfegermeister",
    "wof:placetype":"venue"
},
  "geometry": {"coordinates":[7.3830919266,46.5577850342],"type":"Point"}
}