{
  "type": "Feature",
  "properties": {
    "iso:country":"CH",
    "sg:address":"Ziegelhofstrasse 6",
    "sg:city":"Uznach",
    "sg:orig_category":"Instandhaltung U Reparatur von Automobilen",
    "sg:phone":"+41 55 280 33 05",
    "sg:postcode":"8730",
    "sg:province":"St. Gallen",
    "wof:name":"Summa Garage Gmbh",
    "wof:placetype":"venue"
},
  "geometry": {"coordinates":[8.9814300537,47.221660614],"type":"Point"}
}