{
  "type": "Feature",
  "properties": {
    "iso:country":"CH",
    "sg:address":"Sonnenwiesenstr. 22",
    "sg:city":"Kreuzlingen",
    "sg:classifiers":[
        {
            "category":"Home & Garden",
            "subcategory":"Furniture",
            "type":"Retail Goods"
        }
    ],
    "sg:phone":"+41 71 686 70 50",
    "sg:postcode":"8280",
    "sg:province":"Thurgau",
    "sg:tags":[
        "household",
        "wood"
    ],
    "wof:name":"Kocherhans Ag",
    "wof:placetype":"venue"
},
  "geometry": {"coordinates":[9.1929941177,47.6442756653],"type":"Point"}
}