{
  "type": "Feature",
  "properties": {
    "iso:country":"CH",
    "sg:address":"Chlupfgasse 2 8303 Bassersdorf. Postfach",
    "sg:city":"Bassersdorf",
    "sg:orig_category":"Allgemeiner Hoch U Tiefbau",
    "sg:phone":"+41 18366363",
    "sg:postcode":"8303",
    "sg:province":"Z\u00fcrich",
    "wof:name":"Hauser B., Hoch Und Tiefbau.",
    "wof:placetype":"venue"
},
  "geometry": {"coordinates":[8.623824,47.444668],"type":"Point"}
}