{
  "type": "Feature",
  "properties": {
    "iso:country":"CH",
    "sg:address":"Neudorfstrasse 5",
    "sg:city":"Horgen",
    "sg:orig_category":"Detailhandel mit medizinischen U orthop\u00e4dischen Artikeln",
    "sg:phone":"+41 17256351",
    "sg:postcode":"8810",
    "sg:province":"Z\u00fcrich",
    "wof:name":"Richard Bearth",
    "wof:placetype":"venue"
},
  "geometry": {"coordinates":[8.6001281738,47.2586708069],"type":"Point"}
}