{
  "type": "Feature",
  "properties": {
    "addr:full":"Nidaugasse 35 Biel/bienne Bern 2502",
    "addr:housenumber":"35",
    "addr:postcode":"2502",
    "addr:street":"Nidaugasse",
    "iso:country":"CH",
    "sg:address":"Nidaugasse 35",
    "sg:city":"Biel/bienne",
    "sg:classifiers":[
        {
            "category":"Social Services",
            "subcategory":"Retirement Home",
            "type":"Services"
        }
    ],
    "sg:phone":"+41 32 329 34 00",
    "sg:postcode":"2502",
    "sg:province":"Bern",
    "sg:tags":[
        "jewelled",
        "clock"
    ],
    "wof:name":"Concord Watch Company Sa",
    "wof:placetype":"venue"
},
  "geometry": {"coordinates":[7.246778,47.138573],"type":"Point"}
}