{
  "type": "Feature",
  "properties": {
    "iso:country":"CH",
    "sg:address":"Ostermundigenstrasse 56",
    "sg:city":"Bern",
    "sg:orig_category":"Sportvereine Turnen",
    "sg:phone":"+41 34 435 12 50",
    "sg:postcode":"3006",
    "sg:province":"Bern",
    "wof:name":"Sportver.stv Affoltern-weier",
    "wof:placetype":"venue"
},
  "geometry": {"coordinates":[7.730618,47.065246582],"type":"Point"}
}