{
  "type": "Feature",
  "properties": {
    "iso:country":"CH",
    "sg:address":"Allenwindenstrasse",
    "sg:city":"Kriens",
    "sg:orig_category":"Kosmetikinstitute",
    "sg:phone":"+41 41 320 54 60",
    "sg:postcode":"6010",
    "sg:province":"Luzern",
    "wof:name":"Nelly Stalder Kosmetikinstitut Nelly",
    "wof:placetype":"venue"
},
  "geometry": {"coordinates":[8.2774991989,47.0270423889],"type":"Point"}
}