{
  "type": "Feature",
  "properties": {
    "iso:country":"CH",
    "sg:address":"Laubigartenweg 23",
    "sg:city":"Hochwald",
    "sg:classifiers":[
        {
            "category":"Insurance",
            "subcategory":"Insurance Agent",
            "type":"Services"
        }
    ],
    "sg:phone":"+41 61 751 33 17",
    "sg:postcode":"4146",
    "sg:province":"Solothurn",
    "sg:tags":[
        "versicherungsagenturen",
        "-broker"
    ],
    "wof:name":"Die Mobiliar Versicherungen & Vorsorge",
    "wof:placetype":"venue"
},
  "geometry": {"coordinates":[7.6421561241,47.4539871216],"type":"Point"}
}