{
  "type": "Feature",
  "properties": {
    "iso:country":"CH",
    "sg:address":"Leeg. 6",
    "sg:city":"Niederdorf",
    "sg:classifiers":[
        {
            "category":"Manufacturing",
            "subcategory":"Metals",
            "type":"Manufacturing & Wholesale Goods"
        }
    ],
    "sg:phone":"+41 61 961 00 56",
    "sg:postcode":"4435",
    "sg:province":"Basel-Landschaft",
    "sg:tags":[
        "metallurgy",
        "metalworking",
        "processing"
    ],
    "wof:name":"Plattner Ag",
    "wof:placetype":"venue"
},
  "geometry": {"coordinates":[7.7519869804,47.4048614502],"type":"Point"}
}