{
  "type": "Feature",
  "properties": {
    "iso:country":"CH",
    "sg:address":"Katzenr\u00fcti 324",
    "sg:city":"R\u00fcmlang",
    "sg:orig_category":"Grosshandel mit Obst U Gem\u00fcse",
    "sg:phone":"+41 81 410 11 33",
    "sg:postcode":"8153",
    "sg:province":"Z\u00fcrich",
    "wof:name":"Gela Frutta Cl Kesselring & Co.",
    "wof:placetype":"venue"
},
  "geometry": {"coordinates":[9.8362779617,46.8012771606],"type":"Point"}
}