{
  "type": "Feature",
  "properties": {
    "addr:full":"Zann 55 Speicher Appenzell Ausserrhoden 9042",
    "addr:housenumber":"55",
    "addr:postcode":"9042",
    "addr:street":"Zann;Ausserrhoden",
    "iso:country":"CH",
    "sg:address":"Zann 55",
    "sg:city":"Speicher",
    "sg:classifiers":[
        {
            "category":"Banks & Credit Unions",
            "subcategory":"Bank",
            "type":"Services"
        }
    ],
    "sg:phone":"+41 4171941010",
    "sg:postcode":"9042",
    "sg:province":"Appenzell Ausserrhoden",
    "wof:name":"Appenzell-ausserrhodische, Kantonalbank",
    "wof:placetype":"venue"
},
  "geometry": {"coordinates":[9.443751,47.410404],"type":"Point"}
}