{
  "type": "Feature",
  "properties": {
    "iso:country":"CH",
    "sg:address":"Route Du Faubourg 9",
    "sg:city":"Sugiez",
    "sg:orig_category":"Maurerarbeiten Sonstiger spezialisierter Hoch U Tiefbau",
    "sg:phone":"+41 26 673 10 86",
    "sg:postcode":"1786",
    "sg:province":"Fribourg",
    "wof:name":"Aurelio Tirone Entreprise De Ma\u00e7onnerie",
    "wof:placetype":"venue"
},
  "geometry": {"coordinates":[7.1123561859,46.965221405],"type":"Point"}
}