{
  "type": "Feature",
  "properties": {
    "iso:country":"CH",
    "sg:address":"Rue Voltaire 29",
    "sg:city":"Gen\u00e8ve",
    "sg:orig_category":"Detailhandel mit Bekleidung Detailhandel mit Damenbekleidung",
    "sg:phone":"+41 55 210 70 40",
    "sg:postcode":"1201",
    "sg:province":"Gen\u00e8ve",
    "wof:name":"Les Sportives Diem & Co",
    "wof:placetype":"venue"
},
  "geometry": {"coordinates":[8.817174,47.22633],"type":"Point"}
}