{
  "type": "Feature",
  "properties": {
    "iso:country":"CH",
    "sg:address":"Moosweg 1",
    "sg:city":"Z\u00e4ziwil",
    "sg:orig_category":"Detailhandel Handel mit Motorr\u00e4dern, Teilen U Zubeh\u00f6r Instandhaltung U Reparatur von Motorr\u00e4dern Rep",
    "sg:phone":"+41 31 711 31 07",
    "sg:postcode":"3532",
    "sg:province":"Bern",
    "wof:name":"Stalder Motorsport",
    "wof:placetype":"venue"
},
  "geometry": {"coordinates":[7.6606001854,46.8959465027],"type":"Point"}
}