{
  "type": "Feature",
  "properties": {
    "iso:country":"CH",
    "sg:address":"Avenue De Cour 110",
    "sg:city":"Lausanne",
    "sg:orig_category":"W\u00e4schereien",
    "sg:phone":"+41 21 616 73 45",
    "sg:postcode":"1007",
    "sg:province":"Vaud",
    "wof:name":"Netasec",
    "wof:placetype":"venue"
},
  "geometry": {"coordinates":[6.612267971,46.5166473389],"type":"Point"}
}