{
  "type": "Feature",
  "properties": {
    "iso:country":"CH",
    "sg:address":"In Den Chlepfen 4a",
    "sg:city":"Dietwil",
    "sg:orig_category":"Bauingenieurb\u00fcros allgemein",
    "sg:phone":"+41 21 802 29 33",
    "sg:postcode":"6042",
    "sg:province":"Aargau",
    "wof:name":"G\u00e9rard Chevalier Sa Bureau D'ing\u00e9nieurs",
    "wof:placetype":"venue"
},
  "geometry": {"coordinates":[6.491563,46.509239],"type":"Point"}
}