{
  "type": "Feature",
  "properties": {
    "iso:country":"CH",
    "sg:address":"Buechstrasse 19",
    "sg:city":"Jona",
    "sg:orig_category":"Elektroinstallation",
    "sg:phone":"+41 81 756 43 62",
    "sg:postcode":"8645",
    "sg:province":"St. Gallen",
    "wof:name":"Elektro Tosolini",
    "wof:placetype":"venue"
},
  "geometry": {"coordinates":[9.4776315689,47.1612281799],"type":"Point"}
}