{
  "type": "Feature",
  "properties": {
    "iso:country":"CH",
    "sg:address":"Gsteigstrasse 3",
    "sg:city":"B\u00f6nigen",
    "sg:orig_category":"Sanit\u00e4r, Heizungs U L\u00fcftungsinstallation",
    "sg:postcode":"3806",
    "sg:province":"Bern",
    "wof:name":"Wyss Installationen Gmbh",
    "wof:placetype":"venue"
},
  "geometry": {"coordinates":[7.8913850784,46.6839599609],"type":"Point"}
}