{
  "type": "Feature",
  "properties": {
    "iso:country":"CH",
    "sg:address":"Ecole Chemin De L' 21 1284 Chancy. Postfach",
    "sg:city":"Chancy",
    "sg:orig_category":"Unternehmensberatung",
    "sg:postcode":"1284",
    "sg:province":"Gen\u00e8ve",
    "wof:name":"Crucible Sa Aide Aux Soci\u00e9t\u00e9s \u00e9trang\u00e8res Souhait. S'implanter Dans Le March\u00e9 Europ\u00e9en",
    "wof:placetype":"venue"
},
  "geometry": {"coordinates":[5.9808301926,46.1464691162],"type":"Point"}
}