{
  "type": "Feature",
  "properties": {
    "iso:country":"CH",
    "sg:address":"Kreuzenstrasse 16",
    "sg:city":"Itingen",
    "sg:orig_category":"Malerei",
    "sg:phone":"+41 61 971 58 21",
    "sg:postcode":"4452",
    "sg:province":"Basel-Landschaft",
    "wof:name":"Heinz Sutter Malergesch\u00e4ft",
    "wof:placetype":"venue"
},
  "geometry": {"coordinates":[7.7821540833,47.466884613],"type":"Point"}
}