{
  "type": "Feature",
  "properties": {
    "iso:country":"CH",
    "sg:address":"1724",
    "sg:city":"Sen\u00e8des",
    "sg:orig_category":"Schulpflegen",
    "sg:phone":"+41 26 413 14 20",
    "sg:postcode":"1724",
    "sg:province":"Fribourg",
    "wof:name":"Commission Scolaire De L'\u00e9cole Primaire",
    "wof:placetype":"venue"
},
  "geometry": {"coordinates":[7.1431279182,46.7420806885],"type":"Point"}
}