{
  "type": "Feature",
  "properties": {
    "iso:country":"CH",
    "sg:address":"3658",
    "sg:city":"Merligen",
    "sg:orig_category":"Schulpflegen",
    "sg:phone":"+41 61 751 56 47",
    "sg:postcode":"3658",
    "sg:province":"Bern",
    "wof:name":"Primarschulpflege Der Gemeinde Merligen",
    "wof:placetype":"venue"
},
  "geometry": {"coordinates":[7.7376198769,46.69713974],"type":"Point"}
}