{
  "type": "Feature",
  "properties": {
    "iso:country":"CH",
    "sg:address":"Gerlikonerstrasse 31",
    "sg:city":"Frauenfeld",
    "sg:orig_category":"P\u00e9dicure",
    "sg:phone":"+41 52 720 17 86",
    "sg:postcode":"8500",
    "sg:province":"Thurgau",
    "wof:name":"Erwin St\u00e4heli P\u00e9dicure",
    "wof:placetype":"venue"
},
  "geometry": {"coordinates":[8.8880386353,47.5493354797],"type":"Point"}
}