{
  "type": "Feature",
  "properties": {
    "iso:country":"CH",
    "sg:address":"Grindelstrasse 4",
    "sg:city":"Volketswil",
    "sg:orig_category":"Arztpraxen",
    "sg:phone":"+41 19453737",
    "sg:postcode":"8604",
    "sg:province":"Z\u00fcrich",
    "wof:name":"Dr.med. Ren\u00e9 Utzinger Arzt F\u00fcr Allgem.medizin Fmh",
    "wof:placetype":"venue"
},
  "geometry": {"coordinates":[8.663925,47.385498],"type":"Point"}
}