{
  "type": "Feature",
  "properties": {
    "iso:country":"CH",
    "sg:address":"Via Maggio 1b 6900 Lugano. Postfach 6906 Lugano",
    "sg:city":"Caselle",
    "sg:orig_category":"Interessenvertretungen",
    "sg:postcode":"6",
    "wof:name":"Commenda Svizzera Ordo Dominus Et Nosocomii Sanctis Joannis Jerusalem, Osj",
    "wof:placetype":"venue"
},
  "geometry": {"coordinates":[8.961098671,46.0080337524],"type":"Point"}
}