{
  "type": "Feature",
  "properties": {
    "iso:country":"CH",
    "sg:address":"Hardturmstrasse 135",
    "sg:city":"Z\u00fcrich",
    "sg:orig_category":"Detailhandel mit Antiquit\u00e4ten Detailhandel mit Antiquit\u00e4ten U Gebrauchtwaren in Verkaufsr\u00e4umen",
    "sg:phone":"+41 12712929",
    "sg:postcode":"8005",
    "sg:province":"Z\u00fcrich",
    "wof:name":"Sobel Samuel Antiquit\u00e4ten",
    "wof:placetype":"venue"
},
  "geometry": {"coordinates":[8.512755,47.393398],"type":"Point"}
}