{
  "type": "Feature",
  "properties": {
    "iso:country":"CH",
    "sg:address":"Eschikerstrasse 21 Effretikon 8308 Horben B. Illnau. Postfach",
    "sg:city":"Tagelswangen",
    "sg:orig_category":"Maler U Glasergewerbe",
    "sg:phone":"+41 61 403 94 00",
    "sg:postcode":"8317",
    "sg:province":"Z\u00fcrich",
    "wof:name":"Grummel H. Gmbh",
    "wof:placetype":"venue"
},
  "geometry": {"coordinates":[7.551609993,47.5176239014],"type":"Point"}
}