{
  "type": "Feature",
  "properties": {
    "addr:full":"Jonastrasse 11 Wald Z\u00fcrich 8636",
    "addr:housenumber":"11",
    "addr:postcode":"8636",
    "addr:street":"Jonastrasse",
    "iso:country":"CH",
    "sg:address":"Jonastrasse 11",
    "sg:city":"Wald",
    "sg:classifiers":[
        {
            "category":"Building & Trades",
            "subcategory":"Equipment Rental",
            "type":"Services"
        }
    ],
    "sg:phone":"+41 55 266 10 20",
    "sg:postcode":"8636",
    "sg:province":"Z\u00fcrich",
    "sg:tags":[
        "registers",
        "register",
        "system",
        "cash"
    ],
    "wof:name":"Adega Gmbh",
    "wof:placetype":"venue"
},
  "geometry": {"coordinates":[-106.355003,40.45145],"type":"Point"}
}