{
  "type": "Feature",
  "properties": {
    "iso:country":"CH",
    "sg:address":"Hauptstrasse",
    "sg:city":"Frieswil",
    "sg:orig_category":"Sportvereine Turnen Vereine Damen",
    "sg:postcode":"3035",
    "sg:province":"Bern",
    "wof:name":"Frauenriege Stv Radelfingen",
    "wof:placetype":"venue"
},
  "geometry": {"coordinates":[7.2864561081,46.9949111938],"type":"Point"}
}