{
  "type": "Feature",
  "properties": {
    "addr:full":"Thunstrasse 47 Spiez Bern 3700",
    "addr:housenumber":"47",
    "addr:postcode":"3700",
    "addr:street":"Thunstrasse",
    "iso:country":"CH",
    "sg:address":"Thunstrasse 47",
    "sg:city":"Spiez",
    "sg:orig_category":"Arztpraxen",
    "sg:phone":"+41 33 654 55 83",
    "sg:postcode":"3700",
    "sg:province":"Bern",
    "wof:name":"Dres Med.a. Jost & Th. Beck Spezial\u00e4rzte Fmh",
    "wof:placetype":"venue"
},
  "geometry": {"coordinates":[7.666445,46.691097],"type":"Point"}
}