{
  "type": "Feature",
  "properties": {
    "iso:country":"CH",
    "sg:address":"Schulstrasse 10",
    "sg:city":"Rorschach",
    "sg:orig_category":"Sanit\u00e4rinstallation Sanit\u00e4rinstallation U Spenglerei",
    "sg:phone":"+41 71 841 23 19",
    "sg:postcode":"9400",
    "sg:province":"St. Gallen",
    "wof:name":"Urs Furrer Sanit\u00e4r-heizung & Spenglerei",
    "wof:placetype":"venue"
},
  "geometry": {"coordinates":[9.4947471619,47.4757461548],"type":"Point"}
}