{
  "type": "Feature",
  "properties": {
    "iso:country":"CH",
    "sg:address":"Leinstrasse 4",
    "sg:city":"Muhen",
    "sg:orig_category":"Herstellung von Elektrizit\u00e4tsverteilungs U schalteinrichtungen",
    "sg:phone":"+41 17505036",
    "sg:postcode":"5037",
    "sg:province":"Aargau",
    "wof:name":"Vareg, L\u00fcscher & Co",
    "wof:placetype":"venue"
},
  "geometry": {"coordinates":[8.0573968887,47.3297195435],"type":"Point"}
}