{
  "type": "Feature",
  "properties": {
    "iso:country":"CH",
    "sg:address":"Kronengasse 7",
    "sg:city":"Selzach",
    "sg:orig_category":"Unclassifiable Establishments",
    "sg:postcode":"2545",
    "sg:province":"Solothurn",
    "wof:name":"Restaurant Krone Talevi",
    "wof:placetype":"venue"
},
  "geometry": {"coordinates":[7.4525651932,47.2073745728],"type":"Point"}
}