{
  "type": "Feature",
  "properties": {
    "iso:country":"CH",
    "sg:address":"Cantonale Via",
    "sg:city":"Pregassona",
    "sg:orig_category":"Vermietung U Verpachtung von eigenen Immobilien",
    "sg:postcode":"6963",
    "sg:province":"Ticino",
    "wof:name":"Immobiliare Lagorosso Sa",
    "wof:placetype":"venue"
},
  "geometry": {"coordinates":[8.971824646,46.0180358887],"type":"Point"}
}