{
  "type": "Feature",
  "properties": {
    "iso:country":"CH",
    "sg:address":"Guisan Av. Du G\u00e9n\u00e9ral 15",
    "sg:city":"Sierre",
    "sg:orig_category":"Non-Classified Establishments",
    "sg:postcode":"3960",
    "sg:province":"Valais",
    "wof:name":"Pronotec Sa",
    "wof:placetype":"venue"
},
  "geometry": {"coordinates":[7.5305118561,46.2922592163],"type":"Point"}
}