{
  "type": "Feature",
  "properties": {
    "iso:country":"CH",
    "sg:address":"Predigergasse 15-17 8001 Z\u00fcrich. Postfach",
    "sg:city":"Z\u00fcrich",
    "sg:orig_category":"Herstellung von Schmuck, Gold U Silberschmiedwaren Herstellung von sonstigen M\u00f6beln",
    "sg:phone":"+41 12516714",
    "sg:postcode":"8025",
    "wof:name":"G\u00fcgi H. Vergolden Und Einrahmen Ag",
    "wof:placetype":"venue"
},
  "geometry": {"coordinates":[8.5457677841,47.3733940125],"type":"Point"}
}