{
  "type": "Feature",
  "properties": {
    "iso:country":"CH",
    "sg:address":"Via Giulia 43",
    "sg:city":"Stabio",
    "sg:orig_category":"Handels-H\u00e4user U Gesellschaften",
    "sg:phone":"+41 91 647 14 12",
    "sg:postcode":"6855",
    "sg:province":"Ticino",
    "wof:name":"Basilese Assicurazioni Agenzia Graziano Bobbi\u00e0",
    "wof:placetype":"venue"
},
  "geometry": {"coordinates":[8.9361763,45.8485450745],"type":"Point"}
}