{
  "type": "Feature",
  "properties": {
    "iso:country":"CH",
    "sg:address":"Oberbergstrasse 1",
    "sg:city":"Engelberg",
    "sg:orig_category":"Fahrschulen, Flugschulen",
    "sg:phone":"+41 41 637 22 22",
    "sg:postcode":"6390",
    "sg:province":"Obwalden",
    "wof:name":"Arnold Hurschler Autofahrschule",
    "wof:placetype":"venue"
},
  "geometry": {"coordinates":[8.415140152,46.8176307678],"type":"Point"}
}