{
  "type": "Feature",
  "properties": {
    "iso:country":"CH",
    "sg:address":"H\u00f6henstrasse 5 A",
    "sg:city":"Flurlingen",
    "sg:orig_category":"Sportvereine Wassersport Rudern",
    "sg:postcode":"8247",
    "sg:province":"Z\u00fcrich",
    "wof:name":"Ruderklub Schaffhausen",
    "wof:placetype":"venue"
},
  "geometry": {"coordinates":[8.6303195953,47.686214447],"type":"Point"}
}