{
  "type": "Feature",
  "properties": {
    "iso:country":"CH",
    "sg:address":"Tourelle Chemin De La 12 1209 Gen\u00e8ve. Postfach",
    "sg:city":"Gen\u00e8ve",
    "sg:orig_category":"Unternehmensberatung",
    "sg:postcode":"1207",
    "sg:province":"Gen\u00e8ve",
    "wof:name":"Regazzoni & Luisoni Sa",
    "wof:placetype":"venue"
},
  "geometry": {"coordinates":[9.009595871,45.8600730896],"type":"Point"}
}