{
  "type": "Feature",
  "properties": {
    "iso:country":"CH",
    "sg:address":"Viale Stazione 17.",
    "sg:city":"Bellinzona",
    "sg:orig_category":"Kauf U Verkauf von Immobilien auf eigene Rechnung",
    "sg:postcode":"6500",
    "sg:province":"Ticino",
    "wof:name":"Si Cortina B Sa",
    "wof:placetype":"venue"
},
  "geometry": {"coordinates":[6.8074121475,47.092628479],"type":"Point"}
}