{
  "type": "Feature",
  "properties": {
    "iso:country":"CH",
    "sg:address":"Waldau 7",
    "sg:city":"Landquart",
    "sg:orig_category":"Sanit\u00e4r U Heizungsinstallation Sanit\u00e4rinstallation",
    "sg:phone":"+41 71 245 54 54",
    "sg:postcode":"7302",
    "sg:province":"Graubunden",
    "wof:name":"Martin Eisenring San.installationen Heizungen",
    "wof:placetype":"venue"
},
  "geometry": {"coordinates":[9.3957805634,47.4454841614],"type":"Point"}
}