{
  "type": "Feature",
  "properties": {
    "addr:full":"Vordergasse 34 8200 Schaffhausen. Postfach Schaffhausen Schaffhausen 8201",
    "addr:housenumber":"34",
    "addr:postcode":"8200 schaffhausen. postfach;8201",
    "addr:street":"Vordergasse",
    "iso:country":"CH",
    "sg:address":"Vordergasse 34 8200 Schaffhausen. Postfach",
    "sg:city":"Schaffhausen",
    "sg:orig_category":"Advokaturb\u00fcros",
    "sg:phone":"+41 52 624 64 60",
    "sg:postcode":"8201",
    "sg:province":"Schaffhausen",
    "wof:name":"J\u00fcrg Stahel Advokaturb\u00fcro",
    "wof:placetype":"venue"
},
  "geometry": {"coordinates":[8.63655,47.696205],"type":"Point"}
}