{
  "type": "Feature",
  "properties": {
    "iso:country":"CH",
    "sg:address":"Industrieplatz 1 Sig-areal 8212 Neuhausen. Postfach 513",
    "sg:city":"Schaffhausen",
    "sg:orig_category":"Detailhandel Reparatur von Gebrauchsg\u00fctern Sonstiger Grosshandel",
    "sg:phone":"+41 52 625 03 13",
    "sg:postcode":"8201",
    "sg:province":"Schaffhausen",
    "wof:name":"Free Island Gmbh",
    "wof:placetype":"venue"
},
  "geometry": {"coordinates":[8.6196098328,47.6815681458],"type":"Point"}
}