{
  "type": "Feature",
  "properties": {
    "iso:country":"CH",
    "sg:address":"Fadail 6",
    "sg:city":"Lenzerheide/lai",
    "sg:orig_category":"Detailhandel mit Radio U Fernsehger\u00e4ten Herstellung von sonstigen elektrischen Ausr\u00fcstungen",
    "sg:phone":"+41 81 384 19 04",
    "sg:postcode":"7078",
    "sg:province":"Graubunden",
    "wof:name":"Simeon Paul Ag",
    "wof:placetype":"venue"
},
  "geometry": {"coordinates":[9.5494785309,46.7305831909],"type":"Point"}
}