{
  "type": "Feature",
  "properties": {
    "iso:country":"CH",
    "sg:address":"Siedlungsweg 8 R\u00fcfenacht. 3076 Worb. Postfach",
    "sg:city":"Worb",
    "sg:orig_category":"Herstellung von Konstruktionsteilen, Fertigbauteilen U Ausbauelementen aus Holz",
    "sg:phone":"+41 31 839 01 04",
    "sg:postcode":"3076",
    "sg:province":"Bern",
    "wof:name":"Liechti Erwin.",
    "wof:placetype":"venue"
},
  "geometry": {"coordinates":[7.5633797646,46.9297447205],"type":"Point"}
}