{
  "type": "Feature",
  "properties": {
    "iso:country":"CH",
    "sg:address":"8840",
    "sg:city":"Einsiedeln",
    "sg:orig_category":"G\u00fcterbef\u00f6rderung im Strassenverkehr",
    "sg:postcode":"8840",
    "sg:province":"Schwyz",
    "wof:name":"Lacher-reichmuth Franz.",
    "wof:placetype":"venue"
},
  "geometry": {"coordinates":[8.7460803986,47.1273155212],"type":"Point"}
}