{
  "type": "Feature",
  "properties": {
    "iso:country":"CH",
    "sg:address":"Ch\u00eane-bougeries Rue De 17",
    "sg:city":"Ch\u00eane-bougeries",
    "sg:orig_category":"Betrieb U technische Hilfsdienste des Kultur U Unterhaltungswesens",
    "sg:postcode":"1224",
    "sg:province":"Gen\u00e8ve",
    "wof:name":"Association Eyo",
    "wof:placetype":"venue"
},
  "geometry": {"coordinates":[6.190014,46.196793],"type":"Point"}
}