{
  "type": "Feature",
  "properties": {
    "iso:country":"CH",
    "sg:address":"Ergolzstrasse 3",
    "sg:city":"Lausen",
    "sg:orig_category":"Sonstige mit der Informatik verbundene T\u00e4tigkeiten",
    "sg:postcode":"4415",
    "sg:province":"Basel-Landschaft",
    "wof:name":"Mabruc Geneto",
    "wof:placetype":"venue"
},
  "geometry": {"coordinates":[7.7527871132,47.4760284424],"type":"Point"}
}