{
  "type": "Feature",
  "properties": {
    "iso:country":"CH",
    "sg:address":"Im Wiesengrund 9 8907 Wettswil. Postfach 123",
    "sg:city":"Wettswil",
    "sg:orig_category":"Herstellung von k\u00e4lte U lufttechnischen Erzeugnissen f\u00fcr gewerbliche Zwecke Installation von Heizung",
    "sg:phone":"+41 71 383 43 53",
    "sg:postcode":"8907",
    "sg:province":"Z\u00fcrich",
    "wof:name":"Bauer K\u00e4lte Und W\u00e4rme Gmbh Elektro, Heizungs, K\u00e4ltetechnische Installationen Usw",
    "wof:placetype":"venue"
},
  "geometry": {"coordinates":[9.2475709915,47.4125938416],"type":"Point"}
}