{
  "type": "Feature",
  "properties": {
    "iso:country":"CH",
    "sg:address":"Via Agli Orti 5",
    "sg:city":"Viganello",
    "sg:orig_category":"G\u00fcterbef\u00f6rderung im Strassenverkehr Sonstige Kurierdienste",
    "sg:postcode":"6962",
    "sg:province":"Ticino",
    "wof:name":"Frank Zimmermann Wiz Express",
    "wof:placetype":"venue"
},
  "geometry": {"coordinates":[6.124560833,46.2370758057],"type":"Point"}
}