{
  "type": "Feature",
  "properties": {
    "iso:country":"CH",
    "sg:address":"Via Campagna",
    "sg:city":"Lumino",
    "sg:orig_category":"Non-Classified Establishments",
    "sg:postcode":"6533",
    "sg:province":"Ticino",
    "wof:name":"Pudic Z. Transporte Gmbh",
    "wof:placetype":"venue"
},
  "geometry": {"coordinates":[8.0649843216,47.3898735046],"type":"Point"}
}