{
  "type": "Feature",
  "properties": {
    "iso:country":"CH",
    "sg:address":"Hauptstrasse 2",
    "sg:city":"Plaffeien",
    "sg:classifiers":[
        {
            "category":"Travel",
            "subcategory":"Hotels & Motels",
            "type":"Entertainment"
        }
    ],
    "sg:phone":"+41 26 419 11 13",
    "sg:postcode":"1716",
    "sg:province":"Fribourg",
    "sg:tags":[
        "hotels",
        "mit",
        "restaurant"
    ],
    "wof:name":"Piller Mario, Gasthof Zum Goldenen Kreuz",
    "wof:placetype":"venue"
},
  "geometry": {"coordinates":[7.2865347862,46.7426528931],"type":"Point"}
}