{
  "type": "Feature",
  "properties": {
    "iso:country":"CH",
    "sg:address":"Romont Rue De 17 1700 Fribourg. Postfach",
    "sg:city":"Freiburg",
    "sg:orig_category":"Detailhandel mit Schuhen U Lederwaren",
    "sg:postcode":"1700",
    "sg:province":"Fribourg",
    "wof:name":"Direct-shoes, D\u00e9nervaud C. Commerce Sur Internet De Chaussures Etc",
    "wof:placetype":"venue"
},
  "geometry": {"coordinates":[7.154747963,46.8048362732],"type":"Point"}
}