{
  "type": "Feature",
  "properties": {
    "iso:country":"CH",
    "sg:address":"Bahnhofstrasse 25",
    "sg:city":"Diessenhofen",
    "sg:classifiers":[
        {
            "category":"Banks & Credit Unions",
            "subcategory":"Bank",
            "type":"Services"
        }
    ],
    "sg:phone":"+41 4153373121",
    "sg:postcode":"8253",
    "sg:province":"Thurgau",
    "wof:name":"Thurgauer Kantonalbank",
    "wof:placetype":"venue"
},
  "geometry": {"coordinates":[8.753274,47.687046],"type":"Point"}
}