{
  "type": "Feature",
  "properties": {
    "iso:country":"CH",
    "sg:address":"B\u00fcntstrasse 8",
    "sg:city":"Dielsdorf",
    "sg:orig_category":"Glaserei",
    "sg:phone":"+41 18530313",
    "sg:postcode":"8157",
    "sg:province":"Z\u00fcrich",
    "wof:name":"Jakob Mettler Glaserei",
    "wof:placetype":"venue"
},
  "geometry": {"coordinates":[8.4576330185,47.4801139832],"type":"Point"}
}