{
  "type": "Feature",
  "properties": {
    "iso:country":"CH",
    "sg:address":"Kreuzweg Oberlangenegg",
    "sg:city":"Schwarzenegg",
    "sg:orig_category":"S\u00e4gewerke",
    "sg:phone":"+41 33 453 11 62",
    "sg:postcode":"3616",
    "sg:province":"Bern",
    "wof:name":"Stettler Holz Gmbh S\u00e4gerei & Holzhandlung",
    "wof:placetype":"venue"
},
  "geometry": {"coordinates":[7.7244100571,46.7934951782],"type":"Point"}
}