{
  "type": "Feature",
  "properties": {
    "iso:country":"CH",
    "sg:address":"Rebgasse 1",
    "sg:city":"Basel",
    "sg:orig_category":"Detailhandel mit Blumen U Pflanzen",
    "sg:phone":"+41 21 312 59 00",
    "sg:postcode":"4058",
    "sg:province":"Basel-Stadt",
    "wof:name":"Daniel Roulin",
    "wof:placetype":"venue"
},
  "geometry": {"coordinates":[6.630327,46.523464],"type":"Point"}
}