{
  "type": "Feature",
  "properties": {
    "iso:country":"CH",
    "sg:address":"Hauptstrasse 48",
    "sg:city":"Zurzach",
    "sg:orig_category":"Arztpraxen",
    "sg:phone":"+41 41 871 12 66",
    "sg:postcode":"5330",
    "sg:province":"Aargau",
    "wof:name":"Dr.med.heinrich Maillard Spezialarzt Fmh",
    "wof:placetype":"venue"
},
  "geometry": {"coordinates":[8.649326,46.874863],"type":"Point"}
}