{
  "type": "Feature",
  "properties": {
    "iso:country":"CH",
    "sg:address":"Salvatorstrasse 18",
    "sg:city":"Z\u00fcrich",
    "sg:orig_category":"Malerei",
    "sg:phone":"+41 13118523",
    "sg:postcode":"8050",
    "sg:province":"Z\u00fcrich",
    "wof:name":"Andreas Woltersdorf Malergesch\u00e4ft",
    "wof:placetype":"venue"
},
  "geometry": {"coordinates":[8.552939415,47.4070510864],"type":"Point"}
}