{
  "type": "Feature",
  "properties": {
    "iso:country":"CH",
    "sg:address":"7306",
    "sg:city":"Fl\u00e4sch",
    "sg:orig_category":"RESTAURANTS: TEA-ROOMS",
    "sg:phone":"+41 81 330 77 70",
    "sg:postcode":"7306",
    "sg:province":"Graubunden",
    "wof:name":"Herrmann Martin",
    "wof:placetype":"venue"
},
  "geometry": {"coordinates":[9.5131196976,47.0264663696],"type":"Point"}
}