{
  "type": "Feature",
  "properties": {
    "iso:country":"CH",
    "sg:address":"Chemin Du Coteau 6",
    "sg:city":"Nyon",
    "sg:orig_category":"Erbringung von sonstigen Dienstleistungen f\u00fcr Unterhaltung, Erholung U Freizeit",
    "sg:phone":"+41 22 361 36 65",
    "sg:postcode":"1260",
    "sg:province":"Vaud",
    "wof:name":"Institut De Beaut\u00e9 Canine Menoud Dani\u00e8le",
    "wof:placetype":"venue"
},
  "geometry": {"coordinates":[6.2390799522,46.3823661804],"type":"Point"}
}