{
  "type": "Feature",
  "properties": {
    "iso:country":"CH",
    "sg:address":"Am Bach 19",
    "sg:city":"Bilten",
    "sg:orig_category":"Wirtschaftspr\u00fcfung, Steuerberatung U Treuhand",
    "sg:phone":"+41 55 615 15 15",
    "sg:postcode":"8865",
    "sg:province":"Glarus",
    "wof:name":"Mtw-treuhand F\u00fcllemann",
    "wof:placetype":"venue"
},
  "geometry": {"coordinates":[9.0256443024,47.1500511169],"type":"Point"}
}