{
  "type": "Feature",
  "properties": {
    "iso:country":"CH",
    "sg:address":"Industriestr. 8",
    "sg:city":"Lyssach",
    "sg:orig_category":"Herstellung von elektronischen Bauelementen",
    "sg:phone":"+41 34 445 74 65",
    "sg:postcode":"3421",
    "sg:province":"Bern",
    "wof:name":"Demars Gmbh",
    "wof:placetype":"venue"
},
  "geometry": {"coordinates":[7.5945720673,47.0713615417],"type":"Point"}
}