{
  "type": "Feature",
  "properties": {
    "iso:country":"CH",
    "sg:address":"8542",
    "sg:city":"Wiesendangen",
    "sg:orig_category":"Organisationen des Gesundheitswesen",
    "sg:postcode":"8542",
    "sg:province":"Z\u00fcrich",
    "wof:name":"Samariterverein",
    "wof:placetype":"venue"
},
  "geometry": {"coordinates":[8.7863101959,47.5228881836],"type":"Point"}
}