{
  "type": "Feature",
  "properties": {
    "iso:country":"CH",
    "sg:address":"Jassbach",
    "sg:city":"Lindau",
    "sg:orig_category":"Allgemeiner Hoch U Tiefbau",
    "sg:postcode":"8315",
    "sg:province":"Z\u00fcrich",
    "wof:name":"Von Gunten Martin",
    "wof:placetype":"venue"
},
  "geometry": {"coordinates":[8.671449,47.441353],"type":"Point"}
}