{
  "type": "Feature",
  "properties": {
    "iso:country":"CH",
    "sg:address":"Rebackerstrasse 19",
    "sg:city":"Kerzers",
    "sg:orig_category":"Maler U Glasergewerbe Malerei",
    "sg:phone":"+41 31 755 66 54",
    "sg:postcode":"3210",
    "sg:province":"Fribourg",
    "wof:name":"Meyer Manfred",
    "wof:placetype":"venue"
},
  "geometry": {"coordinates":[7.2121338844,46.974811554],"type":"Point"}
}