{
  "type": "Feature",
  "properties": {
    "iso:country":"CH",
    "sg:address":"Unteres Ziel 3",
    "sg:city":"Appenzell",
    "sg:orig_category":"Detailhandel mit Parf\u00fcmerieartikeln U K\u00f6rperpflegemitteln Grosshandel mit Parf\u00fcmerieartikeln U K\u00f6rpe",
    "sg:phone":"+41 71 788 38 60",
    "sg:postcode":"9050",
    "sg:province":"Appenzell Innerhoden",
    "wof:name":"Parfima Sa",
    "wof:placetype":"venue"
},
  "geometry": {"coordinates":[9.4086341858,47.3347358704],"type":"Point"}
}