{
  "type": "Feature",
  "properties": {
    "iso:country":"CH",
    "sg:address":"Bettmeralp 3981 Blitzingen. Postfach",
    "sg:city":"Bettmeralp",
    "sg:orig_category":"Interessenvertretungen",
    "sg:postcode":"3992",
    "sg:province":"Valais",
    "wof:name":"Verein Aletsch-express, Bettmeralp-riederalp",
    "wof:placetype":"venue"
},
  "geometry": {"coordinates":[8.1907701492,46.4355049133],"type":"Point"}
}