{
  "type": "Feature",
  "properties": {
    "iso:country":"CH",
    "sg:address":"Schmidtenbaumgarten 27",
    "sg:city":"Oberlunkhofen",
    "sg:orig_category":"Werbung",
    "sg:phone":"+41 56 634 44 44",
    "sg:postcode":"8917",
    "sg:province":"Aargau",
    "wof:name":"Alsographic Gmbh",
    "wof:placetype":"venue"
},
  "geometry": {"coordinates":[8.3869953156,47.3141860962],"type":"Point"}
}