{
  "type": "Feature",
  "properties": {
    "iso:country":"CH",
    "sg:address":"Comacini Via Maestri 7",
    "sg:city":"Chiasso",
    "sg:orig_category":"Forschung U Entwicklung im Bereich der Naturwissenschaften",
    "sg:phone":"+41 91 683 01 34",
    "sg:postcode":"6830",
    "sg:province":"Ticino",
    "wof:name":"Newframe Ag, Vaduz, Succursale Di Chiasso",
    "wof:placetype":"venue"
},
  "geometry": {"coordinates":[9.0355348587,45.8352394104],"type":"Point"}
}