{
  "type": "Feature",
  "properties": {
    "iso:country":"CH",
    "sg:address":"Stationsstrasse 50",
    "sg:city":"Seuzach",
    "sg:orig_category":"Polizei",
    "sg:phone":"+41 52 335 29 19",
    "sg:postcode":"8472",
    "sg:province":"Z\u00fcrich",
    "wof:name":"Polizeiposten",
    "wof:placetype":"venue"
},
  "geometry": {"coordinates":[8.7387857437,47.5355682373],"type":"Point"}
}