{
  "type": "Feature",
  "properties": {
    "iso:country":"CH",
    "sg:address":"Industriestrasse 11",
    "sg:city":"Safnern",
    "sg:orig_category":"Herstellung von Betonerzeugnissen f\u00fcr den Bau",
    "sg:phone":"+41 41 497 17 27",
    "sg:postcode":"2553",
    "sg:province":"Bern",
    "wof:name":"Cavag Element- & Beh\u00e4lterbau Ag",
    "wof:placetype":"venue"
},
  "geometry": {"coordinates":[8.1334247589,47.0414505005],"type":"Point"}
}