{
  "type": "Feature",
  "properties": {
    "iso:country":"CH",
    "sg:address":"Avenue De Chamonix 7",
    "sg:city":"Gen\u00e8ve",
    "sg:classifiers":[
        {
            "category":"Professional",
            "subcategory":"Advertising",
            "type":"Services"
        }
    ],
    "sg:phone":"+41 22 786 70 00",
    "sg:postcode":"1207",
    "sg:province":"Gen\u00e8ve",
    "sg:tags":[
        "agency"
    ],
    "wof:name":"Hp Media S.a.",
    "wof:placetype":"venue"
},
  "geometry": {"coordinates":[6.16377,46.20097],"type":"Point"}
}