{
  "type": "Feature",
  "properties": {
    "iso:country":"CH",
    "sg:address":"Spycherweg 11",
    "sg:city":"Weggis",
    "sg:orig_category":"Handelsvermittlung U Grosshandel Sonstiger Grosshandel",
    "sg:phone":"+41 41 390 03 40",
    "sg:postcode":"6353",
    "sg:province":"Luzern",
    "wof:name":"Ekag Einkaufs Ag Giswil",
    "wof:placetype":"venue"
},
  "geometry": {"coordinates":[8.4381999969,47.0325012207],"type":"Point"}
}