{
  "type": "Feature",
  "properties": {
    "iso:country":"CH",
    "sg:address":"Quai De Versoix 2",
    "sg:city":"Versoix",
    "sg:orig_category":"Non-Classified Establishments",
    "sg:postcode":"1290",
    "sg:province":"Gen\u00e8ve",
    "wof:name":"Sauvetage Du L\u00e9man Section De Versoix",
    "wof:placetype":"venue"
},
  "geometry": {"coordinates":[6.170114994,46.276889801],"type":"Point"}
}