{
  "type": "Feature",
  "properties": {
    "addr:full":"Grimselstrasse Guttannen Bern 3864",
    "addr:postcode":"3864",
    "addr:street":"Grimselstrasse",
    "iso:country":"CH",
    "sg:address":"Grimselstrasse",
    "sg:city":"Guttannen",
    "sg:orig_category":"Bauschreinerei Herstellung von Konstruktionsteilen, Fertigbauteilen U Ausbauelementen aus Holz",
    "sg:phone":"+41 33 973 12 73",
    "sg:postcode":"3864",
    "sg:province":"Bern",
    "wof:name":"Rufibach & Schl\u00e4ppi Ag Schreinerei & Innenausbau",
    "wof:placetype":"venue"
},
  "geometry": {"coordinates":[8.289937,46.654659],"type":"Point"}
}