{
  "type": "Feature",
  "properties": {
    "iso:country":"CH",
    "sg:address":"Torgasse 8 8001 Z\u00fcrich. Postfach",
    "sg:city":"Z\u00fcrich",
    "sg:orig_category":"Herstellung von Seilerwaren Herstellung von sonstigen Gummiwaren",
    "sg:phone":"+41 12525834",
    "sg:postcode":"8024",
    "sg:province":"Z\u00fcrich",
    "wof:name":"Seilerei Denzler Ag Seilerwaren, Fischerei, Bootsartikel Usw.; Fabrikation, Handel",
    "wof:placetype":"venue"
},
  "geometry": {"coordinates":[8.5458040237,47.3680267334],"type":"Point"}
}