{
  "type": "Feature",
  "properties": {
    "iso:country":"CH",
    "sg:address":"Rue Des Erables 29",
    "sg:city":"Sion",
    "sg:orig_category":"Sanit\u00e4r, Heizungs U L\u00fcftungsinstallation Sanit\u00e4rinstallation",
    "sg:phone":"+41 79 321 18 26",
    "sg:postcode":"1950",
    "sg:province":"Valais",
    "wof:name":"L\u00e9ger R. Et Andr\u00e9 J. Sa",
    "wof:placetype":"venue"
},
  "geometry": {"coordinates":[7.3551778793,46.2282218933],"type":"Point"}
}