{
  "type": "Feature",
  "properties": {
    "iso:country":"CH",
    "sg:address":"Gampelengasse 64",
    "sg:city":"Ins",
    "sg:orig_category":"Sportvereine Turnen",
    "sg:phone":"+41 32 313 28 20",
    "sg:postcode":"3232",
    "sg:province":"Bern",
    "wof:name":"Turnverein Stv Br\u00fcttelen",
    "wof:placetype":"venue"
},
  "geometry": {"coordinates":[7.0919809341,47.0089111328],"type":"Point"}
}