{
  "type": "Feature",
  "properties": {
    "iso:country":"CH",
    "sg:address":"Unterm\u00fcli 9",
    "sg:city":"Zug",
    "sg:orig_category":"Architekturb\u00fcros",
    "sg:phone":"+41 41 760 39 39",
    "sg:postcode":"6300",
    "sg:province":"Zug",
    "wof:name":"M\u00fcller & Partner Zug Ag",
    "wof:placetype":"venue"
},
  "geometry": {"coordinates":[8.517763,47.180466],"type":"Point"}
}