{
  "type": "Feature",
  "properties": {
    "addr:full":"Haselweg 23 Zofingen Aargau 4800",
    "addr:housenumber":"23",
    "addr:postcode":"4800",
    "addr:street":"Haselweg",
    "iso:country":"CH",
    "sg:address":"Haselweg 23",
    "sg:city":"Zofingen",
    "sg:orig_category":"Datenverarbeitungsdienste Softwareentwicklung U beratung",
    "sg:phone":"+41 62 752 84 55",
    "sg:postcode":"4800",
    "sg:province":"Aargau",
    "wof:name":"Anapro Ag",
    "wof:placetype":"venue"
},
  "geometry": {"coordinates":[7.948305,47.278015],"type":"Point"}
}