{
  "type": "Feature",
  "properties": {
    "iso:country":"CH",
    "sg:address":"Weidlistrasse 8",
    "sg:city":"Zweisimmen",
    "sg:orig_category":"Interessenvertretungen",
    "sg:postcode":"3770",
    "sg:province":"Bern",
    "wof:name":"Dr. Eduard Bloesch-stiftung",
    "wof:placetype":"venue"
},
  "geometry": {"coordinates":[7.3683171272,46.5576057434],"type":"Point"}
}