{
  "type": "Feature",
  "properties": {
    "iso:country":"CH",
    "sg:address":"Tavannes Route De 44",
    "sg:city":"Reconvilier",
    "sg:orig_category":"Softwareentwicklung U beratung",
    "sg:postcode":"2732",
    "sg:province":"Bern",
    "wof:name":"Atomic, Siegrist Daniel",
    "wof:placetype":"venue"
},
  "geometry": {"coordinates":[7.2178001404,47.2330322266],"type":"Point"}
}