{
  "type": "Feature",
  "properties": {
    "iso:country":"CH",
    "sg:address":"Rue De La Tournelle 22",
    "sg:city":"Orbe",
    "sg:orig_category":"G\u00fcterbef\u00f6rderung im Strassenverkehr",
    "sg:phone":"+41 24 441 72 02",
    "sg:postcode":"1350",
    "sg:province":"Vaud",
    "wof:name":"Rochat Daniel",
    "wof:placetype":"venue"
},
  "geometry": {"coordinates":[6.5365481377,46.7235145569],"type":"Point"}
}