{
  "type": "Feature",
  "properties": {
    "addr:full":"Rue Pr\u00e9-de-la-reine 7 Cartigny Gen\u00e8ve 1236",
    "addr:housenumber":"7",
    "addr:postcode":"1236",
    "addr:street":"Rue Pre\u0301-De-La-Reine",
    "iso:country":"CH",
    "sg:address":"Rue Pr\u00e9-de-la-reine 7",
    "sg:city":"Cartigny",
    "sg:classifiers":[
        {
            "category":"Banks & Credit Unions",
            "subcategory":"Bank",
            "type":"Services"
        }
    ],
    "sg:phone":"+41 27 458 27 42",
    "sg:postcode":"1236",
    "sg:province":"Gen\u00e8ve",
    "wof:name":"Banque Raiffeisen Chalais-vercorin",
    "wof:placetype":"venue"
},
  "geometry": {"coordinates":[7.50545,46.265469],"type":"Point"}
}