{
  "type": "Feature",
  "properties": {
    "iso:country":"CH",
    "sg:address":"Alleestrasse 4 8734 Ermenswil. Postfach",
    "sg:city":"Ermenswil",
    "sg:orig_category":"Zimmerei, Dachdeckerei, Bauspenglerei U Abdichtung",
    "sg:postcode":"8734",
    "sg:province":"St. Gallen",
    "wof:name":"Bsb Bauspenglerei Gmbh",
    "wof:placetype":"venue"
},
  "geometry": {"coordinates":[8.8831911087,47.2473983765],"type":"Point"}
}