{
  "type": "Feature",
  "properties": {
    "iso:country":"CH",
    "sg:address":"Alte Landstrasse 11 4456 Tenniken. Postfach",
    "sg:city":"Tenniken",
    "sg:orig_category":"Grosshandel mit Nahrungsmitteln, Getr\u00e4nken U Tabakwaren ohne ausgepr\u00e4gten Schwerpunkt",
    "sg:postcode":"4456",
    "sg:province":"Basel-Landschaft",
    "wof:name":"Sch\u00fcrch + Zwygart Gmbh Lebensmittel; Handel U. Verkauf",
    "wof:placetype":"venue"
},
  "geometry": {"coordinates":[7.8114848137,47.4372787476],"type":"Point"}
}