{
  "type": "Feature",
  "properties": {
    "iso:country":"CH",
    "sg:address":"Liebr\u00fctistrasse 39",
    "sg:city":"Kaiseraugst",
    "sg:orig_category":"Fachdetailhandel mit pharmazeutischen Produkten",
    "sg:phone":"+41 61 811 42 84",
    "sg:postcode":"4303",
    "sg:province":"Aargau",
    "wof:name":"Apotheke Liebr\u00fcti Dres. Ursula + Ulrich Junod",
    "wof:placetype":"venue"
},
  "geometry": {"coordinates":[7.7305221558,47.53515625],"type":"Point"}
}