{
  "type": "Feature",
  "properties": {
    "iso:country":"CH",
    "sg:address":"Dorfstrasse 54",
    "sg:city":"Embrach",
    "sg:orig_category":"Drogerien Sonstiger Fachdetailhandel mit Nahrungsmitteln, Getr\u00e4nken U Tabak in Verkaufsr\u00e4umen",
    "sg:phone":"+41 18650177",
    "sg:postcode":"8424",
    "sg:province":"Z\u00fcrich",
    "wof:name":"Drogerie Weidmann Doris",
    "wof:placetype":"venue"
},
  "geometry": {"coordinates":[8.5941877365,47.5047111511],"type":"Point"}
}