{
  "type": "Feature",
  "properties": {
    "iso:country":"CH",
    "sg:address":"Pr\u00e9-bouvier Rue Du 27",
    "sg:city":"Satigny",
    "sg:orig_category":"Softwareentwicklung U beratung",
    "sg:phone":"+41 22820477",
    "sg:postcode":"1242",
    "sg:province":"Gen\u00e8ve",
    "wof:name":"Intellart Sa",
    "wof:placetype":"venue"
},
  "geometry": {"coordinates":[6.0330247879,46.2154884338],"type":"Point"}
}