{
  "type": "Feature",
  "properties": {
    "iso:country":"CH",
    "sg:address":"Bellerivestrasse 29",
    "sg:city":"Z\u00fcrich",
    "sg:orig_category":"Unclassifiable Establishments",
    "sg:phone":"+41 1524841",
    "sg:postcode":"8008",
    "sg:province":"Z\u00fcrich",
    "wof:name":"Cobral Holding Ag",
    "wof:placetype":"venue"
},
  "geometry": {"coordinates":[8.5501403809,47.3585395813],"type":"Point"}
}