{
  "type": "Feature",
  "properties": {
    "iso:country":"CH",
    "sg:address":"Bahnhofstrasse 15",
    "sg:city":"Sursee",
    "sg:orig_category":"Arztpraxen",
    "sg:phone":"+41 55 415 80 20",
    "sg:postcode":"6210",
    "sg:province":"Luzern",
    "wof:name":"Chirurgische Praxis Cityhaus",
    "wof:placetype":"venue"
},
  "geometry": {"coordinates":[8.778928,47.201492],"type":"Point"}
}