{
  "type": "Feature",
  "properties": {
    "iso:country":"CH",
    "sg:address":"3417",
    "sg:city":"R\u00fcegsau",
    "sg:orig_category":"Sportvereine Sch\u00fctzen",
    "sg:phone":"+41 62 964 13 84",
    "sg:postcode":"3417",
    "sg:province":"Bern",
    "wof:name":"Feldsch\u00fctzengesellschaft",
    "wof:placetype":"venue"
},
  "geometry": {"coordinates":[7.679599762,47.0273208618],"type":"Point"}
}