{
  "type": "Feature",
  "properties": {
    "iso:country":"CH",
    "sg:address":"B\u00e4renburg",
    "sg:city":"Andeer",
    "sg:orig_category":"Elektrizit\u00e4tsversorgung",
    "sg:phone":"+41 81 651 18 33",
    "sg:postcode":"7440",
    "sg:province":"Graubunden",
    "wof:name":"Kraftwerke Hinterrhein Ag",
    "wof:placetype":"venue"
},
  "geometry": {"coordinates":[9.4280443192,46.580165863],"type":"Point"}
}