{
  "type": "Feature",
  "properties": {
    "iso:country":"CH",
    "sg:address":"Maladi\u00e8re Rue De La 83 2000 Neuenburg. Postfach",
    "sg:city":"Neuch\u00e2tel",
    "sg:orig_category":"Detailhandel mit Metallwaren, Anstrichmitteln, Glaswaren, Bau U Heimwerkerbedarf",
    "sg:postcode":"2000",
    "sg:province":"Neuch\u00e2tel",
    "wof:name":"Colibrys Sa Produits Microtechniques Etc.; Fabrication \u00e9galement En Sous-traitance, Achat, Vente Et Distribution",
    "wof:placetype":"venue"
},
  "geometry": {"coordinates":[6.9474377632,46.9974937439],"type":"Point"}
}