{
  "type": "Feature",
  "properties": {
    "iso:country":"CH",
    "sg:address":"Uitikonerstrasse 4",
    "sg:city":"Schlieren",
    "sg:orig_category":"Arztpraxen",
    "sg:phone":"+41 17307648",
    "sg:postcode":"8952",
    "sg:province":"Z\u00fcrich",
    "wof:name":"Dr.med.doris Br\u00fchlmeier Spezial\u00e4rztin Fmh",
    "wof:placetype":"venue"
},
  "geometry": {"coordinates":[8.447866,47.396915],"type":"Point"}
}