{
  "type": "Feature",
  "properties": {
    "iso:country":"CH",
    "sg:address":"1510 Moudon. Postfach",
    "sg:city":"Moudon",
    "sg:orig_category":"G\u00fcterbef\u00f6rderung im Strassenverkehr",
    "sg:phone":"+41 21 784 22 92",
    "sg:postcode":"1510",
    "sg:province":"Vaud",
    "wof:name":"Faucherre Transports Sa",
    "wof:placetype":"venue"
},
  "geometry": {"coordinates":[6.8003668785,46.6674957275],"type":"Point"}
}