{
  "type": "Feature",
  "properties": {
    "iso:country":"CH",
    "sg:address":"Grand-rue 82",
    "sg:city":"Ch\u00e9zard-st-martin",
    "sg:orig_category":"Herstellung von keramischen Haushaltswaren U Ziergegenst\u00e4nden",
    "sg:phone":"+41 32 853 27 55",
    "sg:postcode":"2054",
    "sg:province":"Neuch\u00e2tel",
    "wof:name":"Poterie De Saint-martin",
    "wof:placetype":"venue"
},
  "geometry": {"coordinates":[6.9324131012,47.0659675598],"type":"Point"}
}