{
  "type": "Feature",
  "properties": {
    "iso:country":"CH",
    "sg:address":"Viale C. Olgiati 23",
    "sg:city":"Giubiasco",
    "sg:orig_category":"Sonstiger Grosshandel",
    "sg:phone":"+41 91 857 51 77",
    "sg:postcode":"6512",
    "sg:province":"Ticino",
    "wof:name":"Sperolini Giuseppe",
    "wof:placetype":"venue"
},
  "geometry": {"coordinates":[9.016295433,46.1804924011],"type":"Point"}
}