{
  "type": "Feature",
  "properties": {
    "iso:country":"CH",
    "sg:address":"Hauptstrasse 54",
    "sg:city":"Nidau",
    "sg:orig_category":"Interessenvertretungen",
    "sg:postcode":"2560",
    "sg:province":"Bern",
    "wof:name":"Nidauer Chlouserbletter",
    "wof:placetype":"venue"
},
  "geometry": {"coordinates":[7.2411799431,47.124004364],"type":"Point"}
}