{
  "type": "Feature",
  "properties": {
    "iso:country":"CH",
    "sg:address":"La Fayaulaz 257",
    "sg:city":"Villarepos",
    "sg:orig_category":"Fernmeldedienste Herstellung von sonstigen elektrischen Ausr\u00fcstungen",
    "sg:phone":"+41 26 676 06 06",
    "sg:postcode":"1583",
    "sg:province":"Fribourg",
    "wof:name":"Schneider Daniel T\u00e9l\u00e9communication",
    "wof:placetype":"venue"
},
  "geometry": {"coordinates":[7.0773458481,46.8856277466],"type":"Point"}
}