{
  "type": "Feature",
  "properties": {
    "iso:country":"CH",
    "sg:address":"Remisbergstrasse 14",
    "sg:city":"Kreuzlingen",
    "sg:orig_category":"Grosshandel mit Getr\u00e4nken",
    "sg:postcode":"8280",
    "sg:province":"Thurgau",
    "wof:name":"Schweizer Jean-pierre",
    "wof:placetype":"venue"
},
  "geometry": {"coordinates":[6.1413488388,46.1823997498],"type":"Point"}
}