{
  "type": "Feature",
  "properties": {
    "iso:country":"CH",
    "sg:address":"Avenue De Lo\u00ebs 1bis",
    "sg:city":"Aigle",
    "sg:orig_category":"Bestattungswesen",
    "sg:phone":"+41 24 466 38 34",
    "sg:postcode":"1860",
    "sg:province":"Vaud",
    "wof:name":"Dominique Croset S\u00e0rl Pompes Fun\u00e8bres",
    "wof:placetype":"venue"
},
  "geometry": {"coordinates":[6.9675951004,46.3160362244],"type":"Point"}
}