{
  "type": "Feature",
  "properties": {
    "iso:country":"CH",
    "sg:address":"Reussstrasse 6",
    "sg:city":"Gisikon",
    "sg:orig_category":"Detailhandel mit elektrischen Haushalts-,Radio U Fernsehger\u00e4ten sowie Musikinstrumenten",
    "sg:phone":"+41 77415052",
    "sg:postcode":"6038",
    "sg:province":"Luzern",
    "wof:name":"Von B\u00fcren Theo",
    "wof:placetype":"venue"
},
  "geometry": {"coordinates":[8.3978853226,47.1257781982],"type":"Point"}
}