{
  "type": "Feature",
  "properties": {
    "iso:country":"CH",
    "sg:address":"Feldstrasse 7",
    "sg:city":"Thalwil",
    "sg:orig_category":"Grosshandel mit sonstigen Maschinen U Ausr\u00fcstungen f\u00fcr Industrie, Handel U Schiffahrt",
    "sg:postcode":"8800",
    "sg:province":"Z\u00fcrich",
    "wof:name":"Wetterwald W. A. & Co",
    "wof:placetype":"venue"
},
  "geometry": {"coordinates":[8.563744545,47.2920303345],"type":"Point"}
}