{
  "type": "Feature",
  "properties": {
    "iso:country":"CH",
    "sg:address":"Allmendhubel 590",
    "sg:city":"Schwarzenburg",
    "sg:orig_category":"Erdbewegungsarbeiten Strassenbau",
    "sg:phone":"+41 31 731 14 56",
    "sg:postcode":"3150",
    "sg:province":"Bern",
    "wof:name":"K\u00e4stli Ag Bauunternehmung",
    "wof:placetype":"venue"
},
  "geometry": {"coordinates":[7.3527169228,46.8267326355],"type":"Point"}
}