{
  "type": "Feature",
  "properties": {
    "addr:full":"Breitenbachstrasse 76 B\u00fcsserach Solothurn 4227",
    "addr:housenumber":"76;4227",
    "addr:street":"Breitenbachstrasse;Solothurn",
    "iso:country":"CH",
    "sg:address":"Breitenbachstrasse 76",
    "sg:city":"B\u00fcsserach",
    "sg:orig_category":"Allgemeiner Hoch U Tiefbau Allgemeiner Hochbau",
    "sg:phone":"+41 17840740",
    "sg:postcode":"4227",
    "sg:province":"Solothurn",
    "wof:name":"Baugesch\u00e4ft M\u00fcller Willy Ag",
    "wof:placetype":"venue"
},
  "geometry": {"coordinates":[8.735241,47.203506],"type":"Point"}
}