{
  "type": "Feature",
  "properties": {
    "iso:country":"CH",
    "sg:address":"Pl\u00e4nkestrasse 31",
    "sg:city":"Biel/bienne",
    "sg:orig_category":"Zahnarztpraxen",
    "sg:phone":"+41 32 322 20 88",
    "sg:postcode":"2502",
    "sg:province":"Bern",
    "wof:name":"Dr. Med. Dent. Gerhard Thomke Zahnarzt",
    "wof:placetype":"venue"
},
  "geometry": {"coordinates":[7.2450537682,47.137512207],"type":"Point"}
}