{
  "type": "Feature",
  "properties": {
    "iso:country":"CH",
    "sg:address":"8411 Winterthur. Postfach 5274",
    "sg:city":"Winterthur",
    "sg:orig_category":"Campingpl\u00e4tze",
    "sg:phone":"+41 33 951 18 43",
    "sg:postcode":"8411",
    "sg:province":"Z\u00fcrich",
    "wof:name":"Zysset-fuchs Irene",
    "wof:placetype":"venue"
},
  "geometry": {"coordinates":[8.048863,46.747787],"type":"Point"}
}