{
  "type": "Feature",
  "properties": {
    "iso:country":"CH",
    "sg:address":"Sihlbruggstrasse 105a 6340 Baar. Postfach 450",
    "sg:city":"Baar",
    "sg:orig_category":"Sonstiges Druckgewerbe",
    "sg:phone":"+41 41 767 76 66",
    "sg:postcode":"6341",
    "sg:province":"Zug",
    "wof:name":"Pyramis Ag Digitale Drucktechnik",
    "wof:placetype":"venue"
},
  "geometry": {"coordinates":[8.5390930176,47.1977767944],"type":"Point"}
}