{
  "type": "Feature",
  "properties": {
    "iso:country":"CH",
    "sg:address":"Oberfeldstrasse 26",
    "sg:city":"Kloten",
    "sg:classifiers":[
        {
            "category":"Building & Trades",
            "subcategory":"Electrical",
            "type":"Services"
        }
    ],
    "sg:phone":"+41 43 255 50 00",
    "sg:postcode":"8302",
    "sg:province":"Z\u00fcrich",
    "sg:tags":[
        "installation"
    ],
    "wof:name":"Atel Elektroanlagen K + M Ag",
    "wof:placetype":"venue"
},
  "geometry": {"coordinates":[8.5958023071,47.4481201172],"type":"Point"}
}