{
  "type": "Feature",
  "properties": {
    "iso:country":"CH",
    "sg:address":"Theilingerstrasse 18 Theilingen 8484 Weisslingen. Postfach",
    "sg:city":"Weisslingen",
    "sg:orig_category":"RESTAURANTS: TEA-ROOMS",
    "sg:postcode":"8484",
    "sg:province":"Z\u00fcrich",
    "wof:name":"Restaurant Post, Alitaj",
    "wof:placetype":"venue"
},
  "geometry": {"coordinates":[8.7921962738,47.3190307617],"type":"Point"}
}