{
  "type": "Feature",
  "properties": {
    "iso:country":"CH",
    "sg:address":"Poststrasse 6 9113 Degersheim. Postfach",
    "sg:city":"Degersheim",
    "sg:orig_category":"Versicherungen Hauptagenturen",
    "sg:phone":"+41 79 357 78 87",
    "sg:postcode":"9113",
    "sg:province":"St. Gallen",
    "wof:name":"Helvetia Patria Versicherungen Regionalvertretung",
    "wof:placetype":"venue"
},
  "geometry": {"coordinates":[9.1977453232,47.3723983765],"type":"Point"}
}