{
  "type": "Feature",
  "properties": {
    "iso:country":"CH",
    "sg:address":"Chemin Des Chambrettes 8",
    "sg:city":"Tolochenaz",
    "sg:orig_category":"Vermietung von Automobilen",
    "sg:postcode":"1131",
    "sg:province":"Vaud",
    "wof:name":"New Bleu Ciel Sa",
    "wof:placetype":"venue"
},
  "geometry": {"coordinates":[6.472258091,46.4987258911],"type":"Point"}
}