{
  "type": "Feature",
  "properties": {
    "iso:country":"CH",
    "sg:address":"Chemin Des Fl\u00e9oles 28 2500 Biel/bienne. Postfach",
    "sg:city":"Biel/bienne",
    "sg:orig_category":"Grosshandel mit Nahrungsmitteln, Getr\u00e4nken U Tabakwaren ohne ausgepr\u00e4gten Schwerpunkt",
    "sg:postcode":"2503",
    "sg:province":"Bern",
    "wof:name":"Rebetez Philippe, D\u00e9positaire",
    "wof:placetype":"venue"
},
  "geometry": {"coordinates":[7.2569861412,47.1259803772],"type":"Point"}
}