{
  "type": "Feature",
  "properties": {
    "addr:full":"Ammerswilerstrasse 2 Dottikon Aargau 5605",
    "addr:housenumber":"2",
    "addr:postcode":"5605",
    "addr:street":"Ammerswilerstrasse",
    "iso:country":"CH",
    "sg:address":"Ammerswilerstrasse 2",
    "sg:city":"Dottikon",
    "sg:orig_category":"Bezirks, Sekundar, Realschulen, Oberstufe der Primarschulen",
    "sg:phone":"+41 71 385 21 33",
    "sg:postcode":"5605",
    "sg:province":"Aargau",
    "wof:name":"Sekundarschule Rosenau",
    "wof:placetype":"venue"
},
  "geometry": {"coordinates":[9.25489,47.42202],"type":"Point"}
}