{
  "type": "Feature",
  "properties": {
    "iso:country":"CH",
    "sg:address":"D\u00e9l\u00e8ze Rue De La 11",
    "sg:city":"Martigny",
    "sg:orig_category":"Herstellung von medizinischen U chirurgischen Ger\u00e4ten sowie orthop\u00e4dischen Vorrichtungen",
    "sg:postcode":"1920",
    "sg:province":"Valais",
    "wof:name":"Espace 3000 Fernandez-da Silva Deolinda Maria",
    "wof:placetype":"venue"
},
  "geometry": {"coordinates":[7.0729198456,46.1013793945],"type":"Point"}
}