{
  "type": "Feature",
  "properties": {
    "iso:country":"CH",
    "sg:address":"Robinsonweg 21 3006 Bern. Postfach",
    "sg:city":"Bern",
    "sg:orig_category":"Erbringung von Dienstleistungen f\u00fcr Unternehmen Sonstige mit der Informatik verbundene T\u00e4tigkeiten",
    "sg:phone":"+41 31 941 04 04",
    "sg:postcode":"3005",
    "sg:province":"Bern",
    "wof:name":"Bug Biologie Umweltdaten Gis Feller Burri Franziska Dienstleistungen In D. Ber. Geographische Informationssysteme, Datenbanken Usw.",
    "wof:placetype":"venue"
},
  "geometry": {"coordinates":[7.4822487831,46.9459075928],"type":"Point"}
}