{
  "type": "Feature",
  "properties": {
    "iso:country":"CH",
    "sg:address":"Route De L'industrie 15",
    "sg:city":"Vouvry",
    "sg:orig_category":"Bauschreinerei Herstellung von Konstruktionsteilen, Fertigbauteilen U Ausbauelementen aus Holz",
    "sg:phone":"+41 24 481 21 86",
    "sg:postcode":"1896",
    "sg:province":"Valais",
    "wof:name":"Menuiserie Artisanale De Conte Et Monte Sa",
    "wof:placetype":"venue"
},
  "geometry": {"coordinates":[6.89457,46.332821],"type":"Point"}
}