{
  "type": "Feature",
  "properties": {
    "iso:country":"CH",
    "sg:address":"Neugasse 6",
    "sg:city":"Z\u00fcrich",
    "sg:orig_category":"Architektur U Ingenieurb\u00fcros",
    "sg:phone":"+41 14403455",
    "sg:postcode":"8005",
    "sg:province":"Z\u00fcrich",
    "wof:name":"Othmar Sch\u00e4ublin Dipl. Architekt Eth/sia",
    "wof:placetype":"venue"
},
  "geometry": {"coordinates":[8.532008,47.381363],"type":"Point"}
}