{
  "type": "Feature",
  "properties": {
    "iso:country":"CH",
    "sg:address":"Looslistrasse 15",
    "sg:city":"Bern",
    "sg:orig_category":"Sonstiger Grosshandel",
    "sg:phone":"+41 41 630 35 75",
    "sg:postcode":"3027",
    "sg:province":"Bern",
    "wof:name":"Plima-cop Ag",
    "wof:placetype":"venue"
},
  "geometry": {"coordinates":[8.3142662048,46.9925308228],"type":"Point"}
}