{
  "type": "Feature",
  "properties": {
    "iso:country":"CH",
    "sg:address":"Hauptstrasse 17",
    "sg:city":"Wolfenschiessen",
    "sg:orig_category":"Detailhandel mit Schreib U Papeteriewaren",
    "sg:phone":"+41 71 333 10 80",
    "sg:postcode":"6386",
    "sg:province":"Nidwalden",
    "wof:name":"Markwalder & Co Ag",
    "wof:placetype":"venue"
},
  "geometry": {"coordinates":[9.3886165619,47.3907699585],"type":"Point"}
}