{
  "type": "Feature",
  "properties": {
    "iso:country":"CH",
    "sg:address":"Lindauerstrasse 31",
    "sg:city":"N\u00fcrensdorf",
    "sg:orig_category":"Architektur U Ingenieurb\u00fcros",
    "sg:postcode":"8309",
    "sg:province":"Z\u00fcrich",
    "wof:name":"Architekturb\u00fcro Langhart",
    "wof:placetype":"venue"
},
  "geometry": {"coordinates":[8.65159,47.444469],"type":"Point"}
}