{
  "type": "Feature",
  "properties": {
    "iso:country":"CH",
    "sg:address":"Route De Villarepos 16",
    "sg:city":"Donatyre",
    "sg:orig_category":"Architektur U Ingenieurb\u00fcros Architekturb\u00fcros",
    "sg:phone":"+41 21 671 14 60",
    "sg:postcode":"1582",
    "sg:province":"Vaud",
    "wof:name":"Arcature Atelier De R\u00e9alisation Et Conception D'architecture",
    "wof:placetype":"venue"
},
  "geometry": {"coordinates":[6.581895,46.530563],"type":"Point"}
}