{
  "type": "Feature",
  "properties": {
    "iso:country":"CH",
    "sg:address":"Sch\u00fctzengasse 43",
    "sg:city":"Biel/bienne",
    "sg:orig_category":"Architektur U Ingenieurb\u00fcros",
    "sg:phone":"+41 32 323 66 66",
    "sg:postcode":"2502",
    "sg:province":"Bern",
    "wof:name":"Bauformat G\u00e4umann-spavetti Daniel",
    "wof:placetype":"venue"
},
  "geometry": {"coordinates":[7.24868,47.144882],"type":"Point"}
}