{
  "type": "Feature",
  "properties": {
    "iso:country":"CH",
    "sg:address":"Zofingerstrasse 20",
    "sg:city":"Oftringen",
    "sg:orig_category":"Autogaragen",
    "sg:phone":"+41 17154311",
    "sg:postcode":"4665",
    "sg:province":"Aargau",
    "wof:name":"Thomas Fehr",
    "wof:placetype":"venue"
},
  "geometry": {"coordinates":[8.541044,47.333313],"type":"Point"}
}