{
  "type": "Feature",
  "properties": {
    "addr:full":"Seegartenstrasse 90 Horgen Z\u00fcrich 8810",
    "addr:housenumber":"90",
    "addr:postcode":"8810",
    "addr:street":"Seegartenstrasse",
    "iso:country":"CH",
    "sg:address":"Seegartenstrasse 90",
    "sg:city":"Horgen",
    "sg:orig_category":"Abwasserreinigung",
    "sg:phone":"+41 17251418",
    "sg:postcode":"8810",
    "sg:province":"Z\u00fcrich",
    "wof:name":"Kl\u00e4ranlage Der Gemeinde Horgen",
    "wof:placetype":"venue"
},
  "geometry": {"coordinates":[8.588268,47.267693],"type":"Point"}
}