{
  "type": "Feature",
  "properties": {
    "iso:country":"CH",
    "sg:address":"3966",
    "sg:city":"Chalais",
    "sg:orig_category":"Verlegen von Fliesen U Platten",
    "sg:phone":"+41 52 741 14 19",
    "sg:postcode":"3966",
    "sg:province":"Valais",
    "wof:name":"August Scherrer Ofenbau & Plattenbel\u00e4ge",
    "wof:placetype":"venue"
},
  "geometry": {"coordinates":[8.849190712,47.6655006409],"type":"Point"}
}