{
  "type": "Feature",
  "properties": {
    "addr:full":"Hauptstrasse 64 Herznach Aargau 5027",
    "addr:housenumber":"64",
    "addr:postcode":"5027",
    "addr:street":"Hauptstrasse",
    "iso:country":"CH",
    "sg:address":"Hauptstrasse 64",
    "sg:city":"Herznach",
    "sg:orig_category":"Autogaragen",
    "sg:phone":"+41 79 210 14 29",
    "sg:postcode":"5027",
    "sg:province":"Aargau",
    "wof:name":"Garage M\u00fcller",
    "wof:placetype":"venue"
},
  "geometry": {"coordinates":[8.052718,47.471832],"type":"Point"}
}