{
  "type": "Feature",
  "properties": {
    "iso:country":"CH",
    "sg:address":"Waisenhausstrasse 22",
    "sg:city":"Solothurn",
    "sg:orig_category":"Gartenbau Landschaftsplanungsb\u00fcros U Gartenarchitekturb\u00fcros",
    "sg:phone":"+41 32 622 48 50",
    "sg:postcode":"4500",
    "sg:province":"Solothurn",
    "wof:name":"Gassler Franz",
    "wof:placetype":"venue"
},
  "geometry": {"coordinates":[7.5324840546,47.2188186646],"type":"Point"}
}