{
  "type": "Feature",
  "properties": {
    "addr:full":"Ringstrasse 34 7000 Chur. Postfach Chur Graubunden 7004",
    "addr:housenumber":"34",
    "addr:postcode":"7000;postfach;7004",
    "addr:street":"Ringstrasse",
    "iso:country":"CH",
    "sg:address":"Ringstrasse 34 7000 Chur. Postfach",
    "sg:city":"Chur",
    "sg:orig_category":"Aktivit\u00e4ten der Generalunternehmen im Baugewerbe Baugewerbe",
    "sg:phone":"+41 81 286 60 20",
    "sg:postcode":"7004",
    "sg:province":"Graubunden",
    "wof:name":"Mobag Ag",
    "wof:placetype":"venue"
},
  "geometry": {"coordinates":[9.513987,46.853527],"type":"Point"}
}