{
  "type": "Feature",
  "properties": {
    "iso:country":"CH",
    "sg:address":"Jurastrasse 34 4912 Aarwangen. Postfach",
    "sg:city":"Aarwangen",
    "sg:orig_category":"Unclassifiable Establishments",
    "sg:phone":"+41 62 922 22 73",
    "sg:postcode":"4912",
    "sg:province":"Bern",
    "wof:name":"Arm Franziska, Schlossdrogerie",
    "wof:placetype":"venue"
},
  "geometry": {"coordinates":[7.7669010162,47.2427177429],"type":"Point"}
}