{
  "type": "Feature",
  "properties": {
    "iso:country":"CH",
    "sg:address":"Hauptstrasse 40",
    "sg:city":"Muttenz",
    "sg:orig_category":"Herstellung von Elektromotoren, Generatoren U Transformatoren",
    "sg:postcode":"4132",
    "sg:province":"Basel-Landschaft",
    "wof:name":"Des Deutsche Energiesystem Service Ag",
    "wof:placetype":"venue"
},
  "geometry": {"coordinates":[7.6465229988,47.5247268677],"type":"Point"}
}