{
  "type": "Feature",
  "properties": {
    "iso:country":"CH",
    "sg:address":"Alosenstrasse 7 6315 Ober\u00e4geri. Postfach",
    "sg:city":"Ober\u00e4geri",
    "sg:classifiers":[
        {
            "category":"Professional",
            "subcategory":"Employment Agencies",
            "type":"Services"
        }
    ],
    "sg:postcode":"6315",
    "sg:province":"Zug",
    "sg:tags":[
        "personal",
        "u",
        "stellenvermittlung"
    ],
    "wof:name":"Birchler Bau & Handel Gmbh",
    "wof:placetype":"venue"
},
  "geometry": {"coordinates":[8.6166410446,47.1385002136],"type":"Point"}
}