{
  "type": "Feature",
  "properties": {
    "iso:country":"CH",
    "sg:address":"Davidsbodenstrasse 62",
    "sg:city":"Basel",
    "sg:orig_category":"Wirtschaftspr\u00fcfung, Steuerberatung U Treuhand",
    "sg:phone":"+41 61 751 36 40",
    "sg:postcode":"4056",
    "sg:province":"Basel-Stadt",
    "wof:name":"Treuhandb\u00fcro Fabbri G. Treuhandarbeiten, Bes. Buchhaltungen, Steuererkl\u00e4rungen, Revisionen",
    "wof:placetype":"venue"
},
  "geometry": {"coordinates":[7.5915808678,47.4756202698],"type":"Point"}
}