{
  "type": "Feature",
  "properties": {
    "iso:country":"CH",
    "sg:address":"Dorf",
    "sg:city":"Hemberg",
    "sg:orig_category":"Landesverteidigung, Sozialversicherung \u00d6ffentliche Verwaltung",
    "sg:phone":"+41 71 378 60 30",
    "sg:postcode":"9633",
    "sg:province":"St. Gallen",
    "wof:name":"Zivilschutzstelle Hemberg",
    "wof:placetype":"venue"
},
  "geometry": {"coordinates":[9.1755647659,47.3005752563],"type":"Point"}
}