{
  "type": "Feature",
  "properties": {
    "iso:country":"CH",
    "sg:address":"Rietbr\u00fcelstrasse",
    "sg:city":"Wangs",
    "sg:orig_category":"Malerei-Gipserei Stukkateurgewerbe, Gipserei U Verputzerei",
    "sg:phone":"+41 81 723 42 04",
    "sg:postcode":"7323",
    "sg:province":"St. Gallen",
    "wof:name":"Antonio Manco Gipsergesch\u00e4ft",
    "wof:placetype":"venue"
},
  "geometry": {"coordinates":[9.4327096939,47.0362167358],"type":"Point"}
}