{
  "type": "Feature",
  "properties": {
    "iso:country":"CH",
    "sg:address":"La Crausaz",
    "sg:city":"Vuissens",
    "sg:orig_category":"Grosshandel mit Holz U Bauelementen aus Holz S\u00e4gewerke",
    "sg:phone":"+41 21 903 12 77",
    "sg:postcode":"1486",
    "sg:province":"Fribourg",
    "wof:name":"Genus Sa Commerce Bois Impr\u00e9gn\u00e9s",
    "wof:placetype":"venue"
},
  "geometry": {"coordinates":[6.7882099152,46.6043624878],"type":"Point"}
}