{
  "type": "Feature",
  "properties": {
    "iso:country":"CH",
    "sg:address":"Grubenstrasse 2 8045 Z\u00fcrich. Postfach",
    "sg:city":"Z\u00fcrich",
    "sg:orig_category":"Zimmerei, Ingenieurholzbau",
    "sg:phone":"+41 14621233",
    "sg:postcode":"8045",
    "sg:province":"Z\u00fcrich",
    "wof:name":"St\u00e4ubli Willy Ingenieur Ag Unternehmung F\u00fcr Holz Und Wasserbau",
    "wof:placetype":"venue"
},
  "geometry": {"coordinates":[8.5176973343,47.3617591858],"type":"Point"}
}