{
  "type": "Feature",
  "properties": {
    "iso:country":"CH",
    "sg:address":"Bahnhofstrasse 30",
    "sg:city":"Rheinfelden",
    "sg:orig_category":"Gartenbau",
    "sg:postcode":"4310",
    "sg:province":"Aargau",
    "wof:name":"Gg G\u00f6tz Gartenbau",
    "wof:placetype":"venue"
},
  "geometry": {"coordinates":[7.7920379639,47.5519485474],"type":"Point"}
}