{
  "type": "Feature",
  "properties": {
    "iso:country":"CH",
    "sg:address":"Hauptstrasse 66",
    "sg:city":"Kriegstetten",
    "sg:classifiers":[
        {
            "category":"Restaurant",
            "type":"Food & Drink"
        }
    ],
    "sg:phone":"+41 32 675 60 01",
    "sg:postcode":"4566",
    "sg:province":"Solothurn",
    "wof:name":"Restaurant Ueli Der P\u00e4chter",
    "wof:placetype":"venue"
},
  "geometry": {"coordinates":[7.5976791382,47.1739807129],"type":"Point"}
}