{
  "type": "Feature",
  "properties": {
    "iso:country":"CH",
    "sg:address":"1978",
    "sg:city":"Lens",
    "sg:classifiers":[
        {
            "category":"Insurance",
            "subcategory":"Insurance Agent",
            "type":"Services"
        }
    ],
    "sg:phone":"+41 32 913 82 33",
    "sg:postcode":"1978",
    "sg:province":"Valais",
    "sg:tags":[
        "versicherungsagenturen",
        "-broker"
    ],
    "wof:name":"Alpina Assurances Agence",
    "wof:placetype":"venue"
},
  "geometry": {"coordinates":[6.822496891,47.0986366272],"type":"Point"}
}