{
  "type": "Feature",
  "properties": {
    "iso:country":"CH",
    "sg:address":"Dorfbachstrasse 2",
    "sg:city":"Aarburg",
    "sg:orig_category":"Unternehmensberatung",
    "sg:postcode":"4663",
    "sg:province":"Aargau",
    "wof:name":"Franke Management Ag",
    "wof:placetype":"venue"
},
  "geometry": {"coordinates":[7.899078846,47.3201904297],"type":"Point"}
}