{
  "type": "Feature",
  "properties": {
    "iso:country":"CH",
    "sg:address":"Sommerweid 23",
    "sg:city":"Stansstad",
    "sg:classifiers":[
        {
            "category":"Autos & Motor Vehicles",
            "subcategory":"Recreational Vehicle Sales",
            "type":"Retail Goods"
        }
    ],
    "sg:phone":"+41 41 610 77 03",
    "sg:postcode":"6362",
    "sg:province":"Nidwalden",
    "sg:tags":[
        "machine",
        "tool",
        "accessory"
    ],
    "wof:name":"Bds-industrieberatung Jakob B\u00fcrgi",
    "wof:placetype":"venue"
},
  "geometry": {"coordinates":[8.3434000015,46.9808082581],"type":"Point"}
}