{
  "type": "Feature",
  "properties": {
    "iso:country":"CH",
    "sg:address":"Rue De La Musini\u00e8re 11",
    "sg:city":"St-blaise",
    "sg:orig_category":"Detailhandel mit Waren verschiedener Art, Hauptrichtung Nahrungsmittel Grosshandel mit Obst U Gem\u00fcse",
    "sg:phone":"+41 32 753 25 06",
    "sg:postcode":"2072",
    "sg:province":"Neuch\u00e2tel",
    "wof:name":"Marazzi & Boedts R.boedts Succ",
    "wof:placetype":"venue"
},
  "geometry": {"coordinates":[6.9920239449,47.0111312866],"type":"Point"}
}