{
  "type": "Feature",
  "properties": {
    "iso:country":"CH",
    "sg:address":"4006 Basel. Postfach",
    "sg:city":"Basel",
    "sg:orig_category":"Sportvereine Ballsport Fussball",
    "sg:phone":"+41 32 935 18 80",
    "sg:postcode":"4006",
    "wof:name":"As Vall\u00e9e",
    "wof:placetype":"venue"
},
  "geometry": {"coordinates":[6.6068201065,46.9808044434],"type":"Point"}
}