{
  "type": "Feature",
  "properties": {
    "iso:country":"CH",
    "sg:address":"Gottardo Via San",
    "sg:city":"Tenero",
    "sg:orig_category":"Grosshandel mit sonstigen Gebrauchs U Verbrauchsg\u00fctern",
    "sg:postcode":"6598",
    "sg:province":"Ticino",
    "wof:name":"Idealgame Sagl",
    "wof:placetype":"venue"
},
  "geometry": {"coordinates":[8.8466396332,46.1795730591],"type":"Point"}
}