{
  "type": "Feature",
  "properties": {
    "iso:country":"CH",
    "sg:address":"Baumgartenstrasse 23 8200 Schaffhausen. Postfach",
    "sg:city":"Schaffhausen",
    "sg:orig_category":"Museen",
    "sg:phone":"+41 52 625 25 15",
    "sg:postcode":"8201",
    "sg:province":"Schaffhausen",
    "wof:name":"Hallen F\u00fcr Neue Kunst Museum",
    "wof:placetype":"venue"
},
  "geometry": {"coordinates":[8.635679245,47.6944618225],"type":"Point"}
}