{
  "type": "Feature",
  "properties": {
    "iso:country":"CH",
    "sg:address":"Dorfstrasse 7",
    "sg:city":"Frutigen",
    "sg:orig_category":"Detailhandel mit Schuhen U Lederwaren",
    "sg:postcode":"3714",
    "sg:province":"Bern",
    "wof:name":"H\u00e4nni Hans, Schuhgesch\u00e4ft",
    "wof:placetype":"venue"
},
  "geometry": {"coordinates":[7.6450362206,46.5880622864],"type":"Point"}
}