{
  "type": "Feature",
  "properties": {
    "iso:country":"CH",
    "sg:address":"Baslerstrasse 103a 4123 Allschwil. Postfach Postfach 936",
    "sg:city":"Allschwil",
    "sg:orig_category":"Datenbanken Sonstige mit der Informatik verbundene T\u00e4tigkeiten",
    "sg:phone":"+41 61 485 95 07",
    "sg:postcode":"4123",
    "sg:province":"Basel-Landschaft",
    "wof:name":"Brix Ag Multimedia",
    "wof:placetype":"venue"
},
  "geometry": {"coordinates":[7.545092,47.552597],"type":"Point"}
}