{
  "type": "Feature",
  "properties": {
    "iso:country":"CH",
    "sg:address":"M\u00fchlegasse 11 8001 Z\u00fcrich. Postfach",
    "sg:city":"Z\u00fcrich",
    "sg:orig_category":"Unternehmensberatung Wirtschaftspr\u00fcfung, Steuerberatung U Treuhand",
    "sg:phone":"+41 12525860",
    "sg:postcode":"8025",
    "wof:name":"Dalera Ag",
    "wof:placetype":"venue"
},
  "geometry": {"coordinates":[8.543964386,47.3743553162],"type":"Point"}
}