{
  "type": "Feature",
  "properties": {
    "iso:country":"CH",
    "sg:address":"Rue P\u00e9colat 5",
    "sg:city":"Gen\u00e8ve",
    "sg:orig_category":"Erschliessung von Grundst\u00fccken",
    "sg:postcode":"1201",
    "sg:province":"Gen\u00e8ve",
    "wof:name":"Soci\u00e9t\u00e9 Coop\u00e9rative D'habitation Galaxie",
    "wof:placetype":"venue"
},
  "geometry": {"coordinates":[6.1460499763,46.208896637],"type":"Point"}
}