{
  "type": "Feature",
  "properties": {
    "iso:country":"CH",
    "sg:address":"Rigistrasse 31",
    "sg:city":"Baar",
    "sg:orig_category":"Betrieb U technische Hilfsdienste des Kultur U Unterhaltungswesens",
    "sg:phone":"+41 41 761 71 20",
    "sg:postcode":"6340",
    "sg:province":"Zug",
    "wof:name":"Slowjagd, Zilincan Marian",
    "wof:placetype":"venue"
},
  "geometry": {"coordinates":[8.531368,47.19249],"type":"Point"}
}