{
  "type": "Feature",
  "properties": {
    "iso:country":"CH",
    "sg:address":"St. Gallerstrasse 117",
    "sg:city":"Jona",
    "sg:orig_category":"Vermittlung von Immobilien",
    "sg:phone":"+41 21 691 38 73",
    "sg:postcode":"8645",
    "sg:province":"St. Gallen",
    "wof:name":"Mollenchire Sa Agence Immobili\u00e8re",
    "wof:placetype":"venue"
},
  "geometry": {"coordinates":[6.5628647804,46.5302429199],"type":"Point"}
}