{
  "type": "Feature",
  "properties": {
    "iso:country":"CH",
    "sg:address":"Via Federico Pedotti 6",
    "sg:city":"Bellinzona",
    "sg:orig_category":"Arztpraxen",
    "sg:phone":"+41 91 825 96 22",
    "sg:postcode":"6500",
    "sg:province":"Ticino",
    "wof:name":"Dott.med.enrico L\u00fc\u00f6nd Specialista Fmh",
    "wof:placetype":"venue"
},
  "geometry": {"coordinates":[9.022465,46.187057],"type":"Point"}
}