{
  "type": "Feature",
  "properties": {
    "addr:full":"Petit-cortaillod Cortaillod Neuch\u00e2tel 2016",
    "addr:postcode":"2016",
    "addr:street":"Petit-Cortaillod;Neucha\u0302Tel",
    "iso:country":"CH",
    "sg:address":"Petit-cortaillod",
    "sg:city":"Cortaillod",
    "sg:orig_category":"Campingpl\u00e4tze",
    "sg:phone":"+41 32 841 40 31",
    "sg:postcode":"2016",
    "sg:province":"Neuch\u00e2tel",
    "wof:name":"Camping De Corteillod",
    "wof:placetype":"venue"
},
  "geometry": {"coordinates":[6.853599,46.942436],"type":"Point"}
}