{
  "type": "Feature",
  "properties": {
    "iso:country":"CH",
    "sg:address":"Bachtobelstrasse 20",
    "sg:city":"Z\u00fcrich",
    "sg:orig_category":"Verlegen von Fussboden",
    "sg:phone":"+41 14514041",
    "sg:postcode":"8045",
    "sg:province":"Z\u00fcrich",
    "wof:name":"Claudio Amendola Unterlagsb\u00f6den",
    "wof:placetype":"venue"
},
  "geometry": {"coordinates":[8.5163049698,47.3612365723],"type":"Point"}
}