{
  "type": "Feature",
  "properties": {
    "iso:country":"CH",
    "sg:address":"R\u00f6ssligasse 17 6000 Luzern. Postfach",
    "sg:city":"Luzern",
    "sg:orig_category":"Herstellung von Medikamenten U sonstigen pharmazeutischen Erzeugnissen",
    "sg:postcode":"6003",
    "sg:province":"Luzern",
    "wof:name":"Profipharm Ag",
    "wof:placetype":"venue"
},
  "geometry": {"coordinates":[8.4067115784,46.9998435974],"type":"Point"}
}