{
  "type": "Feature",
  "properties": {
    "iso:country":"CH",
    "sg:address":"Andergia",
    "sg:city":"Mesocco",
    "sg:orig_category":"Detailhandel mit Textilien",
    "sg:phone":"+41 79 604 50 40",
    "sg:postcode":"6563",
    "sg:province":"Graubunden",
    "wof:name":"Marbi, Birrer Martha",
    "wof:placetype":"venue"
},
  "geometry": {"coordinates":[9.2359209061,46.4018859863],"type":"Point"}
}