{
  "type": "Feature",
  "properties": {
    "iso:country":"CH",
    "sg:address":"Teufbach",
    "sg:city":"Muotathal",
    "sg:orig_category":"Bauschreinerei Innenausbau",
    "sg:phone":"+41 41 830 17 28",
    "sg:postcode":"6436",
    "sg:province":"Schwyz",
    "wof:name":"Franz Suter Schreinerei & Innenausbau",
    "wof:placetype":"venue"
},
  "geometry": {"coordinates":[8.781017,46.975803],"type":"Point"}
}