{
  "type": "Feature",
  "properties": {
    "addr:full":"Kirchweg 224 B\u00f6zen Aargau 5076",
    "addr:housenumber":"224",
    "addr:postcode":"5076",
    "addr:street":"Kirchweg",
    "iso:country":"CH",
    "sg:address":"Kirchweg 224",
    "sg:city":"B\u00f6zen",
    "sg:orig_category":"Bauinstallation Malerei",
    "sg:phone":"+41 62 876 16 85",
    "sg:postcode":"5076",
    "sg:province":"Aargau",
    "wof:name":"Emil Fuchs Malergesch\u00e4ft",
    "wof:placetype":"venue"
},
  "geometry": {"coordinates":[8.090406,47.494148],"type":"Point"}
}