{
  "type": "Feature",
  "properties": {
    "iso:country":"CH",
    "sg:address":"Unterdorf 13",
    "sg:city":"Speicher",
    "sg:orig_category":"Advokaturb\u00fcros",
    "sg:phone":"+41 22 707 80 00",
    "sg:postcode":"9042",
    "sg:province":"Appenzell Ausserrhoden",
    "wof:name":"Pietro Sansonetti Etude D'avocat",
    "wof:placetype":"venue"
},
  "geometry": {"coordinates":[6.153519,46.20129],"type":"Point"}
}