{
  "type": "Feature",
  "properties": {
    "iso:country":"CH",
    "sg:address":"Oberdorfstrasse 15",
    "sg:city":"Wohlenschwil",
    "sg:orig_category":"Stukkateurgewerbe, Gipserei U Verputzerei Verlegen von Fussboden",
    "sg:postcode":"5512",
    "sg:province":"Aargau",
    "wof:name":"Naturfarben-malerei",
    "wof:placetype":"venue"
},
  "geometry": {"coordinates":[9.5219268799,47.4485626221],"type":"Point"}
}