{
  "type": "Feature",
  "properties": {
    "addr:full":"Hauptstrasse 24 Luterbach 4708",
    "addr:housenumber":"24",
    "addr:postcode":"4708",
    "addr:street":"Hauptstrasse",
    "iso:country":"CH",
    "sg:address":"Hauptstrasse 24",
    "sg:city":"Luterbach",
    "sg:classifiers":[
        {
            "category":"Banks & Credit Unions",
            "subcategory":"Bank",
            "type":"Services"
        }
    ],
    "sg:phone":"+41 41 978 16 77",
    "sg:postcode":"4708",
    "wof:name":"Raiffeisenbank Luthern",
    "wof:placetype":"venue"
},
  "geometry": {"coordinates":[7.889101,47.071453],"type":"Point"}
}