{
  "type": "Feature",
  "properties": {
    "iso:country":"CH",
    "sg:address":"Patnalerweg 14",
    "sg:city":"Untervaz",
    "sg:orig_category":"Allgemeiner Hoch U Tiefbau Ger\u00fcstbau",
    "sg:postcode":"7204",
    "sg:province":"Graubunden",
    "wof:name":"Meier Gebr. Ger\u00fcstbau Ag",
    "wof:placetype":"venue"
},
  "geometry": {"coordinates":[9.532969,46.929611],"type":"Point"}
}