{
  "type": "Feature",
  "properties": {
    "addr:full":"Latthag 10 Meiringen Bern 3860",
    "addr:housenumber":"10",
    "addr:postcode":"3860",
    "addr:street":"Latthag",
    "iso:country":"CH",
    "sg:address":"Latthag 10",
    "sg:city":"Meiringen",
    "sg:orig_category":"Allgemeiner Hoch U Tiefbau Immobilienwesen",
    "sg:phone":"+41 33 971 34 36",
    "sg:postcode":"3860",
    "sg:province":"Bern",
    "wof:name":"Ernst R. Inglin Bauleitung Immobilien",
    "wof:placetype":"venue"
},
  "geometry": {"coordinates":[8.178686,46.731335],"type":"Point"}
}