{
  "type": "Feature",
  "properties": {
    "iso:country":"CH",
    "sg:address":"Stationsstr. 7 Haus Espach",
    "sg:city":"N\u00e4nikon",
    "sg:orig_category":"Detailhandel mit M\u00f6beln U Haushaltsgegenst\u00e4nden",
    "sg:postcode":"8606",
    "sg:province":"Z\u00fcrich",
    "wof:name":"H\u00e4ssig H. A. Innendekorationen.",
    "wof:placetype":"venue"
},
  "geometry": {"coordinates":[8.677529335,47.365234375],"type":"Point"}
}