{
  "type": "Feature",
  "properties": {
    "addr:full":"Bodenhofstrasse 34 Luzern Luzern 6005",
    "addr:housenumber":"34",
    "addr:postcode":"6005",
    "addr:street":"Bodenhofstrasse",
    "iso:country":"CH",
    "sg:address":"Bodenhofstrasse 34",
    "sg:city":"Luzern",
    "sg:orig_category":"Detailhandel mit Brot, Back U S\u00fcsswaren",
    "sg:phone":"+41 41 360 81 60",
    "sg:postcode":"6005",
    "sg:province":"Luzern",
    "wof:name":"L\u00f6tscher U. Und Ch. Ag",
    "wof:placetype":"venue"
},
  "geometry": {"coordinates":[8.31973,47.03751],"type":"Point"}
}