{
  "type": "Feature",
  "properties": {
    "iso:country":"CH",
    "sg:address":"Baarerstrasse 86",
    "sg:city":"Zug",
    "sg:orig_category":"Wasserversorgung",
    "sg:phone":"+41 41 729 09 05",
    "sg:postcode":"6300",
    "sg:province":"Zug",
    "wof:name":"To Inter Aktiv Ag",
    "wof:placetype":"venue"
},
  "geometry": {"coordinates":[8.5180749893,47.1774101257],"type":"Point"}
}