{
  "type": "Feature",
  "properties": {
    "iso:country":"CH",
    "sg:address":"Route Principale 14",
    "sg:city":"Vellerat",
    "sg:orig_category":"G\u00fcterbef\u00f6rderung im Strassenverkehr",
    "sg:phone":"+41 32 435 73 40",
    "sg:postcode":"2830",
    "sg:province":"Jura",
    "wof:name":"Beat Sch\u00fcrmann Transports",
    "wof:placetype":"venue"
},
  "geometry": {"coordinates":[7.3730211258,47.3398246765],"type":"Point"}
}