{
  "type": "Feature",
  "properties": {
    "iso:country":"CH",
    "sg:address":"5077",
    "sg:city":"Elfingen",
    "sg:orig_category":"Vorschulen, Kinderg\u00e4rten",
    "sg:postcode":"5077",
    "sg:province":"Aargau",
    "wof:name":"Kindergarten",
    "wof:placetype":"venue"
},
  "geometry": {"coordinates":[8.1010398865,47.5100898743],"type":"Point"}
}