{
  "type": "Feature",
  "properties": {
    "iso:country":"CH",
    "sg:address":"Wasserwerkgasse 4",
    "sg:city":"Bern",
    "sg:orig_category":"Architektur U Ingenieurb\u00fcros Architekturb\u00fcros",
    "sg:phone":"+41 31 311 18 76",
    "sg:postcode":"3011",
    "sg:province":"Bern",
    "wof:name":"Baumann Andreas Architekturb\u00fcro",
    "wof:placetype":"venue"
},
  "geometry": {"coordinates":[7.457961,46.94754],"type":"Point"}
}