{
  "type": "Feature",
  "properties": {
    "iso:country":"CH",
    "sg:address":"Schachenstrasse 41 Postfach",
    "sg:city":"Lyssach",
    "sg:classifiers":[
        {
            "category":"Farming",
            "subcategory":"Farm & Veterinary Services",
            "type":"Manufacturing & Wholesale Goods"
        }
    ],
    "sg:phone":"+41 71 385 30 30",
    "sg:postcode":"3421",
    "sg:province":"Bern",
    "sg:tags":[
        "advice",
        "agriculture",
        "livestock",
        "business"
    ],
    "wof:name":"F\u00dcllemann Ag",
    "wof:placetype":"venue"
},
  "geometry": {"coordinates":[9.22821,47.43491],"type":"Point"}
}