{
  "type": "Feature",
  "properties": {
    "iso:country":"CH",
    "sg:address":"Rohrmattstrasse 9 3073 G\u00fcmligen. Postfach",
    "sg:city":"G\u00fcmligen",
    "sg:orig_category":"Unclassifiable Establishments",
    "sg:postcode":"3073",
    "sg:province":"Bern",
    "wof:name":"Canon Express-servicestelle Spielmann M.",
    "wof:placetype":"venue"
},
  "geometry": {"coordinates":[7.506608963,46.9320030212],"type":"Point"}
}