{
  "type": "Feature",
  "properties": {
    "iso:country":"CH",
    "sg:address":"Brisenstrasse 2 6370 Stans. Postfach 238",
    "sg:city":"Stans",
    "sg:orig_category":"Allgemeiner Hoch U Tiefbau Allgemeiner Hochbau",
    "sg:phone":"+41 81 833 36 58",
    "sg:postcode":"6370",
    "sg:province":"Nidwalden",
    "wof:name":"Christoffel Oscar Ag",
    "wof:placetype":"venue"
},
  "geometry": {"coordinates":[9.836173,46.488567],"type":"Point"}
}