{
  "type": "Feature",
  "properties": {
    "iso:country":"CH",
    "sg:address":"Route De Taillepied 125",
    "sg:city":"Ch\u00e2telard-lutry",
    "sg:orig_category":"Wohnheime",
    "sg:phone":"+41 71 622 39 92",
    "sg:postcode":"1095",
    "sg:province":"Vaud",
    "wof:name":"Durchgangsheim F\u00fcr Asylbewerber",
    "wof:placetype":"venue"
},
  "geometry": {"coordinates":[9.1381845474,47.5666694641],"type":"Point"}
}