{
  "type": "Feature",
  "properties": {
    "iso:country":"CH",
    "sg:address":"Drusbergstrasse 112",
    "sg:city":"Z\u00fcrich",
    "sg:orig_category":"Sonstiger Grosshandel",
    "sg:postcode":"8053",
    "sg:province":"Z\u00fcrich",
    "wof:name":"Zehnder Consulting And Trading Waren; Imp, Exp, Handel Usw.",
    "wof:placetype":"venue"
},
  "geometry": {"coordinates":[8.5844535828,47.3559265137],"type":"Point"}
}