{
  "type": "Feature",
  "properties": {
    "iso:country":"CH",
    "sg:address":"6852",
    "sg:city":"Genestrerio",
    "sg:classifiers":[
        {
            "category":"Restaurant",
            "type":"Food & Drink"
        }
    ],
    "sg:phone":"+41 91 647 18 91",
    "sg:postcode":"6852",
    "sg:province":"Ticino",
    "wof:name":"Grotto-ristorante Vallera",
    "wof:placetype":"venue"
},
  "geometry": {"coordinates":[8.9598703384,45.8506202698],"type":"Point"}
}