{
  "type": "Feature",
  "properties": {
    "iso:country":"CH",
    "sg:address":"Oberfeldstrasse 52 B",
    "sg:city":"Boll",
    "sg:orig_category":"Kauf U Verkauf von Immobilien auf eigene Rechnung",
    "sg:postcode":"3067",
    "sg:province":"Bern",
    "wof:name":"Arcasa Immobilien Ag",
    "wof:placetype":"venue"
},
  "geometry": {"coordinates":[7.5444030762,46.9587249756],"type":"Point"}
}