{
  "type": "Feature",
  "properties": {
    "iso:country":"CH",
    "sg:address":"Chemin Du Croissant 11",
    "sg:city":"Ch\u00e2telaine",
    "sg:orig_category":"Allgemeiner Hoch U Tiefbau Maurerarbeiten",
    "sg:phone":"+41 79 205 26 26",
    "sg:postcode":"1219",
    "sg:province":"Gen\u00e8ve",
    "wof:name":"Treleani Tullio",
    "wof:placetype":"venue"
},
  "geometry": {"coordinates":[6.111473,46.209206],"type":"Point"}
}