{
  "type": "Feature",
  "properties": {
    "addr:full":"Via Pambio 3 Paradiso Ticino 6900",
    "addr:housenumber":"3",
    "addr:postcode":"6900",
    "addr:street":"Via Pambio",
    "iso:country":"CH",
    "sg:address":"Via Pambio 3",
    "sg:city":"Paradiso",
    "sg:orig_category":"Chemische Reinigung",
    "sg:phone":"+41 91 994 41 56",
    "sg:postcode":"6900",
    "sg:province":"Ticino",
    "wof:name":"Mariangela Ticozzelli Lavanderia Chimica Mary",
    "wof:placetype":"venue"
},
  "geometry": {"coordinates":[8.942744,45.991173],"type":"Point"}
}