{
  "type": "Feature",
  "properties": {
    "iso:country":"CH",
    "sg:address":"Chemin Du Closel 13-15 1020 Renens Vd. Postfach",
    "sg:city":"Lausanne",
    "sg:orig_category":"Pensionskassen",
    "sg:postcode":"1003",
    "sg:province":"Vaud",
    "wof:name":"Fonds De Secours De La Sev Soci\u00e9t\u00e9 Des Entrep\u00f4ts Vevey Sa",
    "wof:placetype":"venue"
},
  "geometry": {"coordinates":[5.1808700562,45.8973388672],"type":"Point"}
}