{
  "type": "Feature",
  "properties": {
    "iso:country":"CH",
    "sg:address":"Av. Beauregard 3 Case Postale 484",
    "sg:city":"Fribourg",
    "sg:classifiers":[
        {
            "category":"Professional",
            "subcategory":"Printing & Photocopies",
            "type":"Services"
        }
    ],
    "sg:phone":"+41 26 425 87 30",
    "sg:postcode":"1701",
    "sg:province":"Fribourg",
    "sg:tags":[
        "publishing"
    ],
    "wof:name":"Imprimerie St-canisius Sa",
    "wof:placetype":"venue"
},
  "geometry": {"coordinates":[-85.3801956177,32.6425704956],"type":"Point"}
}