{
  "type": "Feature",
  "properties": {
    "iso:country":"CH",
    "sg:address":"Steinerbergstrasse 61",
    "sg:city":"Goldau",
    "sg:orig_category":"Herstellung von Elektromotoren, Generatoren U Transformatoren Mechanische Werkst\u00e4tten",
    "sg:phone":"+41 79 414 78 48",
    "sg:postcode":"6410",
    "sg:province":"Schwyz",
    "wof:name":"Othmar Steiner El'mech.werkst\u00e4tte Wicklerei",
    "wof:placetype":"venue"
},
  "geometry": {"coordinates":[8.5603294373,47.0527267456],"type":"Point"}
}