{
  "type": "Feature",
  "properties": {
    "iso:country":"CH",
    "sg:address":"Dorfstrasse 30a",
    "sg:city":"Wettingen",
    "sg:orig_category":"Sonstiger Grosshandel",
    "sg:phone":"+41 56 430 24 24",
    "sg:postcode":"5430",
    "sg:province":"Aargau",
    "wof:name":"Bretscher C.a. Ag",
    "wof:placetype":"venue"
},
  "geometry": {"coordinates":[8.3320102692,47.4669837952],"type":"Point"}
}