{
  "type": "Feature",
  "properties": {
    "iso:country":"CH",
    "sg:address":"Oberfeldweg 6",
    "sg:city":"Seon",
    "sg:orig_category":"Elektroinstallation",
    "sg:phone":"+41 62 775 26 29",
    "sg:postcode":"5703",
    "sg:province":"Aargau",
    "wof:name":"L\u00e4ubli Ag",
    "wof:placetype":"venue"
},
  "geometry": {"coordinates":[8.1627693176,47.3415718079],"type":"Point"}
}