{
  "type": "Feature",
  "properties": {
    "iso:country":"CH",
    "sg:address":"Rue De La Favi\u00e8re 19",
    "sg:city":"Grand-savagnier",
    "sg:orig_category":"Logistikberatung",
    "sg:phone":"+41 56 282 38 83",
    "sg:postcode":"2065",
    "sg:province":"Neuch\u00e2tel",
    "wof:name":"Lebag Betriebseinrichtungen Ag Lagertechnik",
    "wof:placetype":"venue"
},
  "geometry": {"coordinates":[8.2949857712,47.4924812317],"type":"Point"}
}