{
  "type": "Feature",
  "properties": {
    "iso:country":"CH",
    "sg:address":"Spindelstr. 2",
    "sg:city":"Z\u00fcrich",
    "sg:classifiers":[
        {
            "category":"Professional",
            "subcategory":"Printing & Photocopies",
            "type":"Services"
        }
    ],
    "sg:phone":"+41 32 843 00 20",
    "sg:postcode":"8041",
    "sg:province":"Z\u00fcrich",
    "sg:tags":[
        "publishing"
    ],
    "wof:name":"Gessler & Cie Sa",
    "wof:placetype":"venue"
},
  "geometry": {"coordinates":[8.2241401672,46.8130912781],"type":"Point"}
}