{
  "type": "Feature",
  "properties": {
    "iso:country":"CH",
    "sg:address":"Bachstrasse 6",
    "sg:city":"Lenzburg",
    "sg:orig_category":"Berufsberatungen",
    "sg:phone":"+41 62 891 39 40",
    "sg:postcode":"5600",
    "sg:province":"Aargau",
    "wof:name":"Berufsberatung Bezirk Lenzburg",
    "wof:placetype":"venue"
},
  "geometry": {"coordinates":[8.176366,47.387512],"type":"Point"}
}