{
  "type": "Feature",
  "properties": {
    "iso:country":"CH",
    "sg:address":"Mattenweg",
    "sg:city":"Mogelsberg",
    "sg:orig_category":"Unternehmensberatung",
    "sg:postcode":"9122",
    "sg:province":"St. Gallen",
    "wof:name":"Fatec Gruber R. Betriebsberatung, Organisation Usw; Planung, Schulung",
    "wof:placetype":"venue"
},
  "geometry": {"coordinates":[9.1347303391,47.3629608154],"type":"Point"}
}