{
  "type": "Feature",
  "properties": {
    "iso:country":"CH",
    "sg:address":"Rue De Gen\u00e8ve 64",
    "sg:city":"Ch\u00eane-bourg",
    "sg:orig_category":"Druck ohne Zeitungsdruck Offsetdruck",
    "sg:phone":"+41 22 348 97 07",
    "sg:postcode":"1225",
    "sg:province":"Gen\u00e8ve",
    "wof:name":"Imprimerie G\u00e9rard Challande",
    "wof:placetype":"venue"
},
  "geometry": {"coordinates":[6.1973018646,46.1936264038],"type":"Point"}
}