{
  "type": "Feature",
  "properties": {
    "iso:country":"CH",
    "sg:address":"Kalchgrabenweg 4 4532 Feldbrunnen. Postfach",
    "sg:city":"Feldbrunnen",
    "sg:orig_category":"Kauf U Verkauf von Immobilien auf eigene Rechnung",
    "sg:postcode":"4532",
    "sg:province":"Solothurn",
    "wof:name":"I-tredat Liegenschaften Usw",
    "wof:placetype":"venue"
},
  "geometry": {"coordinates":[7.5561637878,47.2209854126],"type":"Point"}
}