{
  "type": "Feature",
  "properties": {
    "iso:country":"CH",
    "sg:address":"Murbacherstrasse 19",
    "sg:city":"Luzern",
    "sg:orig_category":"Architektur U Ingenieurb\u00fcros",
    "sg:phone":"+41 41 632 50 30",
    "sg:postcode":"6003",
    "sg:province":"Luzern",
    "wof:name":"Ces Bauingenieur Ag",
    "wof:placetype":"venue"
},
  "geometry": {"coordinates":[8.313949,46.994759],"type":"Point"}
}