{
  "type": "Feature",
  "properties": {
    "iso:country":"CH",
    "sg:address":"Cadepiano",
    "sg:city":"Barbengo",
    "sg:orig_category":"Dachdeckerei",
    "sg:phone":"+41 91 995 11 56",
    "sg:postcode":"6917",
    "sg:province":"Ticino",
    "wof:name":"Antonio Pagnamenta Copertura Tetti",
    "wof:placetype":"venue"
},
  "geometry": {"coordinates":[8.91615,45.96104],"type":"Point"}
}