{
  "type": "Feature",
  "properties": {
    "iso:country":"CH",
    "sg:address":"Rue Du Village 22 1967 Bramois. Postfach",
    "sg:city":"Bramois",
    "sg:orig_category":"Fachdetailhandel mit pharmazeutischen Produkten",
    "sg:phone":"+41 27 322 12 34",
    "sg:postcode":"1967",
    "sg:province":"Valais",
    "wof:name":"Maurice Machoud, Mm-pharma.com",
    "wof:placetype":"venue"
},
  "geometry": {"coordinates":[7.4041137695,46.2314071655],"type":"Point"}
}