{
  "type": "Feature",
  "properties": {
    "iso:country":"CH",
    "sg:address":"Schwandenholzstrasse 240",
    "sg:city":"Z\u00fcrich",
    "sg:orig_category":"Schreib U \u00dcbersetzungsb\u00fcros",
    "sg:phone":"+41 13715908",
    "sg:postcode":"8046",
    "sg:province":"Z\u00fcrich",
    "wof:name":"Huber Ruth Admin. Dienstleistungen, Sekretariatsarbeiten",
    "wof:placetype":"venue"
},
  "geometry": {"coordinates":[8.5210027695,47.4242477417],"type":"Point"}
}