{
  "type": "Feature",
  "properties": {
    "iso:country":"CH",
    "sg:address":"Sch\u00fctzenhausstrasse 50",
    "sg:city":"Glarus",
    "sg:orig_category":"Blumen U Zierpflanzenbau",
    "sg:phone":"+41 55 640 23 64",
    "sg:postcode":"8750",
    "sg:province":"Glarus",
    "wof:name":"Heiri Eggli Gmbh Friedhofg\u00e4rtnerei",
    "wof:placetype":"venue"
},
  "geometry": {"coordinates":[9.065943,47.038437],"type":"Point"}
}