{
  "type": "Feature",
  "properties": {
    "iso:country":"CH",
    "sg:address":"Hohwartring 36",
    "sg:city":"Glash\u00fctten",
    "sg:orig_category":"Physiotherapie",
    "sg:phone":"+41 41 488 22 55",
    "sg:postcode":"4856",
    "sg:province":"Aargau",
    "wof:name":"Elsje Sch\u00f6pfer Physiotherapie",
    "wof:placetype":"venue"
},
  "geometry": {"coordinates":[8.0164194107,46.8817749023],"type":"Point"}
}