{
  "type": "Feature",
  "properties": {
    "addr:full":"1405 Pomy Vaud 1405",
    "addr:postcode":"1405;1405",
    "iso:country":"CH",
    "sg:address":"1405",
    "sg:city":"Pomy",
    "sg:orig_category":"Bauschreinerei Herstellung von M\u00f6beln verschiedener Art",
    "sg:phone":"+41 26 656 12 22",
    "sg:postcode":"1405",
    "sg:province":"Vaud",
    "wof:name":"Christian Bosson Menuiserie & Agencements",
    "wof:placetype":"venue"
},
  "geometry": {"coordinates":[6.92144,46.693176],"type":"Point"}
}