{
  "type": "Feature",
  "properties": {
    "iso:country":"CH",
    "sg:address":"M\u00fcliweg 7",
    "sg:city":"Weiach",
    "sg:orig_category":"Architekturb\u00fcros",
    "sg:phone":"+41 18582847",
    "sg:postcode":"8187",
    "sg:province":"Z\u00fcrich",
    "wof:name":"Hans Peter Stahel Architekturb\u00fcro",
    "wof:placetype":"venue"
},
  "geometry": {"coordinates":[8.44112,47.554283],"type":"Point"}
}