{
  "type": "Feature",
  "properties": {
    "iso:country":"CH",
    "sg:address":"Berg 14",
    "sg:city":"Schmitten",
    "sg:classifiers":[
        {
            "category":"Structure",
            "subcategory":"Warehouse",
            "type":"Public Place"
        }
    ],
    "sg:phone":"+41 26 496 33 57",
    "sg:postcode":"3185",
    "sg:province":"Fribourg",
    "sg:tags":[
        "air-conditioning",
        "system"
    ],
    "wof:name":"Hayoz Ag",
    "wof:placetype":"venue"
},
  "geometry": {"coordinates":[7.23555,46.847092],"type":"Point"}
}