{
  "type": "Feature",
  "properties": {
    "iso:country":"CH",
    "sg:address":"Rue Galil\u00e9e 15",
    "sg:city":"Cheseaux-nor\u00e9az",
    "sg:orig_category":"Herstellung von sonstigen elektrischen Ausr\u00fcstungen Softwareentwicklung U beratung",
    "sg:phone":"+41 71 637 70 70",
    "sg:postcode":"1400",
    "sg:province":"Vaud",
    "wof:name":"Dative Ag",
    "wof:placetype":"venue"
},
  "geometry": {"coordinates":[9.1734342575,47.5815963745],"type":"Point"}
}