{
  "type": "Feature",
  "properties": {
    "iso:country":"CH",
    "sg:address":"Sagenblickh\u00f6he 4 6030 Ebikon. Postfach 270",
    "sg:city":"Ebikon",
    "sg:orig_category":"Grosshandel mit Textilien Versandhandel",
    "sg:phone":"+41 41 440 77 28",
    "sg:postcode":"6030",
    "sg:province":"Luzern",
    "wof:name":"Textil-versand Ebikon Gmbh",
    "wof:placetype":"venue"
},
  "geometry": {"coordinates":[8.3413991928,47.0737495422],"type":"Point"}
}