{
  "type": "Feature",
  "properties": {
    "iso:country":"CH",
    "sg:address":"Derendingenstrasse",
    "sg:city":"Gerlafingen",
    "sg:orig_category":"Schwimmb\u00e4der",
    "sg:phone":"+41 32 675 50 10",
    "sg:postcode":"4563",
    "sg:province":"Solothurn",
    "wof:name":"Schwimmbad Eichholz",
    "wof:placetype":"venue"
},
  "geometry": {"coordinates":[7.5783047676,47.1763648987],"type":"Point"}
}