{
  "type": "Feature",
  "properties": {
    "iso:country":"CH",
    "sg:address":"Hauptstrasse 5",
    "sg:city":"K\u00e4nerkinden",
    "sg:orig_category":"Non-Classified Establishments",
    "sg:postcode":"4447",
    "sg:province":"Basel-Landschaft",
    "wof:name":"Rolf Handschin Tv-video-hifi-sat-haushalt",
    "wof:placetype":"venue"
},
  "geometry": {"coordinates":[7.8399429321,47.411781311],"type":"Point"}
}