{
  "type": "Feature",
  "properties": {
    "iso:country":"CH",
    "sg:address":"Einsiedlerstrasse 71e",
    "sg:city":"Horgen",
    "sg:orig_category":"Grosshandel mit Textilien",
    "sg:phone":"+41 73433113",
    "sg:postcode":"8810",
    "sg:province":"Z\u00fcrich",
    "wof:name":"Schwarzer & Co., Siam Import",
    "wof:placetype":"venue"
},
  "geometry": {"coordinates":[8.9703903198,47.4651412964],"type":"Point"}
}