{
  "type": "Feature",
  "properties": {
    "iso:country":"CH",
    "sg:address":"Fabrikmattenweg 11 4144 Arlesheim. Postfach 344",
    "sg:city":"Arlesheim",
    "sg:orig_category":"Grosshandel mit B\u00fcromaschinen U einrichtungen Grosshandel mit B\u00fcrom\u00f6beln",
    "sg:phone":"+41 61 701 85 25",
    "sg:postcode":"4144",
    "sg:province":"Basel-Landschaft",
    "wof:name":"Dauphin (schweiz) Ag",
    "wof:placetype":"venue"
},
  "geometry": {"coordinates":[7.6085791588,47.4946289062],"type":"Point"}
}