{
  "type": "Feature",
  "properties": {
    "iso:country":"CH",
    "sg:address":"Unionstrasse 3",
    "sg:city":"Z\u00fcrich",
    "sg:orig_category":"Werbeberatung",
    "sg:postcode":"8032",
    "sg:province":"Z\u00fcrich",
    "wof:name":"Urs Charles L\u00fcthi Optimas",
    "wof:placetype":"venue"
},
  "geometry": {"coordinates":[8.2771511078,47.3498268127],"type":"Point"}
}