{
  "type": "Feature",
  "properties": {
    "iso:country":"CH",
    "sg:address":"Rue Du Bois-du-lan 8 1217 Meyrin Case Postale 113",
    "sg:city":"Meyrin",
    "sg:orig_category":"Herstellung von Anstrichmitteln, Druckfarben U Kitten",
    "sg:phone":"+41 22 785 26 61",
    "sg:postcode":"1217",
    "sg:province":"Gen\u00e8ve",
    "wof:name":"Elpol Co Sa",
    "wof:placetype":"venue"
},
  "geometry": {"coordinates":[6.0771379471,46.2255897522],"type":"Point"}
}