{
  "type": "Feature",
  "properties": {
    "iso:country":"CH",
    "sg:address":"Simen Via Rinaldo 6600 Locarno. Postfach",
    "sg:city":"Locarno",
    "sg:orig_category":"Tankstellen",
    "sg:phone":"+41 91 751 34 92",
    "sg:postcode":"6600",
    "sg:province":"Ticino",
    "wof:name":"Esso 5 Vie Di Gehri Reto Stazione Di Servizio",
    "wof:placetype":"venue"
},
  "geometry": {"coordinates":[8.7892074585,46.1683959961],"type":"Point"}
}