{
  "type": "Feature",
  "properties": {
    "iso:country":"CH",
    "sg:address":"Lohwisstrasse 32 8123 Ebmatingen. Postfach 321",
    "sg:city":"Ebmatingen",
    "sg:orig_category":"Buchverlag Verlagsgewerbe",
    "sg:phone":"+41 71 277 19 14",
    "sg:postcode":"8123",
    "sg:province":"Z\u00fcrich",
    "wof:name":"Remak Verlags Ag",
    "wof:placetype":"venue"
},
  "geometry": {"coordinates":[9.358754,47.411743],"type":"Point"}
}