{
  "type": "Feature",
  "properties": {
    "iso:country":"CH",
    "sg:address":"Bernstrasse 75",
    "sg:city":"Steffisburg",
    "sg:orig_category":"Religi\u00f6se Vereinigungen divers",
    "sg:phone":"+41 33 437 64 29",
    "sg:postcode":"3613",
    "sg:province":"Bern",
    "wof:name":"Evangelischer Br\u00fcderverein",
    "wof:placetype":"venue"
},
  "geometry": {"coordinates":[7.6185698509,46.7704582214],"type":"Point"}
}