{
  "type": "Feature",
  "properties": {
    "iso:country":"CH",
    "sg:address":"Rue Du Faucon 17",
    "sg:city":"Biel/bienne",
    "sg:classifiers":[
        {
            "category":"Manufacturing",
            "subcategory":"Printing",
            "type":"Manufacturing & Wholesale Goods"
        }
    ],
    "sg:phone":"+41 32 341 55 41",
    "sg:postcode":"2502",
    "sg:province":"Bern",
    "sg:tags":[
        "house",
        "book"
    ],
    "wof:name":"Deltagraph Sarl",
    "wof:placetype":"venue"
},
  "geometry": {"coordinates":[7.25814,47.146866],"type":"Point"}
}