{
  "type": "Feature",
  "properties": {
    "iso:country":"CH",
    "sg:address":"Rosengartenstr. 3",
    "sg:city":"Wattwil",
    "sg:orig_category":"Architektur U Ingenieurb\u00fcros",
    "sg:postcode":"9630",
    "sg:province":"St. Gallen",
    "wof:name":"Brander Bauplanungen Gmbh",
    "wof:placetype":"venue"
},
  "geometry": {"coordinates":[9.087318,47.317196],"type":"Point"}
}