{
  "type": "Feature",
  "properties": {
    "iso:country":"CH",
    "sg:address":"Luterbachstrasse 13c",
    "sg:city":"Deitingen",
    "sg:orig_category":"Softwareentwicklung U beratung Sonstige mit der Informatik verbundene T\u00e4tigkeiten",
    "sg:phone":"+41 32 614 40 20",
    "sg:postcode":"4543",
    "sg:province":"Solothurn",
    "wof:name":"Awetec Informatik Ag",
    "wof:placetype":"venue"
},
  "geometry": {"coordinates":[7.6160001755,47.2196617126],"type":"Point"}
}