{
  "type": "Feature",
  "properties": {
    "addr:full":"Mattenweg 2 Rupperswil Aargau 5102",
    "addr:housenumber":"2",
    "addr:postcode":"5102",
    "addr:street":"Mattenweg",
    "iso:country":"CH",
    "sg:address":"Mattenweg 2",
    "sg:city":"Rupperswil",
    "sg:orig_category":"Bauschreinerei Zimmerei, Dachdeckerei, Bauspenglerei U Abdichtung",
    "sg:phone":"+41 71 393 56 62",
    "sg:postcode":"5102",
    "sg:province":"Aargau",
    "wof:name":"Fitze Walter Ag, Zimmerei Und Schreinerei",
    "wof:placetype":"venue"
},
  "geometry": {"coordinates":[9.226966,47.390137],"type":"Point"}
}