{
  "type": "Feature",
  "properties": {
    "iso:country":"CH",
    "sg:address":"B\u00fcrenstrasse 7",
    "sg:city":"Pieterlen",
    "sg:orig_category":"Herstellung von Betonerzeugnissen f\u00fcr den Bau Herstellung von Zement",
    "sg:phone":"+41 32 377 34 04",
    "sg:postcode":"2542",
    "sg:province":"Bern",
    "wof:name":"Rawyler Bruno Erwin",
    "wof:placetype":"venue"
},
  "geometry": {"coordinates":[7.345708847,47.1718330383],"type":"Point"}
}