{
  "type": "Feature",
  "properties": {
    "iso:country":"CH",
    "sg:address":"L'eglantine",
    "sg:city":"Champ\u00e9ry",
    "sg:orig_category":"Geb\u00e4ude, Wohnungsreinigung Reinigungsgewerbe",
    "sg:phone":"+41 31 832 16 46",
    "sg:postcode":"1874",
    "sg:province":"Valais",
    "wof:name":"Green Clean Gmbh",
    "wof:placetype":"venue"
},
  "geometry": {"coordinates":[7.5625319481,46.9287223816],"type":"Point"}
}