{
  "type": "Feature",
  "properties": {
    "iso:country":"CH",
    "sg:address":"Technopole Bp 860",
    "sg:city":"Sierre",
    "sg:classifiers":[
        {
            "category":"Professional",
            "subcategory":"Printing & Photocopies",
            "type":"Services"
        }
    ],
    "sg:phone":"+41 27 452 25 25",
    "sg:postcode":"3960",
    "sg:province":"Valais",
    "sg:tags":[
        "publishing"
    ],
    "wof:name":"Arts Graphiques Schoechli",
    "wof:placetype":"venue"
},
  "geometry": {"coordinates":[7.5384831429,46.2837677002],"type":"Point"}
}