{
  "type": "Feature",
  "properties": {
    "iso:country":"CH",
    "sg:address":"Hochfelderstrasse 6",
    "sg:city":"Neerach",
    "sg:orig_category":"Grosshandel mit Kaffee, Tee, Kakao U Gew\u00fcrzen",
    "sg:phone":"+41 18581680",
    "sg:postcode":"8173",
    "sg:province":"Z\u00fcrich",
    "wof:name":"Wavo-mix, Peter Waldvogel.",
    "wof:placetype":"venue"
},
  "geometry": {"coordinates":[8.4754753113,47.5136756897],"type":"Point"}
}