{
  "type": "Feature",
  "properties": {
    "iso:country":"CH",
    "sg:address":"Chemin Du N\u00e9avis",
    "sg:city":"Ardon",
    "sg:orig_category":"Elektrizit\u00e4tsversorgung",
    "sg:phone":"+41 27 306 11 22",
    "sg:postcode":"1957",
    "sg:province":"Valais",
    "wof:name":"Soci\u00e9t\u00e9 D'electricit\u00e9 D'ardon",
    "wof:placetype":"venue"
},
  "geometry": {"coordinates":[7.2617230415,46.2139701843],"type":"Point"}
}