{
  "type": "Feature",
  "properties": {
    "iso:country":"CH",
    "sg:address":"Strada Principale.",
    "sg:city":"Vicosoprano",
    "sg:orig_category":"Grosshandel mit Getr\u00e4nken",
    "sg:postcode":"7603",
    "sg:province":"Graubunden",
    "wof:name":"Del Curto Daniele, Di Del Curto Corrado, Chiavenna, Succursale Di Viscosoprano",
    "wof:placetype":"venue"
},
  "geometry": {"coordinates":[9.6205883026,46.3513145447],"type":"Point"}
}