{
  "type": "Feature",
  "properties": {
    "iso:country":"CH",
    "sg:address":"Rue Louis-curtat 4",
    "sg:city":"Lausanne",
    "sg:orig_category":"Innenarchitekturb\u00fcros",
    "sg:phone":"+41 21 323 16 14",
    "sg:postcode":"1005",
    "sg:province":"Vaud",
    "wof:name":"Jean-daniel Hofmann Architecte D'int\u00e9rieur",
    "wof:placetype":"venue"
},
  "geometry": {"coordinates":[6.6360459328,46.5218353271],"type":"Point"}
}