{
  "type": "Feature",
  "properties": {
    "iso:country":"CH",
    "sg:address":"Grand-places 1",
    "sg:city":"Fribourg",
    "sg:orig_category":"Vermietung U Verpachtung von eigenen Immobilien",
    "sg:postcode":"1700",
    "sg:province":"Fribourg",
    "wof:name":"Plamboz Sa",
    "wof:placetype":"venue"
},
  "geometry": {"coordinates":[7.1545848846,46.8032188416],"type":"Point"}
}