{
  "type": "Feature",
  "properties": {
    "iso:country":"CH",
    "sg:address":"Haldenweg 1",
    "sg:city":"Oftringen",
    "sg:orig_category":"Fahrschulen, Flugschulen",
    "sg:phone":"+41 62 797 60 50",
    "sg:postcode":"4665",
    "sg:province":"Aargau",
    "wof:name":"Rolf Meier Autofahrschule",
    "wof:placetype":"venue"
},
  "geometry": {"coordinates":[7.950949192,47.3012084961],"type":"Point"}
}