{
  "type": "Feature",
  "properties": {
    "iso:country":"CH",
    "sg:address":"5644",
    "sg:city":"Auw",
    "sg:orig_category":"Vereine Musik/Blasmusik",
    "sg:phone":"+41 56 668 16 65",
    "sg:postcode":"5644",
    "sg:province":"Aargau",
    "wof:name":"Musikgesellschaft",
    "wof:placetype":"venue"
},
  "geometry": {"coordinates":[8.3645982742,47.2115135193],"type":"Point"}
}