{
  "type": "Feature",
  "properties": {
    "iso:country":"CH",
    "sg:address":"Belpbergstrasse 14",
    "sg:city":"Gerzensee",
    "sg:orig_category":"Primarschulen",
    "sg:phone":"+41 31 741 03 00",
    "sg:postcode":"3115",
    "sg:province":"Bern",
    "wof:name":"Primarschule",
    "wof:placetype":"venue"
},
  "geometry": {"coordinates":[7.5454821587,46.8401565552],"type":"Point"}
}