{
  "type": "Feature",
  "properties": {
    "iso:country":"CH",
    "sg:address":"Chesa Mengiots",
    "sg:city":"Pontresina",
    "sg:orig_category":"Herstellung von Teppichen Verlegen von Fliesen U Platten",
    "sg:phone":"+41 91 605 20 34",
    "sg:postcode":"7504",
    "sg:province":"Graubunden",
    "wof:name":"Cadan Plinio",
    "wof:placetype":"venue"
},
  "geometry": {"coordinates":[8.9050197601,46.0297584534],"type":"Point"}
}