{
  "type": "Feature",
  "properties": {
    "iso:country":"CH",
    "sg:address":"K\u00fcnzistegstrasse 34",
    "sg:city":"Frutigen",
    "sg:classifiers":[
        {
            "category":"Professional",
            "subcategory":"Employment Agencies",
            "type":"Services"
        }
    ],
    "sg:postcode":"3714",
    "sg:province":"Bern",
    "sg:tags":[
        "personal",
        "u",
        "stellenvermittlung"
    ],
    "wof:name":"Vgs Graf-schmid Verena",
    "wof:placetype":"venue"
},
  "geometry": {"coordinates":[7.6455540657,46.5857200623],"type":"Point"}
}