{
  "type": "Feature",
  "properties": {
    "iso:country":"CH",
    "sg:address":"Chemin Du Caudoz 39",
    "sg:city":"Pully",
    "sg:orig_category":"Grosshandel mit sonstigen Halbwaren Grosshandel mit sonstigen Nahrungsmitteln",
    "sg:phone":"+41 21 729 73 49",
    "sg:postcode":"1009",
    "sg:province":"Vaud",
    "wof:name":"Paillard C. & Cie, Successeur Paillard C.",
    "wof:placetype":"venue"
},
  "geometry": {"coordinates":[6.6668591499,46.5143356323],"type":"Point"}
}