{
  "type": "Feature",
  "properties": {
    "iso:country":"CH",
    "sg:address":"Frutigenstrasse 58a 3604 Thun. Postfach 44",
    "sg:city":"Thun",
    "sg:orig_category":"Detailhandel mit Uhren U Schmuck Fachdetailhandel in Verkaufsr\u00e4umen",
    "sg:phone":"+41 33 335 10 30",
    "sg:postcode":"3604",
    "sg:province":"Bern",
    "wof:name":"Chronometrie Bangerter Ag",
    "wof:placetype":"venue"
},
  "geometry": {"coordinates":[7.6265411377,46.7454795837],"type":"Point"}
}