{
  "type": "Feature",
  "properties": {
    "iso:country":"CH",
    "sg:address":"Marktgasse 49 8400 Winterthur. Postfach 944",
    "sg:city":"Winterthur",
    "sg:classifiers":[
        {
            "category":"Travel",
            "subcategory":"Hotels & Motels",
            "type":"Entertainment"
        }
    ],
    "sg:phone":"+41 52 213 25 21",
    "sg:postcode":"8401",
    "sg:province":"Z\u00fcrich",
    "sg:tags":[
        "hotels",
        "mit",
        "restaurant"
    ],
    "wof:name":"Hotel Krone Winterthur",
    "wof:placetype":"venue"
},
  "geometry": {"coordinates":[8.727353096,47.4993743896],"type":"Point"}
}