{
  "type": "Feature",
  "properties": {
    "iso:country":"CH",
    "sg:address":"Route De La Croix-blanche 35 1066 Epalinges Case Postale 184",
    "sg:city":"Epalinges",
    "sg:orig_category":"Elektroinstallation",
    "sg:phone":"+41 21 784 24 25",
    "sg:postcode":"1066",
    "sg:province":"Vaud",
    "wof:name":"D\u00e9traz Marcel Sa",
    "wof:placetype":"venue"
},
  "geometry": {"coordinates":[6.6736950874,46.5484542847],"type":"Point"}
}