{
  "type": "Feature",
  "properties": {
    "iso:country":"CH",
    "sg:address":"Z\u00e4hringerstrasse 26",
    "sg:city":"Z\u00fcrich",
    "sg:orig_category":"Detailhandel mit Antiquit\u00e4ten Kunsthandel",
    "sg:phone":"+41 43 268 02 46",
    "sg:postcode":"8001",
    "sg:province":"Z\u00fcrich",
    "wof:name":"Martin Last",
    "wof:placetype":"venue"
},
  "geometry": {"coordinates":[8.544809,47.375332],"type":"Point"}
}