{
  "type": "Feature",
  "properties": {
    "addr:full":"M\u00fchlebachstrasse 44 Z\u00fcrich Z\u00fcrich 8008",
    "addr:housenumber":"44",
    "addr:postcode":"8008",
    "addr:street":"Muehlebachstrasse",
    "iso:country":"CH",
    "sg:address":"M\u00fchlebachstrasse 44",
    "sg:city":"Z\u00fcrich",
    "sg:orig_category":"Arztpraxen",
    "sg:phone":"+41 12528888",
    "sg:postcode":"8008",
    "sg:province":"Z\u00fcrich",
    "wof:name":"Dr.med.paul Siegwart Spezialarzt Fmh",
    "wof:placetype":"venue"
},
  "geometry": {"coordinates":[8.551109,47.364071],"type":"Point"}
}