{
  "type": "Feature",
  "properties": {
    "iso:country":"CH",
    "sg:address":"7159",
    "sg:city":"Andiast",
    "sg:orig_category":"Landesverteidigung, Sozialversicherung \u00d6ffentliche Verwaltung",
    "sg:phone":"+41 71 385 12 15",
    "sg:postcode":"7159",
    "sg:province":"Graubunden",
    "wof:name":"Zivilschutzstelle Andwil",
    "wof:placetype":"venue"
},
  "geometry": {"coordinates":[9.2681941986,47.4384651184],"type":"Point"}
}