{
  "type": "Feature",
  "properties": {
    "iso:country":"CH",
    "sg:address":"Langfurristrasse 1a",
    "sg:city":"Elgg",
    "sg:orig_category":"Unclassifiable Establishments",
    "sg:phone":"+41 52 364 22 16",
    "sg:postcode":"8353",
    "sg:province":"Z\u00fcrich",
    "wof:name":"Casa-plan Frommenwiler",
    "wof:placetype":"venue"
},
  "geometry": {"coordinates":[8.8661546707,47.4994697571],"type":"Point"}
}