{
  "type": "Feature",
  "properties": {
    "iso:country":"CH",
    "sg:address":"Via Cantonale",
    "sg:city":"Contone",
    "sg:orig_category":"Handel mit Motorr\u00e4dern, Teilen U Zubeh\u00f6r Instandhaltung U Reparatur von Motorr\u00e4dern",
    "sg:phone":"+41 91 840 11 60",
    "sg:postcode":"6594",
    "sg:province":"Ticino",
    "wof:name":"Moto Karlen Sagl",
    "wof:placetype":"venue"
},
  "geometry": {"coordinates":[8.9152402878,46.1521682739],"type":"Point"}
}