{
  "type": "Feature",
  "properties": {
    "iso:country":"CH",
    "sg:address":"B\u00fctzmattstrasse 2",
    "sg:city":"Gansingen",
    "sg:orig_category":"Detailhandel mit Metallwaren, Anstrichmitteln, Glaswaren, Bau U Heimwerkerbedarf",
    "sg:postcode":"5272",
    "sg:province":"Aargau",
    "wof:name":"Prifan Ag",
    "wof:placetype":"venue"
},
  "geometry": {"coordinates":[8.1386394501,47.5404167175],"type":"Point"}
}