{
  "type": "Feature",
  "properties": {
    "iso:country":"CH",
    "sg:address":"Industriestrasse 45",
    "sg:city":"Ebnat",
    "sg:orig_category":"Vorschulen, Kinderg\u00e4rten",
    "sg:phone":"+41 56 622 57 51",
    "sg:postcode":"9642",
    "sg:province":"St. Gallen",
    "wof:name":"Kindergarten Unterstadt",
    "wof:placetype":"venue"
},
  "geometry": {"coordinates":[8.3406467438,47.3526191711],"type":"Point"}
}