{
  "type": "Feature",
  "properties": {
    "iso:country":"CH",
    "sg:address":"Bahnhofstrasse 29",
    "sg:city":"Lenzburg",
    "sg:orig_category":"Versicherungen Hauptagenturen",
    "sg:phone":"+41 62 834 31 11",
    "sg:postcode":"5600",
    "sg:province":"Aargau",
    "wof:name":"National-versicherung Hauptagentur",
    "wof:placetype":"venue"
},
  "geometry": {"coordinates":[8.172785759,47.3900260925],"type":"Point"}
}