{
  "type": "Feature",
  "properties": {
    "iso:country":"CH",
    "sg:address":"Morges Avenue De 141 1004 Lausanne. Postfach",
    "sg:city":"Lausanne",
    "sg:orig_category":"RESTAURANTS: TEA-ROOMS",
    "sg:postcode":"1003",
    "sg:province":"Vaud",
    "wof:name":"Sandmeier Gis\u00e8le Caf\u00e9-restaurant \u00e0 L'ens. Le Caf\u00e9 Des Tramways",
    "wof:placetype":"venue"
},
  "geometry": {"coordinates":[6.632335186,46.5195960999],"type":"Point"}
}