{
  "type": "Feature",
  "properties": {
    "iso:country":"CH",
    "sg:address":"Bahnhofstrasse 6",
    "sg:city":"M\u00fchlau",
    "sg:orig_category":"Instandhaltung U Reparatur von Automobilen Mechanische Werkst\u00e4tten",
    "sg:postcode":"5642",
    "sg:province":"Aargau",
    "wof:name":"Ats Wisler",
    "wof:placetype":"venue"
},
  "geometry": {"coordinates":[8.3868951797,47.2294616699],"type":"Point"}
}