{
  "type": "Feature",
  "properties": {
    "addr:full":"Tannenbaum 18 Unterseen Bern 3800",
    "addr:housenumber":"18",
    "addr:postcode":"3800",
    "addr:street":"Tannenbaum",
    "iso:country":"CH",
    "sg:address":"Tannenbaum 18",
    "sg:city":"Unterseen",
    "sg:orig_category":"Architekturb\u00fcros S\u00e4ge, Hobel U Holzimpr\u00e4gnierwerke",
    "sg:phone":"+41 33 822 03 61",
    "sg:postcode":"3800",
    "sg:province":"Bern",
    "wof:name":"Alfred Zenger Architekturb\u00fcro",
    "wof:placetype":"venue"
},
  "geometry": {"coordinates":[7.84868,46.685402],"type":"Point"}
}