{
  "type": "Feature",
  "properties": {
    "iso:country":"CH",
    "sg:address":"Rue Peillonnex 17",
    "sg:city":"Ch\u00eane-bourg",
    "sg:orig_category":"Erbringung von sonstigen Dienstleistungen f\u00fcr Unternehmen",
    "sg:phone":"+41 79 622 50 09",
    "sg:postcode":"1225",
    "sg:province":"Gen\u00e8ve",
    "wof:name":"Jean-michel Staudhammer Atelier Jms",
    "wof:placetype":"venue"
},
  "geometry": {"coordinates":[6.1962418556,46.1948394775],"type":"Point"}
}