{
  "type": "Feature",
  "properties": {
    "iso:country":"CH",
    "sg:address":"Gstalden",
    "sg:city":"Oberb\u00fcren",
    "sg:orig_category":"Textilveredlung",
    "sg:phone":"+41 71 393 84 90",
    "sg:postcode":"9245",
    "sg:province":"St. Gallen",
    "wof:name":"Hevy-textil Tanner U.",
    "wof:placetype":"venue"
},
  "geometry": {"coordinates":[9.1801614761,47.4421577454],"type":"Point"}
}