{
  "type": "Feature",
  "properties": {
    "iso:country":"CH",
    "sg:address":"Pf\u00e4ffikerstrasse 6",
    "sg:city":"Volketswil",
    "sg:orig_category":"Binnenschiffahrt",
    "sg:phone":"+41 19974090",
    "sg:postcode":"8604",
    "sg:province":"Z\u00fcrich",
    "wof:name":"Marine Parts Heimgartner Bootszubeh\u00f6r",
    "wof:placetype":"venue"
},
  "geometry": {"coordinates":[8.696292,47.388729],"type":"Point"}
}