{
  "type": "Feature",
  "properties": {
    "iso:country":"CH",
    "sg:address":"Langstrasse 234",
    "sg:city":"Z\u00fcrich",
    "sg:orig_category":"Detailhandel mit Uhren U Schmuck Reparatur von Uhren U Schmuck",
    "sg:phone":"+41 12713630",
    "sg:postcode":"8005",
    "sg:province":"Z\u00fcrich",
    "wof:name":"Raymond Bourquin Uhren & Bijouterie",
    "wof:placetype":"venue"
},
  "geometry": {"coordinates":[8.5309686661,47.3838005066],"type":"Point"}
}