{
  "type": "Feature",
  "properties": {
    "iso:country":"CH",
    "sg:address":"Obermatt 22",
    "sg:city":"Rupperswil",
    "sg:orig_category":"Detailhandel mit Milcherzeugnissen U Eiern Verarbeitung von Milch",
    "sg:postcode":"5102",
    "sg:province":"Aargau",
    "wof:name":"K\u00e4sereigesellschaft Rupperswil",
    "wof:placetype":"venue"
},
  "geometry": {"coordinates":[8.1288747787,47.3947143555],"type":"Point"}
}