{
  "type": "Feature",
  "properties": {
    "iso:country":"CH",
    "sg:address":"Meienbreitenstrasse 3",
    "sg:city":"R\u00fcmlang",
    "sg:classifiers":[
        {
            "category":"Manufacturing",
            "subcategory":"Tools & Machinery",
            "type":"Manufacturing & Wholesale Goods"
        }
    ],
    "sg:phone":"+41 18173301",
    "sg:postcode":"8153",
    "sg:province":"Z\u00fcrich",
    "sg:tags":[
        "machining",
        "cnc"
    ],
    "wof:name":"Behr-mechanik Gmbh",
    "wof:placetype":"venue"
},
  "geometry": {"coordinates":[8.527488,47.458855],"type":"Point"}
}