{
  "type": "Feature",
  "properties": {
    "iso:country":"CH",
    "sg:address":"Kasparstrasse 15c",
    "sg:city":"Bern",
    "sg:orig_category":"Vorschulen, Kinderg\u00e4rten",
    "sg:phone":"+41 19109148",
    "sg:postcode":"3027",
    "sg:province":"Bern",
    "wof:name":"Kindergarten Bettlen",
    "wof:placetype":"venue"
},
  "geometry": {"coordinates":[8.603975296,47.3261413574],"type":"Point"}
}