{
  "type": "Feature",
  "properties": {
    "iso:country":"CH",
    "sg:address":"Englischviertelstrasse 54",
    "sg:city":"Z\u00fcrich",
    "sg:orig_category":"Arztpraxen",
    "sg:phone":"+41 13838357",
    "sg:postcode":"8032",
    "sg:province":"Z\u00fcrich",
    "wof:name":"Dr.med.thomas Voegeli Arzt F.allgmeine Medizin Fmh",
    "wof:placetype":"venue"
},
  "geometry": {"coordinates":[8.558195,47.365906],"type":"Point"}
}