{
  "type": "Feature",
  "properties": {
    "iso:country":"CH",
    "sg:address":"4800 Zofingen. Postfach",
    "sg:city":"Zofingen",
    "sg:orig_category":"Sportvereine Sch\u00fctzen Pistolen-& Gewehr",
    "sg:phone":"+41 33 223 18 12",
    "sg:postcode":"4800",
    "sg:province":"Aargau",
    "wof:name":"Unteroffiziersverein",
    "wof:placetype":"venue"
},
  "geometry": {"coordinates":[7.9598298073,47.2871894836],"type":"Point"}
}