{
  "type": "Feature",
  "properties": {
    "iso:country":"CH",
    "sg:address":"Z\u00fcrichstrasse 51",
    "sg:city":"Oftringen",
    "sg:orig_category":"Unclassifiable Establishments",
    "sg:postcode":"4665",
    "sg:province":"Aargau",
    "wof:name":"Computer Oil Gmbh It-dienstleistungen, Besonders Entwicklung Von Software Usw",
    "wof:placetype":"venue"
},
  "geometry": {"coordinates":[8.6982049942,47.6559753418],"type":"Point"}
}