{
  "type": "Feature",
  "properties": {
    "iso:country":"CH",
    "sg:address":"Suberg 3257 Grossaffoltern. Postfach",
    "sg:city":"Grossaffoltern",
    "sg:orig_category":"RESTAURANTS: TEA-ROOMS",
    "sg:phone":"+41 32 389 21 20",
    "sg:postcode":"3257",
    "sg:province":"Bern",
    "wof:name":"Heimberg Walter",
    "wof:placetype":"venue"
},
  "geometry": {"coordinates":[7.3464698792,47.0606765747],"type":"Point"}
}