{
  "type": "Feature",
  "properties": {
    "iso:country":"CH",
    "sg:address":"Rue De Neuch\u00e2tel 1",
    "sg:city":"Peseux",
    "sg:classifiers":[
        {
            "category":"Restaurant",
            "type":"Food & Drink"
        }
    ],
    "sg:phone":"+41 32 731 25 98",
    "sg:postcode":"2034",
    "sg:province":"Neuch\u00e2tel",
    "wof:name":"Restaurant Le Central",
    "wof:placetype":"venue"
},
  "geometry": {"coordinates":[6.8913350105,46.9881401062],"type":"Point"}
}