{
  "type": "Feature",
  "properties": {
    "iso:country":"CH",
    "sg:address":"Bernstrasse 36",
    "sg:city":"Kirchenthurnen",
    "sg:orig_category":"Selbst\u00e4ndige bildende K\u00fcnstler",
    "sg:phone":"+41 31 809 21 00",
    "sg:postcode":"3128",
    "sg:province":"Bern",
    "wof:name":"Christine & Heinz Etter Marmor Steinreplik.skulpturen",
    "wof:placetype":"venue"
},
  "geometry": {"coordinates":[7.5037531853,46.8214874268],"type":"Point"}
}