{
  "type": "Feature",
  "properties": {
    "iso:country":"CH",
    "sg:address":"Industriestrasse.",
    "sg:city":"Reichenburg",
    "sg:orig_category":"R\u00fcckgewinnung U Vorbereitung f\u00fcr die Wiederverwertung Recycling von Schrott",
    "sg:phone":"+41 55 444 16 61",
    "sg:postcode":"8864",
    "sg:province":"Schwyz",
    "wof:name":"Zimmermann Alfred, Autoverwertung.",
    "wof:placetype":"venue"
},
  "geometry": {"coordinates":[8.9875154495,47.1703987122],"type":"Point"}
}