{
  "type": "Feature",
  "properties": {
    "iso:country":"CH",
    "sg:address":"M\u00fchlebachstrasse 3 6370 Stans. Postfach 763",
    "sg:city":"Stans",
    "sg:orig_category":"Grosshandel mit Sportartikeln Herstellung von Sportger\u00e4ten",
    "sg:phone":"+41 81 410 08 18",
    "sg:postcode":"6371",
    "sg:province":"Nidwalden",
    "wof:name":"Rentaski Ag",
    "wof:placetype":"venue"
},
  "geometry": {"coordinates":[9.821603775,46.7966651917],"type":"Point"}
}