{
  "type": "Feature",
  "properties": {
    "iso:country":"CH",
    "sg:address":"B\u00fcttenbergstrasse 46",
    "sg:city":"Biel/bienne",
    "sg:classifiers":[
        {
            "category":"Professional",
            "subcategory":"Employment Agencies",
            "type":"Services"
        }
    ],
    "sg:phone":"+41 79 356 64 00",
    "sg:postcode":"2504",
    "sg:province":"Bern",
    "sg:tags":[
        "personal",
        "u",
        "stellenvermittlung"
    ],
    "wof:name":"Notabene Tanner A.",
    "wof:placetype":"venue"
},
  "geometry": {"coordinates":[7.282307148,47.1466064453],"type":"Point"}
}