{
  "type": "Feature",
  "properties": {
    "iso:country":"CH",
    "sg:address":"Route De Vercorin",
    "sg:city":"R\u00e9chy",
    "sg:orig_category":"Malerei Stukkateurgewerbe, Gipserei U Verputzerei",
    "sg:phone":"+41 79 220 79 87",
    "sg:postcode":"3966",
    "sg:province":"Valais",
    "wof:name":"Henri Zuber Gypserie & Peinture",
    "wof:placetype":"venue"
},
  "geometry": {"coordinates":[7.5054550171,46.2654685974],"type":"Point"}
}