{
  "type": "Feature",
  "properties": {
    "iso:country":"CH",
    "sg:address":"Cantonale Via 19 6900 Lugano. Postfach",
    "sg:city":"Lugano",
    "sg:orig_category":"Non-Classified Establishments",
    "sg:postcode":"6900",
    "sg:province":"Ticino",
    "wof:name":"Hcp Health Care Products Ltd Prodotti Per La Salute Ed Il Benessere D. Persona; Import., Produzione Ecc",
    "wof:placetype":"venue"
},
  "geometry": {"coordinates":[8.9502239227,46.0093307495],"type":"Point"}
}