{
  "type": "Feature",
  "properties": {
    "iso:country":"CH",
    "sg:address":"Route Des Grives 1",
    "sg:city":"Granges-paccot",
    "sg:orig_category":"Massagestudios Solarien",
    "sg:phone":"+41 26 466 44 01",
    "sg:postcode":"1763",
    "sg:province":"Fribourg",
    "wof:name":"Renato Cenci",
    "wof:placetype":"venue"
},
  "geometry": {"coordinates":[7.1512379646,46.8203811646],"type":"Point"}
}