{
  "type": "Feature",
  "properties": {
    "iso:country":"CH",
    "sg:address":"Rue Dr-schwab 16",
    "sg:city":"St-imier",
    "sg:classifiers":[
        {
            "category":"Restaurant",
            "type":"Food & Drink"
        }
    ],
    "sg:phone":"+41 32 941 26 45",
    "sg:postcode":"2610",
    "sg:province":"Bern",
    "wof:name":"Restaurant Montagnard",
    "wof:placetype":"venue"
},
  "geometry": {"coordinates":[7.0026540756,47.1537284851],"type":"Point"}
}