{
  "type": "Feature",
  "properties": {
    "iso:country":"CH",
    "sg:address":"Rue De Zurich 10",
    "sg:city":"Gen\u00e8ve",
    "sg:orig_category":"Herstellung von Schmuck, Gold U Silberschmiedwaren Herstellung von sonstigen M\u00f6beln",
    "sg:postcode":"1201",
    "sg:province":"Gen\u00e8ve",
    "wof:name":"Zago Ursula",
    "wof:placetype":"venue"
},
  "geometry": {"coordinates":[6.1479768753,46.2114753723],"type":"Point"}
}