{
  "type": "Feature",
  "properties": {
    "iso:country":"CH",
    "sg:address":"Sarganserstrasse",
    "sg:city":"Walenstadt",
    "sg:orig_category":"Grosshandel mit Getr\u00e4nken",
    "sg:phone":"+41 81 735 20 30",
    "sg:postcode":"8880",
    "sg:province":"St. Gallen",
    "wof:name":"Linder Paul",
    "wof:placetype":"venue"
},
  "geometry": {"coordinates":[9.3381767273,47.1129570007],"type":"Point"}
}