{
  "type": "Feature",
  "properties": {
    "iso:country":"CH",
    "sg:address":"Uetlibergstrasse 204",
    "sg:city":"Z\u00fcrich",
    "sg:orig_category":"Wirtschaftspr\u00fcfung, Steuerberatung U Treuhand",
    "sg:phone":"+41 14610288",
    "sg:postcode":"8045",
    "sg:province":"Z\u00fcrich",
    "wof:name":"Treuhandb\u00fcro Peyer",
    "wof:placetype":"venue"
},
  "geometry": {"coordinates":[8.5146131516,47.3580245972],"type":"Point"}
}