{
  "type": "Feature",
  "properties": {
    "iso:country":"CH",
    "sg:address":"Winkelstrasse 3",
    "sg:city":"Herisau",
    "sg:orig_category":"Zimmerei, Dachdeckerei, Bauspenglerei U Abdichtung",
    "sg:postcode":"9100",
    "sg:province":"Appenzell Ausserrhoden",
    "wof:name":"Ernst Schoch",
    "wof:placetype":"venue"
},
  "geometry": {"coordinates":[9.2731618881,47.3913040161],"type":"Point"}
}