{
  "type": "Feature",
  "properties": {
    "iso:country":"CH",
    "sg:address":"Avenue De La Gare 55",
    "sg:city":"Bex",
    "sg:orig_category":"Einbau von Schreinerwaren Maschinen and Apparate divers Grosshandel",
    "sg:phone":"+41 24 463 31 00",
    "sg:postcode":"1880",
    "sg:province":"Vaud",
    "wof:name":"Cm-gastro Thomas Milt",
    "wof:placetype":"venue"
},
  "geometry": {"coordinates":[7.0015220642,46.2515335083],"type":"Point"}
}