{
  "type": "Feature",
  "properties": {
    "iso:country":"CH",
    "sg:address":"Affolternstrasse 10",
    "sg:city":"Z\u00fcrich",
    "sg:orig_category":"Handelsvermittlung U Grosshandel Sonstiger Grosshandel",
    "sg:phone":"+41 13131250",
    "sg:postcode":"8050",
    "sg:province":"Z\u00fcrich",
    "wof:name":"Imp Partners Ag",
    "wof:placetype":"venue"
},
  "geometry": {"coordinates":[8.5447301865,47.4124603271],"type":"Point"}
}