{
  "type": "Feature",
  "properties": {
    "iso:country":"CH",
    "sg:address":"Burgstrasse 4",
    "sg:city":"Thun",
    "sg:classifiers":[
        {
            "category":"Education",
            "subcategory":"Library",
            "type":"Public Place"
        }
    ],
    "sg:phone":"+41 33 225 25 55",
    "sg:postcode":"3600",
    "sg:province":"Bern",
    "sg:tags":[
        "software"
    ],
    "wof:name":"Predata Ag",
    "wof:placetype":"venue"
},
  "geometry": {"coordinates":[7.6319909096,46.7596588135],"type":"Point"}
}