{
  "type": "Feature",
  "properties": {
    "addr:full":"Via Al Chioso 9 Lugano Ticino 6900",
    "addr:housenumber":"9",
    "addr:postcode":"6900",
    "addr:street":"Via Al Chioso",
    "iso:country":"CH",
    "sg:address":"Via Al Chioso 9",
    "sg:city":"Lugano",
    "sg:orig_category":"Allgemeinbildende weiterf\u00fchrende Schulen Primarschulen",
    "sg:phone":"+41 91 972 20 07",
    "sg:postcode":"6900",
    "sg:province":"Ticino",
    "wof:name":"Liceo Galileo Galilei Sa",
    "wof:placetype":"venue"
},
  "geometry": {"coordinates":[8.961779,46.00901],"type":"Point"}
}