{
  "type": "Feature",
  "properties": {
    "iso:country":"CH",
    "sg:address":"Birmensdorferstrasse 313",
    "sg:city":"Z\u00fcrich",
    "sg:orig_category":"RESTAURANTS: TEA-ROOMS",
    "sg:phone":"+41 32 373 37 07",
    "sg:postcode":"8055",
    "sg:province":"Z\u00fcrich",
    "wof:name":"Baumgartner Ursula",
    "wof:placetype":"venue"
},
  "geometry": {"coordinates":[7.3017911911,47.1131477356],"type":"Point"}
}