{
  "type": "Feature",
  "properties": {
    "iso:country":"CH",
    "sg:address":"Rue Pestalozzi 6",
    "sg:city":"Gen\u00e8ve",
    "sg:orig_category":"Primarschulen",
    "sg:phone":"+41 22 734 41 26",
    "sg:postcode":"1202",
    "sg:province":"Gen\u00e8ve",
    "wof:name":"Ecole Primaire Trembley I",
    "wof:placetype":"venue"
},
  "geometry": {"coordinates":[6.1287541389,46.2168464661],"type":"Point"}
}