{
  "type": "Feature",
  "properties": {
    "iso:country":"CH",
    "sg:address":"Eschi",
    "sg:city":"Boltigen",
    "sg:orig_category":"Zimmerei, Dachdeckerei, Bauspenglerei U Abdichtung",
    "sg:phone":"+41 33 773 69 32",
    "sg:postcode":"3766",
    "sg:province":"Bern",
    "wof:name":"Walter D\u00e4nzer",
    "wof:placetype":"venue"
},
  "geometry": {"coordinates":[7.3755998611,46.6117782593],"type":"Point"}
}