{
  "type": "Feature",
  "properties": {
    "iso:country":"CH",
    "sg:address":"3860",
    "sg:city":"Meiringen",
    "sg:orig_category":"Vereine Damen Vereine Gesang",
    "sg:postcode":"3860",
    "sg:province":"Bern",
    "wof:name":"T\u00f6chterchor M\u00fcnchwilen",
    "wof:placetype":"venue"
},
  "geometry": {"coordinates":[7.9622101784,47.5386695862],"type":"Point"}
}