{
  "type": "Feature",
  "properties": {
    "iso:country":"CH",
    "sg:address":"Fabrikstrasse 11-13",
    "sg:city":"H\u00e4gendorf",
    "sg:orig_category":"Herstellung von Werkzeugen",
    "sg:phone":"+41 62 216 61 51",
    "sg:postcode":"4614",
    "sg:province":"Solothurn",
    "wof:name":"Retif Floristik Gmbh, Hamm, Zweigniederlassung Floristik H\u00e4gendorf",
    "wof:placetype":"venue"
},
  "geometry": {"coordinates":[7.839029789,47.3294181824],"type":"Point"}
}