{
  "type": "Feature",
  "properties": {
    "iso:country":"CH",
    "sg:address":"Aeulistrasse 25",
    "sg:city":"Vilters",
    "sg:orig_category":"Mechanische Werkst\u00e4tten",
    "sg:phone":"+41 81 723 05 77",
    "sg:postcode":"7324",
    "sg:province":"St. Gallen",
    "wof:name":"Ignaz Guntli & Hans Kobler Mechanische Werkst\u00e4tte",
    "wof:placetype":"venue"
},
  "geometry": {"coordinates":[9.4450893402,47.0289268494],"type":"Point"}
}