{
  "type": "Feature",
  "properties": {
    "iso:country":"CH",
    "sg:address":"Curtibergstrasse 102",
    "sg:city":"Jona",
    "sg:orig_category":"Herstellung von Konstruktionsteilen, Fertigbauteilen U Ausbauelementen aus Holz",
    "sg:postcode":"8645",
    "sg:province":"St. Gallen",
    "wof:name":"Forrer Ruedi Gmbh",
    "wof:placetype":"venue"
},
  "geometry": {"coordinates":[8.8749084473,47.2376937866],"type":"Point"}
}