{
  "type": "Feature",
  "properties": {
    "iso:country":"CH",
    "sg:address":"Place De L'ecole",
    "sg:city":"Courgevaux",
    "sg:orig_category":"Maurerarbeiten",
    "sg:phone":"+41 26 670 14 48",
    "sg:postcode":"1796",
    "sg:province":"Fribourg",
    "wof:name":"Angelo Nolfo Maurergesch\u00e4ft",
    "wof:placetype":"venue"
},
  "geometry": {"coordinates":[7.1115980148,46.9080810547],"type":"Point"}
}