{
  "type": "Feature",
  "properties": {
    "iso:country":"CH",
    "sg:address":"Rainallee 37 4125 Riehen. Postfach",
    "sg:city":"Riehen",
    "sg:orig_category":"Hochschulen U h\u00f6here Ausbildung",
    "sg:phone":"+41 61 641 19 75",
    "sg:postcode":"4125",
    "sg:province":"Basel-Stadt",
    "wof:name":"Iae (institut F\u00fcr Angewandte Ethik) Gmbh Weiterbildungsmassnahmen Auf Allen Gebieten D. Angewandten Ethik Usw",
    "wof:placetype":"venue"
},
  "geometry": {"coordinates":[7.6412768364,47.5739822388],"type":"Point"}
}