{
  "type": "Feature",
  "properties": {
    "iso:country":"CH",
    "sg:address":"Route De Rochefort 16",
    "sg:city":"Vicques",
    "sg:orig_category":"S\u00e4ge, Hobel U Holzimpr\u00e4gnierwerke S\u00e4gewerke",
    "sg:phone":"+41 32 435 64 66",
    "sg:postcode":"2824",
    "sg:province":"Jura",
    "wof:name":"Aebin Emile Sa",
    "wof:placetype":"venue"
},
  "geometry": {"coordinates":[7.4145069122,47.3501548767],"type":"Point"}
}