{
  "type": "Feature",
  "properties": {
    "iso:country":"CH",
    "sg:address":"Tesserete Via 67",
    "sg:city":"Savosa",
    "sg:orig_category":"Vermietung U Verpachtung von eigenen Immobilien",
    "sg:postcode":"6942",
    "sg:province":"Ticino",
    "wof:name":"Madimob Sa",
    "wof:placetype":"venue"
},
  "geometry": {"coordinates":[8.9505434036,46.0234375],"type":"Point"}
}