{
  "type": "Feature",
  "properties": {
    "iso:country":"CH",
    "sg:address":"Weinberglistrasse 28",
    "sg:city":"Luzern",
    "sg:orig_category":"Handels-H\u00e4user U Gesellschaften",
    "sg:phone":"+41 41 360 23 33",
    "sg:postcode":"6005",
    "sg:province":"Luzern",
    "wof:name":"Kemtrade Elektronik Gmbh",
    "wof:placetype":"venue"
},
  "geometry": {"coordinates":[8.317855835,47.0405197144],"type":"Point"}
}