{
  "type": "Feature",
  "properties": {
    "iso:country":"CH",
    "sg:address":"Nassetta Vicolo 2",
    "sg:city":"Lugano",
    "sg:orig_category":"Herstellung von Maschinen f\u00fcr die Textil, Bekleidungsherstellung U die Lederverarbeitung",
    "sg:postcode":"6900",
    "sg:province":"Ticino",
    "wof:name":"L\u00fcro Textil-maschinen Ag",
    "wof:placetype":"venue"
},
  "geometry": {"coordinates":[9.5413970947,47.3785514832],"type":"Point"}
}