{
  "type": "Feature",
  "properties": {
    "iso:country":"CH",
    "sg:address":"Elisabethenstrasse 8",
    "sg:city":"Z\u00fcrich",
    "sg:orig_category":"Werbung",
    "sg:phone":"+41 12913565",
    "sg:postcode":"8004",
    "sg:province":"Z\u00fcrich",
    "wof:name":"Gestalterei Gmbh Klingenberg & Schneider",
    "wof:placetype":"venue"
},
  "geometry": {"coordinates":[8.5233001709,47.3726806641],"type":"Point"}
}