{
  "type": "Feature",
  "properties": {
    "iso:country":"CH",
    "sg:address":"Meichten 6",
    "sg:city":"Altb\u00fcron",
    "sg:orig_category":"Gartenbau",
    "sg:phone":"+41 56 622 81 20",
    "sg:postcode":"6147",
    "sg:province":"Luzern",
    "wof:name":"Alois M\u00fcller Gartenbau",
    "wof:placetype":"venue"
},
  "geometry": {"coordinates":[8.2832107544,47.3441314697],"type":"Point"}
}