{
  "type": "Feature",
  "properties": {
    "iso:country":"CH",
    "sg:address":"Blumenstrasse 6",
    "sg:city":"Rorschach",
    "sg:orig_category":"Sportvereine Unihockey",
    "sg:phone":"+41 71 841 65 91",
    "sg:postcode":"9400",
    "sg:province":"St. Gallen",
    "wof:name":"Uhc Rorschach Hurricans",
    "wof:placetype":"venue"
},
  "geometry": {"coordinates":[9.4958162308,47.4761924744],"type":"Point"}
}