{
  "type": "Feature",
  "properties": {
    "iso:country":"CH",
    "sg:address":"Route De Fontaines 8",
    "sg:city":"Boudevilliers",
    "sg:orig_category":"Sonstiger Grosshandel",
    "sg:phone":"+41 79 240 25 93",
    "sg:postcode":"2043",
    "sg:province":"Neuch\u00e2tel",
    "wof:name":"Marc-andr\u00e9 Pauli Panzerschr\u00e4nke",
    "wof:placetype":"venue"
},
  "geometry": {"coordinates":[6.8905668259,47.0299720764],"type":"Point"}
}