{
  "type": "Feature",
  "properties": {
    "iso:country":"CH",
    "sg:address":"Industriestrasse 15",
    "sg:city":"Luzern",
    "sg:orig_category":"Herstellung von Elektrizit\u00e4tsverteilungs U schalteinrichtungen",
    "sg:phone":"+41 41 360 88 49",
    "sg:postcode":"6005",
    "sg:province":"Luzern",
    "wof:name":"Elektro Steuerungsbau Luzern Widmer Fritz",
    "wof:placetype":"venue"
},
  "geometry": {"coordinates":[8.3118677139,47.0408973694],"type":"Point"}
}