{
  "type": "Feature",
  "properties": {
    "iso:country":"CH",
    "sg:address":"R\u00f6tschmattenweg 9",
    "sg:city":"Ins",
    "sg:orig_category":"Tierarztpraxis",
    "sg:phone":"+41 32 313 10 10",
    "sg:postcode":"3232",
    "sg:province":"Bern",
    "wof:name":"Dr. Med. Vet. Toni Schneider Tierarzt",
    "wof:placetype":"venue"
},
  "geometry": {"coordinates":[7.1096138954,47.0072746277],"type":"Point"}
}