{
  "type": "Feature",
  "properties": {
    "iso:country":"CH",
    "sg:address":"Pf\u00e4ndwiesenstrasse 2a 8152 Opfikon. Postfach",
    "sg:city":"Opfikon",
    "sg:orig_category":"Hardwareberatung",
    "sg:postcode":"8152",
    "sg:province":"Z\u00fcrich",
    "wof:name":"In4matica Delli Bovi Edv-hard Und Software, Peripheriger\u00e4te; Handel Usw",
    "wof:placetype":"venue"
},
  "geometry": {"coordinates":[8.5732460022,47.4323234558],"type":"Point"}
}