{
  "type": "Feature",
  "properties": {
    "iso:country":"CH",
    "sg:address":"G\u00fcterstrasse 5 4654 Lostorf. Postfach",
    "sg:city":"Lostorf",
    "sg:orig_category":"Herstellung von Teppichen",
    "sg:postcode":"4654",
    "sg:province":"Solothurn",
    "wof:name":"Schmid Innendekorationen",
    "wof:placetype":"venue"
},
  "geometry": {"coordinates":[8.1506309509,47.2209205627],"type":"Point"}
}