{
  "type": "Feature",
  "properties": {
    "iso:country":"CH",
    "sg:address":"3960",
    "sg:city":"Sierre",
    "sg:orig_category":"Vermietung U Verpachtung von eigenen Immobilien",
    "sg:phone":"+41 27 483 28 30",
    "sg:postcode":"3960",
    "sg:province":"Valais",
    "wof:name":"Vacances Neige Sa No 7",
    "wof:placetype":"venue"
},
  "geometry": {"coordinates":[7.5306549072,46.2924041748],"type":"Point"}
}