{
  "type": "Feature",
  "properties": {
    "iso:country":"CH",
    "sg:address":"Z\u00fcrcherstrasse 27",
    "sg:city":"Oberengstringen",
    "sg:orig_category":"Malerei Tapeziererei",
    "sg:phone":"+41 17504555",
    "sg:postcode":"8102",
    "sg:province":"Z\u00fcrich",
    "wof:name":"Willi Meier Maler-& Tapezierergesch\u00e4ft",
    "wof:placetype":"venue"
},
  "geometry": {"coordinates":[8.4747152328,47.4053459167],"type":"Point"}
}