{
  "type": "Feature",
  "properties": {
    "iso:country":"CH",
    "sg:address":"Place Des C\u00e8dres 8 1950 Sitten. Postfach",
    "sg:city":"Monthey",
    "sg:orig_category":"Vermietung U Verpachtung von eigenen Immobilien",
    "sg:phone":"+41 24 472 49 40",
    "sg:postcode":"1870",
    "sg:province":"Valais",
    "wof:name":"Si Pr\u00e9ville Sa Monthey",
    "wof:placetype":"venue"
},
  "geometry": {"coordinates":[7.3600950241,46.2301139832],"type":"Point"}
}