{
  "type": "Feature",
  "properties": {
    "iso:country":"CH",
    "sg:address":"Rickenstrasse 21",
    "sg:city":"Wattwil",
    "sg:orig_category":"Grosshandel mit Eisenwaren sowie Installationsbedarf f\u00fcr Gas, Wasser U Heizung Herstellung von sonst",
    "sg:phone":"+41 71 988 13 01",
    "sg:postcode":"9630",
    "sg:province":"St. Gallen",
    "wof:name":"Emil R\u00fcdlinger Eisenwarenhandlung & Wagnerei",
    "wof:placetype":"venue"
},
  "geometry": {"coordinates":[9.0853042603,47.299949646],"type":"Point"}
}