{
  "type": "Feature",
  "properties": {
    "iso:country":"CH",
    "sg:address":"Hauptstrasse 114",
    "sg:city":"Anwil",
    "sg:orig_category":"Sportvereine Turnen Vereine Damen",
    "sg:phone":"+41 61 991 01 35",
    "sg:postcode":"4469",
    "sg:province":"Basel-Landschaft",
    "wof:name":"Frauenriege Stv Anwil",
    "wof:placetype":"venue"
},
  "geometry": {"coordinates":[7.9428081512,47.4514808655],"type":"Point"}
}