{
  "type": "Feature",
  "properties": {
    "iso:country":"CH",
    "sg:address":"Badenerstrasse 575",
    "sg:city":"Z\u00fcrich",
    "sg:orig_category":"Detailhandel mit elektrischen Haushalts-,Radio U Fernsehger\u00e4ten sowie Musikinstrumenten Einzelhandel",
    "sg:phone":"+41 21 635 62 75",
    "sg:postcode":"8048",
    "sg:province":"Z\u00fcrich",
    "wof:name":"Car Audio Concept S.\u00e0 R.l.",
    "wof:placetype":"venue"
},
  "geometry": {"coordinates":[6.5904989243,46.5339851379],"type":"Point"}
}