{
  "type": "Feature",
  "properties": {
    "iso:country":"CH",
    "sg:address":"Fischmarkt 2 4410 Liestal. Postfach 101",
    "sg:city":"Liestal",
    "sg:orig_category":"Detailhandel mit elektrischen Haushalts-,Radio U Fernsehger\u00e4ten sowie Musikinstrumenten Herstellung ",
    "sg:phone":"+41 79 646 08 70",
    "sg:postcode":"4410",
    "sg:province":"Basel-Landschaft",
    "wof:name":"Geigenbau Scheifele Arion Ag",
    "wof:placetype":"venue"
},
  "geometry": {"coordinates":[7.7343001366,47.4839515686],"type":"Point"}
}