{
  "type": "Feature",
  "properties": {
    "iso:country":"CH",
    "sg:address":"Reiterstrasse 5b",
    "sg:city":"Bern",
    "sg:orig_category":"Verwaltung von Immobilien Wirtschaftspr\u00fcfung, Steuerberatung U Treuhand",
    "sg:phone":"+41 31 332 12 21",
    "sg:postcode":"3013",
    "sg:province":"Bern",
    "wof:name":"Hans P. Blank",
    "wof:placetype":"venue"
},
  "geometry": {"coordinates":[7.4608798027,46.9542007446],"type":"Point"}
}