{
  "type": "Feature",
  "properties": {
    "iso:country":"CH",
    "sg:address":"L\u00e4ngfeldweg 111",
    "sg:city":"Biel/bienne",
    "sg:classifiers":[
        {
            "category":"Shopping",
            "type":"Retail Goods"
        }
    ],
    "sg:phone":"+41 32 344 40 20",
    "sg:postcode":"2504",
    "sg:province":"Bern",
    "sg:tags":[
        "metallurgy",
        "finished",
        "-",
        "metalworking",
        "metallic"
    ],
    "wof:name":"Lechmann Ag",
    "wof:placetype":"venue"
},
  "geometry": {"coordinates":[7.289727211,47.1559448242],"type":"Point"}
}