{
  "type": "Feature",
  "properties": {
    "iso:country":"CH",
    "sg:address":"Via Della Pace 1b 6600 Locarno. Postfach",
    "sg:city":"Locarno",
    "sg:orig_category":"Erbringung von sonstigen Dienstleistungen f\u00fcr Unterhaltung, Erholung U Freizeit Konzert- and Theater",
    "sg:phone":"+41 91 751 93 23",
    "sg:postcode":"6600",
    "sg:province":"Ticino",
    "wof:name":"Euroshow Sagl Collocamento Di Artisti",
    "wof:placetype":"venue"
},
  "geometry": {"coordinates":[8.7986574173,46.1687812805],"type":"Point"}
}