{
  "type": "Feature",
  "properties": {
    "iso:country":"CH",
    "sg:address":"Hauptstrasse 72",
    "sg:city":"Tenniken",
    "sg:orig_category":"Wasserversorgung",
    "sg:postcode":"4456",
    "sg:province":"Basel-Landschaft",
    "wof:name":"Wasserversorgung Tenniken Obermatt-rosen",
    "wof:placetype":"venue"
},
  "geometry": {"coordinates":[7.8103270531,47.4338607788],"type":"Point"}
}