{
  "type": "Feature",
  "properties": {
    "iso:country":"CH",
    "sg:address":"T\u00e4gerhardstrasse 94",
    "sg:city":"Wettingen",
    "sg:orig_category":"Oberfl\u00e4chenveredlung U W\u00e4rmebehandlung",
    "sg:phone":"+41 56 426 68 92",
    "sg:postcode":"5430",
    "sg:province":"Aargau",
    "wof:name":"Metallveredlung Kopp Ag",
    "wof:placetype":"venue"
},
  "geometry": {"coordinates":[8.3308887482,47.4570388794],"type":"Point"}
}