{
  "type": "Feature",
  "properties": {
    "iso:country":"CH",
    "sg:address":"Grand-rue 83-87",
    "sg:city":"Morges",
    "sg:classifiers":[
        {
            "category":"Home & Garden",
            "subcategory":"Furniture",
            "type":"Retail Goods"
        }
    ],
    "sg:phone":"+41 21 811 54 00",
    "sg:postcode":"1110",
    "sg:province":"Vaud",
    "sg:tags":[
        "household",
        "wood"
    ],
    "wof:name":"Moyard Sa",
    "wof:placetype":"venue"
},
  "geometry": {"coordinates":[6.4977807999,46.5083389282],"type":"Point"}
}