{
  "type": "Feature",
  "properties": {
    "iso:country":"CH",
    "sg:address":"Furkastrasse 24",
    "sg:city":"Brig",
    "sg:orig_category":"Psychotherapie",
    "sg:phone":"+41 27 924 14 81",
    "sg:postcode":"3900",
    "sg:province":"Valais",
    "wof:name":"Willi Amherd Psychotherapie",
    "wof:placetype":"venue"
},
  "geometry": {"coordinates":[7.9859809875,46.3182296753],"type":"Point"}
}