{
  "type": "Feature",
  "properties": {
    "iso:country":"CH",
    "sg:address":"Bernstrasse 73",
    "sg:city":"Rudolfstetten",
    "sg:classifiers":[
        {
            "category":"Restaurant",
            "type":"Food & Drink"
        }
    ],
    "sg:phone":"+41 19321085",
    "sg:postcode":"8964",
    "sg:province":"Aargau",
    "wof:name":"Restaurant Sternen",
    "wof:placetype":"venue"
},
  "geometry": {"coordinates":[8.7847337723,47.3238143921],"type":"Point"}
}