{
  "type": "Feature",
  "properties": {
    "iso:country":"CH",
    "sg:address":"Thunstr. 3",
    "sg:city":"Schwarzenburg",
    "sg:classifiers":[
        {
            "category":"Shopping",
            "subcategory":"Hobbies, Toys, & Games",
            "type":"Retail Goods"
        }
    ],
    "sg:phone":"+41 31 731 22 20",
    "sg:postcode":"3150",
    "sg:province":"Bern",
    "sg:tags":[
        "product",
        "miscellaneous",
        "entertainment"
    ],
    "wof:name":"Musik Althaus Ag",
    "wof:placetype":"venue"
},
  "geometry": {"coordinates":[7.3443827629,46.8184738159],"type":"Point"}
}