{
  "type": "Feature",
  "properties": {
    "iso:country":"CH",
    "sg:address":"Seefeldstrasse 152 8008 Z\u00fcrich. Postfach",
    "sg:city":"Z\u00fcrich",
    "sg:orig_category":"Architektur U Ingenieurb\u00fcros",
    "sg:phone":"+41 12610974",
    "sg:postcode":"8001",
    "sg:province":"Z\u00fcrich",
    "wof:name":"Architekturb\u00fcro Feyer Thomas Dienstleistungen Im Architektur, Planungsbereich",
    "wof:placetype":"venue"
},
  "geometry": {"coordinates":[8.555116,47.356873],"type":"Point"}
}