{
  "type": "Feature",
  "properties": {
    "iso:country":"CH",
    "sg:address":"Fall\u00e4ckerstrasse 20",
    "sg:city":"Watt",
    "sg:orig_category":"Bauingenieurb\u00fcros allgemein",
    "sg:phone":"+41 18400735",
    "sg:postcode":"8105",
    "sg:province":"Z\u00fcrich",
    "wof:name":"Jakob Zweifel Ingenieurb\u00fcro",
    "wof:placetype":"venue"
},
  "geometry": {"coordinates":[8.477805,47.446762],"type":"Point"}
}