{
  "type": "Feature",
  "properties": {
    "iso:country":"CH",
    "sg:address":"Auenwiesenstrasse 8",
    "sg:city":"Bichelsee",
    "sg:orig_category":"Detailhandel mit Teppichen Herstellung von Teppichen",
    "sg:phone":"+41 41 870 63 00",
    "sg:postcode":"8363",
    "sg:province":"Thurgau",
    "wof:name":"Gisler Walter Bodenbel\u00e4ge Ag",
    "wof:placetype":"venue"
},
  "geometry": {"coordinates":[8.6342916489,46.8864555359],"type":"Point"}
}