{
  "type": "Feature",
  "properties": {
    "iso:country":"CH",
    "sg:address":"M\u00fchlebachstrasse 5",
    "sg:city":"Stans",
    "sg:orig_category":"Gesundheitswesen",
    "sg:postcode":"6370",
    "sg:province":"Nidwalden",
    "wof:name":"Roger Jud",
    "wof:placetype":"venue"
},
  "geometry": {"coordinates":[8.3588171005,46.9670257568],"type":"Point"}
}