{
  "type": "Feature",
  "properties": {
    "iso:country":"CH",
    "sg:address":"Luzernerstrasse 66",
    "sg:city":"Root",
    "sg:classifiers":[
        {
            "category":"Banks & Credit Unions",
            "subcategory":"Investment Brokerage",
            "type":"Services"
        }
    ],
    "sg:phone":"+41 41 450 20 30",
    "sg:postcode":"6037",
    "sg:province":"Luzern",
    "sg:tags":[
        "jam",
        "marmalade"
    ],
    "wof:name":"Schenk Konfit\u00fcren + Sirup",
    "wof:placetype":"venue"
},
  "geometry": {"coordinates":[8.3831481934,47.1089897156],"type":"Point"}
}