{
  "type": "Feature",
  "properties": {
    "iso:country":"CH",
    "sg:address":"Paradieshofweg 29",
    "sg:city":"Binningen",
    "sg:classifiers":[
        {
            "category":"Building & Trades",
            "subcategory":"Construction",
            "type":"Services"
        }
    ],
    "sg:phone":"+41 62 205 58 85",
    "sg:postcode":"4102",
    "sg:province":"Basel-Landschaft",
    "sg:tags":[
        "work",
        "public"
    ],
    "wof:name":"Allenspach & Co Ag",
    "wof:placetype":"venue"
},
  "geometry": {"coordinates":[7.873546,47.342751],"type":"Point"}
}