{
  "type": "Feature",
  "properties": {
    "iso:country":"CH",
    "sg:address":"Gr\u00fcsshaldenstrasse 14 6390 Engelberg. Postfach 257",
    "sg:city":"Engelberg",
    "sg:orig_category":"Unclassifiable Establishments",
    "sg:phone":"+41 41 666 50 30",
    "sg:postcode":"6390",
    "sg:province":"Obwalden",
    "wof:name":"Niederberger & Von Wyl Ag, Filiale Engelberg",
    "wof:placetype":"venue"
},
  "geometry": {"coordinates":[8.393951416,46.8243217468],"type":"Point"}
}