{
  "type": "Feature",
  "properties": {
    "iso:country":"CH",
    "sg:address":"3475",
    "sg:city":"Hermiswil",
    "sg:orig_category":"Instandhaltung U Reparatur von Automobilen",
    "sg:phone":"+41 62 968 14 47",
    "sg:postcode":"3475",
    "sg:province":"Bern",
    "wof:name":"Garage L\u00fcthi Ag Hermiswil",
    "wof:placetype":"venue"
},
  "geometry": {"coordinates":[7.6964049339,47.1530151367],"type":"Point"}
}