{
  "type": "Feature",
  "properties": {
    "iso:country":"CH",
    "sg:address":"Stazione Via 43",
    "sg:city":"Caslano",
    "sg:orig_category":"Architektur U Ingenieurb\u00fcros",
    "sg:phone":"+41 91 606 63 73",
    "sg:postcode":"6987",
    "sg:province":"Ticino",
    "wof:name":"Tulum Sa",
    "wof:placetype":"venue"
},
  "geometry": {"coordinates":[8.878942,45.974457],"type":"Point"}
}