{
  "type": "Feature",
  "properties": {
    "iso:country":"CH",
    "sg:address":"D\u00fcrrast",
    "sg:city":"Giswil",
    "sg:orig_category":"Zimmerei, Dachdeckerei, Bauspenglerei U Abdichtung",
    "sg:phone":"+41 71 755 10 32",
    "sg:postcode":"6074",
    "sg:province":"Obwalden",
    "wof:name":"Mattle Urs Holzbau Ag",
    "wof:placetype":"venue"
},
  "geometry": {"coordinates":[9.5498352051,47.3745880127],"type":"Point"}
}