{
  "type": "Feature",
  "properties": {
    "iso:country":"CH",
    "sg:address":"1323",
    "sg:city":"Romainm\u00f4tier",
    "sg:orig_category":"Verkehrs- and Tourismusb\u00fcros",
    "sg:phone":"+41 81 302 10 61",
    "sg:postcode":"1323",
    "sg:province":"Vaud",
    "wof:name":"Bad Ragaz Tourismus Verkehrsb\u00fcro",
    "wof:placetype":"venue"
},
  "geometry": {"coordinates":[9.5022726059,47.0028953552],"type":"Point"}
}