{
  "type": "Feature",
  "properties": {
    "iso:country":"CH",
    "sg:address":"Wendt Avenue 16 1203 Gen\u00e8ve. Postfach",
    "sg:city":"Gen\u00e8ve",
    "sg:orig_category":"Verwaltung von Immobilien",
    "sg:postcode":"1201",
    "sg:province":"Gen\u00e8ve",
    "wof:name":"Bruggeten Immobilien Gmbh",
    "wof:placetype":"venue"
},
  "geometry": {"coordinates":[8.8610420227,47.1878356934],"type":"Point"}
}