{
  "type": "Feature",
  "properties": {
    "addr:full":"Hauptstrasse 400 Jaun Fribourg 1656",
    "addr:housenumber":"400",
    "addr:postcode":"1656",
    "addr:street":"Hauptstrasse",
    "iso:country":"CH",
    "sg:address":"Hauptstrasse 400",
    "sg:city":"Jaun",
    "sg:orig_category":"Detailhandel mit Brot, Back U S\u00fcsswaren Detailhandel mit Waren verschiedener Art, Hauptrichtung Nahr",
    "sg:phone":"+41 26 929 84 18",
    "sg:postcode":"1656",
    "sg:province":"Fribourg",
    "wof:name":"Mooser Gilbert",
    "wof:placetype":"venue"
},
  "geometry": {"coordinates":[7.275555,46.610722],"type":"Point"}
}