{
  "type": "Feature",
  "properties": {
    "addr:full":"Mittelg\u00e4ustrasse 58 4617 Gunzgen. Postfach 30 Gunzgen Solothurn 4617",
    "addr:housenumber":"58;30",
    "addr:postcode":"4617;4617",
    "addr:street":"Mittelgaeustrasse;Postfach",
    "iso:country":"CH",
    "sg:address":"Mittelg\u00e4ustrasse 58 4617 Gunzgen. Postfach 30",
    "sg:city":"Gunzgen",
    "sg:orig_category":"Darlehenskassen U Raiffeisenbanken",
    "sg:phone":"+41 62 216 20 61",
    "sg:postcode":"4617",
    "sg:province":"Solothurn",
    "wof:name":"Raiffeisenbank",
    "wof:placetype":"venue"
},
  "geometry": {"coordinates":[7.827107,47.315174],"type":"Point"}
}