{
  "type": "Feature",
  "properties": {
    "iso:country":"CH",
    "sg:address":"Dorfstrasse 7",
    "sg:city":"Hindelbank",
    "sg:orig_category":"Innendekorationsateliers",
    "sg:phone":"+41 34 411 21 86",
    "sg:postcode":"3324",
    "sg:province":"Bern",
    "wof:name":"Hanspeter Lehmann Tapezierer-dekorateur",
    "wof:placetype":"venue"
},
  "geometry": {"coordinates":[7.5404062271,47.0429534912],"type":"Point"}
}