{
  "type": "Feature",
  "properties": {
    "iso:country":"CH",
    "sg:address":"Avenue Du Crochetan 10",
    "sg:city":"Monthey",
    "sg:orig_category":"Vermietung U Verpachtung von eigenen Immobilien",
    "sg:postcode":"1870",
    "sg:province":"Valais",
    "wof:name":"Nantermod Jacques Rhonalp.",
    "wof:placetype":"venue"
},
  "geometry": {"coordinates":[6.947892189,46.2541389465],"type":"Point"}
}