{
  "type": "Feature",
  "properties": {
    "iso:country":"CH",
    "sg:address":"5412 Gebenstorf. Postfach 81",
    "sg:city":"Gebenstorf",
    "sg:orig_category":"Sportvereine Ballsport Badminton",
    "sg:phone":"+41 22 418 44 44",
    "sg:postcode":"5412",
    "sg:province":"Aargau",
    "wof:name":"Badminton-club Gen\u00e8ve Cs De La Queue-d'arve",
    "wof:placetype":"venue"
},
  "geometry": {"coordinates":[6.1414251328,46.1833114624],"type":"Point"}
}