{
  "type": "Feature",
  "properties": {
    "iso:country":"CH",
    "sg:address":"Via Bernardino Luini 13",
    "sg:city":"Locarno",
    "sg:orig_category":"Handel mit Motorr\u00e4dern, Teilen U Zubeh\u00f6r Instandhaltung U Reparatur von Motorr\u00e4dern Mechanische Werk",
    "sg:phone":"+41 91 751 37 64",
    "sg:postcode":"6600",
    "sg:province":"Ticino",
    "wof:name":"Maggetti Fausto",
    "wof:placetype":"venue"
},
  "geometry": {"coordinates":[8.7971153259,46.168006897],"type":"Point"}
}