{
  "type": "Feature",
  "properties": {
    "iso:country":"CH",
    "sg:address":"Dorfstrasse 23 2544 Bettlach. Postfach 142",
    "sg:city":"Bettlach",
    "sg:orig_category":"Drogerien",
    "sg:phone":"+41 32 645 19 73",
    "sg:postcode":"2544",
    "sg:province":"Solothurn",
    "wof:name":"Drogerie Frehner",
    "wof:placetype":"venue"
},
  "geometry": {"coordinates":[7.4251480103,47.2008209229],"type":"Point"}
}