{
  "type": "Feature",
  "properties": {
    "iso:country":"CH",
    "sg:address":"Route Du Ch\u00e2telard 52",
    "sg:city":"Lausanne",
    "sg:orig_category":"Detailhandel mit Radio U Fernsehger\u00e4ten Detailhandel mit elektrischen Haushalts-,Radio U Fernsehger\u00e4",
    "sg:phone":"+41 21 646 35 71",
    "sg:postcode":"1018",
    "sg:province":"Vaud",
    "wof:name":"Sertrox S\u00e0rl",
    "wof:placetype":"venue"
},
  "geometry": {"coordinates":[6.6240119934,46.5434341431],"type":"Point"}
}