{
  "type": "Feature",
  "properties": {
    "iso:country":"CH",
    "sg:address":"Chemin Du Lac 11 1291 Commugny. Postfach",
    "sg:city":"Commugny",
    "sg:orig_category":"Herstellung von Duft U K\u00f6rperpflegemitteln",
    "sg:postcode":"1291",
    "sg:province":"Vaud",
    "wof:name":"Grob Cosmitics & Co",
    "wof:placetype":"venue"
},
  "geometry": {"coordinates":[6.1795268059,46.3137741089],"type":"Point"}
}