{
  "type": "Feature",
  "properties": {
    "iso:country":"CH",
    "sg:address":"Romanshorner Strasse 30",
    "sg:city":"Uttwil",
    "sg:orig_category":"Gartenbau Strassenbau",
    "sg:phone":"+41 79 447 78 24",
    "sg:postcode":"8592",
    "sg:province":"Thurgau",
    "wof:name":"Kurt Von K\u00e4nel Garten-& Tiefbau",
    "wof:placetype":"venue"
},
  "geometry": {"coordinates":[9.3471794128,47.5808601379],"type":"Point"}
}