{
  "type": "Feature",
  "properties": {
    "iso:country":"CH",
    "sg:address":"Brunngrabenstrasse 22",
    "sg:city":"Solothurn",
    "sg:orig_category":"Non-Classified Establishments",
    "sg:postcode":"4500",
    "sg:province":"Solothurn",
    "wof:name":"Maurergesch\u00e4ft Hoppler",
    "wof:placetype":"venue"
},
  "geometry": {"coordinates":[7.5162820816,47.2054214478],"type":"Point"}
}