{
  "type": "Feature",
  "properties": {
    "iso:country":"CH",
    "sg:address":"Bergstrasse 6",
    "sg:city":"Seengen",
    "sg:orig_category":"Desktop Publishing Systems And Peripherals",
    "sg:phone":"+41 62 777 03 77",
    "sg:postcode":"5707",
    "sg:province":"Aargau",
    "wof:name":"Abc Promotion Ag",
    "wof:placetype":"venue"
},
  "geometry": {"coordinates":[8.210844,47.328159],"type":"Point"}
}