{
  "type": "Feature",
  "properties": {
    "iso:country":"CH",
    "sg:address":"Route Principale 50 A",
    "sg:city":"Courchapoix",
    "sg:orig_category":"Herstellung U Zusammensetzung von Uhren Herstellung von Uhren",
    "sg:phone":"+41 32 910 90 62",
    "sg:postcode":"2825",
    "sg:province":"Jura",
    "wof:name":"The British Masters Sa Composants, Produits Horlogers Etc; D\u00e9velopp, Fabric, Product, Commerce",
    "wof:placetype":"venue"
},
  "geometry": {"coordinates":[6.8291797638,47.1021652222],"type":"Point"}
}