{
  "type": "Feature",
  "properties": {
    "iso:country":"CH",
    "sg:address":"F\u00fcrstenlandstrasse 96 9014 St. Gallen 14 Zust. Postfach 9014 St. Gallen",
    "sg:city":"Zust",
    "sg:orig_category":"Hochschulen U h\u00f6here Ausbildung",
    "sg:postcode":"14",
    "wof:name":"Lorimar Ag",
    "wof:placetype":"venue"
},
  "geometry": {"coordinates":[8.8267507553,47.1930007935],"type":"Point"}
}