{
  "type": "Feature",
  "properties": {
    "iso:country":"CH",
    "sg:address":"Zweiermatt",
    "sg:city":"Udligenswil",
    "sg:orig_category":"Sanit\u00e4r, Heizungs U L\u00fcftungsinstallation",
    "sg:phone":"+41 41 371 14 85",
    "sg:postcode":"6044",
    "sg:province":"Luzern",
    "wof:name":"Kaiser M. Ag",
    "wof:placetype":"venue"
},
  "geometry": {"coordinates":[8.3986120224,47.0895195007],"type":"Point"}
}