{
  "type": "Feature",
  "properties": {
    "iso:country":"CH",
    "sg:address":"Dennlerstrasse 8000 Z\u00fcrich. Postfach",
    "sg:city":"Z\u00fcrich",
    "sg:orig_category":"Softwareentwicklung U beratung",
    "sg:postcode":"8048",
    "sg:province":"Z\u00fcrich",
    "wof:name":"Aragost Z\u00fcrich",
    "wof:placetype":"venue"
},
  "geometry": {"coordinates":[8.4970798492,47.3799552917],"type":"Point"}
}