{
  "type": "Feature",
  "properties": {
    "iso:country":"CH",
    "sg:address":"1618",
    "sg:city":"Ch\u00e2tel-st-denis",
    "sg:orig_category":"Allgemeiner Hoch U Tiefbau Hoch U Tiefbau",
    "sg:phone":"+41 21 948 77 92",
    "sg:postcode":"1618",
    "sg:province":"Fribourg",
    "wof:name":"Trama Sa",
    "wof:placetype":"venue"
},
  "geometry": {"coordinates":[6.90154,46.527534],"type":"Point"}
}