{
  "type": "Feature",
  "properties": {
    "iso:country":"CH",
    "sg:address":"Waldeggstrasse 3",
    "sg:city":"Interlaken",
    "sg:orig_category":"Politische Parteien FDP",
    "sg:phone":"+41 31 952 78 10",
    "sg:postcode":"3800",
    "sg:province":"Bern",
    "wof:name":"Fdp Sektion Muri-g\u00fcmligen",
    "wof:placetype":"venue"
},
  "geometry": {"coordinates":[7.48229599,46.9336433411],"type":"Point"}
}