{
  "type": "Feature",
  "properties": {
    "iso:country":"CH",
    "sg:address":"Route De Renens 3",
    "sg:city":"Bussigny-pr\u00e8s-lausanne",
    "sg:classifiers":[
        {
            "category":"Home & Garden",
            "subcategory":"Building Materials",
            "type":"Retail Goods"
        }
    ],
    "sg:phone":"+41 21 701 48 44",
    "sg:postcode":"1030",
    "sg:province":"Vaud",
    "sg:tags":[
        "ready-mixed",
        "fresh",
        "concrete"
    ],
    "wof:name":"B\u00e9tonfrais + Pompages S.a.",
    "wof:placetype":"venue"
},
  "geometry": {"coordinates":[6.5661621094,46.5465278625],"type":"Point"}
}