{
  "type": "Feature",
  "properties": {
    "iso:country":"CH",
    "sg:address":"Hauptstrasse",
    "sg:city":"Rohrbach",
    "sg:orig_category":"Detailhandel mit Bekleidung",
    "sg:phone":"+41 62 965 13 68",
    "sg:postcode":"4938",
    "sg:province":"Bern",
    "wof:name":"Hansulrich L\u00fcthi Konfektion",
    "wof:placetype":"venue"
},
  "geometry": {"coordinates":[7.822377,47.130405],"type":"Point"}
}