{
  "type": "Feature",
  "properties": {
    "addr:full":"Holbergstrasse 11 Kloten Z\u00fcrich 8302",
    "addr:housenumber":"11",
    "addr:postcode":"8302",
    "addr:street":"Holbergstrasse",
    "iso:country":"CH",
    "sg:address":"Holbergstrasse 11",
    "sg:city":"Kloten",
    "sg:orig_category":"Detailhandel mit Brot, Back U S\u00fcsswaren",
    "sg:phone":"+41 18137011",
    "sg:postcode":"8302",
    "sg:province":"Z\u00fcrich",
    "wof:name":"Harry Reischmann B\u00e4ckerei-konditorei",
    "wof:placetype":"venue"
},
  "geometry": {"coordinates":[8.580818,47.448498],"type":"Point"}
}