{
  "type": "Feature",
  "properties": {
    "iso:country":"CH",
    "sg:address":"Mulebachstrasse 7 -",
    "sg:city":"Zurich",
    "sg:classifiers":[
        {
            "category":"Professional",
            "subcategory":"Art Services",
            "type":"Services"
        }
    ],
    "sg:phone":"+41 4112688585",
    "sg:postcode":"8008",
    "sg:province":"Z\u00fcrich",
    "sg:tags":[
        "export-import"
    ],
    "wof:name":"French General Consulate",
    "wof:placetype":"venue"
},
  "geometry": {"coordinates":[8.549445,47.365917],"type":"Point"}
}