{
  "type": "Feature",
  "properties": {
    "iso:country":"CH",
    "sg:address":"Etzelstrasse 39",
    "sg:city":"Altendorf",
    "sg:orig_category":"Abbruch U Sprenggewerbe, Erdbewegungsarbeiten",
    "sg:phone":"+41 55 442 59 55",
    "sg:postcode":"8852",
    "sg:province":"Schwyz",
    "wof:name":"Keller Beat, Bagger Und Traxbetrieb",
    "wof:placetype":"venue"
},
  "geometry": {"coordinates":[8.823092,47.190125],"type":"Point"}
}