{
  "type": "Feature",
  "properties": {
    "iso:country":"CH",
    "sg:address":"Triangelstrasse 3",
    "sg:city":"Herisau",
    "sg:orig_category":"Allgemeiner Hoch U Tiefbau Allgemeiner Hochbau",
    "sg:phone":"+41 71 292 30 30",
    "sg:postcode":"9100",
    "sg:province":"Appenzell Ausserrhoden",
    "wof:name":"Walo Bertschinger Ag St. Gallen, Filiale Kirchberg",
    "wof:placetype":"venue"
},
  "geometry": {"coordinates":[9.042801,47.414581],"type":"Point"}
}