{
  "type": "Feature",
  "properties": {
    "iso:country":"CH",
    "sg:address":"Durstgrabenstrasse 20",
    "sg:city":"Neuhausen",
    "sg:orig_category":"G\u00fcterbef\u00f6rderung im Strassenverkehr",
    "sg:phone":"+41 52 672 20 25",
    "sg:postcode":"8212",
    "sg:province":"Schaffhausen",
    "wof:name":"Belyatrans Gmbh",
    "wof:placetype":"venue"
},
  "geometry": {"coordinates":[8.6065502167,47.6776924133],"type":"Point"}
}