{
  "type": "Feature",
  "properties": {
    "iso:country":"CH",
    "sg:address":"D\u00e4ttlikonerstr. 6",
    "sg:city":"Pfungen",
    "sg:classifiers":[
        {
            "category":"Manufacturing",
            "subcategory":"Wood Products",
            "type":"Manufacturing & Wholesale Goods"
        }
    ],
    "sg:phone":"+41 52 315 25 45",
    "sg:postcode":"8422",
    "sg:province":"Z\u00fcrich",
    "sg:tags":[
        "household",
        "furniture",
        "game",
        "miscellaneous",
        "entertainment"
    ],
    "wof:name":"Bamag Babyartikel & M\u00d6bel Ag",
    "wof:placetype":"venue"
},
  "geometry": {"coordinates":[8.6380357742,47.5181159973],"type":"Point"}
}