{
  "type": "Feature",
  "properties": {
    "iso:country":"CH",
    "sg:address":"6405",
    "sg:city":"Immensee",
    "sg:orig_category":"Schulpflegen",
    "sg:phone":"+41 41 850 17 79",
    "sg:postcode":"6405",
    "sg:province":"Schwyz",
    "wof:name":"Schulpflege Der Gemeinde Immensee",
    "wof:placetype":"venue"
},
  "geometry": {"coordinates":[8.4635696411,47.0969085693],"type":"Point"}
}