{
  "type": "Feature",
  "properties": {
    "iso:country":"CH",
    "sg:address":"Friedhofstrasse 16",
    "sg:city":"Zollikon",
    "sg:orig_category":"Reiseb\u00fcros U Reiseveranstalter",
    "sg:postcode":"8702",
    "sg:province":"Z\u00fcrich",
    "wof:name":"Worldwide Executive Travel, Rolf M. Iten",
    "wof:placetype":"venue"
},
  "geometry": {"coordinates":[8.5780992508,47.3367462158],"type":"Point"}
}