{
  "type": "Feature",
  "properties": {
    "iso:country":"CH",
    "sg:address":"Wenkenhaldenweg 15",
    "sg:city":"Riehen",
    "sg:orig_category":"Softwareentwicklung U beratung",
    "sg:phone":"+41 61 641 00 00",
    "sg:postcode":"4125",
    "sg:province":"Basel-Stadt",
    "wof:name":"Hermann Software",
    "wof:placetype":"venue"
},
  "geometry": {"coordinates":[7.6536560059,47.5788040161],"type":"Point"}
}