{
  "type": "Feature",
  "properties": {
    "iso:country":"CH",
    "sg:address":"Industriestrasse 31",
    "sg:city":"Frauenfeld",
    "sg:orig_category":"Detailhandel mit Lederwaren U Reiseartikeln Detailhandel mit Sportartikeln",
    "sg:phone":"+41 52 728 89 35",
    "sg:postcode":"8500",
    "sg:province":"Thurgau",
    "wof:name":"Marc's Lederatelier Marc De Meyer",
    "wof:placetype":"venue"
},
  "geometry": {"coordinates":[8.8942699432,47.5615615845],"type":"Point"}
}