{
  "type": "Feature",
  "properties": {
    "iso:country":"CH",
    "sg:address":"Landstrasse 115",
    "sg:city":"Wettingen",
    "sg:orig_category":"Drogerien",
    "sg:phone":"+41 56 426 73 64",
    "sg:postcode":"5430",
    "sg:province":"Aargau",
    "wof:name":"Dropa Gautschi & H\u00f6rler Ag Drogerie",
    "wof:placetype":"venue"
},
  "geometry": {"coordinates":[8.3294363022,47.4647712708],"type":"Point"}
}