{
  "type": "Feature",
  "properties": {
    "addr:full":"Gotthardstrasse 119 Erstfeld Uri 6472",
    "addr:housenumber":"119",
    "addr:postcode":"6472",
    "addr:street":"Gotthardstrasse;Uri",
    "iso:country":"CH",
    "sg:address":"Gotthardstrasse 119",
    "sg:city":"Erstfeld",
    "sg:orig_category":"Detailhandel mit B\u00fcchern",
    "sg:phone":"+41 41 880 01 01",
    "sg:postcode":"6472",
    "sg:province":"Uri",
    "wof:name":"Bido Ag Papeterie & Buchhandlung",
    "wof:placetype":"venue"
},
  "geometry": {"coordinates":[8.650068,46.824097],"type":"Point"}
}