{
  "type": "Feature",
  "properties": {
    "iso:country":"CH",
    "sg:address":"Steingasse 2",
    "sg:city":"Grossdietwil",
    "sg:orig_category":"Vermittlung von Immobilien Verwaltung von Immobilien",
    "sg:phone":"+41 62 927 25 85",
    "sg:postcode":"6146",
    "sg:province":"Luzern",
    "wof:name":"Koffel & Partner Ag, Dipl. Architekten Htl-stv",
    "wof:placetype":"venue"
},
  "geometry": {"coordinates":[7.8913631439,47.1705551147],"type":"Point"}
}