{
  "type": "Feature",
  "properties": {
    "iso:country":"CH",
    "sg:address":"Nidermattstrasse 8",
    "sg:city":"Birr",
    "sg:orig_category":"RESTAURANTS: TEA-ROOMS",
    "sg:phone":"+41 56 444 94 75",
    "sg:postcode":"5242",
    "sg:province":"Aargau",
    "wof:name":"Caf\u00e9 Carina",
    "wof:placetype":"venue"
},
  "geometry": {"coordinates":[8.2068223953,47.4374237061],"type":"Point"}
}