{
  "type": "Feature",
  "properties": {
    "iso:country":"CH",
    "sg:address":"Niederweg 17",
    "sg:city":"Wettswil",
    "sg:orig_category":"Sanit\u00e4r U Heizungsinstallation Sanit\u00e4r, Heizungs U L\u00fcftungsinstallation",
    "sg:phone":"+41 17011219",
    "sg:postcode":"8907",
    "sg:province":"Z\u00fcrich",
    "wof:name":"Denger Heizungen Ag",
    "wof:placetype":"venue"
},
  "geometry": {"coordinates":[8.4756269455,47.3324432373],"type":"Point"}
}