{
  "type": "Feature",
  "properties": {
    "iso:country":"CH",
    "sg:address":"Schwimmbad",
    "sg:city":"Aarberg",
    "sg:orig_category":"Sportvereine Wassersport",
    "sg:phone":"+41 32 392 41 16",
    "sg:postcode":"3270",
    "sg:province":"Bern",
    "wof:name":"Wassersportgruppe",
    "wof:placetype":"venue"
},
  "geometry": {"coordinates":[7.2756547928,47.0425682068],"type":"Point"}
}