{
  "type": "Feature",
  "properties": {
    "addr:full":"Burggartenstrasse 7 4133 Pratteln. Postfach Pratteln Basel-Landschaft 4133",
    "addr:housenumber":"7",
    "addr:postcode":"4133 pratteln. postfach;4133",
    "addr:street":"Burggartenstrasse",
    "iso:country":"CH",
    "sg:address":"Burggartenstrasse 7 4133 Pratteln. Postfach",
    "sg:city":"Pratteln",
    "sg:orig_category":"Betrieb U technische Hilfsdienste des Kultur U Unterhaltungswesens",
    "sg:postcode":"4133",
    "sg:province":"Basel-Landschaft",
    "wof:name":"Verein Sakarya",
    "wof:placetype":"venue"
},
  "geometry": {"coordinates":[7.693367,47.521435],"type":"Point"}
}