{
  "type": "Feature",
  "properties": {
    "iso:country":"CH",
    "sg:address":"Morillonstrasse 8 & 10",
    "sg:city":"Bern",
    "sg:classifiers":[
        {
            "category":"Restaurant",
            "type":"Food & Drink"
        }
    ],
    "sg:phone":"+41 31 371 20 71",
    "sg:postcode":"3007",
    "sg:province":"Bern",
    "wof:name":"Bistrot Morillon",
    "wof:placetype":"venue"
},
  "geometry": {"coordinates":[7.4358019829,46.9364356995],"type":"Point"}
}