{
  "type": "Feature",
  "properties": {
    "iso:country":"CH",
    "sg:address":"Rue De Bourg 9",
    "sg:city":"Lausanne",
    "sg:orig_category":"Detailhandel mit Bekleidung Detailhandel mit Damenbekleidung",
    "sg:phone":"+41 12611255",
    "sg:postcode":"1003",
    "sg:province":"Vaud",
    "wof:name":"Vero Moda Retail Sa",
    "wof:placetype":"venue"
},
  "geometry": {"coordinates":[6.63529,46.520164],"type":"Point"}
}