{
  "type": "Feature",
  "properties": {
    "iso:country":"CH",
    "sg:address":"Hauptstrasse",
    "sg:city":"Sedrun",
    "sg:orig_category":"Sanit\u00e4r, Heizungs U L\u00fcftungsinstallation",
    "sg:postcode":"7188",
    "sg:province":"Graubunden",
    "wof:name":"Cavegn F.",
    "wof:placetype":"venue"
},
  "geometry": {"coordinates":[8.7735700607,46.6795310974],"type":"Point"}
}