{
  "type": "Feature",
  "properties": {
    "iso:country":"CH",
    "sg:address":"Avant-poste Avenue De L' 6 1005 Lausanne. Postfach",
    "sg:city":"Lausanne",
    "sg:orig_category":"Detailhandel mit Waren verschiedener Art, Hauptrichtung Nahrungsmittel",
    "sg:phone":"+41 21 323 88 35",
    "sg:postcode":"1005",
    "sg:province":"Vaud",
    "wof:name":"In-look, L\u00e9vy Ronald",
    "wof:placetype":"venue"
},
  "geometry": {"coordinates":[6.5851950645,46.5399665833],"type":"Point"}
}