{
  "type": "Feature",
  "properties": {
    "iso:country":"CH",
    "sg:address":"Pfistergasse 38 4800 Zofingen. Postfach 43",
    "sg:city":"Zofingen",
    "sg:orig_category":"Kauf U Verkauf von Immobilien auf eigene Rechnung Vermittlung von Immobilien",
    "sg:phone":"+41 62 745 02 50",
    "sg:postcode":"4800",
    "sg:province":"Aargau",
    "wof:name":"Itz Immobilien-treuhand Ag Zofingen",
    "wof:placetype":"venue"
},
  "geometry": {"coordinates":[7.9450569153,47.2873382568],"type":"Point"}
}