{
  "type": "Feature",
  "properties": {
    "addr:full":"Route De La Vuy 1 Penthalaz Vaud 1305",
    "addr:housenumber":"1",
    "addr:postcode":"1305",
    "addr:street":"Route De La Vuy",
    "iso:country":"CH",
    "sg:address":"Route De La Vuy 1",
    "sg:city":"Penthalaz",
    "sg:classifiers":[
        {
            "category":"Social Services",
            "subcategory":"Retirement Home",
            "type":"Services"
        }
    ],
    "sg:phone":"+41 21 863 03 33",
    "sg:postcode":"1305",
    "sg:province":"Vaud",
    "sg:tags":[
        "pflegeheime",
        "u",
        "alters"
    ],
    "wof:name":"Etablissement M\u00e9dico-social La Venoge",
    "wof:placetype":"venue"
},
  "geometry": {"coordinates":[6.525793,46.609066],"type":"Point"}
}