{
  "type": "Feature",
  "properties": {
    "iso:country":"CH",
    "sg:address":"3672",
    "sg:city":"Oberdiessbach",
    "sg:orig_category":"Pensionskassen",
    "sg:postcode":"3672",
    "sg:province":"Bern",
    "wof:name":"Personalf\u00fcrsorgestiftung Der Ziegelei Oberdiessbach Ag",
    "wof:placetype":"venue"
},
  "geometry": {"coordinates":[7.6189479828,46.8401603699],"type":"Point"}
}