{
  "type": "Feature",
  "properties": {
    "iso:country":"CH",
    "sg:address":"1978",
    "sg:city":"Lens",
    "sg:orig_category":"Instandhaltung U Reparatur von Automobilen",
    "sg:phone":"+41 39260455",
    "sg:postcode":"1978",
    "sg:province":"Valais",
    "wof:name":"Garage Et Carrosserie Des Eplatures Guinand Roland Et Sbarzella Daniel Sa",
    "wof:placetype":"venue"
},
  "geometry": {"coordinates":[6.8036379814,47.0873794556],"type":"Point"}
}