{
  "type": "Feature",
  "properties": {
    "iso:country":"CH",
    "sg:address":"Schwarzwaldstrasse 7",
    "sg:city":"Urdorf",
    "sg:orig_category":"Unclassifiable Establishments",
    "sg:postcode":"8902",
    "sg:province":"Z\u00fcrich",
    "wof:name":"Skibo-sport Group",
    "wof:placetype":"venue"
},
  "geometry": {"coordinates":[8.4345264435,47.3884086609],"type":"Point"}
}