{
  "type": "Feature",
  "properties": {
    "iso:country":"CH",
    "sg:address":"Wengistrasse 1 8004 Z\u00fcrich. Postfach",
    "sg:city":"Z\u00fcrich",
    "sg:classifiers":[
        {
            "category":"Cinema",
            "subcategory":"Movie Theater",
            "type":"Entertainment"
        }
    ],
    "sg:phone":"+41 12913949",
    "sg:postcode":"8026",
    "sg:province":"Z\u00fcrich",
    "sg:tags":[
        "radio",
        "videofilmherstellung",
        "fernsehanstalten",
        "u",
        "film"
    ],
    "wof:name":"Publisuisse Sa",
    "wof:placetype":"venue"
},
  "geometry": {"coordinates":[8.5237846375,47.3746795654],"type":"Point"}
}