{
  "type": "Feature",
  "properties": {
    "iso:country":"CH",
    "sg:address":"Helvetiastrasse 53",
    "sg:city":"St.gallen",
    "sg:orig_category":"Herstellung von sonstigen Maschinen f\u00fcr unspezifische Verwendung",
    "sg:postcode":"9000",
    "sg:province":"St. Gallen",
    "wof:name":"Mip-ag Zweigniederlassung St. Gallen.",
    "wof:placetype":"venue"
},
  "geometry": {"coordinates":[9.3954210281,47.4342803955],"type":"Point"}
}