{
  "type": "Feature",
  "properties": {
    "iso:country":"CH",
    "sg:address":"Grundstrasse 16",
    "sg:city":"Rotkreuz",
    "sg:classifiers":[
        {
            "category":"Professional",
            "subcategory":"Computer Services",
            "type":"Services"
        }
    ],
    "sg:phone":"+41 41 798 11 22",
    "sg:postcode":"6343",
    "sg:province":"Zug",
    "sg:tags":[
        "administration",
        "software"
    ],
    "wof:name":"Codx Software Ag",
    "wof:placetype":"venue"
},
  "geometry": {"coordinates":[8.430782,47.146004],"type":"Point"}
}