{
  "type": "Feature",
  "properties": {
    "iso:country":"CH",
    "sg:address":"Kirschgartenweg 7",
    "sg:city":"Dornach",
    "sg:orig_category":"Organisationen des Gesundheitswesen",
    "sg:phone":"+41 61 701 61 59",
    "sg:postcode":"4143",
    "sg:province":"Solothurn",
    "wof:name":"Kranken-& Hauspflegeverein Hans Zeltner",
    "wof:placetype":"venue"
},
  "geometry": {"coordinates":[7.6137018204,47.479019165],"type":"Point"}
}