{
  "type": "Feature",
  "properties": {
    "iso:country":"CH",
    "sg:address":"Hofmatt 6430 Schwyz. Postfach",
    "sg:city":"Schwyz",
    "sg:orig_category":"Museen",
    "sg:phone":"+41 61 731 11 87",
    "sg:postcode":"6431",
    "sg:province":"Schwyz",
    "wof:name":"Forum Fl\u00fch Bezzola & Co",
    "wof:placetype":"venue"
},
  "geometry": {"coordinates":[7.5159811974,47.475692749],"type":"Point"}
}