{
  "type": "Feature",
  "properties": {
    "iso:country":"CH",
    "sg:address":"Alter Hubelweg 4",
    "sg:city":"H\u00fcnenberg",
    "sg:orig_category":"Herstellung von Metallkonstruktionen",
    "sg:postcode":"6331",
    "sg:province":"Zug",
    "wof:name":"Montageteam Stieger J\u00fcrgen + Wintsch Daniel",
    "wof:placetype":"venue"
},
  "geometry": {"coordinates":[8.5908794403,47.3055839539],"type":"Point"}
}