{
  "type": "Feature",
  "properties": {
    "iso:country":"CH",
    "sg:address":"Les Jonch\u00e8res 31b 2022 Bevaix. Postfach",
    "sg:city":"Bevaix",
    "sg:orig_category":"Unternehmensberatung",
    "sg:postcode":"2022",
    "sg:province":"Neuch\u00e2tel",
    "wof:name":"Junod.ch Junod Nicolas Conseils Et Activit\u00e9s De Management Dans Divers Secteurs Op\u00e9rationnels Etc",
    "wof:placetype":"venue"
},
  "geometry": {"coordinates":[6.809428215,46.9249382019],"type":"Point"}
}