{
  "type": "Feature",
  "properties": {
    "iso:country":"CH",
    "sg:address":"Gemeindestrasse 63",
    "sg:city":"Z\u00fcrich",
    "sg:orig_category":"Detailhandel mit Schreib U Papeteriewaren",
    "sg:phone":"+41 12615346",
    "sg:postcode":"8032",
    "sg:province":"Z\u00fcrich",
    "wof:name":"Anita Pastorini Papeterie",
    "wof:placetype":"venue"
},
  "geometry": {"coordinates":[8.5557289124,47.3696937561],"type":"Point"}
}