{
  "type": "Feature",
  "properties": {
    "iso:country":"CH",
    "sg:address":"S\u00e4gestrasse 75 3098 K\u00f6niz. Postfach 549",
    "sg:city":"K\u00f6niz",
    "sg:orig_category":"Offsetdruck Satzherstellung U Reproduktion",
    "sg:phone":"+41 19531110",
    "sg:postcode":"3098",
    "sg:province":"Bern",
    "wof:name":"Quadrascan File House Ag Reproduktionsherstellung Im Graphischen Gewerbe, Bes. Offsetdruck Usw",
    "wof:placetype":"venue"
},
  "geometry": {"coordinates":[8.7730283737,47.3658180237],"type":"Point"}
}