{
  "type": "Feature",
  "properties": {
    "iso:country":"CH",
    "sg:address":"Altkircherstrasse 26",
    "sg:city":"Basel",
    "sg:orig_category":"Reparatur von Schuhen U Lederwaren",
    "sg:phone":"+41 61 301 24 78",
    "sg:postcode":"4054",
    "sg:province":"Basel-Stadt",
    "wof:name":"Antonino Todaro Expess Schuhservice Nino",
    "wof:placetype":"venue"
},
  "geometry": {"coordinates":[7.569565773,47.5536117554],"type":"Point"}
}