{
  "type": "Feature",
  "properties": {
    "iso:country":"CH",
    "sg:address":"Bettlachstrasse 7",
    "sg:city":"Grenchen",
    "sg:orig_category":"Unclassifiable Establishments",
    "sg:postcode":"2540",
    "sg:province":"Solothurn",
    "wof:name":"Caf\u00e9 M\u00fcnz Monika Schmidlin",
    "wof:placetype":"venue"
},
  "geometry": {"coordinates":[8.5804462433,47.3186416626],"type":"Point"}
}