{
  "type": "Feature",
  "properties": {
    "iso:country":"CH",
    "sg:address":"Jurastrasse 48",
    "sg:city":"Wettingen",
    "sg:orig_category":"Mechanik",
    "sg:postcode":"5430",
    "sg:province":"Aargau",
    "wof:name":"F. Rafanelli",
    "wof:placetype":"venue"
},
  "geometry": {"coordinates":[8.3309640884,47.4583396912],"type":"Point"}
}