{
  "type": "Feature",
  "properties": {
    "iso:country":"CH",
    "sg:address":"Oberstm\u00fchle 10 6370 Stans. Postfach 1058",
    "sg:city":"Stans",
    "sg:orig_category":"G\u00fcterbef\u00f6rderung im Strassenverkehr R\u00fcckgewinnung U Vorbereitung f\u00fcr die Wiederverwertung Recycling",
    "sg:phone":"+41 41 624 91 91",
    "sg:postcode":"6371",
    "sg:province":"Nidwalden",
    "wof:name":"Thepra Trans Ag",
    "wof:placetype":"venue"
},
  "geometry": {"coordinates":[8.3558149338,46.9682922363],"type":"Point"}
}