{
  "type": "Feature",
  "properties": {
    "addr:full":"Seeblickstrasse 7 Altnau Thurgau 8595",
    "addr:housenumber":"7",
    "addr:postcode":"8595",
    "addr:street":"Seeblickstrasse",
    "iso:country":"CH",
    "sg:address":"Seeblickstrasse 7",
    "sg:city":"Altnau",
    "sg:orig_category":"Architektur U Ingenieurb\u00fcros",
    "sg:phone":"+41 71 694 50 70",
    "sg:postcode":"8595",
    "sg:province":"Thurgau",
    "wof:name":"Eah-haueter Kunststoffrecycling Gmbh",
    "wof:placetype":"venue"
},
  "geometry": {"coordinates":[9.265921,47.619919],"type":"Point"}
}