{
  "type": "Feature",
  "properties": {
    "iso:country":"CH",
    "sg:address":"W\u00fclflingerstrasse 36",
    "sg:city":"Winterthur",
    "sg:orig_category":"Gartenbau",
    "sg:phone":"+41 52 213 74 78",
    "sg:postcode":"8400",
    "sg:province":"Z\u00fcrich",
    "wof:name":"Das Garten-team Egli & Steffen",
    "wof:placetype":"venue"
},
  "geometry": {"coordinates":[8.7174320221,47.5054244995],"type":"Point"}
}