{
  "type": "Feature",
  "properties": {
    "iso:country":"CH",
    "sg:address":"B\u00fchlbrunnen",
    "sg:city":"Unter\u00e4geri",
    "sg:orig_category":"Pensionskassen",
    "sg:phone":"+41 19321844",
    "sg:postcode":"6314",
    "sg:province":"Zug",
    "wof:name":"F\u00fcrsorgestiftung Der Aquarex Bauchemie Ag",
    "wof:placetype":"venue"
},
  "geometry": {"coordinates":[8.7984800339,47.3245201111],"type":"Point"}
}