{
  "type": "Feature",
  "properties": {
    "iso:country":"CH",
    "sg:address":"Solibodenstrasse 4",
    "sg:city":"B\u00fclach",
    "sg:orig_category":"Werbung",
    "sg:postcode":"8180",
    "sg:province":"Z\u00fcrich",
    "wof:name":"Hj Werbung, Hollenstein",
    "wof:placetype":"venue"
},
  "geometry": {"coordinates":[8.5407733917,47.5259971619],"type":"Point"}
}