{
  "type": "Feature",
  "properties": {
    "iso:country":"CH",
    "sg:address":"Hauptstrasse 9",
    "sg:city":"Hochdorf",
    "sg:orig_category":"P\u00e9dicure",
    "sg:phone":"+41 41 910 38 55",
    "sg:postcode":"6280",
    "sg:province":"Luzern",
    "wof:name":"Priska Keist Pedicure",
    "wof:placetype":"venue"
},
  "geometry": {"coordinates":[8.290397644,47.1662788391],"type":"Point"}
}