{
  "type": "Feature",
  "properties": {
    "iso:country":"CH",
    "sg:address":"1882",
    "sg:city":"Gryon",
    "sg:orig_category":"Personenbef\u00f6rderung im Linienverkehr zu Land",
    "sg:phone":"+41 24 498 17 33",
    "sg:postcode":"1882",
    "sg:province":"Vaud",
    "wof:name":"T\u00e9l\u00e9-villars-gryon Sa",
    "wof:placetype":"venue"
},
  "geometry": {"coordinates":[7.0617899895,46.2738685608],"type":"Point"}
}