{
  "type": "Feature",
  "properties": {
    "iso:country":"CH",
    "sg:address":"Z\u00fcrichstrasse 77 8134 Adliswil. Postfach",
    "sg:city":"Adliswil",
    "sg:orig_category":"Dienstleistungen von Beteiligungsgesellschaften Grosshandel mit Wein U Spirituosen",
    "sg:phone":"+41 17100548",
    "sg:postcode":"8134",
    "sg:province":"Z\u00fcrich",
    "wof:name":"M\u00f6venpick Dienstleistungs Ag",
    "wof:placetype":"venue"
},
  "geometry": {"coordinates":[8.5286207199,47.3224334717],"type":"Point"}
}