{
  "type": "Feature",
  "properties": {
    "iso:country":"CH",
    "sg:address":"Gerbergasse 4",
    "sg:city":"Basel",
    "sg:orig_category":"Grosshandel mit sonstigen Konsumg\u00fctern",
    "sg:phone":"+41 55 442 59 57",
    "sg:postcode":"4001",
    "sg:province":"Basel-Stadt",
    "wof:name":"Max K\u00e4gi Ag Textil-vertretungen",
    "wof:placetype":"venue"
},
  "geometry": {"coordinates":[8.8568134308,47.1897125244],"type":"Point"}
}