{
  "type": "Feature",
  "properties": {
    "iso:country":"CH",
    "sg:address":"1373",
    "sg:city":"Chavornay",
    "sg:orig_category":"Lagerung",
    "sg:phone":"+41 22 798 90 07",
    "sg:postcode":"1373",
    "sg:province":"Vaud",
    "wof:name":"Ports Francs Et Entrep\u00f4ts De Gen\u00e8ve Sa",
    "wof:placetype":"venue"
},
  "geometry": {"coordinates":[6.1414251328,46.1833114624],"type":"Point"}
}