{
  "type": "Feature",
  "properties": {
    "iso:country":"CH",
    "sg:address":"Place Du March\u00e9",
    "sg:city":"Aigle",
    "sg:orig_category":"Detailhandel mit M\u00f6beln Verlegen von Fussboden",
    "sg:phone":"+41 24 466 26 13",
    "sg:postcode":"1860",
    "sg:province":"Vaud",
    "wof:name":"Raymond Gutknecht D\u00e9coration D'int\u00e9rieur Meubles",
    "wof:placetype":"venue"
},
  "geometry": {"coordinates":[6.9701099396,46.3175544739],"type":"Point"}
}