{
  "type": "Feature",
  "properties": {
    "iso:country":"CH",
    "sg:address":"Im G\u00fcggelbach 2",
    "sg:city":"Ettingen",
    "sg:classifiers":[
        {
            "category":"Banks & Credit Unions",
            "subcategory":"Bank",
            "type":"Services"
        }
    ],
    "sg:phone":"+41 4161731060",
    "sg:postcode":"4107",
    "sg:province":"Basel-Landschaft",
    "wof:name":"Raiffeisenkasse",
    "wof:placetype":"venue"
},
  "geometry": {"coordinates":[7.545559,47.479076],"type":"Point"}
}