{
  "type": "Feature",
  "properties": {
    "iso:country":"CH",
    "sg:address":"Bahnhofstr. 58 8200 Schaffhausen. Postfach",
    "sg:city":"Schaffhausen",
    "sg:orig_category":"RESTAURANTS: TEA-ROOMS",
    "sg:postcode":"8201",
    "sg:province":"Schaffhausen",
    "wof:name":"Wyss Franz",
    "wof:placetype":"venue"
},
  "geometry": {"coordinates":[8.6340103149,47.69896698],"type":"Point"}
}