{
  "type": "Feature",
  "properties": {
    "iso:country":"CH",
    "sg:address":"Luzernerstrasse 7 4800 Zofingen. Postfach",
    "sg:city":"Zofingen",
    "sg:orig_category":"Architektur U Ingenieurb\u00fcros Detailhandel mit M\u00f6beln",
    "sg:phone":"+41 62 751 44 51",
    "sg:postcode":"4800",
    "sg:province":"Aargau",
    "wof:name":"Ueli Frauchiger Design Ag",
    "wof:placetype":"venue"
},
  "geometry": {"coordinates":[7.948213,47.284328],"type":"Point"}
}