{
  "type": "Feature",
  "properties": {
    "iso:country":"CH",
    "sg:address":"1914",
    "sg:city":"Is\u00e9rables",
    "sg:orig_category":"Grossbanken",
    "sg:phone":"+41 844 800 844",
    "sg:postcode":"1914",
    "sg:province":"Valais",
    "wof:name":"Credit Suisse",
    "wof:placetype":"venue"
},
  "geometry": {"coordinates":[7.24518013,46.1604385376],"type":"Point"}
}