{
  "type": "Feature",
  "properties": {
    "iso:country":"CH",
    "sg:address":"H\u00f6ckleri 23 8967 Widen. Postfach",
    "sg:city":"Bern",
    "sg:orig_category":"Erbringung von Dienstleistungen f\u00fcr Unternehmen",
    "sg:phone":"+41 31 313 33 33",
    "sg:postcode":"3005",
    "sg:province":"Bern",
    "wof:name":"Wellness Events Gmbh",
    "wof:placetype":"venue"
},
  "geometry": {"coordinates":[8.358549118,47.3710174561],"type":"Point"}
}