{
  "type": "Feature",
  "properties": {
    "iso:country":"CH",
    "sg:address":"Hauptstrasse 13",
    "sg:city":"Ligerz",
    "sg:orig_category":"Wirtschaftsverb\u00e4nde Industrie, Handel and Gewerbe",
    "sg:phone":"+41 31 332 85 83",
    "sg:postcode":"2514",
    "sg:province":"Bern",
    "wof:name":"Schweizerischer Verband Der Spielzeuglieferanten",
    "wof:placetype":"venue"
},
  "geometry": {"coordinates":[7.4001741409,46.9423446655],"type":"Point"}
}