{
  "type": "Feature",
  "properties": {
    "iso:country":"CH",
    "sg:address":"R\u00e4bengasse 10",
    "sg:city":"Steinen",
    "sg:orig_category":"Einzelhandel mit Automobilteilen U Zubeh\u00f6r Instandhaltung U Reparatur von Automobilen",
    "sg:phone":"+41 31 981 36 32",
    "sg:postcode":"6422",
    "sg:province":"Schwyz",
    "wof:name":"Meier Ag Garage Autoelektro Pneuhaus",
    "wof:placetype":"venue"
},
  "geometry": {"coordinates":[7.3798308372,46.9275169373],"type":"Point"}
}