{
  "type": "Feature",
  "properties": {
    "iso:country":"CH",
    "sg:address":"Theaterstr. 5",
    "sg:city":"Luzern",
    "sg:classifiers":[
        {
            "category":"Banks & Credit Unions",
            "subcategory":"Bank",
            "type":"Services"
        }
    ],
    "sg:phone":"+41 4141233247",
    "sg:postcode":"6003",
    "sg:province":"Luzern",
    "wof:name":"Luzerner Kantonalbank",
    "wof:placetype":"venue"
},
  "geometry": {"coordinates":[8.306729,47.050289],"type":"Point"}
}