{
  "type": "Feature",
  "properties": {
    "iso:country":"CH",
    "sg:address":"Savoie Rue Louis De 92 1110 Morges. Postfach",
    "sg:city":"Lausanne",
    "sg:orig_category":"Unclassifiable Establishments",
    "sg:phone":"+41 21 320 60 45",
    "sg:postcode":"1003",
    "sg:province":"Vaud",
    "wof:name":"Socora Holding Sa Participations Etc",
    "wof:placetype":"venue"
},
  "geometry": {"coordinates":[6.4971051216,46.5074272156],"type":"Point"}
}