{
  "type": "Feature",
  "properties": {
    "iso:country":"CH",
    "sg:address":"Z\u00fcrcherstrasse 300",
    "sg:city":"Frauenfeld",
    "sg:orig_category":"Sanit\u00e4r, Heizungs U L\u00fcftungsinstallation",
    "sg:phone":"+41 21 960 11 19",
    "sg:postcode":"8500",
    "sg:province":"Thurgau",
    "wof:name":"Henry Louis Sa, Chauffages Centraux",
    "wof:placetype":"venue"
},
  "geometry": {"coordinates":[6.9246211052,46.3967247009],"type":"Point"}
}