{
  "type": "Feature",
  "properties": {
    "iso:country":"CH",
    "sg:address":"Friedhofstrasse 54",
    "sg:city":"Z\u00fcrich",
    "sg:orig_category":"Unclassifiable Establishments",
    "sg:postcode":"8048",
    "sg:province":"Z\u00fcrich",
    "wof:name":"Vinolio Rolf Meier",
    "wof:placetype":"venue"
},
  "geometry": {"coordinates":[8.4782514572,47.3852615356],"type":"Point"}
}