{
  "type": "Feature",
  "properties": {
    "iso:country":"CH",
    "sg:address":"8558",
    "sg:city":"Raperswilen",
    "sg:orig_category":"Vereine Gesang",
    "sg:postcode":"8558",
    "sg:province":"Thurgau",
    "wof:name":"M\u00e4nnerchor Rapperswil",
    "wof:placetype":"venue"
},
  "geometry": {"coordinates":[8.7995347977,47.2133331299],"type":"Point"}
}