{
  "type": "Feature",
  "properties": {
    "iso:country":"CH",
    "sg:address":"Bielstrasse 18 4500 Solothurn. Postfach 944",
    "sg:city":"Solothurn",
    "sg:orig_category":"Versicherungen Generalagenturen",
    "sg:phone":"+41 32 625 76 76",
    "sg:postcode":"4502",
    "sg:province":"Solothurn",
    "wof:name":"La Suisse Versicherungen Generalagentur",
    "wof:placetype":"venue"
},
  "geometry": {"coordinates":[7.5319519043,47.209148407],"type":"Point"}
}