{
  "type": "Feature",
  "properties": {
    "iso:country":"CH",
    "sg:address":"Rue De La Borde 77",
    "sg:city":"Lausanne",
    "sg:orig_category":"Maschinenbau",
    "sg:phone":"+41 81 740 60 90",
    "sg:postcode":"1018",
    "sg:province":"Vaud",
    "wof:name":"Egra-engineering",
    "wof:placetype":"venue"
},
  "geometry": {"coordinates":[9.488992691,47.207988739],"type":"Point"}
}