{
  "type": "Feature",
  "properties": {
    "iso:country":"CH",
    "sg:address":"Hardstr. 49 4802 Strengelbach. Postfach 49",
    "sg:city":"Strengelbach",
    "sg:orig_category":"Herstellung von Ger\u00e4ten der Elektrizit\u00e4tserzeugung, -verteilung u.\u00e4. -Herstellung von sonstigen elek",
    "sg:phone":"+41 52 747 21 61",
    "sg:postcode":"4802",
    "sg:province":"Aargau",
    "wof:name":"Meuli H. Sensortechnik",
    "wof:placetype":"venue"
},
  "geometry": {"coordinates":[8.887421608,47.5895500183],"type":"Point"}
}