{
  "type": "Feature",
  "properties": {
    "iso:country":"CH",
    "sg:address":"Sonnenbergstrasse 10",
    "sg:city":"Heiden",
    "sg:orig_category":"Vermietung U Verpachtung von eigenen Immobilien Vermittlung von Immobilien",
    "sg:phone":"+41 26 351 66 66",
    "sg:postcode":"9410",
    "sg:province":"Appenzell Ausserrhoden",
    "wof:name":"Immobilier Cl\u00e9ment Sa",
    "wof:placetype":"venue"
},
  "geometry": {"coordinates":[7.1471509933,46.7546577454],"type":"Point"}
}