{
  "type": "Feature",
  "properties": {
    "iso:country":"CH",
    "sg:address":"Rathausplatz 3 6210 Sursee. Postfach 3146",
    "sg:city":"Sursee",
    "sg:orig_category":"Detailhandel mit Textilien Herstellung von konfektionierten Textilwaren ohne Bekleidung",
    "sg:phone":"+41 41 921 26 68",
    "sg:postcode":"6210",
    "sg:province":"Luzern",
    "wof:name":"Kottmann Heimtextilien Ag",
    "wof:placetype":"venue"
},
  "geometry": {"coordinates":[8.1093196869,47.1730461121],"type":"Point"}
}