{
  "type": "Feature",
  "properties": {
    "addr:full":"Riva Caccia 1 Lugano Ticino 6900",
    "addr:housenumber":"1",
    "addr:postcode":"6900",
    "addr:street":"Riva Caccia",
    "iso:country":"CH",
    "sg:address":"Riva Caccia 1",
    "sg:city":"Lugano",
    "sg:orig_category":"Advokaturb\u00fcros",
    "sg:phone":"+41 79 686 42 47",
    "sg:postcode":"6900",
    "sg:province":"Ticino",
    "wof:name":"Cesare Forni Studio Legale",
    "wof:placetype":"venue"
},
  "geometry": {"coordinates":[8.947586,45.998035],"type":"Point"}
}