{
  "type": "Feature",
  "properties": {
    "iso:country":"CH",
    "sg:address":"Moosstrasse 7",
    "sg:city":"Luzern",
    "sg:orig_category":"RESTAURANTS: TEA-ROOMS",
    "sg:postcode":"6003",
    "sg:province":"Luzern",
    "wof:name":"Cash Events Gmbh",
    "wof:placetype":"venue"
},
  "geometry": {"coordinates":[8.3049650192,47.0458602905],"type":"Point"}
}