{
  "type": "Feature",
  "properties": {
    "iso:country":"CH",
    "sg:address":"Hardturmstrasse 106",
    "sg:city":"Z\u00fcrich",
    "sg:orig_category":"Autogaragen",
    "sg:phone":"+41 12725875",
    "sg:postcode":"8005",
    "sg:province":"Z\u00fcrich",
    "wof:name":"Ferdi Bender Auto-service",
    "wof:placetype":"venue"
},
  "geometry": {"coordinates":[8.51605,47.392696],"type":"Point"}
}