{
  "type": "Feature",
  "properties": {
    "iso:country":"CH",
    "sg:address":"Route De Montheron 8a",
    "sg:city":"Cugy",
    "sg:classifiers":[
        {
            "category":"Education",
            "subcategory":"Dance Studio",
            "type":"Public Place"
        }
    ],
    "sg:phone":"+41 21 731 51 47",
    "sg:postcode":"1053",
    "sg:province":"Vaud",
    "sg:tags":[
        "medicine",
        "homeopathic"
    ],
    "wof:name":"Laboratoire Hom\u00e9opatique De Recherche Kurtoglu Sa",
    "wof:placetype":"venue"
},
  "geometry": {"coordinates":[6.6446361542,46.5900497437],"type":"Point"}
}