{
  "type": "Feature",
  "properties": {
    "iso:country":"CH",
    "sg:address":"Rue Margencel 3 1860 Aigle Case Postale 133",
    "sg:city":"Aigle",
    "sg:orig_category":"Allgemeiner Hoch U Tiefbau Allgemeiner Hochbau",
    "sg:phone":"+41 34 402 52 98",
    "sg:postcode":"1860",
    "sg:province":"Vaud",
    "wof:name":"Marazzi Ag",
    "wof:placetype":"venue"
},
  "geometry": {"coordinates":[7.75759,46.949127],"type":"Point"}
}