{
  "type": "Feature",
  "properties": {
    "iso:country":"CH",
    "sg:address":"Les Grands Jardins 30",
    "sg:city":"Asuel",
    "sg:orig_category":"Allgemeiner Hoch U Tiefbau",
    "sg:postcode":"2954",
    "sg:province":"Jura",
    "wof:name":"G\u00fcttly Michel Sa",
    "wof:placetype":"venue"
},
  "geometry": {"coordinates":[7.211345,47.40107],"type":"Point"}
}