{
  "type": "Feature",
  "properties": {
    "iso:country":"CH",
    "sg:address":"Birnb\u00e4umenstrasse 36",
    "sg:city":"St.gallen",
    "sg:orig_category":"Erschliessung von Grundst\u00fccken",
    "sg:postcode":"9000",
    "sg:province":"St. Gallen",
    "wof:name":"Wohnbaugenossenschaft Birnb\u00e4umen",
    "wof:placetype":"venue"
},
  "geometry": {"coordinates":[9.3938102722,47.42760849],"type":"Point"}
}