{
  "type": "Feature",
  "properties": {
    "iso:country":"CH",
    "sg:address":"Fluhm\u00fchlerain 12",
    "sg:city":"Reussb\u00fchl",
    "sg:classifiers":[
        {
            "category":"Professional",
            "subcategory":"Advertising",
            "type":"Services"
        }
    ],
    "sg:phone":"+41 41 240 44 43",
    "sg:postcode":"6015",
    "sg:province":"Luzern",
    "sg:tags":[
        "agency"
    ],
    "wof:name":"Bossard Kommunikation Ag",
    "wof:placetype":"venue"
},
  "geometry": {"coordinates":[8.283688,47.056217],"type":"Point"}
}