{
  "type": "Feature",
  "properties": {
    "iso:country":"CH",
    "sg:address":"Voglingen",
    "sg:city":"Obstalden",
    "sg:orig_category":"Zimmerei, Dachdeckerei, Bauspenglerei U Abdichtung",
    "sg:postcode":"8758",
    "sg:province":"Glarus",
    "wof:name":"Chrigel Grob Spengler-montagen",
    "wof:placetype":"venue"
},
  "geometry": {"coordinates":[9.1632137299,47.1188774109],"type":"Point"}
}