{
  "type": "Feature",
  "properties": {
    "iso:country":"CH",
    "sg:address":"5618",
    "sg:city":"Bettwil",
    "sg:orig_category":"Politische Parteien CVP",
    "sg:phone":"+41 31 351 13 89",
    "sg:postcode":"5618",
    "sg:province":"Aargau",
    "wof:name":"Cvp Ortspartei Biel",
    "wof:placetype":"venue"
},
  "geometry": {"coordinates":[7.2486801147,47.1438102722],"type":"Point"}
}