{
  "type": "Feature",
  "properties": {
    "iso:country":"CH",
    "sg:address":"Zugerstrasse 47",
    "sg:city":"Cham",
    "sg:orig_category":"Detailhandel mit Damenbekleidung Detailhandel mit Herrenbekleidung",
    "sg:phone":"+41 41 780 70 30",
    "sg:postcode":"6330",
    "sg:province":"Zug",
    "wof:name":"Magic Fashion Boutique",
    "wof:placetype":"venue"
},
  "geometry": {"coordinates":[8.4666290283,47.1820144653],"type":"Point"}
}