{
  "type": "Feature",
  "properties": {
    "iso:country":"CH",
    "sg:address":"Louis Giroud-strasse 20",
    "sg:city":"Olten",
    "sg:orig_category":"Herstellung von Brot U Backwaren Herstellung von Dauerbackwaren",
    "sg:phone":"+41 62 296 46 70",
    "sg:postcode":"4600",
    "sg:province":"Solothurn",
    "wof:name":"Jowa Ag",
    "wof:placetype":"venue"
},
  "geometry": {"coordinates":[7.9096670151,47.3469963074],"type":"Point"}
}