{
  "type": "Feature",
  "properties": {
    "iso:country":"CH",
    "sg:address":"Aussereriz",
    "sg:city":"Eriz",
    "sg:orig_category":"Primarschulen",
    "sg:phone":"+41 19335490",
    "sg:postcode":"3619",
    "sg:province":"Bern",
    "wof:name":"Primarschule B\u00fchl",
    "wof:placetype":"venue"
},
  "geometry": {"coordinates":[8.7956113815,47.3193855286],"type":"Point"}
}