{
  "type": "Feature",
  "properties": {
    "iso:country":"CH",
    "sg:address":"Gr\u00fcnaustrasse 6",
    "sg:city":"Horn",
    "sg:orig_category":"Sportvereine Flug Delta",
    "sg:postcode":"9326",
    "sg:province":"Thurgau",
    "wof:name":"Gleitschirmklub Bergfl\u00f6h",
    "wof:placetype":"venue"
},
  "geometry": {"coordinates":[9.4576330185,47.4923248291],"type":"Point"}
}