{
  "type": "Feature",
  "properties": {
    "iso:country":"CH",
    "sg:address":"Bubikerstrasse 5",
    "sg:city":"Jona",
    "sg:orig_category":"Non-Classified Establishments",
    "sg:postcode":"8645",
    "sg:province":"St. Gallen",
    "wof:name":"Fritz Peter Metzgerei",
    "wof:placetype":"venue"
},
  "geometry": {"coordinates":[8.8194913864,47.2411003113],"type":"Point"}
}