{
  "type": "Feature",
  "properties": {
    "iso:country":"CH",
    "sg:address":"Masanserstrasse 233 7000 Chur. Postfach",
    "sg:city":"Chur",
    "sg:orig_category":"Nationale Postdienste",
    "sg:phone":"+41 81 256 32 94",
    "sg:postcode":"7005",
    "wof:name":"Die Schweizerische Post Chur 5 Masans",
    "wof:placetype":"venue"
},
  "geometry": {"coordinates":[9.5347948074,46.8660430908],"type":"Point"}
}