{
  "type": "Feature",
  "properties": {
    "addr:full":"Amsler-laffon-strasse 1 8200 Schaffhausen. Postfach Schaffhausen Schaffhausen 8201",
    "addr:housenumber":"1",
    "addr:postcode":"8200 schaffhausen. postfach;8201",
    "addr:street":"Amsler-Laffon-Strasse",
    "iso:country":"CH",
    "sg:address":"Amsler-laffon-strasse 1 8200 Schaffhausen. Postfach",
    "sg:city":"Schaffhausen",
    "sg:orig_category":"Allgemeiner Hoch U Tiefbau Grosshandel mit Erzen U Metallen",
    "sg:phone":"+41 52 631 11 11",
    "sg:postcode":"8201",
    "sg:province":"Schaffhausen",
    "wof:name":"Fischer Georg Rohrleitungssysteme (schweiz) Ag",
    "wof:placetype":"venue"
},
  "geometry": {"coordinates":[8.64186,47.707092],"type":"Point"}
}