{
  "type": "Feature",
  "properties": {
    "iso:country":"CH",
    "sg:address":"Via Brentani 10",
    "sg:city":"Lugano",
    "sg:orig_category":"Gymnastik U Fitnesszentren",
    "sg:phone":"+41 81 844 04 43",
    "sg:postcode":"6900",
    "sg:province":"Ticino",
    "wof:name":"Fantastic Fitness Hotel La Romantica",
    "wof:placetype":"venue"
},
  "geometry": {"coordinates":[10.077580452,46.295009613],"type":"Point"}
}