{
  "type": "Feature",
  "properties": {
    "iso:country":"CH",
    "sg:address":"3625",
    "sg:city":"Heiligenschwendi",
    "sg:orig_category":"Kongress- and Tagungshotels mit Restaurant Kurhotels mit Restaurant",
    "sg:phone":"+41 33 244 81 11",
    "sg:postcode":"3625",
    "sg:province":"Bern",
    "wof:name":"Kurhotel Haltenegg",
    "wof:placetype":"venue"
},
  "geometry": {"coordinates":[7.6821198463,46.7525215149],"type":"Point"}
}