{
  "type": "Feature",
  "properties": {
    "iso:country":"CH",
    "sg:address":"Hochh\u00fcsliweid 11",
    "sg:city":"Luzern",
    "sg:orig_category":"Wirtschaftspr\u00fcfung, Steuerberatung U Treuhand",
    "sg:phone":"+41 41 370 96 00",
    "sg:postcode":"6006",
    "sg:province":"Luzern",
    "wof:name":"Aaa - Planzer Consulting",
    "wof:placetype":"venue"
},
  "geometry": {"coordinates":[8.3533821106,47.0594444275],"type":"Point"}
}