{
  "type": "Feature",
  "properties": {
    "iso:country":"CH",
    "sg:address":"1641",
    "sg:city":"Vuippens",
    "sg:orig_category":"Unclassifiable Establishments",
    "sg:postcode":"1641",
    "wof:name":"Si Les Ormeaux, La Tour-de-peilz",
    "wof:placetype":"venue"
},
  "geometry": {"coordinates":[6.8568668365,46.4530258179],"type":"Point"}
}