{
  "type": "Feature",
  "properties": {
    "iso:country":"CH",
    "sg:address":"Marktgasse 5 9050 Appenzell. Postfach",
    "sg:city":"Appenzell",
    "sg:orig_category":"Herstellung von Schmuck, Gold U Silberschmiedwaren",
    "sg:postcode":"9050",
    "sg:province":"Appenzell Innerhoden",
    "wof:name":"Reggie's Goldschmiede Atelier, Th\u00fcr Reggie",
    "wof:placetype":"venue"
},
  "geometry": {"coordinates":[9.4085302353,47.331325531],"type":"Point"}
}