{
  "type": "Feature",
  "properties": {
    "iso:country":"CH",
    "sg:address":"Via San Gottardo 141",
    "sg:city":"Savosa",
    "sg:orig_category":"Grosshandel mit Datenverarbeitungsger\u00e4ten Grosshandel mit Software",
    "sg:postcode":"6942",
    "sg:province":"Ticino",
    "wof:name":"A. Gr\u00f6bli Palmcity",
    "wof:placetype":"venue"
},
  "geometry": {"coordinates":[8.7616949081,47.301410675],"type":"Point"}
}