{
  "type": "Feature",
  "properties": {
    "iso:country":"CH",
    "sg:address":"Bremgartnerstrasse 70",
    "sg:city":"Z\u00fcrich",
    "sg:orig_category":"RESTAURANTS: TEA-ROOMS",
    "sg:postcode":"8003",
    "sg:province":"Z\u00fcrich",
    "wof:name":"Restaurant Feldschl\u00f6sschen Nicora Mario",
    "wof:placetype":"venue"
},
  "geometry": {"coordinates":[7.8681378365,47.3445587158],"type":"Point"}
}