{
  "type": "Feature",
  "properties": {
    "iso:country":"CH",
    "sg:address":"Chemin De Chantemerle",
    "sg:city":"Orbe",
    "sg:classifiers":[
        {
            "category":"Education",
            "subcategory":"Vocational School",
            "type":"Public Place"
        }
    ],
    "sg:postcode":"1350",
    "sg:province":"Vaud",
    "sg:tags":[
        "koch-",
        "haushaltschulen"
    ],
    "wof:name":"Ecole M\u00e9nag\u00e8re R\u00e9gionale",
    "wof:placetype":"venue"
},
  "geometry": {"coordinates":[6.5306301117,46.7327041626],"type":"Point"}
}