{
  "type": "Feature",
  "properties": {
    "iso:country":"CH",
    "sg:address":"Impasse Jardin Du Cerf 1",
    "sg:city":"Estavayer-le-lac",
    "sg:orig_category":"Physiotherapie",
    "sg:phone":"+41 26 663 80 00",
    "sg:postcode":"1470",
    "sg:province":"Fribourg",
    "wof:name":"Physioth\u00e9rapie Du Centre",
    "wof:placetype":"venue"
},
  "geometry": {"coordinates":[6.8473768234,46.8487663269],"type":"Point"}
}