{
  "type": "Feature",
  "properties": {
    "iso:country":"CH",
    "sg:address":"Im Zagg 8",
    "sg:city":"Fontnas",
    "sg:orig_category":"Sportvereine Turnen Damen",
    "sg:postcode":"9476",
    "sg:province":"St. Gallen",
    "wof:name":"Damenturnver.stv Bremgarten",
    "wof:placetype":"venue"
},
  "geometry": {"coordinates":[8.3427963257,47.3519210815],"type":"Point"}
}