{
  "type": "Feature",
  "properties": {
    "iso:country":"CH",
    "sg:address":"Breisacherstrasse 68 4057 Basel. Postfach",
    "sg:city":"Basel",
    "sg:orig_category":"Fachdetailhandel in Verkaufsr\u00e4umen",
    "sg:phone":"+41 79 321 26 89",
    "sg:postcode":"4051",
    "sg:province":"Basel-Stadt",
    "wof:name":"Rhy-charter Basel, L\u00e4sser & W\u00fcthrich Bootsfahrschule. Schiffsf\u00fchrer Im Gebrauch V. Radar U. Rheinfunk; Ausbildung Usw",
    "wof:placetype":"venue"
},
  "geometry": {"coordinates":[7.5890021324,47.567237854],"type":"Point"}
}