{
  "type": "Feature",
  "properties": {
    "iso:country":"CH",
    "sg:address":"Christoph-schnyder-str. 46",
    "sg:city":"Sursee",
    "sg:orig_category":"Herstellung von konfektionierten Textilwaren ohne Bekleidung",
    "sg:postcode":"6210",
    "sg:province":"Luzern",
    "wof:name":"Egli Storen Ag, Zweigniederlassung Hasle",
    "wof:placetype":"venue"
},
  "geometry": {"coordinates":[8.0404596329,46.9726257324],"type":"Point"}
}