{
  "type": "Feature",
  "properties": {
    "iso:country":"CH",
    "sg:address":"Avenue Eug\u00e8ne-rambert 11",
    "sg:city":"Lausanne",
    "sg:orig_category":"Vorschulen, Kinderg\u00e4rten",
    "sg:postcode":"1005",
    "sg:province":"Vaud",
    "wof:name":"Ecole Enfantine Chissiez",
    "wof:placetype":"venue"
},
  "geometry": {"coordinates":[6.6477041245,46.5153503418],"type":"Point"}
}