{
  "type": "Feature",
  "properties": {
    "iso:country":"CH",
    "sg:address":"Corso San Gottardo 8a",
    "sg:city":"Chiasso",
    "sg:orig_category":"Unclassifiable Establishments",
    "sg:postcode":"6830",
    "sg:province":"Ticino",
    "wof:name":"Password Marketing & Sales Sagl",
    "wof:placetype":"venue"
},
  "geometry": {"coordinates":[9.0326051712,45.8329467773],"type":"Point"}
}