{
  "type": "Feature",
  "properties": {
    "iso:country":"CH",
    "sg:address":"Cantonale Via 34/a",
    "sg:city":"Manno",
    "sg:orig_category":"Wirtschaftspr\u00fcfung, Steuerberatung U Treuhand",
    "sg:phone":"+41 91 971 72 24",
    "sg:postcode":"6928",
    "sg:province":"Ticino",
    "wof:name":"E-legal.ch Stock Corporation",
    "wof:placetype":"venue"
},
  "geometry": {"coordinates":[8.919005394,46.0345535278],"type":"Point"}
}