{
  "type": "Feature",
  "properties": {
    "iso:country":"CH",
    "sg:address":"Z\u00fcrichstrasse 64",
    "sg:city":"Einsiedeln",
    "sg:classifiers":[
        {
            "category":"Professional",
            "type":"Services"
        }
    ],
    "sg:phone":"+41 55 418 81 81",
    "sg:postcode":"8840",
    "sg:province":"Schwyz",
    "sg:tags":[
        "transport"
    ],
    "wof:name":"Bingisser Ag",
    "wof:placetype":"venue"
},
  "geometry": {"coordinates":[8.745923,47.13718],"type":"Point"}
}