{
  "type": "Feature",
  "properties": {
    "iso:country":"CH",
    "sg:address":"Tavernier Rue De 9 1170 Aubonne. Postfach",
    "sg:city":"Aubonne",
    "sg:orig_category":"Architektur U Ingenieurb\u00fcros",
    "sg:postcode":"1170",
    "sg:province":"Vaud",
    "wof:name":"Lubex Gmbh, In Pf\u00e4ffikon",
    "wof:placetype":"venue"
},
  "geometry": {"coordinates":[8.793714,47.200607],"type":"Point"}
}