{
  "type": "Feature",
  "properties": {
    "iso:country":"CH",
    "sg:address":"Rue De La Conf\u00e9d\u00e9ration 11",
    "sg:city":"Gen\u00e8ve",
    "sg:orig_category":"Detailhandel mit Uhren U Schmuck Fachdetailhandel in Verkaufsr\u00e4umen",
    "sg:phone":"+41 22 311 70 76",
    "sg:postcode":"1204",
    "sg:province":"Gen\u00e8ve",
    "wof:name":"L. Bader, Meyer-bader Succ. Sa",
    "wof:placetype":"venue"
},
  "geometry": {"coordinates":[6.1449799538,46.2036972046],"type":"Point"}
}