{
  "type": "Feature",
  "properties": {
    "iso:country":"CH",
    "sg:address":"Engelbergstrasse 52",
    "sg:city":"Stans",
    "sg:orig_category":"Herstellung von K\u00fcchenm\u00f6beln",
    "sg:phone":"+41 81 413 30 31",
    "sg:postcode":"6370",
    "sg:province":"Nidwalden",
    "wof:name":"K\u00fcchen Et Cetera Soltmannowski Markus K\u00fcchen- U. Badezimmereinrichtungen Usw",
    "wof:placetype":"venue"
},
  "geometry": {"coordinates":[9.8537597656,46.8327331543],"type":"Point"}
}