{
  "type": "Feature",
  "properties": {
    "iso:country":"CH",
    "sg:address":"B\u00fchlmattenstrasse 18",
    "sg:city":"Fischbach-g\u00f6slikon",
    "sg:orig_category":"Herstellung von Metallerzeugnissen ohne Maschinenbau Maschinenbau",
    "sg:phone":"+41 56 622 94 36",
    "sg:postcode":"5525",
    "sg:province":"Aargau",
    "wof:name":"Kohler O. Ag Vorrichtungs- & Maschinenbau",
    "wof:placetype":"venue"
},
  "geometry": {"coordinates":[8.3078184128,47.3736724854],"type":"Point"}
}