{
  "type": "Feature",
  "properties": {
    "iso:country":"CH",
    "sg:address":"Carmenna",
    "sg:city":"Churwalden",
    "sg:orig_category":"Detailhandel mit Fleisch U Fleischwaren Fleischverarbeitung",
    "sg:phone":"+41 81 382 13 66",
    "sg:postcode":"7075",
    "sg:province":"Graubunden",
    "wof:name":"Domenig Ag",
    "wof:placetype":"venue"
},
  "geometry": {"coordinates":[9.543800354,46.7785453796],"type":"Point"}
}