{
  "type": "Feature",
  "properties": {
    "iso:country":"CH",
    "sg:address":"Route De Lausanne 5b",
    "sg:city":"Echallens",
    "sg:orig_category":"Vermittlung von Immobilien Verwaltung von Immobilien",
    "sg:phone":"+41 32 727 75 00",
    "sg:postcode":"1040",
    "sg:province":"Vaud",
    "wof:name":"Groupe Geco Sa Agence Immobili\u00e8re",
    "wof:placetype":"venue"
},
  "geometry": {"coordinates":[6.9312009811,46.9907722473],"type":"Point"}
}