{
  "type": "Feature",
  "properties": {
    "iso:country":"CH",
    "sg:address":"Kanalweg 30",
    "sg:city":"Zofingen",
    "sg:orig_category":"Detailhandel mit Waren verschiedener Art, Hauptrichtung Nahrungsmittel",
    "sg:phone":"+41 62 751 48 07",
    "sg:postcode":"4800",
    "sg:province":"Aargau",
    "wof:name":"Florio Sonia Import/export",
    "wof:placetype":"venue"
},
  "geometry": {"coordinates":[7.9363698959,47.2830734253],"type":"Point"}
}