{
  "type": "Feature",
  "properties": {
    "iso:country":"CH",
    "sg:address":"R\u00f6merstrasse 9",
    "sg:city":"Ipsach",
    "sg:orig_category":"Fussreflexzonenmassage P\u00e9dicure",
    "sg:phone":"+41 32 331 67 41",
    "sg:postcode":"2563",
    "sg:province":"Bern",
    "wof:name":"Doris D. Simonet Fusspflege & -reflextherapie",
    "wof:placetype":"venue"
},
  "geometry": {"coordinates":[7.2294812202,47.1137123108],"type":"Point"}
}