{
  "type": "Feature",
  "properties": {
    "iso:country":"CH",
    "sg:address":"Via Maistra 46",
    "sg:city":"Pontresina",
    "sg:orig_category":"Detailhandel mit Damenbekleidung",
    "sg:phone":"+41 81 842 74 74",
    "sg:postcode":"7504",
    "sg:province":"Graubunden",
    "wof:name":"Giovanna Merz Moda Laret",
    "wof:placetype":"venue"
},
  "geometry": {"coordinates":[9.902027,46.493507],"type":"Point"}
}