{
  "type": "Feature",
  "properties": {
    "iso:country":"CH",
    "sg:address":"Hoschet",
    "sg:city":"Nidfurn",
    "sg:orig_category":"Betrieb von Taxis",
    "sg:phone":"+41 79 421 42 42",
    "sg:postcode":"8772",
    "sg:province":"Glarus",
    "wof:name":"Therese Rogg Taxi",
    "wof:placetype":"venue"
},
  "geometry": {"coordinates":[9.054455,46.986076],"type":"Point"}
}