{
  "type": "Feature",
  "properties": {
    "iso:country":"CH",
    "sg:address":"Rue Pr\u00e9vost-martin 10",
    "sg:city":"Gen\u00e8ve",
    "sg:orig_category":"Internationale Organisationen mit Beh\u00f6rdecharakter",
    "sg:phone":"+41 22 781 41 60",
    "sg:postcode":"1205",
    "sg:province":"Gen\u00e8ve",
    "wof:name":"Scoutisme Europ\u00e9en Suisse",
    "wof:placetype":"venue"
},
  "geometry": {"coordinates":[6.1455101967,46.1951560974],"type":"Point"}
}