{
  "type": "Feature",
  "properties": {
    "iso:country":"CH",
    "sg:address":"Heckenweg 8",
    "sg:city":"Herrliberg",
    "sg:orig_category":"Sonstiger Grosshandel",
    "sg:phone":"+41 19150649",
    "sg:postcode":"8704",
    "sg:province":"Z\u00fcrich",
    "wof:name":"Sigillum Handels Und Finanz Ag",
    "wof:placetype":"venue"
},
  "geometry": {"coordinates":[8.6255521774,47.284954071],"type":"Point"}
}