{
  "type": "Feature",
  "properties": {
    "iso:country":"CH",
    "sg:address":"Papierm\u00fchlestrasse 71 3014 Bern. Postfach",
    "sg:city":"Bern",
    "sg:orig_category":"Unclassifiable Establishments",
    "sg:postcode":"3014",
    "sg:province":"Bern",
    "wof:name":"Services For Sports Sfs Gmbh Dienstleistungen Im Sportbereich Usw.",
    "wof:placetype":"venue"
},
  "geometry": {"coordinates":[7.4649848938,46.9622497559],"type":"Point"}
}