{
  "type": "Feature",
  "properties": {
    "iso:country":"CH",
    "sg:address":"Hofstrasse 124",
    "sg:city":"Z\u00fcrich",
    "sg:orig_category":"Gesundheitswesen",
    "sg:postcode":"8053",
    "sg:province":"Z\u00fcrich",
    "wof:name":"Massana Knet-blitz, S. Von Brodowski",
    "wof:placetype":"venue"
},
  "geometry": {"coordinates":[8.5645952225,47.3755149841],"type":"Point"}
}