{
  "type": "Feature",
  "properties": {
    "addr:full":"Rubigenstrasse 79 Worb Bern 3076",
    "addr:housenumber":"79",
    "addr:postcode":"3076",
    "addr:street":"Rubigenstrasse",
    "iso:country":"CH",
    "sg:address":"Rubigenstrasse 79",
    "sg:city":"Worb",
    "sg:orig_category":"Berufliche Weiterbildung, Erwachsenenbildung Berufsbildende weiterf\u00fchrende Schulen",
    "sg:phone":"+41 31 839 90 49",
    "sg:postcode":"3076",
    "sg:province":"Bern",
    "wof:name":"Ausbildungszentrum Des Kant.- Bern.maler-& Gipsergewerbes",
    "wof:placetype":"venue"
},
  "geometry": {"coordinates":[7.562965,46.914852],"type":"Point"}
}