{
  "type": "Feature",
  "properties": {
    "iso:country":"CH",
    "sg:address":"Hombrechtikerstrasse 60",
    "sg:city":"Jona",
    "sg:orig_category":"Vermittlung von Immobilien Verwaltung von Immobilien",
    "sg:phone":"+41 55 211 17 48",
    "sg:postcode":"8645",
    "sg:province":"St. Gallen",
    "wof:name":"Erich V\u00f6geli Immobilien Und Verwaltungs Ag",
    "wof:placetype":"venue"
},
  "geometry": {"coordinates":[8.814078331,47.242893219],"type":"Point"}
}