{
  "type": "Feature",
  "properties": {
    "iso:country":"CH",
    "sg:address":"Hauptstr. 133",
    "sg:city":"Welschenrohr",
    "sg:orig_category":"Grosshandel mit Nahrungsmitteln, Getr\u00e4nken U Tabakwaren ohne ausgepr\u00e4gten Schwerpunkt",
    "sg:phone":"+41 32 639 14 25",
    "sg:postcode":"4716",
    "sg:province":"Solothurn",
    "wof:name":"Burri-ries Peter",
    "wof:placetype":"venue"
},
  "geometry": {"coordinates":[7.5274147987,47.280506134],"type":"Point"}
}