{
  "type": "Feature",
  "properties": {
    "iso:country":"CH",
    "sg:address":"Rheinhalde 20",
    "sg:city":"Diessenhofen",
    "sg:orig_category":"Kunsthandel",
    "sg:phone":"+41 52 657 44 04",
    "sg:postcode":"8253",
    "sg:province":"Thurgau",
    "wof:name":"Galerie Rheinhalde",
    "wof:placetype":"venue"
},
  "geometry": {"coordinates":[8.7506818771,47.690246582],"type":"Point"}
}