{
  "type": "Feature",
  "properties": {
    "iso:country":"CH",
    "sg:address":"Bernstrasse 15",
    "sg:city":"Suberg",
    "sg:orig_category":"G\u00fcterbef\u00f6rderung im Strassenverkehr",
    "sg:phone":"+41 32 389 19 70",
    "sg:postcode":"3262",
    "sg:province":"Bern",
    "wof:name":"Roth Transport Ag",
    "wof:placetype":"venue"
},
  "geometry": {"coordinates":[7.3352198601,47.0624809265],"type":"Point"}
}