{
  "type": "Feature",
  "properties": {
    "iso:country":"CH",
    "sg:address":"7430 Thusis. Postfach 110",
    "sg:city":"Thusis",
    "sg:orig_category":"RESTAURANTS: TEA-ROOMS",
    "sg:phone":"+41 81 651 11 23",
    "sg:postcode":"7430",
    "sg:province":"Graubunden",
    "wof:name":"Gyger Ag",
    "wof:placetype":"venue"
},
  "geometry": {"coordinates":[9.4394903183,46.695766449],"type":"Point"}
}