{
  "type": "Feature",
  "properties": {
    "addr:full":"Route De Pierre-pertuis 2 Tavannes Bern 2710",
    "addr:housenumber":"2",
    "addr:postcode":"2710",
    "addr:street":"Route De Pierre-Pertuis",
    "iso:country":"CH",
    "sg:address":"Route De Pierre-pertuis 2",
    "sg:city":"Tavannes",
    "sg:orig_category":"Chemische Reinigung",
    "sg:phone":"+41 32 481 15 30",
    "sg:postcode":"2710",
    "sg:province":"Bern",
    "wof:name":"Reno-matic Textilreinigung",
    "wof:placetype":"venue"
},
  "geometry": {"coordinates":[7.19833,47.220188],"type":"Point"}
}