{
  "type": "Feature",
  "properties": {
    "iso:country":"CH",
    "sg:address":"Dotzmattstrasse 14",
    "sg:city":"Frick",
    "sg:orig_category":"Schreib U \u00dcbersetzungsb\u00fcros",
    "sg:phone":"+41 56 288 39 78",
    "sg:postcode":"5070",
    "sg:province":"Aargau",
    "wof:name":"Strittmatter Bernadette",
    "wof:placetype":"venue"
},
  "geometry": {"coordinates":[8.2973356247,47.4899673462],"type":"Point"}
}