{
  "type": "Feature",
  "properties": {
    "iso:country":"CH",
    "sg:address":"Landes Les 38b",
    "sg:city":"Crans-pr\u00e8s-c\u00e9ligny",
    "sg:orig_category":"Sonstiger Grosshandel",
    "sg:postcode":"1299",
    "sg:province":"Vaud",
    "wof:name":"Lemon S\u00e0rl",
    "wof:placetype":"venue"
},
  "geometry": {"coordinates":[6.2176017761,46.363494873],"type":"Point"}
}