{
  "type": "Feature",
  "properties": {
    "iso:country":"CH",
    "sg:address":"Illighauserstrasse 1 8574 Oberhofen B. Kreuz. Postfach 1509",
    "sg:city":"Kreuzlingen",
    "sg:orig_category":"Jugendorganisationen",
    "sg:phone":"+41 71 672 28 19",
    "sg:postcode":"8280",
    "sg:province":"Thurgau",
    "wof:name":"Jugendmusik Kreuzlingen",
    "wof:placetype":"venue"
},
  "geometry": {"coordinates":[9.1945781708,47.6163635254],"type":"Point"}
}