{
  "type": "Feature",
  "properties": {
    "iso:country":"CH",
    "sg:address":"Luzernerstrasse 2 4800 Zofingen. Postfach",
    "sg:city":"Zofingen",
    "sg:orig_category":"Herstellung von Medikamenten U sonstigen pharmazeutischen Erzeugnissen Herstellung von pharmazeutisc",
    "sg:phone":"+41 62 752 11 60",
    "sg:postcode":"4800",
    "sg:province":"Aargau",
    "wof:name":"Sigma-tau Pharma Ag",
    "wof:placetype":"venue"
},
  "geometry": {"coordinates":[7.9470129013,47.2861709595],"type":"Point"}
}