{
  "type": "Feature",
  "properties": {
    "addr:full":"Lenzburgerstrasse 2 Niederlenz Aargau 5702",
    "addr:housenumber":"2",
    "addr:postcode":"5702",
    "addr:street":"Lenzburgerstrasse",
    "iso:country":"CH",
    "sg:address":"Lenzburgerstrasse 2",
    "sg:city":"Niederlenz",
    "sg:orig_category":"Architekturb\u00fcros",
    "sg:phone":"+41 41 871 03 34",
    "sg:postcode":"5702",
    "sg:province":"Aargau",
    "wof:name":"Hts Architekten & Partner Ag",
    "wof:placetype":"venue"
},
  "geometry": {"coordinates":[8.649485,46.87561],"type":"Point"}
}