{
  "type": "Feature",
  "properties": {
    "iso:country":"CH",
    "sg:address":"2900",
    "sg:city":"Porrentruy",
    "sg:orig_category":"Vorschulen, Kinderg\u00e4rten",
    "sg:phone":"+41 22 342 27 51",
    "sg:postcode":"2900",
    "sg:province":"Jura",
    "wof:name":"Ecole Enfantine Pervenches I-iv",
    "wof:placetype":"venue"
},
  "geometry": {"coordinates":[6.137160778,46.1873130798],"type":"Point"}
}