{
  "type": "Feature",
  "properties": {
    "iso:country":"CH",
    "sg:address":"Oberer Gansbach 5",
    "sg:city":"Appenzell",
    "sg:orig_category":"P\u00e9dicure",
    "sg:phone":"+41 71 787 10 27",
    "sg:postcode":"9050",
    "sg:province":"Appenzell Innerhoden",
    "wof:name":"Mily Brander Kosmetik & P\u00e9dicure",
    "wof:placetype":"venue"
},
  "geometry": {"coordinates":[9.4080638885,47.3298797607],"type":"Point"}
}