{
  "type": "Feature",
  "properties": {
    "iso:country":"CH",
    "sg:address":"1692",
    "sg:city":"Massonnens",
    "sg:orig_category":"Bauschreinerei Einbau von Schreinerwaren",
    "sg:phone":"+41 56 664 43 30",
    "sg:postcode":"1692",
    "sg:province":"Fribourg",
    "wof:name":"Paul Signer Schreinerei K\u00fcchenbau",
    "wof:placetype":"venue"
},
  "geometry": {"coordinates":[8.317482,47.282578],"type":"Point"}
}