{
  "type": "Feature",
  "properties": {
    "iso:country":"CH",
    "sg:address":"Bantigerstrasse 24",
    "sg:city":"Bern",
    "sg:orig_category":"Detailhandel mit Waren verschiedener Art, Hauptrichtung Nahrungsmittel",
    "sg:phone":"+41 56 622 35 94",
    "sg:postcode":"3006",
    "sg:province":"Bern",
    "wof:name":"Hans Roth Kolonialwaren",
    "wof:placetype":"venue"
},
  "geometry": {"coordinates":[8.2737846375,47.3437309265],"type":"Point"}
}