{
  "type": "Feature",
  "properties": {
    "iso:country":"CH",
    "sg:address":"Promenade Des Artisans 28",
    "sg:city":"Meyrin",
    "sg:orig_category":"Detailhandel mit Tabakwaren Vermietung von Gebrauchsg\u00fctern",
    "sg:phone":"+41 22 782 03 51",
    "sg:postcode":"1217",
    "sg:province":"Gen\u00e8ve",
    "wof:name":"Jos\u00e9 Babarro Tabacs & Vid\u00e9o",
    "wof:placetype":"venue"
},
  "geometry": {"coordinates":[6.0795822144,46.2376556396],"type":"Point"}
}