{
  "type": "Feature",
  "properties": {
    "iso:country":"CH",
    "sg:address":"Bodenmattli 25",
    "sg:city":"Willerzell",
    "sg:orig_category":"Sportvereine Sch\u00fctzen Armbrust Sportvereine Sch\u00fctzen Flobert",
    "sg:phone":"+41 41 630 25 81",
    "sg:postcode":"8846",
    "sg:province":"Schwyz",
    "wof:name":"Armbrust-& Flobertsch\u00fctzen",
    "wof:placetype":"venue"
},
  "geometry": {"coordinates":[8.3073043823,46.9928817749],"type":"Point"}
}