{
  "type": "Feature",
  "properties": {
    "iso:country":"CH",
    "sg:address":"Obere Wangenstrasse",
    "sg:city":"Br\u00fcttisellen",
    "sg:orig_category":"Reiseb\u00fcros",
    "sg:phone":"+41 18334381",
    "sg:postcode":"8306",
    "sg:province":"Z\u00fcrich",
    "wof:name":"Travel Dock Ch Reiseb\u00fcro",
    "wof:placetype":"venue"
},
  "geometry": {"coordinates":[8.6356458664,47.4252853394],"type":"Point"}
}