{
  "type": "Feature",
  "properties": {
    "iso:country":"CH",
    "sg:address":"1836",
    "sg:city":"Rossini\u00e8re",
    "sg:classifiers":[
        {
            "category":"Travel",
            "subcategory":"Hotels & Motels",
            "type":"Entertainment"
        }
    ],
    "sg:phone":"+41 26 924 51 75",
    "sg:postcode":"1836",
    "sg:tags":[
        "hotels",
        "mit",
        "restaurant"
    ],
    "wof:name":"G\u00e9taz Serge",
    "wof:placetype":"venue"
},
  "geometry": {"coordinates":[7.083630085,46.466960907],"type":"Point"}
}