{
  "type": "Feature",
  "properties": {
    "iso:country":"CH",
    "sg:address":"Winzerhalde 20a",
    "sg:city":"Z\u00fcrich",
    "sg:orig_category":"Non-Classified Establishments",
    "sg:postcode":"8049",
    "sg:province":"Z\u00fcrich",
    "wof:name":"Forster B., Film-video-computergraphik Lehr Und Werbefilme I. D. Medizin; Herstellung",
    "wof:placetype":"venue"
},
  "geometry": {"coordinates":[8.4924669266,47.3998222351],"type":"Point"}
}