{
  "type": "Feature",
  "properties": {
    "iso:country":"CH",
    "sg:address":"En Rosset",
    "sg:city":"Treyvaux",
    "sg:orig_category":"Grosshandel mit lebenden Tieren",
    "sg:phone":"+41 26 413 12 13",
    "sg:postcode":"1733",
    "sg:province":"Fribourg",
    "wof:name":"Camille Yerli Commerce De Porcs",
    "wof:placetype":"venue"
},
  "geometry": {"coordinates":[7.1441369057,46.7261047363],"type":"Point"}
}