{
  "type": "Feature",
  "properties": {
    "iso:country":"CH",
    "sg:address":"Dorfstrasse 76",
    "sg:city":"Obfelden",
    "sg:orig_category":"Bauspenglerei Zimmerei, Dachdeckerei, Bauspenglerei U Abdichtung",
    "sg:phone":"+41 17614219",
    "sg:postcode":"8912",
    "sg:province":"Z\u00fcrich",
    "wof:name":"Stierli + Co.",
    "wof:placetype":"venue"
},
  "geometry": {"coordinates":[8.41843,47.261711],"type":"Point"}
}