{
  "type": "Feature",
  "properties": {
    "iso:country":"CH",
    "sg:address":"1950 Sion. Postfach",
    "sg:city":"Sitten",
    "sg:orig_category":"Pensionskassen",
    "sg:postcode":"1950",
    "sg:province":"Valais",
    "wof:name":"Ogb-stiftung (stiftung Zu Gunsten Der Orchestergesellschaft Biel)",
    "wof:placetype":"venue"
},
  "geometry": {"coordinates":[7.2853531837,47.1282806396],"type":"Point"}
}