{
  "type": "Feature",
  "properties": {
    "iso:country":"CH",
    "sg:address":"Hirschengraben 13-15 8001 Z\u00fcrich. Postfach 6273",
    "sg:city":"Z\u00fcrich",
    "sg:orig_category":"Detailhandel mit Getr\u00e4nken Rebbau",
    "sg:phone":"+41 12512347",
    "sg:postcode":"8023",
    "sg:province":"Z\u00fcrich",
    "wof:name":"Staatskellereien",
    "wof:placetype":"venue"
},
  "geometry": {"coordinates":[8.5469341278,47.3714027405],"type":"Point"}
}