{
  "type": "Feature",
  "properties": {
    "iso:country":"CH",
    "sg:address":"Lerchenfeldstrasse 6",
    "sg:city":"Meggen",
    "sg:orig_category":"Allgemeiner Gartenbau Dienstleistungen im Gartenbau",
    "sg:postcode":"6045",
    "sg:province":"Luzern",
    "wof:name":"Markus Eisenring Gartenbau & -pflege",
    "wof:placetype":"venue"
},
  "geometry": {"coordinates":[8.211209,46.886616],"type":"Point"}
}