{
  "type": "Feature",
  "properties": {
    "iso:country":"CH",
    "sg:address":"Vogelherdstrasse 17",
    "sg:city":"Solothurn",
    "sg:classifiers":[
        {
            "category":"Restaurant",
            "type":"Food & Drink"
        }
    ],
    "sg:phone":"+41 32 622 29 72",
    "sg:postcode":"4500",
    "sg:province":"Solothurn",
    "wof:name":"Caf\u00e9 De L'industrie",
    "wof:placetype":"venue"
},
  "geometry": {"coordinates":[7.5189957619,47.2144699097],"type":"Point"}
}