{
  "type": "Feature",
  "properties": {
    "iso:country":"CH",
    "sg:address":"Obere Oelerr\u00fctti 12",
    "sg:city":"Schattdorf",
    "sg:orig_category":"Sonstige Personenbef\u00f6rderung im Landverkehr",
    "sg:phone":"+41 79 433 66 44",
    "sg:postcode":"6467",
    "sg:province":"Uri",
    "wof:name":"Rheintal Reisen Gegenschatz Ag",
    "wof:placetype":"venue"
},
  "geometry": {"coordinates":[9.5387401581,47.3779716492],"type":"Point"}
}