{
  "type": "Feature",
  "properties": {
    "iso:country":"CH",
    "sg:address":"Hauptstr. 995",
    "sg:city":"Gontenschwil",
    "sg:orig_category":"Grosshandel mit Nahrungsmitteln, Getr\u00e4nken U Tabakwaren ohne ausgepr\u00e4gten Schwerpunkt",
    "sg:phone":"+41 62 773 19 19",
    "sg:postcode":"5728",
    "sg:province":"Aargau",
    "wof:name":"Aeschbach Und Lanfranchi, Neuhof Lebensmittel Und Metzgerei",
    "wof:placetype":"venue"
},
  "geometry": {"coordinates":[8.1438541412,47.2799186707],"type":"Point"}
}