{
  "type": "Feature",
  "properties": {
    "iso:country":"CH",
    "sg:address":"Viale Stefano Franscini 3 6900 Lugano. Postfach",
    "sg:city":"Lugano",
    "sg:orig_category":"Non-Classified Establishments",
    "sg:postcode":"6900",
    "sg:province":"Ticino",
    "wof:name":"Redfox Holding Sa",
    "wof:placetype":"venue"
},
  "geometry": {"coordinates":[8.9526252747,46.0081977844],"type":"Point"}
}