{
  "type": "Feature",
  "properties": {
    "iso:country":"CH",
    "sg:address":"Roschbrunnen 318",
    "sg:city":"Staffelbach",
    "sg:orig_category":"Instandhaltung U Reparatur von Automobilen",
    "sg:phone":"+41 62 721 38 73",
    "sg:postcode":"5053",
    "sg:province":"Aargau",
    "wof:name":"Team-garage D\u00e4twyler R.",
    "wof:placetype":"venue"
},
  "geometry": {"coordinates":[8.0398101807,47.2840690613],"type":"Point"}
}