{
  "type": "Feature",
  "properties": {
    "iso:country":"CH",
    "sg:address":"Les Prasses",
    "sg:city":"Vex",
    "sg:orig_category":"Allgemeiner Hoch U Tiefbau",
    "sg:phone":"+41 27 207 19 20",
    "sg:postcode":"1981",
    "sg:province":"Valais",
    "wof:name":"Pitteloud & Zermatten, Construction Sa",
    "wof:placetype":"venue"
},
  "geometry": {"coordinates":[7.39371,46.208759],"type":"Point"}
}