{
  "type": "Feature",
  "properties": {
    "iso:country":"CH",
    "sg:address":"Via Sant'abbondio 44",
    "sg:city":"Gentilino",
    "sg:orig_category":"Nationale Postdienste",
    "sg:phone":"+41 91 994 64 56",
    "sg:postcode":"6925",
    "sg:province":"Ticino",
    "wof:name":"La Posta Svizzera",
    "wof:placetype":"venue"
},
  "geometry": {"coordinates":[8.9303617477,45.9904747009],"type":"Point"}
}