{
  "type": "Feature",
  "properties": {
    "iso:country":"CH",
    "sg:address":"Steinler 2",
    "sg:city":"D\u00fcdingen",
    "sg:orig_category":"Mit Sport verbundene T\u00e4tigkeiten",
    "sg:phone":"+41 26 493 28 79",
    "sg:postcode":"3186",
    "sg:province":"Fribourg",
    "wof:name":"Reithalle Steinlera",
    "wof:placetype":"venue"
},
  "geometry": {"coordinates":[7.2146840096,46.8613510132],"type":"Point"}
}