{
  "type": "Feature",
  "properties": {
    "iso:country":"CH",
    "sg:address":"Pension Selun",
    "sg:city":"Wildhaus",
    "sg:classifiers":[
        {
            "category":"Travel",
            "subcategory":"Hotels & Motels",
            "type":"Entertainment"
        }
    ],
    "sg:postcode":"9658",
    "sg:province":"St. Gallen",
    "sg:tags":[
        "hotels",
        "mit",
        "restaurant"
    ],
    "wof:name":"Defila Reto, Pension Selun",
    "wof:placetype":"venue"
},
  "geometry": {"coordinates":[9.3509206772,47.2028656006],"type":"Point"}
}