{
  "type": "Feature",
  "properties": {
    "iso:country":"CH",
    "sg:address":"Karpfenweg 24",
    "sg:city":"Basel",
    "sg:orig_category":"Interessenvertretungen",
    "sg:phone":"+41 27 473 13 34",
    "sg:postcode":"4052",
    "sg:province":"Basel-Stadt",
    "wof:name":"Stiftung F\u00fcr Das Kranke Kind, Leuk",
    "wof:placetype":"venue"
},
  "geometry": {"coordinates":[7.6346597672,46.3163299561],"type":"Point"}
}