{
  "type": "Feature",
  "properties": {
    "iso:country":"CH",
    "sg:address":"Bahnhofplatz 8",
    "sg:city":"Siebnen",
    "sg:orig_category":"Zahnarztpraxen",
    "sg:phone":"+41 81 413 76 43",
    "sg:postcode":"8854",
    "sg:province":"Schwyz",
    "wof:name":"Dr. Med. Dent. Bruno Mazenauer Zahnarzt",
    "wof:placetype":"venue"
},
  "geometry": {"coordinates":[9.8235006332,46.7983398438],"type":"Point"}
}