{
  "type": "Feature",
  "properties": {
    "iso:country":"CH",
    "sg:address":"Gewerbestrasse 6 6314 Unter\u00e4geri. Postfach",
    "sg:city":"Unter\u00e4geri",
    "sg:orig_category":"Erbringung von Dienstleistungen f\u00fcr Unternehmen",
    "sg:postcode":"6314",
    "sg:province":"Zug",
    "wof:name":"Mf Werbe & Reklame Ag",
    "wof:placetype":"venue"
},
  "geometry": {"coordinates":[8.5735826492,47.1344451904],"type":"Point"}
}