{
  "type": "Feature",
  "properties": {
    "iso:country":"CH",
    "sg:address":"1358",
    "sg:city":"Valeyres-rances",
    "sg:orig_category":"Primarschulen",
    "sg:phone":"+41 32 315 17 77",
    "sg:postcode":"1358",
    "sg:province":"Vaud",
    "wof:name":"Ecole Primaire",
    "wof:placetype":"venue"
},
  "geometry": {"coordinates":[6.5307450294,46.7602310181],"type":"Point"}
}