{
  "type": "Feature",
  "properties": {
    "iso:country":"CH",
    "sg:address":"Via Giuseppe Bagutti 4",
    "sg:city":"Lugano",
    "sg:orig_category":"Interessenvertretungen",
    "sg:phone":"+41 91 922 89 24",
    "sg:postcode":"6900",
    "sg:province":"Ticino",
    "wof:name":"Area",
    "wof:placetype":"venue"
},
  "geometry": {"coordinates":[8.9559669495,46.0121421814],"type":"Point"}
}