{
  "type": "Feature",
  "properties": {
    "iso:country":"CH",
    "sg:address":"Via Guisan 10",
    "sg:city":"Paradiso",
    "sg:orig_category":"Detailhandel mit Bekleidung Grosshandel mit Bekleidung",
    "sg:phone":"+41 55 210 09 66",
    "sg:postcode":"6900",
    "sg:province":"Ticino",
    "wof:name":"Western Art Outfitters Kurt Baumgartner",
    "wof:placetype":"venue"
},
  "geometry": {"coordinates":[8.817401,47.22707],"type":"Point"}
}