{
  "type": "Feature",
  "properties": {
    "iso:country":"CH",
    "sg:address":"Avenue Des Sports 5",
    "sg:city":"Yverdon-les-bains",
    "sg:orig_category":"Herstellung von sonstigen landwirtschaftlichen Maschinen",
    "sg:phone":"+41 24 425 71 33",
    "sg:postcode":"1400",
    "sg:province":"Vaud",
    "wof:name":"Bucher-guyer Sa Machines Agricoles",
    "wof:placetype":"venue"
},
  "geometry": {"coordinates":[6.6496071815,46.7816352844],"type":"Point"}
}