{
  "type": "Feature",
  "properties": {
    "iso:country":"CH",
    "sg:address":"Storenstrasse 9",
    "sg:city":"Kreuzlingen",
    "sg:orig_category":"Unclassifiable Establishments",
    "sg:postcode":"8280",
    "sg:province":"Thurgau",
    "wof:name":"Sanliq Sanierungs Und Liquidations Ag",
    "wof:placetype":"venue"
},
  "geometry": {"coordinates":[9.174656868,47.643447876],"type":"Point"}
}