{
  "type": "Feature",
  "properties": {
    "iso:country":"CH",
    "sg:address":"Uraniastrasse 20 8001 Z\u00fcrich. Postfach",
    "sg:city":"Z\u00fcrich",
    "sg:classifiers":[
        {
            "category":"Professional",
            "subcategory":"Employment Agencies",
            "type":"Services"
        }
    ],
    "sg:phone":"+41 12111112",
    "sg:postcode":"8023",
    "sg:province":"Z\u00fcrich",
    "sg:tags":[
        "personal",
        "u",
        "stellenvermittlung"
    ],
    "wof:name":"Esteem Ag Unternehmungsberatung In Personalfragen",
    "wof:placetype":"venue"
},
  "geometry": {"coordinates":[8.536359787,47.3741111755],"type":"Point"}
}