{
  "type": "Feature",
  "properties": {
    "iso:country":"CH",
    "sg:address":"Zumbachweg 8",
    "sg:city":"Luzern",
    "sg:orig_category":"Saunas Solarien",
    "sg:phone":"+41 41 360 72 66",
    "sg:postcode":"6005",
    "sg:province":"Luzern",
    "wof:name":"Sauna Matthof",
    "wof:placetype":"venue"
},
  "geometry": {"coordinates":[8.3285913467,47.0345916748],"type":"Point"}
}