{
  "type": "Feature",
  "properties": {
    "iso:country":"CH",
    "sg:address":"Industriestrasse 13",
    "sg:city":"Maienfeld",
    "sg:classifiers":[
        {
            "category":"Wholesale",
            "subcategory":"Plants",
            "type":"Manufacturing & Wholesale Goods"
        }
    ],
    "sg:phone":"+41 81 300 41 31",
    "sg:postcode":"7304",
    "sg:province":"Graubunden",
    "sg:tags":[
        "textile",
        "machine",
        "assembly"
    ],
    "wof:name":"Thies Ag",
    "wof:placetype":"venue"
},
  "geometry": {"coordinates":[9.52959,47.003139],"type":"Point"}
}