{
  "type": "Feature",
  "properties": {
    "iso:country":"CH",
    "sg:address":"Talstrasse 6",
    "sg:city":"Ennetmoos",
    "sg:orig_category":"Herstellung von Konstruktionsteilen, Fertigbauteilen U Ausbauelementen aus Holz",
    "sg:phone":"+41 91 605 17 41",
    "sg:postcode":"6372",
    "sg:province":"Nidwalden",
    "wof:name":"Bockstaller Erwin",
    "wof:placetype":"venue"
},
  "geometry": {"coordinates":[8.334728241,46.9555168152],"type":"Point"}
}