{
  "type": "Feature",
  "properties": {
    "iso:country":"CH",
    "sg:address":"Rickenbachstrasse 1",
    "sg:city":"Schwyz",
    "sg:orig_category":"Architektur U Ingenieurb\u00fcros Innenarchitekturb\u00fcros",
    "sg:phone":"+41 41 811 61 60",
    "sg:postcode":"6430",
    "sg:province":"Schwyz",
    "wof:name":"Camenzind Josef Gmbh",
    "wof:placetype":"venue"
},
  "geometry": {"coordinates":[8.654131,47.021793],"type":"Point"}
}