{
  "type": "Feature",
  "properties": {
    "iso:country":"CH",
    "sg:address":"S\u00e4gereistr. 5",
    "sg:city":"Niederglatt",
    "sg:classifiers":[
        {
            "category":"Sports & Exercise",
            "subcategory":"Sports Center",
            "type":"Entertainment"
        }
    ],
    "sg:phone":"+41 4118506437",
    "sg:postcode":"8172",
    "sg:province":"Z\u00fcrich",
    "sg:tags":[
        "game"
    ],
    "wof:name":"Tanzschule Z\u00dcri Unterland",
    "wof:placetype":"venue"
},
  "geometry": {"coordinates":[8.5046243668,47.4911575317],"type":"Point"}
}