{
  "type": "Feature",
  "properties": {
    "iso:country":"CH",
    "sg:address":"Talackerstrasse 9 8152 Glattbrugg. Postfach 1817",
    "sg:city":"Z\u00fcrich",
    "sg:orig_category":"Handelsvermittlung U Grosshandel",
    "sg:phone":"+41 81 302 26 49",
    "sg:postcode":"8065",
    "sg:province":"Z\u00fcrich",
    "wof:name":"Franz Blum Handelsagentur",
    "wof:placetype":"venue"
},
  "geometry": {"coordinates":[9.5007143021,47.0138702393],"type":"Point"}
}