{
  "type": "Feature",
  "properties": {
    "iso:country":"CH",
    "sg:address":"Rigistrasse 2",
    "sg:city":"Weggis",
    "sg:orig_category":"Unclassifiable Establishments",
    "sg:postcode":"6353",
    "sg:province":"Luzern",
    "wof:name":"Florido Gmbh",
    "wof:placetype":"venue"
},
  "geometry": {"coordinates":[8.4356184006,47.0327415466],"type":"Point"}
}