{
  "type": "Feature",
  "properties": {
    "iso:country":"CH",
    "sg:address":"Hauptstrasse 38",
    "sg:city":"K\u00fcnten",
    "sg:orig_category":"Sonstige Aktivit\u00e4ten der nicht-\u00e4rztlichen Medizinalberufe",
    "sg:phone":"+41 56 496 04 10",
    "sg:postcode":"5444",
    "sg:province":"Aargau",
    "wof:name":"Simone & Esther Schweitzer Praxis Posivita",
    "wof:placetype":"venue"
},
  "geometry": {"coordinates":[8.3297548294,47.3879737854],"type":"Point"}
}