{
  "type": "Feature",
  "properties": {
    "iso:country":"CH",
    "sg:address":"Arenastrasse 16",
    "sg:city":"Windisch",
    "sg:orig_category":"Herstellung von sonstigen Metallwaren",
    "sg:postcode":"5210",
    "sg:province":"Aargau",
    "wof:name":"Eqs-magnetismus Avgoustatos",
    "wof:placetype":"venue"
},
  "geometry": {"coordinates":[8.2134952545,47.4773864746],"type":"Point"}
}