{
  "type": "Feature",
  "properties": {
    "iso:country":"CH",
    "sg:address":"Route De Rolle 2",
    "sg:city":"St. Prex",
    "sg:classifiers":[
        {
            "category":"Banks & Credit Unions",
            "subcategory":"Bank",
            "type":"Services"
        }
    ],
    "sg:phone":"+41 21 806 23 23",
    "sg:postcode":"1162",
    "sg:province":"Vaud",
    "wof:name":"Caisse D'epargne Et De Cr\u00e9dit",
    "wof:placetype":"venue"
},
  "geometry": {"coordinates":[6.457019,46.48111],"type":"Point"}
}