{
  "type": "Feature",
  "properties": {
    "iso:country":"CH",
    "sg:address":"Allex Route De L' 36a 1880 Bex Case Postale 274",
    "sg:city":"Bex",
    "sg:orig_category":"Zimmerei, Dachdeckerei, Bauspenglerei U Abdichtung",
    "sg:phone":"+41 24 463 10 36",
    "sg:postcode":"1880",
    "sg:province":"Vaud",
    "wof:name":"Richard P. & Fils Sa",
    "wof:placetype":"venue"
},
  "geometry": {"coordinates":[7.0156798363,46.2502593994],"type":"Point"}
}