{
  "type": "Feature",
  "properties": {
    "iso:country":"CH",
    "sg:address":"Netzibodenstrasse 34",
    "sg:city":"Pratteln",
    "sg:classifiers":[
        {
            "category":"Manufacturing",
            "subcategory":"Rubber & Plastics",
            "type":"Manufacturing & Wholesale Goods"
        }
    ],
    "sg:phone":"+41 71 747 27 27",
    "sg:postcode":"4133",
    "sg:province":"Basel-Landschaft",
    "wof:name":"Samaplast Ag",
    "wof:placetype":"venue"
},
  "geometry": {"coordinates":[9.6523456573,47.4473342896],"type":"Point"}
}