{
  "type": "Feature",
  "properties": {
    "iso:country":"CH",
    "sg:address":"Kleinholz",
    "sg:city":"Graben",
    "sg:orig_category":"Allgemeiner Hoch U Tiefbau",
    "sg:postcode":"3376",
    "sg:province":"Bern",
    "wof:name":"Ruedi Fuchs",
    "wof:placetype":"venue"
},
  "geometry": {"coordinates":[8.033483,46.755707],"type":"Point"}
}