{
  "type": "Feature",
  "properties": {
    "iso:country":"CH",
    "sg:address":"Pestalozzistrasse 16",
    "sg:city":"Bern",
    "sg:orig_category":"Softwareentwicklung U beratung",
    "sg:phone":"+41 31 994 20 50",
    "sg:postcode":"3018",
    "sg:province":"Bern",
    "wof:name":"I + S Tec Ag",
    "wof:placetype":"venue"
},
  "geometry": {"coordinates":[7.4250898361,46.9414710999],"type":"Point"}
}