{
  "type": "Feature",
  "properties": {
    "iso:country":"CH",
    "sg:address":"Sch\u00fctzenstrasse 27c",
    "sg:city":"Wallisellen",
    "sg:orig_category":"Unternehmensberatung",
    "sg:phone":"+41 18311527",
    "sg:postcode":"8304",
    "sg:province":"Z\u00fcrich",
    "wof:name":"Burkhardt Kurt",
    "wof:placetype":"venue"
},
  "geometry": {"coordinates":[8.5884199142,47.4189300537],"type":"Point"}
}