{
  "type": "Feature",
  "properties": {
    "iso:country":"CH",
    "sg:address":"Thurgauerstrasse 39",
    "sg:city":"Z\u00fcrich",
    "sg:orig_category":"Grosshandel mit pharmazeutischen Erzeugnissen, medizinischen U orthop\u00e4dischen Artikeln Zahntechnisch",
    "sg:phone":"+41 71 222 87 37",
    "sg:postcode":"8050",
    "sg:province":"Z\u00fcrich",
    "wof:name":"Ley & Spirig Orthodontie Zahntechnisches Labor",
    "wof:placetype":"venue"
},
  "geometry": {"coordinates":[9.3718414307,47.4210281372],"type":"Point"}
}