{
  "type": "Feature",
  "properties": {
    "addr:full":"Kurvenstrasse 35 Z\u00fcrich Z\u00fcrich 8006",
    "addr:housenumber":"35",
    "addr:postcode":"8006",
    "addr:street":"Kurvenstrasse",
    "iso:country":"CH",
    "sg:address":"Kurvenstrasse 35",
    "sg:city":"Z\u00fcrich",
    "sg:orig_category":"Architektur U Ingenieurb\u00fcros",
    "sg:phone":"+41 71 761 35 50",
    "sg:postcode":"8006",
    "sg:province":"Z\u00fcrich",
    "wof:name":"Hengartner Felix Gmbh Planung U. Beratung Von Neu- U. Umbauten Usw.",
    "wof:placetype":"venue"
},
  "geometry": {"coordinates":[9.546888,47.319656],"type":"Point"}
}