{
  "type": "Feature",
  "properties": {
    "iso:country":"CH",
    "sg:address":"9058",
    "sg:city":"Br\u00fclisau",
    "sg:orig_category":"Vereine Musik/Blasmusik",
    "sg:postcode":"9058",
    "sg:province":"Appenzell Innerhoden",
    "wof:name":"Musikgesellschaft",
    "wof:placetype":"venue"
},
  "geometry": {"coordinates":[9.4545249939,47.2966156006],"type":"Point"}
}