{
  "type": "Feature",
  "properties": {
    "iso:country":"CH",
    "sg:address":"Hinterburg",
    "sg:city":"Neuheim",
    "sg:orig_category":"Herstellung von sonstigen Maschinen f\u00fcr unspezifische Verwendung",
    "sg:postcode":"6345",
    "sg:province":"Zug",
    "wof:name":"Weiss Johann.",
    "wof:placetype":"venue"
},
  "geometry": {"coordinates":[8.5699319839,47.1977653503],"type":"Point"}
}