{
  "type": "Feature",
  "properties": {
    "iso:country":"CH",
    "sg:address":"Route De Nyon",
    "sg:city":"St-cergue",
    "sg:classifiers":[
        {
            "category":"Travel",
            "subcategory":"Hotels & Motels",
            "type":"Entertainment"
        }
    ],
    "sg:phone":"+41 22 360 25 45",
    "sg:postcode":"1264",
    "sg:province":"Vaud",
    "sg:tags":[
        "hotels",
        "mit",
        "restaurant"
    ],
    "wof:name":"H\u00f2tel Le Point Du Jour",
    "wof:placetype":"venue"
},
  "geometry": {"coordinates":[6.1585121155,46.4450187683],"type":"Point"}
}