{
  "type": "Feature",
  "properties": {
    "iso:country":"CH",
    "sg:address":"Thielle",
    "sg:city":"Thielle",
    "sg:orig_category":"Detailhandel mit M\u00f6beln U Haushaltsgegenst\u00e4nden",
    "sg:postcode":"2075",
    "sg:province":"Neuch\u00e2tel",
    "wof:name":"Jornod P. & Cie",
    "wof:placetype":"venue"
},
  "geometry": {"coordinates":[7.0219497681,47.0200500488],"type":"Point"}
}