{
  "type": "Feature",
  "properties": {
    "iso:country":"CH",
    "sg:address":"Loomattstrasse 34",
    "sg:city":"Stallikon",
    "sg:orig_category":"Wirtschaftspr\u00fcfung, Steuerberatung U Treuhand",
    "sg:postcode":"8143",
    "sg:province":"Z\u00fcrich",
    "wof:name":"Treuhand Und Steuerberatungen Nauer",
    "wof:placetype":"venue"
},
  "geometry": {"coordinates":[8.7681970596,47.3052825928],"type":"Point"}
}