{
  "type": "Feature",
  "properties": {
    "addr:full":"Tempelstrasse 11 Thun Bern 3608",
    "addr:housenumber":"11",
    "addr:postcode":"3608",
    "addr:street":"Tempelstrasse;Bern",
    "iso:country":"CH",
    "sg:address":"Tempelstrasse 11",
    "sg:city":"Thun",
    "sg:classifiers":[
        {
            "category":"Government",
            "subcategory":"Fire Station",
            "type":"Public Place"
        }
    ],
    "sg:phone":"+41 33 334 30 00",
    "sg:postcode":"3608",
    "sg:province":"Bern",
    "sg:tags":[
        "climbing",
        "net"
    ],
    "wof:name":"Fuchs Thun Ag",
    "wof:placetype":"venue"
},
  "geometry": {"coordinates":[7.596906,46.744762],"type":"Point"}
}