{
  "type": "Feature",
  "properties": {
    "iso:country":"CH",
    "sg:address":"Brauereiweg 3 8309 N\u00fcrensdorf. Postfach 279",
    "sg:city":"N\u00fcrensdorf",
    "sg:orig_category":"Detailhandel mit Waren verschiedener Art, Hauptrichtung Nahrungsmittel Handelsvermittlung U Grosshan",
    "sg:phone":"+41 79 672 20 70",
    "sg:postcode":"8309",
    "sg:province":"Z\u00fcrich",
    "wof:name":"Provalora Cs Ag",
    "wof:placetype":"venue"
},
  "geometry": {"coordinates":[8.6500511169,47.4469223022],"type":"Point"}
}