{
  "type": "Feature",
  "properties": {
    "iso:country":"CH",
    "sg:address":"Ruelle De Borjaux 9",
    "sg:city":"Blonay",
    "sg:orig_category":"Detailhandel mit Beleuchtungs U Haushaltsgegenst\u00e4nden Detailhandel mit elektrischen Haushalts, Radio",
    "sg:phone":"+41 21 731 23 00",
    "sg:postcode":"1807",
    "sg:province":"Vaud",
    "wof:name":"Jean-claude Depierraz Bettina Service \u00e9lectrom\u00e9nager",
    "wof:placetype":"venue"
},
  "geometry": {"coordinates":[6.66395,46.590206],"type":"Point"}
}