{
  "type": "Feature",
  "properties": {
    "iso:country":"CH",
    "sg:address":"Rebhaldenweg 14",
    "sg:city":"Mellingen",
    "sg:orig_category":"Eisenwaren Detailhandel",
    "sg:phone":"+41 56 491 15 33",
    "sg:postcode":"5507",
    "sg:province":"Aargau",
    "wof:name":"Hans Peterhans Eisenwaren",
    "wof:placetype":"venue"
},
  "geometry": {"coordinates":[8.2798671722,47.4209785461],"type":"Point"}
}