{
  "type": "Feature",
  "properties": {
    "iso:country":"CH",
    "sg:address":"Rathausplatz 3- 5",
    "sg:city":"Altst\u00e4tten",
    "sg:classifiers":[
        {
            "category":"Shopping",
            "subcategory":"Clothing, Apparel, & Fashions",
            "type":"Retail Goods"
        }
    ],
    "sg:phone":"+41 71 755 16 44",
    "sg:postcode":"9450",
    "sg:province":"St. Gallen",
    "sg:tags":[
        "textile",
        "clothing",
        "clothes"
    ],
    "wof:name":"Erwin Hutter Ag",
    "wof:placetype":"venue"
},
  "geometry": {"coordinates":[9.540827,47.378098],"type":"Point"}
}