{
  "type": "Feature",
  "properties": {
    "iso:country":"CH",
    "sg:address":"Turnerstrasse 32",
    "sg:city":"Basel",
    "sg:orig_category":"Herstellung von Betonerzeugnissen f\u00fcr den Bau",
    "sg:phone":"+41 26 668 53 54",
    "sg:postcode":"4058",
    "sg:province":"Basel-Stadt",
    "wof:name":"Gram Sa",
    "wof:placetype":"venue"
},
  "geometry": {"coordinates":[6.8695130348,46.7477416992],"type":"Point"}
}