{
  "type": "Feature",
  "properties": {
    "iso:country":"CH",
    "sg:address":"Kugelgasse 32a",
    "sg:city":"Diepoldsau",
    "sg:orig_category":"Sportvereine Turnen",
    "sg:phone":"+41 71 733 20 88",
    "sg:postcode":"9444",
    "sg:province":"St. Gallen",
    "wof:name":"Ktv Widnau",
    "wof:placetype":"venue"
},
  "geometry": {"coordinates":[9.6613140106,47.3907852173],"type":"Point"}
}