{
  "type": "Feature",
  "properties": {
    "iso:country":"CH",
    "sg:address":"Rue Guillaume-farel L 2053 Cernier Case Postale 36",
    "sg:city":"Cernier",
    "sg:orig_category":"Advokaturb\u00fcros Notariate",
    "sg:phone":"+41 32 853 43 33",
    "sg:postcode":"2053",
    "sg:province":"Neuch\u00e2tel",
    "wof:name":"Jean-marc Terrier Etude D'avocat & Notaire",
    "wof:placetype":"venue"
},
  "geometry": {"coordinates":[6.905208,47.061378],"type":"Point"}
}