{
  "type": "Feature",
  "properties": {
    "iso:country":"CH",
    "sg:address":"Gassli 7 5603 Staufen. Postfach 63",
    "sg:city":"Staufen",
    "sg:orig_category":"Non-Classified Establishments",
    "sg:postcode":"5603",
    "sg:province":"Aargau",
    "wof:name":"New Fashion World Sa",
    "wof:placetype":"venue"
},
  "geometry": {"coordinates":[8.2738237381,47.3502388],"type":"Point"}
}