{
  "type": "Feature",
  "properties": {
    "iso:country":"CH",
    "sg:address":"Dorfstrasse 9",
    "sg:city":"Richterswil",
    "sg:orig_category":"Fachdetailhandel in Verkaufsr\u00e4umen",
    "sg:postcode":"8805",
    "sg:province":"Z\u00fcrich",
    "wof:name":"Landscapes Edition, Van Hoorick Edmond",
    "wof:placetype":"venue"
},
  "geometry": {"coordinates":[8.7063827515,47.2063179016],"type":"Point"}
}