{
  "type": "Feature",
  "properties": {
    "iso:country":"CH",
    "sg:address":"1716",
    "sg:city":"Plaffeien",
    "sg:classifiers":[
        {
            "category":"Education",
            "subcategory":"Vocational School",
            "type":"Public Place"
        }
    ],
    "sg:phone":"+41 26 402 54 98",
    "sg:postcode":"1716",
    "sg:province":"Fribourg",
    "sg:tags":[
        "koch-",
        "haushaltschulen"
    ],
    "wof:name":"Haushaltungsschule",
    "wof:placetype":"venue"
},
  "geometry": {"coordinates":[7.2868709564,46.7410163879],"type":"Point"}
}