{
  "type": "Feature",
  "properties": {
    "addr:full":"Haselwart 1 Sursee Luzern 6210",
    "addr:housenumber":"1",
    "addr:postcode":"6210",
    "addr:street":"Haselwart",
    "iso:country":"CH",
    "sg:address":"Haselwart 1",
    "sg:city":"Sursee",
    "sg:orig_category":"Bauschreinerei",
    "sg:phone":"+41 41 921 20 88",
    "sg:postcode":"6210",
    "sg:province":"Luzern",
    "wof:name":"Marlies Stadelmann Schreinerei",
    "wof:placetype":"venue"
},
  "geometry": {"coordinates":[8.10998,47.172508],"type":"Point"}
}