{
  "type": "Feature",
  "properties": {
    "iso:country":"CH",
    "sg:address":"Asylstrasse 58 8032 Z\u00fcrich. Postfach",
    "sg:city":"Z\u00fcrich",
    "sg:orig_category":"Fachdetailhandel mit pharmazeutischen Produkten",
    "sg:phone":"+41 31 371 95 20",
    "sg:postcode":"8030",
    "wof:name":"R\u00f6sli D.",
    "wof:placetype":"venue"
},
  "geometry": {"coordinates":[7.4367179871,46.9398574829],"type":"Point"}
}