{
  "type": "Feature",
  "properties": {
    "iso:country":"CH",
    "sg:address":"Schw\u00e4ntenmos 14",
    "sg:city":"Zumikon",
    "sg:orig_category":"Handel mit Motorr\u00e4dern, Teilen U Zubeh\u00f6r Instandhaltung U Reparatur von Motorr\u00e4dern",
    "sg:postcode":"8126",
    "sg:province":"Z\u00fcrich",
    "wof:name":"Power-bike-shop Hugger Roger",
    "wof:placetype":"venue"
},
  "geometry": {"coordinates":[8.6196470261,47.3388710022],"type":"Point"}
}