{
  "type": "Feature",
  "properties": {
    "iso:country":"CH",
    "sg:address":"M\u00fchlebr\u00fcckestrasse 11",
    "sg:city":"Winterthur",
    "sg:orig_category":"Kinderkrippen U horte",
    "sg:postcode":"8400",
    "sg:province":"Z\u00fcrich",
    "wof:name":"Bolz & Zippel Kinderspielgruppe",
    "wof:placetype":"venue"
},
  "geometry": {"coordinates":[8.7417049408,47.4972877502],"type":"Point"}
}