{
  "type": "Feature",
  "properties": {
    "iso:country":"CH",
    "sg:address":"Felsenhofstrasse 11",
    "sg:city":"Adliswil",
    "sg:orig_category":"Arztpraxen",
    "sg:phone":"+41 17109625",
    "sg:postcode":"8134",
    "sg:province":"Z\u00fcrich",
    "wof:name":"Dr.med.fritz Wegmann Spezialarzt Fmh",
    "wof:placetype":"venue"
},
  "geometry": {"coordinates":[8.534415,47.314827],"type":"Point"}
}