{
  "type": "Feature",
  "properties": {
    "addr:full":"Im Zentrum G\u00fcterstrasse 1a Safenwil Aargau 5745",
    "addr:housenumber":"1a",
    "addr:postcode":"5745",
    "addr:street":"Im Zentrum Gueterstrasse",
    "iso:country":"CH",
    "sg:address":"Im Zentrum G\u00fcterstrasse 1a",
    "sg:city":"Safenwil",
    "sg:classifiers":[
        {
            "category":"Bars & Pubs",
            "type":"Food & Drink"
        }
    ],
    "sg:phone":"+41 62 797 34 74",
    "sg:postcode":"5745",
    "sg:province":"Aargau",
    "sg:tags":[
        "restaurant"
    ],
    "wof:name":"Bar-restaurant Wild Cat",
    "wof:placetype":"venue"
},
  "geometry": {"coordinates":[7.983643,47.318893],"type":"Point"}
}