{
  "type": "Feature",
  "properties": {
    "iso:country":"CH",
    "sg:address":"Burgholz Oey",
    "sg:city":"Diemtigen",
    "sg:orig_category":"Pensionskassen",
    "sg:postcode":"3754",
    "sg:province":"Bern",
    "wof:name":"Personalf\u00fcrsorgestiftung Der M\u00fchle Burgholz",
    "wof:placetype":"venue"
},
  "geometry": {"coordinates":[7.6007881165,46.6655387878],"type":"Point"}
}