{
  "type": "Feature",
  "properties": {
    "iso:country":"CH",
    "sg:address":"Chemin Pr\u00e9 Aux Fleurs 34",
    "sg:city":"Estavayer-le-lac",
    "sg:orig_category":"Unclassifiable Establishments",
    "sg:phone":"+41 26 663 32 81",
    "sg:postcode":"1470",
    "sg:province":"Fribourg",
    "wof:name":"Mac Espace, M. Hermenjat",
    "wof:placetype":"venue"
},
  "geometry": {"coordinates":[6.8430299759,46.8417854309],"type":"Point"}
}