{
  "type": "Feature",
  "properties": {
    "iso:country":"CH",
    "sg:address":"6515 Gudo. Postfach",
    "sg:city":"Gudo",
    "sg:orig_category":"Unternehmensberatung",
    "sg:postcode":"6515",
    "sg:province":"Ticino",
    "wof:name":"Afics Engineering Gmbh",
    "wof:placetype":"venue"
},
  "geometry": {"coordinates":[7.2078771591,46.7501525879],"type":"Point"}
}