{
  "type": "Feature",
  "properties": {
    "iso:country":"CH",
    "sg:address":"6945 Origlio. Postfach 25",
    "sg:city":"Origlio",
    "sg:orig_category":"Sportvereine Ballsport Fussball",
    "sg:phone":"+41 91 966 63 55",
    "sg:postcode":"6945",
    "sg:province":"Ticino",
    "wof:name":"As Origlio",
    "wof:placetype":"venue"
},
  "geometry": {"coordinates":[8.9459600449,46.0508499146],"type":"Point"}
}