{
  "type": "Feature",
  "properties": {
    "addr:full":"Frey.heros\u00e9-strasse 20 Aarau Aargau 5000",
    "addr:housenumber":"20",
    "addr:postcode":"5000",
    "addr:street":"Frey.Herose\u0301-Strasse",
    "iso:country":"CH",
    "sg:address":"Frey.heros\u00e9-strasse 20",
    "sg:city":"Aarau",
    "sg:orig_category":"Advokaturb\u00fcros Notariate",
    "sg:phone":"+41 31 310 46 46",
    "sg:postcode":"5000",
    "sg:province":"Aargau",
    "wof:name":"Zubler & Bertossa Advokatur-& Notariatsb\u00fcro",
    "wof:placetype":"venue"
},
  "geometry": {"coordinates":[7.445048,46.948849],"type":"Point"}
}