{
  "type": "Feature",
  "properties": {
    "iso:country":"CH",
    "sg:address":"Waldst\u00e4tterstrasse 5",
    "sg:city":"Luzern",
    "sg:orig_category":"Detailhandel mit Bekleidungszubeh\u00f6r U Bekleidung ohne ausgepr\u00e4gten Schwerpunkt Detailhandel mit Lede",
    "sg:phone":"+41 41 210 13 16",
    "sg:postcode":"6003",
    "sg:province":"Luzern",
    "wof:name":"Bossa Nova Zuberb\u00fchler",
    "wof:placetype":"venue"
},
  "geometry": {"coordinates":[8.306472,47.045864],"type":"Point"}
}