{
  "type": "Feature",
  "properties": {
    "addr:full":"Rue Cheneau-de-bourg 9-13 Lausanne Vaud 1003",
    "addr:housenumber":"9-13",
    "addr:postcode":"1003",
    "addr:street":"Rue Cheneau-De-Bourg",
    "iso:country":"CH",
    "sg:address":"Rue Cheneau-de-bourg 9-13",
    "sg:city":"Lausanne",
    "sg:orig_category":"Detailhandel mit Antiquit\u00e4ten U Gebrauchtwaren in Verkaufsr\u00e4umen Kunsthandel",
    "sg:phone":"+41 21 323 47 77",
    "sg:postcode":"1003",
    "sg:province":"Vaud",
    "wof:name":"La Vieille Fontaine Antiquit\u00e9s Sa",
    "wof:placetype":"venue"
},
  "geometry": {"coordinates":[6.636533,46.520634],"type":"Point"}
}