{
  "type": "Feature",
  "properties": {
    "iso:country":"CH",
    "sg:address":"Tivoli Avenue De 5",
    "sg:city":"Fribourg",
    "sg:orig_category":"Herstellung von \u00d6fen U Brennern",
    "sg:phone":"+41 26 422 31 10",
    "sg:postcode":"1700",
    "sg:province":"Fribourg",
    "wof:name":"Perriard Cheminees S\u00e0rl",
    "wof:placetype":"venue"
},
  "geometry": {"coordinates":[7.1536831856,46.8037452698],"type":"Point"}
}