{
  "type": "Feature",
  "properties": {
    "iso:country":"CH",
    "sg:address":"Unterer B\u00fcndtenweg 7",
    "sg:city":"Sch\u00f6nenbuch",
    "sg:orig_category":"Primarschulen",
    "sg:phone":"+41 61 481 55 10",
    "sg:postcode":"4124",
    "sg:province":"Basel-Landschaft",
    "wof:name":"Primarschule",
    "wof:placetype":"venue"
},
  "geometry": {"coordinates":[7.5044221878,47.5371551514],"type":"Point"}
}