{
  "type": "Feature",
  "properties": {
    "iso:country":"CH",
    "sg:address":"Hauptstrasse 9",
    "sg:city":"Ziefen",
    "sg:orig_category":"G\u00fcterbef\u00f6rderung im Strassenverkehr",
    "sg:phone":"+41 61 931 34 44",
    "sg:postcode":"4417",
    "sg:province":"Basel-Landschaft",
    "wof:name":"Thommen & Co Ag Mineral\u00f6le & Chemikalien",
    "wof:placetype":"venue"
},
  "geometry": {"coordinates":[7.7181611061,47.4342651367],"type":"Point"}
}