{
  "type": "Feature",
  "properties": {
    "iso:country":"CH",
    "sg:address":"Grand-rue 19",
    "sg:city":"Ponts-de-martel",
    "sg:orig_category":"Diskotheken, Dancings, Night Clubs RESTAURANTS: TEA-ROOMS",
    "sg:phone":"+41 32 937 14 64",
    "sg:postcode":"2316",
    "sg:province":"Neuch\u00e2tel",
    "wof:name":"Restaurant De La Loyaut\u00e9 & Dancing",
    "wof:placetype":"venue"
},
  "geometry": {"coordinates":[6.7315969467,46.9991111755],"type":"Point"}
}