{
  "type": "Feature",
  "properties": {
    "iso:country":"CH",
    "sg:address":"Meggenhus",
    "sg:city":"M\u00f6rschwil",
    "sg:orig_category":"Bauspenglerei Zimmerei, Dachdeckerei, Bauspenglerei U Abdichtung",
    "sg:phone":"+41 71 866 19 61",
    "sg:postcode":"9402",
    "sg:province":"St. Gallen",
    "wof:name":"Lehner G.",
    "wof:placetype":"venue"
},
  "geometry": {"coordinates":[9.445613,47.471302],"type":"Point"}
}