{
  "type": "Feature",
  "properties": {
    "iso:country":"CH",
    "sg:address":"Zeltweg 50 8032 Z\u00fcrich. Postfach 8032 Z\u00fcrich",
    "sg:city":"Zust",
    "sg:orig_category":"Vereine Tierschutz Veterin\u00e4rwesen",
    "sg:phone":"+41 12536720",
    "sg:postcode":"32",
    "wof:name":"Vier Pfoten - Stiftung F\u00fcr Tierschutz Bezweckt Den Gedanken Des Tierschutzes Zu Verbreiten U. Bedr\u00e4ngten Tieren In Not Zu Helfen Usw",
    "wof:placetype":"venue"
},
  "geometry": {"coordinates":[8.5520591736,47.3675994873],"type":"Point"}
}