{
  "type": "Feature",
  "properties": {
    "iso:country":"CH",
    "sg:address":"Tennmoosstrasse 37 8044 Gockhausen. Postfach",
    "sg:city":"Gockhausen",
    "sg:orig_category":"Herstellung von sonstigen Holzwaren",
    "sg:postcode":"8044",
    "sg:province":"Z\u00fcrich",
    "wof:name":"Bauer H.",
    "wof:placetype":"venue"
},
  "geometry": {"coordinates":[8.5961360931,47.3792495728],"type":"Point"}
}