{
  "type": "Feature",
  "properties": {
    "iso:country":"CH",
    "sg:address":"Salen",
    "sg:city":"M\u00f6rschwil",
    "sg:orig_category":"Non-Classified Establishments",
    "sg:postcode":"9402",
    "sg:province":"St. Gallen",
    "wof:name":"Moag Baustoffe Holding Ag",
    "wof:placetype":"venue"
},
  "geometry": {"coordinates":[9.4222021103,47.468624115],"type":"Point"}
}