{
  "type": "Feature",
  "properties": {
    "iso:country":"CH",
    "sg:address":"1820",
    "sg:city":"Veytaux",
    "sg:orig_category":"Primarschulen",
    "sg:phone":"+41 21 964 36 17",
    "sg:postcode":"1820",
    "sg:province":"Vaud",
    "wof:name":"Ecole Primaire Coll\u00e8ge De Veytaux",
    "wof:placetype":"venue"
},
  "geometry": {"coordinates":[6.9288420677,46.4210624695],"type":"Point"}
}