{
  "type": "Feature",
  "properties": {
    "iso:country":"CH",
    "sg:address":"Gr\u00fctlistrasse 44 8002 Z\u00fcrich. Postfach",
    "sg:city":"Z\u00fcrich",
    "sg:orig_category":"Pensionskassen",
    "sg:postcode":"8001",
    "sg:province":"Z\u00fcrich",
    "wof:name":"Pensions Und Unterst\u00fctzungsfonds Des Verbandes Der Schweizerischen Gasindustrie",
    "wof:placetype":"venue"
},
  "geometry": {"coordinates":[8.5309324265,47.3617286682],"type":"Point"}
}