{
  "type": "Feature",
  "properties": {
    "iso:country":"CH",
    "sg:address":"Via Maraini 16",
    "sg:city":"Pregassona",
    "sg:orig_category":"Zeitungsdruck Zeitungsverlag",
    "sg:postcode":"6963",
    "sg:province":"Ticino",
    "wof:name":"Bora Verlags Gmbh",
    "wof:placetype":"venue"
},
  "geometry": {"coordinates":[8.9693498611,46.0267181396],"type":"Point"}
}