{
  "type": "Feature",
  "properties": {
    "iso:country":"CH",
    "sg:address":"Wildbachstrasse 8",
    "sg:city":"Langendorf",
    "sg:orig_category":"Arztpraxen",
    "sg:phone":"+41 32 621 44 33",
    "sg:postcode":"4513",
    "sg:province":"Solothurn",
    "wof:name":"Dr.med.franz Christian Bucher Arzt F.allgemeine Medizin Fmh",
    "wof:placetype":"venue"
},
  "geometry": {"coordinates":[7.513849,47.2253],"type":"Point"}
}