{
  "type": "Feature",
  "properties": {
    "iso:country":"CH",
    "sg:address":"Via Mulino 8a",
    "sg:city":"Stabio",
    "sg:orig_category":"Instandhaltung U Reparatur von Automobilen",
    "sg:phone":"+41 91 862 25 63",
    "sg:postcode":"6855",
    "sg:province":"Ticino",
    "wof:name":"Carrozzeria Torpedo Sa",
    "wof:placetype":"venue"
},
  "geometry": {"coordinates":[8.9068098068,46.3802680969],"type":"Point"}
}