{
  "type": "Feature",
  "properties": {
    "iso:country":"CH",
    "sg:address":"Kr\u00e4henweg 3 7000 Chur. Postfach 39",
    "sg:city":"Chur",
    "sg:orig_category":"Reiseb\u00fcros",
    "sg:phone":"+41 81 285 12 85",
    "sg:postcode":"7006",
    "sg:province":"Graubunden",
    "wof:name":"Raetia-reisen",
    "wof:placetype":"venue"
},
  "geometry": {"coordinates":[9.5225877762,46.860206604],"type":"Point"}
}