{
  "type": "Feature",
  "properties": {
    "iso:country":"CH",
    "sg:address":"Via Vergi\u00f2 25",
    "sg:city":"Breganzona",
    "sg:orig_category":"Unclassifiable Establishments",
    "sg:postcode":"6932",
    "sg:province":"Ticino",
    "wof:name":"Pisapio Silvano",
    "wof:placetype":"venue"
},
  "geometry": {"coordinates":[8.9334173203,46.0121879578],"type":"Point"}
}