{
  "type": "Feature",
  "properties": {
    "addr:full":"Hohle Gasse 13 Frutigen Bern 3714",
    "addr:housenumber":"13",
    "addr:postcode":"3714",
    "addr:street":"Hohle Gasse",
    "iso:country":"CH",
    "sg:address":"Hohle Gasse 13",
    "sg:city":"Frutigen",
    "sg:orig_category":"Bau U Wohngenossenschaften",
    "sg:postcode":"3714",
    "sg:province":"Bern",
    "wof:name":"Glb Frutigen",
    "wof:placetype":"venue"
},
  "geometry": {"coordinates":[7.643685,46.589626],"type":"Point"}
}