{
  "type": "Feature",
  "properties": {
    "iso:country":"CH",
    "sg:address":"Feldackerstrasse 1",
    "sg:city":"Sch\u00f6ftland",
    "sg:orig_category":"Car Radios, Car Hi-Fi Systems",
    "sg:phone":"+41 62 721 00 48",
    "sg:postcode":"5040",
    "sg:province":"Aargau",
    "wof:name":"Fischer Autosport",
    "wof:placetype":"venue"
},
  "geometry": {"coordinates":[8.05193,47.314121],"type":"Point"}
}