{
  "type": "Feature",
  "properties": {
    "iso:country":"CH",
    "sg:address":"Rue De La Conf\u00e9d\u00e9ration 6",
    "sg:city":"Gen\u00e8ve",
    "sg:orig_category":"Detailhandel mit Bekleidung Detailhandel mit Pelzwaren",
    "sg:phone":"+41 22 311 44 33",
    "sg:postcode":"1204",
    "sg:province":"Gen\u00e8ve",
    "wof:name":"Rodolphe Fourrures, Schambeck Rudolf",
    "wof:placetype":"venue"
},
  "geometry": {"coordinates":[6.144466,46.203594],"type":"Point"}
}