{
  "type": "Feature",
  "properties": {
    "iso:country":"CH",
    "sg:address":"Rebbergstrasse 4",
    "sg:city":"Weesen",
    "sg:orig_category":"Technische B\u00fcros Elektro",
    "sg:phone":"+41 55 616 15 15",
    "sg:postcode":"8872",
    "sg:province":"St. Gallen",
    "wof:name":"Gm\u00fcr Elektro-planung",
    "wof:placetype":"venue"
},
  "geometry": {"coordinates":[9.1029615402,47.1373748779],"type":"Point"}
}