{
  "type": "Feature",
  "properties": {
    "iso:country":"CH",
    "sg:address":"Piazza Cioccaro 10",
    "sg:city":"Lugano",
    "sg:orig_category":"Kosmetikinstitute",
    "sg:phone":"+41 91 922 09 57",
    "sg:postcode":"6900",
    "sg:province":"Ticino",
    "wof:name":"Gabriella Borella Bellezza Mon Plaisir",
    "wof:placetype":"venue"
},
  "geometry": {"coordinates":[8.949763298,46.0048484802],"type":"Point"}
}