{
  "type": "Feature",
  "properties": {
    "iso:country":"CH",
    "sg:address":"Chemin De L'arb\u00e9riat 15 1806 St-l\u00e9gier Case Postale",
    "sg:city":"St-l\u00e9gier",
    "sg:orig_category":"Geb\u00e4ude, Wohnungsreinigung Reinigungsgewerbe",
    "sg:phone":"+41 21 624 10 75",
    "sg:postcode":"1806",
    "sg:province":"Vaud",
    "wof:name":"Net-ok Sa Entreprise De Nettoyage",
    "wof:placetype":"venue"
},
  "geometry": {"coordinates":[6.6124401093,46.5197715759],"type":"Point"}
}