{
  "type": "Feature",
  "properties": {
    "iso:country":"CH",
    "sg:address":"Flugplatz Belpmoos 3123 Belp. Postfach 75",
    "sg:city":"Belp",
    "sg:orig_category":"Gelegenheitsflugverkehr",
    "sg:postcode":"3123",
    "sg:province":"Bern",
    "wof:name":"Heliswiss, Schweizerische Helicopter Ag",
    "wof:placetype":"venue"
},
  "geometry": {"coordinates":[7.500125885,46.9141540527],"type":"Point"}
}