{
  "type": "Feature",
  "properties": {
    "addr:full":"Chemin De St-georges 15 Clarens Vaud 1815",
    "addr:housenumber":"15",
    "addr:postcode":"1815",
    "addr:street":"Chemin De St-Georges",
    "iso:country":"CH",
    "sg:address":"Chemin De St-georges 15",
    "sg:city":"Clarens",
    "sg:orig_category":"Architekturb\u00fcros",
    "sg:phone":"+41 21 964 41 58",
    "sg:postcode":"1815",
    "sg:province":"Vaud",
    "wof:name":"Jiri Kotlar Bureau D'ing\u00e9nieur & D'arch.",
    "wof:placetype":"venue"
},
  "geometry": {"coordinates":[6.881031,46.445049],"type":"Point"}
}