{
  "type": "Feature",
  "properties": {
    "iso:country":"CH",
    "sg:address":"Petit Bel-air Chemin Du 107",
    "sg:city":"Th\u00f4nex",
    "sg:orig_category":"Sonstiger Grosshandel",
    "sg:phone":"+41 22 349 46 48",
    "sg:postcode":"1226",
    "sg:province":"Gen\u00e8ve",
    "wof:name":"Insight Geneva, Barrie & Hilary Smith",
    "wof:placetype":"venue"
},
  "geometry": {"coordinates":[6.2054028511,46.2002716064],"type":"Point"}
}