{
  "type": "Feature",
  "properties": {
    "addr:full":"B\u00f6rsenstr. 18 Z\u00fcrich Z\u00fcrich 8001",
    "addr:housenumber":"18",
    "addr:postcode":"8001",
    "addr:street":"Boersenstr.",
    "iso:country":"CH",
    "sg:address":"B\u00f6rsenstr. 18",
    "sg:city":"Z\u00fcrich",
    "sg:classifiers":[
        {
            "category":"Banks & Credit Unions",
            "subcategory":"Bank",
            "type":"Services"
        }
    ],
    "sg:phone":"+41 22 310 57 55",
    "sg:postcode":"8001",
    "sg:province":"Z\u00fcrich",
    "wof:name":"Multifinance Sa",
    "wof:placetype":"venue"
},
  "geometry": {"coordinates":[6.141838,46.204739],"type":"Point"}
}