{
  "type": "Feature",
  "properties": {
    "iso:country":"CH",
    "sg:address":"Rue Tronchin 26",
    "sg:city":"Gen\u00e8ve",
    "sg:orig_category":"Offsetdruck",
    "sg:phone":"+41 22 733 95 25",
    "sg:postcode":"1202",
    "sg:province":"Gen\u00e8ve",
    "wof:name":"A. Barrat & S. Curvaia Imprimerie Du Progr\u00e8s",
    "wof:placetype":"venue"
},
  "geometry": {"coordinates":[6.1348900795,46.2103385925],"type":"Point"}
}