{
  "type": "Feature",
  "properties": {
    "addr:full":"Waldighoferstrasse 16 Basel Basel-Stadt 4055",
    "addr:housenumber":"16",
    "addr:postcode":"4055",
    "addr:street":"Waldighoferstrasse",
    "iso:country":"CH",
    "sg:address":"Waldighoferstrasse 16",
    "sg:city":"Basel",
    "sg:orig_category":"Ausbaugewerbe Hoch U Tiefbau",
    "sg:postcode":"4055",
    "sg:province":"Basel-Stadt",
    "wof:name":"Renova Bau Team Gmbh",
    "wof:placetype":"venue"
},
  "geometry": {"coordinates":[7.561469,47.568047],"type":"Point"}
}