{
  "type": "Feature",
  "properties": {
    "iso:country":"CH",
    "sg:address":"Kreuzstrasse 39",
    "sg:city":"Z\u00fcrich",
    "sg:orig_category":"Softwareentwicklung U beratung",
    "sg:postcode":"8008",
    "sg:province":"Z\u00fcrich",
    "wof:name":"Backplane Gmbh",
    "wof:placetype":"venue"
},
  "geometry": {"coordinates":[8.5543909073,47.3647994995],"type":"Point"}
}