{
  "type": "Feature",
  "properties": {
    "iso:country":"CH",
    "sg:address":"Oltnerstrasse 11",
    "sg:city":"Niederg\u00f6sgen",
    "sg:orig_category":"Sanit\u00e4rinstallation",
    "sg:phone":"+41 27 475 26 51",
    "sg:postcode":"5013",
    "sg:province":"Solothurn",
    "wof:name":"Francis M\u00e9trailler Installations Sanitaires",
    "wof:placetype":"venue"
},
  "geometry": {"coordinates":[7.5843100548,46.1964187622],"type":"Point"}
}