{
  "type": "Feature",
  "properties": {
    "iso:country":"CH",
    "sg:address":"Landstrasse 77 5430 Wettingen. Postfach",
    "sg:city":"Wettingen",
    "sg:orig_category":"Fachdetailhandel in Verkaufsr\u00e4umen",
    "sg:postcode":"5430",
    "sg:province":"Aargau",
    "wof:name":"Juwelier Petillo Ag Juwelen, Schmuck, Uhren; Herstellung, Verarbeitung, Handel",
    "wof:placetype":"venue"
},
  "geometry": {"coordinates":[8.3247079849,47.4670333862],"type":"Point"}
}