{
  "type": "Feature",
  "properties": {
    "iso:country":"CH",
    "sg:address":"Thurstrasse 20 9214 Kradolf. Postfach",
    "sg:city":"Kradolf",
    "sg:orig_category":"Allgemeiner Hoch U Tiefbau",
    "sg:phone":"+41 71 642 20 40",
    "sg:postcode":"9214",
    "sg:province":"Thurgau",
    "wof:name":"Bt Bau+transport Gmbh",
    "wof:placetype":"venue"
},
  "geometry": {"coordinates":[9.194263,47.525799],"type":"Point"}
}