{
  "type": "Feature",
  "properties": {
    "iso:country":"CH",
    "sg:address":"Zweierstrasse 166 8003 Z\u00fcrich. Postfach",
    "sg:city":"Z\u00fcrich",
    "sg:orig_category":"Handel mit Automobilteilen U Zubeh\u00f6r",
    "sg:phone":"+41 19084555",
    "sg:postcode":"8001",
    "sg:province":"Z\u00fcrich",
    "wof:name":"Big Al's Toolkit, Albasini Und Co. Autozubeh\u00f6r; Handel",
    "wof:placetype":"venue"
},
  "geometry": {"coordinates":[8.5181398392,47.3702316284],"type":"Point"}
}