{
  "type": "Feature",
  "properties": {
    "iso:country":"CH",
    "sg:address":"Birkenweg 2",
    "sg:city":"Wallisellen",
    "sg:orig_category":"Druck ohne Zeitungsdruck Offsetdruck",
    "sg:phone":"+41 79 205 74 44",
    "sg:postcode":"8304",
    "sg:province":"Z\u00fcrich",
    "wof:name":"Keller & Co Buchdruck Offsetdruck",
    "wof:placetype":"venue"
},
  "geometry": {"coordinates":[8.2069797516,47.4814758301],"type":"Point"}
}