{
  "type": "Feature",
  "properties": {
    "iso:country":"CH",
    "sg:address":"Kapellenstrasse 28",
    "sg:city":"Bern",
    "sg:orig_category":"Zahnarztpraxen",
    "sg:phone":"+41 31 381 73 88",
    "sg:postcode":"3011",
    "sg:province":"Bern",
    "wof:name":"Dr. Med. Dent. Peter Hess Zahnarzt",
    "wof:placetype":"venue"
},
  "geometry": {"coordinates":[7.4335951805,46.9455223083],"type":"Point"}
}