{
  "type": "Feature",
  "properties": {
    "iso:country":"CH",
    "sg:address":"Centrale Rue 5 1003 Lausanne Case Postale",
    "sg:city":"Lausanne",
    "sg:orig_category":"Vermietung U Verpachtung von eigenen Immobilien",
    "sg:postcode":"1003",
    "sg:province":"Vaud",
    "wof:name":"Berney P. & G.",
    "wof:placetype":"venue"
},
  "geometry": {"coordinates":[6.259950161,46.6153488159],"type":"Point"}
}