{
  "type": "Feature",
  "properties": {
    "iso:country":"CH",
    "sg:address":"Bundkofen 475",
    "sg:city":"Sch\u00fcpfen",
    "sg:orig_category":"Grosshandel mit Getreide, Saatgut U Futtermitteln G\u00fcterbef\u00f6rderung im Strassenverkehr",
    "sg:phone":"+41 31 879 17 33",
    "sg:postcode":"3054",
    "sg:province":"Bern",
    "wof:name":"Affolter M\u00fchle Und Transport Ag",
    "wof:placetype":"venue"
},
  "geometry": {"coordinates":[7.3559398651,47.0498390198],"type":"Point"}
}