{
  "type": "Feature",
  "properties": {
    "iso:country":"CH",
    "sg:address":"Watterstrasse 92",
    "sg:city":"Regensdorf",
    "sg:orig_category":"Grosshandel mit pharmazeutischen Erzeugnissen, medizinischen U orthop\u00e4dischen Artikeln Sonstiger Det",
    "sg:phone":"+41 18403177",
    "sg:postcode":"8105",
    "sg:province":"Z\u00fcrich",
    "wof:name":"Duttweiler & Hohl Ag",
    "wof:placetype":"venue"
},
  "geometry": {"coordinates":[8.4681329727,47.4331321716],"type":"Point"}
}