{
  "type": "Feature",
  "properties": {
    "iso:country":"CH",
    "sg:address":"Sandb\u00fcchel",
    "sg:city":"Rheineck",
    "sg:orig_category":"Vermietung U Verpachtung von eigenen Immobilien",
    "sg:postcode":"9424",
    "sg:province":"St. Gallen",
    "wof:name":"S\u00e4ntisblick Liegenschaften Ag",
    "wof:placetype":"venue"
},
  "geometry": {"coordinates":[9.5893707275,47.4674797058],"type":"Point"}
}