{
  "type": "Feature",
  "properties": {
    "iso:country":"CH",
    "sg:address":"Bachweg 9",
    "sg:city":"Felben",
    "sg:orig_category":"Non-Classified Establishments",
    "sg:postcode":"8552",
    "sg:province":"Thurgau",
    "wof:name":"Blumengarten Felben, C. & S. Sch\u00e4r-blickenstorfer",
    "wof:placetype":"venue"
},
  "geometry": {"coordinates":[8.9440202713,47.57862854],"type":"Point"}
}