{
  "type": "Feature",
  "properties": {
    "addr:full":"N\u00fcschelerstrasse 31 Z\u00fcrich Z\u00fcrich 8001",
    "addr:housenumber":"31",
    "addr:postcode":"8001",
    "addr:street":"Nueschelerstrasse",
    "iso:country":"CH",
    "sg:address":"N\u00fcschelerstrasse 31",
    "sg:city":"Z\u00fcrich",
    "sg:orig_category":"Detailhandel mit Bekleidung Detailhandel mit Damenbekleidung",
    "sg:phone":"+41 12125058",
    "sg:postcode":"8001",
    "sg:province":"Z\u00fcrich",
    "wof:name":"Filatex Ag",
    "wof:placetype":"venue"
},
  "geometry": {"coordinates":[8.535739,47.37225],"type":"Point"}
}