{
  "type": "Feature",
  "properties": {
    "iso:country":"CH",
    "sg:address":"Heiligkreuz 52 9490 Vaduz. Postfach",
    "sg:city":"Vaduz",
    "sg:orig_category":"Versicherungen Generalagenturen",
    "sg:phone":"+423 237 27 00",
    "sg:postcode":"9490",
    "wof:name":"Elvia Versicherungen Generalagentur",
    "wof:placetype":"venue"
},
  "geometry": {"coordinates":[9.5219573975,47.1329574585],"type":"Point"}
}