{
  "type": "Feature",
  "properties": {
    "iso:country":"CH",
    "sg:address":"Avenue De La Vogeaz 10",
    "sg:city":"Morges",
    "sg:orig_category":"Herstellung von keramischen Haushaltswaren U Ziergegenst\u00e4nden",
    "sg:phone":"+41 21 963 10 45",
    "sg:postcode":"1110",
    "sg:province":"Vaud",
    "wof:name":"Myrielle Gugg C\u00e9ramiste",
    "wof:placetype":"venue"
},
  "geometry": {"coordinates":[6.480175972,46.5119400024],"type":"Point"}
}