{
  "type": "Feature",
  "properties": {
    "iso:country":"CH",
    "sg:address":"Bergstrasse 41",
    "sg:city":"M\u00e4nnedorf",
    "sg:orig_category":"Detailhandel mit Schuhen Detailhandel mit medizinischen U orthop\u00e4dischen Artikeln",
    "sg:phone":"+41 19201288",
    "sg:postcode":"8708",
    "sg:province":"Z\u00fcrich",
    "wof:name":"Peter Odermatt Fussorthop\u00e4die Schuhe",
    "wof:placetype":"venue"
},
  "geometry": {"coordinates":[8.6957159042,47.2526893616],"type":"Point"}
}