{
  "type": "Feature",
  "properties": {
    "addr:full":"Rue De La Prulay 31 Meyrin Gen\u00e8ve 1217",
    "addr:housenumber":"31",
    "addr:postcode":"1217",
    "addr:street":"Rue De La Prulay",
    "iso:country":"CH",
    "sg:address":"Rue De La Prulay 31",
    "sg:city":"Meyrin",
    "sg:orig_category":"Arztpraxen",
    "sg:phone":"+41 32 757 24 24",
    "sg:postcode":"1217",
    "sg:province":"Gen\u00e8ve",
    "wof:name":"Dr M\u00e9d.jean-f. De Montmollin M\u00e9decin G\u00e9n\u00e9raliste Fmh",
    "wof:placetype":"venue"
},
  "geometry": {"coordinates":[7.03732,47.050838],"type":"Point"}
}