{
  "type": "Feature",
  "properties": {
    "iso:country":"CH",
    "sg:city":"Ponte Capriasca",
    "sg:classifiers":[
        {
            "category":"Banks & Credit Unions",
            "subcategory":"Bank",
            "type":"Services"
        }
    ],
    "sg:phone":"+41 91 945 27 05",
    "sg:postcode":"6946",
    "sg:province":"Ticino",
    "wof:name":"Raiffeisen Di Origlio - Ponte, Capriasca",
    "wof:placetype":"venue"
},
  "geometry": {"coordinates":[8.95025,46.059029],"type":"Point"}
}