{
  "type": "Feature",
  "properties": {
    "iso:country":"CH",
    "sg:address":"Schulstrasse 7",
    "sg:city":"Urdorf",
    "sg:orig_category":"Politische Parteien CVP",
    "sg:phone":"+41 17343208",
    "sg:postcode":"8902",
    "sg:province":"Z\u00fcrich",
    "wof:name":"Cvp Sektion Urdorf",
    "wof:placetype":"venue"
},
  "geometry": {"coordinates":[8.4280729294,47.3898887634],"type":"Point"}
}