{
  "type": "Feature",
  "properties": {
    "iso:country":"CH",
    "sg:address":"Montedato",
    "sg:city":"Riazzino",
    "sg:orig_category":"Instandhaltung U Reparatur von Automobilen",
    "sg:phone":"+41 91 859 35 48",
    "sg:postcode":"6595",
    "sg:province":"Ticino",
    "wof:name":"Giacomo Longhi Carrozzeria",
    "wof:placetype":"venue"
},
  "geometry": {"coordinates":[8.897600174,46.1745605469],"type":"Point"}
}