{
  "type": "Feature",
  "properties": {
    "iso:country":"CH",
    "sg:address":"Schafhauserstrasse 37",
    "sg:city":"Winterthur",
    "sg:orig_category":"Bauschreinerei Herstellung von M\u00f6beln verschiedener Art",
    "sg:phone":"+41 52 212 82 20",
    "sg:postcode":"8400",
    "sg:province":"Z\u00fcrich",
    "wof:name":"Martin Schriber",
    "wof:placetype":"venue"
},
  "geometry": {"coordinates":[8.723019,47.507305],"type":"Point"}
}