{
  "type": "Feature",
  "properties": {
    "iso:country":"CH",
    "sg:address":"Rue Du Vieux-billard 2",
    "sg:city":"Gen\u00e8ve",
    "sg:classifiers":[
        {
            "category":"Personal",
            "subcategory":"Piercing",
            "type":"Services"
        }
    ],
    "sg:phone":"+41 22 328 06 03",
    "sg:postcode":"1205",
    "sg:province":"Gen\u00e8ve",
    "sg:tags":[
        "tattoo"
    ],
    "wof:name":"Tattoo Studio Body Art",
    "wof:placetype":"venue"
},
  "geometry": {"coordinates":[6.1396560669,46.2003250122],"type":"Point"}
}