{
  "type": "Feature",
  "properties": {
    "iso:country":"CH",
    "sg:address":"Morat Rue De 54 A",
    "sg:city":"Fribourg",
    "sg:orig_category":"Non-Classified Establishments",
    "sg:phone":"+41 26 322 23 81",
    "sg:postcode":"1700",
    "sg:province":"Fribourg",
    "wof:name":"Marbrerie St-l\u00e9onard Sa Fribourg",
    "wof:placetype":"venue"
},
  "geometry": {"coordinates":[7.1536831856,46.8037452698],"type":"Point"}
}