{
  "type": "Feature",
  "properties": {
    "iso:country":"CH",
    "sg:address":"Maunoir Rue 9",
    "sg:city":"Gen\u00e8ve",
    "sg:orig_category":"Unclassifiable Establishments",
    "sg:postcode":"1207",
    "sg:province":"Gen\u00e8ve",
    "wof:name":"Jean-paul Meylan Sa",
    "wof:placetype":"venue"
},
  "geometry": {"coordinates":[6.1601929665,46.2040710449],"type":"Point"}
}