{
  "type": "Feature",
  "properties": {
    "iso:country":"CH",
    "sg:address":"Marktgasse 36",
    "sg:city":"B\u00fclach",
    "sg:orig_category":"Detailhandel mit Beleuchtungs U Haushaltsgegenst\u00e4nden Herstellung von Schneidwaren U Bestecken",
    "sg:phone":"+41 18601327",
    "sg:postcode":"8180",
    "sg:province":"Z\u00fcrich",
    "wof:name":"Scherrer Werner",
    "wof:placetype":"venue"
},
  "geometry": {"coordinates":[8.541264,47.516575],"type":"Point"}
}