{
  "type": "Feature",
  "properties": {
    "iso:country":"CH",
    "sg:address":"Avenue De La Gare 20",
    "sg:city":"Lausanne",
    "sg:orig_category":"Unternehmensberatung",
    "sg:phone":"+41 21 311 76 00",
    "sg:postcode":"1003",
    "sg:province":"Vaud",
    "wof:name":"Amc Alpha Conseils Sa Conseils D Le Domaine Juridique, Fiscal Etc",
    "wof:placetype":"venue"
},
  "geometry": {"coordinates":[6.6334729195,46.5171813965],"type":"Point"}
}