{
  "type": "Feature",
  "properties": {
    "iso:country":"CH",
    "sg:address":"3366",
    "sg:city":"Bettenhausen",
    "sg:orig_category":"Primarschulen",
    "sg:phone":"+41 62 961 12 69",
    "sg:postcode":"3366",
    "sg:province":"Bern",
    "wof:name":"Primarschule",
    "wof:placetype":"venue"
},
  "geometry": {"coordinates":[7.7086801529,47.1700897217],"type":"Point"}
}