{
  "type": "Feature",
  "properties": {
    "iso:country":"CH",
    "sg:address":"Le Port",
    "sg:city":"Cheyres",
    "sg:orig_category":"Druck ohne Zeitungsdruck Siebdruck",
    "sg:phone":"+41 26 663 34 44",
    "sg:postcode":"1468",
    "sg:province":"Fribourg",
    "wof:name":"Juan Gomez At.s\u00e9rigraphie R\u00e9cr\u00e9ation",
    "wof:placetype":"venue"
},
  "geometry": {"coordinates":[6.7846698761,46.8174858093],"type":"Point"}
}