{
  "type": "Feature",
  "properties": {
    "iso:country":"CH",
    "sg:address":"Chemin Du Moulin 3c",
    "sg:city":"Bevaix",
    "sg:classifiers":[
        {
            "category":"Restaurant",
            "type":"Food & Drink"
        }
    ],
    "sg:phone":"+41 32 846 15 54",
    "sg:postcode":"2022",
    "sg:province":"Neuch\u00e2tel",
    "wof:name":"Restaurant La Trinquette",
    "wof:placetype":"venue"
},
  "geometry": {"coordinates":[6.8169641495,46.9217414856],"type":"Point"}
}