{
  "type": "Feature",
  "properties": {
    "iso:country":"CH",
    "sg:address":"Alte Gasse 16",
    "sg:city":"Ibach",
    "sg:orig_category":"Non-Classified Establishments",
    "sg:postcode":"6438",
    "sg:province":"Schwyz",
    "wof:name":"Dzankovic-golos Sanela",
    "wof:placetype":"venue"
},
  "geometry": {"coordinates":[8.6443758011,47.0129089355],"type":"Point"}
}