{
  "type": "Feature",
  "properties": {
    "iso:country":"CH",
    "sg:address":"Hildastrasse 7",
    "sg:city":"Z\u00fcrich",
    "sg:orig_category":"Grosshandel mit B\u00fcromaschinen Grosshandel mit Datenverarbeitungsger\u00e4ten",
    "sg:phone":"+41 12676868",
    "sg:postcode":"8004",
    "sg:province":"Z\u00fcrich",
    "wof:name":"Zillion",
    "wof:placetype":"venue"
},
  "geometry": {"coordinates":[8.5157337189,47.3764152527],"type":"Point"}
}