{
  "type": "Feature",
  "properties": {
    "iso:country":"CH",
    "sg:address":"Luzernstrasse 11",
    "sg:city":"Sursee",
    "sg:orig_category":"Vereine Dramatische and Theater",
    "sg:phone":"+41 56 633 47 04",
    "sg:postcode":"6210",
    "sg:province":"Luzern",
    "wof:name":"Operettenb\u00fchne Bremgarten",
    "wof:placetype":"venue"
},
  "geometry": {"coordinates":[8.3448781967,47.3512954712],"type":"Point"}
}