{
  "type": "Feature",
  "properties": {
    "iso:country":"CH",
    "sg:address":"Thunstrasse 15",
    "sg:city":"Burgdorf",
    "sg:orig_category":"Detailhandel mit Geschenkartikeln U Souvenirs",
    "sg:phone":"+41 34 422 33 59",
    "sg:postcode":"3400",
    "sg:province":"Bern",
    "wof:name":"Kerzenkeller Rita L\u00fcthy",
    "wof:placetype":"venue"
},
  "geometry": {"coordinates":[7.6235342026,47.0491104126],"type":"Point"}
}