{
  "type": "Feature",
  "properties": {
    "iso:country":"CH",
    "sg:address":"Laufen Am Rheinfall",
    "sg:city":"Dachsen",
    "sg:classifiers":[
        {
            "category":"Restaurant",
            "type":"Food & Drink"
        }
    ],
    "sg:phone":"+41 52 659 14 19",
    "sg:postcode":"8447",
    "sg:province":"Z\u00fcrich",
    "wof:name":"Restaurant Schloss Laufen Am Rheinfall",
    "wof:placetype":"venue"
},
  "geometry": {"coordinates":[8.6241998672,47.6626281738],"type":"Point"}
}