{
  "type": "Feature",
  "properties": {
    "iso:country":"CH",
    "sg:address":"Rue Pr\u00e9-de-la-reine 7",
    "sg:city":"Cartigny",
    "sg:classifiers":[
        {
            "category":"Banks & Credit Unions",
            "subcategory":"Bank",
            "type":"Services"
        }
    ],
    "sg:phone":"+41 32 865 14 65",
    "sg:postcode":"1236",
    "sg:province":"Gen\u00e8ve",
    "wof:name":"Banque Raiffeisen Cote-aux-fees",
    "wof:placetype":"venue"
},
  "geometry": {"coordinates":[6.49085,46.86874],"type":"Point"}
}