{
  "type": "Feature",
  "properties": {
    "iso:country":"CH",
    "sg:address":"Waisenhausstrasse 4",
    "sg:city":"Z\u00fcrich",
    "sg:orig_category":"Sportvereine Eissport Eishockey",
    "sg:phone":"+41 12114058",
    "sg:postcode":"8001",
    "sg:province":"Z\u00fcrich",
    "wof:name":"Akadem.eishockey-club",
    "wof:placetype":"venue"
},
  "geometry": {"coordinates":[8.5408859253,47.3765449524],"type":"Point"}
}