{
  "type": "Feature",
  "properties": {
    "iso:country":"CH",
    "sg:address":"Langendorfstrasse 2",
    "sg:city":"Langendorf",
    "sg:orig_category":"Detailhandel mit Gebrauchtwaren in Verkaufsr\u00e4umen",
    "sg:phone":"+41 32 618 37 40",
    "sg:postcode":"4513",
    "sg:province":"Solothurn",
    "wof:name":"Heilsarmee Brockenstube",
    "wof:placetype":"venue"
},
  "geometry": {"coordinates":[7.5151081085,47.2164840698],"type":"Point"}
}