{
  "type": "Feature",
  "properties": {
    "iso:country":"CH",
    "sg:address":"Wallenhofring 14",
    "sg:city":"Sch\u00f6ftland",
    "sg:orig_category":"Kaminfeger",
    "sg:phone":"+41 62 721 12 81",
    "sg:postcode":"5040",
    "sg:province":"Aargau",
    "wof:name":"Martin Haldimann Kaminfegermeister",
    "wof:placetype":"venue"
},
  "geometry": {"coordinates":[8.0543680191,47.3045845032],"type":"Point"}
}