{
  "type": "Feature",
  "properties": {
    "iso:country":"CH",
    "sg:address":"1091",
    "sg:city":"Grandvaux",
    "sg:orig_category":"Sportvereine Sch\u00fctzen",
    "sg:postcode":"1091",
    "sg:province":"Vaud",
    "wof:name":"St\u00e9 De Tir Armes De Guerre La Br\u00e9vine",
    "wof:placetype":"venue"
},
  "geometry": {"coordinates":[6.5342831612,46.9501419067],"type":"Point"}
}