{
  "type": "Feature",
  "properties": {
    "iso:country":"CH",
    "sg:address":"Borenco Via 18",
    "sg:city":"Minusio",
    "sg:orig_category":"Mit dem Versicherungsgewerbe verbundene T\u00e4tigkeiten",
    "sg:phone":"+41 91 743 53 04",
    "sg:postcode":"6648",
    "sg:province":"Ticino",
    "wof:name":"Aldo Bianchi",
    "wof:placetype":"venue"
},
  "geometry": {"coordinates":[8.8108997345,46.1739044189],"type":"Point"}
}