{
  "type": "Feature",
  "properties": {
    "iso:country":"CH",
    "sg:address":"Jonch\u00e8re Chemin De La 4",
    "sg:city":"Cossonay-ville",
    "sg:orig_category":"Unternehmensberatung",
    "sg:phone":"+41 21 862 30 71",
    "sg:postcode":"1304",
    "sg:province":"Vaud",
    "wof:name":"Int\u00e9gration Optimale S\u00e0rl",
    "wof:placetype":"venue"
},
  "geometry": {"coordinates":[6.4875569344,46.6005821228],"type":"Point"}
}