{
  "type": "Feature",
  "properties": {
    "iso:country":"CH",
    "sg:address":"Burggasse 9",
    "sg:city":"Biel/bienne",
    "sg:orig_category":"Detailhandel mit Waren verschiedener Art, Hauptrichtung Nahrungsmittel Fachdetailhandel mit Nahrungs",
    "sg:phone":"+41 22 342 01 23",
    "sg:postcode":"2502",
    "sg:province":"Bern",
    "wof:name":"Marco Trezzini Poissonnerie-comestible",
    "wof:placetype":"venue"
},
  "geometry": {"coordinates":[6.1372442245,46.1862564087],"type":"Point"}
}