{
  "type": "Feature",
  "properties": {
    "iso:country":"CH",
    "sg:address":"Tellenfeld",
    "sg:city":"Frutigen",
    "sg:classifiers":[
        {
            "category":"Government",
            "subcategory":"Post Office",
            "type":"Public Place"
        }
    ],
    "sg:phone":"+41 33 671 14 04",
    "sg:postcode":"3714",
    "sg:province":"Bern",
    "sg:tags":[
        "die",
        "poststellen"
    ],
    "wof:name":"Die Post Frutigen 2",
    "wof:placetype":"venue"
},
  "geometry": {"coordinates":[7.6513600349,46.5794792175],"type":"Point"}
}