{
  "type": "Feature",
  "properties": {
    "iso:country":"CH",
    "sg:address":"B\u00f6dlistrasse 25",
    "sg:city":"Unter\u00e4geri",
    "sg:orig_category":"Detailhandel mit Haustieren U zoologischem Bedarf Grosshandel mit Getreide, Saatgut U Futtermitteln",
    "sg:phone":"+41 41 750 41 04",
    "sg:postcode":"6314",
    "sg:province":"Zug",
    "wof:name":"Nbs Stutz & Co",
    "wof:placetype":"venue"
},
  "geometry": {"coordinates":[8.5772323608,47.1402282715],"type":"Point"}
}