{
  "type": "Feature",
  "properties": {
    "iso:country":"CH",
    "sg:address":"Chemin De Champs-pr\u00e9vost 10",
    "sg:city":"Vernier",
    "sg:orig_category":"G\u00fcterbef\u00f6rderung im Strassenverkehr R\u00fcckgewinnung U Vorbereitung f\u00fcr die Wiederverwertung Recycling ",
    "sg:phone":"+41 22 341 15 19",
    "sg:postcode":"1214",
    "sg:province":"Gen\u00e8ve",
    "wof:name":"Transvoirie Sa Transports Et Service Voirie",
    "wof:placetype":"venue"
},
  "geometry": {"coordinates":[6.0927081108,46.221206665],"type":"Point"}
}