{
  "type": "Feature",
  "properties": {
    "iso:country":"CH",
    "sg:address":"Frey-heros\u00e9-strasse 25",
    "sg:city":"Aarau",
    "sg:orig_category":"Architektur U Ingenieurb\u00fcros Architekturb\u00fcros",
    "sg:phone":"+41 62 822 18 64",
    "sg:postcode":"5000",
    "sg:province":"Aargau",
    "wof:name":"Schibli Werner, Dipl. Architekt Eth/sia Und Raumplaner Bsp",
    "wof:placetype":"venue"
},
  "geometry": {"coordinates":[8.051775,47.389038],"type":"Point"}
}