{
  "type": "Feature",
  "properties": {
    "iso:country":"CH",
    "sg:address":"Kohlplatz 1",
    "sg:city":"Heiden",
    "sg:orig_category":"Vermietung U Verpachtung von eigenen Immobilien",
    "sg:postcode":"9410",
    "sg:province":"Appenzell Ausserrhoden",
    "wof:name":"Fritschi Immobilien Ag",
    "wof:placetype":"venue"
},
  "geometry": {"coordinates":[7.8657898903,47.3410415649],"type":"Point"}
}