{
  "type": "Feature",
  "properties": {
    "addr:full":"Seematt 7 6314 Unter\u00e4geri. Postfach 147 Unter\u00e4geri Zug 6314",
    "addr:housenumber":"7;147",
    "addr:postcode":"6314;6314",
    "addr:street":"Seematt;Postfach;Unteraegeri Zug",
    "iso:country":"CH",
    "sg:address":"Seematt 7 6314 Unter\u00e4geri. Postfach 147",
    "sg:city":"Unter\u00e4geri",
    "sg:orig_category":"Architekturb\u00fcros",
    "sg:phone":"+41 41 750 23 21",
    "sg:postcode":"6314",
    "sg:province":"Zug",
    "wof:name":"Werner Guhl Architekturb\u00fcro",
    "wof:placetype":"venue"
},
  "geometry": {"coordinates":[8.587885,47.135853],"type":"Point"}
}