{
  "type": "Feature",
  "properties": {
    "iso:country":"CH",
    "sg:address":"Industriestrasse 27",
    "sg:city":"Schlieren",
    "sg:orig_category":"Instandhaltung U Reparatur von Automobilen",
    "sg:phone":"+41 33 755 12 00",
    "sg:postcode":"8952",
    "sg:province":"Z\u00fcrich",
    "wof:name":"Joop Van Meel Garage",
    "wof:placetype":"venue"
},
  "geometry": {"coordinates":[7.2672080994,46.3892021179],"type":"Point"}
}