{
  "type": "Feature",
  "properties": {
    "iso:country":"CH",
    "sg:address":"Borghese Via 19",
    "sg:city":"Locarno",
    "sg:orig_category":"Fachdetailhandel in Verkaufsr\u00e4umen",
    "sg:postcode":"6600",
    "sg:province":"Ticino",
    "wof:name":"Bergo Sport Di Bergonzoli Edo",
    "wof:placetype":"venue"
},
  "geometry": {"coordinates":[8.7918815613,46.1698722839],"type":"Point"}
}