{
  "type": "Feature",
  "properties": {
    "iso:country":"CH",
    "sg:address":"Passwangstrasse 10",
    "sg:city":"Breitenbach",
    "sg:orig_category":"Unclassifiable Establishments",
    "sg:postcode":"4226",
    "sg:province":"Solothurn",
    "wof:name":"Allfina-treuhand Kirchhofer&partner",
    "wof:placetype":"venue"
},
  "geometry": {"coordinates":[7.5430240631,47.4069595337],"type":"Point"}
}