{
  "type": "Feature",
  "properties": {
    "iso:country":"CH",
    "sg:address":"Industriestr. 8",
    "sg:city":"Winterthur",
    "sg:classifiers":[
        {
            "category":"Manufacturing",
            "subcategory":"Printing",
            "type":"Manufacturing & Wholesale Goods"
        }
    ],
    "sg:phone":"+41 52 235 71 71",
    "sg:postcode":"8401",
    "sg:province":"Z\u00fcrich",
    "sg:tags":[
        "publishing"
    ],
    "wof:name":"Druckerei Winterthur Dw Ag",
    "wof:placetype":"venue"
},
  "geometry": {"coordinates":[8.7503118515,47.4962654114],"type":"Point"}
}