{
  "type": "Feature",
  "properties": {
    "iso:country":"CH",
    "sg:address":"Bas Du Village 12a 2908 Grandfontaine. Postfach",
    "sg:city":"Grandfontaine",
    "sg:orig_category":"RESTAURANTS: TEA-ROOMS",
    "sg:postcode":"2908",
    "sg:province":"Jura",
    "wof:name":"Caf\u00e9 La Fontaine S\u00e0rl",
    "wof:placetype":"venue"
},
  "geometry": {"coordinates":[6.939748764,47.3908615112],"type":"Point"}
}