{
  "type": "Feature",
  "properties": {
    "iso:country":"CH",
    "sg:address":"Rue Du Bourg 4",
    "sg:city":"Aigle",
    "sg:classifiers":[
        {
            "category":"Restaurant",
            "type":"Food & Drink"
        }
    ],
    "sg:phone":"+41 24 466 28 81",
    "sg:postcode":"1860",
    "sg:province":"Vaud",
    "wof:name":"Caf\u00e9 Rong Town",
    "wof:placetype":"venue"
},
  "geometry": {"coordinates":[6.968914032,46.3182678223],"type":"Point"}
}