{
  "type": "Feature",
  "properties": {
    "iso:country":"CH",
    "sg:address":"St. Gallerstrasse 53 8645 Jona. Postfach",
    "sg:city":"Jona",
    "sg:orig_category":"Herstellung von Werkzeugmaschinen",
    "sg:phone":"+41 55 212 51 16",
    "sg:postcode":"8645",
    "sg:province":"St. Gallen",
    "wof:name":"Hs Schweisstechnik Gmbh",
    "wof:placetype":"venue"
},
  "geometry": {"coordinates":[8.8387012482,47.2301101685],"type":"Point"}
}