{
  "type": "Feature",
  "properties": {
    "iso:country":"CH",
    "sg:address":"Burgstrasse 6",
    "sg:city":"Glarus",
    "sg:orig_category":"Datenverarbeitungsdienste Fernmeldedienste",
    "sg:phone":"+41 55 645 41 71",
    "sg:postcode":"8750",
    "sg:province":"Glarus",
    "wof:name":"Wetege Gmbh",
    "wof:placetype":"venue"
},
  "geometry": {"coordinates":[9.069638,47.039986],"type":"Point"}
}