{
  "type": "Feature",
  "properties": {
    "iso:country":"CH",
    "sg:address":"Rue Caroline 7",
    "sg:city":"Lausanne",
    "sg:orig_category":"Detailhandel mit Lederwaren U Reiseartikeln Detailhandel mit Schuhen U Lederwaren",
    "sg:phone":"+41 21 323 15 38",
    "sg:postcode":"1003",
    "sg:province":"Vaud",
    "wof:name":"L'arcade, Burnand Jacqueline.",
    "wof:placetype":"venue"
},
  "geometry": {"coordinates":[6.6369481087,46.5204772949],"type":"Point"}
}