{
  "type": "Feature",
  "properties": {
    "iso:country":"CH",
    "sg:address":"Gemeindehausplatz 4",
    "sg:city":"Riniken",
    "sg:orig_category":"Tierarztpraxis",
    "sg:phone":"+41 56 442 59 89",
    "sg:postcode":"5223",
    "sg:province":"Aargau",
    "wof:name":"Dr. Med. Vet. Ueli Aeberhard Tierarzt",
    "wof:placetype":"venue"
},
  "geometry": {"coordinates":[8.1888713837,47.4949684143],"type":"Point"}
}