{
  "type": "Feature",
  "properties": {
    "iso:country":"CH",
    "sg:address":"Rothschild Rue 50 1202 Gen\u00e8ve. Postfach",
    "sg:city":"Gen\u00e8ve",
    "sg:orig_category":"Unclassifiable Establishments",
    "sg:postcode":"1202",
    "sg:province":"Gen\u00e8ve",
    "wof:name":"Hech Holding Ag",
    "wof:placetype":"venue"
},
  "geometry": {"coordinates":[9.6351919174,47.4310073853],"type":"Point"}
}