{
  "type": "Feature",
  "properties": {
    "iso:country":"CH",
    "sg:address":"Unterseestrasse 77",
    "sg:city":"Arosa",
    "sg:orig_category":"Detailhandel mit Fahrr\u00e4dern Handel mit Motorr\u00e4dern, Teilen U Zubeh\u00f6r Instandhaltung U Reparatur von ",
    "sg:phone":"+41 81 377 36 56",
    "sg:postcode":"7050",
    "sg:province":"Graubunden",
    "wof:name":"Michael Rohleder Bike O Delic Fahrradshop",
    "wof:placetype":"venue"
},
  "geometry": {"coordinates":[9.6798563004,46.7801856995],"type":"Point"}
}