{
  "type": "Feature",
  "properties": {
    "iso:country":"CH",
    "sg:address":"Bellevuestrasse 2a 6280 Hochdorf. Postfach",
    "sg:city":"Hochdorf",
    "sg:orig_category":"Detailhandel mit elektrischen Haushalts-,Radio U Fernsehger\u00e4ten sowie Musikinstrumenten",
    "sg:postcode":"6280",
    "sg:province":"Luzern",
    "wof:name":"Blasinstrumente Gasser",
    "wof:placetype":"venue"
},
  "geometry": {"coordinates":[8.2882604599,47.1688156128],"type":"Point"}
}