{
  "type": "Feature",
  "properties": {
    "addr:full":"Route Du Seyon 15 Dombresson Neuch\u00e2tel 2056",
    "addr:housenumber":"15",
    "addr:postcode":"2056",
    "addr:street":"Route Du Seyon;Neucha\u0302Tel",
    "iso:country":"CH",
    "sg:address":"Route Du Seyon 15",
    "sg:city":"Dombresson",
    "sg:orig_category":"Architektur U Ingenieurb\u00fcros Grosshandel mit elektrischen Haushaltsger\u00e4ten, Radio U Fernsehger\u00e4ten",
    "sg:phone":"+41 32 853 65 60",
    "sg:postcode":"2056",
    "sg:province":"Neuch\u00e2tel",
    "wof:name":"Ace Cosandier Alain",
    "wof:placetype":"venue"
},
  "geometry": {"coordinates":[6.946348,47.064407],"type":"Point"}
}