{
  "type": "Feature",
  "properties": {
    "iso:country":"CH",
    "sg:address":"Zurlindenstrasse 21",
    "sg:city":"Z\u00fcrich",
    "sg:orig_category":"RESTAURANTS: TEA-ROOMS",
    "sg:phone":"+41 14635924",
    "sg:postcode":"8003",
    "sg:province":"Z\u00fcrich",
    "wof:name":"Pizzeria Boccalino 2 Gmbh",
    "wof:placetype":"venue"
},
  "geometry": {"coordinates":[8.5221300125,47.3681945801],"type":"Point"}
}