{
  "type": "Feature",
  "properties": {
    "iso:country":"CH",
    "sg:address":"Stationsstrasse 2",
    "sg:city":"N\u00e4nikon",
    "sg:orig_category":"Vereine Milit\u00e4r",
    "sg:phone":"+41 19402746",
    "sg:postcode":"8606",
    "sg:province":"Z\u00fcrich",
    "wof:name":"Milit\u00e4rspiel Uster",
    "wof:placetype":"venue"
},
  "geometry": {"coordinates":[8.6934089661,47.3703193665],"type":"Point"}
}