{
  "type": "Feature",
  "properties": {
    "iso:country":"CH",
    "sg:address":"K\u00fchlewil",
    "sg:city":"Zimmerwald",
    "sg:orig_category":"Detailhandel mit Milcherzeugnissen U Eiern Verarbeitung von Milch",
    "sg:phone":"+41 31 819 30 73",
    "sg:postcode":"3086",
    "sg:province":"Bern",
    "wof:name":"Marius Kilch\u00f6r K\u00e4serei",
    "wof:placetype":"venue"
},
  "geometry": {"coordinates":[7.4716010094,46.8815917969],"type":"Point"}
}