{
  "type": "Feature",
  "properties": {
    "iso:country":"CH",
    "sg:address":"Eichstrasse 48",
    "sg:city":"Glattbrugg",
    "sg:orig_category":"Reinigungsgewerbe",
    "sg:phone":"+41 18102421",
    "sg:postcode":"8152",
    "sg:province":"Z\u00fcrich",
    "wof:name":"D'amico Haus & Garten Gmbh",
    "wof:placetype":"venue"
},
  "geometry": {"coordinates":[8.5560951233,47.431476593],"type":"Point"}
}