{
  "type": "Feature",
  "properties": {
    "iso:country":"CH",
    "sg:address":"Lettenstrasse 10",
    "sg:city":"Jonen",
    "sg:orig_category":"Innendekorationsateliers",
    "sg:phone":"+41 18505658",
    "sg:postcode":"8916",
    "sg:province":"Aargau",
    "wof:name":"Fritz Zaugg Innendecorationen Polsterei",
    "wof:placetype":"venue"
},
  "geometry": {"coordinates":[8.5068674088,47.4950637817],"type":"Point"}
}