{
  "type": "Feature",
  "properties": {
    "iso:country":"CH",
    "sg:address":"Junkholzweg 3",
    "sg:city":"Kaiseraugst",
    "sg:orig_category":"Detailhandel mit Teppichen",
    "sg:phone":"+41 61 816 92 22",
    "sg:postcode":"4303",
    "sg:province":"Aargau",
    "wof:name":"Top Tip Rudolf M\u00fcller Ag M\u00f6bel Teppiche",
    "wof:placetype":"venue"
},
  "geometry": {"coordinates":[7.7308330536,47.5379562378],"type":"Point"}
}