{
  "type": "Feature",
  "properties": {
    "iso:country":"CH",
    "sg:address":"4 Rue Fran\u00e7ois Perrard",
    "sg:city":"Ch\u00eane-bourg",
    "sg:classifiers":[
        {
            "category":"Manufacturing",
            "subcategory":"Textiles",
            "type":"Manufacturing & Wholesale Goods"
        }
    ],
    "sg:phone":"+41 22 348 11 77",
    "sg:postcode":"1225",
    "sg:province":"Gen\u00e8ve",
    "sg:tags":[
        "clothing",
        "accessory"
    ],
    "wof:name":"A Mouley Sa",
    "wof:placetype":"venue"
},
  "geometry": {"coordinates":[6.197026,46.195248],"type":"Point"}
}