{
  "type": "Feature",
  "properties": {
    "iso:country":"CH",
    "sg:address":"Rue Du Village 6 1214 Vernier Case Postale 621",
    "sg:city":"Vernier",
    "sg:orig_category":"Primarschulen",
    "sg:phone":"+41 22 341 11 40",
    "sg:postcode":"1214",
    "sg:province":"Gen\u00e8ve",
    "wof:name":"Ecole Primaire Ranches Ii",
    "wof:placetype":"venue"
},
  "geometry": {"coordinates":[6.0848960876,46.2162590027],"type":"Point"}
}