{
  "type": "Feature",
  "properties": {
    "iso:country":"CH",
    "sg:address":"Baselstrasse 32",
    "sg:city":"Muttenz",
    "sg:orig_category":"Herstellung von Frucht U Gem\u00fcses\u00e4ften Herstellung von Obst U Fruchtweinen",
    "sg:phone":"+41 61 461 05 52",
    "sg:postcode":"4132",
    "sg:province":"Basel-Landschaft",
    "wof:name":"Fritz Brunner Kundenmosterei",
    "wof:placetype":"venue"
},
  "geometry": {"coordinates":[7.6414179802,47.5242881775],"type":"Point"}
}