{
  "type": "Feature",
  "properties": {
    "iso:country":"CH",
    "sg:address":"Rouges-terres 31",
    "sg:city":"Hauterive",
    "sg:orig_category":"W\u00e4scherei U chemische Reinigung",
    "sg:phone":"+41 32 753 18 95",
    "sg:postcode":"2068",
    "sg:province":"Neuch\u00e2tel",
    "wof:name":"J.-p.& Antoinette Degrandi Nettoyage Chimique",
    "wof:placetype":"venue"
},
  "geometry": {"coordinates":[6.9761528969,47.0116691589],"type":"Point"}
}