{
  "type": "Feature",
  "properties": {
    "iso:country":"CH",
    "sg:address":"Wettsteinallee 40 4058 Basel. Postfach",
    "sg:city":"Basel",
    "sg:orig_category":"Interessenvertretungen",
    "sg:postcode":"4051",
    "sg:province":"Basel-Stadt",
    "wof:name":"G\u00f6ttertraum Kunstschaffendes Forum Usw.",
    "wof:placetype":"venue"
},
  "geometry": {"coordinates":[7.600894928,47.5602111816],"type":"Point"}
}