{
  "type": "Feature",
  "properties": {
    "iso:country":"CH",
    "sg:address":"Metallstrasse 9a 6300 Zug. Postfach",
    "sg:city":"Zug",
    "sg:orig_category":"Unternehmensberatung",
    "sg:phone":"+41 17131777",
    "sg:postcode":"6300",
    "sg:province":"Zug",
    "wof:name":"Slongo & Partner",
    "wof:placetype":"venue"
},
  "geometry": {"coordinates":[8.5400533676,47.2828903198],"type":"Point"}
}