{
  "type": "Feature",
  "properties": {
    "iso:country":"CH",
    "sg:address":"La Place",
    "sg:city":"Ch\u00e2teau-d'oex",
    "sg:orig_category":"Maler U Glasergewerbe Verlegen von Fussboden",
    "sg:phone":"+41 26 924 61 65",
    "sg:postcode":"1837",
    "wof:name":"Sold\u00e9cor Pierre A.chabloz Tapissier-d\u00e9corateur",
    "wof:placetype":"venue"
},
  "geometry": {"coordinates":[-90.4824676514,30.0648097992],"type":"Point"}
}