{
  "type": "Feature",
  "properties": {
    "iso:country":"CH",
    "sg:address":"Waldheimstrasse 40",
    "sg:city":"Bern",
    "sg:classifiers":[
        {
            "category":"Restaurant",
            "type":"Food & Drink"
        }
    ],
    "sg:phone":"+41 31 301 20 61",
    "sg:postcode":"3012",
    "sg:province":"Bern",
    "wof:name":"Restaurant Waldheim",
    "wof:placetype":"venue"
},
  "geometry": {"coordinates":[7.4265818596,46.9541282654],"type":"Point"}
}