{
  "type": "Feature",
  "properties": {
    "iso:country":"CH",
    "sg:address":"Aeulistrasse 23",
    "sg:city":"Vilters",
    "sg:classifiers":[
        {
            "category":"Building & Trades",
            "subcategory":"Plumbing",
            "type":"Services"
        }
    ],
    "sg:phone":"+41 81 710 51 44",
    "sg:postcode":"7324",
    "sg:province":"St. Gallen",
    "sg:tags":[
        "tub",
        "bath"
    ],
    "wof:name":"Filliger Haustechnik Gmbh",
    "wof:placetype":"venue"
},
  "geometry": {"coordinates":[9.445479,47.029041],"type":"Point"}
}