{
  "type": "Feature",
  "properties": {
    "iso:country":"CH",
    "sg:address":"Bernstrasse 39",
    "sg:city":"Jegenstorf",
    "sg:orig_category":"Non-Classified Establishments",
    "sg:postcode":"3303",
    "sg:province":"Bern",
    "wof:name":"Toni Bracher Gourmet Party Service",
    "wof:placetype":"venue"
},
  "geometry": {"coordinates":[7.505273819,47.0450820923],"type":"Point"}
}