{
  "type": "Feature",
  "properties": {
    "iso:country":"CH",
    "sg:address":"Rue D'yverdon 6",
    "sg:city":"Crissier",
    "sg:orig_category":"Grosshandel mit Getr\u00e4nken Grosshandel mit Wein U Spirituosen",
    "sg:phone":"+41 34 445 65 65",
    "sg:postcode":"1023",
    "sg:province":"Vaud",
    "wof:name":"Laforest Vins Fins Sa",
    "wof:placetype":"venue"
},
  "geometry": {"coordinates":[7.5705728531,47.0944099426],"type":"Point"}
}