{
  "type": "Feature",
  "properties": {
    "iso:country":"CH",
    "sg:address":"Im St\u00fcdacker 7",
    "sg:city":"Urdorf",
    "sg:orig_category":"Softwareentwicklung U beratung",
    "sg:postcode":"8902",
    "sg:province":"Z\u00fcrich",
    "wof:name":"Opco Othmar Ponitz Consulting",
    "wof:placetype":"venue"
},
  "geometry": {"coordinates":[8.4243154526,47.3901138306],"type":"Point"}
}