{
  "type": "Feature",
  "properties": {
    "iso:country":"CH",
    "sg:address":"Baarerstrasse 25",
    "sg:city":"Zug",
    "sg:orig_category":"Non-Classified Establishments",
    "sg:phone":"+41 41 712 00 10",
    "sg:postcode":"6300",
    "sg:province":"Zug",
    "wof:name":"Intigena Beteiligungs Ag",
    "wof:placetype":"venue"
},
  "geometry": {"coordinates":[8.5162143707,47.1727752686],"type":"Point"}
}