{
  "type": "Feature",
  "properties": {
    "iso:country":"CH",
    "sg:address":"Rolliweg 21",
    "sg:city":"Lengnau",
    "sg:classifiers":[
        {
            "category":"Banks & Credit Unions",
            "subcategory":"Investment Brokerage",
            "type":"Services"
        }
    ],
    "sg:phone":"+41 32 653 83 20",
    "sg:postcode":"2543",
    "sg:province":"Bern",
    "sg:tags":[
        "cnc",
        "milling"
    ],
    "wof:name":"Deco-tech Ag",
    "wof:placetype":"venue"
},
  "geometry": {"coordinates":[7.374379,47.178329],"type":"Point"}
}