{
  "type": "Feature",
  "properties": {
    "addr:full":"Zwischenb\u00e4ch 10 9496 Balzers. Postfach 419 Balzers 9496",
    "addr:housenumber":"10;419",
    "addr:postcode":"9496 balzers.;9496",
    "addr:street":"Zwischenbaech;Postfach",
    "iso:country":"CH",
    "sg:address":"Zwischenb\u00e4ch 10 9496 Balzers. Postfach 419",
    "sg:city":"Balzers",
    "sg:orig_category":"Architekturb\u00fcros Hoch U Tiefbau",
    "sg:phone":"+41 75 384 24 40",
    "sg:postcode":"9496",
    "wof:name":"Norbert Vollmar",
    "wof:placetype":"venue"
},
  "geometry": {"coordinates":[9.504964,47.069077],"type":"Point"}
}