{
  "type": "Feature",
  "properties": {
    "iso:country":"CH",
    "sg:address":"Kirchgasse 6",
    "sg:city":"Lenzburg",
    "sg:orig_category":"Vermietung U Verpachtung von eigenen Immobilien",
    "sg:phone":"+41 62 891 34 34",
    "sg:postcode":"5600",
    "sg:province":"Aargau",
    "wof:name":"Realvalor Ag",
    "wof:placetype":"venue"
},
  "geometry": {"coordinates":[8.1792898178,47.387260437],"type":"Point"}
}