{
  "type": "Feature",
  "properties": {
    "iso:country":"CH",
    "sg:address":"Postweg 9",
    "sg:city":"Schneisingen",
    "sg:orig_category":"Sportvereine Ballsport Handball",
    "sg:phone":"+41 56 241 01 63",
    "sg:postcode":"5425",
    "sg:province":"Aargau",
    "wof:name":"Handballclub Ktv Wollishofen",
    "wof:placetype":"venue"
},
  "geometry": {"coordinates":[8.3647489548,47.5193901062],"type":"Point"}
}