{
  "type": "Feature",
  "properties": {
    "iso:country":"CH",
    "sg:address":"Steinhaldenstrasse 24",
    "sg:city":"Geroldswil",
    "sg:orig_category":"Grosshandel mit Eisenwaren sowie Installationsbedarf f\u00fcr Gas, Wasser U Heizung Herstellung von sonst",
    "sg:phone":"+41 17484424",
    "sg:postcode":"8954",
    "sg:province":"Z\u00fcrich",
    "wof:name":"Unimetac Ag",
    "wof:placetype":"venue"
},
  "geometry": {"coordinates":[8.4111499786,47.4197616577],"type":"Point"}
}