{
  "type": "Feature",
  "properties": {
    "iso:country":"CH",
    "sg:address":"Rebstr. 5 8155 Niederhasli. Postfach",
    "sg:city":"Oberhasli",
    "sg:orig_category":"Herstellung von Elektromotoren, Generatoren U Transformatoren",
    "sg:postcode":"8156",
    "sg:province":"Z\u00fcrich",
    "wof:name":"Varimedia Waldschmidt Helmut",
    "wof:placetype":"venue"
},
  "geometry": {"coordinates":[8.5024356842,47.4691352844],"type":"Point"}
}