{
  "type": "Feature",
  "properties": {
    "iso:country":"CH",
    "sg:address":"Via Maraini 18",
    "sg:city":"Lugano",
    "sg:orig_category":"Sanit\u00e4r U Heizungsinstallation Sanit\u00e4rinstallation",
    "sg:phone":"+41 91 993 22 46",
    "sg:postcode":"6900",
    "sg:province":"Ticino",
    "wof:name":"Neoservice Sagl Impianti Di Riscaldamento",
    "wof:placetype":"venue"
},
  "geometry": {"coordinates":[8.9435634613,45.9983634949],"type":"Point"}
}