{
  "type": "Feature",
  "properties": {
    "iso:country":"CH",
    "sg:address":"Thiersteinerallee 95",
    "sg:city":"Basel",
    "sg:orig_category":"Detailhandel mit Textilien",
    "sg:phone":"+41 61 331 16 80",
    "sg:postcode":"4053",
    "sg:province":"Basel-Stadt",
    "wof:name":"Rosy Sollberger Wollgesch\u00e4ft Mille Fili",
    "wof:placetype":"venue"
},
  "geometry": {"coordinates":[7.5965800285,47.5392875671],"type":"Point"}
}