{
  "type": "Feature",
  "properties": {
    "iso:country":"CH",
    "sg:address":"1450",
    "sg:city":"Ste-croix",
    "sg:orig_category":"Pensionskassen",
    "sg:postcode":"1450",
    "sg:province":"Vaud",
    "wof:name":"Fonds De Pr\u00e9voyance De La Fabrique Reuge Sa",
    "wof:placetype":"venue"
},
  "geometry": {"coordinates":[6.5010499954,46.8242111206],"type":"Point"}
}