{
  "type": "Feature",
  "properties": {
    "iso:country":"CH",
    "sg:address":"7168",
    "sg:city":"Schlans",
    "sg:orig_category":"Sportvereine Sch\u00fctzen",
    "sg:postcode":"7168",
    "sg:province":"Graubunden",
    "wof:name":"Schiessverein",
    "wof:placetype":"venue"
},
  "geometry": {"coordinates":[9.0159549713,46.7528953552],"type":"Point"}
}