{
  "type": "Feature",
  "properties": {
    "iso:country":"CH",
    "sg:address":"W\u00fcrenloserstrasse 2",
    "sg:city":"Killwangen",
    "sg:orig_category":"D\u00e4mmung gegen K\u00e4lte, W\u00e4rme, Schall U Ersch\u00fctterung Stukkateurgewerbe, Gipserei U Verputzerei",
    "sg:phone":"+41 56 401 12 88",
    "sg:postcode":"8956",
    "sg:province":"Aargau",
    "wof:name":"Franz Keller Geb\u00e4udeisolationen & Verputze",
    "wof:placetype":"venue"
},
  "geometry": {"coordinates":[8.3580169678,47.4327926636],"type":"Point"}
}