{
  "type": "Feature",
  "properties": {
    "iso:country":"CH",
    "sg:address":"Via San Gottardo 80",
    "sg:city":"Balerna",
    "sg:classifiers":[
        {
            "category":"Travel",
            "subcategory":"Hotels & Motels",
            "type":"Entertainment"
        }
    ],
    "sg:phone":"+41 91 996 11 43",
    "sg:postcode":"6828",
    "sg:province":"Ticino",
    "sg:tags":[
        "hotels",
        "mit",
        "restaurant"
    ],
    "wof:name":"Albergo Bellavista",
    "wof:placetype":"venue"
},
  "geometry": {"coordinates":[8.9249000549,45.9329681396],"type":"Point"}
}