{
  "type": "Feature",
  "properties": {
    "iso:country":"CH",
    "sg:address":"Gotthardstrasse 20 6300 Zug. Postfach 4263",
    "sg:city":"Zug",
    "sg:orig_category":"Grosshandel mit Nahrungsmitteln, Getr\u00e4nken U Tabakwaren",
    "sg:phone":"+41 41 727 71 31",
    "sg:postcode":"6304",
    "sg:province":"Zug",
    "wof:name":"Flagfood Ag",
    "wof:placetype":"venue"
},
  "geometry": {"coordinates":[8.5139894485,47.1727676392],"type":"Point"}
}