{
  "type": "Feature",
  "properties": {
    "iso:country":"CH",
    "sg:address":"Rebenstrasse 8",
    "sg:city":"Goldach",
    "sg:orig_category":"Vermittlung von Immobilien Verwaltung von Immobilien",
    "sg:phone":"+41 61 825 62 11",
    "sg:postcode":"9403",
    "sg:province":"St. Gallen",
    "wof:name":"Lischac Ag Immobilien",
    "wof:placetype":"venue"
},
  "geometry": {"coordinates":[7.6920809746,47.5255203247],"type":"Point"}
}