{
  "type": "Feature",
  "properties": {
    "iso:country":"CH",
    "sg:address":"Zielgasse 8",
    "sg:city":"Kloten",
    "sg:orig_category":"RESTAURANTS: TEA-ROOMS",
    "sg:postcode":"8302",
    "sg:province":"Z\u00fcrich",
    "wof:name":"T\u00fct\u00fcnc\u00fc, Lover-snack",
    "wof:placetype":"venue"
},
  "geometry": {"coordinates":[8.5795545578,47.4523353577],"type":"Point"}
}