{
  "type": "Feature",
  "properties": {
    "iso:country":"CH",
    "sg:address":"B\u00f6sch 25",
    "sg:city":"H\u00fcnenberg",
    "sg:orig_category":"Herstellung von Werkzeugen Mechanische Werkst\u00e4tten",
    "sg:phone":"+41 19303012",
    "sg:postcode":"6331",
    "sg:province":"Zug",
    "wof:name":"Werkzeugsch\u00e4rferei Bachmann & Co",
    "wof:placetype":"venue"
},
  "geometry": {"coordinates":[8.7902326584,47.3309745789],"type":"Point"}
}