{
  "type": "Feature",
  "properties": {
    "iso:country":"CH",
    "sg:address":"Bahnhofstrasse 52",
    "sg:city":"Urdorf",
    "sg:orig_category":"Primarschulen",
    "sg:phone":"+41 17341515",
    "sg:postcode":"8902",
    "sg:province":"Z\u00fcrich",
    "wof:name":"Primarschule",
    "wof:placetype":"venue"
},
  "geometry": {"coordinates":[8.4269685745,47.3860778809],"type":"Point"}
}