{
  "type": "Feature",
  "properties": {
    "iso:country":"CH",
    "sg:address":"Neukirch Herzogsbach",
    "sg:city":"Egnach",
    "sg:orig_category":"Elektrizit\u00e4tsversorgung",
    "sg:phone":"+41 52 365 18 04",
    "sg:postcode":"9322",
    "sg:province":"Thurgau",
    "wof:name":"Elektra Ettenhausen",
    "wof:placetype":"venue"
},
  "geometry": {"coordinates":[8.8953886032,47.4770317078],"type":"Point"}
}