{
  "type": "Feature",
  "properties": {
    "iso:country":"CH",
    "sg:address":"Avenue Haldimand 2",
    "sg:city":"Yverdon-les-bains",
    "sg:orig_category":"Werbevermittlung",
    "sg:phone":"+41 24 426 91 51",
    "sg:postcode":"1400",
    "sg:province":"Vaud",
    "wof:name":"Journal Du Nord Vaudois Service Des Annonces",
    "wof:placetype":"venue"
},
  "geometry": {"coordinates":[6.6431789398,46.779586792],"type":"Point"}
}