{
  "type": "Feature",
  "properties": {
    "iso:country":"CH",
    "sg:address":"Zehntenhausstrasse 64",
    "sg:city":"Z\u00fcrich",
    "sg:orig_category":"Vorschulen, Kinderg\u00e4rten",
    "sg:postcode":"8046",
    "sg:province":"Z\u00fcrich",
    "wof:name":"St\u00e4dtischer Kindergarten",
    "wof:placetype":"venue"
},
  "geometry": {"coordinates":[8.508307457,47.4231910706],"type":"Point"}
}