{
  "type": "Feature",
  "properties": {
    "iso:country":"CH",
    "sg:address":"Hauptstrasse 20",
    "sg:city":"Erlen",
    "sg:orig_category":"Mechanik Stahl U Leichtmetallbau",
    "sg:phone":"+41 22 342 30 20",
    "sg:postcode":"8586",
    "sg:province":"Thurgau",
    "wof:name":"Stalder Et Bullinger Sa",
    "wof:placetype":"venue"
},
  "geometry": {"coordinates":[6.1339907646,46.1876029968],"type":"Point"}
}