{
  "type": "Feature",
  "properties": {
    "iso:country":"CH",
    "sg:address":"Im Fondli",
    "sg:city":"Dietikon",
    "sg:orig_category":"Mit Sport verbundene T\u00e4tigkeiten",
    "sg:phone":"+41 32 351 21 33",
    "sg:postcode":"8953",
    "sg:province":"Z\u00fcrich",
    "wof:name":"T\u00fcfelsburg Ag Reit-& Pensionsstall",
    "wof:placetype":"venue"
},
  "geometry": {"coordinates":[7.4145331383,47.1520652771],"type":"Point"}
}