{
  "type": "Feature",
  "properties": {
    "iso:country":"CH",
    "sg:address":"Rue Du Casino 30 1671 Rue. Postfach",
    "sg:city":"Rue",
    "sg:orig_category":"RESTAURANTS: TEA-ROOMS",
    "sg:phone":"+41 32 968 19 00",
    "sg:postcode":"1671",
    "wof:name":"Caf\u00e9-restaurant L'orologio, Boffelli Guido",
    "wof:placetype":"venue"
},
  "geometry": {"coordinates":[6.8293981552,47.109500885],"type":"Point"}
}