{
  "type": "Feature",
  "properties": {
    "iso:country":"CH",
    "sg:address":"Parkterrasse 16",
    "sg:city":"Bern",
    "sg:orig_category":"Lichtpause U Reprografiebetriebe Offsetdruck",
    "sg:phone":"+41 71 388 48 48",
    "sg:postcode":"3012",
    "sg:province":"Bern",
    "wof:name":"Pius Sch\u00e4fler Ag",
    "wof:placetype":"venue"
},
  "geometry": {"coordinates":[9.2459506989,47.4142608643],"type":"Point"}
}