{
  "type": "Feature",
  "properties": {
    "iso:country":"CH",
    "sg:address":"Waltalingerstrasse 28",
    "sg:city":"Oberneunforn",
    "sg:orig_category":"Detailhandel mit Waren verschiedener Art, Hauptrichtung Nahrungsmittel",
    "sg:phone":"+41 52 745 15 19",
    "sg:postcode":"8526",
    "sg:province":"Thurgau",
    "wof:name":"Landi Oberneunforn",
    "wof:placetype":"venue"
},
  "geometry": {"coordinates":[8.7706203461,47.6087799072],"type":"Point"}
}