{
  "type": "Feature",
  "properties": {
    "iso:country":"CH",
    "sg:address":"Einsiedlerstrasse 43 8834 Schindellegi. Postfach",
    "sg:city":"Schindellegi",
    "sg:orig_category":"Unclassifiable Establishments",
    "sg:phone":"+41 16873904",
    "sg:postcode":"8834",
    "sg:province":"Schwyz",
    "wof:name":"Trend-cars Gmbh",
    "wof:placetype":"venue"
},
  "geometry": {"coordinates":[8.7132177353,47.1750793457],"type":"Point"}
}