{
  "type": "Feature",
  "properties": {
    "iso:country":"CH",
    "sg:address":"Godet Quai Phillipe- 18",
    "sg:city":"Neuch\u00e2tel",
    "sg:orig_category":"Sanit\u00e4r, Heizungs U L\u00fcftungsinstallation",
    "sg:postcode":"2000",
    "sg:province":"Neuch\u00e2tel",
    "wof:name":"Luppi Sa, Chauffage Sanitaire Et Ventilation",
    "wof:placetype":"venue"
},
  "geometry": {"coordinates":[6.9310851097,46.9903335571],"type":"Point"}
}