{
  "type": "Feature",
  "properties": {
    "iso:country":"CH",
    "sg:address":"Haus Dominique",
    "sg:city":"Kippel",
    "sg:orig_category":"Allgemeiner Hochbau Kauf U Verkauf von Immobilien auf eigene Rechnung",
    "sg:phone":"+41 56 484 80 49",
    "sg:postcode":"3917",
    "sg:province":"Valais",
    "wof:name":"Bamir Gmbh",
    "wof:placetype":"venue"
},
  "geometry": {"coordinates":[7.77261,46.399551],"type":"Point"}
}