{
  "type": "Feature",
  "properties": {
    "iso:country":"CH",
    "sg:address":"Petersgraben 21 4051 Basel. Postfach",
    "sg:city":"Basel",
    "sg:orig_category":"Medizinische Labors",
    "sg:phone":"+41 61 261 66 13",
    "sg:postcode":"4003",
    "sg:province":"Basel-Stadt",
    "wof:name":"Medibact Prof. Dr. M. Gasser Medizin. Bakteriologielabor",
    "wof:placetype":"venue"
},
  "geometry": {"coordinates":[7.5847210884,47.5598373413],"type":"Point"}
}