{
  "type": "Feature",
  "properties": {
    "iso:country":"CH",
    "sg:address":"Bahnhofstrasse 3",
    "sg:city":"Romanshorn",
    "sg:orig_category":"Kosmetikinstitute Parf\u00fcmerien U sonstiger Detailhandel mit kosmetischen Artikeln U K\u00f6rperpflegemitte",
    "sg:phone":"+41 71 463 12 09",
    "sg:postcode":"8590",
    "sg:province":"Thurgau",
    "wof:name":"Charlotte Nellen Kosmetiksalon & Parf\u00fcmerie",
    "wof:placetype":"venue"
},
  "geometry": {"coordinates":[9.3779754639,47.5659179688],"type":"Point"}
}