{
  "type": "Feature",
  "properties": {
    "iso:country":"CH",
    "sg:address":"Rotachstrasse 19",
    "sg:city":"Z\u00fcrich",
    "sg:classifiers":[
        {
            "category":"Communications",
            "subcategory":"Radio Station",
            "type":"Services"
        }
    ],
    "sg:postcode":"8003",
    "sg:province":"Z\u00fcrich",
    "sg:tags":[
        "fernsehanstalten",
        "u"
    ],
    "wof:name":"Audiva M. Sch\u00f6nholzer",
    "wof:placetype":"venue"
},
  "geometry": {"coordinates":[8.515961647,47.3699150085],"type":"Point"}
}