{
  "type": "Feature",
  "properties": {
    "iso:country":"CH",
    "sg:address":"Solothurnstrasse 35",
    "sg:city":"Basel",
    "sg:orig_category":"Sportvereine Ballsport Handball",
    "sg:postcode":"4053",
    "sg:province":"Basel-Stadt",
    "wof:name":"Gtv Basel",
    "wof:placetype":"venue"
},
  "geometry": {"coordinates":[7.5909399986,47.5445518494],"type":"Point"}
}