{
  "type": "Feature",
  "properties": {
    "iso:country":"CH",
    "sg:address":"R\u00fctisbergstrasse 12",
    "sg:city":"Oberhasli",
    "sg:orig_category":"Druck ohne Zeitungsdruck Offsetdruck",
    "sg:phone":"+41 18510830",
    "sg:postcode":"8156",
    "sg:province":"Z\u00fcrich",
    "wof:name":"Beryll-druck",
    "wof:placetype":"venue"
},
  "geometry": {"coordinates":[8.5000619888,47.465511322],"type":"Point"}
}