{
  "type": "Feature",
  "properties": {
    "iso:country":"CH",
    "sg:address":"Freiestrasse 27",
    "sg:city":"Winterthur",
    "sg:orig_category":"Architekturb\u00fcros",
    "sg:phone":"+41 52 202 40 66",
    "sg:postcode":"8406",
    "sg:province":"Z\u00fcrich",
    "wof:name":"Hans Motzer Architekturb\u00fcro",
    "wof:placetype":"venue"
},
  "geometry": {"coordinates":[8.713536,47.489864],"type":"Point"}
}