{
  "type": "Feature",
  "properties": {
    "iso:country":"CH",
    "sg:address":"Bahnhofstrasse 9",
    "sg:city":"Engelberg",
    "sg:orig_category":"Nationale Postdienste",
    "sg:phone":"+41 41 637 11 53",
    "sg:postcode":"6390",
    "sg:province":"Obwalden",
    "wof:name":"Die Schweizerische Post",
    "wof:placetype":"venue"
},
  "geometry": {"coordinates":[8.4027070999,46.819442749],"type":"Point"}
}