{
  "type": "Feature",
  "properties": {
    "iso:country":"CH",
    "sg:address":"Talwiesenstrasse 17 8045 Z\u00fcrich. Postfach",
    "sg:city":"Z\u00fcrich",
    "sg:orig_category":"Mechanik Mechanische Werkst\u00e4tten",
    "sg:phone":"+41 14510801",
    "sg:postcode":"8045",
    "sg:province":"Z\u00fcrich",
    "wof:name":"Naef Hans Ag, Z\u00fcrich",
    "wof:placetype":"venue"
},
  "geometry": {"coordinates":[8.5166912079,47.363407135],"type":"Point"}
}