{
  "type": "Feature",
  "properties": {
    "iso:country":"CH",
    "sg:address":"Dorfstrasse 29 4805 Brittnau. Postfach 123",
    "sg:city":"Brittnau",
    "sg:orig_category":"Sanit\u00e4r U Heizungsinstallation Sanit\u00e4rinstallation",
    "sg:phone":"+41 62 751 19 43",
    "sg:postcode":"4805",
    "sg:province":"Aargau",
    "wof:name":"Lerch R. Ag",
    "wof:placetype":"venue"
},
  "geometry": {"coordinates":[7.9429359436,47.2602729797],"type":"Point"}
}