{
  "type": "Feature",
  "properties": {
    "iso:country":"CH",
    "sg:address":"Via Bartolomeo Varenna 17",
    "sg:city":"Locarno",
    "sg:orig_category":"Malerei Verlegen von Fliesen U Platten",
    "sg:phone":"+41 91 751 31 87",
    "sg:postcode":"6600",
    "sg:province":"Ticino",
    "wof:name":"Mario Meneganti Impresa Di Pittura",
    "wof:placetype":"venue"
},
  "geometry": {"coordinates":[8.7911663055,46.1682662964],"type":"Point"}
}