{
  "type": "Feature",
  "properties": {
    "iso:country":"CH",
    "sg:address":"Melchnaustrasse 7 4934 Madiswil. Postfach",
    "sg:city":"Madiswil",
    "sg:orig_category":"Non-Classified Establishments",
    "sg:postcode":"4934",
    "sg:province":"Bern",
    "wof:name":"Wittwer Krebs Engineering Gmbh",
    "wof:placetype":"venue"
},
  "geometry": {"coordinates":[8.208193779,47.4843215942],"type":"Point"}
}