{
  "type": "Feature",
  "properties": {
    "iso:country":"CH",
    "sg:address":"Chemin-dessus",
    "sg:city":"Chemin",
    "sg:classifiers":[
        {
            "category":"Travel",
            "subcategory":"Hotels & Motels",
            "type":"Entertainment"
        }
    ],
    "sg:phone":"+41 27 722 81 64",
    "sg:postcode":"1927",
    "sg:province":"Valais",
    "sg:tags":[
        "hotels",
        "mit",
        "restaurant"
    ],
    "wof:name":"H\u00f4tel Beau-site",
    "wof:placetype":"venue"
},
  "geometry": {"coordinates":[7.0981202126,46.0904846191],"type":"Point"}
}