{
  "type": "Feature",
  "properties": {
    "iso:country":"CH",
    "sg:address":"Route Plaines-du Loup 24 1018 Lausanne Case Postale 164",
    "sg:city":"Lausanne",
    "sg:orig_category":"Vermittlung von Immobilien Verwaltung von Immobilien",
    "sg:phone":"+41 21 647 65 50",
    "sg:postcode":"1018",
    "sg:province":"Vaud",
    "wof:name":"Presidel Sa",
    "wof:placetype":"venue"
},
  "geometry": {"coordinates":[6.6274461746,46.5338821411],"type":"Point"}
}