{
  "type": "Feature",
  "properties": {
    "iso:country":"CH",
    "sg:address":"Dorfstrasse 5",
    "sg:city":"Signau",
    "sg:orig_category":"Landesverteidigung, Sozialversicherung \u00d6ffentliche Verwaltung",
    "sg:phone":"+41 34 495 59 70",
    "sg:postcode":"3534",
    "sg:province":"Bern",
    "wof:name":"Zivilschutzstelle Signau",
    "wof:placetype":"venue"
},
  "geometry": {"coordinates":[7.730591774,46.9240188599],"type":"Point"}
}