{
  "type": "Feature",
  "properties": {
    "iso:country":"CH",
    "sg:address":"Renggerstrasse 56 8038 Z\u00fcrich. Postfach",
    "sg:city":"Z\u00fcrich",
    "sg:orig_category":"Herstellung von Konstruktionsteilen, Fertigbauteilen U Ausbauelementen aus Holz",
    "sg:phone":"+41 71 855 16 62",
    "sg:postcode":"8001",
    "sg:province":"Z\u00fcrich",
    "wof:name":"Grabher R. Hausmontagebautechnik",
    "wof:placetype":"venue"
},
  "geometry": {"coordinates":[9.5679550171,47.465385437],"type":"Point"}
}