{
  "type": "Feature",
  "properties": {
    "iso:country":"CH",
    "sg:address":"Chemin Des Grandes-vignes 10",
    "sg:city":"Founex",
    "sg:classifiers":[
        {
            "category":"Insurance",
            "subcategory":"Insurance Agent",
            "type":"Services"
        }
    ],
    "sg:phone":"+41 22 776 20 84",
    "sg:postcode":"1297",
    "sg:province":"Vaud",
    "sg:tags":[
        "versicherungsagenturen",
        "-broker"
    ],
    "wof:name":"Winterthur-vie Charles Reischmann",
    "wof:placetype":"venue"
},
  "geometry": {"coordinates":[6.199857235,46.3307685852],"type":"Point"}
}