{
  "type": "Feature",
  "properties": {
    "iso:country":"CH",
    "sg:address":"Lettenstrasse 19 8322 Madetswil. Postfach",
    "sg:city":"Madetswil",
    "sg:orig_category":"Elektroinstallation",
    "sg:postcode":"8322",
    "sg:province":"Z\u00fcrich",
    "wof:name":"Wepfer Consulting",
    "wof:placetype":"venue"
},
  "geometry": {"coordinates":[8.7890787125,47.41065979],"type":"Point"}
}