{
  "type": "Feature",
  "properties": {
    "iso:country":"CH",
    "sg:address":"Rathausgasse 4 3011 Bern. Postfach",
    "sg:city":"Bern",
    "sg:orig_category":"Detailhandel mit elektrischen Haushalts-,Radio U Fernsehger\u00e4ten sowie Musikinstrumenten",
    "sg:postcode":"3005",
    "sg:province":"Bern",
    "wof:name":"White Noise, Brock Blagojevic Danielle Musikinstrumente, Musikzubeh\u00f6r; Verkauf",
    "wof:placetype":"venue"
},
  "geometry": {"coordinates":[7.4517378807,46.9486579895],"type":"Point"}
}