{
  "type": "Feature",
  "properties": {
    "iso:country":"CH",
    "sg:address":"Oberriedweg 12",
    "sg:city":"Belp",
    "sg:orig_category":"Arztpraxen",
    "sg:phone":"+41 31 812 06 00",
    "sg:postcode":"3123",
    "sg:province":"Bern",
    "wof:name":"Dres Med. Keller & Wirz Spezial\u00e4rzte Fmh",
    "wof:placetype":"venue"
},
  "geometry": {"coordinates":[7.495995,46.890335],"type":"Point"}
}