{
  "type": "Feature",
  "properties": {
    "iso:country":"CH",
    "sg:address":"Baarermattstrasse 6",
    "sg:city":"Zug",
    "sg:orig_category":"Sprachschulen",
    "sg:phone":"+41 41 760 55 88",
    "sg:postcode":"6300",
    "sg:province":"Zug",
    "wof:name":"Dialogica Zug Sprachschule",
    "wof:placetype":"venue"
},
  "geometry": {"coordinates":[8.5264101028,47.1817588806],"type":"Point"}
}