{
  "type": "Feature",
  "properties": {
    "addr:full":"Avenue De La Gare 11 Ch\u00e2tel-st-denis Fribourg 1618",
    "addr:housenumber":"11",
    "addr:postcode":"1618",
    "addr:street":"Avenue De La Gare",
    "iso:country":"CH",
    "sg:address":"Avenue De La Gare 11",
    "sg:city":"Ch\u00e2tel-st-denis",
    "sg:orig_category":"Blumen U Zierpflanzenbau Gem\u00fcsebau",
    "sg:phone":"+41 26 673 38 78",
    "sg:postcode":"1618",
    "sg:province":"Fribourg",
    "wof:name":"Daniel L\u00fcscher Gartenbau Gmbh",
    "wof:placetype":"venue"
},
  "geometry": {"coordinates":[7.05894,46.946594],"type":"Point"}
}