{
  "type": "Feature",
  "properties": {
    "iso:country":"CH",
    "sg:address":"Route De Suisse 45",
    "sg:city":"Versoix",
    "sg:orig_category":"Detailhandel mit Textilien",
    "sg:phone":"+41 22 755 12 46",
    "sg:postcode":"1290",
    "sg:province":"Gen\u00e8ve",
    "wof:name":"Pelote Laine M.stoeckli & V.olivet",
    "wof:placetype":"venue"
},
  "geometry": {"coordinates":[6.1683168411,46.2780914307],"type":"Point"}
}