{
  "type": "Feature",
  "properties": {
    "iso:country":"CH",
    "sg:address":"7450",
    "sg:city":"Tiefencastel",
    "sg:orig_category":"Unclassifiable Establishments",
    "sg:postcode":"7450",
    "sg:province":"Graubunden",
    "wof:name":"As Aufz\u00fcge Ag",
    "wof:placetype":"venue"
},
  "geometry": {"coordinates":[-86.83531188960001,35.5780715942],"type":"Point"}
}