{
  "type": "Feature",
  "properties": {
    "iso:country":"CH",
    "sg:address":"Naustrasse 65 4242 Laufen. Postfach 540",
    "sg:city":"Laufen",
    "sg:orig_category":"Detailhandel mit Bekleidung Sonstiger Fachdetailhandel in Verkaufsr\u00e4umen",
    "sg:phone":"+41 61 761 30 05",
    "sg:postcode":"4242",
    "sg:province":"Basel-Landschaft",
    "wof:name":"Roger R\u00e9rat B\u00fcchsenmacherei Bekleidung",
    "wof:placetype":"venue"
},
  "geometry": {"coordinates":[7.504206,47.422306],"type":"Point"}
}