{
  "type": "Feature",
  "properties": {
    "iso:country":"CH",
    "sg:address":"Marterey Rue 15 1005 Lausanne. Postfach",
    "sg:city":"Lausanne",
    "sg:orig_category":"Unclassifiable Establishments",
    "sg:postcode":"1006",
    "sg:province":"Vaud",
    "wof:name":"Si Du Ch\u00e2teau D'ouchy",
    "wof:placetype":"venue"
},
  "geometry": {"coordinates":[6.6387619972,46.5209770203],"type":"Point"}
}