{
  "type": "Feature",
  "properties": {
    "iso:country":"CH",
    "sg:address":"Im Moos 9",
    "sg:city":"Flaach",
    "sg:orig_category":"Handelsvermittlung U Grosshandel Technische, physikalische U chemische Untersuchung",
    "sg:phone":"+41 52 318 14 11",
    "sg:postcode":"8416",
    "sg:province":"Z\u00fcrich",
    "wof:name":"Oeko Produkte Schwalm H. U.",
    "wof:placetype":"venue"
},
  "geometry": {"coordinates":[8.602938652,47.5767593384],"type":"Point"}
}