{
  "type": "Feature",
  "properties": {
    "iso:country":"CH",
    "sg:address":"1585",
    "sg:city":"Salavaux",
    "sg:classifiers":[
        {
            "category":"Restaurant",
            "type":"Food & Drink"
        }
    ],
    "sg:phone":"+41 26 677 13 48",
    "sg:postcode":"1585",
    "sg:province":"Vaud",
    "wof:name":"Caf\u00e9 Des Trois-suisses",
    "wof:placetype":"venue"
},
  "geometry": {"coordinates":[7.0223398209,46.9181594849],"type":"Point"}
}