{
  "type": "Feature",
  "properties": {
    "iso:country":"CH",
    "sg:address":"Ueberlandstrasse",
    "sg:city":"Fahrweid",
    "sg:orig_category":"Tankstellen",
    "sg:phone":"+41 17481132",
    "sg:postcode":"8951",
    "sg:province":"Z\u00fcrich",
    "wof:name":"Shell Limmatbr\u00fccke, H.p. Kull",
    "wof:placetype":"venue"
},
  "geometry": {"coordinates":[8.4128446579,47.4059791565],"type":"Point"}
}