{
  "type": "Feature",
  "properties": {
    "iso:country":"CH",
    "sg:address":"Oberdorf 8",
    "sg:city":"Cazis",
    "sg:orig_category":"Herstellung von Elektromotoren, Generatoren U Transformatoren",
    "sg:phone":"+41 81 651 51 00",
    "sg:postcode":"7408",
    "sg:province":"Graubunden",
    "wof:name":"Teletom, Thomas Patt",
    "wof:placetype":"venue"
},
  "geometry": {"coordinates":[9.4291095734,46.7199745178],"type":"Point"}
}