{
  "type": "Feature",
  "properties": {
    "addr:full":"Obergasse 16 Schmerikon St. Gallen 8716",
    "addr:housenumber":"16",
    "addr:postcode":"8716",
    "addr:street":"Obergasse",
    "iso:country":"CH",
    "sg:address":"Obergasse 16",
    "sg:city":"Schmerikon",
    "sg:orig_category":"Bauschreinerei Zimmerei, Dachdeckerei, Bauspenglerei U Abdichtung",
    "sg:phone":"+41 55 282 34 33",
    "sg:postcode":"8716",
    "sg:province":"St. Gallen",
    "wof:name":"Gebr. Wey, Holzbau",
    "wof:placetype":"venue"
},
  "geometry": {"coordinates":[8.946971,47.226749],"type":"Point"}
}