{
  "type": "Feature",
  "properties": {
    "iso:country":"CH",
    "sg:address":"Chemin Des Bossons 3",
    "sg:city":"Lausanne",
    "sg:orig_category":"G\u00fcterbef\u00f6rderung im Strassenverkehr",
    "sg:phone":"+41 21 626 25 61",
    "sg:postcode":"1004",
    "sg:province":"Vaud",
    "wof:name":"Huber Transports",
    "wof:placetype":"venue"
},
  "geometry": {"coordinates":[6.6210188866,46.5357551575],"type":"Point"}
}