{
  "type": "Feature",
  "properties": {
    "iso:country":"CH",
    "sg:address":"Seestrasse 672",
    "sg:city":"Meilen",
    "sg:orig_category":"Unternehmensberatung",
    "sg:phone":"+41 19231988",
    "sg:postcode":"8706",
    "sg:province":"Z\u00fcrich",
    "wof:name":"Estherknaus Ag",
    "wof:placetype":"venue"
},
  "geometry": {"coordinates":[8.6451749802,47.2676467896],"type":"Point"}
}