{
  "type": "Feature",
  "properties": {
    "addr:full":"Via Mastri Ligornettesi Ligornetto Ticino 6853",
    "addr:postcode":"6853",
    "addr:street":"Via Mastri Ligornettesi Ligornetto Ticino",
    "iso:country":"CH",
    "sg:address":"Via Mastri Ligornettesi",
    "sg:city":"Ligornetto",
    "sg:classifiers":[
        {
            "category":"Banks & Credit Unions",
            "subcategory":"Bank",
            "type":"Services"
        }
    ],
    "sg:phone":"+41 91 647 21 41",
    "sg:postcode":"6853",
    "sg:province":"Ticino",
    "wof:name":"Raiffeisen Di Ligornetto",
    "wof:placetype":"venue"
},
  "geometry": {"coordinates":[8.950937,45.862564],"type":"Point"}
}