{
  "type": "Feature",
  "properties": {
    "iso:country":"CH",
    "sg:address":"Gartenstrasse 3",
    "sg:city":"W\u00e4denswil",
    "sg:orig_category":"Bauschreinerei Herstellung von Konstruktionsteilen, Fertigbauteilen U Ausbauelementen aus Holz",
    "sg:phone":"+41 16803707",
    "sg:postcode":"8820",
    "sg:province":"Z\u00fcrich",
    "wof:name":"Br\u00fctsch Roman Schreinerei Gmbh",
    "wof:placetype":"venue"
},
  "geometry": {"coordinates":[8.675732,47.225864],"type":"Point"}
}