{
  "type": "Feature",
  "properties": {
    "iso:country":"CH",
    "sg:address":"2853",
    "sg:city":"Courfaivre",
    "sg:orig_category":"Schulpflegen",
    "sg:phone":"+41 32 426 51 42",
    "sg:postcode":"2853",
    "sg:province":"Jura",
    "wof:name":"Commission Scolaire De L'ecole Primaire",
    "wof:placetype":"venue"
},
  "geometry": {"coordinates":[7.2807021141,47.3344116211],"type":"Point"}
}