{
  "type": "Feature",
  "properties": {
    "iso:country":"CH",
    "sg:address":"Grabenstrasse 8",
    "sg:city":"Schwerzenbach",
    "sg:orig_category":"Herstellung von Schmuck, Gold U Silberschmiedwaren",
    "sg:phone":"+41 18253363",
    "sg:postcode":"8603",
    "sg:province":"Z\u00fcrich",
    "wof:name":"Stiftung Vettori",
    "wof:placetype":"venue"
},
  "geometry": {"coordinates":[8.6591081619,47.3818702698],"type":"Point"}
}