{
  "type": "Feature",
  "properties": {
    "iso:country":"CH",
    "sg:address":"Baslerstrasse 94a",
    "sg:city":"Allschwil",
    "sg:orig_category":"Grosshandel mit B\u00fcromaschinen U einrichtungen Grosshandel mit Datenverarbeitungsger\u00e4ten",
    "sg:phone":"+41 61 481 63 20",
    "sg:postcode":"4123",
    "sg:province":"Basel-Landschaft",
    "wof:name":"Esge B\u00fcrom\u00f6bel Ag",
    "wof:placetype":"venue"
},
  "geometry": {"coordinates":[7.5425400734,47.5528106689],"type":"Point"}
}