{
  "type": "Feature",
  "properties": {
    "iso:country":"CH",
    "sg:address":"Via Girella",
    "sg:city":"Lamone-cadempino",
    "sg:orig_category":"Bauschreinerei Herstellung von Konstruktionsteilen, Fertigbauteilen U Ausbauelementen aus Holz",
    "sg:phone":"+41 81 844 07 41",
    "sg:postcode":"6814",
    "sg:province":"Ticino",
    "wof:name":"Falegnameria La Rasiga Sa",
    "wof:placetype":"venue"
},
  "geometry": {"coordinates":[10.063312,46.310654],"type":"Point"}
}