{
  "type": "Feature",
  "properties": {
    "iso:country":"CH",
    "sg:address":"Etzelstrasse 19",
    "sg:city":"Schaffhausen",
    "sg:orig_category":"Sportvereine Ballsport Tennis",
    "sg:phone":"+41 31 951 50 87",
    "sg:postcode":"8200",
    "sg:province":"Schaffhausen",
    "wof:name":"Tc Bellevue Bern",
    "wof:placetype":"venue"
},
  "geometry": {"coordinates":[7.5244498253,46.9143295288],"type":"Point"}
}