{
  "type": "Feature",
  "properties": {
    "iso:country":"CH",
    "sg:address":"Bergstrasse 19",
    "sg:city":"St\u00e4fa",
    "sg:orig_category":"Herstellung von Oberbekleidung",
    "sg:postcode":"8712",
    "sg:province":"Z\u00fcrich",
    "wof:name":"Boutique Seven, Vural D\u00fclek",
    "wof:placetype":"venue"
},
  "geometry": {"coordinates":[8.7212257385,47.2422866821],"type":"Point"}
}