{
  "type": "Feature",
  "properties": {
    "iso:country":"CH",
    "sg:address":"Im Ifang 16",
    "sg:city":"Effretikon",
    "sg:orig_category":"Versicherungen Hauptagenturen",
    "sg:phone":"+41 61 716 91 91",
    "sg:postcode":"8307",
    "sg:province":"Z\u00fcrich",
    "wof:name":"Z\u00fcrich Versicherungen Hauptagentur",
    "wof:placetype":"venue"
},
  "geometry": {"coordinates":[7.5960898399,47.4893493652],"type":"Point"}
}