{
  "type": "Feature",
  "properties": {
    "iso:country":"CH",
    "sg:address":"B\u00e4derstrasse 28",
    "sg:city":"Baden",
    "sg:orig_category":"RESTAURANTS: TEA-ROOMS",
    "sg:postcode":"5400",
    "sg:province":"Aargau",
    "wof:name":"Ritter Gastro Gmbh",
    "wof:placetype":"venue"
},
  "geometry": {"coordinates":[8.3131513596,47.4801368713],"type":"Point"}
}