{
  "type": "Feature",
  "properties": {
    "iso:country":"CH",
    "sg:address":"Muristrasse 87",
    "sg:city":"Bern",
    "sg:orig_category":"Fotografische Ateliers Fotografisches Gewerbe U fotografische Laboratorien",
    "sg:phone":"+41 31 352 24 44",
    "sg:postcode":"3006",
    "sg:province":"Bern",
    "wof:name":"Guy Jost Atelier F\u00fcr Werbefotografie Ag",
    "wof:placetype":"venue"
},
  "geometry": {"coordinates":[7.470266819,46.9396858215],"type":"Point"}
}