{
  "type": "Feature",
  "properties": {
    "iso:country":"CH",
    "sg:address":"Konstanzerstrasse 10",
    "sg:city":"Kreuzlingen",
    "sg:orig_category":"Softwareentwicklung U beratung",
    "sg:phone":"+41 71 688 94 10",
    "sg:postcode":"8280",
    "sg:province":"Thurgau",
    "wof:name":"Futuretools Lindner",
    "wof:placetype":"venue"
},
  "geometry": {"coordinates":[9.16847229,47.6551628113],"type":"Point"}
}