{
  "type": "Feature",
  "properties": {
    "iso:country":"CH",
    "sg:address":"Juchstrasse 8",
    "sg:city":"W\u00fcrenlos",
    "sg:orig_category":"Detailhandel mit Metallwaren, Anstrichmitteln, Glaswaren, Bau U Heimwerkerbedarf Mechanische Werkst\u00e4",
    "sg:phone":"+41 56 424 04 02",
    "sg:postcode":"5436",
    "sg:province":"Aargau",
    "wof:name":"Ronner Technik Ag",
    "wof:placetype":"venue"
},
  "geometry": {"coordinates":[8.360575676,47.4430580139],"type":"Point"}
}