{
  "type": "Feature",
  "properties": {
    "iso:country":"CH",
    "sg:address":"Bennwilerstrasse",
    "sg:city":"H\u00f6lstein",
    "sg:orig_category":"Mechanische Werkst\u00e4tten",
    "sg:phone":"+41 61 951 20 49",
    "sg:postcode":"4434",
    "sg:province":"Basel-Landschaft",
    "wof:name":"Waltec Gmbh Mechanische Werkst\u00e4tte",
    "wof:placetype":"venue"
},
  "geometry": {"coordinates":[7.7695651054,47.4243049622],"type":"Point"}
}