{
  "type": "Feature",
  "properties": {
    "iso:country":"CH",
    "sg:address":"Avenue Du Delay 6",
    "sg:city":"Morges",
    "sg:orig_category":"Unternehmensberatung",
    "sg:postcode":"1110",
    "sg:province":"Vaud",
    "wof:name":"Concept-image, Didier Sch\u00fctz",
    "wof:placetype":"venue"
},
  "geometry": {"coordinates":[6.488576889,46.5140686035],"type":"Point"}
}