{
  "type": "Feature",
  "properties": {
    "addr:full":"Museumstrasse 10 Sarnen Obwalden 6060",
    "addr:housenumber":"10",
    "addr:postcode":"6060",
    "addr:street":"Museumstrasse",
    "iso:country":"CH",
    "sg:address":"Museumstrasse 10",
    "sg:city":"Sarnen",
    "sg:orig_category":"Blumen U Zierpflanzenbau Detailhandel mit Blumen U Pflanzen",
    "sg:phone":"+41 41 850 11 45",
    "sg:postcode":"6060",
    "sg:province":"Obwalden",
    "wof:name":"Blumen-g\u00f6ssi",
    "wof:placetype":"venue"
},
  "geometry": {"coordinates":[8.442643,47.081451],"type":"Point"}
}