{
  "type": "Feature",
  "properties": {
    "iso:country":"CH",
    "sg:address":"Unterer Graben 35",
    "sg:city":"Winterthur",
    "sg:orig_category":"Technische, physikalische U chemische Untersuchung",
    "sg:postcode":"8400",
    "sg:province":"Z\u00fcrich",
    "wof:name":"Aerzte-laborgenossenschaft Aeskulap",
    "wof:placetype":"venue"
},
  "geometry": {"coordinates":[8.7307395935,47.5001335144],"type":"Point"}
}