{
  "type": "Feature",
  "properties": {
    "iso:country":"CH",
    "sg:address":"Leimenstrasse 46",
    "sg:city":"Basel",
    "sg:orig_category":"Korrespondenz U Nachrichtenb\u00fcros Korrespondenz U Nachrichtenb\u00fcros, selbst\u00e4ndige Journalisten",
    "sg:phone":"+41 71 222 54 11",
    "sg:postcode":"4051",
    "sg:province":"Basel-Stadt",
    "wof:name":"Hornung + Hug, Presseb\u00fcro St. Gallen",
    "wof:placetype":"venue"
},
  "geometry": {"coordinates":[9.3711585999,47.4208221436],"type":"Point"}
}