{
  "type": "Feature",
  "properties": {
    "iso:country":"CH",
    "sg:address":"Au Cr\u00eat 101 2932 Coeuve. Postfach",
    "sg:city":"Coeuve",
    "sg:orig_category":"Sanit\u00e4r, Heizungs U L\u00fcftungsinstallation",
    "sg:postcode":"2932",
    "sg:province":"Jura",
    "wof:name":"Heusler Serge S\u00e0rl Entreprise D'installations Sanitaires, De Chauffage Etc",
    "wof:placetype":"venue"
},
  "geometry": {"coordinates":[7.0998001099,47.448387146],"type":"Point"}
}