{
  "type": "Feature",
  "properties": {
    "iso:country":"CH",
    "sg:address":"Goldhaldenstrasse 32",
    "sg:city":"Zollikon",
    "sg:orig_category":"Fachdetailhandel in Verkaufsr\u00e4umen",
    "sg:postcode":"8702",
    "sg:province":"Z\u00fcrich",
    "wof:name":"Bucher & Glinz",
    "wof:placetype":"venue"
},
  "geometry": {"coordinates":[8.5727043152,47.3351593018],"type":"Point"}
}