{
  "type": "Feature",
  "properties": {
    "iso:country":"CH",
    "sg:address":"Unterm\u00fcli 9",
    "sg:city":"Zug",
    "sg:orig_category":"Vermietung U Verpachtung von eigenen Immobilien",
    "sg:postcode":"6300",
    "sg:province":"Zug",
    "wof:name":"St\u00e9 Coop.immobili\u00e8re Champs Fleuris",
    "wof:placetype":"venue"
},
  "geometry": {"coordinates":[7.0049629211,47.2118835449],"type":"Point"}
}