{
  "type": "Feature",
  "properties": {
    "iso:country":"CH",
    "sg:address":"Rautistr. 58",
    "sg:city":"Z\u00fcrich",
    "sg:classifiers":[
        {
            "category":"Manufacturing",
            "subcategory":"Tools & Machinery",
            "type":"Manufacturing & Wholesale Goods"
        }
    ],
    "sg:phone":"+41 61 717 90 00",
    "sg:postcode":"8048",
    "sg:province":"Z\u00fcrich",
    "sg:tags":[
        "metallurgy",
        "metalworking"
    ],
    "wof:name":"Techno Ag",
    "wof:placetype":"venue"
},
  "geometry": {"coordinates":[7.5999150276,47.4866638184],"type":"Point"}
}