{
  "type": "Feature",
  "properties": {
    "iso:country":"CH",
    "sg:address":"G\u00e4rteli 6 3210 Kerzers. Postfach",
    "sg:city":"Kerzers",
    "sg:orig_category":"Herstellung von nachrichtentechnischen Ger\u00e4ten U Einrichtungen",
    "sg:phone":"+41 31 756 03 20",
    "sg:postcode":"3210",
    "sg:province":"Fribourg",
    "wof:name":"Hamwave K\u00fchne Pirmin Amateurfunkartikel, Elektronik; Vertrieb, Verkauf",
    "wof:placetype":"venue"
},
  "geometry": {"coordinates":[7.2029900551,46.9745521545],"type":"Point"}
}