{
  "type": "Feature",
  "properties": {
    "iso:country":"CH",
    "sg:address":"Rue Pierre-aeby 10 1700 Fribourg. Postfach",
    "sg:city":"Fribourg",
    "sg:orig_category":"Grosshandel mit Holz U Baustoffen",
    "sg:postcode":"1702",
    "sg:province":"Fribourg",
    "wof:name":"Camberway Limited, A Londres (uk), Succursale De Fribourg Mat\u00e9riel De Chantier; Location",
    "wof:placetype":"venue"
},
  "geometry": {"coordinates":[7.1600670815,46.8076248169],"type":"Point"}
}