{
  "type": "Feature",
  "properties": {
    "addr:full":"1727 Magnedens Fribourg 1727",
    "addr:housenumber":"1727",
    "addr:postcode":"1727",
    "addr:street":"Magnedens Fribourg",
    "iso:country":"CH",
    "sg:address":"1727",
    "sg:city":"Magnedens",
    "sg:orig_category":"Detailhandel mit Brot, Back U S\u00fcsswaren",
    "sg:phone":"+41 26 411 12 41",
    "sg:postcode":"1727",
    "sg:province":"Fribourg",
    "wof:name":"Monney, G\u00e9rard",
    "wof:placetype":"venue"
},
  "geometry": {"coordinates":[7.08129,46.74197],"type":"Point"}
}