{
  "type": "Feature",
  "properties": {
    "iso:country":"CH",
    "sg:address":"1313",
    "sg:city":"Ferreyres",
    "sg:orig_category":"RESTAURANTS: TEA-ROOMS",
    "sg:phone":"+41 21 866 14 03",
    "sg:postcode":"1313",
    "sg:province":"Vaud",
    "wof:name":"Yolal Ali Ulvi",
    "wof:placetype":"venue"
},
  "geometry": {"coordinates":[6.4825901985,46.6598892212],"type":"Point"}
}