{
  "type": "Feature",
  "properties": {
    "iso:country":"CH",
    "sg:address":"Bachhofstrasse 7",
    "sg:city":"Sins",
    "sg:orig_category":"Detailhandel mit M\u00f6beln U Haushaltsgegenst\u00e4nden",
    "sg:phone":"+41 41 787 04 73",
    "sg:postcode":"5643",
    "sg:province":"Aargau",
    "wof:name":"Standpunkt Wohnen",
    "wof:placetype":"venue"
},
  "geometry": {"coordinates":[8.3962402344,47.188243866],"type":"Point"}
}