{
  "type": "Feature",
  "properties": {
    "iso:country":"CH",
    "sg:address":"Oberdorfstrasse 12",
    "sg:city":"Staufen",
    "sg:orig_category":"Vereine Diverse",
    "sg:phone":"+41 62 891 73 78",
    "sg:postcode":"5603",
    "sg:province":"Aargau",
    "wof:name":"Inside-club 91",
    "wof:placetype":"venue"
},
  "geometry": {"coordinates":[8.1655788422,47.3813934326],"type":"Point"}
}