{
  "type": "Feature",
  "properties": {
    "iso:country":"CH",
    "sg:address":"1837",
    "sg:city":"Ch\u00e2teau-d'oex",
    "sg:orig_category":"Verwaltung der Rechtspflege, Gerichte",
    "sg:phone":"+41 21 845 56 08",
    "sg:postcode":"1837",
    "wof:name":"Registre Foncier",
    "wof:placetype":"venue"
},
  "geometry": {"coordinates":[6.2309331894,46.6074676514],"type":"Point"}
}