{
  "type": "Feature",
  "properties": {
    "iso:country":"CH",
    "sg:address":"Grabackerstrasse 268",
    "sg:city":"Horriwil",
    "sg:orig_category":"Allgemeiner Hoch U Tiefbau",
    "sg:postcode":"4557",
    "sg:province":"Solothurn",
    "wof:name":"Pippo Bau, Giuseppe Verciglio",
    "wof:placetype":"venue"
},
  "geometry": {"coordinates":[7.6248,47.184719],"type":"Point"}
}