{
  "type": "Feature",
  "properties": {
    "iso:country":"CH",
    "sg:address":"Dorfplatz 108",
    "sg:city":"G\u00fcnsberg",
    "sg:orig_category":"Darlehenskassen U Raiffeisenbanken",
    "sg:phone":"+41 32 637 11 73",
    "sg:postcode":"4524",
    "sg:province":"Solothurn",
    "wof:name":"Raiffeisenbank",
    "wof:placetype":"venue"
},
  "geometry": {"coordinates":[7.576445,47.257469],"type":"Point"}
}