{
  "type": "Feature",
  "properties": {
    "iso:country":"CH",
    "sg:address":"Rue De La Raffinerie 4",
    "sg:city":"Neuenburg",
    "sg:orig_category":"Druckweiterverarbeitung",
    "sg:phone":"+41 32 725 19 43",
    "sg:postcode":"2000",
    "sg:province":"Neuch\u00e2tel",
    "wof:name":"Reliure-brochage-encadrement Richard C.",
    "wof:placetype":"venue"
},
  "geometry": {"coordinates":[6.9286999702,46.9930915833],"type":"Point"}
}