{
  "type": "Feature",
  "properties": {
    "iso:country":"CH",
    "sg:address":"Riedgrabenstrasse 5 8153 R\u00fcmlang. Postfach 288",
    "sg:city":"R\u00fcmlang",
    "sg:orig_category":"Herstellung von Wellpapier U pappe sowie von Verpackungsmitteln aus Papier, Karton U Pappe",
    "sg:phone":"+41 18172364",
    "sg:postcode":"8153",
    "sg:province":"Z\u00fcrich",
    "wof:name":"Dinkel Cartonagen Ag",
    "wof:placetype":"venue"
},
  "geometry": {"coordinates":[8.5199279785,47.4612541199],"type":"Point"}
}