{
  "type": "Feature",
  "properties": {
    "iso:country":"CH",
    "sg:address":"Hadlaubstrasse 56",
    "sg:city":"Z\u00fcrich",
    "sg:orig_category":"Fachdetailhandel in Verkaufsr\u00e4umen",
    "sg:postcode":"8006",
    "sg:province":"Z\u00fcrich",
    "wof:name":"Albert B\u00fchler, Insider Snowboard Shop",
    "wof:placetype":"venue"
},
  "geometry": {"coordinates":[8.6900548935,47.3005561829],"type":"Point"}
}