{
  "type": "Feature",
  "properties": {
    "addr:full":"Faubourg Du Lac 39 Neuch\u00e2tel Neuch\u00e2tel 2000",
    "addr:housenumber":"39",
    "addr:postcode":"2000",
    "addr:street":"Faubourg Du Lac",
    "iso:country":"CH",
    "sg:address":"Faubourg Du Lac 39",
    "sg:city":"Neuch\u00e2tel",
    "sg:orig_category":"Autoelektro and -elektronik Werkst\u00e4tten Autogaragen",
    "sg:phone":"+41 32 724 09 00",
    "sg:postcode":"2000",
    "sg:province":"Neuch\u00e2tel",
    "wof:name":"Jean-pierre Besson Sa Garage De La Rotonde",
    "wof:placetype":"venue"
},
  "geometry": {"coordinates":[6.936337,46.994289],"type":"Point"}
}