{
  "type": "Feature",
  "properties": {
    "iso:country":"CH",
    "sg:address":"Lustm\u00fchle 9062 Lustm\u00fchle. Postfach 50",
    "sg:city":"Lustm\u00fchle",
    "sg:orig_category":"Instandhaltung U Reparatur von Automobilen",
    "sg:phone":"+41 71 333 12 93",
    "sg:postcode":"9062",
    "sg:province":"Appenzell Ausserrhoden",
    "wof:name":"Garage Lustm\u00fchle Ag",
    "wof:placetype":"venue"
},
  "geometry": {"coordinates":[9.3531703949,47.3964309692],"type":"Point"}
}