{
  "type": "Feature",
  "properties": {
    "iso:country":"CH",
    "sg:address":"Kaiserhofstrasse 12",
    "sg:city":"Eglisau",
    "sg:orig_category":"Erschliessung von Grundst\u00fccken",
    "sg:phone":"+41 18672117",
    "sg:postcode":"8193",
    "sg:province":"Z\u00fcrich",
    "wof:name":"Wohnbaugenossenschaft Kaiserhof Eglisau",
    "wof:placetype":"venue"
},
  "geometry": {"coordinates":[8.5265760422,47.5727653503],"type":"Point"}
}