{
  "type": "Feature",
  "properties": {
    "iso:country":"CH",
    "sg:address":"St. Niklausstrasse 1",
    "sg:city":"Solothurn",
    "sg:orig_category":"Unclassifiable Establishments",
    "sg:phone":"+41 32 624 12 24",
    "sg:postcode":"4500",
    "sg:province":"Solothurn",
    "wof:name":"Sphinx Corporation Ag",
    "wof:placetype":"venue"
},
  "geometry": {"coordinates":[7.5393118858,47.2114906311],"type":"Point"}
}