{
  "type": "Feature",
  "properties": {
    "iso:country":"CH",
    "sg:address":"Mittlerer Kreis 45",
    "sg:city":"Therwil",
    "sg:orig_category":"RESTAURANTS: TEA-ROOMS",
    "sg:phone":"+41 61 721 54 54",
    "sg:postcode":"4106",
    "sg:province":"Basel-Landschaft",
    "wof:name":"Restaurant Sternen, Guber Anton",
    "wof:placetype":"venue"
},
  "geometry": {"coordinates":[7.5513319969,47.4987030029],"type":"Point"}
}