{
  "type": "Feature",
  "properties": {
    "iso:country":"CH",
    "sg:address":"Zweierstrasse 167",
    "sg:city":"Z\u00fcrich",
    "sg:orig_category":"Grosshandel mit Geschenkartikeln U Souvenirs",
    "sg:phone":"+41 14516062",
    "sg:postcode":"8003",
    "sg:province":"Z\u00fcrich",
    "wof:name":"Pek-prom-redic Geschenkartikel",
    "wof:placetype":"venue"
},
  "geometry": {"coordinates":[8.5183496475,47.3699951172],"type":"Point"}
}