{
  "type": "Feature",
  "properties": {
    "iso:country":"CH",
    "sg:address":"Bergstrasse 120",
    "sg:city":"M\u00e4nnedorf",
    "sg:orig_category":"Bildung and Forschung, Institute",
    "sg:postcode":"8708",
    "sg:province":"Z\u00fcrich",
    "wof:name":"Kjpd Kinderstation Br\u00fcschhalde",
    "wof:placetype":"venue"
},
  "geometry": {"coordinates":[8.70158,47.25338],"type":"Point"}
}