{
  "type": "Feature",
  "properties": {
    "iso:country":"CH",
    "sg:address":"Brandstrasse 32",
    "sg:city":"Uster",
    "sg:orig_category":"RESTAURANTS: TEA-ROOMS",
    "sg:phone":"+41 56 621 34 43",
    "sg:postcode":"8610",
    "sg:province":"Z\u00fcrich",
    "wof:name":"Restaurant Nord Katalin Szanto",
    "wof:placetype":"venue"
},
  "geometry": {"coordinates":[8.2671537399,47.3544540405],"type":"Point"}
}