{
  "type": "Feature",
  "properties": {
    "iso:country":"CH",
    "sg:address":"3367",
    "sg:city":"Th\u00f6rigen",
    "sg:orig_category":"Pensionskassen",
    "sg:postcode":"3367",
    "sg:province":"Bern",
    "wof:name":"Personalf\u00fcrsorgestiftung Der Federnfabrik Schmid Ag Oetwil Am See",
    "wof:placetype":"venue"
},
  "geometry": {"coordinates":[8.7181177139,47.2699928284],"type":"Point"}
}