{
  "type": "Feature",
  "properties": {
    "addr:full":"Via B. Fontana Chiasso Ticino 6830",
    "addr:postcode":"6830",
    "addr:street":"Via B. Fontana;Ticino",
    "iso:country":"CH",
    "sg:address":"Via B. Fontana",
    "sg:city":"Chiasso",
    "sg:classifiers":[
        {
            "category":"Airport",
            "type":"Transportation"
        }
    ],
    "sg:phone":"+41 91 683 92 02",
    "sg:postcode":"6830",
    "sg:province":"Ticino",
    "sg:tags":[
        "air-freight",
        "forwarders"
    ],
    "wof:name":"Benasso-lavarello Sa",
    "wof:placetype":"venue"
},
  "geometry": {"coordinates":[9.023175,45.837029],"type":"Point"}
}