{
  "type": "Feature",
  "properties": {
    "iso:country":"CH",
    "sg:address":"Breiteweg 36",
    "sg:city":"Ostermundigen",
    "sg:classifiers":[
        {
            "category":"Communications",
            "subcategory":"Film & Video Production",
            "type":"Services"
        }
    ],
    "sg:phone":"+41 31 931 11 22",
    "sg:postcode":"3072",
    "sg:province":"Bern",
    "sg:tags":[
        "videofilmherstellung",
        "u"
    ],
    "wof:name":"Probst Film Tricktechnik Gmbh Dokumentar-& Werbefilm",
    "wof:placetype":"venue"
},
  "geometry": {"coordinates":[7.4805641174,46.9565467834],"type":"Point"}
}