{
  "type": "Feature",
  "properties": {
    "iso:country":"CH",
    "sg:address":"Grand-rue 86",
    "sg:city":"Cornol",
    "sg:orig_category":"Detailhandel mit Fahrr\u00e4dern",
    "sg:phone":"+41 32 462 22 37",
    "sg:postcode":"2952",
    "sg:province":"Jura",
    "wof:name":"Andr\u00e9 Jacquemin Cycles",
    "wof:placetype":"venue"
},
  "geometry": {"coordinates":[7.1613950729,47.407371521],"type":"Point"}
}