{
  "type": "Feature",
  "properties": {
    "addr:full":"Nebenmattstrasse 7 Bennwil Basel-Landschaft 4431",
    "addr:housenumber":"7",
    "addr:postcode":"4431",
    "addr:street":"Nebenmattstrasse",
    "iso:country":"CH",
    "sg:address":"Nebenmattstrasse 7",
    "sg:city":"Bennwil",
    "sg:orig_category":"Architektur U Ingenieurb\u00fcros Architekturb\u00fcros",
    "sg:phone":"+41 61 953 00 55",
    "sg:postcode":"4431",
    "sg:province":"Basel-Landschaft",
    "wof:name":"M\u00fcller + M\u00fcller Architektur Und Immobilien Gmbh",
    "wof:placetype":"venue"
},
  "geometry": {"coordinates":[7.782816,47.406277],"type":"Point"}
}