{
  "type": "Feature",
  "properties": {
    "iso:country":"CH",
    "sg:address":"Z\u00e4hringerstrasse 13",
    "sg:city":"Z\u00fcrich",
    "sg:orig_category":"Public-Relations-Agenturen",
    "sg:phone":"+41 12627390",
    "sg:postcode":"8001",
    "sg:province":"Z\u00fcrich",
    "wof:name":"J\u00fcrg Wehrli Prospec Consulting",
    "wof:placetype":"venue"
},
  "geometry": {"coordinates":[8.5445814133,47.3745079041],"type":"Point"}
}