{
  "type": "Feature",
  "properties": {
    "iso:country":"CH",
    "sg:address":"Weidstrasse 28",
    "sg:city":"Heiden",
    "sg:orig_category":"Sportvereine Turnen",
    "sg:phone":"+41 71 891 39 59",
    "sg:postcode":"9410",
    "sg:province":"Appenzell Ausserrhoden",
    "wof:name":"Turnverein Heiden",
    "wof:placetype":"venue"
},
  "geometry": {"coordinates":[9.5266494751,47.4445648193],"type":"Point"}
}