{
  "type": "Feature",
  "properties": {
    "iso:country":"CH",
    "sg:address":"6850 Mendrisio. Postfach",
    "sg:city":"Mendrisio",
    "sg:orig_category":"Interessenvertretungen",
    "sg:postcode":"6850",
    "sg:province":"Ticino",
    "wof:name":"Fondazione Bernasconi Don Giorgio",
    "wof:placetype":"venue"
},
  "geometry": {"coordinates":[8.9789495468,45.876991272],"type":"Point"}
}