{
  "type": "Feature",
  "properties": {
    "iso:country":"CH",
    "sg:address":"Bleicherweg 58",
    "sg:city":"Z\u00fcrich",
    "sg:orig_category":"Non-Classified Establishments",
    "sg:postcode":"8002",
    "sg:province":"Z\u00fcrich",
    "wof:name":"Frincana Ag",
    "wof:placetype":"venue"
},
  "geometry": {"coordinates":[8.533662796,47.3672180176],"type":"Point"}
}