{
  "type": "Feature",
  "properties": {
    "iso:country":"CH",
    "sg:address":"Chemin Du Vieux-moulin 61b",
    "sg:city":"Chavornay",
    "sg:orig_category":"Dienstleistungen von Beteiligungsgesellschaften",
    "sg:phone":"+41 24 441 86 68",
    "sg:postcode":"1373",
    "sg:province":"Vaud",
    "wof:name":"O.k. Bureau, Bujard Nadine",
    "wof:placetype":"venue"
},
  "geometry": {"coordinates":[6.5722990036,46.6973152161],"type":"Point"}
}