{
  "type": "Feature",
  "properties": {
    "iso:country":"CH",
    "sg:address":"6598",
    "sg:city":"Tenero",
    "sg:orig_category":"Landwirtschaft, Jagd U damit verbundene Dienstleistungen",
    "sg:phone":"+41 61 751 43 60",
    "sg:postcode":"6598",
    "sg:province":"Ticino",
    "wof:name":"Veronica Koellreuter Gutsbetrieb",
    "wof:placetype":"venue"
},
  "geometry": {"coordinates":[7.5904078484,47.4678878784],"type":"Point"}
}