{
  "type": "Feature",
  "properties": {
    "iso:country":"CH",
    "sg:address":"Kastanienweg 2",
    "sg:city":"B\u00e4tterkinden",
    "sg:orig_category":"Offsetdruck",
    "sg:phone":"+41 32 665 10 78",
    "sg:postcode":"3315",
    "sg:province":"Bern",
    "wof:name":"Niffenegger Druckerei Und Kopie Kopiergesch\u00e4ft",
    "wof:placetype":"venue"
},
  "geometry": {"coordinates":[7.5375299454,47.1304512024],"type":"Point"}
}