{
  "type": "Feature",
  "properties": {
    "iso:country":"CH",
    "sg:address":"Krankenhausstrasse 8",
    "sg:city":"Oberdiessbach",
    "sg:orig_category":"Kaminfeger",
    "sg:phone":"+41 31 771 13 32",
    "sg:postcode":"3672",
    "sg:province":"Bern",
    "wof:name":"Fritz Joost Kreiskaminfegermeister",
    "wof:placetype":"venue"
},
  "geometry": {"coordinates":[7.6211590767,46.8384361267],"type":"Point"}
}