{
  "type": "Feature",
  "properties": {
    "iso:country":"CH",
    "sg:address":"Feldstrasse 6",
    "sg:city":"Aarburg",
    "sg:orig_category":"Zahnarztpraxen",
    "sg:phone":"+41 19302384",
    "sg:postcode":"4663",
    "sg:province":"Aargau",
    "wof:name":"Dres Kleisner & Schlumpf Zahn\u00e4rzte",
    "wof:placetype":"venue"
},
  "geometry": {"coordinates":[8.791975975,47.3201942444],"type":"Point"}
}