{
  "type": "Feature",
  "properties": {
    "iso:country":"CH",
    "sg:address":"Chemin De L'ancien-peage 11",
    "sg:city":"Versoix",
    "sg:orig_category":"Instandhaltung U Reparatur von Automobilen",
    "sg:phone":"+41 22 755 53 36",
    "sg:postcode":"1290",
    "sg:province":"Gen\u00e8ve",
    "wof:name":"Piguet Yves",
    "wof:placetype":"venue"
},
  "geometry": {"coordinates":[6.1675620079,46.2760009766],"type":"Point"}
}