{
  "type": "Feature",
  "properties": {
    "iso:country":"CH",
    "sg:address":"Lausanne Rue De 29 1201 Gen\u00e8ve. Postfach",
    "sg:city":"Gen\u00e8ve",
    "sg:orig_category":"Verwertung von Milch",
    "sg:phone":"+41 21 841 11 40",
    "sg:postcode":"1201",
    "sg:province":"Gen\u00e8ve",
    "wof:name":"Charles Et Patrick Hauser Sa",
    "wof:placetype":"venue"
},
  "geometry": {"coordinates":[6.282310009,46.6478347778],"type":"Point"}
}