{
  "type": "Feature",
  "properties": {
    "iso:country":"CH",
    "sg:address":"Forchstrasse 256",
    "sg:city":"Herrliberg",
    "sg:orig_category":"Gartenbau",
    "sg:phone":"+41 19154309",
    "sg:postcode":"8704",
    "sg:province":"Z\u00fcrich",
    "wof:name":"H. Nydegger Rosenkulturen",
    "wof:placetype":"venue"
},
  "geometry": {"coordinates":[8.6309232712,47.2880706787],"type":"Point"}
}