{
  "type": "Feature",
  "properties": {
    "iso:country":"CH",
    "sg:address":"1973 Mayens-de-nax Case Postale 7",
    "sg:city":"Mayens-de-nax",
    "sg:orig_category":"Sportvereine Ski",
    "sg:phone":"+41 27 203 11 33",
    "sg:postcode":"1973",
    "sg:province":"Valais",
    "wof:name":"Ski-club Mont-nobles Nax",
    "wof:placetype":"venue"
},
  "geometry": {"coordinates":[7.4505801201,46.2280006409],"type":"Point"}
}