{
  "type": "Feature",
  "properties": {
    "iso:country":"CH",
    "sg:address":"2608",
    "sg:city":"Courtelary",
    "sg:orig_category":"Herstellung von Ger\u00e4ten der Elektrizit\u00e4tserzeugung, -verteilung u.\u00e4. -Herstellung von elektronischen",
    "sg:phone":"+41 32 494 60 60",
    "sg:postcode":"2608",
    "sg:province":"Bern",
    "wof:name":"Vn Sa",
    "wof:placetype":"venue"
},
  "geometry": {"coordinates":[7.382581234,47.2798233032],"type":"Point"}
}