{
  "type": "Feature",
  "properties": {
    "iso:country":"CH",
    "sg:address":"Mellingerstrasse 10",
    "sg:city":"Niederrohrdorf",
    "sg:orig_category":"Detailhandel mit elektrischen Haushalts-,Radio U Fernsehger\u00e4ten sowie Musikinstrumenten",
    "sg:phone":"+41 17223005",
    "sg:postcode":"5443",
    "sg:province":"Aargau",
    "wof:name":"Swiss Fine Goods Ag",
    "wof:placetype":"venue"
},
  "geometry": {"coordinates":[8.3016490936,47.4247932434],"type":"Point"}
}