{
  "type": "Feature",
  "properties": {
    "iso:country":"CH",
    "sg:address":"Schlossstrasse 32",
    "sg:city":"Boll",
    "sg:orig_category":"Architektur U Ingenieurb\u00fcros",
    "sg:phone":"+41 31 839 00 70",
    "sg:postcode":"3067",
    "sg:province":"Bern",
    "wof:name":"Ingenieurb\u00fcro Brinkmnn R.",
    "wof:placetype":"venue"
},
  "geometry": {"coordinates":[7.544156,46.956337],"type":"Point"}
}