{
  "type": "Feature",
  "properties": {
    "iso:country":"CH",
    "sg:address":"Via Cittadella 3/5",
    "sg:city":"Locarno",
    "sg:orig_category":"Reiseb\u00fcros U Reiseveranstalter",
    "sg:phone":"+41 91 752 22 05",
    "sg:postcode":"6600",
    "sg:province":"Ticino",
    "wof:name":"Vola E V\u00e0 Di Testini Fabrizia",
    "wof:placetype":"venue"
},
  "geometry": {"coordinates":[8.7945222855,46.170337677],"type":"Point"}
}