{
  "type": "Feature",
  "properties": {
    "iso:country":"CH",
    "sg:address":"Via D'alberti 1",
    "sg:city":"Chiasso",
    "sg:orig_category":"Druck ohne Zeitungsdruck Offsetdruck",
    "sg:phone":"+41 91 690 12 85",
    "sg:postcode":"6830",
    "sg:province":"Ticino",
    "wof:name":"Progetto Stampa 2000 Sa",
    "wof:placetype":"venue"
},
  "geometry": {"coordinates":[9.0209560394,45.833770752],"type":"Point"}
}