{
  "type": "Feature",
  "properties": {
    "iso:country":"CH",
    "sg:address":"Hohlstrasse 165",
    "sg:city":"Z\u00fcrich",
    "sg:orig_category":"Non-Classified Establishments",
    "sg:postcode":"8004",
    "sg:province":"Z\u00fcrich",
    "wof:name":"Kiosk Novo Schreier G.",
    "wof:placetype":"venue"
},
  "geometry": {"coordinates":[8.5192842484,47.380355835],"type":"Point"}
}