{
  "type": "Feature",
  "properties": {
    "iso:country":"CH",
    "sg:address":"3257",
    "sg:city":"Grossaffoltern",
    "sg:orig_category":"Sportvereine Sch\u00fctzen",
    "sg:phone":"+41 55 412 82 18",
    "sg:postcode":"3257",
    "sg:province":"Bern",
    "wof:name":"Feldsch\u00fctzengesellschaft",
    "wof:placetype":"venue"
},
  "geometry": {"coordinates":[7.3613591194,47.0663986206],"type":"Point"}
}