{
  "type": "Feature",
  "properties": {
    "addr:full":"Piazza Stazione Mendrisio Ticino 6850",
    "addr:postcode":"6850",
    "addr:street":"Piazza Stazione",
    "iso:country":"CH",
    "sg:address":"Piazza Stazione",
    "sg:city":"Mendrisio",
    "sg:orig_category":"Detailhandel mit Brillen U anderen Sehhilfen Fachdetailhandel in Verkaufsr\u00e4umen",
    "sg:phone":"+41 91 646 78 38",
    "sg:postcode":"6850",
    "sg:province":"Ticino",
    "wof:name":"Real Watch Ottica Squizzato Sa",
    "wof:placetype":"venue"
},
  "geometry": {"coordinates":[8.978745,45.868832],"type":"Point"}
}