{
  "type": "Feature",
  "properties": {
    "iso:country":"CH",
    "sg:address":"Bahnhofplatz 1",
    "sg:city":"Biel/bienne",
    "sg:orig_category":"Vermietung von Automobilen",
    "sg:phone":"+41 81 416 57 90",
    "sg:postcode":"2502",
    "sg:province":"Bern",
    "wof:name":"Hertz Ag",
    "wof:placetype":"venue"
},
  "geometry": {"coordinates":[9.8425140381,46.801525116],"type":"Point"}
}