{
  "type": "Feature",
  "properties": {
    "iso:country":"CH",
    "sg:address":"Boveresses Avenue Des 29",
    "sg:city":"Lausanne",
    "sg:orig_category":"Non-Classified Establishments",
    "sg:postcode":"1010",
    "sg:province":"Vaud",
    "wof:name":"Caf\u00e9-restaurant Des Boveresses, Z. Stanic",
    "wof:placetype":"venue"
},
  "geometry": {"coordinates":[6.66583395,46.5372505188],"type":"Point"}
}