{
  "type": "Feature",
  "properties": {
    "iso:country":"CH",
    "sg:address":"Kirchmoosh\u00f6he 4",
    "sg:city":"Zofingen",
    "sg:orig_category":"Vermittlung von Immobilien Verwaltung von Immobilien",
    "sg:phone":"+41 71 913 70 70",
    "sg:postcode":"4800",
    "sg:province":"Aargau",
    "wof:name":"Horath Treuhand Ag",
    "wof:placetype":"venue"
},
  "geometry": {"coordinates":[9.0466156006,47.4639701843],"type":"Point"}
}