{
  "type": "Feature",
  "properties": {
    "iso:country":"CH",
    "sg:address":"Dorfstrasse 89",
    "sg:city":"Bolligen",
    "sg:orig_category":"Herstellung von Konstruktionsteilen, Fertigbauteilen U Ausbauelementen aus Holz",
    "sg:phone":"+41 31 921 61 43",
    "sg:postcode":"3065",
    "sg:province":"Bern",
    "wof:name":"Schreinerei Graf",
    "wof:placetype":"venue"
},
  "geometry": {"coordinates":[7.5033202171,46.984539032],"type":"Point"}
}