{
  "type": "Feature",
  "properties": {
    "iso:country":"CH",
    "sg:address":"Riedstrasse 1",
    "sg:city":"Rotkreuz",
    "sg:orig_category":"Datenverarbeitungsdienste Informatikdienste",
    "sg:phone":"+41 19327555",
    "sg:postcode":"6343",
    "sg:province":"Zug",
    "wof:name":"Onebyte Gmbh E-buiness Und Webdesign",
    "wof:placetype":"venue"
},
  "geometry": {"coordinates":[8.78526,47.325821],"type":"Point"}
}