{
  "type": "Feature",
  "properties": {
    "iso:country":"CH",
    "sg:address":"Avenue Viollier 14",
    "sg:city":"Nyon",
    "sg:orig_category":"Instandhaltung U Reparatur von Automobilen",
    "sg:phone":"+41 22 361 32 17",
    "sg:postcode":"1260",
    "sg:province":"Vaud",
    "wof:name":"Garage De La R\u00fbche, R. Pinel",
    "wof:placetype":"venue"
},
  "geometry": {"coordinates":[6.2374849319,46.3840713501],"type":"Point"}
}