{
  "type": "Feature",
  "properties": {
    "iso:country":"CH",
    "sg:address":"Chemin De Mongevon 11",
    "sg:city":"Crissier",
    "sg:classifiers":[
        {
            "category":"Utilities",
            "subcategory":"Recycling",
            "type":"Services"
        }
    ],
    "sg:phone":"+41 21 637 66 66",
    "sg:postcode":"1023",
    "sg:province":"Vaud",
    "sg:tags":[
        "paper",
        "waste"
    ],
    "wof:name":"Retripa, Crissier Sa",
    "wof:placetype":"venue"
},
  "geometry": {"coordinates":[6.573431015,46.5482177734],"type":"Point"}
}