{
  "type": "Feature",
  "properties": {
    "iso:country":"CH",
    "sg:address":"Schleusenweg 20",
    "sg:city":"Nidau",
    "sg:orig_category":"Allgemeiner Hoch U Tiefbau Hoch U Tiefbau",
    "sg:phone":"+41 71 245 11 33",
    "sg:postcode":"2560",
    "sg:province":"Bern",
    "wof:name":"Gallus-bau Ag",
    "wof:placetype":"venue"
},
  "geometry": {"coordinates":[9.377725,47.437969],"type":"Point"}
}