{
  "type": "Feature",
  "properties": {
    "iso:country":"CH",
    "sg:address":"3800 Interlaken. Postfach 412",
    "sg:city":"Interlaken",
    "sg:orig_category":"Sonstige mit Sport verbundene T\u00e4tigkeiten",
    "sg:phone":"+41 33 826 77 17",
    "sg:postcode":"3800",
    "sg:province":"Bern",
    "wof:name":"Scenic Air Ag",
    "wof:placetype":"venue"
},
  "geometry": {"coordinates":[7.8534369469,46.6844787598],"type":"Point"}
}