{
  "type": "Feature",
  "properties": {
    "iso:country":"CH",
    "sg:address":"Au Village 25 1776 Montagny-la-ville. Postfach",
    "sg:city":"Montagny-la-ville",
    "sg:orig_category":"Elektroinstallation",
    "sg:phone":"+41 26 660 52 00",
    "sg:postcode":"1776",
    "sg:province":"Fribourg",
    "wof:name":"B.j. Electricit\u00e9, Joye Bernard Installations \u00e9lectriques",
    "wof:placetype":"venue"
},
  "geometry": {"coordinates":[6.993999958,46.8166313171],"type":"Point"}
}