{
  "type": "Feature",
  "properties": {
    "addr:full":"Z\u00fcrcherstrasse 14 Weiningen Z\u00fcrich 8104",
    "addr:housenumber":"14",
    "addr:postcode":"8104",
    "addr:street":"Zuercherstrasse",
    "iso:country":"CH",
    "sg:address":"Z\u00fcrcherstrasse 14",
    "sg:city":"Weiningen",
    "sg:orig_category":"Assembling, Disassembling",
    "sg:phone":"+41 17502040",
    "sg:postcode":"8104",
    "sg:province":"Z\u00fcrich",
    "wof:name":"Uto Tresor- Und Kassenbau",
    "wof:placetype":"venue"
},
  "geometry": {"coordinates":[8.435876,47.418835],"type":"Point"}
}