{
  "type": "Feature",
  "properties": {
    "iso:country":"CH",
    "sg:address":"Freiestrasse 150",
    "sg:city":"Z\u00fcrich",
    "sg:orig_category":"Architekturb\u00fcros",
    "sg:phone":"+41 14227778",
    "sg:postcode":"8032",
    "sg:province":"Z\u00fcrich",
    "wof:name":"Alfred B\u00e4r Architekturb\u00fcro",
    "wof:placetype":"venue"
},
  "geometry": {"coordinates":[8.562123,47.363586],"type":"Point"}
}