{
  "type": "Feature",
  "properties": {
    "iso:country":"CH",
    "sg:address":"Kreuzstrasse 19",
    "sg:city":"Niederg\u00f6sgen",
    "sg:orig_category":"Grosshandel mit sonstigen Nahrungsmitteln",
    "sg:postcode":"5013",
    "sg:province":"Solothurn",
    "wof:name":"Tiefk\u00fchlservice H\u00e4nni Ferdinand",
    "wof:placetype":"venue"
},
  "geometry": {"coordinates":[7.9882531166,47.3726768494],"type":"Point"}
}