{
  "type": "Feature",
  "properties": {
    "iso:country":"CH",
    "sg:address":"Z\u00fcrichstrasse 19",
    "sg:city":"Biel/bienne",
    "sg:orig_category":"Herstellung von Platten, Folien, Schl\u00e4uchen U Profilen aus Kunststoff",
    "sg:phone":"+41 32 323 86 23",
    "sg:postcode":"2500",
    "sg:province":"Bern",
    "wof:name":"Optisa Ag",
    "wof:placetype":"venue"
},
  "geometry": {"coordinates":[7.2911930084,47.1615562439],"type":"Point"}
}