{
  "type": "Feature",
  "properties": {
    "iso:country":"CH",
    "sg:address":"Route Des Daillettes 21 1700 Fribourg Case Postale 323",
    "sg:city":"Fribourg",
    "sg:orig_category":"Allgemeiner Hoch U Tiefbau Allgemeiner Hochbau",
    "sg:phone":"+41 26 425 83 33",
    "sg:postcode":"1709",
    "sg:province":"Fribourg",
    "wof:name":"Tacchini S.a.",
    "wof:placetype":"venue"
},
  "geometry": {"coordinates":[7.146269,46.792519],"type":"Point"}
}