{
  "type": "Feature",
  "properties": {
    "iso:country":"CH",
    "sg:address":"Via S. Balestra 6",
    "sg:city":"Chiasso",
    "sg:orig_category":"Finanzierungsinstitutionen",
    "sg:postcode":"6830",
    "sg:province":"Ticino",
    "wof:name":"Studio's, Llc, Dover (delaware), Succursale Di Chiasso",
    "wof:placetype":"venue"
},
  "geometry": {"coordinates":[9.0282907486,45.8382263184],"type":"Point"}
}