{
  "type": "Feature",
  "properties": {
    "iso:country":"CH",
    "sg:address":"Waldeckweg 49",
    "sg:city":"Binningen",
    "sg:orig_category":"Maler U Glasergewerbe Malerei",
    "sg:phone":"+41 61 771 00 03",
    "sg:postcode":"4102",
    "sg:province":"Basel-Landschaft",
    "wof:name":"Edwin Schlumpf Malerarbeiten",
    "wof:placetype":"venue"
},
  "geometry": {"coordinates":[7.4358792305,47.4045410156],"type":"Point"}
}