{
  "type": "Feature",
  "properties": {
    "iso:country":"CH",
    "sg:address":"Route De Formangueires 9",
    "sg:city":"Belfaux",
    "sg:orig_category":"Verwaltung von Immobilien Wirtschaftspr\u00fcfung, Steuerberatung U Treuhand",
    "sg:phone":"+41 26 475 35 75",
    "sg:postcode":"1782",
    "sg:province":"Fribourg",
    "wof:name":"Belfagestion S\u00e0rl",
    "wof:placetype":"venue"
},
  "geometry": {"coordinates":[7.1153740883,46.8263549805],"type":"Point"}
}