{
  "type": "Feature",
  "properties": {
    "iso:country":"CH",
    "sg:address":"Freie Strasse 43",
    "sg:city":"Trimbach",
    "sg:orig_category":"Markt U Meinungsforschung",
    "sg:postcode":"4632",
    "sg:province":"Solothurn",
    "wof:name":"Bevit-marketing Studer Franz",
    "wof:placetype":"venue"
},
  "geometry": {"coordinates":[7.9043331146,47.3579521179],"type":"Point"}
}