{
  "type": "Feature",
  "properties": {
    "iso:country":"CH",
    "sg:address":"Zurigo Via 5",
    "sg:city":"Lugano",
    "sg:orig_category":"Non-Classified Establishments",
    "sg:postcode":"6900",
    "sg:province":"Ticino",
    "wof:name":"Ferloni Bruno",
    "wof:placetype":"venue"
},
  "geometry": {"coordinates":[9.0045003891,46.0516586304],"type":"Point"}
}