{
  "type": "Feature",
  "properties": {
    "iso:country":"CH",
    "sg:address":"Chamerstrasse 79",
    "sg:city":"Zug",
    "sg:orig_category":"Finanzierungsinstitutionen",
    "sg:postcode":"6300",
    "sg:province":"Zug",
    "wof:name":"Waldvogel Investment",
    "wof:placetype":"venue"
},
  "geometry": {"coordinates":[8.504940033,47.4877891541],"type":"Point"}
}