{
  "type": "Feature",
  "properties": {
    "iso:country":"CH",
    "sg:address":"2075",
    "sg:city":"Thielle-wavre",
    "sg:orig_category":"Schulpflegen",
    "sg:phone":"+41 32 753 77 24",
    "sg:postcode":"2075",
    "sg:province":"Neuch\u00e2tel",
    "wof:name":"Commission Scolaire De L'ecole Primaire",
    "wof:placetype":"venue"
},
  "geometry": {"coordinates":[7.0219497681,47.0200500488],"type":"Point"}
}