{
  "type": "Feature",
  "properties": {
    "iso:country":"CH",
    "sg:address":"Delafl\u00e9ch\u00e8re Rue 13",
    "sg:city":"Nyon",
    "sg:orig_category":"Non-Classified Establishments",
    "sg:phone":"+41 22 342 71 77",
    "sg:postcode":"1260",
    "sg:province":"Vaud",
    "wof:name":"Soins Esth\u00e9tiques Melly Christine",
    "wof:placetype":"venue"
},
  "geometry": {"coordinates":[6.2378101349,46.3814239502],"type":"Point"}
}