{
  "type": "Feature",
  "properties": {
    "iso:country":"CH",
    "sg:address":"Grenzstrasse 4",
    "sg:city":"Kreuzlingen",
    "sg:orig_category":"Detailhandel mit elektrischen Haushalts, Radio U Fernsehger\u00e4ten ohne ausgepr\u00e4gten Schwerpunkt",
    "sg:phone":"+41 71 672 78 80",
    "sg:postcode":"8280",
    "sg:province":"Thurgau",
    "wof:name":"Werner Wick Elektroger\u00e4te",
    "wof:placetype":"venue"
},
  "geometry": {"coordinates":[9.1730070114,47.655292511],"type":"Point"}
}