{
  "type": "Feature",
  "properties": {
    "iso:country":"CH",
    "sg:address":"Via Massagno 24",
    "sg:city":"Lugano",
    "sg:orig_category":"Vermittlung von Immobilien Verwaltung von Immobilien",
    "sg:phone":"+41 91 923 20 78",
    "sg:postcode":"6900",
    "sg:province":"Ticino",
    "wof:name":"Privera Sa Amministrazione Immobiliare",
    "wof:placetype":"venue"
},
  "geometry": {"coordinates":[8.9472208023,46.0100135803],"type":"Point"}
}