{
  "type": "Feature",
  "properties": {
    "iso:country":"CH",
    "sg:address":"Schlatt",
    "sg:city":"Appenzell",
    "sg:orig_category":"Unclassifiable Establishments",
    "sg:phone":"+41 71 787 14 13",
    "sg:postcode":"9050",
    "sg:province":"Appenzell Innerhoden",
    "wof:name":"Restaurant B\u00e4ren",
    "wof:placetype":"venue"
},
  "geometry": {"coordinates":[9.4076833725,47.3314361572],"type":"Point"}
}