{
  "type": "Feature",
  "properties": {
    "iso:country":"CH",
    "sg:address":"Kleeg\u00e4rtenstrasse 16",
    "sg:city":"Visp",
    "sg:orig_category":"Interessenvertretungen",
    "sg:postcode":"3930",
    "sg:province":"Valais",
    "wof:name":"K\u00fctschner Verein Edelweiss",
    "wof:placetype":"venue"
},
  "geometry": {"coordinates":[7.8798332214,46.2965698242],"type":"Point"}
}