{
  "type": "Feature",
  "properties": {
    "iso:country":"CH",
    "sg:address":"Bernstrasse 3",
    "sg:city":"Worb",
    "sg:orig_category":"Sonstiges Versicherungsgewerbe",
    "sg:phone":"+41 34 402 26 33",
    "sg:postcode":"3076",
    "sg:province":"Bern",
    "wof:name":"Emmentalische Mobiliarversich. Hauptagentur",
    "wof:placetype":"venue"
},
  "geometry": {"coordinates":[7.757589817,46.9491271973],"type":"Point"}
}