{
  "type": "Feature",
  "properties": {
    "iso:country":"CH",
    "sg:address":"Rue Des D\u00e9lices 1",
    "sg:city":"Gen\u00e8ve",
    "sg:orig_category":"Detailhandel mit Blumen U Pflanzen",
    "sg:phone":"+41 22 344 42 40",
    "sg:postcode":"1203",
    "sg:province":"Gen\u00e8ve",
    "wof:name":"D\u00e9lices-fleurs",
    "wof:placetype":"venue"
},
  "geometry": {"coordinates":[6.132349,46.206005],"type":"Point"}
}