{
  "type": "Feature",
  "properties": {
    "iso:country":"CH",
    "sg:address":"Merkurstrasse 45 8032 Z\u00fcrich",
    "sg:city":"Zust",
    "sg:orig_category":"Betrieb U technische Hilfsdienste des Kultur U Unterhaltungswesens",
    "sg:phone":"+41 14556170",
    "sg:postcode":"32",
    "wof:name":"Bcom Brunner",
    "wof:placetype":"venue"
},
  "geometry": {"coordinates":[8.56797,47.36684],"type":"Point"}
}