{
  "type": "Feature",
  "properties": {
    "iso:country":"CH",
    "sg:address":"Austrasse 79a",
    "sg:city":"Neuenegg",
    "sg:orig_category":"Vermietung U Verpachtung von eigenen Immobilien",
    "sg:postcode":"3176",
    "sg:province":"Bern",
    "wof:name":"Freelance Gmbh",
    "wof:placetype":"venue"
},
  "geometry": {"coordinates":[7.3175702095,46.8938217163],"type":"Point"}
}