{
  "type": "Feature",
  "properties": {
    "iso:country":"CH",
    "sg:address":"Niederdorf",
    "sg:city":"Eriswil",
    "sg:orig_category":"Landwirtschaftliche Genossenschaften",
    "sg:phone":"+41 71 394 15 40",
    "sg:postcode":"4952",
    "sg:province":"Bern",
    "wof:name":"Landi Lehmgrueb",
    "wof:placetype":"venue"
},
  "geometry": {"coordinates":[9.1329545975,47.4371452332],"type":"Point"}
}