{
  "type": "Feature",
  "properties": {
    "addr:full":"Riehenring 169 Basel Basel-Stadt 4058",
    "addr:housenumber":"169",
    "addr:postcode":"4058",
    "addr:street":"Riehenring",
    "iso:country":"CH",
    "sg:address":"Riehenring 169",
    "sg:city":"Basel",
    "sg:classifiers":[
        {
            "category":"Food & Beverages",
            "subcategory":"Specialty",
            "type":"Retail Goods"
        }
    ],
    "sg:phone":"+41 61 692 82 10",
    "sg:postcode":"4058",
    "sg:province":"Basel-Stadt",
    "sg:tags":[
        "caterer"
    ],
    "wof:name":"Pizzakurier Pizza Mcs",
    "wof:placetype":"venue"
},
  "geometry": {"coordinates":[7.597371,47.568871],"type":"Point"}
}