{
  "type": "Feature",
  "properties": {
    "iso:country":"CH",
    "sg:address":"Jaquet Rue Jean- 2 1201 Gen\u00e8ve. Postfach",
    "sg:city":"Gen\u00e8ve",
    "sg:orig_category":"Reiseb\u00fcros U Reiseveranstalter",
    "sg:phone":"+41 22 738 12 41",
    "sg:postcode":"1201",
    "sg:province":"Gen\u00e8ve",
    "wof:name":"La Rose Des Sables, Ben Hassel Reda",
    "wof:placetype":"venue"
},
  "geometry": {"coordinates":[6.1510391235,46.2118492126],"type":"Point"}
}