{
  "type": "Feature",
  "properties": {
    "iso:country":"CH",
    "sg:address":"Via Stazione",
    "sg:city":"Magliaso",
    "sg:orig_category":"Sonstiger Grosshandel",
    "sg:postcode":"6983",
    "sg:province":"Ticino",
    "wof:name":"Kawe-trading Kaiser Ruth",
    "wof:placetype":"venue"
},
  "geometry": {"coordinates":[8.884349823,45.9820899963],"type":"Point"}
}