{
  "type": "Feature",
  "properties": {
    "iso:country":"CH",
    "sg:address":"Zelgliweg 8",
    "sg:city":"Tenniken",
    "sg:orig_category":"Grosshandel mit sonstigen Halbwaren",
    "sg:phone":"+41 61 971 38 65",
    "sg:postcode":"4456",
    "sg:province":"Basel-Landschaft",
    "wof:name":"Susanne Mundwiler Linea Verde",
    "wof:placetype":"venue"
},
  "geometry": {"coordinates":[7.8110218048,47.4399490356],"type":"Point"}
}