{
  "type": "Feature",
  "properties": {
    "addr:full":"6527 Lodrino Ticino 6527",
    "addr:housenumber":"6527",
    "addr:postcode":"6527",
    "addr:street":"Lodrino Ticino",
    "iso:country":"CH",
    "sg:address":"6527",
    "sg:city":"Lodrino",
    "sg:classifiers":[
        {
            "category":"Personal",
            "subcategory":"Hair Removal",
            "type":"Services"
        }
    ],
    "sg:phone":"+41 71 288 05 40",
    "sg:postcode":"6527",
    "sg:province":"Ticino",
    "sg:tags":[
        "arbour"
    ],
    "wof:name":"Oeko-handels Ag",
    "wof:placetype":"venue"
},
  "geometry": {"coordinates":[9.418676,47.442032],"type":"Point"}
}