{
  "type": "Feature",
  "properties": {
    "iso:country":"CH",
    "sg:address":"Vernes Chemin Des 1936 Verbier. Postfach",
    "sg:city":"Verbier",
    "sg:orig_category":"Sonstiges Versicherungsgewerbe",
    "sg:phone":"+41 24 466 44 33",
    "sg:postcode":"1936",
    "sg:province":"Valais",
    "wof:name":"Ifipp S\u00e0rl",
    "wof:placetype":"venue"
},
  "geometry": {"coordinates":[7.2229619026,46.0967292786],"type":"Point"}
}