{
  "type": "Feature",
  "properties": {
    "addr:full":"1996 Basse-nendaz Valais 1996",
    "addr:housenumber":"1996",
    "addr:postcode":"1996",
    "addr:street":"Basse-Nendaz Valais",
    "iso:country":"CH",
    "sg:address":"1996",
    "sg:city":"Basse-nendaz",
    "sg:orig_category":"Bauschreinerei Herstellung von M\u00f6beln verschiedener Art",
    "sg:phone":"+41 27 288 23 24",
    "sg:postcode":"1996",
    "sg:province":"Valais",
    "wof:name":"Simon Fournier Eb\u00e9nisterie",
    "wof:placetype":"venue"
},
  "geometry": {"coordinates":[7.31218,46.190159],"type":"Point"}
}