{
  "type": "Feature",
  "properties": {
    "iso:country":"CH",
    "sg:address":"Seefeldstrasse 317",
    "sg:city":"Z\u00fcrich",
    "sg:orig_category":"Interessenvertretungen Museen",
    "sg:phone":"+41 13813808",
    "sg:postcode":"8008",
    "sg:province":"Z\u00fcrich",
    "wof:name":"Stiftung F\u00fcr Konstruktive Und Konkrete Kunst",
    "wof:placetype":"venue"
},
  "geometry": {"coordinates":[8.5648288727,47.3471679688],"type":"Point"}
}