{
  "type": "Feature",
  "properties": {
    "iso:country":"CH",
    "sg:address":"Murerh\u00fcsli 5 6214 Schenkon. Postfach",
    "sg:city":"Schenkon",
    "sg:orig_category":"Architektur U Ingenieurb\u00fcros Architekturb\u00fcros",
    "sg:phone":"+41 41 921 48 66",
    "sg:postcode":"6214",
    "sg:province":"Luzern",
    "wof:name":"Zimmermann + Baumeler, Architekten",
    "wof:placetype":"venue"
},
  "geometry": {"coordinates":[8.138495,47.18185],"type":"Point"}
}