{
  "type": "Feature",
  "properties": {
    "iso:country":"CH",
    "sg:address":"B\u00f6zingenstrasse 26b 2500 Biel/bienne. Postfach",
    "sg:city":"Biel/bienne",
    "sg:orig_category":"Maler U Glasergewerbe",
    "sg:phone":"+41 32 373 43 47",
    "sg:postcode":"2502",
    "sg:province":"Bern",
    "wof:name":"Probst Marcel",
    "wof:placetype":"venue"
},
  "geometry": {"coordinates":[7.2545080185,47.1461677551],"type":"Point"}
}