{
  "type": "Feature",
  "properties": {
    "iso:country":"CH",
    "sg:address":"Via Al Forte 3",
    "sg:city":"Lugano",
    "sg:orig_category":"Detailhandel mit Schuhen",
    "sg:phone":"+41 91 922 05 82",
    "sg:postcode":"6900",
    "sg:province":"Ticino",
    "wof:name":"Giulio Strenger Negozio Calzature",
    "wof:placetype":"venue"
},
  "geometry": {"coordinates":[8.9533481598,46.0056495667],"type":"Point"}
}