{
  "type": "Feature",
  "properties": {
    "iso:country":"CH",
    "sg:address":"Rue De Lausanne 26",
    "sg:city":"Payerne",
    "sg:orig_category":"Vermietung U Verpachtung von eigenen Immobilien Vermittlung von Immobilien",
    "sg:phone":"+41 79 310 80 82",
    "sg:postcode":"1530",
    "sg:province":"Vaud",
    "wof:name":"Bugnon Hubert, Bureau Immobilier",
    "wof:placetype":"venue"
},
  "geometry": {"coordinates":[6.9363651276,46.820022583],"type":"Point"}
}