{
  "type": "Feature",
  "properties": {
    "iso:country":"CH",
    "sg:address":"Route D'hermance 501",
    "sg:city":"Hermance",
    "sg:orig_category":"Kunsthandel",
    "sg:phone":"+41 22 751 03 30",
    "sg:postcode":"1248",
    "sg:province":"Gen\u00e8ve",
    "wof:name":"Horizon Galerie D'art",
    "wof:placetype":"venue"
},
  "geometry": {"coordinates":[6.2308797836,46.2983589172],"type":"Point"}
}