{
  "type": "Feature",
  "properties": {
    "iso:country":"CH",
    "sg:address":"Rue Juste-olivier 22",
    "sg:city":"Nyon",
    "sg:orig_category":"Informatikdienste",
    "sg:phone":"+41 18515557",
    "sg:postcode":"1260",
    "sg:province":"Vaud",
    "wof:name":"Q-it Gmbh Edv - Dienstleistungen",
    "wof:placetype":"venue"
},
  "geometry": {"coordinates":[8.4947443008,47.4966125488],"type":"Point"}
}