{
  "type": "Feature",
  "properties": {
    "iso:country":"CH",
    "sg:address":"Glanzenbergstrasse 4",
    "sg:city":"Dietikon",
    "sg:orig_category":"Grosshandel mit B\u00fcromaschinen Softwareentwicklung U beratung",
    "sg:phone":"+41 17405747",
    "sg:postcode":"8953",
    "sg:province":"Z\u00fcrich",
    "wof:name":"Reichert-support",
    "wof:placetype":"venue"
},
  "geometry": {"coordinates":[8.4221391678,47.3983078003],"type":"Point"}
}