{
  "type": "Feature",
  "properties": {
    "iso:country":"CH",
    "sg:address":"Huebacher 27 8153 R\u00fcmlang. Postfach 168",
    "sg:city":"R\u00fcmlang",
    "sg:orig_category":"Herstellung von sonstigen elektrischen Ausr\u00fcstungen",
    "sg:postcode":"8153",
    "sg:province":"Z\u00fcrich",
    "wof:name":"Gutzwiller Digital Systems Elektronik, Software; Verkauf",
    "wof:placetype":"venue"
},
  "geometry": {"coordinates":[8.2184000015,47.3054199219],"type":"Point"}
}