{
  "type": "Feature",
  "properties": {
    "iso:country":"CH",
    "sg:address":"Oberdorf 10",
    "sg:city":"M\u00fchlau",
    "sg:orig_category":"Gemeindeverwaltungen",
    "sg:phone":"+41 27 971 10 12",
    "sg:postcode":"5642",
    "sg:province":"Aargau",
    "wof:name":"Gemeindeverwaltung M\u00fchlebach",
    "wof:placetype":"venue"
},
  "geometry": {"coordinates":[8.1553297043,46.4084701538],"type":"Point"}
}