{
  "type": "Feature",
  "properties": {
    "iso:country":"CH",
    "sg:address":"Tscharnerstrasse 39a",
    "sg:city":"Bern",
    "sg:orig_category":"Markt U Meinungsforschung",
    "sg:postcode":"3007",
    "sg:province":"Bern",
    "wof:name":"Value-add.ch, Marti & Tobler",
    "wof:placetype":"venue"
},
  "geometry": {"coordinates":[7.4274401665,46.9425468445],"type":"Point"}
}