{
  "type": "Feature",
  "properties": {
    "addr:full":"M\u00fchlegasse 2 Aarburg Aargau 4663",
    "addr:housenumber":"2",
    "addr:postcode":"4663",
    "addr:street":"Muehlegasse",
    "iso:country":"CH",
    "sg:address":"M\u00fchlegasse 2",
    "sg:city":"Aarburg",
    "sg:orig_category":"Reisen, Unterk\u00fcnfte",
    "sg:phone":"+41 62 791 40 21",
    "sg:postcode":"4663",
    "sg:province":"Aargau",
    "wof:name":"Michael K\u00f6pfler",
    "wof:placetype":"venue"
},
  "geometry": {"coordinates":[7.900754,47.320389],"type":"Point"}
}