{
  "type": "Feature",
  "properties": {
    "iso:country":"CH",
    "sg:address":"Allmendstrasse 4",
    "sg:city":"Gunzgen",
    "sg:orig_category":"Nationale Postdienste",
    "sg:phone":"+41 62 216 37 00",
    "sg:postcode":"4617",
    "sg:province":"Solothurn",
    "wof:name":"Die Schweizerische Post",
    "wof:placetype":"venue"
},
  "geometry": {"coordinates":[7.8290381432,47.3158836365],"type":"Point"}
}