{
  "type": "Feature",
  "properties": {
    "iso:country":"CH",
    "sg:address":"Rue Madame-de-sta\u00ebl 6",
    "sg:city":"Gen\u00e8ve",
    "sg:orig_category":"Maurerarbeiten Sonstiger spezialisierter Hoch U Tiefbau",
    "sg:phone":"+41 22 344 41 25",
    "sg:postcode":"1201",
    "sg:province":"Gen\u00e8ve",
    "wof:name":"Entreprise Otero",
    "wof:placetype":"venue"
},
  "geometry": {"coordinates":[6.1348719597,46.2076072693],"type":"Point"}
}