{
  "type": "Feature",
  "properties": {
    "iso:country":"CH",
    "sg:address":"Orchideenweg 9",
    "sg:city":"W\u00fcrenlingen",
    "sg:orig_category":"Reiseb\u00fcros U Reiseveranstalter",
    "sg:postcode":"5303",
    "sg:province":"Aargau",
    "wof:name":"Tasman Tours & Travel, Marcel G. Meek",
    "wof:placetype":"venue"
},
  "geometry": {"coordinates":[8.2478370667,47.5247650146],"type":"Point"}
}