{
  "type": "Feature",
  "properties": {
    "iso:country":"CH",
    "sg:address":"4226",
    "sg:city":"Breitenbach",
    "sg:orig_category":"Pensionskassen",
    "sg:phone":"+41 61 406 40 30",
    "sg:postcode":"4226",
    "sg:province":"Solothurn",
    "wof:name":"Personalf\u00fcrsorgestiftung Der Schwenk Schichtex Ag",
    "wof:placetype":"venue"
},
  "geometry": {"coordinates":[7.5554871559,47.5099182129],"type":"Point"}
}