{
  "type": "Feature",
  "properties": {
    "iso:country":"CH",
    "sg:address":"Fuhrstrasse 31 8820 W\u00e4denswil. Postfach",
    "sg:city":"Z\u00fcrich",
    "sg:orig_category":"Sonstige pers\u00f6nliche Dienstleistungen",
    "sg:postcode":"8008",
    "sg:province":"Z\u00fcrich",
    "wof:name":"Valde Value Development Gmbh",
    "wof:placetype":"venue"
},
  "geometry": {"coordinates":[8.6667976379,47.2283477783],"type":"Point"}
}