{
  "type": "Feature",
  "properties": {
    "iso:country":"CH",
    "sg:address":"Baderg\u00e4ssli 6",
    "sg:city":"Aarau",
    "sg:orig_category":"Reiseb\u00fcros U Reiseveranstalter",
    "sg:phone":"+41 62 824 02 84",
    "sg:postcode":"5000",
    "sg:province":"Aargau",
    "wof:name":"Scuba-shop Travel Service Ag",
    "wof:placetype":"venue"
},
  "geometry": {"coordinates":[8.0409889221,47.3919258118],"type":"Point"}
}