{
  "type": "Feature",
  "properties": {
    "iso:country":"CH",
    "sg:address":"Avenue Du Casino 45 1820 Montreux Case Postale 3509",
    "sg:city":"Gen\u00e8ve",
    "sg:orig_category":"Architektur U Ingenieurb\u00fcros",
    "sg:phone":"+41 71 755 61 01",
    "sg:postcode":"1204",
    "sg:province":"Gen\u00e8ve",
    "wof:name":"B + F Architekten Ag",
    "wof:placetype":"venue"
},
  "geometry": {"coordinates":[9.558842,47.37241],"type":"Point"}
}