{
  "type": "Feature",
  "properties": {
    "iso:country":"CH",
    "sg:address":"Grand-rue",
    "sg:city":"Essertines-yverdon",
    "sg:orig_category":"Grosshandel mit Datenverarbeitungsger\u00e4ten Grosshandel mit Software",
    "sg:postcode":"1417",
    "sg:province":"Vaud",
    "wof:name":"Logic Center S\u00e0rl",
    "wof:placetype":"venue"
},
  "geometry": {"coordinates":[6.6377649307,46.7164993286],"type":"Point"}
}