{
  "type": "Feature",
  "properties": {
    "iso:country":"CH",
    "sg:address":"Hauptstrasse 33",
    "sg:city":"Birsfelden",
    "sg:orig_category":"Detailhandel mit Damenbekleidung",
    "sg:phone":"+41 61 311 97 70",
    "sg:postcode":"4127",
    "sg:province":"Basel-Landschaft",
    "wof:name":"Susanne Tarelli Damenmode Tarelli",
    "wof:placetype":"venue"
},
  "geometry": {"coordinates":[7.620405,47.554081],"type":"Point"}
}