{
  "type": "Feature",
  "properties": {
    "addr:full":"Ziefnerstrasse 9 Arboldswil Basel-Landschaft 4424",
    "addr:housenumber":"9",
    "addr:postcode":"4424",
    "addr:street":"Ziefnerstrasse",
    "iso:country":"CH",
    "sg:address":"Ziefnerstrasse 9",
    "sg:city":"Arboldswil",
    "sg:orig_category":"Bauschreinerei",
    "sg:phone":"+41 61 931 11 10",
    "sg:postcode":"4424",
    "sg:province":"Basel-Landschaft",
    "wof:name":"Paul Stohler Schreinerei",
    "wof:placetype":"venue"
},
  "geometry": {"coordinates":[7.716703,47.416325],"type":"Point"}
}