{
  "type": "Feature",
  "properties": {
    "iso:country":"CH",
    "sg:address":"Spychertenstrasse 30",
    "sg:city":"Hilterfingen",
    "sg:orig_category":"Fahrschulen, Flugschulen",
    "sg:postcode":"3652",
    "sg:province":"Bern",
    "wof:name":"Willy Berger",
    "wof:placetype":"venue"
},
  "geometry": {"coordinates":[8.9724836349,47.428478241],"type":"Point"}
}