{
  "type": "Feature",
  "properties": {
    "iso:country":"CH",
    "sg:address":"Seidengasse 13",
    "sg:city":"Z\u00fcrich",
    "sg:orig_category":"Detailhandel mit elektrischen Haushalts-,Radio U Fernsehger\u00e4ten sowie Musikinstrumenten",
    "sg:phone":"+41 12118108",
    "sg:postcode":"8001",
    "sg:province":"Z\u00fcrich",
    "wof:name":"New Black Spot Ag Waren, Bes. Tontr\u00e4ger Usw; Handel",
    "wof:placetype":"venue"
},
  "geometry": {"coordinates":[8.5373048782,47.3751602173],"type":"Point"}
}