{
  "type": "Feature",
  "properties": {
    "iso:country":"CH",
    "sg:address":"Route De Chancy 414",
    "sg:city":"Cartigny",
    "sg:orig_category":"Autospenglereien",
    "sg:phone":"+41 22 756 25 23",
    "sg:postcode":"1236",
    "sg:province":"Gen\u00e8ve",
    "wof:name":"Luigi Di Capua Garage D'eaumorte",
    "wof:placetype":"venue"
},
  "geometry": {"coordinates":[6.041541,46.172131],"type":"Point"}
}