{
  "type": "Feature",
  "properties": {
    "iso:country":"CH",
    "sg:address":"Zelgli 18 5313 Klingnau. Postfach 7",
    "sg:city":"Koblenz",
    "sg:orig_category":"S\u00e4gewerke",
    "sg:phone":"+41 41 660 14 82",
    "sg:postcode":"5322",
    "sg:province":"Aargau",
    "wof:name":"Gebr\u00fcder Robert & Josef Burch S\u00e4gerei",
    "wof:placetype":"venue"
},
  "geometry": {"coordinates":[8.2240428925,46.8806610107],"type":"Point"}
}