{
  "type": "Feature",
  "properties": {
    "iso:country":"CH",
    "sg:address":"Erlenstr. 34",
    "sg:city":"Emmen",
    "sg:orig_category":"Allgemeiner Hoch U Tiefbau",
    "sg:postcode":"6032",
    "sg:province":"Luzern",
    "wof:name":"D + P Fassaden Und Betonsanierungen Pfoster Hans",
    "wof:placetype":"venue"
},
  "geometry": {"coordinates":[8.267477,47.077278],"type":"Point"}
}