{
  "type": "Feature",
  "properties": {
    "iso:country":"CH",
    "sg:address":"D\u00e4ndlikerrain 3",
    "sg:city":"Bern",
    "sg:orig_category":"Elektroinstallation Fernmeldedienste",
    "sg:postcode":"3014",
    "sg:province":"Bern",
    "wof:name":"Turnkey Communications Ag Zweigniederlassung Bern",
    "wof:placetype":"venue"
},
  "geometry": {"coordinates":[7.448390007,46.9649085999],"type":"Point"}
}