{
  "type": "Feature",
  "properties": {
    "iso:country":"CH",
    "sg:address":"Baarerstrasse 36",
    "sg:city":"Zug",
    "sg:orig_category":"Unternehmensberatung",
    "sg:postcode":"6300",
    "sg:province":"Zug",
    "wof:name":"Ams-interconsult Ag",
    "wof:placetype":"venue"
},
  "geometry": {"coordinates":[8.5172119141,47.1742897034],"type":"Point"}
}