{
  "type": "Feature",
  "properties": {
    "iso:country":"CH",
    "sg:address":"Kirchlindachstrasse 121 3052 Zollikofen. Postfach",
    "sg:city":"Zollikofen",
    "sg:orig_category":"Herstellung von Teppichen Verlegen von Fliesen U Platten",
    "sg:phone":"+41 31 911 11 60",
    "sg:postcode":"3052",
    "sg:province":"Bern",
    "wof:name":"Alfred R\u00f6thlisberger Ag",
    "wof:placetype":"venue"
},
  "geometry": {"coordinates":[7.4429187775,47.0034675598],"type":"Point"}
}