{
  "type": "Feature",
  "properties": {
    "iso:country":"CH",
    "sg:address":"Dreilindenstrasse 19",
    "sg:city":"Meggen",
    "sg:orig_category":"Architekturb\u00fcros",
    "sg:phone":"+41 41 377 21 21",
    "sg:postcode":"6045",
    "sg:province":"Luzern",
    "wof:name":"Othmar K\u00fcndig Architekt Htl",
    "wof:placetype":"venue"
},
  "geometry": {"coordinates":[8.367421,47.0467],"type":"Point"}
}