{
  "type": "Feature",
  "properties": {
    "iso:country":"CH",
    "sg:address":"Hafenstrasse 50 A",
    "sg:city":"Kreuzlingen",
    "sg:orig_category":"Gesundheitswesen",
    "sg:phone":"+41 13006407",
    "sg:postcode":"8280",
    "sg:province":"Thurgau",
    "wof:name":"Netzwerk Psychologie Ag",
    "wof:placetype":"venue"
},
  "geometry": {"coordinates":[9.1818981171,47.6485328674],"type":"Point"}
}