{
  "type": "Feature",
  "properties": {
    "iso:country":"CH",
    "sg:address":"Bettenhausenstrasse 3 3360 Herzogenbuchsee. Postfach",
    "sg:city":"Herzogenbuchsee",
    "sg:orig_category":"Flachsaufbereitung U spinnerei",
    "sg:phone":"+41 41 920 16 21",
    "sg:postcode":"3360",
    "sg:province":"Bern",
    "wof:name":"Irie Haus Ren\u00e9 Schmidlin",
    "wof:placetype":"venue"
},
  "geometry": {"coordinates":[8.1154975891,47.1559753418],"type":"Point"}
}