{
  "type": "Feature",
  "properties": {
    "iso:country":"CH",
    "sg:address":"3429",
    "sg:city":"Hellsau",
    "sg:orig_category":"Verwertung von Milch",
    "sg:postcode":"3429",
    "sg:province":"Bern",
    "wof:name":"K\u00e4sereigenossenschaft H\u00f6fen",
    "wof:placetype":"venue"
},
  "geometry": {"coordinates":[7.5760560036,46.7201690674],"type":"Point"}
}