{
  "type": "Feature",
  "properties": {
    "iso:country":"CH",
    "sg:address":"L\u00f6weng\u00e4ssli 1 8246 Langwiesen. Postfach",
    "sg:city":"Langwiesen",
    "sg:orig_category":"Sonstige Kurierdienste",
    "sg:phone":"+41 52 659 27 73",
    "sg:postcode":"8246",
    "sg:province":"Z\u00fcrich",
    "wof:name":"Elan Kleintransporte, A. Weiler",
    "wof:placetype":"venue"
},
  "geometry": {"coordinates":[8.6637763977,47.6840515137],"type":"Point"}
}