{
  "type": "Feature",
  "properties": {
    "iso:country":"CH",
    "sg:address":"Hauptstrasse 10",
    "sg:city":"M\u00fcmliswil",
    "sg:orig_category":"Detailhandel mit Teppichen Verlegen von Fussboden",
    "sg:phone":"+41 41 448 11 81",
    "sg:postcode":"4717",
    "sg:province":"Solothurn",
    "wof:name":"Bruno Leuthard Raumgestaltung",
    "wof:placetype":"venue"
},
  "geometry": {"coordinates":[8.3199453354,47.1380310059],"type":"Point"}
}