{
  "type": "Feature",
  "properties": {
    "iso:country":"CH",
    "sg:address":"Unterm Schloss 90 9496 Balzers. Postfach 162",
    "sg:city":"Balzers",
    "sg:classifiers":[
        {
            "category":"Bars & Pubs",
            "type":"Food & Drink"
        }
    ],
    "sg:phone":"+423 384 12 66",
    "sg:postcode":"9496",
    "sg:tags":[
        "restaurant"
    ],
    "wof:name":"Restaurant Schlosshof & Gutenberg Bar",
    "wof:placetype":"venue"
},
  "geometry": {"coordinates":[9.500072,47.065689],"type":"Point"}
}