{
  "type": "Feature",
  "properties": {
    "iso:country":"CH",
    "sg:address":"Dubied Rue Pierre- 3",
    "sg:city":"Couvet",
    "sg:orig_category":"Grosshandel mit Nahrungsmitteln, Getr\u00e4nken U Tabakwaren ohne ausgepr\u00e4gten Schwerpunkt",
    "sg:postcode":"2108",
    "sg:province":"Neuch\u00e2tel",
    "wof:name":"Baehler Patricia",
    "wof:placetype":"venue"
},
  "geometry": {"coordinates":[6.6346621513,46.9224853516],"type":"Point"}
}