{
  "type": "Feature",
  "properties": {
    "iso:country":"CH",
    "sg:address":"Langwiesstrasse 30a",
    "sg:city":"Frauenfeld",
    "sg:orig_category":"Zimmerei, Dachdeckerei, Bauspenglerei U Abdichtung",
    "sg:postcode":"8500",
    "sg:province":"Thurgau",
    "wof:name":"Schertenleib Ag, F.",
    "wof:placetype":"venue"
},
  "geometry": {"coordinates":[8.9106082916,47.5555953979],"type":"Point"}
}