{
  "type": "Feature",
  "properties": {
    "iso:country":"CH",
    "sg:address":"Rue Du Pr\u00e9-du-pont 29",
    "sg:city":"Collombey",
    "sg:orig_category":"Allgemeiner Hoch U Tiefbau Strassenbau",
    "sg:phone":"+41 24 472 12 12",
    "sg:postcode":"1868",
    "sg:province":"Valais",
    "wof:name":"Atra Sa",
    "wof:placetype":"venue"
},
  "geometry": {"coordinates":[6.95499,46.269451],"type":"Point"}
}