{
  "type": "Feature",
  "properties": {
    "iso:country":"CH",
    "sg:address":"G\u00e4rtli 30 9475 Sevelen. Postfach",
    "sg:city":"Sevelen",
    "sg:orig_category":"Sonstiger Grosshandel",
    "sg:phone":"+41 81 740 11 90",
    "sg:postcode":"9475",
    "sg:province":"St. Gallen",
    "wof:name":"Heinrich Wilhelm Consulting",
    "wof:placetype":"venue"
},
  "geometry": {"coordinates":[9.489991188,47.1186676025],"type":"Point"}
}