{
  "type": "Feature",
  "properties": {
    "iso:country":"CH",
    "sg:address":"Gurzelenstrasse 17",
    "sg:city":"Biel/bienne",
    "sg:orig_category":"Druck ohne Zeitungsdruck Offsetdruck",
    "sg:phone":"+41 19302862",
    "sg:postcode":"2502",
    "sg:province":"Bern",
    "wof:name":"Offset Express Grafikd\u00f6rfli Ag",
    "wof:placetype":"venue"
},
  "geometry": {"coordinates":[8.8131666183,47.3286628723],"type":"Point"}
}