{
  "type": "Feature",
  "properties": {
    "iso:country":"CH",
    "sg:address":"Stockmatt",
    "sg:city":"R\u00fcschegg",
    "sg:classifiers":[
        {
            "category":"Banks & Credit Unions",
            "subcategory":"Bank",
            "type":"Services"
        }
    ],
    "sg:phone":"+41 31 731 14 83",
    "sg:postcode":"3154",
    "sg:province":"Bern",
    "wof:name":"Raiffeisenbank Schwarzwasser",
    "wof:placetype":"venue"
},
  "geometry": {"coordinates":[7.34799,46.84354],"type":"Point"}
}