{
  "type": "Feature",
  "properties": {
    "iso:country":"CH",
    "sg:address":"Domaine De La Grande-br\u00e8che 1956 St-pierre-clages. Postfach",
    "sg:city":"St-pierre-clages",
    "sg:orig_category":"Grosshandel mit Obst U Gem\u00fcse",
    "sg:phone":"+41 27 306 29 30",
    "sg:postcode":"1956",
    "wof:name":"Topfruit S\u00e0rl",
    "wof:placetype":"venue"
},
  "geometry": {"coordinates":[-109.8162078857,48.2440681458],"type":"Point"}
}