{
  "type": "Feature",
  "properties": {
    "iso:country":"CH",
    "sg:address":"Badenerstrasse 5",
    "sg:city":"Dietikon",
    "sg:classifiers":[
        {
            "category":"Shopping",
            "subcategory":"Department Store",
            "type":"Retail Goods"
        }
    ],
    "sg:phone":"+41 17403488",
    "sg:postcode":"8953",
    "sg:province":"Z\u00fcrich",
    "sg:tags":[
        "linen",
        "bed"
    ],
    "wof:name":"Ricotex Textil",
    "wof:placetype":"venue"
},
  "geometry": {"coordinates":[8.399171,47.4053],"type":"Point"}
}