{
  "type": "Feature",
  "properties": {
    "iso:country":"CH",
    "sg:address":"Endingerstrasse 14",
    "sg:city":"W\u00fcrenlingen",
    "sg:orig_category":"Detailhandel mit Fleisch U Fleischwaren Schlachten U Fleischverarbeitung",
    "sg:phone":"+41 27 932 44 06",
    "sg:postcode":"5303",
    "sg:province":"Aargau",
    "wof:name":"Metzgerei, R\u00e4ss Bernhard",
    "wof:placetype":"venue"
},
  "geometry": {"coordinates":[7.7446789742,46.3072509766],"type":"Point"}
}