{
  "type": "Feature",
  "properties": {
    "iso:country":"CH",
    "sg:address":"Ausserdorf 59a",
    "sg:city":"R\u00fcdlingen",
    "sg:orig_category":"Markt U Meinungsforschung",
    "sg:phone":"+41 18671280",
    "sg:postcode":"8455",
    "sg:province":"Schaffhausen",
    "wof:name":"Solitaire Marketing Services Klaentschi Bert J.",
    "wof:placetype":"venue"
},
  "geometry": {"coordinates":[8.5711297989,47.5807914734],"type":"Point"}
}