{
  "type": "Feature",
  "properties": {
    "iso:country":"CH",
    "sg:address":"Delsbergerstrasse 4242 Laufen. Postfach",
    "sg:city":"Laufen",
    "sg:orig_category":"Gewinnung von Natursteinen Herstellung von sonstigen Produkten aus nichtmetallischen Mineralien",
    "sg:phone":"+41 61 761 62 56",
    "sg:postcode":"4242",
    "sg:province":"Basel-Landschaft",
    "wof:name":"M\u00fcller Ren\u00e9 Ag",
    "wof:placetype":"venue"
},
  "geometry": {"coordinates":[7.4985890388,47.4152565002],"type":"Point"}
}