{
  "type": "Feature",
  "properties": {
    "iso:country":"CH",
    "sg:address":"Pellandini Via C. 2 6500 Bellinzona. Postfach",
    "sg:city":"Bellinzona",
    "sg:orig_category":"Unternehmensberatung",
    "sg:phone":"+41 21 845 56 35",
    "sg:postcode":"6500",
    "sg:province":"Ticino",
    "wof:name":"Daq Bureau Conseil, Quenet Dominique",
    "wof:placetype":"venue"
},
  "geometry": {"coordinates":[6.2120537758,46.582359314],"type":"Point"}
}