{
  "type": "Feature",
  "properties": {
    "iso:country":"CH",
    "sg:address":"Kastanienstrasse 43",
    "sg:city":"Dachsen",
    "sg:orig_category":"Ingenieurb\u00fcros divers",
    "sg:phone":"+41 52 654 32 20",
    "sg:postcode":"8447",
    "sg:province":"Z\u00fcrich",
    "wof:name":"Jean-jacques Br\u00fchlmann Br\u00fchlmann Engineering",
    "wof:placetype":"venue"
},
  "geometry": {"coordinates":[8.6135015488,47.6652297974],"type":"Point"}
}