{
  "type": "Feature",
  "properties": {
    "iso:country":"CH",
    "sg:address":"St.galler-ring 225",
    "sg:city":"Basel",
    "sg:orig_category":"Sportvereine Ballsport Tennis",
    "sg:phone":"+41 61 281 16 77",
    "sg:postcode":"4054",
    "sg:province":"Basel-Stadt",
    "wof:name":"Tc Old Boys",
    "wof:placetype":"venue"
},
  "geometry": {"coordinates":[7.5685381889,47.5505714417],"type":"Point"}
}