{
  "type": "Feature",
  "properties": {
    "iso:country":"CH",
    "sg:address":"6215 Berom\u00fcnster. Postfach",
    "sg:city":"Berom\u00fcnster",
    "sg:orig_category":"Museen",
    "sg:postcode":"6215",
    "sg:province":"Luzern",
    "wof:name":"Heimatmuseum Bucheggberg",
    "wof:placetype":"venue"
},
  "geometry": {"coordinates":[7.5133500099,47.1395759583],"type":"Point"}
}