{
  "type": "Feature",
  "properties": {
    "iso:country":"CH",
    "sg:address":"Rue Saint-antoine 7",
    "sg:city":"Vevey",
    "sg:classifiers":[
        {
            "category":"Education",
            "subcategory":"Library",
            "type":"Public Place"
        }
    ],
    "sg:phone":"+41 21 922 05 24",
    "sg:postcode":"1800",
    "sg:province":"Vaud",
    "sg:tags":[
        "u",
        "bibliotheken",
        "archive"
    ],
    "wof:name":"Biblioth\u00e8que Anglaise",
    "wof:placetype":"venue"
},
  "geometry": {"coordinates":[6.851897,46.460709],"type":"Point"}
}