{
  "type": "Feature",
  "properties": {
    "iso:country":"CH",
    "sg:address":"Oberhof",
    "sg:city":"Fischenthal",
    "sg:orig_category":"RESTAURANTS: TEA-ROOMS",
    "sg:phone":"+41 71 385 25 31",
    "sg:postcode":"8497",
    "sg:province":"Z\u00fcrich",
    "wof:name":"Brunner Martin Restaurant Ochsen",
    "wof:placetype":"venue"
},
  "geometry": {"coordinates":[9.2489013672,47.4157028198],"type":"Point"}
}