{
  "type": "Feature",
  "properties": {
    "iso:country":"CH",
    "sg:address":"Dorfstrasse 7a",
    "sg:city":"Triesen",
    "sg:orig_category":"Sonstiger Grosshandel",
    "sg:phone":"+423 392 37 30",
    "sg:postcode":"9495",
    "wof:name":"Ritronik Ag Alarm- & Sicherheitsanlagen",
    "wof:placetype":"venue"
},
  "geometry": {"coordinates":[9.5257368088,47.1094741821],"type":"Point"}
}