{
  "type": "Feature",
  "properties": {
    "iso:country":"CH",
    "sg:address":"Truttikerstrasse 22",
    "sg:city":"Ossingen",
    "sg:orig_category":"Nationale Postdienste",
    "sg:phone":"+41 52 317 11 10",
    "sg:postcode":"8475",
    "sg:province":"Z\u00fcrich",
    "wof:name":"Die Schweizerische Post",
    "wof:placetype":"venue"
},
  "geometry": {"coordinates":[8.7263708115,47.6126403809],"type":"Point"}
}