{
  "type": "Feature",
  "properties": {
    "iso:country":"CH",
    "sg:address":"Hauptgasse 20",
    "sg:city":"Lichtensteig",
    "sg:orig_category":"Herstellung von Reiseartikeln, Leder U Sattlerwaren Verlegen von Fussboden",
    "sg:phone":"+41 26 660 40 88",
    "sg:postcode":"9620",
    "sg:province":"St. Gallen",
    "wof:name":"Burgy Ameublement",
    "wof:placetype":"venue"
},
  "geometry": {"coordinates":[6.8926100731,46.8147010803],"type":"Point"}
}