{
  "type": "Feature",
  "properties": {
    "iso:country":"CH",
    "sg:address":"R\u00fctli 13",
    "sg:city":"Inwil",
    "sg:orig_category":"G\u00fcterbef\u00f6rderung im Strassenverkehr",
    "sg:phone":"+41 41 448 20 42",
    "sg:postcode":"6034",
    "sg:province":"Luzern",
    "wof:name":"Felder Edi Transporte Ueberland",
    "wof:placetype":"venue"
},
  "geometry": {"coordinates":[8.3524494171,47.1240501404],"type":"Point"}
}