{
  "type": "Feature",
  "properties": {
    "iso:country":"CH",
    "sg:address":"Chamerstrasse 79 6300 Zug. Postfach 3361",
    "sg:city":"Zug",
    "sg:orig_category":"Detailhandel mit Metallwaren, Anstrichmitteln, Glaswaren, Bau U Heimwerkerbedarf",
    "sg:phone":"+41 41 741 51 13",
    "sg:postcode":"6303",
    "sg:province":"Zug",
    "wof:name":"Technikontor Ag",
    "wof:placetype":"venue"
},
  "geometry": {"coordinates":[8.49913311,47.1765174866],"type":"Point"}
}