{
  "type": "Feature",
  "properties": {
    "iso:country":"CH",
    "sg:address":"Gen\u00e8ve Rue De 41 1003 Lausanne. Postfach",
    "sg:city":"Lausanne",
    "sg:orig_category":"Tankstellen",
    "sg:postcode":"1003",
    "sg:province":"Vaud",
    "wof:name":"Station Shell Des Entrep\u00f4ts, Anne-marie De Luca Station-service",
    "wof:placetype":"venue"
},
  "geometry": {"coordinates":[6.6252799034,46.5224838257],"type":"Point"}
}