{
  "type": "Feature",
  "properties": {
    "iso:country":"CH",
    "sg:address":"Rue Des Alpes 53",
    "sg:city":"Crissier",
    "sg:orig_category":"Sanit\u00e4r U Heizungsinstallation",
    "sg:phone":"+41 21 634 60 33",
    "sg:postcode":"1023",
    "sg:province":"Vaud",
    "wof:name":"Rezso Chauffages Sa",
    "wof:placetype":"venue"
},
  "geometry": {"coordinates":[6.5799679756,46.5412635803],"type":"Point"}
}