{
  "type": "Feature",
  "properties": {
    "iso:country":"CH",
    "sg:address":"Bammattenweg 10",
    "sg:city":"Naters",
    "sg:orig_category":"G\u00fcterbef\u00f6rderung im Strassenverkehr",
    "sg:phone":"+41 27 923 93 64",
    "sg:postcode":"3904",
    "sg:province":"Valais",
    "wof:name":"Christian Tscherrig Transporte",
    "wof:placetype":"venue"
},
  "geometry": {"coordinates":[7.999710083,46.327709198],"type":"Point"}
}