{
  "type": "Feature",
  "properties": {
    "iso:country":"CH",
    "sg:address":"Sommergasse 9",
    "sg:city":"Allschwil",
    "sg:orig_category":"Maler U Glasergewerbe",
    "sg:postcode":"4123",
    "sg:province":"Basel-Landschaft",
    "wof:name":"Maleratelier Bruno Schw\u00e4gli",
    "wof:placetype":"venue"
},
  "geometry": {"coordinates":[7.5478219986,47.5524291992],"type":"Point"}
}