{
  "type": "Feature",
  "properties": {
    "addr:full":"Eschenhaustrasse 44 Z\u00fcrich Z\u00fcrich 8053",
    "addr:housenumber":"44",
    "addr:postcode":"8053",
    "addr:street":"Eschenhaustrasse",
    "iso:country":"CH",
    "sg:address":"Eschenhaustrasse 44",
    "sg:city":"Z\u00fcrich",
    "sg:orig_category":"Architektur U Ingenieurb\u00fcros Unternehmensberatung",
    "sg:phone":"+41 32 396 37 14",
    "sg:postcode":"8053",
    "sg:province":"Z\u00fcrich",
    "wof:name":"Proceng Moser Gmbh Ingenieurleistungen Im Verfahrenstechnik U. Anlagenbau Usw.",
    "wof:placetype":"venue"
},
  "geometry": {"coordinates":[7.188642,47.031429],"type":"Point"}
}