{
  "type": "Feature",
  "properties": {
    "iso:country":"CH",
    "sg:address":"3956",
    "sg:city":"Feschel",
    "sg:orig_category":"Sportvereine Sch\u00fctzen",
    "sg:postcode":"3956",
    "sg:province":"Valais",
    "wof:name":"Schiessverein Feschel",
    "wof:placetype":"venue"
},
  "geometry": {"coordinates":[7.6783399582,46.3293609619],"type":"Point"}
}