{
  "type": "Feature",
  "properties": {
    "iso:country":"CH",
    "sg:address":"Rebackerweg 17",
    "sg:city":"Dietlikon",
    "sg:orig_category":"Unclassifiable Establishments",
    "sg:phone":"+41 18883888",
    "sg:postcode":"8305",
    "sg:province":"Z\u00fcrich",
    "wof:name":"Appi-tv, Ren\u00e9 F. Appenzeller",
    "wof:placetype":"venue"
},
  "geometry": {"coordinates":[8.6185684204,47.4284095764],"type":"Point"}
}