{
  "type": "Feature",
  "properties": {
    "iso:country":"CH",
    "sg:address":"R\u00fcti",
    "sg:city":"Oberb\u00fcren",
    "sg:orig_category":"Sonstiger spezialisierter Hoch U Tiefbau",
    "sg:phone":"+41 32 954 15 73",
    "sg:postcode":"9245",
    "sg:province":"St. Gallen",
    "wof:name":"Bubani Livio",
    "wof:placetype":"venue"
},
  "geometry": {"coordinates":[7.0049629211,47.2118835449],"type":"Point"}
}