{
  "type": "Feature",
  "properties": {
    "iso:country":"CH",
    "sg:address":"Neubadstrasse 35",
    "sg:city":"Basel",
    "sg:orig_category":"Arztpraxen",
    "sg:phone":"+41 61 281 36 36",
    "sg:postcode":"4054",
    "sg:province":"Basel-Stadt",
    "wof:name":"Dres Med. Wurmser & Landolt Spezial\u00e4rzte Fmh",
    "wof:placetype":"venue"
},
  "geometry": {"coordinates":[7.572667,47.550117],"type":"Point"}
}