{
  "type": "Feature",
  "properties": {
    "iso:country":"CH",
    "sg:address":"Altstetterstrasse 280",
    "sg:city":"Z\u00fcrich",
    "sg:classifiers":[
        {
            "category":"Professional",
            "subcategory":"Engineering",
            "type":"Services"
        }
    ],
    "sg:phone":"+41 32 351 24 24",
    "sg:postcode":"8047",
    "sg:province":"Z\u00fcrich",
    "sg:tags":[
        "civil",
        "underground"
    ],
    "wof:name":"P. Imperiali + Cie Ag",
    "wof:placetype":"venue"
},
  "geometry": {"coordinates":[7.384865,47.143833],"type":"Point"}
}