{
  "type": "Feature",
  "properties": {
    "iso:country":"CH",
    "sg:address":"Avenue De Lavaux 101",
    "sg:city":"Pully",
    "sg:orig_category":"Fernmeldedienste Softwareentwicklung U beratung",
    "sg:phone":"+41 21 721 10 00",
    "sg:postcode":"1009",
    "sg:province":"Vaud",
    "wof:name":"Acsys Engineering S\u00e0rl",
    "wof:placetype":"venue"
},
  "geometry": {"coordinates":[6.6698861122,46.5085792542],"type":"Point"}
}