{
  "type": "Feature",
  "properties": {
    "iso:country":"CH",
    "sg:address":"Boulevard Du Pont-d'arve 14",
    "sg:city":"Gen\u00e8ve",
    "sg:orig_category":"Herstellung von medizinischen U chirurgischen Ger\u00e4ten sowie orthop\u00e4dischen Vorrichtungen Zahntechnis",
    "sg:phone":"+41 62 873 30 33",
    "sg:postcode":"1205",
    "sg:province":"Gen\u00e8ve",
    "wof:name":"Fps-lotus Dental Ag",
    "wof:placetype":"venue"
},
  "geometry": {"coordinates":[7.9539961815,47.5480613708],"type":"Point"}
}