{
  "type": "Feature",
  "properties": {
    "iso:country":"CH",
    "sg:address":"Dorfstrasse 24",
    "sg:city":"Neuendorf",
    "sg:orig_category":"Herstellung von \u00d6fen U Brennern",
    "sg:postcode":"4623",
    "sg:province":"Solothurn",
    "wof:name":"Max + Martin Strasser, Ofenbau, Wand Und Bodenplattenbel\u00e4ge",
    "wof:placetype":"venue"
},
  "geometry": {"coordinates":[8.8598861694,47.6590652466],"type":"Point"}
}