{
  "type": "Feature",
  "properties": {
    "iso:country":"CH",
    "sg:address":"Ziegelgut 12 7206 Igis. Postfach",
    "sg:city":"Chur",
    "sg:orig_category":"Sportvereine Unihockey",
    "sg:phone":"+41 81 284 77 73",
    "sg:postcode":"7006",
    "sg:province":"Graubunden",
    "wof:name":"Torpedo Chur",
    "wof:placetype":"venue"
},
  "geometry": {"coordinates":[9.5664997101,46.9488105774],"type":"Point"}
}