{
  "type": "Feature",
  "properties": {
    "iso:country":"CH",
    "sg:address":"Rigistrasse 29",
    "sg:city":"Baar",
    "sg:orig_category":"Reiseb\u00fcros U Reiseveranstalter",
    "sg:postcode":"6340",
    "sg:province":"Zug",
    "wof:name":"Ferienclub Luftkurort Mitterfels",
    "wof:placetype":"venue"
},
  "geometry": {"coordinates":[8.5315313339,47.1928482056],"type":"Point"}
}