{
  "type": "Feature",
  "properties": {
    "iso:country":"CH",
    "sg:address":"Schachenm\u00fchlestr. 2",
    "sg:city":"Hubersdorf",
    "sg:orig_category":"Werbung",
    "sg:phone":"+41 32 637 00 77",
    "sg:postcode":"4535",
    "sg:province":"Solothurn",
    "wof:name":"Public Relations Ash Schmid",
    "wof:placetype":"venue"
},
  "geometry": {"coordinates":[7.5898008347,47.2468910217],"type":"Point"}
}