{
  "type": "Feature",
  "properties": {
    "iso:country":"CH",
    "sg:address":"Aeschstrasse 23a",
    "sg:city":"Duggingen",
    "sg:orig_category":"Herstellung von elektrischen Lampen U Leuchten",
    "sg:phone":"+41 61 751 36 31",
    "sg:postcode":"4202",
    "sg:province":"Basel-Landschaft",
    "wof:name":"Db-licht Bizzotto Daniel",
    "wof:placetype":"venue"
},
  "geometry": {"coordinates":[7.6070189476,47.4553604126],"type":"Point"}
}