{
  "type": "Feature",
  "properties": {
    "iso:country":"CH",
    "sg:address":"Gautier Rue Jean-ant.- 5 1201 Gen\u00e8ve. Postfach",
    "sg:city":"Gen\u00e8ve",
    "sg:orig_category":"Herstellung von Duft U K\u00f6rperpflegemitteln",
    "sg:postcode":"1201",
    "sg:province":"Gen\u00e8ve",
    "wof:name":"Green Mail Gmbh Konsumg\u00fcter, Bes. Sch\u00f6nheitsprodukte; Versandhandel",
    "wof:placetype":"venue"
},
  "geometry": {"coordinates":[8.8567247391,47.1963386536],"type":"Point"}
}