{
  "type": "Feature",
  "properties": {
    "iso:country":"CH",
    "sg:address":"Dorfstrasse 27",
    "sg:city":"Baar",
    "sg:orig_category":"M\u00f6belschreinereien",
    "sg:phone":"+41 41 761 21 72",
    "sg:postcode":"6340",
    "sg:province":"Zug",
    "wof:name":"Andermatt Jos.",
    "wof:placetype":"venue"
},
  "geometry": {"coordinates":[8.5243778229,47.1937561035],"type":"Point"}
}