{
  "type": "Feature",
  "properties": {
    "iso:country":"CH",
    "sg:address":"Konstanzerstrasse 74 9512 Rossr\u00fcti. Postfach",
    "sg:city":"Rossr\u00fcti",
    "sg:orig_category":"Linienflugverkehr",
    "sg:postcode":"9512",
    "sg:province":"St. Gallen",
    "wof:name":"B\u00fcckair Ag",
    "wof:placetype":"venue"
},
  "geometry": {"coordinates":[9.0677270889,47.4775276184],"type":"Point"}
}