{
  "type": "Feature",
  "properties": {
    "iso:country":"CH",
    "sg:address":"Jonch\u00e8res Rue Des 31",
    "sg:city":"St-imier",
    "sg:orig_category":"Herstellung von Schrauben, Nieten, Ketten U Federn",
    "sg:phone":"+41 32 941 47 05",
    "sg:postcode":"2610",
    "sg:province":"Bern",
    "wof:name":"Gentili Piero",
    "wof:placetype":"venue"
},
  "geometry": {"coordinates":[6.9945340157,47.1507072449],"type":"Point"}
}