{
  "type": "Feature",
  "properties": {
    "iso:country":"CH",
    "sg:address":"Hauptstr. 51",
    "sg:city":"Kriegstetten",
    "sg:orig_category":"Herstellung von konfektionierten Textilwaren ohne Bekleidung",
    "sg:phone":"+41 32 675 55 46",
    "sg:postcode":"4566",
    "sg:province":"Solothurn",
    "wof:name":"Textilagentur Sulzer Bruno",
    "wof:placetype":"venue"
},
  "geometry": {"coordinates":[7.5976037979,47.1772918701],"type":"Point"}
}