{
  "type": "Feature",
  "properties": {
    "iso:country":"CH",
    "sg:address":"Bildstrasse 1",
    "sg:city":"Amriswil",
    "sg:orig_category":"Non-Classified Establishments",
    "sg:postcode":"8580",
    "sg:province":"Thurgau",
    "wof:name":"Naturprodukte-vertrieb Marlis Schuler",
    "wof:placetype":"venue"
},
  "geometry": {"coordinates":[9.2851696014,47.545463562],"type":"Point"}
}