{
  "type": "Feature",
  "properties": {
    "iso:country":"CH",
    "sg:address":"Vert Chemin 9",
    "sg:city":"Corsier-sur-vevey",
    "sg:orig_category":"Gesundheitswesen",
    "sg:postcode":"1804",
    "sg:province":"Vaud",
    "wof:name":"Etme Ecole De Th\u00e9rapie Manuelles Et Energ\u00e9tiques Monod Et Nicolao",
    "wof:placetype":"venue"
},
  "geometry": {"coordinates":[6.8414001465,46.4704856873],"type":"Point"}
}