{
  "type": "Feature",
  "properties": {
    "iso:country":"CH",
    "sg:address":"Kalabinth 23",
    "sg:city":"Speicher",
    "sg:orig_category":"Unclassifiable Establishments",
    "sg:phone":"+41 71 344 42 60",
    "sg:postcode":"9042",
    "sg:province":"Appenzell Ausserrhoden",
    "wof:name":"Gut Elektrotechnik Speicher",
    "wof:placetype":"venue"
},
  "geometry": {"coordinates":[9.4409503937,47.415271759],"type":"Point"}
}