{
  "type": "Feature",
  "properties": {
    "iso:country":"CH",
    "sg:address":"Birmensdorferstrasse 83 8003 Z\u00fcrich. Postfach",
    "sg:city":"Z\u00fcrich",
    "sg:orig_category":"Detailhandel mit Bekleidung",
    "sg:postcode":"8003",
    "sg:province":"Z\u00fcrich",
    "wof:name":"Homys Street Wear M. Oberer",
    "wof:placetype":"venue"
},
  "geometry": {"coordinates":[8.523558,47.370975],"type":"Point"}
}