{
  "type": "Feature",
  "properties": {
    "iso:country":"CH",
    "sg:address":"Vulkanstrasse 120",
    "sg:city":"Z\u00fcrich",
    "sg:orig_category":"Fernmeldedienste Hardwareberatung",
    "sg:phone":"+41 31 748 03 70",
    "sg:postcode":"8048",
    "sg:province":"Z\u00fcrich",
    "wof:name":"Multimedia Networks Hofer",
    "wof:placetype":"venue"
},
  "geometry": {"coordinates":[7.24391222,46.9091491699],"type":"Point"}
}