{
  "type": "Feature",
  "properties": {
    "iso:country":"CH",
    "sg:address":"Widen",
    "sg:city":"Widen",
    "sg:orig_category":"Irradiation Plants, Technical",
    "sg:phone":"+41 56 633 87 12",
    "sg:postcode":"8967",
    "sg:province":"Aargau",
    "wof:name":"Romy K\u00fchnis Medizintechnik",
    "wof:placetype":"venue"
},
  "geometry": {"coordinates":[8.3616752625,47.3671684265],"type":"Point"}
}