{
  "type": "Feature",
  "properties": {
    "iso:country":"CH",
    "sg:address":"Rue Du Chalet 5",
    "sg:city":"Del\u00e9mont",
    "sg:orig_category":"Sonstige Institutionen des Sozialwesens ohne Beherbergung",
    "sg:phone":"+41 32 422 55 34",
    "sg:postcode":"2800",
    "sg:province":"Jura",
    "wof:name":"Centre De Pu\u00e9riculture Du District De Del\u00e9mont & Environ",
    "wof:placetype":"venue"
},
  "geometry": {"coordinates":[7.3487429619,47.36668396],"type":"Point"}
}