{
  "type": "Feature",
  "properties": {
    "iso:country":"CH",
    "sg:address":"Lisi\u00e8re Chemin De La 3",
    "sg:city":"Lausanne",
    "sg:orig_category":"Unclassifiable Establishments",
    "sg:postcode":"1018",
    "sg:province":"Vaud",
    "wof:name":"Jsr Consulting Sa",
    "wof:placetype":"venue"
},
  "geometry": {"coordinates":[6.634540081,46.5387687683],"type":"Point"}
}