{
  "type": "Feature",
  "properties": {
    "iso:country":"CH",
    "sg:address":"Rheinstrasse 43",
    "sg:city":"Frauenfeld",
    "sg:classifiers":[
        {
            "category":"Restaurant",
            "type":"Food & Drink"
        }
    ],
    "sg:phone":"+41 79 430 20 49",
    "sg:postcode":"8500",
    "sg:province":"Thurgau",
    "wof:name":"Restaurant Einkehr",
    "wof:placetype":"venue"
},
  "geometry": {"coordinates":[8.89108181,47.5598106384],"type":"Point"}
}