{
  "type": "Feature",
  "properties": {
    "iso:country":"CH",
    "sg:address":"Route De La Cornache 1",
    "sg:city":"Matran",
    "sg:orig_category":"HERSTELLUNG VON GER\u00c4TEN DER ELEKTRIZIT\u00c4TSERZEUGUNG, -VERTEILUNG U.\u00c4 Herstellung von elektronischen B",
    "sg:phone":"+41 26 411 22 22",
    "sg:postcode":"1753",
    "sg:province":"Fribourg",
    "wof:name":"Montena Components Sa",
    "wof:placetype":"venue"
},
  "geometry": {"coordinates":[7.087269783,46.783241272],"type":"Point"}
}