{
  "type": "Feature",
  "properties": {
    "iso:country":"CH",
    "sg:address":"R\u00f6telstrasse 135",
    "sg:city":"Z\u00fcrich",
    "sg:orig_category":"Grosshandel mit sonstigen Maschinen U Ausr\u00fcstungen f\u00fcr Industrie, Handel U Schiffahrt",
    "sg:postcode":"8037",
    "sg:province":"Z\u00fcrich",
    "wof:name":"Baumgartner Maschinen Und Fahrzeuge Gmbh",
    "wof:placetype":"venue"
},
  "geometry": {"coordinates":[7.5567731857,46.9140968323],"type":"Point"}
}