{
  "type": "Feature",
  "properties": {
    "iso:country":"CH",
    "sg:address":"Fahracker 11",
    "sg:city":"Fulenbach",
    "sg:orig_category":"Fahrschulen, Flugschulen",
    "sg:phone":"+41 79 211 58 58",
    "sg:postcode":"4629",
    "sg:province":"Solothurn",
    "wof:name":"Thomas Schwaller Autofahrschule",
    "wof:placetype":"venue"
},
  "geometry": {"coordinates":[7.8300671577,47.2683563232],"type":"Point"}
}