{
  "type": "Feature",
  "properties": {
    "iso:country":"CH",
    "sg:address":"Hausmatte 3",
    "sg:city":"M\u00fcswangen",
    "sg:orig_category":"Werbung",
    "sg:postcode":"6289",
    "sg:province":"Luzern",
    "wof:name":"Twm Projekte Gmbh",
    "wof:placetype":"venue"
},
  "geometry": {"coordinates":[8.2890148163,47.2383460999],"type":"Point"}
}