{
  "type": "Feature",
  "properties": {
    "iso:country":"CH",
    "sg:address":"Herdernstrasse 61 8004 Z\u00fcrich. Postfach 2367",
    "sg:city":"Z\u00fcrich",
    "sg:orig_category":"Detailhandel mit Fleisch U Fleischwaren Grosshandel mit Fleisch U Fleischwaren",
    "sg:phone":"+41 14979696",
    "sg:postcode":"8040",
    "sg:province":"Z\u00fcrich",
    "wof:name":"Metzgerei Angst Ag",
    "wof:placetype":"venue"
},
  "geometry": {"coordinates":[8.5068702698,47.3840637207],"type":"Point"}
}