{
  "type": "Feature",
  "properties": {
    "iso:country":"CH",
    "sg:address":"Wohlerstrasse 1",
    "sg:city":"Villmergen",
    "sg:orig_category":"RESTAURANTS: TEA-ROOMS",
    "sg:postcode":"5612",
    "sg:province":"Aargau",
    "wof:name":"Rothenfluh Otto.",
    "wof:placetype":"venue"
},
  "geometry": {"coordinates":[8.2457504272,47.3450469971],"type":"Point"}
}