{
  "type": "Feature",
  "properties": {
    "iso:country":"CH",
    "sg:address":"Zieglerstrasse 29 3007 Bern. Postfach",
    "sg:city":"Bern",
    "sg:orig_category":"Pensionskassen",
    "sg:postcode":"3005",
    "sg:province":"Bern",
    "wof:name":"Pensionskasse Der Schweizerischen Bundesbahnen",
    "wof:placetype":"venue"
},
  "geometry": {"coordinates":[7.4297409058,46.9449501038],"type":"Point"}
}