{
  "type": "Feature",
  "properties": {
    "iso:country":"CH",
    "sg:address":"Seestrasse 26 8880 Walenstadt. Postfach 27",
    "sg:city":"Walenstadt",
    "sg:orig_category":"Architektur U Ingenieurb\u00fcros Architekturb\u00fcros",
    "sg:phone":"+41 81 735 23 64",
    "sg:postcode":"8880",
    "sg:province":"St. Gallen",
    "wof:name":"N. Busa & S. Klingler Architekten Ag",
    "wof:placetype":"venue"
},
  "geometry": {"coordinates":[9.313319,47.124611],"type":"Point"}
}