{
  "type": "Feature",
  "properties": {
    "iso:country":"CH",
    "sg:address":"Lindenstrasse 4a 8483 Kollbrunn. Postfach",
    "sg:city":"Kollbrunn",
    "sg:orig_category":"Wirtschaftspr\u00fcfung, Steuerberatung U Treuhand",
    "sg:phone":"+41 31 951 00 01",
    "sg:postcode":"8483",
    "sg:province":"Z\u00fcrich",
    "wof:name":"Ammann Partner Ag Muri-bern",
    "wof:placetype":"venue"
},
  "geometry": {"coordinates":[7.4800372124,46.9351959229],"type":"Point"}
}