{
  "type": "Feature",
  "properties": {
    "iso:country":"CH",
    "sg:address":"Bundesstrasse 31",
    "sg:city":"Basel",
    "sg:orig_category":"Rechtsberatung",
    "sg:phone":"+41 17370014",
    "sg:postcode":"4054",
    "sg:province":"Basel-Stadt",
    "wof:name":"Fischer Consulting",
    "wof:placetype":"venue"
},
  "geometry": {"coordinates":[8.4445180893,47.3487663269],"type":"Point"}
}