{
  "type": "Feature",
  "properties": {
    "iso:country":"CH",
    "sg:address":"Haldenstrasse 11 6006 Luzern. Postfach",
    "sg:city":"Luzern",
    "sg:orig_category":"Fachdetailhandel in Verkaufsr\u00e4umen",
    "sg:phone":"+41 41513060",
    "sg:postcode":"6003",
    "sg:province":"Luzern",
    "wof:name":"Ehrler Uhren, Inhaber F. Schwizer Uhren, Bijouterieartikel; Verkauf",
    "wof:placetype":"venue"
},
  "geometry": {"coordinates":[8.3141956329,47.0550003052],"type":"Point"}
}