{
  "type": "Feature",
  "properties": {
    "iso:country":"CH",
    "sg:address":"Bahnhofstrasse 2",
    "sg:city":"Herzogenbuchsee",
    "sg:orig_category":"Detailhandel mit fotografischen Artikeln",
    "sg:phone":"+41 62 961 33 73",
    "sg:postcode":"3360",
    "sg:province":"Bern",
    "wof:name":"Urs Semling Fotogesch\u00e4ft",
    "wof:placetype":"venue"
},
  "geometry": {"coordinates":[7.70414114,47.1875076294],"type":"Point"}
}