{
  "type": "Feature",
  "properties": {
    "iso:country":"CH",
    "sg:address":"Via Stazione.",
    "sg:city":"Caslano",
    "sg:orig_category":"Grosshandel mit Holz U Baustoffen",
    "sg:phone":"+41 91 606 38 34",
    "sg:postcode":"6987",
    "sg:province":"Ticino",
    "wof:name":"Marrone Giandomenico",
    "wof:placetype":"venue"
},
  "geometry": {"coordinates":[8.8762979507,45.9770011902],"type":"Point"}
}