{
  "type": "Feature",
  "properties": {
    "iso:country":"CH",
    "sg:address":"Sonnenweg 1",
    "sg:city":"Baltschieder",
    "sg:classifiers":[
        {
            "category":"Professional",
            "subcategory":"Employment Agencies",
            "type":"Services"
        }
    ],
    "sg:phone":"+41 27 945 19 85",
    "sg:postcode":"3937",
    "sg:province":"Valais",
    "sg:tags":[
        "personal",
        "u",
        "stellenvermittlung"
    ],
    "wof:name":"Christoph Bacher Careanesth",
    "wof:placetype":"venue"
},
  "geometry": {"coordinates":[7.8607797623,46.3076553345],"type":"Point"}
}