{
  "type": "Feature",
  "properties": {
    "iso:country":"CH",
    "sg:address":"Oberdorfstrasse 39",
    "sg:city":"N\u00e4fels",
    "sg:orig_category":"Advokaturb\u00fcros Notariate",
    "sg:phone":"+41 55 612 36 66",
    "sg:postcode":"8752",
    "sg:province":"Glarus",
    "wof:name":"Landolt & Partner Advokatur- & Notariatsb\u00fcro",
    "wof:placetype":"venue"
},
  "geometry": {"coordinates":[9.062085,47.095604],"type":"Point"}
}