{
  "type": "Feature",
  "properties": {
    "iso:country":"CH",
    "sg:address":"Calas Avenue 20 1206 Gen\u00e8ve. Postfach",
    "sg:city":"Gen\u00e8ve",
    "sg:orig_category":"Finanzierungsinstitutionen",
    "sg:phone":"+41 16872515",
    "sg:postcode":"1206",
    "sg:province":"Gen\u00e8ve",
    "wof:name":"Perfil Gmbh",
    "wof:placetype":"venue"
},
  "geometry": {"coordinates":[8.7366437912,47.2040557861],"type":"Point"}
}