{
  "type": "Feature",
  "properties": {
    "iso:country":"CH",
    "sg:address":"Waldweg 4",
    "sg:city":"Walperswil",
    "sg:orig_category":"Landesverteidigung, Sozialversicherung \u00d6ffentliche Verwaltung",
    "sg:phone":"+41 32 396 18 13",
    "sg:postcode":"3272",
    "sg:province":"Bern",
    "wof:name":"Zivilschutzstelle Walperswil",
    "wof:placetype":"venue"
},
  "geometry": {"coordinates":[7.2259907722,47.0598220825],"type":"Point"}
}