{
  "type": "Feature",
  "properties": {
    "iso:country":"CH",
    "sg:address":"Affolternstrasse 123 8050 Z\u00fcrich",
    "sg:city":"Zust",
    "sg:orig_category":"Erbringung von Dienstleistungen f\u00fcr Unternehmen",
    "sg:postcode":"50",
    "wof:name":"Metropole Schweiz Ausstellung; Planung, Herst",
    "wof:placetype":"venue"
},
  "geometry": {"coordinates":[8.5494403839,47.413520813],"type":"Point"}
}