{
  "type": "Feature",
  "properties": {
    "iso:country":"CH",
    "sg:address":"Les Jordils",
    "sg:city":"Essertes",
    "sg:orig_category":"Detailhandel Reparatur von Gebrauchsg\u00fctern Vermietung von Gebrauchsg\u00fctern",
    "sg:phone":"+41 21 653 44 60",
    "sg:postcode":"1078",
    "sg:province":"Vaud",
    "wof:name":"Buricod",
    "wof:placetype":"venue"
},
  "geometry": {"coordinates":[6.7857151031,46.5595855713],"type":"Point"}
}