{
  "type": "Feature",
  "properties": {
    "iso:country":"CH",
    "sg:address":"Berneckstrasse 12 9435 Heerbrugg. Postfach",
    "sg:city":"Heerbrugg",
    "sg:orig_category":"Vermietung U Verpachtung von eigenen Immobilien",
    "sg:postcode":"9435",
    "sg:province":"St. Gallen",
    "wof:name":"Aram-immobilien Ag",
    "wof:placetype":"venue"
},
  "geometry": {"coordinates":[9.6257324219,47.4112472534],"type":"Point"}
}