{
  "type": "Feature",
  "properties": {
    "iso:country":"CH",
    "sg:address":"Br\u00fcnigstrasse",
    "sg:city":"Sachseln",
    "sg:orig_category":"Grosshandel mit elektrischen Haushaltsger\u00e4ten Maschinen and Apparate divers Grosshandel",
    "sg:phone":"+41 41 666 70 90",
    "sg:postcode":"6072",
    "sg:province":"Obwalden",
    "wof:name":"Tempco Ag Hotel- & Gastronomiebedarf",
    "wof:placetype":"venue"
},
  "geometry": {"coordinates":[8.2377910614,46.8683547974],"type":"Point"}
}