{
  "type": "Feature",
  "properties": {
    "iso:country":"CH",
    "sg:address":"Dubied Rue Pierre- 20",
    "sg:city":"Couvet",
    "sg:orig_category":"Non-Classified Establishments",
    "sg:postcode":"2108",
    "sg:province":"Neuch\u00e2tel",
    "wof:name":"Couvet Business Center Cbc S.a.",
    "wof:placetype":"venue"
},
  "geometry": {"coordinates":[6.6358728409,46.9240837097],"type":"Point"}
}