{
  "type": "Feature",
  "properties": {
    "iso:country":"CH",
    "sg:address":"Oberdorfstrasse 13 6340 Baar. Postfach 2756",
    "sg:city":"Baar",
    "sg:orig_category":"Grosshandel mit Maschinen U Ausr\u00fcstungen Grosshandel mit sonstigen Halbwaren",
    "sg:phone":"+41 41 766 31 11",
    "sg:postcode":"6342",
    "sg:province":"Zug",
    "wof:name":"S\u00fcdpack Europe Ag",
    "wof:placetype":"venue"
},
  "geometry": {"coordinates":[8.5304355621,47.1960144043],"type":"Point"}
}