{
  "type": "Feature",
  "properties": {
    "iso:country":"CH",
    "sg:address":"Neuweg 22",
    "sg:city":"Beringen",
    "sg:orig_category":"Detailhandel mit elektrischen Haushalts, Radio U Fernsehger\u00e4ten ohne ausgepr\u00e4gten Schwerpunkt",
    "sg:phone":"+41 21 634 34 15",
    "sg:postcode":"8222",
    "sg:province":"Schaffhausen",
    "wof:name":"Bula Sa Radio-t\u00e9l\u00e9vison-\u00e9lectricit\u00e9",
    "wof:placetype":"venue"
},
  "geometry": {"coordinates":[6.5797610283,46.5395202637],"type":"Point"}
}