{
  "type": "Feature",
  "properties": {
    "iso:country":"CH",
    "sg:address":"Hauptstr. 417",
    "sg:city":"Murgenthal",
    "sg:orig_category":"Pensionskassen",
    "sg:phone":"+41 71 925 11 55",
    "sg:postcode":"4853",
    "sg:province":"Aargau",
    "wof:name":"Personalf\u00fcrsorgestiftung Der Larag Ag",
    "wof:placetype":"venue"
},
  "geometry": {"coordinates":[9.0477685928,47.4584350586],"type":"Point"}
}