{
  "type": "Feature",
  "properties": {
    "iso:country":"CH",
    "sg:address":"Route De Ch\u00e9rard 6 1027 Lonay. Postfach",
    "sg:city":"Lausanne",
    "sg:orig_category":"RESTAURANTS: TEA-ROOMS",
    "sg:phone":"+41 32 968 95 55",
    "sg:postcode":"1003",
    "sg:province":"Vaud",
    "wof:name":"Kasikara S\u00e0rl Caf\u00e9-restaurant",
    "wof:placetype":"venue"
},
  "geometry": {"coordinates":[6.8298549652,47.1056976318],"type":"Point"}
}