{
  "type": "Feature",
  "properties": {
    "addr:full":"Fluhmattweg 6 6000 Luzern. Postfach Luzern Luzern 6003",
    "addr:housenumber":"6",
    "addr:postcode":"6000;postfach;6003",
    "addr:street":"Fluhmattweg",
    "iso:country":"CH",
    "sg:address":"Fluhmattweg 6 6000 Luzern. Postfach",
    "sg:city":"Luzern",
    "sg:orig_category":"Architektur U Ingenieurb\u00fcros",
    "sg:phone":"+41 41 410 58 51",
    "sg:postcode":"6003",
    "sg:province":"Luzern",
    "wof:name":"Sch\u00e4rli Architekten Ag Architekturb\u00fcro; Dienstleistungen Usw",
    "wof:placetype":"venue"
},
  "geometry": {"coordinates":[8.309124,47.057568],"type":"Point"}
}