{
  "type": "Feature",
  "properties": {
    "iso:country":"CH",
    "sg:address":"Schlossmattstrasse 14",
    "sg:city":"Thun",
    "sg:classifiers":[
        {
            "category":"Personal",
            "subcategory":"Sauna",
            "type":"Services"
        }
    ],
    "sg:phone":"+41 33 222 44 21",
    "sg:postcode":"3600",
    "sg:province":"Bern",
    "wof:name":"Ren\u00e9 Zurbr\u00fcgg Sauna",
    "wof:placetype":"venue"
},
  "geometry": {"coordinates":[7.6262550354,46.755355835],"type":"Point"}
}