{
  "type": "Feature",
  "properties": {
    "iso:country":"CH",
    "sg:address":"Franzosenstrasse 11",
    "sg:city":"Diessenhofen",
    "sg:orig_category":"Mechanik",
    "sg:phone":"+41 52 657 27 93",
    "sg:postcode":"8253",
    "sg:province":"Thurgau",
    "wof:name":"Keller Robert Funkenerosion",
    "wof:placetype":"venue"
},
  "geometry": {"coordinates":[8.7449588776,47.6892127991],"type":"Point"}
}