{
  "type": "Feature",
  "properties": {
    "iso:country":"CH",
    "sg:address":"Allmendstrasse 32",
    "sg:city":"Fehraltorf",
    "sg:orig_category":"Detailhandel mit M\u00f6beln U Haushaltsgegenst\u00e4nden Grosshandel mit sonstigen Konsumg\u00fctern",
    "sg:phone":"+41 19956369",
    "sg:postcode":"8320",
    "sg:province":"Z\u00fcrich",
    "wof:name":"Trendform Ag",
    "wof:placetype":"venue"
},
  "geometry": {"coordinates":[8.7396020889,47.3936882019],"type":"Point"}
}