{
  "type": "Feature",
  "properties": {
    "iso:country":"CH",
    "sg:address":"Gerbergasse 16",
    "sg:city":"Basel",
    "sg:orig_category":"Detailhandel mit Schuhen U Lederwaren",
    "sg:phone":"+41 61 261 22 03",
    "sg:postcode":"4001",
    "sg:province":"Basel-Stadt",
    "wof:name":"Der Schuh Augstburger & Gschwind Gmbh",
    "wof:placetype":"venue"
},
  "geometry": {"coordinates":[7.5879230499,47.5572853088],"type":"Point"}
}