{
  "type": "Feature",
  "properties": {
    "iso:country":"CH",
    "sg:address":"Schaffhauserstrasse 24",
    "sg:city":"Z\u00fcrich",
    "sg:orig_category":"Detailhandel mit Damenbekleidung Versandhandel",
    "sg:phone":"+41 848 899 120",
    "sg:postcode":"8006",
    "sg:province":"Z\u00fcrich",
    "wof:name":"Cornelia Versand Gmbh Textilien, Pforzheim, Zweigniederlassung Gossau",
    "wof:placetype":"venue"
},
  "geometry": {"coordinates":[9.2549495697,47.4144134521],"type":"Point"}
}