{
  "type": "Feature",
  "properties": {
    "iso:country":"CH",
    "sg:address":"Klarastrasse 17",
    "sg:city":"Allschwil",
    "sg:orig_category":"Maler U Glasergewerbe",
    "sg:phone":"+41 61 481 08 24",
    "sg:postcode":"4123",
    "sg:province":"Basel-Landschaft",
    "wof:name":"Hohl + B\u00fcnzli Gmbh",
    "wof:placetype":"venue"
},
  "geometry": {"coordinates":[7.5350680351,47.5519523621],"type":"Point"}
}