{
  "type": "Feature",
  "properties": {
    "iso:country":"CH",
    "sg:address":"Untere Gasse 22 7000 Chur. Postfach",
    "sg:city":"Chur",
    "sg:orig_category":"Reiseb\u00fcros U Reiseveranstalter",
    "sg:phone":"+41 81 252 97 76",
    "sg:postcode":"7002",
    "sg:province":"Graubunden",
    "wof:name":"Ssr Travel Ag",
    "wof:placetype":"venue"
},
  "geometry": {"coordinates":[9.5298051834,46.8486442566],"type":"Point"}
}