{
  "type": "Feature",
  "properties": {
    "iso:country":"CH",
    "sg:address":"Schlossbergstrasse 3",
    "sg:city":"Winterthur",
    "sg:orig_category":"Arztpraxen",
    "sg:phone":"+41 52 202 00 22",
    "sg:postcode":"8408",
    "sg:province":"Z\u00fcrich",
    "wof:name":"Dr.med.fiona Fr\u00f6hlich Egli Aerztin F\u00fcr Allg.medizin Fmh",
    "wof:placetype":"venue"
},
  "geometry": {"coordinates":[8.695239,47.499668],"type":"Point"}
}