{
  "type": "Feature",
  "properties": {
    "iso:country":"CH",
    "sg:address":"Rue Du Simplon 3",
    "sg:city":"Payerne",
    "sg:orig_category":"Detailhandel mit Fleisch U Fleischwaren",
    "sg:phone":"+41 21 634 08 57",
    "sg:postcode":"1530",
    "sg:province":"Vaud",
    "wof:name":"Robert W\u00e4lti Boucherie-charcuterie",
    "wof:placetype":"venue"
},
  "geometry": {"coordinates":[6.5944008827,46.5342102051],"type":"Point"}
}