{
  "type": "Feature",
  "properties": {
    "iso:country":"CH",
    "sg:address":"Wasserfurristrasse 37 8400 Winterthur. Postfach",
    "sg:city":"Winterthur",
    "sg:orig_category":"Schreib U \u00dcbersetzungsb\u00fcros",
    "sg:postcode":"8406",
    "sg:province":"Z\u00fcrich",
    "wof:name":"Tolltext Translations Tollardo E., Winterthur",
    "wof:placetype":"venue"
},
  "geometry": {"coordinates":[8.7111406326,47.4926261902],"type":"Point"}
}