{
  "type": "Feature",
  "properties": {
    "iso:country":"CH",
    "sg:address":"Unterfeld 1",
    "sg:city":"Malters",
    "sg:orig_category":"Physiotherapie",
    "sg:phone":"+41 41 497 39 12",
    "sg:postcode":"6102",
    "sg:province":"Luzern",
    "wof:name":"Physiotherapie Delta",
    "wof:placetype":"venue"
},
  "geometry": {"coordinates":[8.1795749664,47.0368652344],"type":"Point"}
}