{
  "type": "Feature",
  "properties": {
    "addr:full":"Sp\u00e4tach 15 Erstfeld Uri 6472",
    "addr:housenumber":"15",
    "addr:postcode":"6472",
    "addr:street":"Spaetach;Uri",
    "iso:country":"CH",
    "sg:address":"Sp\u00e4tach 15",
    "sg:city":"Erstfeld",
    "sg:orig_category":"Architekturb\u00fcros",
    "sg:phone":"+41 41 880 07 29",
    "sg:postcode":"6472",
    "sg:province":"Uri",
    "wof:name":"Margrit Baumann Architekturb\u00fcro",
    "wof:placetype":"venue"
},
  "geometry": {"coordinates":[8.643282,46.818539],"type":"Point"}
}