{
  "type": "Feature",
  "properties": {
    "iso:country":"CH",
    "sg:address":"Chemin Des Kybourg 1",
    "sg:city":"Fribourg",
    "sg:orig_category":"Unternehmensberatung",
    "sg:postcode":"1700",
    "sg:province":"Fribourg",
    "wof:name":"Von Der Weid Emmanuel.",
    "wof:placetype":"venue"
},
  "geometry": {"coordinates":[7.1674599648,46.8087387085],"type":"Point"}
}