{
  "type": "Feature",
  "properties": {
    "iso:country":"CH",
    "sg:address":"Via Municipio 9",
    "sg:city":"Muralto",
    "sg:orig_category":"Kinderg\u00e4rten, Vor U Grundschulen Kinderkrippen U horte",
    "sg:phone":"+41 91 744 60 54",
    "sg:postcode":"6600",
    "sg:province":"Ticino",
    "wof:name":"Asilo Nido La Tartaruga Di Soldati Stefania",
    "wof:placetype":"venue"
},
  "geometry": {"coordinates":[8.8062772751,46.1729545593],"type":"Point"}
}