{
  "type": "Feature",
  "properties": {
    "iso:country":"CH",
    "sg:address":"Gorenmattstrasse 2",
    "sg:city":"Binningen",
    "sg:orig_category":"Fahrschulen, Flugschulen",
    "sg:phone":"+41 79 415 34 33",
    "sg:postcode":"4102",
    "sg:province":"Basel-Landschaft",
    "wof:name":"Erich St\u00e4hli Autofahrschule",
    "wof:placetype":"venue"
},
  "geometry": {"coordinates":[7.5728740692,47.5327949524],"type":"Point"}
}