{
  "type": "Feature",
  "properties": {
    "iso:country":"CH",
    "sg:address":"La Monte 2f",
    "sg:city":"Pontenet",
    "sg:orig_category":"Sonstiger spezialisierter Hoch U Tiefbau",
    "sg:phone":"+41 32 492 30 31",
    "sg:postcode":"2733",
    "sg:province":"Bern",
    "wof:name":"Zenger Richard",
    "wof:placetype":"venue"
},
  "geometry": {"coordinates":[7.2546601295,47.2382202148],"type":"Point"}
}