{
  "type": "Feature",
  "properties": {
    "iso:country":"CH",
    "sg:address":"Landstrasse 74",
    "sg:city":"Wettingen",
    "sg:orig_category":"Berufsbildende weiterf\u00fchrende Schulen",
    "sg:phone":"+41 56 426 05 77",
    "sg:postcode":"5430",
    "sg:province":"Aargau",
    "wof:name":"Akuma Fachschule F.massagen",
    "wof:placetype":"venue"
},
  "geometry": {"coordinates":[8.323741,47.46703],"type":"Point"}
}