{
  "type": "Feature",
  "properties": {
    "iso:country":"CH",
    "sg:address":"Frauholzstrasse 11",
    "sg:city":"Steinen",
    "sg:orig_category":"Herstellung von Verbrennungsmotoren U Turbinen ohne Motoren f\u00fcr Luft U Strassenfahrzeuge Mechanische",
    "sg:phone":"+41 41 832 16 22",
    "sg:postcode":"6422",
    "sg:province":"Schwyz",
    "wof:name":"Hans Auf Der Maur-von Rickenbach",
    "wof:placetype":"venue"
},
  "geometry": {"coordinates":[8.6065177917,47.046962738],"type":"Point"}
}