{
  "type": "Feature",
  "properties": {
    "iso:country":"CH",
    "sg:address":"Dennliweg 11",
    "sg:city":"Langenthal",
    "sg:orig_category":"Herstellung von Teppichen",
    "sg:postcode":"4900",
    "sg:province":"Bern",
    "wof:name":"Orientteppich-markt M + L Gmbh",
    "wof:placetype":"venue"
},
  "geometry": {"coordinates":[7.7795982361,47.2031517029],"type":"Point"}
}