{
  "type": "Feature",
  "properties": {
    "iso:country":"CH",
    "sg:address":"Alemannenweg 3",
    "sg:city":"G\u00fcttingen",
    "sg:orig_category":"Interessenvertretungen U sonstige Vereinigungen",
    "sg:phone":"+41 71 695 26 73",
    "sg:postcode":"8594",
    "sg:province":"Thurgau",
    "wof:name":"Thurgauischer Fussballverband",
    "wof:placetype":"venue"
},
  "geometry": {"coordinates":[9.2863750458,47.6058120728],"type":"Point"}
}