{
  "type": "Feature",
  "properties": {
    "iso:country":"CH",
    "sg:address":"Oberdorfstrasse 8",
    "sg:city":"Wigoltingen",
    "sg:classifiers":[
        {
            "category":"Restaurant",
            "type":"Food & Drink"
        }
    ],
    "sg:phone":"+41 71 766 11 59",
    "sg:postcode":"8556",
    "sg:province":"Thurgau",
    "wof:name":"Restaurant Sch\u00e4fli",
    "wof:placetype":"venue"
},
  "geometry": {"coordinates":[9.5427856445,47.2828102112],"type":"Point"}
}