{
  "type": "Feature",
  "properties": {
    "iso:country":"CH",
    "sg:address":"Wolfensbergstrasse 60",
    "sg:city":"Winterthur",
    "sg:orig_category":"Organisationen des Gesundheitswesen",
    "sg:phone":"+41 52 213 73 67",
    "sg:postcode":"8400",
    "sg:province":"Z\u00fcrich",
    "wof:name":"Schweizer Kneippverband",
    "wof:placetype":"venue"
},
  "geometry": {"coordinates":[8.7154216766,47.5127754211],"type":"Point"}
}