{
  "type": "Feature",
  "properties": {
    "iso:country":"CH",
    "sg:address":"Holderweg 2 4710 Balsthal. Postfach 126",
    "sg:city":"Balsthal",
    "sg:orig_category":"Landwirtschaftliche Genossenschaften",
    "sg:phone":"+41 62 391 34 14",
    "sg:postcode":"4710",
    "sg:province":"Solothurn",
    "wof:name":"Landi Thal",
    "wof:placetype":"venue"
},
  "geometry": {"coordinates":[7.6935391426,47.3122291565],"type":"Point"}
}