{
  "type": "Feature",
  "properties": {
    "iso:country":"CH",
    "sg:address":"H\u00f6fli",
    "sg:city":"Weisstannen",
    "sg:classifiers":[
        {
            "category":"Banks & Credit Unions",
            "subcategory":"Bank",
            "type":"Services"
        }
    ],
    "sg:phone":"+41 32 639 16 16",
    "sg:postcode":"7326",
    "sg:province":"St. Gallen",
    "wof:name":"Raiffeisenbank Welschenrohr",
    "wof:placetype":"venue"
},
  "geometry": {"coordinates":[7.468104,47.262352],"type":"Point"}
}