{
  "type": "Feature",
  "properties": {
    "iso:country":"CH",
    "sg:address":"Birmensdorferstrasse 249",
    "sg:city":"Z\u00fcrich",
    "sg:orig_category":"Architektur U Ingenieurb\u00fcros",
    "sg:phone":"+41 14625032",
    "sg:postcode":"8055",
    "sg:province":"Z\u00fcrich",
    "wof:name":"Polymaco Engineering Ag",
    "wof:placetype":"venue"
},
  "geometry": {"coordinates":[8.513025,47.370071],"type":"Point"}
}