{
  "type": "Feature",
  "properties": {
    "iso:country":"CH",
    "sg:address":"Ch. De Montelly",
    "sg:city":"Crassier",
    "sg:orig_category":"Erwachsenenbildung U Unterricht",
    "sg:phone":"+41 22 367 10 75",
    "sg:postcode":"1263",
    "sg:province":"Vaud",
    "wof:name":"Rothuizen Julie",
    "wof:placetype":"venue"
},
  "geometry": {"coordinates":[6.1620798111,46.3764038086],"type":"Point"}
}