{
  "type": "Feature",
  "properties": {
    "iso:country":"CH",
    "sg:address":"Rue Centrale 51 2500 Biel/bienne. Postfach",
    "sg:city":"Biel/bienne",
    "sg:orig_category":"Detailhandel mit Tabakwaren",
    "sg:postcode":"2502",
    "sg:province":"Bern",
    "wof:name":"Calame Camille.",
    "wof:placetype":"venue"
},
  "geometry": {"coordinates":[7.2470898628,47.1365814209],"type":"Point"}
}