{
  "type": "Feature",
  "properties": {
    "iso:country":"CH",
    "sg:address":"Wilerstrasse 144 9620 Lichtensteig. Postfach 342",
    "sg:city":"Wattwil",
    "sg:orig_category":"Grosshandel mit B\u00fcromaschinen U einrichtungen",
    "sg:phone":"+41 71 988 19 37",
    "sg:postcode":"9630",
    "sg:province":"St. Gallen",
    "wof:name":"B\u00fcro Str\u00e4ssle Ag",
    "wof:placetype":"venue"
},
  "geometry": {"coordinates":[9.0877408981,47.3240470886],"type":"Point"}
}