{
  "type": "Feature",
  "properties": {
    "iso:country":"CH",
    "sg:address":"Impasse De La Tuilerie 6",
    "sg:city":"Porrentruy",
    "sg:orig_category":"Sportvereine Eissport Curling",
    "sg:phone":"+41 32 466 46 16",
    "sg:postcode":"2900",
    "sg:province":"Jura",
    "wof:name":"Curling-club Porrentruy-ajoie",
    "wof:placetype":"venue"
},
  "geometry": {"coordinates":[7.0704832077,47.4116516113],"type":"Point"}
}