{
  "type": "Feature",
  "properties": {
    "iso:country":"CH",
    "sg:address":"Aarauerstrasse 119",
    "sg:city":"Olten",
    "sg:orig_category":"Herstellung von Metallkonstruktionen",
    "sg:postcode":"4600",
    "sg:province":"Solothurn",
    "wof:name":"Fassda Ag",
    "wof:placetype":"venue"
},
  "geometry": {"coordinates":[7.9148597717,47.3496665955],"type":"Point"}
}