{
  "type": "Feature",
  "properties": {
    "iso:country":"CH",
    "sg:address":"Vadelsweg 2a",
    "sg:city":"Igis",
    "sg:orig_category":"Architektur U Ingenieurb\u00fcros",
    "sg:phone":"+41 81306440",
    "sg:postcode":"7206",
    "sg:province":"Graubunden",
    "wof:name":"Bonanomi Ag Geologische Beratungen",
    "wof:placetype":"venue"
},
  "geometry": {"coordinates":[9.578597,46.948792],"type":"Point"}
}