{
  "type": "Feature",
  "properties": {
    "addr:full":"Sidlerstrasse 4 Bern Bern 3012",
    "addr:housenumber":"4",
    "addr:postcode":"3012",
    "addr:street":"Sidlerstrasse",
    "iso:country":"CH",
    "sg:address":"Sidlerstrasse 4",
    "sg:city":"Bern",
    "sg:orig_category":"Arztpraxen",
    "sg:phone":"+41 41 850 22 88",
    "sg:postcode":"3012",
    "sg:province":"Bern",
    "wof:name":"Dr.med.siegfried G\u00f6ssi Spezialarzt Fmh",
    "wof:placetype":"venue"
},
  "geometry": {"coordinates":[8.438494,47.082478],"type":"Point"}
}