{
  "type": "Feature",
  "properties": {
    "iso:country":"CH",
    "sg:address":"L\u00f6wenstrasse 16",
    "sg:city":"Z\u00fcrich",
    "sg:orig_category":"Interessenvertretungen",
    "sg:phone":"+41 12116041",
    "sg:postcode":"8001",
    "sg:province":"Z\u00fcrich",
    "wof:name":"Afs Intercultural Programs Switzerland F\u00f6rderung Des Gegenseitigen Verst\u00e4ndnisses Von Menschen Verschiedener Herkunft Usw.",
    "wof:placetype":"venue"
},
  "geometry": {"coordinates":[8.535323143,47.3737716675],"type":"Point"}
}