{
  "type": "Feature",
  "properties": {
    "iso:country":"CH",
    "sg:address":"Mon-repos Avenue 4",
    "sg:city":"Lausanne",
    "sg:orig_category":"Handels-H\u00e4user U Gesellschaften",
    "sg:postcode":"1005",
    "sg:province":"Vaud",
    "wof:name":"Diprotec Ltd, Londres, Succursale De Lausanne",
    "wof:placetype":"venue"
},
  "geometry": {"coordinates":[6.6390562057,46.5195007324],"type":"Point"}
}