{
  "type": "Feature",
  "properties": {
    "iso:country":"CH",
    "sg:address":"Alte Strasse 47",
    "sg:city":"Kestenholz",
    "sg:orig_category":"Mechanik Schlossereien",
    "sg:phone":"+41 62 393 11 20",
    "sg:postcode":"4703",
    "sg:province":"Solothurn",
    "wof:name":"Kissling Gebr\u00fcder Ag",
    "wof:placetype":"venue"
},
  "geometry": {"coordinates":[7.7559781075,47.2804946899],"type":"Point"}
}