{
  "type": "Feature",
  "properties": {
    "iso:country":"CH",
    "sg:address":"Ile-aux-bois Route De L'",
    "sg:city":"Monthey",
    "sg:orig_category":"Herstellung von Anstrichmitteln, Druckfarben U Kitten",
    "sg:phone":"+41 31 985 31 31",
    "sg:postcode":"1870",
    "sg:province":"Valais",
    "wof:name":"Coates Lorilleux",
    "wof:placetype":"venue"
},
  "geometry": {"coordinates":[7.3750510216,46.9228477478],"type":"Point"}
}