{
  "type": "Feature",
  "properties": {
    "iso:country":"CH",
    "sg:address":"6215",
    "sg:city":"Berom\u00fcnster",
    "sg:orig_category":"Innendekorationsateliers",
    "sg:phone":"+41 41 930 22 33",
    "sg:postcode":"6215",
    "sg:province":"Luzern",
    "wof:name":"Markus Brun Wohngestaltung",
    "wof:placetype":"venue"
},
  "geometry": {"coordinates":[8.1919603348,47.2064552307],"type":"Point"}
}