{
  "type": "Feature",
  "properties": {
    "iso:country":"CH",
    "sg:address":"Hauptstrasse Schmitten",
    "sg:city":"Gr\u00fcsch",
    "sg:orig_category":"Detailhandel mit M\u00f6beln Detailhandel mit M\u00f6beln U Haushaltsgegenst\u00e4nden",
    "sg:phone":"+41 81 325 12 42",
    "sg:postcode":"7214",
    "sg:province":"Graubunden",
    "wof:name":"Roffler Robert.",
    "wof:placetype":"venue"
},
  "geometry": {"coordinates":[9.6467075348,46.9807434082],"type":"Point"}
}