{
  "type": "Feature",
  "properties": {
    "iso:country":"CH",
    "sg:address":"Mara\u00eechers Rue Des 8",
    "sg:city":"Gen\u00e8ve",
    "sg:orig_category":"Non-Classified Establishments",
    "sg:postcode":"1205",
    "sg:province":"Gen\u00e8ve",
    "wof:name":"Henry Garcia Gonzalez",
    "wof:placetype":"venue"
},
  "geometry": {"coordinates":[6.1350197792,46.1991271973],"type":"Point"}
}