{
  "type": "Feature",
  "properties": {
    "iso:country":"CH",
    "sg:address":"Schwanenplatz 7",
    "sg:city":"Luzern",
    "sg:orig_category":"Detailhandel mit Lederwaren U Reiseartikeln",
    "sg:phone":"+41 71 222 65 66",
    "sg:postcode":"6004",
    "sg:province":"Luzern",
    "wof:name":"Leder Locher Ag",
    "wof:placetype":"venue"
},
  "geometry": {"coordinates":[9.3776798248,47.4246902466],"type":"Point"}
}