{
  "type": "Feature",
  "properties": {
    "iso:country":"CH",
    "sg:address":"8526",
    "sg:city":"Oberneunforn",
    "sg:orig_category":"Mahl U Sch\u00e4lm\u00fchlen",
    "sg:phone":"+41 52 745 12 20",
    "sg:postcode":"8526",
    "sg:province":"Thurgau",
    "wof:name":"Werner Grunder M\u00fchle",
    "wof:placetype":"venue"
},
  "geometry": {"coordinates":[8.7669696808,47.6066207886],"type":"Point"}
}