{
  "type": "Feature",
  "properties": {
    "iso:country":"CH",
    "sg:address":"Bleicherweg 33",
    "sg:city":"Z\u00fcrich",
    "sg:orig_category":"Unclassifiable Establishments",
    "sg:phone":"+41 12016565",
    "sg:postcode":"8002",
    "sg:province":"Z\u00fcrich",
    "wof:name":"Cb Communications-beteiligungs-ag",
    "wof:placetype":"venue"
},
  "geometry": {"coordinates":[8.5336637497,47.3668365479],"type":"Point"}
}