{
  "type": "Feature",
  "properties": {
    "iso:country":"CH",
    "sg:address":"Leutholdstrasse 4",
    "sg:city":"Biberist",
    "sg:orig_category":"Arztpraxen",
    "sg:phone":"+41 32 672 10 23",
    "sg:postcode":"4562",
    "sg:province":"Solothurn",
    "wof:name":"Dres Med.r. Keller & B. Krebs Spezial\u00e4rzte Fmh",
    "wof:placetype":"venue"
},
  "geometry": {"coordinates":[7.559694,47.182098],"type":"Point"}
}