{
  "type": "Feature",
  "properties": {
    "iso:country":"CH",
    "sg:address":"Gartenstrasse 11",
    "sg:city":"Thalwil",
    "sg:orig_category":"Detailhandel mit Waren verschiedener Art, Hauptrichtung Nahrungsmittel",
    "sg:phone":"+41 17222949",
    "sg:postcode":"8800",
    "sg:province":"Z\u00fcrich",
    "wof:name":"Buytheway.ch Gmbh",
    "wof:placetype":"venue"
},
  "geometry": {"coordinates":[8.5646152496,47.2897491455],"type":"Point"}
}