{
  "type": "Feature",
  "properties": {
    "iso:country":"CH",
    "sg:address":"Hagenwil 33a",
    "sg:city":"W\u00e4ngi",
    "sg:orig_category":"Sonstige mit Sport verbundene T\u00e4tigkeiten",
    "sg:postcode":"9545",
    "sg:province":"Thurgau",
    "wof:name":"La Sella, Sennhauser Gebi",
    "wof:placetype":"venue"
},
  "geometry": {"coordinates":[8.9530849457,47.4967689514],"type":"Point"}
}