{
  "type": "Feature",
  "properties": {
    "iso:country":"CH",
    "sg:address":"Chalet Romang",
    "sg:city":"Saanenm\u00f6ser",
    "sg:orig_category":"Bauspenglerei Dachdeckerei",
    "sg:phone":"+41 27 322 10 24",
    "sg:postcode":"3777",
    "sg:province":"Bern",
    "wof:name":"Vuissoz & Pitteloud Inst.sanitaires & Ferblanterie",
    "wof:placetype":"venue"
},
  "geometry": {"coordinates":[7.359069,46.234547],"type":"Point"}
}