{
  "type": "Feature",
  "properties": {
    "iso:country":"CH",
    "sg:address":"Ra Rungiora",
    "sg:city":"Novaggio",
    "sg:orig_category":"Detailhandel mit Brot, Back U S\u00fcsswaren",
    "sg:phone":"+41 91 606 34 58",
    "sg:postcode":"6986",
    "sg:province":"Ticino",
    "wof:name":"Marc Sciolli Pasticceria",
    "wof:placetype":"venue"
},
  "geometry": {"coordinates":[8.855965,46.010857],"type":"Point"}
}