{
  "type": "Feature",
  "properties": {
    "iso:country":"CH",
    "sg:address":"Arogno Via 3",
    "sg:city":"Bissone",
    "sg:orig_category":"Fachdetailhandel mit pharmazeutischen Produkten",
    "sg:phone":"+41 91 649 55 77",
    "sg:postcode":"6816",
    "sg:province":"Ticino",
    "wof:name":"Sanfarm Sa",
    "wof:placetype":"venue"
},
  "geometry": {"coordinates":[8.9645700455,45.9503746033],"type":"Point"}
}