{
  "type": "Feature",
  "properties": {
    "iso:country":"CH",
    "sg:address":"Metzerlenstrasse 4",
    "sg:city":"Mariastein",
    "sg:classifiers":[
        {
            "category":"Restaurant",
            "type":"Food & Drink"
        }
    ],
    "sg:phone":"+41 61 731 10 28",
    "sg:postcode":"4115",
    "sg:province":"Solothurn",
    "wof:name":"Restaurant Lindenhof",
    "wof:placetype":"venue"
},
  "geometry": {"coordinates":[7.4885540009,47.475063324],"type":"Point"}
}