{
  "type": "Feature",
  "properties": {
    "iso:country":"CH",
    "sg:address":"Soodring 20",
    "sg:city":"Adliswil",
    "sg:orig_category":"Non-Standard Screws",
    "sg:phone":"+41 55 284 64 64",
    "sg:postcode":"8134",
    "sg:province":"Z\u00fcrich",
    "wof:name":"P & S Vorspannsysteme Ag",
    "wof:placetype":"venue"
},
  "geometry": {"coordinates":[8.9725599289,47.2464637756],"type":"Point"}
}