{
  "type": "Feature",
  "properties": {
    "iso:country":"CH",
    "sg:address":"Dorfstrasse 44",
    "sg:city":"Neuendorf",
    "sg:orig_category":"Arztpraxen",
    "sg:phone":"+41 62 398 11 21",
    "sg:postcode":"4623",
    "sg:province":"Solothurn",
    "wof:name":"Dr.med. Michael Wyss Arzt F.allgemeine Medizin Fmh",
    "wof:placetype":"venue"
},
  "geometry": {"coordinates":[7.791593,47.301102],"type":"Point"}
}