{
  "type": "Feature",
  "properties": {
    "addr:full":"Rue De L' Ile Falcon Sierre Valais 3960",
    "addr:postcode":"3960",
    "addr:street":"Rue De L ' Ile Falcon",
    "iso:country":"CH",
    "sg:address":"Rue De L' Ile Falcon",
    "sg:city":"Sierre",
    "sg:classifiers":[
        {
            "category":"Wholesale",
            "subcategory":"Wine & Distilled Alcoholic Beverages",
            "type":"Manufacturing & Wholesale Goods"
        }
    ],
    "sg:phone":"+41 27 451 25 25",
    "sg:postcode":"3960",
    "sg:province":"Valais",
    "sg:tags":[
        "cleaning",
        "bottle"
    ],
    "wof:name":"Pro Uva S.a.",
    "wof:placetype":"venue"
},
  "geometry": {"coordinates":[7.550339,46.286301],"type":"Point"}
}