{
  "type": "Feature",
  "properties": {
    "iso:country":"CH",
    "sg:address":"Hirschmattstrasse 21 6003 Luzern. Postfach",
    "sg:city":"Luzern",
    "sg:orig_category":"Herstellung von konfektionierten Textilwaren ohne Bekleidung",
    "sg:postcode":"6003",
    "sg:province":"Luzern",
    "wof:name":"Kaiser Sonnenstoren Und Beschattungstechnik",
    "wof:placetype":"venue"
},
  "geometry": {"coordinates":[7.4413700104,46.4569587708],"type":"Point"}
}