{
  "type": "Feature",
  "properties": {
    "iso:country":"CH",
    "sg:address":"Centre Artisanal",
    "sg:city":"Remaufens",
    "sg:orig_category":"Herstellung von sonstigen elektrischen Ausr\u00fcstungen",
    "sg:phone":"+41 56 470 24 48",
    "sg:postcode":"1617",
    "sg:province":"Fribourg",
    "wof:name":"Pictronic Ag Elektron. Ger\u00e4te; Handel, Rep. Usw",
    "wof:placetype":"venue"
},
  "geometry": {"coordinates":[8.2935466766,47.449306488],"type":"Point"}
}