{
  "type": "Feature",
  "properties": {
    "addr:full":"Kreuzbuchstrasse 100 Luzern Luzern 6006",
    "addr:housenumber":"100",
    "addr:postcode":"6006",
    "addr:street":"Kreuzbuchstrasse",
    "iso:country":"CH",
    "sg:address":"Kreuzbuchstrasse 100",
    "sg:city":"Luzern",
    "sg:orig_category":"Detailhandel mit Computern U Software Hardwareberatung",
    "sg:phone":"+41 41 372 09 60",
    "sg:postcode":"6006",
    "sg:province":"Luzern",
    "wof:name":"Gist Gmbh Informatik-& Organis.beratung",
    "wof:placetype":"venue"
},
  "geometry": {"coordinates":[8.344289,47.051903],"type":"Point"}
}