{
  "type": "Feature",
  "properties": {
    "iso:country":"CH",
    "sg:address":"Bahnhofstrasse 2",
    "sg:city":"Schwarzenburg",
    "sg:orig_category":"Softwareentwicklung U beratung",
    "sg:postcode":"3150",
    "sg:province":"Bern",
    "wof:name":"Nanoware Gmbh",
    "wof:placetype":"venue"
},
  "geometry": {"coordinates":[7.3417010307,46.81848526],"type":"Point"}
}