{
  "type": "Feature",
  "properties": {
    "iso:country":"CH",
    "sg:address":"Route Cantonale 6",
    "sg:city":"Conthey",
    "sg:orig_category":"Fachdetailhandel mit pharmazeutischen Produkten",
    "sg:phone":"+41 27 346 23 87",
    "sg:postcode":"1964",
    "sg:province":"Valais",
    "wof:name":"Pharmacie Sant\u00e9 Sa",
    "wof:placetype":"venue"
},
  "geometry": {"coordinates":[7.2958788872,46.2251815796],"type":"Point"}
}