{
  "type": "Feature",
  "properties": {
    "iso:country":"CH",
    "sg:address":"Via La Santa 33",
    "sg:city":"Viganello",
    "sg:orig_category":"Betrieb von Taxis",
    "sg:phone":"+41 91 972 22 22",
    "sg:postcode":"6962",
    "sg:province":"Ticino",
    "wof:name":"Aba Taxi",
    "wof:placetype":"venue"
},
  "geometry": {"coordinates":[8.965442,46.012245],"type":"Point"}
}