{
  "type": "Feature",
  "properties": {
    "iso:country":"CH",
    "sg:address":"Hauptstrasse 16 9555 Tobel. Postfach",
    "sg:city":"Tobel",
    "sg:orig_category":"RESTAURANTS: TEA-ROOMS",
    "sg:postcode":"9555",
    "sg:province":"Thurgau",
    "wof:name":"Restaurant Linde Matti + Fischer",
    "wof:placetype":"venue"
},
  "geometry": {"coordinates":[9.0326147079,47.5155639648],"type":"Point"}
}