{
  "type": "Feature",
  "properties": {
    "iso:country":"CH",
    "sg:address":"Nussbaumen",
    "sg:city":"B\u00fclach",
    "sg:classifiers":[
        {
            "category":"Restaurant",
            "type":"Food & Drink"
        }
    ],
    "sg:phone":"+41 18601384",
    "sg:postcode":"8180",
    "sg:province":"Z\u00fcrich",
    "wof:name":"Restaurant Sternen",
    "wof:placetype":"venue"
},
  "geometry": {"coordinates":[8.5456628799,47.5304412842],"type":"Point"}
}