{
  "type": "Feature",
  "properties": {
    "iso:country":"CH",
    "sg:address":"Valentin Rue Du 23 1004 Lausanne. Postfach",
    "sg:city":"Lausanne",
    "sg:orig_category":"Architektur U Ingenieurb\u00fcros",
    "sg:postcode":"1000",
    "sg:province":"Vaud",
    "wof:name":"Riva Jean Bureau Techn.",
    "wof:placetype":"venue"
},
  "geometry": {"coordinates":[6.6319,46.524101],"type":"Point"}
}