{
  "type": "Feature",
  "properties": {
    "iso:country":"CH",
    "sg:address":"Schwalbenstrasse 1 8376 Fischingen. Postfach",
    "sg:city":"Fischingen",
    "sg:orig_category":"Sanit\u00e4r, Heizungs U L\u00fcftungsinstallation",
    "sg:postcode":"8376",
    "sg:province":"Thurgau",
    "wof:name":"Nydegger A. Heizungen",
    "wof:placetype":"venue"
},
  "geometry": {"coordinates":[8.9695882797,47.4361152649],"type":"Point"}
}