{
  "type": "Feature",
  "properties": {
    "iso:country":"CH",
    "sg:address":"Avenue De Lucens 5",
    "sg:city":"Moudon",
    "sg:classifiers":[
        {
            "category":"Education",
            "subcategory":"Vocational School",
            "type":"Public Place"
        }
    ],
    "sg:postcode":"1510",
    "sg:province":"Vaud",
    "sg:tags":[
        "koch-",
        "haushaltschulen"
    ],
    "wof:name":"Ecole M\u00e9nag\u00e8re R\u00e9gionale",
    "wof:placetype":"venue"
},
  "geometry": {"coordinates":[6.802590847,46.6715278625],"type":"Point"}
}