{
  "type": "Feature",
  "properties": {
    "iso:country":"CH",
    "sg:address":"J.j. Wepfer-strasse 12",
    "sg:city":"Schaffhausen",
    "sg:classifiers":[
        {
            "category":"Social Services",
            "subcategory":"Retirement Home",
            "type":"Services"
        }
    ],
    "sg:phone":"+41 52 644 93 10",
    "sg:postcode":"8200",
    "sg:province":"Schaffhausen",
    "sg:tags":[
        "pflegeheime",
        "u",
        "alters"
    ],
    "wof:name":"Kantonales Pflegezentrum",
    "wof:placetype":"venue"
},
  "geometry": {"coordinates":[8.638155,47.712963],"type":"Point"}
}