{
  "type": "Feature",
  "properties": {
    "iso:country":"CH",
    "sg:address":"Grabenstrasse 6",
    "sg:city":"Bischofszell",
    "sg:classifiers":[
        {
            "category":"Restaurant",
            "type":"Food & Drink"
        }
    ],
    "sg:phone":"+41 71 422 13 81",
    "sg:postcode":"9220",
    "sg:province":"Thurgau",
    "wof:name":"Restaurant Rosengarten",
    "wof:placetype":"venue"
},
  "geometry": {"coordinates":[9.2410793304,47.494178772],"type":"Point"}
}