{
  "type": "Feature",
  "properties": {
    "iso:country":"CH",
    "sg:address":"De-candolle Rue 11 1205 Gen\u00e8ve. Postfach",
    "sg:city":"Gen\u00e8ve",
    "sg:orig_category":"Architektur U Ingenieurb\u00fcros",
    "sg:postcode":"1205",
    "sg:province":"Gen\u00e8ve",
    "wof:name":"Irl\u00e9-martin Isabelle, Architecte Epfl-sia",
    "wof:placetype":"venue"
},
  "geometry": {"coordinates":[6.146638,46.197243],"type":"Point"}
}