{
  "type": "Feature",
  "properties": {
    "iso:country":"CH",
    "sg:address":"Hohlstrasse 4",
    "sg:city":"Z\u00fcrich",
    "sg:orig_category":"Detailhandel mit Waren verschiedener Art, Hauptrichtung Nahrungsmittel Fachdetailhandel mit Nahrungs",
    "sg:phone":"+41 12421690",
    "sg:postcode":"8004",
    "sg:province":"Z\u00fcrich",
    "wof:name":"Maria-dolores Turienzo Comestibles Granada",
    "wof:placetype":"venue"
},
  "geometry": {"coordinates":[8.528594017,47.3769264221],"type":"Point"}
}