{
  "type": "Feature",
  "properties": {
    "iso:country":"CH",
    "sg:address":"8416",
    "sg:city":"Flaach",
    "sg:orig_category":"Sportvereine Sch\u00fctzen",
    "sg:phone":"+41 52 318 12 95",
    "sg:postcode":"8416",
    "sg:province":"Z\u00fcrich",
    "wof:name":"Milit\u00e4rschiessverein",
    "wof:placetype":"venue"
},
  "geometry": {"coordinates":[8.6080780029,47.5752487183],"type":"Point"}
}