{
  "type": "Feature",
  "properties": {
    "iso:country":"CH",
    "sg:address":"Wagnerenstrasse 40 3800 Matten B. Interl. Postfach 308",
    "sg:city":"Interlaken",
    "sg:orig_category":"Herstellung von Bier",
    "sg:phone":"+41 33 826 46 46",
    "sg:postcode":"3800",
    "sg:province":"Bern",
    "wof:name":"Rugenbr\u00e4u Ag",
    "wof:placetype":"venue"
},
  "geometry": {"coordinates":[7.8550410271,46.6702232361],"type":"Point"}
}