{
  "type": "Feature",
  "properties": {
    "iso:country":"CH",
    "sg:address":"Talstrasse 83",
    "sg:city":"Z\u00fcrich",
    "sg:orig_category":"Architektur U Ingenieurb\u00fcros",
    "sg:phone":"+41 12213356",
    "sg:postcode":"8001",
    "sg:province":"Z\u00fcrich",
    "wof:name":"Dr.anton E. Schrafl Ingenieurb\u00fcro",
    "wof:placetype":"venue"
},
  "geometry": {"coordinates":[8.533979,47.372093],"type":"Point"}
}