{
  "type": "Feature",
  "properties": {
    "iso:country":"CH",
    "sg:address":"Rue De La Prairie 19",
    "sg:city":"Gen\u00e8ve",
    "sg:orig_category":"Arztpraxen",
    "sg:phone":"+41 22 344 45 45",
    "sg:postcode":"1202",
    "sg:province":"Gen\u00e8ve",
    "wof:name":"Drs M\u00e9d. D. & J. Parsai M\u00e9decins Sp\u00e9cialistes Fmh",
    "wof:placetype":"venue"
},
  "geometry": {"coordinates":[6.134818,46.210056],"type":"Point"}
}