{
  "type": "Feature",
  "properties": {
    "iso:country":"CH",
    "sg:address":"Ringstrasse 14",
    "sg:city":"D\u00fcbendorf",
    "sg:orig_category":"Herstellung von Teppichen Verlegen von Fussboden",
    "sg:phone":"+41 55 410 11 66",
    "sg:postcode":"8600",
    "sg:province":"Z\u00fcrich",
    "wof:name":"Carpet-land (suisse) Sa",
    "wof:placetype":"venue"
},
  "geometry": {"coordinates":[8.7992839813,47.2014427185],"type":"Point"}
}