{
  "type": "Feature",
  "properties": {
    "iso:country":"CH",
    "sg:address":"Bethl\u00e9em Chemin De 8",
    "sg:city":"Fribourg",
    "sg:orig_category":"Unclassifiable Establishments",
    "sg:postcode":"1700",
    "sg:province":"Fribourg",
    "wof:name":"Royal Resorts Holdings Sa",
    "wof:placetype":"venue"
},
  "geometry": {"coordinates":[7.1536831856,46.8037452698],"type":"Point"}
}