{
  "type": "Feature",
  "properties": {
    "iso:country":"CH",
    "sg:address":"Bolligenstrasse 101",
    "sg:city":"Bolligen",
    "sg:classifiers":[
        {
            "category":"Professional",
            "subcategory":"Management & Consulting",
            "type":"Services"
        }
    ],
    "sg:phone":"+41 31 922 13 48",
    "sg:postcode":"3065",
    "sg:province":"Bern",
    "sg:tags":[
        "seminar"
    ],
    "wof:name":"Pma Beratungs Ag",
    "wof:placetype":"venue"
},
  "geometry": {"coordinates":[7.4970860481,46.975315094],"type":"Point"}
}