{
  "type": "Feature",
  "properties": {
    "iso:country":"CH",
    "sg:address":"Spiegelgasse 16",
    "sg:city":"Z\u00fcrich",
    "sg:orig_category":"Erbringung von Dienstleistungen f\u00fcr Unternehmen",
    "sg:phone":"+41 12617842",
    "sg:postcode":"8001",
    "sg:province":"Z\u00fcrich",
    "wof:name":"Zoebeli Bischof Sissi Modekollektionen; Entw., Herst. Usw",
    "wof:placetype":"venue"
},
  "geometry": {"coordinates":[8.5450658798,47.3719024658],"type":"Point"}
}