{
  "type": "Feature",
  "properties": {
    "iso:country":"CH",
    "sg:address":"August Keller-strasse 31",
    "sg:city":"Lenzburg",
    "sg:orig_category":"Immobilienwesen",
    "sg:phone":"+41 71 388 40 80",
    "sg:postcode":"5600",
    "sg:province":"Aargau",
    "wof:name":"Coop Immobilien Ag",
    "wof:placetype":"venue"
},
  "geometry": {"coordinates":[9.2770462036,47.4095420837],"type":"Point"}
}