{
  "type": "Feature",
  "properties": {
    "iso:country":"CH",
    "sg:address":"Echo",
    "sg:city":"Reisiswil",
    "sg:orig_category":"Verarbeitung von Milch Verwertung von Milch",
    "sg:phone":"+41 62 927 13 09",
    "sg:postcode":"4919",
    "sg:province":"Bern",
    "wof:name":"Gerber Bruno",
    "wof:placetype":"venue"
},
  "geometry": {"coordinates":[7.8440308571,47.1630935669],"type":"Point"}
}