{
  "type": "Feature",
  "properties": {
    "iso:country":"CH",
    "sg:address":"Baselstrasse 93",
    "sg:city":"Solothurn",
    "sg:orig_category":"Herstellung von pharmazeutischen Grundstoffen",
    "sg:postcode":"4500",
    "sg:province":"Solothurn",
    "wof:name":"Kingshill Pharmaceutica, Dr Konigsberger William.",
    "wof:placetype":"venue"
},
  "geometry": {"coordinates":[6.2200398445,46.4343109131],"type":"Point"}
}