{
  "type": "Feature",
  "properties": {
    "iso:country":"CH",
    "sg:address":"Via Campagnadorna 6852 Genestrerio. Postfach",
    "sg:city":"Genestrerio",
    "sg:orig_category":"Allgemeiner Hoch U Tiefbau",
    "sg:postcode":"6852",
    "sg:province":"Ticino",
    "wof:name":"Edilbussetti Sagl",
    "wof:placetype":"venue"
},
  "geometry": {"coordinates":[8.967311,45.85733],"type":"Point"}
}