{
  "type": "Feature",
  "properties": {
    "iso:country":"CH",
    "sg:address":"Sonnental",
    "sg:city":"Muolen",
    "sg:orig_category":"Instandhaltung U Reparatur von Automobilen",
    "sg:postcode":"9313",
    "sg:province":"St. Gallen",
    "wof:name":"Gerry's Garage Spiess G.",
    "wof:placetype":"venue"
},
  "geometry": {"coordinates":[8.6595315933,47.7849121094],"type":"Point"}
}