{
  "type": "Feature",
  "properties": {
    "iso:country":"CH",
    "sg:address":"Meyrin Route De 372",
    "sg:city":"Meyrin",
    "sg:orig_category":"Tankstellen",
    "sg:postcode":"1217",
    "sg:province":"Gen\u00e8ve",
    "wof:name":"Esso Meyrin, Juchler Bernd",
    "wof:placetype":"venue"
},
  "geometry": {"coordinates":[6.0722160339,46.2284431458],"type":"Point"}
}