{
  "type": "Feature",
  "properties": {
    "iso:country":"CH",
    "sg:address":"Corso San Gottardo 32",
    "sg:city":"Chiasso",
    "sg:orig_category":"Verwaltung von Immobilien",
    "sg:postcode":"6830",
    "sg:province":"Ticino",
    "wof:name":"Bf Verwaltungs Gmbh",
    "wof:placetype":"venue"
},
  "geometry": {"coordinates":[9.0442562103,47.458896637],"type":"Point"}
}