{
  "type": "Feature",
  "properties": {
    "iso:country":"CH",
    "sg:address":"R\u00e4mistrasse 5 8001 Z\u00fcrich. Postfach",
    "sg:city":"Z\u00fcrich",
    "sg:orig_category":"Advokaturb\u00fcros",
    "sg:phone":"+41 12522008",
    "sg:postcode":"8024",
    "sg:province":"Z\u00fcrich",
    "wof:name":"Dr.iur. Roland Ilg Advokaturb\u00fcro",
    "wof:placetype":"venue"
},
  "geometry": {"coordinates":[8.545605,47.367832],"type":"Point"}
}