{
  "type": "Feature",
  "properties": {
    "addr:full":"8645 Jona St. Gallen 8645",
    "addr:postcode":"8645;8645",
    "addr:street":"Jona",
    "iso:country":"CH",
    "sg:address":"8645",
    "sg:city":"Jona",
    "sg:orig_category":"Bezirks, Sekundar, Realschulen, Oberstufe der Primarschulen",
    "sg:phone":"+41 55 212 18 89",
    "sg:postcode":"8645",
    "sg:province":"St. Gallen",
    "wof:name":"Sekundarschule Schulhaus Bollwies",
    "wof:placetype":"venue"
},
  "geometry": {"coordinates":[8.84524,47.229691],"type":"Point"}
}