{
  "type": "Feature",
  "properties": {
    "iso:country":"CH",
    "sg:address":"2103",
    "sg:city":"Noiraigue",
    "sg:orig_category":"Herstellung von Uhren",
    "sg:postcode":"2103",
    "sg:province":"Neuch\u00e2tel",
    "wof:name":"Hamel Fr\u00e8res, H.-l., G. Hamel & Cie Successeurs",
    "wof:placetype":"venue"
},
  "geometry": {"coordinates":[6.7189311981,46.9565238953],"type":"Point"}
}