{
  "type": "Feature",
  "properties": {
    "iso:country":"CH",
    "sg:address":"Talwisstrasse 184",
    "sg:city":"Aathal-seegr\u00e4ben",
    "sg:orig_category":"Fachdetailhandel in Verkaufsr\u00e4umen",
    "sg:phone":"+41 19327639",
    "sg:postcode":"8607",
    "sg:province":"Z\u00fcrich",
    "wof:name":"Waterworld Gmbh",
    "wof:placetype":"venue"
},
  "geometry": {"coordinates":[8.7684850693,47.3358840942],"type":"Point"}
}