{
  "type": "Feature",
  "properties": {
    "addr:full":"Schupfarterstrasse 15 Eiken Aargau 5074",
    "addr:housenumber":"15",
    "addr:postcode":"5074",
    "addr:street":"Schupfarterstrasse",
    "iso:country":"CH",
    "sg:address":"Schupfarterstrasse 15",
    "sg:city":"Eiken",
    "sg:orig_category":"Allgemeiner Hoch U Tiefbau",
    "sg:postcode":"5074",
    "sg:province":"Aargau",
    "wof:name":"Baugesch\u00e4ft Bruno Dinkel.",
    "wof:placetype":"venue"
},
  "geometry": {"coordinates":[7.988266,47.53083],"type":"Point"}
}