{
  "type": "Feature",
  "properties": {
    "addr:full":"Dorfstr. 34 Trubschachen Bern 3555",
    "addr:housenumber":"34",
    "addr:postcode":"3555",
    "addr:street":"Dorfstr.",
    "iso:country":"CH",
    "sg:address":"Dorfstr. 34",
    "sg:city":"Trubschachen",
    "sg:classifiers":[
        {
            "category":"Transit Center",
            "subcategory":"Freight",
            "type":"Transportation"
        }
    ],
    "sg:phone":"+41 32 752 32 32",
    "sg:postcode":"3555",
    "sg:province":"Bern",
    "sg:tags":[
        "metallurgy",
        "pipe",
        "metalworking",
        "sheet"
    ],
    "wof:name":"Lamineries Matthey Sa",
    "wof:placetype":"venue"
},
  "geometry": {"coordinates":[7.090176,47.063038],"type":"Point"}
}