{
  "type": "Feature",
  "properties": {
    "iso:country":"CH",
    "sg:address":"Kleenbrunnenstrasse 4",
    "sg:city":"H\u00e4gglingen",
    "sg:orig_category":"Grosshandel mit lebenden Tieren",
    "sg:phone":"+41 56 624 11 72",
    "sg:postcode":"5607",
    "sg:province":"Aargau",
    "wof:name":"Siegfried Krummenacher Viehhandel",
    "wof:placetype":"venue"
},
  "geometry": {"coordinates":[8.247177124,47.3934326172],"type":"Point"}
}