{
  "type": "Feature",
  "properties": {
    "iso:country":"CH",
    "sg:address":"Sch\u00fctzenmattweg",
    "sg:city":"Olten",
    "sg:orig_category":"Mit Sport verbundene T\u00e4tigkeiten",
    "sg:phone":"+41 62 212 75 98",
    "sg:postcode":"4600",
    "sg:province":"Solothurn",
    "wof:name":"Reitbahngesellschaft Olten Reitbahn",
    "wof:placetype":"venue"
},
  "geometry": {"coordinates":[7.9028921127,47.3489646912],"type":"Point"}
}