{
  "type": "Feature",
  "properties": {
    "iso:country":"CH",
    "sg:address":"Ackerstrasse 50",
    "sg:city":"Uster",
    "sg:classifiers":[
        {
            "category":"Banks & Credit Unions",
            "subcategory":"Investment Brokerage",
            "type":"Services"
        }
    ],
    "sg:phone":"+41 19449000",
    "sg:postcode":"8610",
    "sg:province":"Z\u00fcrich",
    "sg:tags":[
        "bearing",
        "ball"
    ],
    "wof:name":"Berani Kugellager Ag",
    "wof:placetype":"venue"
},
  "geometry": {"coordinates":[8.706922,47.356689],"type":"Point"}
}