{
  "type": "Feature",
  "properties": {
    "iso:country":"CH",
    "sg:address":"Finkenhubelweg 11 3012 Bern. Postfach 8275",
    "sg:city":"Bern",
    "sg:orig_category":"Wirtschaftsverb\u00e4nde Verkehrswesen, Tourismus",
    "sg:phone":"+41 31 359 23 33",
    "sg:postcode":"3001",
    "sg:province":"Bern",
    "wof:name":"Seilbahnen Schweiz Sbs",
    "wof:placetype":"venue"
},
  "geometry": {"coordinates":[7.4551401138,46.9413719177],"type":"Point"}
}