{
  "type": "Feature",
  "properties": {
    "iso:country":"CH",
    "sg:address":"Im Budler 13",
    "sg:city":"Lupsingen",
    "sg:orig_category":"Politische Parteien SVP",
    "sg:postcode":"4419",
    "sg:province":"Basel-Landschaft",
    "wof:name":"Svp Ortspartei Brittnau",
    "wof:placetype":"venue"
},
  "geometry": {"coordinates":[7.6883239746,47.4479293823],"type":"Point"}
}