{
  "type": "Feature",
  "properties": {
    "iso:country":"CH",
    "sg:address":"Fuhrenstrasse 7",
    "sg:city":"Adelboden",
    "sg:classifiers":[
        {
            "category":"Travel",
            "subcategory":"Hotels & Motels",
            "type":"Entertainment"
        }
    ],
    "sg:phone":"+41 33 673 10 60",
    "sg:postcode":"3715",
    "sg:province":"Bern",
    "sg:tags":[
        "hotels",
        "mit",
        "restaurant"
    ],
    "wof:name":"Hotel Sonne",
    "wof:placetype":"venue"
},
  "geometry": {"coordinates":[7.5578670502,46.4822921753],"type":"Point"}
}