{
  "type": "Feature",
  "properties": {
    "iso:country":"CH",
    "sg:address":"Vogelsangweg 32",
    "sg:city":"Herzogenbuchsee",
    "sg:classifiers":[
        {
            "category":"Insurance",
            "subcategory":"Insurance Agent",
            "type":"Services"
        }
    ],
    "sg:phone":"+41 33 951 28 25",
    "sg:postcode":"3360",
    "sg:province":"Bern",
    "sg:tags":[
        "versicherungsagenturen",
        "-broker"
    ],
    "wof:name":"Emmentalische Mobiliarversich. Agentur Brienz",
    "wof:placetype":"venue"
},
  "geometry": {"coordinates":[8.0484256744,46.7546234131],"type":"Point"}
}