{
  "type": "Feature",
  "properties": {
    "iso:country":"CH",
    "sg:address":"Corso San Gottardo 14",
    "sg:city":"Chiasso",
    "sg:orig_category":"Unclassifiable Establishments",
    "sg:postcode":"6830",
    "sg:province":"Ticino",
    "wof:name":"Crociana Sa",
    "wof:placetype":"venue"
},
  "geometry": {"coordinates":[9.0321817398,45.8331260681],"type":"Point"}
}