{
  "type": "Feature",
  "properties": {
    "addr:full":"Boulevard De La Tour 4 Gen\u00e8ve Gen\u00e8ve 1205",
    "addr:housenumber":"4",
    "addr:postcode":"1205",
    "addr:street":"Boulevard De La Tour",
    "iso:country":"CH",
    "sg:address":"Boulevard De La Tour 4",
    "sg:city":"Gen\u00e8ve",
    "sg:orig_category":"Arztpraxen",
    "sg:phone":"+41 22 320 41 33",
    "sg:postcode":"1205",
    "sg:province":"Gen\u00e8ve",
    "wof:name":"Dr M\u00e9d. Anne-lise Bersier M\u00e9decin Sp\u00e9cialiste Fmh",
    "wof:placetype":"venue"
},
  "geometry": {"coordinates":[6.147167,46.195461],"type":"Point"}
}