{
  "type": "Feature",
  "properties": {
    "iso:country":"CH",
    "sg:address":"Unterdorfstrasse 21-23 9116 Wolfertswil. Postfach",
    "sg:city":"Wolfertswil",
    "sg:orig_category":"Herstellung von Hebezeugen U F\u00f6rdermitteln",
    "sg:phone":"+41 71 394 11 00",
    "sg:postcode":"9116",
    "sg:province":"St. Gallen",
    "wof:name":"As Aufz\u00fcge Ag",
    "wof:placetype":"venue"
},
  "geometry": {"coordinates":[9.1841096878,47.395690918],"type":"Point"}
}