{
  "type": "Feature",
  "properties": {
    "iso:country":"CH",
    "sg:address":"Bernstrasse 6",
    "sg:city":"Flamatt",
    "sg:orig_category":"Tankstellen",
    "sg:phone":"+41 31 741 13 73",
    "sg:postcode":"3175",
    "sg:province":"Fribourg",
    "wof:name":"Shell Flamatt Krainer-da-rugna Gmbh",
    "wof:placetype":"venue"
},
  "geometry": {"coordinates":[7.3118801117,46.8897476196],"type":"Point"}
}