{
  "type": "Feature",
  "properties": {
    "iso:country":"CH",
    "sg:address":"Rue Centrale 27",
    "sg:city":"Bex",
    "sg:orig_category":"Reiseb\u00fcros U Reiseveranstalter",
    "sg:phone":"+41 24 463 31 75",
    "sg:postcode":"1880",
    "sg:province":"Vaud",
    "wof:name":"Caravelle Alves Carlos",
    "wof:placetype":"venue"
},
  "geometry": {"coordinates":[7.0153360367,46.2507781982],"type":"Point"}
}