{
  "type": "Feature",
  "properties": {
    "iso:country":"CH",
    "sg:address":"Rathausplatz",
    "sg:city":"Arth",
    "sg:orig_category":"Non-Classified Establishments",
    "sg:postcode":"6415",
    "sg:province":"Schwyz",
    "wof:name":"K\u00fcmin F.",
    "wof:placetype":"venue"
},
  "geometry": {"coordinates":[8.5230588913,47.0629692078],"type":"Point"}
}