{
  "type": "Feature",
  "properties": {
    "iso:country":"CH",
    "sg:address":"Neudorfstr. 33",
    "sg:city":"Horgen",
    "sg:orig_category":"Sonstige mit der Informatik verbundene T\u00e4tigkeiten",
    "sg:phone":"+41 17259022",
    "sg:postcode":"8810",
    "sg:province":"Z\u00fcrich",
    "wof:name":"Roth Mario Edv-beratung",
    "wof:placetype":"venue"
},
  "geometry": {"coordinates":[8.6021413803,47.2580680847],"type":"Point"}
}