{
  "type": "Feature",
  "properties": {
    "iso:country":"CH",
    "sg:address":"Via Industria 17",
    "sg:city":"Muzzano",
    "sg:classifiers":[
        {
            "category":"Manufacturing",
            "subcategory":"Printing",
            "type":"Manufacturing & Wholesale Goods"
        }
    ],
    "sg:phone":"+41 31 352 43 44",
    "sg:postcode":"6933",
    "sg:province":"Ticino",
    "sg:tags":[
        "publishing"
    ],
    "wof:name":"Geiger Ag",
    "wof:placetype":"venue"
},
  "geometry": {"coordinates":[4.4734759331,51.8922538757],"type":"Point"}
}