{
  "type": "Feature",
  "properties": {
    "iso:country":"CH",
    "sg:address":"Rue Des Vermondins 18",
    "sg:city":"Boudry",
    "sg:classifiers":[
        {
            "category":"Education",
            "subcategory":"Library",
            "type":"Public Place"
        }
    ],
    "sg:phone":"+41 32 842 10 41",
    "sg:postcode":"2017",
    "sg:province":"Neuch\u00e2tel",
    "sg:tags":[
        "u",
        "bibliotheken",
        "archive"
    ],
    "wof:name":"Biblioth\u00e8que Paroissiale",
    "wof:placetype":"venue"
},
  "geometry": {"coordinates":[6.832775,46.949818],"type":"Point"}
}