{
  "type": "Feature",
  "properties": {
    "iso:country":"CH",
    "sg:address":"Gr\u00fcnaustrasse 7",
    "sg:city":"Speicherschwendi",
    "sg:orig_category":"Grosshandel mit Holz U Baustoffen Sonstiger Detailhandel mit Metallwaren, Anstrichmitteln, Glaswaren",
    "sg:phone":"+41 71 344 31 20",
    "sg:postcode":"9037",
    "sg:province":"Appenzell Ausserrhoden",
    "wof:name":"Pagel Baustoffe, Willi N\u00fcesch",
    "wof:placetype":"venue"
},
  "geometry": {"coordinates":[9.4394645691,47.4247245789],"type":"Point"}
}