{
  "type": "Feature",
  "properties": {
    "iso:country":"CH",
    "sg:address":"Bergi\u00e8res Avenue 6 1004 Lausanne. Postfach",
    "sg:city":"Lausanne",
    "sg:orig_category":"Interessenvertretungen",
    "sg:phone":"+41 21 643 24 05",
    "sg:postcode":"1003",
    "sg:province":"Vaud",
    "wof:name":"Organisation Internationale Pour La Reconversion Des Danseurs Professionnels",
    "wof:placetype":"venue"
},
  "geometry": {"coordinates":[6.6257548332,46.5274581909],"type":"Point"}
}