{
  "type": "Feature",
  "properties": {
    "iso:country":"CH",
    "sg:address":"3512",
    "sg:city":"Walkringen",
    "sg:orig_category":"Religi\u00f6se Vereinigungen divers",
    "sg:phone":"+41 31 701 22 88",
    "sg:postcode":"3512",
    "sg:province":"Bern",
    "wof:name":"Cvjm",
    "wof:placetype":"venue"
},
  "geometry": {"coordinates":[7.6175780296,46.9424552917],"type":"Point"}
}