{
  "type": "Feature",
  "properties": {
    "iso:country":"CH",
    "sg:address":"Eichstrasse 31",
    "sg:city":"Cham",
    "sg:orig_category":"Softwareentwicklung U beratung",
    "sg:phone":"+41 41 781 31 58",
    "sg:postcode":"6330",
    "sg:province":"Zug",
    "wof:name":"Phirents Gmbh",
    "wof:placetype":"venue"
},
  "geometry": {"coordinates":[8.4716463089,47.1838912964],"type":"Point"}
}