{
  "type": "Feature",
  "properties": {
    "iso:country":"CH",
    "sg:address":"Rue Rainer Maria Rilke 4 3960 Sierre. Postfach",
    "sg:city":"Sierre",
    "sg:orig_category":"Vermittlung von Immobilien Verwaltung von Immobilien",
    "sg:phone":"+41 26 919 04 44",
    "sg:postcode":"3960",
    "sg:province":"Valais",
    "wof:name":"R\u00e9gie Bulle Sa Agence Immobili\u00e8re",
    "wof:placetype":"venue"
},
  "geometry": {"coordinates":[7.0555691719,46.6174583435],"type":"Point"}
}