{
  "type": "Feature",
  "properties": {
    "iso:country":"CH",
    "sg:address":"Bergstrasse 2",
    "sg:city":"Luzern",
    "sg:orig_category":"Reinigungsgewerbe Sonstiges Reinigungsgewerbe",
    "sg:phone":"+41 26 663 43 41",
    "sg:postcode":"6004",
    "sg:province":"Luzern",
    "wof:name":"Burri D\u00e9sinfection",
    "wof:placetype":"venue"
},
  "geometry": {"coordinates":[6.8482789993,46.8487930298],"type":"Point"}
}