{
  "type": "Feature",
  "properties": {
    "addr:full":"Hauptstrasse 1 Erlen Thurgau 8586",
    "addr:housenumber":"1",
    "addr:postcode":"8586",
    "addr:street":"Hauptstrasse",
    "iso:country":"CH",
    "sg:address":"Hauptstrasse 1",
    "sg:city":"Erlen",
    "sg:classifiers":[
        {
            "category":"Building & Trades",
            "subcategory":"Construction",
            "type":"Services"
        }
    ],
    "sg:phone":"+41 71 411 79 54",
    "sg:postcode":"8586",
    "sg:province":"Thurgau",
    "sg:tags":[
        "installation",
        "air-conditioning",
        "system"
    ],
    "wof:name":"Gral Montagen Ren\u00e9 Graf",
    "wof:placetype":"venue"
},
  "geometry": {"coordinates":[9.24426,47.545952],"type":"Point"}
}