{
  "type": "Feature",
  "properties": {
    "iso:country":"CH",
    "sg:address":"Bahnstrasse 23 4932 Lotzwil. Postfach",
    "sg:city":"Lotzwil",
    "sg:orig_category":"Herstellung von Drahtwaren",
    "sg:postcode":"4932",
    "sg:province":"Bern",
    "wof:name":"Drahterosion Aebi E. & Partner Drahterodieren In Lohnarbeit. Maschinen U. Zubeh\u00f6r; Handel Usw",
    "wof:placetype":"venue"
},
  "geometry": {"coordinates":[7.7848229408,47.1971282959],"type":"Point"}
}