{
  "type": "Feature",
  "properties": {
    "iso:country":"CH",
    "sg:address":"Hauptstrasse 135 8274 T\u00e4gerwilen. Postfach",
    "sg:city":"T\u00e4gerwilen",
    "sg:orig_category":"G\u00fcterbef\u00f6rderung im Strassenverkehr",
    "sg:phone":"+41 71 669 28 28",
    "sg:postcode":"8274",
    "sg:province":"Thurgau",
    "wof:name":"Metz J\u00fcrgen Internationale Textilspedition Ag",
    "wof:placetype":"venue"
},
  "geometry": {"coordinates":[9.1484060287,47.652015686],"type":"Point"}
}