{
  "type": "Feature",
  "properties": {
    "iso:country":"CH",
    "sg:address":"Mayenfelserstrasse 15",
    "sg:city":"Pratteln",
    "sg:orig_category":"P\u00e9dicure",
    "sg:phone":"+41 61 821 22 50",
    "sg:postcode":"4133",
    "sg:province":"Basel-Landschaft",
    "wof:name":"Nadia Hersberger P\u00e9dicure",
    "wof:placetype":"venue"
},
  "geometry": {"coordinates":[7.6935830116,47.5163421631],"type":"Point"}
}