{
  "type": "Feature",
  "properties": {
    "iso:country":"CH",
    "sg:address":"Ch. Du Pr\u00e9-bouvier 10",
    "sg:city":"Satigny",
    "sg:orig_category":"Druck ohne Zeitungsdruck",
    "sg:postcode":"1242",
    "sg:province":"Gen\u00e8ve",
    "wof:name":"Irb, R. & D. Bournonville",
    "wof:placetype":"venue"
},
  "geometry": {"coordinates":[6.0564541817,46.2243614197],"type":"Point"}
}