{
  "type": "Feature",
  "properties": {
    "iso:country":"CH",
    "sg:address":"Schneidergasse 28",
    "sg:city":"Basel",
    "sg:orig_category":"Erbringung von Dienstleistungen f\u00fcr Unternehmen",
    "sg:phone":"+41 62 765 70 40",
    "sg:postcode":"4051",
    "sg:province":"Basel-Stadt",
    "wof:name":"Stauffis Messebau",
    "wof:placetype":"venue"
},
  "geometry": {"coordinates":[8.2008571625,47.2762947083],"type":"Point"}
}