{
  "type": "Feature",
  "properties": {
    "iso:country":"CH",
    "sg:address":"Buochserstrasse 25 6370 Stans. Postfach",
    "sg:city":"Stans",
    "sg:orig_category":"Interessenvertretungen",
    "sg:phone":"+41 41 610 22 15",
    "sg:postcode":"6370",
    "sg:province":"Nidwalden",
    "wof:name":"Stiftung Dr. Josef Und Berta Odermatt-h\u00fcsler",
    "wof:placetype":"venue"
},
  "geometry": {"coordinates":[8.3713779449,46.9601821899],"type":"Point"}
}