{
  "type": "Feature",
  "properties": {
    "addr:full":"Marktgasse 41 Winterthur Z\u00fcrich 8400",
    "addr:housenumber":"41",
    "addr:postcode":"8400",
    "addr:street":"Marktgasse",
    "iso:country":"CH",
    "sg:address":"Marktgasse 41",
    "sg:city":"Winterthur",
    "sg:orig_category":"Arztpraxen",
    "sg:phone":"+41 52 212 88 81",
    "sg:postcode":"8400",
    "sg:province":"Z\u00fcrich",
    "wof:name":"Dr.med.mario Antonio Largo Spezialarzt Fmh",
    "wof:placetype":"venue"
},
  "geometry": {"coordinates":[8.727981,47.499416],"type":"Point"}
}