{
  "type": "Feature",
  "properties": {
    "iso:country":"CH",
    "sg:address":"Rainstrasse 33",
    "sg:city":"Unter\u00e4geri",
    "sg:orig_category":"Instandhaltung U Reparatur von Automobilen",
    "sg:phone":"+41 41 750 19 08",
    "sg:postcode":"6314",
    "sg:province":"Zug",
    "wof:name":"Hans Hugener Garage & Carrosserie",
    "wof:placetype":"venue"
},
  "geometry": {"coordinates":[8.5733003616,47.135093689],"type":"Point"}
}