{
  "type": "Feature",
  "properties": {
    "iso:country":"CH",
    "sg:address":"Frankengasse 16",
    "sg:city":"Z\u00fcrich",
    "sg:orig_category":"Herstellung von Musikinstrumenten",
    "sg:phone":"+41 12516668",
    "sg:postcode":"8001",
    "sg:province":"Z\u00fcrich",
    "wof:name":"Peter Westermann Geigenbauwerkst\u00e4tte",
    "wof:placetype":"venue"
},
  "geometry": {"coordinates":[8.5458402634,47.3697357178],"type":"Point"}
}