{
  "type": "Feature",
  "properties": {
    "iso:country":"CH",
    "sg:address":"Gare Cff",
    "sg:city":"St-maurice",
    "sg:classifiers":[
        {
            "category":"Education",
            "subcategory":"Library",
            "type":"Public Place"
        }
    ],
    "sg:phone":"+41 24 485 16 16",
    "sg:postcode":"1890",
    "sg:province":"Valais",
    "sg:tags":[
        "u",
        "bibliotheken",
        "archive"
    ],
    "wof:name":"Naville Sa Biblioth\u00e8que De La Gare",
    "wof:placetype":"venue"
},
  "geometry": {"coordinates":[7.004139,46.216965],"type":"Point"}
}