{
  "type": "Feature",
  "properties": {
    "iso:country":"CH",
    "sg:address":"Chemin De Maillefer 47",
    "sg:city":"Mont-sur-lausanne",
    "sg:orig_category":"Malerei Stukkateurgewerbe, Gipserei U Verputzerei",
    "sg:phone":"+41 41 497 26 09",
    "sg:postcode":"1052",
    "sg:province":"Vaud",
    "wof:name":"Josef Zihlmann Jun. Maler-& Gipsergesch\u00e4ft",
    "wof:placetype":"venue"
},
  "geometry": {"coordinates":[8.1827249527,47.0368156433],"type":"Point"}
}