{
  "type": "Feature",
  "properties": {
    "iso:country":"CH",
    "sg:address":"Untere Steingrubenstrasse 19",
    "sg:city":"Solothurn",
    "sg:orig_category":"Gartenbau Landschaftsplanungsb\u00fcros U Gartenarchitekturb\u00fcros",
    "sg:phone":"+41 32 622 36 67",
    "sg:postcode":"4500",
    "sg:province":"Solothurn",
    "wof:name":"Weber & Saurer Gr\u00fcnplanungsb\u00fcro",
    "wof:placetype":"venue"
},
  "geometry": {"coordinates":[7.5350971222,47.211566925],"type":"Point"}
}