{
  "type": "Feature",
  "properties": {
    "iso:country":"CH",
    "sg:address":"Seestrasse 7",
    "sg:city":"Walenstadt",
    "sg:orig_category":"Detailhandel mit Waren verschiedener Art, Hauptrichtung Nahrungsmittel Grosshandel mit Nahrungsmitte",
    "sg:phone":"+41 81 735 11 89",
    "sg:postcode":"8880",
    "sg:province":"St. Gallen",
    "wof:name":"H\u00e4ssig J. Ag",
    "wof:placetype":"venue"
},
  "geometry": {"coordinates":[9.3143587112,47.1242485046],"type":"Point"}
}