{
  "type": "Feature",
  "properties": {
    "iso:country":"CH",
    "sg:address":"Kantonsstrasse 72",
    "sg:city":"Reichenburg",
    "sg:orig_category":"Detailhandel mit Fleisch U Fleischwaren",
    "sg:phone":"+41 55 444 11 18",
    "sg:postcode":"8864",
    "sg:province":"Schwyz",
    "wof:name":"Ren\u00e9 Mettler",
    "wof:placetype":"venue"
},
  "geometry": {"coordinates":[8.9813652039,47.1673736572],"type":"Point"}
}