{
  "type": "Feature",
  "properties": {
    "iso:country":"CH",
    "sg:address":"Hintere H\u00f6henstrasse 4a",
    "sg:city":"Wettingen",
    "sg:orig_category":"Vereine Musik/Blasmusik",
    "sg:postcode":"5430",
    "sg:province":"Aargau",
    "wof:name":"Musikverein Harmonie Turgi",
    "wof:placetype":"venue"
},
  "geometry": {"coordinates":[8.3384532928,47.4704399109],"type":"Point"}
}