{
  "type": "Feature",
  "properties": {
    "iso:country":"CH",
    "sg:address":"Bressonnaz",
    "sg:city":"Syens",
    "sg:orig_category":"Maurerarbeiten Sonstiger spezialisierter Hoch U Tiefbau",
    "sg:phone":"+41 21 905 13 54",
    "sg:postcode":"1510",
    "sg:province":"Vaud",
    "wof:name":"Bays Ren\u00e9.",
    "wof:placetype":"venue"
},
  "geometry": {"coordinates":[6.7865819931,46.6485786438],"type":"Point"}
}