{
  "type": "Feature",
  "properties": {
    "iso:country":"CH",
    "sg:address":"Rue Du Lac 45",
    "sg:city":"Vevey",
    "sg:orig_category":"RESTAURANTS: TEA-ROOMS",
    "sg:phone":"+41 21 921 50 06",
    "sg:postcode":"1800",
    "sg:province":"Vaud",
    "wof:name":"Restoservices S\u00e0rl",
    "wof:placetype":"venue"
},
  "geometry": {"coordinates":[6.8433117867,46.4588241577],"type":"Point"}
}