{
  "type": "Feature",
  "properties": {
    "iso:country":"CH",
    "sg:address":"Route De La P\u00e9rallaz 116",
    "sg:city":"Ch\u00e2tel-st-denis",
    "sg:orig_category":"Autogaragen",
    "sg:phone":"+41 21 866 64 62",
    "sg:postcode":"1618",
    "sg:province":"Fribourg",
    "wof:name":"Garage De La Tine S\u00e0rl",
    "wof:placetype":"venue"
},
  "geometry": {"coordinates":[6.506244,46.653603],"type":"Point"}
}