{
  "type": "Feature",
  "properties": {
    "iso:country":"CH",
    "sg:address":"Quaderstrasse 5",
    "sg:city":"Chur",
    "sg:orig_category":"Wirtschaftspr\u00fcfung, Steuerberatung U Treuhand",
    "sg:phone":"+41 81 252 61 43",
    "sg:postcode":"7000",
    "sg:province":"Graubunden",
    "wof:name":"Mas Treuhand Und Beratungs Ag",
    "wof:placetype":"venue"
},
  "geometry": {"coordinates":[9.5317020416,46.8523406982],"type":"Point"}
}