{
  "type": "Feature",
  "properties": {
    "iso:country":"CH",
    "sg:address":"Nordweg 18",
    "sg:city":"Muhen",
    "sg:orig_category":"Fernmeldedienste",
    "sg:postcode":"5037",
    "sg:province":"Aargau",
    "wof:name":"Genossenschaft Gemeinschaftsantenne Muhen",
    "wof:placetype":"venue"
},
  "geometry": {"coordinates":[8.0498170853,47.3441581726],"type":"Point"}
}