{
  "type": "Feature",
  "properties": {
    "iso:country":"CH",
    "sg:address":"Kasernenstrasse 21 5000 Aarau. Postfach",
    "sg:city":"Aarau",
    "sg:orig_category":"Bau\u00e4mter",
    "sg:phone":"+41 62 835 35 00",
    "sg:postcode":"5001",
    "sg:province":"Aargau",
    "wof:name":"Kantonales Hochbauamt",
    "wof:placetype":"venue"
},
  "geometry": {"coordinates":[8.04928,47.3923],"type":"Point"}
}