{
  "type": "Feature",
  "properties": {
    "iso:country":"CH",
    "sg:address":"8750",
    "sg:city":"Glarus",
    "sg:orig_category":"RESTAURANTS: TEA-ROOMS",
    "sg:postcode":"8750",
    "sg:province":"Glarus",
    "wof:name":"Locher Ren\u00e9, Restaurant Traube",
    "wof:placetype":"venue"
},
  "geometry": {"coordinates":[7.6346597672,46.3163299561],"type":"Point"}
}