{
  "type": "Feature",
  "properties": {
    "iso:country":"CH",
    "sg:address":"Haldenstrasse 6",
    "sg:city":"Luzern",
    "sg:orig_category":"Unternehmensberatung",
    "sg:phone":"+41 41 410 95 41",
    "sg:postcode":"6006",
    "sg:province":"Luzern",
    "wof:name":"Merk Investments Ag Unternehmens, Verm\u00f6gensverwaltung",
    "wof:placetype":"venue"
},
  "geometry": {"coordinates":[8.3169975281,47.0550460815],"type":"Point"}
}