{
  "type": "Feature",
  "properties": {
    "iso:country":"CH",
    "sg:address":"H\u00f6heweg 90",
    "sg:city":"Interlaken",
    "sg:orig_category":"Detailhandel mit fotografischen Artikeln Fachdetailhandel in Verkaufsr\u00e4umen",
    "sg:phone":"+41 33 823 63 43",
    "sg:postcode":"3800",
    "sg:province":"Bern",
    "wof:name":"Theiler Walter",
    "wof:placetype":"venue"
},
  "geometry": {"coordinates":[7.865208149,46.6892852783],"type":"Point"}
}