{
  "type": "Feature",
  "properties": {
    "iso:country":"CH",
    "sg:address":"Sandb\u00fchl 10",
    "sg:city":"Kehrsatz",
    "sg:orig_category":"Politische Parteien FDP",
    "sg:phone":"+41 31 961 17 29",
    "sg:postcode":"3122",
    "sg:province":"Bern",
    "wof:name":"Fdp Amt Seftigen",
    "wof:placetype":"venue"
},
  "geometry": {"coordinates":[7.472799778,46.9194908142],"type":"Point"}
}