{
  "type": "Feature",
  "properties": {
    "iso:country":"CH",
    "sg:address":"Ringstrasse 28",
    "sg:city":"Schattdorf",
    "sg:orig_category":"Mit dem Versicherungsgewerbe verbundene T\u00e4tigkeiten",
    "sg:phone":"+41 41 871 21 22",
    "sg:postcode":"6467",
    "sg:province":"Uri",
    "wof:name":"Rema Versicherungsberatungen, R. D\u00fcrr & Co",
    "wof:placetype":"venue"
},
  "geometry": {"coordinates":[8.648522377,46.8675842285],"type":"Point"}
}