{
  "type": "Feature",
  "properties": {
    "addr:full":"Alpenstrasse 9 Luzern Luzern 6004",
    "addr:housenumber":"9",
    "addr:postcode":"6004",
    "addr:street":"Alpenstrasse",
    "iso:country":"CH",
    "sg:address":"Alpenstrasse 9",
    "sg:city":"Luzern",
    "sg:orig_category":"Architektur U Ingenieurb\u00fcros",
    "sg:postcode":"6004",
    "sg:province":"Luzern",
    "wof:name":"B\u00fchlmann Dominic",
    "wof:placetype":"venue"
},
  "geometry": {"coordinates":[6.88147,46.581959],"type":"Point"}
}