{
  "type": "Feature",
  "properties": {
    "iso:country":"CH",
    "sg:address":"Breitistrasse 7",
    "sg:city":"Wohlen",
    "sg:classifiers":[
        {
            "category":"Shopping",
            "subcategory":"Clothing, Apparel, & Fashions",
            "type":"Retail Goods"
        }
    ],
    "sg:phone":"+41 91 647 39 71",
    "sg:postcode":"5610",
    "sg:province":"Aargau",
    "sg:tags":[
        "cycling",
        "clothes"
    ],
    "wof:name":"Assos Sa",
    "wof:placetype":"venue"
},
  "geometry": {"coordinates":[8.938919,45.860474],"type":"Point"}
}