{
  "type": "Feature",
  "properties": {
    "iso:country":"CH",
    "sg:address":"Industriestrasse 8",
    "sg:city":"Gr\u00e4nichen",
    "sg:classifiers":[
        {
            "category":"Professional",
            "subcategory":"Computer Services",
            "type":"Services"
        }
    ],
    "sg:phone":"+41 62 842 00 28",
    "sg:postcode":"5722",
    "sg:province":"Aargau",
    "sg:tags":[
        "development",
        "software"
    ],
    "wof:name":"Legon Informatik Gmbh",
    "wof:placetype":"venue"
},
  "geometry": {"coordinates":[8.1070747375,47.3507080078],"type":"Point"}
}