{
  "type": "Feature",
  "properties": {
    "iso:country":"CH",
    "sg:address":"Uraniastrasse 4",
    "sg:city":"Z\u00fcrich",
    "sg:orig_category":"Interessenvertretungen",
    "sg:postcode":"8001",
    "sg:province":"Z\u00fcrich",
    "wof:name":"Fonds Zur F\u00f6rderung Des Jugendschachs In Der Schweiz",
    "wof:placetype":"venue"
},
  "geometry": {"coordinates":[8.5394716263,47.3746528625],"type":"Point"}
}