{
  "type": "Feature",
  "properties": {
    "iso:country":"CH",
    "sg:address":"Hintere Bahnhofstrasse 14 9602 Bazenheid. Postfach 46",
    "sg:city":"Bazenheid",
    "sg:orig_category":"Herstellung von Metallerzeugnissen ohne Maschinenbau Herstellung von sonstigen Metallwaren",
    "sg:phone":"+41 71 931 35 35",
    "sg:postcode":"9602",
    "sg:province":"St. Gallen",
    "wof:name":"Thoma Metallwarenfabrik Ag",
    "wof:placetype":"venue"
},
  "geometry": {"coordinates":[9.0678710938,47.4107627869],"type":"Point"}
}