{
  "type": "Feature",
  "properties": {
    "iso:country":"CH",
    "sg:address":"Rue Du Vieux-village",
    "sg:city":"Ardon",
    "sg:orig_category":"Architekturb\u00fcros",
    "sg:phone":"+41 27 306 13 06",
    "sg:postcode":"1957",
    "sg:province":"Valais",
    "wof:name":"G\u00e9rald Exquis Bureau D'architecture",
    "wof:placetype":"venue"
},
  "geometry": {"coordinates":[7.257025,46.213615],"type":"Point"}
}