{
  "type": "Feature",
  "properties": {
    "iso:country":"CH",
    "sg:address":"Langenthalstrasse 41",
    "sg:city":"Huttwil",
    "sg:orig_category":"Detailhandel mit Radio U Fernsehger\u00e4ten",
    "sg:phone":"+41 62 962 12 45",
    "sg:postcode":"4950",
    "sg:province":"Bern",
    "wof:name":"Werner Zurlinden Radio-television",
    "wof:placetype":"venue"
},
  "geometry": {"coordinates":[7.8344678879,47.1162528992],"type":"Point"}
}