{
  "type": "Feature",
  "properties": {
    "addr:full":"Via Cantonale Lamone Ticino 6814",
    "addr:postcode":"6814",
    "addr:street":"Via Cantonale",
    "iso:country":"CH",
    "sg:address":"Via Cantonale",
    "sg:city":"Lamone",
    "sg:orig_category":"Bauspenglerei Sanit\u00e4rinstallation",
    "sg:phone":"+41 79 341 03 02",
    "sg:postcode":"6814",
    "sg:province":"Ticino",
    "wof:name":"Gebr. Br\u00fcgger Heizung Sanit\u00e4r Bauspenglerei",
    "wof:placetype":"venue"
},
  "geometry": {"coordinates":[7.660341,47.174797],"type":"Point"}
}