{
  "type": "Feature",
  "properties": {
    "iso:country":"CH",
    "sg:address":"Alte Steinhauserstrasse 35 6330 Cham. Postfach 5125 6305 Zug",
    "sg:city":"Annahme",
    "sg:orig_category":"Buchverlag Verlagsgewerbe",
    "sg:phone":"+41 41 741 30 44",
    "sg:postcode":"5",
    "wof:name":"Clyancourt Corporation Meducation Publishing Ag",
    "wof:placetype":"venue"
},
  "geometry": {"coordinates":[8.472861,47.190018],"type":"Point"}
}