{
  "type": "Feature",
  "properties": {
    "iso:country":"CH",
    "sg:address":"Sch\u00f6nb\u00fchlstrasse 15",
    "sg:city":"Schaffhausen",
    "sg:orig_category":"Wohnheime",
    "sg:phone":"+41 52 624 18 79",
    "sg:postcode":"8200",
    "sg:province":"Schaffhausen",
    "wof:name":"M\u00e4nnerheim Sch\u00f6nhalde",
    "wof:placetype":"venue"
},
  "geometry": {"coordinates":[8.6393709183,47.7042503357],"type":"Point"}
}