{
  "type": "Feature",
  "properties": {
    "iso:country":"CH",
    "sg:address":"Chemin Du Signal",
    "sg:city":"Bernex",
    "sg:orig_category":"Gem\u00fcsebau",
    "sg:phone":"+41 21 691 50 68",
    "sg:postcode":"1233",
    "sg:province":"Gen\u00e8ve",
    "wof:name":"Jean Pfenninger Maraicher",
    "wof:placetype":"venue"
},
  "geometry": {"coordinates":[6.5645289421,46.5150756836],"type":"Point"}
}