{
  "type": "Feature",
  "properties": {
    "iso:country":"CH",
    "sg:address":"Hauptstrasse 24",
    "sg:city":"Buchrain",
    "sg:orig_category":"Non-Classified Establishments",
    "sg:phone":"+41 71 393 38 47",
    "sg:postcode":"6033",
    "sg:province":"Luzern",
    "wof:name":"Landgasthof R\u00f6ssli",
    "wof:placetype":"venue"
},
  "geometry": {"coordinates":[9.2117004395,47.4424667358],"type":"Point"}
}