{
  "type": "Feature",
  "properties": {
    "addr:full":"Rue De La Gare 5 Peseux Neuch\u00e2tel 2034",
    "addr:housenumber":"5",
    "addr:postcode":"2034",
    "addr:street":"Rue De La Gare;Neucha\u0302Tel",
    "iso:country":"CH",
    "sg:address":"Rue De La Gare 5",
    "sg:city":"Peseux",
    "sg:orig_category":"Arztpraxen",
    "sg:phone":"+41 32 731 99 00",
    "sg:postcode":"2034",
    "sg:province":"Neuch\u00e2tel",
    "wof:name":"Dr M\u00e9d. Laurent Kaufmann M\u00e9decin G\u00e9n\u00e9raliste Fmh",
    "wof:placetype":"venue"
},
  "geometry": {"coordinates":[6.886616,46.985798],"type":"Point"}
}