{
  "type": "Feature",
  "properties": {
    "iso:country":"CH",
    "sg:address":"H\u00f4tel-de-ville Rue De L' 2",
    "sg:city":"Martigny",
    "sg:orig_category":"RESTAURANTS: TEA-ROOMS",
    "sg:postcode":"1920",
    "sg:province":"Valais",
    "wof:name":"Brim S\u00e0rl",
    "wof:placetype":"venue"
},
  "geometry": {"coordinates":[1.2019699812,49.8808860779],"type":"Point"}
}