{
  "type": "Feature",
  "properties": {
    "iso:country":"CH",
    "sg:address":"Laufengasse 18",
    "sg:city":"Neuhausen",
    "sg:orig_category":"Herstellung von sonstigen Maschinen f\u00fcr unspezifische Verwendung",
    "sg:phone":"+41 52 674 77 77",
    "sg:postcode":"8212",
    "sg:province":"Schaffhausen",
    "wof:name":"Sig Pack International Ag",
    "wof:placetype":"venue"
},
  "geometry": {"coordinates":[8.6164274216,47.6791152954],"type":"Point"}
}