{
  "type": "Feature",
  "properties": {
    "iso:country":"CH",
    "sg:address":"Stauffacherstrasse 28",
    "sg:city":"Z\u00fcrich",
    "sg:orig_category":"P\u00e9dicure",
    "sg:phone":"+41 12424668",
    "sg:postcode":"8004",
    "sg:province":"Z\u00fcrich",
    "wof:name":"Astrid Schmid P\u00e9dicure",
    "wof:placetype":"venue"
},
  "geometry": {"coordinates":[8.5292873383,47.3732032776],"type":"Point"}
}