{
  "type": "Feature",
  "properties": {
    "iso:country":"CH",
    "sg:address":"Ziegelhausstrasse 12",
    "sg:city":"Baden",
    "sg:orig_category":"Unclassifiable Establishments",
    "sg:postcode":"5400",
    "sg:province":"Aargau",
    "wof:name":"Amiran Gmbh",
    "wof:placetype":"venue"
},
  "geometry": {"coordinates":[8.2912998199,47.4656829834],"type":"Point"}
}