{
  "type": "Feature",
  "properties": {
    "iso:country":"CH",
    "sg:address":"Kesslerstrasse 1",
    "sg:city":"Muhen",
    "sg:orig_category":"Herstellung von elektrischen Lampen U Leuchten",
    "sg:postcode":"5037",
    "sg:province":"Aargau",
    "wof:name":"Rigging Service Switzerland Gmbh",
    "wof:placetype":"venue"
},
  "geometry": {"coordinates":[7.5620269775,46.9309158325],"type":"Point"}
}