{
  "type": "Feature",
  "properties": {
    "iso:country":"CH",
    "sg:address":"1172",
    "sg:city":"Bougy-villars",
    "sg:orig_category":"Grosshandel mit Getr\u00e4nken Grosshandel mit Wein U Spirituosen",
    "sg:phone":"+41 21 807 39 31",
    "sg:postcode":"1172",
    "sg:province":"Vaud",
    "wof:name":"Cretegny Philippe Sa",
    "wof:placetype":"venue"
},
  "geometry": {"coordinates":[6.3526201248,46.4799499512],"type":"Point"}
}