{
  "type": "Feature",
  "properties": {
    "iso:country":"CH",
    "sg:address":"Unterdorfstrasse 9 3612 Steffisburg. Postfach 113",
    "sg:city":"Steffisburg",
    "sg:classifiers":[
        {
            "category":"Travel",
            "subcategory":"Hotels & Motels",
            "type":"Entertainment"
        }
    ],
    "sg:phone":"+41 33 437 33 66",
    "sg:postcode":"3612",
    "sg:province":"Bern",
    "sg:tags":[
        "hotels",
        "mit",
        "restaurant"
    ],
    "wof:name":"Hotel Adler",
    "wof:placetype":"venue"
},
  "geometry": {"coordinates":[7.634791851,46.7775688171],"type":"Point"}
}