{
  "type": "Feature",
  "properties": {
    "iso:country":"CH",
    "sg:address":"Rue Du Bourg 15",
    "sg:city":"Ch\u00e2telard-lutry",
    "sg:orig_category":"Grafikateliers, Design",
    "sg:phone":"+41 21 791 30 16",
    "sg:postcode":"1095",
    "sg:province":"Vaud",
    "wof:name":"Philippe Matthey Artiste Peintre",
    "wof:placetype":"venue"
},
  "geometry": {"coordinates":[6.6860780716,46.5030250549],"type":"Point"}
}