{
  "type": "Feature",
  "properties": {
    "iso:country":"CH",
    "sg:address":"Chemin De Ch\u00e2teauneuf 1950 Sion Case Postale 397",
    "sg:city":"Sion",
    "sg:classifiers":[
        {
            "category":"Restaurant",
            "type":"Food & Drink"
        }
    ],
    "sg:phone":"+41 27 322 11 40",
    "sg:postcode":"1951",
    "sg:province":"Valais",
    "wof:name":"Football-club Ch\u00e2teauneuf Buvette Stade La Garenne",
    "wof:placetype":"venue"
},
  "geometry": {"coordinates":[7.334605217,46.2234344482],"type":"Point"}
}