{
  "type": "Feature",
  "properties": {
    "iso:country":"CH",
    "sg:address":"Dorfplatz 1",
    "sg:city":"Urn\u00e4sch",
    "sg:orig_category":"Beherbergungsgewerbe",
    "sg:phone":"+41 71 364 23 55",
    "sg:postcode":"9107",
    "sg:province":"Appenzell Ausserrhoden",
    "wof:name":"Mitel S\u00e4ntis Ag",
    "wof:placetype":"venue"
},
  "geometry": {"coordinates":[9.283169,47.317142],"type":"Point"}
}