{
  "type": "Feature",
  "properties": {
    "iso:country":"CH",
    "sg:address":"R\u00fcmelinsplatz 6",
    "sg:city":"Basel",
    "sg:orig_category":"Interessenvertretungen Pensionskassen",
    "sg:phone":"+41 61 261 09 32",
    "sg:postcode":"4001",
    "sg:province":"Basel-Stadt",
    "wof:name":"Ggg Gesellschaft F\u00fcr Das Gute Und Gemeinn\u00fctzige Basel",
    "wof:placetype":"venue"
},
  "geometry": {"coordinates":[7.5876312256,47.5567779541],"type":"Point"}
}