{
  "type": "Feature",
  "properties": {
    "iso:country":"CH",
    "sg:address":"Wartstrasse 4",
    "sg:city":"Winterthur",
    "sg:orig_category":"Detailhandel mit Damenbekleidung",
    "sg:phone":"+41 52 212 35 96",
    "sg:postcode":"8400",
    "sg:province":"Z\u00fcrich",
    "wof:name":"Zeta-mode Damenmode Boutique",
    "wof:placetype":"venue"
},
  "geometry": {"coordinates":[8.722643,47.500877],"type":"Point"}
}