{
  "type": "Feature",
  "properties": {
    "iso:country":"CH",
    "sg:address":"Bachstrasse 45",
    "sg:city":"Ebnat-kappel",
    "sg:orig_category":"Technische B\u00fcros Hoch-& Tiefbau",
    "sg:phone":"+41 79 207 74 67",
    "sg:postcode":"9642",
    "sg:province":"St. Gallen",
    "wof:name":"Max H\u00e4nni Planungsb\u00fcro",
    "wof:placetype":"venue"
},
  "geometry": {"coordinates":[9.1142549515,47.2730522156],"type":"Point"}
}