{
  "type": "Feature",
  "properties": {
    "iso:country":"CH",
    "sg:address":"Clamogne Chemin De 27",
    "sg:city":"Aubonne",
    "sg:orig_category":"Mechanik",
    "sg:phone":"+41 21 808 78 33",
    "sg:postcode":"1170",
    "sg:province":"Vaud",
    "wof:name":"Zumstein Hansj\u00f6rg",
    "wof:placetype":"venue"
},
  "geometry": {"coordinates":[6.391699791,46.4952468872],"type":"Point"}
}