{
  "type": "Feature",
  "properties": {
    "iso:country":"CH",
    "sg:address":"Dorfstrasse 12 5036 Oberentfelden. Postfach",
    "sg:city":"Oberentfelden",
    "sg:orig_category":"Grosshandel mit sonstigen Nahrungsmitteln",
    "sg:postcode":"5036",
    "sg:province":"Aargau",
    "wof:name":"H. Lanz-m\u00fcller",
    "wof:placetype":"venue"
},
  "geometry": {"coordinates":[8.0464429855,47.3559646606],"type":"Point"}
}