{
  "type": "Feature",
  "properties": {
    "iso:country":"CH",
    "sg:address":"Champs-pr\u00e9vost 30",
    "sg:city":"Vernier",
    "sg:orig_category":"Instandhaltung U Reparatur von Automobilen",
    "sg:postcode":"1214",
    "sg:province":"Gen\u00e8ve",
    "wof:name":"Domingo Et Maria Teresa Mayo",
    "wof:placetype":"venue"
},
  "geometry": {"coordinates":[6.0903282166,46.223033905],"type":"Point"}
}