{
  "type": "Feature",
  "properties": {
    "iso:country":"CH",
    "sg:address":"Kirchweg 28",
    "sg:city":"Untersiggenthal",
    "sg:orig_category":"G\u00fcterbef\u00f6rderung im Strassenverkehr",
    "sg:phone":"+41 71 455 12 56",
    "sg:postcode":"5417",
    "sg:province":"Aargau",
    "wof:name":"Scherrer Ag, Roggwil",
    "wof:placetype":"venue"
},
  "geometry": {"coordinates":[9.3981800079,47.5068588257],"type":"Point"}
}