{
  "type": "Feature",
  "properties": {
    "iso:country":"CH",
    "sg:address":"Buchserstrasse 4",
    "sg:city":"Nassenwil",
    "sg:classifiers":[
        {
            "category":"Banks & Credit Unions",
            "subcategory":"Bureau De Change",
            "type":"Services"
        }
    ],
    "sg:phone":"+41 18506055",
    "sg:postcode":"8155",
    "sg:province":"Z\u00fcrich",
    "sg:tags":[
        "brake",
        "systems",
        "mechanical"
    ],
    "wof:name":"Ehrsam Anh\u00e4nger & Bremssysteme Gmbh",
    "wof:placetype":"venue"
},
  "geometry": {"coordinates":[8.471564,47.466206],"type":"Point"}
}