{
  "type": "Feature",
  "properties": {
    "iso:country":"CH",
    "sg:address":"Manessestrasse 92",
    "sg:city":"Z\u00fcrich",
    "sg:orig_category":"Detailhandel mit Sportartikeln Fachdetailhandel in Verkaufsr\u00e4umen",
    "sg:phone":"+41 14563040",
    "sg:postcode":"8045",
    "sg:province":"Z\u00fcrich",
    "wof:name":"Arrigoni Sport Gmbh ...ihr Zweiradfachgesch\u00e4ft",
    "wof:placetype":"venue"
},
  "geometry": {"coordinates":[8.5216245651,47.3645820618],"type":"Point"}
}