{
  "type": "Feature",
  "properties": {
    "iso:country":"CH",
    "sg:address":"Dorfstrasse",
    "sg:city":"Altenrhein",
    "sg:orig_category":"Nationale Postdienste",
    "sg:phone":"+41 71 855 19 47",
    "sg:postcode":"9423",
    "sg:province":"St. Gallen",
    "wof:name":"Die Schweizerische Post",
    "wof:placetype":"venue"
},
  "geometry": {"coordinates":[9.5552587509,47.4902763367],"type":"Point"}
}