{
  "type": "Feature",
  "properties": {
    "iso:country":"CH",
    "sg:address":"Kreuzweg 5",
    "sg:city":"Goldach",
    "sg:orig_category":"Erbringung von Dienstleistungen f\u00fcr Unternehmen",
    "sg:phone":"+41 79 313 26 55",
    "sg:postcode":"9403",
    "sg:province":"St. Gallen",
    "wof:name":"Ammann Modelltechnik",
    "wof:placetype":"venue"
},
  "geometry": {"coordinates":[9.4707994461,47.4783325195],"type":"Point"}
}