{
  "type": "Feature",
  "properties": {
    "iso:country":"CH",
    "sg:address":"Hauptstrasse 11",
    "sg:city":"Frenkendorf",
    "sg:orig_category":"Softwareentwicklung U beratung",
    "sg:phone":"+41 61 901 83 20",
    "sg:postcode":"4402",
    "sg:province":"Basel-Landschaft",
    "wof:name":"Str\u00e4ssle Design Automation",
    "wof:placetype":"venue"
},
  "geometry": {"coordinates":[7.7138028145,47.5033378601],"type":"Point"}
}