{
  "type": "Feature",
  "properties": {
    "iso:country":"CH",
    "sg:address":"Weekendweg 7 3646 Einigen. Postfach",
    "sg:city":"Einigen",
    "sg:orig_category":"Elektrizit\u00e4tsversorgung",
    "sg:postcode":"3646",
    "sg:province":"Bern",
    "wof:name":"Aare Technologie Und Kommerz Ag",
    "wof:placetype":"venue"
},
  "geometry": {"coordinates":[7.6397638321,46.7129554749],"type":"Point"}
}