{
  "type": "Feature",
  "properties": {
    "iso:country":"CH",
    "sg:address":"Ancien-battoir",
    "sg:city":"Senarclens",
    "sg:orig_category":"Sonstiger spezialisierter Hoch U Tiefbau",
    "sg:postcode":"1304",
    "sg:province":"Vaud",
    "wof:name":"Urech Heinz",
    "wof:placetype":"venue"
},
  "geometry": {"coordinates":[7.8051967621,47.0382156372],"type":"Point"}
}