{
  "type": "Feature",
  "properties": {
    "iso:country":"CH",
    "sg:address":"Via Livio 1",
    "sg:city":"Chiasso",
    "sg:orig_category":"Advokaturb\u00fcros Notariate",
    "sg:phone":"+41 91 695 27 57",
    "sg:postcode":"6830",
    "sg:province":"Ticino",
    "wof:name":"Albisetti & Cereghetti Studio Legale & Notarile",
    "wof:placetype":"venue"
},
  "geometry": {"coordinates":[9.029877,45.833363],"type":"Point"}
}