{
  "type": "Feature",
  "properties": {
    "iso:country":"CH",
    "sg:address":"Av. De La Vallombreuse 87",
    "sg:city":"Prilly",
    "sg:orig_category":"Finanzierungsinstitutionen",
    "sg:phone":"+41 21 647 02 83",
    "sg:postcode":"1008",
    "sg:province":"Vaud",
    "wof:name":"Do",
    "wof:placetype":"venue"
},
  "geometry": {"coordinates":[6.611055851,46.5385551453],"type":"Point"}
}