{
  "type": "Feature",
  "properties": {
    "iso:country":"CH",
    "sg:address":"Landstr. 129",
    "sg:city":"Wettingen",
    "sg:orig_category":"Clothes Construction and Public Works Miscellaneous Products Public works Sport Textiles and Clothin",
    "sg:phone":"+41 56 427 02 25",
    "sg:postcode":"5430",
    "sg:province":"Aargau",
    "wof:name":"Shark Ag",
    "wof:placetype":"venue"
},
  "geometry": {"coordinates":[8.332058,47.463261],"type":"Point"}
}