{
  "type": "Feature",
  "properties": {
    "iso:country":"CH",
    "sg:address":"T\u00f6distrasse 1",
    "sg:city":"Chur",
    "sg:classifiers":[
        {
            "category":"Travel",
            "subcategory":"Hotels & Motels",
            "type":"Entertainment"
        }
    ],
    "sg:postcode":"7000",
    "sg:province":"Graubunden",
    "sg:tags":[
        "hotels",
        "mit",
        "restaurant"
    ],
    "wof:name":"A Porta Paul-andr\u00e9 Et Pierre-henri & Cie",
    "wof:placetype":"venue"
},
  "geometry": {"coordinates":[6.1440749168,46.2103614807],"type":"Point"}
}