{
  "type": "Feature",
  "properties": {
    "iso:country":"CH",
    "sg:address":"Es Chaussisses 1745 Lentigny Case Postale",
    "sg:city":"Fribourg",
    "sg:orig_category":"Grosshandel mit chemischen Erzeugnissen",
    "sg:phone":"+41 26 477 31 95",
    "sg:postcode":"1701",
    "sg:province":"Fribourg",
    "wof:name":"Stapol Sa",
    "wof:placetype":"venue"
},
  "geometry": {"coordinates":[7.004445076,46.7590637207],"type":"Point"}
}