{
  "type": "Feature",
  "properties": {
    "iso:country":"CH",
    "sg:address":"Rue De Gen\u00e8ve 85",
    "sg:city":"Lausanne",
    "sg:orig_category":"Herstellung von sonstigen elektrischen Ausr\u00fcstungen",
    "sg:phone":"+41 21 622 01 22",
    "sg:postcode":"1004",
    "sg:province":"Vaud",
    "wof:name":"Comec Sa",
    "wof:placetype":"venue"
},
  "geometry": {"coordinates":[6.613494873,46.5248336792],"type":"Point"}
}