{
  "type": "Feature",
  "properties": {
    "iso:country":"CH",
    "sg:address":"Chemin Du Village 24",
    "sg:city":"Romanel-s-lausanne",
    "sg:orig_category":"Gemeindeverwaltungen",
    "sg:phone":"+41 21 648 11 51",
    "sg:postcode":"1032",
    "sg:province":"Vaud",
    "wof:name":"Administration Communale De Romanel-sur-lausanne",
    "wof:placetype":"venue"
},
  "geometry": {"coordinates":[6.6074829102,46.5628433228],"type":"Point"}
}