{
  "type": "Feature",
  "properties": {
    "iso:country":"CH",
    "sg:address":"Eibachstrasse 4",
    "sg:city":"Lostorf",
    "sg:orig_category":"Herstellung von Maschinen f\u00fcr die Nahrungsmittel, Getr\u00e4nkeherstellung U die Tabakverarbeitung",
    "sg:phone":"+41 62 295 36 60",
    "sg:postcode":"4654",
    "sg:province":"Solothurn",
    "wof:name":"Grastrocknungsanlage Lostorf Widmer Ren\u00e9",
    "wof:placetype":"venue"
},
  "geometry": {"coordinates":[7.9459481239,47.3727722168],"type":"Point"}
}