{
  "type": "Feature",
  "properties": {
    "iso:country":"CH",
    "sg:address":"Zum Schleif",
    "sg:city":"Leukerbad",
    "sg:orig_category":"Ingenieurb\u00fcros Forst",
    "sg:phone":"+41 27 470 25 31",
    "sg:postcode":"3954",
    "sg:province":"Valais",
    "wof:name":"Kurt Zumofen Ingenieurb\u00fcro",
    "wof:placetype":"venue"
},
  "geometry": {"coordinates":[7.627322197,46.3852081299],"type":"Point"}
}