{
  "type": "Feature",
  "properties": {
    "addr:full":"Route De La Maladi\u00e8re 10 Chavannes-renens Vaud 1022",
    "addr:housenumber":"10",
    "addr:postcode":"1022",
    "addr:street":"Route De La Maladie\u0300Re",
    "iso:country":"CH",
    "sg:address":"Route De La Maladi\u00e8re 10",
    "sg:city":"Chavannes-renens",
    "sg:orig_category":"Chemische Reinigung W\u00e4schereien",
    "sg:phone":"+41 21 691 55 10",
    "sg:postcode":"1022",
    "sg:province":"Vaud",
    "wof:name":"La Boutique Du Pressing Netasec Daniel Fressineau",
    "wof:placetype":"venue"
},
  "geometry": {"coordinates":[6.566765,46.527775],"type":"Point"}
}