{
  "type": "Feature",
  "properties": {
    "iso:country":"CH",
    "sg:address":"2027",
    "sg:city":"Montalchez",
    "sg:orig_category":"Gemeindeverwaltungen",
    "sg:phone":"+41 32 835 13 85",
    "sg:postcode":"2027",
    "sg:province":"Neuch\u00e2tel",
    "wof:name":"Administration Communale De Montalchez",
    "wof:placetype":"venue"
},
  "geometry": {"coordinates":[6.7449741364,46.897354126],"type":"Point"}
}