{
  "type": "Feature",
  "properties": {
    "iso:country":"CH",
    "sg:address":"Heidemurweg 45 4303 Kaiseraugst. Postfach",
    "sg:city":"Kaiseraugst",
    "sg:orig_category":"Maler U Glasergewerbe Tapeziererei",
    "sg:phone":"+41 61 811 14 04",
    "sg:postcode":"4303",
    "sg:province":"Aargau",
    "wof:name":"Roger Oechslin Malergesch\u00e4ft",
    "wof:placetype":"venue"
},
  "geometry": {"coordinates":[7.7257080078,47.5404930115],"type":"Point"}
}