{
  "type": "Feature",
  "properties": {
    "addr:full":"G\u00e4ssliackerweg 19 Breitenbach Solothurn 4226",
    "addr:housenumber":"19",
    "addr:postcode":"4226",
    "addr:street":"Gaessliackerweg",
    "iso:country":"CH",
    "sg:address":"G\u00e4ssliackerweg 19",
    "sg:city":"Breitenbach",
    "sg:orig_category":"Aktivit\u00e4ten der Generalunternehmen im Baugewerbe Architektur U Ingenieurb\u00fcros",
    "sg:phone":"+41 61 751 58 00",
    "sg:postcode":"4226",
    "sg:province":"Solothurn",
    "wof:name":"Jauslin & Stebler Ingenieure Ag",
    "wof:placetype":"venue"
},
  "geometry": {"coordinates":[7.596827,47.469486],"type":"Point"}
}