{
  "type": "Feature",
  "properties": {
    "iso:country":"CH",
    "sg:address":"Moosmattstrasse 4",
    "sg:city":"Luzern",
    "sg:orig_category":"Vereine Gesang",
    "sg:phone":"+41 41 310 04 33",
    "sg:postcode":"6005",
    "sg:province":"Luzern",
    "wof:name":"Paulus-chor Luzern Paulusheim",
    "wof:placetype":"venue"
},
  "geometry": {"coordinates":[8.3032245636,47.0414466858],"type":"Point"}
}