{
  "type": "Feature",
  "properties": {
    "iso:country":"CH",
    "sg:address":"Eckstrasse 15",
    "sg:city":"Villmergen",
    "sg:orig_category":"G\u00fcterbef\u00f6rderung im Strassenverkehr",
    "sg:phone":"+41 56 622 30 66",
    "sg:postcode":"5612",
    "sg:province":"Aargau",
    "wof:name":"Josef Rey Ag",
    "wof:placetype":"venue"
},
  "geometry": {"coordinates":[8.2487049103,47.3430709839],"type":"Point"}
}