{
  "type": "Feature",
  "properties": {
    "iso:country":"CH",
    "sg:address":"Schulhausstrasse",
    "sg:city":"Langendorf",
    "sg:orig_category":"Vorschulen, Kinderg\u00e4rten",
    "sg:phone":"+41 31 701 37 27",
    "sg:postcode":"4513",
    "sg:province":"Solothurn",
    "wof:name":"Kindergarten Weihermatt",
    "wof:placetype":"venue"
},
  "geometry": {"coordinates":[7.5145058632,47.2212028503],"type":"Point"}
}