{
  "type": "Feature",
  "properties": {
    "iso:country":"CH",
    "sg:address":"Pirassay Chemin De 4",
    "sg:city":"Russin",
    "sg:orig_category":"Handels-H\u00e4user U Gesellschaften",
    "sg:phone":"+41 79 658 67 35",
    "sg:postcode":"1281",
    "sg:province":"Gen\u00e8ve",
    "wof:name":"Tt Tao Travel Sarl",
    "wof:placetype":"venue"
},
  "geometry": {"coordinates":[6.0130820274,46.1874389648],"type":"Point"}
}