{
  "type": "Feature",
  "properties": {
    "iso:country":"CH",
    "sg:address":"Dos Le M\u00f4tie 1",
    "sg:city":"Pleigne",
    "sg:orig_category":"Darlehenskassen U Raiffeisenbanken",
    "sg:phone":"+41 32 431 18 16",
    "sg:postcode":"2807",
    "sg:province":"Jura",
    "wof:name":"Banque Raiffeisen",
    "wof:placetype":"venue"
},
  "geometry": {"coordinates":[7.294977,47.408363],"type":"Point"}
}