{
  "type": "Feature",
  "properties": {
    "iso:country":"CH",
    "sg:address":"1839",
    "sg:city":"Flendruz",
    "sg:classifiers":[
        {
            "category":"Restaurant",
            "type":"Food & Drink"
        }
    ],
    "sg:phone":"+41 32 913 12 51",
    "sg:postcode":"1839",
    "wof:name":"Caf\u00e9 Halte Du Ch\u00e2telot",
    "wof:placetype":"venue"
},
  "geometry": {"coordinates":[6.7456102371,47.104850769],"type":"Point"}
}