{
  "type": "Feature",
  "properties": {
    "iso:country":"CH",
    "sg:address":"Corso San Gottardo 12",
    "sg:city":"Chiasso",
    "sg:orig_category":"Non-Classified Establishments",
    "sg:postcode":"6830",
    "sg:province":"Ticino",
    "wof:name":"Staby Consulting S\u00e0rl",
    "wof:placetype":"venue"
},
  "geometry": {"coordinates":[6.9261350632,46.39818573],"type":"Point"}
}