{
  "type": "Feature",
  "properties": {
    "iso:country":"CH",
    "sg:address":"Huebwiesenstrasse 33",
    "sg:city":"Geroldswil",
    "sg:orig_category":"Detailhandel mit Antiquit\u00e4ten U Gebrauchtwaren in Verkaufsr\u00e4umen",
    "sg:phone":"+41 62 771 63 48",
    "sg:postcode":"8954",
    "sg:province":"Z\u00fcrich",
    "wof:name":"W. Hediger Brockenhaus Ag",
    "wof:placetype":"venue"
},
  "geometry": {"coordinates":[8.178383,47.260464],"type":"Point"}
}