{
  "type": "Feature",
  "properties": {
    "iso:country":"CH",
    "sg:address":"Margarethenstrasse 54",
    "sg:city":"Basel",
    "sg:orig_category":"Herstellung von Schmuck, Gold U Silberschmiedwaren Herstellung von sonstigen Metallwaren",
    "sg:phone":"+41 32 968 35 61",
    "sg:postcode":"4053",
    "sg:province":"Basel-Stadt",
    "wof:name":"Mathez Daniel",
    "wof:placetype":"venue"
},
  "geometry": {"coordinates":[6.8337750435,47.1041984558],"type":"Point"}
}