{
  "type": "Feature",
  "properties": {
    "iso:country":"CH",
    "sg:address":"Sch\u00e4rlibachstrasse 5b",
    "sg:city":"Dussnang",
    "sg:orig_category":"Massagestudios",
    "sg:phone":"+41 71 977 19 15",
    "sg:postcode":"8374",
    "sg:province":"Thurgau",
    "wof:name":"Grozdana Lazzeroni Massagen Hermes",
    "wof:placetype":"venue"
},
  "geometry": {"coordinates":[8.9611244202,47.430316925],"type":"Point"}
}