{
  "type": "Feature",
  "properties": {
    "iso:country":"CH",
    "sg:address":"Sur La Chaux",
    "sg:city":"Concise",
    "sg:orig_category":"Maler U Glasergewerbe",
    "sg:phone":"+41 24 434 39 89",
    "sg:postcode":"1426",
    "sg:province":"Vaud",
    "wof:name":"La Ma\u00eetrise Du Feu, D\u00e9nervaud Sa",
    "wof:placetype":"venue"
},
  "geometry": {"coordinates":[6.7109098434,46.8495635986],"type":"Point"}
}