{
  "type": "Feature",
  "properties": {
    "iso:country":"CH",
    "sg:address":"Klausstrasse 48 8008 Z\u00fcrich. Postfach",
    "sg:city":"Z\u00fcrich",
    "sg:orig_category":"Non-Classified Establishments",
    "sg:postcode":"8008",
    "sg:province":"Z\u00fcrich",
    "wof:name":"Si Le Cr\u00eat \u00e0 L'aigle Sa",
    "wof:placetype":"venue"
},
  "geometry": {"coordinates":[8.5523719788,47.3592224121],"type":"Point"}
}