{
  "type": "Feature",
  "properties": {
    "iso:country":"CH",
    "sg:address":"Hofstrasse 20",
    "sg:city":"R\u00fctihof",
    "sg:orig_category":"Kosmetikinstitute",
    "sg:phone":"+41 56 493 45 30",
    "sg:postcode":"5406",
    "sg:province":"Aargau",
    "wof:name":"Annemarie Wirth Coiffure & Kosmetik",
    "wof:placetype":"venue"
},
  "geometry": {"coordinates":[8.2704639435,47.4394645691],"type":"Point"}
}