{
  "type": "Feature",
  "properties": {
    "iso:country":"CH",
    "sg:address":"Francillon Rue 22",
    "sg:city":"St-imier",
    "sg:orig_category":"Non-Classified Establishments",
    "sg:postcode":"2610",
    "sg:province":"Bern",
    "wof:name":"L\u00f6ffel Anita",
    "wof:placetype":"venue"
},
  "geometry": {"coordinates":[6.9986047745,47.1525993347],"type":"Point"}
}