{
  "type": "Feature",
  "properties": {
    "iso:country":"CH",
    "sg:address":"Obsthaldenstrasse 175",
    "sg:city":"Z\u00fcrich",
    "sg:orig_category":"Unclassifiable Establishments",
    "sg:phone":"+41 13720568",
    "sg:postcode":"8046",
    "sg:province":"Z\u00fcrich",
    "wof:name":"Orgabod Bodmer",
    "wof:placetype":"venue"
},
  "geometry": {"coordinates":[8.5139417648,47.4147033691],"type":"Point"}
}