{
  "type": "Feature",
  "properties": {
    "iso:country":"CH",
    "sg:address":"Wehntalerstrasse 44",
    "sg:city":"Dielsdorf",
    "sg:orig_category":"Zahnarztpraxen",
    "sg:phone":"+41 18532274",
    "sg:postcode":"8157",
    "sg:province":"Z\u00fcrich",
    "wof:name":"Dr.med.dent.catherine Bl\u00fcmke Zahn\u00e4rztin",
    "wof:placetype":"venue"
},
  "geometry": {"coordinates":[8.4539279938,47.4804496765],"type":"Point"}
}