{
  "type": "Feature",
  "properties": {
    "iso:country":"CH",
    "sg:address":"Chamerstrasse 42",
    "sg:city":"H\u00fcnenberg",
    "sg:orig_category":"Naturheil\u00e4rzte and Heilpraktiker",
    "sg:phone":"+41 41 781 18 82",
    "sg:postcode":"6331",
    "sg:province":"Zug",
    "wof:name":"Angelika G\u00fcldenstein Praxis F\u00fcr Klass.hom\u00f6opathie",
    "wof:placetype":"venue"
},
  "geometry": {"coordinates":[8.4306116104,47.1787414551],"type":"Point"}
}