{
  "type": "Feature",
  "properties": {
    "iso:country":"CH",
    "sg:address":"Lehenmattstrasse 108",
    "sg:city":"Basel",
    "sg:orig_category":"K\u00fcnstlerische U schriftstellerische T\u00e4tigkeiten U Darbietungen",
    "sg:phone":"+41 61 311 65 36",
    "sg:postcode":"4052",
    "sg:province":"Basel-Stadt",
    "wof:name":"M.s.p. Multimedia System Production, Brun Fredy",
    "wof:placetype":"venue"
},
  "geometry": {"coordinates":[7.6176052094,47.5520515442],"type":"Point"}
}