{
  "type": "Feature",
  "properties": {
    "addr:full":"Stollenrain 17 Arlesheim Basel-Landschaft 4144",
    "addr:housenumber":"17",
    "addr:postcode":"4144",
    "addr:street":"Stollenrain",
    "iso:country":"CH",
    "sg:address":"Stollenrain 17",
    "sg:city":"Arlesheim",
    "sg:classifiers":[
        {
            "category":"Shopping",
            "subcategory":"Books",
            "type":"Retail Goods"
        }
    ],
    "sg:phone":"+41 81 415 81 81",
    "sg:postcode":"4144",
    "sg:province":"Basel-Landschaft",
    "wof:name":"Buchdruckerei Davos Ag",
    "wof:placetype":"venue"
},
  "geometry": {"coordinates":[9.82225,46.797283],"type":"Point"}
}