{
  "type": "Feature",
  "properties": {
    "iso:country":"CH",
    "sg:address":"H\u00f6schgasse 89 8008 Z\u00fcrich. Postfach",
    "sg:city":"Z\u00fcrich",
    "sg:orig_category":"Vermietung U Verpachtung von eigenen Immobilien",
    "sg:postcode":"8001",
    "sg:province":"Z\u00fcrich",
    "wof:name":"Immobilien-aktiengesellschaft Teufenthal",
    "wof:placetype":"venue"
},
  "geometry": {"coordinates":[8.1199712753,47.3283424377],"type":"Point"}
}