{
  "type": "Feature",
  "properties": {
    "iso:country":"CH",
    "sg:address":"Frutigenstrasse 55a 3604 Thun. Postfach 157",
    "sg:city":"Thun",
    "sg:orig_category":"Herstellung von Konstruktionsteilen, Fertigbauteilen U Ausbauelementen aus Holz Innenausbau",
    "sg:phone":"+41 81 854 38 68",
    "sg:postcode":"3604",
    "sg:province":"Bern",
    "wof:name":"Falegnameria Salzgeber",
    "wof:placetype":"venue"
},
  "geometry": {"coordinates":[9.9283809662,46.5763969421],"type":"Point"}
}