{
  "type": "Feature",
  "properties": {
    "iso:country":"CH",
    "sg:address":"Schaffhauserstrasse 109",
    "sg:city":"Glattbrugg",
    "sg:orig_category":"RESTAURANTS: TEA-ROOMS",
    "sg:phone":"+41 18106655",
    "sg:postcode":"8152",
    "sg:province":"Z\u00fcrich",
    "wof:name":"Garim Ag",
    "wof:placetype":"venue"
},
  "geometry": {"coordinates":[8.5655040741,47.4334793091],"type":"Point"}
}