{
  "type": "Feature",
  "properties": {
    "addr:full":"Seebahnstrasse 31 Z\u00fcrich Z\u00fcrich 8003",
    "addr:housenumber":"31",
    "addr:postcode":"8003",
    "addr:street":"Seebahnstrasse",
    "iso:country":"CH",
    "sg:address":"Seebahnstrasse 31",
    "sg:city":"Z\u00fcrich",
    "sg:orig_category":"Detailhandel mit Bekleidung",
    "sg:phone":"+41 14624655",
    "sg:postcode":"8003",
    "sg:province":"Z\u00fcrich",
    "wof:name":"Max Wolf Strickwaren",
    "wof:placetype":"venue"
},
  "geometry": {"coordinates":[8.523496,47.370731],"type":"Point"}
}