{
  "type": "Feature",
  "properties": {
    "iso:country":"CH",
    "sg:address":"Dorfstrasse 31",
    "sg:city":"Urswil",
    "sg:classifiers":[
        {
            "category":"Travel",
            "subcategory":"Hotels & Motels",
            "type":"Entertainment"
        }
    ],
    "sg:phone":"+41 41 910 12 83",
    "sg:postcode":"6280",
    "sg:province":"Luzern",
    "sg:tags":[
        "hotels",
        "mit",
        "restaurant"
    ],
    "wof:name":"Gasthof Huttli Lang-b\u00f6lli Theo",
    "wof:placetype":"venue"
},
  "geometry": {"coordinates":[8.2925014496,47.1486778259],"type":"Point"}
}