{
  "type": "Feature",
  "properties": {
    "iso:country":"CH",
    "sg:address":"Auf Der Mauer 2",
    "sg:city":"Z\u00fcrich",
    "sg:orig_category":"Unternehmensberatung",
    "sg:phone":"+41 17763311",
    "sg:postcode":"8001",
    "sg:province":"Z\u00fcrich",
    "wof:name":"Complex Change Ag",
    "wof:placetype":"venue"
},
  "geometry": {"coordinates":[8.4845342636,47.2712516785],"type":"Point"}
}