{
  "type": "Feature",
  "properties": {
    "iso:country":"CH",
    "sg:address":"Cascade A",
    "sg:city":"R\u00e9chy",
    "sg:orig_category":"Unternehmensberatung",
    "sg:postcode":"3966",
    "sg:province":"Valais",
    "wof:name":"Rap S\u00e0rl",
    "wof:placetype":"venue"
},
  "geometry": {"coordinates":[7.5054550171,46.2654685974],"type":"Point"}
}