{
  "type": "Feature",
  "properties": {
    "iso:country":"CH",
    "sg:address":"Schw\u00e4bisstrasse 40 3613 Steffisburg. Postfach 214",
    "sg:city":"Thun",
    "sg:orig_category":"Grosshandel mit Milch, Milcherzeugnissen, Eiern, Speise\u00f6len U Nahrungsfetten Grosshandel mit Nahrung",
    "sg:phone":"+41 71 911 81 77",
    "sg:postcode":"3602",
    "sg:province":"Bern",
    "wof:name":"Mendler Josef",
    "wof:placetype":"venue"
},
  "geometry": {"coordinates":[9.041185379,47.4678230286],"type":"Point"}
}