{
  "type": "Feature",
  "properties": {
    "iso:country":"CH",
    "sg:address":"Fornaci Via 16c",
    "sg:city":"Balerna",
    "sg:orig_category":"Handels-H\u00e4user U Gesellschaften",
    "sg:postcode":"6828",
    "sg:province":"Ticino",
    "wof:name":"Bepe Dienstleistung Gmbh",
    "wof:placetype":"venue"
},
  "geometry": {"coordinates":[8.9446897507,47.2491989136],"type":"Point"}
}