{
  "type": "Feature",
  "properties": {
    "iso:country":"CH",
    "sg:address":"B\u00e4ckerstrasse 1",
    "sg:city":"Gr\u00e4nichen",
    "sg:orig_category":"Herstellung von Brot U Backwaren Herstellung von Dauerbackwaren",
    "sg:phone":"+41 62 855 81 81",
    "sg:postcode":"5722",
    "sg:province":"Aargau",
    "wof:name":"Jowa Ag",
    "wof:placetype":"venue"
},
  "geometry": {"coordinates":[8.0907974243,47.3658638],"type":"Point"}
}