{
  "type": "Feature",
  "properties": {
    "iso:country":"CH",
    "sg:address":"Avenue D'ouchy 37",
    "sg:city":"Lausanne",
    "sg:orig_category":"Reiseb\u00fcros U Reiseveranstalter",
    "sg:postcode":"1006",
    "sg:province":"Vaud",
    "wof:name":"Ets Reisen Gmbh",
    "wof:placetype":"venue"
},
  "geometry": {"coordinates":[9.3907213211,47.4283714294],"type":"Point"}
}