{
  "type": "Feature",
  "properties": {
    "addr:full":"Florastrasse 8 Ostermundigen Bern 3072",
    "addr:housenumber":"8",
    "addr:postcode":"3072",
    "addr:street":"Florastrasse",
    "iso:country":"CH",
    "sg:address":"Florastrasse 8",
    "sg:city":"Ostermundigen",
    "sg:orig_category":"Dienstleistungen, Sonstige Dienstleistungen",
    "sg:postcode":"3072",
    "sg:province":"Bern",
    "wof:name":"Rh Design, Ostermundigen",
    "wof:placetype":"venue"
},
  "geometry": {"coordinates":[7.485235,46.957584],"type":"Point"}
}