{
  "type": "Feature",
  "properties": {
    "iso:country":"CH",
    "sg:address":"Eggenstrasse 14",
    "sg:city":"Lohn-ammannsegg",
    "sg:orig_category":"Fahrschulen, Flugschulen",
    "sg:phone":"+41 32 677 14 44",
    "sg:postcode":"4573",
    "sg:province":"Solothurn",
    "wof:name":"Alfred Hachen Autofahrschule",
    "wof:placetype":"venue"
},
  "geometry": {"coordinates":[7.5368847847,47.1750335693],"type":"Point"}
}