{
  "type": "Feature",
  "properties": {
    "iso:country":"CH",
    "sg:address":"Gewerbestrasse 26",
    "sg:city":"Ibach",
    "sg:orig_category":"Mechanik Mechanische Werkst\u00e4tten",
    "sg:phone":"+41 41 811 55 50",
    "sg:postcode":"6438",
    "sg:province":"Schwyz",
    "wof:name":"Gwerder Ferdy",
    "wof:placetype":"venue"
},
  "geometry": {"coordinates":[8.632610321,47.0140686035],"type":"Point"}
}