{
  "type": "Feature",
  "properties": {
    "addr:full":"Allmeindlistrasse 29 Reichenburg Schwyz 8864",
    "addr:housenumber":"29",
    "addr:postcode":"8864",
    "addr:street":"Allmeindlistrasse;Schwyz",
    "iso:country":"CH",
    "sg:address":"Allmeindlistrasse 29",
    "sg:city":"Reichenburg",
    "sg:orig_category":"Allgemeiner Hoch U Tiefbau Vermittlung von Immobilien",
    "sg:phone":"+41 41 670 14 16",
    "sg:postcode":"8864",
    "sg:province":"Schwyz",
    "wof:name":"Zumb\u00fchl & Kiser Bauplanungs Ag",
    "wof:placetype":"venue"
},
  "geometry": {"coordinates":[8.271123,46.941566],"type":"Point"}
}