{
  "type": "Feature",
  "properties": {
    "iso:country":"CH",
    "sg:address":"Rue Des Moulins 29",
    "sg:city":"Neuch\u00e2tel",
    "sg:orig_category":"Kunsthandel",
    "sg:phone":"+41 32 724 53 23",
    "sg:postcode":"2000",
    "sg:province":"Neuch\u00e2tel",
    "wof:name":"Galerie M\u00e9dia",
    "wof:placetype":"venue"
},
  "geometry": {"coordinates":[6.9279131889,46.9926109314],"type":"Point"}
}