{
  "type": "Feature",
  "properties": {
    "iso:country":"CH",
    "sg:address":"Hauptstr. 51",
    "sg:city":"Berg",
    "sg:classifiers":[
        {
            "category":"Banks & Credit Unions",
            "subcategory":"Bank",
            "type":"Services"
        }
    ],
    "sg:phone":"+41 33 773 64 66",
    "sg:postcode":"8572",
    "sg:province":"Thurgau",
    "wof:name":"Raiffeisenbank Boltigen",
    "wof:placetype":"venue"
},
  "geometry": {"coordinates":[7.39051,46.628971],"type":"Point"}
}