{
  "type": "Feature",
  "properties": {
    "iso:country":"CH",
    "sg:address":"1040",
    "sg:city":"Villars-le-terroir",
    "sg:classifiers":[
        {
            "category":"Restaurant",
            "type":"Food & Drink"
        }
    ],
    "sg:phone":"+41 21 881 12 26",
    "sg:postcode":"1040",
    "sg:province":"Vaud",
    "wof:name":"Caf\u00e9 Central",
    "wof:placetype":"venue"
},
  "geometry": {"coordinates":[6.638879776,46.6560058594],"type":"Point"}
}