{
  "type": "Feature",
  "properties": {
    "iso:country":"CH",
    "sg:address":"Hauptstrasse 87",
    "sg:city":"Ipsach",
    "sg:orig_category":"Instandhaltung U Reparatur von Automobilen",
    "sg:phone":"+41 32 331 01 21",
    "sg:postcode":"2563",
    "sg:province":"Bern",
    "wof:name":"Garage Kr\u00e4henb\u00fchl Fritz Ag",
    "wof:placetype":"venue"
},
  "geometry": {"coordinates":[7.2265729904,47.1092567444],"type":"Point"}
}