{
  "type": "Feature",
  "properties": {
    "iso:country":"CH",
    "sg:address":"4447",
    "sg:city":"K\u00e4nerkinden",
    "sg:orig_category":"Detailhandel mit Milcherzeugnissen U Eiern Verarbeitung von Milch",
    "sg:postcode":"4447",
    "sg:province":"Basel-Landschaft",
    "wof:name":"Milchgenossenschaft",
    "wof:placetype":"venue"
},
  "geometry": {"coordinates":[7.8345298767,47.4114303589],"type":"Point"}
}