{
  "type": "Feature",
  "properties": {
    "iso:country":"CH",
    "sg:address":"Bahnhofstrasse 3",
    "sg:city":"D\u00fcdingen",
    "sg:orig_category":"Sportvereine Turnen",
    "sg:phone":"+41 26 492 95 95",
    "sg:postcode":"3186",
    "sg:province":"Fribourg",
    "wof:name":"Turnverein St.antoni",
    "wof:placetype":"venue"
},
  "geometry": {"coordinates":[7.1911668777,46.8507423401],"type":"Point"}
}