{
  "type": "Feature",
  "properties": {
    "iso:country":"CH",
    "sg:address":"Trottenstrasse 5",
    "sg:city":"Mellingen",
    "sg:orig_category":"Handelsvermittlung U Grosshandel R\u00fcckgewinnung U Vorbereitung f\u00fcr die Wiederverwertung Recycling",
    "sg:phone":"+41 56 491 22 65",
    "sg:postcode":"5507",
    "sg:province":"Aargau",
    "wof:name":"Walter Theiler Altstoffe & Industrieabf\u00e4lle",
    "wof:placetype":"venue"
},
  "geometry": {"coordinates":[8.2747945786,47.4206085205],"type":"Point"}
}