{
  "type": "Feature",
  "properties": {
    "iso:country":"CH",
    "sg:address":"Zugerstrasse 17",
    "sg:city":"Cham",
    "sg:orig_category":"Bauingenieurb\u00fcros",
    "sg:phone":"+41 41 780 11 25",
    "sg:postcode":"6330",
    "sg:province":"Zug",
    "wof:name":"A.c.e.i. Ag",
    "wof:placetype":"venue"
},
  "geometry": {"coordinates":[8.461845,47.181709],"type":"Point"}
}