{
  "type": "Feature",
  "properties": {
    "iso:country":"CH",
    "sg:address":"Centre Magro",
    "sg:city":"Uvrier",
    "sg:orig_category":"Detailhandel mit B\u00fcchern Detailhandel mit Tabakwaren",
    "sg:phone":"+41 27 203 27 39",
    "sg:postcode":"1958",
    "sg:province":"Valais",
    "wof:name":"Jean & Fran\u00e7ois Revaz Tabac Librairie Papeterie",
    "wof:placetype":"venue"
},
  "geometry": {"coordinates":[7.41169,46.252316],"type":"Point"}
}