{
  "type": "Feature",
  "properties": {
    "iso:country":"CH",
    "sg:address":"Kreuzstrasse 8",
    "sg:city":"Siebnen",
    "sg:orig_category":"Handel mit Motorr\u00e4dern, Teilen U Zubeh\u00f6r Instandhaltung U Reparatur von Motorr\u00e4dern",
    "sg:phone":"+41 62 771 62 60",
    "sg:postcode":"8854",
    "sg:province":"Schwyz",
    "wof:name":"Urech Max.",
    "wof:placetype":"venue"
},
  "geometry": {"coordinates":[8.1689071655,47.2726516724],"type":"Point"}
}