{
  "type": "Feature",
  "properties": {
    "iso:country":"CH",
    "sg:address":"Kosakenweg 27",
    "sg:city":"Z\u00fcrich",
    "sg:classifiers":[
        {
            "category":"Wholesale",
            "subcategory":"Chemicals & Plastics",
            "type":"Manufacturing & Wholesale Goods"
        }
    ],
    "sg:phone":"+41 13012166",
    "sg:postcode":"8052",
    "sg:province":"Z\u00fcrich",
    "sg:tags":[
        "article",
        "hygiene",
        "polyethylene",
        "film"
    ],
    "wof:name":"H. Hurni & Co",
    "wof:placetype":"venue"
},
  "geometry": {"coordinates":[8.549073,47.418343],"type":"Point"}
}