{
  "type": "Feature",
  "properties": {
    "iso:country":"CH",
    "sg:address":"Buchenstrasse 34",
    "sg:city":"Herisau",
    "sg:classifiers":[
        {
            "category":"Restaurant",
            "type":"Food & Drink"
        }
    ],
    "sg:phone":"+41 71 351 10 90",
    "sg:postcode":"9100",
    "sg:province":"Appenzell Ausserrhoden",
    "wof:name":"Restaurant Adler Buchenstr.",
    "wof:placetype":"venue"
},
  "geometry": {"coordinates":[9.2819385529,47.3880958557],"type":"Point"}
}