{
  "type": "Feature",
  "properties": {
    "iso:country":"CH",
    "sg:address":"Ebnit",
    "sg:city":"Saanen",
    "sg:orig_category":"Grosshandel mit lebenden Tieren",
    "sg:phone":"+41 34 495 65 52",
    "sg:postcode":"3792",
    "sg:province":"Bern",
    "wof:name":"Hans Baumgartner Viehhandel",
    "wof:placetype":"venue"
},
  "geometry": {"coordinates":[7.9086809158,46.9677047729],"type":"Point"}
}