{
  "type": "Feature",
  "properties": {
    "iso:country":"CH",
    "sg:address":"Via Dei Pioppi 2",
    "sg:city":"Losone",
    "sg:orig_category":"Reiseb\u00fcros",
    "sg:phone":"+41 91 792 13 45",
    "sg:postcode":"6616",
    "sg:province":"Ticino",
    "wof:name":"Kuoni Viaggi Sa",
    "wof:placetype":"venue"
},
  "geometry": {"coordinates":[8.7709007263,46.1666641235],"type":"Point"}
}