{
  "type": "Feature",
  "properties": {
    "iso:country":"CH",
    "sg:address":"Sch\u00f6nb\u00fchl",
    "sg:city":"Diemtigen",
    "sg:orig_category":"Sportvereine Sch\u00fctzen",
    "sg:postcode":"3754",
    "sg:province":"Bern",
    "wof:name":"Sch\u00fctzenverein Dietschwil",
    "wof:placetype":"venue"
},
  "geometry": {"coordinates":[9.0253381729,47.4088478088],"type":"Point"}
}