{
  "type": "Feature",
  "properties": {
    "iso:country":"CH",
    "sg:address":"Bahnhofstrasse 32 8001 Z\u00fcrich. Postfach",
    "sg:city":"Z\u00fcrich",
    "sg:orig_category":"Interessenvertretungen",
    "sg:phone":"+41 12191111",
    "sg:postcode":"8001",
    "sg:province":"Z\u00fcrich",
    "wof:name":"Bachmann-huber Dr. Med. Ernst Und Fanny-stiftung",
    "wof:placetype":"venue"
},
  "geometry": {"coordinates":[8.5390348434,47.3708877563],"type":"Point"}
}