{
  "type": "Feature",
  "properties": {
    "iso:country":"CH",
    "sg:address":"Stammlerb\u00fchl 9",
    "sg:city":"Thayngen",
    "sg:orig_category":"Kauf U Verkauf von Immobilien auf eigene Rechnung",
    "sg:postcode":"8240",
    "sg:province":"Schaffhausen",
    "wof:name":"Ses Immobilien Ag",
    "wof:placetype":"venue"
},
  "geometry": {"coordinates":[8.7175617218,47.7413444519],"type":"Point"}
}