{
  "type": "Feature",
  "properties": {
    "iso:country":"CH",
    "sg:address":"Hammerweg 4 8274 T\u00e4gerwilen. Postfach 32",
    "sg:city":"T\u00e4gerwilen",
    "sg:orig_category":"Blumen U Zierpflanzenbau",
    "sg:phone":"+41 71 669 11 49",
    "sg:postcode":"8274",
    "sg:province":"Thurgau",
    "wof:name":"Geiger Kurt Pflanzenproduktion",
    "wof:placetype":"venue"
},
  "geometry": {"coordinates":[9.133603,47.658806],"type":"Point"}
}