{
  "type": "Feature",
  "properties": {
    "iso:country":"CH",
    "sg:address":"Seestrasse 21",
    "sg:city":"Weggis",
    "sg:orig_category":"RESTAURANTS: TEA-ROOMS",
    "sg:postcode":"6353",
    "sg:province":"Luzern",
    "wof:name":"Renggli Pius",
    "wof:placetype":"venue"
},
  "geometry": {"coordinates":[8.4310836792,47.0316314697],"type":"Point"}
}