{
  "type": "Feature",
  "properties": {
    "iso:country":"CH",
    "sg:address":"8494",
    "sg:city":"Bauma",
    "sg:orig_category":"Sportvereine Sch\u00fctzen",
    "sg:postcode":"8494",
    "sg:province":"Z\u00fcrich",
    "wof:name":"Sch\u00fctzenverein Juckern-saland",
    "wof:placetype":"venue"
},
  "geometry": {"coordinates":[8.8765048981,47.3678207397],"type":"Point"}
}