{
  "type": "Feature",
  "properties": {
    "iso:country":"CH",
    "sg:address":"Nordstrasse 30 3900 Brig. Postfach 204",
    "sg:city":"Brig",
    "sg:orig_category":"Elektrizit\u00e4tsversorgung",
    "sg:phone":"+41 27 922 45 50",
    "sg:postcode":"3900",
    "sg:province":"Valais",
    "wof:name":"Ewbn Elektrizit\u00e4tswerk Brig-naters Ag",
    "wof:placetype":"venue"
},
  "geometry": {"coordinates":[7.9951210022,46.3195114136],"type":"Point"}
}