{
  "type": "Feature",
  "properties": {
    "iso:country":"CH",
    "sg:address":"Hauptstrasse 53",
    "sg:city":"Frick",
    "sg:orig_category":"Malerei-Gipserei Stukkateurgewerbe, Gipserei U Verputzerei",
    "sg:phone":"+41 62 871 26 08",
    "sg:postcode":"5070",
    "sg:province":"Aargau",
    "wof:name":"Markus Probst Gipsergesch\u00e4ft",
    "wof:placetype":"venue"
},
  "geometry": {"coordinates":[8.0212116241,47.5073318481],"type":"Point"}
}