{
  "type": "Feature",
  "properties": {
    "iso:country":"CH",
    "sg:address":"Route De Bussy 12",
    "sg:city":"Payerne",
    "sg:orig_category":"Herstellung von elektrischen Lampen U Leuchten",
    "sg:phone":"+41 79 342 75 17",
    "sg:postcode":"1530",
    "sg:province":"Vaud",
    "wof:name":"Lumistar, Gauch Oswald",
    "wof:placetype":"venue"
},
  "geometry": {"coordinates":[6.9299411774,46.8239707947],"type":"Point"}
}