{
  "type": "Feature",
  "properties": {
    "iso:country":"CH",
    "sg:address":"Pilgerweg 10",
    "sg:city":"Thalwil",
    "sg:orig_category":"Herstellung von Hebezeugen U F\u00f6rdermitteln",
    "sg:phone":"+41 17222466",
    "sg:postcode":"8800",
    "sg:province":"Z\u00fcrich",
    "wof:name":"Fiba Brem Guido, Fachinspektorat F\u00fcr Bef\u00f6rderungsanlagen",
    "wof:placetype":"venue"
},
  "geometry": {"coordinates":[8.5602092743,47.2985877991],"type":"Point"}
}