{
  "type": "Feature",
  "properties": {
    "iso:country":"CH",
    "sg:address":"St. Johanns-vorstadt 67 4056 Basel. Postfach",
    "sg:city":"Basel",
    "sg:orig_category":"Herstellung von Duft U K\u00f6rperpflegemitteln",
    "sg:phone":"+41 79 687 58 44",
    "sg:postcode":"4004",
    "sg:province":"Basel-Stadt",
    "wof:name":"Nail Point Gmbh",
    "wof:placetype":"venue"
},
  "geometry": {"coordinates":[7.8752398491,47.3413887024],"type":"Point"}
}