{
  "type": "Feature",
  "properties": {
    "iso:country":"CH",
    "sg:address":"Dorf 232",
    "sg:city":"Schmerikon",
    "sg:orig_category":"Grosshandel mit Holz U Baustoffen",
    "sg:postcode":"8716",
    "sg:province":"St. Gallen",
    "wof:name":"Rheinkies Ag",
    "wof:placetype":"venue"
},
  "geometry": {"coordinates":[8.9452991486,47.2260437012],"type":"Point"}
}