{
  "type": "Feature",
  "properties": {
    "iso:country":"CH",
    "sg:address":"Hauptstrasse 51",
    "sg:city":"M\u00fcnchenstein",
    "sg:classifiers":[
        {
            "category":"Restaurant",
            "type":"Food & Drink"
        }
    ],
    "sg:phone":"+41 17504066",
    "sg:postcode":"4142",
    "sg:province":"Basel-Landschaft",
    "wof:name":"Restaurant Winzerhaus",
    "wof:placetype":"venue"
},
  "geometry": {"coordinates":[8.425989151,47.4205856323],"type":"Point"}
}