{
  "type": "Feature",
  "properties": {
    "iso:country":"CH",
    "sg:address":"Dammstrasse 23",
    "sg:city":"Hochdorf",
    "sg:orig_category":"Herstellung von Radio U Fernsehger\u00e4ten sowie phono U videotechnischen Ger\u00e4ten",
    "sg:phone":"+41 41 910 39 48",
    "sg:postcode":"6280",
    "sg:province":"Luzern",
    "wof:name":"Audio Video Service Bissig",
    "wof:placetype":"venue"
},
  "geometry": {"coordinates":[8.2941532135,47.164806366],"type":"Point"}
}