{
  "type": "Feature",
  "properties": {
    "iso:country":"CH",
    "sg:address":"Hernerholzgasse 30",
    "sg:city":"Horgen",
    "sg:orig_category":"Unclassifiable Establishments",
    "sg:postcode":"8810",
    "sg:province":"Z\u00fcrich",
    "wof:name":"Tesar Consulting Gmbh",
    "wof:placetype":"venue"
},
  "geometry": {"coordinates":[8.5855436325,47.2638778687],"type":"Point"}
}