{
  "type": "Feature",
  "properties": {
    "iso:country":"CH",
    "sg:address":"5444",
    "sg:city":"K\u00fcnten",
    "sg:orig_category":"Abwasserreinigung",
    "sg:phone":"+41 19104900",
    "sg:postcode":"5444",
    "sg:province":"Aargau",
    "wof:name":"Kl\u00e4ranlage K\u00fcsnacht-erlenbach",
    "wof:placetype":"venue"
},
  "geometry": {"coordinates":[8.576113,47.324963],"type":"Point"}
}