{
  "type": "Feature",
  "properties": {
    "iso:country":"CH",
    "sg:address":"Hauptstrasse 54",
    "sg:city":"Meggen",
    "sg:orig_category":"Markt U Meinungsforschung Unternehmensberatung",
    "sg:phone":"+41 41 378 04 50",
    "sg:postcode":"6045",
    "sg:province":"Luzern",
    "wof:name":"Sargon Ag Unternehmensberatung",
    "wof:placetype":"venue"
},
  "geometry": {"coordinates":[8.3732023239,47.0462532043],"type":"Point"}
}