{
  "type": "Feature",
  "properties": {
    "iso:country":"CH",
    "sg:address":"Hotzestrasse 29",
    "sg:city":"Z\u00fcrich",
    "sg:classifiers":[
        {
            "category":"Manufacturing",
            "subcategory":"Textiles",
            "type":"Manufacturing & Wholesale Goods"
        }
    ],
    "sg:phone":"+41 13687080",
    "sg:postcode":"8006",
    "sg:province":"Z\u00fcrich",
    "sg:tags":[
        "blended",
        "yarn"
    ],
    "wof:name":"Cwc Textil Ag",
    "wof:placetype":"venue"
},
  "geometry": {"coordinates":[8.540846,47.390617],"type":"Point"}
}