{
  "type": "Feature",
  "properties": {
    "iso:country":"CH",
    "sg:address":"Via Guggirolo 1",
    "sg:city":"Viganello",
    "sg:orig_category":"Solarien",
    "sg:phone":"+41 91 972 48 43",
    "sg:postcode":"6962",
    "sg:province":"Ticino",
    "wof:name":"Primadonna Alessandra Ramelli Solarium",
    "wof:placetype":"venue"
},
  "geometry": {"coordinates":[8.9679374695,46.0117530823],"type":"Point"}
}