{
  "type": "Feature",
  "properties": {
    "addr:full":"Dornacherstrasse 295 4053 Basel. Postfach Basel Basel-Stadt 4018",
    "addr:housenumber":"295",
    "addr:postcode":"4053;4018",
    "addr:street":"Dornacherstrasse;Postfach",
    "iso:country":"CH",
    "sg:address":"Dornacherstrasse 295 4053 Basel. Postfach",
    "sg:city":"Basel",
    "sg:orig_category":"Dachdeckerei D\u00e4mmung gegen K\u00e4lte, W\u00e4rme, Schall U Ersch\u00fctterung",
    "sg:phone":"+41 61 331 88 33",
    "sg:postcode":"4018",
    "sg:province":"Basel-Stadt",
    "wof:name":"Josef Imhof & Co. Bedachungen, Bauisolationen Usw; Handel",
    "wof:placetype":"venue"
},
  "geometry": {"coordinates":[7.600309,47.539917],"type":"Point"}
}