{
  "type": "Feature",
  "properties": {
    "addr:full":"3928 Randa Valais 3928",
    "addr:housenumber":"3928",
    "addr:postcode":"3928",
    "addr:street":"Randa Valais",
    "iso:country":"CH",
    "sg:address":"3928",
    "sg:city":"Randa",
    "sg:orig_category":"Campingpl\u00e4tze Detailhandel mit Zeitungen U Zeitschriften Kioske",
    "sg:phone":"+41 27 967 25 55",
    "sg:postcode":"3928",
    "sg:province":"Valais",
    "wof:name":"Camping Attermenzen Andr\u00e9 Brantschen",
    "wof:placetype":"venue"
},
  "geometry": {"coordinates":[7.780355,46.098598],"type":"Point"}
}