{
  "type": "Feature",
  "properties": {
    "iso:country":"CH",
    "sg:address":"Gemmistrasse",
    "sg:city":"Salgesch",
    "sg:orig_category":"Instandhaltung U Reparatur von Automobilen",
    "sg:phone":"+41 21 943 50 10",
    "sg:postcode":"3970",
    "sg:province":"Valais",
    "wof:name":"Garage Du L\u00e9man Sa",
    "wof:placetype":"venue"
},
  "geometry": {"coordinates":[6.8834300041,46.4704742432],"type":"Point"}
}