{
  "type": "Feature",
  "properties": {
    "iso:country":"CH",
    "sg:address":"Klotenerstrasse 76 8303 Bassersdorf. Postfach 130",
    "sg:city":"Bassersdorf",
    "sg:orig_category":"Architektur U Ingenieurb\u00fcros Innenarchitekturb\u00fcros",
    "sg:phone":"+41 18365474",
    "sg:postcode":"8303",
    "sg:province":"Z\u00fcrich",
    "wof:name":"Burkhart & Furrer, Inhaber Furrer Dieter M\u00f6bel - Teppiche - Vorh\u00e4nge",
    "wof:placetype":"venue"
},
  "geometry": {"coordinates":[8.622948,47.444931],"type":"Point"}
}