{
  "type": "Feature",
  "properties": {
    "iso:country":"CH",
    "sg:address":"Uitikonerstrasse 11",
    "sg:city":"Schlieren",
    "sg:orig_category":"Gold- and Silberschmuck Detailhandel Herstellung von Schmuck, Gold U Silberschmiedwaren",
    "sg:phone":"+41 16873671",
    "sg:postcode":"8952",
    "sg:province":"Z\u00fcrich",
    "wof:name":"Patricia Caspar-edelmann Paca-schmuck",
    "wof:placetype":"venue"
},
  "geometry": {"coordinates":[8.7341480255,47.1973953247],"type":"Point"}
}