{
  "type": "Feature",
  "properties": {
    "iso:country":"CH",
    "sg:address":"Im Baumgarten 8",
    "sg:city":"Effretikon",
    "sg:orig_category":"Vereine Diverse",
    "sg:phone":"+41 52 343 57 73",
    "sg:postcode":"8307",
    "sg:province":"Z\u00fcrich",
    "wof:name":"Verein Robinsonspielplatz",
    "wof:placetype":"venue"
},
  "geometry": {"coordinates":[8.6892433167,47.4326324463],"type":"Point"}
}