{
  "type": "Feature",
  "properties": {
    "iso:country":"CH",
    "sg:address":"R\u00f6slistrasse 57",
    "sg:city":"Z\u00fcrich",
    "sg:orig_category":"Organisationen des Gesundheitswesen",
    "sg:phone":"+41 41 670 20 02",
    "sg:postcode":"8006",
    "sg:province":"Z\u00fcrich",
    "wof:name":"Obwaldner Liga Gegen Tuberku- Lose & Lungenkrankheiten",
    "wof:placetype":"venue"
},
  "geometry": {"coordinates":[8.2649879456,46.9352836609],"type":"Point"}
}