{
  "type": "Feature",
  "properties": {
    "iso:country":"CH",
    "sg:address":"St.-johannes-strasse 10",
    "sg:city":"Zug",
    "sg:orig_category":"D\u00e4mmung gegen K\u00e4lte, W\u00e4rme, Schall U Ersch\u00fctterung Verlegen von Fussboden",
    "sg:phone":"+41 41 741 56 46",
    "sg:postcode":"6300",
    "sg:province":"Zug",
    "wof:name":"Ulrich Unterlagsboden Ag",
    "wof:placetype":"venue"
},
  "geometry": {"coordinates":[8.5066204071,47.1797714233],"type":"Point"}
}