{
  "type": "Feature",
  "properties": {
    "iso:country":"CH",
    "sg:address":"Schnyderweg 4",
    "sg:city":"Thun",
    "sg:orig_category":"Non-Classified Establishments",
    "sg:postcode":"3604",
    "sg:province":"Bern",
    "wof:name":"Fabienne Korous",
    "wof:placetype":"venue"
},
  "geometry": {"coordinates":[7.5635180473,46.9277458191],"type":"Point"}
}