{
  "type": "Feature",
  "properties": {
    "iso:country":"CH",
    "sg:address":"Route De Lannaz",
    "sg:city":"Evol\u00e8ne",
    "sg:classifiers":[
        {
            "category":"Restaurant",
            "type":"Food & Drink"
        }
    ],
    "sg:phone":"+41 27 283 19 42",
    "sg:postcode":"1983",
    "sg:province":"Valais",
    "wof:name":"Caf\u00e9 Refuge",
    "wof:placetype":"venue"
},
  "geometry": {"coordinates":[7.4955410957,46.1114578247],"type":"Point"}
}