{
  "type": "Feature",
  "properties": {
    "iso:country":"CH",
    "sg:address":"Route De L'aurore 6",
    "sg:city":"Cernier",
    "sg:orig_category":"Interessenvertretungen -\u00d6ffentliche Verwaltung Landesverteidigung, Sozialversicherung",
    "sg:phone":"+41 118",
    "sg:postcode":"2053",
    "sg:province":"Neuch\u00e2tel",
    "wof:name":"Cernier Centre Epervier No 4 Sa",
    "wof:placetype":"venue"
},
  "geometry": {"coordinates":[6.9074568748,47.0580596924],"type":"Point"}
}