{
  "type": "Feature",
  "properties": {
    "iso:country":"CH",
    "sg:address":"Neugut",
    "sg:city":"H\u00fctten",
    "sg:orig_category":"Detailhandel mit Fleisch U Fleischwaren",
    "sg:phone":"+41 62 794 06 34",
    "sg:postcode":"8825",
    "sg:province":"Z\u00fcrich",
    "wof:name":"Pgm Gmbh",
    "wof:placetype":"venue"
},
  "geometry": {"coordinates":[8.6527938843,47.1789894104],"type":"Point"}
}