{
  "type": "Feature",
  "properties": {
    "iso:country":"CH",
    "sg:address":"Sennh\u00fcttenstrasse",
    "sg:city":"D\u00fcrnten",
    "sg:orig_category":"Detailhandel mit Waren verschiedener Art, Hauptrichtung Nahrungsmittel Verarbeitung von Milch",
    "sg:phone":"+41 55 240 38 54",
    "sg:postcode":"8635",
    "sg:province":"Z\u00fcrich",
    "wof:name":"Arthur Kl\u00f6ti Molkerei Lebensmittel",
    "wof:placetype":"venue"
},
  "geometry": {"coordinates":[8.8606424332,47.2795982361],"type":"Point"}
}