{
  "type": "Feature",
  "properties": {
    "iso:country":"CH",
    "sg:address":"Vorderbergstrasse 41",
    "sg:city":"Galgenen",
    "sg:orig_category":"Handel mit Automobilen",
    "sg:phone":"+41 79 408 06 53",
    "sg:postcode":"8854",
    "sg:province":"Schwyz",
    "wof:name":"Laubi Consulting Ltd",
    "wof:placetype":"venue"
},
  "geometry": {"coordinates":[8.8901700974,47.1696243286],"type":"Point"}
}