{
  "type": "Feature",
  "properties": {
    "iso:country":"CH",
    "sg:address":"Wicherried",
    "sg:city":"Zeneggen",
    "sg:orig_category":"Unclassifiable Establishments",
    "sg:phone":"+41 27 946 46 38",
    "sg:postcode":"3934",
    "sg:province":"Valais",
    "wof:name":"Zimmermann Edv",
    "wof:placetype":"venue"
},
  "geometry": {"coordinates":[7.8624272346,46.263633728],"type":"Point"}
}