{
  "type": "Feature",
  "properties": {
    "iso:country":"CH",
    "sg:address":"Blumenrainstrasse 25",
    "sg:city":"Appenzell",
    "sg:orig_category":"Geb\u00e4ude, Wohnungsreinigung",
    "sg:phone":"+41 71 787 89 70",
    "sg:postcode":"9050",
    "sg:province":"Appenzell Innerhoden",
    "wof:name":"Ebro-geb\u00e4udereinigungen",
    "wof:placetype":"venue"
},
  "geometry": {"coordinates":[9.4171514511,47.3309516907],"type":"Point"}
}