{
  "type": "Feature",
  "properties": {
    "iso:country":"CH",
    "sg:address":"Schachenstrasse 4",
    "sg:city":"Spiez",
    "sg:orig_category":"Herstellung von keramischen Haushaltswaren U Ziergegenst\u00e4nden",
    "sg:phone":"+41 33 654 54 24",
    "sg:postcode":"3700",
    "sg:province":"Bern",
    "wof:name":"Madeleine Pfluger T\u00f6pferei Atelier Pot",
    "wof:placetype":"venue"
},
  "geometry": {"coordinates":[7.6850218773,46.6886100769],"type":"Point"}
}