{
  "type": "Feature",
  "properties": {
    "iso:country":"CH",
    "sg:address":"Marksteinweg 7",
    "sg:city":"Giebenach",
    "sg:orig_category":"Vorschulen, Kinderg\u00e4rten",
    "sg:phone":"+41 61 811 38 79",
    "sg:postcode":"4304",
    "sg:province":"Basel-Landschaft",
    "wof:name":"Kindergarten",
    "wof:placetype":"venue"
},
  "geometry": {"coordinates":[7.7467298508,47.5246887207],"type":"Point"}
}