{
  "type": "Feature",
  "properties": {
    "iso:country":"CH",
    "sg:address":"Querstrasse 4",
    "sg:city":"Fahrweid",
    "sg:orig_category":"Non-Classified Establishments",
    "sg:postcode":"8951",
    "sg:province":"Z\u00fcrich",
    "wof:name":"Ren\u00e9 Gasser Reinigungen",
    "wof:placetype":"venue"
},
  "geometry": {"coordinates":[8.4142246246,47.4086990356],"type":"Point"}
}