{
  "type": "Feature",
  "properties": {
    "iso:country":"CH",
    "sg:address":"Avenue D'epenex 9",
    "sg:city":"Chavannes-renens",
    "sg:orig_category":"Arztpraxen",
    "sg:phone":"+41 21 635 22 22",
    "sg:postcode":"1022",
    "sg:province":"Vaud",
    "wof:name":"Dr M\u00e9d. Si Minh Pham M\u00e9decin G\u00e9n\u00e9raliste Fmh",
    "wof:placetype":"venue"
},
  "geometry": {"coordinates":[6.57729,46.532799],"type":"Point"}
}