{
  "type": "Feature",
  "properties": {
    "iso:country":"CH",
    "sg:address":"1454",
    "sg:city":"L'auberson",
    "sg:orig_category":"Wohnheime",
    "sg:phone":"+41 32 931 91 51",
    "sg:postcode":"1454",
    "sg:province":"Vaud",
    "wof:name":"Croix-bleue",
    "wof:placetype":"venue"
},
  "geometry": {"coordinates":[6.7467451096,47.056476593],"type":"Point"}
}