{
  "type": "Feature",
  "properties": {
    "iso:country":"CH",
    "sg:address":"Schwadernaustrasse 15",
    "sg:city":"Aegerten",
    "sg:orig_category":"Herstellung von Reiseartikeln, Leder U Sattlerwaren Innendekorationsateliers",
    "sg:phone":"+41 32 373 10 50",
    "sg:postcode":"2558",
    "sg:province":"Bern",
    "wof:name":"Alfred Jutzi Sattler-tapezierer",
    "wof:placetype":"venue"
},
  "geometry": {"coordinates":[7.2897729874,47.1222877502],"type":"Point"}
}