{
  "type": "Feature",
  "properties": {
    "iso:country":"CH",
    "sg:address":"Boulevard Du Pont-d'arve 25",
    "sg:city":"Gen\u00e8ve",
    "sg:orig_category":"Erbringung von Dienstleistungen f\u00fcr Unternehmen Herstellung von sonstigen Metallwaren",
    "sg:phone":"+41 22 321 00 42",
    "sg:postcode":"1205",
    "sg:province":"Gen\u00e8ve",
    "wof:name":"Atelier Br\u00fcderlin Sa",
    "wof:placetype":"venue"
},
  "geometry": {"coordinates":[6.1900620461,46.1969070435],"type":"Point"}
}