{
  "type": "Feature",
  "properties": {
    "addr:full":"11 R De Veyrott Meyrin Gen\u00e8ve 1217",
    "addr:housenumber":"11",
    "addr:postcode":"1217",
    "addr:street":"R De Veyrott",
    "iso:country":"CH",
    "sg:address":"11 R De Veyrott",
    "sg:city":"Meyrin",
    "sg:classifiers":[
        {
            "category":"Health Services",
            "subcategory":"Medical Lab",
            "type":"Services"
        }
    ],
    "sg:phone":"+41 22 989 01 00",
    "sg:postcode":"1217",
    "sg:province":"Gen\u00e8ve",
    "sg:tags":[
        "chemical",
        "pharmaceutical",
        "pharmacy"
    ],
    "wof:name":"Sanofi Synthelabo Sa",
    "wof:placetype":"venue"
},
  "geometry": {"coordinates":[6.072216,46.228443],"type":"Point"}
}