{
  "type": "Feature",
  "properties": {
    "iso:country":"CH",
    "sg:address":"Einfangstrasse 5",
    "sg:city":"Amriswil",
    "sg:orig_category":"Grosshandel mit lebenden Tieren",
    "sg:phone":"+41 71 411 23 29",
    "sg:postcode":"8580",
    "sg:province":"Thurgau",
    "wof:name":"Eberle",
    "wof:placetype":"venue"
},
  "geometry": {"coordinates":[9.286904335,47.5466537476],"type":"Point"}
}