{
  "type": "Feature",
  "properties": {
    "iso:country":"CH",
    "sg:address":"Sur Cr\u00e9",
    "sg:city":"Develier",
    "sg:orig_category":"Vorschulen, Kinderg\u00e4rten",
    "sg:postcode":"2802",
    "sg:province":"Jura",
    "wof:name":"Ecole Enfantine",
    "wof:placetype":"venue"
},
  "geometry": {"coordinates":[7.2925801277,47.3572387695],"type":"Point"}
}