{
  "type": "Feature",
  "properties": {
    "iso:country":"CH",
    "sg:address":"Orelli Piazza 10",
    "sg:city":"Locarno",
    "sg:orig_category":"RESTAURANTS: TEA-ROOMS",
    "sg:postcode":"6600",
    "sg:province":"Ticino",
    "wof:name":"Bui Livio",
    "wof:placetype":"venue"
},
  "geometry": {"coordinates":[8.8003940582,46.1705741882],"type":"Point"}
}