{
  "type": "Feature",
  "properties": {
    "iso:country":"CH",
    "sg:address":"St. Jakob-strasse 397",
    "sg:city":"Basel",
    "sg:orig_category":"Parf\u00fcmerien U sonstiger Detailhandel mit kosmetischen Artikeln U K\u00f6rperpflegemitteln",
    "sg:phone":"+41 61 373 35 10",
    "sg:postcode":"4052",
    "sg:province":"Basel-Stadt",
    "wof:name":"Impo Import Parf\u00fcmerien Ag",
    "wof:placetype":"venue"
},
  "geometry": {"coordinates":[7.6205129623,47.5405693054],"type":"Point"}
}