{
  "type": "Feature",
  "properties": {
    "iso:country":"CH",
    "sg:address":"D\u00f6rflistrasse 5",
    "sg:city":"Nieder\u00f6nz",
    "sg:orig_category":"Detailhandel mit Brot, Back U S\u00fcsswaren Herstellung von Nahrungsmitteln undGetr\u00e4nken",
    "sg:phone":"+41 62 961 10 51",
    "sg:postcode":"3362",
    "sg:province":"Bern",
    "wof:name":"Vermicelles Brand Ag",
    "wof:placetype":"venue"
},
  "geometry": {"coordinates":[7.689372,47.188122],"type":"Point"}
}