{
  "type": "Feature",
  "properties": {
    "iso:country":"CH",
    "sg:address":"Tannacker 113",
    "sg:city":"Aetingen",
    "sg:orig_category":"Unclassifiable Establishments",
    "sg:phone":"+41 32 661 10 17",
    "sg:postcode":"4587",
    "sg:province":"Solothurn",
    "wof:name":"Swiss - Tech Gmbh",
    "wof:placetype":"venue"
},
  "geometry": {"coordinates":[7.5082139969,47.135093689],"type":"Point"}
}