{
  "type": "Feature",
  "properties": {
    "iso:country":"CH",
    "sg:address":"Dynamostrasse 5",
    "sg:city":"Baden",
    "sg:orig_category":"Sonstiger Grosshandel",
    "sg:postcode":"5400",
    "sg:province":"Aargau",
    "wof:name":"Entol Ag",
    "wof:placetype":"venue"
},
  "geometry": {"coordinates":[8.305770874,47.4764823914],"type":"Point"}
}