{
  "type": "Feature",
  "properties": {
    "iso:country":"CH",
    "sg:address":"Pr\u00e9s-du-lac 57ter",
    "sg:city":"Yverdon-les-bains",
    "sg:orig_category":"Grosshandel mit Getr\u00e4nken",
    "sg:postcode":"1400",
    "sg:province":"Vaud",
    "wof:name":"Convers A., Commerce De Vins",
    "wof:placetype":"venue"
},
  "geometry": {"coordinates":[6.2354798317,46.4775047302],"type":"Point"}
}