{
  "type": "Feature",
  "properties": {
    "addr:full":"Bleicherweg 44 Z\u00fcrich Z\u00fcrich 8002",
    "addr:housenumber":"44",
    "addr:postcode":"8002",
    "addr:street":"Bleicherweg",
    "iso:country":"CH",
    "sg:address":"Bleicherweg 44",
    "sg:city":"Z\u00fcrich",
    "sg:orig_category":"Detailhandel mit Brillen U anderen Sehhilfen",
    "sg:phone":"+41 12010825",
    "sg:postcode":"8002",
    "sg:province":"Z\u00fcrich",
    "wof:name":"Niederer Optik Christian Gross Gmbh",
    "wof:placetype":"venue"
},
  "geometry": {"coordinates":[8.535036,47.367985],"type":"Point"}
}