{
  "type": "Feature",
  "properties": {
    "iso:country":"CH",
    "sg:address":"Hohlstrasse 275",
    "sg:city":"Z\u00fcrich",
    "sg:orig_category":"Sonstige mit Sport verbundene T\u00e4tigkeiten",
    "sg:postcode":"8004",
    "sg:province":"Z\u00fcrich",
    "wof:name":"Wassersportschulen Neptun Ag",
    "wof:placetype":"venue"
},
  "geometry": {"coordinates":[8.5132741928,47.3831596375],"type":"Point"}
}