{
  "type": "Feature",
  "properties": {
    "iso:country":"CH",
    "sg:address":"Malincenter",
    "sg:city":"Trimmis",
    "sg:orig_category":"Unclassifiable Establishments",
    "sg:postcode":"7203",
    "sg:province":"Graubunden",
    "wof:name":"Franco Mani",
    "wof:placetype":"venue"
},
  "geometry": {"coordinates":[9.5628290176,46.8994636536],"type":"Point"}
}