{
  "type": "Feature",
  "properties": {
    "iso:country":"CH",
    "sg:address":"Savoie Rue Louis De 12",
    "sg:city":"Morges",
    "sg:orig_category":"Fachdetailhandel in Verkaufsr\u00e4umen",
    "sg:phone":"+41 21 803 23 20",
    "sg:postcode":"1110",
    "sg:province":"Vaud",
    "wof:name":"Vertiges Fleurs, P. Cerri",
    "wof:placetype":"venue"
},
  "geometry": {"coordinates":[6.4998240471,46.5099411011],"type":"Point"}
}