{
  "type": "Feature",
  "properties": {
    "iso:country":"CH",
    "sg:address":"Arbonerstrasse 26 8599 Salmsach. Postfach",
    "sg:city":"Salmsach",
    "sg:orig_category":"Herstellung von Heizk\u00f6rpern U kesseln f\u00fcr die Zentralheizung",
    "sg:postcode":"8599",
    "sg:province":"Thurgau",
    "wof:name":"Baumann Heiztechnik Gmbh",
    "wof:placetype":"venue"
},
  "geometry": {"coordinates":[9.37084198,47.5513420105],"type":"Point"}
}