{
  "type": "Feature",
  "properties": {
    "iso:country":"CH",
    "sg:address":"Hammerstrasse 50",
    "sg:city":"Basel",
    "sg:orig_category":"Unclassifiable Establishments",
    "sg:phone":"+41 61 683 44 70",
    "sg:postcode":"4058",
    "sg:province":"Basel-Stadt",
    "wof:name":"Nmc New Media Concepts, Radtke Gerd U.",
    "wof:placetype":"venue"
},
  "geometry": {"coordinates":[7.5973930359,47.5617790222],"type":"Point"}
}