{
  "type": "Feature",
  "properties": {
    "addr:full":"5201 Brugg Aargau 5201",
    "addr:postcode":"5201;5201",
    "iso:country":"CH",
    "sg:address":"5201",
    "sg:city":"Brugg",
    "sg:orig_category":"Adjustment Rods For Vehicle Seats",
    "sg:phone":"+41 56 464 28 28",
    "sg:postcode":"5201",
    "sg:province":"Aargau",
    "wof:name":"Otto Suhner Ag Transmission Expert",
    "wof:placetype":"venue"
},
  "geometry": {"coordinates":[8.20725,47.483799],"type":"Point"}
}