{
  "type": "Feature",
  "properties": {
    "iso:country":"CH",
    "sg:address":"Rue Des Remparts 5 1400 Yverdon-les-bains Case Postale 3155",
    "sg:city":"Yverdon",
    "sg:orig_category":"Detailhandel mit M\u00f6beln Detailhandel mit M\u00f6beln U Haushaltsgegenst\u00e4nden",
    "sg:phone":"+41 24 426 13 13",
    "sg:postcode":"1401",
    "sg:province":"Vaud",
    "wof:name":"Loft Sa",
    "wof:placetype":"venue"
},
  "geometry": {"coordinates":[6.6412410736,46.7793655396],"type":"Point"}
}