{
  "type": "Feature",
  "properties": {
    "iso:country":"CH",
    "sg:address":"Village Rue Du 24",
    "sg:city":"Vernier",
    "sg:orig_category":"Softwareentwicklung U beratung",
    "sg:phone":"+41 22 341 08 40",
    "sg:postcode":"1214",
    "sg:province":"Gen\u00e8ve",
    "wof:name":"A.s. Software Engineering & Finance Consulting S\u00e0rl",
    "wof:placetype":"venue"
},
  "geometry": {"coordinates":[6.0829029083,46.21434021],"type":"Point"}
}