{
  "type": "Feature",
  "properties": {
    "iso:country":"CH",
    "sg:address":"Stadlerstrasse 7",
    "sg:city":"Weiach",
    "sg:orig_category":"Elektrizit\u00e4tsversorgung Wasserversorgung",
    "sg:phone":"+41 18580162",
    "sg:postcode":"8187",
    "sg:province":"Z\u00fcrich",
    "wof:name":"Gemeindeverwaltung Weiach",
    "wof:placetype":"venue"
},
  "geometry": {"coordinates":[8.4369058609,47.5570373535],"type":"Point"}
}