{
  "type": "Feature",
  "properties": {
    "iso:country":"CH",
    "sg:address":"Chemin J.-ph.-de-sauvage 37",
    "sg:city":"Ch\u00e2telaine",
    "sg:orig_category":"Bauschreinerei Zimmerei, Ingenieurholzbau",
    "sg:phone":"+41 22 796 63 30",
    "sg:postcode":"1219",
    "sg:province":"Gen\u00e8ve",
    "wof:name":"Germain Varone Menuiserie & Charpente",
    "wof:placetype":"venue"
},
  "geometry": {"coordinates":[6.100342,46.197227],"type":"Point"}
}