{
  "type": "Feature",
  "properties": {
    "iso:country":"CH",
    "sg:address":"Fauvette Chemin De La 1",
    "sg:city":"Mont-sur-rolle",
    "sg:orig_category":"Sanit\u00e4r, Heizungs U L\u00fcftungsinstallation",
    "sg:postcode":"1185",
    "sg:province":"Vaud",
    "wof:name":"Rochat Robert Sa, Succursale De Mont-sur-rolle",
    "wof:placetype":"venue"
},
  "geometry": {"coordinates":[6.3381428719,46.4705123901],"type":"Point"}
}