{
  "type": "Feature",
  "properties": {
    "iso:country":"CH",
    "sg:address":"Casa\u00ef Avenue Louis- 79 1217 Meyrin. Postfach",
    "sg:city":"Meyrin",
    "sg:orig_category":"Unclassifiable Establishments",
    "sg:phone":"+41 22 798 01 91",
    "sg:postcode":"1217",
    "sg:province":"Gen\u00e8ve",
    "wof:name":"Le Sens Du Management S\u00e0rl Ressources Humaines, Communication; Conseil, Formation Etc",
    "wof:placetype":"venue"
},
  "geometry": {"coordinates":[6.0722160339,46.2284431458],"type":"Point"}
}