{
  "type": "Feature",
  "properties": {
    "iso:country":"CH",
    "sg:address":"Wyerweg 5",
    "sg:city":"Rothenthurm",
    "sg:orig_category":"Innenausbau Zimmerei, Ingenieurholzbau",
    "sg:phone":"+41 41 838 14 65",
    "sg:postcode":"6418",
    "sg:province":"Schwyz",
    "wof:name":"Dominik Schuler Zimmerei Innenausbau",
    "wof:placetype":"venue"
},
  "geometry": {"coordinates":[8.6731367111,47.1040382385],"type":"Point"}
}