{
  "type": "Feature",
  "properties": {
    "iso:country":"CH",
    "sg:address":"Alte Steinhauserstrasse 15 6330 Cham. Postfach 6305 Zug",
    "sg:city":"Annahme",
    "sg:orig_category":"Werbegrafikateliers",
    "sg:phone":"+41 41 743 24 43",
    "sg:postcode":"5",
    "wof:name":"Visual Studio Dahinden Marcel Grafisches Atelier, Visuelle Dienstleistungen Usw",
    "wof:placetype":"venue"
},
  "geometry": {"coordinates":[8.4741973877,47.1876525879],"type":"Point"}
}