{
  "type": "Feature",
  "properties": {
    "iso:country":"CH",
    "sg:address":"Bachtobelstrasse 44",
    "sg:city":"Z\u00fcrich",
    "sg:orig_category":"Massagestudios",
    "sg:phone":"+41 14630408",
    "sg:postcode":"8045",
    "sg:province":"Z\u00fcrich",
    "wof:name":"Peter Meier Massagen",
    "wof:placetype":"venue"
},
  "geometry": {"coordinates":[8.5152511597,47.3609046936],"type":"Point"}
}