{
  "type": "Feature",
  "properties": {
    "addr:full":"Lausanne Rue De 15 Sion Valais 1950",
    "addr:housenumber":"15",
    "addr:postcode":"1950",
    "addr:street":"Rue De",
    "iso:country":"CH",
    "sg:address":"Lausanne Rue De 15",
    "sg:city":"Sion",
    "sg:orig_category":"Architektur U Ingenieurb\u00fcros",
    "sg:phone":"+41 27 322 77 88",
    "sg:postcode":"1950",
    "sg:province":"Valais",
    "wof:name":"Snc Epicard, Bureau D'ing\u00e9nieurs Gu\u00e9guen Et Meier",
    "wof:placetype":"venue"
},
  "geometry": {"coordinates":[7.359433,46.232563],"type":"Point"}
}