{
  "type": "Feature",
  "properties": {
    "iso:country":"CH",
    "sg:address":"Witikonerstrasse 38",
    "sg:city":"Z\u00fcrich",
    "sg:classifiers":[
        {
            "category":"Travel",
            "subcategory":"Hotels & Motels",
            "type":"Entertainment"
        }
    ],
    "sg:phone":"+41 13803430",
    "sg:postcode":"8032",
    "sg:province":"Z\u00fcrich",
    "sg:tags":[
        "hotels",
        "mit",
        "restaurant"
    ],
    "wof:name":"Porte Klus, Sprachkultur Im Zentrum, Kunz Ineichen Renato Und Ineichen Ursula",
    "wof:placetype":"venue"
},
  "geometry": {"coordinates":[8.5676031113,47.3629264832],"type":"Point"}
}