{
  "type": "Feature",
  "properties": {
    "iso:country":"CH",
    "sg:address":"Schulgasse 9",
    "sg:city":"Nidau",
    "sg:orig_category":"Architektur U Ingenieurb\u00fcros",
    "sg:phone":"+41 32 331 59 58",
    "sg:postcode":"2560",
    "sg:province":"Bern",
    "wof:name":"Althis Ag",
    "wof:placetype":"venue"
},
  "geometry": {"coordinates":[7.240363,47.124512],"type":"Point"}
}