{
  "type": "Feature",
  "properties": {
    "iso:country":"CH",
    "sg:address":"Z\u00fcrcherstrasse 126",
    "sg:city":"Dietikon",
    "sg:orig_category":"Herstellung von Metallkonstruktionen",
    "sg:phone":"+41 17414805",
    "sg:postcode":"8953",
    "sg:province":"Z\u00fcrich",
    "wof:name":"Viktor Locher Metallbau Schlosserei",
    "wof:placetype":"venue"
},
  "geometry": {"coordinates":[8.4115848541,47.3997612],"type":"Point"}
}