{
  "type": "Feature",
  "properties": {
    "iso:country":"CH",
    "sg:address":"Schulstrasse",
    "sg:city":"H\u00fcttwilen",
    "sg:orig_category":"Maler U Glasergewerbe",
    "sg:postcode":"8536",
    "sg:province":"Thurgau",
    "wof:name":"Malergesch\u00e4ft Eugenio Vicente",
    "wof:placetype":"venue"
},
  "geometry": {"coordinates":[8.8719034195,47.6091880798],"type":"Point"}
}