{
  "type": "Feature",
  "properties": {
    "iso:country":"CH",
    "sg:address":"En Segrin",
    "sg:city":"Cortaillod",
    "sg:orig_category":"Grosshandel mit Textilien",
    "sg:postcode":"2016",
    "sg:province":"Neuch\u00e2tel",
    "wof:name":"Carawel S\u00e0rl",
    "wof:placetype":"venue"
},
  "geometry": {"coordinates":[6.8390378952,46.9403419495],"type":"Point"}
}