{
  "type": "Feature",
  "properties": {
    "iso:country":"CH",
    "sg:address":"Br\u00fcnigstr. 42",
    "sg:city":"Giswil",
    "sg:classifiers":[
        {
            "category":"Banks & Credit Unions",
            "subcategory":"Bank",
            "type":"Services"
        }
    ],
    "sg:phone":"+41 41 675 28 30",
    "sg:postcode":"6074",
    "sg:province":"Obwalden",
    "wof:name":"Obwaldner Kantonalbank",
    "wof:placetype":"venue"
},
  "geometry": {"coordinates":[8.186499,46.837479],"type":"Point"}
}