{
  "type": "Feature",
  "properties": {
    "iso:country":"CH",
    "sg:address":"Asylstrasse 14",
    "sg:city":"Thalwil",
    "sg:orig_category":"Satzherstellung U Reproduktion",
    "sg:phone":"+41 17205523",
    "sg:postcode":"8800",
    "sg:province":"Z\u00fcrich",
    "wof:name":"Retouche Atelier Gerhard Z\u00f6ller",
    "wof:placetype":"venue"
},
  "geometry": {"coordinates":[8.5689964294,47.2875785828],"type":"Point"}
}