{
  "type": "Feature",
  "properties": {
    "iso:country":"CH",
    "sg:address":"Vordergasse 3",
    "sg:city":"Schaffhausen",
    "sg:orig_category":"Sonstige mit Sport verbundene T\u00e4tigkeiten",
    "sg:phone":"+41 52 625 39 50",
    "sg:postcode":"8200",
    "sg:province":"Schaffhausen",
    "wof:name":"Kadetten Handball Gmbh",
    "wof:placetype":"venue"
},
  "geometry": {"coordinates":[8.6378498077,47.6957054138],"type":"Point"}
}