{
  "type": "Feature",
  "properties": {
    "iso:country":"CH",
    "sg:address":"Rest.schwizerland",
    "sg:city":"Illighausen",
    "sg:classifiers":[
        {
            "category":"Insurance",
            "subcategory":"Insurance Agent",
            "type":"Services"
        }
    ],
    "sg:phone":"+41 71 688 28 10",
    "sg:postcode":"8574",
    "sg:province":"Thurgau",
    "sg:tags":[
        "versicherungsagenturen",
        "-broker"
    ],
    "wof:name":"Z\u00fcrich-versicherungen Agentur",
    "wof:placetype":"venue"
},
  "geometry": {"coordinates":[9.1937875748,47.6247749329],"type":"Point"}
}