{
  "type": "Feature",
  "properties": {
    "iso:country":"CH",
    "sg:address":"Hauptstrasse 14",
    "sg:city":"Hunzenschwil",
    "sg:orig_category":"Detailhandel mit Blumen U Pflanzen",
    "sg:phone":"+41 62 897 11 78",
    "sg:postcode":"5502",
    "sg:province":"Aargau",
    "wof:name":"Margrit Berner Blumengesch\u00e4ft",
    "wof:placetype":"venue"
},
  "geometry": {"coordinates":[8.131034,47.387005],"type":"Point"}
}