{
  "type": "Feature",
  "properties": {
    "addr:full":"St. Martins-ring 305 9492 Eschen. Postfach 29 Eschen 9492",
    "addr:housenumber":"305;29",
    "addr:postcode":"9492 eschen.;9492",
    "addr:street":"St. Martins-Ring;Postfach;Eschen",
    "iso:country":"CH",
    "sg:address":"St. Martins-ring 305 9492 Eschen. Postfach 29",
    "sg:city":"Eschen",
    "sg:orig_category":"Detailhandel mit Blumen U Pflanzen",
    "sg:phone":"+423 373 37 66",
    "sg:postcode":"9492",
    "wof:name":"Blumen-boutique Monika Ag",
    "wof:placetype":"venue"
},
  "geometry": {"coordinates":[9.524505,47.212151],"type":"Point"}
}