{
  "type": "Feature",
  "properties": {
    "addr:full":"Industriestrasse 24 Dietlikon Z\u00fcrich 8305",
    "addr:housenumber":"24",
    "addr:postcode":"8305",
    "addr:street":"Industriestrasse",
    "iso:country":"CH",
    "sg:address":"Industriestrasse 24",
    "sg:city":"Dietlikon",
    "sg:orig_category":"Allgemeiner Hoch U Tiefbau Vermittlung von Immobilien",
    "sg:phone":"+41 26 912 40 77",
    "sg:postcode":"8305",
    "sg:province":"Z\u00fcrich",
    "wof:name":"Quadra 2000 Sa",
    "wof:placetype":"venue"
},
  "geometry": {"coordinates":[7.04897,46.619438],"type":"Point"}
}