{
  "type": "Feature",
  "properties": {
    "iso:country":"CH",
    "sg:address":"Via Baragge 11",
    "sg:city":"Giubiasco",
    "sg:orig_category":"Handelsvermittlung U Grosshandel R\u00fcckgewinnung U Vorbereitung f\u00fcr die Wiederverwertung Recycling",
    "sg:phone":"+41 62 961 33 23",
    "sg:postcode":"6512",
    "sg:province":"Ticino",
    "wof:name":"Urs Gautschi Alteisen & Metalle",
    "wof:placetype":"venue"
},
  "geometry": {"coordinates":[7.6664738655,47.1808204651],"type":"Point"}
}