{
  "type": "Feature",
  "properties": {
    "iso:country":"CH",
    "sg:address":"Obergasse 12",
    "sg:city":"Schmerikon",
    "sg:orig_category":"Grosshandel mit lebenden Tieren",
    "sg:phone":"+41 55 282 35 89",
    "sg:postcode":"8716",
    "sg:province":"St. Gallen",
    "wof:name":"Boos Anton",
    "wof:placetype":"venue"
},
  "geometry": {"coordinates":[8.9473371506,47.2267074585],"type":"Point"}
}