{
  "type": "Feature",
  "properties": {
    "iso:country":"CH",
    "sg:address":"Innere Margarethenstrasse 2 4051 Basel. Postfach",
    "sg:city":"Basel",
    "sg:orig_category":"Softwareentwicklung U beratung",
    "sg:postcode":"4051",
    "sg:province":"Basel-Stadt",
    "wof:name":"Vcd Virtual Computer Design M.r. N\u00e4geli",
    "wof:placetype":"venue"
},
  "geometry": {"coordinates":[7.5642390251,47.5207366943],"type":"Point"}
}