{
  "type": "Feature",
  "properties": {
    "iso:country":"CH",
    "sg:address":"Sch\u00f6nenwerderstrasse 39",
    "sg:city":"Oberentfelden",
    "sg:orig_category":"Grosshandel mit elektrischen Haushaltsger\u00e4ten Haushaltartikel Detailhandel",
    "sg:phone":"+41 62 723 93 40",
    "sg:postcode":"5036",
    "sg:province":"Aargau",
    "wof:name":"Bel\u00fc Gmbh",
    "wof:placetype":"venue"
},
  "geometry": {"coordinates":[8.0410423279,47.3580093384],"type":"Point"}
}