{
  "type": "Feature",
  "properties": {
    "iso:country":"CH",
    "sg:address":"Solothurnerstrasse 21",
    "sg:city":"Olten",
    "sg:orig_category":"Detailhandel mit Geschenkartikeln U Souvenirs",
    "sg:phone":"+41 62 212 81 18",
    "sg:postcode":"4600",
    "sg:province":"Solothurn",
    "wof:name":"Modeva Ag",
    "wof:placetype":"venue"
},
  "geometry": {"coordinates":[7.8984928131,47.3499984741],"type":"Point"}
}