{
  "type": "Feature",
  "properties": {
    "iso:country":"CH",
    "sg:address":"Theaterstrasse 29 8400 Winterthur. Postfach",
    "sg:city":"Pfungen",
    "sg:orig_category":"Unternehmensberatung",
    "sg:phone":"+41 52 301 00 50",
    "sg:postcode":"8422",
    "sg:province":"Z\u00fcrich",
    "wof:name":"Schreiber Finanz Unternehmensberatung, Bes. In Strategie, Organisation, Finanzen Usw",
    "wof:placetype":"venue"
},
  "geometry": {"coordinates":[8.7289981842,47.5043525696],"type":"Point"}
}