{
  "type": "Feature",
  "properties": {
    "addr:full":"Rudolf-dieselstrasse 28 8400 Winterthur. Postfach Winterthur Z\u00fcrich 8400",
    "addr:housenumber":"28",
    "addr:postcode":"8400;8400",
    "addr:street":"Rudolf-Dieselstrasse;Postfach",
    "iso:country":"CH",
    "sg:address":"Rudolf-dieselstrasse 28 8400 Winterthur. Postfach",
    "sg:city":"Winterthur",
    "sg:orig_category":"Architektur U Ingenieurb\u00fcros",
    "sg:phone":"+41 55 442 42 80",
    "sg:postcode":"8400",
    "sg:province":"Z\u00fcrich",
    "wof:name":"Ag Zur Gerbe Lachen",
    "wof:placetype":"venue"
},
  "geometry": {"coordinates":[8.851067,47.191212],"type":"Point"}
}