{
  "type": "Feature",
  "properties": {
    "iso:country":"CH",
    "sg:address":"Hertistrasse 29",
    "sg:city":"Wallisellen",
    "sg:orig_category":"Softwareentwicklung U beratung",
    "sg:postcode":"8304",
    "sg:province":"Z\u00fcrich",
    "wof:name":"H\u00e4rry Ag",
    "wof:placetype":"venue"
},
  "geometry": {"coordinates":[8.5762367249,47.4161949158],"type":"Point"}
}