{
  "type": "Feature",
  "properties": {
    "iso:country":"CH",
    "sg:address":"Vollandes Rue Des 69 1207 Gen\u00e8ve. Postfach",
    "sg:city":"Veyrier",
    "sg:orig_category":"Non-Classified Establishments",
    "sg:postcode":"1255",
    "sg:province":"Gen\u00e8ve",
    "wof:name":"Communicar, Sarmiento Guerrero",
    "wof:placetype":"venue"
},
  "geometry": {"coordinates":[6.1631989479,46.2027130127],"type":"Point"}
}