{
  "type": "Feature",
  "properties": {
    "iso:country":"CH",
    "sg:address":"Bernstrasse 10",
    "sg:city":"Hindelbank",
    "sg:orig_category":"Maler U Glasergewerbe Malerei",
    "sg:phone":"+41 34 411 23 46",
    "sg:postcode":"3324",
    "sg:province":"Bern",
    "wof:name":"Manfred Hofer",
    "wof:placetype":"venue"
},
  "geometry": {"coordinates":[7.537774086,47.040348053],"type":"Point"}
}