{
  "type": "Feature",
  "properties": {
    "iso:country":"CH",
    "sg:address":"Hauptstrasse 3",
    "sg:city":"Lommis",
    "sg:orig_category":"Mechanische Werkst\u00e4tten",
    "sg:phone":"+41 52 376 22 35",
    "sg:postcode":"9506",
    "sg:province":"Thurgau",
    "wof:name":"Kuhn Schweiz Ag",
    "wof:placetype":"venue"
},
  "geometry": {"coordinates":[8.9899663925,47.5160140991],"type":"Point"}
}