{
  "type": "Feature",
  "properties": {
    "iso:country":"CH",
    "sg:address":"Sch\u00fctzenstrasse 2",
    "sg:city":"Volketswil",
    "sg:orig_category":"Fahrschulen, Flugschulen",
    "sg:phone":"+41 19453646",
    "sg:postcode":"8604",
    "sg:province":"Z\u00fcrich",
    "wof:name":"Uschi Rellstab Autofahrschule",
    "wof:placetype":"venue"
},
  "geometry": {"coordinates":[8.6781482697,47.3939399719],"type":"Point"}
}