{
  "type": "Feature",
  "properties": {
    "iso:country":"CH",
    "sg:address":"Gandastrasse 7",
    "sg:city":"Igis",
    "sg:orig_category":"Geb\u00e4ude, Wohnungsreinigung",
    "sg:phone":"+41 24 471 76 36",
    "sg:postcode":"7206",
    "sg:province":"Graubunden",
    "wof:name":"Arnold Turin Sa Entreprise De Nettoyage",
    "wof:placetype":"venue"
},
  "geometry": {"coordinates":[6.9504208565,46.2534637451],"type":"Point"}
}