{
  "type": "Feature",
  "properties": {
    "iso:country":"CH",
    "sg:address":"Bruggerstrasse 3",
    "sg:city":"Mellingen",
    "sg:orig_category":"Detailhandel mit Brot, Back U S\u00fcsswaren",
    "sg:phone":"+41 56 491 14 00",
    "sg:postcode":"5507",
    "sg:province":"Aargau",
    "wof:name":"Peter Br\u00fcgger B\u00e4ckerei-konditorei",
    "wof:placetype":"venue"
},
  "geometry": {"coordinates":[8.272756,47.419071],"type":"Point"}
}