{
  "type": "Feature",
  "properties": {
    "iso:country":"CH",
    "sg:address":"Hinterdorf.",
    "sg:city":"Auw",
    "sg:orig_category":"Instandhaltung U Reparatur von Automobilen",
    "sg:phone":"+41 56 241 24 33",
    "sg:postcode":"5644",
    "sg:province":"Aargau",
    "wof:name":"Garage B. Grosswiler",
    "wof:placetype":"venue"
},
  "geometry": {"coordinates":[8.3196392059,47.527305603],"type":"Point"}
}