{
  "type": "Feature",
  "properties": {
    "iso:country":"CH",
    "sg:address":"Geerenweg 1",
    "sg:city":"Schleitheim",
    "sg:classifiers":[
        {
            "category":"Banks & Credit Unions",
            "subcategory":"Bureau De Change",
            "type":"Services"
        }
    ],
    "sg:phone":"+41 52 680 13 42",
    "sg:postcode":"8226",
    "sg:province":"Schaffhausen",
    "sg:tags":[
        "flat",
        "construction",
        "roof"
    ],
    "wof:name":"Thomas Bollinger Bauspenglerei - Sanit\u00e4re Anlagen Gmbh",
    "wof:placetype":"venue"
},
  "geometry": {"coordinates":[8.4788,47.74601],"type":"Point"}
}