{
  "type": "Feature",
  "properties": {
    "iso:country":"CH",
    "sg:address":"Hauptstrasse 34",
    "sg:city":"Rorschach",
    "sg:orig_category":"Detailhandel mit Textilien",
    "sg:phone":"+41 71 841 15 44",
    "sg:postcode":"9400",
    "sg:province":"St. Gallen",
    "wof:name":"H\u00fcsler Nest",
    "wof:placetype":"venue"
},
  "geometry": {"coordinates":[9.494934082,47.4780654907],"type":"Point"}
}