{
  "type": "Feature",
  "properties": {
    "iso:country":"CH",
    "sg:address":"Les Longues Raies 2",
    "sg:city":"Sonceboz-sombeval",
    "sg:orig_category":"Grosshandel mit Getr\u00e4nken",
    "sg:postcode":"2605",
    "sg:province":"Bern",
    "wof:name":"Aux Bons Vins Baillod Vins; Commerce Et Importation",
    "wof:placetype":"venue"
},
  "geometry": {"coordinates":[6.7499132156,47.0593414307],"type":"Point"}
}