{
  "type": "Feature",
  "properties": {
    "iso:country":"CH",
    "sg:address":"Unterdorf 5",
    "sg:city":"Bauma",
    "sg:orig_category":"Saunas, Solarien, Fitnesszentren U \u00e4hnliches",
    "sg:postcode":"8494",
    "sg:province":"Z\u00fcrich",
    "wof:name":"Sun World Ruppli C.",
    "wof:placetype":"venue"
},
  "geometry": {"coordinates":[8.8754043579,47.3684463501],"type":"Point"}
}