{
  "type": "Feature",
  "properties": {
    "iso:country":"CH",
    "sg:address":"W\u00fchrestrasse 4 9050 Appenzell. Postfach",
    "sg:city":"Appenzell",
    "sg:orig_category":"Blumen U Zierpflanzenbau Detailhandel mit Blumen U Pflanzen",
    "sg:phone":"+41 71 787 11 35",
    "sg:postcode":"9050",
    "sg:province":"Appenzell Innerhoden",
    "wof:name":"Thomas Gassner Blumen Gartenbau",
    "wof:placetype":"venue"
},
  "geometry": {"coordinates":[9.407724,47.329491],"type":"Point"}
}