{
  "type": "Feature",
  "properties": {
    "iso:country":"CH",
    "sg:address":"Zollbruckweg 13",
    "sg:city":"Landquart",
    "sg:orig_category":"Herstellung von Ger\u00e4ten der Elektrizit\u00e4tserzeugung, -verteilung u.\u00e4. -Herstellung von elektronischen",
    "sg:phone":"+41 81 300 04 06",
    "sg:postcode":"7302",
    "sg:province":"Graubunden",
    "wof:name":"Seag System Engineering Sa",
    "wof:placetype":"venue"
},
  "geometry": {"coordinates":[9.5651216507,46.9677238464],"type":"Point"}
}