{
  "type": "Feature",
  "properties": {
    "iso:country":"CH",
    "sg:address":"Industriestrasse 24",
    "sg:city":"Volketswil",
    "sg:orig_category":"Softwareentwicklung U beratung",
    "sg:phone":"+41 19084040",
    "sg:postcode":"8604",
    "sg:province":"Z\u00fcrich",
    "wof:name":"J.d. Edwards (schweiz) Ag",
    "wof:placetype":"venue"
},
  "geometry": {"coordinates":[8.6792259216,47.3797950745],"type":"Point"}
}