{
  "type": "Feature",
  "properties": {
    "iso:country":"CH",
    "sg:address":"Ringstrasse 16 4600 Olten. Postfach",
    "sg:city":"Olten",
    "sg:orig_category":"Detailhandel mit fotografischen Artikeln Fotografisches Gewerbe U fotografische Laboratorien",
    "sg:phone":"+41 62 212 14 28",
    "sg:postcode":"4603",
    "sg:province":"Solothurn",
    "wof:name":"Werner Rubin Photohaus",
    "wof:placetype":"venue"
},
  "geometry": {"coordinates":[7.9004921913,47.3517532349],"type":"Point"}
}