{
  "type": "Feature",
  "properties": {
    "iso:country":"CH",
    "sg:address":"Folchartstrasse 21",
    "sg:city":"St.gallen",
    "sg:orig_category":"Architektur U Ingenieurb\u00fcros",
    "sg:postcode":"9000",
    "sg:province":"St. Gallen",
    "wof:name":"Qsw Ingenieur J\u00fcrg Meier",
    "wof:placetype":"venue"
},
  "geometry": {"coordinates":[9.378308,47.417912],"type":"Point"}
}