{
  "type": "Feature",
  "properties": {
    "iso:country":"CH",
    "sg:address":"Haldenweg 1",
    "sg:city":"Niederlenz",
    "sg:orig_category":"Grosshandel mit M\u00f6beln, Wohnbedarf, Teppichen U Bodenbel\u00e4gen Herstellung von konfektionierten Textil",
    "sg:phone":"+41 62 892 98 41",
    "sg:postcode":"5702",
    "sg:province":"Aargau",
    "wof:name":"Wasserbetten De Valli\u00e8re Australian Dreamtime Company",
    "wof:placetype":"venue"
},
  "geometry": {"coordinates":[8.179526329,47.4036369324],"type":"Point"}
}