{
  "type": "Feature",
  "properties": {
    "iso:country":"CH",
    "sg:address":"Via Maistra 377",
    "sg:city":"S-chanf",
    "sg:orig_category":"Sanit\u00e4r, Heizungs U L\u00fcftungsinstallation Sanit\u00e4rinstallation",
    "sg:phone":"+41 81 854 16 77",
    "sg:postcode":"7525",
    "sg:province":"Graubunden",
    "wof:name":"Pinggera Ag Heizung - Sanit\u00e4r - Garage - Karosserie",
    "wof:placetype":"venue"
},
  "geometry": {"coordinates":[9.9835653305,46.6119155884],"type":"Point"}
}