{
  "type": "Feature",
  "properties": {
    "iso:country":"CH",
    "sg:address":"Weissensteinstrasse 15 4500 Solothurn. Postfach",
    "sg:city":"Solothurn",
    "sg:orig_category":"Vermietung U Verpachtung von eigenen Immobilien",
    "sg:phone":"+41 32 625 95 65",
    "sg:postcode":"4500",
    "sg:province":"Solothurn",
    "wof:name":"Noba Ag",
    "wof:placetype":"venue"
},
  "geometry": {"coordinates":[7.527990818,47.2112426758],"type":"Point"}
}