{
  "type": "Feature",
  "properties": {
    "iso:country":"CH",
    "sg:address":"Bruchstr. 54",
    "sg:city":"Luzern",
    "sg:orig_category":"RESTAURANTS: TEA-ROOMS",
    "sg:phone":"+41 52 741 22 92",
    "sg:postcode":"6000",
    "sg:province":"Luzern",
    "wof:name":"Restaurant Klosterst\u00fcbli",
    "wof:placetype":"venue"
},
  "geometry": {"coordinates":[8.859623909,47.6590118408],"type":"Point"}
}