{
  "type": "Feature",
  "properties": {
    "iso:country":"CH",
    "sg:address":"Rive Carrefour De 1",
    "sg:city":"Gen\u00e8ve",
    "sg:orig_category":"Fachdetailhandel in Verkaufsr\u00e4umen",
    "sg:phone":"+41 62 205 15 15",
    "sg:postcode":"1207",
    "sg:province":"Gen\u00e8ve",
    "wof:name":"Tramondi Sport Ag",
    "wof:placetype":"venue"
},
  "geometry": {"coordinates":[7.8644337654,47.3423233032],"type":"Point"}
}