{
  "type": "Feature",
  "properties": {
    "iso:country":"CH",
    "sg:address":"Chemin De La For\u00eat 5",
    "sg:city":"Penthalaz",
    "sg:orig_category":"Herstellung von Tanks U Sammelbeh\u00e4ltern aus Metall Sonstiger spezialisierter Hoch U Tiefbau",
    "sg:phone":"+41 21 861 24 59",
    "sg:postcode":"1305",
    "sg:province":"Vaud",
    "wof:name":"Bernard Belet Revisions De Citernes",
    "wof:placetype":"venue"
},
  "geometry": {"coordinates":[6.5222110748,46.6145172119],"type":"Point"}
}