{
  "type": "Feature",
  "properties": {
    "iso:country":"CH",
    "sg:address":"Eggb\u00fchlstrasse 12",
    "sg:city":"Z\u00fcrich",
    "sg:orig_category":"Einzelhandel mit Automobilteilen U Zubeh\u00f6r Herstellung von Bereifungen",
    "sg:phone":"+41 13021662",
    "sg:postcode":"8050",
    "sg:province":"Z\u00fcrich",
    "wof:name":"Pro-pneu Ag",
    "wof:placetype":"venue"
},
  "geometry": {"coordinates":[8.5438070297,47.4163856506],"type":"Point"}
}