{
  "type": "Feature",
  "properties": {
    "iso:country":"CH",
    "sg:address":"Bahnhofstrasse 41",
    "sg:city":"Egnach",
    "sg:orig_category":"Herstellung von Werkzeugen",
    "sg:phone":"+41 71 474 72 32",
    "sg:postcode":"9322",
    "sg:province":"Thurgau",
    "wof:name":"Mpk Kemmer Gmbh Swiss",
    "wof:placetype":"venue"
},
  "geometry": {"coordinates":[9.3751058578,47.5358467102],"type":"Point"}
}