{
  "type": "Feature",
  "properties": {
    "iso:country":"CH",
    "sg:address":"Les Magnolias Chemin Morex",
    "sg:city":"Leysin",
    "sg:orig_category":"Handelsvermittlung U Grosshandel Sonstiger Grosshandel",
    "sg:phone":"+41 24 494 24 53",
    "sg:postcode":"1854",
    "sg:province":"Vaud",
    "wof:name":"Actley Sa Import-export",
    "wof:placetype":"venue"
},
  "geometry": {"coordinates":[7.0130829811,46.3435630798],"type":"Point"}
}