{
  "type": "Feature",
  "properties": {
    "iso:country":"CH",
    "sg:address":"Kronengasse 5",
    "sg:city":"Untervaz",
    "sg:orig_category":"Detailhandel mit Fleisch U Fleischwaren",
    "sg:phone":"+41 81 322 26 44",
    "sg:postcode":"7204",
    "sg:province":"Graubunden",
    "wof:name":"Hans Ryser",
    "wof:placetype":"venue"
},
  "geometry": {"coordinates":[9.5335674286,46.9282417297],"type":"Point"}
}