{
  "type": "Feature",
  "properties": {
    "iso:country":"CH",
    "sg:address":"Kreuzstrasse 60",
    "sg:city":"Z\u00fcrich",
    "sg:classifiers":[
        {
            "category":"Health Services",
            "subcategory":"Hospice",
            "type":"Services"
        }
    ],
    "sg:phone":"+41 12546262",
    "sg:postcode":"8008",
    "sg:province":"Z\u00fcrich",
    "sg:tags":[
        "medicine",
        "infection",
        "mycotic"
    ],
    "wof:name":"Ucb-pharma Ag",
    "wof:placetype":"venue"
},
  "geometry": {"coordinates":[8.5523958206,47.3643722534],"type":"Point"}
}