{
  "type": "Feature",
  "properties": {
    "addr:full":"Achenbergstrasse 6 Koblenz Aargau 5322",
    "addr:housenumber":"6",
    "addr:postcode":"5322",
    "addr:street":"Achenbergstrasse",
    "iso:country":"CH",
    "sg:address":"Achenbergstrasse 6",
    "sg:city":"Koblenz",
    "sg:orig_category":"Abwasserreinigung",
    "sg:phone":"+41 17206583",
    "sg:postcode":"5322",
    "sg:province":"Aargau",
    "wof:name":"Georg Meier Kanalisationsunterhalt/sanit\u00e4r",
    "wof:placetype":"venue"
},
  "geometry": {"coordinates":[8.545325,47.283039],"type":"Point"}
}