{
  "type": "Feature",
  "properties": {
    "iso:country":"CH",
    "sg:address":"Landskronstrasse 40 4056 Basel. Postfach",
    "sg:city":"Basel",
    "sg:orig_category":"Vermietung von Baumaschinen U ger\u00e4ten mit Bedienungspersonal",
    "sg:postcode":"4051",
    "sg:province":"Basel-Stadt",
    "wof:name":"Iannucci D., Kran-montage",
    "wof:placetype":"venue"
},
  "geometry": {"coordinates":[7.5765728951,47.5684127808],"type":"Point"}
}