{
  "type": "Feature",
  "properties": {
    "iso:country":"CH",
    "sg:address":"St. Gallerstrasse 54",
    "sg:city":"Goldach",
    "sg:orig_category":"RESTAURANTS: TEA-ROOMS",
    "sg:postcode":"9403",
    "sg:province":"St. Gallen",
    "wof:name":"Dss Gastrobetrieb Gmbh",
    "wof:placetype":"venue"
},
  "geometry": {"coordinates":[9.4723873138,47.4785995483],"type":"Point"}
}