{
  "type": "Feature",
  "properties": {
    "iso:country":"CH",
    "sg:address":"Alter Sch\u00fctzenweg 7",
    "sg:city":"Niederlenz",
    "sg:orig_category":"Unternehmensberatung",
    "sg:postcode":"5702",
    "sg:province":"Aargau",
    "wof:name":"Baldinger H. Betriebsberatung",
    "wof:placetype":"venue"
},
  "geometry": {"coordinates":[8.1761322021,47.4072532654],"type":"Point"}
}