{
  "type": "Feature",
  "properties": {
    "iso:country":"CH",
    "sg:address":"Dorfstrasse 68 3715 Adelboden. Postfach 129",
    "sg:city":"Adelboden",
    "sg:orig_category":"HOTELS: MIT RESTAURANT HOTELS: OHNE RESTAURANT",
    "sg:phone":"+41 79 352 90 22",
    "sg:postcode":"3715",
    "sg:province":"Bern",
    "wof:name":"Hotel Garni Bernerhof",
    "wof:placetype":"venue"
},
  "geometry": {"coordinates":[7.5554428101,46.4902458191],"type":"Point"}
}