{
  "type": "Feature",
  "properties": {
    "iso:country":"CH",
    "sg:address":"Zugerbergstrasse 5",
    "sg:city":"Unter\u00e4geri",
    "sg:orig_category":"RESTAURANTS: TEA-ROOMS",
    "sg:phone":"+41 41 750 13 66",
    "sg:postcode":"6314",
    "sg:province":"Zug",
    "wof:name":"Restaurant Peking Ente, Chan Hok Kwong",
    "wof:placetype":"venue"
},
  "geometry": {"coordinates":[8.5840988159,47.1370544434],"type":"Point"}
}