{
  "type": "Feature",
  "properties": {
    "iso:country":"CH",
    "sg:address":"Route De Gen\u00e8ve 4",
    "sg:city":"Cheseaux-lausanne",
    "sg:classifiers":[
        {
            "category":"Government",
            "subcategory":"Post Office",
            "type":"Public Place"
        }
    ],
    "sg:phone":"+41 21 732 15 17",
    "sg:postcode":"1033",
    "sg:province":"Vaud",
    "sg:tags":[
        "caf\u00e9s",
        "tea-rooms"
    ],
    "wof:name":"Tea-room Au P'tit Bonheur",
    "wof:placetype":"venue"
},
  "geometry": {"coordinates":[6.6044421196,46.5841674805],"type":"Point"}
}