{
  "type": "Feature",
  "properties": {
    "iso:country":"CH",
    "sg:address":"Bahnhofstr. 30. 8253 Diessenhofen Postfach263",
    "sg:city":"Diessenhofen",
    "sg:orig_category":"Druck ohne Zeitungsdruck",
    "sg:phone":"+41 52 657 11 18",
    "sg:postcode":"8253",
    "sg:province":"Thurgau",
    "wof:name":"Buchdruckerei Sigrist.",
    "wof:placetype":"venue"
},
  "geometry": {"coordinates":[8.7541160583,47.6876296997],"type":"Point"}
}