{
  "type": "Feature",
  "properties": {
    "iso:country":"CH",
    "sg:address":"1165",
    "sg:city":"Allaman",
    "sg:orig_category":"Rebbau",
    "sg:phone":"+41 21 807 31 13",
    "sg:postcode":"1165",
    "sg:province":"Vaud",
    "wof:name":"Ami Grosjean P\u00e9pini\u00e8riste-viticulteur",
    "wof:placetype":"venue"
},
  "geometry": {"coordinates":[6.3946208954,46.4710044861],"type":"Point"}
}