{
  "type": "Feature",
  "properties": {
    "iso:country":"CH",
    "sg:address":"Bahnhofstrasse 29 8932 Mettmenstetten. Postfach 70",
    "sg:city":"Mettmenstetten",
    "sg:orig_category":"Detailhandel mit Radio U Fernsehger\u00e4ten Detailhandel mit elektrischen Haushalts-,Radio U Fernsehger\u00e4",
    "sg:phone":"+41 17670077",
    "sg:postcode":"8932",
    "sg:province":"Z\u00fcrich",
    "wof:name":"Radio-tv Suter E.",
    "wof:placetype":"venue"
},
  "geometry": {"coordinates":[8.4597702026,47.243183136],"type":"Point"}
}