{
  "type": "Feature",
  "properties": {
    "iso:country":"CH",
    "sg:address":"Knonauerstrasse 29",
    "sg:city":"Steinhausen",
    "sg:orig_category":"Druck ohne Zeitungsdruck",
    "sg:postcode":"6312",
    "sg:province":"Zug",
    "wof:name":"Streich Otto, Druck Und Reklame.",
    "wof:placetype":"venue"
},
  "geometry": {"coordinates":[8.4761867523,47.1992530823],"type":"Point"}
}