{
  "type": "Feature",
  "properties": {
    "iso:country":"CH",
    "sg:address":"Bahnhofstrasse 16",
    "sg:city":"T\u00e4gerwilen",
    "sg:orig_category":"Nationale Postdienste",
    "sg:phone":"+41 71 669 11 40",
    "sg:postcode":"8274",
    "sg:province":"Thurgau",
    "wof:name":"Die Schweizerische Post",
    "wof:placetype":"venue"
},
  "geometry": {"coordinates":[9.1324777603,47.6574554443],"type":"Point"}
}