{
  "type": "Feature",
  "properties": {
    "iso:country":"CH",
    "sg:address":"Rue Du Lac 11",
    "sg:city":"Denges",
    "sg:orig_category":"RESTAURANTS: TEA-ROOMS",
    "sg:phone":"+41 21 801 25 38",
    "sg:postcode":"1026",
    "sg:province":"Vaud",
    "wof:name":"Caf\u00e9-restaurant Des Amis, Huissoud Alain",
    "wof:placetype":"venue"
},
  "geometry": {"coordinates":[6.5407419205,46.5236091614],"type":"Point"}
}