{
  "type": "Feature",
  "properties": {
    "iso:country":"CH",
    "sg:address":"Im Tobel 4",
    "sg:city":"Hinwil-hadlikon",
    "sg:classifiers":[
        {
            "category":"Education",
            "subcategory":"Vocational School",
            "type":"Public Place"
        }
    ],
    "sg:phone":"+41 19374650",
    "sg:postcode":"8340",
    "sg:province":"Z\u00fcrich",
    "sg:tags":[
        "assembly",
        "testing",
        "printed",
        "circuit",
        "pcb",
        "board"
    ],
    "wof:name":"Epgz Gmbh Elektronik Produktion",
    "wof:placetype":"venue"
},
  "geometry": {"coordinates":[8.84353,47.30233],"type":"Point"}
}