{
  "type": "Feature",
  "properties": {
    "iso:country":"CH",
    "sg:address":"Luzernerstrasse 82 6010 Kriens. Postfach",
    "sg:city":"Kriens",
    "sg:orig_category":"Wirtschaftspr\u00fcfung, Steuerberatung U Treuhand",
    "sg:phone":"+41 41 317 01 01",
    "sg:postcode":"6011",
    "sg:province":"Luzern",
    "wof:name":"Astifag",
    "wof:placetype":"venue"
},
  "geometry": {"coordinates":[8.2909193039,47.0358924866],"type":"Point"}
}