{
  "type": "Feature",
  "properties": {
    "iso:country":"CH",
    "sg:address":"Via San Bernardo 14",
    "sg:city":"Canobbio",
    "sg:orig_category":"Herstellung von Teppichen",
    "sg:phone":"+41 91 940 61 89",
    "sg:postcode":"6952",
    "sg:province":"Ticino",
    "wof:name":"Pescia A. Pavimenti Sa",
    "wof:placetype":"venue"
},
  "geometry": {"coordinates":[8.9660387039,46.0354309082],"type":"Point"}
}