{
  "type": "Feature",
  "properties": {
    "iso:country":"CH",
    "sg:address":"Rue Colonel-hoffmeyer 43b",
    "sg:city":"Bassecourt",
    "sg:classifiers":[
        {
            "category":"Restaurant",
            "type":"Food & Drink"
        }
    ],
    "sg:phone":"+41 32 426 77 07",
    "sg:postcode":"2854",
    "sg:province":"Jura",
    "wof:name":"Caf\u00e9 Tropical",
    "wof:placetype":"venue"
},
  "geometry": {"coordinates":[7.2428069115,47.3381462097],"type":"Point"}
}