{
  "type": "Feature",
  "properties": {
    "iso:country":"CH",
    "sg:address":"6927",
    "sg:city":"Agra",
    "sg:classifiers":[
        {
            "category":"Travel",
            "subcategory":"Hotels & Motels",
            "type":"Entertainment"
        }
    ],
    "sg:postcode":"6927",
    "sg:province":"Ticino",
    "sg:tags":[
        "hotels",
        "mit",
        "restaurant"
    ],
    "wof:name":"Tanner Paul",
    "wof:placetype":"venue"
},
  "geometry": {"coordinates":[8.6124200821,47.7928199768],"type":"Point"}
}