{
  "type": "Feature",
  "properties": {
    "iso:country":"CH",
    "sg:address":"Grossmatt 229",
    "sg:city":"L\u00fcsslingen",
    "sg:orig_category":"Sportvereine Turnen Vereine Damen",
    "sg:postcode":"4574",
    "sg:province":"Solothurn",
    "wof:name":"Damenturnverein Stv Leuzigen",
    "wof:placetype":"venue"
},
  "geometry": {"coordinates":[7.5013999939,47.1925392151],"type":"Point"}
}