{
  "type": "Feature",
  "properties": {
    "iso:country":"CH",
    "sg:address":"Les Grands-champs 85",
    "sg:city":"Rossemaison",
    "sg:orig_category":"Datenverarbeitungsdienste Softwareentwicklung U beratung",
    "sg:phone":"+41 32 421 44 33",
    "sg:postcode":"2842",
    "sg:province":"Jura",
    "wof:name":"Productec Sa",
    "wof:placetype":"venue"
},
  "geometry": {"coordinates":[7.346427,47.348606],"type":"Point"}
}