{
  "type": "Feature",
  "properties": {
    "iso:country":"CH",
    "sg:address":"Seestrasse 901 8706 Meilen. Postfach",
    "sg:city":"Meilen",
    "sg:orig_category":"Unclassifiable Establishments",
    "sg:phone":"+41 19262530",
    "sg:postcode":"8706",
    "sg:province":"Z\u00fcrich",
    "wof:name":"Ars Vivendi Garten&stein Gmbh K\u00fcnstlerische Gartengestaltung, Bes. Verarbeitung U. Handel Mit Stein, Holz, Metallwaren",
    "wof:placetype":"venue"
},
  "geometry": {"coordinates":[8.6507797241,47.2660903931],"type":"Point"}
}