{
  "type": "Feature",
  "properties": {
    "iso:country":"CH",
    "sg:address":"F\u00fcrst-johannes-strasse 68",
    "sg:city":"Schaan",
    "sg:orig_category":"Grosshandel mit medizinischen U orthop\u00e4dischen Artikeln",
    "sg:phone":"+423 232 17 80",
    "sg:postcode":"9494",
    "wof:name":"Medicina Ag Laborbedarf",
    "wof:placetype":"venue"
},
  "geometry": {"coordinates":[9.5152978897,47.1630783081],"type":"Point"}
}