{
  "type": "Feature",
  "properties": {
    "addr:full":"Route De Ch\u00e2tel-st-denis 16 Corseaux Vaud 1802",
    "addr:housenumber":"16",
    "addr:postcode":"1802",
    "addr:street":"Route De Cha\u0302Tel-St-Denis",
    "iso:country":"CH",
    "sg:address":"Route De Ch\u00e2tel-st-denis 16",
    "sg:city":"Corseaux",
    "sg:orig_category":"Autogaragen",
    "sg:phone":"+41 21 921 02 31",
    "sg:postcode":"1802",
    "sg:province":"Vaud",
    "wof:name":"Garage Emil Frey Sa Vevey",
    "wof:placetype":"venue"
},
  "geometry": {"coordinates":[6.833991,46.471809],"type":"Point"}
}