{
  "type": "Feature",
  "properties": {
    "iso:country":"CH",
    "sg:address":"Langnaustrasse 45",
    "sg:city":"Zollbr\u00fcck",
    "sg:orig_category":"Selbst\u00e4ndige bildende K\u00fcnstler",
    "sg:phone":"+41 34 496 50 55",
    "sg:postcode":"3436",
    "sg:province":"Bern",
    "wof:name":"M. & R. Z\u00fcrcher Ag Grabmalkunst",
    "wof:placetype":"venue"
},
  "geometry": {"coordinates":[7.7512731552,46.9698371887],"type":"Point"}
}