{
  "type": "Feature",
  "properties": {
    "iso:country":"CH",
    "sg:address":"H\u00fcbelacherstrasse 15",
    "sg:city":"Birr-lupfig",
    "sg:orig_category":"Handelsvermittlung U Grosshandel Sonstiger Grosshandel",
    "sg:phone":"+41 52 740 33 80",
    "sg:postcode":"5242",
    "sg:province":"Aargau",
    "wof:name":"Prisma Impex Ag",
    "wof:placetype":"venue"
},
  "geometry": {"coordinates":[8.8604841232,47.6590919495],"type":"Point"}
}