{
  "type": "Feature",
  "properties": {
    "iso:country":"CH",
    "sg:address":"9424 Rheineck. Postfach 349",
    "sg:city":"Rheineck",
    "sg:orig_category":"Sportvereine Ballsport Fussball",
    "sg:phone":"+41 61 831 16 96",
    "sg:postcode":"9424",
    "sg:province":"St. Gallen",
    "wof:name":"Fc Rheinfelden",
    "wof:placetype":"venue"
},
  "geometry": {"coordinates":[7.7915902138,47.5549583435],"type":"Point"}
}