{
  "type": "Feature",
  "properties": {
    "iso:country":"CH",
    "sg:address":"Schneidersmatt 24",
    "sg:city":"W\u00fcnnewil",
    "sg:orig_category":"Autogaragen",
    "sg:phone":"+41 26 496 22 15",
    "sg:postcode":"3184",
    "sg:province":"Fribourg",
    "wof:name":"Hansrudolf & Werner Streit Autoreparaturwerkstatt",
    "wof:placetype":"venue"
},
  "geometry": {"coordinates":[7.272196,46.866398],"type":"Point"}
}