{
  "type": "Feature",
  "properties": {
    "iso:country":"CH",
    "sg:address":"Rue Du Tilleul 13 1700 Fribourg Case Postale 12",
    "sg:city":"Fribourg",
    "sg:orig_category":"Herstellung von sonstigen Erzeugnissen Herstellung von sonstigen Metallwaren",
    "sg:phone":"+41 26 322 19 04",
    "sg:postcode":"1702",
    "sg:province":"Fribourg",
    "wof:name":"Sciboz Roger.",
    "wof:placetype":"venue"
},
  "geometry": {"coordinates":[7.160296917,46.8058547974],"type":"Point"}
}