{
  "type": "Feature",
  "properties": {
    "iso:country":"CH",
    "sg:address":"Ruopigenh\u00f6he 4",
    "sg:city":"Reussb\u00fchl",
    "sg:orig_category":"Erbringung von sonstigen Dienstleistungen f\u00fcr Unternehmen",
    "sg:phone":"+41 41 282 12 82",
    "sg:postcode":"6015",
    "sg:province":"Luzern",
    "wof:name":"Df - Records Internet Service",
    "wof:placetype":"venue"
},
  "geometry": {"coordinates":[8.2745790482,47.0595016479],"type":"Point"}
}