{
  "type": "Feature",
  "properties": {
    "iso:country":"CH",
    "sg:address":"Vorstadtstrasse 7",
    "sg:city":"Gr\u00e4nichen",
    "sg:orig_category":"Elektroinstallation",
    "sg:phone":"+41 62 842 33 33",
    "sg:postcode":"5722",
    "sg:province":"Aargau",
    "wof:name":"Elektro Lattmann Ag",
    "wof:placetype":"venue"
},
  "geometry": {"coordinates":[8.0963182449,47.361114502],"type":"Point"}
}