{
  "type": "Feature",
  "properties": {
    "iso:country":"CH",
    "sg:address":"Bahnhofstrasse 19a",
    "sg:city":"B\u00e4retswil",
    "sg:orig_category":"Nationale Postdienste",
    "sg:phone":"+41 19391205",
    "sg:postcode":"8344",
    "sg:province":"Z\u00fcrich",
    "wof:name":"Die Schweizerische Post",
    "wof:placetype":"venue"
},
  "geometry": {"coordinates":[8.8532838821,47.3361740112],"type":"Point"}
}