{
  "type": "Feature",
  "properties": {
    "iso:country":"CH",
    "sg:address":"Ob Den Reben 26",
    "sg:city":"Witterswil",
    "sg:orig_category":"Vereine Radio, Film and Foto",
    "sg:postcode":"4108",
    "sg:province":"Solothurn",
    "wof:name":"Photographische Gesellschaft",
    "wof:placetype":"venue"
},
  "geometry": {"coordinates":[7.5260548592,47.4888114929],"type":"Point"}
}