{
  "type": "Feature",
  "properties": {
    "iso:country":"CH",
    "sg:address":"Bahnhofstrasse 6 5643 Sins. Postfach",
    "sg:city":"Sins",
    "sg:orig_category":"Bauschreinerei Innenausbau",
    "sg:phone":"+41 41 787 13 47",
    "sg:postcode":"5643",
    "sg:province":"Aargau",
    "wof:name":"A. Br\u00fcndler Ag",
    "wof:placetype":"venue"
},
  "geometry": {"coordinates":[8.396197,47.190735],"type":"Point"}
}