{
  "type": "Feature",
  "properties": {
    "addr:full":"Kindhauserstrasse 2 Volketswil Z\u00fcrich 8604",
    "addr:housenumber":"2",
    "addr:postcode":"8604",
    "addr:street":"Kindhauserstrasse",
    "iso:country":"CH",
    "sg:address":"Kindhauserstrasse 2",
    "sg:city":"Volketswil",
    "sg:orig_category":"Detailhandel mit Blumen U Pflanzen",
    "sg:phone":"+41 19456050",
    "sg:postcode":"8604",
    "sg:province":"Z\u00fcrich",
    "wof:name":"Verena Fischer Blumenhaus Zum Stammbaum",
    "wof:placetype":"venue"
},
  "geometry": {"coordinates":[8.67689,47.39196],"type":"Point"}
}