{
  "type": "Feature",
  "properties": {
    "iso:country":"CH",
    "sg:address":"Altgasse 54",
    "sg:city":"Baar",
    "sg:classifiers":[
        {
            "category":"Building & Trades",
            "subcategory":"Plumbing",
            "type":"Services"
        }
    ],
    "sg:phone":"+41 41 761 32 80",
    "sg:postcode":"6340",
    "sg:province":"Zug",
    "sg:tags":[
        "supraregional",
        "gas"
    ],
    "wof:name":"Brun Sicherheitstechnik Ag",
    "wof:placetype":"venue"
},
  "geometry": {"coordinates":[8.5155591965,47.1920852661],"type":"Point"}
}