{
  "type": "Feature",
  "properties": {
    "iso:country":"CH",
    "sg:address":"Livio Via 7",
    "sg:city":"Chiasso",
    "sg:orig_category":"Herstellung von elektronischen Bauelementen",
    "sg:postcode":"6830",
    "sg:province":"Ticino",
    "wof:name":"Ideva Ltd",
    "wof:placetype":"venue"
},
  "geometry": {"coordinates":[9.0288963318,45.8334503174],"type":"Point"}
}