{
  "type": "Feature",
  "properties": {
    "iso:country":"CH",
    "sg:address":"Dorfwisenstrasse 14",
    "sg:city":"Sch\u00f6fflisdorf",
    "sg:orig_category":"Unternehmensberatung",
    "sg:phone":"+41 18571832",
    "sg:postcode":"8165",
    "sg:province":"Z\u00fcrich",
    "wof:name":"Ethicbusiness Ag",
    "wof:placetype":"venue"
},
  "geometry": {"coordinates":[8.4143428802,47.4989089966],"type":"Point"}
}