{
  "type": "Feature",
  "properties": {
    "iso:country":"CH",
    "sg:address":"Hohle Gasse 85",
    "sg:city":"Wallbach",
    "sg:orig_category":"Unternehmensberatung",
    "sg:phone":"+41 61 861 00 06",
    "sg:postcode":"4323",
    "sg:province":"Aargau",
    "wof:name":"Buchser Unternehmensberatung",
    "wof:placetype":"venue"
},
  "geometry": {"coordinates":[7.8997597694,47.5606613159],"type":"Point"}
}