{
  "type": "Feature",
  "properties": {
    "iso:country":"CH",
    "sg:address":"Via Giovan Battist Pioda 5",
    "sg:city":"Lugano",
    "sg:orig_category":"Vermietung U Verpachtung von eigenen Immobilien",
    "sg:postcode":"6900",
    "sg:province":"Ticino",
    "wof:name":"Bella-tola 40 Sa",
    "wof:placetype":"venue"
},
  "geometry": {"coordinates":[7.5864248276,46.2146835327],"type":"Point"}
}