{
  "type": "Feature",
  "properties": {
    "iso:country":"CH",
    "sg:address":"Eschenmosenstrasse 5",
    "sg:city":"Bachenb\u00fclach",
    "sg:orig_category":"Zimmerei, Ingenieurholzbau",
    "sg:phone":"+41 18609986",
    "sg:postcode":"8184",
    "sg:province":"Z\u00fcrich",
    "wof:name":"Emil Maag Holzbau",
    "wof:placetype":"venue"
},
  "geometry": {"coordinates":[8.5469808578,47.5039253235],"type":"Point"}
}