{
  "type": "Feature",
  "properties": {
    "addr:full":"Moosstrasse 44 R\u00fcti Z\u00fcrich 8630",
    "addr:housenumber":"44",
    "addr:postcode":"8630",
    "addr:street":"Moosstrasse",
    "iso:country":"CH",
    "sg:address":"Moosstrasse 44",
    "sg:city":"R\u00fcti",
    "sg:classifiers":[
        {
            "category":"Professional",
            "subcategory":"Advertising",
            "type":"Services"
        }
    ],
    "sg:phone":"+41 55 240 92 93",
    "sg:postcode":"8630",
    "sg:province":"Z\u00fcrich",
    "sg:tags":[
        "article",
        "metal"
    ],
    "wof:name":"Trend Design",
    "wof:placetype":"venue"
},
  "geometry": {"coordinates":[8.855115,47.252098],"type":"Point"}
}