{
  "type": "Feature",
  "properties": {
    "iso:country":"CH",
    "sg:address":"Manessestrasse 28",
    "sg:city":"Z\u00fcrich",
    "sg:orig_category":"RESTAURANTS: TEA-ROOMS",
    "sg:phone":"+41 55 220 55 22",
    "sg:postcode":"8003",
    "sg:province":"Z\u00fcrich",
    "wof:name":"Gastronomex Gmbh",
    "wof:placetype":"venue"
},
  "geometry": {"coordinates":[8.8223409653,47.2265663147],"type":"Point"}
}