{
  "type": "Feature",
  "properties": {
    "iso:country":"CH",
    "sg:address":"Nassacherstrasse 15",
    "sg:city":"Effretikon",
    "sg:orig_category":"Sportvereine Schach",
    "sg:postcode":"8307",
    "sg:province":"Z\u00fcrich",
    "wof:name":"Schachclub Langnau",
    "wof:placetype":"venue"
},
  "geometry": {"coordinates":[8.5396108627,47.2921447754],"type":"Point"}
}