{
  "type": "Feature",
  "properties": {
    "iso:country":"CH",
    "sg:address":"Imberg\u00e4sslein 33 4051 Basel. Postfach",
    "sg:city":"Basel",
    "sg:orig_category":"Werbegrafikateliers",
    "sg:phone":"+41 61 261 65 67",
    "sg:postcode":"4001",
    "sg:province":"Basel-Stadt",
    "wof:name":"Ab Stehlin",
    "wof:placetype":"venue"
},
  "geometry": {"coordinates":[7.5856170654,47.557926178],"type":"Point"}
}