{
  "type": "Feature",
  "properties": {
    "iso:country":"CH",
    "sg:address":"Monbijoustrasse 97",
    "sg:city":"Bern",
    "sg:classifiers":[
        {
            "category":"Professional",
            "subcategory":"Management & Consulting",
            "type":"Services"
        }
    ],
    "sg:phone":"+41 31 372 10 00",
    "sg:postcode":"3007",
    "sg:province":"Bern",
    "sg:tags":[
        "hr",
        "resource",
        "consultancy",
        "human"
    ],
    "wof:name":"G Mediajob Ag",
    "wof:placetype":"venue"
},
  "geometry": {"coordinates":[7.4362077713,46.9393882751],"type":"Point"}
}