{
  "type": "Feature",
  "properties": {
    "iso:country":"CH",
    "sg:address":"Pfisternstrasse 20",
    "sg:city":"Oberburg",
    "sg:orig_category":"Elektroinstallation",
    "sg:phone":"+41 34 423 13 31",
    "sg:postcode":"3414",
    "sg:province":"Bern",
    "wof:name":"Baumgartner Elektro Gmbh",
    "wof:placetype":"venue"
},
  "geometry": {"coordinates":[7.6294617653,47.0318565369],"type":"Point"}
}