{
  "type": "Feature",
  "properties": {
    "iso:country":"CH",
    "sg:address":"Mutschellen Bahnhofstr. 157",
    "sg:city":"Berikon",
    "sg:orig_category":"Non-Classified Establishments",
    "sg:postcode":"8965",
    "sg:province":"Aargau",
    "wof:name":"Max Keiser Vbv Vita Life Magnetfeldberat.",
    "wof:placetype":"venue"
},
  "geometry": {"coordinates":[8.3144922256,46.991733551],"type":"Point"}
}