{
  "type": "Feature",
  "properties": {
    "iso:country":"CH",
    "sg:address":"Hauptstrasse 35",
    "sg:city":"K\u00f6lliken",
    "sg:orig_category":"Bauspenglerei Dachdeckerei",
    "sg:phone":"+41 27 957 25 34",
    "sg:postcode":"5742",
    "sg:province":"Aargau",
    "wof:name":"Kurt Bumann Sanit\u00e4r Spenglerei Bedachung",
    "wof:placetype":"venue"
},
  "geometry": {"coordinates":[7.933673,46.111717],"type":"Point"}
}