{
  "type": "Feature",
  "properties": {
    "iso:country":"CH",
    "sg:address":"Ch. Des Salines 26",
    "sg:city":"Yvorne",
    "sg:orig_category":"Sonstiger spezialisierter Hoch U Tiefbau",
    "sg:phone":"+41 24 466 70 30",
    "sg:postcode":"1853",
    "sg:province":"Vaud",
    "wof:name":"Calderini Pietro Sa",
    "wof:placetype":"venue"
},
  "geometry": {"coordinates":[6.9589409828,46.3313713074],"type":"Point"}
}