{
  "type": "Feature",
  "properties": {
    "iso:country":"CH",
    "sg:address":"Lerzenstrasse 16",
    "sg:city":"Dietikon",
    "sg:orig_category":"Sonstiger Grosshandel",
    "sg:phone":"+41 17413459",
    "sg:postcode":"8953",
    "sg:province":"Z\u00fcrich",
    "wof:name":"Leimgruber Ag",
    "wof:placetype":"venue"
},
  "geometry": {"coordinates":[8.3979721069,47.4193077087],"type":"Point"}
}