{
  "type": "Feature",
  "properties": {
    "iso:country":"CH",
    "sg:address":"Oberdorfstrasse 33",
    "sg:city":"M\u00fcnchenbuchsee",
    "sg:orig_category":"Architektur U Ingenieurb\u00fcros Architekturb\u00fcros",
    "sg:phone":"+41 31 869 33 43",
    "sg:postcode":"3053",
    "sg:province":"Bern",
    "wof:name":"Arn + Partner Ag",
    "wof:placetype":"venue"
},
  "geometry": {"coordinates":[7.445947,47.020164],"type":"Point"}
}