{
  "type": "Feature",
  "properties": {
    "addr:full":"Rue Des Eaux-vives 20bis Gen\u00e8ve Gen\u00e8ve 1207",
    "addr:housenumber":"20bis",
    "addr:postcode":"1207",
    "addr:street":"Rue Des Eaux-Vives",
    "iso:country":"CH",
    "sg:address":"Rue Des Eaux-vives 20bis",
    "sg:city":"Gen\u00e8ve",
    "sg:orig_category":"Detailhandel mit Beleuchtungs U Haushaltsgegenst\u00e4nden Detailhandel mit M\u00f6beln",
    "sg:phone":"+41 22 700 13 60",
    "sg:postcode":"1207",
    "sg:province":"Gen\u00e8ve",
    "wof:name":"Arcadia Meubles & Luminaires",
    "wof:placetype":"venue"
},
  "geometry": {"coordinates":[6.158601,46.204109],"type":"Point"}
}