{
  "type": "Feature",
  "properties": {
    "iso:country":"CH",
    "sg:address":"Zugerstrasse 19",
    "sg:city":"Horgen",
    "sg:orig_category":"Detailhandel mit Damenbekleidung Herstellung von konfektionierten Textilwaren ohne Bekleidung",
    "sg:phone":"+41 56 442 20 55",
    "sg:postcode":"8810",
    "sg:province":"Z\u00fcrich",
    "wof:name":"Manuela Obrist Boutique Asante",
    "wof:placetype":"venue"
},
  "geometry": {"coordinates":[8.2068767548,47.4855384827],"type":"Point"}
}