{
  "type": "Feature",
  "properties": {
    "iso:country":"CH",
    "sg:address":"Breitlandstrasse 7",
    "sg:city":"Geroldswil",
    "sg:orig_category":"Herstellung von elektrischen Lampen U Leuchten",
    "sg:postcode":"8954",
    "sg:province":"Z\u00fcrich",
    "wof:name":"Tech-serv, Hunkeler Cuno",
    "wof:placetype":"venue"
},
  "geometry": {"coordinates":[8.4092550278,47.4247512817],"type":"Point"}
}