{
  "type": "Feature",
  "properties": {
    "iso:country":"CH",
    "sg:address":"Trockenloostrasse 81",
    "sg:city":"Regensdorf",
    "sg:orig_category":"Gesundheitswesen",
    "sg:postcode":"8105",
    "sg:province":"Z\u00fcrich",
    "wof:name":"Praxis F\u00fcr Traditionelle Chinesische Medizin, Gaby Kempf",
    "wof:placetype":"venue"
},
  "geometry": {"coordinates":[8.4721384048,47.442325592],"type":"Point"}
}