{
  "type": "Feature",
  "properties": {
    "iso:country":"CH",
    "sg:address":"Avenue Du Th\u00e9\u00e2tre 7 1005 Lausanne Case Postale 3693",
    "sg:city":"Lausanne",
    "sg:orig_category":"Versicherungen Generalagenturen",
    "sg:phone":"+41 79 204 21 75",
    "sg:postcode":"1002",
    "sg:province":"Vaud",
    "wof:name":"Rentenanstalt/swiss Life Agence G\u00e9n\u00e9rale",
    "wof:placetype":"venue"
},
  "geometry": {"coordinates":[6.9099469185,46.4352989197],"type":"Point"}
}