{
  "type": "Feature",
  "properties": {
    "iso:country":"CH",
    "sg:address":"1525",
    "sg:city":"Seigneux",
    "sg:orig_category":"Primarschulen",
    "sg:phone":"+41 32 751 24 79",
    "sg:postcode":"1525",
    "sg:province":"Vaud",
    "wof:name":"Ecole Primaire",
    "wof:placetype":"venue"
},
  "geometry": {"coordinates":[6.8668699265,46.7416305542],"type":"Point"}
}