{
  "type": "Feature",
  "properties": {
    "iso:country":"CH",
    "sg:address":"Z\u00fcrcherstrasse 88 8952 Schlieren. Postfach",
    "sg:city":"Schlieren",
    "sg:orig_category":"Non-Classified Establishments",
    "sg:postcode":"8952",
    "sg:province":"Z\u00fcrich",
    "wof:name":"Naturbau Handels Ag",
    "wof:placetype":"venue"
},
  "geometry": {"coordinates":[8.4594116211,47.3978996277],"type":"Point"}
}