{
  "type": "Feature",
  "properties": {
    "iso:country":"CH",
    "sg:address":"Niederschongau",
    "sg:city":"Schongau",
    "sg:orig_category":"Softwareentwicklung U beratung",
    "sg:postcode":"6288",
    "sg:province":"Luzern",
    "wof:name":"Meier Informatik",
    "wof:placetype":"venue"
},
  "geometry": {"coordinates":[8.263215065,47.2792129517],"type":"Point"}
}