{
  "type": "Feature",
  "properties": {
    "iso:country":"CH",
    "sg:address":"Isenrietstrasse 16",
    "sg:city":"M\u00f6nchaltorf",
    "sg:orig_category":"Werbeagenturen",
    "sg:phone":"+41 19481310",
    "sg:postcode":"8617",
    "sg:province":"Z\u00fcrich",
    "wof:name":"Frey Interactive Media",
    "wof:placetype":"venue"
},
  "geometry": {"coordinates":[8.7195320129,47.3027381897],"type":"Point"}
}