{
  "type": "Feature",
  "properties": {
    "iso:country":"CH",
    "sg:address":"Sonnhaldenstrasse 4",
    "sg:city":"Illnau",
    "sg:orig_category":"Technische B\u00fcros Hoch-& Tiefbau",
    "sg:phone":"+41 52 346 26 06",
    "sg:postcode":"8308",
    "sg:province":"Z\u00fcrich",
    "wof:name":"Rolf & Eva Weilenmann Bautechnisches B\u00fcro",
    "wof:placetype":"venue"
},
  "geometry": {"coordinates":[8.7239246368,47.4074707031],"type":"Point"}
}