{
  "type": "Feature",
  "properties": {
    "iso:country":"CH",
    "sg:address":"Weinbergfussweg 4",
    "sg:city":"Z\u00fcrich",
    "sg:orig_category":"Fachdetailhandel in Verkaufsr\u00e4umen Sonstiger Detailhandel mit Metallwaren, Anstrichmitteln, Glasware",
    "sg:phone":"+41 12620717",
    "sg:postcode":"8000",
    "sg:province":"Z\u00fcrich",
    "wof:name":"House Of Beads Scheurmann Lou",
    "wof:placetype":"venue"
},
  "geometry": {"coordinates":[8.5447053909,47.3789176941],"type":"Point"}
}