{
  "type": "Feature",
  "properties": {
    "addr:full":"Ringstrasse 12 Langenthal Bern 4900",
    "addr:housenumber":"12",
    "addr:postcode":"4900",
    "addr:street":"Ringstrasse;Bern",
    "iso:country":"CH",
    "sg:address":"Ringstrasse 12",
    "sg:city":"Langenthal",
    "sg:orig_category":"Bauingenieurb\u00fcros Vermittlung von Immobilien",
    "sg:phone":"+41 62 922 64 65",
    "sg:postcode":"4900",
    "sg:province":"Bern",
    "wof:name":"B\u00fchler Immobilien",
    "wof:placetype":"venue"
},
  "geometry": {"coordinates":[7.783424,47.214928],"type":"Point"}
}