{
  "type": "Feature",
  "properties": {
    "iso:country":"CH",
    "sg:address":"Piazza Cioccaro 11",
    "sg:city":"Lugano",
    "sg:classifiers":[
        {
            "category":"Government",
            "subcategory":"Post Office",
            "type":"Public Place"
        }
    ],
    "sg:phone":"+41 91 923 37 22",
    "sg:postcode":"6900",
    "sg:province":"Ticino",
    "sg:tags":[
        "caf\u00e9s",
        "tea-rooms"
    ],
    "wof:name":"Caffe-gelateria Pan & Salam",
    "wof:placetype":"venue"
},
  "geometry": {"coordinates":[8.9499168396,46.0044212341],"type":"Point"}
}