{
  "type": "Feature",
  "properties": {
    "iso:country":"CH",
    "sg:address":"Moosweg 3",
    "sg:city":"Fahrwangen",
    "sg:classifiers":[
        {
            "category":"Manufacturing",
            "subcategory":"Metals",
            "type":"Manufacturing & Wholesale Goods"
        }
    ],
    "sg:phone":"+41 56 676 60 40",
    "sg:postcode":"5615",
    "sg:province":"Aargau",
    "sg:tags":[
        "metallurgy",
        "metalworking",
        "processing"
    ],
    "wof:name":"Metall Trend Ag",
    "wof:placetype":"venue"
},
  "geometry": {"coordinates":[8.2447786331,47.2969779968],"type":"Point"}
}