{
  "type": "Feature",
  "properties": {
    "iso:country":"CH",
    "sg:address":"Rue De L'industrie 43 1950 Sion Case Postale 881",
    "sg:city":"Sion",
    "sg:orig_category":"Elektrizit\u00e4tsversorgung Wasserversorgung",
    "sg:phone":"+41 32 751 39 51",
    "sg:postcode":"1951",
    "sg:province":"Valais",
    "wof:name":"Services Industriels Eau-electricit\u00e9",
    "wof:placetype":"venue"
},
  "geometry": {"coordinates":[7.091753006,47.0631828308],"type":"Point"}
}