{
  "type": "Feature",
  "properties": {
    "iso:country":"CH",
    "sg:address":"Zentrum Lai 7078 Lenzerheide/lai. Postfach 934",
    "sg:city":"Lenzerheide/lai",
    "sg:orig_category":"Detailhandel mit Fleisch U Fleischwaren",
    "sg:phone":"+41 81 384 38 37",
    "sg:postcode":"7078",
    "sg:province":"Graubunden",
    "wof:name":"Metzgerei Lai, Schafknecht H.",
    "wof:placetype":"venue"
},
  "geometry": {"coordinates":[9.552740097,46.7285499573],"type":"Point"}
}