{
  "type": "Feature",
  "properties": {
    "iso:country":"CH",
    "sg:address":"M\u00fcnsterplatz 6",
    "sg:city":"Schaffhausen",
    "sg:orig_category":"Innendekorationsateliers",
    "sg:phone":"+41 52 625 99 31",
    "sg:postcode":"8200",
    "sg:province":"Schaffhausen",
    "wof:name":"Egon Fux Innendekorationen",
    "wof:placetype":"venue"
},
  "geometry": {"coordinates":[8.6372299194,47.6956596375],"type":"Point"}
}