{
  "type": "Feature",
  "properties": {
    "iso:country":"CH",
    "sg:address":"9000",
    "sg:city":"St.gallen",
    "sg:orig_category":"Unclassifiable Establishments",
    "sg:postcode":"9000",
    "sg:province":"St. Gallen",
    "wof:name":"Restaurant Zur Schmitte Gmbh",
    "wof:placetype":"venue"
},
  "geometry": {"coordinates":[9.3780097961,47.4236297607],"type":"Point"}
}