{
  "type": "Feature",
  "properties": {
    "iso:country":"CH",
    "sg:address":"Lausanne Rue De 32 1201 Gen\u00e8ve. Postfach",
    "sg:city":"Gen\u00e8ve",
    "sg:orig_category":"RESTAURANTS: TEA-ROOMS",
    "sg:postcode":"1201",
    "sg:province":"Gen\u00e8ve",
    "wof:name":"Nicolas Imboden",
    "wof:placetype":"venue"
},
  "geometry": {"coordinates":[6.1453847885,46.2127151489],"type":"Point"}
}