{
  "type": "Feature",
  "properties": {
    "iso:country":"CH",
    "sg:address":"Ackerstrasse 30",
    "sg:city":"Steckborn",
    "sg:orig_category":"Grosshandel mit Holz U Baustoffen Herstellung von sonstigen chemischen Erzeugnissen",
    "sg:phone":"+41 79 419 73 54",
    "sg:postcode":"8266",
    "sg:province":"Thurgau",
    "wof:name":"Kiesel Beratungs Und Vertriebs-gmbh",
    "wof:placetype":"venue"
},
  "geometry": {"coordinates":[8.9795227051,47.663028717],"type":"Point"}
}