{
  "type": "Feature",
  "properties": {
    "iso:country":"CH",
    "sg:address":"Rue Hermann Geiger 2",
    "sg:city":"Sion",
    "sg:orig_category":"Vermittlung von Immobilien",
    "sg:phone":"+41 27 322 43 92",
    "sg:postcode":"1950",
    "sg:province":"Valais",
    "wof:name":"Jean-marc Bourdin Agence Immobili\u00e8re",
    "wof:placetype":"venue"
},
  "geometry": {"coordinates":[7.3362789154,46.2254981995],"type":"Point"}
}