{
  "type": "Feature",
  "properties": {
    "iso:country":"CH",
    "sg:address":"Br\u00fcggstrasse 62",
    "sg:city":"Biel/bienne",
    "sg:orig_category":"Handel mit Motorr\u00e4dern, Teilen U Zubeh\u00f6r Instandhaltung U Reparatur von Motorr\u00e4dern Mechanische Werk",
    "sg:phone":"+41 32 365 67 15",
    "sg:postcode":"2503",
    "sg:province":"Bern",
    "wof:name":"Heri Velos-motos",
    "wof:placetype":"venue"
},
  "geometry": {"coordinates":[7.2547769547,47.1293983459],"type":"Point"}
}