{
  "type": "Feature",
  "properties": {
    "iso:country":"CH",
    "sg:address":"T\u00f6sstalstrasse 79",
    "sg:city":"Turbenthal",
    "sg:orig_category":"Elektroinstallation",
    "sg:phone":"+41 52 242 65 65",
    "sg:postcode":"8488",
    "sg:province":"Z\u00fcrich",
    "wof:name":"Volta K.sch\u00fctz Ag Elektro Und Telekomm Installationen",
    "wof:placetype":"venue"
},
  "geometry": {"coordinates":[8.844420433,47.4394989014],"type":"Point"}
}