{
  "type": "Feature",
  "properties": {
    "iso:country":"CH",
    "sg:address":"Kantonsstrasse 3931 Eyholz. Postfach",
    "sg:city":"Eyholz",
    "sg:orig_category":"Finanzierungsinstitutionen",
    "sg:phone":"+41 56 622 69 79",
    "sg:postcode":"3931",
    "sg:province":"Valais",
    "wof:name":"Tag-finanz Rappo E.",
    "wof:placetype":"venue"
},
  "geometry": {"coordinates":[8.2819623947,47.3438453674],"type":"Point"}
}