{
  "type": "Feature",
  "properties": {
    "iso:country":"CH",
    "sg:address":"Rocher Rue Du 7",
    "sg:city":"Neuch\u00e2tel",
    "sg:orig_category":"Unclassifiable Establishments",
    "sg:postcode":"2000",
    "sg:province":"Neuch\u00e2tel",
    "wof:name":"Si De La Rue Du Rocher No 7",
    "wof:placetype":"venue"
},
  "geometry": {"coordinates":[6.9359731674,46.9980926514],"type":"Point"}
}