{
  "type": "Feature",
  "properties": {
    "iso:country":"CH",
    "sg:address":"Chemin De La Cure 5 1023 Crissier. Postfach",
    "sg:city":"Crissier",
    "sg:orig_category":"Grosshandel mit Wein U Spirituosen",
    "sg:phone":"+41 21 634 35 33",
    "sg:postcode":"1023",
    "sg:province":"Vaud",
    "wof:name":"Soci\u00e9t\u00e9 Coop\u00e9rative D'achat De Vins Le Chai",
    "wof:placetype":"venue"
},
  "geometry": {"coordinates":[6.5795269012,46.5555648804],"type":"Point"}
}