{
  "type": "Feature",
  "properties": {
    "iso:country":"CH",
    "sg:address":"Aubrigstrasse 14 8645 Jona. Postfach",
    "sg:city":"Jona",
    "sg:orig_category":"Architektur U Ingenieurb\u00fcros",
    "sg:postcode":"8645",
    "sg:province":"St. Gallen",
    "wof:name":"Arabesco Gmbh Raumideen Und Erlebniswelten Raumideen U. Erlebniswelten; Planung, Realisation Usw",
    "wof:placetype":"venue"
},
  "geometry": {"coordinates":[8.83847,47.230938],"type":"Point"}
}