{
  "type": "Feature",
  "properties": {
    "iso:country":"CH",
    "sg:address":"4451",
    "sg:city":"Wintersingen",
    "sg:orig_category":"Detailhandel mit Milcherzeugnissen U Eiern Verarbeitung von Milch",
    "sg:postcode":"4451",
    "sg:province":"Basel-Landschaft",
    "wof:name":"Milchgenossenschaft",
    "wof:placetype":"venue"
},
  "geometry": {"coordinates":[7.8239312172,47.4942245483],"type":"Point"}
}