{
  "type": "Feature",
  "properties": {
    "iso:country":"CH",
    "sg:address":"Geissensteinring 41",
    "sg:city":"Luzern",
    "sg:orig_category":"Grafikateliers, Design",
    "sg:phone":"+41 41 361 00 85",
    "sg:postcode":"6005",
    "sg:province":"Luzern",
    "wof:name":"Ferro Innovation & Design",
    "wof:placetype":"venue"
},
  "geometry": {"coordinates":[8.3141374588,47.0413551331],"type":"Point"}
}