{
  "type": "Feature",
  "properties": {
    "iso:country":"CH",
    "sg:address":"1947",
    "sg:city":"Verseg\u00e8res",
    "sg:orig_category":"Organisationen des Gesundheitswesen",
    "sg:phone":"+41 27 778 11 44",
    "sg:postcode":"1947",
    "sg:province":"Valais",
    "wof:name":"St\u00e9 Des Samaritains Section Bagnes",
    "wof:placetype":"venue"
},
  "geometry": {"coordinates":[7.2332229614,46.0660438538],"type":"Point"}
}