{
  "type": "Feature",
  "properties": {
    "addr:full":"Ch-urdorf Z\u00fcrich 8902",
    "addr:postcode":"8902",
    "iso:country":"CH",
    "sg:city":"Ch-urdorf",
    "sg:orig_category":"Wirtschaft U Handel, Arbeit, Arbeitsvermittlung",
    "sg:postcode":"8902",
    "sg:province":"Z\u00fcrich",
    "wof:name":"Rent A Person Beratungs Ag",
    "wof:placetype":"venue"
},
  "geometry": {"coordinates":[8.428093,47.386627],"type":"Point"}
}