{
  "type": "Feature",
  "properties": {
    "iso:country":"CH",
    "sg:address":"Austrasse 40 8045 Z\u00fcrich. Postfach",
    "sg:city":"Z\u00fcrich",
    "sg:orig_category":"Instandhaltung U Reparatur von Automobilen Tankstellen",
    "sg:phone":"+41 79 354 81 81",
    "sg:postcode":"8045",
    "sg:province":"Z\u00fcrich",
    "wof:name":"Garage Wiedikon Cajacob Bruno Ag",
    "wof:placetype":"venue"
},
  "geometry": {"coordinates":[8.5195903778,47.364982605],"type":"Point"}
}