{
  "type": "Feature",
  "properties": {
    "iso:country":"CH",
    "sg:address":"Kirchplatz 6330 Cham. Postfach 465",
    "sg:city":"Cham",
    "sg:orig_category":"Detailhandel mit M\u00f6beln U Haushaltsgegenst\u00e4nden Verlegen von Fussboden",
    "sg:phone":"+41 41 870 13 45",
    "sg:postcode":"6330",
    "sg:province":"Zug",
    "wof:name":"Wohnstudio Schuler Anton",
    "wof:placetype":"venue"
},
  "geometry": {"coordinates":[8.6322755814,46.8791236877],"type":"Point"}
}