{
  "type": "Feature",
  "properties": {
    "iso:country":"CH",
    "sg:address":"Dorf",
    "sg:city":"Heimenschwand",
    "sg:orig_category":"Wasserversorgung",
    "sg:phone":"+41 33 453 21 94",
    "sg:postcode":"3615",
    "sg:province":"Bern",
    "wof:name":"Wasserversorgung Buchholterberg",
    "wof:placetype":"venue"
},
  "geometry": {"coordinates":[7.694524765,46.8284339905],"type":"Point"}
}