{
  "type": "Feature",
  "properties": {
    "iso:country":"CH",
    "sg:address":"M\u00fchledorfstrasse 9",
    "sg:city":"Bern",
    "sg:orig_category":"P\u00e9dicure Solarien",
    "sg:phone":"+41 31 992 21 11",
    "sg:postcode":"3018",
    "sg:province":"Bern",
    "wof:name":"Kosmetikinstitut Bezzola Gauch Karin",
    "wof:placetype":"venue"
},
  "geometry": {"coordinates":[7.3910241127,46.9455718994],"type":"Point"}
}