{
  "type": "Feature",
  "properties": {
    "iso:country":"CH",
    "sg:address":"Sch\u00fctzenstrasse 28 8280 Kreuzlingen. Postfach",
    "sg:city":"Kreuzlingen",
    "sg:orig_category":"Geb\u00e4ude, Wohnungsreinigung Reinigungsgewerbe",
    "sg:phone":"+41 71 670 06 09",
    "sg:postcode":"8280",
    "sg:province":"Thurgau",
    "wof:name":"Wohn & Textil Aufwertung Gmbh Hauswartarbeiten U. Textilreinigungen Usw",
    "wof:placetype":"venue"
},
  "geometry": {"coordinates":[9.1675777435,47.6496582031],"type":"Point"}
}