{
  "type": "Feature",
  "properties": {
    "addr:full":"Rue Des Combes 7 Ligni\u00e8res Neuch\u00e2tel 2523",
    "addr:housenumber":"7",
    "addr:postcode":"2523",
    "addr:street":"Rue Des Combes;Neucha\u0302Tel",
    "iso:country":"CH",
    "sg:address":"Rue Des Combes 7",
    "sg:city":"Ligni\u00e8res",
    "sg:orig_category":"Datenverarbeitungsdienste",
    "sg:phone":"+41 32 751 37 67",
    "sg:postcode":"2523",
    "sg:province":"Neuch\u00e2tel",
    "wof:name":"Sch\u00e4rer Ren\u00e9 Rs Automation",
    "wof:placetype":"venue"
},
  "geometry": {"coordinates":[7.069223,47.082214],"type":"Point"}
}