{
  "type": "Feature",
  "properties": {
    "iso:country":"CH",
    "sg:address":"B\u00fctschels",
    "sg:city":"Kandersteg",
    "sg:orig_category":"Maler U Glasergewerbe",
    "sg:phone":"+41 41 448 25 44",
    "sg:postcode":"3718",
    "sg:province":"Bern",
    "wof:name":"Egli Ag Eschenbach",
    "wof:placetype":"venue"
},
  "geometry": {"coordinates":[8.3104457855,47.1308097839],"type":"Point"}
}