{
  "type": "Feature",
  "properties": {
    "iso:country":"CH",
    "sg:address":"Rathaus",
    "sg:city":"Fanas",
    "sg:orig_category":"Landesverteidigung, Sozialversicherung \u00d6ffentliche Verwaltung",
    "sg:phone":"+41 81 325 12 47",
    "sg:postcode":"7215",
    "sg:province":"Graubunden",
    "wof:name":"Zivilschutzstelle Fanas",
    "wof:placetype":"venue"
},
  "geometry": {"coordinates":[9.6653470993,46.9849891663],"type":"Point"}
}