{
  "type": "Feature",
  "properties": {
    "iso:country":"CH",
    "sg:address":"Hofmattstrasse 6",
    "sg:city":"Egerkingen",
    "sg:orig_category":"Verwertung von Milch",
    "sg:postcode":"4622",
    "sg:province":"Solothurn",
    "wof:name":"Milchgenossenschaft Egg Bei Langnau I.e.",
    "wof:placetype":"venue"
},
  "geometry": {"coordinates":[7.757589817,46.9491271973],"type":"Point"}
}