{
  "type": "Feature",
  "properties": {
    "iso:country":"CH",
    "sg:address":"Rue Des Charpentiers 30",
    "sg:city":"Morges",
    "sg:classifiers":[
        {
            "category":"Communications",
            "subcategory":"Radio Station",
            "type":"Services"
        }
    ],
    "sg:phone":"+41 21 803 06 96",
    "sg:postcode":"1110",
    "sg:province":"Vaud",
    "sg:tags":[
        "fernsehanstalten",
        "u"
    ],
    "wof:name":"Cin\u00e9 Concept, Wilhem & Cie",
    "wof:placetype":"venue"
},
  "geometry": {"coordinates":[6.4963741302,46.5095977783],"type":"Point"}
}