{
  "type": "Feature",
  "properties": {
    "iso:country":"CH",
    "sg:address":"Viehweidstrasse 300 3123 Belp. Postfach",
    "sg:city":"Belp",
    "sg:orig_category":"Mechanik Stahl U Leichtmetallbau",
    "sg:phone":"+41 31 819 07 27",
    "sg:postcode":"3123",
    "sg:province":"Bern",
    "wof:name":"Metallbau Stoller, Belp",
    "wof:placetype":"venue"
},
  "geometry": {"coordinates":[7.5263900757,46.8873977661],"type":"Point"}
}