{
  "type": "Feature",
  "properties": {
    "iso:country":"CH",
    "sg:address":"Hauptstrasse 7",
    "sg:city":"Rheineck",
    "sg:orig_category":"Zahnarztpraxen",
    "sg:phone":"+41 71 888 22 88",
    "sg:postcode":"9424",
    "sg:province":"St. Gallen",
    "wof:name":"Dr.med.dent.reinhard Kriebel Zahnarzt",
    "wof:placetype":"venue"
},
  "geometry": {"coordinates":[9.5895051956,47.4671020508],"type":"Point"}
}