{
  "type": "Feature",
  "properties": {
    "iso:country":"CH",
    "sg:address":"7425",
    "sg:city":"Masein",
    "sg:orig_category":"Gemeindeverwaltungen",
    "sg:phone":"+41 81 651 20 09",
    "sg:postcode":"7425",
    "sg:province":"Graubunden",
    "wof:name":"Gemeindeverwaltung Masein",
    "wof:placetype":"venue"
},
  "geometry": {"coordinates":[9.4189901352,46.6870002747],"type":"Point"}
}