{
  "type": "Feature",
  "properties": {
    "iso:country":"CH",
    "sg:address":"Rue Etraz 12",
    "sg:city":"Lausanne",
    "sg:orig_category":"Naturheil\u00e4rzte and Heilpraktiker",
    "sg:phone":"+41 32 751 67 02",
    "sg:postcode":"1003",
    "sg:province":"Vaud",
    "wof:name":"Jean-jacques Munari Naturopathe",
    "wof:placetype":"venue"
},
  "geometry": {"coordinates":[7.0867509842,47.0612106323],"type":"Point"}
}