{
  "type": "Feature",
  "properties": {
    "iso:country":"CH",
    "sg:address":"Moschtiweg 1",
    "sg:city":"W\u00e4ngi",
    "sg:orig_category":"Bau von Strassen, Sportanlagen U Bahnverkehrsstrecken Chemische Industrie",
    "sg:phone":"+41 52 366 41 90",
    "sg:postcode":"9545",
    "sg:province":"Thurgau",
    "wof:name":"Labosim Markierungs Ag",
    "wof:placetype":"venue"
},
  "geometry": {"coordinates":[8.973155,47.50629],"type":"Point"}
}