{
  "type": "Feature",
  "properties": {
    "iso:country":"CH",
    "sg:address":"6533",
    "sg:city":"Lumino",
    "sg:orig_category":"Sonstige Personenbef\u00f6rderung im Landverkehr",
    "sg:phone":"+41 91 829 26 30",
    "sg:postcode":"6533",
    "sg:province":"Ticino",
    "wof:name":"Pasta Branda Viaggi Sa",
    "wof:placetype":"venue"
},
  "geometry": {"coordinates":[9.065369606,46.23072052],"type":"Point"}
}