{
  "type": "Feature",
  "properties": {
    "iso:country":"CH",
    "sg:address":"Fl\u00e9oles Chemin Des 34 2503 Biel/bienne. Postfach",
    "sg:city":"Biel/bienne",
    "sg:orig_category":"Herstellung von Sportger\u00e4ten",
    "sg:postcode":"2503",
    "sg:province":"Bern",
    "wof:name":"Aqua Fun Sport J.-p. Grandjean",
    "wof:placetype":"venue"
},
  "geometry": {"coordinates":[7.2472572327,47.1408882141],"type":"Point"}
}