{
  "type": "Feature",
  "properties": {
    "iso:country":"CH",
    "sg:address":"Rue Neuve 1",
    "sg:city":"Cossonay-ville",
    "sg:orig_category":"Gemeindeverwaltungen",
    "sg:phone":"+41 21 800 31 10",
    "sg:postcode":"1304",
    "sg:province":"Vaud",
    "wof:name":"Administration Communale De Cottens",
    "wof:placetype":"venue"
},
  "geometry": {"coordinates":[6.4544811249,46.5707092285],"type":"Point"}
}