{
  "type": "Feature",
  "properties": {
    "iso:country":"CH",
    "sg:address":"Hinterbergstrasse 67",
    "sg:city":"Galgenen",
    "sg:orig_category":"Instandhaltung U Reparatur von Automobilen Mechanische Werkst\u00e4tten",
    "sg:phone":"+41 55 440 16 36",
    "sg:postcode":"8854",
    "sg:province":"Schwyz",
    "wof:name":"Kamer Alfred.",
    "wof:placetype":"venue"
},
  "geometry": {"coordinates":[8.864865303,47.1687583923],"type":"Point"}
}