{
  "type": "Feature",
  "properties": {
    "iso:country":"CH",
    "sg:address":"Landvogt Waser-strasse 65 8405 Iberg (winterthur). Postfach",
    "sg:city":"Seen",
    "sg:orig_category":"Fachdetailhandel in Verkaufsr\u00e4umen Wirtschaftspr\u00fcfung, Steuerberatung U Treuhand",
    "sg:phone":"+41 52 232 85 58",
    "sg:postcode":"8405",
    "sg:province":"Z\u00fcrich",
    "wof:name":"Huwiler Paul Handel + Treuhand Polierpech F\u00fcr Optische Ger\u00e4te, Treuhandmandate",
    "wof:placetype":"venue"
},
  "geometry": {"coordinates":[8.7607221603,47.4835586548],"type":"Point"}
}