{
  "type": "Feature",
  "properties": {
    "iso:country":"CH",
    "sg:address":"Via S.gottardo 156",
    "sg:city":"Savosa",
    "sg:orig_category":"Instandhaltung U Reparatur von Automobilen",
    "sg:phone":"+41 91 967 24 73",
    "sg:postcode":"6942",
    "sg:province":"Ticino",
    "wof:name":"Peter Strohmayer Selleria D'auto",
    "wof:placetype":"venue"
},
  "geometry": {"coordinates":[8.9380273819,46.0193252563],"type":"Point"}
}