{
  "type": "Feature",
  "properties": {
    "iso:country":"CH",
    "sg:address":"Ausserdorfweg 4",
    "sg:city":"Siebnen",
    "sg:orig_category":"Malerei",
    "sg:phone":"+41 55 440 24 64",
    "sg:postcode":"8854",
    "sg:province":"Schwyz",
    "wof:name":"Bruno Z\u00fcger Malergesch\u00e4ft",
    "wof:placetype":"venue"
},
  "geometry": {"coordinates":[8.9031763077,47.1753921509],"type":"Point"}
}