{
  "type": "Feature",
  "properties": {
    "iso:country":"CH",
    "sg:address":"Ueberlandstrasse 180",
    "sg:city":"Z\u00fcrich",
    "sg:orig_category":"Autotransporte M\u00f6bel Autotransporte international",
    "sg:phone":"+41 13227070",
    "sg:postcode":"8051",
    "sg:province":"Z\u00fcrich",
    "wof:name":"N\u00e4geli Umz\u00fcge Ag",
    "wof:placetype":"venue"
},
  "geometry": {"coordinates":[8.567631,47.408146],"type":"Point"}
}