{
  "type": "Feature",
  "properties": {
    "iso:country":"CH",
    "sg:address":"Z\u00fcrcherstrasse 1",
    "sg:city":"Rheinfelden",
    "sg:orig_category":"H\u00f6rger\u00e4te Detailhandel",
    "sg:phone":"+41 61 831 05 15",
    "sg:postcode":"4310",
    "sg:province":"Aargau",
    "wof:name":"B\u00fcrgin Ag H\u00f6rberatung",
    "wof:placetype":"venue"
},
  "geometry": {"coordinates":[7.7961878777,47.5531463623],"type":"Point"}
}