{
  "type": "Feature",
  "properties": {
    "iso:country":"CH",
    "sg:address":"Rosenburgerstrasse 36",
    "sg:city":"M\u00fcnchenstein",
    "sg:orig_category":"Dachdeckerei Zimmerei, Dachdeckerei, Bauspenglerei U Abdichtung",
    "sg:phone":"+41 61 701 62 18",
    "sg:postcode":"4142",
    "sg:province":"Basel-Landschaft",
    "wof:name":"Hoba Bedachungen Hostettler & Juen",
    "wof:placetype":"venue"
},
  "geometry": {"coordinates":[7.60277,47.515598],"type":"Point"}
}