{
  "type": "Feature",
  "properties": {
    "iso:country":"CH",
    "sg:address":"Chemin Des Vignes 38",
    "sg:city":"Gland",
    "sg:orig_category":"Stukkateurgewerbe, Gipserei U Verputzerei",
    "sg:phone":"+41 22 364 87 57",
    "sg:postcode":"1196",
    "sg:province":"Vaud",
    "wof:name":"Simeone Rocco",
    "wof:placetype":"venue"
},
  "geometry": {"coordinates":[6.2709608078,46.4248695374],"type":"Point"}
}