{
  "type": "Feature",
  "properties": {
    "iso:country":"CH",
    "sg:address":"Immeuble Le Rawyl",
    "sg:city":"Montana-vermala",
    "sg:orig_category":"Detailhandel mit Geschenkartikeln U Souvenirs",
    "sg:phone":"+41 27 481 44 34",
    "sg:postcode":"3962",
    "wof:name":"Mich\u00e8le Bramaz Boutique Au Bonheur Des Dames",
    "wof:placetype":"venue"
},
  "geometry": {"coordinates":[7.4924340248,46.3144187927],"type":"Point"}
}