{
  "type": "Feature",
  "properties": {
    "iso:country":"CH",
    "sg:address":"Oberwilerstrasse 109",
    "sg:city":"N\u00fcrensdorf",
    "sg:orig_category":"RESTAURANTS: TEA-ROOMS",
    "sg:phone":"+41 18365155",
    "sg:postcode":"8309",
    "sg:province":"Z\u00fcrich",
    "wof:name":"Restaurant Zur Linde Bea Kappeler",
    "wof:placetype":"venue"
},
  "geometry": {"coordinates":[8.6394968033,47.4638748169],"type":"Point"}
}