{
  "type": "Feature",
  "properties": {
    "iso:country":"CH",
    "sg:address":"Rue Des Oeuches 10",
    "sg:city":"Montagne-moutier",
    "sg:orig_category":"Wirtschaftspr\u00fcfung, Steuerberatung U Treuhand",
    "sg:phone":"+41 32 493 53 52",
    "sg:postcode":"2740",
    "sg:province":"Bern",
    "wof:name":"Fiduciaire Ch\u00e9telat Moutier",
    "wof:placetype":"venue"
},
  "geometry": {"coordinates":[7.3711481094,47.2770004272],"type":"Point"}
}