{
  "type": "Feature",
  "properties": {
    "iso:country":"CH",
    "sg:address":"Schaffhauserstrasse 222 8057 Z\u00fcrich. Postfach",
    "sg:city":"Z\u00fcrich",
    "sg:orig_category":"Detailhandel mit Antiquit\u00e4ten U Gebrauchtwaren in Verkaufsr\u00e4umen",
    "sg:postcode":"8001",
    "sg:province":"Z\u00fcrich",
    "wof:name":"Antiquariat W\u00fcthrich Alte B\u00fccher; An, Verkauf, Versand",
    "wof:placetype":"venue"
},
  "geometry": {"coordinates":[8.545841,47.401722],"type":"Point"}
}