{
  "type": "Feature",
  "properties": {
    "iso:country":"CH",
    "sg:address":"Gipserh\u00fctte 1",
    "sg:city":"Ennenda",
    "sg:orig_category":"Handel mit Automobilen",
    "sg:phone":"+41 55 640 66 44",
    "sg:postcode":"8755",
    "sg:province":"Glarus",
    "wof:name":"Elsener Garage Ag & Autohandel",
    "wof:placetype":"venue"
},
  "geometry": {"coordinates":[9.0793762207,47.0304946899],"type":"Point"}
}