{
  "type": "Feature",
  "properties": {
    "iso:country":"CH",
    "sg:address":"Stauffacherstrasse 130a",
    "sg:city":"Bern",
    "sg:orig_category":"Herstellung von Metallkonstruktionen",
    "sg:phone":"+41 62 893 33 30",
    "sg:postcode":"3000",
    "sg:province":"Bern",
    "wof:name":"Casemont Ag",
    "wof:placetype":"venue"
},
  "geometry": {"coordinates":[8.168841362,47.4263458252],"type":"Point"}
}