{
  "type": "Feature",
  "properties": {
    "iso:country":"CH",
    "sg:address":"Gerliswilstrasse 46",
    "sg:city":"Emmenbr\u00fccke",
    "sg:classifiers":[
        {
            "category":"Government",
            "subcategory":"Post Office",
            "type":"Public Place"
        }
    ],
    "sg:phone":"+41 41 260 36 96",
    "sg:postcode":"6020",
    "sg:province":"Luzern",
    "sg:tags":[
        "caf\u00e9s",
        "tea-rooms"
    ],
    "wof:name":"Caf\u00e9 Rio",
    "wof:placetype":"venue"
},
  "geometry": {"coordinates":[8.2777690887,47.0735969543],"type":"Point"}
}