{
  "type": "Feature",
  "properties": {
    "addr:full":"Zinzikerstrasse 11 8404 Oberwinterthur. Postfach Winterthur Z\u00fcrich 8404",
    "addr:housenumber":"11",
    "addr:postcode":"8404;8404",
    "addr:street":"Zinzikerstrasse;Postfach",
    "iso:country":"CH",
    "sg:address":"Zinzikerstrasse 11 8404 Oberwinterthur. Postfach",
    "sg:city":"Winterthur",
    "sg:orig_category":"Architektur U Ingenieurb\u00fcros",
    "sg:phone":"+41 52 242 48 69",
    "sg:postcode":"8404",
    "sg:province":"Z\u00fcrich",
    "wof:name":"Raymond Sommerhalder Beratender Ingenieur F\u00fcr Technische Geb\u00e4udeausr\u00fcstung",
    "wof:placetype":"venue"
},
  "geometry": {"coordinates":[8.755463,47.517014],"type":"Point"}
}