{
  "type": "Feature",
  "properties": {
    "iso:country":"CH",
    "sg:address":"3434",
    "sg:city":"Obergoldbach",
    "sg:classifiers":[
        {
            "category":"Education",
            "subcategory":"Vocational School",
            "type":"Public Place"
        }
    ],
    "sg:phone":"+41 31 701 13 36",
    "sg:postcode":"3434",
    "sg:province":"Bern",
    "sg:tags":[
        "koch-",
        "haushaltschulen"
    ],
    "wof:name":"Haushaltungsschule Schulhaus Landiswil",
    "wof:placetype":"venue"
},
  "geometry": {"coordinates":[7.6721100807,46.9601593018],"type":"Point"}
}