{
  "type": "Feature",
  "properties": {
    "iso:country":"CH",
    "sg:address":"Huggerwaldstrasse 406",
    "sg:city":"Kleinl\u00fctzel",
    "sg:orig_category":"Herstellung von Ausbauelementen aus Metall Herstellung von Elektromotoren, Generatoren U Transformat",
    "sg:phone":"+41 61 771 06 58",
    "sg:postcode":"4245",
    "sg:province":"Solothurn",
    "wof:name":"Hr Huber Metallbau",
    "wof:placetype":"venue"
},
  "geometry": {"coordinates":[7.4181118011,47.4237861633],"type":"Point"}
}