{
  "type": "Feature",
  "properties": {
    "iso:country":"CH",
    "sg:address":"Balberstrasse 49 8038 Z\u00fcrich. Postfach 319",
    "sg:city":"Z\u00fcrich",
    "sg:orig_category":"Sportvereine P\u00e9tanque",
    "sg:phone":"+41 13629944",
    "sg:postcode":"8060",
    "sg:province":"Z\u00fcrich",
    "wof:name":"P\u00e9tanque-club Wollishofen",
    "wof:placetype":"venue"
},
  "geometry": {"coordinates":[8.5276317596,47.3389930725],"type":"Point"}
}