{
  "type": "Feature",
  "properties": {
    "iso:country":"CH",
    "sg:address":"Curtins 101a",
    "sg:city":"Zernez",
    "sg:orig_category":"Sportschulen Ski-& Snowboardschulen",
    "sg:phone":"+41 81 856 15 70",
    "sg:postcode":"7530",
    "sg:province":"Graubunden",
    "wof:name":"Svizra Schweiz.langlaufschule",
    "wof:placetype":"venue"
},
  "geometry": {"coordinates":[10.0944595337,46.7029647827],"type":"Point"}
}