{
  "type": "Feature",
  "properties": {
    "addr:full":"Rue Du 31-d\u00e9cembre 38 Gen\u00e8ve Gen\u00e8ve 1207",
    "addr:housenumber":"38",
    "addr:postcode":"1207",
    "addr:street":"Rue Du 31-De \u0301Cembre",
    "iso:country":"CH",
    "sg:address":"Rue Du 31-d\u00e9cembre 38",
    "sg:city":"Gen\u00e8ve",
    "sg:classifiers":[
        {
            "category":"Restaurant",
            "type":"Food & Drink"
        }
    ],
    "sg:phone":"+41 22 736 68 00",
    "sg:postcode":"1207",
    "sg:province":"Gen\u00e8ve",
    "sg:tags":[
        "caterer"
    ],
    "wof:name":"Pizzeria Mamma Speedy",
    "wof:placetype":"venue"
},
  "geometry": {"coordinates":[6.160498,46.202545],"type":"Point"}
}