{
  "type": "Feature",
  "properties": {
    "iso:country":"CH",
    "sg:address":"Ruederstrasse 13",
    "sg:city":"Sch\u00f6ftland",
    "sg:orig_category":"Bauspenglerei Sanit\u00e4r, Heizungs U L\u00fcftungsinstallation",
    "sg:phone":"+41 62 721 16 22",
    "sg:postcode":"5040",
    "sg:province":"Aargau",
    "wof:name":"F\u00e4s Installationen Ag",
    "wof:placetype":"venue"
},
  "geometry": {"coordinates":[8.0553,47.30492],"type":"Point"}
}