{
  "type": "Feature",
  "properties": {
    "iso:country":"CH",
    "sg:address":"Sandb\u00fchlstrasse 2 5607 H\u00e4gglingen. Postfach 83",
    "sg:city":"H\u00e4gglingen",
    "sg:orig_category":"Herstellung sonstiger Textilien Herstellung von sonstiger Bekleidung U Bekleidungszubeh\u00f6r",
    "sg:phone":"+41 56 624 30 55",
    "sg:postcode":"5607",
    "sg:province":"Aargau",
    "wof:name":"G. Geissmann-huber Ag",
    "wof:placetype":"venue"
},
  "geometry": {"coordinates":[8.2546854019,47.3887138367],"type":"Point"}
}