{
  "type": "Feature",
  "properties": {
    "iso:country":"CH",
    "sg:address":"6516",
    "sg:city":"Cugnasco",
    "sg:orig_category":"Allgemeiner Hoch U Tiefbau",
    "sg:phone":"+41 91 859 21 10",
    "sg:postcode":"6516",
    "sg:province":"Ticino",
    "wof:name":"Costruzioni Losa Sa",
    "wof:placetype":"venue"
},
  "geometry": {"coordinates":[8.91774,46.175251],"type":"Point"}
}