{
  "type": "Feature",
  "properties": {
    "addr:full":"Industriestrasse 19 Neuendorf Solothurn 4623",
    "addr:housenumber":"19",
    "addr:postcode":"4623",
    "addr:street":"Industriestrasse",
    "iso:country":"CH",
    "sg:address":"Industriestrasse 19",
    "sg:city":"Neuendorf",
    "sg:orig_category":"Abwasserreinigung, Abfallbeseitigung U sonstige Entsorgung R\u00fcckgewinnung U Vorbereitung f\u00fcr die Wied",
    "sg:phone":"+41 62 398 50 41",
    "sg:postcode":"4623",
    "sg:province":"Solothurn",
    "wof:name":"Abo Bohni Gmbh",
    "wof:placetype":"venue"
},
  "geometry": {"coordinates":[7.783882,47.311375],"type":"Point"}
}