{
  "type": "Feature",
  "properties": {
    "addr:full":"Geissensteinring 12 Luzern Luzern 6005",
    "addr:housenumber":"12",
    "addr:postcode":"6005",
    "addr:street":"Geissensteinring",
    "iso:country":"CH",
    "sg:address":"Geissensteinring 12",
    "sg:city":"Luzern",
    "sg:orig_category":"Bauschreinerei",
    "sg:phone":"+41 41 360 48 18",
    "sg:postcode":"6005",
    "sg:province":"Luzern",
    "wof:name":"Roland Kaufmann Schreinerei",
    "wof:placetype":"venue"
},
  "geometry": {"coordinates":[8.310081,47.039932],"type":"Point"}
}