{
  "type": "Feature",
  "properties": {
    "iso:country":"CH",
    "sg:address":"Seebleichestrasse 27a",
    "sg:city":"Rorschacherberg",
    "sg:orig_category":"Detailhandel mit Teppichen Verlegen von Fussboden",
    "sg:phone":"+41 79 409 33 21",
    "sg:postcode":"9404",
    "sg:province":"St. Gallen",
    "wof:name":"Scurti D\u00e9co D\u00e9coration D'int\u00e9rieur",
    "wof:placetype":"venue"
},
  "geometry": {"coordinates":[6.8283629417,47.1004486084],"type":"Point"}
}