{
  "type": "Feature",
  "properties": {
    "iso:country":"CH",
    "sg:address":"Lontschenenweg 43",
    "sg:city":"Thun",
    "sg:orig_category":"Vereine Frauen Vereine Gemeinn\u00fctzige",
    "sg:phone":"+41 33 336 49 01",
    "sg:postcode":"3608",
    "sg:province":"Bern",
    "wof:name":"Gemeinn.frauenver.str\u00e4ttligen",
    "wof:placetype":"venue"
},
  "geometry": {"coordinates":[7.600317955,46.7415504456],"type":"Point"}
}