{
  "type": "Feature",
  "properties": {
    "iso:country":"CH",
    "sg:address":"Br\u00fc\u00f6l 10",
    "sg:city":"Schwyz",
    "sg:orig_category":"Vermittlungen Wohnungs-Agenturen,",
    "sg:postcode":"6430",
    "sg:province":"Schwyz",
    "wof:name":"Ag F\u00fcr Wohnungseigentum Br\u00fc\u00f6l",
    "wof:placetype":"venue"
},
  "geometry": {"coordinates":[8.6535720825,47.0191268921],"type":"Point"}
}