{
  "type": "Feature",
  "properties": {
    "iso:country":"CH",
    "sg:address":"Ch\u00e4lenrain 6053 Alpnachstad. Postfach",
    "sg:city":"Alpnachstad",
    "sg:orig_category":"Sonstige mit der Informatik verbundene T\u00e4tigkeiten",
    "sg:phone":"+41 41 670 38 58",
    "sg:postcode":"6053",
    "sg:province":"Obwalden",
    "wof:name":"Axes Systems Ag",
    "wof:placetype":"venue"
},
  "geometry": {"coordinates":[8.2725362778,46.9520606995],"type":"Point"}
}