{
  "type": "Feature",
  "properties": {
    "iso:country":"CH",
    "sg:address":"Sandacker 17 8052 Seebach. Postfach 184",
    "sg:city":"Z\u00fcrich",
    "sg:orig_category":"Fachdetailhandel in Verkaufsr\u00e4umen",
    "sg:postcode":"8052",
    "sg:province":"Z\u00fcrich",
    "wof:name":"Marti Alfred, Inh. Hans Marti.",
    "wof:placetype":"venue"
},
  "geometry": {"coordinates":[8.5402402878,47.4224815369],"type":"Point"}
}