{
  "type": "Feature",
  "properties": {
    "iso:country":"CH",
    "sg:address":"Rue Du Rh\u00f4ne 15",
    "sg:city":"Gen\u00e8ve",
    "sg:orig_category":"Detailhandel mit Damenbekleidung Detailhandel mit Herrenbekleidung",
    "sg:phone":"+41 22 310 60 88",
    "sg:postcode":"1204",
    "sg:province":"Gen\u00e8ve",
    "wof:name":"Olivier & Fran\u00e7ois Ausoni Sa Mode Pour Dames",
    "wof:placetype":"venue"
},
  "geometry": {"coordinates":[6.144862175,46.2046928406],"type":"Point"}
}