{
  "type": "Feature",
  "properties": {
    "addr:full":"Oberhaus 371 Gais Appenzell Ausserrhoden 9056",
    "addr:housenumber":"371",
    "addr:postcode":"9056",
    "addr:street":"Oberhaus;Appenzell Ausserrhoden",
    "iso:country":"CH",
    "sg:address":"Oberhaus 371",
    "sg:city":"Gais",
    "sg:orig_category":"Airveyor Blowers",
    "sg:phone":"+41 71 793 30 50",
    "sg:postcode":"9056",
    "sg:province":"Appenzell Ausserrhoden",
    "wof:name":"Basso Trading",
    "wof:placetype":"venue"
},
  "geometry": {"coordinates":[9.45359,47.362343],"type":"Point"}
}