{
  "type": "Feature",
  "properties": {
    "iso:country":"CH",
    "sg:address":"Altwiesenstrasse 87 8051 Z\u00fcrich. Postfach",
    "sg:city":"Z\u00fcrich",
    "sg:orig_category":"Softwareentwicklung U beratung",
    "sg:postcode":"8051",
    "sg:province":"Z\u00fcrich",
    "wof:name":"Atlantica.ch Seitz Informatik-dienstleistungen",
    "wof:placetype":"venue"
},
  "geometry": {"coordinates":[8.5806350708,47.4031524658],"type":"Point"}
}