{
  "type": "Feature",
  "properties": {
    "iso:country":"CH",
    "sg:address":"Fabrikstrasse 44",
    "sg:city":"Z\u00fcrich",
    "sg:orig_category":"Grosshandel mit Nahrungsmitteln, Getr\u00e4nken U Tabakwaren ohne ausgepr\u00e4gten Schwerpunkt",
    "sg:phone":"+41 12711819",
    "sg:postcode":"8005",
    "sg:province":"Z\u00fcrich",
    "wof:name":"Villanueva Import & Handel Gmbh",
    "wof:placetype":"venue"
},
  "geometry": {"coordinates":[8.5261383057,47.3849945068],"type":"Point"}
}