{
  "type": "Feature",
  "properties": {
    "iso:country":"CH",
    "sg:address":"Guggiweg 20",
    "sg:city":"Zug",
    "sg:orig_category":"Unclassifiable Establishments",
    "sg:postcode":"6300",
    "sg:province":"Zug",
    "wof:name":"Infosnake Gmbh",
    "wof:placetype":"venue"
},
  "geometry": {"coordinates":[8.5195884705,47.1681213379],"type":"Point"}
}