{
  "type": "Feature",
  "properties": {
    "iso:country":"CH",
    "sg:address":"Sunnefeld 7 8634 Hombrechtikon. Postfach",
    "sg:city":"Hombrechtikon",
    "sg:orig_category":"Sonstiger Grosshandel",
    "sg:phone":"+41 55 244 28 66",
    "sg:postcode":"8634",
    "sg:province":"Z\u00fcrich",
    "wof:name":"Kunz Trading Warenhandel. Beratung Im Bereich Pr, Marketing Usw",
    "wof:placetype":"venue"
},
  "geometry": {"coordinates":[8.7763881683,47.2471961975],"type":"Point"}
}