{
  "type": "Feature",
  "properties": {
    "iso:country":"CH",
    "sg:address":"Lochr\u00fctiried",
    "sg:city":"Wolfenschiessen",
    "sg:classifiers":[
        {
            "category":"Professional",
            "subcategory":"Engineering",
            "type":"Services"
        }
    ],
    "sg:phone":"+41 41 629 77 00",
    "sg:postcode":"6386",
    "sg:province":"Nidwalden",
    "sg:tags":[
        "machine",
        "-",
        "mechanical"
    ],
    "wof:name":"Bettermann Ag",
    "wof:placetype":"venue"
},
  "geometry": {"coordinates":[8.3956546783,46.9103431702],"type":"Point"}
}