{
  "type": "Feature",
  "properties": {
    "iso:country":"CH",
    "sg:address":"Via Vallemaggia 83",
    "sg:city":"Locarno",
    "sg:classifiers":[
        {
            "category":"Restaurant",
            "type":"Food & Drink"
        }
    ],
    "sg:phone":"+41 91 751 86 26",
    "sg:postcode":"6600",
    "sg:province":"Ticino",
    "wof:name":"Ristorante La Pergola",
    "wof:placetype":"venue"
},
  "geometry": {"coordinates":[8.7891702652,46.169719696],"type":"Point"}
}