{
  "type": "Feature",
  "properties": {
    "iso:country":"CH",
    "sg:address":"Eigerweg 1",
    "sg:city":"Kirchlindach",
    "sg:orig_category":"Politische Parteien FDP",
    "sg:phone":"+41 31 829 50 20",
    "sg:postcode":"3038",
    "sg:province":"Bern",
    "wof:name":"Fdp Sektion Kirchlindach",
    "wof:placetype":"venue"
},
  "geometry": {"coordinates":[7.4106149673,46.9969367981],"type":"Point"}
}