{
  "type": "Feature",
  "properties": {
    "iso:country":"CH",
    "sg:address":"R\u00fctistrasse",
    "sg:city":"Giswil",
    "sg:orig_category":"Interessenvertretungen",
    "sg:postcode":"6074",
    "sg:province":"Obwalden",
    "wof:name":"Genossenschaft Quartier\u00fcberbauung M\u00f6rlialp",
    "wof:placetype":"venue"
},
  "geometry": {"coordinates":[8.1619405746,46.8501396179],"type":"Point"}
}