{
  "type": "Feature",
  "properties": {
    "iso:country":"CH",
    "sg:address":"Hauptstrasse 257",
    "sg:city":"Zetzwil",
    "sg:orig_category":"Grosshandel mit Datenverarbeitungsger\u00e4ten Hardwareberatung",
    "sg:phone":"+41 62 773 17 72",
    "sg:postcode":"5732",
    "sg:province":"Aargau",
    "wof:name":"De Bastiani Edv-vertrieb",
    "wof:placetype":"venue"
},
  "geometry": {"coordinates":[8.1470136642,47.2879753113],"type":"Point"}
}