{
  "type": "Feature",
  "properties": {
    "iso:country":"CH",
    "sg:address":"Rue Gustave-amweg 9a",
    "sg:city":"Porrentruy",
    "sg:orig_category":"Autogaragen Einzelhandel mit Automobilen",
    "sg:postcode":"2900",
    "sg:province":"Jura",
    "wof:name":"Garage Central, Hulman & Fils Agce Mitsubishi",
    "wof:placetype":"venue"
},
  "geometry": {"coordinates":[7.076591,47.418125],"type":"Point"}
}