{
  "type": "Feature",
  "properties": {
    "iso:country":"CH",
    "sg:address":"Stachenweg 5",
    "sg:city":"Arbon",
    "sg:orig_category":"Strassenbau",
    "sg:phone":"+41 71 446 03 44",
    "sg:postcode":"9320",
    "sg:province":"Thurgau",
    "wof:name":"Meyerhans Ag Strassen-& Tiefbau",
    "wof:placetype":"venue"
},
  "geometry": {"coordinates":[9.4138507843,47.5070381165],"type":"Point"}
}