{
  "type": "Feature",
  "properties": {
    "iso:country":"CH",
    "sg:address":"Museggstrasse 21 6004 Luzern. Postfach",
    "sg:city":"Luzern",
    "sg:orig_category":"Konkurs- and Betreibungs\u00e4mter",
    "sg:phone":"+41 41 410 56 36",
    "sg:postcode":"6002",
    "sg:province":"Luzern",
    "wof:name":"Betreibungsamt Der Stadt Luzern",
    "wof:placetype":"venue"
},
  "geometry": {"coordinates":[8.3066902161,47.0544776917],"type":"Point"}
}