{
  "type": "Feature",
  "properties": {
    "iso:country":"CH",
    "sg:address":"Hauptstrasse 16",
    "sg:city":"Bichelsee",
    "sg:orig_category":"Fotografische Ateliers",
    "sg:phone":"+41 56 633 79 55",
    "sg:postcode":"8363",
    "sg:province":"Thurgau",
    "wof:name":"Daniel Mengi Fotografisches Atelier",
    "wof:placetype":"venue"
},
  "geometry": {"coordinates":[8.3401050568,47.3501625061],"type":"Point"}
}