{
  "type": "Feature",
  "properties": {
    "iso:country":"CH",
    "sg:address":"Axensteinstrasse 21",
    "sg:city":"St.gallen",
    "sg:orig_category":"Unclassifiable Establishments",
    "sg:postcode":"9000",
    "sg:province":"St. Gallen",
    "wof:name":"Stiftung Zur Weiterbildung Reisender Kaufleute",
    "wof:placetype":"venue"
},
  "geometry": {"coordinates":[9.3865871429,47.4258117676],"type":"Point"}
}