{
  "type": "Feature",
  "properties": {
    "iso:country":"CH",
    "sg:address":"Witikonerstrasse 359",
    "sg:city":"Z\u00fcrich",
    "sg:orig_category":"Kinderkrippen U horte",
    "sg:phone":"+41 14220266",
    "sg:postcode":"8053",
    "sg:province":"Z\u00fcrich",
    "wof:name":"Hort Des Schulamtes Der Stadt Z\u00fcrich",
    "wof:placetype":"venue"
},
  "geometry": {"coordinates":[8.5909013748,47.3589782715],"type":"Point"}
}