{
  "type": "Feature",
  "properties": {
    "iso:country":"CH",
    "sg:address":"Place Beaulieu",
    "sg:city":"Sierre",
    "sg:orig_category":"Primarschulen",
    "sg:phone":"+41 27 455 54 73",
    "sg:postcode":"3960",
    "sg:province":"Valais",
    "wof:name":"Ecole Primaire Beaulieu",
    "wof:placetype":"venue"
},
  "geometry": {"coordinates":[7.5289888382,46.2913818359],"type":"Point"}
}