{
  "type": "Feature",
  "properties": {
    "iso:country":"CH",
    "sg:address":"Kyburgerweg 1",
    "sg:city":"Dietlikon",
    "sg:orig_category":"Innendekorationsateliers",
    "sg:phone":"+41 18333887",
    "sg:postcode":"8305",
    "sg:province":"Z\u00fcrich",
    "wof:name":"Reinhold Bliggenstorfer Tapezierer Dekorateur",
    "wof:placetype":"venue"
},
  "geometry": {"coordinates":[8.6176128387,47.4263496399],"type":"Point"}
}