{
  "type": "Feature",
  "properties": {
    "addr:full":"6939 Arosio Ticino 6939",
    "addr:housenumber":"6939",
    "addr:postcode":"6939",
    "addr:street":"Arosio Ticino",
    "iso:country":"CH",
    "sg:address":"6939",
    "sg:city":"Arosio",
    "sg:orig_category":"Allgemeiner Hochbau Strassenbau",
    "sg:phone":"+41 91 609 14 08",
    "sg:postcode":"6939",
    "sg:province":"Ticino",
    "wof:name":"Vide-visa Sa Impresa Costruzione",
    "wof:placetype":"venue"
},
  "geometry": {"coordinates":[8.90275,46.046761],"type":"Point"}
}