{
  "type": "Feature",
  "properties": {
    "iso:country":"CH",
    "sg:address":"Hauptstrasse 25",
    "sg:city":"Eptingen",
    "sg:orig_category":"HOTELS: MIT RESTAURANT Kongress- and Tagungshotels mit Restaurant",
    "sg:phone":"+41 62 285 20 10",
    "sg:postcode":"4458",
    "sg:province":"Basel-Landschaft",
    "wof:name":"Landgasthaus Bad Eptingen",
    "wof:placetype":"venue"
},
  "geometry": {"coordinates":[7.8207411766,47.3854522705],"type":"Point"}
}