{
  "type": "Feature",
  "properties": {
    "iso:country":"CH",
    "sg:address":"Hernerholzgasse 5.",
    "sg:city":"Horgen",
    "sg:orig_category":"Pensionskassen",
    "sg:postcode":"8810",
    "sg:province":"Z\u00fcrich",
    "wof:name":"Personalf\u00fcrsorgestiftung Der Ehrat Arnold Ag.",
    "wof:placetype":"venue"
},
  "geometry": {"coordinates":[8.5884885788,47.2642974854],"type":"Point"}
}