{
  "type": "Feature",
  "properties": {
    "iso:country":"CH",
    "sg:address":"Ecluse Rue De L' 57",
    "sg:city":"Neuch\u00e2tel",
    "sg:orig_category":"Sonstige pers\u00f6nliche Dienstleistungen",
    "sg:phone":"+41 79 608 07 07",
    "sg:postcode":"2000",
    "sg:province":"Neuch\u00e2tel",
    "wof:name":"Unisystem S\u00e0rl",
    "wof:placetype":"venue"
},
  "geometry": {"coordinates":[6.9272999763,46.9934310913],"type":"Point"}
}