{
  "type": "Feature",
  "properties": {
    "iso:country":"CH",
    "sg:address":"Grundstrasse 23",
    "sg:city":"Rorbas",
    "sg:orig_category":"Vorschulen, Kinderg\u00e4rten",
    "sg:phone":"+41 18654614",
    "sg:postcode":"8427",
    "sg:province":"Z\u00fcrich",
    "wof:name":"Montessori-kindergarten Frau Traudi Belz",
    "wof:placetype":"venue"
},
  "geometry": {"coordinates":[8.5697021484,47.5328636169],"type":"Point"}
}