{
  "type": "Feature",
  "properties": {
    "iso:country":"CH",
    "sg:address":"Rosenweg 3",
    "sg:city":"Sch\u00f6nb\u00fchl-urtenen",
    "sg:orig_category":"Sportvereine Turnen",
    "sg:postcode":"3322",
    "sg:province":"Bern",
    "wof:name":"Turnverein Stv Urtenen",
    "wof:placetype":"venue"
},
  "geometry": {"coordinates":[7.4989509583,47.0228729248],"type":"Point"}
}