{
  "type": "Feature",
  "properties": {
    "iso:country":"CH",
    "sg:address":"Narzissenweg 6 2504 Biel/bienne. Postfach",
    "sg:city":"Biel/bienne",
    "sg:orig_category":"Architektur U Ingenieurb\u00fcros",
    "sg:postcode":"2504",
    "sg:province":"Bern",
    "wof:name":"Wbb Weyer R.",
    "wof:placetype":"venue"
},
  "geometry": {"coordinates":[7.27459,47.14526],"type":"Point"}
}