{
  "type": "Feature",
  "properties": {
    "addr:full":"Weissensteinstrasse 62 Langendorf Solothurn 4513",
    "addr:housenumber":"62",
    "addr:postcode":"4513",
    "addr:street":"Weissensteinstrasse",
    "iso:country":"CH",
    "sg:address":"Weissensteinstrasse 62",
    "sg:city":"Langendorf",
    "sg:classifiers":[
        {
            "category":"Train Station",
            "subcategory":"Light Rail",
            "type":"Transportation"
        }
    ],
    "sg:phone":"+41 32 622 60 18",
    "sg:postcode":"4513",
    "sg:province":"Solothurn",
    "sg:tags":[
        "insert",
        "carbide",
        "indexable"
    ],
    "wof:name":"W. Bucher Dipl. Masch.-ing. Eth",
    "wof:placetype":"venue"
},
  "geometry": {"coordinates":[7.512652,47.225277],"type":"Point"}
}