{
  "type": "Feature",
  "properties": {
    "iso:country":"CH",
    "sg:address":"Bahnhofstrasse 131 5322 Koblenz. Postfach",
    "sg:city":"Koblenz",
    "sg:orig_category":"S\u00e4ge, Hobel U Holzimpr\u00e4gnierwerke",
    "sg:phone":"+41 56 246 15 45",
    "sg:postcode":"5322",
    "sg:province":"Aargau",
    "wof:name":"Gebr. Kappeler & Co Ag",
    "wof:placetype":"venue"
},
  "geometry": {"coordinates":[8.2270021439,47.6007347107],"type":"Point"}
}