{
  "type": "Feature",
  "properties": {
    "iso:country":"CH",
    "sg:address":"Terrassi\u00e8re Rue De La 41 1207 Gen\u00e8ve. Postfach",
    "sg:city":"Gen\u00e8ve",
    "sg:orig_category":"Grosshandel mit Getr\u00e4nken",
    "sg:phone":"+41 71 244 34 41",
    "sg:postcode":"1207",
    "sg:province":"Gen\u00e8ve",
    "wof:name":"Victoria-sekt, Feket\u00fc Ferenc",
    "wof:placetype":"venue"
},
  "geometry": {"coordinates":[9.3899326324,47.4358825684],"type":"Point"}
}