{
  "type": "Feature",
  "properties": {
    "addr:full":"Dorfstrasse 10 B\u00fcnzen Aargau 5624",
    "addr:housenumber":"10",
    "addr:postcode":"5624",
    "addr:street":"Dorfstrasse",
    "iso:country":"CH",
    "sg:address":"Dorfstrasse 10",
    "sg:city":"B\u00fcnzen",
    "sg:orig_category":"Autogaragen",
    "sg:phone":"+41 56 666 13 56",
    "sg:postcode":"5624",
    "sg:province":"Aargau",
    "wof:name":"Siegfried Waltisberg Garage",
    "wof:placetype":"venue"
},
  "geometry": {"coordinates":[8.32303,47.31052],"type":"Point"}
}