{
  "type": "Feature",
  "properties": {
    "iso:country":"CH",
    "sg:address":"Buchenstrasse 72",
    "sg:city":"Biberist",
    "sg:orig_category":"Instandhaltung U Reparatur von Automobilen",
    "sg:postcode":"4562",
    "sg:province":"Solothurn",
    "wof:name":"Winz-zimmermann, Hansueli",
    "wof:placetype":"venue"
},
  "geometry": {"coordinates":[7.5616397858,47.1928901672],"type":"Point"}
}