{
  "type": "Feature",
  "properties": {
    "iso:country":"CH",
    "sg:address":"Rue Principale 19 1875 Morgins. Postfach",
    "sg:city":"Morgins",
    "sg:orig_category":"Detailhandel mit Sportartikeln",
    "sg:phone":"+41 79 239 87 57",
    "sg:postcode":"1875",
    "sg:province":"Valais",
    "wof:name":"Snowline Magasin De Sport",
    "wof:placetype":"venue"
},
  "geometry": {"coordinates":[6.8587532043,46.2375221252],"type":"Point"}
}