{
  "type": "Feature",
  "properties": {
    "iso:country":"CH",
    "sg:address":"Missionsstrasse 38",
    "sg:city":"Basel",
    "sg:orig_category":"Detailhandel mit medizinischen U orthop\u00e4dischen Artikeln Herstellung von medizinischen U chirurgisch",
    "sg:phone":"+41 61 381 00 50",
    "sg:postcode":"4055",
    "sg:province":"Basel-Stadt",
    "wof:name":"Gygi Martin Orthop\u00e4die Gmbh",
    "wof:placetype":"venue"
},
  "geometry": {"coordinates":[7.5771012306,47.5602912903],"type":"Point"}
}