{
  "type": "Feature",
  "properties": {
    "iso:country":"CH",
    "sg:address":"8858",
    "sg:city":"Innerthal",
    "sg:classifiers":[
        {
            "category":"Restaurant",
            "type":"Food & Drink"
        }
    ],
    "sg:phone":"+41 55 446 11 55",
    "sg:postcode":"8858",
    "sg:province":"Schwyz",
    "wof:name":"Restaurant Oberhof",
    "wof:placetype":"venue"
},
  "geometry": {"coordinates":[8.9160404205,47.1063041687],"type":"Point"}
}