{
  "type": "Feature",
  "properties": {
    "iso:country":"CH",
    "sg:address":"Neudorf 6",
    "sg:city":"Oberb\u00fcren",
    "sg:orig_category":"Detailhandel mit Waren verschiedener Art, Hauptrichtung Nahrungsmittel",
    "sg:phone":"+41 71 951 58 16",
    "sg:postcode":"9245",
    "sg:province":"St. Gallen",
    "wof:name":"Landw. Genossenschaft Oberb\u00fcren",
    "wof:placetype":"venue"
},
  "geometry": {"coordinates":[9.1600599289,47.4509162903],"type":"Point"}
}