{
  "type": "Feature",
  "properties": {
    "addr:full":"Via Maggio 44 6900 Lugano. Postfach Lugano Ticino 6900",
    "addr:housenumber":"44",
    "addr:postcode":"6900;6900",
    "addr:street":"Via Maggio",
    "iso:country":"CH",
    "sg:address":"Via Maggio 44 6900 Lugano. Postfach",
    "sg:city":"Lugano",
    "sg:orig_category":"Allgemeiner Hoch U Tiefbau",
    "sg:postcode":"6900",
    "sg:province":"Ticino",
    "wof:name":"Fulledil Sa",
    "wof:placetype":"venue"
},
  "geometry": {"coordinates":[8.967271,46.008591],"type":"Point"}
}