{
  "type": "Feature",
  "properties": {
    "iso:country":"CH",
    "sg:address":"Via Cureglia 12",
    "sg:city":"Comano",
    "sg:orig_category":"Detailhandel mit elektrischen Haushalts-,Radio U Fernsehger\u00e4ten sowie Musikinstrumenten Elektroinsta",
    "sg:phone":"+41 91 941 76 57",
    "sg:postcode":"6949",
    "sg:province":"Ticino",
    "wof:name":"Roberto Ghielmini Radio Tv",
    "wof:placetype":"venue"
},
  "geometry": {"coordinates":[8.9535722733,46.0330886841],"type":"Point"}
}