{
  "type": "Feature",
  "properties": {
    "iso:country":"CH",
    "sg:address":"Jeunes Route Des 9",
    "sg:city":"Gen\u00e8ve",
    "sg:orig_category":"Kauf U Verkauf von Immobilien auf eigene Rechnung",
    "sg:phone":"+41 56 631 77 70",
    "sg:postcode":"1200",
    "sg:province":"Gen\u00e8ve",
    "wof:name":"Gia Immobilien Ag",
    "wof:placetype":"venue"
},
  "geometry": {"coordinates":[8.3373966217,47.3500862122],"type":"Point"}
}