{
  "type": "Feature",
  "properties": {
    "iso:country":"CH",
    "sg:address":"Bergstrasse 1",
    "sg:city":"Solothurn",
    "sg:orig_category":"Sonstige Institutionen des Sozialwesens ohne Beherbergung",
    "sg:phone":"+41 62 771 11 72",
    "sg:postcode":"4500",
    "sg:province":"Solothurn",
    "wof:name":"Heilsarmee Reinach",
    "wof:placetype":"venue"
},
  "geometry": {"coordinates":[8.1821174622,47.2531700134],"type":"Point"}
}