{
  "type": "Feature",
  "properties": {
    "iso:country":"CH",
    "sg:address":"Lohwisstr. 52 8124 Maur. Postfach",
    "sg:city":"Ebmatingen",
    "sg:orig_category":"Herstellung von elektronischen Bauelementen",
    "sg:postcode":"8123",
    "sg:province":"Z\u00fcrich",
    "wof:name":"Bebi\u00e9 + Co.",
    "wof:placetype":"venue"
},
  "geometry": {"coordinates":[8.6431131363,47.3578643799],"type":"Point"}
}