{
  "type": "Feature",
  "properties": {
    "iso:country":"CH",
    "sg:address":"Unterer Rheinweg 50",
    "sg:city":"Basel",
    "sg:orig_category":"Vereine Z\u00fcnfte",
    "sg:phone":"+41 61 261 15 46",
    "sg:postcode":"4057",
    "sg:province":"Basel-Stadt",
    "wof:name":"Zunft Zu Rebleuten",
    "wof:placetype":"venue"
},
  "geometry": {"coordinates":[7.587790966,47.5645904541],"type":"Point"}
}