{
  "type": "Feature",
  "properties": {
    "iso:country":"CH",
    "sg:address":"3965 Chippis Case Postale 116",
    "sg:city":"Chippis",
    "sg:orig_category":"Sportvereine Ballsport Tennis",
    "sg:postcode":"3965",
    "sg:province":"Valais",
    "wof:name":"Tennisclub Chippis",
    "wof:placetype":"venue"
},
  "geometry": {"coordinates":[7.5419597626,46.274269104],"type":"Point"}
}