{
  "type": "Feature",
  "properties": {
    "iso:country":"CH",
    "sg:address":"Arvenegg Schluecht 3818 Grindelwald. Postfach 145",
    "sg:city":"Grindelwald",
    "sg:orig_category":"Fachdetailhandel in Verkaufsr\u00e4umen Gartenbau",
    "sg:phone":"+41 33 853 33 02",
    "sg:postcode":"3818",
    "sg:province":"Bern",
    "wof:name":"Burgener Erika",
    "wof:placetype":"venue"
},
  "geometry": {"coordinates":[8.0083599091,46.6287498474],"type":"Point"}
}