{
  "type": "Feature",
  "properties": {
    "iso:country":"CH",
    "sg:address":"Am Stausee 25/17",
    "sg:city":"Birsfelden",
    "sg:orig_category":"Sportvereine Turnen Vereine Damen",
    "sg:phone":"+41 61 311 98 90",
    "sg:postcode":"4127",
    "sg:province":"Basel-Landschaft",
    "wof:name":"Damen-& Frauenriege Birsfelden",
    "wof:placetype":"venue"
},
  "geometry": {"coordinates":[7.6314058304,47.5563926697],"type":"Point"}
}