{
  "type": "Feature",
  "properties": {
    "iso:country":"CH",
    "sg:address":"Witikonerstrasse 295 8053 Z\u00fcrich. Postfach",
    "sg:city":"Z\u00fcrich",
    "sg:orig_category":"Fachdetailhandel mit pharmazeutischen Produkten Sonstiger Fachdetailhandel mit Nahrungsmitteln, Getr",
    "sg:phone":"+41 13882020",
    "sg:postcode":"8053",
    "sg:province":"Z\u00fcrich",
    "wof:name":"Pierre-andr\u00e9 Jud & Co Apotheke Witikon & Feelgood's",
    "wof:placetype":"venue"
},
  "geometry": {"coordinates":[8.5864868164,47.3584098816],"type":"Point"}
}