{
  "type": "Feature",
  "properties": {
    "iso:country":"CH",
    "sg:address":"Paradiesstrasse 52",
    "sg:city":"Z\u00fcrich",
    "sg:orig_category":"Sportvereine Turnen Damen",
    "sg:phone":"+41 71 244 02 01",
    "sg:postcode":"8038",
    "sg:province":"Z\u00fcrich",
    "wof:name":"Frauenturngruppe Heiligkreuz",
    "wof:placetype":"venue"
},
  "geometry": {"coordinates":[9.3920164108,47.4389572144],"type":"Point"}
}