{
  "type": "Feature",
  "properties": {
    "iso:country":"CH",
    "sg:address":"Stand Rue Du 63 2800 Del\u00e9mont. Postfach",
    "sg:city":"Delsberg",
    "sg:orig_category":"Detailhandel mit Metallwaren, Anstrichmitteln, Glaswaren, Bau U Heimwerkerbedarf",
    "sg:postcode":"2800",
    "sg:province":"Jura",
    "wof:name":"Turck Duotec Sa Produits Techniques, Dans Le Dom. De La Microm\u00e9canique Etc.; Achat, Fabrication, D\u00e9velopp., Distr., Vente",
    "wof:placetype":"venue"
},
  "geometry": {"coordinates":[7.3439698219,47.3653564453],"type":"Point"}
}