{
  "type": "Feature",
  "properties": {
    "iso:country":"CH",
    "sg:address":"Steinberggasse 52",
    "sg:city":"Winterthur",
    "sg:orig_category":"Detailhandel mit M\u00f6beln U Haushaltsgegenst\u00e4nden",
    "sg:phone":"+41 52 212 12 35",
    "sg:postcode":"8400",
    "sg:province":"Z\u00fcrich",
    "wof:name":"B\u00fchlhof-m\u00f6bel, Levy-gidion's Erben",
    "wof:placetype":"venue"
},
  "geometry": {"coordinates":[8.7276954651,47.4983177185],"type":"Point"}
}