{
  "type": "Feature",
  "properties": {
    "iso:country":"CH",
    "sg:address":"9400",
    "sg:city":"Rorschach",
    "sg:orig_category":"Interessenvertretungen",
    "sg:postcode":"9400",
    "sg:province":"St. Gallen",
    "wof:name":"Heimatmuseum Rorschach",
    "wof:placetype":"venue"
},
  "geometry": {"coordinates":[9.4960098267,47.4875793457],"type":"Point"}
}