{
  "type": "Feature",
  "properties": {
    "iso:country":"CH",
    "sg:address":"Bodenackerstrasse 79",
    "sg:city":"Dulliken",
    "sg:orig_category":"Sonstiger Grosshandel",
    "sg:phone":"+41 62 295 28 29",
    "sg:postcode":"4657",
    "sg:province":"Solothurn",
    "wof:name":"Hv-service Gmbh",
    "wof:placetype":"venue"
},
  "geometry": {"coordinates":[7.9559922218,47.3499450684],"type":"Point"}
}