{
  "type": "Feature",
  "properties": {
    "addr:full":"Place Gare Gfm 1 Belfaux Fribourg 1782",
    "addr:housenumber":"1",
    "addr:postcode":"1782",
    "addr:street":"Place;Gfm",
    "iso:country":"CH",
    "sg:address":"Place Gare Gfm 1",
    "sg:city":"Belfaux",
    "sg:classifiers":[
        {
            "category":"Professional",
            "subcategory":"Advertising",
            "type":"Services"
        }
    ],
    "sg:phone":"+41 26 475 24 14",
    "sg:postcode":"1782",
    "sg:province":"Fribourg",
    "sg:tags":[
        "agency"
    ],
    "wof:name":"Apw Agence De Publicit\u00e9 Evenement S.a.",
    "wof:placetype":"venue"
},
  "geometry": {"coordinates":[7.107897,46.821709],"type":"Point"}
}