{
  "type": "Feature",
  "properties": {
    "iso:country":"CH",
    "sg:address":"Rue Des Draizes 78",
    "sg:city":"Neuch\u00e2tel",
    "sg:orig_category":"Einzelhandel mit Automobilteilen U Zubeh\u00f6r",
    "sg:phone":"+41 32 731 65 60",
    "sg:postcode":"2000",
    "sg:province":"Neuch\u00e2tel",
    "wof:name":"Alo\u00efs Mettraux Accessoires Pour Voitures",
    "wof:placetype":"venue"
},
  "geometry": {"coordinates":[6.9007568359,46.9891891479],"type":"Point"}
}