{
  "type": "Feature",
  "properties": {
    "iso:country":"CH",
    "sg:address":"Kasernenstrasse 2",
    "sg:city":"Glarus",
    "sg:orig_category":"Zivilschutz",
    "sg:phone":"+41 55 646 63 23",
    "sg:postcode":"8750",
    "sg:province":"Glarus",
    "wof:name":"Kant. Amt F\u00fcr Zivilschutz",
    "wof:placetype":"venue"
},
  "geometry": {"coordinates":[9.065331459,47.0376052856],"type":"Point"}
}