{
  "type": "Feature",
  "properties": {
    "iso:country":"CH",
    "sg:address":"Zipfelweg 10",
    "sg:city":"Adliswil",
    "sg:orig_category":"Bauspenglerei Sanit\u00e4r, Heizungs U L\u00fcftungsinstallation",
    "sg:phone":"+41 17106490",
    "sg:postcode":"8134",
    "sg:province":"Z\u00fcrich",
    "wof:name":"Zanotta Karl",
    "wof:placetype":"venue"
},
  "geometry": {"coordinates":[8.52391,47.312592],"type":"Point"}
}