{
  "type": "Feature",
  "properties": {
    "iso:country":"CH",
    "sg:address":"General-dufour-strasse 4 2502 Biel/bienne. Postfach",
    "sg:city":"Biel/bienne",
    "sg:orig_category":"Fachdetailhandel mit pharmazeutischen Produkten",
    "sg:phone":"+41 32 341 11 22",
    "sg:postcode":"2501",
    "sg:province":"Bern",
    "wof:name":"Geno-apotheke",
    "wof:placetype":"venue"
},
  "geometry": {"coordinates":[7.2705221176,47.1463165283],"type":"Point"}
}