{
  "type": "Feature",
  "properties": {
    "iso:country":"CH",
    "sg:address":"Rathausgasse 5",
    "sg:city":"Glarus",
    "sg:classifiers":[
        {
            "category":"Travel",
            "subcategory":"Hotels & Motels",
            "type":"Entertainment"
        }
    ],
    "sg:phone":"+41 55 640 11 27",
    "sg:postcode":"8750",
    "sg:province":"Glarus",
    "sg:tags":[
        "hotels",
        "mit",
        "restaurant"
    ],
    "wof:name":"Hotel Sonne",
    "wof:placetype":"venue"
},
  "geometry": {"coordinates":[9.067065239,47.0398597717],"type":"Point"}
}