{
  "type": "Feature",
  "properties": {
    "iso:country":"CH",
    "sg:address":"Alderstrasse 49",
    "sg:city":"Z\u00fcrich",
    "sg:orig_category":"Unclassifiable Establishments",
    "sg:postcode":"8008",
    "sg:province":"Z\u00fcrich",
    "wof:name":"Schulsupport Ag",
    "wof:placetype":"venue"
},
  "geometry": {"coordinates":[8.5548458099,47.3569831848],"type":"Point"}
}