{
  "type": "Feature",
  "properties": {
    "iso:country":"CH",
    "sg:address":"Seilergraben 53",
    "sg:city":"Z\u00fcrich",
    "sg:orig_category":"Fachdetailhandel in Verkaufsr\u00e4umen",
    "sg:postcode":"8001",
    "sg:province":"Z\u00fcrich",
    "wof:name":"Vibes United Vu, Ammann Sportbekleidung U. -schuhe; Handel",
    "wof:placetype":"venue"
},
  "geometry": {"coordinates":[8.5451469421,47.3754730225],"type":"Point"}
}