{
  "type": "Feature",
  "properties": {
    "iso:country":"CH",
    "sg:address":"Belchenstrasse 187",
    "sg:city":"Fisibach",
    "sg:orig_category":"Instandhaltung U Reparatur von Automobilen",
    "sg:phone":"+41 18582713",
    "sg:postcode":"5467",
    "sg:province":"Aargau",
    "wof:name":"Garage Zimmermann Ag, Fisibach",
    "wof:placetype":"venue"
},
  "geometry": {"coordinates":[8.4107913971,47.5643577576],"type":"Point"}
}