{
  "type": "Feature",
  "properties": {
    "iso:country":"CH",
    "sg:address":"Saphirs Rue Des 10a",
    "sg:city":"Monthey",
    "sg:orig_category":"Softwareentwicklung U beratung",
    "sg:phone":"+41 24 471 16 78",
    "sg:postcode":"1870",
    "sg:province":"Valais",
    "wof:name":"Mil Diffusion, Leuba Michel",
    "wof:placetype":"venue"
},
  "geometry": {"coordinates":[6.9605259895,46.2525367737],"type":"Point"}
}