{
  "type": "Feature",
  "properties": {
    "addr:full":"1966 Ayent Valais 1966",
    "addr:housenumber":"1966;1966",
    "addr:street":"Ayent Valais",
    "iso:country":"CH",
    "sg:address":"1966",
    "sg:city":"Ayent",
    "sg:orig_category":"Abwasserreinigung",
    "sg:phone":"+41 27 398 16 27",
    "sg:postcode":"1966",
    "sg:province":"Valais",
    "wof:name":"Station De Traitement Des Eaux",
    "wof:placetype":"venue"
},
  "geometry": {"coordinates":[7.406825,46.276783],"type":"Point"}
}