{
  "type": "Feature",
  "properties": {
    "iso:country":"CH",
    "sg:address":"Oberbalmberg 21",
    "sg:city":"G\u00fcnsberg",
    "sg:orig_category":"Unclassifiable Establishments",
    "sg:postcode":"4524",
    "sg:province":"Solothurn",
    "wof:name":"Erlenhof Ag",
    "wof:placetype":"venue"
},
  "geometry": {"coordinates":[9.2549495697,47.4144134521],"type":"Point"}
}