{
  "type": "Feature",
  "properties": {
    "iso:country":"CH",
    "sg:address":"Leihgasse 11 6340 Baar. Postfach 258",
    "sg:city":"Baar",
    "sg:orig_category":"Polizei",
    "sg:phone":"+41 41 760 41 17",
    "sg:postcode":"6341",
    "sg:province":"Zug",
    "wof:name":"Kantonale Polizei",
    "wof:placetype":"venue"
},
  "geometry": {"coordinates":[8.5281066895,47.1944236755],"type":"Point"}
}