{
  "type": "Feature",
  "properties": {
    "iso:country":"CH",
    "sg:address":"Kirchstrasse 8",
    "sg:city":"Oberdiessbach",
    "sg:orig_category":"Herstellung von Duft U K\u00f6rperpflegemitteln",
    "sg:phone":"+41 31 771 21 73",
    "sg:postcode":"3672",
    "sg:province":"Bern",
    "wof:name":"Rubin + Gerber",
    "wof:placetype":"venue"
},
  "geometry": {"coordinates":[7.6204581261,46.8399162292],"type":"Point"}
}