{
  "type": "Feature",
  "properties": {
    "addr:full":"Rue Du Temple 14 St-aubin-sauges Neuch\u00e2tel 2024",
    "addr:housenumber":"14",
    "addr:postcode":"2024",
    "addr:street":"Rue Du Temple;St-Aubin-Sauges Neucha\u0302Tel",
    "iso:country":"CH",
    "sg:address":"Rue Du Temple 14",
    "sg:city":"St-aubin-sauges",
    "sg:orig_category":"B\u00e4ckereien Konditoreien",
    "sg:phone":"+41 32 835 11 71",
    "sg:postcode":"2024",
    "sg:province":"Neuch\u00e2tel",
    "wof:name":"A L'epi Dor\u00e9 Boulangerie",
    "wof:placetype":"venue"
},
  "geometry": {"coordinates":[6.774167,46.895649],"type":"Point"}
}