{
  "type": "Feature",
  "properties": {
    "iso:country":"CH",
    "sg:address":"Grabengasse",
    "sg:city":"Turtmann",
    "sg:orig_category":"Bauschreinerei Herstellung von Konstruktionsteilen, Fertigbauteilen U Ausbauelementen aus Holz",
    "sg:phone":"+41 27 932 36 03",
    "sg:postcode":"3946",
    "sg:province":"Valais",
    "wof:name":"J\u00e4ger & Meichtry Schreinerei Gmbh",
    "wof:placetype":"venue"
},
  "geometry": {"coordinates":[7.703522,46.300522],"type":"Point"}
}