{
  "type": "Feature",
  "properties": {
    "addr:full":"Schwanengasse 52 2503 Biel/bienne Case Postale 892 Biel/bienne Bern 2501",
    "addr:housenumber":"52;892",
    "addr:postcode":"2503;2501",
    "addr:street":"Schwanengasse;Postale",
    "iso:country":"CH",
    "sg:address":"Schwanengasse 52 2503 Biel/bienne Case Postale 892",
    "sg:city":"Biel/bienne",
    "sg:orig_category":"Autotransporte M\u00f6bel Autotransporte international",
    "sg:phone":"+41 32 365 22 77",
    "sg:postcode":"2501",
    "sg:province":"Bern",
    "wof:name":"Danzas Ag",
    "wof:placetype":"venue"
},
  "geometry": {"coordinates":[7.25508,47.13797],"type":"Point"}
}