{
  "type": "Feature",
  "properties": {
    "iso:country":"CH",
    "sg:address":"Schmiedgasse 13",
    "sg:city":"St.gallen",
    "sg:orig_category":"Wirtschaftspr\u00fcfung, Steuerberatung U Treuhand",
    "sg:phone":"+41 71 380 02 65",
    "sg:postcode":"9000",
    "sg:province":"St. Gallen",
    "wof:name":"Eureva Treuhand Gmbh",
    "wof:placetype":"venue"
},
  "geometry": {"coordinates":[9.2467546463,47.4207801819],"type":"Point"}
}