{
  "type": "Feature",
  "properties": {
    "iso:country":"CH",
    "sg:address":"Oberdorfstrasse 41",
    "sg:city":"Wasterkingen",
    "sg:orig_category":"Vereine Musik/Blasmusik",
    "sg:phone":"+41 18691815",
    "sg:postcode":"8195",
    "sg:province":"Z\u00fcrich",
    "wof:name":"Fan-club Der Musikgesellschaft",
    "wof:placetype":"venue"
},
  "geometry": {"coordinates":[8.4716615677,47.5903701782],"type":"Point"}
}