{
  "type": "Feature",
  "properties": {
    "iso:country":"CH",
    "sg:address":"Chr\u00e4merweg 6",
    "sg:city":"Wichtrach",
    "sg:orig_category":"Herstellung von sonstigen landwirtschaftlichen Maschinen",
    "sg:postcode":"3114",
    "sg:province":"Bern",
    "wof:name":"Heinrich W\u00fcthrich",
    "wof:placetype":"venue"
},
  "geometry": {"coordinates":[7.5756688118,46.8487434387],"type":"Point"}
}