{
  "type": "Feature",
  "properties": {
    "iso:country":"CH",
    "sg:address":"Allmendweg 30",
    "sg:city":"Faulensee",
    "sg:orig_category":"Gartenbau",
    "sg:phone":"+41 33 654 57 51",
    "sg:postcode":"3705",
    "sg:province":"Bern",
    "wof:name":"Gartenbau Locher Heinz",
    "wof:placetype":"venue"
},
  "geometry": {"coordinates":[7.7017560005,46.6737251282],"type":"Point"}
}