{
  "type": "Feature",
  "properties": {
    "iso:country":"CH",
    "sg:address":"Obere Wiese 13",
    "sg:city":"Emmenbr\u00fccke",
    "sg:orig_category":"Interessenvertretungen",
    "sg:postcode":"6020",
    "sg:province":"Luzern",
    "wof:name":"Genossenschaft Sch\u00fctzenstube Emmen",
    "wof:placetype":"venue"
},
  "geometry": {"coordinates":[8.2659902573,47.0748291016],"type":"Point"}
}