{
  "type": "Feature",
  "properties": {
    "iso:country":"CH",
    "sg:address":"Rue De Soleure 58",
    "sg:city":"Moutier",
    "sg:orig_category":"Grosshandel mit B\u00fcromaschinen Grosshandel mit Datenverarbeitungsger\u00e4ten",
    "sg:phone":"+41 32 495 10 81",
    "sg:postcode":"2740",
    "sg:province":"Bern",
    "wof:name":"Messerli Informatique",
    "wof:placetype":"venue"
},
  "geometry": {"coordinates":[7.3887939453,47.280418396],"type":"Point"}
}