{
  "type": "Feature",
  "properties": {
    "iso:country":"CH",
    "sg:address":"Place De La Gare 5 2900 Porrentruy Case Postale 240",
    "sg:city":"Porrentruy",
    "sg:orig_category":"Detailhandel mit Sportartikeln Fachdetailhandel in Verkaufsr\u00e4umen",
    "sg:phone":"+41 32 466 25 27",
    "sg:postcode":"2900",
    "sg:province":"Jura",
    "wof:name":"New Sport, Thierry Et Corinne Schaffner",
    "wof:placetype":"venue"
},
  "geometry": {"coordinates":[7.0800018311,47.4210739136],"type":"Point"}
}