{
  "type": "Feature",
  "properties": {
    "iso:country":"CH",
    "sg:address":"Austrasse 4",
    "sg:city":"Vaduz",
    "sg:orig_category":"Zahnarztpraxen",
    "sg:phone":"+41 75 373 50 17",
    "sg:postcode":"9490",
    "wof:name":"Dr. Med. Dent. Reinhold Amann Zahnarzt",
    "wof:placetype":"venue"
},
  "geometry": {"coordinates":[9.5221033096,47.1320152283],"type":"Point"}
}