{
  "type": "Feature",
  "properties": {
    "iso:country":"CH",
    "sg:address":"3256",
    "sg:city":"Dieterswil",
    "sg:orig_category":"Verwertung von Milch",
    "sg:phone":"+41 71551336",
    "sg:postcode":"3256",
    "sg:province":"Bern",
    "wof:name":"K\u00e4sereigenossenschaft Berg",
    "wof:placetype":"venue"
},
  "geometry": {"coordinates":[9.4173192978,47.4896469116],"type":"Point"}
}