{
  "type": "Feature",
  "properties": {
    "iso:country":"CH",
    "sg:address":"Hofweg 5/7 4512 Bellach. Postfach 228",
    "sg:city":"Bellach",
    "sg:orig_category":"Mechanische Werkst\u00e4tten",
    "sg:phone":"+41 32 618 24 16",
    "sg:postcode":"4512",
    "sg:province":"Solothurn",
    "wof:name":"Erich Von B\u00fcren Mechanische Werkstatt",
    "wof:placetype":"venue"
},
  "geometry": {"coordinates":[7.4929480553,47.2109107971],"type":"Point"}
}