{
  "type": "Feature",
  "properties": {
    "iso:country":"CH",
    "sg:address":"Route Andr\u00e9 Piller 1 1762 Givisiez Case Postale 60",
    "sg:city":"Givisiez",
    "sg:orig_category":"Grosshandel mit Holz U Bauelementen aus Holz Grosshandel mit Holz U Baustoffen",
    "sg:phone":"+41 26 467 81 11",
    "sg:postcode":"1762",
    "sg:province":"Fribourg",
    "wof:name":"Glasson Mat\u00e9riaux Sa Succursale De Givisiez",
    "wof:placetype":"venue"
},
  "geometry": {"coordinates":[7.1202101707,46.8125305176],"type":"Point"}
}