{
  "type": "Feature",
  "properties": {
    "iso:country":"CH",
    "sg:address":"Falkensteinerstrasse 22",
    "sg:city":"Balsthal",
    "sg:orig_category":"Hochschulen U h\u00f6here Ausbildung",
    "sg:phone":"+41 62 391 52 40",
    "sg:postcode":"4710",
    "sg:province":"Solothurn",
    "wof:name":"Bs Media Vision",
    "wof:placetype":"venue"
},
  "geometry": {"coordinates":[7.692442894,47.3136367798],"type":"Point"}
}