{
  "type": "Feature",
  "properties": {
    "iso:country":"CH",
    "sg:address":"Les Ponts",
    "sg:city":"Vaulruz",
    "sg:orig_category":"Instandhaltung U Reparatur von Automobilen",
    "sg:phone":"+41 26 912 70 70",
    "sg:postcode":"1627",
    "sg:province":"Fribourg",
    "wof:name":"Garage Des Ponts Grandjean Sa",
    "wof:placetype":"venue"
},
  "geometry": {"coordinates":[6.9802370071,46.6168899536],"type":"Point"}
}