{
  "type": "Feature",
  "properties": {
    "iso:country":"CH",
    "sg:address":"Avenue Samson-reymondin 26",
    "sg:city":"Pully",
    "sg:orig_category":"Wirtschaftspr\u00fcfung, Steuerberatung U Treuhand",
    "sg:phone":"+41 21 310 01 03",
    "sg:postcode":"1009",
    "sg:province":"Vaud",
    "wof:name":"Fiduroconsulting Sa",
    "wof:placetype":"venue"
},
  "geometry": {"coordinates":[6.6645469666,46.5091285706],"type":"Point"}
}