{
  "type": "Feature",
  "properties": {
    "iso:country":"CH",
    "sg:address":"Sundroina",
    "sg:city":"Vaz/obervaz",
    "sg:orig_category":"Herstellung von Drahtwaren",
    "sg:postcode":"7082",
    "sg:province":"Graubunden",
    "wof:name":"Christian Fl\u00fctsch",
    "wof:placetype":"venue"
},
  "geometry": {"coordinates":[9.5615787506,46.7215805054],"type":"Point"}
}