{
  "type": "Feature",
  "properties": {
    "addr:full":"Via Rodari 2 Bellinzona Ticino 6500",
    "addr:housenumber":"2",
    "addr:postcode":"6500",
    "addr:street":"Via Rodari",
    "iso:country":"CH",
    "sg:address":"Via Rodari 2",
    "sg:city":"Bellinzona",
    "sg:orig_category":"Bestattungswesen",
    "sg:phone":"+41 32 968 22 64",
    "sg:postcode":"6500",
    "sg:province":"Ticino",
    "wof:name":"Pompes Fun\u00e8bres Accueil W\u00e4lti Sa Entreprise De Pompes Fun\u00e8bres",
    "wof:placetype":"venue"
},
  "geometry": {"coordinates":[6.829905,47.10281],"type":"Point"}
}