{
  "type": "Feature",
  "properties": {
    "iso:country":"CH",
    "sg:address":"Dorfplatz 3 3150 Schwarzenburg. Postfach",
    "sg:city":"Schwarzenburg",
    "sg:orig_category":"HOTELS: MIT RESTAURANT Kongress- and Tagungshotels mit Restaurant",
    "sg:phone":"+41 31 731 21 21",
    "sg:postcode":"3150",
    "sg:province":"Bern",
    "wof:name":"Hotel Sonne",
    "wof:placetype":"venue"
},
  "geometry": {"coordinates":[7.3413968086,46.8177566528],"type":"Point"}
}