{
  "type": "Feature",
  "properties": {
    "addr:full":"Winkelmatt 24 Brislach Basel-Landschaft 4225",
    "addr:housenumber":"24",
    "addr:postcode":"4225",
    "addr:street":"Winkelmatt",
    "iso:country":"CH",
    "sg:address":"Winkelmatt 24",
    "sg:city":"Brislach",
    "sg:orig_category":"Aktivit\u00e4ten der Generalunternehmen im Baugewerbe Architektur U Ingenieurb\u00fcros",
    "sg:phone":"+41 61 753 90 44",
    "sg:postcode":"4225",
    "sg:province":"Basel-Landschaft",
    "wof:name":"Imfeld J\u00f6rg Architektur & Baumanagement",
    "wof:placetype":"venue"
},
  "geometry": {"coordinates":[7.54184,47.414551],"type":"Point"}
}