{
  "type": "Feature",
  "properties": {
    "iso:country":"CH",
    "sg:address":"Luzernerstrasse 6",
    "sg:city":"Hildisrieden",
    "sg:orig_category":"Autogaragen Autospenglereien",
    "sg:phone":"+41 41 460 18 14",
    "sg:postcode":"6024",
    "sg:province":"Luzern",
    "wof:name":"Edmund Clausen Garage & Spenglerei",
    "wof:placetype":"venue"
},
  "geometry": {"coordinates":[8.229075,47.150192],"type":"Point"}
}