{
  "type": "Feature",
  "properties": {
    "iso:country":"CH",
    "sg:address":"3943",
    "sg:city":"Eischoll",
    "sg:orig_category":"Fachdetailhandel in Verkaufsr\u00e4umen",
    "sg:postcode":"3943",
    "sg:province":"Valais",
    "wof:name":"Sushi-sports, Amacker Kurt",
    "wof:placetype":"venue"
},
  "geometry": {"coordinates":[7.7804951668,46.2933311462],"type":"Point"}
}