{
  "type": "Feature",
  "properties": {
    "iso:country":"CH",
    "sg:address":"Industriestrasse 1 4805 Brittnau. Postfach 33",
    "sg:city":"Brittnau",
    "sg:orig_category":"Herstellung von Haus, Bett U Tischw\u00e4sche Stickerei",
    "sg:phone":"+41 71 855 37 37",
    "sg:postcode":"4805",
    "sg:province":"Aargau",
    "wof:name":"Imba-textil Ag",
    "wof:placetype":"venue"
},
  "geometry": {"coordinates":[9.5067586899,47.476764679],"type":"Point"}
}