{
  "type": "Feature",
  "properties": {
    "addr:full":"I Runch Da Vigana 6 Camorino Ticino 6528",
    "addr:housenumber":"6",
    "addr:postcode":"6528",
    "addr:street":"Camorino Ticino",
    "iso:country":"CH",
    "sg:address":"I Runch Da Vigana 6",
    "sg:city":"Camorino",
    "sg:orig_category":"Advokaturb\u00fcros Notariate",
    "sg:phone":"+41 91 682 04 72",
    "sg:postcode":"6528",
    "sg:province":"Ticino",
    "wof:name":"Giovanni Belossi Studio Legale & Notarile",
    "wof:placetype":"venue"
},
  "geometry": {"coordinates":[8.998059,46.155735],"type":"Point"}
}