{
  "type": "Feature",
  "properties": {
    "iso:country":"CH",
    "sg:address":"Dorf",
    "sg:city":"Kiental",
    "sg:orig_category":"Verkehrs- and Tourismusb\u00fcros",
    "sg:phone":"+41 33 676 10 10",
    "sg:postcode":"3723",
    "sg:province":"Bern",
    "wof:name":"Verkehrsverein Kiental Verkehrsb\u00fcro",
    "wof:placetype":"venue"
},
  "geometry": {"coordinates":[7.7241921425,46.5875396729],"type":"Point"}
}