{
  "type": "Feature",
  "properties": {
    "iso:country":"CH",
    "sg:address":"Piazza Pedrazzini 7a",
    "sg:city":"Locarno",
    "sg:orig_category":"Reiseb\u00fcros U Reiseveranstalter",
    "sg:phone":"+41 91 752 35 20",
    "sg:postcode":"6600",
    "sg:province":"Ticino",
    "wof:name":"Mondial Tours Mt Sa",
    "wof:placetype":"venue"
},
  "geometry": {"coordinates":[8.7991352081,46.1669235229],"type":"Point"}
}