{
  "type": "Feature",
  "properties": {
    "iso:country":"CH",
    "sg:address":"Sternengasse 6 4051 Basel. Postfach",
    "sg:city":"Basel",
    "sg:orig_category":"Detailhandel mit elektrischen Haushalts-,Radio U Fernsehger\u00e4ten sowie Musikinstrumenten",
    "sg:postcode":"4051",
    "sg:province":"Basel-Stadt",
    "wof:name":"Wellenzohn Vertriebs Gmbh",
    "wof:placetype":"venue"
},
  "geometry": {"coordinates":[8.7945251465,47.2024383545],"type":"Point"}
}