{
  "type": "Feature",
  "properties": {
    "iso:country":"CH",
    "sg:address":"Hohlstrasse 150 8004 Z\u00fcrich. Postfach",
    "sg:city":"Z\u00fcrich",
    "sg:orig_category":"Architektur U Ingenieurb\u00fcros",
    "sg:phone":"+41 12710675",
    "sg:postcode":"8001",
    "sg:province":"Z\u00fcrich",
    "wof:name":"Baenziger Ralph Architekten Ag Archtiketurb\u00fcro Usw",
    "wof:placetype":"venue"
},
  "geometry": {"coordinates":[8.520011,47.380978],"type":"Point"}
}