{
  "type": "Feature",
  "properties": {
    "iso:country":"CH",
    "sg:address":"St. Gallerstrasse 35a",
    "sg:city":"Kronb\u00fchl",
    "sg:orig_category":"Bauspenglerei Sanit\u00e4r, Heizungs U L\u00fcftungsinstallation",
    "sg:phone":"+41 71 298 55 47",
    "sg:postcode":"9302",
    "wof:name":"Br\u00fcllhardt Gebr. Ag",
    "wof:placetype":"venue"
},
  "geometry": {"coordinates":[9.39846,47.455639],"type":"Point"}
}