{
  "type": "Feature",
  "properties": {
    "iso:country":"CH",
    "sg:address":"Haufen 225",
    "sg:city":"Lutzenberg",
    "sg:orig_category":"RESTAURANTS: TEA-ROOMS",
    "sg:phone":"+41 71 888 35 05",
    "sg:postcode":"9426",
    "sg:province":"Appenzell Ausserrhoden",
    "wof:name":"Restaurant Anker Gmbh",
    "wof:placetype":"venue"
},
  "geometry": {"coordinates":[9.5661869049,47.4610786438],"type":"Point"}
}