{
  "type": "Feature",
  "properties": {
    "iso:country":"CH",
    "sg:address":"Cattedrale Via 9 6900 Lugano. Postfach",
    "sg:city":"Lugano",
    "sg:orig_category":"Detailhandel mit Waren verschiedener Art, Hauptrichtung Nahrungsmittel",
    "sg:postcode":"6900",
    "sg:province":"Ticino",
    "wof:name":"Phoenicia Trading Int. Ltd, Londra, Succursale Di Lugano Merci E Prodotti, Spec. Nel Sett. Alimentare Ecc.; Acquisto, Vendita, Import.",
    "wof:placetype":"venue"
},
  "geometry": {"coordinates":[8.9493436813,46.0046310425],"type":"Point"}
}