{
  "type": "Feature",
  "properties": {
    "addr:full":"En Perrey Attalens Fribourg 1616",
    "addr:postcode":"1616",
    "iso:country":"CH",
    "sg:address":"En Perrey",
    "sg:city":"Attalens",
    "sg:orig_category":"Architektur U Ingenieurb\u00fcros",
    "sg:postcode":"1616",
    "sg:province":"Fribourg",
    "wof:name":"Kieffer Georges",
    "wof:placetype":"venue"
},
  "geometry": {"coordinates":[6.85264,46.497421],"type":"Point"}
}