{
  "type": "Feature",
  "properties": {
    "iso:country":"CH",
    "sg:address":"1438",
    "sg:city":"Mathod",
    "sg:orig_category":"Verwertung von Milch",
    "sg:postcode":"1438",
    "sg:province":"Vaud",
    "wof:name":"Soci\u00e9t\u00e9 De Laiterie De Mathod",
    "wof:placetype":"venue"
},
  "geometry": {"coordinates":[6.5611200333,46.7628593445],"type":"Point"}
}