{
  "type": "Feature",
  "properties": {
    "iso:country":"CH",
    "sg:address":"Horriwilstrasse 3",
    "sg:city":"Oekingen",
    "sg:orig_category":"Parkettleger",
    "sg:phone":"+41 52 657 14 38",
    "sg:postcode":"4566",
    "sg:province":"Solothurn",
    "wof:name":"Gottlieb Frischknecht Parkettgesch\u00e4ft",
    "wof:placetype":"venue"
},
  "geometry": {"coordinates":[8.6935930252,47.6566009521],"type":"Point"}
}