{
  "type": "Feature",
  "properties": {
    "iso:country":"CH",
    "sg:address":"Gitterlistrasse 8",
    "sg:city":"Liestal",
    "sg:orig_category":"Pensionskassen",
    "sg:postcode":"4410",
    "sg:province":"Basel-Landschaft",
    "wof:name":"Tag-sammelstiftung",
    "wof:placetype":"venue"
},
  "geometry": {"coordinates":[7.7406020164,47.4793739319],"type":"Point"}
}