{
  "type": "Feature",
  "properties": {
    "iso:country":"CH",
    "sg:address":"Birkenweg 8",
    "sg:city":"Seuzach",
    "sg:orig_category":"Grosshandel mit lebenden Tieren",
    "sg:phone":"+41 79 671 57 22",
    "sg:postcode":"8472",
    "sg:province":"Z\u00fcrich",
    "wof:name":"Renz Peter",
    "wof:placetype":"venue"
},
  "geometry": {"coordinates":[8.7356119156,47.5339546204],"type":"Point"}
}