{
  "type": "Feature",
  "properties": {
    "iso:country":"CH",
    "sg:address":"Via Cortini",
    "sg:city":"Poschiavo",
    "sg:orig_category":"Handel mit Motorr\u00e4dern, Teilen U Zubeh\u00f6r Instandhaltung U Reparatur von Motorr\u00e4dern",
    "sg:phone":"+41 81 844 12 84",
    "sg:postcode":"7742",
    "sg:province":"Graubunden",
    "wof:name":"Franco Lardi Biciclette & Ciclomotori",
    "wof:placetype":"venue"
},
  "geometry": {"coordinates":[10.0585670471,46.3211746216],"type":"Point"}
}