{
  "type": "Feature",
  "properties": {
    "iso:country":"CH",
    "sg:address":"Birchlimatt 1a",
    "sg:city":"Einsiedeln",
    "sg:orig_category":"Herstellung von Metallkonstruktionen",
    "sg:phone":"+41 55 412 81 50",
    "sg:postcode":"8840",
    "sg:province":"Schwyz",
    "wof:name":"Roland Gubser Montagen & Metallbau",
    "wof:placetype":"venue"
},
  "geometry": {"coordinates":[8.7670927048,47.1309776306],"type":"Point"}
}