{
  "type": "Feature",
  "properties": {
    "iso:country":"CH",
    "sg:address":"Eisengasse 15 8008 Z\u00fcrich. Postfach",
    "sg:city":"Z\u00fcrich",
    "sg:orig_category":"Softwareentwicklung U beratung",
    "sg:phone":"+41 12677878",
    "sg:postcode":"8032",
    "sg:province":"Z\u00fcrich",
    "wof:name":"Zenith Media Ag",
    "wof:placetype":"venue"
},
  "geometry": {"coordinates":[8.551858902,47.3628425598],"type":"Point"}
}