{
  "type": "Feature",
  "properties": {
    "iso:country":"CH",
    "sg:address":"Bildgass 1",
    "sg:city":"Schaan",
    "sg:orig_category":"Institutionen f\u00fcr Behinderte",
    "sg:postcode":"9494",
    "wof:name":"Besch\u00fctzende Werkst\u00e4tte Verein F.heilp\u00e4dagog.hilfe",
    "wof:placetype":"venue"
},
  "geometry": {"coordinates":[9.5158777237,47.1676445007],"type":"Point"}
}