{
  "type": "Feature",
  "properties": {
    "addr:full":"Via Cesura 12 Losone Ticino 6616",
    "addr:housenumber":"12",
    "addr:postcode":"6616",
    "addr:street":"Via Cesura",
    "iso:country":"CH",
    "sg:address":"Via Cesura 12",
    "sg:city":"Losone",
    "sg:orig_category":"Alters U Pflegeheime Pensionskassen",
    "sg:phone":"+41 91 791 71 35",
    "sg:postcode":"6616",
    "sg:province":"Ticino",
    "wof:name":"Fondazione Patrizia Casa Anziani Losone",
    "wof:placetype":"venue"
},
  "geometry": {"coordinates":[8.760536,46.167007],"type":"Point"}
}