{
  "type": "Feature",
  "properties": {
    "iso:country":"CH",
    "sg:address":"Industriestrasse 4",
    "sg:city":"Giswil",
    "sg:orig_category":"Detailhandel mit Blumen U Pflanzen Gartenbau",
    "sg:phone":"+41 41 675 12 43",
    "sg:postcode":"6074",
    "sg:province":"Obwalden",
    "wof:name":"Frei Heinrich Ag",
    "wof:placetype":"venue"
},
  "geometry": {"coordinates":[8.182702,46.842052],"type":"Point"}
}