{
  "type": "Feature",
  "properties": {
    "iso:country":"CH",
    "sg:address":"Poststrasse 76",
    "sg:city":"Azmoos",
    "sg:classifiers":[
        {
            "category":"Restaurant",
            "type":"Food & Drink"
        }
    ],
    "sg:phone":"+41 81 783 11 84",
    "sg:postcode":"9478",
    "sg:province":"St. Gallen",
    "wof:name":"Restaurant L\u00f6wen",
    "wof:placetype":"venue"
},
  "geometry": {"coordinates":[9.4758167267,47.0813941956],"type":"Point"}
}