{
  "type": "Feature",
  "properties": {
    "iso:country":"CH",
    "sg:address":"Sous Le Ch\u00e2teau 37 1470 Estavayer-le-lac. Postfach",
    "sg:city":"Estavayer-le-lac",
    "sg:orig_category":"Detailhandel mit Waren verschiedener Art, Hauptrichtung Nahrungsmittel",
    "sg:phone":"+41 26 663 47 51",
    "sg:postcode":"1470",
    "sg:province":"Fribourg",
    "wof:name":"Soldati Eliane Produits Alimentaires, Cosm\u00e9tiques; Distribution, Diffusion",
    "wof:placetype":"venue"
},
  "geometry": {"coordinates":[6.8482789993,46.8487930298],"type":"Point"}
}