{
  "type": "Feature",
  "properties": {
    "iso:country":"CH",
    "sg:address":"Vissigen 22 D",
    "sg:city":"Sion",
    "sg:orig_category":"Softwareentwicklung U beratung",
    "sg:postcode":"1950",
    "sg:province":"Valais",
    "wof:name":"Protechnet, Raemy & Reynard",
    "wof:placetype":"venue"
},
  "geometry": {"coordinates":[7.3710589409,46.2305107117],"type":"Point"}
}