{
  "type": "Feature",
  "properties": {
    "iso:country":"CH",
    "sg:address":"Route De B\u00e2le 135",
    "sg:city":"Del\u00e9mont",
    "sg:orig_category":"Softwareentwicklung U beratung",
    "sg:phone":"+41 32 423 17 61",
    "sg:postcode":"2800",
    "sg:province":"Jura",
    "wof:name":"Option Logicielle, Gyger R\u00e9my",
    "wof:placetype":"venue"
},
  "geometry": {"coordinates":[7.3545489311,47.3694877625],"type":"Point"}
}