{
  "type": "Feature",
  "properties": {
    "iso:country":"CH",
    "sg:address":"Plonserfeldstrasse 8889 Plons. Postfach",
    "sg:city":"Mels",
    "sg:orig_category":"Ger\u00fcstbau Tapeziererei",
    "sg:phone":"+41 81 302 14 49",
    "sg:postcode":"8887",
    "sg:province":"St. Gallen",
    "wof:name":"Senti Ag Malerwerkst\u00e4tte",
    "wof:placetype":"venue"
},
  "geometry": {"coordinates":[9.5051698685,47.006439209],"type":"Point"}
}