{
  "type": "Feature",
  "properties": {
    "iso:country":"CH",
    "sg:address":"Hauptstrasse 55 8225 Siblingen. Postfach 27",
    "sg:city":"Siblingen",
    "sg:orig_category":"Hochschulen U h\u00f6here Ausbildung Informatikschulen",
    "sg:phone":"+41 52 672 32 53",
    "sg:postcode":"8225",
    "sg:province":"Schaffhausen",
    "wof:name":"G\u00e4chter A & O Ausbildung Und Organisationsentwicklung",
    "wof:placetype":"venue"
},
  "geometry": {"coordinates":[8.5197658539,47.7142410278],"type":"Point"}
}