{
  "type": "Feature",
  "properties": {
    "iso:country":"CH",
    "sg:address":"Landstrasse 143",
    "sg:city":"Ruggell",
    "sg:orig_category":"Sportvereine Ballsport Handball",
    "sg:phone":"+41 75 373 19 08",
    "sg:postcode":"9491",
    "wof:name":"Handballclub Unterland",
    "wof:placetype":"venue"
},
  "geometry": {"coordinates":[9.5195302963,47.2354698181],"type":"Point"}
}