{
  "type": "Feature",
  "properties": {
    "iso:country":"CH",
    "sg:address":"Bleichestrasse 30",
    "sg:city":"Werdenberg",
    "sg:orig_category":"Politische Parteien FDP",
    "sg:phone":"+41 81 771 19 49",
    "sg:postcode":"9470",
    "sg:province":"St. Gallen",
    "wof:name":"Fdp Ortspartei Werdenberg",
    "wof:placetype":"venue"
},
  "geometry": {"coordinates":[9.4617948532,47.1716384888],"type":"Point"}
}