{
  "type": "Feature",
  "properties": {
    "iso:country":"CH",
    "sg:address":"Chantemerle Chemin De 23",
    "sg:city":"Lausanne",
    "sg:orig_category":"Wirtschaftspr\u00fcfung, Steuerberatung U Treuhand",
    "sg:postcode":"1010",
    "sg:province":"Vaud",
    "wof:name":"Fm Fiscomanda Sa",
    "wof:placetype":"venue"
},
  "geometry": {"coordinates":[6.6516108513,46.5351638794],"type":"Point"}
}