{
  "type": "Feature",
  "properties": {
    "iso:country":"CH",
    "sg:address":"Bernstrasse 2",
    "sg:city":"Rudolfstetten",
    "sg:orig_category":"Herstellung von Metallerzeugnissen ohne Maschinenbau Herstellung von Werkzeugmaschinen",
    "sg:phone":"+41 56 460 67 00",
    "sg:postcode":"8964",
    "sg:province":"Aargau",
    "wof:name":"Fisher + R\u00fcckle Ag",
    "wof:placetype":"venue"
},
  "geometry": {"coordinates":[8.1847200394,47.4678344727],"type":"Point"}
}