{
  "type": "Feature",
  "properties": {
    "iso:country":"CH",
    "sg:address":"5057",
    "sg:city":"Reitnau",
    "sg:orig_category":"Vereine Abstinenten",
    "sg:postcode":"5057",
    "sg:province":"Aargau",
    "wof:name":"Blaues Kreuz",
    "wof:placetype":"venue"
},
  "geometry": {"coordinates":[8.038479805,47.2520103455],"type":"Point"}
}