{
  "type": "Feature",
  "properties": {
    "iso:country":"CH",
    "sg:address":"Maihofstrasse 44",
    "sg:city":"Luzern",
    "sg:orig_category":"Grosshandel mit Nahrungsmitteln, Getr\u00e4nken U Tabakwaren ohne ausgepr\u00e4gten Schwerpunkt",
    "sg:postcode":"6004",
    "sg:province":"Luzern",
    "wof:name":"El Gallego Avolio Caterina",
    "wof:placetype":"venue"
},
  "geometry": {"coordinates":[8.3088998795,47.0616188049],"type":"Point"}
}