{
  "type": "Feature",
  "properties": {
    "iso:country":"CH",
    "sg:address":"Bruggerstrasse 44 5400 Baden. Postfach",
    "sg:city":"Baden",
    "sg:orig_category":"Detektivb\u00fcros U \u00dcberwachung",
    "sg:phone":"+41 56 222 01 29",
    "sg:postcode":"5400",
    "sg:province":"Aargau",
    "wof:name":"Detektei M\u00fcller Peter Allgemeine Detektiv-arbeiten",
    "wof:placetype":"venue"
},
  "geometry": {"coordinates":[8.3049678802,47.4768829346],"type":"Point"}
}