{
  "type": "Feature",
  "properties": {
    "iso:country":"CH",
    "sg:address":"Chemin Sur-rang 4",
    "sg:city":"Vessy",
    "sg:orig_category":"Sanit\u00e4r, Heizungs U L\u00fcftungsinstallation Sanit\u00e4rinstallation",
    "sg:phone":"+41 26 418 17 48",
    "sg:postcode":"1234",
    "sg:province":"Gen\u00e8ve",
    "wof:name":"Gilbert Julmy Sanit\u00e4r-& Heizungsinstallationen Ag",
    "wof:placetype":"venue"
},
  "geometry": {"coordinates":[7.231523037,46.7350845337],"type":"Point"}
}