{
  "type": "Feature",
  "properties": {
    "iso:country":"CH",
    "sg:address":"Wanderstrasse 87",
    "sg:city":"Basel",
    "sg:orig_category":"Non-Classified Establishments",
    "sg:phone":"+41 32 338 24 82",
    "sg:postcode":"4054",
    "sg:province":"Basel-Stadt",
    "wof:name":"\u00c4du's Blumenstand, B\u00e4hler Adrian",
    "wof:placetype":"venue"
},
  "geometry": {"coordinates":[7.0426301956,47.0200386047],"type":"Point"}
}