{
  "type": "Feature",
  "properties": {
    "iso:country":"CH",
    "sg:address":"Centralstrasse 37",
    "sg:city":"Grenchen",
    "sg:orig_category":"Sonstiger Fachdetailhandel mit Nahrungsmitteln, Getr\u00e4nken U Tabak in Verkaufsr\u00e4umen",
    "sg:phone":"+41 32 652 53 21",
    "sg:postcode":"2540",
    "sg:province":"Solothurn",
    "wof:name":"Grenchner Ch\u00e4si Fischer Fred",
    "wof:placetype":"venue"
},
  "geometry": {"coordinates":[7.3950958252,47.1944084167],"type":"Point"}
}