{
  "type": "Feature",
  "properties": {
    "iso:country":"CH",
    "sg:address":"Schiffbaustrasse 6",
    "sg:city":"Z\u00fcrich",
    "sg:orig_category":"Erbringung von sonstigen Dienstleistungen f\u00fcr Unternehmen",
    "sg:phone":"+41 12768000",
    "sg:postcode":"8005",
    "sg:province":"Z\u00fcrich",
    "wof:name":"Moods Im Schiffbau",
    "wof:placetype":"venue"
},
  "geometry": {"coordinates":[8.5187482834,47.3887672424],"type":"Point"}
}