{
  "type": "Feature",
  "properties": {
    "iso:country":"CH",
    "sg:address":"Neugasse 46",
    "sg:city":"St.gallen",
    "sg:orig_category":"RESTAURANTS: TEA-ROOMS",
    "sg:phone":"+41 71 222 16 35",
    "sg:postcode":"9000",
    "sg:province":"St. Gallen",
    "wof:name":"Schildknecht P",
    "wof:placetype":"venue"
},
  "geometry": {"coordinates":[9.3743562698,47.4243774414],"type":"Point"}
}