{
  "type": "Feature",
  "properties": {
    "iso:country":"CH",
    "sg:address":"Stradone Vecchio 18",
    "sg:city":"Biasca",
    "sg:orig_category":"Herstellung von sonstigen Maschinen f\u00fcr bestimmte Verwendung",
    "sg:phone":"+41 91 862 32 08",
    "sg:postcode":"6710",
    "sg:province":"Ticino",
    "wof:name":"Doichgraf Sa",
    "wof:placetype":"venue"
},
  "geometry": {"coordinates":[8.9654932022,46.3536148071],"type":"Point"}
}