{
  "type": "Feature",
  "properties": {
    "addr:full":"Gotthardstrasse 14 6300 Zug. Postfach 4716 Zug Zug 6304",
    "addr:housenumber":"14",
    "addr:postcode":"6300;4716;6304",
    "addr:street":"Gotthardstrasse;Postfach;Zug",
    "iso:country":"CH",
    "sg:address":"Gotthardstrasse 14 6300 Zug. Postfach 4716",
    "sg:city":"Zug",
    "sg:orig_category":"Detailhandel mit Brot, Back U S\u00fcsswaren Detailhandel mit Zeitungen U Zeitschriften Kioske",
    "sg:phone":"+41 41 711 38 76",
    "sg:postcode":"6304",
    "sg:province":"Zug",
    "wof:name":"Speck Confiserie",
    "wof:placetype":"venue"
},
  "geometry": {"coordinates":[8.516021,47.172123],"type":"Point"}
}