{
  "type": "Feature",
  "properties": {
    "iso:country":"CH",
    "sg:address":"Retterswil 5",
    "sg:city":"Seon",
    "sg:orig_category":"Mit Sport verbundene T\u00e4tigkeiten Sonstige mit Sport verbundene T\u00e4tigkeiten",
    "sg:phone":"+41 62 775 22 64",
    "sg:postcode":"5703",
    "sg:province":"Aargau",
    "wof:name":"Gen.reithalle Binzenholz Herrn Otto L\u00fcscher",
    "wof:placetype":"venue"
},
  "geometry": {"coordinates":[8.153960228,47.3467445374],"type":"Point"}
}