{
  "type": "Feature",
  "properties": {
    "iso:country":"CH",
    "sg:address":"Rue Des Vermondins 19",
    "sg:city":"Boudry",
    "sg:orig_category":"Architekturb\u00fcros",
    "sg:phone":"+41 32 842 36 34",
    "sg:postcode":"2017",
    "sg:province":"Neuch\u00e2tel",
    "wof:name":"Michel Tanner Bureau D'architecture",
    "wof:placetype":"venue"
},
  "geometry": {"coordinates":[6.831981,46.94976],"type":"Point"}
}