{
  "type": "Feature",
  "properties": {
    "iso:country":"CH",
    "sg:address":"Chemin Du Cr\u00eat-de-la-palud",
    "sg:city":"St-l\u00e9gier",
    "sg:orig_category":"Mit Sport verbundene T\u00e4tigkeiten",
    "sg:phone":"+41 21 943 18 97",
    "sg:postcode":"1806",
    "sg:province":"Vaud",
    "wof:name":"Edmond Laub Man\u00e8ge & \u00e9cole D'\u00e9quitation",
    "wof:placetype":"venue"
},
  "geometry": {"coordinates":[6.3426499367,43.7803611755],"type":"Point"}
}