{
  "type": "Feature",
  "properties": {
    "addr:full":"Maupas Rue Du 24 Lausanne Vaud 1004",
    "addr:housenumber":"maupas",
    "addr:postcode":"1004",
    "addr:street":"Rue Du 24",
    "iso:country":"CH",
    "sg:address":"Maupas Rue Du 24",
    "sg:city":"Lausanne",
    "sg:orig_category":"Detailhandel mit B\u00fcchern, Zeitungen, Schreib U Papeteriewaren",
    "sg:postcode":"1004",
    "sg:province":"Vaud",
    "wof:name":"Kiosque Mamin",
    "wof:placetype":"venue"
},
  "geometry": {"coordinates":[7.091469,47.063721],"type":"Point"}
}