{
  "type": "Feature",
  "properties": {
    "iso:country":"CH",
    "sg:address":"Rheingasse 23",
    "sg:city":"Basel",
    "sg:orig_category":"Interessenvertretungen",
    "sg:postcode":"4058",
    "sg:province":"Basel-Stadt",
    "wof:name":"Vereinigung Format",
    "wof:placetype":"venue"
},
  "geometry": {"coordinates":[7.5922818184,47.5600662231],"type":"Point"}
}