{
  "type": "Feature",
  "properties": {
    "iso:country":"CH",
    "sg:address":"Kesslerstrasse 1",
    "sg:city":"Muhen",
    "sg:orig_category":"Mechanik Mechanische Werkst\u00e4tten",
    "sg:phone":"+41 62 723 88 86",
    "sg:postcode":"5037",
    "sg:province":"Aargau",
    "wof:name":"Widmer Werner",
    "wof:placetype":"venue"
},
  "geometry": {"coordinates":[8.0551490784,47.3284721375],"type":"Point"}
}