{
  "type": "Feature",
  "properties": {
    "iso:country":"CH",
    "sg:address":"Im Br\u00fchl 1 Postfach",
    "sg:city":"Allschwil",
    "sg:classifiers":[
        {
            "category":"Manufacturing",
            "subcategory":"Wood Products",
            "type":"Manufacturing & Wholesale Goods"
        }
    ],
    "sg:phone":"+41 61 486 95 55",
    "sg:postcode":"4123",
    "sg:province":"Basel-Landschaft",
    "sg:tags":[
        "professional",
        "furniture"
    ],
    "wof:name":"Schweitzer Ag",
    "wof:placetype":"venue"
},
  "geometry": {"coordinates":[6.6815919876,51.252571106],"type":"Point"}
}