{
  "type": "Feature",
  "properties": {
    "iso:country":"CH",
    "sg:address":"Aufhofen 45",
    "sg:city":"Thundorf",
    "sg:orig_category":"Vereine Musik/Blasmusik",
    "sg:phone":"+41 62 390 16 65",
    "sg:postcode":"8512",
    "sg:province":"Thurgau",
    "wof:name":"Musikgesellschaft Eintracht",
    "wof:placetype":"venue"
},
  "geometry": {"coordinates":[7.7717170715,47.3320465088],"type":"Point"}
}