{
  "type": "Feature",
  "properties": {
    "iso:country":"CH",
    "sg:address":"Chemin Des Pr\u00e9s-marais 20",
    "sg:city":"Bernex",
    "sg:classifiers":[
        {
            "category":"Professional",
            "subcategory":"Employment Agencies",
            "type":"Services"
        }
    ],
    "sg:phone":"+41 22 777 00 01",
    "sg:postcode":"1233",
    "sg:province":"Gen\u00e8ve",
    "sg:tags":[
        "personal",
        "u",
        "stellenvermittlung"
    ],
    "wof:name":"Soci\u00e9t\u00e9 De Conseils Et Recrutement Socorec Sa",
    "wof:placetype":"venue"
},
  "geometry": {"coordinates":[6.0792078972,46.179977417],"type":"Point"}
}