{
  "type": "Feature",
  "properties": {
    "iso:country":"CH",
    "sg:address":"Schulhausgasse 14a 3110 M\u00fcnsingen. Postfach 1101",
    "sg:city":"M\u00fcnsingen",
    "sg:orig_category":"Vermittlung von Immobilien Wirtschaftspr\u00fcfung, Steuerberatung U Treuhand",
    "sg:phone":"+41 31 721 06 41",
    "sg:postcode":"3110",
    "sg:province":"Bern",
    "wof:name":"Schwab Treuhand",
    "wof:placetype":"venue"
},
  "geometry": {"coordinates":[7.5651531219,46.8763084412],"type":"Point"}
}