{
  "type": "Feature",
  "properties": {
    "iso:country":"CH",
    "sg:address":"Via Casserinetta 10",
    "sg:city":"Paradiso",
    "sg:orig_category":"Aktivit\u00e4ten der Generalunternehmen im Baugewerbe Vermietung U Verpachtung von eigenen Immobilien",
    "sg:phone":"+41 91 985 20 56",
    "sg:postcode":"6900",
    "sg:province":"Ticino",
    "wof:name":"Edilimmobiliare Sa",
    "wof:placetype":"venue"
},
  "geometry": {"coordinates":[8.951305,46.002975],"type":"Point"}
}