{
  "type": "Feature",
  "properties": {
    "iso:country":"CH",
    "sg:address":"Schaffhauserstrasse 144",
    "sg:city":"Winterthur",
    "sg:orig_category":"Herstellung von isolierten Elektrokabeln, -leitungen U dr\u00e4hten -D\u00e4mmung gegen K\u00e4lte, W\u00e4rme, Schall U",
    "sg:phone":"+41 52 212 05 82",
    "sg:postcode":"8400",
    "sg:province":"Z\u00fcrich",
    "wof:name":"Wintiisol Gmbh",
    "wof:placetype":"venue"
},
  "geometry": {"coordinates":[8.7206506729,47.5160255432],"type":"Point"}
}