{
  "type": "Feature",
  "properties": {
    "addr:full":"Darvella Trun Graubunden 7166",
    "addr:postcode":"7166",
    "iso:country":"CH",
    "sg:address":"Darvella",
    "sg:city":"Trun",
    "sg:orig_category":"Detailhandel mit Antiquit\u00e4ten Detailhandel mit M\u00f6beln",
    "sg:phone":"+41 81 943 22 23",
    "sg:postcode":"7166",
    "sg:province":"Graubunden",
    "wof:name":"Anton Schwarz Arch.intern & Antiquitads",
    "wof:placetype":"venue"
},
  "geometry": {"coordinates":[8.997463,46.744324],"type":"Point"}
}