{
  "type": "Feature",
  "properties": {
    "iso:country":"CH",
    "sg:address":"Halbartenstrasse 71",
    "sg:city":"Wettingen",
    "sg:orig_category":"Allgemeiner Hoch U Tiefbau Strassenbau",
    "sg:phone":"+41 31 819 38 05",
    "sg:postcode":"5430",
    "sg:province":"Aargau",
    "wof:name":"Weibel Muri Ag",
    "wof:placetype":"venue"
},
  "geometry": {"coordinates":[7.504003,46.922558],"type":"Point"}
}