{
  "type": "Feature",
  "properties": {
    "iso:country":"CH",
    "sg:address":"Schueler 7",
    "sg:city":"Thal",
    "sg:orig_category":"Sonstiger Grosshandel",
    "sg:postcode":"9425",
    "sg:province":"St. Gallen",
    "wof:name":"Stieger Ulrich, Handel Und Transporte",
    "wof:placetype":"venue"
},
  "geometry": {"coordinates":[9.5670871735,47.4756317139],"type":"Point"}
}