{
  "type": "Feature",
  "properties": {
    "iso:country":"CH",
    "sg:address":"1136",
    "sg:city":"Bussy-chardonney",
    "sg:orig_category":"Markt U Meinungsforschung",
    "sg:postcode":"1136",
    "sg:province":"Vaud",
    "wof:name":"Disam Emery Pernette",
    "wof:placetype":"venue"
},
  "geometry": {"coordinates":[6.4395899773,46.5308494568],"type":"Point"}
}