{
  "type": "Feature",
  "properties": {
    "iso:country":"CH",
    "sg:address":"Bruderholzrain 4a",
    "sg:city":"Binningen",
    "sg:orig_category":"Finanzierungsinstitutionen",
    "sg:phone":"+41 61 421 83 08",
    "sg:postcode":"4102",
    "sg:province":"Basel-Landschaft",
    "wof:name":"Hrv Consult Ag",
    "wof:placetype":"venue"
},
  "geometry": {"coordinates":[7.5783109665,47.5377502441],"type":"Point"}
}