{
  "type": "Feature",
  "properties": {
    "iso:country":"CH",
    "sg:address":"Tramstrasse 34",
    "sg:city":"M\u00fcnchenstein",
    "sg:orig_category":"Non-Classified Establishments",
    "sg:postcode":"4142",
    "sg:province":"Basel-Landschaft",
    "wof:name":"Boutique A+o Gmbh",
    "wof:placetype":"venue"
},
  "geometry": {"coordinates":[7.6188030243,47.5115318298],"type":"Point"}
}