{
  "type": "Feature",
  "properties": {
    "iso:country":"CH",
    "sg:address":"7562",
    "sg:city":"Samnaun-compatsch",
    "sg:orig_category":"Bauschreinerei Herstellung von Konstruktionsteilen, Fertigbauteilen U Ausbauelementen aus Holz",
    "sg:phone":"+41 41 930 26 56",
    "sg:postcode":"7562",
    "sg:province":"Graubunden",
    "wof:name":"Schreinerei Jurt Gmbh",
    "wof:placetype":"venue"
},
  "geometry": {"coordinates":[8.147112,47.225193],"type":"Point"}
}