{
  "type": "Feature",
  "properties": {
    "iso:country":"CH",
    "sg:address":"Seftigenstrasse 59",
    "sg:city":"Burgistein",
    "sg:orig_category":"Unclassifiable Establishments",
    "sg:phone":"+41 33 356 11 28",
    "sg:postcode":"3664",
    "sg:province":"Bern",
    "wof:name":"M\u00f6bel Ryter Ag M\u00f6bel, Einrichtungsgegenst\u00e4nde; Herstellung, Handel",
    "wof:placetype":"venue"
},
  "geometry": {"coordinates":[7.5223231316,46.7902107239],"type":"Point"}
}