{
  "type": "Feature",
  "properties": {
    "iso:country":"CH",
    "sg:address":"Oberdorfstrasse 12a 8965 Berikon. Postfach",
    "sg:city":"Berikon",
    "sg:orig_category":"Gesundheitswesen",
    "sg:postcode":"8965",
    "sg:province":"Aargau",
    "wof:name":"Praxis F\u00fcr Positive Lebensgestaltung, Helbling D.",
    "wof:placetype":"venue"
},
  "geometry": {"coordinates":[8.3798666,47.3488311768],"type":"Point"}
}