{
  "type": "Feature",
  "properties": {
    "iso:country":"CH",
    "sg:address":"Via Lucerna 11",
    "sg:city":"Biasca",
    "sg:orig_category":"Zahnarztpraxen",
    "sg:phone":"+41 91 862 11 86",
    "sg:postcode":"6710",
    "sg:province":"Ticino",
    "wof:name":"Dottori Med.dent. Domin\u00e9 Dentisti",
    "wof:placetype":"venue"
},
  "geometry": {"coordinates":[8.9691705704,46.3585853577],"type":"Point"}
}