{
  "type": "Feature",
  "properties": {
    "iso:country":"CH",
    "sg:address":"B\u00e4renstrasse 2",
    "sg:city":"Kreuzlingen",
    "sg:orig_category":"Einrahmungen",
    "sg:phone":"+41 71 672 55 87",
    "sg:postcode":"8280",
    "sg:province":"Thurgau",
    "wof:name":"Beat & Margrit Bartholet Einrahmungs-atelier",
    "wof:placetype":"venue"
},
  "geometry": {"coordinates":[9.1712417603,47.6444664001],"type":"Point"}
}