{
  "type": "Feature",
  "properties": {
    "iso:country":"CH",
    "sg:address":"Kantonsschulstrasse 1",
    "sg:city":"Z\u00fcrich",
    "sg:orig_category":"Sonstiger Grosshandel",
    "sg:postcode":"8001",
    "sg:province":"Z\u00fcrich",
    "wof:name":"Epos Export-import S. Radovanovic",
    "wof:placetype":"venue"
},
  "geometry": {"coordinates":[8.5482873917,47.3711357117],"type":"Point"}
}