{
  "type": "Feature",
  "properties": {
    "iso:country":"CH",
    "sg:address":"Flurweg 12",
    "sg:city":"Lyss",
    "sg:orig_category":"Markt U Meinungsforschung",
    "sg:postcode":"3250",
    "sg:province":"Bern",
    "wof:name":"Tec Marketing Gmbh",
    "wof:placetype":"venue"
},
  "geometry": {"coordinates":[7.3019499779,47.0698661804],"type":"Point"}
}