{
  "type": "Feature",
  "properties": {
    "iso:country":"CH",
    "sg:address":"Via Livio 5",
    "sg:city":"Chiasso",
    "sg:orig_category":"Unternehmensberatung",
    "sg:phone":"+41 91 682 49 91",
    "sg:postcode":"6830",
    "sg:province":"Ticino",
    "wof:name":"Studio A.ciocca Sa Consulenze Aziendali",
    "wof:placetype":"venue"
},
  "geometry": {"coordinates":[9.0294589996,45.8333625793],"type":"Point"}
}