{
  "type": "Feature",
  "properties": {
    "iso:country":"CH",
    "sg:address":"T\u00f6sstalstrasse 23",
    "sg:city":"Kollbrunn",
    "sg:orig_category":"Handel mit Automobilen",
    "sg:phone":"+41 33 336 11 44",
    "sg:postcode":"8483",
    "sg:province":"Z\u00fcrich",
    "wof:name":"Sporting Automobile Wittwer F. Ag",
    "wof:placetype":"venue"
},
  "geometry": {"coordinates":[7.6195058823,46.7311820984],"type":"Point"}
}