{
  "type": "Feature",
  "properties": {
    "iso:country":"CH",
    "sg:address":"Oberallmendstrasse 20a 6300 Zug. Postfach 140",
    "sg:city":"Zug",
    "sg:orig_category":"Grosshandel mit Holz U Baustoffen Handelsvermittlung U Grosshandel",
    "sg:phone":"+41 17412704",
    "sg:postcode":"6301",
    "sg:province":"Zug",
    "wof:name":"Durisol Element Ag",
    "wof:placetype":"venue"
},
  "geometry": {"coordinates":[8.3857135773,47.3889694214],"type":"Point"}
}