{
  "type": "Feature",
  "properties": {
    "iso:country":"CH",
    "sg:address":"Avenue De La Praille 31 1227 Carouge Ge. Postfach",
    "sg:city":"Gen\u00e8ve",
    "sg:orig_category":"Parkettleger Reinigungsgewerbe",
    "sg:phone":"+41 22 738 93 48",
    "sg:postcode":"1201",
    "sg:province":"Gen\u00e8ve",
    "wof:name":"Art-mania, Orosa Abel Hermida Et Fraga Jos\u00e9 Entreprise De Nettoyage Et Pose De Parquets",
    "wof:placetype":"venue"
},
  "geometry": {"coordinates":[6.1345100403,46.1868400574],"type":"Point"}
}