{
  "type": "Feature",
  "properties": {
    "iso:country":"CH",
    "sg:address":"Kommetsr\u00fcti 7",
    "sg:city":"Wolhusen",
    "sg:classifiers":[
        {
            "category":"Sports & Exercise",
            "subcategory":"Stables",
            "type":"Entertainment"
        }
    ],
    "sg:phone":"+41 41 492 62 62",
    "sg:postcode":"6110",
    "sg:province":"Luzern",
    "sg:tags":[
        "leather",
        "product",
        "miscellaneous",
        "shoe"
    ],
    "wof:name":"St\u00d6ckli Ski Ag",
    "wof:placetype":"venue"
},
  "geometry": {"coordinates":[8.0685253143,47.0560073853],"type":"Point"}
}