{
  "type": "Feature",
  "properties": {
    "iso:country":"CH",
    "sg:address":"Route De Montcherand",
    "sg:city":"Orbe",
    "sg:orig_category":"Fachdetailhandel mit pharmazeutischen Produkten",
    "sg:phone":"+41 24 441 83 64",
    "sg:postcode":"1350",
    "sg:province":"Vaud",
    "wof:name":"Pharmacentre Sa Pharmacie De La Croix",
    "wof:placetype":"venue"
},
  "geometry": {"coordinates":[6.523018837,46.729511261],"type":"Point"}
}