{
  "type": "Feature",
  "properties": {
    "iso:country":"CH",
    "sg:address":"Viale S.franscini 6",
    "sg:city":"Bellinzona",
    "sg:orig_category":"Steuer\u00e4mter",
    "sg:phone":"+41 91 814 40 51",
    "sg:postcode":"6500",
    "sg:province":"Ticino",
    "wof:name":"Amministrazione Cantonale Delle Contribuzioni",
    "wof:placetype":"venue"
},
  "geometry": {"coordinates":[9.0187263489,46.190738678],"type":"Point"}
}