{
  "type": "Feature",
  "properties": {
    "iso:country":"CH",
    "sg:address":"Via Peri 9b",
    "sg:city":"Lugano",
    "sg:orig_category":"Kauf U Verkauf von Immobilien auf eigene Rechnung Vermittlung von Immobilien",
    "sg:phone":"+41 91 923 47 47",
    "sg:postcode":"6900",
    "sg:province":"Ticino",
    "wof:name":"Titanus Consulting & Promotion Sa Mediazione N. Compravendite E N. Permute Di Fondi Ecc",
    "wof:placetype":"venue"
},
  "geometry": {"coordinates":[8.9505681992,46.0056304932],"type":"Point"}
}