{
  "type": "Feature",
  "properties": {
    "iso:country":"CH",
    "sg:address":"Rue Du Voisinand 14",
    "sg:city":"Ch\u00e2telard-lutry",
    "sg:orig_category":"Fachdetailhandel in Verkaufsr\u00e4umen",
    "sg:postcode":"1095",
    "sg:province":"Vaud",
    "wof:name":"Jouets Kuhn Mme",
    "wof:placetype":"venue"
},
  "geometry": {"coordinates":[6.6870598793,46.5039138794],"type":"Point"}
}