{
  "type": "Feature",
  "properties": {
    "iso:country":"CH",
    "sg:address":"Schweigr\u00fctistrasse 2",
    "sg:city":"Altendorf",
    "sg:orig_category":"Einbau von Schreinerwaren",
    "sg:phone":"+41 55 442 77 25",
    "sg:postcode":"8852",
    "sg:province":"Schwyz",
    "wof:name":"Armin Sp\u00e4ni Schreiner Baumontagen",
    "wof:placetype":"venue"
},
  "geometry": {"coordinates":[8.840256691,47.1749305725],"type":"Point"}
}