{
  "type": "Feature",
  "properties": {
    "iso:country":"CH",
    "sg:address":"Ruessenstrasse 5 6340 Baar. Postfach 1113",
    "sg:city":"Zug",
    "sg:orig_category":"Grosshandel mit Sportartikeln Sonstiger Grosshandel",
    "sg:phone":"+41 81 420 13 88",
    "sg:postcode":"6301",
    "sg:province":"Zug",
    "wof:name":"Adcom Sports Trade Ag",
    "wof:placetype":"venue"
},
  "geometry": {"coordinates":[8.5635023117,47.2124977112],"type":"Point"}
}