{
  "type": "Feature",
  "properties": {
    "addr:full":"8192 Glattfelden Z\u00fcrich 8192",
    "addr:postcode":"8192;8192",
    "iso:country":"CH",
    "sg:address":"8192",
    "sg:city":"Glattfelden",
    "sg:orig_category":"Bauspenglerei Zimmerei, Dachdeckerei, Bauspenglerei U Abdichtung",
    "sg:phone":"+41 18670151",
    "sg:postcode":"8192",
    "sg:province":"Z\u00fcrich",
    "wof:name":"Keller Hch. S\u00f6hne.",
    "wof:placetype":"venue"
},
  "geometry": {"coordinates":[8.50249,47.558846],"type":"Point"}
}