{
  "type": "Feature",
  "properties": {
    "iso:country":"CH",
    "sg:address":"6430",
    "sg:city":"Schwyz",
    "sg:orig_category":"Schulpflegen",
    "sg:postcode":"6430",
    "sg:province":"Schwyz",
    "wof:name":"Schulrat Des Bezirks Wil",
    "wof:placetype":"venue"
},
  "geometry": {"coordinates":[9.0534296036,47.4628791809],"type":"Point"}
}