{
  "type": "Feature",
  "properties": {
    "iso:country":"CH",
    "sg:address":"Vigne Via Alle 15",
    "sg:city":"Pregassona",
    "sg:orig_category":"Herstellung von Radio U Fernsehger\u00e4ten sowie phono U videotechnischen Ger\u00e4ten",
    "sg:postcode":"6963",
    "sg:province":"Ticino",
    "wof:name":"Alba Games Sagl",
    "wof:placetype":"venue"
},
  "geometry": {"coordinates":[8.9687623978,46.0203361511],"type":"Point"}
}