{
  "type": "Feature",
  "properties": {
    "iso:country":"CH",
    "sg:address":"8952 Schlieren. Postfach",
    "sg:city":"Z\u00fcrich-m\u00fclligen",
    "sg:orig_category":"Non-Classified Establishments",
    "sg:phone":"+41 17303681",
    "sg:postcode":"8010",
    "sg:province":"Z\u00fcrich",
    "wof:name":"Wagenwerkst\u00e4tte Ptt",
    "wof:placetype":"venue"
},
  "geometry": {"coordinates":[8.447259903,47.3944702148],"type":"Point"}
}