{
  "type": "Feature",
  "properties": {
    "iso:country":"CH",
    "sg:address":"Hauptstrasse 24a 7240 K\u00fcblis. Postfach",
    "sg:city":"K\u00fcblis",
    "sg:orig_category":"Sonstiger Grosshandel",
    "sg:postcode":"7240",
    "sg:province":"Graubunden",
    "wof:name":"Kaiser Consulting Und Finanzierungen Warenhandel, Beratungen U. Dienstleistungen Im Finanzierungsbereich Usw",
    "wof:placetype":"venue"
},
  "geometry": {"coordinates":[9.7757110596,46.9150047302],"type":"Point"}
}