{
  "type": "Feature",
  "properties": {
    "iso:country":"CH",
    "sg:address":"Haus Waldrand B\u00fctschels",
    "sg:city":"Kandersteg",
    "sg:orig_category":"Wohnheime",
    "sg:phone":"+41 33 675 21 00",
    "sg:postcode":"3718",
    "sg:province":"Bern",
    "wof:name":"Buddhistisches Kloster Dhammapala",
    "wof:placetype":"venue"
},
  "geometry": {"coordinates":[7.6730470657,46.4949836731],"type":"Point"}
}