{
  "type": "Feature",
  "properties": {
    "iso:country":"CH",
    "sg:address":"1775",
    "sg:city":"Mannens",
    "sg:orig_category":"Non-Classified Establishments",
    "sg:phone":"+41 26 660 65 77",
    "sg:postcode":"1775",
    "sg:province":"Fribourg",
    "wof:name":"Dutruit Robert.",
    "wof:placetype":"venue"
},
  "geometry": {"coordinates":[6.9685797691,46.7935905457],"type":"Point"}
}