{
  "type": "Feature",
  "properties": {
    "iso:country":"CH",
    "sg:address":"Kreuzackerstrasse 3",
    "sg:city":"Pfungen",
    "sg:orig_category":"Kaminfeger",
    "sg:phone":"+41 52 315 13 66",
    "sg:postcode":"8422",
    "sg:province":"Z\u00fcrich",
    "wof:name":"Urs Thalmann Kaminfegergesch\u00e4ft",
    "wof:placetype":"venue"
},
  "geometry": {"coordinates":[8.6417484283,47.5171318054],"type":"Point"}
}