{
  "type": "Feature",
  "properties": {
    "iso:country":"CH",
    "sg:address":"Rue Tavernier 12",
    "sg:city":"Aubonne",
    "sg:orig_category":"Bauschreinerei Herstellung von M\u00f6beln verschiedener Art",
    "sg:phone":"+41 21 808 54 22",
    "sg:postcode":"1170",
    "sg:province":"Vaud",
    "wof:name":"Anne-catherine Gaillard Eb\u00e9nisterie",
    "wof:placetype":"venue"
},
  "geometry": {"coordinates":[6.3915758133,46.4962539673],"type":"Point"}
}