{
  "type": "Feature",
  "properties": {
    "iso:country":"CH",
    "sg:address":"Tabazan Rue 3 1204 Gen\u00e8ve. Postfach",
    "sg:city":"Gen\u00e8ve",
    "sg:orig_category":"Architektur U Ingenieurb\u00fcros",
    "sg:postcode":"1201",
    "sg:province":"Gen\u00e8ve",
    "wof:name":"Juon Roman",
    "wof:placetype":"venue"
},
  "geometry": {"coordinates":[6.148252,46.198956],"type":"Point"}
}