{
  "type": "Feature",
  "properties": {
    "iso:country":"CH",
    "sg:address":"Chemin De La Cr\u00e9taux",
    "sg:city":"Gland",
    "sg:orig_category":"Grosshandel mit sonstigen Maschinen U Ausr\u00fcstungen f\u00fcr Industrie, Handel U Schiffahrt Herstellung vo",
    "sg:phone":"+41 55 442 59 05",
    "sg:postcode":"1196",
    "sg:province":"Vaud",
    "wof:name":"Tubi - Tech, Staffa G. & Co. Ablaufleitungen; Vorfabrikation U. Planung",
    "wof:placetype":"venue"
},
  "geometry": {"coordinates":[8.8558244705,47.1920127869],"type":"Point"}
}