{
  "type": "Feature",
  "properties": {
    "iso:country":"CH",
    "sg:address":"Hohlstrasse 221",
    "sg:city":"Z\u00fcrich",
    "sg:orig_category":"Unclassifiable Establishments",
    "sg:postcode":"8004",
    "sg:province":"Z\u00fcrich",
    "wof:name":"Naturheilpraxis Thaler Judith Gmbh",
    "wof:placetype":"venue"
},
  "geometry": {"coordinates":[9.4123220444,47.4432067871],"type":"Point"}
}