{
  "type": "Feature",
  "properties": {
    "iso:country":"CH",
    "sg:address":"Marktg. 7",
    "sg:city":"Huttwil",
    "sg:classifiers":[
        {
            "category":"Shopping",
            "subcategory":"Clothing, Apparel, & Fashions",
            "type":"Retail Goods"
        }
    ],
    "sg:phone":"+41 62 962 22 40",
    "sg:postcode":"4950",
    "sg:province":"Bern",
    "sg:tags":[
        "textile",
        "clothing",
        "clothes"
    ],
    "wof:name":"Niederhauser Mode Ag Huttwil",
    "wof:placetype":"venue"
},
  "geometry": {"coordinates":[7.84726,47.113998],"type":"Point"}
}