{
  "type": "Feature",
  "properties": {
    "iso:country":"CH",
    "sg:address":"Hubenstrasse 15 8057 Z\u00fcrich. Postfach",
    "sg:city":"Z\u00fcrich",
    "sg:orig_category":"Betrieb von Taxis",
    "sg:postcode":"8057",
    "sg:province":"Z\u00fcrich",
    "wof:name":"Giorlando Giovanni Taxi Und Kleintransporte",
    "wof:placetype":"venue"
},
  "geometry": {"coordinates":[8.558737,47.403816],"type":"Point"}
}