{
  "type": "Feature",
  "properties": {
    "iso:country":"CH",
    "sg:address":"Alter Kirchenweg 3",
    "sg:city":"Wallisellen",
    "sg:orig_category":"Sportvereine",
    "sg:phone":"+41 71 288 26 44",
    "sg:postcode":"8304",
    "sg:province":"Z\u00fcrich",
    "wof:name":"Leichtathletik-club Br\u00fchl",
    "wof:placetype":"venue"
},
  "geometry": {"coordinates":[9.3737154007,47.4263916016],"type":"Point"}
}