{
  "type": "Feature",
  "properties": {
    "iso:country":"CH",
    "sg:address":"Chrisegge",
    "sg:city":"Courlevon",
    "sg:orig_category":"Bauschreinerei Innenausbau",
    "sg:phone":"+41 26 684 23 36",
    "sg:postcode":"1795",
    "sg:province":"Fribourg",
    "wof:name":"Fritz M\u00fcller Schreinerei & Innenausbau",
    "wof:placetype":"venue"
},
  "geometry": {"coordinates":[7.107587,46.888096],"type":"Point"}
}