{
  "type": "Feature",
  "properties": {
    "iso:country":"CH",
    "sg:address":"Landstrasse 70 8450 Andelfingen. Postfach",
    "sg:city":"Andelfingen",
    "sg:orig_category":"Offsetdruck Verlagsgewerbe",
    "sg:phone":"+41 52 317 12 87",
    "sg:postcode":"8450",
    "sg:province":"Z\u00fcrich",
    "wof:name":"Druckerei Akeret Ag Druck & Verlag Andelf.zeitung",
    "wof:placetype":"venue"
},
  "geometry": {"coordinates":[8.6791505814,47.596622467],"type":"Point"}
}