{
  "type": "Feature",
  "properties": {
    "iso:country":"CH",
    "sg:address":"Binzm\u00fchlestrasse 13 8000 Z\u00fcrich. Postfach 8050 Z\u00fcrich",
    "sg:city":"Zust",
    "sg:orig_category":"Interessenvertretungen",
    "sg:phone":"+41 13078066",
    "sg:postcode":"50",
    "wof:name":"Schweizerischer Verband Creditreform",
    "wof:placetype":"venue"
},
  "geometry": {"coordinates":[8.5484457016,47.4138221741],"type":"Point"}
}