{
  "type": "Feature",
  "properties": {
    "addr:full":"Waldeggstrasse 7 3097 Liebefeld. Postfach Liebefeld Bern 3097",
    "addr:housenumber":"7",
    "addr:postcode":"3097;postfach;3097",
    "addr:street":"Waldeggstrasse",
    "iso:country":"CH",
    "sg:address":"Waldeggstrasse 7 3097 Liebefeld. Postfach",
    "sg:city":"Liebefeld",
    "sg:orig_category":"Architektur U Ingenieurb\u00fcros",
    "sg:postcode":"3097",
    "sg:province":"Bern",
    "wof:name":"Brodbeck Ernst, Element-planung.",
    "wof:placetype":"venue"
},
  "geometry": {"coordinates":[7.421261,46.932468],"type":"Point"}
}