{
  "type": "Feature",
  "properties": {
    "iso:country":"CH",
    "sg:address":"Chemin De Ballallaz 12",
    "sg:city":"Montreux",
    "sg:orig_category":"Detailhandel mit elektrischen Haushalts-,Radio U Fernsehger\u00e4ten sowie Musikinstrumenten",
    "sg:phone":"+41 79 606 06 11",
    "sg:postcode":"1820",
    "sg:province":"Vaud",
    "wof:name":"Parisod Charles",
    "wof:placetype":"venue"
},
  "geometry": {"coordinates":[6.914203167,46.4351844788],"type":"Point"}
}