{
  "type": "Feature",
  "properties": {
    "iso:country":"CH",
    "sg:address":"Seilerweg 14",
    "sg:city":"Uttigen",
    "sg:orig_category":"Sanit\u00e4r, Heizungs U L\u00fcftungsinstallation Sanit\u00e4rinstallation",
    "sg:phone":"+41 33 345 30 37",
    "sg:postcode":"3628",
    "sg:province":"Bern",
    "wof:name":"Trachsel Rudolf",
    "wof:placetype":"venue"
},
  "geometry": {"coordinates":[7.5733737946,46.7964172363],"type":"Point"}
}