{
  "type": "Feature",
  "properties": {
    "iso:country":"CH",
    "sg:address":"1727",
    "sg:city":"Corpataux",
    "sg:orig_category":"Primarschulen",
    "sg:phone":"+41 26 917 85 42",
    "sg:postcode":"1727",
    "sg:province":"Fribourg",
    "wof:name":"Ecole Primaire",
    "wof:placetype":"venue"
},
  "geometry": {"coordinates":[7.09953022,46.7241897583],"type":"Point"}
}