{
  "type": "Feature",
  "properties": {
    "iso:country":"CH",
    "sg:address":"Chemin De Malley 12",
    "sg:city":"Lausanne",
    "sg:orig_category":"Elektroinstallation Herstellung von sonstigen elektrischen Ausr\u00fcstungen",
    "sg:phone":"+41 41 449 08 08",
    "sg:postcode":"1007",
    "sg:province":"Vaud",
    "wof:name":"Hubert M\u00fcller Elektro Gmbh",
    "wof:placetype":"venue"
},
  "geometry": {"coordinates":[8.3225250244,47.1305160522],"type":"Point"}
}