{
  "type": "Feature",
  "properties": {
    "iso:country":"CH",
    "sg:address":"Bruggmattweg 42 4242 Laufen. Postfach",
    "sg:city":"Laufen",
    "sg:orig_category":"Sonstige mit der Informatik verbundene T\u00e4tigkeiten",
    "sg:postcode":"4242",
    "sg:province":"Basel-Landschaft",
    "wof:name":"Panda Support J\u00e4ggi + Oser",
    "wof:placetype":"venue"
},
  "geometry": {"coordinates":[7.4977731705,47.4163017273],"type":"Point"}
}