{
  "type": "Feature",
  "properties": {
    "iso:country":"CH",
    "sg:address":"Kantonsstrasse 33 3902 Glis. Postfach",
    "sg:city":"Glis",
    "sg:orig_category":"Bauschreinerei Innenausbau",
    "sg:phone":"+41 79 301 42 33",
    "sg:postcode":"3902",
    "sg:province":"Valais",
    "wof:name":"Zeiter Martin + Berchtold Werner Ag",
    "wof:placetype":"venue"
},
  "geometry": {"coordinates":[7.977682,46.31086],"type":"Point"}
}