{
  "type": "Feature",
  "properties": {
    "iso:country":"CH",
    "sg:address":"Schachen 6033 Buchrain. Postfach 463",
    "sg:city":"Buchrain",
    "sg:orig_category":"Herstellung von Tanks U Sammelbeh\u00e4ltern aus Metall Stahl U Leichtmetallbau",
    "sg:phone":"+41 41 448 00 80",
    "sg:postcode":"6033",
    "sg:province":"Luzern",
    "wof:name":"Wirth & Co Ag",
    "wof:placetype":"venue"
},
  "geometry": {"coordinates":[8.3468999863,47.1015892029],"type":"Point"}
}