{
  "type": "Feature",
  "properties": {
    "iso:country":"CH",
    "sg:address":"Dorfstrasse 39",
    "sg:city":"Engelberg",
    "sg:orig_category":"Unternehmensberatung",
    "sg:postcode":"6390",
    "sg:province":"Obwalden",
    "wof:name":"Mirpa-gastro Ag",
    "wof:placetype":"venue"
},
  "geometry": {"coordinates":[8.4025783539,46.8201446533],"type":"Point"}
}