{
  "type": "Feature",
  "properties": {
    "iso:country":"CH",
    "sg:address":"Dorfstrasse 27",
    "sg:city":"Feusisberg",
    "sg:orig_category":"Diskotheken, Dancings, Night Clubs",
    "sg:phone":"+41 71 222 64 17",
    "sg:postcode":"8835",
    "sg:province":"Schwyz",
    "wof:name":"Disco-dancing Blue-point Ag",
    "wof:placetype":"venue"
},
  "geometry": {"coordinates":[9.3726291656,47.4247322083],"type":"Point"}
}