{
  "type": "Feature",
  "properties": {
    "iso:country":"CH",
    "sg:address":"Buchenstrasse 16",
    "sg:city":"Herisau",
    "sg:orig_category":"Lagerung",
    "sg:phone":"+41 71 352 30 66",
    "sg:postcode":"9100",
    "sg:province":"Appenzell Ausserrhoden",
    "wof:name":"Tiefk\u00fchlanlage Herisau",
    "wof:placetype":"venue"
},
  "geometry": {"coordinates":[9.2819671631,47.387336731],"type":"Point"}
}