{
  "type": "Feature",
  "properties": {
    "iso:country":"CH",
    "sg:address":"Lenggenbachstrasse 25",
    "sg:city":"Fahrweid",
    "sg:orig_category":"Vorschulen, Kinderg\u00e4rten",
    "sg:phone":"+41 17308939",
    "sg:postcode":"8951",
    "sg:province":"Z\u00fcrich",
    "wof:name":"Kindergarten Fahrweid- Geroldswil",
    "wof:placetype":"venue"
},
  "geometry": {"coordinates":[8.415722847,47.4105682373],"type":"Point"}
}