{
  "type": "Feature",
  "properties": {
    "iso:country":"CH",
    "sg:address":"Via Balestra 11",
    "sg:city":"Locarno",
    "sg:orig_category":"Elektroinstallation",
    "sg:phone":"+41 22 311 40 77",
    "sg:postcode":"6600",
    "sg:province":"Ticino",
    "wof:name":"Francis Chauvet Sa",
    "wof:placetype":"venue"
},
  "geometry": {"coordinates":[6.149435997,46.2033309937],"type":"Point"}
}