{
  "type": "Feature",
  "properties": {
    "iso:country":"CH",
    "sg:address":"Lindenstr. 12",
    "sg:city":"Frauenfeld",
    "sg:orig_category":"Sonstiges Versicherungsgewerbe",
    "sg:postcode":"8500",
    "sg:province":"Thurgau",
    "wof:name":"Nordostschweizerische Pferdeversicherungsgenossenschaft.",
    "wof:placetype":"venue"
},
  "geometry": {"coordinates":[8.8956251144,47.5585861206],"type":"Point"}
}