{
  "type": "Feature",
  "properties": {
    "iso:country":"CH",
    "sg:address":"6932",
    "sg:city":"Breganzona",
    "sg:orig_category":"Herstellung von Bereifungen",
    "sg:phone":"+41 31 311 87 82",
    "sg:postcode":"6932",
    "sg:province":"Ticino",
    "wof:name":"Rts Ring Tread System (suisse) Sa",
    "wof:placetype":"venue"
},
  "geometry": {"coordinates":[8.9279298782,46.0091590881],"type":"Point"}
}