{
  "type": "Feature",
  "properties": {
    "iso:country":"CH",
    "sg:address":"Rue Du Lac 49",
    "sg:city":"Yverdon-les-bains",
    "sg:orig_category":"Detailhandel mit Bekleidung Detailhandel mit Geschenkartikeln U Souvenirs",
    "sg:phone":"+41 24 426 26 01",
    "sg:postcode":"1400",
    "sg:province":"Vaud",
    "wof:name":"Tendance Oceans F.weszeli Boutique Mode",
    "wof:placetype":"venue"
},
  "geometry": {"coordinates":[6.637979,46.780201],"type":"Point"}
}