{
  "type": "Feature",
  "properties": {
    "addr:full":"Blumenstrasse 24 Diepoldsau St. Gallen 9444",
    "addr:housenumber":"24",
    "addr:postcode":"9444",
    "addr:street":"Blumenstrasse",
    "iso:country":"CH",
    "sg:address":"Blumenstrasse 24",
    "sg:city":"Diepoldsau",
    "sg:orig_category":"Badges, Embroidered",
    "sg:phone":"+41 71 733 12 20",
    "sg:postcode":"9444",
    "sg:province":"St. Gallen",
    "wof:name":"J. Kuster-schweizer Ag",
    "wof:placetype":"venue"
},
  "geometry": {"coordinates":[9.657197,47.379726],"type":"Point"}
}