{
  "type": "Feature",
  "properties": {
    "addr:full":"M\u00fchlegasse 1 4538 Oberbipp. Postfach 50 Oberbipp Bern 4538",
    "addr:housenumber":"1;50",
    "addr:postcode":"4538;4538",
    "addr:street":"Muehlegasse;Postfach",
    "iso:country":"CH",
    "sg:address":"M\u00fchlegasse 1 4538 Oberbipp. Postfach 50",
    "sg:city":"Oberbipp",
    "sg:orig_category":"Architektur U Ingenieurb\u00fcros Architekturb\u00fcros",
    "sg:phone":"+41 32 636 24 84",
    "sg:postcode":"4538",
    "sg:province":"Bern",
    "wof:name":"Eibo Ag Architekturb\u00fcro",
    "wof:placetype":"venue"
},
  "geometry": {"coordinates":[7.659177,47.262836],"type":"Point"}
}