{
  "type": "Feature",
  "properties": {
    "iso:country":"CH",
    "sg:address":"Dorfplatz 20",
    "sg:city":"Nuglar",
    "sg:orig_category":"Pers\u00f6nliche Dienstleistungen Unterhaltung, Kultur U Sport",
    "sg:phone":"+41 76 390 12 07",
    "sg:postcode":"4412",
    "sg:province":"Solothurn",
    "wof:name":"Cliff Agard & Roli Britt Musikveranstaltungen Musik F\u00fcr Trauungen Und Andere Festlichkeiten",
    "wof:placetype":"venue"
},
  "geometry": {"coordinates":[7.692527771,47.4714241028],"type":"Point"}
}