{
  "type": "Feature",
  "properties": {
    "iso:country":"CH",
    "sg:address":"Obertswilstrasse 1",
    "sg:city":"Giffers",
    "sg:orig_category":"Fachdetailhandel mit pharmazeutischen Produkten",
    "sg:phone":"+41 26 418 18 38",
    "sg:postcode":"1735",
    "sg:province":"Fribourg",
    "wof:name":"Gipharm Ag Apotheke Giffers",
    "wof:placetype":"venue"
},
  "geometry": {"coordinates":[7.2084360123,46.7625656128],"type":"Point"}
}