{
  "type": "Feature",
  "properties": {
    "addr:full":"Bahnstrasse 25 8603 Schwerzenbach. Postfach Schwerzenbach Z\u00fcrich 8603",
    "addr:housenumber":"25",
    "addr:postcode":"8603 schwerzenbach. postfach;8603",
    "addr:street":"Bahnstrasse",
    "iso:country":"CH",
    "sg:address":"Bahnstrasse 25 8603 Schwerzenbach. Postfach",
    "sg:city":"Schwerzenbach",
    "sg:orig_category":"Architektur U Ingenieurb\u00fcros",
    "sg:phone":"+41 61 425 55 55",
    "sg:postcode":"8603",
    "sg:province":"Z\u00fcrich",
    "wof:name":"Sytek Ag",
    "wof:placetype":"venue"
},
  "geometry": {"coordinates":[7.575485,47.543324],"type":"Point"}
}