{
  "type": "Feature",
  "properties": {
    "iso:country":"CH",
    "sg:address":"Diessenhoferstrasse 23",
    "sg:city":"Tr\u00fcllikon",
    "sg:classifiers":[
        {
            "category":"Travel",
            "subcategory":"Hotels & Motels",
            "type":"Entertainment"
        }
    ],
    "sg:phone":"+41 52 319 13 17",
    "sg:postcode":"8466",
    "sg:province":"Z\u00fcrich",
    "sg:tags":[
        "hotels",
        "mit",
        "restaurant"
    ],
    "wof:name":"Hotel Hirschen",
    "wof:placetype":"venue"
},
  "geometry": {"coordinates":[8.6948213577,47.6379432678],"type":"Point"}
}