{
  "type": "Feature",
  "properties": {
    "iso:country":"CH",
    "sg:address":"Rue De Bernex 274",
    "sg:city":"Bernex",
    "sg:orig_category":"Detailhandel mit Geschenkartikeln U Souvenirs Fachdetailhandel in Verkaufsr\u00e4umen",
    "sg:phone":"+41 22 757 56 47",
    "sg:postcode":"1233",
    "sg:province":"Gen\u00e8ve",
    "wof:name":"Caprices De Bernex",
    "wof:placetype":"venue"
},
  "geometry": {"coordinates":[6.0734019279,46.1756362915],"type":"Point"}
}