{
  "type": "Feature",
  "properties": {
    "iso:country":"CH",
    "sg:address":"Avenue Du Mont-blanc 1196 Gland Case Postale 28",
    "sg:city":"Gland",
    "sg:orig_category":"Herstellung von elektrischen Lampen U Leuchten",
    "sg:phone":"+41 21 925 37 77",
    "sg:postcode":"1196",
    "sg:province":"Vaud",
    "wof:name":"Scenetec & Co S\u00e0rl",
    "wof:placetype":"venue"
},
  "geometry": {"coordinates":[5.1808700562,45.8973388672],"type":"Point"}
}