{
  "type": "Feature",
  "properties": {
    "iso:country":"CH",
    "sg:address":"Kohlenberg 13",
    "sg:city":"Basel",
    "sg:orig_category":"Unclassifiable Establishments",
    "sg:postcode":"4051",
    "sg:province":"Basel-Stadt",
    "wof:name":"Sia Media Gmbh",
    "wof:placetype":"venue"
},
  "geometry": {"coordinates":[7.5872950554,47.5549163818],"type":"Point"}
}