{
  "type": "Feature",
  "properties": {
    "iso:country":"CH",
    "sg:address":"Rue Prarreyer",
    "sg:city":"Ayer",
    "sg:orig_category":"Sportvereine Ski",
    "sg:postcode":"3961",
    "sg:province":"Valais",
    "wof:name":"Ski-club Cheminots Lausanne",
    "wof:placetype":"venue"
},
  "geometry": {"coordinates":[6.8649258614,46.4564208984],"type":"Point"}
}