{
  "type": "Feature",
  "properties": {
    "iso:country":"CH",
    "sg:address":"S. Antonio Li Curt",
    "sg:city":"Poschiavo",
    "sg:orig_category":"RESTAURANTS: TEA-ROOMS",
    "sg:postcode":"7742",
    "sg:province":"Graubunden",
    "wof:name":"Bontognali-m\u00fcller Mirta.",
    "wof:placetype":"venue"
},
  "geometry": {"coordinates":[10.0568399429,46.3265647888],"type":"Point"}
}