{
  "type": "Feature",
  "properties": {
    "iso:country":"CH",
    "sg:address":"Nelkenweg 19",
    "sg:city":"Solothurn",
    "sg:orig_category":"Sportvereine Sch\u00fctzen",
    "sg:postcode":"4500",
    "sg:province":"Solothurn",
    "wof:name":"Milit\u00e4rsch\u00fctzenges.solothurn",
    "wof:placetype":"venue"
},
  "geometry": {"coordinates":[7.5357060432,47.2157821655],"type":"Point"}
}