{
  "type": "Feature",
  "properties": {
    "iso:country":"CH",
    "sg:address":"St\u00f6cklen 13",
    "sg:city":"Meierskappel",
    "sg:orig_category":"Reparatur von Uhren U Schmuck",
    "sg:phone":"+41 41 790 24 77",
    "sg:postcode":"6344",
    "sg:province":"Luzern",
    "wof:name":"Hannes Bohnenblust Uhrenmacher",
    "wof:placetype":"venue"
},
  "geometry": {"coordinates":[8.4401512146,47.1214485168],"type":"Point"}
}