{
  "type": "Feature",
  "properties": {
    "iso:country":"CH",
    "sg:address":"Bahnhofstrasse 5",
    "sg:city":"Oberriet",
    "sg:classifiers":[
        {
            "category":"Professional",
            "subcategory":"Advertising",
            "type":"Services"
        }
    ],
    "sg:phone":"+41 71 760 05 60",
    "sg:postcode":"9463",
    "sg:province":"St. Gallen",
    "sg:tags":[
        "postcard"
    ],
    "wof:name":"Druckcenter Stieger Ag",
    "wof:placetype":"venue"
},
  "geometry": {"coordinates":[9.569303,47.324024],"type":"Point"}
}