{
  "type": "Feature",
  "properties": {
    "iso:country":"CH",
    "sg:address":"Kirchgasse",
    "sg:city":"Walenstadt",
    "sg:orig_category":"Allgemeiner Hoch U Tiefbau Hoch U Tiefbau",
    "sg:phone":"+41 81 735 19 19",
    "sg:postcode":"8880",
    "sg:province":"St. Gallen",
    "wof:name":"Heidi Tartari Bau-& Plattengesch\u00e4ft",
    "wof:placetype":"venue"
},
  "geometry": {"coordinates":[9.317264,47.126118],"type":"Point"}
}