{
  "type": "Feature",
  "properties": {
    "iso:country":"CH",
    "sg:address":"Wengen",
    "sg:city":"Lauterbrunnen",
    "sg:classifiers":[
        {
            "category":"Travel",
            "subcategory":"Hotels & Motels",
            "type":"Entertainment"
        }
    ],
    "sg:phone":"+41 33 856 69 69",
    "sg:postcode":"3822",
    "sg:province":"Bern",
    "sg:tags":[
        "hotels",
        "mit",
        "restaurant"
    ],
    "wof:name":"Hotel Wengener Hof, Zinnert-regotz Therese Und Harald",
    "wof:placetype":"venue"
},
  "geometry": {"coordinates":[7.9153552055,46.6120605469],"type":"Point"}
}