{
  "type": "Feature",
  "properties": {
    "iso:country":"CH",
    "sg:address":"Riedstrasse 21",
    "sg:city":"Bettlach",
    "sg:orig_category":"Fotografische Ateliers",
    "sg:phone":"+41 32 645 12 26",
    "sg:postcode":"2544",
    "sg:province":"Solothurn",
    "wof:name":"Ernst M\u00fcller Fotografisches Atelier",
    "wof:placetype":"venue"
},
  "geometry": {"coordinates":[7.4157748222,47.2034187317],"type":"Point"}
}