{
  "type": "Feature",
  "properties": {
    "iso:country":"CH",
    "sg:address":"Luzernerstrasse 147 6014 Littau. Postfach",
    "sg:city":"Littau",
    "sg:orig_category":"Handelsvermittlung U Grosshandel Handelsvermittlung U Grosshandel mit Automobilteilen U Zubeh\u00f6r",
    "sg:phone":"+41 41 250 48 48",
    "sg:postcode":"6014",
    "sg:province":"Luzern",
    "wof:name":"Glas Tr\u00f6sch Ag Autoglas",
    "wof:placetype":"venue"
},
  "geometry": {"coordinates":[8.2610845566,47.0491065979],"type":"Point"}
}