{
  "type": "Feature",
  "properties": {
    "iso:country":"CH",
    "sg:address":"La Serve G 14 Torgon 1895 Vionnaz. Postfach",
    "sg:city":"Torgon",
    "sg:orig_category":"Interessenvertretungen",
    "sg:postcode":"1899",
    "sg:province":"Valais",
    "wof:name":"Association Euroswiss Team",
    "wof:placetype":"venue"
},
  "geometry": {"coordinates":[6.8994240761,46.3116989136],"type":"Point"}
}