{
  "type": "Feature",
  "properties": {
    "iso:country":"CH",
    "sg:address":"Petit-moncor Route Du 6",
    "sg:city":"Villars-sur-gl\u00e2ne",
    "sg:orig_category":"Herstellung von sonstigen Nahrungsmitteln",
    "sg:phone":"+41 26 401 60 01",
    "sg:postcode":"1752",
    "sg:province":"Fribourg",
    "wof:name":"Drd Swisslion Ltd, Multinational Company For Production, Technological And Financial Engineering And Consulting",
    "wof:placetype":"venue"
},
  "geometry": {"coordinates":[7.122189045,46.8002204895],"type":"Point"}
}