{
  "type": "Feature",
  "properties": {
    "iso:country":"CH",
    "sg:address":"Linthlistrasse 9",
    "sg:city":"Oberurnen",
    "sg:classifiers":[
        {
            "category":"Building & Trades",
            "subcategory":"Cleaning & Sanitation",
            "type":"Services"
        }
    ],
    "sg:phone":"+41 55 617 20 30",
    "sg:postcode":"8868",
    "sg:province":"Glarus",
    "sg:tags":[
        "system",
        "exhaust",
        "catalytic",
        "air"
    ],
    "wof:name":"Up-to-date Umwelttechnik Ag",
    "wof:placetype":"venue"
},
  "geometry": {"coordinates":[9.063829,47.116997],"type":"Point"}
}