{
  "type": "Feature",
  "properties": {
    "iso:country":"CH",
    "sg:address":"Kirchweg 9",
    "sg:city":"Gachnang",
    "sg:orig_category":"Markt U Meinungsforschung",
    "sg:postcode":"8547",
    "sg:province":"Thurgau",
    "wof:name":"Unite Gmbh",
    "wof:placetype":"venue"
},
  "geometry": {"coordinates":[8.8495111465,47.5387191772],"type":"Point"}
}