{
  "type": "Feature",
  "properties": {
    "iso:country":"CH",
    "sg:address":"Industriestrasse 23",
    "sg:city":"Sarnen",
    "sg:classifiers":[
        {
            "category":"Food & Beverages",
            "subcategory":"Specialty",
            "type":"Retail Goods"
        }
    ],
    "sg:phone":"+41 41 660 80 20",
    "sg:postcode":"6060",
    "sg:province":"Obwalden",
    "sg:tags":[
        "caterer"
    ],
    "wof:name":"Angolo Food Ag",
    "wof:placetype":"venue"
},
  "geometry": {"coordinates":[8.251589,46.902195],"type":"Point"}
}