{
  "type": "Feature",
  "properties": {
    "iso:country":"CH",
    "sg:address":"Quai Gustave-ador 42",
    "sg:city":"Gen\u00e8ve",
    "sg:orig_category":"Herstellung U Zusammensetzung von Uhren Herstellung von Uhren",
    "sg:phone":"+41 22 731 01 06",
    "sg:postcode":"1201",
    "sg:province":"Gen\u00e8ve",
    "wof:name":"Raymond Philippe Sa",
    "wof:placetype":"venue"
},
  "geometry": {"coordinates":[6.1598157883,46.2064323425],"type":"Point"}
}