{
  "type": "Feature",
  "properties": {
    "iso:country":"CH",
    "sg:address":"Bernstrasse 4950 Huttwil. Postfach",
    "sg:city":"Huttwil",
    "sg:orig_category":"Pensionskassen",
    "sg:postcode":"4950",
    "sg:province":"Bern",
    "wof:name":"F\u00fcrsorgefonds Zu Gunsten Des Personals Der Walter Leuenberger Ag Teigwaren Und Senffabrik",
    "wof:placetype":"venue"
},
  "geometry": {"coordinates":[7.8136568069,47.0961990356],"type":"Point"}
}