{
  "type": "Feature",
  "properties": {
    "iso:country":"CH",
    "sg:address":"Stoffelweg 14.",
    "sg:city":"W\u00e4denswil",
    "sg:orig_category":"Holzplattenwerke",
    "sg:postcode":"8820",
    "sg:province":"Z\u00fcrich",
    "wof:name":"Gisler Eddy",
    "wof:placetype":"venue"
},
  "geometry": {"coordinates":[8.6610784531,47.2334442139],"type":"Point"}
}