{
  "type": "Feature",
  "properties": {
    "iso:country":"CH",
    "sg:address":"Hindelbankstrasse 10",
    "sg:city":"Sch\u00f6nb\u00fchl-urtenen",
    "sg:orig_category":"Geschenk- and Werbeartikel Grosshandel",
    "sg:phone":"+41 31 852 19 13",
    "sg:postcode":"3322",
    "sg:province":"Bern",
    "wof:name":"Otti & Partner Arbeitsschutz & Werbegeschenke",
    "wof:placetype":"venue"
},
  "geometry": {"coordinates":[7.5031380653,47.0185546875],"type":"Point"}
}