{
  "type": "Feature",
  "properties": {
    "iso:country":"CH",
    "sg:address":"Altmannsteinstrasse 35",
    "sg:city":"H\u00f6ri",
    "sg:orig_category":"Organisationen des Gesundheitswesen",
    "sg:phone":"+41 18610461",
    "sg:postcode":"8181",
    "sg:province":"Z\u00fcrich",
    "wof:name":"Samariterverein",
    "wof:placetype":"venue"
},
  "geometry": {"coordinates":[8.5170040131,47.5113105774],"type":"Point"}
}