{
  "type": "Feature",
  "properties": {
    "iso:country":"CH",
    "sg:address":"Sch\u00f6llerstrasse 2",
    "sg:city":"Derendingen",
    "sg:orig_category":"Sportvereine Ballsport Tennis",
    "sg:phone":"+41 32 682 29 92",
    "sg:postcode":"4552",
    "sg:province":"Solothurn",
    "wof:name":"Tc Derendingen",
    "wof:placetype":"venue"
},
  "geometry": {"coordinates":[7.5868787766,47.2027702332],"type":"Point"}
}