{
  "type": "Feature",
  "properties": {
    "iso:country":"CH",
    "sg:address":"Postplatz 2 9494 Schaan. Postfach 197",
    "sg:city":"Schaan",
    "sg:orig_category":"F\u00fcrsorge\u00e4mter",
    "sg:phone":"+41 75 236 72 73",
    "sg:postcode":"9494",
    "wof:name":"Amt F\u00fcr Soziale Dienste",
    "wof:placetype":"venue"
},
  "geometry": {"coordinates":[9.5083742142,47.1677856445],"type":"Point"}
}