{
  "type": "Feature",
  "properties": {
    "iso:country":"CH",
    "sg:address":"Avenue Du Midi 8",
    "sg:city":"Sion",
    "sg:orig_category":"Detailhandel mit fotografischen Artikeln Fotografisches Gewerbe U fotografische Laboratorien",
    "sg:phone":"+41 27 322 19 56",
    "sg:postcode":"1950",
    "sg:province":"Valais",
    "wof:name":"Photo G. M\u00e9trailler-borlat",
    "wof:placetype":"venue"
},
  "geometry": {"coordinates":[7.3589577675,46.2306518555],"type":"Point"}
}