{
  "type": "Feature",
  "properties": {
    "iso:country":"CH",
    "sg:address":"Weststrasse 113",
    "sg:city":"Winterthur",
    "sg:orig_category":"Vereine Abstinenten",
    "sg:phone":"+41 52 222 57 69",
    "sg:postcode":"8408",
    "sg:province":"Z\u00fcrich",
    "wof:name":"Blaues Kreuz W\u00fclflingen",
    "wof:placetype":"venue"
},
  "geometry": {"coordinates":[8.7081289291,47.5089187622],"type":"Point"}
}