{
  "type": "Feature",
  "properties": {
    "iso:country":"CH",
    "sg:address":"Via San Jorio 7",
    "sg:city":"Bellinzona",
    "sg:orig_category":"Handelsvermittlung von M\u00f6beln, Einrichtungs U Haushaltsgegenst\u00e4nden, Eisen U Metallwaren Sonstige te",
    "sg:phone":"+41 56 618 74 00",
    "sg:postcode":"6500",
    "sg:province":"Ticino",
    "wof:name":"M. Marchioni Ag",
    "wof:placetype":"venue"
},
  "geometry": {"coordinates":[8.2788333893,47.3424034119],"type":"Point"}
}