{
  "type": "Feature",
  "properties": {
    "iso:country":"CH",
    "sg:address":"Route Wilhelm-kaiser 9 1700 Fribourg. Postfach",
    "sg:city":"Fribourg",
    "sg:orig_category":"Non-Classified Establishments",
    "sg:phone":"+41 19103888",
    "sg:postcode":"1705",
    "sg:province":"Fribourg",
    "wof:name":"Particifin Ag",
    "wof:placetype":"venue"
},
  "geometry": {"coordinates":[8.5821466446,47.3174476624],"type":"Point"}
}