{
  "type": "Feature",
  "properties": {
    "iso:country":"CH",
    "sg:address":"Rosenweg 8",
    "sg:city":"Schwyz",
    "sg:orig_category":"Sonstige pers\u00f6nliche Dienstleistungen",
    "sg:postcode":"6430",
    "sg:province":"Schwyz",
    "wof:name":"Askulap Gmbh",
    "wof:placetype":"venue"
},
  "geometry": {"coordinates":[8.6529035568,47.0276298523],"type":"Point"}
}