{
  "type": "Feature",
  "properties": {
    "iso:country":"CH",
    "sg:address":"Haldenstrasse 7",
    "sg:city":"Luzern",
    "sg:orig_category":"Markt U Meinungsforschung",
    "sg:phone":"+41 62 771 80 18",
    "sg:postcode":"6003",
    "sg:province":"Luzern",
    "wof:name":"Eichenberger H.h. Marketing, Pr Und Kommunikation",
    "wof:placetype":"venue"
},
  "geometry": {"coordinates":[8.1828308105,47.251335144],"type":"Point"}
}