{
  "type": "Feature",
  "properties": {
    "iso:country":"CH",
    "sg:address":"Rue De Blanche-terre 6",
    "sg:city":"Moutier",
    "sg:classifiers":[
        {
            "category":"Insurance",
            "subcategory":"Insurance Agent",
            "type":"Services"
        }
    ],
    "sg:phone":"+41 32 493 26 93",
    "sg:postcode":"2740",
    "sg:province":"Bern",
    "sg:tags":[
        "versicherungsagenturen",
        "-broker"
    ],
    "wof:name":"Alba Assurances Agence",
    "wof:placetype":"venue"
},
  "geometry": {"coordinates":[7.3751797676,47.2765655518],"type":"Point"}
}