{
  "type": "Feature",
  "properties": {
    "iso:country":"CH",
    "sg:address":"Weitegasse",
    "sg:city":"Arbon",
    "sg:classifiers":[
        {
            "category":"Professional",
            "subcategory":"Advertising",
            "type":"Services"
        }
    ],
    "sg:phone":"+41 71 446 66 16",
    "sg:postcode":"9320",
    "sg:province":"Thurgau",
    "sg:tags":[
        "communication",
        "medium"
    ],
    "wof:name":"Risler Reklamen Ag",
    "wof:placetype":"venue"
},
  "geometry": {"coordinates":[9.436516,47.517235],"type":"Point"}
}