{
  "type": "Feature",
  "properties": {
    "iso:country":"CH",
    "sg:address":"Bahnhofstrasse 17",
    "sg:city":"Inkwil",
    "sg:orig_category":"Unternehmensberatung",
    "sg:phone":"+41 71 245 45 40",
    "sg:postcode":"3375",
    "sg:province":"Bern",
    "wof:name":"Future-cube Ag",
    "wof:placetype":"venue"
},
  "geometry": {"coordinates":[9.3815670013,47.4428215027],"type":"Point"}
}