{
  "type": "Feature",
  "properties": {
    "iso:country":"CH",
    "sg:address":"Hotel Sonnenberg",
    "sg:city":"Kriens",
    "sg:classifiers":[
        {
            "category":"Travel",
            "subcategory":"Hotels & Motels",
            "type":"Entertainment"
        }
    ],
    "sg:postcode":"6010",
    "sg:province":"Luzern",
    "sg:tags":[
        "hotels",
        "mit",
        "restaurant"
    ],
    "wof:name":"Ammann Lotti",
    "wof:placetype":"venue"
},
  "geometry": {"coordinates":[8.2931699753,47.0427284241],"type":"Point"}
}