{
  "type": "Feature",
  "properties": {
    "iso:country":"CH",
    "sg:address":"Reutistrasse 17b",
    "sg:city":"Kreuzlingen",
    "sg:classifiers":[
        {
            "category":"Military Area",
            "subcategory":"Air Force Base",
            "type":"Public Place"
        }
    ],
    "sg:phone":"+41 71 686 80 80",
    "sg:postcode":"8280",
    "sg:province":"Thurgau",
    "sg:tags":[
        "window",
        "skylight",
        "dormer"
    ],
    "wof:name":"Brack Fensterbau Ag",
    "wof:placetype":"venue"
},
  "geometry": {"coordinates":[9.1985502243,47.6422080994],"type":"Point"}
}