{
  "type": "Feature",
  "properties": {
    "iso:country":"CH",
    "sg:address":"Rain 26 5000 Aarau. Postfach",
    "sg:city":"Aarau",
    "sg:orig_category":"Betrieb U technische Hilfsdienste des Kultur U Unterhaltungswesens",
    "sg:postcode":"5004",
    "sg:province":"Aargau",
    "wof:name":"Lemon-chocolate Events Gmbh",
    "wof:placetype":"venue"
},
  "geometry": {"coordinates":[8.044013,47.390713],"type":"Point"}
}