{
  "type": "Feature",
  "properties": {
    "iso:country":"CH",
    "sg:address":"Via All'eco",
    "sg:city":"Orselina",
    "sg:orig_category":"Sonstiger Grosshandel",
    "sg:postcode":"6644",
    "sg:province":"Ticino",
    "wof:name":"Finar Sa",
    "wof:placetype":"venue"
},
  "geometry": {"coordinates":[8.7963209152,46.1794471741],"type":"Point"}
}