{
  "type": "Feature",
  "properties": {
    "iso:country":"CH",
    "sg:address":"Opfikonerstrasse 61",
    "sg:city":"Wallisellen",
    "sg:orig_category":"Grosshandel mit Getr\u00e4nken",
    "sg:postcode":"8304",
    "sg:province":"Z\u00fcrich",
    "wof:name":"Michel Perroud Sa",
    "wof:placetype":"venue"
},
  "geometry": {"coordinates":[6.6845641136,48.3388366699],"type":"Point"}
}