{
  "type": "Feature",
  "properties": {
    "iso:country":"CH",
    "sg:address":"Werdstrasse 323a",
    "sg:city":"Neuendorf",
    "sg:orig_category":"Interessenvertretungen",
    "sg:postcode":"4623",
    "sg:province":"Solothurn",
    "wof:name":"Heimatmuseum Neuendorf",
    "wof:placetype":"venue"
},
  "geometry": {"coordinates":[7.8005008698,47.3050422668],"type":"Point"}
}