{
  "type": "Feature",
  "properties": {
    "iso:country":"CH",
    "sg:address":"3935",
    "sg:city":"B\u00fcrchen",
    "sg:orig_category":"Herstellung von Konstruktionsteilen, Fertigbauteilen U Ausbauelementen aus Holz",
    "sg:postcode":"3935",
    "sg:province":"Valais",
    "wof:name":"Schreinerei Ziegler Ag",
    "wof:placetype":"venue"
},
  "geometry": {"coordinates":[8.6394348145,46.8788108826],"type":"Point"}
}