{
  "type": "Feature",
  "properties": {
    "iso:country":"CH",
    "sg:address":"Chemin Des Palettes 5",
    "sg:city":"Grand-lancy",
    "sg:classifiers":[
        {
            "category":"Restaurant",
            "type":"Food & Drink"
        }
    ],
    "sg:phone":"+41 22 794 54 58",
    "sg:postcode":"1212",
    "sg:province":"Gen\u00e8ve",
    "wof:name":"Caf\u00e9-restaurant Palettes",
    "wof:placetype":"venue"
},
  "geometry": {"coordinates":[6.1213908195,46.17552948],"type":"Point"}
}