{
  "type": "Feature",
  "properties": {
    "iso:country":"CH",
    "sg:address":"Z.i. Nord Au Glapin",
    "sg:city":"St-prex",
    "sg:orig_category":"Grosshandel mit Kaffee, Tee, Kakao U Gew\u00fcrzen Grosshandel mit elektrischen Haushaltsger\u00e4ten",
    "sg:postcode":"1162",
    "sg:province":"Vaud",
    "wof:name":"Caff\u00c8 Import Gmbh Kaffeemaschinen & Produkte",
    "wof:placetype":"venue"
},
  "geometry": {"coordinates":[8.7955217361,47.309967041],"type":"Point"}
}