{
  "type": "Feature",
  "properties": {
    "iso:country":"CH",
    "sg:address":"Rue Combe-aubert 12",
    "sg:city":"Tramelan",
    "sg:orig_category":"Erschliessung von Grundst\u00fccken",
    "sg:postcode":"2720",
    "sg:province":"Bern",
    "wof:name":"Soci\u00e9t\u00e9 Coop\u00e9rative D'habitation Les Tilleuls",
    "wof:placetype":"venue"
},
  "geometry": {"coordinates":[7.1073389053,47.2249603271],"type":"Point"}
}