{
  "type": "Feature",
  "properties": {
    "iso:country":"CH",
    "sg:address":"Bahnhofstrasse 24",
    "sg:city":"Oberwichtrach",
    "sg:orig_category":"Unclassifiable Establishments",
    "sg:postcode":"3114",
    "sg:province":"Bern",
    "wof:name":"Bahnhof-drogerie Oberwichtrach Gmbh",
    "wof:placetype":"venue"
},
  "geometry": {"coordinates":[7.576488018,46.8425064087],"type":"Point"}
}