{
  "type": "Feature",
  "properties": {
    "iso:country":"CH",
    "sg:address":"Winterthurstrasse 13 8413 Neftenbach. Postfach 124",
    "sg:city":"Neftenbach",
    "sg:orig_category":"Elektroinstallation Herstellung von Elektromotoren, Generatoren U Transformatoren",
    "sg:phone":"+41 31 839 99 00",
    "sg:postcode":"8413",
    "sg:province":"Z\u00fcrich",
    "wof:name":"A. Zeller Elektro Gmbh",
    "wof:placetype":"venue"
},
  "geometry": {"coordinates":[7.5262989998,46.9323616028],"type":"Point"}
}