{
  "type": "Feature",
  "properties": {
    "iso:country":"CH",
    "sg:address":"1782",
    "sg:city":"Formangueires",
    "sg:orig_category":"Autogaragen",
    "sg:phone":"+41 26 475 25 12",
    "sg:postcode":"1782",
    "sg:province":"Fribourg",
    "wof:name":"Joseph Audriaz R\u00e9paration D'autos",
    "wof:placetype":"venue"
},
  "geometry": {"coordinates":[7.11642,46.827019],"type":"Point"}
}