{
  "type": "Feature",
  "properties": {
    "iso:country":"CH",
    "sg:address":"Piazza Stazione 8 6600 Muralto. Postfach",
    "sg:city":"Muralto",
    "sg:orig_category":"W\u00e4scherei U chemische Reinigung",
    "sg:phone":"+41 17615860",
    "sg:postcode":"6600",
    "sg:province":"Ticino",
    "wof:name":"Silca, Luigi Basile.",
    "wof:placetype":"venue"
},
  "geometry": {"coordinates":[8.448559761,47.2771186829],"type":"Point"}
}