{
  "type": "Feature",
  "properties": {
    "iso:country":"CH",
    "sg:address":"Warpelstrasse 4",
    "sg:city":"D\u00fcdingen",
    "sg:orig_category":"Lagerh\u00e4user, G\u00fcterumschlag, Verteilzentren",
    "sg:postcode":"3186",
    "sg:province":"Fribourg",
    "wof:name":"Dowals Einstellhallen Ag",
    "wof:placetype":"venue"
},
  "geometry": {"coordinates":[7.2020468712,46.8595809937],"type":"Point"}
}