{
  "type": "Feature",
  "properties": {
    "addr:full":"Frauenfelderstr. 49 Sirnach Thurgau 8370",
    "addr:housenumber":"49",
    "addr:postcode":"8370",
    "addr:street":"Frauenfelderstr.",
    "iso:country":"CH",
    "sg:address":"Frauenfelderstr. 49",
    "sg:city":"Sirnach",
    "sg:classifiers":[
        {
            "category":"Professional",
            "subcategory":"Business Services",
            "type":"Services"
        }
    ],
    "sg:phone":"+41 71 969 40 80",
    "sg:postcode":"8370",
    "sg:province":"Thurgau",
    "sg:tags":[
        "information",
        "advice",
        "technology",
        "software"
    ],
    "wof:name":"Hefel Informatik",
    "wof:placetype":"venue"
},
  "geometry": {"coordinates":[8.998178,47.470482],"type":"Point"}
}