{
  "type": "Feature",
  "properties": {
    "iso:country":"CH",
    "sg:address":"Rue Du Stand 27",
    "sg:city":"Peseux",
    "sg:orig_category":"Grosshandel mit Schmuck Grosshandel mit Uhren",
    "sg:phone":"+41 32 730 44 80",
    "sg:postcode":"2034",
    "sg:province":"Neuch\u00e2tel",
    "wof:name":"Trigobox Sa",
    "wof:placetype":"venue"
},
  "geometry": {"coordinates":[6.8919911385,46.9912719727],"type":"Point"}
}