{
  "type": "Feature",
  "properties": {
    "iso:country":"CH",
    "sg:address":"Brunnmattweg 19",
    "sg:city":"Oberentfelden",
    "sg:orig_category":"Arztpraxen",
    "sg:phone":"+41 62 723 42 73",
    "sg:postcode":"5036",
    "sg:province":"Aargau",
    "wof:name":"Dr.med.robert Hasler Arzt F.allgemeine Medizin Fmh",
    "wof:placetype":"venue"
},
  "geometry": {"coordinates":[8.040794,47.357883],"type":"Point"}
}