{
  "type": "Feature",
  "properties": {
    "iso:country":"CH",
    "sg:address":"Chemin De L'ecluse 30",
    "sg:city":"Aigle",
    "sg:orig_category":"Bauschreinerei Herstellung von Konstruktionsteilen, Fertigbauteilen U Ausbauelementen aus Holz",
    "sg:phone":"+41 24 466 20 20",
    "sg:postcode":"1860",
    "sg:province":"Vaud",
    "wof:name":"Atout Bois Charpente Sa",
    "wof:placetype":"venue"
},
  "geometry": {"coordinates":[6.984113,46.315632],"type":"Point"}
}