{
  "type": "Feature",
  "properties": {
    "iso:country":"CH",
    "sg:address":"Haus Bella Vista 6490 Andermatt. Postfach",
    "sg:city":"Andermatt",
    "sg:orig_category":"Sonstige mit Sport verbundene T\u00e4tigkeiten",
    "sg:phone":"+41 81 936 74 74",
    "sg:postcode":"6490",
    "sg:province":"Uri",
    "wof:name":"Alpine Action Unlimited Schweizer Bergsteigerschule",
    "wof:placetype":"venue"
},
  "geometry": {"coordinates":[9.2852306366,46.8366928101],"type":"Point"}
}