{
  "type": "Feature",
  "properties": {
    "iso:country":"CH",
    "sg:address":"Via Fola 8 6963 Pregassona. Postfach",
    "sg:city":"Pregassona",
    "sg:orig_category":"Herstellung von elektronischen Bauelementen",
    "sg:postcode":"6963",
    "sg:province":"Ticino",
    "wof:name":"Diginetwork Sa",
    "wof:placetype":"venue"
},
  "geometry": {"coordinates":[8.9629182816,46.0175895691],"type":"Point"}
}