{
  "type": "Feature",
  "properties": {
    "iso:country":"CH",
    "sg:address":"S\u00e4gegasse 27",
    "sg:city":"Burgdorf",
    "sg:orig_category":"Unclassifiable Establishments",
    "sg:postcode":"3400",
    "sg:province":"Bern",
    "wof:name":"Baumann & Partner",
    "wof:placetype":"venue"
},
  "geometry": {"coordinates":[8.7385997772,47.1973800659],"type":"Point"}
}