{
  "type": "Feature",
  "properties": {
    "iso:country":"CH",
    "sg:address":"Im Tiergarten 11 8055 Z\u00fcrich. Postfach",
    "sg:city":"Z\u00fcrich",
    "sg:orig_category":"Grosshandel mit Getreide, Saatgut U Futtermitteln",
    "sg:postcode":"8055",
    "sg:province":"Z\u00fcrich",
    "wof:name":"Alb. Kuhn & Cie Kraftfutter-fabrikation, Futterhandel Usw.",
    "wof:placetype":"venue"
},
  "geometry": {"coordinates":[8.2893180847,47.3448524475],"type":"Point"}
}