{
  "type": "Feature",
  "properties": {
    "iso:country":"CH",
    "sg:address":"St Amour Mollie-margot",
    "sg:city":"Savigny",
    "sg:orig_category":"Herstellung von sonstigen Nahrungsmitteln",
    "sg:postcode":"1073",
    "sg:province":"Vaud",
    "wof:name":"Perroulaz Jean-daniel",
    "wof:placetype":"venue"
},
  "geometry": {"coordinates":[6.7467451096,46.5596923828],"type":"Point"}
}