{
  "type": "Feature",
  "properties": {
    "iso:country":"CH",
    "sg:address":"Rh\u00f4ne Rue Du 114 1204 Gen\u00e8ve. Postfach",
    "sg:city":"Gen\u00e8ve",
    "sg:orig_category":"Reiseb\u00fcros U Reiseveranstalter",
    "sg:phone":"+41 79 216 32 73",
    "sg:postcode":"1201",
    "sg:province":"Gen\u00e8ve",
    "wof:name":"Mega Travel Gmbh Reisen, Bes. Flugreisen; Vermittlung Usw",
    "wof:placetype":"venue"
},
  "geometry": {"coordinates":[9.037768364,47.4610214233],"type":"Point"}
}