{
  "type": "Feature",
  "properties": {
    "iso:country":"CH",
    "sg:address":"Bahnhofstrasse 4",
    "sg:city":"W\u00e4denswil",
    "sg:orig_category":"Vereine Harmonika and Akkordeon",
    "sg:postcode":"8820",
    "sg:province":"Z\u00fcrich",
    "wof:name":"Harmonika-club Wollishofen",
    "wof:placetype":"venue"
},
  "geometry": {"coordinates":[8.6760044098,47.2279777527],"type":"Point"}
}