{
  "type": "Feature",
  "properties": {
    "iso:country":"CH",
    "sg:address":"1180",
    "sg:city":"Rolle",
    "sg:orig_category":"Pensionskassen",
    "sg:postcode":"1180",
    "sg:province":"Vaud",
    "wof:name":"Fonds De Pr\u00e9voyance De Schenk Sa",
    "wof:placetype":"venue"
},
  "geometry": {"coordinates":[6.3380351067,46.4575614929],"type":"Point"}
}