{
  "type": "Feature",
  "properties": {
    "iso:country":"CH",
    "sg:address":"Sagab\u00f6ngertli 12",
    "sg:city":"Haldenstein",
    "sg:orig_category":"Autospenglereien",
    "sg:phone":"+41 81 353 28 18",
    "sg:postcode":"7023",
    "sg:province":"Graubunden",
    "wof:name":"Hans Panier Carrosserie",
    "wof:placetype":"venue"
},
  "geometry": {"coordinates":[9.5289,46.878693],"type":"Point"}
}