{
  "type": "Feature",
  "properties": {
    "iso:country":"CH",
    "sg:address":"Route De Montagny 87 1775 Grandsivaz. Postfach",
    "sg:city":"Grandsivaz",
    "sg:orig_category":"Maler U Glasergewerbe",
    "sg:phone":"+41 26 660 41 18",
    "sg:postcode":"1775",
    "sg:province":"Fribourg",
    "wof:name":"Art-reco, Grimm Catherine Peintre D\u00e9corateur Et Restauration",
    "wof:placetype":"venue"
},
  "geometry": {"coordinates":[6.9685840607,46.7935943604],"type":"Point"}
}