{
  "type": "Feature",
  "properties": {
    "iso:country":"CH",
    "sg:address":"Aalmattenweg 20",
    "sg:city":"Nidau",
    "sg:orig_category":"Softwareentwicklung U beratung Sonstige mit der Informatik verbundene T\u00e4tigkeiten",
    "sg:phone":"+41 32 332 97 77",
    "sg:postcode":"2560",
    "sg:province":"Bern",
    "wof:name":"Mainsoft Ag",
    "wof:placetype":"venue"
},
  "geometry": {"coordinates":[7.2439699173,47.1229515076],"type":"Point"}
}