{
  "type": "Feature",
  "properties": {
    "iso:country":"CH",
    "sg:address":"Ronchetti 18",
    "sg:city":"Orselina",
    "sg:orig_category":"Verwaltung von Immobilien",
    "sg:phone":"+41 91 743 05 91",
    "sg:postcode":"6644",
    "sg:province":"Ticino",
    "wof:name":"Iweb Gmbh",
    "wof:placetype":"venue"
},
  "geometry": {"coordinates":[8.7986249924,46.1787261963],"type":"Point"}
}