{
  "type": "Feature",
  "properties": {
    "iso:country":"CH",
    "sg:address":"Wabersackerstrasse 65",
    "sg:city":"Liebefeld",
    "sg:orig_category":"Sportvereine Sch\u00fctzen",
    "sg:postcode":"3097",
    "sg:province":"Bern",
    "wof:name":"Sch\u00fctzengesellschaft Schliern",
    "wof:placetype":"venue"
},
  "geometry": {"coordinates":[7.4231262207,46.9281845093],"type":"Point"}
}