{
  "type": "Feature",
  "properties": {
    "iso:country":"CH",
    "sg:address":"3625",
    "sg:city":"Heiligenschwendi",
    "sg:orig_category":"Wasserversorgung",
    "sg:phone":"+41 41 630 10 70",
    "sg:postcode":"3625",
    "sg:province":"Bern",
    "wof:name":"Wasserversorgung Der Gemeinde Hergiswil",
    "wof:placetype":"venue"
},
  "geometry": {"coordinates":[8.3149738312,46.9891281128],"type":"Point"}
}