{
  "type": "Feature",
  "properties": {
    "iso:country":"CH",
    "sg:address":"Brandgrubenstrasse 23",
    "sg:city":"Uster",
    "sg:orig_category":"Hardwareberatung",
    "sg:postcode":"8610",
    "sg:province":"Z\u00fcrich",
    "wof:name":"Css Computer Service Schocher",
    "wof:placetype":"venue"
},
  "geometry": {"coordinates":[8.7104043961,47.3542785645],"type":"Point"}
}