{
  "type": "Feature",
  "properties": {
    "iso:country":"CH",
    "sg:address":"M\u00e4lsner Dorf 19",
    "sg:city":"Balzers",
    "sg:orig_category":"Grosshandel mit B\u00fcromaschinen Grosshandel mit Datenverarbeitungsger\u00e4ten",
    "sg:phone":"+41 31 879 11 44",
    "sg:postcode":"9496",
    "wof:name":"Matex Telekommunikation Ag",
    "wof:placetype":"venue"
},
  "geometry": {"coordinates":[7.4085540771,47.0626831055],"type":"Point"}
}