{
  "type": "Feature",
  "properties": {
    "iso:country":"CH",
    "sg:address":"Hofurlistrasse 36",
    "sg:city":"Ennetb\u00fcrgen",
    "sg:orig_category":"Grosshandel mit Getr\u00e4nken",
    "sg:phone":"+41 22 827 69 50",
    "sg:postcode":"6373",
    "sg:province":"Nidwalden",
    "wof:name":"Eden Springs (europe) Sa",
    "wof:placetype":"venue"
},
  "geometry": {"coordinates":[6.1414251328,46.1833114624],"type":"Point"}
}