{
  "type": "Feature",
  "properties": {
    "iso:country":"CH",
    "sg:address":"Rue Du Coll\u00e8ge 33",
    "sg:city":"Nyon",
    "sg:orig_category":"Handelsschulen",
    "sg:phone":"+41 22 361 13 62",
    "sg:postcode":"1260",
    "sg:province":"Vaud",
    "wof:name":"Ecole Profess.commerciale Epcn",
    "wof:placetype":"venue"
},
  "geometry": {"coordinates":[6.2374548912,46.3812026978],"type":"Point"}
}