{
  "type": "Feature",
  "properties": {
    "iso:country":"CH",
    "sg:address":"Avenue Jean-jacques Mercier 4",
    "sg:city":"Lausanne",
    "sg:orig_category":"Aktivit\u00e4ten der Generalunternehmen im Baugewerbe Architektur U Ingenieurb\u00fcros",
    "sg:phone":"+41 21 312 22 49",
    "sg:postcode":"1003",
    "sg:province":"Vaud",
    "wof:name":"Constructions Individuelles Virchaux & Locher Ci",
    "wof:placetype":"venue"
},
  "geometry": {"coordinates":[6.629709,46.520615],"type":"Point"}
}