{
  "type": "Feature",
  "properties": {
    "iso:country":"CH",
    "sg:address":"6431 Schwyz. Postfach 510",
    "sg:city":"Schwyz",
    "sg:orig_category":"Sportvereine Ballsport Fussball",
    "sg:phone":"+41 41 811 48 21",
    "sg:postcode":"6431",
    "sg:province":"Schwyz",
    "wof:name":"Sc Schwyz",
    "wof:placetype":"venue"
},
  "geometry": {"coordinates":[8.6535100937,47.0209884644],"type":"Point"}
}