{
  "type": "Feature",
  "properties": {
    "iso:country":"CH",
    "sg:address":"Cit\u00e9-vieusseux 15",
    "sg:city":"Gen\u00e8ve",
    "sg:orig_category":"Zahntechnische Laboratorien",
    "sg:phone":"+41 55 246 31 65",
    "sg:postcode":"1203",
    "sg:province":"Gen\u00e8ve",
    "wof:name":"Mauro Ribul Zahntechnisches Labor",
    "wof:placetype":"venue"
},
  "geometry": {"coordinates":[8.9413003922,47.2884101868],"type":"Point"}
}