{
  "type": "Feature",
  "properties": {
    "iso:country":"CH",
    "sg:address":"Sumpfstrasse 26",
    "sg:city":"Zug",
    "sg:orig_category":"Sonstige Kurierdienste",
    "sg:phone":"+41 79 606 46 52",
    "sg:postcode":"6300",
    "sg:province":"Zug",
    "wof:name":"Pack-express Matthey-junod Patrick",
    "wof:placetype":"venue"
},
  "geometry": {"coordinates":[6.5703020096,46.5406684875],"type":"Point"}
}