{
  "type": "Feature",
  "properties": {
    "iso:country":"CH",
    "sg:address":"Hofackerstrasse 17 8409 Hegi (winterthur). Postfach",
    "sg:city":"Winterthur",
    "sg:orig_category":"Kauf U Verkauf von Immobilien auf eigene Rechnung",
    "sg:phone":"+41 19100396",
    "sg:postcode":"8409",
    "sg:province":"Z\u00fcrich",
    "wof:name":"Wullschleger Robert + Max",
    "wof:placetype":"venue"
},
  "geometry": {"coordinates":[8.5913486481,47.3067359924],"type":"Point"}
}