{
  "type": "Feature",
  "properties": {
    "iso:country":"CH",
    "sg:address":"Aescherstrasse 20 5615 Fahrwangen. Postfach",
    "sg:city":"Fahrwangen",
    "sg:orig_category":"Architektur U Ingenieurb\u00fcros",
    "sg:phone":"+41 56 676 62 69",
    "sg:postcode":"5615",
    "sg:province":"Aargau",
    "wof:name":"H + F Architekten Gmbh",
    "wof:placetype":"venue"
},
  "geometry": {"coordinates":[8.239773,47.293751],"type":"Point"}
}