{
  "type": "Feature",
  "properties": {
    "iso:country":"CH",
    "sg:address":"Winterthurerstrasse 10 8370 Sirnach. Postfach",
    "sg:city":"Sirnach",
    "sg:classifiers":[
        {
            "category":"Government",
            "subcategory":"Post Office",
            "type":"Public Place"
        }
    ],
    "sg:phone":"+41 52 741 22 23",
    "sg:postcode":"8370",
    "sg:province":"Thurgau",
    "sg:tags":[
        "caf\u00e9s",
        "tea-rooms"
    ],
    "wof:name":"Caf\u00e9 Krone",
    "wof:placetype":"venue"
},
  "geometry": {"coordinates":[8.8593978882,47.6592559814],"type":"Point"}
}