{
  "type": "Feature",
  "properties": {
    "iso:country":"CH",
    "sg:address":"Magdenauerstrasse 10",
    "sg:city":"Flawil",
    "sg:orig_category":"Fachdetailhandel mit pharmazeutischen Produkten",
    "sg:phone":"+41 71 393 15 69",
    "sg:postcode":"9230",
    "sg:province":"St. Gallen",
    "wof:name":"Ameisen Apotheke Ag",
    "wof:placetype":"venue"
},
  "geometry": {"coordinates":[9.1862382889,47.4128417969],"type":"Point"}
}