{
  "type": "Feature",
  "properties": {
    "iso:country":"CH",
    "sg:address":"Ch\u00f6renmattstrasse 73",
    "sg:city":"Berikon",
    "sg:orig_category":"Wirtschaftspr\u00fcfung, Steuerberatung U Treuhand",
    "sg:phone":"+41 56 633 62 26",
    "sg:postcode":"8965",
    "sg:province":"Aargau",
    "wof:name":"Certa Treuhand W. Nydegger",
    "wof:placetype":"venue"
},
  "geometry": {"coordinates":[8.3671150208,47.3570404053],"type":"Point"}
}