{
  "type": "Feature",
  "properties": {
    "iso:country":"CH",
    "sg:address":"Industriestrasse 16 4415 Lausen. Postfach",
    "sg:city":"Lausen",
    "sg:orig_category":"Einbau von Schreinerwaren Herstellung von Betonerzeugnissen f\u00fcr den Bau",
    "sg:phone":"+41 61 926 83 00",
    "sg:postcode":"4415",
    "sg:province":"Basel-Landschaft",
    "wof:name":"Wisobau Gmbh Bauelemente Im Hochbau; Handel, Montage Usw",
    "wof:placetype":"venue"
},
  "geometry": {"coordinates":[7.7585082054,47.4703559875],"type":"Point"}
}