{
  "type": "Feature",
  "properties": {
    "addr:full":"Archmattenweg 30 Grenchen Solothurn 2540",
    "addr:housenumber":"30",
    "addr:postcode":"2540",
    "addr:street":"Archmattenweg",
    "iso:country":"CH",
    "sg:address":"Archmattenweg 30",
    "sg:city":"Grenchen",
    "sg:classifiers":[
        {
            "category":"Professional",
            "subcategory":"Engineering",
            "type":"Services"
        }
    ],
    "sg:phone":"+41 31 738 84 29",
    "sg:postcode":"2540",
    "sg:province":"Solothurn",
    "sg:tags":[
        "civil",
        "underground"
    ],
    "wof:name":"Hanspeter Thurnherr Tiefbau Ag",
    "wof:placetype":"venue"
},
  "geometry": {"coordinates":[7.408615,46.784225],"type":"Point"}
}