{
  "type": "Feature",
  "properties": {
    "iso:country":"CH",
    "sg:address":"Baselstrasse 60",
    "sg:city":"Riehen",
    "sg:orig_category":"Ern\u00e4hrungsberatung",
    "sg:phone":"+41 61 641 05 02",
    "sg:postcode":"4125",
    "sg:province":"Basel-Stadt",
    "wof:name":"Marion D\u00fcrr Ern\u00e4hrungsberatung",
    "wof:placetype":"venue"
},
  "geometry": {"coordinates":[7.6503901482,47.5858039856],"type":"Point"}
}