{
  "type": "Feature",
  "properties": {
    "iso:country":"CH",
    "sg:address":"Avenue De Rumine 4",
    "sg:city":"Lausanne",
    "sg:orig_category":"Psychotherapie",
    "sg:phone":"+41 21 323 45 10",
    "sg:postcode":"1005",
    "sg:province":"Vaud",
    "wof:name":"Jan Rozmuski Psychologue-conseil",
    "wof:placetype":"venue"
},
  "geometry": {"coordinates":[6.638531208,46.5175209045],"type":"Point"}
}