{
  "type": "Feature",
  "properties": {
    "iso:country":"CH",
    "sg:address":"Gewerbestrasse 5",
    "sg:city":"Cham",
    "sg:orig_category":"Fernmeldedienste",
    "sg:phone":"+41 21 943 23 27",
    "sg:postcode":"6330",
    "sg:province":"Zug",
    "wof:name":"Tobao Sa",
    "wof:placetype":"venue"
},
  "geometry": {"coordinates":[8.7341480255,47.1973953247],"type":"Point"}
}