{
  "type": "Feature",
  "properties": {
    "iso:country":"CH",
    "sg:address":"Route Cantonale 34",
    "sg:city":"Bouveret",
    "sg:classifiers":[
        {
            "category":"Travel",
            "subcategory":"Hotels & Motels",
            "type":"Entertainment"
        }
    ],
    "sg:phone":"+41 24 481 21 26",
    "sg:postcode":"1897",
    "sg:province":"Valais",
    "sg:tags":[
        "hotels",
        "mit",
        "restaurant"
    ],
    "wof:name":"H\u00f4tel Bellevue",
    "wof:placetype":"venue"
},
  "geometry": {"coordinates":[6.8547840118,46.3830718994],"type":"Point"}
}