{
  "type": "Feature",
  "properties": {
    "iso:country":"CH",
    "sg:address":"Monte Boglia Via 23",
    "sg:city":"Lugano",
    "sg:orig_category":"Non-Classified Establishments",
    "sg:postcode":"6900",
    "sg:province":"Ticino",
    "wof:name":"Ccvi Barcelona, S.l., Barcellona, Succursale Di Lugano",
    "wof:placetype":"venue"
},
  "geometry": {"coordinates":[8.9614191055,46.0177955627],"type":"Point"}
}