{
  "type": "Feature",
  "properties": {
    "iso:country":"CH",
    "sg:address":"Route Quatre-communes",
    "sg:city":"Rolle",
    "sg:orig_category":"Grosshandel mit Getr\u00e4nken Grosshandel mit Wein U Spirituosen",
    "sg:phone":"+41 21 825 43 85",
    "sg:postcode":"1180",
    "sg:province":"Vaud",
    "wof:name":"Rauss Willy Sa",
    "wof:placetype":"venue"
},
  "geometry": {"coordinates":[6.3335299492,46.4593467712],"type":"Point"}
}