{
  "type": "Feature",
  "properties": {
    "iso:country":"CH",
    "sg:address":"Beaulieuweg 19",
    "sg:city":"Biel/bienne",
    "sg:orig_category":"Detailhandel mit fotografischen Artikeln Fotografische Ateliers",
    "sg:phone":"+41 55 240 13 60",
    "sg:postcode":"2504",
    "sg:province":"Bern",
    "wof:name":"Heinrich M\u00e4chler",
    "wof:placetype":"venue"
},
  "geometry": {"coordinates":[8.8480796814,47.2584877014],"type":"Point"}
}