{
  "type": "Feature",
  "properties": {
    "iso:country":"CH",
    "sg:address":"Kantonsstrasse",
    "sg:city":"Galgenen",
    "sg:orig_category":"Offsetdruck",
    "sg:phone":"+41 55 440 48 72",
    "sg:postcode":"8854",
    "sg:province":"Schwyz",
    "wof:name":"Bamert Druck",
    "wof:placetype":"venue"
},
  "geometry": {"coordinates":[8.8767795563,47.1817893982],"type":"Point"}
}