{
  "type": "Feature",
  "properties": {
    "iso:country":"CH",
    "sg:address":"Bahnhof-park 10",
    "sg:city":"Baar",
    "sg:orig_category":"Reinigungsgewerbe",
    "sg:postcode":"6340",
    "sg:province":"Zug",
    "wof:name":"Goddard - Clean",
    "wof:placetype":"venue"
},
  "geometry": {"coordinates":[8.5235681534,47.1960868835],"type":"Point"}
}