{
  "type": "Feature",
  "properties": {
    "iso:country":"CH",
    "sg:address":"Promenade Des Vignes",
    "sg:city":"Veyras",
    "sg:orig_category":"Herstellung von sonstigen Metallwaren Schlossereien",
    "sg:phone":"+41 27 456 13 07",
    "sg:postcode":"3968",
    "sg:province":"Valais",
    "wof:name":"St\u00e9phane Zufferey Gravure & Serrurerie",
    "wof:placetype":"venue"
},
  "geometry": {"coordinates":[7.5344772339,46.3042030334],"type":"Point"}
}