{
  "type": "Feature",
  "properties": {
    "iso:country":"CH",
    "sg:address":"Tw\u00e4rfallenstrasse 17c 6313 Finstersee. Postfach",
    "sg:city":"Finstersee",
    "sg:orig_category":"Sonstige pers\u00f6nliche Dienstleistungen",
    "sg:postcode":"6313",
    "sg:province":"Zug",
    "wof:name":"Eprox Consulting Gmbh Warenhandel. Unternehmensberatung U. Buchf\u00fchrung",
    "wof:placetype":"venue"
},
  "geometry": {"coordinates":[8.6283321381,47.1672401428],"type":"Point"}
}