{
  "type": "Feature",
  "properties": {
    "iso:country":"CH",
    "sg:address":"En Budron B",
    "sg:city":"Mont-sur-lausanne",
    "sg:orig_category":"Druckweiterverarbeitung",
    "sg:phone":"+41 21 653 21 22",
    "sg:postcode":"1052",
    "sg:province":"Vaud",
    "wof:name":"Thermo-brochage Sa",
    "wof:placetype":"venue"
},
  "geometry": {"coordinates":[6.6318187714,46.5712928772],"type":"Point"}
}