{
  "type": "Feature",
  "properties": {
    "iso:country":"CH",
    "sg:address":"Hauptstrasse 85 8840 Einsiedeln. Postfach",
    "sg:city":"Einsiedeln",
    "sg:orig_category":"Detailhandel mit B\u00fcchern, Zeitungen, Schreib U Papeteriewaren",
    "sg:postcode":"8840",
    "sg:province":"Schwyz",
    "wof:name":"Buchhandlung Benziger Ag",
    "wof:placetype":"venue"
},
  "geometry": {"coordinates":[8.749653,47.126804],"type":"Point"}
}