{
  "type": "Feature",
  "properties": {
    "iso:country":"CH",
    "sg:address":"Parkettistrasse 9",
    "sg:city":"Buochs",
    "sg:orig_category":"Fahrschulen, Flugschulen",
    "sg:phone":"+41 41 620 41 41",
    "sg:postcode":"6374",
    "sg:province":"Nidwalden",
    "wof:name":"Gody Party Autofahrschule",
    "wof:placetype":"venue"
},
  "geometry": {"coordinates":[8.4203748703,46.9765396118],"type":"Point"}
}