{
  "type": "Feature",
  "properties": {
    "iso:country":"CH",
    "sg:address":"F\u00e4rberstrasse 10",
    "sg:city":"Wollerau",
    "sg:orig_category":"Mechanik Mechanische Werkst\u00e4tten",
    "sg:phone":"+41 61 751 42 35",
    "sg:postcode":"8832",
    "sg:province":"Schwyz",
    "wof:name":"Markus Siegenthaler Schweisserei",
    "wof:placetype":"venue"
},
  "geometry": {"coordinates":[7.6046237946,47.4711761475],"type":"Point"}
}