{
  "type": "Feature",
  "properties": {
    "iso:country":"CH",
    "sg:address":"Lenzb\u00fcel 8370 Sirnach. Postfach 132",
    "sg:city":"Sirnach",
    "sg:orig_category":"Unclassifiable Establishments",
    "sg:phone":"+41 71 969 40 48",
    "sg:postcode":"8370",
    "sg:province":"Thurgau",
    "wof:name":"H\u00fcsler Ag Hemdenfabrik & Textilmaschinen",
    "wof:placetype":"venue"
},
  "geometry": {"coordinates":[9.0248403549,47.4616203308],"type":"Point"}
}