{
  "type": "Feature",
  "properties": {
    "iso:country":"CH",
    "sg:address":"Rue De Maupas 69",
    "sg:city":"Lausanne",
    "sg:orig_category":"Detailhandel mit Waren verschiedener Art, Hauptrichtung Nahrungsmittel",
    "sg:phone":"+41 22 782 75 00",
    "sg:postcode":"1004",
    "sg:province":"Vaud",
    "wof:name":"Migros Meyrin",
    "wof:placetype":"venue"
},
  "geometry": {"coordinates":[6.0827088356,46.2315216064],"type":"Point"}
}