{
  "type": "Feature",
  "properties": {
    "iso:country":"CH",
    "sg:address":"B\u00fcrgerheimstrasse 3",
    "sg:city":"Rehetobel",
    "sg:orig_category":"Softwareentwicklung U beratung",
    "sg:phone":"+41 71 877 25 43",
    "sg:postcode":"9038",
    "sg:province":"Appenzell Ausserrhoden",
    "wof:name":"Edv-software Looser",
    "wof:placetype":"venue"
},
  "geometry": {"coordinates":[9.4885864258,47.4262695312],"type":"Point"}
}