{
  "type": "Feature",
  "properties": {
    "iso:country":"CH",
    "sg:address":"Route Pont-butin 70",
    "sg:city":"Petit-lancy",
    "sg:orig_category":"Gaskets, Washers, Seals",
    "sg:phone":"+41 22 879 04 30",
    "sg:postcode":"1213",
    "sg:province":"Gen\u00e8ve",
    "wof:name":"Ardizio Toitures Sa",
    "wof:placetype":"venue"
},
  "geometry": {"coordinates":[6.1159157753,46.1866798401],"type":"Point"}
}