{
  "type": "Feature",
  "properties": {
    "iso:country":"CH",
    "sg:address":"Landstrasse 129",
    "sg:city":"Wettingen",
    "sg:classifiers":[
        {
            "category":"Food & Beverages",
            "subcategory":"Groceries & Convenience Stores",
            "type":"Retail Goods"
        }
    ],
    "sg:phone":"+41 56 427 02 25",
    "sg:postcode":"5430",
    "sg:province":"Aargau",
    "sg:tags":[
        "dietetic",
        "foodstuff"
    ],
    "wof:name":"Shark Ag",
    "wof:placetype":"venue"
},
  "geometry": {"coordinates":[8.3320579529,47.4632606506],"type":"Point"}
}