{
  "type": "Feature",
  "properties": {
    "iso:country":"CH",
    "sg:address":"Avenue Du Clo\u00eetre 1",
    "sg:city":"Aigle",
    "sg:classifiers":[
        {
            "category":"Restaurant",
            "type":"Food & Drink"
        }
    ],
    "sg:phone":"+41 24 466 24 49",
    "sg:postcode":"1860",
    "sg:province":"Vaud",
    "wof:name":"Caf\u00e9 Du Ch\u00e2teau",
    "wof:placetype":"venue"
},
  "geometry": {"coordinates":[6.970331192,46.3173675537],"type":"Point"}
}