{
  "type": "Feature",
  "properties": {
    "iso:country":"CH",
    "sg:address":"Annonciades Rue Des 9",
    "sg:city":"Porrentruy",
    "sg:orig_category":"Erwachsenenbildung U Unterricht",
    "sg:postcode":"2900",
    "sg:province":"Jura",
    "wof:name":"Chenevi\u00e8res Consulting Sa, Ccsa",
    "wof:placetype":"venue"
},
  "geometry": {"coordinates":[7.0747938156,47.4160766602],"type":"Point"}
}