{
  "type": "Feature",
  "properties": {
    "iso:country":"CH",
    "sg:address":"Alte Winterthurerstrasse 45",
    "sg:city":"Wallisellen",
    "sg:orig_category":"Fotografische Ateliers",
    "sg:phone":"+41 18300758",
    "sg:postcode":"8304",
    "sg:province":"Z\u00fcrich",
    "wof:name":"Josef Kessler Fotografisches Atelier",
    "wof:placetype":"venue"
},
  "geometry": {"coordinates":[8.590918541,47.4164733887],"type":"Point"}
}