{
  "type": "Feature",
  "properties": {
    "iso:country":"CH",
    "sg:address":"Grand-rue 56",
    "sg:city":"Montreux",
    "sg:orig_category":"Detailhandel mit Tabakwaren",
    "sg:phone":"+41 62 873 14 13",
    "sg:postcode":"1820",
    "sg:province":"Vaud",
    "wof:name":"S\u00e4uberli & Co",
    "wof:placetype":"venue"
},
  "geometry": {"coordinates":[7.9529452324,47.551109314],"type":"Point"}
}