{
  "type": "Feature",
  "properties": {
    "iso:country":"CH",
    "sg:address":"Zugerstrasse 170",
    "sg:city":"Unterlunkhofen",
    "sg:orig_category":"Electrogalvanizing Services, Contract",
    "sg:phone":"+41 56 634 15 86",
    "sg:postcode":"8918",
    "sg:province":"Aargau",
    "wof:name":"Hosta-werk Metallveredlungs Ag",
    "wof:placetype":"venue"
},
  "geometry": {"coordinates":[8.3834495544,47.3196487427],"type":"Point"}
}