{
  "type": "Feature",
  "properties": {
    "iso:country":"CH",
    "sg:address":"Bahnhofstrasse 13",
    "sg:city":"Muttenz",
    "sg:orig_category":"Reiseb\u00fcros",
    "sg:phone":"+41 61 461 00 33",
    "sg:postcode":"4132",
    "sg:province":"Basel-Landschaft",
    "wof:name":"Indah Travel",
    "wof:placetype":"venue"
},
  "geometry": {"coordinates":[7.6484618187,47.5293235779],"type":"Point"}
}