{
  "type": "Feature",
  "properties": {
    "iso:country":"CH",
    "sg:address":"Albisstrasse 2",
    "sg:city":"Mettmenstetten",
    "sg:orig_category":"Organisationen des Gesundheitswesen",
    "sg:phone":"+41 17671989",
    "sg:postcode":"8932",
    "sg:province":"Z\u00fcrich",
    "wof:name":"Gemeindekrankenpflege",
    "wof:placetype":"venue"
},
  "geometry": {"coordinates":[8.4633359909,47.2435417175],"type":"Point"}
}