{
  "type": "Feature",
  "properties": {
    "iso:country":"CH",
    "sg:address":"Rheinstrasse 81",
    "sg:city":"Pratteln",
    "sg:classifiers":[
        {
            "category":"Banks & Credit Unions",
            "subcategory":"Investment Brokerage",
            "type":"Services"
        }
    ],
    "sg:phone":"+41 61 811 24 80",
    "sg:postcode":"4133",
    "sg:province":"Basel-Landschaft",
    "sg:tags":[
        "development",
        "electronics"
    ],
    "wof:name":"G & G Technics Ag",
    "wof:placetype":"venue"
},
  "geometry": {"coordinates":[7.710791111,47.5346908569],"type":"Point"}
}