{
  "type": "Feature",
  "properties": {
    "iso:country":"CH",
    "sg:address":"Sulzstrasse 12",
    "sg:city":"Goldach",
    "sg:orig_category":"Pensionskassen",
    "sg:phone":"+41 71 844 94 44",
    "sg:postcode":"9403",
    "sg:province":"St. Gallen",
    "wof:name":"Wohlfahrtsstiftung Der Avd Goldach",
    "wof:placetype":"venue"
},
  "geometry": {"coordinates":[9.4671831131,47.4732170105],"type":"Point"}
}