{
  "type": "Feature",
  "properties": {
    "iso:country":"CH",
    "sg:address":"Im Diebis",
    "sg:city":"Stallikon",
    "sg:orig_category":"Herstellung von Metallkonstruktionen Stahl U Leichtmetallbau",
    "sg:phone":"+41 17003106",
    "sg:postcode":"8143",
    "sg:province":"Z\u00fcrich",
    "wof:name":"Binda Metallbau Ag Chemin\u00e9ebau Ofenbau",
    "wof:placetype":"venue"
},
  "geometry": {"coordinates":[8.4765319824,47.3504981995],"type":"Point"}
}