{
  "type": "Feature",
  "properties": {
    "iso:country":"CH",
    "sg:address":"Dorfstrasse 18",
    "sg:city":"Bettlach",
    "sg:orig_category":"Elektroinstallation",
    "sg:phone":"+41 32 665 50 60",
    "sg:postcode":"2544",
    "sg:province":"Solothurn",
    "wof:name":"Stuber & Heiniger Ag Elektro-anlagen/k\u00fcchen",
    "wof:placetype":"venue"
},
  "geometry": {"coordinates":[7.524810791,47.1698150635],"type":"Point"}
}