{
  "type": "Feature",
  "properties": {
    "iso:country":"CH",
    "sg:address":"Neugasse 7 6300 Zug. Postfach",
    "sg:city":"Zug",
    "sg:orig_category":"Unternehmensberatung",
    "sg:phone":"+41 62 929 40 82",
    "sg:postcode":"6300",
    "sg:province":"Zug",
    "wof:name":"Lipp Toni Projekte & Coaching",
    "wof:placetype":"venue"
},
  "geometry": {"coordinates":[7.8163490295,47.2440338135],"type":"Point"}
}