{
  "type": "Feature",
  "properties": {
    "iso:country":"CH",
    "sg:address":"Neugasse 7 6300 Zug. Postfach 519",
    "sg:city":"Zug",
    "sg:orig_category":"Finanzierungsinstitutionen Handelsvermittlung U Grosshandel",
    "sg:phone":"+41 41 712 37 30",
    "sg:postcode":"6301",
    "sg:province":"Zug",
    "wof:name":"Trendcycles.com Gmbh",
    "wof:placetype":"venue"
},
  "geometry": {"coordinates":[8.5157108307,47.1673927307],"type":"Point"}
}