{
  "type": "Feature",
  "properties": {
    "iso:country":"CH",
    "sg:address":"Diorama Rue Du 14 1204 Gen\u00e8ve. Postfach",
    "sg:city":"Gen\u00e8ve",
    "sg:orig_category":"Herstellung von Hebezeugen U F\u00f6rdermitteln",
    "sg:postcode":"1204",
    "sg:province":"Gen\u00e8ve",
    "wof:name":"Gter-groupement Pour Des Transports Express Regionaux",
    "wof:placetype":"venue"
},
  "geometry": {"coordinates":[6.138958931,46.2016639709],"type":"Point"}
}