{
  "type": "Feature",
  "properties": {
    "iso:country":"CH",
    "sg:address":"Seftigenstrasse 203",
    "sg:city":"Wabern",
    "sg:orig_category":"Arztpraxen",
    "sg:phone":"+41 31 961 12 22",
    "sg:postcode":"3084",
    "sg:province":"Bern",
    "wof:name":"Dr.med.andreas Meinerzhagen Spezialarzt Fmh",
    "wof:placetype":"venue"
},
  "geometry": {"coordinates":[7.448346,46.930244],"type":"Point"}
}