{
  "type": "Feature",
  "properties": {
    "iso:country":"CH",
    "sg:address":"Eggstrasse 39",
    "sg:city":"Oberengstringen",
    "sg:orig_category":"Interessenvertretungen U sonstige Vereinigungen",
    "sg:phone":"+41 17511072",
    "sg:postcode":"8102",
    "sg:province":"Z\u00fcrich",
    "wof:name":"Tennisvereinigung Limmattal",
    "wof:placetype":"venue"
},
  "geometry": {"coordinates":[8.4729661942,47.407371521],"type":"Point"}
}