{
  "type": "Feature",
  "properties": {
    "iso:country":"CH",
    "sg:address":"Schiesserblock Chappelen",
    "sg:city":"Elm",
    "sg:orig_category":"Unternehmensberatung",
    "sg:phone":"+41 55 642 25 80",
    "sg:postcode":"8767",
    "sg:province":"Glarus",
    "wof:name":"Pmag Prozess-management Ag",
    "wof:placetype":"venue"
},
  "geometry": {"coordinates":[9.1579761505,46.9111442566],"type":"Point"}
}