{
  "type": "Feature",
  "properties": {
    "iso:country":"CH",
    "sg:address":"M\u00fchlebachstrasse 7",
    "sg:city":"W\u00e4denswil",
    "sg:orig_category":"Sonstige mit Sport verbundene T\u00e4tigkeiten",
    "sg:phone":"+41 17807203",
    "sg:postcode":"8820",
    "sg:province":"Z\u00fcrich",
    "wof:name":"Undex Underwater Experience P. Luginb\u00fchl",
    "wof:placetype":"venue"
},
  "geometry": {"coordinates":[8.672372818,47.2236557007],"type":"Point"}
}