{
  "type": "Feature",
  "properties": {
    "iso:country":"CH",
    "sg:address":"Meuron Passage Max.- 1 2000 Neuenburg. Postfach",
    "sg:city":"Neuenburg",
    "sg:orig_category":"Unclassifiable Establishments",
    "sg:postcode":"2000",
    "sg:province":"Neuch\u00e2tel",
    "wof:name":"Mustek Trade & Finance Sa Participations Etc",
    "wof:placetype":"venue"
},
  "geometry": {"coordinates":[6.9316511154,46.9924125671],"type":"Point"}
}