{
  "type": "Feature",
  "properties": {
    "iso:country":"CH",
    "sg:address":"Langenthalstrasse 41 4912 Aarwangen. Postfach",
    "sg:city":"Aarwangen",
    "sg:orig_category":"Wirtschaftspr\u00fcfung, Steuerberatung U Treuhand",
    "sg:phone":"+41 62 922 11 88",
    "sg:postcode":"4912",
    "sg:province":"Bern",
    "wof:name":"Gerber Erich Treuhand",
    "wof:placetype":"venue"
},
  "geometry": {"coordinates":[7.7722678185,47.2366409302],"type":"Point"}
}