{
  "type": "Feature",
  "properties": {
    "iso:country":"CH",
    "sg:address":"Rue Du Puits-godet 12a",
    "sg:city":"Neuch\u00e2tel",
    "sg:orig_category":"Elektroinstallation Herstellung von Elektromotoren, Generatoren U Transformatoren",
    "sg:phone":"+41 32 727 70 70",
    "sg:postcode":"2000",
    "sg:province":"Neuch\u00e2tel",
    "wof:name":"Electrocom E+g Sa",
    "wof:placetype":"venue"
},
  "geometry": {"coordinates":[6.9125099182,46.9984054565],"type":"Point"}
}