{
  "type": "Feature",
  "properties": {
    "iso:country":"CH",
    "sg:address":"Zentralstrasse 77",
    "sg:city":"Neuhausen",
    "sg:orig_category":"Unclassifiable Establishments",
    "sg:postcode":"8212",
    "sg:province":"Schaffhausen",
    "wof:name":"Textil Shop Gmbh",
    "wof:placetype":"venue"
},
  "geometry": {"coordinates":[8.6208372116,47.6829833984],"type":"Point"}
}