{
  "type": "Feature",
  "properties": {
    "iso:country":"CH",
    "sg:address":"Glaubtenstrasse 46",
    "sg:city":"Z\u00fcrich",
    "sg:orig_category":"Reinigungsgewerbe",
    "sg:phone":"+41 18304155",
    "sg:postcode":"8046",
    "sg:province":"Z\u00fcrich",
    "wof:name":"Agz Reinigungen (allgemeine Geb\u00e4udereinigungen Z\u00fcrich) Bajrami V.",
    "wof:placetype":"venue"
},
  "geometry": {"coordinates":[8.521194458,47.4130744934],"type":"Point"}
}