{
  "type": "Feature",
  "properties": {
    "iso:country":"CH",
    "sg:address":"Sainas 139b",
    "sg:city":"Ftan",
    "sg:classifiers":[
        {
            "category":"Restaurant",
            "type":"Food & Drink"
        }
    ],
    "sg:phone":"+41 81 921 44 77",
    "sg:postcode":"7551",
    "sg:province":"Graubunden",
    "wof:name":"Ustaria Panorama",
    "wof:placetype":"venue"
},
  "geometry": {"coordinates":[9.267829895,46.8157691956],"type":"Point"}
}