{
  "type": "Feature",
  "properties": {
    "iso:country":"CH",
    "sg:address":"Fraumattweg 39",
    "sg:city":"Brislach",
    "sg:orig_category":"Wirtschaftspr\u00fcfung, Steuerberatung U Treuhand",
    "sg:phone":"+41 61 781 26 68",
    "sg:postcode":"4225",
    "sg:province":"Basel-Landschaft",
    "wof:name":"Salvatore Latino Z\u00fcrich Versicherungen",
    "wof:placetype":"venue"
},
  "geometry": {"coordinates":[7.5454921722,47.4144248962],"type":"Point"}
}