{
  "type": "Feature",
  "properties": {
    "iso:country":"CH",
    "sg:address":"Gemmo Via 11",
    "sg:city":"Lugano",
    "sg:orig_category":"Grosshandel mit Getreide, Saatgut U Futtermitteln",
    "sg:phone":"+41 21 729 97 06",
    "sg:postcode":"6900",
    "sg:province":"Ticino",
    "wof:name":"Dreifuss Claude Et Cie Sa",
    "wof:placetype":"venue"
},
  "geometry": {"coordinates":[8.9361124039,46.0086898804],"type":"Point"}
}