{
  "type": "Feature",
  "properties": {
    "iso:country":"CH",
    "sg:address":"St. Niklausstrasse 1",
    "sg:city":"Solothurn",
    "sg:orig_category":"Architektur U Ingenieurb\u00fcros",
    "sg:phone":"+41 32 621 62 60",
    "sg:postcode":"4500",
    "sg:province":"Solothurn",
    "wof:name":"Ec Chem Ag",
    "wof:placetype":"venue"
},
  "geometry": {"coordinates":[7.539312,47.211491],"type":"Point"}
}