{
  "type": "Feature",
  "properties": {
    "iso:country":"CH",
    "sg:address":"Freiestrasse 15a 8580 Amriswil. Postfach",
    "sg:city":"Amriswil",
    "sg:orig_category":"Vermietung U Verpachtung von eigenen Immobilien",
    "sg:postcode":"8580",
    "sg:province":"Thurgau",
    "wof:name":"Sr Immobilien R\u00fcdis\u00fchli Samuel",
    "wof:placetype":"venue"
},
  "geometry": {"coordinates":[9.2999267578,47.5483322144],"type":"Point"}
}