{
  "type": "Feature",
  "properties": {
    "iso:country":"CH",
    "sg:address":"Chemin De La Combe 8",
    "sg:city":"Sonceboz-sombeval",
    "sg:orig_category":"Sportvereine Ballsport Badminton",
    "sg:postcode":"2605",
    "sg:province":"Bern",
    "wof:name":"Badminton-club Sonceboz",
    "wof:placetype":"venue"
},
  "geometry": {"coordinates":[7.1822338104,47.1988334656],"type":"Point"}
}