{
  "type": "Feature",
  "properties": {
    "iso:country":"CH",
    "sg:address":"6953",
    "sg:city":"Lugaggia",
    "sg:orig_category":"Landesverteidigung, Sozialversicherung \u00d6ffentliche Verwaltung",
    "sg:phone":"+41 91 943 15 70",
    "sg:postcode":"6953",
    "sg:province":"Ticino",
    "wof:name":"Centro Di Protezione Civile Di Lugaggia",
    "wof:placetype":"venue"
},
  "geometry": {"coordinates":[8.9708499908,46.055480957],"type":"Point"}
}