{
  "type": "Feature",
  "properties": {
    "addr:full":"Avenue De La Gare 8 2114 Fleurier Case Postale 88 Fleurier Neuch\u00e2tel 2114",
    "addr:housenumber":"8;88",
    "addr:postcode":"2114;2114",
    "addr:street":"Avenue De La Gare;Case Postale;Neucha\u0302Tel",
    "iso:country":"CH",
    "sg:address":"Avenue De La Gare 8 2114 Fleurier Case Postale 88",
    "sg:city":"Fleurier",
    "sg:orig_category":"Detailhandel mit Blumen U Pflanzen",
    "sg:phone":"+41 32 861 11 54",
    "sg:postcode":"2114",
    "sg:province":"Neuch\u00e2tel",
    "wof:name":"Chabloz Fleurs",
    "wof:placetype":"venue"
},
  "geometry": {"coordinates":[6.581726,46.903282],"type":"Point"}
}