{
  "type": "Feature",
  "properties": {
    "iso:country":"CH",
    "sg:address":"Pergolastrasse 13",
    "sg:city":"W\u00fcnnewil",
    "sg:orig_category":"Allgemeiner Hoch U Tiefbau",
    "sg:phone":"+41 26 494 11 67",
    "sg:postcode":"3184",
    "sg:province":"Fribourg",
    "wof:name":"Rappo Hoch Und Tiefbau Ag",
    "wof:placetype":"venue"
},
  "geometry": {"coordinates":[7.254194,46.796497],"type":"Point"}
}