{
  "type": "Feature",
  "properties": {
    "iso:country":"CH",
    "sg:address":"Hauptstrasse 21",
    "sg:city":"Lyss",
    "sg:orig_category":"Detailhandel mit Spielwaren",
    "sg:phone":"+41 22 310 42 55",
    "sg:postcode":"3250",
    "sg:province":"Bern",
    "wof:name":"Weber Jouets Sa Magasin De Jouets Sp\u00e9cialis\u00e9",
    "wof:placetype":"venue"
},
  "geometry": {"coordinates":[6.1515002251,46.2049484253],"type":"Point"}
}