{
  "type": "Feature",
  "properties": {
    "iso:country":"CH",
    "sg:address":"Bd De Perolles 1",
    "sg:city":"Fribourg",
    "sg:classifiers":[
        {
            "category":"Banks & Credit Unions",
            "subcategory":"Bank",
            "type":"Services"
        }
    ],
    "sg:phone":"+41 37207235",
    "sg:postcode":"1700",
    "sg:province":"Fribourg",
    "wof:name":"Banque De L'etat De Fribourg",
    "wof:placetype":"venue"
},
  "geometry": {"coordinates":[7.151332,46.802055],"type":"Point"}
}