{
  "type": "Feature",
  "properties": {
    "iso:country":"CH",
    "sg:address":"Alte Schmiede 111",
    "sg:city":"Eriswil",
    "sg:orig_category":"Herstellung von Metallkonstruktionen",
    "sg:postcode":"4952",
    "sg:province":"Bern",
    "wof:name":"R\u00f6-la-montage Gmbh",
    "wof:placetype":"venue"
},
  "geometry": {"coordinates":[8.7556581497,47.3081283569],"type":"Point"}
}