{
  "type": "Feature",
  "properties": {
    "iso:country":"CH",
    "sg:address":"Obere Hauptgasse 14 3600 Thun. Postfach 1343",
    "sg:city":"Thun",
    "sg:orig_category":"Detailhandel mit Uhren U Schmuck Herstellung von sonstigen Metallwaren",
    "sg:phone":"+41 33 223 46 66",
    "sg:postcode":"3601",
    "sg:province":"Bern",
    "wof:name":"Goldschmied Ryser Gmbh",
    "wof:placetype":"venue"
},
  "geometry": {"coordinates":[7.629295826,46.7590103149],"type":"Point"}
}