{
  "type": "Feature",
  "properties": {
    "iso:country":"CH",
    "sg:address":"Birkenstrasse 111",
    "sg:city":"Widnau",
    "sg:orig_category":"Herstellung von Maschinen f\u00fcr die Textil, Bekleidungsherstellung U die Lederverarbeitung",
    "sg:phone":"+41 71 722 62 52",
    "sg:postcode":"9443",
    "sg:province":"St. Gallen",
    "wof:name":"Heule Walter Gmbh",
    "wof:placetype":"venue"
},
  "geometry": {"coordinates":[9.6391220093,47.4166221619],"type":"Point"}
}