{
  "type": "Feature",
  "properties": {
    "iso:country":"CH",
    "sg:address":"Therwilerstrasse 22",
    "sg:city":"Basel",
    "sg:orig_category":"Architektur U Ingenieurb\u00fcros Architekturb\u00fcros",
    "sg:phone":"+41 61 281 65 00",
    "sg:postcode":"4054",
    "sg:province":"Basel-Stadt",
    "wof:name":"Paul Kocher Architekturb\u00fcro",
    "wof:placetype":"venue"
},
  "geometry": {"coordinates":[7.576883,47.550476],"type":"Point"}
}