{
  "type": "Feature",
  "properties": {
    "iso:country":"CH",
    "sg:address":"Bahnhofstrasse 25",
    "sg:city":"Effretikon",
    "sg:orig_category":"Zahnarztpraxen",
    "sg:postcode":"8307",
    "sg:province":"Z\u00fcrich",
    "wof:name":"Keller Dres. Med. Dent. Anton Und Kyburz Michael Eidg. Dipl. Zahn\u00e4rzte Praxisgemeinschaft Am Rosenplatz",
    "wof:placetype":"venue"
},
  "geometry": {"coordinates":[9.0471639633,47.4655151367],"type":"Point"}
}