{
  "type": "Feature",
  "properties": {
    "iso:country":"CH",
    "sg:address":"Landammanstrasse 8",
    "sg:city":"Gersau",
    "sg:orig_category":"Non-Classified Establishments",
    "sg:postcode":"6442",
    "sg:province":"Schwyz",
    "wof:name":"Lang Wellness Und Lifestyle",
    "wof:placetype":"venue"
},
  "geometry": {"coordinates":[8.5278949738,46.993019104],"type":"Point"}
}