{
  "type": "Feature",
  "properties": {
    "iso:country":"CH",
    "sg:address":"Chemin Des M\u00e9sanges 14",
    "sg:city":"Th\u00f4nex",
    "sg:orig_category":"Advokaturb\u00fcros",
    "sg:phone":"+41 22 349 81 81",
    "sg:postcode":"1226",
    "sg:province":"Gen\u00e8ve",
    "wof:name":"Evelyne Fiechter Etude D'avocat",
    "wof:placetype":"venue"
},
  "geometry": {"coordinates":[6.204602,46.198799],"type":"Point"}
}