{
  "type": "Feature",
  "properties": {
    "iso:country":"CH",
    "sg:address":"Villardiez Chemin De 31",
    "sg:city":"Pully",
    "sg:orig_category":"Architektur U Ingenieurb\u00fcros",
    "sg:phone":"+41 21 728 68 82",
    "sg:postcode":"1009",
    "sg:province":"Vaud",
    "wof:name":"Atelier 2000 Dessins Techniques Sa",
    "wof:placetype":"venue"
},
  "geometry": {"coordinates":[6.657863,46.51609],"type":"Point"}
}