{
  "type": "Feature",
  "properties": {
    "iso:country":"CH",
    "sg:address":"Hauptstrasse 86",
    "sg:city":"Ober\u00e4geri",
    "sg:orig_category":"Mechanische Werkst\u00e4tten",
    "sg:phone":"+41 41 750 23 88",
    "sg:postcode":"6315",
    "sg:province":"Zug",
    "wof:name":"Hans Rogenmoser Mechanische Werkstatt",
    "wof:placetype":"venue"
},
  "geometry": {"coordinates":[8.6019601822,47.1374511719],"type":"Point"}
}