{
  "type": "Feature",
  "properties": {
    "iso:country":"CH",
    "sg:address":"G\u00fctschh\u00f6he 4",
    "sg:city":"Ballwil",
    "sg:orig_category":"Haltung von Schweinen",
    "sg:phone":"+41 41 448 12 43",
    "sg:postcode":"6275",
    "sg:province":"Luzern",
    "wof:name":"Walter & Niklaus Bucher Schweinezucht",
    "wof:placetype":"venue"
},
  "geometry": {"coordinates":[8.3148126602,47.15234375],"type":"Point"}
}