{
  "type": "Feature",
  "properties": {
    "iso:country":"CH",
    "sg:address":"La Petite Fin",
    "sg:city":"Longirod",
    "sg:orig_category":"Grosshandel mit Parf\u00fcmerieartikeln U K\u00f6rperpflegemitteln Herstellung von Duft U K\u00f6rperpflegemitteln",
    "sg:phone":"+41 22 368 17 44",
    "sg:postcode":"1261",
    "sg:province":"Vaud",
    "wof:name":"Kaiser Diffusion",
    "wof:placetype":"venue"
},
  "geometry": {"coordinates":[6.2589349747,46.4958000183],"type":"Point"}
}