{
  "type": "Feature",
  "properties": {
    "addr:full":"Grigione Vicosoprano Graubunden 7603",
    "addr:postcode":"7603",
    "iso:country":"CH",
    "sg:address":"Grigione",
    "sg:city":"Vicosoprano",
    "sg:classifiers":[
        {
            "category":"Banks & Credit Unions",
            "subcategory":"Bank",
            "type":"Services"
        }
    ],
    "sg:phone":"+41 41 824 11 84",
    "sg:postcode":"7603",
    "sg:province":"Graubunden",
    "wof:name":"Graub\u00fcndner Kantonalbank",
    "wof:placetype":"venue"
},
  "geometry": {"coordinates":[9.620733,46.350803],"type":"Point"}
}