{
  "type": "Feature",
  "properties": {
    "addr:full":"Sempacherstrasse 34 6003 Luzern. Postfach Luzern Luzern 6002",
    "addr:housenumber":"34",
    "addr:postcode":"6003;postfach;6002",
    "addr:street":"Sempacherstrasse",
    "iso:country":"CH",
    "sg:address":"Sempacherstrasse 34 6003 Luzern. Postfach",
    "sg:city":"Luzern",
    "sg:orig_category":"Datenverarbeitungsdienste",
    "sg:phone":"+41 41 210 73 93",
    "sg:postcode":"6002",
    "sg:province":"Luzern",
    "wof:name":"Cc-partner Commerce & Consulting Ag",
    "wof:placetype":"venue"
},
  "geometry": {"coordinates":[8.308804,47.046844],"type":"Point"}
}