{
  "type": "Feature",
  "properties": {
    "iso:country":"CH",
    "sg:address":"Steinbachstrasse 15",
    "sg:city":"Belp",
    "sg:orig_category":"Bauschreinerei Herstellung von Konstruktionsteilen, Fertigbauteilen U Ausbauelementen aus Holz",
    "sg:phone":"+41 31 819 02 37",
    "sg:postcode":"3123",
    "sg:province":"Bern",
    "wof:name":"Gilgen Kurt",
    "wof:placetype":"venue"
},
  "geometry": {"coordinates":[7.495406,46.895168],"type":"Point"}
}