{
  "type": "Feature",
  "properties": {
    "iso:country":"CH",
    "sg:address":"Strass",
    "sg:city":"Frauenfeld",
    "sg:orig_category":"Herstellung von Maschinen f\u00fcr die Nahrungsmittel, Getr\u00e4nkeherstellung U die Tabakverarbeitung",
    "sg:phone":"+41 52 720 50 70",
    "sg:postcode":"8500",
    "sg:province":"Thurgau",
    "wof:name":"Trocknungs-genossenschaft Strass B.frauenfeld",
    "wof:placetype":"venue"
},
  "geometry": {"coordinates":[8.8638896942,47.5634841919],"type":"Point"}
}