{
  "type": "Feature",
  "properties": {
    "iso:country":"CH",
    "sg:address":"2889",
    "sg:city":"Ocourt",
    "sg:classifiers":[
        {
            "category":"Travel",
            "subcategory":"Hotels & Motels",
            "type":"Entertainment"
        }
    ],
    "sg:phone":"+41 32 461 35 35",
    "sg:postcode":"2889",
    "sg:province":"Jura",
    "sg:tags":[
        "hotels",
        "mit",
        "restaurant"
    ],
    "wof:name":"H\u00f4tel Des Deux-clefs",
    "wof:placetype":"venue"
},
  "geometry": {"coordinates":[7.0775098801,47.3512840271],"type":"Point"}
}