{
  "type": "Feature",
  "properties": {
    "iso:country":"CH",
    "sg:address":"Rue Du Parc 11",
    "sg:city":"Sion",
    "sg:orig_category":"Kinderkrippen U horte",
    "sg:postcode":"1950",
    "sg:province":"Valais",
    "wof:name":"Cr\u00e8che Piroutte",
    "wof:placetype":"venue"
},
  "geometry": {"coordinates":[7.3719220161,46.2320594788],"type":"Point"}
}