{
  "type": "Feature",
  "properties": {
    "iso:country":"CH",
    "sg:address":"K\u00f6pfliweg 383",
    "sg:city":"Kestenholz",
    "sg:orig_category":"Malerei",
    "sg:phone":"+41 62 393 23 80",
    "sg:postcode":"4703",
    "sg:province":"Solothurn",
    "wof:name":"Martin Meister Malergesch\u00e4ft",
    "wof:placetype":"venue"
},
  "geometry": {"coordinates":[7.7537198067,47.2782211304],"type":"Point"}
}