{
  "type": "Feature",
  "properties": {
    "iso:country":"CH",
    "sg:address":"Z\u00fcrcherstrasse 96 8640 Rapperswil Sg. Postfach 111",
    "sg:city":"Kempraten",
    "sg:orig_category":"Grosshandel mit Datenverarbeitungsger\u00e4ten Sonstiger Grosshandel",
    "sg:phone":"+41 55 210 67 60",
    "sg:postcode":"8640",
    "sg:province":"Schwyz",
    "wof:name":"Trimpex Ag",
    "wof:placetype":"venue"
},
  "geometry": {"coordinates":[8.8183698654,47.2347145081],"type":"Point"}
}