{
  "type": "Feature",
  "properties": {
    "addr:full":"Industriestr. 26 H\u00e4gendorf Solothurn 4614",
    "addr:housenumber":"26",
    "addr:postcode":"4614",
    "addr:street":"Industriestr.;Solothurn",
    "iso:country":"CH",
    "sg:address":"Industriestr. 26",
    "sg:city":"H\u00e4gendorf",
    "sg:orig_category":"Allgemeiner Hoch U Tiefbau",
    "sg:postcode":"4614",
    "sg:province":"Solothurn",
    "wof:name":"Bau Strub R.",
    "wof:placetype":"venue"
},
  "geometry": {"coordinates":[7.835398,47.329613],"type":"Point"}
}