{
  "type": "Feature",
  "properties": {
    "iso:country":"CH",
    "sg:address":"Villa Hlo-bouil 3 3971 Chermignon. Postfach",
    "sg:city":"Chermignon",
    "sg:orig_category":"Allgemeiner Hoch U Tiefbau",
    "sg:phone":"+41 32 866 12 48",
    "sg:postcode":"3971",
    "sg:province":"Valais",
    "wof:name":"Duckert Pierre Sa, Succursale Des Verri\u00e8res",
    "wof:placetype":"venue"
},
  "geometry": {"coordinates":[6.481222,46.904362],"type":"Point"}
}