{
  "type": "Feature",
  "properties": {
    "iso:country":"CH",
    "sg:address":"R\u00f6thenbachstrasse 23",
    "sg:city":"Linden",
    "sg:orig_category":"Detailhandel mit Brot, Back U S\u00fcsswaren Detailhandel mit Waren verschiedener Art, Hauptrichtung Nahr",
    "sg:postcode":"3673",
    "sg:province":"Bern",
    "wof:name":"Marcel Balbiani",
    "wof:placetype":"venue"
},
  "geometry": {"coordinates":[7.701674,46.849392],"type":"Point"}
}