{
  "type": "Feature",
  "properties": {
    "iso:country":"CH",
    "sg:address":"Chemin Des Bains 1",
    "sg:city":"Echallens",
    "sg:orig_category":"Handelsvermittlung U Grosshandel",
    "sg:phone":"+41 21 881 33 36",
    "sg:postcode":"1040",
    "sg:province":"Vaud",
    "wof:name":"Richtal Ulrich Annen International Distribution",
    "wof:placetype":"venue"
},
  "geometry": {"coordinates":[6.6275281906,46.6429710388],"type":"Point"}
}