{
  "type": "Feature",
  "properties": {
    "iso:country":"CH",
    "sg:address":"Industriestrasse 46 8152 Glattbrugg. Postfach",
    "sg:city":"Glattbrugg",
    "sg:orig_category":"Druck ohne Zeitungsdruck",
    "sg:phone":"+41 18100515",
    "sg:postcode":"8152",
    "sg:province":"Z\u00fcrich",
    "wof:name":"Druck Atelier Hoffmann",
    "wof:placetype":"venue"
},
  "geometry": {"coordinates":[8.5552997589,47.4309387207],"type":"Point"}
}