{
  "type": "Feature",
  "properties": {
    "iso:country":"CH",
    "sg:address":"Im Lindengut 3.",
    "sg:city":"R\u00fcschlikon",
    "sg:orig_category":"Grosshandel mit Nahrungsmitteln, Getr\u00e4nken U Tabakwaren ohne ausgepr\u00e4gten Schwerpunkt",
    "sg:phone":"+41 17241218",
    "sg:postcode":"8803",
    "sg:province":"Z\u00fcrich",
    "wof:name":"Kern, Hans.",
    "wof:placetype":"venue"
},
  "geometry": {"coordinates":[8.5528831482,47.3134651184],"type":"Point"}
}