{
  "type": "Feature",
  "properties": {
    "iso:country":"CH",
    "sg:address":"Zinggenstrasse 4",
    "sg:city":"Widnau",
    "sg:orig_category":"Vereine Diverse",
    "sg:phone":"+41 79 414 47 02",
    "sg:postcode":"9443",
    "sg:province":"St. Gallen",
    "wof:name":"Verein F\u00fcr Pilzkunde",
    "wof:placetype":"venue"
},
  "geometry": {"coordinates":[9.6335172653,47.4053764343],"type":"Point"}
}