{
  "type": "Feature",
  "properties": {
    "addr:full":"Steinmattstrasse 34 3920 Zermatt. Postfach 160 Zermatt Valais 3920",
    "addr:housenumber":"34;160",
    "addr:postcode":"3920 zermatt.;3920",
    "addr:street":"Steinmattstrasse;Postfach",
    "iso:country":"CH",
    "sg:address":"Steinmattstrasse 34 3920 Zermatt. Postfach 160",
    "sg:city":"Zermatt",
    "sg:classifiers":[
        {
            "category":"Bars & Pubs",
            "type":"Food & Drink"
        }
    ],
    "sg:phone":"+41 27 967 40 40",
    "sg:postcode":"3920",
    "sg:province":"Valais",
    "wof:name":"Papperla Pub",
    "wof:placetype":"venue"
},
  "geometry": {"coordinates":[7.748668,46.018745],"type":"Point"}
}