{
  "type": "Feature",
  "properties": {
    "iso:country":"CH",
    "sg:address":"Vorstadt 55",
    "sg:city":"Schaffhausen",
    "sg:classifiers":[
        {
            "category":"Government",
            "subcategory":"Post Office",
            "type":"Public Place"
        }
    ],
    "sg:phone":"+41 52 624 59 46",
    "sg:postcode":"8200",
    "sg:province":"Schaffhausen",
    "sg:tags":[
        "caf\u00e9s",
        "tea-rooms"
    ],
    "wof:name":"Caf\u00e9 Urech Zur Burg",
    "wof:placetype":"venue"
},
  "geometry": {"coordinates":[8.6349439621,47.6992645264],"type":"Point"}
}