{
  "type": "Feature",
  "properties": {
    "iso:country":"CH",
    "sg:address":"B\u00fcchnerstrasse 28 8006 Z\u00fcrich. Postfach",
    "sg:city":"Z\u00fcrich",
    "sg:orig_category":"Ger\u00fcstbau Vermietung von Baumaschinen U ger\u00e4ten",
    "sg:phone":"+41 55 410 44 22",
    "sg:postcode":"8033",
    "sg:province":"Z\u00fcrich",
    "wof:name":"Hasler Ger\u00fcstbauunternehmung",
    "wof:placetype":"venue"
},
  "geometry": {"coordinates":[8.7688207626,47.2007064819],"type":"Point"}
}