{
  "type": "Feature",
  "properties": {
    "iso:country":"CH",
    "sg:address":"Rue De Saint-laurent 5",
    "sg:city":"Estavayer-le-lac",
    "sg:orig_category":"Konkurs- and Betreibungs\u00e4mter",
    "sg:phone":"+41 26 663 12 18",
    "sg:postcode":"1470",
    "sg:province":"Fribourg",
    "wof:name":"Office Des Poursuites",
    "wof:placetype":"venue"
},
  "geometry": {"coordinates":[6.847132206,46.8502845764],"type":"Point"}
}