{
  "type": "Feature",
  "properties": {
    "iso:country":"CH",
    "sg:address":"Lindenweg 9",
    "sg:city":"Dotzigen",
    "sg:orig_category":"Grosshandel mit landwirtschaftlichen Maschinen U Ger\u00e4ten Herstellung von Verpackungsmitteln aus Holz",
    "sg:phone":"+41 32 351 15 35",
    "sg:postcode":"3293",
    "sg:province":"Bern",
    "wof:name":"Karl Christen",
    "wof:placetype":"venue"
},
  "geometry": {"coordinates":[7.3387742043,47.1173248291],"type":"Point"}
}