{
  "type": "Feature",
  "properties": {
    "iso:country":"CH",
    "sg:address":"Poststrasse 45",
    "sg:city":"Biel/bienne",
    "sg:orig_category":"Maler U Glasergewerbe Stukkateurgewerbe, Gipserei U Verputzerei",
    "sg:phone":"+41 79 607 20 24",
    "sg:postcode":"2504",
    "sg:province":"Bern",
    "wof:name":"A. + R. Keller Gmbh",
    "wof:placetype":"venue"
},
  "geometry": {"coordinates":[7.4880418777,46.9334106445],"type":"Point"}
}