{
  "type": "Feature",
  "properties": {
    "iso:country":"CH",
    "sg:address":"Viehweidstrasse 301",
    "sg:city":"Belp",
    "sg:orig_category":"G\u00fcterbef\u00f6rderung im Strassenverkehr",
    "sg:phone":"+41 31 819 06 58",
    "sg:postcode":"3123",
    "sg:province":"Bern",
    "wof:name":"Fritz Schwab Autotransporte",
    "wof:placetype":"venue"
},
  "geometry": {"coordinates":[7.5258898735,46.8876190186],"type":"Point"}
}