{
  "type": "Feature",
  "properties": {
    "iso:country":"CH",
    "sg:address":"9604",
    "sg:city":"L\u00fctisburg",
    "sg:orig_category":"Vereine Gesang",
    "sg:postcode":"9604",
    "sg:province":"St. Gallen",
    "wof:name":"Evangelischer Kirchenchor",
    "wof:placetype":"venue"
},
  "geometry": {"coordinates":[9.0814151764,47.3948440552],"type":"Point"}
}