{
  "type": "Feature",
  "properties": {
    "addr:full":"Veia Da Mulegn Andeer Graubunden 7440",
    "addr:housenumber":"7440",
    "addr:street":"Veia",
    "iso:country":"CH",
    "sg:address":"Veia Da Mulegn",
    "sg:city":"Andeer",
    "sg:orig_category":"Bauschreinerei M\u00f6belschreinerei",
    "sg:phone":"+41 81 661 14 66",
    "sg:postcode":"7440",
    "sg:province":"Graubunden",
    "wof:name":"Georg Mani Mech.bau-& M\u00f6belschreinerei",
    "wof:placetype":"venue"
},
  "geometry": {"coordinates":[9.42409,46.603352],"type":"Point"}
}