{
  "type": "Feature",
  "properties": {
    "addr:full":"Alte Steinhauserstrasse 32 6330 Cham. Postfach 219 Cham Zug 6330",
    "addr:housenumber":"32;219",
    "addr:postcode":"6330;6330",
    "addr:street":"Alte Steinhauserstrasse;Postfach;Zug",
    "iso:country":"CH",
    "sg:address":"Alte Steinhauserstrasse 32 6330 Cham. Postfach 219",
    "sg:city":"Cham",
    "sg:orig_category":"Dachdeckerei Zimmerei, Dachdeckerei, Bauspenglerei U Abdichtung",
    "sg:phone":"+41 26 402 32 83",
    "sg:postcode":"6330",
    "sg:province":"Zug",
    "wof:name":"Gougler & Fils, Successeur Christian Gougler",
    "wof:placetype":"venue"
},
  "geometry": {"coordinates":[7.134726,46.790058],"type":"Point"}
}