{
  "type": "Feature",
  "properties": {
    "iso:country":"CH",
    "sg:address":"Flawilerstrasse 24",
    "sg:city":"Oberuzwil",
    "sg:orig_category":"D\u00e4mmung gegen K\u00e4lte, W\u00e4rme, Schall U Ersch\u00fctterung Stukkateurgewerbe, Gipserei U Verputzerei",
    "sg:phone":"+41 79 410 78 00",
    "sg:postcode":"9242",
    "sg:province":"St. Gallen",
    "wof:name":"Christian Graf Entreprise De Peinture",
    "wof:placetype":"venue"
},
  "geometry": {"coordinates":[6.8343281746,47.099445343],"type":"Point"}
}