{
  "type": "Feature",
  "properties": {
    "iso:country":"CH",
    "sg:address":"Route De Nyon 1",
    "sg:city":"Gland",
    "sg:orig_category":"Herstellung von Konstruktionsteilen, Fertigbauteilen U Ausbauelementen aus Holz",
    "sg:phone":"+41 22 364 36 03",
    "sg:postcode":"1196",
    "sg:province":"Vaud",
    "wof:name":"Gatta Carmine",
    "wof:placetype":"venue"
},
  "geometry": {"coordinates":[6.2680802345,46.4194412231],"type":"Point"}
}