{
  "type": "Feature",
  "properties": {
    "iso:country":"CH",
    "sg:address":"Herti",
    "sg:city":"Buochs",
    "sg:orig_category":"Sonstige mit der Informatik verbundene T\u00e4tigkeiten",
    "sg:phone":"+41 62 772 05 20",
    "sg:postcode":"6374",
    "sg:province":"Nidwalden",
    "wof:name":"Eichenberger Pc-schule Gmbh",
    "wof:placetype":"venue"
},
  "geometry": {"coordinates":[8.1828308105,47.251335144],"type":"Point"}
}