{
  "type": "Feature",
  "properties": {
    "iso:country":"CH",
    "sg:address":"Chamerstrasse 12",
    "sg:city":"H\u00fcnenberg",
    "sg:orig_category":"Detailhandel mit Fahrr\u00e4dern Fachdetailhandel in Verkaufsr\u00e4umen",
    "sg:phone":"+41 79 414 80 01",
    "sg:postcode":"6331",
    "sg:province":"Zug",
    "wof:name":"Bikestar Shop Veloverkauf & Service",
    "wof:placetype":"venue"
},
  "geometry": {"coordinates":[8.4272089005,47.1751022339],"type":"Point"}
}