{
  "type": "Feature",
  "properties": {
    "addr:full":"Place De La Gare Vevey Vaud 1800",
    "addr:postcode":"1800",
    "addr:street":"Place De La Gare",
    "iso:country":"CH",
    "sg:address":"Place De La Gare",
    "sg:city":"Vevey",
    "sg:classifiers":[
        {
            "category":"Banks & Credit Unions",
            "subcategory":"Bank",
            "type":"Services"
        }
    ],
    "sg:phone":"+41 21 921 13 53",
    "sg:postcode":"1800",
    "sg:province":"Vaud",
    "wof:name":"Banque Cantonale Vaudoise",
    "wof:placetype":"venue"
},
  "geometry": {"coordinates":[6.843097,46.462929],"type":"Point"}
}