{
  "type": "Feature",
  "properties": {
    "iso:country":"CH",
    "sg:address":"Floraweg 9",
    "sg:city":"Menziken",
    "sg:orig_category":"Wohnheime",
    "sg:postcode":"5737",
    "sg:province":"Aargau",
    "wof:name":"Alterssiedlung R\u00f6telirain",
    "wof:placetype":"venue"
},
  "geometry": {"coordinates":[8.1946783066,47.2422218323],"type":"Point"}
}