{
  "type": "Feature",
  "properties": {
    "iso:country":"CH",
    "sg:address":"Wildbachstrasse 18",
    "sg:city":"Winterthur",
    "sg:classifiers":[
        {
            "category":"Restaurant",
            "type":"Food & Drink"
        }
    ],
    "sg:phone":"+41 52 212 28 58",
    "sg:postcode":"8400",
    "sg:province":"Z\u00fcrich",
    "wof:name":"Restaurant L\u00f6wengarten",
    "wof:placetype":"venue"
},
  "geometry": {"coordinates":[8.7311477661,47.4960746765],"type":"Point"}
}