{
  "type": "Feature",
  "properties": {
    "iso:country":"CH",
    "sg:address":"Sch\u00f6neggstrasse 69",
    "sg:city":"Grenchen",
    "sg:orig_category":"Autogaragen",
    "sg:phone":"+41 32 652 65 55",
    "sg:postcode":"2540",
    "sg:province":"Solothurn",
    "wof:name":"Cornelius Cotting Garage",
    "wof:placetype":"venue"
},
  "geometry": {"coordinates":[7.393284,47.201534],"type":"Point"}
}