{
  "type": "Feature",
  "properties": {
    "iso:country":"CH",
    "sg:address":"Hammer",
    "sg:city":"Cham",
    "sg:orig_category":"Non-Classified Establishments",
    "sg:postcode":"6330",
    "sg:province":"Zug",
    "wof:name":"Planta C. Von & Co",
    "wof:placetype":"venue"
},
  "geometry": {"coordinates":[8.4532251358,47.1889610291],"type":"Point"}
}