{
  "type": "Feature",
  "properties": {
    "iso:country":"CH",
    "sg:address":"Sch\u00fctzenmattweg 1",
    "sg:city":"Sch\u00f6ftland",
    "sg:orig_category":"Non-Classified Establishments",
    "sg:phone":"+41 62 721 59 44",
    "sg:postcode":"5040",
    "sg:province":"Aargau",
    "wof:name":"Impro L\u00fcchinger",
    "wof:placetype":"venue"
},
  "geometry": {"coordinates":[8.0549201965,47.3032493591],"type":"Point"}
}