{
  "type": "Feature",
  "properties": {
    "addr:full":"Marktgasse 4 Thun Bern 3600",
    "addr:housenumber":"4",
    "addr:postcode":"3600",
    "addr:street":"Marktgasse;Bern",
    "iso:country":"CH",
    "sg:address":"Marktgasse 4",
    "sg:city":"Thun",
    "sg:orig_category":"Detailhandel mit Beleuchtungs U Haushaltsgegenst\u00e4nden",
    "sg:phone":"+41 33 222 10 46",
    "sg:postcode":"3600",
    "sg:province":"Bern",
    "wof:name":"Markus Herrmann Porzellanhaus",
    "wof:placetype":"venue"
},
  "geometry": {"coordinates":[7.628318,46.760666],"type":"Point"}
}