{
  "type": "Feature",
  "properties": {
    "iso:country":"CH",
    "sg:address":"Feldstrasse 6 8370 Sirnach. Postfach",
    "sg:city":"Sirnach",
    "sg:orig_category":"Herstellung von sonstigen Metallwaren Stahl U Leichtmetallbau",
    "sg:phone":"+41 41 811 33 22",
    "sg:postcode":"8370",
    "sg:province":"Thurgau",
    "wof:name":"Weber Paul Ag Eisenbau",
    "wof:placetype":"venue"
},
  "geometry": {"coordinates":[8.6342868805,47.0259666443],"type":"Point"}
}