{
  "type": "Feature",
  "properties": {
    "iso:country":"CH",
    "sg:address":"Eggstrasse 4 8907 Wettswil. Postfach 268",
    "sg:city":"Wettswil",
    "sg:orig_category":"Grosshandel mit Datenverarbeitungsger\u00e4ten Softwareentwicklung U beratung",
    "sg:phone":"+41 17001515",
    "sg:postcode":"8907",
    "sg:province":"Z\u00fcrich",
    "wof:name":"Wengi Informatik Gmbh Generalunternehmung F\u00fcr Informatik. Hardware, Netzwerke; Verkauf, Schulung, Support Usw",
    "wof:placetype":"venue"
},
  "geometry": {"coordinates":[8.4739398956,47.3394050598],"type":"Point"}
}