{
  "type": "Feature",
  "properties": {
    "iso:country":"CH",
    "sg:address":"Karl-neuhaus-strasse 21 2502 Biel/bienne Case Postale 508",
    "sg:city":"Biel/bienne",
    "sg:orig_category":"Notariate",
    "sg:phone":"+41 26 212 26 23",
    "sg:postcode":"2501",
    "sg:province":"Bern",
    "wof:name":"Michel Mooser Etude De Notaire",
    "wof:placetype":"venue"
},
  "geometry": {"coordinates":[7.0559339523,46.6169586182],"type":"Point"}
}