{
  "type": "Feature",
  "properties": {
    "iso:country":"CH",
    "sg:address":"G\u00fctschstrasse 32 8122 Binz. Postfach",
    "sg:city":"Binz",
    "sg:orig_category":"Oberfl\u00e4chenveredlung U W\u00e4rmebehandlung",
    "sg:phone":"+41 19805136",
    "sg:postcode":"8122",
    "sg:province":"Z\u00fcrich",
    "wof:name":"Incoat Gmbh Dienstleistungen U. Entwicklung U. Vertrieb Von Produkten Im Bereich Funktionale D\u00fcnnschichten",
    "wof:placetype":"venue"
},
  "geometry": {"coordinates":[8.6285324097,47.3555107117],"type":"Point"}
}