{
  "type": "Feature",
  "properties": {
    "iso:country":"CH",
    "sg:address":"Freihofstrasse 14",
    "sg:city":"Z\u00fcrich",
    "sg:orig_category":"Berufsberatungen",
    "sg:phone":"+41 22 320 86 55",
    "sg:postcode":"8048",
    "sg:province":"Z\u00fcrich",
    "wof:name":"Office D'orientation & De Formation Professionnelle",
    "wof:placetype":"venue"
},
  "geometry": {"coordinates":[6.145447,46.195721],"type":"Point"}
}