{
  "type": "Feature",
  "properties": {
    "iso:country":"CH",
    "sg:address":"Rue De La Majorie 10",
    "sg:city":"Sion",
    "sg:orig_category":"Sportvereine Ballsport Tischtennis",
    "sg:phone":"+41 27 323 28 98",
    "sg:postcode":"1950",
    "sg:province":"Valais",
    "wof:name":"Ctt Sierre",
    "wof:placetype":"venue"
},
  "geometry": {"coordinates":[7.3617610931,46.2347640991],"type":"Point"}
}