{
  "type": "Feature",
  "properties": {
    "iso:country":"CH",
    "sg:address":"Avenue De France 17",
    "sg:city":"Monthey",
    "sg:orig_category":"Herstellung von Metallkonstruktionen",
    "sg:phone":"+41 24 471 85 04",
    "sg:postcode":"1870",
    "sg:province":"Valais",
    "wof:name":"D\u00e9ly Pascal \u00ac Constructions M\u00e9talliques",
    "wof:placetype":"venue"
},
  "geometry": {"coordinates":[6.9457321167,46.254108429],"type":"Point"}
}