{
  "type": "Feature",
  "properties": {
    "iso:country":"CH",
    "sg:address":"Alte Stationsstrasse 1",
    "sg:city":"Niederweningen",
    "sg:classifiers":[
        {
            "category":"Education",
            "subcategory":"Library",
            "type":"Public Place"
        }
    ],
    "sg:phone":"+41 18750221",
    "sg:postcode":"8166",
    "sg:province":"Z\u00fcrich",
    "sg:tags":[
        "u",
        "bibliotheken",
        "archive"
    ],
    "wof:name":"Schul-& Gemeindebibliothek",
    "wof:placetype":"venue"
},
  "geometry": {"coordinates":[8.379954,47.506973],"type":"Point"}
}