{
  "type": "Feature",
  "properties": {
    "iso:country":"CH",
    "sg:address":"Technikumstrasse 84",
    "sg:city":"Winterthur",
    "sg:orig_category":"Herstellung von keramischen Haushaltswaren U Ziergegenst\u00e4nden",
    "sg:phone":"+41 52 212 03 63",
    "sg:postcode":"8400",
    "sg:province":"Z\u00fcrich",
    "wof:name":"Porzellan Klinik F. + H. Rutschmann Gmbh",
    "wof:placetype":"venue"
},
  "geometry": {"coordinates":[8.7259483337,47.4982528687],"type":"Point"}
}