{
  "type": "Feature",
  "properties": {
    "addr:full":"Marktgasse 7 Sumiswald Bern 3454",
    "addr:housenumber":"7",
    "addr:postcode":"3454",
    "addr:street":"Marktgasse",
    "iso:country":"CH",
    "sg:address":"Marktgasse 7",
    "sg:city":"Sumiswald",
    "sg:orig_category":"Detailhandel mit Blumen U Pflanzen",
    "sg:phone":"+41 34 431 14 94",
    "sg:postcode":"3454",
    "sg:province":"Bern",
    "wof:name":"Hans-rudolf Gfeller Blumen Gfeller",
    "wof:placetype":"venue"
},
  "geometry": {"coordinates":[7.746839,47.027966],"type":"Point"}
}