{
  "type": "Feature",
  "properties": {
    "iso:country":"CH",
    "sg:address":"Grindelstrasse 5 8304 Wallisellen. Postfach",
    "sg:city":"Wallisellen",
    "sg:orig_category":"Wirtschaftspr\u00fcfung, Steuerberatung U Treuhand",
    "sg:postcode":"8304",
    "sg:province":"Z\u00fcrich",
    "wof:name":"Merliansen Gmbh",
    "wof:placetype":"venue"
},
  "geometry": {"coordinates":[8.5874490738,47.4126358032],"type":"Point"}
}