{
  "type": "Feature",
  "properties": {
    "iso:country":"CH",
    "sg:address":"Niederhaslistrasse 8 8157 Dielsdorf. Postfach",
    "sg:city":"Dielsdorf",
    "sg:orig_category":"Hardwareberatung Sonstige mit der Informatik verbundene T\u00e4tigkeiten",
    "sg:phone":"+41 18854040",
    "sg:postcode":"8157",
    "sg:province":"Z\u00fcrich",
    "wof:name":"Compnet Gmbh",
    "wof:placetype":"venue"
},
  "geometry": {"coordinates":[8.4634437561,47.4828643799],"type":"Point"}
}