{
  "type": "Feature",
  "properties": {
    "addr:full":"R\u00f6thlerholzstrasse 17 R\u00fctihof Aargau 5406",
    "addr:housenumber":"17",
    "addr:postcode":"5406",
    "addr:street":"Roethlerholzstrasse",
    "iso:country":"CH",
    "sg:address":"R\u00f6thlerholzstrasse 17",
    "sg:city":"R\u00fctihof",
    "sg:classifiers":[
        {
            "category":"Real Estate",
            "subcategory":"Real Estate Agent",
            "type":"Services"
        }
    ],
    "sg:phone":"+41 56 493 16 16",
    "sg:postcode":"5406",
    "sg:province":"Aargau",
    "sg:tags":[
        "lacquer"
    ],
    "wof:name":"Reform Beizen - Lacke Ag",
    "wof:placetype":"venue"
},
  "geometry": {"coordinates":[8.27252,47.438278],"type":"Point"}
}