{
  "type": "Feature",
  "properties": {
    "iso:country":"CH",
    "sg:address":"Aufnahmezentrum Buchserb.",
    "sg:city":"Buchs",
    "sg:classifiers":[
        {
            "category":"Banks & Credit Unions",
            "subcategory":"Investment Brokerage",
            "type":"Services"
        }
    ],
    "sg:phone":"+41 81 756 10 50",
    "sg:postcode":"9470",
    "sg:province":"St. Gallen",
    "sg:tags":[
        "collector",
        "solar"
    ],
    "wof:name":"Amk-solac Systems Ag",
    "wof:placetype":"venue"
},
  "geometry": {"coordinates":[9.4716262817,47.1653633118],"type":"Point"}
}