{
  "type": "Feature",
  "properties": {
    "iso:country":"CH",
    "sg:address":"8477",
    "sg:city":"Oberstammheim",
    "sg:orig_category":"Vereine Musik/Blasmusik",
    "sg:postcode":"8477",
    "sg:province":"Z\u00fcrich",
    "wof:name":"Musikgesellschaft",
    "wof:placetype":"venue"
},
  "geometry": {"coordinates":[9.0545148849,47.1724510193],"type":"Point"}
}