{
  "type": "Feature",
  "properties": {
    "iso:country":"CH",
    "sg:address":"Quai Gustave-ador 14",
    "sg:city":"Gen\u00e8ve",
    "sg:orig_category":"Markt U Meinungsforschung",
    "sg:phone":"+41 22 786 22 58",
    "sg:postcode":"1207",
    "sg:province":"Gen\u00e8ve",
    "wof:name":"Inter Promotion & Publics Sa Conseil En Publicit\u00e9",
    "wof:placetype":"venue"
},
  "geometry": {"coordinates":[6.1566948891,46.205116272],"type":"Point"}
}