{
  "type": "Feature",
  "properties": {
    "addr:full":"Dorigny 1 Lausanne Vaud 1015",
    "addr:housenumber":"1",
    "addr:postcode":"1015",
    "addr:street":"Dorigny",
    "iso:country":"CH",
    "sg:address":"Dorigny 1",
    "sg:city":"Lausanne",
    "sg:classifiers":[
        {
            "category":"Banks & Credit Unions",
            "subcategory":"Bank",
            "type":"Services"
        }
    ],
    "sg:phone":"+41 21 691 15 01",
    "sg:postcode":"1015",
    "sg:province":"Vaud",
    "wof:name":"Banque Cantonale Vaudoise",
    "wof:placetype":"venue"
},
  "geometry": {"coordinates":[6.57934,46.520161],"type":"Point"}
}