{
  "type": "Feature",
  "properties": {
    "iso:country":"CH",
    "sg:address":"Chalet Les Souvenirs",
    "sg:city":"Val-d'illiez",
    "sg:orig_category":"Sportvereine Ballsport Tennis",
    "sg:postcode":"1873",
    "sg:province":"Valais",
    "wof:name":"Tennisclub Val De Ruz,cernier",
    "wof:placetype":"venue"
},
  "geometry": {"coordinates":[6.9260702133,47.0305709839],"type":"Point"}
}