{
  "type": "Feature",
  "properties": {
    "iso:country":"CH",
    "sg:address":"Cordulaplatz 3 5400 Baden. Postfach",
    "sg:city":"Baden",
    "sg:orig_category":"Pensionskassen",
    "sg:postcode":"5400",
    "sg:province":"Aargau",
    "wof:name":"Personalf\u00fcrsorgestiftung Der Firma Dr. A. Str\u00e4ssle Treuhand Und Revisions-ag",
    "wof:placetype":"venue"
},
  "geometry": {"coordinates":[8.3066263199,47.4721183777],"type":"Point"}
}