{
  "type": "Feature",
  "properties": {
    "iso:country":"CH",
    "sg:address":"Rue De La Tour-de-bo\u00ebl 10",
    "sg:city":"Gen\u00e8ve",
    "sg:classifiers":[
        {
            "category":"Education",
            "subcategory":"Library",
            "type":"Public Place"
        }
    ],
    "sg:phone":"+41 24 471 38 33",
    "sg:postcode":"1204",
    "sg:province":"Gen\u00e8ve",
    "sg:tags":[
        "u",
        "bibliotheken",
        "archive"
    ],
    "wof:name":"Biblioth\u00e8que Municipale",
    "wof:placetype":"venue"
},
  "geometry": {"coordinates":[6.946132,46.25248],"type":"Point"}
}