{
  "type": "Feature",
  "properties": {
    "iso:country":"CH",
    "sg:address":"General Wille-strasse 21",
    "sg:city":"Z\u00fcrich",
    "sg:orig_category":"Unclassifiable Establishments",
    "sg:phone":"+41 31 372 89 46",
    "sg:postcode":"8001",
    "sg:province":"Z\u00fcrich",
    "wof:name":"K.net Holding Ag",
    "wof:placetype":"venue"
},
  "geometry": {"coordinates":[8.5322446823,47.3635292053],"type":"Point"}
}