{
  "type": "Feature",
  "properties": {
    "iso:country":"CH",
    "sg:address":"Corso San Gottardo 32",
    "sg:city":"Chiasso",
    "sg:orig_category":"Herstellung von Schmuck, Gold U Silberschmiedwaren",
    "sg:phone":"+41 91 682 60 38",
    "sg:postcode":"6830",
    "sg:province":"Ticino",
    "wof:name":"Happy Gold Ltd",
    "wof:placetype":"venue"
},
  "geometry": {"coordinates":[9.0298786163,45.8341331482],"type":"Point"}
}