{
  "type": "Feature",
  "properties": {
    "iso:country":"CH",
    "sg:address":"Ueberlandstrasse 420",
    "sg:city":"Z\u00fcrich",
    "sg:orig_category":"Institutionen f\u00fcr Behinderte",
    "sg:phone":"+41 13212618",
    "sg:postcode":"8051",
    "sg:province":"Z\u00fcrich",
    "wof:name":"Behinda Verein Zur F\u00f6rderung Behinderter",
    "wof:placetype":"venue"
},
  "geometry": {"coordinates":[8.5911035538,47.405632019],"type":"Point"}
}