{
  "type": "Feature",
  "properties": {
    "iso:country":"CH",
    "sg:address":"Muraccio Via 5 6612 Ascona. Postfach",
    "sg:city":"Castagnola",
    "sg:orig_category":"Sonstiger Grosshandel",
    "sg:phone":"+41 91 780 50 56",
    "sg:postcode":"6976",
    "sg:province":"Ticino",
    "wof:name":"Kaussen & Oppenheimer & Partners Sa",
    "wof:placetype":"venue"
},
  "geometry": {"coordinates":[8.77348423,46.1544647217],"type":"Point"}
}