{
  "type": "Feature",
  "properties": {
    "iso:country":"CH",
    "sg:address":"St\u00e4delistrasse 18",
    "sg:city":"Goldach",
    "sg:orig_category":"Sportvereine Ballsport Tennis",
    "sg:phone":"+41 62 212 60 98",
    "sg:postcode":"9403",
    "sg:province":"St. Gallen",
    "wof:name":"Tennis-club Wangen Bei Olten",
    "wof:placetype":"venue"
},
  "geometry": {"coordinates":[7.8746628761,47.3349266052],"type":"Point"}
}