{
  "type": "Feature",
  "properties": {
    "iso:country":"CH",
    "sg:address":"Sonnenstrasse 7",
    "sg:city":"Bischofszell",
    "sg:orig_category":"Herstellung von keramischen Haushaltswaren U Ziergegenst\u00e4nden",
    "sg:phone":"+41 71 422 25 63",
    "sg:postcode":"9220",
    "sg:province":"Thurgau",
    "wof:name":"Kurt Wagner Keramikatelier",
    "wof:placetype":"venue"
},
  "geometry": {"coordinates":[9.2386693954,47.4919586182],"type":"Point"}
}