{
  "type": "Feature",
  "properties": {
    "iso:country":"CH",
    "sg:address":"Bruggerstrasse 36",
    "sg:city":"Mellingen",
    "sg:orig_category":"Wirtschaftspr\u00fcfung, Steuerberatung U Treuhand",
    "sg:phone":"+41 56 491 39 60",
    "sg:postcode":"5507",
    "sg:province":"Aargau",
    "wof:name":"Brack Margrit Treuhand",
    "wof:placetype":"venue"
},
  "geometry": {"coordinates":[8.2725248337,47.41954422],"type":"Point"}
}