{
  "type": "Feature",
  "properties": {
    "iso:country":"CH",
    "sg:address":"Dornacherstrasse 1",
    "sg:city":"Olten",
    "sg:orig_category":"Institutionen des Sozialwesens ohne Beherbergung",
    "sg:postcode":"4600",
    "sg:province":"Solothurn",
    "wof:name":"Solothurner St\u00e4dte F\u00fcr Humanit\u00e4re Hilfe",
    "wof:placetype":"venue"
},
  "geometry": {"coordinates":[7.9011821747,47.3508720398],"type":"Point"}
}