{
  "type": "Feature",
  "properties": {
    "iso:country":"CH",
    "sg:address":"Avenue De La Gare 4",
    "sg:city":"Fribourg",
    "sg:classifiers":[
        {
            "category":"Professional",
            "subcategory":"Computer Services",
            "type":"Services"
        }
    ],
    "sg:phone":"+41 26 341 74 11",
    "sg:postcode":"1700",
    "sg:province":"Fribourg",
    "sg:tags":[
        "development",
        "software"
    ],
    "wof:name":"Scia-maps Sa",
    "wof:placetype":"venue"
},
  "geometry": {"coordinates":[7.1517047882,46.8028259277],"type":"Point"}
}