{
  "type": "Feature",
  "properties": {
    "iso:country":"CH",
    "sg:address":"Avenue Du Moulin 3",
    "sg:city":"Morges",
    "sg:orig_category":"Physiotherapie",
    "sg:phone":"+41 91 827 11 87",
    "sg:postcode":"1110",
    "sg:province":"Vaud",
    "wof:name":"Selma Leenders Fisioterapia",
    "wof:placetype":"venue"
},
  "geometry": {"coordinates":[9.128364563,46.2376060486],"type":"Point"}
}