{
  "type": "Feature",
  "properties": {
    "iso:country":"CH",
    "sg:address":"R\u00e4sslerweg 1",
    "sg:city":"Z\u00fcrich",
    "sg:orig_category":"Eisenwaren Detailhandel",
    "sg:phone":"+41 13113293",
    "sg:postcode":"8057",
    "sg:province":"Z\u00fcrich",
    "wof:name":"Werner Leutenegger Werkzeuge",
    "wof:placetype":"venue"
},
  "geometry": {"coordinates":[8.5516796112,47.4030838013],"type":"Point"}
}