{
  "type": "Feature",
  "properties": {
    "iso:country":"CH",
    "sg:address":"Rosiers Chemin Des 4",
    "sg:city":"Fribourg",
    "sg:orig_category":"Unclassifiable Establishments",
    "sg:postcode":"1700",
    "sg:province":"Fribourg",
    "wof:name":"Callcom Gmbh",
    "wof:placetype":"venue"
},
  "geometry": {"coordinates":[9.1381845474,47.5666694641],"type":"Point"}
}