{
  "type": "Feature",
  "properties": {
    "addr:full":"Spitzackerstrasse Bottmingen Basel-Landschaft 4103",
    "addr:postcode":"4103",
    "addr:street":"Spitzackerstrasse",
    "iso:country":"CH",
    "sg:address":"Spitzackerstrasse",
    "sg:city":"Bottmingen",
    "sg:orig_category":"Architektur U Ingenieurb\u00fcros",
    "sg:postcode":"4103",
    "sg:province":"Basel-Landschaft",
    "wof:name":"Schmidt + Partner, Bauingenieure Ag",
    "wof:placetype":"venue"
},
  "geometry": {"coordinates":[7.576905,47.524529],"type":"Point"}
}