{
  "type": "Feature",
  "properties": {
    "iso:country":"CH",
    "sg:address":"Wisshaldenstrasse 1",
    "sg:city":"Wolfhausen",
    "sg:orig_category":"Datenverarbeitungsdienste",
    "sg:phone":"+41 19391050",
    "sg:postcode":"8633",
    "sg:province":"Z\u00fcrich",
    "wof:name":"Ingdata Edv-dienstleistungen",
    "wof:placetype":"venue"
},
  "geometry": {"coordinates":[8.80033,47.259449],"type":"Point"}
}