{
  "type": "Feature",
  "properties": {
    "iso:country":"CH",
    "sg:address":"Bahnhofstrasse 41 8880 Walenstadt. Postfach 75",
    "sg:city":"Walenstadt",
    "sg:classifiers":[
        {
            "category":"Travel",
            "subcategory":"Hotels & Motels",
            "type":"Entertainment"
        }
    ],
    "sg:phone":"+41 81 736 44 44",
    "sg:postcode":"8880",
    "sg:province":"St. Gallen",
    "sg:tags":[
        "hotels",
        "mit",
        "restaurant"
    ],
    "wof:name":"Hotel Curfirsten Ag",
    "wof:placetype":"venue"
},
  "geometry": {"coordinates":[9.3125009537,47.1203155518],"type":"Point"}
}