{
  "type": "Feature",
  "properties": {
    "iso:country":"CH",
    "sg:address":"Kaltacker 314",
    "sg:city":"Kaltacker",
    "sg:orig_category":"Grosshandel mit Getr\u00e4nken Mineralwasser Detailhandel",
    "sg:phone":"+41 34 422 41 07",
    "sg:postcode":"3413",
    "sg:province":"Bern",
    "wof:name":"Z\u00fcrcher Simon",
    "wof:placetype":"venue"
},
  "geometry": {"coordinates":[7.7180261612,47.0799827576],"type":"Point"}
}