{
  "type": "Feature",
  "properties": {
    "iso:country":"CH",
    "sg:address":"Dorfstrasse 11 5303 W\u00fcrenlingen. Postfach",
    "sg:city":"W\u00fcrenlingen",
    "sg:orig_category":"Detailhandel mit Radio U Fernsehger\u00e4ten Detailhandel mit elektrischen Haushalts-,Radio U Fernsehger\u00e4",
    "sg:phone":"+41 56 281 22 77",
    "sg:postcode":"5303",
    "sg:province":"Aargau",
    "wof:name":"U. Schneider",
    "wof:placetype":"venue"
},
  "geometry": {"coordinates":[8.2572689056,47.5317687988],"type":"Point"}
}