{
  "type": "Feature",
  "properties": {
    "iso:country":"CH",
    "sg:address":"Sonnenstrasse 4",
    "sg:city":"Kreuzlingen",
    "sg:orig_category":"Erwachsenenbildung U Unterricht",
    "sg:phone":"+41 71 671 26 20",
    "sg:postcode":"8280",
    "sg:province":"Thurgau",
    "wof:name":"Sfor Ag",
    "wof:placetype":"venue"
},
  "geometry": {"coordinates":[9.1738519669,47.6512107849],"type":"Point"}
}