{
  "type": "Feature",
  "properties": {
    "iso:country":"CH",
    "sg:address":"Route De Lo\u00ebx 151",
    "sg:city":"Bernex",
    "sg:orig_category":"Sport Bows And Arrows",
    "sg:phone":"+41 81 302 79 01",
    "sg:postcode":"1233",
    "sg:province":"Gen\u00e8ve",
    "wof:name":"Agf Gasser Ag",
    "wof:placetype":"venue"
},
  "geometry": {"coordinates":[9.5043268204,47.0118179321],"type":"Point"}
}