{
  "type": "Feature",
  "properties": {
    "iso:country":"CH",
    "sg:address":"Baslerstrasse 7",
    "sg:city":"Oftringen",
    "sg:orig_category":"Erbringung von Dienstleistungen f\u00fcr Unternehmen",
    "sg:phone":"+41 62 797 40 70",
    "sg:postcode":"4665",
    "sg:province":"Aargau",
    "wof:name":"Schriftenatelier Dis, Geyer-m\u00fcller D\u00e9sir\u00e9e",
    "wof:placetype":"venue"
},
  "geometry": {"coordinates":[7.9190359116,47.3133049011],"type":"Point"}
}