{
  "type": "Feature",
  "properties": {
    "iso:country":"CH",
    "sg:address":"Route Du Grand-torry 27",
    "sg:city":"Fribourg",
    "sg:orig_category":"Erschliessung von Grundst\u00fccken",
    "sg:postcode":"1700",
    "sg:province":"Fribourg",
    "wof:name":"Coop\u00e9rative D'habitation Des Cheminots De Fribourg",
    "wof:placetype":"venue"
},
  "geometry": {"coordinates":[7.146337986,46.8129272461],"type":"Point"}
}