{
  "type": "Feature",
  "properties": {
    "iso:country":"CH",
    "sg:address":"6216",
    "sg:city":"Mauensee",
    "sg:orig_category":"Gemeindeverwaltungen",
    "sg:phone":"+41 79 409 75 74",
    "sg:postcode":"6216",
    "sg:province":"Luzern",
    "wof:name":"Gemeindeverwaltung Mauren",
    "wof:placetype":"venue"
},
  "geometry": {"coordinates":[9.541352272,47.2190284729],"type":"Point"}
}