{
  "type": "Feature",
  "properties": {
    "iso:country":"CH",
    "sg:address":"Rue De La Plaine 84",
    "sg:city":"Yverdon-les-bains",
    "sg:classifiers":[
        {
            "category":"Restaurant",
            "type":"Food & Drink"
        }
    ],
    "sg:phone":"+41 21 791 44 75",
    "sg:postcode":"1400",
    "sg:province":"Vaud",
    "wof:name":"Caf\u00e9 Le Portillon",
    "wof:placetype":"venue"
},
  "geometry": {"coordinates":[6.7025499344,46.5161094666],"type":"Point"}
}