{
  "type": "Feature",
  "properties": {
    "iso:country":"CH",
    "sg:address":"Winterthurerstrasse 101",
    "sg:city":"Z\u00fcrich",
    "sg:orig_category":"Detailhandel mit Geschenkartikeln U Souvenirs",
    "sg:phone":"+41 13634266",
    "sg:postcode":"8006",
    "sg:province":"Z\u00fcrich",
    "wof:name":"Boutique D'art Limoges",
    "wof:placetype":"venue"
},
  "geometry": {"coordinates":[8.5448999405,47.3920936584],"type":"Point"}
}