{
  "type": "Feature",
  "properties": {
    "iso:country":"CH",
    "sg:address":"G\u00f6nhardweg 74",
    "sg:city":"Aarau",
    "sg:orig_category":"Unclassifiable Establishments",
    "sg:phone":"+41 62 822 79 13",
    "sg:postcode":"5000",
    "sg:province":"Aargau",
    "wof:name":"Lehner Gastronomie Gmbh",
    "wof:placetype":"venue"
},
  "geometry": {"coordinates":[8.0551137924,47.3820571899],"type":"Point"}
}