{
  "type": "Feature",
  "properties": {
    "iso:country":"CH",
    "sg:address":"Bergliweg 5 8304 Wallisellen. Postfach 239",
    "sg:city":"Wallisellen",
    "sg:orig_category":"Reiseb\u00fcros Vermittlung von Immobilien",
    "sg:phone":"+41 18311808",
    "sg:postcode":"8304",
    "sg:province":"Z\u00fcrich",
    "wof:name":"Polydays Gmbh",
    "wof:placetype":"venue"
},
  "geometry": {"coordinates":[8.595618248,47.4143295288],"type":"Point"}
}