{
  "type": "Feature",
  "properties": {
    "iso:country":"CH",
    "sg:address":"Rue Des Indiennes 1",
    "sg:city":"Marin-epagnier",
    "sg:orig_category":"G\u00fcterbef\u00f6rderung im Strassenverkehr",
    "sg:phone":"+41 79 240 67 53",
    "sg:postcode":"2074",
    "sg:province":"Neuch\u00e2tel",
    "wof:name":"Ignace Reina Transports",
    "wof:placetype":"venue"
},
  "geometry": {"coordinates":[6.9957618713,47.0096702576],"type":"Point"}
}