{
  "type": "Feature",
  "properties": {
    "addr:full":"Impasse Du Melley 15 Grolley Fribourg 1772",
    "addr:housenumber":"15",
    "addr:postcode":"1772",
    "addr:street":"Impasse Du Melley",
    "iso:country":"CH",
    "sg:address":"Impasse Du Melley 15",
    "sg:city":"Grolley",
    "sg:orig_category":"Architektur U Ingenieurb\u00fcros",
    "sg:phone":"+41 26 475 35 25",
    "sg:postcode":"1772",
    "sg:province":"Fribourg",
    "wof:name":"C + C Constructions Conseils S\u00e0rl",
    "wof:placetype":"venue"
},
  "geometry": {"coordinates":[7.056287,46.834785],"type":"Point"}
}