{
  "type": "Feature",
  "properties": {
    "iso:country":"CH",
    "sg:address":"Weissensteinstrasse 14",
    "sg:city":"Langendorf",
    "sg:classifiers":[
        {
            "category":"Restaurant",
            "type":"Food & Drink"
        }
    ],
    "sg:phone":"+41 32 622 20 50",
    "sg:postcode":"4513",
    "sg:province":"Solothurn",
    "wof:name":"Restaurant Witmer",
    "wof:placetype":"venue"
},
  "geometry": {"coordinates":[7.5148868561,47.2196807861],"type":"Point"}
}