{
  "type": "Feature",
  "properties": {
    "iso:country":"CH",
    "sg:address":"Chemin Des Vignes 15",
    "sg:city":"B\u00f4le",
    "sg:orig_category":"Detailhandel mit M\u00f6beln U Haushaltsgegenst\u00e4nden Detailhandel mit Teppichen",
    "sg:phone":"+41 32 842 58 91",
    "sg:postcode":"2014",
    "sg:province":"Neuch\u00e2tel",
    "wof:name":"E. Gans-ruedin Sa Tapis Boutique Orientale",
    "wof:placetype":"venue"
},
  "geometry": {"coordinates":[6.8438339233,46.9641227722],"type":"Point"}
}