{
  "type": "Feature",
  "properties": {
    "iso:country":"CH",
    "sg:address":"Postplatz 1",
    "sg:city":"Arlesheim",
    "sg:orig_category":"Physiotherapie",
    "sg:phone":"+41 61 701 94 40",
    "sg:postcode":"4144",
    "sg:province":"Basel-Landschaft",
    "wof:name":"Physiotherapie Birseck",
    "wof:placetype":"venue"
},
  "geometry": {"coordinates":[7.6192598343,47.4942207336],"type":"Point"}
}