{
  "type": "Feature",
  "properties": {
    "iso:country":"CH",
    "sg:address":"Staatsstrasse 187",
    "sg:city":"Oberriet",
    "sg:classifiers":[
        {
            "category":"Military Area",
            "subcategory":"Air Force Base",
            "type":"Public Place"
        }
    ],
    "sg:phone":"+41 71 760 02 60",
    "sg:postcode":"9463",
    "sg:province":"St. Gallen",
    "sg:tags":[
        "part",
        "deep-drawn",
        "metal"
    ],
    "wof:name":"Bruno L\u00fcchinger Ag Umformtechnik",
    "wof:placetype":"venue"
},
  "geometry": {"coordinates":[9.566667,47.323105],"type":"Point"}
}