{
  "type": "Feature",
  "properties": {
    "iso:country":"CH",
    "sg:address":"Rue Des Eaux-vives 21",
    "sg:city":"Gen\u00e8ve",
    "sg:orig_category":"Detailhandel mit M\u00f6beln",
    "sg:phone":"+41 22 786 23 71",
    "sg:postcode":"1207",
    "sg:province":"Gen\u00e8ve",
    "wof:name":"Terra-luna Luminaires",
    "wof:placetype":"venue"
},
  "geometry": {"coordinates":[6.1579270363,46.2039337158],"type":"Point"}
}