{
  "type": "Feature",
  "properties": {
    "iso:country":"CH",
    "sg:address":"Via San Gottardo 48",
    "sg:city":"Balerna",
    "sg:orig_category":"Handel mit Motorr\u00e4dern, Teilen U Zubeh\u00f6r Instandhaltung U Reparatur von Motorr\u00e4dern",
    "sg:phone":"+41 91 682 04 34",
    "sg:postcode":"6828",
    "sg:province":"Ticino",
    "wof:name":"Scooter Moto Shop Antoinette Leisinger",
    "wof:placetype":"venue"
},
  "geometry": {"coordinates":[9.0106058121,45.8444824219],"type":"Point"}
}