{
  "type": "Feature",
  "properties": {
    "iso:country":"CH",
    "sg:address":"Route De Saint-julien 295b",
    "sg:city":"Perly",
    "sg:orig_category":"Sportvereine Sch\u00fctzen",
    "sg:postcode":"1258",
    "sg:province":"Gen\u00e8ve",
    "wof:name":"Sect.de Tir Des Gymn.ge-ville",
    "wof:placetype":"venue"
},
  "geometry": {"coordinates":[6.0926351547,46.153553009],"type":"Point"}
}