{
  "type": "Feature",
  "properties": {
    "iso:country":"CH",
    "sg:address":"Via St. Abbondio 41",
    "sg:city":"Gentilino",
    "sg:orig_category":"Arztpraxen",
    "sg:phone":"+41 91 994 44 30",
    "sg:postcode":"6925",
    "sg:province":"Ticino",
    "wof:name":"Dott.med. Mauro Riavis Specialista Fmh",
    "wof:placetype":"venue"
},
  "geometry": {"coordinates":[8.933321,45.991215],"type":"Point"}
}