{
  "type": "Feature",
  "properties": {
    "addr:full":"7250 Klosters. Postfach 264 Klosters Graubunden 7250",
    "addr:housenumber":"264",
    "addr:postcode":"7250;7250",
    "addr:street":"Klosters. Postfach",
    "iso:country":"CH",
    "sg:address":"7250 Klosters. Postfach 264",
    "sg:city":"Klosters",
    "sg:orig_category":"Architekturb\u00fcros",
    "sg:phone":"+41 81 422 25 52",
    "sg:postcode":"7250",
    "sg:province":"Graubunden",
    "wof:name":"Hans Bernet Architekturb\u00fcro",
    "wof:placetype":"venue"
},
  "geometry": {"coordinates":[9.88017,46.880047],"type":"Point"}
}