{
  "type": "Feature",
  "properties": {
    "iso:country":"CH",
    "sg:address":"Schaffhauserstrasse 325",
    "sg:city":"Schleitheim",
    "sg:classifiers":[
        {
            "category":"Restaurant",
            "type":"Food & Drink"
        }
    ],
    "sg:phone":"+41 52 680 12 79",
    "sg:postcode":"8226",
    "sg:province":"Schaffhausen",
    "wof:name":"Restaurant Hohbrugg",
    "wof:placetype":"venue"
},
  "geometry": {"coordinates":[8.4888954163,47.7332420349],"type":"Point"}
}