{
  "type": "Feature",
  "properties": {
    "iso:country":"CH",
    "sg:address":"Im Lehenacker 7",
    "sg:city":"Duggingen",
    "sg:orig_category":"Verwaltung von Immobilien Wirtschaftspr\u00fcfung, Steuerberatung U Treuhand",
    "sg:phone":"+41 61 751 84 00",
    "sg:postcode":"4202",
    "sg:province":"Basel-Landschaft",
    "wof:name":"Thommen Treuhand",
    "wof:placetype":"venue"
},
  "geometry": {"coordinates":[7.6104850769,47.4527778625],"type":"Point"}
}