{
  "type": "Feature",
  "properties": {
    "iso:country":"CH",
    "sg:address":"Kasernenstrasse 9",
    "sg:city":"Liestal",
    "sg:orig_category":"Bijouterien Reparatur von Uhren U Schmuck",
    "sg:phone":"+41 81 413 53 83",
    "sg:postcode":"4410",
    "sg:province":"Basel-Landschaft",
    "wof:name":"Liliane Steinmann-st\u00e4uble Bijouterie St\u00e4uble",
    "wof:placetype":"venue"
},
  "geometry": {"coordinates":[9.822282,46.797943],"type":"Point"}
}