{
  "type": "Feature",
  "properties": {
    "iso:country":"CH",
    "sg:address":"Neugasse 42a.",
    "sg:city":"Baar",
    "sg:orig_category":"Werbung",
    "sg:postcode":"6340",
    "sg:province":"Zug",
    "wof:name":"Edaba E. Dahinden",
    "wof:placetype":"venue"
},
  "geometry": {"coordinates":[8.52085495,47.1994972229],"type":"Point"}
}