{
  "type": "Feature",
  "properties": {
    "addr:full":"Oberer Wannenrain 3 Hunzenschwil Aargau 5502",
    "addr:housenumber":"3",
    "addr:postcode":"5502",
    "addr:street":"Oberer Wannenrain",
    "iso:country":"CH",
    "sg:address":"Oberer Wannenrain 3",
    "sg:city":"Hunzenschwil",
    "sg:classifiers":[
        {
            "category":"Banks & Credit Unions",
            "subcategory":"Bank",
            "type":"Services"
        }
    ],
    "sg:phone":"+41 4164472667",
    "sg:postcode":"5502",
    "sg:province":"Aargau",
    "wof:name":"Neue Aargauer Bank",
    "wof:placetype":"venue"
},
  "geometry": {"coordinates":[8.127837,47.383671],"type":"Point"}
}