{
  "type": "Feature",
  "properties": {
    "iso:country":"CH",
    "sg:address":"Neuackerstrasse 34 8125 Zollikerberg. Postfach",
    "sg:city":"Zollikerberg",
    "sg:orig_category":"Handels-H\u00e4user U Gesellschaften",
    "sg:phone":"+41 13916909",
    "sg:postcode":"8125",
    "sg:province":"Z\u00fcrich",
    "wof:name":"Moon Wave Gmbh",
    "wof:placetype":"venue"
},
  "geometry": {"coordinates":[8.5971679688,47.3464202881],"type":"Point"}
}