{
  "type": "Feature",
  "properties": {
    "iso:country":"CH",
    "sg:address":"8890",
    "sg:city":"Flums",
    "sg:orig_category":"Sportvereine Sch\u00fctzen Pistolen-& Gewehr",
    "sg:postcode":"8890",
    "sg:province":"St. Gallen",
    "wof:name":"Pistolensch\u00fctzenverein",
    "wof:placetype":"venue"
},
  "geometry": {"coordinates":[9.3476495743,47.0880584717],"type":"Point"}
}