{
  "type": "Feature",
  "properties": {
    "addr:full":"Rue Baptiste-savoye 48 St-imier Bern 2610",
    "addr:housenumber":"48",
    "addr:postcode":"2610",
    "addr:street":"Rue Baptiste-Savoye",
    "iso:country":"CH",
    "sg:address":"Rue Baptiste-savoye 48",
    "sg:city":"St-imier",
    "sg:orig_category":"Datenverarbeitungsdienste Unternehmensberatung",
    "sg:phone":"+41 32 942 88 00",
    "sg:postcode":"2610",
    "sg:province":"Bern",
    "wof:name":"Nrj Management Sa",
    "wof:placetype":"venue"
},
  "geometry": {"coordinates":[6.993887,47.150906],"type":"Point"}
}