{
  "type": "Feature",
  "properties": {
    "iso:country":"CH",
    "sg:address":"Rest. R\u00f6ssli",
    "sg:city":"Zollbr\u00fcck",
    "sg:orig_category":"Detailhandel mit Fleisch U Fleischwaren",
    "sg:postcode":"3436",
    "sg:province":"Bern",
    "wof:name":"Steiner & Co.",
    "wof:placetype":"venue"
},
  "geometry": {"coordinates":[7.7408971786,46.9739875793],"type":"Point"}
}