{
  "type": "Feature",
  "properties": {
    "iso:country":"CH",
    "sg:address":"Gartenstrasse 31",
    "sg:city":"Adliswil",
    "sg:orig_category":"Wirtschaftspr\u00fcfung, Steuerberatung U Treuhand",
    "sg:postcode":"8134",
    "sg:province":"Z\u00fcrich",
    "wof:name":"Treuhandb\u00fcro Wolfgang Rau",
    "wof:placetype":"venue"
},
  "geometry": {"coordinates":[7.8035287857,47.0474357605],"type":"Point"}
}