{
  "type": "Feature",
  "properties": {
    "iso:country":"CH",
    "sg:address":"Grabenstrasse 3",
    "sg:city":"Schlieren",
    "sg:orig_category":"Handelsvermittlung U Grosshandel mit Automobilen Instandhaltung U Reparatur von Automobilen",
    "sg:phone":"+41 14406080",
    "sg:postcode":"8952",
    "sg:province":"Z\u00fcrich",
    "wof:name":"Line Trading Export Gmbh",
    "wof:placetype":"venue"
},
  "geometry": {"coordinates":[8.4511060715,47.3992538452],"type":"Point"}
}