{
  "type": "Feature",
  "properties": {
    "iso:country":"CH",
    "sg:address":"Levant Chemin Du 2",
    "sg:city":"Aigle",
    "sg:orig_category":"Non-Classified Establishments",
    "sg:postcode":"1860",
    "sg:province":"Vaud",
    "wof:name":"Micronex Sa Bo\u00eetes De Montres",
    "wof:placetype":"venue"
},
  "geometry": {"coordinates":[6.7577629089,47.063533783],"type":"Point"}
}