{
  "type": "Feature",
  "properties": {
    "iso:country":"CH",
    "sg:address":"Rue D'orbe 36",
    "sg:city":"Yverdon-les-bains",
    "sg:orig_category":"Herstellung von Bereifungen",
    "sg:phone":"+41 24 426 49 47",
    "sg:postcode":"1400",
    "sg:province":"Vaud",
    "wof:name":"Kiki-pneus, Daniel Brauch",
    "wof:placetype":"venue"
},
  "geometry": {"coordinates":[6.6414198875,46.778629303],"type":"Point"}
}