{
  "type": "Feature",
  "properties": {
    "addr:full":"4562 Biberist. Postfach Biberist Solothurn 4562",
    "addr:postcode":"4562;postfach;4562",
    "addr:street":"Biberist.",
    "iso:country":"CH",
    "sg:address":"4562 Biberist. Postfach",
    "sg:city":"Biberist",
    "sg:orig_category":"Allgemeiner Hoch U Tiefbau",
    "sg:phone":"+41 32 672 32 56",
    "sg:postcode":"4562",
    "sg:province":"Solothurn",
    "wof:name":"Batigroup Ag",
    "wof:placetype":"venue"
},
  "geometry": {"coordinates":[7.556994,47.181381],"type":"Point"}
}