{
  "type": "Feature",
  "properties": {
    "iso:country":"CH",
    "sg:address":"Murgenthalerstrasse 11",
    "sg:city":"Fulenbach",
    "sg:orig_category":"G\u00fcterbef\u00f6rderung im Strassenverkehr",
    "sg:phone":"+41 62 926 25 49",
    "sg:postcode":"4629",
    "sg:province":"Solothurn",
    "wof:name":"Heinz Sch\u00e4rer Transporte",
    "wof:placetype":"venue"
},
  "geometry": {"coordinates":[7.8320240974,47.2689323425],"type":"Point"}
}