{
  "type": "Feature",
  "properties": {
    "iso:country":"CH",
    "sg:address":"6315",
    "sg:city":"Ober\u00e4geri",
    "sg:orig_category":"Vorschulen, Kinderg\u00e4rten",
    "sg:phone":"+41 71 923 34 54",
    "sg:postcode":"6315",
    "sg:province":"Zug",
    "wof:name":"Kindergarten Flurhof",
    "wof:placetype":"venue"
},
  "geometry": {"coordinates":[9.0531806946,47.4575614929],"type":"Point"}
}