{
  "type": "Feature",
  "properties": {
    "iso:country":"CH",
    "sg:address":"Neptunstrasse 38",
    "sg:city":"Z\u00fcrich",
    "sg:orig_category":"Erwachsenenbildung U Unterricht K\u00fcnstlerische Schulen",
    "sg:phone":"+41 12522828",
    "sg:postcode":"8032",
    "sg:province":"Z\u00fcrich",
    "wof:name":"Schule F\u00fcr Musiktheorie Z\u00fcrich Smz, Specker H.",
    "wof:placetype":"venue"
},
  "geometry": {"coordinates":[8.5560264587,47.3667602539],"type":"Point"}
}