{
  "type": "Feature",
  "properties": {
    "iso:country":"CH",
    "sg:address":"Hintere Dorfstrasse 6",
    "sg:city":"Grossaffoltern",
    "sg:orig_category":"Sonstiger Grosshandel",
    "sg:postcode":"3257",
    "sg:province":"Bern",
    "wof:name":"Swimo Ag",
    "wof:placetype":"venue"
},
  "geometry": {"coordinates":[7.3656740189,47.0712203979],"type":"Point"}
}