{
  "type": "Feature",
  "properties": {
    "iso:country":"CH",
    "sg:address":"Holzmoosr\u00fctisteig 3",
    "sg:city":"W\u00e4denswil",
    "sg:orig_category":"Rohrleitungsbau",
    "sg:phone":"+41 17803160",
    "sg:postcode":"8820",
    "sg:province":"Z\u00fcrich",
    "wof:name":"Bemo Berger Rohrleitungsbau",
    "wof:placetype":"venue"
},
  "geometry": {"coordinates":[8.651386261,47.2350120544],"type":"Point"}
}