{
  "type": "Feature",
  "properties": {
    "iso:country":"CH",
    "sg:address":"Neuweilerstrasse",
    "sg:city":"Allschwil",
    "sg:orig_category":"Zoll- and Grenzb\u00fcros",
    "sg:phone":"+41 61 481 10 40",
    "sg:postcode":"4123",
    "sg:province":"Basel-Landschaft",
    "wof:name":"Zollamt Allschwil-neuwiller",
    "wof:placetype":"venue"
},
  "geometry": {"coordinates":[7.5243330002,47.5380020142],"type":"Point"}
}