{
  "type": "Feature",
  "properties": {
    "iso:country":"CH",
    "sg:address":"Obstgartenstrasse 7 8006 Z\u00fcrich. Postfach",
    "sg:city":"Z\u00fcrich",
    "sg:classifiers":[
        {
            "category":"Insurance",
            "subcategory":"Insurance Agent",
            "type":"Services"
        }
    ],
    "sg:phone":"+41 13636261",
    "sg:postcode":"8035",
    "sg:province":"Z\u00fcrich",
    "sg:tags":[
        "versicherungsagenturen",
        "-broker"
    ],
    "wof:name":"Pwz Ag Versicherungs-& Finanzberatung",
    "wof:placetype":"venue"
},
  "geometry": {"coordinates":[8.5423297882,47.3822364807],"type":"Point"}
}