{
  "type": "Feature",
  "properties": {
    "iso:country":"CH",
    "sg:address":"Milchstrasse 2",
    "sg:city":"Sarnen",
    "sg:orig_category":"Detailhandel mit Brot, Back U S\u00fcsswaren",
    "sg:postcode":"6060",
    "sg:province":"Obwalden",
    "wof:name":"Benno Kuster",
    "wof:placetype":"venue"
},
  "geometry": {"coordinates":[8.245978,46.896366],"type":"Point"}
}