{
  "type": "Feature",
  "properties": {
    "addr:full":"Rosengartenstrasse 1a Z\u00fcrich Z\u00fcrich 8037",
    "addr:housenumber":"1a",
    "addr:postcode":"8037",
    "addr:street":"Rosengartenstrasse",
    "iso:country":"CH",
    "sg:address":"Rosengartenstrasse 1a",
    "sg:city":"Z\u00fcrich",
    "sg:orig_category":"Detailhandel mit Computern U Software Softwareentwicklung U beratung",
    "sg:phone":"+41 14406600",
    "sg:postcode":"8037",
    "sg:province":"Z\u00fcrich",
    "wof:name":"Synthesis Ag",
    "wof:placetype":"venue"
},
  "geometry": {"coordinates":[8.524129,47.393002],"type":"Point"}
}