{
  "type": "Feature",
  "properties": {
    "iso:country":"CH",
    "sg:address":"Brunnmattstrasse 57",
    "sg:city":"Bern",
    "sg:orig_category":"Detailhandel mit Waren verschiedener Art, Hauptrichtung Nahrungsmittel",
    "sg:phone":"+41 31 371 97 22",
    "sg:postcode":"3007",
    "sg:province":"Bern",
    "wof:name":"Primo-markt Hans L\u00fcdi",
    "wof:placetype":"venue"
},
  "geometry": {"coordinates":[7.4254488945,46.9417648315],"type":"Point"}
}