{
  "type": "Feature",
  "properties": {
    "iso:country":"CH",
    "sg:address":"Eisselweg 21 A 3123 Belp. Postfach",
    "sg:city":"Belp",
    "sg:orig_category":"Reinigungsgewerbe",
    "sg:postcode":"3123",
    "sg:province":"Bern",
    "wof:name":"Bruni Marcel Kaminfegergesch\u00e4ft",
    "wof:placetype":"venue"
},
  "geometry": {"coordinates":[7.505879879,46.8983078003],"type":"Point"}
}