{
  "type": "Feature",
  "properties": {
    "iso:country":"CH",
    "sg:address":"8873 Amden. Postfach",
    "sg:city":"Amden",
    "sg:orig_category":"Kurhotels mit Restaurant Medizinische Anstalten",
    "sg:phone":"+41 55 611 12 12",
    "sg:postcode":"8873",
    "sg:province":"St. Gallen",
    "wof:name":"Kurhaus Bergruh",
    "wof:placetype":"venue"
},
  "geometry": {"coordinates":[9.1382074356,47.1490058899],"type":"Point"}
}