{
  "type": "Feature",
  "properties": {
    "iso:country":"CH",
    "sg:address":"Bl\u00fcmlisalpstrasse 63 3627 Heimberg. Postfach",
    "sg:city":"Heimberg",
    "sg:orig_category":"Detailhandel mit elektrischen Haushalts-,Radio U Fernsehger\u00e4ten sowie Musikinstrumenten Sonstiger De",
    "sg:phone":"+41 33 439 30 00",
    "sg:postcode":"3627",
    "sg:province":"Bern",
    "wof:name":"Hobby Ag",
    "wof:placetype":"venue"
},
  "geometry": {"coordinates":[7.6098628044,46.7804374695],"type":"Point"}
}