{
  "type": "Feature",
  "properties": {
    "addr:full":"L\u00f6wenstrasse 22 Z\u00fcrich Z\u00fcrich 8001",
    "addr:housenumber":"22",
    "addr:postcode":"8001",
    "addr:street":"Loewenstrasse",
    "iso:country":"CH",
    "sg:address":"L\u00f6wenstrasse 22",
    "sg:city":"Z\u00fcrich",
    "sg:orig_category":"Advokaturb\u00fcros",
    "sg:phone":"+41 12213633",
    "sg:postcode":"8001",
    "sg:province":"Z\u00fcrich",
    "wof:name":"Silvia Fr\u00fchwirth Advokaturb\u00fcro",
    "wof:placetype":"venue"
},
  "geometry": {"coordinates":[8.535732,47.374168],"type":"Point"}
}