{
  "type": "Feature",
  "properties": {
    "iso:country":"CH",
    "sg:address":"Sennhofweg 19",
    "sg:city":"Zollikerberg",
    "sg:orig_category":"Malerei",
    "sg:phone":"+41 79 216 52 61",
    "sg:postcode":"8125",
    "sg:province":"Z\u00fcrich",
    "wof:name":"Arthur Gautschi Malergesch\u00e4ft",
    "wof:placetype":"venue"
},
  "geometry": {"coordinates":[8.6060943604,47.3457221985],"type":"Point"}
}