{
  "type": "Feature",
  "properties": {
    "iso:country":"CH",
    "sg:address":"Dennigkofenweg",
    "sg:city":"Ostermundigen",
    "sg:orig_category":"Detailhandel mit Zeitungen U Zeitschriften Kioske",
    "sg:phone":"+41 61 711 25 03",
    "sg:postcode":"3072",
    "sg:province":"Bern",
    "wof:name":"Fritz Nussbaum Schwimmbadkiosk",
    "wof:placetype":"venue"
},
  "geometry": {"coordinates":[7.6020240784,47.4948501587],"type":"Point"}
}