{
  "type": "Feature",
  "properties": {
    "addr:full":"Tellsgasse 1 Altdorf Uri 6460",
    "addr:housenumber":"1",
    "addr:postcode":"6460",
    "addr:street":"Tellsgasse;Uri",
    "iso:country":"CH",
    "sg:address":"Tellsgasse 1",
    "sg:city":"Altdorf",
    "sg:classifiers":[
        {
            "category":"Banks & Credit Unions",
            "subcategory":"Bank",
            "type":"Services"
        }
    ],
    "sg:phone":"+41 41 444 41 41",
    "sg:postcode":"6460",
    "sg:province":"Uri",
    "wof:name":"Urner Kantonalbank",
    "wof:placetype":"venue"
},
  "geometry": {"coordinates":[8.643375,46.88176],"type":"Point"}
}