{
  "type": "Feature",
  "properties": {
    "iso:country":"CH",
    "sg:address":"Gotthardstrasse 72",
    "sg:city":"Andermatt",
    "sg:orig_category":"Non-Classified Establishments",
    "sg:postcode":"6490",
    "sg:province":"Uri",
    "wof:name":"Keller Sarah",
    "wof:placetype":"venue"
},
  "geometry": {"coordinates":[8.5954523087,46.6332244873],"type":"Point"}
}