{
  "type": "Feature",
  "properties": {
    "iso:country":"CH",
    "sg:address":"Balgriststrasse 20a",
    "sg:city":"Z\u00fcrich",
    "sg:orig_category":"Herstellung von Reiseartikeln, Leder U Sattlerwaren",
    "sg:postcode":"8008",
    "sg:province":"Z\u00fcrich",
    "wof:name":"Suter Eduard Autosattlerei",
    "wof:placetype":"venue"
},
  "geometry": {"coordinates":[8.7711877823,47.2022171021],"type":"Point"}
}