{
  "type": "Feature",
  "properties": {
    "iso:country":"CH",
    "sg:address":"Helisb\u00fchlstrasse 2",
    "sg:city":"Herbligen",
    "sg:orig_category":"Grosshandel mit lebenden Tieren",
    "sg:phone":"+41 31 771 12 68",
    "sg:postcode":"3671",
    "sg:province":"Bern",
    "wof:name":"Alfred Wittwer Viehhandel",
    "wof:placetype":"venue"
},
  "geometry": {"coordinates":[7.6135320663,46.8207931519],"type":"Point"}
}