{
  "type": "Feature",
  "properties": {
    "iso:country":"CH",
    "sg:address":"Eichstrasse 30",
    "sg:city":"Spreitenbach",
    "sg:orig_category":"Fahrschulen, Flugschulen",
    "sg:phone":"+41 79 680 32 02",
    "sg:postcode":"8957",
    "sg:province":"Aargau",
    "wof:name":"Roger Oesch Autofahrschule",
    "wof:placetype":"venue"
},
  "geometry": {"coordinates":[9.4626941681,47.169380188],"type":"Point"}
}