{
  "type": "Feature",
  "properties": {
    "iso:country":"CH",
    "sg:address":"Via Industria 24",
    "sg:city":"Biasca",
    "sg:classifiers":[
        {
            "category":"Health Services",
            "subcategory":"Nursing And Care Facility",
            "type":"Services"
        }
    ],
    "sg:phone":"+41 91 873 01 10",
    "sg:postcode":"6710",
    "sg:province":"Ticino",
    "sg:tags":[
        "circulatory",
        "cardiac",
        "complaint",
        "remedy",
        "stimulant"
    ],
    "wof:name":"Helsinn Chemicals Sa",
    "wof:placetype":"venue"
},
  "geometry": {"coordinates":[8.971983,46.343517],"type":"Point"}
}