{
  "type": "Feature",
  "properties": {
    "iso:country":"CH",
    "sg:address":"Industriestrasse / Schranken",
    "sg:city":"Frick",
    "sg:orig_category":"G\u00fcterbef\u00f6rderung im Strassenverkehr",
    "sg:phone":"+41 62 871 89 20",
    "sg:postcode":"5070",
    "sg:province":"Aargau",
    "wof:name":"Kurt Alder Transporte",
    "wof:placetype":"venue"
},
  "geometry": {"coordinates":[8.0233249664,47.5061149597],"type":"Point"}
}