{
  "type": "Feature",
  "properties": {
    "iso:country":"CH",
    "sg:address":"Saint-julien Route De 119",
    "sg:city":"Plan-les-ouates",
    "sg:orig_category":"Finanzierungsinstitutionen",
    "sg:postcode":"1228",
    "sg:province":"Gen\u00e8ve",
    "wof:name":"Invest Capital S\u00e0rl",
    "wof:placetype":"venue"
},
  "geometry": {"coordinates":[6.1204991341,46.1696243286],"type":"Point"}
}