{
  "type": "Feature",
  "properties": {
    "addr:full":"Ergolzstrasse 44 Lausen Basel-Landschaft 4415",
    "addr:housenumber":"44",
    "addr:postcode":"4415",
    "addr:street":"Ergolzstrasse",
    "iso:country":"CH",
    "sg:address":"Ergolzstrasse 44",
    "sg:city":"Lausen",
    "sg:orig_category":"Aktivit\u00e4ten der Generalunternehmen im Baugewerbe Vermittlung von Immobilien",
    "sg:phone":"+41 61 921 00 44",
    "sg:postcode":"4415",
    "sg:province":"Basel-Landschaft",
    "wof:name":"Gebr\u00fcder Weibel Generalunternehmung",
    "wof:placetype":"venue"
},
  "geometry": {"coordinates":[7.758847,47.473915],"type":"Point"}
}