{
  "type": "Feature",
  "properties": {
    "iso:country":"CH",
    "sg:address":"Unterdorfstrasse 20",
    "sg:city":"Sirnach",
    "sg:orig_category":"Non-Classified Establishments",
    "sg:postcode":"8370",
    "sg:province":"Thurgau",
    "wof:name":"Ew Sirnach Ag",
    "wof:placetype":"venue"
},
  "geometry": {"coordinates":[8.9944753647,47.4630355835],"type":"Point"}
}