{
  "type": "Feature",
  "properties": {
    "iso:country":"CH",
    "sg:address":"Via Salins 4",
    "sg:city":"Sedrun",
    "sg:orig_category":"Wohnheime f\u00fcr Kinder U Jugendliche",
    "sg:phone":"+41 81 949 13 00",
    "sg:postcode":"7188",
    "sg:province":"Graubunden",
    "wof:name":"Casa Tg\u00e8sa Strem Jugendlager",
    "wof:placetype":"venue"
},
  "geometry": {"coordinates":[8.7701330185,46.6815414429],"type":"Point"}
}