{
  "type": "Feature",
  "properties": {
    "iso:country":"CH",
    "sg:address":"Beim L\u00f6wen",
    "sg:city":"Vorderthal",
    "sg:orig_category":"Sportvereine Ski",
    "sg:phone":"+41 55 446 14 30",
    "sg:postcode":"8857",
    "sg:province":"Schwyz",
    "wof:name":"Skiclub W\u00e4gital Vorderthal",
    "wof:placetype":"venue"
},
  "geometry": {"coordinates":[8.9013547897,47.1198883057],"type":"Point"}
}