{
  "type": "Feature",
  "properties": {
    "iso:country":"CH",
    "sg:address":"Benkenstrasse 61",
    "sg:city":"Binningen",
    "sg:orig_category":"Sonstige pers\u00f6nliche Dienstleistungen",
    "sg:postcode":"4102",
    "sg:province":"Basel-Landschaft",
    "wof:name":"Peca Artservice Ag",
    "wof:placetype":"venue"
},
  "geometry": {"coordinates":[7.5647830963,47.5335922241],"type":"Point"}
}