{
  "type": "Feature",
  "properties": {
    "iso:country":"CH",
    "sg:address":"Feldwyden",
    "sg:city":"Sarnen",
    "sg:orig_category":"Grosshandel mit lebenden Tieren",
    "sg:phone":"+41 41 660 40 07",
    "sg:postcode":"6060",
    "sg:province":"Obwalden",
    "wof:name":"Josef Zumstein Zucht-& Nutzviehhandel",
    "wof:placetype":"venue"
},
  "geometry": {"coordinates":[8.2579174042,46.901802063],"type":"Point"}
}