{
  "type": "Feature",
  "properties": {
    "iso:country":"CH",
    "sg:address":"Rue Du Lac 92",
    "sg:city":"Clarens",
    "sg:orig_category":"Arztpraxen",
    "sg:phone":"+41 21 989 22 30",
    "sg:postcode":"1815",
    "sg:province":"Vaud",
    "wof:name":"Dr M\u00e9d. Andr\u00e9as Messikommer M\u00e9decin Sp\u00e9cialiste Fmh",
    "wof:placetype":"venue"
},
  "geometry": {"coordinates":[6.891702,46.440773],"type":"Point"}
}