{
  "type": "Feature",
  "properties": {
    "iso:country":"CH",
    "sg:address":"La Belle Adze D 1773 L\u00e9chelles. Postfach",
    "sg:city":"L\u00e9chelles",
    "sg:orig_category":"Sanit\u00e4r, Heizungs U L\u00fcftungsinstallation",
    "sg:phone":"+41 26 660 79 97",
    "sg:postcode":"1773",
    "sg:province":"Fribourg",
    "wof:name":"Ottet Fabrice, Chauffage-sanitaire Entrepr. De Chauffage-sanitaire",
    "wof:placetype":"venue"
},
  "geometry": {"coordinates":[7.0104751587,46.8289413452],"type":"Point"}
}