{
  "type": "Feature",
  "properties": {
    "iso:country":"CH",
    "sg:address":"Huebstrasse 3 8633 Wolfhausen. Postfach 361",
    "sg:city":"Wolfhausen",
    "sg:orig_category":"Grosshandel mit Sportartikeln Sonstiger Grosshandel",
    "sg:phone":"+41 81 833 08 33",
    "sg:postcode":"8633",
    "sg:province":"Z\u00fcrich",
    "wof:name":"Les Arcades, Naegeli Georg",
    "wof:placetype":"venue"
},
  "geometry": {"coordinates":[9.8382310867,46.4971809387],"type":"Point"}
}