{
  "type": "Feature",
  "properties": {
    "iso:country":"CH",
    "sg:address":"Schulhausstrasse 16",
    "sg:city":"Selzach",
    "sg:orig_category":"Allgemeiner Hoch U Tiefbau Hoch U Tiefbau",
    "sg:phone":"+41 32 641 23 01",
    "sg:postcode":"2545",
    "sg:province":"Solothurn",
    "wof:name":"Hug Erwin, Nachfolger Hug Anton.",
    "wof:placetype":"venue"
},
  "geometry": {"coordinates":[7.455203,47.206795],"type":"Point"}
}