{
  "type": "Feature",
  "properties": {
    "iso:country":"CH",
    "sg:address":"Schneidergasse 27 4051 Basel. Postfach",
    "sg:city":"Basel",
    "sg:orig_category":"Detailhandel mit Brillen U anderen Sehhilfen",
    "sg:phone":"+41 61 261 61 06",
    "sg:postcode":"4001",
    "sg:province":"Basel-Stadt",
    "wof:name":"Hoenes Optik, Nachfolger Schneider Thomas",
    "wof:placetype":"venue"
},
  "geometry": {"coordinates":[7.586872,47.55759],"type":"Point"}
}