{
  "type": "Feature",
  "properties": {
    "iso:country":"CH",
    "sg:address":"Via Nizzola 1b",
    "sg:city":"Bellinzona",
    "sg:orig_category":"Zahnarztpraxen",
    "sg:phone":"+41 91 825 48 02",
    "sg:postcode":"6500",
    "sg:province":"Ticino",
    "wof:name":"Dottori Fritzsche & De Ry Dentisti",
    "wof:placetype":"venue"
},
  "geometry": {"coordinates":[9.0208530426,46.189365387],"type":"Point"}
}