{
  "type": "Feature",
  "properties": {
    "iso:country":"CH",
    "sg:address":"7610",
    "sg:city":"Soglio",
    "sg:classifiers":[
        {
            "category":"Travel",
            "subcategory":"Hotels & Motels",
            "type":"Entertainment"
        }
    ],
    "sg:phone":"+41 81 822 15 00",
    "sg:postcode":"7610",
    "sg:province":"Graubunden",
    "sg:tags":[
        "hotels",
        "mit",
        "restaurant"
    ],
    "wof:name":"Hotel M\u00fcrias",
    "wof:placetype":"venue"
},
  "geometry": {"coordinates":[9.5379247665,46.3412361145],"type":"Point"}
}