{
  "type": "Feature",
  "properties": {
    "iso:country":"CH",
    "sg:address":"Schwarzenburgstrasse 322",
    "sg:city":"K\u00f6niz",
    "sg:orig_category":"RESTAURANTS: TEA-ROOMS",
    "sg:postcode":"3098",
    "sg:province":"Bern",
    "wof:name":"M. Schwyter",
    "wof:placetype":"venue"
},
  "geometry": {"coordinates":[7.41274786,46.9201507568],"type":"Point"}
}