{
  "type": "Feature",
  "properties": {
    "iso:country":"CH",
    "sg:address":"Rue Du Grand-pr\u00e9 62",
    "sg:city":"Gen\u00e8ve",
    "sg:orig_category":"HOTELS: OHNE RESTAURANT",
    "sg:phone":"+41 22 731 55 30",
    "sg:postcode":"1202",
    "sg:province":"Gen\u00e8ve",
    "wof:name":"H\u00f4tel Lido",
    "wof:placetype":"venue"
},
  "geometry": {"coordinates":[6.1435928345,46.20835495],"type":"Point"}
}