{
  "type": "Feature",
  "properties": {
    "iso:country":"CH",
    "sg:address":"Bachstrasse 27",
    "sg:city":"Obfelden",
    "sg:orig_category":"Instandhaltung U Reparatur von Automobilen",
    "sg:phone":"+41 17614257",
    "sg:postcode":"8912",
    "sg:province":"Z\u00fcrich",
    "wof:name":"Isenberg-garage Gmbh",
    "wof:placetype":"venue"
},
  "geometry": {"coordinates":[8.4227313995,47.2665328979],"type":"Point"}
}