{
  "type": "Feature",
  "properties": {
    "iso:country":"CH",
    "sg:address":"Bodenmattstr. 18.",
    "sg:city":"Witterswil",
    "sg:orig_category":"Fachdetailhandel in Verkaufsr\u00e4umen",
    "sg:postcode":"4108",
    "sg:province":"Solothurn",
    "wof:name":"Miro Gilgen Lone.",
    "wof:placetype":"venue"
},
  "geometry": {"coordinates":[7.5282258987,47.4849586487],"type":"Point"}
}