{
  "type": "Feature",
  "properties": {
    "iso:country":"CH",
    "sg:address":"Kreuzlingerstrasse 1",
    "sg:city":"Amriswil",
    "sg:orig_category":"Zimmerei, Dachdeckerei, Bauspenglerei U Abdichtung",
    "sg:phone":"+41 71 411 58 93",
    "sg:postcode":"8580",
    "sg:province":"Thurgau",
    "wof:name":"So\u00f2s Josef",
    "wof:placetype":"venue"
},
  "geometry": {"coordinates":[9.2825517654,47.5453147888],"type":"Point"}
}