{
  "type": "Feature",
  "properties": {
    "iso:country":"CH",
    "sg:address":"Tittwiesenstrasse 29",
    "sg:city":"Chur",
    "sg:orig_category":"Vermietung U Verpachtung von eigenen Immobilien",
    "sg:postcode":"7000",
    "sg:province":"Graubunden",
    "wof:name":"Immobiliengesellschaft Caluca Sa",
    "wof:placetype":"venue"
},
  "geometry": {"coordinates":[9.5271863937,46.8572120667],"type":"Point"}
}