{
  "type": "Feature",
  "properties": {
    "iso:country":"CH",
    "sg:address":"Gallusstrasse 6",
    "sg:city":"Kriens",
    "sg:orig_category":"Architekturb\u00fcros",
    "sg:phone":"+41 41 320 70 30",
    "sg:postcode":"6010",
    "sg:province":"Luzern",
    "wof:name":"Anton Muff Architekturb\u00fcro",
    "wof:placetype":"venue"
},
  "geometry": {"coordinates":[8.279697,47.033394],"type":"Point"}
}