{
  "type": "Feature",
  "properties": {
    "iso:country":"CH",
    "sg:address":"Gr\u00fcnmattstrasse 19",
    "sg:city":"Z\u00fcrich",
    "sg:orig_category":"Sportvereine Turnen",
    "sg:phone":"+41 41 670 28 19",
    "sg:postcode":"8055",
    "sg:province":"Z\u00fcrich",
    "wof:name":"Lehrerturnverein Obwalden",
    "wof:placetype":"venue"
},
  "geometry": {"coordinates":[8.2684926987,46.9370956421],"type":"Point"}
}