{
  "type": "Feature",
  "properties": {
    "iso:country":"CH",
    "sg:address":"Willadingenstrasse 22",
    "sg:city":"Koppigen",
    "sg:orig_category":"Grosshandel mit Holz U Bauelementen aus Holz S\u00e4gewerke",
    "sg:phone":"+41 34 413 13 11",
    "sg:postcode":"3425",
    "sg:province":"Bern",
    "wof:name":"Aebi Holz Ag",
    "wof:placetype":"venue"
},
  "geometry": {"coordinates":[7.607006073,47.1363220215],"type":"Point"}
}