{
  "type": "Feature",
  "properties": {
    "iso:country":"CH",
    "sg:address":"Milit\u00e4rstrasse 90 8004 Z\u00fcrich. Postfach 4068",
    "sg:city":"Z\u00fcrich",
    "sg:orig_category":"Grosshandel mit Erzen U Metallen Grosshandel mit Holz U Baustoffen",
    "sg:phone":"+41 61 711 73 73",
    "sg:postcode":"8021",
    "sg:province":"Z\u00fcrich",
    "wof:name":"Bab Baustoffe Ag",
    "wof:placetype":"venue"
},
  "geometry": {"coordinates":[7.6006069183,47.488658905],"type":"Point"}
}