{
  "type": "Feature",
  "properties": {
    "iso:country":"CH",
    "sg:address":"Therwilerstrasse 1",
    "sg:city":"Bottmingen",
    "sg:orig_category":"Detailhandel mit Blumen U Pflanzen Detailhandel mit Geschenkartikeln U Souvenirs",
    "sg:phone":"+41 71 311 11 30",
    "sg:postcode":"4103",
    "sg:province":"Basel-Landschaft",
    "wof:name":"Blumen-geschenksboutique Bijou Sturzenegger & Flick",
    "wof:placetype":"venue"
},
  "geometry": {"coordinates":[9.303129,47.404793],"type":"Point"}
}