{
  "type": "Feature",
  "properties": {
    "iso:country":"CH",
    "sg:address":"Mara\u00eechers Rue Des 3 1205 Gen\u00e8ve. Postfach",
    "sg:city":"Gen\u00e8ve",
    "sg:orig_category":"Fachdetailhandel in Verkaufsr\u00e4umen",
    "sg:postcode":"1205",
    "sg:province":"Gen\u00e8ve",
    "wof:name":"S\u00f6nke R\u00fcegg Gmbh",
    "wof:placetype":"venue"
},
  "geometry": {"coordinates":[8.6276226044,46.8828697205],"type":"Point"}
}