{
  "type": "Feature",
  "properties": {
    "iso:country":"CH",
    "sg:address":"Lindenstrasse 1",
    "sg:city":"Kollbrunn",
    "sg:orig_category":"Bauschreinerei Innenausbau",
    "sg:phone":"+41 52 383 11 78",
    "sg:postcode":"8483",
    "sg:province":"Z\u00fcrich",
    "wof:name":"Albert Bosshard",
    "wof:placetype":"venue"
},
  "geometry": {"coordinates":[8.776383,47.456284],"type":"Point"}
}