{
  "type": "Feature",
  "properties": {
    "iso:country":"CH",
    "sg:address":"Bahnstrasse 29",
    "sg:city":"Uster",
    "sg:orig_category":"Instandhaltung U Reparatur von Automobilen",
    "sg:postcode":"8610",
    "sg:province":"Z\u00fcrich",
    "wof:name":"Weber R. Kreuz-garage Ag Autoreparaturwerkst\u00e4tte, Fahrzeughandel, Hotels In Brasilien Usw",
    "wof:placetype":"venue"
},
  "geometry": {"coordinates":[8.7250242233,47.348072052],"type":"Point"}
}