{
  "type": "Feature",
  "properties": {
    "iso:country":"CH",
    "sg:address":"Chemin Des Selli\u00e8res 57",
    "sg:city":"A\u00efre",
    "sg:orig_category":"Autospenglereien",
    "sg:phone":"+41 79 624 63 17",
    "sg:postcode":"1219",
    "sg:province":"Gen\u00e8ve",
    "wof:name":"Daniel Bielser Carrosserie",
    "wof:placetype":"venue"
},
  "geometry": {"coordinates":[6.096066,46.195023],"type":"Point"}
}