{
  "type": "Feature",
  "properties": {
    "iso:country":"CH",
    "sg:address":"6772",
    "sg:city":"Rodi-fiesso",
    "sg:orig_category":"Non-Classified Establishments",
    "sg:phone":"+41 91 795 11 41",
    "sg:postcode":"6772",
    "sg:province":"Ticino",
    "wof:name":"Ristorante La Riva",
    "wof:placetype":"venue"
},
  "geometry": {"coordinates":[8.8414697647,46.1437950134],"type":"Point"}
}