{
  "type": "Feature",
  "properties": {
    "iso:country":"CH",
    "sg:address":"1754",
    "sg:city":"Avry-sur-matran",
    "sg:orig_category":"Detailhandel mit Waren verschiedener Art, Hauptrichtung Nahrungsmittel",
    "sg:phone":"+41 22 979 07 77",
    "sg:postcode":"1754",
    "sg:province":"Fribourg",
    "wof:name":"Migros Belexert",
    "wof:placetype":"venue"
},
  "geometry": {"coordinates":[6.1146712303,46.2194747925],"type":"Point"}
}