{
  "type": "Feature",
  "properties": {
    "iso:country":"CH",
    "sg:address":"Schulgasse 17 4057 Basel. Postfach",
    "sg:city":"Basel",
    "sg:orig_category":"Grosshandel mit elektrischen Haushaltsger\u00e4ten Herstellung von K\u00fcchenm\u00f6beln",
    "sg:phone":"+41 61 631 50 65",
    "sg:postcode":"4019",
    "sg:province":"Basel-Stadt",
    "wof:name":"Irema Ag Apparate, Maschinenhandel Usw",
    "wof:placetype":"venue"
},
  "geometry": {"coordinates":[7.5914697647,47.5833282471],"type":"Point"}
}