{
  "type": "Feature",
  "properties": {
    "iso:country":"CH",
    "sg:address":"6718",
    "sg:city":"Olivone",
    "sg:classifiers":[
        {
            "category":"Travel",
            "subcategory":"Hotels & Motels",
            "type":"Entertainment"
        }
    ],
    "sg:postcode":"6718",
    "sg:province":"Ticino",
    "sg:tags":[
        "hotels",
        "mit",
        "restaurant"
    ],
    "wof:name":"Acquasole Sa",
    "wof:placetype":"venue"
},
  "geometry": {"coordinates":[8.9390602112,46.5288009644],"type":"Point"}
}