{
  "type": "Feature",
  "properties": {
    "iso:country":"CH",
    "sg:address":"Luchten 86",
    "sg:city":"Wolfhalden",
    "sg:orig_category":"Detailhandel mit Milcherzeugnissen U Eiern Verarbeitung von Milch",
    "sg:phone":"+41 71 891 18 02",
    "sg:postcode":"9427",
    "sg:province":"Appenzell Ausserrhoden",
    "wof:name":"Walter Mettler K\u00e4serei",
    "wof:placetype":"venue"
},
  "geometry": {"coordinates":[9.546380043,47.452205658],"type":"Point"}
}