{
  "type": "Feature",
  "properties": {
    "addr:full":"Route De Ch\u00eane 21 Gen\u00e8ve Gen\u00e8ve 1207",
    "addr:housenumber":"21",
    "addr:postcode":"1207",
    "addr:street":"Route De Che\u0302Ne",
    "iso:country":"CH",
    "sg:address":"Route De Ch\u00eane 21",
    "sg:city":"Gen\u00e8ve",
    "sg:classifiers":[
        {
            "category":"Bars & Pubs",
            "type":"Food & Drink"
        }
    ],
    "sg:phone":"+41 22 700 05 70",
    "sg:postcode":"1207",
    "sg:province":"Gen\u00e8ve",
    "sg:tags":[
        "restaurant"
    ],
    "wof:name":"Caf\u00e9-rest. Bar Follia",
    "wof:placetype":"venue"
},
  "geometry": {"coordinates":[6.167035,46.200264],"type":"Point"}
}