{
  "type": "Feature",
  "properties": {
    "iso:country":"CH",
    "sg:address":"Avenue Louis-casa\u00ef 27",
    "sg:city":"Gen\u00e8ve",
    "sg:orig_category":"Detailhandel mit Damenbekleidung Kleiderboutiquen",
    "sg:postcode":"1209",
    "sg:province":"Gen\u00e8ve",
    "wof:name":"Yendi Sa Mode F\u00e9minine",
    "wof:placetype":"venue"
},
  "geometry": {"coordinates":[6.5648651123,46.5335083008],"type":"Point"}
}