{
  "type": "Feature",
  "properties": {
    "iso:country":"CH",
    "sg:address":"Bannholz",
    "sg:city":"Goldingen",
    "sg:orig_category":"Verwertung von Milch",
    "sg:postcode":"8638",
    "sg:province":"St. Gallen",
    "wof:name":"Wieland A.",
    "wof:placetype":"venue"
},
  "geometry": {"coordinates":[8.9516220093,47.2735061646],"type":"Point"}
}