{
  "type": "Feature",
  "properties": {
    "iso:country":"CH",
    "sg:address":"Friedrichstrasse 6",
    "sg:city":"Z\u00fcrich",
    "sg:orig_category":"Handelsvermittlung U Grosshandel Herstellung von sonstigen elektrischen Ausr\u00fcstungen",
    "sg:phone":"+41 13226068",
    "sg:postcode":"8051",
    "sg:province":"Z\u00fcrich",
    "wof:name":"Huber A. K., Sicherheitsbedarf",
    "wof:placetype":"venue"
},
  "geometry": {"coordinates":[8.5696554184,47.4043998718],"type":"Point"}
}