{
  "type": "Feature",
  "properties": {
    "iso:country":"CH",
    "sg:address":"Kantonaspital Baden",
    "sg:city":"Baden",
    "sg:orig_category":"Sportvereine Ballsport Tennis",
    "sg:phone":"+41 56 484 21 11",
    "sg:postcode":"5404",
    "sg:province":"Aargau",
    "wof:name":"Tc Kantonsspital Baden",
    "wof:placetype":"venue"
},
  "geometry": {"coordinates":[8.3064451218,47.4743309021],"type":"Point"}
}