{
  "type": "Feature",
  "properties": {
    "iso:country":"CH",
    "sg:address":"En Sous-villaz",
    "sg:city":"S\u00e9very",
    "sg:orig_category":"Forstwirtschaft ohne Dienstleistungen in der Forstwirtschaft",
    "sg:phone":"+41 21 800 33 78",
    "sg:postcode":"1141",
    "sg:province":"Vaud",
    "wof:name":"Rittener & Fils Sa, Entreprise Foresti\u00e8re",
    "wof:placetype":"venue"
},
  "geometry": {"coordinates":[6.4426550865,46.5759391785],"type":"Point"}
}