{
  "type": "Feature",
  "properties": {
    "iso:country":"CH",
    "sg:address":"H\u00f6henstrasse 22",
    "sg:city":"Fl\u00fcelen",
    "sg:orig_category":"Sonstige Hilfs U Nebent\u00e4tigkeiten f\u00fcr die Schiffahrt",
    "sg:postcode":"6454",
    "sg:province":"Uri",
    "wof:name":"Genossenschaft Bootshafen Fl\u00fcelen",
    "wof:placetype":"venue"
},
  "geometry": {"coordinates":[8.624546051,46.9105453491],"type":"Point"}
}