{
  "type": "Feature",
  "properties": {
    "iso:country":"CH",
    "sg:address":"Gellertstrasse 7",
    "sg:city":"Basel",
    "sg:orig_category":"Arbeitnehmerverb\u00e4nde",
    "sg:phone":"+41 61 312 08 95",
    "sg:postcode":"4052",
    "sg:province":"Basel-Stadt",
    "wof:name":"Merkuria Verein F.kath.kauf- Leute & Beamte Hrn Paul H\u00e4gi",
    "wof:placetype":"venue"
},
  "geometry": {"coordinates":[7.606874,47.552452],"type":"Point"}
}