{
  "type": "Feature",
  "properties": {
    "iso:country":"CH",
    "sg:address":"Fr\u00e9d\u00e9ric-c\u00e9sar-de-la Harpe Av 16",
    "sg:city":"Lausanne",
    "sg:classifiers":[
        {
            "category":"Travel",
            "subcategory":"Hotels & Motels",
            "type":"Entertainment"
        }
    ],
    "sg:postcode":"1000",
    "sg:province":"Vaud",
    "sg:tags":[
        "hotels",
        "mit",
        "restaurant"
    ],
    "wof:name":"Colloquia S\u00e0rl Fourniture De Prestations Dans Le Domaine De L'organisation De Conf\u00e9rences, D'expositions Etc",
    "wof:placetype":"venue"
},
  "geometry": {"coordinates":[6.5606098175,46.5287094116],"type":"Point"}
}