{
  "type": "Feature",
  "properties": {
    "iso:country":"CH",
    "sg:address":"Kasernenstrasse 15",
    "sg:city":"Lyss",
    "sg:classifiers":[
        {
            "category":"Insurance",
            "subcategory":"Insurance Agent",
            "type":"Services"
        }
    ],
    "sg:phone":"+41 32 384 51 11",
    "sg:postcode":"3250",
    "sg:province":"Bern",
    "sg:tags":[
        "versicherungsagenturen",
        "-broker"
    ],
    "wof:name":"Anton Britschgi Agentur National-versicherung",
    "wof:placetype":"venue"
},
  "geometry": {"coordinates":[7.297369957,47.0765228271],"type":"Point"}
}