{
  "type": "Feature",
  "properties": {
    "iso:country":"CH",
    "sg:address":"Obere Spichermatt 12",
    "sg:city":"Stans",
    "sg:orig_category":"Non-Classified Establishments",
    "sg:postcode":"6370",
    "sg:province":"Nidwalden",
    "wof:name":"Ensyco Energy Systems & Components Ag",
    "wof:placetype":"venue"
},
  "geometry": {"coordinates":[8.3595991135,46.966003418],"type":"Point"}
}