{
  "type": "Feature",
  "properties": {
    "iso:country":"CH",
    "sg:address":"Aathalstrasse 38a 8610 Uster. Postfach",
    "sg:city":"Uster",
    "sg:orig_category":"Herstellung von Schuhen",
    "sg:postcode":"8610",
    "sg:province":"Z\u00fcrich",
    "wof:name":"Schuhatelier Gamma",
    "wof:placetype":"venue"
},
  "geometry": {"coordinates":[8.9380836487,45.859539032],"type":"Point"}
}