{
  "type": "Feature",
  "properties": {
    "iso:country":"CH",
    "sg:address":"Chemin Des M\u00e9ssanges 47",
    "sg:city":"Th\u00f4nex",
    "sg:orig_category":"Unclassifiable Establishments",
    "sg:phone":"+41 22 349 99 79",
    "sg:postcode":"1226",
    "sg:province":"Gen\u00e8ve",
    "wof:name":"In Vitro V\u00e9g\u00e9tal Sa",
    "wof:placetype":"venue"
},
  "geometry": {"coordinates":[6.2084999084,46.2000656128],"type":"Point"}
}