{
  "type": "Feature",
  "properties": {
    "iso:country":"CH",
    "sg:address":"Gewerbestrasse 11",
    "sg:city":"Cham",
    "sg:orig_category":"Sonstiger Grosshandel",
    "sg:postcode":"6330",
    "sg:province":"Zug",
    "wof:name":"Staninvest Ag",
    "wof:placetype":"venue"
},
  "geometry": {"coordinates":[8.4720430374,47.1886940002],"type":"Point"}
}