{
  "type": "Feature",
  "properties": {
    "iso:country":"CH",
    "sg:address":"Tannenweg 52",
    "sg:city":"Rheinfelden",
    "sg:orig_category":"Hardwareberatung Softwareentwicklung U beratung",
    "sg:phone":"+41 61 831 74 74",
    "sg:postcode":"4310",
    "sg:province":"Aargau",
    "wof:name":"Personal Computer Beratung D\u00fcnki Geri",
    "wof:placetype":"venue"
},
  "geometry": {"coordinates":[7.7808032036,47.5489463806],"type":"Point"}
}