{
  "type": "Feature",
  "properties": {
    "iso:country":"CH",
    "sg:address":"Moosweg 933 5317 Hettenschwil. Postfach",
    "sg:city":"Hettenschwil",
    "sg:orig_category":"Fachdetailhandel in Verkaufsr\u00e4umen",
    "sg:postcode":"5317",
    "sg:province":"Aargau",
    "wof:name":"Scherrer & Partner Gmbh",
    "wof:placetype":"venue"
},
  "geometry": {"coordinates":[8.1988039017,47.5767021179],"type":"Point"}
}