{
  "type": "Feature",
  "properties": {
    "iso:country":"CH",
    "sg:address":"Rugenparkstrasse 2",
    "sg:city":"Interlaken",
    "sg:classifiers":[
        {
            "category":"Travel",
            "subcategory":"Hotels & Motels",
            "type":"Entertainment"
        }
    ],
    "sg:phone":"+41 33 822 64 81",
    "sg:postcode":"3800",
    "sg:province":"Bern",
    "sg:tags":[
        "hotels",
        "mit",
        "restaurant"
    ],
    "wof:name":"Hotel Gotthard",
    "wof:placetype":"venue"
},
  "geometry": {"coordinates":[7.851556778,46.6819992065],"type":"Point"}
}