{
  "type": "Feature",
  "properties": {
    "iso:country":"CH",
    "sg:address":"6913",
    "sg:city":"Carabbia",
    "sg:orig_category":"Gartenbau",
    "sg:phone":"+41 91 994 17 10",
    "sg:postcode":"6913",
    "sg:province":"Ticino",
    "wof:name":"Fritz Egli Manutenzione Giardini",
    "wof:placetype":"venue"
},
  "geometry": {"coordinates":[8.933429718,45.969959259],"type":"Point"}
}