{
  "type": "Feature",
  "properties": {
    "iso:country":"CH",
    "sg:address":"L\u00e4chenstrasse 28",
    "sg:city":"Flurlingen",
    "sg:orig_category":"Unternehmensberatung",
    "sg:phone":"+41 52 659 44 70",
    "sg:postcode":"8247",
    "sg:province":"Z\u00fcrich",
    "wof:name":"Onion Unternehmensberatung Energie-& Umweltmanagement Ag",
    "wof:placetype":"venue"
},
  "geometry": {"coordinates":[8.6284790039,47.6803474426],"type":"Point"}
}