{
  "type": "Feature",
  "properties": {
    "iso:country":"CH",
    "sg:address":"R\u00e4tschegass 2",
    "sg:city":"Niederhasli",
    "sg:orig_category":"Wirtschaftspr\u00fcfung, Steuerberatung U Treuhand",
    "sg:postcode":"8155",
    "sg:province":"Z\u00fcrich",
    "wof:name":"Confidrevi Gmbh",
    "wof:placetype":"venue"
},
  "geometry": {"coordinates":[8.4852657318,47.4808731079],"type":"Point"}
}