{
  "type": "Feature",
  "properties": {
    "iso:country":"CH",
    "sg:address":"Zubackerweg 9",
    "sg:city":"Herzogenbuchsee",
    "sg:orig_category":"Sportvereine Velo Rad-& Motorfahrer-Bund SRB",
    "sg:postcode":"3360",
    "sg:province":"Bern",
    "wof:name":"Velo-moto-club H\u00e4gendorf",
    "wof:placetype":"venue"
},
  "geometry": {"coordinates":[7.869931221,47.3481903076],"type":"Point"}
}