{
  "type": "Feature",
  "properties": {
    "iso:country":"CH",
    "sg:address":"Ronystrasse 4c",
    "sg:city":"H\u00fcnenberg",
    "sg:orig_category":"Fahrschulen, Flugschulen",
    "sg:phone":"+41 41 780 30 00",
    "sg:postcode":"6331",
    "sg:province":"Zug",
    "wof:name":"Roger Stoll Fahrschule",
    "wof:placetype":"venue"
},
  "geometry": {"coordinates":[8.4245586395,47.1794090271],"type":"Point"}
}