{
  "type": "Feature",
  "properties": {
    "iso:country":"CH",
    "sg:address":"Oberdorfstrasse 11/13",
    "sg:city":"Baar",
    "sg:orig_category":"Herstellung von medizinischen U chirurgischen Ger\u00e4ten sowie orthop\u00e4dischen Vorrichtungen",
    "sg:phone":"+41 41 769 79 66",
    "sg:postcode":"6340",
    "sg:province":"Zug",
    "wof:name":"Tech Aid Development Ag",
    "wof:placetype":"venue"
},
  "geometry": {"coordinates":[8.5302343369,47.1961288452],"type":"Point"}
}