{
  "type": "Feature",
  "properties": {
    "iso:country":"CH",
    "sg:address":"Laupen\u00e4ckerstrasse 7",
    "sg:city":"Unterlunkhofen",
    "sg:orig_category":"Detailhandel mit Textilien",
    "sg:phone":"+41 56 634 21 57",
    "sg:postcode":"8918",
    "sg:province":"Aargau",
    "wof:name":"Christa Frauenfelder Bettwaren",
    "wof:placetype":"venue"
},
  "geometry": {"coordinates":[8.3809089661,47.3225898743],"type":"Point"}
}