{
  "type": "Feature",
  "properties": {
    "iso:country":"CH",
    "sg:address":"7175",
    "sg:city":"Sumvitg",
    "sg:classifiers":[
        {
            "category":"Restaurant",
            "type":"Food & Drink"
        }
    ],
    "sg:phone":"+41 81 635 11 47",
    "sg:postcode":"7175",
    "sg:province":"Graubunden",
    "wof:name":"Ustria Felsenkeller",
    "wof:placetype":"venue"
},
  "geometry": {"coordinates":[9.3398103714,46.8325386047],"type":"Point"}
}