{
  "type": "Feature",
  "properties": {
    "iso:country":"CH",
    "sg:address":"R\u00f6slistrasse 15a",
    "sg:city":"Wallisellen",
    "sg:orig_category":"Architektur U Ingenieurb\u00fcros",
    "sg:phone":"+41 18307140",
    "sg:postcode":"8304",
    "sg:province":"Z\u00fcrich",
    "wof:name":"Jan Richard De Fries Ingenieurb\u00fcro",
    "wof:placetype":"venue"
},
  "geometry": {"coordinates":[8.604905,47.41256],"type":"Point"}
}