{
  "type": "Feature",
  "properties": {
    "iso:country":"CH",
    "sg:address":"Belfaux",
    "sg:city":"Belfaux",
    "sg:orig_category":"Architektur U Ingenieurb\u00fcros",
    "sg:postcode":"1782",
    "sg:province":"Fribourg",
    "wof:name":"Arba't S\u00e0rl",
    "wof:placetype":"venue"
},
  "geometry": {"coordinates":[7.10603,46.82029],"type":"Point"}
}