{
  "type": "Feature",
  "properties": {
    "iso:country":"CH",
    "sg:address":"Gsteigstrasse 3780 Gruben B. Gstaad. Postfach",
    "sg:city":"Gstaad",
    "sg:orig_category":"Herstellung von Konstruktionsteilen, Fertigbauteilen U Ausbauelementen aus Holz",
    "sg:phone":"+41 71677567",
    "sg:postcode":"3780",
    "sg:province":"Bern",
    "wof:name":"Gyger W.",
    "wof:placetype":"venue"
},
  "geometry": {"coordinates":[7.2863688469,46.4651412964],"type":"Point"}
}