{
  "type": "Feature",
  "properties": {
    "iso:country":"CH",
    "sg:address":"Bundesstrasse 7",
    "sg:city":"Zug",
    "sg:orig_category":"Unclassifiable Establishments",
    "sg:phone":"+41 41 760 27 57",
    "sg:postcode":"6300",
    "sg:province":"Zug",
    "wof:name":"Tradevision Holding Ag",
    "wof:placetype":"venue"
},
  "geometry": {"coordinates":[8.513379097,47.1713905334],"type":"Point"}
}