{
  "type": "Feature",
  "properties": {
    "iso:country":"CH",
    "sg:address":"Langr\u00fctistrasse 103",
    "sg:city":"D\u00fcrnten",
    "sg:orig_category":"Interessenvertretungen",
    "sg:postcode":"8635",
    "sg:province":"Z\u00fcrich",
    "wof:name":"Patronale Stiftung Des Kantonalturnverbandes Z\u00fcrich",
    "wof:placetype":"venue"
},
  "geometry": {"coordinates":[8.877743721,47.2750396729],"type":"Point"}
}