{
  "type": "Feature",
  "properties": {
    "iso:country":"CH",
    "sg:address":"2203",
    "sg:city":"Rochefort",
    "sg:orig_category":"Primarschulen",
    "sg:phone":"+41 32 855 10 20",
    "sg:postcode":"2203",
    "wof:name":"Ecole Primaire",
    "wof:placetype":"venue"
},
  "geometry": {"coordinates":[-0.9587000012,45.9348182678],"type":"Point"}
}