{
  "type": "Feature",
  "properties": {
    "iso:country":"CH",
    "sg:address":"Binzhaldenstrasse 1",
    "sg:city":"Unterkulm",
    "sg:orig_category":"Nationale Postdienste",
    "sg:phone":"+41 62 776 13 50",
    "sg:postcode":"5726",
    "sg:province":"Aargau",
    "wof:name":"Die Schweizerische Post",
    "wof:placetype":"venue"
},
  "geometry": {"coordinates":[8.1130895615,47.3128471375],"type":"Point"}
}