{
  "type": "Feature",
  "properties": {
    "iso:country":"CH",
    "sg:address":"Engelgasse 2",
    "sg:city":"Rorschach",
    "sg:orig_category":"Herstellung von Seifen, Wasch U Reinigungsmitteln",
    "sg:phone":"+41 71 845 15 55",
    "sg:postcode":"9400",
    "sg:province":"St. Gallen",
    "wof:name":"Easy Clean Keller P.",
    "wof:placetype":"venue"
},
  "geometry": {"coordinates":[9.4934186935,47.478061676],"type":"Point"}
}