{
  "type": "Feature",
  "properties": {
    "iso:country":"CH",
    "sg:address":"Boulevard De P\u00e9rolles 5 1700 Fribourg Case Postale 571",
    "sg:city":"Fribourg",
    "sg:orig_category":"Versicherungen Generalagenturen",
    "sg:phone":"+41 26 347 33 33",
    "sg:postcode":"1701",
    "sg:province":"Fribourg",
    "wof:name":"La Mobili\u00e8re Assurances & Pr\u00e9voyance",
    "wof:placetype":"venue"
},
  "geometry": {"coordinates":[7.1515917778,46.8015441895],"type":"Point"}
}