{
  "type": "Feature",
  "properties": {
    "iso:country":"CH",
    "sg:address":"R\u00fcmelinsplatz 15",
    "sg:city":"Basel",
    "sg:orig_category":"Detailhandel mit Tabakwaren",
    "sg:phone":"+41 61 261 16 76",
    "sg:postcode":"4001",
    "sg:province":"Basel-Stadt",
    "wof:name":"Pfyffe Laade Wenk Ronald Fachgesch\u00e4ft F. Tabakwaren",
    "wof:placetype":"venue"
},
  "geometry": {"coordinates":[7.5872731209,47.5567398071],"type":"Point"}
}