{
  "type": "Feature",
  "properties": {
    "iso:country":"CH",
    "sg:address":"Avenue Des Glariers",
    "sg:city":"Aigle",
    "sg:orig_category":"Restaurants Schwimmb\u00e4der",
    "sg:phone":"+41 24 466 16 20",
    "sg:postcode":"1860",
    "sg:province":"Vaud",
    "wof:name":"Piscine & Patinoire St\u00e9 Coop.",
    "wof:placetype":"venue"
},
  "geometry": {"coordinates":[6.9661478996,46.3215332031],"type":"Point"}
}