{
  "type": "Feature",
  "properties": {
    "iso:country":"CH",
    "sg:address":"6674 Someo. Postfach",
    "sg:city":"Someo",
    "sg:orig_category":"Detailhandel mit elektrischen Haushalts-,Radio U Fernsehger\u00e4ten sowie Musikinstrumenten",
    "sg:postcode":"6674",
    "sg:province":"Ticino",
    "wof:name":"Pezzoni Flavio.",
    "wof:placetype":"venue"
},
  "geometry": {"coordinates":[8.6663808823,46.2863388062],"type":"Point"}
}