{
  "type": "Feature",
  "properties": {
    "iso:country":"CH",
    "sg:address":"L\u00e4tti 144",
    "sg:city":"M\u00fcnchenbuchsee",
    "sg:orig_category":"D\u00e4mmung gegen K\u00e4lte, W\u00e4rme, Schall U Ersch\u00fctterung Herstellung von sonstigen Produkten aus nichtmeta",
    "sg:phone":"+41 31 869 66 00",
    "sg:postcode":"3053",
    "sg:province":"Bern",
    "wof:name":"Rentsch Ag Isolierungen",
    "wof:placetype":"venue"
},
  "geometry": {"coordinates":[7.4505391121,47.0214271545],"type":"Point"}
}