{
  "type": "Feature",
  "properties": {
    "iso:country":"CH",
    "sg:address":"Petit-ch\u00eane Rue Du 36",
    "sg:city":"Lausanne",
    "sg:orig_category":"Reiseb\u00fcros U Reiseveranstalter",
    "sg:phone":"+41 33 733 30 32",
    "sg:postcode":"1003",
    "sg:province":"Vaud",
    "wof:name":"Sita Reiseb\u00fcro Ag",
    "wof:placetype":"venue"
},
  "geometry": {"coordinates":[7.4391560555,46.4521217346],"type":"Point"}
}