{
  "type": "Feature",
  "properties": {
    "iso:country":"CH",
    "sg:address":"Margarethenstrasse 24",
    "sg:city":"Sissach",
    "sg:orig_category":"Sportvereine Unihockey",
    "sg:phone":"+41 61 971 55 70",
    "sg:postcode":"4450",
    "sg:province":"Basel-Landschaft",
    "wof:name":"Uhc Sissach",
    "wof:placetype":"venue"
},
  "geometry": {"coordinates":[7.8101968765,47.4605789185],"type":"Point"}
}