{
  "type": "Feature",
  "properties": {
    "iso:country":"CH",
    "sg:address":"Neuhofstrasse 4",
    "sg:city":"Baar",
    "sg:orig_category":"Interessenvertretungen",
    "sg:postcode":"6340",
    "sg:province":"Zug",
    "wof:name":"Belch-stiftung",
    "wof:placetype":"venue"
},
  "geometry": {"coordinates":[8.5826339722,47.3222732544],"type":"Point"}
}