{
  "type": "Feature",
  "properties": {
    "iso:country":"CH",
    "sg:address":"Ringstrasse 9 4123 Allschwil. Postfach",
    "sg:city":"Allschwil",
    "sg:orig_category":"Sonstige mit der Informatik verbundene T\u00e4tigkeiten",
    "sg:phone":"+41 61 483 11 88",
    "sg:postcode":"4123",
    "sg:province":"Basel-Landschaft",
    "wof:name":"Auricom Gmbh Dienstleistungen Im Bereich Edv, Bes. Internet Usw",
    "wof:placetype":"venue"
},
  "geometry": {"coordinates":[7.5439038277,47.5578765869],"type":"Point"}
}