{
  "type": "Feature",
  "properties": {
    "iso:country":"CH",
    "sg:address":"Stockerstrasse 16",
    "sg:city":"Horgen",
    "sg:orig_category":"Detailhandel mit Brennstoffen U Heizmaterial Grosshandel mit festen Brennstoffen U Mineral\u00f6lerzeugni",
    "sg:phone":"+41 79 667 34 28",
    "sg:postcode":"8810",
    "sg:province":"Z\u00fcrich",
    "wof:name":"Wettstein H.",
    "wof:placetype":"venue"
},
  "geometry": {"coordinates":[8.595083,47.260513],"type":"Point"}
}