{
  "type": "Feature",
  "properties": {
    "iso:country":"CH",
    "sg:address":"Baugesch\u00e4ft",
    "sg:city":"Eriswil",
    "sg:orig_category":"Allgemeiner Hoch U Tiefbau",
    "sg:postcode":"4952",
    "sg:province":"Bern",
    "wof:name":"W. Kr\u00e4henb\u00fchl",
    "wof:placetype":"venue"
},
  "geometry": {"coordinates":[7.850645,47.07909],"type":"Point"}
}