{
  "type": "Feature",
  "properties": {
    "iso:country":"CH",
    "sg:address":"Niesenweg 7",
    "sg:city":"M\u00fcnsingen",
    "sg:orig_category":"Detailhandel mit Brot, Back U S\u00fcsswaren",
    "sg:phone":"+41 31 721 42 39",
    "sg:postcode":"3110",
    "sg:province":"Bern",
    "wof:name":"Beat Winkler B\u00e4ckerei-konditorei",
    "wof:placetype":"venue"
},
  "geometry": {"coordinates":[7.555857,46.872559],"type":"Point"}
}