{
  "type": "Feature",
  "properties": {
    "iso:country":"CH",
    "sg:address":"Rue De La Place-d'armes 7",
    "sg:city":"Neuch\u00e2tel",
    "sg:orig_category":"Kinderkrippen U horte",
    "sg:phone":"+41 32 724 44 71",
    "sg:postcode":"2000",
    "sg:province":"Neuch\u00e2tel",
    "wof:name":"Cr\u00e8che La Barbouille",
    "wof:placetype":"venue"
},
  "geometry": {"coordinates":[6.9300518036,46.98960495],"type":"Point"}
}