{
  "type": "Feature",
  "properties": {
    "iso:country":"CH",
    "sg:address":"Dornacherstrasse 21 4500 Solothurn. Postfach",
    "sg:city":"Solothurn",
    "sg:orig_category":"Erbringung von Dienstleistungen f\u00fcr Unternehmen",
    "sg:postcode":"4500",
    "sg:province":"Solothurn",
    "wof:name":"Ego Design Gmbh Mode, Lifestyleunternehmen Usw",
    "wof:placetype":"venue"
},
  "geometry": {"coordinates":[7.5396990776,47.2041664124],"type":"Point"}
}