{
  "type": "Feature",
  "properties": {
    "iso:country":"CH",
    "sg:address":"1692",
    "sg:city":"Massonnens",
    "sg:orig_category":"G\u00fcterbef\u00f6rderung im Strassenverkehr",
    "sg:phone":"+41 26 653 12 91",
    "sg:postcode":"1692",
    "sg:province":"Fribourg",
    "wof:name":"Berset Michel",
    "wof:placetype":"venue"
},
  "geometry": {"coordinates":[6.9777002335,46.6972312927],"type":"Point"}
}