{
  "type": "Feature",
  "properties": {
    "iso:country":"CH",
    "sg:address":"Gerstenstrasse 2 5430 Wettingen. Postfach",
    "sg:city":"Wettingen",
    "sg:orig_category":"Herstellung von Mess U Kontrollinstrumenten U vorrichtungen",
    "sg:phone":"+41 56 426 75 24",
    "sg:postcode":"5430",
    "sg:province":"Aargau",
    "wof:name":"Perret Safety Beratung U. Physikalische Berechnungen Auf Dem Gebiet Des Strahlenschutzes U. Der Technischen Sicherheit",
    "wof:placetype":"venue"
},
  "geometry": {"coordinates":[8.3197879791,47.4581336975],"type":"Point"}
}