{
  "type": "Feature",
  "properties": {
    "iso:country":"CH",
    "sg:address":"1279",
    "sg:city":"Chavannes-de-bogis",
    "sg:classifiers":[
        {
            "category":"Restaurant",
            "type":"Food & Drink"
        }
    ],
    "sg:phone":"+41 55 211 01 01",
    "sg:postcode":"1279",
    "sg:province":"Vaud",
    "wof:name":"Restaurant Manora",
    "wof:placetype":"venue"
},
  "geometry": {"coordinates":[8.8190393448,47.2265853882],"type":"Point"}
}