{
  "type": "Feature",
  "properties": {
    "iso:country":"CH",
    "sg:address":"Chemin Des Sports 2",
    "sg:city":"Gen\u00e8ve",
    "sg:orig_category":"Diskotheken, Dancings, Night Clubs",
    "sg:phone":"+41 22 345 19 90",
    "sg:postcode":"1203",
    "sg:province":"Gen\u00e8ve",
    "wof:name":"Dancing Don-juan",
    "wof:placetype":"venue"
},
  "geometry": {"coordinates":[6.1142802238,46.2055702209],"type":"Point"}
}