{
  "type": "Feature",
  "properties": {
    "iso:country":"CH",
    "sg:address":"Route Des Colantzes 1965 Chandolin-savi\u00e8se. Postfach",
    "sg:city":"Chandolin-savi\u00e8se",
    "sg:orig_category":"Grosshandel mit Getr\u00e4nken",
    "sg:postcode":"1965",
    "sg:province":"Valais",
    "wof:name":"Cave Les Colantzes S\u00e0rl",
    "wof:placetype":"venue"
},
  "geometry": {"coordinates":[7.3452091217,46.2439918518],"type":"Point"}
}