{
  "type": "Feature",
  "properties": {
    "addr:full":"Via Al Parco 30 Orselina Ticino 6644",
    "addr:housenumber":"30",
    "addr:postcode":"6644",
    "addr:street":"Via Al Parco",
    "iso:country":"CH",
    "sg:address":"Via Al Parco 30",
    "sg:city":"Orselina",
    "sg:classifiers":[
        {
            "category":"Bars & Pubs",
            "type":"Food & Drink"
        }
    ],
    "sg:phone":"+41 91 743 36 44",
    "sg:postcode":"6644",
    "sg:province":"Ticino",
    "sg:tags":[
        "restaurant"
    ],
    "wof:name":"Osteria Bellavista",
    "wof:placetype":"venue"
},
  "geometry": {"coordinates":[8.800684,46.180012],"type":"Point"}
}