{
  "type": "Feature",
  "properties": {
    "iso:country":"CH",
    "sg:address":"Rue De La Verrerie 1 1870 Monthey. Postfach 224",
    "sg:city":"Sitten",
    "sg:orig_category":"Galvanische Betriebe Herstellung von Metallkonstruktionen",
    "sg:phone":"+41 27 327 25 00",
    "sg:postcode":"1950",
    "sg:province":"Valais",
    "wof:name":"Les Creusets Sa, Ateliers De Constructions \u00e9lectro-m\u00e9caniques",
    "wof:placetype":"venue"
},
  "geometry": {"coordinates":[6.951816082,46.2536392212],"type":"Point"}
}