{
  "type": "Feature",
  "properties": {
    "iso:country":"CH",
    "sg:address":"Wolfzangenstrasse 42",
    "sg:city":"Neftenbach",
    "sg:orig_category":"Rechtsberatung",
    "sg:postcode":"8413",
    "sg:province":"Z\u00fcrich",
    "wof:name":"Enerka-gmbh",
    "wof:placetype":"venue"
},
  "geometry": {"coordinates":[8.6727752686,47.5218467712],"type":"Point"}
}