{
  "type": "Feature",
  "properties": {
    "iso:country":"CH",
    "sg:address":"Sch\u00f6neckstrasse 7",
    "sg:city":"Emmetten",
    "sg:orig_category":"Detailhandel mit Teppichen",
    "sg:phone":"+41 41 620 08 44",
    "sg:postcode":"6376",
    "sg:province":"Nidwalden",
    "wof:name":"Eberhart Herrmann K\u00f6nig Der Teppichkunst",
    "wof:placetype":"venue"
},
  "geometry": {"coordinates":[8.5062847137,46.9588623047],"type":"Point"}
}