{
  "type": "Feature",
  "properties": {
    "addr:full":"Frenkendorf Basel-Landschaft 4402",
    "addr:postcode":"4402",
    "iso:country":"CH",
    "sg:city":"Frenkendorf",
    "sg:orig_category":"Freizeit, Erotik",
    "sg:postcode":"4402",
    "sg:province":"Basel-Landschaft",
    "wof:name":"Crazy Network Gmbh",
    "wof:placetype":"venue"
},
  "geometry": {"coordinates":[7.715121,47.502884],"type":"Point"}
}