{
  "type": "Feature",
  "properties": {
    "iso:country":"CH",
    "sg:address":"Fo Strasse",
    "sg:city":"Naters",
    "sg:orig_category":"Herstellung von Maschinen f\u00fcr die Nahrungsmittel, Getr\u00e4nkeherstellung U die Tabakverarbeitung",
    "sg:phone":"+41 27 924 10 92",
    "sg:postcode":"3904",
    "sg:province":"Valais",
    "wof:name":"Ruckstuhl Patrick",
    "wof:placetype":"venue"
},
  "geometry": {"coordinates":[7.9877901077,46.3243141174],"type":"Point"}
}