{
  "type": "Feature",
  "properties": {
    "iso:country":"CH",
    "sg:address":"D\u00f6beligut 5",
    "sg:city":"Oftringen",
    "sg:orig_category":"Grosshandel mit sonstigen Konsumg\u00fctern Handelsvermittlung von Textilien, Bekleidung, Schuhen U Leder",
    "sg:phone":"+41 62 797 77 44",
    "sg:postcode":"4665",
    "sg:province":"Aargau",
    "wof:name":"Schmidhauser",
    "wof:placetype":"venue"
},
  "geometry": {"coordinates":[7.9436349869,47.2957801819],"type":"Point"}
}