{
  "type": "Feature",
  "properties": {
    "iso:country":"CH",
    "sg:address":"Via Luigi Lavizzari 18 6850 Mendrisio. Postfach",
    "sg:city":"Mendrisio",
    "sg:orig_category":"Unclassifiable Establishments",
    "sg:postcode":"6850",
    "sg:province":"Ticino",
    "wof:name":"Medi Terraneo Holding Sa",
    "wof:placetype":"venue"
},
  "geometry": {"coordinates":[8.9871683121,45.8697738647],"type":"Point"}
}