{
  "type": "Feature",
  "properties": {
    "iso:country":"CH",
    "sg:address":"Seegarten-marina. 3700 Spiez. Postfach",
    "sg:city":"Spiez",
    "sg:classifiers":[
        {
            "category":"Travel",
            "subcategory":"Hotels & Motels",
            "type":"Entertainment"
        }
    ],
    "sg:postcode":"3700",
    "sg:province":"Bern",
    "sg:tags":[
        "hotels",
        "mit",
        "restaurant"
    ],
    "wof:name":"Seegarten-hotel Spiez, M. Beutler",
    "wof:placetype":"venue"
},
  "geometry": {"coordinates":[7.6748552322,46.6898498535],"type":"Point"}
}