{
  "type": "Feature",
  "properties": {
    "iso:country":"CH",
    "sg:address":"Rue Du Grand-pr\u00e9 47",
    "sg:city":"Gen\u00e8ve",
    "sg:orig_category":"Reparatur von Schuhen U Lederwaren",
    "sg:phone":"+41 22 734 22 97",
    "sg:postcode":"1202",
    "sg:province":"Gen\u00e8ve",
    "wof:name":"Cordonnerie Da Silva",
    "wof:placetype":"venue"
},
  "geometry": {"coordinates":[6.1333842278,46.214881897],"type":"Point"}
}