{
  "type": "Feature",
  "properties": {
    "iso:country":"CH",
    "sg:address":"Weinfelderstrasse 30 8580 Amriswil. Postfach",
    "sg:city":"Amriswil",
    "sg:orig_category":"Grosshandel mit Nahrungsmitteln, Getr\u00e4nken U Tabakwaren ohne ausgepr\u00e4gten Schwerpunkt",
    "sg:postcode":"8580",
    "sg:province":"Thurgau",
    "wof:name":"Pick Pay Partner Amriswil, Inhaber Djeric M.",
    "wof:placetype":"venue"
},
  "geometry": {"coordinates":[9.2937164307,47.5453834534],"type":"Point"}
}