{
  "type": "Feature",
  "properties": {
    "iso:country":"CH",
    "sg:address":"Haldenstrasse 2",
    "sg:city":"T\u00fcbach",
    "sg:orig_category":"Elektro- and elektronische Maschinen Grosshandel",
    "sg:phone":"+41 71 841 35 32",
    "sg:postcode":"9327",
    "sg:province":"St. Gallen",
    "wof:name":"Ernst Steiner Registrierkassen",
    "wof:placetype":"venue"
},
  "geometry": {"coordinates":[9.4511222839,47.4856071472],"type":"Point"}
}