{
  "type": "Feature",
  "properties": {
    "iso:country":"CH",
    "sg:address":"Rue Des C\u00e8dres 4",
    "sg:city":"Neuch\u00e2tel",
    "sg:orig_category":"Handel mit Automobilteilen U Zubeh\u00f6r Handelsvermittlung U Grosshandel mit Automobilteilen U Zubeh\u00f6r",
    "sg:phone":"+41 32 724 36 70",
    "sg:postcode":"2000",
    "sg:province":"Neuch\u00e2tel",
    "wof:name":"Continental Turbo Cts Sa",
    "wof:placetype":"venue"
},
  "geometry": {"coordinates":[6.9564161301,47.0035552979],"type":"Point"}
}