{
  "type": "Feature",
  "properties": {
    "iso:country":"CH",
    "sg:address":"Rieden 2",
    "sg:city":"Stans",
    "sg:orig_category":"Handel mit Motorr\u00e4dern, Teilen U Zubeh\u00f6r Instandhaltung U Reparatur von Motorr\u00e4dern",
    "sg:phone":"+41 41 610 01 66",
    "sg:postcode":"6370",
    "sg:province":"Nidwalden",
    "wof:name":"Mo Tec Zweirad Gmbh",
    "wof:placetype":"venue"
},
  "geometry": {"coordinates":[8.383099556,46.9649162292],"type":"Point"}
}