{
  "type": "Feature",
  "properties": {
    "iso:country":"CH",
    "sg:address":"Weinbergstrasse 4",
    "sg:city":"Baar",
    "sg:orig_category":"Grosshandel mit B\u00fcromaschinen Grosshandel mit Datenverarbeitungsger\u00e4ten",
    "sg:phone":"+41 41 760 91 21",
    "sg:postcode":"6340",
    "sg:province":"Zug",
    "wof:name":"Dettling Trade Ag",
    "wof:placetype":"venue"
},
  "geometry": {"coordinates":[8.5363769531,47.1849060059],"type":"Point"}
}