{
  "type": "Feature",
  "properties": {
    "iso:country":"CH",
    "sg:address":"Bodenwiesenweg 270 8232 Merishausen. Postfach 19",
    "sg:city":"Merishausen",
    "sg:orig_category":"Mechanische Werkst\u00e4tten",
    "sg:phone":"+41 52 653 14 54",
    "sg:postcode":"8232",
    "sg:province":"Schaffhausen",
    "wof:name":"Erich Tanner Garage & Mech.werkstatt",
    "wof:placetype":"venue"
},
  "geometry": {"coordinates":[8.6110801697,47.7586288452],"type":"Point"}
}