{
  "type": "Feature",
  "properties": {
    "iso:country":"CH",
    "sg:address":"Ch\u00e2telstrasse 14",
    "sg:city":"Aadorf",
    "sg:orig_category":"Fachdetailhandel in Verkaufsr\u00e4umen",
    "sg:phone":"+41 52 365 16 16",
    "sg:postcode":"8355",
    "sg:province":"Thurgau",
    "wof:name":"Keller Maschi Modernes Gestalten Mit Blumen",
    "wof:placetype":"venue"
},
  "geometry": {"coordinates":[8.9024333954,47.4889793396],"type":"Point"}
}