{
  "type": "Feature",
  "properties": {
    "iso:country":"CH",
    "sg:address":"Castel-savoy",
    "sg:city":"Chailly-montreux",
    "sg:orig_category":"Sportvereine Ballsport Tischtennis",
    "sg:phone":"+41 21 964 65 04",
    "sg:postcode":"1816",
    "sg:province":"Vaud",
    "wof:name":"Ctt Montreux-riviera",
    "wof:placetype":"venue"
},
  "geometry": {"coordinates":[6.8924908638,46.4530982971],"type":"Point"}
}