{
  "type": "Feature",
  "properties": {
    "iso:country":"CH",
    "sg:address":"Trittligasse 19",
    "sg:city":"Z\u00fcrich",
    "sg:orig_category":"Detailhandel mit Antiquit\u00e4ten U Gebrauchtwaren in Verkaufsr\u00e4umen",
    "sg:phone":"+41 12518550",
    "sg:postcode":"8001",
    "sg:province":"Z\u00fcrich",
    "wof:name":"Laube August, Inhaber Laube & Co, Buch Und Kunst-antiquariat",
    "wof:placetype":"venue"
},
  "geometry": {"coordinates":[8.546096,47.369839],"type":"Point"}
}