{
  "type": "Feature",
  "properties": {
    "iso:country":"CH",
    "sg:address":"Rue Centrale 5 1003 Lausanne Case Postale",
    "sg:city":"Lausanne",
    "sg:orig_category":"Vermietung U Verpachtung von eigenen Immobilien Vermittlung von Immobilien",
    "sg:phone":"+41 21 318 82 82",
    "sg:postcode":"1002",
    "sg:province":"Vaud",
    "wof:name":"Vente Et Placements Immobiliers Sa",
    "wof:placetype":"venue"
},
  "geometry": {"coordinates":[6.6323571205,46.5207176208],"type":"Point"}
}