{
  "type": "Feature",
  "properties": {
    "iso:country":"CH",
    "sg:address":"Im Saali 251",
    "sg:city":"Heiligenschwendi",
    "sg:classifiers":[
        {
            "category":"Travel",
            "subcategory":"Hotels & Motels",
            "type":"Entertainment"
        }
    ],
    "sg:phone":"+41 33 243 13 10",
    "sg:postcode":"3625",
    "sg:province":"Bern",
    "sg:tags":[
        "hotels",
        "mit",
        "restaurant"
    ],
    "wof:name":"Hotel Bellevue",
    "wof:placetype":"venue"
},
  "geometry": {"coordinates":[7.6812310219,46.7459983826],"type":"Point"}
}