{
  "type": "Feature",
  "properties": {
    "addr:full":"Rietstrasse 30 Schaffhausen Schaffhausen 8200",
    "addr:housenumber":"30",
    "addr:postcode":"8200",
    "addr:street":"Rietstrasse",
    "iso:country":"CH",
    "sg:address":"Rietstrasse 30",
    "sg:city":"Schaffhausen",
    "sg:orig_category":"Arztpraxen",
    "sg:phone":"+41 52 620 15 05",
    "sg:postcode":"8200",
    "sg:province":"Schaffhausen",
    "wof:name":"Dr.med.edgar Funke Spezialarzt Fmh",
    "wof:placetype":"venue"
},
  "geometry": {"coordinates":[8.623393,47.700848],"type":"Point"}
}