{
  "type": "Feature",
  "properties": {
    "iso:country":"CH",
    "sg:address":"Br\u00fcnnenstrasse 61a 3018 Bern. Postfach",
    "sg:city":"Bern",
    "sg:orig_category":"Grosshandel mit Nahrungsmitteln, Getr\u00e4nken U Tabakwaren ohne ausgepr\u00e4gten Schwerpunkt",
    "sg:postcode":"3018",
    "sg:province":"Bern",
    "wof:name":"Rolli Frau E. Lebensmittelgesch\u00e4ft.",
    "wof:placetype":"venue"
},
  "geometry": {"coordinates":[7.3854489326,46.9439926147],"type":"Point"}
}