{
  "type": "Feature",
  "properties": {
    "iso:country":"CH",
    "sg:address":"Hungerb\u00fcelstrasse 22",
    "sg:city":"Frauenfeld",
    "sg:orig_category":"Ingenieurb\u00fcros Umwelttechnik and \u00d6kologie",
    "sg:phone":"+41 52 724 97 24",
    "sg:postcode":"8500",
    "sg:province":"Thurgau",
    "wof:name":"Ufa Ag Ufa-beratungsdienst",
    "wof:placetype":"venue"
},
  "geometry": {"coordinates":[8.8733463287,47.5624771118],"type":"Point"}
}