{
  "type": "Feature",
  "properties": {
    "iso:country":"CH",
    "sg:address":"T\u00fcbingen Place De 2",
    "sg:city":"Monthey",
    "sg:orig_category":"Unclassifiable Establishments",
    "sg:postcode":"1870",
    "sg:province":"Valais",
    "wof:name":"Boutique Chrysalide S\u00e0rl",
    "wof:placetype":"venue"
},
  "geometry": {"coordinates":[6.9472341537,46.2521438599],"type":"Point"}
}