{
  "type": "Feature",
  "properties": {
    "iso:country":"CH",
    "sg:address":"Via Pierino Tatti 3",
    "sg:city":"Bellinzona",
    "sg:orig_category":"Grosshandel mit B\u00fcromaschinen Grosshandel mit Datenverarbeitungsger\u00e4ten",
    "sg:phone":"+41 41 810 27 17",
    "sg:postcode":"6500",
    "sg:province":"Ticino",
    "wof:name":"St\u00f6cklin Edv",
    "wof:placetype":"venue"
},
  "geometry": {"coordinates":[8.6681747437,47.0146865845],"type":"Point"}
}