{
  "type": "Feature",
  "properties": {
    "iso:country":"CH",
    "sg:address":"1965",
    "sg:city":"Chandolin-savi\u00e8se",
    "sg:orig_category":"Vereine Musik/Blasmusik",
    "sg:phone":"+41 24 494 14 62",
    "sg:postcode":"1965",
    "sg:province":"Valais",
    "wof:name":"Fanfare Rose Des Alpes",
    "wof:placetype":"venue"
},
  "geometry": {"coordinates":[7.3385391235,46.2504730225],"type":"Point"}
}