{
  "type": "Feature",
  "properties": {
    "iso:country":"CH",
    "sg:address":"Le Borget",
    "sg:city":"Oulens-echallens",
    "sg:orig_category":"Elektrizit\u00e4tsversorgung",
    "sg:phone":"+41 21 882 55 24",
    "sg:postcode":"1041",
    "sg:province":"Vaud",
    "wof:name":"Solenergy, Philippe Nicole",
    "wof:placetype":"venue"
},
  "geometry": {"coordinates":[6.576415062,46.6471366882],"type":"Point"}
}