{
  "type": "Feature",
  "properties": {
    "iso:country":"CH",
    "sg:address":"Bahnhofstrasse 1",
    "sg:city":"Berom\u00fcnster",
    "sg:orig_category":"Einbau von Schreinerwaren Herstellung von M\u00f6beln",
    "sg:phone":"+41 17619904",
    "sg:postcode":"6215",
    "sg:province":"Luzern",
    "wof:name":"Schreinerei Markus Gehr",
    "wof:placetype":"venue"
},
  "geometry": {"coordinates":[8.4471340179,47.2702560425],"type":"Point"}
}