{
  "type": "Feature",
  "properties": {
    "iso:country":"CH",
    "sg:address":"3812",
    "sg:city":"Wilderswil",
    "sg:classifiers":[
        {
            "category":"Travel",
            "subcategory":"Hotels & Motels",
            "type":"Entertainment"
        }
    ],
    "sg:phone":"+41 33 828 31 51",
    "sg:postcode":"3812",
    "sg:province":"Bern",
    "sg:tags":[
        "hotels",
        "mit",
        "restaurant"
    ],
    "wof:name":"Hotel B\u00e4ren",
    "wof:placetype":"venue"
},
  "geometry": {"coordinates":[7.8673701286,46.6651268005],"type":"Point"}
}