{
  "type": "Feature",
  "properties": {
    "iso:country":"CH",
    "sg:address":"Ruopigenstrasse 6",
    "sg:city":"Reussb\u00fchl",
    "sg:orig_category":"Fahrschulen, Flugschulen",
    "sg:postcode":"6015",
    "sg:province":"Luzern",
    "wof:name":"Guanzini Aldo, Ecole Mobile D'aviation G\u00e9n\u00e9rale",
    "wof:placetype":"venue"
},
  "geometry": {"coordinates":[6.7201547623,46.6814537048],"type":"Point"}
}