{
  "type": "Feature",
  "properties": {
    "iso:country":"CH",
    "sg:address":"Kirchbannstrasse 564 4703 Kestenholz. Postfach 41",
    "sg:city":"Kestenholz",
    "sg:orig_category":"Grosshandel mit sonstigen Halbwaren Herstellung von Schreibwaren U B\u00fcrobedarf aus Papier, Karton U P",
    "sg:phone":"+41 62 393 25 70",
    "sg:postcode":"4703",
    "sg:province":"Solothurn",
    "wof:name":"Flex-pac Ag",
    "wof:placetype":"venue"
},
  "geometry": {"coordinates":[7.7600598335,47.2832183838],"type":"Point"}
}