{
  "type": "Feature",
  "properties": {
    "iso:country":"CH",
    "sg:address":"Feldstrasse 1",
    "sg:city":"Urdorf",
    "sg:orig_category":"Detailhandel mit Fahrr\u00e4dern",
    "sg:phone":"+41 17345975",
    "sg:postcode":"8902",
    "sg:province":"Z\u00fcrich",
    "wof:name":"Rainer Baumann Velogesch\u00e4ft",
    "wof:placetype":"venue"
},
  "geometry": {"coordinates":[8.4269180298,47.3912734985],"type":"Point"}
}