{
  "type": "Feature",
  "properties": {
    "iso:country":"CH",
    "sg:address":"Bahnhofstrasse 23",
    "sg:city":"Zug",
    "sg:orig_category":"Finanzen, Investment",
    "sg:phone":"+41 41 720 44 11",
    "sg:postcode":"6301",
    "sg:province":"Zug",
    "wof:name":"Alpine Select Ag",
    "wof:placetype":"venue"
},
  "geometry": {"coordinates":[8.515671,47.169979],"type":"Point"}
}