{
  "type": "Feature",
  "properties": {
    "iso:country":"CH",
    "sg:address":"Britternstrasse 22 4583 Aetigkofen. Postfach",
    "sg:city":"Aetigkofen",
    "sg:orig_category":"Hardwareberatung",
    "sg:postcode":"4583",
    "sg:province":"Solothurn",
    "wof:name":"Balli Hard- Software Und Schulung",
    "wof:placetype":"venue"
},
  "geometry": {"coordinates":[7.4667849541,47.1251564026],"type":"Point"}
}