{
  "type": "Feature",
  "properties": {
    "iso:country":"CH",
    "sg:address":"T\u00f6sstalstrasse 163",
    "sg:city":"Turbenthal",
    "sg:classifiers":[
        {
            "category":"Travel",
            "subcategory":"Hotels & Motels",
            "type":"Entertainment"
        }
    ],
    "sg:phone":"+41 52 385 17 21",
    "sg:postcode":"8488",
    "sg:province":"Z\u00fcrich",
    "sg:tags":[
        "hotels",
        "mit",
        "restaurant"
    ],
    "wof:name":"Landgasthof Hotel B\u00e4ren Ag",
    "wof:placetype":"venue"
},
  "geometry": {"coordinates":[8.8461284637,47.4319343567],"type":"Point"}
}