{
  "type": "Feature",
  "properties": {
    "iso:country":"CH",
    "sg:address":"Wankdorffeldstrasse 102/b-348",
    "sg:city":"Bern",
    "sg:orig_category":"Detailhandel mit Metallwaren, Anstrichmitteln, Glaswaren, Bau U Heimwerkerbedarf",
    "sg:postcode":"3014",
    "sg:province":"Bern",
    "wof:name":"Hernandez Commercial-expansion-service",
    "wof:placetype":"venue"
},
  "geometry": {"coordinates":[7.4557619095,46.9643936157],"type":"Point"}
}