{
  "type": "Feature",
  "properties": {
    "iso:country":"CH",
    "sg:address":"Kanderstegstrasse 11",
    "sg:city":"Frutigen",
    "sg:classifiers":[
        {
            "category":"Insurance",
            "subcategory":"Insurance Agent",
            "type":"Services"
        }
    ],
    "sg:phone":"+41 33 671 14 71",
    "sg:postcode":"3714",
    "sg:province":"Bern",
    "sg:tags":[
        "versicherungsagenturen",
        "-broker"
    ],
    "wof:name":"Winterthur Versicherungen Agentur",
    "wof:placetype":"venue"
},
  "geometry": {"coordinates":[7.6464347839,46.5875167847],"type":"Point"}
}