{
  "type": "Feature",
  "properties": {
    "iso:country":"CH",
    "sg:address":"Berne Rue De 32 1201 Gen\u00e8ve. Postfach",
    "sg:city":"Gen\u00e8ve",
    "sg:orig_category":"Detektivb\u00fcros U \u00dcberwachung",
    "sg:postcode":"1201",
    "sg:province":"Gen\u00e8ve",
    "wof:name":"Afm-security Metin Patrouille, Geldtransport, Schutz, Sicherheitsdienst",
    "wof:placetype":"venue"
},
  "geometry": {"coordinates":[8.8683700562,47.2539100647],"type":"Point"}
}