{
  "type": "Feature",
  "properties": {
    "iso:country":"CH",
    "sg:address":"Rue Des Jonquilles 24",
    "sg:city":"Cernier",
    "sg:orig_category":"Tierarztpraxis",
    "sg:phone":"+41 32 853 13 73",
    "sg:postcode":"2053",
    "sg:province":"Neuch\u00e2tel",
    "wof:name":"Dr M\u00e9d. V\u00e9t. Michel Fellrath M\u00e9decin V\u00e9t\u00e9rinaire",
    "wof:placetype":"venue"
},
  "geometry": {"coordinates":[6.8943948746,47.0562400818],"type":"Point"}
}