{
  "type": "Feature",
  "properties": {
    "addr:full":"Waaghaus-passage 8 Bern Bern 3011",
    "addr:housenumber":"8",
    "addr:postcode":"3011",
    "addr:street":"Waaghaus-Passage;Bern",
    "iso:country":"CH",
    "sg:address":"Waaghaus-passage 8",
    "sg:city":"Bern",
    "sg:orig_category":"Arztpraxen",
    "sg:phone":"+41 31 311 55 25",
    "sg:postcode":"3011",
    "sg:province":"Bern",
    "wof:name":"Dr.med.alfred Weil Spezialarzt Fmh",
    "wof:placetype":"venue"
},
  "geometry": {"coordinates":[7.444042,46.948544],"type":"Point"}
}