{
  "type": "Feature",
  "properties": {
    "iso:country":"CH",
    "sg:address":"Hintere Dorfgasse 20",
    "sg:city":"G\u00fcmligen",
    "sg:orig_category":"Sprachschulen",
    "sg:phone":"+41 31 952 75 55",
    "sg:postcode":"3073",
    "sg:province":"Bern",
    "wof:name":"The British School",
    "wof:placetype":"venue"
},
  "geometry": {"coordinates":[7.5136198997,46.9342918396],"type":"Point"}
}