{
  "type": "Feature",
  "properties": {
    "iso:country":"CH",
    "sg:address":"Hallwylstrasse 21 3000 Bern. Postfach",
    "sg:city":"Bern",
    "sg:orig_category":"Interessenvertretungen",
    "sg:postcode":"3005",
    "sg:province":"Bern",
    "wof:name":"Iyengar-yoga-vereinigung-schweiz (iys)",
    "wof:placetype":"venue"
},
  "geometry": {"coordinates":[7.4513320923,46.9413108826],"type":"Point"}
}