{
  "type": "Feature",
  "properties": {
    "iso:country":"CH",
    "sg:address":"K\u00fcntwilerstrasse 50b",
    "sg:city":"Rotkreuz",
    "sg:orig_category":"Massagestudios",
    "sg:phone":"+41 26 494 32 12",
    "sg:postcode":"6343",
    "sg:province":"Zug",
    "wof:name":"Fredy Mahler Massagen",
    "wof:placetype":"venue"
},
  "geometry": {"coordinates":[7.214715004,46.7921676636],"type":"Point"}
}