{
  "type": "Feature",
  "properties": {
    "iso:country":"CH",
    "sg:address":"Baselstrasse 15",
    "sg:city":"Riehen",
    "sg:orig_category":"Sportschulen",
    "sg:phone":"+41 19306069",
    "sg:postcode":"4125",
    "sg:province":"Basel-Stadt",
    "wof:name":"Kampfkunstakademie R.krauer Herrn Markus B\u00fchlmann",
    "wof:placetype":"venue"
},
  "geometry": {"coordinates":[8.8035001755,47.3288803101],"type":"Point"}
}