{
  "type": "Feature",
  "properties": {
    "iso:country":"CH",
    "sg:address":"Moosstrasse 2",
    "sg:city":"G\u00fcmligen",
    "sg:orig_category":"Advokaturb\u00fcros",
    "sg:phone":"+41 31 952 79 82",
    "sg:postcode":"3073",
    "sg:province":"Bern",
    "wof:name":"Feldmann & Quinto",
    "wof:placetype":"venue"
},
  "geometry": {"coordinates":[7.504954,46.932652],"type":"Point"}
}