{
  "type": "Feature",
  "properties": {
    "iso:country":"CH",
    "sg:address":"Bas De Vuary 3",
    "sg:city":"Payerne",
    "sg:orig_category":"Elektrizit\u00e4tsversorgung Elektroinstallation",
    "sg:phone":"+41 26 660 22 57",
    "sg:postcode":"1530",
    "sg:province":"Vaud",
    "wof:name":"Ets Electricit\u00e9 T\u00e9l\u00e9phone Services S\u00e0rl",
    "wof:placetype":"venue"
},
  "geometry": {"coordinates":[6.934718132,46.8249893188],"type":"Point"}
}