{
  "type": "Feature",
  "properties": {
    "iso:country":"CH",
    "sg:address":"Buzibachstrasse 47",
    "sg:city":"Rothenburg",
    "sg:orig_category":"Fachdetailhandel in Verkaufsr\u00e4umen Grosshandel mit chemischen Erzeugnissen",
    "sg:phone":"+41 41 282 21 41",
    "sg:postcode":"6023",
    "sg:province":"Luzern",
    "wof:name":"Swiss Bio Organics F\u00e4ssler + Sochin",
    "wof:placetype":"venue"
},
  "geometry": {"coordinates":[8.2547197342,47.0902519226],"type":"Point"}
}