{
  "type": "Feature",
  "properties": {
    "iso:country":"CH",
    "sg:address":"Esc. Du Court-chemin 7",
    "sg:city":"Fribourg",
    "sg:classifiers":[
        {
            "category":"Restaurant",
            "type":"Food & Drink"
        }
    ],
    "sg:phone":"+41 26 322 85 99",
    "sg:postcode":"1700",
    "sg:province":"Fribourg",
    "wof:name":"Caf\u00e9 Du Lion D'or",
    "wof:placetype":"venue"
},
  "geometry": {"coordinates":[7.1741681099,46.8002319336],"type":"Point"}
}