{
  "type": "Feature",
  "properties": {
    "iso:country":"CH",
    "sg:address":"6527",
    "sg:city":"Lodrino",
    "sg:orig_category":"Softwareentwicklung U beratung",
    "sg:postcode":"6527",
    "sg:province":"Ticino",
    "wof:name":"Scanzio Informatica Di Scanzio Giovanna",
    "wof:placetype":"venue"
},
  "geometry": {"coordinates":[8.9811306,46.2996673584],"type":"Point"}
}