{
  "type": "Feature",
  "properties": {
    "iso:country":"CH",
    "sg:address":"Via Losanna 8",
    "sg:city":"Biasca",
    "sg:orig_category":"Grosshandel mit Eisenwaren sowie Installationsbedarf f\u00fcr Gas, Wasser U Heizung",
    "sg:phone":"+41 91 862 44 77",
    "sg:postcode":"6710",
    "sg:province":"Ticino",
    "wof:name":"Termosan Sa Materiali Impianti Sanitari",
    "wof:placetype":"venue"
},
  "geometry": {"coordinates":[8.9701128006,46.3559799194],"type":"Point"}
}