{
  "type": "Feature",
  "properties": {
    "iso:country":"CH",
    "sg:address":"Chemin Des L\u00e9ch\u00e8res 2",
    "sg:city":"Meyrin",
    "sg:classifiers":[
        {
            "category":"Manufacturing",
            "subcategory":"Printing",
            "type":"Manufacturing & Wholesale Goods"
        }
    ],
    "sg:phone":"+41 22 782 29 29",
    "sg:postcode":"1217",
    "sg:province":"Gen\u00e8ve",
    "sg:tags":[
        "publishing"
    ],
    "wof:name":"Reliure Sa",
    "wof:placetype":"venue"
},
  "geometry": {"coordinates":[6.0675787926,46.2223739624],"type":"Point"}
}