{
  "type": "Feature",
  "properties": {
    "iso:country":"CH",
    "sg:address":"Feldstrasse 23 4663 Aarburg. Postfach 28",
    "sg:city":"Aarburg",
    "sg:orig_category":"Grosshandel mit sonstigen Halbwaren Herstellung von Schreibwaren U B\u00fcrobedarf aus Papier, Karton U P",
    "sg:phone":"+41 71 944 14 55",
    "sg:postcode":"4663",
    "sg:province":"Aargau",
    "wof:name":"Plasan Ag",
    "wof:placetype":"venue"
},
  "geometry": {"coordinates":[9.1234006882,47.4656410217],"type":"Point"}
}