{
  "type": "Feature",
  "properties": {
    "iso:country":"CH",
    "sg:address":"Schlattweg 203",
    "sg:city":"Welschenrohr",
    "sg:orig_category":"Forstwirtschaft ohne Dienstleistungen in der Forstwirtschaft",
    "sg:phone":"+41 32 931 61 39",
    "sg:postcode":"4716",
    "sg:province":"Solothurn",
    "wof:name":"Leuenberger Willy",
    "wof:placetype":"venue"
},
  "geometry": {"coordinates":[6.7232618332,47.0443496704],"type":"Point"}
}