{
  "type": "Feature",
  "properties": {
    "iso:country":"CH",
    "sg:address":"Grives Route Des 85",
    "sg:city":"Granges-paccot",
    "sg:orig_category":"Unclassifiable Establishments",
    "sg:postcode":"1763",
    "sg:province":"Fribourg",
    "wof:name":"B\u00e4chler + G\u00fcttinger Ag",
    "wof:placetype":"venue"
},
  "geometry": {"coordinates":[7.5959148407,46.7431182861],"type":"Point"}
}