{
  "type": "Feature",
  "properties": {
    "iso:country":"CH",
    "sg:address":"Maison Rouge Rue De La 16",
    "sg:city":"Yverdon-les-bains",
    "sg:orig_category":"Architektur U Ingenieurb\u00fcros",
    "sg:phone":"+41 24 420 25 55",
    "sg:postcode":"1400",
    "sg:province":"Vaud",
    "wof:name":"Quadra Sa",
    "wof:placetype":"venue"
},
  "geometry": {"coordinates":[6.643583,46.779205],"type":"Point"}
}