{
  "type": "Feature",
  "properties": {
    "iso:country":"CH",
    "sg:address":"Chemin De Mancy 57",
    "sg:city":"Collonge-bellerive",
    "sg:orig_category":"Institutionen f\u00fcr Behinderte",
    "sg:phone":"+41 22 752 40 59",
    "sg:postcode":"1245",
    "sg:province":"Gen\u00e8ve",
    "wof:name":"Sgipa Atelier Prot\u00e9g\u00e9 Mancy",
    "wof:placetype":"venue"
},
  "geometry": {"coordinates":[6.2029919624,46.2476196289],"type":"Point"}
}