{
  "type": "Feature",
  "properties": {
    "iso:country":"CH",
    "sg:address":"Amaliengasse 4",
    "sg:city":"Einsiedeln",
    "sg:orig_category":"Detailhandel mit Antiquit\u00e4ten Detailhandel mit M\u00f6beln",
    "sg:phone":"+41 55 412 85 40",
    "sg:postcode":"8840",
    "sg:province":"Schwyz",
    "wof:name":"Huber Antiquit\u00e4ten & Einrichtungen",
    "wof:placetype":"venue"
},
  "geometry": {"coordinates":[8.748284,47.12653],"type":"Point"}
}