{
  "type": "Feature",
  "properties": {
    "addr:full":"Schlierenstrasse 14 Urdorf Z\u00fcrich 8902",
    "addr:housenumber":"14",
    "addr:postcode":"8902",
    "addr:street":"Schlierenstrasse",
    "iso:country":"CH",
    "sg:address":"Schlierenstrasse 14",
    "sg:city":"Urdorf",
    "sg:orig_category":"Allgemeiner Hoch U Tiefbau",
    "sg:postcode":"8902",
    "sg:province":"Z\u00fcrich",
    "wof:name":"Thommen Consulting Ag",
    "wof:placetype":"venue"
},
  "geometry": {"coordinates":[8.425281,47.391541],"type":"Point"}
}