{
  "type": "Feature",
  "properties": {
    "iso:country":"CH",
    "sg:address":"6802",
    "sg:city":"Rivera",
    "sg:orig_category":"Grosshandel mit Erzen U Metallen Grosshandel mit pharmazeutischen Erzeugnissen, medizinischen U orth",
    "sg:phone":"+41 91 946 13 75",
    "sg:postcode":"6802",
    "sg:province":"Ticino",
    "wof:name":"Piero & Ernani Gervasoni Rappresentanze",
    "wof:placetype":"venue"
},
  "geometry": {"coordinates":[8.9231395721,46.1164894104],"type":"Point"}
}