{
  "type": "Feature",
  "properties": {
    "iso:country":"CH",
    "sg:address":"Les Moilettes 1610 Ch\u00e2tillens. Postfach",
    "sg:city":"Ch\u00e2tillens",
    "sg:orig_category":"Herstellung von Konstruktionsteilen, Fertigbauteilen U Ausbauelementen aus Holz",
    "sg:postcode":"1610",
    "sg:province":"Vaud",
    "wof:name":"Rittener Roland",
    "wof:placetype":"venue"
},
  "geometry": {"coordinates":[6.7907562256,46.5559883118],"type":"Point"}
}