{
  "type": "Feature",
  "properties": {
    "iso:country":"CH",
    "sg:address":"Kanalstrasse 31",
    "sg:city":"B\u00fcrglen",
    "sg:orig_category":"Filter Frames",
    "sg:phone":"+41 71 633 32 33",
    "sg:postcode":"8575",
    "sg:province":"Thurgau",
    "wof:name":"Alfred Nater Metallbau-schlosserei",
    "wof:placetype":"venue"
},
  "geometry": {"coordinates":[9.1607637405,47.543296814],"type":"Point"}
}