{
  "type": "Feature",
  "properties": {
    "addr:full":"Piazzetta San Carlo 1 Lugano Ticino 6901",
    "addr:housenumber":"1",
    "addr:postcode":"6901",
    "addr:street":"Piazzetta San Carlo",
    "iso:country":"CH",
    "sg:address":"Piazzetta San Carlo 1",
    "sg:city":"Lugano",
    "sg:classifiers":[
        {
            "category":"Banks & Credit Unions",
            "subcategory":"Bank",
            "type":"Services"
        }
    ],
    "sg:phone":"+41 91 910 81 11",
    "sg:postcode":"6901",
    "sg:province":"Ticino",
    "wof:name":"Banco Di Lugano",
    "wof:placetype":"venue"
},
  "geometry": {"coordinates":[8.93435,46.012775],"type":"Point"}
}