{
  "type": "Feature",
  "properties": {
    "iso:country":"CH",
    "sg:address":"Berggasse 45",
    "sg:city":"Chur",
    "sg:orig_category":"Interessenvertretungen",
    "sg:postcode":"7000",
    "sg:province":"Graubunden",
    "wof:name":"Haas Henriette-stiftung",
    "wof:placetype":"venue"
},
  "geometry": {"coordinates":[9.5417995453,46.8562355042],"type":"Point"}
}