{
  "type": "Feature",
  "properties": {
    "iso:country":"CH",
    "sg:address":"Promenade Des Artisans 26",
    "sg:city":"Meyrin",
    "sg:orig_category":"Schreibb\u00fcros",
    "sg:phone":"+41 22 782 85 73",
    "sg:postcode":"1217",
    "sg:province":"Gen\u00e8ve",
    "wof:name":"Jacqueline Aebischer Bureau De Dactylographie",
    "wof:placetype":"venue"
},
  "geometry": {"coordinates":[6.0796518326,46.2377510071],"type":"Point"}
}