{
  "type": "Feature",
  "properties": {
    "iso:country":"CH",
    "sg:address":"Place Du March\u00e9 1",
    "sg:city":"Aigle",
    "sg:orig_category":"Verwaltung der Rechtspflege, Gerichte",
    "sg:phone":"+41 24 466 26 79",
    "sg:postcode":"1860",
    "sg:province":"Vaud",
    "wof:name":"Administration Cantonale Registre Foncier",
    "wof:placetype":"venue"
},
  "geometry": {"coordinates":[6.970184803,46.3175621033],"type":"Point"}
}