{
  "type": "Feature",
  "properties": {
    "iso:country":"CH",
    "sg:address":"B\u00f6sch 65",
    "sg:city":"H\u00fcnenberg",
    "sg:classifiers":[
        {
            "category":"Manufacturing",
            "subcategory":"Food",
            "type":"Manufacturing & Wholesale Goods"
        }
    ],
    "sg:phone":"+41 41 785 65 65",
    "sg:postcode":"6331",
    "sg:province":"Zug",
    "sg:tags":[
        "packaging",
        "machine"
    ],
    "wof:name":"Multivac Export Ag",
    "wof:placetype":"venue"
},
  "geometry": {"coordinates":[8.4385118484,47.1624031067],"type":"Point"}
}