{
  "type": "Feature",
  "properties": {
    "addr:full":"Clarastrasse 11 Basel Basel-Stadt 4058",
    "addr:housenumber":"11",
    "addr:postcode":"4058",
    "addr:street":"Clarastrasse",
    "iso:country":"CH",
    "sg:address":"Clarastrasse 11",
    "sg:city":"Basel",
    "sg:orig_category":"Architekturb\u00fcros",
    "sg:phone":"+41 61 681 39 10",
    "sg:postcode":"4058",
    "sg:province":"Basel-Stadt",
    "wof:name":"Matthias Buser Architekturb\u00fcro",
    "wof:placetype":"venue"
},
  "geometry": {"coordinates":[7.595345,47.562393],"type":"Point"}
}