{
  "type": "Feature",
  "properties": {
    "iso:country":"CH",
    "sg:address":"Rathausweg 2",
    "sg:city":"Thal",
    "sg:orig_category":"Detailhandel mit Waren verschiedener Art, Hauptrichtung Nahrungsmittel Sonstiger Fachdetailhandel mi",
    "sg:phone":"+41 71 888 29 53",
    "sg:postcode":"9425",
    "sg:province":"St. Gallen",
    "wof:name":"J\u00fcrg Fuhrer",
    "wof:placetype":"venue"
},
  "geometry": {"coordinates":[9.5679397583,47.4653701782],"type":"Point"}
}