{
  "type": "Feature",
  "properties": {
    "iso:country":"CH",
    "sg:address":"Route De Diesse 184",
    "sg:city":"Lamboing",
    "sg:orig_category":"Detailhandel mit Brot, Back U S\u00fcsswaren Detailhandel mit Waren verschiedener Art, Hauptrichtung Nahr",
    "sg:postcode":"2516",
    "sg:province":"Bern",
    "wof:name":"Bayard Pierre-alain",
    "wof:placetype":"venue"
},
  "geometry": {"coordinates":[7.12891,47.115871],"type":"Point"}
}