{
  "type": "Feature",
  "properties": {
    "iso:country":"CH",
    "sg:address":"Flurweg 18 3250 Lyss. Postfach",
    "sg:city":"Lyss",
    "sg:orig_category":"Unternehmensberatung",
    "sg:postcode":"3250",
    "sg:province":"Bern",
    "wof:name":"Allinit Schreyer Ueli",
    "wof:placetype":"venue"
},
  "geometry": {"coordinates":[7.3029408455,47.0704498291],"type":"Point"}
}