{
  "type": "Feature",
  "properties": {
    "iso:country":"CH",
    "sg:address":"Lanzmatt",
    "sg:city":"Kleindietwil",
    "sg:orig_category":"Detailhandel mit Milcherzeugnissen U Eiern",
    "sg:phone":"+41 62 965 19 73",
    "sg:postcode":"4936",
    "sg:province":"Bern",
    "wof:name":"Hansruedi Leuenberger Finka-k\u00e4se",
    "wof:placetype":"venue"
},
  "geometry": {"coordinates":[7.7985520363,47.140247345],"type":"Point"}
}