{
  "type": "Feature",
  "properties": {
    "iso:country":"CH",
    "sg:address":"Neugasse 6",
    "sg:city":"Z\u00fcrich",
    "sg:orig_category":"Detailhandel mit elektrischen Haushalts-,Radio U Fernsehger\u00e4ten sowie Musikinstrumenten",
    "sg:phone":"+41 12731333",
    "sg:postcode":"8001",
    "sg:province":"Z\u00fcrich",
    "wof:name":"Otior Ag",
    "wof:placetype":"venue"
},
  "geometry": {"coordinates":[8.5458879471,47.3724861145],"type":"Point"}
}