{
  "type": "Feature",
  "properties": {
    "iso:country":"CH",
    "sg:address":"Grande Fin La 16",
    "sg:city":"Courtepin",
    "sg:orig_category":"Unclassifiable Establishments",
    "sg:phone":"+41 26 684 01 81",
    "sg:postcode":"1784",
    "sg:province":"Fribourg",
    "wof:name":"Apex Vision Gmbh",
    "wof:placetype":"venue"
},
  "geometry": {"coordinates":[7.1301817894,46.8623695374],"type":"Point"}
}