{
  "type": "Feature",
  "properties": {
    "iso:country":"CH",
    "sg:address":"M\u00e4tteli",
    "sg:city":"Sigriswil",
    "sg:orig_category":"Non-Classified Establishments",
    "sg:postcode":"3655",
    "sg:province":"Bern",
    "wof:name":"Motel Mon Abri Ag",
    "wof:placetype":"venue"
},
  "geometry": {"coordinates":[7.7127537727,46.7173995972],"type":"Point"}
}