{
  "type": "Feature",
  "properties": {
    "iso:country":"CH",
    "sg:address":"Wies 330",
    "sg:city":"Trogen",
    "sg:orig_category":"Allgemeiner Hoch U Tiefbau Hoch U Tiefbau",
    "sg:phone":"+41 71 344 41 51",
    "sg:postcode":"9043",
    "sg:province":"Appenzell Ausserrhoden",
    "wof:name":"J\u00fcrg Zollikofer Gmbh Altbaumodernisierung",
    "wof:placetype":"venue"
},
  "geometry": {"coordinates":[9.479081,47.40641],"type":"Point"}
}