{
  "type": "Feature",
  "properties": {
    "iso:country":"CH",
    "sg:address":"Avenue Des Boveresses 42",
    "sg:city":"Lausanne",
    "sg:orig_category":"Personal U Stellenvermittlung Unternehmensberatung",
    "sg:phone":"+41 21 653 29 50",
    "sg:postcode":"1010",
    "sg:province":"Vaud",
    "wof:name":"Losadi, Noujaim Sylviane",
    "wof:placetype":"venue"
},
  "geometry": {"coordinates":[6.6660399437,46.5356407166],"type":"Point"}
}