{
  "type": "Feature",
  "properties": {
    "iso:country":"CH",
    "sg:address":"Avenue Du Grand-champsec 12",
    "sg:city":"Sion",
    "sg:orig_category":"Gymnastik U Fitnesszentren Saunas, Solarien, Fitnesszentren U \u00e4hnliches",
    "sg:phone":"+41 27 203 31 12",
    "sg:postcode":"1950",
    "sg:province":"Valais",
    "wof:name":"Top Fit S\u00e0rl",
    "wof:placetype":"venue"
},
  "geometry": {"coordinates":[7.384914875,46.22996521],"type":"Point"}
}