{
  "type": "Feature",
  "properties": {
    "iso:country":"CH",
    "sg:address":"Neudorfstrasse 2",
    "sg:city":"Steinhausen",
    "sg:orig_category":"Herstellung von medizinischen U chirurgischen Ger\u00e4ten sowie orthop\u00e4dischen Vorrichtungen",
    "sg:postcode":"6312",
    "sg:province":"Zug",
    "wof:name":"Imp Innovative Medical Products Ltd",
    "wof:placetype":"venue"
},
  "geometry": {"coordinates":[8.4838666916,47.1974182129],"type":"Point"}
}