{
  "type": "Feature",
  "properties": {
    "iso:country":"CH",
    "sg:address":"W\u00e4ssrig 12",
    "sg:city":"Oberg\u00f6sgen",
    "sg:orig_category":"Architektur U Ingenieurb\u00fcros Architekturb\u00fcros",
    "sg:phone":"+41 61 711 22 00",
    "sg:postcode":"4653",
    "sg:province":"Solothurn",
    "wof:name":"Floris Bernhard Architekt Ag",
    "wof:placetype":"venue"
},
  "geometry": {"coordinates":[7.586026,47.493717],"type":"Point"}
}