{
  "type": "Feature",
  "properties": {
    "iso:country":"CH",
    "sg:address":"Au Moulin 132",
    "sg:city":"Ch\u00e9nens",
    "sg:orig_category":"Grosshandel mit lebenden Tieren",
    "sg:phone":"+41 18440228",
    "sg:postcode":"1744",
    "sg:province":"Fribourg",
    "wof:name":"Alwin R\u00fcegg Schweinehandlung",
    "wof:placetype":"venue"
},
  "geometry": {"coordinates":[8.4440097809,47.4592285156],"type":"Point"}
}