{
  "type": "Feature",
  "properties": {
    "addr:full":"Langmattstrasse 26c Aarburg Aargau 4663",
    "addr:housenumber":"26c",
    "addr:postcode":"4663",
    "addr:street":"Langmattstrasse",
    "iso:country":"CH",
    "sg:address":"Langmattstrasse 26c",
    "sg:city":"Aarburg",
    "sg:orig_category":"Architektur U Ingenieurb\u00fcros Grafikateliers, Design",
    "sg:phone":"+41 62 791 67 36",
    "sg:postcode":"4663",
    "sg:province":"Aargau",
    "wof:name":"Franz Vimposek",
    "wof:placetype":"venue"
},
  "geometry": {"coordinates":[7.90638,47.331722],"type":"Point"}
}