{
  "type": "Feature",
  "properties": {
    "iso:country":"CH",
    "sg:address":"Baiergasse 38",
    "sg:city":"Bettingen",
    "sg:orig_category":"Erwachsenenbildung U Unterricht",
    "sg:postcode":"4126",
    "sg:province":"Basel-Stadt",
    "wof:name":"Kst Zenklusen",
    "wof:placetype":"venue"
},
  "geometry": {"coordinates":[7.6683149338,47.5701065063],"type":"Point"}
}