{
  "type": "Feature",
  "properties": {
    "iso:country":"CH",
    "sg:address":"Chemin De Platton 17",
    "sg:city":"Troinex",
    "sg:orig_category":"Unclassifiable Establishments",
    "sg:postcode":"1256",
    "sg:province":"Gen\u00e8ve",
    "wof:name":"Widmer Hydroculture, Chavaz Bernard Succ.",
    "wof:placetype":"venue"
},
  "geometry": {"coordinates":[6.1591229439,46.1545257568],"type":"Point"}
}