{
  "type": "Feature",
  "properties": {
    "iso:country":"CH",
    "sg:address":"Rosenbergweg 1a",
    "sg:city":"W\u00e4ngi",
    "sg:orig_category":"Sanit\u00e4r U Heizungsinstallation",
    "sg:phone":"+41 52 378 30 45",
    "sg:postcode":"9545",
    "sg:province":"Thurgau",
    "wof:name":"Osterauer-juchli Heizungs-& Brennerservice",
    "wof:placetype":"venue"
},
  "geometry": {"coordinates":[8.9534826279,47.5041694641],"type":"Point"}
}