{
  "type": "Feature",
  "properties": {
    "addr:full":"Sans Adresse 1610 Oron-la-ville. Postfach Ch\u00e2tillens Vaud 1610",
    "addr:housenumber":"1610",
    "addr:postcode":"1610",
    "addr:street":"Oron-La-Ville. Postfach",
    "iso:country":"CH",
    "sg:address":"Sans Adresse 1610 Oron-la-ville. Postfach",
    "sg:city":"Ch\u00e2tillens",
    "sg:orig_category":"Detailhandel mit B\u00fcchern, Zeitungen, Schreib U Papeteriewaren",
    "sg:phone":"+41 21 922 62 02",
    "sg:postcode":"1610",
    "sg:province":"Vaud",
    "wof:name":"Kiosque Au Soleil, Monnard-kummli Marie-louise",
    "wof:placetype":"venue"
},
  "geometry": {"coordinates":[5.18087,45.897339],"type":"Point"}
}