{
  "type": "Feature",
  "properties": {
    "addr:full":"Buechenrain 7 W\u00e4denswil Z\u00fcrich 8820",
    "addr:housenumber":"7",
    "addr:postcode":"8820",
    "addr:street":"Buechenrain;Zuerich",
    "iso:country":"CH",
    "sg:address":"Buechenrain 7",
    "sg:city":"W\u00e4denswil",
    "sg:orig_category":"Datenverarbeitungsdienste Sonstige mit der Informatik verbundene T\u00e4tigkeiten",
    "sg:phone":"+41 17805290",
    "sg:postcode":"8820",
    "sg:province":"Z\u00fcrich",
    "wof:name":"Mohamed Gharbi",
    "wof:placetype":"venue"
},
  "geometry": {"coordinates":[8.670287,47.223919],"type":"Point"}
}