{
  "type": "Feature",
  "properties": {
    "iso:country":"CH",
    "sg:address":"Rue De L'abb\u00e9-monnin 23",
    "sg:city":"Bassecourt",
    "sg:orig_category":"Zahnarztpraxen",
    "sg:phone":"+41 32 426 68 78",
    "sg:postcode":"2854",
    "sg:province":"Jura",
    "wof:name":"Dr M\u00e9d. Dent. Budimir Popovic M\u00e9decin-dentiste",
    "wof:placetype":"venue"
},
  "geometry": {"coordinates":[7.2469940186,47.3376274109],"type":"Point"}
}