{
  "type": "Feature",
  "properties": {
    "iso:country":"CH",
    "sg:address":"Rue De L'ancien-port 14",
    "sg:city":"Gen\u00e8ve",
    "sg:orig_category":"Werbeagenturen",
    "sg:phone":"+41 22 741 13 41",
    "sg:postcode":"1201",
    "sg:province":"Gen\u00e8ve",
    "wof:name":"Go Uni-publicit\u00e9",
    "wof:placetype":"venue"
},
  "geometry": {"coordinates":[6.1501259804,46.2124290466],"type":"Point"}
}