{
  "type": "Feature",
  "properties": {
    "iso:country":"CH",
    "sg:address":"3503",
    "sg:city":"Gysenstein",
    "sg:orig_category":"Primarschulen",
    "sg:postcode":"3503",
    "sg:province":"Bern",
    "wof:name":"Primarschule",
    "wof:placetype":"venue"
},
  "geometry": {"coordinates":[7.5914897919,46.8902816772],"type":"Point"}
}