{
  "type": "Feature",
  "properties": {
    "iso:country":"CH",
    "sg:address":"Kornweg 5 5506 M\u00e4genwil. Postfach",
    "sg:city":"M\u00e4genwil",
    "sg:orig_category":"Non-Classified Establishments",
    "sg:postcode":"5506",
    "sg:province":"Aargau",
    "wof:name":"H\u00e4chler Marcel Transport Gmbh",
    "wof:placetype":"venue"
},
  "geometry": {"coordinates":[8.2385540009,47.4117584229],"type":"Point"}
}