{
  "type": "Feature",
  "properties": {
    "iso:country":"CH",
    "sg:address":"Bahnhofstrasse 28",
    "sg:city":"Zug",
    "sg:orig_category":"Unclassifiable Establishments",
    "sg:phone":"+41 18583669",
    "sg:postcode":"6300",
    "sg:province":"Zug",
    "wof:name":"Gattiker J\u00f6rg & Partner Transporte, Kurier, Reparaturservice",
    "wof:placetype":"venue"
},
  "geometry": {"coordinates":[8.4177780151,47.569152832],"type":"Point"}
}