{
  "type": "Feature",
  "properties": {
    "iso:country":"CH",
    "sg:address":"St. Jakobs-strasse 133",
    "sg:city":"Muttenz",
    "sg:orig_category":"Autogaragen Autospenglereien",
    "sg:phone":"+41 62 797 17 71",
    "sg:postcode":"4132",
    "sg:province":"Basel-Landschaft",
    "wof:name":"Baumann & H\u00fcrzeler Garage & Carrosserie",
    "wof:placetype":"venue"
},
  "geometry": {"coordinates":[7.962919,47.322655],"type":"Point"}
}