{
  "type": "Feature",
  "properties": {
    "iso:country":"CH",
    "sg:address":"Luvee Via 8",
    "sg:city":"Stabio",
    "sg:orig_category":"Allgemeiner Hoch U Tiefbau",
    "sg:phone":"+41 91 647 17 10",
    "sg:postcode":"6855",
    "sg:province":"Ticino",
    "wof:name":"Croci Alessandro & Co",
    "wof:placetype":"venue"
},
  "geometry": {"coordinates":[8.945398,45.854435],"type":"Point"}
}