{
  "type": "Feature",
  "properties": {
    "iso:country":"CH",
    "sg:address":"Hungerb\u00fchl",
    "sg:city":"Salmsach",
    "sg:orig_category":"Haltung von Schweinen",
    "sg:phone":"+41 71 463 37 43",
    "sg:postcode":"8599",
    "sg:province":"Thurgau",
    "wof:name":"Hansj\u00f6rg Deutsch Schweinemast Bamis",
    "wof:placetype":"venue"
},
  "geometry": {"coordinates":[9.3569660187,47.5532608032],"type":"Point"}
}