{
  "type": "Feature",
  "properties": {
    "iso:country":"CH",
    "sg:address":"Sieberstrasse 10",
    "sg:city":"Z\u00fcrich",
    "sg:classifiers":[
        {
            "category":"Social Services",
            "subcategory":"Retirement Home",
            "type":"Services"
        }
    ],
    "sg:phone":"+41 71 222 20 42",
    "sg:postcode":"8055",
    "sg:province":"Z\u00fcrich",
    "sg:tags":[
        "pflegeheime",
        "u",
        "alters"
    ],
    "wof:name":"Altersheim Wienerberg",
    "wof:placetype":"venue"
},
  "geometry": {"coordinates":[9.374029,47.433067],"type":"Point"}
}