{
  "type": "Feature",
  "properties": {
    "iso:country":"CH",
    "sg:address":"L\u00f6wenstrasse 1",
    "sg:city":"Z\u00fcrich",
    "sg:orig_category":"Advokatur, Notariatsb\u00fcros",
    "sg:phone":"+41 22 317 73 00",
    "sg:postcode":"8001",
    "sg:province":"Z\u00fcrich",
    "wof:name":"Pestalozzi Lachenal Patry",
    "wof:placetype":"venue"
},
  "geometry": {"coordinates":[6.148312,46.203793],"type":"Point"}
}