{
  "type": "Feature",
  "properties": {
    "iso:country":"CH",
    "sg:address":"Av. De Grandson 48",
    "sg:city":"Yverdon-les-bains",
    "sg:classifiers":[
        {
            "category":"Government",
            "subcategory":"Department Of Motor Vehicles",
            "type":"Public Place"
        }
    ],
    "sg:phone":"+41 24 447 22 72",
    "sg:postcode":"1401",
    "sg:province":"Vaud",
    "sg:tags":[
        "equipment",
        "industrial",
        "transport",
        "motor-cars"
    ],
    "wof:name":"Leclanche Groupe",
    "wof:placetype":"venue"
},
  "geometry": {"coordinates":[6.631436,46.787365],"type":"Point"}
}