{
  "type": "Feature",
  "properties": {
    "iso:country":"CH",
    "sg:address":"Ch\u00e2teau D'allaman",
    "sg:city":"Allaman",
    "sg:orig_category":"Detailhandel mit Antiquit\u00e4ten",
    "sg:phone":"+41 21 807 34 44",
    "sg:postcode":"1165",
    "sg:province":"Vaud",
    "wof:name":"Antonio Caruso Meubles Antiquit\u00e9s D\u00e9coration",
    "wof:placetype":"venue"
},
  "geometry": {"coordinates":[6.398283,46.472416],"type":"Point"}
}