{
  "type": "Feature",
  "properties": {
    "iso:country":"CH",
    "sg:address":"Grossacker 373",
    "sg:city":"Hirschthal",
    "sg:orig_category":"Elektroinstallation",
    "sg:postcode":"5042",
    "sg:province":"Aargau",
    "wof:name":"Basler P., Elektro-mechanische Werkstatt",
    "wof:placetype":"venue"
},
  "geometry": {"coordinates":[8.0592594147,47.3192596436],"type":"Point"}
}