{
  "type": "Feature",
  "properties": {
    "iso:country":"CH",
    "sg:address":"Sonnhalde 18",
    "sg:city":"Erlinsbach",
    "sg:orig_category":"Sportvereine Unihockey",
    "sg:phone":"+41 62 844 03 28",
    "sg:postcode":"5018",
    "sg:province":"Solothurn",
    "wof:name":"Stv Erlinsbach",
    "wof:placetype":"venue"
},
  "geometry": {"coordinates":[8.0080060959,47.4086418152],"type":"Point"}
}