{
  "type": "Feature",
  "properties": {
    "iso:country":"CH",
    "sg:address":"Stangenweg 4",
    "sg:city":"Gals",
    "sg:orig_category":"Bauschreinerei S\u00e4gewerke",
    "sg:phone":"+41 32 338 24 84",
    "sg:postcode":"2076",
    "wof:name":"H\u00e4nni Holzbau Ag",
    "wof:placetype":"venue"
},
  "geometry": {"coordinates":[7.040286,47.023769],"type":"Point"}
}