{
  "type": "Feature",
  "properties": {
    "iso:country":"CH",
    "sg:address":"Spitalstrasse 40",
    "sg:city":"Basel",
    "sg:orig_category":"Organisationen der Wohlfahrtspflege",
    "sg:phone":"+41 61 386 92 10",
    "sg:postcode":"4056",
    "sg:province":"Basel-Stadt",
    "wof:name":"Beratungsstelle Slw F\u00fcr Jugend & Familienfragen",
    "wof:placetype":"venue"
},
  "geometry": {"coordinates":[7.5824751854,47.5638084412],"type":"Point"}
}