{
  "type": "Feature",
  "properties": {
    "iso:country":"CH",
    "sg:address":"St. Wendelin 1",
    "sg:city":"Rotkreuz",
    "sg:orig_category":"Unclassifiable Establishments",
    "sg:postcode":"6343",
    "sg:province":"Zug",
    "wof:name":"Jaspen Ag",
    "wof:placetype":"venue"
},
  "geometry": {"coordinates":[8.4660310745,47.1341400146],"type":"Point"}
}