{
  "type": "Feature",
  "properties": {
    "iso:country":"CH",
    "sg:address":"N\u00e4ssistrasse 10",
    "sg:city":"Hallau",
    "sg:orig_category":"Instandhaltung U Reparatur von Automobilen",
    "sg:phone":"+41 52 681 37 16",
    "sg:postcode":"8215",
    "sg:province":"Schaffhausen",
    "wof:name":"Erb Fritz Garage Post",
    "wof:placetype":"venue"
},
  "geometry": {"coordinates":[8.4624471664,47.695098877],"type":"Point"}
}