{
  "type": "Feature",
  "properties": {
    "iso:country":"CH",
    "sg:address":"Heidegg 39a",
    "sg:city":"Niederstocken",
    "sg:orig_category":"Aktivit\u00e4ten der Generalunternehmen im Baugewerbe Verwaltung von Immobilien",
    "sg:phone":"+41 33 341 10 70",
    "sg:postcode":"3632",
    "sg:province":"Bern",
    "wof:name":"Fidias Ag",
    "wof:placetype":"venue"
},
  "geometry": {"coordinates":[7.584505,46.705872],"type":"Point"}
}