{
  "type": "Feature",
  "properties": {
    "iso:country":"CH",
    "sg:address":"Plantaud Avenue De La 17",
    "sg:city":"Monthey",
    "sg:orig_category":"Herstellung von k\u00e4lte U lufttechnischen Erzeugnissen f\u00fcr gewerbliche Zwecke",
    "sg:postcode":"1870",
    "sg:province":"Valais",
    "wof:name":"Filair Sa",
    "wof:placetype":"venue"
},
  "geometry": {"coordinates":[6.9471468925,46.2516288757],"type":"Point"}
}