{
  "type": "Feature",
  "properties": {
    "iso:country":"CH",
    "sg:address":"B\u00fcelenstrasse 4",
    "sg:city":"W\u00e4denswil",
    "sg:orig_category":"Sonstige mit der Informatik verbundene T\u00e4tigkeiten",
    "sg:postcode":"8820",
    "sg:province":"Z\u00fcrich",
    "wof:name":"Infotain W. Fritsche",
    "wof:placetype":"venue"
},
  "geometry": {"coordinates":[8.6635055542,47.2317771912],"type":"Point"}
}