{
  "type": "Feature",
  "properties": {
    "iso:country":"CH",
    "sg:address":"Im Gruebi",
    "sg:city":"Habkern",
    "sg:orig_category":"Erdbewegungsarbeiten Hoch U Tiefbau",
    "sg:phone":"+41 33 843 11 81",
    "sg:postcode":"3804",
    "sg:province":"Bern",
    "wof:name":"Niklaus Zurbuchen & Sohn Aushub & Bauunternehmung",
    "wof:placetype":"venue"
},
  "geometry": {"coordinates":[7.8640518188,46.7258834839],"type":"Point"}
}