{
  "type": "Feature",
  "properties": {
    "iso:country":"CH",
    "sg:address":"Pany 7243 Pany. Postfach",
    "sg:city":"Pany",
    "sg:orig_category":"Instandhaltung U Reparatur von Automobilen",
    "sg:phone":"+41 81 332 15 72",
    "sg:postcode":"7243",
    "sg:province":"Graubunden",
    "wof:name":"Fl\u00fctsch, Andreas",
    "wof:placetype":"venue"
},
  "geometry": {"coordinates":[9.8019504547,46.9529800415],"type":"Point"}
}