{
  "type": "Feature",
  "properties": {
    "iso:country":"CH",
    "sg:address":"Rainacherstr. 12",
    "sg:city":"Obernau",
    "sg:classifiers":[
        {
            "category":"Shopping",
            "subcategory":"Computers & Home Electronics",
            "type":"Retail Goods"
        }
    ],
    "sg:phone":"+41 41 320 32 00",
    "sg:postcode":"6010",
    "sg:province":"Luzern",
    "sg:tags":[
        "equipment",
        "electrical",
        "component",
        "electric",
        "electronic"
    ],
    "wof:name":"B\u00c4chli Ag",
    "wof:placetype":"venue"
},
  "geometry": {"coordinates":[8.250292778,47.0336303711],"type":"Point"}
}