{
  "type": "Feature",
  "properties": {
    "iso:country":"CH",
    "sg:address":"Zollikerstrasse 225",
    "sg:city":"Z\u00fcrich",
    "sg:orig_category":"Herstellung von medizinischen U chirurgischen Ger\u00e4ten sowie orthop\u00e4dischen Vorrichtungen",
    "sg:phone":"+41 18645111",
    "sg:postcode":"8008",
    "sg:province":"Z\u00fcrich",
    "wof:name":"Schneider (europe) Gmbh Medizinische Ger\u00e4te",
    "wof:placetype":"venue"
},
  "geometry": {"coordinates":[8.5652332306,47.3491744995],"type":"Point"}
}