{
  "type": "Feature",
  "properties": {
    "iso:country":"CH",
    "sg:address":"Frauenfelderstrasse 40",
    "sg:city":"Sirnach",
    "sg:classifiers":[
        {
            "category":"Restaurant",
            "type":"Food & Drink"
        }
    ],
    "sg:phone":"+41 71 966 25 66",
    "sg:postcode":"8370",
    "sg:province":"Thurgau",
    "wof:name":"Restaurant Sonnenberg",
    "wof:placetype":"venue"
},
  "geometry": {"coordinates":[8.9984607697,47.4695472717],"type":"Point"}
}