{
  "type": "Feature",
  "properties": {
    "iso:country":"CH",
    "sg:address":"Avenue De La Gare 39",
    "sg:city":"Conthey",
    "sg:orig_category":"Architekturb\u00fcros",
    "sg:phone":"+41 27 346 46 11",
    "sg:postcode":"1964",
    "sg:province":"Valais",
    "wof:name":"Michel Anthoine Bureau D'architecture",
    "wof:placetype":"venue"
},
  "geometry": {"coordinates":[7.303387,46.226433],"type":"Point"}
}