{
  "type": "Feature",
  "properties": {
    "iso:country":"CH",
    "sg:address":"Zugerstrasse 28",
    "sg:city":"Horgen",
    "sg:orig_category":"Detailhandel mit Beleuchtungs U Haushaltsgegenst\u00e4nden Fachdetailhandel in Verkaufsr\u00e4umen",
    "sg:phone":"+41 17255258",
    "sg:postcode":"8810",
    "sg:province":"Z\u00fcrich",
    "wof:name":"Carina Geschenke, Frau Rosmarie Pfister-gnehm",
    "wof:placetype":"venue"
},
  "geometry": {"coordinates":[8.598297,47.258968],"type":"Point"}
}