{
  "type": "Feature",
  "properties": {
    "iso:country":"CH",
    "sg:address":"Huebacher 4",
    "sg:city":"R\u00fcmlang",
    "sg:orig_category":"Herstellung von Metallerzeugnissen ohne Maschinenbau Herstellung von Metallkonstruktionen",
    "sg:phone":"+41 18173461",
    "sg:postcode":"8153",
    "sg:province":"Z\u00fcrich",
    "wof:name":"Z\u00e4hner B. Metallbau Ag",
    "wof:placetype":"venue"
},
  "geometry": {"coordinates":[8.5260353088,47.4464225769],"type":"Point"}
}