{
  "type": "Feature",
  "properties": {
    "iso:country":"CH",
    "sg:address":"Ch\u00e4ppeliacher 29",
    "sg:city":"Ruswil",
    "sg:orig_category":"Sportvereine Sch\u00fctzen",
    "sg:postcode":"6017",
    "sg:province":"Luzern",
    "wof:name":"Feldsch\u00fctzenges.wolhusen",
    "wof:placetype":"venue"
},
  "geometry": {"coordinates":[8.1174917221,47.0871124268],"type":"Point"}
}