{
  "type": "Feature",
  "properties": {
    "iso:country":"CH",
    "sg:address":"Widistrasse 15",
    "sg:city":"Zuchwil",
    "sg:orig_category":"Erwachsenenbildung U Unterricht",
    "sg:phone":"+41 32 685 41 55",
    "sg:postcode":"4528",
    "sg:province":"Solothurn",
    "wof:name":"Im - Puls - Perkussion Fuhrer Tom",
    "wof:placetype":"venue"
},
  "geometry": {"coordinates":[7.557598114,47.2099990845],"type":"Point"}
}