{
  "type": "Feature",
  "properties": {
    "iso:country":"CH",
    "sg:address":"Rigistrasse 2",
    "sg:city":"H\u00e4gglingen",
    "sg:orig_category":"Kosmetikinstitute",
    "sg:phone":"+41 71 277 02 82",
    "sg:postcode":"5607",
    "sg:province":"Aargau",
    "wof:name":"Care Cosmetic Ursula Frei",
    "wof:placetype":"venue"
},
  "geometry": {"coordinates":[9.3537025452,47.4192237854],"type":"Point"}
}