{
  "type": "Feature",
  "properties": {
    "iso:country":"CH",
    "sg:address":"Oberdorf 231",
    "sg:city":"D\u00fcrrenroth",
    "sg:orig_category":"Sportvereine Turnen",
    "sg:phone":"+41 62 964 14 56",
    "sg:postcode":"3465",
    "sg:province":"Bern",
    "wof:name":"Sportverein Stv D\u00fcrrenroth",
    "wof:placetype":"venue"
},
  "geometry": {"coordinates":[7.7916350365,47.0877075195],"type":"Point"}
}