{
  "type": "Feature",
  "properties": {
    "iso:country":"CH",
    "sg:address":"Hungerb\u00fcelstrasse 17 8500 Frauenfeld. Postfach 716",
    "sg:city":"Frauenfeld",
    "sg:orig_category":"Satzherstellung U Reproduktion",
    "sg:phone":"+41 52 720 77 10",
    "sg:postcode":"8500",
    "sg:province":"Thurgau",
    "wof:name":"Pfr\u00fcnder Ag, Clich\u00e9s & Photolithos.",
    "wof:placetype":"venue"
},
  "geometry": {"coordinates":[8.8735303879,47.5622406006],"type":"Point"}
}