{
  "type": "Feature",
  "properties": {
    "iso:country":"CH",
    "sg:address":"Lielistrasse 8",
    "sg:city":"Oberwil-lieli",
    "sg:orig_category":"Mechanische Werkst\u00e4tten",
    "sg:phone":"+41 56 633 49 35",
    "sg:postcode":"8966",
    "sg:province":"Aargau",
    "wof:name":"Walter Koller Ag",
    "wof:placetype":"venue"
},
  "geometry": {"coordinates":[8.3869838715,47.336971283],"type":"Point"}
}