{
  "type": "Feature",
  "properties": {
    "iso:country":"CH",
    "sg:address":"Zeughausgasse 27",
    "sg:city":"Bern",
    "sg:orig_category":"Herstellung von Sportger\u00e4ten",
    "sg:phone":"+41 21 634 04 86",
    "sg:postcode":"3011",
    "sg:province":"Bern",
    "wof:name":"Elan Sport Ag",
    "wof:placetype":"venue"
},
  "geometry": {"coordinates":[7.4451451302,46.9488258362],"type":"Point"}
}