{
  "type": "Feature",
  "properties": {
    "iso:country":"CH",
    "sg:address":"Reutlingerstrasse 25",
    "sg:city":"Seuzach",
    "sg:orig_category":"Pensionskassen",
    "sg:phone":"+41 52 335 22 21",
    "sg:postcode":"8472",
    "sg:province":"Z\u00fcrich",
    "wof:name":"Personalvorsorgestiftung Der Firma Moser & Co Ag",
    "wof:placetype":"venue"
},
  "geometry": {"coordinates":[8.7330350876,47.5339889526],"type":"Point"}
}