{
  "type": "Feature",
  "properties": {
    "iso:country":"CH",
    "sg:address":"Zelglistrasse 8",
    "sg:city":"Kirchdorf",
    "sg:classifiers":[
        {
            "category":"Structure",
            "subcategory":"Tower",
            "type":"Public Place"
        }
    ],
    "sg:phone":"+41 56 282 47 00",
    "sg:postcode":"5416",
    "sg:province":"Aargau",
    "sg:tags":[
        "awning",
        "marquee"
    ],
    "wof:name":"Fuhrer Storen Inh. Markus Neuhaus",
    "wof:placetype":"venue"
},
  "geometry": {"coordinates":[8.272646904,47.4957542419],"type":"Point"}
}