{
  "type": "Feature",
  "properties": {
    "addr:full":"Bernstrasse 4 M\u00fcnchenbuchsee Bern 3053",
    "addr:housenumber":"4",
    "addr:postcode":"3053",
    "addr:street":"Bernstrasse",
    "iso:country":"CH",
    "sg:address":"Bernstrasse 4",
    "sg:city":"M\u00fcnchenbuchsee",
    "sg:orig_category":"Regionalbanken U Sparkassen",
    "sg:phone":"+41 31 869 34 34",
    "sg:postcode":"3053",
    "sg:province":"Bern",
    "wof:name":"Valiant Bank",
    "wof:placetype":"venue"
},
  "geometry": {"coordinates":[7.450758,47.020996],"type":"Point"}
}