{
  "type": "Feature",
  "properties": {
    "iso:country":"CH",
    "sg:address":"Ziegelh\u00fctte 2",
    "sg:city":"Balsthal",
    "sg:orig_category":"Herstellung von Konstruktionsteilen, Fertigbauteilen U Ausbauelementen aus Holz",
    "sg:postcode":"4710",
    "sg:province":"Solothurn",
    "wof:name":"Fruscio, V.",
    "wof:placetype":"venue"
},
  "geometry": {"coordinates":[5.1808700562,45.8973388672],"type":"Point"}
}