{
  "type": "Feature",
  "properties": {
    "iso:country":"CH",
    "sg:address":"Hardturmstrasse 101",
    "sg:city":"Z\u00fcrich",
    "sg:orig_category":"Deadline Control Systems",
    "sg:phone":"+41 14445999",
    "sg:postcode":"8005",
    "sg:province":"Z\u00fcrich",
    "wof:name":"Telindus Network Ag",
    "wof:placetype":"venue"
},
  "geometry": {"coordinates":[8.517737,47.391937],"type":"Point"}
}