{
  "type": "Feature",
  "properties": {
    "iso:country":"CH",
    "sg:address":"Hauptstrasse 35 6015 Reussb\u00fchl. Postfach",
    "sg:city":"Reussb\u00fchl",
    "sg:orig_category":"RESTAURANTS: TEA-ROOMS",
    "sg:postcode":"6015",
    "sg:province":"Luzern",
    "wof:name":"Jomar Ag",
    "wof:placetype":"venue"
},
  "geometry": {"coordinates":[8.2853116989,47.0625],"type":"Point"}
}