{
  "type": "Feature",
  "properties": {
    "iso:country":"CH",
    "sg:address":"Talstrasse 80 8001 Z\u00fcrich. Postfach",
    "sg:city":"Z\u00fcrich",
    "sg:orig_category":"Finanzierungsinstitutionen",
    "sg:postcode":"8001",
    "sg:province":"Z\u00fcrich",
    "wof:name":"Lrc International Finance S\u00e0rl, Luxemburg, Zweigniederlassung Z\u00fcrich Gew\u00e4hren Von Krediten An Gesellschaften Die Der Gruppe Angeh\u00f6ren Usw",
    "wof:placetype":"venue"
},
  "geometry": {"coordinates":[8.5343160629,47.3719444275],"type":"Point"}
}