{
  "type": "Feature",
  "properties": {
    "iso:country":"CH",
    "sg:address":"Hintere Gasse 3 3132 Riggisberg. Postfach",
    "sg:city":"Riggisberg",
    "sg:orig_category":"Detailhandel mit Textilien Herstellung von W\u00e4sche",
    "sg:phone":"+41 61 751 15 14",
    "sg:postcode":"3132",
    "sg:province":"Bern",
    "wof:name":"Mode Annabelle, Meyer Margrit",
    "wof:placetype":"venue"
},
  "geometry": {"coordinates":[7.5969638824,47.4690475464],"type":"Point"}
}