{
  "type": "Feature",
  "properties": {
    "iso:country":"CH",
    "sg:address":"Sulgeneckstrasse 60 3007 Bern. Postfach",
    "sg:city":"Bern",
    "sg:classifiers":[
        {
            "category":"Professional",
            "subcategory":"Employment Agencies",
            "type":"Services"
        }
    ],
    "sg:phone":"+41 31 326 11 11",
    "sg:postcode":"3005",
    "sg:province":"Bern",
    "sg:tags":[
        "personal",
        "u",
        "stellenvermittlung"
    ],
    "wof:name":"Gsa Gesellschaft F\u00fcr Selbstst\u00e4ndige Arbeitsvermittlung Ag",
    "wof:placetype":"venue"
},
  "geometry": {"coordinates":[7.4346628189,46.9451828003],"type":"Point"}
}