{
  "type": "Feature",
  "properties": {
    "iso:country":"CH",
    "sg:address":"Via Del Piano",
    "sg:city":"Giubiasco",
    "sg:orig_category":"Non-Classified Establishments",
    "sg:phone":"+41 91 857 49 98",
    "sg:postcode":"6512",
    "sg:province":"Ticino",
    "wof:name":"Verdenero Sa",
    "wof:placetype":"venue"
},
  "geometry": {"coordinates":[8.9971847534,46.1726341248],"type":"Point"}
}