{
  "type": "Feature",
  "properties": {
    "iso:country":"CH",
    "sg:address":"M\u00fchlemattstrasse 24$ 4112 B\u00e4ttwil. Postfach",
    "sg:city":"B\u00e4ttwil",
    "sg:orig_category":"K\u00fcnstlerische U schriftstellerische T\u00e4tigkeiten U Darbietungen",
    "sg:postcode":"4112",
    "sg:province":"Solothurn",
    "wof:name":"Kistler Paul + Sohn",
    "wof:placetype":"venue"
},
  "geometry": {"coordinates":[7.5045938492,47.4904975891],"type":"Point"}
}