{
  "type": "Feature",
  "properties": {
    "iso:country":"CH",
    "sg:address":"Birmensdorferstrasse 240 8055 Z\u00fcrich. Postfach 925",
    "sg:city":"Z\u00fcrich",
    "sg:orig_category":"Fachdetailhandel in Verkaufsr\u00e4umen",
    "sg:postcode":"8055",
    "sg:province":"Z\u00fcrich",
    "wof:name":"Boutique Moussac Jakob Jona Wohn, Geschenkartikel, Non-food-produkte Des T\u00e4glichen Bedarfs, Antiquit\u00e4ten Usw.; Verkauf",
    "wof:placetype":"venue"
},
  "geometry": {"coordinates":[8.5131702423,47.3702697754],"type":"Point"}
}