{
  "type": "Feature",
  "properties": {
    "iso:country":"CH",
    "sg:address":"Pra De Plan",
    "sg:city":"Ch\u00e2tel-st-denis",
    "sg:orig_category":"Institutionen f\u00fcr Behinderte Tagesheime f\u00fcr Behinderte, gesch\u00fctzte Werkst\u00e4tten",
    "sg:phone":"+41 21 948 98 76",
    "sg:postcode":"1618",
    "sg:province":"Fribourg",
    "wof:name":"La Belle Etoile Instit.pour Adultes Handicap\u00e9s",
    "wof:placetype":"venue"
},
  "geometry": {"coordinates":[6.9031248093,46.5214385986],"type":"Point"}
}