{
  "type": "Feature",
  "properties": {
    "iso:country":"CH",
    "sg:address":"Glattwiesenstrasse 21",
    "sg:city":"Glattbrugg",
    "sg:orig_category":"Architektur U Ingenieurb\u00fcros Bauschreinerei",
    "sg:phone":"+41 71 973 90 50",
    "sg:postcode":"8152",
    "sg:province":"Z\u00fcrich",
    "wof:name":"Siegfried Max Ag",
    "wof:placetype":"venue"
},
  "geometry": {"coordinates":[8.966827,47.461761],"type":"Point"}
}