{
  "type": "Feature",
  "properties": {
    "iso:country":"CH",
    "sg:address":"Bachstrasse 28 8200 Schaffhausen. Postfach",
    "sg:city":"Schaffhausen",
    "sg:orig_category":"RESTAURANTS: TEA-ROOMS",
    "sg:postcode":"8202",
    "sg:province":"Schaffhausen",
    "wof:name":"Take-away G\u00fcrb\u00fcz B.",
    "wof:placetype":"venue"
},
  "geometry": {"coordinates":[8.6380681992,47.6966667175],"type":"Point"}
}