{
  "type": "Feature",
  "properties": {
    "iso:country":"CH",
    "sg:address":"Im Meyerhof 3 5620 Bremgarten Ag. Postfach",
    "sg:city":"Niederg\u00f6sgen",
    "sg:orig_category":"Sportvereine Ballsport Tischtennis",
    "sg:phone":"+41 79 435 92 83",
    "sg:postcode":"5013",
    "sg:province":"Solothurn",
    "wof:name":"Ttc Niederg\u00f6sgen",
    "wof:placetype":"venue"
},
  "geometry": {"coordinates":[8.3401699066,47.345867157],"type":"Point"}
}