{
  "type": "Feature",
  "properties": {
    "iso:country":"CH",
    "sg:address":"Rebgasse 2",
    "sg:city":"Liestal",
    "sg:orig_category":"Unternehmensberatung Wirtschaftspr\u00fcfung, Steuerberatung U Treuhand",
    "sg:phone":"+41 17811858",
    "sg:postcode":"4410",
    "sg:province":"Basel-Landschaft",
    "wof:name":"Jit Jakob Informatik + Treuhand",
    "wof:placetype":"venue"
},
  "geometry": {"coordinates":[8.6482305527,47.2399673462],"type":"Point"}
}