{
  "type": "Feature",
  "properties": {
    "addr:full":"Konstanzerstrasse 8 Kreuzlingen Thurgau 8280",
    "addr:housenumber":"8",
    "addr:postcode":"8280",
    "addr:street":"Konstanzerstrasse",
    "iso:country":"CH",
    "sg:address":"Konstanzerstrasse 8",
    "sg:city":"Kreuzlingen",
    "sg:orig_category":"Architektur U Ingenieurb\u00fcros",
    "sg:postcode":"8280",
    "sg:province":"Thurgau",
    "wof:name":"Felder & Mandia S\u00e0rl",
    "wof:placetype":"venue"
},
  "geometry": {"coordinates":[7.025616,46.749161],"type":"Point"}
}