{
  "type": "Feature",
  "properties": {
    "iso:country":"CH",
    "sg:address":"Eist\u00e4pfestrasse 5242 Birr. Postfach",
    "sg:city":"Birr",
    "sg:orig_category":"Herstellung von Transportbeton",
    "sg:postcode":"5242",
    "sg:province":"Aargau",
    "wof:name":"Kibag Beton, Seewen",
    "wof:placetype":"venue"
},
  "geometry": {"coordinates":[8.6323652267,47.026550293],"type":"Point"}
}