{
  "type": "Feature",
  "properties": {
    "iso:country":"CH",
    "sg:address":"Menznauerstrasse 28a",
    "sg:city":"Wolhusen",
    "sg:orig_category":"Herstellung von konfektionierten Textilwaren ohne Bekleidung",
    "sg:postcode":"6110",
    "sg:province":"Luzern",
    "wof:name":"Store-suri Gmbh",
    "wof:placetype":"venue"
},
  "geometry": {"coordinates":[8.0738458633,47.0609741211],"type":"Point"}
}