{
  "type": "Feature",
  "properties": {
    "iso:country":"CH",
    "sg:address":"Z\u00fcrcherstrasse 20",
    "sg:city":"Schlieren",
    "sg:orig_category":"Detailhandel mit Pelzwaren",
    "sg:phone":"+41 17300630",
    "sg:postcode":"8952",
    "sg:province":"Z\u00fcrich",
    "wof:name":"Pelzatelier Adriano Vigano",
    "wof:placetype":"venue"
},
  "geometry": {"coordinates":[8.4511003494,47.3979988098],"type":"Point"}
}