{
  "type": "Feature",
  "properties": {
    "iso:country":"CH",
    "sg:address":"La Platta 12",
    "sg:city":"Breil/brigels",
    "sg:orig_category":"Herstellung von keramischen Wand U Bodenfliesen U platten",
    "sg:phone":"+41 81 941 16 88",
    "sg:postcode":"7165",
    "sg:province":"Graubunden",
    "wof:name":"Cathomas Maurus",
    "wof:placetype":"venue"
},
  "geometry": {"coordinates":[9.0628461838,46.766204834],"type":"Point"}
}