{
  "type": "Feature",
  "properties": {
    "iso:country":"CH",
    "sg:address":"Rue Des Epancheurs 17",
    "sg:city":"Auvernier",
    "sg:orig_category":"Non-Classified Establishments",
    "sg:postcode":"2012",
    "sg:province":"Neuch\u00e2tel",
    "wof:name":"Menuservice 'les Vins' Von M\u00fchlenen",
    "wof:placetype":"venue"
},
  "geometry": {"coordinates":[6.8776397705,46.9747543335],"type":"Point"}
}