{
  "type": "Feature",
  "properties": {
    "iso:country":"CH",
    "sg:address":"Rue Du G\u00e9n\u00e9ral-dufour 15",
    "sg:city":"Gen\u00e8ve",
    "sg:orig_category":"Softwareentwicklung U beratung",
    "sg:phone":"+41 17613802",
    "sg:postcode":"1204",
    "sg:province":"Gen\u00e8ve",
    "wof:name":"St\u00f6ri Engineering",
    "wof:placetype":"venue"
},
  "geometry": {"coordinates":[8.4507780075,47.2830314636],"type":"Point"}
}