{
  "type": "Feature",
  "properties": {
    "iso:country":"CH",
    "sg:address":"Aeussere Luzernerstrasse 6",
    "sg:city":"Oftringen",
    "sg:orig_category":"Herstellung von konfektionierten Textilwaren ohne Bekleidung",
    "sg:phone":"+41 62 797 70 36",
    "sg:postcode":"4665",
    "sg:province":"Aargau",
    "wof:name":"Scirocco Storentechnik",
    "wof:placetype":"venue"
},
  "geometry": {"coordinates":[7.9322681427,47.3022003174],"type":"Point"}
}