{
  "type": "Feature",
  "properties": {
    "iso:country":"CH",
    "sg:address":"Poststr. 2",
    "sg:city":"Chur",
    "sg:classifiers":[
        {
            "category":"Banks & Credit Unions",
            "subcategory":"Bank",
            "type":"Services"
        }
    ],
    "sg:phone":"+41 81 256 91 11",
    "sg:postcode":"7002",
    "sg:province":"Graubunden",
    "wof:name":"Graub\u00fcndner Kantonalbank",
    "wof:placetype":"venue"
},
  "geometry": {"coordinates":[9.531954,46.850292],"type":"Point"}
}