{
  "type": "Feature",
  "properties": {
    "addr:full":"Alte Kaiserstuhlerstrasse 2 H\u00f6ri Z\u00fcrich 8181",
    "addr:housenumber":"2",
    "addr:postcode":"8181",
    "addr:street":"Kaiserstuhlerstrasse;Zuerich",
    "iso:country":"CH",
    "sg:address":"Alte Kaiserstuhlerstrasse 2",
    "sg:city":"H\u00f6ri",
    "sg:orig_category":"Autospenglereien",
    "sg:phone":"+41 18602216",
    "sg:postcode":"8181",
    "sg:province":"Z\u00fcrich",
    "wof:name":"Ren\u00e9 Steiner Autospenglerei",
    "wof:placetype":"venue"
},
  "geometry": {"coordinates":[8.504218,47.509605],"type":"Point"}
}