{
  "type": "Feature",
  "properties": {
    "iso:country":"CH",
    "sg:address":"M\u00fchlethalstrasse 39",
    "sg:city":"Zofingen",
    "sg:classifiers":[
        {
            "category":"Farming",
            "subcategory":"Farm",
            "type":"Manufacturing & Wholesale Goods"
        }
    ],
    "sg:phone":"+41 62 751 80 72",
    "sg:postcode":"4800",
    "sg:province":"Aargau",
    "sg:tags":[
        "horticulture",
        "agriculture",
        "livestock"
    ],
    "wof:name":"Steger & Lampart Ag",
    "wof:placetype":"venue"
},
  "geometry": {"coordinates":[7.948897,47.297047],"type":"Point"}
}