{
  "type": "Feature",
  "properties": {
    "iso:country":"CH",
    "sg:address":"Haus Theodu",
    "sg:city":"Zermatt",
    "sg:orig_category":"RESTAURANTS: TEA-ROOMS",
    "sg:phone":"+41 27 967 39 96",
    "sg:postcode":"3920",
    "sg:province":"Valais",
    "wof:name":"Restaurant Farmerhaus Biner Thomas Geschw.",
    "wof:placetype":"venue"
},
  "geometry": {"coordinates":[7.7484002113,46.024143219],"type":"Point"}
}