{
  "type": "Feature",
  "properties": {
    "iso:country":"CH",
    "sg:address":"Leimenstrasse 28",
    "sg:city":"Basel",
    "sg:orig_category":"Arztpraxen",
    "sg:phone":"+41 61 272 11 09",
    "sg:postcode":"4051",
    "sg:province":"Basel-Stadt",
    "wof:name":"Dr.med. Annemarie Bucher Spezial\u00e4rztin Fmh",
    "wof:placetype":"venue"
},
  "geometry": {"coordinates":[7.582314,47.554127],"type":"Point"}
}