{
  "type": "Feature",
  "properties": {
    "iso:country":"CH",
    "sg:address":"Kasinostr. 32",
    "sg:city":"Aarau",
    "sg:classifiers":[
        {
            "category":"Banks & Credit Unions",
            "subcategory":"Bank",
            "type":"Services"
        }
    ],
    "sg:phone":"+41 62 824 09 39",
    "sg:postcode":"5000",
    "sg:province":"Aargau",
    "wof:name":"Aufina",
    "wof:placetype":"venue"
},
  "geometry": {"coordinates":[8.047051,47.391693],"type":"Point"}
}