{
  "type": "Feature",
  "properties": {
    "iso:country":"CH",
    "sg:address":"Birkenstrasse 49",
    "sg:city":"Rotkreuz",
    "sg:orig_category":"Unclassifiable Establishments",
    "sg:postcode":"6343",
    "sg:province":"Zug",
    "wof:name":"Bauer Eberhard International Ag",
    "wof:placetype":"venue"
},
  "geometry": {"coordinates":[8.435385704,47.1471481323],"type":"Point"}
}