{
  "type": "Feature",
  "properties": {
    "iso:country":"CH",
    "sg:address":"Forchstrasse 59 8032 Z\u00fcrich. Postfach 221",
    "sg:city":"Z\u00fcrich",
    "sg:orig_category":"Grosshandel mit Maschinen U Ausr\u00fcstungen",
    "sg:phone":"+41 13831857",
    "sg:postcode":"8032",
    "sg:province":"Z\u00fcrich",
    "wof:name":"Coret Ag Waren Usw; Handel, Imp., Exp. Usw",
    "wof:placetype":"venue"
},
  "geometry": {"coordinates":[8.5584516525,47.3628616333],"type":"Point"}
}