{
  "type": "Feature",
  "properties": {
    "iso:country":"CH",
    "sg:address":"Unterhalden 14",
    "sg:city":"Kaisten",
    "sg:orig_category":"Instandhaltung U Reparatur von Automobilen",
    "sg:phone":"+41 79 657 40 57",
    "sg:postcode":"5082",
    "sg:province":"Aargau",
    "wof:name":"Marcel Winter Garage",
    "wof:placetype":"venue"
},
  "geometry": {"coordinates":[8.0486602783,47.5427360535],"type":"Point"}
}