{
  "type": "Feature",
  "properties": {
    "iso:country":"CH",
    "sg:address":"Le Coll\u00e8ge",
    "sg:city":"Berolle",
    "sg:orig_category":"G\u00fcterbef\u00f6rderung im Strassenverkehr",
    "sg:postcode":"1149",
    "sg:province":"Vaud",
    "wof:name":"Tdk Service Kern T.",
    "wof:placetype":"venue"
},
  "geometry": {"coordinates":[6.3381319046,46.5589561462],"type":"Point"}
}