{
  "type": "Feature",
  "properties": {
    "iso:country":"CH",
    "sg:address":"Unterwegli 1",
    "sg:city":"Winterthur",
    "sg:orig_category":"Kosmetikinstitute",
    "sg:phone":"+41 52 242 63 58",
    "sg:postcode":"8404",
    "sg:province":"Z\u00fcrich",
    "wof:name":"Margrit Schad Kosmetikinstitut",
    "wof:placetype":"venue"
},
  "geometry": {"coordinates":[8.7505645752,47.5034332275],"type":"Point"}
}