{
  "type": "Feature",
  "properties": {
    "iso:country":"CH",
    "sg:address":"Sonnhalde 34",
    "sg:city":"Hildisrieden",
    "sg:orig_category":"Unternehmensberatung",
    "sg:postcode":"6024",
    "sg:province":"Luzern",
    "wof:name":"Senexco International Business Consulting Detlev G. Meyer",
    "wof:placetype":"venue"
},
  "geometry": {"coordinates":[8.2219028473,47.1510620117],"type":"Point"}
}