{
  "type": "Feature",
  "properties": {
    "iso:country":"CH",
    "sg:address":"Weiningerstrasse 44",
    "sg:city":"Unterengstringen",
    "sg:orig_category":"Kosmetikinstitute",
    "sg:phone":"+41 62 822 27 10",
    "sg:postcode":"8103",
    "sg:province":"Z\u00fcrich",
    "wof:name":"Regina J\u00e4ggi Kosmetikinstitut",
    "wof:placetype":"venue"
},
  "geometry": {"coordinates":[8.0769920349,47.4018287659],"type":"Point"}
}