{
  "type": "Feature",
  "properties": {
    "iso:country":"CH",
    "sg:address":"Badstrasse 13",
    "sg:city":"Serneus",
    "sg:orig_category":"Instandhaltung U Reparatur von Automobilen",
    "sg:phone":"+41 81 422 47 66",
    "sg:postcode":"7249",
    "sg:province":"Graubunden",
    "wof:name":"Urs R\u00fcedi Garage",
    "wof:placetype":"venue"
},
  "geometry": {"coordinates":[9.8389348984,46.8899612427],"type":"Point"}
}