{
  "type": "Feature",
  "properties": {
    "iso:country":"CH",
    "sg:address":"Weieren 14b",
    "sg:city":"Z\u00fcberwangen",
    "sg:orig_category":"Softwareentwicklung U beratung",
    "sg:phone":"+41 79 207 83 04",
    "sg:postcode":"9523",
    "sg:province":"St. Gallen",
    "wof:name":"Schwab Informatik Gmbh Informatik; Beratung, Schulung. Softwareentwicklung Usw",
    "wof:placetype":"venue"
},
  "geometry": {"coordinates":[9.1010246277,47.4645233154],"type":"Point"}
}