{
  "type": "Feature",
  "properties": {
    "iso:country":"CH",
    "sg:address":"Unt. B\u00f6nigstrasse 10 A 3800 Interlaken. Postfach",
    "sg:city":"Interlaken",
    "sg:orig_category":"Architekturb\u00fcros",
    "sg:phone":"+41 33 828 10 80",
    "sg:postcode":"3800",
    "sg:province":"Bern",
    "wof:name":"Blatti Pfister + Von Allmen Ag",
    "wof:placetype":"venue"
},
  "geometry": {"coordinates":[7.869104,46.68998],"type":"Point"}
}