{
  "type": "Feature",
  "properties": {
    "iso:country":"CH",
    "sg:address":"Amthausstrasse 23",
    "sg:city":"Dornach",
    "sg:orig_category":"Detailhandel mit Beleuchtungs U Haushaltsgegenst\u00e4nden Grosshandel mit Eisenwaren sowie Installations",
    "sg:phone":"+41 61 701 12 04",
    "sg:postcode":"4143",
    "sg:province":"Solothurn",
    "wof:name":"Sutter Max.",
    "wof:placetype":"venue"
},
  "geometry": {"coordinates":[7.608168,47.488251],"type":"Point"}
}