{
  "type": "Feature",
  "properties": {
    "iso:country":"CH",
    "sg:address":"Storchennest 3",
    "sg:city":"Sissach",
    "sg:orig_category":"Erbringung von sonstigen Dienstleistungen f\u00fcr Unterhaltung, Erholung U Freizeit Vermietung U Verpach",
    "sg:phone":"+41 61 973 83 93",
    "sg:postcode":"4450",
    "sg:province":"Basel-Landschaft",
    "wof:name":"Lapesa Gmbh",
    "wof:placetype":"venue"
},
  "geometry": {"coordinates":[7.8209381104,47.4641494751],"type":"Point"}
}