{
  "type": "Feature",
  "properties": {
    "iso:country":"CH",
    "sg:address":"Untere Bahnhofstrasse 26",
    "sg:city":"Wil",
    "sg:classifiers":[
        {
            "category":"Sports & Exercise",
            "subcategory":"Gym",
            "type":"Entertainment"
        }
    ],
    "sg:phone":"+41 71 911 22 28",
    "sg:postcode":"9500",
    "sg:province":"St. Gallen",
    "sg:tags":[
        "body-building",
        "equipment"
    ],
    "wof:name":"Sole Vita Ag",
    "wof:placetype":"venue"
},
  "geometry": {"coordinates":[9.0459833145,47.4630355835],"type":"Point"}
}