{
  "type": "Feature",
  "properties": {
    "iso:country":"CH",
    "sg:address":"Dorfstrasse 15 8239 D\u00f6rflingen. Postfach",
    "sg:city":"D\u00f6rflingen",
    "sg:orig_category":"Werbung",
    "sg:phone":"+41 52 657 11 11",
    "sg:postcode":"8239",
    "sg:province":"Schaffhausen",
    "wof:name":"Aellig & Co Asg Werbeagentur",
    "wof:placetype":"venue"
},
  "geometry": {"coordinates":[8.7198352814,47.7067680359],"type":"Point"}
}