{
  "type": "Feature",
  "properties": {
    "addr:full":"Grienbachstrasse 17 6300 Zug. Postfach Zug Zug 6300",
    "addr:housenumber":"17",
    "addr:postcode":"6300;postfach;6300",
    "addr:street":"Grienbachstrasse;Zug",
    "iso:country":"CH",
    "sg:address":"Grienbachstrasse 17 6300 Zug. Postfach",
    "sg:city":"Zug",
    "sg:orig_category":"Detailhandel mit Bekleidung",
    "sg:postcode":"6300",
    "sg:province":"Zug",
    "wof:name":"Boland Trading Sa",
    "wof:placetype":"venue"
},
  "geometry": {"coordinates":[8.523443,47.183281],"type":"Point"}
}