{
  "type": "Feature",
  "properties": {
    "iso:country":"CH",
    "sg:address":"Bahnhofstrasse 23",
    "sg:city":"Zug",
    "sg:orig_category":"Non-Classified Establishments",
    "sg:postcode":"6300",
    "sg:province":"Zug",
    "wof:name":"Hausherr Kranservice",
    "wof:placetype":"venue"
},
  "geometry": {"coordinates":[8.4526109695,47.2726974487],"type":"Point"}
}