{
  "type": "Feature",
  "properties": {
    "iso:country":"CH",
    "sg:address":"Dorfstrasse 9523 Z\u00fcberwangen. Postfach",
    "sg:city":"Z\u00fcberwangen",
    "sg:orig_category":"Detektivb\u00fcros U \u00dcberwachung",
    "sg:phone":"+41 71 945 75 45",
    "sg:postcode":"9523",
    "sg:province":"St. Gallen",
    "wof:name":"Split-security L\u00e4ber",
    "wof:placetype":"venue"
},
  "geometry": {"coordinates":[9.0906352997,47.4664611816],"type":"Point"}
}