{
  "type": "Feature",
  "properties": {
    "iso:country":"CH",
    "sg:address":"Churerstrasse 4 9400 Rorschach. Postfach",
    "sg:city":"Rorschach",
    "sg:orig_category":"RESTAURANTS: TEA-ROOMS",
    "sg:postcode":"9400",
    "sg:province":"St. Gallen",
    "wof:name":"Beachgastro Gmbh Restaurant, Kioskbetrieb U. Jugendherberge",
    "wof:placetype":"venue"
},
  "geometry": {"coordinates":[9.5078430176,47.4783935547],"type":"Point"}
}