{
  "type": "Feature",
  "properties": {
    "iso:country":"CH",
    "sg:address":"Via Arogno 13",
    "sg:city":"Campione",
    "sg:classifiers":[
        {
            "category":"Communications",
            "subcategory":"Film & Video Production",
            "type":"Services"
        }
    ],
    "sg:phone":"+41 91 649 80 80",
    "sg:postcode":"6911",
    "sg:province":"Ticino",
    "sg:tags":[
        "videofilmherstellung",
        "u"
    ],
    "wof:name":"Dramma Produzion Sas",
    "wof:placetype":"venue"
},
  "geometry": {"coordinates":[10.8212308884,45.0803642273],"type":"Point"}
}