{
  "type": "Feature",
  "properties": {
    "iso:country":"CH",
    "sg:address":"Via Lucino 42",
    "sg:city":"Breganzona",
    "sg:orig_category":"Psychotherapie",
    "sg:phone":"+41 91 950 93 03",
    "sg:postcode":"6932",
    "sg:province":"Ticino",
    "wof:name":"Ren\u00e9 Lehmann Psicoterapia",
    "wof:placetype":"venue"
},
  "geometry": {"coordinates":[8.9319839478,46.0066757202],"type":"Point"}
}