{
  "type": "Feature",
  "properties": {
    "iso:country":"CH",
    "sg:address":"B\u00fcttenbergstrasse 65",
    "sg:city":"Biel/bienne",
    "sg:orig_category":"Religi\u00f6se Vereinigungen divers",
    "sg:phone":"+41 32 341 35 93",
    "sg:postcode":"2504",
    "sg:province":"Bern",
    "wof:name":"Cvjm/f Biel",
    "wof:placetype":"venue"
},
  "geometry": {"coordinates":[7.286719799,47.1465568542],"type":"Point"}
}