{
  "type": "Feature",
  "properties": {
    "iso:country":"CH",
    "sg:address":"Rue Des Tunnels 45",
    "sg:city":"Neuch\u00e2tel",
    "sg:orig_category":"Allgemeiner Hoch U Tiefbau Maurerarbeiten",
    "sg:phone":"+41 32 731 48 64",
    "sg:postcode":"2000",
    "sg:province":"Neuch\u00e2tel",
    "wof:name":"Sgro Et Mantuano Sa",
    "wof:placetype":"venue"
},
  "geometry": {"coordinates":[6.913152,46.989502],"type":"Point"}
}