{
  "type": "Feature",
  "properties": {
    "iso:country":"CH",
    "sg:address":"Rue Eglise Catholique 9b",
    "sg:city":"Montreux",
    "sg:classifiers":[
        {
            "category":"Communications",
            "subcategory":"Film & Video Production",
            "type":"Services"
        }
    ],
    "sg:phone":"+41 21 963 14 23",
    "sg:postcode":"1820",
    "sg:province":"Vaud",
    "sg:tags":[
        "videofilmherstellung",
        "u"
    ],
    "wof:name":"Sguardo S\u00e0rl Communication",
    "wof:placetype":"venue"
},
  "geometry": {"coordinates":[6.9120678902,46.4312362671],"type":"Point"}
}