{
  "type": "Feature",
  "properties": {
    "iso:country":"CH",
    "sg:address":"Sch\u00e4ggistrasse 9",
    "sg:city":"Henggart",
    "sg:orig_category":"Vereine Frauen",
    "sg:phone":"+41 52 316 15 51",
    "sg:postcode":"8444",
    "sg:province":"Z\u00fcrich",
    "wof:name":"Frauezmorge",
    "wof:placetype":"venue"
},
  "geometry": {"coordinates":[8.6785459518,47.5677337646],"type":"Point"}
}