{
  "type": "Feature",
  "properties": {
    "iso:country":"CH",
    "sg:address":"Letzigraben 241",
    "sg:city":"Z\u00fcrich",
    "sg:orig_category":"Allgemeiner Hoch U Tiefbau",
    "sg:postcode":"8047",
    "sg:province":"Z\u00fcrich",
    "wof:name":"L + B Ag, Hgv, Filiale Z\u00fcrich Hoch, Tiefbauten Usw",
    "wof:placetype":"venue"
},
  "geometry": {"coordinates":[8.492522,47.370327],"type":"Point"}
}