{
  "type": "Feature",
  "properties": {
    "iso:country":"CH",
    "sg:address":"Bruggerstrasse 21 5400 Baden. Postfach",
    "sg:city":"Baden",
    "sg:orig_category":"Gesundheitswesen",
    "sg:phone":"+41 56 221 86 66",
    "sg:postcode":"5401",
    "sg:province":"Aargau",
    "wof:name":"Swica Gesundheitsorganisation Agentur Baden",
    "wof:placetype":"venue"
},
  "geometry": {"coordinates":[8.3049125671,47.4754676819],"type":"Point"}
}