{
  "type": "Feature",
  "properties": {
    "iso:country":"CH",
    "sg:address":"Forchstrasse 317 8008 Z\u00fcrich. Postfach",
    "sg:city":"Z\u00fcrich",
    "sg:orig_category":"Detailhandel mit Beleuchtungs U Haushaltsgegenst\u00e4nden Herstellung von K\u00fcchenm\u00f6beln",
    "sg:phone":"+41 12114649",
    "sg:postcode":"8034",
    "sg:province":"Z\u00fcrich",
    "wof:name":"Kitch'n'cook Ag",
    "wof:placetype":"venue"
},
  "geometry": {"coordinates":[8.574472,47.355499],"type":"Point"}
}