{
  "type": "Feature",
  "properties": {
    "iso:country":"CH",
    "sg:address":"Gerschniweg 4 6390 Engelberg. Postfach 655",
    "sg:city":"Engelberg",
    "sg:classifiers":[
        {
            "category":"Travel",
            "subcategory":"Hotels & Motels",
            "type":"Entertainment"
        }
    ],
    "sg:phone":"+41 71 388 86 30",
    "sg:postcode":"6391",
    "sg:province":"Obwalden",
    "sg:tags":[
        "hotels",
        "mit",
        "restaurant"
    ],
    "wof:name":"Hotel Mario",
    "wof:placetype":"venue"
},
  "geometry": {"coordinates":[9.2529573441,47.4168548584],"type":"Point"}
}