{
  "type": "Feature",
  "properties": {
    "iso:country":"CH",
    "sg:address":"Wehntalerstrasse 33 8157 Dielsdorf. Postfach 308",
    "sg:city":"Dielsdorf",
    "sg:orig_category":"Elektrizit\u00e4tsversorgung Elektroinstallation",
    "sg:phone":"+41 18531160",
    "sg:postcode":"8157",
    "sg:province":"Z\u00fcrich",
    "wof:name":"Elektrizit\u00e4tswerke Des Kantons Z\u00fcrich (ekz) Eltop",
    "wof:placetype":"venue"
},
  "geometry": {"coordinates":[8.45358181,47.48279953],"type":"Point"}
}