{
  "type": "Feature",
  "properties": {
    "iso:country":"CH",
    "sg:address":"Muttenzerstrasse 144",
    "sg:city":"Birsfelden",
    "sg:orig_category":"Chemische Industrie Herstellung von chemischen Grundstoffen",
    "sg:phone":"+41 71 858 20 20",
    "sg:postcode":"4127",
    "sg:province":"Basel-Landschaft",
    "wof:name":"Biosynth Ag Chemische Produkte",
    "wof:placetype":"venue"
},
  "geometry": {"coordinates":[9.542933,47.477543],"type":"Point"}
}