{
  "type": "Feature",
  "properties": {
    "iso:country":"CH",
    "sg:address":"Oberschiltstrasse 10 6363 F\u00fcrigen. Postfach",
    "sg:city":"F\u00fcrigen",
    "sg:classifiers":[
        {
            "category":"Travel",
            "subcategory":"Hotels & Motels",
            "type":"Entertainment"
        }
    ],
    "sg:postcode":"6363",
    "sg:province":"Nidwalden",
    "sg:tags":[
        "hotels",
        "mit",
        "restaurant"
    ],
    "wof:name":"Inter Hotel Management Ag",
    "wof:placetype":"venue"
},
  "geometry": {"coordinates":[8.3531703949,46.9833831787],"type":"Point"}
}