{
  "type": "Feature",
  "properties": {
    "iso:country":"CH",
    "sg:address":"Kehlstrasse 33",
    "sg:city":"Baden",
    "sg:orig_category":"Physiotherapie",
    "sg:phone":"+41 56 221 56 41",
    "sg:postcode":"5400",
    "sg:province":"Aargau",
    "wof:name":"Roland Gautschi Physiotherapie",
    "wof:placetype":"venue"
},
  "geometry": {"coordinates":[8.2894620895,47.4662017822],"type":"Point"}
}