{
  "type": "Feature",
  "properties": {
    "iso:country":"CH",
    "sg:address":"Bramantino Via Del 3",
    "sg:city":"Bellinzona",
    "sg:orig_category":"Non-Classified Establishments",
    "sg:postcode":"6500",
    "sg:province":"Ticino",
    "wof:name":"Perimmo Gmbh",
    "wof:placetype":"venue"
},
  "geometry": {"coordinates":[7.5993299484,47.4889030457],"type":"Point"}
}