{
  "type": "Feature",
  "properties": {
    "iso:country":"CH",
    "sg:address":"Breitenzelgstrasse 4",
    "sg:city":"Zufikon",
    "sg:orig_category":"Mechanische Werkst\u00e4tten",
    "sg:phone":"+41 32 957 65 00",
    "sg:postcode":"5621",
    "sg:province":"Aargau",
    "wof:name":"Joseph Baume Sa Atelier M\u00e9canique De Pr\u00e9cision",
    "wof:placetype":"venue"
},
  "geometry": {"coordinates":[6.9626841545,47.2239341736],"type":"Point"}
}