{
  "type": "Feature",
  "properties": {
    "addr:full":"Wengistrasse 50 Grossaffoltern Bern 3257",
    "addr:housenumber":"50",
    "addr:postcode":"3257",
    "addr:street":"Wengistrasse",
    "iso:country":"CH",
    "sg:address":"Wengistrasse 50",
    "sg:city":"Grossaffoltern",
    "sg:orig_category":"Advent Wreaths, Natural",
    "sg:phone":"+41 32 389 20 70",
    "sg:postcode":"3257",
    "sg:province":"Bern",
    "wof:name":"Heinz Bodmer Ag Stroh- Und Kunststoffwaren",
    "wof:placetype":"venue"
},
  "geometry": {"coordinates":[7.375076,47.072498],"type":"Point"}
}