{
  "type": "Feature",
  "properties": {
    "iso:country":"CH",
    "sg:address":"Alfred Schindler-strasse 10",
    "sg:city":"Emmen",
    "sg:orig_category":"Ger\u00fcstbau G\u00fcterbef\u00f6rderung im Strassenverkehr",
    "sg:phone":"+41 79 642 90 35",
    "sg:postcode":"6032",
    "sg:province":"Luzern",
    "wof:name":"Josef M\u00fcller Gmbh Renovationen & Transporte",
    "wof:placetype":"venue"
},
  "geometry": {"coordinates":[8.290178299,47.0749702454],"type":"Point"}
}