{
  "type": "Feature",
  "properties": {
    "iso:country":"CH",
    "sg:address":"Im Pflanzerfeld 279",
    "sg:city":"Eggenwil",
    "sg:classifiers":[
        {
            "category":"Banks & Credit Unions",
            "subcategory":"Bank",
            "type":"Services"
        }
    ],
    "sg:phone":"+41 4157330570",
    "sg:postcode":"5445",
    "sg:province":"Aargau",
    "wof:name":"Schweiz. Mobiliar",
    "wof:placetype":"venue"
},
  "geometry": {"coordinates":[8.342125,47.366829],"type":"Point"}
}