{
  "type": "Feature",
  "properties": {
    "iso:country":"CH",
    "sg:address":"Baslerstrasse 29",
    "sg:city":"Allschwil",
    "sg:orig_category":"Fachdetailhandel mit pharmazeutischen Produkten",
    "sg:phone":"+41 61 481 44 59",
    "sg:postcode":"4123",
    "sg:province":"Basel-Landschaft",
    "wof:name":"Dorfplatz-apotheke Allschwil, Brigitte Wirz-leupolt",
    "wof:placetype":"venue"
},
  "geometry": {"coordinates":[7.5382509232,47.551776886],"type":"Point"}
}