{
  "type": "Feature",
  "properties": {
    "iso:country":"CH",
    "sg:address":"St. Gallerstrasse 26 8580 Amriswil. Postfach 1671",
    "sg:city":"Amriswil",
    "sg:orig_category":"Instandhaltung U Reparatur von Automobilen",
    "sg:phone":"+41 79 437 19 25",
    "sg:postcode":"8580",
    "sg:province":"Thurgau",
    "wof:name":"Garage Dieziger R.",
    "wof:placetype":"venue"
},
  "geometry": {"coordinates":[8.903386116,47.4784927368],"type":"Point"}
}