{
  "type": "Feature",
  "properties": {
    "iso:country":"CH",
    "sg:address":"Rue Du Grand-ch\u00eane 8",
    "sg:city":"Lausanne",
    "sg:orig_category":"Druck ohne Zeitungsdruck Textilveredlung",
    "sg:phone":"+41 71 971 20 20",
    "sg:postcode":"1003",
    "sg:province":"Vaud",
    "wof:name":"Alder Sieb-& Textildruck Ag",
    "wof:placetype":"venue"
},
  "geometry": {"coordinates":[8.9716396332,47.4648551941],"type":"Point"}
}