{
  "type": "Feature",
  "properties": {
    "addr:full":"Avenue Du Bouchet 20a 1200 Genf. Postfach Gen\u00e8ve Gen\u00e8ve 1201",
    "addr:housenumber":"20a",
    "addr:postcode":"1200 genf. postfach;1201",
    "addr:street":"Avenue Du Bouchet",
    "iso:country":"CH",
    "sg:address":"Avenue Du Bouchet 20a 1200 Genf. Postfach",
    "sg:city":"Gen\u00e8ve",
    "sg:orig_category":"Betrieb U technische Hilfsdienste des Kultur U Unterhaltungswesens",
    "sg:postcode":"1201",
    "sg:province":"Gen\u00e8ve",
    "wof:name":"Association Al-zahra",
    "wof:placetype":"venue"
},
  "geometry": {"coordinates":[6.121509,46.218334],"type":"Point"}
}