{
  "type": "Feature",
  "properties": {
    "iso:country":"CH",
    "sg:address":"Herdernstrasse 61-63",
    "sg:city":"Z\u00fcrich",
    "sg:orig_category":"Grosshandel mit Fleisch U Fleischwaren Schlachten U Fleischverarbeitung",
    "sg:phone":"+41 22 342 33 84",
    "sg:postcode":"8004",
    "sg:province":"Z\u00fcrich",
    "wof:name":"Vecchio Sa Abbattoir & Boucherie",
    "wof:placetype":"venue"
},
  "geometry": {"coordinates":[6.12774086,46.1870918274],"type":"Point"}
}