{
  "type": "Feature",
  "properties": {
    "iso:country":"CH",
    "sg:address":"Oberalpstrasse 223f",
    "sg:city":"Disentis/must\u00e9r",
    "sg:orig_category":"Detailhandel mit Sportartikeln",
    "sg:phone":"+41 81 947 55 83",
    "sg:postcode":"7180",
    "sg:province":"Graubunden",
    "wof:name":"Toni Jacomet Fatschenta Da Sport",
    "wof:placetype":"venue"
},
  "geometry": {"coordinates":[8.8531293869,46.7046012878],"type":"Point"}
}