{
  "type": "Feature",
  "properties": {
    "addr:full":"Avenue C.-f.-ramuz 119 Pully Vaud 1009",
    "addr:housenumber":"119",
    "addr:postcode":"1009",
    "addr:street":"Avenue C.-F.-Ramuz",
    "iso:country":"CH",
    "sg:address":"Avenue C.-f.-ramuz 119",
    "sg:city":"Pully",
    "sg:orig_category":"Arztpraxen",
    "sg:phone":"+41 21 729 88 55",
    "sg:postcode":"1009",
    "sg:province":"Vaud",
    "wof:name":"Dr M\u00e9d. Philippe Delorme M\u00e9decin G\u00e9n\u00e9raliste Fmh",
    "wof:placetype":"venue"
},
  "geometry": {"coordinates":[6.63985,46.510124],"type":"Point"}
}