{
  "type": "Feature",
  "properties": {
    "iso:country":"CH",
    "sg:address":"Spycherweg 7",
    "sg:city":"Niederhasli",
    "sg:orig_category":"Softwareentwicklung U beratung",
    "sg:phone":"+41 18851745",
    "sg:postcode":"8155",
    "sg:province":"Z\u00fcrich",
    "wof:name":"Weninger Computing",
    "wof:placetype":"venue"
},
  "geometry": {"coordinates":[8.4854154587,47.4703979492],"type":"Point"}
}