{
  "type": "Feature",
  "properties": {
    "iso:country":"CH",
    "sg:address":"Bahnhofstrasse 52",
    "sg:city":"Schaffhausen",
    "sg:orig_category":"Kosmetikinstitute",
    "sg:postcode":"8200",
    "sg:province":"Schaffhausen",
    "wof:name":"Sakura Praxis F\u00fcr Sch\u00f6nheits- U. Gesundheitspflege Oetjen",
    "wof:placetype":"venue"
},
  "geometry": {"coordinates":[8.6338405609,47.6987915039],"type":"Point"}
}