{
  "type": "Feature",
  "properties": {
    "iso:country":"CH",
    "sg:address":"Zurmattenstrasse 1",
    "sg:city":"Solothurn",
    "sg:orig_category":"Elektroinstallation",
    "sg:postcode":"4500",
    "sg:province":"Solothurn",
    "wof:name":"Gest'electro Jelk Pierre",
    "wof:placetype":"venue"
},
  "geometry": {"coordinates":[6.1366400719,46.1821594238],"type":"Point"}
}