{
  "type": "Feature",
  "properties": {
    "iso:country":"CH",
    "sg:address":"Poststrasse 27",
    "sg:city":"Schleitheim",
    "sg:orig_category":"Herstellung von Konstruktionsteilen, Fertigbauteilen U Ausbauelementen aus Holz",
    "sg:postcode":"8226",
    "sg:province":"Schaffhausen",
    "wof:name":"Bruno Stamm Schreinerarbeiten + Montagen",
    "wof:placetype":"venue"
},
  "geometry": {"coordinates":[8.4834518433,47.7489891052],"type":"Point"}
}