{
  "type": "Feature",
  "properties": {
    "iso:country":"CH",
    "sg:address":"Sunnetalstrasse 35 8117 F\u00e4llanden. Postfach",
    "sg:city":"F\u00e4llanden",
    "sg:orig_category":"Unternehmensberatung",
    "sg:phone":"+41 18256650",
    "sg:postcode":"8117",
    "sg:province":"Z\u00fcrich",
    "wof:name":"Bugmann Erwin Unternehmensberatung Firmen-beratung Und Coaching",
    "wof:placetype":"venue"
},
  "geometry": {"coordinates":[8.6437711716,47.3721656799],"type":"Point"}
}