{
  "type": "Feature",
  "properties": {
    "iso:country":"CH",
    "sg:address":"Jeanrichard Av. Daniel- 8",
    "sg:city":"Fleurier",
    "sg:orig_category":"Elektroinstallation",
    "sg:phone":"+41 21 732 27 23",
    "sg:postcode":"2114",
    "sg:province":"Neuch\u00e2tel",
    "wof:name":"Tecno Montage S\u00e0rl Armoires \u00e9lectriques; Montage Et C\u00e2blage",
    "wof:placetype":"venue"
},
  "geometry": {"coordinates":[6.6639499664,46.5902061462],"type":"Point"}
}