{
  "type": "Feature",
  "properties": {
    "iso:country":"CH",
    "sg:address":"C\u00f4te Malherbe",
    "sg:city":"St-george",
    "sg:orig_category":"Unclassifiable Establishments",
    "sg:postcode":"1261",
    "sg:province":"Vaud",
    "wof:name":"Ems La Renaissance S.a.",
    "wof:placetype":"venue"
},
  "geometry": {"coordinates":[6.271697998,46.5161361694],"type":"Point"}
}