{
  "type": "Feature",
  "properties": {
    "iso:country":"CH",
    "sg:address":"L'occitane",
    "sg:city":"Noville",
    "sg:orig_category":"Detailhandel mit Musikinstrumenten Erbringung von Dienstleistungen f\u00fcr Unternehmen",
    "sg:phone":"+41 21 960 46 27",
    "sg:postcode":"1845",
    "sg:province":"Vaud",
    "wof:name":"Bruno De Angelis Agence Artistique",
    "wof:placetype":"venue"
},
  "geometry": {"coordinates":[6.8991599083,46.3815612793],"type":"Point"}
}