{
  "type": "Feature",
  "properties": {
    "iso:country":"CH",
    "sg:address":"Gare Des Eaux-vives Av. 23",
    "sg:city":"Gen\u00e8ve",
    "sg:orig_category":"Non-Classified Establishments",
    "sg:postcode":"1208",
    "sg:province":"Gen\u00e8ve",
    "wof:name":"F. H\u00f6sli Ag",
    "wof:placetype":"venue"
},
  "geometry": {"coordinates":[9.0810642242,46.9940681458],"type":"Point"}
}