{
  "type": "Feature",
  "properties": {
    "iso:country":"CH",
    "sg:address":"Sulgenbachstrasse 12",
    "sg:city":"Bern",
    "sg:orig_category":"Vermietung U Verpachtung von eigenen Immobilien",
    "sg:phone":"+41 31 378 28 28",
    "sg:postcode":"3007",
    "sg:province":"Bern",
    "wof:name":"Freiburghaus M. & H. Immobilien",
    "wof:placetype":"venue"
},
  "geometry": {"coordinates":[7.4332752228,46.9416313171],"type":"Point"}
}