{
  "type": "Feature",
  "properties": {
    "iso:country":"CH",
    "sg:address":"Route De Malagnou 53 1200 Genf. Postfach",
    "sg:city":"Gen\u00e8ve",
    "sg:orig_category":"Non-Classified Establishments",
    "sg:postcode":"1207",
    "sg:province":"Gen\u00e8ve",
    "wof:name":"Sodinor Participations Sarl",
    "wof:placetype":"venue"
},
  "geometry": {"coordinates":[6.1652407646,46.1965942383],"type":"Point"}
}