{
  "type": "Feature",
  "properties": {
    "iso:country":"CH",
    "sg:address":"Else Z\u00fcblin-strasse 34",
    "sg:city":"Z\u00fcrich",
    "sg:orig_category":"Vorschulen, Kinderg\u00e4rten",
    "sg:phone":"+41 14912043",
    "sg:postcode":"8047",
    "sg:province":"Z\u00fcrich",
    "wof:name":"St\u00e4dtischer Kindergarten Sunnige Hof",
    "wof:placetype":"venue"
},
  "geometry": {"coordinates":[8.4887895584,47.3778610229],"type":"Point"}
}