{
  "type": "Feature",
  "properties": {
    "iso:country":"CH",
    "sg:address":"Habsburgerstrasse 34",
    "sg:city":"Luzern",
    "sg:orig_category":"Herstellung von Bettwaren Herstellung von Matratzen",
    "sg:phone":"+41 41 210 81 66",
    "sg:postcode":"6003",
    "sg:province":"Luzern",
    "wof:name":"Sato.schlaf.r\u00e4ume Ag Futons Naturbetten",
    "wof:placetype":"venue"
},
  "geometry": {"coordinates":[8.3059616089,47.0465087891],"type":"Point"}
}