{
  "type": "Feature",
  "properties": {
    "iso:country":"CH",
    "sg:address":"Kasernenstrasse 92",
    "sg:city":"Chur",
    "sg:orig_category":"RESTAURANTS: TEA-ROOMS",
    "sg:phone":"+41 81 253 38 40",
    "sg:postcode":"7000",
    "sg:province":"Graubunden",
    "wof:name":"Crucitti Paolo",
    "wof:placetype":"venue"
},
  "geometry": {"coordinates":[9.5188331604,46.8470420837],"type":"Point"}
}