{
  "type": "Feature",
  "properties": {
    "iso:country":"CH",
    "sg:address":"Baselstrasse 19",
    "sg:city":"Riehen",
    "sg:orig_category":"Allgemeiner Hoch U Tiefbau Allgemeiner Hochbau",
    "sg:phone":"+41 33 744 44 90",
    "sg:postcode":"4125",
    "sg:province":"Basel-Stadt",
    "wof:name":"Thoenen Bauunternehmung Ag",
    "wof:placetype":"venue"
},
  "geometry": {"coordinates":[7.277753,46.475914],"type":"Point"}
}