{
  "type": "Feature",
  "properties": {
    "iso:country":"CH",
    "sg:address":"Aachstrasse 4 9320 Arbon. Postfach 181",
    "sg:city":"Arbon",
    "sg:orig_category":"Reiseb\u00fcros U Reiseveranstalter",
    "sg:postcode":"9320",
    "sg:province":"Thurgau",
    "wof:name":"Touristik-service Venetz Daniel",
    "wof:placetype":"venue"
},
  "geometry": {"coordinates":[7.9367241859,46.1232452393],"type":"Point"}
}