{
  "type": "Feature",
  "properties": {
    "iso:country":"CH",
    "sg:address":"Goldmattstrasse 14",
    "sg:city":"Sarnen",
    "sg:orig_category":"Erschliessung von Grundst\u00fccken",
    "sg:postcode":"6060",
    "sg:province":"Obwalden",
    "wof:name":"Gemeinn\u00fctzige Wohnbaugenossenschaft Sch\u00f6nthal-rikon",
    "wof:placetype":"venue"
},
  "geometry": {"coordinates":[8.7918300629,47.4517707825],"type":"Point"}
}