{
  "type": "Feature",
  "properties": {
    "addr:full":"Vaz Vaz Graubunden 7082",
    "addr:postcode":"7082",
    "iso:country":"CH",
    "sg:address":"Vaz",
    "sg:city":"Vaz",
    "sg:classifiers":[
        {
            "category":"Banks & Credit Unions",
            "subcategory":"Bank",
            "type":"Services"
        }
    ],
    "sg:phone":"+41 4181341581",
    "sg:postcode":"7082",
    "sg:province":"Graubunden",
    "wof:name":"Raiffeisenbank Vaz Obervaz",
    "wof:placetype":"venue"
},
  "geometry": {"coordinates":[-72.81699399999999,41.461403],"type":"Point"}
}