{
  "type": "Feature",
  "properties": {
    "iso:country":"CH",
    "sg:address":"Wiesentalstr. 68",
    "sg:city":"Uzwil",
    "sg:orig_category":"Architektur U Ingenieurb\u00fcros",
    "sg:postcode":"9240",
    "sg:province":"St. Gallen",
    "wof:name":"Bruc Sa",
    "wof:placetype":"venue"
},
  "geometry": {"coordinates":[7.108453,46.925232],"type":"Point"}
}