{
  "type": "Feature",
  "properties": {
    "iso:country":"CH",
    "sg:address":"Avenue Giuseppe-motta 12 1200 Genf. Postfach",
    "sg:city":"Gen\u00e8ve",
    "sg:orig_category":"Fachdetailhandel in Verkaufsr\u00e4umen",
    "sg:postcode":"1201",
    "sg:province":"Gen\u00e8ve",
    "wof:name":"Edeart S\u00e0rl",
    "wof:placetype":"venue"
},
  "geometry": {"coordinates":[6.1316537857,46.2167701721],"type":"Point"}
}