{
  "type": "Feature",
  "properties": {
    "iso:country":"CH",
    "sg:address":"Dorfgasse 35",
    "sg:city":"Widen",
    "sg:orig_category":"Massagestudios",
    "sg:phone":"+41 56 633 88 78",
    "sg:postcode":"8967",
    "sg:province":"Aargau",
    "wof:name":"Guido Wiederkehr Massagen",
    "wof:placetype":"venue"
},
  "geometry": {"coordinates":[8.3575620651,47.3674316406],"type":"Point"}
}