{
  "type": "Feature",
  "properties": {
    "addr:full":"Br\u00fcggerschweg 17 B Klosters Graubunden 7250",
    "addr:housenumber":"17 b",
    "addr:postcode":"7250",
    "addr:street":"Brueggerschweg",
    "iso:country":"CH",
    "sg:address":"Br\u00fcggerschweg 17 B",
    "sg:city":"Klosters",
    "sg:orig_category":"Architektur U Ingenieurb\u00fcros",
    "sg:postcode":"7250",
    "sg:province":"Graubunden",
    "wof:name":"Scand Engineering Gmbh",
    "wof:placetype":"venue"
},
  "geometry": {"coordinates":[9.881119,46.876549],"type":"Point"}
}