{
  "type": "Feature",
  "properties": {
    "iso:country":"CH",
    "sg:address":"Kapuzinerweg 9",
    "sg:city":"Luzern",
    "sg:orig_category":"Handelsvermittlung U Grosshandel",
    "sg:phone":"+41 41 420 67 01",
    "sg:postcode":"6006",
    "sg:province":"Luzern",
    "wof:name":"Ewig Ag",
    "wof:placetype":"venue"
},
  "geometry": {"coordinates":[8.3124856949,47.057926178],"type":"Point"}
}