{
  "type": "Feature",
  "properties": {
    "iso:country":"CH",
    "sg:address":"Schwanenweg 1b",
    "sg:city":"Grabs",
    "sg:orig_category":"Sonstige pers\u00f6nliche Dienstleistungen",
    "sg:phone":"+41 81 771 21 73",
    "sg:postcode":"9472",
    "sg:province":"St. Gallen",
    "wof:name":"Institut Lord Partnervermittlung",
    "wof:placetype":"venue"
},
  "geometry": {"coordinates":[9.4508733749,47.1751747131],"type":"Point"}
}