{
  "type": "Feature",
  "properties": {
    "iso:country":"CH",
    "sg:address":"7742",
    "sg:city":"Poschiavo",
    "sg:classifiers":[
        {
            "category":"Travel",
            "subcategory":"Hotels & Motels",
            "type":"Entertainment"
        }
    ],
    "sg:postcode":"7742",
    "sg:province":"Graubunden",
    "sg:tags":[
        "hotels",
        "mit",
        "restaurant"
    ],
    "wof:name":"Albrici P. & C. Gebr.",
    "wof:placetype":"venue"
},
  "geometry": {"coordinates":[10.0568399429,46.3265647888],"type":"Point"}
}