{
  "type": "Feature",
  "properties": {
    "iso:country":"CH",
    "sg:address":"Murenbergstrasse 36 4416 Bubendorf. Postfach",
    "sg:city":"Bubendorf",
    "sg:orig_category":"Finanzierungsinstitutionen",
    "sg:phone":"+41 61 931 28 88",
    "sg:postcode":"4416",
    "sg:province":"Basel-Landschaft",
    "wof:name":"Walter Iberg Ag",
    "wof:placetype":"venue"
},
  "geometry": {"coordinates":[7.7426509857,47.4499778748],"type":"Point"}
}