{
  "type": "Feature",
  "properties": {
    "iso:country":"CH",
    "sg:address":"B\u00fctzenweg 20",
    "sg:city":"Zug",
    "sg:orig_category":"Unclassifiable Establishments",
    "sg:phone":"+41 41 711 86 86",
    "sg:postcode":"6300",
    "sg:province":"Zug",
    "wof:name":"Lely Holding Ag",
    "wof:placetype":"venue"
},
  "geometry": {"coordinates":[8.5207080841,47.1563644409],"type":"Point"}
}