{
  "type": "Feature",
  "properties": {
    "iso:country":"CH",
    "sg:address":"Rue Margencel 27",
    "sg:city":"Aigle",
    "sg:orig_category":"Bauingenieurb\u00fcros Hochbau Bauingenieurb\u00fcros allgemein",
    "sg:phone":"+41 56 441 75 86",
    "sg:postcode":"1860",
    "sg:province":"Vaud",
    "wof:name":"Joachim Andri Ingenieurb\u00fcro",
    "wof:placetype":"venue"
},
  "geometry": {"coordinates":[8.168111,47.44949],"type":"Point"}
}