{
  "type": "Feature",
  "properties": {
    "iso:country":"CH",
    "sg:address":"Scheurenweg 16",
    "sg:city":"Biel/bienne",
    "sg:orig_category":"Herstellung von medizinischen U chirurgischen Ger\u00e4ten",
    "sg:phone":"+41 32 341 93 04",
    "sg:postcode":"2504",
    "sg:province":"Bern",
    "wof:name":"Gideon L\u00fcscher Physikalische Medizin",
    "wof:placetype":"venue"
},
  "geometry": {"coordinates":[7.2813048363,47.14402771],"type":"Point"}
}