{
  "type": "Feature",
  "properties": {
    "iso:country":"CH",
    "sg:address":"Borgne 1967 Bramois. Postfach",
    "sg:city":"Bramois",
    "sg:orig_category":"Unclassifiable Establishments",
    "sg:postcode":"1967",
    "sg:province":"Valais",
    "wof:name":"Aladin Technologies S\u00e0rl",
    "wof:placetype":"venue"
},
  "geometry": {"coordinates":[7.3962621689,46.2322502136],"type":"Point"}
}