{
  "type": "Feature",
  "properties": {
    "iso:country":"CH",
    "sg:address":"Bahnhofstrasse 42 2502 Biel/bienne. Postfach",
    "sg:city":"Biel/bienne",
    "sg:orig_category":"Unclassifiable Establishments",
    "sg:postcode":"2502",
    "sg:province":"Bern",
    "wof:name":"Othmar W\u00fcest C/o Spv",
    "wof:placetype":"venue"
},
  "geometry": {"coordinates":[8.2235832214,47.131149292],"type":"Point"}
}