{
  "type": "Feature",
  "properties": {
    "iso:country":"CH",
    "sg:address":"Kreuzgasse 8 3860 Meiringen. Postfach 608",
    "sg:city":"Meiringen",
    "sg:orig_category":"Bauingenieurb\u00fcros Hochbau Bauingenieurb\u00fcros allgemein",
    "sg:phone":"+41 33 971 45 32",
    "sg:postcode":"3860",
    "sg:province":"Bern",
    "wof:name":"Ernst Samuel Pulver Ingenieurb\u00fcro",
    "wof:placetype":"venue"
},
  "geometry": {"coordinates":[8.188592,46.727524],"type":"Point"}
}