{
  "type": "Feature",
  "properties": {
    "iso:country":"CH",
    "sg:address":"Pilatusstrasse 6 6003 Luzern. Postfach",
    "sg:city":"Luzern",
    "sg:orig_category":"Allgemeinbildende weiterf\u00fchrende Schulen Sprachschulen",
    "sg:phone":"+41 41 210 96 26",
    "sg:postcode":"6002",
    "sg:province":"Luzern",
    "wof:name":"B\u00e9n\u00e9dict-schule Luzern Ag",
    "wof:placetype":"venue"
},
  "geometry": {"coordinates":[8.30814,47.049896],"type":"Point"}
}