{
  "type": "Feature",
  "properties": {
    "iso:country":"CH",
    "sg:address":"Solothurnstrasse 7 2504 Biel/bienne. Postfach",
    "sg:city":"Biel/bienne",
    "sg:orig_category":"Interessenvertretungen",
    "sg:phone":"+41 32 341 11 36",
    "sg:postcode":"2504",
    "sg:province":"Bern",
    "wof:name":"Stiftung Der Burgergemeinde B\u00f6zingen Zur F\u00f6rderung Der Ausbildung",
    "wof:placetype":"venue"
},
  "geometry": {"coordinates":[7.2682452202,47.1541595459],"type":"Point"}
}