{
  "type": "Feature",
  "properties": {
    "iso:country":"CH",
    "sg:address":"Zone Industrielle Le Tr\u00e9si 1 1028 Pr\u00e9verenges. Postfach",
    "sg:city":"Pr\u00e9verenges",
    "sg:orig_category":"Instandhaltung U Reparatur von Automobilen",
    "sg:phone":"+41 32 841 10 41",
    "sg:postcode":"1028",
    "sg:province":"Vaud",
    "wof:name":"Garage Le Verny, Bongiovanni O.",
    "wof:placetype":"venue"
},
  "geometry": {"coordinates":[6.864508152,46.9686279297],"type":"Point"}
}