{
  "type": "Feature",
  "properties": {
    "iso:country":"CH",
    "sg:address":"Bramenstrasse 10",
    "sg:city":"Bachenb\u00fclach",
    "sg:orig_category":"Herstellung von Duft U K\u00f6rperpflegemitteln",
    "sg:phone":"+41 18862501",
    "sg:postcode":"8184",
    "sg:province":"Z\u00fcrich",
    "wof:name":"Top Line, Kosmetik-vertrieb, Kramer Daniel",
    "wof:placetype":"venue"
},
  "geometry": {"coordinates":[8.5387611389,47.5036659241],"type":"Point"}
}