{
  "type": "Feature",
  "properties": {
    "iso:country":"CH",
    "sg:address":"Fliederstrasse 5c",
    "sg:city":"Gerlafingen",
    "sg:orig_category":"Grosshandel mit Bekleidung Herstellung von sonstiger Bekleidung U Bekleidungszubeh\u00f6r",
    "sg:phone":"+41 79 206 28 20",
    "sg:postcode":"4563",
    "sg:province":"Solothurn",
    "wof:name":"Kids Fashion V.& D.enters Agentur F.kinderbekleidung",
    "wof:placetype":"venue"
},
  "geometry": {"coordinates":[7.5765600204,47.1652984619],"type":"Point"}
}