{
  "type": "Feature",
  "properties": {
    "addr:full":"1295 Mies-tannay Vaud 1295",
    "addr:housenumber":"1295",
    "addr:postcode":"1295",
    "addr:street":"Mies-Tannay",
    "iso:country":"CH",
    "sg:address":"1295",
    "sg:city":"Mies-tannay",
    "sg:orig_category":"Allgemeiner Hoch U Tiefbau Maurerarbeiten",
    "sg:phone":"+41 22 776 15 46",
    "sg:postcode":"1295",
    "sg:province":"Vaud",
    "wof:name":"Simond Roger.",
    "wof:placetype":"venue"
},
  "geometry": {"coordinates":[6.17609,46.308949],"type":"Point"}
}