{
  "type": "Feature",
  "properties": {
    "iso:country":"CH",
    "sg:address":"Rte De Founex 25",
    "sg:city":"C\u00e9ligny",
    "sg:orig_category":"RESTAURANTS: TEA-ROOMS",
    "sg:postcode":"1298",
    "sg:province":"Gen\u00e8ve",
    "wof:name":"Filograna Giuseppe",
    "wof:placetype":"venue"
},
  "geometry": {"coordinates":[5.1808700562,45.8973388672],"type":"Point"}
}