{
  "type": "Feature",
  "properties": {
    "iso:country":"CH",
    "sg:address":"Quaderstrasse 15 7000 Chur. Postfach 383",
    "sg:city":"Chur",
    "sg:orig_category":"Sportvereine Ballsport Fussball",
    "sg:phone":"+41 81 253 59 05",
    "sg:postcode":"7001",
    "sg:province":"Graubunden",
    "wof:name":"Asociacon Espanola",
    "wof:placetype":"venue"
},
  "geometry": {"coordinates":[9.5328989029,46.8524894714],"type":"Point"}
}