{
  "type": "Feature",
  "properties": {
    "iso:country":"CH",
    "sg:address":"Steinrieselnstrasse 67",
    "sg:city":"Herisau",
    "sg:orig_category":"Dachdeckerei Zimmerei, Dachdeckerei, Bauspenglerei U Abdichtung",
    "sg:phone":"+41 71 351 67 43",
    "sg:postcode":"9100",
    "sg:province":"Appenzell Ausserrhoden",
    "wof:name":"Klarer Bedachungen Ag",
    "wof:placetype":"venue"
},
  "geometry": {"coordinates":[9.290275,47.38662],"type":"Point"}
}