{
  "type": "Feature",
  "properties": {
    "iso:country":"CH",
    "sg:address":"Alpsteinring 12",
    "sg:city":"Arnegg",
    "sg:orig_category":"Architekturb\u00fcros Herstellung von B\u00fcro U Ladenm\u00f6beln",
    "sg:phone":"+41 71 383 19 66",
    "sg:postcode":"9212",
    "sg:province":"St. Gallen",
    "wof:name":"Haueis Ag, Ladenbau & Architekturwerkstatt",
    "wof:placetype":"venue"
},
  "geometry": {"coordinates":[9.25905,47.443794],"type":"Point"}
}