{
  "type": "Feature",
  "properties": {
    "iso:country":"CH",
    "sg:address":"Hauptstrasse 14",
    "sg:city":"Brig",
    "sg:classifiers":[
        {
            "category":"Bars & Pubs",
            "type":"Food & Drink"
        }
    ],
    "sg:phone":"+41 27 924 26 46",
    "sg:postcode":"3900",
    "sg:province":"Valais",
    "sg:tags":[
        "restaurant"
    ],
    "wof:name":"Sherlock's Brig Ag Restaurant Couronne & Bar",
    "wof:placetype":"venue"
},
  "geometry": {"coordinates":[7.987646,46.315891],"type":"Point"}
}