{
  "type": "Feature",
  "properties": {
    "iso:country":"CH",
    "sg:address":"Av. Des Libellules 10",
    "sg:city":"Vernier",
    "sg:orig_category":"Wirtschaftspr\u00fcfung, Steuerberatung U Treuhand",
    "sg:postcode":"1214",
    "sg:province":"Gen\u00e8ve",
    "wof:name":"Offidimp-conseils, Vogt Shirley",
    "wof:placetype":"venue"
},
  "geometry": {"coordinates":[6.109017849,46.2071151733],"type":"Point"}
}