{
  "type": "Feature",
  "properties": {
    "iso:country":"CH",
    "sg:address":"Delsbergerstrasse 127",
    "sg:city":"Laufen",
    "sg:orig_category":"Bauspenglerei Zimmerei, Dachdeckerei, Bauspenglerei U Abdichtung",
    "sg:phone":"+41 61 761 54 75",
    "sg:postcode":"4242",
    "sg:province":"Basel-Landschaft",
    "wof:name":"Saner Urban Jun. Spenglerei, Sanit\u00e4re Installationen, Heizungsanlagen",
    "wof:placetype":"venue"
},
  "geometry": {"coordinates":[7.49962,47.415291],"type":"Point"}
}