{
  "type": "Feature",
  "properties": {
    "iso:country":"CH",
    "sg:address":"Henric Petri-strasse 19 4051 Basel. Postfach",
    "sg:city":"Basel",
    "sg:orig_category":"Sonstiges Versicherungsgewerbe",
    "sg:postcode":"4051",
    "sg:province":"Basel-Stadt",
    "wof:name":"Gn\u00e4dinger Peter R. Generalagentur Generalagentur F\u00fcr Versicherungsgesellschaften",
    "wof:placetype":"venue"
},
  "geometry": {"coordinates":[7.5930747986,47.5518112183],"type":"Point"}
}