{
  "type": "Feature",
  "properties": {
    "iso:country":"CH",
    "sg:address":"Wartstrasse 61",
    "sg:city":"Winterthur",
    "sg:classifiers":[
        {
            "category":"Professional",
            "subcategory":"Employment Agencies",
            "type":"Services"
        }
    ],
    "sg:phone":"+41 52 223 17 62",
    "sg:postcode":"8400",
    "sg:province":"Z\u00fcrich",
    "sg:tags":[
        "personal",
        "u",
        "stellenvermittlung"
    ],
    "wof:name":"Gastro-personal Plus",
    "wof:placetype":"venue"
},
  "geometry": {"coordinates":[8.7147006989,47.5032501221],"type":"Point"}
}