{
  "type": "Feature",
  "properties": {
    "iso:country":"CH",
    "sg:address":"Krummackerstrasse 4",
    "sg:city":"Bubendorf",
    "sg:classifiers":[
        {
            "category":"Restaurant",
            "type":"Food & Drink"
        }
    ],
    "sg:phone":"+41 61 931 14 54",
    "sg:postcode":"4416",
    "sg:province":"Basel-Landschaft",
    "wof:name":"Restaurant Murenberg",
    "wof:placetype":"venue"
},
  "geometry": {"coordinates":[7.7390270233,47.4544754028],"type":"Point"}
}