{
  "type": "Feature",
  "properties": {
    "addr:full":"Kirchenfeldstrasse 35 Lyss Bern 3250",
    "addr:housenumber":"35",
    "addr:postcode":"3250",
    "addr:street":"Kirchenfeldstrasse;Bern",
    "iso:country":"CH",
    "sg:address":"Kirchenfeldstrasse 35",
    "sg:city":"Lyss",
    "sg:classifiers":[
        {
            "category":"Military Area",
            "subcategory":"Air Force Base",
            "type":"Public Place"
        }
    ],
    "sg:phone":"+41 32 384 04 15",
    "sg:postcode":"3250",
    "sg:province":"Bern",
    "sg:tags":[
        "attic",
        "stair"
    ],
    "wof:name":"Feldmann & Co Ag",
    "wof:placetype":"venue"
},
  "geometry": {"coordinates":[7.30408,47.067631],"type":"Point"}
}