{
  "type": "Feature",
  "properties": {
    "addr:full":"Unterdorfstrasse 3 Oberhelfenschwil St. Gallen 9621",
    "addr:housenumber":"3",
    "addr:postcode":"9621",
    "addr:street":"Unterdorfstrasse",
    "iso:country":"CH",
    "sg:address":"Unterdorfstrasse 3",
    "sg:city":"Oberhelfenschwil",
    "sg:orig_category":"Detailhandel mit Brot, Back U S\u00fcsswaren",
    "sg:phone":"+41 71 374 11 80",
    "sg:postcode":"9621",
    "sg:province":"St. Gallen",
    "wof:name":"Brunner Marcel, B\u00e4ckerei-konditorei",
    "wof:placetype":"venue"
},
  "geometry": {"coordinates":[9.114587,47.354332],"type":"Point"}
}