{
  "type": "Feature",
  "properties": {
    "iso:country":"CH",
    "sg:address":"Bindernweg 5",
    "sg:city":"Oberrieden",
    "sg:orig_category":"Sportvereine Wassersport Segeln",
    "sg:phone":"+41 17206472",
    "sg:postcode":"8942",
    "sg:province":"Z\u00fcrich",
    "wof:name":"Seglervereinig.oberrieden Svo",
    "wof:placetype":"venue"
},
  "geometry": {"coordinates":[8.5826349258,47.271900177],"type":"Point"}
}