{
  "type": "Feature",
  "properties": {
    "iso:country":"CH",
    "sg:address":"Gartenstrasse 7",
    "sg:city":"Oberengstringen",
    "sg:orig_category":"Einbau von Schreinerwaren",
    "sg:phone":"+41 14316526",
    "sg:postcode":"8102",
    "sg:province":"Z\u00fcrich",
    "wof:name":"Gastro Engros Heer & Gubler",
    "wof:placetype":"venue"
},
  "geometry": {"coordinates":[8.4617204666,47.410369873],"type":"Point"}
}