{
  "type": "Feature",
  "properties": {
    "iso:country":"CH",
    "sg:address":"Albisstrasse 44",
    "sg:city":"Mettmenstetten",
    "sg:orig_category":"Sonstiger spezialisierter Hoch U Tiefbau",
    "sg:postcode":"8932",
    "sg:province":"Z\u00fcrich",
    "wof:name":"M\u00e4der Hermann, Armierungen",
    "wof:placetype":"venue"
},
  "geometry": {"coordinates":[8.8581380844,47.1926002502],"type":"Point"}
}