{
  "type": "Feature",
  "properties": {
    "iso:country":"CH",
    "sg:address":"H\u00fcbelweg 7",
    "sg:city":"Dittingen",
    "sg:orig_category":"Sportvereine Turnen",
    "sg:phone":"+41 61 761 34 61",
    "sg:postcode":"4243",
    "sg:province":"Basel-Landschaft",
    "wof:name":"Turnverein Stv Dittingen",
    "wof:placetype":"venue"
},
  "geometry": {"coordinates":[7.4979372025,47.4402389526],"type":"Point"}
}