{
  "type": "Feature",
  "properties": {
    "iso:country":"CH",
    "sg:address":"Oberdorfstrasse 60",
    "sg:city":"M\u00fcnchenbuchsee",
    "sg:orig_category":"Detailhandel mit Geschenkartikeln U Souvenirs Herstellung von sonstigen Metallwaren",
    "sg:phone":"+41 31 869 01 68",
    "sg:postcode":"3053",
    "sg:province":"Bern",
    "wof:name":"Gertrud Dreier",
    "wof:placetype":"venue"
},
  "geometry": {"coordinates":[7.4403829575,47.0199928284],"type":"Point"}
}