{
  "type": "Feature",
  "properties": {
    "iso:country":"CH",
    "sg:address":"Livio Via 14",
    "sg:city":"Chiasso",
    "sg:orig_category":"Erzeugung U Erstbearbeitung von Aluminium",
    "sg:phone":"+41 91824991",
    "sg:postcode":"6830",
    "sg:province":"Ticino",
    "wof:name":"Alupro Sa",
    "wof:placetype":"venue"
},
  "geometry": {"coordinates":[9.0282869339,45.8340301514],"type":"Point"}
}