{
  "type": "Feature",
  "properties": {
    "addr:full":"Oberdorfstrasse 5 M\u00fcnchenbuchsee Bern 3053",
    "addr:housenumber":"5",
    "addr:postcode":"3053",
    "addr:street":"Oberdorfstrasse",
    "iso:country":"CH",
    "sg:address":"Oberdorfstrasse 5",
    "sg:city":"M\u00fcnchenbuchsee",
    "sg:orig_category":"Detailhandel mit Bekleidung Grosshandel mit Textilien",
    "sg:phone":"+41 31 869 60 69",
    "sg:postcode":"3053",
    "sg:province":"Bern",
    "wof:name":"Mode Sonja Gmbh",
    "wof:placetype":"venue"
},
  "geometry": {"coordinates":[7.449822,47.021217],"type":"Point"}
}