{
  "type": "Feature",
  "properties": {
    "iso:country":"CH",
    "sg:address":"Benzligenstrasse 28",
    "sg:city":"Vordemwald",
    "sg:orig_category":"Handelsvermittlung U Grosshandel R\u00fcckgewinnung U Vorbereitung f\u00fcr die Wiederverwertung Recycling",
    "sg:phone":"+41 62 751 61 10",
    "sg:postcode":"4803",
    "sg:province":"Aargau",
    "wof:name":"Emil Stalder Alteisenhandel",
    "wof:placetype":"venue"
},
  "geometry": {"coordinates":[7.9055519104,47.2710037231],"type":"Point"}
}