{
  "type": "Feature",
  "properties": {
    "iso:country":"CH",
    "sg:address":"Bahnhofstrasse 122",
    "sg:city":"Schiers",
    "sg:orig_category":"Kantonalbanken",
    "sg:phone":"+41 81 300 22 22",
    "sg:postcode":"7220",
    "sg:province":"Graubunden",
    "wof:name":"Graub\u00fcndner Kantonalbank",
    "wof:placetype":"venue"
},
  "geometry": {"coordinates":[9.6886053085,46.9694213867],"type":"Point"}
}