{
  "type": "Feature",
  "properties": {
    "iso:country":"CH",
    "sg:address":"Bahnhofstrasse 11",
    "sg:city":"Lyss",
    "sg:orig_category":"Vermittlung von Immobilien Verwaltung von Immobilien",
    "sg:phone":"+41 71 220 13 53",
    "sg:postcode":"3250",
    "sg:province":"Bern",
    "wof:name":"Hannes A. R\u00fcttimann Immobilien",
    "wof:placetype":"venue"
},
  "geometry": {"coordinates":[-76.9426116943,43.0785942078],"type":"Point"}
}