{
  "type": "Feature",
  "properties": {
    "iso:country":"CH",
    "sg:address":"Alte Steinhauserstrasse 35 6330 Cham. Postfach 5233",
    "sg:city":"Cham",
    "sg:orig_category":"Unclassifiable Establishments",
    "sg:postcode":"6330",
    "sg:province":"Zug",
    "wof:name":"Hermann Stutz Erben",
    "wof:placetype":"venue"
},
  "geometry": {"coordinates":[8.2894887924,47.3429412842],"type":"Point"}
}