{
  "type": "Feature",
  "properties": {
    "iso:country":"CH",
    "sg:address":"Via Cittadella 7",
    "sg:city":"Locarno",
    "sg:orig_category":"Detailhandel mit Geschenkartikeln U Souvenirs",
    "sg:phone":"+41 91 752 33 09",
    "sg:postcode":"6600",
    "sg:province":"Ticino",
    "wof:name":"Boutique Pucci Piera Ventoso",
    "wof:placetype":"venue"
},
  "geometry": {"coordinates":[8.7943506241,46.1701011658],"type":"Point"}
}