{
  "type": "Feature",
  "properties": {
    "addr:full":"Voreimatt 100 Tecknau Basel-Landschaft 4492",
    "addr:housenumber":"100",
    "addr:postcode":"4492",
    "iso:country":"CH",
    "sg:address":"Voreimatt 100",
    "sg:city":"Tecknau",
    "sg:orig_category":"Abbruch U Sprenggewerbe, Erdbewegungsarbeiten Erdbewegungsarbeiten",
    "sg:phone":"+41 79 603 04 03",
    "sg:postcode":"4492",
    "sg:province":"Basel-Landschaft",
    "wof:name":"Grieder Hans Ag, Aushub Und Tiefbau",
    "wof:placetype":"venue"
},
  "geometry": {"coordinates":[7.890963,47.443211],"type":"Point"}
}