{
  "type": "Feature",
  "properties": {
    "iso:country":"CH",
    "sg:address":"Baselstrasse 9",
    "sg:city":"Luzern",
    "sg:orig_category":"Softwareentwicklung U beratung",
    "sg:phone":"+41 41 240 50 50",
    "sg:postcode":"6003",
    "sg:province":"Luzern",
    "wof:name":"Pc Schn\u00e4ppchen Jud",
    "wof:placetype":"venue"
},
  "geometry": {"coordinates":[8.2987785339,47.051700592],"type":"Point"}
}