{
  "type": "Feature",
  "properties": {
    "iso:country":"CH",
    "sg:address":"Hintere Dammstrasse 1",
    "sg:city":"M\u00f6hlin",
    "sg:orig_category":"Teppichreinigung",
    "sg:phone":"+41 61 851 28 55",
    "sg:postcode":"4313",
    "sg:province":"Aargau",
    "wof:name":"Steam-clean-service Teppichreinigung",
    "wof:placetype":"venue"
},
  "geometry": {"coordinates":[7.8358650208,47.5622901917],"type":"Point"}
}