{
  "type": "Feature",
  "properties": {
    "addr:full":"Obergrundstrasse 28 Luzern Luzern 6003",
    "addr:housenumber":"28",
    "addr:postcode":"6003",
    "addr:street":"Obergrundstrasse",
    "iso:country":"CH",
    "sg:address":"Obergrundstrasse 28",
    "sg:city":"Luzern",
    "sg:orig_category":"Dachdeckerei",
    "sg:phone":"+41 56 245 14 02",
    "sg:postcode":"6003",
    "sg:province":"Luzern",
    "wof:name":"Daniel W\u00fcthrich Dachdeckergesch\u00e4ft",
    "wof:placetype":"venue"
},
  "geometry": {"coordinates":[8.22698,47.496826],"type":"Point"}
}