{
  "type": "Feature",
  "properties": {
    "iso:country":"CH",
    "sg:address":"Rue Du Pasteur-fr\u00eane 2",
    "sg:city":"Tavannes",
    "sg:orig_category":"Herstellung von Metallkonstruktionen",
    "sg:postcode":"2710",
    "sg:province":"Bern",
    "wof:name":"Kculg S\u00e0rl",
    "wof:placetype":"venue"
},
  "geometry": {"coordinates":[7.2014808655,47.2213935852],"type":"Point"}
}