{
  "type": "Feature",
  "properties": {
    "iso:country":"CH",
    "sg:address":"Boulevard Du Th\u00e9\u00e2tre 9",
    "sg:city":"Gen\u00e8ve",
    "sg:orig_category":"Kunsthandel",
    "sg:phone":"+41 22 328 82 21",
    "sg:postcode":"1204",
    "sg:province":"Gen\u00e8ve",
    "wof:name":"Paolo & Gemma Tonon Antiquit\u00e9s Tableaux",
    "wof:placetype":"venue"
},
  "geometry": {"coordinates":[6.1421527863,46.2021827698],"type":"Point"}
}