{
  "type": "Feature",
  "properties": {
    "iso:country":"CH",
    "sg:address":"Hofwiesweg 3",
    "sg:city":"Appenzell",
    "sg:orig_category":"Tierarztpraxis",
    "sg:phone":"+41 71 787 30 88",
    "sg:postcode":"9050",
    "sg:province":"Appenzell Innerhoden",
    "wof:name":"Dr.med.vet. Johann Fritsche Tierarzt",
    "wof:placetype":"venue"
},
  "geometry": {"coordinates":[9.404209137,47.3301696777],"type":"Point"}
}