{
  "type": "Feature",
  "properties": {
    "iso:country":"CH",
    "sg:address":"Bahnhofstrasse 4",
    "sg:city":"Aefligen",
    "sg:orig_category":"Nationale Postdienste",
    "sg:phone":"+41 34 445 22 72",
    "sg:postcode":"3426",
    "sg:province":"Bern",
    "wof:name":"Die Schweizerische Post",
    "wof:placetype":"venue"
},
  "geometry": {"coordinates":[7.5584192276,47.0945854187],"type":"Point"}
}