{
  "type": "Feature",
  "properties": {
    "iso:country":"CH",
    "sg:address":"Bahnhofstrasse 7",
    "sg:city":"Lyss",
    "sg:orig_category":"Detailhandel mit Blumen U Pflanzen Detailhandel mit Geschenkartikeln U Souvenirs",
    "sg:phone":"+41 32 384 84 06",
    "sg:postcode":"3250",
    "sg:province":"Bern",
    "wof:name":"Ursula Styner Flower-in Blumengesch\u00e4ft",
    "wof:placetype":"venue"
},
  "geometry": {"coordinates":[7.306028,47.075539],"type":"Point"}
}