{
  "type": "Feature",
  "properties": {
    "iso:country":"CH",
    "sg:address":"Aeschiweg 15 3700 Spiez. Postfach",
    "sg:city":"Spiez",
    "sg:orig_category":"Herstellung von Konstruktionsteilen, Fertigbauteilen U Ausbauelementen aus Holz",
    "sg:postcode":"3700",
    "sg:province":"Bern",
    "wof:name":"Teuscher J. Schreinerei Bau- U. M\u00f6belschreinerei",
    "wof:placetype":"venue"
},
  "geometry": {"coordinates":[7.6828708649,46.6671180725],"type":"Point"}
}