{
  "type": "Feature",
  "properties": {
    "iso:country":"CH",
    "sg:address":"Feldstrasse 98",
    "sg:city":"Z\u00fcrich",
    "sg:classifiers":[
        {
            "category":"Restaurant",
            "type":"Food & Drink"
        }
    ],
    "sg:phone":"+41 12423432",
    "sg:postcode":"8004",
    "sg:province":"Z\u00fcrich",
    "wof:name":"Pizzeria Grottino 79",
    "wof:placetype":"venue"
},
  "geometry": {"coordinates":[8.523399353,47.3787345886],"type":"Point"}
}