{
  "type": "Feature",
  "properties": {
    "iso:country":"CH",
    "sg:address":"L\u00f6wenstr. 21",
    "sg:city":"Dietikon",
    "sg:orig_category":"Detailhandel mit Parf\u00fcmerieartikeln U K\u00f6rperpflegemitteln",
    "sg:phone":"+41 22 342 42 52",
    "sg:postcode":"8953",
    "sg:province":"Z\u00fcrich",
    "wof:name":"Comptoir D'essences De Parfumerie Cep",
    "wof:placetype":"venue"
},
  "geometry": {"coordinates":[6.1414251328,46.1833114624],"type":"Point"}
}