{
  "type": "Feature",
  "properties": {
    "addr:full":"Gerechtigkeitsgasse 31 Bern Bern 3011",
    "addr:housenumber":"31",
    "addr:postcode":"3011",
    "addr:street":"Gerechtigkeitsgasse",
    "iso:country":"CH",
    "sg:address":"Gerechtigkeitsgasse 31",
    "sg:city":"Bern",
    "sg:orig_category":"Architekturb\u00fcros",
    "sg:phone":"+41 31 312 37 10",
    "sg:postcode":"3011",
    "sg:province":"Bern",
    "wof:name":"Probst Stephan + Partner Ag B\u00fcro F. Architektur U. Bauleistungsaufgaben B. Neubauten Usw. Liegenschaften; Verwaltung, Handel",
    "wof:placetype":"venue"
},
  "geometry": {"coordinates":[7.454405,46.94825],"type":"Point"}
}