{
  "type": "Feature",
  "properties": {
    "iso:country":"CH",
    "sg:address":"Rue De La Gare 5",
    "sg:city":"Montreux",
    "sg:orig_category":"Geb\u00e4ude, Wohnungsreinigung",
    "sg:phone":"+41 21 963 72 57",
    "sg:postcode":"1820",
    "sg:province":"Vaud",
    "wof:name":"Robert Fontolliet Entreprise De Nettoyage",
    "wof:placetype":"venue"
},
  "geometry": {"coordinates":[6.9087290764,46.4375114441],"type":"Point"}
}