{
  "type": "Feature",
  "properties": {
    "iso:country":"CH",
    "sg:address":"Kohlhalden 1",
    "sg:city":"Speicher",
    "sg:orig_category":"Detailhandel mit Brot, Back U S\u00fcsswaren",
    "sg:phone":"+41 27 934 13 98",
    "sg:postcode":"9042",
    "sg:province":"Appenzell Ausserrhoden",
    "wof:name":"B\u00e4ckerei-konditorei, Tea-room - Restaurant Augstbord, Andres Josef & Astrid",
    "wof:placetype":"venue"
},
  "geometry": {"coordinates":[7.803388,46.283012],"type":"Point"}
}