{
  "type": "Feature",
  "properties": {
    "iso:country":"CH",
    "sg:address":"Lehenmattstrasse 352",
    "sg:city":"Basel",
    "sg:orig_category":"Non-Classified Establishments",
    "sg:postcode":"4052",
    "sg:province":"Basel-Stadt",
    "wof:name":"4 Trans Kurier, Marra P. & Co",
    "wof:placetype":"venue"
},
  "geometry": {"coordinates":[7.619987011,47.5437202454],"type":"Point"}
}