{
  "type": "Feature",
  "properties": {
    "iso:country":"CH",
    "sg:address":"Eichb\u00fchl 31",
    "sg:city":"Altishofen",
    "sg:orig_category":"Non-Classified Establishments",
    "sg:postcode":"6246",
    "sg:province":"Luzern",
    "wof:name":"Hunkeler Gartenbau Und Unterhalt",
    "wof:placetype":"venue"
},
  "geometry": {"coordinates":[7.9664402008,47.2028388977],"type":"Point"}
}