{
  "type": "Feature",
  "properties": {
    "iso:country":"CH",
    "sg:address":"Zurlindenstrasse 230",
    "sg:city":"Z\u00fcrich",
    "sg:orig_category":"Detailhandel mit Waren verschiedener Art, Hauptrichtung Nahrungsmittel Fachdetailhandel mit Nahrungs",
    "sg:postcode":"8003",
    "sg:province":"Z\u00fcrich",
    "wof:name":"Alfonso Rusconi Comestibles",
    "wof:placetype":"venue"
},
  "geometry": {"coordinates":[8.5134429932,47.3754005432],"type":"Point"}
}