{
  "type": "Feature",
  "properties": {
    "addr:full":"Kirchstrasse 99 Grenchen Solothurn 2540",
    "addr:housenumber":"99",
    "addr:postcode":"2540",
    "addr:street":"Kirchstrasse",
    "iso:country":"CH",
    "sg:address":"Kirchstrasse 99",
    "sg:city":"Grenchen",
    "sg:orig_category":"Architektur U Ingenieurb\u00fcros",
    "sg:phone":"+41 71 243 52 52",
    "sg:postcode":"2540",
    "sg:province":"Solothurn",
    "wof:name":"Meyer Martin Ag",
    "wof:placetype":"venue"
},
  "geometry": {"coordinates":[9.396907,47.440311],"type":"Point"}
}