{
  "type": "Feature",
  "properties": {
    "iso:country":"CH",
    "sg:address":"G\u00e4bris",
    "sg:city":"Gais",
    "sg:classifiers":[
        {
            "category":"Restaurant",
            "type":"Food & Drink"
        }
    ],
    "sg:phone":"+41 81 416 15 43",
    "sg:postcode":"9056",
    "sg:province":"Appenzell Ausserrhoden",
    "wof:name":"Bergrestaurant Pischa",
    "wof:placetype":"venue"
},
  "geometry": {"coordinates":[9.8416595459,46.8098487854],"type":"Point"}
}