{
  "type": "Feature",
  "properties": {
    "iso:country":"CH",
    "sg:address":"Kohlplatzstrasse 7",
    "sg:city":"Lotzwil",
    "sg:orig_category":"Herstellung von Radio U Fernsehger\u00e4ten sowie phono U videotechnischen Ger\u00e4ten",
    "sg:phone":"+41 71 911 22 20",
    "sg:postcode":"4932",
    "sg:province":"Bern",
    "wof:name":"Hovo Hollenstein Ag",
    "wof:placetype":"venue"
},
  "geometry": {"coordinates":[9.0396347046,47.4645690918],"type":"Point"}
}