{
  "type": "Feature",
  "properties": {
    "iso:country":"CH",
    "sg:address":"Giova Pozzerin",
    "sg:city":"Buseno",
    "sg:orig_category":"Landwirtschaft, Jagd U damit verbundene Dienstleistungen",
    "sg:phone":"+41 91 827 33 24",
    "sg:postcode":"6542",
    "sg:province":"Graubunden",
    "wof:name":"Luigi Fibbioli Azienda Agricola",
    "wof:placetype":"venue"
},
  "geometry": {"coordinates":[9.1070585251,46.2732925415],"type":"Point"}
}