{
  "type": "Feature",
  "properties": {
    "addr:full":"Seewil Dieterswil Bern 3256",
    "addr:postcode":"3256",
    "iso:country":"CH",
    "sg:address":"Seewil",
    "sg:city":"Dieterswil",
    "sg:orig_category":"Bauschreinerei Zimmerei, Dachdeckerei, Bauspenglerei U Abdichtung",
    "sg:phone":"+41 31 879 02 60",
    "sg:postcode":"3256",
    "sg:province":"Bern",
    "wof:name":"Holzbau Junker, Inhaber Jirasek Georg",
    "wof:placetype":"venue"
},
  "geometry": {"coordinates":[7.44884,47.05571],"type":"Point"}
}