{
  "type": "Feature",
  "properties": {
    "addr:full":"Strehlgasse 7 Seuzach Z\u00fcrich 8472",
    "addr:housenumber":"7",
    "addr:postcode":"8472",
    "addr:street":"Strehlgasse",
    "iso:country":"CH",
    "sg:address":"Strehlgasse 7",
    "sg:city":"Seuzach",
    "sg:classifiers":[
        {
            "category":"Education",
            "subcategory":"Library",
            "type":"Public Place"
        }
    ],
    "sg:phone":"+41 52 335 38 81",
    "sg:postcode":"8472",
    "sg:province":"Z\u00fcrich",
    "sg:tags":[
        "u",
        "bibliotheken",
        "archive"
    ],
    "wof:name":"Gemeindebibliothek",
    "wof:placetype":"venue"
},
  "geometry": {"coordinates":[8.73077,47.537148],"type":"Point"}
}