{
  "type": "Feature",
  "properties": {
    "iso:country":"CH",
    "sg:address":"3984",
    "sg:city":"Fiesch",
    "sg:orig_category":"Seilbahnen Sessellifte and Skilifte",
    "sg:phone":"+41 27 971 17 87",
    "sg:postcode":"3984",
    "sg:province":"Valais",
    "wof:name":"Luftseilbahn Fiesch-eggishorn Ag",
    "wof:placetype":"venue"
},
  "geometry": {"coordinates":[8.0610904694,46.4772415161],"type":"Point"}
}