{
  "type": "Feature",
  "properties": {
    "iso:country":"CH",
    "sg:address":"Geissgasse 19",
    "sg:city":"Rheinfelden",
    "sg:classifiers":[
        {
            "category":"Restaurant",
            "type":"Food & Drink"
        }
    ],
    "sg:phone":"+41 61 831 55 65",
    "sg:postcode":"4310",
    "sg:province":"Aargau",
    "sg:tags":[
        "tea-rooms",
        "restaurants"
    ],
    "wof:name":"Bistro Bar Schl\u00fcssel, Schmid C.",
    "wof:placetype":"venue"
},
  "geometry": {"coordinates":[7.7948508263,47.5544471741],"type":"Point"}
}