{
  "type": "Feature",
  "properties": {
    "iso:country":"CH",
    "sg:address":"Schulhausstrasse 10",
    "sg:city":"Langendorf",
    "sg:orig_category":"Herstellung von Konstruktionsteilen, Fertigbauteilen U Ausbauelementen aus Holz",
    "sg:phone":"+41 32 622 12 56",
    "sg:postcode":"4513",
    "sg:province":"Solothurn",
    "wof:name":"Ledermann Ag Langendorf",
    "wof:placetype":"venue"
},
  "geometry": {"coordinates":[7.5127229691,47.2208175659],"type":"Point"}
}