{
  "type": "Feature",
  "properties": {
    "iso:country":"CH",
    "sg:address":"Rehetobelstrasse 39a",
    "sg:city":"St.gallen",
    "sg:orig_category":"Erbringung von Dienstleistungen f\u00fcr Unternehmen",
    "sg:postcode":"9000",
    "sg:province":"St. Gallen",
    "wof:name":"Informationsverlag Gmbh, St. Gallen",
    "wof:placetype":"venue"
},
  "geometry": {"coordinates":[9.4037971497,47.433216095],"type":"Point"}
}