{
  "type": "Feature",
  "properties": {
    "iso:country":"CH",
    "sg:address":"Lehwil 1714 Heitenried. Postfach",
    "sg:city":"Heitenried",
    "sg:orig_category":"Herstellung von Teppichen",
    "sg:postcode":"1714",
    "sg:province":"Fribourg",
    "wof:name":"Kiesel-ort Gmbh Steinb\u00f6den, Bes. Pflastersteinb\u00f6den; Planung, Gestaltung, Herstellung, U. Restaurierung Usw",
    "wof:placetype":"venue"
},
  "geometry": {"coordinates":[7.3815522194,46.9263839722],"type":"Point"}
}