{
  "type": "Feature",
  "properties": {
    "iso:country":"CH",
    "sg:address":"B\u00e4lliz 67",
    "sg:city":"Thun",
    "sg:orig_category":"Architekturb\u00fcros",
    "sg:phone":"+41 31 352 00 28",
    "sg:postcode":"3600",
    "sg:province":"Bern",
    "wof:name":"Peter Baum Architekturb\u00fcro",
    "wof:placetype":"venue"
},
  "geometry": {"coordinates":[7.43221,46.936996],"type":"Point"}
}