{
  "type": "Feature",
  "properties": {
    "addr:full":"Avenue De Tivoli 2 1007 Lausanne Case Postale 2232 Lausanne Vaud 1002",
    "addr:housenumber":"2",
    "addr:postcode":"1007;case postale 2232;1002",
    "addr:street":"Avenue De Tivoli",
    "iso:country":"CH",
    "sg:address":"Avenue De Tivoli 2 1007 Lausanne Case Postale 2232",
    "sg:city":"Lausanne",
    "sg:orig_category":"Architektur U Ingenieurb\u00fcros Architekturb\u00fcros",
    "sg:phone":"+41 21 922 62 74",
    "sg:postcode":"1002",
    "sg:province":"Vaud",
    "wof:name":"Bureau D'architecture, Collaud Eric",
    "wof:placetype":"venue"
},
  "geometry": {"coordinates":[5.60259,45.985413],"type":"Point"}
}