{
  "type": "Feature",
  "properties": {
    "iso:country":"CH",
    "sg:address":"Gr\u00fczenstrasse 10",
    "sg:city":"D\u00fcbendorf",
    "sg:orig_category":"Mechanik Mechanische Werkst\u00e4tten",
    "sg:phone":"+41 18217019",
    "sg:postcode":"8600",
    "sg:province":"Z\u00fcrich",
    "wof:name":"Alf. Pfister Inh.r.scherzinger Mechanische Werkst\u00e4tte",
    "wof:placetype":"venue"
},
  "geometry": {"coordinates":[8.6214094162,47.3945045471],"type":"Point"}
}