{
  "type": "Feature",
  "properties": {
    "addr:full":"Baumgarten Leissigen Bern 3706",
    "addr:postcode":"3706",
    "addr:street":"Baumgarten;Bern",
    "iso:country":"CH",
    "sg:address":"Baumgarten",
    "sg:city":"Leissigen",
    "sg:orig_category":"Bauschreinerei",
    "sg:phone":"+41 33 847 14 08",
    "sg:postcode":"3706",
    "sg:province":"Bern",
    "wof:name":"Roland Ringgenberg Schreinerei",
    "wof:placetype":"venue"
},
  "geometry": {"coordinates":[7.76952,46.65387],"type":"Point"}
}