{
  "type": "Feature",
  "properties": {
    "iso:country":"CH",
    "sg:address":"Hans-hugi-strasse 3 2502 Biel/bienne. Postfach",
    "sg:city":"Biel/bienne",
    "sg:orig_category":"Arztpraxen",
    "sg:phone":"+41 32 322 24 85",
    "sg:postcode":"2501",
    "sg:province":"Bern",
    "wof:name":"Dr.med.werner Niederer Spezialarzt Fmh",
    "wof:placetype":"venue"
},
  "geometry": {"coordinates":[7.24503,47.133167],"type":"Point"}
}