{
  "type": "Feature",
  "properties": {
    "iso:country":"CH",
    "sg:address":"Cossonay Route De 66 1008 Prilly. Postfach",
    "sg:city":"Prilly",
    "sg:orig_category":"Tankstellen",
    "sg:phone":"+41 41 870 33 18",
    "sg:postcode":"1008",
    "sg:province":"Vaud",
    "wof:name":"Migrol Service Huwyler Heinz Tankstelle Mit Shop U. Kiosk",
    "wof:placetype":"venue"
},
  "geometry": {"coordinates":[8.6265630722,46.8961486816],"type":"Point"}
}