{
  "type": "Feature",
  "properties": {
    "iso:country":"CH",
    "sg:address":"Brunnenhofstrasse 36",
    "sg:city":"Bolligen",
    "sg:orig_category":"Herstellung von k\u00e4lte U lufttechnischen Erzeugnissen f\u00fcr gewerbliche Zwecke Installation von Heizung",
    "sg:phone":"+41 31 921 23 45",
    "sg:postcode":"3065",
    "sg:province":"Bern",
    "wof:name":"Bucher B. Ag",
    "wof:placetype":"venue"
},
  "geometry": {"coordinates":[7.4908180237,46.9773101807],"type":"Point"}
}