{
  "type": "Feature",
  "properties": {
    "iso:country":"CH",
    "sg:address":"Welsikerstrasse 1",
    "sg:city":"Berg-d\u00e4gerlen",
    "sg:orig_category":"Architektur U Ingenieurb\u00fcros",
    "sg:phone":"+41 52 316 22 53",
    "sg:postcode":"8471",
    "sg:province":"Z\u00fcrich",
    "wof:name":"Brogle Peter",
    "wof:placetype":"venue"
},
  "geometry": {"coordinates":[8.730515,47.556416],"type":"Point"}
}