{
  "type": "Feature",
  "properties": {
    "iso:country":"CH",
    "sg:address":"Baumgartenweg 1 6233 B\u00fcron. Postfach",
    "sg:city":"B\u00fcron",
    "sg:orig_category":"S\u00e4ge, Hobel U Holzimpr\u00e4gnierwerke S\u00e4gewerke",
    "sg:phone":"+41 41 933 00 13",
    "sg:postcode":"6233",
    "sg:province":"Luzern",
    "wof:name":"Wyss Josef Ag",
    "wof:placetype":"venue"
},
  "geometry": {"coordinates":[8.0945615768,47.2128295898],"type":"Point"}
}