{
  "type": "Feature",
  "properties": {
    "iso:country":"CH",
    "sg:address":"Cordiers Rue Des 19 A 1207 Gen\u00e8ve. Postfach",
    "sg:city":"Gen\u00e8ve",
    "sg:orig_category":"Erbringung von Dienstleistungen f\u00fcr Unternehmen",
    "sg:postcode":"1207",
    "sg:province":"Gen\u00e8ve",
    "wof:name":"Style Et D\u00e9cor, Anzalone Gaetano",
    "wof:placetype":"venue"
},
  "geometry": {"coordinates":[6.1632790565,46.2033653259],"type":"Point"}
}