{
  "type": "Feature",
  "properties": {
    "iso:country":"CH",
    "sg:address":"Glattalstrasse 140",
    "sg:city":"R\u00fcmlang",
    "sg:orig_category":"Maler U Glasergewerbe",
    "sg:phone":"+41 18173287",
    "sg:postcode":"8153",
    "sg:province":"Z\u00fcrich",
    "wof:name":"Paint Art Malergesch\u00e4ft Pampanini",
    "wof:placetype":"venue"
},
  "geometry": {"coordinates":[8.5284767151,47.455329895],"type":"Point"}
}