{
  "type": "Feature",
  "properties": {
    "iso:country":"CH",
    "sg:address":"Rheinstrasse 172",
    "sg:city":"Chur",
    "sg:orig_category":"Fachdetailhandel in Verkaufsr\u00e4umen",
    "sg:phone":"+41 81 284 74 62",
    "sg:postcode":"7000",
    "sg:province":"Graubunden",
    "wof:name":"Karl Finda",
    "wof:placetype":"venue"
},
  "geometry": {"coordinates":[9.5146131516,46.8614196777],"type":"Point"}
}