{
  "type": "Feature",
  "properties": {
    "iso:country":"CH",
    "sg:address":"Gotthardstr. 137 6490 Andermatt. Postfach",
    "sg:city":"Andermatt",
    "sg:orig_category":"RESTAURANTS: TEA-ROOMS",
    "sg:postcode":"6490",
    "sg:province":"Uri",
    "wof:name":"Novoselac Ilija Restaurant Zum Schwarzen B\u00e4ren",
    "wof:placetype":"venue"
},
  "geometry": {"coordinates":[8.5945653915,46.6328659058],"type":"Point"}
}