{
  "type": "Feature",
  "properties": {
    "iso:country":"CH",
    "sg:address":"1714",
    "sg:city":"Heitenried",
    "sg:orig_category":"Mechanik",
    "sg:phone":"+41 32 951 25 22",
    "sg:postcode":"1714",
    "sg:province":"Fribourg",
    "wof:name":"Vorpe Steve",
    "wof:placetype":"venue"
},
  "geometry": {"coordinates":[6.9842767715,47.2712631226],"type":"Point"}
}