{
  "type": "Feature",
  "properties": {
    "iso:country":"CH",
    "sg:address":"Grottenweg 17",
    "sg:city":"Giffers",
    "sg:orig_category":"Sanit\u00e4r U Heizungsinstallation Sanit\u00e4r, Heizungs U L\u00fcftungsinstallation",
    "sg:phone":"+41 26 418 17 56",
    "sg:postcode":"1735",
    "sg:province":"Fribourg",
    "wof:name":"Walter Nydegger Ag",
    "wof:placetype":"venue"
},
  "geometry": {"coordinates":[7.2119078636,46.7566986084],"type":"Point"}
}