{
  "type": "Feature",
  "properties": {
    "iso:country":"CH",
    "sg:address":"Friedmattstrasse 5",
    "sg:city":"Reiden",
    "sg:orig_category":"Finanzierungsinstitutionen",
    "sg:phone":"+41 62 749 05 06",
    "sg:postcode":"6260",
    "sg:province":"Luzern",
    "wof:name":"Rieker Finanz Ag",
    "wof:placetype":"venue"
},
  "geometry": {"coordinates":[7.9687829018,47.2425613403],"type":"Point"}
}