{
  "type": "Feature",
  "properties": {
    "iso:country":"CH",
    "sg:address":"3925 Gr\u00e4chen. Postfach",
    "sg:city":"Gr\u00e4chen",
    "sg:orig_category":"Detailhandel mit Waren verschiedener Art, Hauptrichtung Nahrungsmittel",
    "sg:phone":"+41 27 956 29 49",
    "sg:postcode":"3925",
    "sg:province":"Valais",
    "wof:name":"Coop Center",
    "wof:placetype":"venue"
},
  "geometry": {"coordinates":[7.8392400742,46.1961631775],"type":"Point"}
}