{
  "type": "Feature",
  "properties": {
    "iso:country":"CH",
    "sg:address":"6017",
    "sg:city":"Ruswil",
    "sg:orig_category":"Erschliessung von Grundst\u00fccken",
    "sg:postcode":"6017",
    "sg:province":"Luzern",
    "wof:name":"Wohnbau-genossenschaft Wohlen 1948",
    "wof:placetype":"venue"
},
  "geometry": {"coordinates":[8.2746038437,47.3581085205],"type":"Point"}
}