{
  "type": "Feature",
  "properties": {
    "iso:country":"CH",
    "sg:address":"Bahnhofstrasse 106 8803 R\u00fcschlikon. Postfach 252",
    "sg:city":"R\u00fcschlikon",
    "sg:classifiers":[
        {
            "category":"Professional",
            "subcategory":"Employment Agencies",
            "type":"Services"
        }
    ],
    "sg:phone":"+41 17728787",
    "sg:postcode":"8803",
    "sg:province":"Z\u00fcrich",
    "sg:tags":[
        "personal",
        "u",
        "stellenvermittlung"
    ],
    "wof:name":"Usp Storrer & Partner",
    "wof:placetype":"venue"
},
  "geometry": {"coordinates":[8.5602903366,47.3026313782],"type":"Point"}
}