{
  "type": "Feature",
  "properties": {
    "iso:country":"CH",
    "sg:address":"Waldibr\u00fccke",
    "sg:city":"Emmen",
    "sg:orig_category":"Instandhaltung U Reparatur von Automobilen",
    "sg:phone":"+41 41 260 17 22",
    "sg:postcode":"6032",
    "sg:province":"Luzern",
    "wof:name":"Garage Mathis Ag",
    "wof:placetype":"venue"
},
  "geometry": {"coordinates":[8.3211450577,47.1101608276],"type":"Point"}
}