{
  "type": "Feature",
  "properties": {
    "iso:country":"CH",
    "sg:address":"Rue Gustave-muller-brun 4",
    "sg:city":"Genf",
    "sg:orig_category":"Sonstige mit der Informatik verbundene T\u00e4tigkeiten",
    "sg:postcode":"1200",
    "sg:province":"Gen\u00e8ve",
    "wof:name":"Ping Informatique, Vlacic Nikola",
    "wof:placetype":"venue"
},
  "geometry": {"coordinates":[6.16350317,46.1981277466],"type":"Point"}
}