{
  "type": "Feature",
  "properties": {
    "iso:country":"CH",
    "sg:address":"Klosbachstrasse 123 8032 Z\u00fcrich. Postfach",
    "sg:city":"Z\u00fcrich",
    "sg:orig_category":"Grosshandel mit Bekleidung",
    "sg:phone":"+41 12525559",
    "sg:postcode":"8030",
    "wof:name":"Fip Fashion Import Partners, Genossenschaft Unabh\u00e4ngiger Modeh\u00e4user",
    "wof:placetype":"venue"
},
  "geometry": {"coordinates":[8.5627689362,47.3691749573],"type":"Point"}
}