{
  "type": "Feature",
  "properties": {
    "iso:country":"CH",
    "sg:address":"Zolliker Strasse 60",
    "sg:city":"Zollikon",
    "sg:orig_category":"Wirtschaftspr\u00fcfung, Steuerberatung U Treuhand",
    "sg:phone":"+41 13891111",
    "sg:postcode":"8702",
    "sg:province":"Z\u00fcrich",
    "wof:name":"Sam Group Holding Ag",
    "wof:placetype":"venue"
},
  "geometry": {"coordinates":[8.5716466904,47.3408813477],"type":"Point"}
}