{
  "type": "Feature",
  "properties": {
    "iso:country":"CH",
    "sg:address":"Kasernenstrasse 10",
    "sg:city":"Herisau",
    "sg:orig_category":"Aktivit\u00e4ten der Krankenschwestern U Hebammen, Hauspflege Organisationen des Gesundheitswesen",
    "sg:phone":"+41 71 352 16 16",
    "sg:postcode":"9100",
    "sg:province":"Appenzell Ausserrhoden",
    "wof:name":"Spitex Haus-& Krankenpflegeverein",
    "wof:placetype":"venue"
},
  "geometry": {"coordinates":[9.281907,47.385864],"type":"Point"}
}