{
  "type": "Feature",
  "properties": {
    "iso:country":"CH",
    "sg:address":"Av. Daniel-jeanrichard 3",
    "sg:city":"Fleurier",
    "sg:orig_category":"Pensionskassen",
    "sg:postcode":"2114",
    "sg:province":"Neuch\u00e2tel",
    "wof:name":"Fondation De L'association Paritaire Interprofessionnelle De Fleurier",
    "wof:placetype":"venue"
},
  "geometry": {"coordinates":[6.5823202133,46.9052696228],"type":"Point"}
}