{
  "type": "Feature",
  "properties": {
    "iso:country":"CH",
    "sg:address":"Etraz Route De L'",
    "sg:city":"Vich",
    "sg:orig_category":"Handel mit Automobilen",
    "sg:phone":"+41 22 364 65 00",
    "sg:postcode":"1267",
    "sg:province":"Vaud",
    "wof:name":"Auto Style Sm, Morardo Silvano",
    "wof:placetype":"venue"
},
  "geometry": {"coordinates":[6.2602710724,46.4225234985],"type":"Point"}
}