{
  "type": "Feature",
  "properties": {
    "iso:country":"CH",
    "sg:address":"Hauptstrasse 54",
    "sg:city":"B\u00f6ckten",
    "sg:orig_category":"Architektur U Ingenieurb\u00fcros Architekturb\u00fcros",
    "sg:phone":"+41 61 981 54 34",
    "sg:postcode":"4461",
    "sg:province":"Basel-Landschaft",
    "wof:name":"Grieder Architektur Gmbh",
    "wof:placetype":"venue"
},
  "geometry": {"coordinates":[7.834563,47.462494],"type":"Point"}
}