{
  "type": "Feature",
  "properties": {
    "iso:country":"CH",
    "sg:address":"Cho D'punt 22",
    "sg:city":"Samedan",
    "sg:orig_category":"Abfallbeseitigung",
    "sg:phone":"+41 81 852 38 07",
    "sg:postcode":"7503",
    "sg:province":"Graubunden",
    "wof:name":"Roberto Costa Abfuhrwesen",
    "wof:placetype":"venue"
},
  "geometry": {"coordinates":[9.87283,46.535351],"type":"Point"}
}