{
  "type": "Feature",
  "properties": {
    "iso:country":"CH",
    "sg:address":"Via Guisan 6 6900 Paradiso. Postfach",
    "sg:city":"Paradiso",
    "sg:orig_category":"Wirtschaftspr\u00fcfung, Steuerberatung U Treuhand",
    "sg:phone":"+41 61 713 20 20",
    "sg:postcode":"6900",
    "sg:province":"Ticino",
    "wof:name":"Doppler Buchhaltungen",
    "wof:placetype":"venue"
},
  "geometry": {"coordinates":[7.5977578163,47.5044746399],"type":"Point"}
}