{
  "type": "Feature",
  "properties": {
    "iso:country":"CH",
    "sg:address":"Glariers Rue Des 1890 St-maurice. Postfach",
    "sg:city":"Dailly",
    "sg:orig_category":"Elektroinstallation",
    "sg:postcode":"1890",
    "sg:province":"Valais",
    "wof:name":"Bernard \u00e9lectricit\u00e9 S\u00e0rl Entreprise \u00e9lectricit\u00e9",
    "wof:placetype":"venue"
},
  "geometry": {"coordinates":[7.0044598579,46.2167739868],"type":"Point"}
}