{
  "type": "Feature",
  "properties": {
    "iso:country":"CH",
    "sg:address":"P\u00eacheurs Rue Des 8 1400 Yverdon-les-bains. Postfach",
    "sg:city":"Cheseaux-nor\u00e9az",
    "sg:orig_category":"R\u00fcckgewinnung U Vorbereitung f\u00fcr die Wiederverwertung Recycling von nichtmetallischen Altmaterialien",
    "sg:phone":"+41 24 420 23 60",
    "sg:postcode":"1400",
    "sg:province":"Vaud",
    "wof:name":"Ecod\u00e9chets (yverdon) S\u00e0rl Bureau De Conseils Sp\u00e9cialis\u00e9 Dans La Gestion Des D\u00e9chets",
    "wof:placetype":"venue"
},
  "geometry": {"coordinates":[6.6447529793,46.7814865112],"type":"Point"}
}