{
  "type": "Feature",
  "properties": {
    "iso:country":"CH",
    "sg:address":"B\u00f6dahus",
    "sg:city":"Parpan",
    "sg:orig_category":"Sportvereine Sch\u00fctzen",
    "sg:postcode":"7076",
    "sg:province":"Graubunden",
    "wof:name":"Sch\u00fctzengesellschaft",
    "wof:placetype":"venue"
},
  "geometry": {"coordinates":[9.5574197769,46.7601356506],"type":"Point"}
}