{
  "type": "Feature",
  "properties": {
    "iso:country":"CH",
    "sg:address":"Fronwagplatz 10",
    "sg:city":"Schaffhausen",
    "sg:orig_category":"Detailhandel mit Brillen U anderen Sehhilfen Fachdetailhandel in Verkaufsr\u00e4umen",
    "sg:phone":"+41 61 620 06 25",
    "sg:postcode":"8200",
    "sg:province":"Schaffhausen",
    "wof:name":"Fielmann Ag Brillenfachgesch\u00e4ft",
    "wof:placetype":"venue"
},
  "geometry": {"coordinates":[8.633689,47.696697],"type":"Point"}
}