{
  "type": "Feature",
  "properties": {
    "iso:country":"CH",
    "sg:address":"Husacherweg 280",
    "sg:city":"Unterb\u00f6zberg",
    "sg:orig_category":"Detailhandel mit Uhren U Schmuck Herstellung von Schmuck, Gold U Silberschmiedwaren",
    "sg:phone":"+41 56 442 30 40",
    "sg:postcode":"5224",
    "sg:province":"Aargau",
    "wof:name":"Messmer & Tschupp Goldschmiedeatelier",
    "wof:placetype":"venue"
},
  "geometry": {"coordinates":[8.1458272934,47.4858055115],"type":"Point"}
}