{
  "type": "Feature",
  "properties": {
    "iso:country":"CH",
    "sg:address":"Imm. La Bruy\u00e8re",
    "sg:city":"Aproz",
    "sg:orig_category":"Unclassifiable Establishments",
    "sg:postcode":"1994",
    "sg:province":"Valais",
    "wof:name":"Alarick Sa",
    "wof:placetype":"venue"
},
  "geometry": {"coordinates":[7.3128399849,46.2063903809],"type":"Point"}
}