{
  "type": "Feature",
  "properties": {
    "iso:country":"CH",
    "sg:address":"Kirchstrasse 14",
    "sg:city":"Mels",
    "sg:orig_category":"Architekturb\u00fcros",
    "sg:phone":"+41 81 710 06 10",
    "sg:postcode":"8887",
    "sg:province":"St. Gallen",
    "wof:name":"Linus Good Architekturb\u00fcro",
    "wof:placetype":"venue"
},
  "geometry": {"coordinates":[9.4206,47.047134],"type":"Point"}
}