{
  "type": "Feature",
  "properties": {
    "iso:country":"CH",
    "sg:address":"Hammer 19",
    "sg:city":"Aarau",
    "sg:orig_category":"Unternehmensberatung",
    "sg:phone":"+41 62 836 90 30",
    "sg:postcode":"5000",
    "sg:province":"Aargau",
    "wof:name":"Stellwerk Entwicklungsberatung Von Passavant Chr.",
    "wof:placetype":"venue"
},
  "geometry": {"coordinates":[8.0445137024,47.3945045471],"type":"Point"}
}