{
  "type": "Feature",
  "properties": {
    "iso:country":"CH",
    "sg:address":"Hugi Rue Hans- 3 2502 Biel/bienne. Postfach",
    "sg:city":"Biel/bienne",
    "sg:orig_category":"Markt U Meinungsforschung",
    "sg:phone":"+41 32 328 16 51",
    "sg:postcode":"2502",
    "sg:province":"Bern",
    "wof:name":"Asvm Broglie",
    "wof:placetype":"venue"
},
  "geometry": {"coordinates":[7.2450299263,47.1331672668],"type":"Point"}
}