{
  "type": "Feature",
  "properties": {
    "iso:country":"CH",
    "sg:address":"Lachenal Rue Adrien- 20 1207 Gen\u00e8ve. Postfach",
    "sg:city":"Gen\u00e8ve",
    "sg:orig_category":"Finanzierungsinstitutionen",
    "sg:phone":"+41 22 786 33 35",
    "sg:postcode":"1207",
    "sg:province":"Gen\u00e8ve",
    "wof:name":"Going Public Sa",
    "wof:placetype":"venue"
},
  "geometry": {"coordinates":[6.1560301781,46.1997451782],"type":"Point"}
}