{
  "type": "Feature",
  "properties": {
    "iso:country":"CH",
    "sg:address":"Altstetterstrasse 145",
    "sg:city":"Z\u00fcrich",
    "sg:orig_category":"Detailhandel mit Damenbekleidung",
    "sg:phone":"+41 14332260",
    "sg:postcode":"8048",
    "sg:province":"Z\u00fcrich",
    "wof:name":"Latino Sa Mode Zebra",
    "wof:placetype":"venue"
},
  "geometry": {"coordinates":[8.486906,47.388641],"type":"Point"}
}