{
  "type": "Feature",
  "properties": {
    "iso:country":"CH",
    "sg:address":"Alpsteinstrasse 2",
    "sg:city":"Uzwil",
    "sg:orig_category":"Unclassifiable Establishments",
    "sg:postcode":"9240",
    "sg:province":"St. Gallen",
    "wof:name":"Markus Bernet Managing Real Estate",
    "wof:placetype":"venue"
},
  "geometry": {"coordinates":[9.1260538101,47.4401626587],"type":"Point"}
}