{
  "type": "Feature",
  "properties": {
    "iso:country":"CH",
    "sg:address":"Elvezia Corso 4 6900 Lugano. Postfach",
    "sg:city":"Lugano",
    "sg:orig_category":"Fachdetailhandel mit pharmazeutischen Produkten",
    "sg:phone":"+41 24 425 13 44",
    "sg:postcode":"6900",
    "sg:province":"Ticino",
    "wof:name":"Prospa Sa",
    "wof:placetype":"venue"
},
  "geometry": {"coordinates":[8.9557991028,46.0064582825],"type":"Point"}
}