{
  "type": "Feature",
  "properties": {
    "iso:country":"CH",
    "sg:address":"Via Nocca 20",
    "sg:city":"Bellinzona",
    "sg:classifiers":[
        {
            "category":"Travel",
            "subcategory":"Hotels & Motels",
            "type":"Entertainment"
        }
    ],
    "sg:phone":"+41 91 825 13 32",
    "sg:postcode":"6500",
    "sg:province":"Ticino",
    "sg:tags":[
        "hotels",
        "mit",
        "restaurant"
    ],
    "wof:name":"Albergo Locanda Marco",
    "wof:placetype":"venue"
},
  "geometry": {"coordinates":[9.0248794556,46.1884765625],"type":"Point"}
}