{
  "type": "Feature",
  "properties": {
    "iso:country":"CH",
    "sg:address":"Aegeristrasse 3",
    "sg:city":"Zug",
    "sg:orig_category":"Non-Classified Establishments",
    "sg:postcode":"6300",
    "sg:province":"Zug",
    "wof:name":"Luigi Turrini Coiffeursalon",
    "wof:placetype":"venue"
},
  "geometry": {"coordinates":[8.5162172318,47.1662483215],"type":"Point"}
}