{
  "type": "Feature",
  "properties": {
    "iso:country":"CH",
    "sg:address":"Via San Gottardo 72",
    "sg:city":"Minusio",
    "sg:orig_category":"Softwareentwicklung U beratung",
    "sg:phone":"+41 41 672 71 71",
    "sg:postcode":"6648",
    "sg:province":"Ticino",
    "wof:name":"Navision Software (schweiz) Ag",
    "wof:placetype":"venue"
},
  "geometry": {"coordinates":[8.2701597214,46.9373588562],"type":"Point"}
}