{
  "type": "Feature",
  "properties": {
    "iso:country":"CH",
    "sg:address":"Zone Industrielle La Rippe",
    "sg:city":"Penthaz",
    "sg:orig_category":"Instandhaltung U Reparatur von Automobilen",
    "sg:phone":"+41 21 862 74 84",
    "sg:postcode":"1303",
    "sg:province":"Vaud",
    "wof:name":"Olivier Marguet Garage & Carrosserie",
    "wof:placetype":"venue"
},
  "geometry": {"coordinates":[6.5384898186,46.5996818542],"type":"Point"}
}