{
  "type": "Feature",
  "properties": {
    "iso:country":"CH",
    "sg:address":"Z\u00fcrcherstrasse 24",
    "sg:city":"Siebnen",
    "sg:orig_category":"RESTAURANTS: TEA-ROOMS",
    "sg:phone":"+41 55 442 19 55",
    "sg:postcode":"8854",
    "sg:province":"Schwyz",
    "wof:name":"Restaurant Traube, Ganahl Rudolf",
    "wof:placetype":"venue"
},
  "geometry": {"coordinates":[8.8520145416,47.1928672791],"type":"Point"}
}