{
  "type": "Feature",
  "properties": {
    "iso:country":"CH",
    "sg:address":"Oberlandstrasse 47",
    "sg:city":"Spiez",
    "sg:orig_category":"Detailhandel mit Textilien Sonstiges Textilgewerbe",
    "sg:phone":"+41 71 223 62 80",
    "sg:postcode":"3700",
    "sg:province":"Bern",
    "wof:name":"Anette-stoffe Fend Elisabeth",
    "wof:placetype":"venue"
},
  "geometry": {"coordinates":[9.3748292923,47.4230690002],"type":"Point"}
}