{
  "type": "Feature",
  "properties": {
    "iso:country":"CH",
    "sg:address":"Untere Vogelsangstrasse 11 8400 Winterthur. Postfach",
    "sg:city":"Winterthur",
    "sg:orig_category":"Elektroinstallation",
    "sg:phone":"+41 52 267 61 61",
    "sg:postcode":"8402",
    "sg:province":"Z\u00fcrich",
    "wof:name":"St\u00e4dtische Werke Winterthur Elektroinstallationsgesch\u00e4ft",
    "wof:placetype":"venue"
},
  "geometry": {"coordinates":[8.7223701477,47.4969749451],"type":"Point"}
}