{
  "type": "Feature",
  "properties": {
    "iso:country":"CH",
    "sg:address":"Wiesenstrasse 1",
    "sg:city":"Langenthal",
    "sg:orig_category":"Sonstige mit der Informatik verbundene T\u00e4tigkeiten",
    "sg:phone":"+41 62 923 76 76",
    "sg:postcode":"4900",
    "sg:province":"Bern",
    "wof:name":"3w-publishing Ag",
    "wof:placetype":"venue"
},
  "geometry": {"coordinates":[7.7883028984,47.2118873596],"type":"Point"}
}