{
  "type": "Feature",
  "properties": {
    "iso:country":"CH",
    "sg:address":"Stetterstrasse 60",
    "sg:city":"Mellingen",
    "sg:orig_category":"G\u00fcterbef\u00f6rderung im Strassenverkehr",
    "sg:postcode":"5507",
    "sg:province":"Aargau",
    "wof:name":"Hermann Halter",
    "wof:placetype":"venue"
},
  "geometry": {"coordinates":[8.2815656662,47.4164276123],"type":"Point"}
}