{
  "type": "Feature",
  "properties": {
    "iso:country":"CH",
    "sg:address":"Herrenberg 56",
    "sg:city":"Ermensee",
    "sg:orig_category":"Herstellung von Heizk\u00f6rpern U kesseln f\u00fcr die Zentralheizung",
    "sg:postcode":"6294",
    "sg:province":"Luzern",
    "wof:name":"Atx Suisse Gmbh",
    "wof:placetype":"venue"
},
  "geometry": {"coordinates":[8.2398118973,47.2219047546],"type":"Point"}
}