{
  "type": "Feature",
  "properties": {
    "iso:country":"CH",
    "sg:address":"Aegertenstrasse 1a 2562 Port. Postfach",
    "sg:city":"Port",
    "sg:orig_category":"Herstellung von Kunststoffwaren Herstellung von sonstigen Kunststoffwaren",
    "sg:phone":"+41 31 839 99 77",
    "sg:postcode":"2562",
    "sg:province":"Bern",
    "wof:name":"K. Hofer, Hoco-schaumstoffe",
    "wof:placetype":"venue"
},
  "geometry": {"coordinates":[7.5612258911,46.930644989],"type":"Point"}
}