{
  "type": "Feature",
  "properties": {
    "iso:country":"CH",
    "sg:address":"Via Fontana 13",
    "sg:city":"Balerna",
    "sg:orig_category":"Detailhandel mit Fleisch U Fleischwaren Grosshandel mit Fleisch U Fleischwaren",
    "sg:phone":"+41 91 683 30 33",
    "sg:postcode":"6828",
    "sg:province":"Ticino",
    "wof:name":"Federico Francini",
    "wof:placetype":"venue"
},
  "geometry": {"coordinates":[9.0059642792,45.8504981995],"type":"Point"}
}