{
  "type": "Feature",
  "properties": {
    "iso:country":"CH",
    "sg:address":"Waldweg 8",
    "sg:city":"Orpund",
    "sg:orig_category":"Detailhandel mit Teppichen Verlegen von Fussboden",
    "sg:phone":"+41 32 355 22 61",
    "sg:postcode":"2552",
    "sg:province":"Bern",
    "wof:name":"Rowabo Bodenbel\u00e4ge Parkett Teppiche",
    "wof:placetype":"venue"
},
  "geometry": {"coordinates":[7.3001289368,47.1417579651],"type":"Point"}
}