{
  "type": "Feature",
  "properties": {
    "iso:country":"CH",
    "sg:address":"Breitingerstrasse 17",
    "sg:city":"Z\u00fcrich",
    "sg:orig_category":"Zahnarztpraxen",
    "sg:phone":"+41 12411835",
    "sg:postcode":"8002",
    "sg:province":"Z\u00fcrich",
    "wof:name":"Dr.med.dent.ruthebert Fischer Zahnarzt",
    "wof:placetype":"venue"
},
  "geometry": {"coordinates":[8.8032541275,47.3292655945],"type":"Point"}
}