{
  "type": "Feature",
  "properties": {
    "iso:country":"CH",
    "sg:address":"Via Peri 2",
    "sg:city":"Lugano",
    "sg:orig_category":"Wirtschaftspr\u00fcfung, Steuerberatung U Treuhand",
    "sg:phone":"+41 91 921 07 61",
    "sg:postcode":"6900",
    "sg:province":"Ticino",
    "wof:name":"Renzo Polato Studio Fiduciario",
    "wof:placetype":"venue"
},
  "geometry": {"coordinates":[8.9508810043,46.0053215027],"type":"Point"}
}