{
  "type": "Feature",
  "properties": {
    "iso:country":"CH",
    "sg:address":"Rietgasse 2",
    "sg:city":"Kaltbrunn",
    "sg:orig_category":"Architektur U Ingenieurb\u00fcros",
    "sg:postcode":"8722",
    "sg:province":"St. Gallen",
    "wof:name":"Gujer Engineering",
    "wof:placetype":"venue"
},
  "geometry": {"coordinates":[9.013602,47.21627],"type":"Point"}
}