{
  "type": "Feature",
  "properties": {
    "iso:country":"CH",
    "sg:address":"Riedweg 9 8424 Embrach. Postfach",
    "sg:city":"Embrach",
    "sg:orig_category":"Architektur U Ingenieurb\u00fcros",
    "sg:postcode":"8424",
    "sg:province":"Z\u00fcrich",
    "wof:name":"Baechi Ernst",
    "wof:placetype":"venue"
},
  "geometry": {"coordinates":[8.592447,47.505604],"type":"Point"}
}