{
  "type": "Feature",
  "properties": {
    "iso:country":"CH",
    "sg:address":"Nordstrasse 62",
    "sg:city":"Z\u00fcrich",
    "sg:orig_category":"Sonstiger Grosshandel",
    "sg:postcode":"8006",
    "sg:province":"Z\u00fcrich",
    "wof:name":"Fritz S.",
    "wof:placetype":"venue"
},
  "geometry": {"coordinates":[8.5376091003,47.3868026733],"type":"Point"}
}