{
  "type": "Feature",
  "properties": {
    "iso:country":"CH",
    "sg:address":"Postg. 1",
    "sg:city":"Interlaken",
    "sg:classifiers":[
        {
            "category":"Travel",
            "subcategory":"Hotels & Motels",
            "type":"Entertainment"
        }
    ],
    "sg:phone":"+41 33 827 87 87",
    "sg:postcode":"3800",
    "sg:province":"Bern",
    "sg:tags":[
        "hotels",
        "business",
        "restaurant"
    ],
    "wof:name":"Chalet-hotel Oberland",
    "wof:placetype":"venue"
},
  "geometry": {"coordinates":[7.853437,46.684479],"type":"Point"}
}