{
  "type": "Feature",
  "properties": {
    "iso:country":"CH",
    "sg:address":"Hausacherstrasse 48",
    "sg:city":"Binz",
    "sg:orig_category":"Sportvereine Turnen Vereine Damen",
    "sg:phone":"+41 19804731",
    "sg:postcode":"8122",
    "sg:province":"Z\u00fcrich",
    "wof:name":"Svkt St.anton",
    "wof:placetype":"venue"
},
  "geometry": {"coordinates":[8.627737999,47.3589744568],"type":"Point"}
}