{
  "type": "Feature",
  "properties": {
    "iso:country":"CH",
    "sg:address":"Neuengasse 31",
    "sg:city":"Biel/bienne",
    "sg:orig_category":"Fachdetailhandel in Verkaufsr\u00e4umen",
    "sg:postcode":"2500",
    "sg:province":"Bern",
    "wof:name":"Grindat Regenbekleidung",
    "wof:placetype":"venue"
},
  "geometry": {"coordinates":[7.2448539734,47.138343811],"type":"Point"}
}