{
  "type": "Feature",
  "properties": {
    "iso:country":"CH",
    "sg:address":"Route Des Jeunes 1",
    "sg:city":"Gen\u00e8ve",
    "sg:orig_category":"Unternehmensberatung",
    "sg:postcode":"1200",
    "sg:province":"Gen\u00e8ve",
    "wof:name":"Firmenich International Sa",
    "wof:placetype":"venue"
},
  "geometry": {"coordinates":[6.1282281876,46.1970787048],"type":"Point"}
}