{
  "type": "Feature",
  "properties": {
    "iso:country":"CH",
    "sg:address":"Bahnhofplatz 1",
    "sg:city":"Trubschachen",
    "sg:orig_category":"Grosshandel mit Datenverarbeitungsger\u00e4ten Grosshandel mit Software",
    "sg:phone":"+41 34 461 60 77",
    "sg:postcode":"3555",
    "sg:province":"Bern",
    "wof:name":"Dietlenberger Gmbh",
    "wof:placetype":"venue"
},
  "geometry": {"coordinates":[7.6849250793,47.0063858032],"type":"Point"}
}