{
  "type": "Feature",
  "properties": {
    "iso:country":"CH",
    "sg:address":"Ch. Des Tires 6-8 2034 Peseux. Postfach",
    "sg:city":"Peseux",
    "sg:orig_category":"Pensionskassen",
    "sg:phone":"+41 32 737 10 20",
    "sg:postcode":"2034",
    "sg:province":"Neuch\u00e2tel",
    "wof:name":"Fonds De Pr\u00e9voyance De Sicodor, Sa Industrielle Et Commerciale D'orf\u00e8vrerie",
    "wof:placetype":"venue"
},
  "geometry": {"coordinates":[6.8867850304,46.9829292297],"type":"Point"}
}