{
  "type": "Feature",
  "properties": {
    "iso:country":"CH",
    "sg:address":"Sagenbachstrasse 23",
    "sg:city":"Gersau",
    "sg:orig_category":"Personenbef\u00f6rderung im Linienverkehr zu Land",
    "sg:postcode":"6442",
    "sg:province":"Schwyz",
    "wof:name":"Luftseilbahn Obergschwend-rigi-burggeist Ag",
    "wof:placetype":"venue"
},
  "geometry": {"coordinates":[8.5237321854,46.9952430725],"type":"Point"}
}