{
  "type": "Feature",
  "properties": {
    "iso:country":"CH",
    "sg:address":"Seestrasse 3 3700 Spiez. Postfach",
    "sg:city":"Spiez",
    "sg:orig_category":"Zahnarztpraxen",
    "sg:phone":"+41 61 641 44 50",
    "sg:postcode":"3700",
    "sg:province":"Bern",
    "wof:name":"Dr. Med. Dent. Andreas Borner Zahnarzt",
    "wof:placetype":"venue"
},
  "geometry": {"coordinates":[7.6544280052,47.584186554],"type":"Point"}
}