{
  "type": "Feature",
  "properties": {
    "iso:country":"CH",
    "sg:address":"Grand-rue",
    "sg:city":"Ch\u00e2tel-st-denis",
    "sg:orig_category":"Physiotherapie",
    "sg:phone":"+41 55 410 70 72",
    "sg:postcode":"1618",
    "sg:province":"Fribourg",
    "wof:name":"G\u00e9rard Janssens Physiotherapie",
    "wof:placetype":"venue"
},
  "geometry": {"coordinates":[8.7784986496,47.2003517151],"type":"Point"}
}