{
  "type": "Feature",
  "properties": {
    "iso:country":"CH",
    "sg:address":"Avenue Mon-repos 14",
    "sg:city":"Lausanne",
    "sg:orig_category":"Datenverarbeitungsdienste Sonstige mit der Informatik verbundene T\u00e4tigkeiten",
    "sg:phone":"+41 81 322 68 18",
    "sg:postcode":"1005",
    "sg:province":"Vaud",
    "wof:name":"Wyler Informatik & Co",
    "wof:placetype":"venue"
},
  "geometry": {"coordinates":[9.562748,46.970028],"type":"Point"}
}