{
  "type": "Feature",
  "properties": {
    "iso:country":"CH",
    "sg:address":"Kirchmatte 376",
    "sg:city":"Gontenschwil",
    "sg:orig_category":"Vermietung U Verpachtung von eigenen Immobilien",
    "sg:postcode":"5728",
    "sg:province":"Aargau",
    "wof:name":"Rutrag Ag",
    "wof:placetype":"venue"
},
  "geometry": {"coordinates":[9.0723829269,47.3999328613],"type":"Point"}
}