{
  "type": "Feature",
  "properties": {
    "iso:country":"CH",
    "sg:address":"Rue Centrale 56",
    "sg:city":"Ani\u00e8res",
    "sg:orig_category":"Vorschulen, Kinderg\u00e4rten",
    "sg:phone":"+41 32 931 24 50",
    "sg:postcode":"1247",
    "sg:province":"Gen\u00e8ve",
    "wof:name":"Ecole Enfantine I & Ii",
    "wof:placetype":"venue"
},
  "geometry": {"coordinates":[6.7515478134,47.0516929626],"type":"Point"}
}