{
  "type": "Feature",
  "properties": {
    "iso:country":"CH",
    "sg:address":"Borde Rue De La 22bis 1018 Lausanne. Postfach",
    "sg:city":"Lausanne",
    "sg:orig_category":"Sonstiges Versicherungsgewerbe",
    "sg:phone":"+41 27 722 80 17",
    "sg:postcode":"1018",
    "sg:province":"Vaud",
    "wof:name":"Lavanchy Patrick",
    "wof:placetype":"venue"
},
  "geometry": {"coordinates":[7.0716500282,46.100818634],"type":"Point"}
}