{
  "type": "Feature",
  "properties": {
    "addr:full":"Rue Du Simplon 40 Vevey Vaud 1800",
    "addr:housenumber":"40",
    "addr:postcode":"1800",
    "addr:street":"Rue Du Simplon",
    "iso:country":"CH",
    "sg:address":"Rue Du Simplon 40",
    "sg:city":"Vevey",
    "sg:orig_category":"Architekturb\u00fcros",
    "sg:phone":"+41 21 922 74 64",
    "sg:postcode":"1800",
    "sg:province":"Vaud",
    "wof:name":"Yves Callet-molin Bureau D'architecture",
    "wof:placetype":"venue"
},
  "geometry": {"coordinates":[6.844197,46.46085],"type":"Point"}
}