{
  "type": "Feature",
  "properties": {
    "iso:country":"CH",
    "sg:address":"Hauptstrasse 108",
    "sg:city":"Zetzwil",
    "sg:orig_category":"Detailhandel mit Milcherzeugnissen U Eiern Verarbeitung von Milch",
    "sg:postcode":"5732",
    "sg:province":"Aargau",
    "wof:name":"K\u00e4sereigenossenschaft Zetzwil",
    "wof:placetype":"venue"
},
  "geometry": {"coordinates":[8.1551046371,47.2812805176],"type":"Point"}
}