{
  "type": "Feature",
  "properties": {
    "iso:country":"CH",
    "sg:address":"M\u00fchlehofstrasse 9",
    "sg:city":"Reiden",
    "sg:classifiers":[
        {
            "category":"Retail",
            "subcategory":"Event Space",
            "type":"Services"
        }
    ],
    "sg:phone":"+41 62 749 01 11",
    "sg:postcode":"6260",
    "sg:province":"Luzern",
    "sg:tags":[
        "knitting",
        "yarn"
    ],
    "wof:name":"Lang & Co",
    "wof:placetype":"venue"
},
  "geometry": {"coordinates":[7.9689321518,47.2390899658],"type":"Point"}
}