{
  "type": "Feature",
  "properties": {
    "iso:country":"CH",
    "sg:address":"Solothurnstrasse 18 4542 Luterbach. Postfach",
    "sg:city":"Luterbach",
    "sg:orig_category":"Detailhandel mit Schuhen Detailhandel mit Schuhen U Lederwaren",
    "sg:phone":"+41 32 682 33 54",
    "sg:postcode":"4542",
    "sg:province":"Solothurn",
    "wof:name":"Schuhhaus Jordi",
    "wof:placetype":"venue"
},
  "geometry": {"coordinates":[7.5854411125,47.2154045105],"type":"Point"}
}