{
  "type": "Feature",
  "properties": {
    "iso:country":"CH",
    "sg:address":"Wallisellerstrasse 96",
    "sg:city":"Glattbrugg",
    "sg:orig_category":"Lampen and Beleuchtungsk\u00f6rper Grosshandel M\u00f6belveredelung U restaurierung",
    "sg:phone":"+41 18116600",
    "sg:postcode":"8152",
    "sg:province":"Z\u00fcrich",
    "wof:name":"Theres Glausen Lampenschirmatelier",
    "wof:placetype":"venue"
},
  "geometry": {"coordinates":[8.5713300705,47.4327392578],"type":"Point"}
}