{
  "type": "Feature",
  "properties": {
    "iso:country":"CH",
    "sg:address":"Clubhaus Im Weyer",
    "sg:city":"Rothrist",
    "sg:classifiers":[
        {
            "category":"Sports & Exercise",
            "subcategory":"Tennis Court",
            "type":"Entertainment"
        }
    ],
    "sg:phone":"+41 18701312",
    "sg:postcode":"4852",
    "sg:province":"Aargau",
    "sg:tags":[
        "squash-centers",
        "hallen",
        "tennis-"
    ],
    "wof:name":"Tennisanlage Des Tennisclubs Biber",
    "wof:placetype":"venue"
},
  "geometry": {"coordinates":[8.4599437714,47.4459037781],"type":"Point"}
}