{
  "type": "Feature",
  "properties": {
    "iso:country":"CH",
    "sg:address":"Haldenstrasse 11",
    "sg:city":"Luzern",
    "sg:orig_category":"Non-Classified Establishments",
    "sg:postcode":"6006",
    "sg:province":"Luzern",
    "wof:name":"Pole's Autokosmetik Gmbh",
    "wof:placetype":"venue"
},
  "geometry": {"coordinates":[9.4193458557,47.4391212463],"type":"Point"}
}