{
  "type": "Feature",
  "properties": {
    "iso:country":"CH",
    "sg:address":"Hettlingerstrasse 1",
    "sg:city":"Seuzach",
    "sg:orig_category":"Instandhaltung U Reparatur von Automobilen",
    "sg:phone":"+41 79 620 44 47",
    "sg:postcode":"8472",
    "sg:province":"Z\u00fcrich",
    "wof:name":"Auto Rumpf Gmbh",
    "wof:placetype":"venue"
},
  "geometry": {"coordinates":[8.7294340134,47.5372810364],"type":"Point"}
}