{
  "type": "Feature",
  "properties": {
    "iso:country":"CH",
    "sg:address":"Weid 1",
    "sg:city":"Winznau",
    "sg:orig_category":"Unclassifiable Establishments",
    "sg:postcode":"4652",
    "sg:province":"Solothurn",
    "wof:name":"Spielmann C. Montagen Und Unterhalt",
    "wof:placetype":"venue"
},
  "geometry": {"coordinates":[7.928041935,47.3709144592],"type":"Point"}
}