{
  "type": "Feature",
  "properties": {
    "iso:country":"CH",
    "sg:address":"Gossauerstrasse 7",
    "sg:city":"Niederb\u00fcren",
    "sg:orig_category":"Maler U Glasergewerbe",
    "sg:phone":"+41 71 422 67 77",
    "sg:postcode":"9246",
    "sg:province":"St. Gallen",
    "wof:name":"Malergesch\u00e4ft Gerster Gmbh",
    "wof:placetype":"venue"
},
  "geometry": {"coordinates":[9.2181978226,47.4546699524],"type":"Point"}
}