{
  "type": "Feature",
  "properties": {
    "iso:country":"CH",
    "sg:address":"Zihlstrasse 37",
    "sg:city":"Gr\u00e4nichen",
    "sg:orig_category":"G\u00fcterbef\u00f6rderung im Strassenverkehr",
    "sg:phone":"+41 26 915 23 15",
    "sg:postcode":"5722",
    "sg:province":"Aargau",
    "wof:name":"Bapst Andr\u00e9.",
    "wof:placetype":"venue"
},
  "geometry": {"coordinates":[7.0685901642,46.6771697998],"type":"Point"}
}