{
  "type": "Feature",
  "properties": {
    "addr:full":"Widen 7 Bauma Z\u00fcrich 8494",
    "addr:housenumber":"7",
    "addr:postcode":"8494",
    "addr:street":"Widen",
    "iso:country":"CH",
    "sg:address":"Widen 7",
    "sg:city":"Bauma",
    "sg:classifiers":[
        {
            "category":"Banks & Credit Unions",
            "subcategory":"Investment Brokerage",
            "type":"Services"
        }
    ],
    "sg:phone":"+41 52 394 15 90",
    "sg:postcode":"8494",
    "sg:province":"Z\u00fcrich",
    "sg:tags":[
        "cnc",
        "milling"
    ],
    "wof:name":"Birol Sevic Mechanik",
    "wof:placetype":"venue"
},
  "geometry": {"coordinates":[8.866107,47.370182],"type":"Point"}
}