{
  "type": "Feature",
  "properties": {
    "addr:full":"Route Des Ilettes 6 1869 Massongex. Postfach Massongex Valais 1869",
    "addr:housenumber":"6",
    "addr:postcode":"1869 massongex. postfach;1869",
    "addr:street":"Route Des Ilettes",
    "iso:country":"CH",
    "sg:address":"Route Des Ilettes 6 1869 Massongex. Postfach",
    "sg:city":"Massongex",
    "sg:orig_category":"Allgemeiner Hoch U Tiefbau Allgemeiner Hochbau",
    "sg:phone":"+41 27 203 43 61",
    "sg:postcode":"1869",
    "sg:province":"Valais",
    "wof:name":"Losinger Sion Sa Succursale De Massongex",
    "wof:placetype":"venue"
},
  "geometry": {"coordinates":[6.984791,46.241451],"type":"Point"}
}