{
  "type": "Feature",
  "properties": {
    "iso:country":"CH",
    "sg:address":"Emmenstrasse 2",
    "sg:city":"Malters",
    "sg:orig_category":"Selbst\u00e4ndige bildende K\u00fcnstler",
    "sg:phone":"+41 41 497 10 25",
    "sg:postcode":"6102",
    "sg:province":"Luzern",
    "wof:name":"Hans Ulmi Bildhauer-atelier",
    "wof:placetype":"venue"
},
  "geometry": {"coordinates":[8.1777629852,47.0426483154],"type":"Point"}
}