{
  "type": "Feature",
  "properties": {
    "iso:country":"CH",
    "sg:address":"R\u00f6sslimatt 5",
    "sg:city":"Hellb\u00fchl",
    "sg:orig_category":"Public-Relations-Agenturen Werbeagenturen",
    "sg:phone":"+41 41 468 01 68",
    "sg:postcode":"6016",
    "sg:province":"Luzern",
    "wof:name":"Kunz Marketing & Promotion",
    "wof:placetype":"venue"
},
  "geometry": {"coordinates":[8.1972322464,47.0718460083],"type":"Point"}
}