{
  "type": "Feature",
  "properties": {
    "addr:full":"Kirchgasse 16 Kloten Z\u00fcrich 8302",
    "addr:housenumber":"16",
    "addr:postcode":"8302",
    "addr:street":"Kirchgasse",
    "iso:country":"CH",
    "sg:address":"Kirchgasse 16",
    "sg:city":"Kloten",
    "sg:orig_category":"Aktivit\u00e4ten der Krankenschwestern U Hebammen, Hauspflege Organisationen des Gesundheitswesen",
    "sg:phone":"+41 18140660",
    "sg:postcode":"8302",
    "sg:province":"Z\u00fcrich",
    "wof:name":"Spitex-zentrum Kloten",
    "wof:placetype":"venue"
},
  "geometry": {"coordinates":[8.583274,47.451599],"type":"Point"}
}