{
  "type": "Feature",
  "properties": {
    "iso:country":"CH",
    "sg:address":"Brunnacker.",
    "sg:city":"Eriswil",
    "sg:orig_category":"Herstellung von Konstruktionsteilen, Fertigbauteilen U Ausbauelementen aus Holz",
    "sg:phone":"+41 62 966 15 12",
    "sg:postcode":"4952",
    "sg:province":"Bern",
    "wof:name":"Mathys Oskar.",
    "wof:placetype":"venue"
},
  "geometry": {"coordinates":[7.8572969437,47.0824584961],"type":"Point"}
}