{
  "type": "Feature",
  "properties": {
    "iso:country":"CH",
    "sg:address":"Casa Comunale",
    "sg:city":"Iseo",
    "sg:orig_category":"Gemeindeverwaltungen",
    "sg:phone":"+41 91 605 28 61",
    "sg:postcode":"6993",
    "sg:province":"Ticino",
    "wof:name":"Municipio Iseo Cancelleria Comunale Sportelli",
    "wof:placetype":"venue"
},
  "geometry": {"coordinates":[8.8812351227,46.0055885315],"type":"Point"}
}