{
  "type": "Feature",
  "properties": {
    "iso:country":"CH",
    "sg:address":"Gampelen",
    "sg:city":"Enges",
    "sg:orig_category":"Verwertung von Milch",
    "sg:postcode":"2073",
    "sg:province":"Neuch\u00e2tel",
    "wof:name":"Syndicat D'estivage Les Gravereules",
    "wof:placetype":"venue"
},
  "geometry": {"coordinates":[7.0119218826,47.0563621521],"type":"Point"}
}