{
  "type": "Feature",
  "properties": {
    "iso:country":"CH",
    "sg:address":"Industriestrasse 11 8864 Reichenburg. Postfach",
    "sg:city":"Reichenburg",
    "sg:orig_category":"Linienflugverkehr",
    "sg:postcode":"8864",
    "sg:province":"Schwyz",
    "wof:name":"Cat Heli Ag",
    "wof:placetype":"venue"
},
  "geometry": {"coordinates":[8.9873533249,47.1704788208],"type":"Point"}
}