{
  "type": "Feature",
  "properties": {
    "iso:country":"CH",
    "sg:address":"Seefeldstrasse 231",
    "sg:city":"Z\u00fcrich",
    "sg:orig_category":"Hoch U Tiefbau",
    "sg:phone":"+41 14229090",
    "sg:postcode":"8008",
    "sg:province":"Z\u00fcrich",
    "wof:name":"Hefti Baugesch\u00e4ft Ag",
    "wof:placetype":"venue"
},
  "geometry": {"coordinates":[8.5612449646,47.3511734009],"type":"Point"}
}