{
  "type": "Feature",
  "properties": {
    "iso:country":"CH",
    "sg:address":"Brunnadernstrasse 10",
    "sg:city":"Bern",
    "sg:orig_category":"Institutionen des Sozialwesens ohne Beherbergung",
    "sg:phone":"+41 31 381 04 44",
    "sg:postcode":"3006",
    "sg:province":"Bern",
    "wof:name":"Auricula Sa",
    "wof:placetype":"venue"
},
  "geometry": {"coordinates":[7.4623069763,46.9425392151],"type":"Point"}
}