{
  "type": "Feature",
  "properties": {
    "addr:full":"Doggilochstrasse 12 Klosters Graubunden 7250",
    "addr:housenumber":"12",
    "addr:postcode":"7250",
    "addr:street":"Doggilochstrasse",
    "iso:country":"CH",
    "sg:address":"Doggilochstrasse 12",
    "sg:city":"Klosters",
    "sg:orig_category":"Bauschreinerei",
    "sg:phone":"+41 81 422 13 97",
    "sg:postcode":"7250",
    "sg:province":"Graubunden",
    "wof:name":"Luzi J\u00e4gli Schreinerei",
    "wof:placetype":"venue"
},
  "geometry": {"coordinates":[9.883459,46.864174],"type":"Point"}
}