{
  "type": "Feature",
  "properties": {
    "iso:country":"CH",
    "sg:address":"Rue De L'horizon",
    "sg:city":"Geneveys-coffrane",
    "sg:orig_category":"Instandhaltung U Reparatur von Automobilen",
    "sg:phone":"+41 32 857 18 19",
    "sg:postcode":"2206",
    "sg:province":"Neuch\u00e2tel",
    "wof:name":"Georges Feuz Carrosserie Du Stade",
    "wof:placetype":"venue"
},
  "geometry": {"coordinates":[6.8490428925,47.0107307434],"type":"Point"}
}