{
  "type": "Feature",
  "properties": {
    "iso:country":"CH",
    "sg:address":"Gemeindehausweg 1",
    "sg:city":"Cham",
    "sg:orig_category":"Architektur U Ingenieurb\u00fcros",
    "sg:phone":"+41 41 783 15 10",
    "sg:postcode":"6330",
    "sg:province":"Zug",
    "wof:name":"Schmid Architektur Und Bauleitung Ag",
    "wof:placetype":"venue"
},
  "geometry": {"coordinates":[8.457853,47.180271],"type":"Point"}
}