{
  "type": "Feature",
  "properties": {
    "iso:country":"CH",
    "sg:address":"Antoine-de-chandieu Chemin 1",
    "sg:city":"Lausanne",
    "sg:orig_category":"Herstellung von k\u00e4lte U lufttechnischen Erzeugnissen f\u00fcr gewerbliche Zwecke",
    "sg:phone":"+41 21 617 72 66",
    "sg:postcode":"1000",
    "sg:province":"Vaud",
    "wof:name":"Technocom Ltd, \u00e0 Douglas, Succursale De Lausanne",
    "wof:placetype":"venue"
},
  "geometry": {"coordinates":[6.6947751045,46.5545883179],"type":"Point"}
}