{
  "type": "Feature",
  "properties": {
    "iso:country":"CH",
    "sg:address":"Henauerstrasse 44 9244 Niederuzwil. Postfach",
    "sg:city":"Niederuzwil",
    "sg:orig_category":"RESTAURANTS: TEA-ROOMS",
    "sg:postcode":"9244",
    "sg:province":"St. Gallen",
    "wof:name":"Werz Gastro Gmbh Gastgewerbe-betriebe, Freizeitgestaltung Usw",
    "wof:placetype":"venue"
},
  "geometry": {"coordinates":[9.1344614029,47.4482002258],"type":"Point"}
}