{
  "type": "Feature",
  "properties": {
    "addr:full":"Am Bachgraben 50 Basel Basel-Stadt 4056",
    "addr:housenumber":"50",
    "addr:postcode":"4056",
    "addr:street":"Am Bachgraben",
    "iso:country":"CH",
    "sg:address":"Am Bachgraben 50",
    "sg:city":"Basel",
    "sg:orig_category":"Bauspenglerei Herstellung von Metallkonstruktionen",
    "sg:phone":"+41 61 322 76 28",
    "sg:postcode":"4056",
    "sg:province":"Basel-Stadt",
    "wof:name":"H + B Profil Ag",
    "wof:placetype":"venue"
},
  "geometry": {"coordinates":[7.5671,47.576988],"type":"Point"}
}