{
  "type": "Feature",
  "properties": {
    "iso:country":"CH",
    "sg:address":"Tellistrasse 70",
    "sg:city":"Aarau",
    "sg:orig_category":"Tierarztpraxis",
    "sg:phone":"+423 373 12 43",
    "sg:postcode":"5000",
    "sg:province":"Aargau",
    "wof:name":"Dr. Med. Vet. Peter Malin Tierarzt",
    "wof:placetype":"venue"
},
  "geometry": {"coordinates":[9.5469198227,47.2249908447],"type":"Point"}
}