{
  "type": "Feature",
  "properties": {
    "iso:country":"CH",
    "sg:address":"Locarno Via 45",
    "sg:city":"Ascona",
    "sg:classifiers":[
        {
            "category":"Travel",
            "subcategory":"Hotels & Motels",
            "type":"Entertainment"
        }
    ],
    "sg:postcode":"6612",
    "sg:province":"Ticino",
    "sg:tags":[
        "hotels",
        "mit",
        "restaurant"
    ],
    "wof:name":"Hotelcorp Sagl",
    "wof:placetype":"venue"
},
  "geometry": {"coordinates":[8.7723169327,46.1590843201],"type":"Point"}
}