{
  "type": "Feature",
  "properties": {
    "iso:country":"CH",
    "sg:address":"Ried",
    "sg:city":"Schwarzenegg",
    "sg:orig_category":"Detailhandel mit Brot, Back U S\u00fcsswaren",
    "sg:phone":"+41 33 453 14 41",
    "sg:postcode":"3616",
    "sg:province":"Bern",
    "wof:name":"B\u00e4ckerei-konditorei Aebersold-baumann",
    "wof:placetype":"venue"
},
  "geometry": {"coordinates":[7.711669,46.795074],"type":"Point"}
}