{
  "type": "Feature",
  "properties": {
    "iso:country":"CH",
    "sg:address":"Musy Avenue Jean-marie- 30",
    "sg:city":"Freiburg",
    "sg:orig_category":"Unclassifiable Establishments",
    "sg:postcode":"1700",
    "sg:province":"Fribourg",
    "wof:name":"Elshani S\u00e0rl",
    "wof:placetype":"venue"
},
  "geometry": {"coordinates":[7.1776437759,46.8087043762],"type":"Point"}
}