{
  "type": "Feature",
  "properties": {
    "iso:country":"CH",
    "sg:address":"Staatsstrasse 10 9246 Niederb\u00fcren. Postfach 22",
    "sg:city":"Niederb\u00fcren",
    "sg:orig_category":"Grosshandel mit Eisenwaren sowie Installationsbedarf f\u00fcr Gas, Wasser U Heizung Grosshandel mit Werkz",
    "sg:phone":"+41 71 424 26 00",
    "sg:postcode":"9246",
    "sg:province":"St. Gallen",
    "wof:name":"Springmann Ag Werkzeugmaschinen & Werkzeuge",
    "wof:placetype":"venue"
},
  "geometry": {"coordinates":[9.1999387741,47.464756012],"type":"Point"}
}