{
  "type": "Feature",
  "properties": {
    "iso:country":"CH",
    "sg:address":"Sch\u00fctzenstrasse 34",
    "sg:city":"Birsfelden",
    "sg:orig_category":"Kinderkrippen U horte",
    "sg:phone":"+41 61 311 17 45",
    "sg:postcode":"4127",
    "sg:province":"Basel-Landschaft",
    "wof:name":"Kinderkrippe Tagesheim",
    "wof:placetype":"venue"
},
  "geometry": {"coordinates":[7.6260299683,47.5533180237],"type":"Point"}
}