{
  "type": "Feature",
  "properties": {
    "iso:country":"CH",
    "sg:address":"Bruch",
    "sg:city":"Unterlangenegg",
    "sg:orig_category":"Allgemeiner Hoch U Tiefbau",
    "sg:phone":"+41 33 453 25 08",
    "sg:postcode":"3614",
    "sg:province":"Bern",
    "wof:name":"Gfeller Jakob",
    "wof:placetype":"venue"
},
  "geometry": {"coordinates":[7.70347,46.791965],"type":"Point"}
}