{
  "type": "Feature",
  "properties": {
    "iso:country":"CH",
    "sg:address":"Via Pizzuolo 6862 Rancate. Postfach Caselle Postale 50",
    "sg:city":"Rancate",
    "sg:orig_category":"Herstellung von Nahrungsmitteln undGetr\u00e4nken Herstellung von sonstigen Metallwaren",
    "sg:phone":"+41 17407453",
    "sg:postcode":"6862",
    "sg:province":"Ticino",
    "wof:name":"Roga Tresorbau Ag",
    "wof:placetype":"venue"
},
  "geometry": {"coordinates":[8.9671554565,45.8657112122],"type":"Point"}
}