{
  "type": "Feature",
  "properties": {
    "iso:country":"CH",
    "sg:address":"Dorfstrasse 26",
    "sg:city":"Bachs",
    "sg:classifiers":[
        {
            "category":"Restaurant",
            "type":"Food & Drink"
        }
    ],
    "sg:phone":"+41 18582136",
    "sg:postcode":"8164",
    "sg:province":"Z\u00fcrich",
    "wof:name":"Restaurant Freihof",
    "wof:placetype":"venue"
},
  "geometry": {"coordinates":[8.4393177032,47.5237083435],"type":"Point"}
}