{
  "type": "Feature",
  "properties": {
    "iso:country":"CH",
    "sg:address":"Brand",
    "sg:city":"Obstalden",
    "sg:orig_category":"Allgemeiner Hochbau Dachdeckerei",
    "sg:phone":"+41 79 601 88 11",
    "sg:postcode":"8758",
    "sg:province":"Glarus",
    "wof:name":"Jakob Schrepfer Bedachungen",
    "wof:placetype":"venue"
},
  "geometry": {"coordinates":[9.15054,47.117245],"type":"Point"}
}