{
  "type": "Feature",
  "properties": {
    "iso:country":"CH",
    "sg:address":"R\u00fcckgasse 10",
    "sg:city":"Z\u00fcrich",
    "sg:orig_category":"Arztpraxen",
    "sg:phone":"+41 71 923 65 44",
    "sg:postcode":"8008",
    "sg:province":"Z\u00fcrich",
    "wof:name":"Dr.med.kiem Tho Liem Spezial\u00e4rztin",
    "wof:placetype":"venue"
},
  "geometry": {"coordinates":[9.043361,47.458969],"type":"Point"}
}