{
  "type": "Feature",
  "properties": {
    "iso:country":"CH",
    "sg:address":"Neustadtstrasse 26",
    "sg:city":"Luzern",
    "sg:orig_category":"Datenverarbeitungsdienste",
    "sg:phone":"+41 41 360 52 52",
    "sg:postcode":"6003",
    "sg:province":"Luzern",
    "wof:name":"Computertechnik Gasser Edv-beratung",
    "wof:placetype":"venue"
},
  "geometry": {"coordinates":[8.30857,47.043053],"type":"Point"}
}