{
  "type": "Feature",
  "properties": {
    "iso:country":"CH",
    "sg:address":"Sch\u00fcrgistrasse 74",
    "sg:city":"Z\u00fcrich",
    "sg:orig_category":"Wirtschaftspr\u00fcfung, Steuerberatung U Treuhand",
    "sg:phone":"+41 13212363",
    "sg:postcode":"8051",
    "sg:province":"Z\u00fcrich",
    "wof:name":"Castus Revision Und Unternehmungsberatung Laszlo Banhidi, Lic. Oec. Publ.",
    "wof:placetype":"venue"
},
  "geometry": {"coordinates":[8.5783147812,47.4084663391],"type":"Point"}
}