{
  "type": "Feature",
  "properties": {
    "iso:country":"CH",
    "sg:address":"Quaderstrasse 8",
    "sg:city":"Chur",
    "sg:orig_category":"Wirtschaftspr\u00fcfung, Steuerberatung U Treuhand",
    "sg:phone":"+41 81 258 36 00",
    "sg:postcode":"7000",
    "sg:province":"Graubunden",
    "wof:name":"Treuhand Und Revisionsb\u00fcro Eggenberger Hans-ruedi, Dipl. Wirtschaftspr\u00fcfer",
    "wof:placetype":"venue"
},
  "geometry": {"coordinates":[9.5325269699,46.8522148132],"type":"Point"}
}