{
  "type": "Feature",
  "properties": {
    "iso:country":"CH",
    "sg:address":"Gotthardstrasse 20 6300 Zug. Postfach",
    "sg:city":"Zug",
    "sg:orig_category":"Unclassifiable Establishments",
    "sg:postcode":"6300",
    "sg:province":"Zug",
    "wof:name":"Alabusnet Ag",
    "wof:placetype":"venue"
},
  "geometry": {"coordinates":[8.5139894485,47.1727676392],"type":"Point"}
}