{
  "type": "Feature",
  "properties": {
    "addr:full":"Marktgasse 25/27 Rheinfelden Aargau 4310",
    "addr:housenumber":"25 / 27",
    "addr:postcode":"4310",
    "addr:street":"Marktgasse",
    "iso:country":"CH",
    "sg:address":"Marktgasse 25/27",
    "sg:city":"Rheinfelden",
    "sg:orig_category":"Aktivit\u00e4ten der Generalunternehmen im Baugewerbe Allgemeiner Hoch U Tiefbau",
    "sg:phone":"+41 31 311 42 55",
    "sg:postcode":"4310",
    "sg:province":"Aargau",
    "wof:name":"R\u00e4tz Bau Ag",
    "wof:placetype":"venue"
},
  "geometry": {"coordinates":[7.440827,46.958748],"type":"Point"}
}