{
  "type": "Feature",
  "properties": {
    "iso:country":"CH",
    "sg:address":"Bellevue Sous 13",
    "sg:city":"Porrentruy",
    "sg:orig_category":"Fachdetailhandel in Verkaufsr\u00e4umen",
    "sg:phone":"+41 32 466 14 04",
    "sg:postcode":"2900",
    "sg:province":"Jura",
    "wof:name":"Germain Girardin",
    "wof:placetype":"venue"
},
  "geometry": {"coordinates":[7.0789380074,47.4245452881],"type":"Point"}
}