{
  "type": "Feature",
  "properties": {
    "iso:country":"CH",
    "sg:address":"En Crusille 1441 Valeyres-montagny. Postfach",
    "sg:city":"Valeyres-montagny",
    "sg:orig_category":"Herstellung von konfektionierten Textilwaren ohne Bekleidung",
    "sg:postcode":"1441",
    "sg:province":"Vaud",
    "wof:name":"Olastore S\u00e0rl Stores, Volets, Moustiquaires Etc.; Commerce, Installation",
    "wof:placetype":"venue"
},
  "geometry": {"coordinates":[6.6085128784,46.7989730835],"type":"Point"}
}