{
  "type": "Feature",
  "properties": {
    "addr:full":"Rue De L'h\u00f4tel-de-ville 17 Vevey Vaud 1800",
    "addr:housenumber":"17",
    "addr:postcode":"1800",
    "addr:street":"Rue De L'Ho \u0302Tel-De-Ville",
    "iso:country":"CH",
    "sg:address":"Rue De L'h\u00f4tel-de-ville 17",
    "sg:city":"Vevey",
    "sg:orig_category":"Arztpraxen",
    "sg:phone":"+41 21 921 40 33",
    "sg:postcode":"1800",
    "sg:province":"Vaud",
    "wof:name":"Dr M\u00e9d.ulrich Schmid M\u00e9decin Sp\u00e9cialiste Fmh",
    "wof:placetype":"venue"
},
  "geometry": {"coordinates":[6.846039,46.459057],"type":"Point"}
}