{
  "type": "Feature",
  "properties": {
    "iso:country":"CH",
    "sg:address":"Lavaterstrasse 33 8002 Z\u00fcrich. Postfach 620",
    "sg:city":"Z\u00fcrich",
    "sg:orig_category":"Institutionen f\u00fcr psychosoziale F\u00e4lle",
    "sg:phone":"+41 12025658",
    "sg:postcode":"8027",
    "sg:province":"Z\u00fcrich",
    "wof:name":"Tamach Psychosoz.beratungsst. Holocaust-ueberleb.& Angeh\u00f6r.",
    "wof:placetype":"venue"
},
  "geometry": {"coordinates":[8.5323829651,47.3632278442],"type":"Point"}
}