{
  "type": "Feature",
  "properties": {
    "iso:country":"CH",
    "sg:address":"Rue Principale 8",
    "sg:city":"Villeret",
    "sg:orig_category":"Grosshandel mit Datenverarbeitungsger\u00e4ten Softwareentwicklung U beratung",
    "sg:phone":"+41 79 447 24 51",
    "sg:postcode":"2613",
    "sg:province":"Bern",
    "wof:name":"Kurt W\u00fcthrich, Scandata Distribution",
    "wof:placetype":"venue"
},
  "geometry": {"coordinates":[7.0198411942,47.1586952209],"type":"Point"}
}