{
  "type": "Feature",
  "properties": {
    "iso:country":"CH",
    "sg:address":"2022",
    "sg:city":"Bevaix",
    "sg:orig_category":"Vermietung U Verpachtung von eigenen Immobilien",
    "sg:postcode":"2022",
    "sg:province":"Neuch\u00e2tel",
    "wof:name":"Treytel Sa",
    "wof:placetype":"venue"
},
  "geometry": {"coordinates":[6.8152251244,46.9300765991],"type":"Point"}
}