{
  "type": "Feature",
  "properties": {
    "iso:country":"CH",
    "sg:address":"Bergstr. 2 4500 Solothurn. Postfach",
    "sg:city":"Solothurn",
    "sg:orig_category":"Pensionskassen",
    "sg:phone":"+41 65224379",
    "sg:postcode":"4502",
    "sg:province":"Solothurn",
    "wof:name":"F\u00fcrsorgefonds Der Alphons Glutz-blotzheim Ag",
    "wof:placetype":"venue"
},
  "geometry": {"coordinates":[7.5323829651,47.2141075134],"type":"Point"}
}