{
  "type": "Feature",
  "properties": {
    "iso:country":"CH",
    "sg:address":"Rue Du Rh\u00f4ne 116",
    "sg:city":"Gen\u00e8ve",
    "sg:orig_category":"Solarien",
    "sg:phone":"+41 22 735 26 15",
    "sg:postcode":"1204",
    "sg:province":"Gen\u00e8ve",
    "wof:name":"Bronzage Rive Parc Leyda Bavaud",
    "wof:placetype":"venue"
},
  "geometry": {"coordinates":[6.1544780731,46.202545166],"type":"Point"}
}