{
  "type": "Feature",
  "properties": {
    "iso:country":"CH",
    "sg:address":"Diemtigtalstrasse",
    "sg:city":"Oey",
    "sg:orig_category":"Vorschulen, Kinderg\u00e4rten",
    "sg:phone":"+41 41 978 13 25",
    "sg:postcode":"3753",
    "sg:province":"Bern",
    "wof:name":"Kindergarten",
    "wof:placetype":"venue"
},
  "geometry": {"coordinates":[8.05331707,46.9799346924],"type":"Point"}
}