{
  "type": "Feature",
  "properties": {
    "iso:country":"CH",
    "sg:address":"Ob Dem Dorf 8",
    "sg:city":"Titterten",
    "sg:orig_category":"Sonstige Aktivit\u00e4ten der nicht-\u00e4rztlichen Medizinalberufe",
    "sg:phone":"+41 56 282 57 34",
    "sg:postcode":"4425",
    "sg:province":"Basel-Landschaft",
    "wof:name":"Hanni Schaub Atemtherapie",
    "wof:placetype":"venue"
},
  "geometry": {"coordinates":[8.2737579346,47.4948310852],"type":"Point"}
}