{
  "type": "Feature",
  "properties": {
    "iso:country":"CH",
    "sg:address":"Bahnhofstrasse 23 5605 Dottikon. Postfach 140",
    "sg:city":"Dottikon",
    "sg:orig_category":"Fachdetailhandel mit pharmazeutischen Produkten",
    "sg:phone":"+41 56 624 14 24",
    "sg:postcode":"5605",
    "sg:province":"Aargau",
    "wof:name":"M\u00fchlehof-apotheke Ag",
    "wof:placetype":"venue"
},
  "geometry": {"coordinates":[8.2407226562,47.3818817139],"type":"Point"}
}