{
  "type": "Feature",
  "properties": {
    "iso:country":"CH",
    "sg:address":"Hoch-ybrig",
    "sg:city":"Unteriberg",
    "sg:orig_category":"Jugendherbergen U H\u00fctten",
    "sg:phone":"+41 55 414 17 66",
    "sg:postcode":"8842",
    "sg:province":"Schwyz",
    "wof:name":"Jugendherberge Fuederegg",
    "wof:placetype":"venue"
},
  "geometry": {"coordinates":[8.8039903641,47.063079834],"type":"Point"}
}