{
  "type": "Feature",
  "properties": {
    "iso:country":"CH",
    "sg:address":"Zugerstrasse 74 6340 Baar. Postfach",
    "sg:city":"Baar",
    "sg:orig_category":"Kunststoff-Produkte",
    "sg:phone":"+41 56 675 44 55",
    "sg:postcode":"6340",
    "sg:province":"Zug",
    "wof:name":"Awm Plastpack Ag",
    "wof:placetype":"venue"
},
  "geometry": {"coordinates":[8.3174819946,47.2825775146],"type":"Point"}
}