{
  "type": "Feature",
  "properties": {
    "addr:full":"Chemin Guignard 19-21 1223 Cologny. Postfach Cologny Gen\u00e8ve 1223",
    "addr:housenumber":"19-21",
    "addr:postcode":"1223;postfach;1223",
    "addr:street":"Chemin Guignard",
    "iso:country":"CH",
    "sg:address":"Chemin Guignard 19-21 1223 Cologny. Postfach",
    "sg:city":"Cologny",
    "sg:orig_category":"Bibliotheken U Archive Pensionskassen",
    "sg:phone":"+41 22 736 23 70",
    "sg:postcode":"1223",
    "sg:province":"Gen\u00e8ve",
    "wof:name":"Fondation Martin Bodmer",
    "wof:placetype":"venue"
},
  "geometry": {"coordinates":[6.180992,46.214672],"type":"Point"}
}