{
  "type": "Feature",
  "properties": {
    "iso:country":"CH",
    "sg:address":"3778",
    "sg:city":"Sch\u00f6nried",
    "sg:orig_category":"Personenbef\u00f6rderung im Linienverkehr zu Land",
    "sg:phone":"+41 41 870 03 13",
    "sg:postcode":"3778",
    "sg:province":"Bern",
    "wof:name":"Skiliftgenossenschaft B\u00fcrglen",
    "wof:placetype":"venue"
},
  "geometry": {"coordinates":[8.6637849808,46.8756256104],"type":"Point"}
}