{
  "type": "Feature",
  "properties": {
    "iso:country":"CH",
    "sg:address":"Kreuzbuchstrasse 7",
    "sg:city":"Luzern",
    "sg:orig_category":"Informatikdienste Softwareentwicklung U beratung",
    "sg:phone":"+41 41 372 10 25",
    "sg:postcode":"6006",
    "sg:province":"Luzern",
    "wof:name":"Erkodata, Erwin Koch",
    "wof:placetype":"venue"
},
  "geometry": {"coordinates":[8.3294067383,47.0555000305],"type":"Point"}
}