{
  "type": "Feature",
  "properties": {
    "iso:country":"CH",
    "sg:address":"Benkemerg\u00e4ssli 10",
    "sg:city":"Dachsen",
    "sg:orig_category":"Sportvereine Wassersport Motorboot",
    "sg:phone":"+41 79 421 24 51",
    "sg:postcode":"8447",
    "sg:province":"Z\u00fcrich",
    "wof:name":"Motorbootklub",
    "wof:placetype":"venue"
},
  "geometry": {"coordinates":[8.6260271072,47.6616630554],"type":"Point"}
}