{
  "type": "Feature",
  "properties": {
    "iso:country":"CH",
    "sg:address":"R\u00fctistrasse 5",
    "sg:city":"Baden",
    "sg:orig_category":"Herstellung von keramischen Haushaltswaren U Ziergegenst\u00e4nden",
    "sg:phone":"+41 56 222 35 38",
    "sg:postcode":"5400",
    "sg:province":"Aargau",
    "wof:name":"Verena Thomann Keramikatelier",
    "wof:placetype":"venue"
},
  "geometry": {"coordinates":[8.3048057556,47.4740943909],"type":"Point"}
}