{
  "type": "Feature",
  "properties": {
    "iso:country":"CH",
    "sg:address":"Wettsteinallee 21",
    "sg:city":"Basel",
    "sg:orig_category":"Filmverleih U Videoprogrammanbieter Sonstige Hilfsdienste des Kultur U Unterhaltungswesens",
    "sg:phone":"+41 61 681 81 86",
    "sg:postcode":"4058",
    "sg:province":"Basel-Stadt",
    "wof:name":"Brookfield Television Gmbh Filme; Produktion",
    "wof:placetype":"venue"
},
  "geometry": {"coordinates":[7.5998830795,47.5600624084],"type":"Point"}
}