{
  "type": "Feature",
  "properties": {
    "iso:country":"CH",
    "sg:address":"Kronengasse 3 7000 Chur. Postfach",
    "sg:city":"Chur",
    "sg:classifiers":[
        {
            "category":"Travel",
            "subcategory":"Hotels & Motels",
            "type":"Entertainment"
        }
    ],
    "sg:phone":"+41 81 302 53 53",
    "sg:postcode":"7005",
    "sg:tags":[
        "hotels",
        "mit",
        "restaurant"
    ],
    "wof:name":"Hotel Krone",
    "wof:placetype":"venue"
},
  "geometry": {"coordinates":[9.5008096695,47.0014343262],"type":"Point"}
}