{
  "type": "Feature",
  "properties": {
    "iso:country":"CH",
    "sg:address":"Quai Gustave-ador 1",
    "sg:city":"Gen\u00e8ve",
    "sg:classifiers":[
        {
            "category":"Restaurant",
            "type":"Food & Drink"
        }
    ],
    "sg:phone":"+41 22 736 68 02",
    "sg:postcode":"1207",
    "sg:province":"Gen\u00e8ve",
    "wof:name":"Caf\u00e9 L'apoth\u00e9ose",
    "wof:placetype":"venue"
},
  "geometry": {"coordinates":[6.1552929878,46.2042198181],"type":"Point"}
}