{
  "type": "Feature",
  "properties": {
    "iso:country":"CH",
    "sg:address":"General Wille-strasse 119 8706 Feldmeilen. Postfach",
    "sg:city":"Feldmeilen",
    "sg:classifiers":[
        {
            "category":"Professional",
            "subcategory":"Employment Agencies",
            "type":"Services"
        }
    ],
    "sg:phone":"+41 19236505",
    "sg:postcode":"8706",
    "sg:province":"Z\u00fcrich",
    "sg:tags":[
        "personal",
        "u",
        "stellenvermittlung"
    ],
    "wof:name":"Abderhalden Hildegard",
    "wof:placetype":"venue"
},
  "geometry": {"coordinates":[8.6165037155,47.2784614563],"type":"Point"}
}