{
  "type": "Feature",
  "properties": {
    "iso:country":"CH",
    "sg:city":"Einsiedeln",
    "sg:orig_category":"Industrie, Papier U Verpackung",
    "sg:phone":"+41 55 412 79 76",
    "sg:postcode":"8840",
    "sg:province":"Schwyz",
    "wof:name":"Nicopac-verpackungssysteme Material",
    "wof:placetype":"venue"
},
  "geometry": {"coordinates":[8.74608,47.127316],"type":"Point"}
}