{
  "type": "Feature",
  "properties": {
    "iso:country":"CH",
    "sg:address":"Haldenstrasse 9",
    "sg:city":"M\u00e4genwil",
    "sg:orig_category":"Elektro- and elektronische Maschinen Grosshandel Herstellung von sonstigen elektrischen Ausr\u00fcstungen",
    "sg:phone":"+41 62 896 03 30",
    "sg:postcode":"5506",
    "sg:province":"Aargau",
    "wof:name":"Hawemag Components Gmbh",
    "wof:placetype":"venue"
},
  "geometry": {"coordinates":[8.2384376526,47.4110832214],"type":"Point"}
}