{
  "type": "Feature",
  "properties": {
    "iso:country":"CH",
    "sg:address":"Ebnetstrasse 3 6043 Adligenswil. Postfach 425",
    "sg:city":"Adligenswil",
    "sg:orig_category":"Softwareentwicklung U beratung Unternehmensberatung",
    "sg:phone":"+41 41 370 93 70",
    "sg:postcode":"6043",
    "sg:province":"Luzern",
    "wof:name":"Datasave Schweiz Ag",
    "wof:placetype":"venue"
},
  "geometry": {"coordinates":[8.3594808578,47.0744781494],"type":"Point"}
}