{
  "type": "Feature",
  "properties": {
    "iso:country":"CH",
    "sg:address":"Kirchstrasse 24a",
    "sg:city":"Amriswil",
    "sg:orig_category":"Sonstige mit Sport verbundene T\u00e4tigkeiten",
    "sg:postcode":"8580",
    "sg:province":"Thurgau",
    "wof:name":"Stiftung Pro Kunsteisbahn Oberthurgau",
    "wof:placetype":"venue"
},
  "geometry": {"coordinates":[9.299665451,47.5483131409],"type":"Point"}
}