{
  "type": "Feature",
  "properties": {
    "iso:country":"CH",
    "sg:address":"Sch\u00fctzengasse 4 8001 Z\u00fcrich. Postfach",
    "sg:city":"Z\u00fcrich",
    "sg:orig_category":"Vermietung U Verpachtung von eigenen Immobilien",
    "sg:postcode":"8001",
    "sg:province":"Z\u00fcrich",
    "wof:name":"Verwa Ag Liegenschaften; Erwerb, Vermittlung, \u00dcberbauung, Verwaltung Usw",
    "wof:placetype":"venue"
},
  "geometry": {"coordinates":[8.5406255722,47.3763122559],"type":"Point"}
}