{
  "type": "Feature",
  "properties": {
    "iso:country":"CH",
    "sg:address":"Centralstrasse 18",
    "sg:city":"Grenchen",
    "sg:classifiers":[
        {
            "category":"Government",
            "subcategory":"Post Office",
            "type":"Public Place"
        }
    ],
    "sg:phone":"+41 32 652 94 44",
    "sg:postcode":"2540",
    "sg:province":"Solothurn",
    "sg:tags":[
        "caf\u00e9s",
        "tea-rooms"
    ],
    "wof:name":"Tea-room Eldorado",
    "wof:placetype":"venue"
},
  "geometry": {"coordinates":[7.3957867622,47.1934890747],"type":"Point"}
}