{
  "type": "Feature",
  "properties": {
    "iso:country":"CH",
    "sg:address":"Via Lambertenghi 4",
    "sg:city":"Lugano",
    "sg:orig_category":"Konsumentenorganisationen",
    "sg:phone":"+41 91 922 97 55",
    "sg:postcode":"6900",
    "sg:province":"Ticino",
    "wof:name":"Associazione Consumatrici Della Svizzera Italiana",
    "wof:placetype":"venue"
},
  "geometry": {"coordinates":[8.9577560425,46.008556366],"type":"Point"}
}