{
  "type": "Feature",
  "properties": {
    "iso:country":"CH",
    "sg:address":"Werner-k\u00e4linstrasse 20",
    "sg:city":"Einsiedeln",
    "sg:orig_category":"Bauschreinerei Herstellung von M\u00f6beln verschiedener Art",
    "sg:phone":"+41 55 412 80 88",
    "sg:postcode":"8840",
    "sg:province":"Schwyz",
    "wof:name":"Werner Reichmuth Schreinerei",
    "wof:placetype":"venue"
},
  "geometry": {"coordinates":[8.74593,47.125702],"type":"Point"}
}