{
  "type": "Feature",
  "properties": {
    "iso:country":"CH",
    "sg:address":"Z\u00fcricherstr 35",
    "sg:city":"Wetzikon",
    "sg:classifiers":[
        {
            "category":"Manufacturing",
            "subcategory":"Wood Products",
            "type":"Manufacturing & Wholesale Goods"
        }
    ],
    "sg:phone":"+41 4119330101",
    "sg:postcode":"8620",
    "sg:province":"Z\u00fcrich",
    "sg:tags":[
        "professional",
        "furniture"
    ],
    "wof:name":"Aweso-werke",
    "wof:placetype":"venue"
},
  "geometry": {"coordinates":[8.7868356705,47.323387146],"type":"Point"}
}