{
  "type": "Feature",
  "properties": {
    "iso:country":"CH",
    "sg:address":"Rue Du Pont 6",
    "sg:city":"Tavannes",
    "sg:orig_category":"Stukkateurgewerbe, Gipserei U Verputzerei",
    "sg:phone":"+41 32 481 40 09",
    "sg:postcode":"2710",
    "sg:province":"Bern",
    "wof:name":"Fragnoli Mario, B\u00e2ticolor",
    "wof:placetype":"venue"
},
  "geometry": {"coordinates":[7.1991667747,47.2185440063],"type":"Point"}
}