{
  "type": "Feature",
  "properties": {
    "iso:country":"CH",
    "sg:address":"Hellb\u00fchlerstrasse 22",
    "sg:city":"Ruswil",
    "sg:orig_category":"Shiatsu-Therapie",
    "sg:phone":"+41 41 495 10 25",
    "sg:postcode":"6017",
    "sg:province":"Luzern",
    "wof:name":"Shiatsu-gesundheitspraxis",
    "wof:placetype":"venue"
},
  "geometry": {"coordinates":[8.1291751862,47.0805969238],"type":"Point"}
}