{
  "type": "Feature",
  "properties": {
    "iso:country":"CH",
    "sg:address":"Solothurnstrasse 61 3315 B\u00e4tterkinden. Postfach",
    "sg:city":"B\u00e4tterkinden",
    "sg:orig_category":"Non-Classified Establishments",
    "sg:phone":"+41 81 302 54 57",
    "sg:postcode":"3315",
    "sg:province":"Bern",
    "wof:name":"Genossenschaft Naturladen Sonnenkraft",
    "wof:placetype":"venue"
},
  "geometry": {"coordinates":[9.5003709793,47.0039558411],"type":"Point"}
}