{
  "type": "Feature",
  "properties": {
    "iso:country":"CH",
    "sg:address":"Dorfstrasse 10",
    "sg:city":"Trubschachen",
    "sg:orig_category":"Detailhandel mit Brot, Back U S\u00fcsswaren",
    "sg:phone":"+41 34 495 51 33",
    "sg:postcode":"3555",
    "sg:province":"Bern",
    "wof:name":"Paul Habegger B\u00e4ckerei",
    "wof:placetype":"venue"
},
  "geometry": {"coordinates":[7.8453,46.923],"type":"Point"}
}