{
  "type": "Feature",
  "properties": {
    "iso:country":"CH",
    "sg:address":"Dorfstrasse 2",
    "sg:city":"Herbetswil",
    "sg:orig_category":"Detailhandel mit Waren verschiedener Art, Hauptrichtung Nahrungsmittel Grosshandel mit Nahrungsmitte",
    "sg:phone":"+41 62 394 12 12",
    "sg:postcode":"4715",
    "sg:province":"Solothurn",
    "wof:name":"Scm Lebensmittel Gmbh Primo Laden",
    "wof:placetype":"venue"
},
  "geometry": {"coordinates":[7.5920639038,47.2965431213],"type":"Point"}
}