{
  "type": "Feature",
  "properties": {
    "iso:country":"CH",
    "sg:address":"Pilatusstrasse 7",
    "sg:city":"Hedingen",
    "sg:orig_category":"Sonstiger Grosshandel",
    "sg:phone":"+41 17617165",
    "sg:postcode":"8908",
    "sg:province":"Z\u00fcrich",
    "wof:name":"Perma Perl Margrit",
    "wof:placetype":"venue"
},
  "geometry": {"coordinates":[8.4529008865,47.3003578186],"type":"Point"}
}