{
  "type": "Feature",
  "properties": {
    "addr:full":"St\u00e4hlistrasse 2 Kreuzlingen Thurgau 8280",
    "addr:housenumber":"2",
    "addr:postcode":"8280",
    "addr:street":"Staehlistrasse",
    "iso:country":"CH",
    "sg:address":"St\u00e4hlistrasse 2",
    "sg:city":"Kreuzlingen",
    "sg:classifiers":[
        {
            "category":"Bars & Pubs",
            "type":"Food & Drink"
        }
    ],
    "sg:phone":"+41 71 672 59 66",
    "sg:postcode":"8280",
    "sg:province":"Thurgau",
    "sg:tags":[
        "restaurant"
    ],
    "wof:name":"Grillroom & Bar Paprika",
    "wof:placetype":"venue"
},
  "geometry": {"coordinates":[9.168757,47.642689],"type":"Point"}
}