{
  "type": "Feature",
  "properties": {
    "iso:country":"CH",
    "sg:address":"Staaderstrasse 16",
    "sg:city":"Eschenz",
    "sg:orig_category":"Grosshandel mit B\u00fcromaschinen Grosshandel mit Datenverarbeitungsger\u00e4ten",
    "sg:phone":"+41 79 412 48 68",
    "sg:postcode":"8264",
    "sg:province":"Thurgau",
    "wof:name":"Coment Computer Ag",
    "wof:placetype":"venue"
},
  "geometry": {"coordinates":[8.8765573502,47.6486091614],"type":"Point"}
}