{
  "type": "Feature",
  "properties": {
    "iso:country":"CH",
    "sg:address":"Avenue Maurice-troillet 82",
    "sg:city":"Sion",
    "sg:orig_category":"Herstellung von Karosserien U Anh\u00e4ngern",
    "sg:phone":"+41 71 298 33 88",
    "sg:postcode":"1950",
    "sg:province":"Valais",
    "wof:name":"Auto-marbach",
    "wof:placetype":"venue"
},
  "geometry": {"coordinates":[9.3225393295,47.4286651611],"type":"Point"}
}