{
  "type": "Feature",
  "properties": {
    "iso:country":"CH",
    "sg:address":"Cours De Rive 4",
    "sg:city":"Gen\u00e8ve",
    "sg:orig_category":"Effektenvermittlung Broker Finanzierungsinstitutionen",
    "sg:phone":"+41 71 311 21 36",
    "sg:postcode":"1204",
    "sg:province":"Gen\u00e8ve",
    "wof:name":"Kredit Und Anlage-abwicklung Beck",
    "wof:placetype":"venue"
},
  "geometry": {"coordinates":[9.311041832,47.4163322449],"type":"Point"}
}