{
  "type": "Feature",
  "properties": {
    "iso:country":"CH",
    "sg:address":"Weissenaustr 73",
    "sg:city":"Unterseen",
    "sg:classifiers":[
        {
            "category":"Health Services",
            "subcategory":"Medical Lab",
            "type":"Services"
        }
    ],
    "sg:phone":"+41 33 827 80 00",
    "sg:postcode":"3800",
    "sg:province":"Bern",
    "sg:tags":[
        "chemical",
        "pharmaceutical",
        "pharmacy"
    ],
    "wof:name":"Dr. G. Bichsel Ag Labaratorium",
    "wof:placetype":"venue"
},
  "geometry": {"coordinates":[7.838101,46.677158],"type":"Point"}
}