{
  "type": "Feature",
  "properties": {
    "iso:country":"CH",
    "sg:address":"Krummeneichstrasse 52",
    "sg:city":"Pratteln",
    "sg:orig_category":"Grosshandel mit Nahrungsmitteln, Getr\u00e4nken U Tabakwaren ohne ausgepr\u00e4gten Schwerpunkt",
    "sg:postcode":"4133",
    "sg:province":"Basel-Landschaft",
    "wof:name":"Mini Market Pratteln, Thavaratnam",
    "wof:placetype":"venue"
},
  "geometry": {"coordinates":[7.7091088295,47.5231208801],"type":"Point"}
}