{
  "type": "Feature",
  "properties": {
    "iso:country":"CH",
    "sg:address":"Kirchg\u00e4ssli 5 2500 Biel/bienne. Postfach",
    "sg:city":"Biel/bienne",
    "sg:orig_category":"Detailhandel mit elektrischen Haushalts-,Radio U Fernsehger\u00e4ten sowie Musikinstrumenten",
    "sg:phone":"+41 32225935",
    "sg:postcode":"2502",
    "sg:province":"Bern",
    "wof:name":"Maier Hansj\u00f6rg",
    "wof:placetype":"venue"
},
  "geometry": {"coordinates":[7.2462258339,47.1411209106],"type":"Point"}
}