{
  "type": "Feature",
  "properties": {
    "iso:country":"CH",
    "sg:address":"Kemmatten",
    "sg:city":"Cham",
    "sg:orig_category":"Herstellung von Frucht U Gem\u00fcses\u00e4ften Herstellung von Obst U Fruchtweinen",
    "sg:phone":"+41 41 780 12 63",
    "sg:postcode":"6330",
    "sg:province":"Zug",
    "wof:name":"Franz Boog Mosterei",
    "wof:placetype":"venue"
},
  "geometry": {"coordinates":[8.4456853867,47.1719284058],"type":"Point"}
}