{
  "type": "Feature",
  "properties": {
    "iso:country":"CH",
    "sg:address":"Rossweid",
    "sg:city":"Gisikon",
    "sg:orig_category":"Verwertung von Milch",
    "sg:phone":"+41 71 638 05 38",
    "sg:postcode":"6038",
    "sg:province":"Luzern",
    "wof:name":"Gerber Hans",
    "wof:placetype":"venue"
},
  "geometry": {"coordinates":[9.1668395996,47.5790901184],"type":"Point"}
}