{
  "type": "Feature",
  "properties": {
    "iso:country":"CH",
    "sg:address":"Fischerh\u00e4userstrasse 4",
    "sg:city":"Schaffhausen",
    "sg:orig_category":"RESTAURANTS: TEA-ROOMS",
    "sg:postcode":"8200",
    "sg:province":"Schaffhausen",
    "wof:name":"B\u00fchler Ferdinand.",
    "wof:placetype":"venue"
},
  "geometry": {"coordinates":[8.6415739059,47.6956825256],"type":"Point"}
}