{
  "type": "Feature",
  "properties": {
    "iso:country":"CH",
    "sg:address":"Schulstrasse 15 8542 Wiesendangen. Postfach",
    "sg:city":"Wiesendangen",
    "sg:orig_category":"Immobilienwesen Rechts U Unternehmensberatung, Buchf\u00fchrung",
    "sg:phone":"+41 52 338 27 27",
    "sg:postcode":"8542",
    "sg:province":"Z\u00fcrich",
    "wof:name":"Qualicasa Ag",
    "wof:placetype":"venue"
},
  "geometry": {"coordinates":[8.7867145538,47.5227775574],"type":"Point"}
}