{
  "type": "Feature",
  "properties": {
    "iso:country":"CH",
    "sg:address":"T\u00e4gertschistrasse 7",
    "sg:city":"M\u00fcnsingen",
    "sg:orig_category":"Werbung",
    "sg:postcode":"3110",
    "sg:province":"Bern",
    "wof:name":"Ansatz Werbung & Beschriftung Looser Roland",
    "wof:placetype":"venue"
},
  "geometry": {"coordinates":[7.5652351379,46.8753128052],"type":"Point"}
}