{
  "type": "Feature",
  "properties": {
    "iso:country":"CH",
    "sg:address":"Unterdorf 21a",
    "sg:city":"D\u00e4ttlikon",
    "sg:orig_category":"Unclassifiable Establishments",
    "sg:postcode":"8421",
    "sg:province":"Z\u00fcrich",
    "wof:name":"Guerra Reto, Bauservice",
    "wof:placetype":"venue"
},
  "geometry": {"coordinates":[8.6220779419,47.5251426697],"type":"Point"}
}