{
  "type": "Feature",
  "properties": {
    "iso:country":"CH",
    "sg:address":"Vicolo Motto Di Lena 5",
    "sg:city":"Minusio",
    "sg:orig_category":"Verlagsgewerbe",
    "sg:phone":"+41 91 743 20 56",
    "sg:postcode":"6648",
    "sg:province":"Ticino",
    "wof:name":"Harmonia Verlag Ascona Martha Bakcsy",
    "wof:placetype":"venue"
},
  "geometry": {"coordinates":[8.8077449799,46.1777038574],"type":"Point"}
}