{
  "type": "Feature",
  "properties": {
    "iso:country":"CH",
    "sg:address":"Vogelsangweg 4",
    "sg:city":"Boll",
    "sg:orig_category":"Unclassifiable Establishments",
    "sg:phone":"+41 31 832 44 62",
    "sg:postcode":"3067",
    "sg:province":"Bern",
    "wof:name":"Intake Ag",
    "wof:placetype":"venue"
},
  "geometry": {"coordinates":[7.5616650581,46.9468002319],"type":"Point"}
}