{
  "type": "Feature",
  "properties": {
    "iso:country":"CH",
    "sg:address":"Ebmattstrasse 11",
    "sg:city":"Bubikon",
    "sg:orig_category":"Vermietung U Verpachtung von eigenen Immobilien",
    "sg:postcode":"8608",
    "sg:province":"Z\u00fcrich",
    "wof:name":"Alpstein Immobilien Ag St. Gallen",
    "wof:placetype":"venue"
},
  "geometry": {"coordinates":[9.3892726898,47.4379310608],"type":"Point"}
}