{
  "type": "Feature",
  "properties": {
    "iso:country":"CH",
    "sg:address":"Rue Du Coppet 6",
    "sg:city":"Monthey",
    "sg:orig_category":"Sportvereine Ballsport Badminton",
    "sg:phone":"+41 24 472 36 32",
    "sg:postcode":"1870",
    "sg:province":"Valais",
    "wof:name":"Badminton-club St.maurice",
    "wof:placetype":"venue"
},
  "geometry": {"coordinates":[6.9494152069,46.2523269653],"type":"Point"}
}