{
  "type": "Feature",
  "properties": {
    "iso:country":"CH",
    "sg:address":"Kasernenstrasse 97",
    "sg:city":"Z\u00fcrich",
    "sg:orig_category":"Children's Entertainment",
    "sg:phone":"+41 31 991 51 48",
    "sg:postcode":"8004",
    "sg:province":"Z\u00fcrich",
    "wof:name":"Burgerswiss Gmbh",
    "wof:placetype":"venue"
},
  "geometry": {"coordinates":[8.534958,47.376881],"type":"Point"}
}