{
  "type": "Feature",
  "properties": {
    "iso:country":"CH",
    "sg:address":"7477",
    "sg:city":"Filisur",
    "sg:classifiers":[
        {
            "category":"Education",
            "subcategory":"Library",
            "type":"Public Place"
        }
    ],
    "sg:phone":"+41 81 420 41 65",
    "sg:postcode":"7477",
    "sg:province":"Graubunden",
    "sg:tags":[
        "u",
        "bibliotheken",
        "archive"
    ],
    "wof:name":"Gemeindebibliothek",
    "wof:placetype":"venue"
},
  "geometry": {"coordinates":[9.68588,46.673481],"type":"Point"}
}