{
  "type": "Feature",
  "properties": {
    "iso:country":"CH",
    "sg:address":"Eigerstrasse 60",
    "sg:city":"Bern",
    "sg:orig_category":"Oberfl\u00e4chenveredlung U W\u00e4rmebehandlung",
    "sg:phone":"+41 31 371 12 78",
    "sg:postcode":"3007",
    "sg:province":"Bern",
    "wof:name":"Wilcop Ag",
    "wof:placetype":"venue"
},
  "geometry": {"coordinates":[7.4371089935,46.9396514893],"type":"Point"}
}