{
  "type": "Feature",
  "properties": {
    "iso:country":"CH",
    "sg:address":"Thurgauerstrasse 70",
    "sg:city":"Z\u00fcrich",
    "sg:orig_category":"Herstellung von Werkzeugen",
    "sg:phone":"+41 13022410",
    "sg:postcode":"8050",
    "sg:province":"Z\u00fcrich",
    "wof:name":"Josef Schibli Werkzeugbau",
    "wof:placetype":"venue"
},
  "geometry": {"coordinates":[8.5544776917,47.4176139832],"type":"Point"}
}