{
  "type": "Feature",
  "properties": {
    "iso:country":"CH",
    "sg:address":"Landstrasse 176",
    "sg:city":"Wettingen",
    "sg:orig_category":"Unternehmensberatung",
    "sg:phone":"+41 17373021",
    "sg:postcode":"5430",
    "sg:province":"Aargau",
    "wof:name":"Medical Cfs, Fl\u00fcckiger Paul",
    "wof:placetype":"venue"
},
  "geometry": {"coordinates":[8.4402770996,47.3522644043],"type":"Point"}
}