{
  "type": "Feature",
  "properties": {
    "iso:country":"CH",
    "sg:address":"Wiesen Azmoos 9478 Wartau. Postfach",
    "sg:city":"Azmoos",
    "sg:orig_category":"Non-Classified Establishments",
    "sg:postcode":"9478",
    "sg:province":"St. Gallen",
    "wof:name":"Loosli Transporte",
    "wof:placetype":"venue"
},
  "geometry": {"coordinates":[9.4766893387,47.0802955627],"type":"Point"}
}