{
  "type": "Feature",
  "properties": {
    "iso:country":"CH",
    "sg:address":"Industriestrasse 1 8307 Effretikon. Postfach 140",
    "sg:city":"Effretikon",
    "sg:orig_category":"Herstellung von Schneidwaren U Bestecken Herstellung von Werkzeugen",
    "sg:phone":"+41 52 343 46 10",
    "sg:postcode":"8307",
    "sg:province":"Z\u00fcrich",
    "wof:name":"Leutenegger W. Ag",
    "wof:placetype":"venue"
},
  "geometry": {"coordinates":[8.6847028732,47.418888092],"type":"Point"}
}