{
  "type": "Feature",
  "properties": {
    "iso:country":"CH",
    "sg:address":"Hirschenplatz 8",
    "sg:city":"Lyss",
    "sg:orig_category":"Detailhandel mit Textilien",
    "sg:phone":"+41 32 385 22 10",
    "sg:postcode":"3250",
    "sg:province":"Bern",
    "wof:name":"Tricot Gerber Stoff-& Tricotversand",
    "wof:placetype":"venue"
},
  "geometry": {"coordinates":[7.3063220978,47.0742988586],"type":"Point"}
}