{
  "type": "Feature",
  "properties": {
    "iso:country":"CH",
    "sg:address":"Dreik\u00f6nigstrasse 49",
    "sg:city":"Z\u00fcrich",
    "sg:orig_category":"Interessenvertretungen",
    "sg:postcode":"8002",
    "sg:province":"Z\u00fcrich",
    "wof:name":"Mayer Saly Memorial Stiftung",
    "wof:placetype":"venue"
},
  "geometry": {"coordinates":[8.5331506729,47.3657417297],"type":"Point"}
}