{
  "type": "Feature",
  "properties": {
    "iso:country":"CH",
    "sg:address":"Grand-rue 5",
    "sg:city":"Dombresson",
    "sg:orig_category":"Primarschulen",
    "sg:phone":"+41 32 853 59 27",
    "sg:postcode":"2056",
    "sg:province":"Neuch\u00e2tel",
    "wof:name":"Ecole Primaire",
    "wof:placetype":"venue"
},
  "geometry": {"coordinates":[6.956679821,47.071308136],"type":"Point"}
}