{
  "type": "Feature",
  "properties": {
    "iso:country":"CH",
    "sg:address":"Boden",
    "sg:city":"Unterterzen",
    "sg:orig_category":"Detailhandel mit Zeitungen U Zeitschriften Kioske",
    "sg:phone":"+41 81 738 21 84",
    "sg:postcode":"8882",
    "sg:province":"St. Gallen",
    "wof:name":"Rosmarie Scherrer Kiosk Flumserbergbahn",
    "wof:placetype":"venue"
},
  "geometry": {"coordinates":[9.252325058,47.1129150391],"type":"Point"}
}