{
  "type": "Feature",
  "properties": {
    "iso:country":"CH",
    "sg:address":"W\u00fcrzenbachstrasse 49",
    "sg:city":"Luzern",
    "sg:orig_category":"Sonstige mit Sport verbundene T\u00e4tigkeiten",
    "sg:postcode":"6006",
    "sg:province":"Luzern",
    "wof:name":"Snowledge Snowboardschool Sandra De Martin",
    "wof:placetype":"venue"
},
  "geometry": {"coordinates":[8.3488330841,47.0559844971],"type":"Point"}
}