{
  "type": "Feature",
  "properties": {
    "iso:country":"CH",
    "sg:address":"Sihlbruggstrasse 99",
    "sg:city":"Baar",
    "sg:orig_category":"Kauf U Verkauf von Immobilien auf eigene Rechnung Verwaltung von Immobilien",
    "sg:phone":"+41 61 402 06 03",
    "sg:postcode":"6340",
    "sg:province":"Zug",
    "wof:name":"Karo Liegenschaften Gmbh",
    "wof:placetype":"venue"
},
  "geometry": {"coordinates":[7.5550808907,47.5099182129],"type":"Point"}
}