{
  "type": "Feature",
  "properties": {
    "iso:country":"CH",
    "sg:address":"Hertistrasse 53",
    "sg:city":"Zug",
    "sg:orig_category":"Naturheil\u00e4rzte and Heilpraktiker",
    "sg:phone":"+41 41 711 16 46",
    "sg:postcode":"6300",
    "sg:province":"Zug",
    "wof:name":"Nghia Lam Minh Naturheilpraxis",
    "wof:placetype":"venue"
},
  "geometry": {"coordinates":[8.5103330612,47.1789169312],"type":"Point"}
}