{
  "type": "Feature",
  "properties": {
    "iso:country":"CH",
    "sg:address":"Schl\u00fcsselring 10",
    "sg:city":"Muhen",
    "sg:orig_category":"Gesundheitswesen",
    "sg:phone":"+41 62 723 99 00",
    "sg:postcode":"5037",
    "sg:province":"Aargau",
    "wof:name":"Stiftung Wendepunkt",
    "wof:placetype":"venue"
},
  "geometry": {"coordinates":[8.0524501801,47.3431282043],"type":"Point"}
}