{
  "type": "Feature",
  "properties": {
    "iso:country":"CH",
    "sg:address":"Principala Via",
    "sg:city":"Disentis/must\u00e9r",
    "sg:orig_category":"Instandhaltung U Reparatur von Automobilen",
    "sg:postcode":"7180",
    "sg:province":"Graubunden",
    "wof:name":"Carossaria E Picturia Marcus Coray",
    "wof:placetype":"venue"
},
  "geometry": {"coordinates":[8.8531293869,46.7046012878],"type":"Point"}
}