{
  "type": "Feature",
  "properties": {
    "iso:country":"CH",
    "sg:address":"Im B\u00fcntli 197",
    "sg:city":"Im B\u00fcntli 197",
    "sg:orig_category":"Sonstige mit der Informatik verbundene T\u00e4tigkeiten",
    "sg:phone":"+41 56 243 15 22",
    "sg:postcode":"8439",
    "wof:name":"Edv-beratung Twerenbold",
    "wof:placetype":"venue"
},
  "geometry": {"coordinates":[6.3370699883,52.903881073],"type":"Point"}
}