{
  "type": "Feature",
  "properties": {
    "iso:country":"CH",
    "sg:address":"Varesi Via Dr. Giovanni 40",
    "sg:city":"Locarno",
    "sg:orig_category":"Unclassifiable Establishments",
    "sg:postcode":"6600",
    "sg:province":"Ticino",
    "wof:name":"Pit-stop Pneumatici E Trasporti Sagl",
    "wof:placetype":"venue"
},
  "geometry": {"coordinates":[8.7957925797,46.1622848511],"type":"Point"}
}