{
  "type": "Feature",
  "properties": {
    "iso:country":"CH",
    "sg:address":"M\u00fchlegasse 4",
    "sg:city":"Ziefen",
    "sg:orig_category":"Mahl U Sch\u00e4lm\u00fchlen",
    "sg:phone":"+41 61 931 17 02",
    "sg:postcode":"4417",
    "sg:province":"Basel-Landschaft",
    "wof:name":"Fritz Loeffel Kunden-m\u00fchle",
    "wof:placetype":"venue"
},
  "geometry": {"coordinates":[7.7034139633,47.4293518066],"type":"Point"}
}