{
  "type": "Feature",
  "properties": {
    "iso:country":"CH",
    "sg:address":"Seestrasse 17",
    "sg:city":"Weggis",
    "sg:orig_category":"Detailhandel mit Geschenkartikeln U Souvenirs Sonstiger Fachdetailhandel in Verkaufsr\u00e4umen",
    "sg:phone":"+41 41 390 29 68",
    "sg:postcode":"6353",
    "sg:province":"Luzern",
    "wof:name":"Boutique Robinson Rolf Schmid Fischerei Und Messerfachgesch\u00e4ft",
    "wof:placetype":"venue"
},
  "geometry": {"coordinates":[8.4315214157,47.0317497253],"type":"Point"}
}