{
  "type": "Feature",
  "properties": {
    "iso:country":"CH",
    "sg:address":"G\u00fcterstrasse 2",
    "sg:city":"Gretzenbach",
    "sg:orig_category":"Herstellung von Drahtwaren Herstellung von sonstigen Metallwaren",
    "sg:phone":"+41 62 824 87 17",
    "sg:postcode":"5014",
    "sg:province":"Solothurn",
    "wof:name":"Aare Bau + Beratungs Ag",
    "wof:placetype":"venue"
},
  "geometry": {"coordinates":[7.9913620949,47.3609733582],"type":"Point"}
}