{
  "type": "Feature",
  "properties": {
    "iso:country":"CH",
    "sg:address":"Neustadtgasse 22",
    "sg:city":"Winterthur",
    "sg:orig_category":"Selbst\u00e4ndige bildende K\u00fcnstler",
    "sg:phone":"+41 52 741 33 62",
    "sg:postcode":"8400",
    "sg:province":"Z\u00fcrich",
    "wof:name":"J\u00fcrg St\u00e4heli Bildhaueratelier",
    "wof:placetype":"venue"
},
  "geometry": {"coordinates":[8.8555803299,47.6542472839],"type":"Point"}
}