{
  "type": "Feature",
  "properties": {
    "iso:country":"CH",
    "sg:address":"8757",
    "sg:city":"Filzbach",
    "sg:classifiers":[
        {
            "category":"Restaurant",
            "type":"Food & Drink"
        }
    ],
    "sg:phone":"+41 81 833 36 34",
    "sg:postcode":"8757",
    "sg:province":"Glarus",
    "wof:name":"Bergrestaurant Hahnensee",
    "wof:placetype":"venue"
},
  "geometry": {"coordinates":[9.8381900787,46.4970588684],"type":"Point"}
}