{
  "type": "Feature",
  "properties": {
    "iso:country":"CH",
    "sg:address":"Ellenbogenstrasse 36 8633 Wolfhausen. Postfach",
    "sg:city":"Wolfhausen",
    "sg:orig_category":"Pensionskassen",
    "sg:postcode":"8633",
    "sg:province":"Z\u00fcrich",
    "wof:name":"Vorsorgestiftung Der Firma Orgamat Ag",
    "wof:placetype":"venue"
},
  "geometry": {"coordinates":[8.796169281,47.2617263794],"type":"Point"}
}