{
  "type": "Feature",
  "properties": {
    "iso:country":"CH",
    "sg:address":"En Crevel 81.",
    "sg:city":"Cheyres",
    "sg:orig_category":"Sonstige pers\u00f6nliche Dienstleistungen",
    "sg:phone":"+41 26 663 22 12",
    "sg:postcode":"1468",
    "sg:province":"Fribourg",
    "wof:name":"Astrotest, P. De La Madeleine",
    "wof:placetype":"venue"
},
  "geometry": {"coordinates":[6.7758998871,46.8116149902],"type":"Point"}
}