{
  "type": "Feature",
  "properties": {
    "iso:country":"CH",
    "sg:address":"Englisch-gruss-strasse 10",
    "sg:city":"Glis",
    "sg:orig_category":"Herstellung von Drahtwaren Sonstiger spezialisierter Hoch U Tiefbau",
    "sg:postcode":"3902",
    "sg:province":"Valais",
    "wof:name":"Ren\u00e9 Zbinden Eisen-beton-armierungen",
    "wof:placetype":"venue"
},
  "geometry": {"coordinates":[7.9858808517,46.3162918091],"type":"Point"}
}