{
  "type": "Feature",
  "properties": {
    "iso:country":"CH",
    "sg:address":"Via Pocobelli 2b",
    "sg:city":"Melide",
    "sg:orig_category":"Handel mit Automobilen Handelsvermittlung U Grosshandel mit Automobilen",
    "sg:phone":"+41 91 649 31 52",
    "sg:postcode":"6815",
    "sg:province":"Ticino",
    "wof:name":"Melcar Sa",
    "wof:placetype":"venue"
},
  "geometry": {"coordinates":[8.947183609,45.9548492432],"type":"Point"}
}