{
  "type": "Feature",
  "properties": {
    "iso:country":"CH",
    "sg:address":"Ringstrasse 11",
    "sg:city":"Oberrohrdorf",
    "sg:classifiers":[
        {
            "category":"Restaurant",
            "type":"Food & Drink"
        }
    ],
    "sg:phone":"+41 62 893 12 69",
    "sg:postcode":"5452",
    "sg:province":"Aargau",
    "wof:name":"Restaurant Waage",
    "wof:placetype":"venue"
},
  "geometry": {"coordinates":[8.1823453903,47.4166145325],"type":"Point"}
}