{
  "type": "Feature",
  "properties": {
    "addr:full":"Alte Landstrasse 150 Meilen Z\u00fcrich 8706",
    "addr:housenumber":"150",
    "addr:postcode":"8706",
    "addr:street":"Alte Landstrasse",
    "iso:country":"CH",
    "sg:address":"Alte Landstrasse 150",
    "sg:city":"Meilen",
    "sg:orig_category":"Abwasserreinigung",
    "sg:phone":"+41 19233038",
    "sg:postcode":"8706",
    "sg:province":"Z\u00fcrich",
    "wof:name":"Kl\u00e4ranlage",
    "wof:placetype":"venue"
},
  "geometry": {"coordinates":[8.660948,47.2654],"type":"Point"}
}