{
  "type": "Feature",
  "properties": {
    "iso:country":"CH",
    "sg:address":"Im Chrummacher 5 8604 Volketswil. Postfach",
    "sg:city":"Schwerzenbach",
    "sg:orig_category":"Detailhandel mit elektrischen Haushalts-,Radio U Fernsehger\u00e4ten sowie Musikinstrumenten Grosshandel ",
    "sg:phone":"+41 19455089",
    "sg:postcode":"8603",
    "sg:province":"Z\u00fcrich",
    "wof:name":"Musik Rutschmann Ag",
    "wof:placetype":"venue"
},
  "geometry": {"coordinates":[8.6811800003,47.3797912598],"type":"Point"}
}