{
  "type": "Feature",
  "properties": {
    "iso:country":"CH",
    "sg:address":"Lilienweg 6",
    "sg:city":"Winterthur",
    "sg:orig_category":"Sportvereine Turnen Vereine Damen",
    "sg:phone":"+41 52 222 33 11",
    "sg:postcode":"8400",
    "sg:province":"Z\u00fcrich",
    "wof:name":"Damenturnverein Winterthur",
    "wof:placetype":"venue"
},
  "geometry": {"coordinates":[8.7120399475,47.5081558228],"type":"Point"}
}