{
  "type": "Feature",
  "properties": {
    "iso:country":"CH",
    "sg:address":"Via San Gottardo 71",
    "sg:city":"Massagno",
    "sg:orig_category":"Non-Classified Establishments",
    "sg:postcode":"6900",
    "sg:province":"Ticino",
    "wof:name":"Elleci Sa",
    "wof:placetype":"venue"
},
  "geometry": {"coordinates":[8.9468727112,46.0120697021],"type":"Point"}
}