{
  "type": "Feature",
  "properties": {
    "iso:country":"CH",
    "sg:address":"Chemin Du Parc 2",
    "sg:city":"Bussigny-lausanne",
    "sg:orig_category":"Autogaragen",
    "sg:phone":"+41 79 212 63 12",
    "sg:postcode":"1030",
    "sg:province":"Vaud",
    "wof:name":"Alfonso Di Fiore Garage De La Mascotte",
    "wof:placetype":"venue"
},
  "geometry": {"coordinates":[6.552981,46.549145],"type":"Point"}
}