{
  "type": "Feature",
  "properties": {
    "iso:country":"CH",
    "sg:address":"B\u00fcelstrasse 2",
    "sg:city":"Effretikon",
    "sg:orig_category":"Grosshandel mit Eisenwaren sowie Installationsbedarf f\u00fcr Gas, Wasser U Heizung Sanit\u00e4r, Heizungs U L",
    "sg:phone":"+41 52 343 10 71",
    "sg:postcode":"8307",
    "sg:province":"Z\u00fcrich",
    "wof:name":"L\u00f6rtscher Sanit\u00e4r Gmbh",
    "wof:placetype":"venue"
},
  "geometry": {"coordinates":[8.6863212585,47.4235954285],"type":"Point"}
}