{
  "type": "Feature",
  "properties": {
    "iso:country":"CH",
    "sg:address":"Le Chaluet",
    "sg:city":"Court",
    "sg:classifiers":[
        {
            "category":"Restaurant",
            "type":"Food & Drink"
        }
    ],
    "sg:phone":"+41 71 633 12 14",
    "sg:postcode":"2738",
    "sg:province":"Bern",
    "wof:name":"Restaurant Le Clou",
    "wof:placetype":"venue"
},
  "geometry": {"coordinates":[9.1515369415,47.5506629944],"type":"Point"}
}