{
  "type": "Feature",
  "properties": {
    "iso:country":"CH",
    "sg:address":"6863",
    "sg:city":"Besazio",
    "sg:classifiers":[
        {
            "category":"Restaurant",
            "type":"Food & Drink"
        }
    ],
    "sg:phone":"+41 91 646 36 83",
    "sg:postcode":"6863",
    "sg:province":"Ticino",
    "wof:name":"Grotto Rubiana",
    "wof:placetype":"venue"
},
  "geometry": {"coordinates":[8.9533395767,45.8709411621],"type":"Point"}
}