{
  "type": "Feature",
  "properties": {
    "iso:country":"CH",
    "sg:address":"Geboltshausen",
    "sg:city":"Neuwilen",
    "sg:orig_category":"Grosshandel mit Sportartikeln Handel mit Motorr\u00e4dern, Teilen U Zubeh\u00f6r Instandhaltung U Reparatur vo",
    "sg:phone":"+41 56 621 19 70",
    "sg:postcode":"8566",
    "sg:province":"Thurgau",
    "wof:name":"Moto-corner E. Strebel",
    "wof:placetype":"venue"
},
  "geometry": {"coordinates":[8.2678718567,47.3604888916],"type":"Point"}
}