{
  "type": "Feature",
  "properties": {
    "iso:country":"CH",
    "sg:address":"Bahnhofstrasse 13",
    "sg:city":"Bettwiesen",
    "sg:orig_category":"Instandhaltung U Reparatur von Automobilen",
    "sg:phone":"+41 71 910 20 30",
    "sg:postcode":"9553",
    "sg:province":"Thurgau",
    "wof:name":"Tonis Autowelt Gmbh",
    "wof:placetype":"venue"
},
  "geometry": {"coordinates":[9.0231428146,47.4982643127],"type":"Point"}
}