{
  "type": "Feature",
  "properties": {
    "iso:country":"CH",
    "sg:address":"Via E. Bossi 15",
    "sg:city":"Chiasso",
    "sg:orig_category":"Detailhandel mit elektrischen Haushalts-,Radio U Fernsehger\u00e4ten sowie Musikinstrumenten",
    "sg:postcode":"6830",
    "sg:province":"Ticino",
    "wof:name":"Nifer Sagl",
    "wof:placetype":"venue"
},
  "geometry": {"coordinates":[9.0309963226,45.8344192505],"type":"Point"}
}