{
  "type": "Feature",
  "properties": {
    "iso:country":"CH",
    "sg:address":"Rue Virginio-malnati 37",
    "sg:city":"Meyrin",
    "sg:classifiers":[
        {
            "category":"Building & Trades",
            "subcategory":"Construction",
            "type":"Services"
        }
    ],
    "sg:phone":"+41 22 782 75 85",
    "sg:postcode":"1217",
    "sg:province":"Gen\u00e8ve",
    "sg:tags":[
        "installation",
        "air-conditioning",
        "system"
    ],
    "wof:name":"Vmv Montage Sa",
    "wof:placetype":"venue"
},
  "geometry": {"coordinates":[6.069769,46.226681],"type":"Point"}
}