{
  "type": "Feature",
  "properties": {
    "iso:country":"CH",
    "sg:address":"Flachsacker 8a",
    "sg:city":"Cham",
    "sg:orig_category":"Erbringung von Dienstleistungen f\u00fcr Unternehmen Satzherstellung U Reproduktion",
    "sg:phone":"+41 41 783 27 77",
    "sg:postcode":"6330",
    "sg:province":"Zug",
    "wof:name":"Comart Scans Satz Internet-homepages",
    "wof:placetype":"venue"
},
  "geometry": {"coordinates":[8.4660215378,47.1836585999],"type":"Point"}
}