{
  "type": "Feature",
  "properties": {
    "iso:country":"CH",
    "sg:address":"Spisermarkt Spisergasse 17",
    "sg:city":"St.gallen",
    "sg:classifiers":[
        {
            "category":"Restaurant",
            "type":"Food & Drink"
        }
    ],
    "sg:phone":"+41 19100768",
    "sg:postcode":"9000",
    "sg:province":"St. Gallen",
    "sg:tags":[
        "tea-rooms",
        "restaurants"
    ],
    "wof:name":"Restaurant Sternen, Gebhard Urs Und Manhart Silvia",
    "wof:placetype":"venue"
},
  "geometry": {"coordinates":[8.5881967545,47.3104972839],"type":"Point"}
}