{
  "type": "Feature",
  "properties": {
    "iso:country":"CH",
    "sg:address":"Sauverny Route De 6 1290 Versoix. Postfach",
    "sg:city":"Versoix",
    "sg:orig_category":"Non-Classified Establishments",
    "sg:postcode":"1290",
    "sg:province":"Gen\u00e8ve",
    "wof:name":"Samuel Rossier Transports Sa",
    "wof:placetype":"venue"
},
  "geometry": {"coordinates":[7.2124481201,46.0804595947],"type":"Point"}
}