{
  "type": "Feature",
  "properties": {
    "iso:country":"CH",
    "sg:address":"Burgmatt 32",
    "sg:city":"Baar",
    "sg:orig_category":"Non-Classified Establishments",
    "sg:postcode":"6340",
    "sg:province":"Zug",
    "wof:name":"Brilliant Energy Gerhard",
    "wof:placetype":"venue"
},
  "geometry": {"coordinates":[8.5380268097,47.1933784485],"type":"Point"}
}