{
  "type": "Feature",
  "properties": {
    "iso:country":"CH",
    "sg:address":"Aeschengraben 12",
    "sg:city":"Basel",
    "sg:classifiers":[
        {
            "category":"Banks & Credit Unions",
            "subcategory":"Bank",
            "type":"Services"
        }
    ],
    "sg:postcode":"4010",
    "sg:province":"Basel-Stadt",
    "wof:name":"Isag Kb Immoservice Ag",
    "wof:placetype":"venue"
},
  "geometry": {"coordinates":[9.37371,47.426392],"type":"Point"}
}