{
  "type": "Feature",
  "properties": {
    "iso:country":"CH",
    "sg:address":"Ch\u00e4ppeli",
    "sg:city":"Golaten",
    "sg:orig_category":"Gem\u00fcsebau",
    "sg:phone":"+41 31 755 67 85",
    "sg:postcode":"3207",
    "sg:province":"Bern",
    "wof:name":"Ulrich Brauen Gem\u00fcsebau",
    "wof:placetype":"venue"
},
  "geometry": {"coordinates":[7.2388739586,46.985408783],"type":"Point"}
}