{
  "type": "Feature",
  "properties": {
    "iso:country":"CH",
    "sg:address":"Kappelenweg 5a",
    "sg:city":"Hinterkappelen",
    "sg:orig_category":"Sportvereine Unihockey",
    "sg:phone":"+41 31 901 07 16",
    "sg:postcode":"3032",
    "sg:province":"Bern",
    "wof:name":"Uht Tv Wohlen",
    "wof:placetype":"venue"
},
  "geometry": {"coordinates":[7.3779802322,46.9664573669],"type":"Point"}
}