{
  "type": "Feature",
  "properties": {
    "iso:country":"CH",
    "sg:address":"Via G. Motta 10",
    "sg:city":"Chiasso",
    "sg:orig_category":"Unclassifiable Establishments",
    "sg:postcode":"6830",
    "sg:province":"Ticino",
    "wof:name":"Vin Et Chambres D'h\u00f4tes Holding Sa",
    "wof:placetype":"venue"
},
  "geometry": {"coordinates":[8.7577753067,47.2063064575],"type":"Point"}
}