{
  "type": "Feature",
  "properties": {
    "iso:country":"CH",
    "sg:address":"Engelgasse 9",
    "sg:city":"St.gallen",
    "sg:classifiers":[
        {
            "category":"Travel",
            "subcategory":"Hotels & Motels",
            "type":"Entertainment"
        }
    ],
    "sg:phone":"+41 41 497 12 46",
    "sg:postcode":"9000",
    "sg:province":"St. Gallen",
    "sg:tags":[
        "hotels",
        "mit",
        "restaurant"
    ],
    "wof:name":"Hotel Weisses Kreuz",
    "wof:placetype":"venue"
},
  "geometry": {"coordinates":[8.1731996536,47.0156593323],"type":"Point"}
}