{
  "type": "Feature",
  "properties": {
    "iso:country":"CH",
    "sg:address":"Neudorfstrasse 31 7430 Thusis. Postfach",
    "sg:city":"Thusis",
    "sg:orig_category":"Fachdetailhandel mit pharmazeutischen Produkten",
    "sg:postcode":"7430",
    "sg:province":"Graubunden",
    "wof:name":"Rhein-apotheke Bollinger",
    "wof:placetype":"venue"
},
  "geometry": {"coordinates":[9.4396219254,46.6953125],"type":"Point"}
}