{
  "type": "Feature",
  "properties": {
    "addr:full":"Hauptstrasse 10 Gempen Solothurn 4145",
    "addr:housenumber":"10",
    "addr:postcode":"4145",
    "addr:street":"Hauptstrasse",
    "iso:country":"CH",
    "sg:address":"Hauptstrasse 10",
    "sg:city":"Gempen",
    "sg:orig_category":"Bauschreinerei Herstellung von Konstruktionsteilen, Fertigbauteilen U Ausbauelementen aus Holz",
    "sg:phone":"+41 61 701 12 02",
    "sg:postcode":"4145",
    "sg:province":"Solothurn",
    "wof:name":"Schreinerei V\u00f6gtli Andreas",
    "wof:placetype":"venue"
},
  "geometry": {"coordinates":[7.65879,47.474541],"type":"Point"}
}