{
  "type": "Feature",
  "properties": {
    "iso:country":"CH",
    "sg:address":"Baarerstrasse 94",
    "sg:city":"Zug",
    "sg:orig_category":"Herstellung von Transportbeton",
    "sg:phone":"+41 71 642 19 19",
    "sg:postcode":"6300",
    "sg:province":"Zug",
    "wof:name":"Angelus Holding Ag",
    "wof:placetype":"venue"
},
  "geometry": {"coordinates":[8.5183916092,47.1783332825],"type":"Point"}
}