{
  "type": "Feature",
  "properties": {
    "iso:country":"CH",
    "sg:address":"Eckweg 10",
    "sg:city":"Biel/bienne",
    "sg:orig_category":"Detailhandel mit elektrischen Haushalts-,Radio U Fernsehger\u00e4ten sowie Musikinstrumenten",
    "sg:postcode":"2500",
    "sg:province":"Bern",
    "wof:name":"Audio-vid\u00e9o Centre Palermo L.",
    "wof:placetype":"venue"
},
  "geometry": {"coordinates":[7.2673687935,47.1489067078],"type":"Point"}
}