{
  "type": "Feature",
  "properties": {
    "iso:country":"CH",
    "sg:address":"Bridelstrasse 76",
    "sg:city":"Bern",
    "sg:orig_category":"Sportvereine Ballsport Handball",
    "sg:phone":"+41 31 371 81 41",
    "sg:postcode":"3008",
    "sg:province":"Bern",
    "wof:name":"Sv Eisenbahner",
    "wof:placetype":"venue"
},
  "geometry": {"coordinates":[7.4227161407,46.9391174316],"type":"Point"}
}