{
  "type": "Feature",
  "properties": {
    "iso:country":"CH",
    "sg:address":"Hotzlerweg 3",
    "sg:city":"Blauen",
    "sg:classifiers":[
        {
            "category":"Restaurant",
            "type":"Food & Drink"
        }
    ],
    "sg:phone":"+41 61 761 60 53",
    "sg:postcode":"4223",
    "sg:province":"Basel-Landschaft",
    "wof:name":"Restaurant Stachel",
    "wof:placetype":"venue"
},
  "geometry": {"coordinates":[7.5204620361,47.4493370056],"type":"Point"}
}