{
  "type": "Feature",
  "properties": {
    "iso:country":"CH",
    "sg:address":"Brunnmattstrasse 15 3007 Bern. Postfach",
    "sg:city":"Bern",
    "sg:orig_category":"Architektur U Ingenieurb\u00fcros Vermittlung von Immobilien",
    "sg:postcode":"3007",
    "sg:province":"Bern",
    "wof:name":"Hebeisen Gmbh",
    "wof:placetype":"venue"
},
  "geometry": {"coordinates":[7.486851,46.93074],"type":"Point"}
}