{
  "type": "Feature",
  "properties": {
    "iso:country":"CH",
    "sg:address":"Birchstrasse 593 8052 Seebach. Postfach",
    "sg:city":"Seebach",
    "sg:orig_category":"Herstellung von elektrischen Lampen U Leuchten",
    "sg:postcode":"8052",
    "sg:province":"Z\u00fcrich",
    "wof:name":"Firestorm Light & Soundsystems Wieland Licht, Musikanlagen; Vermietung",
    "wof:placetype":"venue"
},
  "geometry": {"coordinates":[8.5402402878,47.4224815369],"type":"Point"}
}