{
  "type": "Feature",
  "properties": {
    "addr:full":"Schaalgasse 10 Solothurn Solothurn 4500",
    "addr:housenumber":"10",
    "addr:postcode":"4500",
    "addr:street":"Schaalgasse",
    "iso:country":"CH",
    "sg:address":"Schaalgasse 10",
    "sg:city":"Solothurn",
    "sg:orig_category":"Detailhandel an Verkaufsst\u00e4nden U auf M\u00e4rkten",
    "sg:phone":"+41 81 826 52 33",
    "sg:postcode":"4500",
    "sg:province":"Solothurn",
    "wof:name":"Anita Hemmi Bazar Laret",
    "wof:placetype":"venue"
},
  "geometry": {"coordinates":[9.76417,46.428761],"type":"Point"}
}