{
  "type": "Feature",
  "properties": {
    "iso:country":"CH",
    "sg:address":"Scheuchzerstrasse 203",
    "sg:city":"Z\u00fcrich",
    "sg:orig_category":"Malerei",
    "sg:phone":"+41 13615063",
    "sg:postcode":"8057",
    "sg:province":"Z\u00fcrich",
    "wof:name":"Hans Alper S\u00f6hne Malergesch\u00e4ft",
    "wof:placetype":"venue"
},
  "geometry": {"coordinates":[8.5423898697,47.3952827454],"type":"Point"}
}