{
  "type": "Feature",
  "properties": {
    "iso:country":"CH",
    "sg:address":"Schaffhauserstrasse 432",
    "sg:city":"Z\u00fcrich",
    "sg:orig_category":"Arztpraxen",
    "sg:phone":"+41 19304000",
    "sg:postcode":"8050",
    "sg:province":"Z\u00fcrich",
    "wof:name":"Dres Med. Dinner & Zeller Spezial\u00e4rzte Fmh",
    "wof:placetype":"venue"
},
  "geometry": {"coordinates":[8.809136,47.331692],"type":"Point"}
}