{
  "type": "Feature",
  "properties": {
    "iso:country":"CH",
    "sg:address":"Avenue Alfred-cortot 7d",
    "sg:city":"Nyon",
    "sg:orig_category":"Arztpraxen",
    "sg:phone":"+41 32 967 96 30",
    "sg:postcode":"1260",
    "sg:province":"Vaud",
    "wof:name":"Dr M\u00e9d. Daniel Leuba M\u00e9decin Sp\u00e9cialiste Fmh",
    "wof:placetype":"venue"
},
  "geometry": {"coordinates":[6.830084,47.103977],"type":"Point"}
}