{
  "type": "Feature",
  "properties": {
    "iso:country":"CH",
    "sg:address":"Archstrasse 36",
    "sg:city":"Grenchen",
    "sg:classifiers":[
        {
            "category":"Manufacturing",
            "subcategory":"Glass & Minerals",
            "type":"Manufacturing & Wholesale Goods"
        }
    ],
    "sg:phone":"+41 32 653 04 74",
    "sg:postcode":"2540",
    "sg:province":"Solothurn",
    "sg:tags":[
        "made",
        "fa\u00e7ade",
        "panel"
    ],
    "wof:name":"Glas B\u00fcchler Ag",
    "wof:placetype":"venue"
},
  "geometry": {"coordinates":[7.414080143,47.1769294739],"type":"Point"}
}