{
  "type": "Feature",
  "properties": {
    "iso:country":"CH",
    "sg:address":"Schaffhauserstrasse 354",
    "sg:city":"Z\u00fcrich",
    "sg:orig_category":"Architekturb\u00fcros",
    "sg:phone":"+41 56 241 15 91",
    "sg:postcode":"8050",
    "sg:province":"Z\u00fcrich",
    "wof:name":"Robert Bachmann Architekturb\u00fcro",
    "wof:placetype":"venue"
},
  "geometry": {"coordinates":[8.546372,47.409931],"type":"Point"}
}