{
  "type": "Feature",
  "properties": {
    "iso:country":"CH",
    "sg:address":"Winterthurerstrasse 69 8472 Seuzach. Postfach",
    "sg:city":"Seuzach",
    "sg:orig_category":"Zimmerei, Dachdeckerei, Bauspenglerei U Abdichtung",
    "sg:phone":"+41 56 621 88 81",
    "sg:postcode":"8472",
    "sg:province":"Z\u00fcrich",
    "wof:name":"Dachschaden.ch Gmbh",
    "wof:placetype":"venue"
},
  "geometry": {"coordinates":[8.284412384,47.3485794067],"type":"Point"}
}