{
  "type": "Feature",
  "properties": {
    "iso:country":"CH",
    "sg:address":"Viale Stazione 31a",
    "sg:city":"Bellinzona",
    "sg:orig_category":"Elektroinstallation Technische B\u00fcros Elektro",
    "sg:phone":"+41 91 835 49 07",
    "sg:postcode":"6500",
    "sg:province":"Ticino",
    "wof:name":"Mauro Ortelli Studio Tecnico",
    "wof:placetype":"venue"
},
  "geometry": {"coordinates":[9.0277776718,46.194858551],"type":"Point"}
}