{
  "type": "Feature",
  "properties": {
    "iso:country":"CH",
    "sg:address":"Alpstrasse 8",
    "sg:city":"Kreuzlingen",
    "sg:classifiers":[
        {
            "category":"Restaurant",
            "type":"Food & Drink"
        }
    ],
    "sg:phone":"+41 71 672 96 98",
    "sg:postcode":"8280",
    "sg:province":"Thurgau",
    "wof:name":"Restaurant Schl\u00fcssel",
    "wof:placetype":"venue"
},
  "geometry": {"coordinates":[9.1716604233,47.6438369751],"type":"Point"}
}