{
  "type": "Feature",
  "properties": {
    "iso:country":"CH",
    "sg:address":"4224",
    "sg:city":"Nenzlingen",
    "sg:orig_category":"Primarschulen",
    "sg:phone":"+41 61 467 95 25",
    "sg:postcode":"4224",
    "sg:province":"Basel-Landschaft",
    "wof:name":"Primarschule",
    "wof:placetype":"venue"
},
  "geometry": {"coordinates":[7.7212600708,47.5278816223],"type":"Point"}
}