{
  "type": "Feature",
  "properties": {
    "iso:country":"CH",
    "sg:address":"Schrotm\u00e4ttli 13 6014 Littau. Postfach 545",
    "sg:city":"Littau",
    "sg:orig_category":"Detailhandel mit Fahrr\u00e4dern Handel mit Motorr\u00e4dern, Teilen U Zubeh\u00f6r Instandhaltung U Reparatur von ",
    "sg:phone":"+41 71 622 52 06",
    "sg:postcode":"6014",
    "sg:province":"Luzern",
    "wof:name":"M\u00fcller Friedrich Zweiradfachgesch\u00e4ft",
    "wof:placetype":"venue"
},
  "geometry": {"coordinates":[9.1381845474,47.5666694641],"type":"Point"}
}