{
  "type": "Feature",
  "properties": {
    "iso:country":"CH",
    "sg:address":"Maison De Commune",
    "sg:city":"Granges-marnand",
    "sg:orig_category":"Abwasserreinigung Wasserversorgung",
    "sg:phone":"+41 26 668 10 38",
    "sg:postcode":"1523",
    "sg:province":"Vaud",
    "wof:name":"Service Des Eaux De La Commune De Granges",
    "wof:placetype":"venue"
},
  "geometry": {"coordinates":[6.887525,46.76358],"type":"Point"}
}