{
  "type": "Feature",
  "properties": {
    "iso:country":"CH",
    "sg:address":"8201 Schaffhausen. Postfach 488",
    "sg:city":"Schaffhausen",
    "sg:orig_category":"Sportvereine Boxen",
    "sg:phone":"+41 52 643 60 79",
    "sg:postcode":"8201",
    "sg:province":"Schaffhausen",
    "wof:name":"Box-club Schaffhausen",
    "wof:placetype":"venue"
},
  "geometry": {"coordinates":[8.632229805,47.6974716187],"type":"Point"}
}