{
  "type": "Feature",
  "properties": {
    "iso:country":"CH",
    "sg:address":"Lindenhof 2",
    "sg:city":"Sarnen",
    "sg:orig_category":"Arztpraxen",
    "sg:phone":"+41 79 212 99 55",
    "sg:postcode":"6060",
    "sg:province":"Obwalden",
    "wof:name":"Dr.med.alfons Loher Spezialarzt Fmh",
    "wof:placetype":"venue"
},
  "geometry": {"coordinates":[9.360154,47.423138],"type":"Point"}
}