{
  "type": "Feature",
  "properties": {
    "iso:country":"CH",
    "sg:address":"1243",
    "sg:city":"Presinge",
    "sg:classifiers":[
        {
            "category":"Education",
            "subcategory":"Library",
            "type":"Public Place"
        }
    ],
    "sg:postcode":"1243",
    "sg:province":"Gen\u00e8ve",
    "sg:tags":[
        "u",
        "bibliotheken",
        "archive"
    ],
    "wof:name":"Biblioth\u00e8que Communale",
    "wof:placetype":"venue"
},
  "geometry": {"coordinates":[6.26267,46.215858],"type":"Point"}
}