{
  "type": "Feature",
  "properties": {
    "iso:country":"CH",
    "sg:address":"Fraumattstrasse 346",
    "sg:city":"Erstfeld",
    "sg:orig_category":"Sportvereine Alpinismus",
    "sg:phone":"+41 56 442 21 67",
    "sg:postcode":"6472",
    "sg:province":"Uri",
    "wof:name":"Sac Sektion Grenchen",
    "wof:placetype":"venue"
},
  "geometry": {"coordinates":[8.2302284241,47.5009117126],"type":"Point"}
}