{
  "type": "Feature",
  "properties": {
    "addr:full":"Br\u00fchlgasse 9 Kallnach Bern 3283",
    "addr:housenumber":"9",
    "addr:postcode":"3283",
    "addr:street":"Bruehlgasse",
    "iso:country":"CH",
    "sg:address":"Br\u00fchlgasse 9",
    "sg:city":"Kallnach",
    "sg:orig_category":"Autotransporte international Datenverarbeitungsdienste",
    "sg:phone":"+41 32 391 03 60",
    "sg:postcode":"3283",
    "sg:province":"Bern",
    "wof:name":"Marti Logistik Ag Logistik-auftr\u00e4ge Usw.",
    "wof:placetype":"venue"
},
  "geometry": {"coordinates":[7.232519,47.026031],"type":"Point"}
}