{
  "type": "Feature",
  "properties": {
    "iso:country":"CH",
    "sg:address":"Hauptgasse 75",
    "sg:city":"Solothurn",
    "sg:orig_category":"Schreib U \u00dcbersetzungsb\u00fcros",
    "sg:phone":"+41 32 626 46 66",
    "sg:postcode":"4500",
    "sg:province":"Solothurn",
    "wof:name":"Gasser & Co",
    "wof:placetype":"venue"
},
  "geometry": {"coordinates":[7.5389738083,47.2085151672],"type":"Point"}
}