{
  "type": "Feature",
  "properties": {
    "iso:country":"CH",
    "sg:address":"Grand-lancy Route Du 150a 1213 Onex. Postfach",
    "sg:city":"Onex",
    "sg:orig_category":"Vermietung U Verpachtung von eigenen Immobilien",
    "sg:phone":"+41 22 793 56 17",
    "sg:postcode":"1213",
    "sg:province":"Gen\u00e8ve",
    "wof:name":"Dsg G\u00e9rance Immobili\u00e8re, Grobet David Immeubles Etc",
    "wof:placetype":"venue"
},
  "geometry": {"coordinates":[6.1057658195,46.1796798706],"type":"Point"}
}