{
  "type": "Feature",
  "properties": {
    "iso:country":"CH",
    "sg:address":"4312",
    "sg:city":"Magden",
    "sg:orig_category":"Primarschulen",
    "sg:phone":"+41 61 841 13 70",
    "sg:postcode":"4312",
    "sg:province":"Aargau",
    "wof:name":"Primarschule",
    "wof:placetype":"venue"
},
  "geometry": {"coordinates":[7.8130888939,47.5284194946],"type":"Point"}
}