{
  "type": "Feature",
  "properties": {
    "iso:country":"CH",
    "sg:address":"Morena Via 8",
    "sg:city":"Massagno",
    "sg:orig_category":"RESTAURANTS: TEA-ROOMS",
    "sg:phone":"+41 91 966 61 60",
    "sg:postcode":"6900",
    "sg:province":"Ticino",
    "wof:name":"Way Foo Sa",
    "wof:placetype":"venue"
},
  "geometry": {"coordinates":[8.9372549057,46.0105133057],"type":"Point"}
}