{
  "type": "Feature",
  "properties": {
    "iso:country":"CH",
    "sg:address":"Schmitterstrasse 5b",
    "sg:city":"Diepoldsau",
    "sg:orig_category":"Herstellung von Mess U Kontrollinstrumenten U vorrichtungen",
    "sg:postcode":"9444",
    "sg:province":"St. Gallen",
    "wof:name":"Jacovelli Ipm Pr\u00e4zisions-mechanik",
    "wof:placetype":"venue"
},
  "geometry": {"coordinates":[9.659822464,47.3883056641],"type":"Point"}
}