{
  "type": "Feature",
  "properties": {
    "iso:country":"CH",
    "sg:address":"Thurgauerstrasse 10 9400 Rorschach. Postfach 234",
    "sg:city":"Rorschach",
    "sg:orig_category":"Zahnarztpraxen",
    "sg:phone":"+41 71 841 32 22",
    "sg:postcode":"9401",
    "sg:province":"St. Gallen",
    "wof:name":"Dr.med.dent.hanspeter Rickli Zahnarzt",
    "wof:placetype":"venue"
},
  "geometry": {"coordinates":[9.4881381989,47.4793891907],"type":"Point"}
}