{
  "type": "Feature",
  "properties": {
    "iso:country":"CH",
    "sg:address":"Steckweg 17 3014 Bern. Postfach",
    "sg:city":"Bern",
    "sg:orig_category":"Sonstige mit der Informatik verbundene T\u00e4tigkeiten",
    "sg:phone":"+41 31322227",
    "sg:postcode":"3005",
    "sg:province":"Bern",
    "wof:name":"Edv-beratung Und Organisation Wittwer Benjamin",
    "wof:placetype":"venue"
},
  "geometry": {"coordinates":[7.4447407722,46.9587860107],"type":"Point"}
}