{
  "type": "Feature",
  "properties": {
    "iso:country":"CH",
    "sg:address":"Murgenthalstrasse 33",
    "sg:city":"Langenthal",
    "sg:orig_category":"Kaminfeger",
    "sg:phone":"+41 62 922 25 80",
    "sg:postcode":"4900",
    "sg:province":"Bern",
    "wof:name":"Fritz Lanz Kaminfegergesch\u00e4ft",
    "wof:placetype":"venue"
},
  "geometry": {"coordinates":[7.7903409004,47.2251586914],"type":"Point"}
}