{
  "type": "Feature",
  "properties": {
    "iso:country":"CH",
    "sg:address":"Bachlettenstrasse 9",
    "sg:city":"Basel",
    "sg:orig_category":"Detailhandel mit Waren verschiedener Art, Hauptrichtung Nahrungsmittel Grosshandel mit Nahrungsmitte",
    "sg:phone":"+41 61 281 31 33",
    "sg:postcode":"4054",
    "sg:province":"Basel-Stadt",
    "wof:name":"Bachlette-paradiesli, Br\u00e4ndle J.",
    "wof:placetype":"venue"
},
  "geometry": {"coordinates":[7.5805888176,47.5500335693],"type":"Point"}
}