{
  "type": "Feature",
  "properties": {
    "iso:country":"CH",
    "sg:address":"Rue Des P\u00eacheurs 8 1400 Yverdon-les-bains. Postfach",
    "sg:city":"Yverdon",
    "sg:orig_category":"Vereine Mieter",
    "sg:phone":"+41 21 922 79 62",
    "sg:postcode":"1401",
    "sg:province":"Vaud",
    "wof:name":"Asloca,assoc.suisse Des Locat. Vevey La Tour-de-peilz & Env.",
    "wof:placetype":"venue"
},
  "geometry": {"coordinates":[5.1808700562,45.8973388672],"type":"Point"}
}