{
  "type": "Feature",
  "properties": {
    "iso:country":"CH",
    "sg:address":"Landstrasse 76",
    "sg:city":"Wettingen",
    "sg:orig_category":"Detailhandel mit Bekleidung",
    "sg:postcode":"5430",
    "sg:province":"Aargau",
    "wof:name":"Switcher Store Hotz U. + Walser B. Bekleidung U. Accessoires; Verkauf",
    "wof:placetype":"venue"
},
  "geometry": {"coordinates":[8.324032,47.466827],"type":"Point"}
}