{
  "type": "Feature",
  "properties": {
    "iso:country":"CH",
    "sg:address":"Hauptstrasse 33 2560 Nidau. Postfach 405",
    "sg:city":"Nidau",
    "sg:classifiers":[
        {
            "category":"Restaurant",
            "type":"Food & Drink"
        }
    ],
    "sg:phone":"+41 41 810 13 48",
    "sg:postcode":"2560",
    "sg:province":"Bern",
    "wof:name":"Restaurant Kreuz Seewen",
    "wof:placetype":"venue"
},
  "geometry": {"coordinates":[8.6281671524,47.0281181335],"type":"Point"}
}