{
  "type": "Feature",
  "properties": {
    "iso:country":"CH",
    "sg:address":"Erlenweg 501",
    "sg:city":"Kestenholz",
    "sg:orig_category":"Organisationen des Gesundheitswesen",
    "sg:phone":"+41 62 388 33 88",
    "sg:postcode":"4703",
    "sg:province":"Solothurn",
    "wof:name":"Samariterverein Oensingen",
    "wof:placetype":"venue"
},
  "geometry": {"coordinates":[7.7589898109,47.2845306396],"type":"Point"}
}