{
  "type": "Feature",
  "properties": {
    "iso:country":"CH",
    "sg:address":"Route De L'etraz 172",
    "sg:city":"Versoix",
    "sg:orig_category":"Abbruch U Sprenggewerbe, Erdbewegungsarbeiten Maurerarbeiten",
    "sg:phone":"+41 21 921 21 55",
    "sg:postcode":"1290",
    "sg:province":"Gen\u00e8ve",
    "wof:name":"Entreprise Jaggi + Pousaz Sa",
    "wof:placetype":"venue"
},
  "geometry": {"coordinates":[5.18087,45.897339],"type":"Point"}
}