{
  "type": "Feature",
  "properties": {
    "addr:full":"Ueberlandstrasse 99 D\u00fcbendorf Z\u00fcrich 8600",
    "addr:housenumber":"99",
    "addr:postcode":"8600",
    "addr:street":"Ueberlandstrasse",
    "iso:country":"CH",
    "sg:address":"Ueberlandstrasse 99",
    "sg:city":"D\u00fcbendorf",
    "sg:orig_category":"Detailhandel mit Bekleidung Grosshandel mit Bekleidung",
    "sg:phone":"+41 21 695 24 90",
    "sg:postcode":"8600",
    "sg:province":"Z\u00fcrich",
    "wof:name":"Levi Strauss (suisse) Sa",
    "wof:placetype":"venue"
},
  "geometry": {"coordinates":[6.54302,46.51239],"type":"Point"}
}