{
  "type": "Feature",
  "properties": {
    "iso:country":"CH",
    "sg:address":"Eggen",
    "sg:city":"Eggerberg",
    "sg:orig_category":"Regelm\u00e4ssige Personenbef\u00f6rderung im Fernverkehr",
    "sg:phone":"+41 79 214 51 55",
    "sg:postcode":"3939",
    "sg:province":"Valais",
    "wof:name":"Hans Hutter Postautokurse",
    "wof:placetype":"venue"
},
  "geometry": {"coordinates":[7.8822999001,46.3181190491],"type":"Point"}
}