{
  "type": "Feature",
  "properties": {
    "iso:country":"CH",
    "sg:address":"Pelli Via Ferruccio 9",
    "sg:city":"Lugano",
    "sg:orig_category":"Herstellung von Maschinen f\u00fcr die Textil, Bekleidungsherstellung U die Lederverarbeitung",
    "sg:phone":"+41 91 923 29 22",
    "sg:postcode":"6900",
    "sg:province":"Ticino",
    "wof:name":"Sperotto International Sa, Lussemburgo, Succursale Di Lugano",
    "wof:placetype":"venue"
},
  "geometry": {"coordinates":[8.9507932663,46.0079956055],"type":"Point"}
}