{
  "type": "Feature",
  "properties": {
    "iso:country":"CH",
    "sg:address":"Gambini Rue Giovanni- 3",
    "sg:city":"Gen\u00e8ve",
    "sg:orig_category":"Unclassifiable Establishments",
    "sg:postcode":"1206",
    "sg:province":"Gen\u00e8ve",
    "wof:name":"Patrice Bettex Laboratoire Dentaire S\u00e0rl",
    "wof:placetype":"venue"
},
  "geometry": {"coordinates":[6.5715141296,46.908290863],"type":"Point"}
}