{
  "type": "Feature",
  "properties": {
    "iso:country":"CH",
    "sg:address":"Chemin De L'orgerie 25",
    "sg:city":"Tavannes",
    "sg:orig_category":"Interessenvertretungen",
    "sg:postcode":"2710",
    "sg:province":"Bern",
    "wof:name":"Fondation Du Centre Scout Pierre-pertuis Tavannes Et Environs",
    "wof:placetype":"venue"
},
  "geometry": {"coordinates":[7.2055997849,47.2281150818],"type":"Point"}
}