{
  "type": "Feature",
  "properties": {
    "iso:country":"CH",
    "sg:address":"Via Pedevilla 43a",
    "sg:city":"Giubiasco",
    "sg:orig_category":"Elektroinstallation",
    "sg:phone":"+41 91 857 77 07",
    "sg:postcode":"6512",
    "sg:province":"Ticino",
    "wof:name":"Elettroticino Sa Impianti Elettrici",
    "wof:placetype":"venue"
},
  "geometry": {"coordinates":[9.0236148834,46.1818847656],"type":"Point"}
}