{
  "type": "Feature",
  "properties": {
    "addr:full":"Xxxi-d\u00e9cembre Rue Du 42 1207 Gen\u00e8ve. Postfach Gen\u00e8ve Gen\u00e8ve 1207",
    "addr:postcode":"1207;postfach;1207",
    "addr:street":"Rue Du 42",
    "iso:country":"CH",
    "sg:address":"Xxxi-d\u00e9cembre Rue Du 42 1207 Gen\u00e8ve. Postfach",
    "sg:city":"Gen\u00e8ve",
    "sg:orig_category":"Architektur U Ingenieurb\u00fcros",
    "sg:postcode":"1207",
    "sg:province":"Gen\u00e8ve",
    "wof:name":"Aerni Robert Ing\u00e9nieur Sa, Succursale De Gen\u00e8ve Gestion D'un Entreprise D'ing\u00e9nieur En Installation Technique Du B\u00e2timent",
    "wof:placetype":"venue"
},
  "geometry": {"coordinates":[6.16178,46.200588],"type":"Point"}
}