{
  "type": "Feature",
  "properties": {
    "iso:country":"CH",
    "sg:address":"Hemmikerstr. 39",
    "sg:city":"Ormalingen",
    "sg:orig_category":"Pensionskassen",
    "sg:postcode":"4466",
    "sg:province":"Basel-Landschaft",
    "wof:name":"Wohlfahrtsstiftung Der Ruepp Ag",
    "wof:placetype":"venue"
},
  "geometry": {"coordinates":[7.8818612099,47.4718132019],"type":"Point"}
}