{
  "type": "Feature",
  "properties": {
    "iso:country":"CH",
    "sg:address":"Lindenhofstrasse 15",
    "sg:city":"Z\u00fcrich",
    "sg:orig_category":"Public-Relations-Agenturen Werbung",
    "sg:phone":"+41 12114461",
    "sg:postcode":"8001",
    "sg:province":"Z\u00fcrich",
    "wof:name":"K\u00f6ppel + Erb Ag Public Relations",
    "wof:placetype":"venue"
},
  "geometry": {"coordinates":[8.5403308868,47.3738327026],"type":"Point"}
}