{
  "type": "Feature",
  "properties": {
    "iso:country":"CH",
    "sg:address":"B\u00fcttenen 10",
    "sg:city":"Grellingen",
    "sg:orig_category":"Instandhaltung U Reparatur von Automobilen",
    "sg:phone":"+41 61 741 15 33",
    "sg:postcode":"4203",
    "sg:province":"Basel-Landschaft",
    "wof:name":"Christof Dietlin Carrosserie & Spritzwerk",
    "wof:placetype":"venue"
},
  "geometry": {"coordinates":[7.5966510773,47.4426689148],"type":"Point"}
}