{
  "type": "Feature",
  "properties": {
    "iso:country":"CH",
    "sg:address":"R\u00e9seau Communal",
    "sg:city":"Montsevelier",
    "sg:orig_category":"Wasserversorgung",
    "sg:postcode":"2828",
    "sg:province":"Jura",
    "wof:name":"Service Des Eaux De La Commune De Montsevelier",
    "wof:placetype":"venue"
},
  "geometry": {"coordinates":[7.5077900887,47.3606987],"type":"Point"}
}