{
  "type": "Feature",
  "properties": {
    "iso:country":"CH",
    "sg:address":"Luzernerstrasse 16 6330 Cham. Postfach 495",
    "sg:city":"Cham",
    "sg:orig_category":"Detailhandel mit Uhren U Schmuck",
    "sg:phone":"+41 41 780 00 33",
    "sg:postcode":"6330",
    "sg:province":"Zug",
    "wof:name":"Franz Schmid Goldschmiede",
    "wof:placetype":"venue"
},
  "geometry": {"coordinates":[8.4582185745,47.1798858643],"type":"Point"}
}