{
  "type": "Feature",
  "properties": {
    "iso:country":"CH",
    "sg:address":"Turnhallenweg 1",
    "sg:city":"R\u00fcschlikon",
    "sg:orig_category":"Werbeberatung",
    "sg:phone":"+41 43 388 08 08",
    "sg:postcode":"8803",
    "sg:province":"Z\u00fcrich",
    "wof:name":"Urte Sabelus Public Relations Beratung",
    "wof:placetype":"venue"
},
  "geometry": {"coordinates":[8.5568380356,47.3079071045],"type":"Point"}
}