{
  "type": "Feature",
  "properties": {
    "iso:country":"CH",
    "sg:address":"Gr\u00fcngli 117",
    "sg:city":"G\u00fcnsberg",
    "sg:orig_category":"Finanzierungsinstitutionen",
    "sg:postcode":"4524",
    "sg:province":"Solothurn",
    "wof:name":"Schenker Consulting",
    "wof:placetype":"venue"
},
  "geometry": {"coordinates":[7.5768961906,47.2535820007],"type":"Point"}
}