{
  "type": "Feature",
  "properties": {
    "iso:country":"CH",
    "sg:address":"Boulevard De Grancy 19a",
    "sg:city":"Lausanne",
    "sg:orig_category":"Unternehmensberatung",
    "sg:postcode":"1000",
    "sg:province":"Vaud",
    "wof:name":"Sysnet Ag",
    "wof:placetype":"venue"
},
  "geometry": {"coordinates":[8.2827892303,47.3500785828],"type":"Point"}
}