{
  "type": "Feature",
  "properties": {
    "iso:country":"CH",
    "sg:address":"Talweg 143",
    "sg:city":"Uster",
    "sg:orig_category":"Einbau von Schreinerwaren",
    "sg:phone":"+41 19421341",
    "sg:postcode":"8610",
    "sg:province":"Z\u00fcrich",
    "wof:name":"Pierre Furrer Schreiner-montagen",
    "wof:placetype":"venue"
},
  "geometry": {"coordinates":[8.7303342819,47.3485603333],"type":"Point"}
}