{
  "type": "Feature",
  "properties": {
    "addr:full":"Maiengasse 46 Basel Basel-Stadt 4056",
    "addr:housenumber":"46",
    "addr:postcode":"4056",
    "addr:street":"Maiengasse",
    "iso:country":"CH",
    "sg:address":"Maiengasse 46",
    "sg:city":"Basel",
    "sg:orig_category":"Arztpraxen",
    "sg:phone":"+41 61 261 12 81",
    "sg:postcode":"4056",
    "sg:province":"Basel-Stadt",
    "wof:name":"Dr.med. Ir\u00e8ne Hubermann Spezial\u00e4rztin",
    "wof:placetype":"venue"
},
  "geometry": {"coordinates":[7.577817,47.561405],"type":"Point"}
}