{
  "type": "Feature",
  "properties": {
    "iso:country":"CH",
    "sg:address":"Via Locarno 58",
    "sg:city":"Losone",
    "sg:orig_category":"Softwareentwicklung U beratung Unternehmensberatung",
    "sg:phone":"+41 91 780 52 81",
    "sg:postcode":"6616",
    "sg:province":"Ticino",
    "wof:name":"Pierangelo Casarotti",
    "wof:placetype":"venue"
},
  "geometry": {"coordinates":[8.7677497864,46.1651344299],"type":"Point"}
}