{
  "type": "Feature",
  "properties": {
    "iso:country":"CH",
    "sg:address":"Wildbachstrasse 17 8008 Z\u00fcrich. Postfach",
    "sg:city":"Z\u00fcrich",
    "sg:orig_category":"Non-Classified Establishments",
    "sg:postcode":"8008",
    "sg:province":"Z\u00fcrich",
    "wof:name":"Yahoo! Switzerland Gmbh Angebot Von Dienstleistungen U. Produkten Rund Um Das Internet Usw",
    "wof:placetype":"venue"
},
  "geometry": {"coordinates":[8.5573358536,47.3567352295],"type":"Point"}
}