{
  "type": "Feature",
  "properties": {
    "addr:full":"Rosenstrasse 3 3800 Interlaken. Postfach 293 Interlaken Bern 3800",
    "addr:housenumber":"3;293",
    "addr:postcode":"3800;3800",
    "addr:street":"Rosenstrasse;Postfach",
    "iso:country":"CH",
    "sg:address":"Rosenstrasse 3 3800 Interlaken. Postfach 293",
    "sg:city":"Interlaken",
    "sg:orig_category":"Aktivit\u00e4ten der Generalunternehmen im Baugewerbe Allgemeiner Hoch U Tiefbau",
    "sg:phone":"+41 71 744 26 11",
    "sg:postcode":"3800",
    "sg:province":"Bern",
    "wof:name":"Reich J. Ag, Generalunternehmung",
    "wof:placetype":"venue"
},
  "geometry": {"coordinates":[9.62869,47.436661],"type":"Point"}
}