{
  "type": "Feature",
  "properties": {
    "iso:country":"CH",
    "sg:address":"Zona Industriale 3",
    "sg:city":"Quartino",
    "sg:orig_category":"Herstellung von Nahrungsmitteln undGetr\u00e4nken",
    "sg:phone":"+41 91 795 33 85",
    "sg:postcode":"6572",
    "sg:province":"Ticino",
    "wof:name":"Gamma's Saucen & Feinkost Salse & Specialit\u00e0 Gastron.",
    "wof:placetype":"venue"
},
  "geometry": {"coordinates":[8.8953781128,46.1506347656],"type":"Point"}
}