{
  "type": "Feature",
  "properties": {
    "iso:country":"CH",
    "sg:address":"Hofackerstrasse 3a",
    "sg:city":"Muttenz",
    "sg:orig_category":"Wirtschaftspr\u00fcfung, Steuerberatung U Treuhand",
    "sg:phone":"+41 27 398 13 14",
    "sg:postcode":"4132",
    "sg:province":"Basel-Landschaft",
    "wof:name":"Agence D'administration Et De G\u00e9rance Immobili\u00e8re Adagi Sa",
    "wof:placetype":"venue"
},
  "geometry": {"coordinates":[7.4068250656,46.2767829895],"type":"Point"}
}