{
  "type": "Feature",
  "properties": {
    "iso:country":"CH",
    "sg:address":"Bettlistrasse 35 8600 D\u00fcbendorf. Postfach",
    "sg:city":"D\u00fcbendorf",
    "sg:orig_category":"Sonstiges Versicherungsgewerbe",
    "sg:postcode":"8600",
    "sg:province":"Z\u00fcrich",
    "wof:name":"Winterthur-leben, Generalagentur D\u00fcbendorf, Peter H. M\u00fcller",
    "wof:placetype":"venue"
},
  "geometry": {"coordinates":[8.6255559921,47.3974304199],"type":"Point"}
}