{
  "type": "Feature",
  "properties": {
    "iso:country":"CH",
    "sg:address":"Birsigstrasse 2 4054 Basel. Postfach",
    "sg:city":"Basel",
    "sg:orig_category":"Interessenvertretungen",
    "sg:postcode":"4051",
    "sg:province":"Basel-Stadt",
    "wof:name":"Egeria Club F\u00f6rderung D. Pers\u00f6nl., Wirtschaftl., Polit., Kultur., Beziehungen In D. Schweiz U. Ungarn",
    "wof:placetype":"venue"
},
  "geometry": {"coordinates":[7.5854759216,47.5511894226],"type":"Point"}
}