{
  "type": "Feature",
  "properties": {
    "iso:country":"CH",
    "sg:address":"Viale Portone 6",
    "sg:city":"Bellinzona",
    "sg:orig_category":"Herstellung von K\u00fcchenm\u00f6beln Herstellung von Schreinerwaren ohne ausgepr\u00e4gten Schwerpunkt",
    "sg:phone":"+41 91 825 41 06",
    "sg:postcode":"6500",
    "sg:province":"Ticino",
    "wof:name":"Rosso & Figli Sa",
    "wof:placetype":"venue"
},
  "geometry": {"coordinates":[9.02110672,46.1939125061],"type":"Point"}
}