{
  "type": "Feature",
  "properties": {
    "iso:country":"CH",
    "sg:address":"Junkerngasse 24",
    "sg:city":"Hunzenschwil",
    "sg:orig_category":"Kauf U Verkauf von Immobilien auf eigene Rechnung",
    "sg:phone":"+41 19207300",
    "sg:postcode":"5502",
    "sg:province":"Aargau",
    "wof:name":"Lobinvest Ag",
    "wof:placetype":"venue"
},
  "geometry": {"coordinates":[8.6809473038,47.2621803284],"type":"Point"}
}