{
  "type": "Feature",
  "properties": {
    "addr:full":"Erlenweg 11 Burgdorf Bern 3400",
    "addr:housenumber":"11",
    "addr:postcode":"3400",
    "addr:street":"Erlenweg",
    "iso:country":"CH",
    "sg:address":"Erlenweg 11",
    "sg:city":"Burgdorf",
    "sg:orig_category":"Datenverarbeitungsdienste Sonstige mit der Informatik verbundene T\u00e4tigkeiten",
    "sg:phone":"+41 34 420 18 10",
    "sg:postcode":"3400",
    "sg:province":"Bern",
    "wof:name":"Kessi Edv & Betriebsberatung",
    "wof:placetype":"venue"
},
  "geometry": {"coordinates":[7.621852,47.064655],"type":"Point"}
}