{
  "type": "Feature",
  "properties": {
    "iso:country":"CH",
    "sg:address":"St. Jakobs-strasse 377 4052 Basel. Postfach",
    "sg:city":"Basel",
    "sg:orig_category":"RESTAURANTS: TEA-ROOMS",
    "sg:postcode":"4051",
    "sg:province":"Basel-Stadt",
    "wof:name":"Bont Bettina + Eggenberger C\u00e9cile Wirtshaus St. Jakob",
    "wof:placetype":"venue"
},
  "geometry": {"coordinates":[7.6176600456,47.5416641235],"type":"Point"}
}