{
  "type": "Feature",
  "properties": {
    "iso:country":"CH",
    "sg:address":"Rue De La Place 5",
    "sg:city":"Chamoson",
    "sg:orig_category":"Rebbau",
    "sg:phone":"+41 79 220 35 11",
    "sg:postcode":"1955",
    "sg:province":"Valais",
    "wof:name":"Jacques Disner Propri\u00e9taire-encaveur",
    "wof:placetype":"venue"
},
  "geometry": {"coordinates":[7.2224979401,46.1995124817],"type":"Point"}
}