{
  "type": "Feature",
  "properties": {
    "iso:country":"CH",
    "sg:address":"Limmatquai 94",
    "sg:city":"Z\u00fcrich",
    "sg:orig_category":"Softwareentwicklung U beratung",
    "sg:postcode":"8001",
    "sg:province":"Z\u00fcrich",
    "wof:name":"Anytools Gmbh",
    "wof:placetype":"venue"
},
  "geometry": {"coordinates":[8.7355890274,47.1970024109],"type":"Point"}
}