{
  "type": "Feature",
  "properties": {
    "iso:country":"CH",
    "sg:address":"Rue Du Puits-godet 20",
    "sg:city":"Neuch\u00e2tel",
    "sg:orig_category":"Sonstiger Grosshandel Versandhandel",
    "sg:phone":"+41 32 724 50 40",
    "sg:postcode":"2000",
    "sg:province":"Neuch\u00e2tel",
    "wof:name":"Everest Holding Sa",
    "wof:placetype":"venue"
},
  "geometry": {"coordinates":[6.9117689133,46.9982261658],"type":"Point"}
}