{
  "type": "Feature",
  "properties": {
    "iso:country":"CH",
    "sg:address":"Friesenbergstrasse 38",
    "sg:city":"Z\u00fcrich",
    "sg:orig_category":"Grosshandel mit Parf\u00fcmerieartikeln U K\u00f6rperpflegemitteln Herstellung von Duft U K\u00f6rperpflegemitteln",
    "sg:phone":"+41 14516911",
    "sg:postcode":"8055",
    "sg:province":"Z\u00fcrich",
    "wof:name":"Slc Sportsline Cosmetics",
    "wof:placetype":"venue"
},
  "geometry": {"coordinates":[8.5117950439,47.3685722351],"type":"Point"}
}