{
  "type": "Feature",
  "properties": {
    "iso:country":"CH",
    "sg:address":"S\u00e4genstrasse 6",
    "sg:city":"Felsberg",
    "sg:orig_category":"Sanit\u00e4r, Heizungs U L\u00fcftungsinstallation Sanit\u00e4rinstallation",
    "sg:phone":"+41 56 622 83 51",
    "sg:postcode":"7012",
    "sg:province":"Graubunden",
    "wof:name":"Hans Meyer Ag, Sanit\u00e4r- & Heizungsinstallationen",
    "wof:placetype":"venue"
},
  "geometry": {"coordinates":[8.2871751785,47.3456192017],"type":"Point"}
}