{
  "type": "Feature",
  "properties": {
    "iso:country":"CH",
    "sg:address":"Im Loch 1 4539 Rumisberg. Postfach",
    "sg:city":"Rumisberg",
    "sg:orig_category":"Allgemeiner Hoch U Tiefbau",
    "sg:postcode":"4539",
    "sg:province":"Bern",
    "wof:name":"Felber Rohr Und Metallbau Carrosserie Gmbh",
    "wof:placetype":"venue"
},
  "geometry": {"coordinates":[7.641765,47.261795],"type":"Point"}
}