{
  "type": "Feature",
  "properties": {
    "iso:country":"CH",
    "sg:address":"Badstrasse 43",
    "sg:city":"Niederurnen",
    "sg:classifiers":[
        {
            "category":"Travel",
            "subcategory":"Hotels & Motels",
            "type":"Entertainment"
        }
    ],
    "sg:phone":"+41 55 610 17 03",
    "sg:postcode":"8867",
    "sg:province":"Glarus",
    "sg:tags":[
        "hotels",
        "mit",
        "restaurant"
    ],
    "wof:name":"Hrm Hotel Mineralbad Ag",
    "wof:placetype":"venue"
},
  "geometry": {"coordinates":[9.0514268875,47.1292266846],"type":"Point"}
}