{
  "type": "Feature",
  "properties": {
    "iso:country":"CH",
    "sg:address":"Saulcy Route De 17",
    "sg:city":"Glovelier",
    "sg:orig_category":"Forstwirtschaft ohne Dienstleistungen in der Forstwirtschaft",
    "sg:phone":"+41 32 426 62 71",
    "sg:postcode":"2855",
    "sg:province":"Jura",
    "wof:name":"Bailat Bernard",
    "wof:placetype":"venue"
},
  "geometry": {"coordinates":[7.1992797852,47.3326377869],"type":"Point"}
}