{
  "type": "Feature",
  "properties": {
    "addr:full":"Chemin De La Plage 18 St-blaise Neuch\u00e2tel 2072",
    "addr:housenumber":"18",
    "addr:postcode":"2072",
    "addr:street":"Chemin De La Plage;Neucha\u0302Tel",
    "iso:country":"CH",
    "sg:address":"Chemin De La Plage 18",
    "sg:city":"St-blaise",
    "sg:orig_category":"Autogaragen",
    "sg:phone":"+41 32 753 20 03",
    "sg:postcode":"2072",
    "sg:province":"Neuch\u00e2tel",
    "wof:name":"Nicolas Ghezzi Garage Fennec 4x4",
    "wof:placetype":"venue"
},
  "geometry": {"coordinates":[6.981607,47.012459],"type":"Point"}
}