{
  "type": "Feature",
  "properties": {
    "iso:country":"CH",
    "sg:address":"Kantonsstrasse 34",
    "sg:city":"Nottwil",
    "sg:orig_category":"Detailhandel mit Getreide, Futtermitteln U Landesprodukten Technische, physikalische U chemische Unt",
    "sg:phone":"+41 41 937 19 35",
    "sg:postcode":"6207",
    "sg:province":"Luzern",
    "wof:name":"Penac (schweiz) Ag",
    "wof:placetype":"venue"
},
  "geometry": {"coordinates":[8.1322088242,47.137550354],"type":"Point"}
}