{
  "type": "Feature",
  "properties": {
    "iso:country":"CH",
    "sg:address":"Bremgarterstrasse 15",
    "sg:city":"Widen",
    "sg:orig_category":"Tanzschulen, Tanzlehrer",
    "sg:phone":"+41 56 633 66 65",
    "sg:postcode":"8967",
    "sg:province":"Aargau",
    "wof:name":"C\u00e9cile Greminger Tanz-& Gymnastiklehrerin",
    "wof:placetype":"venue"
},
  "geometry": {"coordinates":[8.3611888885,47.3667793274],"type":"Point"}
}