{
  "type": "Feature",
  "properties": {
    "iso:country":"CH",
    "sg:address":"Stationsstrasse 50",
    "sg:city":"Seuzach",
    "sg:orig_category":"Reiseb\u00fcros",
    "sg:phone":"+41 19503908",
    "sg:postcode":"8472",
    "sg:province":"Z\u00fcrich",
    "wof:name":"Petuscha-reisen",
    "wof:placetype":"venue"
},
  "geometry": {"coordinates":[8.7893877029,47.3697433472],"type":"Point"}
}