{
  "type": "Feature",
  "properties": {
    "iso:country":"CH",
    "sg:address":"Ausserschwandstrasse 15",
    "sg:city":"Adelboden",
    "sg:orig_category":"Bestattungswesen Herstellung von Konstruktionsteilen, Fertigbauteilen U Ausbauelementen aus Holz",
    "sg:phone":"+41 33 673 44 55",
    "sg:postcode":"3715",
    "sg:province":"Bern",
    "wof:name":"Allenbach Peter, Schreinerei/bestattungsdienst",
    "wof:placetype":"venue"
},
  "geometry": {"coordinates":[7.566936,46.499386],"type":"Point"}
}