{
  "type": "Feature",
  "properties": {
    "iso:country":"CH",
    "sg:address":"Dorf",
    "sg:city":"Albligen",
    "sg:orig_category":"Detailhandel mit Waren verschiedener Art, Hauptrichtung Nahrungsmittel",
    "sg:phone":"+41 31 741 06 22",
    "sg:postcode":"3183",
    "sg:province":"Bern",
    "wof:name":"Marta Bieri Handlung",
    "wof:placetype":"venue"
},
  "geometry": {"coordinates":[7.3186979294,46.852897644],"type":"Point"}
}