{
  "type": "Feature",
  "properties": {
    "iso:country":"CH",
    "sg:address":"Gotthardstrasse",
    "sg:city":"G\u00f6schenen",
    "sg:orig_category":"Detailhandel mit Waren verschiedener Art, Hauptrichtung Nahrungsmittel",
    "sg:phone":"+41 41 885 14 20",
    "sg:postcode":"6487",
    "sg:province":"Uri",
    "wof:name":"Max Dubacher Handlung",
    "wof:placetype":"venue"
},
  "geometry": {"coordinates":[8.5877485275,46.6632766724],"type":"Point"}
}