{
  "type": "Feature",
  "properties": {
    "iso:country":"CH",
    "sg:address":"9545",
    "sg:city":"W\u00e4ngi",
    "sg:orig_category":"Interessenvertretungen",
    "sg:phone":"+41 52 378 16 08",
    "sg:postcode":"9545",
    "sg:province":"Thurgau",
    "wof:name":"Stiftung Ortsmuseum W\u00e4ngi",
    "wof:placetype":"venue"
},
  "geometry": {"coordinates":[8.9530849457,47.4967689514],"type":"Point"}
}