{
  "type": "Feature",
  "properties": {
    "iso:country":"CH",
    "sg:address":"3272",
    "sg:city":"Walperswil",
    "sg:orig_category":"Verwertung von Milch",
    "sg:postcode":"3272",
    "sg:province":"Bern",
    "wof:name":"K\u00e4sereigenossenschaft Ergeten-niederwil",
    "wof:placetype":"venue"
},
  "geometry": {"coordinates":[9.1631736755,47.4511528015],"type":"Point"}
}