{
  "type": "Feature",
  "properties": {
    "iso:country":"CH",
    "sg:address":"Schwimmbadstrasse 41",
    "sg:city":"Wettingen",
    "sg:orig_category":"Grosshandel mit Datenverarbeitungsger\u00e4ten Softwareentwicklung U beratung",
    "sg:phone":"+41 56 427 07 66",
    "sg:postcode":"5430",
    "sg:province":"Aargau",
    "wof:name":"Wings Information Systems, Schmid G.",
    "wof:placetype":"venue"
},
  "geometry": {"coordinates":[8.3128757477,47.4604644775],"type":"Point"}
}