{
  "type": "Feature",
  "properties": {
    "iso:country":"CH",
    "sg:address":"Dorfstrasse 1 6318 Walchwil. Postfach 179",
    "sg:city":"Walchwil",
    "sg:classifiers":[
        {
            "category":"Restaurant",
            "type":"Food & Drink"
        }
    ],
    "sg:phone":"+41 41 759 04 44",
    "sg:postcode":"6318",
    "sg:province":"Zug",
    "wof:name":"Restaurant Sternen",
    "wof:placetype":"venue"
},
  "geometry": {"coordinates":[8.5129327774,47.0997619629],"type":"Point"}
}