{
  "type": "Feature",
  "properties": {
    "iso:country":"CH",
    "sg:address":"Gottstattstrasse 24",
    "sg:city":"Biel/bienne",
    "sg:classifiers":[
        {
            "category":"Manufacturing",
            "subcategory":"Metals",
            "type":"Manufacturing & Wholesale Goods"
        }
    ],
    "sg:phone":"+41 32 931 66 31",
    "sg:postcode":"2504",
    "sg:province":"Bern",
    "sg:tags":[
        "aluminium"
    ],
    "wof:name":"C\u00f4ta - R. M. Egli",
    "wof:placetype":"venue"
},
  "geometry": {"coordinates":[6.732341,47.04422],"type":"Point"}
}