{
  "type": "Feature",
  "properties": {
    "iso:country":"CH",
    "sg:address":"Schaffhauserstrasse 223",
    "sg:city":"Z\u00fcrich",
    "sg:orig_category":"Sonstiger Grosshandel",
    "sg:phone":"+41 77673816",
    "sg:postcode":"8057",
    "sg:province":"Z\u00fcrich",
    "wof:name":"Vicker Investment & Trading Ag",
    "wof:placetype":"venue"
},
  "geometry": {"coordinates":[8.5459051132,47.4017715454],"type":"Point"}
}