{
  "type": "Feature",
  "properties": {
    "iso:country":"CH",
    "sg:address":"Marktgasse 1",
    "sg:city":"D\u00fcbendorf",
    "sg:orig_category":"Detailhandel mit medizinischen U orthop\u00e4dischen Artikeln Fachdetailhandel in Verkaufsr\u00e4umen",
    "sg:phone":"+41 12613919",
    "sg:postcode":"8600",
    "sg:province":"Z\u00fcrich",
    "wof:name":"Tamagni Ag H\u00f6rger\u00e4te",
    "wof:placetype":"venue"
},
  "geometry": {"coordinates":[8.6171855927,47.3977394104],"type":"Point"}
}