{
  "type": "Feature",
  "properties": {
    "iso:country":"CH",
    "sg:address":"Hauptstrasse 29",
    "sg:city":"Gerolfingen",
    "sg:orig_category":"Detailhandel mit Waren verschiedener Art, Hauptrichtung Nahrungsmittel Grosshandel mit Nahrungsmitte",
    "sg:phone":"+41 32 396 27 20",
    "sg:postcode":"2575",
    "sg:province":"Bern",
    "wof:name":"Bader Anita, Denner-satellit",
    "wof:placetype":"venue"
},
  "geometry": {"coordinates":[7.2002248764,47.0695991516],"type":"Point"}
}