{
  "type": "Feature",
  "properties": {
    "iso:country":"CH",
    "sg:address":"Industrieweg 14",
    "sg:city":"Rothrist",
    "sg:orig_category":"Pensionskassen",
    "sg:phone":"+41 55 284 52 44",
    "sg:postcode":"4852",
    "sg:province":"Aargau",
    "wof:name":"Personalvorsorgestiftung Der Rolba Ag",
    "wof:placetype":"venue"
},
  "geometry": {"coordinates":[8.7806167603,47.3282279968],"type":"Point"}
}