{
  "type": "Feature",
  "properties": {
    "iso:country":"CH",
    "sg:address":"Fin D'oie 101",
    "sg:city":"Bassecourt",
    "sg:orig_category":"G\u00fcterbef\u00f6rderung im Strassenverkehr",
    "sg:phone":"+41 32 426 50 67",
    "sg:postcode":"2854",
    "sg:province":"Jura",
    "wof:name":"Gervais Gisiger Transports",
    "wof:placetype":"venue"
},
  "geometry": {"coordinates":[7.2450299263,47.3370513916],"type":"Point"}
}