{
  "type": "Feature",
  "properties": {
    "iso:country":"CH",
    "sg:address":"Seestrasse 159 6442 Gersau. Postfach",
    "sg:city":"Gersau",
    "sg:orig_category":"HOTELS: MIT RESTAURANT Kongress- and Tagungshotels mit Restaurant",
    "sg:phone":"+41 41 828 22 66",
    "sg:postcode":"6442",
    "sg:province":"Schwyz",
    "wof:name":"Paradieshotel Rotschuo",
    "wof:placetype":"venue"
},
  "geometry": {"coordinates":[8.4872684479,46.9938278198],"type":"Point"}
}