{
  "type": "Feature",
  "properties": {
    "addr:full":"Rugenparkstrasse 7 Interlaken Bern 3800",
    "addr:housenumber":"7",
    "addr:postcode":"3800",
    "addr:street":"Rugenparkstrasse",
    "iso:country":"CH",
    "sg:address":"Rugenparkstrasse 7",
    "sg:city":"Interlaken",
    "sg:orig_category":"Architekturb\u00fcros",
    "sg:phone":"+41 33 822 26 13",
    "sg:postcode":"3800",
    "sg:province":"Bern",
    "wof:name":"Bruno N\u00fcssli Architekturb\u00fcro",
    "wof:placetype":"venue"
},
  "geometry": {"coordinates":[7.851543,46.680534],"type":"Point"}
}