{
  "type": "Feature",
  "properties": {
    "iso:country":"CH",
    "sg:address":"Tannholzstrasse 14 3052 Zollikofen. Postfach 537",
    "sg:city":"Zollikofen",
    "sg:orig_category":"Detailhandel mit Beleuchtungs U Haushaltsgegenst\u00e4nden Grosshandel mit elektrischen Haushaltsger\u00e4ten",
    "sg:phone":"+41 31 911 00 75",
    "sg:postcode":"3052",
    "sg:province":"Bern",
    "wof:name":"Moha Moderne Haushaltwaren Ag",
    "wof:placetype":"venue"
},
  "geometry": {"coordinates":[7.443858,47.003922],"type":"Point"}
}