{
  "type": "Feature",
  "properties": {
    "iso:country":"CH",
    "sg:address":"Avenue G\u00e9n\u00e9ral-guisan 30b",
    "sg:city":"Vevey",
    "sg:orig_category":"Handelsvermittlung U Grosshandel Handelsvermittlung U Grosshandel mit Automobilen",
    "sg:phone":"+41 21 923 62 60",
    "sg:postcode":"1800",
    "sg:province":"Vaud",
    "wof:name":"Linde Lansing Manutention Sa",
    "wof:placetype":"venue"
},
  "geometry": {"coordinates":[6.8392000198,46.4649543762],"type":"Point"}
}