{
  "type": "Feature",
  "properties": {
    "iso:country":"CH",
    "sg:address":"Riedweg 37 8049 Z\u00fcrich. Postfach",
    "sg:city":"Z\u00fcrich",
    "sg:orig_category":"Fachdetailhandel in Verkaufsr\u00e4umen",
    "sg:postcode":"8049",
    "sg:province":"Z\u00fcrich",
    "wof:name":"Meier Regula, Wald Und Flor",
    "wof:placetype":"venue"
},
  "geometry": {"coordinates":[8.4713258743,47.4155807495],"type":"Point"}
}