{
  "type": "Feature",
  "properties": {
    "iso:country":"CH",
    "sg:address":"Loretostrasse 59",
    "sg:city":"Lichtensteig",
    "sg:orig_category":"Unclassifiable Establishments",
    "sg:postcode":"9620",
    "sg:province":"St. Gallen",
    "wof:name":"Pflegeheim Loreto Gmbh",
    "wof:placetype":"venue"
},
  "geometry": {"coordinates":[9.08497715,47.3268089294],"type":"Point"}
}