{
  "type": "Feature",
  "properties": {
    "iso:country":"CH",
    "sg:address":"2103",
    "sg:city":"Noiraigue",
    "sg:orig_category":"Gemeindeverwaltungen",
    "sg:phone":"+41 32 855 13 54",
    "sg:postcode":"2103",
    "sg:province":"Neuch\u00e2tel",
    "wof:name":"Administration Communale De Brot-dessous",
    "wof:placetype":"venue"
},
  "geometry": {"coordinates":[6.7189311981,46.9565238953],"type":"Point"}
}