{
  "type": "Feature",
  "properties": {
    "iso:country":"CH",
    "sg:address":"Rue Des Sablons 32 2000 Neuenburg. Postfach",
    "sg:city":"Neuenburg",
    "sg:orig_category":"Ackerbau",
    "sg:postcode":"2000",
    "sg:province":"Neuch\u00e2tel",
    "wof:name":"Emergence, Soci\u00e9t\u00e9 \u00e0 Responsabilit\u00e9 \u00e0 Bonneville, F, Succursale De Neuch\u00e2tel",
    "wof:placetype":"venue"
},
  "geometry": {"coordinates":[6.931302,46.995678],"type":"Point"}
}