{
  "type": "Feature",
  "properties": {
    "iso:country":"CH",
    "sg:address":"Alte Landstrasse 9 3900 Gamsen. Postfach",
    "sg:city":"Glis",
    "sg:orig_category":"Instandhaltung U Reparatur von Automobilen",
    "sg:phone":"+41 62 291 32 65",
    "sg:postcode":"3902",
    "sg:province":"Valais",
    "wof:name":"Garage Orler Hans",
    "wof:placetype":"venue"
},
  "geometry": {"coordinates":[7.9768018723,47.3563079834],"type":"Point"}
}