{
  "type": "Feature",
  "properties": {
    "iso:country":"CH",
    "sg:address":"Dorfstrasse",
    "sg:city":"Oberhelfenschwil",
    "sg:orig_category":"Verlegen von Fliesen U Platten",
    "sg:phone":"+41 71 374 21 12",
    "sg:postcode":"9621",
    "sg:province":"St. Gallen",
    "wof:name":"Carlo Carigiet Keramische Wand-& Bodenbel\u00e4ge",
    "wof:placetype":"venue"
},
  "geometry": {"coordinates":[9.113240242,47.3541259766],"type":"Point"}
}