{
  "type": "Feature",
  "properties": {
    "iso:country":"CH",
    "sg:address":"Waldeggstrasse 81",
    "sg:city":"Winterthur",
    "sg:orig_category":"Bauschreinerei Innenausbau",
    "sg:phone":"+41 17611189",
    "sg:postcode":"8405",
    "sg:province":"Z\u00fcrich",
    "wof:name":"Kurt Schneebeli Schreinerei Innenausbau",
    "wof:placetype":"venue"
},
  "geometry": {"coordinates":[8.454231,47.277206],"type":"Point"}
}