{
  "type": "Feature",
  "properties": {
    "addr:full":"Granges Vaud 1523",
    "addr:postcode":"1523",
    "iso:country":"CH",
    "sg:city":"Granges",
    "sg:classifiers":[
        {
            "category":"Banks & Credit Unions",
            "subcategory":"Bank",
            "type":"Services"
        }
    ],
    "sg:phone":"+41 4137641145",
    "sg:postcode":"1523",
    "sg:province":"Vaud",
    "wof:name":"Credit Foncier Vaudois",
    "wof:placetype":"venue"
},
  "geometry": {"coordinates":[6.88752,46.76358],"type":"Point"}
}