{
  "type": "Feature",
  "properties": {
    "iso:country":"CH",
    "sg:address":"Thurgauerstrasse 39 8050 Z\u00fcrich. Postfach",
    "sg:city":"Z\u00fcrich",
    "sg:orig_category":"Grosshandel mit chemischen Erzeugnissen Grosshandel mit festen Brennstoffen U Mineral\u00f6lerzeugnissen",
    "sg:phone":"+41 13027979",
    "sg:postcode":"8050",
    "sg:province":"Z\u00fcrich",
    "wof:name":"Kl\u00fcber Lubrication Ag (schweiz) Chem.-techn. Produkte, Bes. Schmier, Trennstoffe; Handel, Import Usw",
    "wof:placetype":"venue"
},
  "geometry": {"coordinates":[8.5502967834,47.4145545959],"type":"Point"}
}