{
  "type": "Feature",
  "properties": {
    "iso:country":"CH",
    "sg:address":"Ch. Des Tamaris 7",
    "sg:city":"Chamb\u00e9sy",
    "sg:orig_category":"Unclassifiable Establishments",
    "sg:postcode":"1292",
    "sg:province":"Gen\u00e8ve",
    "wof:name":"Si Ch\u00eane-vert C",
    "wof:placetype":"venue"
},
  "geometry": {"coordinates":[6.1312379837,46.2432365417],"type":"Point"}
}