{
  "type": "Feature",
  "properties": {
    "iso:country":"CH",
    "sg:address":"B\u00f6hnirainstrasse 14",
    "sg:city":"Thalwil",
    "sg:orig_category":"Werbevermittlung",
    "sg:phone":"+41 32 853 97 72",
    "sg:postcode":"8800",
    "sg:province":"Z\u00fcrich",
    "wof:name":"Mario D'incau Mdi Diffusions",
    "wof:placetype":"venue"
},
  "geometry": {"coordinates":[6.8718662262,47.0459213257],"type":"Point"}
}