{
  "type": "Feature",
  "properties": {
    "iso:country":"CH",
    "sg:address":"5234",
    "sg:city":"Villigen",
    "sg:orig_category":"Sportvereine Turnen",
    "sg:postcode":"5234",
    "sg:province":"Aargau",
    "wof:name":"Turnverein",
    "wof:placetype":"venue"
},
  "geometry": {"coordinates":[8.2110204697,47.5044708252],"type":"Point"}
}