{
  "type": "Feature",
  "properties": {
    "iso:country":"CH",
    "sg:address":"Residenza Belvedere 12",
    "sg:city":"Torricella",
    "sg:orig_category":"Sanit\u00e4rinstallation",
    "sg:phone":"+41 91 945 42 12",
    "sg:postcode":"6808",
    "sg:province":"Ticino",
    "wof:name":"Cesare Andreani Impianti Sanitari",
    "wof:placetype":"venue"
},
  "geometry": {"coordinates":[8.9221410751,46.0651702881],"type":"Point"}
}