{
  "type": "Feature",
  "properties": {
    "iso:country":"CH",
    "sg:address":"N\u00f6llenstrasse 15a",
    "sg:city":"Widnau",
    "sg:orig_category":"Unclassifiable Establishments",
    "sg:postcode":"9443",
    "sg:province":"St. Gallen",
    "wof:name":"Roma Steakhouse No. 1 Gmbh",
    "wof:placetype":"venue"
},
  "geometry": {"coordinates":[8.7871055603,47.329372406],"type":"Point"}
}