{
  "type": "Feature",
  "properties": {
    "iso:country":"CH",
    "sg:address":"Avenue De Luserna 2",
    "sg:city":"Gen\u00e8ve",
    "sg:orig_category":"Physiotherapie",
    "sg:phone":"+41 22 345 05 82",
    "sg:postcode":"1203",
    "sg:province":"Gen\u00e8ve",
    "wof:name":"Physioth\u00e9rapie Luserna",
    "wof:placetype":"venue"
},
  "geometry": {"coordinates":[6.1277937889,46.212436676],"type":"Point"}
}