{
  "type": "Feature",
  "properties": {
    "iso:country":"CH",
    "sg:address":"Venedig-strasse 34",
    "sg:city":"Basel",
    "sg:orig_category":"Installation von Heizungs, L\u00fcftungs U Klimaanlagen Sanit\u00e4r U Heizungsinstallation",
    "sg:phone":"+41 32 727 61 11",
    "sg:postcode":"4053",
    "sg:province":"Basel-Stadt",
    "wof:name":"Calorie Holding Sa",
    "wof:placetype":"venue"
},
  "geometry": {"coordinates":[6.9229950905,46.9919662476],"type":"Point"}
}