{
  "type": "Feature",
  "properties": {
    "iso:country":"CH",
    "sg:address":"4222",
    "sg:city":"Zwingen",
    "sg:orig_category":"Unclassifiable Establishments",
    "sg:postcode":"4222",
    "sg:province":"Basel-Landschaft",
    "wof:name":"Architekturb\u00fcro Sutter",
    "wof:placetype":"venue"
},
  "geometry": {"coordinates":[7.626625061,46.7320594788],"type":"Point"}
}