{
  "type": "Feature",
  "properties": {
    "iso:country":"CH",
    "sg:address":"Klingelbergstrasse 70",
    "sg:city":"Basel",
    "sg:orig_category":"Datenverarbeitungsdienste",
    "sg:phone":"+41 61 267 22 73",
    "sg:postcode":"4056",
    "sg:province":"Basel-Stadt",
    "wof:name":"Universit\u00e4tsrechenzentrum",
    "wof:placetype":"venue"
},
  "geometry": {"coordinates":[7.579777,47.563732],"type":"Point"}
}