{
  "type": "Feature",
  "properties": {
    "iso:country":"CH",
    "sg:address":"Route De Suisse 125",
    "sg:city":"Versoix",
    "sg:orig_category":"Schiffsbau ohne Boots U Yachtbau",
    "sg:phone":"+41 22 755 44 23",
    "sg:postcode":"1290",
    "sg:province":"Gen\u00e8ve",
    "wof:name":"Diffusion Service Vsb S\u00e0rl",
    "wof:placetype":"venue"
},
  "geometry": {"coordinates":[6.1655349731,46.2887268066],"type":"Point"}
}