{
  "type": "Feature",
  "properties": {
    "iso:country":"CH",
    "sg:address":"Bahnhofstrasse 10",
    "sg:city":"Aarau",
    "sg:orig_category":"Rechtsberatung",
    "sg:phone":"+41 62 824 46 24",
    "sg:postcode":"5000",
    "sg:province":"Aargau",
    "wof:name":"Baumann Andreas, Dr. Iur. F\u00fcrsprecher Und Notar",
    "wof:placetype":"venue"
},
  "geometry": {"coordinates":[8.04616642,47.3906288147],"type":"Point"}
}