{
  "type": "Feature",
  "properties": {
    "iso:country":"CH",
    "sg:address":"Kirchweg 24",
    "sg:city":"Oberehrendingen",
    "sg:orig_category":"Elektroinstallation",
    "sg:phone":"+41 56 222 80 33",
    "sg:postcode":"5422",
    "wof:name":"Electrosafe Gmbh",
    "wof:placetype":"venue"
},
  "geometry": {"coordinates":[8.3444871902,47.4986152649],"type":"Point"}
}