{
  "type": "Feature",
  "properties": {
    "iso:country":"CH",
    "sg:address":"Rychgass 1 Basadingen 8254 Basadingen. Postfach",
    "sg:city":"Basadingen",
    "sg:classifiers":[
        {
            "category":"Mining & Drilling",
            "type":"Manufacturing & Wholesale Goods"
        }
    ],
    "sg:phone":"+41 71 634 80 99",
    "sg:postcode":"8254",
    "sg:province":"Thurgau",
    "sg:tags":[
        "test",
        "sondierbohrungen",
        "u"
    ],
    "wof:name":"Fmb B\u00fcrglen Ag",
    "wof:placetype":"venue"
},
  "geometry": {"coordinates":[9.1504201889,47.5487518311],"type":"Point"}
}