{
  "type": "Feature",
  "properties": {
    "iso:country":"CH",
    "sg:address":"Schindelhofstrasse 2",
    "sg:city":"R\u00f6schenz",
    "sg:classifiers":[
        {
            "category":"Banks & Credit Unions",
            "subcategory":"Bank",
            "type":"Services"
        }
    ],
    "sg:phone":"+41 61 761 65 45",
    "sg:postcode":"4244",
    "sg:province":"Basel-Landschaft",
    "wof:name":"Schweiz. Mobiliar",
    "wof:placetype":"venue"
},
  "geometry": {"coordinates":[7.475048,47.424515],"type":"Point"}
}