{
  "type": "Feature",
  "properties": {
    "iso:country":"CH",
    "sg:address":"Breitenbachstrasse 31 4242 Laufen. Postfach",
    "sg:city":"Laufen",
    "sg:orig_category":"Herstellung von sonstigen elektrischen Ausr\u00fcstungen",
    "sg:postcode":"4242",
    "sg:province":"Basel-Landschaft",
    "wof:name":"Henz + Linz Dymac Electronics",
    "wof:placetype":"venue"
},
  "geometry": {"coordinates":[7.5044341087,47.4189529419],"type":"Point"}
}