{
  "type": "Feature",
  "properties": {
    "iso:country":"CH",
    "sg:address":"Maison Silo",
    "sg:city":"Echichens",
    "sg:orig_category":"Interessenvertretungen Wohnheime",
    "sg:phone":"+41 21 804 08 11",
    "sg:postcode":"1112",
    "sg:province":"Vaud",
    "wof:name":"Fondation Silo",
    "wof:placetype":"venue"
},
  "geometry": {"coordinates":[6.4977197647,46.5260047913],"type":"Point"}
}