{
  "type": "Feature",
  "properties": {
    "iso:country":"CH",
    "sg:address":"Dorfstrasse 1",
    "sg:city":"Engelberg",
    "sg:orig_category":"Verwaltung von Immobilien Wirtschaftspr\u00fcfung, Steuerberatung U Treuhand",
    "sg:phone":"+41 79 333 48 56",
    "sg:postcode":"6390",
    "sg:province":"Obwalden",
    "wof:name":"Gody Amrhein",
    "wof:placetype":"venue"
},
  "geometry": {"coordinates":[8.4079837799,46.8208389282],"type":"Point"}
}