{
  "type": "Feature",
  "properties": {
    "iso:country":"CH",
    "sg:address":"Bernstrasse 81",
    "sg:city":"Zollikofen",
    "sg:orig_category":"Instandhaltung U Reparatur von Automobilen",
    "sg:postcode":"3052",
    "sg:province":"Bern",
    "wof:name":"Gleam Car S\u00e0rl Entreprise De Nettoyage De V\u00e9hicules Etc",
    "wof:placetype":"venue"
},
  "geometry": {"coordinates":[6.1414251328,46.1833114624],"type":"Point"}
}