{
  "type": "Feature",
  "properties": {
    "iso:country":"CH",
    "sg:address":"Wasserwerkstrasse 125 8037 Z\u00fcrich. Postfach",
    "sg:city":"Z\u00fcrich",
    "sg:orig_category":"Betrieb U technische Hilfsdienste des Kultur U Unterhaltungswesens",
    "sg:postcode":"8037",
    "sg:province":"Z\u00fcrich",
    "wof:name":"Tibetan Culture Promotion Tcp Gmbh",
    "wof:placetype":"venue"
},
  "geometry": {"coordinates":[8.530756,47.388695],"type":"Point"}
}