{
  "type": "Feature",
  "properties": {
    "addr:full":"M\u00fchledorfstrasse 1 Bern Bern 3018",
    "addr:housenumber":"1",
    "addr:postcode":"3018",
    "addr:street":"Muehledorfstrasse",
    "iso:country":"CH",
    "sg:address":"M\u00fchledorfstrasse 1",
    "sg:city":"Bern",
    "sg:orig_category":"Arztpraxen",
    "sg:phone":"+41 31 992 17 56",
    "sg:postcode":"3018",
    "sg:province":"Bern",
    "wof:name":"Dr.med. Evelyne D\u00e9costerd Spezial\u00e4rztin Fmh",
    "wof:placetype":"venue"
},
  "geometry": {"coordinates":[7.391687,46.945564],"type":"Point"}
}