{
  "type": "Feature",
  "properties": {
    "iso:country":"CH",
    "sg:address":"Br\u00fcggfeld",
    "sg:city":"Ried B. Kerzers",
    "sg:orig_category":"Dienstleistungen, Telekommunikation",
    "sg:postcode":"3216",
    "sg:province":"Fribourg",
    "wof:name":"Weiss Appetitio Ag",
    "wof:placetype":"venue"
},
  "geometry": {"coordinates":[7.189259,46.966087],"type":"Point"}
}