{
  "type": "Feature",
  "properties": {
    "iso:country":"CH",
    "sg:address":"Reller Avenue 44 1804 Corsier-sur-vevey. Postfach",
    "sg:city":"Corsier-sur-vevey",
    "sg:orig_category":"Instandhaltung U Reparatur von Automobilen",
    "sg:postcode":"1804",
    "sg:province":"Vaud",
    "wof:name":"Garage Tannenberg",
    "wof:placetype":"venue"
},
  "geometry": {"coordinates":[-80.06429290769999,41.5731124878],"type":"Point"}
}