{
  "type": "Feature",
  "properties": {
    "iso:country":"CH",
    "sg:address":"Heinib\u00fchlstrasse 32",
    "sg:city":"Lohn-ammannsegg",
    "sg:classifiers":[
        {
            "category":"Autos & Motor Vehicles",
            "subcategory":"Auto Supplies",
            "type":"Retail Goods"
        }
    ],
    "sg:phone":"+41 32 677 16 06",
    "sg:postcode":"4573",
    "sg:province":"Solothurn",
    "sg:tags":[
        "automobile",
        "accessory"
    ],
    "wof:name":"Lafim Ag",
    "wof:placetype":"venue"
},
  "geometry": {"coordinates":[7.540583,47.174618],"type":"Point"}
}