{
  "type": "Feature",
  "properties": {
    "iso:country":"CH",
    "sg:address":"Creusets Rue Des 5",
    "sg:city":"Sion",
    "sg:orig_category":"Druck ohne Zeitungsdruck",
    "sg:phone":"+41 17511887",
    "sg:postcode":"1950",
    "sg:province":"Valais",
    "wof:name":"Perfect Print Service H\u00e4nsli Gerhard",
    "wof:placetype":"venue"
},
  "geometry": {"coordinates":[8.4380197525,47.4168624878],"type":"Point"}
}