{
  "type": "Feature",
  "properties": {
    "iso:country":"CH",
    "sg:address":"Schwerzenbachstrasse 43",
    "sg:city":"F\u00e4llanden",
    "sg:orig_category":"Grosshandel mit keramischen Erzeugnissen, Glaswaren U Reinigungsmitteln Herstellung von sonstigen Pr",
    "sg:phone":"+41 18064040",
    "sg:postcode":"8117",
    "sg:province":"Z\u00fcrich",
    "wof:name":"F\u00e4llander Glas Ag",
    "wof:placetype":"venue"
},
  "geometry": {"coordinates":[8.6414299011,47.373249054],"type":"Point"}
}