{
  "type": "Feature",
  "properties": {
    "iso:country":"CH",
    "sg:address":"Dorfstrasse 21",
    "sg:city":"Brunnadern",
    "sg:orig_category":"Detailhandel mit Waren verschiedener Art, Hauptrichtung Nahrungsmittel Grosshandel mit Nahrungsmitte",
    "sg:phone":"+41 71 374 13 25",
    "sg:postcode":"9125",
    "sg:province":"St. Gallen",
    "wof:name":"Sch\u00f6b-broger Gmbh",
    "wof:placetype":"venue"
},
  "geometry": {"coordinates":[9.1315164566,47.3355407715],"type":"Point"}
}