{
  "type": "Feature",
  "properties": {
    "iso:country":"CH",
    "sg:address":"1982",
    "sg:city":"Euseigne",
    "sg:orig_category":"Organisationen des Gesundheitswesen",
    "sg:phone":"+41 56 664 18 47",
    "sg:postcode":"1982",
    "sg:province":"Valais",
    "wof:name":"Beratungsstelle Der Aarg. Frauenliga Gegen Tuberkulose",
    "wof:placetype":"venue"
},
  "geometry": {"coordinates":[8.3174819946,47.2825775146],"type":"Point"}
}