{
  "type": "Feature",
  "properties": {
    "iso:country":"CH",
    "sg:address":"Sch\u00f6naustrasse 75 4058 Basel. Postfach 4",
    "sg:city":"Basel",
    "sg:orig_category":"Verlagsgewerbe Zeitungsverlag",
    "sg:phone":"+41 61 692 67 38",
    "sg:postcode":"4021",
    "wof:name":"Medien Verlag Chronopress Fricker U.",
    "wof:placetype":"venue"
},
  "geometry": {"coordinates":[7.6030511856,47.5685501099],"type":"Point"}
}