{
  "type": "Feature",
  "properties": {
    "iso:country":"CH",
    "sg:address":"Lindenhofweg 3",
    "sg:city":"Jona",
    "sg:orig_category":"Vereine Harmonika and Akkordeon",
    "sg:postcode":"8645",
    "sg:province":"St. Gallen",
    "wof:name":"Handharmonika-club",
    "wof:placetype":"venue"
},
  "geometry": {"coordinates":[8.821852684,47.2407226562],"type":"Point"}
}