{
  "type": "Feature",
  "properties": {
    "iso:country":"CH",
    "sg:address":"Vordere Hauptgasse 55",
    "sg:city":"Zofingen",
    "sg:orig_category":"Detailhandel mit Uhren U Schmuck Fachdetailhandel in Verkaufsr\u00e4umen",
    "sg:phone":"+41 62 751 33 77",
    "sg:postcode":"4800",
    "sg:province":"Aargau",
    "wof:name":"Stettler Uhren Und Schmuck",
    "wof:placetype":"venue"
},
  "geometry": {"coordinates":[7.945335865,47.2880439758],"type":"Point"}
}