{
  "type": "Feature",
  "properties": {
    "iso:country":"CH",
    "sg:address":"M\u00fchlebachstrasse 44 8008 Z\u00fcrich. Postfach",
    "sg:city":"Z\u00fcrich",
    "sg:orig_category":"Architektur U Ingenieurb\u00fcros Unternehmensberatung",
    "sg:phone":"+41 12669060",
    "sg:postcode":"8034",
    "sg:province":"Z\u00fcrich",
    "wof:name":"Ipetece Orient Technical Consulting Gmbh",
    "wof:placetype":"venue"
},
  "geometry": {"coordinates":[8.551109,47.364071],"type":"Point"}
}