{
  "type": "Feature",
  "properties": {
    "iso:country":"CH",
    "sg:address":"Lambergstrasse 6",
    "sg:city":"Uster",
    "sg:orig_category":"Vereine Frauen Vereine Gesang",
    "sg:phone":"+41 19412957",
    "sg:postcode":"8610",
    "sg:province":"Z\u00fcrich",
    "wof:name":"Frauenchor Kempten",
    "wof:placetype":"venue"
},
  "geometry": {"coordinates":[8.7355308533,47.3419380188],"type":"Point"}
}