{
  "type": "Feature",
  "properties": {
    "iso:country":"CH",
    "sg:address":"Niederdorf",
    "sg:city":"Eriswil",
    "sg:orig_category":"Landwirtschaftliche Genossenschaften",
    "sg:phone":"+41 71 642 15 44",
    "sg:postcode":"4952",
    "sg:province":"Bern",
    "wof:name":"Landi Leimbach-andwil & Umgebung",
    "wof:placetype":"venue"
},
  "geometry": {"coordinates":[9.1813001633,47.5617713928],"type":"Point"}
}