{
  "type": "Feature",
  "properties": {
    "iso:country":"CH",
    "sg:address":"Axenstrasse 15 6440 Brunnen. Postfach 164",
    "sg:city":"Brunnen",
    "sg:classifiers":[
        {
            "category":"Travel",
            "subcategory":"Hotels & Motels",
            "type":"Entertainment"
        }
    ],
    "sg:phone":"+41 41 820 53 69",
    "sg:postcode":"6440",
    "sg:province":"Schwyz",
    "sg:tags":[
        "hotels",
        "mit",
        "restaurant"
    ],
    "wof:name":"Hotel Eden Albert Janser Jun.",
    "wof:placetype":"venue"
},
  "geometry": {"coordinates":[8.6079721451,46.9930992126],"type":"Point"}
}