{
  "type": "Feature",
  "properties": {
    "iso:country":"CH",
    "sg:address":"Gugelmattstrasse 35a",
    "sg:city":"Widen",
    "sg:orig_category":"Detailhandel mit B\u00fcchern, Zeitungen, Schreib U Papeteriewaren",
    "sg:phone":"+41 56 631 12 66",
    "sg:postcode":"8967",
    "sg:province":"Aargau",
    "wof:name":"Handelsbetrieb Mehmann",
    "wof:placetype":"venue"
},
  "geometry": {"coordinates":[8.359604,47.370148],"type":"Point"}
}