{
  "type": "Feature",
  "properties": {
    "iso:country":"CH",
    "sg:address":"Corso San Gottardo 32",
    "sg:city":"Chiasso",
    "sg:orig_category":"Frachtumschlag U Lagerung G\u00fcterbef\u00f6rderung im Strassenverkehr",
    "sg:phone":"+41 91 682 99 29",
    "sg:postcode":"6830",
    "sg:province":"Ticino",
    "wof:name":"Gts Multi-logistics Sa",
    "wof:placetype":"venue"
},
  "geometry": {"coordinates":[9.0298786163,45.8341331482],"type":"Point"}
}