{
  "type": "Feature",
  "properties": {
    "iso:country":"CH",
    "sg:address":"Via Collina 15 6816 Bissone Casella Postale 77",
    "sg:city":"Bissone",
    "sg:orig_category":"Allgemeiner Hoch U Tiefbau Allgemeiner Hochbau",
    "sg:phone":"+41 55 644 22 72",
    "sg:postcode":"6816",
    "sg:province":"Ticino",
    "wof:name":"Ricetti Ag, Bauunternehmung",
    "wof:placetype":"venue"
},
  "geometry": {"coordinates":[9.05763,46.982079],"type":"Point"}
}