{
  "type": "Feature",
  "properties": {
    "iso:country":"CH",
    "sg:address":"Kaspar-koppstrasse 94",
    "sg:city":"Ebikon",
    "sg:orig_category":"Psychotherapie",
    "sg:phone":"+41 41 420 00 42",
    "sg:postcode":"6030",
    "sg:province":"Luzern",
    "wof:name":"Karl B\u00fcrgi Psychotherapie",
    "wof:placetype":"venue"
},
  "geometry": {"coordinates":[8.3186187744,47.070098877],"type":"Point"}
}