{
  "type": "Feature",
  "properties": {
    "iso:country":"CH",
    "sg:address":"Boulevard De Saint-georges 42",
    "sg:city":"Gen\u00e8ve",
    "sg:classifiers":[
        {
            "category":"Restaurant",
            "type":"Food & Drink"
        }
    ],
    "sg:phone":"+41 22 321 00 35",
    "sg:postcode":"1205",
    "sg:province":"Gen\u00e8ve",
    "wof:name":"Restaurant Gallay",
    "wof:placetype":"venue"
},
  "geometry": {"coordinates":[6.1349921227,46.201171875],"type":"Point"}
}