{
  "type": "Feature",
  "properties": {
    "iso:country":"CH",
    "sg:address":"Rathausgasse 3 4500 Solothurn. Postfach 943",
    "sg:city":"Solothurn",
    "sg:orig_category":"Politische Parteien SP",
    "sg:phone":"+41 41 870 50 65",
    "sg:postcode":"4502",
    "sg:province":"Solothurn",
    "wof:name":"Sp Des Kantons Uri",
    "wof:placetype":"venue"
},
  "geometry": {"coordinates":[8.6473083496,46.8770027161],"type":"Point"}
}