{
  "type": "Feature",
  "properties": {
    "iso:country":"CH",
    "sg:address":"1564",
    "sg:city":"Domdidier",
    "sg:orig_category":"Bezirks, Sekundar, Realschulen, Oberstufe der Primarschulen",
    "sg:postcode":"1564",
    "sg:province":"Fribourg",
    "wof:name":"Ecole Secondaire",
    "wof:placetype":"venue"
},
  "geometry": {"coordinates":[7.015135,46.865307],"type":"Point"}
}