{
  "type": "Feature",
  "properties": {
    "iso:country":"CH",
    "sg:address":"Rue Du M\u00f4le 31",
    "sg:city":"Gen\u00e8ve",
    "sg:orig_category":"Detailhandel mit elektrischen Haushalts-,Radio U Fernsehger\u00e4ten sowie Musikinstrumenten Grosshandel ",
    "sg:phone":"+41 22 731 21 09",
    "sg:postcode":"1201",
    "sg:province":"Gen\u00e8ve",
    "wof:name":"Machinor, Campanini Enrico",
    "wof:placetype":"venue"
},
  "geometry": {"coordinates":[6.1459307671,46.2133255005],"type":"Point"}
}