{
  "type": "Feature",
  "properties": {
    "iso:country":"CH",
    "sg:address":"Spiegelstrasse 8",
    "sg:city":"K\u00f6niz",
    "sg:orig_category":"Herstellung von konfektionierten Textilwaren ohne Bekleidung",
    "sg:phone":"+41 31 926 62 62",
    "sg:postcode":"3098",
    "sg:province":"Bern",
    "wof:name":"Tschanz Ag Sonnen Und Wetterschutz",
    "wof:placetype":"venue"
},
  "geometry": {"coordinates":[7.4257330894,46.9211387634],"type":"Point"}
}