{
  "type": "Feature",
  "properties": {
    "iso:country":"CH",
    "sg:address":"Chemin Des Roches 3 1010 Lausanne. Postfach",
    "sg:city":"Lausanne",
    "sg:orig_category":"Schreib U \u00dcbersetzungsb\u00fcros",
    "sg:phone":"+41 21 654 40 50",
    "sg:postcode":"1010",
    "sg:province":"Vaud",
    "wof:name":"Cb Service Sa",
    "wof:placetype":"venue"
},
  "geometry": {"coordinates":[6.6552519798,46.5417137146],"type":"Point"}
}