{
  "type": "Feature",
  "properties": {
    "iso:country":"CH",
    "sg:address":"L\u00e9cheretta Rue 6a 1630 Bulle Case Postale 537",
    "sg:city":"Bulle",
    "sg:orig_category":"G\u00fcterbef\u00f6rderung im Strassenverkehr",
    "sg:phone":"+41 81 756 65 34",
    "sg:postcode":"1630",
    "sg:province":"Fribourg",
    "wof:name":"Renaldo Moser Ag Umz\u00fcge & Transporte",
    "wof:placetype":"venue"
},
  "geometry": {"coordinates":[9.4657430649,47.1689605713],"type":"Point"}
}