{
  "type": "Feature",
  "properties": {
    "iso:country":"CH",
    "sg:address":"Sch\u00fctzenweg 10",
    "sg:city":"Laufen",
    "sg:orig_category":"Gartenbau",
    "sg:phone":"+41 61 761 67 76",
    "sg:postcode":"4242",
    "sg:province":"Basel-Landschaft",
    "wof:name":"Peter H\u00e4nggi, Gartenbau",
    "wof:placetype":"venue"
},
  "geometry": {"coordinates":[7.498114109,47.4175605774],"type":"Point"}
}