{
  "type": "Feature",
  "properties": {
    "iso:country":"CH",
    "sg:address":"Burgstrasse 120",
    "sg:city":"Winterthur",
    "sg:orig_category":"Malerei",
    "sg:phone":"+41 79 421 24 00",
    "sg:postcode":"8408",
    "sg:province":"Z\u00fcrich",
    "wof:name":"Peter Bruckmayer Malergesch\u00e4ft",
    "wof:placetype":"venue"
},
  "geometry": {"coordinates":[8.6978616714,47.5068778992],"type":"Point"}
}