{
  "type": "Feature",
  "properties": {
    "iso:country":"CH",
    "sg:address":"Weiherstrasse 12",
    "sg:city":"Kreuzlingen",
    "sg:orig_category":"Handels-H\u00e4user U Gesellschaften",
    "sg:phone":"+41 71 672 84 69",
    "sg:postcode":"8280",
    "sg:province":"Thurgau",
    "wof:name":"Handelsvertretung Frey Erika",
    "wof:placetype":"venue"
},
  "geometry": {"coordinates":[9.164563179,47.6514511108],"type":"Point"}
}