{
  "type": "Feature",
  "properties": {
    "iso:country":"CH",
    "sg:address":"2923",
    "sg:city":"Courtema\u00eeche",
    "sg:orig_category":"Herstellung von Uhren",
    "sg:postcode":"2923",
    "sg:province":"Jura",
    "wof:name":"Li\u00e8vre Alex",
    "wof:placetype":"venue"
},
  "geometry": {"coordinates":[7.0438098907,47.4589500427],"type":"Point"}
}