{
  "type": "Feature",
  "properties": {
    "iso:country":"CH",
    "sg:address":"Gare Avenue De La 24 1870 Monthey. Postfach",
    "sg:city":"Monthey",
    "sg:orig_category":"Interessenvertretungen",
    "sg:postcode":"1870",
    "sg:province":"Valais",
    "wof:name":"La Maison Internationale Des Talents",
    "wof:placetype":"venue"
},
  "geometry": {"coordinates":[6.9471468925,46.2516288757],"type":"Point"}
}