{
  "type": "Feature",
  "properties": {
    "iso:country":"CH",
    "sg:address":"Lindenplatz 11",
    "sg:city":"Winterthur",
    "sg:orig_category":"Detailhandel mit Damenbekleidung",
    "sg:phone":"+41 52 222 69 89",
    "sg:postcode":"8408",
    "sg:province":"Z\u00fcrich",
    "wof:name":"Heidi Montandon 42 Plus Die Grosse Mode",
    "wof:placetype":"venue"
},
  "geometry": {"coordinates":[8.693428,47.511173],"type":"Point"}
}