{
  "type": "Feature",
  "properties": {
    "iso:country":"CH",
    "sg:address":"Kohlenberg 3",
    "sg:city":"Basel",
    "sg:orig_category":"P\u00e9dicure",
    "sg:phone":"+41 61 281 66 40",
    "sg:postcode":"4051",
    "sg:province":"Basel-Stadt",
    "wof:name":"Silvia Gschwend P\u00e9dicure",
    "wof:placetype":"venue"
},
  "geometry": {"coordinates":[7.5889401436,47.554107666],"type":"Point"}
}