{
  "type": "Feature",
  "properties": {
    "iso:country":"CH",
    "sg:address":"Goldbachweg 5",
    "sg:city":"Flawil",
    "sg:orig_category":"Grosshandel mit Software Wirtschaftspr\u00fcfung, Steuerberatung U Treuhand",
    "sg:phone":"+41 71 393 43 26",
    "sg:postcode":"9230",
    "sg:province":"St. Gallen",
    "wof:name":"Heer & Oggenfuss Gmbh",
    "wof:placetype":"venue"
},
  "geometry": {"coordinates":[9.1876478195,47.4118309021],"type":"Point"}
}