{
  "type": "Feature",
  "properties": {
    "iso:country":"CH",
    "sg:address":"Dorf 75",
    "sg:city":"Walzenhausen",
    "sg:orig_category":"Detailhandel mit Fleisch U Fleischwaren",
    "sg:phone":"+41 71 888 15 25",
    "sg:postcode":"9428",
    "sg:province":"Appenzell Ausserrhoden",
    "wof:name":"Z\u00fcberb\u00fchler Metzgerei",
    "wof:placetype":"venue"
},
  "geometry": {"coordinates":[9.6006317139,47.4505386353],"type":"Point"}
}