{
  "type": "Feature",
  "properties": {
    "iso:country":"CH",
    "sg:address":"Eisengasse 9",
    "sg:city":"Basel",
    "sg:orig_category":"Detailhandel mit Sportartikeln",
    "sg:phone":"+41 61 261 88 52",
    "sg:postcode":"4051",
    "sg:province":"Basel-Stadt",
    "wof:name":"Downtown-surfshop Basel, Rohr + Co Sportger\u00e4te, Freitzeitbekleidung; Handel",
    "wof:placetype":"venue"
},
  "geometry": {"coordinates":[7.5882811546,47.5592498779],"type":"Point"}
}