{
  "type": "Feature",
  "properties": {
    "iso:country":"CH",
    "sg:address":"R\u00fcschen 18",
    "sg:city":"Speicher",
    "sg:orig_category":"Wohnheime",
    "sg:phone":"+41 71 344 23 23",
    "sg:postcode":"9042",
    "sg:province":"Appenzell Ausserrhoden",
    "wof:name":"Heimst\u00e4tte Libanon",
    "wof:placetype":"venue"
},
  "geometry": {"coordinates":[9.4391412735,47.4115982056],"type":"Point"}
}