{
  "type": "Feature",
  "properties": {
    "iso:country":"CH",
    "sg:address":"Tramstrasse 2",
    "sg:city":"M\u00e4nnedorf",
    "sg:orig_category":"Mechanik Mechanische Werkst\u00e4tten",
    "sg:phone":"+41 19211626",
    "sg:postcode":"8708",
    "sg:province":"Z\u00fcrich",
    "wof:name":"R & L Mechanik R\u00fctsch & Lutz",
    "wof:placetype":"venue"
},
  "geometry": {"coordinates":[8.6863603592,47.263130188],"type":"Point"}
}