{
  "type": "Feature",
  "properties": {
    "iso:country":"CH",
    "sg:address":"Rue De Chantepoulet 1-3",
    "sg:city":"Gen\u00e8ve",
    "sg:orig_category":"Autoreiseunternehmen Reiseb\u00fcros",
    "sg:phone":"+41 22 715 04 61",
    "sg:postcode":"1201",
    "sg:province":"Gen\u00e8ve",
    "wof:name":"Gen\u00e8ve Tours Autocars",
    "wof:placetype":"venue"
},
  "geometry": {"coordinates":[6.145472,46.207935],"type":"Point"}
}