{
  "type": "Feature",
  "properties": {
    "iso:country":"CH",
    "sg:address":"Route Du Stand 45",
    "sg:city":"Nyon",
    "sg:classifiers":[
        {
            "category":"Manufacturing",
            "subcategory":"Soap",
            "type":"Manufacturing & Wholesale Goods"
        }
    ],
    "sg:phone":"+41 22 361 41 36",
    "sg:postcode":"1260",
    "sg:province":"Vaud",
    "sg:tags":[
        "industrial"
    ],
    "wof:name":"Sany - Ddv",
    "wof:placetype":"venue"
},
  "geometry": {"coordinates":[6.2188668251,46.3816986084],"type":"Point"}
}