{
  "type": "Feature",
  "properties": {
    "iso:country":"CH",
    "sg:address":"Br\u00fcnigstrasse 42 6074 Giswil. Postfach 141",
    "sg:city":"Giswil",
    "sg:orig_category":"Bauingenieurb\u00fcros Heizung L\u00fcftung Klima",
    "sg:phone":"+41 41 660 61 02",
    "sg:postcode":"6074",
    "sg:province":"Obwalden",
    "wof:name":"Peter Berchtold Ingenieurb\u00fcro",
    "wof:placetype":"venue"
},
  "geometry": {"coordinates":[8.186499,46.837479],"type":"Point"}
}