{
  "type": "Feature",
  "properties": {
    "iso:country":"CH",
    "sg:address":"Rue St-martin 14",
    "sg:city":"Porrentruy",
    "sg:orig_category":"Vereine Radio, Film and Foto",
    "sg:phone":"+41 32 466 47 76",
    "sg:postcode":"2900",
    "sg:province":"Jura",
    "wof:name":"Cin\u00e9-amateurs Ajoulots Club 88",
    "wof:placetype":"venue"
},
  "geometry": {"coordinates":[7.0670700073,47.4108695984],"type":"Point"}
}