{
  "type": "Feature",
  "properties": {
    "iso:country":"CH",
    "sg:address":"Route De Vissigen 20",
    "sg:city":"Sion",
    "sg:orig_category":"Allgemeiner Hoch U Tiefbau Test U Sondierbohrungen",
    "sg:phone":"+41 19841312",
    "sg:postcode":"1950",
    "sg:province":"Valais",
    "wof:name":"Cpk Bautechnik Ag, Zweigniederlassung Egg B. Z\u00fcrich",
    "wof:placetype":"venue"
},
  "geometry": {"coordinates":[8.690055,47.300556],"type":"Point"}
}