{
  "type": "Feature",
  "properties": {
    "iso:country":"CH",
    "sg:address":"Besenb\u00fcrenstrasse 23",
    "sg:city":"B\u00fcnzen",
    "sg:orig_category":"Sanit\u00e4rinstallation",
    "sg:phone":"+41 56 666 11 52",
    "sg:postcode":"5624",
    "sg:province":"Aargau",
    "wof:name":"Jean Roth Sanit\u00e4r-installationen",
    "wof:placetype":"venue"
},
  "geometry": {"coordinates":[8.3298530579,47.3111038208],"type":"Point"}
}