{
  "type": "Feature",
  "properties": {
    "iso:country":"CH",
    "sg:address":"M\u00fclistrasse 4",
    "sg:city":"Fehraltorf",
    "sg:orig_category":"Herstellung von nachrichtentechnischen Ger\u00e4ten U Einrichtungen",
    "sg:phone":"+41 19550222",
    "sg:postcode":"8320",
    "sg:province":"Z\u00fcrich",
    "wof:name":"Commend Ag",
    "wof:placetype":"venue"
},
  "geometry": {"coordinates":[8.7438898087,47.3906402588],"type":"Point"}
}