{
  "type": "Feature",
  "properties": {
    "iso:country":"CH",
    "sg:address":"Kirchenstrasse 13",
    "sg:city":"Zug",
    "sg:orig_category":"Arztpraxen",
    "sg:phone":"+41 41 710 33 59",
    "sg:postcode":"6300",
    "sg:province":"Zug",
    "wof:name":"Dr.med.irene Hegglin Spezial\u00e4rztin Fmh",
    "wof:placetype":"venue"
},
  "geometry": {"coordinates":[8.517024,47.164658],"type":"Point"}
}