{
  "type": "Feature",
  "properties": {
    "iso:country":"CH",
    "sg:address":"Chemin Du Lavasson",
    "sg:city":"Gland",
    "sg:orig_category":"Instandhaltung U Reparatur von Automobilen",
    "sg:phone":"+41 21 312 19 29",
    "sg:postcode":"1196",
    "sg:province":"Vaud",
    "wof:name":"Garage Automar Sa",
    "wof:placetype":"venue"
},
  "geometry": {"coordinates":[6.6395821571,46.5210647583],"type":"Point"}
}