{
  "type": "Feature",
  "properties": {
    "iso:country":"CH",
    "sg:address":"Bahnhofplatz Nr. 10 7000 Chur. Postfach",
    "sg:city":"Chur",
    "sg:orig_category":"Interessenvertretungen",
    "sg:phone":"+41 81 258 23 40",
    "sg:postcode":"7000",
    "sg:province":"Graubunden",
    "wof:name":"Stiftung Der Gebirgs-division 12 Zur F\u00f6rderung Der Gebirgst\u00fcchtigkeit Ihrer Wehrm\u00e4nner",
    "wof:placetype":"venue"
},
  "geometry": {"coordinates":[9.531170845,46.8501968384],"type":"Point"}
}