{
  "type": "Feature",
  "properties": {
    "iso:country":"CH",
    "sg:address":"Wartstrasse 50 8400 Winterthur. Postfach 193",
    "sg:city":"Winterthur",
    "sg:orig_category":"Reiseb\u00fcros Verkehrsverb\u00e4nde",
    "sg:phone":"+41 52 224 04 04",
    "sg:postcode":"8407",
    "wof:name":"Touring-club Der Schweiz Tcs Gesch\u00e4ftsstelle & Reiseb\u00fcro",
    "wof:placetype":"venue"
},
  "geometry": {"coordinates":[8.7181367874,47.5023918152],"type":"Point"}
}