{
  "type": "Feature",
  "properties": {
    "iso:country":"CH",
    "sg:address":"Nassacherstrasse 3",
    "sg:city":"Effretikon",
    "sg:orig_category":"Herstellung von Betonerzeugnissen f\u00fcr den Bau Herstellung von sonstigen Produkten aus nichtmetallisc",
    "sg:phone":"+41 52 343 28 36",
    "sg:postcode":"8307",
    "sg:province":"Z\u00fcrich",
    "wof:name":"Peter Maier Kunststeinfabrik",
    "wof:placetype":"venue"
},
  "geometry": {"coordinates":[8.6942443848,47.4124984741],"type":"Point"}
}