{
  "type": "Feature",
  "properties": {
    "iso:country":"CH",
    "sg:address":"Bahnhofstr. 19 8580 Amriswil. Postfach",
    "sg:city":"Oberaach",
    "sg:orig_category":"Sonstige mit der Informatik verbundene T\u00e4tigkeiten",
    "sg:phone":"+41 71 411 62 60",
    "sg:postcode":"8587",
    "sg:province":"Thurgau",
    "wof:name":"Schweizer Hch.",
    "wof:placetype":"venue"
},
  "geometry": {"coordinates":[9.3017406464,47.5477333069],"type":"Point"}
}