{
  "type": "Feature",
  "properties": {
    "iso:country":"CH",
    "sg:address":"Holderst\u00fcdeliweg 51",
    "sg:city":"Muttenz",
    "sg:orig_category":"Forstwirtschaft ohne Dienstleistungen in der Forstwirtschaft",
    "sg:phone":"+41 61 461 00 44",
    "sg:postcode":"4132",
    "sg:province":"Basel-Landschaft",
    "wof:name":"Walder H. + K. Ag Muttenz",
    "wof:placetype":"venue"
},
  "geometry": {"coordinates":[7.6349329948,47.5306663513],"type":"Point"}
}