{
  "type": "Feature",
  "properties": {
    "iso:country":"CH",
    "sg:address":"Coquelicots Chemin Des 16",
    "sg:city":"Vernier",
    "sg:orig_category":"Gewinnung von Kies U Sand",
    "sg:phone":"+41 21 613 12 60",
    "sg:postcode":"1214",
    "sg:province":"Gen\u00e8ve",
    "wof:name":"Gravi\u00e8res De L'isle Sa",
    "wof:placetype":"venue"
},
  "geometry": {"coordinates":[-93.47286224370001,46.1380386353],"type":"Point"}
}