{
  "type": "Feature",
  "properties": {
    "iso:country":"CH",
    "sg:address":"Forsten 8723 Rufi. Postfach",
    "sg:city":"Rufi",
    "sg:orig_category":"RESTAURANTS: TEA-ROOMS",
    "sg:postcode":"8723",
    "sg:province":"St. Gallen",
    "wof:name":"Restaurant Sonne, Gm\u00fcr",
    "wof:placetype":"venue"
},
  "geometry": {"coordinates":[9.0493240356,47.1895561218],"type":"Point"}
}