{
  "type": "Feature",
  "properties": {
    "iso:country":"CH",
    "sg:address":"Bahnhofstrasse 44",
    "sg:city":"Horw",
    "sg:orig_category":"Instandhaltung U Reparatur von Automobilen",
    "sg:phone":"+41 61 751 36 36",
    "sg:postcode":"6048",
    "sg:province":"Luzern",
    "wof:name":"Lienert Horst",
    "wof:placetype":"venue"
},
  "geometry": {"coordinates":[7.6024050713,47.4726600647],"type":"Point"}
}