{
  "type": "Feature",
  "properties": {
    "iso:country":"CH",
    "sg:address":"Parkstrasse 26",
    "sg:city":"Goldau",
    "sg:classifiers":[
        {
            "category":"Banks & Credit Unions",
            "subcategory":"Investment Brokerage",
            "type":"Services"
        }
    ],
    "sg:phone":"+41 41 855 30 80",
    "sg:postcode":"6410",
    "sg:province":"Schwyz",
    "sg:tags":[
        "caf\u00e9s",
        "tea-rooms",
        "restaurants"
    ],
    "wof:name":"Laddouli-kurmann Ursula Rosa, Caf\u00e9 Tierpark",
    "wof:placetype":"venue"
},
  "geometry": {"coordinates":[8.5517978668,47.0509033203],"type":"Point"}
}