{
  "type": "Feature",
  "properties": {
    "iso:country":"CH",
    "sg:address":"Schlyffistrasse 17f 8807 Freienbach. Postfach",
    "sg:city":"Freienbach",
    "sg:orig_category":"Herstellung von Radio U Fernsehger\u00e4ten sowie phono U videotechnischen Ger\u00e4ten",
    "sg:postcode":"8807",
    "sg:province":"Schwyz",
    "wof:name":"Hir-vertriebs Gmbh",
    "wof:placetype":"venue"
},
  "geometry": {"coordinates":[8.7282190323,47.1985092163],"type":"Point"}
}