{
  "type": "Feature",
  "properties": {
    "iso:country":"CH",
    "sg:address":"Postgasse 9",
    "sg:city":"Staufen",
    "sg:orig_category":"Non-Classified Establishments",
    "sg:postcode":"5603",
    "sg:province":"Aargau",
    "wof:name":"S'h\u00e4xeh\u00fcsli Isabella Mischler / Esther Reusser",
    "wof:placetype":"venue"
},
  "geometry": {"coordinates":[8.2773666382,47.351474762],"type":"Point"}
}