{
  "type": "Feature",
  "properties": {
    "iso:country":"CH",
    "sg:address":"Fuchshubelstrasse 7",
    "sg:city":"Ittigen",
    "sg:orig_category":"Gartenbau",
    "sg:phone":"+41 31 921 48 08",
    "sg:postcode":"3063",
    "sg:province":"Bern",
    "wof:name":"Walter Kocher G\u00e4rtnerei",
    "wof:placetype":"venue"
},
  "geometry": {"coordinates":[7.4772400856,46.9843826294],"type":"Point"}
}