{
  "type": "Feature",
  "properties": {
    "iso:country":"CH",
    "sg:address":"1845",
    "sg:city":"Noville",
    "sg:orig_category":"Gartenbau Landschaftsplanungsb\u00fcros U Gartenarchitekturb\u00fcros",
    "sg:phone":"+41 21 960 45 59",
    "sg:postcode":"1845",
    "sg:province":"Vaud",
    "wof:name":"Laurent Br\u00f6nnimann Cr\u00e8ations-entretiens Jardins",
    "wof:placetype":"venue"
},
  "geometry": {"coordinates":[6.8991661072,46.381565094],"type":"Point"}
}