{
  "type": "Feature",
  "properties": {
    "iso:country":"CH",
    "sg:address":"Seevorstadt 10",
    "sg:city":"Biel/bienne",
    "sg:orig_category":"Architektur U Ingenieurb\u00fcros",
    "sg:phone":"+41 32 322 23 11",
    "sg:postcode":"2502",
    "sg:province":"Bern",
    "wof:name":"Walther Bauphysik Ag",
    "wof:placetype":"venue"
},
  "geometry": {"coordinates":[7.236406,47.135986],"type":"Point"}
}