{
  "type": "Feature",
  "properties": {
    "iso:country":"CH",
    "sg:address":"Talstrasse 131",
    "sg:city":"Trasadingen",
    "sg:orig_category":"Handelsvermittlung U Grosshandel Sonstiger Grosshandel",
    "sg:phone":"+41 79 283 42 62",
    "sg:postcode":"8219",
    "sg:province":"Schaffhausen",
    "wof:name":"Hbv Gmbh",
    "wof:placetype":"venue"
},
  "geometry": {"coordinates":[8.4255361557,47.6690826416],"type":"Point"}
}