{
  "type": "Feature",
  "properties": {
    "iso:country":"CH",
    "sg:address":"Carl Spitteler-strasse 38 8053 Z\u00fcrich. Postfach 361",
    "sg:city":"Z\u00fcrich",
    "sg:orig_category":"Interessenvertretungen",
    "sg:phone":"+41 13813400",
    "sg:postcode":"8053",
    "sg:province":"Z\u00fcrich",
    "wof:name":"Stiftung Paulus-akademie Z\u00fcrich",
    "wof:placetype":"venue"
},
  "geometry": {"coordinates":[8.5904178619,47.3567237854],"type":"Point"}
}