{
  "type": "Feature",
  "properties": {
    "iso:country":"CH",
    "sg:address":"Weinbergstrasse 147",
    "sg:city":"Z\u00fcrich",
    "sg:orig_category":"Religi\u00f6se Vereinigungen",
    "sg:phone":"+41 13501398",
    "sg:postcode":"8006",
    "sg:province":"Z\u00fcrich",
    "wof:name":"Swiss Muslim Society",
    "wof:placetype":"venue"
},
  "geometry": {"coordinates":[8.5397205353,47.3899269104],"type":"Point"}
}