{
  "type": "Feature",
  "properties": {
    "iso:country":"CH",
    "sg:address":"Sebastiangasse 1 Brig 3900 Brig. Postfach",
    "sg:city":"Brig",
    "sg:orig_category":"Sonstige pers\u00f6nliche Dienstleistungen",
    "sg:phone":"+41 79 650 41 53",
    "sg:postcode":"3900",
    "sg:province":"Valais",
    "wof:name":"M.l. Piercing & Tattoo Gmbh K\u00f6rpermodifikationen Wie Piercing, Tatoos, Branding Usw",
    "wof:placetype":"venue"
},
  "geometry": {"coordinates":[7.9876461029,46.3158912659],"type":"Point"}
}