{
  "type": "Feature",
  "properties": {
    "iso:country":"CH",
    "sg:address":"Alpenstrasse 13",
    "sg:city":"Neuhausen",
    "sg:orig_category":"Vereine Wissenschaftliche",
    "sg:postcode":"8212",
    "sg:province":"Schaffhausen",
    "wof:name":"Anthroposophische Gesellschaft",
    "wof:placetype":"venue"
},
  "geometry": {"coordinates":[8.618024826,47.6848907471],"type":"Point"}
}