{
  "type": "Feature",
  "properties": {
    "iso:country":"CH",
    "sg:address":"Grubstrasse 11 9515 Hosenruck. Postfach",
    "sg:city":"Hosenruck",
    "sg:orig_category":"Herstellung von Hebezeugen U F\u00f6rdermitteln",
    "sg:phone":"+41 17847458",
    "sg:postcode":"9515",
    "sg:province":"Thurgau",
    "wof:name":"Wittur Ag",
    "wof:placetype":"venue"
},
  "geometry": {"coordinates":[8.7341480255,47.1973953247],"type":"Point"}
}