{
  "type": "Feature",
  "properties": {
    "iso:country":"CH",
    "sg:address":"Hinterester 8",
    "sg:city":"Bachenb\u00fclach",
    "sg:orig_category":"Erbringung von Dienstleistungen f\u00fcr Unternehmen",
    "sg:postcode":"8184",
    "sg:province":"Z\u00fcrich",
    "wof:name":"F.a.d. Diener Federico A.",
    "wof:placetype":"venue"
},
  "geometry": {"coordinates":[8.5430812836,47.5006866455],"type":"Point"}
}