{
  "type": "Feature",
  "properties": {
    "iso:country":"CH",
    "sg:address":"Via Valle",
    "sg:city":"Caslano",
    "sg:classifiers":[
        {
            "category":"Restaurant",
            "type":"Food & Drink"
        }
    ],
    "sg:phone":"+41 91 606 27 80",
    "sg:postcode":"6987",
    "sg:province":"Ticino",
    "wof:name":"Grotto Della Valle",
    "wof:placetype":"venue"
},
  "geometry": {"coordinates":[8.8800354004,45.9703102112],"type":"Point"}
}