{
  "type": "Feature",
  "properties": {
    "iso:country":"CH",
    "sg:address":"Seestrasse 133",
    "sg:city":"Goldach",
    "sg:orig_category":"Schiffs U Bootsbau",
    "sg:phone":"+41 71 841 18 57",
    "sg:postcode":"9403",
    "sg:province":"St. Gallen",
    "wof:name":"Bootswerft Rietli Mario Lingeri",
    "wof:placetype":"venue"
},
  "geometry": {"coordinates":[9.477930069,47.4834518433],"type":"Point"}
}