{
  "type": "Feature",
  "properties": {
    "iso:country":"CH",
    "sg:address":"Alte Amriswilerstrasse 1",
    "sg:city":"Romanshorn",
    "sg:orig_category":"Haltung von Gefl\u00fcgel",
    "sg:phone":"+41 33 828 15 24",
    "sg:postcode":"8590",
    "sg:province":"Thurgau",
    "wof:name":"H\u00e4ri-gefl\u00fcgelhaltung",
    "wof:placetype":"venue"
},
  "geometry": {"coordinates":[7.8954749107,46.7019309998],"type":"Point"}
}