{
  "type": "Feature",
  "properties": {
    "iso:country":"CH",
    "sg:address":"Pargherastrasse 1/3",
    "sg:city":"Chur",
    "sg:classifiers":[
        {
            "category":"Restaurant",
            "type":"Food & Drink"
        }
    ],
    "sg:phone":"+41 62 893 12 58",
    "sg:postcode":"7000",
    "sg:province":"Graubunden",
    "wof:name":"Pizzeria Trotte",
    "wof:placetype":"venue"
},
  "geometry": {"coordinates":[8.1669282913,47.4312515259],"type":"Point"}
}