{
  "type": "Feature",
  "properties": {
    "iso:country":"CH",
    "sg:address":"Chemin Des C\u00e8dres 2bis",
    "sg:city":"Lausanne",
    "sg:orig_category":"Detailhandel mit Milcherzeugnissen U Eiern Detailhandel mit Waren verschiedener Art, Hauptrichtung N",
    "sg:phone":"+41 21 646 52 01",
    "sg:postcode":"1004",
    "sg:province":"Vaud",
    "wof:name":"Cestari R. Epicerie-primeurs; Laiterie",
    "wof:placetype":"venue"
},
  "geometry": {"coordinates":[6.6268610954,46.5245704651],"type":"Point"}
}