{
  "type": "Feature",
  "properties": {
    "iso:country":"CH",
    "sg:address":"Steinentorstrasse 13",
    "sg:city":"Basel",
    "sg:classifiers":[
        {
            "category":"Shopping",
            "subcategory":"Books",
            "type":"Retail Goods"
        }
    ],
    "sg:phone":"+41 61 467 85 55",
    "sg:postcode":"4051",
    "sg:province":"Basel-Stadt",
    "wof:name":"Emh Schweizerischer \u00c4rzteverlag Ag",
    "wof:placetype":"venue"
},
  "geometry": {"coordinates":[7.589555,47.551662],"type":"Point"}
}