{
  "type": "Feature",
  "properties": {
    "iso:country":"CH",
    "sg:address":"General Wille-strasse 19",
    "sg:city":"Z\u00fcrich",
    "sg:orig_category":"Unternehmensberatung",
    "sg:phone":"+41 12014342",
    "sg:postcode":"8002",
    "sg:province":"Z\u00fcrich",
    "wof:name":"Usp Consult Manfred W.herr Unternehmensberatung",
    "wof:placetype":"venue"
},
  "geometry": {"coordinates":[8.5324373245,47.3634757996],"type":"Point"}
}