{
  "type": "Feature",
  "properties": {
    "addr:full":"Seetalstrasse 105 Schafisheim Aargau 5503",
    "addr:housenumber":"105",
    "addr:postcode":"5503",
    "addr:street":"Seetalstrasse",
    "iso:country":"CH",
    "sg:address":"Seetalstrasse 105",
    "sg:city":"Schafisheim",
    "sg:orig_category":"Arztpraxen",
    "sg:phone":"+41 62 892 01 22",
    "sg:postcode":"5503",
    "sg:province":"Aargau",
    "wof:name":"Dr.med.hans-ulrich Karli Spezialarzt Fmh",
    "wof:placetype":"venue"
},
  "geometry": {"coordinates":[8.142969,47.37685],"type":"Point"}
}