{
  "type": "Feature",
  "properties": {
    "iso:country":"CH",
    "sg:address":"Alpeneggstrasse 1",
    "sg:city":"Bern",
    "sg:orig_category":"Wirtschaftsverb\u00e4nde Industrie, Handel and Gewerbe",
    "sg:phone":"+41 31 351 49 43",
    "sg:postcode":"3012",
    "sg:province":"Bern",
    "wof:name":"Vst - Msp Sekretariat Dr.rothenb\u00fchler",
    "wof:placetype":"venue"
},
  "geometry": {"coordinates":[7.4527831078,46.9436416626],"type":"Point"}
}