{
  "type": "Feature",
  "properties": {
    "iso:country":"CH",
    "sg:address":"Rue Des Roches 30",
    "sg:city":"St-imier",
    "sg:classifiers":[
        {
            "category":"Wholesale",
            "subcategory":"Machinery & Supplies",
            "type":"Manufacturing & Wholesale Goods"
        }
    ],
    "sg:phone":"+41 32 941 42 96",
    "sg:postcode":"2610",
    "sg:province":"Bern",
    "sg:tags":[
        "equipment",
        "equipement",
        "precision",
        "timekeeping"
    ],
    "wof:name":"Dh & Co Sa",
    "wof:placetype":"venue"
},
  "geometry": {"coordinates":[6.9935097694,47.1525497437],"type":"Point"}
}