{
  "type": "Feature",
  "properties": {
    "iso:country":"CH",
    "sg:address":"Avenue Des Alpes 44",
    "sg:city":"Montreux",
    "sg:orig_category":"Kunsthandel",
    "sg:phone":"+41 21 961 16 05",
    "sg:postcode":"1820",
    "sg:province":"Vaud",
    "wof:name":"Art-top Jacques A.guhl Galerie D'art",
    "wof:placetype":"venue"
},
  "geometry": {"coordinates":[6.9111099243,46.4335784912],"type":"Point"}
}