{
  "type": "Feature",
  "properties": {
    "iso:country":"CH",
    "sg:address":"S\u00e4getstrasse 19 4802 Strengelbach. Postfach",
    "sg:city":"Strengelbach",
    "sg:orig_category":"Institutionen f\u00fcr Behinderte Wohnheime",
    "sg:phone":"+41 62 746 96 00",
    "sg:postcode":"4802",
    "sg:province":"Aargau",
    "wof:name":"Arbeitszentrum F\u00fcr Behinderte",
    "wof:placetype":"venue"
},
  "geometry": {"coordinates":[7.92608881,47.2802886963],"type":"Point"}
}