{
  "type": "Feature",
  "properties": {
    "iso:country":"CH",
    "sg:address":"Viaduktstrasse 5",
    "sg:city":"Grenchen",
    "sg:orig_category":"Detailhandel mit elektrischen Haushalts-,Radio U Fernsehger\u00e4ten sowie Musikinstrumenten",
    "sg:postcode":"2540",
    "sg:province":"Solothurn",
    "wof:name":"Japtel Electronic R. H. Vogt",
    "wof:placetype":"venue"
},
  "geometry": {"coordinates":[7.3935670853,47.1959533691],"type":"Point"}
}