{
  "type": "Feature",
  "properties": {
    "iso:country":"CH",
    "sg:address":"Buechstrasse 30",
    "sg:city":"Jona",
    "sg:orig_category":"Handelsvermittlung U Grosshandel Handelsvermittlung U Grosshandel mit Automobilteilen U Zubeh\u00f6r",
    "sg:phone":"+41 61 417 45 10",
    "sg:postcode":"8645",
    "sg:province":"St. Gallen",
    "wof:name":"Derendinger Ag Autobestandteile Autozubeh\u00f6r",
    "wof:placetype":"venue"
},
  "geometry": {"coordinates":[7.6068811417,47.5223007202],"type":"Point"}
}