{
  "type": "Feature",
  "properties": {
    "iso:country":"CH",
    "sg:address":"Seestrasse 32",
    "sg:city":"R\u00fcschlikon",
    "sg:orig_category":"Datenverarbeitungsdienste Softwareentwicklung U beratung",
    "sg:phone":"+41 17728472",
    "sg:postcode":"8803",
    "sg:province":"Z\u00fcrich",
    "wof:name":"Davesoft D.vaccaro Edv-l\u00f6sungen",
    "wof:placetype":"venue"
},
  "geometry": {"coordinates":[8.55633,47.311222],"type":"Point"}
}