{
  "type": "Feature",
  "properties": {
    "addr:full":"Grand'rue 48 Rolle Vaud 1180",
    "addr:housenumber":"48",
    "addr:postcode":"1180",
    "addr:street":"Grand'Rue",
    "iso:country":"CH",
    "sg:address":"Grand'rue 48",
    "sg:city":"Rolle",
    "sg:orig_category":"Detailhandel mit Antiquit\u00e4ten U Gebrauchtwaren in Verkaufsr\u00e4umen",
    "sg:phone":"+41 21 825 39 02",
    "sg:postcode":"1180",
    "sg:province":"Vaud",
    "wof:name":"Gasparetto J.-m.",
    "wof:placetype":"venue"
},
  "geometry": {"coordinates":[6.338232,46.457516],"type":"Point"}
}