{
  "type": "Feature",
  "properties": {
    "iso:country":"CH",
    "sg:address":"Konstanzerstrasse 54",
    "sg:city":"T\u00e4gerwilen",
    "sg:orig_category":"Apples, Fresh",
    "sg:phone":"+41 71 669 11 11",
    "sg:postcode":"8274",
    "sg:province":"Thurgau",
    "wof:name":"Gzt Gem\u00fcsezentrale",
    "wof:placetype":"venue"
},
  "geometry": {"coordinates":[9.13855,47.659847],"type":"Point"}
}