{
  "type": "Feature",
  "properties": {
    "iso:country":"CH",
    "sg:address":"Br\u00fcelmattstrasse 18",
    "sg:city":"Trimbach",
    "sg:orig_category":"Erschliessung von Grundst\u00fccken",
    "sg:postcode":"4632",
    "sg:province":"Solothurn",
    "wof:name":"Genossenschaft F\u00fcr Alters Und Invalidenwohnungen In Den Holdermatten Trimbach",
    "wof:placetype":"venue"
},
  "geometry": {"coordinates":[7.8926429749,47.3656806946],"type":"Point"}
}