{
  "type": "Feature",
  "properties": {
    "iso:country":"CH",
    "sg:address":"Abendsmatt 14",
    "sg:city":"Lampenberg",
    "sg:orig_category":"Kurhotels mit Restaurant",
    "sg:phone":"+41 61 951 10 24",
    "sg:postcode":"4432",
    "sg:province":"Basel-Landschaft",
    "wof:name":"Kurhaus Abendsmatt",
    "wof:placetype":"venue"
},
  "geometry": {"coordinates":[7.7479419708,47.4188079834],"type":"Point"}
}