{
  "type": "Feature",
  "properties": {
    "iso:country":"CH",
    "sg:address":"Moosweg 4",
    "sg:city":"Grossh\u00f6chstetten",
    "sg:orig_category":"Wohnheime",
    "sg:postcode":"3506",
    "sg:province":"Bern",
    "wof:name":"Familienwohngruppe Ruth Fernandez, Sozialp\u00e4dagogische Kleininstitution",
    "wof:placetype":"venue"
},
  "geometry": {"coordinates":[7.6360840797,46.9040565491],"type":"Point"}
}