{
  "type": "Feature",
  "properties": {
    "iso:country":"CH",
    "sg:address":"Seelmatten",
    "sg:city":"Turbenthal",
    "sg:orig_category":"Verwertung von Milch",
    "sg:postcode":"8488",
    "sg:province":"Z\u00fcrich",
    "wof:name":"Sennereigenossenschaft Seelmatten, Niederhofen Und H\u00f6fli",
    "wof:placetype":"venue"
},
  "geometry": {"coordinates":[8.8961400986,47.4541282654],"type":"Point"}
}