{
  "type": "Feature",
  "properties": {
    "iso:country":"CH",
    "sg:address":"Ch. De La Falaise 33",
    "sg:city":"Gland",
    "sg:orig_category":"Unclassifiable Establishments",
    "sg:postcode":"1196",
    "sg:province":"Vaud",
    "wof:name":"Si A Rajada",
    "wof:placetype":"venue"
},
  "geometry": {"coordinates":[6.2866840363,46.4147758484],"type":"Point"}
}