{
  "type": "Feature",
  "properties": {
    "iso:country":"CH",
    "sg:address":"Unterdorf 59",
    "sg:city":"Trogen",
    "sg:orig_category":"Unclassifiable Establishments",
    "sg:phone":"+41 71 344 14 12",
    "sg:postcode":"9043",
    "sg:province":"Appenzell Ausserrhoden",
    "wof:name":"Hotel Hirschen",
    "wof:placetype":"venue"
},
  "geometry": {"coordinates":[9.4657211304,47.4083938599],"type":"Point"}
}