{
  "type": "Feature",
  "properties": {
    "iso:country":"CH",
    "sg:address":"Doktorstr\u00e4ssli 3",
    "sg:city":"Niederbipp",
    "sg:orig_category":"Primarschulen",
    "sg:phone":"+41 71 636 15 11",
    "sg:postcode":"4704",
    "sg:province":"Bern",
    "wof:name":"Primarschule Mittelstufenschulhaus",
    "wof:placetype":"venue"
},
  "geometry": {"coordinates":[9.1665687561,47.5778923035],"type":"Point"}
}