{
  "type": "Feature",
  "properties": {
    "iso:country":"CH",
    "sg:address":"M\u00fchlentalstrasse 86",
    "sg:city":"Schaffhausen",
    "sg:orig_category":"Herstellung von sonstigen Erzeugnissen",
    "sg:phone":"+41 52 631 20 24",
    "sg:postcode":"8200",
    "sg:province":"Schaffhausen",
    "wof:name":"Marcel Nyffenegger Tierpr\u00e4paration",
    "wof:placetype":"venue"
},
  "geometry": {"coordinates":[8.6299600601,47.7043228149],"type":"Point"}
}