{
  "type": "Feature",
  "properties": {
    "iso:country":"CH",
    "sg:address":"Baslerstrasse 176",
    "sg:city":"Allschwil",
    "sg:orig_category":"Detailhandel mit Blumen U Pflanzen",
    "sg:phone":"+41 61 481 26 58",
    "sg:postcode":"4123",
    "sg:province":"Basel-Landschaft",
    "wof:name":"Marianne Kellerhals Blumenhaus Ziegelei",
    "wof:placetype":"venue"
},
  "geometry": {"coordinates":[7.549087,47.55188],"type":"Point"}
}