{
  "type": "Feature",
  "properties": {
    "iso:country":"CH",
    "sg:address":"Route De Bresse 27",
    "sg:city":"V\u00e9troz",
    "sg:orig_category":"Maurerarbeiten",
    "sg:phone":"+41 27 346 10 43",
    "sg:postcode":"1963",
    "sg:province":"Valais",
    "wof:name":"Joseph Sermier Entreprise De Ma\u00e7onnerie",
    "wof:placetype":"venue"
},
  "geometry": {"coordinates":[7.2826747894,46.2206039429],"type":"Point"}
}