{
  "type": "Feature",
  "properties": {
    "iso:country":"CH",
    "sg:address":"Fl\u00fcelastrasse 16",
    "sg:city":"Z\u00fcrich",
    "sg:orig_category":"Druck ohne Zeitungsdruck Offsetdruck",
    "sg:phone":"+41 14059075",
    "sg:postcode":"8048",
    "sg:province":"Z\u00fcrich",
    "wof:name":"Brunner & Scheuble Ag",
    "wof:placetype":"venue"
},
  "geometry": {"coordinates":[8.4966497421,47.3834915161],"type":"Point"}
}