{
  "type": "Feature",
  "properties": {
    "iso:country":"CH",
    "sg:address":"In Bruggen 12",
    "sg:city":"Wettswil",
    "sg:orig_category":"Elektro- and elektronische Maschinen Grosshandel",
    "sg:phone":"+41 41 260 30 40",
    "sg:postcode":"8907",
    "sg:province":"Z\u00fcrich",
    "wof:name":"Sct Servo Control Technology Ag",
    "wof:placetype":"venue"
},
  "geometry": {"coordinates":[8.2812957764,47.0710334778],"type":"Point"}
}