{
  "type": "Feature",
  "properties": {
    "iso:country":"CH",
    "sg:address":"Dangelstrasse 9 8000 Z\u00fcrich. Postfach",
    "sg:city":"Z\u00fcrich",
    "sg:orig_category":"Fachdetailhandel in Verkaufsr\u00e4umen",
    "sg:postcode":"8038",
    "sg:province":"Z\u00fcrich",
    "wof:name":"Sarina's Feine Sachen Hefti",
    "wof:placetype":"venue"
},
  "geometry": {"coordinates":[8.5290641785,47.3342170715],"type":"Point"}
}