{
  "type": "Feature",
  "properties": {
    "iso:country":"CH",
    "sg:address":"Kreuzgasse 8",
    "sg:city":"Meiringen",
    "sg:orig_category":"Kauf U Verkauf von Immobilien auf eigene Rechnung",
    "sg:postcode":"3860",
    "sg:province":"Bern",
    "wof:name":"Areal Rebstock Ag",
    "wof:placetype":"venue"
},
  "geometry": {"coordinates":[8.1885919571,46.7275238037],"type":"Point"}
}