{
  "type": "Feature",
  "properties": {
    "iso:country":"CH",
    "sg:address":"Rue Centrale 11",
    "sg:city":"Moutier",
    "sg:orig_category":"Herstellung von Ger\u00e4ten der Elektrizit\u00e4tserzeugung, -verteilung u.\u00e4. -Herstellung von elektronischen",
    "sg:phone":"+41 21 841 18 41",
    "sg:postcode":"2740",
    "sg:province":"Bern",
    "wof:name":"Eaton Sa Commercial Controls Division",
    "wof:placetype":"venue"
},
  "geometry": {"coordinates":[6.2826080322,46.6466026306],"type":"Point"}
}