{
  "type": "Feature",
  "properties": {
    "iso:country":"CH",
    "sg:address":"1357",
    "sg:city":"Lignerolle",
    "sg:orig_category":"Maler U Glasergewerbe",
    "sg:phone":"+41 24 441 92 44",
    "sg:postcode":"1357",
    "sg:province":"Vaud",
    "wof:name":"Favre Michel",
    "wof:placetype":"venue"
},
  "geometry": {"coordinates":[6.4566149712,46.7404136658],"type":"Point"}
}