{
  "type": "Feature",
  "properties": {
    "iso:country":"CH",
    "sg:address":"Holzmeise",
    "sg:city":"Arosa",
    "sg:orig_category":"Betrieb von Taxis",
    "sg:phone":"+41 81 252 74 50",
    "sg:postcode":"7050",
    "sg:province":"Graubunden",
    "wof:name":"Pfosi-arosa-bus Ag",
    "wof:placetype":"venue"
},
  "geometry": {"coordinates":[9.673115,46.776608],"type":"Point"}
}