{
  "type": "Feature",
  "properties": {
    "iso:country":"CH",
    "sg:address":"Landstrasse 44",
    "sg:city":"Turgi",
    "sg:orig_category":"Detailhandel mit Waren verschiedener Art, Hauptrichtung Nahrungsmittel Wein Detailhandel",
    "sg:postcode":"5300",
    "sg:province":"Aargau",
    "wof:name":"Gregorio Lupisella Lupisella Vinimarket Import",
    "wof:placetype":"venue"
},
  "geometry": {"coordinates":[8.2516393661,47.4898490906],"type":"Point"}
}