{
  "type": "Feature",
  "properties": {
    "iso:country":"CH",
    "sg:address":"Haldenstrasse 363",
    "sg:city":"Gontenschwil",
    "sg:orig_category":"Herstellung von sonstigen Nahrungsmitteln Mineralquellen, Herstellung von alkoholfreien Getr\u00e4nken",
    "sg:phone":"+41 62 773 13 72",
    "sg:postcode":"5728",
    "sg:province":"Aargau",
    "wof:name":"Andr\u00e9 Frey Melissa-sirupfabrikation",
    "wof:placetype":"venue"
},
  "geometry": {"coordinates":[8.1377668381,47.273273468],"type":"Point"}
}