{
  "type": "Feature",
  "properties": {
    "addr:full":"Bergstr. 36 Attiswil Bern 4536",
    "addr:housenumber":"36",
    "addr:postcode":"4536",
    "addr:street":"Bergstr.",
    "iso:country":"CH",
    "sg:address":"Bergstr. 36",
    "sg:city":"Attiswil",
    "sg:orig_category":"Ausbaugewerbe",
    "sg:phone":"+41 32372480",
    "sg:postcode":"4536",
    "sg:province":"Bern",
    "wof:name":"Pl\u00fcss Chemin\u00e9e",
    "wof:placetype":"venue"
},
  "geometry": {"coordinates":[7.610814,47.255619],"type":"Point"}
}