{
  "type": "Feature",
  "properties": {
    "iso:country":"CH",
    "sg:address":"Oberdorf 2",
    "sg:city":"Muttenz",
    "sg:orig_category":"Massagestudios",
    "sg:phone":"+41 61 961 01 06",
    "sg:postcode":"4132",
    "sg:province":"Basel-Landschaft",
    "wof:name":"Fr\u00e4nzi Heckendorn Massageinstitut Fr\u00e4nzi",
    "wof:placetype":"venue"
},
  "geometry": {"coordinates":[7.7511467934,47.3952865601],"type":"Point"}
}