{
  "type": "Feature",
  "properties": {
    "iso:country":"CH",
    "sg:address":"Rebgasse 7",
    "sg:city":"Basel",
    "sg:orig_category":"Architektur U Ingenieurb\u00fcros Innenarchitekturb\u00fcros",
    "sg:phone":"+41 61 681 31 50",
    "sg:postcode":"4058",
    "sg:province":"Basel-Stadt",
    "wof:name":"Bee Toni, Dipl. Innenarchitekt Swb",
    "wof:placetype":"venue"
},
  "geometry": {"coordinates":[7.594355,47.560883],"type":"Point"}
}