{
  "type": "Feature",
  "properties": {
    "addr:full":"T\u00f6ssriedernstr. 29 8193 Eglisau. Postfach Eglisau Z\u00fcrich 8193",
    "addr:housenumber":"29",
    "addr:postcode":"8193 eglisau. postfach;8193",
    "addr:street":"Toessriedernstr.",
    "iso:country":"CH",
    "sg:address":"T\u00f6ssriedernstr. 29 8193 Eglisau. Postfach",
    "sg:city":"Eglisau",
    "sg:orig_category":"Bauschreinerei Innenausbau",
    "sg:phone":"+41 18673090",
    "sg:postcode":"8193",
    "sg:province":"Z\u00fcrich",
    "wof:name":"Hartmann Schreinerei Und Innenausbau Ag",
    "wof:placetype":"venue"
},
  "geometry": {"coordinates":[8.543094,47.566311],"type":"Point"}
}