{
  "type": "Feature",
  "properties": {
    "iso:country":"CH",
    "sg:address":"Poststrasse 6 8462 Rheinau. Postfach",
    "sg:city":"Rheinau",
    "sg:orig_category":"Wirtschaftspr\u00fcfung, Steuerberatung U Treuhand",
    "sg:postcode":"8462",
    "sg:province":"Z\u00fcrich",
    "wof:name":"Mpm Backoffice, Panzolini Michela Management",
    "wof:placetype":"venue"
},
  "geometry": {"coordinates":[8.6052303314,47.6447944641],"type":"Point"}
}