{
  "type": "Feature",
  "properties": {
    "iso:country":"CH",
    "sg:address":"6582",
    "sg:city":"Pianezzo",
    "sg:orig_category":"RESTAURANTS: TEA-ROOMS",
    "sg:phone":"+41 91 857 06 30",
    "sg:postcode":"6582",
    "sg:province":"Ticino",
    "wof:name":"Erni Anna Maria",
    "wof:placetype":"venue"
},
  "geometry": {"coordinates":[9.0291423798,46.1690711975],"type":"Point"}
}