{
  "type": "Feature",
  "properties": {
    "iso:country":"CH",
    "sg:address":"Chemin Des Charmettes 7 1003 Lausanne. Postfach",
    "sg:city":"Lausanne",
    "sg:orig_category":"Datenverarbeitungsdienste",
    "sg:phone":"+41 21 341 81 11",
    "sg:postcode":"1002",
    "sg:province":"Vaud",
    "wof:name":"S2i Services Informatiques Int\u00e9gr\u00e9s Sa",
    "wof:placetype":"venue"
},
  "geometry": {"coordinates":[6.628646,46.519253],"type":"Point"}
}