{
  "type": "Feature",
  "properties": {
    "iso:country":"CH",
    "sg:address":"Lenkstrasse 3",
    "sg:city":"Zweisimmen",
    "sg:orig_category":"Versicherungen Generalagenturen",
    "sg:phone":"+41 79 722 33 13",
    "sg:postcode":"3770",
    "sg:province":"Bern",
    "wof:name":"Die Mobiliar Versicherungen & Vorsorge",
    "wof:placetype":"venue"
},
  "geometry": {"coordinates":[7.3723430634,46.5531539917],"type":"Point"}
}