{
  "type": "Feature",
  "properties": {
    "iso:country":"CH",
    "sg:address":"Chantey Chemin Du 5",
    "sg:city":"Montreux",
    "sg:orig_category":"Wirtschaftspr\u00fcfung, Steuerberatung U Treuhand",
    "sg:postcode":"1820",
    "sg:province":"Vaud",
    "wof:name":"Fmk Fiduciaire Michaela Kiedl",
    "wof:placetype":"venue"
},
  "geometry": {"coordinates":[6.9105057716,46.4316940308],"type":"Point"}
}