{
  "type": "Feature",
  "properties": {
    "iso:country":"CH",
    "sg:address":"Sternenfeldstrasse 16",
    "sg:city":"Birsfelden",
    "sg:orig_category":"Softwareentwicklung U beratung Sonstige mit der Informatik verbundene T\u00e4tigkeiten",
    "sg:phone":"+41 61 373 31 31",
    "sg:postcode":"4127",
    "sg:province":"Basel-Landschaft",
    "wof:name":"Hw-dat Ag",
    "wof:placetype":"venue"
},
  "geometry": {"coordinates":[7.6337780952,47.5522918701],"type":"Point"}
}