{
  "type": "Feature",
  "properties": {
    "iso:country":"CH",
    "sg:address":"Hauptgasse 17",
    "sg:city":"Olten",
    "sg:orig_category":"Detailhandel mit Uhren U Schmuck Herstellung von Schmuck, Gold U Silberschmiedwaren",
    "sg:phone":"+41 62 212 23 22",
    "sg:postcode":"4600",
    "sg:province":"Solothurn",
    "wof:name":"Lambelin P. & Cie",
    "wof:placetype":"venue"
},
  "geometry": {"coordinates":[7.903854847,47.3498268127],"type":"Point"}
}