{
  "type": "Feature",
  "properties": {
    "iso:country":"CH",
    "sg:address":"Bahnhofstrasse 32 6300 Zug. Postfach",
    "sg:city":"Zug",
    "sg:orig_category":"Grosshandel mit Software Softwareentwicklung U beratung",
    "sg:phone":"+41 31 911 10 19",
    "sg:postcode":"6300",
    "sg:province":"Zug",
    "wof:name":"Opentv Ag Software, Bes. F\u00fcr Das Interaktiv-tv Gesch\u00e4ft; Vertrieb. Linzenzen Weltweit Mit Ausnahme Usa; \u00dcbernahme, Abwicklung U. Verwertung Usw",
    "wof:placetype":"venue"
},
  "geometry": {"coordinates":[8.5160121918,47.1704101562],"type":"Point"}
}