{
  "type": "Feature",
  "properties": {
    "iso:country":"CH",
    "sg:address":"M\u00fchlentalstr\u00e4sschen 9 8200 Schaffhausen. Postfach 3005",
    "sg:city":"Schaffhausen",
    "sg:orig_category":"Werbevermittlung",
    "sg:phone":"+41 52 624 61 24",
    "sg:postcode":"8201",
    "sg:province":"Schaffhausen",
    "wof:name":"Apg/sga Allgemeine Plakatgesellschaft",
    "wof:placetype":"venue"
},
  "geometry": {"coordinates":[8.6296977997,47.700176239],"type":"Point"}
}