{
  "type": "Feature",
  "properties": {
    "iso:country":"CH",
    "sg:address":"En F\u00e9lezin",
    "sg:city":"Romanel-s-lausanne",
    "sg:orig_category":"Detailhandel mit Damenbekleidung Detailhandel mit S\u00e4uglings U Kinderbekleidung",
    "sg:phone":"+41 21 648 33 31",
    "sg:postcode":"1032",
    "sg:province":"Vaud",
    "wof:name":"Boutique Onno Jaklin Kazanciyan",
    "wof:placetype":"venue"
},
  "geometry": {"coordinates":[6.6112809181,46.5597114563],"type":"Point"}
}