{
  "type": "Feature",
  "properties": {
    "iso:country":"CH",
    "sg:address":"Felsenaustrasse 29 7000 Chur. Postfach",
    "sg:city":"Chur",
    "sg:orig_category":"Elektrizit\u00e4tsversorgung Gasversorgung",
    "sg:phone":"+41 81 254 48 11",
    "sg:postcode":"7004",
    "sg:province":"Graubunden",
    "wof:name":"Industrielle Betriebe Der Stadt Chur",
    "wof:placetype":"venue"
},
  "geometry": {"coordinates":[9.5134191513,46.8564453125],"type":"Point"}
}