{
  "type": "Feature",
  "properties": {
    "iso:country":"CH",
    "sg:address":"Pfarrmattstrasse 8b",
    "sg:city":"Gretzenbach",
    "sg:orig_category":"Stukkateurgewerbe, Gipserei U Verputzerei",
    "sg:phone":"+41 62 849 39 90",
    "sg:postcode":"5014",
    "sg:province":"Solothurn",
    "wof:name":"Gipsergesch\u00e4ft Prestige G. Aiello Junior",
    "wof:placetype":"venue"
},
  "geometry": {"coordinates":[7.9969248772,47.3604545593],"type":"Point"}
}