{
  "type": "Feature",
  "properties": {
    "iso:country":"CH",
    "sg:address":"Chemin Des Cr\u00eats-de-champel 12",
    "sg:city":"Gen\u00e8ve",
    "sg:orig_category":"Arztpraxen",
    "sg:phone":"+41 22 346 51 43",
    "sg:postcode":"1206",
    "sg:province":"Gen\u00e8ve",
    "wof:name":"Dr M\u00e9d. Anna-maria Stalberg M\u00e9decin Sp\u00e9cialiste Fmh",
    "wof:placetype":"venue"
},
  "geometry": {"coordinates":[6.153761,46.188179],"type":"Point"}
}