{
  "type": "Feature",
  "properties": {
    "iso:country":"CH",
    "sg:address":"Martinsplatz 8",
    "sg:city":"Chur",
    "sg:orig_category":"Herstellung von sonstigen keramischen Erzeugnissen",
    "sg:phone":"+41 81 254 38 52",
    "sg:postcode":"7000",
    "sg:province":"Graubunden",
    "wof:name":"Alro Ag",
    "wof:placetype":"venue"
},
  "geometry": {"coordinates":[9.5323343277,46.8481216431],"type":"Point"}
}