{
  "type": "Feature",
  "properties": {
    "iso:country":"CH",
    "sg:address":"Spitz\u00e4cker Berschis 8880 Walenstadt. Postfach",
    "sg:city":"Berschis",
    "sg:orig_category":"Forstwirtschaft ohne Dienstleistungen in der Forstwirtschaft",
    "sg:postcode":"8892",
    "sg:province":"St. Gallen",
    "wof:name":"Gall Josef, Forstunternehmung Ag",
    "wof:placetype":"venue"
},
  "geometry": {"coordinates":[9.3131351471,47.1246147156],"type":"Point"}
}