{
  "type": "Feature",
  "properties": {
    "iso:country":"CH",
    "sg:address":"Via Alfonso Turconi 9",
    "sg:city":"Mendrisio",
    "sg:orig_category":"Verlegen von Fliesen U Platten",
    "sg:phone":"+41 91 646 49 81",
    "sg:postcode":"6850",
    "sg:province":"Ticino",
    "wof:name":"Gianantonio Pedroli Pavimenti & Rivestimenti",
    "wof:placetype":"venue"
},
  "geometry": {"coordinates":[8.9818048477,45.8649291992],"type":"Point"}
}