{
  "type": "Feature",
  "properties": {
    "iso:country":"CH",
    "sg:address":"1711 Br\u00fcnisried 1719 Zumholz. Postfach",
    "sg:city":"Br\u00fcnisried",
    "sg:orig_category":"Instandhaltung U Reparatur von Automobilen",
    "sg:postcode":"1719",
    "sg:province":"Fribourg",
    "wof:name":"Zbinden Kanis.",
    "wof:placetype":"venue"
},
  "geometry": {"coordinates":[7.2790999413,46.7587509155],"type":"Point"}
}