{
  "type": "Feature",
  "properties": {
    "iso:country":"CH",
    "sg:address":"Rheinfelderstrasse 12",
    "sg:city":"Birsfelden",
    "sg:orig_category":"Handelsvermittlung U Grosshandel Sonstiger Grosshandel",
    "sg:phone":"+41 61 313 18 25",
    "sg:postcode":"4127",
    "sg:province":"Basel-Landschaft",
    "wof:name":"Cetic Sa",
    "wof:placetype":"venue"
},
  "geometry": {"coordinates":[7.6257638931,47.5496788025],"type":"Point"}
}