{
  "type": "Feature",
  "properties": {
    "iso:country":"CH",
    "sg:address":"1533",
    "sg:city":"M\u00e9ni\u00e8res",
    "sg:orig_category":"Verwertung von Milch",
    "sg:postcode":"1533",
    "sg:province":"Fribourg",
    "wof:name":"Soci\u00e9t\u00e9 De Laiterie De M\u00e9ni\u00e8res",
    "wof:placetype":"venue"
},
  "geometry": {"coordinates":[6.884250164,46.7857894897],"type":"Point"}
}