{
  "type": "Feature",
  "properties": {
    "iso:country":"CH",
    "sg:address":"Lavizzari Via 4",
    "sg:city":"Lugano",
    "sg:orig_category":"Handels-H\u00e4user U Gesellschaften",
    "sg:phone":"+41 91 922 21 77",
    "sg:postcode":"6900",
    "sg:province":"Ticino",
    "wof:name":"Wtp Trade Pack Sa",
    "wof:placetype":"venue"
},
  "geometry": {"coordinates":[8.9583463669,46.0064620972],"type":"Point"}
}