{
  "type": "Feature",
  "properties": {
    "iso:country":"CH",
    "sg:address":"Holeestrasse 2-4",
    "sg:city":"Basel",
    "sg:orig_category":"Detailhandel mit M\u00f6beln Detailhandel mit Textilien",
    "sg:phone":"+41 71 911 35 11",
    "sg:postcode":"4054",
    "sg:province":"Basel-Stadt",
    "wof:name":"Sepp Lombriser Wohneinrichtungen H\u00fcsler-nest",
    "wof:placetype":"venue"
},
  "geometry": {"coordinates":[9.0461931229,47.465637207],"type":"Point"}
}