{
  "type": "Feature",
  "properties": {
    "iso:country":"CH",
    "sg:address":"Obermuhlern 122a 3086 Zimmerwald. Postfach",
    "sg:city":"Zimmerwald",
    "sg:orig_category":"Reiseb\u00fcros U Reiseveranstalter",
    "sg:postcode":"3086",
    "sg:province":"Bern",
    "wof:name":"Abenteuer Wildnis Gmbh Trekking, Abenteuer- U. Wildnistouren; Vertrieb, Organisation, Durchf\u00fchrung",
    "wof:placetype":"venue"
},
  "geometry": {"coordinates":[7.4716010094,46.8815917969],"type":"Point"}
}