{
  "type": "Feature",
  "properties": {
    "iso:country":"CH",
    "sg:address":"Portone Viale 5",
    "sg:city":"Bellinzona",
    "sg:orig_category":"Mit dem Versicherungsgewerbe verbundene T\u00e4tigkeiten",
    "sg:postcode":"6500",
    "sg:province":"Ticino",
    "wof:name":"E.c. Soluzioni Sagl",
    "wof:placetype":"venue"
},
  "geometry": {"coordinates":[9.0222902298,46.1937828064],"type":"Point"}
}