{
  "type": "Feature",
  "properties": {
    "iso:country":"CH",
    "sg:address":"Simonstrasse 2",
    "sg:city":"Bern",
    "sg:orig_category":"Herstellung von M\u00f6beln Schlossereien",
    "sg:phone":"+41 31 301 66 61",
    "sg:postcode":"3012",
    "sg:province":"Bern",
    "wof:name":"Anton Winkler Metallm\u00f6belbau & Schlosserei",
    "wof:placetype":"venue"
},
  "geometry": {"coordinates":[7.43328619,46.9582595825],"type":"Point"}
}