{
  "type": "Feature",
  "properties": {
    "iso:country":"CH",
    "sg:address":"Webereistrasse 49",
    "sg:city":"Adliswil",
    "sg:orig_category":"Gesundheitswesen Physiotherapie",
    "sg:phone":"+41 17100800",
    "sg:postcode":"8134",
    "sg:province":"Z\u00fcrich",
    "wof:name":"Physiotherapie Adliswil Van Den Bergh A. & Laseroms H.",
    "wof:placetype":"venue"
},
  "geometry": {"coordinates":[8.5254478455,47.3063774109],"type":"Point"}
}