{
  "type": "Feature",
  "properties": {
    "iso:country":"CH",
    "sg:address":"Rhonesandstrasse 32",
    "sg:city":"Brig",
    "sg:orig_category":"Detailhandel mit Waren verschiedener Art, Hauptrichtung Nahrungsmittel",
    "sg:phone":"+41 27 923 25 23",
    "sg:postcode":"3900",
    "sg:province":"Valais",
    "wof:name":"Denner Top Superdiscount",
    "wof:placetype":"venue"
},
  "geometry": {"coordinates":[7.9912948608,46.3181838989],"type":"Point"}
}