{
  "type": "Feature",
  "properties": {
    "iso:country":"CH",
    "sg:address":"Rue De La Dixence 46",
    "sg:city":"Sion",
    "sg:orig_category":"RESTAURANTS: TEA-ROOMS",
    "sg:postcode":"1950",
    "sg:province":"Valais",
    "wof:name":"Monod, Mme Fran\u00e7oise",
    "wof:placetype":"venue"
},
  "geometry": {"coordinates":[7.3704209328,46.2281990051],"type":"Point"}
}