{
  "type": "Feature",
  "properties": {
    "iso:country":"CH",
    "sg:address":"Hauptstrasse 99",
    "sg:city":"Sissach",
    "sg:orig_category":"Instandhaltung U Reparatur von Automobilen",
    "sg:phone":"+41 19052858",
    "sg:postcode":"4450",
    "sg:province":"Basel-Landschaft",
    "wof:name":"Garage Widmer Ag",
    "wof:placetype":"venue"
},
  "geometry": {"coordinates":[8.7135658264,47.3507003784],"type":"Point"}
}