{
  "type": "Feature",
  "properties": {
    "iso:country":"CH",
    "sg:address":"Schwarzenburgstrasse 150",
    "sg:city":"Liebefeld",
    "sg:orig_category":"Unternehmensberatung",
    "sg:phone":"+41 19204488",
    "sg:postcode":"3097",
    "sg:province":"Bern",
    "wof:name":"Magma Investitionsg\u00fctermarketing",
    "wof:placetype":"venue"
},
  "geometry": {"coordinates":[8.6884021759,47.2736053467],"type":"Point"}
}