{
  "type": "Feature",
  "properties": {
    "iso:country":"CH",
    "sg:address":"Davel Avenue 19 1004 Lausanne. Postfach",
    "sg:city":"Lausanne",
    "sg:orig_category":"Elektroinstallation",
    "sg:postcode":"1003",
    "sg:province":"Vaud",
    "wof:name":"Fest Wilfried Installat. \u00e9lectriques",
    "wof:placetype":"venue"
},
  "geometry": {"coordinates":[6.6276421547,46.5280838013],"type":"Point"}
}