{
  "type": "Feature",
  "properties": {
    "iso:country":"CH",
    "sg:address":"Avenue Mercier-de-molin 1 3960 Sierre. Postfach",
    "sg:city":"Sierre",
    "sg:orig_category":"Detailhandel mit Sportartikeln Fachdetailhandel in Verkaufsr\u00e4umen",
    "sg:phone":"+41 27 207 29 37",
    "sg:postcode":"3960",
    "sg:province":"Valais",
    "wof:name":"Theytaz Sports",
    "wof:placetype":"venue"
},
  "geometry": {"coordinates":[7.3860898018,46.1848449707],"type":"Point"}
}