{
  "type": "Feature",
  "properties": {
    "iso:country":"CH",
    "sg:address":"Kursch\u00fcrliweg 4 1716 Plaffeien. Postfach",
    "sg:city":"Plaffeien",
    "sg:orig_category":"Sonstige pers\u00f6nliche Dienstleistungen Tattoo and Piercing",
    "sg:postcode":"1716",
    "sg:province":"Fribourg",
    "wof:name":"R\u00f6mu's Tattoo & Airbrush Atelier Aebischer Roman T\u00e4towierung U. Airbrusch",
    "wof:placetype":"venue"
},
  "geometry": {"coordinates":[7.286801815,46.7412376404],"type":"Point"}
}