{
  "type": "Feature",
  "properties": {
    "addr:full":"Rue De Saussure 4 Gen\u00e8ve Gen\u00e8ve 1204",
    "addr:housenumber":"4",
    "addr:postcode":"1204",
    "addr:street":"Rue De Saussure",
    "iso:country":"CH",
    "sg:address":"Rue De Saussure 4",
    "sg:city":"Gen\u00e8ve",
    "sg:classifiers":[
        {
            "category":"Banks & Credit Unions",
            "subcategory":"Bank",
            "type":"Services"
        }
    ],
    "sg:phone":"+41 22 708 60 00",
    "sg:postcode":"1204",
    "sg:province":"Gen\u00e8ve",
    "wof:name":"Darier, Hentsch & Cie, Private Bankers",
    "wof:placetype":"venue"
},
  "geometry": {"coordinates":[6.142233,46.199234],"type":"Point"}
}