{
  "type": "Feature",
  "properties": {
    "iso:country":"CH",
    "sg:address":"1937",
    "sg:city":"Orsi\u00e8res",
    "sg:orig_category":"Detailhandel mit elektrischen Haushalts-,Radio U Fernsehger\u00e4ten sowie Musikinstrumenten",
    "sg:postcode":"1937",
    "sg:province":"Valais",
    "wof:name":"Fencom Sa",
    "wof:placetype":"venue"
},
  "geometry": {"coordinates":[6.1193141937,46.2296676636],"type":"Point"}
}