{
  "type": "Feature",
  "properties": {
    "iso:country":"CH",
    "sg:address":"Steinentorstrasse 11 4051 Basel. Postfach",
    "sg:city":"Basel",
    "sg:orig_category":"Non-Classified Establishments",
    "sg:phone":"+41 61 699 18 18",
    "sg:postcode":"4051",
    "sg:province":"Basel-Stadt",
    "wof:name":"Tiscali Datacomm Ag Internet; Unterst\u00fctzung Beim Einrichten, Beratung Usw",
    "wof:placetype":"venue"
},
  "geometry": {"coordinates":[7.5892529488,47.551738739],"type":"Point"}
}