{
  "type": "Feature",
  "properties": {
    "iso:country":"CH",
    "sg:address":"Chollerstrasse 3",
    "sg:city":"Zug",
    "sg:orig_category":"Herstellung von sonstigen elektrischen Ausr\u00fcstungen",
    "sg:postcode":"6300",
    "sg:province":"Zug",
    "wof:name":"Thurwil Ag",
    "wof:placetype":"venue"
},
  "geometry": {"coordinates":[8.4847288132,47.1829490662],"type":"Point"}
}