{
  "type": "Feature",
  "properties": {
    "iso:country":"CH",
    "sg:address":"Romanshornerstrasse 57",
    "sg:city":"Wittenbach",
    "sg:orig_category":"Hobel U Holzimpr\u00e4gnierwerke S\u00e4ge, Hobel U Holzimpr\u00e4gnierwerke",
    "sg:phone":"+41 79 605 27 30",
    "sg:postcode":"9303",
    "wof:name":"Davatz Ulrich L.",
    "wof:placetype":"venue"
},
  "geometry": {"coordinates":[9.3827371597,47.4604110718],"type":"Point"}
}