{
  "type": "Feature",
  "properties": {
    "iso:country":"CH",
    "sg:address":"Rue Du Lion-d'or 5-7 1003 Lausanne. Postfach",
    "sg:city":"Lausanne",
    "sg:orig_category":"Grossbanken",
    "sg:phone":"+41 844 800 844",
    "sg:postcode":"1002",
    "sg:province":"Vaud",
    "wof:name":"Credit Suisse",
    "wof:placetype":"venue"
},
  "geometry": {"coordinates":[5.1808700562,45.8973388672],"type":"Point"}
}