{
  "type": "Feature",
  "properties": {
    "iso:country":"CH",
    "sg:address":"Aeussere Poststrasse",
    "sg:city":"Arosa",
    "sg:orig_category":"Kinos",
    "sg:phone":"+41 81 377 44 62",
    "sg:postcode":"7050",
    "sg:province":"Graubunden",
    "wof:name":"Kino Kursaal",
    "wof:placetype":"venue"
},
  "geometry": {"coordinates":[9.6832551956,46.783164978],"type":"Point"}
}