{
  "type": "Feature",
  "properties": {
    "iso:country":"CH",
    "sg:address":"Eptingerstrasse 20",
    "sg:city":"Basel",
    "sg:orig_category":"Bauschreinerei Herstellung von Konstruktionsteilen, Fertigbauteilen U Ausbauelementen aus Holz",
    "sg:phone":"+41 61 693 35 25",
    "sg:postcode":"4052",
    "sg:province":"Basel-Stadt",
    "wof:name":"Hug Alexander",
    "wof:placetype":"venue"
},
  "geometry": {"coordinates":[7.607967,47.554737],"type":"Point"}
}