{
  "type": "Feature",
  "properties": {
    "iso:country":"CH",
    "sg:address":"B\u00e4retswilerstrasse 22 8494 Bauma. Postfach",
    "sg:city":"Bauma",
    "sg:orig_category":"Grosshandel mit Erzen U Metallen",
    "sg:postcode":"8494",
    "sg:province":"Z\u00fcrich",
    "wof:name":"R\u00fcegg & Iseli Gmbh",
    "wof:placetype":"venue"
},
  "geometry": {"coordinates":[8.8746767044,47.3653831482],"type":"Point"}
}