{
  "type": "Feature",
  "properties": {
    "iso:country":"CH",
    "sg:address":"Pflanzschulstrasse 17 8400 Winterthur. Postfach 19",
    "sg:city":"Winterthur",
    "sg:orig_category":"Herstellung von Erzeugnissen aus Beton, Gips U Zement Herstellung von sonstigen chemischen Erzeugnis",
    "sg:phone":"+41 71 744 36 66",
    "sg:postcode":"8411",
    "sg:province":"Z\u00fcrich",
    "wof:name":"Deitermann Ag",
    "wof:placetype":"venue"
},
  "geometry": {"coordinates":[8.7405004501,47.4963111877],"type":"Point"}
}