{
  "type": "Feature",
  "properties": {
    "iso:country":"CH",
    "sg:address":"Bahnhofstrasse 14",
    "sg:city":"Liestal",
    "sg:classifiers":[
        {
            "category":"Bars & Pubs",
            "type":"Food & Drink"
        }
    ],
    "sg:phone":"+41 61 921 28 40",
    "sg:postcode":"4410",
    "sg:province":"Basel-Landschaft",
    "wof:name":"Nelson Pub",
    "wof:placetype":"venue"
},
  "geometry": {"coordinates":[7.732015,47.484669],"type":"Point"}
}