{
  "type": "Feature",
  "properties": {
    "iso:country":"CH",
    "sg:address":"Juchstrasse 9",
    "sg:city":"Tafers",
    "sg:orig_category":"Berufsberatungen",
    "sg:phone":"+41 26 494 52 51",
    "sg:postcode":"1712",
    "sg:province":"Fribourg",
    "wof:name":"Berufs-& Laufbahnberatung",
    "wof:placetype":"venue"
},
  "geometry": {"coordinates":[7.218424,46.813667],"type":"Point"}
}