{
  "type": "Feature",
  "properties": {
    "iso:country":"CH",
    "sg:address":"Place Chauderon 38",
    "sg:city":"Lausanne",
    "sg:classifiers":[
        {
            "category":"Government",
            "subcategory":"Post Office",
            "type":"Public Place"
        }
    ],
    "sg:phone":"+41 21 624 44 14",
    "sg:postcode":"1003",
    "sg:province":"Vaud",
    "sg:tags":[
        "caf\u00e9s",
        "tea-rooms"
    ],
    "wof:name":"Bar \u00e0 Caf\u00e9 Le Carina",
    "wof:placetype":"venue"
},
  "geometry": {"coordinates":[6.6236610413,46.52368927],"type":"Point"}
}