{
  "type": "Feature",
  "properties": {
    "iso:country":"CH",
    "sg:address":"Le Grand-chemin 70",
    "sg:city":"Epalinges",
    "sg:orig_category":"Fussboden, Fliesen U Plattenlegerei, Tapeziererei Verlegen von Fliesen U Platten",
    "sg:phone":"+41 21 784 17 96",
    "sg:postcode":"1066",
    "sg:province":"Vaud",
    "wof:name":"Breitenhuber Herbert, Remusol",
    "wof:placetype":"venue"
},
  "geometry": {"coordinates":[6.6817250252,46.5515213013],"type":"Point"}
}