{
  "type": "Feature",
  "properties": {
    "iso:country":"CH",
    "sg:address":"Via Mazzini 17",
    "sg:city":"Lugano",
    "sg:orig_category":"Non-Classified Establishments",
    "sg:phone":"+41 91 994 90 41",
    "sg:postcode":"6900",
    "sg:province":"Ticino",
    "wof:name":"Finben Holdings Sa",
    "wof:placetype":"venue"
},
  "geometry": {"coordinates":[8.9442329407,45.9942169189],"type":"Point"}
}