{
  "type": "Feature",
  "properties": {
    "addr:full":"Triebernstrasse Weissbad Appenzell Innerhoden 9057",
    "addr:postcode":"9057",
    "addr:street":"Triebernstrasse",
    "iso:country":"CH",
    "sg:address":"Triebernstrasse",
    "sg:city":"Weissbad",
    "sg:classifiers":[
        {
            "category":"Banks & Credit Unions",
            "subcategory":"Bank",
            "type":"Services"
        }
    ],
    "sg:phone":"+41 71 788 88 88",
    "sg:postcode":"9057",
    "sg:province":"Appenzell Innerhoden",
    "wof:name":"Appenzeller Kantonalbank",
    "wof:placetype":"venue"
},
  "geometry": {"coordinates":[9.40768,47.331429],"type":"Point"}
}