{
  "type": "Feature",
  "properties": {
    "iso:country":"CH",
    "sg:address":"Sch\u00f6nb\u00fchl",
    "sg:city":"Diemtigen",
    "sg:orig_category":"Bauschreinerei",
    "sg:phone":"+41 79 603 53 80",
    "sg:postcode":"3754",
    "sg:province":"Bern",
    "wof:name":"Rosette Risler Bruni Schreinerei",
    "wof:placetype":"venue"
},
  "geometry": {"coordinates":[7.571854,46.653336],"type":"Point"}
}