{
  "type": "Feature",
  "properties": {
    "iso:country":"CH",
    "sg:address":"Br\u00fcckenstrasse 22 8280 Kreuzlingen. Postfach 256",
    "sg:city":"Kreuzlingen",
    "sg:orig_category":"Detailhandel mit B\u00fcchern, Zeitungen, Schreib U Papeteriewaren Detailhandel mit Ton U Bildtr\u00e4gern",
    "sg:phone":"+41 71 672 77 81",
    "sg:postcode":"8280",
    "sg:province":"Thurgau",
    "wof:name":"Asaph Ag",
    "wof:placetype":"venue"
},
  "geometry": {"coordinates":[9.16986,47.654545],"type":"Point"}
}