{
  "type": "Feature",
  "properties": {
    "iso:country":"CH",
    "sg:address":"Nieder\u00e4mterstr. 50",
    "sg:city":"Dulliken",
    "sg:classifiers":[
        {
            "category":"Wholesale",
            "subcategory":"Machinery & Supplies",
            "type":"Manufacturing & Wholesale Goods"
        }
    ],
    "sg:phone":"+41 62 285 44 44",
    "sg:postcode":"4657",
    "sg:province":"Solothurn",
    "sg:tags":[
        "food",
        "processing",
        "-",
        "machine",
        "equipment",
        "engineering",
        "mechanical"
    ],
    "wof:name":"Koch Dulliken Ag",
    "wof:placetype":"venue"
},
  "geometry": {"coordinates":[7.9378609657,47.3540344238],"type":"Point"}
}