{
  "type": "Feature",
  "properties": {
    "addr:full":"6415 Arth. Postfach Arth Schwyz 6415",
    "addr:postcode":"6415;postfach;6415",
    "addr:street":"Arth.",
    "iso:country":"CH",
    "sg:address":"6415 Arth. Postfach",
    "sg:city":"Arth",
    "sg:orig_category":"Detailhandel mit Brot, Back U S\u00fcsswaren",
    "sg:postcode":"6415",
    "sg:province":"Schwyz",
    "wof:name":"Fassbind Franz",
    "wof:placetype":"venue"
},
  "geometry": {"coordinates":[8.52237,47.062809],"type":"Point"}
}