{
  "type": "Feature",
  "properties": {
    "iso:country":"CH",
    "sg:address":"Spalenvorstadt 28",
    "sg:city":"Basel",
    "sg:orig_category":"Detailhandel mit Damenbekleidung",
    "sg:phone":"+41 71 744 15 75",
    "sg:postcode":"4051",
    "sg:province":"Basel-Stadt",
    "wof:name":"Brigitte Roth Mode-atelier",
    "wof:placetype":"venue"
},
  "geometry": {"coordinates":[9.634506,47.452274],"type":"Point"}
}