{
  "type": "Feature",
  "properties": {
    "iso:country":"CH",
    "sg:address":"Matthofring 27 6005 Luzern. Postfach",
    "sg:city":"Luzern",
    "sg:orig_category":"Grosshandel mit Textilien",
    "sg:postcode":"6003",
    "sg:province":"Luzern",
    "wof:name":"Erawan Pfaff Textilien, Spirituosen, Haushaltsartikel Usw; Im, Export",
    "wof:placetype":"venue"
},
  "geometry": {"coordinates":[8.3319587708,47.0354995728],"type":"Point"}
}