{
  "type": "Feature",
  "properties": {
    "iso:country":"CH",
    "sg:address":"Gewerbestrasse 10",
    "sg:city":"Gerlafingen",
    "sg:orig_category":"Alters U Pflegeheime Wohnheime",
    "sg:phone":"+41 32 675 41 63",
    "sg:postcode":"4563",
    "sg:province":"Solothurn",
    "wof:name":"Alterswohnheim Pergola, P. & E. Baumgartner",
    "wof:placetype":"venue"
},
  "geometry": {"coordinates":[7.571776,47.170242],"type":"Point"}
}