{
  "type": "Feature",
  "properties": {
    "iso:country":"CH",
    "sg:address":"6930",
    "sg:city":"Bedano",
    "sg:orig_category":"Bauschreinerei Herstellung von M\u00f6beln verschiedener Art",
    "sg:phone":"+41 91 935 79 55",
    "sg:postcode":"6930",
    "sg:province":"Ticino",
    "wof:name":"Veragouth Materiali E Macchine Edili Sa",
    "wof:placetype":"venue"
},
  "geometry": {"coordinates":[8.91709,46.053699],"type":"Point"}
}