{
  "type": "Feature",
  "properties": {
    "iso:country":"CH",
    "sg:address":"Feldhofstrasse 2",
    "sg:city":"Volketswil",
    "sg:orig_category":"Satzherstellung U Reproduktion",
    "sg:phone":"+41 19456080",
    "sg:postcode":"8604",
    "sg:province":"Z\u00fcrich",
    "wof:name":"Huwiler & Rettich Reprografiebetrieb",
    "wof:placetype":"venue"
},
  "geometry": {"coordinates":[8.6824007034,47.3890609741],"type":"Point"}
}