{
  "type": "Feature",
  "properties": {
    "iso:country":"CH",
    "sg:address":"Br\u00fcnnenstrasse 106",
    "sg:city":"Bern",
    "sg:orig_category":"Detailhandel mit M\u00f6beln U Haushaltsgegenst\u00e4nden Detailhandel mit Teppichen",
    "sg:phone":"+41 31 991 74 74",
    "sg:postcode":"3018",
    "sg:province":"Bern",
    "wof:name":"Teppich Discount Neff",
    "wof:placetype":"venue"
},
  "geometry": {"coordinates":[7.3899049759,46.9419784546],"type":"Point"}
}