{
  "type": "Feature",
  "properties": {
    "addr:full":"Fohrh\u00f6lzlistrasse 14b Niederrohrdorf Aargau 5443",
    "addr:housenumber":"14b",
    "addr:postcode":"5443",
    "addr:street":"Fohrhoelzlistrasse",
    "iso:country":"CH",
    "sg:address":"Fohrh\u00f6lzlistrasse 14b",
    "sg:city":"Niederrohrdorf",
    "sg:orig_category":"Architektur U Ingenieurb\u00fcros",
    "sg:phone":"+41 56 496 64 14",
    "sg:postcode":"5443",
    "sg:province":"Aargau",
    "wof:name":"Ttm Mayer Andreas",
    "wof:placetype":"venue"
},
  "geometry": {"coordinates":[8.305062,47.427788],"type":"Point"}
}