{
  "type": "Feature",
  "properties": {
    "iso:country":"CH",
    "sg:address":"Sternenfeldstrasse 56",
    "sg:city":"Birsfelden",
    "sg:orig_category":"Herstellung von Drahtwaren",
    "sg:postcode":"4127",
    "sg:province":"Basel-Landschaft",
    "wof:name":"Lipka K., Dipl. Ing. Eth, Feindraht - Gewebe - Anwendungs-technologie Feinste Dr\u00e4hte; Handel, Herstellung, Beratung",
    "wof:placetype":"venue"
},
  "geometry": {"coordinates":[8.4377298355,47.419254303],"type":"Point"}
}