{
  "type": "Feature",
  "properties": {
    "iso:country":"CH",
    "sg:address":"Laufenbachstrasse 23",
    "sg:city":"Gossau",
    "sg:orig_category":"Software For Building Maintenance",
    "sg:phone":"+41 19366020",
    "sg:postcode":"8625",
    "sg:province":"Z\u00fcrich",
    "wof:name":"Sogema Vertrieb Gmbh",
    "wof:placetype":"venue"
},
  "geometry": {"coordinates":[8.758434,47.30669],"type":"Point"}
}