{
  "type": "Feature",
  "properties": {
    "iso:country":"CH",
    "sg:address":"Chemin Des Anciens-moulins 13 1009 Pully Case Postale 171",
    "sg:city":"Pully",
    "sg:orig_category":"D\u00e4mmung gegen K\u00e4lte, W\u00e4rme, Schall U Ersch\u00fctterung Stukkateurgewerbe, Gipserei U Verputzerei",
    "sg:phone":"+41 61 751 31 10",
    "sg:postcode":"1009",
    "sg:province":"Vaud",
    "wof:name":"Peter Brunner Gipsergesch\u00e4ft",
    "wof:placetype":"venue"
},
  "geometry": {"coordinates":[7.5978159904,47.4698562622],"type":"Point"}
}