{
  "type": "Feature",
  "properties": {
    "iso:country":"CH",
    "sg:address":"Maiackerstrasse 4 6345 Neuheim. Postfach",
    "sg:city":"Neuheim",
    "sg:orig_category":"RESTAURANTS: TEA-ROOMS",
    "sg:postcode":"6345",
    "sg:province":"Zug",
    "wof:name":"Xanido Ag Gastronomiebetriebe, Bes. Restaurant Krone",
    "wof:placetype":"venue"
},
  "geometry": {"coordinates":[8.574713707,47.2050094604],"type":"Point"}
}