{
  "type": "Feature",
  "properties": {
    "iso:country":"CH",
    "sg:address":"Bauenstrasse",
    "sg:city":"Bauen",
    "sg:orig_category":"RESTAURANTS: TEA-ROOMS",
    "sg:postcode":"6466",
    "sg:province":"Uri",
    "wof:name":"Michael Grob, Restaurant Seegarten",
    "wof:placetype":"venue"
},
  "geometry": {"coordinates":[8.5783348083,46.9332199097],"type":"Point"}
}