{
  "type": "Feature",
  "properties": {
    "iso:country":"CH",
    "sg:address":"Ch\u00e2let Curallaz",
    "sg:city":"Verbier",
    "sg:orig_category":"Eisenwaren Detailhandel",
    "sg:phone":"+41 27 771 32 39",
    "sg:postcode":"1936",
    "sg:province":"Valais",
    "wof:name":"Louis Michaud Quincaillerie Outillage",
    "wof:placetype":"venue"
},
  "geometry": {"coordinates":[7.2229619026,46.0967292786],"type":"Point"}
}