{
  "type": "Feature",
  "properties": {
    "iso:country":"CH",
    "sg:address":"Bankstrasse 22",
    "sg:city":"Glarus",
    "sg:orig_category":"Unclassifiable Establishments",
    "sg:phone":"+41 55 646 21 11",
    "sg:postcode":"8750",
    "sg:province":"Glarus",
    "wof:name":"Tamlik Ag",
    "wof:placetype":"venue"
},
  "geometry": {"coordinates":[9.0684680939,47.0405693054],"type":"Point"}
}