{
  "type": "Feature",
  "properties": {
    "iso:country":"CH",
    "sg:address":"Birmensdorferstrasse 541",
    "sg:city":"Z\u00fcrich",
    "sg:orig_category":"Herstellung von Teppichen Verlegen von Fliesen U Platten",
    "sg:phone":"+41 14635062",
    "sg:postcode":"8055",
    "sg:province":"Z\u00fcrich",
    "wof:name":"Leins Hans Ag",
    "wof:placetype":"venue"
},
  "geometry": {"coordinates":[8.4921636581,47.3667526245],"type":"Point"}
}