{
  "type": "Feature",
  "properties": {
    "iso:country":"CH",
    "sg:address":"S\u00e4ntisstrasse 4",
    "sg:city":"Rorschach",
    "sg:orig_category":"Einrahmungen",
    "sg:phone":"+41 71 841 18 88",
    "sg:postcode":"9400",
    "sg:province":"St. Gallen",
    "wof:name":"Willi Belz Einrahmungsgesch\u00e4ft",
    "wof:placetype":"venue"
},
  "geometry": {"coordinates":[9.484087944,47.4761047363],"type":"Point"}
}