{
  "type": "Feature",
  "properties": {
    "iso:country":"CH",
    "sg:address":"Judeb\u00f6mmlistrasse 523",
    "sg:city":"Ramsen",
    "sg:orig_category":"Interessenvertretungen",
    "sg:postcode":"8262",
    "sg:province":"Schaffhausen",
    "wof:name":"Stiftung Rebstock",
    "wof:placetype":"venue"
},
  "geometry": {"coordinates":[8.8169937134,47.7080574036],"type":"Point"}
}