{
  "type": "Feature",
  "properties": {
    "iso:country":"CH",
    "sg:address":"La Forge",
    "sg:city":"Villars-tiercelin",
    "sg:orig_category":"Bauspenglerei Dachdeckerei",
    "sg:phone":"+41 21 903 30 80",
    "sg:postcode":"1058",
    "sg:province":"Vaud",
    "wof:name":"Max Gisclon Ferblanterie,appareillage",
    "wof:placetype":"venue"
},
  "geometry": {"coordinates":[6.70441,46.624802],"type":"Point"}
}