{
  "type": "Feature",
  "properties": {
    "addr:full":"Sommerweg 41 Glarus Glarus 8750",
    "addr:housenumber":"41",
    "addr:postcode":"8750",
    "addr:street":"Sommerweg",
    "iso:country":"CH",
    "sg:address":"Sommerweg 41",
    "sg:city":"Glarus",
    "sg:orig_category":"Architektur U Ingenieurb\u00fcros",
    "sg:phone":"+41 41 310 16 38",
    "sg:postcode":"8750",
    "sg:province":"Glarus",
    "wof:name":"Architektur + Bauleitung Zweifel Kurt",
    "wof:placetype":"venue"
},
  "geometry": {"coordinates":[9.061333,47.048534],"type":"Point"}
}