{
  "type": "Feature",
  "properties": {
    "iso:country":"CH",
    "sg:address":"8422",
    "sg:city":"Pfungen",
    "sg:orig_category":"Schwimmb\u00e4der",
    "sg:phone":"+41 52 315 17 58",
    "sg:postcode":"8422",
    "sg:province":"Z\u00fcrich",
    "wof:name":"Schwimmbad",
    "wof:placetype":"venue"
},
  "geometry": {"coordinates":[8.64220047,47.5163269043],"type":"Point"}
}