{
  "type": "Feature",
  "properties": {
    "iso:country":"CH",
    "sg:address":"Hochstrasse 3 8200 Schaffhausen. Postfach",
    "sg:city":"Schaffhausen",
    "sg:orig_category":"Detailhandel mit B\u00fcchern, Zeitungen, Schreib U Papeteriewaren Detailhandel mit B\u00fcromaschinen U einri",
    "sg:phone":"+41 52 624 10 20",
    "sg:postcode":"8201",
    "sg:province":"Schaffhausen",
    "wof:name":"Ernst & Co",
    "wof:placetype":"venue"
},
  "geometry": {"coordinates":[8.634015,47.700485],"type":"Point"}
}