{
  "type": "Feature",
  "properties": {
    "iso:country":"CH",
    "sg:address":"Oberdorf",
    "sg:city":"M\u00fcswangen",
    "sg:orig_category":"Verarbeitung von Milch Verwertung von Milch",
    "sg:postcode":"6289",
    "sg:province":"Luzern",
    "wof:name":"K\u00e4sereigenossenschaft M\u00fcswangen",
    "wof:placetype":"venue"
},
  "geometry": {"coordinates":[8.2890148163,47.2383460999],"type":"Point"}
}