{
  "type": "Feature",
  "properties": {
    "iso:country":"CH",
    "sg:address":"Stalde",
    "sg:city":"Raron",
    "sg:orig_category":"Herstellung von sonstigen Holzwaren Selbst\u00e4ndige bildende K\u00fcnstler",
    "sg:phone":"+41 27 934 16 13",
    "sg:postcode":"3942",
    "sg:province":"Valais",
    "wof:name":"Peter Geisler Holzbildhauerei",
    "wof:placetype":"venue"
},
  "geometry": {"coordinates":[7.8005919456,46.3118972778],"type":"Point"}
}