{
  "type": "Feature",
  "properties": {
    "iso:country":"CH",
    "sg:address":"Seefeldstrasse 224",
    "sg:city":"Z\u00fcrich",
    "sg:orig_category":"Interessenvertretungen U sonstige Vereinigungen",
    "sg:phone":"+41 55 644 20 40",
    "sg:postcode":"8008",
    "sg:province":"Z\u00fcrich",
    "wof:name":"Tennisvereinigung Glarnerland",
    "wof:placetype":"venue"
},
  "geometry": {"coordinates":[9.0705604553,46.996421814],"type":"Point"}
}