{
  "type": "Feature",
  "properties": {
    "iso:country":"CH",
    "sg:address":"Hauptstrasse 7",
    "sg:city":"Goldach",
    "sg:orig_category":"Verwaltung von Immobilien",
    "sg:postcode":"9403",
    "sg:province":"St. Gallen",
    "wof:name":"Locher Immobilien-treuhand Ag",
    "wof:placetype":"venue"
},
  "geometry": {"coordinates":[9.4658880234,47.4748764038],"type":"Point"}
}