{
  "type": "Feature",
  "properties": {
    "iso:country":"CH",
    "sg:address":"Thurgauerstr. 40",
    "sg:city":"Z\u00fcrich",
    "sg:classifiers":[
        {
            "category":"Professional",
            "subcategory":"Printing & Photocopies",
            "type":"Services"
        }
    ],
    "sg:phone":"+41 4113086868",
    "sg:postcode":"8052",
    "sg:province":"Z\u00fcrich",
    "sg:tags":[
        "publishing"
    ],
    "wof:name":"Ltv Gelbeseiten Ag",
    "wof:placetype":"venue"
},
  "geometry": {"coordinates":[8.5550470352,47.4182434082],"type":"Point"}
}