{
  "type": "Feature",
  "properties": {
    "iso:country":"CH",
    "sg:address":"Rue Du L\u00e9man 12 Clarens 1820 Montreux. Postfach",
    "sg:city":"Clarens",
    "sg:orig_category":"Grosshandel mit keramischen Erzeugnissen, Glaswaren U Reinigungsmitteln",
    "sg:postcode":"1815",
    "sg:province":"Vaud",
    "wof:name":"Proglass, Yvan Orlando",
    "wof:placetype":"venue"
},
  "geometry": {"coordinates":[6.9105057716,46.4316940308],"type":"Point"}
}