{
  "type": "Feature",
  "properties": {
    "addr:full":"Im Baumacker Altnau Thurgau 8595",
    "addr:postcode":"8595",
    "addr:street":"Im Baumacker",
    "iso:country":"CH",
    "sg:address":"Im Baumacker",
    "sg:city":"Altnau",
    "sg:orig_category":"Allgemeiner Hoch U Tiefbau Allgemeiner Hochbau",
    "sg:phone":"+41 71 463 62 10",
    "sg:postcode":"8595",
    "sg:province":"Thurgau",
    "wof:name":"Egolf Hochbau Thurgau Ag",
    "wof:placetype":"venue"
},
  "geometry": {"coordinates":[9.366556,47.568897],"type":"Point"}
}