{
  "type": "Feature",
  "properties": {
    "iso:country":"CH",
    "sg:address":"Buzibachstrasse 31 6023 Rothenburg. Postfach 246",
    "sg:city":"Rothenburg",
    "sg:orig_category":"Detailhandel mit elektrischen Haushalts-,Radio U Fernsehger\u00e4ten sowie Musikinstrumenten Herstellung ",
    "sg:phone":"+41 41 280 96 66",
    "sg:postcode":"6023",
    "sg:province":"Luzern",
    "wof:name":"Ek Inter Ag",
    "wof:placetype":"venue"
},
  "geometry": {"coordinates":[8.2572145462,47.0911903381],"type":"Point"}
}