{
  "type": "Feature",
  "properties": {
    "iso:country":"CH",
    "sg:address":"Rue Pierre -aeby 223",
    "sg:city":"Fribourg",
    "sg:orig_category":"RESTAURANTS: TEA-ROOMS",
    "sg:postcode":"1700",
    "sg:province":"Fribourg",
    "wof:name":"Aeby Alphonse.",
    "wof:placetype":"venue"
},
  "geometry": {"coordinates":[7.155395031,46.8156280518],"type":"Point"}
}