{
  "type": "Feature",
  "properties": {
    "iso:country":"CH",
    "sg:address":"Avenue De La Concorde 29 1022 Chavannes-renens. Postfach 14",
    "sg:city":"Chavannes-renens",
    "sg:orig_category":"Verlagsgewerbe",
    "sg:phone":"+41 79 210 38 63",
    "sg:postcode":"1022",
    "sg:province":"Vaud",
    "wof:name":"Ducret Jean Sa Edition D'un Magazine Consacr\u00e9 \u00e0 L'h\u00e9licopt\u00e8re Etc",
    "wof:placetype":"venue"
},
  "geometry": {"coordinates":[6.5783991814,46.5283851624],"type":"Point"}
}