{
  "type": "Feature",
  "properties": {
    "iso:country":"CH",
    "sg:address":"Zentralstrasse 20",
    "sg:city":"Ebikon",
    "sg:orig_category":"Detailhandel mit Fleisch U Fleischwaren Sonstiger Fachdetailhandel mit Nahrungsmitteln, Getr\u00e4nken U ",
    "sg:phone":"+41 41 440 11 66",
    "sg:postcode":"6030",
    "sg:province":"Luzern",
    "wof:name":"Doswald Spezialit\u00e4ten",
    "wof:placetype":"venue"
},
  "geometry": {"coordinates":[8.3415021896,47.0815505981],"type":"Point"}
}