{
  "type": "Feature",
  "properties": {
    "addr:full":"Avenue Louis-casa\u00ef 84 Cointrin Gen\u00e8ve 1216",
    "addr:housenumber":"84",
    "addr:postcode":"1216",
    "addr:street":"Avenue Louis-Casai\u0308",
    "iso:country":"CH",
    "sg:address":"Avenue Louis-casa\u00ef 84",
    "sg:city":"Cointrin",
    "sg:orig_category":"Datenverarbeitungsdienste Softwareentwicklung U beratung",
    "sg:phone":"+41 22 733 18 58",
    "sg:postcode":"1216",
    "sg:province":"Gen\u00e8ve",
    "wof:name":"Hummingbird Communications Sa",
    "wof:placetype":"venue"
},
  "geometry": {"coordinates":[6.105859,46.22612],"type":"Point"}
}