{
  "type": "Feature",
  "properties": {
    "iso:country":"CH",
    "sg:address":"Kasernenstrasse 41",
    "sg:city":"Liestal",
    "sg:orig_category":"Non-Classified Establishments",
    "sg:postcode":"4410",
    "sg:province":"Basel-Landschaft",
    "wof:name":"Ptz Stiftung P\u00e4dagogisch-therapeutisches Zentrum F\u00fcr Kinder, Baselland",
    "wof:placetype":"venue"
},
  "geometry": {"coordinates":[7.7399730682,47.4813728333],"type":"Point"}
}