{
  "type": "Feature",
  "properties": {
    "iso:country":"CH",
    "sg:address":"Wylerringstrasse 77 3014 Bern. Postfach",
    "sg:city":"Bern",
    "sg:orig_category":"Sonstige mit der Informatik verbundene T\u00e4tigkeiten",
    "sg:phone":"+41 56 470 07 30",
    "sg:postcode":"3005",
    "sg:province":"Bern",
    "wof:name":"Get-it Gmbh",
    "wof:placetype":"venue"
},
  "geometry": {"coordinates":[8.277545929,47.4615097046],"type":"Point"}
}