{
  "type": "Feature",
  "properties": {
    "iso:country":"CH",
    "sg:address":"Holzh\u00e4usernstrasse 32",
    "sg:city":"Rotkreuz",
    "sg:orig_category":"Detailhandel Handel mit Motorr\u00e4dern, Teilen U Zubeh\u00f6r Instandhaltung U Reparatur von Motorr\u00e4dern Rep",
    "sg:postcode":"6343",
    "sg:province":"Zug",
    "wof:name":"Harywood Gmbh Harley-davidson Werkstatt",
    "wof:placetype":"venue"
},
  "geometry": {"coordinates":[8.4660310745,47.1341400146],"type":"Point"}
}