{
  "type": "Feature",
  "properties": {
    "iso:country":"CH",
    "sg:address":"Chemin Clair-matin 5",
    "sg:city":"Petit-lancy",
    "sg:orig_category":"Sportvereine Ballsport Basketball",
    "sg:phone":"+41 22 792 01 41",
    "sg:postcode":"1213",
    "sg:province":"Gen\u00e8ve",
    "wof:name":"Lancy Basket",
    "wof:placetype":"venue"
},
  "geometry": {"coordinates":[6.112994194,46.1871337891],"type":"Point"}
}