{
  "type": "Feature",
  "properties": {
    "iso:country":"CH",
    "sg:address":"Avenue Fran\u00e7ois-borel 14",
    "sg:city":"Cortaillod",
    "sg:orig_category":"Sanit\u00e4r U Heizungsinstallation Sanit\u00e4r, Heizungs U L\u00fcftungsinstallation",
    "sg:phone":"+41 32 842 18 04",
    "sg:postcode":"2016",
    "sg:province":"Neuch\u00e2tel",
    "wof:name":"Fasel Willy",
    "wof:placetype":"venue"
},
  "geometry": {"coordinates":[6.8538560867,46.9467277527],"type":"Point"}
}