{
  "type": "Feature",
  "properties": {
    "iso:country":"CH",
    "sg:address":"Brauerstrasse 97",
    "sg:city":"Z\u00fcrich",
    "sg:orig_category":"Sicherheitsdienste",
    "sg:phone":"+41 12410225",
    "sg:postcode":"8004",
    "sg:province":"Z\u00fcrich",
    "wof:name":"P.s.s. Puschel Security Service",
    "wof:placetype":"venue"
},
  "geometry": {"coordinates":[8.523686409,47.3794555664],"type":"Point"}
}