{
  "type": "Feature",
  "properties": {
    "iso:country":"CH",
    "sg:address":"Seestrasse 16 8712 St\u00e4fa. Postfach",
    "sg:city":"St\u00e4fa",
    "sg:orig_category":"Zimmerei, Dachdeckerei, Bauspenglerei U Abdichtung",
    "sg:postcode":"8712",
    "sg:province":"Z\u00fcrich",
    "wof:name":"Zimmerei & Holzbau M\u00fcller Peter",
    "wof:placetype":"venue"
},
  "geometry": {"coordinates":[8.7156610489,47.2397880554],"type":"Point"}
}