{
  "type": "Feature",
  "properties": {
    "iso:country":"CH",
    "sg:address":"Zollstrasse",
    "sg:city":"Trasadingen",
    "sg:orig_category":"Vermietung U Verpachtung von eigenen Immobilien",
    "sg:postcode":"8219",
    "sg:province":"Schaffhausen",
    "wof:name":"Tanner Liegenschaften Ag",
    "wof:placetype":"venue"
},
  "geometry": {"coordinates":[8.4349298477,47.6650390625],"type":"Point"}
}