{
  "type": "Feature",
  "properties": {
    "iso:country":"CH",
    "sg:address":"Bahnhofstr. 37",
    "sg:city":"Utzenstorf",
    "sg:classifiers":[
        {
            "category":"Wholesale",
            "subcategory":"Machinery & Supplies",
            "type":"Manufacturing & Wholesale Goods"
        }
    ],
    "sg:phone":"+41 34 422 32 82",
    "sg:postcode":"3427",
    "sg:province":"Bern",
    "sg:tags":[
        "food",
        "processing",
        "-",
        "machine",
        "equipment",
        "engineering",
        "mechanical"
    ],
    "wof:name":"Siback Ag B\u00c4ckereitechnik",
    "wof:placetype":"venue"
},
  "geometry": {"coordinates":[7.553882122,47.1281051636],"type":"Point"}
}