{
  "type": "Feature",
  "properties": {
    "iso:country":"CH",
    "sg:address":"Route Du Prado Crans-sur-sierre 1978 Lens. Postfach",
    "sg:city":"Crans-sur-sierre",
    "sg:orig_category":"Fachdetailhandel in Verkaufsr\u00e4umen",
    "sg:postcode":"3963",
    "sg:province":"Valais",
    "wof:name":"Merkli Peter.",
    "wof:placetype":"venue"
},
  "geometry": {"coordinates":[8.8433771133,47.3004837036],"type":"Point"}
}