{
  "type": "Feature",
  "properties": {
    "iso:country":"CH",
    "sg:address":"Schlossm\u00fchlestrasse 7-9",
    "sg:city":"Frauenfeld",
    "sg:orig_category":"Datenverarbeitungsdienste",
    "sg:phone":"+41 52 724 22 97",
    "sg:postcode":"8510",
    "sg:province":"Thurgau",
    "wof:name":"Amt F\u00fcr Informatik",
    "wof:placetype":"venue"
},
  "geometry": {"coordinates":[8.897569,47.55455],"type":"Point"}
}