{
  "type": "Feature",
  "properties": {
    "iso:country":"CH",
    "sg:address":"Stauseeweg 2 4203 Grellingen. Postfach",
    "sg:city":"Grellingen",
    "sg:orig_category":"Sanit\u00e4r U Heizungsinstallation Sonstiger spezialisierter Hoch U Tiefbau",
    "sg:phone":"+41 79 446 49 67",
    "sg:postcode":"4203",
    "sg:province":"Basel-Landschaft",
    "wof:name":"Kr\u00fcger & Co. Ag Zweigniederlassung Grellingen",
    "wof:placetype":"venue"
},
  "geometry": {"coordinates":[7.5795102119,47.4394493103],"type":"Point"}
}