{
  "type": "Feature",
  "properties": {
    "iso:country":"CH",
    "sg:address":"Le Grand-chemin 104",
    "sg:city":"Epalinges",
    "sg:orig_category":"Softwareentwicklung U beratung",
    "sg:postcode":"1066",
    "sg:province":"Vaud",
    "wof:name":"Lemcad, Lemqadem Sa\u00efd",
    "wof:placetype":"venue"
},
  "geometry": {"coordinates":[6.6842470169,46.5532951355],"type":"Point"}
}