{
  "type": "Feature",
  "properties": {
    "iso:country":"CH",
    "sg:address":"Ebnaterstrasse 58",
    "sg:city":"Ebnat",
    "sg:orig_category":"Detailhandel mit M\u00f6beln U Haushaltsgegenst\u00e4nden Verlegen von Fussboden",
    "sg:phone":"+41 71 993 18 93",
    "sg:postcode":"9642",
    "sg:province":"St. Gallen",
    "wof:name":"Bollhalder Josef",
    "wof:placetype":"venue"
},
  "geometry": {"coordinates":[9.1281423569,47.2590446472],"type":"Point"}
}