{
  "type": "Feature",
  "properties": {
    "iso:country":"CH",
    "sg:address":"Dorfstrasse 47 8712 St\u00e4fa. Postfach",
    "sg:city":"St\u00e4fa",
    "sg:orig_category":"Instandhaltung U Reparatur von Automobilen",
    "sg:postcode":"8712",
    "sg:province":"Z\u00fcrich",
    "wof:name":"Vesna Handels Gmbh",
    "wof:placetype":"venue"
},
  "geometry": {"coordinates":[9.6348695755,47.4514694214],"type":"Point"}
}