{
  "type": "Feature",
  "properties": {
    "iso:country":"CH",
    "sg:address":"4625",
    "sg:city":"Oberbuchsiten",
    "sg:orig_category":"Vereine Gesang",
    "sg:postcode":"4625",
    "sg:province":"Solothurn",
    "wof:name":"Gemischter Chor",
    "wof:placetype":"venue"
},
  "geometry": {"coordinates":[7.7662849426,47.3133049011],"type":"Point"}
}