{
  "type": "Feature",
  "properties": {
    "iso:country":"CH",
    "sg:address":"Via Dott. G. Polar 8",
    "sg:city":"Breganzona",
    "sg:orig_category":"Zahnarztpraxen",
    "sg:phone":"+41 91 966 16 66",
    "sg:postcode":"6932",
    "sg:province":"Ticino",
    "wof:name":"Dott. Med. Dent. Carlo Censi Dentista",
    "wof:placetype":"venue"
},
  "geometry": {"coordinates":[8.934513092,46.0101737976],"type":"Point"}
}