{
  "type": "Feature",
  "properties": {
    "iso:country":"CH",
    "sg:address":"Munzenriet 9658 Wildhaus. Postfach 851",
    "sg:city":"Wildhaus",
    "sg:orig_category":"Detailhandel mit Zeitungen U Zeitschriften Kioske",
    "sg:phone":"+41 71 999 16 11",
    "sg:postcode":"9658",
    "sg:province":"St. Gallen",
    "wof:name":"Kunsteisbahn Kiosk",
    "wof:placetype":"venue"
},
  "geometry": {"coordinates":[9.3430919647,47.2009162903],"type":"Point"}
}