{
  "type": "Feature",
  "properties": {
    "iso:country":"CH",
    "sg:address":"Adlerstrasse 21",
    "sg:city":"Magden",
    "sg:orig_category":"Grosshandel mit H\u00e4uten, Fellen U Leder Herstellung von Uhren",
    "sg:phone":"+41 61 841 03 33",
    "sg:postcode":"4312",
    "sg:province":"Aargau",
    "wof:name":"Oesch Gmbh",
    "wof:placetype":"venue"
},
  "geometry": {"coordinates":[7.8132238388,47.5260391235],"type":"Point"}
}