{
  "type": "Feature",
  "properties": {
    "iso:country":"CH",
    "sg:address":"Wolfackerweg 442",
    "sg:city":"D\u00fcrren\u00e4sch",
    "sg:orig_category":"G\u00fcterbef\u00f6rderung im Strassenverkehr",
    "sg:phone":"+41 62 777 39 19",
    "sg:postcode":"5724",
    "sg:province":"Aargau",
    "wof:name":"R\u00fcegger Susan Transport Gmbh",
    "wof:placetype":"venue"
},
  "geometry": {"coordinates":[8.1686658859,47.3170928955],"type":"Point"}
}