{
  "type": "Feature",
  "properties": {
    "iso:country":"CH",
    "sg:address":"Cademario Via 6934 Bioggio. Postfach",
    "sg:city":"Bioggio",
    "sg:orig_category":"Fachdetailhandel in Verkaufsr\u00e4umen",
    "sg:phone":"+41 33 222 90 65",
    "sg:postcode":"6934",
    "sg:province":"Ticino",
    "wof:name":"Pellemoto Di Crivelli-canzali Pamela",
    "wof:placetype":"venue"
},
  "geometry": {"coordinates":[8.9082527161,46.0169639587],"type":"Point"}
}