{
  "type": "Feature",
  "properties": {
    "iso:country":"CH",
    "sg:address":"Erlenmatt 2 8807 Freienbach. Postfach",
    "sg:city":"Freienbach",
    "sg:orig_category":"Allgemeiner Hoch U Tiefbau",
    "sg:postcode":"8807",
    "sg:province":"Schwyz",
    "wof:name":"Fm Ag",
    "wof:placetype":"venue"
},
  "geometry": {"coordinates":[8.863666,47.190239],"type":"Point"}
}