{
  "type": "Feature",
  "properties": {
    "iso:country":"CH",
    "sg:address":"Route Andr\u00e9-piller 45 1720 Corminboeuf Case Postale 75",
    "sg:city":"Freiburg",
    "sg:orig_category":"Sanit\u00e4rinstallation Wasserversorgung",
    "sg:phone":"+41 26 466 70 80",
    "sg:postcode":"1700",
    "sg:province":"Fribourg",
    "wof:name":"Entretec Sa",
    "wof:placetype":"venue"
},
  "geometry": {"coordinates":[7.11480093,46.8114700317],"type":"Point"}
}