{
  "type": "Feature",
  "properties": {
    "iso:country":"CH",
    "sg:address":"Hauptstrasse 37",
    "sg:city":"Zunzgen",
    "sg:orig_category":"Gartenbau",
    "sg:phone":"+41 61 971 61 88",
    "sg:postcode":"4455",
    "sg:province":"Basel-Landschaft",
    "wof:name":"J\u00f6rg & Heidi Wiesner Gartenbau",
    "wof:placetype":"venue"
},
  "geometry": {"coordinates":[7.8078279495,47.4527359009],"type":"Point"}
}