{
  "type": "Feature",
  "properties": {
    "iso:country":"CH",
    "sg:address":"Sommeraustrasse 2 8634 Hombrechtikon. Postfach 212",
    "sg:city":"Hombrechtikon",
    "sg:orig_category":"HERSTELLUNG VON GER\u00c4TEN DER ELEKTRIZIT\u00c4TSERZEUGUNG, -VERTEILUNG U.\u00c4 Herstellung von sonstigen Produk",
    "sg:phone":"+41 26 912 96 96",
    "sg:postcode":"8634",
    "sg:province":"Z\u00fcrich",
    "wof:name":"Saint-gobain Quartz Sa",
    "wof:placetype":"venue"
},
  "geometry": {"coordinates":[7.0663948059,46.6079711914],"type":"Point"}
}