{
  "type": "Feature",
  "properties": {
    "iso:country":"CH",
    "sg:address":"Hemschlenstrasse 5 6006 Luzern. Postfach",
    "sg:city":"Luzern",
    "sg:orig_category":"Unternehmensberatung",
    "sg:phone":"+41 41 370 57 56",
    "sg:postcode":"6003",
    "sg:province":"Luzern",
    "wof:name":"Simioni Giovanni, Unternehmensberatung",
    "wof:placetype":"venue"
},
  "geometry": {"coordinates":[8.3525419235,47.0609474182],"type":"Point"}
}