{
  "type": "Feature",
  "properties": {
    "iso:country":"CH",
    "sg:address":"1138",
    "sg:city":"Villars-sous-yens",
    "sg:orig_category":"Gemeindeverwaltungen",
    "sg:phone":"+41 26 402 04 74",
    "sg:postcode":"1138",
    "wof:name":"Administration Communale De Villars-sur-gl\u00e2ne",
    "wof:placetype":"venue"
},
  "geometry": {"coordinates":[4.3530302048,45.4674606323],"type":"Point"}
}