{
  "type": "Feature",
  "properties": {
    "iso:country":"CH",
    "sg:address":"Bahnhofstrasse 33 9230 Flawil. Postfach",
    "sg:city":"Flawil",
    "sg:orig_category":"RESTAURANTS: TEA-ROOMS",
    "sg:phone":"+41 17840618",
    "sg:postcode":"9230",
    "sg:province":"St. Gallen",
    "wof:name":"Pizzeria St.verena, Ruch Erika Und Balzarolo Marco",
    "wof:placetype":"venue"
},
  "geometry": {"coordinates":[8.7341480255,47.1973953247],"type":"Point"}
}