{
  "type": "Feature",
  "properties": {
    "iso:country":"CH",
    "sg:address":"Rosengartenstrasse 7",
    "sg:city":"Hochdorf",
    "sg:orig_category":"Sonstiges Gesundheitswesen",
    "sg:phone":"+41 41 910 23 88",
    "sg:postcode":"6280",
    "sg:province":"Luzern",
    "wof:name":"Krankenmobilienmagazin Des Samaritervereins Frau Pia Muff",
    "wof:placetype":"venue"
},
  "geometry": {"coordinates":[8.2949008942,47.1627006531],"type":"Point"}
}