{
  "type": "Feature",
  "properties": {
    "iso:country":"CH",
    "sg:address":"S\u00e4ntisstrasse 16",
    "sg:city":"Rorschach",
    "sg:orig_category":"Non-Classified Establishments",
    "sg:postcode":"9400",
    "sg:province":"St. Gallen",
    "wof:name":"Roland Br\u00e4ndle Siebdruck",
    "wof:placetype":"venue"
},
  "geometry": {"coordinates":[9.4823379517,47.4766654968],"type":"Point"}
}