{
  "type": "Feature",
  "properties": {
    "iso:country":"CH",
    "sg:address":"Industriestrasse 6260 Reiden. Postfach",
    "sg:city":"Bannwil",
    "sg:orig_category":"Sonstiger Detailhandel mit Metallwaren, Anstrichmitteln, Glaswaren, Bau U Heimwerkerbedarf",
    "sg:phone":"+41 62 749 23 23",
    "sg:postcode":"4913",
    "sg:province":"Bern",
    "wof:name":"Himag Holzwaren + Isoliermaterial Ag",
    "wof:placetype":"venue"
},
  "geometry": {"coordinates":[7.9653100967,47.2532463074],"type":"Point"}
}