{
  "type": "Feature",
  "properties": {
    "iso:country":"CH",
    "sg:address":"Mattenberg",
    "sg:city":"Sumiswald",
    "sg:orig_category":"Gartenbau Geb\u00e4ude, Wohnungsreinigung",
    "sg:phone":"+41 34 431 18 21",
    "sg:postcode":"3454",
    "sg:province":"Bern",
    "wof:name":"Klaus-emanuel Jost Areal-& Gr\u00fcnfl\u00e4chenpflege",
    "wof:placetype":"venue"
},
  "geometry": {"coordinates":[7.7318639755,47.0416870117],"type":"Point"}
}