{
  "type": "Feature",
  "properties": {
    "iso:country":"CH",
    "sg:address":"Midi Rue Du 20 1003 Lausanne. Postfach",
    "sg:city":"Lausanne",
    "sg:orig_category":"Detailhandel mit Antiquit\u00e4ten U Gebrauchtwaren in Verkaufsr\u00e4umen",
    "sg:postcode":"1003",
    "sg:province":"Vaud",
    "wof:name":"Arcas Antiquit\u00e9s, Borter Eliane Commerce D'antiquit\u00e9s",
    "wof:placetype":"venue"
},
  "geometry": {"coordinates":[6.632335,46.519596],"type":"Point"}
}