{
  "type": "Feature",
  "properties": {
    "iso:country":"CH",
    "sg:address":"Chemin De La Vieille-ecole 20",
    "sg:city":"Satigny",
    "sg:orig_category":"Grosshandel mit Holz U Baustoffen Herstellung von Betonerzeugnissen f\u00fcr den Bau",
    "sg:phone":"+41 22 753 14 22",
    "sg:postcode":"1242",
    "sg:province":"Gen\u00e8ve",
    "wof:name":"Promat\u00e9riau",
    "wof:placetype":"venue"
},
  "geometry": {"coordinates":[6.0465478897,46.198928833],"type":"Point"}
}