{
  "type": "Feature",
  "properties": {
    "iso:country":"CH",
    "sg:address":"L\u00e4ngenstrasse 26",
    "sg:city":"Rudolfstetten",
    "sg:orig_category":"Vermietung U Verpachtung von eigenen Immobilien Vermittlung von Immobilien",
    "sg:phone":"+41 79 335 00 00",
    "sg:postcode":"8964",
    "sg:province":"Aargau",
    "wof:name":"Bodomus Immobilien Gmbh",
    "wof:placetype":"venue"
},
  "geometry": {"coordinates":[8.3814878464,47.372795105],"type":"Point"}
}