{
  "type": "Feature",
  "properties": {
    "iso:country":"CH",
    "sg:address":"Oberfeldstrasse 7",
    "sg:city":"Gerlafingen",
    "sg:orig_category":"Sonstiger spezialisierter Hoch U Tiefbau Spezieller Tiefbau",
    "sg:postcode":"4563",
    "sg:province":"Solothurn",
    "wof:name":"Alkam-guignet",
    "wof:placetype":"venue"
},
  "geometry": {"coordinates":[7.575193882,47.1677818298],"type":"Point"}
}