{
  "type": "Feature",
  "properties": {
    "iso:country":"CH",
    "sg:address":"Rue Des Terreaux-de-temple 4",
    "sg:city":"Genf",
    "sg:orig_category":"Rechtsberatung",
    "sg:phone":"+41 41 747 42 22",
    "sg:postcode":"1200",
    "sg:province":"Gen\u00e8ve",
    "wof:name":"Kipling Switzerland Ag",
    "wof:placetype":"venue"
},
  "geometry": {"coordinates":[6.1400208473,46.2060317993],"type":"Point"}
}