{
  "type": "Feature",
  "properties": {
    "iso:country":"CH",
    "sg:address":"Zurigo Via 1",
    "sg:city":"Lugano",
    "sg:orig_category":"Stukkateurgewerbe, Gipserei U Verputzerei",
    "sg:phone":"+41 79 207 02 73",
    "sg:postcode":"6900",
    "sg:province":"Ticino",
    "wof:name":"Tigips Di Jovanovic Velibor",
    "wof:placetype":"venue"
},
  "geometry": {"coordinates":[8.9562759399,46.0112724304],"type":"Point"}
}