{
  "type": "Feature",
  "properties": {
    "iso:country":"CH",
    "sg:address":"Hofmattstrasse 16 9602 Bazenheid. Postfach",
    "sg:city":"Bazenheid",
    "sg:orig_category":"Handel mit Automobilen",
    "sg:phone":"+41 71 931 61 73",
    "sg:postcode":"9602",
    "sg:province":"St. Gallen",
    "wof:name":"Topoc Autohandels Gmbh",
    "wof:placetype":"venue"
},
  "geometry": {"coordinates":[9.0609579086,47.4105072021],"type":"Point"}
}