{
  "type": "Feature",
  "properties": {
    "iso:country":"CH",
    "sg:address":"Denkmalstrasse 17",
    "sg:city":"Luzern",
    "sg:orig_category":"Herstellung U Veredlung von sonstigem Glas Herstellung von Hohlglas",
    "sg:phone":"+41 41 410 49 54",
    "sg:postcode":"6006",
    "sg:province":"Luzern",
    "wof:name":"Panozzo G. Neon Arte Lux",
    "wof:placetype":"venue"
},
  "geometry": {"coordinates":[8.309887886,47.0586929321],"type":"Point"}
}