{
  "type": "Feature",
  "properties": {
    "iso:country":"CH",
    "sg:address":"Alte Badenerstrasse 10d",
    "sg:city":"Neerach",
    "sg:orig_category":"Grosshandel mit Holz U Baustoffen",
    "sg:phone":"+41 18583234",
    "sg:postcode":"8173",
    "sg:province":"Z\u00fcrich",
    "wof:name":"Alltec Baubedarf Zimmermann W.",
    "wof:placetype":"venue"
},
  "geometry": {"coordinates":[8.4684505463,47.5113372803],"type":"Point"}
}