{
  "type": "Feature",
  "properties": {
    "iso:country":"CH",
    "sg:address":"Route D'oulteret 42",
    "sg:city":"Nyon",
    "sg:classifiers":[
        {
            "category":"Arena",
            "subcategory":"Sports Club",
            "type":"Entertainment"
        }
    ],
    "sg:phone":"+41 22 362 77 11",
    "sg:postcode":"1260",
    "sg:province":"Vaud",
    "sg:tags":[
        "karate",
        "judo",
        "sportvereine"
    ],
    "wof:name":"Judo-club Nyon Karat\u00e9 Ju-jitsu",
    "wof:placetype":"venue"
},
  "geometry": {"coordinates":[6.2390799522,46.382358551],"type":"Point"}
}