{
  "type": "Feature",
  "properties": {
    "addr:full":"Lyssachstrasse 13 Burgdorf Bern 3400",
    "addr:housenumber":"13",
    "addr:postcode":"3400",
    "addr:street":"Lyssachstrasse",
    "iso:country":"CH",
    "sg:address":"Lyssachstrasse 13",
    "sg:city":"Burgdorf",
    "sg:classifiers":[
        {
            "category":"Manufacturing",
            "subcategory":"Printing",
            "type":"Manufacturing & Wholesale Goods"
        }
    ],
    "sg:phone":"+41 34 424 04 15",
    "sg:postcode":"3400",
    "sg:province":"Bern",
    "sg:tags":[
        "house",
        "book"
    ],
    "wof:name":"Druckkunst Gmbh",
    "wof:placetype":"venue"
},
  "geometry": {"coordinates":[7.623681,47.058487],"type":"Point"}
}