{
  "type": "Feature",
  "properties": {
    "iso:country":"CH",
    "sg:address":"Luzernerstrasse 4",
    "sg:city":"Zofingen",
    "sg:orig_category":"P\u00e9dicure",
    "sg:phone":"+41 61 711 78 12",
    "sg:postcode":"4800",
    "sg:province":"Aargau",
    "wof:name":"Sonja Frei P\u00e9dicure & Kosmetik",
    "wof:placetype":"venue"
},
  "geometry": {"coordinates":[7.5855488777,47.4916763306],"type":"Point"}
}