{
  "type": "Feature",
  "properties": {
    "iso:country":"CH",
    "sg:address":"Avenue De France 33",
    "sg:city":"Lausanne",
    "sg:orig_category":"Datenverarbeitungsdienste Softwareentwicklung U beratung",
    "sg:phone":"+41 21 661 16 75",
    "sg:postcode":"1004",
    "sg:province":"Vaud",
    "wof:name":"Colombus",
    "wof:placetype":"venue"
},
  "geometry": {"coordinates":[6.620565,46.526295],"type":"Point"}
}