{
  "type": "Feature",
  "properties": {
    "iso:country":"CH",
    "sg:address":"M\u00fchlegasse 18",
    "sg:city":"Baar",
    "sg:classifiers":[
        {
            "category":"Professional",
            "subcategory":"Advertising",
            "type":"Services"
        }
    ],
    "sg:phone":"+41 41 768 00 40",
    "sg:postcode":"6340",
    "sg:province":"Zug",
    "sg:tags":[
        "communication",
        "medium"
    ],
    "wof:name":"Gabriel Druck & Direktwerbung",
    "wof:placetype":"venue"
},
  "geometry": {"coordinates":[8.526473,47.199211],"type":"Point"}
}