{
  "type": "Feature",
  "properties": {
    "iso:country":"CH",
    "sg:address":"Burgstrasse 8",
    "sg:city":"Ettingen",
    "sg:orig_category":"Rechtsberatung",
    "sg:postcode":"4107",
    "sg:province":"Basel-Landschaft",
    "wof:name":"Ventocilla Patent Ag",
    "wof:placetype":"venue"
},
  "geometry": {"coordinates":[7.5431928635,47.4833259583],"type":"Point"}
}