{
  "type": "Feature",
  "properties": {
    "iso:country":"CH",
    "sg:address":"Im Wihler 5",
    "sg:city":"B\u00fcttenhardt",
    "sg:orig_category":"Zimmerei, Dachdeckerei, Bauspenglerei U Abdichtung",
    "sg:phone":"+41 91 858 12 58",
    "sg:postcode":"8236",
    "sg:province":"Schaffhausen",
    "wof:name":"Berger Carpenteria Sa",
    "wof:placetype":"venue"
},
  "geometry": {"coordinates":[8.9789495468,46.1534805298],"type":"Point"}
}