{
  "type": "Feature",
  "properties": {
    "iso:country":"CH",
    "sg:address":"Geisacker 2",
    "sg:city":"Basadingen",
    "sg:orig_category":"Hobel U Holzimpr\u00e4gnierwerke S\u00e4ge, Hobel U Holzimpr\u00e4gnierwerke",
    "sg:phone":"+41 79 635 75 88",
    "sg:postcode":"8254",
    "sg:province":"Thurgau",
    "wof:name":"Krebs Fritz, Holzkonservierung",
    "wof:placetype":"venue"
},
  "geometry": {"coordinates":[8.7429838181,47.6676597595],"type":"Point"}
}