{
  "type": "Feature",
  "properties": {
    "iso:country":"CH",
    "sg:address":"Via Giuseppe Petrini 5",
    "sg:city":"Lugano",
    "sg:classifiers":[
        {
            "category":"Home & Garden",
            "subcategory":"Furniture",
            "type":"Retail Goods"
        }
    ],
    "sg:phone":"+41 91 922 09 69",
    "sg:postcode":"6900",
    "sg:province":"Ticino",
    "sg:tags":[
        "small",
        "occasional"
    ],
    "wof:name":"Tamborini Fabbrica Mobili Sa Fratelli",
    "wof:placetype":"venue"
},
  "geometry": {"coordinates":[8.9558458328,46.0136795044],"type":"Point"}
}