{
  "type": "Feature",
  "properties": {
    "iso:country":"CH",
    "sg:address":"Maienstrasse 8",
    "sg:city":"Z\u00fcrich",
    "sg:orig_category":"Chemische Reinigung",
    "sg:phone":"+41 13119339",
    "sg:postcode":"8050",
    "sg:province":"Z\u00fcrich",
    "wof:name":"Walter A. F\u00fcrst Chemische Reinigung",
    "wof:placetype":"venue"
},
  "geometry": {"coordinates":[8.529331,47.409534],"type":"Point"}
}