{
  "type": "Feature",
  "properties": {
    "iso:country":"CH",
    "sg:address":"Winkelriedstrasse 52 8203 Schaffhausen. Postfach 16",
    "sg:city":"Schaffhausen",
    "sg:orig_category":"Pensionskassen",
    "sg:phone":"+41 52 624 60 98",
    "sg:postcode":"8203",
    "sg:province":"Schaffhausen",
    "wof:name":"Grieshaber-stiftung",
    "wof:placetype":"venue"
},
  "geometry": {"coordinates":[8.658039093,47.6996917725],"type":"Point"}
}