{
  "type": "Feature",
  "properties": {
    "addr:full":"B\u00fcndtenweg 36b Binningen Basel-Landschaft 4102",
    "addr:housenumber":"36b",
    "addr:postcode":"4102",
    "addr:street":"Buendtenweg",
    "iso:country":"CH",
    "sg:address":"B\u00fcndtenweg 36b",
    "sg:city":"Binningen",
    "sg:orig_category":"Dachdeckerei Zimmerei, Dachdeckerei, Bauspenglerei U Abdichtung",
    "sg:phone":"+41 61 421 01 20",
    "sg:postcode":"4102",
    "sg:province":"Basel-Landschaft",
    "wof:name":"Bettinger, Holzbau & Bedachungen",
    "wof:placetype":"venue"
},
  "geometry": {"coordinates":[7.568992,47.542515],"type":"Point"}
}