{
  "type": "Feature",
  "properties": {
    "iso:country":"CH",
    "sg:address":"Etzelstrasse 5 8800 Thalwil. Postfach",
    "sg:city":"Thalwil",
    "sg:orig_category":"Erschliessung von Grundst\u00fccken",
    "sg:phone":"+41 81 756 31 58",
    "sg:postcode":"8801",
    "sg:province":"Z\u00fcrich",
    "wof:name":"Baugenossenschaft Swebahov",
    "wof:placetype":"venue"
},
  "geometry": {"coordinates":[9.4756231308,47.1679115295],"type":"Point"}
}