{
  "type": "Feature",
  "properties": {
    "iso:country":"CH",
    "sg:address":"Kasernenstrasse 11",
    "sg:city":"Chur",
    "sg:orig_category":"RESTAURANTS: TEA-ROOMS",
    "sg:postcode":"7000",
    "sg:province":"Graubunden",
    "wof:name":"Dietel Hans Dieter",
    "wof:placetype":"venue"
},
  "geometry": {"coordinates":[9.5258903503,46.8476486206],"type":"Point"}
}