{
  "type": "Feature",
  "properties": {
    "addr:full":"Antoine-de-chandieu Chemin 1 1000 Lausanne. Postfach Lausanne Vaud 1000",
    "addr:postcode":"1000 lausanne. postfach;1000",
    "addr:street":"Chemin 1",
    "iso:country":"CH",
    "sg:address":"Antoine-de-chandieu Chemin 1 1000 Lausanne. Postfach",
    "sg:city":"Lausanne",
    "sg:orig_category":"Datenverarbeitungsdienste",
    "sg:postcode":"1000",
    "sg:province":"Vaud",
    "wof:name":"Hec Analysing Sa, Port-louis, Succursale De Lausanne D\u00e9velopp. De Logiciels Etc",
    "wof:placetype":"venue"
},
  "geometry": {"coordinates":[6.694775,46.554588],"type":"Point"}
}