{
  "type": "Feature",
  "properties": {
    "iso:country":"CH",
    "sg:address":"Bifitstrasse 102",
    "sg:city":"Niederscherli",
    "sg:orig_category":"Vereine Gesang",
    "sg:phone":"+41 31 849 03 21",
    "sg:postcode":"3145",
    "sg:province":"Bern",
    "wof:name":"M\u00e4nnerchor K\u00f6niz",
    "wof:placetype":"venue"
},
  "geometry": {"coordinates":[7.3819551468,46.8810768127],"type":"Point"}
}