{
  "type": "Feature",
  "properties": {
    "iso:country":"CH",
    "sg:address":"Solothurnstrasse 16",
    "sg:city":"Pieterlen",
    "sg:orig_category":"Instandhaltung U Reparatur von Automobilen",
    "sg:phone":"+41 41 787 14 24",
    "sg:postcode":"2542",
    "sg:province":"Bern",
    "wof:name":"Garage Fux Ag",
    "wof:placetype":"venue"
},
  "geometry": {"coordinates":[8.3534126282,47.1736831665],"type":"Point"}
}