{
  "type": "Feature",
  "properties": {
    "iso:country":"CH",
    "sg:address":"Bachlettenstrasse 5",
    "sg:city":"Basel",
    "sg:orig_category":"Sonstige Aktivit\u00e4ten der nicht-\u00e4rztlichen Medizinalberufe",
    "sg:phone":"+41 61 281 14 03",
    "sg:postcode":"4054",
    "sg:province":"Basel-Stadt",
    "wof:name":"Sabine Schenkel Kinesiologie",
    "wof:placetype":"venue"
},
  "geometry": {"coordinates":[7.5808539391,47.5501937866],"type":"Point"}
}