{
  "type": "Feature",
  "properties": {
    "iso:country":"CH",
    "sg:address":"Sophienstrasse 2 8032 Z\u00fcrich. Postfach",
    "sg:city":"Z\u00fcrich",
    "sg:orig_category":"Werbeagenturen",
    "sg:phone":"+41 12671919",
    "sg:postcode":"8030",
    "wof:name":"Matter & Partner Ag Werbeagentur Bsw",
    "wof:placetype":"venue"
},
  "geometry": {"coordinates":[8.5581855774,47.3688659668],"type":"Point"}
}