{
  "type": "Feature",
  "properties": {
    "iso:country":"CH",
    "sg:address":"Fl\u00fcelastrasse 54",
    "sg:city":"Z\u00fcrich",
    "sg:orig_category":"Architektur U Ingenieurb\u00fcros",
    "sg:phone":"+41 14969595",
    "sg:postcode":"8047",
    "sg:province":"Z\u00fcrich",
    "wof:name":"Kalt & Halbeisen Ingenieurb\u00fcro Ag",
    "wof:placetype":"venue"
},
  "geometry": {"coordinates":[8.4939,47.380917],"type":"Point"}
}