{
  "type": "Feature",
  "properties": {
    "iso:country":"CH",
    "sg:address":"Grand-st-bernard Route 21",
    "sg:city":"Bex",
    "sg:orig_category":"Detailhandel mit Bekleidung",
    "sg:phone":"+41 79 212 75 76",
    "sg:postcode":"1880",
    "sg:province":"Vaud",
    "wof:name":"F\u00e9line Diffusion S\u00e0rl",
    "wof:placetype":"venue"
},
  "geometry": {"coordinates":[6.999645,46.258942],"type":"Point"}
}