{
  "type": "Feature",
  "properties": {
    "addr:full":"B\u00e4ndlistrasse 30 8000 Z\u00fcrich. Postfach Z\u00fcrich Z\u00fcrich 8064",
    "addr:housenumber":"30",
    "addr:postcode":"8000 zuerich. postfach;8064",
    "addr:street":"Baendlistrasse",
    "iso:country":"CH",
    "sg:address":"B\u00e4ndlistrasse 30 8000 Z\u00fcrich. Postfach",
    "sg:city":"Z\u00fcrich",
    "sg:classifiers":[
        {
            "category":"Bars & Pubs",
            "type":"Food & Drink"
        }
    ],
    "sg:postcode":"8064",
    "sg:province":"Z\u00fcrich",
    "wof:name":"Frauenbar Gmbh",
    "wof:placetype":"venue"
},
  "geometry": {"coordinates":[8.487323,47.395798],"type":"Point"}
}