{
  "type": "Feature",
  "properties": {
    "iso:country":"CH",
    "sg:address":"Rohrstrasse 2 3507 Biglen. Postfach",
    "sg:city":"Biglen",
    "sg:orig_category":"Herstellung von Maschinen f\u00fcr die Textil, Bekleidungsherstellung U die Lederverarbeitung Textilgewer",
    "sg:phone":"+41 55 286 13 40",
    "sg:postcode":"3507",
    "sg:province":"Bern",
    "wof:name":"Grob Willy Ag",
    "wof:placetype":"venue"
},
  "geometry": {"coordinates":[8.9271659851,47.2355728149],"type":"Point"}
}