{
  "type": "Feature",
  "properties": {
    "iso:country":"CH",
    "sg:address":"K\u00f6nizstrasse 175",
    "sg:city":"Liebefeld",
    "sg:orig_category":"Detailhandel mit Getr\u00e4nken Grosshandel mit Getr\u00e4nken",
    "sg:phone":"+41 79 372 66 14",
    "sg:postcode":"3097",
    "sg:province":"Bern",
    "wof:name":"Cultivino, Aegerter",
    "wof:placetype":"venue"
},
  "geometry": {"coordinates":[7.4155659676,46.9346656799],"type":"Point"}
}