{
  "type": "Feature",
  "properties": {
    "iso:country":"CH",
    "sg:address":"Hauptstrasse 4",
    "sg:city":"Hochwald",
    "sg:orig_category":"Vorschulen, Kinderg\u00e4rten",
    "sg:postcode":"4146",
    "sg:province":"Solothurn",
    "wof:name":"Kindergarten Alte Post",
    "wof:placetype":"venue"
},
  "geometry": {"coordinates":[7.6402211189,47.456615448],"type":"Point"}
}