{
  "type": "Feature",
  "properties": {
    "iso:country":"CH",
    "sg:address":"Oberseglingerstrasse 19",
    "sg:city":"Eglisau",
    "sg:orig_category":"G\u00fcterbef\u00f6rderung im Strassenverkehr",
    "sg:phone":"+41 18674338",
    "sg:postcode":"8193",
    "sg:province":"Z\u00fcrich",
    "wof:name":"Peter Breitenstein Transporte",
    "wof:placetype":"venue"
},
  "geometry": {"coordinates":[8.5237646103,47.5712242126],"type":"Point"}
}