{
  "type": "Feature",
  "properties": {
    "iso:country":"CH",
    "sg:address":"Route De Vevey 68",
    "sg:city":"Ch\u00e2tel-st-denis",
    "sg:orig_category":"Detailhandel mit Radio U Fernsehger\u00e4ten",
    "sg:phone":"+41 21 948 77 54",
    "sg:postcode":"1618",
    "sg:province":"Fribourg",
    "wof:name":"Hunziker T\u00e9l\u00e9vision S\u00e0rl",
    "wof:placetype":"venue"
},
  "geometry": {"coordinates":[6.8996357918,46.5244216919],"type":"Point"}
}