{
  "type": "Feature",
  "properties": {
    "iso:country":"CH",
    "sg:address":"Henauer Strasse 64",
    "sg:city":"Niederuzwil",
    "sg:orig_category":"Stukkateurgewerbe, Gipserei U Verputzerei",
    "sg:phone":"+41 71 951 52 86",
    "sg:postcode":"9244",
    "sg:province":"St. Gallen",
    "wof:name":"Dani Gipsergesch\u00e4ft Gmbh",
    "wof:placetype":"venue"
},
  "geometry": {"coordinates":[9.1309089661,47.4494667053],"type":"Point"}
}