{
  "type": "Feature",
  "properties": {
    "addr:full":"Monthoux Rue De 23 1201 Gen\u00e8ve. Postfach Gen\u00e8ve Gen\u00e8ve 1201",
    "addr:housenumber":"23",
    "addr:postcode":"1201;postfach;1201",
    "addr:street":"Rue De",
    "iso:country":"CH",
    "sg:address":"Monthoux Rue De 23 1201 Gen\u00e8ve. Postfach",
    "sg:city":"Gen\u00e8ve",
    "sg:classifiers":[
        {
            "category":"Bars & Pubs",
            "type":"Food & Drink"
        }
    ],
    "sg:postcode":"1201",
    "sg:province":"Gen\u00e8ve",
    "wof:name":"Mauro Et Mike Cassanelli",
    "wof:placetype":"venue"
},
  "geometry": {"coordinates":[6.746745,47.056477],"type":"Point"}
}