{
  "type": "Feature",
  "properties": {
    "iso:country":"CH",
    "sg:address":"Apollostrasse 3 8032 Z\u00fcrich",
    "sg:city":"Zust",
    "sg:orig_category":"Sonstiger Grosshandel",
    "sg:phone":"+41 71 911 75 59",
    "sg:postcode":"32",
    "wof:name":"Bst Trading, Balmer & Gandossi Waren Usw; Handel, Im, Export",
    "wof:placetype":"venue"
},
  "geometry": {"coordinates":[9.0484905243,47.4660682678],"type":"Point"}
}