{
  "type": "Feature",
  "properties": {
    "iso:country":"CH",
    "sg:address":"Reverdil Avenue 12 1260 Nyon. Postfach",
    "sg:city":"Nyon",
    "sg:orig_category":"Kunststoff-Produkte",
    "sg:phone":"+41 22 994 97 11",
    "sg:postcode":"1260",
    "sg:province":"Vaud",
    "wof:name":"Tupperware Products S.a., Nyon Branch",
    "wof:placetype":"venue"
},
  "geometry": {"coordinates":[6.2323641777,46.3810691833],"type":"Point"}
}