{
  "type": "Feature",
  "properties": {
    "iso:country":"CH",
    "sg:address":"Feldweg 24",
    "sg:city":"Arth",
    "sg:orig_category":"Wirtschafts- and Arbeitgeberverb\u00e4nde",
    "sg:phone":"+41 41 855 35 65",
    "sg:postcode":"6415",
    "sg:province":"Schwyz",
    "wof:name":"Zentralverb.schweizer Volks- Theater,herrn Adalb.spichtig",
    "wof:placetype":"venue"
},
  "geometry": {"coordinates":[8.5314998627,47.0609054565],"type":"Point"}
}