{
  "type": "Feature",
  "properties": {
    "iso:country":"CH",
    "sg:address":"Wehntalerstrasse 3 8057 Z\u00fcrich. Postfach",
    "sg:city":"Z\u00fcrich",
    "sg:orig_category":"Architektur U Ingenieurb\u00fcros",
    "sg:phone":"+41 71 288 51 34",
    "sg:postcode":"8057",
    "sg:province":"Z\u00fcrich",
    "wof:name":"Ing. G\u00f6nc\u00f6l Eva Techn. B\u00fcro",
    "wof:placetype":"venue"
},
  "geometry": {"coordinates":[9.403184,47.443245],"type":"Point"}
}