{
  "type": "Feature",
  "properties": {
    "iso:country":"CH",
    "sg:address":"Tribschenstrasse 19",
    "sg:city":"Luzern",
    "sg:orig_category":"Sonstige pers\u00f6nliche Dienstleistungen",
    "sg:phone":"+41 41 360 13 14",
    "sg:postcode":"6005",
    "sg:province":"Luzern",
    "wof:name":"Bildungszentrum F\u00fcr Spirituelle Entwicklung",
    "wof:placetype":"venue"
},
  "geometry": {"coordinates":[8.3135032654,47.0436019897],"type":"Point"}
}