{
  "type": "Feature",
  "properties": {
    "iso:country":"CH",
    "sg:address":"Grand-rue 2 1204 Gen\u00e8ve. Postfach",
    "sg:city":"Gen\u00e8ve",
    "sg:orig_category":"Sonstiges Textilgewerbe",
    "sg:postcode":"1204",
    "sg:province":"Gen\u00e8ve",
    "wof:name":"Bouthillier De Beaumont Maril\u00e8ne.",
    "wof:placetype":"venue"
},
  "geometry": {"coordinates":[6.1445422173,46.2023658752],"type":"Point"}
}