{
  "type": "Feature",
  "properties": {
    "iso:country":"CH",
    "sg:address":"Rorschacher Strasse 219",
    "sg:city":"St.gallen",
    "sg:orig_category":"Tankstellen",
    "sg:phone":"+41 71 314 00 20",
    "sg:postcode":"9000",
    "sg:province":"St. Gallen",
    "wof:name":"Migrol Auto Service Franchisebetrieb G\u00f6ldi",
    "wof:placetype":"venue"
},
  "geometry": {"coordinates":[9.3144273758,47.416885376],"type":"Point"}
}