{
  "type": "Feature",
  "properties": {
    "iso:country":"CH",
    "sg:address":"Hauptstrasse 68",
    "sg:city":"T\u00e4gerwilen",
    "sg:orig_category":"Vorschulen, Kinderg\u00e4rten",
    "sg:phone":"+41 71 669 24 53",
    "sg:postcode":"8274",
    "sg:province":"Thurgau",
    "wof:name":"Kindergarten Wagenhof",
    "wof:placetype":"venue"
},
  "geometry": {"coordinates":[9.1319379807,47.6552848816],"type":"Point"}
}