{
  "type": "Feature",
  "properties": {
    "iso:country":"CH",
    "sg:address":"Tierfeld 3700 Spiez. Postfach",
    "sg:city":"Einigen",
    "sg:orig_category":"Detailhandel mit Getr\u00e4nken Detailhandel mit elektrischen Haushalts-,Radio U Fernsehger\u00e4ten sowie Mus",
    "sg:phone":"+41 62 771 40 40",
    "sg:postcode":"3646",
    "sg:province":"Bern",
    "wof:name":"Heiz W. Ag Reinach",
    "wof:placetype":"venue"
},
  "geometry": {"coordinates":[8.1837472916,47.253452301],"type":"Point"}
}