{
  "type": "Feature",
  "properties": {
    "iso:country":"CH",
    "sg:address":"Littoral Parc En Noyer-girod",
    "sg:city":"Etoy",
    "sg:orig_category":"Mechanik",
    "sg:postcode":"1163",
    "sg:province":"Vaud",
    "wof:name":"Tecnoweld S\u00e0rl",
    "wof:placetype":"venue"
},
  "geometry": {"coordinates":[6.4193058014,46.4849510193],"type":"Point"}
}