{
  "type": "Feature",
  "properties": {
    "iso:country":"CH",
    "sg:address":"8222",
    "sg:city":"Beringen",
    "sg:orig_category":"Wasserversorgung",
    "sg:phone":"+41 52 741 24 90",
    "sg:postcode":"8222",
    "sg:province":"Schaffhausen",
    "wof:name":"Wasserversorgung",
    "wof:placetype":"venue"
},
  "geometry": {"coordinates":[8.8598861694,47.6590652466],"type":"Point"}
}