{
  "type": "Feature",
  "properties": {
    "iso:country":"CH",
    "sg:address":"Obmoos",
    "sg:city":"Rothenburg",
    "sg:orig_category":"Herstellung von Konstruktionsteilen, Fertigbauteilen U Ausbauelementen aus Holz",
    "sg:phone":"+41 41 280 89 03",
    "sg:postcode":"6023",
    "sg:province":"Luzern",
    "wof:name":"Riechsteiner Paul Fenster- & Glasbau",
    "wof:placetype":"venue"
},
  "geometry": {"coordinates":[8.2679700851,47.1132316589],"type":"Point"}
}