{
  "type": "Feature",
  "properties": {
    "iso:country":"CH",
    "sg:address":"Wohlerstrasse 8",
    "sg:city":"Dottikon",
    "sg:orig_category":"Instandhaltung U Reparatur von Automobilen",
    "sg:phone":"+41 56 443 22 51",
    "sg:postcode":"5605",
    "sg:province":"Aargau",
    "wof:name":"K. H\u00e4usermann Ag",
    "wof:placetype":"venue"
},
  "geometry": {"coordinates":[8.1683893204,47.4422302246],"type":"Point"}
}