{
  "type": "Feature",
  "properties": {
    "iso:country":"CH",
    "sg:address":"Avenue Victor-ruffy 10",
    "sg:city":"Lausanne",
    "sg:orig_category":"Detailhandel mit Waren verschiedener Art, Hauptrichtung Nahrungsmittel",
    "sg:phone":"+41 21 312 83 03",
    "sg:postcode":"1012",
    "sg:province":"Vaud",
    "wof:name":"A Litoral, Dinis",
    "wof:placetype":"venue"
},
  "geometry": {"coordinates":[6.6476049423,46.5237388611],"type":"Point"}
}