{
  "type": "Feature",
  "properties": {
    "iso:country":"CH",
    "sg:address":"Breitenlachenstrasse 21 6005 Luzern. Postfach",
    "sg:city":"Luzern",
    "sg:orig_category":"Unclassifiable Establishments",
    "sg:postcode":"6003",
    "sg:province":"Luzern",
    "wof:name":"Toplag Invest Ag Beteiligungen Usw",
    "wof:placetype":"venue"
},
  "geometry": {"coordinates":[8.3079051971,47.0376586914],"type":"Point"}
}