{
  "type": "Feature",
  "properties": {
    "iso:country":"CH",
    "sg:address":"2710 Tavannes. Postfach 97",
    "sg:city":"Tavannes",
    "sg:orig_category":"Sportvereine Ballsport Fussball",
    "sg:phone":"+41 32 481 43 52",
    "sg:postcode":"2710",
    "sg:province":"Bern",
    "wof:name":"Fc Olympia Tavannes",
    "wof:placetype":"venue"
},
  "geometry": {"coordinates":[7.1996560097,47.2200469971],"type":"Point"}
}