{
  "type": "Feature",
  "properties": {
    "iso:country":"CH",
    "sg:address":"Kanonenstrasse",
    "sg:city":"Luzern",
    "sg:orig_category":"RESTAURANTS: TEA-ROOMS",
    "sg:phone":"+41 41 249 41 00",
    "sg:postcode":"6003",
    "sg:province":"Luzern",
    "wof:name":"Marc Zimmermann Restaurant Ch\u00e2teau G\u00fctsch Ag",
    "wof:placetype":"venue"
},
  "geometry": {"coordinates":[8.2854537964,47.0532226562],"type":"Point"}
}