{
  "type": "Feature",
  "properties": {
    "iso:country":"CH",
    "sg:address":"M\u00fchlegasse 7 3210 Kerzers. Postfach",
    "sg:city":"Kerzers",
    "sg:orig_category":"Sonstige pers\u00f6nliche Dienstleistungen",
    "sg:phone":"+41 31 755 74 68",
    "sg:postcode":"3210",
    "sg:province":"Fribourg",
    "wof:name":"Chung Nam Bracelets Sa Dienstleistungen In Der Uhrenbranche",
    "wof:placetype":"venue"
},
  "geometry": {"coordinates":[7.1935968399,46.9700164795],"type":"Point"}
}