{
  "type": "Feature",
  "properties": {
    "iso:country":"CH",
    "sg:address":"Z\u00fcrichstrasse 2",
    "sg:city":"B\u00fctzberg",
    "sg:orig_category":"Non-Classified Establishments",
    "sg:postcode":"4922",
    "sg:province":"Bern",
    "wof:name":"Drogerie Burkhardt",
    "wof:placetype":"venue"
},
  "geometry": {"coordinates":[7.748896122,47.2162094116],"type":"Point"}
}