{
  "type": "Feature",
  "properties": {
    "iso:country":"CH",
    "sg:address":"Weinfelderstrasse 117",
    "sg:city":"Amriswil",
    "sg:orig_category":"Softwareentwicklung U beratung",
    "sg:postcode":"8580",
    "sg:province":"Thurgau",
    "wof:name":"Medicus Nufer & Co",
    "wof:placetype":"venue"
},
  "geometry": {"coordinates":[9.276309967,47.5445556641],"type":"Point"}
}