{
  "type": "Feature",
  "properties": {
    "iso:country":"CH",
    "sg:address":"Rue Du Perron 9",
    "sg:city":"Gland",
    "sg:orig_category":"Non-Classified Establishments",
    "sg:phone":"+41 22 364 17 98",
    "sg:postcode":"1196",
    "sg:province":"Vaud",
    "wof:name":"Rindlisbacher Jean-pierre",
    "wof:placetype":"venue"
},
  "geometry": {"coordinates":[6.2732000351,46.4200973511],"type":"Point"}
}