{
  "type": "Feature",
  "properties": {
    "iso:country":"CH",
    "sg:address":"Weidweg 37a",
    "sg:city":"Hinterkappelen",
    "sg:orig_category":"Detailhandel mit Waren verschiedener Art, Hauptrichtung Nahrungsmittel Sonstiger Grosshandel",
    "sg:phone":"+41 31 901 02 11",
    "sg:postcode":"3032",
    "sg:province":"Bern",
    "wof:name":"Genossenschaft Laden Aumatt",
    "wof:placetype":"venue"
},
  "geometry": {"coordinates":[7.391283989,46.9683456421],"type":"Point"}
}