{
  "type": "Feature",
  "properties": {
    "iso:country":"CH",
    "sg:address":"Im Lehen 7",
    "sg:city":"Oberriet",
    "sg:orig_category":"Glass-Fibre Reinforced Plastic Grp Gratings",
    "sg:phone":"+41 71 761 32 22",
    "sg:postcode":"9463",
    "sg:province":"St. Gallen",
    "wof:name":"Ibatec Ag",
    "wof:placetype":"venue"
},
  "geometry": {"coordinates":[9.5719814301,47.323299408],"type":"Point"}
}