{
  "type": "Feature",
  "properties": {
    "iso:country":"CH",
    "sg:address":"Rte De Boujean 122 2500 Biel/bienne. Postfach",
    "sg:city":"Biel/bienne",
    "sg:orig_category":"Pensionskassen",
    "sg:postcode":"2500",
    "sg:province":"Bern",
    "wof:name":"Fondation De Pr\u00e9voyance En Faveur Du Personnel Cendres Et M\u00e9taux Sa",
    "wof:placetype":"venue"
},
  "geometry": {"coordinates":[7.2640447617,47.1509399414],"type":"Point"}
}