{
  "type": "Feature",
  "properties": {
    "iso:country":"CH",
    "sg:address":"Rue Mauborget 6",
    "sg:city":"Lausanne",
    "sg:orig_category":"Technische, physikalische U chemische Untersuchung",
    "sg:phone":"+41 79 301 38 42",
    "sg:postcode":"1003",
    "sg:province":"Vaud",
    "wof:name":"Ceb-indoor Sa",
    "wof:placetype":"venue"
},
  "geometry": {"coordinates":[6.6290831566,46.5227775574],"type":"Point"}
}