{
  "type": "Feature",
  "properties": {
    "iso:country":"CH",
    "sg:address":"Nordstrasse 50 8000 Z\u00fcrich. Postfach",
    "sg:city":"Z\u00fcrich",
    "sg:orig_category":"Vermittlungen Wohnungs-Agenturen,",
    "sg:postcode":"8001",
    "sg:province":"Z\u00fcrich",
    "wof:name":"Spring Multi Service",
    "wof:placetype":"venue"
},
  "geometry": {"coordinates":[8.9648952484,47.4627532959],"type":"Point"}
}