{
  "type": "Feature",
  "properties": {
    "iso:country":"CH",
    "sg:address":"Via Mola 34",
    "sg:city":"Coldrerio",
    "sg:orig_category":"Maler U Glasergewerbe",
    "sg:phone":"+41 32 341 43 11",
    "sg:postcode":"6877",
    "sg:province":"Ticino",
    "wof:name":"Trapletti Diego",
    "wof:placetype":"venue"
},
  "geometry": {"coordinates":[8.9871959686,45.8539619446],"type":"Point"}
}