{
  "type": "Feature",
  "properties": {
    "iso:country":"CH",
    "sg:address":"R\u00f6telstrasse 125",
    "sg:city":"Z\u00fcrich",
    "sg:orig_category":"Detektivb\u00fcros U \u00dcberwachung",
    "sg:phone":"+41 79 400 24 24",
    "sg:postcode":"8037",
    "sg:province":"Z\u00fcrich",
    "wof:name":"Graber, Sicherheit & Organisation Personen, Begleitschutz. Wert, Dokumententransport; Planung Usw",
    "wof:placetype":"venue"
},
  "geometry": {"coordinates":[8.5323209763,47.3971748352],"type":"Point"}
}