{
  "type": "Feature",
  "properties": {
    "iso:country":"CH",
    "sg:address":"Feldbachstr. 80",
    "sg:city":"Hombrechtikon",
    "sg:classifiers":[
        {
            "category":"Shopping",
            "subcategory":"Computers & Home Electronics",
            "type":"Retail Goods"
        }
    ],
    "sg:phone":"+41 55 254 51 11",
    "sg:postcode":"8634",
    "sg:province":"Z\u00fcrich",
    "sg:tags":[
        "equipment",
        "electrical",
        "component",
        "electric",
        "electronic"
    ],
    "wof:name":"Nexus Telecom Ag",
    "wof:placetype":"venue"
},
  "geometry": {"coordinates":[8.781375885,47.2455368042],"type":"Point"}
}