{
  "type": "Feature",
  "properties": {
    "iso:country":"CH",
    "sg:address":"B\u00e4umlimattstrasse 151",
    "sg:city":"M\u00f6hlin",
    "sg:orig_category":"Pensionskassen",
    "sg:phone":"+41 62 771 55 55",
    "sg:postcode":"4313",
    "sg:province":"Aargau",
    "wof:name":"Wohlfahrtsstiftung Der Lpm Ag",
    "wof:placetype":"venue"
},
  "geometry": {"coordinates":[8.2041692734,47.2646484375],"type":"Point"}
}