{
  "type": "Feature",
  "properties": {
    "iso:country":"CH",
    "sg:address":"Alexander-moser-strasse 82 2500 Biel/bienne. Postfach",
    "sg:city":"Biel/bienne",
    "sg:orig_category":"Gesundheitswesen",
    "sg:postcode":"2503",
    "sg:province":"Bern",
    "wof:name":"Physiotherapie Brouwer G.",
    "wof:placetype":"venue"
},
  "geometry": {"coordinates":[7.2556071281,47.1263542175],"type":"Point"}
}