{
  "type": "Feature",
  "properties": {
    "iso:country":"CH",
    "sg:address":"Zugerstrasse 41",
    "sg:city":"W\u00e4denswil",
    "sg:orig_category":"Autogaragen",
    "sg:phone":"+41 17806083",
    "sg:postcode":"8820",
    "sg:province":"Z\u00fcrich",
    "wof:name":"City-garage Martin Z\u00fcrcher",
    "wof:placetype":"venue"
},
  "geometry": {"coordinates":[8.667325,47.229942],"type":"Point"}
}