{
  "type": "Feature",
  "properties": {
    "iso:country":"CH",
    "sg:address":"Gr\u00fcnaustrasse 6",
    "sg:city":"Wabern",
    "sg:orig_category":"Arztpraxen",
    "sg:phone":"+41 31 961 44 88",
    "sg:postcode":"3084",
    "sg:province":"Bern",
    "wof:name":"Dr.med. Severin Erzer Spezialarzt Fmh",
    "wof:placetype":"venue"
},
  "geometry": {"coordinates":[7.453919,46.926617],"type":"Point"}
}