{
  "type": "Feature",
  "properties": {
    "iso:country":"CH",
    "sg:address":"Wiesenstrasse 201",
    "sg:city":"Nendeln",
    "sg:orig_category":"Elektroinstallation",
    "sg:phone":"+41 61 711 77 11",
    "sg:postcode":"9485",
    "wof:name":"Grellinger Hansj\u00f6rg",
    "wof:placetype":"venue"
},
  "geometry": {"coordinates":[7.5892968178,47.4920845032],"type":"Point"}
}