{
  "type": "Feature",
  "properties": {
    "addr:full":"Rue De La Chapelle 17 Peseux Neuch\u00e2tel 2034",
    "addr:housenumber":"17",
    "addr:postcode":"2034",
    "addr:street":"Rue De La Chapelle;Neucha\u0302Tel",
    "iso:country":"CH",
    "sg:address":"Rue De La Chapelle 17",
    "sg:city":"Peseux",
    "sg:orig_category":"Arztpraxen",
    "sg:phone":"+41 32 731 14 28",
    "sg:postcode":"2034",
    "sg:province":"Neuch\u00e2tel",
    "wof:name":"Dr M\u00e9d. Michel Walder M\u00e9decin G\u00e9n\u00e9raliste Fmh",
    "wof:placetype":"venue"
},
  "geometry": {"coordinates":[6.890393,46.987282],"type":"Point"}
}