{
  "type": "Feature",
  "properties": {
    "addr:full":"Wartstrasse 31 Winterthur Z\u00fcrich 8400",
    "addr:housenumber":"31",
    "addr:postcode":"8400",
    "addr:street":"Wartstrasse",
    "iso:country":"CH",
    "sg:address":"Wartstrasse 31",
    "sg:city":"Winterthur",
    "sg:orig_category":"Detailhandel mit Blumen U Pflanzen Fachdetailhandel in Verkaufsr\u00e4umen",
    "sg:phone":"+41 52 212 03 21",
    "sg:postcode":"8400",
    "sg:province":"Z\u00fcrich",
    "wof:name":"Blumen-m\u00fcller",
    "wof:placetype":"venue"
},
  "geometry": {"coordinates":[8.719251,47.50172],"type":"Point"}
}