{
  "type": "Feature",
  "properties": {
    "iso:country":"CH",
    "sg:address":"3975",
    "sg:city":"Randogne",
    "sg:orig_category":"Vorschulen, Kinderg\u00e4rten",
    "sg:postcode":"3975",
    "sg:province":"Valais",
    "wof:name":"Ecole Enfantine",
    "wof:placetype":"venue"
},
  "geometry": {"coordinates":[7.463640213,46.2584381104],"type":"Point"}
}