{
  "type": "Feature",
  "properties": {
    "iso:country":"CH",
    "sg:address":"Enney",
    "sg:city":"Bulle",
    "sg:classifiers":[
        {
            "category":"Banks & Credit Unions",
            "subcategory":"Bank",
            "type":"Services"
        }
    ],
    "sg:phone":"+41 2963247",
    "sg:postcode":"1630",
    "sg:province":"Fribourg",
    "wof:name":"Rentenanstalt Swiss Life",
    "wof:placetype":"venue"
},
  "geometry": {"coordinates":[7.057381,46.618603],"type":"Point"}
}