{
  "type": "Feature",
  "properties": {
    "iso:country":"CH",
    "sg:address":"Friedheimstrasse 28",
    "sg:city":"Z\u00fcrich",
    "sg:orig_category":"Elektroinstallation Technische B\u00fcros Elektro",
    "sg:phone":"+41 13102130",
    "sg:postcode":"8057",
    "sg:province":"Z\u00fcrich",
    "wof:name":"Bsb-eng. Staub Bernhard Gmbh",
    "wof:placetype":"venue"
},
  "geometry": {"coordinates":[8.5518550873,47.4044342041],"type":"Point"}
}