{
  "type": "Feature",
  "properties": {
    "iso:country":"CH",
    "sg:address":"Lindengasse 277",
    "sg:city":"Hirschthal",
    "sg:orig_category":"Grosshandel mit Getr\u00e4nken",
    "sg:phone":"+41 79 693 31 70",
    "sg:postcode":"5042",
    "sg:province":"Aargau",
    "wof:name":"Getr\u00e4nkekurier Berner",
    "wof:placetype":"venue"
},
  "geometry": {"coordinates":[8.0526351929,47.3215522766],"type":"Point"}
}