{
  "type": "Feature",
  "properties": {
    "iso:country":"CH",
    "sg:address":"Saleggi Via 18a 6612 Ascona. Postfach",
    "sg:city":"Ascona",
    "sg:orig_category":"Interessenvertretungen",
    "sg:postcode":"6612",
    "sg:province":"Ticino",
    "wof:name":"Fondazione Famiglie Fu Ferrari Ercole Ed Emilio",
    "wof:placetype":"venue"
},
  "geometry": {"coordinates":[8.7841863632,46.1554412842],"type":"Point"}
}