{
  "type": "Feature",
  "properties": {
    "iso:country":"CH",
    "sg:address":"Limmatplatz 3",
    "sg:city":"Z\u00fcrich",
    "sg:orig_category":"RESTAURANTS: TEA-ROOMS",
    "sg:phone":"+41 12719303",
    "sg:postcode":"8005",
    "sg:province":"Z\u00fcrich",
    "wof:name":"Tram-caf\u00e9 Ag",
    "wof:placetype":"venue"
},
  "geometry": {"coordinates":[8.531665802,47.3845481873],"type":"Point"}
}