{
  "type": "Feature",
  "properties": {
    "iso:country":"CH",
    "sg:address":"S\u00f6mmerlistrasse 14",
    "sg:city":"St.gallen",
    "sg:orig_category":"G\u00fcterbef\u00f6rderung im Strassenverkehr",
    "sg:phone":"+41 79 668 60 00",
    "sg:postcode":"9000",
    "sg:province":"St. Gallen",
    "wof:name":"Guido Favetto Transporte",
    "wof:placetype":"venue"
},
  "geometry": {"coordinates":[7.8322777748,47.2304534912],"type":"Point"}
}