{
  "type": "Feature",
  "properties": {
    "iso:country":"CH",
    "sg:address":"Im Siber 7",
    "sg:city":"Flaach",
    "sg:orig_category":"Allgemeiner Hoch U Tiefbau Allgemeiner Hochbau",
    "sg:phone":"+41 34 493 36 78",
    "sg:postcode":"8416",
    "sg:province":"Z\u00fcrich",
    "wof:name":"Brechb\u00fchl & Co, Bauunternehmung",
    "wof:placetype":"venue"
},
  "geometry": {"coordinates":[7.906402,46.865177],"type":"Point"}
}