{
  "type": "Feature",
  "properties": {
    "addr:full":"Gl\u00e4rnischstr. 36 Z\u00fcrich Z\u00fcrich 8002",
    "addr:housenumber":"36",
    "addr:postcode":"8002",
    "addr:street":"Glaernischstr.",
    "iso:country":"CH",
    "sg:address":"Gl\u00e4rnischstr. 36",
    "sg:city":"Z\u00fcrich",
    "sg:classifiers":[
        {
            "category":"Banks & Credit Unions",
            "subcategory":"Bank",
            "type":"Services"
        }
    ],
    "sg:phone":"+41 12074111",
    "sg:postcode":"8002",
    "sg:province":"Z\u00fcrich",
    "wof:name":"Ing Bank (schweiz) Ag",
    "wof:placetype":"venue"
},
  "geometry": {"coordinates":[8.537384,47.368446],"type":"Point"}
}