{
  "type": "Feature",
  "properties": {
    "iso:country":"CH",
    "sg:address":"K\u00fcng Montagen Gmbh",
    "sg:city":"Lengwil-oberhofen",
    "sg:orig_category":"Non-Classified Establishments",
    "sg:postcode":"8574",
    "sg:province":"Thurgau",
    "wof:name":"K\u00fcng Montagen Gmbh",
    "wof:placetype":"venue"
},
  "geometry": {"coordinates":[9.1937875748,47.6247749329],"type":"Point"}
}