{
  "type": "Feature",
  "properties": {
    "iso:country":"CH",
    "sg:address":"Engiberg Seewen Sz",
    "sg:city":"Schwyz",
    "sg:orig_category":"Haltung von Rindern",
    "sg:postcode":"6430",
    "sg:province":"Schwyz",
    "wof:name":"Viehzuchtgenossenschaft Schwyz-uetenbach",
    "wof:placetype":"venue"
},
  "geometry": {"coordinates":[8.6323604584,47.026550293],"type":"Point"}
}