{
  "type": "Feature",
  "properties": {
    "iso:country":"CH",
    "sg:address":"Ancienne Route De Villeret 48",
    "sg:city":"St-imier",
    "sg:orig_category":"Sonstiger Grosshandel",
    "sg:postcode":"2610",
    "sg:province":"Bern",
    "wof:name":"Multi-ventes Sa",
    "wof:placetype":"venue"
},
  "geometry": {"coordinates":[7.0108819008,47.1556396484],"type":"Point"}
}