{
  "type": "Feature",
  "properties": {
    "iso:country":"CH",
    "sg:address":"Haut Des Vies 15",
    "sg:city":"Reconvilier",
    "sg:orig_category":"Herstellung von Bergwerks U Baumaschinen",
    "sg:postcode":"2732",
    "sg:province":"Bern",
    "wof:name":"Grossholz F. X. Machines Et Outillage De Chantier; Comm",
    "wof:placetype":"venue"
},
  "geometry": {"coordinates":[6.9246211052,46.3967247009],"type":"Point"}
}