{
  "type": "Feature",
  "properties": {
    "iso:country":"CH",
    "sg:address":"Kornhausbr\u00fccke 4",
    "sg:city":"Z\u00fcrich",
    "sg:classifiers":[
        {
            "category":"Restaurant",
            "type":"Food & Drink"
        }
    ],
    "sg:phone":"+41 62 771 00 98",
    "sg:postcode":"8005",
    "sg:province":"Z\u00fcrich",
    "wof:name":"Imbiss-ecke Paninoteca",
    "wof:placetype":"venue"
},
  "geometry": {"coordinates":[8.1835489273,47.2527351379],"type":"Point"}
}