{
  "type": "Feature",
  "properties": {
    "iso:country":"CH",
    "sg:address":"Route De Madretsch 44 2500 Biel/bienne. Postfach",
    "sg:city":"Biel/bienne",
    "sg:orig_category":"Fachdetailhandel in Verkaufsr\u00e4umen",
    "sg:postcode":"2502",
    "sg:province":"Bern",
    "wof:name":"La Thune Rossier Eveline",
    "wof:placetype":"venue"
},
  "geometry": {"coordinates":[7.2541899681,47.1333961487],"type":"Point"}
}