{
  "type": "Feature",
  "properties": {
    "iso:country":"CH",
    "sg:address":"Via Argine Zona Industriale 1",
    "sg:city":"Bedano",
    "sg:orig_category":"Unclassifiable Establishments",
    "sg:postcode":"6930",
    "sg:province":"Ticino",
    "wof:name":"Door System Sagl",
    "wof:placetype":"venue"
},
  "geometry": {"coordinates":[8.9187746048,46.0506439209],"type":"Point"}
}