{
  "type": "Feature",
  "properties": {
    "iso:country":"CH",
    "sg:address":"Elisabethenanlage 7",
    "sg:city":"Basel",
    "sg:orig_category":"Finanzierungsinstitutionen",
    "sg:postcode":"4051",
    "sg:province":"Basel-Stadt",
    "wof:name":"Consulta Investment Ag",
    "wof:placetype":"venue"
},
  "geometry": {"coordinates":[8.3142662048,46.9925308228],"type":"Point"}
}