{
  "type": "Feature",
  "properties": {
    "iso:country":"CH",
    "sg:address":"Oberstrasse 24 8274 T\u00e4gerwilen. Postfach 50",
    "sg:city":"T\u00e4gerwilen",
    "sg:orig_category":"Bauspenglerei Sanit\u00e4r, Heizungs U L\u00fcftungsinstallation",
    "sg:phone":"+41 71 669 11 65",
    "sg:postcode":"8274",
    "sg:province":"Thurgau",
    "wof:name":"Burkhardt Umbauten Und Installationen Ag",
    "wof:placetype":"venue"
},
  "geometry": {"coordinates":[9.144142,47.651833],"type":"Point"}
}