{
  "type": "Feature",
  "properties": {
    "iso:country":"CH",
    "sg:address":"Crappun 4",
    "sg:city":"Samedan",
    "sg:orig_category":"Detailhandel mit Uhren U Schmuck",
    "sg:phone":"+41 81 852 57 41",
    "sg:postcode":"7503",
    "sg:province":"Graubunden",
    "wof:name":"Ireneo Scacchi Goldschmied",
    "wof:placetype":"venue"
},
  "geometry": {"coordinates":[9.8711280823,46.5326576233],"type":"Point"}
}