{
  "type": "Feature",
  "properties": {
    "iso:country":"CH",
    "sg:address":"Rue Des Rasses 26",
    "sg:city":"Ste-croix",
    "sg:orig_category":"Bau U Wohngenossenschaften",
    "sg:phone":"+41 24 454 29 68",
    "sg:postcode":"1450",
    "sg:province":"Vaud",
    "wof:name":"St\u00e9 Coop.d'habit.bel-alpes",
    "wof:placetype":"venue"
},
  "geometry": {"coordinates":[6.507556,46.823429],"type":"Point"}
}