{
  "type": "Feature",
  "properties": {
    "iso:country":"CH",
    "sg:address":"5082",
    "sg:city":"Kaisten",
    "sg:orig_category":"Landesverteidigung, Sozialversicherung \u00d6ffentliche Verwaltung",
    "sg:phone":"+41 62 874 21 10",
    "sg:postcode":"5082",
    "sg:province":"Aargau",
    "wof:name":"Zivilschutzstelle Kaisten",
    "wof:placetype":"venue"
},
  "geometry": {"coordinates":[8.0452136993,47.5378799438],"type":"Point"}
}