{
  "type": "Feature",
  "properties": {
    "iso:country":"CH",
    "sg:address":"Winkelriedstrasse 10",
    "sg:city":"Wettingen",
    "sg:orig_category":"Zahnarztpraxen",
    "sg:phone":"+41 56 427 27 05",
    "sg:postcode":"5430",
    "sg:province":"Aargau",
    "wof:name":"Dres Med.dent. M.& S. Jaeggi Zahn\u00e4rzte",
    "wof:placetype":"venue"
},
  "geometry": {"coordinates":[8.3192148209,47.4680023193],"type":"Point"}
}