{
  "type": "Feature",
  "properties": {
    "iso:country":"CH",
    "sg:address":"Canale Via Vecchio",
    "sg:city":"Agno",
    "sg:orig_category":"Markt U Meinungsforschung",
    "sg:phone":"+41 91 605 53 36",
    "sg:postcode":"6982",
    "sg:province":"Ticino",
    "wof:name":"Gore Corporation Sa",
    "wof:placetype":"venue"
},
  "geometry": {"coordinates":[8.9032878876,45.9994316101],"type":"Point"}
}