{
  "type": "Feature",
  "properties": {
    "iso:country":"CH",
    "sg:address":"Seefeldstrasse 14",
    "sg:city":"Z\u00fcrich",
    "sg:orig_category":"Detailhandel mit Uhren U Schmuck",
    "sg:phone":"+41 22 300 49 93",
    "sg:postcode":"8008",
    "sg:province":"Z\u00fcrich",
    "wof:name":"Yves & V\u00e9ronique Denor\u00e9az Bijouterie Vict'or 18",
    "wof:placetype":"venue"
},
  "geometry": {"coordinates":[6.1261291504,46.2242355347],"type":"Point"}
}