{
  "type": "Feature",
  "properties": {
    "iso:country":"CH",
    "sg:address":"Stadtturmstrasse 9",
    "sg:city":"Baden",
    "sg:orig_category":"Detailhandel mit Antiquit\u00e4ten U Gebrauchtwaren in Verkaufsr\u00e4umen",
    "sg:phone":"+41 56 221 26 00",
    "sg:postcode":"5400",
    "sg:province":"Aargau",
    "wof:name":"Antiquariat Dostal",
    "wof:placetype":"venue"
},
  "geometry": {"coordinates":[8.306285,47.474529],"type":"Point"}
}