{
  "type": "Feature",
  "properties": {
    "addr:full":"Le Bourg Montricher Vaud 1147",
    "addr:postcode":"1147",
    "addr:street":"Le Bourg",
    "iso:country":"CH",
    "sg:address":"Le Bourg",
    "sg:city":"Montricher",
    "sg:orig_category":"Abwasserreinigung",
    "sg:phone":"+41 32 373 31 76",
    "sg:postcode":"1147",
    "sg:province":"Vaud",
    "wof:name":"Julien Dubois Kanalreinigung",
    "wof:placetype":"venue"
},
  "geometry": {"coordinates":[7.277512,47.125652],"type":"Point"}
}