{
  "type": "Feature",
  "properties": {
    "iso:country":"CH",
    "sg:address":"Fabrikstrasse 6",
    "sg:city":"Biberist",
    "sg:orig_category":"Herstellung von Elektromotoren, Generatoren U Transformatoren",
    "sg:postcode":"4562",
    "sg:province":"Solothurn",
    "wof:name":"Energie Und Wasser Erlenbach Ag",
    "wof:placetype":"venue"
},
  "geometry": {"coordinates":[8.5920543671,47.3024101257],"type":"Point"}
}