{
  "type": "Feature",
  "properties": {
    "addr:full":"Gubelstrasse 22 6300 Zug. Postfach Zug Zug 6300",
    "addr:housenumber":"22",
    "addr:postcode":"6300;postfach;6300",
    "addr:street":"Gubelstrasse;Zug",
    "iso:country":"CH",
    "sg:address":"Gubelstrasse 22 6300 Zug. Postfach",
    "sg:city":"Zug",
    "sg:orig_category":"Allgemeiner Hoch U Tiefbau",
    "sg:postcode":"6300",
    "sg:province":"Zug",
    "wof:name":"Enzmann Fischer Ghisleni Gmbh",
    "wof:placetype":"venue"
},
  "geometry": {"coordinates":[8.515376,47.174667],"type":"Point"}
}