{
  "type": "Feature",
  "properties": {
    "iso:country":"CH",
    "sg:address":"Aarbergstrasse 27",
    "sg:city":"Lyss",
    "sg:orig_category":"Handel mit Motorr\u00e4dern, Teilen U Zubeh\u00f6r Instandhaltung U Reparatur von Motorr\u00e4dern",
    "sg:postcode":"3250",
    "sg:province":"Bern",
    "wof:name":"Herrli Lyss Gmbh",
    "wof:placetype":"venue"
},
  "geometry": {"coordinates":[7.3036961555,47.0726661682],"type":"Point"}
}