{
  "type": "Feature",
  "properties": {
    "iso:country":"CH",
    "sg:address":"Waldeggstrasse 2",
    "sg:city":"Sch\u00e4nis",
    "sg:orig_category":"Sanit\u00e4r U Heizungsinstallation Sanit\u00e4rinstallation",
    "sg:phone":"+41 55 615 24 77",
    "sg:postcode":"8718",
    "sg:province":"St. Gallen",
    "wof:name":"Hunold Ag Heizung Sanit\u00e4r",
    "wof:placetype":"venue"
},
  "geometry": {"coordinates":[9.0499353409,47.1620483398],"type":"Point"}
}