{
  "type": "Feature",
  "properties": {
    "iso:country":"CH",
    "sg:address":"Z.i. Moulin-du-choc D 1122 Romanel-sur-morges. Postfach",
    "sg:city":"Romanel-sur-morges",
    "sg:orig_category":"Dienstleistungen von Beteiligungsgesellschaften",
    "sg:phone":"+41 21 800 08 08",
    "sg:postcode":"1122",
    "sg:province":"Vaud",
    "wof:name":"Logitech International Sa",
    "wof:placetype":"venue"
},
  "geometry": {"coordinates":[6.5216050148,46.5609664917],"type":"Point"}
}