{
  "type": "Feature",
  "properties": {
    "addr:full":"Fabrizia Via 26 Giubiasco Ticino 6512",
    "addr:housenumber":"26",
    "addr:postcode":"6512",
    "addr:street":"Via",
    "iso:country":"CH",
    "sg:address":"Fabrizia Via 26",
    "sg:city":"Giubiasco",
    "sg:orig_category":"Abwasserreinigung, Abfallbeseitigung U sonstige Entsorgung",
    "sg:phone":"+41 91 857 13 82",
    "sg:postcode":"6512",
    "sg:province":"Ticino",
    "wof:name":"Thermoselect Ticino Sa",
    "wof:placetype":"venue"
},
  "geometry": {"coordinates":[9.010825,46.17308],"type":"Point"}
}