{
  "type": "Feature",
  "properties": {
    "iso:country":"CH",
    "sg:address":"Oberdorfstrasse 11/13 6340 Baar. Postfach 2130",
    "sg:city":"Baar",
    "sg:orig_category":"Wirtschaftspr\u00fcfung, Steuerberatung U Treuhand",
    "sg:phone":"+41 41 769 79 96",
    "sg:postcode":"6342",
    "sg:province":"Zug",
    "wof:name":"Buchecker R. W. Treuhand",
    "wof:placetype":"venue"
},
  "geometry": {"coordinates":[8.5302343369,47.1961288452],"type":"Point"}
}