{
  "type": "Feature",
  "properties": {
    "iso:country":"CH",
    "sg:address":"Route D'echallens 1037 Etagni\u00e8res. Postfach",
    "sg:city":"Etagni\u00e8res",
    "sg:orig_category":"Instandhaltung U Reparatur von Automobilen",
    "sg:postcode":"1037",
    "sg:province":"Vaud",
    "wof:name":"Carrosserie Garage Casale S\u00e0rl",
    "wof:placetype":"venue"
},
  "geometry": {"coordinates":[6.6128358841,46.6001586914],"type":"Point"}
}