{
  "type": "Feature",
  "properties": {
    "iso:country":"CH",
    "sg:address":"Baarerstrasse 57 6300 Zug. Postfach",
    "sg:city":"Zug",
    "sg:orig_category":"Softwareentwicklung U beratung",
    "sg:postcode":"6304",
    "sg:province":"Zug",
    "wof:name":"Maramiro Ecs Gmbh",
    "wof:placetype":"venue"
},
  "geometry": {"coordinates":[8.1833791733,47.2491073608],"type":"Point"}
}