{
  "type": "Feature",
  "properties": {
    "iso:country":"CH",
    "sg:address":"Mellingerstrasse 12",
    "sg:city":"Niederrohrdorf",
    "sg:orig_category":"Detailhandel mit Beleuchtungs U Haushaltsgegenst\u00e4nden Detailhandel mit Radio U Fernsehger\u00e4ten",
    "sg:phone":"+41 56 496 05 05",
    "sg:postcode":"5443",
    "sg:province":"Aargau",
    "wof:name":"Schmidt Elektrohandels Ag Radio-tv",
    "wof:placetype":"venue"
},
  "geometry": {"coordinates":[8.300029,47.42495],"type":"Point"}
}