{
  "type": "Feature",
  "properties": {
    "addr:full":"Dorfgasse Sumiswald Bern 3454",
    "addr:postcode":"3454",
    "addr:street":"Dorfgasse;Bern",
    "iso:country":"CH",
    "sg:address":"Dorfgasse",
    "sg:city":"Sumiswald",
    "sg:orig_category":"Berufsberatungen",
    "sg:phone":"+41 34 431 21 31",
    "sg:postcode":"3454",
    "sg:province":"Bern",
    "wof:name":"Berufs-& Laufbahnberatung Amt Trachselwald",
    "wof:placetype":"venue"
},
  "geometry": {"coordinates":[7.74409,47.029034],"type":"Point"}
}