{
  "type": "Feature",
  "properties": {
    "iso:country":"CH",
    "sg:address":"Rosenfeldstrasse 11",
    "sg:city":"Liestal",
    "sg:orig_category":"Verlegen von Fliesen U Platten",
    "sg:phone":"+41 61 921 93 47",
    "sg:postcode":"4410",
    "sg:province":"Basel-Landschaft",
    "wof:name":"Louis Frei Wand-& Bodenbel\u00e4ge",
    "wof:placetype":"venue"
},
  "geometry": {"coordinates":[7.7412419319,47.4823417664],"type":"Point"}
}