{
  "type": "Feature",
  "properties": {
    "iso:country":"CH",
    "sg:address":"Tellstrasse 14",
    "sg:city":"Amriswil",
    "sg:orig_category":"D\u00e4mmung gegen K\u00e4lte, W\u00e4rme, Schall U Ersch\u00fctterung",
    "sg:phone":"+41 71 411 90 84",
    "sg:postcode":"8580",
    "sg:province":"Thurgau",
    "wof:name":"Hubert Arnold Isolationen",
    "wof:placetype":"venue"
},
  "geometry": {"coordinates":[9.3003978729,47.5489959717],"type":"Point"}
}