{
  "type": "Feature",
  "properties": {
    "iso:country":"CH",
    "sg:address":"Rue Louis-de-montfalcon 2ter",
    "sg:city":"Carouge",
    "sg:classifiers":[
        {
            "category":"Autos & Motor Vehicles",
            "subcategory":"Automobile Sales",
            "type":"Retail Goods"
        }
    ],
    "sg:phone":"+41 22 342 75 80",
    "sg:postcode":"1227",
    "sg:province":"Gen\u00e8ve",
    "sg:tags":[
        "varnish",
        "lacquers"
    ],
    "wof:name":"Autocolor S\u00e0rl",
    "wof:placetype":"venue"
},
  "geometry": {"coordinates":[6.137116,46.18795],"type":"Point"}
}