{
  "type": "Feature",
  "properties": {
    "iso:country":"CH",
    "sg:address":"Sous L'auberge A 1174 Montherod. Postfach",
    "sg:city":"Montherod",
    "sg:orig_category":"Detailhandel mit Brillen U anderen Sehhilfen Fachdetailhandel in Verkaufsr\u00e4umen",
    "sg:phone":"+41 21 807 26 30",
    "sg:postcode":"1174",
    "sg:province":"Vaud",
    "wof:name":"Taboo Optics",
    "wof:placetype":"venue"
},
  "geometry": {"coordinates":[6.36647,46.499031],"type":"Point"}
}