{
  "type": "Feature",
  "properties": {
    "iso:country":"CH",
    "sg:address":"Seestrasse 33",
    "sg:city":"Bottighofen",
    "sg:orig_category":"Feinmechanische and Pr\u00e4zisions Werkst\u00e4tten Herstellung von Mess U Kontrollinstrumenten U vorrichtung",
    "sg:phone":"+41 71 688 66 83",
    "sg:postcode":"8598",
    "sg:province":"Thurgau",
    "wof:name":"Munz Pr\u00e4zisionstechnik",
    "wof:placetype":"venue"
},
  "geometry": {"coordinates":[9.2089624405,47.6430931091],"type":"Point"}
}