{
  "type": "Feature",
  "properties": {
    "iso:country":"CH",
    "sg:address":"Sigelwiesstrasse 2",
    "sg:city":"Kleinandelfingen",
    "sg:orig_category":"Grosshandel mit Getr\u00e4nken",
    "sg:phone":"+41 52 317 22 41",
    "sg:postcode":"8451",
    "sg:province":"Z\u00fcrich",
    "wof:name":"Hochstrasser's Getr\u00e4nke Ag",
    "wof:placetype":"venue"
},
  "geometry": {"coordinates":[8.6895332336,47.6006660461],"type":"Point"}
}