{
  "type": "Feature",
  "properties": {
    "iso:country":"CH",
    "sg:address":"Greina Via 2",
    "sg:city":"Lugano",
    "sg:orig_category":"Non-Classified Establishments",
    "sg:phone":"+41 91 923 11 08",
    "sg:postcode":"6900",
    "sg:province":"Ticino",
    "wof:name":"Ultrim Commerce Sa",
    "wof:placetype":"venue"
},
  "geometry": {"coordinates":[8.9553775787,46.008556366],"type":"Point"}
}