{
  "type": "Feature",
  "properties": {
    "iso:country":"CH",
    "sg:address":"Bahnhofstrasse 9",
    "sg:city":"Biel/bienne",
    "sg:orig_category":"Unclassifiable Establishments",
    "sg:postcode":"2502",
    "sg:province":"Bern",
    "wof:name":"H.o.d. Metallbau B. Demiroski",
    "wof:placetype":"venue"
},
  "geometry": {"coordinates":[7.2431612015,47.1336555481],"type":"Point"}
}