{
  "type": "Feature",
  "properties": {
    "iso:country":"CH",
    "sg:address":"R\u00f6tistrasse 17",
    "sg:city":"Solothurn",
    "sg:orig_category":"Fernmeldedienste",
    "sg:postcode":"4500",
    "sg:province":"Solothurn",
    "wof:name":"Ga-sat Geiser",
    "wof:placetype":"venue"
},
  "geometry": {"coordinates":[8.0331373215,47.1996955872],"type":"Point"}
}