{
  "type": "Feature",
  "properties": {
    "iso:country":"CH",
    "sg:address":"Sennweidstrasse 1b 8608 Bubikon. Postfach",
    "sg:city":"Bubikon",
    "sg:orig_category":"Interessenvertretungen",
    "sg:postcode":"8608",
    "sg:province":"Z\u00fcrich",
    "wof:name":"Stiftung Rampeliecht",
    "wof:placetype":"venue"
},
  "geometry": {"coordinates":[8.8227901459,47.271987915],"type":"Point"}
}