{
  "type": "Feature",
  "properties": {
    "addr:full":"Steinmatt Alpthal Schwyz 8849",
    "addr:postcode":"8849",
    "addr:street":"Schwyz",
    "iso:country":"CH",
    "sg:address":"Steinmatt",
    "sg:city":"Alpthal",
    "sg:orig_category":"Abbruch U Sprenggewerbe, Erdbewegungsarbeiten Erdbewegungsarbeiten",
    "sg:phone":"+41 55 412 54 14",
    "sg:postcode":"8849",
    "sg:province":"Schwyz",
    "wof:name":"Josef Reichlin",
    "wof:placetype":"venue"
},
  "geometry": {"coordinates":[8.71461,47.068119],"type":"Point"}
}