{
  "type": "Feature",
  "properties": {
    "iso:country":"CH",
    "sg:address":"Marktplatz/edisonstrasse 22",
    "sg:city":"Z\u00fcrich",
    "sg:orig_category":"Non-Classified Establishments",
    "sg:postcode":"8000",
    "sg:province":"Z\u00fcrich",
    "wof:name":"Kuoni Reisen Ag, Zweigniederlassung Z\u00fcrich-oerlikon",
    "wof:placetype":"venue"
},
  "geometry": {"coordinates":[8.4809503555,47.3614616394],"type":"Point"}
}