{
  "type": "Feature",
  "properties": {
    "iso:country":"CH",
    "sg:address":"Strandbadstrasse 7",
    "sg:city":"Auslikon",
    "sg:orig_category":"Allgemeiner Hoch U Tiefbau ohne ausgepr\u00e4gten Schwerpunkt",
    "sg:phone":"+41 19505533",
    "sg:postcode":"8331",
    "sg:province":"Z\u00fcrich",
    "wof:name":"Zeindler & Kessler Ag Bauunternehmung",
    "wof:placetype":"venue"
},
  "geometry": {"coordinates":[8.805907,47.343338],"type":"Point"}
}