{
  "type": "Feature",
  "properties": {
    "iso:country":"CH",
    "sg:address":"Via R\u00e9siga 11",
    "sg:city":"Novazzano",
    "sg:orig_category":"Elektroinstallation Radioanstalten",
    "sg:phone":"+41 91 683 93 81",
    "sg:postcode":"6883",
    "sg:province":"Ticino",
    "wof:name":"Mauro Bergomi & Co Videocavo",
    "wof:placetype":"venue"
},
  "geometry": {"coordinates":[8.9976453781,45.8372001648],"type":"Point"}
}