{
  "type": "Feature",
  "properties": {
    "iso:country":"CH",
    "sg:address":"St\u00fcdliackerstrasse 10",
    "sg:city":"Schaffhausen",
    "sg:orig_category":"Detailhandel mit Damenbekleidung",
    "sg:phone":"+41 52 643 42 55",
    "sg:postcode":"8207",
    "sg:province":"Schaffhausen",
    "wof:name":"Chicor\u00e9e Mode Ag Einkaufszentrum Herblingen",
    "wof:placetype":"venue"
},
  "geometry": {"coordinates":[8.665751,47.721611],"type":"Point"}
}