{
  "type": "Feature",
  "properties": {
    "iso:country":"CH",
    "sg:address":"Kurhausstrasse 65 8032 Z\u00fcrich. Postfach 337",
    "sg:city":"Z\u00fcrich",
    "sg:classifiers":[
        {
            "category":"Travel",
            "subcategory":"Hotels & Motels",
            "type":"Entertainment"
        }
    ],
    "sg:phone":"+41 21 785 11 11",
    "sg:postcode":"8030",
    "wof:name":"Ecole H\u00f4teli\u00e8re De La Ssh",
    "wof:placetype":"venue"
},
  "geometry": {"coordinates":[6.682115078,46.5612640381],"type":"Point"}
}