{
  "type": "Feature",
  "properties": {
    "iso:country":"CH",
    "sg:address":"5728",
    "sg:city":"Gontenschwil",
    "sg:orig_category":"Vereine Musik/Blasmusik",
    "sg:phone":"+41 62 773 15 39",
    "sg:postcode":"5728",
    "sg:province":"Aargau",
    "wof:name":"Musikgesellschaft",
    "wof:placetype":"venue"
},
  "geometry": {"coordinates":[8.1438541412,47.2799186707],"type":"Point"}
}