{
  "type": "Feature",
  "properties": {
    "iso:country":"CH",
    "sg:address":"S\u00e4gegasse 19",
    "sg:city":"M\u00fcnsingen",
    "sg:orig_category":"Zahnarztpraxen",
    "sg:phone":"+41 31 721 11 01",
    "sg:postcode":"3110",
    "sg:province":"Bern",
    "wof:name":"Dr. Med. Dent. Daniel Turin Zahnarzt",
    "wof:placetype":"venue"
},
  "geometry": {"coordinates":[7.5561699867,46.8737220764],"type":"Point"}
}