{
  "type": "Feature",
  "properties": {
    "iso:country":"CH",
    "sg:address":"Dorfstrasse 193",
    "sg:city":"Oberkulm",
    "sg:orig_category":"Herstellung von sonstigen Holzwaren, von Kork, Flecht U Korbwaren",
    "sg:phone":"+41 21 903 07 77",
    "sg:postcode":"5727",
    "sg:province":"Aargau",
    "wof:name":"Genus Sa",
    "wof:placetype":"venue"
},
  "geometry": {"coordinates":[6.7746901512,46.604133606],"type":"Point"}
}