{
  "type": "Feature",
  "properties": {
    "iso:country":"CH",
    "sg:address":"T\u00e4gernaustrasse 131",
    "sg:city":"Jona",
    "sg:orig_category":"Grosshandel mit Nahrungsmitteln, Getr\u00e4nken U Tabakwaren ohne ausgepr\u00e4gten Schwerpunkt",
    "sg:phone":"+41 55 212 36 27",
    "sg:postcode":"8645",
    "sg:province":"St. Gallen",
    "wof:name":"B\u00f6sch Fredy, Park-discount",
    "wof:placetype":"venue"
},
  "geometry": {"coordinates":[8.8474197388,47.2354316711],"type":"Point"}
}