{
  "type": "Feature",
  "properties": {
    "iso:country":"CH",
    "sg:address":"3253",
    "sg:city":"Schnottwil",
    "sg:orig_category":"Primarschulen",
    "sg:phone":"+41 32 351 20 43",
    "sg:postcode":"3253",
    "sg:province":"Solothurn",
    "wof:name":"Primarschule",
    "wof:placetype":"venue"
},
  "geometry": {"coordinates":[7.3906450272,47.1115226746],"type":"Point"}
}