{
  "type": "Feature",
  "properties": {
    "iso:country":"CH",
    "sg:address":"Rue De L'h\u00f4pital 26",
    "sg:city":"Yverdon-les-bains",
    "sg:orig_category":"Sonstiges Gesundheitswesen",
    "sg:phone":"+41 71 455 15 23",
    "sg:postcode":"1400",
    "sg:province":"Vaud",
    "wof:name":"Praxis F\u00fcr Bewegungs-und Tanztherapie Nach Der Psychosomatischen Funktionslehre Sabine Suter-bach",
    "wof:placetype":"venue"
},
  "geometry": {"coordinates":[9.3981647491,47.4990692139],"type":"Point"}
}