{
  "type": "Feature",
  "properties": {
    "iso:country":"CH",
    "sg:address":"Ecouralaz Chemin De L' 14",
    "sg:city":"Chardonne",
    "sg:orig_category":"Softwareentwicklung U beratung",
    "sg:postcode":"1803",
    "sg:province":"Vaud",
    "wof:name":"Imagine Software, Mermod Philippe",
    "wof:placetype":"venue"
},
  "geometry": {"coordinates":[6.8199400902,46.4791908264],"type":"Point"}
}