{
  "type": "Feature",
  "properties": {
    "iso:country":"CH",
    "sg:address":"Allmendstrasse 96a",
    "sg:city":"Kestenholz",
    "sg:orig_category":"Herstellung von elektronischen Bauelementen",
    "sg:phone":"+41 62 393 04 30",
    "sg:postcode":"4703",
    "sg:province":"Solothurn",
    "wof:name":"Compu & Sign Rudolf Von Rohr",
    "wof:placetype":"venue"
},
  "geometry": {"coordinates":[7.7596421242,47.2771873474],"type":"Point"}
}