{
  "type": "Feature",
  "properties": {
    "iso:country":"CH",
    "sg:address":"Rainweg 5a",
    "sg:city":"Adelboden",
    "sg:orig_category":"Sportvereine Sch\u00fctzen",
    "sg:phone":"+41 33 673 27 39",
    "sg:postcode":"3715",
    "sg:province":"Bern",
    "wof:name":"Milit\u00e4rsch\u00fctzengesellschaft",
    "wof:placetype":"venue"
},
  "geometry": {"coordinates":[7.5719108582,46.5038871765],"type":"Point"}
}