{
  "type": "Feature",
  "properties": {
    "iso:country":"CH",
    "sg:address":"Friedauweg 7",
    "sg:city":"Aadorf",
    "sg:orig_category":"Unclassifiable Establishments",
    "sg:postcode":"8355",
    "sg:province":"Thurgau",
    "wof:name":"Giovanni Armiento Malergesch\u00e4ft",
    "wof:placetype":"venue"
},
  "geometry": {"coordinates":[8.9097547531,47.4855422974],"type":"Point"}
}