{
  "type": "Feature",
  "properties": {
    "iso:country":"CH",
    "sg:address":"Route De La Mytha 161 1669 Sciernes-d'albeuve. Postfach",
    "sg:city":"Sciernes-d'albeuve",
    "sg:orig_category":"Detailhandel mit Brot, Back U S\u00fcsswaren Herstellung von Brot U Backwaren",
    "sg:phone":"+41 26 928 10 45",
    "sg:postcode":"1669",
    "sg:province":"Fribourg",
    "wof:name":"Magnin Louis",
    "wof:placetype":"venue"
},
  "geometry": {"coordinates":[7.05588,46.518822],"type":"Point"}
}