{
  "type": "Feature",
  "properties": {
    "iso:country":"CH",
    "sg:address":"Dorfplatz 1 8810 Horgen. Postfach",
    "sg:city":"Horgen",
    "sg:orig_category":"Detailhandel mit Uhren U Schmuck Herstellung von Schmuck, Gold U Silberschmiedwaren",
    "sg:phone":"+41 17253313",
    "sg:postcode":"8810",
    "sg:province":"Z\u00fcrich",
    "wof:name":"Herzog Goldschmied Ag",
    "wof:placetype":"venue"
},
  "geometry": {"coordinates":[8.5975809097,47.2598724365],"type":"Point"}
}