{
  "type": "Feature",
  "properties": {
    "iso:country":"CH",
    "sg:address":"Gottfried Kellerstrasse 74 8606 Greifensee. Postfach",
    "sg:city":"N\u00e4nikon",
    "sg:orig_category":"Sonstige mit der Informatik verbundene T\u00e4tigkeiten",
    "sg:postcode":"8606",
    "sg:province":"Z\u00fcrich",
    "wof:name":"Jencik Computersysteme Und Software Ag",
    "wof:placetype":"venue"
},
  "geometry": {"coordinates":[8.6760463715,47.3642234802],"type":"Point"}
}