{
  "type": "Feature",
  "properties": {
    "addr:full":"Technikumstr. 2 Burgdorf Bern 3401",
    "addr:housenumber":"2",
    "addr:postcode":"3401",
    "addr:street":"Technikumstr.",
    "iso:country":"CH",
    "sg:address":"Technikumstr. 2",
    "sg:city":"Burgdorf",
    "sg:classifiers":[
        {
            "category":"Banks & Credit Unions",
            "subcategory":"Bank",
            "type":"Services"
        }
    ],
    "sg:phone":"+41 31 724 74 11",
    "sg:postcode":"3401",
    "sg:province":"Bern",
    "wof:name":"Swiss Bank Corp.",
    "wof:placetype":"venue"
},
  "geometry": {"coordinates":[7.562234,46.87405],"type":"Point"}
}