{
  "type": "Feature",
  "properties": {
    "iso:country":"CH",
    "sg:address":"Grubenstrasse 7",
    "sg:city":"Dietikon",
    "sg:orig_category":"Maurerarbeiten",
    "sg:phone":"+41 32 652 46 60",
    "sg:postcode":"8953",
    "sg:province":"Z\u00fcrich",
    "wof:name":"Walter Rihs Maurerarbeiten",
    "wof:placetype":"venue"
},
  "geometry": {"coordinates":[7.3706231117,47.1839141846],"type":"Point"}
}