{
  "type": "Feature",
  "properties": {
    "iso:country":"CH",
    "sg:address":"Dammstrasse 14",
    "sg:city":"Grenchen",
    "sg:orig_category":"Interessenvertretungen",
    "sg:phone":"+41 41 870 12 23",
    "sg:postcode":"2540",
    "sg:province":"Solothurn",
    "wof:name":"D\u00e4twyler Stiftung",
    "wof:placetype":"venue"
},
  "geometry": {"coordinates":[8.6390476227,46.8796806335],"type":"Point"}
}