{
  "type": "Feature",
  "properties": {
    "iso:country":"CH",
    "sg:address":"Hertensteinstrasse 100",
    "sg:city":"Weggis",
    "sg:orig_category":"Bauingenieurb\u00fcros Industriebau",
    "sg:phone":"+41 19229292",
    "sg:postcode":"6353",
    "sg:province":"Luzern",
    "wof:name":"Turhan G\u00fcner G\u00fcner Engineering",
    "wof:placetype":"venue"
},
  "geometry": {"coordinates":[8.674731,47.25951],"type":"Point"}
}