{
  "type": "Feature",
  "properties": {
    "iso:country":"CH",
    "sg:address":"Chem Verseuse 1",
    "sg:city":"A\u00efre",
    "sg:classifiers":[
        {
            "category":"Shopping",
            "subcategory":"Pharmacy",
            "type":"Retail Goods"
        }
    ],
    "sg:phone":"+41 22 796 15 85",
    "sg:postcode":"1219",
    "sg:province":"Gen\u00e8ve",
    "sg:tags":[
        "chemical",
        "pharmaceutical",
        "chemistry"
    ],
    "wof:name":"Laboratoires Plan Sa",
    "wof:placetype":"venue"
},
  "geometry": {"coordinates":[6.095917,46.195427],"type":"Point"}
}