{
  "type": "Feature",
  "properties": {
    "iso:country":"CH",
    "sg:address":"Washingtonstrasse 34 9400 Rorschach. Postfach 499",
    "sg:city":"Rorschach",
    "sg:orig_category":"Garne U Zwirne",
    "sg:phone":"+41 71 844 89 30",
    "sg:postcode":"9400",
    "sg:province":"St. Gallen",
    "wof:name":"Arova Mettler Ag",
    "wof:placetype":"venue"
},
  "geometry": {"coordinates":[9.4899148941,47.4732131958],"type":"Point"}
}