{
  "type": "Feature",
  "properties": {
    "iso:country":"CH",
    "sg:address":"D\u00eeme Rue De La 3",
    "sg:city":"Neuenburg",
    "sg:orig_category":"Vermietung U Verpachtung von eigenen Immobilien",
    "sg:postcode":"2000",
    "sg:province":"Neuch\u00e2tel",
    "wof:name":"D\u00eeme Sa",
    "wof:placetype":"venue"
},
  "geometry": {"coordinates":[6.9310851097,46.9903335571],"type":"Point"}
}