{
  "type": "Feature",
  "properties": {
    "iso:country":"CH",
    "sg:address":"Tuggenerstrasse 3",
    "sg:city":"Z\u00fcrich",
    "sg:orig_category":"Unternehmensberatung",
    "sg:postcode":"8008",
    "sg:province":"Z\u00fcrich",
    "wof:name":"Bourgeois & Bisang Communication",
    "wof:placetype":"venue"
},
  "geometry": {"coordinates":[8.5551214218,47.3574752808],"type":"Point"}
}