{
  "type": "Feature",
  "properties": {
    "iso:country":"CH",
    "sg:address":"Hauptstrasse 17",
    "sg:city":"Unterkulm",
    "sg:orig_category":"Bijouterien Reparatur von Uhren U Schmuck",
    "sg:phone":"+41 17370405",
    "sg:postcode":"5726",
    "sg:province":"Aargau",
    "wof:name":"Marianne K\u00fcmmerli Uhren Bijouterie",
    "wof:placetype":"venue"
},
  "geometry": {"coordinates":[8.436834,47.35358],"type":"Point"}
}