{
  "type": "Feature",
  "properties": {
    "iso:country":"CH",
    "sg:address":"Im Haufacker 4",
    "sg:city":"Tuttwil",
    "sg:orig_category":"Architektur U Ingenieurb\u00fcros",
    "sg:postcode":"9546",
    "sg:province":"Thurgau",
    "wof:name":"Abditec Gmbh",
    "wof:placetype":"venue"
},
  "geometry": {"coordinates":[8.937002,47.483578],"type":"Point"}
}