{
  "type": "Feature",
  "properties": {
    "iso:country":"CH",
    "sg:address":"Douane Route De La 81 D",
    "sg:city":"Fahy",
    "sg:orig_category":"Herstellung U Zusammensetzung von Uhren Herstellung von Uhren",
    "sg:phone":"+41 32 476 60 76",
    "sg:postcode":"2916",
    "sg:province":"Jura",
    "wof:name":"Hauert Serge Et Fils Sa",
    "wof:placetype":"venue"
},
  "geometry": {"coordinates":[6.9486298561,47.4190559387],"type":"Point"}
}