{
  "type": "Feature",
  "properties": {
    "iso:country":"CH",
    "sg:address":"Z\u00fcrcherstrasse 172",
    "sg:city":"Neuenhof",
    "sg:orig_category":"Sonstige Kultur U Unterhaltungseinrichtungen",
    "sg:phone":"+41 56 406 31 53",
    "sg:postcode":"5432",
    "sg:province":"Aargau",
    "wof:name":"Jugendtreff Neuenhof",
    "wof:placetype":"venue"
},
  "geometry": {"coordinates":[8.3320007324,47.4449615479],"type":"Point"}
}