{
  "type": "Feature",
  "properties": {
    "iso:country":"CH",
    "sg:address":"Im Glockenacker 52",
    "sg:city":"Z\u00fcrich",
    "sg:orig_category":"Werbung",
    "sg:phone":"+41 71 244 66 31",
    "sg:postcode":"8053",
    "sg:province":"Z\u00fcrich",
    "wof:name":"Bpr Werbeagentur Ag",
    "wof:placetype":"venue"
},
  "geometry": {"coordinates":[9.3975257874,47.4310379028],"type":"Point"}
}