{
  "type": "Feature",
  "properties": {
    "iso:country":"CH",
    "sg:address":"Amriswilerstrasse",
    "sg:city":"Amriswil",
    "sg:orig_category":"RESTAURANTS: TEA-ROOMS",
    "sg:phone":"+41 71 411 74 20",
    "sg:postcode":"8580",
    "sg:province":"Thurgau",
    "wof:name":"Chenaux Restaurationsbetriebe",
    "wof:placetype":"venue"
},
  "geometry": {"coordinates":[9.3283185959,47.5384597778],"type":"Point"}
}