{
  "type": "Feature",
  "properties": {
    "iso:country":"CH",
    "sg:address":"Steinenstrasse 23",
    "sg:city":"Horw",
    "sg:orig_category":"Verlegen von Fliesen U Platten",
    "sg:phone":"+41 41 340 37 25",
    "sg:postcode":"6048",
    "sg:province":"Luzern",
    "wof:name":"Emil Wermelinger Plattengesch\u00e4ft",
    "wof:placetype":"venue"
},
  "geometry": {"coordinates":[8.303237915,47.0152778625],"type":"Point"}
}