{
  "type": "Feature",
  "properties": {
    "iso:country":"CH",
    "sg:address":"1143",
    "sg:city":"Apples",
    "sg:orig_category":"Stukkateurgewerbe, Gipserei U Verputzerei",
    "sg:phone":"+41 22 342 73 68",
    "sg:postcode":"1143",
    "sg:province":"Vaud",
    "wof:name":"Preziuso Fr\u00e8res Gypserie & Peinture",
    "wof:placetype":"venue"
},
  "geometry": {"coordinates":[6.1423997879,46.1807746887],"type":"Point"}
}