{
  "type": "Feature",
  "properties": {
    "iso:country":"CH",
    "sg:address":"3970",
    "sg:city":"Salgesch",
    "sg:orig_category":"Herstellung von Drahtwaren",
    "sg:phone":"+41 79 435 24 30",
    "sg:postcode":"3970",
    "sg:province":"Valais",
    "wof:name":"Roby Ferraillage Sa Armierungen",
    "wof:placetype":"venue"
},
  "geometry": {"coordinates":[7.5696148872,46.3114013672],"type":"Point"}
}