{
  "type": "Feature",
  "properties": {
    "iso:country":"CH",
    "sg:address":"Chemin Des Coquelicots 11",
    "sg:city":"Vernier",
    "sg:orig_category":"Grosshandel mit Geschenkartikeln U Souvenirs Reiseb\u00fcros U Reiseveranstalter",
    "sg:phone":"+41 17421642",
    "sg:postcode":"1214",
    "sg:province":"Gen\u00e8ve",
    "wof:name":"Nioe Nostalgie Istanbul Orient Express Ag",
    "wof:placetype":"venue"
},
  "geometry": {"coordinates":[8.3954296112,47.4204406738],"type":"Point"}
}