{
  "type": "Feature",
  "properties": {
    "iso:country":"CH",
    "sg:address":"Hintergasse 4 8180 B\u00fclach. Postfach",
    "sg:city":"B\u00fclach",
    "sg:orig_category":"Architektur U Ingenieurb\u00fcros Architekturb\u00fcros",
    "sg:phone":"+41 18602474",
    "sg:postcode":"8180",
    "sg:province":"Z\u00fcrich",
    "wof:name":"Bohli Gerhard",
    "wof:placetype":"venue"
},
  "geometry": {"coordinates":[8.541019,47.518013],"type":"Point"}
}