{
  "type": "Feature",
  "properties": {
    "iso:country":"CH",
    "sg:address":"Hofstrasse 14",
    "sg:city":"H\u00f6ri",
    "sg:orig_category":"Autogaragen",
    "sg:phone":"+41 18602208",
    "sg:postcode":"8181",
    "sg:province":"Z\u00fcrich",
    "wof:name":"Josef Lamparter Autoreparaturwerkst\u00e4tte",
    "wof:placetype":"venue"
},
  "geometry": {"coordinates":[8.518547,47.51228],"type":"Point"}
}