{
  "type": "Feature",
  "properties": {
    "iso:country":"CH",
    "sg:address":"Weissensteinstrasse 53b",
    "sg:city":"Bern",
    "sg:orig_category":"Detailhandel mit Fahrr\u00e4dern Handel mit Motorr\u00e4dern, Teilen U Zubeh\u00f6r Instandhaltung U Reparatur von ",
    "sg:phone":"+41 31 371 55 16",
    "sg:postcode":"3007",
    "sg:province":"Bern",
    "wof:name":"Heinz M\u00fcller Velos-motos",
    "wof:placetype":"venue"
},
  "geometry": {"coordinates":[7.4272689819,46.9391403198],"type":"Point"}
}