{
  "type": "Feature",
  "properties": {
    "iso:country":"CH",
    "sg:address":"Leimenstrasse 76",
    "sg:city":"Basel",
    "sg:classifiers":[
        {
            "category":"Professional",
            "subcategory":"Advertising",
            "type":"Services"
        }
    ],
    "sg:phone":"+41 61 271 95 55",
    "sg:postcode":"4051",
    "sg:province":"Basel-Stadt",
    "sg:tags":[
        "postcard"
    ],
    "wof:name":"Emil Kr\u00e4uliger Ag",
    "wof:placetype":"venue"
},
  "geometry": {"coordinates":[7.579955,47.551804],"type":"Point"}
}