{
  "type": "Feature",
  "properties": {
    "iso:country":"CH",
    "sg:address":"Gerenstrasse 71",
    "sg:city":"Regensdorf",
    "sg:orig_category":"G\u00fcterbef\u00f6rderung im Strassenverkehr",
    "sg:postcode":"8105",
    "sg:province":"Z\u00fcrich",
    "wof:name":"Kuster",
    "wof:placetype":"venue"
},
  "geometry": {"coordinates":[8.4621400833,47.4357452393],"type":"Point"}
}