{
  "type": "Feature",
  "properties": {
    "iso:country":"CH",
    "sg:address":"Forchstrasse 1",
    "sg:city":"Kloten",
    "sg:orig_category":"Allgemeiner Hoch U Tiefbau",
    "sg:postcode":"8302",
    "sg:province":"Z\u00fcrich",
    "wof:name":"W\u00fcest-haslimeier Leo",
    "wof:placetype":"venue"
},
  "geometry": {"coordinates":[8.57619,47.44709],"type":"Point"}
}