{
  "type": "Feature",
  "properties": {
    "iso:country":"CH",
    "sg:address":"Escherwiese",
    "sg:city":"Uznach",
    "sg:orig_category":"Maler U Glasergewerbe Maurerarbeiten",
    "sg:phone":"+41 55 280 66 85",
    "sg:postcode":"8730",
    "sg:province":"St. Gallen",
    "wof:name":"Mm Martin Meier Gmbh",
    "wof:placetype":"venue"
},
  "geometry": {"coordinates":[8.9802513123,47.2238464355],"type":"Point"}
}