{
  "type": "Feature",
  "properties": {
    "iso:country":"CH",
    "sg:address":"Allmeindstrasse 13",
    "sg:city":"Schmerikon",
    "sg:orig_category":"Herstellung von Werkzeugen Herstellung von Werkzeugmaschinen",
    "sg:phone":"+41 55 286 12 21",
    "sg:postcode":"8716",
    "sg:province":"St. Gallen",
    "wof:name":"Frema Ag",
    "wof:placetype":"venue"
},
  "geometry": {"coordinates":[8.9540605545,47.2227096558],"type":"Point"}
}