{
  "type": "Feature",
  "properties": {
    "iso:country":"CH",
    "sg:address":"Riedacker",
    "sg:city":"Plasselb",
    "sg:orig_category":"Bauspenglerei Dachdeckerei",
    "sg:phone":"+41 26 419 10 60",
    "sg:postcode":"1737",
    "sg:province":"Fribourg",
    "wof:name":"Max Krattinger Spenglerei & Bedachungen",
    "wof:placetype":"venue"
},
  "geometry": {"coordinates":[7.254154,46.731316],"type":"Point"}
}