{
  "type": "Feature",
  "properties": {
    "iso:country":"CH",
    "sg:address":"Alte Steinhauserstrasse 21 6330 Cham. Postfach 5337",
    "sg:city":"Cham",
    "sg:orig_category":"Grosshandel mit B\u00fcromaschinen Grosshandel mit Datenverarbeitungsger\u00e4ten",
    "sg:phone":"+41 41 741 77 22",
    "sg:postcode":"6330",
    "sg:province":"Zug",
    "wof:name":"Zenon Ag",
    "wof:placetype":"venue"
},
  "geometry": {"coordinates":[8.4744729996,47.188709259],"type":"Point"}
}