{
  "type": "Feature",
  "properties": {
    "iso:country":"CH",
    "sg:address":"Bellikerstrasse",
    "sg:city":"Berikon",
    "sg:orig_category":"Fachdetailhandel mit Nahrungsmitteln, Getr\u00e4nken U Tabakwaren in Verkaufsr\u00e4umen",
    "sg:phone":"+41 56 633 33 00",
    "sg:postcode":"8965",
    "sg:province":"Aargau",
    "wof:name":"Spar Supermarkt",
    "wof:placetype":"venue"
},
  "geometry": {"coordinates":[8.3669900894,47.3627738953],"type":"Point"}
}