{
  "type": "Feature",
  "properties": {
    "iso:country":"CH",
    "sg:address":"Krist 93",
    "sg:city":"Eschen",
    "sg:orig_category":"Sonstiges Gesundheitswesen",
    "sg:postcode":"9492",
    "wof:name":"Krankenmobilienmagazin Des Samaritervereins Unterland",
    "wof:placetype":"venue"
},
  "geometry": {"coordinates":[9.5155000687,47.2162513733],"type":"Point"}
}