{
  "type": "Feature",
  "properties": {
    "iso:country":"CH",
    "sg:address":"Neubr\u00fcckstrasse 72",
    "sg:city":"Bern",
    "sg:orig_category":"Herstellung von Hebezeugen U F\u00f6rdermitteln",
    "sg:phone":"+41 31 301 84 00",
    "sg:postcode":"3012",
    "sg:province":"Bern",
    "wof:name":"Anko Comtrans Gmbh",
    "wof:placetype":"venue"
},
  "geometry": {"coordinates":[7.4374232292,46.9571914673],"type":"Point"}
}