{
  "type": "Feature",
  "properties": {
    "iso:country":"CH",
    "sg:address":"Riedweg 4",
    "sg:city":"D\u00fcbendorf",
    "sg:orig_category":"Unternehmensberatung",
    "sg:phone":"+41 18225033",
    "sg:postcode":"8600",
    "sg:province":"Z\u00fcrich",
    "wof:name":"Beglinger Rolf, Beratungen",
    "wof:placetype":"venue"
},
  "geometry": {"coordinates":[8.6207885742,47.4042358398],"type":"Point"}
}