{
  "type": "Feature",
  "properties": {
    "iso:country":"CH",
    "sg:address":"Hauptstrasse 33 3186 D\u00fcdingen. Postfach 50",
    "sg:city":"D\u00fcdingen",
    "sg:orig_category":"Bau U Wohngenossenschaften",
    "sg:phone":"+41 26 493 18 45",
    "sg:postcode":"3186",
    "sg:province":"Fribourg",
    "wof:name":"Wohnbau Riedli Ag Demant Ag",
    "wof:placetype":"venue"
},
  "geometry": {"coordinates":[7.19073,46.851006],"type":"Point"}
}