{
  "type": "Feature",
  "properties": {
    "iso:country":"CH",
    "sg:address":"Petit-saconnex Chemin Du 28 1209 Gen\u00e8ve. Postfach",
    "sg:city":"Gen\u00e8ve",
    "sg:orig_category":"Grosshandel mit sonstigen Maschinen U Ausr\u00fcstungen f\u00fcr Industrie, Handel U Schiffahrt",
    "sg:postcode":"1209",
    "sg:province":"Gen\u00e8ve",
    "wof:name":"Abela Casa Sa",
    "wof:placetype":"venue"
},
  "geometry": {"coordinates":[6.1322398186,46.2238006592],"type":"Point"}
}