{
  "type": "Feature",
  "properties": {
    "iso:country":"CH",
    "sg:address":"M\u00fchlestrasse 20",
    "sg:city":"Oberwangen B. Bern",
    "sg:orig_category":"Wirtschaft U Handel, Transport U Versand",
    "sg:phone":"+41 31 980 40 41",
    "sg:postcode":"3173",
    "sg:province":"Bern",
    "wof:name":"Medipool Ag",
    "wof:placetype":"venue"
},
  "geometry": {"coordinates":[7.361641,46.916481],"type":"Point"}
}