{
  "type": "Feature",
  "properties": {
    "iso:country":"CH",
    "sg:address":"Binzstrasse 18 8045 Z\u00fcrich. Postfach 8045 Z\u00fcrich",
    "sg:city":"Zust",
    "sg:orig_category":"Wirtschaftspr\u00fcfung, Steuerberatung U Treuhand",
    "sg:phone":"+41 14556200",
    "sg:postcode":"45",
    "wof:name":"Kabo-treuhand Bobak Monika",
    "wof:placetype":"venue"
},
  "geometry": {"coordinates":[8.5150213242,47.3627510071],"type":"Point"}
}