{
  "type": "Feature",
  "properties": {
    "iso:country":"CH",
    "sg:address":"6934",
    "sg:city":"Bioggio",
    "sg:orig_category":"Schulpflegen",
    "sg:postcode":"6934",
    "sg:province":"Ticino",
    "wof:name":"Delegazione Scolastica Del Comune Di Bioggio",
    "wof:placetype":"venue"
},
  "geometry": {"coordinates":[8.9089002609,46.0141906738],"type":"Point"}
}