{
  "type": "Feature",
  "properties": {
    "iso:country":"CH",
    "sg:address":"Rietwisstrasse 5",
    "sg:city":"Herisau",
    "sg:classifiers":[
        {
            "category":"Landmark",
            "subcategory":"Fountain",
            "type":"Public Place"
        }
    ],
    "sg:phone":"+41 71 352 43 09",
    "sg:postcode":"9100",
    "sg:province":"Appenzell Ausserrhoden",
    "wof:name":"Riedl Steinbildhauerei",
    "wof:placetype":"venue"
},
  "geometry": {"coordinates":[9.2632846832,47.3976554871],"type":"Point"}
}