{
  "type": "Feature",
  "properties": {
    "iso:country":"CH",
    "sg:address":"Via S.bernardo 7",
    "sg:city":"Canobbio",
    "sg:orig_category":"Allgemeiner Hochbau Strassenbau",
    "sg:phone":"+41 91 942 71 59",
    "sg:postcode":"6952",
    "sg:province":"Ticino",
    "wof:name":"Sessi-spiess Sa Impresa Edile",
    "wof:placetype":"venue"
},
  "geometry": {"coordinates":[8.96624,46.034813],"type":"Point"}
}