{
  "type": "Feature",
  "properties": {
    "iso:country":"CH",
    "sg:address":"Sch\u00fctzengraben 24",
    "sg:city":"Schaffhausen",
    "sg:orig_category":"Detailhandel mit Waren verschiedener Art, Hauptrichtung Nahrungsmittel",
    "sg:phone":"+41 52 625 06 68",
    "sg:postcode":"8200",
    "sg:province":"Schaffhausen",
    "wof:name":"Gidor Coiffure",
    "wof:placetype":"venue"
},
  "geometry": {"coordinates":[8.6354541779,47.6989479065],"type":"Point"}
}