{
  "type": "Feature",
  "properties": {
    "iso:country":"CH",
    "sg:address":"6702",
    "sg:city":"Claro",
    "sg:orig_category":"G\u00fcterbef\u00f6rderung im Strassenverkehr",
    "sg:phone":"+41 91 863 23 03",
    "sg:postcode":"6702",
    "sg:province":"Ticino",
    "wof:name":"Karp D Sa",
    "wof:placetype":"venue"
},
  "geometry": {"coordinates":[9.020321846,46.2521896362],"type":"Point"}
}