{
  "type": "Feature",
  "properties": {
    "iso:country":"CH",
    "sg:address":"T\u00f6distrasse 32",
    "sg:city":"Hombrechtikon",
    "sg:classifiers":[
        {
            "category":"Insurance",
            "subcategory":"Insurance Agent",
            "type":"Services"
        }
    ],
    "sg:phone":"+41 55 244 32 74",
    "sg:postcode":"8634",
    "sg:province":"Z\u00fcrich",
    "sg:tags":[
        "versicherungsagenturen",
        "-broker"
    ],
    "wof:name":"Elvia Versicherungen Agentur Hugo G\u00fcnter",
    "wof:placetype":"venue"
},
  "geometry": {"coordinates":[8.7812070847,47.2546272278],"type":"Point"}
}