{
  "type": "Feature",
  "properties": {
    "iso:country":"CH",
    "sg:address":"Industriestrasse 9",
    "sg:city":"Zug",
    "sg:orig_category":"Unternehmensberatung",
    "sg:phone":"+41 14013234",
    "sg:postcode":"6300",
    "sg:province":"Zug",
    "wof:name":"Klein Peter Consulting",
    "wof:placetype":"venue"
},
  "geometry": {"coordinates":[8.4491834641,47.3757247925],"type":"Point"}
}