{
  "type": "Feature",
  "properties": {
    "iso:country":"CH",
    "sg:address":"Baarerstrasse 2",
    "sg:city":"Zug",
    "sg:orig_category":"Wirtschaftspr\u00fcfung, Steuerberatung U Treuhand",
    "sg:postcode":"6300",
    "sg:province":"Zug",
    "wof:name":"Blk Consulting Gmbh",
    "wof:placetype":"venue"
},
  "geometry": {"coordinates":[8.5161046982,47.1706962585],"type":"Point"}
}