{
  "type": "Feature",
  "properties": {
    "iso:country":"CH",
    "sg:address":"Farbg\u00e4ssli 1",
    "sg:city":"Klus",
    "sg:classifiers":[
        {
            "category":"Restaurant",
            "type":"Food & Drink"
        }
    ],
    "sg:phone":"+41 62 391 50 24",
    "sg:postcode":"4710",
    "sg:province":"Solothurn",
    "wof:name":"Restaurant Burg",
    "wof:placetype":"venue"
},
  "geometry": {"coordinates":[7.6893429756,47.3072738647],"type":"Point"}
}