{
  "type": "Feature",
  "properties": {
    "iso:country":"CH",
    "sg:address":"Gewerbestrasse 12",
    "sg:city":"Subingen",
    "sg:classifiers":[
        {
            "category":"Building & Trades",
            "subcategory":"Cleaning & Sanitation",
            "type":"Services"
        }
    ],
    "sg:phone":"+41 32 682 27 27",
    "sg:postcode":"4553",
    "sg:province":"Solothurn",
    "sg:tags":[
        "carpet"
    ],
    "wof:name":"Stampfli Reinigungen Ag",
    "wof:placetype":"venue"
},
  "geometry": {"coordinates":[7.604132,47.196888],"type":"Point"}
}