{
  "type": "Feature",
  "properties": {
    "iso:country":"CH",
    "sg:address":"Hinter Dem Ack 31",
    "sg:city":"Speicherschwendi",
    "sg:orig_category":"Fachdetailhandel in Verkaufsr\u00e4umen",
    "sg:phone":"+41 71 222 68 74",
    "sg:postcode":"9037",
    "sg:province":"Appenzell Ausserrhoden",
    "wof:name":"Photofront Gmbh",
    "wof:placetype":"venue"
},
  "geometry": {"coordinates":[9.4368848801,47.4252853394],"type":"Point"}
}