{
  "type": "Feature",
  "properties": {
    "iso:country":"CH",
    "sg:address":"Avenue De Marcelin 7",
    "sg:city":"Morges",
    "sg:orig_category":"Berufsberatungen",
    "sg:phone":"+41 21 801 73 46",
    "sg:postcode":"1110",
    "sg:province":"Vaud",
    "wof:name":"Orientation Professionnelle De La C\u00f4te-est",
    "wof:placetype":"venue"
},
  "geometry": {"coordinates":[6.49231,46.512936],"type":"Point"}
}