{
  "type": "Feature",
  "properties": {
    "iso:country":"CH",
    "sg:address":"Unionstrasse 4",
    "sg:city":"Goldach",
    "sg:orig_category":"Kauf U Verkauf von Immobilien auf eigene Rechnung",
    "sg:postcode":"9403",
    "sg:province":"St. Gallen",
    "wof:name":"Asiram Ag",
    "wof:placetype":"venue"
},
  "geometry": {"coordinates":[8.2856721878,47.3546485901],"type":"Point"}
}