{
  "type": "Feature",
  "properties": {
    "iso:country":"CH",
    "sg:address":"Grundstrasse 11 8004 Z\u00fcrich. Postfach 1274",
    "sg:city":"Z\u00fcrich",
    "sg:orig_category":"Detailhandel mit Beleuchtungs U Haushaltsgegenst\u00e4nden",
    "sg:phone":"+41 12414450",
    "sg:postcode":"8040",
    "sg:province":"Z\u00fcrich",
    "wof:name":"A. Seiler Haushaltsartikel Ag",
    "wof:placetype":"venue"
},
  "geometry": {"coordinates":[8.498932,47.384705],"type":"Point"}
}