{
  "type": "Feature",
  "properties": {
    "addr:full":"3929 T\u00e4sch Valais 3929",
    "addr:housenumber":"3929",
    "addr:postcode":"3929",
    "addr:street":"Taesch Valais",
    "iso:country":"CH",
    "sg:address":"3929",
    "sg:city":"T\u00e4sch",
    "sg:orig_category":"Detailhandel mit Brot, Back U S\u00fcsswaren",
    "sg:phone":"+41 27 967 35 92",
    "sg:postcode":"3929",
    "sg:province":"Valais",
    "wof:name":"B\u00e4ckerei-konditorei Mooser-gruber Bruno",
    "wof:placetype":"venue"
},
  "geometry": {"coordinates":[7.776325,46.069695],"type":"Point"}
}