{
  "type": "Feature",
  "properties": {
    "iso:country":"CH",
    "sg:address":"Aumattweg 4a",
    "sg:city":"Aarau",
    "sg:orig_category":"Praxis f\u00fcr Atlaslogie",
    "sg:phone":"+41 62 823 24 32",
    "sg:postcode":"5000",
    "sg:province":"Aargau",
    "wof:name":"Paulo Bleisch Praxis F\u00fcr Atlaslogie",
    "wof:placetype":"venue"
},
  "geometry": {"coordinates":[8.0534515381,47.3963623047],"type":"Point"}
}