{
  "type": "Feature",
  "properties": {
    "iso:country":"CH",
    "sg:address":"H\u00f6henweg 320",
    "sg:city":"Berikon",
    "sg:orig_category":"Vermietung U Verpachtung von eigenen Immobilien Vermittlung von Immobilien",
    "sg:phone":"+41 56 633 24 78",
    "sg:postcode":"8965",
    "sg:province":"Aargau",
    "wof:name":"Christian Schmid Immobilien",
    "wof:placetype":"venue"
},
  "geometry": {"coordinates":[8.3605098724,47.3597297668],"type":"Point"}
}