{
  "type": "Feature",
  "properties": {
    "iso:country":"CH",
    "sg:address":"L\u00f6wenstrasse 26 8001 Z\u00fcrich. Postfach 8023",
    "sg:city":"Z\u00fcrich",
    "sg:orig_category":"Grosshandel mit Textilien",
    "sg:phone":"+41 12111752",
    "sg:postcode":"8000",
    "sg:province":"Z\u00fcrich",
    "wof:name":"Rueff Ag",
    "wof:placetype":"venue"
},
  "geometry": {"coordinates":[8.5358667374,47.3744392395],"type":"Point"}
}