{
  "type": "Feature",
  "properties": {
    "iso:country":"CH",
    "sg:address":"Landstrasse 82",
    "sg:city":"W\u00fcrenlos",
    "sg:orig_category":"Erbringung von Dienstleistungen f\u00fcr Unternehmen",
    "sg:phone":"+41 56 424 13 06",
    "sg:postcode":"5436",
    "sg:province":"Aargau",
    "wof:name":"Aebischer Raumgestaltung Gmbh",
    "wof:placetype":"venue"
},
  "geometry": {"coordinates":[8.362953186,47.4417228699],"type":"Point"}
}