{
  "type": "Feature",
  "properties": {
    "addr:full":"Bahnhofstrasse 30 Laufen Basel-Landschaft 4242",
    "addr:housenumber":"30",
    "addr:postcode":"4242",
    "addr:street":"Bahnhofstrasse",
    "iso:country":"CH",
    "sg:address":"Bahnhofstrasse 30",
    "sg:city":"Laufen",
    "sg:classifiers":[
        {
            "category":"Banks & Credit Unions",
            "subcategory":"Bank",
            "type":"Services"
        }
    ],
    "sg:phone":"+41 61 761 60 11",
    "sg:postcode":"4242",
    "sg:province":"Basel-Landschaft",
    "wof:name":"Basellandschaftliche, Kantonalbank",
    "wof:placetype":"venue"
},
  "geometry": {"coordinates":[7.501909,47.418682],"type":"Point"}
}