{
  "type": "Feature",
  "properties": {
    "iso:country":"CH",
    "sg:address":"Dorfstrasse 1a",
    "sg:city":"Hinterkappelen",
    "sg:orig_category":"Tanzschulen, Tanzlehrer",
    "sg:phone":"+41 31 901 07 13",
    "sg:postcode":"3032",
    "sg:province":"Bern",
    "wof:name":"Gudrun Blom Tanzwerkstatt",
    "wof:placetype":"venue"
},
  "geometry": {"coordinates":[7.377767086,46.9680290222],"type":"Point"}
}