{
  "type": "Feature",
  "properties": {
    "addr:full":"Rosengartenstrasse 6 Weesen St. Gallen 8872",
    "addr:housenumber":"6",
    "addr:postcode":"8872",
    "addr:street":"Rosengartenstrasse",
    "iso:country":"CH",
    "sg:address":"Rosengartenstrasse 6",
    "sg:city":"Weesen",
    "sg:orig_category":"Arztpraxen",
    "sg:phone":"+41 19107770",
    "sg:postcode":"8872",
    "sg:province":"St. Gallen",
    "wof:name":"Dr.med.elisabeth Toszeghi Spezial\u00e4rztin Fmh",
    "wof:placetype":"venue"
},
  "geometry": {"coordinates":[8.588091,47.306877],"type":"Point"}
}