{
  "type": "Feature",
  "properties": {
    "iso:country":"CH",
    "sg:address":"Rue Haldimand 61. 1400 Yverdon-les-bains. Postfach",
    "sg:city":"Yverdon-les-bains",
    "sg:orig_category":"Elektroinstallation",
    "sg:phone":"+41 22 328 30 11",
    "sg:postcode":"1400",
    "sg:province":"Vaud",
    "wof:name":"Galera Juan",
    "wof:placetype":"venue"
},
  "geometry": {"coordinates":[6.1900620461,46.1969070435],"type":"Point"}
}