{
  "type": "Feature",
  "properties": {
    "iso:country":"CH",
    "sg:address":"Kirchstrasse 24 8580 Amriswil. Postfach",
    "sg:city":"Amriswil",
    "sg:orig_category":"Schiffsbau ohne Boots U Yachtbau",
    "sg:postcode":"8580",
    "sg:province":"Thurgau",
    "wof:name":"San Benedetto Schifffahrt Ag",
    "wof:placetype":"venue"
},
  "geometry": {"coordinates":[9.299665451,47.5483131409],"type":"Point"}
}