{
  "type": "Feature",
  "properties": {
    "iso:country":"CH",
    "sg:address":"Rue Du Grand-ch\u00eane 4",
    "sg:city":"Lausanne",
    "sg:orig_category":"Arztpraxen",
    "sg:phone":"+41 21 320 39 00",
    "sg:postcode":"1003",
    "sg:province":"Vaud",
    "wof:name":"Dr M\u00e9d. Marie Belen Ona M\u00e9decin Sp\u00e9cialiste Fmh",
    "wof:placetype":"venue"
},
  "geometry": {"coordinates":[6.631256,46.51981],"type":"Point"}
}