{
  "type": "Feature",
  "properties": {
    "iso:country":"CH",
    "sg:address":"Chemin Nicolas-bogueret 26",
    "sg:city":"Vernier",
    "sg:orig_category":"Non-Classified Establishments",
    "sg:postcode":"1214",
    "sg:province":"Gen\u00e8ve",
    "wof:name":"Fiorenzo Magro",
    "wof:placetype":"venue"
},
  "geometry": {"coordinates":[6.0981807709,46.2014961243],"type":"Point"}
}