{
  "type": "Feature",
  "properties": {
    "iso:country":"CH",
    "sg:address":"Dorfstrasse 27",
    "sg:city":"Baden-d\u00e4ttwil",
    "sg:orig_category":"Industrie, Metallindustrie",
    "sg:phone":"+41 56 470 27 22",
    "sg:postcode":"5405",
    "sg:province":"Aargau",
    "wof:name":"Siewal Gmbh",
    "wof:placetype":"venue"
},
  "geometry": {"coordinates":[8.286133,47.452168],"type":"Point"}
}