{
  "type": "Feature",
  "properties": {
    "iso:country":"CH",
    "sg:address":"Eberm\u00e4tteli 8",
    "sg:city":"Maisprach",
    "sg:classifiers":[
        {
            "category":"Manufacturing",
            "subcategory":"Metals",
            "type":"Manufacturing & Wholesale Goods"
        }
    ],
    "sg:phone":"+41 61 845 94 44",
    "sg:postcode":"4464",
    "sg:province":"Basel-Landschaft",
    "sg:tags":[
        "-",
        "machine",
        "equipment",
        "engineering",
        "machinery",
        "mechanical"
    ],
    "wof:name":"Schwarz & Riethm\u00dcller Ag",
    "wof:placetype":"venue"
},
  "geometry": {"coordinates":[7.8412399292,47.5241127014],"type":"Point"}
}