{
  "type": "Feature",
  "properties": {
    "iso:country":"CH",
    "sg:address":"Blumenaustrasse 36",
    "sg:city":"St.gallen",
    "sg:orig_category":"Sonstige Hilfs U Nebent\u00e4tigkeiten f\u00fcr die Schiffahrt",
    "sg:postcode":"9000",
    "sg:province":"St. Gallen",
    "wof:name":"Genossenschaft Bootslager Schw\u00e4rzebach",
    "wof:placetype":"venue"
},
  "geometry": {"coordinates":[9.3787813187,47.4287757874],"type":"Point"}
}