{
  "type": "Feature",
  "properties": {
    "iso:country":"CH",
    "sg:address":"Vermont Rue De 42 1202 Gen\u00e8ve. Postfach",
    "sg:city":"Gen\u00e8ve",
    "sg:orig_category":"Unclassifiable Establishments",
    "sg:phone":"+41 22 733 30 58",
    "sg:postcode":"1201",
    "sg:province":"Gen\u00e8ve",
    "wof:name":"De Boursac Guy",
    "wof:placetype":"venue"
},
  "geometry": {"coordinates":[6.1379771233,46.2188873291],"type":"Point"}
}