{
  "type": "Feature",
  "properties": {
    "iso:country":"CH",
    "sg:address":"Breitenmattstrasse 3",
    "sg:city":"D\u00fcrnten",
    "sg:orig_category":"Erbringung von Dienstleistungen f\u00fcr Unternehmen",
    "sg:postcode":"8635",
    "sg:province":"Z\u00fcrich",
    "wof:name":"Tobler Grafik",
    "wof:placetype":"venue"
},
  "geometry": {"coordinates":[8.8725204468,47.2759552002],"type":"Point"}
}