{
  "type": "Feature",
  "properties": {
    "iso:country":"CH",
    "sg:address":"Blumenstrasse 18",
    "sg:city":"Goldach",
    "sg:orig_category":"Pensionskassen",
    "sg:phone":"+41 71 841 12 72",
    "sg:postcode":"9403",
    "sg:province":"St. Gallen",
    "wof:name":"Personalf\u00fcrsorgestiftung Der Firma Z\u00fcllig & Co Ag Goldach",
    "wof:placetype":"venue"
},
  "geometry": {"coordinates":[9.4680814743,47.4754905701],"type":"Point"}
}