{
  "type": "Feature",
  "properties": {
    "iso:country":"CH",
    "sg:address":"Grundstrasse 14",
    "sg:city":"Rotkreuz",
    "sg:classifiers":[
        {
            "category":"Internet Cafe",
            "subcategory":"None",
            "type":"Food & Drink"
        }
    ],
    "sg:phone":"+41 41 792 20 20",
    "sg:postcode":"6343",
    "sg:province":"Zug",
    "sg:tags":[
        "provider"
    ],
    "wof:name":"Internezzo Ag Agentur F\u00fcr Web-kommunikation",
    "wof:placetype":"venue"
},
  "geometry": {"coordinates":[8.4304237366,47.145866394],"type":"Point"}
}