{
  "type": "Feature",
  "properties": {
    "iso:country":"CH",
    "sg:address":"Neue Winterthurerstrasse 40",
    "sg:city":"Bassersdorf",
    "sg:orig_category":"Gartenbau Wohnheime f\u00fcr Kinder U Jugendliche",
    "sg:phone":"+41 18365454",
    "sg:postcode":"8303",
    "sg:province":"Z\u00fcrich",
    "wof:name":"Landheim Br\u00fcttisellen",
    "wof:placetype":"venue"
},
  "geometry": {"coordinates":[8.6381416321,47.4277610779],"type":"Point"}
}