{
  "type": "Feature",
  "properties": {
    "iso:country":"CH",
    "sg:address":"Oberdorf 10",
    "sg:city":"W\u00e4ldi",
    "sg:orig_category":"Softwareentwicklung U beratung",
    "sg:phone":"+41 71 477 17 84",
    "sg:postcode":"8564",
    "sg:province":"Thurgau",
    "wof:name":"Bruhin Informatik",
    "wof:placetype":"venue"
},
  "geometry": {"coordinates":[9.0966882706,47.6182174683],"type":"Point"}
}