{
  "type": "Feature",
  "properties": {
    "iso:country":"CH",
    "sg:address":"Unteres Ziel 3 9050 Appenzell. Postfach",
    "sg:city":"Appenzell",
    "sg:orig_category":"Handels-H\u00e4user U Gesellschaften",
    "sg:postcode":"9050",
    "sg:province":"Appenzell Innerhoden",
    "wof:name":"Seagull Trading Gmbh",
    "wof:placetype":"venue"
},
  "geometry": {"coordinates":[9.4086341858,47.3347358704],"type":"Point"}
}