{
  "type": "Feature",
  "properties": {
    "iso:country":"CH",
    "sg:address":"Linth-escher-strasse 27 8865 Bilten. Postfach",
    "sg:city":"Bilten",
    "sg:orig_category":"Herstellung von sonstigen Holzwaren",
    "sg:postcode":"8865",
    "sg:province":"Glarus",
    "wof:name":"Kosi Gmbh",
    "wof:placetype":"venue"
},
  "geometry": {"coordinates":[9.0311899185,47.1502037048],"type":"Point"}
}