{
  "type": "Feature",
  "properties": {
    "iso:country":"CH",
    "sg:address":"Quinta Via 48",
    "sg:city":"Biasca",
    "sg:orig_category":"Vermietung U Verpachtung von eigenen Immobilien",
    "sg:postcode":"6710",
    "sg:province":"Ticino",
    "wof:name":"Immobiliare Quinta Sa",
    "wof:placetype":"venue"
},
  "geometry": {"coordinates":[8.9716949463,46.3516616821],"type":"Point"}
}