{
  "type": "Feature",
  "properties": {
    "iso:country":"CH",
    "sg:address":"Krankenhausweg 2",
    "sg:city":"M\u00fcnsingen",
    "sg:orig_category":"Haltung von Gefl\u00fcgel",
    "sg:phone":"+41 26 411 17 34",
    "sg:postcode":"3110",
    "sg:province":"Bern",
    "wof:name":"Narcisse Dupraz Parc Avicole",
    "wof:placetype":"venue"
},
  "geometry": {"coordinates":[7.0834698677,46.7041091919],"type":"Point"}
}