{
  "type": "Feature",
  "properties": {
    "iso:country":"CH",
    "sg:address":"Georg Kempf-strasse 14",
    "sg:city":"Z\u00fcrich",
    "sg:orig_category":"Maurerarbeiten Stukkateurgewerbe, Gipserei U Verputzerei",
    "sg:phone":"+41 79 439 10 54",
    "sg:postcode":"8046",
    "sg:province":"Z\u00fcrich",
    "wof:name":"Donz\u00e9 Fr\u00e9sard Sa",
    "wof:placetype":"venue"
},
  "geometry": {"coordinates":[6.9546380043,47.2234611511],"type":"Point"}
}