{
  "type": "Feature",
  "properties": {
    "iso:country":"CH",
    "sg:address":"Hauptstrasse",
    "sg:city":"Stein",
    "sg:classifiers":[
        {
            "category":"Banks & Credit Unions",
            "subcategory":"Bank",
            "type":"Services"
        }
    ],
    "sg:phone":"+41 71 477 18 47",
    "sg:postcode":"9655",
    "sg:province":"St. Gallen",
    "wof:name":"Raiffeisenbank Steinach Berg Freidorf",
    "wof:placetype":"venue"
},
  "geometry": {"coordinates":[9.407158,47.486282],"type":"Point"}
}