{
  "type": "Feature",
  "properties": {
    "addr:full":"Pfarrhaus Wila Z\u00fcrich 8492",
    "addr:postcode":"8492",
    "addr:street":"Zuerich",
    "iso:country":"CH",
    "sg:address":"Pfarrhaus",
    "sg:city":"Wila",
    "sg:classifiers":[
        {
            "category":"Education",
            "subcategory":"Library",
            "type":"Public Place"
        }
    ],
    "sg:phone":"+41 52 385 12 45",
    "sg:postcode":"8492",
    "sg:province":"Z\u00fcrich",
    "sg:tags":[
        "u",
        "bibliotheken",
        "archive"
    ],
    "wof:name":"Volksbibliothek",
    "wof:placetype":"venue"
},
  "geometry": {"coordinates":[8.846028,47.419601],"type":"Point"}
}