{
  "type": "Feature",
  "properties": {
    "iso:country":"CH",
    "sg:address":"Saint-jean Rue De 58 1203 Gen\u00e8ve. Postfach",
    "sg:city":"Gen\u00e8ve",
    "sg:classifiers":[
        {
            "category":"Bars & Pubs",
            "type":"Food & Drink"
        }
    ],
    "sg:postcode":"1203",
    "sg:province":"Gen\u00e8ve",
    "wof:name":"Antonio Luis Almada",
    "wof:placetype":"venue"
},
  "geometry": {"coordinates":[6.132445,46.205273],"type":"Point"}
}