{
  "type": "Feature",
  "properties": {
    "iso:country":"CH",
    "sg:address":"Allmendstrasse 42 3600 Thun. Postfach 1228",
    "sg:city":"Thun",
    "sg:orig_category":"Detailhandel mit Brennstoffen U Heizmaterial G\u00fcterbef\u00f6rderung im Strassenverkehr",
    "sg:phone":"+41 41 630 12 46",
    "sg:postcode":"3601",
    "sg:province":"Bern",
    "wof:name":"Klara Bucher Brennstoffe Gasdep. Transporte",
    "wof:placetype":"venue"
},
  "geometry": {"coordinates":[8.311734,46.987858],"type":"Point"}
}