{
  "type": "Feature",
  "properties": {
    "iso:country":"CH",
    "sg:address":"Berufsschulstrasse 2",
    "sg:city":"Uster",
    "sg:orig_category":"Vereine Radio, Film and Foto",
    "sg:postcode":"8610",
    "sg:province":"Z\u00fcrich",
    "wof:name":"Foto-club Uster",
    "wof:placetype":"venue"
},
  "geometry": {"coordinates":[8.7079410553,47.3498306274],"type":"Point"}
}