{
  "type": "Feature",
  "properties": {
    "iso:country":"CH",
    "sg:address":"Route D'evian 1898 St-gingolph. Postfach",
    "sg:city":"St-gingolph",
    "sg:orig_category":"Binnenschiffahrt",
    "sg:phone":"+41 24 481 85 48",
    "sg:postcode":"1898",
    "sg:province":"Valais",
    "wof:name":"Navigation V + S",
    "wof:placetype":"venue"
},
  "geometry": {"coordinates":[6.80548,46.39275],"type":"Point"}
}