{
  "type": "Feature",
  "properties": {
    "iso:country":"CH",
    "sg:address":"T\u00e4fernstrasse 26",
    "sg:city":"D\u00e4ttwil",
    "sg:classifiers":[
        {
            "category":"Manufacturing",
            "subcategory":"Motor Vehicles & Parts",
            "type":"Manufacturing & Wholesale Goods"
        }
    ],
    "sg:phone":"+41 56 483 25 80",
    "sg:postcode":"5405",
    "sg:province":"Aargau",
    "sg:tags":[
        "adapter"
    ],
    "wof:name":"Gps Pr\u00fcftechnik Ag",
    "wof:placetype":"venue"
},
  "geometry": {"coordinates":[8.292271,47.449757],"type":"Point"}
}