{
  "type": "Feature",
  "properties": {
    "addr:full":"Im Rybeli 6 Willisau Luzern 6130",
    "addr:housenumber":"6",
    "addr:postcode":"6130",
    "addr:street":"Im Rybeli",
    "iso:country":"CH",
    "sg:address":"Im Rybeli 6",
    "sg:city":"Willisau",
    "sg:classifiers":[
        {
            "category":"Banks & Credit Unions",
            "subcategory":"Bank",
            "type":"Services"
        }
    ],
    "sg:phone":"+41 4145813495",
    "sg:postcode":"6130",
    "sg:province":"Luzern",
    "wof:name":"Rentenanstalt Swiss Life",
    "wof:placetype":"venue"
},
  "geometry": {"coordinates":[7.97783,47.119152],"type":"Point"}
}