{
  "type": "Feature",
  "properties": {
    "iso:country":"CH",
    "sg:address":"Sonnenhof 17",
    "sg:city":"Benglen",
    "sg:orig_category":"Handelsvermittlung U Grosshandel",
    "sg:phone":"+41 18251034",
    "sg:postcode":"8121",
    "sg:province":"Z\u00fcrich",
    "wof:name":"Naturapart Lamprecht",
    "wof:placetype":"venue"
},
  "geometry": {"coordinates":[8.6370754242,47.3585510254],"type":"Point"}
}