{
  "type": "Feature",
  "properties": {
    "iso:country":"CH",
    "sg:address":"Grabenweg 34",
    "sg:city":"Weisslingen",
    "sg:orig_category":"Kauf U Verkauf von Immobilien auf eigene Rechnung",
    "sg:phone":"+41 81 750 52 22",
    "sg:postcode":"8484",
    "sg:province":"Z\u00fcrich",
    "wof:name":"Success Internationale Verm\u00f6gensverwaltung Ag",
    "wof:placetype":"venue"
},
  "geometry": {"coordinates":[9.4732599258,47.1659355164],"type":"Point"}
}