{
  "type": "Feature",
  "properties": {
    "iso:country":"CH",
    "sg:address":"Le Portillon",
    "sg:city":"Tartegnin",
    "sg:orig_category":"Detailhandel mit Getr\u00e4nken Rebbau",
    "sg:phone":"+41 21 825 29 54",
    "sg:postcode":"1180",
    "sg:province":"Vaud",
    "wof:name":"Edgar Blanchard",
    "wof:placetype":"venue"
},
  "geometry": {"coordinates":[6.3380351067,46.4575614929],"type":"Point"}
}