{
  "type": "Feature",
  "properties": {
    "iso:country":"CH",
    "sg:address":"Bahnhofstrasse 2 3860 Meiringen. Postfach 704",
    "sg:city":"Meiringen",
    "sg:classifiers":[
        {
            "category":"Insurance",
            "subcategory":"Insurance Agent",
            "type":"Services"
        }
    ],
    "sg:phone":"+41 33 971 32 85",
    "sg:postcode":"3860",
    "sg:province":"Bern",
    "sg:tags":[
        "versicherungsagenturen",
        "-broker"
    ],
    "wof:name":"Winterthur-versicherungen Agentur Meiringen",
    "wof:placetype":"venue"
},
  "geometry": {"coordinates":[8.1853952408,46.7278938293],"type":"Point"}
}