{
  "type": "Feature",
  "properties": {
    "iso:country":"CH",
    "sg:address":"Chamerstrasse 52 6340 Baar. Postfach",
    "sg:city":"Zug",
    "sg:orig_category":"Unclassifiable Establishments",
    "sg:postcode":"6300",
    "sg:province":"Zug",
    "wof:name":"Pembal Holdings Ag",
    "wof:placetype":"venue"
},
  "geometry": {"coordinates":[8.5262966156,47.1947250366],"type":"Point"}
}