{
  "type": "Feature",
  "properties": {
    "iso:country":"CH",
    "sg:address":"Oskar Biderstrasse 5",
    "sg:city":"Langenbruck",
    "sg:orig_category":"Verkehrs- and Tourismusb\u00fcros",
    "sg:phone":"+41 62 390 17 77",
    "sg:postcode":"4438",
    "sg:province":"Basel-Landschaft",
    "wof:name":"Verkehrsb\u00fcro Langenbruck",
    "wof:placetype":"venue"
},
  "geometry": {"coordinates":[7.7692251205,47.3477210999],"type":"Point"}
}