{
  "type": "Feature",
  "properties": {
    "iso:country":"CH",
    "sg:address":"Schachen 723 3537 Eggiwil. Postfach 7264",
    "sg:city":"Bern",
    "sg:orig_category":"Grosshandel mit elektrischen Haushaltsger\u00e4ten, Radio U Fernsehger\u00e4ten Sonstiger Grosshandel",
    "sg:phone":"+41 21 624 37 23",
    "sg:postcode":"3001",
    "sg:province":"Bern",
    "wof:name":"Drep-superelectro Sa",
    "wof:placetype":"venue"
},
  "geometry": {"coordinates":[6.605342865,46.5278663635],"type":"Point"}
}