{
  "type": "Feature",
  "properties": {
    "iso:country":"CH",
    "sg:address":"Birmensdorferstrasse 83",
    "sg:city":"Z\u00fcrich",
    "sg:orig_category":"Herstellung von sonstigen chemischen Erzeugnissen Herstellung von sonstigen organischen Grundstoffen",
    "sg:phone":"+41 26 322 22 77",
    "sg:postcode":"8003",
    "sg:province":"Z\u00fcrich",
    "wof:name":"Nouvelle Fir Ag",
    "wof:placetype":"venue"
},
  "geometry": {"coordinates":[7.2044138908,46.7950325012],"type":"Point"}
}