{
  "type": "Feature",
  "properties": {
    "iso:country":"CH",
    "sg:address":"B\u00f6hlisjockes 9057 Weissbad. Postfach",
    "sg:city":"Weissbad",
    "sg:orig_category":"Verwaltung von Immobilien",
    "sg:postcode":"9057",
    "sg:province":"Appenzell Innerhoden",
    "wof:name":"Iva Gmbh",
    "wof:placetype":"venue"
},
  "geometry": {"coordinates":[9.436173439,47.3099136353],"type":"Point"}
}