{
  "type": "Feature",
  "properties": {
    "iso:country":"CH",
    "sg:address":"Halden 10",
    "sg:city":"Aarau",
    "sg:orig_category":"Arztpraxen",
    "sg:phone":"+41 56 622 99 50",
    "sg:postcode":"5000",
    "sg:province":"Aargau",
    "wof:name":"Dr.med.andr\u00e9 Miezi Arzt F.allgemeine Medizin Fmh",
    "wof:placetype":"venue"
},
  "geometry": {"coordinates":[8.273175,47.34906],"type":"Point"}
}