{
  "type": "Feature",
  "properties": {
    "iso:country":"CH",
    "sg:address":"Schena Voa La 2 7077 Valbella. Postfach",
    "sg:city":"Valbella",
    "sg:orig_category":"Finanzierungsinstitutionen",
    "sg:postcode":"7077",
    "sg:province":"Graubunden",
    "wof:name":"Guarda Lai Ag Investment-projekte; Evaluation, Realisierung Usw",
    "wof:placetype":"venue"
},
  "geometry": {"coordinates":[9.555934906,46.7498664856],"type":"Point"}
}