{
  "type": "Feature",
  "properties": {
    "iso:country":"CH",
    "sg:address":"Ch\u00e4ppeliacher 2 B 6017 Ruswil. Postfach",
    "sg:city":"Ruswil",
    "sg:orig_category":"Gesundheitswesen",
    "sg:postcode":"6017",
    "sg:province":"Luzern",
    "wof:name":"Poli Massagen Und Sauna Gmbh",
    "wof:placetype":"venue"
},
  "geometry": {"coordinates":[8.1172523499,47.0867996216],"type":"Point"}
}