{
  "type": "Feature",
  "properties": {
    "iso:country":"CH",
    "sg:address":"Kasernenstrasse 18",
    "sg:city":"Liestal",
    "sg:orig_category":"RESTAURANTS: TEA-ROOMS",
    "sg:postcode":"4410",
    "sg:province":"Basel-Landschaft",
    "wof:name":"Sensebr\u00fcggli Gmbh",
    "wof:placetype":"venue"
},
  "geometry": {"coordinates":[7.2383298874,46.8992385864],"type":"Point"}
}