{
  "type": "Feature",
  "properties": {
    "iso:country":"CH",
    "sg:address":"Seestrasse 110 8266 Steckborn. Postfach",
    "sg:city":"Steckborn",
    "sg:orig_category":"Effektenvermittlung Broker",
    "sg:phone":"+41 52 761 29 24",
    "sg:postcode":"8266",
    "sg:province":"Thurgau",
    "wof:name":"Carmine Cupello Cupitex-kreditvermittlung",
    "wof:placetype":"venue"
},
  "geometry": {"coordinates":[8.981880188,47.6678276062],"type":"Point"}
}