{
  "type": "Feature",
  "properties": {
    "iso:country":"CH",
    "sg:address":"Wissenbachstrasse 1",
    "sg:city":"Biberstein",
    "sg:orig_category":"Detailhandel mit Boden U Wandbel\u00e4gen ohne Teppiche Detailhandel mit Teppichen",
    "sg:phone":"+41 62 827 45 66",
    "sg:postcode":"5023",
    "sg:province":"Aargau",
    "wof:name":"Ren\u00e9 Schwarz Teppiche Vorh\u00e4nge",
    "wof:placetype":"venue"
},
  "geometry": {"coordinates":[8.070125,47.411339],"type":"Point"}
}