{
  "type": "Feature",
  "properties": {
    "iso:country":"CH",
    "sg:address":"Bahnhofstrasse 38",
    "sg:city":"Z\u00fcrich",
    "sg:orig_category":"Fachdetailhandel in Verkaufsr\u00e4umen",
    "sg:phone":"+41 12120473",
    "sg:postcode":"8001",
    "sg:province":"Z\u00fcrich",
    "wof:name":"Blumen-kr\u00e4mer Engros Ag Blumen U. Pflanzen En Gros; Import U. Handel.",
    "wof:placetype":"venue"
},
  "geometry": {"coordinates":[8.5388870239,47.3713798523],"type":"Point"}
}