{
  "type": "Feature",
  "properties": {
    "iso:country":"CH",
    "sg:address":"Langenmattstrasse 54",
    "sg:city":"M\u00f6nchaltorf",
    "sg:orig_category":"Sportvereine Turnen Vereine Damen",
    "sg:phone":"+41 19481720",
    "sg:postcode":"8617",
    "sg:province":"Z\u00fcrich",
    "wof:name":"Damenriege D\u00fcbendorf",
    "wof:placetype":"venue"
},
  "geometry": {"coordinates":[8.718501091,47.3144989014],"type":"Point"}
}