{
  "type": "Feature",
  "properties": {
    "iso:country":"CH",
    "sg:address":"Via Mulini",
    "sg:city":"Bioggio",
    "sg:orig_category":"Sanit\u00e4rinstallation Sanit\u00e4rinstallation U Spenglerei",
    "sg:phone":"+41 22 307 78 14",
    "sg:postcode":"6934",
    "sg:province":"Ticino",
    "wof:name":"Technisan S\u00e0rl Sanitaires & Ferblanterie",
    "wof:placetype":"venue"
},
  "geometry": {"coordinates":[6.1339178085,46.1858177185],"type":"Point"}
}