{
  "type": "Feature",
  "properties": {
    "iso:country":"CH",
    "sg:address":"Seetalstrasse 138",
    "sg:city":"Schafisheim",
    "sg:orig_category":"Detailhandel mit Damenbekleidung Detailhandel mit Herrenbekleidung",
    "sg:phone":"+41 62 891 45 67",
    "sg:postcode":"5503",
    "sg:province":"Aargau",
    "wof:name":"Erika Johler Kleider-mode Johler",
    "wof:placetype":"venue"
},
  "geometry": {"coordinates":[8.1430215836,47.3745613098],"type":"Point"}
}