{
  "type": "Feature",
  "properties": {
    "iso:country":"CH",
    "sg:address":"M\u00fcllheimerstrasse 89 4057 Basel. Postfach",
    "sg:city":"Basel",
    "sg:orig_category":"Erschliessung von Grundst\u00fccken",
    "sg:postcode":"4051",
    "sg:province":"Basel-Stadt",
    "wof:name":"Wohngenossenschaft Diogenes",
    "wof:placetype":"venue"
},
  "geometry": {"coordinates":[7.5921292305,47.5679397583],"type":"Point"}
}