{
  "type": "Feature",
  "properties": {
    "iso:country":"CH",
    "sg:address":"In Den Schorenmatten 20",
    "sg:city":"Basel",
    "sg:orig_category":"Bau U Wohngenossenschaften",
    "sg:phone":"+41 61 683 42 25",
    "sg:postcode":"4058",
    "sg:province":"Basel-Stadt",
    "wof:name":"Wohngen.r\u00fcttibrunnen",
    "wof:placetype":"venue"
},
  "geometry": {"coordinates":[7.609451,47.571148],"type":"Point"}
}