{
  "type": "Feature",
  "properties": {
    "iso:country":"CH",
    "sg:address":"Z\u00fcrcherstrasse 244",
    "sg:city":"Dietikon",
    "sg:orig_category":"Architektur U Ingenieurb\u00fcros",
    "sg:phone":"+41 56 441 79 87",
    "sg:postcode":"8953",
    "sg:province":"Z\u00fcrich",
    "wof:name":"Ingenieurb\u00fcro Wittwer",
    "wof:placetype":"venue"
},
  "geometry": {"coordinates":[8.208194,47.484322],"type":"Point"}
}