{
  "type": "Feature",
  "properties": {
    "addr:full":"Rue De Fribourg 9 Gen\u00e8ve Gen\u00e8ve 1201",
    "addr:housenumber":"9",
    "addr:postcode":"1201",
    "addr:street":"Rue De Fribourg",
    "iso:country":"CH",
    "sg:address":"Rue De Fribourg 9",
    "sg:city":"Gen\u00e8ve",
    "sg:orig_category":"Aktivit\u00e4t der Bankinstitute",
    "sg:phone":"+41 22 735 31 84",
    "sg:postcode":"1201",
    "sg:province":"Gen\u00e8ve",
    "wof:name":"Banco De Sabadell",
    "wof:placetype":"venue"
},
  "geometry": {"coordinates":[6.155975,46.203747],"type":"Point"}
}