{
  "type": "Feature",
  "properties": {
    "iso:country":"CH",
    "sg:address":"Wallisberg 85",
    "sg:city":"Tscheppach",
    "sg:classifiers":[
        {
            "category":"Insurance",
            "subcategory":"Insurance Agent",
            "type":"Services"
        }
    ],
    "sg:phone":"+41 32 661 15 62",
    "sg:postcode":"4576",
    "sg:province":"Solothurn",
    "sg:tags":[
        "versicherungsagenturen",
        "-broker"
    ],
    "wof:name":"Z\u00fcrich-versicherungen Agentur Christian Baumberger",
    "wof:placetype":"venue"
},
  "geometry": {"coordinates":[7.4772381783,47.143245697],"type":"Point"}
}