{
  "type": "Feature",
  "properties": {
    "iso:country":"CH",
    "sg:address":"M\u00f6sli",
    "sg:city":"Winistorf",
    "sg:classifiers":[
        {
            "category":"Restaurant",
            "type":"Food & Drink"
        }
    ],
    "sg:phone":"+41 34 402 65 55",
    "sg:postcode":"4558",
    "sg:province":"Solothurn",
    "wof:name":"Restaurant Zum Goldenen L\u00f6wen",
    "wof:placetype":"venue"
},
  "geometry": {"coordinates":[7.757589817,46.9491271973],"type":"Point"}
}