{
  "type": "Feature",
  "properties": {
    "iso:country":"CH",
    "sg:address":"Schwanenplatz 7",
    "sg:city":"Luzern",
    "sg:orig_category":"Herstellung von sonstigen Nahrungsmitteln",
    "sg:phone":"+41 41 410 05 19",
    "sg:postcode":"6004",
    "sg:province":"Luzern",
    "wof:name":"Farfalla Duftladen Gisler Richard & Furrer",
    "wof:placetype":"venue"
},
  "geometry": {"coordinates":[8.3087491989,47.0537376404],"type":"Point"}
}