{
  "type": "Feature",
  "properties": {
    "iso:country":"CH",
    "sg:address":"Via Cantonale",
    "sg:city":"Cugnasco",
    "sg:classifiers":[
        {
            "category":"Sports & Exercise",
            "subcategory":"Sports Center",
            "type":"Entertainment"
        }
    ],
    "sg:phone":"+41 91 859 22 26",
    "sg:postcode":"6516",
    "sg:province":"Ticino",
    "sg:tags":[
        "grinding"
    ],
    "wof:name":"Affilama S.a.g.l.",
    "wof:placetype":"venue"
},
  "geometry": {"coordinates":[8.9189109802,46.1752662659],"type":"Point"}
}