{
  "type": "Feature",
  "properties": {
    "iso:country":"CH",
    "sg:address":"B\u00fchlweg 3a 3072 Ostermundigen. Postfach",
    "sg:city":"Ostermundigen",
    "sg:orig_category":"Gewinnung von Kies U Sand",
    "sg:phone":"+41 31 931 10 56",
    "sg:postcode":"3072",
    "sg:province":"Bern",
    "wof:name":"B. & P. K\u00fcnti Ag Ostermundigen",
    "wof:placetype":"venue"
},
  "geometry": {"coordinates":[7.4913239479,46.9544067383],"type":"Point"}
}