{
  "type": "Feature",
  "properties": {
    "iso:country":"CH",
    "sg:address":"Reckholderstrasse 17",
    "sg:city":"Uesslingen",
    "sg:orig_category":"Innendekorationsateliers",
    "sg:phone":"+41 22 300 11 38",
    "sg:postcode":"8524",
    "sg:province":"Thurgau",
    "wof:name":"Mpm Decors M.belahbib",
    "wof:placetype":"venue"
},
  "geometry": {"coordinates":[6.1443538666,46.1844673157],"type":"Point"}
}