{
  "type": "Feature",
  "properties": {
    "iso:country":"CH",
    "sg:address":"Avenue G\u00e9n\u00e9ral-guisan 41",
    "sg:city":"Vevey",
    "sg:orig_category":"RESTAURANTS: TEA-ROOMS",
    "sg:phone":"+41 21 922 82 04",
    "sg:postcode":"1800",
    "sg:province":"Vaud",
    "wof:name":"Mayr Siegmund",
    "wof:placetype":"venue"
},
  "geometry": {"coordinates":[6.8387708664,46.4646949768],"type":"Point"}
}