{
  "type": "Feature",
  "properties": {
    "iso:country":"CH",
    "sg:address":"1513",
    "sg:city":"Rossenges",
    "sg:orig_category":"Detailhandel mit Blumen U Pflanzen",
    "sg:phone":"+41 21 905 63 46",
    "sg:postcode":"1513",
    "sg:province":"Vaud",
    "wof:name":"Cannagrow S\u00e0rl",
    "wof:placetype":"venue"
},
  "geometry": {"coordinates":[6.776206,46.652439],"type":"Point"}
}