{
  "type": "Feature",
  "properties": {
    "iso:country":"CH",
    "sg:address":"Im R\u00fchrets 7",
    "sg:city":"R\u00fcschlikon",
    "sg:orig_category":"Innendekorationsateliers",
    "sg:phone":"+41 17242465",
    "sg:postcode":"8803",
    "sg:province":"Z\u00fcrich",
    "wof:name":"Alfred Hotz Innendekoration",
    "wof:placetype":"venue"
},
  "geometry": {"coordinates":[8.5489301682,47.2970809937],"type":"Point"}
}