{
  "type": "Feature",
  "properties": {
    "iso:country":"CH",
    "sg:address":"Malbun",
    "sg:city":"Triesenberg",
    "sg:classifiers":[
        {
            "category":"Restaurant",
            "type":"Food & Drink"
        }
    ],
    "sg:phone":"+41 41 675 21 41",
    "sg:postcode":"9497",
    "wof:name":"Bergrestaurant Schwendi-kaltbad Ag",
    "wof:placetype":"venue"
},
  "geometry": {"coordinates":[8.2112092972,46.8866157532],"type":"Point"}
}