{
  "type": "Feature",
  "properties": {
    "iso:country":"CH",
    "sg:address":"Rue De La Croix 22",
    "sg:city":"Courroux",
    "sg:orig_category":"Instandhaltung U Reparatur von Automobilen",
    "sg:phone":"+41 32 423 24 40",
    "sg:postcode":"2822",
    "sg:province":"Jura",
    "wof:name":"Sauvain Norbert",
    "wof:placetype":"venue"
},
  "geometry": {"coordinates":[7.3838129044,47.3572883606],"type":"Point"}
}