{
  "type": "Feature",
  "properties": {
    "iso:country":"CH",
    "sg:address":"Pestalozzistrasse 69a",
    "sg:city":"Thun",
    "sg:orig_category":"Betrieb von Sportanlagen",
    "sg:postcode":"3600",
    "sg:province":"Bern",
    "wof:name":"Genossenschaft Mur Mehrzweckhalle Unihockey/rollhockey Thun",
    "wof:placetype":"venue"
},
  "geometry": {"coordinates":[7.614125,46.750973],"type":"Point"}
}