{
  "type": "Feature",
  "properties": {
    "addr:full":"Grand'rue 24 Moudon Vaud 1510",
    "addr:housenumber":"24",
    "addr:postcode":"1510",
    "addr:street":"Grand'Rue",
    "iso:country":"CH",
    "sg:address":"Grand'rue 24",
    "sg:city":"Moudon",
    "sg:classifiers":[
        {
            "category":"Bars & Pubs",
            "type":"Food & Drink"
        }
    ],
    "sg:phone":"+41 21 905 28 54",
    "sg:postcode":"1510",
    "sg:province":"Vaud",
    "wof:name":"La Palmeraie S\u00e0rl",
    "wof:placetype":"venue"
},
  "geometry": {"coordinates":[6.796222,46.669727],"type":"Point"}
}