{
  "type": "Feature",
  "properties": {
    "iso:country":"CH",
    "sg:address":"Pflanzschulstrasse 7 8004 Z\u00fcrich. Postfach",
    "sg:city":"Z\u00fcrich",
    "sg:orig_category":"Interessenvertretungen",
    "sg:postcode":"8001",
    "sg:province":"Z\u00fcrich",
    "wof:name":"Stiftung Baumgartner-ehrsam Unterst\u00fctzung V. Institutionen M. Gemeinn. Zwecksetzung",
    "wof:placetype":"venue"
},
  "geometry": {"coordinates":[8.5192308426,47.3751869202],"type":"Point"}
}