{
  "type": "Feature",
  "properties": {
    "iso:country":"CH",
    "sg:address":"Friedaustrasse 17 4600 Olten. Postfach",
    "sg:city":"Olten",
    "sg:orig_category":"Architektur U Ingenieurb\u00fcros",
    "sg:postcode":"4600",
    "sg:province":"Solothurn",
    "wof:name":"H & O Hagmann, Oegerli, Brunner Architekturb\u00fcro, M\u00f6beldesign, Kaffeebar",
    "wof:placetype":"venue"
},
  "geometry": {"coordinates":[7.8964810371,47.3517494202],"type":"Point"}
}