{
  "type": "Feature",
  "properties": {
    "iso:country":"CH",
    "sg:address":"Via Mazzini 14",
    "sg:city":"Lugano",
    "sg:orig_category":"Grosshandel mit sonstigen Maschinen U Ausr\u00fcstungen f\u00fcr Industrie, Handel U Schiffahrt Herstellung vo",
    "sg:phone":"+41 91 923 13 15",
    "sg:postcode":"6900",
    "sg:province":"Ticino",
    "wof:name":"Cometal Trade Services Sa, Lussemburgo, Succursale Di Lugano",
    "wof:placetype":"venue"
},
  "geometry": {"coordinates":[8.9446792603,45.994594574],"type":"Point"}
}