{
  "type": "Feature",
  "properties": {
    "iso:country":"CH",
    "sg:address":"Hubel",
    "sg:city":"Habkern",
    "sg:orig_category":"S\u00e4ge, Hobel U Holzimpr\u00e4gnierwerke",
    "sg:phone":"+41 79 335 91 43",
    "sg:postcode":"3804",
    "sg:province":"Bern",
    "wof:name":"Hans Tschiemer",
    "wof:placetype":"venue"
},
  "geometry": {"coordinates":[7.8631010056,46.7265548706],"type":"Point"}
}