{
  "type": "Feature",
  "properties": {
    "iso:country":"CH",
    "sg:address":"Manessestrasse 96",
    "sg:city":"Z\u00fcrich",
    "sg:orig_category":"Softwareentwicklung U beratung",
    "sg:phone":"+41 14512191",
    "sg:postcode":"8045",
    "sg:province":"Z\u00fcrich",
    "wof:name":"Cd Game Express A.feldmann Vertrieb Von Pc-spielen",
    "wof:placetype":"venue"
},
  "geometry": {"coordinates":[8.5216579437,47.3644599915],"type":"Point"}
}