{
  "type": "Feature",
  "properties": {
    "iso:country":"CH",
    "sg:address":"Badenerstrasse 43",
    "sg:city":"Fislisbach",
    "sg:orig_category":"Beleuchtungsk\u00f6rper Detailhandel Elektroinstallation",
    "sg:phone":"+41 56 493 70 01",
    "sg:postcode":"5442",
    "sg:province":"Aargau",
    "wof:name":"Elektro Fl\u00fcckiger & Frei Ag",
    "wof:placetype":"venue"
},
  "geometry": {"coordinates":[8.292413,47.441715],"type":"Point"}
}