{
  "type": "Feature",
  "properties": {
    "iso:country":"CH",
    "sg:address":"Guggerhofstrasse 7",
    "sg:city":"Buochs",
    "sg:orig_category":"Herstellung von Elektrizit\u00e4tsverteilungs U schalteinrichtungen",
    "sg:postcode":"6374",
    "sg:province":"Nidwalden",
    "wof:name":"Ekd, Wilhelm B.",
    "wof:placetype":"venue"
},
  "geometry": {"coordinates":[8.4168100357,46.9721107483],"type":"Point"}
}