{
  "type": "Feature",
  "properties": {
    "iso:country":"CH",
    "sg:address":"Gesellschaftsstrasse 41 3000 Bern. Postfach",
    "sg:city":"Bern",
    "sg:orig_category":"Forschung U Entwicklung im Bereich der Naturwissenschaften",
    "sg:postcode":"3005",
    "sg:province":"Bern",
    "wof:name":"Jing-cast Technology Gmbh",
    "wof:placetype":"venue"
},
  "geometry": {"coordinates":[7.4340372086,46.9538574219],"type":"Point"}
}