{
  "type": "Feature",
  "properties": {
    "iso:country":"CH",
    "sg:address":"3970",
    "sg:city":"Salgesch",
    "sg:orig_category":"Mechanische Werkst\u00e4tten",
    "sg:phone":"+41 71 744 29 19",
    "sg:postcode":"3970",
    "sg:province":"Valais",
    "wof:name":"Emil Zellweger Mechanische Werkst\u00e4tte",
    "wof:placetype":"venue"
},
  "geometry": {"coordinates":[9.6328849792,47.4283485413],"type":"Point"}
}