{
  "type": "Feature",
  "properties": {
    "iso:country":"CH",
    "sg:address":"Boulevard James-fazy 8",
    "sg:city":"Gen\u00e8ve",
    "sg:orig_category":"Detektivb\u00fcros U \u00dcberwachung Unternehmensberatung",
    "sg:phone":"+41 22 715 35 11",
    "sg:postcode":"1201",
    "sg:province":"Gen\u00e8ve",
    "wof:name":"Berkeley, Intellectual Property Services",
    "wof:placetype":"venue"
},
  "geometry": {"coordinates":[6.1399669647,46.2072563171],"type":"Point"}
}