{
  "type": "Feature",
  "properties": {
    "iso:country":"CH",
    "sg:address":"Weihergasse 7",
    "sg:city":"Bern",
    "sg:orig_category":"Public-Relations-Agenturen",
    "sg:phone":"+41 31 998 44 35",
    "sg:postcode":"3005",
    "sg:province":"Bern",
    "wof:name":"Morf Communication Ag Dienstleistungen In Den Bereichen \u00d6ffentlichkeitsarbeit, Werbung U. Grafik",
    "wof:placetype":"venue"
},
  "geometry": {"coordinates":[7.4447398186,46.945400238],"type":"Point"}
}