{
  "type": "Feature",
  "properties": {
    "iso:country":"CH",
    "sg:address":"Thurgauerstrasse 13",
    "sg:city":"Rorschach",
    "sg:orig_category":"Non-Classified Establishments",
    "sg:postcode":"9400",
    "sg:province":"St. Gallen",
    "wof:name":"Restaurant Asian Charm, Teik Choon Lim",
    "wof:placetype":"venue"
},
  "geometry": {"coordinates":[9.4877004623,47.479221344],"type":"Point"}
}