{
  "type": "Feature",
  "properties": {
    "iso:country":"CH",
    "sg:address":"Z\u00fcrcherstrasse 94 8730 Uznach. Postfach",
    "sg:city":"Uznach",
    "sg:orig_category":"Spinnstoffaufbereitung U Spinnerei",
    "sg:phone":"+41 55 285 86 60",
    "sg:postcode":"8730",
    "sg:province":"St. Gallen",
    "wof:name":"Spinnerei Am Uznaberg",
    "wof:placetype":"venue"
},
  "geometry": {"coordinates":[8.9651021957,47.2299194336],"type":"Point"}
}