{
  "type": "Feature",
  "properties": {
    "iso:country":"CH",
    "sg:address":"Moli\u00e8re Rue De La 26",
    "sg:city":"Del\u00e9mont",
    "sg:orig_category":"Verwaltung von Immobilien",
    "sg:postcode":"2800",
    "sg:province":"Jura",
    "wof:name":"Si Grenier 20 Sa",
    "wof:placetype":"venue"
},
  "geometry": {"coordinates":[6.8230748177,47.0989723206],"type":"Point"}
}