{
  "type": "Feature",
  "properties": {
    "iso:country":"CH",
    "sg:address":"Birkenweg 28 3123 Belp. Postfach",
    "sg:city":"Belp",
    "sg:orig_category":"Grosshandel mit sonstigen Maschinen U Ausr\u00fcstungen f\u00fcr Industrie, Handel U Schiffahrt",
    "sg:phone":"+41 31 819 83 83",
    "sg:postcode":"3123",
    "sg:province":"Bern",
    "wof:name":"Difosa Consulting Gmbh",
    "wof:placetype":"venue"
},
  "geometry": {"coordinates":[7.4975099564,46.8865966797],"type":"Point"}
}