{
  "type": "Feature",
  "properties": {
    "iso:country":"CH",
    "sg:address":"Jurastrasse 46",
    "sg:city":"Langenthal",
    "sg:orig_category":"Sonstige Institutionen des Sozialwesens ohne Beherbergung",
    "sg:phone":"+41 62 922 35 35",
    "sg:postcode":"4900",
    "sg:province":"Bern",
    "wof:name":"Erziehungsberatung Des Kts Be Langenthal & Oberaargau",
    "wof:placetype":"venue"
},
  "geometry": {"coordinates":[7.7855000496,47.2169647217],"type":"Point"}
}