{
  "type": "Feature",
  "properties": {
    "iso:country":"CH",
    "sg:address":"Via Muraccio 1",
    "sg:city":"Ascona",
    "sg:orig_category":"Detailhandel mit Zeitungen U Zeitschriften Kioske",
    "sg:phone":"+41 62 212 03 51",
    "sg:postcode":"6612",
    "sg:province":"Ticino",
    "wof:name":"Rosa Wyrsch Kiosk",
    "wof:placetype":"venue"
},
  "geometry": {"coordinates":[7.8652148247,47.3422889709],"type":"Point"}
}