{
  "type": "Feature",
  "properties": {
    "iso:country":"CH",
    "sg:address":"Freudenbergstrasse 34 9507 Stettfurt. Postfach",
    "sg:city":"Stettfurt",
    "sg:orig_category":"Fachdetailhandel in Verkaufsr\u00e4umen",
    "sg:phone":"+41 52 366 60 33",
    "sg:postcode":"9507",
    "sg:province":"Thurgau",
    "wof:name":"Hph Ag",
    "wof:placetype":"venue"
},
  "geometry": {"coordinates":[8.9490480423,47.5300064087],"type":"Point"}
}