{
  "type": "Feature",
  "properties": {
    "iso:country":"CH",
    "sg:address":"Rue Des P\u00eacheurs 8",
    "sg:city":"Yverdon-les-bains",
    "sg:orig_category":"Gymnastik U Fitnesszentren Saunas, Solarien, Fitnesszentren U \u00e4hnliches",
    "sg:phone":"+41 24 425 20 29",
    "sg:postcode":"1400",
    "sg:province":"Vaud",
    "wof:name":"Leader Athletic Fitness Line Sa",
    "wof:placetype":"venue"
},
  "geometry": {"coordinates":[6.6447529793,46.7814865112],"type":"Point"}
}