{
  "type": "Feature",
  "properties": {
    "iso:country":"CH",
    "sg:address":"9658",
    "sg:city":"Wildhaus",
    "sg:orig_category":"Vorschulen, Kinderg\u00e4rten",
    "sg:phone":"+41 71 999 31 44",
    "sg:postcode":"9658",
    "sg:province":"St. Gallen",
    "wof:name":"Kindergarten",
    "wof:placetype":"venue"
},
  "geometry": {"coordinates":[9.3509206772,47.2028656006],"type":"Point"}
}