{
  "type": "Feature",
  "properties": {
    "iso:country":"CH",
    "sg:address":"Mittelwiesstrasse 39",
    "sg:city":"M\u00e4nnedorf",
    "sg:orig_category":"Zahnarztpraxen",
    "sg:phone":"+41 19202021",
    "sg:postcode":"8708",
    "sg:province":"Z\u00fcrich",
    "wof:name":"Dr. Med. Dent. Ueli Frey Zahnarzt",
    "wof:placetype":"venue"
},
  "geometry": {"coordinates":[8.6952838898,47.2528076172],"type":"Point"}
}