{
  "type": "Feature",
  "properties": {
    "iso:country":"CH",
    "sg:address":"Rue De L'arquebuse 10",
    "sg:city":"Gen\u00e8ve",
    "sg:orig_category":"Verlagsgewerbe",
    "sg:phone":"+41 71 744 72 70",
    "sg:postcode":"1204",
    "sg:province":"Gen\u00e8ve",
    "wof:name":"Rheintaler Bote Zeitungs-verlag",
    "wof:placetype":"venue"
},
  "geometry": {"coordinates":[9.6315259933,47.4533538818],"type":"Point"}
}