{
  "type": "Feature",
  "properties": {
    "iso:country":"CH",
    "sg:address":"Couleuvres Chemin Des 4 A",
    "sg:city":"Mies-tannay",
    "sg:orig_category":"Non-Classified Establishments",
    "sg:postcode":"1295",
    "sg:province":"Vaud",
    "wof:name":"Centre M\u00e9dico-chirurgical Pr\u00e9-vert Tannay S\u00e0rl",
    "wof:placetype":"venue"
},
  "geometry": {"coordinates":[6.1724500656,46.3060684204],"type":"Point"}
}