{
  "type": "Feature",
  "properties": {
    "iso:country":"CH",
    "sg:address":"3623",
    "sg:city":"Horrenbach-buchen",
    "sg:orig_category":"Sportvereine Sch\u00fctzen",
    "sg:phone":"+41 31 738 87 36",
    "sg:postcode":"3623",
    "sg:province":"Bern",
    "wof:name":"Feldsch\u00fctzengesellschaft R\u00fcschegg Graben",
    "wof:placetype":"venue"
},
  "geometry": {"coordinates":[7.4069471359,46.7818603516],"type":"Point"}
}