{
  "type": "Feature",
  "properties": {
    "iso:country":"CH",
    "sg:address":"Route De La Chapelle 29b",
    "sg:city":"Grand-lancy",
    "sg:orig_category":"Gem\u00fcsebau",
    "sg:phone":"+41 21 801 13 53",
    "sg:postcode":"1212",
    "sg:province":"Gen\u00e8ve",
    "wof:name":"Jean Kohler Maraicher",
    "wof:placetype":"venue"
},
  "geometry": {"coordinates":[6.4657878876,46.5014610291],"type":"Point"}
}