{
  "type": "Feature",
  "properties": {
    "iso:country":"CH",
    "sg:address":"Aegeristrasse 61",
    "sg:city":"Baar",
    "sg:orig_category":"Autogaragen",
    "sg:phone":"+41 41 761 49 84",
    "sg:postcode":"6340",
    "sg:province":"Zug",
    "wof:name":"Martin H\u00e4usler Autoreparatur-service",
    "wof:placetype":"venue"
},
  "geometry": {"coordinates":[8.539238,47.191311],"type":"Point"}
}