{
  "type": "Feature",
  "properties": {
    "iso:country":"CH",
    "sg:address":"S\u00e4nnelocherstrasse 2",
    "sg:city":"D\u00f6ttingen",
    "sg:orig_category":"Fahrschulen, Flugschulen",
    "sg:phone":"+41 79 243 95 26",
    "sg:postcode":"5312",
    "sg:province":"Aargau",
    "wof:name":"Alex Knecht Autofahrschule",
    "wof:placetype":"venue"
},
  "geometry": {"coordinates":[8.2696809769,47.566493988],"type":"Point"}
}