{
  "type": "Feature",
  "properties": {
    "iso:country":"CH",
    "sg:address":"Gr\u00fcdstrasse 65",
    "sg:city":"Toffen",
    "sg:orig_category":"Architektur U Ingenieurb\u00fcros",
    "sg:phone":"+41 31 819 15 51",
    "sg:postcode":"3125",
    "sg:province":"Bern",
    "wof:name":"Rolf Beck Ingenieurb\u00fcro",
    "wof:placetype":"venue"
},
  "geometry": {"coordinates":[7.49541,46.854652],"type":"Point"}
}