{
  "type": "Feature",
  "properties": {
    "iso:country":"CH",
    "sg:address":"B\u00fcrenstrasse 91",
    "sg:city":"Solothurn",
    "sg:classifiers":[
        {
            "category":"Government",
            "subcategory":"Jail",
            "type":"Public Place"
        }
    ],
    "sg:phone":"+41 32 622 16 29",
    "sg:postcode":"4500",
    "sg:province":"Solothurn",
    "sg:tags":[
        "planning",
        "designing"
    ],
    "wof:name":"Ps Architektur- Und Innenarchitektur",
    "wof:placetype":"venue"
},
  "geometry": {"coordinates":[7.531597,47.19994],"type":"Point"}
}