{
  "type": "Feature",
  "properties": {
    "iso:country":"CH",
    "sg:address":"Route Des Esserts 4 B",
    "sg:city":"Duillier",
    "sg:orig_category":"Non-Classified Establishments",
    "sg:postcode":"1266",
    "sg:province":"Vaud",
    "wof:name":"Rare - Respect And Responsibility, Pascale D. Morand Francis",
    "wof:placetype":"venue"
},
  "geometry": {"coordinates":[6.2353620529,46.4109153748],"type":"Point"}
}