{
  "type": "Feature",
  "properties": {
    "addr:full":"Chlotisberg Gelfingen Luzern 6284",
    "addr:postcode":"6284",
    "iso:country":"CH",
    "sg:address":"Chlotisberg",
    "sg:city":"Gelfingen",
    "sg:orig_category":"Betrieb von Sportanlagen",
    "sg:postcode":"6284",
    "sg:province":"Luzern",
    "wof:name":"Genossenschaft Chlotisberg - Ausbildungszentrum Des Svkt Frauensportverbandes",
    "wof:placetype":"venue"
},
  "geometry": {"coordinates":[8.286877,47.216541],"type":"Point"}
}