{
  "type": "Feature",
  "properties": {
    "iso:country":"CH",
    "sg:address":"Landstrasse 146",
    "sg:city":"Klosters",
    "sg:classifiers":[
        {
            "category":"Travel",
            "subcategory":"Hotels & Motels",
            "type":"Entertainment"
        }
    ],
    "sg:phone":"+41 81 422 45 45",
    "sg:postcode":"7250",
    "sg:province":"Graubunden",
    "sg:tags":[
        "hotels",
        "mit",
        "restaurant"
    ],
    "wof:name":"Hotel Steinbock",
    "wof:placetype":"venue"
},
  "geometry": {"coordinates":[9.8808088303,46.8717689514],"type":"Point"}
}