{
  "type": "Feature",
  "properties": {
    "iso:country":"CH",
    "sg:address":"Bois-du-lan Rue Du 22 1217 Meyrin Case Postale",
    "sg:city":"Meyrin",
    "sg:orig_category":"Herstellung von Medikamenten U sonstigen pharmazeutischen Erzeugnissen",
    "sg:postcode":"1217",
    "sg:province":"Gen\u00e8ve",
    "wof:name":"Ombran Ag.",
    "wof:placetype":"venue"
},
  "geometry": {"coordinates":[8.4415683746,47.0812110901],"type":"Point"}
}