{
  "type": "Feature",
  "properties": {
    "iso:country":"CH",
    "sg:address":"Kannenfeldstrasse 22 4056 Basel. Postfach",
    "sg:city":"Basel",
    "sg:orig_category":"Softwareentwicklung U beratung",
    "sg:postcode":"4051",
    "sg:province":"Basel-Stadt",
    "wof:name":"Jahia Ag",
    "wof:placetype":"venue"
},
  "geometry": {"coordinates":[9.3665018082,47.4142036438],"type":"Point"}
}