{
  "type": "Feature",
  "properties": {
    "iso:country":"CH",
    "sg:address":"Baarerstrasse 59",
    "sg:city":"Zug",
    "sg:orig_category":"Detailhandel mit M\u00f6beln U Haushaltsgegenst\u00e4nden",
    "sg:phone":"+41 41 710 35 30",
    "sg:postcode":"6300",
    "sg:province":"Zug",
    "wof:name":"Fuerza Ag",
    "wof:placetype":"venue"
},
  "geometry": {"coordinates":[8.5171394348,47.1753692627],"type":"Point"}
}