{
  "type": "Feature",
  "properties": {
    "addr:full":"Schlossmatte 6017 Ruswil. Postfach 313 Ruswil Luzern 6017",
    "addr:housenumber":"313",
    "addr:postcode":"6017 ruswil.;6017",
    "addr:street":"Schlossmatte;Postfach",
    "iso:country":"CH",
    "sg:address":"Schlossmatte 6017 Ruswil. Postfach 313",
    "sg:city":"Ruswil",
    "sg:orig_category":"Aktivit\u00e4ten der Krankenschwestern U Hebammen, Hauspflege Organisationen des Gesundheitswesen",
    "sg:phone":"+41 41 495 22 20",
    "sg:postcode":"6017",
    "sg:province":"Luzern",
    "wof:name":"Spitex Gemeindekrankenpflege",
    "wof:placetype":"venue"
},
  "geometry": {"coordinates":[8.128549,47.084221],"type":"Point"}
}