{
  "type": "Feature",
  "properties": {
    "iso:country":"CH",
    "sg:address":"Pfingstweidstrasse 70",
    "sg:city":"Z\u00fcrich",
    "sg:orig_category":"Einzelhandel mit Automobilteilen U Zubeh\u00f6r Herstellung von Teilen U Zubeh\u00f6r f\u00fcr Automobile",
    "sg:phone":"+41 12717751",
    "sg:postcode":"8005",
    "sg:province":"Z\u00fcrich",
    "wof:name":"Rikag Pneu-service Ag",
    "wof:placetype":"venue"
},
  "geometry": {"coordinates":[8.513835907,47.3896713257],"type":"Point"}
}