{
  "type": "Feature",
  "properties": {
    "addr:full":"Tannackerstr. 24 A 3074 Muri B. Bern. Postfach G\u00fcmligen Bern 3073",
    "addr:housenumber":"24 a",
    "addr:postcode":"3074;3073",
    "addr:street":"Tannackerstr.",
    "iso:country":"CH",
    "sg:address":"Tannackerstr. 24 A 3074 Muri B. Bern. Postfach",
    "sg:city":"G\u00fcmligen",
    "sg:orig_category":"Architektur U Ingenieurb\u00fcros",
    "sg:postcode":"3073",
    "sg:province":"Bern",
    "wof:name":"Architekturb\u00fcro Bracher Hans",
    "wof:placetype":"venue"
},
  "geometry": {"coordinates":[7.820361,47.046375],"type":"Point"}
}