{
  "type": "Feature",
  "properties": {
    "iso:country":"CH",
    "sg:address":"G\u00fcrbeweg 20",
    "sg:city":"Belp",
    "sg:orig_category":"Werbegrafikateliers",
    "sg:phone":"+41 62 212 62 02",
    "sg:postcode":"3123",
    "sg:province":"Bern",
    "wof:name":"Grafik & Design Hans Kohlmann",
    "wof:placetype":"venue"
},
  "geometry": {"coordinates":[7.8741688728,47.3405914307],"type":"Point"}
}