{
  "type": "Feature",
  "properties": {
    "iso:country":"CH",
    "sg:address":"Rue Des Ch\u00eanes 12",
    "sg:city":"Court\u00e9telle",
    "sg:orig_category":"Aktivit\u00e4ten der Generalunternehmen im Baugewerbe",
    "sg:phone":"+41 32 422 11 80",
    "sg:postcode":"2852",
    "sg:province":"Jura",
    "wof:name":"Icar Concept S\u00e0rl Entreprise De Construction",
    "wof:placetype":"venue"
},
  "geometry": {"coordinates":[7.316792,47.347157],"type":"Point"}
}