{
  "type": "Feature",
  "properties": {
    "iso:country":"CH",
    "sg:address":"Pf\u00e4fersweg 35",
    "sg:city":"Sevelen",
    "sg:orig_category":"Bau von Strassen, Sportanlagen U Bahnverkehrsstrecken",
    "sg:postcode":"9475",
    "sg:province":"St. Gallen",
    "wof:name":"H\u00fcppi Ag, Zweigniederlassung Sevelen",
    "wof:placetype":"venue"
},
  "geometry": {"coordinates":[9.482126,47.124546],"type":"Point"}
}