{
  "type": "Feature",
  "properties": {
    "iso:country":"CH",
    "sg:address":"Route Des Plaines-du-loup 26",
    "sg:city":"Lausanne",
    "sg:orig_category":"Tankstellen",
    "sg:phone":"+41 21 647 66 46",
    "sg:postcode":"1018",
    "sg:province":"Vaud",
    "wof:name":"Gatoil (suisse) Sa Station D'essence",
    "wof:placetype":"venue"
},
  "geometry": {"coordinates":[6.6255278587,46.5348892212],"type":"Point"}
}