{
  "type": "Feature",
  "properties": {
    "iso:country":"CH",
    "sg:address":"Challex Route De 5",
    "sg:city":"Dardagny",
    "sg:orig_category":"Herstellung von Schl\u00f6ssern U Beschl\u00e4gen",
    "sg:phone":"+41 22 754 20 22",
    "sg:postcode":"1282",
    "wof:name":"Areas M.a., Entreprise De Montage Et Construction",
    "wof:placetype":"venue"
},
  "geometry": {"coordinates":[5.9685101509,46.1791687012],"type":"Point"}
}