{
  "type": "Feature",
  "properties": {
    "iso:country":"CH",
    "sg:address":"Aarestrasse 38 B",
    "sg:city":"Thun",
    "sg:orig_category":"Unternehmensberatung",
    "sg:phone":"+41 33 221 50 59",
    "sg:postcode":"3600",
    "sg:province":"Bern",
    "wof:name":"Accent Ag",
    "wof:placetype":"venue"
},
  "geometry": {"coordinates":[7.6284542084,46.7567749023],"type":"Point"}
}