{
  "type": "Feature",
  "properties": {
    "addr:full":"Boulevard Des Philosophes 13 Gen\u00e8ve Gen\u00e8ve 1205",
    "addr:housenumber":"13",
    "addr:postcode":"1205",
    "addr:street":"Boulevard Des Philosophes",
    "iso:country":"CH",
    "sg:address":"Boulevard Des Philosophes 13",
    "sg:city":"Gen\u00e8ve",
    "sg:orig_category":"Arztpraxen",
    "sg:phone":"+41 22 320 15 31",
    "sg:postcode":"1205",
    "sg:province":"Gen\u00e8ve",
    "wof:name":"Dr M\u00e9d. Hugo Goldschlag M\u00e9decin Sp\u00e9cialiste Fmh",
    "wof:placetype":"venue"
},
  "geometry": {"coordinates":[6.144727,46.197273],"type":"Point"}
}