{
  "type": "Feature",
  "properties": {
    "iso:country":"CH",
    "sg:address":"Zinnengasse 5",
    "sg:city":"Z\u00fcrich",
    "sg:orig_category":"Detailhandel mit Uhren U Schmuck Herstellung von Schmuck, Gold U Silberschmiedwaren",
    "sg:phone":"+41 12117043",
    "sg:postcode":"8001",
    "sg:province":"Z\u00fcrich",
    "wof:name":"Trudel Juwelier",
    "wof:placetype":"venue"
},
  "geometry": {"coordinates":[8.5415725708,47.3704452515],"type":"Point"}
}