{
  "type": "Feature",
  "properties": {
    "iso:country":"CH",
    "sg:address":"Schinhuetstr. 658. 5036 Oberentfelden. Postfach",
    "sg:city":"Oberentfelden",
    "sg:orig_category":"Pensionskassen",
    "sg:postcode":"5036",
    "sg:province":"Aargau",
    "wof:name":"Personalf\u00fcrsorgestiftung Der Frey Transport Ag",
    "wof:placetype":"venue"
},
  "geometry": {"coordinates":[8.0536003113,47.3610496521],"type":"Point"}
}