{
  "type": "Feature",
  "properties": {
    "iso:country":"CH",
    "sg:address":"Z\u00fcrichbergstrasse 118",
    "sg:city":"Z\u00fcrich",
    "sg:orig_category":"Architektur U Ingenieurb\u00fcros",
    "sg:postcode":"8044",
    "sg:province":"Z\u00fcrich",
    "wof:name":"Atelier F\u00fcr Architektur Und Bau-consulting Romano F. Architektur, Bau, Immobilien-beratung, Entwurf, Planung, Gestaltung, Design",
    "wof:placetype":"venue"
},
  "geometry": {"coordinates":[8.885993,47.586899],"type":"Point"}
}