{
  "type": "Feature",
  "properties": {
    "iso:country":"CH",
    "sg:address":"B\u00f6zingenstr. 157 2500 Biel/bienne. Postfach",
    "sg:city":"Biel/bienne",
    "sg:orig_category":"Zimmerei, Dachdeckerei, Bauspenglerei U Abdichtung",
    "sg:postcode":"2504",
    "sg:province":"Bern",
    "wof:name":"Frank Theo Spenglerei, San. Installationen",
    "wof:placetype":"venue"
},
  "geometry": {"coordinates":[8.4864501953,47.2838897705],"type":"Point"}
}