{
  "type": "Feature",
  "properties": {
    "iso:country":"CH",
    "sg:address":"Bretzwilerstr. 257.",
    "sg:city":"Nunningen",
    "sg:orig_category":"Mechanik",
    "sg:postcode":"4208",
    "sg:province":"Solothurn",
    "wof:name":"Hauser & Jeker",
    "wof:placetype":"venue"
},
  "geometry": {"coordinates":[7.6265521049,47.3939704895],"type":"Point"}
}