{
  "type": "Feature",
  "properties": {
    "iso:country":"CH",
    "sg:address":"Via Campagna 10",
    "sg:city":"Savosa",
    "sg:orig_category":"Bauschreinerei M\u00f6belschreinerei",
    "sg:phone":"+41 91 967 67 53",
    "sg:postcode":"6942",
    "sg:province":"Ticino",
    "wof:name":"Severino Fiscalini Mobili & Serramenti",
    "wof:placetype":"venue"
},
  "geometry": {"coordinates":[8.942601,46.016182],"type":"Point"}
}