{
  "type": "Feature",
  "properties": {
    "iso:country":"CH",
    "sg:address":"General Guisanstrasse 23",
    "sg:city":"Interlaken",
    "sg:orig_category":"HOTELS: OHNE RESTAURANT",
    "sg:phone":"+41 33 822 36 26",
    "sg:postcode":"3800",
    "sg:province":"Bern",
    "wof:name":"Hotel Swiss-inn",
    "wof:placetype":"venue"
},
  "geometry": {"coordinates":[7.8549451828,46.6822128296],"type":"Point"}
}