{
  "type": "Feature",
  "properties": {
    "iso:country":"CH",
    "sg:address":"Rebbergstrasse 30",
    "sg:city":"Geroldswil",
    "sg:orig_category":"Grosshandel mit Datenverarbeitungsger\u00e4ten Softwareentwicklung U beratung",
    "sg:phone":"+41 17481683",
    "sg:postcode":"8954",
    "sg:province":"Z\u00fcrich",
    "wof:name":"Seim Informatik Gmbh",
    "wof:placetype":"venue"
},
  "geometry": {"coordinates":[8.407661438,47.4258346558],"type":"Point"}
}