{
  "type": "Feature",
  "properties": {
    "addr:full":"K\u00fcrzeweg 2 Zunzgen Basel-Landschaft 4455",
    "addr:housenumber":"2",
    "addr:postcode":"4455",
    "addr:street":"Kuerzeweg",
    "iso:country":"CH",
    "sg:address":"K\u00fcrzeweg 2",
    "sg:city":"Zunzgen",
    "sg:orig_category":"Architektur U Ingenieurb\u00fcros",
    "sg:phone":"+41 26 411 02 01",
    "sg:postcode":"4455",
    "sg:province":"Basel-Landschaft",
    "wof:name":"Buser Engineering",
    "wof:placetype":"venue"
},
  "geometry": {"coordinates":[7.082269,46.705143],"type":"Point"}
}