{
  "type": "Feature",
  "properties": {
    "iso:country":"CH",
    "sg:address":"Le Begu",
    "sg:city":"Font",
    "sg:orig_category":"Kosmetikinstitute",
    "sg:phone":"+41 26 663 33 23",
    "sg:postcode":"1473",
    "sg:province":"Fribourg",
    "wof:name":"Anne-marie Ramuz Institut De Beaut\u00e9 Marybelle",
    "wof:placetype":"venue"
},
  "geometry": {"coordinates":[6.8248848915,46.8349533081],"type":"Point"}
}