{
  "type": "Feature",
  "properties": {
    "iso:country":"CH",
    "sg:address":"Lilienberg",
    "sg:city":"Ermatingen",
    "sg:orig_category":"Unclassifiable Establishments",
    "sg:phone":"+41 19836000",
    "sg:postcode":"8272",
    "sg:province":"Thurgau",
    "wof:name":"Wrh Reist Walter Holding Ag",
    "wof:placetype":"venue"
},
  "geometry": {"coordinates":[9.073059082,47.6683807373],"type":"Point"}
}