{
  "type": "Feature",
  "properties": {
    "iso:country":"CH",
    "sg:address":"Oltnerstrasse 25 5012 Sch\u00f6nenwerd. Postfach",
    "sg:city":"Sch\u00f6nenwerd",
    "sg:orig_category":"Fachdetailhandel mit pharmazeutischen Produkten",
    "sg:phone":"+41 80300001",
    "sg:postcode":"5012",
    "sg:province":"Solothurn",
    "wof:name":"Apotheke Husmatt",
    "wof:placetype":"venue"
},
  "geometry": {"coordinates":[8.282951355,47.4549484253],"type":"Point"}
}