{
  "type": "Feature",
  "properties": {
    "iso:country":"CH",
    "sg:address":"Neugasse 12",
    "sg:city":"Interlaken",
    "sg:orig_category":"Detailhandel mit Waren verschiedener Art, Hauptrichtung Nahrungsmittel Grosshandel mit Obst U Gem\u00fcse",
    "sg:phone":"+41 33 822 27 76",
    "sg:postcode":"3800",
    "sg:province":"Bern",
    "wof:name":"Jametti Ag Interlaken Fr\u00fcchte & Gem\u00fcse",
    "wof:placetype":"venue"
},
  "geometry": {"coordinates":[7.8544898033,46.6866493225],"type":"Point"}
}