{
  "type": "Feature",
  "properties": {
    "iso:country":"CH",
    "sg:address":"Route De Verbois 1288 Aire-la-ville Case Postale 25",
    "sg:city":"Aire-la-ville",
    "sg:orig_category":"Abfallbeseitigung",
    "sg:phone":"+41 22 343 01 50",
    "sg:postcode":"1288",
    "sg:province":"Gen\u00e8ve",
    "wof:name":"Voirie De La Ville De Gen\u00e8ve Service Lev\u00e9e Des R\u00e9sidus",
    "wof:placetype":"venue"
},
  "geometry": {"coordinates":[6.141425,46.183311],"type":"Point"}
}