{
  "type": "Feature",
  "properties": {
    "iso:country":"CH",
    "sg:address":"Im Z\u00fcbli 26 8730 Uznach. Postfach",
    "sg:city":"Uznach",
    "sg:orig_category":"Allgemeiner Hoch U Tiefbau",
    "sg:phone":"+41 55 280 46 59",
    "sg:postcode":"8730",
    "sg:province":"St. Gallen",
    "wof:name":"Bachmann B. Bau Gmbh Baugesch\u00e4ft Usw.",
    "wof:placetype":"venue"
},
  "geometry": {"coordinates":[8.980741,47.228603],"type":"Point"}
}