{
  "type": "Feature",
  "properties": {
    "iso:country":"CH",
    "sg:address":"Industriestrasse 1",
    "sg:city":"M\u00fcnsingen",
    "sg:orig_category":"Herstellung von keramischen Wand U Bodenfliesen U platten Maurerarbeiten",
    "sg:phone":"+41 31 721 14 41",
    "sg:postcode":"3110",
    "sg:province":"Bern",
    "wof:name":"Esaltato Salvatore",
    "wof:placetype":"venue"
},
  "geometry": {"coordinates":[7.5591077805,46.8728218079],"type":"Point"}
}