{
  "type": "Feature",
  "properties": {
    "iso:country":"CH",
    "sg:address":"Zugerstr. 8a",
    "sg:city":"Baar",
    "sg:classifiers":[
        {
            "category":"Wholesale",
            "subcategory":"Machinery & Supplies",
            "type":"Manufacturing & Wholesale Goods"
        }
    ],
    "sg:phone":"+41 41 761 97 77",
    "sg:postcode":"6341",
    "sg:province":"Zug",
    "sg:tags":[
        "food",
        "processing",
        "-",
        "machine",
        "equipment",
        "engineering",
        "mechanical"
    ],
    "wof:name":"Tmci Ag",
    "wof:placetype":"venue"
},
  "geometry": {"coordinates":[8.5227413177,47.192527771],"type":"Point"}
}