{
  "type": "Feature",
  "properties": {
    "iso:country":"CH",
    "sg:address":"Schnyders\u00e4cker",
    "sg:city":"Ramsen",
    "sg:orig_category":"Grosshandel mit lebenden Tieren",
    "sg:phone":"+41 52 743 10 10",
    "sg:postcode":"8262",
    "sg:province":"Schaffhausen",
    "wof:name":"Schmid Karl",
    "wof:placetype":"venue"
},
  "geometry": {"coordinates":[8.8115100861,47.7071456909],"type":"Point"}
}