{
  "type": "Feature",
  "properties": {
    "iso:country":"CH",
    "sg:address":"Solothurnerstrasse 46 4000 Basel. Postfach",
    "sg:city":"Basel",
    "sg:orig_category":"Unternehmensberatung",
    "sg:phone":"+41 61 606 96 90",
    "sg:postcode":"4051",
    "sg:province":"Basel-Stadt",
    "wof:name":"Ruetz & Partner Gmbh",
    "wof:placetype":"venue"
},
  "geometry": {"coordinates":[7.6321678162,47.569984436],"type":"Point"}
}