{
  "type": "Feature",
  "properties": {
    "iso:country":"CH",
    "sg:address":"Unterdorf 9",
    "sg:city":"Oberb\u00fcren",
    "sg:orig_category":"Gemeindeverwaltungen",
    "sg:phone":"+41 71 955 90 30",
    "sg:postcode":"9245",
    "sg:province":"St. Gallen",
    "wof:name":"Gemeindeverwaltung Oberb\u00fcren",
    "wof:placetype":"venue"
},
  "geometry": {"coordinates":[9.1588068008,47.4518661499],"type":"Point"}
}