{
  "type": "Feature",
  "properties": {
    "iso:country":"CH",
    "sg:address":"Stadterwingert 10",
    "sg:city":"Sargans",
    "sg:orig_category":"Sanit\u00e4r U Heizungsinstallation Sanit\u00e4rinstallation",
    "sg:postcode":"7320",
    "sg:province":"St. Gallen",
    "wof:name":"Heizung-sanit\u00e4r Ag Mels",
    "wof:placetype":"venue"
},
  "geometry": {"coordinates":[9.4267139435,47.0538406372],"type":"Point"}
}