{
  "type": "Feature",
  "properties": {
    "iso:country":"CH",
    "sg:address":"Simplon Rue Du 13",
    "sg:city":"Fribourg",
    "sg:orig_category":"Druck ohne Zeitungsdruck",
    "sg:phone":"+41 22 342 64 63",
    "sg:postcode":"1700",
    "sg:province":"Fribourg",
    "wof:name":"Corti Raymond Et Marianne Atelier Serigraph",
    "wof:placetype":"venue"
},
  "geometry": {"coordinates":[6.1361908913,46.1834716797],"type":"Point"}
}