{
  "type": "Feature",
  "properties": {
    "iso:country":"CH",
    "sg:address":"Oetlingerstrasse 177",
    "sg:city":"Basel",
    "sg:orig_category":"Bauschreinerei Herstellung von Fenstern U T\u00fcren aus Holz",
    "sg:phone":"+41 61 686 91 91",
    "sg:postcode":"4057",
    "sg:province":"Basel-Stadt",
    "wof:name":"Robert Schweizer Ag",
    "wof:placetype":"venue"
},
  "geometry": {"coordinates":[7.5957899094,47.5680618286],"type":"Point"}
}