{
  "type": "Feature",
  "properties": {
    "iso:country":"CH",
    "sg:address":"Granois",
    "sg:city":"Chandolin-savi\u00e8se",
    "sg:orig_category":"RESTAURANTS: TEA-ROOMS",
    "sg:phone":"+41 27 207 12 88",
    "sg:postcode":"1965",
    "sg:province":"Valais",
    "wof:name":"Roten, Bernard",
    "wof:placetype":"venue"
},
  "geometry": {"coordinates":[7.3364601135,46.1857681274],"type":"Point"}
}