{
  "type": "Feature",
  "properties": {
    "iso:country":"CH",
    "sg:address":"Terrassenweg 1a",
    "sg:city":"Zug",
    "sg:orig_category":"Unclassifiable Establishments",
    "sg:postcode":"6300",
    "sg:province":"Zug",
    "wof:name":"Khp Marketing Gmbh",
    "wof:placetype":"venue"
},
  "geometry": {"coordinates":[8.5191020966,47.171295166],"type":"Point"}
}