{
  "type": "Feature",
  "properties": {
    "iso:country":"CH",
    "sg:address":"Bahnhofstrasse 4",
    "sg:city":"G\u00fcttingen",
    "sg:orig_category":"Primarschulen",
    "sg:phone":"+41 71 463 12 74",
    "sg:postcode":"8594",
    "sg:province":"Thurgau",
    "wof:name":"Primarschule",
    "wof:placetype":"venue"
},
  "geometry": {"coordinates":[9.2882909775,47.6037788391],"type":"Point"}
}