{
  "type": "Feature",
  "properties": {
    "iso:country":"CH",
    "sg:address":"Bernstrasse 145 3052 Zollikofen. Postfach",
    "sg:city":"Zollikofen",
    "sg:orig_category":"Herstellung von sonstigen elektrischen Ausr\u00fcstungen",
    "sg:phone":"+41 31 915 44 44",
    "sg:postcode":"3052",
    "sg:province":"Bern",
    "wof:name":"Gebr\u00fcder Meier Ag",
    "wof:placetype":"venue"
},
  "geometry": {"coordinates":[7.4583559036,46.9961051941],"type":"Point"}
}