{
  "type": "Feature",
  "properties": {
    "iso:country":"CH",
    "sg:address":"Herrengass 12a",
    "sg:city":"Lyss",
    "sg:orig_category":"Wohnheime",
    "sg:phone":"+41 32 384 18 36",
    "sg:postcode":"3250",
    "sg:province":"Bern",
    "wof:name":"Stiftung Alterssiedlungen Lyss",
    "wof:placetype":"venue"
},
  "geometry": {"coordinates":[7.3079900742,47.0719146729],"type":"Point"}
}