{
  "type": "Feature",
  "properties": {
    "iso:country":"CH",
    "sg:address":"Lerchenb\u00fchlstrasse 36 6045 Meggen. Postfach",
    "sg:city":"Meggen",
    "sg:orig_category":"Detailhandel mit Waren verschiedener Art, Hauptrichtung Nahrungsmittel",
    "sg:postcode":"6045",
    "sg:province":"Luzern",
    "wof:name":"Landwirtschaftliche Genossenschaft Meggen",
    "wof:placetype":"venue"
},
  "geometry": {"coordinates":[8.3657369614,47.0387306213],"type":"Point"}
}