{
  "type": "Feature",
  "properties": {
    "iso:country":"CH",
    "sg:address":"Kreuzgasse",
    "sg:city":"Latterbach",
    "sg:orig_category":"Druck ohne Zeitungsdruck Offsetdruck",
    "sg:phone":"+41 31 382 31 26",
    "sg:postcode":"3758",
    "sg:province":"Bern",
    "wof:name":"Druckerei Gerteis Ag",
    "wof:placetype":"venue"
},
  "geometry": {"coordinates":[7.4170198441,46.9473342896],"type":"Point"}
}