{
  "type": "Feature",
  "properties": {
    "iso:country":"CH",
    "sg:address":"Alte Wildenstrasse 2",
    "sg:city":"Zezikon",
    "sg:orig_category":"Allgemeiner Hoch U Tiefbau",
    "sg:phone":"+41 71 657 27 17",
    "sg:postcode":"9556",
    "sg:province":"Thurgau",
    "wof:name":"Flury Baumanagement",
    "wof:placetype":"venue"
},
  "geometry": {"coordinates":[9.030931,47.526489],"type":"Point"}
}