{
  "type": "Feature",
  "properties": {
    "iso:country":"CH",
    "sg:address":"Sunnige Hof 30",
    "sg:city":"Z\u00fcrich",
    "sg:orig_category":"Hardwareberatung",
    "sg:phone":"+41 13227125",
    "sg:postcode":"8051",
    "sg:province":"Z\u00fcrich",
    "wof:name":"Haas, Pc Pirat",
    "wof:placetype":"venue"
},
  "geometry": {"coordinates":[8.5870723724,47.3993911743],"type":"Point"}
}