{
  "type": "Feature",
  "properties": {
    "iso:country":"CH",
    "sg:address":"Sonnenweg 8 9400 Rorschach. Postfach",
    "sg:city":"Rorschach",
    "sg:orig_category":"Grosshandel mit Getr\u00e4nken",
    "sg:postcode":"9400",
    "sg:province":"St. Gallen",
    "wof:name":"Vinoteca Del Duero Gmbh",
    "wof:placetype":"venue"
},
  "geometry": {"coordinates":[9.4888191223,47.4758300781],"type":"Point"}
}