{
  "type": "Feature",
  "properties": {
    "iso:country":"CH",
    "sg:address":"Bahnhofstrasse 17",
    "sg:city":"Inkwil",
    "sg:orig_category":"Unternehmensberatung",
    "sg:phone":"+41 62 961 91 64",
    "sg:postcode":"3375",
    "sg:province":"Bern",
    "wof:name":"A. & A. Martin Future Vision",
    "wof:placetype":"venue"
},
  "geometry": {"coordinates":[7.672688961,47.1978416443],"type":"Point"}
}