{
  "type": "Feature",
  "properties": {
    "iso:country":"CH",
    "sg:address":"Ch\u00e4ppelistrasse 11",
    "sg:city":"D\u00f6ttingen",
    "sg:orig_category":"Zimmerei, Dachdeckerei, Bauspenglerei U Abdichtung",
    "sg:phone":"+41 56 223 11 77",
    "sg:postcode":"5312",
    "sg:province":"Aargau",
    "wof:name":"W\u00fcthrich Daniel",
    "wof:placetype":"venue"
},
  "geometry": {"coordinates":[8.2548542023,47.5623893738],"type":"Point"}
}