{
  "type": "Feature",
  "properties": {
    "iso:country":"CH",
    "sg:address":"Schorenstrasse 1",
    "sg:city":"Thun",
    "sg:orig_category":"Zahnarztpraxen",
    "sg:phone":"+41 33 336 10 40",
    "sg:postcode":"3604",
    "sg:province":"Bern",
    "wof:name":"Dr. Med. Dent. Daniel Kusy Zahnarzt",
    "wof:placetype":"venue"
},
  "geometry": {"coordinates":[7.6243848801,46.7401123047],"type":"Point"}
}