{
  "type": "Feature",
  "properties": {
    "iso:country":"CH",
    "sg:address":"Hardturmstrasse 134 8005 Z\u00fcrich. Postfach",
    "sg:city":"Z\u00fcrich",
    "sg:orig_category":"Allgemeiner Hoch U Tiefbau",
    "sg:phone":"+41 19105600",
    "sg:postcode":"8048",
    "sg:province":"Z\u00fcrich",
    "wof:name":"Handloser J.",
    "wof:placetype":"venue"
},
  "geometry": {"coordinates":[8.583652,47.312244],"type":"Point"}
}