{
  "type": "Feature",
  "properties": {
    "iso:country":"CH",
    "sg:address":"Chamossaire Avenue Du 6 1860 Aigle. Postfach",
    "sg:city":"Aigle",
    "sg:orig_category":"Reinigungsgewerbe",
    "sg:phone":"+41 24 466 54 11",
    "sg:postcode":"1860",
    "sg:province":"Vaud",
    "wof:name":"Piota Services Sa, Succursale D'aigle",
    "wof:placetype":"venue"
},
  "geometry": {"coordinates":[6.9684658051,46.3164825439],"type":"Point"}
}