{
  "type": "Feature",
  "properties": {
    "iso:country":"CH",
    "sg:address":"R\u00e4bacher 2",
    "sg:city":"Stallikon",
    "sg:orig_category":"Fussreflexzonenmassage P\u00e9dicure",
    "sg:phone":"+41 71 245 45 80",
    "sg:postcode":"8143",
    "sg:province":"Z\u00fcrich",
    "wof:name":"Silvia Rothlin",
    "wof:placetype":"venue"
},
  "geometry": {"coordinates":[9.3773231506,47.4277572632],"type":"Point"}
}