{
  "type": "Feature",
  "properties": {
    "iso:country":"CH",
    "sg:address":"Rue Du Mont-noble 32 3960 Siders. Postfach",
    "sg:city":"Sierre",
    "sg:orig_category":"R\u00fcckgewinnung U Vorbereitung f\u00fcr die Wiederverwertung Recycling von Schrott",
    "sg:postcode":"3960",
    "sg:province":"Valais",
    "wof:name":"Colakovic M. Ferrailleur S\u00e0rl",
    "wof:placetype":"venue"
},
  "geometry": {"coordinates":[7.5206661224,46.2854804993],"type":"Point"}
}