{
  "type": "Feature",
  "properties": {
    "iso:country":"CH",
    "sg:address":"Eichtalboden 31",
    "sg:city":"Baden",
    "sg:orig_category":"Sonstige Aktivit\u00e4ten der nicht-\u00e4rztlichen Medizinalberufe",
    "sg:phone":"+41 56 222 53 72",
    "sg:postcode":"5400",
    "sg:province":"Aargau",
    "wof:name":"Gerty Koch Atemtherapie",
    "wof:placetype":"venue"
},
  "geometry": {"coordinates":[8.2848720551,47.4730873108],"type":"Point"}
}