{
  "type": "Feature",
  "properties": {
    "iso:country":"CH",
    "sg:address":"Rue De La Carrosserie 3",
    "sg:city":"Crans-pr\u00e8s-c\u00e9ligny",
    "sg:orig_category":"Softwareentwicklung U beratung",
    "sg:phone":"+41 22 960 18 18",
    "sg:postcode":"1299",
    "sg:province":"Vaud",
    "wof:name":"Softnet Sa",
    "wof:placetype":"venue"
},
  "geometry": {"coordinates":[6.2042970657,46.3565101624],"type":"Point"}
}