{
  "type": "Feature",
  "properties": {
    "iso:country":"CH",
    "sg:address":"Hauptstrasse 9",
    "sg:city":"Bennwil",
    "sg:orig_category":"K\u00fcnstlerische U schriftstellerische T\u00e4tigkeiten U Darbietungen",
    "sg:postcode":"4431",
    "sg:province":"Basel-Landschaft",
    "wof:name":"Glas Und Porzellan Gesch\u00e4nkl\u00e4deli Friedli U.",
    "wof:placetype":"venue"
},
  "geometry": {"coordinates":[7.7827110291,47.405582428],"type":"Point"}
}