{
  "type": "Feature",
  "properties": {
    "iso:country":"CH",
    "sg:address":"M\u00fchledorfstrasse 11",
    "sg:city":"Bern",
    "sg:orig_category":"Detailhandel mit Waren verschiedener Art, Hauptrichtung Nahrungsmittel",
    "sg:phone":"+41 31 992 37 34",
    "sg:postcode":"3018",
    "sg:province":"Bern",
    "wof:name":"De Oliveira Cunha Por Do Sol",
    "wof:placetype":"venue"
},
  "geometry": {"coordinates":[7.3908419609,46.9455070496],"type":"Point"}
}