{
  "type": "Feature",
  "properties": {
    "iso:country":"CH",
    "sg:address":"Baselstrasse 10",
    "sg:city":"Laufen",
    "sg:classifiers":[
        {
            "category":"Restaurant",
            "type":"Food & Drink"
        }
    ],
    "sg:phone":"+41 61 761 62 43",
    "sg:postcode":"4242",
    "sg:province":"Basel-Landschaft",
    "wof:name":"Restaurant Hirschen",
    "wof:placetype":"venue"
},
  "geometry": {"coordinates":[7.5008897781,47.4235687256],"type":"Point"}
}