{
  "type": "Feature",
  "properties": {
    "iso:country":"CH",
    "sg:address":"1972",
    "sg:city":"Anz\u00e8re",
    "sg:classifiers":[
        {
            "category":"Restaurant",
            "type":"Food & Drink"
        }
    ],
    "sg:phone":"+41 27 398 27 41",
    "sg:postcode":"1972",
    "sg:province":"Valais",
    "wof:name":"Restaurant Poste",
    "wof:placetype":"venue"
},
  "geometry": {"coordinates":[7.4004211426,46.2969818115],"type":"Point"}
}