{
  "type": "Feature",
  "properties": {
    "iso:country":"CH",
    "sg:address":"Bahnhofstrasse 43",
    "sg:city":"Lenzburg",
    "sg:orig_category":"RESTAURANTS: TEA-ROOMS",
    "sg:phone":"+41 62 891 16 42",
    "sg:postcode":"5600",
    "sg:province":"Aargau",
    "wof:name":"Restaurant Warteck",
    "wof:placetype":"venue"
},
  "geometry": {"coordinates":[8.1713008881,47.3904685974],"type":"Point"}
}