{
  "type": "Feature",
  "properties": {
    "iso:country":"CH",
    "sg:address":"Schl\u00fcssbergstrasse 9",
    "sg:city":"Gr\u00fcningen",
    "sg:orig_category":"Wirtschaftspr\u00fcfung, Steuerberatung U Treuhand",
    "sg:phone":"+41 16877010",
    "sg:postcode":"8627",
    "sg:province":"Z\u00fcrich",
    "wof:name":"B. Althaus & T. Z\u00fcrcher Treuhandb\u00fcro",
    "wof:placetype":"venue"
},
  "geometry": {"coordinates":[8.756357193,47.2773361206],"type":"Point"}
}