{
  "type": "Feature",
  "properties": {
    "iso:country":"CH",
    "sg:address":"Forchstr. 113b 8124 Maur. Postfach",
    "sg:city":"Forch",
    "sg:orig_category":"RESTAURANTS: TEA-ROOMS",
    "sg:phone":"+41 62 771 12 75",
    "sg:postcode":"8127",
    "sg:province":"Z\u00fcrich",
    "wof:name":"Mathilde Brunner-r\u00fcede",
    "wof:placetype":"venue"
},
  "geometry": {"coordinates":[8.1824913025,47.2581558228],"type":"Point"}
}