{
  "type": "Feature",
  "properties": {
    "iso:country":"CH",
    "sg:address":"Hauptstrasse 1632",
    "sg:city":"Wildhaus",
    "sg:classifiers":[
        {
            "category":"Travel",
            "subcategory":"Hotels & Motels",
            "type":"Entertainment"
        }
    ],
    "sg:phone":"+41 71 999 16 16",
    "sg:postcode":"9658",
    "sg:province":"St. Gallen",
    "sg:tags":[
        "hotels",
        "mit",
        "restaurant"
    ],
    "wof:name":"Hotel Selun",
    "wof:placetype":"venue"
},
  "geometry": {"coordinates":[9.3415031433,47.2019233704],"type":"Point"}
}