{
  "type": "Feature",
  "properties": {
    "iso:country":"CH",
    "sg:address":"Sommeraustrasse 3",
    "sg:city":"Hombrechtikon",
    "sg:orig_category":"Innendekorationsateliers",
    "sg:phone":"+41 55 244 24 42",
    "sg:postcode":"8634",
    "sg:province":"Z\u00fcrich",
    "wof:name":"Brigitte Baumgartner Sommerau-innendekorationen",
    "wof:placetype":"venue"
},
  "geometry": {"coordinates":[8.762008667,47.2503623962],"type":"Point"}
}