{
  "type": "Feature",
  "properties": {
    "iso:country":"CH",
    "sg:address":"Bromberg 27",
    "sg:city":"Laufen",
    "sg:orig_category":"Unclassifiable Establishments",
    "sg:phone":"+41 61 761 62 15",
    "sg:postcode":"4242",
    "sg:province":"Basel-Landschaft",
    "wof:name":"Jermann Heinz Interbrain",
    "wof:placetype":"venue"
},
  "geometry": {"coordinates":[7.491765976,47.4237365723],"type":"Point"}
}