{
  "type": "Feature",
  "properties": {
    "iso:country":"CH",
    "sg:address":"Wohlengraben 1",
    "sg:city":"Hinterkappelen",
    "sg:orig_category":"Ger\u00fcstbau Sonstiger spezialisierter Hoch U Tiefbau",
    "sg:postcode":"3032",
    "sg:province":"Bern",
    "wof:name":"Ger\u00fcst-'fritz' Ag",
    "wof:placetype":"venue"
},
  "geometry": {"coordinates":[7.3841328621,46.9673461914],"type":"Point"}
}