{
  "type": "Feature",
  "properties": {
    "iso:country":"CH",
    "sg:address":"Zielstrasse 50",
    "sg:city":"Appenzell",
    "sg:orig_category":"Autospenglereien",
    "sg:phone":"+41 71 787 46 02",
    "sg:postcode":"9050",
    "sg:province":"Appenzell Innerhoden",
    "wof:name":"Robert Rechsteiner Autospenglerei",
    "wof:placetype":"venue"
},
  "geometry": {"coordinates":[9.407593,47.3353],"type":"Point"}
}