{
  "type": "Feature",
  "properties": {
    "iso:country":"CH",
    "sg:address":"Bahnhofstrasse 15",
    "sg:city":"Schwyz",
    "sg:orig_category":"Interessenvertretungen",
    "sg:phone":"+41 41 819 19 15",
    "sg:postcode":"6430",
    "sg:province":"Schwyz",
    "wof:name":"Ausbildungs-stiftung F\u00fcr Den Kanton Schwyz Und Die Bezirke See Und Gaster (kanton St. Gallen)",
    "wof:placetype":"venue"
},
  "geometry": {"coordinates":[8.6492977142,47.0214271545],"type":"Point"}
}