{
  "type": "Feature",
  "properties": {
    "iso:country":"CH",
    "sg:address":"Haslenstrasse 17",
    "sg:city":"Appenzell",
    "sg:orig_category":"Zimmerei, Ingenieurholzbau",
    "sg:phone":"+41 71 787 19 42",
    "sg:postcode":"9050",
    "sg:province":"Appenzell Innerhoden",
    "wof:name":"Hans Koller Zimmerei",
    "wof:placetype":"venue"
},
  "geometry": {"coordinates":[9.4027929306,47.3386116028],"type":"Point"}
}