{
  "type": "Feature",
  "properties": {
    "iso:country":"CH",
    "sg:address":"Obermattstrasse 34",
    "sg:city":"Schwyz",
    "sg:orig_category":"Stukkateurgewerbe, Gipserei U Verputzerei",
    "sg:postcode":"6430",
    "sg:province":"Schwyz",
    "wof:name":"Nider\u00f6st Gipsergesch\u00e4ft",
    "wof:placetype":"venue"
},
  "geometry": {"coordinates":[8.6541652679,47.027053833],"type":"Point"}
}