{
  "type": "Feature",
  "properties": {
    "iso:country":"CH",
    "sg:address":"Kupferstrasse 12",
    "sg:city":"Chur",
    "sg:classifiers":[
        {
            "category":"Personal",
            "subcategory":"Piercing",
            "type":"Services"
        }
    ],
    "sg:phone":"+41 79 406 71 22",
    "sg:postcode":"7000",
    "sg:province":"Graubunden",
    "sg:tags":[
        "tattoo"
    ],
    "wof:name":"Tattoo-studio Skin-art",
    "wof:placetype":"venue"
},
  "geometry": {"coordinates":[9.5301790237,46.8484649658],"type":"Point"}
}