{
  "type": "Feature",
  "properties": {
    "iso:country":"CH",
    "sg:address":"Route Des Aunaires 15",
    "sg:city":"Monthey",
    "sg:orig_category":"Architektur U Ingenieurb\u00fcros",
    "sg:phone":"+41 79 216 90 25",
    "sg:postcode":"1870",
    "sg:province":"Valais",
    "wof:name":"Moix Ing\u00e9nieur Conseil S\u00e0rl",
    "wof:placetype":"venue"
},
  "geometry": {"coordinates":[6.95568,46.260677],"type":"Point"}
}