{
  "type": "Feature",
  "properties": {
    "iso:country":"CH",
    "sg:address":"Bernstrasse Suberg",
    "sg:city":"Grossaffoltern",
    "sg:orig_category":"Grosshandel mit lebenden Tieren",
    "sg:phone":"+41 32 389 11 86",
    "sg:postcode":"3257",
    "sg:province":"Bern",
    "wof:name":"Liniger-hofer Max, Vieh Und Fleischhandel",
    "wof:placetype":"venue"
},
  "geometry": {"coordinates":[7.3613591194,47.0663986206],"type":"Point"}
}