{
  "type": "Feature",
  "properties": {
    "iso:country":"CH",
    "sg:address":"Baselstrasse 30",
    "sg:city":"Dagmersellen",
    "sg:orig_category":"Darlehenskassen U Raiffeisenbanken",
    "sg:phone":"+41 62 756 36 86",
    "sg:postcode":"6252",
    "sg:province":"Luzern",
    "wof:name":"Raiffeisenbank",
    "wof:placetype":"venue"
},
  "geometry": {"coordinates":[7.98622,47.215298],"type":"Point"}
}