{
  "type": "Feature",
  "properties": {
    "iso:country":"CH",
    "sg:address":"Chasseralweg 1",
    "sg:city":"Kappelen",
    "sg:orig_category":"Fuse Elements, Fuse Sockets",
    "sg:phone":"+41 32 391 70 50",
    "sg:postcode":"3273",
    "sg:province":"Bern",
    "wof:name":"H. Baumann Ag",
    "wof:placetype":"venue"
},
  "geometry": {"coordinates":[7.265021801,47.0593261719],"type":"Point"}
}