{
  "type": "Feature",
  "properties": {
    "iso:country":"CH",
    "sg:address":"Baselstrasse 41",
    "sg:city":"Dagmersellen",
    "sg:orig_category":"Architektur U Ingenieurb\u00fcros",
    "sg:phone":"+41 62 748 20 70",
    "sg:postcode":"6252",
    "sg:province":"Luzern",
    "wof:name":"Igd Gr\u00fcter Ag",
    "wof:placetype":"venue"
},
  "geometry": {"coordinates":[7.984161,47.216591],"type":"Point"}
}