{
  "type": "Feature",
  "properties": {
    "addr:full":"Eschikerstrasse 21 Effretikon Z\u00fcrich 8307",
    "addr:housenumber":"21",
    "addr:postcode":"8307",
    "addr:street":"Eschikerstrasse",
    "iso:country":"CH",
    "sg:address":"Eschikerstrasse 21",
    "sg:city":"Effretikon",
    "sg:orig_category":"Architektur U Ingenieurb\u00fcros Bauingenieurb\u00fcros Hochbau",
    "sg:phone":"+41 19863666",
    "sg:postcode":"8307",
    "sg:province":"Z\u00fcrich",
    "wof:name":"Hetzer, J\u00e4ckli & Partner Ingenieurb\u00fcro Ag",
    "wof:placetype":"venue"
},
  "geometry": {"coordinates":[8.68906,47.4347],"type":"Point"}
}