{
  "type": "Feature",
  "properties": {
    "iso:country":"CH",
    "sg:address":"Epagny Route D' 559",
    "sg:city":"Broc",
    "sg:orig_category":"Detailhandel mit Textilien",
    "sg:postcode":"1636",
    "sg:province":"Fribourg",
    "wof:name":"Prin F. Machines \u00e0 Coudre",
    "wof:placetype":"venue"
},
  "geometry": {"coordinates":[7.0859889984,46.5971984863],"type":"Point"}
}