{
  "type": "Feature",
  "properties": {
    "iso:country":"CH",
    "sg:address":"Kirchgasse 18",
    "sg:city":"Schupfart",
    "sg:orig_category":"Sportvereine Ballsport Handball",
    "sg:postcode":"4325",
    "sg:province":"Aargau",
    "wof:name":"Tv Schupfart",
    "wof:placetype":"venue"
},
  "geometry": {"coordinates":[7.9678769112,47.5131607056],"type":"Point"}
}