{
  "type": "Feature",
  "properties": {
    "iso:country":"CH",
    "sg:address":"Via Agli Orti 5",
    "sg:city":"Melide",
    "sg:orig_category":"Fachdetailhandel in Verkaufsr\u00e4umen Handelsvermittlung U Grosshandel",
    "sg:phone":"+41 91 649 66 03",
    "sg:postcode":"6815",
    "sg:province":"Ticino",
    "wof:name":"Anaku-vertrieb Di Irma Uygun Importaz.-esportaz.",
    "wof:placetype":"venue"
},
  "geometry": {"coordinates":[8.9469022751,45.9529762268],"type":"Point"}
}