{
  "type": "Feature",
  "properties": {
    "iso:country":"CH",
    "sg:address":"Z\u00e4hringerstrasse 19",
    "sg:city":"Luzern",
    "sg:orig_category":"Kinesiologie",
    "sg:phone":"+41 41 422 00 28",
    "sg:postcode":"6003",
    "sg:province":"Luzern",
    "wof:name":"Edith Dober Kinesiologie",
    "wof:placetype":"venue"
},
  "geometry": {"coordinates":[8.30148983,47.0473060608],"type":"Point"}
}