{
  "type": "Feature",
  "properties": {
    "iso:country":"CH",
    "sg:address":"3063 Ittigen. Postfach",
    "sg:city":"Worblaufen",
    "sg:orig_category":"Detailhandel mit Metallwaren, Anstrichmitteln, Glaswaren, Bau U Heimwerkerbedarf",
    "sg:phone":"+41 31 921 50 95",
    "sg:postcode":"3048",
    "sg:province":"Bern",
    "wof:name":"Kurz Theo.",
    "wof:placetype":"venue"
},
  "geometry": {"coordinates":[7.4793901443,46.9816894531],"type":"Point"}
}