{
  "type": "Feature",
  "properties": {
    "iso:country":"CH",
    "sg:address":"Grand-rue 1",
    "sg:city":"Lutry",
    "sg:orig_category":"Arztpraxen",
    "sg:phone":"+41 21 791 59 91",
    "sg:postcode":"1095",
    "sg:province":"Vaud",
    "wof:name":"Dr M\u00e9d. Martine Francioli M\u00e9decin Sp\u00e9cialiste Fmh",
    "wof:placetype":"venue"
},
  "geometry": {"coordinates":[6.683913,46.502895],"type":"Point"}
}