{
  "type": "Feature",
  "properties": {
    "iso:country":"CH",
    "sg:address":"Aemtlerstrasse 152",
    "sg:city":"Z\u00fcrich",
    "sg:orig_category":"Selbst\u00e4ndige bildende K\u00fcnstler",
    "sg:phone":"+41 14930557",
    "sg:postcode":"8003",
    "sg:province":"Z\u00fcrich",
    "wof:name":"Gebr\u00fcder M\u00fcrset Bildhauer-& Naturstein Ag",
    "wof:placetype":"venue"
},
  "geometry": {"coordinates":[8.5107002258,47.3760643005],"type":"Point"}
}