{
  "type": "Feature",
  "properties": {
    "iso:country":"CH",
    "sg:address":"Chemin Des Abeilles",
    "sg:city":"No\u00ebs",
    "sg:orig_category":"Fahrschulen, Flugschulen",
    "sg:phone":"+41 79 207 15 75",
    "sg:postcode":"3976",
    "sg:province":"Valais",
    "wof:name":"Angelo-rico Attanasio Autoscuola",
    "wof:placetype":"venue"
},
  "geometry": {"coordinates":[8.9731969833,46.1599578857],"type":"Point"}
}