{
  "type": "Feature",
  "properties": {
    "iso:country":"CH",
    "sg:address":"Bonne-esp\u00e9rance Ch. De 35 1006 Lausanne. Postfach",
    "sg:city":"Lausanne",
    "sg:classifiers":[
        {
            "category":"Travel",
            "subcategory":"Hotels & Motels",
            "type":"Entertainment"
        }
    ],
    "sg:phone":"+41 21 728 79 39",
    "sg:postcode":"1003",
    "sg:province":"Vaud",
    "sg:tags":[
        "hotels",
        "mit",
        "restaurant"
    ],
    "wof:name":"Residence Du Midi S\u00e0rl Appartements-h\u00f4tels",
    "wof:placetype":"venue"
},
  "geometry": {"coordinates":[6.6489992142,46.5134086609],"type":"Point"}
}