{
  "type": "Feature",
  "properties": {
    "iso:country":"CH",
    "sg:address":"Grand-rue 53",
    "sg:city":"Morges",
    "sg:orig_category":"Fotografische Ateliers Fotografisches Gewerbe U fotografische Laboratorien",
    "sg:phone":"+41 21 801 40 41",
    "sg:postcode":"1110",
    "sg:province":"Vaud",
    "wof:name":"Santo Tizzian Studio De Photographie",
    "wof:placetype":"venue"
},
  "geometry": {"coordinates":[6.4986329079,46.5092086792],"type":"Point"}
}