{
  "type": "Feature",
  "properties": {
    "addr:full":"J\u00f6ndliweg 15 Rothrist Aargau 4852",
    "addr:housenumber":"15",
    "addr:postcode":"4852",
    "addr:street":"Joendliweg",
    "iso:country":"CH",
    "sg:address":"J\u00f6ndliweg 15",
    "sg:city":"Rothrist",
    "sg:orig_category":"Detailhandel mit Bekleidung",
    "sg:postcode":"4852",
    "sg:province":"Aargau",
    "wof:name":"Meier-haas Versandhandel",
    "wof:placetype":"venue"
},
  "geometry": {"coordinates":[7.917763,47.296654],"type":"Point"}
}