{
  "type": "Feature",
  "properties": {
    "iso:country":"CH",
    "sg:address":"Langfeld 2",
    "sg:city":"Kaltbrunn",
    "sg:orig_category":"G\u00fcterbef\u00f6rderung im Strassenverkehr",
    "sg:phone":"+41 55 283 32 68",
    "sg:postcode":"8722",
    "sg:province":"St. Gallen",
    "wof:name":"Waren Und Umzugtransport Umjenovic Stevo",
    "wof:placetype":"venue"
},
  "geometry": {"coordinates":[9.0212469101,47.213886261],"type":"Point"}
}