{
  "type": "Feature",
  "properties": {
    "iso:country":"CH",
    "sg:address":"Zur Neum\u00fchle",
    "sg:city":"Beggingen",
    "sg:orig_category":"S\u00e4gewerke",
    "sg:phone":"+41 52 680 14 19",
    "sg:postcode":"8228",
    "sg:province":"Schaffhausen",
    "wof:name":"Fedor Vogelsanger S\u00e4gerei",
    "wof:placetype":"venue"
},
  "geometry": {"coordinates":[8.5309143066,47.7655220032],"type":"Point"}
}