{
  "type": "Feature",
  "properties": {
    "iso:country":"CH",
    "sg:address":"Route De Thonon 148",
    "sg:city":"V\u00e9senaz",
    "sg:orig_category":"Einzelhandel mit Automobilteilen U Zubeh\u00f6r",
    "sg:phone":"+41 22 752 45 85",
    "sg:postcode":"1222",
    "sg:province":"Gen\u00e8ve",
    "wof:name":"R\u00e9my Holzapfel Pneus Claude",
    "wof:placetype":"venue"
},
  "geometry": {"coordinates":[6.2120451927,46.2464485168],"type":"Point"}
}