{
  "type": "Feature",
  "properties": {
    "iso:country":"CH",
    "sg:address":"Via Pobbia 13",
    "sg:city":"Sementina",
    "sg:orig_category":"Instandhaltung U Reparatur von Automobilen",
    "sg:phone":"+41 91 857 43 65",
    "sg:postcode":"6514",
    "sg:province":"Ticino",
    "wof:name":"Garage Autovama Sa",
    "wof:placetype":"venue"
},
  "geometry": {"coordinates":[8.9979448318,46.1782455444],"type":"Point"}
}