{
  "type": "Feature",
  "properties": {
    "iso:country":"CH",
    "sg:address":"Via Alla Ramogna 8",
    "sg:city":"Locarno",
    "sg:orig_category":"Parf\u00fcmerien U sonstiger Detailhandel mit kosmetischen Artikeln U K\u00f6rperpflegemitteln",
    "sg:phone":"+41 91 751 94 47",
    "sg:postcode":"6600",
    "sg:province":"Ticino",
    "wof:name":"Parf\u00fcmerie Douglas Sa",
    "wof:placetype":"venue"
},
  "geometry": {"coordinates":[8.799372673,46.1709861755],"type":"Point"}
}