{
  "type": "Feature",
  "properties": {
    "iso:country":"CH",
    "sg:address":"Oberwilerstrasse 3",
    "sg:city":"Therwil",
    "sg:orig_category":"Nahrungsmittel-Industrie: Rohstoffe",
    "sg:postcode":"4106",
    "sg:province":"Basel-Landschaft",
    "wof:name":"A Portuguesa Do Nascimento Ilda",
    "wof:placetype":"venue"
},
  "geometry": {"coordinates":[9.4688119888,47.1664924622],"type":"Point"}
}