{
  "type": "Feature",
  "properties": {
    "iso:country":"CH",
    "sg:address":"Via Trevano 7a",
    "sg:city":"Lugano",
    "sg:orig_category":"Effektenvermittlung Broker Finanzierungsinstitutionen",
    "sg:phone":"+41 22 849 55 00",
    "sg:postcode":"6900",
    "sg:province":"Ticino",
    "wof:name":"Dalgest Sa",
    "wof:placetype":"venue"
},
  "geometry": {"coordinates":[6.1545290947,46.2016983032],"type":"Point"}
}