{
  "type": "Feature",
  "properties": {
    "iso:country":"CH",
    "sg:address":"9322",
    "sg:city":"Egnach",
    "sg:orig_category":"Mechanik",
    "sg:postcode":"9322",
    "sg:province":"Thurgau",
    "wof:name":"Ackermann Walter",
    "wof:placetype":"venue"
},
  "geometry": {"coordinates":[9.3818778992,47.5442619324],"type":"Point"}
}