{
  "type": "Feature",
  "properties": {
    "iso:country":"CH",
    "sg:address":"Sennweidweg 4",
    "sg:city":"Feusisberg",
    "sg:orig_category":"Abbruch U Sprenggewerbe, Erdbewegungsarbeiten",
    "sg:phone":"+41 79 691 71 41",
    "sg:postcode":"8835",
    "sg:province":"Schwyz",
    "wof:name":"Huber Daniel",
    "wof:placetype":"venue"
},
  "geometry": {"coordinates":[8.763535,47.187302],"type":"Point"}
}