{
  "type": "Feature",
  "properties": {
    "iso:country":"CH",
    "sg:address":"Route De Champ Colin 18 1260 Nyon. Postfach",
    "sg:city":"Gen\u00e8ve",
    "sg:classifiers":[
        {
            "category":"Professional",
            "subcategory":"Employment Agencies",
            "type":"Services"
        }
    ],
    "sg:postcode":"1201",
    "sg:province":"Gen\u00e8ve",
    "sg:tags":[
        "personal",
        "u",
        "stellenvermittlung"
    ],
    "wof:name":"Integra Services Sa",
    "wof:placetype":"venue"
},
  "geometry": {"coordinates":[6.2187519073,46.3821868896],"type":"Point"}
}