{
  "type": "Feature",
  "properties": {
    "iso:country":"CH",
    "sg:address":"Gasterweg 17",
    "sg:city":"Uznach",
    "sg:orig_category":"Betrieb U technische Hilfsdienste des Kultur U Unterhaltungswesens Patentverwertung",
    "sg:phone":"+41 55 445 24 00",
    "sg:postcode":"8730",
    "sg:province":"St. Gallen",
    "wof:name":"Medwell Ag",
    "wof:placetype":"venue"
},
  "geometry": {"coordinates":[8.990202,47.225201],"type":"Point"}
}