{
  "type": "Feature",
  "properties": {
    "iso:country":"CH",
    "sg:address":"1732",
    "sg:city":"Arconciel",
    "sg:orig_category":"Verwertung von Milch",
    "sg:postcode":"1732",
    "sg:province":"Fribourg",
    "wof:name":"Soci\u00e9t\u00e9 De Laiterie D'arconciel",
    "wof:placetype":"venue"
},
  "geometry": {"coordinates":[7.1173400879,46.7530403137],"type":"Point"}
}