{
  "type": "Feature",
  "properties": {
    "iso:country":"CH",
    "sg:address":"Unterherten",
    "sg:city":"Altikon",
    "sg:orig_category":"Autogaragen",
    "sg:phone":"+41 52 336 14 18",
    "sg:postcode":"8479",
    "sg:province":"Z\u00fcrich",
    "wof:name":"Hansuli Wiesmann Garage",
    "wof:placetype":"venue"
},
  "geometry": {"coordinates":[8.800837,47.568531],"type":"Point"}
}