{
  "type": "Feature",
  "properties": {
    "iso:country":"CH",
    "sg:address":"Rte Des Jeunes 4bis",
    "sg:city":"Grand-lancy",
    "sg:orig_category":"Pensionskassen",
    "sg:postcode":"1212",
    "sg:province":"Gen\u00e8ve",
    "wof:name":"Fondation De Pr\u00e9voyance En Faveur Du Personnel De La Maison Solo, Fours Industriels Sa",
    "wof:placetype":"venue"
},
  "geometry": {"coordinates":[7.2642469406,47.1211776733],"type":"Point"}
}