{
  "type": "Feature",
  "properties": {
    "iso:country":"CH",
    "sg:address":"Wanngasse 29",
    "sg:city":"Thayngen",
    "sg:orig_category":"Blumen U Zierpflanzenbau Detailhandel mit Blumen U Pflanzen",
    "sg:phone":"+41 52 649 35 33",
    "sg:postcode":"8240",
    "sg:province":"Schaffhausen",
    "wof:name":"Hanspeter & Elisabeth Schalch G\u00e4rtnerei & Blumengesch\u00e4ft",
    "wof:placetype":"venue"
},
  "geometry": {"coordinates":[8.714383,47.747528],"type":"Point"}
}