{
  "type": "Feature",
  "properties": {
    "iso:country":"CH",
    "sg:address":"Pfaffensteinstrasse 20",
    "sg:city":"Pfaffhausen",
    "sg:orig_category":"Sportvereine Sch\u00fctzen",
    "sg:phone":"+41 18251793",
    "sg:postcode":"8118",
    "sg:province":"Z\u00fcrich",
    "wof:name":"Sch\u00fctzenverein F\u00e4llanden",
    "wof:placetype":"venue"
},
  "geometry": {"coordinates":[8.6292552948,47.367477417],"type":"Point"}
}