{
  "type": "Feature",
  "properties": {
    "iso:country":"CH",
    "sg:address":"Bergacher 14 3325 Hettiswil. Postfach",
    "sg:city":"Hettiswil",
    "sg:orig_category":"Sonstige pers\u00f6nliche Dienstleistungen",
    "sg:postcode":"3325",
    "sg:province":"Bern",
    "wof:name":"Soder & Partner Dienstleistungen Im Ber. Beratung U. Planung.",
    "wof:placetype":"venue"
},
  "geometry": {"coordinates":[7.5583438873,47.0327949524],"type":"Point"}
}