{
  "type": "Feature",
  "properties": {
    "iso:country":"CH",
    "sg:address":"Kreuzgasse 26",
    "sg:city":"Schmerikon",
    "sg:orig_category":"Detailhandel mit Getr\u00e4nken",
    "sg:phone":"+41 55 282 22 76",
    "sg:postcode":"8716",
    "sg:province":"St. Gallen",
    "wof:name":"Josef Boos Getr\u00e4nkedienst",
    "wof:placetype":"venue"
},
  "geometry": {"coordinates":[8.9420995712,47.226272583],"type":"Point"}
}