{
  "type": "Feature",
  "properties": {
    "iso:country":"CH",
    "sg:address":"Quaderstrasse 7",
    "sg:city":"Chur",
    "sg:classifiers":[
        {
            "category":"Insurance",
            "subcategory":"Insurance Agent",
            "type":"Services"
        }
    ],
    "sg:phone":"+41 81 253 60 31",
    "sg:postcode":"7000",
    "sg:province":"Graubunden",
    "sg:tags":[
        "versicherungsagenturen",
        "-broker"
    ],
    "wof:name":"Uvb Panorama Unabh\u00e4ngige Vers'beratung",
    "wof:placetype":"venue"
},
  "geometry": {"coordinates":[9.5320730209,46.8523750305],"type":"Point"}
}