{
  "type": "Feature",
  "properties": {
    "iso:country":"CH",
    "sg:address":"Kresta 32",
    "sg:city":"Schaan",
    "sg:orig_category":"Zahnarztpraxen",
    "sg:phone":"+41 75 232 71 91",
    "sg:postcode":"9494",
    "wof:name":"Dr. Med. Dent. Norman Kranz Zahnarzt",
    "wof:placetype":"venue"
},
  "geometry": {"coordinates":[9.5168361664,47.1699256897],"type":"Point"}
}