{
  "type": "Feature",
  "properties": {
    "iso:country":"CH",
    "sg:address":"Bielstrasse 111 4500 Solothurn. Postfach",
    "sg:city":"Solothurn",
    "sg:orig_category":"Advokaturb\u00fcros Notariate",
    "sg:phone":"+41 32 621 72 70",
    "sg:postcode":"4503",
    "sg:province":"Solothurn",
    "wof:name":"Kunz D\u00e4twyler Harder & Heusi Advokatur- & Notariatsb\u00fcro",
    "wof:placetype":"venue"
},
  "geometry": {"coordinates":[7.520158,47.212101],"type":"Point"}
}