{
  "type": "Feature",
  "properties": {
    "iso:country":"CH",
    "sg:address":"K\u00fcrzeweg 31 2542 Pieterlen. Postfach 24",
    "sg:city":"Pieterlen",
    "sg:orig_category":"Sanit\u00e4r U Heizungsinstallation Sanit\u00e4r, Heizungs U L\u00fcftungsinstallation",
    "sg:postcode":"2542",
    "sg:province":"Bern",
    "wof:name":"Schneiter Emil, Zentralheizungen",
    "wof:placetype":"venue"
},
  "geometry": {"coordinates":[8.7936935425,47.3207130432],"type":"Point"}
}