{
  "type": "Feature",
  "properties": {
    "iso:country":"CH",
    "sg:address":"Nussbaumstrasse 11 8003 Z\u00fcrich. Postfach",
    "sg:city":"Z\u00fcrich",
    "sg:orig_category":"Architektur U Ingenieurb\u00fcros",
    "sg:postcode":"8001",
    "sg:province":"Z\u00fcrich",
    "wof:name":"Architekturb\u00fcro Gantenbein J.",
    "wof:placetype":"venue"
},
  "geometry": {"coordinates":[8.514688,47.371525],"type":"Point"}
}