{
  "type": "Feature",
  "properties": {
    "iso:country":"CH",
    "sg:address":"Pilatusstrasse 17 6003 Luzern. Postfach",
    "sg:city":"Luzern",
    "sg:orig_category":"Internet Provider Sonstige mit der Informatik verbundene T\u00e4tigkeiten",
    "sg:phone":"+41 41 220 21 60",
    "sg:postcode":"6003",
    "sg:province":"Luzern",
    "wof:name":"Cape Consulting Gmbh Provider Of Business Solution; Beratung Usw",
    "wof:placetype":"venue"
},
  "geometry": {"coordinates":[8.306599617,47.0489692688],"type":"Point"}
}