{
  "type": "Feature",
  "properties": {
    "iso:country":"CH",
    "sg:address":"Aeschenplatz 2",
    "sg:city":"Basel",
    "sg:orig_category":"Non-Classified Establishments",
    "sg:postcode":"4052",
    "sg:province":"Basel-Stadt",
    "wof:name":"Indchem Sa",
    "wof:placetype":"venue"
},
  "geometry": {"coordinates":[7.5956292152,47.551235199],"type":"Point"}
}