{
  "type": "Feature",
  "properties": {
    "iso:country":"CH",
    "sg:address":"Neugasse 10",
    "sg:city":"Horgen",
    "sg:orig_category":"Reinigungsgewerbe",
    "sg:postcode":"8810",
    "sg:province":"Z\u00fcrich",
    "wof:name":"Stamenkovic Reinigungs Gmbh",
    "wof:placetype":"venue"
},
  "geometry": {"coordinates":[8.5885400772,47.2578392029],"type":"Point"}
}