{
  "type": "Feature",
  "properties": {
    "iso:country":"CH",
    "sg:address":"Hertizentrum 15",
    "sg:city":"Zug",
    "sg:orig_category":"Interessenvertretungen",
    "sg:postcode":"6300",
    "sg:province":"Zug",
    "wof:name":"Freie Anthroposophische Studiengemeinschaft",
    "wof:placetype":"venue"
},
  "geometry": {"coordinates":[8.5050945282,47.1781158447],"type":"Point"}
}