{
  "type": "Feature",
  "properties": {
    "iso:country":"CH",
    "sg:address":"Vaucher Avenue Edmond- 47 1203 Gen\u00e8ve. Postfach",
    "sg:city":"Gen\u00e8ve",
    "sg:orig_category":"RESTAURANTS: TEA-ROOMS",
    "sg:postcode":"1203",
    "sg:province":"Gen\u00e8ve",
    "wof:name":"Patricia Junod",
    "wof:placetype":"venue"
},
  "geometry": {"coordinates":[6.1184492111,46.2154312134],"type":"Point"}
}