{
  "type": "Feature",
  "properties": {
    "iso:country":"CH",
    "sg:address":"Oberdorfstrasse 11",
    "sg:city":"Uttwil",
    "sg:orig_category":"Elektroinstallation",
    "sg:phone":"+41 71 463 63 22",
    "sg:postcode":"8592",
    "sg:province":"Thurgau",
    "wof:name":"Elektro R\u00fcthemann Ag",
    "wof:placetype":"venue"
},
  "geometry": {"coordinates":[9.3419523239,47.5821456909],"type":"Point"}
}