{
  "type": "Feature",
  "properties": {
    "iso:country":"CH",
    "sg:address":"Postackerstrasse 28 4710 Balsthal. Postfach 106",
    "sg:city":"Balsthal",
    "sg:orig_category":"Maler U Glasergewerbe Malerei",
    "sg:phone":"+41 52 672 59 90",
    "sg:postcode":"4710",
    "sg:province":"Solothurn",
    "wof:name":"Kull Martin.",
    "wof:placetype":"venue"
},
  "geometry": {"coordinates":[8.6172103882,47.682964325],"type":"Point"}
}