{
  "type": "Feature",
  "properties": {
    "iso:country":"CH",
    "sg:address":"Promenade Des Artisans 26.",
    "sg:city":"Meyrin",
    "sg:orig_category":"Druck ohne Zeitungsdruck",
    "sg:postcode":"1217",
    "sg:province":"Gen\u00e8ve",
    "wof:name":"Color-offset, Ernst Ren\u00e9.",
    "wof:placetype":"venue"
},
  "geometry": {"coordinates":[6.0796518326,46.2377510071],"type":"Point"}
}