{
  "type": "Feature",
  "properties": {
    "iso:country":"CH",
    "sg:address":"Br\u00fcnigstrasse 101 6078 Lungern. Postfach 146",
    "sg:city":"Lungern",
    "sg:orig_category":"Detailhandel mit Uhren U Schmuck Herstellung von Schmuck, Gold U Silberschmiedwaren",
    "sg:phone":"+41 41 678 19 55",
    "sg:postcode":"6078",
    "sg:province":"Obwalden",
    "wof:name":"Halter Christoph, Goldschmiede",
    "wof:placetype":"venue"
},
  "geometry": {"coordinates":[8.1593828201,46.7848320007],"type":"Point"}
}