{
  "type": "Feature",
  "properties": {
    "iso:country":"CH",
    "sg:address":"Im Lot 7",
    "sg:city":"Uster",
    "sg:orig_category":"Architektur U Ingenieurb\u00fcros",
    "sg:phone":"+41 21 960 11 27",
    "sg:postcode":"8610",
    "sg:province":"Z\u00fcrich",
    "wof:name":"Thaulaz G\u00e9rald",
    "wof:placetype":"venue"
},
  "geometry": {"coordinates":[6.925924,46.39666],"type":"Point"}
}