{
  "type": "Feature",
  "properties": {
    "iso:country":"CH",
    "sg:address":"Schachenstrasse 3 3700 Spiez. Postfach",
    "sg:city":"Spiez",
    "sg:classifiers":[
        {
            "category":"Travel",
            "subcategory":"Hotels & Motels",
            "type":"Entertainment"
        }
    ],
    "sg:postcode":"3700",
    "sg:province":"Bern",
    "sg:tags":[
        "hotels",
        "mit",
        "restaurant"
    ],
    "wof:name":"Gastro Ag 73",
    "wof:placetype":"venue"
},
  "geometry": {"coordinates":[7.6867780685,46.6886138916],"type":"Point"}
}