{
  "type": "Feature",
  "properties": {
    "iso:country":"CH",
    "sg:address":"Oberdorfstrasse 7 3296 Arch. Postfach 110",
    "sg:city":"Arch",
    "sg:orig_category":"Herstellung U Zusammensetzung von Uhren Herstellung von Uhren",
    "sg:phone":"+41 22 707 31 31",
    "sg:postcode":"3296",
    "sg:province":"Bern",
    "wof:name":"Baume & Mercier Sa",
    "wof:placetype":"venue"
},
  "geometry": {"coordinates":[6.173855,46.199917],"type":"Point"}
}