{
  "type": "Feature",
  "properties": {
    "iso:country":"CH",
    "sg:address":"Salita Alle Chiese",
    "sg:city":"Biasca",
    "sg:classifiers":[
        {
            "category":"Education",
            "subcategory":"Library",
            "type":"Public Place"
        }
    ],
    "sg:phone":"+41 91 862 17 02",
    "sg:postcode":"6710",
    "sg:province":"Ticino",
    "sg:tags":[
        "u",
        "bibliotheken",
        "archive"
    ],
    "wof:name":"Biblioteca Popolare Parrocchiale",
    "wof:placetype":"venue"
},
  "geometry": {"coordinates":[8.971689,46.359718],"type":"Point"}
}