{
  "type": "Feature",
  "properties": {
    "iso:country":"CH",
    "sg:address":"Flurstrasse 19",
    "sg:city":"Boswil",
    "sg:orig_category":"Unternehmensberatung",
    "sg:postcode":"5623",
    "sg:province":"Aargau",
    "wof:name":"Limburg Eric Consulting",
    "wof:placetype":"venue"
},
  "geometry": {"coordinates":[8.321018219,47.3028144836],"type":"Point"}
}