{
  "type": "Feature",
  "properties": {
    "iso:country":"CH",
    "sg:address":"Rue Du Clos 21-23 1200 Genf. Postfach",
    "sg:city":"Genf",
    "sg:orig_category":"Finanzierungsinstitutionen",
    "sg:phone":"+41 22 736 74 50",
    "sg:postcode":"1200",
    "sg:province":"Gen\u00e8ve",
    "wof:name":"Somecofi Sa",
    "wof:placetype":"venue"
},
  "geometry": {"coordinates":[6.1633520126,46.2051925659],"type":"Point"}
}