{
  "type": "Feature",
  "properties": {
    "iso:country":"CH",
    "sg:address":"Grand-rue 4",
    "sg:city":"Yvonand",
    "sg:orig_category":"Detailhandel mit Blumen U Pflanzen",
    "sg:phone":"+41 24 430 24 44",
    "sg:postcode":"1462",
    "sg:province":"Vaud",
    "wof:name":"Mireille Broillet Annie Fleurs",
    "wof:placetype":"venue"
},
  "geometry": {"coordinates":[6.747033,46.799065],"type":"Point"}
}