{
  "type": "Feature",
  "properties": {
    "iso:country":"CH",
    "sg:address":"Rue De Remanan 3",
    "sg:city":"Bussigny-lausanne",
    "sg:orig_category":"Physiotherapie",
    "sg:phone":"+41 21 701 01 59",
    "sg:postcode":"1030",
    "sg:province":"Vaud",
    "wof:name":"Barbara Watson Physioth\u00e9rapie",
    "wof:placetype":"venue"
},
  "geometry": {"coordinates":[6.5503292084,46.5498046875],"type":"Point"}
}