{
  "type": "Feature",
  "properties": {
    "iso:country":"CH",
    "sg:address":"1145",
    "sg:city":"Bi\u00e8re",
    "sg:classifiers":[
        {
            "category":"Travel",
            "subcategory":"Hotels & Motels",
            "type":"Entertainment"
        }
    ],
    "sg:phone":"+41 21 809 51 23",
    "sg:postcode":"1145",
    "sg:province":"Vaud",
    "sg:tags":[
        "hotels",
        "mit",
        "restaurant"
    ],
    "wof:name":"H\u00f4tel Des Trois Sapins",
    "wof:placetype":"venue"
},
  "geometry": {"coordinates":[6.3328051567,46.5380134583],"type":"Point"}
}