{
  "type": "Feature",
  "properties": {
    "iso:country":"CH",
    "sg:address":"Chemin De La Pr\u00e9v\u00f4t\u00e9 10 2500 Biel/bienne. Postfach",
    "sg:city":"Biel/bienne",
    "sg:orig_category":"Stukkateurgewerbe, Gipserei U Verputzerei",
    "sg:postcode":"2504",
    "sg:province":"Bern",
    "wof:name":"Bezzola Jean, Successeur Riccardo Bezzola",
    "wof:placetype":"venue"
},
  "geometry": {"coordinates":[7.267343998,47.1481246948],"type":"Point"}
}