{
  "type": "Feature",
  "properties": {
    "iso:country":"CH",
    "sg:address":"Riedstrasse 4c",
    "sg:city":"Hedingen",
    "sg:orig_category":"Softwareentwicklung U beratung",
    "sg:phone":"+41 17763090",
    "sg:postcode":"8908",
    "sg:province":"Z\u00fcrich",
    "wof:name":"Ibt Ren\u00e9 Maurer Innovative B\u00fcrotechnik",
    "wof:placetype":"venue"
},
  "geometry": {"coordinates":[8.4466180801,47.2941894531],"type":"Point"}
}