{
  "type": "Feature",
  "properties": {
    "iso:country":"CH",
    "sg:address":"Gersauerstrasse 23",
    "sg:city":"Brunnen",
    "sg:orig_category":"Herstellung von sonstigen Holzwaren",
    "sg:phone":"+41 41 820 56 73",
    "sg:postcode":"6440",
    "sg:province":"Schwyz",
    "wof:name":"Schelbert Werner Ag",
    "wof:placetype":"venue"
},
  "geometry": {"coordinates":[8.602473259,46.9954147339],"type":"Point"}
}