{
  "type": "Feature",
  "properties": {
    "iso:country":"CH",
    "sg:address":"Obertal",
    "sg:city":"Walchwil",
    "sg:orig_category":"Verwertung von Milch",
    "sg:postcode":"6318",
    "sg:province":"Zug",
    "wof:name":"Milchverwertungsgenossenschaft R\u00e4geten.",
    "wof:placetype":"venue"
},
  "geometry": {"coordinates":[8.5066585541,47.1188583374],"type":"Point"}
}