{
  "type": "Feature",
  "properties": {
    "iso:country":"CH",
    "sg:address":"Spitalgasse 3011 Bern. Postfach",
    "sg:city":"Bern",
    "sg:orig_category":"Detailhandel mit Herrenbekleidung",
    "sg:phone":"+41 31 311 43 13",
    "sg:postcode":"3001",
    "sg:province":"Bern",
    "wof:name":"Pkz Burger-kehl & Co. Aktiengesellschaft Herren, Knabenkleider Usw; Fabrikation, Handel",
    "wof:placetype":"venue"
},
  "geometry": {"coordinates":[7.4433150291,46.9481735229],"type":"Point"}
}