{
  "type": "Feature",
  "properties": {
    "iso:country":"CH",
    "sg:address":"Route Du Chaluet 17",
    "sg:city":"Court",
    "sg:orig_category":"Pensionskassen",
    "sg:postcode":"2738",
    "sg:province":"Bern",
    "wof:name":"Caisse De Retraite En Faveur Du Personnel D'henri Girod Sa.",
    "wof:placetype":"venue"
},
  "geometry": {"coordinates":[7.3527851105,47.2433166504],"type":"Point"}
}