{
  "type": "Feature",
  "properties": {
    "iso:country":"CH",
    "sg:address":"Route D'aubonne",
    "sg:city":"Gimel",
    "sg:orig_category":"Instandhaltung U Reparatur von Automobilen",
    "sg:phone":"+41 21 828 00 00",
    "sg:postcode":"1188",
    "sg:province":"Vaud",
    "wof:name":"Garage De L'ezili\u00e8re, Baudin Christian",
    "wof:placetype":"venue"
},
  "geometry": {"coordinates":[6.3243031502,46.5066184998],"type":"Point"}
}