{
  "type": "Feature",
  "properties": {
    "iso:country":"CH",
    "sg:address":"Oltnerstrasse 3",
    "sg:city":"H\u00e4gendorf",
    "sg:orig_category":"Kauf U Verkauf von Immobilien auf eigene Rechnung",
    "sg:phone":"+41 62612415",
    "sg:postcode":"4614",
    "sg:province":"Solothurn",
    "wof:name":"Nb Neubau Ag",
    "wof:placetype":"venue"
},
  "geometry": {"coordinates":[7.8444228172,47.3333892822],"type":"Point"}
}