{
  "type": "Feature",
  "properties": {
    "addr:full":"Sonnenpl\u00e4tzli 11 Schwyz Schwyz 6430",
    "addr:housenumber":"11",
    "addr:postcode":"6430",
    "addr:street":"Sonnenplaetzli",
    "iso:country":"CH",
    "sg:address":"Sonnenpl\u00e4tzli 11",
    "sg:city":"Schwyz",
    "sg:orig_category":"Detailhandel mit Brot, Back U S\u00fcsswaren",
    "sg:phone":"+41 41 811 22 13",
    "sg:postcode":"6430",
    "sg:province":"Schwyz",
    "wof:name":"Rey-r\u00fctsche Hans, B\u00e4ckerei",
    "wof:placetype":"venue"
},
  "geometry": {"coordinates":[8.657115,47.020451],"type":"Point"}
}