{
  "type": "Feature",
  "properties": {
    "iso:country":"CH",
    "sg:address":"Industriestrasse 1",
    "sg:city":"Triesen",
    "sg:orig_category":"Unclassifiable Establishments",
    "sg:phone":"+41 75 399 33 11",
    "sg:postcode":"9495",
    "wof:name":"Mcdonald's Restaurant",
    "wof:placetype":"venue"
},
  "geometry": {"coordinates":[9.5235214233,47.1194572449],"type":"Point"}
}