{
  "type": "Feature",
  "properties": {
    "iso:country":"CH",
    "sg:address":"Arsenalstr. 24",
    "sg:city":"Kriens",
    "sg:classifiers":[
        {
            "category":"Manufacturing",
            "subcategory":"Printing",
            "type":"Manufacturing & Wholesale Goods"
        }
    ],
    "sg:phone":"+41 41 318 34 34",
    "sg:postcode":"6010",
    "sg:province":"Luzern",
    "sg:tags":[
        "publishing"
    ],
    "wof:name":"Brunner Ag",
    "wof:placetype":"venue"
},
  "geometry": {"coordinates":[8.2946176529,47.031993866],"type":"Point"}
}