{
  "type": "Feature",
  "properties": {
    "iso:country":"CH",
    "sg:address":"1904",
    "sg:city":"Vernayaz",
    "sg:orig_category":"Zimmerei, Dachdeckerei, Bauspenglerei U Abdichtung",
    "sg:phone":"+41 27 764 12 17",
    "sg:postcode":"1904",
    "sg:province":"Valais",
    "wof:name":"Sch\u00fcrch Andr\u00e9.",
    "wof:placetype":"venue"
},
  "geometry": {"coordinates":[7.0386400223,46.1323814392],"type":"Point"}
}