{
  "type": "Feature",
  "properties": {
    "iso:country":"CH",
    "sg:address":"Mattenweg 9 3098 K\u00f6niz. Postfach",
    "sg:city":"Wabern",
    "sg:classifiers":[
        {
            "category":"Communications",
            "subcategory":"Radio Station",
            "type":"Services"
        }
    ],
    "sg:postcode":"3084",
    "sg:province":"Bern",
    "sg:tags":[
        "fernsehanstalten",
        "u"
    ],
    "wof:name":"Rokkkom Abegglen Th.",
    "wof:placetype":"venue"
},
  "geometry": {"coordinates":[7.4582328796,46.9265060425],"type":"Point"}
}