{
  "type": "Feature",
  "properties": {
    "iso:country":"CH",
    "sg:address":"Bahnhofstrasse 78 5000 Aarau. Postfach",
    "sg:city":"Aarau",
    "sg:orig_category":"Wirtschaftspr\u00fcfung, Steuerberatung U Treuhand",
    "sg:phone":"+41 32 953 18 55",
    "sg:postcode":"5001",
    "sg:province":"Aargau",
    "wof:name":"Jean Gyger Bureau Fiduciaire",
    "wof:placetype":"venue"
},
  "geometry": {"coordinates":[6.9603819847,47.224319458],"type":"Point"}
}