{
  "type": "Feature",
  "properties": {
    "iso:country":"CH",
    "sg:address":"8092",
    "sg:city":"Z\u00fcrich",
    "sg:classifiers":[
        {
            "category":"Education",
            "subcategory":"Library",
            "type":"Public Place"
        }
    ],
    "sg:phone":"+41 13774411",
    "sg:postcode":"8092",
    "sg:province":"Z\u00fcrich",
    "sg:tags":[
        "u",
        "bibliotheken",
        "archive"
    ],
    "wof:name":"Bibliothek Des Institutes F\u00fcr Wirtschaftsforschung Ethz",
    "wof:placetype":"venue"
},
  "geometry": {"coordinates":[8.53801,47.369091],"type":"Point"}
}