{
  "type": "Feature",
  "properties": {
    "iso:country":"CH",
    "sg:address":"Industrie Nord 27",
    "sg:city":"Merenschwand",
    "sg:orig_category":"Master Batches For Pe Films",
    "sg:phone":"+41 56 664 22 22",
    "sg:postcode":"5634",
    "sg:province":"Aargau",
    "wof:name":"Granula Ag",
    "wof:placetype":"venue"
},
  "geometry": {"coordinates":[8.3852453232,47.2613945007],"type":"Point"}
}