{
  "type": "Feature",
  "properties": {
    "addr:full":"B\u00f6lli 17 Lenzburg Aargau 5600",
    "addr:housenumber":"17",
    "addr:postcode":"5600",
    "addr:street":"Boelli",
    "iso:country":"CH",
    "sg:address":"B\u00f6lli 17",
    "sg:city":"Lenzburg",
    "sg:orig_category":"Architektur U Ingenieurb\u00fcros Datenverarbeitungsdienste",
    "sg:phone":"+41 41 988 28 03",
    "sg:postcode":"5600",
    "sg:province":"Aargau",
    "wof:name":"Tis Ag",
    "wof:placetype":"venue"
},
  "geometry": {"coordinates":[7.919718,47.136787],"type":"Point"}
}