{
  "type": "Feature",
  "properties": {
    "iso:country":"CH",
    "sg:address":"B\u00e4chaustrasse 32",
    "sg:city":"B\u00e4ch",
    "sg:orig_category":"Disposal Of Photochemicals",
    "sg:phone":"+41 52 670 00 80",
    "sg:postcode":"8806",
    "sg:province":"Schwyz",
    "wof:name":"Drent Ag",
    "wof:placetype":"venue"
},
  "geometry": {"coordinates":[8.6175794601,47.6805152893],"type":"Point"}
}