{
  "type": "Feature",
  "properties": {
    "iso:country":"CH",
    "sg:address":"1261",
    "sg:city":"St-george",
    "sg:orig_category":"Primarschulen",
    "sg:postcode":"1261",
    "sg:province":"Vaud",
    "wof:name":"Ecole Primaire",
    "wof:placetype":"venue"
},
  "geometry": {"coordinates":[6.2603201866,46.5135612488],"type":"Point"}
}