{
  "type": "Feature",
  "properties": {
    "iso:country":"CH",
    "sg:address":"Eierbrechtstrasse 63",
    "sg:city":"Z\u00fcrich",
    "sg:orig_category":"Grosshandel mit Eisenwaren sowie Installationsbedarf f\u00fcr Gas, Wasser U Heizung Grosshandel mit Erzen",
    "sg:phone":"+41 13814337",
    "sg:postcode":"8053",
    "sg:province":"Z\u00fcrich",
    "wof:name":"Ferofin Ag",
    "wof:placetype":"venue"
},
  "geometry": {"coordinates":[8.5796108246,47.357208252],"type":"Point"}
}