{
  "type": "Feature",
  "properties": {
    "iso:country":"CH",
    "sg:address":"Via Livio 1 6830 Chiasso. Postfach",
    "sg:city":"Chiasso",
    "sg:orig_category":"Wirtschaftspr\u00fcfung, Steuerberatung U Treuhand",
    "sg:postcode":"6830",
    "sg:province":"Ticino",
    "wof:name":"Veco Trust Sa, Succursale Di Chiasso",
    "wof:placetype":"venue"
},
  "geometry": {"coordinates":[9.029876709,45.8333625793],"type":"Point"}
}