{
  "type": "Feature",
  "properties": {
    "iso:country":"CH",
    "sg:address":"Steigerhubelstrasse 94",
    "sg:city":"Bern",
    "sg:orig_category":"Sonstiger Grosshandel",
    "sg:phone":"+41 21 635 21 63",
    "sg:postcode":"3008",
    "sg:province":"Bern",
    "wof:name":"Idis S\u00e0rl",
    "wof:placetype":"venue"
},
  "geometry": {"coordinates":[6.579390049,46.5390815735],"type":"Point"}
}