{
  "type": "Feature",
  "properties": {
    "iso:country":"CH",
    "sg:address":"Via Stefano Franscini 24. 6850 Mendrisio. Postfach",
    "sg:city":"Mendrisio",
    "sg:orig_category":"Sonstiger Grosshandel",
    "sg:postcode":"6850",
    "sg:province":"Ticino",
    "wof:name":"Rezzonico Marco.",
    "wof:placetype":"venue"
},
  "geometry": {"coordinates":[8.9813499451,45.8707389832],"type":"Point"}
}