{
  "type": "Feature",
  "properties": {
    "iso:country":"CH",
    "sg:address":"R\u00fcnenbergerstrasse 31 4460 Gelterkinden. Postfach",
    "sg:city":"Gelterkinden",
    "sg:orig_category":"Instandhaltung U Reparatur von Automobilen",
    "sg:postcode":"4460",
    "sg:province":"Basel-Landschaft",
    "wof:name":"Garage H\u00e4ner Ren\u00e9",
    "wof:placetype":"venue"
},
  "geometry": {"coordinates":[7.8607149124,47.4602050781],"type":"Point"}
}