{
  "type": "Feature",
  "properties": {
    "iso:country":"CH",
    "sg:address":"Gempenstrasse 68",
    "sg:city":"Pratteln",
    "sg:orig_category":"Vereine Musik/Blasmusik",
    "sg:phone":"+41 61 821 71 73",
    "sg:postcode":"4133",
    "sg:province":"Basel-Landschaft",
    "wof:name":"Musikgesellschaft Pratteln",
    "wof:placetype":"venue"
},
  "geometry": {"coordinates":[7.6858658791,47.5155448914],"type":"Point"}
}