{
  "type": "Feature",
  "properties": {
    "iso:country":"CH",
    "sg:address":"Vollikerstrasse 11 8133 Esslingen. Postfach",
    "sg:city":"Esslingen",
    "sg:orig_category":"Unternehmensberatung",
    "sg:postcode":"8133",
    "sg:province":"Z\u00fcrich",
    "wof:name":"Novena Treuhand & Beratung Gmbh",
    "wof:placetype":"venue"
},
  "geometry": {"coordinates":[8.7110824585,47.2861976624],"type":"Point"}
}