{
  "type": "Feature",
  "properties": {
    "iso:country":"CH",
    "sg:address":"Bahnhofstrasse",
    "sg:city":"W\u00e4denswil",
    "sg:orig_category":"Pensionskassen",
    "sg:postcode":"8820",
    "sg:province":"Z\u00fcrich",
    "wof:name":"Bvg-stiftung Der Obst Und Weinbaugenossenschaft Vom Z\u00fcrichsee",
    "wof:placetype":"venue"
},
  "geometry": {"coordinates":[8.6745796204,47.2293167114],"type":"Point"}
}