{
  "type": "Feature",
  "properties": {
    "iso:country":"CH",
    "sg:address":"Hauptstrasse 9",
    "sg:city":"M\u00f6hlin",
    "sg:orig_category":"Detailhandel mit Waren verschiedener Art, Hauptrichtung Nahrungsmittel",
    "sg:phone":"+41 61 751 15 15",
    "sg:postcode":"4313",
    "sg:province":"Aargau",
    "wof:name":"Coop Center",
    "wof:placetype":"venue"
},
  "geometry": {"coordinates":[7.5968370438,47.4693641663],"type":"Point"}
}