{
  "type": "Feature",
  "properties": {
    "iso:country":"CH",
    "sg:address":"Route De Berne 8",
    "sg:city":"Fribourg",
    "sg:orig_category":"Herstellung von Bereifungen",
    "sg:phone":"+41 26 481 38 44",
    "sg:postcode":"1700",
    "sg:province":"Fribourg",
    "wof:name":"Siffert Peter",
    "wof:placetype":"venue"
},
  "geometry": {"coordinates":[7.1664280891,46.8098526001],"type":"Point"}
}