{
  "type": "Feature",
  "properties": {
    "iso:country":"CH",
    "sg:address":"Gerbergasse 24 4001 Basel. Postfach",
    "sg:city":"Basel",
    "sg:orig_category":"Sonstiger Fachdetailhandel in Verkaufsr\u00e4umen",
    "sg:postcode":"4001",
    "sg:province":"Basel-Stadt",
    "wof:name":"Philaclassica Ag Briefmarken Usw; Handel",
    "wof:placetype":"venue"
},
  "geometry": {"coordinates":[7.5882081985,47.5569114685],"type":"Point"}
}