{
  "type": "Feature",
  "properties": {
    "iso:country":"CH",
    "sg:address":"Dorfstrasse 31",
    "sg:city":"H\u00e4ggenschwil",
    "sg:orig_category":"Hobel U Holzimpr\u00e4gnierwerke Mechanik",
    "sg:phone":"+41 71 298 53 44",
    "sg:postcode":"9312",
    "sg:province":"St. Gallen",
    "wof:name":"Kopa Cnc-dreherei K.petros",
    "wof:placetype":"venue"
},
  "geometry": {"coordinates":[9.3470001221,47.4943313599],"type":"Point"}
}