{
  "type": "Feature",
  "properties": {
    "iso:country":"CH",
    "sg:address":"Grand-rue 43",
    "sg:city":"Vallorbe",
    "sg:orig_category":"Detailhandel mit Waren verschiedener Art, Hauptrichtung Nahrungsmittel",
    "sg:phone":"+41 21 843 28 06",
    "sg:postcode":"1337",
    "sg:province":"Vaud",
    "wof:name":"Denner Top Superdiscount",
    "wof:placetype":"venue"
},
  "geometry": {"coordinates":[6.3761129379,46.7116775513],"type":"Point"}
}