{
  "type": "Feature",
  "properties": {
    "iso:country":"CH",
    "sg:address":"Obere Gasse 10",
    "sg:city":"Arlesheim",
    "sg:orig_category":"Pensionskassen",
    "sg:phone":"+41 61 701 20 75",
    "sg:postcode":"4144",
    "sg:province":"Basel-Landschaft",
    "wof:name":"Stiftung Sonnenhof Hilfsverein",
    "wof:placetype":"venue"
},
  "geometry": {"coordinates":[7.6221461296,47.4921188354],"type":"Point"}
}