{
  "type": "Feature",
  "properties": {
    "iso:country":"CH",
    "sg:address":"Br\u00fcckmatt",
    "sg:city":"Entlebuch",
    "sg:orig_category":"Zimmerei, Dachdeckerei, Bauspenglerei U Abdichtung",
    "sg:phone":"+41 41 480 13 33",
    "sg:postcode":"6162",
    "sg:province":"Luzern",
    "wof:name":"K\u00fcng Walter Holzbau",
    "wof:placetype":"venue"
},
  "geometry": {"coordinates":[8.0649986267,46.9928016663],"type":"Point"}
}