{
  "type": "Feature",
  "properties": {
    "iso:country":"CH",
    "sg:address":"Grabenstrasse 8",
    "sg:city":"Zug",
    "sg:orig_category":"Architektur U Ingenieurb\u00fcros",
    "sg:postcode":"6300",
    "sg:province":"Zug",
    "wof:name":"Ppfm Project Planning & Finance Management Ag",
    "wof:placetype":"venue"
},
  "geometry": {"coordinates":[8.514805,47.166367],"type":"Point"}
}