{
  "type": "Feature",
  "properties": {
    "iso:country":"CH",
    "sg:address":"San Burtulumee 4",
    "sg:city":"Camorino",
    "sg:orig_category":"Gartenbau",
    "sg:phone":"+41 79 686 26 75",
    "sg:postcode":"6528",
    "sg:province":"Ticino",
    "wof:name":"Riccardo Nonnella Giardini",
    "wof:placetype":"venue"
},
  "geometry": {"coordinates":[9.0118970871,46.1684417725],"type":"Point"}
}