{
  "type": "Feature",
  "properties": {
    "iso:country":"CH",
    "sg:address":"Talstrasse 4",
    "sg:city":"Ennetmoos",
    "sg:orig_category":"Architekturb\u00fcros",
    "sg:phone":"+41 31 301 21 80",
    "sg:postcode":"6372",
    "sg:province":"Nidwalden",
    "wof:name":"Belvedere B\u00f6lsterli Peter Planungs, Architektur, Gestaltungsauftr\u00e4ge; Bearbeitung",
    "wof:placetype":"venue"
},
  "geometry": {"coordinates":[7.42489,46.974785],"type":"Point"}
}