{
  "type": "Feature",
  "properties": {
    "iso:country":"CH",
    "sg:address":"Rue Des M\u00fbriers 3",
    "sg:city":"Del\u00e9mont",
    "sg:orig_category":"Sanit\u00e4r, Heizungs U L\u00fcftungsinstallation Sanit\u00e4rinstallation",
    "sg:postcode":"2800",
    "sg:province":"Jura",
    "wof:name":"Broquet Jean-pierre Sa",
    "wof:placetype":"venue"
},
  "geometry": {"coordinates":[7.3472790718,47.369052887],"type":"Point"}
}