{
  "type": "Feature",
  "properties": {
    "addr:full":"Pintelgasse 19e Wimmis Bern 3752",
    "addr:housenumber":"19e",
    "addr:postcode":"3752",
    "addr:street":"Pintelgasse;Bern",
    "iso:country":"CH",
    "sg:address":"Pintelgasse 19e",
    "sg:city":"Wimmis",
    "sg:orig_category":"Architektur U Ingenieurb\u00fcros",
    "sg:postcode":"3752",
    "sg:province":"Bern",
    "wof:name":"Reman Konstruktions Und Handels Gmbh",
    "wof:placetype":"venue"
},
  "geometry": {"coordinates":[7.642112,46.676128],"type":"Point"}
}