{
  "type": "Feature",
  "properties": {
    "iso:country":"CH",
    "sg:address":"Alte Landstrasse 46",
    "sg:city":"M\u00e4nnedorf",
    "sg:orig_category":"Werbegrafikateliers",
    "sg:phone":"+41 19205164",
    "sg:postcode":"8708",
    "sg:province":"Z\u00fcrich",
    "wof:name":"Roland Z\u00f6bel Grafik-service",
    "wof:placetype":"venue"
},
  "geometry": {"coordinates":[8.6819887161,47.2585449219],"type":"Point"}
}