{
  "type": "Feature",
  "properties": {
    "iso:country":"CH",
    "sg:address":"B\u00e4lliz 40",
    "sg:city":"Thun",
    "sg:classifiers":[
        {
            "category":"Professional",
            "subcategory":"Employment Agencies",
            "type":"Services"
        }
    ],
    "sg:phone":"+41 33 225 11 44",
    "sg:postcode":"3600",
    "sg:province":"Bern",
    "sg:tags":[
        "personal",
        "u",
        "stellenvermittlung"
    ],
    "wof:name":"Adecco Human Resources Ag",
    "wof:placetype":"venue"
},
  "geometry": {"coordinates":[7.6270318031,46.7587013245],"type":"Point"}
}