{
  "type": "Feature",
  "properties": {
    "iso:country":"CH",
    "sg:address":"Via Norello 6928 Manno. Postfach",
    "sg:city":"Manno",
    "sg:orig_category":"Maler U Glasergewerbe",
    "sg:postcode":"6928",
    "sg:province":"Ticino",
    "wof:name":"Cartopittura Di Ierace Pasquale Dipl.fed",
    "wof:placetype":"venue"
},
  "geometry": {"coordinates":[8.9203052521,46.035369873],"type":"Point"}
}