{
  "type": "Feature",
  "properties": {
    "iso:country":"CH",
    "sg:address":"Via Baraggie 35",
    "sg:city":"Ascona",
    "sg:orig_category":"Gartenbau Landschaftsplanungsb\u00fcros U Gartenarchitekturb\u00fcros",
    "sg:phone":"+41 21 732 12 00",
    "sg:postcode":"6612",
    "sg:province":"Ticino",
    "wof:name":"Jacky Kurzen Paysagiste",
    "wof:placetype":"venue"
},
  "geometry": {"coordinates":[6.6774148941,46.5133132935],"type":"Point"}
}