{
  "type": "Feature",
  "properties": {
    "iso:country":"CH",
    "sg:address":"Industriestrasse Tych 4665 Oftringen. Postfach",
    "sg:city":"Oftringen",
    "sg:orig_category":"Herstellung von Papier, Karton U Pappe",
    "sg:phone":"+41 62 788 22 22",
    "sg:postcode":"4665",
    "sg:province":"Aargau",
    "wof:name":"Sca Packaging Switzerland Ag",
    "wof:placetype":"venue"
},
  "geometry": {"coordinates":[7.9209251404,47.3165397644],"type":"Point"}
}