{
  "type": "Feature",
  "properties": {
    "iso:country":"CH",
    "sg:address":"Egelgasse 67",
    "sg:city":"Bern",
    "sg:orig_category":"Sonstiger Fachdetailhandel mit Nahrungsmitteln, Getr\u00e4nken U Tabak in Verkaufsr\u00e4umen",
    "sg:phone":"+41 32 935 13 83",
    "sg:postcode":"3006",
    "sg:province":"Bern",
    "wof:name":"Christiane B\u00e4hler Epicerie",
    "wof:placetype":"venue"
},
  "geometry": {"coordinates":[6.6071381569,46.9804916382],"type":"Point"}
}