{
  "type": "Feature",
  "properties": {
    "iso:country":"CH",
    "sg:address":"Winterthurstrasse",
    "sg:city":"Neftenbach",
    "sg:classifiers":[
        {
            "category":"Building & Trades",
            "subcategory":"Construction",
            "type":"Services"
        }
    ],
    "sg:phone":"+41 52 315 14 82",
    "sg:postcode":"8413",
    "sg:province":"Z\u00fcrich",
    "sg:tags":[
        "balcony",
        "add-on"
    ],
    "wof:name":"Sprenger S\u00f6hne Ag",
    "wof:placetype":"venue"
},
  "geometry": {"coordinates":[8.669262,47.5233],"type":"Point"}
}