{
  "type": "Feature",
  "properties": {
    "iso:country":"CH",
    "sg:address":"Via Carducci 4 6900 Lugano. Postfach Caselle Postale 2331",
    "sg:city":"Lugano",
    "sg:orig_category":"Detailhandel mit Radio U Fernsehger\u00e4ten Detailhandel mit elektrischen Haushalts-,Radio U Fernsehger\u00e4",
    "sg:phone":"+41 91 923 32 87",
    "sg:postcode":"6901",
    "sg:province":"Ticino",
    "wof:name":"Tv Musica Di Heidi Cresto-weibel",
    "wof:placetype":"venue"
},
  "geometry": {"coordinates":[8.9533252716,46.0047531128],"type":"Point"}
}