{
  "type": "Feature",
  "properties": {
    "iso:country":"CH",
    "sg:address":"Hohrainstrasse 6 5036 Oberentfelden. Postfach",
    "sg:city":"Oberentfelden",
    "sg:orig_category":"Sonstiger Grosshandel",
    "sg:postcode":"5036",
    "sg:province":"Aargau",
    "wof:name":"H & S Handels Gmbh Waren; Im, Export, Handel",
    "wof:placetype":"venue"
},
  "geometry": {"coordinates":[8.0528030396,47.3558235168],"type":"Point"}
}