{
  "type": "Feature",
  "properties": {
    "iso:country":"CH",
    "sg:address":"Les Maisons-rouges",
    "sg:city":"Burtigny",
    "sg:orig_category":"Gartenbau Landschaftsplanungsb\u00fcros U Gartenarchitekturb\u00fcros",
    "sg:phone":"+41 26 673 19 73",
    "sg:postcode":"1261",
    "sg:province":"Vaud",
    "wof:name":"Jean Johner Jardinier-paysagiste",
    "wof:placetype":"venue"
},
  "geometry": {"coordinates":[7.0605969429,46.9436416626],"type":"Point"}
}