{
  "type": "Feature",
  "properties": {
    "iso:country":"CH",
    "sg:address":"St\u00f6ckeln 7",
    "sg:city":"Meierskappel",
    "sg:orig_category":"Kauf U Verkauf von Immobilien auf eigene Rechnung",
    "sg:postcode":"6344",
    "sg:province":"Luzern",
    "wof:name":"Stiwa Invest Walter Stierli & Co.",
    "wof:placetype":"venue"
},
  "geometry": {"coordinates":[8.3114833832,46.9857254028],"type":"Point"}
}