{
  "type": "Feature",
  "properties": {
    "iso:country":"CH",
    "sg:address":"Bahnhofstrasse 88",
    "sg:city":"Burgdorf",
    "sg:orig_category":"Detailhandel mit B\u00fcchern Detailhandel mit Ton U Bildtr\u00e4gern",
    "sg:phone":"+41 34 422 33 28",
    "sg:postcode":"3400",
    "sg:province":"Bern",
    "wof:name":"Ex Libris Ag",
    "wof:placetype":"venue"
},
  "geometry": {"coordinates":[7.621506,47.060101],"type":"Point"}
}