{
  "type": "Feature",
  "properties": {
    "iso:country":"CH",
    "sg:address":"Gut Hochstrass.",
    "sg:city":"T\u00e4gerwilen",
    "sg:orig_category":"Vermietung U Verpachtung von eigenen Immobilien",
    "sg:postcode":"8274",
    "sg:province":"Thurgau",
    "wof:name":"Gut Hochstrass Immobilien Ag",
    "wof:placetype":"venue"
},
  "geometry": {"coordinates":[9.1572647095,47.6499290466],"type":"Point"}
}