{
  "type": "Feature",
  "properties": {
    "iso:country":"CH",
    "sg:address":"Bahnhofstrasse 21 7000 Chur. Postfach 425",
    "sg:city":"Chur",
    "sg:orig_category":"Verm\u00f6gensverwaltung",
    "sg:phone":"+41 81 250 70 45",
    "sg:postcode":"7002",
    "sg:province":"Graubunden",
    "wof:name":"Innovative Independent Trust Ag",
    "wof:placetype":"venue"
},
  "geometry": {"coordinates":[9.5308704376,46.8524589539],"type":"Point"}
}