{
  "type": "Feature",
  "properties": {
    "iso:country":"CH",
    "sg:address":"Haldenweg 10",
    "sg:city":"W\u00fcrenlingen",
    "sg:orig_category":"Sportvereine Turnen Vereine Damen",
    "sg:phone":"+41 56 281 22 38",
    "sg:postcode":"5303",
    "sg:province":"Aargau",
    "wof:name":"Damenriege Etv Untersiggenthal",
    "wof:placetype":"venue"
},
  "geometry": {"coordinates":[8.254940033,47.5292625427],"type":"Point"}
}