{
  "type": "Feature",
  "properties": {
    "iso:country":"CH",
    "sg:address":"Chemin De L'arzillier 1 1040 Echallens. Postfach",
    "sg:city":"Echallens",
    "sg:orig_category":"Grosshandel mit sonstigen Maschinen U Ausr\u00fcstungen f\u00fcr Industrie, Handel U Schiffahrt Herstellung vo",
    "sg:phone":"+41 21 886 22 50",
    "sg:postcode":"1040",
    "sg:province":"Vaud",
    "wof:name":"Matec Soudure S\u00e0rl Technique De Soudure",
    "wof:placetype":"venue"
},
  "geometry": {"coordinates":[6.6370739937,46.646320343],"type":"Point"}
}