{
  "type": "Feature",
  "properties": {
    "iso:country":"CH",
    "sg:address":"Im Holderacker 14",
    "sg:city":"Felben",
    "sg:classifiers":[
        {
            "category":"Professional",
            "subcategory":"Employment Agencies",
            "type":"Services"
        }
    ],
    "sg:phone":"+41 71 677 40 80",
    "sg:postcode":"8552",
    "sg:province":"Thurgau",
    "sg:tags":[
        "personal",
        "u",
        "stellenvermittlung"
    ],
    "wof:name":"Litscher & Co. Ag",
    "wof:placetype":"venue"
},
  "geometry": {"coordinates":[8.9351978302,47.5767478943],"type":"Point"}
}