{
  "type": "Feature",
  "properties": {
    "iso:country":"CH",
    "sg:address":"La Courtaz",
    "sg:city":"Salins",
    "sg:orig_category":"Sanit\u00e4r U Heizungsinstallation Sanit\u00e4rinstallation",
    "sg:phone":"+41 27 207 33 67",
    "sg:postcode":"1991",
    "sg:province":"Valais",
    "wof:name":"Georges Lagger Inst.sanitaires & Chauffages",
    "wof:placetype":"venue"
},
  "geometry": {"coordinates":[7.3570380211,46.2146606445],"type":"Point"}
}