{
  "type": "Feature",
  "properties": {
    "iso:country":"CH",
    "sg:address":"Balierestrasse 29 8500 Frauenfeld. Postfach 467",
    "sg:city":"Frauenfeld",
    "sg:orig_category":"Ledererzeugung",
    "sg:phone":"+41 52 720 43 20",
    "sg:postcode":"8500",
    "sg:province":"Thurgau",
    "wof:name":"Gerberei Kappeler Ag",
    "wof:placetype":"venue"
},
  "geometry": {"coordinates":[8.894452095,47.5550003052],"type":"Point"}
}