{
  "type": "Feature",
  "properties": {
    "iso:country":"CH",
    "sg:address":"Bohl 14 6424 Lauerz. Postfach",
    "sg:city":"Lauerz",
    "sg:orig_category":"Non-Classified Establishments",
    "sg:postcode":"6424",
    "sg:province":"Schwyz",
    "wof:name":"Gotthard Ag Beteiligungen Usw",
    "wof:placetype":"venue"
},
  "geometry": {"coordinates":[8.5843391418,47.0314369202],"type":"Point"}
}