{
  "type": "Feature",
  "properties": {
    "iso:country":"CH",
    "sg:address":"Route De Saint-julien 129 1228 Plan-les-ouates. Postfach",
    "sg:city":"Plan-les-ouates",
    "sg:orig_category":"Elektrizit\u00e4tsversorgung Planer f\u00fcr Alternativenergie and Solararchitektur",
    "sg:phone":"+41 22 884 14 84",
    "sg:postcode":"1228",
    "sg:province":"Gen\u00e8ve",
    "wof:name":"Ses Societe D'energie Solaire Sa Produits Li\u00e9s \u00e0 L'utilisation De L' \u00e9nergie Solaire; D\u00e9veloppement, Production, Diffusion Etc",
    "wof:placetype":"venue"
},
  "geometry": {"coordinates":[6.1191310883,46.1688728333],"type":"Point"}
}