{
  "type": "Feature",
  "properties": {
    "iso:country":"CH",
    "sg:address":"Zythusmatt 23 6330 Cham. Postfach",
    "sg:city":"Cham",
    "sg:orig_category":"Softwareentwicklung U beratung",
    "sg:phone":"+41 41 781 36 10",
    "sg:postcode":"6330",
    "sg:province":"Zug",
    "wof:name":"Amsaro Electronics Gmbh",
    "wof:placetype":"venue"
},
  "geometry": {"coordinates":[8.447514534,47.1753349304],"type":"Point"}
}