{
  "type": "Feature",
  "properties": {
    "iso:country":"CH",
    "sg:address":"Fromatt",
    "sg:city":"Sch\u00fcpfheim",
    "sg:orig_category":"Sanit\u00e4r U Heizungsinstallation Sanit\u00e4rinstallation",
    "sg:phone":"+41 41 484 12 48",
    "sg:postcode":"6170",
    "sg:province":"Luzern",
    "wof:name":"Stadelmann Ag Sanit\u00e4r Heizung & K\u00fcchen",
    "wof:placetype":"venue"
},
  "geometry": {"coordinates":[8.0194749832,46.9536094666],"type":"Point"}
}