{
  "type": "Feature",
  "properties": {
    "addr:full":"Steinhofstrasse 44 Luzern Luzern 6005",
    "addr:housenumber":"44",
    "addr:postcode":"6005",
    "addr:street":"Steinhofstrasse",
    "iso:country":"CH",
    "sg:address":"Steinhofstrasse 44",
    "sg:city":"Luzern",
    "sg:orig_category":"Architekturb\u00fcros",
    "sg:phone":"+41 41 318 30 60",
    "sg:postcode":"6005",
    "sg:province":"Luzern",
    "wof:name":"Markus Boyer Dipl.architekt Eth/sia",
    "wof:placetype":"venue"
},
  "geometry": {"coordinates":[8.29767,47.044296],"type":"Point"}
}