{
  "type": "Feature",
  "properties": {
    "iso:country":"CH",
    "sg:address":"Via Alla Fiera 14",
    "sg:city":"Biasca",
    "sg:orig_category":"Bauspenglerei Herstellung von Metallkonstruktionen",
    "sg:phone":"+41 91 873 01 33",
    "sg:postcode":"6710",
    "sg:province":"Ticino",
    "wof:name":"Degiorgi & Fusco Sa Impianti Sanitari",
    "wof:placetype":"venue"
},
  "geometry": {"coordinates":[8.972628,46.362564],"type":"Point"}
}