{
  "type": "Feature",
  "properties": {
    "iso:country":"CH",
    "sg:address":"Oberdorfstr. 251",
    "sg:city":"Weiach",
    "sg:orig_category":"Betrieb von Taxis",
    "sg:postcode":"8187",
    "sg:province":"Z\u00fcrich",
    "wof:name":"Fawaz Saleh, Taxiunternehmen",
    "wof:placetype":"venue"
},
  "geometry": {"coordinates":[8.442662,47.553833],"type":"Point"}
}