{
  "type": "Feature",
  "properties": {
    "iso:country":"CH",
    "sg:address":"Bahnhofstrasse 15",
    "sg:city":"Pratteln",
    "sg:orig_category":"Vereine Fasnacht",
    "sg:phone":"+41 61 821 78 15",
    "sg:postcode":"4133",
    "sg:province":"Basel-Landschaft",
    "wof:name":"Buure-l\u00fcmmel",
    "wof:placetype":"venue"
},
  "geometry": {"coordinates":[7.6919631958,47.5210342407],"type":"Point"}
}