{
  "type": "Feature",
  "properties": {
    "addr:full":"Avenue Petit-chasseur 66 Sion Valais 1950",
    "addr:housenumber":"66",
    "addr:postcode":"1950",
    "addr:street":"Avenue Petit-Chasseur",
    "iso:country":"CH",
    "sg:address":"Avenue Petit-chasseur 66",
    "sg:city":"Sion",
    "sg:orig_category":"Aktivit\u00e4ten der Generalunternehmen im Baugewerbe",
    "sg:phone":"+41 22 796 63 74",
    "sg:postcode":"1950",
    "sg:province":"Valais",
    "wof:name":"Eric Lauper Entreprise G\u00e9n.de Construction",
    "wof:placetype":"venue"
},
  "geometry": {"coordinates":[6.09723,46.202751],"type":"Point"}
}