{
  "type": "Feature",
  "properties": {
    "iso:country":"CH",
    "sg:address":"Hauptstrasse 9",
    "sg:city":"Sch\u00f6nenwerd",
    "sg:orig_category":"Sonstiges Textilgewerbe",
    "sg:phone":"+41 62 849 77 88",
    "sg:postcode":"5012",
    "sg:province":"Solothurn",
    "wof:name":"Texat Ag",
    "wof:placetype":"venue"
},
  "geometry": {"coordinates":[8.0026493073,47.3721618652],"type":"Point"}
}