{
  "type": "Feature",
  "properties": {
    "iso:country":"CH",
    "sg:address":"Hauptstrasse 7078 Lenzerheide/lai. Postfach",
    "sg:city":"Lenzerheide/lai",
    "sg:orig_category":"Herstellung von Elektromotoren, Generatoren U Transformatoren",
    "sg:phone":"+41 79 681 17 80",
    "sg:postcode":"7078",
    "sg:province":"Graubunden",
    "wof:name":"Elektro-raetus Ag",
    "wof:placetype":"venue"
},
  "geometry": {"coordinates":[9.5578527451,46.7245788574],"type":"Point"}
}