{
  "type": "Feature",
  "properties": {
    "iso:country":"CH",
    "sg:address":"Rue Voltaire 7",
    "sg:city":"Lausanne",
    "sg:orig_category":"Grosshandel mit Foto U Kinoger\u00e4ten, feinmechanischen U optischen Erzeugnissen",
    "sg:phone":"+41 21 616 10 20",
    "sg:postcode":"1006",
    "sg:province":"Vaud",
    "wof:name":"Jenni O. Appareils Pour Le Cin\u00e9ma; Comm. Et Repr\u00e9sent.",
    "wof:placetype":"venue"
},
  "geometry": {"coordinates":[6.6265659332,46.5131416321],"type":"Point"}
}