{
  "type": "Feature",
  "properties": {
    "iso:country":"CH",
    "sg:address":"Governo Piazza 4",
    "sg:city":"Bellinzona",
    "sg:orig_category":"Herstellung von sonstigen Nahrungsmitteln",
    "sg:phone":"+41 91261121",
    "sg:postcode":"6500",
    "sg:province":"Ticino",
    "wof:name":"Aromsaline Sa",
    "wof:placetype":"venue"
},
  "geometry": {"coordinates":[9.0210189819,46.1914329529],"type":"Point"}
}