{
  "type": "Feature",
  "properties": {
    "iso:country":"CH",
    "sg:address":"Mellingerstrasse 12",
    "sg:city":"Niederrohrdorf",
    "sg:orig_category":"Herstellung von Konstruktionsteilen, Fertigbauteilen U Ausbauelementen aus Holz Innenausbau",
    "sg:phone":"+41 79 418 13 83",
    "sg:postcode":"5443",
    "sg:province":"Aargau",
    "wof:name":"Irniger Jakob, Schreinerei & Innenausbau Ag",
    "wof:placetype":"venue"
},
  "geometry": {"coordinates":[8.300028801,47.424949646],"type":"Point"}
}