{
  "type": "Feature",
  "properties": {
    "iso:country":"CH",
    "sg:address":"Arisd\u00f6rferstrasse 10",
    "sg:city":"Liestal",
    "sg:orig_category":"Kaminfeger",
    "sg:phone":"+41 61 922 15 24",
    "sg:postcode":"4410",
    "sg:province":"Basel-Landschaft",
    "wof:name":"Armin Ricklin Kreiskaminfegermeister",
    "wof:placetype":"venue"
},
  "geometry": {"coordinates":[7.7400817871,47.4864082336],"type":"Point"}
}