{
  "type": "Feature",
  "properties": {
    "addr:full":"Stauffacherstrasse 60 8004 Z\u00fcrich. Postfach Z\u00fcrich Z\u00fcrich 8026",
    "addr:housenumber":"60",
    "addr:postcode":"8004 zuerich. postfach;8026",
    "addr:street":"Stauffacherstrasse",
    "iso:country":"CH",
    "sg:address":"Stauffacherstrasse 60 8004 Z\u00fcrich. Postfach",
    "sg:city":"Z\u00fcrich",
    "sg:orig_category":"Arbeitnehmerverb\u00e4nde",
    "sg:phone":"+41 31 331 35 20",
    "sg:postcode":"8026",
    "sg:province":"Z\u00fcrich",
    "wof:name":"Hebammenverband",
    "wof:placetype":"venue"
},
  "geometry": {"coordinates":[7.449981,46.960972],"type":"Point"}
}