{
  "type": "Feature",
  "properties": {
    "iso:country":"CH",
    "sg:address":"Bernstrasse 12",
    "sg:city":"Luzern",
    "sg:orig_category":"Werbegrafikateliers",
    "sg:phone":"+41 41 240 45 68",
    "sg:postcode":"6003",
    "sg:province":"Luzern",
    "wof:name":"Illustration Grafik Schnyder",
    "wof:placetype":"venue"
},
  "geometry": {"coordinates":[8.2894620895,47.0543403625],"type":"Point"}
}