{
  "type": "Feature",
  "properties": {
    "iso:country":"CH",
    "sg:address":"Hauptstrasse 115b",
    "sg:city":"H\u00e4usernmoos",
    "sg:orig_category":"Dachdeckerei Zimmerei, Dachdeckerei, Bauspenglerei U Abdichtung",
    "sg:phone":"+41 34 435 13 03",
    "sg:postcode":"3463",
    "sg:province":"Bern",
    "wof:name":"Hadorn Fritz.",
    "wof:placetype":"venue"
},
  "geometry": {"coordinates":[7.749359,47.078815],"type":"Point"}
}