{
  "type": "Feature",
  "properties": {
    "iso:country":"CH",
    "sg:address":"Zeisigweg 2",
    "sg:city":"D\u00fcbendorf",
    "sg:orig_category":"Grosshandel mit pharmazeutischen Erzeugnissen, medizinischen U orthop\u00e4dischen Artikeln",
    "sg:phone":"+41 22 735 71 25",
    "sg:postcode":"8600",
    "sg:province":"Z\u00fcrich",
    "wof:name":"Prodonta",
    "wof:placetype":"venue"
},
  "geometry": {"coordinates":[6.1578598022,46.2034339905],"type":"Point"}
}