{
  "type": "Feature",
  "properties": {
    "iso:country":"CH",
    "sg:address":"Route De Gy 37 1252 Meinier. Postfach",
    "sg:city":"Meinier",
    "sg:orig_category":"Sportvereine Ski",
    "sg:phone":"+41 21 841 15 55",
    "sg:postcode":"1252",
    "sg:province":"Gen\u00e8ve",
    "wof:name":"Ski-club Charbonni\u00e8res",
    "wof:placetype":"venue"
},
  "geometry": {"coordinates":[6.3145170212,46.6668548584],"type":"Point"}
}