{
  "type": "Feature",
  "properties": {
    "iso:country":"CH",
    "sg:address":"Villardiez Chemin De 1",
    "sg:city":"Pully",
    "sg:orig_category":"Finanzierungsinstitutionen",
    "sg:phone":"+41 71 744 78 66",
    "sg:postcode":"1009",
    "sg:province":"Vaud",
    "wof:name":"Bornhauser D., Nice Price",
    "wof:placetype":"venue"
},
  "geometry": {"coordinates":[9.6346435547,47.4514160156],"type":"Point"}
}