{
  "type": "Feature",
  "properties": {
    "iso:country":"CH",
    "sg:address":"Industriestrasse 21",
    "sg:city":"B\u00f6singen",
    "sg:orig_category":"Softwareentwicklung U beratung",
    "sg:phone":"+41 31 747 63 00",
    "sg:postcode":"3178",
    "sg:province":"Fribourg",
    "wof:name":"Viktor Jezler Informatik Gmbh",
    "wof:placetype":"venue"
},
  "geometry": {"coordinates":[7.2316727638,46.90026474],"type":"Point"}
}