{
  "type": "Feature",
  "properties": {
    "iso:country":"CH",
    "sg:address":"Vogesenstrasse 102 4056 Basel. Postfach",
    "sg:city":"Basel",
    "sg:orig_category":"Erzeugung U Erstbearbeitung von Aluminium",
    "sg:phone":"+41 61 321 51 25",
    "sg:postcode":"4051",
    "sg:province":"Basel-Stadt",
    "wof:name":"Alutechnik Lanz Robert Aluminium; Technische Beratung Usw",
    "wof:placetype":"venue"
},
  "geometry": {"coordinates":[7.5760979652,47.5682792664],"type":"Point"}
}