{
  "type": "Feature",
  "properties": {
    "iso:country":"CH",
    "sg:address":"Vigie Rue De La 3 1003 Lausanne. Postfach",
    "sg:city":"Lausanne",
    "sg:orig_category":"Architektur U Ingenieurb\u00fcros",
    "sg:postcode":"1003",
    "sg:province":"Vaud",
    "wof:name":"Technique Papeti\u00e8re F\u00fcrst Hans",
    "wof:placetype":"venue"
},
  "geometry": {"coordinates":[6.92753,47.032436],"type":"Point"}
}