{
  "type": "Feature",
  "properties": {
    "iso:country":"CH",
    "sg:address":"Nidaugasse 49 2500 Biel/bienne. Postfach",
    "sg:city":"Biel/bienne",
    "sg:orig_category":"Interessenvertretungen",
    "sg:postcode":"2502",
    "sg:province":"Bern",
    "wof:name":"Huber Jeanne-stiftung",
    "wof:placetype":"venue"
},
  "geometry": {"coordinates":[7.2469029427,47.1373291016],"type":"Point"}
}