{
  "type": "Feature",
  "properties": {
    "iso:country":"CH",
    "sg:address":"Baarerstrasse 135",
    "sg:city":"Zug",
    "sg:orig_category":"Finanzierungsinstitutionen",
    "sg:postcode":"6300",
    "sg:province":"Zug",
    "wof:name":"Furlong Investment Management Ag",
    "wof:placetype":"venue"
},
  "geometry": {"coordinates":[8.5190448761,47.1812820435],"type":"Point"}
}