{
  "type": "Feature",
  "properties": {
    "iso:country":"CH",
    "sg:address":"Feldmoos 9622 Krinau. Postfach",
    "sg:city":"Krinau",
    "sg:orig_category":"Herstellung von Haus, Bett U Tischw\u00e4sche Weberei",
    "sg:phone":"+41 71 988 14 53",
    "sg:postcode":"9622",
    "sg:province":"St. Gallen",
    "wof:name":"Weberei Graf Ag",
    "wof:placetype":"venue"
},
  "geometry": {"coordinates":[9.0497646332,47.3174209595],"type":"Point"}
}