{
  "type": "Feature",
  "properties": {
    "iso:country":"CH",
    "sg:address":"Gsteigstrasse 20",
    "sg:city":"B\u00f6nigen",
    "sg:orig_category":"Maler U Glasergewerbe Malerei",
    "sg:phone":"+41 33 822 14 25",
    "sg:postcode":"3806",
    "sg:province":"Bern",
    "wof:name":"Malergesch\u00e4ft Schnuuz Peter Siegrist",
    "wof:placetype":"venue"
},
  "geometry": {"coordinates":[7.8896489143,46.6818809509],"type":"Point"}
}