{
  "type": "Feature",
  "properties": {
    "addr:full":"Leuzigenstrasse 7 L\u00fcterkofen-ichert Solothurn 4571",
    "addr:housenumber":"7",
    "addr:postcode":"4571",
    "addr:street":"Leuzigenstrasse;Solothurn",
    "iso:country":"CH",
    "sg:address":"Leuzigenstrasse 7",
    "sg:city":"L\u00fcterkofen-ichert",
    "sg:orig_category":"Architekturb\u00fcros",
    "sg:phone":"+41 32 677 16 58",
    "sg:postcode":"4571",
    "sg:province":"Solothurn",
    "wof:name":"Verena Zimmermann Architekturb\u00fcro",
    "wof:placetype":"venue"
},
  "geometry": {"coordinates":[7.50805,47.163822],"type":"Point"}
}