{
  "type": "Feature",
  "properties": {
    "iso:country":"CH",
    "sg:address":"Rue De L'industrie 9",
    "sg:city":"Del\u00e9mont",
    "sg:orig_category":"Architektur U Ingenieurb\u00fcros",
    "sg:phone":"+41 71 994 22 44",
    "sg:postcode":"2800",
    "sg:province":"Jura",
    "wof:name":"Scherrer Ingenieurb\u00fcro Ag",
    "wof:placetype":"venue"
},
  "geometry": {"coordinates":[9.19936,47.22419],"type":"Point"}
}