{
  "type": "Feature",
  "properties": {
    "iso:country":"CH",
    "sg:address":"Badenerstrasse 281 8003 Z\u00fcrich. Postfach",
    "sg:city":"Z\u00fcrich",
    "sg:orig_category":"Softwareentwicklung U beratung",
    "sg:phone":"+41 14508470",
    "sg:postcode":"8001",
    "sg:province":"Z\u00fcrich",
    "wof:name":"Blue Logic Ag Informatikl\u00f6sungen; Entwicklung. Unternehmen, Welche Solche L\u00f6sungen Verwenden; Beratung, Konzepterstellung Usw",
    "wof:placetype":"venue"
},
  "geometry": {"coordinates":[8.5142936707,47.3762969971],"type":"Point"}
}