{
  "type": "Feature",
  "properties": {
    "iso:country":"CH",
    "sg:address":"B\u00fchlweg",
    "sg:city":"Krattigen",
    "sg:classifiers":[
        {
            "category":"Insurance",
            "subcategory":"Insurance Agent",
            "type":"Services"
        }
    ],
    "sg:phone":"+41 79 409 59 93",
    "sg:postcode":"3704",
    "sg:province":"Bern",
    "sg:tags":[
        "versicherungsagenturen",
        "-broker"
    ],
    "wof:name":"Die Mobiliar Versicherungen & Vorsorge",
    "wof:placetype":"venue"
},
  "geometry": {"coordinates":[8.8576889038,47.6607322693],"type":"Point"}
}