{
  "type": "Feature",
  "properties": {
    "iso:country":"CH",
    "sg:address":"8542",
    "sg:city":"Wiesendangen",
    "sg:orig_category":"Organisationen des Gesundheitswesen",
    "sg:phone":"+41 18214732",
    "sg:postcode":"8542",
    "sg:province":"Z\u00fcrich",
    "wof:name":"Samariterverein",
    "wof:placetype":"venue"
},
  "geometry": {"coordinates":[8.6456403732,47.4106483459],"type":"Point"}
}