{
  "type": "Feature",
  "properties": {
    "iso:country":"CH",
    "sg:address":"Loomattstrasse 14c",
    "sg:city":"Stallikon",
    "sg:orig_category":"Sanit\u00e4r U Heizungsinstallation Sanit\u00e4rinstallation",
    "sg:phone":"+41 17003520",
    "sg:postcode":"8143",
    "sg:province":"Z\u00fcrich",
    "wof:name":"Aqua-plan & Bau Ag Haustechnik",
    "wof:placetype":"venue"
},
  "geometry": {"coordinates":[8.4859867096,47.3393478394],"type":"Point"}
}