{
  "type": "Feature",
  "properties": {
    "iso:country":"CH",
    "sg:address":"Amselweg 6",
    "sg:city":"Solothurn",
    "sg:orig_category":"Vereine Gesang",
    "sg:postcode":"4500",
    "sg:province":"Solothurn",
    "wof:name":"Gemischter Chor Biberist",
    "wof:placetype":"venue"
},
  "geometry": {"coordinates":[7.5433869362,47.2149963379],"type":"Point"}
}