{
  "type": "Feature",
  "properties": {
    "iso:country":"CH",
    "sg:address":"Hagenholzstrasse 93",
    "sg:city":"Kloten",
    "sg:orig_category":"Sportvereine Ballsport Tischtennis",
    "sg:phone":"+41 18030736",
    "sg:postcode":"8302",
    "sg:province":"Z\u00fcrich",
    "wof:name":"Ttc Kloten",
    "wof:placetype":"venue"
},
  "geometry": {"coordinates":[8.5917730331,47.4459953308],"type":"Point"}
}