{
  "type": "Feature",
  "properties": {
    "iso:country":"CH",
    "sg:address":"Chemin Des Grand-buissons 11",
    "sg:city":"Bernex",
    "sg:orig_category":"Fahrschulen, Flugschulen",
    "sg:phone":"+41 22 757 12 10",
    "sg:postcode":"1233",
    "sg:province":"Gen\u00e8ve",
    "wof:name":"Marc Mauris Auto-\u00e9cole",
    "wof:placetype":"venue"
},
  "geometry": {"coordinates":[6.0564789772,46.1632385254],"type":"Point"}
}