{
  "type": "Feature",
  "properties": {
    "iso:country":"CH",
    "sg:address":"Blumenrainstrasse 8",
    "sg:city":"Grenchen",
    "sg:orig_category":"Herstellung von Werkzeugen Mechanik",
    "sg:phone":"+41 32 653 10 44",
    "sg:postcode":"2540",
    "sg:province":"Solothurn",
    "wof:name":"Marti Paul",
    "wof:placetype":"venue"
},
  "geometry": {"coordinates":[7.3890471458,47.193901062],"type":"Point"}
}