{
  "type": "Feature",
  "properties": {
    "iso:country":"CH",
    "sg:address":"Spissenstrasse 4",
    "sg:city":"Kastanienbaum",
    "sg:orig_category":"Unternehmensberatung",
    "sg:phone":"+41 41 340 10 50",
    "sg:postcode":"6047",
    "sg:province":"Luzern",
    "wof:name":"Synthex Ag Unternehmensberatung",
    "wof:placetype":"venue"
},
  "geometry": {"coordinates":[8.33959198,47.0078048706],"type":"Point"}
}