{
  "type": "Feature",
  "properties": {
    "iso:country":"CH",
    "sg:address":"Oltnerstrasse 35",
    "sg:city":"Aarburg",
    "sg:orig_category":"Handel mit Automobilen",
    "sg:postcode":"4663",
    "sg:province":"Aargau",
    "wof:name":"Pl\u00fcss Automobil Ag",
    "wof:placetype":"venue"
},
  "geometry": {"coordinates":[7.8991060257,47.3243255615],"type":"Point"}
}