{
  "type": "Feature",
  "properties": {
    "iso:country":"CH",
    "sg:address":"Wavre",
    "sg:city":"Thielle",
    "sg:orig_category":"Sonstiger Grosshandel",
    "sg:phone":"+41 32 753 25 38",
    "sg:postcode":"2075",
    "sg:province":"Neuch\u00e2tel",
    "wof:name":"Onewa Sa",
    "wof:placetype":"venue"
},
  "geometry": {"coordinates":[7.0219497681,47.0200500488],"type":"Point"}
}