{
  "type": "Feature",
  "properties": {
    "iso:country":"CH",
    "sg:address":"Schlossbergstrasse 22",
    "sg:city":"Zollikon",
    "sg:orig_category":"Grosshandel mit Bekleidung",
    "sg:phone":"+41 71 223 10 89",
    "sg:postcode":"8702",
    "sg:province":"Z\u00fcrich",
    "wof:name":"Stadler Ag M\u00fcnz Uniform & Technik",
    "wof:placetype":"venue"
},
  "geometry": {"coordinates":[9.3837471008,47.4449958801],"type":"Point"}
}