{
  "type": "Feature",
  "properties": {
    "iso:country":"CH",
    "sg:address":"M\u00fchlematthof 9",
    "sg:city":"Boniswil",
    "sg:classifiers":[
        {
            "category":"Professional",
            "subcategory":"Management & Consulting",
            "type":"Services"
        }
    ],
    "sg:phone":"+41 62 777 38 30",
    "sg:postcode":"5706",
    "sg:province":"Aargau",
    "sg:tags":[
        "seminar"
    ],
    "wof:name":"A-z Management-dienste F\u00fcr Unterricht Und Weiterbildung Ag",
    "wof:placetype":"venue"
},
  "geometry": {"coordinates":[8.185385704,47.317363739],"type":"Point"}
}