{
  "type": "Feature",
  "properties": {
    "iso:country":"CH",
    "sg:address":"Bahnhofplatz 11",
    "sg:city":"Herisau",
    "sg:orig_category":"Zahnarztpraxen",
    "sg:phone":"+41 71 350 11 33",
    "sg:postcode":"9100",
    "sg:province":"Appenzell Ausserrhoden",
    "wof:name":"Dres Med.dent M. & E. Zeller Zahn\u00e4rzte",
    "wof:placetype":"venue"
},
  "geometry": {"coordinates":[9.279047966,47.3908119202],"type":"Point"}
}