{
  "type": "Feature",
  "properties": {
    "iso:country":"CH",
    "sg:address":"B\u00fcrenstrasse 9",
    "sg:city":"Dotzigen",
    "sg:orig_category":"Herstellung von Werkzeugen",
    "sg:postcode":"3293",
    "sg:province":"Bern",
    "wof:name":"Beuret Sa",
    "wof:placetype":"venue"
},
  "geometry": {"coordinates":[7.4550700188,47.285369873],"type":"Point"}
}