{
  "type": "Feature",
  "properties": {
    "iso:country":"CH",
    "sg:address":"4143",
    "sg:city":"Dornach",
    "sg:orig_category":"Sportvereine Ballsport Tennis",
    "sg:phone":"+41 61 701 23 42",
    "sg:postcode":"4143",
    "sg:province":"Solothurn",
    "wof:name":"Tennisklub Metallwerke C/o Swissmetal",
    "wof:placetype":"venue"
},
  "geometry": {"coordinates":[7.6169772148,47.4787712097],"type":"Point"}
}