{
  "type": "Feature",
  "properties": {
    "iso:country":"CH",
    "sg:address":"Dorfstr. 26.",
    "sg:city":"Laupersdorf",
    "sg:orig_category":"RESTAURANTS: TEA-ROOMS",
    "sg:phone":"+41 62 391 59 29",
    "sg:postcode":"4712",
    "sg:province":"Solothurn",
    "wof:name":"Koch-bl\u00e4si Robert",
    "wof:placetype":"venue"
},
  "geometry": {"coordinates":[7.6545248032,47.3120040894],"type":"Point"}
}