{
  "type": "Feature",
  "properties": {
    "iso:country":"CH",
    "sg:address":"Untere Br\u00fchlstrasse 21",
    "sg:city":"Zofingen",
    "sg:orig_category":"Kauf U Verkauf von Immobilien auf eigene Rechnung Vermittlung von Immobilien",
    "sg:phone":"+41 41 810 00 53",
    "sg:postcode":"4800",
    "sg:province":"Aargau",
    "wof:name":"Alma Grundst\u00fcck Gmbh",
    "wof:placetype":"venue"
},
  "geometry": {"coordinates":[8.6318378448,47.0290374756],"type":"Point"}
}