{
  "type": "Feature",
  "properties": {
    "iso:country":"CH",
    "sg:address":"Bahnhofstrasse 9 6340 Baar. Postfach 315",
    "sg:city":"Baar",
    "sg:orig_category":"Erbringung von Dienstleistungen f\u00fcr Unternehmen Sonstige mit der Informatik verbundene T\u00e4tigkeiten",
    "sg:phone":"+41 41 761 88 20",
    "sg:postcode":"6341",
    "sg:province":"Zug",
    "wof:name":"Dots Sa Services Informatiques Etc",
    "wof:placetype":"venue"
},
  "geometry": {"coordinates":[8.5244979858,47.1954307556],"type":"Point"}
}