{
  "type": "Feature",
  "properties": {
    "iso:country":"CH",
    "sg:address":"Hauptstrasse 26",
    "sg:city":"Ueken",
    "sg:orig_category":"R\u00fcckgewinnung U Vorbereitung f\u00fcr die Wiederverwertung Recycling",
    "sg:phone":"+41 62 871 47 06",
    "sg:postcode":"5028",
    "sg:province":"Aargau",
    "wof:name":"Elku Recycling",
    "wof:placetype":"venue"
},
  "geometry": {"coordinates":[8.0484552383,47.4853363037],"type":"Point"}
}