{
  "type": "Feature",
  "properties": {
    "iso:country":"CH",
    "sg:address":"Rue De La Tour-maitresse 4",
    "sg:city":"Gen\u00e8ve",
    "sg:orig_category":"Detailhandel mit Bekleidung Detailhandel mit Geschenkartikeln U Souvenirs",
    "sg:phone":"+41 22 311 22 92",
    "sg:postcode":"1204",
    "sg:province":"Gen\u00e8ve",
    "wof:name":"Db Domus Bis Sa",
    "wof:placetype":"venue"
},
  "geometry": {"coordinates":[6.151683,46.202858],"type":"Point"}
}