{
  "type": "Feature",
  "properties": {
    "iso:country":"CH",
    "sg:address":"Rothenhausen",
    "sg:city":"Rothenhausen",
    "sg:orig_category":"Vermietung U Verpachtung von eigenen Immobilien",
    "sg:phone":"+41 56 621 97 02",
    "sg:postcode":"9565",
    "sg:province":"Thurgau",
    "wof:name":"Immofort Ag",
    "wof:placetype":"venue"
},
  "geometry": {"coordinates":[8.2746238708,47.330657959],"type":"Point"}
}