{
  "type": "Feature",
  "properties": {
    "addr:full":"Rufibachstrasse 9 6318 Walchwil. Postfach 195 Walchwil Zug 6318",
    "addr:housenumber":"9;195",
    "addr:postcode":"6318 walchwil.;6318",
    "addr:street":"Rufibachstrasse;Postfach;Zug",
    "iso:country":"CH",
    "sg:address":"Rufibachstrasse 9 6318 Walchwil. Postfach 195",
    "sg:city":"Walchwil",
    "sg:orig_category":"Allgemeiner Hoch U Tiefbau Allgemeiner Hochbau",
    "sg:phone":"+41 41 758 12 69",
    "sg:postcode":"6318",
    "sg:province":"Zug",
    "wof:name":"Birrer Bau Ag.",
    "wof:placetype":"venue"
},
  "geometry": {"coordinates":[8.522567,47.090652],"type":"Point"}
}