{
  "type": "Feature",
  "properties": {
    "iso:country":"CH",
    "sg:address":"Kirchgasse 13",
    "sg:city":"Z\u00fcrich",
    "sg:orig_category":"Religi\u00f6se Vereinigungen",
    "sg:phone":"+41 12615311",
    "sg:postcode":"8001",
    "sg:province":"Z\u00fcrich",
    "wof:name":"Helferei Grossm\u00fcnster",
    "wof:placetype":"venue"
},
  "geometry": {"coordinates":[8.5451126099,47.3703842163],"type":"Point"}
}