{
  "type": "Feature",
  "properties": {
    "iso:country":"CH",
    "sg:address":"6163",
    "sg:city":"Ebnet",
    "sg:orig_category":"S\u00e4gewerke",
    "sg:phone":"+41 32 622 37 28",
    "sg:postcode":"6163",
    "sg:province":"Luzern",
    "wof:name":"Martin Adam S\u00e4gerei",
    "wof:placetype":"venue"
},
  "geometry": {"coordinates":[7.4999890327,47.231464386],"type":"Point"}
}