{
  "type": "Feature",
  "properties": {
    "iso:country":"CH",
    "sg:address":"Aarestrasse 32 3600 Thun. Postfach 1244",
    "sg:city":"Thun",
    "sg:orig_category":"Vermittlung von Immobilien Verwaltung von Immobilien",
    "sg:phone":"+41 33 221 42 38",
    "sg:postcode":"3601",
    "sg:province":"Bern",
    "wof:name":"Heinz Lanz Immobilien-treuhand",
    "wof:placetype":"venue"
},
  "geometry": {"coordinates":[7.6274957657,46.7571411133],"type":"Point"}
}