{
  "type": "Feature",
  "properties": {
    "iso:country":"CH",
    "sg:address":"Breton Ruelle 7",
    "sg:city":"Neuch\u00e2tel",
    "sg:orig_category":"Vermietung U Verpachtung von eigenen Immobilien",
    "sg:postcode":"2000",
    "sg:province":"Neuch\u00e2tel",
    "wof:name":"Nesped Sa",
    "wof:placetype":"venue"
},
  "geometry": {"coordinates":[6.9298481941,46.9917144775],"type":"Point"}
}