{
  "type": "Feature",
  "properties": {
    "iso:country":"CH",
    "sg:address":"Tiglio Via Del 6",
    "sg:city":"Giubiasco",
    "sg:orig_category":"Druck ohne Zeitungsdruck",
    "sg:postcode":"6512",
    "sg:province":"Ticino",
    "wof:name":"Rapid-offset Sagl",
    "wof:placetype":"venue"
},
  "geometry": {"coordinates":[9.000243187,46.1707267761],"type":"Point"}
}