{
  "type": "Feature",
  "properties": {
    "iso:country":"CH",
    "sg:address":"Avenue Eugene Lance 38 1212 Grand-lancy Case Postale 584",
    "sg:city":"Grand-lancy",
    "sg:orig_category":"Herstellung von Ger\u00e4ten der Elektrizit\u00e4tserzeugung, -verteilung u.\u00e4. -Herstellung von elektronischen",
    "sg:phone":"+41 17721011",
    "sg:postcode":"1212",
    "sg:province":"Gen\u00e8ve",
    "wof:name":"Cetrix Gmbh",
    "wof:placetype":"venue"
},
  "geometry": {"coordinates":[8.5495529175,47.3242607117],"type":"Point"}
}