{
  "type": "Feature",
  "properties": {
    "iso:country":"CH",
    "sg:address":"Riedweg 1",
    "sg:city":"Bern",
    "sg:orig_category":"Malerei",
    "sg:phone":"+41 31 301 37 33",
    "sg:postcode":"3012",
    "sg:province":"Bern",
    "wof:name":"Otto Hauser Malergesch\u00e4ft",
    "wof:placetype":"venue"
},
  "geometry": {"coordinates":[7.4357042313,46.959487915],"type":"Point"}
}