{
  "type": "Feature",
  "properties": {
    "iso:country":"CH",
    "sg:address":"Bahnweg 12",
    "sg:city":"Duggingen",
    "sg:orig_category":"Mechanische Werkst\u00e4tten",
    "sg:phone":"+41 61 741 13 54",
    "sg:postcode":"4202",
    "sg:province":"Basel-Landschaft",
    "wof:name":"Hans Geiser Mechanische Werkstatt",
    "wof:placetype":"venue"
},
  "geometry": {"coordinates":[7.5996022224,47.4502487183],"type":"Point"}
}