{
  "type": "Feature",
  "properties": {
    "iso:country":"CH",
    "sg:address":"Rue Giovanni-gambini 1",
    "sg:city":"Gen\u00e8ve",
    "sg:orig_category":"Physiotherapie",
    "sg:phone":"+41 22 346 44 13",
    "sg:postcode":"1206",
    "sg:province":"Gen\u00e8ve",
    "wof:name":"Mireille Gorg\u00e9 Physioth\u00e9rapie",
    "wof:placetype":"venue"
},
  "geometry": {"coordinates":[6.1648402214,46.1916618347],"type":"Point"}
}