{
  "type": "Feature",
  "properties": {
    "iso:country":"CH",
    "sg:address":"Hohwartring 28",
    "sg:city":"Glash\u00fctten",
    "sg:orig_category":"Vorschulen, Kinderg\u00e4rten",
    "sg:phone":"+41 62 926 00 24",
    "sg:postcode":"4856",
    "sg:province":"Aargau",
    "wof:name":"Kindergarten Hohwart",
    "wof:placetype":"venue"
},
  "geometry": {"coordinates":[7.8451700211,47.2586479187],"type":"Point"}
}