{
  "type": "Feature",
  "properties": {
    "iso:country":"CH",
    "sg:address":"Lohwisstrasse 24",
    "sg:city":"Ebmatingen",
    "sg:orig_category":"Organisationen des Gesundheitswesen",
    "sg:phone":"+41 19800742",
    "sg:postcode":"8123",
    "sg:province":"Z\u00fcrich",
    "wof:name":"Samariterverein Maur",
    "wof:placetype":"venue"
},
  "geometry": {"coordinates":[8.6435565948,47.3559989929],"type":"Point"}
}