{
  "type": "Feature",
  "properties": {
    "iso:country":"CH",
    "sg:address":"Jolimont Rue 5",
    "sg:city":"Del\u00e9mont",
    "sg:orig_category":"Vermietung U Verpachtung von eigenen Immobilien",
    "sg:postcode":"2800",
    "sg:province":"Jura",
    "wof:name":"Si Le Stand Sa",
    "wof:placetype":"venue"
},
  "geometry": {"coordinates":[7.3390598297,47.3617591858],"type":"Point"}
}