{
  "type": "Feature",
  "properties": {
    "iso:country":"CH",
    "sg:address":"Haferweg 6",
    "sg:city":"Suhr",
    "sg:orig_category":"Eisenbahnverkehr",
    "sg:phone":"+41 62 842 45 48",
    "sg:postcode":"5034",
    "sg:province":"Aargau",
    "wof:name":"Speedrail Ag",
    "wof:placetype":"venue"
},
  "geometry": {"coordinates":[8.0791311264,47.3715744019],"type":"Point"}
}