{
  "type": "Feature",
  "properties": {
    "addr:full":"Wesemlin-terrasse 30 Luzern Luzern 6006",
    "addr:housenumber":"30",
    "addr:postcode":"6006",
    "addr:street":"Wesemlin-Terrasse",
    "iso:country":"CH",
    "sg:address":"Wesemlin-terrasse 30",
    "sg:city":"Luzern",
    "sg:orig_category":"Architektur U Ingenieurb\u00fcros",
    "sg:phone":"+41 62 756 49 87",
    "sg:postcode":"6006",
    "sg:province":"Luzern",
    "wof:name":"Fischer Bernhard Beratender Ingenieur Htl/swki/stv",
    "wof:placetype":"venue"
},
  "geometry": {"coordinates":[8.316708,47.064457],"type":"Point"}
}