{
  "type": "Feature",
  "properties": {
    "iso:country":"CH",
    "sg:address":"Forchstrasse 233 8000 Z\u00fcrich. Postfach 8032 Z\u00fcrich",
    "sg:city":"Zust",
    "sg:orig_category":"Hardwareberatung",
    "sg:postcode":"32",
    "wof:name":"Netrange Ag Netzwerke Im Computer- U. Kommunikationsbereich; Aufbau, Unterhalt. Hard- U. Software; Handel Usw.",
    "wof:placetype":"venue"
},
  "geometry": {"coordinates":[9.3969068527,47.4403114319],"type":"Point"}
}