{
  "type": "Feature",
  "properties": {
    "iso:country":"CH",
    "sg:address":"Vordere Hauptgasse 28",
    "sg:city":"Zofingen",
    "sg:orig_category":"Detailhandel mit Blumen U Pflanzen Fachdetailhandel in Verkaufsr\u00e4umen",
    "sg:phone":"+41 52 672 27 47",
    "sg:postcode":"4800",
    "sg:province":"Aargau",
    "wof:name":"Schmid E. Vorm. Joho Emil",
    "wof:placetype":"venue"
},
  "geometry": {"coordinates":[8.619202,47.681347],"type":"Point"}
}