{
  "type": "Feature",
  "properties": {
    "iso:country":"CH",
    "sg:address":"6037 Root. Postfach",
    "sg:city":"Perlen",
    "sg:orig_category":"Instandhaltung U Reparatur von Automobilen",
    "sg:phone":"+41 24 471 84 09",
    "sg:postcode":"6035",
    "sg:province":"Luzern",
    "wof:name":"Suter Pascal",
    "wof:placetype":"venue"
},
  "geometry": {"coordinates":[6.9625577927,46.2510261536],"type":"Point"}
}