{
  "type": "Feature",
  "properties": {
    "iso:country":"CH",
    "sg:address":"Neptunstrasse 14",
    "sg:city":"Z\u00fcrich",
    "sg:orig_category":"Arztpraxen",
    "sg:phone":"+41 81 302 77 66",
    "sg:postcode":"8032",
    "sg:province":"Z\u00fcrich",
    "wof:name":"Dr.med.susanna Schneider Aerztin F.allgemeine Medizin",
    "wof:placetype":"venue"
},
  "geometry": {"coordinates":[9.49944,47.002171],"type":"Point"}
}