{
  "type": "Feature",
  "properties": {
    "iso:country":"CH",
    "sg:address":"Viktoriastrasse 31",
    "sg:city":"Z\u00fcrich",
    "sg:orig_category":"Sonstige Aktivit\u00e4ten der nicht-\u00e4rztlichen Medizinalberufe",
    "sg:phone":"+41 13116052",
    "sg:postcode":"8057",
    "sg:province":"Z\u00fcrich",
    "wof:name":"Edith Surer Kinesiologie",
    "wof:placetype":"venue"
},
  "geometry": {"coordinates":[8.5504827499,47.4043693542],"type":"Point"}
}