{
  "type": "Feature",
  "properties": {
    "iso:country":"CH",
    "sg:address":"Niederdorfstrasse 43 8001 Z\u00fcrich. Postfach",
    "sg:city":"Z\u00fcrich",
    "sg:orig_category":"Fachdetailhandel in Verkaufsr\u00e4umen Sonstiger Fachdetailhandel in Verkaufsr\u00e4umen",
    "sg:phone":"+41 71 767 70 20",
    "sg:postcode":"8025",
    "wof:name":"Pea-nut Ag",
    "wof:placetype":"venue"
},
  "geometry": {"coordinates":[9.5170345306,47.2772102356],"type":"Point"}
}