{
  "type": "Feature",
  "properties": {
    "iso:country":"CH",
    "sg:address":"Poststrasse 6",
    "sg:city":"Burgdorf",
    "sg:orig_category":"Non-Classified Establishments",
    "sg:phone":"+41 22 736 93 69",
    "sg:postcode":"3400",
    "sg:province":"Bern",
    "wof:name":"Universal Music Sa Produits Audiovisuels",
    "wof:placetype":"venue"
},
  "geometry": {"coordinates":[6.158898,46.205231],"type":"Point"}
}