{
  "type": "Feature",
  "properties": {
    "iso:country":"CH",
    "sg:address":"Oberdorfstrasse 22",
    "sg:city":"Steffisburg",
    "sg:orig_category":"Kosmetikinstitute",
    "sg:phone":"+41 33 437 75 50",
    "sg:postcode":"3612",
    "sg:province":"Bern",
    "wof:name":"Priska Brodbeck Kosmetikinstitut Prisma",
    "wof:placetype":"venue"
},
  "geometry": {"coordinates":[7.6340041161,46.7797622681],"type":"Point"}
}