{
  "type": "Feature",
  "properties": {
    "iso:country":"CH",
    "sg:address":"Cantonni\u00e8re Chemin De La 20",
    "sg:city":"Troinex",
    "sg:orig_category":"Herstellung von Konstruktionsteilen, Fertigbauteilen U Ausbauelementen aus Holz",
    "sg:phone":"+41 22 890 03 48",
    "sg:postcode":"1256",
    "sg:province":"Gen\u00e8ve",
    "wof:name":"Labat J\u00e9r\u00f4me",
    "wof:placetype":"venue"
},
  "geometry": {"coordinates":[6.1485409737,46.1604347229],"type":"Point"}
}