{
  "type": "Feature",
  "properties": {
    "iso:country":"CH",
    "sg:address":"Hasleren",
    "sg:city":"Ober\u00e4geri",
    "sg:orig_category":"Zimmerei, Dachdeckerei, Bauspenglerei U Abdichtung",
    "sg:postcode":"6315",
    "sg:province":"Zug",
    "wof:name":"Meier Robert",
    "wof:placetype":"venue"
},
  "geometry": {"coordinates":[8.6416397095,47.1052818298],"type":"Point"}
}