{
  "type": "Feature",
  "properties": {
    "iso:country":"CH",
    "sg:address":"Hauptstrasse 25a 6280 Hochdorf. Postfach 132",
    "sg:city":"Hochdorf",
    "sg:orig_category":"Elektroinstallation",
    "sg:phone":"+41 41 911 04 11",
    "sg:postcode":"6281",
    "sg:province":"Luzern",
    "wof:name":"Elgi-plan Gmbh",
    "wof:placetype":"venue"
},
  "geometry": {"coordinates":[8.2890644073,47.1669845581],"type":"Point"}
}