{
  "type": "Feature",
  "properties": {
    "iso:country":"CH",
    "sg:address":"Josefstrasse 32 8005 Z\u00fcrich. Postfach",
    "sg:city":"Z\u00fcrich",
    "sg:orig_category":"Film U Videofilmherstellung Fotografische Ateliers",
    "sg:phone":"+41 12718833",
    "sg:postcode":"8048",
    "sg:province":"Z\u00fcrich",
    "wof:name":"Rmk Art Productions Gmbh Filme, Fotos, Werbung; Produktion, Vertrieb",
    "wof:placetype":"venue"
},
  "geometry": {"coordinates":[8.5335321426,47.381313324],"type":"Point"}
}