{
  "type": "Feature",
  "properties": {
    "iso:country":"CH",
    "sg:address":"Dorfstrasse 49",
    "sg:city":"St\u00e4fa",
    "sg:classifiers":[
        {
            "category":"Food & Beverages",
            "subcategory":"Specialty",
            "type":"Retail Goods"
        }
    ],
    "sg:postcode":"8712",
    "sg:province":"Z\u00fcrich",
    "sg:tags":[
        "caterer"
    ],
    "wof:name":"A-z Geschirr- & Infrastruktur- Vermietungs Gmbh",
    "wof:placetype":"venue"
},
  "geometry": {"coordinates":[8.737774,47.238579],"type":"Point"}
}