{
  "type": "Feature",
  "properties": {
    "iso:country":"CH",
    "sg:address":"Abendweg 4",
    "sg:city":"Z\u00fcrich",
    "sg:orig_category":"Wirtschaftsverb\u00e4nde Gastgewerbe",
    "sg:phone":"+41 14871048",
    "sg:postcode":"8038",
    "sg:province":"Z\u00fcrich",
    "wof:name":"Verband F\u00fcr Gastronomie-& Gemeinschaftsverpfleg.svgg",
    "wof:placetype":"venue"
},
  "geometry": {"coordinates":[8.5288972855,47.3496017456],"type":"Point"}
}