{
  "type": "Feature",
  "properties": {
    "iso:country":"CH",
    "sg:address":"Brunnweg 11",
    "sg:city":"M\u00fchleberg",
    "sg:orig_category":"Unternehmensberatung",
    "sg:phone":"+41 31 752 10 10",
    "sg:postcode":"3203",
    "sg:province":"Bern",
    "wof:name":"Vario-treuhand Peter Zinniker",
    "wof:placetype":"venue"
},
  "geometry": {"coordinates":[7.263657093,46.9545173645],"type":"Point"}
}