{
  "type": "Feature",
  "properties": {
    "iso:country":"CH",
    "sg:address":"Einkaufszentrum Telli 5004 Aarau. Postfach 618",
    "sg:city":"Aarau",
    "sg:orig_category":"Detailhandel mit B\u00fcchern Detailhandel mit Ton U Bildtr\u00e4gern",
    "sg:phone":"+41 62 824 76 84",
    "sg:postcode":"5004",
    "sg:province":"Aargau",
    "wof:name":"Ex Libris Ag",
    "wof:placetype":"venue"
},
  "geometry": {"coordinates":[8.04999,47.391815],"type":"Point"}
}