{
  "type": "Feature",
  "properties": {
    "iso:country":"CH",
    "sg:address":"Bernstrasse 23 3308 Grafenried. Postfach",
    "sg:city":"Grafenried",
    "sg:orig_category":"R\u00fcckgewinnung U Vorbereitung f\u00fcr die Wiederverwertung Recycling von Schrott",
    "sg:phone":"+41 31 767 77 77",
    "sg:postcode":"3308",
    "sg:province":"Bern",
    "wof:name":"Ernst Egger Ag Autoverwertung",
    "wof:placetype":"venue"
},
  "geometry": {"coordinates":[7.5116100311,47.0762786865],"type":"Point"}
}