{
  "type": "Feature",
  "properties": {
    "iso:country":"CH",
    "sg:address":"9312",
    "sg:city":"H\u00e4ggenschwil",
    "sg:orig_category":"Sportvereine Sch\u00fctzen",
    "sg:phone":"+41 71 298 54 60",
    "sg:postcode":"9312",
    "sg:province":"St. Gallen",
    "wof:name":"Milit\u00e4rsch\u00fctzenverein",
    "wof:placetype":"venue"
},
  "geometry": {"coordinates":[9.3351097107,47.4884796143],"type":"Point"}
}