{
  "type": "Feature",
  "properties": {
    "iso:country":"CH",
    "sg:address":"Inzlingerstrasse 51",
    "sg:city":"Riehen",
    "sg:orig_category":"Pensionskassen",
    "sg:phone":"+41 61 645 88 88",
    "sg:postcode":"4125",
    "sg:province":"Basel-Stadt",
    "wof:name":"Philipp Merian'sche Stiftung",
    "wof:placetype":"venue"
},
  "geometry": {"coordinates":[7.6534972191,47.5884628296],"type":"Point"}
}