{
  "type": "Feature",
  "properties": {
    "addr:full":"Gutstrasse 51 Winterthur Z\u00fcrich 8400",
    "addr:housenumber":"51",
    "addr:postcode":"8400",
    "addr:street":"Gutstrasse",
    "iso:country":"CH",
    "sg:address":"Gutstrasse 51",
    "sg:city":"Winterthur",
    "sg:orig_category":"Allgemeiner Hoch U Tiefbau",
    "sg:postcode":"8400",
    "sg:province":"Z\u00fcrich",
    "wof:name":"Tresana Ag",
    "wof:placetype":"venue"
},
  "geometry": {"coordinates":[9.03163,47.465118],"type":"Point"}
}