{
  "type": "Feature",
  "properties": {
    "iso:country":"CH",
    "sg:address":"Gessnerallee 38",
    "sg:city":"Z\u00fcrich",
    "sg:orig_category":"Abfallbeseitigung R\u00fcckgewinnung U Vorbereitung f\u00fcr die Wiederverwertung Recycling von nichtmetallisc",
    "sg:phone":"+41 19373934",
    "sg:postcode":"8001",
    "sg:province":"Z\u00fcrich",
    "wof:name":"Keller Recycling Ag Kehricht-transporte",
    "wof:placetype":"venue"
},
  "geometry": {"coordinates":[8.854086,47.286449],"type":"Point"}
}