{
  "type": "Feature",
  "properties": {
    "iso:country":"CH",
    "sg:address":"Untere Zulgstrasse 8",
    "sg:city":"Steffisburg",
    "sg:orig_category":"Autogaragen",
    "sg:phone":"+41 34 437 18 71",
    "sg:postcode":"3613",
    "sg:province":"Bern",
    "wof:name":"Hans Beck Autoreparaturwerkst\u00e4tte",
    "wof:placetype":"venue"
},
  "geometry": {"coordinates":[7.748366,47.061417],"type":"Point"}
}