{
  "type": "Feature",
  "properties": {
    "iso:country":"CH",
    "sg:address":"Deux-ponts Rue Des 33 1205 Gen\u00e8ve. Postfach",
    "sg:city":"Gen\u00e8ve",
    "sg:orig_category":"Herstellung von Teilen U Zubeh\u00f6r f\u00fcr Automobile",
    "sg:postcode":"1205",
    "sg:province":"Gen\u00e8ve",
    "wof:name":"Jean-pierre Bapst",
    "wof:placetype":"venue"
},
  "geometry": {"coordinates":[6.1294231415,46.1998634338],"type":"Point"}
}