{
  "type": "Feature",
  "properties": {
    "iso:country":"CH",
    "sg:address":"Br\u00fcnigstrasse 10 6056 K\u00e4giswil. Postfach",
    "sg:city":"K\u00e4giswil",
    "sg:orig_category":"Instandhaltung U Reparatur von Automobilen",
    "sg:phone":"+41 79 432 11 54",
    "sg:postcode":"6056",
    "sg:province":"Obwalden",
    "wof:name":"Auto Ruckstuhl Citr\u00f6en, Honda U. Suzuki",
    "wof:placetype":"venue"
},
  "geometry": {"coordinates":[8.2641019821,46.9241790771],"type":"Point"}
}