{
  "type": "Feature",
  "properties": {
    "iso:country":"CH",
    "sg:address":"Entlebucherstrasse 3 6110 Wolhusen. Postfach 140",
    "sg:city":"Wolhusen",
    "sg:orig_category":"Blumen U Zierpflanzenbau Detailhandel mit Blumen U Pflanzen",
    "sg:phone":"+41 41 490 11 61",
    "sg:postcode":"6110",
    "sg:province":"Luzern",
    "wof:name":"Killer Blumen Ag",
    "wof:placetype":"venue"
},
  "geometry": {"coordinates":[8.072795,47.058491],"type":"Point"}
}