{
  "type": "Feature",
  "properties": {
    "iso:country":"CH",
    "sg:address":"4245",
    "sg:city":"Kleinl\u00fctzel",
    "sg:orig_category":"Giessereiindustrie Pulvermetallurgie Schmieden, Pressen, Stanzen U Profilwalzen von Metallen",
    "sg:phone":"+41 61 775 11 11",
    "sg:postcode":"4245",
    "sg:province":"Solothurn",
    "wof:name":"Schloss- & Beschl\u00e4gefabrik Ag",
    "wof:placetype":"venue"
},
  "geometry": {"coordinates":[7.4160170555,47.425819397],"type":"Point"}
}