{
  "type": "Feature",
  "properties": {
    "iso:country":"CH",
    "sg:address":"Melchr\u00fctistrasse 23a",
    "sg:city":"Wallisellen",
    "sg:orig_category":"Hardwareberatung",
    "sg:postcode":"8304",
    "sg:province":"Z\u00fcrich",
    "wof:name":"Cd-tech Jost",
    "wof:placetype":"venue"
},
  "geometry": {"coordinates":[8.5792016983,47.4171333313],"type":"Point"}
}