{
  "type": "Feature",
  "properties": {
    "iso:country":"CH",
    "sg:address":"Rue De Neuch\u00e2tel 35",
    "sg:city":"Peseux",
    "sg:orig_category":"Herstellung von Konstruktionsteilen, Fertigbauteilen U Ausbauelementen aus Holz",
    "sg:postcode":"2034",
    "sg:province":"Neuch\u00e2tel",
    "wof:name":"Menuiserie Arrigo Sa",
    "wof:placetype":"venue"
},
  "geometry": {"coordinates":[6.8963241577,46.988735199],"type":"Point"}
}