{
  "type": "Feature",
  "properties": {
    "iso:country":"CH",
    "sg:address":"Le Pichoux",
    "sg:city":"Sornetan",
    "sg:classifiers":[
        {
            "category":"Travel",
            "subcategory":"Hotels & Motels",
            "type":"Entertainment"
        }
    ],
    "sg:phone":"+41 32 484 91 28",
    "sg:postcode":"2716",
    "sg:province":"Bern",
    "sg:tags":[
        "hotels",
        "mit",
        "restaurant"
    ],
    "wof:name":"H\u00f4tel De La Couronne",
    "wof:placetype":"venue"
},
  "geometry": {"coordinates":[7.2298898697,47.2790756226],"type":"Point"}
}