{
  "type": "Feature",
  "properties": {
    "iso:country":"CH",
    "sg:address":"Rue Merle-d'aubign\u00e9 22",
    "sg:city":"Gen\u00e8ve",
    "sg:orig_category":"Herstellung von M\u00f6beln",
    "sg:phone":"+41 22 736 41 22",
    "sg:postcode":"1207",
    "sg:province":"Gen\u00e8ve",
    "wof:name":"Atelier Arc-en-ciel",
    "wof:placetype":"venue"
},
  "geometry": {"coordinates":[6.1637701988,46.2052192688],"type":"Point"}
}