{
  "type": "Feature",
  "properties": {
    "iso:country":"CH",
    "sg:address":"Mittlere Strasse 13",
    "sg:city":"Thun",
    "sg:classifiers":[
        {
            "category":"Manufacturing",
            "subcategory":"Tools & Machinery",
            "type":"Manufacturing & Wholesale Goods"
        }
    ],
    "sg:phone":"+41 33 227 33 33",
    "sg:postcode":"3600",
    "sg:province":"Bern",
    "sg:tags":[
        "chucking"
    ],
    "wof:name":"Kellenberger Ag",
    "wof:placetype":"venue"
},
  "geometry": {"coordinates":[7.622365,46.756798],"type":"Point"}
}