{
  "type": "Feature",
  "properties": {
    "iso:country":"CH",
    "sg:address":"Mont-blanc Rue Du 26",
    "sg:city":"Gen\u00e8ve",
    "sg:orig_category":"Herstellung von k\u00e4lte U lufttechnischen Erzeugnissen f\u00fcr gewerbliche Zwecke",
    "sg:phone":"+41 22 738 31 60",
    "sg:postcode":"1201",
    "sg:province":"Gen\u00e8ve",
    "wof:name":"Unifroid Sa",
    "wof:placetype":"venue"
},
  "geometry": {"coordinates":[6.152616024,46.2111206055],"type":"Point"}
}