{
  "type": "Feature",
  "properties": {
    "iso:country":"CH",
    "sg:address":"Hofacher",
    "sg:city":"Mund",
    "sg:orig_category":"Herstellung von Metallkonstruktionen",
    "sg:phone":"+41 21 841 18 19",
    "sg:postcode":"3903",
    "sg:province":"Valais",
    "wof:name":"Martin Aubert Construction M\u00e9tallique S\u00e0rl",
    "wof:placetype":"venue"
},
  "geometry": {"coordinates":[6.2955889702,46.6561660767],"type":"Point"}
}