{
  "type": "Feature",
  "properties": {
    "iso:country":"CH",
    "sg:address":"Seltisbergerstrasse 6",
    "sg:city":"Basel",
    "sg:orig_category":"Interessenvertretungen U sonstige Vereinigungen Sonstige mit Sport verbundene T\u00e4tigkeiten",
    "sg:phone":"+41 61 331 71 96",
    "sg:postcode":"4059",
    "sg:province":"Basel-Stadt",
    "wof:name":"European Tennis Association",
    "wof:placetype":"venue"
},
  "geometry": {"coordinates":[7.6006331444,47.5301132202],"type":"Point"}
}