{
  "type": "Feature",
  "properties": {
    "iso:country":"CH",
    "sg:address":"Frohsinnstrasse 11",
    "sg:city":"Dussnang",
    "sg:orig_category":"RESTAURANTS: TEA-ROOMS",
    "sg:postcode":"8374",
    "sg:province":"Thurgau",
    "wof:name":"Restaurant Sch\u00f6negg Marianne Stamm",
    "wof:placetype":"venue"
},
  "geometry": {"coordinates":[8.2020425797,47.4825515747],"type":"Point"}
}