{
  "type": "Feature",
  "properties": {
    "iso:country":"CH",
    "sg:address":"Waldweg 3",
    "sg:city":"Klingnau",
    "sg:orig_category":"Herstellung von sonstigen Maschinen f\u00fcr bestimmte Verwendung",
    "sg:postcode":"5313",
    "sg:province":"Aargau",
    "wof:name":"H\u00e4nssler Martin",
    "wof:placetype":"venue"
},
  "geometry": {"coordinates":[8.8475618362,47.4153175354],"type":"Point"}
}