{
  "type": "Feature",
  "properties": {
    "iso:country":"CH",
    "sg:address":"Neugasse 24a",
    "sg:city":"Berneck",
    "sg:orig_category":"Herstellung von sonstigen chemischen Erzeugnissen",
    "sg:phone":"+41 71 744 91 49",
    "sg:postcode":"9442",
    "sg:province":"St. Gallen",
    "wof:name":"Loher Paul H.",
    "wof:placetype":"venue"
},
  "geometry": {"coordinates":[9.612783432,47.4253425598],"type":"Point"}
}