{
  "type": "Feature",
  "properties": {
    "iso:country":"CH",
    "sg:address":"Route Du Stand 19",
    "sg:city":"Nyon",
    "sg:orig_category":"Dachdeckerei Zimmerei, Dachdeckerei, Bauspenglerei U Abdichtung",
    "sg:phone":"+41 22 361 01 20",
    "sg:postcode":"1260",
    "sg:province":"Vaud",
    "wof:name":"Christen Kurt",
    "wof:placetype":"venue"
},
  "geometry": {"coordinates":[6.223962,46.382214],"type":"Point"}
}