{
  "type": "Feature",
  "properties": {
    "iso:country":"CH",
    "sg:address":"Berglistrasse 33",
    "sg:city":"Ebnat-kappel",
    "sg:orig_category":"Fahrschulen, Flugschulen",
    "sg:phone":"+41 71 993 29 29",
    "sg:postcode":"9642",
    "sg:province":"St. Gallen",
    "wof:name":"Hans Grob Autofahrschule",
    "wof:placetype":"venue"
},
  "geometry": {"coordinates":[9.1184053421,47.2694702148],"type":"Point"}
}