{
  "type": "Feature",
  "properties": {
    "iso:country":"CH",
    "sg:address":"G\u00e4uggelistrasse 6",
    "sg:city":"Chur",
    "sg:orig_category":"Physiotherapie",
    "sg:phone":"+41 56 622 42 50",
    "sg:postcode":"7000",
    "sg:province":"Graubunden",
    "wof:name":"Cornelia Humbel Physiotherapie",
    "wof:placetype":"venue"
},
  "geometry": {"coordinates":[8.2738389969,47.3509674072],"type":"Point"}
}