{
  "type": "Feature",
  "properties": {
    "iso:country":"CH",
    "sg:address":"Les Sciernes-picats",
    "sg:city":"Flendruz",
    "sg:classifiers":[
        {
            "category":"Restaurant",
            "type":"Food & Drink"
        }
    ],
    "sg:phone":"+41 26 925 81 57",
    "sg:postcode":"1839",
    "wof:name":"Caf\u00e9 Du Vanil",
    "wof:placetype":"venue"
},
  "geometry": {"coordinates":[7.183740139,46.4823112488],"type":"Point"}
}