{
  "type": "Feature",
  "properties": {
    "iso:country":"CH",
    "sg:address":"D\u00fcnnernstrasse 20 4702 Oensingen. Postfach",
    "sg:city":"Oensingen",
    "sg:orig_category":"Herstellung von Elektromotoren, Generatoren U Transformatoren",
    "sg:phone":"+41 62 396 24 16",
    "sg:postcode":"4702",
    "sg:province":"Solothurn",
    "wof:name":"Victor Gyger Elektrowicklerei",
    "wof:placetype":"venue"
},
  "geometry": {"coordinates":[7.7163119316,47.2844352722],"type":"Point"}
}