{
  "type": "Feature",
  "properties": {
    "iso:country":"CH",
    "sg:address":"Morges Route De 5",
    "sg:city":"St-prex",
    "sg:orig_category":"Finanzierungsinstitutionen",
    "sg:postcode":"1162",
    "sg:province":"Vaud",
    "wof:name":"Mt Concept S\u00e0rl",
    "wof:placetype":"venue"
},
  "geometry": {"coordinates":[6.4576702118,46.4821166992],"type":"Point"}
}