{
  "type": "Feature",
  "properties": {
    "iso:country":"CH",
    "sg:address":"Guetstrasse 5",
    "sg:city":"Oensingen",
    "sg:orig_category":"Grosshandel mit Datenverarbeitungsger\u00e4ten Grosshandel mit Software",
    "sg:phone":"+41 26 919 55 05",
    "sg:postcode":"4702",
    "sg:province":"Solothurn",
    "wof:name":"Job4it S\u00e0rl",
    "wof:placetype":"venue"
},
  "geometry": {"coordinates":[7.0595607758,46.6176338196],"type":"Point"}
}