{
  "type": "Feature",
  "properties": {
    "iso:country":"CH",
    "sg:address":"Tribschenstrasse 7 6005 Luzern. Postfach",
    "sg:city":"Luzern",
    "sg:orig_category":"Grosshandel mit Erzen U Metallen",
    "sg:postcode":"6005",
    "sg:province":"Luzern",
    "wof:name":"Gespro, Gesellschaft F\u00fcr \u00dcberseeprodukte",
    "wof:placetype":"venue"
},
  "geometry": {"coordinates":[8.3125286102,47.044052124],"type":"Point"}
}