{
  "type": "Feature",
  "properties": {
    "iso:country":"CH",
    "sg:address":"Laghetto Via Pian 1 6500 Bellinzona. Postfach",
    "sg:city":"Bellinzona",
    "sg:orig_category":"Interessenvertretungen",
    "sg:postcode":"6500",
    "sg:province":"Ticino",
    "wof:name":"Fondazione Sasso Corbaro Promozione Della Documentazione, Dello Studio Ecc. Nel Campo Delle Medical Humanities E Dell'etica Clinica",
    "wof:placetype":"venue"
},
  "geometry": {"coordinates":[9.0364131927,46.1909561157],"type":"Point"}
}