{
  "type": "Feature",
  "properties": {
    "iso:country":"CH",
    "sg:address":"Gliserallee 90 3902 Glis. Postfach",
    "sg:city":"Glis",
    "sg:orig_category":"Einbau von Schreinerwaren Herstellung von Betonerzeugnissen f\u00fcr den Bau",
    "sg:phone":"+41 22 342 60 70",
    "sg:postcode":"3902",
    "sg:province":"Valais",
    "wof:name":"Piatti Bruno Sa",
    "wof:placetype":"venue"
},
  "geometry": {"coordinates":[6.1385250092,46.1865119934],"type":"Point"}
}