{
  "type": "Feature",
  "properties": {
    "iso:country":"CH",
    "sg:address":"Chamerstrasse 170",
    "sg:city":"Zug",
    "sg:orig_category":"Bauingenieurb\u00fcros allgemein Ingenieurb\u00fcros Umwelttechnik and \u00d6kologie",
    "sg:phone":"+41 41 748 20 80",
    "sg:postcode":"6300",
    "sg:province":"Zug",
    "wof:name":"Berchtold & Eicher Bauingenieure Ag",
    "wof:placetype":"venue"
},
  "geometry": {"coordinates":[8.48544,47.181026],"type":"Point"}
}