{
  "type": "Feature",
  "properties": {
    "iso:country":"CH",
    "sg:address":"Industriestrasse 99 3902 Glis. Postfach",
    "sg:city":"Glis",
    "sg:orig_category":"Non-Classified Establishments",
    "sg:postcode":"3902",
    "sg:province":"Valais",
    "wof:name":"Tauchshop Octopus Und Tauchschule Mountain Divers, Biner Christina",
    "wof:placetype":"venue"
},
  "geometry": {"coordinates":[7.9776821136,46.3108596802],"type":"Point"}
}