{
  "type": "Feature",
  "properties": {
    "iso:country":"CH",
    "sg:address":"Speerstrasse",
    "sg:city":"Goldingen",
    "sg:orig_category":"Herstellung von Hebezeugen U F\u00f6rdermitteln",
    "sg:phone":"+41 55 284 12 35",
    "sg:postcode":"8638",
    "sg:province":"St. Gallen",
    "wof:name":"Sportbahnen Atzm\u00e4nnig Ag",
    "wof:placetype":"venue"
},
  "geometry": {"coordinates":[8.9617519379,47.2632255554],"type":"Point"}
}