{
  "type": "Feature",
  "properties": {
    "iso:country":"CH",
    "sg:address":"Strandweg 34 3004 Bern. Postfach",
    "sg:city":"Bern",
    "sg:orig_category":"Fernmeldedienste",
    "sg:phone":"+41 31 305 39 01",
    "sg:postcode":"3004",
    "sg:province":"Bern",
    "wof:name":"Smartrek Mathys",
    "wof:placetype":"venue"
},
  "geometry": {"coordinates":[7.4397788048,46.972858429],"type":"Point"}
}