{
  "type": "Feature",
  "properties": {
    "iso:country":"CH",
    "sg:address":"1409",
    "sg:city":"Chan\u00e9az",
    "sg:orig_category":"Non-Classified Establishments",
    "sg:postcode":"1409",
    "sg:province":"Vaud",
    "wof:name":"Heitec Holding Sa",
    "wof:placetype":"venue"
},
  "geometry": {"coordinates":[6.7457399368,46.7287902832],"type":"Point"}
}