{
  "type": "Feature",
  "properties": {
    "iso:country":"CH",
    "sg:address":"2338",
    "sg:city":"Emibois-muriaux",
    "sg:orig_category":"G\u00fcterbef\u00f6rderung im Strassenverkehr",
    "sg:phone":"+41 79 355 42 20",
    "sg:postcode":"2338",
    "sg:province":"Jura",
    "wof:name":"Raymond Sandoz Transports",
    "wof:placetype":"venue"
},
  "geometry": {"coordinates":[6.8992409706,47.0410118103],"type":"Point"}
}