{
  "type": "Feature",
  "properties": {
    "iso:country":"CH",
    "sg:address":"Kornfeldweg 2",
    "sg:city":"Fraubrunnen",
    "sg:orig_category":"Detailhandel mit Textilien",
    "sg:phone":"+41 31 767 77 04",
    "sg:postcode":"3312",
    "sg:province":"Bern",
    "wof:name":"Stricken Mit Christine Chr.kaderli",
    "wof:placetype":"venue"
},
  "geometry": {"coordinates":[7.5331721306,47.0840568542],"type":"Point"}
}