{
  "type": "Feature",
  "properties": {
    "iso:country":"CH",
    "sg:address":"Premier-mars Avenue Du 16",
    "sg:city":"Neuch\u00e2tel",
    "sg:orig_category":"Sonstiges Versicherungsgewerbe",
    "sg:postcode":"2000",
    "sg:province":"Neuch\u00e2tel",
    "wof:name":"Jaquet Claude, Courtier",
    "wof:placetype":"venue"
},
  "geometry": {"coordinates":[6.9371180534,46.9933815002],"type":"Point"}
}