{
  "type": "Feature",
  "properties": {
    "iso:country":"CH",
    "sg:address":"Centralbahnstrasse 7 4051 Basel. Postfach",
    "sg:city":"Basel",
    "sg:orig_category":"Markt U Meinungsforschung",
    "sg:postcode":"4051",
    "sg:province":"Basel-Stadt",
    "wof:name":"Cas Sys Gmbh Marketing Bes. Informationsmanagement, Konzeption, Planung Usw",
    "wof:placetype":"venue"
},
  "geometry": {"coordinates":[7.5883860588,47.548500061],"type":"Point"}
}