{
  "type": "Feature",
  "properties": {
    "iso:country":"CH",
    "sg:address":"Av. Cardinal-mermillod 42-44",
    "sg:city":"Carouge",
    "sg:classifiers":[
        {
            "category":"Banks & Credit Unions",
            "subcategory":"Bureau De Change",
            "type":"Services"
        }
    ],
    "sg:phone":"+41 22 309 31 31",
    "sg:postcode":"1227",
    "sg:province":"Gen\u00e8ve",
    "sg:tags":[
        "solution",
        "complete",
        "internet"
    ],
    "wof:name":"Psideo S.a.",
    "wof:placetype":"venue"
},
  "geometry": {"coordinates":[6.1443600655,46.1853790283],"type":"Point"}
}