{
  "type": "Feature",
  "properties": {
    "iso:country":"CH",
    "sg:address":"Bruderholzstrasse 47 4053 Basel. Postfach",
    "sg:city":"Basel",
    "sg:orig_category":"Betrieb U technische Hilfsdienste des Kultur U Unterhaltungswesens",
    "sg:phone":"+41 61 361 03 68",
    "sg:postcode":"4051",
    "sg:province":"Basel-Stadt",
    "wof:name":"Broadway Theater Ag Vari\u00e9t\u00e9-theater Mit Konsumation",
    "wof:placetype":"venue"
},
  "geometry": {"coordinates":[7.594691,47.543224],"type":"Point"}
}