{
  "type": "Feature",
  "properties": {
    "iso:country":"CH",
    "sg:address":"Untere Rebzelg 7 3662 Seftigen. Postfach",
    "sg:city":"Seftigen",
    "sg:orig_category":"Erwachsenenbildung U Unterricht",
    "sg:postcode":"3662",
    "sg:province":"Bern",
    "wof:name":"Freespeech English Schild-johnson Barbara L.",
    "wof:placetype":"venue"
},
  "geometry": {"coordinates":[7.5439310074,46.7908554077],"type":"Point"}
}