{
  "type": "Feature",
  "properties": {
    "iso:country":"CH",
    "sg:address":"Via Reslina 48",
    "sg:city":"Losone",
    "sg:orig_category":"Grosshandel mit Holz U Bauelementen aus Holz Handelsvermittlung von Maschinen, technischem Bedarf, W",
    "sg:phone":"+41 91 791 11 23",
    "sg:postcode":"6616",
    "sg:province":"Ticino",
    "wof:name":"Industrie-vertretungen-beratung Ivb Di Schincke J\u00fcrgen",
    "wof:placetype":"venue"
},
  "geometry": {"coordinates":[8.7597322464,46.1772651672],"type":"Point"}
}