{
  "type": "Feature",
  "properties": {
    "iso:country":"CH",
    "sg:address":"Dreik\u00f6nigstrasse 12 8002 Z\u00fcrich. Postfach 2399",
    "sg:city":"Z\u00fcrich",
    "sg:orig_category":"Versicherungen Generalagenturen",
    "sg:phone":"+41 12834333",
    "sg:postcode":"8022",
    "sg:province":"Z\u00fcrich",
    "wof:name":"Helvetia Patria Versicherungen Generalagentur",
    "wof:placetype":"venue"
},
  "geometry": {"coordinates":[8.5370550156,47.3673934937],"type":"Point"}
}