{
  "type": "Feature",
  "properties": {
    "iso:country":"CH",
    "sg:address":"Bahnhofstrasse 19",
    "sg:city":"Stansstad",
    "sg:orig_category":"Nationale Postdienste",
    "sg:phone":"+41 41 610 18 10",
    "sg:postcode":"6362",
    "sg:province":"Nidwalden",
    "wof:name":"Die Schweizerische Post",
    "wof:placetype":"venue"
},
  "geometry": {"coordinates":[8.3373346329,46.976890564],"type":"Point"}
}