{
  "type": "Feature",
  "properties": {
    "iso:country":"CH",
    "sg:address":"Neugutstr. 19",
    "sg:city":"Oberengstringen",
    "sg:classifiers":[
        {
            "category":"Professional",
            "subcategory":"Engineering",
            "type":"Services"
        }
    ],
    "sg:phone":"+41 4117518444",
    "sg:postcode":"8102",
    "sg:province":"Z\u00fcrich",
    "sg:tags":[
        "machine",
        "-",
        "mechanical"
    ],
    "wof:name":"Oscar Beck Ag",
    "wof:placetype":"venue"
},
  "geometry": {"coordinates":[8.4564409256,47.4076728821],"type":"Point"}
}