{
  "type": "Feature",
  "properties": {
    "iso:country":"CH",
    "sg:address":"Im Altried 3c",
    "sg:city":"Z\u00fcrich",
    "sg:orig_category":"Allgemeiner Hoch U Tiefbau",
    "sg:phone":"+41 13212588",
    "sg:postcode":"8051",
    "sg:province":"Z\u00fcrich",
    "wof:name":"Ruckstuhl M. Ag",
    "wof:placetype":"venue"
},
  "geometry": {"coordinates":[8.59103,47.404469],"type":"Point"}
}