{
  "type": "Feature",
  "properties": {
    "iso:country":"CH",
    "sg:address":"Val Sporz 60",
    "sg:city":"Vaz/obervaz",
    "sg:orig_category":"Non-Classified Establishments",
    "sg:postcode":"7082",
    "sg:province":"Graubunden",
    "wof:name":"Olona Investment Ag",
    "wof:placetype":"venue"
},
  "geometry": {"coordinates":[9.5401754379,46.7024993896],"type":"Point"}
}