{
  "type": "Feature",
  "properties": {
    "iso:country":"CH",
    "sg:address":"Rosenmatt",
    "sg:city":"Luthern",
    "sg:orig_category":"Bauschreinerei Detailhandel mit Waren verschiedener Art, Hauptrichtung Nahrungsmittel",
    "sg:phone":"+41 41 978 14 45",
    "sg:postcode":"6156",
    "sg:province":"Luzern",
    "wof:name":"Josef Birrer Schreinerei & Holzbau",
    "wof:placetype":"venue"
},
  "geometry": {"coordinates":[7.916532,47.061913],"type":"Point"}
}