{
  "type": "Feature",
  "properties": {
    "iso:country":"CH",
    "sg:address":"Bahnhofplatz 5",
    "sg:city":"Bern",
    "sg:orig_category":"RESTAURANTS: TEA-ROOMS",
    "sg:phone":"+41 31 311 33 25",
    "sg:postcode":"3011",
    "sg:province":"Bern",
    "wof:name":"Caf\u00e9 Apero Bar Eichenberger Ag",
    "wof:placetype":"venue"
},
  "geometry": {"coordinates":[7.4411530495,46.9481658936],"type":"Point"}
}