{
  "type": "Feature",
  "properties": {
    "iso:country":"CH",
    "sg:address":"Haldenstrasse 121 5728 Gontenschwil. Postfach",
    "sg:city":"Gontenschwil",
    "sg:orig_category":"Druck ohne Zeitungsdruck",
    "sg:postcode":"5728",
    "sg:province":"Aargau",
    "wof:name":"Werbepromo Ag Drucksachen Zu Werbezwecken; Handel, Veredelung",
    "wof:placetype":"venue"
},
  "geometry": {"coordinates":[8.2430696487,47.2655067444],"type":"Point"}
}