{
  "type": "Feature",
  "properties": {
    "iso:country":"CH",
    "sg:address":"Moosgrabenstrasse 13",
    "sg:city":"Altnau",
    "sg:orig_category":"Herstellung von sonstigen M\u00f6beln",
    "sg:phone":"+41 71 695 10 63",
    "sg:postcode":"8595",
    "sg:province":"Thurgau",
    "wof:name":"Garten & Freizeit Bruno Gresser",
    "wof:placetype":"venue"
},
  "geometry": {"coordinates":[9.2681217194,47.6169281006],"type":"Point"}
}