{
  "type": "Feature",
  "properties": {
    "iso:country":"CH",
    "sg:address":"Gerlisbrunnenstrasse 20",
    "sg:city":"Benglen",
    "sg:orig_category":"Architektur U Ingenieurb\u00fcros",
    "sg:phone":"+41 18872440",
    "sg:postcode":"8121",
    "sg:province":"Z\u00fcrich",
    "wof:name":"Thomas B\u00fcrki Gmbh",
    "wof:placetype":"venue"
},
  "geometry": {"coordinates":[8.63483,47.359509],"type":"Point"}
}