{
  "type": "Feature",
  "properties": {
    "iso:country":"CH",
    "sg:address":"Suhrenmatteng\u00e4ssli 4",
    "sg:city":"Oberentfelden",
    "sg:classifiers":[
        {
            "category":"Manufacturing",
            "subcategory":"Chemicals & Compounds",
            "type":"Manufacturing & Wholesale Goods"
        }
    ],
    "sg:phone":"+41 62 737 46 00",
    "sg:postcode":"5036",
    "sg:province":"Aargau",
    "sg:tags":[
        "pharmaceutical",
        "chemistry",
        "-",
        "by-product"
    ],
    "wof:name":"Aarolac Ag",
    "wof:placetype":"venue"
},
  "geometry": {"coordinates":[8.054108,47.360542],"type":"Point"}
}