{
  "type": "Feature",
  "properties": {
    "iso:country":"CH",
    "sg:address":"Hauptstrasse 373 4717 M\u00fcmliswil. Postfach 136",
    "sg:city":"M\u00fcmliswil",
    "sg:orig_category":"Sportvereine Sch\u00fctzen",
    "sg:postcode":"4717",
    "sg:province":"Solothurn",
    "wof:name":"Sch\u00fctzenges.m'wil-reckenkien",
    "wof:placetype":"venue"
},
  "geometry": {"coordinates":[7.702767849,47.3411178589],"type":"Point"}
}