{
  "type": "Feature",
  "properties": {
    "iso:country":"CH",
    "sg:address":"6775",
    "sg:city":"Ambr\u00ec",
    "sg:orig_category":"Instandhaltung U Reparatur von Automobilen",
    "sg:postcode":"6775",
    "sg:province":"Ticino",
    "wof:name":"Erwin Bleuer Ag",
    "wof:placetype":"venue"
},
  "geometry": {"coordinates":[7.3009009361,47.1139678955],"type":"Point"}
}