{
  "type": "Feature",
  "properties": {
    "addr:full":"Witikonerstrasse 285 Z\u00fcrich Z\u00fcrich 8053",
    "addr:housenumber":"285",
    "addr:postcode":"8053",
    "addr:street":"Witikonerstrasse",
    "iso:country":"CH",
    "sg:address":"Witikonerstrasse 285",
    "sg:city":"Z\u00fcrich",
    "sg:classifiers":[
        {
            "category":"Banks & Credit Unions",
            "subcategory":"Bank",
            "type":"Services"
        }
    ],
    "sg:phone":"+41 1534800",
    "sg:postcode":"8053",
    "sg:province":"Z\u00fcrich",
    "wof:name":"Union Bank Of Switzerland",
    "wof:placetype":"venue"
},
  "geometry": {"coordinates":[8.58598,47.358418],"type":"Point"}
}