{
  "type": "Feature",
  "properties": {
    "iso:country":"CH",
    "sg:address":"Kantonsstrasse 73 3931 Eyholz Case Postale 264",
    "sg:city":"Visp",
    "sg:orig_category":"Elektroinstallation",
    "sg:phone":"+41 27 948 10 20",
    "sg:postcode":"3930",
    "sg:province":"Valais",
    "wof:name":"Etg Salzmann Ag Installations \u00e9lectriques, \u00e9lectrom\u00e9caniques Etc.; Planification, Construction Etc",
    "wof:placetype":"venue"
},
  "geometry": {"coordinates":[7.9033398628,46.2992095947],"type":"Point"}
}