{
  "type": "Feature",
  "properties": {
    "iso:country":"CH",
    "sg:address":"Via Della Salina 7 6600 Muralto. Postfach Cp 444",
    "sg:city":"Muralto",
    "sg:orig_category":"Architektur U Ingenieurb\u00fcros",
    "sg:phone":"+41 31 318 80 00",
    "sg:postcode":"6602",
    "sg:province":"Ticino",
    "wof:name":"Semtec Psc Ag",
    "wof:placetype":"venue"
},
  "geometry": {"coordinates":[7.453759,46.956284],"type":"Point"}
}