{
  "type": "Feature",
  "properties": {
    "iso:country":"CH",
    "sg:address":"Seestrasse 64",
    "sg:city":"Oberrieden",
    "sg:orig_category":"Herstellung von sonstigen Nahrungsmitteln Schlankheitsinstitute",
    "sg:phone":"+41 17212725",
    "sg:postcode":"8942",
    "sg:province":"Z\u00fcrich",
    "wof:name":"Alparom Body Care Gmbh",
    "wof:placetype":"venue"
},
  "geometry": {"coordinates":[8.5825357437,47.2739257812],"type":"Point"}
}