{
  "type": "Feature",
  "properties": {
    "iso:country":"CH",
    "sg:address":"Rue Du Temple 3",
    "sg:city":"St-aubin-sauges",
    "sg:orig_category":"Verwertung von Milch",
    "sg:phone":"+41 32 835 17 33",
    "sg:postcode":"2024",
    "sg:province":"Neuch\u00e2tel",
    "wof:name":"Laiterie De St-aubin-sauges",
    "wof:placetype":"venue"
},
  "geometry": {"coordinates":[6.7746458054,46.8957710266],"type":"Point"}
}