{
  "type": "Feature",
  "properties": {
    "iso:country":"CH",
    "sg:address":"Chemin Des Tormes",
    "sg:city":"Chesi\u00e8res",
    "sg:orig_category":"Stukkateurgewerbe, Gipserei U Verputzerei Tapeziererei",
    "sg:phone":"+41 24 495 20 09",
    "sg:postcode":"1885",
    "sg:province":"Vaud",
    "wof:name":"Ramirez & Cie Sa Peinture & Gypserie",
    "wof:placetype":"venue"
},
  "geometry": {"coordinates":[7.0401649475,46.2994422913],"type":"Point"}
}