{
  "type": "Feature",
  "properties": {
    "iso:country":"CH",
    "sg:address":"Hammergutstrasse 10",
    "sg:city":"Zufikon",
    "sg:orig_category":"Architektur U Ingenieurb\u00fcros Softwareentwicklung U beratung",
    "sg:phone":"+41 56 633 92 12",
    "sg:postcode":"5621",
    "sg:province":"Aargau",
    "wof:name":"Bak Tallichet R.",
    "wof:placetype":"venue"
},
  "geometry": {"coordinates":[8.353286,47.356041],"type":"Point"}
}