{
  "type": "Feature",
  "properties": {
    "iso:country":"CH",
    "sg:address":"Dorfstrasse 22",
    "sg:city":"L\u00fctzelfl\u00fch-goldb",
    "sg:orig_category":"Herstellung von Radio U Fernsehger\u00e4ten sowie phono U videotechnischen Ger\u00e4ten",
    "sg:postcode":"3432",
    "sg:province":"Bern",
    "wof:name":"Radio-tv Jenni Gmbh",
    "wof:placetype":"venue"
},
  "geometry": {"coordinates":[8.4965848923,47.48828125],"type":"Point"}
}