{
  "type": "Feature",
  "properties": {
    "iso:country":"CH",
    "sg:address":"Via Olgiati 20.1",
    "sg:city":"Giubiasco",
    "sg:orig_category":"Grosshandel mit chemischen Erzeugnissen",
    "sg:phone":"+41 91 857 19 60",
    "sg:postcode":"6512",
    "sg:province":"Ticino",
    "wof:name":"Clivin Import Di Ciardone Dario L.",
    "wof:placetype":"venue"
},
  "geometry": {"coordinates":[9.014093399,46.1761703491],"type":"Point"}
}