{
  "type": "Feature",
  "properties": {
    "iso:country":"CH",
    "sg:address":"Bodenweg 2",
    "sg:city":"Arlesheim",
    "sg:orig_category":"Erschliessung von Grundst\u00fccken",
    "sg:postcode":"4144",
    "sg:province":"Basel-Landschaft",
    "wof:name":"Wohngenossenschaft Wolfmatten",
    "wof:placetype":"venue"
},
  "geometry": {"coordinates":[7.6196761131,47.4990272522],"type":"Point"}
}