{
  "type": "Feature",
  "properties": {
    "iso:country":"CH",
    "sg:address":"Vadianstrasse 41",
    "sg:city":"St.gallen",
    "sg:orig_category":"Wirtschaftspr\u00fcfung, Steuerberatung U Treuhand Zahntechnische Laboratorien",
    "sg:phone":"+41 71 222 40 55",
    "sg:postcode":"9000",
    "sg:province":"St. Gallen",
    "wof:name":"Fritsche Hans",
    "wof:placetype":"venue"
},
  "geometry": {"coordinates":[9.369767189,47.4212036133],"type":"Point"}
}