{
  "type": "Feature",
  "properties": {
    "iso:country":"CH",
    "sg:address":"Chemin De Sur-beauvent 2 1232 Confignon. Postfach",
    "sg:city":"Confignon",
    "sg:orig_category":"Sonstige mit der Informatik verbundene T\u00e4tigkeiten",
    "sg:postcode":"1232",
    "sg:province":"Gen\u00e8ve",
    "wof:name":"Suter - Sofiae",
    "wof:placetype":"venue"
},
  "geometry": {"coordinates":[6.0798740387,46.1726303101],"type":"Point"}
}