{
  "type": "Feature",
  "properties": {
    "iso:country":"CH",
    "sg:address":"Rosenstrasse 6",
    "sg:city":"Gerlafingen",
    "sg:orig_category":"Wirtschaftspr\u00fcfung, Steuerberatung U Treuhand",
    "sg:postcode":"4563",
    "sg:province":"Solothurn",
    "wof:name":"B\u00fcro R\u00fcedi",
    "wof:placetype":"venue"
},
  "geometry": {"coordinates":[7.5705170631,47.1664237976],"type":"Point"}
}