{
  "type": "Feature",
  "properties": {
    "iso:country":"CH",
    "sg:address":"1567",
    "sg:city":"Delley",
    "sg:orig_category":"Detailhandel mit Waren verschiedener Art, Hauptrichtung Nahrungsmittel Grosshandel mit Nahrungsmitte",
    "sg:phone":"+41 26 677 16 24",
    "sg:postcode":"1567",
    "sg:province":"Fribourg",
    "wof:name":"Alimentation Vis-\u00e0-vis Collomb & Musy",
    "wof:placetype":"venue"
},
  "geometry": {"coordinates":[6.9719600677,46.9128189087],"type":"Point"}
}