{
  "type": "Feature",
  "properties": {
    "iso:country":"CH",
    "sg:address":"Stockerstrasse 50",
    "sg:city":"Z\u00fcrich",
    "sg:orig_category":"Sonstige Institutionen des Sozialwesens ohne Beherbergung",
    "sg:phone":"+41 90575075",
    "sg:postcode":"8002",
    "sg:province":"Z\u00fcrich",
    "wof:name":"Schleudertrauma-beratungsst.",
    "wof:placetype":"venue"
},
  "geometry": {"coordinates":[8.5344629288,47.3684577942],"type":"Point"}
}