{
  "type": "Feature",
  "properties": {
    "iso:country":"CH",
    "sg:address":"Terminus Bahnhofstrasse",
    "sg:city":"Spiez",
    "sg:classifiers":[
        {
            "category":"Professional",
            "subcategory":"Employment Agencies",
            "type":"Services"
        }
    ],
    "sg:phone":"+41 33 650 70 10",
    "sg:postcode":"3700",
    "sg:province":"Bern",
    "sg:tags":[
        "personal",
        "u",
        "stellenvermittlung"
    ],
    "wof:name":"Rav Berner Oberland Regionales Arbeitsvermittlungszentrum",
    "wof:placetype":"venue"
},
  "geometry": {"coordinates":[7.6742949486,46.6892204285],"type":"Point"}
}