{
  "type": "Feature",
  "properties": {
    "iso:country":"CH",
    "sg:address":"Mont Sentier Du 8",
    "sg:city":"Corsier-sur-vevey",
    "sg:orig_category":"Herstellung von Spielwaren",
    "sg:postcode":"1804",
    "sg:province":"Vaud",
    "wof:name":"M\u00fcllhaupt + Co, Aqua Curiosa",
    "wof:placetype":"venue"
},
  "geometry": {"coordinates":[8.860994339,47.2800827026],"type":"Point"}
}