{
  "type": "Feature",
  "properties": {
    "iso:country":"CH",
    "sg:address":"3962",
    "sg:city":"Montana-vermala",
    "sg:classifiers":[
        {
            "category":"Travel",
            "subcategory":"Hotels & Motels",
            "type":"Entertainment"
        }
    ],
    "sg:phone":"+41 32 725 25 77",
    "sg:postcode":"3962",
    "sg:tags":[
        "hotels",
        "mit",
        "restaurant"
    ],
    "wof:name":"H\u00f4tel City Bl\u00e4ttler A. H\u00f4tel-caf\u00e9-rest. City",
    "wof:placetype":"venue"
},
  "geometry": {"coordinates":[6.9349050522,46.9925498962],"type":"Point"}
}