{
  "type": "Feature",
  "properties": {
    "addr:full":"Hartbertstrasse 1 Chur Graubunden 7000",
    "addr:housenumber":"1",
    "addr:postcode":"7000",
    "addr:street":"Hartbertstrasse",
    "iso:country":"CH",
    "sg:address":"Hartbertstrasse 1",
    "sg:city":"Chur",
    "sg:orig_category":"Detailhandel mit B\u00fcchern, Zeitungen, Schreib U Papeteriewaren",
    "sg:postcode":"7000",
    "sg:province":"Graubunden",
    "wof:name":"Bhc-buchhandels Ag",
    "wof:placetype":"venue"
},
  "geometry": {"coordinates":[9.532393,46.852619],"type":"Point"}
}