{
  "type": "Feature",
  "properties": {
    "iso:country":"CH",
    "sg:address":"6390",
    "sg:city":"Engelberg",
    "sg:orig_category":"RESTAURANTS: TEA-ROOMS",
    "sg:postcode":"6390",
    "sg:province":"Obwalden",
    "wof:name":"Feierabend Josef",
    "wof:placetype":"venue"
},
  "geometry": {"coordinates":[8.4227695465,46.8370513916],"type":"Point"}
}