{
  "type": "Feature",
  "properties": {
    "iso:country":"CH",
    "sg:address":"Ecuvillens",
    "sg:city":"Ecuvillens",
    "sg:orig_category":"Detailhandel mit Brot, Back U S\u00fcsswaren Sonstiger Fachdetailhandel mit Nahrungsmitteln, Getr\u00e4nken U ",
    "sg:phone":"+41 26 411 11 28",
    "sg:postcode":"1730",
    "sg:province":"Fribourg",
    "wof:name":"Marcel Barbey",
    "wof:placetype":"venue"
},
  "geometry": {"coordinates":[7.089211,46.757923],"type":"Point"}
}