{
  "type": "Feature",
  "properties": {
    "iso:country":"CH",
    "sg:address":"Usserdorf 57",
    "sg:city":"H\u00e4rkingen",
    "sg:orig_category":"Vermietung U Verpachtung von eigenen Immobilien",
    "sg:phone":"+41 62 389 08 00",
    "sg:postcode":"4624",
    "sg:province":"Solothurn",
    "wof:name":"Wyss Immobilien Und Beteiligungen Ag",
    "wof:placetype":"venue"
},
  "geometry": {"coordinates":[7.8220257759,47.300983429],"type":"Point"}
}