{
  "type": "Feature",
  "properties": {
    "iso:country":"CH",
    "sg:address":"In Der Gyrhalden 9",
    "sg:city":"Urdorf",
    "sg:orig_category":"Sonstige mit der Informatik verbundene T\u00e4tigkeiten",
    "sg:phone":"+41 17364341",
    "sg:postcode":"8902",
    "sg:province":"Z\u00fcrich",
    "wof:name":"Angelsberger M., Edv Analyse Und Beratung",
    "wof:placetype":"venue"
},
  "geometry": {"coordinates":[8.4352941513,47.3854598999],"type":"Point"}
}