{
  "type": "Feature",
  "properties": {
    "iso:country":"CH",
    "sg:address":"Dorfstrasse 1",
    "sg:city":"Sch\u00fcpfen",
    "sg:orig_category":"Arztpraxen",
    "sg:phone":"+41 31 879 06 67",
    "sg:postcode":"3054",
    "sg:province":"Bern",
    "wof:name":"Dr.med.hansulrich Blunier Arzt F.allgemeine Medizin Fmh",
    "wof:placetype":"venue"
},
  "geometry": {"coordinates":[7.378376,47.040577],"type":"Point"}
}