{
  "type": "Feature",
  "properties": {
    "iso:country":"CH",
    "sg:address":"Metzgergasse 20",
    "sg:city":"Aarau",
    "sg:orig_category":"Fahrschulen, Flugschulen",
    "sg:phone":"+41 62 824 38 38",
    "sg:postcode":"5000",
    "sg:province":"Aargau",
    "wof:name":"Autostudio 70 Autofahrschule Der Fahrlehrer-vereinigung",
    "wof:placetype":"venue"
},
  "geometry": {"coordinates":[8.043800354,47.3936386108],"type":"Point"}
}