{
  "type": "Feature",
  "properties": {
    "iso:country":"CH",
    "sg:address":"Solothurnstrasse 14",
    "sg:city":"Ober\u00f6nz",
    "sg:orig_category":"Bauschreinerei Herstellung von Konstruktionsteilen, Fertigbauteilen U Ausbauelementen aus Holz",
    "sg:phone":"+41 62 961 14 49",
    "sg:postcode":"3363",
    "sg:province":"Bern",
    "wof:name":"Schmid Schreinerei Und Innenausbau",
    "wof:placetype":"venue"
},
  "geometry": {"coordinates":[7.692399,47.180698],"type":"Point"}
}