{
  "type": "Feature",
  "properties": {
    "iso:country":"CH",
    "sg:address":"Kirchsteig 14",
    "sg:city":"Wittenbach",
    "sg:orig_category":"Kaminfeger Reinigungsgewerbe",
    "sg:phone":"+41 71 298 48 68",
    "sg:postcode":"9303",
    "wof:name":"Franz Diethelm Kaminfegerbetrieb",
    "wof:placetype":"venue"
},
  "geometry": {"coordinates":[9.3816213608,47.4628715515],"type":"Point"}
}