{
  "type": "Feature",
  "properties": {
    "iso:country":"CH",
    "sg:address":"Rue De La Gare 3",
    "sg:city":"Aigle",
    "sg:orig_category":"Detailhandel mit Radio U Fernsehger\u00e4ten",
    "sg:phone":"+41 24 466 26 11",
    "sg:postcode":"1860",
    "sg:province":"Vaud",
    "wof:name":"Carmelo La Mendola Expert Radio-t\u00e9l\u00e9vision",
    "wof:placetype":"venue"
},
  "geometry": {"coordinates":[6.9685277939,46.31798172],"type":"Point"}
}