{
  "type": "Feature",
  "properties": {
    "iso:country":"CH",
    "sg:address":"Ch.du Pont-du-centenaire 1",
    "sg:city":"Plan-les-ouates",
    "sg:orig_category":"Reiseb\u00fcros U Reiseveranstalter",
    "sg:postcode":"1228",
    "sg:province":"Gen\u00e8ve",
    "wof:name":"Transalp, Andr\u00e9 Et Suzanne Kropf",
    "wof:placetype":"venue"
},
  "geometry": {"coordinates":[6.1034197807,46.1748390198],"type":"Point"}
}