{
  "type": "Feature",
  "properties": {
    "iso:country":"CH",
    "sg:address":"Grossmatte-ost 2 6014 Littau. Postfach",
    "sg:city":"Littau",
    "sg:orig_category":"Informatikschulen Sonstige mit der Informatik verbundene T\u00e4tigkeiten",
    "sg:phone":"+41 41 250 22 24",
    "sg:postcode":"6014",
    "sg:province":"Luzern",
    "wof:name":"Windata Schulung Gmbh Schulung Im Bereich Der Informatik Usw",
    "wof:placetype":"venue"
},
  "geometry": {"coordinates":[8.266330719,47.0486679077],"type":"Point"}
}