{
  "type": "Feature",
  "properties": {
    "iso:country":"CH",
    "sg:address":"Paradiesweg 11",
    "sg:city":"Worb",
    "sg:orig_category":"Kaminfeger",
    "sg:phone":"+41 32 392 35 08",
    "sg:postcode":"3076",
    "sg:province":"Bern",
    "wof:name":"Kurt Schwab Kaminfegermeister",
    "wof:placetype":"venue"
},
  "geometry": {"coordinates":[7.3157129288,47.0305671692],"type":"Point"}
}