{
  "type": "Feature",
  "properties": {
    "iso:country":"CH",
    "sg:address":"Hauptstr. 3",
    "sg:city":"Bennwil",
    "sg:classifiers":[
        {
            "category":"Manufacturing",
            "subcategory":"Motor Vehicles & Parts",
            "type":"Manufacturing & Wholesale Goods"
        }
    ],
    "sg:phone":"+41 61 956 92 92",
    "sg:postcode":"4431",
    "sg:province":"Basel-Landschaft",
    "sg:tags":[
        "engine",
        "machine",
        "engineering",
        "-",
        "mechanical"
    ],
    "wof:name":"Schneto Ag",
    "wof:placetype":"venue"
},
  "geometry": {"coordinates":[7.7868962288,47.4076652527],"type":"Point"}
}