{
  "type": "Feature",
  "properties": {
    "iso:country":"CH",
    "sg:address":"Gerbergasse 7",
    "sg:city":"Zofingen",
    "sg:orig_category":"Detailhandel mit Bekleidung Detailhandel mit S\u00e4uglings U Kinderbekleidung",
    "sg:phone":"+41 62 751 35 40",
    "sg:postcode":"4800",
    "sg:province":"Aargau",
    "wof:name":"Kindermode Zum Schn\u00e4ggehuus",
    "wof:placetype":"venue"
},
  "geometry": {"coordinates":[7.946699,47.287312],"type":"Point"}
}