{
  "type": "Feature",
  "properties": {
    "iso:country":"CH",
    "sg:address":"Usterstrasse 3",
    "sg:city":"M\u00f6nchaltorf",
    "sg:classifiers":[
        {
            "category":"Personal",
            "subcategory":"Sauna",
            "type":"Services"
        }
    ],
    "sg:phone":"+41 19480784",
    "sg:postcode":"8617",
    "sg:province":"Z\u00fcrich",
    "wof:name":"Vreni Hafner Sauna",
    "wof:placetype":"venue"
},
  "geometry": {"coordinates":[8.7213783264,47.3099060059],"type":"Point"}
}