{
  "type": "Feature",
  "properties": {
    "iso:country":"CH",
    "sg:address":"Wieshalde",
    "sg:city":"Baar",
    "sg:orig_category":"Instandhaltung U Reparatur von Automobilen",
    "sg:postcode":"6340",
    "sg:province":"Zug",
    "wof:name":"Garage Herzog G. Ag Automobile-handel, Reparatur Und Servicearbeiten Usw",
    "wof:placetype":"venue"
},
  "geometry": {"coordinates":[8.5417375565,47.1972122192],"type":"Point"}
}