{
  "type": "Feature",
  "properties": {
    "iso:country":"CH",
    "sg:address":"Merkurstrasse 51",
    "sg:city":"Allschwil",
    "sg:orig_category":"Detailhandel mit Pelzwaren",
    "sg:phone":"+41 61 302 90 56",
    "sg:postcode":"4123",
    "sg:province":"Basel-Landschaft",
    "wof:name":"Margrit Gerber Pelzverarbeitung",
    "wof:placetype":"venue"
},
  "geometry": {"coordinates":[7.5596451759,47.5546417236],"type":"Point"}
}