{
  "type": "Feature",
  "properties": {
    "iso:country":"CH",
    "sg:address":"1175",
    "sg:city":"Lavigny",
    "sg:orig_category":"Landwirtschaftliche Genossenschaften",
    "sg:postcode":"1175",
    "sg:province":"Vaud",
    "wof:name":"Coop\u00e9rative D'utilisation De Machines Agricoles",
    "wof:placetype":"venue"
},
  "geometry": {"coordinates":[6.4087700844,46.4994010925],"type":"Point"}
}