{
  "type": "Feature",
  "properties": {
    "iso:country":"CH",
    "sg:address":"Stationsstrasse 89",
    "sg:city":"Rothenburg",
    "sg:orig_category":"Personenbef\u00f6rderung im Linienverkehr zu Land",
    "sg:postcode":"6023",
    "sg:province":"Luzern",
    "wof:name":"Avers Skibetriebs Ag",
    "wof:placetype":"venue"
},
  "geometry": {"coordinates":[-121.4092712402,39.8416595459],"type":"Point"}
}