{
  "type": "Feature",
  "properties": {
    "iso:country":"CH",
    "sg:address":"Grafenauweg 6 6300 Zug. Postfach",
    "sg:city":"Zug",
    "sg:orig_category":"Sonstige Finanzierungsinstitutionen",
    "sg:phone":"+41 41 725 33 11",
    "sg:postcode":"6304",
    "sg:province":"Zug",
    "wof:name":"Asa Environment & Energy Holding Ag",
    "wof:placetype":"venue"
},
  "geometry": {"coordinates":[8.5129060745,47.1741371155],"type":"Point"}
}