{
  "type": "Feature",
  "properties": {
    "iso:country":"CH",
    "sg:address":"Avenue De La Gare 13",
    "sg:city":"Ste-croix",
    "sg:orig_category":"Stukkateurgewerbe, Gipserei U Verputzerei",
    "sg:phone":"+41 24 454 38 25",
    "sg:postcode":"1450",
    "sg:province":"Vaud",
    "wof:name":"Scorti Victor",
    "wof:placetype":"venue"
},
  "geometry": {"coordinates":[6.5007362366,46.8211212158],"type":"Point"}
}