{
  "type": "Feature",
  "properties": {
    "addr:full":"Kapellenstrasse 24 3011 Bern. Postfach 8622 Bern Bern 3001",
    "addr:housenumber":"24",
    "addr:postcode":"3011;postfach 8622 bern;3001",
    "addr:street":"Kapellenstrasse",
    "iso:country":"CH",
    "sg:address":"Kapellenstrasse 24 3011 Bern. Postfach 8622",
    "sg:city":"Bern",
    "sg:orig_category":"Advokaturb\u00fcros",
    "sg:phone":"+41 31 301 73 33",
    "sg:postcode":"3001",
    "sg:province":"Bern",
    "wof:name":"Stucki & Maurer",
    "wof:placetype":"venue"
},
  "geometry": {"coordinates":[7.434031,46.945354],"type":"Point"}
}