{
  "type": "Feature",
  "properties": {
    "iso:country":"CH",
    "sg:address":"Jean-pierre Riat 62a",
    "sg:city":"Chevenez",
    "sg:orig_category":"Nationale Postdienste",
    "sg:phone":"+41 32 476 64 05",
    "sg:postcode":"2906",
    "sg:province":"Jura",
    "wof:name":"La Poste Suisse",
    "wof:placetype":"venue"
},
  "geometry": {"coordinates":[6.9997329712,47.3915519714],"type":"Point"}
}