{
  "type": "Feature",
  "properties": {
    "iso:country":"CH",
    "sg:address":"Hauptstrasse 1 7240 K\u00fcblis. Postfach",
    "sg:city":"K\u00fcblis",
    "sg:orig_category":"Saunas, Solarien, Fitnesszentren U \u00e4hnliches",
    "sg:phone":"+41 81 332 36 33",
    "sg:postcode":"7240",
    "sg:province":"Graubunden",
    "wof:name":"Holiboli Walli Fitness-studio",
    "wof:placetype":"venue"
},
  "geometry": {"coordinates":[9.7695837021,46.9134368896],"type":"Point"}
}