{
  "type": "Feature",
  "properties": {
    "iso:country":"CH",
    "sg:address":"Louis-giroud-strasse 37",
    "sg:city":"Olten",
    "sg:orig_category":"Maschinen-Fabrikation",
    "sg:phone":"+41 71 767 90 50",
    "sg:postcode":"4600",
    "sg:province":"Solothurn",
    "wof:name":"Glessmann Ag",
    "wof:placetype":"venue"
},
  "geometry": {"coordinates":[9.5370931625,47.2944946289],"type":"Point"}
}