{
  "type": "Feature",
  "properties": {
    "iso:country":"CH",
    "sg:address":"Colmarerstrasse 49",
    "sg:city":"Basel",
    "sg:orig_category":"Sportvereine Sch\u00fctzen",
    "sg:postcode":"4055",
    "sg:province":"Basel-Stadt",
    "wof:name":"Bsc Old-boys Schiessektion",
    "wof:placetype":"venue"
},
  "geometry": {"coordinates":[7.5714869499,47.5597610474],"type":"Point"}
}