{
  "type": "Feature",
  "properties": {
    "iso:country":"CH",
    "sg:address":"1977",
    "sg:city":"Icogne",
    "sg:orig_category":"Herstellung von Teppichen",
    "sg:postcode":"1977",
    "sg:province":"Valais",
    "wof:name":"Aymon Jo\u00ebl",
    "wof:placetype":"venue"
},
  "geometry": {"coordinates":[7.438272953,46.2908935547],"type":"Point"}
}