{
  "type": "Feature",
  "properties": {
    "iso:country":"CH",
    "sg:address":"Baumackerstrasse 53",
    "sg:city":"Z\u00fcrich",
    "sg:classifiers":[
        {
            "category":"Home & Garden",
            "subcategory":"Carpets & Floor Coverings",
            "type":"Retail Goods"
        }
    ],
    "sg:phone":"+41 21 651 34 40",
    "sg:postcode":"8050",
    "sg:province":"Z\u00fcrich",
    "sg:tags":[
        "wall",
        "insulating"
    ],
    "wof:name":"Schneider Technique D'isolation Sa",
    "wof:placetype":"venue"
},
  "geometry": {"coordinates":[6.6288890839,46.5719108582],"type":"Point"}
}