{
  "type": "Feature",
  "properties": {
    "iso:country":"CH",
    "sg:address":"Rue De L'avenir 1",
    "sg:city":"Sion",
    "sg:orig_category":"Grosshandel mit B\u00fcromaschinen",
    "sg:phone":"+41 27 323 22 25",
    "sg:postcode":"1950",
    "sg:province":"Valais",
    "wof:name":"Danka Suisse Sa",
    "wof:placetype":"venue"
},
  "geometry": {"coordinates":[7.3446087837,46.2257652283],"type":"Point"}
}