{
  "type": "Feature",
  "properties": {
    "iso:country":"CH",
    "sg:address":"Rue Louis De Savoie 60",
    "sg:city":"Morges",
    "sg:orig_category":"Detailhandel mit Brot, Back U S\u00fcsswaren",
    "sg:phone":"+41 21 801 21 07",
    "sg:postcode":"1110",
    "sg:province":"Vaud",
    "wof:name":"Richard Maier Sa Confiserie",
    "wof:placetype":"venue"
},
  "geometry": {"coordinates":[6.498436,46.508484],"type":"Point"}
}