{
  "type": "Feature",
  "properties": {
    "iso:country":"CH",
    "sg:address":"Krankenhausweg 6",
    "sg:city":"M\u00fcnsingen",
    "sg:orig_category":"Interessenvertretungen",
    "sg:postcode":"3110",
    "sg:province":"Bern",
    "wof:name":"Scheuner-stiftung",
    "wof:placetype":"venue"
},
  "geometry": {"coordinates":[7.566945076,46.8739967346],"type":"Point"}
}