{
  "type": "Feature",
  "properties": {
    "iso:country":"CH",
    "sg:address":"Rotenboden 127a",
    "sg:city":"Triesenberg",
    "sg:orig_category":"Schreibb\u00fcros",
    "sg:phone":"+423 268 41 35",
    "sg:postcode":"9497",
    "wof:name":"Marie-therese Von Halem B\u00fcro-service",
    "wof:placetype":"venue"
},
  "geometry": {"coordinates":[9.5391674042,47.1267280579],"type":"Point"}
}