{
  "type": "Feature",
  "properties": {
    "iso:country":"CH",
    "sg:address":"Village",
    "sg:city":"Troistorrents",
    "sg:orig_category":"RESTAURANTS: TEA-ROOMS",
    "sg:phone":"+41 27 475 12 87",
    "sg:postcode":"1872",
    "sg:province":"Valais",
    "wof:name":"Viaccoz Ren\u00e9",
    "wof:placetype":"venue"
},
  "geometry": {"coordinates":[7.6151399612,46.1528205872],"type":"Point"}
}