{
  "type": "Feature",
  "properties": {
    "iso:country":"CH",
    "sg:address":"Stegweg 1",
    "sg:city":"Siebnen",
    "sg:orig_category":"Non-Classified Establishments",
    "sg:postcode":"8854",
    "sg:province":"Schwyz",
    "wof:name":"Petra Koller Skin Care",
    "wof:placetype":"venue"
},
  "geometry": {"coordinates":[8.8894844055,47.1775665283],"type":"Point"}
}