{
  "type": "Feature",
  "properties": {
    "iso:country":"CH",
    "sg:address":"Hofwiesenstrasse 18 8057 Z\u00fcrich. Postfach 206",
    "sg:city":"Z\u00fcrich",
    "sg:orig_category":"Berufliche Weiterbildung, Erwachsenenbildung",
    "sg:phone":"+41 21 637 21 51",
    "sg:postcode":"8042",
    "sg:province":"Z\u00fcrich",
    "wof:name":"Kuoni Voyages Sa Centre De Formation",
    "wof:placetype":"venue"
},
  "geometry": {"coordinates":[6.580886,46.535789],"type":"Point"}
}