{
  "type": "Feature",
  "properties": {
    "iso:country":"CH",
    "sg:address":"Cours De Rive 11",
    "sg:city":"Gen\u00e8ve",
    "sg:orig_category":"Datenverarbeitungsdienste Sonstige mit der Informatik verbundene T\u00e4tigkeiten",
    "sg:phone":"+41 56 631 62 10",
    "sg:postcode":"1204",
    "sg:province":"Gen\u00e8ve",
    "wof:name":"Edv Beratung Casutt Gmbh",
    "wof:placetype":"venue"
},
  "geometry": {"coordinates":[8.348666,47.353958],"type":"Point"}
}