{
  "type": "Feature",
  "properties": {
    "iso:country":"CH",
    "sg:address":"T\u00f6ssriederenstrasse 15",
    "sg:city":"Eglisau",
    "sg:orig_category":"Kauf U Verkauf von Immobilien auf eigene Rechnung Vermittlung von Immobilien",
    "sg:phone":"+41 18674236",
    "sg:postcode":"8193",
    "sg:province":"Z\u00fcrich",
    "wof:name":"Eggler Hans J. + Partner",
    "wof:placetype":"venue"
},
  "geometry": {"coordinates":[8.5428819656,47.5667724609],"type":"Point"}
}