{
  "type": "Feature",
  "properties": {
    "iso:country":"CH",
    "sg:address":"Aubrigstrasse 7",
    "sg:city":"Siebnen",
    "sg:orig_category":"Datenverarbeitungsdienste Softwareentwicklung U beratung",
    "sg:phone":"+41 71 274 02 80",
    "sg:postcode":"8854",
    "sg:province":"Schwyz",
    "wof:name":"Bluematic Ag",
    "wof:placetype":"venue"
},
  "geometry": {"coordinates":[9.335341,47.40752],"type":"Point"}
}