{
  "type": "Feature",
  "properties": {
    "iso:country":"CH",
    "sg:address":"Via Alpsu 13",
    "sg:city":"Sedrun",
    "sg:orig_category":"G\u00fcterbef\u00f6rderung im Strassenverkehr",
    "sg:phone":"+41 81 949 12 20",
    "sg:postcode":"7188",
    "sg:province":"Graubunden",
    "wof:name":"Benedetg Monn Transporte & Camionnage",
    "wof:placetype":"venue"
},
  "geometry": {"coordinates":[8.7807159424,46.6815910339],"type":"Point"}
}