{
  "type": "Feature",
  "properties": {
    "iso:country":"CH",
    "sg:address":"Aegertenstrasse 53",
    "sg:city":"Bern",
    "sg:orig_category":"Hardwareberatung",
    "sg:phone":"+41 31 352 80 58",
    "sg:postcode":"3005",
    "sg:province":"Bern",
    "wof:name":"Leong T.y. & Co Edv-dienstleistungen",
    "wof:placetype":"venue"
},
  "geometry": {"coordinates":[7.4476280212,46.9387054443],"type":"Point"}
}