{
  "type": "Feature",
  "properties": {
    "addr:full":"Bielstrasse 21 Selzach Solothurn 2545",
    "addr:housenumber":"21",
    "addr:postcode":"2545",
    "addr:street":"Bielstrasse",
    "iso:country":"CH",
    "sg:address":"Bielstrasse 21",
    "sg:city":"Selzach",
    "sg:orig_category":"Autogaragen",
    "sg:phone":"+41 32 641 13 69",
    "sg:postcode":"2545",
    "sg:province":"Solothurn",
    "wof:name":"Martin Meyer Ueberland-garage",
    "wof:placetype":"venue"
},
  "geometry": {"coordinates":[7.452448,47.202007],"type":"Point"}
}