{
  "type": "Feature",
  "properties": {
    "iso:country":"CH",
    "sg:address":"Weichlenstrasse 7",
    "sg:city":"Ebikon",
    "sg:orig_category":"Non-Classified Establishments",
    "sg:postcode":"6030",
    "sg:province":"Luzern",
    "wof:name":"Frewal Ag Schulung F\u00fcr Personalf\u00f6rderung & Beratung",
    "wof:placetype":"venue"
},
  "geometry": {"coordinates":[-91.30876159669999,42.9951286316],"type":"Point"}
}