{
  "type": "Feature",
  "properties": {
    "iso:country":"CH",
    "sg:address":"Sarmenstorferstrasse 31",
    "sg:city":"Fahrwangen",
    "sg:orig_category":"Herstellung von Metallerzeugnissen ohne Maschinenbau Maschinenbau",
    "sg:phone":"+41 56 667 41 11",
    "sg:postcode":"5615",
    "sg:province":"Aargau",
    "wof:name":"Graber Ag",
    "wof:placetype":"venue"
},
  "geometry": {"coordinates":[8.245267868,47.2993583679],"type":"Point"}
}