{
  "type": "Feature",
  "properties": {
    "iso:country":"CH",
    "sg:address":"Raft",
    "sg:city":"Sigriswil",
    "sg:orig_category":"Sportvereine Turnen Vereine Damen",
    "sg:phone":"+41 33 251 24 84",
    "sg:postcode":"3655",
    "sg:province":"Bern",
    "wof:name":"Frauenriege Stv Sigriswil",
    "wof:placetype":"venue"
},
  "geometry": {"coordinates":[7.7093701363,46.7170600891],"type":"Point"}
}