{
  "type": "Feature",
  "properties": {
    "iso:country":"CH",
    "sg:address":"Bahnhofstrasse 26",
    "sg:city":"Steinen",
    "sg:orig_category":"Pulvermetallurgie Schlossereien Schmieden, Pressen, Stanzen U Profilwalzen von Metallen",
    "sg:phone":"+41 41 832 15 46",
    "sg:postcode":"6422",
    "sg:province":"Schwyz",
    "wof:name":"Robert Schorno Schlosserei & Hammerwerk",
    "wof:placetype":"venue"
},
  "geometry": {"coordinates":[8.6085271835,47.0484237671],"type":"Point"}
}