{
  "type": "Feature",
  "properties": {
    "iso:country":"CH",
    "sg:address":"Stichweg 6",
    "sg:city":"M\u00f6hlin",
    "sg:orig_category":"Sportvereine Turnen",
    "sg:phone":"+41 61 851 45 63",
    "sg:postcode":"4313",
    "sg:province":"Aargau",
    "wof:name":"Turnverein Mumpf",
    "wof:placetype":"venue"
},
  "geometry": {"coordinates":[7.8482298851,47.55311203],"type":"Point"}
}