{
  "type": "Feature",
  "properties": {
    "iso:country":"CH",
    "sg:address":"Hauptstrasse 45a 6260 Reiden. Postfach 523",
    "sg:city":"Reiden",
    "sg:orig_category":"Herstellung von sonstigen chemischen Erzeugnissen",
    "sg:phone":"+41 62 758 57 57",
    "sg:postcode":"6260",
    "sg:province":"Luzern",
    "wof:name":"Shs Steiert R. Gmbh",
    "wof:placetype":"venue"
},
  "geometry": {"coordinates":[7.971387,47.245941],"type":"Point"}
}