{
  "type": "Feature",
  "properties": {
    "iso:country":"CH",
    "sg:address":"6926",
    "sg:city":"Montagnola",
    "sg:orig_category":"Non-Classified Establishments",
    "sg:phone":"+41 91 960 59 00",
    "sg:postcode":"6926",
    "sg:province":"Ticino",
    "wof:name":"Ilapak Holding Sa",
    "wof:placetype":"venue"
},
  "geometry": {"coordinates":[8.9168901443,45.9819107056],"type":"Point"}
}