{
  "type": "Feature",
  "properties": {
    "iso:country":"CH",
    "sg:address":"Chemin De La Baconni\u00e8re 53",
    "sg:city":"Boudry",
    "sg:orig_category":"Feinmechanische and Pr\u00e4zisions Werkst\u00e4tten",
    "sg:phone":"+41 32 842 11 55",
    "sg:postcode":"2017",
    "sg:province":"Neuch\u00e2tel",
    "wof:name":"Reinaldo Mamani Atelier M\u00e9canique",
    "wof:placetype":"venue"
},
  "geometry": {"coordinates":[6.8404397964,46.9570121765],"type":"Point"}
}