{
  "type": "Feature",
  "properties": {
    "iso:country":"CH",
    "sg:address":"6370 Stans. Postfach 125",
    "sg:city":"Stans",
    "sg:orig_category":"Vereine Gesang",
    "sg:phone":"+41 41 932 40 32",
    "sg:postcode":"6371",
    "sg:province":"Nidwalden",
    "wof:name":"M\u00e4nnerchor Stans",
    "wof:placetype":"venue"
},
  "geometry": {"coordinates":[8.365904808,46.9572486877],"type":"Point"}
}