{
  "type": "Feature",
  "properties": {
    "iso:country":"CH",
    "sg:address":"Missionsstrasse 15 4000 Basel. Postfach",
    "sg:city":"Basel",
    "sg:orig_category":"Softwareentwicklung U beratung",
    "sg:postcode":"4051",
    "sg:province":"Basel-Stadt",
    "wof:name":"Requiris Is Management Gmbh",
    "wof:placetype":"venue"
},
  "geometry": {"coordinates":[7.5794429779,47.5587806702],"type":"Point"}
}