{
  "type": "Feature",
  "properties": {
    "iso:country":"CH",
    "sg:address":"Wellhauserweg 50 8500 Frauenfeld. Postfach",
    "sg:city":"Frauenfeld",
    "sg:orig_category":"Detailhandel mit Bekleidung",
    "sg:postcode":"8500",
    "sg:province":"Thurgau",
    "wof:name":"Scherrer Herrenmode Ag.",
    "wof:placetype":"venue"
},
  "geometry": {"coordinates":[8.918425,47.565727],"type":"Point"}
}