{
  "type": "Feature",
  "properties": {
    "iso:country":"CH",
    "sg:address":"Corso San Gottardo 35",
    "sg:city":"Chiasso",
    "sg:orig_category":"Reiseb\u00fcros U Reiseveranstalter",
    "sg:postcode":"6830",
    "sg:province":"Ticino",
    "wof:name":"Agroh\u00f4tel S\u00e0rl",
    "wof:placetype":"venue"
},
  "geometry": {"coordinates":[6.8742251396,47.0492553711],"type":"Point"}
}