{
  "type": "Feature",
  "properties": {
    "iso:country":"CH",
    "sg:address":"Delfterstrasse 40 5000 Aarau. Postfach",
    "sg:city":"Aarau",
    "sg:orig_category":"Wohnheime",
    "sg:postcode":"5004",
    "sg:province":"Aargau",
    "wof:name":"Ott Hans Gmbh",
    "wof:placetype":"venue"
},
  "geometry": {"coordinates":[8.0622529984,47.3983421326],"type":"Point"}
}