{
  "type": "Feature",
  "properties": {
    "iso:country":"CH",
    "sg:address":"Bahnhofplatz 8 7000 Chur. Postfach",
    "sg:city":"Chur",
    "sg:orig_category":"Detailhandel mit Waren verschiedener Art, Hauptrichtung Nahrungsmittel",
    "sg:postcode":"7000",
    "sg:province":"Graubunden",
    "wof:name":"St\u00e4dtli - Markt Genossenschaft",
    "wof:placetype":"venue"
},
  "geometry": {"coordinates":[9.5298366547,46.8529434204],"type":"Point"}
}