{
  "type": "Feature",
  "properties": {
    "iso:country":"CH",
    "sg:address":"Brambergstrasse 38",
    "sg:city":"Neuenegg",
    "sg:orig_category":"Detailhandel mit Textilien Herstellung von Reiseartikeln, Leder U Sattlerwaren",
    "sg:phone":"+41 31 741 09 11",
    "sg:postcode":"3176",
    "sg:province":"Bern",
    "wof:name":"Walter Badertscher Sattlerei & Bettwaren",
    "wof:placetype":"venue"
},
  "geometry": {"coordinates":[7.2780308723,46.9062652588],"type":"Point"}
}