{
  "type": "Feature",
  "properties": {
    "iso:country":"CH",
    "sg:address":"Sous-gay Chemin 6",
    "sg:city":"Commugny",
    "sg:orig_category":"Unclassifiable Establishments",
    "sg:phone":"+41 22 776 80 29",
    "sg:postcode":"1291",
    "sg:province":"Vaud",
    "wof:name":"L\u00e9manjardin S\u00e0rl",
    "wof:placetype":"venue"
},
  "geometry": {"coordinates":[6.1803150177,46.317401886],"type":"Point"}
}