{
  "type": "Feature",
  "properties": {
    "iso:country":"CH",
    "sg:address":"Rue Du Lac 54 1815 Clarens. Postfach",
    "sg:city":"Clarens",
    "sg:orig_category":"Herstellung von elektrischen Lampen U Leuchten",
    "sg:phone":"+41 21 964 64 20",
    "sg:postcode":"1815",
    "sg:province":"Vaud",
    "wof:name":"Artina S\u00e0rl Fabr.d'abat-jour",
    "wof:placetype":"venue"
},
  "geometry": {"coordinates":[6.8959889412,46.4403152466],"type":"Point"}
}