{
  "type": "Feature",
  "properties": {
    "iso:country":"CH",
    "sg:address":"Chemin Des Buclines 16a",
    "sg:city":"Ch\u00eane-bougeries",
    "sg:orig_category":"Fahrschulen, Flugschulen",
    "sg:phone":"+41 22 349 09 69",
    "sg:postcode":"1224",
    "sg:province":"Gen\u00e8ve",
    "wof:name":"Mario Bressani Auto-\u00e9cole",
    "wof:placetype":"venue"
},
  "geometry": {"coordinates":[6.1932630539,46.2060127258],"type":"Point"}
}