{
  "type": "Feature",
  "properties": {
    "iso:country":"CH",
    "sg:address":"Kriesbachstrasse 7",
    "sg:city":"Wallisellen",
    "sg:orig_category":"Sonstiger Grosshandel",
    "sg:phone":"+41 41 710 35 70",
    "sg:postcode":"8304",
    "sg:province":"Z\u00fcrich",
    "wof:name":"Technophil Ag",
    "wof:placetype":"venue"
},
  "geometry": {"coordinates":[8.6129751205,47.409576416],"type":"Point"}
}