{
  "type": "Feature",
  "properties": {
    "addr:full":"Hintereggstrasse 4 Achseten Bern 3725",
    "addr:housenumber":"4",
    "addr:postcode":"3725",
    "addr:street":"Hintereggstrasse",
    "iso:country":"CH",
    "sg:address":"Hintereggstrasse 4",
    "sg:city":"Achseten",
    "sg:orig_category":"Bauspenglerei Sanit\u00e4rinstallation U Spenglerei",
    "sg:phone":"+41 33 733 11 21",
    "sg:postcode":"3725",
    "sg:province":"Bern",
    "wof:name":"Ernst W\u00e4lti Luft-& Klimatechnik",
    "wof:placetype":"venue"
},
  "geometry": {"coordinates":[7.437435,46.46125],"type":"Point"}
}