{
  "type": "Feature",
  "properties": {
    "iso:country":"CH",
    "sg:address":"Schulhausstrasse 1",
    "sg:city":"Auw",
    "sg:orig_category":"Landesverteidigung, Sozialversicherung \u00d6ffentliche Verwaltung",
    "sg:phone":"+41 56 668 11 36",
    "sg:postcode":"5644",
    "sg:province":"Aargau",
    "wof:name":"Zivilschutzstelle Auw",
    "wof:placetype":"venue"
},
  "geometry": {"coordinates":[8.366353035,47.2100448608],"type":"Point"}
}