{
  "type": "Feature",
  "properties": {
    "iso:country":"CH",
    "sg:address":"H\u00f6heweg 15",
    "sg:city":"Interlaken",
    "sg:orig_category":"Erschliessung von Grundst\u00fccken",
    "sg:postcode":"3800",
    "sg:province":"Bern",
    "wof:name":"Wohnbaugenossenschaft Postgasse Interlaken",
    "wof:placetype":"venue"
},
  "geometry": {"coordinates":[7.8554120064,46.6854095459],"type":"Point"}
}