{
  "type": "Feature",
  "properties": {
    "iso:country":"CH",
    "sg:address":"Hauptstrasse 2",
    "sg:city":"Laufen",
    "sg:orig_category":"Forst\u00e4mter",
    "sg:phone":"+41 61 761 63 75",
    "sg:postcode":"4242",
    "sg:province":"Basel-Landschaft",
    "wof:name":"Kreisforstamt Laufen",
    "wof:placetype":"venue"
},
  "geometry": {"coordinates":[7.5006670952,47.4210357666],"type":"Point"}
}