{
  "type": "Feature",
  "properties": {
    "iso:country":"CH",
    "sg:address":"Jubil\u00e4umsstrasse 93 3005 Bern. Postfach 1065",
    "sg:city":"Bern",
    "sg:orig_category":"Konsulate",
    "sg:phone":"+41 31 357 70 11",
    "sg:postcode":"3001",
    "sg:province":"Bern",
    "wof:name":"Ambassade Des Etats-unis D'am\u00e9rique",
    "wof:placetype":"venue"
},
  "geometry": {"coordinates":[7.4466171265,46.9358978271],"type":"Point"}
}