{
  "type": "Feature",
  "properties": {
    "iso:country":"CH",
    "sg:address":"Vorstadt 45",
    "sg:city":"Schaffhausen",
    "sg:classifiers":[
        {
            "category":"Restaurant",
            "type":"Food & Drink"
        }
    ],
    "sg:phone":"+41 52 625 81 10",
    "sg:postcode":"8200",
    "sg:province":"Schaffhausen",
    "wof:name":"Restaurant Kleinen K\u00e4fig",
    "wof:placetype":"venue"
},
  "geometry": {"coordinates":[8.6346940994,47.6989212036],"type":"Point"}
}