{
  "type": "Feature",
  "properties": {
    "iso:country":"CH",
    "sg:address":"Lorrainestrasse 6a 3013 Bern. Postfach",
    "sg:city":"Bern",
    "sg:orig_category":"Handel mit Motorr\u00e4dern, Teilen U Zubeh\u00f6r Instandhaltung U Reparatur von Motorr\u00e4dern",
    "sg:phone":"+41 79 204 62 11",
    "sg:postcode":"3013",
    "sg:province":"Bern",
    "wof:name":"Velokurierladen Bern Gmbh Fahrradgesch\u00e4ft. Zweir\u00e4der; Handel, Reparatur Usw.",
    "wof:placetype":"venue"
},
  "geometry": {"coordinates":[7.4454431534,46.9552536011],"type":"Point"}
}