{
  "type": "Feature",
  "properties": {
    "iso:country":"CH",
    "sg:address":"Rue Du Lac 126bis 1820 Montreux. Postfach",
    "sg:city":"Clarens",
    "sg:orig_category":"Architektur U Ingenieurb\u00fcros",
    "sg:postcode":"1815",
    "sg:province":"Vaud",
    "wof:name":"Bureau Esr T\u00e4schler.",
    "wof:placetype":"venue"
},
  "geometry": {"coordinates":[6.901775,46.44104],"type":"Point"}
}