{
  "type": "Feature",
  "properties": {
    "iso:country":"CH",
    "sg:address":"Sur Les C\u00f4tes 16 2950 Courgenay. Postfach",
    "sg:city":"Courgenay",
    "sg:orig_category":"Herstellung von elektronischen Bauelementen",
    "sg:phone":"+41 79 251 04 34",
    "sg:postcode":"2950",
    "sg:province":"Jura",
    "wof:name":"Hanser Philippe Mat\u00e9riel \u00e9lectronique Et Informatique Etc.; D\u00e9velopp., Commercialisation",
    "wof:placetype":"venue"
},
  "geometry": {"coordinates":[7.1145792007,47.4086685181],"type":"Point"}
}