{
  "type": "Feature",
  "properties": {
    "iso:country":"CH",
    "sg:address":"Eichh\u00f6lzlistrasse 18",
    "sg:city":"Glattfelden",
    "sg:orig_category":"Sonstiger spezialisierter Hoch U Tiefbau",
    "sg:phone":"+41 18672480",
    "sg:postcode":"8192",
    "sg:province":"Z\u00fcrich",
    "wof:name":"Lombardi C. Gmbh",
    "wof:placetype":"venue"
},
  "geometry": {"coordinates":[8.5058670044,47.5557022095],"type":"Point"}
}