{
  "type": "Feature",
  "properties": {
    "iso:country":"CH",
    "sg:address":"Leimstrasse 19",
    "sg:city":"Vordemwald",
    "sg:orig_category":"Politische Parteien CVP",
    "sg:phone":"+41 56 222 97 97",
    "sg:postcode":"4803",
    "sg:province":"Aargau",
    "wof:name":"Cvp Ortsgruppe Strengelbach",
    "wof:placetype":"venue"
},
  "geometry": {"coordinates":[7.9019379616,47.2720184326],"type":"Point"}
}