{
  "type": "Feature",
  "properties": {
    "iso:country":"CH",
    "sg:address":"Boulevard De Grancy 19a",
    "sg:city":"Lausanne",
    "sg:orig_category":"Herstellung von Hebezeugen U F\u00f6rdermitteln Herstellung von sonstigen elektrischen Ausr\u00fcstungen",
    "sg:phone":"+41 21 617 72 60",
    "sg:postcode":"1006",
    "sg:province":"Vaud",
    "wof:name":"Daimlerchrysler Rail Systems (schweiz) Ag",
    "wof:placetype":"venue"
},
  "geometry": {"coordinates":[6.6293449402,46.515247345],"type":"Point"}
}