{
  "type": "Feature",
  "properties": {
    "addr:full":"Boulevard Paderewski 12 Vevey Vaud 1800",
    "addr:housenumber":"12",
    "addr:postcode":"1800",
    "addr:street":"Boulevard Paderewski",
    "iso:country":"CH",
    "sg:address":"Boulevard Paderewski 12",
    "sg:city":"Vevey",
    "sg:orig_category":"Detailhandel mit Brot, Back U S\u00fcsswaren",
    "sg:phone":"+41 21 922 50 56",
    "sg:postcode":"1800",
    "sg:province":"Vaud",
    "wof:name":"Marina Pasini Boulangerie & P\u00e2tisserie",
    "wof:placetype":"venue"
},
  "geometry": {"coordinates":[6.854033,46.46159],"type":"Point"}
}