{
  "type": "Feature",
  "properties": {
    "iso:country":"CH",
    "sg:address":"Piller Route Andr\u00e9 21",
    "sg:city":"Givisiez",
    "sg:orig_category":"Herstellung von K\u00fcchenm\u00f6beln",
    "sg:postcode":"1762",
    "sg:province":"Fribourg",
    "wof:name":"Cuisines De Charme S\u00e0rl Cuisines Etc.; Construction, Am\u00e9nagement",
    "wof:placetype":"venue"
},
  "geometry": {"coordinates":[7.1634221077,46.6216278076],"type":"Point"}
}