{
  "type": "Feature",
  "properties": {
    "iso:country":"CH",
    "sg:address":"F\u00f6hrenstrasse 33",
    "sg:city":"Schaffhausen",
    "sg:orig_category":"Detailhandel mit Getr\u00e4nken Detailhandel mit Waren verschiedener Art, Hauptrichtung Nahrungsmittel",
    "sg:phone":"+41 31 971 08 74",
    "sg:postcode":"8200",
    "sg:province":"Schaffhausen",
    "wof:name":"Alfred Linder Milchhandlung",
    "wof:placetype":"venue"
},
  "geometry": {"coordinates":[7.4136447906,46.9087715149],"type":"Point"}
}