{
  "type": "Feature",
  "properties": {
    "iso:country":"CH",
    "sg:address":"Moosstrasse 2",
    "sg:city":"Koppigen",
    "sg:orig_category":"Bauschreinerei Herstellung von M\u00f6beln verschiedener Art",
    "sg:phone":"+41 34 413 15 31",
    "sg:postcode":"3425",
    "sg:province":"Bern",
    "wof:name":"Pfister Holzwerkstatt",
    "wof:placetype":"venue"
},
  "geometry": {"coordinates":[7.60206,47.13131],"type":"Point"}
}