{
  "type": "Feature",
  "properties": {
    "iso:country":"CH",
    "sg:address":"G\u00e4sseli 5",
    "sg:city":"Berneck",
    "sg:orig_category":"Vereine Geselligkeit",
    "sg:postcode":"9442",
    "sg:province":"St. Gallen",
    "wof:name":"Verein Ehem.sekundarsch\u00fcler Berneck Vesber",
    "wof:placetype":"venue"
},
  "geometry": {"coordinates":[9.6101703644,47.4258956909],"type":"Point"}
}