{
  "type": "Feature",
  "properties": {
    "iso:country":"CH",
    "sg:address":"Saint-julien Route De 276",
    "sg:city":"Perly",
    "sg:orig_category":"Instandhaltung U Reparatur von Automobilen",
    "sg:phone":"+41 22 771 10 06",
    "sg:postcode":"1258",
    "sg:province":"Gen\u00e8ve",
    "wof:name":"Perly Automobiles, Barman M.",
    "wof:placetype":"venue"
},
  "geometry": {"coordinates":[6.0884399414,46.1579589844],"type":"Point"}
}