{
  "type": "Feature",
  "properties": {
    "iso:country":"CH",
    "sg:address":"7557",
    "sg:city":"Vn\u00e0",
    "sg:orig_category":"Museen",
    "sg:phone":"+41 55 246 12 03",
    "sg:postcode":"7557",
    "sg:province":"Graubunden",
    "wof:name":"Heimatmuseum Wald",
    "wof:placetype":"venue"
},
  "geometry": {"coordinates":[8.9413003922,47.2884101868],"type":"Point"}
}