{
  "type": "Feature",
  "properties": {
    "iso:country":"CH",
    "sg:address":"Seestrasse 34",
    "sg:city":"Zollikon",
    "sg:orig_category":"Sonstiger spezialisierter Hoch U Tiefbau",
    "sg:phone":"+41 12523500",
    "sg:postcode":"8702",
    "sg:province":"Z\u00fcrich",
    "wof:name":"Armafer Armierungs Ag",
    "wof:placetype":"venue"
},
  "geometry": {"coordinates":[8.5674161911,47.3404769897],"type":"Point"}
}