{
  "type": "Feature",
  "properties": {
    "iso:country":"CH",
    "sg:address":"Arnold Baumgartnerstrasse 11",
    "sg:city":"Grenchen",
    "sg:classifiers":[
        {
            "category":"Banks & Credit Unions",
            "subcategory":"Financial Services",
            "type":"Services"
        }
    ],
    "sg:phone":"+41 32 653 09 03",
    "sg:postcode":"2540",
    "sg:province":"Solothurn",
    "sg:tags":[
        "cutting",
        "gear"
    ],
    "wof:name":"Rolla Microgear Ag",
    "wof:placetype":"venue"
},
  "geometry": {"coordinates":[7.3883171082,47.2019882202],"type":"Point"}
}