{
  "type": "Feature",
  "properties": {
    "iso:country":"CH",
    "sg:address":"Effingerstrasse 14 3011 Bern. Postfach",
    "sg:city":"Bern",
    "sg:orig_category":"Saunas, Solarien, Fitnesszentren U \u00e4hnliches",
    "sg:postcode":"3005",
    "sg:province":"Bern",
    "wof:name":"Gymnastikstudio Bieri R.",
    "wof:placetype":"venue"
},
  "geometry": {"coordinates":[9.0421457291,47.4557304382],"type":"Point"}
}