{
  "type": "Feature",
  "properties": {
    "iso:country":"CH",
    "sg:address":"Friedmattstrasse 14",
    "sg:city":"Reiden",
    "sg:orig_category":"Grosshandel mit Werkzeugmaschinen Mechanische Werkst\u00e4tten",
    "sg:phone":"+41 62 758 30 18",
    "sg:postcode":"6260",
    "sg:province":"Luzern",
    "wof:name":"Pr\u00e4zisions-schaberei Sch\u00e4rli",
    "wof:placetype":"venue"
},
  "geometry": {"coordinates":[7.9689459801,47.2437667847],"type":"Point"}
}