{
  "type": "Feature",
  "properties": {
    "iso:country":"CH",
    "sg:address":"Rue De Vevey 1630 Bulle. Postfach",
    "sg:city":"Bulle",
    "sg:orig_category":"Allgemeiner Hoch U Tiefbau",
    "sg:postcode":"1630",
    "sg:province":"Fribourg",
    "wof:name":"Entreprise De G\u00e9nie Civil S.a. Etudes Et Travaux Se Rapportant Au G\u00e9nie Civil",
    "wof:placetype":"venue"
},
  "geometry": {"coordinates":[7.054282,46.61599],"type":"Point"}
}