{
  "type": "Feature",
  "properties": {
    "iso:country":"CH",
    "sg:address":"Flurweg 3",
    "sg:city":"Wettingen",
    "sg:orig_category":"Sportvereine Eissport Curling",
    "sg:phone":"+41 31 839 05 98",
    "sg:postcode":"5430",
    "sg:province":"Aargau",
    "wof:name":"Curling Club Worb",
    "wof:placetype":"venue"
},
  "geometry": {"coordinates":[7.5609722137,46.9281806946],"type":"Point"}
}