{
  "type": "Feature",
  "properties": {
    "iso:country":"CH",
    "sg:address":"La Ferme",
    "sg:city":"Montcherand",
    "sg:orig_category":"Herstellung von Seifen, Wasch U Reinigungsmitteln",
    "sg:postcode":"1354",
    "sg:province":"Vaud",
    "wof:name":"Neves Guilherme",
    "wof:placetype":"venue"
},
  "geometry": {"coordinates":[6.5100951195,46.7321853638],"type":"Point"}
}