{
  "type": "Feature",
  "properties": {
    "iso:country":"CH",
    "sg:address":"Rue De Neuch\u00e2tel 11a",
    "sg:city":"Peseux",
    "sg:orig_category":"Detektivb\u00fcros U \u00dcberwachung",
    "sg:phone":"+41 32 731 19 34",
    "sg:postcode":"2034",
    "sg:province":"Neuch\u00e2tel",
    "wof:name":"D\u00e9tect-phil Philippe Dahinden",
    "wof:placetype":"venue"
},
  "geometry": {"coordinates":[6.8926610947,46.9881858826],"type":"Point"}
}