{
  "type": "Feature",
  "properties": {
    "iso:country":"CH",
    "sg:address":"Kastanienbaumstrasse 5",
    "sg:city":"Horw",
    "sg:orig_category":"Herstellung von keramischen Wand U Bodenfliesen U platten Verlegen von Fliesen U Platten",
    "sg:phone":"+41 41 340 21 61",
    "sg:postcode":"6048",
    "sg:province":"Luzern",
    "wof:name":"Bacchetta Baukeramik Gmbh",
    "wof:placetype":"venue"
},
  "geometry": {"coordinates":[8.3089923859,47.0236778259],"type":"Point"}
}