{
  "type": "Feature",
  "properties": {
    "iso:country":"CH",
    "sg:address":"Chemin Des Crusilles",
    "sg:city":"Valeyres-montagny",
    "sg:orig_category":"Organisationen des Gesundheitswesen",
    "sg:phone":"+41 24 445 26 48",
    "sg:postcode":"1441",
    "sg:province":"Vaud",
    "wof:name":"St\u00e9 Des Samaritains Grandson",
    "wof:placetype":"venue"
},
  "geometry": {"coordinates":[6.6114859581,46.7971954346],"type":"Point"}
}