{
  "type": "Feature",
  "properties": {
    "iso:country":"CH",
    "sg:address":"L\u00e4ndli 142",
    "sg:city":"Olsberg",
    "sg:orig_category":"Herstellung von Ger\u00e4ten der Elektrizit\u00e4tserzeugung, -verteilung u.\u00e4. -Herstellung von elektronischen",
    "sg:phone":"+41 61 841 19 90",
    "sg:postcode":"4305",
    "sg:province":"Aargau",
    "wof:name":"Ueli Leuenberger Industrielle Automation",
    "wof:placetype":"venue"
},
  "geometry": {"coordinates":[7.7820611,47.5210037231],"type":"Point"}
}