{
  "type": "Feature",
  "properties": {
    "iso:country":"CH",
    "sg:address":"Gerbergasse 14 4001 Basel. Postfach 459",
    "sg:city":"Basel",
    "sg:classifiers":[
        {
            "category":"Professional",
            "subcategory":"Employment Agencies",
            "type":"Services"
        }
    ],
    "sg:phone":"+41 61 260 92 22",
    "sg:postcode":"4001",
    "sg:province":"Basel-Stadt",
    "sg:tags":[
        "personal",
        "u",
        "stellenvermittlung"
    ],
    "wof:name":"Planova Human Capital Ag Stellenvermittlung Zweigniederlassung Basel",
    "wof:placetype":"venue"
},
  "geometry": {"coordinates":[7.587993145,47.5573005676],"type":"Point"}
}