{
  "type": "Feature",
  "properties": {
    "iso:country":"CH",
    "sg:address":"Feldhofstrasse 22",
    "sg:city":"Weinfelden",
    "sg:orig_category":"Grosshandel mit Bekleidung Handelsvermittlung von Textilien, Bekleidung, Schuhen U Lederwaren",
    "sg:phone":"+41 71 622 59 02",
    "sg:postcode":"8570",
    "sg:province":"Thurgau",
    "wof:name":"Vestilo Handelsagentur Karl A.herzog & Sohn",
    "wof:placetype":"venue"
},
  "geometry": {"coordinates":[9.1112947464,47.5640296936],"type":"Point"}
}