{
  "type": "Feature",
  "properties": {
    "iso:country":"CH",
    "sg:address":"Zelgstrasse 71 3661 Uetendorf. Postfach",
    "sg:city":"Uetendorf",
    "sg:orig_category":"Non-Classified Establishments",
    "sg:postcode":"3661",
    "sg:province":"Bern",
    "wof:name":"Aaa Ambulantes Augenzentrum Altst\u00e4tten Ag",
    "wof:placetype":"venue"
},
  "geometry": {"coordinates":[9.5417413712,47.3815765381],"type":"Point"}
}