{
  "type": "Feature",
  "properties": {
    "iso:country":"CH",
    "sg:address":"Chemin Fleurettes 6",
    "sg:city":"Chavornay",
    "sg:orig_category":"Stukkateurgewerbe, Gipserei U Verputzerei",
    "sg:phone":"+41 24 441 16 16",
    "sg:postcode":"1373",
    "sg:province":"Vaud",
    "wof:name":"Alain Besan\u00e7on Gypserie & Peinture",
    "wof:placetype":"venue"
},
  "geometry": {"coordinates":[6.5744948387,46.7086601257],"type":"Point"}
}