{
  "type": "Feature",
  "properties": {
    "iso:country":"CH",
    "sg:address":"Alpenstrasse 1",
    "sg:city":"Zug",
    "sg:orig_category":"Non-Classified Establishments",
    "sg:phone":"+41 41 726 23 62",
    "sg:postcode":"6300",
    "sg:province":"Zug",
    "wof:name":"Ptl Holdings Luxembourg S\u00e0rl, Luxemburg, Zug Branch/switzerland",
    "wof:placetype":"venue"
},
  "geometry": {"coordinates":[8.5137405396,47.1711502075],"type":"Point"}
}