{
  "type": "Feature",
  "properties": {
    "iso:country":"CH",
    "sg:address":"Verenastrasse 11",
    "sg:city":"Wollerau",
    "sg:orig_category":"Herstellung von Ger\u00e4ten der Elektrizit\u00e4tserzeugung, -verteilung u.\u00e4. -Herstellung von elektronischen",
    "sg:phone":"+41 17862030",
    "sg:postcode":"8832",
    "sg:province":"Schwyz",
    "wof:name":"Flex-control Porzi Hottinger & Heid Steuerungsbau, Automatisierung, Softwareerstellung",
    "wof:placetype":"venue"
},
  "geometry": {"coordinates":[8.7227239609,47.1934089661],"type":"Point"}
}