{
  "type": "Feature",
  "properties": {
    "iso:country":"CH",
    "sg:address":"Petit-cortaillod 38",
    "sg:city":"Cortaillod",
    "sg:classifiers":[
        {
            "category":"Travel",
            "subcategory":"Hotels & Motels",
            "type":"Entertainment"
        }
    ],
    "sg:phone":"+41 32 843 44 77",
    "sg:postcode":"2016",
    "sg:province":"Neuch\u00e2tel",
    "sg:tags":[
        "hotels",
        "business",
        "restaurant"
    ],
    "wof:name":"H\u00d4tel-restaurant Du Vaisseau",
    "wof:placetype":"venue"
},
  "geometry": {"coordinates":[6.853694,46.942554],"type":"Point"}
}