{
  "type": "Feature",
  "properties": {
    "iso:country":"CH",
    "sg:address":"Feldweg 21",
    "sg:city":"Arth",
    "sg:orig_category":"Elektroinstallation Herstellung von sonstigen elektrischen Ausr\u00fcstungen",
    "sg:phone":"+41 18444144",
    "sg:postcode":"6415",
    "sg:province":"Schwyz",
    "wof:name":"Ammann Elektro",
    "wof:placetype":"venue"
},
  "geometry": {"coordinates":[8.4380941391,47.4535331726],"type":"Point"}
}