{
  "type": "Feature",
  "properties": {
    "iso:country":"CH",
    "sg:address":"Place Du Ch\u00e2teau 2",
    "sg:city":"Grandson",
    "sg:orig_category":"Versicherungen Hauptagenturen",
    "sg:phone":"+41 24 445 44 51",
    "sg:postcode":"1422",
    "sg:province":"Vaud",
    "wof:name":"Assurance Cantonale Contre L'incendie & Les \u00e9l\u00e9ments Nat.",
    "wof:placetype":"venue"
},
  "geometry": {"coordinates":[6.6459121704,46.8091926575],"type":"Point"}
}