{
  "type": "Feature",
  "properties": {
    "iso:country":"CH",
    "sg:address":"3436",
    "sg:city":"Zollbr\u00fcck",
    "sg:orig_category":"Primarschulen",
    "sg:phone":"+41 34 496 86 30",
    "sg:postcode":"3436",
    "sg:province":"Bern",
    "wof:name":"Primarschule Unterfrittenbach",
    "wof:placetype":"venue"
},
  "geometry": {"coordinates":[7.7408971786,46.9739875793],"type":"Point"}
}