{
  "type": "Feature",
  "properties": {
    "iso:country":"CH",
    "sg:address":"Waldrainstrasse 30",
    "sg:city":"Biel/bienne",
    "sg:orig_category":"Sonstige Aktivit\u00e4ten der nicht-\u00e4rztlichen Medizinalberufe",
    "sg:phone":"+41 77323565",
    "sg:postcode":"2503",
    "sg:province":"Bern",
    "wof:name":"Elsbeth Hirt Akupunktur & Akupunkt-massage",
    "wof:placetype":"venue"
},
  "geometry": {"coordinates":[7.2613801956,47.1366081238],"type":"Point"}
}