{
  "type": "Feature",
  "properties": {
    "iso:country":"CH",
    "sg:address":"Dorfplatz 3 4460 Gelterkinden. Postfach 94",
    "sg:city":"Gelterkinden",
    "sg:orig_category":"Arztpraxen",
    "sg:phone":"+41 61 981 10 60",
    "sg:postcode":"4460",
    "sg:province":"Basel-Landschaft",
    "wof:name":"Dr.med.peter Jenny Arzt F.allgemeine Medizin Fmh",
    "wof:placetype":"venue"
},
  "geometry": {"coordinates":[7.856894,47.464783],"type":"Point"}
}