{
  "type": "Feature",
  "properties": {
    "iso:country":"CH",
    "sg:address":"Beethovenstrasse 24",
    "sg:city":"G\u00fcmligen",
    "sg:orig_category":"Zahnarztpraxen",
    "sg:phone":"+41 31 951 43 05",
    "sg:postcode":"3073",
    "sg:province":"Bern",
    "wof:name":"Dr. Med. Dent. Gilbert Minder Zahnarzt",
    "wof:placetype":"venue"
},
  "geometry": {"coordinates":[7.4926571846,46.9326324463],"type":"Point"}
}