{
  "type": "Feature",
  "properties": {
    "iso:country":"CH",
    "sg:address":"Hafenstrasse",
    "sg:city":"Altnau",
    "sg:classifiers":[
        {
            "category":"Travel",
            "subcategory":"Hotels & Motels",
            "type":"Entertainment"
        }
    ],
    "sg:phone":"+41 71 695 19 12",
    "sg:postcode":"8595",
    "sg:province":"Thurgau",
    "sg:tags":[
        "hotels",
        "mit",
        "restaurant"
    ],
    "wof:name":"Gasthof Krone Zivoi Peri",
    "wof:placetype":"venue"
},
  "geometry": {"coordinates":[9.2675037384,47.6218338013],"type":"Point"}
}