{
  "type": "Feature",
  "properties": {
    "iso:country":"CH",
    "sg:address":"Gill Ennetb\u00fchl 9651 Ennetb\u00fchl. Postfach",
    "sg:city":"Ennetb\u00fchl",
    "sg:orig_category":"Kauf U Verkauf von Immobilien auf eigene Rechnung",
    "sg:postcode":"9651",
    "sg:province":"St. Gallen",
    "wof:name":"Hlmw B\u00f6sch Gmbh",
    "wof:placetype":"venue"
},
  "geometry": {"coordinates":[9.2110414505,47.2402038574],"type":"Point"}
}