{
  "type": "Feature",
  "properties": {
    "iso:country":"CH",
    "sg:address":"Grauenstein 8",
    "sg:city":"Hettiswil",
    "sg:orig_category":"Elektroinstallation Herstellung von Elektromotoren, Generatoren U Transformatoren",
    "sg:phone":"+41 34 411 23 80",
    "sg:postcode":"3325",
    "sg:province":"Bern",
    "wof:name":"Buri Elektro",
    "wof:placetype":"venue"
},
  "geometry": {"coordinates":[7.5607829094,47.0306396484],"type":"Point"}
}