{
  "type": "Feature",
  "properties": {
    "iso:country":"CH",
    "sg:address":"M\u00fchlemattweg 4",
    "sg:city":"M\u00fcnchenbuchsee",
    "sg:orig_category":"Mechanische Werkst\u00e4tten",
    "sg:phone":"+41 31 869 23 14",
    "sg:postcode":"3053",
    "sg:province":"Bern",
    "wof:name":"R. Fehlmann Waagenservice",
    "wof:placetype":"venue"
},
  "geometry": {"coordinates":[7.4555568695,47.0206489563],"type":"Point"}
}