{
  "type": "Feature",
  "properties": {
    "iso:country":"CH",
    "sg:address":"Grossmattenring 23",
    "sg:city":"D\u00f6ttingen",
    "sg:orig_category":"Tierarztpraxis",
    "sg:phone":"+41 56 441 41 66",
    "sg:postcode":"5312",
    "sg:province":"Aargau",
    "wof:name":"Dr.med.vet.peter Baumgartner Tierarzt",
    "wof:placetype":"venue"
},
  "geometry": {"coordinates":[8.2269802094,47.4968261719],"type":"Point"}
}