{
  "type": "Feature",
  "properties": {
    "iso:country":"CH",
    "sg:address":"Mattenweg 22",
    "sg:city":"Giswil",
    "sg:orig_category":"Notariate",
    "sg:phone":"+41 41 675 19 25",
    "sg:postcode":"6074",
    "sg:province":"Obwalden",
    "wof:name":"Josef Bitzi Notariatsb\u00fcro",
    "wof:placetype":"venue"
},
  "geometry": {"coordinates":[8.1860942841,46.8411026001],"type":"Point"}
}