{
  "type": "Feature",
  "properties": {
    "iso:country":"CH",
    "sg:address":"Seestrasse 1",
    "sg:city":"Cham",
    "sg:orig_category":"Architektur U Ingenieurb\u00fcros",
    "sg:postcode":"6330",
    "sg:province":"Zug",
    "wof:name":"Bandack Cabral Architecte Epfl-sia",
    "wof:placetype":"venue"
},
  "geometry": {"coordinates":[6.701798,46.515484],"type":"Point"}
}