{
  "type": "Feature",
  "properties": {
    "iso:country":"CH",
    "sg:address":"Baarerstrasse 73",
    "sg:city":"Zug",
    "sg:orig_category":"Non-Classified Establishments",
    "sg:postcode":"6300",
    "sg:province":"Zug",
    "wof:name":"Ipro Sa",
    "wof:placetype":"venue"
},
  "geometry": {"coordinates":[6.836979866,47.1053962708],"type":"Point"}
}