{
  "type": "Feature",
  "properties": {
    "iso:country":"CH",
    "sg:address":"Pierre Rue Saint- 18",
    "sg:city":"Fribourg",
    "sg:orig_category":"Herstellung von sonstigen Nahrungsmitteln",
    "sg:phone":"+41 56 424 00 60",
    "sg:postcode":"1700",
    "sg:province":"Fribourg",
    "wof:name":"Aroma Group Sa Produits Aromatiques, Cosm\u00e9tiques, Alimentaires; Achat, Vente Etc",
    "wof:placetype":"venue"
},
  "geometry": {"coordinates":[7.1558661461,46.8040313721],"type":"Point"}
}