{
  "type": "Feature",
  "properties": {
    "iso:country":"CH",
    "sg:address":"Eschikon 28",
    "sg:city":"Lindau",
    "sg:orig_category":"Interessenvertretungen",
    "sg:postcode":"8315",
    "sg:province":"Z\u00fcrich",
    "wof:name":"F\u00f6rderverein Rindergesundheitsdienst",
    "wof:placetype":"venue"
},
  "geometry": {"coordinates":[8.6714487076,47.4413528442],"type":"Point"}
}