{
  "type": "Feature",
  "properties": {
    "iso:country":"CH",
    "sg:address":"Sonnenweg 55",
    "sg:city":"N\u00e4fels",
    "sg:orig_category":"Arbeitnehmerverb\u00e4nde",
    "sg:phone":"+41 71 755 34 58",
    "sg:postcode":"8752",
    "sg:province":"Glarus",
    "wof:name":"Christl.holz-& Bauarbeiter- Verb.altst\u00e4tten Luigi Totaro",
    "wof:placetype":"venue"
},
  "geometry": {"coordinates":[9.550371,47.376312],"type":"Point"}
}