{
  "type": "Feature",
  "properties": {
    "addr:full":"Klingentalstrasse 12 Basel Basel-Stadt 4057",
    "addr:housenumber":"12",
    "addr:postcode":"4057",
    "addr:street":"Klingentalstrasse",
    "iso:country":"CH",
    "sg:address":"Klingentalstrasse 12",
    "sg:city":"Basel",
    "sg:orig_category":"Autogaragen",
    "sg:phone":"+41 61 681 46 46",
    "sg:postcode":"4057",
    "sg:province":"Basel-Stadt",
    "wof:name":"Merkur Garage Rappoltshof Mti Merkur Trading Ag",
    "wof:placetype":"venue"
},
  "geometry": {"coordinates":[7.593264,47.563278],"type":"Point"}
}