{
  "type": "Feature",
  "properties": {
    "iso:country":"CH",
    "sg:address":"Z\u00fcrcherstrasse 139",
    "sg:city":"Frauenfeld",
    "sg:orig_category":"Interessenvertretungen",
    "sg:postcode":"8500",
    "sg:province":"Thurgau",
    "wof:name":"B\u00fcchi-stiftung Paul",
    "wof:placetype":"venue"
},
  "geometry": {"coordinates":[8.8950366974,47.5544891357],"type":"Point"}
}