{
  "type": "Feature",
  "properties": {
    "iso:country":"CH",
    "sg:address":"Les Briesses 3963 Crans-sur-sierre Case Postale 232",
    "sg:city":"Crans-sur-sierre",
    "sg:orig_category":"Unclassifiable Establishments",
    "sg:phone":"+41 27 481 63 06",
    "sg:postcode":"3963",
    "sg:province":"Valais",
    "wof:name":"Mittaz Gilles Sa",
    "wof:placetype":"venue"
},
  "geometry": {"coordinates":[7.4674968719,46.3017692566],"type":"Point"}
}