{
  "type": "Feature",
  "properties": {
    "iso:country":"CH",
    "sg:address":"6523",
    "sg:city":"Preonzo",
    "sg:orig_category":"Landwirtschaft, Jagd U damit verbundene Dienstleistungen",
    "sg:phone":"+41 91 863 18 07",
    "sg:postcode":"6523",
    "sg:province":"Ticino",
    "wof:name":"Renato Bianchi Azienda Agricola",
    "wof:placetype":"venue"
},
  "geometry": {"coordinates":[8.9998292923,46.2651481628],"type":"Point"}
}