{
  "type": "Feature",
  "properties": {
    "iso:country":"CH",
    "sg:address":"7050",
    "sg:city":"Arosa",
    "sg:orig_category":"Wirtschafts- and Arbeitgeberverb\u00e4nde",
    "sg:phone":"+41 81 302 15 33",
    "sg:postcode":"7050",
    "sg:province":"Graubunden",
    "wof:name":"Hotelierverein Bad Ragaz- Pf\u00e4fers Herrn Achille Sandi",
    "wof:placetype":"venue"
},
  "geometry": {"coordinates":[9.505109787,47.0095329285],"type":"Point"}
}