{
  "type": "Feature",
  "properties": {
    "iso:country":"CH",
    "sg:address":"Dorf 6",
    "sg:city":"Rehetobel",
    "sg:classifiers":[
        {
            "category":"Restaurant",
            "type":"Food & Drink"
        }
    ],
    "sg:phone":"+41 71 877 14 42",
    "sg:postcode":"9038",
    "sg:province":"Appenzell Ausserrhoden",
    "wof:name":"Restaurant Post",
    "wof:placetype":"venue"
},
  "geometry": {"coordinates":[9.4836673737,47.4263076782],"type":"Point"}
}