{
  "type": "Feature",
  "properties": {
    "iso:country":"CH",
    "sg:address":"Trotteweg 2",
    "sg:city":"M\u00fclligen",
    "sg:orig_category":"Haltung von Gefl\u00fcgel",
    "sg:phone":"+41 56 225 15 05",
    "sg:postcode":"5243",
    "sg:province":"Aargau",
    "wof:name":"Heinrich Barth Gefl\u00fcgelfarm",
    "wof:placetype":"venue"
},
  "geometry": {"coordinates":[8.2291278839,47.4519081116],"type":"Point"}
}