{
  "type": "Feature",
  "properties": {
    "iso:country":"CH",
    "sg:address":"Flurhofstrasse 136",
    "sg:city":"St.gallen",
    "sg:orig_category":"Allgemeiner Hoch U Tiefbau",
    "sg:postcode":"9000",
    "sg:province":"St. Gallen",
    "wof:name":"Preisig Paul Ag",
    "wof:placetype":"venue"
},
  "geometry": {"coordinates":[9.401203,47.430737],"type":"Point"}
}