{
  "type": "Feature",
  "properties": {
    "iso:country":"CH",
    "sg:address":"Seestrasse 58",
    "sg:city":"Weggis",
    "sg:orig_category":"Kosmetikinstitute",
    "sg:phone":"+41 41 390 01 83",
    "sg:postcode":"6353",
    "sg:province":"Luzern",
    "wof:name":"Kosmetiksalon Zimmermann Christina",
    "wof:placetype":"venue"
},
  "geometry": {"coordinates":[8.4246959686,47.0316619873],"type":"Point"}
}