{
  "type": "Feature",
  "properties": {
    "iso:country":"CH",
    "sg:address":"Obere Zollgasse 83",
    "sg:city":"Ostermundigen",
    "sg:orig_category":"Instandhaltung U Reparatur von Automobilen",
    "sg:phone":"+41 31 931 24 24",
    "sg:postcode":"3072",
    "sg:province":"Bern",
    "wof:name":"Carrosserie Zollgasse Daniel Probst",
    "wof:placetype":"venue"
},
  "geometry": {"coordinates":[7.4843091965,46.9481925964],"type":"Point"}
}