{
  "type": "Feature",
  "properties": {
    "iso:country":"CH",
    "sg:address":"Bundesrat R. Mingerstrasse 1a",
    "sg:city":"Sch\u00fcpfen",
    "sg:orig_category":"Bauschreinerei Zimmerei, Ingenieurholzbau",
    "sg:phone":"+41 32 385 30 65",
    "sg:postcode":"3054",
    "sg:province":"Bern",
    "wof:name":"Urs Schlatter Zimmerei & Schreinerei",
    "wof:placetype":"venue"
},
  "geometry": {"coordinates":[7.316119,47.100483],"type":"Point"}
}