{
  "type": "Feature",
  "properties": {
    "iso:country":"CH",
    "sg:address":"Rue Des Ateliers 7",
    "sg:city":"Meyrin",
    "sg:orig_category":"Instandhaltung U Reparatur von Automobilen",
    "sg:phone":"+41 22 782 11 34",
    "sg:postcode":"1217",
    "sg:province":"Gen\u00e8ve",
    "wof:name":"Carrosserie Du Vieux-bureau",
    "wof:placetype":"venue"
},
  "geometry": {"coordinates":[6.0805001259,46.2237434387],"type":"Point"}
}