{
  "type": "Feature",
  "properties": {
    "iso:country":"CH",
    "sg:address":"Schwendiweg 9a",
    "sg:city":"Gretzenbach",
    "sg:orig_category":"Elektroinstallation Softwareentwicklung U beratung",
    "sg:phone":"+41 62 849 10 61",
    "sg:postcode":"5014",
    "sg:province":"Solothurn",
    "wof:name":"Pr-elektronik Gmbh",
    "wof:placetype":"venue"
},
  "geometry": {"coordinates":[8.0004673004,47.3533477783],"type":"Point"}
}