{
  "type": "Feature",
  "properties": {
    "iso:country":"CH",
    "sg:address":"Avenue De La Gare 9",
    "sg:city":"Sion",
    "sg:classifiers":[
        {
            "category":"Government",
            "subcategory":"Post Office",
            "type":"Public Place"
        }
    ],
    "sg:phone":"+41 27 323 49 98",
    "sg:postcode":"1950",
    "sg:province":"Valais",
    "sg:tags":[
        "caf\u00e9s",
        "tea-rooms"
    ],
    "wof:name":"Caf\u00e9 2000",
    "wof:placetype":"venue"
},
  "geometry": {"coordinates":[7.3586759567,46.2288818359],"type":"Point"}
}