{
  "type": "Feature",
  "properties": {
    "iso:country":"CH",
    "sg:address":"Schaufelb\u00fchl",
    "sg:city":"Gr\u00fcnenmatt",
    "sg:orig_category":"Sonstige Institutionen des Sozialwesens ohne Beherbergung",
    "sg:phone":"+41 34 431 12 21",
    "sg:postcode":"3452",
    "sg:province":"Bern",
    "wof:name":"Rosalie Messerli M\u00fctterberatung Trachselwald",
    "wof:placetype":"venue"
},
  "geometry": {"coordinates":[7.7264041901,47.0078697205],"type":"Point"}
}