{
  "type": "Feature",
  "properties": {
    "iso:country":"CH",
    "sg:address":"Schmiedgasse 5",
    "sg:city":"Hochfelden",
    "sg:orig_category":"Sonstige mit der Informatik verbundene T\u00e4tigkeiten",
    "sg:postcode":"8182",
    "sg:province":"Z\u00fcrich",
    "wof:name":"Syntratec Bacher T.",
    "wof:placetype":"venue"
},
  "geometry": {"coordinates":[8.5165624619,47.5216712952],"type":"Point"}
}