{
  "type": "Feature",
  "properties": {
    "iso:country":"CH",
    "sg:address":"Frutigenstrasse 61b",
    "sg:city":"Thun",
    "sg:orig_category":"Detailhandel mit Radio U Fernsehger\u00e4ten",
    "sg:phone":"+41 33 336 00 72",
    "sg:postcode":"3604",
    "sg:province":"Bern",
    "wof:name":"Audiotechnik L\u00fcthi",
    "wof:placetype":"venue"
},
  "geometry": {"coordinates":[7.6277008057,46.7455444336],"type":"Point"}
}