{
  "type": "Feature",
  "properties": {
    "iso:country":"CH",
    "sg:address":"Weissbadstrasse 4",
    "sg:city":"Appenzell",
    "sg:orig_category":"Sportvereine Ballsport Tennis",
    "sg:phone":"+41 71 787 35 45",
    "sg:postcode":"9050",
    "sg:province":"Appenzell Innerhoden",
    "wof:name":"Tc Appenzell",
    "wof:placetype":"venue"
},
  "geometry": {"coordinates":[9.4110641479,47.3303909302],"type":"Point"}
}