{
  "type": "Feature",
  "properties": {
    "iso:country":"CH",
    "sg:address":"Baselstrasse 2",
    "sg:city":"Duggingen",
    "sg:orig_category":"RESTAURANTS: TEA-ROOMS",
    "sg:phone":"+41 61 751 15 65",
    "sg:postcode":"4202",
    "sg:province":"Basel-Landschaft",
    "wof:name":"Schmirmaul Roland, Restaurant Angenstein",
    "wof:placetype":"venue"
},
  "geometry": {"coordinates":[7.6047201157,47.4623031616],"type":"Point"}
}