{
  "type": "Feature",
  "properties": {
    "addr:full":"Obere Bahnhofstrasse 46 Rapperswil Schwyz 8640",
    "addr:housenumber":"46",
    "addr:postcode":"8640",
    "addr:street":"Obere Bahnhofstrasse;Schwyz",
    "iso:country":"CH",
    "sg:address":"Obere Bahnhofstrasse 46",
    "sg:city":"Rapperswil",
    "sg:classifiers":[
        {
            "category":"Professional",
            "subcategory":"Advertising",
            "type":"Services"
        }
    ],
    "sg:phone":"+41 55 210 41 00",
    "sg:postcode":"8640",
    "sg:province":"Schwyz",
    "sg:tags":[
        "agency"
    ],
    "wof:name":"Leuzinger & Benz Ag",
    "wof:placetype":"venue"
},
  "geometry": {"coordinates":[8.819225,47.227394],"type":"Point"}
}