{
  "type": "Feature",
  "properties": {
    "iso:country":"CH",
    "sg:address":"Bahnhofplatz",
    "sg:city":"Chur",
    "sg:orig_category":"Reiseb\u00fcros",
    "sg:phone":"+41 51 228 53 03",
    "sg:postcode":"7000",
    "sg:province":"Graubunden",
    "wof:name":"Sbb Reiseb\u00fcro Kuoni",
    "wof:placetype":"venue"
},
  "geometry": {"coordinates":[9.5295085907,46.8529396057],"type":"Point"}
}