{
  "type": "Feature",
  "properties": {
    "iso:country":"CH",
    "sg:address":"Bahnhofstrasse 8",
    "sg:city":"Huttwil",
    "sg:orig_category":"Non-Classified Establishments",
    "sg:postcode":"4950",
    "sg:province":"Bern",
    "wof:name":"Eberle + Rickli",
    "wof:placetype":"venue"
},
  "geometry": {"coordinates":[7.8474149704,47.1141357422],"type":"Point"}
}