{
  "type": "Feature",
  "properties": {
    "iso:country":"CH",
    "sg:address":"8600",
    "sg:city":"D\u00fcbendorf",
    "sg:orig_category":"Schwimmb\u00e4der",
    "sg:phone":"+41 18216500",
    "sg:postcode":"8600",
    "sg:province":"Z\u00fcrich",
    "wof:name":"Schwimmbad",
    "wof:placetype":"venue"
},
  "geometry": {"coordinates":[8.6222238541,47.3997840881],"type":"Point"}
}