{
  "type": "Feature",
  "properties": {
    "iso:country":"CH",
    "sg:address":"Avenue De La Fusion 48",
    "sg:city":"Martigny",
    "sg:orig_category":"Allgemeiner Hoch U Tiefbau Strassenbau",
    "sg:phone":"+41 79 628 13 72",
    "sg:postcode":"1920",
    "sg:province":"Valais",
    "wof:name":"Carenbit Sa",
    "wof:placetype":"venue"
},
  "geometry": {"coordinates":[7.066739,46.100197],"type":"Point"}
}