{
  "type": "Feature",
  "properties": {
    "iso:country":"CH",
    "sg:address":"Saint-jean Rue De 26 1203 Gen\u00e8ve. Postfach",
    "sg:city":"Gen\u00e8ve",
    "sg:orig_category":"Interessenvertretungen",
    "sg:phone":"+41 22 340 32 00",
    "sg:postcode":"1203",
    "sg:province":"Gen\u00e8ve",
    "wof:name":"Association De Gestion Internationale Collective Des Oeuvres Audio-visuelles (agicoa)",
    "wof:placetype":"venue"
},
  "geometry": {"coordinates":[6.1280112267,46.2045822144],"type":"Point"}
}