{
  "type": "Feature",
  "properties": {
    "addr:full":"Industriestrasse Maienfeld Graubunden 7304",
    "addr:postcode":"7304",
    "addr:street":"Industriestrasse;Graubunden",
    "iso:country":"CH",
    "sg:address":"Industriestrasse",
    "sg:city":"Maienfeld",
    "sg:orig_category":"Allgemeiner Hoch U Tiefbau",
    "sg:postcode":"7304",
    "sg:province":"Graubunden",
    "wof:name":"Karo Handels Ag",
    "wof:placetype":"venue"
},
  "geometry": {"coordinates":[9.524715,47.000584],"type":"Point"}
}