{
  "type": "Feature",
  "properties": {
    "iso:country":"CH",
    "sg:address":"Hohlenbaumstr. 18 8200 Schaffhausen. Postfach 560",
    "sg:city":"Schaffhausen",
    "sg:orig_category":"Pensionskassen",
    "sg:postcode":"8201",
    "sg:province":"Schaffhausen",
    "wof:name":"Personalf\u00fcrsorgestiftung Der Firma Stima-m\u00f6bel Ag, 6204 Sempach",
    "wof:placetype":"venue"
},
  "geometry": {"coordinates":[8.2235832214,47.131149292],"type":"Point"}
}