{
  "type": "Feature",
  "properties": {
    "iso:country":"CH",
    "sg:address":"Feldstrasse 99 8180 B\u00fclach. Postfach",
    "sg:city":"B\u00fclach",
    "sg:orig_category":"Grosshandel mit B\u00fcromaschinen Grosshandel mit Datenverarbeitungsger\u00e4ten",
    "sg:phone":"+41 79 400 56 63",
    "sg:postcode":"8180",
    "sg:province":"Z\u00fcrich",
    "wof:name":"Rimo Consulting Ag",
    "wof:placetype":"venue"
},
  "geometry": {"coordinates":[8.5413227081,47.5080070496],"type":"Point"}
}