{
  "type": "Feature",
  "properties": {
    "iso:country":"CH",
    "sg:address":"3284",
    "sg:city":"Fr\u00e4schels",
    "sg:orig_category":"Gem\u00fcsebau",
    "sg:phone":"+41 31 755 55 34",
    "sg:postcode":"3284",
    "sg:province":"Fribourg",
    "wof:name":"Willy Hunziker Gem\u00fcsebau",
    "wof:placetype":"venue"
},
  "geometry": {"coordinates":[7.2066998482,46.9978981018],"type":"Point"}
}