{
  "type": "Feature",
  "properties": {
    "iso:country":"CH",
    "sg:address":"Albulastrasse 34",
    "sg:city":"Z\u00fcrich",
    "sg:orig_category":"Radio U Fernsehanstalten Verlagsgewerbe",
    "sg:phone":"+41 14056070",
    "sg:postcode":"8048",
    "sg:province":"Z\u00fcrich",
    "wof:name":"Additiv Ag F\u00fcr Informations Und Medienmarketing",
    "wof:placetype":"venue"
},
  "geometry": {"coordinates":[8.4933691025,47.3883361816],"type":"Point"}
}