{
  "type": "Feature",
  "properties": {
    "iso:country":"CH",
    "sg:address":"6817",
    "sg:city":"Maroggia",
    "sg:orig_category":"Unclassifiable Establishments",
    "sg:postcode":"6817",
    "sg:province":"Ticino",
    "wof:name":"Sulda Sa",
    "wof:placetype":"venue"
},
  "geometry": {"coordinates":[8.9697504044,45.9363708496],"type":"Point"}
}