{
  "type": "Feature",
  "properties": {
    "iso:country":"CH",
    "sg:address":"Amselweg 5",
    "sg:city":"Steinach",
    "sg:orig_category":"Architektur U Ingenieurb\u00fcros",
    "sg:phone":"+41 71 440 13 40",
    "sg:postcode":"9323",
    "sg:province":"St. Gallen",
    "wof:name":"Metasoft Ag",
    "wof:placetype":"venue"
},
  "geometry": {"coordinates":[9.437653,47.501354],"type":"Point"}
}