{
  "type": "Feature",
  "properties": {
    "iso:country":"CH",
    "sg:address":"Fliederweg 4 6438 Ibach. Postfach",
    "sg:city":"Ibach",
    "sg:orig_category":"Herstellung von \u00d6fen U Brennern",
    "sg:postcode":"6438",
    "sg:province":"Schwyz",
    "wof:name":"Karl L\u00fc\u00f6nd, Ofenbau-plattenbel\u00e4ge",
    "wof:placetype":"venue"
},
  "geometry": {"coordinates":[8.6512889862,47.0112571716],"type":"Point"}
}