{
  "type": "Feature",
  "properties": {
    "iso:country":"CH",
    "sg:address":"Pizolstrasse 2 7320 Sargans. Postfach 47",
    "sg:city":"Sargans",
    "sg:orig_category":"Kauf U Verkauf von Immobilien auf eigene Rechnung Verwaltung von Immobilien",
    "sg:phone":"+41 81 723 65 68",
    "sg:postcode":"7320",
    "sg:province":"St. Gallen",
    "wof:name":"Bbs Bereiter Buildings Immobilienverwaltung",
    "wof:placetype":"venue"
},
  "geometry": {"coordinates":[9.4418897629,47.045665741],"type":"Point"}
}