{
  "type": "Feature",
  "properties": {
    "iso:country":"CH",
    "sg:address":"Kasernenstrasse 67",
    "sg:city":"Chur",
    "sg:orig_category":"Pensionskassen",
    "sg:postcode":"7000",
    "sg:province":"Graubunden",
    "wof:name":"Personalvorsorgestiftung Der Senn Unternehmungen",
    "wof:placetype":"venue"
},
  "geometry": {"coordinates":[9.5210819244,46.8469734192],"type":"Point"}
}