{
  "type": "Feature",
  "properties": {
    "iso:country":"CH",
    "sg:address":"Zentralstrasse 43",
    "sg:city":"Biel/bienne",
    "sg:classifiers":[
        {
            "category":"Government",
            "subcategory":"Post Office",
            "type":"Public Place"
        }
    ],
    "sg:phone":"+41 32 322 79 33",
    "sg:postcode":"2502",
    "sg:province":"Bern",
    "sg:tags":[
        "caf\u00e9s",
        "tea-rooms"
    ],
    "wof:name":"Caf\u00e9 Libresso",
    "wof:placetype":"venue"
},
  "geometry": {"coordinates":[7.2461919785,47.1375732422],"type":"Point"}
}