{
  "type": "Feature",
  "properties": {
    "iso:country":"CH",
    "sg:address":"Rue Du Rh\u00f4ne 26 1950 Sion Case Postale 531",
    "sg:city":"Sion",
    "sg:orig_category":"Wirtschaftspr\u00fcfung, Steuerberatung U Treuhand",
    "sg:phone":"+41 27 322 76 49",
    "sg:postcode":"1951",
    "sg:province":"Valais",
    "wof:name":"Fiduciaire Follonier G\u00e9rard",
    "wof:placetype":"venue"
},
  "geometry": {"coordinates":[7.3612642288,46.2321815491],"type":"Point"}
}