{
  "type": "Feature",
  "properties": {
    "iso:country":"CH",
    "sg:address":"Cresedo",
    "sg:city":"Aquila",
    "sg:orig_category":"Malerei Tapeziererei",
    "sg:phone":"+41 91 872 19 49",
    "sg:postcode":"6719",
    "sg:province":"Ticino",
    "wof:name":"Pasquale Devittori Impresa Di Pittura",
    "wof:placetype":"venue"
},
  "geometry": {"coordinates":[8.9494161606,46.504699707],"type":"Point"}
}