{
  "type": "Feature",
  "properties": {
    "iso:country":"CH",
    "sg:address":"Dorfstrasse 54 6142 Gettnau. Postfach",
    "sg:city":"Gettnau",
    "sg:classifiers":[
        {
            "category":"Bars & Pubs",
            "type":"Food & Drink"
        }
    ],
    "sg:postcode":"6142",
    "sg:province":"Luzern",
    "wof:name":"Bpm Hondert 50 Schmidiger Marcel",
    "wof:placetype":"venue"
},
  "geometry": {"coordinates":[7.96668,47.139828],"type":"Point"}
}