{
  "type": "Feature",
  "properties": {
    "iso:country":"CH",
    "sg:address":"2576",
    "sg:city":"L\u00fcscherz",
    "sg:orig_category":"Primarschulen",
    "sg:phone":"+41 32 396 23 72",
    "sg:postcode":"2576",
    "sg:province":"Bern",
    "wof:name":"Primarschule",
    "wof:placetype":"venue"
},
  "geometry": {"coordinates":[7.1840701103,47.0295181274],"type":"Point"}
}