{
  "type": "Feature",
  "properties": {
    "iso:country":"CH",
    "sg:address":"Industriestrasse 5 4253 Liesberg. Postfach",
    "sg:city":"Liesberg",
    "sg:orig_category":"Erzeugung U Erstbearbeitung von Aluminium",
    "sg:phone":"+41 61 775 22 22",
    "sg:postcode":"4253",
    "sg:province":"Basel-Landschaft",
    "wof:name":"Aluminium - Laufen Ag Liesberg",
    "wof:placetype":"venue"
},
  "geometry": {"coordinates":[7.4295458794,47.3949317932],"type":"Point"}
}