{
  "type": "Feature",
  "properties": {
    "iso:country":"CH",
    "sg:address":"6817",
    "sg:city":"Maroggia",
    "sg:orig_category":"Grosshandel mit Uhren Grosshandel mit elektrischen Haushaltsger\u00e4ten",
    "sg:phone":"+41 91 649 86 70",
    "sg:postcode":"6817",
    "sg:province":"Ticino",
    "wof:name":"Termiquarz Sa",
    "wof:placetype":"venue"
},
  "geometry": {"coordinates":[8.9697504044,45.9363708496],"type":"Point"}
}