{
  "type": "Feature",
  "properties": {
    "iso:country":"CH",
    "sg:address":"St. Jakobstrasse 60",
    "sg:city":"Cham",
    "sg:orig_category":"Sonstiger Grosshandel",
    "sg:phone":"+41 24 471 48 93",
    "sg:postcode":"6330",
    "sg:province":"Zug",
    "wof:name":"Dolce Canna - Weber Jean-paul",
    "wof:placetype":"venue"
},
  "geometry": {"coordinates":[6.9263191223,46.2791175842],"type":"Point"}
}