{
  "type": "Feature",
  "properties": {
    "iso:country":"CH",
    "sg:address":"Rue De Champ-barby 61",
    "sg:city":"Bulle",
    "sg:classifiers":[
        {
            "category":"Banks & Credit Unions",
            "subcategory":"Investment Brokerage",
            "type":"Services"
        }
    ],
    "sg:phone":"+41 26 919 11 22",
    "sg:postcode":"1630",
    "sg:province":"Fribourg",
    "sg:tags":[
        "bearing",
        "ball"
    ],
    "wof:name":"Wib - W\u00e4lzlager Industriewerke Bulle Ag",
    "wof:placetype":"venue"
},
  "geometry": {"coordinates":[7.06646,46.612232],"type":"Point"}
}