{
  "type": "Feature",
  "properties": {
    "iso:country":"CH",
    "sg:address":"Avenue De La Gare 24",
    "sg:city":"Del\u00e9mont",
    "sg:orig_category":"Detailhandel mit Bekleidung Detailhandel mit Damenbekleidung",
    "sg:phone":"+41 32 422 32 56",
    "sg:postcode":"2800",
    "sg:province":"Jura",
    "wof:name":"Cyb\u00e8le Sa",
    "wof:placetype":"venue"
},
  "geometry": {"coordinates":[7.348983,47.364796],"type":"Point"}
}