{
  "type": "Feature",
  "properties": {
    "iso:country":"CH",
    "sg:address":"Bahnhofstrasse 14",
    "sg:city":"Brig",
    "sg:classifiers":[
        {
            "category":"Restaurant",
            "type":"Food & Drink"
        }
    ],
    "sg:phone":"+41 27 924 24 64",
    "sg:postcode":"3900",
    "sg:province":"Valais",
    "wof:name":"Restauranr New Couronne",
    "wof:placetype":"venue"
},
  "geometry": {"coordinates":[7.9879851341,46.3168106079],"type":"Point"}
}