{
  "type": "Feature",
  "properties": {
    "iso:country":"CH",
    "sg:address":"Maienb\u00fchlstr\u00e4sschen 31",
    "sg:city":"Riehen",
    "sg:orig_category":"Detailhandel mit Waren verschiedener Art, Hauptrichtung Nahrungsmittel",
    "sg:phone":"+41 34 491 14 44",
    "sg:postcode":"4125",
    "sg:province":"Basel-Stadt",
    "wof:name":"Landwirtschaftliche Genossenschaft R\u00f6thenbach-eggiwil Und Umgebung",
    "wof:placetype":"venue"
},
  "geometry": {"coordinates":[7.7429900169,46.8556518555],"type":"Point"}
}