{
  "type": "Feature",
  "properties": {
    "iso:country":"CH",
    "sg:address":"Vorderi H\u00f6chi 8816 Hirzel. Postfach",
    "sg:city":"Hirzel",
    "sg:orig_category":"Interessenvertretungen",
    "sg:postcode":"8816",
    "sg:province":"Z\u00fcrich",
    "wof:name":"Verein P\u00e4dagogisch-therapeutische Grossfamilie, Vordere H\u00f6he, 8816 Hirzel",
    "wof:placetype":"venue"
},
  "geometry": {"coordinates":[8.6054592133,47.217716217],"type":"Point"}
}