{
  "type": "Feature",
  "properties": {
    "iso:country":"CH",
    "sg:address":"Blegistrasse 11a/b",
    "sg:city":"Baar",
    "sg:orig_category":"Herstellung von Konstruktionsteilen, Fertigbauteilen U Ausbauelementen aus Holz",
    "sg:postcode":"6340",
    "sg:province":"Zug",
    "wof:name":"Baumgartner Werner",
    "wof:placetype":"venue"
},
  "geometry": {"coordinates":[9.4729261398,47.1647262573],"type":"Point"}
}