{
  "type": "Feature",
  "properties": {
    "iso:country":"CH",
    "sg:address":"Gupfenstrasse 11",
    "sg:city":"Niederweningen",
    "sg:orig_category":"Grosshandel mit B\u00fcromaschinen Grosshandel mit Datenverarbeitungsger\u00e4ten",
    "sg:phone":"+41 18857161",
    "sg:postcode":"8166",
    "sg:province":"Z\u00fcrich",
    "wof:name":"Furrer Edv-avk",
    "wof:placetype":"venue"
},
  "geometry": {"coordinates":[8.3749809265,47.5034561157],"type":"Point"}
}