{
  "type": "Feature",
  "properties": {
    "addr:full":"Via Stazione 51 Caslano Ticino 6987",
    "addr:housenumber":"51",
    "addr:postcode":"6987",
    "addr:street":"Via Stazione",
    "iso:country":"CH",
    "sg:address":"Via Stazione 51",
    "sg:city":"Caslano",
    "sg:orig_category":"Arztpraxen",
    "sg:phone":"+41 91 606 46 46",
    "sg:postcode":"6987",
    "sg:province":"Ticino",
    "wof:name":"Dott.med.johnny De Luigi Specialista Fmh",
    "wof:placetype":"venue"
},
  "geometry": {"coordinates":[8.878241,45.97506],"type":"Point"}
}