{
  "type": "Feature",
  "properties": {
    "iso:country":"CH",
    "sg:address":"Frikartstrasse 3",
    "sg:city":"Zofingen",
    "sg:orig_category":"Unclassifiable Establishments",
    "sg:postcode":"4800",
    "sg:province":"Aargau",
    "wof:name":"Schweizer Unternehmungen Ag",
    "wof:placetype":"venue"
},
  "geometry": {"coordinates":[7.94602108,47.2828292847],"type":"Point"}
}