{
  "type": "Feature",
  "properties": {
    "addr:full":"Sonnenbergstrasse 7 Winterthur Z\u00fcrich 8400",
    "addr:housenumber":"7",
    "addr:postcode":"8400",
    "addr:street":"Sonnenbergstrasse",
    "iso:country":"CH",
    "sg:address":"Sonnenbergstrasse 7",
    "sg:city":"Winterthur",
    "sg:orig_category":"Architektur U Ingenieurb\u00fcros",
    "sg:phone":"+41 52 212 16 65",
    "sg:postcode":"8400",
    "sg:province":"Z\u00fcrich",
    "wof:name":"New Visions Engineering, Goel G. Dipl. Ing.",
    "wof:placetype":"venue"
},
  "geometry": {"coordinates":[8.724931,47.492352],"type":"Point"}
}