{
  "type": "Feature",
  "properties": {
    "iso:country":"CH",
    "sg:address":"Hauptstrasse 41",
    "sg:city":"H\u00f6lstein",
    "sg:orig_category":"Detailhandel mit Waren verschiedener Art, Hauptrichtung Nahrungsmittel Nahrungsmittel-Industrie: Roh",
    "sg:phone":"+41 32 914 12 33",
    "sg:postcode":"4434",
    "sg:province":"Basel-Landschaft",
    "wof:name":"Casa Resende - Da Silva A. S\u00e0rl Magasins D'alimentation, Principalement Portugaise. Commerce De Denr\u00e9es Alimentaires",
    "wof:placetype":"venue"
},
  "geometry": {"coordinates":[6.8183012009,47.0961227417],"type":"Point"}
}