{
  "type": "Feature",
  "properties": {
    "iso:country":"CH",
    "sg:address":"Bahnhofstrasse 5",
    "sg:city":"W\u00e4denswil",
    "sg:orig_category":"Technische, physikalische U chemische Untersuchung",
    "sg:phone":"+41 17808330",
    "sg:postcode":"8820",
    "sg:province":"Z\u00fcrich",
    "wof:name":"Z\u00fcrichsee-labor",
    "wof:placetype":"venue"
},
  "geometry": {"coordinates":[8.6751394272,47.22889328],"type":"Point"}
}