{
  "type": "Feature",
  "properties": {
    "iso:country":"CH",
    "sg:address":"1905",
    "sg:city":"Dor\u00e9naz",
    "sg:orig_category":"Herstellung von Teilen U Zubeh\u00f6r f\u00fcr Automobile R\u00fcckgewinnung U Vorbereitung f\u00fcr die Wiederverwertun",
    "sg:phone":"+41 27 764 14 69",
    "sg:postcode":"1905",
    "sg:province":"Valais",
    "wof:name":"Revaz Francis Et Marcel",
    "wof:placetype":"venue"
},
  "geometry": {"coordinates":[7.0422902107,46.1487998962],"type":"Point"}
}