{
  "type": "Feature",
  "properties": {
    "iso:country":"CH",
    "sg:address":"Gare Route De La 24 1163 Etoy. Postfach",
    "sg:city":"Etoy",
    "sg:orig_category":"Herstellung von Radio U Fernsehger\u00e4ten sowie phono U videotechnischen Ger\u00e4ten",
    "sg:postcode":"1163",
    "sg:province":"Vaud",
    "wof:name":"Rohrer Handels Ag",
    "wof:placetype":"venue"
},
  "geometry": {"coordinates":[8.2710981369,47.3501052856],"type":"Point"}
}