{
  "type": "Feature",
  "properties": {
    "iso:country":"CH",
    "sg:address":"Sonnegg",
    "sg:city":"Udligenswil",
    "sg:orig_category":"Haltung von Schweinen",
    "sg:phone":"+41 71 648 18 56",
    "sg:postcode":"6044",
    "sg:province":"Luzern",
    "wof:name":"Fritz Roth Schweinezucht",
    "wof:placetype":"venue"
},
  "geometry": {"coordinates":[9.2330951691,47.5481987],"type":"Point"}
}