{
  "type": "Feature",
  "properties": {
    "iso:country":"CH",
    "sg:address":"Zone Industrielle La Veyre 1806 St-l\u00e9gier. Postfach 109",
    "sg:city":"St-l\u00e9gier",
    "sg:orig_category":"Instandhaltung U Reparatur von Automobilen",
    "sg:phone":"+41 21 943 47 70",
    "sg:postcode":"1806",
    "sg:province":"Vaud",
    "wof:name":"Carrosserie De La Veyre Sa",
    "wof:placetype":"venue"
},
  "geometry": {"coordinates":[3.1718599796,45.6728591919],"type":"Point"}
}