{
  "type": "Feature",
  "properties": {
    "iso:country":"CH",
    "sg:address":"Grand'rue Maison Roch",
    "sg:city":"Ch\u00e2teau-d'oex",
    "sg:orig_category":"Unclassifiable Establishments",
    "sg:postcode":"1837",
    "wof:name":"Sounouk S\u00e0rl",
    "wof:placetype":"venue"
},
  "geometry": {"coordinates":[4.6324892044,50.3284072876],"type":"Point"}
}