{
  "type": "Feature",
  "properties": {
    "iso:country":"CH",
    "sg:address":"Luzernstrasse 5",
    "sg:city":"Subingen",
    "sg:orig_category":"Fahrschulen, Flugschulen",
    "sg:phone":"+41 32 614 17 57",
    "sg:postcode":"4553",
    "sg:province":"Solothurn",
    "wof:name":"Manfred Schreier Autofahrschule",
    "wof:placetype":"venue"
},
  "geometry": {"coordinates":[7.6074228287,47.1978149414],"type":"Point"}
}