{
  "type": "Feature",
  "properties": {
    "iso:country":"CH",
    "sg:address":"Fl\u00fcelistrasse 20",
    "sg:city":"Kerns",
    "sg:orig_category":"Dachdeckerei Zimmerei, Dachdeckerei, Bauspenglerei U Abdichtung",
    "sg:phone":"+41 41 660 56 09",
    "sg:postcode":"6064",
    "sg:province":"Obwalden",
    "wof:name":"R\u00f6thlin Ernst",
    "wof:placetype":"venue"
},
  "geometry": {"coordinates":[8.273179,46.897408],"type":"Point"}
}