{
  "type": "Feature",
  "properties": {
    "iso:country":"CH",
    "sg:address":"Rue Du 31-d\u00e9cembre 38. 1200 Genf. Postfach",
    "sg:city":"Gen\u00e8ve",
    "sg:orig_category":"RESTAURANTS: TEA-ROOMS",
    "sg:postcode":"1207",
    "sg:province":"Gen\u00e8ve",
    "wof:name":"Moreno Manuel.",
    "wof:placetype":"venue"
},
  "geometry": {"coordinates":[6.1604981422,46.202545166],"type":"Point"}
}