{
  "type": "Feature",
  "properties": {
    "iso:country":"CH",
    "sg:address":"Dorfstrasse 54",
    "sg:city":"Ried-brig",
    "sg:orig_category":"Bauschreinerei",
    "sg:phone":"+41 19304257",
    "sg:postcode":"3911",
    "sg:province":"Valais",
    "wof:name":"Herbert Fischer Schreinerei",
    "wof:placetype":"venue"
},
  "geometry": {"coordinates":[8.79848,47.32452],"type":"Point"}
}