{
  "type": "Feature",
  "properties": {
    "iso:country":"CH",
    "sg:address":"Loretoh\u00f6he 1",
    "sg:city":"Zug",
    "sg:orig_category":"Gartenbau Landschaftsplanungsb\u00fcros U Gartenarchitekturb\u00fcros",
    "sg:phone":"+41 41 711 82 67",
    "sg:postcode":"6300",
    "sg:province":"Zug",
    "wof:name":"Franz Schuler Gartengestaltung",
    "wof:placetype":"venue"
},
  "geometry": {"coordinates":[8.5237474442,47.1723327637],"type":"Point"}
}