{
  "type": "Feature",
  "properties": {
    "iso:country":"CH",
    "sg:address":"Bahnhofstrasse 3 6312 Steinhausen. Postfach 340",
    "sg:city":"Steinhausen",
    "sg:orig_category":"Polizei",
    "sg:phone":"+41 41 741 62 17",
    "sg:postcode":"6312",
    "sg:province":"Zug",
    "wof:name":"Kantonale Polizei",
    "wof:placetype":"venue"
},
  "geometry": {"coordinates":[8.4839468002,47.19581604],"type":"Point"}
}