{
  "type": "Feature",
  "properties": {
    "iso:country":"CH",
    "sg:address":"B. Rechsteiner-strasse 2",
    "sg:city":"Biel/bienne",
    "sg:orig_category":"Naturheil\u00e4rzte and Heilpraktiker",
    "sg:phone":"+41 32 323 27 06",
    "sg:postcode":"2502",
    "sg:province":"Bern",
    "wof:name":"Hans-ruedi Luder Augendiagnose Iridologie",
    "wof:placetype":"venue"
},
  "geometry": {"coordinates":[7.2429838181,47.1352920532],"type":"Point"}
}