{
  "type": "Feature",
  "properties": {
    "iso:country":"CH",
    "sg:address":"Hofstattg\u00e4ssli 53",
    "sg:city":"M\u00fcmliswil",
    "sg:orig_category":"Vereine Hundedressur",
    "sg:phone":"+41 34 445 93 40",
    "sg:postcode":"4717",
    "sg:province":"Solothurn",
    "wof:name":"Schw.cl.f.schnauzer & Pinscher",
    "wof:placetype":"venue"
},
  "geometry": {"coordinates":[7.5886831284,47.0854911804],"type":"Point"}
}