{
  "type": "Feature",
  "properties": {
    "iso:country":"CH",
    "sg:address":"Schutzengelstrasse 36 6340 Baar. Postfach 2154",
    "sg:city":"Baar",
    "sg:orig_category":"Finanzierungsinstitutionen Handelsvermittlung U Grosshandel",
    "sg:phone":"+41 22 347 14 00",
    "sg:postcode":"6342",
    "sg:province":"Zug",
    "wof:name":"Capco Capacity Finance Sa",
    "wof:placetype":"venue"
},
  "geometry": {"coordinates":[6.1556987762,46.1962547302],"type":"Point"}
}