{
  "type": "Feature",
  "properties": {
    "iso:country":"CH",
    "sg:address":"Industrie Haslen",
    "sg:city":"Oberb\u00fcren",
    "sg:orig_category":"Fernmeldedienste Herstellung von optischen Instrumenten",
    "sg:phone":"+41 71 952 63 66",
    "sg:postcode":"9245",
    "sg:province":"St. Gallen",
    "wof:name":"Optonet Ag",
    "wof:placetype":"venue"
},
  "geometry": {"coordinates":[9.1535625458,47.4516448975],"type":"Point"}
}