{
  "type": "Feature",
  "properties": {
    "iso:country":"CH",
    "sg:address":"Schmiedgasse 9",
    "sg:city":"St.gallen",
    "sg:orig_category":"Detailhandel mit Bekleidung",
    "sg:phone":"+41 71 220 00 55",
    "sg:postcode":"9000",
    "sg:province":"St. Gallen",
    "wof:name":"Utka Flagshipshops Gmbh Helly Hansen",
    "wof:placetype":"venue"
},
  "geometry": {"coordinates":[9.376459,47.424141],"type":"Point"}
}