{
  "type": "Feature",
  "properties": {
    "iso:country":"CH",
    "sg:address":"Zielweg 14",
    "sg:city":"R\u00f6schenz",
    "sg:orig_category":"Vermietung U Verpachtung von eigenen Immobilien Wirtschaftspr\u00fcfung, Steuerberatung U Treuhand",
    "sg:phone":"+41 61 761 32 33",
    "sg:postcode":"4244",
    "sg:province":"Basel-Landschaft",
    "wof:name":"Fuchs + Partner",
    "wof:placetype":"venue"
},
  "geometry": {"coordinates":[7.4753170013,47.427822113],"type":"Point"}
}