{
  "type": "Feature",
  "properties": {
    "iso:country":"CH",
    "sg:address":"Hauptstrasse 11",
    "sg:city":"Pieterlen",
    "sg:classifiers":[
        {
            "category":"Restaurant",
            "type":"Food & Drink"
        }
    ],
    "sg:phone":"+41 32 377 15 15",
    "sg:postcode":"2542",
    "sg:province":"Bern",
    "wof:name":"Pizzeria La Perla",
    "wof:placetype":"venue"
},
  "geometry": {"coordinates":[7.3367137909,47.1747245789],"type":"Point"}
}