{
  "type": "Feature",
  "properties": {
    "iso:country":"CH",
    "sg:address":"Stelzenstrasse 6",
    "sg:city":"Opfikon",
    "sg:orig_category":"Erwachsenenbildung U Unterricht",
    "sg:postcode":"8152",
    "sg:province":"Z\u00fcrich",
    "wof:name":"Babylonia Gmbh",
    "wof:placetype":"venue"
},
  "geometry": {"coordinates":[8.5591802597,47.4253120422],"type":"Point"}
}