{
  "type": "Feature",
  "properties": {
    "iso:country":"CH",
    "sg:address":"Bernstrasse 79",
    "sg:city":"Moosseedorf",
    "sg:orig_category":"Detailhandel mit M\u00f6beln Detailhandel mit M\u00f6beln U Haushaltsgegenst\u00e4nden",
    "sg:phone":"+41 56 417 91 11",
    "sg:postcode":"3302",
    "sg:province":"Bern",
    "wof:name":"Interio Ag",
    "wof:placetype":"venue"
},
  "geometry": {"coordinates":[7.4887089729,47.0180015564],"type":"Point"}
}