{
  "type": "Feature",
  "properties": {
    "iso:country":"CH",
    "sg:address":"Steindlerstrasse 36 C 3800 Unterseen. Postfach 123",
    "sg:city":"Unterseen",
    "sg:orig_category":"Grosshandel mit sonstigen Gebrauchs U Verbrauchsg\u00fctern",
    "sg:phone":"+41 33 822 53 47",
    "sg:postcode":"3800",
    "sg:province":"Bern",
    "wof:name":"Blaser",
    "wof:placetype":"venue"
},
  "geometry": {"coordinates":[7.8363509178,46.6865768433],"type":"Point"}
}