{
  "type": "Feature",
  "properties": {
    "iso:country":"CH",
    "sg:address":"Rue Du Pr\u00e9-de-la-fontaine 13",
    "sg:city":"Meyrin",
    "sg:orig_category":"Autogaragen",
    "sg:phone":"+41 22 785 48 68",
    "sg:postcode":"1217",
    "sg:province":"Gen\u00e8ve",
    "wof:name":"Europe Garage Carmine Liquori",
    "wof:placetype":"venue"
},
  "geometry": {"coordinates":[6.072216,46.228443],"type":"Point"}
}