{
  "type": "Feature",
  "properties": {
    "iso:country":"CH",
    "sg:address":"Boulervard De Saint-georges 36",
    "sg:city":"Gen\u00e8ve",
    "sg:orig_category":"Meer U K\u00fcstenschiffahrt Reiseb\u00fcros U Reiseveranstalter",
    "sg:phone":"+41 22 781 04 04",
    "sg:postcode":"1205",
    "sg:province":"Gen\u00e8ve",
    "wof:name":"Mincar Sa",
    "wof:placetype":"venue"
},
  "geometry": {"coordinates":[6.1341657639,46.2012290955],"type":"Point"}
}