{
  "type": "Feature",
  "properties": {
    "iso:country":"CH",
    "sg:address":"Hauptstrasse 28",
    "sg:city":"Bichelsee",
    "sg:classifiers":[
        {
            "category":"Restaurant",
            "type":"Food & Drink"
        }
    ],
    "sg:phone":"+41 71 971 16 12",
    "sg:postcode":"8363",
    "sg:province":"Thurgau",
    "wof:name":"Restaurant Landhaus",
    "wof:placetype":"venue"
},
  "geometry": {"coordinates":[8.9212579727,47.4486694336],"type":"Point"}
}