{
  "type": "Feature",
  "properties": {
    "iso:country":"CH",
    "sg:address":"Route D'evian",
    "sg:city":"Aigle",
    "sg:orig_category":"Detailhandel Einzelhandel mit Automobilteilen U Zubeh\u00f6r Reparatur von Gebrauchsg\u00fctern",
    "sg:phone":"+41 24 466 11 10",
    "sg:postcode":"1860",
    "sg:province":"Vaud",
    "wof:name":"Autobur Sa",
    "wof:placetype":"venue"
},
  "geometry": {"coordinates":[6.9486808777,46.3150749207],"type":"Point"}
}