{
  "type": "Feature",
  "properties": {
    "iso:country":"CH",
    "sg:address":"Bernerstrasse Nord 208 8064 Z\u00fcrich. Postfach",
    "sg:city":"Z\u00fcrich",
    "sg:orig_category":"Schlossereien",
    "sg:phone":"+41 17256765",
    "sg:postcode":"8045",
    "sg:province":"Z\u00fcrich",
    "wof:name":"Lamina Stephan Mettler",
    "wof:placetype":"venue"
},
  "geometry": {"coordinates":[8.5988044739,47.2596664429],"type":"Point"}
}