{
  "type": "Feature",
  "properties": {
    "iso:country":"CH",
    "sg:address":"Collombey Route De 35",
    "sg:city":"Monthey",
    "sg:orig_category":"Softwareentwicklung U beratung",
    "sg:postcode":"1870",
    "sg:province":"Valais",
    "wof:name":"Colombara Val\u00e9rie",
    "wof:placetype":"venue"
},
  "geometry": {"coordinates":[6.9471468925,46.2516288757],"type":"Point"}
}