{
  "type": "Feature",
  "properties": {
    "iso:country":"CH",
    "sg:address":"Sternenstrasse 9",
    "sg:city":"Flawil",
    "sg:orig_category":"Tanzschulen, Tanzlehrer",
    "sg:phone":"+41 71 393 16 14",
    "sg:postcode":"9230",
    "sg:province":"St. Gallen",
    "wof:name":"Betty Schilling Ballet-gymnastik-studio",
    "wof:placetype":"venue"
},
  "geometry": {"coordinates":[9.1859273911,47.4149246216],"type":"Point"}
}