{
  "type": "Feature",
  "properties": {
    "iso:country":"CH",
    "sg:address":"Rue Charles-e De Rivaz",
    "sg:city":"St-maurice",
    "sg:orig_category":"Verwertung von Milch",
    "sg:phone":"+41 32 665 22 10",
    "sg:postcode":"1890",
    "sg:province":"Valais",
    "wof:name":"Max L\u00fcthi",
    "wof:placetype":"venue"
},
  "geometry": {"coordinates":[7.5586838722,47.1513328552],"type":"Point"}
}