{
  "type": "Feature",
  "properties": {
    "iso:country":"CH",
    "sg:address":"M\u00fchlentalstrasse 28",
    "sg:city":"Schaffhausen",
    "sg:orig_category":"Datenverarbeitungsdienste",
    "sg:phone":"+41 52 682 23 20",
    "sg:postcode":"8200",
    "sg:province":"Schaffhausen",
    "wof:name":"Rcs Invest Gmbh Edv-dienstleistungen",
    "wof:placetype":"venue"
},
  "geometry": {"coordinates":[8.630222,47.700619],"type":"Point"}
}