{
  "type": "Feature",
  "properties": {
    "iso:country":"CH",
    "sg:address":"Neufeldstrasse 3000 Bern. Postfach",
    "sg:city":"Bern",
    "sg:orig_category":"Detailhandel mit B\u00fcchern, Zeitungen, Schreib U Papeteriewaren",
    "sg:postcode":"3005",
    "sg:province":"Bern",
    "wof:name":"Kiosk-boutique Keller Monica",
    "wof:placetype":"venue"
},
  "geometry": {"coordinates":[7.435606,46.9585],"type":"Point"}
}