{
  "type": "Feature",
  "properties": {
    "iso:country":"CH",
    "sg:address":"Bahnhofstrasse 40",
    "sg:city":"Arbon",
    "sg:orig_category":"Reiseb\u00fcros U Reiseveranstalter",
    "sg:phone":"+41 71 447 85 00",
    "sg:postcode":"9320",
    "sg:province":"Thurgau",
    "wof:name":"Reiseb\u00fcro Fuchs Ag",
    "wof:placetype":"venue"
},
  "geometry": {"coordinates":[9.4334506989,47.5117340088],"type":"Point"}
}