{
  "type": "Feature",
  "properties": {
    "iso:country":"CH",
    "sg:address":"Bitzihofstrasse 17",
    "sg:city":"Siebnen",
    "sg:orig_category":"Wirtschaftspr\u00fcfung, Steuerberatung U Treuhand",
    "sg:phone":"+41 55 450 51 61",
    "sg:postcode":"8854",
    "sg:province":"Schwyz",
    "wof:name":"Kistler + Steiner, Treuhand + Beratung",
    "wof:placetype":"venue"
},
  "geometry": {"coordinates":[8.9044399261,47.1787490845],"type":"Point"}
}