{
  "type": "Feature",
  "properties": {
    "iso:country":"CH",
    "sg:address":"Solothurnstrasse 2",
    "sg:city":"Oensingen",
    "sg:orig_category":"Detailhandel mit M\u00f6beln U Haushaltsgegenst\u00e4nden Verlegen von Fussboden",
    "sg:phone":"+41 62 396 12 14",
    "sg:postcode":"4702",
    "sg:province":"Solothurn",
    "wof:name":"M\u00f6bel Schwaller",
    "wof:placetype":"venue"
},
  "geometry": {"coordinates":[7.7032089233,47.2829742432],"type":"Point"}
}