{
  "type": "Feature",
  "properties": {
    "iso:country":"CH",
    "sg:address":"Unterer Rheinweg 14",
    "sg:city":"Basel",
    "sg:classifiers":[
        {
            "category":"Health Services",
            "subcategory":"Nursing And Care Facility",
            "type":"Services"
        }
    ],
    "sg:phone":"+41 61 683 38 93",
    "sg:postcode":"4058",
    "sg:province":"Basel-Stadt",
    "sg:tags":[
        "electro-medical",
        "apparatus"
    ],
    "wof:name":"Morvay Analytik Gmbh",
    "wof:placetype":"venue"
},
  "geometry": {"coordinates":[7.5906229019,47.5610580444],"type":"Point"}
}