{
  "type": "Feature",
  "properties": {
    "iso:country":"CH",
    "sg:address":"Alte Gfennstrasse 23",
    "sg:city":"D\u00fcbendorf",
    "sg:orig_category":"Vereine Vogel-& Naturschutz",
    "sg:phone":"+41 18216293",
    "sg:postcode":"8600",
    "sg:province":"Z\u00fcrich",
    "wof:name":"Naturfreunde D\u00fcbendorf",
    "wof:placetype":"venue"
},
  "geometry": {"coordinates":[8.627207756,47.3950614929],"type":"Point"}
}