{
  "type": "Feature",
  "properties": {
    "addr:full":"Ennetb\u00fcrgerstrasse 1 6374 Buochs. Postfach Buochs Nidwalden 6374",
    "addr:housenumber":"1",
    "addr:postcode":"6374 buochs. postfach;6374",
    "addr:street":"Ennetbuergerstrasse",
    "iso:country":"CH",
    "sg:address":"Ennetb\u00fcrgerstrasse 1 6374 Buochs. Postfach",
    "sg:city":"Buochs",
    "sg:orig_category":"Architektur U Ingenieurb\u00fcros",
    "sg:postcode":"6374",
    "sg:province":"Nidwalden",
    "wof:name":"Achermann Risi Architekten Gmbh",
    "wof:placetype":"venue"
},
  "geometry": {"coordinates":[8.420005,46.97411],"type":"Point"}
}