{
  "type": "Feature",
  "properties": {
    "iso:country":"CH",
    "sg:address":"Hauptgasse 62",
    "sg:city":"Solothurn",
    "sg:orig_category":"Unternehmensberatung",
    "sg:phone":"+41 32 623 46 94",
    "sg:postcode":"4500",
    "sg:province":"Solothurn",
    "wof:name":"Schmutz Ewald, Atelier F\u00fcr F\u00fchrungsumsetzung",
    "wof:placetype":"venue"
},
  "geometry": {"coordinates":[7.5383229256,47.2078170776],"type":"Point"}
}