{
  "type": "Feature",
  "properties": {
    "iso:country":"CH",
    "sg:address":"Ruelle Sous-le-bourg 1",
    "sg:city":"Aigle",
    "sg:orig_category":"Detailhandel mit Fleisch U Fleischwaren",
    "sg:phone":"+41 24 466 25 85",
    "sg:postcode":"1860",
    "sg:province":"Vaud",
    "wof:name":"Boucherie Chevaline Von Euw Viandes & Salaisons S\u00e0rl",
    "wof:placetype":"venue"
},
  "geometry": {"coordinates":[6.9684481621,46.3186836243],"type":"Point"}
}