{
  "type": "Feature",
  "properties": {
    "iso:country":"CH",
    "sg:address":"1913",
    "sg:city":"Saillon",
    "sg:classifiers":[
        {
            "category":"Restaurant",
            "type":"Food & Drink"
        }
    ],
    "sg:phone":"+41 27 744 13 89",
    "sg:postcode":"1913",
    "sg:province":"Valais",
    "wof:name":"Relais De La Sarvaz Restaurant",
    "wof:placetype":"venue"
},
  "geometry": {"coordinates":[7.1852998734,46.1719093323],"type":"Point"}
}