{
  "type": "Feature",
  "properties": {
    "iso:country":"CH",
    "sg:address":"Avenue Du Vieux-bourg 14",
    "sg:city":"Ch\u00eane-bourg",
    "sg:orig_category":"Aktivit\u00e4ten der Generalunternehmen im Baugewerbe Allgemeiner Hoch U Tiefbau",
    "sg:phone":"+41 34 448 32 32",
    "sg:postcode":"1225",
    "sg:province":"Gen\u00e8ve",
    "wof:name":"M\u00fchlemann Bauunternehmung Ag",
    "wof:placetype":"venue"
},
  "geometry": {"coordinates":[7.570942,47.095043],"type":"Point"}
}