{
  "type": "Feature",
  "properties": {
    "iso:country":"CH",
    "sg:address":"Belpbergstrasse 93",
    "sg:city":"M\u00fcnsingen",
    "sg:orig_category":"Wirtschaftspr\u00fcfung, Steuerberatung U Treuhand",
    "sg:postcode":"3110",
    "sg:province":"Bern",
    "wof:name":"Treuhand Und Verwaltungsgesellschaft Zenith, Aktiengesellschaft",
    "wof:placetype":"venue"
},
  "geometry": {"coordinates":[7.5510749817,46.8672065735],"type":"Point"}
}