{
  "type": "Feature",
  "properties": {
    "iso:country":"CH",
    "sg:address":"Chemin Des Grands Champs 2 1033 Cheseaux-lausanne Case Postale 124",
    "sg:city":"Cheseaux-lausanne",
    "sg:orig_category":"Herstellung von Kunststoffwaren Siebdruck",
    "sg:phone":"+41 32 913 76 06",
    "sg:postcode":"1033",
    "sg:province":"Vaud",
    "wof:name":"Ruegg Sa La Chaux-de-fonds",
    "wof:placetype":"venue"
},
  "geometry": {"coordinates":[6.8212461472,47.1028900146],"type":"Point"}
}