{
  "type": "Feature",
  "properties": {
    "iso:country":"CH",
    "sg:address":"Unterdorf 4",
    "sg:city":"Neuenhof",
    "sg:orig_category":"Arztpraxen",
    "sg:phone":"+41 56 406 20 24",
    "sg:postcode":"5432",
    "sg:province":"Aargau",
    "wof:name":"Dr.med. Andreas Loosli Spezialarzt Fmh",
    "wof:placetype":"venue"
},
  "geometry": {"coordinates":[8.326817,47.449944],"type":"Point"}
}