{
  "type": "Feature",
  "properties": {
    "iso:country":"CH",
    "sg:address":"Cordastrasse 391",
    "sg:city":"Gurmels",
    "sg:orig_category":"Gelegenheitsflugverkehr",
    "sg:postcode":"3212",
    "sg:province":"Fribourg",
    "wof:name":"Heli-west Ag",
    "wof:placetype":"venue"
},
  "geometry": {"coordinates":[7.1673579216,46.8904571533],"type":"Point"}
}