{
  "type": "Feature",
  "properties": {
    "iso:country":"CH",
    "sg:address":"Gardi 4",
    "sg:city":"Schwyz",
    "sg:orig_category":"Non-Classified Establishments",
    "sg:postcode":"6430",
    "sg:province":"Schwyz",
    "wof:name":"Botanic-products Birrer + Beeler",
    "wof:placetype":"venue"
},
  "geometry": {"coordinates":[8.652428627,47.0216674805],"type":"Point"}
}