{
  "type": "Feature",
  "properties": {
    "iso:country":"CH",
    "sg:address":"Kantonsstrasse 153",
    "sg:city":"Freienbach",
    "sg:orig_category":"Markt U Meinungsforschung",
    "sg:postcode":"8807",
    "sg:province":"Schwyz",
    "wof:name":"Chiang Consulting",
    "wof:placetype":"venue"
},
  "geometry": {"coordinates":[8.7646446228,47.2043037415],"type":"Point"}
}