{
  "type": "Feature",
  "properties": {
    "iso:country":"CH",
    "sg:address":"Postgasse 6",
    "sg:city":"Arbon",
    "sg:orig_category":"Herstellung von sonstiger Bekleidung U Bekleidungszubeh\u00f6r",
    "sg:phone":"+41 71 446 49 59",
    "sg:postcode":"9320",
    "sg:province":"Thurgau",
    "wof:name":"B\u00fcchler M. Baby-center",
    "wof:placetype":"venue"
},
  "geometry": {"coordinates":[9.4358272552,47.5156326294],"type":"Point"}
}