{
  "type": "Feature",
  "properties": {
    "iso:country":"CH",
    "sg:address":"Fidmenstrasse 9",
    "sg:city":"Gersau",
    "sg:orig_category":"Kauf U Verkauf von Immobilien auf eigene Rechnung",
    "sg:postcode":"6442",
    "sg:province":"Schwyz",
    "wof:name":"Mfti Merchant Financial Trust & Investment Ag",
    "wof:placetype":"venue"
},
  "geometry": {"coordinates":[8.3102197647,46.9972305298],"type":"Point"}
}