{
  "type": "Feature",
  "properties": {
    "iso:country":"CH",
    "sg:address":"Romanshornerstrasse 4",
    "sg:city":"Arbon",
    "sg:classifiers":[
        {
            "category":"Government",
            "subcategory":"Fire Station",
            "type":"Public Place"
        }
    ],
    "sg:phone":"+41 71 447 41 41",
    "sg:postcode":"9320",
    "sg:province":"Thurgau",
    "sg:tags":[
        "steel",
        "stainless",
        "drain",
        "trough"
    ],
    "wof:name":"Herman Forster Ag Stahlrohrtechnik",
    "wof:placetype":"venue"
},
  "geometry": {"coordinates":[9.4318971634,47.5167617798],"type":"Point"}
}