{
  "type": "Feature",
  "properties": {
    "iso:country":"CH",
    "sg:address":"Leimackerstrasse 6a 8583 Sulgen. Postfach 32",
    "sg:city":"Sulgen",
    "sg:orig_category":"Instandhaltung U Reparatur von Automobilen",
    "sg:postcode":"8583",
    "sg:province":"Thurgau",
    "wof:name":"Dorfgarage Uetikon, Enrico Rindlisbacher",
    "wof:placetype":"venue"
},
  "geometry": {"coordinates":[8.6789388657,47.2651596069],"type":"Point"}
}