{
  "type": "Feature",
  "properties": {
    "iso:country":"CH",
    "sg:address":"Bernstrasse 46 3072 Ostermundigen. Postfach",
    "sg:city":"Ostermundigen",
    "sg:orig_category":"Versicherungen Generalagenturen",
    "sg:phone":"+41 71 913 96 10",
    "sg:postcode":"3072",
    "sg:province":"Bern",
    "wof:name":"Winterthur-versicherungen Generalagentur",
    "wof:placetype":"venue"
},
  "geometry": {"coordinates":[9.0437936783,47.4658126831],"type":"Point"}
}