{
  "type": "Feature",
  "properties": {
    "iso:country":"CH",
    "sg:address":"Besson Avenue Fran\u00e7ois- 21",
    "sg:city":"Meyrin",
    "sg:orig_category":"Fachdetailhandel in Verkaufsr\u00e4umen",
    "sg:postcode":"1217",
    "sg:province":"Gen\u00e8ve",
    "wof:name":"Sultana Traders, Mr Et Mme Sualeheen",
    "wof:placetype":"venue"
},
  "geometry": {"coordinates":[6.0770421028,46.2350311279],"type":"Point"}
}