{
  "type": "Feature",
  "properties": {
    "iso:country":"CH",
    "sg:address":"Lerzenstrasse 13a",
    "sg:city":"Dietikon",
    "sg:orig_category":"Handelsvermittlung U Grosshandel mit Automobilteilen U Zubeh\u00f6r Pensionskassen",
    "sg:phone":"+41 61 811 66 00",
    "sg:postcode":"8953",
    "sg:province":"Z\u00fcrich",
    "wof:name":"Wohlfahrtsfonds Der Bridgestone/firestone (schweiz) Ag Depot",
    "wof:placetype":"venue"
},
  "geometry": {"coordinates":[8.3989973068,47.4171142578],"type":"Point"}
}