{
  "type": "Feature",
  "properties": {
    "iso:country":"CH",
    "sg:address":"Falkenriedweg 43 3032 Hinterkappelen. Postfach 135",
    "sg:city":"Hinterkappelen",
    "sg:orig_category":"Grosshandel mit sonstigen Maschinen U Ausr\u00fcstungen f\u00fcr Industrie, Handel U Schiffahrt",
    "sg:phone":"+41 31 901 02 03",
    "sg:postcode":"3032",
    "sg:province":"Bern",
    "wof:name":"M\u00fcller-technik Ag",
    "wof:placetype":"venue"
},
  "geometry": {"coordinates":[7.3903479576,46.9687385559],"type":"Point"}
}