{
  "type": "Feature",
  "properties": {
    "iso:country":"CH",
    "sg:address":"Ch. Du Pont-du-centenaire 15",
    "sg:city":"Onex",
    "sg:orig_category":"Architekturb\u00fcros",
    "sg:phone":"+41 22 793 98 46",
    "sg:postcode":"1213",
    "sg:province":"Gen\u00e8ve",
    "wof:name":"Werner Meier Bureau D'architecture",
    "wof:placetype":"venue"
},
  "geometry": {"coordinates":[6.099705,46.178841],"type":"Point"}
}