{
  "type": "Feature",
  "properties": {
    "addr:full":"Bruechstrasse 136 Meilen Z\u00fcrich 8706",
    "addr:housenumber":"136",
    "addr:postcode":"8706",
    "addr:street":"Bruechstrasse",
    "iso:country":"CH",
    "sg:address":"Bruechstrasse 136",
    "sg:city":"Meilen",
    "sg:classifiers":[
        {
            "category":"Manufacturing",
            "subcategory":"Furniture",
            "type":"Manufacturing & Wholesale Goods"
        }
    ],
    "sg:phone":"+41 19233555",
    "sg:postcode":"8706",
    "sg:province":"Z\u00fcrich",
    "sg:tags":[
        "bedroom"
    ],
    "wof:name":"Rolf Aeschlimann",
    "wof:placetype":"venue"
},
  "geometry": {"coordinates":[8.649194,47.269157],"type":"Point"}
}