{
  "type": "Feature",
  "properties": {
    "addr:full":"Via Manzoni 4 Lugano Ticino 6900",
    "addr:housenumber":"4",
    "addr:postcode":"6900",
    "addr:street":"Via Manzoni",
    "iso:country":"CH",
    "sg:address":"Via Manzoni 4",
    "sg:city":"Lugano",
    "sg:orig_category":"Aktivit\u00e4t der Bankinstitute",
    "sg:phone":"+41 22 818 53 15",
    "sg:postcode":"6900",
    "sg:province":"Ticino",
    "wof:name":"Cim Banque",
    "wof:placetype":"venue"
},
  "geometry": {"coordinates":[6.148087,46.20166],"type":"Point"}
}