{
  "type": "Feature",
  "properties": {
    "iso:country":"CH",
    "sg:address":"Schachenstrasse 2",
    "sg:city":"Oberg\u00f6sgen",
    "sg:orig_category":"Vereine Gesang",
    "sg:phone":"+41 62 295 45 12",
    "sg:postcode":"4653",
    "sg:province":"Solothurn",
    "wof:name":"Musikgesellschaft Oberg\u00f6sgen",
    "wof:placetype":"venue"
},
  "geometry": {"coordinates":[7.9524288177,47.3637733459],"type":"Point"}
}