{
  "type": "Feature",
  "properties": {
    "iso:country":"CH",
    "sg:address":"Bumbach",
    "sg:city":"Bumbach",
    "sg:classifiers":[
        {
            "category":"Travel",
            "subcategory":"Hotels & Motels",
            "type":"Entertainment"
        }
    ],
    "sg:phone":"+41 34 493 31 33",
    "sg:postcode":"6197",
    "sg:province":"Bern",
    "sg:tags":[
        "hotels",
        "mit",
        "restaurant"
    ],
    "wof:name":"Gasthof Alpenrose Ag",
    "wof:placetype":"venue"
},
  "geometry": {"coordinates":[7.9009509087,46.8138618469],"type":"Point"}
}