{
  "type": "Feature",
  "properties": {
    "iso:country":"CH",
    "sg:address":"Via San Gottardo 15",
    "sg:city":"Tenero",
    "sg:orig_category":"Chemische Reinigung Teppichreinigung",
    "sg:phone":"+41 91 745 03 04",
    "sg:postcode":"6598",
    "sg:province":"Ticino",
    "wof:name":"Qiuck-net Lavanderia",
    "wof:placetype":"venue"
},
  "geometry": {"coordinates":[8.846667,46.179714],"type":"Point"}
}