{
  "type": "Feature",
  "properties": {
    "iso:country":"CH",
    "sg:address":"Magergasse 2",
    "sg:city":"Igis",
    "sg:orig_category":"Gartenbau",
    "sg:postcode":"7206",
    "sg:province":"Graubunden",
    "wof:name":"Floraris Caluna Gmbh",
    "wof:placetype":"venue"
},
  "geometry": {"coordinates":[9.573759079,46.9455604553],"type":"Point"}
}