{
  "type": "Feature",
  "properties": {
    "iso:country":"CH",
    "sg:address":"Romanshornerstr. 10 9303 Wittenbach. Postfach",
    "sg:city":"Kronb\u00fchl",
    "sg:classifiers":[
        {
            "category":"Travel",
            "subcategory":"Hotels & Motels",
            "type":"Entertainment"
        }
    ],
    "sg:postcode":"9302",
    "sg:tags":[
        "hotels",
        "mit",
        "restaurant"
    ],
    "wof:name":"Gasthaus Und B\u00e4ckerei Sonne Niederhauser Alfred",
    "wof:placetype":"venue"
},
  "geometry": {"coordinates":[8.0160102844,46.8831787109],"type":"Point"}
}