{
  "type": "Feature",
  "properties": {
    "iso:country":"CH",
    "sg:address":"G\u00fcterstrasse 291",
    "sg:city":"Basel",
    "sg:orig_category":"Sonstiger Grosshandel",
    "sg:postcode":"4053",
    "sg:province":"Basel-Stadt",
    "wof:name":"Janiak's Trading & Consulting",
    "wof:placetype":"venue"
},
  "geometry": {"coordinates":[7.6006278992,47.5412254333],"type":"Point"}
}