{
  "type": "Feature",
  "properties": {
    "iso:country":"CH",
    "sg:address":"Kapellgasse 3 6004 Luzern. Postfach",
    "sg:city":"Luzern",
    "sg:orig_category":"Druckweiterverarbeitung",
    "sg:postcode":"6003",
    "sg:province":"Luzern",
    "wof:name":"Wave-advertising Ag",
    "wof:placetype":"venue"
},
  "geometry": {"coordinates":[8.3073825836,47.0524559021],"type":"Point"}
}