{
  "type": "Feature",
  "properties": {
    "iso:country":"CH",
    "sg:address":"Heimatstrasse 6 8008 Z\u00fcrich. Postfach",
    "sg:city":"Z\u00fcrich",
    "sg:orig_category":"Verlagsgewerbe",
    "sg:phone":"+41 13822425",
    "sg:postcode":"8034",
    "sg:province":"Z\u00fcrich",
    "wof:name":"Gabriela Omlin A & O Des Wissens Verlag",
    "wof:placetype":"venue"
},
  "geometry": {"coordinates":[8.5540351868,47.353969574],"type":"Point"}
}