{
  "type": "Feature",
  "properties": {
    "iso:country":"CH",
    "sg:address":"R\u00fcegsaustrasse 35",
    "sg:city":"R\u00fcegsau",
    "sg:orig_category":"Wirtschaftspr\u00fcfung, Steuerberatung U Treuhand",
    "sg:phone":"+41 34 460 50 50",
    "sg:postcode":"3417",
    "sg:province":"Bern",
    "wof:name":"Emme Treuhand Reist + Stalder",
    "wof:placetype":"venue"
},
  "geometry": {"coordinates":[7.6641402245,47.0201187134],"type":"Point"}
}