{
  "type": "Feature",
  "properties": {
    "iso:country":"CH",
    "sg:address":"Sch\u00f6nb\u00fchlstrasse 10",
    "sg:city":"Z\u00fcrich",
    "sg:orig_category":"Werbeagenturen",
    "sg:phone":"+41 12567087",
    "sg:postcode":"8032",
    "sg:province":"Z\u00fcrich",
    "wof:name":"Catchup Communications Ag",
    "wof:placetype":"venue"
},
  "geometry": {"coordinates":[8.5579843521,47.3698806763],"type":"Point"}
}