{
  "type": "Feature",
  "properties": {
    "iso:country":"CH",
    "sg:address":"Paradiesstrasse 9",
    "sg:city":"Jona",
    "sg:orig_category":"Unternehmensberatung",
    "sg:phone":"+41 55 210 70 61",
    "sg:postcode":"8645",
    "sg:province":"St. Gallen",
    "wof:name":"Mfs Zuppiger",
    "wof:placetype":"venue"
},
  "geometry": {"coordinates":[8.8153371811,47.2405662537],"type":"Point"}
}