{
  "type": "Feature",
  "properties": {
    "addr:full":"Sch\u00f6nb\u00fchlring 7 Luzern Luzern 6005",
    "addr:housenumber":"7",
    "addr:postcode":"6005",
    "addr:street":"Schoenbuehlring",
    "iso:country":"CH",
    "sg:address":"Sch\u00f6nb\u00fchlring 7",
    "sg:city":"Luzern",
    "sg:orig_category":"Arztpraxen",
    "sg:phone":"+41 41 360 11 41",
    "sg:postcode":"6005",
    "sg:province":"Luzern",
    "wof:name":"Dr.med.arnold Schl\u00e4pfer Spezialarzt Fmh",
    "wof:placetype":"venue"
},
  "geometry": {"coordinates":[8.326043,47.038643],"type":"Point"}
}