{
  "type": "Feature",
  "properties": {
    "iso:country":"CH",
    "sg:address":"Niederhaslistrasse 4",
    "sg:city":"Regensdorf",
    "sg:orig_category":"Herstellung von Pflanzenschutzmitteln U sonstigen agro- chemikalischen Erzeugnissen",
    "sg:phone":"+41 18431070",
    "sg:postcode":"8105",
    "sg:province":"Z\u00fcrich",
    "wof:name":"Nb (suisse) Ag",
    "wof:placetype":"venue"
},
  "geometry": {"coordinates":[8.4817285538,47.4430961609],"type":"Point"}
}