{
  "type": "Feature",
  "properties": {
    "iso:country":"CH",
    "sg:address":"Brunismatt",
    "sg:city":"Wattenwil",
    "sg:orig_category":"Polizei",
    "sg:phone":"+41 33 356 11 17",
    "sg:postcode":"3665",
    "sg:province":"Bern",
    "wof:name":"Kantonale Polizei",
    "wof:placetype":"venue"
},
  "geometry": {"coordinates":[7.5088400841,46.7714729309],"type":"Point"}
}