{
  "type": "Feature",
  "properties": {
    "iso:country":"CH",
    "sg:address":"Chemin Des Epinettes 1",
    "sg:city":"Lausanne",
    "sg:orig_category":"Architektur U Ingenieurb\u00fcros Architekturb\u00fcros",
    "sg:phone":"+41 21 617 41 27",
    "sg:postcode":"1007",
    "sg:province":"Vaud",
    "wof:name":"Atelier Des Architectes Dembowski Et Kyburz S\u00e0rl",
    "wof:placetype":"venue"
},
  "geometry": {"coordinates":[6.623959,46.517029],"type":"Point"}
}