{
  "type": "Feature",
  "properties": {
    "iso:country":"CH",
    "sg:address":"Hauptstrasse 110",
    "sg:city":"Kreuzlingen",
    "sg:orig_category":"Detailhandel mit Teppichen Fachdetailhandel in Verkaufsr\u00e4umen",
    "sg:phone":"+41 71 672 77 30",
    "sg:postcode":"8280",
    "sg:province":"Thurgau",
    "wof:name":"Ali Orient-teppiche, Khorramabadi.",
    "wof:placetype":"venue"
},
  "geometry": {"coordinates":[9.1796808243,47.6446495056],"type":"Point"}
}