{
  "type": "Feature",
  "properties": {
    "iso:country":"CH",
    "sg:address":"Dorfstrasse 16",
    "sg:city":"Bennwil",
    "sg:orig_category":"Bauschreinerei",
    "sg:phone":"+41 79 407 97 41",
    "sg:postcode":"4431",
    "sg:province":"Basel-Landschaft",
    "wof:name":"Andy Junker Schreinerei",
    "wof:placetype":"venue"
},
  "geometry": {"coordinates":[7.778892,47.401966],"type":"Point"}
}