{
  "type": "Feature",
  "properties": {
    "iso:country":"CH",
    "sg:address":"S\u00e4gestrasse 51 5600 Lenzburg. Postfach",
    "sg:city":"Lenzburg",
    "sg:orig_category":"Instandhaltung U Reparatur von Automobilen",
    "sg:postcode":"5600",
    "sg:province":"Aargau",
    "wof:name":"Yilmaz S., Handel, Autotechnik + Elektronik Motorfahrzeuge U. Zubeh\u00f6r; Reparatur U. Handel",
    "wof:placetype":"venue"
},
  "geometry": {"coordinates":[9.544678688,47.4842567444],"type":"Point"}
}