{
  "type": "Feature",
  "properties": {
    "iso:country":"CH",
    "sg:address":"Le Champ-du-clos",
    "sg:city":"Villars-tiercelin",
    "sg:orig_category":"Tierarztpraxis",
    "sg:phone":"+41 21 903 29 00",
    "sg:postcode":"1058",
    "sg:province":"Vaud",
    "wof:name":"Dr M\u00e9d. V\u00e9t. Gabriel Daenzer M\u00e9decin V\u00e9t\u00e9rinaire",
    "wof:placetype":"venue"
},
  "geometry": {"coordinates":[6.7044100761,46.6248016357],"type":"Point"}
}