{
  "type": "Feature",
  "properties": {
    "iso:country":"CH",
    "sg:address":"Forstweg 65",
    "sg:city":"Bern",
    "sg:orig_category":"Geb\u00e4ude, Wohnungsreinigung",
    "sg:phone":"+41 31 302 38 60",
    "sg:postcode":"3012",
    "sg:province":"Bern",
    "wof:name":"Hermann Zumbach Reinigungen",
    "wof:placetype":"venue"
},
  "geometry": {"coordinates":[7.4245948792,46.9556427002],"type":"Point"}
}