{
  "type": "Feature",
  "properties": {
    "iso:country":"CH",
    "sg:address":"Zollikerstrasse 4",
    "sg:city":"Zollikon",
    "sg:orig_category":"Elektroinstallation",
    "sg:phone":"+41 13914540",
    "sg:postcode":"8702",
    "sg:province":"Z\u00fcrich",
    "wof:name":"Heinrich Brandenberg Ag Elektrische Installationen",
    "wof:placetype":"venue"
},
  "geometry": {"coordinates":[8.567027092,47.3468437195],"type":"Point"}
}