{
  "type": "Feature",
  "properties": {
    "iso:country":"CH",
    "sg:address":"Sensemattstrasse",
    "sg:city":"Th\u00f6rishaus",
    "sg:orig_category":"Vorschulen, Kinderg\u00e4rten",
    "sg:phone":"+41 31 889 00 79",
    "sg:postcode":"3174",
    "sg:province":"Bern",
    "wof:name":"Kindergarten",
    "wof:placetype":"venue"
},
  "geometry": {"coordinates":[7.3514051437,46.8927650452],"type":"Point"}
}