{
  "type": "Feature",
  "properties": {
    "iso:country":"CH",
    "sg:address":"Pfistergasse 8",
    "sg:city":"Luzern",
    "sg:orig_category":"Detailhandel mit M\u00f6beln Detailhandel mit M\u00f6beln U Haushaltsgegenst\u00e4nden",
    "sg:phone":"+41 41 241 14 41",
    "sg:postcode":"6003",
    "sg:province":"Luzern",
    "wof:name":"Wohn Team Collection",
    "wof:placetype":"venue"
},
  "geometry": {"coordinates":[8.3027515411,47.0507049561],"type":"Point"}
}