{
  "type": "Feature",
  "properties": {
    "iso:country":"CH",
    "sg:address":"Haldenstrasse 6",
    "sg:city":"Mels",
    "sg:classifiers":[
        {
            "category":"Professional",
            "subcategory":"Computer Services",
            "type":"Services"
        }
    ],
    "sg:phone":"+41 81 710 53 30",
    "sg:postcode":"8887",
    "sg:province":"St. Gallen",
    "sg:tags":[
        "development",
        "software"
    ],
    "wof:name":"Eniosoft",
    "wof:placetype":"venue"
},
  "geometry": {"coordinates":[9.4168901443,47.0452613831],"type":"Point"}
}