{
  "type": "Feature",
  "properties": {
    "iso:country":"CH",
    "sg:address":"6544",
    "sg:city":"Braggio",
    "sg:orig_category":"Sportvereine Ski",
    "sg:phone":"+41 91 828 12 41",
    "sg:postcode":"6544",
    "sg:province":"Graubunden",
    "wof:name":"Sci Club Braggio",
    "wof:placetype":"venue"
},
  "geometry": {"coordinates":[9.1235952377,46.3029937744],"type":"Point"}
}