{
  "type": "Feature",
  "properties": {
    "iso:country":"CH",
    "sg:address":"Schachenstrasse 15",
    "sg:city":"Oensingen",
    "sg:orig_category":"Vorschulen, Kinderg\u00e4rten",
    "sg:phone":"+41 62 396 25 17",
    "sg:postcode":"4702",
    "sg:province":"Solothurn",
    "wof:name":"Kindergarten Schachen",
    "wof:placetype":"venue"
},
  "geometry": {"coordinates":[7.7118749619,47.2891616821],"type":"Point"}
}