{
  "type": "Feature",
  "properties": {
    "iso:country":"CH",
    "sg:address":"Fabrikstrasse 3",
    "sg:city":"Hinwil",
    "sg:orig_category":"Tanzschulen, Tanzlehrer",
    "sg:phone":"+41 19375152",
    "sg:postcode":"8340",
    "sg:province":"Z\u00fcrich",
    "wof:name":"Elvira Gautschi Gymnastik-& Tanzschule",
    "wof:placetype":"venue"
},
  "geometry": {"coordinates":[8.8384313583,47.2996177673],"type":"Point"}
}