{
  "type": "Feature",
  "properties": {
    "iso:country":"CH",
    "sg:address":"Forchstrasse 182",
    "sg:city":"Z\u00fcrich",
    "sg:classifiers":[
        {
            "category":"Personal",
            "subcategory":"Sauna",
            "type":"Services"
        }
    ],
    "sg:phone":"+41 14227530",
    "sg:postcode":"8032",
    "sg:province":"Z\u00fcrich",
    "wof:name":"Sauna 182 Frau Irmgard Rombach",
    "wof:placetype":"venue"
},
  "geometry": {"coordinates":[8.5666389465,47.360206604],"type":"Point"}
}