{
  "type": "Feature",
  "properties": {
    "iso:country":"CH",
    "sg:address":"T\u00f6distrasse 107",
    "sg:city":"Thalwil",
    "sg:orig_category":"Sportvereine Ballsport Handball",
    "sg:phone":"+41 17200948",
    "sg:postcode":"8800",
    "sg:province":"Z\u00fcrich",
    "wof:name":"Tv Thalwil",
    "wof:placetype":"venue"
},
  "geometry": {"coordinates":[8.5609340668,47.2943344116],"type":"Point"}
}