{
  "type": "Feature",
  "properties": {
    "iso:country":"CH",
    "sg:address":"Chemin Du Ch\u00e2telard 1",
    "sg:city":"Cheseaux-lausanne",
    "sg:orig_category":"Finanzierungsinstitutionen",
    "sg:phone":"+41 21 731 18 88",
    "sg:postcode":"1033",
    "sg:province":"Vaud",
    "wof:name":"Ci Com Sa",
    "wof:placetype":"venue"
},
  "geometry": {"coordinates":[6.5928339958,46.5791282654],"type":"Point"}
}