{
  "type": "Feature",
  "properties": {
    "iso:country":"CH",
    "sg:address":"Hauptstrasse 60 4132 Muttenz. Postfach 576",
    "sg:city":"Muttenz",
    "sg:orig_category":"Gewinnung von Kies U Sand",
    "sg:phone":"+41 61 465 92 00",
    "sg:postcode":"4132",
    "sg:province":"Basel-Landschaft",
    "wof:name":"Karl Meyer-spinnler Ag",
    "wof:placetype":"venue"
},
  "geometry": {"coordinates":[7.647195816,47.5258293152],"type":"Point"}
}