{
  "type": "Feature",
  "properties": {
    "iso:country":"CH",
    "sg:address":"Sport-motel",
    "sg:city":"Zweisimmen",
    "sg:classifiers":[
        {
            "category":"Travel",
            "subcategory":"Hotels & Motels",
            "type":"Entertainment"
        }
    ],
    "sg:phone":"+41 33 729 80 80",
    "sg:postcode":"3770",
    "sg:province":"Bern",
    "sg:tags":[
        "hotels",
        "mit",
        "restaurant"
    ],
    "wof:name":"Sport-motel Zweisimmen Ag",
    "wof:placetype":"venue"
},
  "geometry": {"coordinates":[7.3726348877,46.5528755188],"type":"Point"}
}