{
  "type": "Feature",
  "properties": {
    "iso:country":"CH",
    "sg:address":"Bahnhofplatz 1",
    "sg:city":"Brunnen",
    "sg:orig_category":"G\u00fcterbef\u00f6rderung im Strassenverkehr",
    "sg:postcode":"6440",
    "sg:province":"Schwyz",
    "wof:name":"Elstner Transporte",
    "wof:placetype":"venue"
},
  "geometry": {"coordinates":[8.606710434,47.000377655],"type":"Point"}
}