{
  "type": "Feature",
  "properties": {
    "iso:country":"CH",
    "sg:address":"Sur-le-bochet",
    "sg:city":"Chernex",
    "sg:orig_category":"D\u00e4mmung gegen K\u00e4lte, W\u00e4rme, Schall U Ersch\u00fctterung",
    "sg:phone":"+41 21 964 56 78",
    "sg:postcode":"1822",
    "sg:province":"Vaud",
    "wof:name":"Rossire Raymond",
    "wof:placetype":"venue"
},
  "geometry": {"coordinates":[6.9113750458,46.4435462952],"type":"Point"}
}