{
  "type": "Feature",
  "properties": {
    "addr:full":"Kirchstrasse 8 9490 Vaduz. Postfach 1533 Vaduz 9490",
    "addr:housenumber":"8",
    "addr:postcode":"9490 vaduz. postfach 1533;9490",
    "addr:street":"Kirchstrasse",
    "iso:country":"CH",
    "sg:address":"Kirchstrasse 8 9490 Vaduz. Postfach 1533",
    "sg:city":"Vaduz",
    "sg:orig_category":"Aktivit\u00e4t der Bankinstitute",
    "sg:phone":"+41 75 236 07 77",
    "sg:postcode":"9490",
    "wof:name":"Neue Bank Ag",
    "wof:placetype":"venue"
},
  "geometry": {"coordinates":[9.520548,47.136913],"type":"Point"}
}