{
  "type": "Feature",
  "properties": {
    "iso:country":"CH",
    "sg:address":"Grand-rue 68",
    "sg:city":"Morges",
    "sg:orig_category":"Non-Classified Establishments",
    "sg:postcode":"1110",
    "sg:province":"Vaud",
    "wof:name":"Visilab Morges Optique",
    "wof:placetype":"venue"
},
  "geometry": {"coordinates":[6.4978780746,46.5088691711],"type":"Point"}
}