{
  "type": "Feature",
  "properties": {
    "iso:country":"CH",
    "sg:address":"Place Du Temple 12",
    "sg:city":"Cossonay-ville",
    "sg:orig_category":"Allgemeiner Hoch U Tiefbau",
    "sg:postcode":"1304",
    "sg:province":"Vaud",
    "wof:name":"Gewerbe-bau Hinwil Ag",
    "wof:placetype":"venue"
},
  "geometry": {"coordinates":[8.847535,47.299946],"type":"Point"}
}