{
  "type": "Feature",
  "properties": {
    "iso:country":"CH",
    "sg:address":"Tuileries Chemin Des 3",
    "sg:city":"Bellevue",
    "sg:orig_category":"Finanzierungsinstitutionen",
    "sg:phone":"+41 22 774 19 91",
    "sg:postcode":"1293",
    "sg:province":"Gen\u00e8ve",
    "wof:name":"Sete Advisory Services Sa",
    "wof:placetype":"venue"
},
  "geometry": {"coordinates":[6.1551737785,46.2550239563],"type":"Point"}
}