{
  "type": "Feature",
  "properties": {
    "iso:country":"CH",
    "sg:address":"Alterswiler Strasse",
    "sg:city":"Siegershausen",
    "sg:orig_category":"Detailhandel mit Waren verschiedener Art, Hauptrichtung Nahrungsmittel",
    "sg:phone":"+41 71 697 00 89",
    "sg:postcode":"8573",
    "sg:province":"Thurgau",
    "wof:name":"Landi Kemmental",
    "wof:placetype":"venue"
},
  "geometry": {"coordinates":[9.1667299271,47.6101837158],"type":"Point"}
}