{
  "type": "Feature",
  "properties": {
    "iso:country":"CH",
    "sg:address":"Rappenhalde 11",
    "sg:city":"Effretikon",
    "sg:orig_category":"Datenverarbeitungsdienste Softwareentwicklung U beratung",
    "sg:phone":"+41 71 910 13 86",
    "sg:postcode":"8307",
    "sg:province":"Z\u00fcrich",
    "wof:name":"L-informatik Lehmann M.",
    "wof:placetype":"venue"
},
  "geometry": {"coordinates":[9.050227,47.455578],"type":"Point"}
}