{
  "type": "Feature",
  "properties": {
    "iso:country":"CH",
    "sg:address":"Feldbachstrasse 80",
    "sg:city":"Hombrechtikon",
    "sg:orig_category":"Help Desk Systems Software",
    "sg:phone":"+41 55 254 12 54",
    "sg:postcode":"8634",
    "sg:province":"Z\u00fcrich",
    "wof:name":"Frox Communication Ag",
    "wof:placetype":"venue"
},
  "geometry": {"coordinates":[8.781375885,47.2455368042],"type":"Point"}
}