{
  "type": "Feature",
  "properties": {
    "iso:country":"CH",
    "sg:address":"Fr\u00e9d\u00e9ric-ingold-weg 5 U. 5a 2500 Biel/bienne. Postfach",
    "sg:city":"Biel/bienne",
    "sg:orig_category":"Herstellung von Uhren",
    "sg:phone":"+41 32 913 18 08",
    "sg:postcode":"2500",
    "sg:province":"Bern",
    "wof:name":"Gomez, Modesto",
    "wof:placetype":"venue"
},
  "geometry": {"coordinates":[6.8196291924,47.1000747681],"type":"Point"}
}