{
  "type": "Feature",
  "properties": {
    "iso:country":"CH",
    "sg:address":"Chalet Am Alten Grimselweg",
    "sg:city":"Obergesteln",
    "sg:orig_category":"Unclassifiable Establishments",
    "sg:postcode":"3981",
    "wof:name":"Alnova Ag",
    "wof:placetype":"venue"
},
  "geometry": {"coordinates":[8.1907701492,46.4355049133],"type":"Point"}
}