{
  "type": "Feature",
  "properties": {
    "iso:country":"CH",
    "sg:address":"Rue De La Gare 5",
    "sg:city":"Montreux",
    "sg:orig_category":"Betrieb von Taxis",
    "sg:phone":"+41 21 963 41 30",
    "sg:postcode":"1820",
    "sg:province":"Vaud",
    "wof:name":"Gaston Jolidon Taxi Gare Mob",
    "wof:placetype":"venue"
},
  "geometry": {"coordinates":[6.908729,46.437511],"type":"Point"}
}