{
  "type": "Feature",
  "properties": {
    "iso:country":"CH",
    "sg:address":"H\u00f6henweg 15",
    "sg:city":"Berikon",
    "sg:orig_category":"Fernmeldedienste",
    "sg:phone":"+41 56 633 91 03",
    "sg:postcode":"8965",
    "sg:province":"Aargau",
    "wof:name":"Clipboard Communication H\u00fcsser & Co.",
    "wof:placetype":"venue"
},
  "geometry": {"coordinates":[8.3648643494,47.3557319641],"type":"Point"}
}