{
  "type": "Feature",
  "properties": {
    "iso:country":"CH",
    "sg:address":"B\u00fcelenweg 17 8820 W\u00e4denswil. Postfach",
    "sg:city":"W\u00e4denswil",
    "sg:orig_category":"Sonstiger Grosshandel",
    "sg:postcode":"8820",
    "sg:province":"Z\u00fcrich",
    "wof:name":"Colombo Donald, Dc Dental Ag.",
    "wof:placetype":"venue"
},
  "geometry": {"coordinates":[8.6617288589,47.2332382202],"type":"Point"}
}