{
  "type": "Feature",
  "properties": {
    "iso:country":"CH",
    "sg:address":"Bruggweg 10",
    "sg:city":"Dornach",
    "sg:orig_category":"Innendekorationsateliers",
    "sg:phone":"+41 61 702 01 06",
    "sg:postcode":"4143",
    "sg:province":"Solothurn",
    "wof:name":"Heinrich Geisinger Innendekorationen",
    "wof:placetype":"venue"
},
  "geometry": {"coordinates":[7.6095252037,47.48777771],"type":"Point"}
}