{
  "type": "Feature",
  "properties": {
    "iso:country":"CH",
    "sg:address":"Via Dil Bogn 16",
    "sg:city":"Sedrun",
    "sg:orig_category":"Schwimmb\u00e4der",
    "sg:phone":"+41 33 733 19 01",
    "sg:postcode":"7188",
    "sg:province":"Graubunden",
    "wof:name":"Hallenbad Ag Wallbach",
    "wof:placetype":"venue"
},
  "geometry": {"coordinates":[7.4244599342,46.4599838257],"type":"Point"}
}