{
  "type": "Feature",
  "properties": {
    "iso:country":"CH",
    "sg:address":"Santeri Via 73",
    "sg:city":"Ilanz",
    "sg:orig_category":"Instandhaltung U Reparatur von Automobilen",
    "sg:phone":"+41 21 800 33 37",
    "sg:postcode":"7130",
    "sg:province":"Graubunden",
    "wof:name":"Castelli G.",
    "wof:placetype":"venue"
},
  "geometry": {"coordinates":[6.4544811249,46.5707092285],"type":"Point"}
}