{
  "type": "Feature",
  "properties": {
    "iso:country":"CH",
    "sg:address":"Limmatstrasse 33",
    "sg:city":"Z\u00fcrich",
    "sg:orig_category":"Fotografische Ateliers",
    "sg:phone":"+41 12721043",
    "sg:postcode":"8005",
    "sg:province":"Z\u00fcrich",
    "wof:name":"Pitsch Schmid Fotografisches Atelier Pitsch",
    "wof:placetype":"venue"
},
  "geometry": {"coordinates":[8.5361061096,47.3810539246],"type":"Point"}
}