{
  "type": "Feature",
  "properties": {
    "iso:country":"CH",
    "sg:address":"M\u00fchlegasse 12a 6340 Baar. Postfach 2260",
    "sg:city":"Baar",
    "sg:orig_category":"Grosshandel mit chemischen Erzeugnissen Grosshandel mit pharmazeutischen Erzeugnissen, medizinischen",
    "sg:phone":"+41 41 766 09 08",
    "sg:postcode":"6342",
    "sg:province":"Zug",
    "wof:name":"Multivers Sa",
    "wof:placetype":"venue"
},
  "geometry": {"coordinates":[8.5280370712,47.1993522644],"type":"Point"}
}