{
  "type": "Feature",
  "properties": {
    "iso:country":"CH",
    "sg:address":"Wenkenhaldenweg 8 4125 Riehen. Postfach",
    "sg:city":"Riehen",
    "sg:orig_category":"Unternehmensberatung",
    "sg:postcode":"4125",
    "sg:province":"Basel-Stadt",
    "wof:name":"Pro Transfer, Krieg B.",
    "wof:placetype":"venue"
},
  "geometry": {"coordinates":[7.6526699066,47.5785751343],"type":"Point"}
}