{
  "type": "Feature",
  "properties": {
    "iso:country":"CH",
    "sg:address":"Stella Via 10",
    "sg:city":"Mendrisio",
    "sg:orig_category":"Stukkateurgewerbe, Gipserei U Verputzerei",
    "sg:postcode":"6850",
    "sg:province":"Ticino",
    "wof:name":"Oceana Sagl",
    "wof:placetype":"venue"
},
  "geometry": {"coordinates":[8.9878873825,45.8718032837],"type":"Point"}
}