{
  "type": "Feature",
  "properties": {
    "iso:country":"CH",
    "sg:address":"Bahnhofstrasse 40",
    "sg:city":"Landquart",
    "sg:orig_category":"Detailhandel mit elektrischen Haushalts, Radio U Fernsehger\u00e4ten ohne ausgepr\u00e4gten Schwerpunkt Elektr",
    "sg:phone":"+41 55 240 88 00",
    "sg:postcode":"7302",
    "sg:province":"Graubunden",
    "wof:name":"Elektro Frauchiger Ag",
    "wof:placetype":"venue"
},
  "geometry": {"coordinates":[8.8613977432,47.2599487305],"type":"Point"}
}