{
  "type": "Feature",
  "properties": {
    "iso:country":"CH",
    "sg:address":"Stockenerstrasse 23 9220 Bischofszell. Postfach",
    "sg:city":"Bischofszell",
    "sg:orig_category":"RESTAURANTS: TEA-ROOMS",
    "sg:postcode":"9220",
    "sg:province":"Thurgau",
    "wof:name":"Landhaus Bischofszell Gmbh",
    "wof:placetype":"venue"
},
  "geometry": {"coordinates":[9.2525138855,47.4975509644],"type":"Point"}
}