{
  "type": "Feature",
  "properties": {
    "iso:country":"CH",
    "sg:address":"Beau-soleil Chemin De 22",
    "sg:city":"Gen\u00e8ve",
    "sg:orig_category":"Non-Classified Establishments",
    "sg:postcode":"1206",
    "sg:province":"Gen\u00e8ve",
    "wof:name":"Arsystem Rabaeus & Cie",
    "wof:placetype":"venue"
},
  "geometry": {"coordinates":[6.1614952087,46.1889076233],"type":"Point"}
}