{
  "type": "Feature",
  "properties": {
    "iso:country":"CH",
    "sg:address":"Hersbergerweg 5",
    "sg:city":"Basel",
    "sg:orig_category":"G\u00fcterbef\u00f6rderung im Strassenverkehr",
    "sg:phone":"+41 61 601 11 82",
    "sg:postcode":"4058",
    "sg:province":"Basel-Stadt",
    "wof:name":"K\u00fcnzle Transporte",
    "wof:placetype":"venue"
},
  "geometry": {"coordinates":[7.6197228432,47.5631027222],"type":"Point"}
}