{
  "type": "Feature",
  "properties": {
    "iso:country":"CH",
    "sg:address":"Parc Scientifique Epfl",
    "sg:city":"Lausanne",
    "sg:orig_category":"Herstellung von Mess U Kontrollinstrumenten U vorrichtungen",
    "sg:postcode":"1015",
    "sg:province":"Vaud",
    "wof:name":"Sepp Oberdanner",
    "wof:placetype":"venue"
},
  "geometry": {"coordinates":[9.5074882507,47.0112953186],"type":"Point"}
}