{
  "type": "Feature",
  "properties": {
    "iso:country":"CH",
    "sg:address":"Winterthurerstrasse 22",
    "sg:city":"Z\u00fcrich",
    "sg:orig_category":"Sonstiger Fachdetailhandel mit Nahrungsmitteln, Getr\u00e4nken U Tabak in Verkaufsr\u00e4umen",
    "sg:postcode":"8006",
    "sg:province":"Z\u00fcrich",
    "wof:name":"Frei Delikatessen",
    "wof:placetype":"venue"
},
  "geometry": {"coordinates":[8.5474758148,47.3873176575],"type":"Point"}
}