{
  "type": "Feature",
  "properties": {
    "iso:country":"CH",
    "sg:address":"St. Gallerstrasse 30",
    "sg:city":"Tuggen",
    "sg:orig_category":"RESTAURANTS: TEA-ROOMS",
    "sg:phone":"+41 55 445 21 89",
    "sg:postcode":"8856",
    "sg:province":"Schwyz",
    "wof:name":"Gastroma Gmbh",
    "wof:placetype":"venue"
},
  "geometry": {"coordinates":[8.9463453293,47.2034072876],"type":"Point"}
}