{
  "type": "Feature",
  "properties": {
    "iso:country":"CH",
    "sg:address":"5064",
    "sg:city":"Wittnau",
    "sg:orig_category":"Abwasserreinigung",
    "sg:phone":"+41 62 871 32 51",
    "sg:postcode":"5064",
    "sg:province":"Aargau",
    "wof:name":"Kl\u00e4ranlage",
    "wof:placetype":"venue"
},
  "geometry": {"coordinates":[7.98453,47.483082],"type":"Point"}
}