{
  "type": "Feature",
  "properties": {
    "iso:country":"CH",
    "sg:address":"Grauholzstrasse 11",
    "sg:city":"Ittigen",
    "sg:classifiers":[
        {
            "category":"Social Services",
            "subcategory":"Retirement Home",
            "type":"Services"
        }
    ],
    "sg:phone":"+41 31 921 69 22",
    "sg:postcode":"3063",
    "sg:province":"Bern",
    "sg:tags":[
        "pflegeheime",
        "u",
        "alters"
    ],
    "wof:name":"Altersheim Aespliz",
    "wof:placetype":"venue"
},
  "geometry": {"coordinates":[7.476825,46.976978],"type":"Point"}
}