{
  "type": "Feature",
  "properties": {
    "iso:country":"CH",
    "sg:address":"Aareweg 11 C",
    "sg:city":"Uttigen",
    "sg:orig_category":"Softwareentwicklung U beratung",
    "sg:phone":"+41 33 345 55 24",
    "sg:postcode":"3628",
    "sg:province":"Bern",
    "wof:name":"Itprojects Gmbh",
    "wof:placetype":"venue"
},
  "geometry": {"coordinates":[7.580373764,46.795627594],"type":"Point"}
}