{
  "type": "Feature",
  "properties": {
    "iso:country":"CH",
    "sg:address":"Badenerstrasse 808",
    "sg:city":"Z\u00fcrich",
    "sg:orig_category":"Datenverarbeitungsdienste Softwareentwicklung U beratung",
    "sg:phone":"+41 14305450",
    "sg:postcode":"8048",
    "sg:province":"Z\u00fcrich",
    "wof:name":"Innovate It Ag",
    "wof:placetype":"venue"
},
  "geometry": {"coordinates":[8.474895,47.393093],"type":"Point"}
}