{
  "type": "Feature",
  "properties": {
    "iso:country":"CH",
    "sg:address":"Waldeggstrasse 84",
    "sg:city":"Interlaken",
    "sg:orig_category":"Herstellung von Konstruktionsteilen, Fertigbauteilen U Ausbauelementen aus Holz",
    "sg:postcode":"3800",
    "sg:province":"Bern",
    "wof:name":"Fels",
    "wof:placetype":"venue"
},
  "geometry": {"coordinates":[7.8522129059,46.6779823303],"type":"Point"}
}