{
  "type": "Feature",
  "properties": {
    "iso:country":"CH",
    "sg:address":"Tr\u00fcbsee",
    "sg:city":"Engelberg",
    "sg:orig_category":"HOTELS: MIT RESTAURANT Kongress- and Tagungshotels mit Restaurant",
    "sg:phone":"+41 41 637 13 71",
    "sg:postcode":"6390",
    "sg:province":"Obwalden",
    "wof:name":"Berghotel Tr\u00fcbseehof",
    "wof:placetype":"venue"
},
  "geometry": {"coordinates":[8.4043922424,46.8209877014],"type":"Point"}
}