{
  "type": "Feature",
  "properties": {
    "iso:country":"CH",
    "sg:address":"Hofstrasse 5 8872 Weesen. Postfach",
    "sg:city":"Weesen",
    "sg:orig_category":"Softwareentwicklung U beratung",
    "sg:postcode":"8872",
    "sg:province":"St. Gallen",
    "wof:name":"Osd.ch Gmbh Software Agentur Usw.",
    "wof:placetype":"venue"
},
  "geometry": {"coordinates":[9.1031236649,47.135093689],"type":"Point"}
}