{
  "type": "Feature",
  "properties": {
    "iso:country":"CH",
    "sg:address":"6803",
    "sg:city":"Camignolo",
    "sg:classifiers":[
        {
            "category":"Bars & Pubs",
            "type":"Food & Drink"
        }
    ],
    "sg:phone":"+41 91 946 44 97",
    "sg:postcode":"6803",
    "sg:province":"Ticino",
    "sg:tags":[
        "restaurant"
    ],
    "wof:name":"Osteria Tony Bar",
    "wof:placetype":"venue"
},
  "geometry": {"coordinates":[8.95045,46.10437],"type":"Point"}
}