{
  "type": "Feature",
  "properties": {
    "iso:country":"CH",
    "sg:address":"Zentrumstrasse 2",
    "sg:city":"Wikon",
    "sg:orig_category":"Herstellung von Glas U Glaswaren Verarbeitung U Veredlung von Flachglas",
    "sg:phone":"+41 62 752 12 88",
    "sg:postcode":"4806",
    "sg:province":"Luzern",
    "wof:name":"Pilkington (schweiz) Ag Glas Herstellung Und Veredlung",
    "wof:placetype":"venue"
},
  "geometry": {"coordinates":[7.9649510384,47.2626419067],"type":"Point"}
}