{
  "type": "Feature",
  "properties": {
    "iso:country":"CH",
    "sg:address":"Arneggerstrasse 28",
    "sg:city":"Waldkirch",
    "sg:orig_category":"RESTAURANTS: TEA-ROOMS",
    "sg:phone":"+41 71 433 16 66",
    "sg:postcode":"9205",
    "sg:province":"St. Gallen",
    "wof:name":"Restaurant Friedegg Wenzinger A.",
    "wof:placetype":"venue"
},
  "geometry": {"coordinates":[9.2806997299,47.4664268494],"type":"Point"}
}