{
  "type": "Feature",
  "properties": {
    "iso:country":"CH",
    "sg:address":"Oberer Flurweg 12 3072 Ostermundigen. Postfach",
    "sg:city":"Ostermundigen",
    "sg:classifiers":[
        {
            "category":"Travel",
            "subcategory":"Hotels & Motels",
            "type":"Entertainment"
        }
    ],
    "sg:phone":"+41 31 932 10 15",
    "sg:postcode":"3072",
    "sg:province":"Bern",
    "sg:tags":[
        "hotels",
        "mit",
        "restaurant"
    ],
    "wof:name":"Fhh Frauenseminar Hofweber Heidi Pers\u00f6nlichkeitsorientierte Seminare F\u00fcr Frauen",
    "wof:placetype":"venue"
},
  "geometry": {"coordinates":[7.4923992157,46.9536476135],"type":"Point"}
}