{
  "type": "Feature",
  "properties": {
    "iso:country":"CH",
    "sg:address":"Marais-rouges",
    "sg:city":"Ponts-de-martel",
    "sg:orig_category":"Grosshandel mit lebenden Tieren",
    "sg:phone":"+41 32 937 18 31",
    "sg:postcode":"2316",
    "sg:province":"Neuch\u00e2tel",
    "wof:name":"Nordwestag Sa Commerce De Chevaux",
    "wof:placetype":"venue"
},
  "geometry": {"coordinates":[6.7363801003,46.9974136353],"type":"Point"}
}