{
  "type": "Feature",
  "properties": {
    "iso:country":"CH",
    "sg:address":"Eystrasse 52",
    "sg:city":"Sumiswald",
    "sg:orig_category":"Vereine Vogel-& Naturschutz",
    "sg:phone":"+41 34 431 25 28",
    "sg:postcode":"3454",
    "sg:province":"Bern",
    "wof:name":"Ornith.verein Sumiswald & Umg.",
    "wof:placetype":"venue"
},
  "geometry": {"coordinates":[7.7541742325,47.0271263123],"type":"Point"}
}