{
  "type": "Feature",
  "properties": {
    "iso:country":"CH",
    "sg:address":"Chemin Du Montillier",
    "sg:city":"Bottens",
    "sg:orig_category":"Allgemeiner Hoch U Tiefbau",
    "sg:postcode":"1041",
    "sg:province":"Vaud",
    "wof:name":"Herv\u00e9 Anken",
    "wof:placetype":"venue"
},
  "geometry": {"coordinates":[6.65732,46.619091],"type":"Point"}
}