{
  "type": "Feature",
  "properties": {
    "iso:country":"CH",
    "sg:address":"8895",
    "sg:city":"Portels",
    "sg:orig_category":"Bau U Wohngenossenschaften",
    "sg:postcode":"8895",
    "sg:province":"St. Gallen",
    "wof:name":"Gen.f\u00fcr Landwirtschaftl.bauen Flums-kleinberg",
    "wof:placetype":"venue"
},
  "geometry": {"coordinates":[9.33448,47.082722],"type":"Point"}
}