{
  "type": "Feature",
  "properties": {
    "iso:country":"CH",
    "sg:address":"Asilo Via 6930 Bedano. Postfach",
    "sg:city":"Bedano",
    "sg:orig_category":"Sonstige mit Sport verbundene T\u00e4tigkeiten",
    "sg:postcode":"6930",
    "sg:province":"Ticino",
    "wof:name":"Castelli Lavori Lacustri Sagl",
    "wof:placetype":"venue"
},
  "geometry": {"coordinates":[8.9197845459,46.0522499084],"type":"Point"}
}