{
  "type": "Feature",
  "properties": {
    "iso:country":"CH",
    "sg:address":"Obere Zollgasse 59a",
    "sg:city":"Ostermundigen",
    "sg:orig_category":"Sonstiger Grosshandel",
    "sg:postcode":"3072",
    "sg:province":"Bern",
    "wof:name":"Bircher Hugo",
    "wof:placetype":"venue"
},
  "geometry": {"coordinates":[7.4855360985,46.9518737793],"type":"Point"}
}