{
  "type": "Feature",
  "properties": {
    "iso:country":"CH",
    "sg:address":"Schweizergasse 1",
    "sg:city":"Oberentfelden",
    "sg:orig_category":"Politische Parteien SP",
    "sg:postcode":"5036",
    "sg:province":"Aargau",
    "wof:name":"Sp Ortspartei Oberentfelden",
    "wof:placetype":"venue"
},
  "geometry": {"coordinates":[8.039888382,47.3639373779],"type":"Point"}
}