{
  "type": "Feature",
  "properties": {
    "iso:country":"CH",
    "sg:address":"Pfaffengasse 26",
    "sg:city":"Igis",
    "sg:orig_category":"Finanzierungsinstitutionen Handelsvermittlung U Grosshandel",
    "sg:phone":"+41 19951950",
    "sg:postcode":"7206",
    "sg:province":"Graubunden",
    "wof:name":"Codingraph Ag",
    "wof:placetype":"venue"
},
  "geometry": {"coordinates":[8.7675390244,47.3718681335],"type":"Point"}
}