{
  "type": "Feature",
  "properties": {
    "iso:country":"CH",
    "sg:address":"5728",
    "sg:city":"Gontenschwil",
    "sg:orig_category":"Herstellung von Metallerzeugnissen ohne Maschinenbau Herstellung von Metallkonstruktionen",
    "sg:phone":"+41 34 445 11 33",
    "sg:postcode":"5728",
    "sg:province":"Aargau",
    "wof:name":"Dial-norm Ag",
    "wof:placetype":"venue"
},
  "geometry": {"coordinates":[7.5711040497,47.0926322937],"type":"Point"}
}