{
  "type": "Feature",
  "properties": {
    "addr:full":"Lagerplatz 13 Winterthur Z\u00fcrich 8400",
    "addr:housenumber":"13",
    "addr:postcode":"8400",
    "addr:street":"Lagerplatz",
    "iso:country":"CH",
    "sg:address":"Lagerplatz 13",
    "sg:city":"Winterthur",
    "sg:orig_category":"Architektur U Ingenieurb\u00fcros",
    "sg:postcode":"8400",
    "sg:province":"Z\u00fcrich",
    "wof:name":"Beat Schneider Architektur Gmbh",
    "wof:placetype":"venue"
},
  "geometry": {"coordinates":[9.138185,47.566669],"type":"Point"}
}