{
  "type": "Feature",
  "properties": {
    "iso:country":"CH",
    "sg:address":"Rombachstrasse 4 5024 K\u00fcttigen. Postfach",
    "sg:city":"K\u00fcttigen",
    "sg:orig_category":"Sonstiger Grosshandel",
    "sg:phone":"+41 62 827 31 31",
    "sg:postcode":"5024",
    "sg:province":"Aargau",
    "wof:name":"Bockstette Ueli Freelancer Konsum- U. Investitionsg\u00fcter; Verkauf",
    "wof:placetype":"venue"
},
  "geometry": {"coordinates":[8.0437173843,47.4002952576],"type":"Point"}
}