{
  "type": "Feature",
  "properties": {
    "iso:country":"CH",
    "sg:address":"Marktstrasse 3",
    "sg:city":"Niederuzwil",
    "sg:orig_category":"Architekturb\u00fcros",
    "sg:phone":"+41 71 944 17 32",
    "sg:postcode":"9244",
    "sg:province":"St. Gallen",
    "wof:name":"Ds Architektur Ag",
    "wof:placetype":"venue"
},
  "geometry": {"coordinates":[9.142594,47.445957],"type":"Point"}
}