{
  "type": "Feature",
  "properties": {
    "iso:country":"CH",
    "sg:address":"Rychenbergstrasse 155",
    "sg:city":"Winterthur",
    "sg:orig_category":"Unternehmensberatung",
    "sg:phone":"+41 31 951 88 44",
    "sg:postcode":"8400",
    "sg:province":"Z\u00fcrich",
    "wof:name":"Nevimex Ag",
    "wof:placetype":"venue"
},
  "geometry": {"coordinates":[7.4767398834,46.9269523621],"type":"Point"}
}