{
  "type": "Feature",
  "properties": {
    "iso:country":"CH",
    "sg:address":"Haldenstrasse 1",
    "sg:city":"Mammern",
    "sg:orig_category":"Detailhandel mit B\u00fcchern, Zeitungen, Schreib U Papeteriewaren",
    "sg:phone":"+41 71 672 15 72",
    "sg:postcode":"8265",
    "sg:province":"Thurgau",
    "wof:name":"Sauter Ulrich",
    "wof:placetype":"venue"
},
  "geometry": {"coordinates":[8.91733,47.64558],"type":"Point"}
}