{
  "type": "Feature",
  "properties": {
    "iso:country":"CH",
    "sg:address":"Avenue De Gennecy 26",
    "sg:city":"Avully",
    "sg:orig_category":"Geb\u00e4ude, Wohnungsreinigung",
    "sg:phone":"+41 71 278 76 63",
    "sg:postcode":"1237",
    "sg:province":"Gen\u00e8ve",
    "wof:name":"Virgilio Di Felice Bau-reinigung",
    "wof:placetype":"venue"
},
  "geometry": {"coordinates":[9.3469219208,47.4172821045],"type":"Point"}
}