{
  "type": "Feature",
  "properties": {
    "iso:country":"CH",
    "sg:address":"Via Scer",
    "sg:city":"Rancate",
    "sg:orig_category":"Herstellung von Schreinerwaren ohne ausgepr\u00e4gten Schwerpunkt",
    "sg:phone":"+41 91 646 57 68",
    "sg:postcode":"6862",
    "sg:province":"Ticino",
    "wof:name":"Xilema Di G. Croci & M. Pellegrini",
    "wof:placetype":"venue"
},
  "geometry": {"coordinates":[8.9708471298,45.8720321655],"type":"Point"}
}