{
  "type": "Feature",
  "properties": {
    "iso:country":"CH",
    "sg:address":"Rue Marc Morand 11",
    "sg:city":"Martigny",
    "sg:orig_category":"Dienstleistungen von Beteiligungsgesellschaften",
    "sg:phone":"+41 27 722 36 03",
    "sg:postcode":"1920",
    "sg:province":"Valais",
    "wof:name":"Sefico S\u00e0rl",
    "wof:placetype":"venue"
},
  "geometry": {"coordinates":[7.0722870827,46.1030235291],"type":"Point"}
}