{
  "type": "Feature",
  "properties": {
    "iso:country":"CH",
    "sg:address":"Zentralstrasse 16 6030 Ebikon. Postfach",
    "sg:city":"Ebikon",
    "sg:classifiers":[
        {
            "category":"Professional",
            "subcategory":"Employment Agencies",
            "type":"Services"
        }
    ],
    "sg:phone":"+41 41 440 47 47",
    "sg:postcode":"6031",
    "sg:province":"Luzern",
    "sg:tags":[
        "personal",
        "u",
        "stellenvermittlung"
    ],
    "wof:name":"Zentra Ag Personalberatung Und Tempor\u00e4r",
    "wof:placetype":"venue"
},
  "geometry": {"coordinates":[8.3407239914,47.0811538696],"type":"Point"}
}