{
  "type": "Feature",
  "properties": {
    "iso:country":"CH",
    "sg:address":"Italie Rue D' 1204 Gen\u00e8ve. Postfach",
    "sg:city":"Gen\u00e8ve",
    "sg:orig_category":"Softwareentwicklung U beratung",
    "sg:postcode":"1201",
    "sg:province":"Gen\u00e8ve",
    "wof:name":"Business Information Consulting S\u00e0rl Effectuer Des Activit\u00e9s En Relation Avec L'informatique, Notamm. L'assistance Etc",
    "wof:placetype":"venue"
},
  "geometry": {"coordinates":[6.1515002251,46.2049484253],"type":"Point"}
}