{
  "type": "Feature",
  "properties": {
    "iso:country":"CH",
    "sg:address":"Closalet Chemin De 4",
    "sg:city":"Crissier",
    "sg:orig_category":"Maschinen-Fabrikation",
    "sg:postcode":"1023",
    "sg:province":"Vaud",
    "wof:name":"Smcr Krajewski Ing\u00e9nierie D'automation",
    "wof:placetype":"venue"
},
  "geometry": {"coordinates":[6.5774769783,46.5531997681],"type":"Point"}
}