{
  "type": "Feature",
  "properties": {
    "iso:country":"CH",
    "sg:address":"Sommeristrasse 38",
    "sg:city":"Sommeri",
    "sg:orig_category":"Herstellung von Betonerzeugnissen f\u00fcr den Bau Herstellung von Erzeugnissen aus Beton, Gips U Zement",
    "sg:phone":"+41 71 411 23 06",
    "sg:postcode":"8580",
    "sg:province":"Thurgau",
    "wof:name":"Scalco D.",
    "wof:placetype":"venue"
},
  "geometry": {"coordinates":[9.2995681763,47.54504776],"type":"Point"}
}