{
  "type": "Feature",
  "properties": {
    "iso:country":"CH",
    "sg:address":"Dorfstrasse 22",
    "sg:city":"Trubschachen",
    "sg:orig_category":"Religi\u00f6se Vereinigungen divers",
    "sg:postcode":"3555",
    "sg:province":"Bern",
    "wof:name":"Cvjm",
    "wof:placetype":"venue"
},
  "geometry": {"coordinates":[7.8436441422,46.9231033325],"type":"Point"}
}