{
  "type": "Feature",
  "properties": {
    "iso:country":"CH",
    "sg:address":"Hubelweg 191",
    "sg:city":"Kestenholz",
    "sg:orig_category":"Bauschreinerei Herstellung von M\u00f6beln verschiedener Art",
    "sg:phone":"+41 62 393 18 10",
    "sg:postcode":"4703",
    "sg:province":"Solothurn",
    "wof:name":"Othmar Ris Bau-& M\u00f6belschreinerei",
    "wof:placetype":"venue"
},
  "geometry": {"coordinates":[7.75672,47.28014],"type":"Point"}
}