{
  "type": "Feature",
  "properties": {
    "iso:country":"CH",
    "sg:address":"Alemannenstrasse 13 9320 Arbon. Postfach 163",
    "sg:city":"Arbon",
    "sg:orig_category":"Druck ohne Zeitungsdruck Offsetdruck",
    "sg:phone":"+41 71 446 42 12",
    "sg:postcode":"9320",
    "sg:province":"Thurgau",
    "wof:name":"Schoop Ernst Ag Arbon",
    "wof:placetype":"venue"
},
  "geometry": {"coordinates":[9.4290771484,47.512966156],"type":"Point"}
}