{
  "type": "Feature",
  "properties": {
    "iso:country":"CH",
    "sg:address":"Amselweg 15",
    "sg:city":"Bennau",
    "sg:orig_category":"Elektro- and elektronische Maschinen Grosshandel",
    "sg:phone":"+41 55 412 85 00",
    "sg:postcode":"8836",
    "sg:province":"Schwyz",
    "wof:name":"Tele Com Net Ag",
    "wof:placetype":"venue"
},
  "geometry": {"coordinates":[8.7297849655,47.1484451294],"type":"Point"}
}