{
  "type": "Feature",
  "properties": {
    "iso:country":"CH",
    "sg:address":"Kastelstrasse 38",
    "sg:city":"Basel",
    "sg:orig_category":"Mechanische Werkst\u00e4tten",
    "sg:phone":"+41 61 281 04 88",
    "sg:postcode":"4054",
    "sg:province":"Basel-Stadt",
    "wof:name":"Tusag Graf. Techn. Unterhalt U. Service, Elektrisch-mechanische Werkst\u00e4tte.",
    "wof:placetype":"venue"
},
  "geometry": {"coordinates":[7.5729789734,47.5463638306],"type":"Point"}
}