{
  "type": "Feature",
  "properties": {
    "iso:country":"CH",
    "sg:address":"Hochschulstrasse 17",
    "sg:city":"Bern",
    "sg:orig_category":"Verwaltung der Rechtspflege, Gerichte",
    "sg:phone":"+41 31 634 71 11",
    "sg:postcode":"3012",
    "sg:province":"Bern",
    "wof:name":"Obergericht Des Kantons Bern",
    "wof:placetype":"venue"
},
  "geometry": {"coordinates":[7.4360218048,46.9494171143],"type":"Point"}
}