{
  "type": "Feature",
  "properties": {
    "iso:country":"CH",
    "sg:address":"Geibelstrasse 37",
    "sg:city":"Z\u00fcrich",
    "sg:orig_category":"Malerei",
    "sg:phone":"+41 12715347",
    "sg:postcode":"8037",
    "sg:province":"Z\u00fcrich",
    "wof:name":"Rolf Meyer Malergesch\u00e4ft",
    "wof:placetype":"venue"
},
  "geometry": {"coordinates":[8.5277023315,47.3952255249],"type":"Point"}
}