{
  "type": "Feature",
  "properties": {
    "iso:country":"CH",
    "sg:address":"Feldbergstrasse 41",
    "sg:city":"Basel",
    "sg:orig_category":"Herstellung von Metallerzeugnissen ohne Maschinenbau",
    "sg:phone":"+41 61 692 10 56",
    "sg:postcode":"4057",
    "sg:province":"Basel-Stadt",
    "wof:name":"Willy Ulmer Apparatebau",
    "wof:placetype":"venue"
},
  "geometry": {"coordinates":[7.5904269218,47.5663108826],"type":"Point"}
}