{
  "type": "Feature",
  "properties": {
    "iso:country":"CH",
    "sg:address":"Chemin I.-de-montolieu 177",
    "sg:city":"Lausanne",
    "sg:orig_category":"Non-Classified Establishments",
    "sg:postcode":"1000",
    "sg:province":"Vaud",
    "wof:name":"Mitrusic R., Paysagiste",
    "wof:placetype":"venue"
},
  "geometry": {"coordinates":[6.6947751045,46.5545883179],"type":"Point"}
}