{
  "type": "Feature",
  "properties": {
    "iso:country":"CH",
    "sg:address":"Oberbergstrasse 3",
    "sg:city":"Littau",
    "sg:orig_category":"Herstellung der Ausstattung von Uhren Herstellung von Uhren",
    "sg:phone":"+41 41 250 37 88",
    "sg:postcode":"6014",
    "sg:province":"Luzern",
    "wof:name":"Bunz Montres Sa",
    "wof:placetype":"venue"
},
  "geometry": {"coordinates":[8.264705658,47.0513153076],"type":"Point"}
}