{
  "type": "Feature",
  "properties": {
    "iso:country":"CH",
    "sg:address":"Couchant Chemin Du 1 1272 Genolier. Postfach",
    "sg:city":"Genolier",
    "sg:orig_category":"Architektur U Ingenieurb\u00fcros",
    "sg:phone":"+41 71 636 14 53",
    "sg:postcode":"1272",
    "sg:province":"Vaud",
    "wof:name":"Aebischer + Stiefel",
    "wof:placetype":"venue"
},
  "geometry": {"coordinates":[9.163672,47.580597],"type":"Point"}
}