{
  "type": "Feature",
  "properties": {
    "iso:country":"CH",
    "sg:address":"Gare Place De La 8",
    "sg:city":"Nyon",
    "sg:orig_category":"Erschliessung von Grundst\u00fccken",
    "sg:postcode":"1260",
    "sg:province":"Vaud",
    "wof:name":"Coopelia, Coop\u00e9rative Sociale Pour L'encouragement \u00e0 La Construction De Logements Individuels Et Associatifs",
    "wof:placetype":"venue"
},
  "geometry": {"coordinates":[6.2390799522,46.3823661804],"type":"Point"}
}