{
  "type": "Feature",
  "properties": {
    "iso:country":"CH",
    "sg:address":"Oberdorfstrasse 16",
    "sg:city":"W\u00e4denswil",
    "sg:orig_category":"Architekturb\u00fcros",
    "sg:phone":"+41 17804578",
    "sg:postcode":"8820",
    "sg:province":"Z\u00fcrich",
    "wof:name":"Hans Bossert Architekturb\u00fcro",
    "wof:placetype":"venue"
},
  "geometry": {"coordinates":[8.669514,47.228107],"type":"Point"}
}