{
  "type": "Feature",
  "properties": {
    "iso:country":"CH",
    "sg:address":"Nauengasse 24",
    "sg:city":"Rorbas",
    "sg:orig_category":"Unclassifiable Establishments",
    "sg:postcode":"8427",
    "sg:province":"Z\u00fcrich",
    "wof:name":"Color, Style + Beauty Consulting Schmidt",
    "wof:placetype":"venue"
},
  "geometry": {"coordinates":[8.5776290894,47.5338096619],"type":"Point"}
}