{
  "type": "Feature",
  "properties": {
    "addr:full":"Amsler-laffon-strasse 14 Schaffhausen Schaffhausen 8200",
    "addr:housenumber":"14",
    "addr:postcode":"8200",
    "addr:street":"Amsler-Laffon-Strasse",
    "iso:country":"CH",
    "sg:address":"Amsler-laffon-strasse 14",
    "sg:city":"Schaffhausen",
    "sg:orig_category":"Bauspenglerei Sanit\u00e4rinstallation U Spenglerei",
    "sg:phone":"+41 52 624 38 40",
    "sg:postcode":"8200",
    "sg:province":"Schaffhausen",
    "wof:name":"Ren\u00e9 Maag Spenglerei Ag",
    "wof:placetype":"venue"
},
  "geometry": {"coordinates":[8.643066,47.707756],"type":"Point"}
}