{
  "type": "Feature",
  "properties": {
    "addr:full":"Toggenburgerstrasse 4 9608 Ganterschwil. Postfach Ganterschwil St. Gallen 9608",
    "addr:housenumber":"4",
    "addr:postcode":"9608;9608",
    "addr:street":"Toggenburgerstrasse;Postfach",
    "iso:country":"CH",
    "sg:address":"Toggenburgerstrasse 4 9608 Ganterschwil. Postfach",
    "sg:city":"Ganterschwil",
    "sg:orig_category":"Bauschreinerei Herstellung von Konstruktionsteilen, Fertigbauteilen U Ausbauelementen aus Holz",
    "sg:phone":"+41 71 983 14 33",
    "sg:postcode":"9608",
    "sg:province":"St. Gallen",
    "wof:name":"R\u00fcegg Anton Ag, Ganterschwil",
    "wof:placetype":"venue"
},
  "geometry": {"coordinates":[9.088972,47.380886],"type":"Point"}
}