{
  "type": "Feature",
  "properties": {
    "iso:country":"CH",
    "sg:address":"Tschamerie 6",
    "sg:city":"Hasle-r\u00fcegsau",
    "sg:orig_category":"G\u00fcterbef\u00f6rderung im Strassenverkehr",
    "sg:phone":"+41 55 442 16 23",
    "sg:postcode":"3415",
    "sg:province":"Bern",
    "wof:name":"Benz Transporte Gmbh",
    "wof:placetype":"venue"
},
  "geometry": {"coordinates":[8.8575296402,47.1917457581],"type":"Point"}
}