{
  "type": "Feature",
  "properties": {
    "iso:country":"CH",
    "sg:address":"Via Cantonale",
    "sg:city":"Intragna",
    "sg:classifiers":[
        {
            "category":"Travel",
            "subcategory":"Hotels & Motels",
            "type":"Entertainment"
        }
    ],
    "sg:phone":"+41 91 796 18 61",
    "sg:postcode":"6655",
    "sg:province":"Ticino",
    "sg:tags":[
        "hotels",
        "mit",
        "restaurant"
    ],
    "wof:name":"Grotto Du Rii",
    "wof:placetype":"venue"
},
  "geometry": {"coordinates":[8.7009992599,46.1780548096],"type":"Point"}
}