{
  "type": "Feature",
  "properties": {
    "iso:country":"CH",
    "sg:address":"Ulmenstrasse 56",
    "sg:city":"Frauenfeld",
    "sg:orig_category":"Unternehmensberatung",
    "sg:phone":"+41 52 720 28 97",
    "sg:postcode":"8500",
    "sg:province":"Thurgau",
    "wof:name":"Alfred M\u00fcnch",
    "wof:placetype":"venue"
},
  "geometry": {"coordinates":[8.876947403,47.5516891479],"type":"Point"}
}