{
  "type": "Feature",
  "properties": {
    "iso:country":"CH",
    "sg:address":"Gerbergasse 16",
    "sg:city":"Basel",
    "sg:orig_category":"Kosmetikinstitute",
    "sg:phone":"+41 61 261 48 78",
    "sg:postcode":"4001",
    "sg:province":"Basel-Stadt",
    "wof:name":"Yolanda Schumacher Kosmetikinstitut Art Beaut\u00e9",
    "wof:placetype":"venue"
},
  "geometry": {"coordinates":[7.5879230499,47.5572853088],"type":"Point"}
}