{
  "type": "Feature",
  "properties": {
    "iso:country":"CH",
    "sg:address":"Gertrudstrasse 65",
    "sg:city":"Z\u00fcrich",
    "sg:classifiers":[
        {
            "category":"Travel",
            "subcategory":"Hotels & Motels",
            "type":"Entertainment"
        }
    ],
    "sg:phone":"+41 14612524",
    "sg:postcode":"8003",
    "sg:province":"Z\u00fcrich",
    "sg:tags":[
        "hotels",
        "mit",
        "restaurant"
    ],
    "wof:name":"Das Kinderhotel Kinderkids",
    "wof:placetype":"venue"
},
  "geometry": {"coordinates":[8.5135478973,47.3723602295],"type":"Point"}
}