{
  "type": "Feature",
  "properties": {
    "iso:country":"CH",
    "sg:address":"Huebstrasse 1 9302 Kronb\u00fchl. Postfach",
    "sg:city":"Winterthur",
    "sg:orig_category":"Finanzierungsinstitutionen",
    "sg:phone":"+41 19224080",
    "sg:postcode":"8404",
    "sg:province":"Z\u00fcrich",
    "wof:name":"Anv Anlage-& Neutrale Versicherungsberatung Gmbh",
    "wof:placetype":"venue"
},
  "geometry": {"coordinates":[8.6817512512,47.2697181702],"type":"Point"}
}