{
  "type": "Feature",
  "properties": {
    "iso:country":"CH",
    "sg:address":"Untereggerstrasse 53 9403 Goldach. Postfach 108",
    "sg:city":"Goldach",
    "sg:orig_category":"Herstellung von Ger\u00e4ten der Elektrizit\u00e4tserzeugung, -verteilung u.\u00e4. -Herstellung von sonstigen elek",
    "sg:phone":"+41 17373181",
    "sg:postcode":"9403",
    "sg:province":"St. Gallen",
    "wof:name":"Palomar Elektronik Ag",
    "wof:placetype":"venue"
},
  "geometry": {"coordinates":[8.4296512604,47.3659133911],"type":"Point"}
}