{
  "type": "Feature",
  "properties": {
    "iso:country":"CH",
    "sg:address":"R\u00fcmlangerstrasse 16",
    "sg:city":"Watt",
    "sg:orig_category":"Unclassifiable Establishments",
    "sg:postcode":"8105",
    "sg:province":"Z\u00fcrich",
    "wof:name":"Wbg D. Bundespersonals Reckenholz",
    "wof:placetype":"venue"
},
  "geometry": {"coordinates":[8.4820184708,47.4426231384],"type":"Point"}
}