{
  "type": "Feature",
  "properties": {
    "iso:country":"CH",
    "sg:address":"Riva Giocondo Albertolli 1 6900 Lugano. Postfach",
    "sg:city":"Lugano",
    "sg:orig_category":"Non-Classified Establishments",
    "sg:postcode":"6900",
    "sg:province":"Ticino",
    "wof:name":"Mantex Ag",
    "wof:placetype":"venue"
},
  "geometry": {"coordinates":[9.3798112869,47.4287872314],"type":"Point"}
}