{
  "type": "Feature",
  "properties": {
    "iso:country":"CH",
    "sg:address":"Via Cantonale 8",
    "sg:city":"Lugano",
    "sg:orig_category":"Vermietung U Verpachtung von eigenen Immobilien",
    "sg:postcode":"6900",
    "sg:province":"Ticino",
    "wof:name":"Gerri Sa",
    "wof:placetype":"venue"
},
  "geometry": {"coordinates":[8.9503984451,46.0078544617],"type":"Point"}
}