{
  "type": "Feature",
  "properties": {
    "iso:country":"CH",
    "sg:address":"L\u00e4rchenweg 8",
    "sg:city":"H\u00e4gendorf",
    "sg:orig_category":"Werbegrafikateliers",
    "sg:phone":"+41 62 216 24 29",
    "sg:postcode":"4614",
    "sg:province":"Solothurn",
    "wof:name":"Josef Rippstein Grafisches Atelier Asg",
    "wof:placetype":"venue"
},
  "geometry": {"coordinates":[7.8472480774,47.336555481],"type":"Point"}
}