{
  "type": "Feature",
  "properties": {
    "iso:country":"CH",
    "sg:address":"Morgartenstrasse 3",
    "sg:city":"Luzern",
    "sg:orig_category":"Advokaturb\u00fcros Notariate",
    "sg:phone":"+41 24 472 41 54",
    "sg:postcode":"6003",
    "sg:province":"Luzern",
    "wof:name":"Alphonse-marie Veuthey Etude D'avocat & Notaire",
    "wof:placetype":"venue"
},
  "geometry": {"coordinates":[6.945436,46.250767],"type":"Point"}
}