{
  "type": "Feature",
  "properties": {
    "addr:full":"General-dufour-strasse 48 Biel/bienne Bern 2502",
    "addr:housenumber":"48",
    "addr:postcode":"2502",
    "addr:street":"General-Dufour-Strasse",
    "iso:country":"CH",
    "sg:address":"General-dufour-strasse 48",
    "sg:city":"Biel/bienne",
    "sg:orig_category":"Detailhandel mit Damenbekleidung",
    "sg:phone":"+41 79 228 58 58",
    "sg:postcode":"2502",
    "sg:province":"Bern",
    "wof:name":"Brautboutique Caroline Caroline Baum\u00fcller",
    "wof:placetype":"venue"
},
  "geometry": {"coordinates":[7.251193,47.141392],"type":"Point"}
}