{
  "type": "Feature",
  "properties": {
    "iso:country":"CH",
    "sg:address":"Gheidweg 42",
    "sg:city":"Olten",
    "sg:orig_category":"Sanit\u00e4r, Heizungs U L\u00fcftungsinstallation Sanit\u00e4rinstallation",
    "sg:phone":"+41 62 212 94 40",
    "sg:postcode":"4600",
    "sg:province":"Solothurn",
    "wof:name":"Wenger Paul Ag",
    "wof:placetype":"venue"
},
  "geometry": {"coordinates":[7.8918590546,47.3478775024],"type":"Point"}
}