{
  "type": "Feature",
  "properties": {
    "iso:country":"CH",
    "sg:address":"Ueberlandstrasse 34",
    "sg:city":"Z\u00fcrich",
    "sg:orig_category":"Allgemeiner Hoch U Tiefbau",
    "sg:postcode":"8000",
    "sg:province":"Z\u00fcrich",
    "wof:name":"Fritsche Ren\u00e9, Autoreinigung Und Autohandel",
    "wof:placetype":"venue"
},
  "geometry": {"coordinates":[8.557712,47.405098],"type":"Point"}
}