{
  "type": "Feature",
  "properties": {
    "iso:country":"CH",
    "sg:address":"Ueberlandstrasse 291",
    "sg:city":"Z\u00fcrich",
    "sg:orig_category":"Geb\u00e4ude, Wohnungsreinigung Reinigungsgewerbe",
    "sg:phone":"+41 13222028",
    "sg:postcode":"8051",
    "sg:province":"Z\u00fcrich",
    "wof:name":"Rmh Gmbh",
    "wof:placetype":"venue"
},
  "geometry": {"coordinates":[8.5772562027,47.4096603394],"type":"Point"}
}