{
  "type": "Feature",
  "properties": {
    "iso:country":"CH",
    "sg:address":"Nassackerstrasse 10 8952 Schlieren. Postfach",
    "sg:city":"Schlieren",
    "sg:orig_category":"Detailhandel mit elektrischen Haushalts-,Radio U Fernsehger\u00e4ten sowie Musikinstrumenten",
    "sg:postcode":"8952",
    "sg:province":"Z\u00fcrich",
    "wof:name":"Homevideo - Dvd Aleonis Dvd-video Master; Herstellung",
    "wof:placetype":"venue"
},
  "geometry": {"coordinates":[8.441778183,47.3958816528],"type":"Point"}
}