{
  "type": "Feature",
  "properties": {
    "addr:full":"Dorfstrasse 93 8706 Meilen. Postfach Meilen Z\u00fcrich 8706",
    "addr:housenumber":"93",
    "addr:postcode":"8706 meilen. postfach;8706",
    "addr:street":"Dorfstrasse",
    "iso:country":"CH",
    "sg:address":"Dorfstrasse 93 8706 Meilen. Postfach",
    "sg:city":"Meilen",
    "sg:orig_category":"Detailhandel mit Brillen U anderen Sehhilfen Fachdetailhandel in Verkaufsr\u00e4umen",
    "sg:phone":"+41 21 648 46 46",
    "sg:postcode":"8706",
    "sg:province":"Z\u00fcrich",
    "wof:name":"Clin D'oeil Sa Optique",
    "wof:placetype":"venue"
},
  "geometry": {"coordinates":[6.620024,46.536201],"type":"Point"}
}