{
  "type": "Feature",
  "properties": {
    "iso:country":"CH",
    "sg:address":"Schulhausstrasse 43",
    "sg:city":"Wynau",
    "sg:orig_category":"Mechanik",
    "sg:phone":"+41 32 358 10 40",
    "sg:postcode":"4923",
    "sg:province":"Bern",
    "wof:name":"Ammt-applications M\u00e9caniques, Li\u00e8vre-pneus-services",
    "wof:placetype":"venue"
},
  "geometry": {"coordinates":[7.2123589516,47.1627883911],"type":"Point"}
}