{
  "type": "Feature",
  "properties": {
    "iso:country":"CH",
    "sg:address":"B\u00fchlstrasse 30 8103 Unterengstringen. Postfach 12",
    "sg:city":"Unterengstringen",
    "sg:orig_category":"Herstellung von k\u00e4lte U lufttechnischen Erzeugnissen f\u00fcr gewerbliche Zwecke Installation von Heizung",
    "sg:phone":"+41 79 286 95 85",
    "sg:postcode":"8103",
    "sg:province":"Z\u00fcrich",
    "wof:name":"Felutex Ag",
    "wof:placetype":"venue"
},
  "geometry": {"coordinates":[8.7675390244,47.3718681335],"type":"Point"}
}