{
  "type": "Feature",
  "properties": {
    "addr:full":"St-cergue Route De 303 Nyon Vaud 1260",
    "addr:housenumber":"303",
    "addr:postcode":"1260",
    "addr:street":"Route De",
    "iso:country":"CH",
    "sg:address":"St-cergue Route De 303",
    "sg:city":"Nyon",
    "sg:orig_category":"Betrieb von Sportanlagen",
    "sg:phone":"+41 22 994 35 75",
    "sg:postcode":"1260",
    "sg:province":"Vaud",
    "wof:name":"Bowling Switzerland Inc., Wilmington, Succursale De Nyon",
    "wof:placetype":"venue"
},
  "geometry": {"coordinates":[6.23908,46.382366],"type":"Point"}
}