{
  "type": "Feature",
  "properties": {
    "iso:country":"CH",
    "sg:address":"Marktgasse 9 2500 Biel/bienne. Postfach 3113",
    "sg:city":"Biel/bienne",
    "sg:orig_category":"Non-Classified Establishments",
    "sg:phone":"+41 32 328 18 18",
    "sg:postcode":"2500",
    "sg:province":"Bern",
    "wof:name":"Str\u00e4ssler + Storck",
    "wof:placetype":"venue"
},
  "geometry": {"coordinates":[7.2461361885,47.1400718689],"type":"Point"}
}