{
  "type": "Feature",
  "properties": {
    "iso:country":"CH",
    "sg:address":"Oltnerstrasse 11",
    "sg:city":"Oberg\u00f6sgen",
    "sg:orig_category":"Kauf U Verkauf von Immobilien auf eigene Rechnung Vermittlung von Immobilien",
    "sg:phone":"+41 62 723 95 63",
    "sg:postcode":"4653",
    "sg:province":"Solothurn",
    "wof:name":"Melcano Ag",
    "wof:placetype":"venue"
},
  "geometry": {"coordinates":[7.9593610764,47.3519935608],"type":"Point"}
}