{
  "type": "Feature",
  "properties": {
    "iso:country":"CH",
    "sg:address":"1937",
    "sg:city":"Orsi\u00e8res",
    "sg:orig_category":"RESTAURANTS: TEA-ROOMS",
    "sg:postcode":"1937",
    "sg:province":"Valais",
    "wof:name":"Chambrier Michel",
    "wof:placetype":"venue"
},
  "geometry": {"coordinates":[6.5879321098,46.5380516052],"type":"Point"}
}