{
  "type": "Feature",
  "properties": {
    "iso:country":"CH",
    "sg:address":"Wilerstrasse 66",
    "sg:city":"Wattwil",
    "sg:orig_category":"Non-Classified Establishments",
    "sg:postcode":"9630",
    "sg:province":"St. Gallen",
    "wof:name":"Bto Consulting, Jack Plump",
    "wof:placetype":"venue"
},
  "geometry": {"coordinates":[9.0838937759,47.3116836548],"type":"Point"}
}