{
  "type": "Feature",
  "properties": {
    "iso:country":"CH",
    "sg:address":"Chemin De La Milice 15",
    "sg:city":"Plan-les-ouates",
    "sg:classifiers":[
        {
            "category":"Manufacturing",
            "subcategory":"Metals",
            "type":"Manufacturing & Wholesale Goods"
        }
    ],
    "sg:phone":"+41 22 794 96 92",
    "sg:postcode":"1228",
    "sg:province":"Gen\u00e8ve",
    "sg:tags":[
        "alloy",
        "construction",
        "lightweight"
    ],
    "wof:name":"Atelier De Plan-les-ouates",
    "wof:placetype":"venue"
},
  "geometry": {"coordinates":[6.1258950233,46.1690292358],"type":"Point"}
}