{
  "type": "Feature",
  "properties": {
    "iso:country":"CH",
    "sg:address":"Gr\u00fctstrasse 23",
    "sg:city":"Jona",
    "sg:orig_category":"Fotografische Ateliers",
    "sg:phone":"+41 55 216 20 40",
    "sg:postcode":"8645",
    "sg:province":"St. Gallen",
    "wof:name":"Peter R. Bruggmann Pr'bmedia Fotoreportagen",
    "wof:placetype":"venue"
},
  "geometry": {"coordinates":[8.8424034119,47.2356147766],"type":"Point"}
}