{
  "type": "Feature",
  "properties": {
    "iso:country":"CH",
    "sg:address":"Schneckelerstrasse 1",
    "sg:city":"F\u00fcllinsdorf",
    "sg:orig_category":"Babyartikel Detailhandel",
    "sg:phone":"+41 61 902 11 11",
    "sg:postcode":"4414",
    "sg:province":"Basel-Landschaft",
    "wof:name":"Valery Baby Center",
    "wof:placetype":"venue"
},
  "geometry": {"coordinates":[7.721008,47.512497],"type":"Point"}
}