{
  "type": "Feature",
  "properties": {
    "iso:country":"CH",
    "sg:address":"Stapfenackerstrasse 47",
    "sg:city":"Bern",
    "sg:orig_category":"Interessenvertretungen",
    "sg:postcode":"3018",
    "sg:province":"Bern",
    "wof:name":"Baumeister Armin Und Katharina Kessler-stiftung",
    "wof:placetype":"venue"
},
  "geometry": {"coordinates":[7.3848237991,46.9430618286],"type":"Point"}
}