{
  "type": "Feature",
  "properties": {
    "iso:country":"CH",
    "sg:address":"R\u00f6schenzstrasse 8 4242 Laufen. Postfach",
    "sg:city":"Laufen",
    "sg:orig_category":"Verwaltung von Immobilien",
    "sg:phone":"+41 61 761 18 80",
    "sg:postcode":"4242",
    "sg:province":"Basel-Landschaft",
    "wof:name":"Rita Frieder Palamidessa",
    "wof:placetype":"venue"
},
  "geometry": {"coordinates":[7.4999051094,47.421131134],"type":"Point"}
}