{
  "type": "Feature",
  "properties": {
    "iso:country":"CH",
    "sg:address":"Rheinstrasse 12",
    "sg:city":"Liestal",
    "sg:orig_category":"Arztpraxen",
    "sg:phone":"+41 61 923 33 44",
    "sg:postcode":"4410",
    "sg:province":"Basel-Landschaft",
    "wof:name":"Dr.med. Heidi Klaus Spezial\u00e4rztin Fmh",
    "wof:placetype":"venue"
},
  "geometry": {"coordinates":[7.732004,47.486122],"type":"Point"}
}