{
  "type": "Feature",
  "properties": {
    "iso:country":"CH",
    "sg:address":"4247",
    "sg:city":"Grindel",
    "sg:orig_category":"Vereine Musik/Blasmusik",
    "sg:postcode":"4247",
    "sg:province":"Solothurn",
    "wof:name":"Musikgesellschaft",
    "wof:placetype":"venue"
},
  "geometry": {"coordinates":[7.5048699379,47.3801116943],"type":"Point"}
}