{
  "type": "Feature",
  "properties": {
    "iso:country":"CH",
    "sg:address":"Breitweg 30",
    "sg:city":"N\u00fcrensdorf",
    "sg:orig_category":"Architektur U Ingenieurb\u00fcros Softwareentwicklung U beratung",
    "sg:phone":"+41 62 874 43 09",
    "sg:postcode":"8309",
    "sg:province":"Z\u00fcrich",
    "wof:name":"Hb Consulting Heinz B\u00fcchi",
    "wof:placetype":"venue"
},
  "geometry": {"coordinates":[8.634741,47.464115],"type":"Point"}
}