{
  "type": "Feature",
  "properties": {
    "iso:country":"CH",
    "sg:address":"Les Biolles",
    "sg:city":"Corcelles-le-jorat",
    "sg:orig_category":"Handel mit Automobilen",
    "sg:phone":"+41 21 903 16 40",
    "sg:postcode":"1082",
    "sg:province":"Vaud",
    "wof:name":"Mischler, A.",
    "wof:placetype":"venue"
},
  "geometry": {"coordinates":[6.7320251465,46.6003990173],"type":"Point"}
}