{
  "type": "Feature",
  "properties": {
    "iso:country":"CH",
    "sg:address":"Via A.pini 26",
    "sg:city":"Biasca",
    "sg:orig_category":"Detailhandel mit Uhren U Schmuck Reparatur von Uhren U Schmuck",
    "sg:phone":"+41 91 862 38 77",
    "sg:postcode":"6710",
    "sg:province":"Ticino",
    "wof:name":"Agma Mario Agustoni Orologeria & Gioielleria",
    "wof:placetype":"venue"
},
  "geometry": {"coordinates":[8.969704628,46.3601112366],"type":"Point"}
}