{
  "type": "Feature",
  "properties": {
    "iso:country":"CH",
    "sg:address":"Brunnmattstrasse 10 6048 Horw. Postfach",
    "sg:city":"Horw",
    "sg:orig_category":"Reiseb\u00fcros U Reiseveranstalter",
    "sg:phone":"+41 22 732 32 27",
    "sg:postcode":"6048",
    "sg:province":"Luzern",
    "wof:name":"Vogue-voyages, La Bourse Aux Voyages Sa",
    "wof:placetype":"venue"
},
  "geometry": {"coordinates":[6.1433987617,46.2081375122],"type":"Point"}
}