{
  "type": "Feature",
  "properties": {
    "iso:country":"CH",
    "sg:address":"Oberh\u00f6flistr. 1",
    "sg:city":"Sch\u00fcbelbach",
    "sg:orig_category":"Herstellung von Metallkonstruktionen",
    "sg:phone":"+41 55 440 38 83",
    "sg:postcode":"8862",
    "sg:province":"Schwyz",
    "wof:name":"Kaiser & Zehnder Metallbau Ag",
    "wof:placetype":"venue"
},
  "geometry": {"coordinates":[8.9176301956,47.1759986877],"type":"Point"}
}