{
  "type": "Feature",
  "properties": {
    "iso:country":"CH",
    "sg:address":"Ankengasse 5",
    "sg:city":"Z\u00fcrich",
    "sg:classifiers":[
        {
            "category":"Bars & Pubs",
            "type":"Food & Drink"
        }
    ],
    "sg:postcode":"8001",
    "sg:province":"Z\u00fcrich",
    "wof:name":"Ak\u00e7abel S\u00e0rl",
    "wof:placetype":"venue"
},
  "geometry": {"coordinates":[6.823551,47.099262],"type":"Point"}
}