{
  "type": "Feature",
  "properties": {
    "iso:country":"CH",
    "sg:address":"Aurorastrasse 69 8032 Z\u00fcrich",
    "sg:city":"Zust",
    "sg:orig_category":"Herstellung von Bereifungen",
    "sg:postcode":"32",
    "wof:name":"Stooss J.m.",
    "wof:placetype":"venue"
},
  "geometry": {"coordinates":[6.9928541183,46.2956199646],"type":"Point"}
}