{
  "type": "Feature",
  "properties": {
    "iso:country":"CH",
    "sg:address":"Ch. Du Guinchet 50",
    "sg:city":"Collombey",
    "sg:orig_category":"Versandhandel",
    "sg:phone":"+41 24 472 86 83",
    "sg:postcode":"1868",
    "sg:province":"Valais",
    "wof:name":"Les Jardins De Provence Li\u00e8vre Jean Pierre Et Marianne",
    "wof:placetype":"venue"
},
  "geometry": {"coordinates":[6.9473781586,46.2740325928],"type":"Point"}
}