{
  "type": "Feature",
  "properties": {
    "iso:country":"CH",
    "sg:address":"Loretostrasse 1 6300 Zug. Postfach 925",
    "sg:city":"Zug",
    "sg:orig_category":"Unternehmensberatung Wirtschaftspr\u00fcfung, Steuerberatung U Treuhand",
    "sg:phone":"+41 41 711 05 19",
    "sg:postcode":"6301",
    "sg:province":"Zug",
    "wof:name":"Christoph Oesch Dr. Oec. Hsg Steuer Und Unternehmensberatung Ag",
    "wof:placetype":"venue"
},
  "geometry": {"coordinates":[8.5240898132,47.1716423035],"type":"Point"}
}