{
  "type": "Feature",
  "properties": {
    "iso:country":"CH",
    "sg:address":"Viale Portone 3",
    "sg:city":"Bellinzona",
    "sg:orig_category":"Zahnarztpraxen",
    "sg:phone":"+41 91 826 21 26",
    "sg:postcode":"6500",
    "sg:province":"Ticino",
    "wof:name":"Dott. Med. Dent. Marina Kojic Dentista",
    "wof:placetype":"venue"
},
  "geometry": {"coordinates":[9.0226011276,46.1938171387],"type":"Point"}
}