{
  "type": "Feature",
  "properties": {
    "iso:country":"CH",
    "sg:address":"Flurhof.",
    "sg:city":"Muolen",
    "sg:orig_category":"Kauf U Verkauf von Immobilien auf eigene Rechnung",
    "sg:postcode":"9313",
    "sg:province":"St. Gallen",
    "wof:name":"D\u00e4hler Liegenschaften.",
    "wof:placetype":"venue"
},
  "geometry": {"coordinates":[9.3268699646,47.5196647644],"type":"Point"}
}