{
  "type": "Feature",
  "properties": {
    "iso:country":"CH",
    "sg:address":"Reichsgasse 42",
    "sg:city":"Chur",
    "sg:orig_category":"Hom\u00f6opathie Naturheil\u00e4rzte and Heilpraktiker",
    "sg:postcode":"7000",
    "sg:province":"Graubunden",
    "wof:name":"Stefan Bauer Naturheilpraxis",
    "wof:placetype":"venue"
},
  "geometry": {"coordinates":[9.5333003998,46.8498725891],"type":"Point"}
}