{
  "type": "Feature",
  "properties": {
    "iso:country":"CH",
    "sg:address":"8634",
    "sg:city":"Hombrechtikon",
    "sg:orig_category":"Schwimmb\u00e4der",
    "sg:phone":"+41 55 244 11 18",
    "sg:postcode":"8634",
    "sg:province":"Z\u00fcrich",
    "wof:name":"Badi L\u00fctzelsee",
    "wof:placetype":"venue"
},
  "geometry": {"coordinates":[8.7669401169,47.2505340576],"type":"Point"}
}