{
  "type": "Feature",
  "properties": {
    "iso:country":"CH",
    "sg:address":"1964",
    "sg:city":"Conthey",
    "sg:orig_category":"RESTAURANTS: TEA-ROOMS",
    "sg:postcode":"1964",
    "sg:province":"Valais",
    "wof:name":"Papin Ren\u00e9e.",
    "wof:placetype":"venue"
},
  "geometry": {"coordinates":[6.8212571144,47.0997009277],"type":"Point"}
}