{
  "type": "Feature",
  "properties": {
    "iso:country":"CH",
    "sg:address":"Zypressenstrasse 58 8004 Z\u00fcrich. Postfach",
    "sg:city":"Z\u00fcrich",
    "sg:orig_category":"Softwareentwicklung U beratung",
    "sg:phone":"+41 12953090",
    "sg:postcode":"8040",
    "sg:province":"Z\u00fcrich",
    "wof:name":"Inax Ag",
    "wof:placetype":"venue"
},
  "geometry": {"coordinates":[8.513669014,47.3777427673],"type":"Point"}
}