{
  "type": "Feature",
  "properties": {
    "iso:country":"CH",
    "sg:address":"Hohenrainstrasse 36 6280 Hochdorf. Postfach 938",
    "sg:city":"Hochdorf",
    "sg:orig_category":"Herstellung von Metallerzeugnissen ohne Maschinenbau Maschinenbau",
    "sg:phone":"+41 41 910 50 80",
    "sg:postcode":"6281",
    "sg:province":"Luzern",
    "wof:name":"Ramatech Ag",
    "wof:placetype":"venue"
},
  "geometry": {"coordinates":[8.3029384613,47.1680755615],"type":"Point"}
}