{
  "type": "Feature",
  "properties": {
    "iso:country":"CH",
    "sg:address":"Place Grand-st-jean 2",
    "sg:city":"Lausanne",
    "sg:orig_category":"Detailhandel mit Waren verschiedener Art, Hauptrichtung Nahrungsmittel Herstellung von Teigwaren",
    "sg:phone":"+41 21 635 30 55",
    "sg:postcode":"1003",
    "sg:province":"Vaud",
    "wof:name":"Dario Traiteur",
    "wof:placetype":"venue"
},
  "geometry": {"coordinates":[6.5903968811,46.5282745361],"type":"Point"}
}