{
  "type": "Feature",
  "properties": {
    "iso:country":"CH",
    "sg:address":"Via Dei Casagrande 27",
    "sg:city":"Breganzona",
    "sg:orig_category":"Unclassifiable Establishments",
    "sg:postcode":"6932",
    "sg:province":"Ticino",
    "wof:name":"Mediaworld Sagl",
    "wof:placetype":"venue"
},
  "geometry": {"coordinates":[8.9281997681,46.0114021301],"type":"Point"}
}