{
  "type": "Feature",
  "properties": {
    "iso:country":"CH",
    "sg:address":"Kreuzgasse",
    "sg:city":"Latterbach",
    "sg:orig_category":"Autoelektro and -elektronik Werkst\u00e4tten Autogaragen",
    "sg:phone":"+41 33 681 81 21",
    "sg:postcode":"3758",
    "sg:province":"Bern",
    "wof:name":"Balmer Garage Ag Autoelektroservice",
    "wof:placetype":"venue"
},
  "geometry": {"coordinates":[7.57805,46.663994],"type":"Point"}
}