{
  "type": "Feature",
  "properties": {
    "iso:country":"CH",
    "sg:address":"Route De La Gl\u00e2ne 26 1700 Fribourg Case Postale 723",
    "sg:city":"Fribourg",
    "sg:orig_category":"Herstellung von Metallerzeugnissen ohne Maschinenbau Herstellung von sonstigen Maschinen f\u00fcr unspezi",
    "sg:phone":"+41 61 421 23 60",
    "sg:postcode":"1701",
    "sg:province":"Fribourg",
    "wof:name":"Primus Sa Mat\u00e9riel Contre L'incendie",
    "wof:placetype":"venue"
},
  "geometry": {"coordinates":[5.1808700562,45.8973388672],"type":"Point"}
}