{
  "type": "Feature",
  "properties": {
    "iso:country":"CH",
    "sg:address":"Sulzberg 28",
    "sg:city":"Rorschacherberg",
    "sg:orig_category":"RESTAURANTS: TEA-ROOMS",
    "sg:phone":"+41 71 855 11 71",
    "sg:postcode":"9404",
    "sg:province":"St. Gallen",
    "wof:name":"Hotel Sulzberg",
    "wof:placetype":"venue"
},
  "geometry": {"coordinates":[9.4817552567,47.4673805237],"type":"Point"}
}