{
  "type": "Feature",
  "properties": {
    "iso:country":"CH",
    "sg:address":"Sempacherstrasse 22 8000 Z\u00fcrich. Postfach 8032 Z\u00fcrich",
    "sg:city":"Zust",
    "sg:orig_category":"Werbung",
    "sg:postcode":"32",
    "wof:name":"Birrer Susann Communication Art",
    "wof:placetype":"venue"
},
  "geometry": {"coordinates":[8.5665788651,47.3626174927],"type":"Point"}
}