{
  "type": "Feature",
  "properties": {
    "iso:country":"CH",
    "sg:address":"In Der Weid 3 8122 Binz. Postfach",
    "sg:city":"Binz",
    "sg:orig_category":"Architektur U Ingenieurb\u00fcros",
    "sg:postcode":"8122",
    "sg:province":"Z\u00fcrich",
    "wof:name":"Ingenieurb\u00fcro Bader E.",
    "wof:placetype":"venue"
},
  "geometry": {"coordinates":[8.623427,47.360237],"type":"Point"}
}