{
  "type": "Feature",
  "properties": {
    "iso:country":"CH",
    "sg:address":"Habsburgstrasse 1a",
    "sg:city":"Windisch",
    "sg:orig_category":"Institutionen f\u00fcr Behinderte Wohnheime",
    "sg:phone":"+41 56 442 17 77",
    "sg:postcode":"5210",
    "sg:province":"Aargau",
    "wof:name":"Stiftung F\u00fcr Behinderte Region Brugg-windisch",
    "wof:placetype":"venue"
},
  "geometry": {"coordinates":[8.2100496292,47.4741592407],"type":"Point"}
}