{
  "type": "Feature",
  "properties": {
    "iso:country":"CH",
    "sg:address":"Heldswilerstrasse 15",
    "sg:city":"Kradolf",
    "sg:orig_category":"Handelsvermittlung U Grosshandel mit Automobilen Herstellung von Automobilen",
    "sg:phone":"+41 71 642 21 42",
    "sg:postcode":"9214",
    "sg:province":"Thurgau",
    "wof:name":"Preisig Willi Ag",
    "wof:placetype":"venue"
},
  "geometry": {"coordinates":[9.2019081116,47.5279922485],"type":"Point"}
}