{
  "type": "Feature",
  "properties": {
    "iso:country":"CH",
    "sg:address":"Egelmoosweg 7",
    "sg:city":"Biberist",
    "sg:orig_category":"Sanit\u00e4r, Heizungs U L\u00fcftungsinstallation",
    "sg:phone":"+41 27 306 35 01",
    "sg:postcode":"4562",
    "sg:province":"Solothurn",
    "wof:name":"Thomas Paul & Fils Sa",
    "wof:placetype":"venue"
},
  "geometry": {"coordinates":[7.2086448669,46.1864585876],"type":"Point"}
}