{
  "type": "Feature",
  "properties": {
    "iso:country":"CH",
    "sg:address":"5603",
    "sg:city":"Staufen",
    "sg:orig_category":"Vereine Vogel-& Naturschutz",
    "sg:postcode":"5603",
    "sg:province":"Aargau",
    "wof:name":"Vogelschutzverein",
    "wof:placetype":"venue"
},
  "geometry": {"coordinates":[8.1618900299,47.376209259],"type":"Point"}
}