{
  "type": "Feature",
  "properties": {
    "iso:country":"CH",
    "sg:address":"Sonneland 1",
    "sg:city":"Neuenkirch",
    "sg:orig_category":"Tierarztpraxis",
    "sg:phone":"+41 19352327",
    "sg:postcode":"6206",
    "sg:province":"Luzern",
    "wof:name":"Dr. Med. Vet. Ursula Kind Tier\u00e4rztin",
    "wof:placetype":"venue"
},
  "geometry": {"coordinates":[8.7327699661,47.2911911011],"type":"Point"}
}