{
  "type": "Feature",
  "properties": {
    "iso:country":"CH",
    "sg:address":"M\u00fcnsterberg 1",
    "sg:city":"Basel",
    "sg:orig_category":"Sonstige pers\u00f6nliche Dienstleistungen Unternehmensberatung",
    "sg:phone":"+41 41 670 24 29",
    "sg:postcode":"4051",
    "sg:province":"Basel-Stadt",
    "wof:name":"Habsburgblick Ag",
    "wof:placetype":"venue"
},
  "geometry": {"coordinates":[8.2710876465,46.9404907227],"type":"Point"}
}