{
  "type": "Feature",
  "properties": {
    "iso:country":"CH",
    "sg:address":"Chemin De Ball\u00e8gue 1",
    "sg:city":"Epalinges",
    "sg:orig_category":"Herstellung von Mess U Kontrollinstrumenten U vorrichtungen",
    "sg:phone":"+41 21 784 35 44",
    "sg:postcode":"1066",
    "sg:province":"Vaud",
    "wof:name":"Analysis, Narbel Andr\u00e9",
    "wof:placetype":"venue"
},
  "geometry": {"coordinates":[6.6700801849,46.555229187],"type":"Point"}
}