{
  "type": "Feature",
  "properties": {
    "iso:country":"CH",
    "sg:address":"Riedmattstrasse 7",
    "sg:city":"Sattel",
    "sg:orig_category":"Zimmerei, Ingenieurholzbau",
    "sg:phone":"+41 41 835 12 23",
    "sg:postcode":"6417",
    "sg:province":"Schwyz",
    "wof:name":"Karl Schuler Zimmerei",
    "wof:placetype":"venue"
},
  "geometry": {"coordinates":[8.6268196106,47.0831451416],"type":"Point"}
}