{
  "type": "Feature",
  "properties": {
    "iso:country":"CH",
    "sg:address":"8502 Frauenfeld. Postfach 2034",
    "sg:city":"Frauenfeld",
    "sg:orig_category":"Sportvereine Ballsport Fussball",
    "sg:phone":"+41 18307912",
    "sg:postcode":"8502",
    "sg:province":"Thurgau",
    "wof:name":"Fc Frauenfeld",
    "wof:placetype":"venue"
},
  "geometry": {"coordinates":[8.8958101273,47.5561904907],"type":"Point"}
}