{
  "type": "Feature",
  "properties": {
    "iso:country":"CH",
    "sg:address":"Schulstrasse 16 8542 Wiesendangen. Postfach",
    "sg:city":"Wiesendangen",
    "sg:orig_category":"Finanzierungsinstitutionen",
    "sg:phone":"+41 52 337 26 14",
    "sg:postcode":"8542",
    "sg:province":"Z\u00fcrich",
    "wof:name":"Jpm Consultant M\u00fcller Jonny P. Anlage Und Vorsorgeberatung Bes. Im Bereich Der Beruflichen Vorsorge",
    "wof:placetype":"venue"
},
  "geometry": {"coordinates":[8.7867145538,47.5223808289],"type":"Point"}
}