{
  "type": "Feature",
  "properties": {
    "iso:country":"CH",
    "sg:address":"9402",
    "sg:city":"M\u00f6rschwil",
    "sg:orig_category":"Schulpflegen",
    "sg:phone":"+41 71 866 22 90",
    "sg:postcode":"9402",
    "sg:province":"St. Gallen",
    "wof:name":"Schulrat Der Gemeinde M\u00f6rschwil",
    "wof:placetype":"venue"
},
  "geometry": {"coordinates":[9.4222021103,47.468624115],"type":"Point"}
}