{
  "type": "Feature",
  "properties": {
    "iso:country":"CH",
    "sg:address":"Leehalderweg 45",
    "sg:city":"R\u00fcmlang",
    "sg:orig_category":"Sportvereine Sch\u00fctzen",
    "sg:phone":"+41 18171429",
    "sg:postcode":"8153",
    "sg:province":"Z\u00fcrich",
    "wof:name":"Schiessverein",
    "wof:placetype":"venue"
},
  "geometry": {"coordinates":[8.5300750732,47.4530143738],"type":"Point"}
}