{
  "type": "Feature",
  "properties": {
    "iso:country":"CH",
    "sg:address":"Eichiweg 27",
    "sg:city":"Z\u00e4ziwil",
    "sg:orig_category":"Herstellung von Haus, Bett U Tischw\u00e4sche Weberei",
    "sg:phone":"+41 31 711 04 08",
    "sg:postcode":"3532",
    "sg:province":"Bern",
    "wof:name":"Emmentaler Handweberei Z\u00e4ziwil A.augustin",
    "wof:placetype":"venue"
},
  "geometry": {"coordinates":[7.6536130905,46.9019126892],"type":"Point"}
}