{
  "type": "Feature",
  "properties": {
    "iso:country":"CH",
    "sg:address":"M\u00fchlentalstrasse 289 8200 Schaffhausen. Postfach",
    "sg:city":"Schaffhausen",
    "sg:orig_category":"Vereine Diverse",
    "sg:phone":"+41 52 643 29 92",
    "sg:postcode":"8201",
    "sg:province":"Schaffhausen",
    "wof:name":"Cb-funk-club Isar",
    "wof:placetype":"venue"
},
  "geometry": {"coordinates":[8.6312599182,47.713142395],"type":"Point"}
}