{
  "type": "Feature",
  "properties": {
    "iso:country":"CH",
    "sg:address":"Gerbefeld",
    "sg:city":"Altishofen",
    "sg:orig_category":"Grosshandel mit Holz U Baustoffen",
    "sg:phone":"+41 62 756 23 79",
    "sg:postcode":"6246",
    "sg:province":"Luzern",
    "wof:name":"Fischer Hans Holzhandlung",
    "wof:placetype":"venue"
},
  "geometry": {"coordinates":[7.9673700333,47.2001686096],"type":"Point"}
}