{
  "type": "Feature",
  "properties": {
    "addr:full":"Sihlquai 253 Zurzach Z\u00fcrich 8031",
    "addr:housenumber":"253",
    "addr:postcode":"8031",
    "addr:street":"Sihlquai",
    "iso:country":"CH",
    "sg:address":"Sihlquai 253",
    "sg:city":"Zurzach",
    "sg:classifiers":[
        {
            "category":"Banks & Credit Unions",
            "subcategory":"Bank",
            "type":"Services"
        }
    ],
    "sg:phone":"+41 56 212 64 64",
    "sg:postcode":"8031",
    "sg:province":"Z\u00fcrich",
    "wof:name":"Tokai Bank, (schweiz) Ag",
    "wof:placetype":"venue"
},
  "geometry": {"coordinates":[8.529029,47.387882],"type":"Point"}
}