{
  "type": "Feature",
  "properties": {
    "iso:country":"CH",
    "sg:address":"Industriestrasse 14",
    "sg:city":"Aarwangen",
    "sg:orig_category":"Allgemeiner Hoch U Tiefbau",
    "sg:phone":"+41 62 916 30 77",
    "sg:postcode":"4912",
    "sg:province":"Bern",
    "wof:name":"Baumgartner Hoch + Tiefbau Ag",
    "wof:placetype":"venue"
},
  "geometry": {"coordinates":[7.774331,47.230129],"type":"Point"}
}