{
  "type": "Feature",
  "properties": {
    "iso:country":"CH",
    "sg:address":"Malzstrasse 2 8045 Z\u00fcrich. Postfach",
    "sg:city":"Z\u00fcrich",
    "sg:orig_category":"Grosshandel mit B\u00fcromaschinen Hardwareberatung",
    "sg:phone":"+41 14511810",
    "sg:postcode":"8036",
    "sg:province":"Z\u00fcrich",
    "wof:name":"C And E Gmbh Edv-ger\u00e4te, Software; Handel. Hard, Software; Wartung, Unterst\u00fctzung",
    "wof:placetype":"venue"
},
  "geometry": {"coordinates":[8.5212469101,47.3657684326],"type":"Point"}
}