{
  "type": "Feature",
  "properties": {
    "iso:country":"CH",
    "sg:address":"Chaletstrasse 1",
    "sg:city":"D\u00fcbendorf",
    "sg:orig_category":"Herstellung von Schl\u00f6ssern U Beschl\u00e4gen",
    "sg:phone":"+41 18201415",
    "sg:postcode":"8600",
    "sg:province":"Z\u00fcrich",
    "wof:name":"Schl\u00fcssel 24, Ch. Rosset",
    "wof:placetype":"venue"
},
  "geometry": {"coordinates":[8.6269388199,47.4044494629],"type":"Point"}
}