{
  "type": "Feature",
  "properties": {
    "iso:country":"CH",
    "sg:address":"Zielmatte 27",
    "sg:city":"Stansstad",
    "sg:orig_category":"Herstellung von Schmuck, Gold U Silberschmiedwaren Tapeziererei",
    "sg:phone":"+41 41 610 18 15",
    "sg:postcode":"6362",
    "sg:province":"Nidwalden",
    "wof:name":"Josef Cometto Maler-& Tapezierergesch\u00e4ft",
    "wof:placetype":"venue"
},
  "geometry": {"coordinates":[8.3410730362,46.9767570496],"type":"Point"}
}