{
  "type": "Feature",
  "properties": {
    "iso:country":"CH",
    "sg:address":"Wildbachstrasse 48",
    "sg:city":"Z\u00fcrich",
    "sg:orig_category":"Architektur U Ingenieurb\u00fcros Architekturb\u00fcros",
    "sg:phone":"+41 22 343 09 43",
    "sg:postcode":"8008",
    "sg:province":"Z\u00fcrich",
    "wof:name":"Daniel Mouchet",
    "wof:placetype":"venue"
},
  "geometry": {"coordinates":[6.137219,46.183788],"type":"Point"}
}