{
  "type": "Feature",
  "properties": {
    "iso:country":"CH",
    "sg:address":"Gallusstrasse 5",
    "sg:city":"Wattwil",
    "sg:orig_category":"Vermietung U Verpachtung von eigenen Immobilien",
    "sg:postcode":"9630",
    "sg:province":"St. Gallen",
    "wof:name":"Biwa Immobilien Ag",
    "wof:placetype":"venue"
},
  "geometry": {"coordinates":[9.0817251205,47.3069381714],"type":"Point"}
}