{
  "type": "Feature",
  "properties": {
    "iso:country":"CH",
    "sg:address":"Winterthurerstrasse 1",
    "sg:city":"Bassersdorf",
    "sg:orig_category":"Erbringung von Dienstleistungen f\u00fcr Unternehmen Werbeberatung",
    "sg:phone":"+41 43 266 04 04",
    "sg:postcode":"8303",
    "sg:province":"Z\u00fcrich",
    "wof:name":"Volltext Werbetexte - Ideen - Konzepte",
    "wof:placetype":"venue"
},
  "geometry": {"coordinates":[8.6288414001,47.443649292],"type":"Point"}
}