{
  "type": "Feature",
  "properties": {
    "iso:country":"CH",
    "sg:address":"Rue Centrale 26",
    "sg:city":"Montagne-moutier",
    "sg:orig_category":"Interessenvertretungen",
    "sg:phone":"+41 32 493 17 70",
    "sg:postcode":"2740",
    "sg:province":"Bern",
    "wof:name":"Fonds Paritaire Pour La Famille, Jura Bernois",
    "wof:placetype":"venue"
},
  "geometry": {"coordinates":[7.3759541512,47.2801856995],"type":"Point"}
}