{
  "type": "Feature",
  "properties": {
    "iso:country":"CH",
    "sg:address":"Avenue G\u00e9n\u00e9ral-guisan 11",
    "sg:city":"Sierre",
    "sg:orig_category":"Non-Classified Establishments",
    "sg:postcode":"3960",
    "sg:province":"Valais",
    "wof:name":"Gil Bonnet & Fils Sa",
    "wof:placetype":"venue"
},
  "geometry": {"coordinates":[7.5309009552,46.2923622131],"type":"Point"}
}