{
  "type": "Feature",
  "properties": {
    "iso:country":"CH",
    "sg:address":"St\u00e4dtlistrasse 9",
    "sg:city":"Dallenwil",
    "sg:orig_category":"Grosshandel mit B\u00fcromaschinen Grosshandel mit Datenverarbeitungsger\u00e4ten",
    "sg:phone":"+41 41 628 18 24",
    "sg:postcode":"6383",
    "sg:province":"Nidwalden",
    "wof:name":"Smb Schulmaterialbedarf Georges Balmer",
    "wof:placetype":"venue"
},
  "geometry": {"coordinates":[8.3906335831,46.9323158264],"type":"Point"}
}