{
  "type": "Feature",
  "properties": {
    "iso:country":"CH",
    "sg:address":"Im Tiefen Boden 30",
    "sg:city":"Basel",
    "sg:orig_category":"Datenverarbeitungsdienste",
    "sg:phone":"+41 61 363 33 11",
    "sg:postcode":"4059",
    "sg:province":"Basel-Stadt",
    "wof:name":"Partrade Ag Elektrotechnische Artikel",
    "wof:placetype":"venue"
},
  "geometry": {"coordinates":[7.590699,47.530781],"type":"Point"}
}