{
  "type": "Feature",
  "properties": {
    "iso:country":"CH",
    "sg:address":"Alter Z\u00fcrichweg 21.",
    "sg:city":"Schlieren",
    "sg:orig_category":"Detailhandel mit Parf\u00fcmerieartikeln U K\u00f6rperpflegemitteln",
    "sg:postcode":"8952",
    "sg:province":"Z\u00fcrich",
    "wof:name":"Vipa, Sina Piergianni",
    "wof:placetype":"venue"
},
  "geometry": {"coordinates":[8.4513721466,47.3948745728],"type":"Point"}
}