{
  "type": "Feature",
  "properties": {
    "addr:full":"Schulstrasse 30 Frick Aargau 5070",
    "addr:housenumber":"30",
    "addr:postcode":"5070",
    "addr:street":"Schulstrasse",
    "iso:country":"CH",
    "sg:address":"Schulstrasse 30",
    "sg:city":"Frick",
    "sg:orig_category":"Dachdeckerei",
    "sg:phone":"+41 19327872",
    "sg:postcode":"5070",
    "sg:province":"Aargau",
    "wof:name":"Hans Temperli Dachdeckergesch\u00e4ft",
    "wof:placetype":"venue"
},
  "geometry": {"coordinates":[8.791831,47.325527],"type":"Point"}
}