{
  "type": "Feature",
  "properties": {
    "iso:country":"CH",
    "sg:address":"Kronenstrasse 12 6418 Rothenthurm. Postfach 65",
    "sg:city":"Rothenthurm",
    "sg:orig_category":"Unclassifiable Establishments",
    "sg:phone":"+41 41 819 31 31",
    "sg:postcode":"6418",
    "sg:province":"Schwyz",
    "wof:name":"Schuler-beteiligungen Ag",
    "wof:placetype":"venue"
},
  "geometry": {"coordinates":[8.633329,47.02417],"type":"Point"}
}