{
  "type": "Feature",
  "properties": {
    "iso:country":"CH",
    "sg:address":"Rosswiesstrasse 29 8608 Bubikon. Postfach",
    "sg:city":"Bubikon",
    "sg:orig_category":"Softwareentwicklung U beratung",
    "sg:postcode":"8608",
    "sg:province":"Z\u00fcrich",
    "wof:name":"Aaeon Electronics Europe Inc",
    "wof:placetype":"venue"
},
  "geometry": {"coordinates":[8.8257980347,47.2701683044],"type":"Point"}
}