{
  "type": "Feature",
  "properties": {
    "iso:country":"CH",
    "sg:address":"Route De Moudon",
    "sg:city":"Ursy",
    "sg:orig_category":"Kosmetikinstitute",
    "sg:phone":"+41 61 751 48 89",
    "sg:postcode":"1670",
    "sg:province":"Fribourg",
    "wof:name":"Anita Gottardo Kosmetikinstitut Anita",
    "wof:placetype":"venue"
},
  "geometry": {"coordinates":[7.602519989,47.4764442444],"type":"Point"}
}