{
  "type": "Feature",
  "properties": {
    "iso:country":"CH",
    "sg:address":"Trubeg\u00fcetlistrasse 30",
    "sg:city":"Neuhausen",
    "sg:orig_category":"Organisationen des Gesundheitswesen",
    "sg:phone":"+41 52 672 23 44",
    "sg:postcode":"8212",
    "sg:province":"Schaffhausen",
    "wof:name":"Samariterverein Neuhausen",
    "wof:placetype":"venue"
},
  "geometry": {"coordinates":[8.6206550598,47.6945724487],"type":"Point"}
}