{
  "type": "Feature",
  "properties": {
    "iso:country":"CH",
    "sg:address":"Grund",
    "sg:city":"Diemtigen",
    "sg:orig_category":"Haltung von Rindern",
    "sg:postcode":"3754",
    "sg:province":"Bern",
    "wof:name":"Viehzuchtgenossenschaft Diemtigen Ii",
    "wof:placetype":"venue"
},
  "geometry": {"coordinates":[7.5691142082,46.6420173645],"type":"Point"}
}