{
  "type": "Feature",
  "properties": {
    "iso:country":"CH",
    "sg:address":"St\u00e4hlistrasse 3 8280 Kreuzlingen. Postfach",
    "sg:city":"Kreuzlingen",
    "sg:orig_category":"Allgemeiner Hoch U Tiefbau Allgemeiner Hoch U Tiefbau ohne ausgepr\u00e4gten Schwerpunkt",
    "sg:phone":"+41 71 672 15 14",
    "sg:postcode":"8280",
    "sg:province":"Thurgau",
    "wof:name":"Bau Fuchs Gmbh Kreuzlingen Hoch- U. Tiefbauten Usw",
    "wof:placetype":"venue"
},
  "geometry": {"coordinates":[9.167975,47.642712],"type":"Point"}
}