{
  "type": "Feature",
  "properties": {
    "iso:country":"CH",
    "sg:address":"Pobbia Via",
    "sg:city":"Sementina",
    "sg:orig_category":"Instandhaltung U Reparatur von Automobilen",
    "sg:phone":"+41 91 857 24 69",
    "sg:postcode":"6514",
    "sg:province":"Ticino",
    "wof:name":"Minore Sagl",
    "wof:placetype":"venue"
},
  "geometry": {"coordinates":[8.9997558594,46.1812362671],"type":"Point"}
}