{
  "type": "Feature",
  "properties": {
    "iso:country":"CH",
    "sg:address":"Sch\u00fcsselrain 34",
    "sg:city":"Hildisrieden",
    "sg:orig_category":"Schreib U \u00dcbersetzungsb\u00fcros",
    "sg:phone":"+41 41 460 10 68",
    "sg:postcode":"6024",
    "sg:province":"Luzern",
    "wof:name":"Office Pro Von D\u00e4niken Carmen Sekretariatsarbeiten Usw",
    "wof:placetype":"venue"
},
  "geometry": {"coordinates":[8.2236471176,47.1479301453],"type":"Point"}
}