{
  "type": "Feature",
  "properties": {
    "iso:country":"CH",
    "sg:address":"Fallenacker 3",
    "sg:city":"Othmarsingen",
    "sg:orig_category":"Sonstiger Fachdetailhandel mit Nahrungsmitteln, Getr\u00e4nken U Tabak in Verkaufsr\u00e4umen Verwaltung von I",
    "sg:phone":"+41 62 896 31 33",
    "sg:postcode":"5504",
    "sg:province":"Aargau",
    "wof:name":"Epa Superdiscount",
    "wof:placetype":"venue"
},
  "geometry": {"coordinates":[8.2179222107,47.4057693481],"type":"Point"}
}