{
  "type": "Feature",
  "properties": {
    "iso:country":"CH",
    "sg:address":"Chemin Du Boisy 54",
    "sg:city":"Lausanne",
    "sg:orig_category":"Betrieb von Taxis",
    "sg:phone":"+41 79 621 92 34",
    "sg:postcode":"1004",
    "sg:province":"Vaud",
    "wof:name":"G\u00e9rard Ethenoz Taxi",
    "wof:placetype":"venue"
},
  "geometry": {"coordinates":[6.613642,46.536983],"type":"Point"}
}