{
  "type": "Feature",
  "properties": {
    "iso:country":"CH",
    "sg:address":"Ave Des Grandes Maresches 108",
    "sg:city":"Martigny",
    "sg:orig_category":"Bauschreinerei Herstellung von Konstruktionsteilen, Fertigbauteilen U Ausbauelementen aus Holz",
    "sg:phone":"+41 27 722 21 14",
    "sg:postcode":"1920",
    "sg:province":"Valais",
    "wof:name":"Michel Porcellana Menuiserie & Agencement",
    "wof:placetype":"venue"
},
  "geometry": {"coordinates":[7.090341,46.113361],"type":"Point"}
}