{
  "type": "Feature",
  "properties": {
    "iso:country":"CH",
    "sg:address":"Saint-jean Rue De 42 1203 Gen\u00e8ve. Postfach",
    "sg:city":"Gen\u00e8ve",
    "sg:orig_category":"RESTAURANTS: TEA-ROOMS",
    "sg:postcode":"1203",
    "sg:province":"Gen\u00e8ve",
    "wof:name":"A. Rao",
    "wof:placetype":"venue"
},
  "geometry": {"coordinates":[6.1302027702,46.2048683167],"type":"Point"}
}