{
  "type": "Feature",
  "properties": {
    "iso:country":"CH",
    "sg:address":"Chrummacker 9",
    "sg:city":"Frauenkappelen",
    "sg:orig_category":"Sportvereine Turnen",
    "sg:phone":"+41 18650819",
    "sg:postcode":"3202",
    "sg:province":"Bern",
    "wof:name":"Turnverein Stv Freienstein",
    "wof:placetype":"venue"
},
  "geometry": {"coordinates":[8.5665950775,47.5481529236],"type":"Point"}
}