{
  "type": "Feature",
  "properties": {
    "iso:country":"CH",
    "sg:address":"Grand-st-jean Rue 5 1003 Lausanne. Postfach",
    "sg:city":"Lausanne",
    "sg:orig_category":"Detailhandel mit B\u00fcchern, Zeitungen, Schreib U Papeteriewaren",
    "sg:postcode":"1003",
    "sg:province":"Vaud",
    "wof:name":"Librairie Du Grand-st-jean, R. Ryter.",
    "wof:placetype":"venue"
},
  "geometry": {"coordinates":[6.631027,46.521938],"type":"Point"}
}