{
  "type": "Feature",
  "properties": {
    "iso:country":"CH",
    "sg:address":"Avenue Du Fey 13",
    "sg:city":"Moudon",
    "sg:orig_category":"Herstellung von Reiseartikeln, Leder U Sattlerwaren",
    "sg:phone":"+41 21 905 10 21",
    "sg:postcode":"1510",
    "sg:province":"Vaud",
    "wof:name":"Bertholet Andr\u00e9",
    "wof:placetype":"venue"
},
  "geometry": {"coordinates":[6.7955861092,46.6651115417],"type":"Point"}
}