{
  "type": "Feature",
  "properties": {
    "iso:country":"CH",
    "sg:address":"6742",
    "sg:city":"Pollegio",
    "sg:orig_category":"Architektur U Ingenieurb\u00fcros",
    "sg:postcode":"6742",
    "sg:province":"Ticino",
    "wof:name":"R\u00f6\u00f6sli Marc, Studio D'architettura",
    "wof:placetype":"venue"
},
  "geometry": {"coordinates":[8.94664,46.372318],"type":"Point"}
}