{
  "type": "Feature",
  "properties": {
    "iso:country":"CH",
    "sg:address":"M\u00fchlemattstrasse 20",
    "sg:city":"Aarau",
    "sg:orig_category":"Pulvermetallurgie Schmieden, Pressen, Stanzen U Profilwalzen von Metallen",
    "sg:phone":"+41 62 822 12 12",
    "sg:postcode":"5000",
    "sg:province":"Aargau",
    "wof:name":"Felix Schweizer Metalldr\u00fcckerei",
    "wof:placetype":"venue"
},
  "geometry": {"coordinates":[8.0445232391,47.394947052],"type":"Point"}
}