{
  "type": "Feature",
  "properties": {
    "iso:country":"CH",
    "sg:address":"6670",
    "sg:city":"Avegno",
    "sg:orig_category":"Herstellung von Betonerzeugnissen f\u00fcr den Bau Herstellung von Transportbeton",
    "sg:phone":"+41 56 443 01 20",
    "sg:postcode":"6670",
    "sg:province":"Ticino",
    "wof:name":"Element Ag Veltheim Spannbetonwerk",
    "wof:placetype":"venue"
},
  "geometry": {"coordinates":[8.1576557159,47.4346466064],"type":"Point"}
}