{
  "type": "Feature",
  "properties": {
    "iso:country":"CH",
    "sg:address":"Chemin De Pierrefleur 40",
    "sg:city":"Lausanne",
    "sg:classifiers":[
        {
            "category":"Restaurant",
            "type":"Food & Drink"
        }
    ],
    "sg:phone":"+41 21 646 02 02",
    "sg:postcode":"1004",
    "sg:province":"Vaud",
    "wof:name":"Restaurant-chinois Dun-huang",
    "wof:placetype":"venue"
},
  "geometry": {"coordinates":[6.6157870293,46.5358886719],"type":"Point"}
}