{
  "type": "Feature",
  "properties": {
    "iso:country":"CH",
    "sg:address":"Dorfstrasse 18",
    "sg:city":"Trubschachen",
    "sg:orig_category":"Primarschulen",
    "sg:phone":"+41 34 495 56 73",
    "sg:postcode":"3555",
    "sg:province":"Bern",
    "wof:name":"Primarschule Dorf",
    "wof:placetype":"venue"
},
  "geometry": {"coordinates":[7.8437399864,46.9233055115],"type":"Point"}
}