{
  "type": "Feature",
  "properties": {
    "addr:full":"Centro Quadri Taverne Ticino 6807",
    "addr:housenumber":"6807",
    "iso:country":"CH",
    "sg:address":"Centro Quadri",
    "sg:city":"Taverne",
    "sg:orig_category":"Autogaragen Autospenglereien",
    "sg:phone":"+41 91 945 23 14",
    "sg:postcode":"6807",
    "sg:province":"Ticino",
    "wof:name":"Giacomo Pasetti Garage & Carrozzeria",
    "wof:placetype":"venue"
},
  "geometry": {"coordinates":[8.933329,46.067173],"type":"Point"}
}