{
  "type": "Feature",
  "properties": {
    "iso:country":"CH",
    "sg:address":"Emsbach 4",
    "sg:city":"Susten",
    "sg:orig_category":"Offsetdruck Werbung",
    "sg:phone":"+41 79 449 80 64",
    "sg:postcode":"3952",
    "sg:province":"Valais",
    "wof:name":"Turin Robert",
    "wof:placetype":"venue"
},
  "geometry": {"coordinates":[6.1083650589,46.2214851379],"type":"Point"}
}