{
  "type": "Feature",
  "properties": {
    "iso:country":"CH",
    "sg:address":"Pr\u00e9-de-la-tour Chemin Du 7",
    "sg:city":"Pully",
    "sg:orig_category":"Verwaltung von Immobilien",
    "sg:phone":"+41 21 729 39 00",
    "sg:postcode":"1009",
    "sg:province":"Vaud",
    "wof:name":"Guignard Laurent",
    "wof:placetype":"venue"
},
  "geometry": {"coordinates":[6.6589741707,46.5119361877],"type":"Point"}
}