{
  "type": "Feature",
  "properties": {
    "iso:country":"CH",
    "sg:address":"5600",
    "sg:city":"Lenzburg",
    "sg:orig_category":"Verwertung von Milch",
    "sg:postcode":"5600",
    "sg:province":"Aargau",
    "wof:name":"Milchgenossenschaft Ammerswil",
    "wof:placetype":"venue"
},
  "geometry": {"coordinates":[8.1787919998,47.3867912292],"type":"Point"}
}