{
  "type": "Feature",
  "properties": {
    "iso:country":"CH",
    "sg:address":"Neugutstrasse 12",
    "sg:city":"Wallisellen",
    "sg:orig_category":"Allgemeiner Hoch U Tiefbau",
    "sg:phone":"+41 18326866",
    "sg:postcode":"8304",
    "sg:province":"Z\u00fcrich",
    "wof:name":"Adali Engineering",
    "wof:placetype":"venue"
},
  "geometry": {"coordinates":[8.594482,47.412457],"type":"Point"}
}