{
  "type": "Feature",
  "properties": {
    "iso:country":"CH",
    "sg:address":"Kleiner Muristalden 28",
    "sg:city":"Bern",
    "sg:orig_category":"Non-Classified Establishments",
    "sg:postcode":"3006",
    "sg:province":"Bern",
    "wof:name":"Marlies Ammann Psychotherapie",
    "wof:placetype":"venue"
},
  "geometry": {"coordinates":[7.4611978531,46.9450454712],"type":"Point"}
}