{
  "type": "Feature",
  "properties": {
    "addr:full":"1673 Auboranges. Postfach Auboranges Fribourg 1673",
    "addr:housenumber":"1673",
    "addr:postcode":"1673",
    "addr:street":"Auboranges. Postfach",
    "iso:country":"CH",
    "sg:address":"1673 Auboranges. Postfach",
    "sg:city":"Auboranges",
    "sg:orig_category":"Allgemeiner Hoch U Tiefbau",
    "sg:postcode":"1673",
    "sg:province":"Fribourg",
    "wof:name":"Cba - Constructions B\u00e2timents Agricoles Sa",
    "wof:placetype":"venue"
},
  "geometry": {"coordinates":[6.805467,46.581802],"type":"Point"}
}