{
  "type": "Feature",
  "properties": {
    "iso:country":"CH",
    "sg:address":"Alpenstrasse 25",
    "sg:city":"R\u00fcschlikon",
    "sg:orig_category":"Institutionen des Sozialwesens ohne Beherbergung",
    "sg:postcode":"8803",
    "sg:province":"Z\u00fcrich",
    "wof:name":"B\u00dcro F\u00dcr Konfliktforschung In Entwicklungsl\u00c4ndern, Weilenmann Dr. Markus",
    "wof:placetype":"venue"
},
  "geometry": {"coordinates":[8.5554628372,47.301399231],"type":"Point"}
}