{
  "type": "Feature",
  "properties": {
    "iso:country":"CH",
    "sg:address":"Resega Via Chiosso 17",
    "sg:city":"Porza",
    "sg:orig_category":"Mechanische Werkst\u00e4tten",
    "sg:postcode":"6948",
    "sg:province":"Ticino",
    "wof:name":"Michelino Chiodero Airnova",
    "wof:placetype":"venue"
},
  "geometry": {"coordinates":[8.95216465,46.0259933472],"type":"Point"}
}