{
  "type": "Feature",
  "properties": {
    "iso:country":"CH",
    "sg:address":"Rebbergstrasse 22 8706 Meilen. Postfach",
    "sg:city":"Meilen",
    "sg:orig_category":"Herstellung von k\u00e4lte U lufttechnischen Erzeugnissen f\u00fcr gewerbliche Zwecke",
    "sg:postcode":"8706",
    "sg:province":"Z\u00fcrich",
    "wof:name":"Aerofix Gmbh",
    "wof:placetype":"venue"
},
  "geometry": {"coordinates":[8.5261621475,47.4808311462],"type":"Point"}
}