{
  "type": "Feature",
  "properties": {
    "iso:country":"CH",
    "sg:address":"M\u00fcllerwis 14",
    "sg:city":"Greifensee",
    "sg:orig_category":"Zimmerei, Dachdeckerei, Bauspenglerei U Abdichtung",
    "sg:phone":"+41 19417963",
    "sg:postcode":"8606",
    "sg:province":"Z\u00fcrich",
    "wof:name":"Giger Bau",
    "wof:placetype":"venue"
},
  "geometry": {"coordinates":[8.6806097031,47.3696632385],"type":"Point"}
}