{
  "type": "Feature",
  "properties": {
    "iso:country":"CH",
    "sg:address":"Mafroi 5",
    "sg:city":"Nyon",
    "sg:orig_category":"Detailhandel mit Waren verschiedener Art, Hauptrichtung Nahrungsmittel",
    "sg:phone":"+41 22 361 02 72",
    "sg:postcode":"1260",
    "sg:province":"Vaud",
    "wof:name":"B.r.e.a.d. Bureau De Renseignements Et D'etudes Alimentaires & Di\u00e9t\u00e9tiques S\u00e0rl",
    "wof:placetype":"venue"
},
  "geometry": {"coordinates":[6.2425460815,46.3852958679],"type":"Point"}
}