{
  "type": "Feature",
  "properties": {
    "addr:full":"Berninastrasse 11b Z\u00fcrich Z\u00fcrich 8057",
    "addr:housenumber":"11b",
    "addr:postcode":"8057",
    "addr:street":"Berninastrasse",
    "iso:country":"CH",
    "sg:address":"Berninastrasse 11b",
    "sg:city":"Z\u00fcrich",
    "sg:classifiers":[
        {
            "category":"Professional",
            "subcategory":"Advertising",
            "type":"Services"
        }
    ],
    "sg:phone":"+41 13120009",
    "sg:postcode":"8057",
    "sg:province":"Z\u00fcrich",
    "sg:tags":[
        "agency"
    ],
    "wof:name":"Wyss & Partner Ag",
    "wof:placetype":"venue"
},
  "geometry": {"coordinates":[8.552018,47.402546],"type":"Point"}
}