{
  "type": "Feature",
  "properties": {
    "iso:country":"CH",
    "sg:address":"Obstgartenstrasse 12a",
    "sg:city":"Wittenbach",
    "sg:orig_category":"Herstellung von Konstruktionsteilen, Fertigbauteilen U Ausbauelementen aus Holz",
    "sg:postcode":"9303",
    "wof:name":"Grozdanov - Montagen",
    "wof:placetype":"venue"
},
  "geometry": {"coordinates":[9.3871746063,47.4594268799],"type":"Point"}
}