{
  "type": "Feature",
  "properties": {
    "iso:country":"CH",
    "sg:address":"Zinggentorstr. 2 6000 Luzern. Postfach",
    "sg:city":"Luzern",
    "sg:orig_category":"Pensionskassen",
    "sg:postcode":"6003",
    "sg:province":"Luzern",
    "wof:name":"Personalf\u00fcrsorgestiftung Der Grand Hotel National Ag Luzern",
    "wof:placetype":"venue"
},
  "geometry": {"coordinates":[8.3154678345,47.055606842],"type":"Point"}
}