{
  "type": "Feature",
  "properties": {
    "iso:country":"CH",
    "sg:address":"Elsterweg 11a",
    "sg:city":"Thun",
    "sg:orig_category":"Detailhandel mit elektrischen Haushalts-,Radio U Fernsehger\u00e4ten sowie Musikinstrumenten",
    "sg:phone":"+41 33 222 08 36",
    "sg:postcode":"3603",
    "sg:province":"Bern",
    "wof:name":"Music World Bieri",
    "wof:placetype":"venue"
},
  "geometry": {"coordinates":[7.6029839516,46.7673416138],"type":"Point"}
}