{
  "type": "Feature",
  "properties": {
    "iso:country":"CH",
    "sg:address":"7610",
    "sg:city":"Soglio",
    "sg:orig_category":"Gemeindeverwaltungen",
    "sg:phone":"+41 52 649 11 49",
    "sg:postcode":"7610",
    "sg:province":"Graubunden",
    "wof:name":"Canzleira Comunala Lohn",
    "wof:placetype":"venue"
},
  "geometry": {"coordinates":[9.4254198074,46.6509017944],"type":"Point"}
}