{
  "type": "Feature",
  "properties": {
    "iso:country":"CH",
    "sg:address":"Hauptplatz 6017 Ruswil. Postfach 539",
    "sg:city":"Ruswil",
    "sg:classifiers":[
        {
            "category":"Travel",
            "subcategory":"Hotels & Motels",
            "type":"Entertainment"
        }
    ],
    "sg:phone":"+41 41 495 11 25",
    "sg:postcode":"6017",
    "sg:province":"Luzern",
    "sg:tags":[
        "hotels",
        "mit",
        "restaurant"
    ],
    "wof:name":"Erni-wicki Robert",
    "wof:placetype":"venue"
},
  "geometry": {"coordinates":[8.1267251968,47.0840606689],"type":"Point"}
}