{
  "type": "Feature",
  "properties": {
    "iso:country":"CH",
    "sg:address":"Dorfstrasse 16",
    "sg:city":"Baar",
    "sg:orig_category":"Non-Classified Establishments",
    "sg:phone":"+41 41 767 46 54",
    "sg:postcode":"6340",
    "sg:province":"Zug",
    "wof:name":"Mapex Gmbh",
    "wof:placetype":"venue"
},
  "geometry": {"coordinates":[8.5248403549,47.1942100525],"type":"Point"}
}