{
  "type": "Feature",
  "properties": {
    "iso:country":"CH",
    "sg:address":"Im Lehn 3674 Bleiken. Postfach",
    "sg:city":"Bleiken",
    "sg:orig_category":"Markt U Meinungsforschung",
    "sg:phone":"+41 31 772 13 00",
    "sg:postcode":"3674",
    "sg:province":"Bern",
    "wof:name":"Schlag Alexander Beratungsb\u00fcro F\u00fcr Unfalluntersuchung, Marketing, Projektleitung Usw.",
    "wof:placetype":"venue"
},
  "geometry": {"coordinates":[7.6402778625,46.8135871887],"type":"Point"}
}