{
  "type": "Feature",
  "properties": {
    "iso:country":"CH",
    "sg:address":"Englisch-gruss-strasse 48",
    "sg:city":"Glis",
    "sg:orig_category":"Herstellung von Radio U Fernsehger\u00e4ten sowie phono U videotechnischen Ger\u00e4ten",
    "sg:phone":"+41 17864556",
    "sg:postcode":"3902",
    "sg:province":"Valais",
    "wof:name":"Previtali Pre Netcom",
    "wof:placetype":"venue"
},
  "geometry": {"coordinates":[8.7341480255,47.1973953247],"type":"Point"}
}