{
  "type": "Feature",
  "properties": {
    "iso:country":"CH",
    "sg:address":"Unterer R\u00fctiweg 2",
    "sg:city":"Bassersdorf",
    "sg:classifiers":[
        {
            "category":"Professional",
            "subcategory":"Employment Agencies",
            "type":"Services"
        }
    ],
    "sg:phone":"+41 79 228 90 50",
    "sg:postcode":"8303",
    "sg:province":"Z\u00fcrich",
    "sg:tags":[
        "personal",
        "u",
        "stellenvermittlung"
    ],
    "wof:name":"Dbs Bautechnik Gmbh",
    "wof:placetype":"venue"
},
  "geometry": {"coordinates":[8.6433610916,47.4278373718],"type":"Point"}
}