{
  "type": "Feature",
  "properties": {
    "iso:country":"CH",
    "sg:address":"Wehntalerstrasse 253 8000 Z\u00fcrich. Postfach",
    "sg:city":"Z\u00fcrich",
    "sg:orig_category":"Handel mit Automobilen",
    "sg:postcode":"8046",
    "sg:province":"Z\u00fcrich",
    "wof:name":"Kabrit Autohandel",
    "wof:placetype":"venue"
},
  "geometry": {"coordinates":[8.5273838043,47.4100875854],"type":"Point"}
}