{
  "type": "Feature",
  "properties": {
    "iso:country":"CH",
    "sg:address":"Rue Du Bourg-aux-favre 4",
    "sg:city":"Monthey",
    "sg:orig_category":"Detailhandel mit Waren verschiedener Art, Hauptrichtung Nahrungsmittel",
    "sg:postcode":"1870",
    "sg:province":"Valais",
    "wof:name":"Alimentation J.m. Glaus Sa",
    "wof:placetype":"venue"
},
  "geometry": {"coordinates":[6.9466118813,46.2522659302],"type":"Point"}
}