{
  "type": "Feature",
  "properties": {
    "iso:country":"CH",
    "sg:address":"Drahtzugstrasse 18 8008 Z\u00fcrich. Postfach",
    "sg:city":"Z\u00fcrich",
    "sg:orig_category":"Unclassifiable Establishments",
    "sg:postcode":"8001",
    "sg:province":"Z\u00fcrich",
    "wof:name":"Krause Otto R. Ag Beteiligungen Usw; Verwaltung. Handelsgesch\u00e4fte",
    "wof:placetype":"venue"
},
  "geometry": {"coordinates":[8.5609178543,47.3605995178],"type":"Point"}
}