{
  "type": "Feature",
  "properties": {
    "iso:country":"CH",
    "sg:address":"Hauptstrasse 59",
    "sg:city":"Reitnau",
    "sg:orig_category":"G\u00fcterbef\u00f6rderung im Strassenverkehr",
    "sg:phone":"+41 79 320 04 81",
    "sg:postcode":"5057",
    "sg:province":"Aargau",
    "wof:name":"Willi Hochuli Ag Transporte",
    "wof:placetype":"venue"
},
  "geometry": {"coordinates":[8.0489387512,47.2474632263],"type":"Point"}
}