{
  "type": "Feature",
  "properties": {
    "iso:country":"CH",
    "sg:address":"Z\u00fcrcherstrasse 33",
    "sg:city":"Windisch",
    "sg:orig_category":"Detailhandel mit Fahrr\u00e4dern Handel mit Motorr\u00e4dern, Teilen U Zubeh\u00f6r Instandhaltung U Reparatur von ",
    "sg:phone":"+41 56 441 72 22",
    "sg:postcode":"5210",
    "sg:province":"Aargau",
    "wof:name":"Bike Zone Gmbh Windisch",
    "wof:placetype":"venue"
},
  "geometry": {"coordinates":[8.2213468552,47.4785881042],"type":"Point"}
}