{
  "type": "Feature",
  "properties": {
    "iso:country":"CH",
    "sg:address":"8401 Winterthur. Postfach 1223",
    "sg:city":"Winterthur",
    "sg:classifiers":[
        {
            "category":"Education",
            "subcategory":"Library",
            "type":"Public Place"
        }
    ],
    "sg:postcode":"8401",
    "sg:province":"Z\u00fcrich",
    "sg:tags":[
        "u",
        "bibliotheken",
        "archive"
    ],
    "wof:name":"Bibliothek Des Technikervereins Argovia",
    "wof:placetype":"venue"
},
  "geometry": {"coordinates":[8.72616,47.499882],"type":"Point"}
}