{
  "type": "Feature",
  "properties": {
    "iso:country":"CH",
    "sg:address":"Ch\u00eatre Rue De 20",
    "sg:city":"Del\u00e9mont",
    "sg:orig_category":"Grosshandel mit Holz U Baustoffen",
    "sg:phone":"+41 32 423 01 27",
    "sg:postcode":"2800",
    "sg:province":"Jura",
    "wof:name":"Fehr Technologie S\u00e0rl",
    "wof:placetype":"venue"
},
  "geometry": {"coordinates":[7.3429698944,47.3676185608],"type":"Point"}
}