{
  "type": "Feature",
  "properties": {
    "iso:country":"CH",
    "sg:address":"Route De Bitternaz 16",
    "sg:city":"Corcelles-payerne",
    "sg:classifiers":[
        {
            "category":"Travel",
            "subcategory":"Hotels & Motels",
            "type":"Entertainment"
        }
    ],
    "sg:phone":"+41 61 331 56 22",
    "sg:postcode":"1562",
    "sg:province":"Vaud",
    "sg:tags":[
        "hotels",
        "mit",
        "restaurant"
    ],
    "wof:name":"Florini Antonio",
    "wof:placetype":"venue"
},
  "geometry": {"coordinates":[9.0076999664,45.8654785156],"type":"Point"}
}