{
  "type": "Feature",
  "properties": {
    "iso:country":"CH",
    "sg:address":"Steinberg",
    "sg:city":"H\u00fcswil",
    "sg:orig_category":"Gewinnung von Kies U Sand",
    "sg:phone":"+41 41 988 12 63",
    "sg:postcode":"6152",
    "sg:province":"Luzern",
    "wof:name":"Kieswerk H\u00fcswil Ag",
    "wof:placetype":"venue"
},
  "geometry": {"coordinates":[7.9067640305,47.1275482178],"type":"Point"}
}