{
  "type": "Feature",
  "properties": {
    "iso:country":"CH",
    "sg:address":"Stationsstr. 7 Sulz",
    "sg:city":"Rickenbach-attikon",
    "sg:orig_category":"RESTAURANTS: TEA-ROOMS",
    "sg:phone":"+41 52 337 13 40",
    "sg:postcode":"8544",
    "sg:province":"Z\u00fcrich",
    "wof:name":"Marmillod Jacques, Restaurant Bahnhof",
    "wof:placetype":"venue"
},
  "geometry": {"coordinates":[8.797454834,47.5358734131],"type":"Point"}
}