{
  "type": "Feature",
  "properties": {
    "iso:country":"CH",
    "sg:address":"Humrigenflurstrasse 4",
    "sg:city":"Herrliberg",
    "sg:orig_category":"Detailhandel mit Boden U Wandbel\u00e4gen ohne Teppiche Verlegen von Fussboden",
    "sg:phone":"+41 19151417",
    "sg:postcode":"8704",
    "sg:province":"Z\u00fcrich",
    "wof:name":"Kaspar Leuthold Bodenbel\u00e4ge",
    "wof:placetype":"venue"
},
  "geometry": {"coordinates":[8.620682,47.284157],"type":"Point"}
}