{
  "type": "Feature",
  "properties": {
    "iso:country":"CH",
    "sg:address":"Lagerstrasse 95",
    "sg:city":"Z\u00fcrich",
    "sg:orig_category":"Reiseb\u00fcros U Reiseveranstalter",
    "sg:postcode":"8004",
    "sg:province":"Z\u00fcrich",
    "wof:name":"Travel Together, Faschian Yvonne Reisepartnervermittlung. M\u00f6blierte Wohnungen Auf Zeit; Vermittlung",
    "wof:placetype":"venue"
},
  "geometry": {"coordinates":[8.5297498703,47.3792800903],"type":"Point"}
}