{
  "type": "Feature",
  "properties": {
    "addr:full":"Rue Du Temple 7 St-blaise Neuch\u00e2tel 2072",
    "addr:housenumber":"7",
    "addr:postcode":"2072",
    "addr:street":"Rue Du Temple;Neucha\u0302Tel",
    "iso:country":"CH",
    "sg:address":"Rue Du Temple 7",
    "sg:city":"St-blaise",
    "sg:orig_category":"Detailhandel mit Brot, Back U S\u00fcsswaren",
    "sg:phone":"+41 32 753 41 29",
    "sg:postcode":"2072",
    "sg:province":"Neuch\u00e2tel",
    "wof:name":"Michel Garnier Boulangerie & P\u00e2tisserie",
    "wof:placetype":"venue"
},
  "geometry": {"coordinates":[6.987169,47.01384],"type":"Point"}
}