{
  "type": "Feature",
  "properties": {
    "iso:country":"CH",
    "sg:address":"Im Kleinholz 20",
    "sg:city":"Olten",
    "sg:orig_category":"Unternehmensberatung",
    "sg:phone":"+41 62 213 87 80",
    "sg:postcode":"4600",
    "sg:province":"Solothurn",
    "wof:name":"Innovation Unternehmensberatung Wellinger Karl Dipl. Ing. Eth",
    "wof:placetype":"venue"
},
  "geometry": {"coordinates":[7.9007439613,47.3448791504],"type":"Point"}
}