{
  "type": "Feature",
  "properties": {
    "iso:country":"CH",
    "sg:address":"Corso Elvezia 7",
    "sg:city":"Lugano",
    "sg:orig_category":"Erbringung von Dienstleistungen f\u00fcr Unternehmen Innendekorationsateliers",
    "sg:phone":"+41 91 923 54 36",
    "sg:postcode":"6900",
    "sg:province":"Ticino",
    "wof:name":"Rezzonico Claudia",
    "wof:placetype":"venue"
},
  "geometry": {"coordinates":[8.95545578,46.0065612793],"type":"Point"}
}