{
  "type": "Feature",
  "properties": {
    "iso:country":"CH",
    "sg:address":"Weissensteinstrasse 8",
    "sg:city":"Wiedlisbach",
    "sg:orig_category":"Grosshandel mit Geschenkartikeln U Souvenirs Markt U Meinungsforschung",
    "sg:phone":"+41 32 637 32 33",
    "sg:postcode":"4537",
    "sg:province":"Bern",
    "wof:name":"Jora Line Pfister & Partner",
    "wof:placetype":"venue"
},
  "geometry": {"coordinates":[7.6414551735,47.2512283325],"type":"Point"}
}