{
  "type": "Feature",
  "properties": {
    "iso:country":"CH",
    "sg:address":"Zum Wisse Segel 20",
    "sg:city":"Arlesheim",
    "sg:orig_category":"Vermittlung von Immobilien Verwaltung von Immobilien",
    "sg:phone":"+41 61 701 41 93",
    "sg:postcode":"4144",
    "sg:province":"Basel-Landschaft",
    "wof:name":"Alexander Litzius Immobilien-dienstleistungs Ag",
    "wof:placetype":"venue"
},
  "geometry": {"coordinates":[7.6202712059,47.4896011353],"type":"Point"}
}