{
  "type": "Feature",
  "properties": {
    "iso:country":"CH",
    "sg:address":"Gerechtigkeitsgasse 33",
    "sg:city":"Bern",
    "sg:orig_category":"Grosshandel mit Blumen U Pflanzen Grosshandel mit sonstigen Gebrauchs U Verbrauchsg\u00fctern",
    "sg:phone":"+41 31 311 03 38",
    "sg:postcode":"3011",
    "sg:province":"Bern",
    "wof:name":"Decofloram Ag Textilblumen, Floristisches Dekorationsmaterial; Handel, Verarbeitung",
    "wof:placetype":"venue"
},
  "geometry": {"coordinates":[7.4543581009,46.9482002258],"type":"Point"}
}