{
  "type": "Feature",
  "properties": {
    "iso:country":"CH",
    "sg:address":"Gotthelfstrasse 17",
    "sg:city":"Biberist",
    "sg:orig_category":"Institutionen f\u00fcr psychosoziale F\u00e4lle Sonderschulen",
    "sg:phone":"+41 32 671 62 71",
    "sg:postcode":"4562",
    "sg:province":"Solothurn",
    "wof:name":"Gotthelf-haus",
    "wof:placetype":"venue"
},
  "geometry": {"coordinates":[7.5606760979,47.193145752],"type":"Point"}
}