{
  "type": "Feature",
  "properties": {
    "iso:country":"CH",
    "sg:address":"Waffenplatzstrasse 46 8000 Z\u00fcrich. Postfach 157",
    "sg:city":"Z\u00fcrich",
    "sg:orig_category":"Detailhandel mit elektrischen Haushalts-,Radio U Fernsehger\u00e4ten sowie Musikinstrumenten",
    "sg:phone":"+41 12416232",
    "sg:postcode":"8002",
    "sg:province":"Z\u00fcrich",
    "wof:name":"Goldspring P.l.c., London, Zweigniederlassung Z\u00fcrich Musik, Mode- U. Kunstartikel ; Gross, Detailhandel",
    "wof:placetype":"venue"
},
  "geometry": {"coordinates":[8.5267820358,47.3590126038],"type":"Point"}
}