{
  "type": "Feature",
  "properties": {
    "iso:country":"CH",
    "sg:address":"Landstrasse 23",
    "sg:city":"Andelfingen",
    "sg:orig_category":"Selbst\u00e4ndige bildende K\u00fcnstler",
    "sg:phone":"+41 52 317 31 15",
    "sg:postcode":"8450",
    "sg:province":"Z\u00fcrich",
    "wof:name":"Christian Koradi Bildhauerei-grabmalkunst",
    "wof:placetype":"venue"
},
  "geometry": {"coordinates":[8.6804790497,47.5910568237],"type":"Point"}
}