{
  "type": "Feature",
  "properties": {
    "iso:country":"CH",
    "sg:address":"Moosgasse 31",
    "sg:city":"Ins",
    "sg:orig_category":"Architektur U Ingenieurb\u00fcros Geometerb\u00fcros",
    "sg:phone":"+41 32 313 19 65",
    "sg:postcode":"3232",
    "sg:province":"Bern",
    "wof:name":"L\u00fcscher & Aeschlimann Ag",
    "wof:placetype":"venue"
},
  "geometry": {"coordinates":[7.108244,47.001431],"type":"Point"}
}