{
  "type": "Feature",
  "properties": {
    "iso:country":"CH",
    "sg:address":"Rheinstrasse 7",
    "sg:city":"Liestal",
    "sg:orig_category":"Pensionskassen",
    "sg:postcode":"4410",
    "sg:province":"Basel-Landschaft",
    "wof:name":"Freiz\u00fcgigkeitsstiftung Der Basellandschaftlichen Kantonalbank",
    "wof:placetype":"venue"
},
  "geometry": {"coordinates":[7.7322149277,47.4860992432],"type":"Point"}
}