{
  "type": "Feature",
  "properties": {
    "iso:country":"CH",
    "sg:address":"Rue Jean-ant.-gautier 18",
    "sg:city":"Gen\u00e8ve",
    "sg:classifiers":[
        {
            "category":"Restaurant",
            "type":"Food & Drink"
        }
    ],
    "sg:phone":"+41 22 738 38 58",
    "sg:postcode":"1201",
    "sg:province":"Gen\u00e8ve",
    "wof:name":"Caf\u00e9 Jazz",
    "wof:placetype":"venue"
},
  "geometry": {"coordinates":[6.1494650841,46.2140426636],"type":"Point"}
}