{
  "type": "Feature",
  "properties": {
    "iso:country":"CH",
    "sg:address":"Lerchenberg 16",
    "sg:city":"Z\u00fcrich",
    "sg:orig_category":"Allgemeinbildende weiterf\u00fchrende Schulen",
    "sg:postcode":"8046",
    "sg:province":"Z\u00fcrich",
    "wof:name":"Nowesa Schule P. N\u00e4f Schule Zur Vorbereitung Auf Soziale Berufe Usw.",
    "wof:placetype":"venue"
},
  "geometry": {"coordinates":[8.508014,47.412903],"type":"Point"}
}