{
  "type": "Feature",
  "properties": {
    "iso:country":"CH",
    "sg:address":"Steinacherstrasse 150",
    "sg:city":"W\u00e4denswil",
    "sg:orig_category":"Sportvereine Billard",
    "sg:phone":"+41 79 637 20 19",
    "sg:postcode":"8820",
    "sg:province":"Z\u00fcrich",
    "wof:name":"Cl.billard Du Vignoble Neuch.",
    "wof:placetype":"venue"
},
  "geometry": {"coordinates":[6.8547291756,46.9666748047],"type":"Point"}
}