{
  "type": "Feature",
  "properties": {
    "iso:country":"CH",
    "sg:address":"Sumpfstrasse 6",
    "sg:city":"Steinhausen",
    "sg:orig_category":"Herstellung von sonstigen elektrischen Ausr\u00fcstungen",
    "sg:phone":"+41 41 743 10 30",
    "sg:postcode":"6312",
    "sg:province":"Zug",
    "wof:name":"Dymatic Ag",
    "wof:placetype":"venue"
},
  "geometry": {"coordinates":[8.4914398193,47.1870918274],"type":"Point"}
}