{
  "type": "Feature",
  "properties": {
    "iso:country":"CH",
    "sg:address":"Ch\u00e2teau R.de La Coll\u00e9giale 12",
    "sg:city":"Neuch\u00e2tel",
    "sg:orig_category":"Verwaltung der Rechtspflege, Gerichte",
    "sg:phone":"+41 21 315 52 62",
    "sg:postcode":"2000",
    "sg:province":"Neuch\u00e2tel",
    "wof:name":"Service Du Cadastre & De L'informat.sur Le Territoire",
    "wof:placetype":"venue"
},
  "geometry": {"coordinates":[6.6342368126,46.5247840881],"type":"Point"}
}