{
  "type": "Feature",
  "properties": {
    "iso:country":"CH",
    "sg:address":"Franscini Viale 12",
    "sg:city":"Lugano",
    "sg:orig_category":"Museen",
    "sg:phone":"+41 91 808 19 88",
    "sg:postcode":"6900",
    "sg:province":"Ticino",
    "wof:name":"Fondazione Galleria Gottardo",
    "wof:placetype":"venue"
},
  "geometry": {"coordinates":[8.9513053894,46.0029754639],"type":"Point"}
}