{
  "type": "Feature",
  "properties": {
    "iso:country":"CH",
    "sg:address":"Hasenstrasse 2",
    "sg:city":"Riedholz",
    "sg:orig_category":"Landesverteidigung, Sozialversicherung \u00d6ffentliche Verwaltung",
    "sg:phone":"+41 61 646 81 11",
    "sg:postcode":"4533",
    "sg:province":"Solothurn",
    "wof:name":"Zivilschutzstelle Riehen",
    "wof:placetype":"venue"
},
  "geometry": {"coordinates":[7.6511301994,47.5845756531],"type":"Point"}
}