{
  "type": "Feature",
  "properties": {
    "addr:full":"Hauptstrasse 158 Schwanden Glarus 8762",
    "addr:housenumber":"158",
    "addr:postcode":"8762",
    "addr:street":"Hauptstrasse;Glarus",
    "iso:country":"CH",
    "sg:address":"Hauptstrasse 158",
    "sg:city":"Schwanden",
    "sg:classifiers":[
        {
            "category":"Manufacturing",
            "subcategory":"Wood Products",
            "type":"Manufacturing & Wholesale Goods"
        }
    ],
    "sg:phone":"+41 55 647 48 88",
    "sg:postcode":"8762",
    "sg:province":"Glarus",
    "sg:tags":[
        "made",
        "balcony"
    ],
    "wof:name":"Wirth Holzbau Ag",
    "wof:placetype":"venue"
},
  "geometry": {"coordinates":[9.060582,46.989223],"type":"Point"}
}