{
  "type": "Feature",
  "properties": {
    "iso:country":"CH",
    "sg:address":"Geroldstrasse 28 8005 Z\u00fcrich. Postfach",
    "sg:city":"Z\u00fcrich",
    "sg:orig_category":"Sonstiges Textilgewerbe",
    "sg:phone":"+41 55 210 20 05",
    "sg:postcode":"8001",
    "sg:province":"Z\u00fcrich",
    "wof:name":"Portobello Idea Pubblicita Delli Colli R.",
    "wof:placetype":"venue"
},
  "geometry": {"coordinates":[8.8177194595,47.2274703979],"type":"Point"}
}