{
  "type": "Feature",
  "properties": {
    "addr:full":"G\u00e4ustrasse 11 4703 Kestenholz. Postfach 52 Kestenholz Solothurn 4703",
    "addr:housenumber":"11;52",
    "addr:postcode":"4703 kestenholz.;4703",
    "addr:street":"Gaeustrasse;Postfach",
    "iso:country":"CH",
    "sg:address":"G\u00e4ustrasse 11 4703 Kestenholz. Postfach 52",
    "sg:city":"Kestenholz",
    "sg:orig_category":"Allgemeiner Hoch U Tiefbau Allgemeiner Hochbau",
    "sg:phone":"+41 62 393 10 10",
    "sg:postcode":"4703",
    "sg:province":"Solothurn",
    "wof:name":"Von D\u00e4niken + Fritschi Ag",
    "wof:placetype":"venue"
},
  "geometry": {"coordinates":[7.758519,47.28643],"type":"Point"}
}