{
  "type": "Feature",
  "properties": {
    "iso:country":"CH",
    "sg:address":"Weilerweg 11",
    "sg:city":"Basel",
    "sg:orig_category":"Tankstellen",
    "sg:phone":"+41 61 631 04 44",
    "sg:postcode":"4057",
    "sg:province":"Basel-Stadt",
    "wof:name":"Shell-service-station Baslertor, Bernadette Cherbuin-wilde",
    "wof:placetype":"venue"
},
  "geometry": {"coordinates":[7.5936059952,47.5849990845],"type":"Point"}
}