{
  "type": "Feature",
  "properties": {
    "iso:country":"CH",
    "sg:address":"Winkelriedstrasse 75",
    "sg:city":"Schaffhausen",
    "sg:orig_category":"Sportvereine Ballsport Tennis",
    "sg:phone":"+41 52 624 48 45",
    "sg:postcode":"8200",
    "sg:province":"Schaffhausen",
    "wof:name":"Tc Buchthalen",
    "wof:placetype":"venue"
},
  "geometry": {"coordinates":[8.6522035599,47.7011413574],"type":"Point"}
}