{
  "type": "Feature",
  "properties": {
    "iso:country":"CH",
    "sg:address":"Rue De La Samaritaine 40.",
    "sg:city":"Fribourg",
    "sg:orig_category":"Pensionskassen",
    "sg:postcode":"1700",
    "sg:province":"Fribourg",
    "wof:name":"Fonds De Pr\u00e9voyance En Faveur Du Personnel De L'entreprise Louis Corpataux, Carrelages Et Rev\u00eatements.",
    "wof:placetype":"venue"
},
  "geometry": {"coordinates":[7.1673841476,46.8034973145],"type":"Point"}
}