{
  "type": "Feature",
  "properties": {
    "iso:country":"CH",
    "sg:address":"Chrea 69",
    "sg:city":"Schiers",
    "sg:orig_category":"Detailhandel mit Ton U Bildtr\u00e4gern Versandhandel",
    "sg:phone":"+41 81 328 17 83",
    "sg:postcode":"7220",
    "sg:province":"Graubunden",
    "wof:name":"Hawi Volksmusik-versand",
    "wof:placetype":"venue"
},
  "geometry": {"coordinates":[9.6896972656,46.9700660706],"type":"Point"}
}