{
  "type": "Feature",
  "properties": {
    "iso:country":"CH",
    "sg:address":"8413",
    "sg:city":"Neftenbach",
    "sg:orig_category":"Vereine Gesang",
    "sg:postcode":"8413",
    "sg:province":"Z\u00fcrich",
    "wof:name":"Christl.gesangsverein",
    "wof:placetype":"venue"
},
  "geometry": {"coordinates":[8.6679525375,47.5288391113],"type":"Point"}
}