{
  "type": "Feature",
  "properties": {
    "iso:country":"CH",
    "sg:address":"Grundstrasse 584",
    "sg:city":"St\u00e4fa",
    "sg:orig_category":"Vorschulen, Kinderg\u00e4rten",
    "sg:phone":"+41 21 634 74 38",
    "sg:postcode":"8712",
    "sg:province":"Z\u00fcrich",
    "wof:name":"Garderie D'enfants De Florissant,marie-louise Guex",
    "wof:placetype":"venue"
},
  "geometry": {"coordinates":[6.579390049,46.5390815735],"type":"Point"}
}