{
  "type": "Feature",
  "properties": {
    "iso:country":"CH",
    "sg:address":"Biestr. 158",
    "sg:city":"Solothurn",
    "sg:classifiers":[
        {
            "category":"Professional",
            "subcategory":"Employment Agencies",
            "type":"Services"
        }
    ],
    "sg:phone":"+41 32 622 20 46",
    "sg:postcode":"4500",
    "sg:province":"Solothurn",
    "sg:tags":[
        "good",
        "fabric",
        "household",
        "textile",
        "linen",
        "wood",
        "clothing",
        "furniture"
    ],
    "wof:name":"Eberhard Innenausstattungen",
    "wof:placetype":"venue"
},
  "geometry": {"coordinates":[7.5185399055,47.2124137878],"type":"Point"}
}