{
  "type": "Feature",
  "properties": {
    "iso:country":"CH",
    "sg:address":"Vors\u00e4ss",
    "sg:city":"Ennetmoos",
    "sg:orig_category":"Architektur U Ingenieurb\u00fcros",
    "sg:phone":"+41 41 610 43 59",
    "sg:postcode":"6372",
    "sg:province":"Nidwalden",
    "wof:name":"Architekturb\u00fcro Br\u00fchlmann",
    "wof:placetype":"venue"
},
  "geometry": {"coordinates":[8.302936,46.94368],"type":"Point"}
}