{
  "type": "Feature",
  "properties": {
    "iso:country":"CH",
    "sg:address":"Winon",
    "sg:city":"Berom\u00fcnster",
    "sg:orig_category":"Detailhandel mit Milcherzeugnissen U Eiern Verarbeitung von Milch",
    "sg:phone":"+41 41 930 15 43",
    "sg:postcode":"6215",
    "sg:province":"Luzern",
    "wof:name":"Meinrad Abt K\u00e4serei",
    "wof:placetype":"venue"
},
  "geometry": {"coordinates":[8.1919603348,47.2064552307],"type":"Point"}
}