{
  "type": "Feature",
  "properties": {
    "iso:country":"CH",
    "sg:address":"Stutzstrasse 16",
    "sg:city":"Niederwichtrach",
    "sg:orig_category":"Sportvereine Turnen Vereine Damen",
    "sg:phone":"+41 31 781 24 37",
    "sg:postcode":"3114",
    "sg:province":"Bern",
    "wof:name":"Damenriege Stv M\u00fcnsingen",
    "wof:placetype":"venue"
},
  "geometry": {"coordinates":[7.5804729462,46.8497047424],"type":"Point"}
}