{
  "type": "Feature",
  "properties": {
    "iso:country":"CH",
    "sg:address":"Rickenstr. 24",
    "sg:city":"Ernetschwil",
    "sg:orig_category":"Detektivb\u00fcros U \u00dcberwachung",
    "sg:postcode":"8725",
    "sg:province":"St. Gallen",
    "wof:name":"Pl\u00fcss W. Sicherheitsdienst",
    "wof:placetype":"venue"
},
  "geometry": {"coordinates":[9.0075178146,47.2517852783],"type":"Point"}
}