{
  "type": "Feature",
  "properties": {
    "iso:country":"CH",
    "sg:address":"Juraweg 12",
    "sg:city":"Lyss",
    "sg:orig_category":"Maler U Glasergewerbe Malerei",
    "sg:phone":"+41 32 384 39 24",
    "sg:postcode":"3250",
    "sg:province":"Bern",
    "wof:name":"Mattioni Elio.",
    "wof:placetype":"venue"
},
  "geometry": {"coordinates":[7.3042411804,47.0745582581],"type":"Point"}
}