{
  "type": "Feature",
  "properties": {
    "iso:country":"CH",
    "sg:address":"Reichsgasse 18 7000 Chur. Postfach",
    "sg:city":"Chur",
    "sg:orig_category":"HOTELS: MIT RESTAURANT Kongress- and Tagungshotels mit Restaurant",
    "sg:phone":"+41 81 252 17 25",
    "sg:postcode":"7002",
    "sg:province":"Graubunden",
    "wof:name":"Hotel Drei K\u00f6nige",
    "wof:placetype":"venue"
},
  "geometry": {"coordinates":[9.5338783264,46.8509750366],"type":"Point"}
}