{
  "type": "Feature",
  "properties": {
    "iso:country":"CH",
    "sg:address":"Schloss-strasse 7",
    "sg:city":"Oberdiessbach",
    "sg:orig_category":"G\u00fcterbef\u00f6rderung im Strassenverkehr",
    "sg:phone":"+41 31 771 04 23",
    "sg:postcode":"3672",
    "sg:province":"Bern",
    "wof:name":"Graf Hansrudolf",
    "wof:placetype":"venue"
},
  "geometry": {"coordinates":[7.6191949844,46.8394165039],"type":"Point"}
}