{
  "type": "Feature",
  "properties": {
    "iso:country":"CH",
    "sg:address":"Kirchstrasse 99",
    "sg:city":"Grenchen",
    "sg:orig_category":"Allgemeiner Hochbau K\u00fcnstlerische U schriftstellerische T\u00e4tigkeiten U Darbietungen",
    "sg:phone":"+41 81 854 28 19",
    "sg:postcode":"2540",
    "sg:province":"Solothurn",
    "wof:name":"Nuotcl\u00e0 Paulin, Restaurator",
    "wof:placetype":"venue"
},
  "geometry": {"coordinates":[9.924975,46.57967],"type":"Point"}
}