{
  "type": "Feature",
  "properties": {
    "iso:country":"CH",
    "sg:address":"Sch\u00fctzengartenstrasse 2 9242 Oberuzwil. Postfach",
    "sg:city":"Oberuzwil",
    "sg:orig_category":"Allgemeiner Hoch U Tiefbau Allgemeiner Hoch U Tiefbau ohne ausgepr\u00e4gten Schwerpunkt",
    "sg:phone":"+41 71 951 94 01",
    "sg:postcode":"9242",
    "sg:province":"St. Gallen",
    "wof:name":"Hagmann Ag, Bauunternehmung Hoch, Tiefbau, Liegenschaften",
    "wof:placetype":"venue"
},
  "geometry": {"coordinates":[9.122498,47.430637],"type":"Point"}
}