{
  "type": "Feature",
  "properties": {
    "iso:country":"CH",
    "sg:address":"Kirchgasse 17",
    "sg:city":"Uesslingen",
    "sg:orig_category":"Grosshandel mit sonstigen Maschinen U Ausr\u00fcstungen f\u00fcr Industrie, Handel U Schiffahrt Handelsvermitt",
    "sg:phone":"+41 52 746 13 28",
    "sg:postcode":"8524",
    "sg:province":"Thurgau",
    "wof:name":"Feller Vertretungen Gmbh",
    "wof:placetype":"venue"
},
  "geometry": {"coordinates":[8.8295240402,47.579750061],"type":"Point"}
}