{
  "type": "Feature",
  "properties": {
    "iso:country":"CH",
    "sg:address":"Dorfstrasse 2",
    "sg:city":"Sch\u00f6ftland",
    "sg:orig_category":"Detailhandel mit Waren verschiedener Art, Hauptrichtung Nahrungsmittel",
    "sg:phone":"+41 62 721 12 80",
    "sg:postcode":"5040",
    "sg:province":"Aargau",
    "wof:name":"Landw.genossenschaft Suhrental",
    "wof:placetype":"venue"
},
  "geometry": {"coordinates":[8.0510931015,47.3036994934],"type":"Point"}
}