{
  "type": "Feature",
  "properties": {
    "iso:country":"CH",
    "sg:address":"Avenue Des Boveresses 32 1000 Lausanne. Postfach",
    "sg:city":"Lausanne",
    "sg:orig_category":"Sanit\u00e4r, Heizungs U L\u00fcftungsinstallation",
    "sg:postcode":"1002",
    "sg:province":"Vaud",
    "wof:name":"Erard Chauffage",
    "wof:placetype":"venue"
},
  "geometry": {"coordinates":[6.6640210152,46.5355300903],"type":"Point"}
}