{
  "type": "Feature",
  "properties": {
    "addr:full":"Le Montessingeoz Attalens Fribourg 1616",
    "addr:postcode":"1616",
    "iso:country":"CH",
    "sg:address":"Le Montessingeoz",
    "sg:city":"Attalens",
    "sg:orig_category":"Bauschreinerei Zimmerei, Ingenieurholzbau",
    "sg:phone":"+41 21 947 42 57",
    "sg:postcode":"1616",
    "sg:province":"Fribourg",
    "wof:name":"Menuiserie-charpente Constructions Dumoulin Sa",
    "wof:placetype":"venue"
},
  "geometry": {"coordinates":[6.841823,46.510887],"type":"Point"}
}