{
  "type": "Feature",
  "properties": {
    "iso:country":"CH",
    "sg:address":"Baslerstrasse 40 4102 Binningen. Postfach",
    "sg:city":"Binningen",
    "sg:orig_category":"Herstellung von elektrischen Lampen U Leuchten",
    "sg:postcode":"4102",
    "sg:province":"Basel-Landschaft",
    "wof:name":"Schaublicht Gmbh",
    "wof:placetype":"venue"
},
  "geometry": {"coordinates":[7.5754299164,47.538898468],"type":"Point"}
}