{
  "type": "Feature",
  "properties": {
    "addr:full":"Route De Taillepied 79 Ch\u00e2telard-lutry Vaud 1095",
    "addr:housenumber":"79",
    "addr:postcode":"1095",
    "addr:street":"Route De Taillepied",
    "iso:country":"CH",
    "sg:address":"Route De Taillepied 79",
    "sg:city":"Ch\u00e2telard-lutry",
    "sg:orig_category":"Bau von Strassen, Sportanlagen U Bahnverkehrsstrecken Sonstiger Grosshandel",
    "sg:phone":"+41 21 791 68 33",
    "sg:postcode":"1095",
    "sg:province":"Vaud",
    "wof:name":"Ipp Irrigation, Piscines Et Pompes, Brian Charlton",
    "wof:placetype":"venue"
},
  "geometry": {"coordinates":[6.680891,46.505257],"type":"Point"}
}