{
  "type": "Feature",
  "properties": {
    "iso:country":"CH",
    "sg:address":"Rue De Gen\u00e8ve 76",
    "sg:city":"Ch\u00eane-bourg",
    "sg:orig_category":"RESTAURANTS: TEA-ROOMS",
    "sg:phone":"+41 22 349 66 40",
    "sg:postcode":"1225",
    "sg:province":"Gen\u00e8ve",
    "wof:name":"La Gourmandine, Marie Catherine Marquet",
    "wof:placetype":"venue"
},
  "geometry": {"coordinates":[6.1980080605,46.1935081482],"type":"Point"}
}