{
  "type": "Feature",
  "properties": {
    "addr:full":"Route Des Perveuils 10 Marin-epagnier Neuch\u00e2tel 2074",
    "addr:housenumber":"10",
    "addr:postcode":"2074",
    "addr:street":"Route Des Perveuils;Marin-Epagnier Neucha\u0302Tel",
    "iso:country":"CH",
    "sg:address":"Route Des Perveuils 10",
    "sg:city":"Marin-epagnier",
    "sg:classifiers":[
        {
            "category":"Airport",
            "type":"Transportation"
        }
    ],
    "sg:phone":"+41 32 756 00 60",
    "sg:postcode":"2074",
    "sg:province":"Neuch\u00e2tel",
    "sg:tags":[
        "air-freight",
        "forwarders"
    ],
    "wof:name":"Wittwer S.a.",
    "wof:placetype":"venue"
},
  "geometry": {"coordinates":[7.01221,47.01215],"type":"Point"}
}