{
  "type": "Feature",
  "properties": {
    "addr:full":"31 Chemin William Barbey - Case Postake 39 - 1291 Chambesy 31",
    "addr:housenumber":"31;39;31",
    "addr:postcode":"1291",
    "addr:street":"Chemin William Barbey Case Postake;Chambesy",
    "iso:country":"CH",
    "sg:address":"31",
    "sg:city":"Chemin William Barbey - Case Postake 39 - 1291 Chambesy",
    "sg:classifiers":[
        {
            "category":"Professional",
            "subcategory":"Art Services",
            "type":"Services"
        }
    ],
    "sg:phone":"+41 7581988",
    "sg:postcode":"31",
    "sg:tags":[
        "export-import"
    ],
    "wof:name":"Bahrain Consulate",
    "wof:placetype":"venue"
},
  "geometry": {"coordinates":[6.148766,46.240746],"type":"Point"}
}