{
  "type": "Feature",
  "properties": {
    "iso:country":"CH",
    "sg:address":"Sonnenstrasse 7",
    "sg:city":"Biel/bienne",
    "sg:orig_category":"Vorschulen, Kinderg\u00e4rten",
    "sg:phone":"+41 61 421 44 27",
    "sg:postcode":"2504",
    "sg:province":"Bern",
    "wof:name":"Kindergarten",
    "wof:placetype":"venue"
},
  "geometry": {"coordinates":[7.5990819931,47.4978408813],"type":"Point"}
}