{
  "type": "Feature",
  "properties": {
    "iso:country":"CH",
    "sg:address":"Langendorfstrasse 2",
    "sg:city":"Langendorf",
    "sg:orig_category":"Einzelhandel mit Automobilteilen U Zubeh\u00f6r Herstellung von Bereifungen",
    "sg:phone":"+41 32 618 11 48",
    "sg:postcode":"4513",
    "sg:province":"Solothurn",
    "wof:name":"Pneuhaus Ruch",
    "wof:placetype":"venue"
},
  "geometry": {"coordinates":[7.5151081085,47.2164840698],"type":"Point"}
}