{
  "type": "Feature",
  "properties": {
    "iso:country":"CH",
    "sg:address":"Frohaldenstrasse 14 8180 B\u00fclach. Postfach 18",
    "sg:city":"B\u00fclach",
    "sg:orig_category":"Kauf U Verkauf von Immobilien auf eigene Rechnung Vorschulen, Kinderg\u00e4rten",
    "sg:phone":"+41 32 968 67 50",
    "sg:postcode":"8180",
    "sg:province":"Z\u00fcrich",
    "wof:name":"G\u00e9rance Esplanade S\u00e0rl",
    "wof:placetype":"venue"
},
  "geometry": {"coordinates":[6.8404078484,47.1069641113],"type":"Point"}
}