{
  "type": "Feature",
  "properties": {
    "iso:country":"CH",
    "sg:address":"Freiburgstrasse 11",
    "sg:city":"Schwarzenburg",
    "sg:orig_category":"Tierarztpraxis",
    "sg:phone":"+41 31 731 02 67",
    "sg:postcode":"3150",
    "sg:province":"Bern",
    "wof:name":"Dr.med.vet. Beat H\u00e4hni Tierarzt",
    "wof:placetype":"venue"
},
  "geometry": {"coordinates":[7.3385639191,46.817401886],"type":"Point"}
}