{
  "type": "Feature",
  "properties": {
    "iso:country":"CH",
    "sg:address":"Brunnmattstrasse 1",
    "sg:city":"Baden",
    "sg:orig_category":"Herstellung von Schmuck, Gold U Silberschmiedwaren Herstellung von sonstigen Metallwaren",
    "sg:phone":"+41 56 222 64 45",
    "sg:postcode":"5400",
    "sg:province":"Aargau",
    "wof:name":"Walter G\u00fcller Gravierwerkst\u00e4tte",
    "wof:placetype":"venue"
},
  "geometry": {"coordinates":[8.3060483932,47.4656982422],"type":"Point"}
}