{
  "type": "Feature",
  "properties": {
    "iso:country":"CH",
    "sg:address":"Hauptstrasse 992b",
    "sg:city":"Goldswil",
    "sg:orig_category":"Autolackierereien Autospenglereien",
    "sg:phone":"+41 71 385 21 66",
    "sg:postcode":"3805",
    "sg:province":"Bern",
    "wof:name":"Daniel Bollhalder Carrosserie & Spritzwerk",
    "wof:placetype":"venue"
},
  "geometry": {"coordinates":[9.236809,47.417187],"type":"Point"}
}