{
  "type": "Feature",
  "properties": {
    "iso:country":"CH",
    "sg:address":"Via Dei Balconi",
    "sg:city":"Barbengo",
    "sg:orig_category":"Autogaragen Autospenglereien",
    "sg:postcode":"6917",
    "sg:province":"Ticino",
    "wof:name":"Gyga Car Sa",
    "wof:placetype":"venue"
},
  "geometry": {"coordinates":[8.925066,45.966976],"type":"Point"}
}