{
  "type": "Feature",
  "properties": {
    "iso:country":"CH",
    "sg:address":"Moulin De La Plaza 1a 1302 Vufflens-la-ville. Postfach",
    "sg:city":"Vufflens-la-ville",
    "sg:orig_category":"K\u00fcnstlerische U schriftstellerische T\u00e4tigkeiten U Darbietungen",
    "sg:postcode":"1302",
    "sg:province":"Vaud",
    "wof:name":"Besan\u00e7on J. Peinture Peinture Artistique",
    "wof:placetype":"venue"
},
  "geometry": {"coordinates":[6.5325350761,46.579208374],"type":"Point"}
}