{
  "type": "Feature",
  "properties": {
    "iso:country":"CH",
    "sg:address":"Hellstrasse 4",
    "sg:city":"Forch",
    "sg:orig_category":"Wirtschaftspr\u00fcfung, Steuerberatung U Treuhand",
    "sg:phone":"+41 19806885",
    "sg:postcode":"8127",
    "sg:province":"Z\u00fcrich",
    "wof:name":"G\u00f6ko Treuhand R. W. Goepfert",
    "wof:placetype":"venue"
},
  "geometry": {"coordinates":[8.6550750732,47.3287506104],"type":"Point"}
}