{
  "type": "Feature",
  "properties": {
    "iso:country":"CH",
    "sg:address":"Bahnhofstrasse 37",
    "sg:city":"Sursee",
    "sg:orig_category":"Kosmetikinstitute",
    "sg:phone":"+41 41 921 20 10",
    "sg:postcode":"6210",
    "sg:province":"Luzern",
    "wof:name":"Yvonne Greber Kosmetikinstitut Mimi",
    "wof:placetype":"venue"
},
  "geometry": {"coordinates":[8.1001195908,47.1715545654],"type":"Point"}
}