{
  "type": "Feature",
  "properties": {
    "iso:country":"CH",
    "sg:address":"Tournettes Route Des 7",
    "sg:city":"Veyrier",
    "sg:orig_category":"Sanit\u00e4r, Heizungs U L\u00fcftungsinstallation",
    "sg:postcode":"1255",
    "sg:province":"Gen\u00e8ve",
    "wof:name":"Vouilloz R. Installations Sanitaires S\u00e0rl",
    "wof:placetype":"venue"
},
  "geometry": {"coordinates":[6.1801261902,46.1622390747],"type":"Point"}
}