{
  "type": "Feature",
  "properties": {
    "iso:country":"CH",
    "sg:address":"Hauptstrasse 19",
    "sg:city":"Brunnenthal",
    "sg:classifiers":[
        {
            "category":"Restaurant",
            "type":"Food & Drink"
        }
    ],
    "sg:phone":"+41 31 765 52 25",
    "sg:postcode":"3307",
    "sg:province":"Solothurn",
    "wof:name":"Restaurant Dorfbeizli",
    "wof:placetype":"venue"
},
  "geometry": {"coordinates":[7.4649100304,47.0950088501],"type":"Point"}
}