{
  "type": "Feature",
  "properties": {
    "iso:country":"CH",
    "sg:address":"Aescherstrasse 22",
    "sg:city":"Fahrwangen",
    "sg:orig_category":"Grosshandel mit sonstigen Maschinen U Ausr\u00fcstungen f\u00fcr Industrie, Handel U Schiffahrt",
    "sg:phone":"+41 56 667 05 20",
    "sg:postcode":"5615",
    "sg:province":"Aargau",
    "wof:name":"Leonetti Reinigungssysteme",
    "wof:placetype":"venue"
},
  "geometry": {"coordinates":[8.239572525,47.2935600281],"type":"Point"}
}