{
  "type": "Feature",
  "properties": {
    "iso:country":"CH",
    "sg:address":"Gerlisbrunnenstrasse 29",
    "sg:city":"Benglen",
    "sg:orig_category":"Handelsvermittlung U Grosshandel Sonstiger Grosshandel",
    "sg:phone":"+41 18255656",
    "sg:postcode":"8121",
    "sg:province":"Z\u00fcrich",
    "wof:name":"Pfenninger & Partner",
    "wof:placetype":"venue"
},
  "geometry": {"coordinates":[8.6328859329,47.3586120605],"type":"Point"}
}