{
  "type": "Feature",
  "properties": {
    "iso:country":"CH",
    "sg:address":"Obergasse 14",
    "sg:city":"Biel/bienne",
    "sg:orig_category":"Detailhandel mit Getr\u00e4nken Grosshandel mit Getr\u00e4nken",
    "sg:phone":"+41 32 325 20 30",
    "sg:postcode":"2502",
    "sg:province":"Bern",
    "wof:name":"Altstadt-kellerei Biel",
    "wof:placetype":"venue"
},
  "geometry": {"coordinates":[7.2467617989,47.1422843933],"type":"Point"}
}