{
  "type": "Feature",
  "properties": {
    "iso:country":"CH",
    "sg:address":"Rigistrasse 5 5634 Merenschwand. Postfach 39",
    "sg:city":"Merenschwand",
    "sg:orig_category":"Herstellung von sonstigen Maschinen f\u00fcr unspezifische Verwendung Mechanische Werkst\u00e4tten",
    "sg:phone":"+41 26 674 25 20",
    "sg:postcode":"5634",
    "sg:province":"Aargau",
    "wof:name":"Pmc Pr\u00e4zisions Mechanik Cressier Ag",
    "wof:placetype":"venue"
},
  "geometry": {"coordinates":[7.149023056,46.9037857056],"type":"Point"}
}