{
  "type": "Feature",
  "properties": {
    "iso:country":"CH",
    "sg:address":"Oberdorfstrasse 25",
    "sg:city":"Konolfingen",
    "sg:orig_category":"Detailhandel mit Schuhen Detailhandel mit Sportartikeln",
    "sg:phone":"+41 31 791 05 66",
    "sg:postcode":"3510",
    "sg:province":"Bern",
    "wof:name":"Hansruedi Berger Schuhe & Sport",
    "wof:placetype":"venue"
},
  "geometry": {"coordinates":[7.6290669441,46.8891372681],"type":"Point"}
}