{
  "type": "Feature",
  "properties": {
    "iso:country":"CH",
    "sg:address":"8245",
    "sg:city":"Feuerthalen",
    "sg:orig_category":"Schulpflegen",
    "sg:phone":"+41 52 647 45 06",
    "sg:postcode":"8245",
    "sg:province":"Z\u00fcrich",
    "wof:name":"Schulpflege Der Gemeinde Feuerthalen",
    "wof:placetype":"venue"
},
  "geometry": {"coordinates":[8.6455898285,47.6896018982],"type":"Point"}
}