{
  "type": "Feature",
  "properties": {
    "iso:country":"CH",
    "sg:address":"Poststrasse 14 5018 Erlinsbach. Postfach",
    "sg:city":"Erlinsbach",
    "sg:orig_category":"Unternehmensberatung",
    "sg:phone":"+41 79 455 48 18",
    "sg:postcode":"5018",
    "sg:province":"Solothurn",
    "wof:name":"Real-projects Gmbh",
    "wof:placetype":"venue"
},
  "geometry": {"coordinates":[8.008559227,47.4039726257],"type":"Point"}
}