{
  "type": "Feature",
  "properties": {
    "iso:country":"CH",
    "sg:address":"Zumhofhalde 70",
    "sg:city":"Kriens",
    "sg:orig_category":"Non-Classified Establishments",
    "sg:phone":"+41 61 641 25 25",
    "sg:postcode":"6010",
    "sg:province":"Luzern",
    "wof:name":"Gemeindespital Riehen",
    "wof:placetype":"venue"
},
  "geometry": {"coordinates":[7.6543951035,47.5849456787],"type":"Point"}
}