{
  "type": "Feature",
  "properties": {
    "iso:country":"CH",
    "sg:address":"Avenue De La Gare 31",
    "sg:city":"Lausanne",
    "sg:classifiers":[
        {
            "category":"Travel",
            "subcategory":"Hotels & Motels",
            "type":"Entertainment"
        }
    ],
    "sg:phone":"+41 21 341 42 43",
    "sg:postcode":"1003",
    "sg:province":"Vaud",
    "sg:tags":[
        "hotels",
        "mit",
        "restaurant"
    ],
    "wof:name":"H\u00f4tel Mirabeau Sa",
    "wof:placetype":"venue"
},
  "geometry": {"coordinates":[6.6355781555,46.5168190002],"type":"Point"}
}