{
  "type": "Feature",
  "properties": {
    "iso:country":"CH",
    "sg:address":"Technoramastrasse 10",
    "sg:city":"Winterthur",
    "sg:classifiers":[
        {
            "category":"Structure",
            "subcategory":"Bridge",
            "type":"Public Place"
        }
    ],
    "sg:phone":"+41 52 244 33 33",
    "sg:postcode":"8404",
    "sg:province":"Z\u00fcrich",
    "sg:tags":[
        "construction"
    ],
    "wof:name":"H\u00fcppi Ag",
    "wof:placetype":"venue"
},
  "geometry": {"coordinates":[8.762756,47.512043],"type":"Point"}
}