{
  "type": "Feature",
  "properties": {
    "iso:country":"CH",
    "sg:address":"B. Bahnhof Gampel.",
    "sg:city":"Turtmann",
    "sg:orig_category":"RESTAURANTS: TEA-ROOMS",
    "sg:postcode":"3946",
    "sg:province":"Valais",
    "wof:name":"Bahnhofbuffet L\u00fctholf Hans.",
    "wof:placetype":"venue"
},
  "geometry": {"coordinates":[7.7031202316,46.3017997742],"type":"Point"}
}