{
  "type": "Feature",
  "properties": {
    "iso:country":"CH",
    "sg:address":"Voltastrasse 88",
    "sg:city":"Basel",
    "sg:orig_category":"Sonstige Kultur U Unterhaltungseinrichtungen",
    "sg:postcode":"4056",
    "sg:province":"Basel-Stadt",
    "wof:name":"Billard-center Meilan",
    "wof:placetype":"venue"
},
  "geometry": {"coordinates":[7.5764408112,47.5709991455],"type":"Point"}
}