{
  "type": "Feature",
  "properties": {
    "iso:country":"CH",
    "sg:address":"Talackerhalde 11",
    "sg:city":"Kriens",
    "sg:orig_category":"Grosshandel mit Maschinen U Ausr\u00fcstungen",
    "sg:phone":"+41 41 310 52 07",
    "sg:postcode":"6010",
    "sg:province":"Luzern",
    "wof:name":"Technoclean Ag Reinigungstechnik",
    "wof:placetype":"venue"
},
  "geometry": {"coordinates":[8.2830495834,47.0292510986],"type":"Point"}
}