{
  "type": "Feature",
  "properties": {
    "iso:country":"CH",
    "sg:address":"Pappelweg 21 3013 Bern. Postfach",
    "sg:city":"Bern",
    "sg:orig_category":"Satzherstellung U Reproduktion",
    "sg:postcode":"3013",
    "sg:province":"Bern",
    "wof:name":"Satz-atelier Heinz Wegm\u00fcller Hewesa",
    "wof:placetype":"venue"
},
  "geometry": {"coordinates":[7.4482479095,46.9585151672],"type":"Point"}
}