{
  "type": "Feature",
  "properties": {
    "iso:country":"CH",
    "sg:address":"Route Industrielle 1",
    "sg:city":"Avenches",
    "sg:classifiers":[
        {
            "category":"Military Area",
            "subcategory":"Air Force Base",
            "type":"Public Place"
        }
    ],
    "sg:phone":"+41 26 676 96 96",
    "sg:postcode":"1580",
    "sg:province":"Vaud",
    "sg:tags":[
        "chemical",
        "paint",
        "product",
        "lacquer",
        "industry"
    ],
    "wof:name":"Schweizerhall Chimie Sa",
    "wof:placetype":"venue"
},
  "geometry": {"coordinates":[7.049551,46.889099],"type":"Point"}
}