{
  "type": "Feature",
  "properties": {
    "iso:country":"CH",
    "sg:address":"1630",
    "sg:city":"Bulle",
    "sg:orig_category":"Sonstiger Grosshandel",
    "sg:postcode":"1630",
    "sg:province":"Fribourg",
    "wof:name":"D\u00f6rpinghaus Kurt",
    "wof:placetype":"venue"
},
  "geometry": {"coordinates":[7.0232000351,46.6070785522],"type":"Point"}
}