{
  "type": "Feature",
  "properties": {
    "iso:country":"CH",
    "sg:address":"Bahnhofstrasse 5",
    "sg:city":"K\u00fcblis",
    "sg:orig_category":"Verkehrs- and Tourismusb\u00fcros",
    "sg:phone":"+41 81 332 22 79",
    "sg:postcode":"7240",
    "sg:province":"Graubunden",
    "wof:name":"Verkehrsverein",
    "wof:placetype":"venue"
},
  "geometry": {"coordinates":[9.7712211609,46.9141311646],"type":"Point"}
}