{
  "type": "Feature",
  "properties": {
    "iso:country":"CH",
    "sg:address":"Duftbach",
    "sg:city":"Leissigen",
    "sg:orig_category":"Haltung von Rindern",
    "sg:postcode":"3706",
    "sg:province":"Bern",
    "wof:name":"Simmenthaler-fleckviehzucht-genossenschaft",
    "wof:placetype":"venue"
},
  "geometry": {"coordinates":[7.7740898132,46.6546554565],"type":"Point"}
}