{
  "type": "Feature",
  "properties": {
    "iso:country":"CH",
    "sg:address":"Avenue De Beaulieu 2",
    "sg:city":"St-maurice",
    "sg:orig_category":"Detailhandel mit Getr\u00e4nken",
    "sg:phone":"+41 24 485 10 38",
    "sg:postcode":"1890",
    "sg:province":"Valais",
    "wof:name":"Casimir Gex Vins Eaux",
    "wof:placetype":"venue"
},
  "geometry": {"coordinates":[7.0042390823,46.2126922607],"type":"Point"}
}