{
  "type": "Feature",
  "properties": {
    "addr:full":"In Der Deisten 15 8125 Zollikerberg. Postfach Zollikerberg Z\u00fcrich 8125",
    "addr:housenumber":"15",
    "addr:postcode":"8125 zollikerberg. postfach;8125",
    "addr:street":"In Der Deisten",
    "iso:country":"CH",
    "sg:address":"In Der Deisten 15 8125 Zollikerberg. Postfach",
    "sg:city":"Zollikerberg",
    "sg:orig_category":"Architektur U Ingenieurb\u00fcros",
    "sg:phone":"+41 13902876",
    "sg:postcode":"8125",
    "sg:province":"Z\u00fcrich",
    "wof:name":"Csbi Unholz Matthis Beratung Und Management Im Bereich Technischer Dienste",
    "wof:placetype":"venue"
},
  "geometry": {"coordinates":[8.604496,47.347267],"type":"Point"}
}