{
  "type": "Feature",
  "properties": {
    "iso:country":"CH",
    "sg:address":"Landquartstrasse 92",
    "sg:city":"Arbon",
    "sg:classifiers":[
        {
            "category":"Retail",
            "subcategory":"Repair Shop",
            "type":"Services"
        }
    ],
    "sg:phone":"+41 71 446 52 22",
    "sg:postcode":"9320",
    "sg:province":"Thurgau",
    "sg:tags":[
        "hardening"
    ],
    "wof:name":"H\u00e4rterei Arbon Ag Aka",
    "wof:placetype":"venue"
},
  "geometry": {"coordinates":[9.422917366,47.4993095398],"type":"Point"}
}