{
  "type": "Feature",
  "properties": {
    "iso:country":"CH",
    "sg:address":"Kastanienbaumstrasse 301",
    "sg:city":"Kastanienbaum",
    "sg:orig_category":"Nationale Postdienste",
    "sg:phone":"+41 56 634 11 70",
    "sg:postcode":"6047",
    "sg:province":"Luzern",
    "wof:name":"Die Schweizerische Post",
    "wof:placetype":"venue"
},
  "geometry": {"coordinates":[8.4385242462,47.3228569031],"type":"Point"}
}