{
  "type": "Feature",
  "properties": {
    "iso:country":"CH",
    "sg:address":"Klinglerstrasse",
    "sg:city":"Ermatingen",
    "sg:orig_category":"Grosshandel mit Eisenwaren sowie Installationsbedarf f\u00fcr Gas, Wasser U Heizung Herstellung von Metal",
    "sg:phone":"+41 71 664 33 44",
    "sg:postcode":"8272",
    "sg:province":"Thurgau",
    "wof:name":"Brunitec Sa",
    "wof:placetype":"venue"
},
  "geometry": {"coordinates":[9.0927705765,47.6643867493],"type":"Point"}
}