{
  "type": "Feature",
  "properties": {
    "iso:country":"CH",
    "sg:address":"Schweizerhofstrasse 3",
    "sg:city":"Glarus",
    "sg:orig_category":"Zahnarztpraxen",
    "sg:postcode":"8750",
    "sg:province":"Glarus",
    "wof:name":"Genossenschaft Schulzahnklinik Des Kantons Glarus",
    "wof:placetype":"venue"
},
  "geometry": {"coordinates":[9.0706586838,47.0401420593],"type":"Point"}
}