{
  "type": "Feature",
  "properties": {
    "iso:country":"CH",
    "sg:address":"Hohenemserstrasse 37",
    "sg:city":"Diepoldsau",
    "sg:orig_category":"Non-Classified Establishments",
    "sg:phone":"+41 71 733 16 82",
    "sg:postcode":"9444",
    "sg:province":"St. Gallen",
    "wof:name":"Hutter Natursteine Ag",
    "wof:placetype":"venue"
},
  "geometry": {"coordinates":[9.6621084213,47.3821983337],"type":"Point"}
}