{
  "type": "Feature",
  "properties": {
    "iso:country":"CH",
    "sg:address":"Gibelinstrasse 25",
    "sg:city":"Solothurn",
    "sg:orig_category":"Herstellung von Besen U B\u00fcrsten",
    "sg:postcode":"4500",
    "sg:province":"Solothurn",
    "wof:name":"Zaugg A.",
    "wof:placetype":"venue"
},
  "geometry": {"coordinates":[5.1808700562,45.8973388672],"type":"Point"}
}