{
  "type": "Feature",
  "properties": {
    "iso:country":"CH",
    "sg:address":"6537",
    "sg:city":"Grono",
    "sg:orig_category":"Wohnheime",
    "sg:phone":"+41 91 820 34 00",
    "sg:postcode":"6537",
    "sg:province":"Graubunden",
    "wof:name":"Casa Di Cura Opera Mater Christi",
    "wof:placetype":"venue"
},
  "geometry": {"coordinates":[9.1464338303,46.2478141785],"type":"Point"}
}