{
  "type": "Feature",
  "properties": {
    "iso:country":"CH",
    "sg:address":"Karpfenstrasse 8a",
    "sg:city":"Oberrieden",
    "sg:orig_category":"Reinigungsgewerbe",
    "sg:postcode":"8942",
    "sg:province":"Z\u00fcrich",
    "wof:name":"Lentech E. Lendenmann",
    "wof:placetype":"venue"
},
  "geometry": {"coordinates":[8.5792818069,47.2807579041],"type":"Point"}
}