{
  "type": "Feature",
  "properties": {
    "iso:country":"CH",
    "sg:address":"Avenue De La Gare 2",
    "sg:city":"Neuch\u00e2tel",
    "sg:orig_category":"Gymnastikschulen",
    "sg:phone":"+41 61 711 21 71",
    "sg:postcode":"2000",
    "sg:province":"Neuch\u00e2tel",
    "wof:name":"Lina Nichele Gymnastik",
    "wof:placetype":"venue"
},
  "geometry": {"coordinates":[7.5990362167,47.5110168457],"type":"Point"}
}