{
  "type": "Feature",
  "properties": {
    "iso:country":"CH",
    "sg:address":"Altgasse 1",
    "sg:city":"Jegenstorf",
    "sg:orig_category":"Vereine Damen Vereine Gesang",
    "sg:phone":"+41 61 721 26 39",
    "sg:postcode":"3303",
    "sg:province":"Bern",
    "wof:name":"Frauenchor",
    "wof:placetype":"venue"
},
  "geometry": {"coordinates":[7.5247178078,47.5038948059],"type":"Point"}
}