{
  "type": "Feature",
  "properties": {
    "iso:country":"CH",
    "sg:address":"Uraniastrasse 40 8001 Z\u00fcrich. Postfach",
    "sg:city":"Z\u00fcrich",
    "sg:orig_category":"Grosshandel mit festen Brennstoffen U Mineral\u00f6lerzeugnissen Mineral\u00f6lverarbeitung",
    "sg:phone":"+41 71 455 18 45",
    "sg:postcode":"8021",
    "sg:province":"Z\u00fcrich",
    "wof:name":"Forster Handels Ag",
    "wof:placetype":"venue"
},
  "geometry": {"coordinates":[9.4000177383,47.4882659912],"type":"Point"}
}