{
  "type": "Feature",
  "properties": {
    "iso:country":"CH",
    "sg:address":"Joos\u00e4ckerstrasse 12 8957 Spreitenbach. Postfach",
    "sg:city":"Spreitenbach",
    "sg:orig_category":"Non-Classified Establishments",
    "sg:postcode":"8957",
    "sg:province":"Aargau",
    "wof:name":"Scorproduction Gmbh Film, Videoproduktionen Usw",
    "wof:placetype":"venue"
},
  "geometry": {"coordinates":[8.3832130432,47.4145355225],"type":"Point"}
}