{
  "type": "Feature",
  "properties": {
    "iso:country":"CH",
    "sg:address":"Impasse Du Triolet 2",
    "sg:city":"Ecuvillens",
    "sg:orig_category":"Siebdruck",
    "sg:phone":"+41 26 411 27 04",
    "sg:postcode":"1730",
    "sg:province":"Fribourg",
    "wof:name":"J Design Cr\u00e9ation Graphique",
    "wof:placetype":"venue"
},
  "geometry": {"coordinates":[7.0892109871,46.7579231262],"type":"Point"}
}