{
  "type": "Feature",
  "properties": {
    "iso:country":"CH",
    "sg:address":"Sterneng\u00e4ssi 6",
    "sg:city":"Leukerbad",
    "sg:classifiers":[
        {
            "category":"Restaurant",
            "type":"Food & Drink"
        }
    ],
    "sg:phone":"+41 27 470 11 20",
    "sg:postcode":"3954",
    "sg:province":"Valais",
    "wof:name":"Restaurant Sternen",
    "wof:placetype":"venue"
},
  "geometry": {"coordinates":[7.6298308372,46.3788528442],"type":"Point"}
}