{
  "type": "Feature",
  "properties": {
    "iso:country":"CH",
    "sg:address":"Poststrasse 14",
    "sg:city":"Uster",
    "sg:orig_category":"Warenh\u00e4user",
    "sg:phone":"+41 32 723 89 89",
    "sg:postcode":"8610",
    "sg:province":"Z\u00fcrich",
    "wof:name":"Globus Grands Magasin",
    "wof:placetype":"venue"
},
  "geometry": {"coordinates":[6.9295368195,46.9913711548],"type":"Point"}
}