{
  "type": "Feature",
  "properties": {
    "iso:country":"CH",
    "sg:address":"Hornbachstrasse 50",
    "sg:city":"Z\u00fcrich",
    "sg:orig_category":"Non-Classified Establishments",
    "sg:phone":"+41 13815918",
    "sg:postcode":"8008",
    "sg:province":"Z\u00fcrich",
    "wof:name":"W\u00e4chli Sven, Internet + Multimedia",
    "wof:placetype":"venue"
},
  "geometry": {"coordinates":[8.5551967621,47.3554000854],"type":"Point"}
}