{
  "type": "Feature",
  "properties": {
    "iso:country":"CH",
    "sg:address":"Avenue Des Coll\u00e8ges 48",
    "sg:city":"Pully",
    "sg:orig_category":"Werbeagenturen Werbegrafikateliers",
    "sg:phone":"+41 21 728 22 19",
    "sg:postcode":"1009",
    "sg:province":"Vaud",
    "wof:name":"Jean Poffet Publicit\u00e9 & Arts Graphiques",
    "wof:placetype":"venue"
},
  "geometry": {"coordinates":[6.6518859863,46.5106658936],"type":"Point"}
}