{
  "type": "Feature",
  "properties": {
    "iso:country":"CH",
    "sg:address":"Marktgasse 36",
    "sg:city":"Bern",
    "sg:orig_category":"Wirtschafts- and Arbeitgeberverb\u00e4nde",
    "sg:phone":"+41 31 318 10 60",
    "sg:postcode":"3011",
    "sg:province":"Bern",
    "wof:name":"Bund Schweiz.frauenorganisat.",
    "wof:placetype":"venue"
},
  "geometry": {"coordinates":[7.4453468323,46.9480552673],"type":"Point"}
}