{
  "type": "Feature",
  "properties": {
    "iso:country":"CH",
    "sg:address":"Rue Centrale 15",
    "sg:city":"Corsier-sur-vevey",
    "sg:orig_category":"Non-Classified Establishments",
    "sg:postcode":"1804",
    "sg:province":"Vaud",
    "wof:name":"Gavillet Sa Pompes Fun\u00e8bres",
    "wof:placetype":"venue"
},
  "geometry": {"coordinates":[6.8427801132,46.4707832336],"type":"Point"}
}