{
  "type": "Feature",
  "properties": {
    "addr:full":"Place De La Gare 5 Coppet Vaud 1296",
    "addr:housenumber":"5",
    "addr:postcode":"1296",
    "addr:street":"Place De La Gare",
    "iso:country":"CH",
    "sg:address":"Place De La Gare 5",
    "sg:city":"Coppet",
    "sg:orig_category":"Position Controls",
    "sg:phone":"+41 22 776 36 24",
    "sg:postcode":"1296",
    "sg:province":"Vaud",
    "wof:name":"Infranor S.a.",
    "wof:placetype":"venue"
},
  "geometry": {"coordinates":[6.187568,46.316723],"type":"Point"}
}