{
  "type": "Feature",
  "properties": {
    "iso:country":"CH",
    "sg:address":"6914",
    "sg:city":"Carona",
    "sg:classifiers":[
        {
            "category":"Travel",
            "subcategory":"Hotels & Motels",
            "type":"Entertainment"
        }
    ],
    "sg:phone":"+41 91 606 58 71",
    "sg:postcode":"6914",
    "sg:province":"Ticino",
    "sg:tags":[
        "hotels",
        "mit",
        "restaurant"
    ],
    "wof:name":"Albergo Villa Elena",
    "wof:placetype":"venue"
},
  "geometry": {"coordinates":[8.8631696701,45.9705963135],"type":"Point"}
}