{
  "type": "Feature",
  "properties": {
    "iso:country":"CH",
    "sg:address":"Alpenstrasse 86",
    "sg:city":"Schaffhausen",
    "sg:orig_category":"Grosshandel mit sonstigen Maschinen U Ausr\u00fcstungen f\u00fcr Industrie, Handel U Schiffahrt",
    "sg:phone":"+41 52 624 06 62",
    "sg:postcode":"8200",
    "sg:province":"Schaffhausen",
    "wof:name":"Heral Gmbh",
    "wof:placetype":"venue"
},
  "geometry": {"coordinates":[8.6503362656,47.6987419128],"type":"Point"}
}