{
  "type": "Feature",
  "properties": {
    "iso:country":"CH",
    "sg:address":"Hauptstrasse 22",
    "sg:city":"Heinrichswil",
    "sg:orig_category":"Grosshandel mit Getr\u00e4nken",
    "sg:postcode":"4558",
    "sg:province":"Solothurn",
    "wof:name":"F\u00fcrst Weinhandlung",
    "wof:placetype":"venue"
},
  "geometry": {"coordinates":[7.6360301971,47.1568374634],"type":"Point"}
}