{
  "type": "Feature",
  "properties": {
    "iso:country":"CH",
    "sg:address":"Unterdorfstrasse 24",
    "sg:city":"Stettfurt",
    "sg:orig_category":"Bauspenglerei Zimmerei, Dachdeckerei, Bauspenglerei U Abdichtung",
    "sg:phone":"+41 52 376 15 55",
    "sg:postcode":"9507",
    "sg:province":"Thurgau",
    "wof:name":"Kaufmann F. Ag",
    "wof:placetype":"venue"
},
  "geometry": {"coordinates":[8.955468,47.522179],"type":"Point"}
}