{
  "type": "Feature",
  "properties": {
    "iso:country":"CH",
    "sg:address":"1964",
    "sg:city":"Conthey",
    "sg:orig_category":"Pensionskassen",
    "sg:phone":"+41 27 345 46 40",
    "sg:postcode":"1964",
    "sg:province":"Valais",
    "wof:name":"Fondation De Pr\u00e9voyance En Faveur Du Personnel De Quennoz Sa Et Des Soci\u00e9t\u00e9s Affili\u00e9es.",
    "wof:placetype":"venue"
},
  "geometry": {"coordinates":[7.302670002,46.2224006653],"type":"Point"}
}