{
  "type": "Feature",
  "properties": {
    "iso:country":"CH",
    "sg:address":"Hinterbergweg 8 5018 Erlinsbach. Postfach",
    "sg:city":"Erlinsbach",
    "sg:orig_category":"G\u00fcterbef\u00f6rderung im Strassenverkehr",
    "sg:postcode":"5018",
    "sg:province":"Solothurn",
    "wof:name":"B\u00fcrgi Dieter Transporte",
    "wof:placetype":"venue"
},
  "geometry": {"coordinates":[8.0135097504,47.3985137939],"type":"Point"}
}