{
  "type": "Feature",
  "properties": {
    "iso:country":"CH",
    "sg:address":"Grotte Rue De La 6 1003 Lausanne Case Postale",
    "sg:city":"Lausanne",
    "sg:orig_category":"Pensionskassen",
    "sg:postcode":"1003",
    "sg:province":"Vaud",
    "wof:name":"Fonds De Secours Et De Pr\u00e9voyance De L'entreprise Egger Emile & Cie Sa",
    "wof:placetype":"venue"
},
  "geometry": {"coordinates":[7.0333590508,47.0478248596],"type":"Point"}
}