{
  "type": "Feature",
  "properties": {
    "iso:country":"CH",
    "sg:address":"K\u00e4ferholzstrasse 250 8046 Z\u00fcrich. Postfach 174",
    "sg:city":"Z\u00fcrich",
    "sg:orig_category":"Unternehmensberatung Wirtschaftspr\u00fcfung, Steuerberatung U Treuhand",
    "sg:phone":"+41 13717403",
    "sg:postcode":"8056",
    "wof:name":"Thosmi S\u00e0rl",
    "wof:placetype":"venue"
},
  "geometry": {"coordinates":[8.5242853165,47.4105033875],"type":"Point"}
}