{
  "type": "Feature",
  "properties": {
    "iso:country":"CH",
    "sg:address":"Chemin De La Combette 5",
    "sg:city":"Vessy",
    "sg:orig_category":"Detailhandel mit Brot, Back U S\u00fcsswaren",
    "sg:phone":"+41 32 968 36 06",
    "sg:postcode":"1234",
    "sg:province":"Gen\u00e8ve",
    "wof:name":"Albert Roth Boulangerie",
    "wof:placetype":"venue"
},
  "geometry": {"coordinates":[6.834913,47.100449],"type":"Point"}
}