{
  "type": "Feature",
  "properties": {
    "iso:country":"CH",
    "sg:address":"Rue Du Pr\u00e9 Bernard 6",
    "sg:city":"Tavannes",
    "sg:orig_category":"Wirtschaftspr\u00fcfung, Steuerberatung U Treuhand",
    "sg:phone":"+41 71 351 55 93",
    "sg:postcode":"2710",
    "sg:province":"Bern",
    "wof:name":"Corolla Sa",
    "wof:placetype":"venue"
},
  "geometry": {"coordinates":[9.128364563,46.2376060486],"type":"Point"}
}