{
  "type": "Feature",
  "properties": {
    "iso:country":"CH",
    "sg:address":"Wiesentlastrasse Buriet",
    "sg:city":"Thal",
    "sg:orig_category":"Sonstiger Grosshandel",
    "sg:postcode":"9425",
    "sg:province":"St. Gallen",
    "wof:name":"Rankhandel, Haller Hans",
    "wof:placetype":"venue"
},
  "geometry": {"coordinates":[9.5773801804,47.4785842896],"type":"Point"}
}