{
  "type": "Feature",
  "properties": {
    "iso:country":"CH",
    "sg:address":"Gaswerkstrasse 66 D 4900 Langenthal. Postfach",
    "sg:city":"Langenthal",
    "sg:orig_category":"Herstellung von Konstruktionsteilen, Fertigbauteilen U Ausbauelementen aus Holz",
    "sg:postcode":"4900",
    "sg:province":"Bern",
    "wof:name":"Nicollier Philippe",
    "wof:placetype":"venue"
},
  "geometry": {"coordinates":[2.2539389133,49.8641166687],"type":"Point"}
}