{
  "type": "Feature",
  "properties": {
    "iso:country":"CH",
    "sg:address":"Egg",
    "sg:city":"Schwenden",
    "sg:orig_category":"Personenbef\u00f6rderung im Linienverkehr zu Land Regelm\u00e4ssige Personenbef\u00f6rderung im Fernverkehr",
    "sg:phone":"+41 71 912 47 47",
    "sg:postcode":"3757",
    "sg:province":"Bern",
    "wof:name":"Bus-halter Ag",
    "wof:placetype":"venue"
},
  "geometry": {"coordinates":[9.0444898605,47.4605293274],"type":"Point"}
}