{
  "type": "Feature",
  "properties": {
    "iso:country":"CH",
    "sg:address":"Iseliguet 2 8750 Glarus. Postfach",
    "sg:city":"Bilten",
    "sg:orig_category":"Grosshandel mit Nahrungsmitteln, Getr\u00e4nken U Tabakwaren ohne ausgepr\u00e4gten Schwerpunkt",
    "sg:phone":"+41 33 849 14 49",
    "sg:postcode":"8865",
    "sg:province":"Glarus",
    "wof:name":"Lebensmittelgesch\u00e4ft Amacher Erna",
    "wof:placetype":"venue"
},
  "geometry": {"coordinates":[7.9288029671,46.7170982361],"type":"Point"}
}