{
  "type": "Feature",
  "properties": {
    "iso:country":"CH",
    "sg:address":"Dietfurt 9606 B\u00fctschwil. Postfach",
    "sg:city":"Dietfurt",
    "sg:orig_category":"RESTAURANTS: TEA-ROOMS",
    "sg:postcode":"9615",
    "sg:province":"St. Gallen",
    "wof:name":"Restaurant Krone Braun H.",
    "wof:placetype":"venue"
},
  "geometry": {"coordinates":[9.0641145706,47.3373413086],"type":"Point"}
}