{
  "type": "Feature",
  "properties": {
    "iso:country":"CH",
    "sg:address":"Sch\u00fctzenwisstrasse 1",
    "sg:city":"Maur",
    "sg:orig_category":"Herstellung von keramischen Wand U Bodenfliesen U platten",
    "sg:phone":"+41 19803858",
    "sg:postcode":"8124",
    "sg:province":"Z\u00fcrich",
    "wof:name":"Jud Alex & Robert Ag",
    "wof:placetype":"venue"
},
  "geometry": {"coordinates":[8.6681137085,47.3401985168],"type":"Point"}
}