{
  "type": "Feature",
  "properties": {
    "iso:country":"CH",
    "sg:address":"General-dufour-strasse 4 2500 Biel/bienne. Postfach",
    "sg:city":"Biel/bienne",
    "sg:orig_category":"Fachdetailhandel mit pharmazeutischen Produkten",
    "sg:postcode":"2502",
    "sg:province":"Bern",
    "wof:name":"Geno-apotheken Biel",
    "wof:placetype":"venue"
},
  "geometry": {"coordinates":[7.2464981079,47.1391716003],"type":"Point"}
}