{
  "type": "Feature",
  "properties": {
    "iso:country":"CH",
    "sg:address":"Zimmertalstrasse 1",
    "sg:city":"Sarnen",
    "sg:orig_category":"Sonstige Aktivit\u00e4ten der nicht-\u00e4rztlichen Medizinalberufe",
    "sg:phone":"+41 17153111",
    "sg:postcode":"6060",
    "sg:province":"Obwalden",
    "wof:name":"Susanna Kimmich Atemtherapie",
    "wof:placetype":"venue"
},
  "geometry": {"coordinates":[8.5406780243,47.3184318542],"type":"Point"}
}