{
  "type": "Feature",
  "properties": {
    "iso:country":"CH",
    "sg:address":"Jungstrasse 12",
    "sg:city":"Basel",
    "sg:orig_category":"Detailhandel mit M\u00f6beln U Haushaltsgegenst\u00e4nden",
    "sg:postcode":"4056",
    "sg:province":"Basel-Stadt",
    "wof:name":"Controverso Eulilli Gilberto",
    "wof:placetype":"venue"
},
  "geometry": {"coordinates":[7.5795059204,47.5676651001],"type":"Point"}
}