{
  "type": "Feature",
  "properties": {
    "iso:country":"CH",
    "sg:address":"Fischerg\u00e4sschen 13",
    "sg:city":"Schaffhausen",
    "sg:orig_category":"Arztpraxen",
    "sg:phone":"+41 52 624 43 71",
    "sg:postcode":"8200",
    "sg:province":"Schaffhausen",
    "wof:name":"Dr.med.renate Sommerhalder Spezial\u00e4rztin",
    "wof:placetype":"venue"
},
  "geometry": {"coordinates":[8.639138,47.695492],"type":"Point"}
}