{
  "type": "Feature",
  "properties": {
    "iso:country":"CH",
    "sg:address":"Allens",
    "sg:city":"Cossonay-ville",
    "sg:orig_category":"Mahl U Sch\u00e4lm\u00fchlen S\u00e4gewerke",
    "sg:phone":"+41 26 918 51 77",
    "sg:postcode":"1304",
    "sg:province":"Vaud",
    "wof:name":"Charles Lambert Moulin & Scierie",
    "wof:placetype":"venue"
},
  "geometry": {"coordinates":[6.9270949364,46.5727844238],"type":"Point"}
}