{
  "type": "Feature",
  "properties": {
    "iso:country":"CH",
    "sg:address":"Boulevard De P\u00e9rolles 11",
    "sg:city":"Fribourg",
    "sg:orig_category":"Verwertung von Milch",
    "sg:phone":"+41 71 277 16 54",
    "sg:postcode":"1700",
    "sg:province":"Fribourg",
    "wof:name":"Frauenriege St.gallen-west",
    "wof:placetype":"venue"
},
  "geometry": {"coordinates":[9.3304977417,47.4043464661],"type":"Point"}
}