{
  "type": "Feature",
  "properties": {
    "iso:country":"CH",
    "sg:address":"Triebernstrasse",
    "sg:city":"Weissbad",
    "sg:classifiers":[
        {
            "category":"Banks & Credit Unions",
            "subcategory":"Bank",
            "type":"Services"
        }
    ],
    "sg:phone":"+41 4171881616",
    "sg:postcode":"9057",
    "sg:province":"Appenzell Innerhoden",
    "wof:name":"Appenzell-innerrhodische, Kantonalbank",
    "wof:placetype":"venue"
},
  "geometry": {"coordinates":[9.436173,47.309914],"type":"Point"}
}