{
  "type": "Feature",
  "properties": {
    "iso:country":"CH",
    "sg:address":"Industriestrasse 49",
    "sg:city":"Zug",
    "sg:orig_category":"Grosshandel mit chemischen Erzeugnissen",
    "sg:phone":"+41 52 672 62 22",
    "sg:postcode":"6300",
    "sg:province":"Zug",
    "wof:name":"Cleanit Ag",
    "wof:placetype":"venue"
},
  "geometry": {"coordinates":[8.6040248871,47.6752586365],"type":"Point"}
}