{
  "type": "Feature",
  "properties": {
    "iso:country":"CH",
    "sg:address":"Poststrasse 96",
    "sg:city":"Spreitenbach",
    "sg:orig_category":"Softwareentwicklung U beratung",
    "sg:phone":"+41 79 402 17 27",
    "sg:postcode":"8957",
    "sg:province":"Aargau",
    "wof:name":"Abex Software Ag",
    "wof:placetype":"venue"
},
  "geometry": {"coordinates":[8.3609247208,47.4241943359],"type":"Point"}
}