{
  "type": "Feature",
  "properties": {
    "iso:country":"CH",
    "sg:address":"Rutlenstrasse 31",
    "sg:city":"Oberegg",
    "sg:orig_category":"Grosshandel mit lebenden Tieren",
    "sg:phone":"+41 71 891 23 17",
    "sg:postcode":"9413",
    "sg:province":"Appenzell Innerhoden",
    "wof:name":"Martin Schmid K\u00e4lberhandel",
    "wof:placetype":"venue"
},
  "geometry": {"coordinates":[9.548948288,47.4252891541],"type":"Point"}
}