{
  "type": "Feature",
  "properties": {
    "iso:country":"CH",
    "sg:address":"Lindenstrasse 23",
    "sg:city":"Rheinfelden",
    "sg:orig_category":"Maurerarbeiten",
    "sg:phone":"+41 79 219 97 62",
    "sg:postcode":"4310",
    "sg:province":"Aargau",
    "wof:name":"Josef Rava Maurergesch\u00e4ft Chemin\u00e9ebau",
    "wof:placetype":"venue"
},
  "geometry": {"coordinates":[8.9413003922,47.2884101868],"type":"Point"}
}