{
  "type": "Feature",
  "properties": {
    "iso:country":"CH",
    "sg:address":"En Vallapraz.",
    "sg:city":"Aclens",
    "sg:orig_category":"Allgemeiner Hoch U Tiefbau",
    "sg:postcode":"1123",
    "sg:province":"Vaud",
    "wof:name":"Reymond Jean-louis.",
    "wof:placetype":"venue"
},
  "geometry": {"coordinates":[6.50843,46.567589],"type":"Point"}
}