{
  "type": "Feature",
  "properties": {
    "addr:full":"La Ch\u00e8vrerie Arzier 1264 St-cergue. Postfach St-cergue Vaud 1264",
    "addr:postcode":"1264;postfach st-cergue;1264",
    "addr:street":"Arzier",
    "iso:country":"CH",
    "sg:address":"La Ch\u00e8vrerie Arzier 1264 St-cergue. Postfach",
    "sg:city":"St-cergue",
    "sg:orig_category":"Datenverarbeitungsdienste Softwareentwicklung U beratung",
    "sg:phone":"+41 62 875 14 75",
    "sg:postcode":"1264",
    "sg:province":"Vaud",
    "wof:name":"Fischer Informatik",
    "wof:placetype":"venue"
},
  "geometry": {"coordinates":[8.151868,47.558918],"type":"Point"}
}