{
  "type": "Feature",
  "properties": {
    "iso:country":"CH",
    "sg:address":"G\u00fcttinger Strasse 4",
    "sg:city":"Altnau",
    "sg:orig_category":"Primarschulen",
    "sg:phone":"+41 71 695 12 08",
    "sg:postcode":"8595",
    "sg:province":"Thurgau",
    "wof:name":"Primarschule",
    "wof:placetype":"venue"
},
  "geometry": {"coordinates":[9.2584886551,47.6097984314],"type":"Point"}
}