{
  "type": "Feature",
  "properties": {
    "iso:country":"CH",
    "sg:address":"Langholzstrasse 26",
    "sg:city":"H\u00fcnenberg",
    "sg:orig_category":"Handelsvermittlung U Grosshandel Wirtschaftspr\u00fcfung, Steuerberatung U Treuhand",
    "sg:phone":"+41 41 785 62 85",
    "sg:postcode":"6331",
    "sg:province":"Zug",
    "wof:name":"Bucheli Partners Ag",
    "wof:placetype":"venue"
},
  "geometry": {"coordinates":[8.4422340393,47.1706390381],"type":"Point"}
}