{
  "type": "Feature",
  "properties": {
    "iso:country":"CH",
    "sg:address":"3534",
    "sg:city":"Signau",
    "sg:orig_category":"Landw. Genossenschaften Viehzucht",
    "sg:phone":"+41 34 497 14 65",
    "sg:postcode":"3534",
    "sg:province":"Bern",
    "wof:name":"Braunviehzuchtgenossenschaft",
    "wof:placetype":"venue"
},
  "geometry": {"coordinates":[7.7206711769,46.916934967],"type":"Point"}
}