{
  "type": "Feature",
  "properties": {
    "iso:country":"CH",
    "sg:address":"Neumattstrasse 23",
    "sg:city":"Thun",
    "sg:orig_category":"Allgemeiner Hoch U Tiefbau",
    "sg:postcode":"3600",
    "sg:province":"Bern",
    "wof:name":"Fidag Immobilien + Handels Ag",
    "wof:placetype":"venue"
},
  "geometry": {"coordinates":[7.626406,46.747623],"type":"Point"}
}