{
  "type": "Feature",
  "properties": {
    "iso:country":"CH",
    "sg:address":"Konradstrasse 71",
    "sg:city":"Z\u00fcrich",
    "sg:orig_category":"Artworks, Digital",
    "sg:phone":"+41 12788070",
    "sg:postcode":"8005",
    "sg:province":"Z\u00fcrich",
    "wof:name":"Colorscan Ag",
    "wof:placetype":"venue"
},
  "geometry": {"coordinates":[8.533462,47.381908],"type":"Point"}
}