{
  "type": "Feature",
  "properties": {
    "iso:country":"CH",
    "sg:address":"G\u00fcterstrasse 279",
    "sg:city":"Basel",
    "sg:orig_category":"Detailhandel Reparatur von Gebrauchsg\u00fctern Vermietung von Gebrauchsg\u00fctern",
    "sg:phone":"+41 61 331 33 24",
    "sg:postcode":"4053",
    "sg:province":"Basel-Stadt",
    "wof:name":"Homevideo El Flamenco",
    "wof:placetype":"venue"
},
  "geometry": {"coordinates":[7.5996828079,47.5414810181],"type":"Point"}
}