{
  "type": "Feature",
  "properties": {
    "iso:country":"CH",
    "sg:address":"Chemin De M\u00e8re-voie 103",
    "sg:city":"Plan-les-ouates",
    "sg:orig_category":"Zahntechnische Laboratorien",
    "sg:phone":"+41 22 794 45 44",
    "sg:postcode":"1228",
    "sg:province":"Gen\u00e8ve",
    "wof:name":"Max Seiler Laboratoire Dentaire",
    "wof:placetype":"venue"
},
  "geometry": {"coordinates":[6.1156888008,46.1692695618],"type":"Point"}
}