{
  "type": "Feature",
  "properties": {
    "iso:country":"CH",
    "sg:address":"Burgerholzstrasse 17",
    "sg:city":"Frauenfeld",
    "sg:orig_category":"Grosshandel mit Holz U Bauelementen aus Holz",
    "sg:phone":"+41 79 437 85 54",
    "sg:postcode":"8500",
    "sg:province":"Thurgau",
    "wof:name":"Hansj\u00f6rg Bosshard Holztechnik",
    "wof:placetype":"venue"
},
  "geometry": {"coordinates":[8.8851995468,47.559879303],"type":"Point"}
}