{
  "type": "Feature",
  "properties": {
    "iso:country":"CH",
    "sg:address":"Z\u00fcrichstrasse 23",
    "sg:city":"B\u00fctzberg",
    "sg:orig_category":"Handel mit Automobilen",
    "sg:phone":"+41 62 963 25 85",
    "sg:postcode":"4922",
    "sg:province":"Bern",
    "wof:name":"Top Auto Gmbh",
    "wof:placetype":"venue"
},
  "geometry": {"coordinates":[7.7535867691,47.2173042297],"type":"Point"}
}