{
  "type": "Feature",
  "properties": {
    "iso:country":"CH",
    "sg:address":"Via Rinaldo Simen 71",
    "sg:city":"Minusio",
    "sg:orig_category":"Wirtschaftspr\u00fcfung, Steuerberatung U Treuhand",
    "sg:phone":"+41 91 730 11 30",
    "sg:postcode":"6648",
    "sg:province":"Ticino",
    "wof:name":"Studio Contabile Rodoni & Mainetti Sagl",
    "wof:placetype":"venue"
},
  "geometry": {"coordinates":[8.8245763779,46.1773338318],"type":"Point"}
}