{
  "type": "Feature",
  "properties": {
    "iso:country":"CH",
    "sg:address":"6772 Rodi-fiesso. Postfach",
    "sg:city":"Rodi-fiesso",
    "sg:orig_category":"Unclassifiable Establishments",
    "sg:postcode":"6772",
    "sg:province":"Ticino",
    "wof:name":"Elmar Ag Heizung- Klima- Umwelttechnik",
    "wof:placetype":"venue"
},
  "geometry": {"coordinates":[7.8201341629,47.248374939],"type":"Point"}
}