{
  "type": "Feature",
  "properties": {
    "iso:country":"CH",
    "sg:address":"M\u00fchlackerstrasse 13/2",
    "sg:city":"Frenkendorf",
    "sg:orig_category":"Zahnarztpraxen",
    "sg:phone":"+41 61 901 15 50",
    "sg:postcode":"4402",
    "sg:province":"Basel-Landschaft",
    "wof:name":"Dr. Med. Dent. Urs Hersberger Zahnarzt",
    "wof:placetype":"venue"
},
  "geometry": {"coordinates":[7.7183351517,47.5003471375],"type":"Point"}
}