{
  "type": "Feature",
  "properties": {
    "addr:full":"Margencel Rue 14 Aigle Vaud 1860",
    "addr:housenumber":"margencel;14",
    "addr:postcode":"1860",
    "addr:street":"Rue",
    "iso:country":"CH",
    "sg:address":"Margencel Rue 14",
    "sg:city":"Aigle",
    "sg:orig_category":"Beherbergungsgewerbe",
    "sg:postcode":"1860",
    "sg:province":"Vaud",
    "wof:name":"Jeunesse An 2000 Sa",
    "wof:placetype":"venue"
},
  "geometry": {"coordinates":[6.965492,46.317627],"type":"Point"}
}