{
  "type": "Feature",
  "properties": {
    "iso:country":"CH",
    "sg:address":"B\u00fcrenweg 20",
    "sg:city":"Gempen",
    "sg:orig_category":"Massagestudios",
    "sg:phone":"+41 61 701 95 30",
    "sg:postcode":"4145",
    "sg:province":"Solothurn",
    "wof:name":"Alwin Schwabe Massage",
    "wof:placetype":"venue"
},
  "geometry": {"coordinates":[7.66208601,47.4729881287],"type":"Point"}
}