{
  "type": "Feature",
  "properties": {
    "iso:country":"CH",
    "sg:address":"Bahnhofstrasse 9",
    "sg:city":"Schlieren",
    "sg:orig_category":"Detailhandel mit Brillen U anderen Sehhilfen",
    "sg:phone":"+41 17304856",
    "sg:postcode":"8952",
    "sg:province":"Z\u00fcrich",
    "wof:name":"Alfons Auer Optiker",
    "wof:placetype":"venue"
},
  "geometry": {"coordinates":[8.447983,47.398251],"type":"Point"}
}