{
  "type": "Feature",
  "properties": {
    "iso:country":"CH",
    "sg:address":"Rue Louis-de-savoie 53",
    "sg:city":"Morges",
    "sg:orig_category":"Detailhandel mit S\u00e4uglings U Kinderbekleidung",
    "sg:phone":"+41 21 803 73 70",
    "sg:postcode":"1110",
    "sg:province":"Vaud",
    "wof:name":"Boutique L'orchid\u00e9e Mode Enfantine",
    "wof:placetype":"venue"
},
  "geometry": {"coordinates":[6.4987387657,46.5083122253],"type":"Point"}
}