{
  "type": "Feature",
  "properties": {
    "iso:country":"CH",
    "sg:address":"Rue Des Sources 3",
    "sg:city":"Gen\u00e8ve",
    "sg:orig_category":"Detailhandel mit Uhren U Schmuck Fachdetailhandel in Verkaufsr\u00e4umen",
    "sg:phone":"+41 22 329 00 51",
    "sg:postcode":"1205",
    "sg:province":"Gen\u00e8ve",
    "wof:name":"Geoffroy Et Gysin.",
    "wof:placetype":"venue"
},
  "geometry": {"coordinates":[6.1434988976,46.1962013245],"type":"Point"}
}