{
  "type": "Feature",
  "properties": {
    "addr:full":"Bergstrasse 65 5036 Oberentfelden. Postfach K\u00f6lliken Aargau 5742",
    "addr:housenumber":"65",
    "addr:postcode":"5036;5742",
    "addr:street":"Bergstrasse;Postfach Koelliken",
    "iso:country":"CH",
    "sg:address":"Bergstrasse 65 5036 Oberentfelden. Postfach",
    "sg:city":"K\u00f6lliken",
    "sg:orig_category":"Dachdeckerei Sanit\u00e4rinstallation",
    "sg:phone":"+41 62 724 14 03",
    "sg:postcode":"5742",
    "sg:province":"Aargau",
    "wof:name":"Dachbautechnik Gmbh",
    "wof:placetype":"venue"
},
  "geometry": {"coordinates":[8.061042,47.352264],"type":"Point"}
}