{
  "type": "Feature",
  "properties": {
    "iso:country":"CH",
    "sg:address":"Rathaus 9043 Trogen. Postfach 162",
    "sg:city":"Trogen",
    "sg:orig_category":"Verwaltung der Rechtspflege, Gerichte",
    "sg:phone":"+41 41 875 22 44",
    "sg:postcode":"9043",
    "sg:province":"Appenzell Ausserrhoden",
    "wof:name":"Kantonale Justizdirektion",
    "wof:placetype":"venue"
},
  "geometry": {"coordinates":[8.644156456,46.8820419312],"type":"Point"}
}