{
  "type": "Feature",
  "properties": {
    "iso:country":"CH",
    "sg:address":"L\u00f6bernstrasse 16c 6330 Cham. Postfach",
    "sg:city":"Cham",
    "sg:classifiers":[
        {
            "category":"Travel",
            "subcategory":"Hotels & Motels",
            "type":"Entertainment"
        }
    ],
    "sg:postcode":"6330",
    "sg:province":"Zug",
    "sg:tags":[
        "hotels",
        "mit",
        "restaurant"
    ],
    "wof:name":"Hmti Gmbh",
    "wof:placetype":"venue"
},
  "geometry": {"coordinates":[8.4622859955,47.1849441528],"type":"Point"}
}