{
  "type": "Feature",
  "properties": {
    "iso:country":"CH",
    "sg:address":"Bahngasse 5",
    "sg:city":"M\u00e4nnedorf",
    "sg:classifiers":[
        {
            "category":"Wholesale",
            "subcategory":"Vending Machines",
            "type":"Manufacturing & Wholesale Goods"
        }
    ],
    "sg:phone":"+41 19200426",
    "sg:postcode":"8708",
    "sg:province":"Z\u00fcrich",
    "sg:tags":[
        "boring",
        "combined",
        "machines",
        "milling"
    ],
    "wof:name":"Hans Wittwer Ag",
    "wof:placetype":"venue"
},
  "geometry": {"coordinates":[8.691897,47.253216],"type":"Point"}
}