{
  "type": "Feature",
  "properties": {
    "iso:country":"CH",
    "sg:address":"Heimstrasse 3",
    "sg:city":"Arbon",
    "sg:orig_category":"Sportvereine Ballsport Tischtennis",
    "sg:phone":"+41 71 446 67 63",
    "sg:postcode":"9320",
    "sg:province":"Thurgau",
    "wof:name":"Ttc Arbon",
    "wof:placetype":"venue"
},
  "geometry": {"coordinates":[9.4237823486,47.5105781555],"type":"Point"}
}