{
  "type": "Feature",
  "properties": {
    "iso:country":"CH",
    "sg:address":"Route De Saint-cergue 33 1260 Nyon. Postfach",
    "sg:city":"Mies",
    "sg:orig_category":"Finanzierungsinstitutionen",
    "sg:phone":"+41 22 755 66 21",
    "sg:postcode":"1295",
    "sg:province":"Vaud",
    "wof:name":"Din A., Inter-survey Consultant Finance, Informatique; Conseils, Prestations",
    "wof:placetype":"venue"
},
  "geometry": {"coordinates":[6.233602047,46.3873062134],"type":"Point"}
}