{
  "type": "Feature",
  "properties": {
    "iso:country":"CH",
    "sg:address":"Murtenstrasse 41",
    "sg:city":"G\u00fcmmenen",
    "sg:orig_category":"Grosshandel mit Eisenwaren sowie Installationsbedarf f\u00fcr Gas, Wasser U Heizung",
    "sg:phone":"+41 31 751 13 45",
    "sg:postcode":"3205",
    "sg:province":"Bern",
    "wof:name":"Ferratherm Gmbh Heizsysteme/heizkessel",
    "wof:placetype":"venue"
},
  "geometry": {"coordinates":[7.2443580627,46.9445915222],"type":"Point"}
}