{
  "type": "Feature",
  "properties": {
    "iso:country":"CH",
    "sg:address":"H\u00f6henweg 7",
    "sg:city":"Hermetschwil-staff",
    "sg:orig_category":"G\u00fcterbef\u00f6rderung im Strassenverkehr",
    "sg:phone":"+41 56 631 91 21",
    "sg:postcode":"5626",
    "sg:province":"Aargau",
    "wof:name":"Alfred Weber Transporte",
    "wof:placetype":"venue"
},
  "geometry": {"coordinates":[8.3385362625,47.3326377869],"type":"Point"}
}