{
  "type": "Feature",
  "properties": {
    "addr:full":"Rainstrasse 32 Theilingen Z\u00fcrich 8484",
    "addr:housenumber":"32",
    "addr:postcode":"8484",
    "addr:street":"Rainstrasse",
    "iso:country":"CH",
    "sg:address":"Rainstrasse 32",
    "sg:city":"Theilingen",
    "sg:orig_category":"Bauspenglerei Sanit\u00e4rinstallation",
    "sg:phone":"+41 19100226",
    "sg:postcode":"8484",
    "sg:province":"Z\u00fcrich",
    "wof:name":"Martin Kuhn Haustechnik",
    "wof:placetype":"venue"
},
  "geometry": {"coordinates":[8.580141,47.318897],"type":"Point"}
}