{
  "type": "Feature",
  "properties": {
    "iso:country":"CH",
    "sg:address":"Solothurnerstrasse 14",
    "sg:city":"H\u00e4gendorf",
    "sg:orig_category":"Fachdetailhandel in Verkaufsr\u00e4umen Handelsvermittlung U Grosshandel",
    "sg:phone":"+41 71 385 14 76",
    "sg:postcode":"4614",
    "sg:province":"Solothurn",
    "wof:name":"Korea Trade, Inh. Inauen-lee Hyun Ja Waren, Bes. Aus Korea; Handel",
    "wof:placetype":"venue"
},
  "geometry": {"coordinates":[9.2477283478,47.4207305908],"type":"Point"}
}