{
  "type": "Feature",
  "properties": {
    "iso:country":"CH",
    "sg:address":"Dorfstr. 32",
    "sg:city":"Bichwil",
    "sg:classifiers":[
        {
            "category":"Banks & Credit Unions",
            "subcategory":"Bank",
            "type":"Services"
        }
    ],
    "sg:phone":"+41 71 951 43 85",
    "sg:postcode":"9248",
    "sg:province":"St. Gallen",
    "wof:name":"Raiffeisenbank Bichwil-oberuzwil",
    "wof:placetype":"venue"
},
  "geometry": {"coordinates":[9.139918,47.420326],"type":"Point"}
}