{
  "type": "Feature",
  "properties": {
    "iso:country":"CH",
    "sg:address":"Freiburgstrasse 947",
    "sg:city":"Th\u00f6rishaus",
    "sg:orig_category":"Baugewerbe Innenausbau",
    "sg:phone":"+41 79 651 47 93",
    "sg:postcode":"3174",
    "sg:province":"Bern",
    "wof:name":"Beat Leuenberger Innenausbau & Montagen",
    "wof:placetype":"venue"
},
  "geometry": {"coordinates":[7.355225,46.898727],"type":"Point"}
}