{
  "type": "Feature",
  "properties": {
    "iso:country":"CH",
    "sg:address":"H\u00f6lzli Wolfertswil 9113 Degersheim. Postfach",
    "sg:city":"Wolfertswil",
    "sg:orig_category":"Interessenvertretungen",
    "sg:postcode":"9116",
    "sg:province":"St. Gallen",
    "wof:name":"Verein Viala",
    "wof:placetype":"venue"
},
  "geometry": {"coordinates":[7.8132300377,46.7012748718],"type":"Point"}
}