{
  "type": "Feature",
  "properties": {
    "iso:country":"CH",
    "sg:address":"Steinengraben 18 4051 Basel. Postfach",
    "sg:city":"Basel",
    "sg:orig_category":"Markt U Meinungsforschung",
    "sg:phone":"+41 61 285 14 51",
    "sg:postcode":"4002",
    "sg:province":"Basel-Stadt",
    "wof:name":"Emr Ltd",
    "wof:placetype":"venue"
},
  "geometry": {"coordinates":[7.5851998329,47.5544471741],"type":"Point"}
}