{
  "type": "Feature",
  "properties": {
    "iso:country":"CH",
    "sg:address":"Einsiedlerstrasse 32",
    "sg:city":"W\u00e4denswil",
    "sg:orig_category":"Herstellung von sonstigen Maschinen f\u00fcr unspezifische Verwendung Installation von Heizungs, L\u00fcftungs",
    "sg:phone":"+41 79 693 38 59",
    "sg:postcode":"8820",
    "sg:province":"Z\u00fcrich",
    "wof:name":"Global Feuerschutz & Sicherheit J.winkler",
    "wof:placetype":"venue"
},
  "geometry": {"coordinates":[8.6858701706,47.2199172974],"type":"Point"}
}