{
  "type": "Feature",
  "properties": {
    "iso:country":"CH",
    "sg:address":"R\u00fctenenweg 13",
    "sg:city":"Feuerthalen",
    "sg:orig_category":"Architektur U Ingenieurb\u00fcros",
    "sg:phone":"+41 52 659 37 72",
    "sg:postcode":"8245",
    "sg:province":"Z\u00fcrich",
    "wof:name":"Peb Planung, Entwicklung, Beratung Schwaninger Walter",
    "wof:placetype":"venue"
},
  "geometry": {"coordinates":[8.642915,47.68845],"type":"Point"}
}