{
  "type": "Feature",
  "properties": {
    "addr:full":"Route Cantonale Servion Vaud 1077",
    "addr:postcode":"1077",
    "addr:street":"Route Cantonale",
    "iso:country":"CH",
    "sg:address":"Route Cantonale",
    "sg:city":"Servion",
    "sg:orig_category":"Autogaragen",
    "sg:phone":"+41 79 632 55 52",
    "sg:postcode":"1077",
    "sg:province":"Vaud",
    "wof:name":"Pierre Reichenbach Garage Des P\u00e2querettes",
    "wof:placetype":"venue"
},
  "geometry": {"coordinates":[6.835973,47.103516],"type":"Point"}
}