{
  "type": "Feature",
  "properties": {
    "iso:country":"CH",
    "sg:address":"Rte De Courroux 39",
    "sg:city":"Vicques",
    "sg:orig_category":"Herstellung von sonstigen landwirtschaftlichen Maschinen",
    "sg:phone":"+41 32 435 63 15",
    "sg:postcode":"2824",
    "sg:province":"Jura",
    "wof:name":"Chapatte Maurice Sa",
    "wof:placetype":"venue"
},
  "geometry": {"coordinates":[7.4020061493,47.3518867493],"type":"Point"}
}