{
  "type": "Feature",
  "properties": {
    "iso:country":"CH",
    "sg:address":"Hauptstrasse 26",
    "sg:city":"Bettwiesen",
    "sg:orig_category":"Instandhaltung U Reparatur von Automobilen",
    "sg:phone":"+41 71 911 56 02",
    "sg:postcode":"9553",
    "sg:province":"Thurgau",
    "wof:name":"Braun F. Schlossgarage",
    "wof:placetype":"venue"
},
  "geometry": {"coordinates":[9.0251216888,47.4934616089],"type":"Point"}
}