{
  "type": "Feature",
  "properties": {
    "iso:country":"CH",
    "sg:address":"Fadstrasse 4",
    "sg:city":"Sch\u00fcbelbach",
    "sg:classifiers":[
        {
            "category":"Shopping",
            "subcategory":"Department Store",
            "type":"Retail Goods"
        }
    ],
    "sg:phone":"+41 55 440 70 70",
    "sg:postcode":"8862",
    "sg:province":"Schwyz",
    "sg:tags":[
        "linen",
        "bed"
    ],
    "wof:name":"Robert Ruoss & Co",
    "wof:placetype":"venue"
},
  "geometry": {"coordinates":[8.930191,47.172478],"type":"Point"}
}