{
  "type": "Feature",
  "properties": {
    "iso:country":"CH",
    "sg:address":"Grand-places",
    "sg:city":"Fribourg",
    "sg:orig_category":"Vermietung U Verpachtung von eigenen Immobilien",
    "sg:postcode":"1700",
    "sg:province":"Fribourg",
    "wof:name":"Immogreen Ag",
    "wof:placetype":"venue"
},
  "geometry": {"coordinates":[7.1533350945,46.8027229309],"type":"Point"}
}