{
  "type": "Feature",
  "properties": {
    "iso:country":"CH",
    "sg:address":"Dicki 194",
    "sg:city":"Hasle-r\u00fcegsau",
    "sg:orig_category":"Mechanische Werkst\u00e4tten",
    "sg:phone":"+41 34 461 40 06",
    "sg:postcode":"3415",
    "sg:province":"Bern",
    "wof:name":"Rudolf Buri Mechanische Werkstatt",
    "wof:placetype":"venue"
},
  "geometry": {"coordinates":[7.6541280746,47.0085105896],"type":"Point"}
}