{
  "type": "Feature",
  "properties": {
    "iso:country":"CH",
    "sg:address":"Badstrasse 31 5400 Baden. Postfach 1219",
    "sg:city":"Baden",
    "sg:orig_category":"Architektur U Ingenieurb\u00fcros",
    "sg:phone":"+41 56 222 60 55",
    "sg:postcode":"5401",
    "sg:province":"Aargau",
    "wof:name":"Konstruktionsbureau Othmar Schmid",
    "wof:placetype":"venue"
},
  "geometry": {"coordinates":[8.308652,47.475655],"type":"Point"}
}