{
  "type": "Feature",
  "properties": {
    "iso:country":"CH",
    "sg:address":"Jungfraustrasse 34",
    "sg:city":"Interlaken",
    "sg:orig_category":"Architektur U Ingenieurb\u00fcros Architekturb\u00fcros",
    "sg:phone":"+41 71 747 58 30",
    "sg:postcode":"3800",
    "sg:province":"Bern",
    "wof:name":"W. Faisst & B. Vorburger Architektur & Bauleitung Ag",
    "wof:placetype":"venue"
},
  "geometry": {"coordinates":[9.638376,47.449303],"type":"Point"}
}