{
  "type": "Feature",
  "properties": {
    "iso:country":"CH",
    "sg:address":"M\u00fchleweg 9",
    "sg:city":"Therwil",
    "sg:orig_category":"Pensionskassen",
    "sg:postcode":"4106",
    "sg:province":"Basel-Landschaft",
    "wof:name":"Personalf\u00fcrsorgestiftung Der Firma Emil Gschwind, Baugesch\u00e4ft, Vormals Gebr. Gschwind",
    "wof:placetype":"venue"
},
  "geometry": {"coordinates":[7.5507612228,47.4976654053],"type":"Point"}
}