{
  "type": "Feature",
  "properties": {
    "iso:country":"CH",
    "sg:address":"Lindenfeldweg 1",
    "sg:city":"Therwil",
    "sg:orig_category":"Detailhandel mit M\u00f6beln Innendekorationsateliers",
    "sg:phone":"+41 71 966 20 22",
    "sg:postcode":"4106",
    "sg:province":"Basel-Landschaft",
    "wof:name":"Walter Meier Caveng Polsterwerkst\u00e4tte",
    "wof:placetype":"venue"
},
  "geometry": {"coordinates":[8.9907236099,47.4823951721],"type":"Point"}
}