{
  "type": "Feature",
  "properties": {
    "iso:country":"CH",
    "sg:address":"Schild-ruststrasse 17",
    "sg:city":"Grenchen",
    "sg:orig_category":"Pensionskassen",
    "sg:phone":"+41 32 652 12 61",
    "sg:postcode":"2540",
    "sg:province":"Solothurn",
    "wof:name":"Wohlfahrts-stiftung Eta Sa Fabriques D'ebauches",
    "wof:placetype":"venue"
},
  "geometry": {"coordinates":[7.3955030441,47.1942634583],"type":"Point"}
}