{
  "type": "Feature",
  "properties": {
    "iso:country":"CH",
    "sg:address":"Meiniswilstrasse 100 4912 Aarwangen. Postfach",
    "sg:city":"Aarwangen",
    "sg:orig_category":"Gewinnung von Kies U Sand Herstellung von sonstigen Produkten aus nichtmetallischen Mineralien",
    "sg:phone":"+41 62 963 25 44",
    "sg:postcode":"4912",
    "sg:province":"Bern",
    "wof:name":"Kiesgrube Risi",
    "wof:placetype":"venue"
},
  "geometry": {"coordinates":[7.7672901154,47.2394599915],"type":"Point"}
}