{
  "type": "Feature",
  "properties": {
    "iso:country":"CH",
    "sg:address":"Hauptstr. 85",
    "sg:city":"Waldenburg",
    "sg:classifiers":[
        {
            "category":"Manufacturing",
            "subcategory":"Aerospace",
            "type":"Manufacturing & Wholesale Goods"
        }
    ],
    "sg:phone":"+41 61 965 22 22",
    "sg:postcode":"4437",
    "sg:province":"Basel-Landschaft",
    "sg:tags":[
        "equipment",
        "aeronautic",
        "transport",
        "vehicle"
    ],
    "wof:name":"Revue Thommen Ag",
    "wof:placetype":"venue"
},
  "geometry": {"coordinates":[7.746663,47.381077],"type":"Point"}
}