{
  "type": "Feature",
  "properties": {
    "iso:country":"CH",
    "sg:address":"G\u00fcterstr. 61",
    "sg:city":"Pratteln",
    "sg:classifiers":[
        {
            "category":"Banks & Credit Unions",
            "subcategory":"Investment Brokerage",
            "type":"Services"
        }
    ],
    "sg:phone":"+41 61 315 91 91",
    "sg:postcode":"4133",
    "sg:province":"Basel-Landschaft",
    "sg:tags":[
        "-",
        "transport",
        "related"
    ],
    "wof:name":"Danzas Ag, Dhl Solution",
    "wof:placetype":"venue"
},
  "geometry": {"coordinates":[7.6783719063,47.5226402283],"type":"Point"}
}