{
  "type": "Feature",
  "properties": {
    "iso:country":"CH",
    "sg:address":"Ludetswilerstrasse",
    "sg:city":"Weisslingen",
    "sg:orig_category":"Vermietung U Verpachtung von eigenen Immobilien",
    "sg:phone":"+41 19562050",
    "sg:postcode":"8484",
    "sg:province":"Z\u00fcrich",
    "wof:name":"Ps-immobilien Ag",
    "wof:placetype":"venue"
},
  "geometry": {"coordinates":[8.791683197,47.4289054871],"type":"Point"}
}