{
  "type": "Feature",
  "properties": {
    "iso:country":"CH",
    "sg:address":"Schulstrasse 2",
    "sg:city":"Hinterkappelen",
    "sg:classifiers":[
        {
            "category":"Manufacturing",
            "subcategory":"Building Materials",
            "type":"Manufacturing & Wholesale Goods"
        }
    ],
    "sg:phone":"+41 31 901 26 67",
    "sg:postcode":"3032",
    "sg:province":"Bern",
    "sg:tags":[
        "insulation",
        "electrical"
    ],
    "wof:name":"Althaus + Klopfstein Isolationen Ag",
    "wof:placetype":"venue"
},
  "geometry": {"coordinates":[7.379199028,46.9678230286],"type":"Point"}
}