{
  "type": "Feature",
  "properties": {
    "iso:country":"CH",
    "sg:address":"8471",
    "sg:city":"D\u00e4gerlen",
    "sg:classifiers":[
        {
            "category":"Restaurant",
            "type":"Food & Drink"
        }
    ],
    "sg:phone":"+41 52 316 11 82",
    "sg:postcode":"8471",
    "sg:province":"Z\u00fcrich",
    "wof:name":"Restaurant Frohsinn",
    "wof:placetype":"venue"
},
  "geometry": {"coordinates":[8.7215652466,47.5612297058],"type":"Point"}
}