{
  "type": "Feature",
  "properties": {
    "iso:country":"CH",
    "sg:address":"Route De St-cierges 1",
    "sg:city":"Thierrens",
    "sg:orig_category":"Nationale Postdienste",
    "sg:phone":"+41 21 905 30 05",
    "sg:postcode":"1410",
    "sg:province":"Vaud",
    "wof:name":"La Poste Suisse",
    "wof:placetype":"venue"
},
  "geometry": {"coordinates":[6.7524399757,46.7024383545],"type":"Point"}
}