{
  "type": "Feature",
  "properties": {
    "iso:country":"CH",
    "sg:address":"Witikonerstrasse 239",
    "sg:city":"Z\u00fcrich",
    "sg:orig_category":"Architektur U Ingenieurb\u00fcros",
    "sg:postcode":"8053",
    "sg:province":"Z\u00fcrich",
    "wof:name":"Ingenieurb\u00fcro Dolenc",
    "wof:placetype":"venue"
},
  "geometry": {"coordinates":[8.581162,47.359642],"type":"Point"}
}