{
  "type": "Feature",
  "properties": {
    "iso:country":"CH",
    "sg:address":"Via Francesco Ballerini 3",
    "sg:city":"Locarno",
    "sg:classifiers":[
        {
            "category":"Shopping",
            "subcategory":"Stationery & Office Supplies",
            "type":"Retail Goods"
        }
    ],
    "sg:phone":"+41 91 751 89 75",
    "sg:postcode":"6600",
    "sg:province":"Ticino",
    "sg:tags":[
        "packaging",
        "material"
    ],
    "wof:name":"Tisca Nova Sa",
    "wof:placetype":"venue"
},
  "geometry": {"coordinates":[8.7989768982,46.1657714844],"type":"Point"}
}