{
  "type": "Feature",
  "properties": {
    "iso:country":"CH",
    "sg:address":"2560 Nidau. Postfach 302",
    "sg:city":"Nidau",
    "sg:orig_category":"Sportvereine Ballsport Handball",
    "sg:phone":"+41 32 365 03 28",
    "sg:postcode":"2560",
    "sg:province":"Bern",
    "wof:name":"Tv Nidau",
    "wof:placetype":"venue"
},
  "geometry": {"coordinates":[7.2374000549,47.1240196228],"type":"Point"}
}