{
  "type": "Feature",
  "properties": {
    "addr:full":"Wangenstrasse 71 Herzogenbuchsee Bern 3360",
    "addr:housenumber":"71",
    "addr:postcode":"3360",
    "addr:street":"Wangenstrasse;Bern",
    "iso:country":"CH",
    "sg:address":"Wangenstrasse 71",
    "sg:city":"Herzogenbuchsee",
    "sg:orig_category":"Allgemeiner Hochbau Zimmerei, Dachdeckerei, Bauspenglerei U Abdichtung",
    "sg:phone":"+41 62 961 73 50",
    "sg:postcode":"3360",
    "sg:province":"Bern",
    "wof:name":"K\u00e4mpfer & Co",
    "wof:placetype":"venue"
},
  "geometry": {"coordinates":[7.699716,47.195526],"type":"Point"}
}