{
  "type": "Feature",
  "properties": {
    "iso:country":"CH",
    "sg:address":"Les Sorbiers 1867 Ollon Vd. Postfach",
    "sg:city":"Chesi\u00e8res",
    "sg:orig_category":"Detailhandel mit Fleisch U Fleischwaren",
    "sg:postcode":"1885",
    "sg:province":"Vaud",
    "wof:name":"Erard P.-a.",
    "wof:placetype":"venue"
},
  "geometry": {"coordinates":[6.9953799248,46.2966117859],"type":"Point"}
}