{
  "type": "Feature",
  "properties": {
    "iso:country":"CH",
    "sg:address":"Mannwilweg 3",
    "sg:city":"Selzach",
    "sg:orig_category":"Grosshandel mit Getr\u00e4nken",
    "sg:phone":"+41 32 641 16 50",
    "sg:postcode":"2545",
    "sg:province":"Solothurn",
    "wof:name":"Greder Erwin.",
    "wof:placetype":"venue"
},
  "geometry": {"coordinates":[7.4592461586,47.2072486877],"type":"Point"}
}