{
  "type": "Feature",
  "properties": {
    "iso:country":"CH",
    "sg:address":"Route De Cossonay 15",
    "sg:city":"Prilly",
    "sg:orig_category":"Detailhandel mit Uhren U Schmuck Reparatur von Uhren U Schmuck",
    "sg:phone":"+41 21 624 19 84",
    "sg:postcode":"1008",
    "sg:province":"Vaud",
    "wof:name":"Huber Michael Bijoutier - Joaillier",
    "wof:placetype":"venue"
},
  "geometry": {"coordinates":[6.6064200401,46.5338134766],"type":"Point"}
}