{
  "type": "Feature",
  "properties": {
    "iso:country":"CH",
    "sg:address":"Kronenstrasse 12 6418 Rothenthurm. Postfach 65",
    "sg:city":"Rothenthurm",
    "sg:orig_category":"Grosshandel mit Holz U Baustoffen",
    "sg:phone":"+41 81 833 45 25",
    "sg:postcode":"6418",
    "sg:province":"Schwyz",
    "wof:name":"Schumacher Plattenbel\u00e4ge Ag",
    "wof:placetype":"venue"
},
  "geometry": {"coordinates":[9.8381910324,46.4970664978],"type":"Point"}
}