{
  "type": "Feature",
  "properties": {
    "iso:country":"CH",
    "sg:address":"Hafenstrasse 27",
    "sg:city":"Kreuzlingen",
    "sg:orig_category":"G\u00fcterbef\u00f6rderung im Strassenverkehr",
    "sg:phone":"+41 71 672 65 85",
    "sg:postcode":"8280",
    "sg:province":"Thurgau",
    "wof:name":"J\u00fcrg Diggelmann Transporte",
    "wof:placetype":"venue"
},
  "geometry": {"coordinates":[9.1785125732,47.6510009766],"type":"Point"}
}