{
  "type": "Feature",
  "properties": {
    "iso:country":"CH",
    "sg:address":"Gourgas Rue 4 1205 Gen\u00e8ve. Postfach",
    "sg:city":"Gen\u00e8ve",
    "sg:orig_category":"Vermietung von Gebrauchsg\u00fctern",
    "sg:postcode":"1205",
    "sg:province":"Gen\u00e8ve",
    "wof:name":"Games 2001, Vazquez Blanca",
    "wof:placetype":"venue"
},
  "geometry": {"coordinates":[6.1392021179,46.199344635],"type":"Point"}
}