{
  "type": "Feature",
  "properties": {
    "iso:country":"CH",
    "sg:address":"Widen",
    "sg:city":"Oberb\u00fcren",
    "sg:orig_category":"G\u00fcterbef\u00f6rderung im Strassenverkehr",
    "sg:postcode":"9245",
    "sg:province":"St. Gallen",
    "wof:name":"Kaiser Richard, Autotransporte",
    "wof:placetype":"venue"
},
  "geometry": {"coordinates":[9.1381845474,47.5666694641],"type":"Point"}
}