{
  "type": "Feature",
  "properties": {
    "iso:country":"CH",
    "sg:address":"Fromagerie",
    "sg:city":"Villaraboud",
    "sg:orig_category":"Verwertung von Milch",
    "sg:phone":"+41 26 655 00 65",
    "sg:postcode":"1679",
    "sg:province":"Fribourg",
    "wof:name":"Guenat Pascal",
    "wof:placetype":"venue"
},
  "geometry": {"coordinates":[6.9119868279,46.659576416],"type":"Point"}
}