{
  "type": "Feature",
  "properties": {
    "iso:country":"CH",
    "sg:address":"Rufacherstrasse 7",
    "sg:city":"Basel",
    "sg:orig_category":"Non-Classified Establishments",
    "sg:postcode":"4055",
    "sg:province":"Basel-Stadt",
    "wof:name":"Koo Kon Gmbh",
    "wof:placetype":"venue"
},
  "geometry": {"coordinates":[7.5726017952,47.5575675964],"type":"Point"}
}