{
  "type": "Feature",
  "properties": {
    "iso:country":"CH",
    "sg:address":"Bachtelenstrasse 71 2540 Grenchen. Postfach",
    "sg:city":"Grenchen",
    "sg:orig_category":"Unclassifiable Establishments",
    "sg:postcode":"2540",
    "sg:province":"Solothurn",
    "wof:name":"Canareva Ag Beteiligungen Usw",
    "wof:placetype":"venue"
},
  "geometry": {"coordinates":[7.3786959648,47.1939888],"type":"Point"}
}