{
  "type": "Feature",
  "properties": {
    "addr:full":"Av. De La Harpe 15. 1000 Lausanne. Postfach Lausanne Vaud 1003",
    "addr:housenumber":"15",
    "addr:postcode":"1000;postfach;1003",
    "addr:street":"Av. De La Harpe",
    "iso:country":"CH",
    "sg:address":"Av. De La Harpe 15. 1000 Lausanne. Postfach",
    "sg:city":"Lausanne",
    "sg:orig_category":"Detailhandel mit Brot, Back U S\u00fcsswaren",
    "sg:phone":"+41 21 616 33 14",
    "sg:postcode":"1003",
    "sg:province":"Vaud",
    "wof:name":"Jaquier Fr\u00e9dy Boulangerie-p\u00e2tisserie.",
    "wof:placetype":"venue"
},
  "geometry": {"coordinates":[6.625915,46.512493],"type":"Point"}
}