{
  "type": "Feature",
  "properties": {
    "iso:country":"CH",
    "sg:address":"Dorfstrasse 100",
    "sg:city":"Geroldswil",
    "sg:orig_category":"Personal U Stellenvermittlung Unternehmensberatung",
    "sg:postcode":"8954",
    "sg:province":"Z\u00fcrich",
    "wof:name":"Regina Fl\u00fcckiger Quality System Manager",
    "wof:placetype":"venue"
},
  "geometry": {"coordinates":[8.4091272354,47.4242134094],"type":"Point"}
}