{
  "type": "Feature",
  "properties": {
    "iso:country":"CH",
    "sg:address":"Parkweg 2",
    "sg:city":"Oftringen",
    "sg:orig_category":"Herstellung von Teppichen",
    "sg:phone":"+41 62 797 85 00",
    "sg:postcode":"4665",
    "sg:province":"Aargau",
    "wof:name":"B\u00fcrge Parkett & Bodenbel\u00e4ge",
    "wof:placetype":"venue"
},
  "geometry": {"coordinates":[7.9228758812,47.3117103577],"type":"Point"}
}