{
  "type": "Feature",
  "properties": {
    "iso:country":"CH",
    "sg:address":"Comercialstrasse 22",
    "sg:city":"Chur",
    "sg:orig_category":"Andere Ausbildungsst\u00e4tten der h\u00f6heren Berufsausbildung",
    "sg:phone":"+41 81 257 16 40",
    "sg:postcode":"7000",
    "sg:province":"Graubunden",
    "wof:name":"Zentrum F\u00fcr Verwaltungs- Management An Der Htw Chur",
    "wof:placetype":"venue"
},
  "geometry": {"coordinates":[9.50893,46.847336],"type":"Point"}
}