{
  "type": "Feature",
  "properties": {
    "iso:country":"CH",
    "sg:address":"Thuraustrasse 54",
    "sg:city":"Ebnat-kappel",
    "sg:orig_category":"Sanit\u00e4r U Heizungsinstallation Sanit\u00e4rinstallation",
    "sg:phone":"+41 79 697 70 43",
    "sg:postcode":"9642",
    "sg:province":"St. Gallen",
    "wof:name":"Rudolf Hasler San.-& Heizungsinstallationen",
    "wof:placetype":"venue"
},
  "geometry": {"coordinates":[9.1243944168,47.2583503723],"type":"Point"}
}