{
  "type": "Feature",
  "properties": {
    "addr:full":"Roggia Via Alla 28 6962 Viganello. Postfach Viganello Ticino 6962",
    "addr:housenumber":"28",
    "addr:postcode":"6962 viganello. postfach;6962",
    "addr:street":"Via Alla",
    "iso:country":"CH",
    "sg:address":"Roggia Via Alla 28 6962 Viganello. Postfach",
    "sg:city":"Viganello",
    "sg:orig_category":"Betrieb von Sportanlagen",
    "sg:postcode":"6962",
    "sg:province":"Ticino",
    "wof:name":"New Forum Sa Impianti Sportivi Ed Accessori Ecc.; Comm., Progettazione, Installazione",
    "wof:placetype":"venue"
},
  "geometry": {"coordinates":[8.965783,46.010506],"type":"Point"}
}