{
  "type": "Feature",
  "properties": {
    "iso:country":"CH",
    "sg:address":"Hofstrasse 12",
    "sg:city":"H\u00f6ri",
    "sg:orig_category":"Instandhaltung U Reparatur von Automobilen",
    "sg:phone":"+41 18620752",
    "sg:postcode":"8181",
    "sg:province":"Z\u00fcrich",
    "wof:name":"Rs Carrosserie Schnyder Ren\u00e9",
    "wof:placetype":"venue"
},
  "geometry": {"coordinates":[8.5194292068,47.5125427246],"type":"Point"}
}