{
  "type": "Feature",
  "properties": {
    "iso:country":"CH",
    "sg:address":"Bellariastrasse 56",
    "sg:city":"Z\u00fcrich",
    "sg:orig_category":"Herstellung von Oberbekleidung",
    "sg:phone":"+41 14510690",
    "sg:postcode":"8038",
    "sg:province":"Z\u00fcrich",
    "wof:name":"Vogue Ag",
    "wof:placetype":"venue"
},
  "geometry": {"coordinates":[8.5292949677,47.3494186401],"type":"Point"}
}