{
  "type": "Feature",
  "properties": {
    "iso:country":"CH",
    "sg:address":"9546",
    "sg:city":"Tuttwil",
    "sg:orig_category":"Vorschulen, Kinderg\u00e4rten",
    "sg:phone":"+41 17614928",
    "sg:postcode":"9546",
    "sg:province":"Thurgau",
    "wof:name":"Kindergarten T\u00e4gerstein",
    "wof:placetype":"venue"
},
  "geometry": {"coordinates":[8.4532852173,47.2772254944],"type":"Point"}
}