{
  "type": "Feature",
  "properties": {
    "iso:country":"CH",
    "sg:address":"Gerechtigkeitsgasse 22",
    "sg:city":"Bern",
    "sg:orig_category":"Unternehmensberatung Wirtschaftspr\u00fcfung, Steuerberatung U Treuhand",
    "sg:phone":"+41 71 222 92 22",
    "sg:postcode":"3011",
    "sg:province":"Bern",
    "wof:name":"Bonfida Treuhand Ag",
    "wof:placetype":"venue"
},
  "geometry": {"coordinates":[9.377158165,47.4247245789],"type":"Point"}
}