{
  "type": "Feature",
  "properties": {
    "iso:country":"CH",
    "sg:address":"Im Schilling 666",
    "sg:city":"Marthalen",
    "sg:orig_category":"Elektroinstallation",
    "sg:phone":"+41 52 319 19 52",
    "sg:postcode":"8460",
    "sg:province":"Z\u00fcrich",
    "wof:name":"Alex Camenisch",
    "wof:placetype":"venue"
},
  "geometry": {"coordinates":[8.6515455246,47.6335792542],"type":"Point"}
}