{
  "type": "Feature",
  "properties": {
    "iso:country":"CH",
    "sg:address":"Schutzengelstrasse 25",
    "sg:city":"Baar",
    "sg:orig_category":"Wasserversorgung",
    "sg:phone":"+41 41 761 36 64",
    "sg:postcode":"6340",
    "sg:province":"Zug",
    "wof:name":"Wasserversorgung Der Korporation Baar",
    "wof:placetype":"venue"
},
  "geometry": {"coordinates":[8.5364542007,47.1989097595],"type":"Point"}
}