{
  "type": "Feature",
  "properties": {
    "iso:country":"CH",
    "sg:address":"Bahnhofstrasse",
    "sg:city":"Landquart",
    "sg:orig_category":"Vorschulen, Kinderg\u00e4rten",
    "sg:phone":"+41 81 322 39 88",
    "sg:postcode":"7302",
    "sg:province":"Graubunden",
    "wof:name":"Kindergarten Igis-landquart",
    "wof:placetype":"venue"
},
  "geometry": {"coordinates":[9.558139801,46.9678115845],"type":"Point"}
}