{
  "type": "Feature",
  "properties": {
    "addr:full":"Hasenmoostrasse 31 Rothenburg Luzern 6023",
    "addr:housenumber":"31",
    "addr:postcode":"6023",
    "addr:street":"Hasenmoostrasse",
    "iso:country":"CH",
    "sg:address":"Hasenmoostrasse 31",
    "sg:city":"Rothenburg",
    "sg:orig_category":"Detailhandel mit Brot, Back U S\u00fcsswaren Unternehmensberatung",
    "sg:postcode":"6023",
    "sg:province":"Luzern",
    "wof:name":"Proback Ag",
    "wof:placetype":"venue"
},
  "geometry": {"coordinates":[8.240147,47.100914],"type":"Point"}
}