{
  "type": "Feature",
  "properties": {
    "iso:country":"CH",
    "sg:address":"Ruelle Du Coll\u00e8ge 4",
    "sg:city":"V\u00e9troz",
    "sg:orig_category":"Rebbau",
    "sg:phone":"+41 27 346 17 51",
    "sg:postcode":"1963",
    "sg:province":"Valais",
    "wof:name":"Aim\u00e9 Disi\u00e8re Producteur-encaveur",
    "wof:placetype":"venue"
},
  "geometry": {"coordinates":[7.2829017639,46.2262611389],"type":"Point"}
}