{
  "type": "Feature",
  "properties": {
    "iso:country":"CH",
    "sg:address":"Casa Fontana",
    "sg:city":"Cavergno",
    "sg:orig_category":"Vereine Musik/Blasmusik",
    "sg:phone":"+41 91 754 21 45",
    "sg:postcode":"6690",
    "sg:province":"Ticino",
    "wof:name":"Banda Di Cavergno",
    "wof:placetype":"venue"
},
  "geometry": {"coordinates":[8.6107549667,46.3444137573],"type":"Point"}
}