{
  "type": "Feature",
  "properties": {
    "iso:country":"CH",
    "sg:address":"Oberdorf 3753 Oey. Postfach 10",
    "sg:city":"Oey",
    "sg:orig_category":"Datenverarbeitungsdienste Sonstige mit der Informatik verbundene T\u00e4tigkeiten",
    "sg:phone":"+41 33 681 12 09",
    "sg:postcode":"3753",
    "sg:province":"Bern",
    "wof:name":"Teuscher Informatik",
    "wof:placetype":"venue"
},
  "geometry": {"coordinates":[7.57717,46.659599],"type":"Point"}
}