{
  "type": "Feature",
  "properties": {
    "iso:country":"CH",
    "sg:address":"Rue St-maurice 3",
    "sg:city":"Del\u00e9mont",
    "sg:orig_category":"Feinmechanische and Pr\u00e4zisions Werkst\u00e4tten",
    "sg:phone":"+41 32 853 73 50",
    "sg:postcode":"2800",
    "sg:province":"Jura",
    "wof:name":"Jo\u00ebl Ballaman M\u00e9canique De Pr\u00e9cision",
    "wof:placetype":"venue"
},
  "geometry": {"coordinates":[6.8751878738,47.0489082336],"type":"Point"}
}