{
  "type": "Feature",
  "properties": {
    "iso:country":"CH",
    "sg:address":"L'ochette",
    "sg:city":"Montcherand",
    "sg:orig_category":"Herstellung von Seifen, Wasch U Reinigungsmitteln",
    "sg:phone":"+41 24 441 10 27",
    "sg:postcode":"1354",
    "sg:province":"Vaud",
    "wof:name":"Rps Reguin Jean-michel",
    "wof:placetype":"venue"
},
  "geometry": {"coordinates":[6.5104799271,46.7344207764],"type":"Point"}
}