{
  "type": "Feature",
  "properties": {
    "iso:country":"CH",
    "sg:address":"Lengenacherstrasse 10",
    "sg:city":"Meiringen",
    "sg:orig_category":"Sonstiges Gesundheitswesen",
    "sg:phone":"+41 33 971 32 66",
    "sg:postcode":"3860",
    "sg:province":"Bern",
    "wof:name":"Krankenmobilienmagazin",
    "wof:placetype":"venue"
},
  "geometry": {"coordinates":[8.1854839325,46.7302513123],"type":"Point"}
}