{
  "type": "Feature",
  "properties": {
    "iso:country":"CH",
    "sg:address":"Piazza Della Riforma 2",
    "sg:city":"Lugano",
    "sg:orig_category":"Detailhandel mit Uhren U Schmuck Herstellung von Schmuck, Gold U Silberschmiedwaren",
    "sg:phone":"+41 91 922 65 45",
    "sg:postcode":"6900",
    "sg:province":"Ticino",
    "wof:name":"Goldgem Sa Gioielleria-pietre Preziose",
    "wof:placetype":"venue"
},
  "geometry": {"coordinates":[8.9507904053,46.0038108826],"type":"Point"}
}