{
  "type": "Feature",
  "properties": {
    "iso:country":"CH",
    "sg:address":"Schultheissenstrasse 2 4950 Huttwil. Postfach",
    "sg:city":"Huttwil",
    "sg:orig_category":"Hardwareberatung",
    "sg:postcode":"4950",
    "sg:province":"Bern",
    "wof:name":"Mr. Goodbyte Pc Systeme Gmbh",
    "wof:placetype":"venue"
},
  "geometry": {"coordinates":[7.8471889496,47.114440918],"type":"Point"}
}