{
  "type": "Feature",
  "properties": {
    "iso:country":"CH",
    "sg:address":"Rue Centrale 57",
    "sg:city":"Conthey",
    "sg:classifiers":[
        {
            "category":"Banks & Credit Unions",
            "subcategory":"Bank",
            "type":"Services"
        }
    ],
    "sg:phone":"+41 27 345 38 50",
    "sg:postcode":"1964",
    "sg:province":"Valais",
    "wof:name":"Banque Raiffeisen",
    "wof:placetype":"venue"
},
  "geometry": {"coordinates":[7.305961,46.230778],"type":"Point"}
}