{
  "type": "Feature",
  "properties": {
    "iso:country":"CH",
    "sg:address":"Lohningerweg 95 8240 Thayngen. Postfach",
    "sg:city":"Thayngen",
    "sg:orig_category":"Satzherstellung U Reproduktion",
    "sg:phone":"+41 52 649 42 80",
    "sg:postcode":"8240",
    "sg:province":"Schaffhausen",
    "wof:name":"High Scan, Reprotechnik Thayngen Gmbh",
    "wof:placetype":"venue"
},
  "geometry": {"coordinates":[8.6969404221,47.7495498657],"type":"Point"}
}