{
  "type": "Feature",
  "properties": {
    "iso:country":"CH",
    "sg:address":"Spitalackerstrasse 26 3013 Bern. Postfach",
    "sg:city":"Bern",
    "sg:classifiers":[
        {
            "category":"Professional",
            "subcategory":"Employment Agencies",
            "type":"Services"
        }
    ],
    "sg:phone":"+41 32 861 35 15",
    "sg:postcode":"3005",
    "sg:province":"Bern",
    "sg:tags":[
        "personal",
        "u",
        "stellenvermittlung"
    ],
    "wof:name":"Sisyphe Travail Fixe & Temp. Georges-andr\u00e9 Gobat",
    "wof:placetype":"venue"
},
  "geometry": {"coordinates":[6.4778800011,46.6214408875],"type":"Point"}
}