{
  "type": "Feature",
  "properties": {
    "iso:country":"CH",
    "sg:address":"Brambergstrasse 3b",
    "sg:city":"Luzern",
    "sg:orig_category":"Non-Classified Establishments",
    "sg:postcode":"6004",
    "sg:province":"Luzern",
    "wof:name":"Boris Hunold Architekturb\u00fcro",
    "wof:placetype":"venue"
},
  "geometry": {"coordinates":[8.3074998856,47.0551376343],"type":"Point"}
}