{
  "type": "Feature",
  "properties": {
    "iso:country":"CH",
    "sg:address":"Feldeggstrasse 49",
    "sg:city":"Z\u00fcrich",
    "sg:orig_category":"Reiseb\u00fcros U Reiseveranstalter",
    "sg:postcode":"8008",
    "sg:province":"Z\u00fcrich",
    "wof:name":"Madexplor Ag",
    "wof:placetype":"venue"
},
  "geometry": {"coordinates":[8.4388933182,47.3513183594],"type":"Point"}
}