{
  "type": "Feature",
  "properties": {
    "iso:country":"CH",
    "sg:address":"Morgartenstrasse 5",
    "sg:city":"Z\u00fcrich",
    "sg:classifiers":[
        {
            "category":"Restaurant",
            "type":"Food & Drink"
        }
    ],
    "sg:phone":"+41 12424859",
    "sg:postcode":"8004",
    "sg:province":"Z\u00fcrich",
    "wof:name":"Christophorus Restaurant-pizzeria",
    "wof:placetype":"venue"
},
  "geometry": {"coordinates":[8.5295686722,47.3711357117],"type":"Point"}
}