{
  "type": "Feature",
  "properties": {
    "iso:country":"CH",
    "sg:address":"Bernrainstrasse 19",
    "sg:city":"Kreuzlingen",
    "sg:orig_category":"Arztpraxen",
    "sg:phone":"+41 71 672 92 92",
    "sg:postcode":"8280",
    "sg:province":"Thurgau",
    "wof:name":"Dr.med. Andrea Mohr Spezialarzt Fmh",
    "wof:placetype":"venue"
},
  "geometry": {"coordinates":[9.160965,47.645481],"type":"Point"}
}