{
  "type": "Feature",
  "properties": {
    "iso:country":"CH",
    "sg:address":"R\u00fcttistrasse 12",
    "sg:city":"Eiken",
    "sg:orig_category":"Massagestudios",
    "sg:phone":"+41 62 871 29 06",
    "sg:postcode":"5074",
    "sg:province":"Aargau",
    "wof:name":"Hansruedi Dinkel Maz-din Massagen",
    "wof:placetype":"venue"
},
  "geometry": {"coordinates":[7.9843568802,47.5335464478],"type":"Point"}
}