{
  "type": "Feature",
  "properties": {
    "iso:country":"CH",
    "sg:address":"Cantonale Via 19",
    "sg:city":"Lugano",
    "sg:orig_category":"Finanzierungsinstitutionen",
    "sg:postcode":"6900",
    "sg:province":"Ticino",
    "wof:name":"Transacom Sa",
    "wof:placetype":"venue"
},
  "geometry": {"coordinates":[8.9502239227,46.0093307495],"type":"Point"}
}