{
  "type": "Feature",
  "properties": {
    "iso:country":"CH",
    "sg:address":"Uerkenweg 7",
    "sg:city":"Unterentfelden",
    "sg:orig_category":"Allgemeiner Hochbau Zimmerei, Dachdeckerei, Bauspenglerei U Abdichtung",
    "sg:phone":"+41 62 723 59 48",
    "sg:postcode":"5035",
    "sg:province":"Aargau",
    "wof:name":"Kazan-bedachungen",
    "wof:placetype":"venue"
},
  "geometry": {"coordinates":[8.044769,47.36261],"type":"Point"}
}