{
  "type": "Feature",
  "properties": {
    "iso:country":"CH",
    "sg:address":"F\u00f6hrenweg 7",
    "sg:city":"Gutenswil",
    "sg:orig_category":"Autogaragen",
    "sg:phone":"+41 77626660",
    "sg:postcode":"8605",
    "sg:province":"Z\u00fcrich",
    "wof:name":"Bruno Meier Autogarage",
    "wof:placetype":"venue"
},
  "geometry": {"coordinates":[8.721049,47.386387],"type":"Point"}
}