{
  "type": "Feature",
  "properties": {
    "iso:country":"CH",
    "sg:address":"Blumenfeldstrasse 51 8046 Z\u00fcrich. Postfach 280",
    "sg:city":"Z\u00fcrich",
    "sg:orig_category":"Architektur U Ingenieurb\u00fcros",
    "sg:phone":"+41 13714422",
    "sg:postcode":"8046",
    "sg:province":"Z\u00fcrich",
    "wof:name":"M + F Engineering Ag",
    "wof:placetype":"venue"
},
  "geometry": {"coordinates":[8.503808,47.423363],"type":"Point"}
}