{
  "type": "Feature",
  "properties": {
    "iso:country":"CH",
    "sg:address":"1794",
    "sg:city":"Salvenach",
    "sg:orig_category":"Herstellung von Metallkonstruktionen Schlossereien",
    "sg:phone":"+41 18515252",
    "sg:postcode":"1794",
    "sg:province":"Fribourg",
    "wof:name":"Berico Ag Niederglatt Metallbau",
    "wof:placetype":"venue"
},
  "geometry": {"coordinates":[8.5043296814,47.4856567383],"type":"Point"}
}