{
  "type": "Feature",
  "properties": {
    "addr:full":"Bundesgasse 20 Bern Bern 3011",
    "addr:housenumber":"20",
    "addr:postcode":"3011",
    "addr:street":"Bundesgasse",
    "iso:country":"CH",
    "sg:address":"Bundesgasse 20",
    "sg:city":"Bern",
    "sg:orig_category":"Detailhandel mit Damenbekleidung",
    "sg:phone":"+41 31 318 31 20",
    "sg:postcode":"3011",
    "sg:province":"Bern",
    "wof:name":"Popken & Co Ulla Popken Mode",
    "wof:placetype":"venue"
},
  "geometry": {"coordinates":[7.441221,46.94659],"type":"Point"}
}