{
  "type": "Feature",
  "properties": {
    "iso:country":"CH",
    "sg:address":"Gerliswilstrasse 26",
    "sg:city":"Emmenbr\u00fccke",
    "sg:orig_category":"Messeorganisationen",
    "sg:phone":"+41 21 962 21 41",
    "sg:postcode":"6020",
    "sg:province":"Luzern",
    "wof:name":"Centre Affaires Culturelles De Montreux",
    "wof:placetype":"venue"
},
  "geometry": {"coordinates":[6.9046978951,46.4393806458],"type":"Point"}
}