{
  "type": "Feature",
  "properties": {
    "iso:country":"CH",
    "sg:address":"Spalenring 15",
    "sg:city":"Basel",
    "sg:orig_category":"Sonstiger Grosshandel",
    "sg:postcode":"4055",
    "sg:province":"Basel-Stadt",
    "wof:name":"Choukhmane Mohammed",
    "wof:placetype":"venue"
},
  "geometry": {"coordinates":[7.5743751526,47.5609359741],"type":"Point"}
}