{
  "type": "Feature",
  "properties": {
    "iso:country":"CH",
    "sg:address":"Le Verger",
    "sg:city":"Moudon",
    "sg:orig_category":"Oberfl\u00e4chenveredlung U W\u00e4rmebehandlung",
    "sg:phone":"+41 21 905 45 00",
    "sg:postcode":"1510",
    "sg:province":"Vaud",
    "wof:name":"Microgalvano, Roth Bruno",
    "wof:placetype":"venue"
},
  "geometry": {"coordinates":[6.7970471382,46.6660995483],"type":"Point"}
}