{
  "type": "Feature",
  "properties": {
    "iso:country":"CH",
    "sg:address":"Riset",
    "sg:city":"Bauma",
    "sg:orig_category":"Herstellung von sonstigen elektrischen Ausr\u00fcstungen",
    "sg:phone":"+41 52 386 14 00",
    "sg:postcode":"8494",
    "sg:province":"Z\u00fcrich",
    "wof:name":"Winau Gmbh",
    "wof:placetype":"venue"
},
  "geometry": {"coordinates":[8.8927059174,47.3815689087],"type":"Point"}
}