{
  "type": "Feature",
  "properties": {
    "iso:country":"CH",
    "sg:address":"Aedelswil",
    "sg:city":"Herisau",
    "sg:orig_category":"Handelsvermittlung U Grosshandel Sonstiger Grosshandel",
    "sg:phone":"+41 62 824 59 05",
    "sg:postcode":"9100",
    "sg:province":"Appenzell Ausserrhoden",
    "wof:name":"Bosporus, Kanik + Uygun",
    "wof:placetype":"venue"
},
  "geometry": {"coordinates":[8.0877580643,47.3881721497],"type":"Point"}
}