{
  "type": "Feature",
  "properties": {
    "iso:country":"CH",
    "sg:address":"Brunnenwiesenstrasse 15",
    "sg:city":"Regensdorf",
    "sg:orig_category":"Finanzierungsinstitutionen",
    "sg:postcode":"8105",
    "sg:province":"Z\u00fcrich",
    "wof:name":"Doll Invest Consult",
    "wof:placetype":"venue"
},
  "geometry": {"coordinates":[8.4805173874,47.4282684326],"type":"Point"}
}