{
  "type": "Feature",
  "properties": {
    "iso:country":"CH",
    "sg:address":"Ziegeleistrasse 1",
    "sg:city":"Basadingen",
    "sg:orig_category":"Herstellung von Kunststoff in Prim\u00e4rformen Herstellung von Kunststoffwaren",
    "sg:phone":"+41 52 657 15 55",
    "sg:postcode":"8254",
    "sg:province":"Thurgau",
    "wof:name":"Cadplast Ag",
    "wof:placetype":"venue"
},
  "geometry": {"coordinates":[8.7468767166,47.6690711975],"type":"Point"}
}