{
  "type": "Feature",
  "properties": {
    "iso:country":"CH",
    "sg:address":"Allmendstrasse 6",
    "sg:city":"Zuchwil",
    "sg:orig_category":"Alters U Hinterlassenenversicherung AHV, Invalidenversicherung IV, Arbeitslosenversicherung ALV",
    "sg:phone":"+41 41 874 50 10",
    "sg:postcode":"4528",
    "sg:province":"Solothurn",
    "wof:name":"Ausgleichskasse Des Kantons Uri",
    "wof:placetype":"venue"
},
  "geometry": {"coordinates":[8.645674,46.879757],"type":"Point"}
}