{
  "type": "Feature",
  "properties": {
    "iso:country":"CH",
    "sg:address":"Limmataustrasse 8",
    "sg:city":"Schlieren",
    "sg:orig_category":"Architekturb\u00fcros",
    "sg:phone":"+41 17303939",
    "sg:postcode":"8952",
    "sg:province":"Z\u00fcrich",
    "wof:name":"Architekturb\u00fcro Wally Demuth",
    "wof:placetype":"venue"
},
  "geometry": {"coordinates":[8.449284,47.40686],"type":"Point"}
}