{
  "type": "Feature",
  "properties": {
    "iso:country":"CH",
    "sg:address":"Rue Du Jura 18",
    "sg:city":"Chavornay",
    "sg:orig_category":"Herstellung von Metallerzeugnissen ohne Maschinenbau Herstellung von k\u00e4lte U lufttechnischen Erzeugn",
    "sg:phone":"+41 24 441 62 66",
    "sg:postcode":"1373",
    "sg:province":"Vaud",
    "wof:name":"Satag Thermotechnik Ag",
    "wof:placetype":"venue"
},
  "geometry": {"coordinates":[6.5687198639,46.7101783752],"type":"Point"}
}