{
  "type": "Feature",
  "properties": {
    "iso:country":"CH",
    "sg:address":"Spitalackerstrasse 69",
    "sg:city":"Bern",
    "sg:orig_category":"Interessenvertretungen",
    "sg:postcode":"3013",
    "sg:province":"Bern",
    "wof:name":"Pro Flora, Verein Der Freunde Des Botanischen Gartens In Bern",
    "wof:placetype":"venue"
},
  "geometry": {"coordinates":[7.4510917664,46.9571456909],"type":"Point"}
}