{
  "type": "Feature",
  "properties": {
    "iso:country":"CH",
    "sg:address":"Fuyens",
    "sg:city":"Villaz-st-pierre",
    "sg:orig_category":"Verwertung von Milch",
    "sg:postcode":"1690",
    "sg:province":"Fribourg",
    "wof:name":"Soci\u00e9t\u00e9 De Laiterie De Villaz-st-pierre.",
    "wof:placetype":"venue"
},
  "geometry": {"coordinates":[6.9733071327,46.7120018005],"type":"Point"}
}