{
  "type": "Feature",
  "properties": {
    "iso:country":"CH",
    "sg:address":"T\u00f6pfereistrasse 9",
    "sg:city":"Ersigen",
    "sg:orig_category":"Non-Classified Establishments",
    "sg:postcode":"3423",
    "sg:province":"Bern",
    "wof:name":"R\u00f6sti Unternehmensentwicklung & Interimsmanagement",
    "wof:placetype":"venue"
},
  "geometry": {"coordinates":[7.6292757988,46.7149467468],"type":"Point"}
}