{
  "type": "Feature",
  "properties": {
    "iso:country":"CH",
    "sg:address":"Falkenstrasse 30",
    "sg:city":"Langenthal",
    "sg:orig_category":"Sportvereine Turnen Vereine Damen",
    "sg:phone":"+41 56 282 50 40",
    "sg:postcode":"4900",
    "sg:province":"Bern",
    "wof:name":"Damenturnverein",
    "wof:placetype":"venue"
},
  "geometry": {"coordinates":[8.2991409302,47.4871864319],"type":"Point"}
}