{
  "type": "Feature",
  "properties": {
    "iso:country":"CH",
    "sg:address":"Krummackerweg 1",
    "sg:city":"Ormalingen",
    "sg:orig_category":"Arztpraxen",
    "sg:phone":"+41 61 981 35 35",
    "sg:postcode":"4466",
    "sg:province":"Basel-Landschaft",
    "wof:name":"Dr.med.thomas Schwyter Arzt F.allgemeine Medizin Fmh",
    "wof:placetype":"venue"
},
  "geometry": {"coordinates":[7.873131,47.471935],"type":"Point"}
}