{
  "type": "Feature",
  "properties": {
    "iso:country":"CH",
    "sg:address":"Bot La Pala",
    "sg:city":"Vaz/obervaz",
    "sg:orig_category":"Vermietung U Verpachtung von eigenen Immobilien",
    "sg:phone":"+41 81 384 42 92",
    "sg:postcode":"7082",
    "sg:province":"Graubunden",
    "wof:name":"La Pala Immobilien Ag",
    "wof:placetype":"venue"
},
  "geometry": {"coordinates":[9.5459785461,46.7287597656],"type":"Point"}
}