{
  "type": "Feature",
  "properties": {
    "iso:country":"CH",
    "sg:address":"Lagerstrasse 25",
    "sg:city":"Herzogenbuchsee",
    "sg:orig_category":"Grosshandel mit Getr\u00e4nken Grosshandel mit Wein U Spirituosen",
    "sg:phone":"+41 21 825 11 41",
    "sg:postcode":"3360",
    "sg:province":"Bern",
    "wof:name":"Hammel Ag",
    "wof:placetype":"venue"
},
  "geometry": {"coordinates":[7.7019371986,47.190410614],"type":"Point"}
}