{
  "type": "Feature",
  "properties": {
    "iso:country":"CH",
    "sg:address":"Boulevard James-fazy 5",
    "sg:city":"Gen\u00e8ve",
    "sg:orig_category":"Detailhandel mit Damenbekleidung",
    "sg:phone":"+41 22 732 26 76",
    "sg:postcode":"1201",
    "sg:province":"Gen\u00e8ve",
    "wof:name":"Jos\u00e9phine Brigante Boutique Monic",
    "wof:placetype":"venue"
},
  "geometry": {"coordinates":[6.139325,46.206905],"type":"Point"}
}