{
  "type": "Feature",
  "properties": {
    "iso:country":"CH",
    "sg:address":"Rue Verte 11 1200 Gen\u00e8ve. Postfach",
    "sg:city":"Gen\u00e8ve",
    "sg:orig_category":"Herstellung von sonstigen Maschinen f\u00fcr bestimmte Verwendung",
    "sg:phone":"+41 22 321 68 50",
    "sg:postcode":"1205",
    "sg:province":"Gen\u00e8ve",
    "wof:name":"Graphic Solutions, Nicholas Palffy",
    "wof:placetype":"venue"
},
  "geometry": {"coordinates":[6.1445908546,46.1898880005],"type":"Point"}
}