{
  "type": "Feature",
  "properties": {
    "iso:country":"CH",
    "sg:address":"Bankstr. 1",
    "sg:city":"Weinfelden",
    "sg:classifiers":[
        {
            "category":"Banks & Credit Unions",
            "subcategory":"Bank",
            "type":"Services"
        }
    ],
    "sg:phone":"+41 4172211333",
    "sg:postcode":"8570",
    "sg:province":"Thurgau",
    "wof:name":"Credit Suisse",
    "wof:placetype":"venue"
},
  "geometry": {"coordinates":[9.108901,47.567951],"type":"Point"}
}