{
  "type": "Feature",
  "properties": {
    "iso:country":"CH",
    "sg:address":"Hauptstrasse 19",
    "sg:city":"Gempen",
    "sg:orig_category":"Herstellung von keramischen Haushaltswaren U Ziergegenst\u00e4nden",
    "sg:phone":"+41 61 701 52 18",
    "sg:postcode":"4145",
    "sg:province":"Solothurn",
    "wof:name":"T\u00f6pferei Campus S.saladin",
    "wof:placetype":"venue"
},
  "geometry": {"coordinates":[7.6585221291,47.4753494263],"type":"Point"}
}