{
  "type": "Feature",
  "properties": {
    "iso:country":"CH",
    "sg:address":"Baarerstrasse 36",
    "sg:city":"Zug",
    "sg:classifiers":[
        {
            "category":"Travel",
            "subcategory":"Hotels & Motels",
            "type":"Entertainment"
        }
    ],
    "sg:phone":"+41 41 711 32 88",
    "sg:postcode":"6300",
    "sg:province":"Zug",
    "sg:tags":[
        "hotels",
        "mit",
        "restaurant"
    ],
    "wof:name":"Alphatec Inter Ag",
    "wof:placetype":"venue"
},
  "geometry": {"coordinates":[8.5172119141,47.1742897034],"type":"Point"}
}