{
  "type": "Feature",
  "properties": {
    "iso:country":"CH",
    "sg:address":"Obersieg 80",
    "sg:city":"Oberkulm",
    "sg:orig_category":"Druck ohne Zeitungsdruck",
    "sg:phone":"+41 22 781 28 48",
    "sg:postcode":"5727",
    "sg:province":"Aargau",
    "wof:name":"Transph\u00e8re Sa",
    "wof:placetype":"venue"
},
  "geometry": {"coordinates":[6.1357288361,46.1987266541],"type":"Point"}
}