{
  "type": "Feature",
  "properties": {
    "iso:country":"CH",
    "sg:address":"8180 B\u00fclach. Postfach 2",
    "sg:city":"B\u00fclach",
    "sg:orig_category":"Sportvereine Unihockey",
    "sg:phone":"+41 18137930",
    "sg:postcode":"8180",
    "sg:province":"Z\u00fcrich",
    "wof:name":"Uhc Kloten-b\u00fclach Jets",
    "wof:placetype":"venue"
},
  "geometry": {"coordinates":[8.5452299118,47.5292510986],"type":"Point"}
}