{
  "type": "Feature",
  "properties": {
    "iso:country":"CH",
    "sg:address":"M\u00fchlebachstrasse 86 8008 Z\u00fcrich. Postfach 1011 8032 Z\u00fcrich",
    "sg:city":"Zust",
    "sg:orig_category":"Vereine Quartier",
    "sg:postcode":"32",
    "wof:name":"Aktives Mohren",
    "wof:placetype":"venue"
},
  "geometry": {"coordinates":[9.5555429459,47.4025039673],"type":"Point"}
}