{
  "type": "Feature",
  "properties": {
    "iso:country":"CH",
    "sg:address":"Acherweg 9 6370 Stans. Postfach",
    "sg:city":"Stans",
    "sg:orig_category":"Sonstige pers\u00f6nliche Dienstleistungen",
    "sg:postcode":"6370",
    "sg:province":"Nidwalden",
    "wof:name":"Off-serve Tremp M.b. Dienstleistungen Im B\u00fcrobereich",
    "wof:placetype":"venue"
},
  "geometry": {"coordinates":[8.3650903702,46.962802887],"type":"Point"}
}