{
  "type": "Feature",
  "properties": {
    "iso:country":"CH",
    "sg:address":"Im Werd 6 8952 Schlieren. Postfach",
    "sg:city":"Schlieren",
    "sg:orig_category":"Instandhaltung U Reparatur von Automobilen",
    "sg:phone":"+41 79 209 62 68",
    "sg:postcode":"8952",
    "sg:province":"Z\u00fcrich",
    "wof:name":"Garage Remo Corte",
    "wof:placetype":"venue"
},
  "geometry": {"coordinates":[8.4514198303,47.3982124329],"type":"Point"}
}