{
  "type": "Feature",
  "properties": {
    "iso:country":"CH",
    "sg:address":"San Bastiaun 30",
    "sg:city":"Samedan",
    "sg:orig_category":"Tierarztpraxis",
    "sg:phone":"+41 81 852 44 77",
    "sg:postcode":"7503",
    "sg:province":"Graubunden",
    "wof:name":"Dr. Med. Vet. Mauro Vattolo Tierarzt",
    "wof:placetype":"venue"
},
  "geometry": {"coordinates":[9.8682041168,46.5315208435],"type":"Point"}
}