{
  "type": "Feature",
  "properties": {
    "iso:country":"CH",
    "sg:address":"De-senger Rue Hugo- 10 1200 Genf. Postfach",
    "sg:city":"Gen\u00e8ve",
    "sg:orig_category":"Herstellung von konfektionierten Textilwaren ohne Bekleidung",
    "sg:postcode":"1205",
    "sg:province":"Gen\u00e8ve",
    "wof:name":"Ab\u00e4nderungsschneider H\u00f6fler",
    "wof:placetype":"venue"
},
  "geometry": {"coordinates":[7.4441518784,47.4579734802],"type":"Point"}
}