{
  "type": "Feature",
  "properties": {
    "iso:country":"CH",
    "sg:address":"St\u00e4dtli 1",
    "sg:city":"Pfyn",
    "sg:orig_category":"Vorschulen, Kinderg\u00e4rten",
    "sg:phone":"+41 71 288 45 30",
    "sg:postcode":"8505",
    "sg:province":"Thurgau",
    "wof:name":"Kindergarten Schulkindergarten",
    "wof:placetype":"venue"
},
  "geometry": {"coordinates":[9.4059391022,47.4359893799],"type":"Point"}
}