{
  "type": "Feature",
  "properties": {
    "iso:country":"CH",
    "sg:address":"B\u00e4ndlistr. 87/89",
    "sg:city":"Z\u00fcrich",
    "sg:classifiers":[
        {
            "category":"Utilities",
            "subcategory":"Electric",
            "type":"Services"
        }
    ],
    "sg:phone":"+41 4114342020",
    "sg:postcode":"8064",
    "sg:province":"Z\u00fcrich",
    "sg:tags":[
        "electricity",
        "raw",
        "energy",
        "material"
    ],
    "wof:name":"Pangas",
    "wof:placetype":"venue"
},
  "geometry": {"coordinates":[8.4814691544,47.3969497681],"type":"Point"}
}