{
  "type": "Feature",
  "properties": {
    "iso:country":"CH",
    "sg:address":"Steinenweg 45 4133 Pratteln. Postfach",
    "sg:city":"Pratteln",
    "sg:orig_category":"Interessenvertretungen",
    "sg:phone":"+41 61 821 55 79",
    "sg:postcode":"4133",
    "sg:province":"Basel-Landschaft",
    "wof:name":"Kiesverband Pratteln",
    "wof:placetype":"venue"
},
  "geometry": {"coordinates":[7.6926231384,47.5130805969],"type":"Point"}
}