{
  "type": "Feature",
  "properties": {
    "iso:country":"CH",
    "sg:address":"Weststrasse 23",
    "sg:city":"Unter\u00e4geri",
    "sg:orig_category":"Unternehmensberatung",
    "sg:phone":"+41 41 750 21 85",
    "sg:postcode":"6314",
    "sg:province":"Zug",
    "wof:name":"Frey Hans Creawork",
    "wof:placetype":"venue"
},
  "geometry": {"coordinates":[8.570690155,47.1362609863],"type":"Point"}
}