{
  "type": "Feature",
  "properties": {
    "iso:country":"CH",
    "sg:address":"Rhonesandstr. 13",
    "sg:city":"Brig",
    "sg:orig_category":"Detailhandel mit Brillen U anderen Sehhilfen Fachdetailhandel in Verkaufsr\u00e4umen",
    "sg:phone":"+41 27 922 04 40",
    "sg:postcode":"3900",
    "sg:province":"Valais",
    "wof:name":"Fl\u00fcckiger Und Moser, Zentrum Optik, Brig",
    "wof:placetype":"venue"
},
  "geometry": {"coordinates":[7.989634,46.317848],"type":"Point"}
}