{
  "type": "Feature",
  "properties": {
    "iso:country":"CH",
    "sg:address":"Industriestrasse 40 Glattbrugg 8152 Opfikon. Postfach",
    "sg:city":"Glattbrugg",
    "sg:orig_category":"Detailhandel mit Bekleidung",
    "sg:postcode":"8152",
    "sg:province":"Z\u00fcrich",
    "wof:name":"Beluno Gmbh",
    "wof:placetype":"venue"
},
  "geometry": {"coordinates":[8.57401,47.429298],"type":"Point"}
}