{
  "type": "Feature",
  "properties": {
    "iso:country":"CH",
    "sg:address":"D\u00fcrrbach",
    "sg:city":"Cham",
    "sg:orig_category":"Bauschreinerei Herstellung von Konstruktionsteilen, Fertigbauteilen U Ausbauelementen aus Holz",
    "sg:phone":"+41 79 432 13 12",
    "sg:postcode":"6330",
    "sg:province":"Zug",
    "wof:name":"Wyttenbach Friedrich",
    "wof:placetype":"venue"
},
  "geometry": {"coordinates":[8.447745,47.203979],"type":"Point"}
}