{
  "type": "Feature",
  "properties": {
    "iso:country":"CH",
    "sg:address":"Teufenthalerstrasse 68",
    "sg:city":"D\u00fcrren\u00e4sch",
    "sg:orig_category":"Detailhandel mit Fleisch U Fleischwaren Grosshandel mit lebenden Tieren",
    "sg:phone":"+41 62 777 15 47",
    "sg:postcode":"5724",
    "sg:province":"Aargau",
    "wof:name":"Hans Rudolf Gloor, Pferdemetzgerei Und Pferdehandel",
    "wof:placetype":"venue"
},
  "geometry": {"coordinates":[8.1517353058,47.3218383789],"type":"Point"}
}