{
  "type": "Feature",
  "properties": {
    "iso:country":"CH",
    "sg:address":"Gutenbergstrasse 19",
    "sg:city":"Biberist",
    "sg:orig_category":"Sportvereine Turnen",
    "sg:phone":"+41 32 672 29 17",
    "sg:postcode":"4562",
    "sg:province":"Solothurn",
    "wof:name":"Damenturnverein Biberist",
    "wof:placetype":"venue"
},
  "geometry": {"coordinates":[7.5607991219,47.1812133789],"type":"Point"}
}