{
  "type": "Feature",
  "properties": {
    "iso:country":"CH",
    "sg:address":"Rte D'italie",
    "sg:city":"Uvrier",
    "sg:orig_category":"Unclassifiable Establishments",
    "sg:postcode":"1958",
    "sg:province":"Valais",
    "wof:name":"Golden Optic Uvrier S\u00e0rl",
    "wof:placetype":"venue"
},
  "geometry": {"coordinates":[7.4114508629,46.2519340515],"type":"Point"}
}