{
  "type": "Feature",
  "properties": {
    "iso:country":"CH",
    "sg:address":"3929",
    "sg:city":"T\u00e4sch",
    "sg:classifiers":[
        {
            "category":"Travel",
            "subcategory":"Hotels & Motels",
            "type":"Entertainment"
        }
    ],
    "sg:phone":"+41 27 966 39 66",
    "sg:postcode":"3929",
    "sg:province":"Valais",
    "sg:tags":[
        "hotels",
        "mit",
        "restaurant"
    ],
    "wof:name":"Hotel Walliserhof",
    "wof:placetype":"venue"
},
  "geometry": {"coordinates":[7.7763252258,46.069694519],"type":"Point"}
}