{
  "type": "Feature",
  "properties": {
    "iso:country":"CH",
    "sg:address":"Fr\u00f6hlichstrasse 54",
    "sg:city":"Z\u00fcrich",
    "sg:orig_category":"Reinigungsgewerbe",
    "sg:phone":"+41 71 277 76 75",
    "sg:postcode":"8008",
    "sg:province":"Z\u00fcrich",
    "wof:name":"Stefan Grubenmann",
    "wof:placetype":"venue"
},
  "geometry": {"coordinates":[9.3220500946,47.4189910889],"type":"Point"}
}