{
  "type": "Feature",
  "properties": {
    "iso:country":"CH",
    "sg:address":"Rue De Lavetan",
    "sg:city":"Leytron",
    "sg:orig_category":"Detailhandel mit Getr\u00e4nken Rebbau",
    "sg:phone":"+41 27 306 20 57",
    "sg:postcode":"1912",
    "sg:province":"Valais",
    "wof:name":"Andr\u00e9 Bonvin",
    "wof:placetype":"venue"
},
  "geometry": {"coordinates":[7.2069888115,46.1880226135],"type":"Point"}
}