{
  "type": "Feature",
  "properties": {
    "iso:country":"CH",
    "sg:address":"Sommeristrasse 37",
    "sg:city":"Amriswil",
    "sg:orig_category":"Herstellung von Bettwaren",
    "sg:phone":"+41 71 414 15 15",
    "sg:postcode":"8580",
    "sg:province":"Thurgau",
    "wof:name":"Wiedemann Ag Schlafsysteme",
    "wof:placetype":"venue"
},
  "geometry": {"coordinates":[9.2950277328,47.5506668091],"type":"Point"}
}