{
  "type": "Feature",
  "properties": {
    "iso:country":"CH",
    "sg:address":"Brunnenstrasse 41",
    "sg:city":"Uster",
    "sg:classifiers":[
        {
            "category":"Restaurant",
            "type":"Food & Drink"
        }
    ],
    "sg:phone":"+41 19401268",
    "sg:postcode":"8610",
    "sg:province":"Z\u00fcrich",
    "wof:name":"Restaurant Freihof",
    "wof:placetype":"venue"
},
  "geometry": {"coordinates":[8.7232866287,47.3539161682],"type":"Point"}
}