{
  "type": "Feature",
  "properties": {
    "iso:country":"CH",
    "sg:address":"Le Centre 1145 Bi\u00e8re. Postfach",
    "sg:city":"Bi\u00e8re",
    "sg:orig_category":"Fachdetailhandel mit pharmazeutischen Produkten",
    "sg:phone":"+41 21 809 55 47",
    "sg:postcode":"1145",
    "sg:province":"Vaud",
    "wof:name":"Daniel Vocat Pharmacie De Bi\u00e8re",
    "wof:placetype":"venue"
},
  "geometry": {"coordinates":[6.3328051567,46.5380134583],"type":"Point"}
}