{
  "type": "Feature",
  "properties": {
    "iso:country":"CH",
    "sg:address":"Rhypark/rheinweg 4 Schaffhausen 8212 Neuhausen. Postfach",
    "sg:city":"Schaffhausen",
    "sg:orig_category":"Herstellung von Schmuck, Gold U Silberschmiedwaren",
    "sg:phone":"+41 52 643 48 74",
    "sg:postcode":"8200",
    "sg:province":"Schaffhausen",
    "wof:name":"Hochstrasser & Co.",
    "wof:placetype":"venue"
},
  "geometry": {"coordinates":[8.6196098328,47.6815681458],"type":"Point"}
}