{
  "type": "Feature",
  "properties": {
    "iso:country":"CH",
    "sg:address":"Dedelmatt 68 3453 Heimisbach. Postfach",
    "sg:city":"Heimisbach",
    "sg:orig_category":"Fachdetailhandel in Verkaufsr\u00e4umen",
    "sg:postcode":"3453",
    "sg:province":"Bern",
    "wof:name":"Astrolith, Stalder Dominique Schmuck; Herstellung U. Verkauf",
    "wof:placetype":"venue"
},
  "geometry": {"coordinates":[7.7603111267,47.011756897],"type":"Point"}
}