{
  "type": "Feature",
  "properties": {
    "iso:country":"CH",
    "sg:address":"Dottikerstrasse 5 5611 Anglikon. Postfach",
    "sg:city":"Anglikon",
    "sg:orig_category":"Handel mit Automobilen",
    "sg:phone":"+41 55 240 25 25",
    "sg:postcode":"5611",
    "sg:province":"Aargau",
    "wof:name":"Auto Menzi Ag",
    "wof:placetype":"venue"
},
  "geometry": {"coordinates":[8.844909668,47.2565765381],"type":"Point"}
}