{
  "type": "Feature",
  "properties": {
    "iso:country":"CH",
    "sg:address":"Mittlerer Kreis 2",
    "sg:city":"Therwil",
    "sg:orig_category":"Arztpraxen",
    "sg:phone":"+41 79 354 79 31",
    "sg:postcode":"4106",
    "sg:province":"Basel-Landschaft",
    "wof:name":"Dr.med.christoph T. Weidmann Arzt F.allgemeine Medizin Fmh",
    "wof:placetype":"venue"
},
  "geometry": {"coordinates":[7.553018,47.49889],"type":"Point"}
}