{
  "type": "Feature",
  "properties": {
    "iso:country":"CH",
    "sg:address":"Chemin Du Bosquet 4",
    "sg:city":"Cossonay-ville",
    "sg:orig_category":"Einbau von Schreinerwaren",
    "sg:phone":"+41 71 385 13 41",
    "sg:postcode":"1304",
    "sg:province":"Vaud",
    "wof:name":"Moser Paul-j., Schreinerei",
    "wof:placetype":"venue"
},
  "geometry": {"coordinates":[9.2535123825,47.4162712097],"type":"Point"}
}