{
  "type": "Feature",
  "properties": {
    "iso:country":"CH",
    "sg:address":"Route Des Ronquoz 39",
    "sg:city":"Sion",
    "sg:orig_category":"Autogaragen",
    "sg:phone":"+41 27 321 21 05",
    "sg:postcode":"1950",
    "sg:province":"Valais",
    "wof:name":"Garage Cannistra Francesco R\u00e9paration D'autos",
    "wof:placetype":"venue"
},
  "geometry": {"coordinates":[7.361879,46.224525],"type":"Point"}
}