{
  "type": "Feature",
  "properties": {
    "iso:country":"CH",
    "sg:address":"3455",
    "sg:city":"Gr\u00fcnen",
    "sg:orig_category":"Organisationen des Gesundheitswesen",
    "sg:phone":"+41 34 431 42 78",
    "sg:postcode":"3455",
    "sg:province":"Bern",
    "wof:name":"Samariterverein Sumiswald",
    "wof:placetype":"venue"
},
  "geometry": {"coordinates":[7.736893177,47.0250778198],"type":"Point"}
}