{
  "type": "Feature",
  "properties": {
    "iso:country":"CH",
    "sg:address":"Walenseestrasse",
    "sg:city":"Mols",
    "sg:classifiers":[
        {
            "category":"Travel",
            "subcategory":"Hotels & Motels",
            "type":"Entertainment"
        }
    ],
    "sg:phone":"+41 81 738 12 25",
    "sg:postcode":"8885",
    "sg:province":"St. Gallen",
    "sg:tags":[
        "hotels",
        "mit",
        "restaurant"
    ],
    "wof:name":"Hotel Schiffahrt",
    "wof:placetype":"venue"
},
  "geometry": {"coordinates":[9.2764253616,47.1129493713],"type":"Point"}
}