{
  "type": "Feature",
  "properties": {
    "iso:country":"CH",
    "sg:address":"3253",
    "sg:city":"Schnottwil",
    "sg:orig_category":"Bezirks, Sekundar, Realschulen, Oberstufe der Primarschulen",
    "sg:phone":"+41 71 377 19 50",
    "sg:postcode":"3253",
    "sg:province":"Solothurn",
    "wof:name":"Oberstufenschulhaus Baumgarten",
    "wof:placetype":"venue"
},
  "geometry": {"coordinates":[9.18159,47.321461],"type":"Point"}
}