{
  "type": "Feature",
  "properties": {
    "iso:country":"CH",
    "sg:address":"Els\u00e4sserstrasse 184",
    "sg:city":"Basel",
    "sg:classifiers":[
        {
            "category":"Banks & Credit Unions",
            "subcategory":"Bank",
            "type":"Services"
        }
    ],
    "sg:phone":"+41 61 322 58 50",
    "sg:postcode":"4056",
    "sg:province":"Basel-Stadt",
    "wof:name":"Gzb Genossenschaftliche, Zentralbank Ag",
    "wof:placetype":"venue"
},
  "geometry": {"coordinates":[7.574139,47.574924],"type":"Point"}
}