{
  "type": "Feature",
  "properties": {
    "iso:country":"CH",
    "sg:address":"Alte Landstrasse 76",
    "sg:city":"Zollikon",
    "sg:orig_category":"Primarschulen",
    "sg:phone":"+41 13918153",
    "sg:postcode":"8702",
    "sg:province":"Z\u00fcrich",
    "wof:name":"Primarschule Chirchhof",
    "wof:placetype":"venue"
},
  "geometry": {"coordinates":[8.5742082596,47.3386955261],"type":"Point"}
}