{
  "type": "Feature",
  "properties": {
    "iso:country":"CH",
    "sg:address":"Hagartenstrasse 10",
    "sg:city":"Biberist",
    "sg:orig_category":"Zahnarztpraxen",
    "sg:phone":"+41 32 672 32 73",
    "sg:postcode":"4562",
    "sg:province":"Solothurn",
    "wof:name":"Dr. Med. Dent. Rico Calderara Zahnarzt",
    "wof:placetype":"venue"
},
  "geometry": {"coordinates":[7.553440094,47.1805343628],"type":"Point"}
}