{
  "type": "Feature",
  "properties": {
    "iso:country":"CH",
    "sg:address":"Haupstrasse 31",
    "sg:city":"Muttenz",
    "sg:orig_category":"Detailhandel mit Fahrr\u00e4dern Handel mit Motorr\u00e4dern, Teilen U Zubeh\u00f6r Instandhaltung U Reparatur von ",
    "sg:phone":"+41 61 461 29 75",
    "sg:postcode":"4132",
    "sg:province":"Basel-Landschaft",
    "wof:name":"Peter Zeltner Velos/motos",
    "wof:placetype":"venue"
},
  "geometry": {"coordinates":[7.6457538605,47.524181366],"type":"Point"}
}