{
  "type": "Feature",
  "properties": {
    "iso:country":"CH",
    "sg:address":"Weinfelderstrasse 15 8580 Amriswil. Postfach",
    "sg:city":"Amriswil",
    "sg:orig_category":"Pensionskassen",
    "sg:phone":"+41 71 414 24 44",
    "sg:postcode":"8580",
    "sg:province":"Thurgau",
    "wof:name":"Personalstiftung Sallmann Ag",
    "wof:placetype":"venue"
},
  "geometry": {"coordinates":[9.2956752777,47.5452346802],"type":"Point"}
}