{
  "type": "Feature",
  "properties": {
    "iso:country":"CH",
    "sg:address":"Widmenhalde 11",
    "sg:city":"Dietikon",
    "sg:classifiers":[
        {
            "category":"Farming",
            "subcategory":"Aquatic Farm",
            "type":"Manufacturing & Wholesale Goods"
        }
    ],
    "sg:phone":"+41 17459500",
    "sg:postcode":"8953",
    "sg:province":"Z\u00fcrich",
    "sg:tags":[
        "bath-robes"
    ],
    "wof:name":"Symphony Textil Ag",
    "wof:placetype":"venue"
},
  "geometry": {"coordinates":[8.40405,47.400318],"type":"Point"}
}