{
  "type": "Feature",
  "properties": {
    "iso:country":"CH",
    "sg:address":"Via Clemente Maraini 5",
    "sg:city":"Lugano",
    "sg:orig_category":"Finanzierungsinstitutionen",
    "sg:postcode":"6900",
    "sg:province":"Ticino",
    "wof:name":"Bosco Cornea Sa",
    "wof:placetype":"venue"
},
  "geometry": {"coordinates":[8.9477758408,46.0015296936],"type":"Point"}
}