{
  "type": "Feature",
  "properties": {
    "iso:country":"CH",
    "sg:address":"Am Falter 5",
    "sg:city":"Oberwil-lieli",
    "sg:orig_category":"Unternehmensberatung",
    "sg:phone":"+41 56 631 12 09",
    "sg:postcode":"8966",
    "sg:province":"Aargau",
    "wof:name":"Adico Unternehmensberatung",
    "wof:placetype":"venue"
},
  "geometry": {"coordinates":[8.3887348175,47.3380355835],"type":"Point"}
}