{
  "type": "Feature",
  "properties": {
    "iso:country":"CH",
    "sg:address":"8574",
    "sg:city":"Illighausen",
    "sg:classifiers":[
        {
            "category":"Restaurant",
            "type":"Food & Drink"
        }
    ],
    "sg:phone":"+41 19200288",
    "sg:postcode":"8574",
    "sg:province":"Thurgau",
    "wof:name":"Restaurant Sonnenhof",
    "wof:placetype":"venue"
},
  "geometry": {"coordinates":[8.6777038574,47.2625427246],"type":"Point"}
}