{
  "type": "Feature",
  "properties": {
    "iso:country":"CH",
    "sg:address":"5643 Sins. Postfach 19",
    "sg:city":"Sins",
    "sg:orig_category":"Sportvereine Ballsport Fussball",
    "sg:phone":"+41 41 320 08 14",
    "sg:postcode":"5643",
    "sg:province":"Aargau",
    "wof:name":"Fc Sins",
    "wof:placetype":"venue"
},
  "geometry": {"coordinates":[8.3962402344,47.188243866],"type":"Point"}
}