{
  "type": "Feature",
  "properties": {
    "iso:country":"CH",
    "sg:address":"Dorfstrasse 4",
    "sg:city":"Engelberg",
    "sg:orig_category":"Finanzierungsinstitutionen",
    "sg:postcode":"6390",
    "sg:province":"Obwalden",
    "wof:name":"Bondshare Investment Ag",
    "wof:placetype":"venue"
},
  "geometry": {"coordinates":[8.4076871872,46.8212203979],"type":"Point"}
}