{
  "type": "Feature",
  "properties": {
    "iso:country":"CH",
    "sg:address":"Avenue De France 14-20",
    "sg:city":"Sion",
    "sg:orig_category":"Detailhandel mit Waren verschiedener Art, Hauptrichtung Nahrungsmittel",
    "sg:phone":"+41 24 472 61 71",
    "sg:postcode":"1950",
    "sg:province":"Valais",
    "wof:name":"Migros",
    "wof:placetype":"venue"
},
  "geometry": {"coordinates":[6.9517960548,46.2540359497],"type":"Point"}
}