{
  "type": "Feature",
  "properties": {
    "iso:country":"CH",
    "sg:address":"Route De Saint-julien 187",
    "sg:city":"Plan-les-ouates",
    "sg:classifiers":[
        {
            "category":"Restaurant",
            "type":"Food & Drink"
        }
    ],
    "sg:phone":"+41 22 771 10 63",
    "sg:postcode":"1228",
    "sg:province":"Gen\u00e8ve",
    "wof:name":"Auberge Du Tambour Major",
    "wof:placetype":"venue"
},
  "geometry": {"coordinates":[6.1103100777,46.1648445129],"type":"Point"}
}