{
  "type": "Feature",
  "properties": {
    "iso:country":"CH",
    "sg:address":"Rudolf Wackernagel-strasse 86",
    "sg:city":"Riehen",
    "sg:orig_category":"Wirtschaftspr\u00fcfung, Steuerberatung U Treuhand",
    "sg:phone":"+41 61 601 79 97",
    "sg:postcode":"4125",
    "sg:province":"Basel-Stadt",
    "wof:name":"Mrb Treuhand, K\u00e4ser-berto M.",
    "wof:placetype":"venue"
},
  "geometry": {"coordinates":[7.6480331421,47.571182251],"type":"Point"}
}