{
  "type": "Feature",
  "properties": {
    "iso:country":"CH",
    "sg:address":"Industriestrasse 6 3600 Thun. Postfach 1482",
    "sg:city":"Thun",
    "sg:orig_category":"Chemische Industrie R\u00fcckgewinnung U Vorbereitung f\u00fcr die Wiederverwertung Recycling",
    "sg:phone":"+41 33 222 60 14",
    "sg:postcode":"3601",
    "sg:province":"Bern",
    "wof:name":"Tas Ag",
    "wof:placetype":"venue"
},
  "geometry": {"coordinates":[7.613649,46.756779],"type":"Point"}
}