{
  "type": "Feature",
  "properties": {
    "iso:country":"CH",
    "sg:address":"Centro L'uovo Di Manno",
    "sg:city":"Manno",
    "sg:orig_category":"Herstellung von nachrichtentechnischen Ger\u00e4ten U Einrichtungen",
    "sg:phone":"+41 91 600 14 24",
    "sg:postcode":"6928",
    "sg:province":"Ticino",
    "wof:name":"Omnisystem Sa",
    "wof:placetype":"venue"
},
  "geometry": {"coordinates":[8.9201698303,46.029838562],"type":"Point"}
}