{
  "type": "Feature",
  "properties": {
    "iso:country":"CH",
    "sg:address":"Bahnhofstrasse 18 6170 Sch\u00fcpfheim. Postfach 54",
    "sg:city":"Sch\u00fcpfheim",
    "sg:orig_category":"Mineral\u00f6lverarbeitung Tankstellen",
    "sg:phone":"+41 41 484 11 24",
    "sg:postcode":"6170",
    "sg:province":"Luzern",
    "wof:name":"Balmer Ag",
    "wof:placetype":"venue"
},
  "geometry": {"coordinates":[8.0135307312,46.9486656189],"type":"Point"}
}