{
  "type": "Feature",
  "properties": {
    "iso:country":"CH",
    "sg:address":"Via Mulini",
    "sg:city":"Bioggio",
    "sg:orig_category":"Kunststoff- and Kautschukwaren Grosshandel Pneus Grosshandel",
    "sg:phone":"+41 91 605 38 54",
    "sg:postcode":"6934",
    "sg:province":"Ticino",
    "wof:name":"Goodyear Dunlop Tires Suisse Sa",
    "wof:placetype":"venue"
},
  "geometry": {"coordinates":[8.9142141342,46.0094223022],"type":"Point"}
}