{
  "type": "Feature",
  "properties": {
    "iso:country":"CH",
    "sg:address":"H\u00f6h",
    "sg:city":"Heimenschwand",
    "sg:orig_category":"Datenverarbeitungsdienste Unternehmensberatung",
    "sg:phone":"+41 79 422 85 90",
    "sg:postcode":"3615",
    "sg:province":"Bern",
    "wof:name":"Conpro Consulting Ag",
    "wof:placetype":"venue"
},
  "geometry": {"coordinates":[7.696945,46.828621],"type":"Point"}
}