{
  "type": "Feature",
  "properties": {
    "iso:country":"CH",
    "sg:address":"Etzelstrasse 2",
    "sg:city":"Z\u00fcrich",
    "sg:orig_category":"Grosshandel mit sonstigen Maschinen U Ausr\u00fcstungen f\u00fcr Industrie, Handel U Schiffahrt",
    "sg:phone":"+41 13803555",
    "sg:postcode":"8038",
    "sg:province":"Z\u00fcrich",
    "wof:name":"Terlinden Textilpflege Ag",
    "wof:placetype":"venue"
},
  "geometry": {"coordinates":[8.5302410126,47.3442649841],"type":"Point"}
}