{
  "type": "Feature",
  "properties": {
    "iso:country":"CH",
    "sg:address":"Thorbergstrasse 3",
    "sg:city":"Krauchthal",
    "sg:orig_category":"Stukkateurgewerbe, Gipserei U Verputzerei",
    "sg:phone":"+41 34 411 24 33",
    "sg:postcode":"3326",
    "sg:province":"Bern",
    "wof:name":"D\u00fcrig H., Gipser + Maler Ag",
    "wof:placetype":"venue"
},
  "geometry": {"coordinates":[7.5660719872,47.0067749023],"type":"Point"}
}