{
  "type": "Feature",
  "properties": {
    "iso:country":"CH",
    "sg:address":"Spielhofweg 12 8942 Oberrieden. Postfach",
    "sg:city":"Oberrieden",
    "sg:orig_category":"Bau U Wohngenossenschaften",
    "sg:phone":"+41 17202146",
    "sg:postcode":"8942",
    "sg:province":"Z\u00fcrich",
    "wof:name":"Gen.f\u00fcr Alterswohnungen",
    "wof:placetype":"venue"
},
  "geometry": {"coordinates":[8.574383,47.277958],"type":"Point"}
}