{
  "type": "Feature",
  "properties": {
    "iso:country":"CH",
    "sg:address":"Unterg\u00e4ssli 9",
    "sg:city":"Biel/bienne",
    "sg:classifiers":[
        {
            "category":"Restaurant",
            "type":"Food & Drink"
        }
    ],
    "sg:phone":"+41 32 322 34 55",
    "sg:postcode":"2502",
    "sg:province":"Bern",
    "wof:name":"Restaurant Au Vieux Valais",
    "wof:placetype":"venue"
},
  "geometry": {"coordinates":[7.2461810112,47.1413497925],"type":"Point"}
}