{
  "type": "Feature",
  "properties": {
    "iso:country":"CH",
    "sg:address":"Tschumi Rue Adolphe- 3",
    "sg:city":"Gen\u00e8ve",
    "sg:orig_category":"Unclassifiable Establishments",
    "sg:phone":"+41 55 410 19 62",
    "sg:postcode":"1201",
    "sg:province":"Gen\u00e8ve",
    "wof:name":"Dominant Holdings Ag Beteiligungen, Finanzierungen Usw",
    "wof:placetype":"venue"
},
  "geometry": {"coordinates":[8.7796049118,47.2022857666],"type":"Point"}
}