{
  "type": "Feature",
  "properties": {
    "iso:country":"CH",
    "sg:address":"Grand-rue 17",
    "sg:city":"Gen\u00e8ve",
    "sg:orig_category":"Architektur U Ingenieurb\u00fcros Innenarchitekturb\u00fcros",
    "sg:phone":"+41 22 311 97 11",
    "sg:postcode":"1204",
    "sg:province":"Gen\u00e8ve",
    "wof:name":"Structure 17",
    "wof:placetype":"venue"
},
  "geometry": {"coordinates":[6.145522,46.202148],"type":"Point"}
}