{
  "type": "Feature",
  "properties": {
    "iso:country":"CH",
    "sg:address":"Chemin De Pr\u00e9-marquis 1b",
    "sg:city":"Puplinge",
    "sg:orig_category":"Arztpraxen",
    "sg:phone":"+41 26 477 97 97",
    "sg:postcode":"1241",
    "sg:province":"Gen\u00e8ve",
    "wof:name":"Dr M\u00e9d. Rodolphe Thomi M\u00e9decin G\u00e9n\u00e9raliste Fmh",
    "wof:placetype":"venue"
},
  "geometry": {"coordinates":[7.034962,46.753521],"type":"Point"}
}