{
  "type": "Feature",
  "properties": {
    "iso:country":"CH",
    "sg:address":"Ch. Des Leppes 14",
    "sg:city":"Montreux",
    "sg:orig_category":"Dienstleistungen von Beteiligungsgesellschaften",
    "sg:postcode":"1820",
    "sg:province":"Vaud",
    "wof:name":"Borgya S\u00e0rl",
    "wof:placetype":"venue"
},
  "geometry": {"coordinates":[6.888212204,46.4491271973],"type":"Point"}
}