{
  "type": "Feature",
  "properties": {
    "iso:country":"CH",
    "sg:address":"Hauptstrasse 26",
    "sg:city":"Ueken",
    "sg:orig_category":"Autogaragen",
    "sg:phone":"+41 62 871 46 66",
    "sg:postcode":"5028",
    "sg:province":"Aargau",
    "wof:name":"Felix R\u00fcegger Garage",
    "wof:placetype":"venue"
},
  "geometry": {"coordinates":[8.048455,47.485336],"type":"Point"}
}