{
  "type": "Feature",
  "properties": {
    "iso:country":"CH",
    "sg:address":"Weizacker 3",
    "sg:city":"St-ours",
    "sg:orig_category":"G\u00fcterbef\u00f6rderung im Strassenverkehr",
    "sg:phone":"+41 37443059",
    "sg:postcode":"1717",
    "sg:province":"Fribourg",
    "wof:name":"Neuhaus Stephan Transporte",
    "wof:placetype":"venue"
},
  "geometry": {"coordinates":[7.214594841,46.793094635],"type":"Point"}
}