{
  "type": "Feature",
  "properties": {
    "iso:country":"CH",
    "sg:address":"Poststrasse 18",
    "sg:city":"St.gallen",
    "sg:orig_category":"Kauf U Verkauf von Immobilien auf eigene Rechnung",
    "sg:postcode":"9000",
    "sg:province":"St. Gallen",
    "wof:name":"Hintere Poststrasse 16/18/20 Ag",
    "wof:placetype":"venue"
},
  "geometry": {"coordinates":[9.3722600937,47.4245681763],"type":"Point"}
}