{
  "type": "Feature",
  "properties": {
    "iso:country":"CH",
    "sg:address":"Sch\u00fctzenstrasse 77 6438 Ibach. Postfach",
    "sg:city":"Ibach",
    "sg:orig_category":"Museen",
    "sg:phone":"+41 41 810 36 20",
    "sg:postcode":"6438",
    "sg:province":"Schwyz",
    "wof:name":"Galerie Zur Hammerm\u00fchle, Mirer Hanni",
    "wof:placetype":"venue"
},
  "geometry": {"coordinates":[8.6506090164,47.0158195496],"type":"Point"}
}