{
  "type": "Feature",
  "properties": {
    "iso:country":"CH",
    "sg:address":"Rebhaldenweg 14",
    "sg:city":"M\u00e4nnedorf",
    "sg:orig_category":"Sonstiger Grosshandel",
    "sg:phone":"+41 1201935",
    "sg:postcode":"8708",
    "sg:province":"Z\u00fcrich",
    "wof:name":"Forma Danica, Poul V. Kamp",
    "wof:placetype":"venue"
},
  "geometry": {"coordinates":[8.6981964111,47.2529640198],"type":"Point"}
}