{
  "type": "Feature",
  "properties": {
    "iso:country":"CH",
    "sg:address":"Lisone",
    "sg:city":"Cademario",
    "sg:classifiers":[
        {
            "category":"Travel",
            "subcategory":"Hotels & Motels",
            "type":"Entertainment"
        }
    ],
    "sg:phone":"+41 91 605 22 36",
    "sg:postcode":"6936",
    "sg:province":"Ticino",
    "sg:tags":[
        "hotels",
        "mit",
        "restaurant"
    ],
    "wof:name":"Kurhaus Cacciatori",
    "wof:placetype":"venue"
},
  "geometry": {"coordinates":[8.8894739151,46.0216598511],"type":"Point"}
}