{
  "type": "Feature",
  "properties": {
    "iso:country":"CH",
    "sg:address":"1041",
    "sg:city":"Poliez-le-grand",
    "sg:orig_category":"Sonstige mit der Informatik verbundene T\u00e4tigkeiten",
    "sg:phone":"+41 79 250 10 43",
    "sg:postcode":"1041",
    "sg:province":"Vaud",
    "wof:name":"Orix Pc Assistance, Rolf Weiss",
    "wof:placetype":"venue"
},
  "geometry": {"coordinates":[6.6645698547,46.6371917725],"type":"Point"}
}