{
  "type": "Feature",
  "properties": {
    "iso:country":"CH",
    "sg:address":"Fischrain 64 3063 Ittigen. Postfach",
    "sg:city":"Ittigen",
    "sg:orig_category":"Fotografische Ateliers Sonstiges Druckgewerbe",
    "sg:postcode":"3063",
    "sg:province":"Bern",
    "wof:name":"Peter Schmid Foto & Design",
    "wof:placetype":"venue"
},
  "geometry": {"coordinates":[8.7164869308,47.2713050842],"type":"Point"}
}