{
  "type": "Feature",
  "properties": {
    "iso:country":"CH",
    "sg:address":"Walligrund 3931 Eyholz. Postfach 14",
    "sg:city":"Eyholz",
    "sg:orig_category":"Einzelhandel mit Automobilteilen U Zubeh\u00f6r Instandhaltung U Reparatur von Automobilen",
    "sg:phone":"+41 56 631 96 56",
    "sg:postcode":"3931",
    "sg:province":"Valais",
    "wof:name":"Garage Zubler Erich",
    "wof:placetype":"venue"
},
  "geometry": {"coordinates":[8.3199033737,47.3591003418],"type":"Point"}
}