{
  "type": "Feature",
  "properties": {
    "iso:country":"CH",
    "sg:address":"Zweierstrasse 35",
    "sg:city":"Z\u00fcrich",
    "sg:orig_category":"Geb\u00e4ude, Wohnungsreinigung",
    "sg:phone":"+41 12419840",
    "sg:postcode":"8004",
    "sg:province":"Z\u00fcrich",
    "wof:name":"Office Clean Ag Reinigungsinstitut",
    "wof:placetype":"venue"
},
  "geometry": {"coordinates":[8.5256214142,47.3726348877],"type":"Point"}
}