{
  "type": "Feature",
  "properties": {
    "iso:country":"CH",
    "sg:address":"5728",
    "sg:city":"Gontenschwil",
    "sg:orig_category":"Museen",
    "sg:phone":"+41 79 622 35 83",
    "sg:postcode":"5728",
    "sg:province":"Aargau",
    "wof:name":"Museum Herrn Kurt Gautschi",
    "wof:placetype":"venue"
},
  "geometry": {"coordinates":[8.1438541412,47.2799186707],"type":"Point"}
}