{
  "type": "Feature",
  "properties": {
    "iso:country":"CH",
    "sg:address":"M\u00fchlebachstrasse 36",
    "sg:city":"Thalwil",
    "sg:orig_category":"RESTAURANTS: TEA-ROOMS",
    "sg:phone":"+41 77464760",
    "sg:postcode":"8800",
    "sg:province":"Z\u00fcrich",
    "wof:name":"Anri Gmbh",
    "wof:placetype":"venue"
},
  "geometry": {"coordinates":[8.344078064,47.3511047363],"type":"Point"}
}