{
  "type": "Feature",
  "properties": {
    "addr:full":"Lohn-ammannsegg Solothurn 4573",
    "addr:postcode":"4573",
    "iso:country":"CH",
    "sg:city":"Lohn-ammannsegg",
    "sg:orig_category":"Industrie, Chemie U Biologie",
    "sg:phone":"+41 32 677 14 88",
    "sg:postcode":"4573",
    "sg:province":"Solothurn",
    "wof:name":"Solva Chemie Ag",
    "wof:placetype":"venue"
},
  "geometry": {"coordinates":[7.524811,47.169815],"type":"Point"}
}