{
  "type": "Feature",
  "properties": {
    "iso:country":"CH",
    "sg:address":"Rue Oscar-huguenin 1",
    "sg:city":"Boudry",
    "sg:orig_category":"Detailhandel mit Damenbekleidung Fachdetailhandel in Verkaufsr\u00e4umen",
    "sg:phone":"+41 32 842 26 79",
    "sg:postcode":"2017",
    "sg:province":"Neuch\u00e2tel",
    "wof:name":"Dubois Francine",
    "wof:placetype":"venue"
},
  "geometry": {"coordinates":[6.8380031586,46.9494857788],"type":"Point"}
}