{
  "type": "Feature",
  "properties": {
    "iso:country":"CH",
    "sg:address":"Amriswilerstrasse 16a",
    "sg:city":"Romanshorn",
    "sg:orig_category":"Unclassifiable Establishments",
    "sg:postcode":"8590",
    "sg:province":"Thurgau",
    "wof:name":"Zysset Design",
    "wof:placetype":"venue"
},
  "geometry": {"coordinates":[9.3620500565,47.5649185181],"type":"Point"}
}