{
  "type": "Feature",
  "properties": {
    "iso:country":"CH",
    "sg:address":"Untere Br\u00fchlstrasse 39",
    "sg:city":"Zofingen",
    "sg:orig_category":"Kaminfeger",
    "sg:phone":"+41 79 332 96 83",
    "sg:postcode":"4800",
    "sg:province":"Aargau",
    "wof:name":"Urs Husner Kaminfegermeister",
    "wof:placetype":"venue"
},
  "geometry": {"coordinates":[7.93045187,47.2972106934],"type":"Point"}
}