{
  "type": "Feature",
  "properties": {
    "iso:country":"CH",
    "sg:address":"Alte Birmenstorferstrasse 5",
    "sg:city":"Fislisbach",
    "sg:orig_category":"Grosshandel mit Nahrungsmitteln, Getr\u00e4nken U Tabakwaren ohne ausgepr\u00e4gten Schwerpunkt Verarbeitung v",
    "sg:phone":"+41 41 850 10 14",
    "sg:postcode":"5442",
    "sg:province":"Aargau",
    "wof:name":"Dober, Lebensmittel Und Molkerei",
    "wof:placetype":"venue"
},
  "geometry": {"coordinates":[8.440114975,47.0809936523],"type":"Point"}
}