{
  "type": "Feature",
  "properties": {
    "iso:country":"CH",
    "sg:address":"Weidstrasse 9",
    "sg:city":"Rotkreuz",
    "sg:orig_category":"Vereine Fasnacht",
    "sg:phone":"+41 41 790 20 83",
    "sg:postcode":"6343",
    "sg:province":"Zug",
    "wof:name":"Guggenmusik Ohregr\u00f6bler",
    "wof:placetype":"venue"
},
  "geometry": {"coordinates":[8.430970192,47.1360015869],"type":"Point"}
}