{
  "type": "Feature",
  "properties": {
    "iso:country":"CH",
    "sg:address":"Mouline Rue De La 4",
    "sg:city":"Chavannes-renens",
    "sg:orig_category":"Ger\u00fcstbau Sonstiger spezialisierter Hoch U Tiefbau",
    "sg:phone":"+41 62 771 72 42",
    "sg:postcode":"1022",
    "sg:province":"Vaud",
    "wof:name":"Hurschler Franz Ger\u00fcstbau",
    "wof:placetype":"venue"
},
  "geometry": {"coordinates":[8.1684350967,47.2521514893],"type":"Point"}
}