{
  "type": "Feature",
  "properties": {
    "iso:country":"CH",
    "sg:address":"Utengasse 20",
    "sg:city":"Basel",
    "sg:orig_category":"Unclassifiable Establishments",
    "sg:postcode":"4058",
    "sg:province":"Basel-Stadt",
    "wof:name":"Silberfisch, Lea Wittmer",
    "wof:placetype":"venue"
},
  "geometry": {"coordinates":[7.5926117897,47.5602684021],"type":"Point"}
}