{
  "type": "Feature",
  "properties": {
    "iso:country":"CH",
    "sg:address":"Via Vincenzo Vela 21",
    "sg:city":"Mendrisio",
    "sg:orig_category":"W\u00e4scherei U chemische Reinigung",
    "sg:phone":"+41 91 646 30 68",
    "sg:postcode":"6850",
    "sg:province":"Ticino",
    "wof:name":"Baldassare & Francesca Nastasi Lavanderia",
    "wof:placetype":"venue"
},
  "geometry": {"coordinates":[8.9864006042,45.8722648621],"type":"Point"}
}