{
  "type": "Feature",
  "properties": {
    "addr:full":"Sch\u00fctzenweg 75 Laufen Basel-Landschaft 4242",
    "addr:housenumber":"75",
    "addr:postcode":"4242",
    "addr:street":"Schuetzenweg",
    "iso:country":"CH",
    "sg:address":"Sch\u00fctzenweg 75",
    "sg:city":"Laufen",
    "sg:orig_category":"Allgemeiner Hoch U Tiefbau",
    "sg:phone":"+41 21 922 18 58",
    "sg:postcode":"4242",
    "sg:province":"Basel-Landschaft",
    "wof:name":"Fibre Lac Sa",
    "wof:placetype":"venue"
},
  "geometry": {"coordinates":[5.18087,45.897339],"type":"Point"}
}