{
  "type": "Feature",
  "properties": {
    "iso:country":"CH",
    "sg:address":"Bleicherweg 39",
    "sg:city":"Z\u00fcrich",
    "sg:orig_category":"Non-Classified Establishments",
    "sg:phone":"+41 12859093",
    "sg:postcode":"8001",
    "sg:province":"Z\u00fcrich",
    "wof:name":"Besfin Ag",
    "wof:placetype":"venue"
},
  "geometry": {"coordinates":[8.5379171371,47.3687667847],"type":"Point"}
}