{
  "type": "Feature",
  "properties": {
    "iso:country":"CH",
    "sg:address":"Rosenstr. 8",
    "sg:city":"G\u00fcttingen",
    "sg:orig_category":"Grosshandel mit Getr\u00e4nken",
    "sg:phone":"+41 71 695 10 82",
    "sg:postcode":"8594",
    "sg:province":"Thurgau",
    "wof:name":"Hsg Hans Schibli",
    "wof:placetype":"venue"
},
  "geometry": {"coordinates":[9.2913780212,47.6037940979],"type":"Point"}
}