{
  "type": "Feature",
  "properties": {
    "addr:full":"G\u00fcterstrasse 1a Grenchen Solothurn 2540",
    "addr:housenumber":"1a",
    "addr:postcode":"2540",
    "addr:street":"Gueterstrasse",
    "iso:country":"CH",
    "sg:address":"G\u00fcterstrasse 1a",
    "sg:city":"Grenchen",
    "sg:orig_category":"Architektur U Ingenieurb\u00fcros",
    "sg:phone":"+41 32 377 33 44",
    "sg:postcode":"2540",
    "sg:province":"Solothurn",
    "wof:name":"R\u00fcegg Ingenieurb\u00fcro Gmbh",
    "wof:placetype":"venue"
},
  "geometry": {"coordinates":[7.401107,47.189819],"type":"Point"}
}