{
  "type": "Feature",
  "properties": {
    "iso:country":"CH",
    "sg:address":"Obere Halde 33",
    "sg:city":"Baden",
    "sg:orig_category":"Grosshandel mit Getr\u00e4nken",
    "sg:phone":"+41 56 222 56 66",
    "sg:postcode":"5400",
    "sg:province":"Aargau",
    "wof:name":"Corti's Schweizer Haus-weine Gmbh",
    "wof:placetype":"venue"
},
  "geometry": {"coordinates":[8.3090801239,47.4728546143],"type":"Point"}
}