{
  "type": "Feature",
  "properties": {
    "iso:country":"CH",
    "sg:address":"L\u00e4rchenweg 5",
    "sg:city":"Hombrechtikon",
    "sg:classifiers":[
        {
            "category":"Professional",
            "subcategory":"Advertising",
            "type":"Services"
        }
    ],
    "sg:phone":"+41 55 244 42 42",
    "sg:postcode":"8634",
    "sg:province":"Z\u00fcrich",
    "sg:tags":[
        "agency"
    ],
    "wof:name":"Monnin Ag Werbeagentur Jjm",
    "wof:placetype":"venue"
},
  "geometry": {"coordinates":[8.76694,47.250534],"type":"Point"}
}