{
  "type": "Feature",
  "properties": {
    "iso:country":"CH",
    "sg:address":"Untere Roostmatt 8",
    "sg:city":"Zug",
    "sg:orig_category":"Vermietung U Verpachtung von eigenen Immobilien",
    "sg:postcode":"6300",
    "sg:province":"Zug",
    "wof:name":"Confida Vertriebs Und Verwaltung Gmbh",
    "wof:placetype":"venue"
},
  "geometry": {"coordinates":[8.5120000839,47.1567726135],"type":"Point"}
}