{
  "type": "Feature",
  "properties": {
    "iso:country":"CH",
    "sg:address":"Via Birreria 6500 Bellinzona. Postfach",
    "sg:city":"Bellinzona",
    "sg:orig_category":"RESTAURANTS: TEA-ROOMS",
    "sg:phone":"+41 91 825 16 95",
    "sg:postcode":"6503",
    "sg:province":"Ticino",
    "wof:name":"Delc\u00f2 Raffaele",
    "wof:placetype":"venue"
},
  "geometry": {"coordinates":[9.0086431503,46.1956710815],"type":"Point"}
}