{
  "type": "Feature",
  "properties": {
    "iso:country":"CH",
    "sg:address":"Avenue Du G\u00e9n\u00e9ral Guisan 28",
    "sg:city":"Sierre",
    "sg:orig_category":"Detailhandel mit Radio U Fernsehger\u00e4ten Detailhandel mit fotografischen Artikeln",
    "sg:phone":"+41 27 456 85 11",
    "sg:postcode":"3960",
    "sg:province":"Valais",
    "wof:name":"Interdiscount Ag Hi-fi Video Photo Radio",
    "wof:placetype":"venue"
},
  "geometry": {"coordinates":[7.5299930573,46.2923355103],"type":"Point"}
}