{
  "type": "Feature",
  "properties": {
    "iso:country":"CH",
    "sg:address":"Seefeldstrasse 224",
    "sg:city":"Z\u00fcrich",
    "sg:orig_category":"Unternehmensberatung",
    "sg:phone":"+41 55 214 41 56",
    "sg:postcode":"8008",
    "sg:province":"Z\u00fcrich",
    "wof:name":"Tcg Tan Consulting Group Gmbh Informatik",
    "wof:placetype":"venue"
},
  "geometry": {"coordinates":[8.8324222565,47.2320594788],"type":"Point"}
}