{
  "type": "Feature",
  "properties": {
    "iso:country":"CH",
    "sg:address":"Pr\u00e9 Des Hirondelles",
    "sg:city":"Cudrefin",
    "sg:orig_category":"Fahrschulen, Flugschulen",
    "sg:phone":"+41 79 679 77 77",
    "sg:postcode":"1588",
    "sg:province":"Vaud",
    "wof:name":"Jean-marie Calame-rosset Auto-\u00e9cole",
    "wof:placetype":"venue"
},
  "geometry": {"coordinates":[7.0185198784,46.9558601379],"type":"Point"}
}