{
  "type": "Feature",
  "properties": {
    "iso:country":"CH",
    "sg:address":"Belchenstrasse 22",
    "sg:city":"Fisibach",
    "sg:orig_category":"Vorschulen, Kinderg\u00e4rten",
    "sg:phone":"+41 18582414",
    "sg:postcode":"5467",
    "sg:province":"Aargau",
    "wof:name":"Kindergarten",
    "wof:placetype":"venue"
},
  "geometry": {"coordinates":[8.4009771347,47.5626029968],"type":"Point"}
}