{
  "type": "Feature",
  "properties": {
    "iso:country":"CH",
    "sg:address":"Furkastrasse 116",
    "sg:city":"Naters",
    "sg:orig_category":"Elektrizit\u00e4tsversorgung Herstellung von Elektrizit\u00e4tsverteilungs U schalteinrichtungen",
    "sg:phone":"+41 27 923 23 78",
    "sg:postcode":"3904",
    "sg:province":"Valais",
    "wof:name":"Kalbermatter Jean Ag",
    "wof:placetype":"venue"
},
  "geometry": {"coordinates":[8.0088596344,46.3272285461],"type":"Point"}
}