{
  "type": "Feature",
  "properties": {
    "iso:country":"CH",
    "sg:address":"Nelkenstrasse 51 2502 Biel/bienne. Postfach",
    "sg:city":"Biel/bienne",
    "sg:orig_category":"Unternehmensberatung",
    "sg:phone":"+41 32 342 11 77",
    "sg:postcode":"2502",
    "sg:province":"Bern",
    "wof:name":"Uebelhart Beat Consulting + Coaching",
    "wof:placetype":"venue"
},
  "geometry": {"coordinates":[7.2565097809,47.1432113647],"type":"Point"}
}