{
  "type": "Feature",
  "properties": {
    "iso:country":"CH",
    "sg:address":"Marktgasse 4",
    "sg:city":"Basel",
    "sg:classifiers":[
        {
            "category":"Restaurant",
            "type":"Food & Drink"
        }
    ],
    "sg:phone":"+41 55 644 14 70",
    "sg:postcode":"4051",
    "sg:province":"Basel-Stadt",
    "wof:name":"Restaurant B\u00fchl",
    "wof:placetype":"venue"
},
  "geometry": {"coordinates":[9.0576295853,46.9820785522],"type":"Point"}
}