{
  "type": "Feature",
  "properties": {
    "iso:country":"CH",
    "sg:address":"Parkstrasse 15",
    "sg:city":"Baden",
    "sg:orig_category":"Sportvereine Ballsport Volleyball",
    "sg:phone":"+41 12622630",
    "sg:postcode":"5400",
    "sg:province":"Aargau",
    "wof:name":"Volleyball-club Sv Z\u00fcrich",
    "wof:placetype":"venue"
},
  "geometry": {"coordinates":[8.3088312149,47.4785881042],"type":"Point"}
}