{
  "type": "Feature",
  "properties": {
    "iso:country":"CH",
    "sg:address":"Av. De Beaumont 4",
    "sg:city":"Fribourg",
    "sg:orig_category":"Non-Classified Establishments",
    "sg:postcode":"1700",
    "sg:province":"Fribourg",
    "wof:name":"Orient-yverdon C. \u00e0 Fribourg",
    "wof:placetype":"venue"
},
  "geometry": {"coordinates":[7.1447172165,46.7961044312],"type":"Point"}
}