{
  "type": "Feature",
  "properties": {
    "iso:country":"CH",
    "sg:address":"Vorstadt 32",
    "sg:city":"Zug",
    "sg:orig_category":"Grosshandel mit medizinischen U orthop\u00e4dischen Artikeln Herstellung von medizinischen U chirurgische",
    "sg:phone":"+41 41 710 27 17",
    "sg:postcode":"6300",
    "sg:province":"Zug",
    "wof:name":"Mpt Medical Products Trading Ag",
    "wof:placetype":"venue"
},
  "geometry": {"coordinates":[8.5143957138,47.1694755554],"type":"Point"}
}