{
  "type": "Feature",
  "properties": {
    "iso:country":"CH",
    "sg:address":"Meiefeldstrasse 13",
    "sg:city":"Burgdorf",
    "sg:orig_category":"Baugewerbe Herstellung von Metallkonstruktionen",
    "sg:phone":"+41 34 422 14 12",
    "sg:postcode":"3400",
    "sg:province":"Bern",
    "wof:name":"Profex Technik Gmbh",
    "wof:placetype":"venue"
},
  "geometry": {"coordinates":[7.608085,47.061508],"type":"Point"}
}