{
  "type": "Feature",
  "properties": {
    "iso:country":"CH",
    "sg:address":"Papierm\u00fchlestrasse 50",
    "sg:city":"Bern",
    "sg:classifiers":[
        {
            "category":"Restaurant",
            "type":"Food & Drink"
        }
    ],
    "sg:phone":"+41 31 331 80 28",
    "sg:postcode":"3014",
    "sg:province":"Bern",
    "wof:name":"Restaurant Festhalle",
    "wof:placetype":"venue"
},
  "geometry": {"coordinates":[7.4641981125,46.9594573975],"type":"Point"}
}