{
  "type": "Feature",
  "properties": {
    "iso:country":"CH",
    "sg:address":"Saurenhorn 265",
    "sg:city":"Sch\u00fcpfen",
    "sg:orig_category":"Bauschreinerei Zimmerei, Dachdeckerei, Bauspenglerei U Abdichtung",
    "sg:phone":"+41 31 879 19 15",
    "sg:postcode":"3054",
    "sg:province":"Bern",
    "wof:name":"Schenk Peter, Holzbau",
    "wof:placetype":"venue"
},
  "geometry": {"coordinates":[7.342345,47.031731],"type":"Point"}
}