{
  "type": "Feature",
  "properties": {
    "iso:country":"CH",
    "sg:address":"Rothb\u00fcndtweg",
    "sg:city":"Wermatswil",
    "sg:orig_category":"Vereine Quartier",
    "sg:postcode":"8615",
    "sg:province":"Z\u00fcrich",
    "wof:name":"Dorfverein Wermatswil",
    "wof:placetype":"venue"
},
  "geometry": {"coordinates":[8.7478523254,47.3624343872],"type":"Point"}
}