{
  "type": "Feature",
  "properties": {
    "iso:country":"CH",
    "sg:address":"Baslerstrasse 78",
    "sg:city":"Trimbach",
    "sg:orig_category":"Detailhandel mit Beleuchtungs U Haushaltsgegenst\u00e4nden Elektroinstallation",
    "sg:phone":"+41 62 293 30 30",
    "sg:postcode":"4632",
    "sg:province":"Solothurn",
    "wof:name":"Rolf Emch",
    "wof:placetype":"venue"
},
  "geometry": {"coordinates":[7.899856,47.361221],"type":"Point"}
}