{
  "type": "Feature",
  "properties": {
    "iso:country":"CH",
    "sg:address":"Spalenring 139 4055 Basel. Postfach",
    "sg:city":"Basel",
    "sg:orig_category":"Architekturb\u00fcros Innenarchitekturb\u00fcros",
    "sg:phone":"+41 61 271 01 40",
    "sg:postcode":"4027",
    "wof:name":"Hans Ammann",
    "wof:placetype":"venue"
},
  "geometry": {"coordinates":[7.576084,47.555225],"type":"Point"}
}