{
  "type": "Feature",
  "properties": {
    "iso:country":"CH",
    "sg:address":"Regensdorferstrasse 190",
    "sg:city":"Z\u00fcrich",
    "sg:orig_category":"Interessenvertretungen Sonderschulen",
    "sg:phone":"+41 13420208",
    "sg:postcode":"8049",
    "sg:province":"Z\u00fcrich",
    "wof:name":"Prima Sonderschulung",
    "wof:placetype":"venue"
},
  "geometry": {"coordinates":[8.4839744568,47.4132041931],"type":"Point"}
}