{
  "type": "Feature",
  "properties": {
    "iso:country":"CH",
    "sg:address":"Croix-blanche Rte De La 38 1066 Epalinges. Postfach",
    "sg:city":"Epalinges",
    "sg:orig_category":"Handels-H\u00e4user U Gesellschaften",
    "sg:postcode":"1066",
    "sg:province":"Vaud",
    "wof:name":"La Bo\u00eete \u00e0 Ch\u00e2teaux, Pittet P. Courtage Immobilier Etc",
    "wof:placetype":"venue"
},
  "geometry": {"coordinates":[6.6727600098,46.5479125977],"type":"Point"}
}