{
  "type": "Feature",
  "properties": {
    "iso:country":"CH",
    "sg:address":"Envol Rue De L' 13",
    "sg:city":"Sion",
    "sg:orig_category":"Betrieb von Taxis",
    "sg:phone":"+41 27 322 44 55",
    "sg:postcode":"1950",
    "sg:province":"Valais",
    "wof:name":"Taxis Lanthemann Transport De Personnes",
    "wof:placetype":"venue"
},
  "geometry": {"coordinates":[7.3634,46.236698],"type":"Point"}
}