{
  "type": "Feature",
  "properties": {
    "iso:country":"CH",
    "sg:address":"St-randoald Rue 5",
    "sg:city":"Montagne-moutier",
    "sg:orig_category":"Sonstige mit der Informatik verbundene T\u00e4tigkeiten",
    "sg:phone":"+41 79 335 85 65",
    "sg:postcode":"2740",
    "sg:province":"Bern",
    "wof:name":"Catseye L'oeil De L'expert S\u00e0rl",
    "wof:placetype":"venue"
},
  "geometry": {"coordinates":[7.3609480858,47.2778434753],"type":"Point"}
}