{
  "type": "Feature",
  "properties": {
    "iso:country":"CH",
    "sg:address":"Grand'place 14",
    "sg:city":"Fribourg",
    "sg:orig_category":"Non-Classified Establishments",
    "sg:postcode":"1700",
    "sg:province":"Fribourg",
    "wof:name":"Loginvest Sa",
    "wof:placetype":"venue"
},
  "geometry": {"coordinates":[7.1648077965,46.8054084778],"type":"Point"}
}