{
  "type": "Feature",
  "properties": {
    "iso:country":"CH",
    "sg:address":"Les Cruz 1180 Rolle Case Postale 199",
    "sg:city":"Rolle",
    "sg:orig_category":"Grosshandel mit Getr\u00e4nken",
    "sg:postcode":"1180",
    "sg:province":"Vaud",
    "wof:name":"Cave De La Bornettaz",
    "wof:placetype":"venue"
},
  "geometry": {"coordinates":[6.3295588493,46.4619026184],"type":"Point"}
}