{
  "type": "Feature",
  "properties": {
    "iso:country":"CH",
    "sg:address":"Hohenkr\u00e4henstrasse 19",
    "sg:city":"Schaffhausen",
    "sg:orig_category":"Kauf U Verkauf von Immobilien auf eigene Rechnung",
    "sg:postcode":"8200",
    "sg:province":"Schaffhausen",
    "wof:name":"Platte Ag",
    "wof:placetype":"venue"
},
  "geometry": {"coordinates":[8.6463050842,47.7002487183],"type":"Point"}
}