{
  "type": "Feature",
  "properties": {
    "iso:country":"CH",
    "sg:address":"Dorfplatz 6",
    "sg:city":"Schwarzenburg",
    "sg:orig_category":"Interessenvertretungen",
    "sg:phone":"+41 31 731 01 00",
    "sg:postcode":"3150",
    "sg:province":"Bern",
    "wof:name":"Detaillistenverein Schwarzenburg Und Umgebung",
    "wof:placetype":"venue"
},
  "geometry": {"coordinates":[7.3413500786,46.8176803589],"type":"Point"}
}