{
  "type": "Feature",
  "properties": {
    "iso:country":"CH",
    "sg:address":"Leiernstrasse 3",
    "sg:city":"Sch\u00fcpfen",
    "sg:orig_category":"Detailhandel mit Brot, Back U S\u00fcsswaren",
    "sg:phone":"+41 31 879 22 00",
    "sg:postcode":"3054",
    "sg:province":"Bern",
    "wof:name":"Paul & Helga Burkhard B\u00e4ckerei-konditorei",
    "wof:placetype":"venue"
},
  "geometry": {"coordinates":[7.379398,47.041245],"type":"Point"}
}