{
  "type": "Feature",
  "properties": {
    "iso:country":"CH",
    "sg:address":"Rheinstrasse 6",
    "sg:city":"Diepoldsau",
    "sg:orig_category":"Herstellung von industriellen Prozesssteuerungsanlagen",
    "sg:postcode":"9444",
    "sg:province":"St. Gallen",
    "wof:name":"Haller & Co. Steuerungsbau Gmbh",
    "wof:placetype":"venue"
},
  "geometry": {"coordinates":[9.6616544724,47.3883514404],"type":"Point"}
}