{
  "type": "Feature",
  "properties": {
    "addr:full":"M\u00fchlegasse 33 8001 Z\u00fcrich. Postfach Z\u00fcrich 8025",
    "addr:housenumber":"33",
    "addr:postcode":"8001 zuerich. postfach;8025",
    "addr:street":"Muehlegasse",
    "iso:country":"CH",
    "sg:address":"M\u00fchlegasse 33 8001 Z\u00fcrich. Postfach",
    "sg:city":"Z\u00fcrich",
    "sg:orig_category":"Advokaturb\u00fcros",
    "sg:phone":"+41 12513121",
    "sg:postcode":"8025",
    "wof:name":"Kranich & Gruenberg Advokaturb\u00fcro",
    "wof:placetype":"venue"
},
  "geometry": {"coordinates":[8.545451,47.374615],"type":"Point"}
}