{
  "type": "Feature",
  "properties": {
    "iso:country":"CH",
    "sg:address":"Rue Oscar-huguenin 10",
    "sg:city":"Boudry",
    "sg:orig_category":"Detailhandel mit Waren verschiedener Art, Hauptrichtung Nahrungsmittel",
    "sg:phone":"+41 32 842 62 82",
    "sg:postcode":"2017",
    "sg:province":"Neuch\u00e2tel",
    "wof:name":"Migros",
    "wof:placetype":"venue"
},
  "geometry": {"coordinates":[6.8373007774,46.9501228333],"type":"Point"}
}