{
  "type": "Feature",
  "properties": {
    "iso:country":"CH",
    "sg:address":"Frobenstrasse 75",
    "sg:city":"Basel",
    "sg:classifiers":[
        {
            "category":"Autos & Motor Vehicles",
            "subcategory":"Auto Supplies",
            "type":"Retail Goods"
        }
    ],
    "sg:phone":"+41 61 271 72 22",
    "sg:postcode":"4053",
    "sg:province":"Basel-Stadt",
    "sg:tags":[
        "lamp",
        "fog"
    ],
    "wof:name":"Mitralux International Ag",
    "wof:placetype":"venue"
},
  "geometry": {"coordinates":[7.5849208832,47.5433197021],"type":"Point"}
}