{
  "type": "Feature",
  "properties": {
    "iso:country":"CH",
    "sg:address":"Morges Rue De 23",
    "sg:city":"Crissier",
    "sg:orig_category":"Non-Classified Establishments",
    "sg:phone":"+41 55 410 25 26",
    "sg:postcode":"1023",
    "sg:province":"Vaud",
    "wof:name":"Mcdonald's-drive-in Restaurant Autobahnrestaurant N3",
    "wof:placetype":"venue"
},
  "geometry": {"coordinates":[8.7244729996,47.1969032288],"type":"Point"}
}