{
  "type": "Feature",
  "properties": {
    "iso:country":"CH",
    "sg:address":"Vorstadt 8 8200 Schaffhausen. Postfach",
    "sg:city":"Schaffhausen",
    "sg:orig_category":"Unclassifiable Establishments",
    "sg:postcode":"8203",
    "sg:province":"Schaffhausen",
    "wof:name":"Intellectual Capital Management Ag",
    "wof:placetype":"venue"
},
  "geometry": {"coordinates":[8.6339912415,47.6976356506],"type":"Point"}
}