{
  "type": "Feature",
  "properties": {
    "iso:country":"CH",
    "sg:address":"Vieux-pont Rue Du 25",
    "sg:city":"Bulle",
    "sg:orig_category":"Zimmerei, Dachdeckerei, Bauspenglerei U Abdichtung",
    "sg:phone":"+41 24 492 25 02",
    "sg:postcode":"1630",
    "sg:province":"Fribourg",
    "wof:name":"Charpente 2000 S\u00e0rl",
    "wof:placetype":"venue"
},
  "geometry": {"coordinates":[7.1565098763,46.3527908325],"type":"Point"}
}