{
  "type": "Feature",
  "properties": {
    "iso:country":"CH",
    "sg:address":"Zentralstr. 7",
    "sg:city":"Luzern",
    "sg:classifiers":[
        {
            "category":"Professional",
            "subcategory":"Computer Services",
            "type":"Services"
        }
    ],
    "sg:phone":"+41 41 227 52 27",
    "sg:postcode":"6002",
    "sg:province":"Luzern",
    "sg:tags":[
        "information",
        "technology",
        "software"
    ],
    "wof:name":"Cpc Argus Internationale Ag",
    "wof:placetype":"venue"
},
  "geometry": {"coordinates":[8.3043746948,47.0495452881],"type":"Point"}
}