{
  "type": "Feature",
  "properties": {
    "iso:country":"CH",
    "sg:address":"Piazza Nosetto",
    "sg:city":"Bellinzona",
    "sg:orig_category":"Fachdetailhandel mit pharmazeutischen Produkten",
    "sg:phone":"+41 91 648 22 44",
    "sg:postcode":"6500",
    "sg:province":"Ticino",
    "wof:name":"Farmacia Neuroni Sa",
    "wof:placetype":"venue"
},
  "geometry": {"coordinates":[8.9712247849,45.9057006836],"type":"Point"}
}