{
  "type": "Feature",
  "properties": {
    "iso:country":"CH",
    "sg:address":"Bahnhofstrasse 20 3296 Arch. Postfach 30",
    "sg:city":"Arch",
    "sg:orig_category":"Allgemeiner Hochbau Strassenbau",
    "sg:phone":"+41 79 444 72 88",
    "sg:postcode":"3296",
    "sg:province":"Bern",
    "wof:name":"Werner Ryter Bauunternehmung",
    "wof:placetype":"venue"
},
  "geometry": {"coordinates":[7.41906,47.165031],"type":"Point"}
}