{
  "type": "Feature",
  "properties": {
    "iso:country":"CH",
    "sg:address":"Bahnhofstrasse 37",
    "sg:city":"Landquart",
    "sg:orig_category":"Versicherungen Hauptagenturen",
    "sg:phone":"+41 81 300 02 77",
    "sg:postcode":"7302",
    "sg:province":"Graubunden",
    "wof:name":"National-versicherung Hauptagentur",
    "wof:placetype":"venue"
},
  "geometry": {"coordinates":[9.55975914,46.9680900574],"type":"Point"}
}