{
  "type": "Feature",
  "properties": {
    "iso:country":"CH",
    "sg:address":"Sattelstrasse 3",
    "sg:city":"Morgarten",
    "sg:classifiers":[
        {
            "category":"Travel",
            "subcategory":"Hotels & Motels",
            "type":"Entertainment"
        }
    ],
    "sg:phone":"+41 41 750 12 91",
    "sg:postcode":"6315",
    "sg:province":"Zug",
    "sg:tags":[
        "hotels",
        "mit",
        "restaurant"
    ],
    "wof:name":"Hotel Morgarten Am Aegerisee",
    "wof:placetype":"venue"
},
  "geometry": {"coordinates":[8.6401367188,47.1033744812],"type":"Point"}
}