{
  "type": "Feature",
  "properties": {
    "iso:country":"CH",
    "sg:address":"Bomattstrasse 7",
    "sg:city":"Zollbr\u00fcck",
    "sg:orig_category":"Detailhandel mit Textilien Versandhandel",
    "sg:phone":"+41 34 496 31 36",
    "sg:postcode":"3436",
    "sg:province":"Bern",
    "wof:name":"Jakob Ag Jakob-markt",
    "wof:placetype":"venue"
},
  "geometry": {"coordinates":[7.7490401268,46.9715538025],"type":"Point"}
}