{
  "type": "Feature",
  "properties": {
    "iso:country":"CH",
    "sg:address":"Chileweg 15 5413 Birmenstorf Ag. Postfach",
    "sg:city":"Baden",
    "sg:orig_category":"Herstellung von Konstruktionsteilen, Fertigbauteilen U Ausbauelementen aus Holz",
    "sg:phone":"+41 56 200 82 70",
    "sg:postcode":"5400",
    "sg:province":"Aargau",
    "wof:name":"In Plan Innenausbau + Planung Gmbh",
    "wof:placetype":"venue"
},
  "geometry": {"coordinates":[8.2504959106,47.4611320496],"type":"Point"}
}