{
  "type": "Feature",
  "properties": {
    "iso:country":"CH",
    "sg:address":"3236",
    "sg:city":"Gampelen",
    "sg:orig_category":"Verwertung von Milch",
    "sg:postcode":"3236",
    "sg:province":"Bern",
    "wof:name":"Gerber-leuenberger Erwin",
    "wof:placetype":"venue"
},
  "geometry": {"coordinates":[7.0584812164,47.0145874023],"type":"Point"}
}