{
  "type": "Feature",
  "properties": {
    "iso:country":"CH",
    "sg:address":"Rue De Lausanne 64-66",
    "sg:city":"Gen\u00e8ve",
    "sg:orig_category":"Aktivit\u00e4t der Bankinstitute",
    "sg:phone":"+41 22 732 13 39",
    "sg:postcode":"1202",
    "sg:province":"Gen\u00e8ve",
    "wof:name":"Banco Popular Espanol",
    "wof:placetype":"venue"
},
  "geometry": {"coordinates":[6.147112,46.215176],"type":"Point"}
}