{
  "type": "Feature",
  "properties": {
    "iso:country":"CH",
    "sg:address":"Brunngasse 7 8708 M\u00e4nnedorf. Postfach",
    "sg:city":"M\u00e4nnedorf",
    "sg:orig_category":"Reiseb\u00fcros U Reiseveranstalter",
    "sg:phone":"+41 19216060",
    "sg:postcode":"8708",
    "sg:province":"Z\u00fcrich",
    "wof:name":"Zentrum Reisen Ag",
    "wof:placetype":"venue"
},
  "geometry": {"coordinates":[8.6918077469,47.2525863647],"type":"Point"}
}