{
  "type": "Feature",
  "properties": {
    "iso:country":"CH",
    "sg:address":"Rossackerstrasse 124",
    "sg:city":"Z\u00fcrich",
    "sg:orig_category":"Grosshandel mit Kaffee, Tee, Kakao U Gew\u00fcrzen Sonstiger Grosshandel",
    "sg:phone":"+41 14015455",
    "sg:postcode":"8047",
    "sg:province":"Z\u00fcrich",
    "wof:name":"Tsai Niedermann & Co Import & Export",
    "wof:placetype":"venue"
},
  "geometry": {"coordinates":[8.4882717133,47.370174408],"type":"Point"}
}