{
  "type": "Feature",
  "properties": {
    "iso:country":"CH",
    "sg:address":"Po Box 1380 Ch-8021 Z\u00fcrich Switzerland.^^po Box 1380 Badenerstrasse 6",
    "sg:city":"Z\u00fcrich",
    "sg:classifiers":[
        {
            "category":"Banks & Credit Unions",
            "subcategory":"Bank",
            "type":"Services"
        }
    ],
    "sg:postcode":"8021",
    "sg:province":"Z\u00fcrich",
    "wof:name":"Uiag Universal Ingenieur Ag",
    "wof:placetype":"venue"
},
  "geometry": {"coordinates":[7.43995,46.94825],"type":"Point"}
}