{
  "type": "Feature",
  "properties": {
    "addr:full":"Po Box 1380 Ch-8021 Z\u00fcrich Switzerland.^^po Box 1380 Badenerstrasse 6 Z\u00fcrich Z\u00fcrich 8021",
    "addr:housenumber":"po;1380;6",
    "addr:postcode":"ch-8021;8021",
    "addr:street":"Box 1380;Badenerstrasse",
    "iso:country":"CH",
    "sg:address":"Po Box 1380 Ch-8021 Z\u00fcrich Switzerland.^^po Box 1380 Badenerstrasse 6",
    "sg:city":"Z\u00fcrich",
    "sg:classifiers":[
        {
            "category":"Banks & Credit Unions",
            "subcategory":"Bank",
            "type":"Services"
        }
    ],
    "sg:postcode":"8021",
    "sg:province":"Z\u00fcrich",
    "wof:name":"Uiag Universal Ingenieur Ag",
    "wof:placetype":"venue"
},
  "geometry": {"coordinates":[7.43995,46.94825],"type":"Point"}
}