{
  "type": "Feature",
  "properties": {
    "iso:country":"CH",
    "sg:address":"Via San Bernardino",
    "sg:city":"Castione",
    "sg:orig_category":"Elektroinstallation Grosshandel mit elektrischen Haushaltsger\u00e4ten",
    "sg:phone":"+41 91 829 02 07",
    "sg:postcode":"6532",
    "sg:province":"Ticino",
    "wof:name":"Deac Sagl Elettrotecnica",
    "wof:placetype":"venue"
},
  "geometry": {"coordinates":[9.0526809692,46.2243881226],"type":"Point"}
}