{
  "type": "Feature",
  "properties": {
    "iso:country":"CH",
    "sg:address":"Alte Stockstrasse 480",
    "sg:city":"Rombach",
    "sg:orig_category":"Gartenbau",
    "sg:phone":"+41 62 822 62 00",
    "sg:postcode":"5022",
    "sg:province":"Aargau",
    "wof:name":"Hermann L\u00fcthi G\u00e4rtnerei",
    "wof:placetype":"venue"
},
  "geometry": {"coordinates":[8.0505151749,47.4076728821],"type":"Point"}
}