{
  "type": "Feature",
  "properties": {
    "iso:country":"CH",
    "sg:address":"Fontana",
    "sg:city":"Tarasp",
    "sg:orig_category":"Bauschreinerei",
    "sg:phone":"+41 81 864 02 85",
    "sg:postcode":"7553",
    "sg:province":"Graubunden",
    "wof:name":"Jon Grass Mechanische Schreinerei",
    "wof:placetype":"venue"
},
  "geometry": {"coordinates":[10.258493,46.774395],"type":"Point"}
}