{
  "type": "Feature",
  "properties": {
    "iso:country":"CH",
    "sg:address":"B\u00e2timent La Mayorie",
    "sg:city":"Mayens-de-saxon",
    "sg:orig_category":"Sonstiger Grosshandel",
    "sg:phone":"+41 77745758",
    "sg:postcode":"1907",
    "sg:province":"Valais",
    "wof:name":"Girod Produkte Gmbh",
    "wof:placetype":"venue"
},
  "geometry": {"coordinates":[7.5983381271,47.5054664612],"type":"Point"}
}