{
  "type": "Feature",
  "properties": {
    "iso:country":"CH",
    "sg:address":"Industriestr. 16",
    "sg:city":"D\u00e4llikon",
    "sg:classifiers":[
        {
            "category":"Professional",
            "subcategory":"Engineering",
            "type":"Services"
        }
    ],
    "sg:phone":"+41 4118466777",
    "sg:postcode":"8108",
    "sg:province":"Z\u00fcrich",
    "sg:tags":[
        "machine",
        "-",
        "mechanical"
    ],
    "wof:name":"K\u00c4rcher Ag",
    "wof:placetype":"venue"
},
  "geometry": {"coordinates":[8.4367723465,47.4452934265],"type":"Point"}
}