{
  "type": "Feature",
  "properties": {
    "iso:country":"CH",
    "sg:address":"Br\u00fchlweg 5a",
    "sg:city":"Sargans",
    "sg:orig_category":"Kaminfeger",
    "sg:phone":"+41 81 723 55 22",
    "sg:postcode":"7320",
    "sg:province":"St. Gallen",
    "wof:name":"Beat Bonderer Kaminfegermeister",
    "wof:placetype":"venue"
},
  "geometry": {"coordinates":[9.4374132156,47.0491752625],"type":"Point"}
}