{
  "type": "Feature",
  "properties": {
    "iso:country":"CH",
    "sg:address":"Fabrikstrasse 24 8152 Glattbrugg. Postfach",
    "sg:city":"Glattbrugg",
    "sg:orig_category":"Oberfl\u00e4chenveredlung U W\u00e4rmebehandlung",
    "sg:phone":"+41 18108058",
    "sg:postcode":"8152",
    "sg:province":"Z\u00fcrich",
    "wof:name":"Erismann H.j. Feueremail.",
    "wof:placetype":"venue"
},
  "geometry": {"coordinates":[8.5652999878,47.4339408875],"type":"Point"}
}