{
  "type": "Feature",
  "properties": {
    "iso:country":"CH",
    "sg:address":"Chemin Pra Novy",
    "sg:city":"Sugiez",
    "sg:orig_category":"Detailhandel mit Waren verschiedener Art, Hauptrichtung Nahrungsmittel",
    "sg:phone":"+41 26 673 17 12",
    "sg:postcode":"1786",
    "sg:province":"Fribourg",
    "wof:name":"Jean-no\u00ebl Marion Denner-satellite",
    "wof:placetype":"venue"
},
  "geometry": {"coordinates":[7.1134171486,46.9619750977],"type":"Point"}
}