{
  "type": "Feature",
  "properties": {
    "iso:country":"CH",
    "sg:address":"Kirchstrasse 11",
    "sg:city":"Amriswil",
    "sg:orig_category":"Warenh\u00e4user",
    "sg:phone":"+41 21 921 75 51",
    "sg:postcode":"8580",
    "sg:province":"Thurgau",
    "wof:name":"Epa Ag",
    "wof:placetype":"venue"
},
  "geometry": {"coordinates":[5.6025900841,45.9854125977],"type":"Point"}
}