{
  "type": "Feature",
  "properties": {
    "iso:country":"CH",
    "sg:address":"Industriestrasse 11/13",
    "sg:city":"Rotkreuz",
    "sg:orig_category":"Herstellung von Medikamenten U sonstigen pharmazeutischen Erzeugnissen Herstellung von pharmazeutisc",
    "sg:phone":"+41 22 362 17 44",
    "sg:postcode":"6343",
    "sg:province":"Zug",
    "wof:name":"Novartis Consumer Health Sa",
    "wof:placetype":"venue"
},
  "geometry": {"coordinates":[6.2393360138,46.388053894],"type":"Point"}
}