{
  "type": "Feature",
  "properties": {
    "iso:country":"CH",
    "sg:address":"Gyreggstrasse 6",
    "sg:city":"Alosen",
    "sg:orig_category":"Hoch U Tiefbau",
    "sg:phone":"+41 41 750 28 70",
    "sg:postcode":"6315",
    "sg:province":"Zug",
    "wof:name":"Karl Nussbaumer Baugesch\u00e4ft",
    "wof:placetype":"venue"
},
  "geometry": {"coordinates":[8.6373138428,47.141658783],"type":"Point"}
}