{
  "type": "Feature",
  "properties": {
    "iso:country":"CH",
    "sg:address":"Rue De La Fenatte 3",
    "sg:city":"Courrendlin",
    "sg:orig_category":"Herstellung von Metallkonstruktionen",
    "sg:phone":"+41 32 435 52 62",
    "sg:postcode":"2830",
    "sg:province":"Jura",
    "wof:name":"Consmetal S\u00e0rl",
    "wof:placetype":"venue"
},
  "geometry": {"coordinates":[7.3682851791,47.3387145996],"type":"Point"}
}