{
  "type": "Feature",
  "properties": {
    "iso:country":"CH",
    "sg:address":"Kesslerweg 3",
    "sg:city":"Ittigen",
    "sg:orig_category":"Non-Classified Establishments",
    "sg:postcode":"3063",
    "sg:province":"Bern",
    "wof:name":"Patricia Nyfeler Imageberatung Fsfm",
    "wof:placetype":"venue"
},
  "geometry": {"coordinates":[7.4762282372,46.9766082764],"type":"Point"}
}