{
  "type": "Feature",
  "properties": {
    "iso:country":"CH",
    "sg:address":"Grand-rue 30 1630 Bulle. Postfach",
    "sg:city":"Bulle",
    "sg:orig_category":"RESTAURANTS: TEA-ROOMS",
    "sg:postcode":"1630",
    "sg:province":"Fribourg",
    "wof:name":"Melocoton Club S\u00e0rl Bars, Caf\u00e9s, Restaurants, Discoth\u00e8ques, Cabarets Etc",
    "wof:placetype":"venue"
},
  "geometry": {"coordinates":[7.0576748848,46.6189804077],"type":"Point"}
}