{
  "type": "Feature",
  "properties": {
    "iso:country":"CH",
    "sg:address":"Sch\u00f6neggstrasse 30",
    "sg:city":"Dietikon",
    "sg:orig_category":"Zahnkliniken",
    "sg:phone":"+41 17401980",
    "sg:postcode":"8953",
    "sg:province":"Z\u00fcrich",
    "wof:name":"Schulzahnklinik",
    "wof:placetype":"venue"
},
  "geometry": {"coordinates":[8.4046421051,47.4012680054],"type":"Point"}
}