{
  "type": "Feature",
  "properties": {
    "iso:country":"CH",
    "sg:address":"Bann 5 6312 Steinhausen. Postfach",
    "sg:city":"Steinhausen",
    "sg:orig_category":"Unternehmensberatung",
    "sg:postcode":"6312",
    "sg:province":"Zug",
    "wof:name":"Dysli Peter Consulting & Coaching Dienstleistungen Im Ber. Unternehmens-f\u00fchrung Und Informatik",
    "wof:placetype":"venue"
},
  "geometry": {"coordinates":[8.4865617752,47.2052078247],"type":"Point"}
}