{
  "type": "Feature",
  "properties": {
    "iso:country":"CH",
    "sg:address":"Wasserwerkstrasse 127",
    "sg:city":"Z\u00fcrich",
    "sg:orig_category":"Weitere Kultur U Unterhaltungseinrichtungen",
    "sg:phone":"+41 13502610",
    "sg:postcode":"8037",
    "sg:province":"Z\u00fcrich",
    "wof:name":"Tanzhaus Wasserwerk",
    "wof:placetype":"venue"
},
  "geometry": {"coordinates":[8.5305185318,47.3888511658],"type":"Point"}
}