{
  "type": "Feature",
  "properties": {
    "iso:country":"CH",
    "sg:address":"Rathausgasse 12",
    "sg:city":"Arbon",
    "sg:orig_category":"Detailhandel mit Textilien",
    "sg:postcode":"9320",
    "sg:province":"Thurgau",
    "wof:name":"\u00abspycher\u00bb-handwerk Ag",
    "wof:placetype":"venue"
},
  "geometry": {"coordinates":[9.0747652054,47.4425849915],"type":"Point"}
}