{
  "type": "Feature",
  "properties": {
    "iso:country":"CH",
    "sg:address":"Hauptgasse 57",
    "sg:city":"Solothurn",
    "sg:classifiers":[
        {
            "category":"Communications",
            "subcategory":"Film & Video Production",
            "type":"Services"
        }
    ],
    "sg:postcode":"4500",
    "sg:province":"Solothurn",
    "sg:tags":[
        "videofilmherstellung",
        "u"
    ],
    "wof:name":"Ambass Film Ag",
    "wof:placetype":"venue"
},
  "geometry": {"coordinates":[7.5378990173,47.2079658508],"type":"Point"}
}