{
  "type": "Feature",
  "properties": {
    "iso:country":"CH",
    "sg:address":"Kl\u00f6sterlistrasse 25",
    "sg:city":"Schwyz",
    "sg:orig_category":"Selbst\u00e4ndige bildende K\u00fcnstler",
    "sg:phone":"+41 41 811 31 82",
    "sg:postcode":"6430",
    "sg:province":"Schwyz",
    "wof:name":"Josef Fries Wurzelschnitzerei",
    "wof:placetype":"venue"
},
  "geometry": {"coordinates":[8.6608533859,47.0231361389],"type":"Point"}
}