{
  "type": "Feature",
  "properties": {
    "iso:country":"CH",
    "sg:address":"W\u00e4ldli",
    "sg:city":"Filzbach",
    "sg:orig_category":"Landesverteidigung, Sozialversicherung \u00d6ffentliche Verwaltung",
    "sg:phone":"+41 55 614 13 51",
    "sg:postcode":"8757",
    "sg:province":"Glarus",
    "wof:name":"Zivilschutzstelle M\u00fchlehorn",
    "wof:placetype":"venue"
},
  "geometry": {"coordinates":[9.1336193085,47.1195144653],"type":"Point"}
}