{
  "type": "Feature",
  "properties": {
    "iso:country":"CH",
    "sg:address":"Poststr. 24 8226 Schleitheim. Postfach",
    "sg:city":"Bern",
    "sg:orig_category":"Detailhandel mit Beleuchtungs U Haushaltsgegenst\u00e4nden Elektroinstallation",
    "sg:phone":"+41 27 475 18 40",
    "sg:postcode":"3013",
    "sg:province":"Bern",
    "wof:name":"Zufferey Charly",
    "wof:placetype":"venue"
},
  "geometry": {"coordinates":[7.58431,46.196419],"type":"Point"}
}