{
  "type": "Feature",
  "properties": {
    "iso:country":"CH",
    "sg:address":"Schwarzenburgstrasse 804",
    "sg:city":"Niederscherli",
    "sg:orig_category":"Elektroinstallation",
    "sg:phone":"+41 31 849 11 47",
    "sg:postcode":"3145",
    "sg:province":"Bern",
    "wof:name":"Rohrbach Ulrich",
    "wof:placetype":"venue"
},
  "geometry": {"coordinates":[7.3884482384,46.88514328],"type":"Point"}
}