{
  "type": "Feature",
  "properties": {
    "iso:country":"CH",
    "sg:address":"Ursprungstrasse",
    "sg:city":"M\u00fcnchenbuchsee",
    "sg:orig_category":"Vorschulen, Kinderg\u00e4rten",
    "sg:phone":"+41 31 869 36 47",
    "sg:postcode":"3053",
    "sg:province":"Bern",
    "wof:name":"Kindergarten Ursprung A & B",
    "wof:placetype":"venue"
},
  "geometry": {"coordinates":[7.4569659233,47.0170974731],"type":"Point"}
}