{
  "type": "Feature",
  "properties": {
    "iso:country":"CH",
    "sg:address":"H\u00f6lzliwisenstrasse 5",
    "sg:city":"Volketswil",
    "sg:classifiers":[
        {
            "category":"Government",
            "subcategory":"Fire Station",
            "type":"Public Place"
        }
    ],
    "sg:phone":"+41 43 399 30 95",
    "sg:postcode":"8604",
    "sg:province":"Z\u00fcrich",
    "sg:tags":[
        "diffuser",
        "scent",
        "freshener",
        "air"
    ],
    "wof:name":"Phibena Ag",
    "wof:placetype":"venue"
},
  "geometry": {"coordinates":[8.679204,47.378117],"type":"Point"}
}