{
  "type": "Feature",
  "properties": {
    "iso:country":"CH",
    "sg:address":"Savoie Rue Louis De 27",
    "sg:city":"Morges",
    "sg:orig_category":"Herstellung von Medikamenten U sonstigen pharmazeutischen Erzeugnissen",
    "sg:phone":"+41 21 803 06 36",
    "sg:postcode":"1110",
    "sg:province":"Vaud",
    "wof:name":"Crdp Clinical Research & Development Of Pharmaceuticals Sa",
    "wof:placetype":"venue"
},
  "geometry": {"coordinates":[6.4996829033,46.5091972351],"type":"Point"}
}