{
  "type": "Feature",
  "properties": {
    "iso:country":"CH",
    "sg:address":"Via Orico 15",
    "sg:city":"Bellinzona",
    "sg:orig_category":"Fahrschulen, Flugschulen",
    "sg:phone":"+41 91 825 99 54",
    "sg:postcode":"6500",
    "sg:province":"Ticino",
    "wof:name":"Istituto Rass Sa Aggiornamento Sicurezza Stradale",
    "wof:placetype":"venue"
},
  "geometry": {"coordinates":[9.0189943314,46.1922187805],"type":"Point"}
}