{
  "type": "Feature",
  "properties": {
    "iso:country":"CH",
    "sg:address":"Verney En",
    "sg:city":"Payerne",
    "sg:orig_category":"Erbringung von sonstigen Dienstleistungen f\u00fcr Unterhaltung, Erholung U Freizeit",
    "sg:postcode":"1530",
    "sg:province":"Vaud",
    "wof:name":"Karting Indoor Attractions Sa",
    "wof:placetype":"venue"
},
  "geometry": {"coordinates":[6.9542050362,46.8126144409],"type":"Point"}
}