{
  "type": "Feature",
  "properties": {
    "iso:country":"CH",
    "sg:address":"Hofmattstrasse 5",
    "sg:city":"Waltenschwil",
    "sg:orig_category":"Herstellung von Kunststoffwaren Herstellung von sonstigen chemischen Erzeugnissen",
    "sg:phone":"+41 56 622 68 92",
    "sg:postcode":"5622",
    "sg:province":"Aargau",
    "wof:name":"Gastro Master Gmbh",
    "wof:placetype":"venue"
},
  "geometry": {"coordinates":[8.297246933,47.3360023499],"type":"Point"}
}