{
  "type": "Feature",
  "properties": {
    "iso:country":"CH",
    "sg:address":"Industrieplatz 8212 Neuhausen. Postfach",
    "sg:city":"Zug",
    "sg:orig_category":"Grosshandel mit sonstigen Gebrauchs U Verbrauchsg\u00fctern Herstellung von Wellpapier U pappe sowie von ",
    "sg:phone":"+41 61 332 13 43",
    "sg:postcode":"6300",
    "sg:province":"Zug",
    "wof:name":"Sidler Papierposten",
    "wof:placetype":"venue"
},
  "geometry": {"coordinates":[7.610929966,47.5289382935],"type":"Point"}
}