{
  "type": "Feature",
  "properties": {
    "iso:country":"CH",
    "sg:address":"Avenue Du L\u00e9man 55",
    "sg:city":"Lausanne",
    "sg:orig_category":"Arztpraxen",
    "sg:phone":"+41 21 711 00 21",
    "sg:postcode":"1005",
    "sg:province":"Vaud",
    "wof:name":"Dr M\u00e9d. Willy Favre M\u00e9decin Sp\u00e9cialiste Fmh",
    "wof:placetype":"venue"
},
  "geometry": {"coordinates":[6.650296,46.515289],"type":"Point"}
}