{
  "type": "Feature",
  "properties": {
    "iso:country":"CH",
    "sg:address":"Arvenweg 1",
    "sg:city":"Einsiedeln",
    "sg:orig_category":"Herstellung von Metallkonstruktionen",
    "sg:phone":"+41 55 412 10 16",
    "sg:postcode":"8840",
    "sg:province":"Schwyz",
    "wof:name":"Wolfgang Sp\u00e4ni, Schreiner-montagen",
    "wof:placetype":"venue"
},
  "geometry": {"coordinates":[8.7374305725,47.1217651367],"type":"Point"}
}