{
  "type": "Feature",
  "properties": {
    "iso:country":"CH",
    "sg:address":"Bielstrasse 96",
    "sg:city":"Solothurn",
    "sg:orig_category":"Unclassifiable Establishments",
    "sg:postcode":"4500",
    "sg:province":"Solothurn",
    "wof:name":"Pneu Express Gmbh",
    "wof:placetype":"venue"
},
  "geometry": {"coordinates":[7.52495718,47.2114524841],"type":"Point"}
}