{
  "type": "Feature",
  "properties": {
    "iso:country":"CH",
    "sg:address":"Altelweg 12 3661 Uetendorf. Postfach",
    "sg:city":"Steffisburg",
    "sg:orig_category":"Softwareentwicklung U beratung",
    "sg:phone":"+41 33 438 02 16",
    "sg:postcode":"3612",
    "sg:province":"Bern",
    "wof:name":"Ina Ingena Gmbh Dienstleistungen In Den Ber. Informatik U. Kommunikation Usw.",
    "wof:placetype":"venue"
},
  "geometry": {"coordinates":[7.5922498703,46.7794303894],"type":"Point"}
}