{
  "type": "Feature",
  "properties": {
    "iso:country":"CH",
    "sg:address":"Toggenburgerstrasse 26",
    "sg:city":"Ganterschwil",
    "sg:classifiers":[
        {
            "category":"Restaurant",
            "type":"Food & Drink"
        }
    ],
    "sg:phone":"+41 71 983 15 11",
    "sg:postcode":"9608",
    "sg:province":"St. Gallen",
    "wof:name":"Restaurant Hirschen",
    "wof:placetype":"venue"
},
  "geometry": {"coordinates":[9.085934639,47.3791656494],"type":"Point"}
}