{
  "type": "Feature",
  "properties": {
    "iso:country":"CH",
    "sg:address":"Steinr\u00fctistrasse 9658 Wildhaus. Postfach 642",
    "sg:city":"Wildhaus",
    "sg:orig_category":"HOTELS: MIT RESTAURANT Kongress- and Tagungshotels mit Restaurant",
    "sg:phone":"+41 33 243 15 12",
    "sg:postcode":"9658",
    "sg:province":"St. Gallen",
    "wof:name":"Hotel Niesenblick",
    "wof:placetype":"venue"
},
  "geometry": {"coordinates":[7.6818051338,46.724357605],"type":"Point"}
}