{
  "type": "Feature",
  "properties": {
    "iso:country":"CH",
    "sg:address":"Engelbergstrasse 39",
    "sg:city":"Stans",
    "sg:orig_category":"Spielsalons",
    "sg:phone":"+41 41 610 97 07",
    "sg:postcode":"6370",
    "sg:province":"Nidwalden",
    "wof:name":"Spielsalon Bod\u00e4rotli Son-game Ag",
    "wof:placetype":"venue"
},
  "geometry": {"coordinates":[8.3711423874,46.9567680359],"type":"Point"}
}