{
  "type": "Feature",
  "properties": {
    "iso:country":"CH",
    "sg:address":"Costa Di Fuori Via 99",
    "sg:city":"Brissago",
    "sg:orig_category":"Architektur U Ingenieurb\u00fcros",
    "sg:postcode":"6614",
    "sg:province":"Ticino",
    "wof:name":"Bjp Di Jelmoni Ivan",
    "wof:placetype":"venue"
},
  "geometry": {"coordinates":[8.699063,46.110683],"type":"Point"}
}