{
  "type": "Feature",
  "properties": {
    "iso:country":"CH",
    "sg:address":"Chauderon Place 3 1003 Lausanne. Postfach",
    "sg:city":"Lausanne",
    "sg:orig_category":"Dienstleistungen von Beteiligungsgesellschaften",
    "sg:phone":"+41 21 626 01 15",
    "sg:postcode":"1003",
    "sg:province":"Vaud",
    "wof:name":"Gb Consulting, Gauthey B.",
    "wof:placetype":"venue"
},
  "geometry": {"coordinates":[6.6262698174,46.5232391357],"type":"Point"}
}