{
  "type": "Feature",
  "properties": {
    "iso:country":"CH",
    "sg:address":"G\u00f6sgerstrasse 9",
    "sg:city":"Niedererlinsbach",
    "sg:orig_category":"Malerei",
    "sg:phone":"+41 79 647 78 43",
    "sg:postcode":"5015",
    "sg:province":"Solothurn",
    "wof:name":"Marcel Ritter Malergesch\u00e4ft",
    "wof:placetype":"venue"
},
  "geometry": {"coordinates":[7.9514670372,47.5431137085],"type":"Point"}
}