{
  "type": "Feature",
  "properties": {
    "iso:country":"CH",
    "sg:address":"Herrengasse 3 4710 Balsthal. Postfach",
    "sg:city":"Balsthal",
    "sg:orig_category":"Detailhandel mit Musikinstrumenten Detailhandel mit elektrischen Haushalts-,Radio U Fernsehger\u00e4ten s",
    "sg:phone":"+41 62 391 32 30",
    "sg:postcode":"4710",
    "sg:province":"Solothurn",
    "wof:name":"Musikwelt Jaus Boris Musikinstrumente U. Tontr\u00e4ger; Handel U. Vermietung",
    "wof:placetype":"venue"
},
  "geometry": {"coordinates":[7.6958432198,47.3159294128],"type":"Point"}
}