{
  "type": "Feature",
  "properties": {
    "iso:country":"CH",
    "sg:address":"Frenkend\u00f6rferstrasse 27",
    "sg:city":"Liestal",
    "sg:orig_category":"Pensionskassen",
    "sg:phone":"+41 61 901 21 21",
    "sg:postcode":"4410",
    "sg:province":"Basel-Landschaft",
    "wof:name":"Wohlfahrtsfonds Der Ladenbau Ag",
    "wof:placetype":"venue"
},
  "geometry": {"coordinates":[7.7200288773,47.4981002808],"type":"Point"}
}