{
  "type": "Feature",
  "properties": {
    "iso:country":"CH",
    "sg:address":"Sempacherstrasse 3",
    "sg:city":"Luzern",
    "sg:classifiers":[
        {
            "category":"Professional",
            "subcategory":"Employment Agencies",
            "type":"Services"
        }
    ],
    "sg:phone":"+41 41 226 12 12",
    "sg:postcode":"6003",
    "sg:province":"Luzern",
    "sg:tags":[
        "personal",
        "u",
        "stellenvermittlung"
    ],
    "wof:name":"Vediornewjob Ag",
    "wof:placetype":"venue"
},
  "geometry": {"coordinates":[8.3073291779,47.0490684509],"type":"Point"}
}