{
  "type": "Feature",
  "properties": {
    "iso:country":"CH",
    "sg:address":"Dufourstrasse 14",
    "sg:city":"Luzern",
    "sg:orig_category":"Unternehmensberatung",
    "sg:phone":"+41 41 240 95 24",
    "sg:postcode":"6003",
    "sg:province":"Luzern",
    "wof:name":"Fries Erwin Treuhand Steuer, Unternehmens- U. Wirtschaftsberatung Usw",
    "wof:placetype":"venue"
},
  "geometry": {"coordinates":[8.3017530441,47.0477409363],"type":"Point"}
}