{
  "type": "Feature",
  "properties": {
    "iso:country":"CH",
    "sg:address":"8452",
    "sg:city":"Adlikon",
    "sg:orig_category":"Ingenieurb\u00fcros Elektro",
    "sg:phone":"+41 52 317 22 34",
    "sg:postcode":"8452",
    "sg:province":"Z\u00fcrich",
    "wof:name":"Ernst Waser Ingenieurb\u00fcro",
    "wof:placetype":"venue"
},
  "geometry": {"coordinates":[8.6925001144,47.5826721191],"type":"Point"}
}