{
  "type": "Feature",
  "properties": {
    "iso:country":"CH",
    "sg:address":"Place Du 16-mars 2",
    "sg:city":"St-imier",
    "sg:classifiers":[
        {
            "category":"Restaurant",
            "type":"Food & Drink"
        }
    ],
    "sg:phone":"+41 32 940 12 77",
    "sg:postcode":"2610",
    "sg:province":"Bern",
    "wof:name":"R\u00f4tisserie De La Reine-berthe",
    "wof:placetype":"venue"
},
  "geometry": {"coordinates":[7.0003080368,47.1528892517],"type":"Point"}
}