{
  "type": "Feature",
  "properties": {
    "iso:country":"CH",
    "sg:address":"Adlikerstrasse 89",
    "sg:city":"Regensdorf",
    "sg:orig_category":"Innenarchitekturb\u00fcros",
    "sg:phone":"+41 18404482",
    "sg:postcode":"8105",
    "sg:province":"Z\u00fcrich",
    "wof:name":"Robert Fivian Innenarchitektur",
    "wof:placetype":"venue"
},
  "geometry": {"coordinates":[8.4637184143,47.4345588684],"type":"Point"}
}