{
  "type": "Feature",
  "properties": {
    "iso:country":"CH",
    "sg:address":"Baumschulstrasse 2",
    "sg:city":"Schaffhausen",
    "sg:orig_category":"Vereine Abstinenten",
    "sg:phone":"+41 52 624 42 73",
    "sg:postcode":"8200",
    "sg:province":"Schaffhausen",
    "wof:name":"Guttemplergruppe Rheinfall",
    "wof:placetype":"venue"
},
  "geometry": {"coordinates":[8.6453695297,47.7054138184],"type":"Point"}
}