{
  "type": "Feature",
  "properties": {
    "iso:country":"CH",
    "sg:address":"Eggenacherstrasse 32",
    "sg:city":"Aarburg",
    "sg:orig_category":"Interessenvertretungen",
    "sg:postcode":"4663",
    "sg:province":"Aargau",
    "wof:name":"Kulturfonds Aarburg, Byland-cadieli-stiftung",
    "wof:placetype":"venue"
},
  "geometry": {"coordinates":[7.9079680443,47.3305740356],"type":"Point"}
}