{
  "type": "Feature",
  "properties": {
    "iso:country":"CH",
    "sg:address":"Marktstrasse 17",
    "sg:city":"Flums",
    "sg:orig_category":"Finanzierungsinstitutionen",
    "sg:postcode":"8890",
    "sg:province":"St. Gallen",
    "wof:name":"Curatio Ag",
    "wof:placetype":"venue"
},
  "geometry": {"coordinates":[9.3453874588,47.0910873413],"type":"Point"}
}