{
  "type": "Feature",
  "properties": {
    "iso:country":"CH",
    "sg:address":"2610 St-imier Case Postale",
    "sg:city":"St-imier",
    "sg:orig_category":"Unclassifiable Establishments",
    "sg:phone":"+41 32 942 41 11",
    "sg:postcode":"2610",
    "sg:province":"Bern",
    "wof:name":"Soci\u00e9t\u00e9 Des Forces \u00e9lectriques De La Goule",
    "wof:placetype":"venue"
},
  "geometry": {"coordinates":[6.9958171844,47.1520423889],"type":"Point"}
}