{
  "type": "Feature",
  "properties": {
    "iso:country":"CH",
    "sg:address":"Wyb\u00e4rgstrasse 10",
    "sg:city":"Geuensee",
    "sg:orig_category":"Arztpraxen",
    "sg:phone":"+41 41 921 20 31",
    "sg:postcode":"6232",
    "sg:province":"Luzern",
    "wof:name":"Dr.med.karl Heinz Bauersfeld Spezialarzt Fmh",
    "wof:placetype":"venue"
},
  "geometry": {"coordinates":[8.111748,47.198372],"type":"Point"}
}