{
  "type": "Feature",
  "properties": {
    "iso:country":"CH",
    "sg:address":"Frohnibiel",
    "sg:city":"Birgisch",
    "sg:orig_category":"Sportvereine Unihockey",
    "sg:postcode":"3901",
    "sg:province":"Valais",
    "wof:name":"Uhc Neyruz Rhinos",
    "wof:placetype":"venue"
},
  "geometry": {"coordinates":[7.0673398972,46.76612854],"type":"Point"}
}