{
  "type": "Feature",
  "properties": {
    "iso:country":"CH",
    "sg:address":"L\u00f6wengartenstrasse 11 9400 Rorschach. Postfach",
    "sg:city":"Rorschach",
    "sg:orig_category":"Sportvereine Flug Aero-Club",
    "sg:phone":"+41 71 841 40 01",
    "sg:postcode":"9401",
    "sg:province":"St. Gallen",
    "wof:name":"Ae.c.s.modellfluggruppe",
    "wof:placetype":"venue"
},
  "geometry": {"coordinates":[9.4826068878,47.4774131775],"type":"Point"}
}