{
  "type": "Feature",
  "properties": {
    "iso:country":"CH",
    "sg:address":"General Wille-strasse 165",
    "sg:city":"Feldmeilen",
    "sg:orig_category":"Unclassifiable Establishments",
    "sg:postcode":"8706",
    "sg:province":"Z\u00fcrich",
    "wof:name":"Genossenschaft Schnabel",
    "wof:placetype":"venue"
},
  "geometry": {"coordinates":[8.6189155579,47.2771835327],"type":"Point"}
}