{
  "type": "Feature",
  "properties": {
    "iso:country":"CH",
    "sg:address":"Hurdenerstrasse 137",
    "sg:city":"Freienbach",
    "sg:orig_category":"Unclassifiable Establishments",
    "sg:postcode":"8807",
    "sg:province":"Schwyz",
    "wof:name":"Kiwesa Holding Ag",
    "wof:placetype":"venue"
},
  "geometry": {"coordinates":[8.8052949905,47.2164382935],"type":"Point"}
}