{
  "type": "Feature",
  "properties": {
    "iso:country":"CH",
    "sg:address":"Ringgenmatt 2",
    "sg:city":"Schwarzenburg",
    "sg:classifiers":[
        {
            "category":"Manufacturing",
            "subcategory":"Rubber & Plastics",
            "type":"Manufacturing & Wholesale Goods"
        }
    ],
    "sg:phone":"+41 22 884 99 00",
    "sg:postcode":"3150",
    "sg:province":"Bern",
    "wof:name":"Vink Sa",
    "wof:placetype":"venue"
},
  "geometry": {"coordinates":[6.108080864,46.1704978943],"type":"Point"}
}