{
  "type": "Feature",
  "properties": {
    "iso:country":"CH",
    "sg:address":"Wettingerstrasse 5",
    "sg:city":"Baden",
    "sg:orig_category":"Sonstiger Grosshandel",
    "sg:phone":"+41 41 610 60 39",
    "sg:postcode":"5400",
    "sg:province":"Aargau",
    "wof:name":"Sibaas Ag",
    "wof:placetype":"venue"
},
  "geometry": {"coordinates":[8.3142662048,46.9925308228],"type":"Point"}
}