{
  "type": "Feature",
  "properties": {
    "iso:country":"CH",
    "sg:address":"St. Gallerstrasse 44",
    "sg:city":"Arbon",
    "sg:orig_category":"Fachdetailhandel in Verkaufsr\u00e4umen",
    "sg:phone":"+41 71 440 05 75",
    "sg:postcode":"9320",
    "sg:province":"Thurgau",
    "wof:name":"Florissima Gosetto Hanni",
    "wof:placetype":"venue"
},
  "geometry": {"coordinates":[9.4268026352,47.5108604431],"type":"Point"}
}