{
  "type": "Feature",
  "properties": {
    "iso:country":"CH",
    "sg:address":"R\u00fctschelengasse 11",
    "sg:city":"Burgdorf",
    "sg:orig_category":"Grosshandel mit Nahrungsmitteln, Getr\u00e4nken U Tabakwaren ohne ausgepr\u00e4gten Schwerpunkt",
    "sg:postcode":"3400",
    "sg:province":"Bern",
    "wof:name":"Erdeljan-boka",
    "wof:placetype":"venue"
},
  "geometry": {"coordinates":[7.6274352074,47.0555725098],"type":"Point"}
}