{
  "type": "Feature",
  "properties": {
    "iso:country":"CH",
    "sg:address":"1442",
    "sg:city":"Montagny-yverdon",
    "sg:orig_category":"Mechanik Stahl U Leichtmetallbau",
    "sg:phone":"+41 21 921 60 15",
    "sg:postcode":"1442",
    "sg:province":"Vaud",
    "wof:name":"Altobelli S\u00e0rl Serrurerie",
    "wof:placetype":"venue"
},
  "geometry": {"coordinates":[5.1808700562,45.8973388672],"type":"Point"}
}