{
  "type": "Feature",
  "properties": {
    "iso:country":"CH",
    "sg:address":"5703",
    "sg:city":"Seon",
    "sg:orig_category":"Berufsbildende weiterf\u00fchrende Schulen",
    "sg:phone":"+41 62 775 10 56",
    "sg:postcode":"5703",
    "sg:province":"Aargau",
    "wof:name":"Berufswahlschule",
    "wof:placetype":"venue"
},
  "geometry": {"coordinates":[8.160384,47.346741],"type":"Point"}
}