{
  "type": "Feature",
  "properties": {
    "addr:full":"Wyssgasse 6 Z\u00fcrich Z\u00fcrich 8004",
    "addr:housenumber":"6",
    "addr:postcode":"8004",
    "addr:street":"Wyssgasse",
    "iso:country":"CH",
    "sg:address":"Wyssgasse 6",
    "sg:city":"Z\u00fcrich",
    "sg:classifiers":[
        {
            "category":"Professional",
            "subcategory":"Detective & Security Services",
            "type":"Services"
        }
    ],
    "sg:phone":"+41 12411414",
    "sg:postcode":"8004",
    "sg:province":"Z\u00fcrich",
    "sg:tags":[
        "agency"
    ],
    "wof:name":"A+a Privatdetektivb\u00fcro Ag",
    "wof:placetype":"venue"
},
  "geometry": {"coordinates":[8.525606,47.373642],"type":"Point"}
}