{
  "type": "Feature",
  "properties": {
    "iso:country":"CH",
    "sg:address":"1726",
    "sg:city":"Posat",
    "sg:classifiers":[
        {
            "category":"Restaurant",
            "type":"Food & Drink"
        }
    ],
    "sg:phone":"+41 26 411 11 20",
    "sg:postcode":"1726",
    "sg:province":"Fribourg",
    "wof:name":"Caf\u00e9 Croix D'or",
    "wof:placetype":"venue"
},
  "geometry": {"coordinates":[7.0575900078,46.7377510071],"type":"Point"}
}