{
  "type": "Feature",
  "properties": {
    "iso:country":"CH",
    "sg:address":"Bergmatt Schlatt Appenzell 9050 Appenzell. Postfach",
    "sg:city":"Appenzell",
    "sg:orig_category":"Herstellung von Konstruktionsteilen, Fertigbauteilen U Ausbauelementen aus Holz Zimmerei, Dachdecker",
    "sg:phone":"+41 71 787 37 32",
    "sg:postcode":"9050",
    "sg:province":"Appenzell Innerhoden",
    "wof:name":"D\u00f6rig & Br\u00fclisauer Gmbh Zimmerei Und Bauschreinerei",
    "wof:placetype":"venue"
},
  "geometry": {"coordinates":[9.4076833725,47.3314361572],"type":"Point"}
}