{
  "type": "Feature",
  "properties": {
    "iso:country":"CH",
    "sg:address":"Chemin Du Grand Record 17",
    "sg:city":"Echallens",
    "sg:orig_category":"Grosshandel mit sonstigen Nahrungsmitteln Herstellung von Maschinen f\u00fcr die Nahrungsmittel, Getr\u00e4nke",
    "sg:phone":"+41 17614306",
    "sg:postcode":"1040",
    "sg:province":"Vaud",
    "wof:name":"B\u00e4ckerei-& K\u00fcchenmaschinen Peter Stutz",
    "wof:placetype":"venue"
},
  "geometry": {"coordinates":[8.4434213638,47.275932312],"type":"Point"}
}