{
  "type": "Feature",
  "properties": {
    "iso:country":"CH",
    "sg:address":"Buchw\u00e4ldlistrasse 5",
    "sg:city":"Werthenstein",
    "sg:orig_category":"G\u00fcterbef\u00f6rderung im Strassenverkehr",
    "sg:phone":"+41 32 385 15 12",
    "sg:postcode":"6106",
    "sg:province":"Luzern",
    "wof:name":"Alfred Lehmann Carreisen & Transporte",
    "wof:placetype":"venue"
},
  "geometry": {"coordinates":[7.3162817955,47.1003036499],"type":"Point"}
}