{
  "type": "Feature",
  "properties": {
    "iso:country":"CH",
    "sg:address":"Unterdorfstrasse 1",
    "sg:city":"Salgesch",
    "sg:orig_category":"Kauf U Verkauf von Immobilien auf eigene Rechnung",
    "sg:phone":"+41 27 451 21 00",
    "sg:postcode":"3970",
    "sg:province":"Valais",
    "wof:name":"Hotel Arkanum",
    "wof:placetype":"venue"
},
  "geometry": {"coordinates":[7.5697078705,46.3114013672],"type":"Point"}
}