{
  "type": "Feature",
  "properties": {
    "iso:country":"CH",
    "sg:address":"Marktgasse 37 3011 Bern. Postfach",
    "sg:city":"Bern",
    "sg:orig_category":"Interessenvertretungen",
    "sg:phone":"+41 31 311 21 21",
    "sg:postcode":"3005",
    "sg:province":"Bern",
    "wof:name":"Berner M\u00fcnster-stiftung",
    "wof:placetype":"venue"
},
  "geometry": {"coordinates":[7.4452261925,46.9479026794],"type":"Point"}
}