{
  "type": "Feature",
  "properties": {
    "iso:country":"CH",
    "sg:address":"Herdern 2",
    "sg:city":"Ennetb\u00fcrgen",
    "sg:orig_category":"Institutionen f\u00fcr Finanzierungsleasing",
    "sg:phone":"+41 41 624 40 20",
    "sg:postcode":"6373",
    "sg:province":"Nidwalden",
    "wof:name":"Gamo Leasing Ag",
    "wof:placetype":"venue"
},
  "geometry": {"coordinates":[8.3965072632,46.979598999],"type":"Point"}
}