{
  "type": "Feature",
  "properties": {
    "iso:country":"CH",
    "sg:address":"Chemin Praz-devant 6",
    "sg:city":"Romanel-s-lausanne",
    "sg:orig_category":"Markt U Meinungsforschung",
    "sg:phone":"+41 21 731 93 00",
    "sg:postcode":"1032",
    "sg:province":"Vaud",
    "wof:name":"Tandem Marketing Et Communication, Bauer",
    "wof:placetype":"venue"
},
  "geometry": {"coordinates":[6.6031517982,46.5697822571],"type":"Point"}
}