{
  "type": "Feature",
  "properties": {
    "iso:country":"CH",
    "sg:address":"Neuve Rue 6",
    "sg:city":"Nyon",
    "sg:orig_category":"Architektur U Ingenieurb\u00fcros",
    "sg:phone":"+41 22 363 88 60",
    "sg:postcode":"1260",
    "sg:province":"Vaud",
    "wof:name":"Glauser Georges",
    "wof:placetype":"venue"
},
  "geometry": {"coordinates":[6.23886,46.383179],"type":"Point"}
}