{
  "type": "Feature",
  "properties": {
    "iso:country":"CH",
    "sg:address":"Schlossstrasse 1",
    "sg:city":"Nidau",
    "sg:orig_category":"Rechtsberatung",
    "sg:postcode":"2560",
    "sg:province":"Bern",
    "wof:name":"Notariat M\u00fcller D.",
    "wof:placetype":"venue"
},
  "geometry": {"coordinates":[8.3064451218,47.4743309021],"type":"Point"}
}