{
  "type": "Feature",
  "properties": {
    "iso:country":"CH",
    "sg:address":"Weidstrasse 13",
    "sg:city":"Fischbach-g\u00f6slikon",
    "sg:orig_category":"Kauf U Verkauf von Immobilien auf eigene Rechnung",
    "sg:phone":"+41 56 621 00 73",
    "sg:postcode":"5525",
    "sg:province":"Aargau",
    "wof:name":"Schmid Sibylle Immobilien",
    "wof:placetype":"venue"
},
  "geometry": {"coordinates":[8.3136167526,47.3643569946],"type":"Point"}
}