{
  "type": "Feature",
  "properties": {
    "iso:country":"CH",
    "sg:address":"Gasstrasse 36",
    "sg:city":"Basel",
    "sg:orig_category":"Allgemeiner Hoch U Tiefbau",
    "sg:postcode":"4056",
    "sg:province":"Basel-Stadt",
    "wof:name":"Master Bau Gmbh",
    "wof:placetype":"venue"
},
  "geometry": {"coordinates":[7.576226,47.569923],"type":"Point"}
}