{
  "type": "Feature",
  "properties": {
    "iso:country":"CH",
    "sg:address":"Worb",
    "sg:city":"Worb",
    "sg:classifiers":[
        {
            "category":"Banks & Credit Unions",
            "subcategory":"Bank",
            "type":"Services"
        }
    ],
    "sg:phone":"+41 31 839 73 73",
    "sg:postcode":"3076",
    "sg:province":"Bern",
    "wof:name":"Spar + Leihkasse M\u00fcnsingen",
    "wof:placetype":"venue"
},
  "geometry": {"coordinates":[7.56338,46.929745],"type":"Point"}
}