{
  "type": "Feature",
  "properties": {
    "iso:country":"CH",
    "sg:address":"General Guisan-strasse 51",
    "sg:city":"Basel",
    "sg:orig_category":"Detailhandel mit Metallwaren, Anstrichmitteln, Glaswaren, Bau U Heimwerkerbedarf Maschinen and Appar",
    "sg:phone":"+41 61 756 63 30",
    "sg:postcode":"4054",
    "sg:province":"Basel-Stadt",
    "wof:name":"E-instruments Ag",
    "wof:placetype":"venue"
},
  "geometry": {"coordinates":[7.5680971146,47.5508155823],"type":"Point"}
}