{
  "type": "Feature",
  "properties": {
    "iso:country":"CH",
    "sg:address":"Ebenaustrasse 12",
    "sg:city":"Horw",
    "sg:orig_category":"Innenausbau M\u00f6belschreinerei",
    "sg:postcode":"6048",
    "sg:province":"Luzern",
    "wof:name":"Marcel Krummenacher Schreinerei-innenausbau K\u00fcchen",
    "wof:placetype":"venue"
},
  "geometry": {"coordinates":[8.3075761795,47.0132865906],"type":"Point"}
}