{
  "type": "Feature",
  "properties": {
    "iso:country":"CH",
    "sg:address":"Hauptstrasse 39",
    "sg:city":"Hunzenschwil",
    "sg:classifiers":[
        {
            "category":"Government",
            "subcategory":"Post Office",
            "type":"Public Place"
        }
    ],
    "sg:phone":"+41 62 889 22 29",
    "sg:postcode":"5502",
    "sg:province":"Aargau",
    "sg:tags":[
        "caf\u00e9s",
        "tea-rooms"
    ],
    "wof:name":"Caf\u00e9 Gt",
    "wof:placetype":"venue"
},
  "geometry": {"coordinates":[8.117389679,47.3871917725],"type":"Point"}
}