{
  "type": "Feature",
  "properties": {
    "iso:country":"CH",
    "sg:address":"Binzstrasse 4",
    "sg:city":"Pfaffhausen",
    "sg:orig_category":"Dachdeckerei Reinigungsgewerbe",
    "sg:phone":"+41 18253068",
    "sg:postcode":"8118",
    "sg:province":"Z\u00fcrich",
    "wof:name":"Hans Markwalder Kaminfeger-& Dachdeckergesch.",
    "wof:placetype":"venue"
},
  "geometry": {"coordinates":[8.627021,47.368645],"type":"Point"}
}