{
  "type": "Feature",
  "properties": {
    "iso:country":"CH",
    "sg:address":"Avenue Du Rothorn 9 B",
    "sg:city":"Sierre",
    "sg:orig_category":"Verarbeitung von Tee U Kaffee",
    "sg:phone":"+41 27 455 15 77",
    "sg:postcode":"3960",
    "sg:province":"Valais",
    "wof:name":"Mercure Sa",
    "wof:placetype":"venue"
},
  "geometry": {"coordinates":[7.5320620537,46.2934951782],"type":"Point"}
}