{
  "type": "Feature",
  "properties": {
    "iso:country":"CH",
    "sg:address":"Staffelnrain 3",
    "sg:city":"Reussb\u00fchl",
    "sg:orig_category":"Sonstiges Gesundheitswesen",
    "sg:phone":"+41 41 260 45 26",
    "sg:postcode":"6015",
    "sg:province":"Luzern",
    "wof:name":"Krankenmobilienmagazin Frau E.h\u00e4fliger",
    "wof:placetype":"venue"
},
  "geometry": {"coordinates":[8.2798471451,47.0627593994],"type":"Point"}
}