{
  "type": "Feature",
  "properties": {
    "iso:country":"CH",
    "sg:address":"Cap-de-ville Rue Pr\u00e9-fleuri 2c 3960 Sierre. Postfach",
    "sg:city":"Lausanne",
    "sg:orig_category":"Detailhandel mit M\u00f6beln U Haushaltsgegenst\u00e4nden",
    "sg:postcode":"1003",
    "sg:province":"Vaud",
    "wof:name":"Meubles Et Int\u00e9rieurs S\u00e0rl",
    "wof:placetype":"venue"
},
  "geometry": {"coordinates":[7.5306549072,46.2924041748],"type":"Point"}
}