{
  "type": "Feature",
  "properties": {
    "iso:country":"CH",
    "sg:address":"F\u00fcrfelderstrasse 1 4125 Riehen. Postfach",
    "sg:city":"Riehen",
    "sg:orig_category":"Reinigungsgewerbe",
    "sg:postcode":"4125",
    "sg:province":"Basel-Stadt",
    "wof:name":"Sari Gmbh Geb\u00e4udereinigungen",
    "wof:placetype":"venue"
},
  "geometry": {"coordinates":[7.6363039017,47.5756645203],"type":"Point"}
}