{
  "type": "Feature",
  "properties": {
    "iso:country":"CH",
    "sg:address":"Via Stazione",
    "sg:city":"Airolo",
    "sg:orig_category":"Wirtschafts- and Arbeitgeberverb\u00e4nde",
    "sg:phone":"+41 91 869 22 98",
    "sg:postcode":"6780",
    "sg:province":"Ticino",
    "wof:name":"Fed.esercenti & Albergatori Ti Albergo Forni",
    "wof:placetype":"venue"
},
  "geometry": {"coordinates":[8.6040563583,46.5281944275],"type":"Point"}
}