{
  "type": "Feature",
  "properties": {
    "iso:country":"CH",
    "sg:address":"Avenue De Rhodanie 2 1000 Lausanne. Postfach",
    "sg:city":"Lausanne",
    "sg:orig_category":"Sonstiger Grosshandel",
    "sg:postcode":"1003",
    "sg:province":"Vaud",
    "wof:name":"L'eclipse S\u00e0rl",
    "wof:placetype":"venue"
},
  "geometry": {"coordinates":[6.6246881485,46.5079307556],"type":"Point"}
}