{
  "type": "Feature",
  "properties": {
    "iso:country":"CH",
    "sg:address":"Avenue De Ch\u00e2telain 1",
    "sg:city":"Rolle",
    "sg:orig_category":"Herstellung von Tanks U Sammelbeh\u00e4ltern aus Metall",
    "sg:phone":"+41 21 825 36 90",
    "sg:postcode":"1180",
    "sg:province":"Vaud",
    "wof:name":"Claude Meylan R\u00e9vision Citernes Service",
    "wof:placetype":"venue"
},
  "geometry": {"coordinates":[6.3413820267,46.4608612061],"type":"Point"}
}