{
  "type": "Feature",
  "properties": {
    "iso:country":"CH",
    "sg:address":"Egg\u00e4cker 15",
    "sg:city":"Berikon",
    "sg:orig_category":"RESTAURANTS: TEA-ROOMS",
    "sg:postcode":"8965",
    "sg:province":"Aargau",
    "wof:name":"Die Bar Im Stalden Gmbh",
    "wof:placetype":"venue"
},
  "geometry": {"coordinates":[8.3751964569,47.3479957581],"type":"Point"}
}