{
  "type": "Feature",
  "properties": {
    "iso:country":"CH",
    "sg:address":"Chemin Des Plantaz 44",
    "sg:city":"Nyon",
    "sg:orig_category":"Allgemeiner Hoch U Tiefbau Architekturb\u00fcros",
    "sg:phone":"+41 71 380 07 47",
    "sg:postcode":"1260",
    "sg:province":"Vaud",
    "wof:name":"Rensch-haus Ag",
    "wof:placetype":"venue"
},
  "geometry": {"coordinates":[9.244817,47.416916],"type":"Point"}
}