{
  "type": "Feature",
  "properties": {
    "iso:country":"CH",
    "sg:address":"Im Meierhof 7",
    "sg:city":"Olten",
    "sg:orig_category":"Sanit\u00e4r U Heizungsinstallation",
    "sg:phone":"+41 62 296 35 32",
    "sg:postcode":"4600",
    "sg:province":"Solothurn",
    "wof:name":"Martin Str\u00e4hl Heizungen Oelfeuerungen",
    "wof:placetype":"venue"
},
  "geometry": {"coordinates":[7.9237370491,47.3556518555],"type":"Point"}
}