{
  "type": "Feature",
  "properties": {
    "iso:country":"CH",
    "sg:address":"Unterm\u00fcli 7",
    "sg:city":"Zug",
    "sg:orig_category":"Gymnastik U Fitnesszentren",
    "sg:phone":"+41 41 761 10 12",
    "sg:postcode":"6300",
    "sg:province":"Zug",
    "wof:name":"Fitness-& Athletiksport Studio",
    "wof:placetype":"venue"
},
  "geometry": {"coordinates":[8.5177021027,47.1804161072],"type":"Point"}
}