{
  "type": "Feature",
  "properties": {
    "iso:country":"CH",
    "sg:address":"Obere Gasse 41",
    "sg:city":"Chur",
    "sg:classifiers":[
        {
            "category":"Restaurant",
            "type":"Food & Drink"
        }
    ],
    "sg:phone":"+41 71 222 45 37",
    "sg:postcode":"7000",
    "sg:province":"Graubunden",
    "wof:name":"Restaurant Bodega Ram\u00f2n",
    "wof:placetype":"venue"
},
  "geometry": {"coordinates":[9.3718643188,47.420085907],"type":"Point"}
}