{
  "type": "Feature",
  "properties": {
    "iso:country":"CH",
    "sg:address":"Bernstrasse 20a 3110 M\u00fcnsingen. Postfach 1312",
    "sg:city":"M\u00fcnsingen",
    "sg:orig_category":"Herstellung von Metallerzeugnissen ohne Maschinenbau",
    "sg:phone":"+41 31 721 08 48",
    "sg:postcode":"3110",
    "sg:province":"Bern",
    "wof:name":"Howel Ag",
    "wof:placetype":"venue"
},
  "geometry": {"coordinates":[7.5616621971,46.8780403137],"type":"Point"}
}