{
  "type": "Feature",
  "properties": {
    "iso:country":"CH",
    "sg:address":"Im R\u00fcschell 1",
    "sg:city":"Kerzers",
    "sg:orig_category":"Grosshandel mit lebenden Tieren",
    "sg:phone":"+41 31 755 69 26",
    "sg:postcode":"3210",
    "sg:province":"Fribourg",
    "wof:name":"Beat Notz Pferdehandel",
    "wof:placetype":"venue"
},
  "geometry": {"coordinates":[7.2040791512,46.970123291],"type":"Point"}
}