{
  "type": "Feature",
  "properties": {
    "iso:country":"CH",
    "sg:address":"Dorfstrasse 23",
    "sg:city":"Bellach",
    "sg:orig_category":"Maler U Glasergewerbe",
    "sg:phone":"+41 32 618 37 81",
    "sg:postcode":"4512",
    "sg:province":"Solothurn",
    "wof:name":"Kammer Urs",
    "wof:placetype":"venue"
},
  "geometry": {"coordinates":[7.4952311516,47.2126655579],"type":"Point"}
}