{
  "type": "Feature",
  "properties": {
    "iso:country":"CH",
    "sg:address":"Kirchgasse 4",
    "sg:city":"B\u00fctschwil",
    "sg:orig_category":"Detailhandel mit Radio U Fernsehger\u00e4ten",
    "sg:phone":"+41 71 983 23 77",
    "sg:postcode":"9606",
    "sg:province":"St. Gallen",
    "wof:name":"Felix Stadler Radio-tv-video",
    "wof:placetype":"venue"
},
  "geometry": {"coordinates":[9.0728216171,47.3591003418],"type":"Point"}
}