{
  "type": "Feature",
  "properties": {
    "iso:country":"CH",
    "sg:address":"Oberer Graben 3 4600 Olten. Postfach",
    "sg:city":"Olten",
    "sg:orig_category":"Detailhandel mit medizinischen U orthop\u00e4dischen Artikeln Herstellung von medizinischen U chirurgisch",
    "sg:phone":"+41 21 922 15 22",
    "sg:postcode":"4603",
    "sg:province":"Solothurn",
    "wof:name":"Audison S\u00e0rl",
    "wof:placetype":"venue"
},
  "geometry": {"coordinates":[5.1808700562,45.8973388672],"type":"Point"}
}