{
  "type": "Feature",
  "properties": {
    "iso:country":"CH",
    "sg:address":"Aegerten Rue D' 19 2503 Biel/bienne. Postfach",
    "sg:city":"Biel/bienne",
    "sg:orig_category":"Betrieb U technische Hilfsdienste des Kultur U Unterhaltungswesens",
    "sg:phone":"+41 71 279 33 00",
    "sg:postcode":"2502",
    "sg:province":"Bern",
    "wof:name":"Vita.life International Marketing Center Ag Veranstaltungen, Seminaren, Schulungen; Konzeption, Vermittlung Usw",
    "wof:placetype":"venue"
},
  "geometry": {"coordinates":[9.361107,47.423065],"type":"Point"}
}