{
  "type": "Feature",
  "properties": {
    "iso:country":"CH",
    "sg:address":"Rue De L'eglise 3",
    "sg:city":"Echandens",
    "sg:orig_category":"Architekturb\u00fcros",
    "sg:phone":"+41 79 212 89 93",
    "sg:postcode":"1026",
    "sg:province":"Vaud",
    "wof:name":"Daniel Monod Bureau D'architecture",
    "wof:placetype":"venue"
},
  "geometry": {"coordinates":[6.53714,46.532021],"type":"Point"}
}