{
  "type": "Feature",
  "properties": {
    "iso:country":"CH",
    "sg:address":"Crasta",
    "sg:city":"Fex",
    "sg:orig_category":"Dachdeckerei Zimmerei, Dachdeckerei, Bauspenglerei U Abdichtung",
    "sg:phone":"+41 81 826 56 75",
    "sg:postcode":"7514",
    "sg:province":"Graubunden",
    "wof:name":"Meuli Peter Ag",
    "wof:placetype":"venue"
},
  "geometry": {"coordinates":[9.76417,46.428761],"type":"Point"}
}