{
  "type": "Feature",
  "properties": {
    "iso:country":"CH",
    "sg:address":"Hirschg\u00e4sslein 40",
    "sg:city":"Basel",
    "sg:orig_category":"Berufsberatungen",
    "sg:phone":"+41 61 272 85 23",
    "sg:postcode":"4051",
    "sg:province":"Basel-Stadt",
    "wof:name":"Erich Ebi Berufsberatung",
    "wof:placetype":"venue"
},
  "geometry": {"coordinates":[7.592732,47.551044],"type":"Point"}
}