{
  "type": "Feature",
  "properties": {
    "iso:country":"CH",
    "sg:address":"Bachserstrasse 113",
    "sg:city":"Fisibach",
    "sg:orig_category":"Maler U Glasergewerbe Malerei",
    "sg:phone":"+41 18581743",
    "sg:postcode":"5467",
    "sg:province":"Aargau",
    "wof:name":"K. Rutschmann Ag Malergesch\u00e4ft",
    "wof:placetype":"venue"
},
  "geometry": {"coordinates":[8.4099302292,47.5626144409],"type":"Point"}
}