{
  "type": "Feature",
  "properties": {
    "addr:full":"Rue Pichard 20 1003 Lausanne. Postfach Lausanne Vaud 1002",
    "addr:housenumber":"20",
    "addr:postcode":"1003;postfach;1002",
    "addr:street":"Rue Pichard",
    "iso:country":"CH",
    "sg:address":"Rue Pichard 20 1003 Lausanne. Postfach",
    "sg:city":"Lausanne",
    "sg:orig_category":"Allgemeinbildende weiterf\u00fchrende Schulen",
    "sg:phone":"+41 21 312 98 07",
    "sg:postcode":"1002",
    "sg:province":"Vaud",
    "wof:name":"Ecole Alphalif, Lazreg",
    "wof:placetype":"venue"
},
  "geometry": {"coordinates":[6.63076,46.521515],"type":"Point"}
}