{
  "type": "Feature",
  "properties": {
    "iso:country":"CH",
    "sg:address":"1115",
    "sg:city":"Vullierens",
    "sg:orig_category":"Herstellung von K\u00e4se Verwertung von Milch",
    "sg:postcode":"1115",
    "sg:province":"Vaud",
    "wof:name":"Sch\u00fcpbach Christian.",
    "wof:placetype":"venue"
},
  "geometry": {"coordinates":[7.3696432114,47.1394119263],"type":"Point"}
}