{
  "type": "Feature",
  "properties": {
    "iso:country":"CH",
    "sg:address":"Gassa Sur\u00f2 8",
    "sg:city":"Domat/ems",
    "sg:orig_category":"Maschinen-Fabrikation",
    "sg:phone":"+41 81 630 32 70",
    "sg:postcode":"7013",
    "sg:province":"Graubunden",
    "wof:name":"Pro Technologies Gmbh",
    "wof:placetype":"venue"
},
  "geometry": {"coordinates":[9.4508037567,46.8349876404],"type":"Point"}
}