{
  "type": "Feature",
  "properties": {
    "iso:country":"CH",
    "sg:address":"Riedackerstrasse 17",
    "sg:city":"R\u00fcmlang",
    "sg:orig_category":"Herstellung von Metallerzeugnissen ohne Maschinenbau",
    "sg:phone":"+41 18187450",
    "sg:postcode":"8153",
    "sg:province":"Z\u00fcrich",
    "wof:name":"Letrona Ag Mastbau & Geh\u00e4usetechnik",
    "wof:placetype":"venue"
},
  "geometry": {"coordinates":[8.523191452,47.4625473022],"type":"Point"}
}