{
  "type": "Feature",
  "properties": {
    "iso:country":"CH",
    "sg:address":"Schweizerhubelstrasse 1 3052 Zollikofen. Postfach",
    "sg:city":"Zollikofen",
    "sg:orig_category":"Unternehmensberatung",
    "sg:postcode":"3052",
    "sg:province":"Bern",
    "wof:name":"Intenso Consulting Voegeli Andreas",
    "wof:placetype":"venue"
},
  "geometry": {"coordinates":[7.4480700493,46.9991607666],"type":"Point"}
}