{
  "type": "Feature",
  "properties": {
    "iso:country":"CH",
    "sg:address":"Chemin Isaac-machard 6 1290 Versoix. Postfach",
    "sg:city":"Versoix",
    "sg:orig_category":"Non-Classified Establishments",
    "sg:postcode":"1290",
    "sg:province":"Gen\u00e8ve",
    "wof:name":"Probst Ict-consulting",
    "wof:placetype":"venue"
},
  "geometry": {"coordinates":[6.1669921875,46.286365509],"type":"Point"}
}