{
  "type": "Feature",
  "properties": {
    "iso:country":"CH",
    "sg:address":"Route De La Plaine 20",
    "sg:city":"Denges",
    "sg:orig_category":"Tankstellen",
    "sg:postcode":"1026",
    "sg:province":"Vaud",
    "wof:name":"Rossier Michel",
    "wof:placetype":"venue"
},
  "geometry": {"coordinates":[6.5371022224,46.5249404907],"type":"Point"}
}