{
  "type": "Feature",
  "properties": {
    "iso:country":"CH",
    "sg:address":"Marktgasse 14 8001 Z\u00fcrich. Postfach",
    "sg:city":"Z\u00fcrich",
    "sg:orig_category":"Betrieb U technische Hilfsdienste des Kultur U Unterhaltungswesens",
    "sg:postcode":"8001",
    "sg:province":"Z\u00fcrich",
    "wof:name":"Rr Music Enterprises S.a.",
    "wof:placetype":"venue"
},
  "geometry": {"coordinates":[6.931085,46.990334],"type":"Point"}
}