{
  "type": "Feature",
  "properties": {
    "iso:country":"CH",
    "sg:address":"Leep\u00fcntstrasse 28 8600 D\u00fcbendorf. Postfach",
    "sg:city":"D\u00fcbendorf",
    "sg:orig_category":"Herstellung von keramischen Wand U Bodenfliesen U platten Verlegen von Fliesen U Platten",
    "sg:phone":"+41 18212692",
    "sg:postcode":"8600",
    "sg:province":"Z\u00fcrich",
    "wof:name":"Tresch Ag, Wand Und Bodenbel\u00e4ge",
    "wof:placetype":"venue"
},
  "geometry": {"coordinates":[8.6175794601,47.395160675],"type":"Point"}
}