{
  "type": "Feature",
  "properties": {
    "iso:country":"CH",
    "sg:address":"Lothringerstrasse 106 4056 Basel. Postfach",
    "sg:city":"Basel",
    "sg:orig_category":"Gymnastik U Fitnesszentren",
    "sg:phone":"+41 61 321 86 85",
    "sg:postcode":"4013",
    "sg:province":"Basel-Stadt",
    "wof:name":"Soujitra Keller Fitness-club",
    "wof:placetype":"venue"
},
  "geometry": {"coordinates":[7.5759239197,47.5701599121],"type":"Point"}
}