{
  "type": "Feature",
  "properties": {
    "iso:country":"CH",
    "sg:address":"Stampfenbachstrasse 48 8006 Z\u00fcrich. Postfach 155",
    "sg:city":"Z\u00fcrich",
    "sg:orig_category":"Advokaturb\u00fcros",
    "sg:phone":"+41 13657777",
    "sg:postcode":"8035",
    "sg:province":"Z\u00fcrich",
    "wof:name":"Waeber Ferrari & Kupper Advokaturb\u00fcro",
    "wof:placetype":"venue"
},
  "geometry": {"coordinates":[8.542853,47.380653],"type":"Point"}
}