{
  "type": "Feature",
  "properties": {
    "iso:country":"CH",
    "sg:address":"Metzerstrasse 29",
    "sg:city":"Basel",
    "sg:orig_category":"W\u00e4schereien",
    "sg:phone":"+41 61 321 66 72",
    "sg:postcode":"4056",
    "sg:province":"Basel-Stadt",
    "wof:name":"Elisabeth L\u00fcscher W\u00e4scherei & Gl\u00e4tterei",
    "wof:placetype":"venue"
},
  "geometry": {"coordinates":[7.5770039558,47.5643577576],"type":"Point"}
}