{
  "type": "Feature",
  "properties": {
    "iso:country":"CH",
    "sg:address":"Amerbachstrasse 53",
    "sg:city":"Basel",
    "sg:orig_category":"Grosshandel mit Getr\u00e4nken Grosshandel mit Wein U Spirituosen",
    "sg:phone":"+41 61 691 19 20",
    "sg:postcode":"4057",
    "sg:province":"Basel-Stadt",
    "wof:name":"Vinenzo, Cavaliere Cuzzucoli E. Gmbh",
    "wof:placetype":"venue"
},
  "geometry": {"coordinates":[7.5938439369,47.5694351196],"type":"Point"}
}