{
  "type": "Feature",
  "properties": {
    "iso:country":"CH",
    "sg:address":"Baslerstrasse 7",
    "sg:city":"Binningen",
    "sg:classifiers":[
        {
            "category":"Restaurant",
            "type":"Food & Drink"
        }
    ],
    "sg:phone":"+41 17133505",
    "sg:postcode":"4102",
    "sg:province":"Basel-Landschaft",
    "wof:name":"Restaurant Albis",
    "wof:placetype":"venue"
},
  "geometry": {"coordinates":[8.5205211639,47.2764053345],"type":"Point"}
}