{
  "type": "Feature",
  "properties": {
    "iso:country":"CH",
    "sg:address":"Ch. De La Mousse 36",
    "sg:city":"Ch\u00eane-bourg",
    "sg:orig_category":"Unclassifiable Establishments",
    "sg:postcode":"1225",
    "sg:province":"Gen\u00e8ve",
    "wof:name":"Si La Mousse",
    "wof:placetype":"venue"
},
  "geometry": {"coordinates":[6.1991500854,46.197265625],"type":"Point"}
}