{
  "type": "Feature",
  "properties": {
    "iso:country":"CH",
    "sg:address":"Dorf",
    "sg:city":"Wyssachen",
    "sg:orig_category":"Detailhandel mit Beleuchtungs U Haushaltsgegenst\u00e4nden",
    "sg:phone":"+41 71 755 11 20",
    "sg:postcode":"4954",
    "sg:province":"Bern",
    "wof:name":"Sandmann Ag Glas & Porzellan",
    "wof:placetype":"venue"
},
  "geometry": {"coordinates":[9.540268,47.377998],"type":"Point"}
}