{
  "type": "Feature",
  "properties": {
    "iso:country":"CH",
    "sg:address":"Josefengasse 6",
    "sg:city":"Dornach",
    "sg:orig_category":"Fachdetailhandel in Verkaufsr\u00e4umen",
    "sg:phone":"+41 61 701 27 30",
    "sg:postcode":"4143",
    "sg:province":"Solothurn",
    "wof:name":"Tiziani C., Carmen-floristik",
    "wof:placetype":"venue"
},
  "geometry": {"coordinates":[7.615737915,47.4789505005],"type":"Point"}
}