{
  "type": "Feature",
  "properties": {
    "iso:country":"CH",
    "sg:address":"Lavorgo 6746 Lavorgo. Postfach",
    "sg:city":"Lavorgo",
    "sg:orig_category":"Herstellung von sonstigen landwirtschaftlichen Maschinen",
    "sg:phone":"+41 21 881 26 81",
    "sg:postcode":"6746",
    "sg:province":"Ticino",
    "wof:name":"Engler J. Rasen Und Motorger\u00e4te",
    "wof:placetype":"venue"
},
  "geometry": {"coordinates":[7.5574388504,46.9344978333],"type":"Point"}
}