{
  "type": "Feature",
  "properties": {
    "addr:full":"Baslerstrasse 310 Allschwil Basel-Landschaft 4123",
    "addr:housenumber":"310",
    "addr:postcode":"4123",
    "addr:street":"Baslerstrasse",
    "iso:country":"CH",
    "sg:address":"Baslerstrasse 310",
    "sg:city":"Allschwil",
    "sg:orig_category":"Detailhandel mit B\u00fcromaschinen U einrichtungen Detailhandel mit Schreib U Papeteriewaren",
    "sg:phone":"+41 61 481 62 11",
    "sg:postcode":"4123",
    "sg:province":"Basel-Landschaft",
    "wof:name":"Erwin Peyer Papeterie/b\u00fcrobedarf",
    "wof:placetype":"venue"
},
  "geometry": {"coordinates":[7.559991,47.557453],"type":"Point"}
}