{
  "type": "Feature",
  "properties": {
    "iso:country":"CH",
    "sg:address":"Mellingerstrasse 138",
    "sg:city":"Baden",
    "sg:orig_category":"Handelsvermittlung U Grosshandel Handelsvermittlung U Grosshandel mit Automobilteilen U Zubeh\u00f6r",
    "sg:phone":"+41 56 203 42 10",
    "sg:postcode":"5400",
    "sg:province":"Aargau",
    "wof:name":"Derendinger Ag Autobestandteile Autozubeh\u00f6r",
    "wof:placetype":"venue"
},
  "geometry": {"coordinates":[8.2940759659,47.4675521851],"type":"Point"}
}