{
  "type": "Feature",
  "properties": {
    "iso:country":"CH",
    "sg:address":"L\u00fctzelmattweg 8",
    "sg:city":"Luzern",
    "sg:orig_category":"Architekturb\u00fcros",
    "sg:phone":"+41 41 226 36 66",
    "sg:postcode":"6006",
    "sg:province":"Luzern",
    "wof:name":"Andreas Moser Architekturb\u00fcro",
    "wof:placetype":"venue"
},
  "geometry": {"coordinates":[8.331601,47.059242],"type":"Point"}
}