{
  "type": "Feature",
  "properties": {
    "iso:country":"CH",
    "sg:address":"Kirchbergstrasse 70",
    "sg:city":"Burgdorf",
    "sg:classifiers":[
        {
            "category":"Travel",
            "subcategory":"Hotels & Motels",
            "type":"Entertainment"
        }
    ],
    "sg:phone":"+41 34 422 22 75",
    "sg:postcode":"3400",
    "sg:province":"Bern",
    "sg:tags":[
        "hotels",
        "mit",
        "restaurant"
    ],
    "wof:name":"Hotel Emmenhof",
    "wof:placetype":"venue"
},
  "geometry": {"coordinates":[7.6192221642,47.0624542236],"type":"Point"}
}