{
  "type": "Feature",
  "properties": {
    "iso:country":"CH",
    "sg:address":"Bernstrasse 66 3184 W\u00fcnnewil. Postfach",
    "sg:city":"Flamatt",
    "sg:orig_category":"Instandhaltung U Reparatur von Automobilen",
    "sg:phone":"+41 21 968 22 22",
    "sg:postcode":"3175",
    "sg:province":"Fribourg",
    "wof:name":"Garage Heiniger J. Sa",
    "wof:placetype":"venue"
},
  "geometry": {"coordinates":[6.9235172272,46.3966560364],"type":"Point"}
}