{
  "type": "Feature",
  "properties": {
    "iso:country":"CH",
    "sg:address":"St\u00fcsslingerstrasse 54 5015 Niedererlinsbach. Postfach",
    "sg:city":"Niedererlinsbach",
    "sg:orig_category":"Wirtschaftspr\u00fcfung, Steuerberatung U Treuhand",
    "sg:phone":"+41 62 844 03 33",
    "sg:postcode":"5015",
    "sg:province":"Solothurn",
    "wof:name":"Gusamo Ag Treuhand",
    "wof:placetype":"venue"
},
  "geometry": {"coordinates":[8.0013523102,47.3994789124],"type":"Point"}
}