{
  "type": "Feature",
  "properties": {
    "iso:country":"CH",
    "sg:address":"Loup Chemin Au 16 1027 Lonay. Postfach",
    "sg:city":"Lonay",
    "sg:orig_category":"Unternehmensberatung",
    "sg:phone":"+41 21 801 40 47",
    "sg:postcode":"1027",
    "sg:province":"Vaud",
    "wof:name":"Boscarato Doliano, Conseiller D'entreprise Ex\u00e9cutions De Mandats De Recherche, D'analyse Et De Conseils D.le Domaine Del'\u00e9conomie D'entreprise Etc",
    "wof:placetype":"venue"
},
  "geometry": {"coordinates":[6.520678997,46.5264778137],"type":"Point"}
}