{
  "type": "Feature",
  "properties": {
    "iso:country":"CH",
    "sg:address":"Chemin De La Viane 37",
    "sg:city":"Mont-sur-lausanne",
    "sg:orig_category":"Unternehmensberatung",
    "sg:phone":"+41 79 210 69 60",
    "sg:postcode":"1052",
    "sg:province":"Vaud",
    "wof:name":"Wos Management & Marketing, Osterwalder W. Ed.",
    "wof:placetype":"venue"
},
  "geometry": {"coordinates":[6.6265788078,46.5616073608],"type":"Point"}
}