{
  "type": "Feature",
  "properties": {
    "iso:country":"CH",
    "sg:address":"4458",
    "sg:city":"Eptingen",
    "sg:orig_category":"Vereine Musik/Blasmusik",
    "sg:phone":"+41 79 508 05 76",
    "sg:postcode":"4458",
    "sg:province":"Basel-Landschaft",
    "wof:name":"Musikgesellschaft",
    "wof:placetype":"venue"
},
  "geometry": {"coordinates":[7.820827961,47.3850898743],"type":"Point"}
}