{
  "type": "Feature",
  "properties": {
    "iso:country":"CH",
    "sg:address":"Ettiswilerstrasse 26",
    "sg:city":"Willisau",
    "sg:classifiers":[
        {
            "category":"Travel",
            "subcategory":"Hotels & Motels",
            "type":"Entertainment"
        }
    ],
    "sg:phone":"+41 41 972 60 80",
    "sg:postcode":"6130",
    "sg:province":"Luzern",
    "sg:tags":[
        "equipment",
        "hotels",
        "restaurant"
    ],
    "wof:name":"Bel Etage Ag",
    "wof:placetype":"venue"
},
  "geometry": {"coordinates":[7.996846199,47.1256637573],"type":"Point"}
}