{
  "type": "Feature",
  "properties": {
    "iso:country":"CH",
    "sg:address":"Neugutstrasse 49",
    "sg:city":"D\u00fcbendorf",
    "sg:orig_category":"Sportvereine Sch\u00fctzen Armbrust",
    "sg:phone":"+41 52 741 26 76",
    "sg:postcode":"8600",
    "sg:province":"Z\u00fcrich",
    "wof:name":"Armbrustsch\u00fctzen.hohenklingen",
    "wof:placetype":"venue"
},
  "geometry": {"coordinates":[8.859413147,47.6621246338],"type":"Point"}
}