{
  "type": "Feature",
  "properties": {
    "iso:country":"CH",
    "sg:address":"Rue Du Perron 16",
    "sg:city":"Gen\u00e8ve",
    "sg:orig_category":"Vereine Literarische and Lese",
    "sg:phone":"+41 22 311 50 76",
    "sg:postcode":"1204",
    "sg:province":"Gen\u00e8ve",
    "wof:name":"Societ\u00e0 Dante Alighieri",
    "wof:placetype":"venue"
},
  "geometry": {"coordinates":[6.1475710869,46.2018661499],"type":"Point"}
}