{
  "type": "Feature",
  "properties": {
    "iso:country":"CH",
    "sg:address":"Buchholzstrasse 141",
    "sg:city":"Z\u00fcrich",
    "sg:orig_category":"Herstellung von Duft U K\u00f6rperpflegemitteln",
    "sg:postcode":"8053",
    "sg:province":"Z\u00fcrich",
    "wof:name":"Mynn John Alpine Beauty Care. Kosmetische Produkte Aus Alpinen Kr\u00e4uter; Handel.",
    "wof:placetype":"venue"
},
  "geometry": {"coordinates":[8.5905323029,47.3612709045],"type":"Point"}
}