{
  "type": "Feature",
  "properties": {
    "iso:country":"CH",
    "sg:address":"Rue Du Cin\u00e9ma 1",
    "sg:city":"Tramelan",
    "sg:orig_category":"Kinos",
    "sg:phone":"+41 32 487 45 61",
    "sg:postcode":"2720",
    "sg:province":"Bern",
    "wof:name":"Cinematographe-royal",
    "wof:placetype":"venue"
},
  "geometry": {"coordinates":[7.1019649506,47.2227134705],"type":"Point"}
}