{
  "type": "Feature",
  "properties": {
    "iso:country":"CH",
    "sg:address":"Marmorgasse 10",
    "sg:city":"Z\u00fcrich",
    "sg:orig_category":"Solarien",
    "sg:phone":"+41 19503636",
    "sg:postcode":"8004",
    "sg:province":"Z\u00fcrich",
    "wof:name":"Br\u00e4unungsstudio Sunspot Solarien",
    "wof:placetype":"venue"
},
  "geometry": {"coordinates":[8.7834348679,47.3666038513],"type":"Point"}
}