{
  "type": "Feature",
  "properties": {
    "iso:country":"CH",
    "sg:address":"Glennerstrasse 10 7130 Ilanz. Postfach",
    "sg:city":"Ilanz",
    "sg:orig_category":"Detailhandel mit Fleisch U Fleischwaren",
    "sg:phone":"+41 81 925 15 64",
    "sg:postcode":"7130",
    "sg:province":"Graubunden",
    "wof:name":"Zimmermann Jean-claude Stadt-metzg",
    "wof:placetype":"venue"
},
  "geometry": {"coordinates":[9.2063398361,46.7740936279],"type":"Point"}
}