{
  "type": "Feature",
  "properties": {
    "iso:country":"CH",
    "sg:address":"Rue Du Village 22",
    "sg:city":"Ch\u00e2telard-lutry",
    "sg:orig_category":"Gem\u00fcsebau Rebbau",
    "sg:phone":"+41 21 791 48 84",
    "sg:postcode":"1095",
    "sg:province":"Vaud",
    "wof:name":"Pierre Dentan Maraicher Vigneron",
    "wof:placetype":"venue"
},
  "geometry": {"coordinates":[6.6937718391,46.5073356628],"type":"Point"}
}