{
  "type": "Feature",
  "properties": {
    "iso:country":"CH",
    "sg:address":"Standstrasse 6",
    "sg:city":"Arbon",
    "sg:orig_category":"Vorschulen, Kinderg\u00e4rten",
    "sg:phone":"+41 52 383 19 44",
    "sg:postcode":"9320",
    "sg:province":"Thurgau",
    "wof:name":"Kindergarten",
    "wof:placetype":"venue"
},
  "geometry": {"coordinates":[8.8217439651,47.4449424744],"type":"Point"}
}