{
  "type": "Feature",
  "properties": {
    "iso:country":"CH",
    "sg:address":"Bergli",
    "sg:city":"Churwalden",
    "sg:orig_category":"Fahrschulen, Flugschulen",
    "sg:phone":"+41 79 238 34 34",
    "sg:postcode":"7075",
    "sg:province":"Graubunden",
    "wof:name":"Christian Palancon Autofahrschule",
    "wof:placetype":"venue"
},
  "geometry": {"coordinates":[9.5439338684,46.7758483887],"type":"Point"}
}