{
  "type": "Feature",
  "properties": {
    "iso:country":"CH",
    "sg:address":"Wilenstrasse 2 9322 Egnach. Postfach",
    "sg:city":"Egnach",
    "sg:orig_category":"Unternehmensberatung Wirtschaftspr\u00fcfung, Steuerberatung U Treuhand",
    "sg:phone":"+41 52 722 41 58",
    "sg:postcode":"9322",
    "sg:province":"Thurgau",
    "wof:name":"Steuri Treuhand Gmbh",
    "wof:placetype":"venue"
},
  "geometry": {"coordinates":[9.3803682327,47.5447006226],"type":"Point"}
}