{
  "type": "Feature",
  "properties": {
    "iso:country":"CH",
    "sg:address":"Tavel Route De 4",
    "sg:city":"Fribourg",
    "sg:orig_category":"Herstellung von B\u00fcromaschinen",
    "sg:phone":"+41 19216262",
    "sg:postcode":"1700",
    "sg:province":"Fribourg",
    "wof:name":"Kontroll-systeme W. Neuhaus",
    "wof:placetype":"venue"
},
  "geometry": {"coordinates":[8.6837940216,47.2632446289],"type":"Point"}
}