{
  "type": "Feature",
  "properties": {
    "iso:country":"CH",
    "sg:address":"Kalchmatt",
    "sg:city":"Zollbr\u00fcck",
    "sg:orig_category":"Herstellung von sonstigen Fahrzeugen Innenausbau",
    "sg:phone":"+41 34 496 73 75",
    "sg:postcode":"3436",
    "sg:province":"Bern",
    "wof:name":"Hans Rufer Wagnerei & Innenausbau",
    "wof:placetype":"venue"
},
  "geometry": {"coordinates":[7.7411880493,46.9713478088],"type":"Point"}
}