{
  "type": "Feature",
  "properties": {
    "iso:country":"CH",
    "sg:address":"Loch\u00e4ckerstrasse 31",
    "sg:city":"Kloten",
    "sg:orig_category":"Werbevermittlung",
    "sg:phone":"+41 18133730",
    "sg:postcode":"8302",
    "sg:province":"Z\u00fcrich",
    "wof:name":"Peter M\u00fcller Werbeagentur",
    "wof:placetype":"venue"
},
  "geometry": {"coordinates":[8.5913295746,47.4446640015],"type":"Point"}
}