{
  "type": "Feature",
  "properties": {
    "iso:country":"CH",
    "sg:address":"B\u00fchl 3700 Spiez. Postfach",
    "sg:city":"Hondrich",
    "sg:orig_category":"S\u00e4ge, Hobel U Holzimpr\u00e4gnierwerke",
    "sg:postcode":"3702",
    "sg:province":"Bern",
    "wof:name":"Kr\u00f6pfli R.",
    "wof:placetype":"venue"
},
  "geometry": {"coordinates":[7.6786088943,46.6670951843],"type":"Point"}
}