{
  "type": "Feature",
  "properties": {
    "iso:country":"CH",
    "sg:address":"Bahnhofstrasse 106",
    "sg:city":"Z\u00fcrich",
    "sg:orig_category":"Gesundheitswesen",
    "sg:phone":"+41 19298111",
    "sg:postcode":"8001",
    "sg:province":"Z\u00fcrich",
    "wof:name":"Stiftung F\u00fcr Psychisch Behinderte F\u00fchrung Sozialpsychiatrischer Einrichtungen Usw",
    "wof:placetype":"venue"
},
  "geometry": {"coordinates":[8.7200746536,47.2700691223],"type":"Point"}
}