{
  "type": "Feature",
  "properties": {
    "addr:full":"Sternenhofstrasse 15 Reinach Basel-Landschaft 4153",
    "addr:housenumber":"15",
    "addr:postcode":"4153",
    "addr:street":"Sternenhofstrasse",
    "iso:country":"CH",
    "sg:address":"Sternenhofstrasse 15",
    "sg:city":"Reinach",
    "sg:orig_category":"Electromagnetic Compatibility Emc Measurement For Vehicles",
    "sg:phone":"+41 61 717 91 91",
    "sg:postcode":"4153",
    "sg:province":"Basel-Landschaft",
    "wof:name":"Em Test Ag",
    "wof:placetype":"venue"
},
  "geometry": {"coordinates":[7.59609,47.489349],"type":"Point"}
}