{
  "type": "Feature",
  "properties": {
    "iso:country":"CH",
    "sg:address":"St-germain",
    "sg:city":"Savi\u00e8se",
    "sg:orig_category":"Fachdetailhandel mit pharmazeutischen Produkten",
    "sg:phone":"+41 27 395 11 21",
    "sg:postcode":"1965",
    "sg:province":"Valais",
    "wof:name":"Anna Luyet Pharmacie De Savi\u00e8se",
    "wof:placetype":"venue"
},
  "geometry": {"coordinates":[7.3478050232,46.2532310486],"type":"Point"}
}