{
  "type": "Feature",
  "properties": {
    "iso:country":"CH",
    "sg:address":"Holzikerstrasse 8",
    "sg:city":"Sch\u00f6ftland",
    "sg:orig_category":"Detailhandel mit Waren verschiedener Art, Hauptrichtung Nahrungsmittel",
    "sg:phone":"+41 71 223 31 63",
    "sg:postcode":"5040",
    "sg:province":"Aargau",
    "wof:name":"Erwin Fuggini Fr\u00fcchte-& Gem\u00fcsehandel",
    "wof:placetype":"venue"
},
  "geometry": {"coordinates":[9.3634557724,47.4272842407],"type":"Point"}
}