{
  "type": "Feature",
  "properties": {
    "iso:country":"CH",
    "sg:address":"Plazza Staziun 5",
    "sg:city":"Domat/ems",
    "sg:classifiers":[
        {
            "category":"Restaurant",
            "type":"Food & Drink"
        }
    ],
    "sg:phone":"+41 81 633 11 60",
    "sg:postcode":"7013",
    "sg:province":"Graubunden",
    "wof:name":"Restaurant Rh\u00e4t.bahn",
    "wof:placetype":"venue"
},
  "geometry": {"coordinates":[9.4523239136,46.8330917358],"type":"Point"}
}