{
  "type": "Feature",
  "properties": {
    "iso:country":"CH",
    "sg:address":"Alpenblick 7",
    "sg:city":"Cham",
    "sg:orig_category":"Reparatur von Uhren U Schmuck",
    "sg:phone":"+41 41 781 37 33",
    "sg:postcode":"6330",
    "sg:province":"Zug",
    "wof:name":"Willy Sch\u00e4dler Uhrmacher",
    "wof:placetype":"venue"
},
  "geometry": {"coordinates":[8.4747018814,47.184135437],"type":"Point"}
}