{
  "type": "Feature",
  "properties": {
    "iso:country":"CH",
    "sg:address":"Bahnhofstrasse 26",
    "sg:city":"Langenthal",
    "sg:orig_category":"Unclassifiable Establishments",
    "sg:postcode":"4900",
    "sg:province":"Bern",
    "wof:name":"Dr.med.simon Schneeberger Spezialarzt Fmh",
    "wof:placetype":"venue"
},
  "geometry": {"coordinates":[7.7866802216,47.2135810852],"type":"Point"}
}