{
  "type": "Feature",
  "properties": {
    "iso:country":"CH",
    "sg:address":"Holgasse 37",
    "sg:city":"Mellikon",
    "sg:orig_category":"G\u00fcterbef\u00f6rderung im Strassenverkehr",
    "sg:phone":"+41 56 243 12 38",
    "sg:postcode":"5465",
    "sg:province":"Aargau",
    "wof:name":"Ulrich Binder Transporte",
    "wof:placetype":"venue"
},
  "geometry": {"coordinates":[8.3524675369,47.5661849976],"type":"Point"}
}