{
  "type": "Feature",
  "properties": {
    "iso:country":"CH",
    "sg:address":"Schweigmatt 34 8055 Z\u00fcrich. Postfach 806",
    "sg:city":"Z\u00fcrich",
    "sg:orig_category":"Herstellung von Baubedarfsartikeln aus Kunststoff",
    "sg:phone":"+41 14637735",
    "sg:postcode":"8055",
    "sg:province":"Z\u00fcrich",
    "wof:name":"Gottfried Mathys Storen & Rolladen",
    "wof:placetype":"venue"
},
  "geometry": {"coordinates":[8.5015001297,47.3660011292],"type":"Point"}
}