{
  "type": "Feature",
  "properties": {
    "iso:country":"CH",
    "sg:address":"3800",
    "sg:city":"Sundlauenen",
    "sg:orig_category":"Sportvereine Sch\u00fctzen",
    "sg:postcode":"3800",
    "sg:province":"Bern",
    "wof:name":"Feldsch\u00fctzenges.sundlauenen",
    "wof:placetype":"venue"
},
  "geometry": {"coordinates":[7.795129776,46.6875915527],"type":"Point"}
}