{
  "type": "Feature",
  "properties": {
    "iso:country":"CH",
    "sg:address":"Hauptstrasse 17",
    "sg:city":"Fischingen",
    "sg:orig_category":"Detailhandel mit Milcherzeugnissen U Eiern",
    "sg:phone":"+41 71 977 15 20",
    "sg:postcode":"8376",
    "sg:province":"Thurgau",
    "wof:name":"Roland & Pia Egger Ch\u00e4s-egge",
    "wof:placetype":"venue"
},
  "geometry": {"coordinates":[8.9172821045,47.4006004333],"type":"Point"}
}