{
  "type": "Feature",
  "properties": {
    "iso:country":"CH",
    "sg:address":"Brantschenhaus 10 3920 Zermatt. Postfach",
    "sg:city":"Zermatt",
    "sg:orig_category":"Fuhrhaltereien",
    "sg:phone":"+41 27 967 56 36",
    "sg:postcode":"3920",
    "sg:province":"Valais",
    "wof:name":"Pferdetaxi, Imboden Werner",
    "wof:placetype":"venue"
},
  "geometry": {"coordinates":[7.7469358444,46.0225143433],"type":"Point"}
}