{
  "type": "Feature",
  "properties": {
    "iso:country":"CH",
    "sg:address":"Fischmarkt 2",
    "sg:city":"Zug",
    "sg:orig_category":"Vereine Lions",
    "sg:phone":"+41 19722931",
    "sg:postcode":"6300",
    "sg:province":"Zug",
    "wof:name":"Lions Club Z\u00fcrcher Oberland",
    "wof:placetype":"venue"
},
  "geometry": {"coordinates":[8.7856664658,47.3322868347],"type":"Point"}
}