{
  "type": "Feature",
  "properties": {
    "iso:country":"CH",
    "sg:address":"Choully",
    "sg:city":"Satigny",
    "sg:orig_category":"Haltung von Schweinen",
    "sg:phone":"+41 26 413 33 31",
    "sg:postcode":"1242",
    "sg:province":"Gen\u00e8ve",
    "wof:name":"Porcherie Du Schlatt La Roche Sa",
    "wof:placetype":"venue"
},
  "geometry": {"coordinates":[7.1380701065,46.6968002319],"type":"Point"}
}