{
  "type": "Feature",
  "properties": {
    "iso:country":"CH",
    "sg:address":"Reichsgasse 17",
    "sg:city":"Chur",
    "sg:classifiers":[
        {
            "category":"Professional",
            "subcategory":"Employment Agencies",
            "type":"Services"
        }
    ],
    "sg:phone":"+41 13640303",
    "sg:postcode":"7000",
    "sg:province":"Graubunden",
    "sg:tags":[
        "personal",
        "u",
        "stellenvermittlung"
    ],
    "wof:name":"Bibamodels, Mayer",
    "wof:placetype":"venue"
},
  "geometry": {"coordinates":[9.5340642929,46.8509788513],"type":"Point"}
}