{
  "type": "Feature",
  "properties": {
    "iso:country":"CH",
    "sg:address":"M\u00fcller-friedberg-strasse 11",
    "sg:city":"St.gallen",
    "sg:orig_category":"Kauf U Verkauf von Immobilien auf eigene Rechnung",
    "sg:postcode":"9000",
    "sg:province":"St. Gallen",
    "wof:name":"Riedi Ag",
    "wof:placetype":"venue"
},
  "geometry": {"coordinates":[8.7572603226,50.3367004395],"type":"Point"}
}