{
  "type": "Feature",
  "properties": {
    "iso:country":"CH",
    "sg:address":"Giornicostrasse 144",
    "sg:city":"Basel",
    "sg:orig_category":"Grosshandel mit Schreibwaren, B\u00fcchern U Zeitungen Pensionskassen",
    "sg:phone":"+41 61 331 14 07",
    "sg:postcode":"4059",
    "sg:province":"Basel-Stadt",
    "wof:name":"Hilfsfonds Der Wohngenossenschaft 1943 Jakobsberg",
    "wof:placetype":"venue"
},
  "geometry": {"coordinates":[7.5976758003,47.5273246765],"type":"Point"}
}