{
  "type": "Feature",
  "properties": {
    "iso:country":"CH",
    "sg:address":"2613 Villeret Case Postale 25",
    "sg:city":"Villeret",
    "sg:orig_category":"Sportvereine Ballsport Fussball",
    "sg:postcode":"2613",
    "sg:province":"Bern",
    "wof:name":"Uscv Villeneuve",
    "wof:placetype":"venue"
},
  "geometry": {"coordinates":[6.8668699265,46.7416305542],"type":"Point"}
}