{
  "type": "Feature",
  "properties": {
    "iso:country":"CH",
    "sg:address":"Ressiga Via",
    "sg:city":"Giubiasco",
    "sg:orig_category":"Erbringung von Dienstleistungen f\u00fcr Unternehmen",
    "sg:phone":"+41 91 606 68 19",
    "sg:postcode":"6512",
    "sg:province":"Ticino",
    "wof:name":"Masera Franco Societ\u00e0 A Garanzia Limitata",
    "wof:placetype":"venue"
},
  "geometry": {"coordinates":[9.0033226013,46.1699523926],"type":"Point"}
}