{
  "type": "Feature",
  "properties": {
    "iso:country":"CH",
    "sg:address":"Weiherweg 86",
    "sg:city":"Basel",
    "sg:orig_category":"Sonstige pers\u00f6nliche Dienstleistungen",
    "sg:postcode":"4054",
    "sg:province":"Basel-Stadt",
    "wof:name":"James Express-butler, E. Siegenthaler",
    "wof:placetype":"venue"
},
  "geometry": {"coordinates":[7.5727658272,47.5533332825],"type":"Point"}
}