{
  "type": "Feature",
  "properties": {
    "iso:country":"CH",
    "sg:address":"Bahnhofstrasse 15",
    "sg:city":"Gr\u00e4nichen",
    "sg:orig_category":"Aktivit\u00e4ten der Krankenschwestern U Hebammen, Hauspflege",
    "sg:phone":"+41 62 842 00 20",
    "sg:postcode":"5722",
    "sg:province":"Aargau",
    "wof:name":"Spitex-verein",
    "wof:placetype":"venue"
},
  "geometry": {"coordinates":[8.098724,47.361229],"type":"Point"}
}