{
  "type": "Feature",
  "properties": {
    "iso:country":"CH",
    "sg:address":"Bernstrasse 3175 Flamatt. Postfach",
    "sg:city":"Flamatt",
    "sg:orig_category":"Herstellung von Maschinen f\u00fcr die Nahrungsmittel, Getr\u00e4nkeherstellung U die Tabakverarbeitung",
    "sg:phone":"+41 31 741 01 86",
    "sg:postcode":"3175",
    "sg:province":"Fribourg",
    "wof:name":"Rindlisbacher Hermann H. Heimberg Nachfolger",
    "wof:placetype":"venue"
},
  "geometry": {"coordinates":[7.3265447617,46.8907623291],"type":"Point"}
}