{
  "type": "Feature",
  "properties": {
    "iso:country":"CH",
    "sg:address":"H\u00f6schgasse 68",
    "sg:city":"Z\u00fcrich",
    "sg:orig_category":"Grosshandel mit Erzen U Metallen",
    "sg:phone":"+41 13884788",
    "sg:postcode":"8008",
    "sg:province":"Z\u00fcrich",
    "wof:name":"European Trading Group (switzerland) Gmbh",
    "wof:placetype":"venue"
},
  "geometry": {"coordinates":[8.5557842255,47.3579788208],"type":"Point"}
}