{
  "type": "Feature",
  "properties": {
    "addr:full":"Schleif Wengen Bern 3823",
    "addr:postcode":"3823",
    "addr:street":"Wengen",
    "iso:country":"CH",
    "sg:address":"Schleif",
    "sg:city":"Wengen",
    "sg:orig_category":"Betrieb von Taxis Detailhandel mit Brennstoffen U Heizmaterial",
    "sg:phone":"+41 33 855 18 19",
    "sg:postcode":"3823",
    "sg:province":"Bern",
    "wof:name":"Bischoff Transport Ag",
    "wof:placetype":"venue"
},
  "geometry": {"coordinates":[7.923563,46.608749],"type":"Point"}
}