{
  "type": "Feature",
  "properties": {
    "iso:country":"CH",
    "sg:address":"Bannhaldenstrasse 49",
    "sg:city":"Frauenfeld",
    "sg:orig_category":"Non-Classified Establishments",
    "sg:postcode":"8500",
    "sg:province":"Thurgau",
    "wof:name":"Gph Green Power Holding Ag",
    "wof:placetype":"venue"
},
  "geometry": {"coordinates":[8.9173612595,47.5575675964],"type":"Point"}
}