{
  "type": "Feature",
  "properties": {
    "addr:full":"Getwing 17 Zermatt Valais 3920",
    "addr:housenumber":"17",
    "addr:postcode":"3920",
    "addr:street":"Getwing",
    "iso:country":"CH",
    "sg:address":"Getwing 17",
    "sg:city":"Zermatt",
    "sg:orig_category":"Detailhandel mit Blumen U Pflanzen Gartenbau",
    "sg:phone":"+41 27 967 54 64",
    "sg:postcode":"3920",
    "sg:province":"Valais",
    "wof:name":"J\u00fcrg Herren",
    "wof:placetype":"venue"
},
  "geometry": {"coordinates":[7.750018,46.020809],"type":"Point"}
}