{
  "type": "Feature",
  "properties": {
    "iso:country":"CH",
    "sg:address":"Helisb\u00fchlstrasse 13",
    "sg:city":"Herbligen",
    "sg:orig_category":"Haltung von Gefl\u00fcgel",
    "sg:phone":"+41 41 989 85 00",
    "sg:postcode":"3671",
    "sg:province":"Bern",
    "wof:name":"Seg-z\u00fcrich/basel",
    "wof:placetype":"venue"
},
  "geometry": {"coordinates":[7.9269800186,47.1364784241],"type":"Point"}
}