{
  "type": "Feature",
  "properties": {
    "iso:country":"CH",
    "sg:address":"Cit\u00e9-vieusseux 9",
    "sg:city":"Gen\u00e8ve",
    "sg:orig_category":"Physiotherapie",
    "sg:phone":"+41 22 345 14 38",
    "sg:postcode":"1203",
    "sg:province":"Gen\u00e8ve",
    "wof:name":"Physioth\u00e9rapie Vieusseux",
    "wof:placetype":"venue"
},
  "geometry": {"coordinates":[6.1204080582,46.2131309509],"type":"Point"}
}