{
  "type": "Feature",
  "properties": {
    "iso:country":"CH",
    "sg:address":"Industrie Neuhof 4",
    "sg:city":"Kirchberg",
    "sg:classifiers":[
        {
            "category":"Structure",
            "subcategory":"Warehouse",
            "type":"Public Place"
        }
    ],
    "sg:phone":"+41 34 445 69 80",
    "sg:postcode":"3422",
    "sg:province":"Bern",
    "sg:tags":[
        "chiller",
        "air-conditioning",
        "system"
    ],
    "wof:name":"Coolwave Ag",
    "wof:placetype":"venue"
},
  "geometry": {"coordinates":[7.57178,47.094318],"type":"Point"}
}