{
  "type": "Feature",
  "properties": {
    "addr:full":"Via Al Fiume Viganello Ticino 6962",
    "addr:postcode":"6962",
    "addr:street":"Via Al Fiume",
    "iso:country":"CH",
    "sg:address":"Via Al Fiume",
    "sg:city":"Viganello",
    "sg:orig_category":"Detailhandel mit B\u00fcchern, Zeitungen, Schreib U Papeteriewaren",
    "sg:postcode":"6962",
    "sg:province":"Ticino",
    "wof:name":"Bunea Ioan",
    "wof:placetype":"venue"
},
  "geometry": {"coordinates":[8.964505,46.014778],"type":"Point"}
}