{
  "type": "Feature",
  "properties": {
    "iso:country":"CH",
    "sg:address":"Place De La Gare",
    "sg:city":"Fleurier",
    "sg:classifiers":[
        {
            "category":"Travel",
            "subcategory":"Hotels & Motels",
            "type":"Entertainment"
        }
    ],
    "sg:phone":"+41 32 861 40 23",
    "sg:postcode":"2114",
    "sg:province":"Neuch\u00e2tel",
    "sg:tags":[
        "hotels",
        "mit",
        "restaurant"
    ],
    "wof:name":"H\u00f4tel National",
    "wof:placetype":"venue"
},
  "geometry": {"coordinates":[6.6120810509,46.9111251831],"type":"Point"}
}