{
  "type": "Feature",
  "properties": {
    "iso:country":"CH",
    "sg:address":"Hauptstrasse 50 3186 D\u00fcdingen. Postfach 9",
    "sg:city":"D\u00fcdingen",
    "sg:orig_category":"Architektur U Ingenieurb\u00fcros Handelsvermittlung U Grosshandel",
    "sg:phone":"+41 26 492 99 11",
    "sg:postcode":"3186",
    "sg:province":"Fribourg",
    "wof:name":"Ass Ag Antriebstechnik",
    "wof:placetype":"venue"
},
  "geometry": {"coordinates":[7.192016,46.851524],"type":"Point"}
}