{
  "type": "Feature",
  "properties": {
    "iso:country":"CH",
    "sg:address":"H\u00e9liport",
    "sg:city":"Leysin",
    "sg:orig_category":"Gelegenheitsflugverkehr",
    "sg:phone":"+41 24 494 34 34",
    "sg:postcode":"1854",
    "sg:province":"Vaud",
    "wof:name":"Heli-chablais S.a.",
    "wof:placetype":"venue"
},
  "geometry": {"coordinates":[7.0130829811,46.3435630798],"type":"Point"}
}