{
  "type": "Feature",
  "properties": {
    "iso:country":"CH",
    "sg:address":"Industriestrasse 6280 Hochdorf. Postfach 823",
    "sg:city":"Hochdorf",
    "sg:orig_category":"Elektrizit\u00e4tsversorgung Wasserversorgung",
    "sg:phone":"+41 41 914 11 11",
    "sg:postcode":"6281",
    "sg:province":"Luzern",
    "wof:name":"Elektrizit\u00e4ts-& Wasserwerk Der Gemeinde Hochdorf",
    "wof:placetype":"venue"
},
  "geometry": {"coordinates":[8.2809371948,47.1730155945],"type":"Point"}
}