{
  "type": "Feature",
  "properties": {
    "iso:country":"CH",
    "sg:address":"R\u00f6schibachstrasse 52",
    "sg:city":"Z\u00fcrich",
    "sg:orig_category":"Reparatur von Schuhen U Lederwaren",
    "sg:phone":"+41 12728201",
    "sg:postcode":"8037",
    "sg:province":"Z\u00fcrich",
    "wof:name":"Werner Rastetter Schuhservice",
    "wof:placetype":"venue"
},
  "geometry": {"coordinates":[8.5265159607,47.3933639526],"type":"Point"}
}