{
  "type": "Feature",
  "properties": {
    "iso:country":"CH",
    "sg:address":"Muespacherstrasse 76 4055 Basel. Postfach",
    "sg:city":"Basel",
    "sg:orig_category":"Schaustellergewerbe U Vergn\u00fcgungsparks",
    "sg:postcode":"4051",
    "sg:province":"Basel-Stadt",
    "wof:name":"Manfred Vergn\u00fcgungsbetriebe, Stammler Alex Festanl\u00e4sse, Bes. Aufstellung U. F\u00fchrung V. Vergn\u00fcgungsbetriebe",
    "wof:placetype":"venue"
},
  "geometry": {"coordinates":[7.5665678978,47.5615615845],"type":"Point"}
}