{
  "type": "Feature",
  "properties": {
    "iso:country":"CH",
    "sg:address":"K\u00e4genhofweg 9",
    "sg:city":"Reinach",
    "sg:classifiers":[
        {
            "category":"Home & Garden",
            "subcategory":"Home Furnishings",
            "type":"Retail Goods"
        }
    ],
    "sg:phone":"+41 61 711 99 55",
    "sg:postcode":"4153",
    "sg:province":"Basel-Landschaft",
    "sg:tags":[
        "premise"
    ],
    "wof:name":"Pro B\u00fcro Ag",
    "wof:placetype":"venue"
},
  "geometry": {"coordinates":[7.5994319916,47.4891853333],"type":"Point"}
}