{
  "type": "Feature",
  "properties": {
    "iso:country":"CH",
    "sg:address":"Grand-rue 37",
    "sg:city":"Gen\u00e8ve",
    "sg:orig_category":"Unclassifiable Establishments",
    "sg:postcode":"1204",
    "sg:province":"Gen\u00e8ve",
    "wof:name":"Interspace Sarl",
    "wof:placetype":"venue"
},
  "geometry": {"coordinates":[6.1468901634,46.2013778687],"type":"Point"}
}