{
  "type": "Feature",
  "properties": {
    "iso:country":"CH",
    "sg:address":"G\u00e4uggelistrasse 33",
    "sg:city":"Chur",
    "sg:orig_category":"D\u00e4mmung gegen K\u00e4lte, W\u00e4rme, Schall U Ersch\u00fctterung Herstellung von keramischen Wand U Bodenfliesen U",
    "sg:phone":"+41 81 252 81 81",
    "sg:postcode":"7000",
    "sg:province":"Graubunden",
    "wof:name":"Heinrich Wellenzohn Plattenbel\u00e4ge Unterlagsb\u00f6den",
    "wof:placetype":"venue"
},
  "geometry": {"coordinates":[9.5268659592,46.8510894775],"type":"Point"}
}