{
  "type": "Feature",
  "properties": {
    "iso:country":"CH",
    "sg:address":"Pilatusweg 2",
    "sg:city":"Zofingen",
    "sg:orig_category":"Kinderkrippen U horte",
    "sg:phone":"+41 62 751 65 85",
    "sg:postcode":"4800",
    "sg:province":"Aargau",
    "wof:name":"Kinderkrippe Ringier Ag",
    "wof:placetype":"venue"
},
  "geometry": {"coordinates":[7.9473500252,47.2797431946],"type":"Point"}
}