{
  "type": "Feature",
  "properties": {
    "iso:country":"CH",
    "sg:address":"Bleichemattstrasse 33",
    "sg:city":"Biberist",
    "sg:orig_category":"Zahnarztpraxen",
    "sg:phone":"+41 32 671 62 62",
    "sg:postcode":"4562",
    "sg:province":"Solothurn",
    "wof:name":"Dr. Med. Dent. Arthur Kaufmann Zahnarzt",
    "wof:placetype":"venue"
},
  "geometry": {"coordinates":[7.5627799034,47.1808013916],"type":"Point"}
}