{
  "type": "Feature",
  "properties": {
    "iso:country":"CH",
    "sg:address":"Aeusserer Turmacker 21 4566 Halten. Postfach",
    "sg:city":"Halten",
    "sg:orig_category":"Handel mit Motorr\u00e4dern, Teilen U Zubeh\u00f6r Instandhaltung U Reparatur von Motorr\u00e4dern",
    "sg:phone":"+41 32 675 27 40",
    "sg:postcode":"4566",
    "sg:province":"Solothurn",
    "wof:name":"L\u00fcscher Radsport Fahrr\u00e4der U. Zubeh\u00f6r; Verkauf, Reparatur",
    "wof:placetype":"venue"
},
  "geometry": {"coordinates":[7.6105408669,47.1680183411],"type":"Point"}
}