{
  "type": "Feature",
  "properties": {
    "iso:country":"CH",
    "sg:address":"Zinggenstrasse 114",
    "sg:city":"Wilchingen",
    "sg:orig_category":"Caterer Dauerkulturbau",
    "sg:phone":"+41 52 681 39 92",
    "sg:postcode":"8217",
    "sg:province":"Schaffhausen",
    "wof:name":"Eugen's Party-service C.chalet & E.stottele",
    "wof:placetype":"venue"
},
  "geometry": {"coordinates":[8.468905,47.668972],"type":"Point"}
}