{
  "type": "Feature",
  "properties": {
    "iso:country":"CH",
    "sg:address":"5013",
    "sg:city":"Niederg\u00f6sgen",
    "sg:classifiers":[
        {
            "category":"Education",
            "subcategory":"Vocational School",
            "type":"Public Place"
        }
    ],
    "sg:postcode":"5013",
    "sg:province":"Solothurn",
    "sg:tags":[
        "koch-",
        "haushaltschulen"
    ],
    "wof:name":"Haushaltungsschule",
    "wof:placetype":"venue"
},
  "geometry": {"coordinates":[7.9830999374,47.3749008179],"type":"Point"}
}