{
  "type": "Feature",
  "properties": {
    "iso:country":"CH",
    "sg:address":"Weinbergstrasse 39",
    "sg:city":"Kloten",
    "sg:orig_category":"Detailhandel mit M\u00f6beln U Haushaltsgegenst\u00e4nden",
    "sg:postcode":"8302",
    "sg:province":"Z\u00fcrich",
    "wof:name":"Tapina Pfister Heinrich",
    "wof:placetype":"venue"
},
  "geometry": {"coordinates":[8.5798273087,47.4662017822],"type":"Point"}
}