{
  "type": "Feature",
  "properties": {
    "iso:country":"CH",
    "sg:address":"Chemin De La Combe 7",
    "sg:city":"Prangins",
    "sg:orig_category":"Vorschulen, Kinderg\u00e4rten",
    "sg:postcode":"1197",
    "sg:province":"Vaud",
    "wof:name":"Ecole Enfantine I & Ii Coll\u00e8ge Primaire",
    "wof:placetype":"venue"
},
  "geometry": {"coordinates":[6.2467741966,46.3938026428],"type":"Point"}
}