{
  "type": "Feature",
  "properties": {
    "iso:country":"CH",
    "sg:address":"Avenue De Provence 12",
    "sg:city":"Lausanne",
    "sg:orig_category":"Herstellung von Maschinen f\u00fcr die Textil, Bekleidungsherstellung U die Lederverarbeitung Herstellung",
    "sg:phone":"+41 21 625 00 55",
    "sg:postcode":"1007",
    "sg:province":"Vaud",
    "wof:name":"Schulthess Maschinen Sa",
    "wof:placetype":"venue"
},
  "geometry": {"coordinates":[6.609181881,46.5235443115],"type":"Point"}
}