{
  "type": "Feature",
  "properties": {
    "iso:country":"CH",
    "sg:address":"Wolfgrubenstrasse 22b",
    "sg:city":"K\u00f6lliken",
    "sg:orig_category":"Sportvereine Eissport Eishockey",
    "sg:phone":"+41 71 622 81 66",
    "sg:postcode":"5742",
    "sg:province":"Aargau",
    "wof:name":"Hc Thurgau",
    "wof:placetype":"venue"
},
  "geometry": {"coordinates":[9.1381845474,47.5666694641],"type":"Point"}
}