{
  "type": "Feature",
  "properties": {
    "iso:country":"CH",
    "sg:address":"Oberstrasse 218",
    "sg:city":"St.gallen",
    "sg:orig_category":"Sportvereine Wassersport Segeln",
    "sg:phone":"+41 71 245 13 20",
    "sg:postcode":"9000",
    "sg:province":"St. Gallen",
    "wof:name":"Segelvereinigung Horn Svh",
    "wof:placetype":"venue"
},
  "geometry": {"coordinates":[9.3489284515,47.4120254517],"type":"Point"}
}