{
  "type": "Feature",
  "properties": {
    "iso:country":"CH",
    "sg:address":"Z\u00fcckerrain 5",
    "sg:city":"Ruswil",
    "sg:orig_category":"Tierkliniken",
    "sg:phone":"+41 41 495 11 66",
    "sg:postcode":"6017",
    "sg:province":"Luzern",
    "wof:name":"Tierklinik Z\u00fccken Gst",
    "wof:placetype":"venue"
},
  "geometry": {"coordinates":[8.1300001144,47.0820388794],"type":"Point"}
}