{
  "type": "Feature",
  "properties": {
    "iso:country":"CH",
    "sg:address":"Stansstaderstrasse 104 6370 Stans. Postfach",
    "sg:city":"Stans",
    "sg:orig_category":"Herstellung von Wellpapier U pappe sowie von Verpackungsmitteln aus Papier, Karton U Pappe",
    "sg:postcode":"6370",
    "sg:province":"Nidwalden",
    "wof:name":"Cag Handel & Transport Ag",
    "wof:placetype":"venue"
},
  "geometry": {"coordinates":[8.3518152237,46.9697914124],"type":"Point"}
}