{
  "type": "Feature",
  "properties": {
    "iso:country":"CH",
    "sg:address":"M\u00fchlewiesestrasse 6 8355 Aadorf. Postfach 152",
    "sg:city":"Aadorf",
    "sg:orig_category":"Aktivit\u00e4ten der Krankenschwestern U Hebammen, Hauspflege Sonstiges Gesundheitswesen",
    "sg:phone":"+41 52 365 37 67",
    "sg:postcode":"8355",
    "sg:province":"Thurgau",
    "wof:name":"Spitex Krankenpflege Krankenmobilien",
    "wof:placetype":"venue"
},
  "geometry": {"coordinates":[8.905666,47.489998],"type":"Point"}
}