{
  "type": "Feature",
  "properties": {
    "iso:country":"CH",
    "sg:address":"Weinbergstrasse 19",
    "sg:city":"Cham",
    "sg:orig_category":"Allgemeiner Hoch U Tiefbau Maurerarbeiten",
    "sg:phone":"+41 41 780 10 91",
    "sg:postcode":"6330",
    "sg:province":"Zug",
    "wof:name":"B. Baumgartner Akkord Ag Bauakkordarbeiten",
    "wof:placetype":"venue"
},
  "geometry": {"coordinates":[8.461819,47.186588],"type":"Point"}
}