{
  "type": "Feature",
  "properties": {
    "iso:country":"CH",
    "sg:address":"G\u00e4ssle 11",
    "sg:city":"Triesen",
    "sg:orig_category":"Detailhandel mit Waren verschiedener Art, Hauptrichtung Nahrungsmittel",
    "sg:phone":"+41 41 610 33 50",
    "sg:postcode":"9495",
    "wof:name":"Paul Lussi Lebensmittel & Gem\u00fcse",
    "wof:placetype":"venue"
},
  "geometry": {"coordinates":[8.3842763901,46.9576225281],"type":"Point"}
}