{
  "type": "Feature",
  "properties": {
    "iso:country":"CH",
    "sg:address":"Kurb\u00fcro Alte Post",
    "sg:city":"Valens",
    "sg:orig_category":"Verkehrs- and Tourismusb\u00fcros",
    "sg:phone":"+41 81 302 54 00",
    "sg:postcode":"7317",
    "sg:province":"St. Gallen",
    "wof:name":"Kur-& Verkehrsverein Valens-vas\u00f6n",
    "wof:placetype":"venue"
},
  "geometry": {"coordinates":[9.4783477783,46.9679756165],"type":"Point"}
}