{
  "type": "Feature",
  "properties": {
    "iso:country":"CH",
    "sg:address":"8887 Mels. Postfach 7",
    "sg:city":"Mels",
    "sg:orig_category":"Sportvereine Ballsport Fussball",
    "sg:phone":"+41 81 723 29 54",
    "sg:postcode":"8887",
    "sg:province":"St. Gallen",
    "wof:name":"Fc Mels",
    "wof:placetype":"venue"
},
  "geometry": {"coordinates":[9.4209651947,47.0455932617],"type":"Point"}
}