{
  "type": "Feature",
  "properties": {
    "iso:country":"CH",
    "sg:address":"Langnaustrasse 68",
    "sg:city":"Zollbr\u00fcck",
    "sg:orig_category":"Reparatur von elektrischen Haushaltsger\u00e4ten",
    "sg:phone":"+41 56 426 43 43",
    "sg:postcode":"3436",
    "sg:province":"Bern",
    "wof:name":"Mf Repair Center Gmbh",
    "wof:placetype":"venue"
},
  "geometry": {"coordinates":[8.3183250427,47.4623146057],"type":"Point"}
}