{
  "type": "Feature",
  "properties": {
    "iso:country":"CH",
    "sg:address":"Rue Du Camus 11 1470 Estavayer-le-lac. Postfach",
    "sg:city":"Estavayer-le-lac",
    "sg:orig_category":"Vermietung U Verpachtung von eigenen Immobilien",
    "sg:postcode":"1470",
    "sg:province":"Fribourg",
    "wof:name":"Wotan Sa.",
    "wof:placetype":"venue"
},
  "geometry": {"coordinates":[6.8492851257,46.8501205444],"type":"Point"}
}