{
  "type": "Feature",
  "properties": {
    "iso:country":"CH",
    "sg:address":"Neumatt 508",
    "sg:city":"Kleinl\u00fctzel",
    "sg:orig_category":"Detailhandel mit Brot, Back U S\u00fcsswaren",
    "sg:phone":"+41 71 222 45 77",
    "sg:postcode":"4245",
    "sg:province":"Solothurn",
    "wof:name":"Ralph Erni V\u00f6geli-beck",
    "wof:placetype":"venue"
},
  "geometry": {"coordinates":[9.378517,47.424706],"type":"Point"}
}