{
  "type": "Feature",
  "properties": {
    "iso:country":"CH",
    "sg:address":"Corso San Gottardo 12 6830 Chiasso. Postfach Caselle Postale 211",
    "sg:city":"Chiasso",
    "sg:orig_category":"Grosshandel mit chemischen Erzeugnissen Handelsvermittlung von Brennstoffen, Erzen, Metallen U Chemi",
    "sg:phone":"+41 91 682 76 21",
    "sg:postcode":"6830",
    "sg:province":"Ticino",
    "wof:name":"Synco Chemicals Ltd Gomma & Materie Plastiche",
    "wof:placetype":"venue"
},
  "geometry": {"coordinates":[9.032327652,45.8330726624],"type":"Point"}
}