{
  "type": "Feature",
  "properties": {
    "iso:country":"CH",
    "sg:address":"Unterdorf 47",
    "sg:city":"Bussnang",
    "sg:orig_category":"Zimmerei, Dachdeckerei, Bauspenglerei U Abdichtung",
    "sg:postcode":"9565",
    "sg:province":"Thurgau",
    "wof:name":"Mazzeo-fuchs F.",
    "wof:placetype":"venue"
},
  "geometry": {"coordinates":[9.0787296295,47.5577392578],"type":"Point"}
}