{
  "type": "Feature",
  "properties": {
    "iso:country":"CH",
    "sg:address":"Zentrum 1",
    "sg:city":"Oberengstringen",
    "sg:orig_category":"Detailhandel mit Damenbekleidung",
    "sg:phone":"+41 17501581",
    "sg:postcode":"8102",
    "sg:province":"Z\u00fcrich",
    "wof:name":"Bistra Alkalay Riva Damenmode",
    "wof:placetype":"venue"
},
  "geometry": {"coordinates":[8.460897,47.408615],"type":"Point"}
}