{
  "type": "Feature",
  "properties": {
    "iso:country":"CH",
    "sg:address":"K\u00f6llikerstrasse 1 5036 Oberentfelden. Postfach 201",
    "sg:city":"Oberentfelden",
    "sg:orig_category":"RESTAURANTS: TEA-ROOMS",
    "sg:phone":"+41 71 288 11 66",
    "sg:postcode":"5036",
    "sg:province":"Aargau",
    "wof:name":"Rest. Intermezzo Rechsteiner O.",
    "wof:placetype":"venue"
},
  "geometry": {"coordinates":[9.4027109146,47.4376106262],"type":"Point"}
}