{
  "type": "Feature",
  "properties": {
    "iso:country":"CH",
    "sg:address":"Place De Bel-air 6",
    "sg:city":"Nyon",
    "sg:orig_category":"Verwaltung der Rechtspflege, Gerichte",
    "sg:phone":"+41 22 361 28 05",
    "sg:postcode":"1260",
    "sg:province":"Vaud",
    "wof:name":"Registre Foncier",
    "wof:placetype":"venue"
},
  "geometry": {"coordinates":[6.2381849289,46.3826560974],"type":"Point"}
}