{
  "type": "Feature",
  "properties": {
    "iso:country":"CH",
    "sg:address":"Dentenbergstrasse 34",
    "sg:city":"Worb",
    "sg:classifiers":[
        {
            "category":"Sports & Exercise",
            "subcategory":"Skate Park",
            "type":"Entertainment"
        }
    ],
    "sg:phone":"+41 31 839 02 82",
    "sg:postcode":"3076",
    "sg:province":"Bern",
    "sg:tags":[
        "mushroom"
    ],
    "wof:name":"Kurt Denier Champignons",
    "wof:placetype":"venue"
},
  "geometry": {"coordinates":[7.5477018356,46.9297409058],"type":"Point"}
}