{
  "type": "Feature",
  "properties": {
    "iso:country":"CH",
    "sg:address":"Route Des Carolins 14",
    "sg:city":"Sion",
    "sg:orig_category":"Handelsvermittlung U Grosshandel mit Automobilen Herstellung von Automobilen",
    "sg:phone":"+41 27 203 75 80",
    "sg:postcode":"1950",
    "sg:province":"Valais",
    "wof:name":"Ips-importation Polaris Sufag Sa",
    "wof:placetype":"venue"
},
  "geometry": {"coordinates":[7.3640909195,46.2229042053],"type":"Point"}
}