{
  "type": "Feature",
  "properties": {
    "iso:country":"CH",
    "sg:address":"Chemin Du Mont-blanc 20",
    "sg:city":"Penthaz",
    "sg:orig_category":"Unclassifiable Establishments",
    "sg:postcode":"1303",
    "sg:province":"Vaud",
    "wof:name":"Xantec S\u00e0rl",
    "wof:placetype":"venue"
},
  "geometry": {"coordinates":[6.5423760414,46.596031189],"type":"Point"}
}