{
  "type": "Feature",
  "properties": {
    "iso:country":"CH",
    "sg:address":"Avenue De La Gare 50",
    "sg:city":"Martigny",
    "sg:orig_category":"P\u00e9dicure",
    "sg:phone":"+41 27 722 48 76",
    "sg:postcode":"1920",
    "sg:province":"Valais",
    "wof:name":"L\u00e9ny Mani P\u00e9dicure",
    "wof:placetype":"venue"
},
  "geometry": {"coordinates":[7.0778670311,46.104801178],"type":"Point"}
}