{
  "type": "Feature",
  "properties": {
    "iso:country":"CH",
    "sg:address":"Boostockstrasse 28",
    "sg:city":"Spreitenbach",
    "sg:orig_category":"Arztpraxen",
    "sg:phone":"+41 56 401 20 00",
    "sg:postcode":"8957",
    "sg:province":"Aargau",
    "wof:name":"Dr.med.daria Amgwerd Spezial\u00e4rztin Fmh",
    "wof:placetype":"venue"
},
  "geometry": {"coordinates":[8.364743,47.419594],"type":"Point"}
}