{
  "type": "Feature",
  "properties": {
    "addr:full":"Ackerstrasse 4 Uster Z\u00fcrich 8610",
    "addr:housenumber":"4",
    "addr:postcode":"8610",
    "addr:street":"Ackerstrasse",
    "iso:country":"CH",
    "sg:address":"Ackerstrasse 4",
    "sg:city":"Uster",
    "sg:orig_category":"Arztpraxen",
    "sg:phone":"+41 61 361 88 80",
    "sg:postcode":"8610",
    "sg:province":"Z\u00fcrich",
    "wof:name":"Dr.med.rudolf Ott Arzt F.allgemeine Medizin Fmh",
    "wof:placetype":"venue"
},
  "geometry": {"coordinates":[7.525643,47.50684],"type":"Point"}
}