{
  "type": "Feature",
  "properties": {
    "iso:country":"CH",
    "sg:address":"Bahnhofstrasse 28",
    "sg:city":"St\u00e4fa",
    "sg:orig_category":"Unternehmensberatung",
    "sg:phone":"+41 18202688",
    "sg:postcode":"8712",
    "sg:province":"Z\u00fcrich",
    "wof:name":"Studer Consulting",
    "wof:placetype":"venue"
},
  "geometry": {"coordinates":[8.721830368,47.2400436401],"type":"Point"}
}