{
  "type": "Feature",
  "properties": {
    "iso:country":"CH",
    "sg:address":"Wasserwerkstrasse 4",
    "sg:city":"R\u00fcmlang",
    "sg:orig_category":"Wasserversorgung",
    "sg:phone":"+41 18170648",
    "sg:postcode":"8153",
    "sg:province":"Z\u00fcrich",
    "wof:name":"Wasserwerk",
    "wof:placetype":"venue"
},
  "geometry": {"coordinates":[8.5295877457,47.453742981],"type":"Point"}
}