{
  "type": "Feature",
  "properties": {
    "iso:country":"CH",
    "sg:address":"3176",
    "sg:city":"Neuenegg",
    "sg:orig_category":"Wohnheime f\u00fcr Kinder U Jugendliche",
    "sg:phone":"+41 79 302 13 64",
    "sg:postcode":"3176",
    "sg:province":"Bern",
    "wof:name":"Pfadfinderheim B\u00e4renklaue",
    "wof:placetype":"venue"
},
  "geometry": {"coordinates":[7.3022098541,46.8938751221],"type":"Point"}
}