{
  "type": "Feature",
  "properties": {
    "iso:country":"CH",
    "sg:address":"8247",
    "sg:city":"Flurlingen",
    "sg:orig_category":"Pensionskassen",
    "sg:phone":"+41 52 647 33 11",
    "sg:postcode":"8247",
    "sg:province":"Z\u00fcrich",
    "wof:name":"F\u00fcrsorgestiftung Der Arova Schaffhausen Ag",
    "wof:placetype":"venue"
},
  "geometry": {"coordinates":[8.6418800354,47.6835517883],"type":"Point"}
}