{
  "type": "Feature",
  "properties": {
    "iso:country":"CH",
    "sg:address":"Bahnhofstrasse 4 4932 Lotzwil. Postfach 144",
    "sg:city":"Lotzwil",
    "sg:orig_category":"Gemeindeverwaltungen",
    "sg:phone":"+41 62 916 00 40",
    "sg:postcode":"4932",
    "sg:province":"Bern",
    "wof:name":"Gemeindeverwaltung Lotzwil",
    "wof:placetype":"venue"
},
  "geometry": {"coordinates":[7.7893900871,47.1900520325],"type":"Point"}
}