{
  "type": "Feature",
  "properties": {
    "iso:country":"CH",
    "sg:address":"Sch\u00fctzenstrasse 31",
    "sg:city":"Dietikon",
    "sg:orig_category":"Grosshandel mit B\u00fcromaschinen Grosshandel mit Datenverarbeitungsger\u00e4ten",
    "sg:phone":"+41 56 633 37 55",
    "sg:postcode":"8953",
    "sg:province":"Z\u00fcrich",
    "wof:name":"Ordaplan Ag.",
    "wof:placetype":"venue"
},
  "geometry": {"coordinates":[8.4012460709,47.3409156799],"type":"Point"}
}