{
  "type": "Feature",
  "properties": {
    "iso:country":"CH",
    "sg:address":"Unter Spitalhof 46",
    "sg:city":"Emmen",
    "sg:orig_category":"Herstellung von Ger\u00e4ten der Elektrizit\u00e4tserzeugung, -verteilung u.\u00e4. -Detailhandel mit Metallwaren, ",
    "sg:phone":"+41 41 260 14 47",
    "sg:postcode":"6032",
    "sg:province":"Luzern",
    "wof:name":"Exodor Ag Elektroapparate",
    "wof:placetype":"venue"
},
  "geometry": {"coordinates":[8.3061599731,47.0793304443],"type":"Point"}
}