{
  "type": "Feature",
  "properties": {
    "iso:country":"CH",
    "sg:address":"Via Delta",
    "sg:city":"Ascona",
    "sg:orig_category":"Bauschreinerei Herstellung von sonstigen M\u00f6beln",
    "sg:phone":"+41 91 791 41 26",
    "sg:postcode":"6612",
    "sg:province":"Ticino",
    "wof:name":"Zibetti Sa Laboratorio Di Restauro Mobili",
    "wof:placetype":"venue"
},
  "geometry": {"coordinates":[8.78379,46.159679],"type":"Point"}
}