{
  "type": "Feature",
  "properties": {
    "iso:country":"CH",
    "sg:address":"Seestrasse 2 3700 Spiez. Postfach 589",
    "sg:city":"Spiez",
    "sg:orig_category":"Kauf U Verkauf von Immobilien auf eigene Rechnung",
    "sg:phone":"+41 33 654 46 85",
    "sg:postcode":"3700",
    "sg:province":"Bern",
    "wof:name":"Toma Verwaltungen Gmbh",
    "wof:placetype":"venue"
},
  "geometry": {"coordinates":[7.681221962,46.6863098145],"type":"Point"}
}