{
  "type": "Feature",
  "properties": {
    "iso:country":"CH",
    "sg:address":"Landriani Via 1",
    "sg:city":"Lugano",
    "sg:orig_category":"Non-Classified Establishments",
    "sg:postcode":"6900",
    "sg:province":"Ticino",
    "wof:name":"Textil Holding 44 Sa",
    "wof:placetype":"venue"
},
  "geometry": {"coordinates":[8.9589290619,46.00598526],"type":"Point"}
}