{
  "type": "Feature",
  "properties": {
    "iso:country":"CH",
    "sg:address":"Rue De La Gare 5",
    "sg:city":"Morges",
    "sg:orig_category":"Zahnarztpraxen",
    "sg:phone":"+41 21 801 66 33",
    "sg:postcode":"1110",
    "sg:province":"Vaud",
    "wof:name":"Dr M\u00e9d.dent.andr\u00e9 Ebersberger M\u00e9decin-dentiste",
    "wof:placetype":"venue"
},
  "geometry": {"coordinates":[6.4960618019,46.5083427429],"type":"Point"}
}