{
  "type": "Feature",
  "properties": {
    "iso:country":"CH",
    "sg:address":"R\u00f6merstrasse 3",
    "sg:city":"Triesen",
    "sg:orig_category":"Reparatur von Schuhen U Lederwaren",
    "sg:phone":"+423 392 24 75",
    "sg:postcode":"9495",
    "wof:name":"Xaver Kindle Schuhmacherei",
    "wof:placetype":"venue"
},
  "geometry": {"coordinates":[9.5328645706,47.1054496765],"type":"Point"}
}