{
  "type": "Feature",
  "properties": {
    "iso:country":"CH",
    "sg:address":"Lenkstrasse",
    "sg:city":"Blankenburg",
    "sg:orig_category":"Bauingenieurb\u00fcros allgemein",
    "sg:phone":"+41 33 722 34 44",
    "sg:postcode":"3771",
    "sg:province":"Bern",
    "wof:name":"Ewald Josi Ingenieurb\u00fcro",
    "wof:placetype":"venue"
},
  "geometry": {"coordinates":[7.386366,46.544018],"type":"Point"}
}