{
  "type": "Feature",
  "properties": {
    "iso:country":"CH",
    "sg:address":"Dorfstrasse 4 3646 Einigen. Postfach",
    "sg:city":"Einigen",
    "sg:orig_category":"Non-Classified Establishments",
    "sg:postcode":"3646",
    "sg:province":"Bern",
    "wof:name":"Oesch Daniel Gartenbau",
    "wof:placetype":"venue"
},
  "geometry": {"coordinates":[7.6504068375,46.7067871094],"type":"Point"}
}