{
  "type": "Feature",
  "properties": {
    "iso:country":"CH",
    "sg:address":"Hambergersteig 11b 8000 Z\u00fcrich. Postfach",
    "sg:city":"Z\u00fcrich",
    "sg:orig_category":"Non-Classified Establishments",
    "sg:postcode":"8008",
    "sg:province":"Z\u00fcrich",
    "wof:name":"Arrow Holding",
    "wof:placetype":"venue"
},
  "geometry": {"coordinates":[8.5613832474,47.3510284424],"type":"Point"}
}