{
  "type": "Feature",
  "properties": {
    "iso:country":"CH",
    "sg:address":"B\u00fcchnerstrasse 8",
    "sg:city":"Z\u00fcrich",
    "sg:orig_category":"Kinos",
    "sg:phone":"+41 12624144",
    "sg:postcode":"8006",
    "sg:province":"Z\u00fcrich",
    "wof:name":"Kinohaus Ag Z\u00fcrich",
    "wof:placetype":"venue"
},
  "geometry": {"coordinates":[8.5516653061,47.38331604],"type":"Point"}
}