{
  "type": "Feature",
  "properties": {
    "addr:full":"Rue De Lyon 108 Gen\u00e8ve Gen\u00e8ve 1203",
    "addr:housenumber":"108",
    "addr:postcode":"1203",
    "addr:street":"Rue De Lyon",
    "iso:country":"CH",
    "sg:address":"Rue De Lyon 108",
    "sg:city":"Gen\u00e8ve",
    "sg:classifiers":[
        {
            "category":"Autos & Motor Vehicles",
            "subcategory":"Auto Supplies",
            "type":"Retail Goods"
        }
    ],
    "sg:phone":"+41 22 338 38 38",
    "sg:postcode":"1203",
    "sg:province":"Gen\u00e8ve",
    "sg:tags":[
        "automobile",
        "accessory"
    ],
    "wof:name":"Fiat Auto (suisse) Sa",
    "wof:placetype":"venue"
},
  "geometry": {"coordinates":[6.122342,46.209244],"type":"Point"}
}