{
  "type": "Feature",
  "properties": {
    "addr:full":"Alte Zurzacherstr. 30 Tegerfelden Aargau 5306",
    "addr:housenumber":"30",
    "addr:postcode":"5306",
    "addr:street":"Tegerfelden Aargau",
    "iso:country":"CH",
    "sg:address":"Alte Zurzacherstr. 30",
    "sg:city":"Tegerfelden",
    "sg:orig_category":"Miscellaneous Products",
    "sg:phone":"+41 56 268 68 58",
    "sg:postcode":"5306",
    "sg:province":"Aargau",
    "wof:name":"Heinz Baumgartner Ag",
    "wof:placetype":"venue"
},
  "geometry": {"coordinates":[8.28609,47.564049],"type":"Point"}
}