{
  "type": "Feature",
  "properties": {
    "iso:country":"CH",
    "sg:address":"Pflugstrasse 30",
    "sg:city":"Vaduz",
    "sg:orig_category":"Fotografische Ateliers",
    "sg:phone":"+423 232 23 29",
    "sg:postcode":"9490",
    "wof:name":"Heinz Preute Fotografisches Atelier",
    "wof:placetype":"venue"
},
  "geometry": {"coordinates":[9.5248298645,47.1241416931],"type":"Point"}
}