{
  "type": "Feature",
  "properties": {
    "iso:country":"CH",
    "sg:address":"Industrielle Rue 26",
    "sg:city":"Montreux",
    "sg:orig_category":"Vermietung U Verpachtung von eigenen Immobilien",
    "sg:postcode":"1820",
    "sg:province":"Vaud",
    "wof:name":"Scorp Sa",
    "wof:placetype":"venue"
},
  "geometry": {"coordinates":[6.913672924,46.4328689575],"type":"Point"}
}