{
  "type": "Feature",
  "properties": {
    "iso:country":"CH",
    "sg:address":"M\u00fclligerstrasse70",
    "sg:city":"Windisch",
    "sg:orig_category":"Architektur U Ingenieurb\u00fcros",
    "sg:phone":"+41 56 441 04 10",
    "sg:postcode":"5210",
    "sg:province":"Aargau",
    "wof:name":"Fischer Ag Ingenieurb\u00fcro",
    "wof:placetype":"venue"
},
  "geometry": {"coordinates":[8.216858,47.478909],"type":"Point"}
}