{
  "type": "Feature",
  "properties": {
    "iso:country":"CH",
    "sg:address":"Seestrasse 42",
    "sg:city":"Horn",
    "sg:orig_category":"Unclassifiable Establishments",
    "sg:phone":"+41 71 841 22 74",
    "sg:postcode":"9326",
    "sg:province":"Thurgau",
    "wof:name":"Gasthaus Gr\u00fctli",
    "wof:placetype":"venue"
},
  "geometry": {"coordinates":[9.4674110413,47.4949073792],"type":"Point"}
}