{
  "type": "Feature",
  "properties": {
    "iso:country":"CH",
    "sg:address":"Avenue Choiseul 21 1290 Versoix Case Postale 316",
    "sg:city":"Versoix",
    "sg:orig_category":"Herstellung von Mess U Kontrollinstrumenten U vorrichtungen",
    "sg:phone":"+41 22 755 43 59",
    "sg:postcode":"1290",
    "sg:province":"Gen\u00e8ve",
    "wof:name":"Imatex Sa",
    "wof:placetype":"venue"
},
  "geometry": {"coordinates":[6.1633958817,46.2889289856],"type":"Point"}
}