{
  "type": "Feature",
  "properties": {
    "iso:country":"CH",
    "sg:address":"Centro Carvina",
    "sg:city":"Taverne",
    "sg:orig_category":"Markt U Meinungsforschung",
    "sg:phone":"+41 91 945 00 45",
    "sg:postcode":"6807",
    "sg:province":"Ticino",
    "wof:name":"Market 2000 Sa",
    "wof:placetype":"venue"
},
  "geometry": {"coordinates":[8.9333286285,46.0671730042],"type":"Point"}
}