{
  "type": "Feature",
  "properties": {
    "iso:country":"CH",
    "sg:address":"Ch\u00fceferistrasse 16",
    "sg:city":"Fehraltorf",
    "sg:orig_category":"Herstellung von elektronischen Bauelementen",
    "sg:phone":"+41 19551212",
    "sg:postcode":"8320",
    "sg:province":"Z\u00fcrich",
    "wof:name":"Mettler-toledo Gmbh",
    "wof:placetype":"venue"
},
  "geometry": {"coordinates":[8.754442215,47.3840522766],"type":"Point"}
}