{
  "type": "Feature",
  "properties": {
    "iso:country":"CH",
    "sg:address":"7403",
    "sg:city":"Rh\u00e4z\u00fcns",
    "sg:orig_category":"Detailhandel mit Brot, Back U S\u00fcsswaren",
    "sg:phone":"+41 81 641 31 41",
    "sg:postcode":"7403",
    "sg:province":"Graubunden",
    "wof:name":"Rolf Schmid Stgier Scrl",
    "wof:placetype":"venue"
},
  "geometry": {"coordinates":[9.397965,46.79855],"type":"Point"}
}