{
  "type": "Feature",
  "properties": {
    "iso:country":"CH",
    "sg:address":"Kirchb\u00fcndtenstrasse 5",
    "sg:city":"Ettingen",
    "sg:orig_category":"Vereine Gesang",
    "sg:postcode":"4107",
    "sg:province":"Basel-Landschaft",
    "wof:name":"M\u00e4nnerchor Arlesheim",
    "wof:placetype":"venue"
},
  "geometry": {"coordinates":[7.550134182,47.4813804626],"type":"Point"}
}