{
  "type": "Feature",
  "properties": {
    "iso:country":"CH",
    "sg:address":"Spitalgasse 9",
    "sg:city":"Bern",
    "sg:orig_category":"Pensionskassen",
    "sg:postcode":"3011",
    "sg:province":"Bern",
    "wof:name":"Stiftung Solidarit\u00e4tsfonds Des Vereins Berner Journalistinnen Und Journalisten Vbjj",
    "wof:placetype":"venue"
},
  "geometry": {"coordinates":[7.4429187775,46.9480171204],"type":"Point"}
}