{
  "type": "Feature",
  "properties": {
    "iso:country":"CH",
    "sg:address":"Parkstrasse 33",
    "sg:city":"Weggis",
    "sg:orig_category":"Non-Classified Establishments",
    "sg:postcode":"6353",
    "sg:province":"Luzern",
    "wof:name":"Freude Am Garten-freude Im Leben Ueli Brenner",
    "wof:placetype":"venue"
},
  "geometry": {"coordinates":[8.4259901047,47.032749176],"type":"Point"}
}