{
  "type": "Feature",
  "properties": {
    "addr:full":"Avenue Du Fey 1510 Moudon Case Postale 240 Moudon Vaud 1510",
    "addr:postcode":"1510;240;1510",
    "addr:street":"Avenue Du Fey;Case Postale",
    "iso:country":"CH",
    "sg:address":"Avenue Du Fey 1510 Moudon Case Postale 240",
    "sg:city":"Moudon",
    "sg:orig_category":"Allgemeiner Hoch U Tiefbau Allgemeiner Hochbau",
    "sg:phone":"+41 21 905 12 16",
    "sg:postcode":"1510",
    "sg:province":"Vaud",
    "wof:name":"Ratti Sa",
    "wof:placetype":"venue"
},
  "geometry": {"coordinates":[6.795471,46.665287],"type":"Point"}
}