{
  "type": "Feature",
  "properties": {
    "iso:country":"CH",
    "sg:address":"Chemin De Rosaire 4",
    "sg:city":"Aclens",
    "sg:orig_category":"Grosshandel mit sonstigen Halbwaren",
    "sg:phone":"+41 21 869 92 82",
    "sg:postcode":"1123",
    "sg:province":"Vaud",
    "wof:name":"Brangs & Heinrich Sa Papiers Engros",
    "wof:placetype":"venue"
},
  "geometry": {"coordinates":[6.5223021507,46.5713615417],"type":"Point"}
}