{
  "type": "Feature",
  "properties": {
    "iso:country":"CH",
    "sg:address":"Parkstrasse 1",
    "sg:city":"Weggis",
    "sg:orig_category":"Gemeindeverwaltungen",
    "sg:phone":"+41 17502323",
    "sg:postcode":"6353",
    "sg:province":"Luzern",
    "wof:name":"Gemeindeverwaltung Weiningen",
    "wof:placetype":"venue"
},
  "geometry": {"coordinates":[8.4327421188,47.4190788269],"type":"Point"}
}