{
  "type": "Feature",
  "properties": {
    "addr:full":"Weier 6a Schwarzenegg Bern 3616",
    "addr:housenumber":"6a",
    "addr:postcode":"3616",
    "addr:street":"Weier",
    "iso:country":"CH",
    "sg:address":"Weier 6a",
    "sg:city":"Schwarzenegg",
    "sg:classifiers":[
        {
            "category":"Banks & Credit Unions",
            "subcategory":"Bank",
            "type":"Services"
        }
    ],
    "sg:phone":"+41 56 282 01 82",
    "sg:postcode":"3616",
    "sg:province":"Bern",
    "wof:name":"Raiffeisenbank Obersiggenthal",
    "wof:placetype":"venue"
},
  "geometry": {"coordinates":[8.293214,47.486698],"type":"Point"}
}