{
  "type": "Feature",
  "properties": {
    "iso:country":"CH",
    "sg:address":"Kalabinth 21",
    "sg:city":"Speicher",
    "sg:classifiers":[
        {
            "category":"Shopping",
            "subcategory":"Clothing, Apparel, & Fashions",
            "type":"Retail Goods"
        }
    ],
    "sg:phone":"+41 71 343 72 72",
    "sg:postcode":"9042",
    "sg:province":"Appenzell Ausserrhoden",
    "sg:tags":[
        "textile",
        "clothing",
        "clothes"
    ],
    "wof:name":"Akris Pr\u00cat-\u00c1-porter Ag",
    "wof:placetype":"venue"
},
  "geometry": {"coordinates":[9.44095,47.415272],"type":"Point"}
}