{
  "type": "Feature",
  "properties": {
    "addr:full":"Les Ochettes Oron-le-ch\u00e2tel Fribourg 1608",
    "addr:postcode":"1608",
    "iso:country":"CH",
    "sg:address":"Les Ochettes",
    "sg:city":"Oron-le-ch\u00e2tel",
    "sg:orig_category":"Dachdeckerei Herstellung von Metallkonstruktionen",
    "sg:phone":"+41 21 907 98 03",
    "sg:postcode":"1608",
    "sg:province":"Fribourg",
    "wof:name":"Bally Pascal",
    "wof:placetype":"venue"
},
  "geometry": {"coordinates":[6.83847,46.57415],"type":"Point"}
}