{
  "type": "Feature",
  "properties": {
    "iso:country":"CH",
    "sg:address":"Jurastrasse 37",
    "sg:city":"Langenthal",
    "sg:orig_category":"Advokaturb\u00fcros",
    "sg:phone":"+41 62 922 88 11",
    "sg:postcode":"4900",
    "sg:province":"Bern",
    "wof:name":"Andr\u00e9 Sommer Advokaturb\u00fcro",
    "wof:placetype":"venue"
},
  "geometry": {"coordinates":[7.786083,47.215813],"type":"Point"}
}