{
  "type": "Feature",
  "properties": {
    "iso:country":"CH",
    "sg:address":"Tannholzstrasse 14 3052 Zollikofen. Postfach 409",
    "sg:city":"Zollikofen",
    "sg:orig_category":"Herstellung von Beh\u00e4ltern aus Metall Mechanische Werkst\u00e4tten",
    "sg:phone":"+41 19302378",
    "sg:postcode":"3052",
    "sg:province":"Bern",
    "wof:name":"Indusaid Ag",
    "wof:placetype":"venue"
},
  "geometry": {"coordinates":[8.8084897995,47.3316688538],"type":"Point"}
}