{
  "type": "Feature",
  "properties": {
    "iso:country":"CH",
    "sg:address":"Industriestr.",
    "sg:city":"Safenwil",
    "sg:classifiers":[
        {
            "category":"Autos & Motor Vehicles",
            "subcategory":"Automobile Sales",
            "type":"Retail Goods"
        }
    ],
    "sg:phone":"+41 21 967 05 05",
    "sg:postcode":"5745",
    "sg:province":"Aargau",
    "sg:tags":[
        "equipment",
        "transport"
    ],
    "wof:name":"Bombardier Transport Vevey Technologies Sa",
    "wof:placetype":"venue"
},
  "geometry": {"coordinates":[6.9261350632,46.39818573],"type":"Point"}
}