{
  "type": "Feature",
  "properties": {
    "iso:country":"CH",
    "sg:address":"Weiherstrasse 20b",
    "sg:city":"Amriswil",
    "sg:orig_category":"Berufliche Weiterbildung, Erwachsenenbildung Sonstige pers\u00f6nliche Dienstleistungen",
    "sg:phone":"+41 71 411 34 49",
    "sg:postcode":"8580",
    "sg:province":"Thurgau",
    "wof:name":"Dtc Derivatives Teaching And Consulting, Zinn\u00e0 Vincenzo",
    "wof:placetype":"venue"
},
  "geometry": {"coordinates":[9.298532,47.552181],"type":"Point"}
}