{
  "type": "Feature",
  "properties": {
    "iso:country":"CH",
    "sg:address":"Suhrenmattstrasse 34",
    "sg:city":"Unterentfelden",
    "sg:orig_category":"Architektur U Ingenieurb\u00fcros",
    "sg:phone":"+41 52 320 90 20",
    "sg:postcode":"5035",
    "sg:province":"Aargau",
    "wof:name":"M\u00fchlebach Akustik & Bauphysik Ingenieurb\u00fcro F\u00fcr Akustik U. Bauphysik",
    "wof:placetype":"venue"
},
  "geometry": {"coordinates":[173.1698,52.833542],"type":"Point"}
}