{
  "type": "Feature",
  "properties": {
    "iso:country":"CH",
    "sg:address":"Zweigstrasse 6",
    "sg:city":"Holziken",
    "sg:orig_category":"Werbung",
    "sg:phone":"+41 62 721 69 00",
    "sg:postcode":"5043",
    "sg:province":"Aargau",
    "wof:name":"Cr Communications Gmbh",
    "wof:placetype":"venue"
},
  "geometry": {"coordinates":[8.0409402847,47.3209838867],"type":"Point"}
}