{
  "type": "Feature",
  "properties": {
    "iso:country":"CH",
    "sg:address":"Bahnhofstrasse 24",
    "sg:city":"M\u00f6hlin",
    "sg:orig_category":"Werbegrafikateliers",
    "sg:phone":"+41 61 851 15 65",
    "sg:postcode":"4313",
    "sg:province":"Aargau",
    "wof:name":"Bruno Kym Grafisches Atelier",
    "wof:placetype":"venue"
},
  "geometry": {"coordinates":[7.838891983,47.5607452393],"type":"Point"}
}