{
  "type": "Feature",
  "properties": {
    "iso:country":"CH",
    "sg:address":"Dorfstrasse 52",
    "sg:city":"Adelboden",
    "sg:classifiers":[
        {
            "category":"Restaurant",
            "type":"Food & Drink"
        }
    ],
    "sg:phone":"+41 33 673 22 18",
    "sg:postcode":"3715",
    "sg:province":"Bern",
    "wof:name":"Pizzeria Trattoria Alfredo",
    "wof:placetype":"venue"
},
  "geometry": {"coordinates":[7.5568752289,46.4911231995],"type":"Point"}
}