{
  "type": "Feature",
  "properties": {
    "iso:country":"CH",
    "sg:address":"B\u00e4renmatt 12",
    "sg:city":"Biel/bienne",
    "sg:classifiers":[
        {
            "category":"Restaurant",
            "type":"Food & Drink"
        }
    ],
    "sg:phone":"+41 32 365 34 05",
    "sg:postcode":"2503",
    "sg:province":"Bern",
    "wof:name":"Spaghetteria Hirschen",
    "wof:placetype":"venue"
},
  "geometry": {"coordinates":[7.2524452209,47.1312561035],"type":"Point"}
}