{
  "type": "Feature",
  "properties": {
    "iso:country":"CH",
    "sg:address":"Bahnhofstrasse 4 2502 Biel/bienne. Postfach",
    "sg:city":"Biel/bienne",
    "sg:classifiers":[
        {
            "category":"Bars & Pubs",
            "type":"Food & Drink"
        }
    ],
    "sg:phone":"+41 24 471 15 67",
    "sg:postcode":"2501",
    "sg:province":"Bern",
    "sg:tags":[
        "restaurant"
    ],
    "wof:name":"Caf\u00e9 De La Nouvelle Poste & Bar",
    "wof:placetype":"venue"
},
  "geometry": {"coordinates":[6.948625,46.25317],"type":"Point"}
}