{
  "type": "Feature",
  "properties": {
    "iso:country":"CH",
    "sg:address":"Kirchstrasse 2",
    "sg:city":"Rehetobel",
    "sg:orig_category":"Grosshandel mit Textilien",
    "sg:phone":"+41 71 877 12 73",
    "sg:postcode":"9038",
    "sg:province":"Appenzell Ausserrhoden",
    "wof:name":"Solenthaler Textil Ag",
    "wof:placetype":"venue"
},
  "geometry": {"coordinates":[9.482583046,47.4267311096],"type":"Point"}
}