{
  "type": "Feature",
  "properties": {
    "iso:country":"CH",
    "sg:address":"Route De Sonvillier 32",
    "sg:city":"St-imier",
    "sg:orig_category":"Wohnheime",
    "sg:postcode":"2610",
    "sg:province":"Bern",
    "wof:name":"Croix-bleue",
    "wof:placetype":"venue"
},
  "geometry": {"coordinates":[6.8533701897,46.9680976868],"type":"Point"}
}