{
  "type": "Feature",
  "properties": {
    "iso:country":"CH",
    "sg:address":"Rue Du Temple 9",
    "sg:city":"St-blaise",
    "sg:orig_category":"Herstellung von Metallkonstruktionen Mechanik",
    "sg:phone":"+41 32 753 18 33",
    "sg:postcode":"2072",
    "sg:province":"Neuch\u00e2tel",
    "wof:name":"Hegel A. Sa.",
    "wof:placetype":"venue"
},
  "geometry": {"coordinates":[6.9872179031,47.0139045715],"type":"Point"}
}