{
  "type": "Feature",
  "properties": {
    "addr:full":"Rue Du Grand-st-jean 4 Lausanne Vaud 1003",
    "addr:housenumber":"4",
    "addr:postcode":"1003",
    "addr:street":"Rue Du Grand-St-Jean",
    "iso:country":"CH",
    "sg:address":"Rue Du Grand-st-jean 4",
    "sg:city":"Lausanne",
    "sg:orig_category":"Detailhandel mit Damenbekleidung",
    "sg:phone":"+41 21 311 54 31",
    "sg:postcode":"1003",
    "sg:province":"Vaud",
    "wof:name":"Popken & Co Ulla Popken Mode",
    "wof:placetype":"venue"
},
  "geometry": {"coordinates":[6.631904,46.521408],"type":"Point"}
}