{
  "type": "Feature",
  "properties": {
    "iso:country":"CH",
    "sg:address":"Seefeldstrasse 177",
    "sg:city":"Z\u00fcrich",
    "sg:classifiers":[
        {
            "category":"Restaurant",
            "type":"Food & Drink"
        }
    ],
    "sg:phone":"+41 14220246",
    "sg:postcode":"8008",
    "sg:province":"Z\u00fcrich",
    "wof:name":"Restaurant Schl\u00fcssel",
    "wof:placetype":"venue"
},
  "geometry": {"coordinates":[8.5573940277,47.3548545837],"type":"Point"}
}