{
  "type": "Feature",
  "properties": {
    "iso:country":"CH",
    "sg:address":"Grienbachstrasse 26",
    "sg:city":"Zug",
    "sg:orig_category":"Grosshandel mit Datenverarbeitungsger\u00e4ten Informatikdienste",
    "sg:phone":"+41 41 763 67 70",
    "sg:postcode":"6300",
    "sg:province":"Zug",
    "wof:name":"Blue Vision Ag Computersysteme",
    "wof:placetype":"venue"
},
  "geometry": {"coordinates":[8.5245018005,47.182926178],"type":"Point"}
}