{
  "type": "Feature",
  "properties": {
    "iso:country":"CH",
    "sg:address":"Zugerstrasse 46 6314 Unter\u00e4geri. Postfach",
    "sg:city":"Unter\u00e4geri",
    "sg:orig_category":"Finanzierungsinstitutionen",
    "sg:postcode":"6314",
    "sg:province":"Zug",
    "wof:name":"I.g.s. Leasing Ag Dienstleistungen Im Finanz- U. Leasingbereich. Waren; Handel Usw",
    "wof:placetype":"venue"
},
  "geometry": {"coordinates":[9.2577762604,47.417930603],"type":"Point"}
}