{
  "type": "Feature",
  "properties": {
    "iso:country":"CH",
    "sg:address":"Rautistrasse 281",
    "sg:city":"Z\u00fcrich",
    "sg:orig_category":"G\u00fcterbef\u00f6rderung im Strassenverkehr",
    "sg:phone":"+41 79 435 94 73",
    "sg:postcode":"8048",
    "sg:province":"Z\u00fcrich",
    "wof:name":"Emil Wirz Transporte",
    "wof:placetype":"venue"
},
  "geometry": {"coordinates":[7.8499732018,47.4853134155],"type":"Point"}
}