{
  "type": "Feature",
  "properties": {
    "iso:country":"CH",
    "sg:address":"Via Cantonale 6912 Pazzallo. Postfach",
    "sg:city":"Pambio-noranco",
    "sg:orig_category":"Diskotheken, Dancings, Night Clubs",
    "sg:phone":"+41 91 985 60 10",
    "sg:postcode":"6915",
    "sg:province":"Ticino",
    "wof:name":"Discoteca Titanic & Night-club-dancing",
    "wof:placetype":"venue"
},
  "geometry": {"coordinates":[8.9427642822,45.9843292236],"type":"Point"}
}