{
  "type": "Feature",
  "properties": {
    "iso:country":"CH",
    "sg:address":"Rue Des Marach\u00eechers 38",
    "sg:city":"Gen\u00e8ve",
    "sg:orig_category":"Fachdetailhandel in Verkaufsr\u00e4umen",
    "sg:phone":"+41 81 740 56 80",
    "sg:postcode":"1200",
    "sg:province":"Gen\u00e8ve",
    "wof:name":"S.t.c. Sport Technologie Center Ag",
    "wof:placetype":"venue"
},
  "geometry": {"coordinates":[9.4788551331,47.1645050049],"type":"Point"}
}