{
  "type": "Feature",
  "properties": {
    "iso:country":"CH",
    "sg:address":"Rue Rodolphe-toepffer 21",
    "sg:city":"Gen\u00e8ve",
    "sg:orig_category":"Tanzschulen, Tanzlehrer",
    "sg:phone":"+41 22 346 45 84",
    "sg:postcode":"1206",
    "sg:province":"Gen\u00e8ve",
    "wof:name":"Youra Tch\u00e9r\u00e9missinoff Ecole De Danse Classique",
    "wof:placetype":"venue"
},
  "geometry": {"coordinates":[6.1546711922,46.1980514526],"type":"Point"}
}