{
  "type": "Feature",
  "properties": {
    "iso:country":"CH",
    "sg:address":"Route De Peney 50",
    "sg:city":"Vernier",
    "sg:orig_category":"Handel mit Automobilen",
    "sg:phone":"+41 22 341 21 21",
    "sg:postcode":"1214",
    "sg:province":"Gen\u00e8ve",
    "wof:name":"Transit Autos Export, Barth",
    "wof:placetype":"venue"
},
  "geometry": {"coordinates":[6.0754499435,46.2109451294],"type":"Point"}
}