{
  "type": "Feature",
  "properties": {
    "iso:country":"CH",
    "sg:address":"Ch. Des Anciens-moulins 18",
    "sg:city":"Pully",
    "sg:orig_category":"Grosshandel mit Getr\u00e4nken",
    "sg:postcode":"1009",
    "sg:province":"Vaud",
    "wof:name":"Cvc J.-p. Barendse",
    "wof:placetype":"venue"
},
  "geometry": {"coordinates":[6.2354798317,46.4775047302],"type":"Point"}
}