{
  "type": "Feature",
  "properties": {
    "iso:country":"CH",
    "sg:address":"Bertastrasse 23 8003 Z\u00fcrich. Postfach",
    "sg:city":"Z\u00fcrich",
    "sg:orig_category":"Sonstiger Grosshandel",
    "sg:postcode":"8003",
    "sg:province":"Z\u00fcrich",
    "wof:name":"Matrimex Ltd",
    "wof:placetype":"venue"
},
  "geometry": {"coordinates":[8.5148963928,47.3745155334],"type":"Point"}
}