{
  "type": "Feature",
  "properties": {
    "iso:country":"CH",
    "sg:address":"Stutzstr. 7 3700 Spiez. Postfach",
    "sg:city":"Hondrich",
    "sg:orig_category":"Werbung",
    "sg:phone":"+41 19155838",
    "sg:postcode":"3702",
    "sg:province":"Bern",
    "wof:name":"Agentur Meier Oskar",
    "wof:placetype":"venue"
},
  "geometry": {"coordinates":[8.6020917892,47.2958564758],"type":"Point"}
}