{
  "type": "Feature",
  "properties": {
    "iso:country":"CH",
    "sg:address":"Corso Elvezia 1 6900 Lugano. Postfach Caselle Postale 2106",
    "sg:city":"Lugano",
    "sg:orig_category":"Grosshandel mit Bekleidung Grosshandel mit Textilien",
    "sg:phone":"+41 91 922 00 83",
    "sg:postcode":"6901",
    "sg:province":"Ticino",
    "wof:name":"Figli Di Leo Rubinfeld & Co. Articoli Di Abbigliamento E Biancheria Ecc; Compra, Vendita",
    "wof:placetype":"venue"
},
  "geometry": {"coordinates":[8.9553623199,46.0057983398],"type":"Point"}
}