{
  "type": "Feature",
  "properties": {
    "iso:country":"CH",
    "sg:address":"1305 Penthalaz Case Postale 60",
    "sg:city":"Penthalaz",
    "sg:orig_category":"Non-Classified Establishments",
    "sg:phone":"+41 61 751 41 61",
    "sg:postcode":"1305",
    "sg:province":"Vaud",
    "wof:name":"Provini Steuern + Treuhand",
    "wof:placetype":"venue"
},
  "geometry": {"coordinates":[7.6007962227,47.4779167175],"type":"Point"}
}