{
  "type": "Feature",
  "properties": {
    "iso:country":"CH",
    "sg:address":"Bremgartenstrasse 30",
    "sg:city":"Z\u00fcrich",
    "sg:orig_category":"Fachdetailhandel in Verkaufsr\u00e4umen",
    "sg:phone":"+41 14616121",
    "sg:postcode":"8003",
    "sg:province":"Z\u00fcrich",
    "wof:name":"Nussbaumer Doris Modeschmuck",
    "wof:placetype":"venue"
},
  "geometry": {"coordinates":[8.5188961029,47.371547699],"type":"Point"}
}