{
  "type": "Feature",
  "properties": {
    "iso:country":"CH",
    "sg:address":"Route De Florissant 70",
    "sg:city":"Gen\u00e8ve",
    "sg:orig_category":"Arztpraxen",
    "sg:phone":"+41 22 347 96 96",
    "sg:postcode":"1206",
    "sg:province":"Gen\u00e8ve",
    "wof:name":"Dr M\u00e9d. Paul Desjacques M\u00e9decin Sp\u00e9cialiste Fmh",
    "wof:placetype":"venue"
},
  "geometry": {"coordinates":[6.162417,46.192921],"type":"Point"}
}