{
  "type": "Feature",
  "properties": {
    "iso:country":"CH",
    "sg:address":"L\u00f6sliweg 183.",
    "sg:city":"Felsberg",
    "sg:orig_category":"Herstellung von Ausbauelementen aus Metall",
    "sg:postcode":"7012",
    "sg:province":"Graubunden",
    "wof:name":"Ammann Storen Ag",
    "wof:placetype":"venue"
},
  "geometry": {"coordinates":[9.3557453156,47.4161453247],"type":"Point"}
}