{
  "type": "Feature",
  "properties": {
    "iso:country":"CH",
    "sg:address":"Chemin De Vermont 14",
    "sg:city":"Lausanne",
    "sg:orig_category":"Fahrschulen, Flugschulen",
    "sg:phone":"+41 21 617 82 56",
    "sg:postcode":"1006",
    "sg:province":"Vaud",
    "wof:name":"Jean-michel Chollet Auto-\u00e9cole",
    "wof:placetype":"venue"
},
  "geometry": {"coordinates":[6.6402177811,46.5112724304],"type":"Point"}
}