{
  "type": "Feature",
  "properties": {
    "iso:country":"CH",
    "sg:address":"Flurwaldweg 6",
    "sg:city":"T\u00e4gerig",
    "sg:orig_category":"Dachdeckerei Zimmerei, Dachdeckerei, Bauspenglerei U Abdichtung",
    "sg:phone":"+41 56 631 05 69",
    "sg:postcode":"5522",
    "sg:province":"Aargau",
    "wof:name":"Meier Haustec Ag",
    "wof:placetype":"venue"
},
  "geometry": {"coordinates":[8.394902,47.341244],"type":"Point"}
}