{
  "type": "Feature",
  "properties": {
    "iso:country":"CH",
    "sg:address":"Eggstrasse 5 6232 Geuensee. Postfach",
    "sg:city":"Sursee",
    "sg:orig_category":"Verarbeitung von Tee U Kaffee",
    "sg:postcode":"6210",
    "sg:province":"Luzern",
    "wof:name":"Kafi Box Ag Kaffee; Hanel Usw",
    "wof:placetype":"venue"
},
  "geometry": {"coordinates":[8.1151676178,47.1983680725],"type":"Point"}
}