{
  "type": "Feature",
  "properties": {
    "iso:country":"CH",
    "sg:address":"St. Jakobs-strasse 222 4051 Basel. Postfach Postfach 2647",
    "sg:city":"Basel",
    "sg:orig_category":"Autotransporte international Lagerh\u00e4user",
    "sg:phone":"+41 71 466 01 11",
    "sg:postcode":"4002",
    "sg:province":"Basel-Stadt",
    "wof:name":"Danzas Ag",
    "wof:placetype":"venue"
},
  "geometry": {"coordinates":[9.37343,47.556782],"type":"Point"}
}