{
  "type": "Feature",
  "properties": {
    "iso:country":"CH",
    "sg:address":"Eichhornweg 6",
    "sg:city":"Kreuzlingen",
    "sg:orig_category":"Vermietung U Verpachtung von eigenen Immobilien Vermittlung von Immobilien",
    "sg:phone":"+41 71 672 43 37",
    "sg:postcode":"8280",
    "sg:province":"Thurgau",
    "wof:name":"Escasa Ag",
    "wof:placetype":"venue"
},
  "geometry": {"coordinates":[9.1814126968,47.6380310059],"type":"Point"}
}