{
  "type": "Feature",
  "properties": {
    "iso:country":"CH",
    "sg:address":"8880 Walenstadt. Postfach 3",
    "sg:city":"Walenstadt",
    "sg:orig_category":"Sportvereine Ballsport Fussball Vereine Damen",
    "sg:phone":"+41 81 735 13 04",
    "sg:postcode":"8880",
    "sg:province":"St. Gallen",
    "wof:name":"Fc Walenstadt Abt.damen",
    "wof:placetype":"venue"
},
  "geometry": {"coordinates":[9.3131351471,47.1246147156],"type":"Point"}
}