{
  "type": "Feature",
  "properties": {
    "iso:country":"CH",
    "sg:address":"Chemin Des Chenevi\u00e8res 20",
    "sg:city":"Bulle",
    "sg:orig_category":"Grosshandel mit Getreide, Saatgut U Futtermitteln G\u00fcterbef\u00f6rderung im Strassenverkehr",
    "sg:phone":"+41 26 912 61 56",
    "sg:postcode":"1630",
    "sg:province":"Fribourg",
    "wof:name":"Yerly Michel",
    "wof:placetype":"venue"
},
  "geometry": {"coordinates":[7.0598978996,46.6218414307],"type":"Point"}
}