{
  "type": "Feature",
  "properties": {
    "iso:country":"CH",
    "sg:address":"Schlossmattstrasse 17",
    "sg:city":"Thun",
    "sg:orig_category":"Non-Classified Establishments",
    "sg:postcode":"3600",
    "sg:province":"Bern",
    "wof:name":"Baumaterialien Von Gunten Ag",
    "wof:placetype":"venue"
},
  "geometry": {"coordinates":[7.6266131401,46.7555274963],"type":"Point"}
}