{
  "type": "Feature",
  "properties": {
    "iso:country":"CH",
    "sg:address":"Falkenstrasse 3 A",
    "sg:city":"Langenthal",
    "sg:orig_category":"Unclassifiable Establishments",
    "sg:postcode":"4900",
    "sg:province":"Bern",
    "wof:name":"Thg Treuhand Gmbh",
    "wof:placetype":"venue"
},
  "geometry": {"coordinates":[7.7834420204,47.2222518921],"type":"Point"}
}