{
  "type": "Feature",
  "properties": {
    "iso:country":"CH",
    "sg:address":"Bernstrasse 10",
    "sg:city":"Biberist",
    "sg:orig_category":"Veterin\u00e4rwesen",
    "sg:postcode":"4562",
    "sg:province":"Solothurn",
    "wof:name":"Tiermed Ag",
    "wof:placetype":"venue"
},
  "geometry": {"coordinates":[7.5550570488,47.1807556152],"type":"Point"}
}