{
  "type": "Feature",
  "properties": {
    "iso:country":"CH",
    "sg:address":"Ohmstrasse 14",
    "sg:city":"Z\u00fcrich",
    "sg:orig_category":"Fussreflexzonenmassage",
    "sg:phone":"+41 19101521",
    "sg:postcode":"8050",
    "sg:province":"Z\u00fcrich",
    "wof:name":"Helen Oliva Fussreflexzonentherapie",
    "wof:placetype":"venue"
},
  "geometry": {"coordinates":[8.5911579132,47.3046913147],"type":"Point"}
}