{
  "type": "Feature",
  "properties": {
    "iso:country":"CH",
    "sg:address":"Waffengasse 1 2502 Biel/bienne. Postfach",
    "sg:city":"Biel/bienne",
    "sg:orig_category":"RESTAURANTS: TEA-ROOMS",
    "sg:postcode":"2502",
    "sg:province":"Bern",
    "wof:name":"Brander Rudolf",
    "wof:placetype":"venue"
},
  "geometry": {"coordinates":[9.3020200729,47.4868774414],"type":"Point"}
}