{
  "type": "Feature",
  "properties": {
    "iso:country":"CH",
    "sg:address":"Rue Dr-schwab 16",
    "sg:city":"St-imier",
    "sg:classifiers":[
        {
            "category":"Restaurant",
            "type":"Food & Drink"
        }
    ],
    "sg:phone":"+41 26 413 21 27",
    "sg:postcode":"2610",
    "sg:province":"Bern",
    "wof:name":"Restaurant Montagnards",
    "wof:placetype":"venue"
},
  "geometry": {"coordinates":[7.1380701065,46.6968002319],"type":"Point"}
}