{
  "type": "Feature",
  "properties": {
    "iso:country":"CH",
    "sg:address":"Clochettes Chemin Des 16 1206 Gen\u00e8ve. Postfach",
    "sg:city":"Gen\u00e8ve",
    "sg:orig_category":"Gesundheitswesen",
    "sg:postcode":"1206",
    "sg:province":"Gen\u00e8ve",
    "wof:name":"Winfood, Mme Winberg",
    "wof:placetype":"venue"
},
  "geometry": {"coordinates":[6.158768177,46.1886672974],"type":"Point"}
}