{
  "type": "Feature",
  "properties": {
    "iso:country":"CH",
    "sg:address":"Langmattstrasse 2b 6343 Rotkreuz. Postfach",
    "sg:city":"Rotkreuz",
    "sg:orig_category":"Unclassifiable Establishments",
    "sg:postcode":"6343",
    "sg:province":"Zug",
    "wof:name":"Meyer Kleintransporte Kleintransporte",
    "wof:placetype":"venue"
},
  "geometry": {"coordinates":[8.4349794388,47.140335083],"type":"Point"}
}