{
  "type": "Feature",
  "properties": {
    "addr:full":"Place Du Midi 40 1950 Sion Case Postale 185 Sion Valais 1951",
    "addr:housenumber":"40;185",
    "addr:postcode":"1950;1951",
    "addr:street":"Place Du Midi;Postale",
    "iso:country":"CH",
    "sg:address":"Place Du Midi 40 1950 Sion Case Postale 185",
    "sg:city":"Sion",
    "sg:orig_category":"Alters U Hinterlassenenversicherung AHV, Invalidenversicherung IV, Arbeitslosenversicherung ALV",
    "sg:phone":"+41 27 323 72 30",
    "sg:postcode":"1951",
    "sg:province":"Valais",
    "wof:name":"Caisse Publique Cantonale Valaisanne De Ch\u00f4mage",
    "wof:placetype":"venue"
},
  "geometry": {"coordinates":[7.361875,46.231525],"type":"Point"}
}