{
  "type": "Feature",
  "properties": {
    "iso:country":"CH",
    "sg:address":"Bettenhausenstrasse 22",
    "sg:city":"Herzogenbuchsee",
    "sg:orig_category":"Schmieden",
    "sg:phone":"+41 62 961 19 10",
    "sg:postcode":"3360",
    "sg:province":"Bern",
    "wof:name":"Friedrich Moser Messerschmiede",
    "wof:placetype":"venue"
},
  "geometry": {"coordinates":[7.7066030502,47.18542099],"type":"Point"}
}