{
  "type": "Feature",
  "properties": {
    "iso:country":"CH",
    "sg:address":"K\u00f6niztalstrasse 23",
    "sg:city":"K\u00f6niz",
    "sg:orig_category":"Sonstige mit Sport verbundene T\u00e4tigkeiten",
    "sg:phone":"+41 31 971 48 40",
    "sg:postcode":"3098",
    "sg:province":"Bern",
    "wof:name":"Eldorado Reitsport Genossenschaft, Gurtent\u00e4li",
    "wof:placetype":"venue"
},
  "geometry": {"coordinates":[7.4215621948,46.9171676636],"type":"Point"}
}