{
  "type": "Feature",
  "properties": {
    "iso:country":"CH",
    "sg:address":"Schipfe 45",
    "sg:city":"Z\u00fcrich",
    "sg:orig_category":"Werbegrafikateliers",
    "sg:phone":"+41 12119477",
    "sg:postcode":"8001",
    "sg:province":"Z\u00fcrich",
    "wof:name":"Odermatt & Tissi Grafisches Atelier",
    "wof:placetype":"venue"
},
  "geometry": {"coordinates":[8.5416507721,47.3736991882],"type":"Point"}
}