{
  "type": "Feature",
  "properties": {
    "iso:country":"CH",
    "sg:address":"Eymattstrasse 71",
    "sg:city":"Bern",
    "sg:orig_category":"Detailhandel mit Schreib U Papeteriewaren Grafikateliers, Design",
    "sg:phone":"+41 31 994 27 81",
    "sg:postcode":"3027",
    "sg:province":"Bern",
    "wof:name":"Andreas Harisberger Harisign/beschriftungsbedarf",
    "wof:placetype":"venue"
},
  "geometry": {"coordinates":[7.3928399086,46.951210022],"type":"Point"}
}