{
  "type": "Feature",
  "properties": {
    "iso:country":"CH",
    "sg:address":"Moosackerweg 7",
    "sg:city":"Zunzgen",
    "sg:orig_category":"Grosshandel mit Geschenkartikeln U Souvenirs Herstellung von sonstigen Maschinen f\u00fcr bestimmte Verwe",
    "sg:phone":"+41 79 674 24 44",
    "sg:postcode":"4455",
    "sg:province":"Basel-Landschaft",
    "wof:name":"Heiwiprint Wildhaber",
    "wof:placetype":"venue"
},
  "geometry": {"coordinates":[7.8042111397,47.4544677734],"type":"Point"}
}