{
  "type": "Feature",
  "properties": {
    "iso:country":"CH",
    "sg:address":"Seestrasse 324",
    "sg:city":"Horgen",
    "sg:orig_category":"Hoch U Tiefbau",
    "sg:phone":"+41 17253215",
    "sg:postcode":"8810",
    "sg:province":"Z\u00fcrich",
    "wof:name":"Ren\u00e9 Vigini Baugesch\u00e4ft",
    "wof:placetype":"venue"
},
  "geometry": {"coordinates":[8.6078329086,47.2568054199],"type":"Point"}
}