{
  "type": "Feature",
  "properties": {
    "addr:full":"Ch. Grand-cour 8 Troinex Gen\u00e8ve 1256",
    "addr:housenumber":"8",
    "addr:postcode":"1256",
    "addr:street":"Ch. Grand-Cour",
    "iso:country":"CH",
    "sg:address":"Ch. Grand-cour 8",
    "sg:city":"Troinex",
    "sg:classifiers":[
        {
            "category":"Banks & Credit Unions",
            "subcategory":"Bank",
            "type":"Services"
        }
    ],
    "sg:phone":"+41 24 479 13 43",
    "sg:postcode":"1256",
    "sg:province":"Gen\u00e8ve",
    "wof:name":"Banque Raiffeisen Val D'illiez-champ\u00e9ry",
    "wof:placetype":"venue"
},
  "geometry": {"coordinates":[6.87068,46.179401],"type":"Point"}
}