{
  "type": "Feature",
  "properties": {
    "iso:country":"CH",
    "sg:address":"Gotthelfstrasse 23",
    "sg:city":"Burgdorf",
    "sg:classifiers":[
        {
            "category":"Health Services",
            "subcategory":"Dentist",
            "type":"Services"
        }
    ],
    "sg:phone":"+41 34 422 75 22",
    "sg:postcode":"3400",
    "sg:province":"Bern",
    "sg:tags":[
        "dental",
        "implant"
    ],
    "wof:name":"Thomas K\u00fchne Zahntechnisches Laboratorium",
    "wof:placetype":"venue"
},
  "geometry": {"coordinates":[7.625844,47.059086],"type":"Point"}
}