{
  "type": "Feature",
  "properties": {
    "iso:country":"CH",
    "sg:address":"Steinhofstrasse 33",
    "sg:city":"Luzern",
    "sg:classifiers":[
        {
            "category":"Insurance",
            "subcategory":"Insurance Agent",
            "type":"Services"
        }
    ],
    "sg:phone":"+41 41 310 68 40",
    "sg:postcode":"6005",
    "sg:province":"Luzern",
    "sg:tags":[
        "versicherungsagenturen",
        "-broker"
    ],
    "wof:name":"Walter Bucher Versicherungen",
    "wof:placetype":"venue"
},
  "geometry": {"coordinates":[8.2973022461,47.0437164307],"type":"Point"}
}