{
  "type": "Feature",
  "properties": {
    "iso:country":"CH",
    "sg:address":"Gare Rue De La 4 2710 Tavannes. Postfach",
    "sg:city":"Tavannes",
    "sg:classifiers":[
        {
            "category":"Travel",
            "subcategory":"Hotels & Motels",
            "type":"Entertainment"
        }
    ],
    "sg:postcode":"2710",
    "sg:province":"Bern",
    "sg:tags":[
        "hotels",
        "mit",
        "restaurant"
    ],
    "wof:name":"Gaschen Jacques Hotel-restaurant De La Gare",
    "wof:placetype":"venue"
},
  "geometry": {"coordinates":[7.1996560097,47.2200469971],"type":"Point"}
}