{
  "type": "Feature",
  "properties": {
    "iso:country":"CH",
    "sg:address":"Route Des Ch\u00e2taigniers 1816 Chailly-montreux. Postfach",
    "sg:city":"Chailly-montreux",
    "sg:orig_category":"Einzelhandel mit Automobilen Instandhaltung U Reparatur von Automobilen",
    "sg:phone":"+41 21 964 31 91",
    "sg:postcode":"1816",
    "sg:province":"Vaud",
    "wof:name":"Garage-carrosserie Du Stade - D'amario Dario S\u00e0rl",
    "wof:placetype":"venue"
},
  "geometry": {"coordinates":[6.8933029175,46.4530754089],"type":"Point"}
}