{
  "type": "Feature",
  "properties": {
    "iso:country":"CH",
    "sg:address":"Campagna Via",
    "sg:city":"Biogno",
    "sg:orig_category":"G\u00fcterbef\u00f6rderung im Strassenverkehr",
    "sg:postcode":"6932",
    "sg:province":"Ticino",
    "wof:name":"Jacky Maeder Sa Per Trasporti Internazionali, Succursale Di Bioggio",
    "wof:placetype":"venue"
},
  "geometry": {"coordinates":[8.9248876572,46.0064048767],"type":"Point"}
}