{
  "type": "Feature",
  "properties": {
    "iso:country":"CH",
    "sg:address":"Sonnmatt 1",
    "sg:city":"Rotkreuz",
    "sg:orig_category":"Handels-H\u00e4user U Gesellschaften",
    "sg:postcode":"6343",
    "sg:province":"Zug",
    "wof:name":"W. Br\u00e4ndli Handels - Agentur Gmbh",
    "wof:placetype":"venue"
},
  "geometry": {"coordinates":[8.4299097061,47.143787384],"type":"Point"}
}