{
  "type": "Feature",
  "properties": {
    "iso:country":"CH",
    "sg:address":"Neuengass-passage 3",
    "sg:city":"Bern",
    "sg:orig_category":"Detailhandel mit Uhren U Schmuck Fachdetailhandel in Verkaufsr\u00e4umen",
    "sg:phone":"+41 24 495 37 59",
    "sg:postcode":"3011",
    "sg:province":"Bern",
    "wof:name":"Ortime Sa",
    "wof:placetype":"venue"
},
  "geometry": {"coordinates":[7.0550079346,46.2969665527],"type":"Point"}
}