{
  "type": "Feature",
  "properties": {
    "iso:country":"CH",
    "sg:address":"Hinterb\u00fcelstrasse 3",
    "sg:city":"Effretikon",
    "sg:orig_category":"Spezieller Tiefbau Test U Sondierbohrungen",
    "sg:phone":"+41 52 347 01 30",
    "sg:postcode":"8307",
    "sg:province":"Z\u00fcrich",
    "wof:name":"Sif-groutbor Sa",
    "wof:placetype":"venue"
},
  "geometry": {"coordinates":[8.6871385574,47.4275588989],"type":"Point"}
}