{
  "type": "Feature",
  "properties": {
    "iso:country":"CH",
    "sg:address":"Wydlerweg 19 8047 Z\u00fcrich. Postfach 1695",
    "sg:city":"Z\u00fcrich",
    "sg:orig_category":"Sportvereine Ballsport Fussball",
    "sg:phone":"+41 14313069",
    "sg:postcode":"8048",
    "sg:province":"Z\u00fcrich",
    "wof:name":"Fc Altstetten Zh",
    "wof:placetype":"venue"
},
  "geometry": {"coordinates":[8.486287117,47.3766517639],"type":"Point"}
}