{
  "type": "Feature",
  "properties": {
    "addr:full":"Hitzigweg 11 8032 Z\u00fcrich 32 Zust. Postfach 8032 Z\u00fcrich Zust 32",
    "addr:housenumber":"11;32;32",
    "addr:postcode":"8032;8032",
    "addr:street":"Hitzigweg;Postfach;Zust",
    "iso:country":"CH",
    "sg:address":"Hitzigweg 11 8032 Z\u00fcrich 32 Zust. Postfach 8032 Z\u00fcrich",
    "sg:city":"Zust",
    "sg:orig_category":"Pensionskassen",
    "sg:phone":"+41 19143535",
    "sg:postcode":"32",
    "wof:name":"Stamfag-personalvorsorgestiftung",
    "wof:placetype":"venue"
},
  "geometry": {"coordinates":[8.582382,47.319427],"type":"Point"}
}