{
  "type": "Feature",
  "properties": {
    "iso:country":"CH",
    "sg:address":"Rue Centrale 31",
    "sg:city":"Lausanne",
    "sg:orig_category":"Kosmetikinstitute",
    "sg:phone":"+41 21 311 45 11",
    "sg:postcode":"1003",
    "sg:province":"Vaud",
    "wof:name":"Cath\u00e9rine Schaub Institut De Beaut\u00e9 Aquarelle",
    "wof:placetype":"venue"
},
  "geometry": {"coordinates":[6.6360068321,46.5210113525],"type":"Point"}
}