{
  "type": "Feature",
  "properties": {
    "iso:country":"CH",
    "sg:address":"Rte Du Simplon",
    "sg:city":"Charrat",
    "sg:orig_category":"Mechanik",
    "sg:postcode":"1906",
    "sg:province":"Valais",
    "wof:name":"Chappuis Michel",
    "wof:placetype":"venue"
},
  "geometry": {"coordinates":[7.3421578407,47.3270568848],"type":"Point"}
}