{
  "type": "Feature",
  "properties": {
    "iso:country":"CH",
    "sg:address":"Rain 41 5000 Aarau. Postfach",
    "sg:city":"Aarau",
    "sg:orig_category":"Organisationen der Wohlfahrtspflege",
    "sg:phone":"+41 19339020",
    "sg:postcode":"5001",
    "sg:province":"Aargau",
    "wof:name":"Pro Infirmis",
    "wof:placetype":"venue"
},
  "geometry": {"coordinates":[8.8005952835,47.3209381104],"type":"Point"}
}