{
  "type": "Feature",
  "properties": {
    "iso:country":"CH",
    "sg:address":"Rue Fr\u00e9d\u00e9ric Soguel 1",
    "sg:city":"Cernier",
    "sg:orig_category":"Detailhandel mit Geschenkartikeln U Souvenirs",
    "sg:phone":"+41 32 853 21 93",
    "sg:postcode":"2053",
    "sg:province":"Neuch\u00e2tel",
    "wof:name":"Anne-marie Marietta Boutique La Chiffonnerie",
    "wof:placetype":"venue"
},
  "geometry": {"coordinates":[6.9035720825,47.0597648621],"type":"Point"}
}