{
  "type": "Feature",
  "properties": {
    "iso:country":"CH",
    "sg:address":"Nant Rue Du 8 1207 Gen\u00e8ve. Postfach",
    "sg:city":"Gen\u00e8ve",
    "sg:orig_category":"Werbung",
    "sg:phone":"+41 32 913 51 52",
    "sg:postcode":"1201",
    "sg:province":"Gen\u00e8ve",
    "wof:name":"Polygone Publicit\u00e9 Et Communication S\u00e0rl",
    "wof:placetype":"venue"
},
  "geometry": {"coordinates":[6.8235998154,47.1000022888],"type":"Point"}
}