{
  "type": "Feature",
  "properties": {
    "iso:country":"CH",
    "sg:address":"Ottikerstrasse 2",
    "sg:city":"Z\u00fcrich",
    "sg:orig_category":"Grosshandel mit B\u00fcromaschinen Grosshandel mit Datenverarbeitungsger\u00e4ten",
    "sg:phone":"+41 71 913 99 55",
    "sg:postcode":"8006",
    "sg:province":"Z\u00fcrich",
    "wof:name":"Datapark Ag",
    "wof:placetype":"venue"
},
  "geometry": {"coordinates":[9.0351219177,47.4612464905],"type":"Point"}
}