{
  "type": "Feature",
  "properties": {
    "iso:country":"CH",
    "sg:address":"1138",
    "sg:city":"Villars-sous-yens",
    "sg:orig_category":"Detailhandel mit Waren verschiedener Art, Hauptrichtung Nahrungsmittel",
    "sg:phone":"+41 21 800 38 00",
    "sg:postcode":"1138",
    "wof:name":"Les Nectars Du Terroir Epicerie",
    "wof:placetype":"venue"
},
  "geometry": {"coordinates":[6.4161701202,46.5183753967],"type":"Point"}
}