{
  "type": "Feature",
  "properties": {
    "iso:country":"CH",
    "sg:address":"Balgacherstrasse 16",
    "sg:city":"Rebstein",
    "sg:orig_category":"Fahrschulen, Flugschulen",
    "sg:phone":"+41 71 777 39 15",
    "sg:postcode":"9445",
    "sg:province":"St. Gallen",
    "wof:name":"Walti's Fahrschule",
    "wof:placetype":"venue"
},
  "geometry": {"coordinates":[9.591047287,47.3955535889],"type":"Point"}
}