{
  "type": "Feature",
  "properties": {
    "iso:country":"CH",
    "sg:address":"Wittenwilerstrasse 14",
    "sg:city":"Aadorf",
    "sg:classifiers":[
        {
            "category":"Insurance",
            "subcategory":"Insurance Agent",
            "type":"Services"
        }
    ],
    "sg:phone":"+41 52 365 22 66",
    "sg:postcode":"8355",
    "sg:province":"Thurgau",
    "sg:tags":[
        "versicherungsagenturen",
        "-broker"
    ],
    "wof:name":"Basler Versicherungen Agentur",
    "wof:placetype":"venue"
},
  "geometry": {"coordinates":[8.9004793167,47.4947662354],"type":"Point"}
}