{
  "type": "Feature",
  "properties": {
    "iso:country":"CH",
    "sg:address":"Rue Centrale 7",
    "sg:city":"Corsier-sur-vevey",
    "sg:orig_category":"Instandhaltung U Reparatur von Automobilen",
    "sg:postcode":"1804",
    "sg:province":"Vaud",
    "wof:name":"Gattoni Maintenance Poids Lourds Sa",
    "wof:placetype":"venue"
},
  "geometry": {"coordinates":[6.8423280716,46.4706039429],"type":"Point"}
}