{
  "type": "Feature",
  "properties": {
    "iso:country":"CH",
    "sg:address":"Bolgengasse 33",
    "sg:city":"Zweisimmen",
    "sg:orig_category":"Herstellung von sonstigen elektrischen Ausr\u00fcstungen Telecomshops",
    "sg:phone":"+41 33 722 24 81",
    "sg:postcode":"3770",
    "sg:province":"Bern",
    "wof:name":"Recom Electronic, Hansruedi Reutiger",
    "wof:placetype":"venue"
},
  "geometry": {"coordinates":[7.3715162277,46.5581359863],"type":"Point"}
}