{
  "type": "Feature",
  "properties": {
    "iso:country":"CH",
    "sg:address":"Dorf",
    "sg:city":"M\u00fcswangen",
    "sg:classifiers":[
        {
            "category":"Restaurant",
            "type":"Food & Drink"
        }
    ],
    "sg:phone":"+41 41 917 13 71",
    "sg:postcode":"6289",
    "sg:province":"Luzern",
    "wof:name":"Restaurant Linde",
    "wof:placetype":"venue"
},
  "geometry": {"coordinates":[8.2895555496,47.2336540222],"type":"Point"}
}