{
  "type": "Feature",
  "properties": {
    "iso:country":"CH",
    "sg:address":"Haselstrasse 27",
    "sg:city":"Baden",
    "sg:orig_category":"Reparatur von Schuhen U Lederwaren",
    "sg:phone":"+41 56 222 51 83",
    "sg:postcode":"5400",
    "sg:province":"Aargau",
    "wof:name":"Silvestro Maffei Schuhmachergesch\u00e4ft",
    "wof:placetype":"venue"
},
  "geometry": {"coordinates":[8.3050813675,47.4775390625],"type":"Point"}
}