{
  "type": "Feature",
  "properties": {
    "iso:country":"CH",
    "sg:address":"Via Beltramina 20a",
    "sg:city":"Lugano",
    "sg:orig_category":"Vereine Gemeinn\u00fctzige",
    "sg:phone":"+41 91 972 14 72",
    "sg:postcode":"6900",
    "sg:province":"Ticino",
    "wof:name":"Assoc.ticinese Terza Et\u00e0 Gruppo Luganese",
    "wof:placetype":"venue"
},
  "geometry": {"coordinates":[8.9610071182,46.0163993835],"type":"Point"}
}