{
  "type": "Feature",
  "properties": {
    "iso:country":"CH",
    "sg:address":"Oberdorfstrasse 14b",
    "sg:city":"Herisau",
    "sg:orig_category":"Architektur U Ingenieurb\u00fcros",
    "sg:phone":"+41 71 350 15 60",
    "sg:postcode":"9100",
    "sg:province":"Appenzell Ausserrhoden",
    "wof:name":"Halter Engineering Gmbh",
    "wof:placetype":"venue"
},
  "geometry": {"coordinates":[9.279271,47.38517],"type":"Point"}
}