{
  "type": "Feature",
  "properties": {
    "iso:country":"CH",
    "sg:address":"Stadtturmstrasse 10",
    "sg:city":"Baden",
    "sg:orig_category":"Vermittlung von Immobilien Verwaltung von Immobilien",
    "sg:phone":"+41 56 203 00 70",
    "sg:postcode":"5400",
    "sg:province":"Aargau",
    "wof:name":"Privera Ag Immobilien & Verwaltungen",
    "wof:placetype":"venue"
},
  "geometry": {"coordinates":[8.3057947159,47.4759101868],"type":"Point"}
}