{
  "type": "Feature",
  "properties": {
    "iso:country":"CH",
    "sg:address":"Bleichemattstrasse 1",
    "sg:city":"Aarau",
    "sg:orig_category":"Forst\u00e4mter",
    "sg:phone":"+41 62 835 28 20",
    "sg:postcode":"5000",
    "sg:province":"Aargau",
    "wof:name":"Finanzdepartement Aargau Abteilung Wald",
    "wof:placetype":"venue"
},
  "geometry": {"coordinates":[8.0527591705,47.3906097412],"type":"Point"}
}