{
  "type": "Feature",
  "properties": {
    "iso:country":"CH",
    "sg:address":"Worbstrasse 36 3113 Rubigen. Postfach",
    "sg:city":"Rubigen",
    "sg:orig_category":"Religi\u00f6se Vereinigungen divers",
    "sg:phone":"+41 71 227 33 33",
    "sg:postcode":"3113",
    "sg:province":"Bern",
    "wof:name":"Verwaltung & Kanzlei Des Kath. Konfessionsteils,admin.kath.",
    "wof:placetype":"venue"
},
  "geometry": {"coordinates":[9.3777246475,47.423374176],"type":"Point"}
}