{
  "type": "Feature",
  "properties": {
    "iso:country":"CH",
    "sg:address":"3186 D\u00fcdingen. Postfach 230",
    "sg:city":"D\u00fcdingen",
    "sg:orig_category":"Detailhandel mit elektrischen Haushalts-,Radio U Fernsehger\u00e4ten sowie Musikinstrumenten",
    "sg:postcode":"3186",
    "sg:province":"Fribourg",
    "wof:name":"Video-tropic, Ackermann Eliane",
    "wof:placetype":"venue"
},
  "geometry": {"coordinates":[7.1900749207,46.8504104614],"type":"Point"}
}