{
  "type": "Feature",
  "properties": {
    "iso:country":"CH",
    "sg:address":"Route D'yverdon 8",
    "sg:city":"Pr\u00e9verenges",
    "sg:orig_category":"Architektur U Ingenieurb\u00fcros Architekturb\u00fcros",
    "sg:phone":"+41 21 803 42 72",
    "sg:postcode":"1028",
    "sg:province":"Vaud",
    "wof:name":"Gutscher Architectes Sa",
    "wof:placetype":"venue"
},
  "geometry": {"coordinates":[6.528641,46.520184],"type":"Point"}
}