{
  "type": "Feature",
  "properties": {
    "iso:country":"CH",
    "sg:address":"Chemin Du Vaugueny",
    "sg:city":"Epalinges",
    "sg:orig_category":"Kosmetikinstitute",
    "sg:phone":"+41 21 652 30 20",
    "sg:postcode":"1066",
    "sg:province":"Vaud",
    "wof:name":"Institut De Beaut\u00e9 L\u00e9ore, Lotfy-pointet Claudine",
    "wof:placetype":"venue"
},
  "geometry": {"coordinates":[6.6583237648,46.5456161499],"type":"Point"}
}