{
  "type": "Feature",
  "properties": {
    "iso:country":"CH",
    "sg:address":"Esserts Fin Des",
    "sg:city":"Cousset",
    "sg:orig_category":"Softwareentwicklung U beratung",
    "sg:postcode":"1774",
    "sg:province":"Fribourg",
    "wof:name":"Harcon S\u00e0rl",
    "wof:placetype":"venue"
},
  "geometry": {"coordinates":[6.9772849083,46.8183364868],"type":"Point"}
}