{
  "type": "Feature",
  "properties": {
    "iso:country":"CH",
    "sg:address":"Bahnhofstrasse 18",
    "sg:city":"Diessenhofen",
    "sg:orig_category":"Filter Bags, Tubular",
    "sg:phone":"+41 52 657 11 28",
    "sg:postcode":"8253",
    "sg:province":"Thurgau",
    "wof:name":"Fink S\u00f6hne Ag",
    "wof:placetype":"venue"
},
  "geometry": {"coordinates":[8.7530927658,47.6862030029],"type":"Point"}
}