{
  "type": "Feature",
  "properties": {
    "iso:country":"CH",
    "sg:address":"Route De La Bergerie",
    "sg:city":"Courtepin",
    "sg:orig_category":"Mahl U Sch\u00e4lm\u00fchlen",
    "sg:phone":"+41 26 684 83 83",
    "sg:postcode":"1784",
    "sg:province":"Fribourg",
    "wof:name":"Moulin Agricole & S\u00e9choirs",
    "wof:placetype":"venue"
},
  "geometry": {"coordinates":[7.1214761734,46.8684997559],"type":"Point"}
}