{
  "type": "Feature",
  "properties": {
    "iso:country":"CH",
    "sg:address":"H\u00fcsliguet",
    "sg:city":"Mitl\u00f6di",
    "sg:orig_category":"Haltung von Rindern",
    "sg:postcode":"8756",
    "sg:province":"Glarus",
    "wof:name":"Braunviehzuchtgenossenschaft Mitl\u00f6di & Umgebung",
    "wof:placetype":"venue"
},
  "geometry": {"coordinates":[9.0863323212,47.0148925781],"type":"Point"}
}