{
  "type": "Feature",
  "properties": {
    "iso:country":"CH",
    "sg:address":"B\u00e9thusy Avenue De 4 1005 Lausanne. Postfach",
    "sg:city":"Lausanne",
    "sg:orig_category":"Grosshandel mit Textilien",
    "sg:postcode":"1003",
    "sg:province":"Vaud",
    "wof:name":"Gottlieb Bachmann",
    "wof:placetype":"venue"
},
  "geometry": {"coordinates":[9.0338716507,47.4487266541],"type":"Point"}
}