{
  "type": "Feature",
  "properties": {
    "iso:country":"CH",
    "sg:address":"Kleinsch\u00f6nenbergstrasse 56",
    "sg:city":"Tafers",
    "sg:orig_category":"Allgemeiner Hoch U Tiefbau",
    "sg:phone":"+41 26 488 06 06",
    "sg:postcode":"1712",
    "sg:province":"Fribourg",
    "wof:name":"Innoservice Ag",
    "wof:placetype":"venue"
},
  "geometry": {"coordinates":[7.183454,46.805481],"type":"Point"}
}