{
  "type": "Feature",
  "properties": {
    "iso:country":"CH",
    "sg:address":"Schulstrasse 26",
    "sg:city":"Thun",
    "sg:orig_category":"Detailhandel mit Geschenkartikeln U Souvenirs Oberfl\u00e4chenveredlung U W\u00e4rmebehandlung",
    "sg:postcode":"3604",
    "sg:province":"Bern",
    "wof:name":"Anita Fahrni Sportpreise-geschenke Gravuren",
    "wof:placetype":"venue"
},
  "geometry": {"coordinates":[7.6234102249,46.7403488159],"type":"Point"}
}