{
  "type": "Feature",
  "properties": {
    "iso:country":"CH",
    "sg:address":"G\u00fcterstrasse 41",
    "sg:city":"Pratteln",
    "sg:classifiers":[
        {
            "category":"Manufacturing",
            "subcategory":"Rubber & Plastics",
            "type":"Manufacturing & Wholesale Goods"
        }
    ],
    "sg:phone":"+41 61 821 36 67",
    "sg:postcode":"4133",
    "sg:province":"Basel-Landschaft",
    "sg:tags":[
        "processing"
    ],
    "wof:name":"Bws Mecoplast",
    "wof:placetype":"venue"
},
  "geometry": {"coordinates":[7.6852259636,47.5223808289],"type":"Point"}
}