{
  "type": "Feature",
  "properties": {
    "iso:country":"CH",
    "sg:address":"Bahnhofstrasse 60",
    "sg:city":"Muttenz",
    "sg:orig_category":"Baugewerbe Personal U Stellenvermittlung",
    "sg:phone":"+41 61 461 81 18",
    "sg:postcode":"4132",
    "sg:province":"Basel-Landschaft",
    "wof:name":"Leutenegger Hans Sa",
    "wof:placetype":"venue"
},
  "geometry": {"coordinates":[7.648363,47.533173],"type":"Point"}
}