{
  "type": "Feature",
  "properties": {
    "iso:country":"CH",
    "sg:address":"Torre B",
    "sg:city":"Coldrerio",
    "sg:orig_category":"Finanzierungsinstitutionen",
    "sg:phone":"+41 91 683 17 21",
    "sg:postcode":"6877",
    "sg:province":"Ticino",
    "wof:name":"Clarion Finanz Ag",
    "wof:placetype":"venue"
},
  "geometry": {"coordinates":[8.987575531,45.8543815613],"type":"Point"}
}