{
  "type": "Feature",
  "properties": {
    "iso:country":"CH",
    "sg:address":"Industriestrasse 26 8604 Volketswil. Postfach 473",
    "sg:city":"Volketswil",
    "sg:orig_category":"Herstellung von sonstiger Bekleidung U Bekleidungszubeh\u00f6r Textilgewerbe",
    "sg:phone":"+41 19086655",
    "sg:postcode":"8604",
    "sg:province":"Z\u00fcrich",
    "wof:name":"Muller Charles Sa",
    "wof:placetype":"venue"
},
  "geometry": {"coordinates":[8.678874,47.37949],"type":"Point"}
}