{
  "type": "Feature",
  "properties": {
    "iso:country":"CH",
    "sg:address":"Elvezia Corso 23",
    "sg:city":"Lugano",
    "sg:orig_category":"Non-Classified Establishments",
    "sg:postcode":"6900",
    "sg:province":"Ticino",
    "wof:name":"Wamatech Gmbh",
    "wof:placetype":"venue"
},
  "geometry": {"coordinates":[7.3721818924,47.1777496338],"type":"Point"}
}