{
  "type": "Feature",
  "properties": {
    "iso:country":"CH",
    "sg:address":"Dorf",
    "sg:city":"Kiental",
    "sg:orig_category":"Mechanische Werkst\u00e4tten",
    "sg:phone":"+41 33 676 10 21",
    "sg:postcode":"3723",
    "sg:province":"Bern",
    "wof:name":"Christian Aellig Feinmechanische Werkst\u00e4tte",
    "wof:placetype":"venue"
},
  "geometry": {"coordinates":[7.7241921425,46.5875396729],"type":"Point"}
}