{
  "type": "Feature",
  "properties": {
    "iso:country":"CH",
    "sg:address":"Grand Rue 52",
    "sg:city":"Montreux",
    "sg:classifiers":[
        {
            "category":"Insurance",
            "subcategory":"Insurance Agent",
            "type":"Services"
        }
    ],
    "sg:phone":"+41 21 963 89 81",
    "sg:postcode":"1820",
    "sg:province":"Vaud",
    "sg:tags":[
        "versicherungsagenturen",
        "-broker"
    ],
    "wof:name":"Vaudoise Assurances Agence Fran\u00e7ois Junod",
    "wof:placetype":"venue"
},
  "geometry": {"coordinates":[6.910077095,46.4341621399],"type":"Point"}
}