{
  "type": "Feature",
  "properties": {
    "iso:country":"CH",
    "sg:address":"Sch\u00fctzenmattstrasse 1171",
    "sg:city":"B\u00fclach",
    "sg:orig_category":"Detailhandel mit elektrischen Haushalts-,Radio U Fernsehger\u00e4ten sowie Musikinstrumenten",
    "sg:phone":"+41 18624445",
    "sg:postcode":"8180",
    "sg:province":"Z\u00fcrich",
    "wof:name":"Street Beat, Hubacher R.",
    "wof:placetype":"venue"
},
  "geometry": {"coordinates":[8.5331268311,47.5279045105],"type":"Point"}
}