{
  "type": "Feature",
  "properties": {
    "iso:country":"CH",
    "sg:address":"La Carri\u00e8re",
    "sg:city":"Thierrens",
    "sg:orig_category":"Kalb U Schweine-M\u00e4sterei U Zucht",
    "sg:phone":"+41 21 905 33 82",
    "sg:postcode":"1410",
    "sg:province":"Vaud",
    "wof:name":"L'arzelly Sa",
    "wof:placetype":"venue"
},
  "geometry": {"coordinates":[6.7515048981,46.7145614624],"type":"Point"}
}