{
  "type": "Feature",
  "properties": {
    "iso:country":"CH",
    "sg:address":"Dorfstrasse 5b",
    "sg:city":"Untersiggenthal",
    "sg:orig_category":"Stukkateurgewerbe, Gipserei U Verputzerei",
    "sg:postcode":"5417",
    "sg:province":"Aargau",
    "wof:name":"Donno & Sohn Gmbh",
    "wof:placetype":"venue"
},
  "geometry": {"coordinates":[8.2632770538,47.498374939],"type":"Point"}
}