{
  "type": "Feature",
  "properties": {
    "iso:country":"CH",
    "sg:address":"Hintere Bahnhofstrasse 3",
    "sg:city":"Suhr",
    "sg:orig_category":"Druck ohne Zeitungsdruck Satzherstellung U Reproduktion",
    "sg:phone":"+41 62 842 68 68",
    "sg:postcode":"5034",
    "sg:province":"Aargau",
    "wof:name":"Helm Ag",
    "wof:placetype":"venue"
},
  "geometry": {"coordinates":[8.0819559097,47.3701858521],"type":"Point"}
}