{
  "type": "Feature",
  "properties": {
    "iso:country":"CH",
    "sg:address":"Turnhallenstrasse 13",
    "sg:city":"Gelterkinden",
    "sg:orig_category":"Detailhandel mit Damenbekleidung",
    "sg:phone":"+41 61 981 16 75",
    "sg:postcode":"4460",
    "sg:province":"Basel-Landschaft",
    "wof:name":"Hedy Koch Modes",
    "wof:placetype":"venue"
},
  "geometry": {"coordinates":[7.853472,47.463139],"type":"Point"}
}