{
  "type": "Feature",
  "properties": {
    "iso:country":"CH",
    "sg:address":"T\u00fcfacherweg 7",
    "sg:city":"Glattfelden",
    "sg:orig_category":"Werbeagenturen",
    "sg:phone":"+41 18673175",
    "sg:postcode":"8192",
    "sg:province":"Z\u00fcrich",
    "wof:name":"Anton Da Costa Industriewerbung",
    "wof:placetype":"venue"
},
  "geometry": {"coordinates":[8.5007781982,47.5613708496],"type":"Point"}
}