{
  "type": "Feature",
  "properties": {
    "iso:country":"CH",
    "sg:address":"Rue Du Milieu 16",
    "sg:city":"Yverdon-les-bains",
    "sg:orig_category":"Detailhandel mit Uhren U Schmuck Fachdetailhandel in Verkaufsr\u00e4umen",
    "sg:phone":"+41 24 425 21 59",
    "sg:postcode":"1400",
    "sg:province":"Vaud",
    "wof:name":"Boutique D'or, Moser Sybille",
    "wof:placetype":"venue"
},
  "geometry": {"coordinates":[6.6398220062,46.7789268494],"type":"Point"}
}