{
  "type": "Feature",
  "properties": {
    "iso:country":"CH",
    "sg:address":"Meinrad Lienert-strasse 5",
    "sg:city":"Z\u00fcrich",
    "sg:orig_category":"Detailhandel mit Radio U Fernsehger\u00e4ten Detailhandel mit elektrischen Haushalts-,Radio U Fernsehger\u00e4",
    "sg:phone":"+41 14613626",
    "sg:postcode":"8003",
    "sg:province":"Z\u00fcrich",
    "wof:name":"Hifi-video Giovanoli",
    "wof:placetype":"venue"
},
  "geometry": {"coordinates":[8.5185346603,47.3742332458],"type":"Point"}
}