{
  "type": "Feature",
  "properties": {
    "addr:full":"R\u00fchrbergstrasse 2 Birsfelden Basel-Landschaft 4127",
    "addr:housenumber":"2",
    "addr:postcode":"4127",
    "addr:street":"Ruehrbergstrasse",
    "iso:country":"CH",
    "sg:address":"R\u00fchrbergstrasse 2",
    "sg:city":"Birsfelden",
    "sg:orig_category":"Allgemeiner Hoch U Tiefbau Hoch U Tiefbau",
    "sg:phone":"+41 61 313 05 27",
    "sg:postcode":"4127",
    "sg:province":"Basel-Landschaft",
    "wof:name":"Huber Straub Ag, Zweigniederlassung Birsfelden",
    "wof:placetype":"venue"
},
  "geometry": {"coordinates":[7.634175,47.555],"type":"Point"}
}