{
  "type": "Feature",
  "properties": {
    "iso:country":"CH",
    "sg:address":"Kasernenstrasse 33",
    "sg:city":"B\u00fclach",
    "sg:orig_category":"Arztpraxen",
    "sg:phone":"+41 18607171",
    "sg:postcode":"8180",
    "sg:province":"Z\u00fcrich",
    "wof:name":"Dres Med. Nauer & De Duonni Aerzte F.allgem. Medizin Fmh",
    "wof:placetype":"venue"
},
  "geometry": {"coordinates":[8.536615,47.517605],"type":"Point"}
}