{
  "type": "Feature",
  "properties": {
    "iso:country":"CH",
    "sg:address":"Espenstrasse 24 9220 Bischofszell. Postfach",
    "sg:city":"Bischofszell",
    "sg:orig_category":"Detailhandel mit Brennstoffen U Heizmaterial Grosshandel mit festen Brennstoffen U Mineral\u00f6lerzeugni",
    "sg:phone":"+41 21 944 65 65",
    "sg:postcode":"9220",
    "sg:province":"Thurgau",
    "wof:name":"Lehmann-stein Sa Combustibles Et Transports",
    "wof:placetype":"venue"
},
  "geometry": {"coordinates":[6.856671,46.452991],"type":"Point"}
}