{
  "type": "Feature",
  "properties": {
    "iso:country":"CH",
    "sg:address":"Bahnhofstrasse 7b",
    "sg:city":"Derendingen",
    "sg:orig_category":"Herstellung von Chemiefasern",
    "sg:phone":"+41 32 682 36 31",
    "sg:postcode":"4552",
    "sg:province":"Solothurn",
    "wof:name":"Wyss Manfred Handelsagentur",
    "wof:placetype":"venue"
},
  "geometry": {"coordinates":[7.5812320709,47.2004203796],"type":"Point"}
}