{
  "type": "Feature",
  "properties": {
    "iso:country":"CH",
    "sg:address":"Hombrechtikerstrasse 1",
    "sg:city":"Jona",
    "sg:orig_category":"Finanzierungsinstitutionen",
    "sg:phone":"+41 55 210 45 00",
    "sg:postcode":"8645",
    "sg:province":"St. Gallen",
    "wof:name":"Kaiser Markus O.",
    "wof:placetype":"venue"
},
  "geometry": {"coordinates":[8.8196659088,47.240562439],"type":"Point"}
}