{
  "type": "Feature",
  "properties": {
    "addr:full":"Flurstrasse 14 Hagendorn Zug 6332",
    "addr:housenumber":"14",
    "addr:postcode":"6332",
    "addr:street":"Flurstrasse;Zug",
    "iso:country":"CH",
    "sg:address":"Flurstrasse 14",
    "sg:city":"Hagendorn",
    "sg:orig_category":"Datenverarbeitungsdienste Softwareentwicklung U beratung",
    "sg:phone":"+41 41 781 07 73",
    "sg:postcode":"6332",
    "sg:province":"Zug",
    "wof:name":"Urs Graf Edv-beratung",
    "wof:placetype":"venue"
},
  "geometry": {"coordinates":[8.430784,47.202023],"type":"Point"}
}