{
  "type": "Feature",
  "properties": {
    "iso:country":"CH",
    "sg:address":"Sch\u00f6neggstrasse 10",
    "sg:city":"Biel/bienne",
    "sg:orig_category":"Malerei Stukkateurgewerbe, Gipserei U Verputzerei",
    "sg:phone":"+41 32 322 48 42",
    "sg:postcode":"2503",
    "sg:province":"Bern",
    "wof:name":"Hugo Von K\u00e4nel Malerei-gipserei",
    "wof:placetype":"venue"
},
  "geometry": {"coordinates":[7.248524189,47.131477356],"type":"Point"}
}