{
  "type": "Feature",
  "properties": {
    "iso:country":"CH",
    "sg:address":"Boulevard De Grancy 17",
    "sg:city":"Lausanne",
    "sg:orig_category":"Reparatur von Schuhen U Lederwaren",
    "sg:phone":"+41 21 616 93 24",
    "sg:postcode":"1006",
    "sg:province":"Vaud",
    "wof:name":"Carmine Giglio Cordonnerie",
    "wof:placetype":"venue"
},
  "geometry": {"coordinates":[6.6297659874,46.5151596069],"type":"Point"}
}