{
  "type": "Feature",
  "properties": {
    "iso:country":"CH",
    "sg:address":"Herrenfeld",
    "sg:city":"Maienfeld",
    "sg:orig_category":"Sportvereine Turnen Vereine Damen",
    "sg:postcode":"7304",
    "sg:province":"Graubunden",
    "wof:name":"Frauenturnverein",
    "wof:placetype":"venue"
},
  "geometry": {"coordinates":[9.5322399139,47.0068626404],"type":"Point"}
}