{
  "type": "Feature",
  "properties": {
    "iso:country":"CH",
    "sg:address":"Sonnmattstrasse 11",
    "sg:city":"Rickenbach",
    "sg:classifiers":[
        {
            "category":"Banks & Credit Unions",
            "subcategory":"Financial Services",
            "type":"Services"
        }
    ],
    "sg:phone":"+41 32 631 22 64",
    "sg:postcode":"9532",
    "sg:province":"Thurgau",
    "sg:tags":[
        "cutting",
        "gear"
    ],
    "wof:name":"Brechb\u00fchl Zahnr\u00e4der Zahnr\u00e4derfabrik",
    "wof:placetype":"venue"
},
  "geometry": {"coordinates":[7.655933857,47.2298088074],"type":"Point"}
}