{
  "type": "Feature",
  "properties": {
    "iso:country":"CH",
    "sg:address":"Bahnhofstrasse 70",
    "sg:city":"Z\u00fcrich",
    "sg:orig_category":"Detailhandel mit B\u00fcchern",
    "sg:phone":"+41 12110444",
    "sg:postcode":"8001",
    "sg:province":"Z\u00fcrich",
    "wof:name":"Orell F\u00fcssli The Bookshop",
    "wof:placetype":"venue"
},
  "geometry": {"coordinates":[8.538519,47.373924],"type":"Point"}
}