{
  "type": "Feature",
  "properties": {
    "iso:country":"CH",
    "sg:address":"Alpenstrasse 5",
    "sg:city":"Switzerland",
    "sg:classifiers":[
        {
            "category":"Industrial Area",
            "type":"Public Place"
        }
    ],
    "sg:phone":"+41 26 492 75 55",
    "sg:postcode":"6",
    "sg:tags":[
        "large",
        "private"
    ],
    "wof:name":"Escor Casinos & Entertainment Sa",
    "wof:placetype":"venue"
},
  "geometry": {"coordinates":[7.1863389015,46.8516731262],"type":"Point"}
}