{
  "type": "Feature",
  "properties": {
    "iso:country":"CH",
    "sg:address":"Rte De Pampigny",
    "sg:city":"Apples",
    "sg:orig_category":"Herstellung von Schl\u00f6ssern U Beschl\u00e4gen",
    "sg:phone":"+41 21 800 99 00",
    "sg:postcode":"1143",
    "sg:province":"Vaud",
    "wof:name":"Matthey Et Cie Sa",
    "wof:placetype":"venue"
},
  "geometry": {"coordinates":[6.430847168,46.5538673401],"type":"Point"}
}