{
  "type": "Feature",
  "properties": {
    "iso:country":"CH",
    "sg:address":"Hirschengraben 17 6003 Luzern. Postfach",
    "sg:city":"Luzern",
    "sg:orig_category":"Polizei",
    "sg:phone":"+41 41 208 77 11",
    "sg:postcode":"6002",
    "sg:province":"Luzern",
    "wof:name":"Stadtverwaltung Luzern",
    "wof:placetype":"venue"
},
  "geometry": {"coordinates":[8.3044872284,47.0494613647],"type":"Point"}
}