{
  "type": "Feature",
  "properties": {
    "iso:country":"CH",
    "sg:address":"Breitenaustrasse 128",
    "sg:city":"Schaffhausen",
    "sg:orig_category":"Maler U Glasergewerbe Malerei",
    "sg:phone":"+41 52 625 94 91",
    "sg:postcode":"8200",
    "sg:province":"Schaffhausen",
    "wof:name":"Gallucci Malergesch\u00e4ft",
    "wof:placetype":"venue"
},
  "geometry": {"coordinates":[8.6227302551,47.7065010071],"type":"Point"}
}