{
  "type": "Feature",
  "properties": {
    "iso:country":"CH",
    "sg:address":"Bahnhofstrasse 90 8500 Frauenfeld. Postfach",
    "sg:city":"Frauenfeld",
    "sg:orig_category":"Wohnheime",
    "sg:postcode":"8500",
    "sg:province":"Thurgau",
    "wof:name":"Verein Wohnheim Adler Frauenfeld",
    "wof:placetype":"venue"
},
  "geometry": {"coordinates":[8.9012966156,47.5605926514],"type":"Point"}
}