{
  "type": "Feature",
  "properties": {
    "iso:country":"CH",
    "sg:address":"5728",
    "sg:city":"Gontenschwil",
    "sg:orig_category":"Primarschulen",
    "sg:phone":"+41 71 393 66 20",
    "sg:postcode":"5728",
    "sg:province":"Aargau",
    "wof:name":"Primarschule Schulhaus",
    "wof:placetype":"venue"
},
  "geometry": {"coordinates":[9.4897251129,47.2097892761],"type":"Point"}
}