{
  "type": "Feature",
  "properties": {
    "addr:full":"Rue Des Moulins 1 Yverdon-les-bains Vaud 1400",
    "addr:housenumber":"1",
    "addr:postcode":"1400",
    "addr:street":"Rue Des Moulins",
    "iso:country":"CH",
    "sg:address":"Rue Des Moulins 1",
    "sg:city":"Yverdon-les-bains",
    "sg:orig_category":"Detailhandel mit Brot, Back U S\u00fcsswaren",
    "sg:phone":"+41 24 425 17 95",
    "sg:postcode":"1400",
    "sg:province":"Vaud",
    "wof:name":"Rocco Sorge Boulangerie & P\u00e2tisserie",
    "wof:placetype":"venue"
},
  "geometry": {"coordinates":[6.637191,46.779156],"type":"Point"}
}