{
  "type": "Feature",
  "properties": {
    "iso:country":"CH",
    "sg:address":"Bahnhofplatz 11",
    "sg:city":"Affoltern",
    "sg:classifiers":[
        {
            "category":"Banks & Credit Unions",
            "subcategory":"Bank",
            "type":"Services"
        }
    ],
    "sg:phone":"+41 17615855",
    "sg:postcode":"8910",
    "sg:province":"Z\u00fcrich",
    "wof:name":"Sparkasse W\u00e4denswil-, Richterswil-knonaueramt",
    "wof:placetype":"venue"
},
  "geometry": {"coordinates":[8.447611,47.276302],"type":"Point"}
}