{
  "type": "Feature",
  "properties": {
    "iso:country":"CH",
    "sg:address":"Avenue Des Platanes 6 3960 Sierre Case Postale 564",
    "sg:city":"Sierre",
    "sg:orig_category":"Mechanische Werkst\u00e4tten Schlossereien",
    "sg:phone":"+41 27 455 05 53",
    "sg:postcode":"3960",
    "sg:province":"Valais",
    "wof:name":"Etablissements Torsa Sa",
    "wof:placetype":"venue"
},
  "geometry": {"coordinates":[7.5308117867,46.2904548645],"type":"Point"}
}