{
  "type": "Feature",
  "properties": {
    "iso:country":"CH",
    "sg:address":"4932",
    "sg:city":"Lotzwil",
    "sg:orig_category":"Wirtschaftsverb\u00e4nde Gewerbeverb\u00e4nde/-vereine",
    "sg:postcode":"4932",
    "sg:province":"Bern",
    "wof:name":"Handwerker-& Gewerbeverein",
    "wof:placetype":"venue"
},
  "geometry": {"coordinates":[7.7903900146,47.1904907227],"type":"Point"}
}