{
  "type": "Feature",
  "properties": {
    "iso:country":"CH",
    "sg:address":"Gandr\u00fctti 2",
    "sg:city":"Schattdorf",
    "sg:orig_category":"Sportvereine Turnen Damen",
    "sg:phone":"+41 41 870 52 35",
    "sg:postcode":"6467",
    "sg:province":"Uri",
    "wof:name":"Damenriege Schattdorf",
    "wof:placetype":"venue"
},
  "geometry": {"coordinates":[8.6472444534,46.8614196777],"type":"Point"}
}