{
  "type": "Feature",
  "properties": {
    "iso:country":"CH",
    "sg:address":"Br\u00fcschstrasse 39",
    "sg:city":"M\u00e4nnedorf",
    "sg:orig_category":"Softwareentwicklung U beratung",
    "sg:phone":"+41 17902888",
    "sg:postcode":"8708",
    "sg:province":"Z\u00fcrich",
    "wof:name":"Cbs Custom-made Business Solutions Gmbh",
    "wof:placetype":"venue"
},
  "geometry": {"coordinates":[8.7036037445,47.251247406],"type":"Point"}
}