{
  "type": "Feature",
  "properties": {
    "iso:country":"CH",
    "sg:address":"Lyssachstrasse 27",
    "sg:city":"Burgdorf",
    "sg:orig_category":"Herstellung von Brot U Backwaren Herstellung von Dauerbackwaren",
    "sg:phone":"+41 32 373 69 69",
    "sg:postcode":"3400",
    "sg:province":"Bern",
    "wof:name":"Jowa Ag Hausb\u00e4ckerei Center Br\u00fcgg",
    "wof:placetype":"venue"
},
  "geometry": {"coordinates":[7.2666568756,47.1203079224],"type":"Point"}
}