{
  "type": "Feature",
  "properties": {
    "iso:country":"CH",
    "sg:address":"St\u00e4mpflistrasse 35-37",
    "sg:city":"Zollikofen",
    "sg:orig_category":"Erschliessung von Grundst\u00fccken",
    "sg:phone":"+41 31 911 56 35",
    "sg:postcode":"3052",
    "sg:province":"Bern",
    "wof:name":"Wohnbaugenossenschaft Beau-site",
    "wof:placetype":"venue"
},
  "geometry": {"coordinates":[7.4548788071,46.9997215271],"type":"Point"}
}