{
  "type": "Feature",
  "properties": {
    "iso:country":"CH",
    "sg:address":"Tschessweg 16",
    "sg:city":"Grabs",
    "sg:orig_category":"Erschliessung von Grundst\u00fccken",
    "sg:postcode":"9472",
    "sg:province":"St. Gallen",
    "wof:name":"Wohneigentums-gen.sonnmatt",
    "wof:placetype":"venue"
},
  "geometry": {"coordinates":[9.444609642,47.1888313293],"type":"Point"}
}