{
  "type": "Feature",
  "properties": {
    "iso:country":"CH",
    "sg:address":"Sch\u00fctzenhaus 7204 Untervaz. Postfach",
    "sg:city":"Untervaz",
    "sg:orig_category":"Sportvereine Sch\u00fctzen",
    "sg:phone":"+41 81 322 44 85",
    "sg:postcode":"7204",
    "sg:province":"Graubunden",
    "wof:name":"Sch\u00fctzenverein",
    "wof:placetype":"venue"
},
  "geometry": {"coordinates":[9.5350799561,46.9275856018],"type":"Point"}
}