{
  "type": "Feature",
  "properties": {
    "iso:country":"CH",
    "sg:address":"St\u00e4deliweg 13",
    "sg:city":"Rorschacherberg",
    "sg:orig_category":"Vermietung U Verpachtung von eigenen Immobilien Vermittlung von Immobilien",
    "sg:phone":"+41 71 288 14 14",
    "sg:postcode":"9404",
    "sg:province":"St. Gallen",
    "wof:name":"Domino Immobilien Waldvogel Margrith",
    "wof:placetype":"venue"
},
  "geometry": {"coordinates":[9.4839487076,47.467830658],"type":"Point"}
}