{
  "type": "Feature",
  "properties": {
    "iso:country":"CH",
    "sg:address":"Bachstrasse 111 5000 Aarau. Postfach",
    "sg:city":"Aarau",
    "sg:orig_category":"Interessenvertretungen U sonstige Vereinigungen Organisationen der Wohlfahrtspflege",
    "sg:phone":"+41 62 837 50 70",
    "sg:postcode":"5001",
    "sg:province":"Aargau",
    "wof:name":"Pro Senectute Aargau",
    "wof:placetype":"venue"
},
  "geometry": {"coordinates":[8.0565500259,47.3868713379],"type":"Point"}
}