{
  "type": "Feature",
  "properties": {
    "iso:country":"CH",
    "sg:address":"Altweg 5",
    "sg:city":"Frauenfeld",
    "sg:classifiers":[
        {
            "category":"Restaurant",
            "type":"Food & Drink"
        }
    ],
    "sg:phone":"+41 52 720 17 32",
    "sg:postcode":"8500",
    "sg:province":"Thurgau",
    "wof:name":"Restaurant Pierhahne",
    "wof:placetype":"venue"
},
  "geometry": {"coordinates":[8.8940401077,47.554309845],"type":"Point"}
}