{
  "type": "Feature",
  "properties": {
    "iso:country":"CH",
    "sg:address":"Schartenstrasse 22 9445 Rebstein. Postfach",
    "sg:city":"Feusisberg",
    "sg:orig_category":"Gesundheitswesen",
    "sg:phone":"+41 71 891 40 04",
    "sg:postcode":"8835",
    "sg:province":"Schwyz",
    "wof:name":"Nueva Vista Praxis Elbe Ursula",
    "wof:placetype":"venue"
},
  "geometry": {"coordinates":[9.5878038406,47.4016151428],"type":"Point"}
}