{
  "type": "Feature",
  "properties": {
    "iso:country":"CH",
    "sg:address":"Klimmweg 36",
    "sg:city":"Dietlikon",
    "sg:orig_category":"Unclassifiable Establishments",
    "sg:postcode":"8305",
    "sg:province":"Z\u00fcrich",
    "wof:name":"Guido Beyeler, Gartenpflege Gmbh",
    "wof:placetype":"venue"
},
  "geometry": {"coordinates":[8.6206846237,47.4316329956],"type":"Point"}
}