{
  "type": "Feature",
  "properties": {
    "iso:country":"CH",
    "sg:address":"Bahnhofstrasse 16",
    "sg:city":"Kaiseraugst",
    "sg:orig_category":"Vermietung U Verpachtung von eigenen Immobilien",
    "sg:phone":"+41 61 811 25 56",
    "sg:postcode":"4303",
    "sg:province":"Aargau",
    "wof:name":"Buebechilch Ag",
    "wof:placetype":"venue"
},
  "geometry": {"coordinates":[7.7232408524,47.5378952026],"type":"Point"}
}