{
  "type": "Feature",
  "properties": {
    "iso:country":"CH",
    "sg:address":"Weidengasse 18",
    "sg:city":"Sch\u00f6nenwerd",
    "sg:orig_category":"Schlossereien Schmieden",
    "sg:phone":"+41 62 849 12 87",
    "sg:postcode":"5012",
    "sg:province":"Solothurn",
    "wof:name":"Peter Frey Schmiede & Schlosserei",
    "wof:placetype":"venue"
},
  "geometry": {"coordinates":[8.0020399094,47.3682556152],"type":"Point"}
}