{
  "type": "Feature",
  "properties": {
    "iso:country":"CH",
    "sg:address":"Rue Jean-calvin 12",
    "sg:city":"Gen\u00e8ve",
    "sg:orig_category":"Finanzierungsinstitutionen",
    "sg:phone":"+41 22 311 73 55",
    "sg:postcode":"1204",
    "sg:province":"Gen\u00e8ve",
    "wof:name":"Sefin-services Financiers Sa",
    "wof:placetype":"venue"
},
  "geometry": {"coordinates":[6.1468448639,46.2018547058],"type":"Point"}
}