{
  "type": "Feature",
  "properties": {
    "iso:country":"CH",
    "sg:address":"7144 Vella. Postfach 22",
    "sg:city":"Vella",
    "sg:orig_category":"Verwaltung der Rechtspflege, Gerichte",
    "sg:phone":"+41 81 931 31 48",
    "sg:postcode":"7144",
    "sg:province":"Graubunden",
    "wof:name":"Kreisamt Lugnez/ Lumnezia",
    "wof:placetype":"venue"
},
  "geometry": {"coordinates":[9.1733598709,46.7175865173],"type":"Point"}
}