{
  "type": "Feature",
  "properties": {
    "iso:country":"CH",
    "sg:address":"Mellingerstrasse 12",
    "sg:city":"Niederrohrdorf",
    "sg:orig_category":"Non-Classified Establishments",
    "sg:postcode":"5443",
    "sg:province":"Aargau",
    "wof:name":"Atelier A-b, Beatrice Meier-baumann",
    "wof:placetype":"venue"
},
  "geometry": {"coordinates":[8.300028801,47.424949646],"type":"Point"}
}