{
  "type": "Feature",
  "properties": {
    "iso:country":"CH",
    "sg:address":"La Schmetta 34 7078 Lenzerheide/lai. Postfach",
    "sg:city":"Lenzerheide/lai",
    "sg:orig_category":"Interessenvertretungen",
    "sg:postcode":"7078",
    "sg:province":"Graubunden",
    "wof:name":"Genossenschaft La Schmetta",
    "wof:placetype":"venue"
},
  "geometry": {"coordinates":[9.553565979,46.7192306519],"type":"Point"}
}