{
  "type": "Feature",
  "properties": {
    "iso:country":"CH",
    "sg:address":"Clamogne Chemin De 1170 Aubonne. Postfach",
    "sg:city":"Aubonne",
    "sg:orig_category":"Grosshandel mit sonstigen Halbwaren",
    "sg:phone":"+41 21 821 52 71",
    "sg:postcode":"1170",
    "sg:province":"Vaud",
    "wof:name":"Dufour Industries Sa",
    "wof:placetype":"venue"
},
  "geometry": {"coordinates":[6.391699791,46.4952468872],"type":"Point"}
}