{
  "type": "Feature",
  "properties": {
    "iso:country":"CH",
    "sg:address":"Route De L'etraz 62",
    "sg:city":"Nyon",
    "sg:orig_category":"Markt U Meinungsforschung",
    "sg:phone":"+41 79 402 13 56",
    "sg:postcode":"1260",
    "sg:province":"Vaud",
    "wof:name":"Jods Frei Hannes",
    "wof:placetype":"venue"
},
  "geometry": {"coordinates":[8.9534664154,47.2439231873],"type":"Point"}
}