{
  "type": "Feature",
  "properties": {
    "iso:country":"CH",
    "sg:address":"Vogelsangstrasse 52",
    "sg:city":"Z\u00fcrich",
    "sg:orig_category":"Gesundheitswesen",
    "sg:postcode":"8006",
    "sg:province":"Z\u00fcrich",
    "wof:name":"Candit.com Gmbh",
    "wof:placetype":"venue"
},
  "geometry": {"coordinates":[8.5484666824,47.3841552734],"type":"Point"}
}