{
  "type": "Feature",
  "properties": {
    "iso:country":"CH",
    "sg:address":"Rachholtern 66b",
    "sg:city":"Fahrni",
    "sg:classifiers":[
        {
            "category":"Banks & Credit Unions",
            "subcategory":"Bank",
            "type":"Services"
        }
    ],
    "sg:phone":"+41 33 439 23 92",
    "sg:postcode":"3617",
    "sg:province":"Bern",
    "wof:name":"Raiffeisenbank Fahrni-teuffenthal",
    "wof:placetype":"venue"
},
  "geometry": {"coordinates":[7.668769,46.796879],"type":"Point"}
}