{
  "type": "Feature",
  "properties": {
    "iso:country":"CH",
    "sg:address":"Dorfstrasse 15",
    "sg:city":"Niederbipp",
    "sg:orig_category":"Interessenvertretungen",
    "sg:postcode":"4704",
    "sg:province":"Bern",
    "wof:name":"Stiftung R\u00f6hrenhaus In B\u00e4riswil",
    "wof:placetype":"venue"
},
  "geometry": {"coordinates":[7.5296797752,47.0157699585],"type":"Point"}
}