{
  "type": "Feature",
  "properties": {
    "iso:country":"CH",
    "sg:address":"Zelglistrasse 13",
    "sg:city":"Br\u00fctten",
    "sg:orig_category":"Unternehmensberatung",
    "sg:phone":"+41 26 672 16 50",
    "sg:postcode":"8311",
    "sg:province":"Z\u00fcrich",
    "wof:name":"B\u00fcrki Jacqueline Betriebsorganisation",
    "wof:placetype":"venue"
},
  "geometry": {"coordinates":[7.1084527969,46.9252319336],"type":"Point"}
}