{
  "type": "Feature",
  "properties": {
    "iso:country":"CH",
    "sg:address":"Bahnhofstrasse 7 7000 Chur. Postfach",
    "sg:city":"Chur",
    "sg:orig_category":"Sonstiges Versicherungsgewerbe",
    "sg:postcode":"7000",
    "sg:province":"Graubunden",
    "wof:name":"Helvetia Versicherungen, Generalagentur Heinz N\u00e4f",
    "wof:placetype":"venue"
},
  "geometry": {"coordinates":[9.5306978226,46.8528327942],"type":"Point"}
}