{
  "type": "Feature",
  "properties": {
    "addr:full":"R\u00fctenenstrasse 88 Beckenried Nidwalden 6375",
    "addr:housenumber":"88",
    "addr:postcode":"6375",
    "addr:street":"Ruetenenstrasse",
    "iso:country":"CH",
    "sg:address":"R\u00fctenenstrasse 88",
    "sg:city":"Beckenried",
    "sg:classifiers":[
        {
            "category":"Banks & Credit Unions",
            "subcategory":"Investment Brokerage",
            "type":"Services"
        }
    ],
    "sg:phone":"+41 41 620 63 93",
    "sg:postcode":"6375",
    "sg:province":"Nidwalden",
    "sg:tags":[
        "shutter",
        "roller",
        "accessory"
    ],
    "wof:name":"Huggel Storen",
    "wof:placetype":"venue"
},
  "geometry": {"coordinates":[8.492571,46.962051],"type":"Point"}
}