{
  "type": "Feature",
  "properties": {
    "iso:country":"CH",
    "sg:address":"Aproz 1994 Aproz. Postfach",
    "sg:city":"Aproz",
    "sg:orig_category":"Dachdeckerei Sanit\u00e4r, Heizungs U L\u00fcftungsinstallation",
    "sg:phone":"+41 27 398 53 16",
    "sg:postcode":"1994",
    "sg:province":"Valais",
    "wof:name":"Pitteloud, Fumeaux & Fils S\u00e0rl Entrepr. De Chauffage, D'install. Sanitaires Etc",
    "wof:placetype":"venue"
},
  "geometry": {"coordinates":[7.315196,46.207649],"type":"Point"}
}