{
  "type": "Feature",
  "properties": {
    "iso:country":"CH",
    "sg:address":"Falaises Route Des 7 2000 Neuenburg. Postfach",
    "sg:city":"Neuenburg",
    "sg:orig_category":"Allgemeiner Hoch U Tiefbau",
    "sg:postcode":"2000",
    "sg:province":"Neuch\u00e2tel",
    "wof:name":"Zschokke Construction Sa",
    "wof:placetype":"venue"
},
  "geometry": {"coordinates":[6.931085,46.990334],"type":"Point"}
}