{
  "type": "Feature",
  "properties": {
    "addr:full":"Untere Bahnhofstrasse Amriswil Thurgau 8580",
    "addr:postcode":"8580",
    "addr:street":"Untere Bahnhofstrasse",
    "iso:country":"CH",
    "sg:address":"Untere Bahnhofstrasse",
    "sg:city":"Amriswil",
    "sg:orig_category":"Architektur U Ingenieurb\u00fcros",
    "sg:postcode":"8580",
    "sg:province":"Thurgau",
    "wof:name":"Ingenieurb\u00fcro Senn Tiefbau",
    "wof:placetype":"venue"
},
  "geometry": {"coordinates":[8.291582,47.486916],"type":"Point"}
}