{
  "type": "Feature",
  "properties": {
    "iso:country":"CH",
    "sg:address":"Allmendstrasse 6",
    "sg:city":"Udligenswil",
    "sg:orig_category":"Grosshandel mit Holz U Bauelementen aus Holz Herstellung von sonstigen Holzwaren",
    "sg:phone":"+41 22 307 85 55",
    "sg:postcode":"6044",
    "sg:province":"Luzern",
    "wof:name":"May Et Cie Sa",
    "wof:placetype":"venue"
},
  "geometry": {"coordinates":[6.1328430176,46.1793212891],"type":"Point"}
}