{
  "type": "Feature",
  "properties": {
    "iso:country":"CH",
    "sg:address":"Perron Rue Du 8 1196 Gland. Postfach",
    "sg:city":"Gland",
    "sg:orig_category":"Non-Classified Establishments",
    "sg:postcode":"1196",
    "sg:province":"Vaud",
    "wof:name":"Mjp Mirra Jardinier-paysagiste S\u00e0rl",
    "wof:placetype":"venue"
},
  "geometry": {"coordinates":[6.2723469734,46.419757843],"type":"Point"}
}