{
  "type": "Feature",
  "properties": {
    "iso:country":"CH",
    "sg:address":"Unterstrasse 8",
    "sg:city":"Herzogenbuchsee",
    "sg:orig_category":"Unclassifiable Establishments",
    "sg:postcode":"3360",
    "sg:province":"Bern",
    "wof:name":"Maxime's Hot Slicks",
    "wof:placetype":"venue"
},
  "geometry": {"coordinates":[9.2693748474,47.4148902893],"type":"Point"}
}