{
  "type": "Feature",
  "properties": {
    "iso:country":"CH",
    "sg:address":"Bahnhofstrasse 15 6003 Luzern. Postfach",
    "sg:city":"Luzern",
    "sg:orig_category":"Verwaltung der Rechtspflege, Gerichte",
    "sg:phone":"+41 71 222 03 03",
    "sg:postcode":"6002",
    "sg:province":"Luzern",
    "wof:name":"Kant. Kassationsgericht",
    "wof:placetype":"venue"
},
  "geometry": {"coordinates":[9.3763303757,47.4260559082],"type":"Point"}
}