{
  "type": "Feature",
  "properties": {
    "addr:full":"Universit\u00e4tstrasse 116 Z\u00fcrich Z\u00fcrich 8006",
    "addr:housenumber":"116",
    "addr:postcode":"8006",
    "addr:street":"Universitaetstrasse",
    "iso:country":"CH",
    "sg:address":"Universit\u00e4tstrasse 116",
    "sg:city":"Z\u00fcrich",
    "sg:orig_category":"Chemische Reinigung",
    "sg:phone":"+41 55 210 72 17",
    "sg:postcode":"8006",
    "sg:province":"Z\u00fcrich",
    "wof:name":"Werner Wilhelm Textilreinigung Perfekt",
    "wof:placetype":"venue"
},
  "geometry": {"coordinates":[8.815683,47.226856],"type":"Point"}
}