{
  "type": "Feature",
  "properties": {
    "iso:country":"CH",
    "sg:address":"Geisshaldenweg 21",
    "sg:city":"Schaffhausen",
    "sg:orig_category":"Detailhandel mit Ton U Bildtr\u00e4gern Detailhandel mit elektrischen Haushalts-,Radio U Fernsehger\u00e4ten s",
    "sg:phone":"+41 52 625 99 65",
    "sg:postcode":"8200",
    "sg:province":"Schaffhausen",
    "wof:name":"Grammoton",
    "wof:placetype":"venue"
},
  "geometry": {"coordinates":[8.6381416321,47.7094116211],"type":"Point"}
}