{
  "type": "Feature",
  "properties": {
    "iso:country":"CH",
    "sg:address":"Solothurnerstrasse 231",
    "sg:city":"Olten",
    "sg:orig_category":"Allgemeinbildende weiterf\u00fchrende Schulen",
    "sg:phone":"+41 62 212 04 02",
    "sg:postcode":"4600",
    "sg:province":"Solothurn",
    "wof:name":"Fsg Freie Schule F\u00fcr Gestaltung Gmbh",
    "wof:placetype":"venue"
},
  "geometry": {"coordinates":[7.890064,47.348141],"type":"Point"}
}