{
  "type": "Feature",
  "properties": {
    "iso:country":"CH",
    "sg:city":"Zimmerwald",
    "sg:classifiers":[
        {
            "category":"Banks & Credit Unions",
            "subcategory":"Bank",
            "type":"Services"
        }
    ],
    "sg:postcode":"3086",
    "sg:province":"Bern",
    "wof:name":"Bb Bank Belp",
    "wof:placetype":"venue"
},
  "geometry": {"coordinates":[7.498641,46.890717],"type":"Point"}
}