{
  "type": "Feature",
  "properties": {
    "iso:country":"CH",
    "sg:address":"8942 Oberrieden. Postfach 5",
    "sg:city":"Oberrieden",
    "sg:orig_category":"Sportvereine Ballsport Fussball Vereine Damen",
    "sg:phone":"+41 17203993",
    "sg:postcode":"8942",
    "sg:province":"Z\u00fcrich",
    "wof:name":"Fc Oberrieden Abt.damen",
    "wof:placetype":"venue"
},
  "geometry": {"coordinates":[8.5756807327,47.2782669067],"type":"Point"}
}