{
  "type": "Feature",
  "properties": {
    "iso:country":"CH",
    "sg:address":"Via Valegia 12",
    "sg:city":"Montagnola",
    "sg:orig_category":"Allgemeiner Hochbau Strassenbau",
    "sg:phone":"+41 91 994 65 34",
    "sg:postcode":"6926",
    "sg:province":"Ticino",
    "wof:name":"Flavio Riva Sa",
    "wof:placetype":"venue"
},
  "geometry": {"coordinates":[8.918718,45.987034],"type":"Point"}
}