{
  "type": "Feature",
  "properties": {
    "iso:country":"CH",
    "sg:address":"Schachenhof 4",
    "sg:city":"Littau",
    "sg:classifiers":[
        {
            "category":"Professional",
            "subcategory":"Engineering",
            "type":"Services"
        }
    ],
    "sg:phone":"+41 21 633 26 44",
    "sg:postcode":"6014",
    "sg:province":"Luzern",
    "sg:tags":[
        "machine",
        "-",
        "mechanical"
    ],
    "wof:name":"Mayer Et Soutter Sa",
    "wof:placetype":"venue"
},
  "geometry": {"coordinates":[6.6060152054,46.5232925415],"type":"Point"}
}