{
  "type": "Feature",
  "properties": {
    "iso:country":"CH",
    "sg:address":"Stettmerstrasse 50 8207 Schaffhausen. Postfach",
    "sg:city":"Schaffhausen",
    "sg:orig_category":"Herstellung von elektrischen Haushaltsger\u00e4ten",
    "sg:phone":"+41 52 643 39 00",
    "sg:postcode":"8207",
    "sg:province":"Schaffhausen",
    "wof:name":"Restola Ag",
    "wof:placetype":"venue"
},
  "geometry": {"coordinates":[8.6562004089,47.7232246399],"type":"Point"}
}