{
  "type": "Feature",
  "properties": {
    "iso:country":"CH",
    "sg:address":"Degersheimerstrasse 66",
    "sg:city":"Herisau",
    "sg:orig_category":"Sportvereine Ballsport Handball",
    "sg:phone":"+41 78 607 91 04",
    "sg:postcode":"9100",
    "sg:province":"Appenzell Ausserrhoden",
    "wof:name":"Hc Herisau",
    "wof:placetype":"venue"
},
  "geometry": {"coordinates":[9.2649116516,47.3879623413],"type":"Point"}
}