{
  "type": "Feature",
  "properties": {
    "iso:country":"CH",
    "sg:address":"Gemeindekanzlei",
    "sg:city":"Grosswangen",
    "sg:orig_category":"Interessenvertretungen",
    "sg:postcode":"6022",
    "sg:province":"Luzern",
    "wof:name":"Stiftung Zur F\u00f6rderung Und Unterst\u00fctzung Des Betagtenheimes Grosswangen",
    "wof:placetype":"venue"
},
  "geometry": {"coordinates":[8.0485649109,47.1336936951],"type":"Point"}
}