{
  "type": "Feature",
  "properties": {
    "iso:country":"CH",
    "sg:address":"Underem Gfell 20",
    "sg:city":"Meiringen",
    "sg:orig_category":"Fachdetailhandel in Verkaufsr\u00e4umen",
    "sg:postcode":"3860",
    "sg:province":"Bern",
    "wof:name":"Segel Und Motorbootfahrschule Pegasus, Gsteiger Bruno",
    "wof:placetype":"venue"
},
  "geometry": {"coordinates":[8.1942558289,46.7276687622],"type":"Point"}
}