{
  "type": "Feature",
  "properties": {
    "iso:country":"CH",
    "sg:address":"Chemin De La Musardi\u00e8re",
    "sg:city":"Tolochenaz",
    "sg:orig_category":"Herstellung von sonstigen Waren aus Papier, Karton U Pappe",
    "sg:postcode":"1131",
    "sg:province":"Vaud",
    "wof:name":"Landgraf Sa",
    "wof:placetype":"venue"
},
  "geometry": {"coordinates":[6.478099823,46.509059906],"type":"Point"}
}