{
  "type": "Feature",
  "properties": {
    "iso:country":"CH",
    "sg:address":"Rehburgstrasse 3",
    "sg:city":"St.gallen",
    "sg:orig_category":"Architektur U Ingenieurb\u00fcros",
    "sg:phone":"+41 71 245 61 71",
    "sg:postcode":"9000",
    "sg:province":"St. Gallen",
    "wof:name":"Marzari P. Consulting",
    "wof:placetype":"venue"
},
  "geometry": {"coordinates":[9.397169,47.431335],"type":"Point"}
}