{
  "type": "Feature",
  "properties": {
    "iso:country":"CH",
    "sg:address":"B\u00e4chis 15",
    "sg:city":"Hinterforst",
    "sg:orig_category":"Sportvereine Ballsport Tennis",
    "sg:phone":"+41 71 755 19 13",
    "sg:postcode":"9452",
    "sg:province":"St. Gallen",
    "wof:name":"Tc Altst\u00e4tten",
    "wof:placetype":"venue"
},
  "geometry": {"coordinates":[9.5319480896,47.3635826111],"type":"Point"}
}