{
  "type": "Feature",
  "properties": {
    "iso:country":"CH",
    "sg:address":"Pilatusstrasse 46a",
    "sg:city":"Luzern",
    "sg:orig_category":"Non-Classified Establishments",
    "sg:phone":"+41 41 240 48 48",
    "sg:postcode":"6003",
    "sg:province":"Luzern",
    "wof:name":"Kaya's Take-away-imbiss",
    "wof:placetype":"venue"
},
  "geometry": {"coordinates":[8.3031339645,47.0475654602],"type":"Point"}
}