{
  "type": "Feature",
  "properties": {
    "iso:country":"CH",
    "sg:address":"Krieg Avenue 5 1208 Gen\u00e8ve. Postfach",
    "sg:city":"Gen\u00e8ve",
    "sg:orig_category":"W\u00e4scherei U chemische Reinigung",
    "sg:postcode":"1208",
    "sg:province":"Gen\u00e8ve",
    "wof:name":"Teppich-atelier Rellstab Astrid",
    "wof:placetype":"venue"
},
  "geometry": {"coordinates":[8.455909729,47.3601608276],"type":"Point"}
}