{
  "type": "Feature",
  "properties": {
    "iso:country":"CH",
    "sg:address":"Les Riaux 16",
    "sg:city":"Prez-vers-nor\u00e9az",
    "sg:orig_category":"Architektur U Ingenieurb\u00fcros",
    "sg:phone":"+41 26 470 08 50",
    "sg:postcode":"1746",
    "sg:province":"Fribourg",
    "wof:name":"Sallin Jean-marc",
    "wof:placetype":"venue"
},
  "geometry": {"coordinates":[7.008389,46.781857],"type":"Point"}
}