{
  "type": "Feature",
  "properties": {
    "iso:country":"CH",
    "sg:address":"Via Cantonale",
    "sg:city":"Rivera",
    "sg:orig_category":"Einzelhandel mit Automobilteilen U Zubeh\u00f6r Instandhaltung U Reparatur von Automobilen",
    "sg:phone":"+41 91 946 12 30",
    "sg:postcode":"6802",
    "sg:province":"Ticino",
    "wof:name":"Gottardi E Co. Garage Rivera",
    "wof:placetype":"venue"
},
  "geometry": {"coordinates":[8.9266147614,46.121055603],"type":"Point"}
}