{
  "type": "Feature",
  "properties": {
    "iso:country":"CH",
    "sg:address":"Bergstrasse 4",
    "sg:city":"St\u00e4fa",
    "sg:orig_category":"Wirtschafts- and Arbeitgeberverb\u00e4nde",
    "sg:phone":"+41 55 644 35 14",
    "sg:postcode":"8712",
    "sg:province":"Z\u00fcrich",
    "wof:name":"Spenglermeister-& Installat.- Verband,herrn Amo Rohr",
    "wof:placetype":"venue"
},
  "geometry": {"coordinates":[9.065290451,46.9961395264],"type":"Point"}
}