{
  "type": "Feature",
  "properties": {
    "iso:country":"CH",
    "sg:address":"Im R\u00f6tel 10a",
    "sg:city":"Zug",
    "sg:orig_category":"Unclassifiable Establishments",
    "sg:phone":"+41 41 727 80 56",
    "sg:postcode":"6300",
    "sg:province":"Zug",
    "wof:name":"Sea Arrow Ag",
    "wof:placetype":"venue"
},
  "geometry": {"coordinates":[8.5248756409,47.165309906],"type":"Point"}
}