{
  "type": "Feature",
  "properties": {
    "addr:full":"1450 Ste-croix Vaud 1450",
    "addr:postcode":"1450 ste-croix;1450",
    "iso:country":"CH",
    "sg:address":"1450",
    "sg:city":"Ste-croix",
    "sg:orig_category":"Allgemeiner Hoch U Tiefbau",
    "sg:postcode":"1450",
    "sg:province":"Vaud",
    "wof:name":"Architecture Et Urbanisme Les Amis Du Trait Sa, Succursale De Vouvry",
    "wof:placetype":"venue"
},
  "geometry": {"coordinates":[6.50105,46.824211],"type":"Point"}
}