{
  "type": "Feature",
  "properties": {
    "iso:country":"CH",
    "sg:address":"Birmannsgasse 24 4055 Basel. Postfach",
    "sg:city":"Basel",
    "sg:orig_category":"Sonstiger Grosshandel",
    "sg:phone":"+41 61 271 04 72",
    "sg:postcode":"4051",
    "sg:province":"Basel-Stadt",
    "wof:name":"Gesundheit Waren; Imp., Exp., Grosshandel",
    "wof:placetype":"venue"
},
  "geometry": {"coordinates":[7.5769610405,47.5576934814],"type":"Point"}
}