{
  "type": "Feature",
  "properties": {
    "iso:country":"CH",
    "sg:address":"Loreto Via 6",
    "sg:city":"Lugano",
    "sg:orig_category":"Dienstleistungen von Beteiligungsgesellschaften",
    "sg:phone":"+41 71 333 44 13",
    "sg:postcode":"6900",
    "sg:province":"Ticino",
    "wof:name":"Fr\u00fch Verwaltungs Ag",
    "wof:placetype":"venue"
},
  "geometry": {"coordinates":[9.3621683121,47.3862419128],"type":"Point"}
}