{
  "type": "Feature",
  "properties": {
    "addr:full":"Hinterhaldenstrasse 1 Villnachern Aargau 5213",
    "addr:housenumber":"1",
    "addr:postcode":"5213",
    "addr:street":"Hinterhaldenstrasse",
    "iso:country":"CH",
    "sg:address":"Hinterhaldenstrasse 1",
    "sg:city":"Villnachern",
    "sg:classifiers":[
        {
            "category":"Banks & Credit Unions",
            "subcategory":"Bank",
            "type":"Services"
        }
    ],
    "sg:phone":"+41 4156417733",
    "sg:postcode":"5213",
    "sg:province":"Aargau",
    "wof:name":"Aargauische Kantonalbank",
    "wof:placetype":"venue"
},
  "geometry": {"coordinates":[8.16325,47.473148],"type":"Point"}
}