{
  "type": "Feature",
  "properties": {
    "iso:country":"CH",
    "sg:address":"Gotthardstrasse 6415 Arth. Postfach",
    "sg:city":"Lauerz",
    "sg:orig_category":"RESTAURANTS: TEA-ROOMS",
    "sg:postcode":"6424",
    "sg:province":"Schwyz",
    "wof:name":"Steiner-herger Ren\u00e9",
    "wof:placetype":"venue"
},
  "geometry": {"coordinates":[8.5258178711,47.0612106323],"type":"Point"}
}