{
  "type": "Feature",
  "properties": {
    "addr:full":"Talackerstrasse 70 Glattbrugg Z\u00fcrich 8152",
    "addr:housenumber":"70",
    "addr:postcode":"8152",
    "addr:street":"Talackerstrasse",
    "iso:country":"CH",
    "sg:address":"Talackerstrasse 70",
    "sg:city":"Glattbrugg",
    "sg:orig_category":"Aktivit\u00e4ten der Krankenschwestern U Hebammen, Hauspflege Gesundheitswesen",
    "sg:phone":"+41 19327553",
    "sg:postcode":"8152",
    "sg:province":"Z\u00fcrich",
    "wof:name":"Spitex-verein Wetzikon-seegr\u00e4ben",
    "wof:placetype":"venue"
},
  "geometry": {"coordinates":[8.796802,47.320812],"type":"Point"}
}