{
  "type": "Feature",
  "properties": {
    "iso:country":"CH",
    "sg:address":"Zona Industriale 3",
    "sg:city":"Mezzovico",
    "sg:orig_category":"Herstellung von Kunststoffwaren Sonstiges Textilgewerbe",
    "sg:phone":"+41 71 923 21 44",
    "sg:postcode":"6805",
    "sg:province":"Ticino",
    "wof:name":"Faser-plast Ag",
    "wof:placetype":"venue"
},
  "geometry": {"coordinates":[-77.13302612299999,40.4769287109],"type":"Point"}
}