{
  "type": "Feature",
  "properties": {
    "iso:country":"CH",
    "sg:address":"Tessenbergstrasse 28 2505 Biel/bienne. Postfach",
    "sg:city":"Biel/bienne",
    "sg:orig_category":"Non-Classified Establishments",
    "sg:postcode":"2505",
    "sg:province":"Bern",
    "wof:name":"Danz Ce Beteiligungen An Gesellschaften Usw",
    "wof:placetype":"venue"
},
  "geometry": {"coordinates":[7.2161970139,47.1290550232],"type":"Point"}
}