{
  "type": "Feature",
  "properties": {
    "iso:country":"CH",
    "sg:address":"Engermatte",
    "sg:city":"Kleindietwil",
    "sg:orig_category":"Gartenbau",
    "sg:phone":"+41 79 414 05 04",
    "sg:postcode":"4936",
    "sg:province":"Bern",
    "wof:name":"Wolf Gartenbau",
    "wof:placetype":"venue"
},
  "geometry": {"coordinates":[7.7884631157,47.1461105347],"type":"Point"}
}