{
  "type": "Feature",
  "properties": {
    "iso:country":"CH",
    "sg:address":"Mittlere Strasse 22",
    "sg:city":"Thun",
    "sg:orig_category":"Detailhandel mit Sportartikeln",
    "sg:phone":"+41 33 223 32 83",
    "sg:postcode":"3600",
    "sg:province":"Bern",
    "wof:name":"Reitsport Thun Hans Schwarz",
    "wof:placetype":"venue"
},
  "geometry": {"coordinates":[7.6214818954,46.7570228577],"type":"Point"}
}