{
  "type": "Feature",
  "properties": {
    "iso:country":"CH",
    "sg:address":"R\u00fcdenplatz 2",
    "sg:city":"Z\u00fcrich",
    "sg:orig_category":"Gold- and Silberschmuck Detailhandel",
    "sg:phone":"+41 12617972",
    "sg:postcode":"8001",
    "sg:province":"Z\u00fcrich",
    "wof:name":"Philippe Pfeiffer Gold-& Silberschmiede",
    "wof:placetype":"venue"
},
  "geometry": {"coordinates":[8.5432634354,47.3710975647],"type":"Point"}
}