{
  "type": "Feature",
  "properties": {
    "iso:country":"CH",
    "sg:address":"Route De Lullier 62 1254 Jussy. Postfach",
    "sg:city":"Jussy",
    "sg:orig_category":"Non-Classified Establishments",
    "sg:postcode":"1254",
    "sg:province":"Gen\u00e8ve",
    "wof:name":"Au Petit Jardinier, Ruiz",
    "wof:placetype":"venue"
},
  "geometry": {"coordinates":[6.2628102303,46.232421875],"type":"Point"}
}