{
  "type": "Feature",
  "properties": {
    "iso:country":"CH",
    "sg:address":"Oberdorfstrasse 68 9100 Herisau. Postfach",
    "sg:city":"Herisau",
    "sg:orig_category":"Pensionskassen",
    "sg:postcode":"9100",
    "sg:province":"Appenzell Ausserrhoden",
    "wof:name":"Personalvorsorge-stiftung Providus",
    "wof:placetype":"venue"
},
  "geometry": {"coordinates":[9.3945455551,47.4299163818],"type":"Point"}
}