{
  "type": "Feature",
  "properties": {
    "iso:country":"CH",
    "sg:address":"Au Cholaic Bluche",
    "sg:city":"Randogne",
    "sg:orig_category":"Architekturb\u00fcros",
    "sg:phone":"+41 27 481 40 31",
    "sg:postcode":"3975",
    "sg:province":"Valais",
    "wof:name":"Claude Salamin Bureau D'architecture",
    "wof:placetype":"venue"
},
  "geometry": {"coordinates":[7.510419,46.31184],"type":"Point"}
}