{
  "type": "Feature",
  "properties": {
    "iso:country":"CH",
    "sg:address":"Ch\u00e2tillon 15",
    "sg:city":"Pr\u00eales",
    "sg:orig_category":"Sonstige pers\u00f6nliche Dienstleistungen",
    "sg:postcode":"2515",
    "sg:province":"Bern",
    "wof:name":"Multi Gs Fratianni",
    "wof:placetype":"venue"
},
  "geometry": {"coordinates":[7.1248269081,47.1008682251],"type":"Point"}
}