{
  "type": "Feature",
  "properties": {
    "iso:country":"CH",
    "sg:address":"1562 Corcelles-payerne Case Postale 44",
    "sg:city":"Corcelles-payerne",
    "sg:orig_category":"Sportvereine Ballsport Fussball",
    "sg:phone":"+41 32 731 95 91",
    "sg:postcode":"1562",
    "sg:province":"Vaud",
    "wof:name":"Fc Corcelles-cormondr\u00e8che",
    "wof:placetype":"venue"
},
  "geometry": {"coordinates":[6.8612399101,46.98828125],"type":"Point"}
}