{
  "type": "Feature",
  "properties": {
    "iso:country":"CH",
    "sg:address":"Industriestrasse 22",
    "sg:city":"Zug",
    "sg:orig_category":"Fernmeldedienste",
    "sg:postcode":"6300",
    "sg:province":"Zug",
    "wof:name":"Global Metro Networks Switzerland Gmbh",
    "wof:placetype":"venue"
},
  "geometry": {"coordinates":[8.5192642212,47.1744651794],"type":"Point"}
}