{
  "type": "Feature",
  "properties": {
    "iso:country":"CH",
    "sg:address":"Hauptstrasse 25",
    "sg:city":"Bonaduz",
    "sg:orig_category":"Architektur U Ingenieurb\u00fcros",
    "sg:postcode":"7402",
    "sg:province":"Graubunden",
    "wof:name":"Perez-weber Esther",
    "wof:placetype":"venue"
},
  "geometry": {"coordinates":[9.400116,46.810867],"type":"Point"}
}