{
  "type": "Feature",
  "properties": {
    "iso:country":"CH",
    "sg:address":"Route De Chany",
    "sg:city":"Domdidier",
    "sg:orig_category":"Sportvereine Ballsport Tischtennis",
    "sg:phone":"+41 32 853 54 62",
    "sg:postcode":"1564",
    "sg:province":"Fribourg",
    "wof:name":"Ctt Ensa",
    "wof:placetype":"venue"
},
  "geometry": {"coordinates":[6.9260702133,47.0305709839],"type":"Point"}
}