{
  "type": "Feature",
  "properties": {
    "iso:country":"CH",
    "sg:address":"Rue De La Fusion 2 1920 Martigny. Postfach",
    "sg:city":"Martigny",
    "sg:orig_category":"Erbringung von Dienstleistungen f\u00fcr Unternehmen",
    "sg:postcode":"1920",
    "sg:province":"Valais",
    "wof:name":"Malveiro Lopes Francisca",
    "wof:placetype":"venue"
},
  "geometry": {"coordinates":[7.0711679459,46.1029853821],"type":"Point"}
}