{
  "type": "Feature",
  "properties": {
    "iso:country":"CH",
    "sg:address":"Friedlisbergstrasse 234",
    "sg:city":"Rudolfstetten",
    "sg:orig_category":"Mechanik Mechanische Werkst\u00e4tten",
    "sg:phone":"+41 56 631 65 48",
    "sg:postcode":"8964",
    "sg:province":"Aargau",
    "wof:name":"Josef Brem Mechanische Werkstatt",
    "wof:placetype":"venue"
},
  "geometry": {"coordinates":[8.3816795349,47.3669395447],"type":"Point"}
}