{
  "type": "Feature",
  "properties": {
    "iso:country":"CH",
    "sg:address":"Route Aloys-fauquez 21",
    "sg:city":"Lausanne",
    "sg:classifiers":[
        {
            "category":"Education",
            "subcategory":"Library",
            "type":"Public Place"
        }
    ],
    "sg:phone":"+41 21 647 34 97",
    "sg:postcode":"1018",
    "sg:province":"Vaud",
    "sg:tags":[
        "u",
        "bibliotheken",
        "archive"
    ],
    "wof:name":"Biblioth\u00e8que De La Paroisse De Bellevaux",
    "wof:placetype":"venue"
},
  "geometry": {"coordinates":[6.632859,46.532932],"type":"Point"}
}