{
  "type": "Feature",
  "properties": {
    "iso:country":"CH",
    "sg:address":"Oerlikonerstrasse 88",
    "sg:city":"Z\u00fcrich",
    "sg:orig_category":"Allgemeiner Hoch U Tiefbau",
    "sg:phone":"+41 13151717",
    "sg:postcode":"8057",
    "sg:province":"Z\u00fcrich",
    "wof:name":"Sks Ingenieure Ag",
    "wof:placetype":"venue"
},
  "geometry": {"coordinates":[8.546589,47.405033],"type":"Point"}
}