{
  "type": "Feature",
  "properties": {
    "iso:country":"CH",
    "sg:address":"Paradieshofstrasse 120",
    "sg:city":"Basel",
    "sg:orig_category":"Unclassifiable Establishments",
    "sg:phone":"+41 61 302 46 49",
    "sg:postcode":"4054",
    "sg:province":"Basel-Stadt",
    "wof:name":"Atelier99, Gerber Helena, Atelier F\u00fcr Kommunikation, Bildung Und Gesundheit",
    "wof:placetype":"venue"
},
  "geometry": {"coordinates":[7.5588021278,47.5476303101],"type":"Point"}
}