{
  "type": "Feature",
  "properties": {
    "iso:country":"CH",
    "sg:address":"Girabodaw\u00e4g 36",
    "sg:city":"Churwalden",
    "sg:orig_category":"Dienstleistungen in der Forstwirtschaft Erdbewegungsarbeiten",
    "sg:phone":"+41 81 382 23 74",
    "sg:postcode":"7075",
    "sg:province":"Graubunden",
    "wof:name":"Werner W\u00e4spi Baggerarbeiten",
    "wof:placetype":"venue"
},
  "geometry": {"coordinates":[9.5414457321,46.7769889832],"type":"Point"}
}