{
  "type": "Feature",
  "properties": {
    "iso:country":"CH",
    "sg:address":"Hellb\u00fchlerstrasse 2 6017 Ruswil. Postfach 131",
    "sg:city":"Ruswil",
    "sg:orig_category":"Regionalbanken U Sparkassen",
    "sg:phone":"+41 52 320 98 98",
    "sg:postcode":"6017",
    "sg:province":"Luzern",
    "wof:name":"Zlb Z\u00fcrcher Landbank",
    "wof:placetype":"venue"
},
  "geometry": {"coordinates":[8.7937240601,47.5510139465],"type":"Point"}
}