{
  "type": "Feature",
  "properties": {
    "iso:country":"CH",
    "sg:address":"Kappelenstrasse 91",
    "sg:city":"Wynigen",
    "sg:classifiers":[
        {
            "category":"Restaurant",
            "type":"Food & Drink"
        }
    ],
    "sg:phone":"+41 34 415 11 87",
    "sg:postcode":"3472",
    "sg:province":"Bern",
    "wof:name":"Restaurant B\u00e4dli",
    "wof:placetype":"venue"
},
  "geometry": {"coordinates":[7.6849350929,47.1047668457],"type":"Point"}
}