{
  "type": "Feature",
  "properties": {
    "iso:country":"CH",
    "sg:address":"Chaindon 50",
    "sg:city":"Reconvilier",
    "sg:orig_category":"Zimmerei, Dachdeckerei, Bauspenglerei U Abdichtung",
    "sg:postcode":"2732",
    "sg:province":"Bern",
    "wof:name":"Schatz Holzbau Gmbh",
    "wof:placetype":"venue"
},
  "geometry": {"coordinates":[8.2140302658,47.4884109497],"type":"Point"}
}