{
  "type": "Feature",
  "properties": {
    "iso:country":"CH",
    "sg:address":"Obere Kirchgasse 18",
    "sg:city":"Meilen",
    "sg:orig_category":"Berufsberatungen",
    "sg:phone":"+41 19335220",
    "sg:postcode":"8706",
    "sg:province":"Z\u00fcrich",
    "wof:name":"Biz Wetzikon",
    "wof:placetype":"venue"
},
  "geometry": {"coordinates":[8.794683,47.319103],"type":"Point"}
}