{
  "type": "Feature",
  "properties": {
    "iso:country":"CH",
    "sg:address":"Kurzgasse 4",
    "sg:city":"Z\u00fcrich",
    "sg:classifiers":[
        {
            "category":"Bars & Pubs",
            "type":"Food & Drink"
        }
    ],
    "sg:phone":"+41 12405876",
    "sg:postcode":"8004",
    "sg:province":"Z\u00fcrich",
    "wof:name":"Angels Bar",
    "wof:placetype":"venue"
},
  "geometry": {"coordinates":[8.527535,47.377224],"type":"Point"}
}