{
  "type": "Feature",
  "properties": {
    "iso:country":"CH",
    "sg:address":"Gr\u00fcnenmatt",
    "sg:city":"Gr\u00fcnenmatt",
    "sg:classifiers":[
        {
            "category":"Manufacturing",
            "subcategory":"Metals",
            "type":"Manufacturing & Wholesale Goods"
        }
    ],
    "sg:phone":"+41 34 431 12 13",
    "sg:postcode":"3452",
    "sg:province":"Bern",
    "sg:tags":[
        "alloy",
        "construction",
        "lightweight"
    ],
    "wof:name":"H. + F. Aeschlimann Ag",
    "wof:placetype":"venue"
},
  "geometry": {"coordinates":[7.7211480141,47.0077285767],"type":"Point"}
}