{
  "type": "Feature",
  "properties": {
    "iso:country":"CH",
    "sg:address":"Br\u00fcnnlirain 9",
    "sg:city":"Riehen",
    "sg:orig_category":"Sportvereine Ballsport Handball",
    "sg:phone":"+41 61 641 01 16",
    "sg:postcode":"4125",
    "sg:province":"Basel-Stadt",
    "wof:name":"Ptv Basel Stadt",
    "wof:placetype":"venue"
},
  "geometry": {"coordinates":[7.6544971466,47.5926132202],"type":"Point"}
}