{
  "type": "Feature",
  "properties": {
    "iso:country":"CH",
    "sg:address":"Schwalbenweg 16",
    "sg:city":"Rheinfelden",
    "sg:orig_category":"Tapeziererei Verlegen von Fliesen U Platten",
    "sg:phone":"+41 61 831 60 51",
    "sg:postcode":"4310",
    "sg:province":"Aargau",
    "wof:name":"Maler Fleig Ag",
    "wof:placetype":"venue"
},
  "geometry": {"coordinates":[7.7940211296,47.5470962524],"type":"Point"}
}