{
  "type": "Feature",
  "properties": {
    "iso:country":"CH",
    "sg:address":"Rue Des Jonch\u00e8res 43",
    "sg:city":"St-imier",
    "sg:orig_category":"Maler U Glasergewerbe Malerei",
    "sg:phone":"+41 32 941 28 76",
    "sg:postcode":"2610",
    "sg:province":"Bern",
    "wof:name":"Valiani Vincent",
    "wof:placetype":"venue"
},
  "geometry": {"coordinates":[6.9955220222,47.1510887146],"type":"Point"}
}