{
  "type": "Feature",
  "properties": {
    "iso:country":"CH",
    "sg:address":"Waltenstein",
    "sg:city":"Schlatt",
    "sg:classifiers":[
        {
            "category":"Restaurant",
            "type":"Food & Drink"
        }
    ],
    "sg:phone":"+41 52 363 11 41",
    "sg:postcode":"8418",
    "sg:province":"Z\u00fcrich",
    "wof:name":"Restaurant Freihof",
    "wof:placetype":"venue"
},
  "geometry": {"coordinates":[8.8194103241,47.478679657],"type":"Point"}
}