{
  "type": "Feature",
  "properties": {
    "iso:country":"CH",
    "sg:address":"Gastern",
    "sg:city":"Kandersteg",
    "sg:classifiers":[
        {
            "category":"Travel",
            "subcategory":"Hotels & Motels",
            "type":"Entertainment"
        }
    ],
    "sg:phone":"+41 41 660 13 83",
    "sg:postcode":"3718",
    "sg:province":"Bern",
    "sg:tags":[
        "hotels",
        "mit",
        "restaurant"
    ],
    "wof:name":"Hotel Waldheim Am See, Townend Genoni Alexandra",
    "wof:placetype":"venue"
},
  "geometry": {"coordinates":[8.2240428925,46.8806610107],"type":"Point"}
}