{
  "type": "Feature",
  "properties": {
    "iso:country":"CH",
    "sg:address":"Eichr\u00fcti 8 6331 H\u00fcnenberg. Postfach 3",
    "sg:city":"H\u00fcnenberg",
    "sg:orig_category":"Handelsvermittlung U Grosshandel",
    "sg:phone":"+41 41 780 82 80",
    "sg:postcode":"6331",
    "sg:province":"Zug",
    "wof:name":"Bls-technik Ag",
    "wof:placetype":"venue"
},
  "geometry": {"coordinates":[8.4481258392,47.1669273376],"type":"Point"}
}