{
  "type": "Feature",
  "properties": {
    "iso:country":"CH",
    "sg:address":"Via Guisan 16 6902 Paradiso. Postfach",
    "sg:city":"Paradiso",
    "sg:orig_category":"Fachdetailhandel in Verkaufsr\u00e4umen",
    "sg:postcode":"6900",
    "sg:province":"Ticino",
    "wof:name":"Artemarc Sagl",
    "wof:placetype":"venue"
},
  "geometry": {"coordinates":[8.9471750259,45.9904403687],"type":"Point"}
}