{
  "type": "Feature",
  "properties": {
    "iso:country":"CH",
    "sg:address":"Breiteweg 1 3006 Bern. Postfach",
    "sg:city":"Bern",
    "sg:orig_category":"Grosshandel mit Nahrungsmitteln, Getr\u00e4nken U Tabakwaren ohne ausgepr\u00e4gten Schwerpunkt",
    "sg:postcode":"3005",
    "sg:province":"Bern",
    "wof:name":"Maria Beutler",
    "wof:placetype":"venue"
},
  "geometry": {"coordinates":[7.4768137932,46.9558448792],"type":"Point"}
}