{
  "type": "Feature",
  "properties": {
    "iso:country":"CH",
    "sg:address":"1742",
    "sg:city":"Autigny",
    "sg:orig_category":"Bauschreinerei Herstellung von Konstruktionsteilen, Fertigbauteilen U Ausbauelementen aus Holz",
    "sg:postcode":"1742",
    "sg:province":"Fribourg",
    "wof:name":"Huguenot Ren\u00e9",
    "wof:placetype":"venue"
},
  "geometry": {"coordinates":[7.01836,46.736584],"type":"Point"}
}