{
  "type": "Feature",
  "properties": {
    "iso:country":"CH",
    "sg:address":"1636",
    "sg:city":"Broc",
    "sg:classifiers":[
        {
            "category":"Travel",
            "subcategory":"Hotels & Motels",
            "type":"Entertainment"
        }
    ],
    "sg:postcode":"1636",
    "sg:province":"Fribourg",
    "sg:tags":[
        "hotels",
        "mit",
        "restaurant"
    ],
    "wof:name":"Sunapart Ag",
    "wof:placetype":"venue"
},
  "geometry": {"coordinates":[9.267829895,46.8157691956],"type":"Point"}
}