{
  "type": "Feature",
  "properties": {
    "iso:country":"CH",
    "sg:address":"Bahnhofstrasse 12 3150 Schwarzenburg. Postfach 103",
    "sg:city":"Schwarzenburg",
    "sg:orig_category":"Detailhandel mit Damenbekleidung Detailhandel mit S\u00e4uglings U Kinderbekleidung",
    "sg:phone":"+41 31 731 15 69",
    "sg:postcode":"3150",
    "sg:province":"Bern",
    "wof:name":"Hosechnopf Kleiderb\u00f6rse",
    "wof:placetype":"venue"
},
  "geometry": {"coordinates":[7.343421936,46.8183097839],"type":"Point"}
}