{
  "type": "Feature",
  "properties": {
    "iso:country":"CH",
    "sg:address":"Weststrasse 10",
    "sg:city":"Oberdiessbach",
    "sg:orig_category":"Herstellung von Betonerzeugnissen f\u00fcr den Bau",
    "sg:phone":"+41 62 288 99 00",
    "sg:postcode":"3672",
    "sg:province":"Bern",
    "wof:name":"Favre Betonwaren Ag",
    "wof:placetype":"venue"
},
  "geometry": {"coordinates":[7.9825348854,47.3588905334],"type":"Point"}
}