{
  "type": "Feature",
  "properties": {
    "iso:country":"CH",
    "sg:address":"Rue Pellegrino-rossi 7 1200 Genf. Postfach",
    "sg:city":"Gen\u00e8ve",
    "sg:orig_category":"RESTAURANTS: TEA-ROOMS",
    "sg:postcode":"1201",
    "sg:province":"Gen\u00e8ve",
    "wof:name":"Gurtner",
    "wof:placetype":"venue"
},
  "geometry": {"coordinates":[6.146130085,46.2102241516],"type":"Point"}
}