{
  "type": "Feature",
  "properties": {
    "iso:country":"CH",
    "sg:address":"Zillern 6374 Buochs. Postfach 62",
    "sg:city":"Buochs",
    "sg:orig_category":"Herstellung von Automobilen Herstellung von Metallerzeugnissen ohne Maschinenbau",
    "sg:phone":"+41 41 620 18 44",
    "sg:postcode":"6374",
    "sg:province":"Nidwalden",
    "wof:name":"Albar Fahrzeuge Alois Barmettler",
    "wof:placetype":"venue"
},
  "geometry": {"coordinates":[8.4258022308,46.9684448242],"type":"Point"}
}