{
  "type": "Feature",
  "properties": {
    "iso:country":"CH",
    "sg:address":"6147",
    "sg:city":"Altb\u00fcron",
    "sg:orig_category":"Organisationen des Gesundheitswesen",
    "sg:phone":"+41 62 927 20 42",
    "sg:postcode":"6147",
    "sg:province":"Luzern",
    "wof:name":"Samariterverein",
    "wof:placetype":"venue"
},
  "geometry": {"coordinates":[7.8819937706,47.1784286499],"type":"Point"}
}