{
  "type": "Feature",
  "properties": {
    "iso:country":"CH",
    "sg:address":"Bonte-brolla",
    "sg:city":"Tegna",
    "sg:classifiers":[
        {
            "category":"Travel",
            "subcategory":"Hotels & Motels",
            "type":"Entertainment"
        }
    ],
    "sg:postcode":"6652",
    "sg:province":"Ticino",
    "sg:tags":[
        "hotels",
        "mit",
        "restaurant"
    ],
    "wof:name":"Schmed Elisabeth.",
    "wof:placetype":"venue"
},
  "geometry": {"coordinates":[8.7447624207,46.1868515015],"type":"Point"}
}