{
  "type": "Feature",
  "properties": {
    "iso:country":"CH",
    "sg:address":"Parkstrasse 15",
    "sg:city":"Baden",
    "sg:classifiers":[
        {
            "category":"Professional",
            "subcategory":"Employment Agencies",
            "type":"Services"
        }
    ],
    "sg:phone":"+41 56 210 34 84",
    "sg:postcode":"5400",
    "sg:province":"Aargau",
    "sg:tags":[
        "personal",
        "u",
        "stellenvermittlung"
    ],
    "wof:name":"Andrea Senn Forum Hauswirtschaft",
    "wof:placetype":"venue"
},
  "geometry": {"coordinates":[8.3088312149,47.4785881042],"type":"Point"}
}