{
  "type": "Feature",
  "properties": {
    "iso:country":"CH",
    "sg:address":"Seestrasse 295",
    "sg:city":"Horgen",
    "sg:orig_category":"Autogaragen",
    "sg:phone":"+41 17703311",
    "sg:postcode":"8810",
    "sg:province":"Z\u00fcrich",
    "wof:name":"Th. Willy Ag Eine Unternehmung Der Willy-gruppe",
    "wof:placetype":"venue"
},
  "geometry": {"coordinates":[8.60616,47.25761],"type":"Point"}
}