{
  "type": "Feature",
  "properties": {
    "iso:country":"CH",
    "sg:address":"Hauptstrasse 53",
    "sg:city":"Reitnau",
    "sg:orig_category":"RESTAURANTS: TEA-ROOMS",
    "sg:postcode":"5057",
    "sg:province":"Aargau",
    "wof:name":"Sch\u00e4rli-fischer Verena",
    "wof:placetype":"venue"
},
  "geometry": {"coordinates":[8.0451622009,47.2507400513],"type":"Point"}
}