{
  "type": "Feature",
  "properties": {
    "iso:country":"CH",
    "sg:address":"Industriestrasse 10 6010 Kriens. Postfach",
    "sg:city":"Kriens",
    "sg:orig_category":"RESTAURANTS: TEA-ROOMS",
    "sg:postcode":"6010",
    "sg:province":"Luzern",
    "wof:name":"Kompetenz-zentrum F\u00fcr Das Gastgewerbe Und Die Hotellerie Ag Dienstleistungen Von Betrieben Des Gastgewerbes U. Der Hotellerie, Bes. Des Marketings, Rechnungswesens, Personalvermittlung Usw",
    "wof:placetype":"venue"
},
  "geometry": {"coordinates":[8.2997646332,47.0244598389],"type":"Point"}
}