{
  "type": "Feature",
  "properties": {
    "iso:country":"CH",
    "sg:address":"Burghalde 2",
    "sg:city":"Gr\u00e4nichen",
    "sg:orig_category":"Hoch U Tiefbau",
    "sg:phone":"+41 62 842 24 89",
    "sg:postcode":"5722",
    "sg:province":"Aargau",
    "wof:name":"Rolf Leutwiler Baugesch\u00e4ft",
    "wof:placetype":"venue"
},
  "geometry": {"coordinates":[8.096326828,47.3580169678],"type":"Point"}
}