{
  "type": "Feature",
  "properties": {
    "iso:country":"CH",
    "sg:address":"Dr. Schneider-strasse 16",
    "sg:city":"Nidau",
    "sg:orig_category":"Elektroinstallation Ingenieurb\u00fcros Elektro",
    "sg:phone":"+41 32 332 22 22",
    "sg:postcode":"2560",
    "sg:province":"Bern",
    "wof:name":"Bkw Isp Ag Elektroinstallationen Gesch\u00e4ftsstelle Biel",
    "wof:placetype":"venue"
},
  "geometry": {"coordinates":[7.2389769554,47.1283950806],"type":"Point"}
}