{
  "type": "Feature",
  "properties": {
    "iso:country":"CH",
    "sg:address":"Milit\u00e4rstrasse 90",
    "sg:city":"Z\u00fcrich",
    "sg:orig_category":"Reiseb\u00fcros U Reiseveranstalter",
    "sg:phone":"+41 17814353",
    "sg:postcode":"8004",
    "sg:province":"Z\u00fcrich",
    "wof:name":"Central Reisen, Iris Varco",
    "wof:placetype":"venue"
},
  "geometry": {"coordinates":[8.6310749054,47.2476158142],"type":"Point"}
}