{
  "type": "Feature",
  "properties": {
    "iso:country":"CH",
    "sg:address":"Route De Montreux 1618 Ch\u00e2tel-st-denis Case Postale 75",
    "sg:city":"Ch\u00e2tel-st-denis",
    "sg:orig_category":"R\u00fcckgewinnung U Vorbereitung f\u00fcr die Wiederverwertung Recycling R\u00fcckgewinnung U Vorbereitung f\u00fcr die",
    "sg:phone":"+41 21 948 75 20",
    "sg:postcode":"1618",
    "sg:province":"Fribourg",
    "wof:name":"Sorval Sa",
    "wof:placetype":"venue"
},
  "geometry": {"coordinates":[6.9056220055,46.5163612366],"type":"Point"}
}