{
  "type": "Feature",
  "properties": {
    "addr:full":"Usteristrasse 9 Z\u00fcrich Z\u00fcrich 8001",
    "addr:housenumber":"9",
    "addr:postcode":"8001",
    "addr:street":"Usteristrasse",
    "iso:country":"CH",
    "sg:address":"Usteristrasse 9",
    "sg:city":"Z\u00fcrich",
    "sg:orig_category":"Allgemeiner Hoch U Tiefbau Personal U Stellenvermittlung",
    "sg:phone":"+41 12186080",
    "sg:postcode":"8001",
    "sg:province":"Z\u00fcrich",
    "wof:name":"Gross Ag Arbeit Personalvermittlung",
    "wof:placetype":"venue"
},
  "geometry": {"coordinates":[8.537979,47.375355],"type":"Point"}
}