{
  "type": "Feature",
  "properties": {
    "iso:country":"CH",
    "sg:address":"Holzgasse 23",
    "sg:city":"Sch\u00f6nb\u00fchl-urtenen",
    "sg:orig_category":"Erbringung von Dienstleistungen f\u00fcr Unternehmen",
    "sg:phone":"+41 32 377 17 12",
    "sg:postcode":"3322",
    "sg:province":"Bern",
    "wof:name":"Vinifera Gmbh",
    "wof:placetype":"venue"
},
  "geometry": {"coordinates":[7.3284368515,47.1750411987],"type":"Point"}
}