{
  "type": "Feature",
  "properties": {
    "iso:country":"CH",
    "sg:address":"Industriestrasse 14",
    "sg:city":"Lausen",
    "sg:orig_category":"Bauschreinerei Verlegen von Fussboden",
    "sg:phone":"+41 21 691 46 66",
    "sg:postcode":"4415",
    "sg:province":"Basel-Landschaft",
    "wof:name":"Jean Raynal Menuiserie Linol\u00e9um Tapis",
    "wof:placetype":"venue"
},
  "geometry": {"coordinates":[6.54782,46.513725],"type":"Point"}
}