{
  "type": "Feature",
  "properties": {
    "iso:country":"CH",
    "sg:address":"Place Du Midi 36",
    "sg:city":"Sion",
    "sg:orig_category":"Tanzschulen, Tanzlehrer",
    "sg:phone":"+41 18883333",
    "sg:postcode":"1950",
    "sg:province":"Valais",
    "wof:name":"Blue Moon Tanzschule",
    "wof:placetype":"venue"
},
  "geometry": {"coordinates":[8.6544208527,47.401550293],"type":"Point"}
}