{
  "type": "Feature",
  "properties": {
    "iso:country":"CH",
    "sg:address":"Wunderlistrasse 8",
    "sg:city":"Z\u00fcrich",
    "sg:orig_category":"Verlagsgewerbe",
    "sg:phone":"+41 12728507",
    "sg:postcode":"8037",
    "sg:province":"Z\u00fcrich",
    "wof:name":"Basta Verlag",
    "wof:placetype":"venue"
},
  "geometry": {"coordinates":[8.5229740143,47.3971099854],"type":"Point"}
}