{
  "type": "Feature",
  "properties": {
    "iso:country":"CH",
    "sg:address":"1950",
    "sg:city":"Sion",
    "sg:orig_category":"Sonstige mit Sport verbundene T\u00e4tigkeiten",
    "sg:postcode":"1950",
    "sg:province":"Valais",
    "wof:name":"Soci\u00e9t\u00e9 Des Tireurs De La Borgne",
    "wof:placetype":"venue"
},
  "geometry": {"coordinates":[7.3633999825,46.2366981506],"type":"Point"}
}