{
  "type": "Feature",
  "properties": {
    "iso:country":"CH",
    "sg:address":"Rue Centrale 5b 1804 Corsier-sur-vevey Case Postale 32",
    "sg:city":"Corsier-sur-vevey",
    "sg:orig_category":"G\u00fcterbef\u00f6rderung im Strassenverkehr",
    "sg:phone":"+41 21 921 65 44",
    "sg:postcode":"1804",
    "sg:province":"Vaud",
    "wof:name":"Abc D\u00e9m\u00e9nagements & Transports Sa",
    "wof:placetype":"venue"
},
  "geometry": {"coordinates":[6.842196,46.470531],"type":"Point"}
}