{
  "type": "Feature",
  "properties": {
    "iso:country":"CH",
    "sg:address":"Sonnmattstrasse 7",
    "sg:city":"Endingen",
    "sg:orig_category":"Softwareentwicklung U beratung",
    "sg:postcode":"5304",
    "sg:province":"Aargau",
    "wof:name":"Siteware Systems Gmbh",
    "wof:placetype":"venue"
},
  "geometry": {"coordinates":[8.2942762375,47.538684845],"type":"Point"}
}