{
  "type": "Feature",
  "properties": {
    "iso:country":"CH",
    "sg:address":"Birchlistrasse 13",
    "sg:city":"Neerach",
    "sg:orig_category":"Werbeberatung",
    "sg:phone":"+41 18858005",
    "sg:postcode":"8173",
    "sg:province":"Z\u00fcrich",
    "wof:name":"Van Der Geest Edwin, Public Relations & Consulting",
    "wof:placetype":"venue"
},
  "geometry": {"coordinates":[8.4689569473,47.5017585754],"type":"Point"}
}