{
  "type": "Feature",
  "properties": {
    "addr:full":"1463 Rovray Vaud 1463",
    "addr:postcode":"1463;1463",
    "iso:country":"CH",
    "sg:address":"1463",
    "sg:city":"Rovray",
    "sg:classifiers":[
        {
            "category":"Education",
            "subcategory":"Library",
            "type":"Public Place"
        }
    ],
    "sg:postcode":"1463",
    "sg:province":"Vaud",
    "sg:tags":[
        "u",
        "bibliotheken",
        "archive"
    ],
    "wof:name":"Biblioth\u00e8que Populaire",
    "wof:placetype":"venue"
},
  "geometry": {"coordinates":[6.76234,46.78574],"type":"Point"}
}