{
  "type": "Feature",
  "properties": {
    "iso:country":"CH",
    "sg:address":"Via Industria",
    "sg:city":"Lamone-cadempino",
    "sg:orig_category":"Grosshandel mit Bekleidung Grosshandel mit H\u00e4uten, Fellen U Leder",
    "sg:phone":"+41 91 960 16 00",
    "sg:postcode":"6814",
    "sg:province":"Ticino",
    "wof:name":"Gucci International N.v. Amsterdam Succ.di Cadempino",
    "wof:placetype":"venue"
},
  "geometry": {"coordinates":[8.9248304367,46.0384063721],"type":"Point"}
}