{
  "type": "Feature",
  "properties": {
    "iso:country":"CH",
    "sg:address":"St. Urbanstrasse 1",
    "sg:city":"Langenthal",
    "sg:classifiers":[
        {
            "category":"Travel",
            "subcategory":"Hotels & Motels",
            "type":"Entertainment"
        }
    ],
    "sg:phone":"+41 62 919 17 17",
    "sg:postcode":"4900",
    "sg:province":"Bern",
    "sg:tags":[
        "hotels",
        "mit",
        "restaurant"
    ],
    "wof:name":"Aktiengesellschaft B\u00e4ren Langenthal",
    "wof:placetype":"venue"
},
  "geometry": {"coordinates":[7.7893900871,47.2122459412],"type":"Point"}
}