{
  "type": "Feature",
  "properties": {
    "iso:country":"CH",
    "sg:address":"Brunnenrain 4",
    "sg:city":"Ittigen",
    "sg:orig_category":"Detailhandel mit Milcherzeugnissen U Eiern",
    "sg:phone":"+41 31 921 03 35",
    "sg:postcode":"3063",
    "sg:province":"Bern",
    "wof:name":"Alfred B\u00e4rtschi Ch\u00e4sloube Brunnenhof",
    "wof:placetype":"venue"
},
  "geometry": {"coordinates":[7.486260891,46.9794387817],"type":"Point"}
}