{
  "type": "Feature",
  "properties": {
    "iso:country":"CH",
    "sg:address":"Ulmgasse 3",
    "sg:city":"Untervaz",
    "sg:orig_category":"Nationale Postdienste",
    "sg:phone":"+41 81 322 14 97",
    "sg:postcode":"7204",
    "sg:province":"Graubunden",
    "wof:name":"Die Schweizerische Post",
    "wof:placetype":"venue"
},
  "geometry": {"coordinates":[9.5348653793,46.9280815125],"type":"Point"}
}