{
  "type": "Feature",
  "properties": {
    "iso:country":"CH",
    "sg:address":"Duboule Chemin Mo\u00efse- 43 1209 Gen\u00e8ve. Postfach",
    "sg:city":"Gen\u00e8ve",
    "sg:orig_category":"Softwareentwicklung U beratung",
    "sg:phone":"+41 71 960 08 40",
    "sg:postcode":"1209",
    "sg:province":"Gen\u00e8ve",
    "wof:name":"Jnet Systems Ag",
    "wof:placetype":"venue"
},
  "geometry": {"coordinates":[8.985710144,47.4722251892],"type":"Point"}
}