{
  "type": "Feature",
  "properties": {
    "iso:country":"CH",
    "sg:address":"Rue De Bourg 20",
    "sg:city":"Lausanne",
    "sg:classifiers":[
        {
            "category":"Shopping",
            "subcategory":"Clothing, Apparel, & Fashions",
            "type":"Retail Goods"
        }
    ],
    "sg:phone":"+41 21 320 40 71",
    "sg:postcode":"1003",
    "sg:province":"Vaud",
    "sg:tags":[
        "textile",
        "clothing",
        "clothes"
    ],
    "wof:name":"Canton & Cie Fourrures",
    "wof:placetype":"venue"
},
  "geometry": {"coordinates":[6.63566,46.519936],"type":"Point"}
}