{
  "type": "Feature",
  "properties": {
    "iso:country":"CH",
    "sg:address":"Industriestrasse 3 6300 Zug. Postfach 33",
    "sg:city":"Zug",
    "sg:orig_category":"Grosshandel mit Obst U Gem\u00fcse Sonstiger Grosshandel",
    "sg:phone":"+41 41 711 50 48",
    "sg:postcode":"6301",
    "sg:province":"Zug",
    "wof:name":"Foodexport Gmbh Zug.",
    "wof:placetype":"venue"
},
  "geometry": {"coordinates":[8.5176343918,47.1703681946],"type":"Point"}
}