{
  "type": "Feature",
  "properties": {
    "iso:country":"CH",
    "sg:address":"Chemin De La Pallanterie 11",
    "sg:city":"Meinier",
    "sg:classifiers":[
        {
            "category":"Utilities",
            "subcategory":"Refuse",
            "type":"Services"
        }
    ],
    "sg:phone":"+41 22 722 06 60",
    "sg:postcode":"1252",
    "sg:province":"Gen\u00e8ve",
    "sg:tags":[
        "equipment",
        "anti-theft"
    ],
    "wof:name":"Promo T. Et I. Sa",
    "wof:placetype":"venue"
},
  "geometry": {"coordinates":[6.220335,46.246841],"type":"Point"}
}