{
  "type": "Feature",
  "properties": {
    "iso:country":"CH",
    "sg:address":"Winkelstrasse 18",
    "sg:city":"Kleind\u00f6ttingen",
    "sg:orig_category":"G\u00fcterbef\u00f6rderung im Strassenverkehr",
    "sg:phone":"+41 56 245 34 66",
    "sg:postcode":"5314",
    "sg:province":"Aargau",
    "wof:name":"Kalt Kurt Transporte.",
    "wof:placetype":"venue"
},
  "geometry": {"coordinates":[8.2510843277,47.5697212219],"type":"Point"}
}