{
  "type": "Feature",
  "properties": {
    "iso:country":"CH",
    "sg:address":"H\u00fcbel 849",
    "sg:city":"M\u00fcmliswil",
    "sg:orig_category":"Dachdeckerei Zimmerei, Dachdeckerei, Bauspenglerei U Abdichtung",
    "sg:phone":"+41 79 320 02 67",
    "sg:postcode":"4717",
    "sg:province":"Solothurn",
    "wof:name":"Otto B\u00e4bi Dachdeckergesch\u00e4ft",
    "wof:placetype":"venue"
},
  "geometry": {"coordinates":[7.704631,47.347599],"type":"Point"}
}