{
  "type": "Feature",
  "properties": {
    "iso:country":"CH",
    "sg:address":"Place Du March\u00e9 8",
    "sg:city":"Montreux",
    "sg:orig_category":"Fachdetailhandel in Verkaufsr\u00e4umen Kunsthandel",
    "sg:phone":"+41 21 963 05 17",
    "sg:postcode":"1820",
    "sg:province":"Vaud",
    "wof:name":"Wian Sa",
    "wof:placetype":"venue"
},
  "geometry": {"coordinates":[6.909673214,46.4319458008],"type":"Point"}
}