{
  "type": "Feature",
  "properties": {
    "iso:country":"CH",
    "sg:address":"Route De Daillens",
    "sg:city":"Assens",
    "sg:orig_category":"Detailhandel mit Waren verschiedener Art, Hauptrichtung Nahrungsmittel Handelsvermittlung U Grosshan",
    "sg:phone":"+41 21 882 55 07",
    "sg:postcode":"1042",
    "sg:province":"Vaud",
    "wof:name":"Labovet, Rovero Marc-aur\u00e8le",
    "wof:placetype":"venue"
},
  "geometry": {"coordinates":[6.6212000847,46.6141357422],"type":"Point"}
}