{
  "type": "Feature",
  "properties": {
    "iso:country":"CH",
    "sg:address":"Hauptstrasse 32",
    "sg:city":"Pratteln",
    "sg:orig_category":"Detailhandel mit Teppichen Erbringung von Dienstleistungen f\u00fcr Unternehmen",
    "sg:phone":"+41 19300566",
    "sg:postcode":"4133",
    "sg:province":"Basel-Landschaft",
    "wof:name":"Schumacher Urs Innendekorationen",
    "wof:placetype":"venue"
},
  "geometry": {"coordinates":[8.806055069,47.3228111267],"type":"Point"}
}