{
  "type": "Feature",
  "properties": {
    "iso:country":"CH",
    "sg:address":"Via Codeborgo 12",
    "sg:city":"Bellinzona",
    "sg:classifiers":[
        {
            "category":"Restaurant",
            "type":"Food & Drink"
        }
    ],
    "sg:phone":"+41 55 240 73 22",
    "sg:postcode":"6500",
    "sg:province":"Ticino",
    "wof:name":"Pizzeria Portofino",
    "wof:placetype":"venue"
},
  "geometry": {"coordinates":[8.8533086777,47.252407074],"type":"Point"}
}