{
  "type": "Feature",
  "properties": {
    "iso:country":"CH",
    "sg:address":"Oberdorfstrasse 36",
    "sg:city":"Z\u00fcrich",
    "sg:orig_category":"Sonstiges Gesundheitswesen",
    "sg:phone":"+41 12625401",
    "sg:postcode":"8001",
    "sg:province":"Z\u00fcrich",
    "wof:name":"Krankenmobilienmagazin Altstadt",
    "wof:placetype":"venue"
},
  "geometry": {"coordinates":[8.5445928574,47.3695983887],"type":"Point"}
}