{
  "type": "Feature",
  "properties": {
    "iso:country":"CH",
    "sg:address":"Bahnhofstrasse 14 2502 Biel/bienne Case Postale 422",
    "sg:city":"Biel/bienne",
    "sg:orig_category":"Herstellung U Zusammensetzung von Uhren Herstellung von Uhren",
    "sg:phone":"+41 32 341 13 35",
    "sg:postcode":"2501",
    "sg:province":"Bern",
    "wof:name":"Montres Pertuis, Arranger K. & Fleury J.",
    "wof:placetype":"venue"
},
  "geometry": {"coordinates":[7.2562141418,47.144329071],"type":"Point"}
}