{
  "type": "Feature",
  "properties": {
    "iso:country":"CH",
    "sg:address":"Flugplatz Langenthal",
    "sg:city":"Bleienbach",
    "sg:orig_category":"Herstellung von Metallerzeugnissen ohne Maschinenbau Luft U Raumfahrzeugbau",
    "sg:phone":"+41 41 852 00 00",
    "sg:postcode":"3368",
    "sg:province":"Bern",
    "wof:name":"Asa Aero Safety Ag",
    "wof:placetype":"venue"
},
  "geometry": {"coordinates":[8.4319238663,47.0811309814],"type":"Point"}
}