{
  "type": "Feature",
  "properties": {
    "iso:country":"CH",
    "sg:address":"Viale Stazione 27",
    "sg:city":"Bellinzona",
    "sg:orig_category":"Interessenvertretungen",
    "sg:postcode":"6500",
    "sg:province":"Ticino",
    "wof:name":"Fondazione Balli Dr. Ettore",
    "wof:placetype":"venue"
},
  "geometry": {"coordinates":[9.0273542404,46.1945915222],"type":"Point"}
}