{
  "type": "Feature",
  "properties": {
    "iso:country":"CH",
    "sg:address":"Chemin Des Places 2",
    "sg:city":"Del\u00e9mont",
    "sg:orig_category":"Herstellung von Bekleidung U Pelzwaren Herstellung von gewirktem U gestricktem Stoff",
    "sg:phone":"+41 32 422 15 68",
    "sg:postcode":"2800",
    "sg:province":"Jura",
    "wof:name":"Vacchelli-billieux & Cie Fabrique De Bonneterie",
    "wof:placetype":"venue"
},
  "geometry": {"coordinates":[7.3452868462,47.3633918762],"type":"Point"}
}