{
  "type": "Feature",
  "properties": {
    "iso:country":"CH",
    "sg:address":"Mezzaro Via 30 6648 Minusio. Postfach",
    "sg:city":"Minusio",
    "sg:orig_category":"Unclassifiable Establishments",
    "sg:phone":"+41 91 730 15 08",
    "sg:postcode":"6648",
    "sg:province":"Ticino",
    "wof:name":"Websolutions Cordasco Soluzioni Internet",
    "wof:placetype":"venue"
},
  "geometry": {"coordinates":[8.8176622391,46.176651001],"type":"Point"}
}