{
  "type": "Feature",
  "properties": {
    "iso:country":"CH",
    "sg:address":"Ferme Du Ravaret",
    "sg:city":"Bremblens",
    "sg:orig_category":"Fahrschulen, Flugschulen",
    "sg:phone":"+41 21 801 27 11",
    "sg:postcode":"1121",
    "sg:province":"Vaud",
    "wof:name":"Olivier Keuffer Auto-\u00e9cole",
    "wof:placetype":"venue"
},
  "geometry": {"coordinates":[6.5147027969,46.5446891785],"type":"Point"}
}