{
  "type": "Feature",
  "properties": {
    "iso:country":"CH",
    "sg:address":"Rebhaldenstrasse 23",
    "sg:city":"Neerach",
    "sg:orig_category":"Grosshandel mit Erzen U Metallen Herstellung von Elektromotoren, Generatoren U Transformatoren",
    "sg:phone":"+41 61 281 41 51",
    "sg:postcode":"8173",
    "sg:province":"Z\u00fcrich",
    "wof:name":"Unidrive Gmbh",
    "wof:placetype":"venue"
},
  "geometry": {"coordinates":[7.596558094,47.4980239868],"type":"Point"}
}