{
  "type": "Feature",
  "properties": {
    "iso:country":"CH",
    "sg:address":"Langmattstrasse 10",
    "sg:city":"Rotkreuz",
    "sg:orig_category":"Fachdetailhandel mit pharmazeutischen Produkten",
    "sg:phone":"+41 41902034",
    "sg:postcode":"6343",
    "sg:province":"Zug",
    "wof:name":"K-trade, Kurt Arnet",
    "wof:placetype":"venue"
},
  "geometry": {"coordinates":[8.4354496002,47.1396217346],"type":"Point"}
}