{
  "type": "Feature",
  "properties": {
    "iso:country":"CH",
    "sg:address":"Lussery",
    "sg:city":"Lussery-villars",
    "sg:orig_category":"Verwertung von Milch",
    "sg:postcode":"1307",
    "sg:province":"Vaud",
    "wof:name":"Soci\u00e9t\u00e9 De Laiterie De Villars-lussery",
    "wof:placetype":"venue"
},
  "geometry": {"coordinates":[6.5258197784,46.6319198608],"type":"Point"}
}