{
  "type": "Feature",
  "properties": {
    "iso:country":"CH",
    "sg:address":"Alte Simplonstrasse 19 3900 Brig. Postfach",
    "sg:city":"Brig",
    "sg:orig_category":"Sonstiges Versicherungsgewerbe",
    "sg:postcode":"3900",
    "sg:province":"Valais",
    "wof:name":"Schweizerische Mobiliar Versicherungsgesellschaft Generalagentur Rapperswil, Landis Rolf",
    "wof:placetype":"venue"
},
  "geometry": {"coordinates":[8.8199644089,47.2292785645],"type":"Point"}
}