{
  "type": "Feature",
  "properties": {
    "iso:country":"CH",
    "sg:address":"Fendringen",
    "sg:city":"B\u00f6singen",
    "sg:orig_category":"Grosshandel mit lebenden Tieren Sonstiger Fachdetailhandel mit Nahrungsmitteln, Getr\u00e4nken U Tabak in",
    "sg:postcode":"3178",
    "sg:province":"Fribourg",
    "wof:name":"Schmidh\u00e4usler August",
    "wof:placetype":"venue"
},
  "geometry": {"coordinates":[7.2416858673,46.8834190369],"type":"Point"}
}