{
  "type": "Feature",
  "properties": {
    "iso:country":"CH",
    "sg:address":"Beim R\u00fctihof",
    "sg:city":"Herrliberg",
    "sg:orig_category":"Institutionen f\u00fcr Behinderte",
    "sg:phone":"+41 19152260",
    "sg:postcode":"8704",
    "sg:province":"Z\u00fcrich",
    "wof:name":"Heim R\u00fctib\u00fchl F\u00fcr Frauen M. Einer Geistigen Behinderung",
    "wof:placetype":"venue"
},
  "geometry": {"coordinates":[8.6135377884,47.2861976624],"type":"Point"}
}