{
  "type": "Feature",
  "properties": {
    "iso:country":"CH",
    "sg:address":"Route De La Gruy\u00e8re 17",
    "sg:city":"Fribourg",
    "sg:orig_category":"Herstellung von Konstruktionsteilen, Fertigbauteilen U Ausbauelementen aus Holz",
    "sg:phone":"+41 26 424 59 59",
    "sg:postcode":"1700",
    "sg:province":"Fribourg",
    "wof:name":"Musco Luigi, Menuiserie, Agencement, Transformations",
    "wof:placetype":"venue"
},
  "geometry": {"coordinates":[7.1426110268,46.7956085205],"type":"Point"}
}