{
  "type": "Feature",
  "properties": {
    "iso:country":"CH",
    "sg:address":"Route De Del\u00e9mont 63 2802 Develier Case Postale 104",
    "sg:city":"Develier",
    "sg:orig_category":"Autogaragen",
    "sg:phone":"+41 32 423 24 24",
    "sg:postcode":"2802",
    "sg:province":"Jura",
    "wof:name":"Thal Garage Develier Sa Concess. Volvo",
    "wof:placetype":"venue"
},
  "geometry": {"coordinates":[7.307868,47.360909],"type":"Point"}
}