{
  "type": "Feature",
  "properties": {
    "iso:country":"CH",
    "sg:address":"Dosso Via Al 30 6828 Balerna. Postfach",
    "sg:city":"Balerna",
    "sg:orig_category":"Abwasserreinigung, Abfallbeseitigung U sonstige Entsorgung",
    "sg:postcode":"6828",
    "sg:province":"Ticino",
    "wof:name":"Capoferri G E M Servizi Ecologici",
    "wof:placetype":"venue"
},
  "geometry": {"coordinates":[9.007515,45.849682],"type":"Point"}
}