{
  "type": "Feature",
  "properties": {
    "iso:country":"CH",
    "sg:address":"Rathausquai 3",
    "sg:city":"Luzern",
    "sg:orig_category":"Detailhandel mit Geschenkartikeln U Souvenirs",
    "sg:phone":"+41 41 260 30 32",
    "sg:postcode":"6004",
    "sg:province":"Luzern",
    "wof:name":"Boutique Ammann, Inhaberin Bachmann-ammann Barbara",
    "wof:placetype":"venue"
},
  "geometry": {"coordinates":[8.3076505661,47.0523071289],"type":"Point"}
}