{
  "type": "Feature",
  "properties": {
    "iso:country":"CH",
    "sg:address":"M\u00fchlegasse 9 4571 Ichertswil. Postfach",
    "sg:city":"Ichertswil",
    "sg:orig_category":"Softwareentwicklung U beratung",
    "sg:phone":"+41 71 311 50 31",
    "sg:postcode":"4571",
    "sg:province":"Solothurn",
    "wof:name":"B\u00e4nziger Software Ag",
    "wof:placetype":"venue"
},
  "geometry": {"coordinates":[9.3162250519,47.4056282043],"type":"Point"}
}