{
  "type": "Feature",
  "properties": {
    "iso:country":"CH",
    "sg:address":"3778",
    "sg:city":"Sch\u00f6nried",
    "sg:orig_category":"Personenbef\u00f6rderung im Linienverkehr zu Land",
    "sg:postcode":"3778",
    "sg:province":"Bern",
    "wof:name":"Skiliftgenossenschaft Geschinen",
    "wof:placetype":"venue"
},
  "geometry": {"coordinates":[8.2801904678,46.4953765869],"type":"Point"}
}