{
  "type": "Feature",
  "properties": {
    "iso:country":"CH",
    "sg:address":"Hirzenbachstrasse 48",
    "sg:city":"Z\u00fcrich",
    "sg:orig_category":"Detailhandel mit Teppichen Verlegen von Fussboden",
    "sg:phone":"+41 13221906",
    "sg:postcode":"8051",
    "sg:province":"Z\u00fcrich",
    "wof:name":"Otto Loosli Bodenbel\u00e4ge",
    "wof:placetype":"venue"
},
  "geometry": {"coordinates":[8.5889387131,47.4041748047],"type":"Point"}
}