{
  "type": "Feature",
  "properties": {
    "iso:country":"CH",
    "sg:address":"Industriestrasse 1",
    "sg:city":"Volketswil",
    "sg:orig_category":"Fachdetailhandel mit pharmazeutischen Produkten",
    "sg:phone":"+41 19456666",
    "sg:postcode":"8604",
    "sg:province":"Z\u00fcrich",
    "wof:name":"Apotheke Volkiland",
    "wof:placetype":"venue"
},
  "geometry": {"coordinates":[8.6681413651,47.3819656372],"type":"Point"}
}