{
  "type": "Feature",
  "properties": {
    "iso:country":"CH",
    "sg:address":"Rohrmattstrasse 4",
    "sg:city":"B\u00f6ckten",
    "sg:orig_category":"Detailhandel mit Getr\u00e4nken Grosshandel mit Getr\u00e4nken",
    "sg:phone":"+41 19203330",
    "sg:postcode":"4461",
    "sg:province":"Basel-Landschaft",
    "wof:name":"Christen Stephan, Weinhandel",
    "wof:placetype":"venue"
},
  "geometry": {"coordinates":[8.6811342239,47.2625961304],"type":"Point"}
}