{
  "type": "Feature",
  "properties": {
    "iso:country":"CH",
    "sg:address":"Sch\u00fctzenstrasse 17",
    "sg:city":"Neuhausen",
    "sg:orig_category":"Detektivb\u00fcros U \u00dcberwachung Sonstige pers\u00f6nliche Dienstleistungen",
    "sg:phone":"+41 52 672 17 58",
    "sg:postcode":"8212",
    "sg:province":"Schaffhausen",
    "wof:name":"Ihr Haus-sitter Voelin Daniel",
    "wof:placetype":"venue"
},
  "geometry": {"coordinates":[8.6055860519,47.6798934937],"type":"Point"}
}