{
  "type": "Feature",
  "properties": {
    "iso:country":"CH",
    "sg:address":"Schmiedgasse 65",
    "sg:city":"Schwyz",
    "sg:orig_category":"Unclassifiable Establishments",
    "sg:postcode":"6430",
    "sg:province":"Schwyz",
    "wof:name":"Karl L\u00fc\u00f6nd, Dany's Fast-food Restaurant",
    "wof:placetype":"venue"
},
  "geometry": {"coordinates":[8.6516399384,47.0194206238],"type":"Point"}
}