{
  "type": "Feature",
  "properties": {
    "iso:country":"CH",
    "sg:address":"Winkeliweg 1",
    "sg:city":"M\u00fclligen",
    "sg:orig_category":"Einzelhandel mit Automobilteilen U Zubeh\u00f6r Instandhaltung U Reparatur von Automobilen",
    "sg:phone":"+41 55 442 37 40",
    "sg:postcode":"5243",
    "sg:province":"Aargau",
    "wof:name":"Kessler J\u00fcrg",
    "wof:placetype":"venue"
},
  "geometry": {"coordinates":[8.8663730621,47.1926956177],"type":"Point"}
}