{
  "type": "Feature",
  "properties": {
    "iso:country":"CH",
    "sg:address":"B\u00fcrerfeld 2",
    "sg:city":"Oberb\u00fcren",
    "sg:orig_category":"Grosshandel mit Bekleidung Grosshandel mit Textilien",
    "sg:phone":"+41 18216600",
    "sg:postcode":"9245",
    "sg:province":"St. Gallen",
    "wof:name":"Bosshard Emil Ag",
    "wof:placetype":"venue"
},
  "geometry": {"coordinates":[8.6412239075,47.3938293457],"type":"Point"}
}