{
  "type": "Feature",
  "properties": {
    "iso:country":"CH",
    "sg:address":"Cantonale Via",
    "sg:city":"Camorino",
    "sg:orig_category":"RESTAURANTS: TEA-ROOMS",
    "sg:postcode":"6528",
    "sg:province":"Ticino",
    "wof:name":"Gedema Sa",
    "wof:placetype":"venue"
},
  "geometry": {"coordinates":[9.0069608688,46.1635017395],"type":"Point"}
}