{
  "type": "Feature",
  "properties": {
    "iso:country":"CH",
    "sg:address":"Crausa Route 35",
    "sg:city":"Lugnorre",
    "sg:orig_category":"Allgemeiner Hoch U Tiefbau",
    "sg:phone":"+41 79 635 18 67",
    "sg:postcode":"1789",
    "sg:province":"Fribourg",
    "wof:name":"Entreprise Turuani Sa Payerne, Succursale De Lugnorre",
    "wof:placetype":"venue"
},
  "geometry": {"coordinates":[7.082371,46.947933],"type":"Point"}
}