{
  "type": "Feature",
  "properties": {
    "iso:country":"CH",
    "sg:address":"Dumont Rue Etienne- 14 1204 Gen\u00e8ve. Postfach",
    "sg:city":"Gen\u00e8ve",
    "sg:orig_category":"Wirtschaftspr\u00fcfung, Steuerberatung U Treuhand",
    "sg:phone":"+41 79 632 20 79",
    "sg:postcode":"1204",
    "sg:province":"Gen\u00e8ve",
    "wof:name":"Alrevis Treuhand Ag",
    "wof:placetype":"venue"
},
  "geometry": {"coordinates":[9.0469112396,47.4630699158],"type":"Point"}
}