{
  "type": "Feature",
  "properties": {
    "iso:country":"CH",
    "sg:address":"Rue Du Perron",
    "sg:city":"Coppet",
    "sg:orig_category":"Wirtschaftspr\u00fcfung, Steuerberatung U Treuhand",
    "sg:phone":"+41 22 776 13 86",
    "sg:postcode":"1296",
    "sg:province":"Vaud",
    "wof:name":"Wenger Nicolas.",
    "wof:placetype":"venue"
},
  "geometry": {"coordinates":[6.1922750473,46.316368103],"type":"Point"}
}