{
  "type": "Feature",
  "properties": {
    "iso:country":"CH",
    "sg:address":"Glaubtenstrasse 27",
    "sg:city":"Z\u00fcrich",
    "sg:orig_category":"Grosshandel mit Nahrungsmitteln, Getr\u00e4nken U Tabakwaren Grosshandel mit Nahrungsmitteln, Getr\u00e4nken U",
    "sg:phone":"+41 13713050",
    "sg:postcode":"8046",
    "sg:province":"Z\u00fcrich",
    "wof:name":"Ermitil Gmbh",
    "wof:placetype":"venue"
},
  "geometry": {"coordinates":[8.5169448853,47.4125137329],"type":"Point"}
}