{
  "type": "Feature",
  "properties": {
    "iso:country":"CH",
    "sg:address":"Baselstrasse 26",
    "sg:city":"Dagmersellen",
    "sg:orig_category":"Detailhandel mit Waren verschiedener Art, Hauptrichtung Nahrungsmittel",
    "sg:phone":"+41 62 756 12 45",
    "sg:postcode":"6252",
    "sg:province":"Luzern",
    "wof:name":"Coop Center Wiggertal",
    "wof:placetype":"venue"
},
  "geometry": {"coordinates":[7.9865818024,47.2150039673],"type":"Point"}
}