{
  "type": "Feature",
  "properties": {
    "iso:country":"CH",
    "sg:address":"Rouges-terres Route Des 21 2068 Hauterive. Postfach",
    "sg:city":"Hauterive",
    "sg:orig_category":"Elektrizit\u00e4tsversorgung",
    "sg:postcode":"2068",
    "sg:province":"Neuch\u00e2tel",
    "wof:name":"Elektra Abtwil",
    "wof:placetype":"venue"
},
  "geometry": {"coordinates":[8.3526887894,47.1731681824],"type":"Point"}
}