{
  "type": "Feature",
  "properties": {
    "iso:country":"CH",
    "sg:address":"Chemin De Maisonneuve 9 1219 Ch\u00e2telaine Case Postale 7",
    "sg:city":"Ch\u00e2telaine",
    "sg:classifiers":[
        {
            "category":"Manufacturing",
            "subcategory":"Metals",
            "type":"Manufacturing & Wholesale Goods"
        }
    ],
    "sg:phone":"+41 79 626 51 45",
    "sg:postcode":"1219",
    "sg:province":"Gen\u00e8ve",
    "sg:tags":[
        "u",
        "leichtmetallbau",
        "stahl"
    ],
    "wof:name":"Auporta Sa",
    "wof:placetype":"venue"
},
  "geometry": {"coordinates":[6.1122522354,46.2122497559],"type":"Point"}
}