{
  "type": "Feature",
  "properties": {
    "addr:full":"Sonnhalde 47 Hildisrieden Luzern 6024",
    "addr:housenumber":"47",
    "addr:postcode":"6024",
    "addr:street":"Sonnhalde",
    "iso:country":"CH",
    "sg:address":"Sonnhalde 47",
    "sg:city":"Hildisrieden",
    "sg:orig_category":"Bau von Strassen, Sportanlagen U Bahnverkehrsstrecken",
    "sg:phone":"+41 41 210 31 16",
    "sg:postcode":"6024",
    "sg:province":"Luzern",
    "wof:name":"Tharo Ag",
    "wof:placetype":"venue"
},
  "geometry": {"coordinates":[8.221669,47.150707],"type":"Point"}
}