{
  "type": "Feature",
  "properties": {
    "addr:full":"Le S\u00e9pey Vaud 1863",
    "addr:postcode":"1863",
    "iso:country":"CH",
    "sg:city":"Le S\u00e9pey",
    "sg:classifiers":[
        {
            "category":"Banks & Credit Unions",
            "subcategory":"Bank",
            "type":"Services"
        }
    ],
    "sg:phone":"+41 24 491 14 52",
    "sg:postcode":"1863",
    "sg:province":"Vaud",
    "wof:name":"Raiffeisen",
    "wof:placetype":"venue"
},
  "geometry": {"coordinates":[7.053485,46.361645],"type":"Point"}
}