{
  "type": "Feature",
  "properties": {
    "iso:country":"CH",
    "sg:address":"1638",
    "sg:city":"Morlon",
    "sg:orig_category":"Stukkateurgewerbe, Gipserei U Verputzerei",
    "sg:postcode":"1638",
    "sg:province":"Fribourg",
    "wof:name":"Pecoraro Giannino Pl\u00e2tre Sa",
    "wof:placetype":"venue"
},
  "geometry": {"coordinates":[7.0896701813,46.624168396],"type":"Point"}
}