{
  "type": "Feature",
  "properties": {
    "iso:country":"CH",
    "sg:address":"Weinfelder Strasse 30a",
    "sg:city":"Amriswil",
    "sg:orig_category":"Kosmetikinstitute",
    "sg:phone":"+41 71 411 43 43",
    "sg:postcode":"8580",
    "sg:province":"Thurgau",
    "wof:name":"Sue Cosmetics",
    "wof:placetype":"venue"
},
  "geometry": {"coordinates":[9.2937164307,47.5453834534],"type":"Point"}
}