{
  "type": "Feature",
  "properties": {
    "iso:country":"CH",
    "sg:address":"Nordstrasse 1",
    "sg:city":"Chur",
    "sg:orig_category":"Arztpraxen",
    "sg:phone":"+41 81 250 65 55",
    "sg:postcode":"7000",
    "sg:province":"Graubunden",
    "wof:name":"Dr.med.elisabeth K. Waldeck Spezial\u00e4rztin Fmh",
    "wof:placetype":"venue"
},
  "geometry": {"coordinates":[9.52688,46.854729],"type":"Point"}
}