{
  "type": "Feature",
  "properties": {
    "iso:country":"CH",
    "sg:address":"Weidackerstrasse 3",
    "sg:city":"Oberb\u00fcren",
    "sg:orig_category":"Detailhandel mit Getr\u00e4nken",
    "sg:phone":"+41 71 951 46 75",
    "sg:postcode":"9245",
    "sg:province":"St. Gallen",
    "wof:name":"Richard Metzger Getr\u00e4nke",
    "wof:placetype":"venue"
},
  "geometry": {"coordinates":[9.1631345749,47.4551773071],"type":"Point"}
}