{
  "type": "Feature",
  "properties": {
    "iso:country":"CH",
    "sg:address":"Seestrasse 325 8038 Z\u00fcrich. Postfach",
    "sg:city":"Z\u00fcrich",
    "sg:orig_category":"Allgemeiner Hoch U Tiefbau",
    "sg:postcode":"8038",
    "sg:province":"Z\u00fcrich",
    "wof:name":"Pfister Ag Bauunternehmung Z\u00fcrich",
    "wof:placetype":"venue"
},
  "geometry": {"coordinates":[8.532936,47.347832],"type":"Point"}
}