{
  "type": "Feature",
  "properties": {
    "iso:country":"CH",
    "sg:address":"Maulbeerstrasse 63",
    "sg:city":"Basel",
    "sg:orig_category":"Sonstige mit der Informatik verbundene T\u00e4tigkeiten",
    "sg:phone":"+41 61 692 76 15",
    "sg:postcode":"4058",
    "sg:province":"Basel-Stadt",
    "wof:name":"Peeko Huynh Co",
    "wof:placetype":"venue"
},
  "geometry": {"coordinates":[7.6029748917,47.567855835],"type":"Point"}
}