{
  "type": "Feature",
  "properties": {
    "iso:country":"CH",
    "sg:address":"General-dufour-strasse 7",
    "sg:city":"Biel/bienne",
    "sg:classifiers":[
        {
            "category":"Restaurant",
            "type":"Food & Drink"
        }
    ],
    "sg:phone":"+41 32 323 23 81",
    "sg:postcode":"2502",
    "sg:province":"Bern",
    "wof:name":"Bigg's Restaurant",
    "wof:placetype":"venue"
},
  "geometry": {"coordinates":[7.2464852333,47.1394920349],"type":"Point"}
}