{
  "type": "Feature",
  "properties": {
    "iso:country":"CH",
    "sg:address":"H\u00f6lli 20",
    "sg:city":"Othmarsingen",
    "sg:orig_category":"Bauschreinerei Innenausbau",
    "sg:phone":"+41 62 896 12 10",
    "sg:postcode":"5504",
    "sg:province":"Aargau",
    "wof:name":"H. & H. Binder M\u00f6bel Und Innenausbau",
    "wof:placetype":"venue"
},
  "geometry": {"coordinates":[8.21831,47.403118],"type":"Point"}
}