{
  "type": "Feature",
  "properties": {
    "iso:country":"CH",
    "sg:address":"Barozzo Via",
    "sg:city":"Besazio",
    "sg:orig_category":"Elektroinstallation",
    "sg:postcode":"6863",
    "sg:province":"Ticino",
    "wof:name":"Enco-electric Sagl",
    "wof:placetype":"venue"
},
  "geometry": {"coordinates":[8.9626159668,45.8715019226],"type":"Point"}
}