{
  "type": "Feature",
  "properties": {
    "iso:country":"CH",
    "sg:address":"Landorfstrasse 8",
    "sg:city":"K\u00f6niz",
    "sg:orig_category":"Instandhaltung U Reparatur von Automobilen",
    "sg:postcode":"3098",
    "sg:province":"Bern",
    "wof:name":"Carosserie Zbinden B.",
    "wof:placetype":"venue"
},
  "geometry": {"coordinates":[7.4132370949,46.923084259],"type":"Point"}
}