{
  "type": "Feature",
  "properties": {
    "iso:country":"CH",
    "sg:address":"Z\u00fcrcherstrasse 61",
    "sg:city":"Sargans",
    "sg:orig_category":"Grosshandel mit Nahrungsmitteln, Getr\u00e4nken U Tabakwaren ohne ausgepr\u00e4gten Schwerpunkt",
    "sg:phone":"+41 71 622 56 68",
    "sg:postcode":"7320",
    "sg:province":"St. Gallen",
    "wof:name":"Lebensmittel Da Caruso Inhaber Caruso Tindaro",
    "wof:placetype":"venue"
},
  "geometry": {"coordinates":[9.1381845474,47.5666694641],"type":"Point"}
}