{
  "type": "Feature",
  "properties": {
    "addr:full":"Unterer Rheinweg 56 Basel Basel-Stadt 4057",
    "addr:housenumber":"56",
    "addr:postcode":"4057",
    "addr:street":"Unterer Rheinweg",
    "iso:country":"CH",
    "sg:address":"Unterer Rheinweg 56",
    "sg:city":"Basel",
    "sg:orig_category":"Architekturb\u00fcros",
    "sg:phone":"+41 61 272 27 37",
    "sg:postcode":"4057",
    "sg:province":"Basel-Stadt",
    "wof:name":"Wilfrid & Katharina Steib Architekturb\u00fcro",
    "wof:placetype":"venue"
},
  "geometry": {"coordinates":[7.587586,47.565018],"type":"Point"}
}