{
  "type": "Feature",
  "properties": {
    "iso:country":"CH",
    "sg:address":"Fabrikstrasse 2",
    "sg:city":"Kaltbrunn",
    "sg:orig_category":"Wirtschaftspr\u00fcfung, Steuerberatung U Treuhand",
    "sg:phone":"+41 55 292 21 70",
    "sg:postcode":"8722",
    "sg:province":"St. Gallen",
    "wof:name":"Zweifel Treuhand Gmbh",
    "wof:placetype":"venue"
},
  "geometry": {"coordinates":[9.0379285812,47.2071647644],"type":"Point"}
}