{
  "type": "Feature",
  "properties": {
    "iso:country":"CH",
    "sg:address":"Schlossmattweg 8",
    "sg:city":"Zollikofen",
    "sg:orig_category":"Werbeagenturen Werbegrafikateliers",
    "sg:phone":"+41 17130033",
    "sg:postcode":"3052",
    "sg:province":"Bern",
    "wof:name":"Atelier Schutzbach Ag Werbung & Grafik",
    "wof:placetype":"venue"
},
  "geometry": {"coordinates":[8.5360240936,47.2945404053],"type":"Point"}
}