{
  "type": "Feature",
  "properties": {
    "iso:country":"CH",
    "sg:address":"Hof 15",
    "sg:city":"Gommiswald",
    "sg:orig_category":"Autolackierereien",
    "sg:phone":"+41 55 280 59 19",
    "sg:postcode":"8737",
    "sg:province":"St. Gallen",
    "wof:name":"Claudio B\u00fctler Autospritzwerk",
    "wof:placetype":"venue"
},
  "geometry": {"coordinates":[9.0207796097,47.2341651917],"type":"Point"}
}