{
  "type": "Feature",
  "properties": {
    "iso:country":"CH",
    "sg:address":"Laurenzenvorstadt 131",
    "sg:city":"Aarau",
    "sg:orig_category":"Herstellung von Schmuck, Gold U Silberschmiedwaren",
    "sg:phone":"+41 62 824 16 41",
    "sg:postcode":"5000",
    "sg:province":"Aargau",
    "wof:name":"Hans Haberstich Vergolderei & Rahmenatelier",
    "wof:placetype":"venue"
},
  "geometry": {"coordinates":[8.0544834137,47.3934288025],"type":"Point"}
}