{
  "type": "Feature",
  "properties": {
    "iso:country":"CH",
    "sg:address":"Moulins Rue Des 51",
    "sg:city":"Neuch\u00e2tel",
    "sg:orig_category":"Unclassifiable Establishments",
    "sg:postcode":"2000",
    "sg:province":"Neuch\u00e2tel",
    "wof:name":"Si Cr\u00eatets 82 Sa",
    "wof:placetype":"venue"
},
  "geometry": {"coordinates":[6.8282241821,47.1015625],"type":"Point"}
}