{
  "type": "Feature",
  "properties": {
    "iso:country":"CH",
    "sg:address":"Hagr\u00f6sliweg 28 A 3612 Steffisburg. Postfach",
    "sg:city":"Zollbr\u00fcck",
    "sg:orig_category":"RESTAURANTS: TEA-ROOMS",
    "sg:postcode":"3436",
    "sg:province":"Bern",
    "wof:name":"Lehner Tea Room Gmbh",
    "wof:placetype":"venue"
},
  "geometry": {"coordinates":[7.6388850212,46.7808609009],"type":"Point"}
}