{
  "type": "Feature",
  "properties": {
    "iso:country":"CH",
    "sg:address":"Hauptstrasse 22",
    "sg:city":"Koppigen",
    "sg:orig_category":"Herstellung von Frucht U Gem\u00fcses\u00e4ften Herstellung von Obst U Fruchtweinen",
    "sg:phone":"+41 34 413 11 77",
    "sg:postcode":"3425",
    "sg:province":"Bern",
    "wof:name":"Wy Vom Wyh\u00fcsli Ag",
    "wof:placetype":"venue"
},
  "geometry": {"coordinates":[7.6058630943,47.1318626404],"type":"Point"}
}