{
  "type": "Feature",
  "properties": {
    "iso:country":"CH",
    "sg:address":"Via Clem.maraini 18",
    "sg:city":"Lugano",
    "sg:orig_category":"Tierheime",
    "sg:phone":"+41 32 926 51 93",
    "sg:postcode":"6900",
    "sg:province":"Ticino",
    "wof:name":"Fran\u00e7oise Duperthuis Pension Pour Chats",
    "wof:placetype":"venue"
},
  "geometry": {"coordinates":[6.8141617775,47.0932540894],"type":"Point"}
}