{
  "type": "Feature",
  "properties": {
    "iso:country":"CH",
    "sg:address":"Rue De Neuch\u00e2tel 42",
    "sg:city":"Yverdon-les-bains",
    "sg:orig_category":"Detailhandel mit Waren verschiedener Art, Hauptrichtung Nahrungsmittel",
    "sg:phone":"+41 24 425 01 35",
    "sg:postcode":"1400",
    "sg:province":"Vaud",
    "wof:name":"Denner Top Superdiscount",
    "wof:placetype":"venue"
},
  "geometry": {"coordinates":[6.6348800659,46.7831764221],"type":"Point"}
}