{
  "type": "Feature",
  "properties": {
    "addr:full":"1911 Ovronnaz Valais 1911",
    "addr:housenumber":"1911",
    "addr:postcode":"1911",
    "addr:street":"Ovronnaz Valais",
    "iso:country":"CH",
    "sg:address":"1911",
    "sg:city":"Ovronnaz",
    "sg:orig_category":"Detailhandel an Verkaufsst\u00e4nden U auf M\u00e4rkten",
    "sg:phone":"+41 27 306 34 57",
    "sg:postcode":"1911",
    "sg:province":"Valais",
    "wof:name":"Bazar D'ovrannaz Claude Luisier",
    "wof:placetype":"venue"
},
  "geometry": {"coordinates":[7.17272,46.197411],"type":"Point"}
}