{
  "type": "Feature",
  "properties": {
    "iso:country":"CH",
    "sg:address":"1982 Euseigne Case Postale 4134",
    "sg:city":"Euseigne",
    "sg:orig_category":"Zimmerei, Dachdeckerei, Bauspenglerei U Abdichtung",
    "sg:phone":"+41 79 344 66 68",
    "sg:postcode":"1982",
    "sg:province":"Valais",
    "wof:name":"Gebr. Bissig Holzbau",
    "wof:placetype":"venue"
},
  "geometry": {"coordinates":[8.6348848343,46.8676376343],"type":"Point"}
}