{
  "type": "Feature",
  "properties": {
    "iso:country":"CH",
    "sg:address":"Obstgartenstrasse 6 8472 Seuzach. Postfach",
    "sg:city":"Seuzach",
    "sg:orig_category":"Grosshandel mit Holz U Baustoffen Sonstiger Detailhandel mit Metallwaren, Anstrichmitteln, Glaswaren",
    "sg:phone":"+41 52 335 16 72",
    "sg:postcode":"8472",
    "sg:province":"Z\u00fcrich",
    "wof:name":"Mohr Bau Und Hobbycenter Gmbh Bau, Hobby, Bastelartikel; Handel, Verkauf",
    "wof:placetype":"venue"
},
  "geometry": {"coordinates":[8.73458004,47.5360488892],"type":"Point"}
}