{
  "type": "Feature",
  "properties": {
    "iso:country":"CH",
    "sg:address":"Chemin Wilhelm-kutter 35",
    "sg:city":"Biel/bienne",
    "sg:orig_category":"Grosshandel mit sonstigen Gebrauchs U Verbrauchsg\u00fctern",
    "sg:postcode":"2500",
    "sg:province":"Bern",
    "wof:name":"Service De R\u00e9parations Photo-av Vermot-petit-outhenin M.",
    "wof:placetype":"venue"
},
  "geometry": {"coordinates":[7.2567138672,47.1255378723],"type":"Point"}
}