{
  "type": "Feature",
  "properties": {
    "iso:country":"CH",
    "sg:address":"Rotrischstrasse 9",
    "sg:city":"Oberrohrdorf",
    "sg:orig_category":"Architekturb\u00fcros",
    "sg:phone":"+41 56 496 62 00",
    "sg:postcode":"5452",
    "sg:province":"Aargau",
    "wof:name":"Freddy Seyfang Bauausf\u00fchrung & Architektur",
    "wof:placetype":"venue"
},
  "geometry": {"coordinates":[8.311888,47.427811],"type":"Point"}
}