{
  "type": "Feature",
  "properties": {
    "iso:country":"CH",
    "sg:address":"Untere Staffel",
    "sg:city":"Spl\u00fcgen",
    "sg:orig_category":"Landw. Genossenschaften Alpgenossenschaften",
    "sg:phone":"+41 81 664 11 74",
    "sg:postcode":"7435",
    "sg:province":"Graubunden",
    "wof:name":"Donatzalpgenossenschaft",
    "wof:placetype":"venue"
},
  "geometry": {"coordinates":[9.3164844513,46.5507087708],"type":"Point"}
}