{
  "type": "Feature",
  "properties": {
    "iso:country":"CH",
    "sg:address":"Champoussin-village",
    "sg:city":"Val-d'illiez",
    "sg:orig_category":"Vermietung U Verpachtung von eigenen Immobilien",
    "sg:postcode":"1873",
    "sg:province":"Valais",
    "wof:name":"Location Service - Eggen",
    "wof:placetype":"venue"
},
  "geometry": {"coordinates":[6.8638601303,46.2090797424],"type":"Point"}
}