{
  "type": "Feature",
  "properties": {
    "iso:country":"CH",
    "sg:address":"Sonnmattstrasse 1737 9122 Mogelsberg. Postfach",
    "sg:city":"Mogelsberg",
    "sg:orig_category":"Unclassifiable Establishments",
    "sg:postcode":"9122",
    "sg:province":"St. Gallen",
    "wof:name":"Scanzi's Piatti D'oro, Nachfolgerin Silvia Scanzi",
    "wof:placetype":"venue"
},
  "geometry": {"coordinates":[9.1361398697,47.3594894409],"type":"Point"}
}