{
  "type": "Feature",
  "properties": {
    "addr:full":"5637 Wallenschwil Aargau 5637",
    "addr:postcode":"5637;5637",
    "addr:street":"Wallenschwil",
    "iso:country":"CH",
    "sg:address":"5637",
    "sg:city":"Wallenschwil",
    "sg:orig_category":"Allgemeiner Gartenbau",
    "sg:phone":"+41 56 668 16 26",
    "sg:postcode":"5637",
    "sg:province":"Aargau",
    "wof:name":"Wolfisberg Baumschulen",
    "wof:placetype":"venue"
},
  "geometry": {"coordinates":[8.36559,47.23814],"type":"Point"}
}