{
  "type": "Feature",
  "properties": {
    "addr:full":"Versonnex Rue Fran\u00e7ois- 19 1207 Gen\u00e8ve. Postfach Gen\u00e8ve Gen\u00e8ve 1207",
    "addr:housenumber":"versonnex;19",
    "addr:postcode":"1207;postfach;1207",
    "addr:street":"Rue Franc\u0327Ois",
    "iso:country":"CH",
    "sg:address":"Versonnex Rue Fran\u00e7ois- 19 1207 Gen\u00e8ve. Postfach",
    "sg:city":"Gen\u00e8ve",
    "sg:orig_category":"Detailhandel mit B\u00fcchern, Zeitungen, Schreib U Papeteriewaren",
    "sg:postcode":"1207",
    "sg:province":"Gen\u00e8ve",
    "wof:name":"Librairie Galerie Keller, Ferri Keller, Krauer & Co",
    "wof:placetype":"venue"
},
  "geometry": {"coordinates":[6.156563,46.20282],"type":"Point"}
}