{
  "type": "Feature",
  "properties": {
    "iso:country":"CH",
    "sg:address":"Bahnhofplatz 10 7000 Chur. Postfach",
    "sg:city":"Chur",
    "sg:classifiers":[
        {
            "category":"Insurance",
            "subcategory":"Insurance Agent",
            "type":"Services"
        }
    ],
    "sg:phone":"+41 81 253 54 34",
    "sg:postcode":"7002",
    "sg:province":"Graubunden",
    "sg:tags":[
        "versicherungsagenturen",
        "-broker"
    ],
    "wof:name":"Winterthur-versicherungen Agentur City",
    "wof:placetype":"venue"
},
  "geometry": {"coordinates":[9.5294218063,46.852722168],"type":"Point"}
}