{
  "type": "Feature",
  "properties": {
    "iso:country":"CH",
    "sg:address":"Rue Des Granges 8",
    "sg:city":"Aubonne",
    "sg:orig_category":"Sonstige mit der Informatik verbundene T\u00e4tigkeiten",
    "sg:phone":"+41 21 808 73 24",
    "sg:postcode":"1170",
    "sg:province":"Vaud",
    "wof:name":"Laurent Serge.",
    "wof:placetype":"venue"
},
  "geometry": {"coordinates":[6.3888731003,46.4963951111],"type":"Point"}
}