{
  "type": "Feature",
  "properties": {
    "addr:full":"Industriestrasse 29 D\u00e4llikon Z\u00fcrich 8108",
    "addr:housenumber":"29",
    "addr:postcode":"8108",
    "addr:street":"Industriestrasse;Zuerich",
    "iso:country":"CH",
    "sg:address":"Industriestrasse 29",
    "sg:city":"D\u00e4llikon",
    "sg:orig_category":"Architektur U Ingenieurb\u00fcros",
    "sg:phone":"+41 18442342",
    "sg:postcode":"8108",
    "sg:province":"Z\u00fcrich",
    "wof:name":"Refka Engineering, K\u00e4gi Erich A.",
    "wof:placetype":"venue"
},
  "geometry": {"coordinates":[8.409753,47.443375],"type":"Point"}
}