{
  "type": "Feature",
  "properties": {
    "iso:country":"CH",
    "sg:address":"Via Birreria 31",
    "sg:city":"Bellinzona",
    "sg:orig_category":"Detailhandel mit Getr\u00e4nken Grosshandel mit Getr\u00e4nken",
    "sg:phone":"+41 91 826 22 19",
    "sg:postcode":"6503",
    "sg:province":"Ticino",
    "wof:name":"Bibite Scimonelli Sagl",
    "wof:placetype":"venue"
},
  "geometry": {"coordinates":[9.0088357925,46.1956558228],"type":"Point"}
}