{
  "type": "Feature",
  "properties": {
    "iso:country":"CH",
    "sg:address":"H\u00fcbeli",
    "sg:city":"Unterlangenegg",
    "sg:orig_category":"Herstellung von Konstruktionsteilen, Fertigbauteilen U Ausbauelementen aus Holz Innenausbau",
    "sg:phone":"+41 71 245 25 45",
    "sg:postcode":"3614",
    "sg:province":"Bern",
    "wof:name":"Peretti Markus Schreinerei",
    "wof:placetype":"venue"
},
  "geometry": {"coordinates":[9.3936929703,47.4332427979],"type":"Point"}
}