{
  "type": "Feature",
  "properties": {
    "iso:country":"CH",
    "sg:address":"Tellstrasse 16a",
    "sg:city":"Winterthur",
    "sg:orig_category":"Sonstiger spezialisierter Hoch U Tiefbau",
    "sg:phone":"+41 52 213 19 10",
    "sg:postcode":"8400",
    "sg:province":"Z\u00fcrich",
    "wof:name":"Marena Giovanni, Generalunternehmen",
    "wof:placetype":"venue"
},
  "geometry": {"coordinates":[8.7200727463,47.5021705627],"type":"Point"}
}