{
  "type": "Feature",
  "properties": {
    "iso:country":"CH",
    "sg:address":"Bitzighofen",
    "sg:city":"Sarnen",
    "sg:classifiers":[
        {
            "category":"Travel",
            "subcategory":"Travel Agent",
            "type":"Entertainment"
        }
    ],
    "sg:phone":"+41 4141666575",
    "sg:postcode":"6060",
    "sg:province":"Obwalden",
    "wof:name":"Wirz Travel",
    "wof:placetype":"venue"
},
  "geometry": {"coordinates":[8.2475996017,46.9025917053],"type":"Point"}
}