{
  "type": "Feature",
  "properties": {
    "iso:country":"CH",
    "sg:address":"4629",
    "sg:city":"Fulenbach",
    "sg:orig_category":"Schulpflegen",
    "sg:phone":"+41 62 926 35 04",
    "sg:postcode":"4629",
    "sg:province":"Solothurn",
    "wof:name":"Schulkommission Der Gemeinde Fulenbach",
    "wof:placetype":"venue"
},
  "geometry": {"coordinates":[7.8317699432,47.280380249],"type":"Point"}
}