{
  "type": "Feature",
  "properties": {
    "iso:country":"CH",
    "sg:address":"St. Galler Strasse 7",
    "sg:city":"Engelburg",
    "sg:orig_category":"Detailhandel mit Fleisch U Fleischwaren Grosshandel mit Fleisch U Fleischwaren",
    "sg:phone":"+41 71 220 85 49",
    "sg:postcode":"9032",
    "sg:province":"St. Gallen",
    "wof:name":"Lila Handels Gmbh",
    "wof:placetype":"venue"
},
  "geometry": {"coordinates":[9.3417110443,47.4437980652],"type":"Point"}
}