{
  "type": "Feature",
  "properties": {
    "iso:country":"CH",
    "sg:address":"Im Staubenweidli 21",
    "sg:city":"W\u00e4denswil",
    "sg:orig_category":"Unclassifiable Establishments",
    "sg:postcode":"8820",
    "sg:province":"Z\u00fcrich",
    "wof:name":"Haltiner-wanke W.",
    "wof:placetype":"venue"
},
  "geometry": {"coordinates":[8.686923027,47.2211952209],"type":"Point"}
}