{
  "type": "Feature",
  "properties": {
    "iso:country":"CH",
    "sg:address":"Kirchlindachstrasse 98 3052 Zollikofen. Postfach 787",
    "sg:city":"Zollikofen",
    "sg:orig_category":"Vermietung U Verpachtung von eigenen Immobilien Vermittlung von Immobilien",
    "sg:phone":"+41 31 911 07 75",
    "sg:postcode":"3052",
    "sg:province":"Bern",
    "wof:name":"Zimmermann + Imhof Generalunternehmung Ag",
    "wof:placetype":"venue"
},
  "geometry": {"coordinates":[7.4424262047,47.003742218],"type":"Point"}
}