{
  "type": "Feature",
  "properties": {
    "iso:country":"CH",
    "sg:address":"Industriestrasse 13",
    "sg:city":"Kriens",
    "sg:classifiers":[
        {
            "category":"Internet Cafe",
            "subcategory":"None",
            "type":"Food & Drink"
        }
    ],
    "sg:phone":"+41 41 787 33 50",
    "sg:postcode":"6010",
    "sg:province":"Luzern",
    "sg:tags":[
        "datenverarbeitungsdienste",
        "provider"
    ],
    "wof:name":"Daba Informatik",
    "wof:placetype":"venue"
},
  "geometry": {"coordinates":[8.35242,47.173382],"type":"Point"}
}