{
  "type": "Feature",
  "properties": {
    "addr:full":"Eichenstrasse 20 Basel Basel-Stadt 4054",
    "addr:housenumber":"20",
    "addr:postcode":"4054",
    "addr:street":"Eichenstrasse",
    "iso:country":"CH",
    "sg:address":"Eichenstrasse 20",
    "sg:city":"Basel",
    "sg:orig_category":"Arztpraxen",
    "sg:phone":"+41 61 302 28 00",
    "sg:postcode":"4054",
    "sg:province":"Basel-Stadt",
    "wof:name":"Prof.dr.med. Alfonso Almendral Spezialarzt Fmh",
    "wof:placetype":"venue"
},
  "geometry": {"coordinates":[7.570167,47.556129],"type":"Point"}
}