{
  "type": "Feature",
  "properties": {
    "iso:country":"CH",
    "sg:address":"Hammerstrasse 81 8032 Z\u00fcrich. Postfach 1331",
    "sg:city":"Z\u00fcrich",
    "sg:orig_category":"Buchverlag Verlagsgewerbe",
    "sg:phone":"+41 32 677 50 50",
    "sg:postcode":"8032",
    "sg:province":"Z\u00fcrich",
    "wof:name":"Proinfo Ag",
    "wof:placetype":"venue"
},
  "geometry": {"coordinates":[7.524811,47.169815],"type":"Point"}
}