{
  "type": "Feature",
  "properties": {
    "iso:country":"CH",
    "sg:address":"Chesslerstrasse 4",
    "sg:city":"Oberstammheim",
    "sg:orig_category":"Unternehmensberatung",
    "sg:postcode":"8477",
    "sg:province":"Z\u00fcrich",
    "wof:name":"Disona Gmbh",
    "wof:placetype":"venue"
},
  "geometry": {"coordinates":[8.7969827652,47.6316223145],"type":"Point"}
}