{
  "type": "Feature",
  "properties": {
    "iso:country":"CH",
    "sg:address":"Ibelweg 18a 6300 Zug. Postfach",
    "sg:city":"Zug",
    "sg:orig_category":"Unternehmensberatung",
    "sg:phone":"+41 79 282 19 22",
    "sg:postcode":"6300",
    "sg:province":"Zug",
    "wof:name":"Nachbur-consulting, Rolf Nachbur Ing. Htl/stv",
    "wof:placetype":"venue"
},
  "geometry": {"coordinates":[8.2868509293,47.4918632507],"type":"Point"}
}