{
  "type": "Feature",
  "properties": {
    "iso:country":"CH",
    "sg:address":"Dorf 35",
    "sg:city":"Roggliswil",
    "sg:orig_category":"Detailhandel mit Waren verschiedener Art, Hauptrichtung Nahrungsmittel",
    "sg:phone":"+41 62 754 11 36",
    "sg:postcode":"6265",
    "sg:province":"Luzern",
    "wof:name":"Stephan Winterberg Lebensmittel",
    "wof:placetype":"venue"
},
  "geometry": {"coordinates":[7.8859119415,47.2110671997],"type":"Point"}
}