{
  "type": "Feature",
  "properties": {
    "addr:full":"8475 Ossingen Z\u00fcrich 8475",
    "addr:postcode":"8475;8475",
    "iso:country":"CH",
    "sg:address":"8475",
    "sg:city":"Ossingen",
    "sg:classifiers":[
        {
            "category":"Education",
            "subcategory":"Library",
            "type":"Public Place"
        }
    ],
    "sg:postcode":"8475",
    "sg:province":"Z\u00fcrich",
    "sg:tags":[
        "u",
        "bibliotheken",
        "archive"
    ],
    "wof:name":"Volksbibliothek",
    "wof:placetype":"venue"
},
  "geometry": {"coordinates":[9.00563,47.607639],"type":"Point"}
}