{
  "type": "Feature",
  "properties": {
    "iso:country":"CH",
    "sg:address":"Zullwilerstrasse 35",
    "sg:city":"Nunningen",
    "sg:orig_category":"Malerei-Gipserei Stukkateurgewerbe, Gipserei U Verputzerei",
    "sg:phone":"+41 61 791 00 28",
    "sg:postcode":"4208",
    "sg:province":"Solothurn",
    "wof:name":"H\u00e4nggi Alfons Gmbh Gipserarbeiten",
    "wof:placetype":"venue"
},
  "geometry": {"coordinates":[7.6151309013,47.3916816711],"type":"Point"}
}