{
  "type": "Feature",
  "properties": {
    "iso:country":"CH",
    "sg:address":"Liebewilstrasse 77",
    "sg:city":"Th\u00f6rishaus",
    "sg:classifiers":[
        {
            "category":"Banks & Credit Unions",
            "subcategory":"Investment Brokerage",
            "type":"Services"
        }
    ],
    "sg:phone":"+41 31 971 10 53",
    "sg:postcode":"3174",
    "sg:province":"Bern",
    "sg:tags":[
        "joint",
        "sealing"
    ],
    "wof:name":"Ferdinand Thalmann Fugenabdichtungen",
    "wof:placetype":"venue"
},
  "geometry": {"coordinates":[7.3583450317,46.9041595459],"type":"Point"}
}