{
  "type": "Feature",
  "properties": {
    "iso:country":"CH",
    "sg:address":"Route De Vernier 215",
    "sg:city":"Vernier",
    "sg:orig_category":"RESTAURANTS: TEA-ROOMS",
    "sg:postcode":"1214",
    "sg:province":"Gen\u00e8ve",
    "wof:name":"Lovisa Raymond",
    "wof:placetype":"venue"
},
  "geometry": {"coordinates":[7.020275116,46.1201057434],"type":"Point"}
}