{
  "type": "Feature",
  "properties": {
    "iso:country":"CH",
    "sg:address":"6515",
    "sg:city":"Gudo",
    "sg:orig_category":"Detailhandel mit Waren verschiedener Art, Hauptrichtung Nahrungsmittel RESTAURANTS: TEA-ROOMS",
    "sg:postcode":"6515",
    "sg:province":"Ticino",
    "wof:name":"Primogusto Gmbh",
    "wof:placetype":"venue"
},
  "geometry": {"coordinates":[8.826458931,47.2300834656],"type":"Point"}
}