{
  "type": "Feature",
  "properties": {
    "addr:full":"Melchnaustrasse 64 Langenthal Bern 4900",
    "addr:housenumber":"64",
    "addr:postcode":"4900",
    "addr:street":"Melchnaustrasse;Bern",
    "iso:country":"CH",
    "sg:address":"Melchnaustrasse 64",
    "sg:city":"Langenthal",
    "sg:orig_category":"Allgemeiner Gartenbau",
    "sg:phone":"+41 71 455 11 84",
    "sg:postcode":"4900",
    "sg:province":"Bern",
    "wof:name":"Rudolf Studer Baumschulen",
    "wof:placetype":"venue"
},
  "geometry": {"coordinates":[9.40159,47.51556],"type":"Point"}
}