{
  "type": "Feature",
  "properties": {
    "iso:country":"CH",
    "sg:address":"Hauptstrasse 65",
    "sg:city":"T\u00e4gerwilen",
    "sg:orig_category":"Detailhandel mit Brot, Back U S\u00fcsswaren",
    "sg:phone":"+41 71 669 22 77",
    "sg:postcode":"8274",
    "sg:province":"Thurgau",
    "wof:name":"Walter Studerus B\u00e4ckerei-konditorei",
    "wof:placetype":"venue"
},
  "geometry": {"coordinates":[9.131463,47.655643],"type":"Point"}
}