{
  "type": "Feature",
  "properties": {
    "iso:country":"CH",
    "sg:address":"Zurich Rue De 19 2504 Biel/bienne. Postfach",
    "sg:city":"Biel/bienne",
    "sg:orig_category":"Dienstleistungen von Beteiligungsgesellschaften",
    "sg:postcode":"2502",
    "sg:province":"Bern",
    "wof:name":"Dop Gestion Fleury Patrick",
    "wof:placetype":"venue"
},
  "geometry": {"coordinates":[7.2911930084,47.1615562439],"type":"Point"}
}