{
  "type": "Feature",
  "properties": {
    "iso:country":"CH",
    "sg:address":"Avenue Eug\u00e8ne Burnand 26",
    "sg:city":"Moudon",
    "sg:orig_category":"Vermietung von Automobilen",
    "sg:postcode":"1510",
    "sg:province":"Vaud",
    "wof:name":"Mobiloc, N\u00f6ding F.",
    "wof:placetype":"venue"
},
  "geometry": {"coordinates":[6.7953867912,46.6626548767],"type":"Point"}
}