{
  "type": "Feature",
  "properties": {
    "iso:country":"CH",
    "sg:address":"Br\u00fcnigstrasse 5",
    "sg:city":"Sachseln",
    "sg:classifiers":[
        {
            "category":"Travel",
            "subcategory":"Hotels & Motels",
            "type":"Entertainment"
        }
    ],
    "sg:phone":"+41 33 849 11 45",
    "sg:postcode":"6072",
    "sg:province":"Obwalden",
    "sg:tags":[
        "hotels",
        "mit",
        "restaurant"
    ],
    "wof:name":"Zurbuchen Ernst",
    "wof:placetype":"venue"
},
  "geometry": {"coordinates":[7.9288029671,46.7170982361],"type":"Point"}
}