{
  "type": "Feature",
  "properties": {
    "iso:country":"CH",
    "sg:address":"Baselstrasse 7",
    "sg:city":"Solothurn",
    "sg:orig_category":"Betrieb U technische Hilfsdienste des Kultur U Unterhaltungswesens",
    "sg:postcode":"4500",
    "sg:province":"Solothurn",
    "wof:name":"Stiftung Neues St\u00e4dtebundtheater",
    "wof:placetype":"venue"
},
  "geometry": {"coordinates":[7.541629,47.209911],"type":"Point"}
}