{
  "type": "Feature",
  "properties": {
    "addr:full":"Muret-fleuri Chexbres Vaud 1071",
    "addr:postcode":"1071",
    "iso:country":"CH",
    "sg:address":"Muret-fleuri",
    "sg:city":"Chexbres",
    "sg:orig_category":"Detailhandel mit Antiquit\u00e4ten U Gebrauchtwaren in Verkaufsr\u00e4umen",
    "sg:postcode":"1071",
    "sg:province":"Vaud",
    "wof:name":"Morel Mme Suzanne",
    "wof:placetype":"venue"
},
  "geometry": {"coordinates":[6.77624,46.482113],"type":"Point"}
}