{
  "type": "Feature",
  "properties": {
    "iso:country":"CH",
    "sg:address":"Rue G\u00e9n.-boinod 17",
    "sg:city":"Aubonne",
    "sg:orig_category":"Chemische Reinigung W\u00e4schereien",
    "sg:phone":"+41 21 808 58 49",
    "sg:postcode":"1170",
    "sg:province":"Vaud",
    "wof:name":"Marie-louise Tille Blanchisserie & Nett.chimique",
    "wof:placetype":"venue"
},
  "geometry": {"coordinates":[6.390959,46.495651],"type":"Point"}
}