{
  "type": "Feature",
  "properties": {
    "iso:country":"CH",
    "sg:address":"Hardstrasse 8604 Volketswil. Postfach",
    "sg:city":"Volketswil",
    "sg:orig_category":"Gewinnung von Kies U Sand Herstellung von Transportbeton",
    "sg:phone":"+41 19473111",
    "sg:postcode":"8604",
    "sg:province":"Z\u00fcrich",
    "wof:name":"Hard Ag",
    "wof:placetype":"venue"
},
  "geometry": {"coordinates":[8.6901216507,47.3889808655],"type":"Point"}
}