{
  "type": "Feature",
  "properties": {
    "iso:country":"CH",
    "sg:address":"Lostorferstrasse 55",
    "sg:city":"Oberg\u00f6sgen",
    "sg:classifiers":[
        {
            "category":"Education",
            "subcategory":"Vocational School",
            "type":"Public Place"
        }
    ],
    "sg:phone":"+41 62 295 28 34",
    "sg:postcode":"4653",
    "sg:province":"Solothurn",
    "sg:tags":[
        "koch-",
        "haushaltschulen"
    ],
    "wof:name":"Haushaltungsschule",
    "wof:placetype":"venue"
},
  "geometry": {"coordinates":[7.9478740692,47.3676376343],"type":"Point"}
}