{
  "type": "Feature",
  "properties": {
    "iso:country":"CH",
    "sg:address":"Rue De L'envol 5",
    "sg:city":"Sion",
    "sg:orig_category":"Herstellung von Drahtwaren Maurerarbeiten",
    "sg:phone":"+41 27 322 61 22",
    "sg:postcode":"1950",
    "sg:province":"Valais",
    "wof:name":"Good Sa Ma\u00e7onnerie & B\u00e9ton Arm\u00e9",
    "wof:placetype":"venue"
},
  "geometry": {"coordinates":[7.3415818214,46.227394104],"type":"Point"}
}