{
  "type": "Feature",
  "properties": {
    "iso:country":"CH",
    "sg:address":"M\u00fcnstergasse 60",
    "sg:city":"Bern",
    "sg:orig_category":"RESTAURANTS: TEA-ROOMS",
    "sg:phone":"+41 71 222 25 10",
    "sg:postcode":"3011",
    "sg:province":"Bern",
    "wof:name":"Restaurant Metzgertor",
    "wof:placetype":"venue"
},
  "geometry": {"coordinates":[9.3747596741,47.4272918701],"type":"Point"}
}