{
  "type": "Feature",
  "properties": {
    "iso:country":"CH",
    "sg:address":"Bettingerstrasse 235",
    "sg:city":"Riehen",
    "sg:orig_category":"Detailhandel mit Metallwaren, Anstrichmitteln, Glaswaren, Bau U Heimwerkerbedarf",
    "sg:phone":"+41 32 846 20 60",
    "sg:postcode":"4125",
    "sg:province":"Basel-Stadt",
    "wof:name":"Kla Instruments Sa",
    "wof:placetype":"venue"
},
  "geometry": {"coordinates":[6.836979866,47.1053962708],"type":"Point"}
}