{
  "type": "Feature",
  "properties": {
    "iso:country":"CH",
    "sg:address":"Wylandstrasse 1",
    "sg:city":"Winterthur",
    "sg:orig_category":"Herstellung von k\u00e4lte U lufttechnischen Erzeugnissen f\u00fcr gewerbliche Zwecke Installation von Heizung",
    "sg:phone":"+41 52 212 92 71",
    "sg:postcode":"8400",
    "sg:province":"Z\u00fcrich",
    "wof:name":"Flach Kurt",
    "wof:placetype":"venue"
},
  "geometry": {"coordinates":[8.7248792648,47.4904594421],"type":"Point"}
}