{
  "type": "Feature",
  "properties": {
    "iso:country":"CH",
    "sg:address":"Dorfstrasse 22a 3324 Hindelbank. Postfach",
    "sg:city":"Hindelbank",
    "sg:orig_category":"Entkalkung, Entrostung, Kalkschutz, Rostschutz",
    "sg:postcode":"3324",
    "sg:province":"Bern",
    "wof:name":"Kalkmeister Team Gmbh Anlagen, Bes. Warmwasseranlagen; Entkalkung Usw",
    "wof:placetype":"venue"
},
  "geometry": {"coordinates":[7.54043293,47.045249939],"type":"Point"}
}