{
  "type": "Feature",
  "properties": {
    "iso:country":"CH",
    "sg:address":"Via Cittadella 9 6600 Locarno Casella Postale 1713",
    "sg:city":"Locarno",
    "sg:classifiers":[
        {
            "category":"Restaurant",
            "type":"Food & Drink"
        }
    ],
    "sg:phone":"+41 91 791 42 61",
    "sg:postcode":"6601",
    "sg:province":"Ticino",
    "wof:name":"Ristorante Centro",
    "wof:placetype":"venue"
},
  "geometry": {"coordinates":[8.7278585434,46.1463546753],"type":"Point"}
}