{
  "type": "Feature",
  "properties": {
    "iso:country":"CH",
    "sg:address":"Burghaldenstrasse 47",
    "sg:city":"Richterswil",
    "sg:orig_category":"Interessenvertretungen",
    "sg:postcode":"8805",
    "sg:province":"Z\u00fcrich",
    "wof:name":"Stiftung Pfl\u00e4gifonds",
    "wof:placetype":"venue"
},
  "geometry": {"coordinates":[8.6998796463,47.2096786499],"type":"Point"}
}