{
  "type": "Feature",
  "properties": {
    "iso:country":"CH",
    "sg:address":"Dufourstrasse 54 4052 Basel. Postfach",
    "sg:city":"Basel",
    "sg:orig_category":"Grosshandel mit chemischen Erzeugnissen Grosshandel mit pharmazeutischen Erzeugnissen",
    "sg:phone":"+41 61 295 25 25",
    "sg:postcode":"4002",
    "sg:province":"Basel-Stadt",
    "wof:name":"Boehringer Ingelheim (schweiz) Gmbh",
    "wof:placetype":"venue"
},
  "geometry": {"coordinates":[7.5952329636,47.5517082214],"type":"Point"}
}