{
  "type": "Feature",
  "properties": {
    "iso:country":"CH",
    "sg:address":"Davesco Soragno",
    "sg:city":"Davesco Soragno",
    "sg:classifiers":[
        {
            "category":"Banks & Credit Unions",
            "subcategory":"Bank",
            "type":"Services"
        }
    ],
    "sg:phone":"+41 91 942 31 34",
    "sg:postcode":"6964",
    "sg:province":"Ticino",
    "wof:name":"Raiffeisen Di Davesco-soragno",
    "wof:placetype":"venue"
},
  "geometry": {"coordinates":[8.98953,46.032558],"type":"Point"}
}