{
  "type": "Feature",
  "properties": {
    "iso:country":"CH",
    "sg:address":"Villa Hlo-bouil 3 3971 Chermignon. Postfach",
    "sg:city":"Chermignon",
    "sg:orig_category":"Allgemeiner Hoch U Tiefbau",
    "sg:postcode":"3971",
    "sg:province":"Valais",
    "wof:name":"Duc Richard, Entreprise De Constructions S\u00e0rl",
    "wof:placetype":"venue"
},
  "geometry": {"coordinates":[7.481699,46.284084],"type":"Point"}
}