{
  "type": "Feature",
  "properties": {
    "iso:country":"CH",
    "sg:address":"Rietbergstrasse 55 9403 Goldach. Postfach 146",
    "sg:city":"Goldach",
    "sg:orig_category":"Verwaltung von Immobilien",
    "sg:phone":"+41 71 841 00 46",
    "sg:postcode":"9403",
    "sg:province":"St. Gallen",
    "wof:name":"Rudolf Kellenberger Treuhandgesellschaft",
    "wof:placetype":"venue"
},
  "geometry": {"coordinates":[9.4760541916,47.4822235107],"type":"Point"}
}