{
  "type": "Feature",
  "properties": {
    "iso:country":"CH",
    "sg:address":"H\u00f6henweg 6",
    "sg:city":"Pratteln",
    "sg:orig_category":"Erschliessung von Grundst\u00fccken",
    "sg:postcode":"4133",
    "sg:province":"Basel-Landschaft",
    "wof:name":"Freie Wohnbaugen.atrium 3",
    "wof:placetype":"venue"
},
  "geometry": {"coordinates":[7.695494175,47.5138931274],"type":"Point"}
}