{
  "type": "Feature",
  "properties": {
    "iso:country":"CH",
    "sg:address":"Seestrasse 19 8805 Richterswil. Postfach",
    "sg:city":"Richterswil",
    "sg:orig_category":"Gemeindeverwaltungen",
    "sg:phone":"+41 52 320 95 00",
    "sg:postcode":"8805",
    "sg:province":"Z\u00fcrich",
    "wof:name":"Gemeindeverwaltung Rickenbach-winterthur",
    "wof:placetype":"venue"
},
  "geometry": {"coordinates":[8.7937240601,47.5510139465],"type":"Point"}
}