{
  "type": "Feature",
  "properties": {
    "iso:country":"CH",
    "sg:address":"Reussstrasse",
    "sg:city":"Gisikon",
    "sg:orig_category":"HOTELS: OHNE RESTAURANT",
    "sg:phone":"+41 41 455 31 31",
    "sg:postcode":"6038",
    "sg:province":"Luzern",
    "wof:name":"Hotel Garni An Der Reuss Tellhof",
    "wof:placetype":"venue"
},
  "geometry": {"coordinates":[8.3978347778,47.1261672974],"type":"Point"}
}