{
  "type": "Feature",
  "properties": {
    "iso:country":"CH",
    "sg:address":"R\u00f6tzmattweg 24",
    "sg:city":"Olten",
    "sg:orig_category":"Detailhandel mit Damenbekleidung Detailhandel mit Herrenbekleidung",
    "sg:phone":"+41 62 212 14 74",
    "sg:postcode":"4600",
    "sg:province":"Solothurn",
    "wof:name":"Luigi Bionda Herren-& Damen-massatelier",
    "wof:placetype":"venue"
},
  "geometry": {"coordinates":[7.8987278938,47.3471679688],"type":"Point"}
}