{
  "type": "Feature",
  "properties": {
    "iso:country":"CH",
    "sg:address":"Luzernstrasse",
    "sg:city":"Huttwil",
    "sg:classifiers":[
        {
            "category":"Travel",
            "subcategory":"Hotels & Motels",
            "type":"Entertainment"
        }
    ],
    "sg:phone":"+41 32 861 23 30",
    "sg:postcode":"4950",
    "sg:province":"Bern",
    "sg:tags":[
        "hotels",
        "mit",
        "restaurant"
    ],
    "wof:name":"Rossetto-mele Myriam",
    "wof:placetype":"venue"
},
  "geometry": {"coordinates":[6.5715141296,46.908290863],"type":"Point"}
}