{
  "type": "Feature",
  "properties": {
    "iso:country":"CH",
    "sg:address":"Dorfstrasse 33 Wangs 7324 Vilters. Postfach",
    "sg:city":"Wangs",
    "sg:orig_category":"Unclassifiable Establishments",
    "sg:postcode":"7323",
    "sg:province":"St. Gallen",
    "wof:name":"Pich-ag",
    "wof:placetype":"venue"
},
  "geometry": {"coordinates":[8.819442749,47.2296028137],"type":"Point"}
}