{
  "type": "Feature",
  "properties": {
    "iso:country":"CH",
    "sg:address":"Letten-dagmersellen",
    "sg:city":"Winikon",
    "sg:orig_category":"Grosshandel mit Blumen U Pflanzen Herstellung von Metallkonstruktionen",
    "sg:phone":"+41 62 756 53 06",
    "sg:postcode":"6235",
    "sg:province":"Luzern",
    "wof:name":"A. Frei Gew\u00e4chshaustechnik",
    "wof:placetype":"venue"
},
  "geometry": {"coordinates":[8.0483570099,47.2349472046],"type":"Point"}
}