{
  "type": "Feature",
  "properties": {
    "iso:country":"CH",
    "sg:address":"M\u00fchlestig",
    "sg:city":"Dallenwil",
    "sg:orig_category":"Herstellung von Konstruktionsteilen, Fertigbauteilen U Ausbauelementen aus Holz",
    "sg:phone":"+41 41 628 11 23",
    "sg:postcode":"6383",
    "sg:province":"Nidwalden",
    "wof:name":"Niederberger-burger Walter.",
    "wof:placetype":"venue"
},
  "geometry": {"coordinates":[8.392159462,46.9343948364],"type":"Point"}
}