{
  "type": "Feature",
  "properties": {
    "iso:country":"CH",
    "sg:address":"Rue De La Piscine",
    "sg:city":"Verbier",
    "sg:orig_category":"Vermittlung von Immobilien",
    "sg:phone":"+41 27 775 29 00",
    "sg:postcode":"1936",
    "sg:province":"Valais",
    "wof:name":"Multi-invest Sa Agence Immobili\u00e8re",
    "wof:placetype":"venue"
},
  "geometry": {"coordinates":[7.2217497826,46.0982284546],"type":"Point"}
}