{
  "type": "Feature",
  "properties": {
    "iso:country":"CH",
    "sg:address":"Via Balestra 27 6900 Lugano. Postfach",
    "sg:city":"Lugano",
    "sg:orig_category":"Unternehmensberatung Wirtschaftspr\u00fcfung, Steuerberatung U Treuhand",
    "sg:phone":"+41 91 910 97 90",
    "sg:postcode":"6900",
    "sg:province":"Ticino",
    "wof:name":"Sts Studio Tributario Societario Sa Mandati Di Consulenza In Materia Fiscale E Legale Ecc",
    "wof:placetype":"venue"
},
  "geometry": {"coordinates":[8.9577894211,46.0079498291],"type":"Point"}
}