{
  "type": "Feature",
  "properties": {
    "iso:country":"CH",
    "sg:address":"Mattenstrasse 6",
    "sg:city":"Feldbrunnen",
    "sg:orig_category":"Gymnastikschulen",
    "sg:phone":"+41 32 622 69 82",
    "sg:postcode":"4532",
    "sg:province":"Solothurn",
    "wof:name":"Barbara Maienfisch Gymnastikschule",
    "wof:placetype":"venue"
},
  "geometry": {"coordinates":[7.5569591522,47.2187995911],"type":"Point"}
}