{
  "type": "Feature",
  "properties": {
    "iso:country":"CH",
    "sg:address":"Besso Via 7",
    "sg:city":"Lugano",
    "sg:orig_category":"Architektur U Ingenieurb\u00fcros",
    "sg:phone":"+41 41 850 60 70",
    "sg:postcode":"6900",
    "sg:province":"Ticino",
    "wof:name":"Dirlewanger Ariane",
    "wof:placetype":"venue"
},
  "geometry": {"coordinates":[8.433517,47.084484],"type":"Point"}
}