{
  "type": "Feature",
  "properties": {
    "iso:country":"CH",
    "sg:address":"Landstrasse 125",
    "sg:city":"Wettingen",
    "sg:orig_category":"Vermietung U Verpachtung von eigenen Immobilien",
    "sg:postcode":"5430",
    "sg:province":"Aargau",
    "wof:name":"L\u00e4gern Immobilien Ag",
    "wof:placetype":"venue"
},
  "geometry": {"coordinates":[8.3312110901,47.4637184143],"type":"Point"}
}