{
  "type": "Feature",
  "properties": {
    "iso:country":"CH",
    "sg:address":"Weinbergstrasse 14",
    "sg:city":"Zug",
    "sg:orig_category":"Softwareentwicklung U beratung",
    "sg:postcode":"6300",
    "sg:province":"Zug",
    "wof:name":"Plus90 Networking Und Telecommunication, E. Y\u00fccebas",
    "wof:placetype":"venue"
},
  "geometry": {"coordinates":[8.5251541138,47.1683578491],"type":"Point"}
}