{
  "type": "Feature",
  "properties": {
    "iso:country":"CH",
    "sg:address":"8596 Scherzingen. Postfach 154",
    "sg:city":"Scherzingen",
    "sg:orig_category":"Vereine Gemeinn\u00fctzige",
    "sg:postcode":"8596",
    "sg:province":"Thurgau",
    "wof:name":"Thurg.hilfsverein F.genesende Gem\u00fctskranke M\u00fcnsterlingen",
    "wof:placetype":"venue"
},
  "geometry": {"coordinates":[9.2290496826,47.6274681091],"type":"Point"}
}