{
  "type": "Feature",
  "properties": {
    "iso:country":"CH",
    "sg:address":"Buechmatt 1",
    "sg:city":"W\u00fcrenlos",
    "sg:orig_category":"Garne U Zwirne",
    "sg:postcode":"5436",
    "sg:province":"Aargau",
    "wof:name":"Zum Wulle-chn\u00e4uel / Perosa U. Gebistorf",
    "wof:placetype":"venue"
},
  "geometry": {"coordinates":[8.3616571426,47.4366912842],"type":"Point"}
}