{
  "type": "Feature",
  "properties": {
    "iso:country":"CH",
    "sg:address":"St. Georgen-strasse 88",
    "sg:city":"Winterthur",
    "sg:orig_category":"Bezirks, Sekundar, Realschulen, Oberstufe der Primarschulen Primarschulen",
    "sg:postcode":"8400",
    "sg:province":"Z\u00fcrich",
    "wof:name":"Primarschule & Oberstufe St.georgen",
    "wof:placetype":"venue"
},
  "geometry": {"coordinates":[8.72694,47.502636],"type":"Point"}
}