{
  "type": "Feature",
  "properties": {
    "iso:country":"CH",
    "sg:address":"Hadlaubstrasse 83",
    "sg:city":"Z\u00fcrich",
    "sg:orig_category":"Akupunktur",
    "sg:phone":"+41 13642428",
    "sg:postcode":"8006",
    "sg:province":"Z\u00fcrich",
    "wof:name":"Rita Hangartner Akupunktur",
    "wof:placetype":"venue"
},
  "geometry": {"coordinates":[8.551169,47.387299],"type":"Point"}
}