{
  "type": "Feature",
  "properties": {
    "iso:country":"CH",
    "sg:address":"Flurstrasse 3",
    "sg:city":"Bern",
    "sg:orig_category":"Vereine Gesang",
    "sg:postcode":"3014",
    "sg:province":"Bern",
    "wof:name":"Doppelquartett B\u00e4rgli",
    "wof:placetype":"venue"
},
  "geometry": {"coordinates":[7.4523172379,46.9618263245],"type":"Point"}
}