{
  "type": "Feature",
  "properties": {
    "iso:country":"CH",
    "sg:address":"Dorfstrasse 2",
    "sg:city":"Embrach",
    "sg:orig_category":"RESTAURANTS: TEA-ROOMS",
    "sg:postcode":"8424",
    "sg:province":"Z\u00fcrich",
    "wof:name":"Bl\u00fcmlisalp Alterswil Ag",
    "wof:placetype":"venue"
},
  "geometry": {"coordinates":[7.2517299652,46.7967414856],"type":"Point"}
}