{
  "type": "Feature",
  "properties": {
    "iso:country":"CH",
    "sg:address":"Route De Florissant 103",
    "sg:city":"Conches",
    "sg:orig_category":"Handelsvermittlung U Grosshandel",
    "sg:phone":"+41 22 346 87 11",
    "sg:postcode":"1231",
    "sg:province":"Gen\u00e8ve",
    "wof:name":"Cogemi Sa",
    "wof:placetype":"venue"
},
  "geometry": {"coordinates":[6.1684041023,46.1891746521],"type":"Point"}
}