{
  "type": "Feature",
  "properties": {
    "iso:country":"CH",
    "sg:address":"Ruchwiesenstrasse 8 8157 Dielsdorf. Postfach 270",
    "sg:city":"Dielsdorf",
    "sg:orig_category":"Grosshandel mit Blumen U Pflanzen Herstellung von Kork, Flecht U Korbwaren",
    "sg:phone":"+41 18549494",
    "sg:postcode":"8157",
    "sg:province":"Z\u00fcrich",
    "wof:name":"Duco Ag",
    "wof:placetype":"venue"
},
  "geometry": {"coordinates":[8.4671325684,47.4809074402],"type":"Point"}
}