{
  "type": "Feature",
  "properties": {
    "iso:country":"CH",
    "sg:address":"Sous-bois Chemin De 19b 1202 Gen\u00e8ve. Postfach",
    "sg:city":"Gen\u00e8ve",
    "sg:orig_category":"Unclassifiable Establishments",
    "sg:postcode":"1202",
    "sg:province":"Gen\u00e8ve",
    "wof:name":"Si Sirisco",
    "wof:placetype":"venue"
},
  "geometry": {"coordinates":[6.1348338127,46.2229232788],"type":"Point"}
}