{
  "type": "Feature",
  "properties": {
    "iso:country":"CH",
    "sg:address":"Aeschenmatte 6",
    "sg:city":"Ebikon",
    "sg:orig_category":"Architektur U Ingenieurb\u00fcros",
    "sg:postcode":"6030",
    "sg:province":"Luzern",
    "wof:name":"Basalamah Communications Bascom",
    "wof:placetype":"venue"
},
  "geometry": {"coordinates":[8.344875,47.08062],"type":"Point"}
}