{
  "type": "Feature",
  "properties": {
    "addr:full":"Zehntenplatz 2 Willisau Luzern 6130",
    "addr:housenumber":"2",
    "addr:postcode":"6130",
    "addr:street":"Zehntenplatz",
    "iso:country":"CH",
    "sg:address":"Zehntenplatz 2",
    "sg:city":"Willisau",
    "sg:orig_category":"Arztpraxen",
    "sg:phone":"+41 41 970 37 81",
    "sg:postcode":"6130",
    "sg:province":"Luzern",
    "wof:name":"Dr.med.franz Wicki Arzt F.allgemeine Medizin Fmh",
    "wof:placetype":"venue"
},
  "geometry": {"coordinates":[7.988127,47.119698],"type":"Point"}
}