{
  "type": "Feature",
  "properties": {
    "iso:country":"CH",
    "sg:address":"Alte Landstrasse 91",
    "sg:city":"Zollikon",
    "sg:orig_category":"Grossbanken",
    "sg:phone":"+41 81 303 47 11",
    "sg:postcode":"8702",
    "sg:province":"Z\u00fcrich",
    "wof:name":"Credit Suisse",
    "wof:placetype":"venue"
},
  "geometry": {"coordinates":[9.5004749298,47.0018081665],"type":"Point"}
}