{
  "type": "Feature",
  "properties": {
    "iso:country":"CH",
    "sg:address":"Rue Pr\u00e9 Borvey 8",
    "sg:city":"Martigny",
    "sg:orig_category":"Malerei",
    "sg:phone":"+41 79 631 86 86",
    "sg:postcode":"1920",
    "sg:province":"Valais",
    "wof:name":"Roland Notari Malergesch\u00e4ft",
    "wof:placetype":"venue"
},
  "geometry": {"coordinates":[8.7318191528,47.2026748657],"type":"Point"}
}