{
  "type": "Feature",
  "properties": {
    "iso:country":"CH",
    "sg:address":"Eigerplatz 2",
    "sg:city":"Bern",
    "sg:orig_category":"Zahnarztpraxen",
    "sg:phone":"+41 31 371 45 17",
    "sg:postcode":"3007",
    "sg:province":"Bern",
    "wof:name":"Dres Med.dent.u. & C. Zgraggen Zahn\u00e4rzte",
    "wof:placetype":"venue"
},
  "geometry": {"coordinates":[7.4305739403,46.9415054321],"type":"Point"}
}