{
  "type": "Feature",
  "properties": {
    "iso:country":"CH",
    "sg:address":"Leonhardsstrasse 53",
    "sg:city":"Basel",
    "sg:orig_category":"Allgemeiner Hoch U Tiefbau",
    "sg:phone":"+41 61 295 67 87",
    "sg:postcode":"4051",
    "sg:province":"Basel-Stadt",
    "wof:name":"Bbg Wagner Ag",
    "wof:placetype":"venue"
},
  "geometry": {"coordinates":[7.583375,47.55394],"type":"Point"}
}