{
  "type": "Feature",
  "properties": {
    "iso:country":"CH",
    "sg:address":"Sonnhaldeweg 2",
    "sg:city":"Riniken",
    "sg:orig_category":"Sportvereine Turnen",
    "sg:phone":"+41 62 212 10 36",
    "sg:postcode":"5223",
    "sg:province":"Aargau",
    "wof:name":"Turnverein Winznau",
    "wof:placetype":"venue"
},
  "geometry": {"coordinates":[7.8687319756,47.3472976685],"type":"Point"}
}