{
  "type": "Feature",
  "properties": {
    "iso:country":"CH",
    "sg:address":"Schiffm\u00fchle 4 5417 Untersiggenthal. Postfach",
    "sg:city":"Untersiggenthal",
    "sg:classifiers":[
        {
            "category":"Professional",
            "subcategory":"Employment Agencies",
            "type":"Services"
        }
    ],
    "sg:postcode":"5417",
    "sg:province":"Aargau",
    "sg:tags":[
        "personal",
        "u",
        "stellenvermittlung"
    ],
    "wof:name":"Work Consulting R. Willi",
    "wof:placetype":"venue"
},
  "geometry": {"coordinates":[8.2642412186,47.4898414612],"type":"Point"}
}