{
  "type": "Feature",
  "properties": {
    "iso:country":"CH",
    "sg:address":"Tannengasse 1",
    "sg:city":"Zurzach",
    "sg:orig_category":"Hundesalons",
    "sg:phone":"+41 56 249 26 92",
    "sg:postcode":"5330",
    "sg:province":"Aargau",
    "wof:name":"Margrit Lenz Hundesalon Nadja",
    "wof:placetype":"venue"
},
  "geometry": {"coordinates":[8.2927303314,47.5857620239],"type":"Point"}
}