{
  "type": "Feature",
  "properties": {
    "iso:country":"CH",
    "sg:address":"Maison De Commune 1066 Epalinges Case Postale 187",
    "sg:city":"Epalinges",
    "sg:orig_category":"Gemeindeverwaltungen",
    "sg:phone":"+41 21 784 18 72",
    "sg:postcode":"1066",
    "sg:province":"Vaud",
    "wof:name":"Administration Communale De Epalinges",
    "wof:placetype":"venue"
},
  "geometry": {"coordinates":[6.6711440086,46.5477027893],"type":"Point"}
}