{
  "type": "Feature",
  "properties": {
    "iso:country":"CH",
    "sg:address":"Rebmattstrasse 3",
    "sg:city":"Niederg\u00f6sgen",
    "sg:orig_category":"Herstellung von Metallkonstruktionen",
    "sg:phone":"+41 62 849 42 26",
    "sg:postcode":"5013",
    "sg:province":"Solothurn",
    "wof:name":"Fadomont Fabio De Donatis Storen & Rolladen",
    "wof:placetype":"venue"
},
  "geometry": {"coordinates":[7.9923901558,47.3765182495],"type":"Point"}
}