{
  "type": "Feature",
  "properties": {
    "iso:country":"CH",
    "sg:address":"Distelweg 11",
    "sg:city":"Frutigen",
    "sg:orig_category":"Sportvereine Flug Delta",
    "sg:phone":"+41 33 733 22 21",
    "sg:postcode":"3714",
    "sg:province":"Bern",
    "wof:name":"Gleitschirm Club Obersimmental",
    "wof:placetype":"venue"
},
  "geometry": {"coordinates":[7.4413700104,46.4569587708],"type":"Point"}
}