{
  "type": "Feature",
  "properties": {
    "addr:full":"Chem Des Pi\u00e8ces-chaperon 14 Cortaillod Neuch\u00e2tel 2016",
    "addr:housenumber":"14",
    "addr:postcode":"2016",
    "addr:street":"Neucha\u0302Tel",
    "iso:country":"CH",
    "sg:address":"Chem Des Pi\u00e8ces-chaperon 14",
    "sg:city":"Cortaillod",
    "sg:classifiers":[
        {
            "category":"Manufacturing",
            "subcategory":"Metals",
            "type":"Manufacturing & Wholesale Goods"
        }
    ],
    "sg:phone":"+41 32 842 63 33",
    "sg:postcode":"2016",
    "sg:province":"Neuch\u00e2tel",
    "sg:tags":[
        "-",
        "machine",
        "equipment",
        "engineering",
        "machinery",
        "mechanical"
    ],
    "wof:name":"Zimmerli Sa",
    "wof:placetype":"venue"
},
  "geometry": {"coordinates":[6.84112,46.942497],"type":"Point"}
}