{
  "type": "Feature",
  "properties": {
    "addr:full":"Poststrasse 2 Gelterkinden Basel-Landschaft 4460",
    "addr:housenumber":"2",
    "addr:postcode":"4460",
    "addr:street":"Poststrasse",
    "iso:country":"CH",
    "sg:address":"Poststrasse 2",
    "sg:city":"Gelterkinden",
    "sg:classifiers":[
        {
            "category":"Banks & Credit Unions",
            "subcategory":"Bank",
            "type":"Services"
        }
    ],
    "sg:phone":"+41 61 981 11 07",
    "sg:postcode":"4460",
    "sg:province":"Basel-Landschaft",
    "wof:name":"Basellandschaftliche, Kantonalbank",
    "wof:placetype":"venue"
},
  "geometry": {"coordinates":[7.853863,47.465843],"type":"Point"}
}