{
  "type": "Feature",
  "properties": {
    "iso:country":"CH",
    "sg:address":"Thunstrasse 30 3005 Bern. Postfach",
    "sg:city":"Bern",
    "sg:orig_category":"Unternehmensberatung",
    "sg:postcode":"3005",
    "sg:province":"Bern",
    "wof:name":"Unternehmungsberatung St\u00f6ckli Unternehmungsberatung F Industrie U Gewerbe, Personalf\u00fchrung Usw",
    "wof:placetype":"venue"
},
  "geometry": {"coordinates":[7.4551639557,46.9415016174],"type":"Point"}
}