{
  "type": "Feature",
  "properties": {
    "iso:country":"CH",
    "sg:address":"Rue De La Berg\u00e8re 1a",
    "sg:city":"Meyrin",
    "sg:orig_category":"Autotransporte international",
    "sg:phone":"+41 22 798 44 68",
    "sg:postcode":"1217",
    "sg:province":"Gen\u00e8ve",
    "wof:name":"Schneider & Cie Sa Transports Internationaux",
    "wof:placetype":"venue"
},
  "geometry": {"coordinates":[6.066571,46.221989],"type":"Point"}
}