{
  "type": "Feature",
  "properties": {
    "iso:country":"CH",
    "sg:address":"Neugasse 16.",
    "sg:city":"Widnau",
    "sg:orig_category":"Grosshandel mit Textilien",
    "sg:phone":"+41 71 722 17 33",
    "sg:postcode":"9443",
    "sg:province":"St. Gallen",
    "wof:name":"B\u00f6sch & Co., Nachf. Loher-b\u00f6sch Gaby + Co",
    "wof:placetype":"venue"
},
  "geometry": {"coordinates":[9.6395940781,47.4050521851],"type":"Point"}
}