{
  "type": "Feature",
  "properties": {
    "iso:country":"CH",
    "sg:address":"L\u00f6wenstrasse 12",
    "sg:city":"Kreuzlingen",
    "sg:orig_category":"Detailhandel mit Lederwaren U Reiseartikeln Detailhandel mit Schuhen",
    "sg:phone":"+41 71 672 12 16",
    "sg:postcode":"8280",
    "sg:province":"Thurgau",
    "wof:name":"Boutique Lago Schuhe & Accessoires",
    "wof:placetype":"venue"
},
  "geometry": {"coordinates":[9.1726007462,47.6478691101],"type":"Point"}
}