{
  "type": "Feature",
  "properties": {
    "iso:country":"CH",
    "sg:address":"Rue Des Croix 43 2014 B\u00f4le Case Postale 108",
    "sg:city":"B\u00f4le",
    "sg:orig_category":"Herstellung von Mess U Kontrollinstrumenten U vorrichtungen Herstellung von Metallerzeugnissen ohne ",
    "sg:phone":"+41 32 843 83 83",
    "sg:postcode":"2014",
    "sg:province":"Neuch\u00e2tel",
    "wof:name":"Maret Sa",
    "wof:placetype":"venue"
},
  "geometry": {"coordinates":[6.8445777893,46.9646034241],"type":"Point"}
}