{
  "type": "Feature",
  "properties": {
    "iso:country":"CH",
    "sg:address":"Via Serafino Balestra 31/33",
    "sg:city":"Lugano",
    "sg:orig_category":"Datenverarbeitungsdienste",
    "sg:phone":"+41 91 923 37 67",
    "sg:postcode":"6900",
    "sg:province":"Ticino",
    "wof:name":"Thema Consulting Sa Consulenza Informatica",
    "wof:placetype":"venue"
},
  "geometry": {"coordinates":[8.958808,46.008003],"type":"Point"}
}