{
  "type": "Feature",
  "properties": {
    "iso:country":"CH",
    "sg:address":"Moosstrasse",
    "sg:city":"Pieterlen",
    "sg:orig_category":"Erdbewegungsarbeiten",
    "sg:phone":"+41 32 377 33 18",
    "sg:postcode":"2542",
    "sg:province":"Bern",
    "wof:name":"Adrian Christen Trax-& Baggerunternehmung",
    "wof:placetype":"venue"
},
  "geometry": {"coordinates":[7.3157868385,47.1678924561],"type":"Point"}
}