{
  "type": "Feature",
  "properties": {
    "iso:country":"CH",
    "sg:address":"Avenue De La Gare 40",
    "sg:city":"Martigny",
    "sg:orig_category":"Fahrschulen, Flugschulen",
    "sg:phone":"+41 27 722 12 20",
    "sg:postcode":"1920",
    "sg:province":"Valais",
    "wof:name":"Jean M\u00e9troz Auto-\u00e9cole",
    "wof:placetype":"venue"
},
  "geometry": {"coordinates":[7.0766072273,46.1038703918],"type":"Point"}
}