{
  "type": "Feature",
  "properties": {
    "iso:country":"CH",
    "sg:address":"Haus Pulvetta",
    "sg:city":"Ramosch",
    "sg:orig_category":"Allgemeiner Hoch U Tiefbau",
    "sg:phone":"+41 81 860 15 50",
    "sg:postcode":"7556",
    "sg:province":"Graubunden",
    "wof:name":"Laurent Alfred Ag",
    "wof:placetype":"venue"
},
  "geometry": {"coordinates":[10.380715,46.832623],"type":"Point"}
}