{
  "type": "Feature",
  "properties": {
    "iso:country":"CH",
    "sg:address":"Kirchbodenstrasse 73a",
    "sg:city":"Thalwil",
    "sg:orig_category":"Datenverarbeitungsdienste Softwareentwicklung U beratung",
    "sg:phone":"+41 17721341",
    "sg:postcode":"8800",
    "sg:province":"Z\u00fcrich",
    "wof:name":"Infonic Ag Information Engineering",
    "wof:placetype":"venue"
},
  "geometry": {"coordinates":[8.568766,47.291286],"type":"Point"}
}