{
  "type": "Feature",
  "properties": {
    "iso:country":"CH",
    "sg:address":"1911",
    "sg:city":"Mayens-de-chamoson",
    "sg:classifiers":[
        {
            "category":"Travel",
            "subcategory":"Hotels & Motels",
            "type":"Entertainment"
        }
    ],
    "sg:phone":"+41 27 305 25 25",
    "sg:postcode":"1911",
    "sg:province":"Valais",
    "sg:tags":[
        "hotels",
        "mit",
        "restaurant"
    ],
    "wof:name":"H\u00f4tel Ard\u00e8ve Ovronnaz",
    "wof:placetype":"venue"
},
  "geometry": {"coordinates":[7.1859002113,46.2066612244],"type":"Point"}
}