{
  "type": "Feature",
  "properties": {
    "iso:country":"CH",
    "sg:address":"Thurgauerstrasse 74 8050 Z\u00fcrich. Postfach",
    "sg:city":"Z\u00fcrich",
    "sg:orig_category":"Grosshandel mit Eisenwaren sowie Installationsbedarf f\u00fcr Gas, Wasser U Heizung Grosshandel mit sonst",
    "sg:phone":"+41 13024866",
    "sg:postcode":"8050",
    "sg:province":"Z\u00fcrich",
    "wof:name":"Intercambio-handels Ag.",
    "wof:placetype":"venue"
},
  "geometry": {"coordinates":[8.5552158356,47.4176864624],"type":"Point"}
}