{
  "type": "Feature",
  "properties": {
    "iso:country":"CH",
    "sg:address":"Beau-s\u00e9jour Rue 28",
    "sg:city":"Lausanne",
    "sg:orig_category":"Unclassifiable Establishments",
    "sg:postcode":"1003",
    "sg:province":"Vaud",
    "wof:name":"Si Cl\u00e9matite",
    "wof:placetype":"venue"
},
  "geometry": {"coordinates":[7.4068250656,46.2767829895],"type":"Point"}
}