{
  "type": "Feature",
  "properties": {
    "iso:country":"CH",
    "sg:address":"Birsigstrasse 10",
    "sg:city":"Basel",
    "sg:orig_category":"Arztpraxen",
    "sg:phone":"+41 61 281 13 33",
    "sg:postcode":"4054",
    "sg:province":"Basel-Stadt",
    "wof:name":"Dr.med.jean-christian Loeliger Spezialarzt",
    "wof:placetype":"venue"
},
  "geometry": {"coordinates":[7.585063,47.551041],"type":"Point"}
}