{
  "type": "Feature",
  "properties": {
    "iso:country":"CH",
    "sg:address":"Chemin De Chandieu 23",
    "sg:city":"Lausanne",
    "sg:orig_category":"Vorschulen, Kinderg\u00e4rten",
    "sg:postcode":"1006",
    "sg:province":"Vaud",
    "wof:name":"Ecole Enfantine Chandieu I/ii",
    "wof:placetype":"venue"
},
  "geometry": {"coordinates":[6.6400260925,46.5124320984],"type":"Point"}
}