{
  "type": "Feature",
  "properties": {
    "iso:country":"CH",
    "sg:address":"Oberwilerstrasse 10 4102 Binningen. Postfach",
    "sg:city":"Binningen",
    "sg:orig_category":"Maler U Glasergewerbe",
    "sg:postcode":"4102",
    "sg:province":"Basel-Landschaft",
    "wof:name":"Maler Pally",
    "wof:placetype":"venue"
},
  "geometry": {"coordinates":[8.7228803635,47.2736358643],"type":"Point"}
}