{
  "type": "Feature",
  "properties": {
    "iso:country":"CH",
    "sg:address":"Bergstrasse 25",
    "sg:city":"Sevelen",
    "sg:orig_category":"Herstellung von Pumpen U Kompressoren",
    "sg:phone":"+41 81 785 16 81",
    "sg:postcode":"9475",
    "sg:province":"St. Gallen",
    "wof:name":"Brunner Ag Maschinen Und Pumpen",
    "wof:placetype":"venue"
},
  "geometry": {"coordinates":[9.4842634201,47.1226501465],"type":"Point"}
}