{
  "type": "Feature",
  "properties": {
    "iso:country":"CH",
    "sg:address":"Konstanzerstrasse 56 8274 T\u00e4gerwilen. Postfach 160",
    "sg:city":"T\u00e4gerwilen",
    "sg:orig_category":"Fachdetailhandel in Verkaufsr\u00e4umen",
    "sg:phone":"+41 71 669 21 10",
    "sg:postcode":"8274",
    "sg:province":"Thurgau",
    "wof:name":"Motomarine Ag",
    "wof:placetype":"venue"
},
  "geometry": {"coordinates":[9.1389341354,47.6598739624],"type":"Point"}
}