{
  "type": "Feature",
  "properties": {
    "iso:country":"CH",
    "sg:address":"Deutsche Strasse 5",
    "sg:city":"Chur",
    "sg:orig_category":"Grosshandel mit Bekleidung",
    "sg:phone":"+41 81 356 00 45",
    "sg:postcode":"7000",
    "sg:province":"Graubunden",
    "wof:name":"Sigra, Kurt Gradolf & Co Arbeitsschutz",
    "wof:placetype":"venue"
},
  "geometry": {"coordinates":[9.5401802063,46.8862686157],"type":"Point"}
}