{
  "type": "Feature",
  "properties": {
    "iso:country":"CH",
    "sg:address":"Z.i.chemin Des Ducats",
    "sg:city":"Orbe",
    "sg:orig_category":"Instandhaltung U Reparatur von Automobilen",
    "sg:phone":"+41 79 611 60 36",
    "sg:postcode":"1350",
    "sg:province":"Vaud",
    "wof:name":"Pascal Ray Carrosserie Des Ducats",
    "wof:placetype":"venue"
},
  "geometry": {"coordinates":[6.5309619904,46.7247772217],"type":"Point"}
}