{
  "type": "Feature",
  "properties": {
    "iso:country":"CH",
    "sg:address":"Rosenbergstrasse 36",
    "sg:city":"St.gallen",
    "sg:orig_category":"Unclassifiable Establishments",
    "sg:postcode":"9000",
    "sg:province":"St. Gallen",
    "wof:name":"St. Gallen Master Diplome Ag",
    "wof:placetype":"venue"
},
  "geometry": {"coordinates":[9.3698606491,47.4243621826],"type":"Point"}
}