{
  "type": "Feature",
  "properties": {
    "iso:country":"CH",
    "sg:address":"Ringstrasse 35 C",
    "sg:city":"Chur",
    "sg:orig_category":"Herstellung von Radio U Fernsehger\u00e4ten sowie phono U videotechnischen Ger\u00e4ten",
    "sg:postcode":"7000",
    "sg:province":"Graubunden",
    "wof:name":"Gamefreakshop Caminada",
    "wof:placetype":"venue"
},
  "geometry": {"coordinates":[9.5146121979,46.8543815613],"type":"Point"}
}