{
  "type": "Feature",
  "properties": {
    "iso:country":"CH",
    "sg:address":"Chemin Des Terrasses 32",
    "sg:city":"Ch\u00e2telard-lutry",
    "sg:orig_category":"Grosshandel mit Textilien Grosshandel mit sonstigen Konsumg\u00fctern",
    "sg:phone":"+41 21 791 55 15",
    "sg:postcode":"1095",
    "sg:province":"Vaud",
    "wof:name":"Nikki Trading Ltd",
    "wof:placetype":"venue"
},
  "geometry": {"coordinates":[6.6846661568,46.506652832],"type":"Point"}
}