{
  "type": "Feature",
  "properties": {
    "iso:country":"CH",
    "sg:address":"Truttwisenstrasse 6",
    "sg:city":"Stadel",
    "sg:orig_category":"Wirtschaftspr\u00fcfung, Steuerberatung U Treuhand",
    "sg:postcode":"8174",
    "sg:province":"Z\u00fcrich",
    "wof:name":"Property Offices, Ferber R.",
    "wof:placetype":"venue"
},
  "geometry": {"coordinates":[8.4666872025,47.5304107666],"type":"Point"}
}