{
  "type": "Feature",
  "properties": {
    "iso:country":"CH",
    "sg:address":"2515",
    "sg:city":"Pr\u00eales",
    "sg:classifiers":[
        {
            "category":"Travel",
            "subcategory":"Hotels & Motels",
            "type":"Entertainment"
        }
    ],
    "sg:postcode":"2515",
    "sg:province":"Bern",
    "sg:tags":[
        "hotels",
        "mit",
        "restaurant"
    ],
    "wof:name":"Bourquin-schmidlin E.",
    "wof:placetype":"venue"
},
  "geometry": {"coordinates":[7.1306600571,47.0995941162],"type":"Point"}
}