{
  "type": "Feature",
  "properties": {
    "iso:country":"CH",
    "sg:address":"Quai Des Alpes",
    "sg:city":"Nyon",
    "sg:orig_category":"Non-Classified Establishments",
    "sg:phone":"+41 56 633 11 40",
    "sg:postcode":"1260",
    "sg:province":"Vaud",
    "wof:name":"Restaurant Metzgerst\u00fcbli, Jukic Zvonko",
    "wof:placetype":"venue"
},
  "geometry": {"coordinates":[8.3861837387,47.3353805542],"type":"Point"}
}