{
  "type": "Feature",
  "properties": {
    "iso:country":"CH",
    "sg:address":"Aarbergstr. 100 2500 Biel/bienne. Postfach",
    "sg:city":"Biel/bienne",
    "sg:orig_category":"Grosshandel mit Nahrungsmitteln, Getr\u00e4nken U Tabakwaren ohne ausgepr\u00e4gten Schwerpunkt",
    "sg:postcode":"2502",
    "sg:province":"Bern",
    "wof:name":"Nani Filippo",
    "wof:placetype":"venue"
},
  "geometry": {"coordinates":[8.9955282211,46.187713623],"type":"Point"}
}