{
  "type": "Feature",
  "properties": {
    "iso:country":"CH",
    "sg:address":"Hauptstrasse 25 4562 Biberist. Postfach",
    "sg:city":"Biberist",
    "sg:orig_category":"Handel mit Motorr\u00e4dern, Teilen U Zubeh\u00f6r Instandhaltung U Reparatur von Motorr\u00e4dern",
    "sg:postcode":"4562",
    "sg:province":"Solothurn",
    "wof:name":"Moto-center, Hermsdorf Michel Motorr\u00e4der, Roller; Reparatur, Handel",
    "wof:placetype":"venue"
},
  "geometry": {"coordinates":[7.5627808571,47.1826782227],"type":"Point"}
}