{
  "type": "Feature",
  "properties": {
    "iso:country":"CH",
    "sg:address":"Rue De La Gru\u00e8re 11 2350 Saignel\u00e9gier. Postfach",
    "sg:city":"Saignel\u00e9gier",
    "sg:orig_category":"Detailhandel mit B\u00fcchern",
    "sg:phone":"+41 32 951 18 30",
    "sg:postcode":"2350",
    "sg:province":"Jura",
    "wof:name":"Jean-michel Steiger Librairie L'ivraie",
    "wof:placetype":"venue"
},
  "geometry": {"coordinates":[6.998535,47.255318],"type":"Point"}
}