{
  "type": "Feature",
  "properties": {
    "iso:country":"CH",
    "sg:address":"R\u00fctlistrasse 43",
    "sg:city":"Illnau",
    "sg:orig_category":"Elektroinstallation",
    "sg:phone":"+41 52 346 10 10",
    "sg:postcode":"8308",
    "sg:province":"Z\u00fcrich",
    "wof:name":"Frebel Ag",
    "wof:placetype":"venue"
},
  "geometry": {"coordinates":[8.7322263718,47.4040184021],"type":"Point"}
}