{
  "type": "Feature",
  "properties": {
    "addr:full":"Chemin Des Semailles 34 Grand-lancy Gen\u00e8ve 1212",
    "addr:housenumber":"34",
    "addr:postcode":"1212",
    "addr:street":"Chemin Des Semailles",
    "iso:country":"CH",
    "sg:address":"Chemin Des Semailles 34",
    "sg:city":"Grand-lancy",
    "sg:orig_category":"Arztpraxen",
    "sg:phone":"+41 79 446 11 00",
    "sg:postcode":"1212",
    "sg:province":"Gen\u00e8ve",
    "wof:name":"Dr M\u00e9d. Patrick Monnier M\u00e9decin Sp\u00e9cialiste Fmh",
    "wof:placetype":"venue"
},
  "geometry": {"coordinates":[6.82978,47.102913],"type":"Point"}
}