{
  "type": "Feature",
  "properties": {
    "iso:country":"CH",
    "sg:address":"Via Locarno 6",
    "sg:city":"Sementina",
    "sg:orig_category":"Architektur U Ingenieurb\u00fcros",
    "sg:phone":"+41 91 857 81 32",
    "sg:postcode":"6514",
    "sg:province":"Ticino",
    "wof:name":"Studio Ingegneria Ambrosini Ing. P. G. Sa",
    "wof:placetype":"venue"
},
  "geometry": {"coordinates":[8.99156,46.185768],"type":"Point"}
}