{
  "type": "Feature",
  "properties": {
    "iso:country":"CH",
    "sg:address":"Viale Portone 3",
    "sg:city":"Bellinzona",
    "sg:orig_category":"Architektur U Ingenieurb\u00fcros Vermittlung von Immobilien",
    "sg:phone":"+41 91 825 54 75",
    "sg:postcode":"6500",
    "sg:province":"Ticino",
    "wof:name":"Doninelli Livio E Renato Sa",
    "wof:placetype":"venue"
},
  "geometry": {"coordinates":[9.022601,46.193817],"type":"Point"}
}