{
  "type": "Feature",
  "properties": {
    "iso:country":"CH",
    "sg:address":"Weinbergstrasse 79",
    "sg:city":"Z\u00fcrich",
    "sg:orig_category":"Wirtschaftspr\u00fcfung, Steuerberatung U Treuhand",
    "sg:phone":"+41 19304331",
    "sg:postcode":"8006",
    "sg:province":"Z\u00fcrich",
    "wof:name":"Ehrismann + Partner Treuhand Ag",
    "wof:placetype":"venue"
},
  "geometry": {"coordinates":[8.8083190918,47.3317565918],"type":"Point"}
}