{
  "type": "Feature",
  "properties": {
    "addr:full":"Corso Elvezia 8 Lugano Ticino 6900",
    "addr:housenumber":"8",
    "addr:postcode":"6900",
    "addr:street":"Corso Elvezia",
    "iso:country":"CH",
    "sg:address":"Corso Elvezia 8",
    "sg:city":"Lugano",
    "sg:classifiers":[
        {
            "category":"Bars & Pubs",
            "type":"Food & Drink"
        }
    ],
    "sg:phone":"+41 91 922 70 97",
    "sg:postcode":"6900",
    "sg:province":"Ticino",
    "wof:name":"Bar Apollo",
    "wof:placetype":"venue"
},
  "geometry": {"coordinates":[8.955774,46.006809],"type":"Point"}
}