{
  "type": "Feature",
  "properties": {
    "iso:country":"CH",
    "sg:address":"Eymattstrasse 7 3027 Bern. Postfach",
    "sg:city":"Bern",
    "sg:orig_category":"Grosshandel mit B\u00fcromaschinen Grosshandel mit Datenverarbeitungsger\u00e4ten",
    "sg:phone":"+41 32 725 07 57",
    "sg:postcode":"3027",
    "sg:province":"Bern",
    "wof:name":"Sharp Electronics (suisse) Sa Syst\u00e8mes Copieurs & Fax",
    "wof:placetype":"venue"
},
  "geometry": {"coordinates":[6.9243540764,46.9904441833],"type":"Point"}
}