{
  "type": "Feature",
  "properties": {
    "iso:country":"CH",
    "sg:address":"3825",
    "sg:city":"M\u00fcrren",
    "sg:orig_category":"Personenbef\u00f6rderung im Linienverkehr zu Land",
    "sg:phone":"+41 33 828 74 47",
    "sg:postcode":"3825",
    "sg:province":"Bern",
    "wof:name":"M\u00fcrrenbahn",
    "wof:placetype":"venue"
},
  "geometry": {"coordinates":[7.8951401711,46.560218811],"type":"Point"}
}