{
  "type": "Feature",
  "properties": {
    "iso:country":"CH",
    "sg:address":"Landenbergstrasse 34 6005 Luzern. Postfach",
    "sg:city":"Luzern",
    "sg:classifiers":[
        {
            "category":"Communications",
            "subcategory":"Radio Station",
            "type":"Services"
        }
    ],
    "sg:postcode":"6003",
    "sg:province":"Luzern",
    "sg:tags":[
        "fernsehanstalten",
        "u"
    ],
    "wof:name":"Mpp Medien Gmbh Print-medien; Herstellung, Vertrieb. Rundfunk- U. Tv-produktionen Usw",
    "wof:placetype":"venue"
},
  "geometry": {"coordinates":[8.3168144226,47.0460205078],"type":"Point"}
}