{
  "type": "Feature",
  "properties": {
    "iso:country":"CH",
    "sg:address":"Avenue De S\u00e9cheron 10",
    "sg:city":"Gen\u00e8ve",
    "sg:orig_category":"Reiseb\u00fcros",
    "sg:phone":"+41 71 245 31 51",
    "sg:postcode":"1202",
    "sg:province":"Gen\u00e8ve",
    "wof:name":"Sunshine Reisen Tauchreisen",
    "wof:placetype":"venue"
},
  "geometry": {"coordinates":[9.3777980804,47.4283256531],"type":"Point"}
}