{
  "type": "Feature",
  "properties": {
    "iso:country":"CH",
    "sg:address":"Schulhausstrasse 5",
    "sg:city":"Mettmenstetten",
    "sg:orig_category":"Herstellung von Reiseartikeln, Leder U Sattlerwaren Innendekorationsateliers",
    "sg:phone":"+41 17670410",
    "sg:postcode":"8932",
    "sg:province":"Z\u00fcrich",
    "wof:name":"Ernst Langenegger Sattler-& Tapezierergesch\u00e4ft",
    "wof:placetype":"venue"
},
  "geometry": {"coordinates":[8.4646272659,47.2450828552],"type":"Point"}
}