{
  "type": "Feature",
  "properties": {
    "iso:country":"CH",
    "sg:address":"Place Du Saugey 7",
    "sg:city":"Echandens",
    "sg:classifiers":[
        {
            "category":"Wholesale",
            "subcategory":"Hardware",
            "type":"Manufacturing & Wholesale Goods"
        }
    ],
    "sg:phone":"+41 21 701 29 21",
    "sg:postcode":"1026",
    "sg:province":"Vaud",
    "sg:tags":[
        "anti-virus"
    ],
    "wof:name":"Epps Sa",
    "wof:placetype":"venue"
},
  "geometry": {"coordinates":[6.540407,46.533962],"type":"Point"}
}