{
  "type": "Feature",
  "properties": {
    "iso:country":"CH",
    "sg:address":"Wachterweg 15",
    "sg:city":"Z\u00fcrich",
    "sg:orig_category":"Sportvereine Ballsport Handball",
    "sg:phone":"+41 13634827",
    "sg:postcode":"8057",
    "sg:province":"Z\u00fcrich",
    "wof:name":"Satus Unterstrass",
    "wof:placetype":"venue"
},
  "geometry": {"coordinates":[8.5345058441,47.3954925537],"type":"Point"}
}