{
  "type": "Feature",
  "properties": {
    "iso:country":"CH",
    "sg:address":"Oberlangnauer Strasse 6",
    "sg:city":"M\u00e4rwil",
    "sg:orig_category":"Bauschreinerei Einbau von Schreinerwaren",
    "sg:phone":"+41 71 655 11 48",
    "sg:postcode":"9562",
    "sg:province":"Thurgau",
    "wof:name":"Max Sutter Einbauk\u00fcchen & Schreinerei",
    "wof:placetype":"venue"
},
  "geometry": {"coordinates":[9.073084,47.531498],"type":"Point"}
}