{
  "type": "Feature",
  "properties": {
    "iso:country":"CH",
    "sg:address":"Dorf",
    "sg:city":"R\u00fcegsau",
    "sg:orig_category":"Detailhandel mit Brot, Back U S\u00fcsswaren",
    "sg:phone":"+41 34 461 13 67",
    "sg:postcode":"3417",
    "sg:province":"Bern",
    "wof:name":"Hans-peter Aeschbacher B\u00e4ckerei",
    "wof:placetype":"venue"
},
  "geometry": {"coordinates":[7.67234,47.024899],"type":"Point"}
}