{
  "type": "Feature",
  "properties": {
    "iso:country":"CH",
    "sg:address":"Mariahilfgasse 1",
    "sg:city":"Andermatt",
    "sg:orig_category":"Unternehmensberatung",
    "sg:phone":"+41 41 370 59 59",
    "sg:postcode":"6490",
    "sg:province":"Uri",
    "wof:name":"Mts, Ag F\u00fcr Management-training Umd -services",
    "wof:placetype":"venue"
},
  "geometry": {"coordinates":[8.5959873199,46.6330833435],"type":"Point"}
}