{
  "type": "Feature",
  "properties": {
    "iso:country":"CH",
    "sg:address":"Frutigenstrasse 18",
    "sg:city":"Thun",
    "sg:orig_category":"Tankstellen",
    "sg:phone":"+41 33 223 41 44",
    "sg:postcode":"3600",
    "sg:province":"Bern",
    "wof:name":"Zumstein Werner Gmbh",
    "wof:placetype":"venue"
},
  "geometry": {"coordinates":[7.6276087761,46.7542419434],"type":"Point"}
}