{
  "type": "Feature",
  "properties": {
    "iso:country":"CH",
    "sg:address":"Mittelstrasse 123",
    "sg:city":"Gunten",
    "sg:orig_category":"Herstellung von Metallkonstruktionen Schlossereien",
    "sg:phone":"+41 33 251 10 47",
    "sg:postcode":"3654",
    "sg:province":"Bern",
    "wof:name":"Karl M\u00fcller Schlosserei Metallbau",
    "wof:placetype":"venue"
},
  "geometry": {"coordinates":[7.7015390396,46.7136726379],"type":"Point"}
}