{
  "type": "Feature",
  "properties": {
    "iso:country":"CH",
    "sg:address":"7205",
    "sg:city":"Zizers",
    "sg:classifiers":[
        {
            "category":"Restaurant",
            "type":"Food & Drink"
        }
    ],
    "sg:phone":"+41 33 654 18 66",
    "sg:postcode":"7205",
    "sg:province":"Graubunden",
    "wof:name":"Restaurant Pochtenfall",
    "wof:placetype":"venue"
},
  "geometry": {"coordinates":[7.7636270523,46.6223258972],"type":"Point"}
}