{
  "type": "Feature",
  "properties": {
    "iso:country":"CH",
    "sg:address":"Hauptstrasse 3",
    "sg:city":"Auw",
    "sg:orig_category":"Wasserversorgung",
    "sg:phone":"+41 56 668 15 75",
    "sg:postcode":"5644",
    "sg:province":"Aargau",
    "wof:name":"Wasserversorgung R\u00fcstenschwil",
    "wof:placetype":"venue"
},
  "geometry": {"coordinates":[8.3645982742,47.2115135193],"type":"Point"}
}