{
  "type": "Feature",
  "properties": {
    "iso:country":"CH",
    "sg:address":"Bahnhofstrasse 11",
    "sg:city":"Brig",
    "sg:orig_category":"Detailhandel mit Bekleidung Detailhandel mit Herrenbekleidung",
    "sg:phone":"+41 81 756 11 10",
    "sg:postcode":"3900",
    "sg:province":"Valais",
    "wof:name":"Hilty Mode Ag",
    "wof:placetype":"venue"
},
  "geometry": {"coordinates":[9.476933,47.166695],"type":"Point"}
}