{
  "type": "Feature",
  "properties": {
    "iso:country":"CH",
    "sg:address":"M\u00fchlerainweg 6",
    "sg:city":"Grossdietwil",
    "sg:orig_category":"Dachdeckerei Zimmerei, Dachdeckerei, Bauspenglerei U Abdichtung",
    "sg:phone":"+41 62 927 23 30",
    "sg:postcode":"6146",
    "sg:province":"Luzern",
    "wof:name":"Wassermann & Partner Wapro-dach",
    "wof:placetype":"venue"
},
  "geometry": {"coordinates":[7.889069,47.169006],"type":"Point"}
}