{
  "type": "Feature",
  "properties": {
    "iso:country":"CH",
    "sg:address":"Unterdorf 10",
    "sg:city":"N\u00e4fels",
    "sg:orig_category":"Bauspenglerei Zimmerei, Dachdeckerei, Bauspenglerei U Abdichtung",
    "sg:phone":"+41 55 612 10 44",
    "sg:postcode":"8752",
    "sg:province":"Glarus",
    "wof:name":"Ernst M\u00fcller Spenglerei - Sanit\u00e4re Anlagen Gmbh",
    "wof:placetype":"venue"
},
  "geometry": {"coordinates":[9.062761,47.100857],"type":"Point"}
}