{
  "type": "Feature",
  "properties": {
    "iso:country":"CH",
    "sg:address":"Ausserdorf 2",
    "sg:city":"Langenbruck",
    "sg:classifiers":[
        {
            "category":"Travel",
            "subcategory":"Hotels & Motels",
            "type":"Entertainment"
        }
    ],
    "sg:postcode":"4438",
    "sg:province":"Basel-Landschaft",
    "sg:tags":[
        "hotels",
        "mit",
        "restaurant"
    ],
    "wof:name":"Ren\u00e9 Murbach",
    "wof:placetype":"venue"
},
  "geometry": {"coordinates":[9.0401592255,47.41065979],"type":"Point"}
}