{
  "type": "Feature",
  "properties": {
    "iso:country":"CH",
    "sg:address":"Scheideggstrasse 30 8400 Winterthur. Postfach",
    "sg:city":"Winterthur",
    "sg:orig_category":"Unternehmensberatung",
    "sg:postcode":"8411",
    "sg:province":"Z\u00fcrich",
    "wof:name":"Colliers Csl Ag, Zweigniederlassung Winterthur",
    "wof:placetype":"venue"
},
  "geometry": {"coordinates":[8.7505903244,47.4946098328],"type":"Point"}
}