{
  "type": "Feature",
  "properties": {
    "iso:country":"CH",
    "sg:address":"Rue De L'h\u00f4pital 22",
    "sg:city":"Del\u00e9mont",
    "sg:orig_category":"Detailhandel mit Waren verschiedener Art, Hauptrichtung Nahrungsmittel Grosshandel mit Nahrungsmitte",
    "sg:phone":"+41 32 422 22 66",
    "sg:postcode":"2800",
    "sg:province":"Jura",
    "wof:name":"Alimentation Ch. Wirz Et J. Wirz",
    "wof:placetype":"venue"
},
  "geometry": {"coordinates":[7.3439698219,47.3653488159],"type":"Point"}
}