{
  "type": "Feature",
  "properties": {
    "iso:country":"CH",
    "sg:address":"3532 Z\u00e4ziwil. Postfach",
    "sg:city":"Z\u00e4ziwil",
    "sg:orig_category":"Unclassifiable Establishments",
    "sg:postcode":"3532",
    "sg:province":"Bern",
    "wof:name":"Ueli L\u00fcthi",
    "wof:placetype":"venue"
},
  "geometry": {"coordinates":[7.6618599892,46.9018783569],"type":"Point"}
}