{
  "type": "Feature",
  "properties": {
    "addr:full":"Bubikonerstrasse 39 D\u00fcrnten Z\u00fcrich 8635",
    "addr:housenumber":"39",
    "addr:postcode":"8635",
    "addr:street":"Bubikonerstrasse;Zuerich",
    "iso:country":"CH",
    "sg:address":"Bubikonerstrasse 39",
    "sg:city":"D\u00fcrnten",
    "sg:orig_category":"Blanking, Punching, Stamping, Embossing And Drawing Dies, Progressive Dies",
    "sg:phone":"+41 55 251 00 00",
    "sg:postcode":"8635",
    "sg:province":"Z\u00fcrich",
    "wof:name":"Runox Ag Werkzeug- Und Apparatebau",
    "wof:placetype":"venue"
},
  "geometry": {"coordinates":[8.834162,47.276428],"type":"Point"}
}