{
  "type": "Feature",
  "properties": {
    "iso:country":"CH",
    "sg:address":"Arnold Baumgartner-strasse 9",
    "sg:city":"Grenchen",
    "sg:orig_category":"Detailhandel mit elektrischen Haushalts-,Radio U Fernsehger\u00e4ten sowie Musikinstrumenten Verlag von b",
    "sg:phone":"+41 32 653 29 47",
    "sg:postcode":"2540",
    "sg:province":"Solothurn",
    "wof:name":"Vinylium Gmbh",
    "wof:placetype":"venue"
},
  "geometry": {"coordinates":[7.3878531456,47.2021408081],"type":"Point"}
}