{
  "type": "Feature",
  "properties": {
    "iso:country":"CH",
    "sg:address":"Binzm\u00fchlenstr. 95",
    "sg:city":"Z\u00fcrich",
    "sg:classifiers":[
        {
            "category":"Utilities",
            "subcategory":"Telephone",
            "type":"Services"
        }
    ],
    "sg:phone":"+41 4113089510",
    "sg:postcode":"8050",
    "sg:province":"Z\u00fcrich",
    "sg:tags":[
        "telecommunication"
    ],
    "wof:name":"Lhs Ag",
    "wof:placetype":"venue"
},
  "geometry": {"coordinates":[8.5405778885,47.4138069153],"type":"Point"}
}