{
  "type": "Feature",
  "properties": {
    "iso:country":"CH",
    "sg:address":"Hirschengraben 48 6003 Luzern. Postfach",
    "sg:city":"Luzern",
    "sg:orig_category":"Tankstellen",
    "sg:phone":"+41 31 982 02 02",
    "sg:postcode":"6002",
    "sg:province":"Luzern",
    "wof:name":"Auto Marti Ag Garage",
    "wof:placetype":"venue"
},
  "geometry": {"coordinates":[7.3801851273,46.9305381775],"type":"Point"}
}