{
  "type": "Feature",
  "properties": {
    "iso:country":"CH",
    "sg:address":"R\u00f6merstrasse 2",
    "sg:city":"Balsthal",
    "sg:orig_category":"Landw. Genossenschaften Viehzucht",
    "sg:postcode":"4710",
    "sg:province":"Solothurn",
    "wof:name":"Fleckviehzuchtgenossenschaft Balsthal",
    "wof:placetype":"venue"
},
  "geometry": {"coordinates":[7.720717907,47.3235054016],"type":"Point"}
}