{
  "type": "Feature",
  "properties": {
    "iso:country":"CH",
    "sg:address":"M\u00e4dergutstrasse 55 3018 Bern. Postfach",
    "sg:city":"Bern",
    "sg:orig_category":"Reiseb\u00fcros U Reiseveranstalter",
    "sg:postcode":"3018",
    "sg:province":"Bern",
    "wof:name":"Ufo-flugreisen M. Dovrtel Fernost-flugreisen",
    "wof:placetype":"venue"
},
  "geometry": {"coordinates":[7.385119915,46.9377403259],"type":"Point"}
}