{
  "type": "Feature",
  "properties": {
    "iso:country":"CH",
    "sg:address":"Staatsstrasse 138",
    "sg:city":"H\u00fcnibach",
    "sg:orig_category":"Nationale Postdienste",
    "sg:phone":"+41 33 243 46 05",
    "sg:postcode":"3626",
    "sg:province":"Bern",
    "wof:name":"Die Schweizerische Post",
    "wof:placetype":"venue"
},
  "geometry": {"coordinates":[7.6447591782,46.7454528809],"type":"Point"}
}