{
  "type": "Feature",
  "properties": {
    "iso:country":"CH",
    "sg:address":"Lehwil",
    "sg:city":"Heitenried",
    "sg:orig_category":"Herstellung von Teppichen Verlegen von Fussboden",
    "sg:phone":"+41 26 495 12 13",
    "sg:postcode":"1714",
    "sg:province":"Fribourg",
    "wof:name":"Botec Bodenbelagstechnik Gmbh",
    "wof:placetype":"venue"
},
  "geometry": {"coordinates":[7.2813301086,46.8358001709],"type":"Point"}
}