{
  "type": "Feature",
  "properties": {
    "iso:country":"CH",
    "sg:address":"Bielstrasse 4b",
    "sg:city":"Kappelen",
    "sg:orig_category":"Vereine Musik/Blasmusik",
    "sg:phone":"+41 32 392 23 86",
    "sg:postcode":"3273",
    "sg:province":"Bern",
    "wof:name":"Musikgesellschaft Kappelen",
    "wof:placetype":"venue"
},
  "geometry": {"coordinates":[7.2564558983,47.0602645874],"type":"Point"}
}