{
  "type": "Feature",
  "properties": {
    "iso:country":"CH",
    "sg:address":"Unterdorfstrasse 16",
    "sg:city":"Buchrain",
    "sg:orig_category":"Kauf U Verkauf von Immobilien auf eigene Rechnung",
    "sg:phone":"+41 41 440 57 53",
    "sg:postcode":"6033",
    "sg:province":"Luzern",
    "wof:name":"Bircher M. & H.",
    "wof:placetype":"venue"
},
  "geometry": {"coordinates":[8.3502435684,47.0953216553],"type":"Point"}
}