{
  "type": "Feature",
  "properties": {
    "iso:country":"CH",
    "sg:address":"Konolfingenstrasse",
    "sg:city":"H\u00e4utligen",
    "sg:orig_category":"Herstellung von Schreinerwaren ohne ausgepr\u00e4gten Schwerpunkt Herstellung von sonstigen Fahrzeugen",
    "sg:phone":"+41 31 791 09 21",
    "sg:postcode":"3510",
    "sg:province":"Bern",
    "wof:name":"Hans Brenzikofer Schreinerei-wagnerei",
    "wof:placetype":"venue"
},
  "geometry": {"coordinates":[7.602930069,46.8604393005],"type":"Point"}
}