{
  "type": "Feature",
  "properties": {
    "iso:country":"CH",
    "sg:address":"Rue Jean-ant.-gautier 12",
    "sg:city":"Gen\u00e8ve",
    "sg:orig_category":"Gymnastik U Fitnesszentren",
    "sg:phone":"+41 22 732 80 50",
    "sg:postcode":"1201",
    "sg:province":"Gen\u00e8ve",
    "wof:name":"Silhouette Health & Fitness Sa Wilson",
    "wof:placetype":"venue"
},
  "geometry": {"coordinates":[6.1501040459,46.213924408],"type":"Point"}
}