{
  "type": "Feature",
  "properties": {
    "addr:full":"Marktgasse 41 8180 B\u00fclach. Postfach B\u00fclach Z\u00fcrich 8180",
    "addr:housenumber":"41",
    "addr:postcode":"8180;8180",
    "addr:street":"Marktgasse;Postfach Buelach Zuerich",
    "iso:country":"CH",
    "sg:address":"Marktgasse 41 8180 B\u00fclach. Postfach",
    "sg:city":"B\u00fclach",
    "sg:orig_category":"Bau\u00e4mter",
    "sg:phone":"+41 18603730",
    "sg:postcode":"8180",
    "sg:province":"Z\u00fcrich",
    "wof:name":"Bauamt",
    "wof:placetype":"venue"
},
  "geometry": {"coordinates":[8.54168,47.516605],"type":"Point"}
}