{
  "type": "Feature",
  "properties": {
    "iso:country":"CH",
    "sg:address":"Traubenweg 24",
    "sg:city":"Frick",
    "sg:orig_category":"Finanzierungsinstitutionen",
    "sg:phone":"+41 62 871 07 37",
    "sg:postcode":"5070",
    "sg:province":"Aargau",
    "wof:name":"Tesan Anlageberatung Und Verm\u00f6gensverwaltung",
    "wof:placetype":"venue"
},
  "geometry": {"coordinates":[8.0257501602,47.5105514526],"type":"Point"}
}