{
  "type": "Feature",
  "properties": {
    "iso:country":"CH",
    "sg:address":"Bahnhofstrasse 54",
    "sg:city":"M\u00fchlethurnen",
    "sg:orig_category":"Fachdetailhandel in Verkaufsr\u00e4umen",
    "sg:phone":"+41 33 356 12 33",
    "sg:postcode":"3127",
    "sg:province":"Bern",
    "wof:name":"Stebi's Check Point Gmbh",
    "wof:placetype":"venue"
},
  "geometry": {"coordinates":[7.5129199028,46.8137512207],"type":"Point"}
}