{
  "type": "Feature",
  "properties": {
    "iso:country":"CH",
    "sg:address":"Thurgauerstrasse 56 8000 Z\u00fcrich. Postfach 8050 Z\u00fcrich",
    "sg:city":"Zust",
    "sg:orig_category":"Instandhaltung U Reparatur von Automobilen",
    "sg:postcode":"50",
    "wof:name":"Credit Suisse Fleetmanagement",
    "wof:placetype":"venue"
},
  "geometry": {"coordinates":[8.5529708862,47.4160308838],"type":"Point"}
}