{
  "type": "Feature",
  "properties": {
    "iso:country":"CH",
    "sg:address":"Povro Via 16",
    "sg:city":"Breganzona",
    "sg:orig_category":"Allgemeiner Hoch U Tiefbau",
    "sg:phone":"+41 91 960 89 70",
    "sg:postcode":"6932",
    "sg:province":"Ticino",
    "wof:name":"Dad Design Architettura Direzione Lavori Sa",
    "wof:placetype":"venue"
},
  "geometry": {"coordinates":[8.924888,46.006405],"type":"Point"}
}