{
  "type": "Feature",
  "properties": {
    "iso:country":"CH",
    "sg:address":"R\u00fctiweg 11",
    "sg:city":"Ostermundigen",
    "sg:orig_category":"Primarschulen",
    "sg:phone":"+41 31 931 16 40",
    "sg:postcode":"3072",
    "sg:province":"Bern",
    "wof:name":"Primarschule R\u00fcti",
    "wof:placetype":"venue"
},
  "geometry": {"coordinates":[7.5013508797,46.9579162598],"type":"Point"}
}