{
  "type": "Feature",
  "properties": {
    "iso:country":"CH",
    "sg:address":"L\u00f6wenstrasse 22",
    "sg:city":"Z\u00fcrich",
    "sg:orig_category":"Reiseb\u00fcros U Reiseveranstalter",
    "sg:phone":"+41 32 913 40 40",
    "sg:postcode":"8001",
    "sg:province":"Z\u00fcrich",
    "wof:name":"Croisitour Voyages Sa",
    "wof:placetype":"venue"
},
  "geometry": {"coordinates":[6.8247351646,47.1003837585],"type":"Point"}
}