{
  "type": "Feature",
  "properties": {
    "iso:country":"CH",
    "sg:address":"Archstrasse 1 8800 Thalwil. Postfach",
    "sg:city":"Thalwil",
    "sg:orig_category":"Betrieb von Taxis",
    "sg:postcode":"8800",
    "sg:province":"Z\u00fcrich",
    "wof:name":"Wenzin-teuscher Gertrud",
    "wof:placetype":"venue"
},
  "geometry": {"coordinates":[8.561709,47.295746],"type":"Point"}
}