{
  "type": "Feature",
  "properties": {
    "iso:country":"CH",
    "sg:address":"Riva Paradiso 26",
    "sg:city":"Paradiso",
    "sg:orig_category":"Vermietung von Automobilen",
    "sg:phone":"+41 91 993 13 13",
    "sg:postcode":"6900",
    "sg:province":"Ticino",
    "wof:name":"Smart Rent Sagl",
    "wof:placetype":"venue"
},
  "geometry": {"coordinates":[8.9507608414,45.9903411865],"type":"Point"}
}