{
  "type": "Feature",
  "properties": {
    "iso:country":"CH",
    "sg:address":"Prayoud Route De 81",
    "sg:city":"Ch\u00e2tel-st-denis",
    "sg:orig_category":"Erbringung von Dienstleistungen f\u00fcr Unternehmen",
    "sg:phone":"+41 21 948 05 61",
    "sg:postcode":"1618",
    "sg:province":"Fribourg",
    "wof:name":"Beram S\u00e0rl",
    "wof:placetype":"venue"
},
  "geometry": {"coordinates":[6.9015398026,46.5275344849],"type":"Point"}
}