{
  "type": "Feature",
  "properties": {
    "iso:country":"CH",
    "sg:address":"Allmendstrasse 1",
    "sg:city":"Huttwil",
    "sg:orig_category":"Maler U Glasergewerbe Tapeziererei",
    "sg:phone":"+41 32 652 42 46",
    "sg:postcode":"4950",
    "sg:province":"Bern",
    "wof:name":"Pedro Miguel Tapezier-& Malergesch\u00e4ft",
    "wof:placetype":"venue"
},
  "geometry": {"coordinates":[7.374915123,47.1866111755],"type":"Point"}
}