{
  "type": "Feature",
  "properties": {
    "iso:country":"CH",
    "sg:address":"Fohlenweidstrasse 45 8615 Wermatswil. Postfach",
    "sg:city":"Wermatswil",
    "sg:orig_category":"Fahrschulen, Flugschulen",
    "sg:phone":"+41 79 661 22 22",
    "sg:postcode":"8615",
    "sg:province":"Z\u00fcrich",
    "wof:name":"Decio & Nicoletta Piccaluga Autofahrschule",
    "wof:placetype":"venue"
},
  "geometry": {"coordinates":[8.7372360229,47.3629379272],"type":"Point"}
}