{
  "type": "Feature",
  "properties": {
    "iso:country":"CH",
    "sg:address":"M\u00fchlegasse 12",
    "sg:city":"Hindelbank",
    "sg:orig_category":"Bauschreinerei Zimmerei, Ingenieurholzbau",
    "sg:phone":"+41 17371536",
    "sg:postcode":"3324",
    "sg:province":"Bern",
    "wof:name":"Heinz Meili Zimmerei Und Innenausbau",
    "wof:placetype":"venue"
},
  "geometry": {"coordinates":[8.435008,47.352821],"type":"Point"}
}