{
  "type": "Feature",
  "properties": {
    "iso:country":"CH",
    "sg:address":"Ruggisberg 9312 H\u00e4ggenschwil. Postfach",
    "sg:city":"L\u00f6mmenschwil",
    "sg:orig_category":"RESTAURANTS: TEA-ROOMS",
    "sg:postcode":"9308",
    "sg:province":"St. Gallen",
    "wof:name":"Wirtschaft Zum Ruggisberg Burgi Und Willy Emmenegger",
    "wof:placetype":"venue"
},
  "geometry": {"coordinates":[9.3715457916,47.4897460938],"type":"Point"}
}