{
  "type": "Feature",
  "properties": {
    "iso:country":"CH",
    "sg:address":"Mettstrasse 83",
    "sg:city":"Biel/bienne",
    "sg:orig_category":"Sportvereine Alpinismus",
    "sg:postcode":"2504",
    "sg:province":"Bern",
    "wof:name":"Bergclub Fl\u00fcgelrad",
    "wof:placetype":"venue"
},
  "geometry": {"coordinates":[7.2673511505,47.1414375305],"type":"Point"}
}