{
  "type": "Feature",
  "properties": {
    "iso:country":"CH",
    "sg:address":"Rue De Cossonay 1bis",
    "sg:city":"Prilly",
    "sg:orig_category":"Sportvereine Ballsport Fussball",
    "sg:postcode":"1008",
    "sg:province":"Vaud",
    "wof:name":"Fc Vepode",
    "wof:placetype":"venue"
},
  "geometry": {"coordinates":[6.6087999344,46.5330200195],"type":"Point"}
}