{
  "type": "Feature",
  "properties": {
    "iso:country":"CH",
    "sg:address":"Belchenstrasse 3 4054 Basel. Postfach",
    "sg:city":"Basel",
    "sg:orig_category":"RESTAURANTS: TEA-ROOMS",
    "sg:postcode":"4051",
    "sg:province":"Basel-Stadt",
    "wof:name":"W. Andres",
    "wof:placetype":"venue"
},
  "geometry": {"coordinates":[7.5742411613,47.5538673401],"type":"Point"}
}