{
  "type": "Feature",
  "properties": {
    "iso:country":"CH",
    "sg:address":"T\u00e4fernstrasse 22a",
    "sg:city":"Baden",
    "sg:orig_category":"Datenverarbeitungsdienste Sonstige mit der Informatik verbundene T\u00e4tigkeiten",
    "sg:phone":"+41 56 483 04 00",
    "sg:postcode":"5405",
    "sg:province":"Aargau",
    "wof:name":"Reich & Fischer Informatik Gmbh",
    "wof:placetype":"venue"
},
  "geometry": {"coordinates":[8.293495,47.447426],"type":"Point"}
}