{
  "type": "Feature",
  "properties": {
    "iso:country":"CH",
    "sg:address":"Lindenstrasse 28",
    "sg:city":"Orpund",
    "sg:orig_category":"D\u00e4mmung gegen K\u00e4lte, W\u00e4rme, Schall U Ersch\u00fctterung",
    "sg:phone":"+41 32 355 31 75",
    "sg:postcode":"2552",
    "sg:province":"Bern",
    "wof:name":"Roland Gastl Sonnen-& Blendschutzsysteme",
    "wof:placetype":"venue"
},
  "geometry": {"coordinates":[7.3124990463,47.1402053833],"type":"Point"}
}