{
  "type": "Feature",
  "properties": {
    "iso:country":"CH",
    "sg:address":"Wattstrasse 26 8307 Effretikon. Postfach",
    "sg:city":"Effretikon",
    "sg:classifiers":[
        {
            "category":"Professional",
            "subcategory":"Employment Agencies",
            "type":"Services"
        }
    ],
    "sg:postcode":"8307",
    "sg:province":"Z\u00fcrich",
    "sg:tags":[
        "personal",
        "u",
        "stellenvermittlung"
    ],
    "wof:name":"Emigrant Heinz Schmid",
    "wof:placetype":"venue"
},
  "geometry": {"coordinates":[8.6929988861,47.4284706116],"type":"Point"}
}