{
  "type": "Feature",
  "properties": {
    "iso:country":"CH",
    "sg:address":"Seminarstrasse 79",
    "sg:city":"Wettingen",
    "sg:classifiers":[
        {
            "category":"Building & Trades",
            "subcategory":"Construction",
            "type":"Services"
        }
    ],
    "sg:phone":"+41 56 426 76 46",
    "sg:postcode":"5430",
    "sg:province":"Aargau",
    "sg:tags":[
        "work",
        "public"
    ],
    "wof:name":"Gartenbau Widmer",
    "wof:placetype":"venue"
},
  "geometry": {"coordinates":[8.314514,47.46228],"type":"Point"}
}