{
  "type": "Feature",
  "properties": {
    "iso:country":"CH",
    "sg:address":"Bundesstrasse 15 6300 Zug. Postfach 4255",
    "sg:city":"Zug",
    "sg:orig_category":"Sonstige Institutionen des Sozialwesens ohne Beherbergung",
    "sg:phone":"+41 41 726 47 77",
    "sg:postcode":"6304",
    "sg:province":"Zug",
    "wof:name":"Beratungstelle Der Evang.- Ref. Kirchgemeinde",
    "wof:placetype":"venue"
},
  "geometry": {"coordinates":[8.512430191,47.171672821],"type":"Point"}
}