{
  "type": "Feature",
  "properties": {
    "iso:country":"CH",
    "sg:address":"Sihlquai 280",
    "sg:city":"Z\u00fcrich",
    "sg:orig_category":"Hardwareberatung",
    "sg:postcode":"8005",
    "sg:province":"Z\u00fcrich",
    "wof:name":"Progress System Sa",
    "wof:placetype":"venue"
},
  "geometry": {"coordinates":[8.5276851654,47.3892478943],"type":"Point"}
}