{
  "type": "Feature",
  "properties": {
    "iso:country":"CH",
    "sg:address":"Gurtengasse 2",
    "sg:city":"Bern",
    "sg:orig_category":"Non-Classified Establishments",
    "sg:postcode":"3011",
    "sg:province":"Bern",
    "wof:name":"Dr. Med. Marco Colombo Spezialarzt Fmh",
    "wof:placetype":"venue"
},
  "geometry": {"coordinates":[7.6849250793,47.0063858032],"type":"Point"}
}