{
  "type": "Feature",
  "properties": {
    "iso:country":"CH",
    "sg:address":"Muristrasse 8",
    "sg:city":"Boswil",
    "sg:orig_category":"Autogaragen",
    "sg:phone":"+41 79 437 86 82",
    "sg:postcode":"5623",
    "sg:province":"Aargau",
    "wof:name":"Erwin Meier Garage Eichb\u00fcel",
    "wof:placetype":"venue"
},
  "geometry": {"coordinates":[8.725045,47.274071],"type":"Point"}
}