{
  "type": "Feature",
  "properties": {
    "iso:country":"CH",
    "sg:address":"Birmensdorferstrasse 280",
    "sg:city":"Z\u00fcrich",
    "sg:orig_category":"Reiseb\u00fcros",
    "sg:phone":"+41 14541133",
    "sg:postcode":"8055",
    "sg:province":"Z\u00fcrich",
    "wof:name":"Plus Reisen Ag",
    "wof:placetype":"venue"
},
  "geometry": {"coordinates":[8.5103111267,47.370059967],"type":"Point"}
}