{
  "type": "Feature",
  "properties": {
    "iso:country":"CH",
    "sg:address":"Dammstrasse 1",
    "sg:city":"Zuchwil",
    "sg:orig_category":"Primarschulen",
    "sg:postcode":"4528",
    "sg:province":"Solothurn",
    "wof:name":"Primarschule Pisoni",
    "wof:placetype":"venue"
},
  "geometry": {"coordinates":[7.5557699203,47.2046051025],"type":"Point"}
}