{
  "type": "Feature",
  "properties": {
    "iso:country":"CH",
    "sg:address":"Bahnhofplatz 3 6370 Stans. Postfach",
    "sg:city":"Stans",
    "sg:orig_category":"Sonstiges Versicherungsgewerbe",
    "sg:postcode":"6370",
    "sg:province":"Nidwalden",
    "wof:name":"Generalagentur Stans Der Schweizerischen Lebensversicherungs Und Rentenanstalt, Bugnon Christoph",
    "wof:placetype":"venue"
},
  "geometry": {"coordinates":[8.3670463562,46.9586791992],"type":"Point"}
}