{
  "type": "Feature",
  "properties": {
    "iso:country":"CH",
    "sg:address":"Grindelstrasse 19 8303 Bassersdorf. Postfach",
    "sg:city":"Bassersdorf",
    "sg:orig_category":"Unclassifiable Establishments",
    "sg:phone":"+41 18386666",
    "sg:postcode":"8303",
    "sg:province":"Z\u00fcrich",
    "wof:name":"Stuco J.p.gysel Bastelmaterialien",
    "wof:placetype":"venue"
},
  "geometry": {"coordinates":[8.6111097336,47.444519043],"type":"Point"}
}