{
  "type": "Feature",
  "properties": {
    "iso:country":"CH",
    "sg:address":"Lindenstrasse 16",
    "sg:city":"Baar",
    "sg:orig_category":"Bauingenieurb\u00fcros Hoch- and Tiefbau",
    "sg:phone":"+41 71 626 98 00",
    "sg:postcode":"6340",
    "sg:province":"Zug",
    "wof:name":"Baur & Partner Architektur Gmbh",
    "wof:placetype":"venue"
},
  "geometry": {"coordinates":[9.138185,47.566669],"type":"Point"}
}