{
  "type": "Feature",
  "properties": {
    "iso:country":"CH",
    "sg:address":"Metzerlenstrasse 11 4115 Mariastein. Postfach",
    "sg:city":"Mariastein",
    "sg:orig_category":"RESTAURANTS: TEA-ROOMS",
    "sg:postcode":"4115",
    "sg:province":"Solothurn",
    "wof:name":"Landgasthof Engel Vrecar I.",
    "wof:placetype":"venue"
},
  "geometry": {"coordinates":[7.4863381386,47.4742012024],"type":"Point"}
}