{
  "type": "Feature",
  "properties": {
    "iso:country":"CH",
    "sg:address":"Chaletweg 4",
    "sg:city":"Rothrist",
    "sg:orig_category":"Public-Relations-Agenturen Werbung",
    "sg:phone":"+41 62 794 35 34",
    "sg:postcode":"4852",
    "sg:province":"Aargau",
    "wof:name":"Werbeagentur Williams Design Communications Gmbh",
    "wof:placetype":"venue"
},
  "geometry": {"coordinates":[7.8843388557,47.3034324646],"type":"Point"}
}