{
  "type": "Feature",
  "properties": {
    "iso:country":"CH",
    "sg:address":"Lerchenweg 11",
    "sg:city":"Sch\u00f6nb\u00fchl-urtenen",
    "sg:orig_category":"Grosshandel mit Geschenkartikeln U Souvenirs Grosshandel mit Spielwaren",
    "sg:phone":"+41 31 859 04 46",
    "sg:postcode":"3322",
    "sg:province":"Bern",
    "wof:name":"Peter Oberlin Handelsagentur",
    "wof:placetype":"venue"
},
  "geometry": {"coordinates":[7.4895200729,47.0213088989],"type":"Point"}
}