{
  "type": "Feature",
  "properties": {
    "iso:country":"CH",
    "sg:address":"Ringwilerstrasse 19",
    "sg:city":"Hinwil",
    "sg:orig_category":"Abwasserreinigung",
    "sg:phone":"+41 79 693 77 81",
    "sg:postcode":"8340",
    "sg:province":"Z\u00fcrich",
    "wof:name":"Heinz Zwicky Kanalreinigung",
    "wof:placetype":"venue"
},
  "geometry": {"coordinates":[8.848455,47.30658],"type":"Point"}
}