{
  "type": "Feature",
  "properties": {
    "iso:country":"CH",
    "sg:address":"Meiersmattstrasse 60",
    "sg:city":"Adligenswil",
    "sg:classifiers":[
        {
            "category":"Professional",
            "subcategory":"Employment Agencies",
            "type":"Services"
        }
    ],
    "sg:phone":"+41 41 370 72 69",
    "sg:postcode":"6043",
    "sg:province":"Luzern",
    "sg:tags":[
        "personal",
        "u",
        "stellenvermittlung"
    ],
    "wof:name":"Personal Portmann",
    "wof:placetype":"venue"
},
  "geometry": {"coordinates":[8.3658504486,47.0673217773],"type":"Point"}
}