{
  "type": "Feature",
  "properties": {
    "iso:country":"CH",
    "sg:address":"Dorfstrasse 19",
    "sg:city":"Ballwil",
    "sg:orig_category":"Kosmetikinstitute",
    "sg:phone":"+41 41 448 31 75",
    "sg:postcode":"6275",
    "sg:province":"Luzern",
    "wof:name":"Madlen F\u00e4ssler Kosmetikinstitut Kosama",
    "wof:placetype":"venue"
},
  "geometry": {"coordinates":[8.3207740784,47.1529960632],"type":"Point"}
}