{
  "type": "Feature",
  "properties": {
    "iso:country":"CH",
    "sg:address":"Wellhauserweg 42 8500 Frauenfeld. Postfach",
    "sg:city":"Frauenfeld",
    "sg:orig_category":"Unclassifiable Establishments",
    "sg:phone":"+41 79 446 74 20",
    "sg:postcode":"8500",
    "sg:province":"Thurgau",
    "wof:name":"Simmi's Gartenpflege Inhaber Wehrli Simon",
    "wof:placetype":"venue"
},
  "geometry": {"coordinates":[8.9170751572,47.5652885437],"type":"Point"}
}