{
  "type": "Feature",
  "properties": {
    "iso:country":"CH",
    "sg:address":"Wolfensbergstrasse 60",
    "sg:city":"Winterthur",
    "sg:orig_category":"Organisationen des Gesundheitswesen",
    "sg:phone":"+41 71 977 21 37",
    "sg:postcode":"8400",
    "sg:province":"Z\u00fcrich",
    "wof:name":"Schweizer Kneippverein",
    "wof:placetype":"venue"
},
  "geometry": {"coordinates":[8.9712963104,47.4314804077],"type":"Point"}
}