{
  "type": "Feature",
  "properties": {
    "iso:country":"CH",
    "sg:address":"Kleinfeldstrasse 9",
    "sg:city":"Triengen",
    "sg:orig_category":"Verlegen von Fliesen U Platten",
    "sg:phone":"+41 41 933 18 33",
    "sg:postcode":"6234",
    "sg:province":"Luzern",
    "wof:name":"Paul Steiger Gmbh Plattenbel\u00e4ge & Chemin\u00e9ebau",
    "wof:placetype":"venue"
},
  "geometry": {"coordinates":[8.0761184692,47.2401313782],"type":"Point"}
}