{
  "type": "Feature",
  "properties": {
    "iso:country":"CH",
    "sg:address":"Route De Schiffenen 12",
    "sg:city":"Fribourg",
    "sg:orig_category":"Malerei Stukkateurgewerbe, Gipserei U Verputzerei",
    "sg:phone":"+41 26 481 50 64",
    "sg:postcode":"1700",
    "sg:province":"Fribourg",
    "wof:name":"Delinor Sa Entreprise De Peinture",
    "wof:placetype":"venue"
},
  "geometry": {"coordinates":[7.1730952263,46.8172111511],"type":"Point"}
}