{
  "type": "Feature",
  "properties": {
    "iso:country":"CH",
    "sg:address":"Busswilstrasse 9c 3250 Lyss. Postfach 55",
    "sg:city":"Lyss",
    "sg:orig_category":"Elektroinstallation",
    "sg:phone":"+41 32 384 49 84",
    "sg:postcode":"3250",
    "sg:province":"Bern",
    "wof:name":"Meinrad Stemmer Elektrische Installationen",
    "wof:placetype":"venue"
},
  "geometry": {"coordinates":[7.3084621429,47.0848617554],"type":"Point"}
}