{
  "type": "Feature",
  "properties": {
    "iso:country":"CH",
    "sg:address":"Laufenstr. 172",
    "sg:city":"Kleinl\u00fctzel",
    "sg:classifiers":[
        {
            "category":"Manufacturing",
            "subcategory":"Tools & Machinery",
            "type":"Manufacturing & Wholesale Goods"
        }
    ],
    "sg:phone":"+41 61 775 11 11",
    "sg:postcode":"4245",
    "sg:province":"Solothurn",
    "sg:tags":[
        "metallurgy",
        "finished",
        "-",
        "metalworking",
        "metallic"
    ],
    "wof:name":"Schloss-und Beschl\u00c4gefabrik Ag",
    "wof:placetype":"venue"
},
  "geometry": {"coordinates":[7.4374370575,47.4290771484],"type":"Point"}
}