{
  "type": "Feature",
  "properties": {
    "iso:country":"CH",
    "sg:address":"1595 Faoug. Postfach",
    "sg:city":"Faoug",
    "sg:orig_category":"Fachdetailhandel in Verkaufsr\u00e4umen",
    "sg:phone":"+41 26 670 27 97",
    "sg:postcode":"1595",
    "sg:province":"Bern",
    "wof:name":"Marina Port De Faoug Sa",
    "wof:placetype":"venue"
},
  "geometry": {"coordinates":[7.0785198212,46.908531189],"type":"Point"}
}