{
  "type": "Feature",
  "properties": {
    "iso:country":"CH",
    "sg:address":"Dorfstrasse 6 1716 Plaffeien. Postfach",
    "sg:city":"Plaffeien",
    "sg:orig_category":"Detailhandel mit Fleisch U Fleischwaren",
    "sg:phone":"+41 26 419 11 08",
    "sg:postcode":"1716",
    "sg:province":"Fribourg",
    "wof:name":"Riedo-bapst Armin",
    "wof:placetype":"venue"
},
  "geometry": {"coordinates":[7.2872858047,46.7409629822],"type":"Point"}
}