{
  "type": "Feature",
  "properties": {
    "iso:country":"CH",
    "sg:address":"B\u00f6sch 104",
    "sg:city":"H\u00fcnenberg",
    "sg:orig_category":"Herstellung von Medikamenten U sonstigen pharmazeutischen Erzeugnissen Herstellung von pharmazeutisc",
    "sg:phone":"+41 41 785 63 40",
    "sg:postcode":"6331",
    "sg:province":"Zug",
    "wof:name":"Dermapharm Ag",
    "wof:placetype":"venue"
},
  "geometry": {"coordinates":[8.4339942932,47.1605987549],"type":"Point"}
}