{
  "type": "Feature",
  "properties": {
    "iso:country":"CH",
    "sg:address":"Le Central",
    "sg:city":"Haute-nendaz",
    "sg:orig_category":"Detailhandel mit fotografischen Artikeln Fotografische Ateliers",
    "sg:phone":"+41 27 288 12 51",
    "sg:postcode":"1997",
    "sg:province":"Valais",
    "wof:name":"Jean-pierre Guillermin",
    "wof:placetype":"venue"
},
  "geometry": {"coordinates":[7.2981119156,46.1841583252],"type":"Point"}
}