{
  "type": "Feature",
  "properties": {
    "iso:country":"CH",
    "sg:address":"D\u00e4ndlikerweg 46",
    "sg:city":"Bern",
    "sg:orig_category":"Vorschulen, Kinderg\u00e4rten",
    "sg:phone":"+41 31 331 00 02",
    "sg:postcode":"3014",
    "sg:province":"Bern",
    "wof:name":"Kindergarten Wylergut I",
    "wof:placetype":"venue"
},
  "geometry": {"coordinates":[7.448363781,46.9645729065],"type":"Point"}
}