{
  "type": "Feature",
  "properties": {
    "iso:country":"CH",
    "sg:address":"Route De Neuch\u00e2tel",
    "sg:city":"Payerne",
    "sg:classifiers":[
        {
            "category":"Utilities",
            "subcategory":"Recycling",
            "type":"Services"
        }
    ],
    "sg:phone":"+41 26 662 71 11",
    "sg:postcode":"1530",
    "sg:province":"Vaud",
    "sg:tags":[
        "vehicle",
        "truck",
        "accessory"
    ],
    "wof:name":"Pwp S.a.",
    "wof:placetype":"venue"
},
  "geometry": {"coordinates":[6.9385,46.824795],"type":"Point"}
}