{
  "type": "Feature",
  "properties": {
    "iso:country":"CH",
    "sg:address":"Avenue De La Confr\u00e9rie 3",
    "sg:city":"Prilly",
    "sg:orig_category":"Detailhandel mit Waren verschiedener Art, Hauptrichtung Nahrungsmittel Grosshandel mit Nahrungsmitte",
    "sg:phone":"+41 32 953 12 28",
    "sg:postcode":"1008",
    "sg:province":"Vaud",
    "wof:name":"Alimentation De La Rauracie Jacques & Nelly Lollier",
    "wof:placetype":"venue"
},
  "geometry": {"coordinates":[6.9565172195,47.2243614197],"type":"Point"}
}