{
  "type": "Feature",
  "properties": {
    "iso:country":"CH",
    "sg:address":"Les Cr\u00eats Leyron",
    "sg:city":"Grandvaux",
    "sg:orig_category":"Architektur U Ingenieurb\u00fcros",
    "sg:phone":"+41 21 799 25 92",
    "sg:postcode":"1091",
    "sg:province":"Vaud",
    "wof:name":"Planidec Sa",
    "wof:placetype":"venue"
},
  "geometry": {"coordinates":[6.727161,46.502434],"type":"Point"}
}