{
  "type": "Feature",
  "properties": {
    "iso:country":"CH",
    "sg:address":"Route Du Simplon 44",
    "sg:city":"Ardon",
    "sg:orig_category":"Nationale Postdienste",
    "sg:phone":"+41 27 306 55 00",
    "sg:postcode":"1957",
    "sg:province":"Valais",
    "wof:name":"La Poste Suisse",
    "wof:placetype":"venue"
},
  "geometry": {"coordinates":[7.2577929497,46.211555481],"type":"Point"}
}