{
  "type": "Feature",
  "properties": {
    "iso:country":"CH",
    "sg:address":"Capite Route De La 18 A",
    "sg:city":"Cologny",
    "sg:orig_category":"Vermietung U Verpachtung von eigenen Immobilien",
    "sg:postcode":"1223",
    "sg:province":"Gen\u00e8ve",
    "wof:name":"Jps Sa",
    "wof:placetype":"venue"
},
  "geometry": {"coordinates":[7.4068250656,46.2767829895],"type":"Point"}
}