{
  "type": "Feature",
  "properties": {
    "iso:country":"CH",
    "sg:address":"Via Rovedo 22",
    "sg:city":"Locarno",
    "sg:orig_category":"Werbegrafikateliers",
    "sg:phone":"+41 91 751 96 57",
    "sg:postcode":"6600",
    "sg:province":"Ticino",
    "wof:name":"Ray Knobel Studio Grafico",
    "wof:placetype":"venue"
},
  "geometry": {"coordinates":[8.7870426178,46.1658363342],"type":"Point"}
}