{
  "type": "Feature",
  "properties": {
    "iso:country":"CH",
    "sg:address":"Hauptstrasse 52",
    "sg:city":"Orpund",
    "sg:orig_category":"Elektroinstallation",
    "sg:phone":"+41 32 355 27 77",
    "sg:postcode":"2552",
    "sg:province":"Bern",
    "wof:name":"Electroteam Arn & Lenggenhager",
    "wof:placetype":"venue"
},
  "geometry": {"coordinates":[7.2897171974,47.1413879395],"type":"Point"}
}