{
  "type": "Feature",
  "properties": {
    "iso:country":"CH",
    "sg:address":"1978 Lens. Postfach 37",
    "sg:city":"Lens",
    "sg:orig_category":"Sportvereine Ballsport Fussball",
    "sg:phone":"+41 27 483 43 95",
    "sg:postcode":"1978",
    "sg:province":"Valais",
    "wof:name":"Fc Lens",
    "wof:placetype":"venue"
},
  "geometry": {"coordinates":[7.4485402107,46.2786102295],"type":"Point"}
}