{
  "type": "Feature",
  "properties": {
    "iso:country":"CH",
    "sg:address":"Appenzellerstrasse 1",
    "sg:city":"Rheineck",
    "sg:orig_category":"Instandhaltung U Reparatur von Automobilen",
    "sg:phone":"+41 71 888 11 20",
    "sg:postcode":"9424",
    "sg:province":"St. Gallen",
    "wof:name":"Hersche Alexander",
    "wof:placetype":"venue"
},
  "geometry": {"coordinates":[9.5919933319,47.4644317627],"type":"Point"}
}