{
  "type": "Feature",
  "properties": {
    "iso:country":"CH",
    "sg:address":"Claragraben 117",
    "sg:city":"Basel",
    "sg:orig_category":"Werbung",
    "sg:postcode":"4057",
    "sg:province":"Basel-Stadt",
    "wof:name":"Ping Pong Kommunikation Frank Mario",
    "wof:placetype":"venue"
},
  "geometry": {"coordinates":[7.5929708481,47.5637588501],"type":"Point"}
}