{
  "type": "Feature",
  "properties": {
    "addr:full":"Kramershaus Heimisbach Bern 3453",
    "addr:postcode":"3453",
    "iso:country":"CH",
    "sg:address":"Kramershaus",
    "sg:city":"Heimisbach",
    "sg:orig_category":"Detailhandel mit Brot, Back U S\u00fcsswaren",
    "sg:phone":"+41 34 431 16 32",
    "sg:postcode":"3453",
    "sg:province":"Bern",
    "wof:name":"Hans Anliker B\u00e4ckerei",
    "wof:placetype":"venue"
},
  "geometry": {"coordinates":[7.76107,47.012047],"type":"Point"}
}