{
  "type": "Feature",
  "properties": {
    "iso:country":"CH",
    "sg:address":"Obertor 38 8400 Winterthur. Postfach",
    "sg:city":"Winterthur",
    "sg:orig_category":"Detailhandel mit Radio U Fernsehger\u00e4ten Detailhandel mit fotografischen Artikeln",
    "sg:phone":"+41 52 214 11 61",
    "sg:postcode":"8402",
    "sg:province":"Z\u00fcrich",
    "wof:name":"Interdiscount Ag Hi-fi Video Photo Radio",
    "wof:placetype":"venue"
},
  "geometry": {"coordinates":[8.7317028046,47.500125885],"type":"Point"}
}