{
  "type": "Feature",
  "properties": {
    "addr:full":"Hauptstrasse Mandach Aargau 5318",
    "addr:postcode":"5318",
    "addr:street":"Hauptstrasse",
    "iso:country":"CH",
    "sg:address":"Hauptstrasse",
    "sg:city":"Mandach",
    "sg:classifiers":[
        {
            "category":"Banks & Credit Unions",
            "subcategory":"Bank",
            "type":"Services"
        }
    ],
    "sg:phone":"+41 4156442306",
    "sg:postcode":"5318",
    "sg:province":"Aargau",
    "wof:name":"Raiffeisenbank",
    "wof:placetype":"venue"
},
  "geometry": {"coordinates":[8.186914,47.547901],"type":"Point"}
}