{
  "type": "Feature",
  "properties": {
    "iso:country":"CH",
    "sg:address":"Baumgarten 754",
    "sg:city":"Kleinl\u00fctzel",
    "sg:orig_category":"K\u00fcnstlerische U schriftstellerische T\u00e4tigkeiten U Darbietungen",
    "sg:phone":"+41 61 773 00 80",
    "sg:postcode":"4245",
    "sg:province":"Solothurn",
    "wof:name":"Canadian Arctic Gallery Grunder",
    "wof:placetype":"venue"
},
  "geometry": {"coordinates":[7.4209618568,47.4239234924],"type":"Point"}
}