{
  "type": "Feature",
  "properties": {
    "iso:country":"CH",
    "sg:address":"Avenue De La Rochelle 20",
    "sg:city":"Prilly",
    "sg:orig_category":"Architektur U Ingenieurb\u00fcros",
    "sg:phone":"+41 21 624 96 82",
    "sg:postcode":"1008",
    "sg:province":"Vaud",
    "wof:name":"Eric Mellier Bureau D'ing\u00e9nieur",
    "wof:placetype":"venue"
},
  "geometry": {"coordinates":[6.601885,46.532791],"type":"Point"}
}