{
  "type": "Feature",
  "properties": {
    "iso:country":"CH",
    "sg:address":"Chemin De La Traverse 5",
    "sg:city":"Aubonne",
    "sg:orig_category":"Sonstiger Grosshandel",
    "sg:phone":"+41 71 633 17 94",
    "sg:postcode":"1170",
    "sg:province":"Vaud",
    "wof:name":"Schoch Trading Cie",
    "wof:placetype":"venue"
},
  "geometry": {"coordinates":[9.1522407532,47.5501747131],"type":"Point"}
}