{
  "type": "Feature",
  "properties": {
    "iso:country":"CH",
    "sg:address":"5108",
    "sg:city":"Oberflachs",
    "sg:orig_category":"Sportvereine Sch\u00fctzen",
    "sg:phone":"+41 31 791 38 28",
    "sg:postcode":"5108",
    "sg:province":"Aargau",
    "wof:name":"Feldsch\u00fctzengesellschaft",
    "wof:placetype":"venue"
},
  "geometry": {"coordinates":[8.1235198975,47.4377593994],"type":"Point"}
}