{
  "type": "Feature",
  "properties": {
    "iso:country":"CH",
    "sg:address":"Buchmattstrasse 19",
    "sg:city":"Thunstetten",
    "sg:orig_category":"Sportvereine Ballsport Tennis",
    "sg:phone":"+41 62 963 21 70",
    "sg:postcode":"4922",
    "sg:province":"Bern",
    "wof:name":"Tc Herzogenbuchsee",
    "wof:placetype":"venue"
},
  "geometry": {"coordinates":[7.7613148689,47.2047080994],"type":"Point"}
}