{
  "type": "Feature",
  "properties": {
    "iso:country":"CH",
    "sg:address":"Industriestr. 34",
    "sg:city":"W\u00fcnnewil",
    "sg:orig_category":"Herstellung von Elektrizit\u00e4tsverteilungs U schalteinrichtungen",
    "sg:phone":"+41 31 741 11 11",
    "sg:postcode":"3184",
    "sg:province":"Fribourg",
    "wof:name":"Aebi & Zbinden Elektrobau Gmbh",
    "wof:placetype":"venue"
},
  "geometry": {"coordinates":[7.3271780014,46.8878135681],"type":"Point"}
}