{
  "type": "Feature",
  "properties": {
    "iso:country":"CH",
    "sg:address":"Kapfweid 14",
    "sg:city":"Emmenbr\u00fccke",
    "sg:orig_category":"Gartenbau",
    "sg:phone":"+41 41 280 18 92",
    "sg:postcode":"6020",
    "sg:province":"Luzern",
    "wof:name":"Kliebensch\u00e4del Karl",
    "wof:placetype":"venue"
},
  "geometry": {"coordinates":[8.2756671906,47.0884056091],"type":"Point"}
}