{
  "type": "Feature",
  "properties": {
    "iso:country":"CH",
    "sg:address":"Charmilles Chemin Des 7",
    "sg:city":"Blonay",
    "sg:orig_category":"Grosshandel mit sonstigen Gebrauchs U Verbrauchsg\u00fctern",
    "sg:phone":"+41 21 943 20 18",
    "sg:postcode":"1807",
    "sg:province":"Vaud",
    "wof:name":"Roadrunner Mkt & Import S\u00e0rl",
    "wof:placetype":"venue"
},
  "geometry": {"coordinates":[6.8949828148,46.4651298523],"type":"Point"}
}