{
  "type": "Feature",
  "properties": {
    "iso:country":"CH",
    "sg:address":"Dapples Avenue 9",
    "sg:city":"Lausanne",
    "sg:orig_category":"Dienstleistungen von Beteiligungsgesellschaften",
    "sg:phone":"+41 55 462 18 81",
    "sg:postcode":"1006",
    "sg:province":"Vaud",
    "wof:name":"Las Ag Aerzteservices",
    "wof:placetype":"venue"
},
  "geometry": {"coordinates":[8.8618116379,47.2033348083],"type":"Point"}
}