{
  "type": "Feature",
  "properties": {
    "iso:country":"CH",
    "sg:address":"G\u00f6nhardweg 28 5000 Aarau. Postfach",
    "sg:city":"Aarau",
    "sg:orig_category":"Allgemeiner Hoch U Tiefbau Herstellung von Fenstern U T\u00fcren aus Holz",
    "sg:phone":"+41 62 822 77 22",
    "sg:postcode":"5001",
    "sg:province":"Aargau",
    "wof:name":"Zubler Ag",
    "wof:placetype":"venue"
},
  "geometry": {"coordinates":[8.051699,47.385891],"type":"Point"}
}