{
  "type": "Feature",
  "properties": {
    "iso:country":"CH",
    "sg:address":"Aarbergergasse 29 3011 Bern. Postfach 6161",
    "sg:city":"Bern",
    "sg:orig_category":"Advokaturb\u00fcros",
    "sg:phone":"+41 31 311 62 81",
    "sg:postcode":"3001",
    "sg:province":"Bern",
    "wof:name":"Alphonse Fivaz Advokaturb\u00fcro",
    "wof:placetype":"venue"
},
  "geometry": {"coordinates":[7.442708,46.949547],"type":"Point"}
}