{
  "type": "Feature",
  "properties": {
    "iso:country":"CH",
    "sg:address":"Rue Louis-favre 29",
    "sg:city":"Gen\u00e8ve",
    "sg:orig_category":"Fachdetailhandel in Verkaufsr\u00e4umen Kunsthandel",
    "sg:phone":"+41 22 734 71 58",
    "sg:postcode":"1201",
    "sg:province":"Gen\u00e8ve",
    "wof:name":"Art D\u00e9veloppement Adt Sa",
    "wof:placetype":"venue"
},
  "geometry": {"coordinates":[6.137430191,46.2114143372],"type":"Point"}
}