{
  "type": "Feature",
  "properties": {
    "iso:country":"CH",
    "sg:address":"Gotthardstrasse 20",
    "sg:city":"Thalwil",
    "sg:orig_category":"Unclassifiable Establishments",
    "sg:postcode":"8800",
    "sg:province":"Z\u00fcrich",
    "wof:name":"Modeagentur Duett Elzbieta Benz",
    "wof:placetype":"venue"
},
  "geometry": {"coordinates":[8.4105043411,47.4451332092],"type":"Point"}
}