{
  "type": "Feature",
  "properties": {
    "iso:country":"CH",
    "sg:address":"Kosthausstrasse 6",
    "sg:city":"Kriens",
    "sg:orig_category":"Sonstige mit der Informatik verbundene T\u00e4tigkeiten",
    "sg:phone":"+41 41 329 81 81",
    "sg:postcode":"6010",
    "sg:province":"Luzern",
    "wof:name":"Ksm Komsoft M\u00fcller",
    "wof:placetype":"venue"
},
  "geometry": {"coordinates":[8.2751569748,47.0337677002],"type":"Point"}
}