{
  "type": "Feature",
  "properties": {
    "iso:country":"CH",
    "sg:address":"Mantegazza Via Gregorio 6600 Locarno. Postfach",
    "sg:city":"Locarno",
    "sg:orig_category":"Handel mit Automobilen",
    "sg:postcode":"6600",
    "sg:province":"Ticino",
    "wof:name":"Seixa Freitas Jos\u00e9 Luciano Import-export Di Auto, Centro Di Recupero Auto",
    "wof:placetype":"venue"
},
  "geometry": {"coordinates":[8.7942647934,46.1657409668],"type":"Point"}
}