{
  "type": "Feature",
  "properties": {
    "iso:country":"CH",
    "sg:address":"Avenue De La Gare 26 1003 Lausanne Case Postale 1112",
    "sg:city":"Lausanne",
    "sg:orig_category":"Vermietung U Verpachtung von eigenen Immobilien Vermittlung von Immobilien",
    "sg:phone":"+41 21 311 11 11",
    "sg:postcode":"1001",
    "sg:province":"Vaud",
    "wof:name":"Nicod Bernard Sa",
    "wof:placetype":"venue"
},
  "geometry": {"coordinates":[6.6328759193,46.5172195435],"type":"Point"}
}