{
  "type": "Feature",
  "properties": {
    "iso:country":"CH",
    "sg:address":"Hohenb\u00fchlstrasse 1 8032 Z\u00fcrich",
    "sg:city":"Zust",
    "sg:orig_category":"Kauf U Verkauf von Immobilien auf eigene Rechnung",
    "sg:postcode":"32",
    "wof:name":"Ag Fellhof 76",
    "wof:placetype":"venue"
},
  "geometry": {"coordinates":[8.5679702759,47.3668403625],"type":"Point"}
}