{
  "type": "Feature",
  "properties": {
    "iso:country":"CH",
    "sg:address":"Dornacherstrasse 31",
    "sg:city":"Solothurn",
    "sg:orig_category":"Allgemeiner Hoch U Tiefbau",
    "sg:phone":"+41 32 622 13 22",
    "sg:postcode":"4500",
    "sg:province":"Solothurn",
    "wof:name":"Keller + D\u00e4llenbach Ag, Ingenieurb\u00fcro",
    "wof:placetype":"venue"
},
  "geometry": {"coordinates":[7.540301,47.204262],"type":"Point"}
}