{
  "type": "Feature",
  "properties": {
    "iso:country":"CH",
    "sg:address":"Poststrasse 14",
    "sg:city":"Luterbach",
    "sg:orig_category":"Mechanische Werkst\u00e4tten",
    "sg:phone":"+41 71 870 00 55",
    "sg:postcode":"4542",
    "sg:province":"Solothurn",
    "wof:name":"Repi Repair Gmbh",
    "wof:placetype":"venue"
},
  "geometry": {"coordinates":[9.4898195267,47.4155807495],"type":"Point"}
}