{
  "type": "Feature",
  "properties": {
    "iso:country":"CH",
    "sg:address":"Chemin Du Foron 19 1226 Th\u00f4nex Case Postale 332",
    "sg:city":"Th\u00f4nex",
    "sg:orig_category":"Herstellung von Anstrichmitteln, Druckfarben U Kitten Herstellung von Klebstoffen U Gelatinen",
    "sg:phone":"+41 26 912 16 16",
    "sg:postcode":"1226",
    "sg:province":"Gen\u00e8ve",
    "wof:name":"Carryfix Promotion Sa",
    "wof:placetype":"venue"
},
  "geometry": {"coordinates":[7.0522799492,46.6153488159],"type":"Point"}
}