{
  "type": "Feature",
  "properties": {
    "iso:country":"CH",
    "sg:address":"Kradolfstrasse 15 8583 Sulgen. Postfach 83",
    "sg:city":"Sulgen",
    "sg:orig_category":"Landesverteidigung, Sozialversicherung \u00d6ffentliche Verwaltung",
    "sg:phone":"+41 62 875 12 36",
    "sg:postcode":"8583",
    "sg:province":"Thurgau",
    "wof:name":"Zivilschutzstelle Sulz",
    "wof:placetype":"venue"
},
  "geometry": {"coordinates":[8.0957698822,47.5344696045],"type":"Point"}
}