{
  "type": "Feature",
  "properties": {
    "iso:country":"CH",
    "sg:address":"Hardstrasse 41 5430 Wettingen. Postfach",
    "sg:city":"Aarau",
    "sg:orig_category":"Detailhandel mit elektrischen Haushalts-,Radio U Fernsehger\u00e4ten sowie Musikinstrumenten Grosshandel ",
    "sg:phone":"+41 56 437 90 90",
    "sg:postcode":"5000",
    "sg:province":"Aargau",
    "wof:name":"Macrosystem Digital Video Schweiz Ag Produkte Der Digitalen Videobe Und Verarbeitung; Vertrieb",
    "wof:placetype":"venue"
},
  "geometry": {"coordinates":[8.3325529099,47.4593391418],"type":"Point"}
}