{
  "type": "Feature",
  "properties": {
    "iso:country":"CH",
    "sg:address":"H\u00e4rkingerstrasse 1 4617 Gunzgen. Postfach 69",
    "sg:city":"Gunzgen",
    "sg:orig_category":"Herstellung von Betonerzeugnissen f\u00fcr den Bau Herstellung von Erzeugnissen aus Beton, Gips U Zement",
    "sg:phone":"+41 62 209 40 50",
    "sg:postcode":"4617",
    "sg:province":"Solothurn",
    "wof:name":"Fritschi Bauelemente Ag",
    "wof:placetype":"venue"
},
  "geometry": {"coordinates":[7.8373699188,47.3065032959],"type":"Point"}
}