{
  "type": "Feature",
  "properties": {
    "iso:country":"CH",
    "sg:address":"Buchzelgstrasse 52",
    "sg:city":"Z\u00fcrich",
    "sg:classifiers":[
        {
            "category":"Restaurant",
            "type":"Food & Drink"
        }
    ],
    "sg:phone":"+41 13816540",
    "sg:postcode":"8053",
    "sg:province":"Z\u00fcrich",
    "wof:name":"Restaurant Buchzelg",
    "wof:placetype":"venue"
},
  "geometry": {"coordinates":[8.587348938,47.3595428467],"type":"Point"}
}