{
  "type": "Feature",
  "properties": {
    "iso:country":"CH",
    "sg:address":"Hochwangstrasse",
    "sg:city":"Zizers",
    "sg:orig_category":"Finanzierungsinstitutionen",
    "sg:postcode":"7205",
    "sg:province":"Graubunden",
    "wof:name":"Capricorn Management, Van Der Wees, Philippus Johannes",
    "wof:placetype":"venue"
},
  "geometry": {"coordinates":[9.5692186356,46.9380302429],"type":"Point"}
}