{
  "type": "Feature",
  "properties": {
    "iso:country":"CH",
    "sg:address":"Piazza Comunale 5",
    "sg:city":"Biasca",
    "sg:orig_category":"Sportvereine Ski",
    "sg:phone":"+41 91 862 45 30",
    "sg:postcode":"6710",
    "sg:province":"Ticino",
    "wof:name":"Sci Club Biasca",
    "wof:placetype":"venue"
},
  "geometry": {"coordinates":[8.9711856842,46.3615379333],"type":"Point"}
}