{
  "type": "Feature",
  "properties": {
    "iso:country":"CH",
    "sg:address":"Avenue Du L\u00e9man 62",
    "sg:city":"Lausanne",
    "sg:orig_category":"Physiotherapie",
    "sg:phone":"+41 21 944 23 84",
    "sg:postcode":"1004",
    "sg:province":"Vaud",
    "wof:name":"Anne-marie Ramel Physioth\u00e9rapie",
    "wof:placetype":"venue"
},
  "geometry": {"coordinates":[6.8676290512,46.4506874084],"type":"Point"}
}