{
  "type": "Feature",
  "properties": {
    "iso:country":"CH",
    "sg:address":"Via Maggio 1 6900 Lugano. Postfach 6906 Lugano",
    "sg:city":"Caselle",
    "sg:orig_category":"Sonstige mit der Informatik verbundene T\u00e4tigkeiten",
    "sg:postcode":"6",
    "wof:name":"Eidosmedia Investments Sl, Madrid, Succursale Di Lugano",
    "wof:placetype":"venue"
},
  "geometry": {"coordinates":[8.961098671,46.0080337524],"type":"Point"}
}