{
  "type": "Feature",
  "properties": {
    "iso:country":"CH",
    "sg:address":"9038",
    "sg:city":"Rehetobel",
    "sg:orig_category":"Vereine Frauen Vereine Gemeinn\u00fctzige",
    "sg:phone":"+41 71 877 22 38",
    "sg:postcode":"9038",
    "sg:province":"Appenzell Ausserrhoden",
    "wof:name":"Gemeinn\u00fctziger Frauenverein",
    "wof:placetype":"venue"
},
  "geometry": {"coordinates":[9.4833850861,47.4260749817],"type":"Point"}
}