{
  "type": "Feature",
  "properties": {
    "iso:country":"CH",
    "sg:address":"K\u00fchlhausstrasse 8 4900 Langenthal. Postfach",
    "sg:city":"Langenthal",
    "sg:orig_category":"Grosshandel mit Obst U Gem\u00fcse",
    "sg:phone":"+41 62 916 13 01",
    "sg:postcode":"4901",
    "sg:province":"Bern",
    "wof:name":"Fr\u00fcchte Geiser Ag",
    "wof:placetype":"venue"
},
  "geometry": {"coordinates":[7.7825160027,47.2181396484],"type":"Point"}
}