{
  "type": "Feature",
  "properties": {
    "iso:country":"CH",
    "sg:address":"Rue De L'h\u00f4pital 2",
    "sg:city":"Fribourg",
    "sg:orig_category":"Organisationen der Wohlfahrtspflege",
    "sg:phone":"+41 71 223 67 67",
    "sg:postcode":"1700",
    "sg:province":"Fribourg",
    "wof:name":"Ostschweiz.diabetes- Gesellschaft",
    "wof:placetype":"venue"
},
  "geometry": {"coordinates":[9.3748483658,47.4239997864],"type":"Point"}
}