{
  "type": "Feature",
  "properties": {
    "addr:full":"Hirschwiesenweg 7 Schaffhausen Schaffhausen 8200",
    "addr:housenumber":"7",
    "addr:postcode":"8200",
    "addr:street":"Hirschwiesenweg",
    "iso:country":"CH",
    "sg:address":"Hirschwiesenweg 7",
    "sg:city":"Schaffhausen",
    "sg:orig_category":"Architektur U Ingenieurb\u00fcros Architekturb\u00fcros",
    "sg:phone":"+41 52 643 30 32",
    "sg:postcode":"8200",
    "sg:province":"Schaffhausen",
    "wof:name":"M\u00fcller Erwin Ag",
    "wof:placetype":"venue"
},
  "geometry": {"coordinates":[8.646361,47.718498],"type":"Point"}
}