{
  "type": "Feature",
  "properties": {
    "iso:country":"CH",
    "sg:address":"Bernstrasse 1",
    "sg:city":"Thun",
    "sg:orig_category":"Bestattungswesen",
    "sg:phone":"+41 33 223 24 09",
    "sg:postcode":"3600",
    "sg:province":"Bern",
    "wof:name":"Hansruedi B\u00f6nzli Bestattungen",
    "wof:placetype":"venue"
},
  "geometry": {"coordinates":[7.628563,46.762039],"type":"Point"}
}