{
  "type": "Feature",
  "properties": {
    "iso:country":"CH",
    "sg:address":"Alter Hubelweg 4",
    "sg:city":"H\u00fcnenberg",
    "sg:orig_category":"Herstellung von Metallkonstruktionen",
    "sg:postcode":"6331",
    "sg:province":"Zug",
    "wof:name":"Montageservice Hirschi",
    "wof:placetype":"venue"
},
  "geometry": {"coordinates":[8.4318161011,47.1779975891],"type":"Point"}
}