{
  "type": "Feature",
  "properties": {
    "iso:country":"CH",
    "sg:address":"Roseli\u00e8re Chemin De La",
    "sg:city":"F\u00e9chy",
    "sg:orig_category":"Herstellung von elektronischen Bauelementen",
    "sg:postcode":"1173",
    "sg:province":"Vaud",
    "wof:name":"Stratos Technologie Sa",
    "wof:placetype":"venue"
},
  "geometry": {"coordinates":[6.3701400757,46.4815368652],"type":"Point"}
}