{
  "type": "Feature",
  "properties": {
    "iso:country":"CH",
    "sg:address":"Allmendweg 2",
    "sg:city":"Laufen",
    "sg:orig_category":"Non-Classified Establishments",
    "sg:postcode":"4242",
    "sg:province":"Basel-Landschaft",
    "wof:name":"Dr.med.martin Tschan Spezialarzt Fmh",
    "wof:placetype":"venue"
},
  "geometry": {"coordinates":[7.5004210472,47.4241409302],"type":"Point"}
}