{
  "type": "Feature",
  "properties": {
    "iso:country":"CH",
    "sg:address":"Piazza Borromini 21",
    "sg:city":"Bissone",
    "sg:orig_category":"Unclassifiable Establishments",
    "sg:phone":"+41 91 649 51 50",
    "sg:postcode":"6816",
    "sg:province":"Ticino",
    "wof:name":"Ristorante Ticino",
    "wof:placetype":"venue"
},
  "geometry": {"coordinates":[8.9646701813,45.9501533508],"type":"Point"}
}