{
  "type": "Feature",
  "properties": {
    "iso:country":"CH",
    "sg:address":"Alte Bahnhofstrasse 5",
    "sg:city":"Wohlen",
    "sg:classifiers":[
        {
            "category":"Shopping",
            "subcategory":"Musical Instruments",
            "type":"Retail Goods"
        }
    ],
    "sg:phone":"+41 56 622 48 36",
    "sg:postcode":"5610",
    "sg:province":"Aargau",
    "sg:tags":[
        "brass"
    ],
    "wof:name":"Musik Bieri Ag",
    "wof:placetype":"venue"
},
  "geometry": {"coordinates":[8.271098,47.350105],"type":"Point"}
}