{
  "type": "Feature",
  "properties": {
    "iso:country":"CH",
    "sg:address":"Route De St-cergue 68",
    "sg:city":"Nyon",
    "sg:orig_category":"Handel mit Motorr\u00e4dern, Teilen U Zubeh\u00f6r Instandhaltung U Reparatur von Automobilen Instandhaltung U",
    "sg:phone":"+41 22 361 32 45",
    "sg:postcode":"1260",
    "sg:province":"Vaud",
    "wof:name":"Jean-pierre Baudat Cycles Motos",
    "wof:placetype":"venue"
},
  "geometry": {"coordinates":[6.2312488556,46.3914108276],"type":"Point"}
}