{
  "type": "Feature",
  "properties": {
    "iso:country":"CH",
    "sg:address":"Bachstrasse 17",
    "sg:city":"Oberstammheim",
    "sg:orig_category":"Herstellung von sonstigen Holzwaren",
    "sg:postcode":"8477",
    "sg:province":"Z\u00fcrich",
    "wof:name":"Berseth Adrien.",
    "wof:placetype":"venue"
},
  "geometry": {"coordinates":[6.2603201866,46.5135612488],"type":"Point"}
}