{
  "type": "Feature",
  "properties": {
    "iso:country":"CH",
    "sg:address":"Sonnmattstrand 17",
    "sg:city":"Neuenkirch",
    "sg:orig_category":"Rechtsberatung Unternehmensberatung",
    "sg:phone":"+41 41 467 24 28",
    "sg:postcode":"6206",
    "sg:province":"Luzern",
    "wof:name":"Bauinvestment Stachon Unternehmens-& Rechtsberatung",
    "wof:placetype":"venue"
},
  "geometry": {"coordinates":[8.2195749283,47.0959014893],"type":"Point"}
}