{
  "type": "Feature",
  "properties": {
    "iso:country":"CH",
    "sg:address":"Kaspar-koppstrasse 81",
    "sg:city":"Ebikon",
    "sg:orig_category":"Detailhandel mit Uhren U Schmuck",
    "sg:phone":"+41 41 420 44 00",
    "sg:postcode":"6030",
    "sg:province":"Luzern",
    "wof:name":"Jakob & Anton Huber Gold-& Silberschmiede",
    "wof:placetype":"venue"
},
  "geometry": {"coordinates":[8.3224048615,47.0716056824],"type":"Point"}
}