{
  "type": "Feature",
  "properties": {
    "iso:country":"CH",
    "sg:address":"Im Schachenhof 23 B",
    "sg:city":"Bonstetten",
    "sg:orig_category":"Herstellung von elektrischen Lampen U Leuchten",
    "sg:postcode":"8906",
    "sg:province":"Z\u00fcrich",
    "wof:name":"Pmm Orlemann Production",
    "wof:placetype":"venue"
},
  "geometry": {"coordinates":[8.4728717804,47.3276901245],"type":"Point"}
}