{
  "type": "Feature",
  "properties": {
    "addr:full":"1588 Cudrefin Vaud 1588",
    "addr:postcode":"1588;1588",
    "iso:country":"CH",
    "sg:address":"1588",
    "sg:city":"Cudrefin",
    "sg:orig_category":"Blumen U Zierpflanzenbau",
    "sg:phone":"+41 71 277 63 28",
    "sg:postcode":"1588",
    "sg:province":"Vaud",
    "wof:name":"Dieter Ansorge G\u00e4rtnerei",
    "wof:placetype":"venue"
},
  "geometry": {"coordinates":[9.353453,47.42181],"type":"Point"}
}