{
  "type": "Feature",
  "properties": {
    "iso:country":"CH",
    "sg:address":"8424",
    "sg:city":"Embrach",
    "sg:orig_category":"Vereine Frauen Vereine Gemeinn\u00fctzige",
    "sg:phone":"+41 19101479",
    "sg:postcode":"8424",
    "sg:province":"Z\u00fcrich",
    "wof:name":"Frauenverein Erlenbach",
    "wof:placetype":"venue"
},
  "geometry": {"coordinates":[8.5967206955,47.3044052124],"type":"Point"}
}