{
  "type": "Feature",
  "properties": {
    "iso:country":"CH",
    "sg:address":"Z\u00fcrcherstrasse 160",
    "sg:city":"Frauenfeld",
    "sg:orig_category":"Detailhandel mit elektrischen Haushalts-,Radio U Fernsehger\u00e4ten sowie Musikinstrumenten",
    "sg:phone":"+41 52 721 28 02",
    "sg:postcode":"8500",
    "sg:province":"Thurgau",
    "wof:name":"Bernina N\u00e4hcenter Inhaberin Loretz Andrea",
    "wof:placetype":"venue"
},
  "geometry": {"coordinates":[8.8975000381,47.5559844971],"type":"Point"}
}