{
  "type": "Feature",
  "properties": {
    "iso:country":"CH",
    "sg:address":"Via Spinatscha 9",
    "sg:city":"Sedrun",
    "sg:orig_category":"Reiseb\u00fcros U Reiseveranstalter Wohnheime",
    "sg:phone":"+41 27 957 37 98",
    "sg:postcode":"7188",
    "sg:province":"Graubunden",
    "wof:name":"Ferienhaus Heino",
    "wof:placetype":"venue"
},
  "geometry": {"coordinates":[7.9367241859,46.1232452393],"type":"Point"}
}