{
  "type": "Feature",
  "properties": {
    "iso:country":"CH",
    "sg:address":"Turbinenstrasse 27",
    "sg:city":"Z\u00fcrich",
    "sg:orig_category":"Detailhandel mit Blumen U Pflanzen Saatgut and Samen Grosshandel",
    "sg:phone":"+41 43 366 93 60",
    "sg:postcode":"8005",
    "sg:province":"Z\u00fcrich",
    "wof:name":"Agrologic.ch Ag",
    "wof:placetype":"venue"
},
  "geometry": {"coordinates":[8.515107,47.387115],"type":"Point"}
}