{
  "type": "Feature",
  "properties": {
    "iso:country":"CH",
    "sg:address":"1436",
    "sg:city":"Treycovagnes",
    "sg:orig_category":"Mechanik",
    "sg:postcode":"1436",
    "sg:province":"Vaud",
    "wof:name":"Sutter Technik",
    "wof:placetype":"venue"
},
  "geometry": {"coordinates":[7.687374115,47.1622085571],"type":"Point"}
}