{
  "type": "Feature",
  "properties": {
    "iso:country":"CH",
    "sg:address":"Fischmattweg 5",
    "sg:city":"Arth",
    "sg:orig_category":"Fachdetailhandel in Verkaufsr\u00e4umen",
    "sg:postcode":"6415",
    "sg:province":"Schwyz",
    "wof:name":"Barth Christian, Sportartikel",
    "wof:placetype":"venue"
},
  "geometry": {"coordinates":[8.5308027267,47.0691833496],"type":"Point"}
}