{
  "type": "Feature",
  "properties": {
    "iso:country":"CH",
    "sg:address":"3532",
    "sg:city":"Z\u00e4ziwil",
    "sg:orig_category":"Landesverteidigung, Sozialversicherung \u00d6ffentliche Verwaltung",
    "sg:phone":"+41 31 711 22 68",
    "sg:postcode":"3532",
    "sg:province":"Bern",
    "wof:name":"Zivilschutzstelle Z\u00e4ziwil",
    "wof:placetype":"venue"
},
  "geometry": {"coordinates":[7.6618599892,46.9018783569],"type":"Point"}
}