{
  "type": "Feature",
  "properties": {
    "iso:country":"CH",
    "sg:address":"Brown Boveri Pl. 1 Pf 1259",
    "sg:city":"Baden",
    "sg:classifiers":[
        {
            "category":"Professional",
            "subcategory":"Advertising",
            "type":"Services"
        }
    ],
    "sg:phone":"+41 56 204 04 00",
    "sg:postcode":"5400",
    "sg:province":"Aargau",
    "sg:tags":[
        "information",
        "medium",
        "communication"
    ],
    "wof:name":"Sterk Lichtspieltheater Ag",
    "wof:placetype":"venue"
},
  "geometry": {"coordinates":[8.306445,47.474331],"type":"Point"}
}