{
  "type": "Feature",
  "properties": {
    "iso:country":"CH",
    "sg:address":"Zentrumstrasse 20 5607 H\u00e4gglingen. Postfach",
    "sg:city":"H\u00e4gglingen",
    "sg:orig_category":"Herstellung von Konstruktionsteilen, Fertigbauteilen U Ausbauelementen aus Holz",
    "sg:postcode":"5607",
    "sg:province":"Aargau",
    "wof:name":"Eugen Hartmann",
    "wof:placetype":"venue"
},
  "geometry": {"coordinates":[8.2521800995,47.3869781494],"type":"Point"}
}