{
  "type": "Feature",
  "properties": {
    "iso:country":"CH",
    "sg:address":"Chemin Des Roseaux 18",
    "sg:city":"V\u00e9troz",
    "sg:orig_category":"Herstellung von sonstigen landwirtschaftlichen Maschinen Mechanische Werkst\u00e4tten",
    "sg:phone":"+41 27 346 32 93",
    "sg:postcode":"1963",
    "sg:province":"Valais",
    "wof:name":"Alfred Buchs Rep.machines De Cantier",
    "wof:placetype":"venue"
},
  "geometry": {"coordinates":[7.2793607712,46.2207450867],"type":"Point"}
}