{
  "type": "Feature",
  "properties": {
    "iso:country":"CH",
    "sg:address":"Rue Des Deux Fontaines 9",
    "sg:city":"Chernex",
    "sg:classifiers":[
        {
            "category":"Manufacturing",
            "subcategory":"Motor Vehicles & Parts",
            "type":"Manufacturing & Wholesale Goods"
        }
    ],
    "sg:phone":"+41 32 931 74 74",
    "sg:postcode":"1822",
    "sg:province":"Vaud",
    "sg:tags":[
        "electronic",
        "assembling",
        "component"
    ],
    "wof:name":"Cloos Engineering S.a. Cnt",
    "wof:placetype":"venue"
},
  "geometry": {"coordinates":[6.766818,47.064289],"type":"Point"}
}