{
  "type": "Feature",
  "properties": {
    "iso:country":"CH",
    "sg:address":"Bleiche",
    "sg:city":"Niederurnen",
    "sg:orig_category":"Verwertung von Milch",
    "sg:phone":"+41 56 622 78 91",
    "sg:postcode":"8867",
    "sg:province":"Glarus",
    "wof:name":"Milchgenossenschaft Niederwil",
    "wof:placetype":"venue"
},
  "geometry": {"coordinates":[8.2931985855,47.3803901672],"type":"Point"}
}