{
  "type": "Feature",
  "properties": {
    "iso:country":"CH",
    "sg:address":"Buchsackerstrasse 26",
    "sg:city":"Dietikon",
    "sg:orig_category":"Instandhaltung U Reparatur von Automobilen",
    "sg:phone":"+41 17401943",
    "sg:postcode":"8953",
    "sg:province":"Z\u00fcrich",
    "wof:name":"Heinrich Duc Autosattlerei",
    "wof:placetype":"venue"
},
  "geometry": {"coordinates":[8.4067306519,47.4059829712],"type":"Point"}
}