{
  "type": "Feature",
  "properties": {
    "iso:country":"CH",
    "sg:address":"Br\u00fchlstrasse 10",
    "sg:city":"Arbon",
    "sg:orig_category":"Instandhaltung U Reparatur von Automobilen",
    "sg:phone":"+41 71 446 49 46",
    "sg:postcode":"9320",
    "sg:province":"Thurgau",
    "wof:name":"Frei Martin, Br\u00fchlgarage",
    "wof:placetype":"venue"
},
  "geometry": {"coordinates":[9.4303636551,47.5128479004],"type":"Point"}
}