{
  "type": "Feature",
  "properties": {
    "iso:country":"CH",
    "sg:address":"Neuhofweg 2 6045 Meggen. Postfach",
    "sg:city":"Meggen",
    "sg:orig_category":"Herstellung von Bergwerks U Baumaschinen",
    "sg:postcode":"6045",
    "sg:province":"Luzern",
    "wof:name":"Bz Engineering Ag, Zweigniederlassung Meggen Maschinen U. Maschinenteile Im Bau- U. F\u00f6rderbereich; Handel, Herstellung",
    "wof:placetype":"venue"
},
  "geometry": {"coordinates":[8.3846302032,47.0604248047],"type":"Point"}
}