{
  "type": "Feature",
  "properties": {
    "iso:country":"CH",
    "sg:address":"Fachstrasse 40",
    "sg:city":"Oberrieden",
    "sg:orig_category":"Unternehmensberatung",
    "sg:phone":"+41 17202402",
    "sg:postcode":"8942",
    "sg:province":"Z\u00fcrich",
    "wof:name":"Urs St\u00fcdi Treuhandb\u00fcro",
    "wof:placetype":"venue"
},
  "geometry": {"coordinates":[8.5796098709,47.2762718201],"type":"Point"}
}