{
  "type": "Feature",
  "properties": {
    "iso:country":"CH",
    "sg:address":"Oberr\u00fctistrasse 12",
    "sg:city":"Hinterforst",
    "sg:orig_category":"Detailhandel mit Metallwaren, Anstrichmitteln, Glaswaren, Bau U Heimwerkerbedarf Handelsvermittlung ",
    "sg:phone":"+41 71 755 70 50",
    "sg:postcode":"9452",
    "sg:province":"St. Gallen",
    "wof:name":"Saratech Gmbh",
    "wof:placetype":"venue"
},
  "geometry": {"coordinates":[9.5270557404,47.3554954529],"type":"Point"}
}