{
  "type": "Feature",
  "properties": {
    "iso:country":"CH",
    "sg:address":"Aarestrasse 47",
    "sg:city":"Uetendorf",
    "sg:orig_category":"Softwareentwicklung U beratung",
    "sg:phone":"+41 2371677",
    "sg:postcode":"3661",
    "sg:province":"Bern",
    "wof:name":"Gerinfo Gerber Informatik Consulting & Support Gmbh",
    "wof:placetype":"venue"
},
  "geometry": {"coordinates":[7.5984888077,46.7771263123],"type":"Point"}
}