{
  "type": "Feature",
  "properties": {
    "iso:country":"CH",
    "sg:address":"Zurlindenstrasse 52a",
    "sg:city":"Z\u00fcrich",
    "sg:orig_category":"Non-Classified Establishments",
    "sg:postcode":"8003",
    "sg:province":"Z\u00fcrich",
    "wof:name":"Glamourama S.\u00e0.r.l.",
    "wof:placetype":"venue"
},
  "geometry": {"coordinates":[8.5210466385,47.3693885803],"type":"Point"}
}