{
  "type": "Feature",
  "properties": {
    "iso:country":"CH",
    "sg:address":"Seestrasse 60",
    "sg:city":"Weggis",
    "sg:orig_category":"Architektur U Ingenieurb\u00fcros",
    "sg:postcode":"6353",
    "sg:province":"Luzern",
    "wof:name":"Alear Ag",
    "wof:placetype":"venue"
},
  "geometry": {"coordinates":[7.595199,47.502075],"type":"Point"}
}