{
  "type": "Feature",
  "properties": {
    "iso:country":"CH",
    "sg:address":"Propst-huber-strasse 1",
    "sg:city":"H\u00e4gglingen",
    "sg:orig_category":"Softwareentwicklung U beratung",
    "sg:postcode":"5607",
    "sg:province":"Aargau",
    "wof:name":"Asta Development Meier Christian",
    "wof:placetype":"venue"
},
  "geometry": {"coordinates":[8.2462091446,47.3894615173],"type":"Point"}
}