{
  "type": "Feature",
  "properties": {
    "iso:country":"CH",
    "sg:address":"Talstr. 20",
    "sg:city":"Z\u00fcrich",
    "sg:classifiers":[
        {
            "category":"Banks & Credit Unions",
            "subcategory":"Financial Services",
            "type":"Services"
        }
    ],
    "sg:phone":"+41 4112252424",
    "sg:postcode":"8024",
    "sg:province":"Z\u00fcrich",
    "sg:tags":[
        "banking",
        "insurance",
        "institution",
        "finance"
    ],
    "wof:name":"Fimat Switzerland Ag",
    "wof:placetype":"venue"
},
  "geometry": {"coordinates":[8.538337,47.368904],"type":"Point"}
}