{
  "type": "Feature",
  "properties": {
    "addr:full":"Rue Du Vingt-trois Juin 82 St-ursanne Jura 2882",
    "addr:housenumber":"82",
    "addr:postcode":"2882",
    "addr:street":"Rue Du Vingt-Trois Juin;Jura",
    "iso:country":"CH",
    "sg:address":"Rue Du Vingt-trois Juin 82",
    "sg:city":"St-ursanne",
    "sg:orig_category":"Bauschreinerei Innenausbau",
    "sg:phone":"+41 31 951 06 73",
    "sg:postcode":"2882",
    "sg:province":"Jura",
    "wof:name":"Herbert K\u00f6hli Schreinerei & Innenausbau",
    "wof:placetype":"venue"
},
  "geometry": {"coordinates":[7.49016,46.936089],"type":"Point"}
}