{
  "type": "Feature",
  "properties": {
    "iso:country":"CH",
    "sg:address":"6527 Lodrino. Postfach",
    "sg:city":"Lodrino",
    "sg:orig_category":"Unclassifiable Establishments",
    "sg:postcode":"6527",
    "sg:province":"Ticino",
    "wof:name":"Gr\u00fcenb\u00e4rgli Holding Sa",
    "wof:placetype":"venue"
},
  "geometry": {"coordinates":[8.9811306,46.2996673584],"type":"Point"}
}