{
  "type": "Feature",
  "properties": {
    "iso:country":"CH",
    "sg:address":"Amselstrasse 14 9230 Flawil. Postfach",
    "sg:city":"Flawil",
    "sg:orig_category":"Sonstiger spezialisierter Hoch U Tiefbau",
    "sg:postcode":"9230",
    "sg:province":"St. Gallen",
    "wof:name":"Cannistraci Francesco",
    "wof:placetype":"venue"
},
  "geometry": {"coordinates":[9.1770334244,47.4168319702],"type":"Point"}
}