{
  "type": "Feature",
  "properties": {
    "iso:country":"CH",
    "sg:address":"Hauptstrasse 14",
    "sg:city":"Hochdorf",
    "sg:orig_category":"Detailhandel mit Schuhen U Lederwaren",
    "sg:phone":"+41 41 910 10 41",
    "sg:postcode":"6280",
    "sg:province":"Luzern",
    "wof:name":"Baumgartner Agnes",
    "wof:placetype":"venue"
},
  "geometry": {"coordinates":[8.2906141281,47.1664619446],"type":"Point"}
}