{
  "type": "Feature",
  "properties": {
    "iso:country":"CH",
    "sg:address":"Elfenaustrasse 19",
    "sg:city":"Luzern",
    "sg:orig_category":"Arbeitnehmerverb\u00e4nde",
    "sg:phone":"+41 41 360 85 80",
    "sg:postcode":"6005",
    "sg:province":"Luzern",
    "wof:name":"Kath.arbeitnehmerbewegung Lu Herrn Ferdinand Luthiger",
    "wof:placetype":"venue"
},
  "geometry": {"coordinates":[8.311958,47.039707],"type":"Point"}
}