{
  "type": "Feature",
  "properties": {
    "iso:country":"CH",
    "sg:address":"M\u00fclhauserstrasse 72",
    "sg:city":"Basel",
    "sg:orig_category":"Herstellung von Konstruktionsteilen, Fertigbauteilen U Ausbauelementen aus Holz",
    "sg:phone":"+41 61 332 32 47",
    "sg:postcode":"4056",
    "sg:province":"Basel-Stadt",
    "wof:name":"Nais Vasic",
    "wof:placetype":"venue"
},
  "geometry": {"coordinates":[7.5791330338,47.5682792664],"type":"Point"}
}