{
  "type": "Feature",
  "properties": {
    "iso:country":"CH",
    "sg:address":"Oberdorfstrasse 2",
    "sg:city":"Mettmenstetten",
    "sg:orig_category":"Markt U Meinungsforschung",
    "sg:phone":"+41 17671000",
    "sg:postcode":"8932",
    "sg:province":"Z\u00fcrich",
    "wof:name":"Kleeb Consulting Ag",
    "wof:placetype":"venue"
},
  "geometry": {"coordinates":[8.4716110229,47.2461471558],"type":"Point"}
}