{
  "type": "Feature",
  "properties": {
    "iso:country":"CH",
    "sg:address":"Dorf 2",
    "sg:city":"B\u00fchler",
    "sg:orig_category":"Detailhandel mit Waren verschiedener Art, Hauptrichtung Nahrungsmittel",
    "sg:phone":"+41 27 956 12 94",
    "sg:postcode":"9055",
    "sg:province":"Appenzell Ausserrhoden",
    "wof:name":"Konsumverein Gasenried Lebensmittel",
    "wof:placetype":"venue"
},
  "geometry": {"coordinates":[7.8021001816,46.1756591797],"type":"Point"}
}