{
  "type": "Feature",
  "properties": {
    "iso:country":"CH",
    "sg:address":"Chemin De M\u00e9zery 2",
    "sg:city":"Prilly",
    "sg:orig_category":"Softwareentwicklung U beratung",
    "sg:phone":"+41 71 260 25 80",
    "sg:postcode":"1008",
    "sg:province":"Vaud",
    "wof:name":"Soft Solutions Edv Glaus",
    "wof:placetype":"venue"
},
  "geometry": {"coordinates":[9.3479280472,47.4112091064],"type":"Point"}
}