{
  "type": "Feature",
  "properties": {
    "iso:country":"CH",
    "sg:address":"G\u00f6tzisbodenweg 7",
    "sg:city":"Pratteln",
    "sg:orig_category":"Unclassifiable Establishments",
    "sg:postcode":"4133",
    "sg:province":"Basel-Landschaft",
    "wof:name":"Paul Welker Holding Ag",
    "wof:placetype":"venue"
},
  "geometry": {"coordinates":[7.7011799812,47.5259361267],"type":"Point"}
}