{
  "type": "Feature",
  "properties": {
    "iso:country":"CH",
    "sg:address":"Ottenhusen",
    "sg:city":"Ballwil",
    "sg:orig_category":"Detailhandel mit Metallwaren, Anstrichmitteln, Glaswaren, Bau U Heimwerkerbedarf Sonstiger Detailhan",
    "sg:phone":"+41 41 910 65 88",
    "sg:postcode":"6275",
    "sg:province":"Luzern",
    "wof:name":"Hak\u00f6ma K\u00f6llinger H.j.",
    "wof:placetype":"venue"
},
  "geometry": {"coordinates":[8.3279600143,47.164730072],"type":"Point"}
}