{
  "type": "Feature",
  "properties": {
    "iso:country":"CH",
    "sg:address":"Rotbergstrasse 22 4116 Metzerlen. Postfach",
    "sg:city":"Metzerlen",
    "sg:orig_category":"Non-Classified Establishments",
    "sg:phone":"+41 61 761 20 10",
    "sg:postcode":"4116",
    "sg:province":"Solothurn",
    "wof:name":"Haberth\u00fcr Sonnen Und Wetterschutz Ag",
    "wof:placetype":"venue"
},
  "geometry": {"coordinates":[7.4690108299,47.4658813477],"type":"Point"}
}