{
  "type": "Feature",
  "properties": {
    "iso:country":"CH",
    "sg:address":"Route De Moncor 2",
    "sg:city":"Villars-sur-gl\u00e2ne",
    "sg:orig_category":"Wirtschaftspr\u00fcfung, Steuerberatung U Treuhand",
    "sg:phone":"+41 26 401 01 17",
    "sg:postcode":"1752",
    "sg:province":"Fribourg",
    "wof:name":"Cabinet De Conseil Fiscal, Cotting Andr\u00e9-claude",
    "wof:placetype":"venue"
},
  "geometry": {"coordinates":[7.1267280579,46.7985572815],"type":"Point"}
}