{
  "type": "Feature",
  "properties": {
    "iso:country":"CH",
    "sg:address":"Floozstrasse 9620 Lichtensteig. Postfach 263",
    "sg:city":"Lichtensteig",
    "sg:orig_category":"Herstellung von sonstigen Metallwaren Pulvermetallurgie Schmieden, Pressen, Stanzen U Profilwalzen v",
    "sg:phone":"+41 31 980 83 33",
    "sg:postcode":"9620",
    "sg:province":"St. Gallen",
    "wof:name":"Styner+bienz Formtech Ag",
    "wof:placetype":"venue"
},
  "geometry": {"coordinates":[7.3748221397,46.9243469238],"type":"Point"}
}