{
  "type": "Feature",
  "properties": {
    "iso:country":"CH",
    "sg:address":"Rue Du Nord 1",
    "sg:city":"Lausanne",
    "sg:orig_category":"Bauspenglerei Dachdeckerei",
    "sg:phone":"+41 32 926 55 25",
    "sg:postcode":"1005",
    "sg:province":"Vaud",
    "wof:name":"Denis Cramatte Ferblanterie & Couverture",
    "wof:placetype":"venue"
},
  "geometry": {"coordinates":[6.813284,47.096592],"type":"Point"}
}