{
  "type": "Feature",
  "properties": {
    "iso:country":"CH",
    "sg:address":"Strengelbacherstrasse 25b",
    "sg:city":"Zofingen",
    "sg:orig_category":"Maturit\u00e4tsschulen, Lehrerseminarien",
    "sg:phone":"+41 62 745 56 90",
    "sg:postcode":"4800",
    "sg:province":"Aargau",
    "wof:name":"H\u00f6here P\u00e4dagogische Lehranstalt",
    "wof:placetype":"venue"
},
  "geometry": {"coordinates":[7.9407429695,47.2828445435],"type":"Point"}
}