{
  "type": "Feature",
  "properties": {
    "iso:country":"CH",
    "sg:address":"Weidhofstrasse 3",
    "sg:city":"Merenschwand",
    "sg:orig_category":"Herstellung von k\u00e4lte U lufttechnischen Erzeugnissen f\u00fcr gewerbliche Zwecke Installation von Heizung",
    "sg:phone":"+41 56 664 50 64",
    "sg:postcode":"5634",
    "sg:province":"Aargau",
    "wof:name":"Franz Andermatt K\u00e4lte-& Klimaanlagen",
    "wof:placetype":"venue"
},
  "geometry": {"coordinates":[8.3729782104,47.2544670105],"type":"Point"}
}