{
  "type": "Feature",
  "properties": {
    "iso:country":"CH",
    "sg:address":"Austrasse 116",
    "sg:city":"Basel",
    "sg:orig_category":"Architektur U Ingenieurb\u00fcros",
    "sg:phone":"+41 61 731 30 53",
    "sg:postcode":"4051",
    "sg:province":"Basel-Stadt",
    "wof:name":"Immoseg Seghers St.",
    "wof:placetype":"venue"
},
  "geometry": {"coordinates":[7.51652,47.479534],"type":"Point"}
}