{
  "type": "Feature",
  "properties": {
    "iso:country":"CH",
    "sg:address":"1716",
    "sg:city":"Plaffeien",
    "sg:orig_category":"Primarschulen",
    "sg:phone":"+41 26 419 29 39",
    "sg:postcode":"1716",
    "sg:province":"Fribourg",
    "wof:name":"Primarschule",
    "wof:placetype":"venue"
},
  "geometry": {"coordinates":[7.2868709564,46.7410163879],"type":"Point"}
}