{
  "type": "Feature",
  "properties": {
    "iso:country":"CH",
    "sg:address":"Stockistrasse 32",
    "sg:city":"Glattfelden",
    "sg:orig_category":"Gartenbau Landschaftsplanungsb\u00fcros U Gartenarchitekturb\u00fcros",
    "sg:phone":"+41 18671731",
    "sg:postcode":"8192",
    "sg:province":"Z\u00fcrich",
    "wof:name":"Creative Begr\u00fcnung Ch.tr\u00f6sch",
    "wof:placetype":"venue"
},
  "geometry": {"coordinates":[8.5004444122,47.5563011169],"type":"Point"}
}