{
  "type": "Feature",
  "properties": {
    "iso:country":"CH",
    "sg:address":"Cit\u00e9 Vieusseux 9",
    "sg:city":"Gen\u00e8ve",
    "sg:orig_category":"Detailhandel mit Brot, Back U S\u00fcsswaren",
    "sg:phone":"+41 22 342 01 43",
    "sg:postcode":"1203",
    "sg:province":"Gen\u00e8ve",
    "wof:name":"Jean-charles Ruckstuhl Boulangerie-p\u00e2tisserie",
    "wof:placetype":"venue"
},
  "geometry": {"coordinates":[6.134782,46.190662],"type":"Point"}
}