{
  "type": "Feature",
  "properties": {
    "iso:country":"CH",
    "sg:address":"Rue Des Moulins 25",
    "sg:city":"Versoix",
    "sg:orig_category":"Detailhandel mit Geschenkartikeln U Souvenirs",
    "sg:phone":"+41 22 755 39 55",
    "sg:postcode":"1290",
    "sg:province":"Gen\u00e8ve",
    "wof:name":"Boutique Tamara",
    "wof:placetype":"venue"
},
  "geometry": {"coordinates":[6.168091774,46.277015686],"type":"Point"}
}