{
  "type": "Feature",
  "properties": {
    "iso:country":"CH",
    "sg:address":"M\u00fclhauserstrasse 111-113",
    "sg:city":"Basel",
    "sg:orig_category":"Instandhaltung U Reparatur von Automobilen",
    "sg:phone":"+41 62 824 10 21",
    "sg:postcode":"4056",
    "sg:province":"Basel-Stadt",
    "wof:name":"Kappeler Garage",
    "wof:placetype":"venue"
},
  "geometry": {"coordinates":[8.0715484619,47.3896865845],"type":"Point"}
}