{
  "type": "Feature",
  "properties": {
    "iso:country":"CH",
    "sg:address":"Steinligasse 11 A",
    "sg:city":"M\u00f6hlin",
    "sg:orig_category":"Grosshandel mit Nahrungsmitteln, Getr\u00e4nken U Tabakwaren ohne ausgepr\u00e4gten Schwerpunkt",
    "sg:postcode":"4313",
    "sg:province":"Aargau",
    "wof:name":"E. Kaufmann, Handel",
    "wof:placetype":"venue"
},
  "geometry": {"coordinates":[7.842154026,47.5671768188],"type":"Point"}
}