{
  "type": "Feature",
  "properties": {
    "iso:country":"CH",
    "sg:address":"G\u00e4ttenhusenstrasse 2",
    "sg:city":"F\u00e4llanden",
    "sg:orig_category":"Rechtsberatung",
    "sg:phone":"+41 31 921 78 44",
    "sg:postcode":"8117",
    "sg:province":"Z\u00fcrich",
    "wof:name":"Iba-interbuch Ag",
    "wof:placetype":"venue"
},
  "geometry": {"coordinates":[8.6283349991,47.3692359924],"type":"Point"}
}