{
  "type": "Feature",
  "properties": {
    "iso:country":"CH",
    "sg:address":"D\u00e4llikerstrasse 144",
    "sg:city":"Regensdorf",
    "sg:orig_category":"Verwertung von Milch",
    "sg:postcode":"8105",
    "sg:province":"Z\u00fcrich",
    "wof:name":"Milchverwertungsgenossenschaft Regensdorf",
    "wof:placetype":"venue"
},
  "geometry": {"coordinates":[8.4584245682,47.4342193604],"type":"Point"}
}