{
  "type": "Feature",
  "properties": {
    "iso:country":"CH",
    "sg:address":"Alte Badstrasse 4",
    "sg:city":"Lostorf",
    "sg:orig_category":"Herstellung von Metallkonstruktionen",
    "sg:postcode":"4654",
    "sg:province":"Solothurn",
    "wof:name":"Fairwork Bisig & Co",
    "wof:placetype":"venue"
},
  "geometry": {"coordinates":[7.9378180504,47.3940505981],"type":"Point"}
}