{
  "type": "Feature",
  "properties": {
    "iso:country":"CH",
    "sg:address":"Giessenstrasse 20",
    "sg:city":"Vaduz",
    "sg:orig_category":"Bezirks, Sekundar, Realschulen, Oberstufe der Primarschulen",
    "sg:phone":"+423 232 19 84",
    "sg:postcode":"9490",
    "wof:name":"Oberschule",
    "wof:placetype":"venue"
},
  "geometry": {"coordinates":[9.519781,47.138546],"type":"Point"}
}