{
  "type": "Feature",
  "properties": {
    "addr:full":"Worbstrasse 220 G\u00fcmligen Bern 3073",
    "addr:housenumber":"220",
    "addr:postcode":"3073",
    "addr:street":"Worbstrasse",
    "iso:country":"CH",
    "sg:address":"Worbstrasse 220",
    "sg:city":"G\u00fcmligen",
    "sg:classifiers":[
        {
            "category":"Banks & Credit Unions",
            "subcategory":"Investment Brokerage",
            "type":"Services"
        }
    ],
    "sg:phone":"+41 79 208 14 83",
    "sg:postcode":"3073",
    "sg:province":"Bern",
    "sg:tags":[
        "ceiling",
        "covering"
    ],
    "wof:name":"Db Gmbh",
    "wof:placetype":"venue"
},
  "geometry": {"coordinates":[7.505785,46.933266],"type":"Point"}
}