{
  "type": "Feature",
  "properties": {
    "iso:country":"CH",
    "sg:address":"Via Franzoni 1 6600 Locarno Casella Postale 146",
    "sg:city":"Locarno",
    "sg:orig_category":"Eisenbahnverkehr Personenbef\u00f6rderung im Linienverkehr zu Land",
    "sg:phone":"+41 91 751 13 47",
    "sg:postcode":"6601",
    "sg:province":"Ticino",
    "wof:name":"Societ\u00e0 Per Le Ferrovie Autolinee Regionali Ticinesi (fart) Sa",
    "wof:placetype":"venue"
},
  "geometry": {"coordinates":[8.8003940582,46.1705741882],"type":"Point"}
}