{
  "type": "Feature",
  "properties": {
    "iso:country":"CH",
    "sg:address":"Delsbergerallee 74 4053 Basel. Postfach",
    "sg:city":"Basel",
    "sg:orig_category":"Herstellung von Teppichen Verlegen von Fussboden",
    "sg:phone":"+41 61 333 12 30",
    "sg:postcode":"4051",
    "sg:province":"Basel-Stadt",
    "wof:name":"H. & H. Bodenbel\u00e4ge Gmbh",
    "wof:placetype":"venue"
},
  "geometry": {"coordinates":[7.5990190506,47.5394363403],"type":"Point"}
}