{
  "type": "Feature",
  "properties": {
    "iso:country":"CH",
    "sg:address":"Piazza Molino Nuovo 15",
    "sg:city":"Lugano",
    "sg:orig_category":"RESTAURANTS: TEA-ROOMS",
    "sg:phone":"+41 91 922 81 08",
    "sg:postcode":"6900",
    "sg:province":"Ticino",
    "wof:name":"Pub Piccolo Principe",
    "wof:placetype":"venue"
},
  "geometry": {"coordinates":[8.9554157257,46.0125350952],"type":"Point"}
}