{
  "type": "Feature",
  "properties": {
    "iso:country":"CH",
    "sg:address":"M\u00e4rwilerstrasse 39 9556 Affeltrangen. Postfach",
    "sg:city":"Affeltrangen",
    "sg:orig_category":"Zimmerei, Dachdeckerei, Bauspenglerei U Abdichtung",
    "sg:postcode":"9556",
    "sg:province":"Thurgau",
    "wof:name":"Hossmann Holzbau Ag",
    "wof:placetype":"venue"
},
  "geometry": {"coordinates":[9.03586483,47.5252914429],"type":"Point"}
}