{
  "type": "Feature",
  "properties": {
    "iso:country":"CH",
    "sg:address":"Riedsortstrasse 49",
    "sg:city":"Weggis",
    "sg:orig_category":"Detailhandel mit Damenbekleidung Herstellung von sonstiger Bekleidung U Bekleidungszubeh\u00f6r",
    "sg:phone":"+41 41 240 79 86",
    "sg:postcode":"6353",
    "sg:province":"Luzern",
    "wof:name":"Catherine Collection Spindler C.",
    "wof:placetype":"venue"
},
  "geometry": {"coordinates":[8.455239296,47.0266075134],"type":"Point"}
}