{
  "type": "Feature",
  "properties": {
    "iso:country":"CH",
    "sg:address":"Gl\u00e4rnischstrasse 12",
    "sg:city":"Mollis",
    "sg:orig_category":"Vereine Frauen Vereine Gemeinn\u00fctzige",
    "sg:phone":"+41 55 612 32 09",
    "sg:postcode":"8753",
    "sg:province":"Glarus",
    "wof:name":"Gemeinn\u00fctziger Frauenverein",
    "wof:placetype":"venue"
},
  "geometry": {"coordinates":[9.0701303482,47.0882301331],"type":"Point"}
}