{
  "type": "Feature",
  "properties": {
    "iso:country":"CH",
    "sg:address":"Gutenbergstrasse 6",
    "sg:city":"Bern",
    "sg:orig_category":"Arztpraxen",
    "sg:phone":"+41 31 398 70 80",
    "sg:postcode":"3011",
    "sg:province":"Bern",
    "wof:name":"Dr.med. Harald Rigoni Arzt F.allgemeine Medizin Fmh",
    "wof:placetype":"venue"
},
  "geometry": {"coordinates":[7.435683,46.945538],"type":"Point"}
}