{
  "type": "Feature",
  "properties": {
    "iso:country":"CH",
    "sg:address":"Bachtelestrasse 2 3752 Wimmis. Postfach",
    "sg:city":"Wimmis",
    "sg:orig_category":"Grosshandel mit Getr\u00e4nken",
    "sg:postcode":"3752",
    "sg:province":"Bern",
    "wof:name":"Pittet A. Commerce De Vins, Bi\u00e8res Et Limonades",
    "wof:placetype":"venue"
},
  "geometry": {"coordinates":[6.6639499664,46.5902061462],"type":"Point"}
}