{
  "type": "Feature",
  "properties": {
    "iso:country":"CH",
    "sg:address":"Vorstadtstrasse 28",
    "sg:city":"Dietikon",
    "sg:orig_category":"Softwareentwicklung U beratung",
    "sg:phone":"+41 52 232 30 30",
    "sg:postcode":"8953",
    "sg:province":"Z\u00fcrich",
    "wof:name":"Is Informatik Support Ag",
    "wof:placetype":"venue"
},
  "geometry": {"coordinates":[8.7607221603,47.4835586548],"type":"Point"}
}