{
  "type": "Feature",
  "properties": {
    "iso:country":"CH",
    "sg:address":"Stauffacherstrasse 28",
    "sg:city":"Bern",
    "sg:orig_category":"Stukkateurgewerbe, Gipserei U Verputzerei",
    "sg:postcode":"3014",
    "sg:province":"Bern",
    "wof:name":"Meier + Baumgartner, Nachfolger Daniel Baumgartner",
    "wof:placetype":"venue"
},
  "geometry": {"coordinates":[7.4549441338,46.962387085],"type":"Point"}
}