{
  "type": "Feature",
  "properties": {
    "iso:country":"CH",
    "sg:address":"Chemin Du Bornalet 13",
    "sg:city":"Satigny",
    "sg:orig_category":"Abbruch U Sprenggewerbe Abbruch U Sprenggewerbe, Erdbewegungsarbeiten",
    "sg:phone":"+41 22 341 24 13",
    "sg:postcode":"1242",
    "sg:province":"Gen\u00e8ve",
    "wof:name":"Entreprise De D\u00e9molition Sa",
    "wof:placetype":"venue"
},
  "geometry": {"coordinates":[6.030324,46.215023],"type":"Point"}
}