{
  "type": "Feature",
  "properties": {
    "iso:country":"CH",
    "sg:address":"W\u00fcrzgrabenstrasse 6",
    "sg:city":"Z\u00fcrich",
    "sg:classifiers":[
        {
            "category":"Home & Garden",
            "subcategory":"Home Furnishings",
            "type":"Retail Goods"
        }
    ],
    "sg:phone":"+41 14382525",
    "sg:postcode":"8048",
    "sg:province":"Z\u00fcrich",
    "sg:tags":[
        "bathroom",
        "wc",
        "fitting"
    ],
    "wof:name":"Richner Ag",
    "wof:placetype":"venue"
},
  "geometry": {"coordinates":[8.493897,47.393044],"type":"Point"}
}