{
  "type": "Feature",
  "properties": {
    "iso:country":"CH",
    "sg:address":"R\u00fcti 1683",
    "sg:city":"Herisau",
    "sg:classifiers":[
        {
            "category":"Travel",
            "subcategory":"Hotels & Motels",
            "type":"Entertainment"
        }
    ],
    "sg:postcode":"9100",
    "sg:province":"Appenzell Ausserrhoden",
    "sg:tags":[
        "hotels",
        "mit",
        "restaurant"
    ],
    "wof:name":"W. Zwimpfer-berweger",
    "wof:placetype":"venue"
},
  "geometry": {"coordinates":[9.2858963013,47.3964958191],"type":"Point"}
}