{
  "type": "Feature",
  "properties": {
    "iso:country":"CH",
    "sg:address":"Chemin Du Grand-h\u00f4tel 3 2067 Chaumont. Postfach",
    "sg:city":"Chaumont",
    "sg:orig_category":"Vermittlung von Immobilien Verwaltung von Immobilien",
    "sg:phone":"+41 81 833 42 96",
    "sg:postcode":"2067",
    "sg:province":"Neuch\u00e2tel",
    "wof:name":"Torag Immobilien Ag",
    "wof:placetype":"venue"
},
  "geometry": {"coordinates":[9.8400716782,46.4991760254],"type":"Point"}
}