{
  "type": "Feature",
  "properties": {
    "addr:full":"Rue De Lausanne 18 1200 Gen\u00e8ve. Postfach Gen\u00e8ve Gen\u00e8ve 1201",
    "addr:housenumber":"18",
    "addr:postcode":"1200;postfach;1201",
    "addr:street":"Rue De Lausanne",
    "iso:country":"CH",
    "sg:address":"Rue De Lausanne 18 1200 Gen\u00e8ve. Postfach",
    "sg:city":"Gen\u00e8ve",
    "sg:orig_category":"Detailhandel mit Bekleidung",
    "sg:postcode":"1201",
    "sg:province":"Gen\u00e8ve",
    "wof:name":"Jessica, Lutz Fernand",
    "wof:placetype":"venue"
},
  "geometry": {"coordinates":[6.1446,46.211231],"type":"Point"}
}