{
  "type": "Feature",
  "properties": {
    "iso:country":"CH",
    "sg:address":"5424",
    "sg:city":"Unterehrendingen",
    "sg:orig_category":"Vorschulen, Kinderg\u00e4rten",
    "sg:phone":"+41 56 222 72 30",
    "sg:postcode":"5424",
    "wof:name":"Kindergarten",
    "wof:placetype":"venue"
},
  "geometry": {"coordinates":[8.3552303314,47.4961013794],"type":"Point"}
}