{
  "type": "Feature",
  "properties": {
    "addr:full":"Unter-pfaffwil Inwil Luzern 6034",
    "addr:postcode":"6034",
    "iso:country":"CH",
    "sg:address":"Unter-pfaffwil",
    "sg:city":"Inwil",
    "sg:orig_category":"Chalet- and Holzbau Zimmerei",
    "sg:postcode":"6034",
    "sg:province":"Luzern",
    "wof:name":"Werner Portmann Holzbau",
    "wof:placetype":"venue"
},
  "geometry": {"coordinates":[8.382765,47.130894],"type":"Point"}
}