{
  "type": "Feature",
  "properties": {
    "iso:country":"CH",
    "sg:address":"8192",
    "sg:city":"Glattfelden",
    "sg:orig_category":"Haltung von Rindern",
    "sg:postcode":"8192",
    "sg:province":"Z\u00fcrich",
    "wof:name":"Fleckviehzucht-genossenschaft Pf\u00e4ffikon-hittnau.",
    "wof:placetype":"venue"
},
  "geometry": {"coordinates":[8.7815437317,47.3674468994],"type":"Point"}
}