{
  "type": "Feature",
  "properties": {
    "iso:country":"CH",
    "sg:address":"K\u00e4sereistrasse 2",
    "sg:city":"Ermensee",
    "sg:orig_category":"Detailhandel mit Milcherzeugnissen U Eiern Verarbeitung von Milch",
    "sg:phone":"+41 32 636 20 05",
    "sg:postcode":"6294",
    "sg:province":"Luzern",
    "wof:name":"Paul Krummenacher K\u00e4serei",
    "wof:placetype":"venue"
},
  "geometry": {"coordinates":[8.2407102585,47.2276191711],"type":"Point"}
}