{
  "type": "Feature",
  "properties": {
    "iso:country":"CH",
    "sg:address":"Haus Viktoria",
    "sg:city":"Zermatt",
    "sg:orig_category":"Fachdetailhandel in Verkaufsr\u00e4umen",
    "sg:postcode":"3920",
    "sg:province":"Valais",
    "wof:name":"Alpine-photo-shop, Cortez F\u00e9 & Victor",
    "wof:placetype":"venue"
},
  "geometry": {"coordinates":[7.7484951019,46.0236206055],"type":"Point"}
}