{
  "type": "Feature",
  "properties": {
    "iso:country":"CH",
    "sg:address":"Weizacker 3",
    "sg:city":"St-ours",
    "sg:orig_category":"G\u00fcterbef\u00f6rderung im Strassenverkehr",
    "sg:phone":"+41 71 220 13 66",
    "sg:postcode":"1717",
    "sg:province":"Fribourg",
    "wof:name":"Neutra Railway Ag",
    "wof:placetype":"venue"
},
  "geometry": {"coordinates":[9.3747415543,47.4248428345],"type":"Point"}
}