{
  "type": "Feature",
  "properties": {
    "iso:country":"CH",
    "sg:address":"Oetwilerstrasse 43",
    "sg:city":"H\u00fcttikon",
    "sg:classifiers":[
        {
            "category":"Professional",
            "subcategory":"Employment Agencies",
            "type":"Services"
        }
    ],
    "sg:phone":"+41 18451253",
    "sg:postcode":"8115",
    "sg:province":"Z\u00fcrich",
    "sg:tags":[
        "personal",
        "u",
        "stellenvermittlung"
    ],
    "wof:name":"Job & Co Sa Conseil En Mati\u00e8re De Ressources Humaines, S\u00e9lection, Placement De Personnel",
    "wof:placetype":"venue"
},
  "geometry": {"coordinates":[8.3875255585,47.4434890747],"type":"Point"}
}