{
  "type": "Feature",
  "properties": {
    "iso:country":"CH",
    "sg:address":"Landstrasse 21",
    "sg:city":"Otelfingen",
    "sg:classifiers":[
        {
            "category":"Professional",
            "subcategory":"Computer Services",
            "type":"Services"
        }
    ],
    "sg:phone":"+41 18472070",
    "sg:postcode":"8112",
    "sg:province":"Z\u00fcrich",
    "sg:tags":[
        "development",
        "software"
    ],
    "wof:name":"Pitsoft Ag",
    "wof:placetype":"venue"
},
  "geometry": {"coordinates":[8.3881387711,47.4600563049],"type":"Point"}
}