{
  "type": "Feature",
  "properties": {
    "iso:country":"CH",
    "sg:address":"Hell 191",
    "sg:city":"Maur",
    "sg:orig_category":"Sonstige mit Sport verbundene T\u00e4tigkeiten",
    "sg:postcode":"8124",
    "sg:province":"Z\u00fcrich",
    "wof:name":"Reiterhof Hell Jost Vera",
    "wof:placetype":"venue"
},
  "geometry": {"coordinates":[8.6676549911,47.3246955872],"type":"Point"}
}