{
  "type": "Feature",
  "properties": {
    "addr:full":"Avenue De Beauregard 51 Auvernier Neuch\u00e2tel 2012",
    "addr:housenumber":"51",
    "addr:postcode":"2012",
    "addr:street":"Avenue De Beauregard;Neucha\u0302Tel",
    "iso:country":"CH",
    "sg:address":"Avenue De Beauregard 51",
    "sg:city":"Auvernier",
    "sg:orig_category":"Architektur U Ingenieurb\u00fcros",
    "sg:postcode":"2012",
    "sg:province":"Neuch\u00e2tel",
    "wof:name":"Indicosa Ing\u00e9nieurs Dipl\u00f4m\u00e9s Et Conseils Sa",
    "wof:placetype":"venue"
},
  "geometry": {"coordinates":[6.878534,46.9818],"type":"Point"}
}