{
  "type": "Feature",
  "properties": {
    "iso:country":"CH",
    "sg:address":"Bahnhofstrasse 297",
    "sg:city":"Ramsen",
    "sg:orig_category":"Nationale Postdienste",
    "sg:phone":"+41 52 743 11 42",
    "sg:postcode":"8262",
    "sg:province":"Schaffhausen",
    "wof:name":"Die Schweizerische Post",
    "wof:placetype":"venue"
},
  "geometry": {"coordinates":[8.8158340454,47.7070732117],"type":"Point"}
}