{
  "type": "Feature",
  "properties": {
    "iso:country":"CH",
    "sg:address":"Rheinweg 1",
    "sg:city":"Schaffhausen",
    "sg:orig_category":"Aktivit\u00e4ten der Generalunternehmen im Baugewerbe Architektur U Ingenieurb\u00fcros",
    "sg:phone":"+41 52 630 06 77",
    "sg:postcode":"8200",
    "sg:province":"Schaffhausen",
    "wof:name":"Ixtegra Ag Planung U. Realisierung Von Bauten",
    "wof:placetype":"venue"
},
  "geometry": {"coordinates":[8.632711,47.693886],"type":"Point"}
}