{
  "type": "Feature",
  "properties": {
    "iso:country":"CH",
    "sg:address":"Bahnhofstrasse 106",
    "sg:city":"Rafz",
    "sg:orig_category":"Elektrizit\u00e4tsversorgung",
    "sg:postcode":"8197",
    "sg:province":"Z\u00fcrich",
    "wof:name":"Energieplanung Neukom Armin",
    "wof:placetype":"venue"
},
  "geometry": {"coordinates":[8.5436000824,47.6041183472],"type":"Point"}
}