{
  "type": "Feature",
  "properties": {
    "iso:country":"CH",
    "sg:address":"P\u00e9rolles Boulevard De 55",
    "sg:city":"Fribourg",
    "sg:orig_category":"Sonstiger Grosshandel",
    "sg:postcode":"1702",
    "sg:province":"Fribourg",
    "wof:name":"Gerber Christian",
    "wof:placetype":"venue"
},
  "geometry": {"coordinates":[7.8549938202,47.3366966248],"type":"Point"}
}