{
  "type": "Feature",
  "properties": {
    "iso:country":"CH",
    "sg:address":"Poststrasse 9",
    "sg:city":"Zug",
    "sg:orig_category":"Sonstiger Grosshandel",
    "sg:postcode":"6300",
    "sg:province":"Zug",
    "wof:name":"Predrag Ciric",
    "wof:placetype":"venue"
},
  "geometry": {"coordinates":[8.6541128159,47.2427024841],"type":"Point"}
}