{
  "type": "Feature",
  "properties": {
    "iso:country":"CH",
    "sg:address":"Scheurhofstrasse 4",
    "sg:city":"Aarwangen",
    "sg:orig_category":"Sportvereine Schwingen",
    "sg:postcode":"4912",
    "sg:province":"Bern",
    "wof:name":"Schwingklub Langenthal",
    "wof:placetype":"venue"
},
  "geometry": {"coordinates":[7.7645301819,47.2457351685],"type":"Point"}
}