{
  "type": "Feature",
  "properties": {
    "iso:country":"CH",
    "sg:address":"Grand Place Ouest 3963 Crans-sur-sierre. Postfach",
    "sg:city":"Crans-sur-sierre",
    "sg:orig_category":"Vermietung U Verpachtung von eigenen Immobilien",
    "sg:postcode":"3963",
    "sg:province":"Valais",
    "wof:name":"Elite-immobilien Ag Zuzwil",
    "wof:placetype":"venue"
},
  "geometry": {"coordinates":[9.1129798889,47.4723396301],"type":"Point"}
}