{
  "type": "Feature",
  "properties": {
    "iso:country":"CH",
    "sg:address":"2827",
    "sg:city":"Mervelier",
    "sg:orig_category":"Vereine Musik/Blasmusik",
    "sg:postcode":"2827",
    "sg:province":"Bern",
    "wof:name":"Fanfare Concordia",
    "wof:placetype":"venue"
},
  "geometry": {"coordinates":[7.4998111725,47.3437919617],"type":"Point"}
}