{
  "type": "Feature",
  "properties": {
    "iso:country":"CH",
    "sg:address":"Frohb\u00fcelstrasse 3",
    "sg:city":"Gr\u00fcningen",
    "sg:orig_category":"Herstellung von sonstigen chemischen Erzeugnissen",
    "sg:phone":"+41 19352455",
    "sg:postcode":"8627",
    "sg:province":"Z\u00fcrich",
    "wof:name":"Ziegler A. Chemisch-technische Spezialprodukte",
    "wof:placetype":"venue"
},
  "geometry": {"coordinates":[8.7577295303,47.2799568176],"type":"Point"}
}