{
  "type": "Feature",
  "properties": {
    "iso:country":"CH",
    "sg:address":"Br\u00fchlmattweg 5",
    "sg:city":"Ettingen",
    "sg:orig_category":"Handelsvermittlung U Grosshandel Sonstiger Grosshandel",
    "sg:phone":"+41 41 368 10 91",
    "sg:postcode":"4107",
    "sg:province":"Basel-Landschaft",
    "wof:name":"Metamex Ag",
    "wof:placetype":"venue"
},
  "geometry": {"coordinates":[8.3324298859,47.0359840393],"type":"Point"}
}