{
  "type": "Feature",
  "properties": {
    "iso:country":"CH",
    "sg:address":"Tulpenstrasse 39",
    "sg:city":"Z\u00fcrich",
    "sg:orig_category":"Grosshandel mit Eisenwaren sowie Installationsbedarf f\u00fcr Gas, Wasser U Heizung Grosshandel mit Werkz",
    "sg:phone":"+41 13227233",
    "sg:postcode":"8051",
    "sg:province":"Z\u00fcrich",
    "wof:name":"Bitterlin Herbert Ag",
    "wof:placetype":"venue"
},
  "geometry": {"coordinates":[8.5678977966,47.4056282043],"type":"Point"}
}