{
  "type": "Feature",
  "properties": {
    "iso:country":"CH",
    "sg:address":"Rue Du Levant 21",
    "sg:city":"Grimisuat",
    "sg:orig_category":"Ingenieurb\u00fcros Forst Technische, physikalische U chemische Untersuchung",
    "sg:phone":"+41 27 398 39 53",
    "sg:postcode":"1971",
    "sg:province":"Valais",
    "wof:name":"Nivalp Sa Etudes For\u00eat Et Environnement",
    "wof:placetype":"venue"
},
  "geometry": {"coordinates":[7.3791542053,46.2536087036],"type":"Point"}
}