{
  "type": "Feature",
  "properties": {
    "iso:country":"CH",
    "sg:address":"Haldenweg 7",
    "sg:city":"Lyss",
    "sg:orig_category":"Detailhandel mit Uhren U Schmuck",
    "sg:phone":"+41 32 384 25 40",
    "sg:postcode":"3250",
    "sg:province":"Bern",
    "wof:name":"Luciano Rosa Goldschmiede-atelier",
    "wof:placetype":"venue"
},
  "geometry": {"coordinates":[7.3123569489,47.0706367493],"type":"Point"}
}