{
  "type": "Feature",
  "properties": {
    "iso:country":"CH",
    "sg:address":"Albert-ankerstrasse 15",
    "sg:city":"Grenchen",
    "sg:orig_category":"Detailhandel mit Getr\u00e4nken G\u00fcterbef\u00f6rderung im Strassenverkehr",
    "sg:phone":"+41 62 873 13 45",
    "sg:postcode":"2540",
    "sg:province":"Solothurn",
    "wof:name":"Woodtli Transporte & Getr\u00e4nke Ag",
    "wof:placetype":"venue"
},
  "geometry": {"coordinates":[7.9680042267,47.539730072],"type":"Point"}
}