{
  "type": "Feature",
  "properties": {
    "iso:country":"CH",
    "sg:address":"Poststr. 4",
    "sg:city":"Ober\u00e4geri",
    "sg:classifiers":[
        {
            "category":"Banks & Credit Unions",
            "subcategory":"Bank",
            "type":"Services"
        }
    ],
    "sg:phone":"+41 4142724472",
    "sg:postcode":"6315",
    "sg:province":"Zug",
    "wof:name":"Zuger Kantonalbank",
    "wof:placetype":"venue"
},
  "geometry": {"coordinates":[8.611757,47.134663],"type":"Point"}
}