{
  "type": "Feature",
  "properties": {
    "iso:country":"CH",
    "sg:address":"In Der Fadmatt 5 8902 Urdorf. Postfach",
    "sg:city":"Urdorf",
    "sg:orig_category":"Softwareentwicklung U beratung",
    "sg:postcode":"8902",
    "sg:province":"Z\u00fcrich",
    "wof:name":"Foi Data, Felix Organisation Und Informatik",
    "wof:placetype":"venue"
},
  "geometry": {"coordinates":[8.4267272949,47.3818435669],"type":"Point"}
}