{
  "type": "Feature",
  "properties": {
    "iso:country":"CH",
    "sg:address":"Herrengasse 7 7000 Chur. Postfach",
    "sg:city":"Chur",
    "sg:orig_category":"Grosshandel mit Kaffee, Tee, Kakao U Gew\u00fcrzen",
    "sg:postcode":"7000",
    "sg:province":"Graubunden",
    "wof:name":"Neapolis Gmbh",
    "wof:placetype":"venue"
},
  "geometry": {"coordinates":[9.5311355591,46.8487052917],"type":"Point"}
}