{
  "type": "Feature",
  "properties": {
    "iso:country":"CH",
    "sg:address":"Landstrasse 33",
    "sg:city":"Andelfingen",
    "sg:orig_category":"Gymnastik U Fitnesszentren Physiotherapie",
    "sg:phone":"+41 81 740 08 40",
    "sg:postcode":"8450",
    "sg:province":"Z\u00fcrich",
    "wof:name":"Enggist Medical Fitness Gmbh Physiotherapie- U. Trainings-center Usw",
    "wof:placetype":"venue"
},
  "geometry": {"coordinates":[9.4732599258,47.1659355164],"type":"Point"}
}