{
  "type": "Feature",
  "properties": {
    "iso:country":"CH",
    "sg:address":"Beckenhofstrasse 61",
    "sg:city":"Z\u00fcrich",
    "sg:orig_category":"Softwareentwicklung U beratung",
    "sg:phone":"+41 19107870",
    "sg:postcode":"8006",
    "sg:province":"Z\u00fcrich",
    "wof:name":"Tremegisto Consulting",
    "wof:placetype":"venue"
},
  "geometry": {"coordinates":[8.5859270096,47.3189353943],"type":"Point"}
}