{
  "type": "Feature",
  "properties": {
    "iso:country":"CH",
    "sg:address":"Route De La Poudri\u00e8re 13",
    "sg:city":"Fribourg",
    "sg:orig_category":"Non-Classified Establishments",
    "sg:phone":"+41 26 424 07 39",
    "sg:postcode":"1700",
    "sg:province":"Fribourg",
    "wof:name":"Mulhauser Jean-claude.",
    "wof:placetype":"venue"
},
  "geometry": {"coordinates":[7.1397919655,46.7994918823],"type":"Point"}
}