{
  "type": "Feature",
  "properties": {
    "iso:country":"CH",
    "sg:address":"Herrengasse 25",
    "sg:city":"Schwyz",
    "sg:orig_category":"Religi\u00f6se Vereinigungen",
    "sg:phone":"+41 41 811 32 32",
    "sg:postcode":"6430",
    "sg:province":"Schwyz",
    "wof:name":"Franziskanische Gemeinschaft (fg) Der Deutschen Schweiz",
    "wof:placetype":"venue"
},
  "geometry": {"coordinates":[8.6507749557,47.0220680237],"type":"Point"}
}