{
  "type": "Feature",
  "properties": {
    "iso:country":"CH",
    "sg:address":"Alte Steinhauserstrasse 1",
    "sg:city":"Cham",
    "sg:orig_category":"Reiseb\u00fcros U Reiseveranstalter",
    "sg:phone":"+41 12611111",
    "sg:postcode":"6330",
    "sg:province":"Zug",
    "wof:name":"Reisewelt Ag",
    "wof:placetype":"venue"
},
  "geometry": {"coordinates":[8.4739131927,47.1866035461],"type":"Point"}
}