{
  "type": "Feature",
  "properties": {
    "iso:country":"CH",
    "sg:address":"Chemin Du Ch\u00e2telard 1 1033 Cheseaux-lausanne. Postfach",
    "sg:city":"Cheseaux-lausanne",
    "sg:orig_category":"Herstellung von B\u00fcro U Ladenm\u00f6beln",
    "sg:phone":"+41 71 388 10 90",
    "sg:postcode":"1033",
    "sg:province":"Vaud",
    "wof:name":"Swissdesign Ladenbau Ag",
    "wof:placetype":"venue"
},
  "geometry": {"coordinates":[9.2511377335,47.4156455994],"type":"Point"}
}