{
  "type": "Feature",
  "properties": {
    "iso:country":"CH",
    "sg:address":"Riet 391",
    "sg:city":"Zihlschlacht",
    "sg:orig_category":"Sportvereine Ballsport Badminton",
    "sg:phone":"+41 71 422 42 17",
    "sg:postcode":"8588",
    "sg:province":"Thurgau",
    "wof:name":"Badminton-club Sitterdorf",
    "wof:placetype":"venue"
},
  "geometry": {"coordinates":[9.2709503174,47.516078949],"type":"Point"}
}