{
  "type": "Feature",
  "properties": {
    "iso:country":"CH",
    "sg:address":"Hintergasse",
    "sg:city":"Rohrbach",
    "sg:orig_category":"Blumen U Zierpflanzenbau Detailhandel mit Blumen U Pflanzen",
    "sg:phone":"+41 62 965 27 05",
    "sg:postcode":"4938",
    "sg:province":"Bern",
    "wof:name":"Hans Lanz",
    "wof:placetype":"venue"
},
  "geometry": {"coordinates":[7.812567,47.138699],"type":"Point"}
}