{
  "type": "Feature",
  "properties": {
    "iso:country":"CH",
    "sg:address":"Grabenackerstrasse 268",
    "sg:city":"Horriwil",
    "sg:classifiers":[
        {
            "category":"Arena",
            "subcategory":"Sports Club",
            "type":"Entertainment"
        }
    ],
    "sg:postcode":"4557",
    "sg:province":"Solothurn",
    "sg:tags":[
        "karate",
        "judo",
        "sportvereine"
    ],
    "wof:name":"Karateclub Gerlafingen",
    "wof:placetype":"venue"
},
  "geometry": {"coordinates":[7.6230959892,47.1816482544],"type":"Point"}
}