{
  "type": "Feature",
  "properties": {
    "iso:country":"CH",
    "sg:address":"Ragazerstrasse 43a 7320 Sargans. Postfach",
    "sg:city":"Sargans",
    "sg:orig_category":"Non-Classified Establishments",
    "sg:postcode":"7320",
    "sg:province":"St. Gallen",
    "wof:name":"Good Transporte Gmbh",
    "wof:placetype":"venue"
},
  "geometry": {"coordinates":[9.4483585358,47.0421600342],"type":"Point"}
}