{
  "type": "Feature",
  "properties": {
    "iso:country":"CH",
    "sg:address":"En Budron E7 1052 Mont-sur-lausanne Case Postale 287",
    "sg:city":"Mont-sur-lausanne",
    "sg:orig_category":"Grosshandel mit Nahrungsmitteln, Getr\u00e4nken U Tabakwaren",
    "sg:phone":"+41 21 652 19 86",
    "sg:postcode":"1052",
    "sg:province":"Vaud",
    "wof:name":"Vopal Sa Import.champignons S\u00e9ch\u00e9s",
    "wof:placetype":"venue"
},
  "geometry": {"coordinates":[6.63539505,46.5568962097],"type":"Point"}
}