{
  "type": "Feature",
  "properties": {
    "iso:country":"CH",
    "sg:address":"Im Schlund",
    "sg:city":"Kriens",
    "sg:orig_category":"Sonstige mit Sport verbundene T\u00e4tigkeiten",
    "sg:postcode":"6010",
    "sg:province":"Luzern",
    "wof:name":"Schmid Susi",
    "wof:placetype":"venue"
},
  "geometry": {"coordinates":[8.2946548462,47.0198402405],"type":"Point"}
}