{
  "type": "Feature",
  "properties": {
    "iso:country":"CH",
    "sg:address":"Chemin Des Neigles 31",
    "sg:city":"Fribourg",
    "sg:classifiers":[
        {
            "category":"Restaurant",
            "type":"Food & Drink"
        }
    ],
    "sg:phone":"+41 26 481 36 22",
    "sg:postcode":"1700",
    "sg:province":"Fribourg",
    "wof:name":"Caf\u00e9 La Passerelle",
    "wof:placetype":"venue"
},
  "geometry": {"coordinates":[7.1620941162,46.8105278015],"type":"Point"}
}