{
  "type": "Feature",
  "properties": {
    "iso:country":"CH",
    "sg:address":"Bernstr. 41",
    "sg:city":"Jegenstorf",
    "sg:classifiers":[
        {
            "category":"Manufacturing",
            "subcategory":"Printing",
            "type":"Manufacturing & Wholesale Goods"
        }
    ],
    "sg:phone":"+41 31 762 18 19",
    "sg:postcode":"3303",
    "sg:province":"Bern",
    "sg:tags":[
        "publishing"
    ],
    "wof:name":"Kletex Siebdruck Ag",
    "wof:placetype":"venue"
},
  "geometry": {"coordinates":[7.5052371025,47.0448951721],"type":"Point"}
}