{
  "type": "Feature",
  "properties": {
    "iso:country":"CH",
    "sg:address":"W\u00fchrenbach 8815 Horgenberg. Postfach",
    "sg:city":"Horgenberg",
    "sg:orig_category":"Sonstige mit Sport verbundene T\u00e4tigkeiten",
    "sg:postcode":"8815",
    "sg:province":"Z\u00fcrich",
    "wof:name":"Reitzentrum Schmid",
    "wof:placetype":"venue"
},
  "geometry": {"coordinates":[7.273291111,46.4793434143],"type":"Point"}
}