{
  "type": "Feature",
  "properties": {
    "iso:country":"CH",
    "sg:address":"Villa Jeanne D'arc",
    "sg:city":"Ch\u00e2teau-d'oex",
    "sg:orig_category":"Herstellung von Teppichen Verlegen von Fliesen U Platten",
    "sg:phone":"+41 26 924 60 09",
    "sg:postcode":"1837",
    "wof:name":"Vago Michel",
    "wof:placetype":"venue"
},
  "geometry": {"coordinates":[0.6858400106,45.2460517883],"type":"Point"}
}