{
  "type": "Feature",
  "properties": {
    "iso:country":"CH",
    "sg:address":"Roches Chemin Des 16",
    "sg:city":"Pully",
    "sg:orig_category":"Wirtschaftspr\u00fcfung, Steuerberatung U Treuhand",
    "sg:phone":"+41 21283270",
    "sg:postcode":"1009",
    "sg:province":"Vaud",
    "wof:name":"Fiduciaire Marc Freiburghaus",
    "wof:placetype":"venue"
},
  "geometry": {"coordinates":[6.6598000526,46.5102577209],"type":"Point"}
}