{
  "type": "Feature",
  "properties": {
    "iso:country":"CH",
    "sg:address":"Rue Du Pr\u00e9 Dse La Fontaine 11 1242 Satigny. Postfach",
    "sg:city":"Meyrin",
    "sg:orig_category":"Herstellung von Konstruktionsteilen, Fertigbauteilen U Ausbauelementen aus Holz",
    "sg:postcode":"1217",
    "sg:province":"Gen\u00e8ve",
    "wof:name":"Menuiserie \u00ac Agencement",
    "wof:placetype":"venue"
},
  "geometry": {"coordinates":[6.0540099144,46.2238502502],"type":"Point"}
}