{
  "type": "Feature",
  "properties": {
    "iso:country":"CH",
    "sg:address":"Badweg 13",
    "sg:city":"Seengen",
    "sg:orig_category":"Sportvereine Orientierungslauf",
    "sg:postcode":"5707",
    "sg:province":"Aargau",
    "wof:name":"Olk Argus",
    "wof:placetype":"venue"
},
  "geometry": {"coordinates":[8.2074556351,47.3198280334],"type":"Point"}
}