{
  "type": "Feature",
  "properties": {
    "iso:country":"CH",
    "sg:address":"Henauerstrasse 17",
    "sg:city":"Niederuzwil",
    "sg:classifiers":[
        {
            "category":"Travel",
            "subcategory":"Hotels & Motels",
            "type":"Entertainment"
        }
    ],
    "sg:phone":"+41 71 951 51 18",
    "sg:postcode":"9244",
    "sg:province":"St. Gallen",
    "sg:tags":[
        "hotels",
        "mit",
        "restaurant"
    ],
    "wof:name":"Hotel L\u00f6wen Go West Niederuzwil",
    "wof:placetype":"venue"
},
  "geometry": {"coordinates":[9.1398210526,47.4452934265],"type":"Point"}
}