{
  "type": "Feature",
  "properties": {
    "iso:country":"CH",
    "sg:address":"Chollerweg 36",
    "sg:city":"Trimbach",
    "sg:orig_category":"Politische Parteien SVP",
    "sg:phone":"+41 41 870 31 37",
    "sg:postcode":"4632",
    "sg:province":"Solothurn",
    "wof:name":"Svp Uri",
    "wof:placetype":"venue"
},
  "geometry": {"coordinates":[8.6153059006,46.881893158],"type":"Point"}
}