{
  "type": "Feature",
  "properties": {
    "iso:country":"CH",
    "sg:address":"Birkenstrasse 1",
    "sg:city":"Therwil",
    "sg:classifiers":[
        {
            "category":"Insurance",
            "subcategory":"Insurance Agent",
            "type":"Services"
        }
    ],
    "sg:phone":"+41 56 427 23 23",
    "sg:postcode":"4106",
    "sg:province":"Basel-Landschaft",
    "sg:tags":[
        "versicherungsagenturen",
        "-broker"
    ],
    "wof:name":"Winterthur Leben Agentur Walter Schneider",
    "wof:placetype":"venue"
},
  "geometry": {"coordinates":[8.3128318787,47.466594696],"type":"Point"}
}