{
  "type": "Feature",
  "properties": {
    "iso:country":"CH",
    "sg:address":"Belpstrasse 67",
    "sg:city":"Bern",
    "sg:orig_category":"Druck ohne Zeitungsdruck Offsetdruck",
    "sg:phone":"+41 31 371 04 44",
    "sg:postcode":"3007",
    "sg:province":"Bern",
    "wof:name":"Buch- & Offsetdruck Haeni Ag",
    "wof:placetype":"venue"
},
  "geometry": {"coordinates":[7.4312791824,46.9418754578],"type":"Point"}
}