{
  "type": "Feature",
  "properties": {
    "iso:country":"CH",
    "sg:address":"Zugerstrasse 45",
    "sg:city":"Cham",
    "sg:orig_category":"Herstellung von Sportger\u00e4ten",
    "sg:postcode":"6330",
    "sg:province":"Zug",
    "wof:name":"Royal P\u00eache, Rivero Miguel",
    "wof:placetype":"venue"
},
  "geometry": {"coordinates":[6.8356318474,47.1064758301],"type":"Point"}
}