{
  "type": "Feature",
  "properties": {
    "iso:country":"CH",
    "sg:address":"Weidstrasse",
    "sg:city":"Walchwil",
    "sg:orig_category":"Bildung and Forschung, Schulen",
    "sg:phone":"+41 41 758 21 26",
    "sg:postcode":"6318",
    "sg:province":"Zug",
    "wof:name":"Institut Montana",
    "wof:placetype":"venue"
},
  "geometry": {"coordinates":[8.507818,47.120113],"type":"Point"}
}