{
  "type": "Feature",
  "properties": {
    "iso:country":"CH",
    "sg:address":"Wieslergasse 2",
    "sg:city":"Z\u00fcrich",
    "sg:classifiers":[
        {
            "category":"Banks & Credit Unions",
            "subcategory":"Bank",
            "type":"Services"
        }
    ],
    "sg:phone":"+41 13411660",
    "sg:postcode":"8049",
    "sg:province":"Z\u00fcrich",
    "wof:name":"Credit Suisse",
    "wof:placetype":"venue"
},
  "geometry": {"coordinates":[8.495753,47.402405],"type":"Point"}
}