{
  "type": "Feature",
  "properties": {
    "iso:country":"CH",
    "sg:address":"1911",
    "sg:city":"Ovronnaz",
    "sg:classifiers":[
        {
            "category":"Restaurant",
            "type":"Food & Drink"
        }
    ],
    "sg:phone":"+41 27 306 25 55",
    "sg:postcode":"1911",
    "sg:province":"Valais",
    "wof:name":"Restaurant Vieux Valais & Pizzeria",
    "wof:placetype":"venue"
},
  "geometry": {"coordinates":[7.1727199554,46.1974105835],"type":"Point"}
}