{
  "type": "Feature",
  "properties": {
    "iso:country":"CH",
    "sg:address":"Petit-cottens 1268 Begnins Case Postale",
    "sg:city":"Begnins",
    "sg:orig_category":"Interessenvertretungen",
    "sg:postcode":"1268",
    "sg:province":"Vaud",
    "wof:name":"Groupement De D\u00e9fense Contre La Gr\u00eale Et Les Calamit\u00e9s Naturelles De Begnins Et Environs",
    "wof:placetype":"venue"
},
  "geometry": {"coordinates":[6.2577261925,46.4408340454],"type":"Point"}
}