{
  "type": "Feature",
  "properties": {
    "iso:country":"CH",
    "sg:address":"L\u00e4nggasse 1c",
    "sg:city":"Thun",
    "sg:orig_category":"K\u00fcnstlerische Schulen Sonstige mit der Informatik verbundene T\u00e4tigkeiten",
    "sg:phone":"+41 79 622 40 34",
    "sg:postcode":"3600",
    "sg:province":"Bern",
    "wof:name":"Schmid It",
    "wof:placetype":"venue"
},
  "geometry": {"coordinates":[7.6269922256,46.7546844482],"type":"Point"}
}