{
  "type": "Feature",
  "properties": {
    "iso:country":"CH",
    "sg:address":"Hasliweg 1",
    "sg:city":"D\u00fcdingen",
    "sg:orig_category":"Verwertung von Milch",
    "sg:postcode":"3186",
    "sg:province":"Fribourg",
    "wof:name":"Dumas Jos.",
    "wof:placetype":"venue"
},
  "geometry": {"coordinates":[6.93791008,46.6277694702],"type":"Point"}
}