{
  "type": "Feature",
  "properties": {
    "iso:country":"CH",
    "sg:address":"Lagerstr. 12",
    "sg:city":"Dintikon",
    "sg:classifiers":[
        {
            "category":"Professional",
            "type":"Services"
        }
    ],
    "sg:phone":"+41 56 616 96 96",
    "sg:postcode":"5606",
    "sg:province":"Aargau",
    "sg:tags":[
        "transport",
        "road"
    ],
    "wof:name":"Setz G\u00dctertransport Ag",
    "wof:placetype":"venue"
},
  "geometry": {"coordinates":[8.231048584,47.3686065674],"type":"Point"}
}