{
  "type": "Feature",
  "properties": {
    "addr:full":"Ueberlandstrasse 131 D\u00fcbendorf Z\u00fcrich 8600",
    "addr:housenumber":"131",
    "addr:postcode":"8600",
    "addr:street":"Ueberlandstrasse;Zuerich",
    "iso:country":"CH",
    "sg:address":"Ueberlandstrasse 131",
    "sg:city":"D\u00fcbendorf",
    "sg:classifiers":[
        {
            "category":"Education",
            "subcategory":"Library",
            "type":"Public Place"
        }
    ],
    "sg:postcode":"8600",
    "sg:province":"Z\u00fcrich",
    "sg:tags":[
        "u",
        "bibliotheken",
        "archive"
    ],
    "wof:name":"Empa Bibliothek",
    "wof:placetype":"venue"
},
  "geometry": {"coordinates":[8.613964,47.401169],"type":"Point"}
}