{
  "type": "Feature",
  "properties": {
    "iso:country":"CH",
    "sg:address":"Fabrikmattenweg 4",
    "sg:city":"Arlesheim",
    "sg:orig_category":"Hardwareberatung",
    "sg:postcode":"4144",
    "sg:province":"Basel-Landschaft",
    "wof:name":"Linc Software Services Private Ltd, Bangalore, Zweigniederlassung Arlesheim",
    "wof:placetype":"venue"
},
  "geometry": {"coordinates":[7.6093201637,47.4947128296],"type":"Point"}
}