{
  "type": "Feature",
  "properties": {
    "iso:country":"CH",
    "sg:address":"Magdalenastrasse 46",
    "sg:city":"Magden",
    "sg:orig_category":"Elektromechanische Werkst\u00e4tten",
    "sg:phone":"+41 61 843 10 30",
    "sg:postcode":"4312",
    "sg:province":"Aargau",
    "wof:name":"Franz Hess Technischer Service",
    "wof:placetype":"venue"
},
  "geometry": {"coordinates":[7.8167247772,47.5262947083],"type":"Point"}
}