{
  "type": "Feature",
  "properties": {
    "iso:country":"CH",
    "sg:address":"3472 Wynigen. Postfach",
    "sg:city":"Wynigen",
    "sg:orig_category":"Detailhandel mit Waren verschiedener Art, Hauptrichtung Nahrungsmittel",
    "sg:phone":"+41 34 415 12 47",
    "sg:postcode":"3472",
    "sg:province":"Bern",
    "wof:name":"Landi Wynigen - Burgdorf",
    "wof:placetype":"venue"
},
  "geometry": {"coordinates":[7.667828083,47.1060791016],"type":"Point"}
}