{
  "type": "Feature",
  "properties": {
    "iso:country":"CH",
    "sg:address":"7438",
    "sg:city":"Hinterrhein",
    "sg:orig_category":"Non-Classified Establishments",
    "sg:phone":"+41 91 828 11 22",
    "sg:postcode":"7438",
    "sg:province":"Graubunden",
    "wof:name":"Cava Quarzite Sa",
    "wof:placetype":"venue"
},
  "geometry": {"coordinates":[9.1967449188,46.530380249],"type":"Point"}
}