{
  "type": "Feature",
  "properties": {
    "iso:country":"CH",
    "sg:address":"Heinrich Stutz-strasse 23",
    "sg:city":"Urdorf",
    "sg:orig_category":"Detailhandel mit Metallwaren, Anstrichmitteln, Glaswaren, Bau U Heimwerkerbedarf Einzelhandel mit Au",
    "sg:phone":"+41 17344949",
    "sg:postcode":"8902",
    "sg:province":"Z\u00fcrich",
    "wof:name":"Autoglaserei Brombach Ag",
    "wof:placetype":"venue"
},
  "geometry": {"coordinates":[8.4251089096,47.3700027466],"type":"Point"}
}