{
  "type": "Feature",
  "properties": {
    "iso:country":"CH",
    "sg:address":"Zugerstrasse 4",
    "sg:city":"Cham",
    "sg:orig_category":"Zahntechnische Laboratorien",
    "sg:phone":"+41 41 781 10 40",
    "sg:postcode":"6330",
    "sg:province":"Zug",
    "wof:name":"Antonio Torsello Dental-labor",
    "wof:placetype":"venue"
},
  "geometry": {"coordinates":[8.4604520798,47.1811637878],"type":"Point"}
}