{
  "type": "Feature",
  "properties": {
    "iso:country":"CH",
    "sg:address":"Luzernerstrasse 16",
    "sg:city":"Ebikon",
    "sg:orig_category":"Grosshandel mit festen Brennstoffen U Mineral\u00f6lerzeugnissen Tankstellen",
    "sg:phone":"+41 41 440 92 88",
    "sg:postcode":"6030",
    "sg:province":"Luzern",
    "wof:name":"Hans Jun. Tiefenauer Tankstellenbetrieb",
    "wof:placetype":"venue"
},
  "geometry": {"coordinates":[8.3354120255,47.0784835815],"type":"Point"}
}