{
  "type": "Feature",
  "properties": {
    "iso:country":"CH",
    "sg:address":"Erlenbachstr. 3 B",
    "sg:city":"Herisau",
    "sg:orig_category":"Herstellung von sonstigen Maschinen f\u00fcr unspezifische Verwendung",
    "sg:phone":"+41 71 352 37 78",
    "sg:postcode":"9100",
    "sg:province":"Appenzell Ausserrhoden",
    "wof:name":"Techmax-tanner",
    "wof:placetype":"venue"
},
  "geometry": {"coordinates":[9.2772789001,47.3791046143],"type":"Point"}
}