{
  "type": "Feature",
  "properties": {
    "iso:country":"CH",
    "sg:address":"Hauptstrasse 5",
    "sg:city":"Niedererlinsbach",
    "sg:orig_category":"Unclassifiable Establishments",
    "sg:postcode":"5015",
    "sg:province":"Solothurn",
    "wof:name":"Kreuz Drogerie Ag",
    "wof:placetype":"venue"
},
  "geometry": {"coordinates":[8.008272171,47.3978729248],"type":"Point"}
}