{
  "type": "Feature",
  "properties": {
    "iso:country":"CH",
    "sg:address":"Rotbuchstrasse 8 8006 Z\u00fcrich. Postfach",
    "sg:city":"Z\u00fcrich",
    "sg:orig_category":"Wirtschaftspr\u00fcfung, Steuerberatung U Treuhand",
    "sg:phone":"+41 13630400",
    "sg:postcode":"8042",
    "sg:province":"Z\u00fcrich",
    "wof:name":"Weisskopf Elisabeth",
    "wof:placetype":"venue"
},
  "geometry": {"coordinates":[8.5375471115,47.3914260864],"type":"Point"}
}