{
  "type": "Feature",
  "properties": {
    "iso:country":"CH",
    "sg:address":"Au Village",
    "sg:city":"Chamblon",
    "sg:orig_category":"Wirtschaftspr\u00fcfung, Steuerberatung U Treuhand",
    "sg:phone":"+41 24 445 52 52",
    "sg:postcode":"1436",
    "sg:province":"Vaud",
    "wof:name":"Fiduciaire Heiz Daniel Sa",
    "wof:placetype":"venue"
},
  "geometry": {"coordinates":[6.6037330627,46.7782745361],"type":"Point"}
}