{
  "type": "Feature",
  "properties": {
    "addr:full":"Dorfstrasse 14 Schindellegi Schwyz 8834",
    "addr:housenumber":"14",
    "addr:postcode":"8834",
    "addr:street":"Dorfstrasse;Schwyz",
    "iso:country":"CH",
    "sg:address":"Dorfstrasse 14",
    "sg:city":"Schindellegi",
    "sg:orig_category":"Detailhandel mit Blumen U Pflanzen",
    "sg:phone":"+41 17841008",
    "sg:postcode":"8834",
    "sg:province":"Schwyz",
    "wof:name":"Flower Power Andrea K\u00e4lin Blumengesch\u00e4ft",
    "wof:placetype":"venue"
},
  "geometry": {"coordinates":[8.711153,47.175175],"type":"Point"}
}