{
  "type": "Feature",
  "properties": {
    "iso:country":"CH",
    "sg:address":"Gutenbergstrasse 4",
    "sg:city":"Kreuzlingen",
    "sg:orig_category":"Gesundheitswesen",
    "sg:postcode":"8280",
    "sg:province":"Thurgau",
    "wof:name":"Biothera Gmbh",
    "wof:placetype":"venue"
},
  "geometry": {"coordinates":[9.1714811325,47.6507263184],"type":"Point"}
}