{
  "type": "Feature",
  "properties": {
    "iso:country":"CH",
    "sg:address":"Poststrasse 22",
    "sg:city":"Biel/bienne",
    "sg:orig_category":"Detailhandel mit Fleisch U Fleischwaren",
    "sg:phone":"+41 32 341 71 65",
    "sg:postcode":"2504",
    "sg:province":"Bern",
    "wof:name":"Balkan Metzgerei Gmbh",
    "wof:placetype":"venue"
},
  "geometry": {"coordinates":[7.2725110054,47.1459579468],"type":"Point"}
}