{
  "type": "Feature",
  "properties": {
    "addr:full":"Hauptstrasse 35 Birsfelden Basel-Landschaft 4127",
    "addr:housenumber":"35",
    "addr:postcode":"4127",
    "addr:street":"Hauptstrasse",
    "iso:country":"CH",
    "sg:address":"Hauptstrasse 35",
    "sg:city":"Birsfelden",
    "sg:orig_category":"Arztpraxen",
    "sg:phone":"+41 61 312 30 50",
    "sg:postcode":"4127",
    "sg:province":"Basel-Landschaft",
    "wof:name":"Dr.med.evelyne Wagner Spezial\u00e4rztin Fmh",
    "wof:placetype":"venue"
},
  "geometry": {"coordinates":[7.620555,47.554016],"type":"Point"}
}