{
  "type": "Feature",
  "properties": {
    "iso:country":"CH",
    "sg:address":"Neue Winterthurerstrasse 26",
    "sg:city":"Wallisellen",
    "sg:orig_category":"Mechanische Werkst\u00e4tten",
    "sg:phone":"+41 21 801 24 50",
    "sg:postcode":"8304",
    "sg:province":"Z\u00fcrich",
    "wof:name":"Bruno D\u00fcrst Atelier M\u00e9canique De Pr\u00e9cision",
    "wof:placetype":"venue"
},
  "geometry": {"coordinates":[6.496372,46.508636],"type":"Point"}
}