{
  "type": "Feature",
  "properties": {
    "iso:country":"CH",
    "sg:address":"Rathausgasse 62",
    "sg:city":"Bern",
    "sg:orig_category":"Reparatur von Uhren U Schmuck Sonstiger Fachdetailhandel in Verkaufsr\u00e4umen",
    "sg:phone":"+41 31 311 50 82",
    "sg:postcode":"3011",
    "sg:province":"Bern",
    "wof:name":"Lowositz Uhren M\u00fcnzen",
    "wof:placetype":"venue"
},
  "geometry": {"coordinates":[7.449174881,46.9485092163],"type":"Point"}
}