{
  "type": "Feature",
  "properties": {
    "iso:country":"CH",
    "sg:address":"Klosterplatz 9 4500 Solothurn. Postfach 1117",
    "sg:city":"Solothurn",
    "sg:orig_category":"Fotografische Ateliers Fotografisches Gewerbe U fotografische Laboratorien",
    "sg:phone":"+41 32 622 66 07",
    "sg:postcode":"4502",
    "sg:province":"Solothurn",
    "wof:name":"Fotografie Staub Matthias",
    "wof:placetype":"venue"
},
  "geometry": {"coordinates":[7.5394558907,47.2073364258],"type":"Point"}
}