{
  "type": "Feature",
  "properties": {
    "iso:country":"CH",
    "sg:address":"L\u00f6wenstrasse 16",
    "sg:city":"Goldach",
    "sg:orig_category":"Vermittlung von Immobilien Verwaltung von Immobilien",
    "sg:phone":"+41 71 841 73 08",
    "sg:postcode":"9403",
    "sg:province":"St. Gallen",
    "wof:name":"Btg Bau-treuhand-gesellschaft Immogaplan Ag",
    "wof:placetype":"venue"
},
  "geometry": {"coordinates":[9.4683790207,47.4762687683],"type":"Point"}
}