{
  "type": "Feature",
  "properties": {
    "iso:country":"CH",
    "sg:address":"1946",
    "sg:city":"Bourg-st-pierre",
    "sg:orig_category":"Pensionskassen",
    "sg:postcode":"1946",
    "sg:province":"Valais",
    "wof:name":"Fonds De Pr\u00e9voyance En Faveur Du Personnel De La Soci\u00e9t\u00e9 Du Tunnel Du Grand-st-bernard Sa",
    "wof:placetype":"venue"
},
  "geometry": {"coordinates":[7.2080621719,45.9501571655],"type":"Point"}
}