{
  "type": "Feature",
  "properties": {
    "iso:country":"CH",
    "sg:address":"Gottardo Via San 10",
    "sg:city":"Lugano",
    "sg:orig_category":"Unternehmensberatung",
    "sg:postcode":"6900",
    "sg:province":"Ticino",
    "wof:name":"Prestige Wirtschafts-und Beratungs Ag",
    "wof:placetype":"venue"
},
  "geometry": {"coordinates":[8.9495763779,46.0090141296],"type":"Point"}
}