{
  "type": "Feature",
  "properties": {
    "iso:country":"CH",
    "sg:address":"Meikirchstrasse 3 3042 Ortschwaben. Postfach",
    "sg:city":"Ortschwaben",
    "sg:orig_category":"Wirtschaftspr\u00fcfung, Steuerberatung U Treuhand",
    "sg:phone":"+41 79 234 59 39",
    "sg:postcode":"3042",
    "sg:province":"Bern",
    "wof:name":"M\u00e4chler Treuhand",
    "wof:placetype":"venue"
},
  "geometry": {"coordinates":[8.8602313995,47.2519683838],"type":"Point"}
}