{
  "type": "Feature",
  "properties": {
    "iso:country":"CH",
    "sg:address":"Z\u00fcrcherstr. 42",
    "sg:city":"Zurzach",
    "sg:classifiers":[
        {
            "category":"Manufacturing",
            "subcategory":"Chemicals & Compounds",
            "type":"Manufacturing & Wholesale Goods"
        }
    ],
    "sg:phone":"+41 56 269 61 61",
    "sg:postcode":"5330",
    "sg:province":"Aargau",
    "sg:tags":[
        "pharmaceutical",
        "chemistry",
        "-",
        "by-product"
    ],
    "wof:name":"Solvay (schweiz) Ag",
    "wof:placetype":"venue"
},
  "geometry": {"coordinates":[8.30769,47.581566],"type":"Point"}
}