{
  "type": "Feature",
  "properties": {
    "iso:country":"CH",
    "sg:address":"Elisabethenstrasse 2 4051 Basel. Postfach 130",
    "sg:city":"Basel",
    "sg:orig_category":"Advokaturb\u00fcros Notariate",
    "sg:phone":"+41 61 272 12 40",
    "sg:postcode":"4010",
    "sg:province":"Basel-Stadt",
    "wof:name":"Kuster Fl\u00fcckiger Mayer Zellweger & Meyer",
    "wof:placetype":"venue"
},
  "geometry": {"coordinates":[7.591765,47.553627],"type":"Point"}
}