{
  "type": "Feature",
  "properties": {
    "addr:full":"Monbijoustrasse 27 3011 Bern. Postfach Bern Bern 3011",
    "addr:housenumber":"27",
    "addr:postcode":"3011;postfach;3011",
    "addr:street":"Monbijoustrasse",
    "iso:country":"CH",
    "sg:address":"Monbijoustrasse 27 3011 Bern. Postfach",
    "sg:city":"Bern",
    "sg:orig_category":"Allgemeinbildende weiterf\u00fchrende Schulen",
    "sg:phone":"+41 31 382 28 43",
    "sg:postcode":"3011",
    "sg:province":"Bern",
    "wof:name":"Ikf Institut F\u00fcr Kulturelle Forschung Ag",
    "wof:placetype":"venue"
},
  "geometry": {"coordinates":[7.436127,46.943966],"type":"Point"}
}