{
  "type": "Feature",
  "properties": {
    "addr:full":"Poststrasse 37 Spreitenbach Aargau 8957",
    "addr:housenumber":"37",
    "addr:postcode":"8957",
    "addr:street":"Poststrasse",
    "iso:country":"CH",
    "sg:address":"Poststrasse 37",
    "sg:city":"Spreitenbach",
    "sg:orig_category":"Allgemeiner Hoch U Tiefbau Allgemeiner Hochbau",
    "sg:phone":"+41 56 401 11 76",
    "sg:postcode":"8957",
    "sg:province":"Aargau",
    "wof:name":"Febi Ag Hoch-& Tiefbau",
    "wof:placetype":"venue"
},
  "geometry": {"coordinates":[8.361479,47.421078],"type":"Point"}
}