{
  "type": "Feature",
  "properties": {
    "iso:country":"CH",
    "sg:address":"Chlingenstrasse 18",
    "sg:city":"Baar",
    "sg:orig_category":"K\u00fcnstlerische U schriftstellerische T\u00e4tigkeiten U Darbietungen",
    "sg:postcode":"6340",
    "sg:province":"Zug",
    "wof:name":"Buss G\u00fcnter",
    "wof:placetype":"venue"
},
  "geometry": {"coordinates":[8.5358200073,47.199546814],"type":"Point"}
}