{
  "type": "Feature",
  "properties": {
    "iso:country":"CH",
    "sg:address":"Dorfstrasse 28",
    "sg:city":"Sch\u00fcpfen",
    "sg:orig_category":"Mahl U Sch\u00e4lm\u00fchlen",
    "sg:phone":"+41 81 756 11 23",
    "sg:postcode":"3054",
    "sg:province":"Bern",
    "wof:name":"Landi Buchs",
    "wof:placetype":"venue"
},
  "geometry": {"coordinates":[9.4795560837,47.1641387939],"type":"Point"}
}