{
  "type": "Feature",
  "properties": {
    "iso:country":"CH",
    "sg:address":"Widenbachstrasse 4",
    "sg:city":"Hinterforst",
    "sg:orig_category":"Herstellung von k\u00e4lte U lufttechnischen Erzeugnissen f\u00fcr gewerbliche Zwecke Sanit\u00e4rinstallation",
    "sg:phone":"+41 71 755 55 90",
    "sg:postcode":"9452",
    "sg:province":"St. Gallen",
    "wof:name":"As-heiztechnik, Schlegel Heidi",
    "wof:placetype":"venue"
},
  "geometry": {"coordinates":[9.5329999924,47.3626022339],"type":"Point"}
}