{
  "type": "Feature",
  "properties": {
    "iso:country":"CH",
    "sg:address":"Rue Des Moulins 14",
    "sg:city":"Neuch\u00e2tel",
    "sg:orig_category":"Unclassifiable Establishments",
    "sg:postcode":"2000",
    "sg:province":"Neuch\u00e2tel",
    "wof:name":"Violette Pini Boutique Ca Marche",
    "wof:placetype":"venue"
},
  "geometry": {"coordinates":[6.9284381866,46.9922447205],"type":"Point"}
}