{
  "type": "Feature",
  "properties": {
    "addr:full":"Riehenstrasse 157 Basel Basel-Stadt 4058",
    "addr:housenumber":"157",
    "addr:postcode":"4058",
    "addr:street":"Riehenstrasse",
    "iso:country":"CH",
    "sg:address":"Riehenstrasse 157",
    "sg:city":"Basel",
    "sg:orig_category":"Bau U Wohngenossenschaften",
    "sg:postcode":"4058",
    "sg:province":"Basel-Stadt",
    "wof:name":"Bau-& Wohngen.allschwil",
    "wof:placetype":"venue"
},
  "geometry": {"coordinates":[7.851775,47.485214],"type":"Point"}
}