{
  "type": "Feature",
  "properties": {
    "iso:country":"CH",
    "sg:address":"Eichenweg 12a",
    "sg:city":"Uttigen",
    "sg:orig_category":"Herstellung von K\u00fcchenm\u00f6beln",
    "sg:phone":"+41 33 345 72 70",
    "sg:postcode":"3628",
    "sg:province":"Bern",
    "wof:name":"Fk K\u00fcchen Und B\u00e4der Gmbh",
    "wof:placetype":"venue"
},
  "geometry": {"coordinates":[7.5837221146,46.7896614075],"type":"Point"}
}