{
  "type": "Feature",
  "properties": {
    "iso:country":"CH",
    "sg:address":"Avenue De Belmont 6",
    "sg:city":"Pully",
    "sg:orig_category":"Interessenvertretungen",
    "sg:postcode":"1009",
    "sg:province":"Vaud",
    "wof:name":"Fondation Les Tamaris",
    "wof:placetype":"venue"
},
  "geometry": {"coordinates":[6.6626391411,46.5171699524],"type":"Point"}
}