{
  "type": "Feature",
  "properties": {
    "iso:country":"CH",
    "sg:address":"Dorf 29b",
    "sg:city":"Uebeschi",
    "sg:orig_category":"Bauschreinerei",
    "sg:phone":"+41 33 345 38 60",
    "sg:postcode":"3635",
    "sg:province":"Bern",
    "wof:name":"Hans Scheidegger Schreinerei",
    "wof:placetype":"venue"
},
  "geometry": {"coordinates":[7.553265,46.738708],"type":"Point"}
}