{
  "type": "Feature",
  "properties": {
    "iso:country":"CH",
    "sg:address":"L\u00f6weng\u00e4sschen 2",
    "sg:city":"Schaffhausen",
    "sg:orig_category":"Parf\u00fcmerien U sonstiger Detailhandel mit kosmetischen Artikeln U K\u00f6rperpflegemitteln",
    "sg:phone":"+41 71 222 55 58",
    "sg:postcode":"8200",
    "sg:province":"Schaffhausen",
    "wof:name":"The Body Shop Levy Ag",
    "wof:placetype":"venue"
},
  "geometry": {"coordinates":[9.3763341904,47.4250946045],"type":"Point"}
}