{
  "type": "Feature",
  "properties": {
    "iso:country":"CH",
    "sg:address":"Weinmarkt 11 6004 Luzern. Postfach 4840",
    "sg:city":"Luzern",
    "sg:orig_category":"Grosshandel mit Obst U Gem\u00fcse",
    "sg:phone":"+41 41 410 67 45",
    "sg:postcode":"6002",
    "sg:province":"Luzern",
    "wof:name":"Alpha Fruit-trade Sa",
    "wof:placetype":"venue"
},
  "geometry": {"coordinates":[8.304186821,47.0519752502],"type":"Point"}
}