{
  "type": "Feature",
  "properties": {
    "iso:country":"CH",
    "sg:address":"Rheinparkstrasse 3",
    "sg:city":"Birsfelden",
    "sg:orig_category":"Satzherstellung U Reproduktion",
    "sg:phone":"+41 61 311 16 66",
    "sg:postcode":"4127",
    "sg:province":"Basel-Landschaft",
    "wof:name":"Namalith Ag",
    "wof:placetype":"venue"
},
  "geometry": {"coordinates":[7.622964859,47.5571784973],"type":"Point"}
}