{
  "type": "Feature",
  "properties": {
    "iso:country":"CH",
    "sg:address":"6837",
    "sg:city":"Bruzella",
    "sg:orig_category":"Unclassifiable Establishments",
    "sg:postcode":"6837",
    "sg:province":"Ticino",
    "wof:name":"Comizzoli Prathana",
    "wof:placetype":"venue"
},
  "geometry": {"coordinates":[9.0350847244,45.8812866211],"type":"Point"}
}