{
  "type": "Feature",
  "properties": {
    "iso:country":"CH",
    "sg:address":"Eichgutstrasse 1 8400 Winterthur. Postfach",
    "sg:city":"Winterthur",
    "sg:orig_category":"Gesundheitswesen",
    "sg:phone":"+41 52 214 26 76",
    "sg:postcode":"8400",
    "sg:province":"Z\u00fcrich",
    "wof:name":"Veso Verein F\u00fcr Sozialpsychiatrie Region Winterthur",
    "wof:placetype":"venue"
},
  "geometry": {"coordinates":[8.7225322723,47.5021247864],"type":"Point"}
}