{
  "type": "Feature",
  "properties": {
    "iso:country":"CH",
    "sg:address":"Rue Du Botzet 3",
    "sg:city":"Fribourg",
    "sg:orig_category":"Erwachsenenbildung U Unterricht Sprachschulen",
    "sg:phone":"+41 19108805",
    "sg:postcode":"1700",
    "sg:province":"Fribourg",
    "wof:name":"Ecofon K\u00fcsnacht, Sprachlerncenter, Inh. K\u00fcrsteiner B.",
    "wof:placetype":"venue"
},
  "geometry": {"coordinates":[8.5802087784,47.3160514832],"type":"Point"}
}