{
  "type": "Feature",
  "properties": {
    "addr:full":"Kornhausstrasse 25 St.gallen St. Gallen 9000",
    "addr:housenumber":"25",
    "addr:postcode":"9000",
    "addr:street":"Kornhausstrasse",
    "iso:country":"CH",
    "sg:address":"Kornhausstrasse 25",
    "sg:city":"St.gallen",
    "sg:orig_category":"Detailhandel mit Computern U Software",
    "sg:phone":"+41 71 222 60 05",
    "sg:postcode":"9000",
    "sg:province":"St. Gallen",
    "wof:name":"Pc World St. Gallen Gmbh",
    "wof:placetype":"venue"
},
  "geometry": {"coordinates":[9.372146,47.42205],"type":"Point"}
}