{
  "type": "Feature",
  "properties": {
    "iso:country":"CH",
    "sg:address":"Thunstrasse 11",
    "sg:city":"Konolfingen",
    "sg:orig_category":"Detailhandel mit Brot, Back U S\u00fcsswaren",
    "sg:postcode":"3510",
    "sg:province":"Bern",
    "wof:name":"B\u00e4ckerei-konditorei Kindler B. + Hiltbrunner B.",
    "wof:placetype":"venue"
},
  "geometry": {"coordinates":[7.620721,46.877834],"type":"Point"}
}