{
  "type": "Feature",
  "properties": {
    "iso:country":"CH",
    "sg:address":"Badstrasse 36",
    "sg:city":"Baden",
    "sg:orig_category":"Detailhandel mit Schuhen",
    "sg:phone":"+41 56 210 98 10",
    "sg:postcode":"5400",
    "sg:province":"Aargau",
    "wof:name":"Ochsner Schuhe & Sport Ag",
    "wof:placetype":"venue"
},
  "geometry": {"coordinates":[8.3089370728,47.4755554199],"type":"Point"}
}