{
  "type": "Feature",
  "properties": {
    "iso:country":"CH",
    "sg:address":"Von Rollstrasse 2",
    "sg:city":"Oensingen",
    "sg:orig_category":"Verwaltung von Immobilien",
    "sg:postcode":"4702",
    "sg:province":"Solothurn",
    "wof:name":"Allemann Immobilien-treuhand",
    "wof:placetype":"venue"
},
  "geometry": {"coordinates":[7.7093467712,47.2856864929],"type":"Point"}
}