{
  "type": "Feature",
  "properties": {
    "iso:country":"CH",
    "sg:address":"Weingartenstrasse 14",
    "sg:city":"H\u00f6ri",
    "sg:orig_category":"Fahrschulen, Flugschulen",
    "sg:phone":"+41 18604364",
    "sg:postcode":"8181",
    "sg:province":"Z\u00fcrich",
    "wof:name":"Karl Madei Autofahrschule",
    "wof:placetype":"venue"
},
  "geometry": {"coordinates":[8.4958639145,47.5050621033],"type":"Point"}
}