{
  "type": "Feature",
  "properties": {
    "iso:country":"CH",
    "sg:address":"Dorfstrasse",
    "sg:city":"Windisch",
    "sg:orig_category":"Vorschulen, Kinderg\u00e4rten",
    "sg:phone":"+41 56 441 44 94",
    "sg:postcode":"5210",
    "sg:province":"Aargau",
    "wof:name":"Kindergarten Unterdorf",
    "wof:placetype":"venue"
},
  "geometry": {"coordinates":[8.2293052673,47.4825897217],"type":"Point"}
}