{
  "type": "Feature",
  "properties": {
    "iso:country":"CH",
    "sg:address":"Avenue De La Rosiaz 4",
    "sg:city":"Pully",
    "sg:orig_category":"Sonstige mit der Informatik verbundene T\u00e4tigkeiten",
    "sg:phone":"+41 21 728 15 42",
    "sg:postcode":"1009",
    "sg:province":"Vaud",
    "wof:name":"Agopian Paul",
    "wof:placetype":"venue"
},
  "geometry": {"coordinates":[6.6609921455,46.5195617676],"type":"Point"}
}