{
  "type": "Feature",
  "properties": {
    "iso:country":"CH",
    "sg:address":"Kermely Chemin 5 1206 Gen\u00e8ve. Postfach",
    "sg:city":"Gen\u00e8ve",
    "sg:orig_category":"Interessenvertretungen",
    "sg:postcode":"1206",
    "sg:province":"Gen\u00e8ve",
    "wof:name":"Fondation La Pl\u00e9iade",
    "wof:placetype":"venue"
},
  "geometry": {"coordinates":[-82.42250061039999,36.2902984619],"type":"Point"}
}