{
  "type": "Feature",
  "properties": {
    "iso:country":"CH",
    "sg:address":"Chemin Du Fosseau 8",
    "sg:city":"Collonge-bellerive",
    "sg:orig_category":"Non-Classified Establishments",
    "sg:postcode":"1245",
    "sg:province":"Gen\u00e8ve",
    "wof:name":"Tecnacron Sa",
    "wof:placetype":"venue"
},
  "geometry": {"coordinates":[6.1975622177,46.2536010742],"type":"Point"}
}