{
  "type": "Feature",
  "properties": {
    "addr:full":"H\u00f6heweg 35 Interlaken Bern 3800",
    "addr:housenumber":"35",
    "addr:postcode":"3800",
    "addr:street":"Hoeheweg",
    "iso:country":"CH",
    "sg:address":"H\u00f6heweg 35",
    "sg:city":"Interlaken",
    "sg:classifiers":[
        {
            "category":"Banks & Credit Unions",
            "subcategory":"Bank",
            "type":"Services"
        }
    ],
    "sg:phone":"+41 33 826 61 31",
    "sg:postcode":"3800",
    "sg:province":"Bern",
    "wof:name":"Berner Kantonalbank",
    "wof:placetype":"venue"
},
  "geometry": {"coordinates":[7.856247,46.685795],"type":"Point"}
}