{
  "type": "Feature",
  "properties": {
    "addr:full":"Bergstrasse 9 Meggen Luzern 6045",
    "addr:housenumber":"9",
    "addr:postcode":"6045",
    "addr:street":"Bergstrasse",
    "iso:country":"CH",
    "sg:address":"Bergstrasse 9",
    "sg:city":"Meggen",
    "sg:orig_category":"Dachdeckerei",
    "sg:phone":"+41 41 377 15 69",
    "sg:postcode":"6045",
    "sg:province":"Luzern",
    "wof:name":"Adolf Huwiler Dachdeckergesch\u00e4ft",
    "wof:placetype":"venue"
},
  "geometry": {"coordinates":[8.385183,47.061207],"type":"Point"}
}