{
  "type": "Feature",
  "properties": {
    "addr:full":"Champ Ruppan Puidoux Vaud 1070",
    "addr:postcode":"1070",
    "addr:street":"Champ Ruppan",
    "iso:country":"CH",
    "sg:address":"Champ Ruppan",
    "sg:city":"Puidoux",
    "sg:orig_category":"Allgemeiner Hoch U Tiefbau",
    "sg:postcode":"1070",
    "sg:province":"Vaud",
    "wof:name":"Minages Et Travaux Souterrains Sa",
    "wof:placetype":"venue"
},
  "geometry": {"coordinates":[6.76967,46.493355],"type":"Point"}
}