{
  "type": "Feature",
  "properties": {
    "iso:country":"CH",
    "sg:address":"Hofmattweg 15 6045 Meggen. Postfach",
    "sg:city":"Meggen",
    "sg:orig_category":"Chalet- and Holzbau Zimmerei, Dachdeckerei, Bauspenglerei U Abdichtung",
    "sg:phone":"+41 41 378 08 88",
    "sg:postcode":"6045",
    "sg:province":"Luzern",
    "wof:name":"L\u00f6tscher Bauplanung Gmbh Bauten, Bes. Holzbauarbeiten; Planung, Erstellung Usw",
    "wof:placetype":"venue"
},
  "geometry": {"coordinates":[8.371145,47.04607],"type":"Point"}
}