{
  "type": "Feature",
  "properties": {
    "iso:country":"CH",
    "sg:address":"Buchlernstrasse 30",
    "sg:city":"Z\u00fcrich",
    "sg:orig_category":"Vorschulen, Kinderg\u00e4rten",
    "sg:phone":"+41 14312678",
    "sg:postcode":"8048",
    "sg:province":"Z\u00fcrich",
    "wof:name":"St\u00e4dtischer Kindergarten Schulhaus Buchlern",
    "wof:placetype":"venue"
},
  "geometry": {"coordinates":[8.477684021,47.3826713562],"type":"Point"}
}