{
  "type": "Feature",
  "properties": {
    "iso:country":"CH",
    "sg:address":"P\u00fcnt 11",
    "sg:city":"Bottighofen",
    "sg:orig_category":"Sportvereine Wassersport Segeln",
    "sg:phone":"+41 79 670 97 51",
    "sg:postcode":"8598",
    "sg:province":"Thurgau",
    "wof:name":"Seglervereinig.bottighofen Svb",
    "wof:placetype":"venue"
},
  "geometry": {"coordinates":[9.2081518173,47.6380882263],"type":"Point"}
}