{
  "type": "Feature",
  "properties": {
    "iso:country":"CH",
    "sg:address":"Pavillons Rue Des 14 1205 Gen\u00e8ve. Postfach",
    "sg:city":"Gen\u00e8ve",
    "sg:orig_category":"Sanit\u00e4r, Heizungs U L\u00fcftungsinstallation",
    "sg:phone":"+41 22 328 65 17",
    "sg:postcode":"1201",
    "sg:province":"Gen\u00e8ve",
    "wof:name":"Entreprise Costa Sa",
    "wof:placetype":"venue"
},
  "geometry": {"coordinates":[6.1399550438,46.1961097717],"type":"Point"}
}