{
  "type": "Feature",
  "properties": {
    "iso:country":"CH",
    "sg:address":"Eichwisrain 14",
    "sg:city":"Hombrechtikon",
    "sg:orig_category":"Wirtschaftspr\u00fcfung, Steuerberatung U Treuhand",
    "sg:phone":"+41 55 244 19 30",
    "sg:postcode":"8634",
    "sg:province":"Z\u00fcrich",
    "wof:name":"Tsh Schmid Therese",
    "wof:placetype":"venue"
},
  "geometry": {"coordinates":[8.7826662064,47.2503128052],"type":"Point"}
}