{
  "type": "Feature",
  "properties": {
    "iso:country":"CH",
    "sg:address":"Wartenbergstrasse 75",
    "sg:city":"Pratteln",
    "sg:orig_category":"Institutionen f\u00fcr Behinderte Tagesheime f\u00fcr Behinderte, gesch\u00fctzte Werkst\u00e4tten",
    "sg:phone":"+41 61 821 08 61",
    "sg:postcode":"4133",
    "sg:province":"Basel-Landschaft",
    "wof:name":"Wohnheim K\u00e4steli F\u00fcr Behinderte",
    "wof:placetype":"venue"
},
  "geometry": {"coordinates":[7.679309845,47.5196685791],"type":"Point"}
}