{
  "type": "Feature",
  "properties": {
    "iso:country":"CH",
    "sg:address":"Hauptgasse 65",
    "sg:city":"Solothurn",
    "sg:orig_category":"Interessenvertretungen",
    "sg:postcode":"4500",
    "sg:province":"Solothurn",
    "wof:name":"Stiftung Pro Ruppigonia",
    "wof:placetype":"venue"
},
  "geometry": {"coordinates":[7.5382080078,47.2080612183],"type":"Point"}
}