{
  "type": "Feature",
  "properties": {
    "iso:country":"CH",
    "sg:address":"Route De Lausanne 128 1052 Mont-sur-lausanne. Postfach",
    "sg:city":"Mont-sur-lausanne",
    "sg:orig_category":"Public-Relations-Agenturen",
    "sg:phone":"+41 52 740 25 50",
    "sg:postcode":"1052",
    "sg:province":"Vaud",
    "wof:name":"Felix Braun Bsp Braun Promotion",
    "wof:placetype":"venue"
},
  "geometry": {"coordinates":[8.8309755325,47.6282310486],"type":"Point"}
}