{
  "type": "Feature",
  "properties": {
    "iso:country":"CH",
    "sg:address":"Fiechtlerweg 2",
    "sg:city":"G\u00fcnsberg",
    "sg:classifiers":[
        {
            "category":"Manufacturing",
            "subcategory":"Tools & Machinery",
            "type":"Manufacturing & Wholesale Goods"
        }
    ],
    "sg:phone":"+41 32 637 14 46",
    "sg:postcode":"4524",
    "sg:province":"Solothurn",
    "sg:tags":[
        "part",
        "turned",
        "cnc"
    ],
    "wof:name":"Henzi Tech Gmbh",
    "wof:placetype":"venue"
},
  "geometry": {"coordinates":[7.579102,47.259151],"type":"Point"}
}