{
  "type": "Feature",
  "properties": {
    "iso:country":"CH",
    "sg:address":"Aarauerstrasse 85 4600 Olten. Postfach",
    "sg:city":"Olten",
    "sg:orig_category":"Reiseb\u00fcros U Reiseveranstalter",
    "sg:phone":"+41 62 296 30 18",
    "sg:postcode":"4601",
    "sg:province":"Solothurn",
    "wof:name":"Reiseb\u00fcro Simsek B\u00fcro",
    "wof:placetype":"venue"
},
  "geometry": {"coordinates":[7.9126372337,47.3490066528],"type":"Point"}
}