{
  "type": "Feature",
  "properties": {
    "iso:country":"CH",
    "sg:address":"Allmeindstrasse 3 8750 Glarus. Postfach 313",
    "sg:city":"Glarus",
    "sg:orig_category":"Detailhandel mit B\u00fcchern",
    "sg:phone":"+41 55 640 56 15",
    "sg:postcode":"8750",
    "sg:province":"Glarus",
    "wof:name":"Fridolin B\u00fccherecke Freie Evang.gemeinde",
    "wof:placetype":"venue"
},
  "geometry": {"coordinates":[9.07009,47.038551],"type":"Point"}
}