{
  "type": "Feature",
  "properties": {
    "iso:country":"CH",
    "sg:address":"Kasernenstrasse 66a",
    "sg:city":"Liestal",
    "sg:orig_category":"Herstellung von Konstruktionsteilen, Fertigbauteilen U Ausbauelementen aus Holz",
    "sg:postcode":"4410",
    "sg:province":"Basel-Landschaft",
    "wof:name":"Schreinerei Furler Gmbh",
    "wof:placetype":"venue"
},
  "geometry": {"coordinates":[7.7429208755,47.4785461426],"type":"Point"}
}