{
  "type": "Feature",
  "properties": {
    "iso:country":"CH",
    "sg:address":"Hochstrasse 35 8000 Z\u00fcrich. Postfach",
    "sg:city":"Z\u00fcrich",
    "sg:orig_category":"Interessenvertretungen",
    "sg:postcode":"8044",
    "sg:province":"Z\u00fcrich",
    "wof:name":"Stiftung Lambarene-spital",
    "wof:placetype":"venue"
},
  "geometry": {"coordinates":[8.5527582169,47.3801116943],"type":"Point"}
}