{
  "type": "Feature",
  "properties": {
    "iso:country":"CH",
    "sg:address":"Mattenbachstrasse 4-6",
    "sg:city":"Winterthur",
    "sg:orig_category":"Bauschreinerei Innenausbau",
    "sg:phone":"+41 52 232 23 12",
    "sg:postcode":"8400",
    "sg:province":"Z\u00fcrich",
    "wof:name":"B\u00f6ckli Karl Ag",
    "wof:placetype":"venue"
},
  "geometry": {"coordinates":[8.734882,47.494453],"type":"Point"}
}