{
  "type": "Feature",
  "properties": {
    "iso:country":"CH",
    "sg:address":"Allmeindstrasse 10",
    "sg:city":"Schmerikon",
    "sg:orig_category":"Grosshandel mit B\u00fcromaschinen Grosshandel mit Datenverarbeitungsger\u00e4ten",
    "sg:phone":"+41 55 282 59 33",
    "sg:postcode":"8716",
    "sg:province":"St. Gallen",
    "wof:name":"Infolog Sa Conseil En Informatique",
    "wof:placetype":"venue"
},
  "geometry": {"coordinates":[8.9475774765,47.2252426147],"type":"Point"}
}