{
  "type": "Feature",
  "properties": {
    "iso:country":"CH",
    "sg:address":"6776 Piotta. Postfach",
    "sg:city":"Piotta",
    "sg:orig_category":"RESTAURANTS: TEA-ROOMS",
    "sg:postcode":"6776",
    "sg:province":"Ticino",
    "wof:name":"Ristorante Gobbi Di Gobbi Loris",
    "wof:placetype":"venue"
},
  "geometry": {"coordinates":[8.6772546768,46.5128364563],"type":"Point"}
}