{
  "type": "Feature",
  "properties": {
    "iso:country":"CH",
    "sg:address":"Piazza Grande 7 6512 Giubiasco. Postfach",
    "sg:city":"Giubiasco",
    "sg:orig_category":"Verwaltung von Immobilien",
    "sg:postcode":"6512",
    "sg:province":"Ticino",
    "wof:name":"Bel Ristoro Sagl",
    "wof:placetype":"venue"
},
  "geometry": {"coordinates":[9.0111083984,46.1710510254],"type":"Point"}
}