{
  "type": "Feature",
  "properties": {
    "iso:country":"CH",
    "sg:address":"Hofstrasse 6 9642 Ebnat. Postfach",
    "sg:city":"Ebnat-kappel",
    "sg:orig_category":"Druck ohne Zeitungsdruck",
    "sg:phone":"+41 71 993 31 11",
    "sg:postcode":"9642",
    "sg:province":"St. Gallen",
    "wof:name":"Druckerei Fuchs Ag, Ebnat-kappel",
    "wof:placetype":"venue"
},
  "geometry": {"coordinates":[9.1273136139,47.2603034973],"type":"Point"}
}