{
  "type": "Feature",
  "properties": {
    "iso:country":"CH",
    "sg:address":"Limmatstrasse 8 8957 Spreitenbach. Postfach 343",
    "sg:city":"Spreitenbach",
    "sg:orig_category":"Elektro- and elektronische Maschinen Grosshandel Grosshandel mit elektrischen Haushaltsger\u00e4ten, Radi",
    "sg:phone":"+41 56 401 47 41",
    "sg:postcode":"8957",
    "sg:province":"Aargau",
    "wof:name":"A. Steffen Ag Elektro-& Industriebedarf",
    "wof:placetype":"venue"
},
  "geometry": {"coordinates":[8.373796463,47.4285545349],"type":"Point"}
}