{
  "type": "Feature",
  "properties": {
    "iso:country":"CH",
    "sg:address":"Quellenweg 9",
    "sg:city":"Sarmenstorf",
    "sg:orig_category":"Unclassifiable Establishments",
    "sg:postcode":"5614",
    "sg:province":"Aargau",
    "wof:name":"Wibe Revisions Gmbh",
    "wof:placetype":"venue"
},
  "geometry": {"coordinates":[8.2529211044,47.314868927],"type":"Point"}
}