{
  "type": "Feature",
  "properties": {
    "iso:country":"CH",
    "sg:address":"Kirchenstrasse 46",
    "sg:city":"Oberiberg",
    "sg:classifiers":[
        {
            "category":"Restaurant",
            "type":"Food & Drink"
        }
    ],
    "sg:phone":"+41 55 414 11 14",
    "sg:postcode":"8843",
    "sg:province":"Schwyz",
    "wof:name":"Restaurant Hirschen",
    "wof:placetype":"venue"
},
  "geometry": {"coordinates":[8.7867126465,47.0414237976],"type":"Point"}
}