{
  "type": "Feature",
  "properties": {
    "iso:country":"CH",
    "sg:address":"M\u00fchlemattstrasse 56",
    "sg:city":"Aarau",
    "sg:orig_category":"Interessenvertretungen",
    "sg:postcode":"5000",
    "sg:province":"Aargau",
    "wof:name":"Schul- & Bildungsstiftung Des Kv Aarau",
    "wof:placetype":"venue"
},
  "geometry": {"coordinates":[8.0482692719,47.395275116],"type":"Point"}
}