{
  "type": "Feature",
  "properties": {
    "iso:country":"CH",
    "sg:address":"L\u00f6wenstrasse 16 8280 Kreuzlingen. Postfach 2243",
    "sg:city":"Kreuzlingen",
    "sg:orig_category":"Wirtschaftspr\u00fcfung, Steuerberatung U Treuhand",
    "sg:phone":"+41 41 874 70 70",
    "sg:postcode":"8280",
    "sg:province":"Thurgau",
    "wof:name":"Bdo Visura",
    "wof:placetype":"venue"
},
  "geometry": {"coordinates":[8.6445388794,46.8819274902],"type":"Point"}
}