{
  "type": "Feature",
  "properties": {
    "iso:country":"CH",
    "sg:address":"St. Gallerstrasse 85",
    "sg:city":"Flawil",
    "sg:orig_category":"Architekturb\u00fcros",
    "sg:phone":"+41 71 393 13 82",
    "sg:postcode":"9230",
    "sg:province":"St. Gallen",
    "wof:name":"Alex K\u00fcnzle Architekturb\u00fcro",
    "wof:placetype":"venue"
},
  "geometry": {"coordinates":[9.193027,47.412579],"type":"Point"}
}