{
  "type": "Feature",
  "properties": {
    "iso:country":"CH",
    "sg:address":"Im Weingarten 6",
    "sg:city":"Oberuzwil",
    "sg:orig_category":"Politische Parteien FDP",
    "sg:phone":"+41 71 951 43 15",
    "sg:postcode":"9242",
    "sg:province":"St. Gallen",
    "wof:name":"Fdp Ortspartei Oberuzwil",
    "wof:placetype":"venue"
},
  "geometry": {"coordinates":[9.1234798431,47.432975769],"type":"Point"}
}