{
  "type": "Feature",
  "properties": {
    "iso:country":"CH",
    "sg:address":"Zwieseln",
    "sg:city":"B\u00fctschwil",
    "sg:orig_category":"Verwertung von Milch",
    "sg:postcode":"9606",
    "sg:province":"St. Gallen",
    "wof:name":"K\u00e4serei Thoma",
    "wof:placetype":"venue"
},
  "geometry": {"coordinates":[9.0499429703,47.3435745239],"type":"Point"}
}