{
  "type": "Feature",
  "properties": {
    "iso:country":"CH",
    "sg:address":"Avenue J.-d.-maillard 11",
    "sg:city":"Meyrin",
    "sg:orig_category":"Arztpraxen",
    "sg:phone":"+41 22 782 97 78",
    "sg:postcode":"1217",
    "sg:province":"Gen\u00e8ve",
    "wof:name":"Dr M\u00e9d. Marc Zimmermann M\u00e9decin Sp\u00e9cialiste Fmh",
    "wof:placetype":"venue"
},
  "geometry": {"coordinates":[6.068964,46.228619],"type":"Point"}
}