{
  "type": "Feature",
  "properties": {
    "addr:full":"Loorenstrasse 15 Niederrohrdorf Aargau 5443",
    "addr:housenumber":"15",
    "addr:postcode":"5443",
    "addr:street":"Loorenstrasse",
    "iso:country":"CH",
    "sg:address":"Loorenstrasse 15",
    "sg:city":"Niederrohrdorf",
    "sg:orig_category":"Blumen U Zierpflanzenbau Detailhandel mit Blumen U Pflanzen",
    "sg:phone":"+41 56 496 13 21",
    "sg:postcode":"5443",
    "sg:province":"Aargau",
    "wof:name":"Werner Fl\u00fcckiger",
    "wof:placetype":"venue"
},
  "geometry": {"coordinates":[8.30242,47.427635],"type":"Point"}
}