{
  "type": "Feature",
  "properties": {
    "iso:country":"CH",
    "sg:address":"De-luserna Avenue 9 1203 Gen\u00e8ve. Postfach",
    "sg:city":"Neuenburg",
    "sg:orig_category":"Grosshandel mit sonstigen Gebrauchs U Verbrauchsg\u00fctern",
    "sg:postcode":"2000",
    "sg:province":"Neuch\u00e2tel",
    "wof:name":"Diaminter Sa Diamants, Pierres Pr\u00e9cieuses Etc.; Commerce",
    "wof:placetype":"venue"
},
  "geometry": {"coordinates":[6.1267619133,46.2125663757],"type":"Point"}
}