{
  "type": "Feature",
  "properties": {
    "iso:country":"CH",
    "sg:address":"Rue De L'industrie 43 1950 Sion Case Postale 881",
    "sg:city":"Sion",
    "sg:orig_category":"Elektrizit\u00e4tsversorgung Wasserversorgung",
    "sg:phone":"+41 24 475 76 76",
    "sg:postcode":"1951",
    "sg:province":"Valais",
    "wof:name":"Services Industriels Monthey Electricit\u00e9-eau-epuration",
    "wof:placetype":"venue"
},
  "geometry": {"coordinates":[6.9500951767,46.2491531372],"type":"Point"}
}