{
  "type": "Feature",
  "properties": {
    "iso:country":"CH",
    "sg:address":"Maiweg 2 5073 Gipf-oberfrick. Postfach 43",
    "sg:city":"Gipf-oberfrick",
    "sg:orig_category":"Sanit\u00e4r, Heizungs U L\u00fcftungsinstallation",
    "sg:phone":"+41 62 871 19 17",
    "sg:postcode":"5073",
    "sg:province":"Aargau",
    "wof:name":"Eduard M\u00f6sch Sanit\u00e4tsmaterialien 5073 Gipf-oberfrick",
    "wof:placetype":"venue"
},
  "geometry": {"coordinates":[8.0042877197,47.4971122742],"type":"Point"}
}