{
  "type": "Feature",
  "properties": {
    "iso:country":"CH",
    "sg:address":"Place Bel-air 8",
    "sg:city":"Nyon",
    "sg:classifiers":[
        {
            "category":"Banks & Credit Unions",
            "subcategory":"Bank",
            "type":"Services"
        }
    ],
    "sg:phone":"+41 21 886 22 11",
    "sg:postcode":"1260",
    "sg:province":"Vaud",
    "wof:name":"Swiss Bank Corp.",
    "wof:placetype":"venue"
},
  "geometry": {"coordinates":[6.63436,46.640862],"type":"Point"}
}