{
  "type": "Feature",
  "properties": {
    "iso:country":"CH",
    "sg:address":"Via Giacomo Luvini 4",
    "sg:city":"Lugano",
    "sg:orig_category":"Vermietung U Verpachtung von eigenen Immobilien",
    "sg:postcode":"6900",
    "sg:province":"Ticino",
    "wof:name":"Franscinia Sa",
    "wof:placetype":"venue"
},
  "geometry": {"coordinates":[8.9511098862,46.0047035217],"type":"Point"}
}