{
  "type": "Feature",
  "properties": {
    "iso:country":"CH",
    "sg:address":"Pont-sapin 10e",
    "sg:city":"Pontenet",
    "sg:orig_category":"Tierheime",
    "sg:phone":"+41 32 492 12 65",
    "sg:postcode":"2733",
    "sg:province":"Bern",
    "wof:name":"Hans Berger Pension Pour Animaux",
    "wof:placetype":"venue"
},
  "geometry": {"coordinates":[7.2546601295,47.2384185791],"type":"Point"}
}