{
  "type": "Feature",
  "properties": {
    "iso:country":"CH",
    "sg:address":"Place Du Ch\u00e2teau 1",
    "sg:city":"Ballaigues",
    "sg:classifiers":[
        {
            "category":"Travel",
            "subcategory":"Hotels & Motels",
            "type":"Entertainment"
        }
    ],
    "sg:phone":"+41 21 843 26 09",
    "sg:postcode":"1338",
    "sg:province":"Vaud",
    "sg:tags":[
        "hotels",
        "mit",
        "restaurant"
    ],
    "wof:name":"H\u00f4tel De La Croix D'or",
    "wof:placetype":"venue"
},
  "geometry": {"coordinates":[6.4159622192,46.7293624878],"type":"Point"}
}