{
  "type": "Feature",
  "properties": {
    "iso:country":"CH",
    "sg:address":"Seefeldstrasse 19",
    "sg:city":"Z\u00fcrich",
    "sg:orig_category":"Finanzierungsinstitutionen",
    "sg:postcode":"8008",
    "sg:province":"Z\u00fcrich",
    "wof:name":"Hyuto Holding Ag",
    "wof:placetype":"venue"
},
  "geometry": {"coordinates":[8.5490865707,47.3641319275],"type":"Point"}
}