{
  "type": "Feature",
  "properties": {
    "iso:country":"CH",
    "sg:address":"Rue Du Ch\u00e2teau 1",
    "sg:city":"Lutry",
    "sg:classifiers":[
        {
            "category":"Education",
            "subcategory":"Library",
            "type":"Public Place"
        }
    ],
    "sg:phone":"+41 21 791 10 15",
    "sg:postcode":"1095",
    "sg:province":"Vaud",
    "sg:tags":[
        "u",
        "bibliotheken",
        "archive"
    ],
    "wof:name":"Biblioth\u00e8que De Lutry",
    "wof:placetype":"venue"
},
  "geometry": {"coordinates":[6.686597,46.502926],"type":"Point"}
}