{
  "type": "Feature",
  "properties": {
    "iso:country":"CH",
    "sg:address":"Seuzachstrasse 15",
    "sg:city":"Neftenbach",
    "sg:orig_category":"Hobel U Holzimpr\u00e4gnierwerke",
    "sg:phone":"+41 52 315 40 10",
    "sg:postcode":"8413",
    "sg:province":"Z\u00fcrich",
    "wof:name":"Heinz Hummel Drechslerei",
    "wof:placetype":"venue"
},
  "geometry": {"coordinates":[8.6697473526,47.5290603638],"type":"Point"}
}