{
  "type": "Feature",
  "properties": {
    "iso:country":"CH",
    "sg:address":"Tricouni Chemin 6 1255 Veyrier. Postfach",
    "sg:city":"Vessy",
    "sg:orig_category":"Herstellung von sonstigen Maschinen f\u00fcr unspezifische Verwendung",
    "sg:postcode":"1234",
    "sg:province":"Gen\u00e8ve",
    "wof:name":"Prevent Feu Entretien Et Maintenance S\u00e0rl",
    "wof:placetype":"venue"
},
  "geometry": {"coordinates":[6.181219101,46.1629219055],"type":"Point"}
}