{
  "type": "Feature",
  "properties": {
    "iso:country":"CH",
    "sg:address":"Grossmatte 28 6014 Littau. Postfach",
    "sg:city":"Littau",
    "sg:orig_category":"Grosshandel mit sonstigen Gebrauchs U Verbrauchsg\u00fctern Herstellung von sonstigen Erzeugnissen",
    "sg:phone":"+41 52 741 11 21",
    "sg:postcode":"6014",
    "sg:province":"Luzern",
    "wof:name":"Sieco Messger\u00e4te Ag",
    "wof:placetype":"venue"
},
  "geometry": {"coordinates":[8.8552799225,47.6541366577],"type":"Point"}
}