{
  "type": "Feature",
  "properties": {
    "iso:country":"CH",
    "sg:address":"Baarerstrasse 25",
    "sg:city":"Zug",
    "sg:orig_category":"Sonstige mit Sport verbundene T\u00e4tigkeiten",
    "sg:phone":"+41 42233577",
    "sg:postcode":"6300",
    "sg:province":"Zug",
    "wof:name":"Just 4 Fun, Flugschule M\u00e4rchy",
    "wof:placetype":"venue"
},
  "geometry": {"coordinates":[8.5162143707,47.1727752686],"type":"Point"}
}