{
  "type": "Feature",
  "properties": {
    "iso:country":"CH",
    "sg:address":"Dorfstrasse 114",
    "sg:city":"Obfelden",
    "sg:orig_category":"Fachdetailhandel in Verkaufsr\u00e4umen",
    "sg:phone":"+41 17604151",
    "sg:postcode":"8912",
    "sg:province":"Z\u00fcrich",
    "wof:name":"Reussflor Huber Nadja",
    "wof:placetype":"venue"
},
  "geometry": {"coordinates":[8.4101276398,47.2631416321],"type":"Point"}
}