{
  "type": "Feature",
  "properties": {
    "iso:country":"CH",
    "sg:address":"H\u00f6fli",
    "sg:city":"Engi",
    "sg:orig_category":"Forstwirtschaft ohne Dienstleistungen in der Forstwirtschaft",
    "sg:phone":"+41 55 642 12 14",
    "sg:postcode":"8765",
    "sg:province":"Glarus",
    "wof:name":"Altmann Heinz Ag, Forst Und Montage-unternehmung",
    "wof:placetype":"venue"
},
  "geometry": {"coordinates":[9.1329631805,46.9917831421],"type":"Point"}
}