{
  "type": "Feature",
  "properties": {
    "iso:country":"CH",
    "sg:address":"Route De Cho\u00f3ex",
    "sg:city":"Monthey",
    "sg:orig_category":"Fahrschulen, Flugschulen",
    "sg:postcode":"1870",
    "sg:province":"Valais",
    "wof:name":"Besse Patrice",
    "wof:placetype":"venue"
},
  "geometry": {"coordinates":[6.9513959885,46.2470474243],"type":"Point"}
}