{
  "type": "Feature",
  "properties": {
    "iso:country":"CH",
    "sg:address":"Chemin Des Corjons 22 1052 Mont-sur-lausanne Case Postale 136",
    "sg:city":"Mont-sur-lausanne",
    "sg:orig_category":"Sanit\u00e4r, Heizungs U L\u00fcftungsinstallation Sanit\u00e4rinstallation",
    "sg:phone":"+41 21 620 07 70",
    "sg:postcode":"1052",
    "sg:province":"Vaud",
    "wof:name":"Fleury M. Et Cie Sa",
    "wof:placetype":"venue"
},
  "geometry": {"coordinates":[6.6316738129,46.5553741455],"type":"Point"}
}