{
  "type": "Feature",
  "properties": {
    "iso:country":"CH",
    "sg:address":"Poststrasse 6",
    "sg:city":"Uster",
    "sg:orig_category":"Detailhandel mit Textilien",
    "sg:phone":"+41 19302325",
    "sg:postcode":"8610",
    "sg:province":"Z\u00fcrich",
    "wof:name":"Stoff Fortuna R.& U.reiser",
    "wof:placetype":"venue"
},
  "geometry": {"coordinates":[8.7993927002,47.3269195557],"type":"Point"}
}