{
  "type": "Feature",
  "properties": {
    "iso:country":"CH",
    "sg:address":"M\u00fcnstergasse 38",
    "sg:city":"Bern",
    "sg:orig_category":"Unclassifiable Establishments",
    "sg:postcode":"3011",
    "sg:province":"Bern",
    "wof:name":"Hans-ulrich Meyer Architekt Bsa Sia",
    "wof:placetype":"venue"
},
  "geometry": {"coordinates":[7.4502530098,46.9476013184],"type":"Point"}
}