{
  "type": "Feature",
  "properties": {
    "iso:country":"CH",
    "sg:address":"Schorenstrasse 75",
    "sg:city":"St.gallen",
    "sg:orig_category":"Sonstige mit Sport verbundene T\u00e4tigkeiten",
    "sg:postcode":"9000",
    "sg:province":"St. Gallen",
    "wof:name":"Kiew-club International (schweiz)",
    "wof:placetype":"venue"
},
  "geometry": {"coordinates":[9.3643789291,47.4278068542],"type":"Point"}
}