{
  "type": "Feature",
  "properties": {
    "iso:country":"CH",
    "sg:address":"Dorfstrasse 62",
    "sg:city":"Rain",
    "sg:orig_category":"Detailhandel mit Beleuchtungs U Haushaltsgegenst\u00e4nden Detailhandel mit elektrischen Haushalts-,Radio",
    "sg:phone":"+41 41 459 00 50",
    "sg:postcode":"6026",
    "sg:province":"Luzern",
    "wof:name":"Hb Benno Heggli Haushaltger\u00e4te",
    "wof:placetype":"venue"
},
  "geometry": {"coordinates":[8.246045,47.126644],"type":"Point"}
}