{
  "type": "Feature",
  "properties": {
    "iso:country":"CH",
    "sg:address":"Freilagerstrasse 40 8047 Z\u00fcrich. Postfach",
    "sg:city":"Z\u00fcrich",
    "sg:orig_category":"Pensionskassen",
    "sg:phone":"+41 14955826",
    "sg:postcode":"8047",
    "sg:province":"Z\u00fcrich",
    "wof:name":"Pensionskasse Der Siemens Gesellschaften In Der Schweiz",
    "wof:placetype":"venue"
},
  "geometry": {"coordinates":[8.4911022186,47.3794212341],"type":"Point"}
}