{
  "type": "Feature",
  "properties": {
    "iso:country":"CH",
    "sg:address":"Gellertstrasse 5 4052 Basel. Postfach",
    "sg:city":"Basel",
    "sg:orig_category":"Wirtschaftspr\u00fcfung, Steuerberatung U Treuhand",
    "sg:postcode":"4051",
    "sg:province":"Basel-Stadt",
    "wof:name":"Treuverbund Ag Treuhand, Revisionsgesch\u00e4fte Usw",
    "wof:placetype":"venue"
},
  "geometry": {"coordinates":[7.60668993,47.5524864197],"type":"Point"}
}