{
  "type": "Feature",
  "properties": {
    "iso:country":"CH",
    "sg:address":"1112",
    "sg:city":"Echichens",
    "sg:orig_category":"Mechanik Mechanische Werkst\u00e4tten",
    "sg:phone":"+41 21 801 26 11",
    "sg:postcode":"1112",
    "sg:province":"Vaud",
    "wof:name":"Antoniazza F. & Cie.",
    "wof:placetype":"venue"
},
  "geometry": {"coordinates":[6.4942998886,46.5308494568],"type":"Point"}
}