{
  "type": "Feature",
  "properties": {
    "iso:country":"CH",
    "sg:address":"Rue De La Fontaine 4",
    "sg:city":"Sierre",
    "sg:orig_category":"Unclassifiable Establishments",
    "sg:postcode":"3960",
    "sg:province":"Valais",
    "wof:name":"Jean Quirighetti Garage De La Fontaine",
    "wof:placetype":"venue"
},
  "geometry": {"coordinates":[7.5226788521,46.2889823914],"type":"Point"}
}