{
  "type": "Feature",
  "properties": {
    "iso:country":"CH",
    "sg:address":"Bahnhofstrasse 28",
    "sg:city":"Effretikon",
    "sg:orig_category":"Hochschulen U h\u00f6here Ausbildung Informatikschulen",
    "sg:phone":"+41 56 631 63 01",
    "sg:postcode":"8307",
    "sg:province":"Z\u00fcrich",
    "wof:name":"Computerschule West Ag",
    "wof:placetype":"venue"
},
  "geometry": {"coordinates":[8.3348617554,47.3456077576],"type":"Point"}
}