{
  "type": "Feature",
  "properties": {
    "iso:country":"CH",
    "sg:address":"Fabrikstrasse 5",
    "sg:city":"Affeltrangen",
    "sg:orig_category":"Sonstiger Grosshandel",
    "sg:postcode":"9556",
    "sg:province":"Thurgau",
    "wof:name":"Red-scorpion Pf\u00c4ndler",
    "wof:placetype":"venue"
},
  "geometry": {"coordinates":[9.0327119827,47.5279960632],"type":"Point"}
}