{
  "type": "Feature",
  "properties": {
    "iso:country":"CH",
    "sg:address":"Auer Strasse 6a",
    "sg:city":"Heerbrugg",
    "sg:orig_category":"Hochschulen U h\u00f6here Ausbildung Primarschulen",
    "sg:phone":"+41 16326038",
    "sg:postcode":"9435",
    "sg:province":"St. Gallen",
    "wof:name":"Delta Schule + Bildungs Ag",
    "wof:placetype":"venue"
},
  "geometry": {"coordinates":[8.5849618912,47.3126449585],"type":"Point"}
}