{
  "type": "Feature",
  "properties": {
    "iso:country":"CH",
    "sg:address":"Neudorfstrasse 32",
    "sg:city":"W\u00e4denswil",
    "sg:orig_category":"Sportvereine Ballsport Squash",
    "sg:phone":"+41 17801012",
    "sg:postcode":"8820",
    "sg:province":"Z\u00fcrich",
    "wof:name":"Squash Club Zimmerberg",
    "wof:placetype":"venue"
},
  "geometry": {"coordinates":[8.6630411148,47.2339515686],"type":"Point"}
}