{
  "type": "Feature",
  "properties": {
    "iso:country":"CH",
    "sg:address":"Kehr 5",
    "sg:city":"Gais",
    "sg:orig_category":"Berufliche Weiterbildung, Erwachsenenbildung Softwareentwicklung U beratung",
    "sg:postcode":"9056",
    "sg:province":"Appenzell Ausserrhoden",
    "wof:name":"Karl G\u00f6ltenbolth Gis Informatik Service",
    "wof:placetype":"venue"
},
  "geometry": {"coordinates":[9.457251,47.362804],"type":"Point"}
}