{
  "type": "Feature",
  "properties": {
    "iso:country":"CH",
    "sg:address":"Bahnhofstrasse 71 8001 Z\u00fcrich. Postfach",
    "sg:city":"Z\u00fcrich",
    "sg:orig_category":"Sonstiger Grosshandel",
    "sg:phone":"+41 17842216",
    "sg:postcode":"8001",
    "sg:province":"Z\u00fcrich",
    "wof:name":"Xenya-gmbh",
    "wof:placetype":"venue"
},
  "geometry": {"coordinates":[8.7327022552,47.1987571716],"type":"Point"}
}