{
  "type": "Feature",
  "properties": {
    "iso:country":"CH",
    "sg:address":"Industriestrasse 14 6300 Zug. Postfach 4663",
    "sg:city":"Zug",
    "sg:classifiers":[
        {
            "category":"Travel",
            "subcategory":"Hotels & Motels",
            "type":"Entertainment"
        }
    ],
    "sg:phone":"+41 41 727 48 48",
    "sg:postcode":"6304",
    "sg:province":"Zug",
    "sg:tags":[
        "hotels",
        "mit",
        "restaurant"
    ],
    "wof:name":"Parkhotel Zug Ag",
    "wof:placetype":"venue"
},
  "geometry": {"coordinates":[8.5189199448,47.1724128723],"type":"Point"}
}