{
  "type": "Feature",
  "properties": {
    "iso:country":"CH",
    "sg:address":"Grand-rue 13",
    "sg:city":"St-maurice",
    "sg:orig_category":"Detailhandel mit Damenbekleidung Detailhandel mit Herrenbekleidung",
    "sg:phone":"+41 24 485 14 17",
    "sg:postcode":"1890",
    "sg:province":"Valais",
    "wof:name":"Aida Travaglini Boutique 2000 Confection",
    "wof:placetype":"venue"
},
  "geometry": {"coordinates":[7.004409,46.217815],"type":"Point"}
}