{
  "type": "Feature",
  "properties": {
    "iso:country":"CH",
    "sg:address":"V. Besso 42 Casella Postale 219",
    "sg:city":"Lugano",
    "sg:classifiers":[
        {
            "category":"Manufacturing",
            "subcategory":"Printing",
            "type":"Manufacturing & Wholesale Goods"
        }
    ],
    "sg:phone":"+41 91 966 11 61",
    "sg:postcode":"6903",
    "sg:province":"Ticino",
    "sg:tags":[
        "publishing"
    ],
    "wof:name":"Societ\u00c0 D'arti Grafiche Gi\u00c0 Veladini & Co Sa",
    "wof:placetype":"venue"
},
  "geometry": {"coordinates":[8.9461364746,45.9767837524],"type":"Point"}
}