{
  "type": "Feature",
  "properties": {
    "iso:country":"CH",
    "sg:address":"Lochstrasse 22",
    "sg:city":"Schaffhausen",
    "sg:orig_category":"Kosmetikinstitute",
    "sg:phone":"+41 52 625 59 46",
    "sg:postcode":"8200",
    "sg:province":"Schaffhausen",
    "wof:name":"Bellissima Kosmetik-studio Isabella Nardozza",
    "wof:placetype":"venue"
},
  "geometry": {"coordinates":[8.62819767,47.7084274292],"type":"Point"}
}