{
  "type": "Feature",
  "properties": {
    "iso:country":"CH",
    "sg:address":"Montalbano Via 19a 6855 Stabio. Postfach",
    "sg:city":"Stabio",
    "sg:orig_category":"Unclassifiable Establishments",
    "sg:postcode":"6855",
    "sg:province":"Ticino",
    "wof:name":"Haas Holding Sa Partecipazione Ecc",
    "wof:placetype":"venue"
},
  "geometry": {"coordinates":[8.9350481033,45.8528671265],"type":"Point"}
}