{
  "type": "Feature",
  "properties": {
    "iso:country":"CH",
    "sg:address":"Elvezia Corso 27",
    "sg:city":"Lugano",
    "sg:orig_category":"Detailhandel mit B\u00fcchern, Zeitungen, Schreib U Papeteriewaren",
    "sg:postcode":"6900",
    "sg:province":"Ticino",
    "wof:name":"Radistal Corporation Sa",
    "wof:placetype":"venue"
},
  "geometry": {"coordinates":[8.955823,46.008999],"type":"Point"}
}