{
  "type": "Feature",
  "properties": {
    "iso:country":"CH",
    "sg:address":"Rue De La Dent-blanche 18",
    "sg:city":"Sion",
    "sg:orig_category":"Finanzierungsinstitutionen",
    "sg:phone":"+41 22 788 36 36",
    "sg:postcode":"1950",
    "sg:province":"Valais",
    "wof:name":"Longitude Investment Sa",
    "wof:placetype":"venue"
},
  "geometry": {"coordinates":[6.1277852058,46.2348480225],"type":"Point"}
}