{
  "type": "Feature",
  "properties": {
    "iso:country":"CH",
    "sg:address":"Freiburgstrasse 572",
    "sg:city":"Niederwangen",
    "sg:classifiers":[
        {
            "category":"Communications",
            "subcategory":"Film & Video Production",
            "type":"Services"
        }
    ],
    "sg:phone":"+41 31 984 03 60",
    "sg:postcode":"3172",
    "sg:province":"Bern",
    "sg:tags":[
        "images",
        "graphic",
        "creating"
    ],
    "wof:name":"Busag Graphic Ag",
    "wof:placetype":"venue"
},
  "geometry": {"coordinates":[7.376325,46.923916],"type":"Point"}
}