{
  "type": "Feature",
  "properties": {
    "iso:country":"CH",
    "sg:address":"Entlebucherstrasse 41",
    "sg:city":"Wolhusen",
    "sg:classifiers":[
        {
            "category":"Travel",
            "subcategory":"Hotels & Motels",
            "type":"Entertainment"
        }
    ],
    "sg:phone":"+41 41 490 11 23",
    "sg:postcode":"6110",
    "sg:province":"Luzern",
    "sg:tags":[
        "hotels",
        "mit",
        "restaurant"
    ],
    "wof:name":"Hotel Krone",
    "wof:placetype":"venue"
},
  "geometry": {"coordinates":[8.0708179474,47.0581359863],"type":"Point"}
}