{
  "type": "Feature",
  "properties": {
    "iso:country":"CH",
    "sg:address":"Zentalstrasse 37 8036 Z\u00fcrich. Postfach",
    "sg:city":"Z\u00fcrich",
    "sg:orig_category":"Non-Classified Establishments",
    "sg:postcode":"8002",
    "sg:province":"Z\u00fcrich",
    "wof:name":"Thyssen Holding Und Finanzierungs Ag",
    "wof:placetype":"venue"
},
  "geometry": {"coordinates":[8.5195703506,47.3714904785],"type":"Point"}
}