{
  "type": "Feature",
  "properties": {
    "iso:country":"CH",
    "sg:address":"Schaffhauserstrasse 128 8152 Glattbrugg. Postfach 3129",
    "sg:city":"Glattbrugg",
    "sg:orig_category":"Geb\u00e4ude, Wohnungsreinigung Reinigungsgewerbe",
    "sg:phone":"+41 55 440 77 88",
    "sg:postcode":"8152",
    "sg:province":"Z\u00fcrich",
    "wof:name":"Haustec Geb\u00e4udereinigung Ag",
    "wof:placetype":"venue"
},
  "geometry": {"coordinates":[8.8962087631,47.1902313232],"type":"Point"}
}