{
  "type": "Feature",
  "properties": {
    "iso:country":"CH",
    "sg:address":"1344",
    "sg:city":"L'abbaye",
    "sg:orig_category":"Hobel U Holzimpr\u00e4gnierwerke S\u00e4gewerke",
    "sg:phone":"+41 21 841 12 34",
    "sg:postcode":"1344",
    "sg:province":"Vaud",
    "wof:name":"Louis-ami Berney Sa Scierie & Raboterie",
    "wof:placetype":"venue"
},
  "geometry": {"coordinates":[127.7818603516,41.5887489319],"type":"Point"}
}