{
  "type": "Feature",
  "properties": {
    "iso:country":"CH",
    "sg:address":"Am Widagraba 3",
    "sg:city":"Vaduz",
    "sg:orig_category":"Ingenieurb\u00fcros Vermessung",
    "sg:phone":"+41 75 232 27 48",
    "sg:postcode":"9490",
    "wof:name":"Seger & Gassner Ag Ing.-& Vermessungsb\u00fcro",
    "wof:placetype":"venue"
},
  "geometry": {"coordinates":[9.5164880753,47.1396865845],"type":"Point"}
}