{
  "type": "Feature",
  "properties": {
    "addr:full":"Rue De La Gare 4 1030 Bussigny-lausanne Case Postale 224 Bussigny-lausanne Vaud 1030",
    "addr:housenumber":"4;224",
    "addr:postcode":"1030;1030",
    "addr:street":"Rue De La Gare;Case Postale",
    "iso:country":"CH",
    "sg:address":"Rue De La Gare 4 1030 Bussigny-lausanne Case Postale 224",
    "sg:city":"Bussigny-lausanne",
    "sg:orig_category":"Detailhandel mit Brillen U anderen Sehhilfen Fachdetailhandel in Verkaufsr\u00e4umen",
    "sg:phone":"+41 21 702 30 80",
    "sg:postcode":"1030",
    "sg:province":"Vaud",
    "wof:name":"Optic 2000 Bussigny Sa",
    "wof:placetype":"venue"
},
  "geometry": {"coordinates":[6.553022,46.548176],"type":"Point"}
}