{
  "type": "Feature",
  "properties": {
    "iso:country":"CH",
    "sg:address":"Asylstrasse 21 8032 Z\u00fcrich. Postfach",
    "sg:city":"Z\u00fcrich",
    "sg:orig_category":"Architekturb\u00fcros",
    "sg:phone":"+41 71 911 41 64",
    "sg:postcode":"8030",
    "wof:name":"Hans Stutz Architekturb\u00fcro",
    "wof:placetype":"venue"
},
  "geometry": {"coordinates":[9.039102,47.463791],"type":"Point"}
}