{
  "type": "Feature",
  "properties": {
    "iso:country":"CH",
    "sg:address":"Violaweg 81",
    "sg:city":"Kaiseraugst",
    "sg:orig_category":"Sportvereine Eissport Curling",
    "sg:phone":"+41 61 811 65 41",
    "sg:postcode":"4303",
    "sg:province":"Aargau",
    "wof:name":"C.c.arlesheim-birseck",
    "wof:placetype":"venue"
},
  "geometry": {"coordinates":[7.7338562012,47.5342254639],"type":"Point"}
}