{
  "type": "Feature",
  "properties": {
    "iso:country":"CH",
    "sg:address":"Freulerstrasse 4",
    "sg:city":"Birsfelden",
    "sg:orig_category":"Grosshandel mit chemischen Erzeugnissen Grosshandel mit sonstigen Halbwaren",
    "sg:phone":"+41 71 288 30 30",
    "sg:postcode":"4127",
    "sg:province":"Basel-Landschaft",
    "wof:name":"Maag Technic Ag Filiale",
    "wof:placetype":"venue"
},
  "geometry": {"coordinates":[9.4187402725,47.4383850098],"type":"Point"}
}