{
  "type": "Feature",
  "properties": {
    "iso:country":"CH",
    "sg:address":"Neuenggstrasse 9",
    "sg:city":"W\u00fcnnewil",
    "sg:orig_category":"Herstellung von sonstigen chemischen Erzeugnissen",
    "sg:postcode":"3184",
    "sg:province":"Fribourg",
    "wof:name":"Lignol, Ass Swiss-aqua-stop-systems Ag",
    "wof:placetype":"venue"
},
  "geometry": {"coordinates":[7.3032808304,46.8913650513],"type":"Point"}
}