{
  "type": "Feature",
  "properties": {
    "iso:country":"CH",
    "sg:address":"Poste Rue De La 29 1926 Fully. Postfach",
    "sg:city":"Fully",
    "sg:orig_category":"Elektroinstallation",
    "sg:phone":"+41 21 624 02 05",
    "sg:postcode":"1926",
    "sg:province":"Valais",
    "wof:name":"Peneveyre A. Sa, Entreprise G\u00e9n\u00e9rale D'installations \u00e9lectriques",
    "wof:placetype":"venue"
},
  "geometry": {"coordinates":[6.6187300682,46.5334892273],"type":"Point"}
}