{
  "type": "Feature",
  "properties": {
    "iso:country":"CH",
    "sg:address":"Chemin Du Bois-de-vaux 19c",
    "sg:city":"Lausanne",
    "sg:orig_category":"Sportvereine Sch\u00fctzen",
    "sg:postcode":"1007",
    "sg:province":"Vaud",
    "wof:name":"St\u00e9 De Tir Le Chamois Nendaz",
    "wof:placetype":"venue"
},
  "geometry": {"coordinates":[7.3247652054,46.1818466187],"type":"Point"}
}