{
  "type": "Feature",
  "properties": {
    "iso:country":"CH",
    "sg:address":"Birmensdorferstrasse 313",
    "sg:city":"Z\u00fcrich",
    "sg:orig_category":"Unclassifiable Establishments",
    "sg:phone":"+41 56 633 15 70",
    "sg:postcode":"8055",
    "sg:province":"Z\u00fcrich",
    "wof:name":"Restaurant Drei K\u00f6nige",
    "wof:placetype":"venue"
},
  "geometry": {"coordinates":[8.341635704,47.3512573242],"type":"Point"}
}