{
  "type": "Feature",
  "properties": {
    "iso:country":"CH",
    "sg:address":"Pioda Via 5",
    "sg:city":"Lugano",
    "sg:orig_category":"Vermietung U Verpachtung von eigenen Immobilien",
    "sg:phone":"+41 21 971 10 02",
    "sg:postcode":"6900",
    "sg:province":"Ticino",
    "wof:name":"Laduree S\u00e0rl",
    "wof:placetype":"venue"
},
  "geometry": {"coordinates":[6.8568668365,46.4530258179],"type":"Point"}
}