{
  "type": "Feature",
  "properties": {
    "iso:country":"CH",
    "sg:address":"Hochwachtstrasse 17",
    "sg:city":"St.gallen",
    "sg:orig_category":"Korrespondenz U Nachrichtenb\u00fcros, selbst\u00e4ndige Journalisten",
    "sg:phone":"+41 71 277 86 69",
    "sg:postcode":"9000",
    "sg:province":"St. Gallen",
    "wof:name":"Roger Huber",
    "wof:placetype":"venue"
},
  "geometry": {"coordinates":[9.3606624603,47.4125099182],"type":"Point"}
}