{
  "type": "Feature",
  "properties": {
    "iso:country":"CH",
    "sg:address":"Seestrasse 780 8706 Meilen. Postfach 117",
    "sg:city":"Meilen",
    "sg:classifiers":[
        {
            "category":"Insurance",
            "subcategory":"Insurance Agent",
            "type":"Services"
        }
    ],
    "sg:phone":"+41 19237350",
    "sg:postcode":"8706",
    "sg:province":"Z\u00fcrich",
    "sg:tags":[
        "versicherungsagenturen",
        "-broker"
    ],
    "wof:name":"Vaudoise Versicherungen",
    "wof:placetype":"venue"
},
  "geometry": {"coordinates":[8.6512556076,47.2655601501],"type":"Point"}
}