{
  "type": "Feature",
  "properties": {
    "iso:country":"CH",
    "sg:address":"1933",
    "sg:city":"Sembrancher",
    "sg:orig_category":"Vorschulen, Kinderg\u00e4rten",
    "sg:postcode":"1933",
    "sg:province":"Valais",
    "wof:name":"Ecole Enfantine",
    "wof:placetype":"venue"
},
  "geometry": {"coordinates":[7.1504249573,46.0785903931],"type":"Point"}
}