{
  "type": "Feature",
  "properties": {
    "iso:country":"CH",
    "sg:address":"D\u00f6rfli",
    "sg:city":"Engi",
    "sg:orig_category":"Detailhandel mit Waren verschiedener Art, Hauptrichtung Nahrungsmittel",
    "sg:phone":"+41 55 642 11 18",
    "sg:postcode":"8765",
    "sg:province":"Glarus",
    "wof:name":"Dorfl\u00e4deli Blumer & Wichser",
    "wof:placetype":"venue"
},
  "geometry": {"coordinates":[9.1541223526,46.9818992615],"type":"Point"}
}