{
  "type": "Feature",
  "properties": {
    "iso:country":"CH",
    "sg:address":"Chemin De La Planchette",
    "sg:city":"Aigle",
    "sg:orig_category":"Detailhandel mit Waren verschiedener Art in Verkaufsr\u00e4umen",
    "sg:postcode":"1860",
    "sg:province":"Vaud",
    "wof:name":"Supermarch\u00e9 Pam",
    "wof:placetype":"venue"
},
  "geometry": {"coordinates":[6.9595351219,46.3197517395],"type":"Point"}
}