{
  "type": "Feature",
  "properties": {
    "iso:country":"CH",
    "sg:address":"Rue Des Vernes 11",
    "sg:city":"Payerne",
    "sg:orig_category":"Verlegen von Fliesen U Platten",
    "sg:phone":"+41 71 622 55 32",
    "sg:postcode":"1530",
    "sg:province":"Vaud",
    "wof:name":"Rolf Bianco Ofenbau & Plattenbel\u00e4ge",
    "wof:placetype":"venue"
},
  "geometry": {"coordinates":[9.1364603043,47.567741394],"type":"Point"}
}