{
  "type": "Feature",
  "properties": {
    "iso:country":"CH",
    "sg:address":"Papierm\u00fchlestrasse 9 3013 Bern. Postfach",
    "sg:city":"Bern",
    "sg:orig_category":"Pensionskassen",
    "sg:phone":"+41 31 931 31 96",
    "sg:postcode":"3005",
    "sg:province":"Bern",
    "wof:name":"Personalvorsorgestiftung Elenka Bvg",
    "wof:placetype":"venue"
},
  "geometry": {"coordinates":[7.4598059654,46.9542770386],"type":"Point"}
}