{
  "type": "Feature",
  "properties": {
    "iso:country":"CH",
    "sg:address":"Flurstrasse 89",
    "sg:city":"Z\u00fcrich",
    "sg:orig_category":"M\u00f6belschreinereien",
    "sg:postcode":"8047",
    "sg:province":"Z\u00fcrich",
    "wof:name":"Schreinerei R\u00f6lli P. M\u00f6belschreinerei U. Innenausbau",
    "wof:placetype":"venue"
},
  "geometry": {"coordinates":[8.4923563004,47.3817443848],"type":"Point"}
}