{
  "type": "Feature",
  "properties": {
    "addr:full":"Hardhof Eglisau Z\u00fcrich 8193",
    "addr:postcode":"8193",
    "addr:street":"Zuerich",
    "iso:country":"CH",
    "sg:address":"Hardhof",
    "sg:city":"Eglisau",
    "sg:orig_category":"Betrieb U technische Hilfsdienste des Kultur U Unterhaltungswesens",
    "sg:postcode":"8193",
    "sg:province":"Z\u00fcrich",
    "wof:name":"Activity Office Luder Jack Ag",
    "wof:placetype":"venue"
},
  "geometry": {"coordinates":[8.541867,47.592285],"type":"Point"}
}