{
  "type": "Feature",
  "properties": {
    "iso:country":"CH",
    "sg:address":"Via Giulio Vicari 12",
    "sg:city":"Lugano",
    "sg:orig_category":"Instandhaltung U Reparatur von Automobilen",
    "sg:phone":"+41 91 973 22 20",
    "sg:postcode":"6900",
    "sg:province":"Ticino",
    "wof:name":"Vanossi Sa",
    "wof:placetype":"venue"
},
  "geometry": {"coordinates":[8.9683637619,46.0070571899],"type":"Point"}
}