{
  "type": "Feature",
  "properties": {
    "iso:country":"CH",
    "sg:address":"Gewerbestrasse 1",
    "sg:city":"M\u00fchleberg",
    "sg:orig_category":"Schlossereien Zimmerei, Dachdeckerei, Bauspenglerei U Abdichtung",
    "sg:phone":"+41 31 751 12 95",
    "sg:postcode":"3203",
    "sg:province":"Bern",
    "wof:name":"B\u00fcttner Rolf",
    "wof:placetype":"venue"
},
  "geometry": {"coordinates":[7.2748780251,46.9597129822],"type":"Point"}
}