{
  "type": "Feature",
  "properties": {
    "iso:country":"CH",
    "sg:address":"Gare Rue De La 2",
    "sg:city":"St-prex",
    "sg:orig_category":"Non-Classified Establishments",
    "sg:phone":"+41 21 806 14 59",
    "sg:postcode":"1162",
    "sg:province":"Vaud",
    "wof:name":"Burri Patrick, Horticulteur",
    "wof:placetype":"venue"
},
  "geometry": {"coordinates":[6.4576702118,46.4821166992],"type":"Point"}
}