{
  "type": "Feature",
  "properties": {
    "iso:country":"CH",
    "sg:address":"Via Nassa 27",
    "sg:city":"Lugano",
    "sg:orig_category":"Detailhandel mit Damenbekleidung Herstellung von W\u00e4sche",
    "sg:phone":"+41 55 283 44 55",
    "sg:postcode":"6900",
    "sg:province":"Ticino",
    "wof:name":"Mode Charme Aeschlimann",
    "wof:placetype":"venue"
},
  "geometry": {"coordinates":[9.0054197311,47.19764328],"type":"Point"}
}