{
  "type": "Feature",
  "properties": {
    "iso:country":"CH",
    "sg:address":"Kanonengasse 11 4410 Liestal. Postfach",
    "sg:city":"Liestal",
    "sg:orig_category":"Bauspenglerei Sanit\u00e4rinstallation",
    "sg:phone":"+41 61 921 43 37",
    "sg:postcode":"4410",
    "sg:province":"Basel-Landschaft",
    "wof:name":"Fredy Schaub Sanit\u00e4re Anlagen & Spenglerei",
    "wof:placetype":"venue"
},
  "geometry": {"coordinates":[7.735995,47.484318],"type":"Point"}
}