{
  "type": "Feature",
  "properties": {
    "iso:country":"CH",
    "sg:address":"Grundstrasse 10 6343 Rotkreuz. Postfach",
    "sg:city":"Rotkreuz",
    "sg:orig_category":"Grosshandel mit sonstigen Maschinen U Ausr\u00fcstungen f\u00fcr Industrie, Handel U Schiffahrt",
    "sg:phone":"+41 41 799 77 77",
    "sg:postcode":"6343",
    "sg:province":"Zug",
    "wof:name":"Pe Ag",
    "wof:placetype":"venue"
},
  "geometry": {"coordinates":[8.430644989,47.1453056335],"type":"Point"}
}