{
  "type": "Feature",
  "properties": {
    "iso:country":"CH",
    "sg:address":"Schlossbergstrasse 20 8702 Zollikon. Postfach",
    "sg:city":"Zollikon",
    "sg:orig_category":"Herstellung von Papier, Karton U Pappe",
    "sg:postcode":"8702",
    "sg:province":"Z\u00fcrich",
    "wof:name":"Dietimmobil Ag",
    "wof:placetype":"venue"
},
  "geometry": {"coordinates":[8.5805902481,47.3439559937],"type":"Point"}
}