{
  "type": "Feature",
  "properties": {
    "iso:country":"CH",
    "sg:address":"Merkurstrasse 2 6210 Sursee. Postfach 429",
    "sg:city":"Sursee",
    "sg:orig_category":"Herstellung von Metallerzeugnissen ohne Maschinenbau Herstellung von landwirtschaftlichen Maschinen",
    "sg:phone":"+41 41 926 18 00",
    "sg:postcode":"6210",
    "sg:province":"Luzern",
    "wof:name":"Schauer Agrotronic Ag Computerges.f\u00fctterungsanlagen",
    "wof:placetype":"venue"
},
  "geometry": {"coordinates":[8.1014461517,47.1674919128],"type":"Point"}
}