{
  "type": "Feature",
  "properties": {
    "iso:country":"CH",
    "sg:address":"Rue Du Closillon 5",
    "sg:city":"Monthey",
    "sg:orig_category":"Vereine Wissenschaftliche",
    "sg:phone":"+41 24 471 94 28",
    "sg:postcode":"1870",
    "sg:province":"Valais",
    "wof:name":"Cercle Arch\u00e9olog.du Chablais",
    "wof:placetype":"venue"
},
  "geometry": {"coordinates":[6.9565491676,46.2560119629],"type":"Point"}
}