{
  "type": "Feature",
  "properties": {
    "iso:country":"CH",
    "sg:address":"Zollhausstrasse 55",
    "sg:city":"Biel/bienne",
    "sg:orig_category":"Sportvereine Behindertensport",
    "sg:phone":"+41 32 341 01 65",
    "sg:postcode":"2504",
    "sg:province":"Bern",
    "wof:name":"Svbs Biel Asi",
    "wof:placetype":"venue"
},
  "geometry": {"coordinates":[7.2666611671,47.1552200317],"type":"Point"}
}