{
  "type": "Feature",
  "properties": {
    "iso:country":"CH",
    "sg:address":"Solothurnstrasse 129",
    "sg:city":"Grenchen",
    "sg:orig_category":"Instandhaltung U Reparatur von Automobilen",
    "sg:phone":"+41 18404393",
    "sg:postcode":"2540",
    "sg:province":"Solothurn",
    "wof:name":"Auto Wallishauser Ag",
    "wof:placetype":"venue"
},
  "geometry": {"coordinates":[8.463312149,47.4487762451],"type":"Point"}
}