{
  "type": "Feature",
  "properties": {
    "iso:country":"CH",
    "sg:address":"J\u00e4gerweg 4",
    "sg:city":"Grabs",
    "sg:orig_category":"Mechanische Werkst\u00e4tten",
    "sg:phone":"+41 24 499 12 02",
    "sg:postcode":"9472",
    "sg:province":"St. Gallen",
    "wof:name":"Fernand Crolla Atelier \u00e9lectro-m\u00e9canique",
    "wof:placetype":"venue"
},
  "geometry": {"coordinates":[6.9964599609,46.2834510803],"type":"Point"}
}