{
  "type": "Feature",
  "properties": {
    "iso:country":"CH",
    "sg:address":"Chemin Chasse-peines 2 2068 Hauterive Case Postale",
    "sg:city":"Hauterive",
    "sg:orig_category":"Architektur U Ingenieurb\u00fcros",
    "sg:phone":"+41 32 754 30 00",
    "sg:postcode":"2068",
    "sg:province":"Neuch\u00e2tel",
    "wof:name":"Fahrni Pierre Sa",
    "wof:placetype":"venue"
},
  "geometry": {"coordinates":[6.971835,47.013763],"type":"Point"}
}