{
  "type": "Feature",
  "properties": {
    "iso:country":"CH",
    "sg:address":"Friedhofstrasse 1",
    "sg:city":"B\u00e4retswil",
    "sg:orig_category":"Personenbef\u00f6rderung im Linienverkehr zu Land",
    "sg:postcode":"8344",
    "sg:province":"Z\u00fcrich",
    "wof:name":"Skilift-genossenschaft Steig-b\u00e4retswil",
    "wof:placetype":"venue"
},
  "geometry": {"coordinates":[8.8534421921,47.3355484009],"type":"Point"}
}