{
  "type": "Feature",
  "properties": {
    "iso:country":"CH",
    "sg:address":"Grande-rue 36 1304 Cossonay-ville. Postfach",
    "sg:city":"Allens",
    "sg:orig_category":"Instandhaltung U Reparatur von Automobilen",
    "sg:phone":"+41 21 861 11 79",
    "sg:postcode":"1304",
    "sg:province":"Vaud",
    "wof:name":"Garage De Cossonay, De Bellis Jean",
    "wof:placetype":"venue"
},
  "geometry": {"coordinates":[6.4875569344,46.6005821228],"type":"Point"}
}