{
  "type": "Feature",
  "properties": {
    "iso:country":"CH",
    "sg:address":"Blauenstrasse 30",
    "sg:city":"Basel",
    "sg:classifiers":[
        {
            "category":"Professional",
            "subcategory":"Art Services",
            "type":"Services"
        }
    ],
    "sg:phone":"+41 61 301 65 14",
    "sg:postcode":"4054",
    "sg:province":"Basel-Stadt",
    "sg:tags":[
        "artistic",
        "glazings"
    ],
    "wof:name":"Rehberg Glasmalerei",
    "wof:placetype":"venue"
},
  "geometry": {"coordinates":[7.573194,47.555164],"type":"Point"}
}