{
  "type": "Feature",
  "properties": {
    "iso:country":"CH",
    "sg:address":"Hiltystrasse 22 3006 Bern. Postfach",
    "sg:city":"Bern",
    "sg:orig_category":"Vermietung U Verpachtung von eigenen Immobilien",
    "sg:postcode":"3005",
    "sg:province":"Bern",
    "wof:name":"U. Messerli Und B. Nicaise-messerli + Cie Immobilien. Kr\u00e4uter; Handel",
    "wof:placetype":"venue"
},
  "geometry": {"coordinates":[7.4742650986,46.9350852966],"type":"Point"}
}