{
  "type": "Feature",
  "properties": {
    "iso:country":"CH",
    "sg:address":"Simmentalstrasse 30",
    "sg:city":"Spiez",
    "sg:orig_category":"Einzelhandel mit Automobilteilen U Zubeh\u00f6r Tankstellen",
    "sg:phone":"+41 24 436 18 53",
    "sg:postcode":"3700",
    "sg:province":"Bern",
    "wof:name":"Bernard Chiri Station-service",
    "wof:placetype":"venue"
},
  "geometry": {"coordinates":[6.6853108406,46.8349838257],"type":"Point"}
}