{
  "type": "Feature",
  "properties": {
    "iso:country":"CH",
    "sg:address":"Clarastrasse 9",
    "sg:city":"Basel",
    "sg:orig_category":"Herstellung von Schmuck, Gold U Silberschmiedwaren",
    "sg:postcode":"4058",
    "sg:province":"Basel-Stadt",
    "wof:name":"Goldhaus Van Wyk Schmuckwaren; Gross Und Einzelhandel",
    "wof:placetype":"venue"
},
  "geometry": {"coordinates":[9.3753051758,47.426235199],"type":"Point"}
}