{
  "type": "Feature",
  "properties": {
    "iso:country":"CH",
    "sg:address":"Via Lucomagno 13",
    "sg:city":"Bellinzona",
    "sg:orig_category":"Detailhandel mit Waren verschiedener Art, Hauptrichtung Nahrungsmittel Fachdetailhandel mit Nahrungs",
    "sg:phone":"+41 91 826 19 48",
    "sg:postcode":"6500",
    "sg:province":"Ticino",
    "wof:name":"Prc Di Piazzini Mario",
    "wof:placetype":"venue"
},
  "geometry": {"coordinates":[9.0208282471,46.2002105713],"type":"Point"}
}