{
  "type": "Feature",
  "properties": {
    "addr:full":"Grandcour Route De 73 1530 Payerne Case Postale 426 Payerne Vaud 1530",
    "addr:housenumber":"grandcour;73",
    "addr:postcode":"1530;1530",
    "addr:street":"Route De;Postale 426",
    "iso:country":"CH",
    "sg:address":"Grandcour Route De 73 1530 Payerne Case Postale 426",
    "sg:city":"Payerne",
    "sg:orig_category":"Bestattungswesen",
    "sg:phone":"+41 26 660 16 76",
    "sg:postcode":"1530",
    "sg:province":"Vaud",
    "wof:name":"Pompes Fun\u00e8bres Verdon Sa",
    "wof:placetype":"venue"
},
  "geometry": {"coordinates":[6.935218,46.832058],"type":"Point"}
}