{
  "type": "Feature",
  "properties": {
    "iso:country":"CH",
    "sg:address":"Unterdorfstrasse 19",
    "sg:city":"R\u00f6schenz",
    "sg:orig_category":"Maschinen-Fabrikation",
    "sg:postcode":"4244",
    "sg:province":"Basel-Landschaft",
    "wof:name":"Schnell Engineering Gmbh",
    "wof:placetype":"venue"
},
  "geometry": {"coordinates":[7.4779539108,47.4240074158],"type":"Point"}
}