{
  "type": "Feature",
  "properties": {
    "iso:country":"CH",
    "sg:address":"Industriestrasse 28 8108 D\u00e4llikon. Postfach",
    "sg:city":"D\u00e4llikon",
    "sg:orig_category":"Pensionskassen",
    "sg:postcode":"8108",
    "sg:province":"Z\u00fcrich",
    "wof:name":"Personalf\u00fcrsorgestiftung Der We Switzerland Ag",
    "wof:placetype":"venue"
},
  "geometry": {"coordinates":[8.4324607849,47.4461631775],"type":"Point"}
}