{
  "type": "Feature",
  "properties": {
    "iso:country":"CH",
    "sg:address":"6011 Kriens. Postfach 292",
    "sg:city":"Kriens",
    "sg:orig_category":"Sportvereine Ballsport Fussball",
    "sg:phone":"+41 41 322 16 16",
    "sg:postcode":"6011",
    "sg:province":"Luzern",
    "wof:name":"Sc Kriens",
    "wof:placetype":"venue"
},
  "geometry": {"coordinates":[8.2787704468,47.0337295532],"type":"Point"}
}