{
  "type": "Feature",
  "properties": {
    "iso:country":"CH",
    "sg:address":"Unterm\u00fcli 9 6300 Zug. Postfach 2317",
    "sg:city":"Zug",
    "sg:orig_category":"Finanzierungsinstitutionen Grosshandel mit festen Brennstoffen U Mineral\u00f6lerzeugnissen",
    "sg:phone":"+41 41 760 18 80",
    "sg:postcode":"6302",
    "sg:province":"Zug",
    "wof:name":"Intercontrade Zug Ag",
    "wof:placetype":"venue"
},
  "geometry": {"coordinates":[8.5177631378,47.1804656982],"type":"Point"}
}