{
  "type": "Feature",
  "properties": {
    "iso:country":"CH",
    "sg:address":"Sonnenb\u00fchlweg 11",
    "sg:city":"Kriens",
    "sg:orig_category":"Vereine Mandolinen and Gitarren",
    "sg:phone":"+41 41 319 41 11",
    "sg:postcode":"6010",
    "sg:province":"Luzern",
    "wof:name":"Zitherclub Luzern",
    "wof:placetype":"venue"
},
  "geometry": {"coordinates":[8.2913970947,47.0375556946],"type":"Point"}
}