{
  "type": "Feature",
  "properties": {
    "iso:country":"CH",
    "sg:address":"Hinterwil",
    "sg:city":"Uerkheim",
    "sg:orig_category":"Verwertung von Milch",
    "sg:postcode":"4813",
    "sg:province":"Aargau",
    "wof:name":"K\u00e4sereigesellschaft Uerkheim",
    "wof:placetype":"venue"
},
  "geometry": {"coordinates":[7.9919471741,47.3033027649],"type":"Point"}
}