{
  "type": "Feature",
  "properties": {
    "iso:country":"CH",
    "sg:address":"Via Nocca 6500 Bellinzona. Postfach",
    "sg:city":"Bellinzona",
    "sg:orig_category":"RESTAURANTS: TEA-ROOMS",
    "sg:postcode":"6500",
    "sg:province":"Ticino",
    "wof:name":"Giudici Augusto",
    "wof:placetype":"venue"
},
  "geometry": {"coordinates":[9.0249595642,46.1887512207],"type":"Point"}
}