{
  "type": "Feature",
  "properties": {
    "iso:country":"CH",
    "sg:address":"La Villa D'oex",
    "sg:city":"Ch\u00e2teau-d'oex",
    "sg:orig_category":"Geometerb\u00fcros",
    "sg:phone":"+41 26 924 67 66",
    "sg:postcode":"1837",
    "wof:name":"Etter Frund Ansermot Ing\u00e9nieurs-g\u00e9om\u00e8tres Off.sa",
    "wof:placetype":"venue"
},
  "geometry": {"coordinates":[-97.92877960209999,26.298330307],"type":"Point"}
}