{
  "type": "Feature",
  "properties": {
    "iso:country":"CH",
    "sg:address":"Flughafen Z\u00fcrich-kloten 8058 Z\u00fcrich. Postfach 221",
    "sg:city":"Z\u00fcrich",
    "sg:orig_category":"Finanzierungsinstitutionen",
    "sg:postcode":"8058",
    "sg:province":"Z\u00fcrich",
    "wof:name":"Jumbo Air Cargo 2000 Sa",
    "wof:placetype":"venue"
},
  "geometry": {"coordinates":[8.5380096436,47.3690910339],"type":"Point"}
}