{
  "type": "Feature",
  "properties": {
    "iso:country":"CH",
    "sg:address":"Rue Du 1er-mars 50",
    "sg:city":"Geneveys-coffrane",
    "sg:orig_category":"Stukkateurgewerbe, Gipserei U Verputzerei Tapeziererei",
    "sg:phone":"+41 32 857 13 02",
    "sg:postcode":"2206",
    "sg:province":"Neuch\u00e2tel",
    "wof:name":"Vitali Mme P.",
    "wof:placetype":"venue"
},
  "geometry": {"coordinates":[6.8476309776,47.0133895874],"type":"Point"}
}