{
  "type": "Feature",
  "properties": {
    "iso:country":"CH",
    "sg:address":"Nationalstrasse 6",
    "sg:city":"Kreuzlingen",
    "sg:orig_category":"Gymnastik U Fitnesszentren Saunas, Solarien, Fitnesszentren U \u00e4hnliches",
    "sg:phone":"+41 71 672 44 94",
    "sg:postcode":"8280",
    "sg:province":"Thurgau",
    "wof:name":"Wolfram Ehrling Kieser-training",
    "wof:placetype":"venue"
},
  "geometry": {"coordinates":[9.1688480377,47.6517944336],"type":"Point"}
}