{
  "type": "Feature",
  "properties": {
    "iso:country":"CH",
    "sg:address":"Hanflandstrasse 17",
    "sg:city":"D\u00fcrnten",
    "sg:orig_category":"Vereine Frauen Vereine Gemeinn\u00fctzige",
    "sg:phone":"+41 55 240 62 14",
    "sg:postcode":"8635",
    "sg:province":"Z\u00fcrich",
    "wof:name":"Frauenverein Oberd\u00fcrnten",
    "wof:placetype":"venue"
},
  "geometry": {"coordinates":[8.8759756088,47.27394104],"type":"Point"}
}