{
  "type": "Feature",
  "properties": {
    "iso:country":"CH",
    "sg:address":"Chemin De La Morgette",
    "sg:city":"Chigny",
    "sg:orig_category":"Maurerarbeiten",
    "sg:phone":"+41 21 803 30 04",
    "sg:postcode":"1134",
    "sg:province":"Vaud",
    "wof:name":"Jean-daniel Nicolier Entreprise De B\u00e2timents",
    "wof:placetype":"venue"
},
  "geometry": {"coordinates":[6.4794998169,46.5178756714],"type":"Point"}
}