{
  "type": "Feature",
  "properties": {
    "iso:country":"CH",
    "sg:address":"T\u00fcbacherstrasse 12b",
    "sg:city":"Horn",
    "sg:orig_category":"Allgemeiner Hoch U Tiefbau Hoch U Tiefbau",
    "sg:phone":"+41 71 841 02 42",
    "sg:postcode":"9326",
    "sg:province":"Thurgau",
    "wof:name":"Colorimo, Wojneschitz Peter",
    "wof:placetype":"venue"
},
  "geometry": {"coordinates":[9.46157,47.494503],"type":"Point"}
}