{
  "type": "Feature",
  "properties": {
    "iso:country":"CH",
    "sg:address":"Erlenweg 12",
    "sg:city":"Oberentfelden",
    "sg:orig_category":"Autogaragen Instandhaltung U Reparatur von Automobilen",
    "sg:phone":"+41 79 415 15 85",
    "sg:postcode":"5036",
    "sg:province":"Aargau",
    "wof:name":"Datacars Holliger",
    "wof:placetype":"venue"
},
  "geometry": {"coordinates":[8.044008,47.359875],"type":"Point"}
}