{
  "type": "Feature",
  "properties": {
    "iso:country":"CH",
    "sg:address":"Rue De La Pr\u00e9v\u00f4t\u00e9 21f",
    "sg:city":"Courrendlin",
    "sg:orig_category":"Sportvereine Eissport Eishockey",
    "sg:phone":"+41 32 435 69 57",
    "sg:postcode":"2830",
    "sg:province":"Jura",
    "wof:name":"Hockey-club Courrendlin",
    "wof:placetype":"venue"
},
  "geometry": {"coordinates":[7.3708348274,47.3351173401],"type":"Point"}
}