{
  "type": "Feature",
  "properties": {
    "iso:country":"CH",
    "sg:address":"Oberes Emmenholz",
    "sg:city":"Zuchwil",
    "sg:orig_category":"Medizin, Pharmaprodukte",
    "sg:phone":"+41 32 685 54 40",
    "sg:postcode":"4528",
    "sg:province":"Solothurn",
    "wof:name":"Anandayurveda",
    "wof:placetype":"venue"
},
  "geometry": {"coordinates":[7.571217,47.211384],"type":"Point"}
}