{
  "type": "Feature",
  "properties": {
    "iso:country":"CH",
    "sg:address":"Chemin De La Barge 15",
    "sg:city":"Bernex",
    "sg:orig_category":"Architektur U Ingenieurb\u00fcros",
    "sg:phone":"+41 22 757 47 17",
    "sg:postcode":"1233",
    "sg:province":"Gen\u00e8ve",
    "wof:name":"Fichtner Klaus Ing\u00e9nieur Conseil",
    "wof:placetype":"venue"
},
  "geometry": {"coordinates":[6.074833,46.161995],"type":"Point"}
}