{
  "type": "Feature",
  "properties": {
    "addr:full":"Avenue C\u00e9cil 6 Lausanne Vaud 1007",
    "addr:housenumber":"6",
    "addr:postcode":"1007",
    "addr:street":"Avenue Ce\u0301Cil",
    "iso:country":"CH",
    "sg:address":"Avenue C\u00e9cil 6",
    "sg:city":"Lausanne",
    "sg:orig_category":"Chiropraktik",
    "sg:phone":"+41 22 342 42 30",
    "sg:postcode":"1007",
    "sg:province":"Vaud",
    "wof:name":"Pierre Tapponnier Chiropraticien",
    "wof:placetype":"venue"
},
  "geometry": {"coordinates":[6.141425,46.183311],"type":"Point"}
}