{
  "type": "Feature",
  "properties": {
    "iso:country":"CH",
    "sg:address":"Monbijoustrasse 36 3011 Bern. Postfach",
    "sg:city":"Bern",
    "sg:orig_category":"Interessenvertretungen",
    "sg:postcode":"3005",
    "sg:province":"Bern",
    "wof:name":"Gesellschaft Praktizierender Wirtschaftsberater",
    "wof:placetype":"venue"
},
  "geometry": {"coordinates":[7.4353709221,46.9434356689],"type":"Point"}
}