{
  "type": "Feature",
  "properties": {
    "iso:country":"CH",
    "sg:address":"Quaderstrasse 8",
    "sg:city":"Chur",
    "sg:classifiers":[
        {
            "category":"Restaurant",
            "type":"Food & Drink"
        }
    ],
    "sg:phone":"+41 71 912 20 80",
    "sg:postcode":"7000",
    "sg:province":"Graubunden",
    "wof:name":"Restaurant Gl\u00e4rnisch",
    "wof:placetype":"venue"
},
  "geometry": {"coordinates":[9.0386285782,47.4620285034],"type":"Point"}
}