{
  "type": "Feature",
  "properties": {
    "iso:country":"CH",
    "sg:address":"Liebr\u00fctistrasse 31",
    "sg:city":"Kaiseraugst",
    "sg:orig_category":"Geb\u00e4ude, Wohnungsreinigung Reinigungsgewerbe",
    "sg:phone":"+41 76 318 53 37",
    "sg:postcode":"4303",
    "sg:province":"Aargau",
    "wof:name":"A-z Reinigung M\u00fcller Hofmann",
    "wof:placetype":"venue"
},
  "geometry": {"coordinates":[7.7291688919,47.5349121094],"type":"Point"}
}