{
  "type": "Feature",
  "properties": {
    "iso:country":"CH",
    "sg:address":"3904",
    "sg:city":"Naters",
    "sg:orig_category":"Sportvereine Sch\u00fctzen",
    "sg:postcode":"3904",
    "sg:province":"Valais",
    "wof:name":"Milit\u00e4rschiessverein",
    "wof:placetype":"venue"
},
  "geometry": {"coordinates":[7.7845520973,46.4042396545],"type":"Point"}
}