{
  "type": "Feature",
  "properties": {
    "iso:country":"CH",
    "sg:address":"Maiacherstrasse 32",
    "sg:city":"Volketswil",
    "sg:orig_category":"Vereine Gesang Vereine Gesang and Jodler",
    "sg:postcode":"8604",
    "sg:province":"Z\u00fcrich",
    "wof:name":"Jodelclub S\u00e4ngerrunde",
    "wof:placetype":"venue"
},
  "geometry": {"coordinates":[8.6610946655,47.3913002014],"type":"Point"}
}