{
  "type": "Feature",
  "properties": {
    "iso:country":"CH",
    "sg:address":"3792",
    "sg:city":"Saanen",
    "sg:orig_category":"Interessenvertretungen",
    "sg:postcode":"3792",
    "sg:province":"Bern",
    "wof:name":"Strassengenossenschaft Sch\u00f6nried-moos",
    "wof:placetype":"venue"
},
  "geometry": {"coordinates":[7.2361397743,46.463218689],"type":"Point"}
}