{
  "type": "Feature",
  "properties": {
    "iso:country":"CH",
    "sg:address":"M\u00fcnsterplatz 2 4051 Basel. Postfach",
    "sg:city":"Basel",
    "sg:orig_category":"Museen",
    "sg:phone":"+41 61 267 84 01",
    "sg:postcode":"4001",
    "sg:province":"Basel-Stadt",
    "wof:name":"Museen Basel Koordinationsstelle",
    "wof:placetype":"venue"
},
  "geometry": {"coordinates":[7.5911450386,47.5570449829],"type":"Point"}
}