{
  "type": "Feature",
  "properties": {
    "iso:country":"CH",
    "sg:address":"Marzilistrasse 10a",
    "sg:city":"Bern",
    "sg:orig_category":"Kaminfeger",
    "sg:phone":"+41 75 373 59 71",
    "sg:postcode":"3005",
    "sg:province":"Bern",
    "wof:name":"Benedikt Kuster Kaminfeger",
    "wof:placetype":"venue"
},
  "geometry": {"coordinates":[9.5522651672,47.2217750549],"type":"Point"}
}