{
  "type": "Feature",
  "properties": {
    "iso:country":"CH",
    "sg:address":"Friedhofstrasse 28",
    "sg:city":"Aarwangen",
    "sg:orig_category":"Selbst\u00e4ndige bildende K\u00fcnstler",
    "sg:phone":"+41 62 922 46 32",
    "sg:postcode":"4912",
    "sg:province":"Bern",
    "wof:name":"Andreas Fiechter Bildhauer-atelier",
    "wof:placetype":"venue"
},
  "geometry": {"coordinates":[7.7698130608,47.2437057495],"type":"Point"}
}