{
  "type": "Feature",
  "properties": {
    "iso:country":"CH",
    "sg:address":"Fischerweg 31",
    "sg:city":"Oftringen",
    "sg:orig_category":"G\u00fcterbef\u00f6rderung im Strassenverkehr",
    "sg:phone":"+41 62 797 54 30",
    "sg:postcode":"4665",
    "sg:province":"Aargau",
    "wof:name":"Peter Kernen Transporte",
    "wof:placetype":"venue"
},
  "geometry": {"coordinates":[7.9389748573,47.2997055054],"type":"Point"}
}