{
  "type": "Feature",
  "properties": {
    "iso:country":"CH",
    "sg:address":"Haldenstrasse 8",
    "sg:city":"Kloten",
    "sg:orig_category":"Non-Classified Establishments",
    "sg:postcode":"8302",
    "sg:province":"Z\u00fcrich",
    "wof:name":"Tradeinvest Holding Ag",
    "wof:placetype":"venue"
},
  "geometry": {"coordinates":[8.5942630768,47.455165863],"type":"Point"}
}