{
  "type": "Feature",
  "properties": {
    "iso:country":"CH",
    "sg:address":"Radm\u00fchlestrasse 18",
    "sg:city":"Amriswil",
    "sg:orig_category":"Verlegen von Fliesen U Platten",
    "sg:phone":"+41 71 411 56 30",
    "sg:postcode":"8580",
    "sg:province":"Thurgau",
    "wof:name":"Guido Huber Boden-& Wandbel\u00e4ge",
    "wof:placetype":"venue"
},
  "geometry": {"coordinates":[9.2888278961,47.5546417236],"type":"Point"}
}