{
  "type": "Feature",
  "properties": {
    "iso:country":"CH",
    "sg:address":"Chandieu Rue 5",
    "sg:city":"Gen\u00e8ve",
    "sg:orig_category":"Unclassifiable Establishments",
    "sg:postcode":"1202",
    "sg:province":"Gen\u00e8ve",
    "wof:name":"Martinez Val\u00e9rie",
    "wof:placetype":"venue"
},
  "geometry": {"coordinates":[6.1342868805,46.2159042358],"type":"Point"}
}