{
  "type": "Feature",
  "properties": {
    "iso:country":"CH",
    "sg:address":"In Der Schappe 12",
    "sg:city":"Arlesheim",
    "sg:orig_category":"Interessenvertretungen",
    "sg:phone":"+41 61 701 78 67",
    "sg:postcode":"4144",
    "sg:province":"Basel-Landschaft",
    "wof:name":"Verein F\u00fcr Biographiearbeit Auf Grundlage Der Anthroposophie",
    "wof:placetype":"venue"
},
  "geometry": {"coordinates":[7.607776165,47.4933547974],"type":"Point"}
}