{
  "type": "Feature",
  "properties": {
    "iso:country":"CH",
    "sg:address":"Rue De La Berg\u00e8re 1a",
    "sg:city":"Meyrin",
    "sg:orig_category":"Internationale Organisationen mit Beh\u00f6rdecharakter",
    "sg:phone":"+41 22 798 41 21",
    "sg:postcode":"1217",
    "sg:province":"Gen\u00e8ve",
    "wof:name":"Alliance Coop\u00e9rative Internationale Aci",
    "wof:placetype":"venue"
},
  "geometry": {"coordinates":[6.1319308281,46.2313728333],"type":"Point"}
}