{
  "type": "Feature",
  "properties": {
    "iso:country":"CH",
    "sg:address":"L\u00fcsisstrasse 4b",
    "sg:city":"Walenstadt",
    "sg:orig_category":"Fachdetailhandel mit pharmazeutischen Produkten",
    "sg:phone":"+41 81 710 20 61",
    "sg:postcode":"8880",
    "sg:province":"St. Gallen",
    "wof:name":"Epac Pharma Ag",
    "wof:placetype":"venue"
},
  "geometry": {"coordinates":[9.3264141083,47.1244850159],"type":"Point"}
}