{
  "type": "Feature",
  "properties": {
    "iso:country":"CH",
    "sg:address":"Dorfmattenstrasse 12",
    "sg:city":"H\u00e4gglingen",
    "sg:orig_category":"Politische Parteien SVP",
    "sg:phone":"+41 56 624 15 37",
    "sg:postcode":"5607",
    "sg:province":"Aargau",
    "wof:name":"Svp Ortspartei H\u00e4gglingen",
    "wof:placetype":"venue"
},
  "geometry": {"coordinates":[8.2477779388,47.3873291016],"type":"Point"}
}