{
  "type": "Feature",
  "properties": {
    "iso:country":"CH",
    "sg:address":"1948",
    "sg:city":"Fionnay",
    "sg:orig_category":"Elektrizit\u00e4tsversorgung",
    "sg:phone":"+41 27 778 12 42",
    "sg:postcode":"1948",
    "sg:province":"Valais",
    "wof:name":"Grande Dixence Sa Usine \u00e9lectrique",
    "wof:placetype":"venue"
},
  "geometry": {"coordinates":[7.3077502251,46.0328483582],"type":"Point"}
}