{
  "type": "Feature",
  "properties": {
    "iso:country":"CH",
    "sg:address":"8036 Z\u00fcrich. Postfach 8050 Z\u00fcrich",
    "sg:city":"Zust",
    "sg:orig_category":"Softwareentwicklung U beratung",
    "sg:postcode":"50",
    "wof:name":"Dsg Datasoft Ag",
    "wof:placetype":"venue"
},
  "geometry": {"coordinates":[9.3806724548,47.4336357117],"type":"Point"}
}