{
  "type": "Feature",
  "properties": {
    "iso:country":"CH",
    "sg:address":"Rue Du Parc 14",
    "sg:city":"Yverdon-les-bains",
    "sg:orig_category":"Schiffs U Bootsbau",
    "sg:phone":"+41 24 425 00 36",
    "sg:postcode":"1400",
    "sg:province":"Vaud",
    "wof:name":"Chantier Naval Burkhalter",
    "wof:placetype":"venue"
},
  "geometry": {"coordinates":[6.6391777992,46.7875709534],"type":"Point"}
}