{
  "type": "Feature",
  "properties": {
    "iso:country":"CH",
    "sg:address":"Zeughausgasse 14",
    "sg:city":"Bern 7",
    "sg:orig_category":"Finanzen, Versicherungen",
    "sg:phone":"+41 31 312 63 93",
    "sg:postcode":"3000",
    "sg:province":"Bern",
    "wof:name":"Murette Ag Versicherungs- Und R\u00fcckversicherungs-vermittlung",
    "wof:placetype":"venue"
},
  "geometry": {"coordinates":[7.445447,46.949059],"type":"Point"}
}