{
  "type": "Feature",
  "properties": {
    "iso:country":"CH",
    "sg:address":"Via Santa Maria 58 6596 Gordola. Postfach Caselle Postale 116",
    "sg:city":"Gordola",
    "sg:orig_category":"Sanit\u00e4r U Heizungsinstallation Sonstiger spezialisierter Hoch U Tiefbau",
    "sg:phone":"+41 91 745 24 61",
    "sg:postcode":"6596",
    "sg:province":"Ticino",
    "wof:name":"Kr\u00fcger & Co Ag",
    "wof:placetype":"venue"
},
  "geometry": {"coordinates":[8.8650569916,46.1717414856],"type":"Point"}
}