{
  "type": "Feature",
  "properties": {
    "iso:country":"CH",
    "sg:address":"Zeughausgasse 22 3011 Bern. Postfach",
    "sg:city":"Bern",
    "sg:classifiers":[
        {
            "category":"Communications",
            "subcategory":"Radio Station",
            "type":"Services"
        }
    ],
    "sg:phone":"+41 31 318 18 50",
    "sg:postcode":"3011",
    "sg:province":"Bern",
    "sg:tags":[
        "fernsehanstalten",
        "u"
    ],
    "wof:name":"Maxomedia Gmbh",
    "wof:placetype":"venue"
},
  "geometry": {"coordinates":[7.4449501038,46.9491500854],"type":"Point"}
}