{
  "type": "Feature",
  "properties": {
    "iso:country":"CH",
    "sg:address":"Wiesenstrasse 18",
    "sg:city":"Winterthur",
    "sg:orig_category":"Vorschulen, Kinderg\u00e4rten",
    "sg:phone":"+41 52 222 27 03",
    "sg:postcode":"8400",
    "sg:province":"Z\u00fcrich",
    "wof:name":"Kindergarten Wiesenstrasse",
    "wof:placetype":"venue"
},
  "geometry": {"coordinates":[8.7150363922,47.5078277588],"type":"Point"}
}