{
  "type": "Feature",
  "properties": {
    "iso:country":"CH",
    "sg:address":"Harschwendi",
    "sg:city":"Waldstatt",
    "sg:classifiers":[
        {
            "category":"Restaurant",
            "type":"Food & Drink"
        }
    ],
    "sg:phone":"+41 41 850 10 25",
    "sg:postcode":"9104",
    "sg:province":"Appenzell Ausserrhoden",
    "wof:name":"Restaurant Adler",
    "wof:placetype":"venue"
},
  "geometry": {"coordinates":[8.4413928986,47.0811882019],"type":"Point"}
}