{
  "type": "Feature",
  "properties": {
    "iso:country":"CH",
    "sg:address":"Freiestrasse 131",
    "sg:city":"Z\u00fcrich",
    "sg:orig_category":"\u00dcbersetzungsb\u00fcros",
    "sg:phone":"+41 13834396",
    "sg:postcode":"8032",
    "sg:province":"Z\u00fcrich",
    "wof:name":"Dr.ahmad Yakout Uebersetzungen",
    "wof:placetype":"venue"
},
  "geometry": {"coordinates":[8.5610542297,47.3647346497],"type":"Point"}
}