{
  "type": "Feature",
  "properties": {
    "iso:country":"CH",
    "sg:address":"2926",
    "sg:city":"Boncourt",
    "sg:orig_category":"Pensionskassen",
    "sg:phone":"+41 26 912 96 96",
    "sg:postcode":"2926",
    "sg:province":"Jura",
    "wof:name":"Fonds Social De La Soci\u00e9t\u00e9 Electrothermique De La Tour-de-tr\u00eame.",
    "wof:placetype":"venue"
},
  "geometry": {"coordinates":[7.0663948059,46.6079711914],"type":"Point"}
}