{
  "type": "Feature",
  "properties": {
    "iso:country":"CH",
    "sg:address":"Grossfeldstrasse 74a",
    "sg:city":"Sargans",
    "sg:orig_category":"Schreib U \u00dcbersetzungsb\u00fcros",
    "sg:phone":"+41 79 610 44 86",
    "sg:postcode":"7320",
    "sg:province":"St. Gallen",
    "wof:name":"Krohn Bauadministration",
    "wof:placetype":"venue"
},
  "geometry": {"coordinates":[9.4335174561,47.0474815369],"type":"Point"}
}