{
  "type": "Feature",
  "properties": {
    "iso:country":"CH",
    "sg:address":"Linckweg 23",
    "sg:city":"Zollikofen",
    "sg:classifiers":[
        {
            "category":"Insurance",
            "subcategory":"Insurance Agent",
            "type":"Services"
        }
    ],
    "sg:phone":"+41 71 385 73 80",
    "sg:postcode":"3052",
    "sg:province":"Bern",
    "sg:tags":[
        "versicherungsagenturen",
        "-broker"
    ],
    "wof:name":"Die Mobiliar Versicherungen & Vorsorge",
    "wof:placetype":"venue"
},
  "geometry": {"coordinates":[9.273645401,47.4411582947],"type":"Point"}
}