{
  "type": "Feature",
  "properties": {
    "iso:country":"CH",
    "sg:address":"Einsiedlerstrasse 284 8810 Horgen. Postfach",
    "sg:city":"Horgen",
    "sg:orig_category":"Grosshandel mit Textilien",
    "sg:postcode":"8810",
    "sg:province":"Z\u00fcrich",
    "wof:name":"G\u00d6kg\u00dcrler T. International Merchandising Office",
    "wof:placetype":"venue"
},
  "geometry": {"coordinates":[8.6040210724,47.2492179871],"type":"Point"}
}