{
  "type": "Feature",
  "properties": {
    "iso:country":"CH",
    "sg:address":"Witimatte",
    "sg:city":"Lauterbrunnen",
    "sg:orig_category":"Blumen U Zierpflanzenbau",
    "sg:phone":"+41 33 855 19 19",
    "sg:postcode":"3822",
    "sg:province":"Bern",
    "wof:name":"Urs & Elsbeth Heiniger Friedhofg\u00e4rtnerei",
    "wof:placetype":"venue"
},
  "geometry": {"coordinates":[7.912918,46.591827],"type":"Point"}
}