{
  "type": "Feature",
  "properties": {
    "iso:country":"CH",
    "sg:address":"Freilagerstrasse 47 8043 Z\u00fcrich. Postfach 105",
    "sg:city":"Z\u00fcrich",
    "sg:orig_category":"Detailhandel mit M\u00f6beln U Haushaltsgegenst\u00e4nden Grosshandel mit M\u00f6beln, Wohnbedarf, Teppichen U Bode",
    "sg:phone":"+41 14012300",
    "sg:postcode":"8043",
    "sg:province":"Z\u00fcrich",
    "wof:name":"Ramezani Moghadam Oriental Carpets",
    "wof:placetype":"venue"
},
  "geometry": {"coordinates":[8.4902496338,47.3798408508],"type":"Point"}
}