{
  "type": "Feature",
  "properties": {
    "iso:country":"CH",
    "sg:address":"Grand'rue",
    "sg:city":"Yens",
    "sg:orig_category":"Elektroinstallation",
    "sg:phone":"+41 19290910",
    "sg:postcode":"1137",
    "wof:name":"Daniel F\u00e4h F\u00e4h Elektro",
    "wof:placetype":"venue"
},
  "geometry": {"coordinates":[8.7395153046,47.2749900818],"type":"Point"}
}