{
  "type": "Feature",
  "properties": {
    "iso:country":"CH",
    "sg:address":"Place Des Balances 15",
    "sg:city":"Echallens",
    "sg:orig_category":"Detailhandel mit Getr\u00e4nken Grosshandel mit Getr\u00e4nken",
    "sg:phone":"+41 21 881 11 48",
    "sg:postcode":"1040",
    "sg:province":"Vaud",
    "wof:name":"Caves G. Nicod",
    "wof:placetype":"venue"
},
  "geometry": {"coordinates":[6.6348462105,46.642036438],"type":"Point"}
}