{
  "type": "Feature",
  "properties": {
    "iso:country":"CH",
    "sg:address":"Turnhallestrasse 5 4912 Aarwangen. Postfach",
    "sg:city":"Aarwangen",
    "sg:orig_category":"Maurerarbeiten Sonstiger spezialisierter Hoch U Tiefbau",
    "sg:phone":"+41 62 923 64 72",
    "sg:postcode":"4912",
    "sg:province":"Bern",
    "wof:name":"Maurergesch\u00e4ft Gerber Martin Gmbh",
    "wof:placetype":"venue"
},
  "geometry": {"coordinates":[7.7703499794,47.237449646],"type":"Point"}
}