{
  "type": "Feature",
  "properties": {
    "iso:country":"CH",
    "sg:address":"Chemin Du Vallon 1",
    "sg:city":"Bussigny-lausanne",
    "sg:orig_category":"Unclassifiable Establishments",
    "sg:postcode":"1030",
    "sg:province":"Vaud",
    "wof:name":"Tekno Parts Ltd Cycles & Motos",
    "wof:placetype":"venue"
},
  "geometry": {"coordinates":[6.5512981415,46.5465202332],"type":"Point"}
}