{
  "type": "Feature",
  "properties": {
    "iso:country":"CH",
    "sg:address":"Pocobelli Via 14",
    "sg:city":"Melide",
    "sg:orig_category":"Sonstiger Grosshandel",
    "sg:postcode":"6815",
    "sg:province":"Ticino",
    "wof:name":"Folio Consultancy And Investment Limited, Majuro (isole Marshall), Filiale Di Melide",
    "wof:placetype":"venue"
},
  "geometry": {"coordinates":[8.9459056854,45.952922821],"type":"Point"}
}