{
  "type": "Feature",
  "properties": {
    "iso:country":"CH",
    "sg:address":"Borghetto Via 9",
    "sg:city":"Giubiasco",
    "sg:orig_category":"Sonstiger Grosshandel",
    "sg:postcode":"6512",
    "sg:province":"Ticino",
    "wof:name":"Airport Gazebo Sa",
    "wof:placetype":"venue"
},
  "geometry": {"coordinates":[9.0122241974,46.1738243103],"type":"Point"}
}