{
  "type": "Feature",
  "properties": {
    "iso:country":"CH",
    "sg:address":"Via Camara 58",
    "sg:city":"Breganzona",
    "sg:orig_category":"Architekturb\u00fcros",
    "sg:phone":"+41 91 966 53 04",
    "sg:postcode":"6932",
    "sg:province":"Ticino",
    "wof:name":"Paul Frauchiger Studio D'architettura",
    "wof:placetype":"venue"
},
  "geometry": {"coordinates":[8.929948,46.009666],"type":"Point"}
}