{
  "type": "Feature",
  "properties": {
    "iso:country":"CH",
    "sg:address":"Via Bossi 6",
    "sg:city":"Lugano",
    "sg:orig_category":"Grosshandel mit Parf\u00fcmerieartikeln U K\u00f6rperpflegemitteln Grosshandel mit pharmazeutischen Erzeugniss",
    "sg:phone":"+41 41 260 58 75",
    "sg:postcode":"6900",
    "sg:province":"Ticino",
    "wof:name":"Bio-science Products Ag",
    "wof:placetype":"venue"
},
  "geometry": {"coordinates":[8.2817163467,47.0747947693],"type":"Point"}
}