{
  "type": "Feature",
  "properties": {
    "iso:country":"CH",
    "sg:address":"Rosenb\u00fchlstrasse 32",
    "sg:city":"Z\u00fcrich",
    "sg:orig_category":"\u00dcbersetzungsb\u00fcros",
    "sg:phone":"+41 12525852",
    "sg:postcode":"8044",
    "sg:province":"Z\u00fcrich",
    "wof:name":"Translator Uebersetzungen B.francisco & B.m\u00fcller",
    "wof:placetype":"venue"
},
  "geometry": {"coordinates":[8.5678663254,47.3794784546],"type":"Point"}
}