{
  "type": "Feature",
  "properties": {
    "iso:country":"CH",
    "sg:address":"Cagetto Via",
    "sg:city":"Brissago",
    "sg:orig_category":"Unternehmensberatung",
    "sg:phone":"+41 91 780 51 60",
    "sg:postcode":"6614",
    "sg:province":"Ticino",
    "wof:name":"Riegel Sa",
    "wof:placetype":"venue"
},
  "geometry": {"coordinates":[8.6954078674,46.1034164429],"type":"Point"}
}