{
  "type": "Feature",
  "properties": {
    "iso:country":"CH",
    "sg:address":"Route Des Marches 6 1636 Broc Case Postale 36",
    "sg:city":"Broc",
    "sg:orig_category":"Sportvereine Ballsport Tennis",
    "sg:phone":"+41 26 912 76 06",
    "sg:postcode":"1636",
    "sg:province":"Fribourg",
    "wof:name":"Tennisclub Bulle",
    "wof:placetype":"venue"
},
  "geometry": {"coordinates":[7.0232000351,46.6070785522],"type":"Point"}
}