{
  "type": "Feature",
  "properties": {
    "iso:country":"CH",
    "sg:address":"Sismondi Rue 3 1201 Gen\u00e8ve. Postfach",
    "sg:city":"Gen\u00e8ve",
    "sg:orig_category":"Reiseb\u00fcros U Reiseveranstalter",
    "sg:postcode":"1201",
    "sg:province":"Gen\u00e8ve",
    "wof:name":"Baraka Voyages, Laurent Fallet",
    "wof:placetype":"venue"
},
  "geometry": {"coordinates":[6.1476430893,46.2097854614],"type":"Point"}
}