{
  "type": "Feature",
  "properties": {
    "iso:country":"CH",
    "sg:address":"3124",
    "sg:city":"Belpberg",
    "sg:orig_category":"Detailhandel mit Waren verschiedener Art, Hauptrichtung Nahrungsmittel",
    "sg:phone":"+41 31 819 21 69",
    "sg:postcode":"3124",
    "sg:province":"Bern",
    "wof:name":"Landwirtschaftliche Genossenschaft Belpberg",
    "wof:placetype":"venue"
},
  "geometry": {"coordinates":[7.5252900124,46.8671188354],"type":"Point"}
}