{
  "type": "Feature",
  "properties": {
    "iso:country":"CH",
    "sg:address":"Bachlettenstrasse 30 4054 Basel. Postfach",
    "sg:city":"Basel",
    "sg:orig_category":"Erbringung von Dienstleistungen f\u00fcr Unternehmen",
    "sg:phone":"+41 61 281 91 14",
    "sg:postcode":"4051",
    "sg:province":"Basel-Stadt",
    "wof:name":"Dillier Oswald Modell, Prototypenbau Usw",
    "wof:placetype":"venue"
},
  "geometry": {"coordinates":[7.5796542168,47.549621582],"type":"Point"}
}