{
  "type": "Feature",
  "properties": {
    "iso:country":"CH",
    "sg:address":"Dorfstrasse 5",
    "sg:city":"Schindellegi",
    "sg:orig_category":"Detailhandel mit Fleisch U Fleischwaren",
    "sg:phone":"+41 17850181",
    "sg:postcode":"8834",
    "sg:province":"Schwyz",
    "wof:name":"Metzgerei Ochsen, B\u00fcrgi Christoph",
    "wof:placetype":"venue"
},
  "geometry": {"coordinates":[8.7115497589,47.1747360229],"type":"Point"}
}