{
  "type": "Feature",
  "properties": {
    "iso:country":"CH",
    "sg:address":"Picardiestrasse 3",
    "sg:city":"Sch\u00f6ftland",
    "sg:orig_category":"Wirtschaftspr\u00fcfung, Steuerberatung U Treuhand",
    "sg:phone":"+41 61 402 04 37",
    "sg:postcode":"5040",
    "sg:province":"Aargau",
    "wof:name":"Atg Getzmann",
    "wof:placetype":"venue"
},
  "geometry": {"coordinates":[7.5650892258,47.5208091736],"type":"Point"}
}