{
  "type": "Feature",
  "properties": {
    "iso:country":"CH",
    "sg:address":"J\u00f6ndliweg 5",
    "sg:city":"Rothrist",
    "sg:orig_category":"G\u00fcterbef\u00f6rderung im Strassenverkehr",
    "sg:phone":"+41 62 794 14 65",
    "sg:postcode":"4852",
    "sg:province":"Aargau",
    "wof:name":"Hans-rudolf Schmid Transporte",
    "wof:placetype":"venue"
},
  "geometry": {"coordinates":[7.9158859253,47.3034706116],"type":"Point"}
}