{
  "type": "Feature",
  "properties": {
    "iso:country":"CH",
    "sg:address":"B\u00e4zweg 14",
    "sg:city":"Andermatt",
    "sg:orig_category":"Bau U Wohngenossenschaften",
    "sg:postcode":"6490",
    "sg:province":"Uri",
    "wof:name":"Bau-& Mietergen.andermatt",
    "wof:placetype":"venue"
},
  "geometry": {"coordinates":[8.591939,46.634548],"type":"Point"}
}