{
  "type": "Feature",
  "properties": {
    "iso:country":"CH",
    "sg:address":"8574",
    "sg:city":"Illighausen",
    "sg:orig_category":"Primarschulen",
    "sg:phone":"+41 71 633 13 39",
    "sg:postcode":"8574",
    "sg:province":"Thurgau",
    "wof:name":"Primarschule",
    "wof:placetype":"venue"
},
  "geometry": {"coordinates":[9.1571903229,47.5665817261],"type":"Point"}
}