{
  "type": "Feature",
  "properties": {
    "iso:country":"CH",
    "sg:address":"Dufourstrasse 131",
    "sg:city":"Z\u00fcrich",
    "sg:classifiers":[
        {
            "category":"Personal",
            "subcategory":"Nail Salon",
            "type":"Services"
        }
    ],
    "sg:phone":"+41 79 208 01 11",
    "sg:postcode":"8008",
    "sg:province":"Z\u00fcrich",
    "sg:tags":[
        "manicure"
    ],
    "wof:name":"Cats Nail Studio, Irene Peter",
    "wof:placetype":"venue"
},
  "geometry": {"coordinates":[8.5532369614,47.3570861816],"type":"Point"}
}