{
  "type": "Feature",
  "properties": {
    "iso:country":"CH",
    "sg:address":"Rychenbergstrasse 135",
    "sg:city":"Winterthur",
    "sg:orig_category":"K\u00fcnstlerische Schulen",
    "sg:phone":"+41 52 242 58 72",
    "sg:postcode":"8400",
    "sg:province":"Z\u00fcrich",
    "wof:name":"Sonja Puppikofer Musikschule",
    "wof:placetype":"venue"
},
  "geometry": {"coordinates":[8.7396917343,47.5047721863],"type":"Point"}
}