{
  "type": "Feature",
  "properties": {
    "iso:country":"CH",
    "sg:address":"Rue Principale 20 B",
    "sg:city":"Cormoret",
    "sg:orig_category":"Sonstiger Grosshandel",
    "sg:phone":"+41 32 944 15 47",
    "sg:postcode":"2612",
    "sg:province":"Bern",
    "wof:name":"K\u00fcnzi Daniel",
    "wof:placetype":"venue"
},
  "geometry": {"coordinates":[7.0560040474,47.1748008728],"type":"Point"}
}