{
  "type": "Feature",
  "properties": {
    "iso:country":"CH",
    "sg:address":"Frauholzstrasse 9b",
    "sg:city":"Steinen",
    "sg:orig_category":"Fachdetailhandel in Verkaufsr\u00e4umen Grosshandel mit Sportartikeln",
    "sg:phone":"+41 41 671 02 71",
    "sg:postcode":"6422",
    "sg:province":"Schwyz",
    "wof:name":"Sky-sports Ag Gleitschirme Import & Vertrieb",
    "wof:placetype":"venue"
},
  "geometry": {"coordinates":[8.6063766479,47.0474052429],"type":"Point"}
}