{
  "type": "Feature",
  "properties": {
    "iso:country":"CH",
    "sg:address":"Bankstrasse 21",
    "sg:city":"Glarus",
    "sg:orig_category":"Unclassifiable Establishments",
    "sg:postcode":"8750",
    "sg:province":"Glarus",
    "wof:name":"Valentin Feubli Gmbh Architektur-b\u00fcro",
    "wof:placetype":"venue"
},
  "geometry": {"coordinates":[8.6508302689,46.8718147278],"type":"Point"}
}