{
  "type": "Feature",
  "properties": {
    "addr:full":"Freiburgstrasse 11 1712 Tafers. Postfach Tafers Fribourg 1712",
    "addr:housenumber":"11",
    "addr:postcode":"1712 tafers. postfach;1712",
    "addr:street":"Freiburgstrasse",
    "iso:country":"CH",
    "sg:address":"Freiburgstrasse 11 1712 Tafers. Postfach",
    "sg:city":"Tafers",
    "sg:orig_category":"Architektur U Ingenieurb\u00fcros Architekturb\u00fcros",
    "sg:phone":"+41 26 494 31 95",
    "sg:postcode":"1712",
    "sg:province":"Fribourg",
    "wof:name":"Favre Behausungen Gmbh Architekturplanungen Von \u00f6konomischen, \u00f6kologischen Wohnungs Und Gewerbebauten Sowie Landwirtschaftliche Bauten Usw",
    "wof:placetype":"venue"
},
  "geometry": {"coordinates":[7.212422,46.814392],"type":"Point"}
}