{
  "type": "Feature",
  "properties": {
    "iso:country":"CH",
    "sg:address":"Lusciago Via 15a 6616 Losone. Postfach",
    "sg:city":"Intragna",
    "sg:orig_category":"Herstellung von medizinischen U chirurgischen Ger\u00e4ten sowie orthop\u00e4dischen Vorrichtungen",
    "sg:phone":"+41 22 349 71 22",
    "sg:postcode":"6655",
    "sg:province":"Ticino",
    "wof:name":"Unident Sa",
    "wof:placetype":"venue"
},
  "geometry": {"coordinates":[6.1644659042,46.190120697],"type":"Point"}
}