{
  "type": "Feature",
  "properties": {
    "iso:country":"CH",
    "sg:address":"Bendel",
    "sg:city":"Ebnat-kappel",
    "sg:classifiers":[
        {
            "category":"Restaurant",
            "type":"Food & Drink"
        }
    ],
    "sg:phone":"+41 71 993 17 02",
    "sg:postcode":"9642",
    "sg:province":"St. Gallen",
    "wof:name":"Restaurant Sternen Bendel",
    "wof:placetype":"venue"
},
  "geometry": {"coordinates":[9.1654500961,47.265209198],"type":"Point"}
}