{
  "type": "Feature",
  "properties": {
    "iso:country":"CH",
    "sg:address":"Usine De L'islettaz 1305 Penthalaz. Postfach",
    "sg:city":"Penthalaz",
    "sg:orig_category":"Herstellung von Drahtwaren Herstellung von medizinischen U chirurgischen Ger\u00e4ten sowie orthop\u00e4dische",
    "sg:phone":"+41 21 861 89 18",
    "sg:postcode":"1305",
    "sg:province":"Vaud",
    "wof:name":"Metalor Technologies Medical Sa",
    "wof:placetype":"venue"
},
  "geometry": {"coordinates":[6.5224580765,46.6078414917],"type":"Point"}
}