{
  "type": "Feature",
  "properties": {
    "iso:country":"CH",
    "sg:address":"Lessingstrasse 11",
    "sg:city":"Z\u00fcrich",
    "sg:classifiers":[
        {
            "category":"Communications",
            "subcategory":"Radio Station",
            "type":"Services"
        }
    ],
    "sg:phone":"+41 12529000",
    "sg:postcode":"8002",
    "sg:province":"Z\u00fcrich",
    "sg:tags":[
        "fernsehanstalten",
        "u"
    ],
    "wof:name":"Goldbach Media Ag",
    "wof:placetype":"venue"
},
  "geometry": {"coordinates":[8.5741252899,47.3273048401],"type":"Point"}
}