{
  "type": "Feature",
  "properties": {
    "iso:country":"CH",
    "sg:address":"Goldbrunnenstrasse 144 8038 Z\u00fcrich. Postfach 862",
    "sg:city":"Z\u00fcrich",
    "sg:orig_category":"Detailhandel mit M\u00f6beln U Haushaltsgegenst\u00e4nden Innenarchitekturb\u00fcros",
    "sg:phone":"+41 14615845",
    "sg:postcode":"8055",
    "sg:province":"Z\u00fcrich",
    "wof:name":"Faschian Rolf Design",
    "wof:placetype":"venue"
},
  "geometry": {"coordinates":[8.5113792419,47.371799469],"type":"Point"}
}