{
  "type": "Feature",
  "properties": {
    "iso:country":"CH",
    "sg:address":"Industriestrasse 29",
    "sg:city":"Dietlikon",
    "sg:orig_category":"Unclassifiable Establishments",
    "sg:postcode":"8305",
    "sg:province":"Z\u00fcrich",
    "wof:name":"Tp Consulting Gmbh",
    "wof:placetype":"venue"
},
  "geometry": {"coordinates":[8.8529558182,47.1920051575],"type":"Point"}
}