{
  "type": "Feature",
  "properties": {
    "iso:country":"CH",
    "sg:address":"Austrasse 22",
    "sg:city":"Z\u00fcrich",
    "sg:orig_category":"Detailhandel mit M\u00f6beln Innenausbau",
    "sg:phone":"+41 41 988 12 27",
    "sg:postcode":"8045",
    "sg:province":"Z\u00fcrich",
    "wof:name":"Gregor St\u00f6ckli M\u00f6belgesch\u00e4ft & H\u00fcsler Nest",
    "wof:placetype":"venue"
},
  "geometry": {"coordinates":[7.9396719933,47.1366424561],"type":"Point"}
}