{
  "type": "Feature",
  "properties": {
    "iso:country":"CH",
    "sg:address":"Davidstrasse 19",
    "sg:city":"St.gallen",
    "sg:orig_category":"Druck ohne Zeitungsdruck Offsetdruck",
    "sg:phone":"+41 71 223 42 49",
    "sg:postcode":"9000",
    "sg:province":"St. Gallen",
    "wof:name":"Wenger's Schnelldruck",
    "wof:placetype":"venue"
},
  "geometry": {"coordinates":[9.3702573776,47.4206352234],"type":"Point"}
}