{
  "type": "Feature",
  "properties": {
    "iso:country":"CH",
    "sg:address":"Am Krayenrain 27",
    "sg:city":"Basel",
    "sg:orig_category":"Detailhandel mit B\u00fcchern, Zeitungen, Schreib U Papeteriewaren Detailhandel mit Schreib U Papeteriewa",
    "sg:phone":"+41 61 321 72 50",
    "sg:postcode":"4056",
    "sg:province":"Basel-Stadt",
    "wof:name":"Papeterie Hug Elisabeth",
    "wof:placetype":"venue"
},
  "geometry": {"coordinates":[7.575339,47.565197],"type":"Point"}
}