{
  "type": "Feature",
  "properties": {
    "iso:country":"CH",
    "sg:address":"Beim Einschnitt 25",
    "sg:city":"Laupersdorf",
    "sg:classifiers":[
        {
            "category":"Communications",
            "subcategory":"Film & Video Production",
            "type":"Services"
        }
    ],
    "sg:phone":"+41 62 398 22 05",
    "sg:postcode":"4712",
    "sg:province":"Solothurn",
    "sg:tags":[
        "net",
        "barrier"
    ],
    "wof:name":"Seilerei Berger Gmbh",
    "wof:placetype":"venue"
},
  "geometry": {"coordinates":[7.658364,47.311687],"type":"Point"}
}