{
  "type": "Feature",
  "properties": {
    "iso:country":"CH",
    "sg:city":"Vogorno",
    "sg:classifiers":[
        {
            "category":"Banks & Credit Unions",
            "subcategory":"Bank",
            "type":"Services"
        }
    ],
    "sg:phone":"+41 4193673857",
    "sg:postcode":"6632",
    "sg:province":"Ticino",
    "wof:name":"Banca Raiffeisen",
    "wof:placetype":"venue"
},
  "geometry": {"coordinates":[8.856679,46.223572],"type":"Point"}
}