{
  "type": "Feature",
  "properties": {
    "iso:country":"CH",
    "sg:address":"Linthlistrasse 11",
    "sg:city":"Oberurnen",
    "sg:orig_category":"Detailhandel mit Beleuchtungs U Haushaltsgegenst\u00e4nden Textilgewerbe",
    "sg:phone":"+41 71 222 81 61",
    "sg:postcode":"8868",
    "sg:province":"Glarus",
    "wof:name":"Hermann Hollenstein",
    "wof:placetype":"venue"
},
  "geometry": {"coordinates":[9.380916,47.424057],"type":"Point"}
}