{
  "type": "Feature",
  "properties": {
    "iso:country":"CH",
    "sg:address":"Gorges Rue Des 8",
    "sg:city":"Court",
    "sg:orig_category":"Herstellung von Werkzeugen",
    "sg:postcode":"2738",
    "sg:province":"Bern",
    "wof:name":"Delmeco Sa",
    "wof:placetype":"venue"
},
  "geometry": {"coordinates":[7.3414521217,47.2410430908],"type":"Point"}
}