{
  "type": "Feature",
  "properties": {
    "iso:country":"CH",
    "sg:address":"Vedeggio Via Al 1",
    "sg:city":"Manno",
    "sg:orig_category":"Schiffsbau ohne Boots U Yachtbau",
    "sg:postcode":"6928",
    "sg:province":"Ticino",
    "wof:name":"Bs Bulk Shipping & Trade (international) Limited, Dublino, Succursale Di Manno",
    "wof:placetype":"venue"
},
  "geometry": {"coordinates":[8.9243679047,46.0362014771],"type":"Point"}
}