{
  "type": "Feature",
  "properties": {
    "iso:country":"CH",
    "sg:address":"Rte De St Cergue 295",
    "sg:city":"Nyon",
    "sg:classifiers":[
        {
            "category":"Autos & Motor Vehicles",
            "subcategory":"Automobile Sales",
            "type":"Retail Goods"
        }
    ],
    "sg:phone":"+41 22 544 28 00",
    "sg:postcode":"1260",
    "sg:province":"Vaud",
    "sg:tags":[
        "equipment",
        "motor-cars",
        "transport"
    ],
    "wof:name":"Acacias Motors Sa",
    "wof:placetype":"venue"
},
  "geometry": {"coordinates":[6.1300530434,46.1925201416],"type":"Point"}
}