{
  "type": "Feature",
  "properties": {
    "iso:country":"CH",
    "sg:address":"Welletenstrasse 376",
    "sg:city":"Biberstein",
    "sg:orig_category":"Bau U Wohngenossenschaften",
    "sg:phone":"+41 71 245 17 17",
    "sg:postcode":"5023",
    "sg:province":"Aargau",
    "wof:name":"Wohnbaugen.blumenwies",
    "wof:placetype":"venue"
},
  "geometry": {"coordinates":[9.392027,47.440056],"type":"Point"}
}