{
  "type": "Feature",
  "properties": {
    "iso:country":"CH",
    "sg:address":"W\u00fclflingerstrasse 42",
    "sg:city":"Winterthur",
    "sg:orig_category":"Bezirks, Sekundar, Realschulen, Oberstufe der Primarschulen Primarschulen",
    "sg:phone":"+41 52 222 82 71",
    "sg:postcode":"8400",
    "sg:province":"Z\u00fcrich",
    "wof:name":"Primarschule & Oberstufe W\u00fclflingerstrasse",
    "wof:placetype":"venue"
},
  "geometry": {"coordinates":[8.716574,47.505787],"type":"Point"}
}