{
  "type": "Feature",
  "properties": {
    "iso:country":"CH",
    "sg:address":"Rue Des Eaux-vives 16",
    "sg:city":"Gen\u00e8ve",
    "sg:orig_category":"Fachdetailhandel mit pharmazeutischen Produkten",
    "sg:phone":"+41 22 736 15 01",
    "sg:postcode":"1207",
    "sg:province":"Gen\u00e8ve",
    "wof:name":"Pharmacie Des Eaux-vives Celardin Mme I.",
    "wof:placetype":"venue"
},
  "geometry": {"coordinates":[6.1582431793,46.2038955688],"type":"Point"}
}