{
  "type": "Feature",
  "properties": {
    "iso:country":"CH",
    "sg:address":"Schwarzwaldallee 44",
    "sg:city":"Basel",
    "sg:orig_category":"Massagestudios",
    "sg:phone":"+41 61 322 50 00",
    "sg:postcode":"4058",
    "sg:province":"Basel-Stadt",
    "wof:name":"Raymond Engler Klassische Massage",
    "wof:placetype":"venue"
},
  "geometry": {"coordinates":[7.6114377975,47.5606498718],"type":"Point"}
}