{
  "type": "Feature",
  "properties": {
    "addr:full":"Z\u00fcrcherstrasse 12 8400 Winterthur. Postfach 414 Winterthur Z\u00fcrich 8401",
    "addr:housenumber":"12;414",
    "addr:postcode":"8400;8401",
    "addr:street":"Zuercherstrasse;Postfach",
    "iso:country":"CH",
    "sg:address":"Z\u00fcrcherstrasse 12 8400 Winterthur. Postfach 414",
    "sg:city":"Winterthur",
    "sg:orig_category":"Architektur U Ingenieurb\u00fcros Maurerarbeiten",
    "sg:phone":"+41 71 642 42 22",
    "sg:postcode":"8401",
    "sg:province":"Z\u00fcrich",
    "wof:name":"Amsas Gmbh",
    "wof:placetype":"venue"
},
  "geometry": {"coordinates":[9.19918,47.52166],"type":"Point"}
}