{
  "type": "Feature",
  "properties": {
    "iso:country":"CH",
    "sg:address":"Bahnhofstrasse 19",
    "sg:city":"Naters",
    "sg:orig_category":"Handels-H\u00e4user U Gesellschaften",
    "sg:postcode":"3904",
    "sg:province":"Valais",
    "wof:name":"Naters Cti Coating, Trading And Investment Ag",
    "wof:placetype":"venue"
},
  "geometry": {"coordinates":[7.9852170944,46.3236236572],"type":"Point"}
}