{
  "type": "Feature",
  "properties": {
    "iso:country":"CH",
    "sg:address":"Hauptstrasse 22",
    "sg:city":"Bubendorf",
    "sg:orig_category":"Grosshandel mit Holz U Baustoffen",
    "sg:phone":"+41 61 931 15 46",
    "sg:postcode":"4416",
    "sg:province":"Basel-Landschaft",
    "wof:name":"Erb Ag, Bauspezialprodukte - Baumaterialien",
    "wof:placetype":"venue"
},
  "geometry": {"coordinates":[7.7377300262,47.4540214539],"type":"Point"}
}