{
  "type": "Feature",
  "properties": {
    "iso:country":"CH",
    "sg:address":"Baslerstrasse 24",
    "sg:city":"Allschwil",
    "sg:orig_category":"Grosshandel mit chemischen Erzeugnissen Herstellung von sonstigen chemischen Erzeugnissen",
    "sg:phone":"+41 61 482 34 32",
    "sg:postcode":"4123",
    "sg:province":"Basel-Landschaft",
    "wof:name":"Langer Ag",
    "wof:placetype":"venue"
},
  "geometry": {"coordinates":[7.5384640694,47.5515441895],"type":"Point"}
}