{
  "type": "Feature",
  "properties": {
    "iso:country":"CH",
    "sg:address":"Collegio Via 6",
    "sg:city":"Ascona",
    "sg:orig_category":"Architektur U Ingenieurb\u00fcros",
    "sg:postcode":"6612",
    "sg:province":"Ticino",
    "wof:name":"Swibaco Gmbh",
    "wof:placetype":"venue"
},
  "geometry": {"coordinates":[8.989321,47.474823],"type":"Point"}
}