{
  "type": "Feature",
  "properties": {
    "iso:country":"CH",
    "sg:address":"Oberdorf 16d",
    "sg:city":"Roggenburg",
    "sg:orig_category":"Fussboden, Fliesen U Plattenlegerei, Tapeziererei",
    "sg:phone":"+41 56 631 14 94",
    "sg:postcode":"2814",
    "sg:province":"Basel-Landschaft",
    "wof:name":"Peter Meyer Bodenbel\u00e4ge",
    "wof:placetype":"venue"
},
  "geometry": {"coordinates":[8.3487443924,47.3528862],"type":"Point"}
}