{
  "type": "Feature",
  "properties": {
    "iso:country":"CH",
    "sg:address":"B\u00fcessikon",
    "sg:city":"Baar",
    "sg:orig_category":"Kalb U Schweine-M\u00e4sterei U Zucht",
    "sg:phone":"+41 41 921 33 72",
    "sg:postcode":"6340",
    "sg:province":"Zug",
    "wof:name":"Schweinemast B\u00fcssikon Ag",
    "wof:placetype":"venue"
},
  "geometry": {"coordinates":[8.5576782227,47.2178878784],"type":"Point"}
}