{
  "type": "Feature",
  "properties": {
    "iso:country":"CH",
    "sg:address":"M\u00fchlegasse 13 8001 Z\u00fcrich. Postfach",
    "sg:city":"Z\u00fcrich",
    "sg:orig_category":"Wirtschaftsverb\u00e4nde Landwirtschaft",
    "sg:phone":"+41 12614488",
    "sg:postcode":"8025",
    "wof:name":"Landdienst",
    "wof:placetype":"venue"
},
  "geometry": {"coordinates":[8.5441865921,47.374370575],"type":"Point"}
}