{
  "type": "Feature",
  "properties": {
    "iso:country":"CH",
    "sg:address":"Allmendzentrum 2",
    "sg:city":"Rorbas",
    "sg:orig_category":"Nationale Postdienste",
    "sg:phone":"+41 18650700",
    "sg:postcode":"8427",
    "sg:province":"Z\u00fcrich",
    "wof:name":"Die Schweizerische Post",
    "wof:placetype":"venue"
},
  "geometry": {"coordinates":[8.5804843903,47.5312004089],"type":"Point"}
}