{
  "type": "Feature",
  "properties": {
    "iso:country":"CH",
    "sg:address":"L\u00e4delistrasse 12",
    "sg:city":"Luzern",
    "sg:orig_category":"Rolladen- and Storenmontage",
    "sg:phone":"+41 41 240 88 13",
    "sg:postcode":"6003",
    "sg:province":"Luzern",
    "wof:name":"Bruno Castelletti Rolladen Storen",
    "wof:placetype":"venue"
},
  "geometry": {"coordinates":[8.294002533,47.0539321899],"type":"Point"}
}