{
  "type": "Feature",
  "properties": {
    "iso:country":"CH",
    "sg:address":"Bundesplatz 2 3011 Bern. Postfach",
    "sg:city":"Bern",
    "sg:orig_category":"Sonstiger Fachdetailhandel in Verkaufsr\u00e4umen",
    "sg:phone":"+41 844 800 844",
    "sg:postcode":"3001",
    "sg:province":"Bern",
    "wof:name":"Schweiz.kreditanstalt Numismatische Abteilung",
    "wof:placetype":"venue"
},
  "geometry": {"coordinates":[7.444466114,46.9474029541],"type":"Point"}
}