{
  "type": "Feature",
  "properties": {
    "iso:country":"CH",
    "sg:address":"1405",
    "sg:city":"Pomy",
    "sg:orig_category":"Detailhandel mit Waren verschiedener Art, Hauptrichtung Nahrungsmittel",
    "sg:postcode":"1405",
    "sg:province":"Vaud",
    "wof:name":"Syndicat Agricole Et D'\u00e9levage De Pomy.",
    "wof:placetype":"venue"
},
  "geometry": {"coordinates":[6.6688499451,46.7578010559],"type":"Point"}
}