{
  "type": "Feature",
  "properties": {
    "iso:country":"CH",
    "sg:address":"Kanalstrasse 21",
    "sg:city":"Mollis",
    "sg:orig_category":"Zahnarztpraxen",
    "sg:phone":"+41 55 612 12 25",
    "sg:postcode":"8753",
    "sg:province":"Glarus",
    "wof:name":"Dr. Med. Dent. Ivo Kruljac Zahnarzt",
    "wof:placetype":"venue"
},
  "geometry": {"coordinates":[9.0711708069,47.0948524475],"type":"Point"}
}