{
  "type": "Feature",
  "properties": {
    "iso:country":"CH",
    "sg:address":"Brauerstrasse 68",
    "sg:city":"Winterthur",
    "sg:orig_category":"Herstellung von medizinischen U chirurgischen Ger\u00e4ten sowie orthop\u00e4dischen Vorrichtungen Zahntechnis",
    "sg:phone":"+41 52 213 72 40",
    "sg:postcode":"8400",
    "sg:province":"Z\u00fcrich",
    "wof:name":"Bandschapp Werner, Dental-technik.",
    "wof:placetype":"venue"
},
  "geometry": {"coordinates":[8.7246427536,47.5088768005],"type":"Point"}
}