{
  "type": "Feature",
  "properties": {
    "iso:country":"CH",
    "sg:address":"Luzernstrasse 7",
    "sg:city":"Derendingen",
    "sg:orig_category":"Detailhandel mit Blumen U Pflanzen",
    "sg:phone":"+41 56 621 24 42",
    "sg:postcode":"4552",
    "sg:province":"Solothurn",
    "wof:name":"Monika Oldenburger C.r.e.a. Deko & Floristik",
    "wof:placetype":"venue"
},
  "geometry": {"coordinates":[8.275568,47.31562],"type":"Point"}
}