{
  "type": "Feature",
  "properties": {
    "iso:country":"CH",
    "sg:address":"Scheibenstrasse 2",
    "sg:city":"Thun",
    "sg:orig_category":"Detailhandel mit Zeitungen U Zeitschriften Kioske",
    "sg:phone":"+41 33 222 45 07",
    "sg:postcode":"3600",
    "sg:province":"Bern",
    "wof:name":"Paddock Kiosk Ag",
    "wof:placetype":"venue"
},
  "geometry": {"coordinates":[7.6254878044,46.7601127625],"type":"Point"}
}