{
  "type": "Feature",
  "properties": {
    "iso:country":"CH",
    "sg:address":"Fischmarkt 2",
    "sg:city":"Zug",
    "sg:orig_category":"RESTAURANTS: TEA-ROOMS",
    "sg:postcode":"6300",
    "sg:province":"Zug",
    "wof:name":"R\u00fcttimann Kurt",
    "wof:placetype":"venue"
},
  "geometry": {"coordinates":[8.5144939423,47.1661949158],"type":"Point"}
}