{
  "type": "Feature",
  "properties": {
    "iso:country":"CH",
    "sg:address":"Z\u00fcrichstrasse 9",
    "sg:city":"D\u00fcbendorf",
    "sg:orig_category":"Detailhandel mit Haustieren U zoologischem Bedarf Detailhandel mit Sportartikeln",
    "sg:phone":"+41 18215249",
    "sg:postcode":"8600",
    "sg:province":"Z\u00fcrich",
    "wof:name":"Hans-ueli Studerus Fischerei Und Zooartikel",
    "wof:placetype":"venue"
},
  "geometry": {"coordinates":[8.6163396835,47.3968467712],"type":"Point"}
}