{
  "type": "Feature",
  "properties": {
    "iso:country":"CH",
    "sg:address":"Ballonstrasse 20",
    "sg:city":"Schlieren",
    "sg:orig_category":"Instandhaltung U Reparatur von Automobilen",
    "sg:postcode":"8952",
    "sg:province":"Z\u00fcrich",
    "wof:name":"Auto- / Lkw - Spenglerei K. B\u00fchlmann",
    "wof:placetype":"venue"
},
  "geometry": {"coordinates":[8.4639053345,47.401550293],"type":"Point"}
}