{
  "type": "Feature",
  "properties": {
    "iso:country":"CH",
    "sg:address":"Hohfuristrasse 12",
    "sg:city":"Neerach",
    "sg:orig_category":"Unternehmensberatung",
    "sg:postcode":"8173",
    "sg:province":"Z\u00fcrich",
    "wof:name":"Stratego Business Development Gmbh",
    "wof:placetype":"venue"
},
  "geometry": {"coordinates":[8.2951660156,47.3754463196],"type":"Point"}
}