{
  "type": "Feature",
  "properties": {
    "iso:country":"CH",
    "sg:address":"Diemtigtalstrasse 3758 Latterbach. Postfach",
    "sg:city":"Latterbach",
    "sg:orig_category":"Zimmerei, Dachdeckerei, Bauspenglerei U Abdichtung",
    "sg:phone":"+41 55 282 27 24",
    "sg:postcode":"3758",
    "sg:province":"Bern",
    "wof:name":"Pro Mass Morger Gmbh",
    "wof:placetype":"venue"
},
  "geometry": {"coordinates":[8.924249649,47.2375335693],"type":"Point"}
}