{
  "type": "Feature",
  "properties": {
    "iso:country":"CH",
    "sg:address":"Neudorfstrasse 70",
    "sg:city":"Thusis",
    "sg:orig_category":"Detailhandel mit S\u00e4uglings U Kinderbekleidung Herstellung von sonstiger Bekleidung U Bekleidungszube",
    "sg:phone":"+41 81 651 55 33",
    "sg:postcode":"7430",
    "sg:province":"Graubunden",
    "wof:name":"Kinder-mode Conrad",
    "wof:placetype":"venue"
},
  "geometry": {"coordinates":[9.4395599365,46.6972160339],"type":"Point"}
}