{
  "type": "Feature",
  "properties": {
    "iso:country":"CH",
    "sg:address":"Chemin Des Corjons 14",
    "sg:city":"Mont-sur-lausanne",
    "sg:orig_category":"Wirtschaftspr\u00fcfung, Steuerberatung U Treuhand",
    "sg:phone":"+41 21 653 07 43",
    "sg:postcode":"1052",
    "sg:province":"Vaud",
    "wof:name":"Simval Fiduciaire, Vallotton Bernard",
    "wof:placetype":"venue"
},
  "geometry": {"coordinates":[6.6315507889,46.5559463501],"type":"Point"}
}