{
  "type": "Feature",
  "properties": {
    "iso:country":"CH",
    "sg:address":"Steig 3",
    "sg:city":"Tr\u00fcllikon",
    "sg:orig_category":"Maler U Glasergewerbe Malerei",
    "sg:phone":"+41 52 319 41 62",
    "sg:postcode":"8466",
    "sg:province":"Z\u00fcrich",
    "wof:name":"D\u00fcnki-wipf Thomas, Malergesch\u00e4ft",
    "wof:placetype":"venue"
},
  "geometry": {"coordinates":[8.692653656,47.6384277344],"type":"Point"}
}