{
  "type": "Feature",
  "properties": {
    "iso:country":"CH",
    "sg:address":"Artherstr. 120 Oberwil/zug. 6300 Zug. Postfach 756",
    "sg:city":"Zug",
    "sg:orig_category":"Detailhandel mit Brot, Back U S\u00fcsswaren",
    "sg:postcode":"6301",
    "sg:province":"Zug",
    "wof:name":"Steiner H.",
    "wof:placetype":"venue"
},
  "geometry": {"coordinates":[8.516215,47.171509],"type":"Point"}
}