{
  "type": "Feature",
  "properties": {
    "iso:country":"CH",
    "sg:address":"Ruessenstrasse 18",
    "sg:city":"Baar",
    "sg:orig_category":"Herstellung von elektronischen Bauelementen",
    "sg:phone":"+41 41 760 44 50",
    "sg:postcode":"6340",
    "sg:province":"Zug",
    "wof:name":"Hofer Peter",
    "wof:placetype":"venue"
},
  "geometry": {"coordinates":[8.5638980865,47.2123222351],"type":"Point"}
}