{
  "type": "Feature",
  "properties": {
    "iso:country":"CH",
    "sg:address":"Himmeriweg 9 8052 Z\u00fcrich. Postfach",
    "sg:city":"Seebach",
    "sg:classifiers":[
        {
            "category":"Professional",
            "subcategory":"Employment Agencies",
            "type":"Services"
        }
    ],
    "sg:phone":"+41 13012194",
    "sg:postcode":"8052",
    "sg:province":"Z\u00fcrich",
    "sg:tags":[
        "personal",
        "u",
        "stellenvermittlung"
    ],
    "wof:name":"Efty Marketing Ag Patente; Entwurf, Entw., Verkauf. Gebrauchsartikel; Vermarktung Usw",
    "wof:placetype":"venue"
},
  "geometry": {"coordinates":[8.5367088318,47.4182701111],"type":"Point"}
}