{
  "type": "Feature",
  "properties": {
    "iso:country":"CH",
    "sg:address":"Thunstr. 8 A 3110 M\u00fcnsingen. Postfach",
    "sg:city":"M\u00fcnsingen",
    "sg:orig_category":"Maler U Glasergewerbe",
    "sg:phone":"+41 31 721 53 03",
    "sg:postcode":"3110",
    "sg:province":"Bern",
    "wof:name":"Martin Schertenleib",
    "wof:placetype":"venue"
},
  "geometry": {"coordinates":[7.5623550415,46.8732147217],"type":"Point"}
}