{
  "type": "Feature",
  "properties": {
    "iso:country":"CH",
    "sg:address":"Albisstrasse 113",
    "sg:city":"Z\u00fcrich",
    "sg:orig_category":"Autogaragen",
    "sg:phone":"+41 14819579",
    "sg:postcode":"8038",
    "sg:province":"Z\u00fcrich",
    "wof:name":"Garage Da Riva",
    "wof:placetype":"venue"
},
  "geometry": {"coordinates":[8.530266,47.337578],"type":"Point"}
}