{
  "type": "Feature",
  "properties": {
    "iso:country":"CH",
    "sg:address":"Aarauerstrasse 39",
    "sg:city":"Rupperswil",
    "sg:orig_category":"Herstellung von konfektionierten Textilwaren ohne Bekleidung",
    "sg:phone":"+41 62 897 54 64",
    "sg:postcode":"5102",
    "sg:province":"Aargau",
    "wof:name":"Kernen Eduard",
    "wof:placetype":"venue"
},
  "geometry": {"coordinates":[8.1182432175,47.4042510986],"type":"Point"}
}