{
  "type": "Feature",
  "properties": {
    "iso:country":"CH",
    "sg:address":"Rue De Lausanne 35",
    "sg:city":"Fribourg",
    "sg:orig_category":"Herstellung von Lederbekleidung",
    "sg:postcode":"1700",
    "sg:province":"Fribourg",
    "wof:name":"Eva La Mode, Bartucz Andr\u00e9",
    "wof:placetype":"venue"
},
  "geometry": {"coordinates":[7.1593551636,46.8059043884],"type":"Point"}
}