{
  "type": "Feature",
  "properties": {
    "iso:country":"CH",
    "sg:address":"Chalet Caeilia",
    "sg:city":"Gryon",
    "sg:orig_category":"Zimmerei, Dachdeckerei, Bauspenglerei U Abdichtung",
    "sg:postcode":"1882",
    "sg:province":"Vaud",
    "wof:name":"Moreschi Celeste Sa Succursale Di Monte Carasso",
    "wof:placetype":"venue"
},
  "geometry": {"coordinates":[8.9955282211,46.187713623],"type":"Point"}
}