{
  "type": "Feature",
  "properties": {
    "iso:country":"CH",
    "sg:address":"Montagny Rue De 14",
    "sg:city":"Yverdon-les-bains",
    "sg:orig_category":"Herstellung von Anstrichmitteln, Druckfarben U Kitten",
    "sg:phone":"+41 24 446 16 40",
    "sg:postcode":"1400",
    "sg:province":"Vaud",
    "wof:name":"Ivanovic Dragan",
    "wof:placetype":"venue"
},
  "geometry": {"coordinates":[6.6265540123,46.7806396484],"type":"Point"}
}