{
  "type": "Feature",
  "properties": {
    "iso:country":"CH",
    "sg:address":"Signal Chemin Du 7 1071 Chexbres. Postfach",
    "sg:city":"Chexbres",
    "sg:orig_category":"Reinigungsgewerbe",
    "sg:postcode":"1071",
    "sg:province":"Vaud",
    "wof:name":"Desinfex, Serge Gumy",
    "wof:placetype":"venue"
},
  "geometry": {"coordinates":[6.776239872,46.4821128845],"type":"Point"}
}