{
  "type": "Feature",
  "properties": {
    "iso:country":"CH",
    "sg:address":"Wiesentalstrasse 80",
    "sg:city":"Chur",
    "sg:orig_category":"Non-Classified Establishments",
    "sg:postcode":"7000",
    "sg:province":"Graubunden",
    "wof:name":"Grenci Kundenmaurer / Baurenovationen Gmbh",
    "wof:placetype":"venue"
},
  "geometry": {"coordinates":[9.530872345,46.8602638245],"type":"Point"}
}