{
  "type": "Feature",
  "properties": {
    "iso:country":"CH",
    "sg:address":"Burgmatt 6",
    "sg:city":"Baar",
    "sg:orig_category":"Grosshandel mit Wein U Spirituosen",
    "sg:phone":"+41 41 761 79 93",
    "sg:postcode":"6340",
    "sg:province":"Zug",
    "wof:name":"Wilfried Gantenbein Weinhandel",
    "wof:placetype":"venue"
},
  "geometry": {"coordinates":[8.5386924744,47.1915626526],"type":"Point"}
}