{
  "type": "Feature",
  "properties": {
    "iso:country":"CH",
    "sg:address":"Gauschlastrasse 4",
    "sg:city":"Sevelen",
    "sg:orig_category":"Politische Parteien CVP",
    "sg:phone":"+41 81 785 10 75",
    "sg:postcode":"9475",
    "sg:province":"St. Gallen",
    "wof:name":"Cvp Ortspartei Sevelen",
    "wof:placetype":"venue"
},
  "geometry": {"coordinates":[9.4876012802,47.126739502],"type":"Point"}
}