{
  "type": "Feature",
  "properties": {
    "iso:country":"CH",
    "sg:address":"Erlenweg 2",
    "sg:city":"Anglikon",
    "sg:classifiers":[
        {
            "category":"Personal",
            "subcategory":"Nail Salon",
            "type":"Services"
        }
    ],
    "sg:phone":"+41 56 622 46 58",
    "sg:postcode":"5611",
    "sg:province":"Aargau",
    "sg:tags":[
        "manicure"
    ],
    "wof:name":"Rita Burri Nail-kosmetik",
    "wof:placetype":"venue"
},
  "geometry": {"coordinates":[8.2618293762,47.3646888733],"type":"Point"}
}