{
  "type": "Feature",
  "properties": {
    "iso:country":"CH",
    "sg:address":"6760",
    "sg:city":"Calpiogna",
    "sg:classifiers":[
        {
            "category":"Restaurant",
            "type":"Food & Drink"
        }
    ],
    "sg:phone":"+41 91 943 48 97",
    "sg:postcode":"6760",
    "sg:province":"Ticino",
    "wof:name":"Osteria La Ginestra",
    "wof:placetype":"venue"
},
  "geometry": {"coordinates":[8.9848299026,46.0777893066],"type":"Point"}
}