{
  "type": "Feature",
  "properties": {
    "iso:country":"CH",
    "sg:address":"Dorfstrasse",
    "sg:city":"Says",
    "sg:orig_category":"Sportvereine Wassersport Segeln",
    "sg:phone":"+41 81 353 32 44",
    "sg:postcode":"7202",
    "sg:province":"Graubunden",
    "wof:name":"Blue Lagoon/bakea",
    "wof:placetype":"venue"
},
  "geometry": {"coordinates":[9.5793991089,46.9065437317],"type":"Point"}
}