{
  "type": "Feature",
  "properties": {
    "iso:country":"CH",
    "sg:address":"Schweizistrasse 15",
    "sg:city":"Rupperswil",
    "sg:orig_category":"Maler U Glasergewerbe Malerei",
    "sg:phone":"+41 62 897 35 44",
    "sg:postcode":"5102",
    "sg:province":"Aargau",
    "wof:name":"Calogero Lanza Malergesch\u00e4ft",
    "wof:placetype":"venue"
},
  "geometry": {"coordinates":[8.1318836212,47.4028396606],"type":"Point"}
}