{
  "type": "Feature",
  "properties": {
    "iso:country":"CH",
    "sg:address":"Aareweg 1 5105 Auenstein. Postfach",
    "sg:city":"Auenstein",
    "sg:orig_category":"Vermietung U Verpachtung von eigenen Immobilien",
    "sg:postcode":"5105",
    "sg:province":"Aargau",
    "wof:name":"H. + L. Hochstrasser Immobilien Ag",
    "wof:placetype":"venue"
},
  "geometry": {"coordinates":[8.1349811554,47.4167022705],"type":"Point"}
}