{
  "type": "Feature",
  "properties": {
    "iso:country":"CH",
    "sg:address":"Via Ai Lotti",
    "sg:city":"Vezia",
    "sg:orig_category":"Herstellung von sonstigen landwirtschaftlichen Maschinen Mechanische Werkst\u00e4tten",
    "sg:phone":"+41 79 686 77 19",
    "sg:postcode":"6943",
    "sg:province":"Ticino",
    "wof:name":"Giuseppe Sonvico Off.meccanica-macchine Agric.",
    "wof:placetype":"venue"
},
  "geometry": {"coordinates":[8.9344348907,46.0205802917],"type":"Point"}
}