{
  "type": "Feature",
  "properties": {
    "iso:country":"CH",
    "sg:address":"Bahnhofstrasse 54 4663 Aarburg. Postfach",
    "sg:city":"Aarburg",
    "sg:classifiers":[
        {
            "category":"Professional",
            "subcategory":"Employment Agencies",
            "type":"Services"
        }
    ],
    "sg:phone":"+41 62 787 40 80",
    "sg:postcode":"4663",
    "sg:province":"Aargau",
    "sg:tags":[
        "personal",
        "u",
        "stellenvermittlung"
    ],
    "wof:name":"Gst Stellendienst Ag Aarburg",
    "wof:placetype":"venue"
},
  "geometry": {"coordinates":[7.9079270363,47.3198051453],"type":"Point"}
}