{
  "type": "Feature",
  "properties": {
    "iso:country":"CH",
    "sg:address":"6213 Bad Knutwil. Postfach",
    "sg:city":"B\u00fcron",
    "sg:orig_category":"Grosshandel mit Getr\u00e4nken Mineralquellen, Herstellung von alkoholfreien Getr\u00e4nken",
    "sg:phone":"+41 41 921 23 23",
    "sg:postcode":"6233",
    "sg:province":"Luzern",
    "wof:name":"Mineralquelle Bad Knutwil Ag Wilihof",
    "wof:placetype":"venue"
},
  "geometry": {"coordinates":[8.0722904205,47.2124214172],"type":"Point"}
}