{
  "type": "Feature",
  "properties": {
    "iso:country":"CH",
    "sg:address":"Burghalde 1a 5722 Gr\u00e4nichen. Postfach",
    "sg:city":"Gr\u00e4nichen",
    "sg:orig_category":"Wirtschaftspr\u00fcfung, Steuerberatung U Treuhand",
    "sg:phone":"+41 62 842 68 52",
    "sg:postcode":"5722",
    "sg:province":"Aargau",
    "wof:name":"J. Vogel",
    "wof:placetype":"venue"
},
  "geometry": {"coordinates":[8.0966024399,47.35779953],"type":"Point"}
}