{
  "type": "Feature",
  "properties": {
    "iso:country":"CH",
    "sg:address":"Route De La Gl\u00e2ne 107",
    "sg:city":"Villars-sur-gl\u00e2ne",
    "sg:orig_category":"Revision Wirtschaftspr\u00fcfung, Steuerberatung U Treuhand",
    "sg:phone":"+41 41 280 00 81",
    "sg:postcode":"1752",
    "sg:province":"Fribourg",
    "wof:name":"Opes Revision Ag",
    "wof:placetype":"venue"
},
  "geometry": {"coordinates":[8.2760801315,47.0858039856],"type":"Point"}
}