{
  "type": "Feature",
  "properties": {
    "iso:country":"CH",
    "sg:address":"Hauptstrasse 42 9400 Rorschach. Postfach",
    "sg:city":"Rorschach",
    "sg:orig_category":"Pensionskassen",
    "sg:phone":"+41 71 841 62 12",
    "sg:postcode":"9400",
    "sg:province":"St. Gallen",
    "wof:name":"Personalf\u00fcrsorgestiftung Der Firma Engensperger Ag, Rorschach Sg",
    "wof:placetype":"venue"
},
  "geometry": {"coordinates":[9.4939851761,47.4782752991],"type":"Point"}
}