{
  "type": "Feature",
  "properties": {
    "iso:country":"CH",
    "sg:address":"Saint-julien Route De 163 1228 Plan-les-ouates. Postfach",
    "sg:city":"Plan-les-ouates",
    "sg:orig_category":"Kauf U Verkauf von Immobilien auf eigene Rechnung",
    "sg:postcode":"1228",
    "sg:province":"Gen\u00e8ve",
    "wof:name":"Si Route De Saint-julien 163.",
    "wof:placetype":"venue"
},
  "geometry": {"coordinates":[6.1154518127,46.1670837402],"type":"Point"}
}