{
  "type": "Feature",
  "properties": {
    "addr:full":"Heugatterstrasse 25 D\u00fcbendorf Z\u00fcrich 8600",
    "addr:housenumber":"25",
    "addr:postcode":"8600",
    "addr:street":"Heugatterstrasse;Zuerich",
    "iso:country":"CH",
    "sg:address":"Heugatterstrasse 25",
    "sg:city":"D\u00fcbendorf",
    "sg:orig_category":"Architekturb\u00fcros",
    "sg:phone":"+41 41 448 24 55",
    "sg:postcode":"8600",
    "sg:province":"Z\u00fcrich",
    "wof:name":"J\u00f6rg Traber Architekturb\u00fcro",
    "wof:placetype":"venue"
},
  "geometry": {"coordinates":[8.325287,47.127819],"type":"Point"}
}