{
  "type": "Feature",
  "properties": {
    "iso:country":"CH",
    "sg:address":"Gossauerstrasse 78 9100 Herisau. Postfach",
    "sg:city":"Herisau",
    "sg:orig_category":"Grosshandel mit Nahrungsmitteln, Getr\u00e4nken U Tabakwaren ohne ausgepr\u00e4gten Schwerpunkt",
    "sg:phone":"+41 71 351 72 44",
    "sg:postcode":"9100",
    "sg:province":"Appenzell Ausserrhoden",
    "wof:name":"Filipiniana Shop Riedler Asiatische Lebensmittel U. Handicrafts; Verkauf Usw",
    "wof:placetype":"venue"
},
  "geometry": {"coordinates":[9.2727308273,47.3910369873],"type":"Point"}
}