{
  "type": "Feature",
  "properties": {
    "iso:country":"CH",
    "sg:address":"Eichweg 32",
    "sg:city":"Trimmis",
    "sg:orig_category":"Unclassifiable Establishments",
    "sg:phone":"+41 81 353 40 02",
    "sg:postcode":"7203",
    "sg:province":"Graubunden",
    "wof:name":"Robbi Haustechnik",
    "wof:placetype":"venue"
},
  "geometry": {"coordinates":[9.5563554764,46.9018287659],"type":"Point"}
}