{
  "type": "Feature",
  "properties": {
    "iso:country":"CH",
    "sg:address":"T\u00fcrliacherweg 1 3629 Jaberg. Postfach",
    "sg:city":"Jaberg",
    "sg:orig_category":"R\u00fcckgewinnung U Vorbereitung f\u00fcr die Wiederverwertung Recycling R\u00fcckgewinnung U Vorbereitung f\u00fcr die",
    "sg:phone":"+41 31 780 21 21",
    "sg:postcode":"3629",
    "sg:province":"Bern",
    "wof:name":"Ag F.abfallverwertung Avag",
    "wof:placetype":"venue"
},
  "geometry": {"coordinates":[7.5629172325,46.8199005127],"type":"Point"}
}