{
  "type": "Feature",
  "properties": {
    "iso:country":"CH",
    "sg:address":"Rue Alexander-moser 45 2503 Biel/bienne. Postfach",
    "sg:city":"Biel/bienne",
    "sg:orig_category":"Grosshandel mit sonstigen Maschinen U Ausr\u00fcstungen f\u00fcr Industrie, Handel U Schiffahrt",
    "sg:phone":"+41 32 365 20 91",
    "sg:postcode":"2501",
    "sg:province":"Bern",
    "wof:name":"R. Camponovo Ag",
    "wof:placetype":"venue"
},
  "geometry": {"coordinates":[7.2544460297,47.126285553],"type":"Point"}
}