{
  "type": "Feature",
  "properties": {
    "addr:full":"Chemin Des Clochettes 4 Gen\u00e8ve Gen\u00e8ve 1206",
    "addr:housenumber":"4",
    "addr:postcode":"1206",
    "addr:street":"Chemin Des Clochettes",
    "iso:country":"CH",
    "sg:address":"Chemin Des Clochettes 4",
    "sg:city":"Gen\u00e8ve",
    "sg:orig_category":"Architekturb\u00fcros Innenarchitekturb\u00fcros",
    "sg:phone":"+41 22 347 60 45",
    "sg:postcode":"1206",
    "sg:province":"Gen\u00e8ve",
    "wof:name":"Fran\u00e7oise Magnin",
    "wof:placetype":"venue"
},
  "geometry": {"coordinates":[6.157796,46.18766],"type":"Point"}
}