{
  "type": "Feature",
  "properties": {
    "iso:country":"CH",
    "sg:address":"Buchhaldenstrasse 14",
    "sg:city":"Kloten",
    "sg:orig_category":"Maler U Glasergewerbe",
    "sg:phone":"+41 18137781",
    "sg:postcode":"8302",
    "sg:province":"Z\u00fcrich",
    "wof:name":"Rudolf Ag, Malergesch\u00e4ft",
    "wof:placetype":"venue"
},
  "geometry": {"coordinates":[8.5868272781,47.4480209351],"type":"Point"}
}