{
  "type": "Feature",
  "properties": {
    "iso:country":"CH",
    "sg:address":"Heilmannstrasse 2a",
    "sg:city":"Biel/bienne",
    "sg:orig_category":"Grosshandel mit Nahrungsmitteln, Getr\u00e4nken U Tabakwaren ohne ausgepr\u00e4gten Schwerpunkt",
    "sg:phone":"+41 32 323 65 53",
    "sg:postcode":"2500",
    "sg:province":"Bern",
    "wof:name":"Resiti O.",
    "wof:placetype":"venue"
},
  "geometry": {"coordinates":[7.2899799347,47.1467399597],"type":"Point"}
}