{
  "type": "Feature",
  "properties": {
    "iso:country":"CH",
    "sg:address":"Hotel Kaubad",
    "sg:city":"Appenzell",
    "sg:classifiers":[
        {
            "category":"Travel",
            "subcategory":"Hotels & Motels",
            "type":"Entertainment"
        }
    ],
    "sg:postcode":"9050",
    "sg:province":"Appenzell Innerhoden",
    "sg:tags":[
        "hotels",
        "mit",
        "restaurant"
    ],
    "wof:name":"Bernold Robert.",
    "wof:placetype":"venue"
},
  "geometry": {"coordinates":[9.3835430145,47.3126831055],"type":"Point"}
}