{
  "type": "Feature",
  "properties": {
    "iso:country":"CH",
    "sg:address":"Ottenbergstrasse 74",
    "sg:city":"Z\u00fcrich",
    "sg:orig_category":"Rechtsberatung Wirtschaftspr\u00fcfung, Steuerberatung U Treuhand",
    "sg:postcode":"8049",
    "sg:province":"Z\u00fcrich",
    "wof:name":"G\u00f6ldi Grimm Meier & Partner Treuhand Ag",
    "wof:placetype":"venue"
},
  "geometry": {"coordinates":[8.5807180405,47.3175773621],"type":"Point"}
}