{
  "type": "Feature",
  "properties": {
    "addr:full":"Aarauerstrasse 16 Sch\u00f6ftland Aargau 5040",
    "addr:housenumber":"16",
    "addr:postcode":"5040",
    "addr:street":"Aarauerstrasse",
    "iso:country":"CH",
    "sg:address":"Aarauerstrasse 16",
    "sg:city":"Sch\u00f6ftland",
    "sg:orig_category":"Autolackierereien",
    "sg:phone":"+41 62 721 00 07",
    "sg:postcode":"5040",
    "sg:province":"Aargau",
    "wof:name":"Georg Fischer Automalerei",
    "wof:placetype":"venue"
},
  "geometry": {"coordinates":[8.051544,47.311134],"type":"Point"}
}