{
  "type": "Feature",
  "properties": {
    "iso:country":"CH",
    "sg:address":"Rh\u00f4ne Rue Du 26 1950 Sion. Postfach",
    "sg:city":"Sion",
    "sg:orig_category":"Detailhandel mit Bekleidung",
    "sg:postcode":"1950",
    "sg:province":"Valais",
    "wof:name":"Boutin & Cie V\u00eatements; Vente",
    "wof:placetype":"venue"
},
  "geometry": {"coordinates":[7.358857,46.228092],"type":"Point"}
}