{
  "type": "Feature",
  "properties": {
    "iso:country":"CH",
    "sg:address":"Stadelhoferstrasse 8 8000 Z\u00fcrich. Postfach",
    "sg:city":"Z\u00fcrich",
    "sg:orig_category":"Herstellung von Duft U K\u00f6rperpflegemitteln",
    "sg:postcode":"8001",
    "sg:province":"Z\u00fcrich",
    "wof:name":"Aviva Shop Gaudard-ramirez J.",
    "wof:placetype":"venue"
},
  "geometry": {"coordinates":[8.5482368469,47.3664855957],"type":"Point"}
}