{
  "type": "Feature",
  "properties": {
    "iso:country":"CH",
    "sg:address":"Route De Fribourg 42",
    "sg:city":"Marly",
    "sg:orig_category":"Fittings, Valves",
    "sg:phone":"+41 26 439 94 90",
    "sg:postcode":"1723",
    "sg:province":"Fribourg",
    "wof:name":"Raric Ag",
    "wof:placetype":"venue"
},
  "geometry": {"coordinates":[7.1492118835,46.7858047485],"type":"Point"}
}