{
  "type": "Feature",
  "properties": {
    "iso:country":"CH",
    "sg:address":"Charmilles Rue Des 40 1203 Gen\u00e8ve. Postfach",
    "sg:city":"Gen\u00e8ve",
    "sg:orig_category":"RESTAURANTS: TEA-ROOMS",
    "sg:postcode":"1203",
    "sg:province":"Gen\u00e8ve",
    "wof:name":"Dif Richard",
    "wof:placetype":"venue"
},
  "geometry": {"coordinates":[6.1277770996,46.2076301575],"type":"Point"}
}