{
  "type": "Feature",
  "properties": {
    "iso:country":"CH",
    "sg:address":"Vonmattstrasse 20",
    "sg:city":"Luzern",
    "sg:orig_category":"Bauschreinerei Innenausbau",
    "sg:phone":"+41 41 240 87 43",
    "sg:postcode":"6003",
    "sg:province":"Luzern",
    "wof:name":"Hugo Vonlaufen",
    "wof:placetype":"venue"
},
  "geometry": {"coordinates":[8.299603,47.047707],"type":"Point"}
}