{
  "type": "Feature",
  "properties": {
    "iso:country":"CH",
    "sg:address":"Hubackerstrasse 14",
    "sg:city":"Regensdorf",
    "sg:orig_category":"Grosshandel mit M\u00f6beln, Wohnbedarf, Teppichen U Bodenbel\u00e4gen",
    "sg:phone":"+41 18403151",
    "sg:postcode":"8105",
    "sg:province":"Z\u00fcrich",
    "wof:name":"J\u00f6rg B\u00fcchi Teppich-consulting",
    "wof:placetype":"venue"
},
  "geometry": {"coordinates":[8.4625511169,47.4287872314],"type":"Point"}
}