{
  "type": "Feature",
  "properties": {
    "iso:country":"CH",
    "sg:address":"Holz 780 9427 Wolfhalden. Postfach",
    "sg:city":"Wolfhalden",
    "sg:orig_category":"Grosshandel mit Holz U Baustoffen",
    "sg:postcode":"9427",
    "sg:province":"Appenzell Ausserrhoden",
    "wof:name":"Fermo Pizio-sonderegger",
    "wof:placetype":"venue"
},
  "geometry": {"coordinates":[9.5497522354,47.453414917],"type":"Point"}
}