{
  "type": "Feature",
  "properties": {
    "iso:country":"CH",
    "sg:address":"Buchmattstrasse 13 3400 Burgdorf. Postfach 804",
    "sg:city":"Burgdorf",
    "sg:orig_category":"Herstellung von Elektrizit\u00e4tsverteilungs U schalteinrichtungen",
    "sg:phone":"+41 56 633 82 72",
    "sg:postcode":"3401",
    "sg:province":"Bern",
    "wof:name":"Schmid Kurt Schaltanlagen Und Steuerungsbau Gmbh",
    "wof:placetype":"venue"
},
  "geometry": {"coordinates":[8.3199033737,47.3591003418],"type":"Point"}
}