{
  "type": "Feature",
  "properties": {
    "iso:country":"CH",
    "sg:address":"Rainackerweg 1",
    "sg:city":"St\u00fcsslingen",
    "sg:orig_category":"Erdbewegungsarbeiten",
    "sg:phone":"+41 26 418 12 13",
    "sg:postcode":"4655",
    "sg:province":"Solothurn",
    "wof:name":"Josef Zbinden Traxunternehmung",
    "wof:placetype":"venue"
},
  "geometry": {"coordinates":[7.2107200623,46.7464981079],"type":"Point"}
}