{
  "type": "Feature",
  "properties": {
    "iso:country":"CH",
    "sg:address":"Klybeckstrasse 124 4057 Basel. Postfach 10",
    "sg:city":"Basel",
    "sg:orig_category":"Maler U Glasergewerbe Tapeziererei",
    "sg:phone":"+41 17802250",
    "sg:postcode":"4007",
    "sg:province":"Basel-Stadt",
    "wof:name":"R. Schneider Maler-tapezierergesch\u00e4ft",
    "wof:placetype":"venue"
},
  "geometry": {"coordinates":[8.645359993,47.2416801453],"type":"Point"}
}