{
  "type": "Feature",
  "properties": {
    "iso:country":"CH",
    "sg:address":"Metzgergasse 24",
    "sg:city":"St.gallen",
    "sg:orig_category":"RESTAURANTS: TEA-ROOMS",
    "sg:postcode":"9000",
    "sg:province":"St. Gallen",
    "wof:name":"New White Swan Lau",
    "wof:placetype":"venue"
},
  "geometry": {"coordinates":[9.375289917,47.427116394],"type":"Point"}
}