{
  "type": "Feature",
  "properties": {
    "iso:country":"CH",
    "sg:address":"Zuchwilstrasse 20",
    "sg:city":"Luterbach",
    "sg:orig_category":"Mechanische Werkst\u00e4tten",
    "sg:phone":"+41 32 682 30 53",
    "sg:postcode":"4542",
    "sg:province":"Solothurn",
    "wof:name":"Leibundgut & Co Mechanische Werkstatt",
    "wof:placetype":"venue"
},
  "geometry": {"coordinates":[7.5778131485,47.2155914307],"type":"Point"}
}