{
  "type": "Feature",
  "properties": {
    "addr:full":"Via Rime 1 Mendrisio Ticino 6850",
    "addr:housenumber":"1",
    "addr:postcode":"6850",
    "addr:street":"Via Rime",
    "iso:country":"CH",
    "sg:address":"Via Rime 1",
    "sg:city":"Mendrisio",
    "sg:classifiers":[
        {
            "category":"Science Facility",
            "type":"Public Place"
        }
    ],
    "sg:phone":"+41 91 646 31 33",
    "sg:postcode":"6850",
    "sg:province":"Ticino",
    "sg:tags":[
        "electromechanical",
        "engineering",
        "apparatus"
    ],
    "wof:name":"Fulk Sa",
    "wof:placetype":"venue"
},
  "geometry": {"coordinates":[8.977332,45.869057],"type":"Point"}
}