{
  "type": "Feature",
  "properties": {
    "iso:country":"CH",
    "sg:address":"Talstrasse 49",
    "sg:city":"G\u00e4chlingen",
    "sg:orig_category":"Allgemeiner Hoch U Tiefbau Hoch U Tiefbau",
    "sg:phone":"+41 52 681 13 19",
    "sg:postcode":"8214",
    "sg:province":"Schaffhausen",
    "wof:name":"M\u00fcller Hans",
    "wof:placetype":"venue"
},
  "geometry": {"coordinates":[8.49335,47.704109],"type":"Point"}
}