{
  "type": "Feature",
  "properties": {
    "iso:country":"CH",
    "sg:address":"Allmendstrasse 1402",
    "sg:city":"Villmergen",
    "sg:orig_category":"Pensionskassen",
    "sg:postcode":"5612",
    "sg:province":"Aargau",
    "wof:name":"Personalvorsorgestiftung Der Mlb Max Bertschinger Ag",
    "wof:placetype":"venue"
},
  "geometry": {"coordinates":[8.2487869263,47.3568000793],"type":"Point"}
}