{
  "type": "Feature",
  "properties": {
    "iso:country":"CH",
    "sg:address":"Stampfenbachstrasse 131 8006 Z\u00fcrich. Postfach",
    "sg:city":"Z\u00fcrich",
    "sg:orig_category":"Hardwareberatung",
    "sg:postcode":"8006",
    "sg:province":"Z\u00fcrich",
    "wof:name":"Brine Solutions Ag",
    "wof:placetype":"venue"
},
  "geometry": {"coordinates":[8.539642334,47.3856048584],"type":"Point"}
}