{
  "type": "Feature",
  "properties": {
    "iso:country":"CH",
    "sg:address":"Casa La Pergola",
    "sg:city":"Barbengo",
    "sg:orig_category":"Elektroinstallation",
    "sg:phone":"+41 79 620 33 24",
    "sg:postcode":"6917",
    "sg:province":"Ticino",
    "wof:name":"Fankhauser F. Electro-assist",
    "wof:placetype":"venue"
},
  "geometry": {"coordinates":[8.9250659943,45.9669761658],"type":"Point"}
}