{
  "type": "Feature",
  "properties": {
    "iso:country":"CH",
    "sg:address":"T\u00f6sstalstrasse 999 8483 Kollbrunn. Postfach",
    "sg:city":"Kollbrunn",
    "sg:orig_category":"Fachdetailhandel in Verkaufsr\u00e4umen",
    "sg:postcode":"8483",
    "sg:province":"Z\u00fcrich",
    "wof:name":"Sport, Rosmarie Boss.",
    "wof:placetype":"venue"
},
  "geometry": {"coordinates":[7.8617801666,49.1125106812],"type":"Point"}
}