{
  "type": "Feature",
  "properties": {
    "iso:country":"CH",
    "sg:address":"Kornamtsweg 1",
    "sg:city":"Z\u00fcrich",
    "sg:orig_category":"Herstellung von \u00d6fen U Brennern",
    "sg:postcode":"8046",
    "sg:province":"Z\u00fcrich",
    "wof:name":"Knecht E. Und Partner, Kachelofen Und Chemineebau",
    "wof:placetype":"venue"
},
  "geometry": {"coordinates":[8.5069351196,47.4270057678],"type":"Point"}
}