{
  "type": "Feature",
  "properties": {
    "iso:country":"CH",
    "sg:address":"B\u00fcelmattweg 6",
    "sg:city":"Baar",
    "sg:orig_category":"Grosshandel mit pharmazeutischen Erzeugnissen, medizinischen U orthop\u00e4dischen Artikeln",
    "sg:phone":"+41 41 767 20 57",
    "sg:postcode":"6340",
    "sg:province":"Zug",
    "wof:name":"Herbothek, Fallegger A.",
    "wof:placetype":"venue"
},
  "geometry": {"coordinates":[8.5274009705,47.1973342896],"type":"Point"}
}