{
  "type": "Feature",
  "properties": {
    "iso:country":"CH",
    "sg:address":"Avenue De Jurigoz 20",
    "sg:city":"Lausanne",
    "sg:orig_category":"Fahrschulen, Flugschulen",
    "sg:phone":"+41 22 300 45 85",
    "sg:postcode":"1006",
    "sg:province":"Vaud",
    "wof:name":"Sylvio Roman Auto-\u00e9cole",
    "wof:placetype":"venue"
},
  "geometry": {"coordinates":[6.1359620094,46.1838645935],"type":"Point"}
}