{
  "type": "Feature",
  "properties": {
    "iso:country":"CH",
    "sg:address":"Im Oberhof 19",
    "sg:city":"Thayngen",
    "sg:orig_category":"Dachdeckerei",
    "sg:phone":"+41 52 649 24 94",
    "sg:postcode":"8240",
    "sg:province":"Schaffhausen",
    "wof:name":"Otto Wahrenberger Jun. Steil-& Flachbedachungen",
    "wof:placetype":"venue"
},
  "geometry": {"coordinates":[8.712384,47.74847],"type":"Point"}
}