{
  "type": "Feature",
  "properties": {
    "iso:country":"CH",
    "sg:address":"Dorfstrasse 27 9508 Kalth\u00e4usern. Postfach",
    "sg:city":"Kalth\u00e4usern",
    "sg:orig_category":"Sonstige mit der Informatik verbundene T\u00e4tigkeiten",
    "sg:postcode":"9508",
    "sg:province":"Thurgau",
    "wof:name":"Dodos Computerschule Gmbh Informatik, Treuhand; Schulung, Beratung, Vermittlung, Dienstl., Verwaltung Usw",
    "wof:placetype":"venue"
},
  "geometry": {"coordinates":[8.9850873947,47.5218925476],"type":"Point"}
}