{
  "type": "Feature",
  "properties": {
    "iso:country":"CH",
    "sg:address":"Wohlerstrasse 6 5612 Villmergen. Postfach 97",
    "sg:city":"Villmergen",
    "sg:orig_category":"Instandhaltung U Reparatur von Automobilen",
    "sg:phone":"+41 56 622 69 50",
    "sg:postcode":"5612",
    "sg:province":"Aargau",
    "wof:name":"Rh Auto-service Ag",
    "wof:placetype":"venue"
},
  "geometry": {"coordinates":[8.2458963394,47.3448295593],"type":"Point"}
}