{
  "type": "Feature",
  "properties": {
    "iso:country":"CH",
    "sg:address":"Obere Z\u00e4une 19",
    "sg:city":"Z\u00fcrich",
    "sg:classifiers":[
        {
            "category":"Restaurant",
            "type":"Food & Drink"
        }
    ],
    "sg:phone":"+41 62 891 23 04",
    "sg:postcode":"8001",
    "sg:province":"Z\u00fcrich",
    "wof:name":"Restaurant Zum Untern Tor",
    "wof:placetype":"venue"
},
  "geometry": {"coordinates":[8.1793060303,47.3871841431],"type":"Point"}
}