{
  "type": "Feature",
  "properties": {
    "iso:country":"CH",
    "sg:address":"Chemin De L'esparcette 5",
    "sg:city":"Crissier",
    "sg:orig_category":"Grosshandel mit Getr\u00e4nken Grosshandel mit chemischen Erzeugnissen",
    "sg:phone":"+41 21 634 26 26",
    "sg:postcode":"1023",
    "sg:province":"Vaud",
    "wof:name":"Bourcoud Oenologie",
    "wof:placetype":"venue"
},
  "geometry": {"coordinates":[6.5736432076,46.5530166626],"type":"Point"}
}