{
  "type": "Feature",
  "properties": {
    "iso:country":"CH",
    "sg:address":"Chemin De Palud 25",
    "sg:city":"Vevey",
    "sg:orig_category":"Architektur U Ingenieurb\u00fcros Architekturb\u00fcros",
    "sg:phone":"+41 21 921 72 15",
    "sg:postcode":"1800",
    "sg:province":"Vaud",
    "wof:name":"Andreas Ras Bureau D'architecture & D'ing.",
    "wof:placetype":"venue"
},
  "geometry": {"coordinates":[6.853823,46.466892],"type":"Point"}
}