{
  "type": "Feature",
  "properties": {
    "iso:country":"CH",
    "sg:address":"Zugerbergstrasse 39a",
    "sg:city":"Unter\u00e4geri",
    "sg:orig_category":"Unclassifiable Establishments",
    "sg:phone":"+41 41 750 52 25",
    "sg:postcode":"6314",
    "sg:province":"Zug",
    "wof:name":"Jsi Engineering Ag",
    "wof:placetype":"venue"
},
  "geometry": {"coordinates":[8.5797138214,47.1355323792],"type":"Point"}
}