{
  "type": "Feature",
  "properties": {
    "iso:country":"CH",
    "sg:address":"Bahnhofstrasse 76",
    "sg:city":"Aarau",
    "sg:orig_category":"Detailhandel mit B\u00fcromaschinen U einrichtungen Detailhandel mit Schreib U Papeteriewaren",
    "sg:phone":"+41 62 824 94 40",
    "sg:postcode":"5000",
    "sg:province":"Aargau",
    "wof:name":"H\u00fcssy Ag Papeterie & B\u00fcromaschinen",
    "wof:placetype":"venue"
},
  "geometry": {"coordinates":[8.051814,47.391422],"type":"Point"}
}