{
  "type": "Feature",
  "properties": {
    "iso:country":"CH",
    "sg:address":"Allmendstrasse 6 6210 Sursee. Postfach",
    "sg:city":"Sursee",
    "sg:orig_category":"Technische, physikalische U chemische Untersuchung",
    "sg:postcode":"6210",
    "sg:province":"Luzern",
    "wof:name":"Wascom Ag Umweltschutz- U. Industrieanlangen, Usw.; Planung U. Ausf\u00fchrung",
    "wof:placetype":"venue"
},
  "geometry": {"coordinates":[8.1089773178,47.1804199219],"type":"Point"}
}