{
  "type": "Feature",
  "properties": {
    "iso:country":"CH",
    "sg:address":"Anzenwil 265",
    "sg:city":"Ganterschwil",
    "sg:orig_category":"Sanit\u00e4rinstallation",
    "sg:phone":"+41 71 983 43 72",
    "sg:postcode":"9608",
    "sg:province":"St. Gallen",
    "wof:name":"Hansruedi Z\u00e4hnler Sanit\u00e4r-& Haustechnik",
    "wof:placetype":"venue"
},
  "geometry": {"coordinates":[9.1229381561,47.3748588562],"type":"Point"}
}