{
  "type": "Feature",
  "properties": {
    "iso:country":"CH",
    "sg:address":"L\u00f6wenstrasse 26",
    "sg:city":"Dietikon",
    "sg:orig_category":"Parf\u00fcmerien U sonstiger Detailhandel mit kosmetischen Artikeln U K\u00f6rperpflegemitteln Sonstiger Gross",
    "sg:phone":"+41 22 311 71 97",
    "sg:postcode":"8953",
    "sg:province":"Z\u00fcrich",
    "wof:name":"Tr\u00e9sors De L'eau Sarl",
    "wof:placetype":"venue"
},
  "geometry": {"coordinates":[6.1499328613,46.2021903992],"type":"Point"}
}