{
  "type": "Feature",
  "properties": {
    "iso:country":"CH",
    "sg:address":"1757",
    "sg:city":"Nor\u00e9az",
    "sg:orig_category":"Sportvereine Ballsport Fussball",
    "sg:phone":"+41 26 684 30 26",
    "sg:postcode":"1757",
    "sg:province":"Fribourg",
    "wof:name":"Fc Nor\u00e9az-ros\u00e9",
    "wof:placetype":"venue"
},
  "geometry": {"coordinates":[7.0277352333,46.8016815186],"type":"Point"}
}