{
  "type": "Feature",
  "properties": {
    "addr:full":"Rheinsprung 1 4051 Basel. Postfach 1911 Basel Basel-Stadt 4001",
    "addr:housenumber":"1",
    "addr:postcode":"4051;1911;4001",
    "addr:street":"Rheinsprung;Postfach",
    "iso:country":"CH",
    "sg:address":"Rheinsprung 1 4051 Basel. Postfach 1911",
    "sg:city":"Basel",
    "sg:orig_category":"Advokaturb\u00fcros Notariate",
    "sg:phone":"+41 61 261 58 18",
    "sg:postcode":"4001",
    "sg:province":"Basel-Stadt",
    "wof:name":"Petitjean Eckert & Berger Advokatur- & Notariatsb\u00fcro",
    "wof:placetype":"venue"
},
  "geometry": {"coordinates":[7.588726,47.559464],"type":"Point"}
}