{
  "type": "Feature",
  "properties": {
    "iso:country":"CH",
    "sg:address":"La Gru\u00e8re 1",
    "sg:city":"Saignel\u00e9gier",
    "sg:orig_category":"Unclassifiable Establishments",
    "sg:postcode":"2350",
    "sg:province":"Jura",
    "wof:name":"Melnal Sa",
    "wof:placetype":"venue"
},
  "geometry": {"coordinates":[7.0513877869,47.2354774475],"type":"Point"}
}