{
  "type": "Feature",
  "properties": {
    "iso:country":"CH",
    "sg:address":"La Fontaine",
    "sg:city":"Martigny-croix",
    "sg:orig_category":"Unclassifiable Establishments",
    "sg:postcode":"1921",
    "sg:province":"Valais",
    "wof:name":"Girard Constructions Sa",
    "wof:placetype":"venue"
},
  "geometry": {"coordinates":[7.036438942,46.0777816772],"type":"Point"}
}