{
  "type": "Feature",
  "properties": {
    "iso:country":"CH",
    "sg:address":"Praz-jean",
    "sg:city":"Euseigne",
    "sg:orig_category":"Grosshandel mit Holz U Bauelementen aus Holz S\u00e4gewerke",
    "sg:phone":"+41 27 281 11 20",
    "sg:postcode":"1982",
    "sg:province":"Valais",
    "wof:name":"Moix Sa",
    "wof:placetype":"venue"
},
  "geometry": {"coordinates":[7.4239468575,46.1709899902],"type":"Point"}
}