{
  "type": "Feature",
  "properties": {
    "iso:country":"CH",
    "sg:address":"Hauptstrasse 10",
    "sg:city":"Arbon",
    "sg:orig_category":"Wirtschafts- and Arbeitgeberverb\u00e4nde",
    "sg:phone":"+41 71 622 25 07",
    "sg:postcode":"9320",
    "sg:province":"Thurgau",
    "wof:name":"Thurg.malermeister-verband Pr\u00e4s.herrn Martin Vock",
    "wof:placetype":"venue"
},
  "geometry": {"coordinates":[9.1381845474,47.5666694641],"type":"Point"}
}