{
  "type": "Feature",
  "properties": {
    "iso:country":"CH",
    "sg:address":"Ausserfeld 6",
    "sg:city":"Stansstad",
    "sg:orig_category":"Herstellung von sonstigen elektrischen Ausr\u00fcstungen",
    "sg:postcode":"6362",
    "sg:province":"Nidwalden",
    "wof:name":"Polytrona Multimedia Ag",
    "wof:placetype":"venue"
},
  "geometry": {"coordinates":[8.3409252167,46.9727897644],"type":"Point"}
}