{
  "type": "Feature",
  "properties": {
    "iso:country":"CH",
    "sg:address":"Frankfurt-strasse 86 4142 M\u00fcnchenstein. Postfach",
    "sg:city":"Basel",
    "sg:orig_category":"Grosshandel mit Erzen U Metallen",
    "sg:phone":"+41 61 411 33 77",
    "sg:postcode":"4002",
    "sg:province":"Basel-Stadt",
    "wof:name":"H\u00e4uselmann Ag Metalle",
    "wof:placetype":"venue"
},
  "geometry": {"coordinates":[7.6065330505,47.5259552002],"type":"Point"}
}