{
  "type": "Feature",
  "properties": {
    "iso:country":"CH",
    "sg:address":"Holenackerstrasse 85",
    "sg:city":"Bern",
    "sg:orig_category":"Arztpraxen",
    "sg:phone":"+41 31 992 55 56",
    "sg:postcode":"3027",
    "sg:province":"Bern",
    "wof:name":"Dr.med.werner Graf Spezialarzt Fmh",
    "wof:placetype":"venue"
},
  "geometry": {"coordinates":[7.378775,46.95023],"type":"Point"}
}