{
  "type": "Feature",
  "properties": {
    "iso:country":"CH",
    "sg:address":"Rue Joseph-pasquier 9",
    "sg:city":"Gen\u00e8ve",
    "sg:orig_category":"Kosmetikinstitute",
    "sg:phone":"+41 61 712 13 11",
    "sg:postcode":"1203",
    "sg:province":"Gen\u00e8ve",
    "wof:name":"Simone W\u00fcrth Kosmetikinstitut Simone",
    "wof:placetype":"venue"
},
  "geometry": {"coordinates":[7.5868730545,47.4918251038],"type":"Point"}
}