{
  "type": "Feature",
  "properties": {
    "iso:country":"CH",
    "sg:address":"Bremgartenstrasse 20",
    "sg:city":"Merenschwand",
    "sg:orig_category":"Instandhaltung U Reparatur von Automobilen",
    "sg:phone":"+41 61 751 63 35",
    "sg:postcode":"5634",
    "sg:province":"Aargau",
    "wof:name":"Beat Wetzel Garage",
    "wof:placetype":"venue"
},
  "geometry": {"coordinates":[7.5984778404,47.4674758911],"type":"Point"}
}