{
  "type": "Feature",
  "properties": {
    "iso:country":"CH",
    "sg:address":"Oberdorfstrasse 42",
    "sg:city":"Sch\u00fcpfen",
    "sg:orig_category":"Fotografisches Gewerbe U fotografische Laboratorien",
    "sg:phone":"+41 61 981 31 03",
    "sg:postcode":"3054",
    "sg:province":"Bern",
    "wof:name":"W\u00e4lti-portner Gmbh",
    "wof:placetype":"venue"
},
  "geometry": {"coordinates":[7.3758678436,47.0336875916],"type":"Point"}
}