{
  "type": "Feature",
  "properties": {
    "iso:country":"CH",
    "sg:address":"Schluhmattstrasse 53",
    "sg:city":"Zermatt",
    "sg:orig_category":"Detailhandel mit Teppichen Verlegen von Fussboden",
    "sg:phone":"+41 27 967 22 28",
    "sg:postcode":"3920",
    "sg:province":"Valais",
    "wof:name":"Charles Bittel Teppiche & Vorh\u00e4nge",
    "wof:placetype":"venue"
},
  "geometry": {"coordinates":[7.7461080551,46.0172958374],"type":"Point"}
}