{
  "type": "Feature",
  "properties": {
    "iso:country":"CH",
    "sg:address":"M\u00fchlebachstrasse 112 8008 Z\u00fcrich. Postfach",
    "sg:city":"Z\u00fcrich",
    "sg:orig_category":"Maturit\u00e4tsschulen, Lehrerseminarien",
    "sg:phone":"+41 13838372",
    "sg:postcode":"8034",
    "sg:province":"Z\u00fcrich",
    "wof:name":"Kantonsschule Riesbach Diplommittelschule",
    "wof:placetype":"venue"
},
  "geometry": {"coordinates":[8.5550746918,47.3604888916],"type":"Point"}
}