{
  "type": "Feature",
  "properties": {
    "iso:country":"CH",
    "sg:address":"Axenstrasse 2",
    "sg:city":"Brunnen",
    "sg:orig_category":"Non-Classified Establishments",
    "sg:postcode":"6440",
    "sg:province":"Schwyz",
    "wof:name":"Beach Club Ag",
    "wof:placetype":"venue"
},
  "geometry": {"coordinates":[8.6072740555,46.9931945801],"type":"Point"}
}