{
  "type": "Feature",
  "properties": {
    "iso:country":"CH",
    "sg:address":"Poststrasse 5 3400 Burgdorf. Postfach",
    "sg:city":"Burgdorf",
    "sg:orig_category":"Polizei",
    "sg:phone":"+41 34 421 80 01",
    "sg:postcode":"3401",
    "sg:province":"Bern",
    "wof:name":"Kantonale Polizei",
    "wof:placetype":"venue"
},
  "geometry": {"coordinates":[7.6244487762,47.0602416992],"type":"Point"}
}