{
  "type": "Feature",
  "properties": {
    "iso:country":"CH",
    "sg:address":"Alleestrasse 2",
    "sg:city":"Amriswil",
    "sg:orig_category":"Reiseb\u00fcros",
    "sg:phone":"+41 71 411 03 23",
    "sg:postcode":"8580",
    "sg:province":"Thurgau",
    "wof:name":"D\u00f6nd\u00fc Yildirim Reiseb\u00fcro World Travel",
    "wof:placetype":"venue"
},
  "geometry": {"coordinates":[9.2954454422,47.5458755493],"type":"Point"}
}