{
  "type": "Feature",
  "properties": {
    "iso:country":"CH",
    "sg:address":"Boulevard De P\u00e9rolles 7",
    "sg:city":"Fribourg",
    "sg:orig_category":"Campingpl\u00e4tze",
    "sg:phone":"+41 22 819 08 14",
    "sg:postcode":"1700",
    "sg:province":"Fribourg",
    "wof:name":"Camph\u00f4tels Sa",
    "wof:placetype":"venue"
},
  "geometry": {"coordinates":[7.151737,46.801235],"type":"Point"}
}