{
  "type": "Feature",
  "properties": {
    "iso:country":"CH",
    "sg:address":"Lissignol Rue 5 1201 Gen\u00e8ve. Postfach",
    "sg:city":"Gen\u00e8ve",
    "sg:orig_category":"Herstellung von konfektionierten Textilwaren ohne Bekleidung",
    "sg:postcode":"1201",
    "sg:province":"Gen\u00e8ve",
    "wof:name":"Minire Ademi",
    "wof:placetype":"venue"
},
  "geometry": {"coordinates":[6.1439781189,46.2075233459],"type":"Point"}
}