{
  "type": "Feature",
  "properties": {
    "iso:country":"CH",
    "sg:address":"Tiefenhofstrasse 15",
    "sg:city":"W\u00e4denswil",
    "sg:orig_category":"Zahntechnische Laboratorien",
    "sg:phone":"+41 17803871",
    "sg:postcode":"8820",
    "sg:province":"Z\u00fcrich",
    "wof:name":"Markus Ingold Zahntechnisches Labor",
    "wof:placetype":"venue"
},
  "geometry": {"coordinates":[8.659450531,47.2335739136],"type":"Point"}
}