{
  "type": "Feature",
  "properties": {
    "iso:country":"CH",
    "sg:address":"Gubelstrasse 19",
    "sg:city":"Zug",
    "sg:orig_category":"Grosshandel mit Eisenwaren sowie Installationsbedarf f\u00fcr Gas, Wasser U Heizung Grosshandel mit sonst",
    "sg:phone":"+41 41 711 50 35",
    "sg:postcode":"6300",
    "sg:province":"Zug",
    "wof:name":"Wisan Technik Ag",
    "wof:placetype":"venue"
},
  "geometry": {"coordinates":[8.5164470673,47.1744422913],"type":"Point"}
}