{
  "type": "Feature",
  "properties": {
    "iso:country":"CH",
    "sg:address":"H\u00f6fjiweg 27",
    "sg:city":"Klosters",
    "sg:orig_category":"Internationale Organisationen mit Beh\u00f6rdecharakter",
    "sg:phone":"+41 81 422 52 27",
    "sg:postcode":"7250",
    "sg:province":"Graubunden",
    "wof:name":"Europ.evangelische Allianz Herrn Pfr.willi Sartorius",
    "wof:placetype":"venue"
},
  "geometry": {"coordinates":[9.8877420425,46.8702354431],"type":"Point"}
}