{
  "type": "Feature",
  "properties": {
    "iso:country":"CH",
    "sg:address":"Riedwiesstrasse 18",
    "sg:city":"Gebenstorf",
    "sg:orig_category":"Unternehmensberatung",
    "sg:phone":"+41 56 223 25 37",
    "sg:postcode":"5412",
    "sg:province":"Aargau",
    "wof:name":"Symbionik Gmbh",
    "wof:placetype":"venue"
},
  "geometry": {"coordinates":[8.2403011322,47.4780426025],"type":"Point"}
}