{
  "type": "Feature",
  "properties": {
    "iso:country":"CH",
    "sg:address":"Grand-rue 67",
    "sg:city":"Rolle",
    "sg:orig_category":"Erschliessung von Grundst\u00fccken",
    "sg:postcode":"1180",
    "sg:province":"Vaud",
    "wof:name":"Soci\u00e9t\u00e9 Coop\u00e9rative Courchant",
    "wof:placetype":"venue"
},
  "geometry": {"coordinates":[6.3373188972,46.4566879272],"type":"Point"}
}