{
  "type": "Feature",
  "properties": {
    "iso:country":"CH",
    "sg:address":"Tourne Route De La",
    "sg:city":"Montmollin",
    "sg:orig_category":"Wirtschaftspr\u00fcfung, Steuerberatung U Treuhand",
    "sg:phone":"+41 32 842 46 82",
    "sg:postcode":"2205",
    "wof:name":"Walter Mich\u00e8le",
    "wof:placetype":"venue"
},
  "geometry": {"coordinates":[6.846930027,46.9922790527],"type":"Point"}
}