{
  "type": "Feature",
  "properties": {
    "iso:country":"CH",
    "sg:address":"Rue De L'industrie 19",
    "sg:city":"Ponts-de-martel",
    "sg:orig_category":"Interessenvertretungen U sonstige Vereinigungen",
    "sg:phone":"+41 26 652 21 78",
    "sg:postcode":"2316",
    "sg:province":"Neuch\u00e2tel",
    "wof:name":"Ass.fribourgeoise De Judo",
    "wof:placetype":"venue"
},
  "geometry": {"coordinates":[6.9174537659,46.6935997009],"type":"Point"}
}