{
  "type": "Feature",
  "properties": {
    "iso:country":"CH",
    "sg:address":"Gotthardstrasse 61 6490 Andermatt. Postfach 162",
    "sg:city":"Andermatt",
    "sg:orig_category":"Detailhandel mit fotografischen Artikeln",
    "sg:phone":"+41 41 887 12 55",
    "sg:postcode":"6490",
    "sg:province":"Uri",
    "wof:name":"Rudolf Noack",
    "wof:placetype":"venue"
},
  "geometry": {"coordinates":[8.5971298218,46.6343231201],"type":"Point"}
}