{
  "type": "Feature",
  "properties": {
    "iso:country":"CH",
    "sg:address":"Preyel Le 1",
    "sg:city":"Couvet",
    "sg:orig_category":"Herstellung von Uhren",
    "sg:postcode":"2108",
    "sg:province":"Neuch\u00e2tel",
    "wof:name":"Lovekey Diffusion Sa",
    "wof:placetype":"venue"
},
  "geometry": {"coordinates":[6.841753006,47.1108283997],"type":"Point"}
}