{
  "type": "Feature",
  "properties": {
    "iso:country":"CH",
    "sg:address":"Bahnhofstrasse 69 8803 R\u00fcschlikon. Postfach",
    "sg:city":"R\u00fcschlikon",
    "sg:orig_category":"Architektur U Ingenieurb\u00fcros",
    "sg:phone":"+41 17045262",
    "sg:postcode":"8803",
    "sg:province":"Z\u00fcrich",
    "wof:name":"Fuerte Ag Architektur- U. Planungsarbeiten",
    "wof:placetype":"venue"
},
  "geometry": {"coordinates":[8.556768,47.305305],"type":"Point"}
}