{
  "type": "Feature",
  "properties": {
    "iso:country":"CH",
    "sg:address":"Florissant Route De 4 1206 Gen\u00e8ve. Postfach",
    "sg:city":"Gen\u00e8ve",
    "sg:orig_category":"Vermietung U Verpachtung von eigenen Immobilien",
    "sg:phone":"+41 32 911 90 90",
    "sg:postcode":"1206",
    "sg:province":"Gen\u00e8ve",
    "wof:name":"Soci\u00e9t\u00e9 De Construction Pour La Chaux-de-fonds",
    "wof:placetype":"venue"
},
  "geometry": {"coordinates":[6.8297801018,47.1029129028],"type":"Point"}
}