{
  "type": "Feature",
  "properties": {
    "addr:full":"Rue De Vevey 11 Bulle Fribourg 1630",
    "addr:housenumber":"11",
    "addr:postcode":"1630",
    "addr:street":"Rue De Vevey",
    "iso:country":"CH",
    "sg:address":"Rue De Vevey 11",
    "sg:city":"Bulle",
    "sg:orig_category":"Architekturb\u00fcros",
    "sg:phone":"+41 21 799 28 69",
    "sg:postcode":"1630",
    "sg:province":"Fribourg",
    "wof:name":"Cearba Charles B\u00e4hler Bureau D'architecture",
    "wof:placetype":"venue"
},
  "geometry": {"coordinates":[6.728117,46.494286],"type":"Point"}
}