{
  "type": "Feature",
  "properties": {
    "iso:country":"CH",
    "sg:address":"Route De Fribourg 44",
    "sg:city":"Courtepin",
    "sg:orig_category":"Forst\u00e4mter",
    "sg:phone":"+41 26 684 16 32",
    "sg:postcode":"1784",
    "sg:province":"Fribourg",
    "wof:name":"Inspection Des For\u00eats Du 5\u00e8me Arrondissement",
    "wof:placetype":"venue"
},
  "geometry": {"coordinates":[7.1240229607,46.8641204834],"type":"Point"}
}