{
  "type": "Feature",
  "properties": {
    "iso:country":"CH",
    "sg:address":"Rue Du Simplon 20",
    "sg:city":"Lausanne",
    "sg:orig_category":"Detailhandel mit Musikinstrumenten",
    "sg:phone":"+41 21 601 55 50",
    "sg:postcode":"1000",
    "sg:province":"Vaud",
    "wof:name":"Pianoworld",
    "wof:placetype":"venue"
},
  "geometry": {"coordinates":[6.6302661896,46.5159912109],"type":"Point"}
}