{
  "type": "Feature",
  "properties": {
    "iso:country":"CH",
    "sg:address":"Via Br\u00fcga",
    "sg:city":"Lamone",
    "sg:orig_category":"Vorschulen, Kinderg\u00e4rten",
    "sg:postcode":"6814",
    "sg:province":"Ticino",
    "wof:name":"Scuola Materna Lamone",
    "wof:placetype":"venue"
},
  "geometry": {"coordinates":[8.9260196686,46.0466194153],"type":"Point"}
}