{
  "type": "Feature",
  "properties": {
    "iso:country":"CH",
    "sg:address":"Chlupfwisstrasse 31",
    "sg:city":"Oberweningen",
    "sg:orig_category":"Softwareentwicklung U beratung",
    "sg:phone":"+41 62 212 74 40",
    "sg:postcode":"8165",
    "sg:province":"Z\u00fcrich",
    "wof:name":"Mega-bus Sa Med.computersystem",
    "wof:placetype":"venue"
},
  "geometry": {"coordinates":[7.8732891083,47.3441543579],"type":"Point"}
}