{
  "type": "Feature",
  "properties": {
    "iso:country":"CH",
    "sg:address":"Rte De Grandcour Case Postale 267",
    "sg:city":"Payerne",
    "sg:classifiers":[
        {
            "category":"Manufacturing",
            "subcategory":"Tools & Machinery",
            "type":"Manufacturing & Wholesale Goods"
        }
    ],
    "sg:phone":"+41 26 662 36 36",
    "sg:postcode":"1530",
    "sg:province":"Vaud",
    "sg:tags":[
        "metallurgy",
        "metalworking"
    ],
    "wof:name":"Sfs Unimarket Ag",
    "wof:placetype":"venue"
},
  "geometry": {"coordinates":[6.9286150932,46.8717956543],"type":"Point"}
}