{
  "type": "Feature",
  "properties": {
    "iso:country":"CH",
    "sg:address":"Rue De Martheray 14 1268 Begnins Case Postale 247",
    "sg:city":"Begnins",
    "sg:orig_category":"Bauschreinerei Herstellung von Konstruktionsteilen, Fertigbauteilen U Ausbauelementen aus Holz",
    "sg:phone":"+41 22 366 35 75",
    "sg:postcode":"1268",
    "sg:province":"Vaud",
    "wof:name":"Narbois Sa",
    "wof:placetype":"venue"
},
  "geometry": {"coordinates":[6.250168,46.440697],"type":"Point"}
}