{
  "type": "Feature",
  "properties": {
    "iso:country":"CH",
    "sg:address":"Gr\u00fctlistrasse 16",
    "sg:city":"St.gallen",
    "sg:orig_category":"Sonstige pers\u00f6nliche Dienstleistungen",
    "sg:postcode":"9000",
    "sg:province":"St. Gallen",
    "wof:name":"Monitor Tools Ag",
    "wof:placetype":"venue"
},
  "geometry": {"coordinates":[9.4040737152,47.4337425232],"type":"Point"}
}