{
  "type": "Feature",
  "properties": {
    "iso:country":"CH",
    "sg:address":"Im Kirschgarten 47",
    "sg:city":"Binningen",
    "sg:orig_category":"Sonstige Weberei",
    "sg:phone":"+41 62 771 12 62",
    "sg:postcode":"4102",
    "sg:province":"Basel-Landschaft",
    "wof:name":"Alfred F. Rohrbach Ag Reinach 6 Spezialb\u00e4nder F\u00fcr Gewerbl. U. Techn. Zwecke; Fabr U. Handel",
    "wof:placetype":"venue"
},
  "geometry": {"coordinates":[8.1879444122,47.2636680603],"type":"Point"}
}