{
  "type": "Feature",
  "properties": {
    "iso:country":"CH",
    "sg:address":"Stampastrasse 14",
    "sg:city":"Chur",
    "sg:orig_category":"Vorschulen, Kinderg\u00e4rten",
    "sg:phone":"+41 81 353 32 74",
    "sg:postcode":"7000",
    "sg:province":"Graubunden",
    "wof:name":"St\u00e4dtischer Kindergarten Turnerwiese",
    "wof:placetype":"venue"
},
  "geometry": {"coordinates":[9.5323648453,46.8581085205],"type":"Point"}
}