{
  "type": "Feature",
  "properties": {
    "iso:country":"CH",
    "sg:address":"Friedensgasse 2",
    "sg:city":"Dornach",
    "sg:orig_category":"Arztpraxen",
    "sg:phone":"+41 61 701 13 12",
    "sg:postcode":"4143",
    "sg:province":"Solothurn",
    "wof:name":"Dr.med.hans-peter Naegeli Arzt F\u00fcr Allgemeine Medizin",
    "wof:placetype":"venue"
},
  "geometry": {"coordinates":[7.60975,47.488499],"type":"Point"}
}