{
  "type": "Feature",
  "properties": {
    "iso:country":"CH",
    "sg:address":"Im Baumgarten 1",
    "sg:city":"Dietwil",
    "sg:orig_category":"Sonstiger spezialisierter Hoch U Tiefbau",
    "sg:phone":"+41 41 787 37 52",
    "sg:postcode":"6042",
    "sg:province":"Aargau",
    "wof:name":"Pefutech, Peter M\u00fcller",
    "wof:placetype":"venue"
},
  "geometry": {"coordinates":[8.393237114,47.1501426697],"type":"Point"}
}