{
  "type": "Feature",
  "properties": {
    "iso:country":"CH",
    "sg:address":"1326",
    "sg:city":"Juriens",
    "sg:orig_category":"Architektur U Ingenieurb\u00fcros",
    "sg:postcode":"1326",
    "sg:province":"Vaud",
    "wof:name":"Elc Thorimbert Serge",
    "wof:placetype":"venue"
},
  "geometry": {"coordinates":[6.450215,46.691341],"type":"Point"}
}