{
  "type": "Feature",
  "properties": {
    "iso:country":"CH",
    "sg:address":"Alter Seeweg 13",
    "sg:city":"Maur",
    "sg:classifiers":[
        {
            "category":"Cinema",
            "subcategory":"Movie Theater",
            "type":"Entertainment"
        }
    ],
    "sg:phone":"+41 19803889",
    "sg:postcode":"8124",
    "sg:province":"Z\u00fcrich",
    "sg:tags":[
        "radio",
        "videofilmherstellung",
        "fernsehanstalten",
        "u",
        "film"
    ],
    "wof:name":"B\u00f6hler Georges",
    "wof:placetype":"venue"
},
  "geometry": {"coordinates":[8.6738195419,47.339969635],"type":"Point"}
}