{
  "type": "Feature",
  "properties": {
    "iso:country":"CH",
    "sg:address":"Grossmattweg 5",
    "sg:city":"Selzach",
    "sg:orig_category":"Mechanische Werkst\u00e4tten",
    "sg:phone":"+41 32 641 16 04",
    "sg:postcode":"2545",
    "sg:province":"Solothurn",
    "wof:name":"August Walker Werkzeugsch\u00e4rferei",
    "wof:placetype":"venue"
},
  "geometry": {"coordinates":[7.4474701881,47.1938362122],"type":"Point"}
}