{
  "type": "Feature",
  "properties": {
    "iso:country":"CH",
    "sg:address":"Z\u00fcrcherstrasse 238 8500 Frauenfeld. Postfach",
    "sg:city":"Z\u00fcrich",
    "sg:orig_category":"Grosshandel mit festen Brennstoffen U Mineral\u00f6lerzeugnissen Handelsvermittlung U Grosshandel",
    "sg:phone":"+41 12127151",
    "sg:postcode":"8022",
    "sg:province":"Z\u00fcrich",
    "wof:name":"Dehages Ag",
    "wof:placetype":"venue"
},
  "geometry": {"coordinates":[8.9017553329,47.5601005554],"type":"Point"}
}