{
  "type": "Feature",
  "properties": {
    "iso:country":"CH",
    "sg:address":"B\u00fcrklistrasse 9",
    "sg:city":"M\u00f6hlin",
    "sg:orig_category":"Softwareentwicklung U beratung",
    "sg:phone":"+41 61 853 90 30",
    "sg:postcode":"4313",
    "sg:province":"Aargau",
    "wof:name":"Amsler Trading",
    "wof:placetype":"venue"
},
  "geometry": {"coordinates":[7.8404688835,47.5726165771],"type":"Point"}
}