{
  "type": "Feature",
  "properties": {
    "iso:country":"CH",
    "sg:address":"Sonnmattweg 2",
    "sg:city":"Neuenhof",
    "sg:orig_category":"Organisationen des Gesundheitswesen",
    "sg:phone":"+41 56 406 23 23",
    "sg:postcode":"5432",
    "sg:province":"Aargau",
    "wof:name":"Krankenpflegeverein",
    "wof:placetype":"venue"
},
  "geometry": {"coordinates":[8.3323249817,47.450050354],"type":"Point"}
}