{
  "type": "Feature",
  "properties": {
    "iso:country":"CH",
    "sg:address":"Barkenweg 1c",
    "sg:city":"Biel/bienne",
    "sg:orig_category":"Herstellung von Werkzeugmaschinen Mechanische Werkst\u00e4tten",
    "sg:phone":"+41 32 323 82 57",
    "sg:postcode":"2503",
    "sg:province":"Bern",
    "wof:name":"Animex Imer Sa",
    "wof:placetype":"venue"
},
  "geometry": {"coordinates":[7.2394051552,47.1299438477],"type":"Point"}
}