{
  "type": "Feature",
  "properties": {
    "iso:country":"CH",
    "sg:address":"Allmendstrasse 14",
    "sg:city":"Villmergen",
    "sg:orig_category":"Grosshandel mit Eisenwaren sowie Installationsbedarf f\u00fcr Gas, Wasser U Heizung Grosshandel mit Werkz",
    "sg:phone":"+41 17991818",
    "sg:postcode":"5612",
    "sg:province":"Aargau",
    "wof:name":"Wallima-werkzeugmaschinen, Draca M.",
    "wof:placetype":"venue"
},
  "geometry": {"coordinates":[8.7197971344,47.2714233398],"type":"Point"}
}