{
  "type": "Feature",
  "properties": {
    "iso:country":"CH",
    "sg:address":"Rappoltshof 10 4057 Basel. Postfach",
    "sg:city":"Basel",
    "sg:orig_category":"Detailhandel mit Teppichen Verlegen von Fussboden",
    "sg:phone":"+41 32 373 22 72",
    "sg:postcode":"4005",
    "sg:province":"Basel-Stadt",
    "wof:name":"M. Richard Teppiche & Bodenbel\u00e4ge",
    "wof:placetype":"venue"
},
  "geometry": {"coordinates":[7.2833042145,47.1238708496],"type":"Point"}
}