{
  "type": "Feature",
  "properties": {
    "iso:country":"CH",
    "sg:address":"Albisstrasse 17",
    "sg:city":"Adliswil",
    "sg:orig_category":"Detailhandel mit Radio U Fernsehger\u00e4ten Herstellung von Radio U Fernsehger\u00e4ten sowie phono U videote",
    "sg:phone":"+41 17107236",
    "sg:postcode":"8134",
    "sg:province":"Z\u00fcrich",
    "wof:name":"Gysin Radio Tv Ag",
    "wof:placetype":"venue"
},
  "geometry": {"coordinates":[8.5256652832,47.3106613159],"type":"Point"}
}