{
  "type": "Feature",
  "properties": {
    "addr:full":"Boulevard De P\u00e9rolles 21b Fribourg Fribourg 1700",
    "addr:housenumber":"21b",
    "addr:postcode":"1700",
    "addr:street":"Boulevard De Pe\u0301Rolles",
    "iso:country":"CH",
    "sg:address":"Boulevard De P\u00e9rolles 21b",
    "sg:city":"Fribourg",
    "sg:orig_category":"Detailhandel mit Bekleidung",
    "sg:postcode":"1700",
    "sg:province":"Fribourg",
    "wof:name":"Wear Shop Perolles Sa",
    "wof:placetype":"venue"
},
  "geometry": {"coordinates":[7.152371,46.799789],"type":"Point"}
}