{
  "type": "Feature",
  "properties": {
    "iso:country":"CH",
    "sg:address":"Delfterstrasse 31",
    "sg:city":"Aarau",
    "sg:orig_category":"Herstellung von sonstigen elektrischen Ausr\u00fcstungen",
    "sg:phone":"+41 17814538",
    "sg:postcode":"5004",
    "sg:province":"Aargau",
    "wof:name":"Koch Ren\u00e9 Ag",
    "wof:placetype":"venue"
},
  "geometry": {"coordinates":[8.0611915588,47.4010543823],"type":"Point"}
}