{
  "type": "Feature",
  "properties": {
    "addr:full":"Voyeboeuf 3a Porrentruy Jura 2900",
    "addr:housenumber":"3a",
    "addr:postcode":"2900",
    "addr:street":"Voyeboeuf;Jura",
    "iso:country":"CH",
    "sg:address":"Voyeboeuf 3a",
    "sg:city":"Porrentruy",
    "sg:orig_category":"Autogaragen",
    "sg:phone":"+41 32 466 40 45",
    "sg:postcode":"2900",
    "sg:province":"Jura",
    "wof:name":"Garage R. Affolter Sa",
    "wof:placetype":"venue"
},
  "geometry": {"coordinates":[7.09234,47.417248],"type":"Point"}
}