{
  "type": "Feature",
  "properties": {
    "iso:country":"CH",
    "sg:address":"Rue Caroline 8 1200 Gen\u00e8ve Case Postale 453",
    "sg:city":"Genf",
    "sg:orig_category":"Sanit\u00e4r, Heizungs U L\u00fcftungsinstallation",
    "sg:postcode":"1200",
    "sg:province":"Gen\u00e8ve",
    "wof:name":"Daniel Sch\u00fcpbach Et Fils Sa",
    "wof:placetype":"venue"
},
  "geometry": {"coordinates":[6.2120537758,46.582359314],"type":"Point"}
}