{
  "type": "Feature",
  "properties": {
    "iso:country":"CH",
    "sg:address":"Egglistrasse 3780 Gruben B. Gstaad. Postfach",
    "sg:city":"Gstaad",
    "sg:orig_category":"Unclassifiable Establishments",
    "sg:postcode":"3780",
    "sg:province":"Bern",
    "wof:name":"Sumo Web-service, Tschan Markus",
    "wof:placetype":"venue"
},
  "geometry": {"coordinates":[7.283686161,46.4672813416],"type":"Point"}
}