{
  "type": "Feature",
  "properties": {
    "iso:country":"CH",
    "sg:address":"Sagenhofweg 16",
    "sg:city":"Ebikon",
    "sg:orig_category":"Allgemeiner Hoch U Tiefbau Allgemeiner Hochbau",
    "sg:phone":"+41 41 440 66 12",
    "sg:postcode":"6030",
    "sg:province":"Luzern",
    "wof:name":"Gebr\u00fcder K\u00e4ppeli Ag Ebikon Hoch-& Tiefbauunternehmung",
    "wof:placetype":"venue"
},
  "geometry": {"coordinates":[8.33693,47.074837],"type":"Point"}
}