{
  "type": "Feature",
  "properties": {
    "iso:country":"CH",
    "sg:address":"Kramgasse 45",
    "sg:city":"Bern",
    "sg:orig_category":"Wein Detailhandel",
    "sg:phone":"+41 31 312 17 17",
    "sg:postcode":"3011",
    "sg:province":"Bern",
    "wof:name":"M\u00fcnsterkellerei Ag",
    "wof:placetype":"venue"
},
  "geometry": {"coordinates":[7.4499430656,46.9478302002],"type":"Point"}
}