{
  "type": "Feature",
  "properties": {
    "iso:country":"CH",
    "sg:address":"Ruelle Du Temple 2 1033 Cheseaux-lausanne. Postfach",
    "sg:city":"Cheseaux-lausanne",
    "sg:orig_category":"Grosshandel mit sonstigen Gebrauchs U Verbrauchsg\u00fctern",
    "sg:postcode":"1033",
    "sg:province":"Vaud",
    "wof:name":"Armes Anciennes De Collection L'esponton Joyet Emile",
    "wof:placetype":"venue"
},
  "geometry": {"coordinates":[6.605700016,46.5846672058],"type":"Point"}
}