{
  "type": "Feature",
  "properties": {
    "iso:country":"CH",
    "sg:address":"Wilhelmstrasse 2",
    "sg:city":"Z\u00fcrich",
    "sg:orig_category":"Unclassifiable Establishments",
    "sg:postcode":"8005",
    "sg:province":"Z\u00fcrich",
    "wof:name":"Renovago Gmbh",
    "wof:placetype":"venue"
},
  "geometry": {"coordinates":[8.5232172012,47.3901557922],"type":"Point"}
}