{
  "type": "Feature",
  "properties": {
    "iso:country":"CH",
    "sg:address":"Bahnhofstrasse 311 5325 Leibstadt. Postfach 9",
    "sg:city":"Leibstadt",
    "sg:orig_category":"Grosshandel mit Erzen U Metallen",
    "sg:phone":"+41 56 247 16 57",
    "sg:postcode":"5325",
    "sg:province":"Aargau",
    "wof:name":"Dorweiler Metall Ag",
    "wof:placetype":"venue"
},
  "geometry": {"coordinates":[8.1681804657,47.5912513733],"type":"Point"}
}