{
  "type": "Feature",
  "properties": {
    "iso:country":"CH",
    "sg:address":"Freiestrasse 41",
    "sg:city":"Schlieren",
    "sg:orig_category":"Non-Classified Establishments",
    "sg:postcode":"8952",
    "sg:province":"Z\u00fcrich",
    "wof:name":"Kryeziu",
    "wof:placetype":"venue"
},
  "geometry": {"coordinates":[8.4416723251,47.3954811096],"type":"Point"}
}