{
  "type": "Feature",
  "properties": {
    "iso:country":"CH",
    "sg:address":"Grieshalde 6",
    "sg:city":"Diessenhofen",
    "sg:orig_category":"Interessenvertretungen",
    "sg:postcode":"8253",
    "sg:province":"Thurgau",
    "wof:name":"A.r.t. (association Pour La R\u00e9cup\u00e9ration Et Le Travail) Contribuer \u00e0 La Protection De L'environnement Par Des Activit\u00e9s De Recyclage Et Apporter Une Aide Etc",
    "wof:placetype":"venue"
},
  "geometry": {"coordinates":[6.7670779228,47.0650253296],"type":"Point"}
}