{
  "type": "Feature",
  "properties": {
    "iso:country":"CH",
    "sg:address":"Sch\u00fctzengasse 10",
    "sg:city":"Richterswil",
    "sg:orig_category":"Unternehmensberatung",
    "sg:phone":"+41 16871653",
    "sg:postcode":"8805",
    "sg:province":"Z\u00fcrich",
    "wof:name":"Specht R. Dr., Unternehmensberatung",
    "wof:placetype":"venue"
},
  "geometry": {"coordinates":[8.7049407959,47.2068519592],"type":"Point"}
}