{
  "type": "Feature",
  "properties": {
    "iso:country":"CH",
    "sg:address":"M\u00fchlegasse 17",
    "sg:city":"Hindelbank",
    "sg:orig_category":"Polizei",
    "sg:phone":"+41 34 411 31 11",
    "sg:postcode":"3324",
    "sg:province":"Bern",
    "wof:name":"Kantonale Polizei",
    "wof:placetype":"venue"
},
  "geometry": {"coordinates":[7.5416841507,47.0402565002],"type":"Point"}
}