{
  "type": "Feature",
  "properties": {
    "iso:country":"CH",
    "sg:address":"Industriestrasse 6",
    "sg:city":"Neuheim",
    "sg:orig_category":"G\u00fcterbef\u00f6rderung im Strassenverkehr",
    "sg:phone":"+41 41 755 13 14",
    "sg:postcode":"6345",
    "sg:province":"Zug",
    "wof:name":"Josef Iten Transporte",
    "wof:placetype":"venue"
},
  "geometry": {"coordinates":[8.5770902634,47.202167511],"type":"Point"}
}