{
  "type": "Feature",
  "properties": {
    "iso:country":"CH",
    "sg:address":"Gstaltenrainweg 21",
    "sg:city":"Riehen",
    "sg:orig_category":"Maler U Glasergewerbe",
    "sg:postcode":"4125",
    "sg:province":"Basel-Stadt",
    "wof:name":"Jouan & Partner",
    "wof:placetype":"venue"
},
  "geometry": {"coordinates":[7.6385169029,47.576210022],"type":"Point"}
}