{
  "type": "Feature",
  "properties": {
    "iso:country":"CH",
    "sg:address":"Am B\u00e4chli 6 4102 Binningen. Postfach",
    "sg:city":"Binningen",
    "sg:orig_category":"Unternehmensberatung",
    "sg:phone":"+41 61 303 13 23",
    "sg:postcode":"4102",
    "sg:province":"Basel-Landschaft",
    "wof:name":"Quarto Consulting Gmbh Unternehmensberatung Usw",
    "wof:placetype":"venue"
},
  "geometry": {"coordinates":[7.5606651306,47.5445976257],"type":"Point"}
}