{
  "type": "Feature",
  "properties": {
    "iso:country":"CH",
    "sg:address":"St. Annagasse 16 8001 Z\u00fcrich. Postfach",
    "sg:city":"Z\u00fcrich",
    "sg:orig_category":"Architektur U Ingenieurb\u00fcros",
    "sg:phone":"+41 12128312",
    "sg:postcode":"8021",
    "sg:province":"Z\u00fcrich",
    "wof:name":"M\u00fcller + M\u00fcller Ag Z\u00fcrich",
    "wof:placetype":"venue"
},
  "geometry": {"coordinates":[8.536504,47.373428],"type":"Point"}
}