{
  "type": "Feature",
  "properties": {
    "iso:country":"CH",
    "sg:address":"Hauptstrasse 120",
    "sg:city":"Wenslingen",
    "sg:orig_category":"Vereine Vogel-& Naturschutz",
    "sg:postcode":"4493",
    "sg:province":"Basel-Landschaft",
    "wof:name":"Ornithologische Gesellschaft",
    "wof:placetype":"venue"
},
  "geometry": {"coordinates":[7.9066801071,47.4408721924],"type":"Point"}
}