{
  "type": "Feature",
  "properties": {
    "iso:country":"CH",
    "sg:address":"9621",
    "sg:city":"Oberhelfenschwil",
    "sg:classifiers":[
        {
            "category":"Restaurant",
            "type":"Food & Drink"
        }
    ],
    "sg:phone":"+41 71 374 23 73",
    "sg:postcode":"9621",
    "sg:province":"St. Gallen",
    "wof:name":"Kurhaus Dorfplatz Restaurant",
    "wof:placetype":"venue"
},
  "geometry": {"coordinates":[9.1094970703,47.356918335],"type":"Point"}
}