{
  "type": "Feature",
  "properties": {
    "iso:country":"CH",
    "sg:address":"Industriegebiet Ribi 4",
    "sg:city":"Balterswil",
    "sg:classifiers":[
        {
            "category":"Professional",
            "subcategory":"Engineering",
            "type":"Services"
        }
    ],
    "sg:phone":"+41 71 971 20 73",
    "sg:postcode":"8362",
    "sg:province":"Thurgau",
    "sg:tags":[
        "manufacturing",
        "cnc"
    ],
    "wof:name":"Hans Heinrich Steiner Ag",
    "wof:placetype":"venue"
},
  "geometry": {"coordinates":[8.93931,47.454376],"type":"Point"}
}