{
  "type": "Feature",
  "properties": {
    "iso:country":"CH",
    "sg:address":"Staldenweg 3",
    "sg:city":"Oberengstringen",
    "sg:orig_category":"Herstellung von keramischen Wand U Bodenfliesen U platten Verlegen von Fliesen U Platten",
    "sg:phone":"+41 17506358",
    "sg:postcode":"8102",
    "sg:province":"Z\u00fcrich",
    "wof:name":"Isceri V. Keramische Platten",
    "wof:placetype":"venue"
},
  "geometry": {"coordinates":[8.4659690857,47.4101867676],"type":"Point"}
}