{
  "type": "Feature",
  "properties": {
    "iso:country":"CH",
    "sg:address":"Binningerstrasse 141 4123 Allschwil. Postfach",
    "sg:city":"Basel",
    "sg:orig_category":"Malerei",
    "sg:phone":"+41 61 486 46 46",
    "sg:postcode":"4027",
    "wof:name":"Marcel Fischer Ag Basel Malerei & Spritzerei",
    "wof:placetype":"venue"
},
  "geometry": {"coordinates":[7.551928997,47.5471954346],"type":"Point"}
}