{
  "type": "Feature",
  "properties": {
    "iso:country":"CH",
    "sg:address":"Aeschi 6410 Goldau. Postfach",
    "sg:city":"Goldau",
    "sg:orig_category":"Verwaltung von Immobilien",
    "sg:postcode":"6410",
    "sg:province":"Schwyz",
    "wof:name":"Affaires Immobili\u00e8res Dumuid Catherine",
    "wof:placetype":"venue"
},
  "geometry": {"coordinates":[6.6775941849,46.5586891174],"type":"Point"}
}