{
  "type": "Feature",
  "properties": {
    "iso:country":"CH",
    "sg:address":"Hauptstrasse 8",
    "sg:city":"Oberr\u00fcti",
    "sg:classifiers":[
        {
            "category":"Manufacturing",
            "subcategory":"Building Materials",
            "type":"Manufacturing & Wholesale Goods"
        }
    ],
    "sg:phone":"+41 41 787 23 10",
    "sg:postcode":"5647",
    "sg:province":"Aargau",
    "sg:tags":[
        "insulating",
        "cellulose"
    ],
    "wof:name":"Goetschi Isolationstechnik Gmbh",
    "wof:placetype":"venue"
},
  "geometry": {"coordinates":[8.3942117691,47.1647262573],"type":"Point"}
}