{
  "type": "Feature",
  "properties": {
    "iso:country":"CH",
    "sg:address":"Mettlenstrasse 5 9050 Appenzell. Postfach 35",
    "sg:city":"Appenzell",
    "sg:orig_category":"Herstellung von Metallerzeugnissen ohne Maschinenbau Herstellung von elektrischen Haushaltsger\u00e4ten",
    "sg:phone":"+41 71 787 48 28",
    "sg:postcode":"9050",
    "sg:province":"Appenzell Innerhoden",
    "wof:name":"Elektro Schwizer Ag",
    "wof:placetype":"venue"
},
  "geometry": {"coordinates":[9.4021043777,47.3347549438],"type":"Point"}
}