{
  "type": "Feature",
  "properties": {
    "addr:full":"Rue Basse 17-19 Grandson Vaud 1422",
    "addr:postcode":"17-19;1422",
    "addr:street":"Rue Basse",
    "iso:country":"CH",
    "sg:address":"Rue Basse 17-19",
    "sg:city":"Grandson",
    "sg:orig_category":"Architektur U Ingenieurb\u00fcros",
    "sg:postcode":"1422",
    "sg:province":"Vaud",
    "wof:name":"Fast, Philippe Fehlbaum",
    "wof:placetype":"venue"
},
  "geometry": {"coordinates":[6.64453,46.808121],"type":"Point"}
}