{
  "type": "Feature",
  "properties": {
    "iso:country":"CH",
    "sg:address":"Z\u00fcrichstrasse 70",
    "sg:city":"Br\u00fcttisellen",
    "sg:orig_category":"Chemische Industrie",
    "sg:phone":"+41 18882615",
    "sg:postcode":"8306",
    "sg:province":"Z\u00fcrich",
    "wof:name":"Coop Tankstelle",
    "wof:placetype":"venue"
},
  "geometry": {"coordinates":[8.625624,47.419701],"type":"Point"}
}