{
  "type": "Feature",
  "properties": {
    "iso:country":"CH",
    "sg:address":"M\u00fchleweg 3 4112 B\u00e4ttwil. Postfach",
    "sg:city":"B\u00e4ttwil",
    "sg:orig_category":"Unternehmensberatung",
    "sg:phone":"+41 61 731 35 72",
    "sg:postcode":"4112",
    "sg:province":"Solothurn",
    "wof:name":"Consulting Scherler J\u00f6rg H. Unternehmensberatung",
    "wof:placetype":"venue"
},
  "geometry": {"coordinates":[7.5077462196,47.49010849],"type":"Point"}
}