{
  "type": "Feature",
  "properties": {
    "iso:country":"CH",
    "sg:address":"Landstrasse",
    "sg:city":"Klosters",
    "sg:orig_category":"Detailhandel mit Bekleidung Detailhandel mit Sportartikeln",
    "sg:postcode":"7250",
    "sg:province":"Graubunden",
    "wof:name":"Bardill - Sport Ag Sporthaus",
    "wof:placetype":"venue"
},
  "geometry": {"coordinates":[9.879498,46.881596],"type":"Point"}
}