{
  "type": "Feature",
  "properties": {
    "iso:country":"CH",
    "sg:address":"Toggwilerstrasse 11",
    "sg:city":"Meilen",
    "sg:orig_category":"Interessenvertretungen",
    "sg:phone":"+41 19236509",
    "sg:postcode":"8706",
    "sg:province":"Z\u00fcrich",
    "wof:name":"Egn\u00e9r Dr. Margrit-stiftung",
    "wof:placetype":"venue"
},
  "geometry": {"coordinates":[8.647567749,47.2744827271],"type":"Point"}
}