{
  "type": "Feature",
  "properties": {
    "iso:country":"CH",
    "sg:address":"Niederlenzer Kirchweg 15",
    "sg:city":"Lenzburg",
    "sg:orig_category":"Herstellung von Fenstern U T\u00fcren aus Holz Herstellung von Konstruktionsteilen, Fertigbauteilen U Aus",
    "sg:phone":"+41 62 888 80 50",
    "sg:postcode":"5600",
    "sg:province":"Aargau",
    "wof:name":"Alpsteg Fenster Ag",
    "wof:placetype":"venue"
},
  "geometry": {"coordinates":[8.1738996506,47.394618988],"type":"Point"}
}