{
  "type": "Feature",
  "properties": {
    "iso:country":"CH",
    "sg:address":"Blauenstrasse 13",
    "sg:city":"Therwil",
    "sg:orig_category":"Grosshandel mit medizinischen U orthop\u00e4dischen Artikeln",
    "sg:phone":"+41 61 721 28 73",
    "sg:postcode":"4106",
    "sg:province":"Basel-Landschaft",
    "wof:name":"Dr.hermann Keck & Partner Gmbh Laborbedarf",
    "wof:placetype":"venue"
},
  "geometry": {"coordinates":[7.5664710999,47.4972686768],"type":"Point"}
}