{
  "type": "Feature",
  "properties": {
    "iso:country":"CH",
    "sg:address":"Cholplatzweg 28",
    "sg:city":"Trimmis",
    "sg:orig_category":"Herstellung von Metallkonstruktionen Mechanik",
    "sg:phone":"+41 81 353 50 45",
    "sg:postcode":"7203",
    "sg:province":"Graubunden",
    "wof:name":"Ns Metallbau Schrofer N.",
    "wof:placetype":"venue"
},
  "geometry": {"coordinates":[9.5536136627,46.9026908875],"type":"Point"}
}