{
  "type": "Feature",
  "properties": {
    "iso:country":"CH",
    "sg:address":"Technikumstrasse 90 8400 Winterthur. Postfach",
    "sg:city":"Winterthur",
    "sg:orig_category":"Arbeitnehmerverb\u00e4nde",
    "sg:phone":"+41 52 212 29 78",
    "sg:postcode":"8401",
    "sg:province":"Z\u00fcrich",
    "wof:name":"Gewerkschaft Bau & Industrie Sekretariat",
    "wof:placetype":"venue"
},
  "geometry": {"coordinates":[8.725334,47.498516],"type":"Point"}
}