{
  "type": "Feature",
  "properties": {
    "addr:full":"Kohlenberg 1 4051 Basel. Postfach Basel Basel-Stadt 4001",
    "addr:housenumber":"1",
    "addr:postcode":"4051;4001",
    "addr:street":"Kohlenberg;Postfach",
    "iso:country":"CH",
    "sg:address":"Kohlenberg 1 4051 Basel. Postfach",
    "sg:city":"Basel",
    "sg:orig_category":"Berufliche Weiterbildung, Erwachsenenbildung Sprachschulen",
    "sg:phone":"+41 61 226 90 90",
    "sg:postcode":"4001",
    "sg:province":"Basel-Stadt",
    "wof:name":"Els Schulen Usa First Study Ag",
    "wof:placetype":"venue"
},
  "geometry": {"coordinates":[7.589,47.554131],"type":"Point"}
}