{
  "type": "Feature",
  "properties": {
    "iso:country":"CH",
    "sg:address":"Forchstrasse 224",
    "sg:city":"Z\u00fcrich",
    "sg:orig_category":"Elektroinstallation",
    "sg:phone":"+41 13814095",
    "sg:postcode":"8032",
    "sg:province":"Z\u00fcrich",
    "wof:name":"Bertogg Ag",
    "wof:placetype":"venue"
},
  "geometry": {"coordinates":[8.5697917938,47.3592643738],"type":"Point"}
}