{
  "type": "Feature",
  "properties": {
    "iso:country":"CH",
    "sg:address":"3507 Biglen. Postfach 5",
    "sg:city":"Biglen",
    "sg:classifiers":[
        {
            "category":"Arena",
            "subcategory":"Sports Club",
            "type":"Entertainment"
        }
    ],
    "sg:phone":"+41 31 839 25 24",
    "sg:postcode":"3507",
    "sg:province":"Bern",
    "sg:tags":[
        "karate",
        "judo",
        "sportvereine"
    ],
    "wof:name":"Jjjc Biglen",
    "wof:placetype":"venue"
},
  "geometry": {"coordinates":[7.6302599907,46.9310417175],"type":"Point"}
}