{
  "type": "Feature",
  "properties": {
    "iso:country":"CH",
    "sg:address":"Via Moncucco 11",
    "sg:city":"Lugano",
    "sg:orig_category":"Detailhandel mit elektrischen Haushalts-,Radio U Fernsehger\u00e4ten sowie Musikinstrumenten",
    "sg:postcode":"6900",
    "sg:province":"Ticino",
    "wof:name":"Ben Video Benamane Kemal Karim",
    "wof:placetype":"venue"
},
  "geometry": {"coordinates":[8.9414024353,46.0048866272],"type":"Point"}
}