{
  "type": "Feature",
  "properties": {
    "iso:country":"CH",
    "sg:address":"Seestrasse 14b 5432 Neuenhof. Postfach",
    "sg:city":"Untersiggenthal",
    "sg:orig_category":"Elektroinstallation",
    "sg:phone":"+41 56 288 24 82",
    "sg:postcode":"5417",
    "sg:province":"Aargau",
    "wof:name":"Graf + Locher Engineering Ag",
    "wof:placetype":"venue"
},
  "geometry": {"coordinates":[8.3241167068,47.4556694031],"type":"Point"}
}