{
  "type": "Feature",
  "properties": {
    "iso:country":"CH",
    "sg:address":"Tiergartenrain 5 4054 Basel. Postfach",
    "sg:city":"Basel",
    "sg:orig_category":"Fachdetailhandel in Verkaufsr\u00e4umen",
    "sg:postcode":"4051",
    "sg:province":"Basel-Stadt",
    "wof:name":"Anita Teuwen Kunstgegenst\u00e4nde, Textilien; Handel",
    "wof:placetype":"venue"
},
  "geometry": {"coordinates":[7.582048893,47.5499992371],"type":"Point"}
}