{
  "type": "Feature",
  "properties": {
    "iso:country":"CH",
    "sg:address":"Rain 20",
    "sg:city":"Aarau",
    "sg:orig_category":"Herstellung von sonstigen Nahrungsmitteln Sonstiger Detailhandel mit Waren verschiedener Art, Hauptr",
    "sg:phone":"+41 62 824 20 40",
    "sg:postcode":"5000",
    "sg:province":"Aargau",
    "wof:name":"Farfalla Duftladen Gisler Richard & Furrer",
    "wof:placetype":"venue"
},
  "geometry": {"coordinates":[8.044084549,47.3909301758],"type":"Point"}
}