{
  "type": "Feature",
  "properties": {
    "iso:country":"CH",
    "sg:address":"6866",
    "sg:city":"Meride",
    "sg:orig_category":"Wirtschaftspr\u00fcfung, Steuerberatung U Treuhand",
    "sg:phone":"+41 91 646 96 41",
    "sg:postcode":"6866",
    "sg:province":"Ticino",
    "wof:name":"Gianni Auriglietti Ufficio Fiduciario",
    "wof:placetype":"venue"
},
  "geometry": {"coordinates":[8.955031395,45.8902359009],"type":"Point"}
}