{
  "type": "Feature",
  "properties": {
    "iso:country":"CH",
    "sg:address":"Ringstrasse 5",
    "sg:city":"Kronb\u00fchl",
    "sg:orig_category":"Non-Classified Establishments",
    "sg:postcode":"9302",
    "wof:name":"Trimi Montage Thaci",
    "wof:placetype":"venue"
},
  "geometry": {"coordinates":[9.3922901154,47.4609107971],"type":"Point"}
}