{
  "type": "Feature",
  "properties": {
    "iso:country":"CH",
    "sg:address":"Treitengasse 16",
    "sg:city":"M\u00fcntschemier",
    "sg:orig_category":"Gem\u00fcsebau",
    "sg:phone":"+41 32 313 32 63",
    "sg:postcode":"3225",
    "sg:province":"Bern",
    "wof:name":"Bruno Scheurer Gem\u00fcsebau",
    "wof:placetype":"venue"
},
  "geometry": {"coordinates":[7.146253109,46.9968185425],"type":"Point"}
}