{
  "type": "Feature",
  "properties": {
    "iso:country":"CH",
    "sg:address":"Z\u00fcrcherstr. 7 Birri",
    "sg:city":"Aristau",
    "sg:classifiers":[
        {
            "category":"Travel",
            "subcategory":"Hotels & Motels",
            "type":"Entertainment"
        }
    ],
    "sg:postcode":"5628",
    "sg:province":"Aargau",
    "sg:tags":[
        "hotels",
        "mit",
        "restaurant"
    ],
    "wof:name":"Max Koch-hirtle",
    "wof:placetype":"venue"
},
  "geometry": {"coordinates":[8.3617992401,47.2870178223],"type":"Point"}
}