{
  "type": "Feature",
  "properties": {
    "iso:country":"CH",
    "sg:address":"Avenue De Rumine 7",
    "sg:city":"Lausanne",
    "sg:orig_category":"Detailhandel mit Geschenkartikeln U Souvenirs Herstellung von Oberbekleidung",
    "sg:phone":"+41 21 311 49 78",
    "sg:postcode":"1005",
    "sg:province":"Vaud",
    "wof:name":"Cordey C.",
    "wof:placetype":"venue"
},
  "geometry": {"coordinates":[6.6387891769,46.5176963806],"type":"Point"}
}