{
  "type": "Feature",
  "properties": {
    "iso:country":"CH",
    "sg:address":"Adlergartenstrasse",
    "sg:city":"Schattdorf",
    "sg:orig_category":"Vorschulen, Kinderg\u00e4rten",
    "sg:phone":"+41 41 870 98 22",
    "sg:postcode":"6467",
    "sg:province":"Uri",
    "wof:name":"Kindergarten",
    "wof:placetype":"venue"
},
  "geometry": {"coordinates":[8.6500701904,46.8646125793],"type":"Point"}
}