{
  "type": "Feature",
  "properties": {
    "iso:country":"CH",
    "sg:address":"Patinoire 1884 Villars-sur-ollon. Postfach",
    "sg:city":"Villars-sur-ollon",
    "sg:orig_category":"Sonstige mit Sport verbundene T\u00e4tigkeiten",
    "sg:postcode":"1884",
    "sg:province":"Vaud",
    "wof:name":"Villars Ski School, Thierry Chevalley",
    "wof:placetype":"venue"
},
  "geometry": {"coordinates":[6.9953799248,46.2966117859],"type":"Point"}
}