{
  "type": "Feature",
  "properties": {
    "iso:country":"CH",
    "sg:address":"Sch\u00fctzengasse 8",
    "sg:city":"Erstfeld",
    "sg:orig_category":"Non-Classified Establishments",
    "sg:phone":"+41 41 880 05 45",
    "sg:postcode":"6472",
    "sg:province":"Uri",
    "wof:name":"\u00dcrner Stei B\u00fcd\u00e4 Steinmetzbetrieb",
    "wof:placetype":"venue"
},
  "geometry": {"coordinates":[8.652340889,46.8201141357],"type":"Point"}
}