{
  "type": "Feature",
  "properties": {
    "iso:country":"CH",
    "sg:address":"Lagerstrasse 14",
    "sg:city":"D\u00fcbendorf",
    "sg:classifiers":[
        {
            "category":"Communications",
            "type":"Services"
        }
    ],
    "sg:phone":"+41 18202266",
    "sg:postcode":"8600",
    "sg:province":"Z\u00fcrich",
    "sg:tags":[
        "radar",
        "sensor"
    ],
    "wof:name":"Ces Complete Electronics Systems Ag",
    "wof:placetype":"venue"
},
  "geometry": {"coordinates":[8.6035528183,47.4002456665],"type":"Point"}
}