{
  "type": "Feature",
  "properties": {
    "addr:full":"Rumi Dagmersellen Luzern 6252",
    "addr:postcode":"6252",
    "iso:country":"CH",
    "sg:address":"Rumi",
    "sg:city":"Dagmersellen",
    "sg:orig_category":"Dauerkulturbau Rebbau",
    "sg:phone":"+41 62 756 00 55",
    "sg:postcode":"6252",
    "sg:province":"Luzern",
    "wof:name":"Markus & Thomas Bisang",
    "wof:placetype":"venue"
},
  "geometry": {"coordinates":[7.989055,47.213055],"type":"Point"}
}