{
  "type": "Feature",
  "properties": {
    "iso:country":"CH",
    "sg:address":"Platz 229",
    "sg:city":"Walzenhausen",
    "sg:orig_category":"Blueing Tools",
    "sg:phone":"+41 71 886 49 00",
    "sg:postcode":"9428",
    "sg:province":"Appenzell Ausserrhoden",
    "wof:name":"Weiss Ag",
    "wof:placetype":"venue"
},
  "geometry": {"coordinates":[9.610206,47.442974],"type":"Point"}
}