{
  "type": "Feature",
  "properties": {
    "iso:country":"CH",
    "sg:address":"B\u00e4chlerstrasse 44",
    "sg:city":"Z\u00fcrich",
    "sg:orig_category":"Softwareentwicklung U beratung",
    "sg:phone":"+41 61 753 84 25",
    "sg:postcode":"8046",
    "sg:province":"Z\u00fcrich",
    "wof:name":"Pi-device Ag Forschungs, Entwicklungs, Herstellungs- U. Handelsunternehmung Von Elektron. Ger\u00e4ten Mit Software",
    "wof:placetype":"venue"
},
  "geometry": {"coordinates":[7.5985097885,47.4770698547],"type":"Point"}
}