{
  "type": "Feature",
  "properties": {
    "iso:country":"CH",
    "sg:address":"Rue Du Lac 34",
    "sg:city":"Yverdon-les-bains",
    "sg:orig_category":"Schnelldruck U Kopierservice",
    "sg:phone":"+41 24 445 33 35",
    "sg:postcode":"1400",
    "sg:province":"Vaud",
    "wof:name":"Copy Service",
    "wof:placetype":"venue"
},
  "geometry": {"coordinates":[6.6395101547,46.7796173096],"type":"Point"}
}