{
  "type": "Feature",
  "properties": {
    "iso:country":"CH",
    "sg:address":"Effingerstrasse 16",
    "sg:city":"Bern",
    "sg:orig_category":"Unclassifiable Establishments",
    "sg:postcode":"3008",
    "sg:province":"Bern",
    "wof:name":"Tong Yang Group Ag",
    "wof:placetype":"venue"
},
  "geometry": {"coordinates":[7.4217600822,46.9446487427],"type":"Point"}
}