{
  "type": "Feature",
  "properties": {
    "iso:country":"CH",
    "sg:address":"Teichstrasse 36",
    "sg:city":"Therwil",
    "sg:orig_category":"Architekturb\u00fcros",
    "sg:phone":"+41 61 721 46 43",
    "sg:postcode":"4106",
    "sg:province":"Basel-Landschaft",
    "wof:name":"Max Itin Architekturb\u00fcro",
    "wof:placetype":"venue"
},
  "geometry": {"coordinates":[7.550942,47.501369],"type":"Point"}
}