{
  "type": "Feature",
  "properties": {
    "iso:country":"CH",
    "sg:address":"Fliederstrasse 6",
    "sg:city":"Bischofszell",
    "sg:orig_category":"Bauschreinerei G\u00fcterbef\u00f6rderung im Strassenverkehr",
    "sg:phone":"+41 71 422 40 87",
    "sg:postcode":"9220",
    "sg:province":"Thurgau",
    "wof:name":"Felix D\u00f6rflinger Transporte & Schreinerei",
    "wof:placetype":"venue"
},
  "geometry": {"coordinates":[9.25175,47.495087],"type":"Point"}
}