{
  "type": "Feature",
  "properties": {
    "iso:country":"CH",
    "sg:address":"Jennerweg 5a 3000 Bern. Postfach",
    "sg:city":"Bern",
    "sg:orig_category":"Interessenvertretungen",
    "sg:postcode":"3005",
    "sg:province":"Bern",
    "wof:name":"Mcdonald Ronald Haus Stiftung Bern",
    "wof:placetype":"venue"
},
  "geometry": {"coordinates":[7.4262042046,46.9464111328],"type":"Point"}
}