{
  "type": "Feature",
  "properties": {
    "iso:country":"CH",
    "sg:address":"Via Gregorio Mantegazza",
    "sg:city":"Locarno",
    "sg:classifiers":[
        {
            "category":"Restaurant",
            "type":"Food & Drink"
        }
    ],
    "sg:phone":"+41 91 751 21 35",
    "sg:postcode":"6600",
    "sg:province":"Ticino",
    "wof:name":"Ristorante Stella D'italia",
    "wof:placetype":"venue"
},
  "geometry": {"coordinates":[8.7942647934,46.1657409668],"type":"Point"}
}