{
  "type": "Feature",
  "properties": {
    "iso:country":"CH",
    "sg:address":"Kirchbergstrasse 3 3400 Burgdorf. Postfach",
    "sg:city":"Burgdorf",
    "sg:orig_category":"Grosshandel mit Erzen U Metallen",
    "sg:phone":"+41 34 427 27 27",
    "sg:postcode":"3401",
    "sg:province":"Bern",
    "wof:name":"Egger & Co Ag, Eisen & Metalle, Burgdorf",
    "wof:placetype":"venue"
},
  "geometry": {"coordinates":[7.6242508888,47.0611991882],"type":"Point"}
}