{
  "type": "Feature",
  "properties": {
    "iso:country":"CH",
    "sg:address":"R\u00fcmligenstrasse 15",
    "sg:city":"R\u00fcmligen",
    "sg:orig_category":"Sonstige k\u00fcnstlerische U schriftstellerische T\u00e4tigkeiten U Darbietungen",
    "sg:phone":"+41 31 809 29 09",
    "sg:postcode":"3128",
    "sg:province":"Bern",
    "wof:name":"Andr\u00e9 Egli Restaurationen",
    "wof:placetype":"venue"
},
  "geometry": {"coordinates":[7.4966468811,46.8306655884],"type":"Point"}
}