{
  "type": "Feature",
  "properties": {
    "iso:country":"CH",
    "sg:address":"Bahnhofstr. 22",
    "sg:city":"Huttwil",
    "sg:orig_category":"Unterrichtswesen",
    "sg:phone":"+41 62 962 21 20",
    "sg:postcode":"4950",
    "sg:province":"Bern",
    "wof:name":"Blatter Wicki Ag Papeterie-buchhandlung",
    "wof:placetype":"venue"
},
  "geometry": {"coordinates":[7.845053196,47.1140441895],"type":"Point"}
}