{
  "type": "Feature",
  "properties": {
    "iso:country":"CH",
    "sg:address":"Nefenstrasse 22 9435 Heerbrugg. Postfach",
    "sg:city":"Heerbrugg",
    "sg:orig_category":"Gesundheitswesen",
    "sg:postcode":"9435",
    "sg:province":"St. Gallen",
    "wof:name":"Mesana - Messmer Ruth Massagen Zur Gesundheitsf\u00f6rderung. Kurse, Gesundheits- U. Lebensberatung Usw.",
    "wof:placetype":"venue"
},
  "geometry": {"coordinates":[9.6219549179,47.4074363708],"type":"Point"}
}