{
  "type": "Feature",
  "properties": {
    "iso:country":"CH",
    "sg:address":"In Der Ey 22 8047 Z\u00fcrich. Postfach 513",
    "sg:city":"Z\u00fcrich",
    "sg:orig_category":"Erschliessung von Grundst\u00fccken",
    "sg:phone":"+41 14011414",
    "sg:postcode":"8047",
    "sg:province":"Z\u00fcrich",
    "wof:name":"Baugenossenschaft Sch\u00f6nheim Preisw. Wohnungen, Land, Baurechte, Solide Wohnh\u00e4user Usw",
    "wof:placetype":"venue"
},
  "geometry": {"coordinates":[8.4861183167,47.3742637634],"type":"Point"}
}