{
  "type": "Feature",
  "properties": {
    "iso:country":"CH",
    "sg:address":"Kirchgasse 50",
    "sg:city":"Z\u00fcrich",
    "sg:orig_category":"Finanzierungsinstitutionen Verm\u00f6gensverwaltung",
    "sg:phone":"+41 12536970",
    "sg:postcode":"8001",
    "sg:province":"Z\u00fcrich",
    "wof:name":"Aa&v Finanz Ag",
    "wof:placetype":"venue"
},
  "geometry": {"coordinates":[8.5466480255,47.3707084656],"type":"Point"}
}