{
  "type": "Feature",
  "properties": {
    "iso:country":"CH",
    "sg:address":"Madretschstrasse 16",
    "sg:city":"Biel/bienne",
    "sg:orig_category":"Detailhandel mit Spielwaren",
    "sg:phone":"+41 32 365 04 64",
    "sg:postcode":"2503",
    "sg:province":"Bern",
    "wof:name":"Pl\u00fcsch-paradies",
    "wof:placetype":"venue"
},
  "geometry": {"coordinates":[7.2532849312,47.1327095032],"type":"Point"}
}