{
  "type": "Feature",
  "properties": {
    "iso:country":"CH",
    "sg:address":"1742",
    "sg:city":"Autigny",
    "sg:orig_category":"Verarbeitung von Milch Verwertung von Milch",
    "sg:postcode":"1742",
    "sg:province":"Fribourg",
    "wof:name":"Soci\u00e9t\u00e9 De Laiterie D'ecublens-eschiens",
    "wof:placetype":"venue"
},
  "geometry": {"coordinates":[6.8084278107,46.609588623],"type":"Point"}
}