{
  "type": "Feature",
  "properties": {
    "iso:country":"CH",
    "sg:address":"M\u00fchlebach 6375 Beckenried. Postfach",
    "sg:city":"Beckenried",
    "sg:orig_category":"Interessenvertretungen",
    "sg:postcode":"6375",
    "sg:province":"Nidwalden",
    "wof:name":"Schellenberg-stiftung Ingeborg Und Walter",
    "wof:placetype":"venue"
},
  "geometry": {"coordinates":[8.4834365845,46.9624938965],"type":"Point"}
}