{
  "type": "Feature",
  "properties": {
    "addr:full":"Dorfstrasse 40 Schindellegi Schwyz 8834",
    "addr:housenumber":"40",
    "addr:postcode":"8834",
    "addr:street":"Dorfstrasse;Schwyz",
    "iso:country":"CH",
    "sg:address":"Dorfstrasse 40",
    "sg:city":"Schindellegi",
    "sg:orig_category":"Bauschreinerei Herstellung von sonstigen M\u00f6beln",
    "sg:phone":"+41 17846938",
    "sg:postcode":"8834",
    "sg:province":"Schwyz",
    "wof:name":"Kyburz Rudolf",
    "wof:placetype":"venue"
},
  "geometry": {"coordinates":[8.709291,47.177372],"type":"Point"}
}