{
  "type": "Feature",
  "properties": {
    "iso:country":"CH",
    "sg:address":"Grosse Kirchgasse 3",
    "sg:city":"Mellingen",
    "sg:orig_category":"Grosshandel mit B\u00fcromaschinen Grosshandel mit Datenverarbeitungsger\u00e4ten",
    "sg:phone":"+41 41 729 09 35",
    "sg:postcode":"5507",
    "sg:province":"Aargau",
    "wof:name":"Iumentum Gmbh",
    "wof:placetype":"venue"
},
  "geometry": {"coordinates":[8.7644128799,47.3074951172],"type":"Point"}
}