{
  "type": "Feature",
  "properties": {
    "iso:country":"CH",
    "sg:address":"Kirschgartenweg 6 4419 Lupsingen. Postfach 29",
    "sg:city":"Lupsingen",
    "sg:orig_category":"Detailhandel mit M\u00f6beln U Haushaltsgegenst\u00e4nden Grosshandel mit M\u00f6beln, Wohnbedarf, Teppichen U Bode",
    "sg:phone":"+41 17613020",
    "sg:postcode":"4419",
    "sg:province":"Basel-Landschaft",
    "wof:name":"Egetaepper Ag",
    "wof:placetype":"venue"
},
  "geometry": {"coordinates":[8.4538841248,47.2802848816],"type":"Point"}
}