{
  "type": "Feature",
  "properties": {
    "iso:country":"CH",
    "sg:address":"7435",
    "sg:city":"Spl\u00fcgen",
    "sg:orig_category":"Schulpflegen",
    "sg:postcode":"7435",
    "sg:province":"Graubunden",
    "wof:name":"Schulrat Der Gemeinde St.gallenkappel",
    "wof:placetype":"venue"
},
  "geometry": {"coordinates":[8.9673299789,47.2448883057],"type":"Point"}
}