{
  "type": "Feature",
  "properties": {
    "iso:country":"CH",
    "sg:address":"Seestrasse 20",
    "sg:city":"Altendorf",
    "sg:orig_category":"Unclassifiable Establishments",
    "sg:phone":"+41 81 632 61 11",
    "sg:postcode":"8852",
    "sg:province":"Schwyz",
    "wof:name":"Swissco Group Sa",
    "wof:placetype":"venue"
},
  "geometry": {"coordinates":[8.8249673843,47.1940956116],"type":"Point"}
}