{
  "type": "Feature",
  "properties": {
    "addr:full":"Juraweg 15 Hindelbank Bern 3324",
    "addr:housenumber":"15",
    "addr:postcode":"3324",
    "addr:street":"Juraweg",
    "iso:country":"CH",
    "sg:address":"Juraweg 15",
    "sg:city":"Hindelbank",
    "sg:orig_category":"Allgemeiner Hoch U Tiefbau",
    "sg:postcode":"3324",
    "sg:province":"Bern",
    "wof:name":"General Bau Gmbh",
    "wof:placetype":"venue"
},
  "geometry": {"coordinates":[7.54331,47.051682],"type":"Point"}
}