{
  "type": "Feature",
  "properties": {
    "iso:country":"CH",
    "sg:address":"Burgwiesenstrasse 3a",
    "sg:city":"Hittnau",
    "sg:orig_category":"Architektur U Ingenieurb\u00fcros Sonstige technische Beratung U Planung",
    "sg:phone":"+41 19510666",
    "sg:postcode":"8335",
    "sg:province":"Z\u00fcrich",
    "wof:name":"Beat Hediger Architekturb\u00fcro",
    "wof:placetype":"venue"
},
  "geometry": {"coordinates":[8.831657,47.364349],"type":"Point"}
}