{
  "type": "Feature",
  "properties": {
    "iso:country":"CH",
    "sg:address":"Z\u00fcrcherstrasse 63",
    "sg:city":"Baden",
    "sg:orig_category":"Maurerarbeiten Sonstiger spezialisierter Hoch U Tiefbau",
    "sg:phone":"+41 56 222 16 85",
    "sg:postcode":"5400",
    "sg:province":"Aargau",
    "wof:name":"Stutz G. & Co",
    "wof:placetype":"venue"
},
  "geometry": {"coordinates":[8.3061408997,47.46534729],"type":"Point"}
}