{
  "type": "Feature",
  "properties": {
    "iso:country":"CH",
    "sg:address":"Lattrigenweg 2",
    "sg:city":"Hermrigen",
    "sg:orig_category":"Herstellung von k\u00e4lte U lufttechnischen Erzeugnissen f\u00fcr gewerbliche Zwecke",
    "sg:postcode":"3274",
    "sg:province":"Bern",
    "wof:name":"Cool-tec Gmbh",
    "wof:placetype":"venue"
},
  "geometry": {"coordinates":[7.2426371574,47.0822982788],"type":"Point"}
}