{
  "type": "Feature",
  "properties": {
    "iso:country":"CH",
    "sg:address":"Rue Hans-geiler 2",
    "sg:city":"Fribourg",
    "sg:orig_category":"Grosshandel mit Holz U Baustoffen",
    "sg:phone":"+41 26 322 46 41",
    "sg:postcode":"1700",
    "sg:province":"Fribourg",
    "wof:name":"Favre Ren\u00e9",
    "wof:placetype":"venue"
},
  "geometry": {"coordinates":[7.1532559395,46.7995185852],"type":"Point"}
}