{
  "type": "Feature",
  "properties": {
    "iso:country":"CH",
    "sg:address":"Route Du Rawyl 11",
    "sg:city":"Sierre",
    "sg:orig_category":"Fahrschulen, Flugschulen",
    "sg:phone":"+41 79 301 35 82",
    "sg:postcode":"3960",
    "sg:province":"Valais",
    "wof:name":"Christina Nilsson Auto-\u00e9cole",
    "wof:placetype":"venue"
},
  "geometry": {"coordinates":[6.8571820259,46.9659881592],"type":"Point"}
}