{
  "type": "Feature",
  "properties": {
    "iso:country":"CH",
    "sg:address":"V. Cantonale",
    "sg:city":"Riazzino",
    "sg:classifiers":[
        {
            "category":"Manufacturing",
            "subcategory":"Tools & Machinery",
            "type":"Manufacturing & Wholesale Goods"
        }
    ],
    "sg:phone":"+41 52 763 33 88",
    "sg:postcode":"6595",
    "sg:province":"Ticino",
    "sg:tags":[
        "equipment",
        "measurement",
        "-",
        "precision",
        "instrument"
    ],
    "wof:name":"Becatron Ag",
    "wof:placetype":"venue"
},
  "geometry": {"coordinates":[8.9935703278,47.5989227295],"type":"Point"}
}