{
  "type": "Feature",
  "properties": {
    "iso:country":"CH",
    "sg:address":"Winterthurerstrasse 72",
    "sg:city":"Uster",
    "sg:orig_category":"Telecomshops",
    "sg:phone":"+41 19415308",
    "sg:postcode":"8610",
    "sg:province":"Z\u00fcrich",
    "wof:name":"Marco Gio\u00e9 Natelhandel",
    "wof:placetype":"venue"
},
  "geometry": {"coordinates":[8.7114038467,47.3595428467],"type":"Point"}
}