{
  "type": "Feature",
  "properties": {
    "iso:country":"CH",
    "sg:address":"R\u00f6hrliberg 18",
    "sg:city":"Cham",
    "sg:orig_category":"Reiseb\u00fcros",
    "sg:phone":"+41 33 733 33 33",
    "sg:postcode":"6330",
    "sg:province":"Zug",
    "wof:name":"Oehrli's Reiseb\u00fcro",
    "wof:placetype":"venue"
},
  "geometry": {"coordinates":[7.4422779083,46.4571418762],"type":"Point"}
}