{
  "type": "Feature",
  "properties": {
    "iso:country":"CH",
    "sg:address":"Rue De Saint-gu\u00e9rin 16 1950 Sitten. Postfach",
    "sg:city":"Sion",
    "sg:orig_category":"Oberfl\u00e4chenveredlung U W\u00e4rmebehandlung",
    "sg:phone":"+41 32 652 14 63",
    "sg:postcode":"1951",
    "sg:province":"Valais",
    "wof:name":"Schelling & Arnaboldi Gmbh Galvanotechnik",
    "wof:placetype":"venue"
},
  "geometry": {"coordinates":[7.3900032043,47.1945953369],"type":"Point"}
}