{
  "type": "Feature",
  "properties": {
    "iso:country":"CH",
    "sg:address":"Hauptstrasse 68",
    "sg:city":"K\u00f6lliken",
    "sg:orig_category":"Detailhandel mit Spielwaren Detailhandel mit S\u00e4uglings U Kinderbekleidung",
    "sg:phone":"+41 61 712 14 18",
    "sg:postcode":"5742",
    "sg:province":"Aargau",
    "wof:name":"Secondhand Strizzi Kinderkleider & Zubeh\u00f6r",
    "wof:placetype":"venue"
},
  "geometry": {"coordinates":[7.5944838524,47.4967651367],"type":"Point"}
}