{
  "type": "Feature",
  "properties": {
    "iso:country":"CH",
    "sg:address":"Sous Banbois 32",
    "sg:city":"Pr\u00eales",
    "sg:orig_category":"Unclassifiable Establishments",
    "sg:phone":"+41 32 315 18 28",
    "sg:postcode":"2515",
    "sg:province":"Bern",
    "wof:name":"Mecatech Automobiles S\u00e0rl",
    "wof:placetype":"venue"
},
  "geometry": {"coordinates":[7.130027771,47.0956611633],"type":"Point"}
}