{
  "type": "Feature",
  "properties": {
    "iso:country":"CH",
    "sg:address":"Grendelstrasse 19",
    "sg:city":"Luzern",
    "sg:classifiers":[
        {
            "category":"Restaurant",
            "type":"Food & Drink"
        }
    ],
    "sg:phone":"+41 41 410 52 22",
    "sg:postcode":"6004",
    "sg:province":"Luzern",
    "wof:name":"Restaurant M\u00f6venpick Am Grendel",
    "wof:placetype":"venue"
},
  "geometry": {"coordinates":[8.3071250916,47.053314209],"type":"Point"}
}