{
  "type": "Feature",
  "properties": {
    "iso:country":"CH",
    "sg:address":"Schlossbergstrasse 10a",
    "sg:city":"Zollikon",
    "sg:orig_category":"Architektur U Ingenieurb\u00fcros",
    "sg:phone":"+41 13919545",
    "sg:postcode":"8702",
    "sg:province":"Z\u00fcrich",
    "wof:name":"Ingenieur Und Planungsb\u00fcro B\u00fchlmann",
    "wof:placetype":"venue"
},
  "geometry": {"coordinates":[8.579958,47.345531],"type":"Point"}
}