{
  "type": "Feature",
  "properties": {
    "iso:country":"CH",
    "sg:address":"Rue De Lausanne 32 1950 Sion Case Postale 946",
    "sg:city":"Sion",
    "sg:orig_category":"Notariate",
    "sg:phone":"+41 34 461 15 85",
    "sg:postcode":"1951",
    "sg:province":"Valais",
    "wof:name":"Fritz Aeberhardt Notariatsb\u00fcro",
    "wof:placetype":"venue"
},
  "geometry": {"coordinates":[7.6849250793,47.0063858032],"type":"Point"}
}