{
  "type": "Feature",
  "properties": {
    "iso:country":"CH",
    "sg:address":"M\u00fchleweg 6",
    "sg:city":"Flums",
    "sg:orig_category":"Organisationen des Gesundheitswesen",
    "sg:phone":"+41 81 733 20 90",
    "sg:postcode":"8890",
    "sg:province":"St. Gallen",
    "wof:name":"Samariterverein Flums",
    "wof:placetype":"venue"
},
  "geometry": {"coordinates":[9.3428726196,47.089515686],"type":"Point"}
}