{
  "type": "Feature",
  "properties": {
    "iso:country":"CH",
    "sg:address":"Les Chavannes",
    "sg:city":"Saillon",
    "sg:orig_category":"Detailhandel mit Getr\u00e4nken",
    "sg:phone":"+41 27 744 24 91",
    "sg:postcode":"1913",
    "sg:province":"Valais",
    "wof:name":"Firmin Bertholet Commerce De Vins",
    "wof:placetype":"venue"
},
  "geometry": {"coordinates":[7.1837649345,46.1717414856],"type":"Point"}
}