{
  "type": "Feature",
  "properties": {
    "iso:country":"CH",
    "sg:address":"Stoossstrasse 4",
    "sg:city":"Bern",
    "sg:orig_category":"Detailhandel mit Uhren U Schmuck Grosshandel mit Schmuck",
    "sg:phone":"+41 31 382 99 40",
    "sg:postcode":"3008",
    "sg:province":"Bern",
    "wof:name":"M. Beugger & M. Hengartner",
    "wof:placetype":"venue"
},
  "geometry": {"coordinates":[7.4145088196,46.9429168701],"type":"Point"}
}