{
  "type": "Feature",
  "properties": {
    "iso:country":"CH",
    "sg:address":"Hafenstrasse 50",
    "sg:city":"Kreuzlingen",
    "sg:orig_category":"Non-Classified Establishments",
    "sg:phone":"+41 21 624 08 40",
    "sg:postcode":"8280",
    "sg:province":"Thurgau",
    "wof:name":"Gms Musco",
    "wof:placetype":"venue"
},
  "geometry": {"coordinates":[6.5833349228,46.5305404663],"type":"Point"}
}