{
  "type": "Feature",
  "properties": {
    "iso:country":"CH",
    "sg:address":"Rue De La Citadelle 2 2114 Fleurier Case Postale 224",
    "sg:city":"Fleurier",
    "sg:orig_category":"Grosshandel mit Getr\u00e4nken Grosshandel mit Wein U Spirituosen",
    "sg:phone":"+41 32 861 10 96",
    "sg:postcode":"2114",
    "sg:province":"Neuch\u00e2tel",
    "wof:name":"Cave De La Citadelle Jacot Et Cie Sa",
    "wof:placetype":"venue"
},
  "geometry": {"coordinates":[6.5850629807,46.9014015198],"type":"Point"}
}