{
  "type": "Feature",
  "properties": {
    "iso:country":"CH",
    "sg:address":"Dufourstrasse 18",
    "sg:city":"Bern",
    "sg:orig_category":"Handels-H\u00e4user U Gesellschaften",
    "sg:postcode":"3005",
    "sg:province":"Bern",
    "wof:name":"Zimmermann Charles",
    "wof:placetype":"venue"
},
  "geometry": {"coordinates":[8.5982561111,47.2960128784],"type":"Point"}
}