{
  "type": "Feature",
  "properties": {
    "iso:country":"CH",
    "sg:address":"Mattenstalden",
    "sg:city":"Weissenburg",
    "sg:orig_category":"G\u00fcterbef\u00f6rderung im Strassenverkehr",
    "sg:phone":"+41 33 783 13 07",
    "sg:postcode":"3764",
    "sg:province":"Bern",
    "wof:name":"Arthur Knutti Transporte",
    "wof:placetype":"venue"
},
  "geometry": {"coordinates":[7.4780130386,46.6574821472],"type":"Point"}
}