{
  "type": "Feature",
  "properties": {
    "iso:country":"CH",
    "sg:address":"Forchstrasse 92",
    "sg:city":"Z\u00fcrich",
    "sg:orig_category":"Arztpraxen",
    "sg:phone":"+41 13803636",
    "sg:postcode":"8008",
    "sg:province":"Z\u00fcrich",
    "wof:name":"Dres Med. Gyurech & Schilling Aerzte F.allgemeine Medizin",
    "wof:placetype":"venue"
},
  "geometry": {"coordinates":[8.55586,47.363972],"type":"Point"}
}