{
  "type": "Feature",
  "properties": {
    "addr:full":"Ulmenstrasse 14 Allschwil Basel-Landschaft 4123",
    "addr:housenumber":"14",
    "addr:postcode":"4123",
    "addr:street":"Ulmenstrasse",
    "iso:country":"CH",
    "sg:address":"Ulmenstrasse 14",
    "sg:city":"Allschwil",
    "sg:orig_category":"Arztpraxen",
    "sg:phone":"+41 61 481 33 45",
    "sg:postcode":"4123",
    "sg:province":"Basel-Landschaft",
    "wof:name":"Dres Med Teelmann & H\u00fcrlimann Spezial\u00e4rztinnen Fmh",
    "wof:placetype":"venue"
},
  "geometry": {"coordinates":[7.559261,47.559536],"type":"Point"}
}