{
  "type": "Feature",
  "properties": {
    "iso:country":"CH",
    "sg:address":"R\u00fctistrasse 45",
    "sg:city":"Jona",
    "sg:orig_category":"Maler U Glasergewerbe Malerei",
    "sg:phone":"+41 18411020",
    "sg:postcode":"8645",
    "sg:province":"St. Gallen",
    "wof:name":"Malergesch\u00e4ft G\u00fcrkan Hakim",
    "wof:placetype":"venue"
},
  "geometry": {"coordinates":[8.4627180099,47.453414917],"type":"Point"}
}