{
  "type": "Feature",
  "properties": {
    "iso:country":"CH",
    "sg:address":"Trevano Via 49",
    "sg:city":"Lugano",
    "sg:orig_category":"Finanzierungsinstitutionen",
    "sg:postcode":"6900",
    "sg:province":"Ticino",
    "wof:name":"Medelain Sa",
    "wof:placetype":"venue"
},
  "geometry": {"coordinates":[8.9559078217,46.0169448853],"type":"Point"}
}