{
  "type": "Feature",
  "properties": {
    "iso:country":"CH",
    "sg:address":"Grand Rue 16",
    "sg:city":"Echallens",
    "sg:orig_category":"Detailhandel mit Textilien",
    "sg:phone":"+41 32 931 29 86",
    "sg:postcode":"1040",
    "sg:province":"Vaud",
    "wof:name":"Boutique D'art Nelly Jacot Broderie",
    "wof:placetype":"venue"
},
  "geometry": {"coordinates":[6.7483859062,47.0565185547],"type":"Point"}
}