{
  "type": "Feature",
  "properties": {
    "addr:full":"Friedrichshafner Strasse 51 Romanshorn Thurgau 8590",
    "addr:housenumber":"51",
    "addr:postcode":"8590",
    "addr:street":"Friedrichshafner Strasse",
    "iso:country":"CH",
    "sg:address":"Friedrichshafner Strasse 51",
    "sg:city":"Romanshorn",
    "sg:orig_category":"Buchverlag Sonstiges Verlagsgewerbe",
    "sg:phone":"+41 71 466 90 80",
    "sg:postcode":"8590",
    "sg:province":"Thurgau",
    "wof:name":"Ediciones Arriba Gmbh",
    "wof:placetype":"venue"
},
  "geometry": {"coordinates":[9.373423,47.556915],"type":"Point"}
}