{
  "type": "Feature",
  "properties": {
    "iso:country":"CH",
    "sg:address":"G\u00e4ssli 17",
    "sg:city":"Netstal",
    "sg:classifiers":[
        {
            "category":"Insurance",
            "subcategory":"Insurance Agent",
            "type":"Services"
        }
    ],
    "sg:phone":"+41 55 640 44 20",
    "sg:postcode":"8754",
    "sg:province":"Glarus",
    "sg:tags":[
        "versicherungsagenturen",
        "-broker"
    ],
    "wof:name":"Helvetia Patria Versicherungen Agentur",
    "wof:placetype":"venue"
},
  "geometry": {"coordinates":[9.0513591766,47.0593566895],"type":"Point"}
}