{
  "type": "Feature",
  "properties": {
    "iso:country":"CH",
    "sg:address":"Zwinglistrasse 16",
    "sg:city":"Bern",
    "sg:orig_category":"Kosmetikinstitute",
    "sg:phone":"+41 31 371 05 07",
    "sg:postcode":"3007",
    "sg:province":"Bern",
    "wof:name":"Franziska Filliol Kosmetikinstitut",
    "wof:placetype":"venue"
},
  "geometry": {"coordinates":[7.4332590103,46.9350624084],"type":"Point"}
}