{
  "type": "Feature",
  "properties": {
    "iso:country":"CH",
    "sg:address":"Pr\u00e9s-courbes Chemin Des 7 1226 Th\u00f4nex. Postfach",
    "sg:city":"Th\u00f4nex",
    "sg:orig_category":"Finanzierungsinstitutionen",
    "sg:postcode":"1226",
    "sg:province":"Gen\u00e8ve",
    "wof:name":"Ayodhya Management Sa",
    "wof:placetype":"venue"
},
  "geometry": {"coordinates":[6.2115821838,46.1989021301],"type":"Point"}
}