{
  "type": "Feature",
  "properties": {
    "iso:country":"CH",
    "sg:address":"Favon Bvd Georges- 7 1204 Gen\u00e8ve. Postfach",
    "sg:city":"Gen\u00e8ve",
    "sg:orig_category":"Pensionskassen",
    "sg:postcode":"1201",
    "sg:province":"Gen\u00e8ve",
    "wof:name":"Fondation De Pr\u00e9voyance En Faveur Du Personnel De La Kredietbank (suisse) Sa Et Soci\u00e9t\u00e9s Apparent\u00e9es",
    "wof:placetype":"venue"
},
  "geometry": {"coordinates":[6.1401891708,46.2032012939],"type":"Point"}
}