{
  "type": "Feature",
  "properties": {
    "iso:country":"CH",
    "sg:address":"En Chamard 1442 Montagny-yverdon. Postfach",
    "sg:city":"Montagny-yverdon",
    "sg:orig_category":"Fachdetailhandel in Verkaufsr\u00e4umen",
    "sg:phone":"+41 71 633 21 77",
    "sg:postcode":"1442",
    "sg:province":"Vaud",
    "wof:name":"W\u00fcthrich Max",
    "wof:placetype":"venue"
},
  "geometry": {"coordinates":[9.1505317688,47.5507926941],"type":"Point"}
}