{
  "type": "Feature",
  "properties": {
    "iso:country":"CH",
    "sg:address":"Reutet En B",
    "sg:city":"Collombey",
    "sg:orig_category":"Mechanik",
    "sg:phone":"+41 81 630 07 17",
    "sg:postcode":"1868",
    "sg:province":"Valais",
    "wof:name":"Gr - Mechanik, Giovanoli & Rudolf",
    "wof:placetype":"venue"
},
  "geometry": {"coordinates":[9.4502401352,46.7011146545],"type":"Point"}
}