{
  "type": "Feature",
  "properties": {
    "iso:country":"CH",
    "sg:address":"Rue Des Annonciades 9",
    "sg:city":"Porrentruy",
    "sg:orig_category":"Advokaturb\u00fcros Notariate",
    "sg:phone":"+41 32 466 18 40",
    "sg:postcode":"2900",
    "sg:province":"Jura",
    "wof:name":"Daniel Farine Etude D'avocat & Notaire",
    "wof:placetype":"venue"
},
  "geometry": {"coordinates":[7.074794,47.416077],"type":"Point"}
}