{
  "type": "Feature",
  "properties": {
    "iso:country":"CH",
    "sg:address":"Schmiedengasse 12",
    "sg:city":"Biel/bienne",
    "sg:orig_category":"RESTAURANTS: TEA-ROOMS",
    "sg:phone":"+41 32 322 18 39",
    "sg:postcode":"2502",
    "sg:province":"Bern",
    "wof:name":"Tavola Calda Gmbh",
    "wof:placetype":"venue"
},
  "geometry": {"coordinates":[7.2461929321,47.1407966614],"type":"Point"}
}