{
  "type": "Feature",
  "properties": {
    "iso:country":"CH",
    "sg:address":"Kirchweg 22 8750 Glarus. Postfach",
    "sg:city":"Glarus",
    "sg:orig_category":"Erbringung von Dienstleistungen f\u00fcr Unternehmen Sonstige pers\u00f6nliche Dienstleistungen",
    "sg:phone":"+41 79 337 70 11",
    "sg:postcode":"8750",
    "sg:province":"Glarus",
    "wof:name":"Prisca Romer Gmbh",
    "wof:placetype":"venue"
},
  "geometry": {"coordinates":[9.0703868866,47.0385665894],"type":"Point"}
}