{
  "type": "Feature",
  "properties": {
    "iso:country":"CH",
    "sg:address":"Route De Berne 1",
    "sg:city":"Avenches",
    "sg:classifiers":[
        {
            "category":"Restaurant",
            "type":"Food & Drink"
        }
    ],
    "sg:phone":"+41 79 611 36 57",
    "sg:postcode":"1580",
    "sg:province":"Vaud",
    "wof:name":"Restaurant Des Bains",
    "wof:placetype":"venue"
},
  "geometry": {"coordinates":[7.0453081131,46.8831481934],"type":"Point"}
}