{
  "type": "Feature",
  "properties": {
    "iso:country":"CH",
    "sg:address":"Hauptstrasse 56",
    "sg:city":"Triboltingen",
    "sg:orig_category":"Kaminfeger",
    "sg:phone":"+41 71 664 23 48",
    "sg:postcode":"8273",
    "sg:province":"Thurgau",
    "wof:name":"Karl & Rita Sauter Kaminfegergesch\u00e4ft",
    "wof:placetype":"venue"
},
  "geometry": {"coordinates":[9.1109628677,47.6604385376],"type":"Point"}
}