{
  "type": "Feature",
  "properties": {
    "iso:country":"CH",
    "sg:address":"Rue Des Marach\u00eechers 38",
    "sg:city":"Gen\u00e8ve",
    "sg:orig_category":"Fachdetailhandel in Verkaufsr\u00e4umen",
    "sg:postcode":"1200",
    "sg:province":"Gen\u00e8ve",
    "wof:name":"S.e.m., Fallwickl Edeltraud",
    "wof:placetype":"venue"
},
  "geometry": {"coordinates":[6.1360368729,46.1985549927],"type":"Point"}
}