{
  "type": "Feature",
  "properties": {
    "iso:country":"CH",
    "sg:address":"Dorfstrasse 36",
    "sg:city":"Heimenhausen",
    "sg:orig_category":"Sportvereine Unihockey",
    "sg:phone":"+41 62 961 13 17",
    "sg:postcode":"3373",
    "sg:province":"Bern",
    "wof:name":"Uhc Racoons Heimenhausen",
    "wof:placetype":"venue"
},
  "geometry": {"coordinates":[7.6968388557,47.2066459656],"type":"Point"}
}