{
  "type": "Feature",
  "properties": {
    "iso:country":"CH",
    "sg:address":"Im Bockte 139",
    "sg:city":"Marthalen",
    "sg:orig_category":"Erwachsenenbildung U Unterricht",
    "sg:phone":"+41 52 319 19 90",
    "sg:postcode":"8460",
    "sg:province":"Z\u00fcrich",
    "wof:name":"Musik Klinger",
    "wof:placetype":"venue"
},
  "geometry": {"coordinates":[8.6509304047,47.6270294189],"type":"Point"}
}