{
  "type": "Feature",
  "properties": {
    "iso:country":"CH",
    "sg:address":"Seehaldenstrasse 13",
    "sg:city":"Rorschacherberg",
    "sg:orig_category":"Vereine Musik/Blasmusik",
    "sg:phone":"+41 71 855 72 14",
    "sg:postcode":"9404",
    "sg:province":"St. Gallen",
    "wof:name":"Stadtharmonie Eintracht",
    "wof:placetype":"venue"
},
  "geometry": {"coordinates":[9.5233278275,47.4760665894],"type":"Point"}
}