{
  "type": "Feature",
  "properties": {
    "iso:country":"CH",
    "sg:address":"Bogenstrasse 6",
    "sg:city":"Diepoldsau",
    "sg:orig_category":"Wirtschaftspr\u00fcfung, Steuerberatung U Treuhand",
    "sg:phone":"+41 71 737 99 00",
    "sg:postcode":"9444",
    "sg:province":"St. Gallen",
    "wof:name":"Markus Hartmann Treuhand Ag",
    "wof:placetype":"venue"
},
  "geometry": {"coordinates":[9.6604471207,47.3865013123],"type":"Point"}
}