{
  "type": "Feature",
  "properties": {
    "iso:country":"CH",
    "sg:address":"Freiestrasse 93",
    "sg:city":"Z\u00fcrich",
    "sg:orig_category":"Detailhandel mit Waren verschiedener Art, Hauptrichtung Nahrungsmittel Grosshandel mit Nahrungsmitte",
    "sg:phone":"+41 12517679",
    "sg:postcode":"8032",
    "sg:province":"Z\u00fcrich",
    "wof:name":"Lebensmittelgesch\u00e4ft Milenkovic",
    "wof:placetype":"venue"
},
  "geometry": {"coordinates":[8.5584802628,47.3671684265],"type":"Point"}
}