{
  "type": "Feature",
  "properties": {
    "iso:country":"CH",
    "sg:address":"Am Schr\u00e4gen Weg 9",
    "sg:city":"Vaduz",
    "sg:orig_category":"Elektroinstallation",
    "sg:phone":"+41 75 236 18 70",
    "sg:postcode":"9490",
    "wof:name":"Ospelt Elektro-telekom Ag",
    "wof:placetype":"venue"
},
  "geometry": {"coordinates":[9.5182723999,47.1393127441],"type":"Point"}
}