{
  "type": "Feature",
  "properties": {
    "iso:country":"CH",
    "sg:address":"Dorf 90",
    "sg:city":"Roggliswil",
    "sg:orig_category":"Sportvereine Sch\u00fctzen",
    "sg:phone":"+41 62 754 12 57",
    "sg:postcode":"6265",
    "sg:province":"Luzern",
    "wof:name":"Feldsch\u00fctzengesellschaft",
    "wof:placetype":"venue"
},
  "geometry": {"coordinates":[7.8858270645,47.211139679],"type":"Point"}
}