{
  "type": "Feature",
  "properties": {
    "iso:country":"CH",
    "sg:address":"Buchenweg 3 5213 Villnachern. Postfach",
    "sg:city":"Villnachern",
    "sg:orig_category":"Fotografische Laboratorien",
    "sg:phone":"+41 56 441 81 42",
    "sg:postcode":"5213",
    "sg:province":"Aargau",
    "wof:name":"Mikrofilm-partner H.r.salzmann Labor",
    "wof:placetype":"venue"
},
  "geometry": {"coordinates":[8.157324791,47.4735298157],"type":"Point"}
}