{
  "type": "Feature",
  "properties": {
    "addr:full":"Biederthalstrasse 46 Rodersdorf Solothurn 4118",
    "addr:housenumber":"46",
    "addr:postcode":"4118",
    "addr:street":"Biederthalstrasse",
    "iso:country":"CH",
    "sg:address":"Biederthalstrasse 46",
    "sg:city":"Rodersdorf",
    "sg:orig_category":"Bauschreinerei Herstellung von M\u00f6beln verschiedener Art",
    "sg:phone":"+41 32 377 24 14",
    "sg:postcode":"4118",
    "sg:province":"Solothurn",
    "wof:name":"Roland Kuhn Eb\u00e9nisterie",
    "wof:placetype":"venue"
},
  "geometry": {"coordinates":[7.340281,47.189003],"type":"Point"}
}