{
  "type": "Feature",
  "properties": {
    "iso:country":"CH",
    "sg:address":"Rigistrasse 8",
    "sg:city":"Dierikon",
    "sg:classifiers":[
        {
            "category":"Banks & Credit Unions",
            "subcategory":"Bank",
            "type":"Services"
        }
    ],
    "sg:phone":"+41 41 787 30 30",
    "sg:postcode":"6036",
    "sg:province":"Luzern",
    "wof:name":"Raiffeisenbank Dietwil",
    "wof:placetype":"venue"
},
  "geometry": {"coordinates":[8.39444,47.149559],"type":"Point"}
}