{
  "type": "Feature",
  "properties": {
    "iso:country":"CH",
    "sg:address":"Dorf",
    "sg:city":"B\u00fcron",
    "sg:orig_category":"Sportvereine Wassersport Rudern",
    "sg:postcode":"6233",
    "sg:province":"Luzern",
    "wof:name":"J & S Fachleiter",
    "wof:placetype":"venue"
},
  "geometry": {"coordinates":[8.0922899246,47.2157402039],"type":"Point"}
}