{
  "type": "Feature",
  "properties": {
    "iso:country":"CH",
    "sg:address":"Hauptstrasse 30 4127 Birsfelden. Postfach",
    "sg:city":"Birsfelden",
    "sg:orig_category":"Grosshandel mit Holz U Baustoffen",
    "sg:phone":"+41 61 311 78 66",
    "sg:postcode":"4127",
    "sg:province":"Basel-Landschaft",
    "wof:name":"Maxit Baustoffe Ag",
    "wof:placetype":"venue"
},
  "geometry": {"coordinates":[7.6194319725,47.5542068481],"type":"Point"}
}