{
  "type": "Feature",
  "properties": {
    "iso:country":"CH",
    "sg:address":"Marschalkenstrasse 22 4000 Basel. Postfach",
    "sg:city":"Basel",
    "sg:orig_category":"Verwaltung von Immobilien",
    "sg:postcode":"4051",
    "sg:province":"Basel-Stadt",
    "wof:name":"Mm Partner Immobilien-treuhand Ag",
    "wof:placetype":"venue"
},
  "geometry": {"coordinates":[7.5743308067,47.5507507324],"type":"Point"}
}