{
  "type": "Feature",
  "properties": {
    "iso:country":"CH",
    "sg:address":"Goldbrunnenstrasse 115",
    "sg:city":"Z\u00fcrich",
    "sg:orig_category":"Detailhandel Reparatur von Gebrauchsg\u00fctern",
    "sg:phone":"+41 13131312",
    "sg:postcode":"8055",
    "sg:province":"Z\u00fcrich",
    "wof:name":"City Video Ag",
    "wof:placetype":"venue"
},
  "geometry": {"coordinates":[8.5131702423,47.3702697754],"type":"Point"}
}