{
  "type": "Feature",
  "properties": {
    "iso:country":"CH",
    "sg:address":"Etschibrunnen",
    "sg:city":"Kerns",
    "sg:orig_category":"Fussboden, Fliesen U Plattenlegerei, Tapeziererei",
    "sg:postcode":"6064",
    "sg:province":"Obwalden",
    "wof:name":"Durrer Tony Plattengesch\u00e4ft Gmbh",
    "wof:placetype":"venue"
},
  "geometry": {"coordinates":[8.2749996185,46.9008216858],"type":"Point"}
}