{
  "type": "Feature",
  "properties": {
    "iso:country":"CH",
    "sg:address":"Grand-rue 31",
    "sg:city":"Bulle",
    "sg:orig_category":"Detailhandel mit Bekleidung",
    "sg:phone":"+41 26 912 22 28",
    "sg:postcode":"1630",
    "sg:province":"Fribourg",
    "wof:name":"Myst\u00e8re, Fran\u00e7oise Monnard",
    "wof:placetype":"venue"
},
  "geometry": {"coordinates":[7.057343,46.619034],"type":"Point"}
}