{
  "type": "Feature",
  "properties": {
    "addr:full":"G\u00fcterstrasse 141 Basel Basel-Stadt 4053",
    "addr:housenumber":"141",
    "addr:postcode":"4053",
    "addr:street":"Gueterstrasse",
    "iso:country":"CH",
    "sg:address":"G\u00fcterstrasse 141",
    "sg:city":"Basel",
    "sg:orig_category":"Autotransporte international G\u00fcterbef\u00f6rderung in der Binnenschiffahrt",
    "sg:phone":"+41 61 363 08 90",
    "sg:postcode":"4053",
    "sg:province":"Basel-Stadt",
    "wof:name":"Euroute Ab Schweiz Zweigniederlassung",
    "wof:placetype":"venue"
},
  "geometry": {"coordinates":[7.589771,47.544815],"type":"Point"}
}