{
  "type": "Feature",
  "properties": {
    "iso:country":"CH",
    "sg:address":"Route De Villars 37",
    "sg:city":"Fribourg",
    "sg:orig_category":"Detailhandel mit Uhren U Schmuck",
    "sg:phone":"+41 26 424 30 35",
    "sg:postcode":"1700",
    "sg:province":"Fribourg",
    "wof:name":"Pierres & Bijoux Raymond Jutzet",
    "wof:placetype":"venue"
},
  "geometry": {"coordinates":[7.1389718056,46.8003501892],"type":"Point"}
}