{
  "type": "Feature",
  "properties": {
    "iso:country":"CH",
    "sg:address":"Str. Nuova 8",
    "sg:city":"Riva San Vitale",
    "sg:classifiers":[
        {
            "category":"Banks & Credit Unions",
            "subcategory":"Bank",
            "type":"Services"
        }
    ],
    "sg:phone":"+41 91 648 14 42",
    "sg:postcode":"6826",
    "sg:province":"Ticino",
    "wof:name":"Raiffeisen Di Riva S. Vitale",
    "wof:placetype":"venue"
},
  "geometry": {"coordinates":[8.972467,45.905102],"type":"Point"}
}