{
  "type": "Feature",
  "properties": {
    "iso:country":"CH",
    "sg:address":"Arcas 11",
    "sg:city":"Chur",
    "sg:orig_category":"Reiseb\u00fcros U Reiseveranstalter",
    "sg:phone":"+41 81 250 56 50",
    "sg:postcode":"7000",
    "sg:province":"Graubunden",
    "wof:name":"Orbit 1 Reisen Gmbh",
    "wof:placetype":"venue"
},
  "geometry": {"coordinates":[9.5316295624,46.8478317261],"type":"Point"}
}