{
  "type": "Feature",
  "properties": {
    "iso:country":"CH",
    "sg:address":"Bruchmattstrasse 10 6003 Luzern. Postfach",
    "sg:city":"Luzern",
    "sg:orig_category":"Herstellung von pharmazeutischen Grundstoffen",
    "sg:postcode":"6003",
    "sg:province":"Luzern",
    "wof:name":"Krebs Walter Ag Chemisch-pharmazeut. Produkte Usw; Fabrik., Handel",
    "wof:placetype":"venue"
},
  "geometry": {"coordinates":[8.2977237701,47.0474357605],"type":"Point"}
}