{
  "type": "Feature",
  "properties": {
    "iso:country":"CH",
    "sg:address":"Chemin De La Coulaz 2 1530 Payerne Case Postale 176",
    "sg:city":"Payerne",
    "sg:orig_category":"Verwaltung von Immobilien Wirtschaftspr\u00fcfung, Steuerberatung U Treuhand",
    "sg:phone":"+41 26 660 21 41",
    "sg:postcode":"1530",
    "sg:province":"Vaud",
    "wof:name":"Ficog\u00e8re Fiduciaire Conseils G\u00e9rances Payerne Sa",
    "wof:placetype":"venue"
},
  "geometry": {"coordinates":[6.9305372238,46.8190231323],"type":"Point"}
}