{
  "type": "Feature",
  "properties": {
    "iso:country":"CH",
    "sg:address":"Terreaux Rue Des 14",
    "sg:city":"Moudon",
    "sg:orig_category":"Non-Classified Establishments",
    "sg:postcode":"1510",
    "sg:province":"Vaud",
    "wof:name":"Boulangerie-p\u00e2tisserie Pascal Demierre",
    "wof:placetype":"venue"
},
  "geometry": {"coordinates":[6.7973418236,46.6670188904],"type":"Point"}
}