{
  "type": "Feature",
  "properties": {
    "iso:country":"CH",
    "sg:address":"Compognastrasse",
    "sg:city":"Thusis",
    "sg:orig_category":"Herstellung von sonstigen landwirtschaftlichen Maschinen",
    "sg:phone":"+41 81 651 26 52",
    "sg:postcode":"7430",
    "sg:province":"Graubunden",
    "wof:name":"Fankhauser Peter",
    "wof:placetype":"venue"
},
  "geometry": {"coordinates":[9.439997673,46.7051582336],"type":"Point"}
}