{
  "type": "Feature",
  "properties": {
    "addr:full":"Dorfstrasse 32 Richterswil Z\u00fcrich 8805",
    "addr:housenumber":"32",
    "addr:postcode":"8805",
    "addr:street":"Dorfstrasse",
    "iso:country":"CH",
    "sg:address":"Dorfstrasse 32",
    "sg:city":"Richterswil",
    "sg:orig_category":"Arztpraxen",
    "sg:phone":"+41 17846262",
    "sg:postcode":"8805",
    "sg:province":"Z\u00fcrich",
    "wof:name":"Dr.med.gabor Schimert Spezialarzt Fmh",
    "wof:placetype":"venue"
},
  "geometry": {"coordinates":[8.705788,47.207134],"type":"Point"}
}