{
  "type": "Feature",
  "properties": {
    "iso:country":"CH",
    "sg:address":"H\u00f6lzliweg 2 4106 Therwil. Postfach",
    "sg:city":"Therwil",
    "sg:orig_category":"Reiseb\u00fcros U Reiseveranstalter",
    "sg:postcode":"4106",
    "sg:province":"Basel-Landschaft",
    "wof:name":"Rondo Musikreisen Gmbh",
    "wof:placetype":"venue"
},
  "geometry": {"coordinates":[7.5609102249,47.5037765503],"type":"Point"}
}