{
  "type": "Feature",
  "properties": {
    "iso:country":"CH",
    "sg:address":"Hauptstrasse 28",
    "sg:city":"M\u00e4genwil",
    "sg:classifiers":[
        {
            "category":"Restaurant",
            "type":"Food & Drink"
        }
    ],
    "sg:phone":"+41 62 896 12 79",
    "sg:postcode":"5506",
    "sg:province":"Aargau",
    "wof:name":"Restaurant Brauerei",
    "wof:placetype":"venue"
},
  "geometry": {"coordinates":[8.2309761047,47.4116516113],"type":"Point"}
}