{
  "type": "Feature",
  "properties": {
    "iso:country":"CH",
    "sg:address":"6947",
    "sg:city":"Vaglio",
    "sg:orig_category":"Landesverteidigung, Sozialversicherung \u00d6ffentliche Verwaltung",
    "sg:phone":"+41 91 944 11 36",
    "sg:postcode":"6947",
    "sg:province":"Ticino",
    "wof:name":"Centro Di Protezione Civile Di Valcolla",
    "wof:placetype":"venue"
},
  "geometry": {"coordinates":[9.0501403809,46.087638855],"type":"Point"}
}