{
  "type": "Feature",
  "properties": {
    "iso:country":"CH",
    "sg:address":"Kirchgasse 10",
    "sg:city":"Herzogenbuchsee",
    "sg:orig_category":"Detailhandel mit Fleisch U Fleischwaren Detailhandel mit Waren verschiedener Art, Hauptrichtung Nahr",
    "sg:phone":"+41 62 961 14 09",
    "sg:postcode":"3360",
    "sg:province":"Bern",
    "wof:name":"Margrit W\u00fcthrich Metzgerei & Lebensmittel",
    "wof:placetype":"venue"
},
  "geometry": {"coordinates":[7.7066597939,47.187664032],"type":"Point"}
}