{
  "type": "Feature",
  "properties": {
    "iso:country":"CH",
    "sg:address":"Hauptstrasse 10-12",
    "sg:city":"Magden",
    "sg:orig_category":"Architekturb\u00fcros",
    "sg:phone":"+41 61 843 91 91",
    "sg:postcode":"4312",
    "sg:province":"Aargau",
    "wof:name":"Architektur & Informatik Gmbh",
    "wof:placetype":"venue"
},
  "geometry": {"coordinates":[7.814295,47.527004],"type":"Point"}
}