{
  "type": "Feature",
  "properties": {
    "iso:country":"CH",
    "sg:address":"Socinstrasse 5",
    "sg:city":"Basel",
    "sg:orig_category":"Medien, Werbung, Marketing, PR",
    "sg:phone":"+41 61 263 20 63",
    "sg:postcode":"4051",
    "sg:province":"Basel-Stadt",
    "wof:name":"Corporate Sound Ag",
    "wof:placetype":"venue"
},
  "geometry": {"coordinates":[7.579492,47.557987],"type":"Point"}
}