{
  "type": "Feature",
  "properties": {
    "iso:country":"CH",
    "sg:address":"Spitalgasse 1",
    "sg:city":"St.gallen",
    "sg:orig_category":"Sonstiger Grosshandel",
    "sg:postcode":"9000",
    "sg:province":"St. Gallen",
    "wof:name":"Grossglauser Import Export S\u00e0rl",
    "wof:placetype":"venue"
},
  "geometry": {"coordinates":[7.0721898079,46.788318634],"type":"Point"}
}