{
  "type": "Feature",
  "properties": {
    "iso:country":"CH",
    "sg:address":"Vignes Chemin Des 10",
    "sg:city":"Mont-sur-rolle",
    "sg:orig_category":"Saunas, Solarien, Fitnesszentren U \u00e4hnliches",
    "sg:phone":"+41 21 826 02 56",
    "sg:postcode":"1185",
    "sg:province":"Vaud",
    "wof:name":"Magic Personal Training S\u00e0rl",
    "wof:placetype":"venue"
},
  "geometry": {"coordinates":[6.3381428719,46.4705123901],"type":"Point"}
}