{
  "type": "Feature",
  "properties": {
    "iso:country":"CH",
    "sg:address":"St-germain",
    "sg:city":"Chandolin-savi\u00e8se",
    "sg:orig_category":"Sonstiges Versicherungsgewerbe",
    "sg:phone":"+41 27 395 39 00",
    "sg:postcode":"1965",
    "sg:province":"Valais",
    "wof:name":"Gestas Varone Jean-daniel",
    "wof:placetype":"venue"
},
  "geometry": {"coordinates":[7.3478050232,46.2532310486],"type":"Point"}
}