{
  "type": "Feature",
  "properties": {
    "iso:country":"CH",
    "sg:address":"Bahnhofstrasse 3",
    "sg:city":"Olten",
    "sg:orig_category":"Detailhandel mit Waren verschiedener Art, Hauptrichtung Nahrungsmittel",
    "sg:phone":"+41 79 345 78 48",
    "sg:postcode":"4600",
    "sg:province":"Solothurn",
    "wof:name":"Gamze Market Im Winkel Kiraz Veysel",
    "wof:placetype":"venue"
},
  "geometry": {"coordinates":[7.9066371918,47.3490333557],"type":"Point"}
}