{
  "type": "Feature",
  "properties": {
    "iso:country":"CH",
    "sg:address":"Le Ch\u00e2telard 1937 Orsi\u00e8res. Postfach",
    "sg:city":"Orsi\u00e8res",
    "sg:orig_category":"Detailhandel mit Radio U Fernsehger\u00e4ten Herstellung von sonstigen elektrischen Ausr\u00fcstungen",
    "sg:phone":"+41 27 783 30 71",
    "sg:postcode":"1937",
    "sg:province":"Valais",
    "wof:name":"Net'audio Sa Appareils \u00e9lectroniques De Investissement, T\u00e9l\u00e9communications Etc.; Vente, R\u00e9paration",
    "wof:placetype":"venue"
},
  "geometry": {"coordinates":[7.1443190575,46.0279312134],"type":"Point"}
}