{
  "type": "Feature",
  "properties": {
    "iso:country":"CH",
    "sg:address":"Via Campagna 1",
    "sg:city":"Giubiasco",
    "sg:orig_category":"Detailhandel mit Damenbekleidung Detailhandel mit Herrenbekleidung",
    "sg:phone":"+41 91 857 11 12",
    "sg:postcode":"6512",
    "sg:province":"Ticino",
    "wof:name":"Romano Baroni Confezione Pellicce",
    "wof:placetype":"venue"
},
  "geometry": {"coordinates":[9.0023298264,46.1677513123],"type":"Point"}
}