{
  "type": "Feature",
  "properties": {
    "iso:country":"CH",
    "sg:address":"Auf Der H\u00f6he 6 5742 K\u00f6lliken. Postfach",
    "sg:city":"K\u00f6lliken",
    "sg:orig_category":"Sonstige mit der Informatik verbundene T\u00e4tigkeiten",
    "sg:phone":"+41 62 724 99 00",
    "sg:postcode":"5742",
    "sg:province":"Aargau",
    "wof:name":"Pemsoft Gmbh",
    "wof:placetype":"venue"
},
  "geometry": {"coordinates":[8.0193223953,47.3327827454],"type":"Point"}
}