{
  "type": "Feature",
  "properties": {
    "iso:country":"CH",
    "sg:address":"Kreuzberg 7",
    "sg:city":"Kerzers",
    "sg:orig_category":"Sonstige mit der Informatik verbundene T\u00e4tigkeiten",
    "sg:postcode":"3210",
    "sg:province":"Fribourg",
    "wof:name":"Ncnet Gmbh",
    "wof:placetype":"venue"
},
  "geometry": {"coordinates":[7.1955451965,46.9703292847],"type":"Point"}
}