{
  "type": "Feature",
  "properties": {
    "iso:country":"CH",
    "sg:address":"Augustins Place Des 15 1205 Gen\u00e8ve. Postfach",
    "sg:city":"Gen\u00e8ve",
    "sg:orig_category":"Sonstige pers\u00f6nliche Dienstleistungen",
    "sg:postcode":"1205",
    "sg:province":"Gen\u00e8ve",
    "wof:name":"Concept'com, Anastasios Hatzigiannakis",
    "wof:placetype":"venue"
},
  "geometry": {"coordinates":[6.144548893,46.1909255981],"type":"Point"}
}