{
  "type": "Feature",
  "properties": {
    "iso:country":"CH",
    "sg:address":"Avenue Beauregard 1",
    "sg:city":"Freiburg",
    "sg:orig_category":"Softwareentwicklung U beratung",
    "sg:phone":"+41 26 424 95 46",
    "sg:postcode":"1700",
    "sg:province":"Fribourg",
    "wof:name":"It Works Cunningham S\u00e0rl",
    "wof:placetype":"venue"
},
  "geometry": {"coordinates":[7.1489992142,46.8023338318],"type":"Point"}
}