{
  "type": "Feature",
  "properties": {
    "iso:country":"CH",
    "sg:address":"Diggelmannstrasse 31",
    "sg:city":"Z\u00fcrich",
    "sg:orig_category":"Datenverarbeitungsdienste Unternehmensberatung",
    "sg:phone":"+41 14000700",
    "sg:postcode":"8047",
    "sg:province":"Z\u00fcrich",
    "wof:name":"Winterberg Consulting Ag",
    "wof:placetype":"venue"
},
  "geometry": {"coordinates":[8.481066,47.378071],"type":"Point"}
}