{
  "type": "Feature",
  "properties": {
    "iso:country":"CH",
    "sg:address":"Laveggio Via 14 6850 Mendrisio. Postfach",
    "sg:city":"Chardonne",
    "sg:orig_category":"Herstellung von sonstigen elektrischen Ausr\u00fcstungen",
    "sg:postcode":"1803",
    "sg:province":"Vaud",
    "wof:name":"Devicing Sa Stores, Notamm. De Syst\u00e8mes De Protection Solaire; Fabrication",
    "wof:placetype":"venue"
},
  "geometry": {"coordinates":[8.9781484604,45.8811035156],"type":"Point"}
}