{
  "type": "Feature",
  "properties": {
    "iso:country":"CH",
    "sg:address":"Gartenstrasse 98",
    "sg:city":"Brunnenthal",
    "sg:orig_category":"Non-Classified Establishments",
    "sg:postcode":"3307",
    "sg:province":"Solothurn",
    "wof:name":"Haffa Sportplatzbau Ag",
    "wof:placetype":"venue"
},
  "geometry": {"coordinates":[7.468184948,47.0864715576],"type":"Point"}
}