{
  "type": "Feature",
  "properties": {
    "iso:country":"CH",
    "sg:address":"Ueberlandstrasse 220",
    "sg:city":"D\u00fcbendorf",
    "sg:orig_category":"Detailhandel mit Spielwaren",
    "sg:phone":"+41 90573059",
    "sg:postcode":"8600",
    "sg:province":"Z\u00fcrich",
    "wof:name":"Uhu Spiellad\u00e4",
    "wof:placetype":"venue"
},
  "geometry": {"coordinates":[8.6244468689,47.4001464844],"type":"Point"}
}