{
  "type": "Feature",
  "properties": {
    "iso:country":"CH",
    "sg:address":"Av. De La Gare 2800 Del\u00e9mont Case Postale",
    "sg:city":"Delsberg",
    "sg:orig_category":"Detailhandel mit Waren verschiedener Art, Hauptrichtung Nichtnahrungsmittel",
    "sg:phone":"+41 32 421 46 48",
    "sg:postcode":"2800",
    "sg:province":"Jura",
    "wof:name":"Grands Magasins Manor, Nordmann & Cie",
    "wof:placetype":"venue"
},
  "geometry": {"coordinates":[7.3486709595,47.3661766052],"type":"Point"}
}