{
  "type": "Feature",
  "properties": {
    "iso:country":"CH",
    "sg:address":"N\u00fcschelerstrasse 11",
    "sg:city":"Z\u00fcrich",
    "sg:classifiers":[
        {
            "category":"Communications",
            "subcategory":"Film & Video Production",
            "type":"Services"
        }
    ],
    "sg:phone":"+41 12116666",
    "sg:postcode":"8001",
    "sg:province":"Z\u00fcrich",
    "sg:tags":[
        "videofilmherstellung",
        "u"
    ],
    "wof:name":"Studio 4, Filmpodium",
    "wof:placetype":"venue"
},
  "geometry": {"coordinates":[8.5367593765,47.3715362549],"type":"Point"}
}