{
  "type": "Feature",
  "properties": {
    "iso:country":"CH",
    "sg:address":"Boulevard De La Cluse 14",
    "sg:city":"Gen\u00e8ve",
    "sg:orig_category":"Unclassifiable Establishments",
    "sg:phone":"+41 22 781 46 92",
    "sg:postcode":"1205",
    "sg:province":"Gen\u00e8ve",
    "wof:name":"Ebat M'bundani-ky",
    "wof:placetype":"venue"
},
  "geometry": {"coordinates":[6.1445860863,46.1881408691],"type":"Point"}
}