{
  "type": "Feature",
  "properties": {
    "iso:country":"CH",
    "sg:address":"Hauptstrasse 16",
    "sg:city":"Bussnang",
    "sg:orig_category":"Elektroinstallation",
    "sg:phone":"+41 71 622 53 22",
    "sg:postcode":"9565",
    "sg:province":"Thurgau",
    "wof:name":"Elektro Ausderau Ag",
    "wof:placetype":"venue"
},
  "geometry": {"coordinates":[9.0787725449,47.5575523376],"type":"Point"}
}