{
  "type": "Feature",
  "properties": {
    "iso:country":"CH",
    "sg:address":"1996",
    "sg:city":"Basse-nendaz",
    "sg:classifiers":[
        {
            "category":"Education",
            "subcategory":"Library",
            "type":"Public Place"
        }
    ],
    "sg:phone":"+41 32 853 23 61",
    "sg:postcode":"1996",
    "sg:province":"Valais",
    "sg:tags":[
        "u",
        "bibliotheken",
        "archive"
    ],
    "wof:name":"Biblioth\u00e8que Communale",
    "wof:placetype":"venue"
},
  "geometry": {"coordinates":[6.89966,47.03722],"type":"Point"}
}