{
  "type": "Feature",
  "properties": {
    "iso:country":"CH",
    "sg:address":"Wilerstrasse 12",
    "sg:city":"Sirnach",
    "sg:orig_category":"Detailhandel mit Geschenkartikeln U Souvenirs",
    "sg:phone":"+41 81 413 55 78",
    "sg:postcode":"8370",
    "sg:province":"Thurgau",
    "wof:name":"Traugott Kast Souvenirs",
    "wof:placetype":"venue"
},
  "geometry": {"coordinates":[9.8244256973,46.7989082336],"type":"Point"}
}