{
  "type": "Feature",
  "properties": {
    "iso:country":"CH",
    "sg:address":"Rue De Gottefrey 32",
    "sg:city":"Saxon",
    "sg:orig_category":"Detailhandel mit Fleisch U Fleischwaren",
    "sg:phone":"+41 27 744 17 87",
    "sg:postcode":"1907",
    "sg:province":"Valais",
    "wof:name":"Emile Fumeaux Boucherie-charcuterie",
    "wof:placetype":"venue"
},
  "geometry": {"coordinates":[7.1738038063,46.1490364075],"type":"Point"}
}