{
  "type": "Feature",
  "properties": {
    "addr:full":"Ibelweg 18a Baar Zug 6340",
    "addr:housenumber":"18a",
    "addr:postcode":"6340",
    "addr:street":"Ibelweg;Zug",
    "iso:country":"CH",
    "sg:address":"Ibelweg 18a",
    "sg:city":"Baar",
    "sg:orig_category":"Architektur U Ingenieurb\u00fcros",
    "sg:phone":"+41 41 763 15 55",
    "sg:postcode":"6340",
    "sg:province":"Zug",
    "wof:name":"Diag Design Ag",
    "wof:placetype":"venue"
},
  "geometry": {"coordinates":[8.525491,47.180523],"type":"Point"}
}