{
  "type": "Feature",
  "properties": {
    "iso:country":"CH",
    "sg:address":"Gattikerstrasse 8",
    "sg:city":"Z\u00fcrich",
    "sg:orig_category":"Werbevermittlung",
    "sg:phone":"+41 13821050",
    "sg:postcode":"8032",
    "sg:province":"Z\u00fcrich",
    "wof:name":"Tschebi Idee & Ausf\u00fchrung Von Trzebiatowski Esther + Peter",
    "wof:placetype":"venue"
},
  "geometry": {"coordinates":[8.5670404434,47.3608627319],"type":"Point"}
}