{
  "type": "Feature",
  "properties": {
    "iso:country":"CH",
    "sg:address":"Sternenfeldstrasse 16 4127 Birsfelden. Postfach 627",
    "sg:city":"Birsfelden",
    "sg:orig_category":"Rechtsberatung Wirtschaftspr\u00fcfung, Steuerberatung U Treuhand",
    "sg:phone":"+41 61 311 44 36",
    "sg:postcode":"4127",
    "sg:province":"Basel-Landschaft",
    "wof:name":"Pdg Treuhand Gmbh",
    "wof:placetype":"venue"
},
  "geometry": {"coordinates":[7.6337780952,47.5522918701],"type":"Point"}
}