{
  "type": "Feature",
  "properties": {
    "iso:country":"CH",
    "sg:address":"Via Sonvico 9",
    "sg:city":"Porza",
    "sg:orig_category":"Handel mit Motorr\u00e4dern, Teilen U Zubeh\u00f6r Instandhaltung U Reparatur von Motorr\u00e4dern",
    "sg:postcode":"6948",
    "sg:province":"Ticino",
    "wof:name":"Vegos Sa",
    "wof:placetype":"venue"
},
  "geometry": {"coordinates":[8.9626054764,46.0250549316],"type":"Point"}
}