{
  "type": "Feature",
  "properties": {
    "iso:country":"CH",
    "sg:address":"Bata-park 5",
    "sg:city":"M\u00f6hlin",
    "sg:orig_category":"Herstellung von Metallkonstruktionen",
    "sg:phone":"+41 18500225",
    "sg:postcode":"4313",
    "sg:province":"Aargau",
    "wof:name":"Ren\u00e9 Lenzinger Metallbau",
    "wof:placetype":"venue"
},
  "geometry": {"coordinates":[8.5188446045,47.4763755798],"type":"Point"}
}