{
  "type": "Feature",
  "properties": {
    "iso:country":"CH",
    "sg:address":"Bl\u00fcemlismatt 130",
    "sg:city":"Egerkingen",
    "sg:orig_category":"RESTAURANTS: TEA-ROOMS",
    "sg:phone":"+41 62 398 14 68",
    "sg:postcode":"4622",
    "sg:province":"Solothurn",
    "wof:name":"Studer Markus",
    "wof:placetype":"venue"
},
  "geometry": {"coordinates":[7.7776842117,47.3295135498],"type":"Point"}
}