{
  "type": "Feature",
  "properties": {
    "iso:country":"CH",
    "sg:address":"Toggwil",
    "sg:city":"Meilen",
    "sg:orig_category":"Oberfl\u00e4chenreinigung Sandstrahlen",
    "sg:phone":"+41 19235930",
    "sg:postcode":"8706",
    "sg:province":"Z\u00fcrich",
    "wof:name":"Dieter Tritten Sandstrahlereien",
    "wof:placetype":"venue"
},
  "geometry": {"coordinates":[8.6536798477,47.2880706787],"type":"Point"}
}