{
  "type": "Feature",
  "properties": {
    "iso:country":"CH",
    "sg:address":"Schwendi",
    "sg:city":"Nessental",
    "sg:orig_category":"Zimmerei, Dachdeckerei, Bauspenglerei U Abdichtung Zimmerei, Ingenieurholzbau",
    "sg:phone":"+41 33 973 11 43",
    "sg:postcode":"3863",
    "sg:province":"Bern",
    "wof:name":"Rufibach & Steudler Ag Zimmerei & Bedachungen",
    "wof:placetype":"venue"
},
  "geometry": {"coordinates":[8.3496618271,46.7370605469],"type":"Point"}
}