{
  "type": "Feature",
  "properties": {
    "iso:country":"CH",
    "sg:address":"Riedstrasse 2",
    "sg:city":"Schlosswil",
    "sg:orig_category":"Grosshandel mit Nahrungsmitteln, Getr\u00e4nken U Tabakwaren ohne ausgepr\u00e4gten Schwerpunkt",
    "sg:phone":"+41 31 711 30 64",
    "sg:postcode":"3082",
    "sg:province":"Bern",
    "wof:name":"Susanne Bieri-jaun",
    "wof:placetype":"venue"
},
  "geometry": {"coordinates":[7.6089038849,46.9095802307],"type":"Point"}
}