{
  "type": "Feature",
  "properties": {
    "iso:country":"CH",
    "sg:address":"Platz",
    "sg:city":"Trun",
    "sg:classifiers":[
        {
            "category":"Travel",
            "subcategory":"Hotels & Motels",
            "type":"Entertainment"
        }
    ],
    "sg:phone":"+41 81 416 21 21",
    "sg:postcode":"7166",
    "sg:province":"Graubunden",
    "sg:tags":[
        "hotels",
        "mit",
        "restaurant"
    ],
    "wof:name":"Hubli Felix",
    "wof:placetype":"venue"
},
  "geometry": {"coordinates":[9.8537597656,46.8327331543],"type":"Point"}
}