{
  "type": "Feature",
  "properties": {
    "iso:country":"CH",
    "sg:address":"Bahnhofplatz 14 8400 Winterthur. Postfach",
    "sg:city":"Winterthur",
    "sg:orig_category":"Grosshandel mit Schmuck Sonstiger Grosshandel",
    "sg:phone":"+41 19203242",
    "sg:postcode":"8401",
    "sg:province":"Z\u00fcrich",
    "wof:name":"Helag Ag Lagler A. & H.",
    "wof:placetype":"venue"
},
  "geometry": {"coordinates":[8.6892232895,47.2691612244],"type":"Point"}
}