{
  "type": "Feature",
  "properties": {
    "iso:country":"CH",
    "sg:address":"3961",
    "sg:city":"Grimentz",
    "sg:orig_category":"Kinderkrippen U horte",
    "sg:postcode":"3961",
    "sg:province":"Valais",
    "wof:name":"Garderie D'enfants St\u00e9 De D\u00e9veloppement",
    "wof:placetype":"venue"
},
  "geometry": {"coordinates":[7.5763998032,46.1804466248],"type":"Point"}
}