{
  "type": "Feature",
  "properties": {
    "iso:country":"CH",
    "sg:address":"Freudenbergstrasse 27 9242 Oberuzwil. Postfach",
    "sg:city":"Oberuzwil",
    "sg:orig_category":"Detailhandel mit B\u00fcchern, Zeitungen, Schreib U Papeteriewaren",
    "sg:phone":"+41 71 950 07 68",
    "sg:postcode":"9242",
    "sg:province":"St. Gallen",
    "wof:name":"Kurland Drucksachen Drucksachen U. B\u00fcrobedarf; Handel",
    "wof:placetype":"venue"
},
  "geometry": {"coordinates":[9.126905,47.435394],"type":"Point"}
}