{
  "type": "Feature",
  "properties": {
    "iso:country":"CH",
    "sg:address":"3067 Boll. Postfach 136",
    "sg:city":"Boll",
    "sg:orig_category":"Sportvereine Eissport Eishockey",
    "sg:phone":"+41 26 913 97 40",
    "sg:postcode":"3067",
    "sg:province":"Bern",
    "wof:name":"Eishockey-club Boll",
    "wof:placetype":"venue"
},
  "geometry": {"coordinates":[7.5565361977,46.9822425842],"type":"Point"}
}