{
  "type": "Feature",
  "properties": {
    "iso:country":"CH",
    "sg:address":"Weidstrasse 63 8542 Wiesendangen. Postfach",
    "sg:city":"Wiesendangen",
    "sg:orig_category":"Sonstige mit der Informatik verbundene T\u00e4tigkeiten",
    "sg:postcode":"8542",
    "sg:province":"Z\u00fcrich",
    "wof:name":"Prointec - Professional Information Technology Ag",
    "wof:placetype":"venue"
},
  "geometry": {"coordinates":[8.8000240326,47.5222434998],"type":"Point"}
}