{
  "type": "Feature",
  "properties": {
    "iso:country":"CH",
    "sg:address":"Dorfstrasse 12",
    "sg:city":"Wabern",
    "sg:orig_category":"Detailhandel mit Getr\u00e4nken",
    "sg:phone":"+41 31 961 81 81",
    "sg:postcode":"3084",
    "sg:province":"Bern",
    "wof:name":"Rita Krebs Weinperle",
    "wof:placetype":"venue"
},
  "geometry": {"coordinates":[7.4469671249,46.9299736023],"type":"Point"}
}