{
  "type": "Feature",
  "properties": {
    "iso:country":"CH",
    "sg:address":"Aemtlerstrasse 32 8003 Z\u00fcrich. Postfach",
    "sg:city":"Z\u00fcrich",
    "sg:orig_category":"Fachdetailhandel in Verkaufsr\u00e4umen",
    "sg:postcode":"8001",
    "sg:province":"Z\u00fcrich",
    "wof:name":"Caddy Point Ag Sportartikel, Ger\u00e4tschaften; Handel, Fabrikation, Im, Export, Reparaturen Usw",
    "wof:placetype":"venue"
},
  "geometry": {"coordinates":[8.5155897141,47.3720321655],"type":"Point"}
}