{
  "type": "Feature",
  "properties": {
    "iso:country":"CH",
    "sg:address":"Englischviertelstrasse 22",
    "sg:city":"Z\u00fcrich",
    "sg:orig_category":"Allgemeiner Hoch U Tiefbau Architekturb\u00fcros",
    "sg:phone":"+41 12522080",
    "sg:postcode":"8032",
    "sg:province":"Z\u00fcrich",
    "wof:name":"Hornberger Architekten Ag",
    "wof:placetype":"venue"
},
  "geometry": {"coordinates":[8.556278,47.36763],"type":"Point"}
}