{
  "type": "Feature",
  "properties": {
    "iso:country":"CH",
    "sg:address":"Dorstrasse 6",
    "sg:city":"Br\u00fctten",
    "sg:orig_category":"Sportvereine Velo Rad-& Motorfahrer-Bund SRB",
    "sg:postcode":"8311",
    "sg:province":"Z\u00fcrich",
    "wof:name":"Gruppo Sportivo Ital Grenchen",
    "wof:placetype":"venue"
},
  "geometry": {"coordinates":[7.3994002342,47.1928787231],"type":"Point"}
}