{
  "type": "Feature",
  "properties": {
    "iso:country":"CH",
    "sg:address":"Rue Centrale 15 1003 Lausanne Case Postale 3328",
    "sg:city":"Lausanne",
    "sg:classifiers":[
        {
            "category":"Professional",
            "subcategory":"Employment Agencies",
            "type":"Services"
        }
    ],
    "sg:phone":"+41 21 320 38 81",
    "sg:postcode":"1002",
    "sg:province":"Vaud",
    "sg:tags":[
        "personal",
        "u",
        "stellenvermittlung"
    ],
    "wof:name":"Multi Personnel Service Sa",
    "wof:placetype":"venue"
},
  "geometry": {"coordinates":[6.6339712143,46.5211029053],"type":"Point"}
}