{
  "type": "Feature",
  "properties": {
    "iso:country":"CH",
    "sg:address":"Elvezia Corso 16",
    "sg:city":"Lugano",
    "sg:orig_category":"Architektur U Ingenieurb\u00fcros",
    "sg:postcode":"6900",
    "sg:province":"Ticino",
    "wof:name":"R.e. Motors Sa",
    "wof:placetype":"venue"
},
  "geometry": {"coordinates":[8.955887,46.007774],"type":"Point"}
}