{
  "type": "Feature",
  "properties": {
    "iso:country":"CH",
    "sg:address":"Baragge Via 13c 6512 Giubiasco. Postfach",
    "sg:city":"Giubiasco",
    "sg:orig_category":"Architektur U Ingenieurb\u00fcros",
    "sg:postcode":"6512",
    "sg:province":"Ticino",
    "wof:name":"B\u00e4rtschi Sa Centro Ingegneria Impiantistica",
    "wof:placetype":"venue"
},
  "geometry": {"coordinates":[8.992711,46.171112],"type":"Point"}
}