{
  "type": "Feature",
  "properties": {
    "iso:country":"CH",
    "sg:address":"Strandbadstrasse 3 3800 Interlaken. Postfach 305",
    "sg:city":"Interlaken",
    "sg:orig_category":"Reiseb\u00fcros U Reiseveranstalter",
    "sg:phone":"+41 33 828 32 32",
    "sg:postcode":"3800",
    "sg:province":"Bern",
    "wof:name":"Jungfrau Tours Ag",
    "wof:placetype":"venue"
},
  "geometry": {"coordinates":[7.8547120094,46.6870117188],"type":"Point"}
}