{
  "type": "Feature",
  "properties": {
    "iso:country":"CH",
    "sg:address":"Avenue William-fraisse 6",
    "sg:city":"Lausanne",
    "sg:orig_category":"Detailhandel mit Geschenkartikeln U Souvenirs",
    "sg:phone":"+41 21 312 46 90",
    "sg:postcode":"1006",
    "sg:province":"Vaud",
    "wof:name":"F. Pf\u00e4ndler Sa Boutique La Tienda",
    "wof:placetype":"venue"
},
  "geometry": {"coordinates":[6.6256079674,46.5160903931],"type":"Point"}
}