{
  "type": "Feature",
  "properties": {
    "iso:country":"CH",
    "sg:address":"Rue Achille-merguin 16",
    "sg:city":"Porrentruy",
    "sg:orig_category":"Detailhandel mit Waren verschiedener Art, Hauptrichtung Nahrungsmittel",
    "sg:phone":"+41 32 941 26 41",
    "sg:postcode":"2900",
    "sg:province":"Jura",
    "wof:name":"Denner Top Superdiscount",
    "wof:placetype":"venue"
},
  "geometry": {"coordinates":[6.9958171844,47.1520423889],"type":"Point"}
}