{
  "type": "Feature",
  "properties": {
    "iso:country":"CH",
    "sg:address":"Bahnhofstrasse 74",
    "sg:city":"Cazis",
    "sg:orig_category":"Arztpraxen",
    "sg:phone":"+41 81 650 04 40",
    "sg:postcode":"7408",
    "sg:province":"Graubunden",
    "wof:name":"Dr.med.walter Huber Arzt F.allgemeine Medizin Fmh",
    "wof:placetype":"venue"
},
  "geometry": {"coordinates":[9.433363,46.719189],"type":"Point"}
}