{
  "type": "Feature",
  "properties": {
    "iso:country":"CH",
    "sg:address":"Hardstrasse 6 4127 Birsfelden. Postfach",
    "sg:city":"Allschwil",
    "sg:orig_category":"Sonstiges Versicherungsgewerbe",
    "sg:phone":"+41 61 311 87 50",
    "sg:postcode":"4123",
    "sg:province":"Basel-Landschaft",
    "wof:name":"Winterthur Versicherungen, Hauptagentur Allschwil, Germain Groeppelin",
    "wof:placetype":"venue"
},
  "geometry": {"coordinates":[7.6238698959,47.5523605347],"type":"Point"}
}