{
  "type": "Feature",
  "properties": {
    "iso:country":"CH",
    "sg:address":"Zone Industrielle De Grivaz 1607 Pal\u00e9zieux-gare. Postfach",
    "sg:city":"Pal\u00e9zieux-village",
    "sg:orig_category":"Instandhaltung U Reparatur von Automobilen",
    "sg:phone":"+41 21 907 90 66",
    "sg:postcode":"1607",
    "sg:province":"Vaud",
    "wof:name":"Rs Automobiles Lambert",
    "wof:placetype":"venue"
},
  "geometry": {"coordinates":[6.8379130363,46.5426216125],"type":"Point"}
}