{
  "type": "Feature",
  "properties": {
    "iso:country":"CH",
    "sg:address":"Augustinergasse 9",
    "sg:city":"Suhr",
    "sg:orig_category":"Sonstige Personenbef\u00f6rderung im Landverkehr",
    "sg:phone":"+41 62 824 82 48",
    "sg:postcode":"5034",
    "sg:province":"Aargau",
    "wof:name":"Gautschi - Reisen",
    "wof:placetype":"venue"
},
  "geometry": {"coordinates":[8.0816516876,47.3746604919],"type":"Point"}
}