{
  "type": "Feature",
  "properties": {
    "iso:country":"CH",
    "sg:address":"Laubisr\u00fctistrasse 24 8712 St\u00e4fa. Postfach 279",
    "sg:city":"St\u00e4fa",
    "sg:orig_category":"Grosshandel mit Nahrungsmitteln, Getr\u00e4nken U Tabakwaren Grosshandel mit Nahrungsmitteln, Getr\u00e4nken U",
    "sg:phone":"+41 19268010",
    "sg:postcode":"8712",
    "sg:province":"Z\u00fcrich",
    "wof:name":"Sanfrut Bianchi, Sauter & Co.",
    "wof:placetype":"venue"
},
  "geometry": {"coordinates":[8.7425575256,47.2390670776],"type":"Point"}
}