{
  "type": "Feature",
  "properties": {
    "iso:country":"CH",
    "sg:address":"Rheinstr. 81",
    "sg:city":"Pratteln",
    "sg:classifiers":[
        {
            "category":"Professional",
            "subcategory":"Advertising",
            "type":"Services"
        }
    ],
    "sg:phone":"+41 61 816 61 61",
    "sg:postcode":"4133",
    "sg:province":"Basel-Landschaft",
    "sg:tags":[
        "marketing",
        "medium",
        "communication"
    ],
    "wof:name":"Promena Ag",
    "wof:placetype":"venue"
},
  "geometry": {"coordinates":[7.710791,47.534691],"type":"Point"}
}