{
  "type": "Feature",
  "properties": {
    "iso:country":"CH",
    "sg:address":"Bernstrasse 47",
    "sg:city":"Rothrist",
    "sg:orig_category":"Detailhandel mit Fleisch U Fleischwaren",
    "sg:phone":"+41 62 794 10 23",
    "sg:postcode":"4852",
    "sg:province":"Aargau",
    "wof:name":"Felix Kunz",
    "wof:placetype":"venue"
},
  "geometry": {"coordinates":[7.9004278183,47.3055343628],"type":"Point"}
}