{
  "type": "Feature",
  "properties": {
    "iso:country":"CH",
    "sg:address":"Month\u00e9olo 17",
    "sg:city":"Monthey",
    "sg:orig_category":"Elektroinstallation",
    "sg:phone":"+41 24 472 81 72",
    "sg:postcode":"1870",
    "sg:province":"Valais",
    "wof:name":"Cottet Electronic Sa",
    "wof:placetype":"venue"
},
  "geometry": {"coordinates":[6.9506111145,46.2573776245],"type":"Point"}
}