{
  "type": "Feature",
  "properties": {
    "iso:country":"CH",
    "sg:address":"Kriegackerstrasse 91",
    "sg:city":"Muttenz",
    "sg:orig_category":"Unclassifiable Establishments",
    "sg:phone":"+41 61 466 91 11",
    "sg:postcode":"4132",
    "sg:province":"Basel-Landschaft",
    "wof:name":"M & R Immobilien Ag",
    "wof:placetype":"venue"
},
  "geometry": {"coordinates":[7.6351881027,47.5349159241],"type":"Point"}
}