{
  "type": "Feature",
  "properties": {
    "iso:country":"CH",
    "sg:address":"Z\u00fcrcherstrasse 379",
    "sg:city":"Frauenfeld",
    "sg:orig_category":"Instandhaltung U Reparatur von Automobilen",
    "sg:phone":"+41 52 722 12 72",
    "sg:postcode":"8500",
    "sg:province":"Thurgau",
    "wof:name":"G\u00e4hwiler.",
    "wof:placetype":"venue"
},
  "geometry": {"coordinates":[8.9210777283,47.5701637268],"type":"Point"}
}