{
  "type": "Feature",
  "properties": {
    "iso:country":"CH",
    "sg:address":"4717",
    "sg:city":"M\u00fcmliswil",
    "sg:classifiers":[
        {
            "category":"Restaurant",
            "type":"Food & Drink"
        }
    ],
    "sg:phone":"+41 62 391 20 98",
    "sg:postcode":"4717",
    "sg:province":"Solothurn",
    "wof:name":"Naturfreundehaus Passwang Restaurant",
    "wof:placetype":"venue"
},
  "geometry": {"coordinates":[7.7031598091,47.3411102295],"type":"Point"}
}