{
  "type": "Feature",
  "properties": {
    "iso:country":"CH",
    "sg:address":"Gersauerstrasse 12",
    "sg:city":"Brunnen",
    "sg:orig_category":"Detailhandel mit Textilien",
    "sg:phone":"+41 32 618 27 53",
    "sg:postcode":"6440",
    "sg:province":"Schwyz",
    "wof:name":"Ruth Hesse W\u00e4rkl\u00e4deli",
    "wof:placetype":"venue"
},
  "geometry": {"coordinates":[7.3658008575,47.1770248413],"type":"Point"}
}