{
  "type": "Feature",
  "properties": {
    "addr:full":"Abendweg 6 6247 Sch\u00f6tz. Postfach Sch\u00f6tz Luzern 6247",
    "addr:housenumber":"6",
    "addr:postcode":"6247;6247",
    "addr:street":"Abendweg;Postfach Schoetz",
    "iso:country":"CH",
    "sg:address":"Abendweg 6 6247 Sch\u00f6tz. Postfach",
    "sg:city":"Sch\u00f6tz",
    "sg:orig_category":"Architektur U Ingenieurb\u00fcros",
    "sg:postcode":"6247",
    "sg:province":"Luzern",
    "wof:name":"Barmade Ag Innenarchitektur-unternehmen Usw",
    "wof:placetype":"venue"
},
  "geometry": {"coordinates":[7.984665,47.170559],"type":"Point"}
}