{
  "type": "Feature",
  "properties": {
    "iso:country":"CH",
    "sg:address":"T\u00f6sstalstrasse 14",
    "sg:city":"Wallenwil",
    "sg:orig_category":"Detailhandel mit Bekleidung",
    "sg:postcode":"8360",
    "sg:province":"Thurgau",
    "wof:name":"Ehrbar Mode",
    "wof:placetype":"venue"
},
  "geometry": {"coordinates":[7.278503,47.124561],"type":"Point"}
}