{
  "type": "Feature",
  "properties": {
    "iso:country":"CH",
    "sg:address":"Dorfstrasse 3",
    "sg:city":"Wuppenau",
    "sg:orig_category":"Vereine Diverse",
    "sg:phone":"+41 71 944 26 61",
    "sg:postcode":"9514",
    "sg:province":"Thurgau",
    "wof:name":"Fan-club Die Pauldauer",
    "wof:placetype":"venue"
},
  "geometry": {"coordinates":[9.1088275909,47.4970855713],"type":"Point"}
}