{
  "type": "Feature",
  "properties": {
    "iso:country":"CH",
    "sg:address":"Hauptstrasse 49 4132 Muttenz. Postfach",
    "sg:city":"Liestal",
    "sg:orig_category":"Pensionskassen",
    "sg:postcode":"4410",
    "sg:province":"Basel-Landschaft",
    "wof:name":"Krimmelstiftung",
    "wof:placetype":"venue"
},
  "geometry": {"coordinates":[7.6461429596,47.524810791],"type":"Point"}
}