{
  "type": "Feature",
  "properties": {
    "iso:country":"CH",
    "sg:address":"D\u00f6rfm\u00e4tteli 924 5617 Tennwil. Postfach",
    "sg:city":"Tennwil",
    "sg:orig_category":"Hardwareberatung",
    "sg:postcode":"5617",
    "sg:province":"Aargau",
    "wof:name":"Impress Affinito & Muntwyler",
    "wof:placetype":"venue"
},
  "geometry": {"coordinates":[8.2232055664,47.3060073853],"type":"Point"}
}