{
  "type": "Feature",
  "properties": {
    "iso:country":"CH",
    "sg:address":"Via Alla Chiesa",
    "sg:city":"Bioggio",
    "sg:orig_category":"Erbringung von sonstigen Dienstleistungen f\u00fcr Unterhaltung, Erholung U Freizeit",
    "sg:postcode":"6934",
    "sg:province":"Ticino",
    "wof:name":"Sh\u00e9h\u00e9razade Sagl",
    "wof:placetype":"venue"
},
  "geometry": {"coordinates":[8.9049100876,46.015209198],"type":"Point"}
}