{
  "type": "Feature",
  "properties": {
    "addr:full":"Forchstrasse 60 8008 Z\u00fcrich. Postfach Z\u00fcrich Z\u00fcrich 8001",
    "addr:housenumber":"60",
    "addr:postcode":"8008 zuerich. postfach;8001",
    "addr:street":"Forchstrasse",
    "iso:country":"CH",
    "sg:address":"Forchstrasse 60 8008 Z\u00fcrich. Postfach",
    "sg:city":"Z\u00fcrich",
    "sg:orig_category":"Architektur U Ingenieurb\u00fcros",
    "sg:postcode":"8001",
    "sg:province":"Z\u00fcrich",
    "wof:name":"Hans-rudolf Weiss Planung U. Architektur",
    "wof:placetype":"venue"
},
  "geometry": {"coordinates":[8.55586,47.363972],"type":"Point"}
}