{
  "type": "Feature",
  "properties": {
    "iso:country":"CH",
    "sg:address":"Dettighofen",
    "sg:city":"Lengwil-oberhofen",
    "sg:orig_category":"Gemeindeverwaltungen",
    "sg:phone":"+41 71 688 27 26",
    "sg:postcode":"8574",
    "sg:province":"Thurgau",
    "wof:name":"Gemeindeverwaltung Politische Gemeinde Lengwil",
    "wof:placetype":"venue"
},
  "geometry": {"coordinates":[9.1991233826,47.6225738525],"type":"Point"}
}