{
  "type": "Feature",
  "properties": {
    "iso:country":"CH",
    "sg:address":"Im Kugelfang 29",
    "sg:city":"Binningen",
    "sg:orig_category":"Handelsvermittlung U Grosshandel Sonstiger Grosshandel",
    "sg:phone":"+41 61 421 69 48",
    "sg:postcode":"4102",
    "sg:province":"Basel-Landschaft",
    "wof:name":"Ong-trading Gmbh",
    "wof:placetype":"venue"
},
  "geometry": {"coordinates":[7.5668182373,47.5311584473],"type":"Point"}
}