{
  "type": "Feature",
  "properties": {
    "iso:country":"CH",
    "sg:address":"Kaiserstrasse 6",
    "sg:city":"Rheinfelden",
    "sg:orig_category":"Nationale Postdienste",
    "sg:phone":"+41 61 831 59 60",
    "sg:postcode":"4310",
    "sg:province":"Aargau",
    "wof:name":"Die Schweizerische Post Rheinfelden 1",
    "wof:placetype":"venue"
},
  "geometry": {"coordinates":[7.7949957848,47.5531921387],"type":"Point"}
}