{
  "type": "Feature",
  "properties": {
    "addr:full":"Rue Robert-c\u00e9ard 6 Gen\u00e8ve Gen\u00e8ve 1204",
    "addr:housenumber":"6",
    "addr:postcode":"1204",
    "addr:street":"Rue Robert-Ce\u0301Ard",
    "iso:country":"CH",
    "sg:address":"Rue Robert-c\u00e9ard 6",
    "sg:city":"Gen\u00e8ve",
    "sg:orig_category":"Detailhandel mit Damenbekleidung Detailhandel mit Herrenbekleidung",
    "sg:phone":"+41 22 310 31 81",
    "sg:postcode":"1204",
    "sg:province":"Gen\u00e8ve",
    "wof:name":"Boutique Gianfranco Ferr\u00e9 Homme & Femme",
    "wof:placetype":"venue"
},
  "geometry": {"coordinates":[6.148845,46.203617],"type":"Point"}
}