{
  "type": "Feature",
  "properties": {
    "iso:country":"CH",
    "sg:address":"Unterdorf",
    "sg:city":"Buttisholz",
    "sg:orig_category":"Herstellung von sonstigen Metallwaren",
    "sg:phone":"+41 41 928 18 08",
    "sg:postcode":"6018",
    "sg:province":"Luzern",
    "wof:name":"Franz R\u00e4ber Gravuren",
    "wof:placetype":"venue"
},
  "geometry": {"coordinates":[8.0909700394,47.1134643555],"type":"Point"}
}