{
  "type": "Feature",
  "properties": {
    "iso:country":"CH",
    "sg:address":"Rathausstrasse 2",
    "sg:city":"Visp",
    "sg:orig_category":"Non-Classified Establishments",
    "sg:postcode":"3930",
    "sg:province":"Valais",
    "wof:name":"Thomas Burgener Netz Internet-dienstleistungen",
    "wof:placetype":"venue"
},
  "geometry": {"coordinates":[7.8815879822,46.2885513306],"type":"Point"}
}