{
  "type": "Feature",
  "properties": {
    "iso:country":"CH",
    "sg:address":"Herbetswil",
    "sg:city":"Herbetswil",
    "sg:classifiers":[
        {
            "category":"Banks & Credit Unions",
            "subcategory":"Bank",
            "type":"Services"
        }
    ],
    "sg:phone":"+41 4162741252",
    "sg:postcode":"4715",
    "sg:province":"Solothurn",
    "wof:name":"Raiffeisenbank Herbetswil",
    "wof:placetype":"venue"
},
  "geometry": {"coordinates":[7.594283,47.293507],"type":"Point"}
}