{
  "type": "Feature",
  "properties": {
    "iso:country":"CH",
    "sg:address":"Sur Le Moulin",
    "sg:city":"Rivaz",
    "sg:orig_category":"Rebbau",
    "sg:phone":"+41 21 946 11 31",
    "sg:postcode":"1812",
    "wof:name":"Fernand Chappuis Viticulteur",
    "wof:placetype":"venue"
},
  "geometry": {"coordinates":[6.7786898613,46.4763259888],"type":"Point"}
}