{
  "type": "Feature",
  "properties": {
    "iso:country":"CH",
    "sg:address":"Lion D'or Passage Du 1",
    "sg:city":"Echallens",
    "sg:orig_category":"Gartenbau",
    "sg:postcode":"1040",
    "sg:province":"Vaud",
    "wof:name":"Maillard Cr\u00e9ations Sa",
    "wof:placetype":"venue"
},
  "geometry": {"coordinates":[1.7690769434,48.0816841125],"type":"Point"}
}