{
  "type": "Feature",
  "properties": {
    "iso:country":"CH",
    "sg:address":"Vill\u00e4ggen 6b",
    "sg:city":"N\u00e4fels",
    "sg:orig_category":"Innendekorationsateliers",
    "sg:phone":"+41 55 612 11 34",
    "sg:postcode":"8752",
    "sg:province":"Glarus",
    "wof:name":"Luzia B\u00fcsser Vorhang-atelier",
    "wof:placetype":"venue"
},
  "geometry": {"coordinates":[9.0635728836,47.096786499],"type":"Point"}
}