{
  "type": "Feature",
  "properties": {
    "addr:full":"1413 Orzens Vaud 1413",
    "addr:postcode":"1413;1413",
    "iso:country":"CH",
    "sg:address":"1413",
    "sg:city":"Orzens",
    "sg:orig_category":"Allgemeiner Hoch U Tiefbau",
    "sg:phone":"+41 21 887 77 10",
    "sg:postcode":"1413",
    "sg:province":"Vaud",
    "wof:name":"Wagni\u00e8re Willy",
    "wof:placetype":"venue"
},
  "geometry": {"coordinates":[6.68318,46.72356],"type":"Point"}
}