{
  "type": "Feature",
  "properties": {
    "iso:country":"CH",
    "sg:address":"Im D\u00f6rfli 6",
    "sg:city":"Rotkreuz",
    "sg:orig_category":"Softwareentwicklung U beratung",
    "sg:phone":"+41 41 790 61 50",
    "sg:postcode":"6343",
    "sg:province":"Zug",
    "wof:name":"Imsa Ag Softwareprodukte",
    "wof:placetype":"venue"
},
  "geometry": {"coordinates":[8.4660310745,47.1341400146],"type":"Point"}
}