{
  "type": "Feature",
  "properties": {
    "iso:country":"CH",
    "sg:address":"Gros-ch\u00eane Avenue Du 27",
    "sg:city":"Onex",
    "sg:orig_category":"Erbringung von sonstigen Dienstleistungen f\u00fcr Unterhaltung, Erholung U Freizeit",
    "sg:phone":"+41 22 792 57 47",
    "sg:postcode":"1213",
    "sg:province":"Gen\u00e8ve",
    "wof:name":"Ted, Pazos Natalia",
    "wof:placetype":"venue"
},
  "geometry": {"coordinates":[6.1043162346,46.1883239746],"type":"Point"}
}