{
  "type": "Feature",
  "properties": {
    "iso:country":"CH",
    "sg:address":"Wangenstrasse 49c",
    "sg:city":"Bern",
    "sg:orig_category":"Maler U Glasergewerbe Malerei",
    "sg:phone":"+41 81 322 29 19",
    "sg:postcode":"3018",
    "sg:province":"Bern",
    "wof:name":"Fried + Pelizzatti",
    "wof:placetype":"venue"
},
  "geometry": {"coordinates":[9.5760345459,46.977973938],"type":"Point"}
}