{
  "type": "Feature",
  "properties": {
    "iso:country":"CH",
    "sg:address":"Zelgstrasse 71b",
    "sg:city":"Uetendorf",
    "sg:orig_category":"Grosshandel mit elektrischen Haushaltsger\u00e4ten, Radio U Fernsehger\u00e4ten Sonstiger Grosshandel",
    "sg:phone":"+41 33 345 42 15",
    "sg:postcode":"3661",
    "sg:province":"Bern",
    "wof:name":"Intergros Gmbh",
    "wof:placetype":"venue"
},
  "geometry": {"coordinates":[7.5890097618,46.7797203064],"type":"Point"}
}