{
  "type": "Feature",
  "properties": {
    "iso:country":"CH",
    "sg:address":"Oetlingerstrasse 8",
    "sg:city":"Basel",
    "sg:orig_category":"Herstellung von Elektromotoren, Generatoren U Transformatoren Ingenieurb\u00fcros Umwelttechnik and \u00d6kolo",
    "sg:phone":"+41 61 683 54 01",
    "sg:postcode":"4057",
    "sg:province":"Basel-Stadt",
    "wof:name":"Reist Ingenieurtechnik Ag",
    "wof:placetype":"venue"
},
  "geometry": {"coordinates":[7.5873842239,47.5671844482],"type":"Point"}
}