{
  "type": "Feature",
  "properties": {
    "iso:country":"CH",
    "sg:address":"Gotthardstrasse",
    "sg:city":"Silenen",
    "sg:orig_category":"Sonstiger spezialisierter Hoch U Tiefbau",
    "sg:phone":"+41 41 883 11 48",
    "sg:postcode":"6473",
    "sg:province":"Uri",
    "wof:name":"Gunit Ag",
    "wof:placetype":"venue"
},
  "geometry": {"coordinates":[8.672162056,46.7781867981],"type":"Point"}
}