{
  "type": "Feature",
  "properties": {
    "iso:country":"CH",
    "sg:address":"Buchenstrasse",
    "sg:city":"Lenggenwil",
    "sg:orig_category":"Zimmerei, Dachdeckerei, Bauspenglerei U Abdichtung",
    "sg:phone":"+41 71 947 18 18",
    "sg:postcode":"9525",
    "sg:province":"St. Gallen",
    "wof:name":"Voser, Josef, Holzbau Ag",
    "wof:placetype":"venue"
},
  "geometry": {"coordinates":[9.1476726532,47.476524353],"type":"Point"}
}