{
  "type": "Feature",
  "properties": {
    "iso:country":"CH",
    "sg:address":"Rohr",
    "sg:city":"Tafers",
    "sg:orig_category":"Verwertung von Milch",
    "sg:postcode":"1712",
    "sg:province":"Fribourg",
    "wof:name":"K\u00e4sereigenossenschaft Rohr",
    "wof:placetype":"venue"
},
  "geometry": {"coordinates":[7.2341599464,46.8236503601],"type":"Point"}
}