{
  "type": "Feature",
  "properties": {
    "iso:country":"CH",
    "sg:address":"Rankstrasse 5",
    "sg:city":"Ermensee",
    "sg:classifiers":[
        {
            "category":"Manufacturing",
            "subcategory":"Tools & Machinery",
            "type":"Manufacturing & Wholesale Goods"
        }
    ],
    "sg:phone":"+41 41 917 04 24",
    "sg:postcode":"6294",
    "sg:province":"Luzern",
    "sg:tags":[
        "construction",
        "container",
        "apparatus"
    ],
    "wof:name":"Fribatec Lukas Fries",
    "wof:placetype":"venue"
},
  "geometry": {"coordinates":[8.241536,47.226944],"type":"Point"}
}