{
  "type": "Feature",
  "properties": {
    "iso:country":"CH",
    "sg:address":"Seminarstrasse 27",
    "sg:city":"Z\u00fcrich",
    "sg:orig_category":"Tanzschulen, Tanzlehrer",
    "sg:phone":"+41 71 222 27 14",
    "sg:postcode":"8057",
    "sg:province":"Z\u00fcrich",
    "wof:name":"Regina Karrer Manser Rhythmik/tanz & Bewegung",
    "wof:placetype":"venue"
},
  "geometry": {"coordinates":[9.3721151352,47.4263687134],"type":"Point"}
}