{
  "type": "Feature",
  "properties": {
    "iso:country":"CH",
    "sg:address":"Gibelfeldstrasse 5 2540 Grenchen. Postfach 110",
    "sg:city":"Grenchen",
    "sg:orig_category":"Interessenvertretungen",
    "sg:postcode":"2540",
    "sg:province":"Solothurn",
    "wof:name":"Stiftung Stadtmusik Grenchen",
    "wof:placetype":"venue"
},
  "geometry": {"coordinates":[7.3902788162,47.1890220642],"type":"Point"}
}