{
  "type": "Feature",
  "properties": {
    "iso:country":"CH",
    "sg:address":"La M\u00eal\u00e9e 2",
    "sg:city":"Aigle",
    "sg:orig_category":"Gesundheitswesen",
    "sg:postcode":"1860",
    "sg:province":"Vaud",
    "wof:name":"Burdy Olivier",
    "wof:placetype":"venue"
},
  "geometry": {"coordinates":[6.9363789558,46.3184127808],"type":"Point"}
}