{
  "type": "Feature",
  "properties": {
    "iso:country":"CH",
    "sg:address":"Bahnhof",
    "sg:city":"Weinfelden",
    "sg:classifiers":[
        {
            "category":"Restaurant",
            "type":"Food & Drink"
        }
    ],
    "sg:phone":"+41 71 622 00 93",
    "sg:postcode":"8570",
    "sg:province":"Thurgau",
    "wof:name":"Snack-bar",
    "wof:placetype":"venue"
},
  "geometry": {"coordinates":[9.1064252853,47.5673484802],"type":"Point"}
}