{
  "type": "Feature",
  "properties": {
    "iso:country":"CH",
    "sg:address":"Im Haufland 21",
    "sg:city":"Gr\u00fcningen",
    "sg:orig_category":"Sonstige mit der Informatik verbundene T\u00e4tigkeiten",
    "sg:phone":"+41 19352823",
    "sg:postcode":"8627",
    "sg:province":"Z\u00fcrich",
    "wof:name":"Appenzeller H. Edv-dienstleistungen",
    "wof:placetype":"venue"
},
  "geometry": {"coordinates":[8.7678098679,47.2836494446],"type":"Point"}
}