{
  "type": "Feature",
  "properties": {
    "iso:country":"CH",
    "sg:address":"Strassburgerallee 116",
    "sg:city":"Basel",
    "sg:orig_category":"Grosshandel mit Eisenwaren sowie Installationsbedarf f\u00fcr Gas, Wasser U Heizung",
    "sg:phone":"+41 61 381 30 33",
    "sg:postcode":"4055",
    "sg:province":"Basel-Stadt",
    "wof:name":"Econair Ag L\u00fcftungs, Klima, Energie, Umwelttechnik; Projektierung Usw",
    "wof:placetype":"venue"
},
  "geometry": {"coordinates":[7.5679659843,47.5607566833],"type":"Point"}
}