{
  "type": "Feature",
  "properties": {
    "iso:country":"CH",
    "sg:address":"Bergstrasse 59 4500 Solothurn. Postfach",
    "sg:city":"Solothurn",
    "sg:orig_category":"Werbeagenturen",
    "sg:phone":"+41 32 622 90 60",
    "sg:postcode":"4502",
    "sg:province":"Solothurn",
    "wof:name":"Impact Werbung Kommunikation",
    "wof:placetype":"venue"
},
  "geometry": {"coordinates":[7.5296897888,47.2195358276],"type":"Point"}
}