{
  "type": "Feature",
  "properties": {
    "iso:country":"CH",
    "sg:address":"1772",
    "sg:city":"Grolley",
    "sg:orig_category":"Schulpflegen",
    "sg:phone":"+41 26 475 10 18",
    "sg:postcode":"1772",
    "sg:province":"Fribourg",
    "wof:name":"Commission Scolaire De L'\u00e9cole Primaire",
    "wof:placetype":"venue"
},
  "geometry": {"coordinates":[7.0707321167,46.8333053589],"type":"Point"}
}