{
  "type": "Feature",
  "properties": {
    "iso:country":"CH",
    "sg:address":"Tannenrauchstrasse 52",
    "sg:city":"Z\u00fcrich",
    "sg:orig_category":"Wirtschaftspr\u00fcfung, Steuerberatung U Treuhand",
    "sg:phone":"+41 14871414",
    "sg:postcode":"8038",
    "sg:province":"Z\u00fcrich",
    "wof:name":"Asb Treuhand + Revision Gmbh",
    "wof:placetype":"venue"
},
  "geometry": {"coordinates":[8.5269298553,47.3464241028],"type":"Point"}
}