{
  "type": "Feature",
  "properties": {
    "iso:country":"CH",
    "sg:address":"Gewerbestrasse 6",
    "sg:city":"Unter\u00e4geri",
    "sg:orig_category":"Herstellung von Duft U K\u00f6rperpflegemitteln",
    "sg:postcode":"6314",
    "sg:province":"Zug",
    "wof:name":"Distroma Tc2 Gmbh",
    "wof:placetype":"venue"
},
  "geometry": {"coordinates":[8.5735826492,47.1344451904],"type":"Point"}
}