{
  "type": "Feature",
  "properties": {
    "iso:country":"CH",
    "sg:address":"Im Rank 6",
    "sg:city":"Ermatingen",
    "sg:orig_category":"Allgemeiner Hoch U Tiefbau",
    "sg:phone":"+41 71 660 01 61",
    "sg:postcode":"8272",
    "sg:province":"Thurgau",
    "wof:name":"Ilg Gebr. Rohrleitungsbau Ag",
    "wof:placetype":"venue"
},
  "geometry": {"coordinates":[9.086132,47.671375],"type":"Point"}
}