{
  "type": "Feature",
  "properties": {
    "iso:country":"CH",
    "sg:address":"Wannenweg",
    "sg:city":"Pratteln",
    "sg:orig_category":"RESTAURANTS: TEA-ROOMS",
    "sg:postcode":"4133",
    "sg:province":"Basel-Landschaft",
    "wof:name":"Ruedi's Imbiss, Rudolf Utzinger",
    "wof:placetype":"venue"
},
  "geometry": {"coordinates":[7.7122650146,47.5243835449],"type":"Point"}
}