{
  "type": "Feature",
  "properties": {
    "iso:country":"CH",
    "sg:address":"Wyde 7",
    "sg:city":"Birr",
    "sg:orig_category":"Vorschulen, Kinderg\u00e4rten",
    "sg:phone":"+41 71 911 43 06",
    "sg:postcode":"5242",
    "sg:province":"Aargau",
    "wof:name":"Kindergarten",
    "wof:placetype":"venue"
},
  "geometry": {"coordinates":[9.0592842102,47.4677848816],"type":"Point"}
}