{
  "type": "Feature",
  "properties": {
    "iso:country":"CH",
    "sg:address":"Haslistrasse 4",
    "sg:city":"Windlach",
    "sg:orig_category":"Grosshandel mit Eisenwaren sowie Installationsbedarf f\u00fcr Gas, Wasser U Heizung",
    "sg:phone":"+41 79 665 35 62",
    "sg:postcode":"8175",
    "sg:province":"Z\u00fcrich",
    "wof:name":"Heinrich Vaterlaus Werkzeuge & Schrauben",
    "wof:placetype":"venue"
},
  "geometry": {"coordinates":[8.473985672,47.5394210815],"type":"Point"}
}