{
  "type": "Feature",
  "properties": {
    "iso:country":"CH",
    "sg:address":"Sch\u00fctzenmatte B 6",
    "sg:city":"Stansstad",
    "sg:classifiers":[
        {
            "category":"Professional",
            "subcategory":"Employment Agencies",
            "type":"Services"
        }
    ],
    "sg:phone":"+41 19109706",
    "sg:postcode":"6362",
    "sg:province":"Nidwalden",
    "sg:tags":[
        "personal",
        "u",
        "stellenvermittlung"
    ],
    "wof:name":"B\u00fcchi Werner Dr. Gmbh",
    "wof:placetype":"venue"
},
  "geometry": {"coordinates":[8.6012573242,47.3304595947],"type":"Point"}
}