{
  "type": "Feature",
  "properties": {
    "iso:country":"CH",
    "sg:address":"Industrieweg 14",
    "sg:city":"Rothrist",
    "sg:classifiers":[
        {
            "category":"Food Court",
            "type":"Food & Drink"
        }
    ],
    "sg:phone":"+41 32 861 14 45",
    "sg:postcode":"4852",
    "sg:province":"Aargau",
    "sg:tags":[
        "product",
        "related"
    ],
    "wof:name":"Perrenoud Sa",
    "wof:placetype":"venue"
},
  "geometry": {"coordinates":[6.6155362129,46.9108734131],"type":"Point"}
}