{
  "type": "Feature",
  "properties": {
    "iso:country":"CH",
    "sg:address":"8932",
    "sg:city":"Mettmenstetten",
    "sg:orig_category":"Vereine Musik/Blasmusik",
    "sg:phone":"+41 17671069",
    "sg:postcode":"8932",
    "sg:province":"Z\u00fcrich",
    "wof:name":"Musikverein",
    "wof:placetype":"venue"
},
  "geometry": {"coordinates":[8.4629936218,47.2436332703],"type":"Point"}
}