{
  "type": "Feature",
  "properties": {
    "iso:country":"CH",
    "sg:address":"Kronenweg 2",
    "sg:city":"St\u00e4fa",
    "sg:orig_category":"Sonstiges Gesundheitswesen",
    "sg:phone":"+41 32 652 40 58",
    "sg:postcode":"8712",
    "sg:province":"Z\u00fcrich",
    "wof:name":"Krankenmobilienmagazin Frau Lilly Renfer",
    "wof:placetype":"venue"
},
  "geometry": {"coordinates":[7.3667187691,47.1777992249],"type":"Point"}
}