{
  "type": "Feature",
  "properties": {
    "iso:country":"CH",
    "sg:address":"Gempenstrasse 72",
    "sg:city":"Basel",
    "sg:orig_category":"Vereine Fasnacht",
    "sg:phone":"+41 61 711 12 28",
    "sg:postcode":"4053",
    "sg:province":"Basel-Stadt",
    "wof:name":"Basler Rolli",
    "wof:placetype":"venue"
},
  "geometry": {"coordinates":[7.5984492302,47.5064964294],"type":"Point"}
}