{
  "type": "Feature",
  "properties": {
    "addr:full":"Steghofweg 2 Luzern Luzern 6005",
    "addr:housenumber":"2",
    "addr:postcode":"6005",
    "addr:street":"Steghofweg",
    "iso:country":"CH",
    "sg:address":"Steghofweg 2",
    "sg:city":"Luzern",
    "sg:orig_category":"Architektur U Ingenieurb\u00fcros",
    "sg:phone":"+41 41 360 52 45",
    "sg:postcode":"6005",
    "sg:province":"Luzern",
    "wof:name":"Ritz Zimmerli Sigrist Ag",
    "wof:placetype":"venue"
},
  "geometry": {"coordinates":[8.307025,47.03957],"type":"Point"}
}