{
  "type": "Feature",
  "properties": {
    "iso:country":"CH",
    "sg:address":"Rue Du Ch\u00e2teau-d'en-bas 2",
    "sg:city":"Bulle",
    "sg:orig_category":"Verbraucherm\u00e4rkte > 2500 m2",
    "sg:phone":"+41 26 913 11 11",
    "sg:postcode":"1630",
    "sg:province":"Fribourg",
    "wof:name":"Gruy\u00e8re-centre",
    "wof:placetype":"venue"
},
  "geometry": {"coordinates":[7.0823850632,46.5843086243],"type":"Point"}
}