{
  "type": "Feature",
  "properties": {
    "iso:country":"CH",
    "sg:address":"Dorf",
    "sg:city":"Werthenstein",
    "sg:orig_category":"Detailhandel mit Fleisch U Fleischwaren",
    "sg:phone":"+41 33 951 12 15",
    "sg:postcode":"6106",
    "sg:province":"Luzern",
    "wof:name":"Hans Egli-rettenmund",
    "wof:placetype":"venue"
},
  "geometry": {"coordinates":[8.0334672928,46.7543563843],"type":"Point"}
}