{
  "type": "Feature",
  "properties": {
    "iso:country":"CH",
    "sg:address":"Kirchgasse 15",
    "sg:city":"Ermatingen",
    "sg:orig_category":"Fachdetailhandel in Verkaufsr\u00e4umen",
    "sg:postcode":"8272",
    "sg:province":"Thurgau",
    "wof:name":"Saya Yachtsport Gmbh",
    "wof:placetype":"venue"
},
  "geometry": {"coordinates":[9.0808877945,47.6705818176],"type":"Point"}
}