{
  "type": "Feature",
  "properties": {
    "iso:country":"CH",
    "sg:address":"B\u00e4cherg\u00e4ssli 10",
    "sg:city":"Wollerau",
    "sg:classifiers":[
        {
            "category":"Restaurant",
            "type":"Food & Drink"
        }
    ],
    "sg:phone":"+41 17845958",
    "sg:postcode":"8832",
    "sg:province":"Schwyz",
    "wof:name":"Restaurant Gmurethus",
    "wof:placetype":"venue"
},
  "geometry": {"coordinates":[8.7209863663,47.1967964172],"type":"Point"}
}