{
  "type": "Feature",
  "properties": {
    "iso:country":"CH",
    "sg:address":"Kilchbergstrasse 18",
    "sg:city":"Adliswil",
    "sg:orig_category":"Softwareentwicklung U beratung",
    "sg:phone":"+41 79 414 22 88",
    "sg:postcode":"8134",
    "sg:province":"Z\u00fcrich",
    "wof:name":"Infosa Gmbh",
    "wof:placetype":"venue"
},
  "geometry": {"coordinates":[8.5291852951,47.312538147],"type":"Point"}
}