{
  "type": "Feature",
  "properties": {
    "iso:country":"CH",
    "sg:address":"Route De Crans 7",
    "sg:city":"C\u00e9ligny",
    "sg:orig_category":"Vorschulen, Kinderg\u00e4rten",
    "sg:phone":"+41 22 776 17 13",
    "sg:postcode":"1298",
    "sg:province":"Gen\u00e8ve",
    "wof:name":"Ecole Enfantine",
    "wof:placetype":"venue"
},
  "geometry": {"coordinates":[6.1955070496,46.3508377075],"type":"Point"}
}