{
  "type": "Feature",
  "properties": {
    "iso:country":"CH",
    "sg:address":"Aemtlerstrasse 23",
    "sg:city":"Z\u00fcrich",
    "sg:orig_category":"Sonstige Kultur U Unterhaltungseinrichtungen",
    "sg:phone":"+41 14561030",
    "sg:postcode":"8003",
    "sg:province":"Z\u00fcrich",
    "wof:name":"Theaterhaus Rats",
    "wof:placetype":"venue"
},
  "geometry": {"coordinates":[8.5159301758,47.3715782166],"type":"Point"}
}