{
  "type": "Feature",
  "properties": {
    "iso:country":"CH",
    "sg:address":"Aarbergstrasse 68",
    "sg:city":"Biel/bienne",
    "sg:orig_category":"Sanit\u00e4r U Heizungsinstallation Sanit\u00e4rinstallation",
    "sg:phone":"+41 32 322 26 06",
    "sg:postcode":"2503",
    "sg:province":"Bern",
    "wof:name":"Vittorio Sportelli",
    "wof:placetype":"venue"
},
  "geometry": {"coordinates":[7.2398090363,47.131477356],"type":"Point"}
}