{
  "type": "Feature",
  "properties": {
    "iso:country":"CH",
    "sg:address":"Schwanengasse 10 3011 Bern. Postfach",
    "sg:city":"Bern",
    "sg:orig_category":"Grosshandel mit pharmazeutischen Erzeugnissen, medizinischen U orthop\u00e4dischen Artikeln",
    "sg:postcode":"3005",
    "sg:province":"Bern",
    "wof:name":"Spiritalis K\u00fcnzi Kurt Naturheilmittel; Produktion, Verarbeitung, Vertrieb. Apotheke",
    "wof:placetype":"venue"
},
  "geometry": {"coordinates":[7.4388608932,46.9466743469],"type":"Point"}
}