{
  "type": "Feature",
  "properties": {
    "iso:country":"CH",
    "sg:address":"Incella",
    "sg:city":"Brissago",
    "sg:orig_category":"Vereine K\u00fcnstler",
    "sg:phone":"+41 91 793 43 36",
    "sg:postcode":"6614",
    "sg:province":"Ticino",
    "wof:name":"Amici Dell'arte",
    "wof:placetype":"venue"
},
  "geometry": {"coordinates":[8.7016801834,46.1166000366],"type":"Point"}
}