{
  "type": "Feature",
  "properties": {
    "iso:country":"CH",
    "sg:address":"T\u00f6beli 21 7204 Untervaz. Postfach",
    "sg:city":"Untervaz",
    "sg:orig_category":"Architektur U Ingenieurb\u00fcros Grosshandel mit sonstigen Halbwaren",
    "sg:phone":"+41 81 330 63 88",
    "sg:postcode":"7204",
    "sg:province":"Graubunden",
    "wof:name":"Gabriel Ag, Gesellschaft F\u00fcr Produktion Und Handel",
    "wof:placetype":"venue"
},
  "geometry": {"coordinates":[9.533911,46.929379],"type":"Point"}
}