{
  "type": "Feature",
  "properties": {
    "iso:country":"CH",
    "sg:address":"Michelstrasse 2 8000 Z\u00fcrich. Postfach",
    "sg:city":"Z\u00fcrich",
    "sg:orig_category":"Herstellung von Anstrichmitteln, Druckfarben U Kitten",
    "sg:phone":"+41 13413128",
    "sg:postcode":"8049",
    "sg:province":"Z\u00fcrich",
    "wof:name":"B & B 84 Ag",
    "wof:placetype":"venue"
},
  "geometry": {"coordinates":[8.4962043762,47.4041976929],"type":"Point"}
}