{
  "type": "Feature",
  "properties": {
    "iso:country":"CH",
    "sg:address":"Badenerstrasse 21",
    "sg:city":"Dietikon",
    "sg:orig_category":"Wirtschafts- and Arbeitgeberverb\u00e4nde",
    "sg:phone":"+41 17421222",
    "sg:postcode":"8953",
    "sg:province":"Z\u00fcrich",
    "wof:name":"Fitcom Fitness Company Verein. F\u00fchrender Fitnesscenter",
    "wof:placetype":"venue"
},
  "geometry": {"coordinates":[8.3975076675,47.4059906006],"type":"Point"}
}