{
  "type": "Feature",
  "properties": {
    "iso:country":"CH",
    "sg:address":"P\u00e9rolles Boulevard De 37",
    "sg:city":"Freiburg",
    "sg:orig_category":"Non-Classified Establishments",
    "sg:postcode":"1700",
    "sg:province":"Fribourg",
    "wof:name":"Cdr Communications Holding Ag Beteiligungen. Autoren- U Urheberrechte Usw; Erwerb, Verwertung",
    "wof:placetype":"venue"
},
  "geometry": {"coordinates":[9.3852109909,47.4388961792],"type":"Point"}
}