{
  "type": "Feature",
  "properties": {
    "iso:country":"CH",
    "sg:address":"Poststrasse 3",
    "sg:city":"Bronschhofen",
    "sg:orig_category":"Sanit\u00e4r U Heizungsinstallation",
    "sg:phone":"+41 71 911 65 23",
    "sg:postcode":"9552",
    "sg:province":"St. Gallen",
    "wof:name":"Ernst Baumgartner Elektro-speicher-heizsysteme",
    "wof:placetype":"venue"
},
  "geometry": {"coordinates":[9.0350847244,47.4781455994],"type":"Point"}
}