{
  "type": "Feature",
  "properties": {
    "iso:country":"CH",
    "sg:address":"Hauptstrasse 47",
    "sg:city":"Kreuzlingen",
    "sg:orig_category":"Herstellung von sonstiger Bekleidung U Bekleidungszubeh\u00f6r",
    "sg:phone":"+41 71 672 25 61",
    "sg:postcode":"8280",
    "sg:province":"Thurgau",
    "wof:name":"Frau Jonasch-bitschnau Maria",
    "wof:placetype":"venue"
},
  "geometry": {"coordinates":[9.1748657227,47.6496620178],"type":"Point"}
}