{
  "type": "Feature",
  "properties": {
    "iso:country":"CH",
    "sg:address":"Hochwangstrasse 7304 Maienfeld. Postfach",
    "sg:city":"Maienfeld",
    "sg:orig_category":"Technische, physikalische U chemische Untersuchung",
    "sg:postcode":"7304",
    "sg:province":"Graubunden",
    "wof:name":"Oe-plus Verein F\u00fcr \u00d6konomie + \u00d6kologie + Gesellschaft",
    "wof:placetype":"venue"
},
  "geometry": {"coordinates":[9.537405014,47.0029945374],"type":"Point"}
}