{
  "type": "Feature",
  "properties": {
    "iso:country":"CH",
    "sg:address":"Forchstrasse 319",
    "sg:city":"Z\u00fcrich",
    "sg:orig_category":"Zahnarztpraxen",
    "sg:phone":"+41 13815560",
    "sg:postcode":"8008",
    "sg:province":"Z\u00fcrich",
    "wof:name":"Dr. Med. Dent. Dieter L. Neff Zahnarzt",
    "wof:placetype":"venue"
},
  "geometry": {"coordinates":[8.574590683,47.3553695679],"type":"Point"}
}