{
  "type": "Feature",
  "properties": {
    "iso:country":"CH",
    "sg:address":"Waldhofstrasse 8",
    "sg:city":"Rheinfelden",
    "sg:orig_category":"Wohnheime",
    "sg:phone":"+41 34 431 47 45",
    "sg:postcode":"4310",
    "sg:province":"Aargau",
    "wof:name":"Stiftung Behindertenwerke Oberemmental",
    "wof:placetype":"venue"
},
  "geometry": {"coordinates":[7.757589817,46.9491271973],"type":"Point"}
}