{
  "type": "Feature",
  "properties": {
    "iso:country":"CH",
    "sg:address":"Spitalstrasse 76/1302",
    "sg:city":"Schlieren",
    "sg:orig_category":"Elektro- and elektronische Maschinen Grosshandel",
    "sg:phone":"+41 17301259",
    "sg:postcode":"8952",
    "sg:province":"Z\u00fcrich",
    "wof:name":"Walter Berchtold Electronic",
    "wof:placetype":"venue"
},
  "geometry": {"coordinates":[8.4272823334,47.3965072632],"type":"Point"}
}