{
  "type": "Feature",
  "properties": {
    "iso:country":"CH",
    "sg:address":"Fenkernstrasse 2",
    "sg:city":"Kriens",
    "sg:classifiers":[
        {
            "category":"Government",
            "subcategory":"Post Office",
            "type":"Public Place"
        }
    ],
    "sg:phone":"+41 41 320 14 18",
    "sg:postcode":"6010",
    "sg:province":"Luzern",
    "sg:tags":[
        "caf\u00e9s",
        "tea-rooms"
    ],
    "wof:name":"Caf\u00e9 Fenkern",
    "wof:placetype":"venue"
},
  "geometry": {"coordinates":[8.277633667,47.0339775085],"type":"Point"}
}