{
  "type": "Feature",
  "properties": {
    "iso:country":"CH",
    "sg:address":"Luisenstrasse 7",
    "sg:city":"Z\u00fcrich",
    "sg:orig_category":"Architektur U Ingenieurb\u00fcros Architekturb\u00fcros",
    "sg:phone":"+41 12714040",
    "sg:postcode":"8005",
    "sg:province":"Z\u00fcrich",
    "wof:name":"Dpd Drost Peper Dittli Ag, Dipl. Architekten Eth/sia",
    "wof:placetype":"venue"
},
  "geometry": {"coordinates":[8.528499,47.382687],"type":"Point"}
}