{
  "type": "Feature",
  "properties": {
    "iso:country":"CH",
    "sg:address":"Z.i. En Vannel C 1880 Bex Case Postale 119",
    "sg:city":"Bex",
    "sg:orig_category":"Allgemeiner Hoch U Tiefbau Strassenbau",
    "sg:phone":"+41 33 951 32 35",
    "sg:postcode":"1880",
    "sg:province":"Vaud",
    "wof:name":"Eggenberg Tiefbau Ag",
    "wof:placetype":"venue"
},
  "geometry": {"coordinates":[8.055492,46.759052],"type":"Point"}
}