{
  "type": "Feature",
  "properties": {
    "iso:country":"CH",
    "sg:address":"Murtenstrasse 70",
    "sg:city":"Biel/bienne",
    "sg:orig_category":"Grosshandel mit Fleisch U Fleischwaren Lagerung",
    "sg:phone":"+41 32 323 87 87",
    "sg:postcode":"2503",
    "sg:province":"Bern",
    "wof:name":"Marbot H.r. Ag",
    "wof:placetype":"venue"
},
  "geometry": {"coordinates":[7.2460198402,47.1308517456],"type":"Point"}
}