{
  "type": "Feature",
  "properties": {
    "iso:country":"CH",
    "sg:address":"Schaffhauserstrasse 91 8500 Frauenfeld. Postfach",
    "sg:city":"Frauenfeld",
    "sg:orig_category":"Architekturb\u00fcros",
    "sg:phone":"+41 52 720 86 88",
    "sg:postcode":"8503",
    "sg:province":"Thurgau",
    "wof:name":"J\u00f6rg H\u00e4ni Architekturb\u00fcro",
    "wof:placetype":"venue"
},
  "geometry": {"coordinates":[8.87925,47.562851],"type":"Point"}
}