{
  "type": "Feature",
  "properties": {
    "iso:country":"CH",
    "sg:address":"1532",
    "sg:city":"F\u00e9tigny",
    "sg:orig_category":"Schulpflegen",
    "sg:postcode":"1532",
    "sg:province":"Fribourg",
    "wof:name":"Commission Scolaire De L'ecole Primaire",
    "wof:placetype":"venue"
},
  "geometry": {"coordinates":[6.9136800766,46.7945709229],"type":"Point"}
}