{
  "type": "Feature",
  "properties": {
    "iso:country":"CH",
    "sg:address":"3207",
    "sg:city":"Golaten",
    "sg:orig_category":"Primarschulen",
    "sg:postcode":"3207",
    "sg:province":"Bern",
    "wof:name":"Primarschule",
    "wof:placetype":"venue"
},
  "geometry": {"coordinates":[7.2424230576,46.9858665466],"type":"Point"}
}