{
  "type": "Feature",
  "properties": {
    "iso:country":"CH",
    "sg:address":"Grindelstrasse",
    "sg:city":"Volketswil",
    "sg:orig_category":"Vorschulen, Kinderg\u00e4rten",
    "sg:postcode":"8604",
    "sg:province":"Z\u00fcrich",
    "wof:name":"Kindergarten Steibrugg",
    "wof:placetype":"venue"
},
  "geometry": {"coordinates":[8.6656093597,47.3864135742],"type":"Point"}
}