{
  "type": "Feature",
  "properties": {
    "iso:country":"CH",
    "sg:address":"St. Galler-strasse 27",
    "sg:city":"Winterthur",
    "sg:orig_category":"Mechanische Werkst\u00e4tten",
    "sg:phone":"+41 52 213 06 55",
    "sg:postcode":"8400",
    "sg:province":"Z\u00fcrich",
    "wof:name":"Marino Di Basilico Mechanische Werkstatt",
    "wof:placetype":"venue"
},
  "geometry": {"coordinates":[8.7360315323,47.4983673096],"type":"Point"}
}