{
  "type": "Feature",
  "properties": {
    "iso:country":"CH",
    "sg:address":"Adlibogenstrasse 20",
    "sg:city":"Niederhasli",
    "sg:orig_category":"Einbau von Schreinerwaren Grosshandel mit M\u00f6beln, Wohnbedarf, Teppichen U Bodenbel\u00e4gen",
    "sg:phone":"+41 18505055",
    "sg:postcode":"8155",
    "sg:province":"Z\u00fcrich",
    "wof:name":"Gch Gastro-consulting Und Handels Ag, Glattbrugg, Zweigniederlassung Niederhasli",
    "wof:placetype":"venue"
},
  "geometry": {"coordinates":[8.4952306747,47.4800071716],"type":"Point"}
}