{
  "type": "Feature",
  "properties": {
    "iso:country":"CH",
    "sg:address":"Solothurnstrasse 142",
    "sg:city":"Biel/bienne",
    "sg:orig_category":"Detailhandel mit Beleuchtungs U Haushaltsgegenst\u00e4nden",
    "sg:phone":"+41 32 341 34 24",
    "sg:postcode":"2504",
    "sg:province":"Bern",
    "wof:name":"Lumimart",
    "wof:placetype":"venue"
},
  "geometry": {"coordinates":[7.284147,47.161728],"type":"Point"}
}