{
  "type": "Feature",
  "properties": {
    "iso:country":"CH",
    "sg:address":"Baarerstrasse 101",
    "sg:city":"Zug",
    "sg:orig_category":"Unclassifiable Establishments",
    "sg:postcode":"6300",
    "sg:province":"Zug",
    "wof:name":"Vega Software Corporation Sa",
    "wof:placetype":"venue"
},
  "geometry": {"coordinates":[8.518157959,47.1787376404],"type":"Point"}
}