{
  "type": "Feature",
  "properties": {
    "iso:country":"CH",
    "sg:address":"Christoffelgasse 4",
    "sg:city":"Bern",
    "sg:classifiers":[
        {
            "category":"Shopping",
            "subcategory":"Clothing, Apparel, & Fashions",
            "type":"Retail Goods"
        }
    ],
    "sg:phone":"+41 31 311 00 88",
    "sg:postcode":"3011",
    "sg:province":"Bern",
    "sg:tags":[
        "blouse",
        "ladies'",
        "dress"
    ],
    "wof:name":"Ackermann Shops Ag",
    "wof:placetype":"venue"
},
  "geometry": {"coordinates":[7.4406409264,46.946937561],"type":"Point"}
}