{
  "type": "Feature",
  "properties": {
    "iso:country":"CH",
    "sg:address":"L\u00e4ngg\u00e4ssli 9 3604 Thun. Postfach",
    "sg:city":"Thun",
    "sg:orig_category":"Instandhaltung U Reparatur von Automobilen",
    "sg:postcode":"3604",
    "sg:province":"Bern",
    "wof:name":"Alpin Kraftfahrzeugtechnik, Stucki Adrian",
    "wof:placetype":"venue"
},
  "geometry": {"coordinates":[7.6135129929,46.7335128784],"type":"Point"}
}