{
  "type": "Feature",
  "properties": {
    "iso:country":"CH",
    "sg:address":"Allschwilerstrasse 71",
    "sg:city":"Basel",
    "sg:orig_category":"Herstellung von Speiseeis U Sorbets",
    "sg:postcode":"4055",
    "sg:province":"Basel-Stadt",
    "wof:name":"Soft-ice Z\u00fcger & Zwicky",
    "wof:placetype":"venue"
},
  "geometry": {"coordinates":[9.2693748474,47.4148902893],"type":"Point"}
}