{
  "type": "Feature",
  "properties": {
    "iso:country":"CH",
    "sg:address":"Austrasse 38",
    "sg:city":"Z\u00fcrich",
    "sg:orig_category":"Architektur U Ingenieurb\u00fcros Innenarchitekturb\u00fcros",
    "sg:phone":"+41 14502277",
    "sg:postcode":"8045",
    "sg:province":"Z\u00fcrich",
    "wof:name":"Mosersidler Ag F\u00fcr Lichtplanung",
    "wof:placetype":"venue"
},
  "geometry": {"coordinates":[8.519549,47.365074],"type":"Point"}
}