{
  "type": "Feature",
  "properties": {
    "addr:full":"Kapellen 4 Meiringen Bern 3860",
    "addr:housenumber":"4",
    "addr:postcode":"3860",
    "addr:street":"Kapellen",
    "iso:country":"CH",
    "sg:address":"Kapellen 4",
    "sg:city":"Meiringen",
    "sg:orig_category":"Bezirks, Sekundar, Realschulen, Oberstufe der Primarschulen",
    "sg:phone":"+41 33 971 19 09",
    "sg:postcode":"3860",
    "sg:province":"Bern",
    "wof:name":"Sekundarschule",
    "wof:placetype":"venue"
},
  "geometry": {"coordinates":[8.189276,46.728977],"type":"Point"}
}