{
  "type": "Feature",
  "properties": {
    "iso:country":"CH",
    "sg:address":"Thesenacher 30",
    "sg:city":"Zumikon",
    "sg:orig_category":"Detailhandel mit Damenbekleidung",
    "sg:phone":"+41 19181655",
    "sg:postcode":"8126",
    "sg:province":"Z\u00fcrich",
    "wof:name":"Festmode Elisabeth Elisabeth Rose",
    "wof:placetype":"venue"
},
  "geometry": {"coordinates":[8.630992,47.327522],"type":"Point"}
}