{
  "type": "Feature",
  "properties": {
    "iso:country":"CH",
    "sg:address":"Bahnhofstrasse 1",
    "sg:city":"Littau",
    "sg:orig_category":"Non-Classified Establishments",
    "sg:postcode":"6014",
    "sg:province":"Luzern",
    "wof:name":"Sch\u00e4rli 'beck', B\u00e4ckerei-konditorei",
    "wof:placetype":"venue"
},
  "geometry": {"coordinates":[8.2586584091,47.0515174866],"type":"Point"}
}