{
  "type": "Feature",
  "properties": {
    "iso:country":"CH",
    "sg:address":"Im Eisernen Zeit 38",
    "sg:city":"Z\u00fcrich",
    "sg:orig_category":"Unternehmensberatung",
    "sg:phone":"+41 13637689",
    "sg:postcode":"8057",
    "sg:province":"Z\u00fcrich",
    "wof:name":"Wettler Roman A. Management Consulting",
    "wof:placetype":"venue"
},
  "geometry": {"coordinates":[8.5419626236,47.3923912048],"type":"Point"}
}