{
  "type": "Feature",
  "properties": {
    "iso:country":"CH",
    "sg:address":"Alte Bernstrasse 17",
    "sg:city":"Schnottwil",
    "sg:orig_category":"Selbst\u00e4ndige bildende K\u00fcnstler",
    "sg:phone":"+41 32 351 40 59",
    "sg:postcode":"3253",
    "sg:province":"Solothurn",
    "wof:name":"Marc Reist Grabmalkunst Bildhauerei",
    "wof:placetype":"venue"
},
  "geometry": {"coordinates":[7.3893489838,47.1146011353],"type":"Point"}
}