{
  "type": "Feature",
  "properties": {
    "iso:country":"CH",
    "sg:address":"Via Pusterla 2a",
    "sg:city":"Balerna",
    "sg:orig_category":"Detailhandel mit Waren verschiedener Art, Hauptrichtung Nahrungsmittel",
    "sg:phone":"+41 91 683 31 82",
    "sg:postcode":"6828",
    "sg:province":"Ticino",
    "wof:name":"Alfredo Butti Negozio",
    "wof:placetype":"venue"
},
  "geometry": {"coordinates":[9.0073490143,45.8490829468],"type":"Point"}
}