{
  "type": "Feature",
  "properties": {
    "iso:country":"CH",
    "sg:address":"Blumenstrasse 4 9400 Rorschach. Postfach",
    "sg:city":"Rorschach",
    "sg:orig_category":"Zahntechnische Laboratorien",
    "sg:phone":"+41 71 841 75 56",
    "sg:postcode":"9400",
    "sg:province":"St. Gallen",
    "wof:name":"Thoma-gravuren Zahntechnisches Labor",
    "wof:placetype":"venue"
},
  "geometry": {"coordinates":[9.4958181381,47.4763336182],"type":"Point"}
}