{
  "type": "Feature",
  "properties": {
    "iso:country":"CH",
    "sg:address":"Kirchgasse 9",
    "sg:city":"Aarau",
    "sg:orig_category":"Detailhandel mit Geschenkartikeln U Souvenirs",
    "sg:phone":"+41 62 822 55 76",
    "sg:postcode":"5000",
    "sg:province":"Aargau",
    "wof:name":"Wwf Panda Boutique M\u00fcller K.",
    "wof:placetype":"venue"
},
  "geometry": {"coordinates":[8.0431842804,47.3924674988],"type":"Point"}
}