{
  "type": "Feature",
  "properties": {
    "iso:country":"CH",
    "sg:address":"Im Wiesengrund 18",
    "sg:city":"Wettswil",
    "sg:orig_category":"Wirtschafts- and Arbeitgeberverb\u00e4nde",
    "sg:phone":"+41 17779221",
    "sg:postcode":"8907",
    "sg:province":"Z\u00fcrich",
    "wof:name":"Schweizerischer Baumeister- Verband Affoltern",
    "wof:placetype":"venue"
},
  "geometry": {"coordinates":[8.4732151031,47.3325576782],"type":"Point"}
}