{
  "type": "Feature",
  "properties": {
    "iso:country":"CH",
    "sg:address":"Ebenaustrasse 10",
    "sg:city":"Horw",
    "sg:orig_category":"Softwareentwicklung U beratung",
    "sg:phone":"+41 41 340 46 01",
    "sg:postcode":"6048",
    "sg:province":"Luzern",
    "wof:name":"Virtual Graphixx M. M\u00fcller",
    "wof:placetype":"venue"
},
  "geometry": {"coordinates":[8.3079395294,47.0138587952],"type":"Point"}
}