{
  "type": "Feature",
  "properties": {
    "iso:country":"CH",
    "sg:address":"Aarbergstrasse 91",
    "sg:city":"Biel/bienne",
    "sg:orig_category":"Sonstige technische Beratung U Planung",
    "sg:phone":"+41 32 328 11 44",
    "sg:postcode":"2502",
    "sg:province":"Bern",
    "wof:name":"B\u00fcro Iseli & B\u00f6siger Umweltberatung",
    "wof:placetype":"venue"
},
  "geometry": {"coordinates":[7.2398028374,47.1340141296],"type":"Point"}
}