{
  "type": "Feature",
  "properties": {
    "iso:country":"CH",
    "sg:address":"Via Lido 27",
    "sg:city":"Ascona",
    "sg:orig_category":"Arztpraxen",
    "sg:phone":"+41 79 239 04 04",
    "sg:postcode":"6612",
    "sg:province":"Ticino",
    "wof:name":"Dott.med.nello Broggini Medico Generico Fmh",
    "wof:placetype":"venue"
},
  "geometry": {"coordinates":[8.77505,46.151489],"type":"Point"}
}