{
  "type": "Feature",
  "properties": {
    "iso:country":"CH",
    "sg:address":"Ringstrasse 2b",
    "sg:city":"Ostermundigen",
    "sg:orig_category":"Instandhaltung U Reparatur von Automobilen",
    "sg:phone":"+41 31 931 94 45",
    "sg:postcode":"3072",
    "sg:province":"Bern",
    "wof:name":"Garage Melina",
    "wof:placetype":"venue"
},
  "geometry": {"coordinates":[7.4789719582,46.9543952942],"type":"Point"}
}