{
  "type": "Feature",
  "properties": {
    "iso:country":"CH",
    "sg:address":"Rue Des Vollandes 24-26",
    "sg:city":"Gen\u00e8ve",
    "sg:orig_category":"Bauspenglerei Sanit\u00e4rinstallation",
    "sg:phone":"+41 32 757 12 82",
    "sg:postcode":"1207",
    "sg:province":"Gen\u00e8ve",
    "wof:name":"Pierre-andr\u00e9 Richard Ferblanterie & Appareillage",
    "wof:placetype":"venue"
},
  "geometry": {"coordinates":[7.03706,47.052319],"type":"Point"}
}