{
  "type": "Feature",
  "properties": {
    "iso:country":"CH",
    "sg:address":"L\u00e4ttenstrasse 9",
    "sg:city":"Lindau",
    "sg:orig_category":"Herstellung von Konstruktionsteilen, Fertigbauteilen U Ausbauelementen aus Holz",
    "sg:phone":"+41 52 345 19 36",
    "sg:postcode":"8315",
    "sg:province":"Z\u00fcrich",
    "wof:name":"Hans Gerber Ag",
    "wof:placetype":"venue"
},
  "geometry": {"coordinates":[8.66609478,47.444355011],"type":"Point"}
}