{
  "type": "Feature",
  "properties": {
    "iso:country":"CH",
    "sg:address":"Avenue Dapples 54",
    "sg:city":"Lausanne",
    "sg:orig_category":"Architektur U Ingenieurb\u00fcros",
    "sg:phone":"+41 62 212 84 35",
    "sg:postcode":"1006",
    "sg:province":"Vaud",
    "wof:name":"Frey & Gnehm Olten Ag Ingenieurb\u00fcro",
    "wof:placetype":"venue"
},
  "geometry": {"coordinates":[7.862888,47.345604],"type":"Point"}
}