{
  "type": "Feature",
  "properties": {
    "iso:country":"CH",
    "sg:address":"Stampfenbachstrasse 105",
    "sg:city":"Z\u00fcrich",
    "sg:orig_category":"Unternehmensberatung",
    "sg:postcode":"8006",
    "sg:province":"Z\u00fcrich",
    "wof:name":"Wirz Zollinger Baumanagement Ag",
    "wof:placetype":"venue"
},
  "geometry": {"coordinates":[8.5409936905,47.3830757141],"type":"Point"}
}