{
  "type": "Feature",
  "properties": {
    "iso:country":"CH",
    "sg:address":"Thalerstrasse 26",
    "sg:city":"Heiden",
    "sg:orig_category":"Grosshandel mit Milch, Milcherzeugnissen, Eiern, Speise\u00f6len U Nahrungsfetten",
    "sg:phone":"+41 71 891 18 42",
    "sg:postcode":"9410",
    "sg:province":"Appenzell Ausserrhoden",
    "wof:name":"Kurt Wehrli K\u00e4se Engros",
    "wof:placetype":"venue"
},
  "geometry": {"coordinates":[9.5391407013,47.4548912048],"type":"Point"}
}