{
  "type": "Feature",
  "properties": {
    "iso:country":"CH",
    "sg:address":"Route De L'usine-\u00e0-gaz 4",
    "sg:city":"A\u00efre",
    "sg:orig_category":"Instandhaltung U Reparatur von Automobilen Tankstellen",
    "sg:phone":"+41 22 796 41 43",
    "sg:postcode":"1219",
    "sg:province":"Gen\u00e8ve",
    "wof:name":"Mcs Motor Car Services Sa",
    "wof:placetype":"venue"
},
  "geometry": {"coordinates":[6.0969829559,49.6145744324],"type":"Point"}
}