{
  "type": "Feature",
  "properties": {
    "iso:country":"CH",
    "sg:address":"H\u00f6henstrasse 10 8304 Wallisellen. Postfach",
    "sg:city":"Kloten",
    "sg:orig_category":"Herstellung von Radio U Fernsehger\u00e4ten sowie phono U videotechnischen Ger\u00e4ten",
    "sg:postcode":"8302",
    "sg:province":"Z\u00fcrich",
    "wof:name":"Balint A., Communications And Electronics",
    "wof:placetype":"venue"
},
  "geometry": {"coordinates":[8.5954189301,47.4199867249],"type":"Point"}
}