{
  "type": "Feature",
  "properties": {
    "iso:country":"CH",
    "sg:address":"Riederalp",
    "sg:city":"Ried-m\u00f6rel",
    "sg:orig_category":"RESTAURANTS: TEA-ROOMS",
    "sg:postcode":"3986",
    "sg:province":"Valais",
    "wof:name":"Restaurant Derby, Peter Albrecht",
    "wof:placetype":"venue"
},
  "geometry": {"coordinates":[8.0320081711,46.3573417664],"type":"Point"}
}