{
  "type": "Feature",
  "properties": {
    "addr:full":"Kanalstrasse 13 Stansstad Nidwalden 6362",
    "addr:housenumber":"13",
    "addr:postcode":"6362",
    "addr:street":"Kanalstrasse",
    "iso:country":"CH",
    "sg:address":"Kanalstrasse 13",
    "sg:city":"Stansstad",
    "sg:orig_category":"Architektur U Ingenieurb\u00fcros Architekturb\u00fcros",
    "sg:phone":"+41 41 610 52 84",
    "sg:postcode":"6362",
    "sg:province":"Nidwalden",
    "wof:name":"Battagello & Hugentobler Architekturb\u00fcro Ag.",
    "wof:placetype":"venue"
},
  "geometry": {"coordinates":[8.342077,46.970425],"type":"Point"}
}