{
  "type": "Feature",
  "properties": {
    "iso:country":"CH",
    "sg:address":"Chemin Des Myosotis 14 1214 Vernier. Postfach",
    "sg:city":"Vernier",
    "sg:orig_category":"Maler U Glasergewerbe",
    "sg:postcode":"1214",
    "sg:province":"Gen\u00e8ve",
    "wof:name":"Inan Tony",
    "wof:placetype":"venue"
},
  "geometry": {"coordinates":[6.0906748772,46.2167205811],"type":"Point"}
}