{
  "type": "Feature",
  "properties": {
    "iso:country":"CH",
    "sg:address":"Berninastrasse 112",
    "sg:city":"Z\u00fcrich",
    "sg:orig_category":"Reiseb\u00fcros U Reiseveranstalter",
    "sg:phone":"+41 13114141",
    "sg:postcode":"8057",
    "sg:province":"Z\u00fcrich",
    "wof:name":"W\u00e4ckerlin Carreisen Ag",
    "wof:placetype":"venue"
},
  "geometry": {"coordinates":[8.5396976471,47.4066581726],"type":"Point"}
}