{
  "type": "Feature",
  "properties": {
    "iso:country":"CH",
    "sg:address":"Ey 6",
    "sg:city":"Ittigen",
    "sg:orig_category":"Sportvereine Sch\u00fctzen",
    "sg:phone":"+41 31 921 04 88",
    "sg:postcode":"3063",
    "sg:province":"Bern",
    "wof:name":"Feldsch\u00fctzengesell.geristein",
    "wof:placetype":"venue"
},
  "geometry": {"coordinates":[7.4725689888,46.9750213623],"type":"Point"}
}