{
  "type": "Feature",
  "properties": {
    "iso:country":"CH",
    "sg:address":"Franscini Viale 40",
    "sg:city":"Lugano",
    "sg:orig_category":"Unclassifiable Establishments",
    "sg:phone":"+41 91 912 64 50",
    "sg:postcode":"6900",
    "sg:province":"Ticino",
    "wof:name":"The Net Fashion Holding Bv, Amsterdam, Succursale Di Lugano",
    "wof:placetype":"venue"
},
  "geometry": {"coordinates":[8.9548912048,46.0112876892],"type":"Point"}
}