{
  "type": "Feature",
  "properties": {
    "iso:country":"CH",
    "sg:address":"Borgo",
    "sg:city":"Brusio",
    "sg:orig_category":"Dauerkulturbau Herstellung von Getr\u00e4nken",
    "sg:phone":"+41 81 723 71 40",
    "sg:postcode":"7743",
    "sg:province":"Graubunden",
    "wof:name":"M\u00fcller Franz Weinbau",
    "wof:placetype":"venue"
},
  "geometry": {"coordinates":[9.406994,47.061893],"type":"Point"}
}