{
  "type": "Feature",
  "properties": {
    "iso:country":"CH",
    "sg:address":"Zugerstrasse 55",
    "sg:city":"Steinhausen",
    "sg:orig_category":"Herstellung von Elektrizit\u00e4tsverteilungs U schalteinrichtungen",
    "sg:postcode":"6312",
    "sg:province":"Zug",
    "wof:name":"B\u00e4rg, Schaltanlagen Und Elektronik, Walter B\u00e4rtschiger",
    "wof:placetype":"venue"
},
  "geometry": {"coordinates":[8.4893131256,47.1916046143],"type":"Point"}
}