{
  "type": "Feature",
  "properties": {
    "iso:country":"CH",
    "sg:address":"Schulhausstrasse 28",
    "sg:city":"Villmergen",
    "sg:classifiers":[
        {
            "category":"Restaurant",
            "type":"Food & Drink"
        }
    ],
    "sg:phone":"+41 56 622 10 07",
    "sg:postcode":"5612",
    "sg:province":"Aargau",
    "wof:name":"Restaurant Frohheim",
    "wof:placetype":"venue"
},
  "geometry": {"coordinates":[8.2411966324,47.3492927551],"type":"Point"}
}