{
  "type": "Feature",
  "properties": {
    "iso:country":"CH",
    "sg:address":"R\u00fcti 8883 Quarten. Postfach",
    "sg:city":"Murg",
    "sg:orig_category":"Unternehmensberatung",
    "sg:postcode":"8877",
    "sg:province":"St. Gallen",
    "wof:name":"Schwager Christian B\u00fcro F\u00fcr Verkauf U. Beratung",
    "wof:placetype":"venue"
},
  "geometry": {"coordinates":[9.2411851883,47.1078948975],"type":"Point"}
}