{
  "type": "Feature",
  "properties": {
    "iso:country":"CH",
    "sg:address":"Kanzleistrasse 15",
    "sg:city":"Z\u00fcrich",
    "sg:orig_category":"RESTAURANTS: TEA-ROOMS",
    "sg:phone":"+41 12417378",
    "sg:postcode":"8004",
    "sg:province":"Z\u00fcrich",
    "wof:name":"Villiger Beat, Restaurant Les Mains Bleues",
    "wof:placetype":"venue"
},
  "geometry": {"coordinates":[8.5274600983,47.3737335205],"type":"Point"}
}