{
  "type": "Feature",
  "properties": {
    "iso:country":"CH",
    "sg:address":"Murbacherstrasse 1",
    "sg:city":"Luzern",
    "sg:orig_category":"Allgemeiner Hoch U Tiefbau",
    "sg:postcode":"6003",
    "sg:province":"Luzern",
    "wof:name":"Rohner Franz Ag",
    "wof:placetype":"venue"
},
  "geometry": {"coordinates":[8.309463,47.048599],"type":"Point"}
}