{
  "type": "Feature",
  "properties": {
    "addr:full":"Hauptstrasse 289 Brusio Graubunden 7743",
    "addr:housenumber":"289;7743",
    "addr:street":"Hauptstrasse",
    "iso:country":"CH",
    "sg:address":"Hauptstrasse 289",
    "sg:city":"Brusio",
    "sg:orig_category":"Dauerkulturbau",
    "sg:phone":"+41 81 846 55 65",
    "sg:postcode":"7743",
    "sg:province":"Graubunden",
    "wof:name":"Plozza Sa",
    "wof:placetype":"venue"
},
  "geometry": {"coordinates":[10.125009,46.2589],"type":"Point"}
}