{
  "type": "Feature",
  "properties": {
    "iso:country":"CH",
    "sg:address":"Fribourg Route De 15",
    "sg:city":"Marly",
    "sg:orig_category":"Sonstiger Grosshandel",
    "sg:phone":"+41 26 435 33 33",
    "sg:postcode":"1723",
    "sg:province":"Fribourg",
    "wof:name":"Axo-texcomp Intertrade Ltd Sa",
    "wof:placetype":"venue"
},
  "geometry": {"coordinates":[7.151031971,46.7801628113],"type":"Point"}
}