{
  "type": "Feature",
  "properties": {
    "addr:full":"Birchstrasse 6 Seuzach Z\u00fcrich 8472",
    "addr:housenumber":"6",
    "addr:postcode":"8472",
    "addr:street":"Birchstrasse",
    "iso:country":"CH",
    "sg:address":"Birchstrasse 6",
    "sg:city":"Seuzach",
    "sg:orig_category":"Detailhandel mit Damenbekleidung",
    "sg:phone":"+41 52 335 39 85",
    "sg:postcode":"8472",
    "sg:province":"Z\u00fcrich",
    "wof:name":"Erica Steinbr\u00fcchel Damenmoden",
    "wof:placetype":"venue"
},
  "geometry": {"coordinates":[8.73593,47.536011],"type":"Point"}
}