{
  "type": "Feature",
  "properties": {
    "iso:country":"CH",
    "sg:address":"Ettiswilerstrasse 17",
    "sg:city":"Willisau",
    "sg:orig_category":"Unclassifiable Establishments",
    "sg:postcode":"6130",
    "sg:province":"Luzern",
    "wof:name":"Romy St\u00fcrmlin",
    "wof:placetype":"venue"
},
  "geometry": {"coordinates":[7.9953999519,47.1245689392],"type":"Point"}
}