{
  "type": "Feature",
  "properties": {
    "iso:country":"CH",
    "sg:address":"Industriestrasse 11",
    "sg:city":"Uetendorf",
    "sg:orig_category":"Physiotherapie",
    "sg:phone":"+41 79 311 08 92",
    "sg:postcode":"3661",
    "sg:province":"Bern",
    "wof:name":"Physiotherapie Uetendorf",
    "wof:placetype":"venue"
},
  "geometry": {"coordinates":[7.5792560577,46.7766685486],"type":"Point"}
}