{
  "type": "Feature",
  "properties": {
    "iso:country":"CH",
    "sg:address":"Chemin Des Cherpines 7 1228 Plan-les-ouates. Postfach",
    "sg:city":"Plan-les-ouates",
    "sg:orig_category":"Herstellung von Speiseeis U Sorbets",
    "sg:postcode":"1228",
    "sg:province":"Gen\u00e8ve",
    "wof:name":"Le Glacier Des Alpes S\u00e0rl",
    "wof:placetype":"venue"
},
  "geometry": {"coordinates":[6.106359005,46.1747550964],"type":"Point"}
}