{
  "type": "Feature",
  "properties": {
    "iso:country":"CH",
    "sg:address":"Bahnhofstrasse 29",
    "sg:city":"N\u00e4fels",
    "sg:classifiers":[
        {
            "category":"Travel",
            "subcategory":"Hotels & Motels",
            "type":"Entertainment"
        }
    ],
    "sg:phone":"+41 55 612 10 42",
    "sg:postcode":"8752",
    "sg:province":"Glarus",
    "sg:tags":[
        "hotels",
        "mit",
        "restaurant"
    ],
    "wof:name":"Hotel Bahnhof",
    "wof:placetype":"venue"
},
  "geometry": {"coordinates":[9.0675458908,47.0995635986],"type":"Point"}
}