{
  "type": "Feature",
  "properties": {
    "iso:country":"CH",
    "sg:address":"Lausanne Rue De 120 1202 Gen\u00e8ve. Postfach",
    "sg:city":"Gen\u00e8ve",
    "sg:orig_category":"Interessenvertretungen",
    "sg:postcode":"1202",
    "sg:province":"Gen\u00e8ve",
    "wof:name":"Fondation Poletti Paul",
    "wof:placetype":"venue"
},
  "geometry": {"coordinates":[6.1497020721,46.2198410034],"type":"Point"}
}