{
  "type": "Feature",
  "properties": {
    "addr:full":"Bahnhofwiese 7 St\u00e4fa Z\u00fcrich 8712",
    "addr:housenumber":"7",
    "addr:postcode":"8712",
    "addr:street":"Bahnhofwiese;Zuerich",
    "iso:country":"CH",
    "sg:address":"Bahnhofwiese 7",
    "sg:city":"St\u00e4fa",
    "sg:orig_category":"Detailhandel mit Blumen U Pflanzen",
    "sg:phone":"+41 19262251",
    "sg:postcode":"8712",
    "sg:province":"Z\u00fcrich",
    "wof:name":"Siegfried Pl\u00fcschke Blumen Corso",
    "wof:placetype":"venue"
},
  "geometry": {"coordinates":[8.722111,47.241463],"type":"Point"}
}