{
  "type": "Feature",
  "properties": {
    "iso:country":"CH",
    "sg:address":"Route De Cl\u00e9menty 64",
    "sg:city":"Nyon",
    "sg:orig_category":"Sonstige mit der Informatik verbundene T\u00e4tigkeiten",
    "sg:phone":"+41 22 362 10 17",
    "sg:postcode":"1260",
    "sg:province":"Vaud",
    "wof:name":"Cabinet Waridel P. M.",
    "wof:placetype":"venue"
},
  "geometry": {"coordinates":[6.228219986,46.3816337585],"type":"Point"}
}