{
  "type": "Feature",
  "properties": {
    "iso:country":"CH",
    "sg:address":"Dufour Via 2",
    "sg:city":"Lugano",
    "sg:orig_category":"Vermietung U Verpachtung von eigenen Immobilien",
    "sg:postcode":"6900",
    "sg:province":"Ticino",
    "wof:name":"Keiser Immobilien Ag Hergiswil",
    "wof:placetype":"venue"
},
  "geometry": {"coordinates":[8.3106822968,46.9874076843],"type":"Point"}
}