{
  "type": "Feature",
  "properties": {
    "iso:country":"CH",
    "sg:address":"R\u00fcschlistrasse 2",
    "sg:city":"Biel/bienne",
    "sg:orig_category":"Detailhandel mit Antiquit\u00e4ten Kunsthandel",
    "sg:phone":"+41 79 323 14 55",
    "sg:postcode":"2502",
    "sg:province":"Bern",
    "wof:name":"Hans & Marl\u00e8ne Wiedemann Antiquit\u00e4ten-& Kunsthandel",
    "wof:placetype":"venue"
},
  "geometry": {"coordinates":[7.242665,47.139339],"type":"Point"}
}