{
  "type": "Feature",
  "properties": {
    "iso:country":"CH",
    "sg:address":"Hegenstrasse 16",
    "sg:city":"Bollodingen",
    "sg:orig_category":"RESTAURANTS: TEA-ROOMS",
    "sg:phone":"+41 62 961 02 42",
    "sg:postcode":"3366",
    "sg:province":"Bern",
    "wof:name":"Heiniger Yvonne, Restaurant Sonne",
    "wof:placetype":"venue"
},
  "geometry": {"coordinates":[7.7080101967,47.1714057922],"type":"Point"}
}