{
  "type": "Feature",
  "properties": {
    "iso:country":"CH",
    "sg:address":"1142",
    "sg:city":"Pampigny",
    "sg:orig_category":"Elektroinstallation",
    "sg:phone":"+41 21 800 50 93",
    "sg:postcode":"1142",
    "sg:province":"Vaud",
    "wof:name":"Aubert Fernand",
    "wof:placetype":"venue"
},
  "geometry": {"coordinates":[6.4278230667,46.5800819397],"type":"Point"}
}