{
  "type": "Feature",
  "properties": {
    "iso:country":"CH",
    "sg:address":"H\u00f6lzliweg 3",
    "sg:city":"Fulenbach",
    "sg:orig_category":"Sanit\u00e4r, Heizungs U L\u00fcftungsinstallation",
    "sg:phone":"+41 62 926 28 24",
    "sg:postcode":"4629",
    "sg:province":"Solothurn",
    "wof:name":"Sanit\u00e4r J\u00e4ggi-pl\u00fcss",
    "wof:placetype":"venue"
},
  "geometry": {"coordinates":[7.8381757736,47.2801628113],"type":"Point"}
}