{
  "type": "Feature",
  "properties": {
    "iso:country":"CH",
    "sg:address":"Sonnenstrasse 7",
    "sg:city":"Brig",
    "sg:orig_category":"G\u00fcterbef\u00f6rderung im Strassenverkehr",
    "sg:phone":"+41 27 923 66 22",
    "sg:postcode":"3900",
    "sg:province":"Valais",
    "wof:name":"Audi & Cie., Internationale Transporte, Nachfolger Schmid Beat",
    "wof:placetype":"venue"
},
  "geometry": {"coordinates":[7.9868879318,46.3177947998],"type":"Point"}
}