{
  "type": "Feature",
  "properties": {
    "iso:country":"CH",
    "sg:address":"Pestalozzistrasse 57 5000 Aarau. Postfach",
    "sg:city":"Aarau",
    "sg:orig_category":"Grosshandel mit landwirtschaftlichen Maschinen U Ger\u00e4ten Herstellung von Beh\u00e4ltern aus Metall",
    "sg:phone":"+41 62 824 56 54",
    "sg:postcode":"5001",
    "sg:province":"Aargau",
    "wof:name":"Ass Milchkannen Und Seriebeh\u00e4lter Wildeisen H. U.",
    "wof:placetype":"venue"
},
  "geometry": {"coordinates":[8.0395374298,47.3855018616],"type":"Point"}
}