{
  "type": "Feature",
  "properties": {
    "iso:country":"CH",
    "sg:address":"6632",
    "sg:city":"Vogorno",
    "sg:orig_category":"RESTAURANTS: TEA-ROOMS",
    "sg:postcode":"6632",
    "sg:province":"Ticino",
    "wof:name":"Marcionetti Fabrizio",
    "wof:placetype":"venue"
},
  "geometry": {"coordinates":[8.8566789627,46.2235717773],"type":"Point"}
}