{
  "type": "Feature",
  "properties": {
    "iso:country":"CH",
    "sg:address":"Bahnhofstrasse 21",
    "sg:city":"B\u00fclach",
    "sg:orig_category":"Zahnarztpraxen",
    "sg:phone":"+41 71 245 38 35",
    "sg:postcode":"8180",
    "sg:province":"Z\u00fcrich",
    "wof:name":"Dr. Med. Dent. W. Birchmeier Zahnarzt",
    "wof:placetype":"venue"
},
  "geometry": {"coordinates":[8.5393600464,47.5209617615],"type":"Point"}
}