{
  "type": "Feature",
  "properties": {
    "iso:country":"CH",
    "sg:address":"Sedelstrasse 19",
    "sg:city":"Emmenbr\u00fccke",
    "sg:orig_category":"Grosshandel mit Baumaschinen Herstellung von Bergwerks U Baumaschinen",
    "sg:phone":"+41 41 261 05 04",
    "sg:postcode":"6020",
    "sg:province":"Luzern",
    "wof:name":"K\u00fcchler Ankertechnik Gmbh",
    "wof:placetype":"venue"
},
  "geometry": {"coordinates":[8.2882032394,47.0703430176],"type":"Point"}
}