{
  "type": "Feature",
  "properties": {
    "iso:country":"CH",
    "sg:address":"Dorf",
    "sg:city":"Heitenried",
    "sg:orig_category":"Organisationen des Gesundheitswesen",
    "sg:phone":"+41 26 495 14 61",
    "sg:postcode":"1714",
    "sg:province":"Fribourg",
    "wof:name":"Samariterverein Heitenried",
    "wof:placetype":"venue"
},
  "geometry": {"coordinates":[7.2986240387,46.8276405334],"type":"Point"}
}