{
  "type": "Feature",
  "properties": {
    "iso:country":"CH",
    "sg:address":"Felseggstrasse 24",
    "sg:city":"Henau",
    "sg:classifiers":[
        {
            "category":"Restaurant",
            "type":"Food & Drink"
        }
    ],
    "sg:phone":"+41 31 879 02 49",
    "sg:postcode":"9247",
    "sg:province":"St. Gallen",
    "wof:name":"Restaurant Hirschen",
    "wof:placetype":"venue"
},
  "geometry": {"coordinates":[7.3934698105,47.0661201477],"type":"Point"}
}