{
  "type": "Feature",
  "properties": {
    "iso:country":"CH",
    "sg:address":"Plattenweg 48",
    "sg:city":"Schaffhausen",
    "sg:orig_category":"Verwaltung von Immobilien Wirtschaftspr\u00fcfung, Steuerberatung U Treuhand",
    "sg:phone":"+41 31 352 83 33",
    "sg:postcode":"8200",
    "sg:province":"Schaffhausen",
    "wof:name":"Treuhand Und Verwaltungs Ag Bern",
    "wof:placetype":"venue"
},
  "geometry": {"coordinates":[7.4548950195,46.9415130615],"type":"Point"}
}