{
  "type": "Feature",
  "properties": {
    "iso:country":"CH",
    "sg:address":"Hegibergstrasse 65",
    "sg:city":"Trimbach",
    "sg:orig_category":"Aktivit\u00e4ten der Krankenschwestern U Hebammen, Hauspflege",
    "sg:phone":"+41 14911807",
    "sg:postcode":"4632",
    "sg:province":"Solothurn",
    "wof:name":"Spitex Uitikon Waldegg",
    "wof:placetype":"venue"
},
  "geometry": {"coordinates":[8.455465,47.369717],"type":"Point"}
}