{
  "type": "Feature",
  "properties": {
    "iso:country":"CH",
    "sg:address":"Obere Wallisellerstrasse 16",
    "sg:city":"Opfikon",
    "sg:orig_category":"Herstellung von Mess U Kontrollinstrumenten U vorrichtungen",
    "sg:phone":"+41 32 751 42 55",
    "sg:postcode":"8152",
    "sg:province":"Z\u00fcrich",
    "wof:name":"Enercom S\u00e0rl",
    "wof:placetype":"venue"
},
  "geometry": {"coordinates":[7.0664801598,47.0551681519],"type":"Point"}
}