{
  "type": "Feature",
  "properties": {
    "iso:country":"CH",
    "sg:address":"Frohburgstrasse 20a",
    "sg:city":"Z\u00fcrich",
    "sg:orig_category":"Unclassifiable Establishments",
    "sg:postcode":"8006",
    "sg:province":"Z\u00fcrich",
    "wof:name":"Safety Tech Ag",
    "wof:placetype":"venue"
},
  "geometry": {"coordinates":[8.5485877991,47.387008667],"type":"Point"}
}