{
  "type": "Feature",
  "properties": {
    "iso:country":"CH",
    "sg:address":"Chemin Vandelle 12 1290 Versoix Case Postale 427",
    "sg:city":"Versoix",
    "sg:orig_category":"Non-Classified Establishments",
    "sg:phone":"+41 22 755 62 14",
    "sg:postcode":"1290",
    "sg:province":"Gen\u00e8ve",
    "wof:name":"Arnaldo Carneiro Serrurerie",
    "wof:placetype":"venue"
},
  "geometry": {"coordinates":[6.1655797958,46.2811203003],"type":"Point"}
}