{
  "type": "Feature",
  "properties": {
    "iso:country":"CH",
    "sg:address":"Birrfeldstrasse 22",
    "sg:city":"M\u00fclligen",
    "sg:classifiers":[
        {
            "category":"Restaurant",
            "type":"Food & Drink"
        }
    ],
    "sg:phone":"+41 41 870 22 35",
    "sg:postcode":"5243",
    "sg:province":"Aargau",
    "wof:name":"Restaurant Waldheim",
    "wof:placetype":"venue"
},
  "geometry": {"coordinates":[8.6130313873,46.8810310364],"type":"Point"}
}