{
  "type": "Feature",
  "properties": {
    "iso:country":"CH",
    "sg:address":"Rue Du Nord 9",
    "sg:city":"Martigny",
    "sg:orig_category":"Arztpraxen",
    "sg:phone":"+41 27 722 85 00",
    "sg:postcode":"1920",
    "sg:province":"Valais",
    "wof:name":"Dr M\u00e9d. Paul-bernard Roduit M\u00e9decin Sp\u00e9cialiste Fmh",
    "wof:placetype":"venue"
},
  "geometry": {"coordinates":[7.074261,46.104195],"type":"Point"}
}