{
  "type": "Feature",
  "properties": {
    "iso:country":"CH",
    "sg:address":"1845",
    "sg:city":"Noville",
    "sg:orig_category":"Landw. Genossenschaften Viehzucht",
    "sg:postcode":"1845",
    "sg:province":"Vaud",
    "wof:name":"Syndicat D'\u00e9levage Bovin De La Plaine Du Rh\u00f4ne",
    "wof:placetype":"venue"
},
  "geometry": {"coordinates":[6.8991661072,46.381565094],"type":"Point"}
}