{
  "type": "Feature",
  "properties": {
    "iso:country":"CH",
    "sg:address":"Weekendweg 21",
    "sg:city":"Einigen",
    "sg:orig_category":"Detailhandel mit elektrischen Haushalts, Radio U Fernsehger\u00e4ten ohne ausgepr\u00e4gten Schwerpunkt",
    "sg:phone":"+41 33 654 67 75",
    "sg:postcode":"3646",
    "sg:province":"Bern",
    "wof:name":"Fritz Sch\u00e4r Elektroapparate",
    "wof:placetype":"venue"
},
  "geometry": {"coordinates":[7.6424841881,46.7116622925],"type":"Point"}
}