{
  "type": "Feature",
  "properties": {
    "iso:country":"CH",
    "sg:address":"Piazza Nosetto 4",
    "sg:city":"Bellinzona",
    "sg:orig_category":"Arztpraxen",
    "sg:phone":"+41 91 826 31 44",
    "sg:postcode":"6500",
    "sg:province":"Ticino",
    "wof:name":"Dott.med.ernesto Frick Specialista Fmh",
    "wof:placetype":"venue"
},
  "geometry": {"coordinates":[9.022673,46.191013],"type":"Point"}
}