{
  "type": "Feature",
  "properties": {
    "iso:country":"CH",
    "sg:address":"Avenue De Chailly 34 1000 Lausanne. Postfach",
    "sg:city":"Lausanne",
    "sg:orig_category":"W\u00e4scherei U chemische Reinigung",
    "sg:postcode":"1002",
    "sg:province":"Vaud",
    "wof:name":"Vit-a-sec, Martins Ribeiro",
    "wof:placetype":"venue"
},
  "geometry": {"coordinates":[6.6536870003,46.5240936279],"type":"Point"}
}