{
  "type": "Feature",
  "properties": {
    "iso:country":"CH",
    "sg:address":"Rue Des Terreaux 2 1000 Lausanne. Postfach",
    "sg:city":"Lausanne",
    "sg:orig_category":"Fernmeldedienste",
    "sg:postcode":"1003",
    "sg:province":"Vaud",
    "wof:name":"Cartel S.a",
    "wof:placetype":"venue"
},
  "geometry": {"coordinates":[6.6287631989,46.522518158],"type":"Point"}
}