{
  "type": "Feature",
  "properties": {
    "iso:country":"CH",
    "sg:address":"Fischeracherstrasse 80",
    "sg:city":"Lindau",
    "sg:orig_category":"Vorschulen, Kinderg\u00e4rten",
    "sg:phone":"+41 52 345 19 01",
    "sg:postcode":"8315",
    "sg:province":"Z\u00fcrich",
    "wof:name":"Kindergarten Brunnacher",
    "wof:placetype":"venue"
},
  "geometry": {"coordinates":[8.6749343872,47.4421234131],"type":"Point"}
}