{
  "type": "Feature",
  "properties": {
    "iso:country":"CH",
    "sg:address":"Olivier Rue Juste 5 Bis",
    "sg:city":"Nyon",
    "sg:orig_category":"Sonstiger Grosshandel",
    "sg:phone":"+41 22 362 61 73",
    "sg:postcode":"1260",
    "sg:province":"Vaud",
    "wof:name":"Intent Sa",
    "wof:placetype":"venue"
},
  "geometry": {"coordinates":[6.2367501259,46.3836364746],"type":"Point"}
}