{
  "type": "Feature",
  "properties": {
    "iso:country":"CH",
    "sg:address":"Feldstrasse 1",
    "sg:city":"Dietikon",
    "sg:orig_category":"Maler U Glasergewerbe",
    "sg:phone":"+41 17410275",
    "sg:postcode":"8953",
    "sg:province":"Z\u00fcrich",
    "wof:name":"La Rocca W. + Urban G., Malergesch\u00e4ft",
    "wof:placetype":"venue"
},
  "geometry": {"coordinates":[8.3970384598,47.4065093994],"type":"Point"}
}