{
  "type": "Feature",
  "properties": {
    "iso:country":"CH",
    "sg:address":"Aeby Rue Pierre - 12",
    "sg:city":"Fribourg",
    "sg:orig_category":"Sonstige pers\u00f6nliche Dienstleistungen",
    "sg:phone":"+41 26 426 74 72",
    "sg:postcode":"1700",
    "sg:province":"Fribourg",
    "wof:name":"De Muralt Bernard - Courtoisie Et Savoir-vivre",
    "wof:placetype":"venue"
},
  "geometry": {"coordinates":[7.1593790054,46.8078117371],"type":"Point"}
}