{
  "type": "Feature",
  "properties": {
    "iso:country":"CH",
    "sg:address":"B\u00fcelstrasse 54",
    "sg:city":"Dinhard",
    "sg:orig_category":"Grosshandel mit B\u00fcrom\u00f6beln",
    "sg:phone":"+41 52 336 18 44",
    "sg:postcode":"8474",
    "sg:province":"Z\u00fcrich",
    "wof:name":"Hp-norm Ag Lager-& Betriebseinrichtungen",
    "wof:placetype":"venue"
},
  "geometry": {"coordinates":[8.7679815292,47.558052063],"type":"Point"}
}