{
  "type": "Feature",
  "properties": {
    "iso:country":"CH",
    "sg:address":"Rebhalde 16",
    "sg:city":"Baar",
    "sg:orig_category":"Vermietung U Verpachtung von eigenen Immobilien",
    "sg:postcode":"6340",
    "sg:province":"Zug",
    "wof:name":"Dugla Bau + Immobilien Ag",
    "wof:placetype":"venue"
},
  "geometry": {"coordinates":[8.5202960968,47.2052307129],"type":"Point"}
}