{
  "type": "Feature",
  "properties": {
    "iso:country":"CH",
    "sg:address":"4714",
    "sg:city":"Aedermannsdorf",
    "sg:orig_category":"Landw. Genossenschaften Viehzucht",
    "sg:postcode":"4714",
    "sg:province":"Solothurn",
    "wof:name":"Viehzuchtgenossenschaft",
    "wof:placetype":"venue"
},
  "geometry": {"coordinates":[7.6105318069,47.3044586182],"type":"Point"}
}