{
  "type": "Feature",
  "properties": {
    "addr:full":"Kriesbachstrasse 3 8304 Wallisellen. Postfach Wallisellen Z\u00fcrich 8304",
    "addr:housenumber":"3",
    "addr:postcode":"8304;8304",
    "addr:street":"Kriesbachstrasse",
    "iso:country":"CH",
    "sg:address":"Kriesbachstrasse 3 8304 Wallisellen. Postfach",
    "sg:city":"Wallisellen",
    "sg:orig_category":"Autogaragen",
    "sg:phone":"+41 79 240 67 37",
    "sg:postcode":"8304",
    "sg:province":"Z\u00fcrich",
    "wof:name":"Arco Garage",
    "wof:placetype":"venue"
},
  "geometry": {"coordinates":[6.47224,46.615742],"type":"Point"}
}