{
  "type": "Feature",
  "properties": {
    "iso:country":"CH",
    "sg:address":"Passwangstr. 6.",
    "sg:city":"Erschwil",
    "sg:orig_category":"Allgemeiner Hoch U Tiefbau",
    "sg:phone":"+41 31 312 58 18",
    "sg:postcode":"4228",
    "sg:province":"Solothurn",
    "wof:name":"Neutron Gmbh Liegenschaftsrenovationen, Bes. Architekturdienstleistungen, Bauarbeiten Usw",
    "wof:placetype":"venue"
},
  "geometry": {"coordinates":[7.454227,46.946445],"type":"Point"}
}