{
  "type": "Feature",
  "properties": {
    "iso:country":"CH",
    "sg:address":"Mellingerstrasse 6",
    "sg:city":"Baden",
    "sg:orig_category":"Vermietung U Verpachtung von eigenen Immobilien Vermittlung von Immobilien",
    "sg:phone":"+41 71 891 46 66",
    "sg:postcode":"5400",
    "sg:province":"Aargau",
    "wof:name":"Flurhof-immobilien Ag",
    "wof:placetype":"venue"
},
  "geometry": {"coordinates":[9.5031204224,47.4540405273],"type":"Point"}
}