{
  "type": "Feature",
  "properties": {
    "iso:country":"CH",
    "sg:address":"Steinrain 10",
    "sg:city":"B\u00e4ttwil-fl\u00fch",
    "sg:orig_category":"Sportvereine Ballsport Badminton",
    "sg:phone":"+41 61 731 29 31",
    "sg:postcode":"4112",
    "sg:province":"Solothurn",
    "wof:name":"Badminton-club Laubfrosch",
    "wof:placetype":"venue"
},
  "geometry": {"coordinates":[7.4978308678,47.488067627],"type":"Point"}
}