{
  "type": "Feature",
  "properties": {
    "iso:country":"CH",
    "sg:address":"Industriestrasse 23",
    "sg:city":"W\u00fcrenlingen",
    "sg:orig_category":"Baugewerbe Innenausbau",
    "sg:phone":"+41 55 282 27 48",
    "sg:postcode":"5303",
    "sg:province":"Aargau",
    "wof:name":"Hanspeter Blaser Innenausbau & Montagen",
    "wof:placetype":"venue"
},
  "geometry": {"coordinates":[8.925942,47.240643],"type":"Point"}
}