{
  "type": "Feature",
  "properties": {
    "iso:country":"CH",
    "sg:address":"C. F. L. Lohnerstrasse 24",
    "sg:city":"Gwatt",
    "sg:classifiers":[
        {
            "category":"Professional",
            "subcategory":"Computer Services",
            "type":"Services"
        }
    ],
    "sg:phone":"+41 33 334 23 70",
    "sg:postcode":"3645",
    "sg:province":"Bern",
    "sg:tags":[
        "administration",
        "software"
    ],
    "wof:name":"Nexplore Ag",
    "wof:placetype":"venue"
},
  "geometry": {"coordinates":[7.618745,46.73233],"type":"Point"}
}