{
  "type": "Feature",
  "properties": {
    "iso:country":"CH",
    "sg:address":"Alte Steinhauserstrasse 1",
    "sg:city":"Cham",
    "sg:orig_category":"Wirtschaftspr\u00fcfung, Steuerberatung U Treuhand",
    "sg:phone":"+41 41 748 62 68",
    "sg:postcode":"6330",
    "sg:province":"Zug",
    "wof:name":"Computreu Ag",
    "wof:placetype":"venue"
},
  "geometry": {"coordinates":[8.4739131927,47.1866035461],"type":"Point"}
}