{
  "type": "Feature",
  "properties": {
    "iso:country":"CH",
    "sg:address":"Gesellschaftsstrasse 34",
    "sg:city":"Bern",
    "sg:orig_category":"Chiropraktik",
    "sg:phone":"+41 31 302 61 44",
    "sg:postcode":"3012",
    "sg:province":"Bern",
    "wof:name":"Dr.roberto Salvisberg Chiropraktor",
    "wof:placetype":"venue"
},
  "geometry": {"coordinates":[7.43447,46.953957],"type":"Point"}
}