{
  "type": "Feature",
  "properties": {
    "addr:full":"Heinerich Wirri-strasse 3 5000 Aarau. Postfach Aarau Aargau 5001",
    "addr:housenumber":"3",
    "addr:postcode":"5000 aarau. postfach;5001",
    "addr:street":"Heinerich Wirri-Strasse",
    "iso:country":"CH",
    "sg:address":"Heinerich Wirri-strasse 3 5000 Aarau. Postfach",
    "sg:city":"Aarau",
    "sg:orig_category":"Alters U Hinterlassenenversicherung AHV, Invalidenversicherung IV, Arbeitslosenversicherung ALV",
    "sg:phone":"+41 62 837 71 71",
    "sg:postcode":"5001",
    "sg:province":"Aargau",
    "wof:name":"Ausgleichskasse Gastrosuisse",
    "wof:placetype":"venue"
},
  "geometry": {"coordinates":[8.051295,47.38348],"type":"Point"}
}