{
  "type": "Feature",
  "properties": {
    "addr:full":"Mellingerstrasse 1 Baden Aargau 5400",
    "addr:housenumber":"1",
    "addr:postcode":"5400",
    "addr:street":"Mellingerstrasse",
    "iso:country":"CH",
    "sg:address":"Mellingerstrasse 1",
    "sg:city":"Baden",
    "sg:orig_category":"Arztpraxen",
    "sg:phone":"+41 71 222 20 10",
    "sg:postcode":"5400",
    "sg:province":"Aargau",
    "wof:name":"Dr.med.christian Mullis Arzt F.allgemeine Medizin Fmh",
    "wof:placetype":"venue"
},
  "geometry": {"coordinates":[9.383299,47.426441],"type":"Point"}
}