{
  "type": "Feature",
  "properties": {
    "iso:country":"CH",
    "sg:address":"Baarerstrasse 19",
    "sg:city":"Zug",
    "sg:orig_category":"Herstellung von Werkzeugen",
    "sg:phone":"+41 91 683 55 37",
    "sg:postcode":"6300",
    "sg:province":"Zug",
    "wof:name":"Regine Switzerland Sa",
    "wof:placetype":"venue"
},
  "geometry": {"coordinates":[9.0151357651,45.8474807739],"type":"Point"}
}