{
  "type": "Feature",
  "properties": {
    "iso:country":"CH",
    "sg:address":"Mettlenstrasse 20a",
    "sg:city":"Uzwil",
    "sg:orig_category":"Architektur U Ingenieurb\u00fcros",
    "sg:phone":"+41 71 951 45 45",
    "sg:postcode":"9240",
    "sg:province":"St. Gallen",
    "wof:name":"Ds Architektur Ag",
    "wof:placetype":"venue"
},
  "geometry": {"coordinates":[9.132955,47.437145],"type":"Point"}
}