{
  "type": "Feature",
  "properties": {
    "addr:full":"Bahnhofstrasse 21 Frauenfeld Thurgau 8500",
    "addr:housenumber":"21",
    "addr:postcode":"8500",
    "addr:street":"Bahnhofstrasse",
    "iso:country":"CH",
    "sg:address":"Bahnhofstrasse 21",
    "sg:city":"Frauenfeld",
    "sg:orig_category":"Datenverarbeitungsdienste Institutionen f\u00fcr Finanzierungsleasing",
    "sg:phone":"+41 22 301 12 13",
    "sg:postcode":"8500",
    "sg:province":"Thurgau",
    "wof:name":"Phg Philippe Girardclos Leasing & Informatique",
    "wof:placetype":"venue"
},
  "geometry": {"coordinates":[6.143475,46.185608],"type":"Point"}
}