{
  "type": "Feature",
  "properties": {
    "iso:country":"CH",
    "sg:address":"Hauptstrasse 2",
    "sg:city":"Gempenach",
    "sg:orig_category":"Detailhandel mit Fahrr\u00e4dern Handel mit Motorr\u00e4dern, Teilen U Zubeh\u00f6r Instandhaltung U Reparatur von ",
    "sg:phone":"+41 79 316 77 31",
    "sg:postcode":"3215",
    "sg:province":"Fribourg",
    "wof:name":"Christian Thomi Velos-mofas",
    "wof:placetype":"venue"
},
  "geometry": {"coordinates":[7.2009868622,46.940952301],"type":"Point"}
}