{
  "type": "Feature",
  "properties": {
    "iso:country":"CH",
    "sg:address":"9565",
    "sg:city":"Oberbussnang",
    "sg:orig_category":"Herstellung von Metallkonstruktionen Schmieden",
    "sg:phone":"+41 71 622 55 36",
    "sg:postcode":"9565",
    "sg:province":"Thurgau",
    "wof:name":"Thomas Herzog Schmiede & Metallbau",
    "wof:placetype":"venue"
},
  "geometry": {"coordinates":[9.0902996063,47.5488204956],"type":"Point"}
}