{
  "type": "Feature",
  "properties": {
    "iso:country":"CH",
    "sg:address":"Junkerbifangstrasse 2",
    "sg:city":"Zofingen",
    "sg:orig_category":"Sportvereine Ballsport Basketball",
    "sg:phone":"+41 62 751 57 60",
    "sg:postcode":"4800",
    "sg:province":"Aargau",
    "wof:name":"Bc Zofingen",
    "wof:placetype":"venue"
},
  "geometry": {"coordinates":[7.9456119537,47.2847328186],"type":"Point"}
}