{
  "type": "Feature",
  "properties": {
    "iso:country":"CH",
    "sg:address":"Bahnhofstrasse 17",
    "sg:city":"Zug",
    "sg:orig_category":"Rechtsberatung",
    "sg:phone":"+41 41 727 99 22",
    "sg:postcode":"6300",
    "sg:province":"Zug",
    "wof:name":"Egger & Rutz Anlagen Ag",
    "wof:placetype":"venue"
},
  "geometry": {"coordinates":[8.5156183243,47.1694488525],"type":"Point"}
}