{
  "type": "Feature",
  "properties": {
    "iso:country":"CH",
    "sg:address":"Dorfstrasse 44",
    "sg:city":"Bolligen",
    "sg:orig_category":"Fachdetailhandel in Verkaufsr\u00e4umen",
    "sg:phone":"+41 79 607 15 14",
    "sg:postcode":"3065",
    "sg:province":"Bern",
    "wof:name":"Element X Gmbh",
    "wof:placetype":"venue"
},
  "geometry": {"coordinates":[7.4991230965,46.9840087891],"type":"Point"}
}