{
  "type": "Feature",
  "properties": {
    "iso:country":"CH",
    "sg:address":"Chemin De Bellevue 5",
    "sg:city":"Morges",
    "sg:orig_category":"Sportvereine Turnen Vereine Damen",
    "sg:phone":"+41 22 329 44 30",
    "sg:postcode":"1110",
    "sg:province":"Vaud",
    "wof:name":"St\u00e9 De Gymnastique Gpe Dames",
    "wof:placetype":"venue"
},
  "geometry": {"coordinates":[6.4957818985,46.5169372559],"type":"Point"}
}