{
  "type": "Feature",
  "properties": {
    "iso:country":"CH",
    "sg:address":"Kirchbergstrasse 147",
    "sg:city":"Burgdorf",
    "sg:orig_category":"Jugendorganisationen",
    "sg:phone":"+41 34 422 11 03",
    "sg:postcode":"3400",
    "sg:province":"Bern",
    "wof:name":"Kadettenkorps Burgdorf",
    "wof:placetype":"venue"
},
  "geometry": {"coordinates":[7.6088252068,47.0653991699],"type":"Point"}
}