{
  "type": "Feature",
  "properties": {
    "iso:country":"CH",
    "sg:address":"Ruelle Du Lapin-vert 2",
    "sg:city":"Lausanne",
    "sg:classifiers":[
        {
            "category":"Restaurant",
            "type":"Food & Drink"
        }
    ],
    "sg:phone":"+41 21 312 13 17",
    "sg:postcode":"1005",
    "sg:province":"Vaud",
    "wof:name":"Caf\u00e9 Le Lapin Vert",
    "wof:placetype":"venue"
},
  "geometry": {"coordinates":[6.6360387802,46.5235595703],"type":"Point"}
}