{
  "type": "Feature",
  "properties": {
    "iso:country":"CH",
    "sg:address":"Ch\u00f6renmattstrasse 2",
    "sg:city":"Berikon",
    "sg:classifiers":[
        {
            "category":"Bars & Pubs",
            "subcategory":"Gay Bar",
            "type":"Food & Drink"
        }
    ],
    "sg:phone":"+41 56 648 41 21",
    "sg:postcode":"8965",
    "sg:province":"Aargau",
    "sg:tags":[
        "tub",
        "accessory",
        "bath"
    ],
    "wof:name":"Kleine Wolke Ag",
    "wof:placetype":"venue"
},
  "geometry": {"coordinates":[8.367285,47.360977],"type":"Point"}
}