{
  "type": "Feature",
  "properties": {
    "iso:country":"CH",
    "sg:address":"Hauptstrasse 101",
    "sg:city":"Sissach",
    "sg:orig_category":"Gymnastikschulen",
    "sg:phone":"+41 79 686 21 41",
    "sg:postcode":"4450",
    "sg:province":"Basel-Landschaft",
    "wof:name":"Gymnastikstudio Sissach Frau Heidy Gass Epple",
    "wof:placetype":"venue"
},
  "geometry": {"coordinates":[7.8088121414,47.4646377563],"type":"Point"}
}