{
  "type": "Feature",
  "properties": {
    "iso:country":"CH",
    "sg:address":"2887",
    "sg:city":"Soubey",
    "sg:orig_category":"Verwertung von Milch",
    "sg:postcode":"2887",
    "sg:province":"Jura",
    "wof:name":"Soci\u00e9t\u00e9 De Laiterie De Souboz",
    "wof:placetype":"venue"
},
  "geometry": {"coordinates":[7.2430181503,47.2740287781],"type":"Point"}
}