{
  "type": "Feature",
  "properties": {
    "iso:country":"CH",
    "sg:address":"Rorschacher Strasse 152",
    "sg:city":"St.gallen",
    "sg:orig_category":"Detailhandel mit Waren verschiedener Art, Hauptrichtung Nahrungsmittel",
    "sg:phone":"+41 79 660 07 62",
    "sg:postcode":"9000",
    "sg:province":"St. Gallen",
    "wof:name":"Spar-markt B\u00f6hi",
    "wof:placetype":"venue"
},
  "geometry": {"coordinates":[9.0356063843,47.4511833191],"type":"Point"}
}