{
  "type": "Feature",
  "properties": {
    "iso:country":"CH",
    "sg:address":"P\u00e9rolles Boulevard De 7 1700 Fribourg. Postfach",
    "sg:city":"Freiburg",
    "sg:orig_category":"Unclassifiable Establishments",
    "sg:phone":"+41 26 475 33 44",
    "sg:postcode":"1700",
    "sg:province":"Fribourg",
    "wof:name":"Compagnie Des Casinos Holding Sa D\u00e9tention D'actions De St\u00e9s Anonyme Dont Le But Est L'exploitation De Casinos",
    "wof:placetype":"venue"
},
  "geometry": {"coordinates":[7.1536831856,46.8037452698],"type":"Point"}
}