{
  "type": "Feature",
  "properties": {
    "iso:country":"CH",
    "sg:address":"Bahnhofstrasse 44",
    "sg:city":"Zollikon",
    "sg:orig_category":"Softwareentwicklung U beratung",
    "sg:phone":"+41 13902232",
    "sg:postcode":"8702",
    "sg:province":"Z\u00fcrich",
    "wof:name":"Codenmore Ag",
    "wof:placetype":"venue"
},
  "geometry": {"coordinates":[8.572218895,47.3396377563],"type":"Point"}
}