{
  "type": "Feature",
  "properties": {
    "iso:country":"CH",
    "sg:address":"Gryphenh\u00fcbeliweg 6 3006 Bern. Postfach",
    "sg:city":"Bern",
    "sg:orig_category":"Non-Classified Establishments",
    "sg:postcode":"3005",
    "sg:province":"Bern",
    "wof:name":"Bkd Film Service Boris Kralj - Dasovic Film-vorproduktion, -produktion U -nachproduktion",
    "wof:placetype":"venue"
},
  "geometry": {"coordinates":[7.4573879242,46.9442634583],"type":"Point"}
}