{
  "type": "Feature",
  "properties": {
    "iso:country":"CH",
    "sg:address":"Neumarkt 28",
    "sg:city":"Z\u00fcrich",
    "sg:orig_category":"Non-Classified Establishments",
    "sg:phone":"+41 12624210",
    "sg:postcode":"8001",
    "sg:province":"Z\u00fcrich",
    "wof:name":"N28 Rodolfo Sacchi Sgd",
    "wof:placetype":"venue"
},
  "geometry": {"coordinates":[8.5466499329,47.3728523254],"type":"Point"}
}