{
  "type": "Feature",
  "properties": {
    "iso:country":"CH",
    "sg:address":"Spiegelbergweg 1",
    "sg:city":"Steinen",
    "sg:orig_category":"Herstellung von Teppichen Verlegen von Fliesen U Platten",
    "sg:phone":"+41 79 434 37 02",
    "sg:postcode":"6422",
    "sg:province":"Schwyz",
    "wof:name":"Donremo, Donauer M.",
    "wof:placetype":"venue"
},
  "geometry": {"coordinates":[8.6149930954,47.0503044128],"type":"Point"}
}