{
  "type": "Feature",
  "properties": {
    "iso:country":"CH",
    "sg:address":"Mattenweg 33",
    "sg:city":"Olten",
    "sg:orig_category":"Stukkateurgewerbe, Gipserei U Verputzerei",
    "sg:phone":"+41 62 296 53 15",
    "sg:postcode":"4600",
    "sg:province":"Solothurn",
    "wof:name":"Bruno Tedeschi Gipsergesch\u00e4ft",
    "wof:placetype":"venue"
},
  "geometry": {"coordinates":[7.9175510406,47.3487968445],"type":"Point"}
}