{
  "type": "Feature",
  "properties": {
    "iso:country":"CH",
    "sg:address":"Lucchini Via 2",
    "sg:city":"Lugano",
    "sg:orig_category":"Non-Classified Establishments",
    "sg:postcode":"6900",
    "sg:province":"Ticino",
    "wof:name":"Troller H. Ag",
    "wof:placetype":"venue"
},
  "geometry": {"coordinates":[8.1577129364,47.5602645874],"type":"Point"}
}