{
  "type": "Feature",
  "properties": {
    "iso:country":"CH",
    "sg:address":"Schloss 4",
    "sg:city":"Obermumpf",
    "sg:orig_category":"Jugendorganisationen",
    "sg:phone":"+41 62 873 19 15",
    "sg:postcode":"4324",
    "sg:province":"Aargau",
    "wof:name":"Jugendmusik Fischingertal",
    "wof:placetype":"venue"
},
  "geometry": {"coordinates":[7.932808876,47.5307312012],"type":"Point"}
}