{
  "type": "Feature",
  "properties": {
    "iso:country":"CH",
    "sg:address":"Lenzburgerstrasse 2 5702 Niederlenz. Postfach",
    "sg:city":"Niederlenz",
    "sg:orig_category":"Grosshandel mit Maschinen U Ausr\u00fcstungen Herstellung von sonstigen landwirtschaftlichen Maschinen",
    "sg:phone":"+41 41 930 12 04",
    "sg:postcode":"5702",
    "sg:province":"Aargau",
    "wof:name":"Schmid Forst Und Gartenger\u00e4te",
    "wof:placetype":"venue"
},
  "geometry": {"coordinates":[8.145737648,47.2250823975],"type":"Point"}
}