{
  "type": "Feature",
  "properties": {
    "iso:country":"CH",
    "sg:address":"D\u00e4ttlikonerstrasse 5",
    "sg:city":"Pfungen",
    "sg:orig_category":"Sonstige Verkehrsvermittlung",
    "sg:phone":"+41 52 304 09 09",
    "sg:postcode":"8422",
    "sg:province":"Z\u00fcrich",
    "wof:name":"Tes Tag-express-system Gmbh",
    "wof:placetype":"venue"
},
  "geometry": {"coordinates":[8.6380357742,47.5181159973],"type":"Point"}
}