{
  "type": "Feature",
  "properties": {
    "addr:full":"Pilatusstrasse 19 Luzern Luzern 6003",
    "addr:housenumber":"19",
    "addr:postcode":"6003",
    "addr:street":"Pilatusstrasse",
    "iso:country":"CH",
    "sg:address":"Pilatusstrasse 19",
    "sg:city":"Luzern",
    "sg:orig_category":"Architektur U Ingenieurb\u00fcros Architekturb\u00fcros",
    "sg:phone":"+41 41 210 50 53",
    "sg:postcode":"6003",
    "sg:province":"Luzern",
    "wof:name":"Schrepfer Monika",
    "wof:placetype":"venue"
},
  "geometry": {"coordinates":[8.306069,47.048615],"type":"Point"}
}