{
  "type": "Feature",
  "properties": {
    "addr:full":"Seestrasse 22 3700 Spiez. Postfach Spiez Bern 3700",
    "addr:housenumber":"22",
    "addr:postcode":"3700 spiez. postfach;3700",
    "addr:street":"Seestrasse",
    "iso:country":"CH",
    "sg:address":"Seestrasse 22 3700 Spiez. Postfach",
    "sg:city":"Spiez",
    "sg:orig_category":"Architektur U Ingenieurb\u00fcros Ingenieurb\u00fcros Geologie",
    "sg:phone":"+41 33 650 72 82",
    "sg:postcode":"3700",
    "sg:province":"Bern",
    "wof:name":"Geotechnisches Institut Ag Spezial-ingenieurdienstleistungen Usw.",
    "wof:placetype":"venue"
},
  "geometry": {"coordinates":[7.679833,46.687565],"type":"Point"}
}