{
  "type": "Feature",
  "properties": {
    "iso:country":"CH",
    "sg:address":"L\u00e4rchenweg 8",
    "sg:city":"Giswil",
    "sg:orig_category":"Handelsvermittlung U Grosshandel Sonstige Kurierdienste",
    "sg:phone":"+41 41 675 06 52",
    "sg:postcode":"6074",
    "sg:province":"Obwalden",
    "wof:name":"Othmar Krauer Krauer Express-kurier",
    "wof:placetype":"venue"
},
  "geometry": {"coordinates":[8.1885910034,46.8393135071],"type":"Point"}
}