{
  "type": "Feature",
  "properties": {
    "addr:full":"Dorfstrasse 44 Kefikon Thurgau 8546",
    "addr:housenumber":"44",
    "addr:postcode":"8546",
    "addr:street":"Dorfstrasse",
    "iso:country":"CH",
    "sg:address":"Dorfstrasse 44",
    "sg:city":"Kefikon",
    "sg:orig_category":"Autoreiseunternehmen",
    "sg:phone":"+41 76 335 31 91",
    "sg:postcode":"8546",
    "sg:province":"Thurgau",
    "wof:name":"Jakob Keller Thurtal-reisen",
    "wof:placetype":"venue"
},
  "geometry": {"coordinates":[8.832315,47.550762],"type":"Point"}
}