{
  "type": "Feature",
  "properties": {
    "iso:country":"CH",
    "sg:address":"Aarauerstrasse 8",
    "sg:city":"Oberg\u00f6sgen",
    "sg:classifiers":[
        {
            "category":"Restaurant",
            "type":"Food & Drink"
        }
    ],
    "sg:phone":"+41 14916170",
    "sg:postcode":"4653",
    "sg:province":"Solothurn",
    "wof:name":"Restaurant Frohsinn",
    "wof:placetype":"venue"
},
  "geometry": {"coordinates":[8.4524011612,47.3702392578],"type":"Point"}
}