{
  "type": "Feature",
  "properties": {
    "iso:country":"CH",
    "sg:address":"Seidenweg 56",
    "sg:city":"Bern",
    "sg:orig_category":"Wirtschaftspr\u00fcfung, Steuerberatung U Treuhand",
    "sg:phone":"+41 31 301 27 68",
    "sg:postcode":"3012",
    "sg:province":"Bern",
    "wof:name":"Beck-treuhand",
    "wof:placetype":"venue"
},
  "geometry": {"coordinates":[7.4329710007,46.9559783936],"type":"Point"}
}