{
  "type": "Feature",
  "properties": {
    "iso:country":"CH",
    "sg:address":"Schaugentobelstrasse 64 9037 Speicherschwendi. Postfach",
    "sg:city":"Speicherschwendi",
    "sg:orig_category":"Interessenvertretungen",
    "sg:postcode":"9037",
    "sg:province":"Appenzell Ausserrhoden",
    "wof:name":"Loppacher-stiftung Unterst\u00fctzung Wirtschaftlich Notleidender Personen, Bes. Kranker Personen Und/oder Deren Angeh\u00f6rige Usw",
    "wof:placetype":"venue"
},
  "geometry": {"coordinates":[9.4368848801,47.4252853394],"type":"Point"}
}