{
  "type": "Feature",
  "properties": {
    "iso:country":"CH",
    "sg:address":"Hauptstrasse 37",
    "sg:city":"Welschenrohr",
    "sg:orig_category":"Unclassifiable Establishments",
    "sg:postcode":"4716",
    "sg:province":"Solothurn",
    "wof:name":"Schwaller Verena, Primo-lebensmittel",
    "wof:placetype":"venue"
},
  "geometry": {"coordinates":[7.5295858383,47.2810058594],"type":"Point"}
}