{
  "type": "Feature",
  "properties": {
    "iso:country":"CH",
    "sg:address":"Lauterbachstrasse 19",
    "sg:city":"Oberburg",
    "sg:orig_category":"Mechanische Werkst\u00e4tten",
    "sg:phone":"+41 34 422 23 03",
    "sg:postcode":"3414",
    "sg:province":"Bern",
    "wof:name":"Kurt Schaffer Reparaturwerkstatt",
    "wof:placetype":"venue"
},
  "geometry": {"coordinates":[7.581193924,46.9897956848],"type":"Point"}
}