{
  "type": "Feature",
  "properties": {
    "iso:country":"CH",
    "sg:address":"Florentins Place Des 1",
    "sg:city":"Gen\u00e8ve",
    "sg:orig_category":"Unternehmensberatung",
    "sg:phone":"+41 71 744 22 66",
    "sg:postcode":"1204",
    "sg:province":"Gen\u00e8ve",
    "wof:name":"Wisba Consulting & Verwaltungs Ag, Triesen Fl, Zweigniederlassung St. Margrethen",
    "wof:placetype":"venue"
},
  "geometry": {"coordinates":[9.6346359253,47.4533653259],"type":"Point"}
}