{
  "type": "Feature",
  "properties": {
    "iso:country":"CH",
    "sg:address":"Bahnhofstrasse 12",
    "sg:city":"Wallisellen",
    "sg:orig_category":"Handels-H\u00e4user U Gesellschaften",
    "sg:postcode":"8304",
    "sg:province":"Z\u00fcrich",
    "wof:name":"Swisstrans Gmbh",
    "wof:placetype":"venue"
},
  "geometry": {"coordinates":[8.5896043777,47.4146652222],"type":"Point"}
}