{
  "type": "Feature",
  "properties": {
    "iso:country":"CH",
    "sg:address":"Dorfstrasse 4 8834 Schindellegi. Postfach",
    "sg:city":"Schindellegi",
    "sg:orig_category":"Maler U Glasergewerbe",
    "sg:postcode":"8834",
    "sg:province":"Schwyz",
    "wof:name":"Paul Suter Kundenmalerei/gipserarbeiten",
    "wof:placetype":"venue"
},
  "geometry": {"coordinates":[8.7117061615,47.1748886108],"type":"Point"}
}