{
  "type": "Feature",
  "properties": {
    "iso:country":"CH",
    "sg:address":"Avenue De France 82",
    "sg:city":"Sion",
    "sg:orig_category":"Zahntechnische Laboratorien",
    "sg:phone":"+41 27 322 58 58",
    "sg:postcode":"1950",
    "sg:province":"Valais",
    "wof:name":"Jean-michel Debons Laboratoire Dentaire",
    "wof:placetype":"venue"
},
  "geometry": {"coordinates":[7.3463001251,46.2285118103],"type":"Point"}
}