{
  "type": "Feature",
  "properties": {
    "iso:country":"CH",
    "sg:address":"1613",
    "sg:city":"Maracon",
    "sg:orig_category":"Herstellung von Armaturen Herstellung von Metallerzeugnissen ohne Maschinenbau",
    "sg:phone":"+41 79 449 58 37",
    "sg:postcode":"1613",
    "sg:province":"Vaud",
    "wof:name":"Htm Hydrotechnique Maracon Sa",
    "wof:placetype":"venue"
},
  "geometry": {"coordinates":[6.8825302124,46.556060791],"type":"Point"}
}