{
  "type": "Feature",
  "properties": {
    "iso:country":"CH",
    "sg:address":"Ringgenmatt 3150 Schwarzenburg. Postfach 68",
    "sg:city":"Schwarzenburg",
    "sg:orig_category":"Wasserversorgung",
    "sg:phone":"+41 31 731 15 08",
    "sg:postcode":"3150",
    "sg:province":"Bern",
    "wof:name":"Wasserversorgung Wahlern",
    "wof:placetype":"venue"
},
  "geometry": {"coordinates":[7.3486652374,46.8226165771],"type":"Point"}
}