{
  "type": "Feature",
  "properties": {
    "iso:country":"CH",
    "sg:address":"L\u00f6rracherstrasse 50 4125 Riehen. Postfach",
    "sg:city":"Riehen",
    "sg:orig_category":"Maschinen-Fabrikation",
    "sg:postcode":"4125",
    "sg:province":"Basel-Stadt",
    "wof:name":"Estag Engineering Ltd",
    "wof:placetype":"venue"
},
  "geometry": {"coordinates":[8.8199644089,47.2292785645],"type":"Point"}
}