{
  "type": "Feature",
  "properties": {
    "iso:country":"CH",
    "sg:address":"Kantonsstrasse",
    "sg:city":"Reichenburg",
    "sg:orig_category":"R\u00fcckgewinnung U Vorbereitung f\u00fcr die Wiederverwertung Recycling von Schrott",
    "sg:postcode":"8864",
    "sg:province":"Schwyz",
    "wof:name":"Autohalle J\u00e4ggin Roggwil Gmbh",
    "wof:placetype":"venue"
},
  "geometry": {"coordinates":[7.8207712173,47.2484741211],"type":"Point"}
}