{
  "type": "Feature",
  "properties": {
    "iso:country":"CH",
    "sg:address":"Einsiedlerstrasse 25 8820 W\u00e4denswil. Postfach 696",
    "sg:city":"W\u00e4denswil",
    "sg:orig_category":"Vermittlung von Immobilien Verwaltung von Immobilien",
    "sg:phone":"+41 17800205",
    "sg:postcode":"8820",
    "sg:province":"Z\u00fcrich",
    "wof:name":"Tuwag Immobilien Ag",
    "wof:placetype":"venue"
},
  "geometry": {"coordinates":[8.6856184006,47.2205886841],"type":"Point"}
}