{
  "type": "Feature",
  "properties": {
    "iso:country":"CH",
    "sg:address":"Route De Vaulion",
    "sg:city":"Romainm\u00f4tier",
    "sg:orig_category":"Detailhandel mit Waren verschiedener Art, Hauptrichtung Nahrungsmittel Grosshandel mit Nahrungsmitte",
    "sg:phone":"+41 24 453 12 73",
    "sg:postcode":"1323",
    "sg:province":"Vaud",
    "wof:name":"Epicerie D'en-haut Marl\u00e8ne R\u00e9zenne",
    "wof:placetype":"venue"
},
  "geometry": {"coordinates":[6.4620318413,46.6940917969],"type":"Point"}
}