{
  "type": "Feature",
  "properties": {
    "addr:full":"Unterdorfstrasse 11 Menznau Luzern 6122",
    "addr:housenumber":"11",
    "addr:postcode":"6122",
    "addr:street":"Unterdorfstrasse",
    "iso:country":"CH",
    "sg:address":"Unterdorfstrasse 11",
    "sg:city":"Menznau",
    "sg:orig_category":"Arztpraxen",
    "sg:phone":"+41 41 493 10 10",
    "sg:postcode":"6122",
    "sg:province":"Luzern",
    "wof:name":"Dr.med.andr\u00e9 Terrier Arzt F.allgemeine Medizin Fmh",
    "wof:placetype":"venue"
},
  "geometry": {"coordinates":[8.039704,47.08551],"type":"Point"}
}