{
  "type": "Feature",
  "properties": {
    "iso:country":"CH",
    "sg:address":"Schulhausstrasse 315 4938 Rohrbach. Postfach 50",
    "sg:city":"Rohrbach",
    "sg:orig_category":"Sanit\u00e4r, Heizungs U L\u00fcftungsinstallation Sanit\u00e4rinstallation",
    "sg:phone":"+41 62 965 32 66",
    "sg:postcode":"4938",
    "sg:province":"Bern",
    "wof:name":"Fl\u00fcckiger Alfred",
    "wof:placetype":"venue"
},
  "geometry": {"coordinates":[7.8151741028,47.1363182068],"type":"Point"}
}