{
  "type": "Feature",
  "properties": {
    "addr:full":"8340 Hinwil Z\u00fcrich 8340",
    "addr:postcode":"8340;8340",
    "iso:country":"CH",
    "sg:address":"8340",
    "sg:city":"Hinwil",
    "sg:classifiers":[
        {
            "category":"Bars & Pubs",
            "type":"Food & Drink"
        }
    ],
    "sg:phone":"+41 19373222",
    "sg:postcode":"8340",
    "sg:province":"Z\u00fcrich",
    "sg:tags":[
        "restaurant"
    ],
    "wof:name":"Restaurant Bad Erlosen & B\u00e4dli-bar",
    "wof:placetype":"venue"
},
  "geometry": {"coordinates":[8.84481,47.303059],"type":"Point"}
}