{
  "type": "Feature",
  "properties": {
    "iso:country":"CH",
    "sg:address":"Rue Du Rh\u00f4ne 69",
    "sg:city":"Gen\u00e8ve",
    "sg:classifiers":[
        {
            "category":"Home & Garden",
            "subcategory":"Building Materials",
            "type":"Retail Goods"
        }
    ],
    "sg:phone":"+41 71 278 62 55",
    "sg:postcode":"1207",
    "sg:province":"Gen\u00e8ve",
    "sg:tags":[
        "aluminium",
        "window"
    ],
    "wof:name":"Schlosserei St\u00f6ckle Ag",
    "wof:placetype":"venue"
},
  "geometry": {"coordinates":[9.347623,47.422642],"type":"Point"}
}