{
  "type": "Feature",
  "properties": {
    "addr:full":"Eggb\u00fchlstrasse 36 8050 Z\u00fcrich. Postfach 8192 Z\u00fcrich Z\u00fcrich 8050",
    "addr:housenumber":"36",
    "addr:postcode":"8050 zuerich. postfach 8192;8050",
    "addr:street":"Eggbuehlstrasse",
    "iso:country":"CH",
    "sg:address":"Eggb\u00fchlstrasse 36 8050 Z\u00fcrich. Postfach 8192",
    "sg:city":"Z\u00fcrich",
    "sg:orig_category":"Bau von Strassen, Sportanlagen U Bahnverkehrsstrecken Strassenbau",
    "sg:phone":"+41 13021147",
    "sg:postcode":"8050",
    "sg:province":"Z\u00fcrich",
    "wof:name":"Cellere Ag Z\u00fcrich, Bauunternehmung",
    "wof:placetype":"venue"
},
  "geometry": {"coordinates":[8.542073,47.416756],"type":"Point"}
}