{
  "type": "Feature",
  "properties": {
    "iso:country":"CH",
    "sg:address":"Gellertstrasse 2a",
    "sg:city":"Basel",
    "sg:orig_category":"Zahnarztpraxen",
    "sg:phone":"+41 61 311 14 33",
    "sg:postcode":"4052",
    "sg:province":"Basel-Stadt",
    "wof:name":"Dr. Med. Dent. Paul Egloff Zahnarzt",
    "wof:placetype":"venue"
},
  "geometry": {"coordinates":[7.6053957939,47.5524101257],"type":"Point"}
}