{
  "type": "Feature",
  "properties": {
    "iso:country":"CH",
    "sg:address":"Balestra Via Serafino 18 6900 Lugano. Postfach",
    "sg:city":"Lugano",
    "sg:orig_category":"Handels-H\u00e4user U Gesellschaften",
    "sg:postcode":"6900",
    "sg:province":"Ticino",
    "wof:name":"Ssm International Sa Trading Di Materiali, Prodotti, Ed Apparecchiature Ecc",
    "wof:placetype":"venue"
},
  "geometry": {"coordinates":[8.957780838,46.0076789856],"type":"Point"}
}