{
  "type": "Feature",
  "properties": {
    "addr:full":"Avenue De Cour 6a Lausanne Vaud 1007",
    "addr:housenumber":"6a",
    "addr:postcode":"1007",
    "addr:street":"Avenue De Cour",
    "iso:country":"CH",
    "sg:address":"Avenue De Cour 6a",
    "sg:city":"Lausanne",
    "sg:orig_category":"Detailhandel mit Brot, Back U S\u00fcsswaren",
    "sg:phone":"+41 21 617 88 38",
    "sg:postcode":"1007",
    "sg:province":"Vaud",
    "wof:name":"Jos\u00e9 Ferreira Tea-room",
    "wof:placetype":"venue"
},
  "geometry": {"coordinates":[6.626258,46.51226],"type":"Point"}
}