{
  "type": "Feature",
  "properties": {
    "iso:country":"CH",
    "sg:address":"T\u00fcrlistock 953",
    "sg:city":"Ueberstorf",
    "sg:orig_category":"Handelsvermittlung U Grosshandel Herstellung von sonstigen Metallwaren",
    "sg:phone":"+41 31 741 32 37",
    "sg:postcode":"3182",
    "sg:province":"Fribourg",
    "wof:name":"H\u00f6fert Rolf Ag",
    "wof:placetype":"venue"
},
  "geometry": {"coordinates":[7.3240399361,46.8740997314],"type":"Point"}
}