{
  "type": "Feature",
  "properties": {
    "iso:country":"CH",
    "sg:address":"Ch\u00e2teau Grillet 1267 Vich. Postfach",
    "sg:city":"Gen\u00e8ve",
    "sg:orig_category":"Dienstleistungen von Beteiligungsgesellschaften",
    "sg:postcode":"1201",
    "sg:province":"Gen\u00e8ve",
    "wof:name":"Richemond H\u00e9ritage Sa",
    "wof:placetype":"venue"
},
  "geometry": {"coordinates":[6.2421088219,46.4333763123],"type":"Point"}
}