{
  "type": "Feature",
  "properties": {
    "iso:country":"CH",
    "sg:address":"Bodenacherweg 81",
    "sg:city":"Scheuren",
    "sg:orig_category":"Sportvereine Turnen Vereine Damen",
    "sg:phone":"+41 76 559 07 09",
    "sg:postcode":"2556",
    "sg:province":"Bern",
    "wof:name":"Damenriege Stv Wahlen",
    "wof:placetype":"venue"
},
  "geometry": {"coordinates":[7.5198078156,47.4016342163],"type":"Point"}
}