{
  "type": "Feature",
  "properties": {
    "iso:country":"CH",
    "sg:address":"Gatternweg 23",
    "sg:city":"Riehen",
    "sg:orig_category":"Sportvereine Sch\u00fctzen Pistolen-& Gewehr",
    "sg:phone":"+41 61 272 78 45",
    "sg:postcode":"4125",
    "sg:province":"Basel-Stadt",
    "wof:name":"Uov Basel-stadt Schiess-sektion",
    "wof:placetype":"venue"
},
  "geometry": {"coordinates":[7.6436719894,47.5808067322],"type":"Point"}
}