{
  "type": "Feature",
  "properties": {
    "iso:country":"CH",
    "sg:address":"Route De Pr\u00e9verenges 4",
    "sg:city":"Denges",
    "sg:orig_category":"Unclassifiable Establishments",
    "sg:postcode":"1026",
    "sg:province":"Vaud",
    "wof:name":"Swaptec, Cherbuin Et Cie",
    "wof:placetype":"venue"
},
  "geometry": {"coordinates":[6.5370059013,46.5252151489],"type":"Point"}
}