{
  "type": "Feature",
  "properties": {
    "addr:full":"Gewerbezone Bahnhof Nord 4a Wimmis Bern 3752",
    "addr:housenumber":"4a",
    "addr:postcode":"3752",
    "addr:street":"Gewerbezone Bahnhof Nord",
    "iso:country":"CH",
    "sg:address":"Gewerbezone Bahnhof Nord 4a",
    "sg:city":"Wimmis",
    "sg:orig_category":"Baugewerbe Herstellung von Konstruktionsteilen, Fertigbauteilen U Ausbauelementen aus Holz",
    "sg:phone":"+41 33 657 20 21",
    "sg:postcode":"3752",
    "sg:province":"Bern",
    "wof:name":"Andres W\u00e4lti Zaun-& Gartenhauscenter",
    "wof:placetype":"venue"
},
  "geometry": {"coordinates":[7.63496,46.674484],"type":"Point"}
}