{
  "type": "Feature",
  "properties": {
    "iso:country":"CH",
    "sg:address":"Erlenstrasse 36",
    "sg:city":"Emmenbr\u00fccke",
    "sg:orig_category":"Religi\u00f6se Vereinigungen",
    "sg:phone":"+41 41 340 94 98",
    "sg:postcode":"6020",
    "sg:province":"Luzern",
    "wof:name":"Verein Der Indochina-buddhisten In Der Schweiz",
    "wof:placetype":"venue"
},
  "geometry": {"coordinates":[8.2673053741,47.0771942139],"type":"Point"}
}