{
  "type": "Feature",
  "properties": {
    "iso:country":"CH",
    "sg:address":"Klybeckstrasse 64 4057 Basel. Postfach",
    "sg:city":"Basel",
    "sg:orig_category":"Datenbanken",
    "sg:postcode":"4051",
    "sg:province":"Basel-Stadt",
    "wof:name":"Labcom Fontanilles Medienwerkstatt, Bes. F. Kulturschaffende",
    "wof:placetype":"venue"
},
  "geometry": {"coordinates":[7.591292,47.565689],"type":"Point"}
}