{
  "type": "Feature",
  "properties": {
    "iso:country":"CH",
    "sg:address":"Gummen 2",
    "sg:city":"Orpund",
    "sg:orig_category":"Sanit\u00e4r U Heizungsinstallation Sanit\u00e4rinstallation",
    "sg:phone":"+41 32 355 18 25",
    "sg:postcode":"2552",
    "sg:province":"Bern",
    "wof:name":"Loevenich Engineering Ag Heizung Sanit\u00e4r Schwimmbad",
    "wof:placetype":"venue"
},
  "geometry": {"coordinates":[7.3006868362,47.1413116455],"type":"Point"}
}