{
  "type": "Feature",
  "properties": {
    "iso:country":"CH",
    "sg:address":"Stammlerb\u00fchlstr. 9",
    "sg:city":"Thayngen",
    "sg:orig_category":"G\u00fcterbef\u00f6rderung im Strassenverkehr",
    "sg:phone":"+41 52 645 32 22",
    "sg:postcode":"8240",
    "sg:province":"Schaffhausen",
    "wof:name":"Belfracht Gmbh",
    "wof:placetype":"venue"
},
  "geometry": {"coordinates":[8.7175617218,47.7413444519],"type":"Point"}
}