{
  "type": "Feature",
  "properties": {
    "iso:country":"CH",
    "sg:address":"Hofackerstrasse 30",
    "sg:city":"Nuglar",
    "sg:orig_category":"Allgemeiner Hochbau Stukkateurgewerbe, Gipserei U Verputzerei",
    "sg:phone":"+41 61 911 07 40",
    "sg:postcode":"4412",
    "sg:province":"Solothurn",
    "wof:name":"Frei Walter, Gipserei-fassadenbau",
    "wof:placetype":"venue"
},
  "geometry": {"coordinates":[7.688209,47.468472],"type":"Point"}
}