{
  "type": "Feature",
  "properties": {
    "iso:country":"CH",
    "sg:address":"Ch\u00e2tillon Route De 8",
    "sg:city":"Courrendlin",
    "sg:orig_category":"Gesundheitswesen",
    "sg:phone":"+41 32 435 50 10",
    "sg:postcode":"2830",
    "sg:province":"Jura",
    "wof:name":"Physio Sant\u00e9 S\u00e0rl",
    "wof:placetype":"venue"
},
  "geometry": {"coordinates":[7.3719158173,47.3387145996],"type":"Point"}
}