{
  "type": "Feature",
  "properties": {
    "iso:country":"CH",
    "sg:address":"Campagnora Via 19 6532 Castione. Postfach",
    "sg:city":"Castione",
    "sg:orig_category":"Interessenvertretungen",
    "sg:postcode":"6532",
    "sg:province":"Ticino",
    "wof:name":"Fondazione \u00abcampagnora\u00bb Della Banca Raiffeisen Di Castione",
    "wof:placetype":"venue"
},
  "geometry": {"coordinates":[9.0435819626,46.2270698547],"type":"Point"}
}