{
  "type": "Feature",
  "properties": {
    "iso:country":"CH",
    "sg:address":"Westerholz 5",
    "sg:city":"Biel/bienne",
    "sg:orig_category":"Herstellung von sonstigen Maschinen f\u00fcr unspezifische Verwendung Mechanische Werkst\u00e4tten",
    "sg:phone":"+41 32 341 29 19",
    "sg:postcode":"2504",
    "sg:province":"Bern",
    "wof:name":"Mollet Pr\u00e4zisionsmechanik Ag",
    "wof:placetype":"venue"
},
  "geometry": {"coordinates":[7.272028923,47.1505661011],"type":"Point"}
}