{
  "type": "Feature",
  "properties": {
    "iso:country":"CH",
    "sg:address":"Eichh\u00f6lzlistrasse 1",
    "sg:city":"Zwingen",
    "sg:orig_category":"Detailhandel mit Beleuchtungs U Haushaltsgegenst\u00e4nden Elektroinstallation",
    "sg:phone":"+41 79 333 56 34",
    "sg:postcode":"4222",
    "sg:province":"Basel-Landschaft",
    "wof:name":"Heinz Herzig Haushaltger\u00e4te",
    "wof:placetype":"venue"
},
  "geometry": {"coordinates":[7.530186,47.432667],"type":"Point"}
}