{
  "type": "Feature",
  "properties": {
    "iso:country":"CH",
    "sg:address":"Stationsstrasse 66a",
    "sg:city":"Wettswil",
    "sg:orig_category":"Sportvereine Ski",
    "sg:phone":"+41 17003129",
    "sg:postcode":"8907",
    "sg:province":"Z\u00fcrich",
    "wof:name":"Skiclub Z\u00fcrich Kathourg",
    "wof:placetype":"venue"
},
  "geometry": {"coordinates":[8.4738960266,47.330581665],"type":"Point"}
}