{
  "type": "Feature",
  "properties": {
    "iso:country":"CH",
    "sg:address":"Laubbachstrasse 7",
    "sg:city":"Altnau",
    "sg:classifiers":[
        {
            "category":"Insurance",
            "subcategory":"Insurance Agent",
            "type":"Services"
        }
    ],
    "sg:phone":"+41 71 695 13 15",
    "sg:postcode":"8595",
    "sg:province":"Thurgau",
    "sg:tags":[
        "versicherungsagenturen",
        "-broker"
    ],
    "wof:name":"Winterthur Versicherungen Agentur Paul Edelmann",
    "wof:placetype":"venue"
},
  "geometry": {"coordinates":[9.2583341599,47.6138534546],"type":"Point"}
}