{
  "type": "Feature",
  "properties": {
    "iso:country":"CH",
    "sg:address":"Bischofszellerstrasse 340",
    "sg:city":"Arnegg",
    "sg:orig_category":"Vermietung U Verpachtung von eigenen Immobilien",
    "sg:postcode":"9212",
    "sg:province":"St. Gallen",
    "wof:name":"Ilgenwiese Immobilien Ag",
    "wof:placetype":"venue"
},
  "geometry": {"coordinates":[9.255698204,47.4431381226],"type":"Point"}
}