{
  "type": "Feature",
  "properties": {
    "iso:country":"CH",
    "sg:address":"2827",
    "sg:city":"Mervelier",
    "sg:orig_category":"S\u00e4gewerke",
    "sg:phone":"+41 55 282 27 07",
    "sg:postcode":"2827",
    "sg:province":"Bern",
    "wof:name":"Gerhard Gebert S\u00e4gerei",
    "wof:placetype":"venue"
},
  "geometry": {"coordinates":[8.9155378342,47.2347297668],"type":"Point"}
}