{
  "type": "Feature",
  "properties": {
    "addr:full":"Bergstrasse 21 Zollikon Z\u00fcrich 8702",
    "addr:housenumber":"21",
    "addr:postcode":"8702",
    "addr:street":"Bergstrasse",
    "iso:country":"CH",
    "sg:address":"Bergstrasse 21",
    "sg:city":"Zollikon",
    "sg:orig_category":"Allgemeiner Hoch U Tiefbau",
    "sg:postcode":"8702",
    "sg:province":"Z\u00fcrich",
    "wof:name":"Baugemeinschaft M\u00e4henried Ag",
    "wof:placetype":"venue"
},
  "geometry": {"coordinates":[8.576638,47.341167],"type":"Point"}
}