{
  "type": "Feature",
  "properties": {
    "iso:country":"CH",
    "sg:address":"Fl\u00e9ch\u00e8re En",
    "sg:city":"Grens",
    "sg:orig_category":"Fotografisches Gewerbe U fotografische Laboratorien",
    "sg:phone":"+41 22 363 03 22",
    "sg:postcode":"1274",
    "sg:province":"Vaud",
    "wof:name":"Photo Signy, Higueras Victor",
    "wof:placetype":"venue"
},
  "geometry": {"coordinates":[6.1920938492,46.3949508667],"type":"Point"}
}