{
  "type": "Feature",
  "properties": {
    "iso:country":"CH",
    "sg:address":"Rue Des Cerisiers",
    "sg:city":"Payerne",
    "sg:orig_category":"Alters U Pflegeheime Institutionen f\u00fcr Behinderte",
    "sg:phone":"+41 21 866 02 33",
    "sg:postcode":"1530",
    "sg:province":"Vaud",
    "wof:name":"Etablissement M\u00e9dico-social Les Cyclades",
    "wof:placetype":"venue"
},
  "geometry": {"coordinates":[6.511807,46.656322],"type":"Point"}
}