{
  "type": "Feature",
  "properties": {
    "iso:country":"CH",
    "sg:address":"Moosbruggstrasse 1",
    "sg:city":"St.gallen",
    "sg:orig_category":"HOTELS: MIT RESTAURANT RESTAURANTS: NICHT EIGENST\u00c4NDIG",
    "sg:phone":"+41 71 228 82 83",
    "sg:postcode":"9000",
    "sg:province":"St. Gallen",
    "wof:name":"Hotel Des Artistes Am Spisertor",
    "wof:placetype":"venue"
},
  "geometry": {"coordinates":[9.3798389435,47.4241752625],"type":"Point"}
}