{
  "type": "Feature",
  "properties": {
    "iso:country":"CH",
    "sg:address":"Via Maggio 9",
    "sg:city":"Lugano",
    "sg:orig_category":"Arztpraxen",
    "sg:phone":"+41 91 972 15 73",
    "sg:postcode":"6900",
    "sg:province":"Ticino",
    "wof:name":"Dott.med. Luisa H\u00f6rler Specialista Fmh",
    "wof:placetype":"venue"
},
  "geometry": {"coordinates":[8.961989,46.008224],"type":"Point"}
}