{
  "type": "Feature",
  "properties": {
    "addr:full":"Moserstrasse 8 8200 Schaffhausen. Postfach Schaffhausen Schaffhausen 8202",
    "addr:housenumber":"8",
    "addr:postcode":"8200 schaffhausen. postfach;8202",
    "addr:street":"Moserstrasse",
    "iso:country":"CH",
    "sg:address":"Moserstrasse 8 8200 Schaffhausen. Postfach",
    "sg:city":"Schaffhausen",
    "sg:classifiers":[
        {
            "category":"Bars & Pubs",
            "type":"Food & Drink"
        }
    ],
    "sg:phone":"+41 52 624 71 21",
    "sg:postcode":"8202",
    "sg:province":"Schaffhausen",
    "sg:tags":[
        "restaurant"
    ],
    "wof:name":"Restaurant & Bar Metropol",
    "wof:placetype":"venue"
},
  "geometry": {"coordinates":[8.639817,47.6954],"type":"Point"}
}