{
  "type": "Feature",
  "properties": {
    "iso:country":"CH",
    "sg:address":"Holderboden 19",
    "sg:city":"Sool",
    "sg:orig_category":"Grosshandel mit Geschenkartikeln U Souvenirs Sonstiges Verlagsgewerbe",
    "sg:phone":"+41 55 654 10 71",
    "sg:postcode":"8762",
    "sg:province":"Glarus",
    "wof:name":"Uhlmann, Sigrun M.",
    "wof:placetype":"venue"
},
  "geometry": {"coordinates":[9.0833702087,46.9986877441],"type":"Point"}
}