{
  "type": "Feature",
  "properties": {
    "iso:country":"CH",
    "sg:address":"Schaffhauserstrasse 90",
    "sg:city":"Glattbrugg",
    "sg:orig_category":"Detailhandel mit Waren verschiedener Art, Hauptrichtung Nahrungsmittel Grosshandel mit Nahrungsmitte",
    "sg:phone":"+41 18106168",
    "sg:postcode":"8152",
    "sg:province":"Z\u00fcrich",
    "wof:name":"Keiser Leo, Gourmi",
    "wof:placetype":"venue"
},
  "geometry": {"coordinates":[8.5640392303,47.4322166443],"type":"Point"}
}