{
  "type": "Feature",
  "properties": {
    "iso:country":"CH",
    "sg:address":"Huben",
    "sg:city":"Grosswangen",
    "sg:orig_category":"Wasserversorgung",
    "sg:postcode":"6022",
    "sg:province":"Luzern",
    "wof:name":"Wasserversorgungsgenossenschaft Huben, Grosswangen (wgh)",
    "wof:placetype":"venue"
},
  "geometry": {"coordinates":[8.0459299088,47.1219787598],"type":"Point"}
}