{
  "type": "Feature",
  "properties": {
    "iso:country":"CH",
    "sg:address":"Nordstrasse 145",
    "sg:city":"Z\u00fcrich",
    "sg:orig_category":"Saunas, Solarien, Fitnesszentren U \u00e4hnliches",
    "sg:postcode":"8037",
    "sg:province":"Z\u00fcrich",
    "wof:name":"Hamburger & Thomi",
    "wof:placetype":"venue"
},
  "geometry": {"coordinates":[8.5331249237,47.3906478882],"type":"Point"}
}