{
  "type": "Feature",
  "properties": {
    "iso:country":"CH",
    "sg:address":"Rohrstrasse 19",
    "sg:city":"Glattbrugg",
    "sg:orig_category":"Herstellung von Pflanzenschutzmitteln U sonstigen agro- chemikalischen Erzeugnissen Sonstiges Reinig",
    "sg:phone":"+41 18116611",
    "sg:postcode":"8152",
    "sg:province":"Z\u00fcrich",
    "wof:name":"Spinn-ex Beat Riedweg",
    "wof:placetype":"venue"
},
  "geometry": {"coordinates":[8.5648822784,47.4350700378],"type":"Point"}
}