{
  "type": "Feature",
  "properties": {
    "iso:country":"CH",
    "sg:address":"Via Montalbano 2",
    "sg:city":"Gentilino",
    "sg:orig_category":"Grosshandel mit B\u00fcromaschinen Grosshandel mit Datenverarbeitungsger\u00e4ten",
    "sg:phone":"+41 91 994 66 47",
    "sg:postcode":"6925",
    "sg:province":"Ticino",
    "wof:name":"Simar Sa",
    "wof:placetype":"venue"
},
  "geometry": {"coordinates":[8.9366912842,45.9922904968],"type":"Point"}
}