{
  "type": "Feature",
  "properties": {
    "addr:full":"Leberngasse 7 Olten Solothurn 4600",
    "addr:housenumber":"7",
    "addr:postcode":"4600",
    "addr:street":"Leberngasse",
    "iso:country":"CH",
    "sg:address":"Leberngasse 7",
    "sg:city":"Olten",
    "sg:orig_category":"Architektur U Ingenieurb\u00fcros Architekturb\u00fcros",
    "sg:phone":"+41 62 291 14 18",
    "sg:postcode":"4600",
    "sg:province":"Solothurn",
    "wof:name":"Gr\u00fcnig Ernst Architekturb\u00fcro",
    "wof:placetype":"venue"
},
  "geometry": {"coordinates":[7.987445,47.35104],"type":"Point"}
}