{
  "type": "Feature",
  "properties": {
    "iso:country":"CH",
    "sg:address":"Cresciano",
    "sg:city":"Cresciano",
    "sg:classifiers":[
        {
            "category":"Banks & Credit Unions",
            "subcategory":"Bank",
            "type":"Services"
        }
    ],
    "sg:phone":"+41 91 850 59 59",
    "sg:postcode":"6705",
    "sg:province":"Ticino",
    "wof:name":"Banca Raiffeisen Cugnasco-gudo-riazzino",
    "wof:placetype":"venue"
},
  "geometry": {"coordinates":[8.91774,46.175251],"type":"Point"}
}