{
  "type": "Feature",
  "properties": {
    "iso:country":"CH",
    "sg:address":"Rue Du Simplon 39",
    "sg:city":"Vevey",
    "sg:orig_category":"Detailhandel mit Uhren U Schmuck Reparatur von Uhren U Schmuck",
    "sg:phone":"+41 21 921 77 11",
    "sg:postcode":"1800",
    "sg:province":"Vaud",
    "wof:name":"Orfeo Montres & Bijoux",
    "wof:placetype":"venue"
},
  "geometry": {"coordinates":[6.8438057899,46.4609107971],"type":"Point"}
}