{
  "type": "Feature",
  "properties": {
    "iso:country":"CH",
    "sg:address":"Sus Les Devens",
    "sg:city":"Lussy-sur-morges",
    "sg:orig_category":"Verm\u00f6gensverwaltung",
    "sg:phone":"+41 21 803 21 58",
    "sg:postcode":"1133",
    "wof:name":"Jan Sandberg Verm\u00f6gensverwaltung",
    "wof:placetype":"venue"
},
  "geometry": {"coordinates":[6.4414310455,46.5027732849],"type":"Point"}
}