{
  "type": "Feature",
  "properties": {
    "iso:country":"CH",
    "sg:address":"1145",
    "sg:city":"Bi\u00e8re",
    "sg:orig_category":"Schulpflegen",
    "sg:postcode":"1145",
    "sg:province":"Vaud",
    "wof:name":"Commission Scolaire De La Commune Des Verri\u00e8res",
    "wof:placetype":"venue"
},
  "geometry": {"coordinates":[6.4812221527,46.9043617249],"type":"Point"}
}