{
  "type": "Feature",
  "properties": {
    "addr:full":"H\u00f6henstrasse St\u00f6ck B\u00e4retswil Z\u00fcrich 8344",
    "addr:postcode":"8344",
    "addr:street":"Hoehenstrasse;Baeretswil Zuerich",
    "iso:country":"CH",
    "sg:address":"H\u00f6henstrasse St\u00f6ck",
    "sg:city":"B\u00e4retswil",
    "sg:orig_category":"Autospenglereien",
    "sg:phone":"+41 19391880",
    "sg:postcode":"8344",
    "sg:province":"Z\u00fcrich",
    "wof:name":"Hans Trachsler Autospenglerei",
    "wof:placetype":"venue"
},
  "geometry": {"coordinates":[8.856669,47.335869],"type":"Point"}
}