{
  "type": "Feature",
  "properties": {
    "iso:country":"CH",
    "sg:address":"Ulmenweg 17",
    "sg:city":"Obergerlafingen",
    "sg:orig_category":"Wirtschafts- and Arbeitgeberverb\u00e4nde",
    "sg:postcode":"4564",
    "sg:province":"Bern",
    "wof:name":"Das Gewerbe Beider Gerlafingen",
    "wof:placetype":"venue"
},
  "geometry": {"coordinates":[7.5850148201,47.1570014954],"type":"Point"}
}