{
  "type": "Feature",
  "properties": {
    "iso:country":"CH",
    "sg:address":"Freiestrasse 49",
    "sg:city":"Grenchen",
    "sg:orig_category":"Herstellung von Duft U K\u00f6rperpflegemitteln",
    "sg:phone":"+41 62 772 03 08",
    "sg:postcode":"2540",
    "sg:province":"Solothurn",
    "wof:name":"Gebr\u00fcder Wolff Gmbh",
    "wof:placetype":"venue"
},
  "geometry": {"coordinates":[8.2005596161,47.2711257935],"type":"Point"}
}