{
  "type": "Feature",
  "properties": {
    "iso:country":"CH",
    "sg:address":"Le Verney A 1070 Puidoux-gare Case Postale 490",
    "sg:city":"Pully",
    "sg:orig_category":"Herstellung von Mess U Kontrollinstrumenten U vorrichtungen Herstellung von Metallerzeugnissen ohne ",
    "sg:phone":"+41 21 729 64 66",
    "sg:postcode":"1009",
    "sg:province":"Vaud",
    "wof:name":"Waldner Ag",
    "wof:placetype":"venue"
},
  "geometry": {"coordinates":[6.7685251236,46.4927902222],"type":"Point"}
}