{
  "type": "Feature",
  "properties": {
    "iso:country":"CH",
    "sg:address":"Frankenstrasse 12",
    "sg:city":"Luzern",
    "sg:orig_category":"Advokaturb\u00fcros",
    "sg:phone":"+41 41 227 58 58",
    "sg:postcode":"6003",
    "sg:province":"Luzern",
    "wof:name":"Sury Brun & Hool Advokaturb\u00fcro",
    "wof:placetype":"venue"
},
  "geometry": {"coordinates":[8.307678,47.049015],"type":"Point"}
}