{
  "type": "Feature",
  "properties": {
    "iso:country":"CH",
    "sg:address":"Unterm\u00fcli 9",
    "sg:city":"Zug",
    "sg:orig_category":"Grosshandel mit sonstigen Maschinen U Ausr\u00fcstungen f\u00fcr Industrie, Handel U Schiffahrt",
    "sg:postcode":"6300",
    "sg:province":"Zug",
    "wof:name":"Bertei",
    "wof:placetype":"venue"
},
  "geometry": {"coordinates":[7.414276123,46.9228744507],"type":"Point"}
}