{
  "type": "Feature",
  "properties": {
    "iso:country":"CH",
    "sg:address":"Bahnhofplatz 9 2500 Biel/bienne Case Postale 699",
    "sg:city":"Biel/bienne",
    "sg:orig_category":"Herstellung U Zusammensetzung von Uhren Herstellung von Uhren",
    "sg:phone":"+41 32 925 36 00",
    "sg:postcode":"2502",
    "sg:province":"Bern",
    "wof:name":"Horoswiss Sa",
    "wof:placetype":"venue"
},
  "geometry": {"coordinates":[6.8057179451,47.0911598206],"type":"Point"}
}