{
  "type": "Feature",
  "properties": {
    "iso:country":"CH",
    "sg:address":"Trenschenstieg 2a",
    "sg:city":"Schaffhausen",
    "sg:orig_category":"Vermittlung von Immobilien Verwaltung von Immobilien",
    "sg:phone":"+41 21 671 01 71",
    "sg:postcode":"8207",
    "sg:province":"Schaffhausen",
    "wof:name":"Jean-fran\u00e7ois Roux Agence Immobili\u00e8re",
    "wof:placetype":"venue"
},
  "geometry": {"coordinates":[6.5974841118,46.5357666016],"type":"Point"}
}