{
  "type": "Feature",
  "properties": {
    "iso:country":"CH",
    "sg:address":"Pilatusstrasse 18 6003 Luzern. Postfach",
    "sg:city":"Luzern",
    "sg:orig_category":"Interessenvertretungen",
    "sg:phone":"+41 41 210 07 22",
    "sg:postcode":"6003",
    "sg:province":"Luzern",
    "wof:name":"Johannes-stiftung Wohlt\u00e4tige, Kulturelle, Erzieherische Gebiete Usw; F\u00f6rderung",
    "wof:placetype":"venue"
},
  "geometry": {"coordinates":[8.3059082031,47.0487670898],"type":"Point"}
}