{
  "type": "Feature",
  "properties": {
    "iso:country":"CH",
    "sg:address":"Hauptstrasse 87 4492 Tecknau. Postfach",
    "sg:city":"Tecknau",
    "sg:orig_category":"Datenverarbeitungsdienste G\u00fcterbef\u00f6rderung im Strassenverkehr",
    "sg:phone":"+41 61 981 25 65",
    "sg:postcode":"4492",
    "sg:province":"Basel-Landschaft",
    "wof:name":"Burri Logistik Ag Logistik, Transporte, Organisation; Dienstleistungen Und Beratungen",
    "wof:placetype":"venue"
},
  "geometry": {"coordinates":[7.887955,47.445992],"type":"Point"}
}