{
  "type": "Feature",
  "properties": {
    "iso:country":"CH",
    "sg:address":"3925",
    "sg:city":"Gr\u00e4chen",
    "sg:classifiers":[
        {
            "category":"Government",
            "subcategory":"Post Office",
            "type":"Public Place"
        }
    ],
    "sg:phone":"+41 27 956 33 47",
    "sg:postcode":"3925",
    "sg:province":"Valais",
    "sg:tags":[
        "caf\u00e9s",
        "tea-rooms"
    ],
    "wof:name":"Tea-room Thomas-platter-stube",
    "wof:placetype":"venue"
},
  "geometry": {"coordinates":[7.8392400742,46.1961631775],"type":"Point"}
}