{
  "type": "Feature",
  "properties": {
    "iso:country":"CH",
    "sg:address":"6345",
    "sg:city":"Neuheim",
    "sg:classifiers":[
        {
            "category":"Travel",
            "subcategory":"Hotels & Motels",
            "type":"Entertainment"
        }
    ],
    "sg:postcode":"6345",
    "sg:province":"Zug",
    "sg:tags":[
        "hotels",
        "mit",
        "restaurant"
    ],
    "wof:name":"W\u00fcrfel-zegg Werner",
    "wof:placetype":"venue"
},
  "geometry": {"coordinates":[10.3613004684,46.9444885254],"type":"Point"}
}