{
  "type": "Feature",
  "properties": {
    "iso:country":"CH",
    "sg:address":"H\u00f6nggerstrasse 5",
    "sg:city":"Oberengstringen",
    "sg:orig_category":"Kauf U Verkauf von Immobilien auf eigene Rechnung",
    "sg:phone":"+41 61 717 93 20",
    "sg:postcode":"8102",
    "sg:province":"Z\u00fcrich",
    "wof:name":"Suissepromotion Immobilien Ag",
    "wof:placetype":"venue"
},
  "geometry": {"coordinates":[7.6030101776,47.5112495422],"type":"Point"}
}