{
  "type": "Feature",
  "properties": {
    "iso:country":"CH",
    "sg:address":"Eschenbachstrasse 7",
    "sg:city":"Oetwil",
    "sg:orig_category":"Detailhandel mit Parf\u00fcmerieartikeln U K\u00f6rperpflegemitteln Herstellung von Duft U K\u00f6rperpflegemitteln",
    "sg:phone":"+41 55 415 54 00",
    "sg:postcode":"8955",
    "sg:province":"Z\u00fcrich",
    "wof:name":"Cosmopolitan Cosmetics Ag",
    "wof:placetype":"venue"
},
  "geometry": {"coordinates":[8.7278995514,47.2013206482],"type":"Point"}
}