{
  "type": "Feature",
  "properties": {
    "iso:country":"CH",
    "sg:address":"Campingstrasse",
    "sg:city":"Giswil",
    "sg:orig_category":"Campingpl\u00e4tze Detailhandel mit Zeitungen U Zeitschriften Kioske",
    "sg:phone":"+41 41 675 23 55",
    "sg:postcode":"6074",
    "sg:province":"Obwalden",
    "wof:name":"Campingplatz Sarnersee",
    "wof:placetype":"venue"
},
  "geometry": {"coordinates":[8.175465,46.854694],"type":"Point"}
}