{
  "type": "Feature",
  "properties": {
    "iso:country":"CH",
    "sg:address":"Schaffhauserstrasse",
    "sg:city":"Frauenfeld",
    "sg:orig_category":"Instandhaltung U Reparatur von Automobilen",
    "sg:phone":"+41 52 720 88 33",
    "sg:postcode":"8500",
    "sg:province":"Thurgau",
    "wof:name":"Erzenholz Garage Gmbh",
    "wof:placetype":"venue"
},
  "geometry": {"coordinates":[8.8808050156,47.5625762939],"type":"Point"}
}