{
  "type": "Feature",
  "properties": {
    "addr:full":"Sonnenwiesenstrasse 8 Kreuzlingen Thurgau 8280",
    "addr:housenumber":"8",
    "addr:postcode":"8280",
    "addr:street":"Sonnenwiesenstrasse",
    "iso:country":"CH",
    "sg:address":"Sonnenwiesenstrasse 8",
    "sg:city":"Kreuzlingen",
    "sg:orig_category":"Allgemeiner Hoch U Tiefbau",
    "sg:phone":"+41 79 416 88 15",
    "sg:postcode":"8280",
    "sg:province":"Thurgau",
    "wof:name":"Klaus Konstruktionsbau Ag",
    "wof:placetype":"venue"
},
  "geometry": {"coordinates":[9.189285,47.645855],"type":"Point"}
}