{
  "type": "Feature",
  "properties": {
    "iso:country":"CH",
    "sg:address":"Hermolingenstrasse 1",
    "sg:city":"Rothenburg",
    "sg:orig_category":"Sanit\u00e4r U Heizungsinstallation Sanit\u00e4rinstallation",
    "sg:phone":"+41 41 280 36 94",
    "sg:postcode":"6023",
    "sg:province":"Luzern",
    "wof:name":"Kurt Regli Heizungen & Sanit.anlagen",
    "wof:placetype":"venue"
},
  "geometry": {"coordinates":[8.2641029358,47.0957603455],"type":"Point"}
}