{
  "type": "Feature",
  "properties": {
    "iso:country":"CH",
    "sg:address":"Promenade Des Grandes-buttes 1",
    "sg:city":"Rolle",
    "sg:orig_category":"Primarschulen",
    "sg:phone":"+41 21 825 15 59",
    "sg:postcode":"1180",
    "sg:province":"Vaud",
    "wof:name":"Ecole Primaire Coll\u00e8ge Des Grandes-buttes",
    "wof:placetype":"venue"
},
  "geometry": {"coordinates":[6.3375191689,46.4599838257],"type":"Point"}
}