{
  "type": "Feature",
  "properties": {
    "iso:country":"CH",
    "sg:address":"Avenue Tronchet 34",
    "sg:city":"Th\u00f4nex",
    "sg:orig_category":"Elektro- and elektronische Maschinen Grosshandel Softwareentwicklung U beratung",
    "sg:phone":"+41 22 349 59 40",
    "sg:postcode":"1226",
    "sg:province":"Gen\u00e8ve",
    "wof:name":"Hst S\u00e0rl",
    "wof:placetype":"venue"
},
  "geometry": {"coordinates":[6.205930233,46.195930481],"type":"Point"}
}