{
  "type": "Feature",
  "properties": {
    "iso:country":"CH",
    "sg:address":"Lindenweg 19",
    "sg:city":"Pfaffhausen",
    "sg:orig_category":"Werbegrafikateliers",
    "sg:phone":"+41 79 216 15 49",
    "sg:postcode":"8118",
    "sg:province":"Z\u00fcrich",
    "wof:name":"Raymond Rohr Grafisches Atelier",
    "wof:placetype":"venue"
},
  "geometry": {"coordinates":[8.6265935898,47.3684272766],"type":"Point"}
}