{
  "type": "Feature",
  "properties": {
    "addr:full":"Route Du Vorbourg 28 Soyhi\u00e8res Jura 2805",
    "addr:housenumber":"28",
    "addr:postcode":"2805",
    "addr:street":"Route Du Vorbourg;Jura",
    "iso:country":"CH",
    "sg:address":"Route Du Vorbourg 28",
    "sg:city":"Soyhi\u00e8res",
    "sg:classifiers":[
        {
            "category":"Bars & Pubs",
            "type":"Food & Drink"
        }
    ],
    "sg:postcode":"2805",
    "sg:province":"Jura",
    "wof:name":"Adler Bar Gossau Ag",
    "wof:placetype":"venue"
},
  "geometry": {"coordinates":[9.248501,47.415394],"type":"Point"}
}