{
  "type": "Feature",
  "properties": {
    "iso:country":"CH",
    "sg:address":"Bruderb\u00fcelstrasse 28",
    "sg:city":"Russikon",
    "sg:orig_category":"Softwareentwicklung U beratung",
    "sg:phone":"+41 19542325",
    "sg:postcode":"8332",
    "sg:province":"Z\u00fcrich",
    "wof:name":"Ammann Softec",
    "wof:placetype":"venue"
},
  "geometry": {"coordinates":[8.7797555923,47.3913497925],"type":"Point"}
}