{
  "type": "Feature",
  "properties": {
    "iso:country":"CH",
    "sg:address":"Bahnhofstrasse 22",
    "sg:city":"Zollikon",
    "sg:orig_category":"Hoch U Tiefbau",
    "sg:phone":"+41 81 844 11 26",
    "sg:postcode":"8702",
    "sg:province":"Z\u00fcrich",
    "wof:name":"Mario Tuena Baugesch\u00e4ft",
    "wof:placetype":"venue"
},
  "geometry": {"coordinates":[10.0683355331,46.3065032959],"type":"Point"}
}