{
  "type": "Feature",
  "properties": {
    "iso:country":"CH",
    "sg:address":"Kirschbl\u00fctenweg 15",
    "sg:city":"Basel",
    "sg:orig_category":"Softwareentwicklung U beratung",
    "sg:phone":"+41 61 363 24 61",
    "sg:postcode":"4059",
    "sg:province":"Basel-Stadt",
    "wof:name":"Prog. Bal Ag Baumanagement/ Informatikber.",
    "wof:placetype":"venue"
},
  "geometry": {"coordinates":[7.5890440941,47.5361404419],"type":"Point"}
}