{
  "type": "Feature",
  "properties": {
    "addr:full":"Thundorferstrasse 27 Frauenfeld Thurgau 8500",
    "addr:housenumber":"27",
    "addr:postcode":"8500",
    "addr:street":"Thundorferstrasse",
    "iso:country":"CH",
    "sg:address":"Thundorferstrasse 27",
    "sg:city":"Frauenfeld",
    "sg:classifiers":[
        {
            "category":"Food & Beverages",
            "subcategory":"Specialty",
            "type":"Retail Goods"
        }
    ],
    "sg:phone":"+41 52 721 51 51",
    "sg:postcode":"8500",
    "sg:province":"Thurgau",
    "sg:tags":[
        "caterer"
    ],
    "wof:name":"Telepizza Gmbh",
    "wof:placetype":"venue"
},
  "geometry": {"coordinates":[8.900799,47.554665],"type":"Point"}
}