{
  "type": "Feature",
  "properties": {
    "iso:country":"CH",
    "sg:address":"Gerbergasse 4",
    "sg:city":"Solothurn",
    "sg:orig_category":"Kauf U Verkauf von Immobilien auf eigene Rechnung",
    "sg:postcode":"4500",
    "sg:province":"Solothurn",
    "wof:name":"Trisag Solothurn Ag",
    "wof:placetype":"venue"
},
  "geometry": {"coordinates":[7.5357851982,47.2061233521],"type":"Point"}
}