{
  "type": "Feature",
  "properties": {
    "iso:country":"CH",
    "sg:address":"3823",
    "sg:city":"Wengen",
    "sg:classifiers":[
        {
            "category":"Travel",
            "subcategory":"Hotels & Motels",
            "type":"Entertainment"
        }
    ],
    "sg:phone":"+41 79 216 91 82",
    "sg:postcode":"3823",
    "sg:province":"Bern",
    "sg:tags":[
        "hotels",
        "mit",
        "restaurant"
    ],
    "wof:name":"Brunner Richard.",
    "wof:placetype":"venue"
},
  "geometry": {"coordinates":[6.640250206,46.5850296021],"type":"Point"}
}