{
  "type": "Feature",
  "properties": {
    "iso:country":"CH",
    "sg:address":"Eigenweg 10",
    "sg:city":"Herzogenbuchsee",
    "sg:orig_category":"Restaurants Schwimmb\u00e4der",
    "sg:phone":"+41 56 441 03 46",
    "sg:postcode":"3360",
    "sg:province":"Bern",
    "wof:name":"Restaurant Hallen-& Freibad",
    "wof:placetype":"venue"
},
  "geometry": {"coordinates":[8.1947755814,47.4817314148],"type":"Point"}
}