{
  "type": "Feature",
  "properties": {
    "addr:full":"Grienbachstrasse 15 Zug Zug 6300",
    "addr:housenumber":"15",
    "addr:postcode":"6300",
    "addr:street":"Grienbachstrasse;Zug",
    "iso:country":"CH",
    "sg:address":"Grienbachstrasse 15",
    "sg:city":"Zug",
    "sg:orig_category":"Architektur U Ingenieurb\u00fcros",
    "sg:phone":"+41 41 761 44 47",
    "sg:postcode":"6300",
    "sg:province":"Zug",
    "wof:name":"Terraproject Rl Luthiger Ingenieurb\u00fcro",
    "wof:placetype":"venue"
},
  "geometry": {"coordinates":[8.522926,47.183426],"type":"Point"}
}