{
  "type": "Feature",
  "properties": {
    "iso:country":"CH",
    "sg:address":"Nauenstrasse 63a 4052 Basel. Postfach",
    "sg:city":"Basel",
    "sg:orig_category":"Wirtschaftspr\u00fcfung, Steuerberatung U Treuhand",
    "sg:phone":"+41 61 272 27 91",
    "sg:postcode":"4051",
    "sg:province":"Basel-Stadt",
    "wof:name":"Treuhandbureau Walter Maritz",
    "wof:placetype":"venue"
},
  "geometry": {"coordinates":[7.5941081047,47.5469856262],"type":"Point"}
}