{
  "type": "Feature",
  "properties": {
    "iso:country":"CH",
    "sg:address":"Riva Paradiso 26",
    "sg:city":"Paradiso",
    "sg:orig_category":"Fachdetailhandel mit pharmazeutischen, medizinischen U kosmetischen Artikeln in Verkaufsr\u00e4umen Herst",
    "sg:phone":"+41 91 993 06 66",
    "sg:postcode":"6900",
    "sg:province":"Ticino",
    "wof:name":"Eco Key Sa",
    "wof:placetype":"venue"
},
  "geometry": {"coordinates":[8.9507608414,45.9903411865],"type":"Point"}
}