{
  "type": "Feature",
  "properties": {
    "iso:country":"CH",
    "sg:address":"Schulhausstrasse",
    "sg:city":"Weite",
    "sg:classifiers":[
        {
            "category":"Restaurant",
            "type":"Food & Drink"
        }
    ],
    "sg:phone":"+41 17863474",
    "sg:postcode":"9476",
    "sg:province":"St. Gallen",
    "wof:name":"Restaurant Hirschen",
    "wof:placetype":"venue"
},
  "geometry": {"coordinates":[8.732375145,47.2032585144],"type":"Point"}
}