{
  "type": "Feature",
  "properties": {
    "iso:country":"CH",
    "sg:address":"Montana-vermala 3975 Bluche-randogne. Postfach",
    "sg:city":"Montana-vermala",
    "sg:orig_category":"Interessenvertretungen",
    "sg:postcode":"3962",
    "wof:name":"Fondation Georgette Wander",
    "wof:placetype":"venue"
},
  "geometry": {"coordinates":[7.5151138306,46.2997512817],"type":"Point"}
}