{
  "type": "Feature",
  "properties": {
    "iso:country":"CH",
    "sg:address":"Industriestr. 17",
    "sg:city":"Lausen",
    "sg:orig_category":"Architektur U Ingenieurb\u00fcros Sonstige technische Beratung U Planung",
    "sg:phone":"+41 61 923 31 20",
    "sg:postcode":"4415",
    "sg:province":"Basel-Landschaft",
    "wof:name":"Hptec Gmbh",
    "wof:placetype":"venue"
},
  "geometry": {"coordinates":[7.758814,47.47023],"type":"Point"}
}