{
  "type": "Feature",
  "properties": {
    "iso:country":"CH",
    "sg:address":"Riedeggweg 70",
    "sg:city":"Bern",
    "sg:orig_category":"Sonstiger Grosshandel",
    "sg:phone":"+41 71 277 87 17",
    "sg:postcode":"3020",
    "sg:province":"Bern",
    "wof:name":"Egli Robert Vertriebsagentur S\u00fcsswaren, Geschenkartikel Usw; Vertrieb, Handel",
    "wof:placetype":"venue"
},
  "geometry": {"coordinates":[9.3686714172,47.4128990173],"type":"Point"}
}