{
  "type": "Feature",
  "properties": {
    "iso:country":"CH",
    "sg:address":"Schaffhauserstrasse 39",
    "sg:city":"Winterthur",
    "sg:orig_category":"Gesundheitswesen",
    "sg:phone":"+41 26 670 09 90",
    "sg:postcode":"8400",
    "sg:province":"Z\u00fcrich",
    "wof:name":"Rr R\u00e9flexologie, Ringier",
    "wof:placetype":"venue"
},
  "geometry": {"coordinates":[1.9467660189,50.2957191467],"type":"Point"}
}