{
  "type": "Feature",
  "properties": {
    "iso:country":"CH",
    "sg:address":"Bergellerstrasse 31",
    "sg:city":"Z\u00fcrich",
    "sg:classifiers":[
        {
            "category":"Professional",
            "subcategory":"Employment Agencies",
            "type":"Services"
        }
    ],
    "sg:phone":"+41 21 311 88 53",
    "sg:postcode":"8049",
    "sg:province":"Z\u00fcrich",
    "sg:tags":[
        "personal",
        "u",
        "stellenvermittlung"
    ],
    "wof:name":"Job \u00e0 La Carte Sa",
    "wof:placetype":"venue"
},
  "geometry": {"coordinates":[6.6288552284,46.5224647522],"type":"Point"}
}