{
  "type": "Feature",
  "properties": {
    "iso:country":"CH",
    "sg:address":"Pommier Rue Du 4",
    "sg:city":"Neuch\u00e2tel",
    "sg:orig_category":"Grosshandel mit Getr\u00e4nken",
    "sg:phone":"+41 32 721 12 30",
    "sg:postcode":"2000",
    "sg:province":"Neuch\u00e2tel",
    "wof:name":"Crelier-chevalley Fabienne",
    "wof:placetype":"venue"
},
  "geometry": {"coordinates":[6.9272480011,46.9916267395],"type":"Point"}
}