{
  "type": "Feature",
  "properties": {
    "iso:country":"CH",
    "sg:address":"St. Johanns-ring 109 4056 Basel. Postfach",
    "sg:city":"Basel",
    "sg:orig_category":"Druck ohne Zeitungsdruck Satzherstellung U Reproduktion",
    "sg:phone":"+41 61 382 91 26",
    "sg:postcode":"4051",
    "sg:province":"Basel-Stadt",
    "wof:name":"Philamedia Schmocker Peter Satz, Grafik U. Druck Von Drucksachen Usw",
    "wof:placetype":"venue"
},
  "geometry": {"coordinates":[7.5758638382,47.5628433228],"type":"Point"}
}