{
  "type": "Feature",
  "properties": {
    "iso:country":"CH",
    "sg:address":"Untere Hauptgasse 32",
    "sg:city":"Thun",
    "sg:classifiers":[
        {
            "category":"Restaurant",
            "type":"Food & Drink"
        }
    ],
    "sg:phone":"+41 41 630 19 12",
    "sg:postcode":"3600",
    "sg:province":"Bern",
    "wof:name":"R\u00f6ssli Die Beiz",
    "wof:placetype":"venue"
},
  "geometry": {"coordinates":[8.3116025925,46.9845046997],"type":"Point"}
}