{
  "type": "Feature",
  "properties": {
    "iso:country":"CH",
    "sg:address":"Kriesbachstrasse 5",
    "sg:city":"Wallisellen",
    "sg:orig_category":"Hardwareberatung Wirtschaftspr\u00fcfung, Steuerberatung U Treuhand",
    "sg:phone":"+41 18333279",
    "sg:postcode":"8304",
    "sg:province":"Z\u00fcrich",
    "wof:name":"Siscom Ag",
    "wof:placetype":"venue"
},
  "geometry": {"coordinates":[8.6130228043,47.4102020264],"type":"Point"}
}