{
  "type": "Feature",
  "properties": {
    "iso:country":"CH",
    "sg:address":"B\u00fcro-und Gewerbezentrum 9497 Triesenberg. Postfach 1101",
    "sg:city":"Triesenberg",
    "sg:orig_category":"Unternehmensberatung",
    "sg:phone":"+41 75 262 33 33",
    "sg:postcode":"9497",
    "wof:name":"Wegelin Aktiengesellschaft Unternehmens-& Wirtschaftsber.",
    "wof:placetype":"venue"
},
  "geometry": {"coordinates":[9.5441665649,47.1186065674],"type":"Point"}
}