{
  "type": "Feature",
  "properties": {
    "addr:full":"Christoph-schnyder-strasse 46 6210 Sursee. Postfach Sursee Luzern 6210",
    "addr:housenumber":"46",
    "addr:postcode":"6210 sursee. postfach;6210",
    "addr:street":"Christoph-Schnyder-Strasse",
    "iso:country":"CH",
    "sg:address":"Christoph-schnyder-strasse 46 6210 Sursee. Postfach",
    "sg:city":"Sursee",
    "sg:orig_category":"Architekturb\u00fcros",
    "sg:phone":"+41 79 350 66 79",
    "sg:postcode":"6210",
    "sg:province":"Luzern",
    "wof:name":"Werner Portmann Architekturb\u00fcro",
    "wof:placetype":"venue"
},
  "geometry": {"coordinates":[8.105453,47.165878],"type":"Point"}
}