{
  "type": "Feature",
  "properties": {
    "iso:country":"CH",
    "sg:address":"Rue Des Boulangers 16",
    "sg:city":"Veyrier",
    "sg:orig_category":"Gewinnung von Natursteinen f\u00fcr den Bau Herstellung von sonstigen Produkten aus nichtmetallischen Min",
    "sg:phone":"+41 22 784 16 28",
    "sg:postcode":"1255",
    "sg:province":"Gen\u00e8ve",
    "wof:name":"Fran\u00e7ois Chavaz Carri\u00e8res & Transports",
    "wof:placetype":"venue"
},
  "geometry": {"coordinates":[6.1854219437,46.1674842834],"type":"Point"}
}