{
  "type": "Feature",
  "properties": {
    "addr:full":"Rue Jaquet-droz 2 Neuch\u00e2tel Neuch\u00e2tel 2000",
    "addr:housenumber":"2",
    "addr:postcode":"2000",
    "addr:street":"Rue Jaquet-Droz",
    "iso:country":"CH",
    "sg:address":"Rue Jaquet-droz 2",
    "sg:city":"Neuch\u00e2tel",
    "sg:orig_category":"Detailhandel mit Brot, Back U S\u00fcsswaren",
    "sg:phone":"+41 32 725 28 54",
    "sg:postcode":"2000",
    "sg:province":"Neuch\u00e2tel",
    "wof:name":"Tea-room Du Mail",
    "wof:placetype":"venue"
},
  "geometry": {"coordinates":[6.947888,46.997875],"type":"Point"}
}