{
  "type": "Feature",
  "properties": {
    "iso:country":"CH",
    "sg:address":"Rue De Lausanne 70",
    "sg:city":"Morges",
    "sg:orig_category":"HOTELS: MIT RESTAURANT Kongress- and Tagungshotels mit Restaurant",
    "sg:phone":"+41 21 802 43 11",
    "sg:postcode":"1110",
    "sg:province":"Vaud",
    "wof:name":"H\u00f4tel Fleur Du Lac",
    "wof:placetype":"venue"
},
  "geometry": {"coordinates":[6.5088610649,46.5166816711],"type":"Point"}
}