{
  "type": "Feature",
  "properties": {
    "iso:country":"CH",
    "sg:address":"Lindauerstrasse 2",
    "sg:city":"N\u00fcrensdorf",
    "sg:orig_category":"Nationale Postdienste",
    "sg:phone":"+41 18365245",
    "sg:postcode":"8309",
    "sg:province":"Z\u00fcrich",
    "wof:name":"Die Schweizerische Post",
    "wof:placetype":"venue"
},
  "geometry": {"coordinates":[8.6489906311,47.4466743469],"type":"Point"}
}