{
  "type": "Feature",
  "properties": {
    "iso:country":"CH",
    "sg:address":"Therwilerstrasse 93 4103 Bottmingen. Postfach 125",
    "sg:city":"Bottmingen",
    "sg:orig_category":"Herstellung von Maschinen f\u00fcr die Nahrungsmittel, Getr\u00e4nkeherstellung U die Tabakverarbeitung",
    "sg:phone":"+41 61 401 42 34",
    "sg:postcode":"4103",
    "sg:province":"Basel-Landschaft",
    "wof:name":"Begg Tec Ag Miwe-servicetechnik",
    "wof:placetype":"venue"
},
  "geometry": {"coordinates":[7.5675711632,47.5190238953],"type":"Point"}
}