{
  "type": "Feature",
  "properties": {
    "iso:country":"CH",
    "sg:address":"Via San Gottardo 98",
    "sg:city":"Bellinzona",
    "sg:orig_category":"Grosshandel mit Holz U Baustoffen Herstellung von keramischen Wand U Bodenfliesen U platten",
    "sg:phone":"+41 91 825 16 34",
    "sg:postcode":"6500",
    "sg:province":"Ticino",
    "wof:name":"Valli & Gehri Piastrelle Sa",
    "wof:placetype":"venue"
},
  "geometry": {"coordinates":[9.0372200012,46.2056846619],"type":"Point"}
}