{
  "type": "Feature",
  "properties": {
    "iso:country":"CH",
    "sg:address":"Freilagerstrasse 40",
    "sg:city":"Z\u00fcrich",
    "sg:orig_category":"HERSTELLUNG VON GER\u00c4TEN DER ELEKTRIZIT\u00c4TSERZEUGUNG, -VERTEILUNG U.\u00c4 Herstellung von sonstigen Maschi",
    "sg:phone":"+41 71 311 33 94",
    "sg:postcode":"8047",
    "sg:province":"Z\u00fcrich",
    "wof:name":"Sutter Apparatebau Ag",
    "wof:placetype":"venue"
},
  "geometry": {"coordinates":[9.311756134,47.4167671204],"type":"Point"}
}