{
  "type": "Feature",
  "properties": {
    "iso:country":"CH",
    "sg:address":"Neustadtstrasse 36 6003 Luzern. Postfach",
    "sg:city":"Luzern",
    "sg:orig_category":"Sanit\u00e4r U Heizungsinstallation Sanit\u00e4rinstallation",
    "sg:phone":"+41 62 771 41 69",
    "sg:postcode":"6002",
    "sg:province":"Luzern",
    "wof:name":"Urs Regli Heizung Sanit\u00e4r",
    "wof:placetype":"venue"
},
  "geometry": {"coordinates":[8.1946773529,47.2513122559],"type":"Point"}
}