{
  "type": "Feature",
  "properties": {
    "iso:country":"CH",
    "sg:address":"Riedikerstrasse 50",
    "sg:city":"Uster",
    "sg:orig_category":"Fachdetailhandel in Verkaufsr\u00e4umen",
    "sg:phone":"+41 61 332 09 32",
    "sg:postcode":"8610",
    "sg:province":"Z\u00fcrich",
    "wof:name":"Goldenway Tiernahrungs Und Zubeh\u00f6r-center, Ernst Furrer",
    "wof:placetype":"venue"
},
  "geometry": {"coordinates":[8.7135791779,47.3379325867],"type":"Point"}
}