{
  "type": "Feature",
  "properties": {
    "iso:country":"CH",
    "sg:address":"1535",
    "sg:city":"Combremont-grand",
    "sg:orig_category":"Landesverteidigung, Sozialversicherung \u00d6ffentliche Verwaltung",
    "sg:phone":"+41 26 666 12 95",
    "sg:postcode":"1535",
    "sg:province":"Vaud",
    "wof:name":"Centre De Protection Civile",
    "wof:placetype":"venue"
},
  "geometry": {"coordinates":[6.8175902367,46.7612991333],"type":"Point"}
}