{
  "type": "Feature",
  "properties": {
    "iso:country":"CH",
    "sg:address":"Breitenweg 28",
    "sg:city":"Seon",
    "sg:orig_category":"Non-Classified Establishments",
    "sg:postcode":"5703",
    "sg:province":"Aargau",
    "wof:name":"Profil-express Sljivic V.",
    "wof:placetype":"venue"
},
  "geometry": {"coordinates":[8.1620264053,47.3555030823],"type":"Point"}
}