{
  "type": "Feature",
  "properties": {
    "iso:country":"CH",
    "sg:address":"Kolinplatz 8",
    "sg:city":"Zug",
    "sg:orig_category":"Unclassifiable Establishments",
    "sg:postcode":"6300",
    "sg:province":"Zug",
    "wof:name":"Hem M\u00fchlethaler",
    "wof:placetype":"venue"
},
  "geometry": {"coordinates":[8.515206337,47.1661148071],"type":"Point"}
}