{
  "type": "Feature",
  "properties": {
    "iso:country":"CH",
    "sg:address":"Bahnhofstrasse 2 9602 Bazenheid. Postfach",
    "sg:city":"Bazenheid",
    "sg:orig_category":"RESTAURANTS: TEA-ROOMS",
    "sg:postcode":"9602",
    "sg:province":"St. Gallen",
    "wof:name":"Keller Verena Rest. B\u00e4ren",
    "wof:placetype":"venue"
},
  "geometry": {"coordinates":[9.0691890717,47.4109115601],"type":"Point"}
}