{
  "type": "Feature",
  "properties": {
    "iso:country":"CH",
    "sg:address":"N\u00e4gelig\u00e4ssli 5",
    "sg:city":"Port",
    "sg:orig_category":"Mechanik Mechanische Werkst\u00e4tten",
    "sg:phone":"+41 19307530",
    "sg:postcode":"2562",
    "sg:province":"Bern",
    "wof:name":"Femec Ag",
    "wof:placetype":"venue"
},
  "geometry": {"coordinates":[8.8061571121,47.3328895569],"type":"Point"}
}