{
  "type": "Feature",
  "properties": {
    "iso:country":"CH",
    "sg:address":"Dufourstrasse 90 8008 Z\u00fcrich. Postfach 820",
    "sg:city":"Z\u00fcrich",
    "sg:orig_category":"Detailhandel mit B\u00fcromaschinen U einrichtungen",
    "sg:phone":"+41 41 410 41 81",
    "sg:postcode":"8034",
    "sg:province":"Z\u00fcrich",
    "wof:name":"Interoffice Design Ag B\u00fcroeinrichtungen",
    "wof:placetype":"venue"
},
  "geometry": {"coordinates":[8.309281,47.059055],"type":"Point"}
}