{
  "type": "Feature",
  "properties": {
    "iso:country":"CH",
    "sg:address":"Steinacherstrasse 150",
    "sg:city":"W\u00e4denswil",
    "sg:orig_category":"Fotografische Ateliers Fotografisches Gewerbe U fotografische Laboratorien",
    "sg:phone":"+41 16832288",
    "sg:postcode":"8820",
    "sg:province":"Z\u00fcrich",
    "wof:name":"Die Bildmacher, Bello Lorenzo",
    "wof:placetype":"venue"
},
  "geometry": {"coordinates":[8.6373844147,47.2402496338],"type":"Point"}
}