{
  "type": "Feature",
  "properties": {
    "iso:country":"CH",
    "sg:address":"Sennweidstr. 41",
    "sg:city":"Steinhausen",
    "sg:classifiers":[
        {
            "category":"Social Services",
            "subcategory":"Job Training",
            "type":"Services"
        }
    ],
    "sg:phone":"+41 32 926 03 95",
    "sg:postcode":"6312",
    "sg:province":"Zug",
    "sg:tags":[
        "metallurgy",
        "metal",
        "processing",
        "-",
        "metalworking",
        "machine",
        "engineering",
        "mechanical"
    ],
    "wof:name":"Demhosa Sa",
    "wof:placetype":"venue"
},
  "geometry": {"coordinates":[6.8207798004,47.090473175],"type":"Point"}
}