{
  "type": "Feature",
  "properties": {
    "iso:country":"CH",
    "sg:address":"Wiesentalstrasse 22 8355 Aadorf. Postfach 122",
    "sg:city":"Aadorf",
    "sg:orig_category":"Herstellung von Werkzeugen Herstellung von Werkzeugmaschinen",
    "sg:phone":"+41 52 365 10 82",
    "sg:postcode":"8355",
    "sg:province":"Thurgau",
    "wof:name":"Ehrensberger Werkzeugbau Ag",
    "wof:placetype":"venue"
},
  "geometry": {"coordinates":[8.8994131088,47.4923782349],"type":"Point"}
}