{
  "type": "Feature",
  "properties": {
    "iso:country":"CH",
    "sg:address":"Weststrasse 8",
    "sg:city":"Unter\u00e4geri",
    "sg:orig_category":"Maler U Glasergewerbe Malerei",
    "sg:phone":"+41 41 460 47 08",
    "sg:postcode":"6314",
    "sg:province":"Zug",
    "wof:name":"Maler Alexander Nikolic",
    "wof:placetype":"venue"
},
  "geometry": {"coordinates":[8.2235832214,47.131149292],"type":"Point"}
}