{
  "type": "Feature",
  "properties": {
    "iso:country":"CH",
    "sg:address":"S\u00e4genstrasse 6",
    "sg:city":"Felsberg",
    "sg:orig_category":"Sanit\u00e4r, Heizungs U L\u00fcftungsinstallation Sanit\u00e4rinstallation",
    "sg:phone":"+41 81 252 79 90",
    "sg:postcode":"7012",
    "sg:province":"Graubunden",
    "wof:name":"Hans A. Danuser San.installationen & Heizungen",
    "wof:placetype":"venue"
},
  "geometry": {"coordinates":[9.4808607101,46.8473396301],"type":"Point"}
}