{
  "type": "Feature",
  "properties": {
    "iso:country":"CH",
    "sg:address":"Avenue De La Promenade 4",
    "sg:city":"Payerne",
    "sg:orig_category":"Non-Classified Establishments",
    "sg:postcode":"1530",
    "sg:province":"Vaud",
    "wof:name":"Dr M\u00e9d. Alain Schreyer M\u00e9decin Sp\u00e9cialiste Fmh",
    "wof:placetype":"venue"
},
  "geometry": {"coordinates":[6.9418578148,46.822467804],"type":"Point"}
}