{
  "type": "Feature",
  "properties": {
    "iso:country":"CH",
    "sg:address":"Hauptstrasse 65",
    "sg:city":"Zihlschlacht",
    "sg:orig_category":"Mechanische Werkst\u00e4tten",
    "sg:phone":"+41 79 406 47 19",
    "sg:postcode":"8588",
    "sg:province":"Thurgau",
    "wof:name":"Markus Egloff Mechanische Werkstatt",
    "wof:placetype":"venue"
},
  "geometry": {"coordinates":[9.2601633072,47.5237846375],"type":"Point"}
}