{
  "type": "Feature",
  "properties": {
    "iso:country":"CH",
    "sg:address":"Hauptstrasse 45",
    "sg:city":"Frick",
    "sg:orig_category":"Herstellung von Spielwaren",
    "sg:phone":"+41 34 435 13 25",
    "sg:postcode":"5070",
    "sg:province":"Aargau",
    "wof:name":"Pilgram Spielzeug Gmbh",
    "wof:placetype":"venue"
},
  "geometry": {"coordinates":[7.7318201065,47.064781189],"type":"Point"}
}