{
  "type": "Feature",
  "properties": {
    "iso:country":"CH",
    "sg:address":"Rainstrasse 92",
    "sg:city":"Z\u00fcrich",
    "sg:orig_category":"Schreib U \u00dcbersetzungsb\u00fcros",
    "sg:phone":"+41 14802626",
    "sg:postcode":"8038",
    "sg:province":"Z\u00fcrich",
    "wof:name":"Weigum Marliese - Eins\u00e4tze Nach Bedarf Und Budget",
    "wof:placetype":"venue"
},
  "geometry": {"coordinates":[8.5254936218,47.3464775085],"type":"Point"}
}