{
  "type": "Feature",
  "properties": {
    "iso:country":"CH",
    "sg:address":"Centralstrasse 3",
    "sg:city":"Grenchen",
    "sg:orig_category":"Reiseb\u00fcros U Reiseveranstalter",
    "sg:phone":"+41 32 652 36 23",
    "sg:postcode":"2540",
    "sg:province":"Solothurn",
    "wof:name":"A + L Tourist Club Gmbh",
    "wof:placetype":"venue"
},
  "geometry": {"coordinates":[7.3955202103,47.1931343079],"type":"Point"}
}