{
  "type": "Feature",
  "properties": {
    "iso:country":"CH",
    "sg:address":"Grabenstrasse 15",
    "sg:city":"Chur",
    "sg:orig_category":"Kauf U Verkauf von Immobilien auf eigene Rechnung",
    "sg:phone":"+41 81 252 20 22",
    "sg:postcode":"7000",
    "sg:province":"Graubunden",
    "wof:name":"Mira Chur Sa",
    "wof:placetype":"venue"
},
  "geometry": {"coordinates":[9.5321493149,46.8507995605],"type":"Point"}
}