{
  "type": "Feature",
  "properties": {
    "iso:country":"CH",
    "sg:city":"Wila",
    "sg:orig_category":"Internet, Webseiten U -systeme",
    "sg:postcode":"8492",
    "sg:province":"Z\u00fcrich",
    "wof:name":"Dbolliger",
    "wof:placetype":"venue"
},
  "geometry": {"coordinates":[8.846028,47.419601],"type":"Point"}
}