{
  "type": "Feature",
  "properties": {
    "iso:country":"CH",
    "sg:address":"Restaurant Bahnhofbuffet 3718 Kandersteg. Postfach",
    "sg:city":"Kandersteg",
    "sg:orig_category":"RESTAURANTS: TEA-ROOMS",
    "sg:phone":"+41 27 956 27 76",
    "sg:postcode":"3718",
    "sg:province":"Bern",
    "wof:name":"Restaurant Bahnhofbuffet, Fux Robert",
    "wof:placetype":"venue"
},
  "geometry": {"coordinates":[7.8021001816,46.1756591797],"type":"Point"}
}