{
  "type": "Feature",
  "properties": {
    "iso:country":"CH",
    "sg:address":"Christoffelgasse 4 3011 Bern. Postfach",
    "sg:city":"Bern",
    "sg:orig_category":"Detailhandel mit Bekleidung",
    "sg:phone":"+41 32 725 33 55",
    "sg:postcode":"3005",
    "sg:province":"Bern",
    "wof:name":"Jaquet Jie Trading Co",
    "wof:placetype":"venue"
},
  "geometry": {"coordinates":[6.857987,46.965614],"type":"Point"}
}