{
  "type": "Feature",
  "properties": {
    "iso:country":"CH",
    "sg:address":"Wiggiswilweg 2",
    "sg:city":"Jegenstorf",
    "sg:orig_category":"Allgemeiner Hoch U Tiefbau Hoch U Tiefbau",
    "sg:phone":"+41 31 761 14 14",
    "sg:postcode":"3303",
    "sg:province":"Bern",
    "wof:name":"Zaugg Theo.",
    "wof:placetype":"venue"
},
  "geometry": {"coordinates":[7.502418,47.047382],"type":"Point"}
}