{
  "type": "Feature",
  "properties": {
    "iso:country":"CH",
    "sg:address":"Belchenstrasse 6",
    "sg:city":"Basel",
    "sg:orig_category":"Pensionskassen",
    "sg:phone":"+41 61 302 46 00",
    "sg:postcode":"4054",
    "sg:province":"Basel-Stadt",
    "wof:name":"Personalf\u00fcrsorgestiftung Der E. Kalt Ag, Klima Und Energietechnik",
    "wof:placetype":"venue"
},
  "geometry": {"coordinates":[7.5739102364,47.5542984009],"type":"Point"}
}