{
  "type": "Feature",
  "properties": {
    "iso:country":"CH",
    "sg:address":"H\u00e4ldeliweg 17",
    "sg:city":"Z\u00fcrich",
    "sg:orig_category":"Pensionskassen",
    "sg:phone":"+41 16322002",
    "sg:postcode":"8044",
    "sg:province":"Z\u00fcrich",
    "wof:name":"L\u00fcck Albert-stiftung Personalf\u00fcrsorge Usw",
    "wof:placetype":"venue"
},
  "geometry": {"coordinates":[8.5545597076,47.3770523071],"type":"Point"}
}