{
  "type": "Feature",
  "properties": {
    "iso:country":"CH",
    "sg:address":"Marktgasse 2",
    "sg:city":"Endingen",
    "sg:orig_category":"Detailhandel mit Blumen U Pflanzen",
    "sg:phone":"+41 56 242 24 74",
    "sg:postcode":"5304",
    "sg:province":"Aargau",
    "wof:name":"Steigi's Blueme-farm",
    "wof:placetype":"venue"
},
  "geometry": {"coordinates":[8.291046,47.536686],"type":"Point"}
}