{
  "type": "Feature",
  "properties": {
    "iso:country":"CH",
    "sg:address":"Kreuzgasse 11",
    "sg:city":"Worb",
    "sg:orig_category":"Arztpraxen",
    "sg:phone":"+41 31 839 07 08",
    "sg:postcode":"3076",
    "sg:province":"Bern",
    "wof:name":"Dr.med.stephan Tresch Spezialarzt Fmh",
    "wof:placetype":"venue"
},
  "geometry": {"coordinates":[7.563518,46.927746],"type":"Point"}
}