{
  "type": "Feature",
  "properties": {
    "iso:country":"CH",
    "sg:address":"Pl. Du Vingt-trois Juin 2 2350 Saignel\u00e9gier. Postfach",
    "sg:city":"Neuenburg",
    "sg:orig_category":"Detailhandel mit Bekleidung",
    "sg:postcode":"2000",
    "sg:province":"Neuch\u00e2tel",
    "wof:name":"Act'or S\u00e0rl V\u00eatements; Commerce, Fabrication",
    "wof:placetype":"venue"
},
  "geometry": {"coordinates":[6.996539,47.256149],"type":"Point"}
}