{
  "type": "Feature",
  "properties": {
    "iso:country":"CH",
    "sg:address":"Dorf",
    "sg:city":"Sch\u00f6nengrund",
    "sg:orig_category":"Primarschulen",
    "sg:phone":"+41 71 361 10 25",
    "sg:postcode":"9105",
    "sg:province":"Appenzell Ausserrhoden",
    "wof:name":"Primarschule Sch\u00f6nengrund-wald",
    "wof:placetype":"venue"
},
  "geometry": {"coordinates":[9.226940155,47.3268241882],"type":"Point"}
}