{
  "type": "Feature",
  "properties": {
    "iso:country":"CH",
    "sg:address":"Eggweg 3",
    "sg:city":"Ormalingen",
    "sg:orig_category":"Massagestudios P\u00e9dicure",
    "sg:phone":"+41 81 756 14 23",
    "sg:postcode":"4466",
    "sg:province":"Basel-Landschaft",
    "wof:name":"Esther Mosimann",
    "wof:placetype":"venue"
},
  "geometry": {"coordinates":[9.4764537811,47.1675453186],"type":"Point"}
}