{
  "type": "Feature",
  "properties": {
    "addr:full":"Rotzbergstrasse 19 Stansstad Nidwalden 6362",
    "addr:housenumber":"19",
    "addr:postcode":"6362",
    "addr:street":"Rotzbergstrasse",
    "iso:country":"CH",
    "sg:address":"Rotzbergstrasse 19",
    "sg:city":"Stansstad",
    "sg:classifiers":[
        {
            "category":"Military Area",
            "subcategory":"Air Force Base",
            "type":"Public Place"
        }
    ],
    "sg:phone":"+41 41 610 25 17",
    "sg:postcode":"6362",
    "sg:province":"Nidwalden",
    "sg:tags":[
        "equipment",
        "system",
        "dehumidification"
    ],
    "wof:name":"Bautrent Ag",
    "wof:placetype":"venue"
},
  "geometry": {"coordinates":[8.33895,46.97028],"type":"Point"}
}