{
  "type": "Feature",
  "properties": {
    "iso:country":"CH",
    "sg:address":"Saint-fran\u00e7ois Passage 10 1003 Lausanne Case Postale 2633",
    "sg:city":"Lausanne",
    "sg:orig_category":"Druck ohne Zeitungsdruck",
    "sg:phone":"+41 21 321 14 21",
    "sg:postcode":"1003",
    "sg:province":"Vaud",
    "wof:name":"Diapress, Debraine Yves",
    "wof:placetype":"venue"
},
  "geometry": {"coordinates":[6.6325941086,46.5203475952],"type":"Point"}
}