{
  "type": "Feature",
  "properties": {
    "iso:country":"CH",
    "sg:address":"R\u00f6sslimattstrasse 39",
    "sg:city":"Luzern",
    "sg:orig_category":"Bauschreinerei Herstellung von K\u00fcchenm\u00f6beln",
    "sg:phone":"+41 41 360 27 66",
    "sg:postcode":"6005",
    "sg:province":"Luzern",
    "wof:name":"Piatti K\u00fcchenforum Ag",
    "wof:placetype":"venue"
},
  "geometry": {"coordinates":[8.314549,47.044651],"type":"Point"}
}