{
  "type": "Feature",
  "properties": {
    "iso:country":"CH",
    "sg:address":"Rietgrabenstrasse 42",
    "sg:city":"Opfikon",
    "sg:orig_category":"Sportvereine Triathlon Laufen, Schwimmen, Velo",
    "sg:phone":"+41 18105016",
    "sg:postcode":"8152",
    "sg:province":"Z\u00fcrich",
    "wof:name":"Triathlon-club Amphibion",
    "wof:placetype":"venue"
},
  "geometry": {"coordinates":[8.5756654739,47.4262809753],"type":"Point"}
}