{
  "type": "Feature",
  "properties": {
    "iso:country":"CH",
    "sg:address":"Weststr. 10",
    "sg:city":"Bern",
    "sg:classifiers":[
        {
            "category":"Professional",
            "subcategory":"Business Services",
            "type":"Services"
        }
    ],
    "sg:phone":"+41 31 359 51 11",
    "sg:postcode":"3006",
    "sg:province":"Bern",
    "sg:tags":[
        "body",
        "advice"
    ],
    "wof:name":"Schweizer Milchproduzenten",
    "wof:placetype":"venue"
},
  "geometry": {"coordinates":[7.44777,46.943104],"type":"Point"}
}