{
  "type": "Feature",
  "properties": {
    "iso:country":"CH",
    "sg:address":"3979",
    "sg:city":"Gr\u00f4ne",
    "sg:orig_category":"Detailhandel mit Fleisch U Fleischwaren",
    "sg:phone":"+41 21 845 57 21",
    "sg:postcode":"3979",
    "sg:province":"Valais",
    "wof:name":"Daniel Brunisso Boucherie-charcuterie",
    "wof:placetype":"venue"
},
  "geometry": {"coordinates":[6.2331790924,46.6099128723],"type":"Point"}
}