{
  "type": "Feature",
  "properties": {
    "iso:country":"CH",
    "sg:address":"Hegistrasse 35 8404 Stadel(winterthur). Postfach",
    "sg:city":"Oberwinterthur",
    "sg:orig_category":"Allgemeiner Hoch U Tiefbau Baugewerbe",
    "sg:phone":"+41 71 966 49 24",
    "sg:postcode":"8404",
    "sg:province":"Z\u00fcrich",
    "wof:name":"Chirivi Gmbh Renovations Und Bauunternehmung",
    "wof:placetype":"venue"
},
  "geometry": {"coordinates":[9.00223,47.490181],"type":"Point"}
}