{
  "type": "Feature",
  "properties": {
    "iso:country":"CH",
    "sg:address":"Hauptstrasse 101",
    "sg:city":"Rorschach",
    "sg:orig_category":"Unclassifiable Establishments",
    "sg:postcode":"9400",
    "sg:province":"St. Gallen",
    "wof:name":"A. Horber, Schule F\u00fcr Manuelle Therapien Manamed",
    "wof:placetype":"venue"
},
  "geometry": {"coordinates":[9.4891452789,47.478969574],"type":"Point"}
}