{
  "type": "Feature",
  "properties": {
    "iso:country":"CH",
    "sg:address":"3920",
    "sg:city":"Zermatt",
    "sg:orig_category":"Primarschulen",
    "sg:phone":"+41 27 952 22 95",
    "sg:postcode":"3920",
    "sg:province":"Valais",
    "wof:name":"Primarschule",
    "wof:placetype":"venue"
},
  "geometry": {"coordinates":[7.8664298058,46.2315216064],"type":"Point"}
}