{
  "type": "Feature",
  "properties": {
    "addr:full":"Oberholzweg 25 Boll Bern 3067",
    "addr:housenumber":"25",
    "addr:postcode":"3067",
    "addr:street":"Oberholzweg",
    "iso:country":"CH",
    "sg:address":"Oberholzweg 25",
    "sg:city":"Boll",
    "sg:orig_category":"Datenverarbeitungsdienste",
    "sg:phone":"+41 61 401 26 77",
    "sg:postcode":"3067",
    "sg:province":"Bern",
    "wof:name":"H\u00e4berli & Weber Informatik Ag",
    "wof:placetype":"venue"
},
  "geometry": {"coordinates":[7.557599,47.516846],"type":"Point"}
}