{
  "type": "Feature",
  "properties": {
    "iso:country":"CH",
    "sg:address":"2926",
    "sg:city":"Boncourt",
    "sg:orig_category":"Gartenbau Herstellung von Konstruktionsteilen, Fertigbauteilen U Ausbauelementen aus Holz",
    "sg:phone":"+41 32 475 52 48",
    "sg:postcode":"2926",
    "sg:province":"Jura",
    "wof:name":"Babey S\u00e0rl",
    "wof:placetype":"venue"
},
  "geometry": {"coordinates":[7.0156798363,47.4972915649],"type":"Point"}
}