{
  "type": "Feature",
  "properties": {
    "iso:country":"CH",
    "sg:address":"Ringgeliweg 3",
    "sg:city":"Wynigen",
    "sg:orig_category":"Gartenbau",
    "sg:phone":"+41 79 420 62 38",
    "sg:postcode":"3472",
    "sg:province":"Bern",
    "wof:name":"Heinrich Gartmann Gartenpflege & Gartenbau",
    "wof:placetype":"venue"
},
  "geometry": {"coordinates":[8.1352176666,47.4444999695],"type":"Point"}
}