{
  "type": "Feature",
  "properties": {
    "iso:country":"CH",
    "sg:address":"Im Bogen 6 8546 Islikon. Postfach",
    "sg:city":"Islikon",
    "sg:classifiers":[
        {
            "category":"Professional",
            "subcategory":"Employment Agencies",
            "type":"Services"
        }
    ],
    "sg:phone":"+41 71 220 33 55",
    "sg:postcode":"8546",
    "sg:province":"Thurgau",
    "sg:tags":[
        "personal",
        "u",
        "stellenvermittlung"
    ],
    "wof:name":"Personal Placement Service Zollinger M.",
    "wof:placetype":"venue"
},
  "geometry": {"coordinates":[8.8409566879,47.54322052],"type":"Point"}
}