{
  "type": "Feature",
  "properties": {
    "iso:country":"CH",
    "sg:address":"Hofackerstrasse 18",
    "sg:city":"Dietikon",
    "sg:orig_category":"Gesundheitswesen",
    "sg:phone":"+41 17405592",
    "sg:postcode":"8953",
    "sg:province":"Z\u00fcrich",
    "wof:name":"Suter Viktor",
    "wof:placetype":"venue"
},
  "geometry": {"coordinates":[8.4128990173,47.3968276978],"type":"Point"}
}