{
  "type": "Feature",
  "properties": {
    "iso:country":"CH",
    "sg:address":"Heimgartenweg 12",
    "sg:city":"Allschwil",
    "sg:orig_category":"Ern\u00e4hrungsberatung",
    "sg:phone":"+41 61 481 81 60",
    "sg:postcode":"4123",
    "sg:province":"Basel-Landschaft",
    "wof:name":"Pia Brodbeck Ern\u00e4hrungsberatung",
    "wof:placetype":"venue"
},
  "geometry": {"coordinates":[7.552670002,47.5544776917],"type":"Point"}
}