{
  "type": "Feature",
  "properties": {
    "iso:country":"CH",
    "sg:address":"8737",
    "sg:city":"Gommiswald",
    "sg:orig_category":"Vereine Gesang",
    "sg:postcode":"8737",
    "sg:province":"St. Gallen",
    "wof:name":"Gemischter Chor Gommiswald",
    "wof:placetype":"venue"
},
  "geometry": {"coordinates":[9.0180501938,47.2323799133],"type":"Point"}
}