{
  "type": "Feature",
  "properties": {
    "iso:country":"CH",
    "sg:address":"Verdel Rue Du 8 1453 Bullet. Postfach",
    "sg:city":"Bullet",
    "sg:orig_category":"Detailhandel mit M\u00f6beln U Haushaltsgegenst\u00e4nden",
    "sg:phone":"+41 26 919 55 10",
    "sg:postcode":"1453",
    "sg:province":"Vaud",
    "wof:name":"Agendec Sa",
    "wof:placetype":"venue"
},
  "geometry": {"coordinates":[6.5547862053,46.8312492371],"type":"Point"}
}