{
  "type": "Feature",
  "properties": {
    "iso:country":"CH",
    "sg:address":"1233 Bernex Case Postale 358",
    "sg:city":"Bernex",
    "sg:orig_category":"Sportvereine Sch\u00fctzen",
    "sg:postcode":"1233",
    "sg:province":"Gen\u00e8ve",
    "wof:name":"St\u00e9 De Tir Militaire Le Cr\u00eat",
    "wof:placetype":"venue"
},
  "geometry": {"coordinates":[6.9104480743,46.6096229553],"type":"Point"}
}