{
  "type": "Feature",
  "properties": {
    "iso:country":"CH",
    "sg:address":"Alte Landstrasse 19 C",
    "sg:city":"Islikon",
    "sg:orig_category":"Instandhaltung U Reparatur von Automobilen",
    "sg:phone":"+41 52 375 21 32",
    "sg:postcode":"8546",
    "sg:province":"Thurgau",
    "wof:name":"Roland N\u00fcssli Fahrzeug-experte",
    "wof:placetype":"venue"
},
  "geometry": {"coordinates":[8.8445396423,47.5478019714],"type":"Point"}
}