{
  "type": "Feature",
  "properties": {
    "iso:country":"CH",
    "sg:address":"Speiserstrasse 46",
    "sg:city":"Olten",
    "sg:orig_category":"Vorschulen, Kinderg\u00e4rten",
    "sg:phone":"+41 62 212 23 60",
    "sg:postcode":"4600",
    "sg:province":"Solothurn",
    "wof:name":"Kindergarten",
    "wof:placetype":"venue"
},
  "geometry": {"coordinates":[7.9207091331,47.3456420898],"type":"Point"}
}