{
  "type": "Feature",
  "properties": {
    "iso:country":"CH",
    "sg:address":"Rue De La Gaine 1",
    "sg:city":"Chez-le-bart",
    "sg:classifiers":[
        {
            "category":"Shopping",
            "subcategory":"Computers & Home Electronics",
            "type":"Retail Goods"
        }
    ],
    "sg:phone":"+41 32 835 24 34",
    "sg:postcode":"2025",
    "sg:province":"Neuch\u00e2tel",
    "sg:tags":[
        "equipment",
        "electrical",
        "component",
        "electric",
        "electronic"
    ],
    "wof:name":"Micro-concept E.weise",
    "wof:placetype":"venue"
},
  "geometry": {"coordinates":[6.7860870361,46.900554657],"type":"Point"}
}