{
  "type": "Feature",
  "properties": {
    "iso:country":"CH",
    "sg:address":"Route De Moutier 109",
    "sg:city":"Del\u00e9mont",
    "sg:orig_category":"Grosshandel mit Wein U Spirituosen Grosshandel mit sonstigen Getr\u00e4nken",
    "sg:postcode":"2800",
    "sg:province":"Jura",
    "wof:name":"Feldschl\u00f6sschen Boissons Sa",
    "wof:placetype":"venue"
},
  "geometry": {"coordinates":[6.8051810265,47.0893974304],"type":"Point"}
}