{
  "type": "Feature",
  "properties": {
    "iso:country":"CH",
    "sg:address":"Im Moos 16",
    "sg:city":"Interlaken",
    "sg:orig_category":"Instandhaltung U Reparatur von Automobilen",
    "sg:phone":"+41 33 822 71 88",
    "sg:postcode":"3800",
    "sg:province":"Bern",
    "wof:name":"Kaufmann Auto & Pneu Ag",
    "wof:placetype":"venue"
},
  "geometry": {"coordinates":[7.8842949867,46.6891174316],"type":"Point"}
}