{
  "type": "Feature",
  "properties": {
    "addr:full":"Wichel Fieschertal Valais 3984",
    "addr:postcode":"3984",
    "iso:country":"CH",
    "sg:address":"Wichel",
    "sg:city":"Fieschertal",
    "sg:orig_category":"Allgemeiner Hochbau Strassenbau",
    "sg:phone":"+41 79 508 94 13",
    "sg:postcode":"3984",
    "sg:province":"Valais",
    "wof:name":"Bortis Bau Gmbh",
    "wof:placetype":"venue"
},
  "geometry": {"coordinates":[8.145614,46.421169],"type":"Point"}
}