{
  "type": "Feature",
  "properties": {
    "iso:country":"CH",
    "sg:address":"Rue De B\u00e2le 28",
    "sg:city":"Gen\u00e8ve",
    "sg:classifiers":[
        {
            "category":"Communications",
            "subcategory":"Film & Video Production",
            "type":"Services"
        }
    ],
    "sg:phone":"+41 22 741 47 47",
    "sg:postcode":"1201",
    "sg:province":"Gen\u00e8ve",
    "sg:tags":[
        "videofilmherstellung",
        "u"
    ],
    "wof:name":"Intermezzo Films Sa",
    "wof:placetype":"venue"
},
  "geometry": {"coordinates":[6.1492199898,46.2132492065],"type":"Point"}
}