{
  "type": "Feature",
  "properties": {
    "iso:country":"CH",
    "sg:address":"Chemin De Maillefer 38",
    "sg:city":"Mont-sur-lausanne",
    "sg:orig_category":"Herstellung von Brot U Backwaren Landwirtschaft, Jagd U damit verbundene Dienstleistungen",
    "sg:phone":"+41 21 647 64 64",
    "sg:postcode":"1052",
    "sg:province":"Vaud",
    "wof:name":"Polli A. Sa",
    "wof:placetype":"venue"
},
  "geometry": {"coordinates":[6.6283020973,46.5423164368],"type":"Point"}
}