{
  "type": "Feature",
  "properties": {
    "iso:country":"CH",
    "sg:address":"Langelenstrasse 12",
    "sg:city":"Herisau",
    "sg:orig_category":"Vereine Harmonika and Akkordeon",
    "sg:phone":"+41 71 351 39 79",
    "sg:postcode":"9100",
    "sg:province":"Appenzell Ausserrhoden",
    "wof:name":"Harmonika Orchester Herisau",
    "wof:placetype":"venue"
},
  "geometry": {"coordinates":[9.282286644,47.3746070862],"type":"Point"}
}