{
  "type": "Feature",
  "properties": {
    "iso:country":"CH",
    "sg:address":"Breitestrasse 96 8400 Winterthur. Postfach",
    "sg:city":"Winterthur",
    "sg:orig_category":"Non-Classified Establishments",
    "sg:phone":"+41 52 202 40 71",
    "sg:postcode":"8400",
    "sg:province":"Z\u00fcrich",
    "wof:name":"D\u00f6beli Peter + Partner Kommunikations-beratung, Bes. Media-beratung Im Bereich Werbung",
    "wof:placetype":"venue"
},
  "geometry": {"coordinates":[8.7230615616,47.4907188416],"type":"Point"}
}