{
  "type": "Feature",
  "properties": {
    "iso:country":"CH",
    "sg:address":"Aie Via Delle 17",
    "sg:city":"Lugano",
    "sg:orig_category":"Grosshandel mit sonstigen Gebrauchs U Verbrauchsg\u00fctern",
    "sg:phone":"+41 79 438 11 64",
    "sg:postcode":"6900",
    "sg:province":"Ticino",
    "wof:name":"Labotest Ag",
    "wof:placetype":"venue"
},
  "geometry": {"coordinates":[8.8190374374,47.3039855957],"type":"Point"}
}