{
  "type": "Feature",
  "properties": {
    "iso:country":"CH",
    "sg:address":"Eschenstrasse 9",
    "sg:city":"Goldach",
    "sg:orig_category":"Arztpraxen",
    "sg:phone":"+41 71 278 74 22",
    "sg:postcode":"9403",
    "sg:province":"St. Gallen",
    "wof:name":"Dr.med.roman Sieber Spezialarzt Fmh",
    "wof:placetype":"venue"
},
  "geometry": {"coordinates":[9.365459,47.422256],"type":"Point"}
}