{
  "type": "Feature",
  "properties": {
    "iso:country":"CH",
    "sg:address":"Erlenstrasse 23",
    "sg:city":"Birsfelden",
    "sg:orig_category":"Vereine Diverse",
    "sg:phone":"+41 61 612 71 10",
    "sg:postcode":"4127",
    "sg:province":"Basel-Landschaft",
    "wof:name":"Wertli Brothers Zufikon",
    "wof:placetype":"venue"
},
  "geometry": {"coordinates":[7.6308221817,47.5493888855],"type":"Point"}
}