{
  "type": "Feature",
  "properties": {
    "iso:country":"CH",
    "sg:address":"Chamer Fussweg 11",
    "sg:city":"Zug",
    "sg:orig_category":"Korrespondenz U Nachrichtenb\u00fcros, selbst\u00e4ndige Journalisten",
    "sg:postcode":"6300",
    "sg:province":"Zug",
    "wof:name":"Stockfood Bildagentur Ag",
    "wof:placetype":"venue"
},
  "geometry": {"coordinates":[8.5019950867,47.1751441956],"type":"Point"}
}