{
  "type": "Feature",
  "properties": {
    "iso:country":"CH",
    "sg:address":"Hotel Eden 3822 Lauterbrunnen. Postfach",
    "sg:city":"Wengen",
    "sg:classifiers":[
        {
            "category":"Travel",
            "subcategory":"Hotels & Motels",
            "type":"Entertainment"
        }
    ],
    "sg:postcode":"3823",
    "sg:province":"Bern",
    "sg:tags":[
        "hotels",
        "mit",
        "restaurant"
    ],
    "wof:name":"Bucher Kerstin, Hotel Eden, Wengen",
    "wof:placetype":"venue"
},
  "geometry": {"coordinates":[7.9075479507,46.5979499817],"type":"Point"}
}