{
  "type": "Feature",
  "properties": {
    "iso:country":"CH",
    "sg:address":"Place Centrale 1936 Verbier 1 Case Postale 175",
    "sg:city":"Verbier",
    "sg:orig_category":"Architektur U Ingenieurb\u00fcros Architekturb\u00fcros",
    "sg:phone":"+41 27 771 22 87",
    "sg:postcode":"1936",
    "sg:province":"Valais",
    "wof:name":"Architecture Et Engineering Martin Et Michellod Sa",
    "wof:placetype":"venue"
},
  "geometry": {"coordinates":[7.22874,46.096268],"type":"Point"}
}