{
  "type": "Feature",
  "properties": {
    "iso:country":"CH",
    "sg:address":"Seehaldenstrasse 28",
    "sg:city":"Rorschach",
    "sg:orig_category":"Fussreflexzonenmassage",
    "sg:phone":"+41 71 855 36 79",
    "sg:postcode":"9400",
    "sg:province":"St. Gallen",
    "wof:name":"Elisabeth Wonisch Fussreflexzonen-massagen",
    "wof:placetype":"venue"
},
  "geometry": {"coordinates":[9.4952001572,47.4779396057],"type":"Point"}
}