{
  "type": "Feature",
  "properties": {
    "iso:country":"CH",
    "sg:address":"Kistlerstrasse 14",
    "sg:city":"Bolligen",
    "sg:orig_category":"Fahrschulen, Flugschulen",
    "sg:phone":"+41 31 922 41 86",
    "sg:postcode":"3065",
    "sg:province":"Bern",
    "wof:name":"Vladimir Fabian Autofahrschule",
    "wof:placetype":"venue"
},
  "geometry": {"coordinates":[7.4969120026,46.9738960266],"type":"Point"}
}