{
  "type": "Feature",
  "properties": {
    "iso:country":"CH",
    "sg:address":"Weidenweg 10",
    "sg:city":"Birsfelden",
    "sg:orig_category":"Installation von Heizungs, L\u00fcftungs U Klimaanlagen",
    "sg:phone":"+41 71 923 84 53",
    "sg:postcode":"4127",
    "sg:province":"Basel-Landschaft",
    "wof:name":"Jandl Haushaltger\u00e4te Klima-l\u00fcftung",
    "wof:placetype":"venue"
},
  "geometry": {"coordinates":[9.0347585678,47.4505004883],"type":"Point"}
}