{
  "type": "Feature",
  "properties": {
    "iso:country":"CH",
    "sg:address":"Rainweg 4",
    "sg:city":"Brittnau",
    "sg:orig_category":"Gartenbau",
    "sg:phone":"+41 62 751 60 31",
    "sg:postcode":"4805",
    "sg:province":"Aargau",
    "wof:name":"M\u00fcller & Frey Gartenbau",
    "wof:placetype":"venue"
},
  "geometry": {"coordinates":[7.946158886,47.254863739],"type":"Point"}
}