{
  "type": "Feature",
  "properties": {
    "iso:country":"CH",
    "sg:address":"Eigasse 3",
    "sg:city":"H\u00e4gendorf",
    "sg:classifiers":[
        {
            "category":"Utilities",
            "subcategory":"Cable",
            "type":"Services"
        }
    ],
    "sg:phone":"+41 62 216 27 27",
    "sg:postcode":"4614",
    "sg:province":"Solothurn",
    "sg:tags":[
        "fibre",
        "assembly",
        "optic"
    ],
    "wof:name":"Elektro-f\u00fcrst Ag",
    "wof:placetype":"venue"
},
  "geometry": {"coordinates":[7.8421292305,47.3337097168],"type":"Point"}
}