{
  "type": "Feature",
  "properties": {
    "addr:full":"7556 Ramosch Graubunden 7556",
    "addr:housenumber":"7556",
    "addr:postcode":"7556",
    "addr:street":"Ramosch Graubunden",
    "iso:country":"CH",
    "sg:address":"7556",
    "sg:city":"Ramosch",
    "sg:orig_category":"Abbruch U Sprenggewerbe, Erdbewegungsarbeiten Gewinnung von Kies U Sand",
    "sg:phone":"+41 81 866 34 04",
    "sg:postcode":"7556",
    "sg:province":"Graubunden",
    "wof:name":"Koch Gebr.",
    "wof:placetype":"venue"
},
  "geometry": {"coordinates":[10.381161,46.833279],"type":"Point"}
}