{
  "type": "Feature",
  "properties": {
    "iso:country":"CH",
    "sg:address":"Burisholzweg 127",
    "sg:city":"Niederscherli",
    "sg:orig_category":"Sonstige Aktivit\u00e4ten der nicht-\u00e4rztlichen Medizinalberufe",
    "sg:phone":"+41 31 849 22 32",
    "sg:postcode":"3145",
    "sg:province":"Bern",
    "wof:name":"Ursula Rawyler Atemtherapie",
    "wof:placetype":"venue"
},
  "geometry": {"coordinates":[7.3942909241,46.8858375549],"type":"Point"}
}