{
  "type": "Feature",
  "properties": {
    "iso:country":"CH",
    "sg:address":"Poststrasse 2",
    "sg:city":"Solothurn",
    "sg:orig_category":"Architekturb\u00fcros",
    "sg:phone":"+41 32 622 92 43",
    "sg:postcode":"4500",
    "sg:province":"Solothurn",
    "wof:name":"Staub & Partner Architekturb\u00fcro",
    "wof:placetype":"venue"
},
  "geometry": {"coordinates":[7.534298,47.205856],"type":"Point"}
}