{
  "type": "Feature",
  "properties": {
    "iso:country":"CH",
    "sg:address":"Herrenmoosweg 33",
    "sg:city":"Nidau",
    "sg:orig_category":"Zahnarztpraxen",
    "sg:phone":"+41 32 331 83 83",
    "sg:postcode":"2560",
    "sg:province":"Bern",
    "wof:name":"Dr. Med. Dent. Tino Borter Zahnarzt",
    "wof:placetype":"venue"
},
  "geometry": {"coordinates":[7.2346191406,47.1216621399],"type":"Point"}
}