{
  "type": "Feature",
  "properties": {
    "iso:country":"CH",
    "sg:address":"Haldenstrasse 11",
    "sg:city":"Luzern",
    "sg:orig_category":"Arztpraxen",
    "sg:phone":"+41 41 410 16 60",
    "sg:postcode":"6006",
    "sg:province":"Luzern",
    "wof:name":"Dr.med.josef Kaufmann Spezialarzt Fmh",
    "wof:placetype":"venue"
},
  "geometry": {"coordinates":[8.314196,47.055],"type":"Point"}
}