{
  "type": "Feature",
  "properties": {
    "iso:country":"CH",
    "sg:address":"Chemin Saint-hubert 41 1950 Sion Case Postale",
    "sg:city":"Sion",
    "sg:classifiers":[
        {
            "category":"Professional",
            "subcategory":"Employment Agencies",
            "type":"Services"
        }
    ],
    "sg:phone":"+41 27 322 00 22",
    "sg:postcode":"1951",
    "sg:province":"Valais",
    "sg:tags":[
        "personal",
        "u",
        "stellenvermittlung"
    ],
    "wof:name":"Emploi 2000 S\u00e0rl",
    "wof:placetype":"venue"
},
  "geometry": {"coordinates":[7.3526082039,46.222743988],"type":"Point"}
}