{
  "type": "Feature",
  "properties": {
    "iso:country":"CH",
    "sg:address":"Chemin De L'ecu 13 1214 Vernier. Postfach",
    "sg:city":"Vernier",
    "sg:orig_category":"Stukkateurgewerbe, Gipserei U Verputzerei",
    "sg:postcode":"1214",
    "sg:province":"Gen\u00e8ve",
    "wof:name":"Plafonds Services S\u00e0rl",
    "wof:placetype":"venue"
},
  "geometry": {"coordinates":[6.1081490517,46.2091598511],"type":"Point"}
}