{
  "type": "Feature",
  "properties": {
    "iso:country":"CH",
    "sg:address":"Steinackerstrasse 35",
    "sg:city":"Kloten",
    "sg:orig_category":"Non-Classified Establishments",
    "sg:postcode":"8302",
    "sg:province":"Z\u00fcrich",
    "wof:name":"7 Pasta Pizzakurier Gmbh",
    "wof:placetype":"venue"
},
  "geometry": {"coordinates":[8.6005163193,47.4484062195],"type":"Point"}
}