{
  "type": "Feature",
  "properties": {
    "iso:country":"CH",
    "sg:address":"Bachmattstrasse 41",
    "sg:city":"Z\u00fcrich",
    "sg:orig_category":"Landwirtschaftliche Maschinen Wartung and Reparatur Werkzeugschleifereien",
    "sg:phone":"+41 14320814",
    "sg:postcode":"8048",
    "sg:province":"Z\u00fcrich",
    "wof:name":"E. N\u00e4geli Gmbh Feinschleiferei, Gartenger\u00e4te",
    "wof:placetype":"venue"
},
  "geometry": {"coordinates":[8.4842061996,47.3899154663],"type":"Point"}
}