{
  "type": "Feature",
  "properties": {
    "iso:country":"CH",
    "sg:address":"Hammerstrasse 10",
    "sg:city":"Basel",
    "sg:orig_category":"Unclassifiable Establishments",
    "sg:postcode":"4058",
    "sg:province":"Basel-Stadt",
    "wof:name":"Bridge2think Ag",
    "wof:placetype":"venue"
},
  "geometry": {"coordinates":[7.5984349251,47.5596504211],"type":"Point"}
}