{
  "type": "Feature",
  "properties": {
    "iso:country":"CH",
    "sg:address":"Rue De Lausanne 39",
    "sg:city":"Sion",
    "sg:orig_category":"Zahnarztpraxen",
    "sg:phone":"+41 27 322 47 58",
    "sg:postcode":"1950",
    "sg:province":"Valais",
    "wof:name":"Dr M\u00e9d.dent.christian De Roten M\u00e9decin-dentiste",
    "wof:placetype":"venue"
},
  "geometry": {"coordinates":[7.3565797806,46.2316856384],"type":"Point"}
}