{
  "type": "Feature",
  "properties": {
    "iso:country":"CH",
    "sg:address":"Looslistrasse 16",
    "sg:city":"Bern",
    "sg:orig_category":"Berufsbildende weiterf\u00fchrende Schulen",
    "sg:phone":"+41 71 222 62 14",
    "sg:postcode":"3027",
    "sg:province":"Bern",
    "wof:name":"Schweiz.m\u00fcllerei-fachschule St.gallen",
    "wof:placetype":"venue"
},
  "geometry": {"coordinates":[9.3714,47.425358],"type":"Point"}
}