{
  "type": "Feature",
  "properties": {
    "iso:country":"CH",
    "sg:address":"Heiligkreuz 42 9490 Vaduz. Postfach 1117",
    "sg:city":"Vaduz",
    "sg:orig_category":"Unternehmensberatung",
    "sg:phone":"+41 71 944 29 04",
    "sg:postcode":"9490",
    "wof:name":"Advisum Wirtschaftspr\u00fcfung & Steuerberatung",
    "wof:placetype":"venue"
},
  "geometry": {"coordinates":[9.1010293961,47.4753341675],"type":"Point"}
}