{
  "type": "Feature",
  "properties": {
    "iso:country":"CH",
    "sg:address":"Aarauerstrasse 8",
    "sg:city":"Wildegg",
    "sg:orig_category":"Handel mit Automobilen",
    "sg:phone":"+41 55 410 75 16",
    "sg:postcode":"5103",
    "sg:province":"Aargau",
    "wof:name":"Mc Modern-cars Gmbh",
    "wof:placetype":"venue"
},
  "geometry": {"coordinates":[8.7852945328,47.2015342712],"type":"Point"}
}