{
  "type": "Feature",
  "properties": {
    "iso:country":"CH",
    "sg:address":"Friedhofstrasse 15",
    "sg:city":"Romanshorn",
    "sg:orig_category":"Handelsvermittlung U Grosshandel Sonstiger Grosshandel",
    "sg:postcode":"8590",
    "sg:province":"Thurgau",
    "wof:name":"Boro Handels Ag",
    "wof:placetype":"venue"
},
  "geometry": {"coordinates":[9.3741855621,47.5609436035],"type":"Point"}
}