{
  "type": "Feature",
  "properties": {
    "iso:country":"CH",
    "sg:address":"Route De La Gare 34",
    "sg:city":"Penthalaz",
    "sg:orig_category":"Detailhandel mit Fleisch U Fleischwaren",
    "sg:phone":"+41 21 861 08 38",
    "sg:postcode":"1305",
    "sg:province":"Vaud",
    "wof:name":"G\u00e9rard Schmid Boucherie",
    "wof:placetype":"venue"
},
  "geometry": {"coordinates":[6.5256910324,46.6106643677],"type":"Point"}
}