{
  "type": "Feature",
  "properties": {
    "iso:country":"CH",
    "sg:address":"Dumont Rue Etienne- 20 1204 Gen\u00e8ve. Postfach",
    "sg:city":"Gen\u00e8ve",
    "sg:orig_category":"Interessenvertretungen",
    "sg:postcode":"1201",
    "sg:province":"Gen\u00e8ve",
    "wof:name":"Fondation De L'encyclop\u00e9die De Gen\u00e8ve",
    "wof:placetype":"venue"
},
  "geometry": {"coordinates":[6.1492218971,46.199092865],"type":"Point"}
}