{
  "type": "Feature",
  "properties": {
    "iso:country":"CH",
    "sg:address":"Veia Sandeilas 11",
    "sg:city":"Savognin",
    "sg:orig_category":"Zahnarztpraxen",
    "sg:phone":"+41 79 433 88 44",
    "sg:postcode":"7460",
    "sg:province":"Graubunden",
    "wof:name":"Dr.med.dent.christer Johansson Zahnarzt",
    "wof:placetype":"venue"
},
  "geometry": {"coordinates":[9.5948963165,46.5973587036],"type":"Point"}
}