{
  "type": "Feature",
  "properties": {
    "iso:country":"CH",
    "sg:address":"1428",
    "sg:city":"Mutrux",
    "sg:orig_category":"Autospenglereien",
    "sg:phone":"+41 24 434 18 18",
    "sg:postcode":"1428",
    "sg:province":"Vaud",
    "wof:name":"Carrosserie Du Mutrux",
    "wof:placetype":"venue"
},
  "geometry": {"coordinates":[6.727121,46.883614],"type":"Point"}
}