{
  "type": "Feature",
  "properties": {
    "iso:country":"CH",
    "sg:address":"Untere Matt",
    "sg:city":"Sternenberg",
    "sg:orig_category":"Elektroinstallation",
    "sg:phone":"+41 52 386 28 83",
    "sg:postcode":"8499",
    "sg:province":"Z\u00fcrich",
    "wof:name":"Fidel Sigg Elektromontagen",
    "wof:placetype":"venue"
},
  "geometry": {"coordinates":[8.9102401733,47.3872947693],"type":"Point"}
}