{
  "type": "Feature",
  "properties": {
    "iso:country":"CH",
    "sg:address":"Z\u00fcrcherstrasse 115",
    "sg:city":"Neuenhof",
    "sg:classifiers":[
        {
            "category":"Banks & Credit Unions",
            "subcategory":"Bank",
            "type":"Services"
        }
    ],
    "sg:phone":"+41 4156862071",
    "sg:postcode":"5432",
    "sg:province":"Aargau",
    "wof:name":"Gewerbebank Baden",
    "wof:placetype":"venue"
},
  "geometry": {"coordinates":[8.3273954391,47.4497299194],"type":"Point"}
}