{
  "type": "Feature",
  "properties": {
    "addr:full":"Schachenstrasse 19 B\u00e4tterkinden Bern 3315",
    "addr:housenumber":"19",
    "addr:postcode":"3315",
    "addr:street":"Schachenstrasse",
    "iso:country":"CH",
    "sg:address":"Schachenstrasse 19",
    "sg:city":"B\u00e4tterkinden",
    "sg:orig_category":"Detailhandel mit Bekleidung Versandhandel",
    "sg:phone":"+41 32 665 26 04",
    "sg:postcode":"3315",
    "sg:province":"Bern",
    "wof:name":"Werner Frutiger Textilversand",
    "wof:placetype":"venue"
},
  "geometry": {"coordinates":[7.542923,47.134178],"type":"Point"}
}