{
  "type": "Feature",
  "properties": {
    "iso:country":"CH",
    "sg:address":"6817",
    "sg:city":"Maroggia",
    "sg:orig_category":"Zimmerei, Dachdeckerei, Bauspenglerei U Abdichtung Zimmerei, Ingenieurholzbau",
    "sg:phone":"+41 91 649 95 68",
    "sg:postcode":"6817",
    "sg:province":"Ticino",
    "wof:name":"Realini Carpenteria & Copertura Tetti Sa",
    "wof:placetype":"venue"
},
  "geometry": {"coordinates":[8.9697504044,45.9363708496],"type":"Point"}
}