{
  "type": "Feature",
  "properties": {
    "iso:country":"CH",
    "sg:address":"Frauenfelderstr. 39",
    "sg:city":"Matzingen",
    "sg:orig_category":"Instandhaltung U Reparatur von Automobilen",
    "sg:postcode":"9548",
    "sg:province":"Thurgau",
    "wof:name":"Kummer Ernst, Autospenglerei.",
    "wof:placetype":"venue"
},
  "geometry": {"coordinates":[8.9288063049,47.5226707458],"type":"Point"}
}