{
  "type": "Feature",
  "properties": {
    "iso:country":"CH",
    "sg:address":"Gartenstrasse 46",
    "sg:city":"Oberengstringen",
    "sg:orig_category":"G\u00fcterbef\u00f6rderung im Strassenverkehr",
    "sg:phone":"+41 17503058",
    "sg:postcode":"8102",
    "sg:province":"Z\u00fcrich",
    "wof:name":"Mangold Urs, Transporte",
    "wof:placetype":"venue"
},
  "geometry": {"coordinates":[8.4577198029,47.4120101929],"type":"Point"}
}