{
  "type": "Feature",
  "properties": {
    "iso:country":"CH",
    "sg:address":"Rampe De La Gare 5",
    "sg:city":"Versoix",
    "sg:orig_category":"Detailhandel mit Blumen U Pflanzen Fachdetailhandel in Verkaufsr\u00e4umen",
    "sg:phone":"+41 22 755 50 60",
    "sg:postcode":"1290",
    "sg:province":"Gen\u00e8ve",
    "wof:name":"Pascale & Nathalie Brack Flor\u00e9al Magasin De Fleurs",
    "wof:placetype":"venue"
},
  "geometry": {"coordinates":[6.167151,46.279335],"type":"Point"}
}