{
  "type": "Feature",
  "properties": {
    "iso:country":"CH",
    "sg:address":"Blatten",
    "sg:city":"Oberegg",
    "sg:orig_category":"Detailhandel mit Milcherzeugnissen U Eiern Verarbeitung von Milch",
    "sg:phone":"+41 71 891 22 40",
    "sg:postcode":"9413",
    "sg:province":"Appenzell Innerhoden",
    "wof:name":"Anton Geiger K\u00e4serei",
    "wof:placetype":"venue"
},
  "geometry": {"coordinates":[9.5754804611,47.4287719727],"type":"Point"}
}