{
  "type": "Feature",
  "properties": {
    "iso:country":"CH",
    "sg:address":"Feldweg 8 4242 Laufen. Postfach",
    "sg:city":"Laufen",
    "sg:orig_category":"Sonstiger spezialisierter Hoch U Tiefbau",
    "sg:postcode":"4242",
    "sg:province":"Basel-Landschaft",
    "wof:name":"Franz Ludwig, Kamin Und Chemin\u00e9ebau",
    "wof:placetype":"venue"
},
  "geometry": {"coordinates":[7.5127310753,47.4225120544],"type":"Point"}
}