{
  "type": "Feature",
  "properties": {
    "iso:country":"CH",
    "sg:address":"3920",
    "sg:city":"Zermatt",
    "sg:orig_category":"Vermietung U Verpachtung von eigenen Immobilien",
    "sg:postcode":"3920",
    "sg:province":"Valais",
    "wof:name":"Raffy, Immobilien Ag Zermatt",
    "wof:placetype":"venue"
},
  "geometry": {"coordinates":[7.7484002113,46.024143219],"type":"Point"}
}