{
  "type": "Feature",
  "properties": {
    "iso:country":"CH",
    "sg:address":"Bomertstrasse 9",
    "sg:city":"Altenrhein",
    "sg:orig_category":"Softwareentwicklung U beratung",
    "sg:phone":"+41 79 646 24 92",
    "sg:postcode":"9423",
    "sg:province":"St. Gallen",
    "wof:name":"Econsit Gmbh Informatik-dienstleistungen",
    "wof:placetype":"venue"
},
  "geometry": {"coordinates":[8.4118499756,47.4228363037],"type":"Point"}
}