{
  "type": "Feature",
  "properties": {
    "iso:country":"CH",
    "sg:address":"Etzelstrasse 60",
    "sg:city":"Freienbach",
    "sg:orig_category":"Detailhandel mit elektrischen Haushalts-,Radio U Fernsehger\u00e4ten sowie Musikinstrumenten",
    "sg:postcode":"8807",
    "sg:province":"Schwyz",
    "wof:name":"Videorent Ag",
    "wof:placetype":"venue"
},
  "geometry": {"coordinates":[8.7810649872,47.1966133118],"type":"Point"}
}