{
  "type": "Feature",
  "properties": {
    "iso:country":"CH",
    "sg:address":"Hauptgasse 19",
    "sg:city":"Murten",
    "sg:classifiers":[
        {
            "category":"Restaurant",
            "type":"Food & Drink"
        }
    ],
    "sg:phone":"+41 26 670 22 40",
    "sg:postcode":"3280",
    "sg:province":"Fribourg",
    "wof:name":"Restaurant Eintracht",
    "wof:placetype":"venue"
},
  "geometry": {"coordinates":[7.1167578697,46.9282608032],"type":"Point"}
}