{
  "type": "Feature",
  "properties": {
    "iso:country":"CH",
    "sg:address":"Aeschenvorstadt 37",
    "sg:city":"Basel",
    "sg:orig_category":"Personal U Stellenvermittlung Unternehmensberatung",
    "sg:phone":"+41 61 717 99 88",
    "sg:postcode":"4051",
    "sg:province":"Basel-Stadt",
    "wof:name":"Induserv Industrial Services Ltd",
    "wof:placetype":"venue"
},
  "geometry": {"coordinates":[7.5900878906,47.4933700562],"type":"Point"}
}