{
  "type": "Feature",
  "properties": {
    "iso:country":"CH",
    "sg:address":"Furtstrasse 3",
    "sg:city":"Oberhittnau",
    "sg:orig_category":"Herstellung von Ger\u00e4ten der Elektrizit\u00e4tserzeugung, -verteilung u.\u00e4. -Herstellung von sonstigen elek",
    "sg:phone":"+41 19501414",
    "sg:postcode":"8335",
    "sg:province":"Z\u00fcrich",
    "wof:name":"Alphatronic Ag",
    "wof:placetype":"venue"
},
  "geometry": {"coordinates":[8.8220977783,47.360912323],"type":"Point"}
}