{
  "type": "Feature",
  "properties": {
    "iso:country":"CH",
    "sg:address":"Oesliweg 4 4410 Liestal. Postfach",
    "sg:city":"Liestal",
    "sg:orig_category":"Erwachsenenbildung U Unterricht",
    "sg:phone":"+41 61 901 34 09",
    "sg:postcode":"4410",
    "sg:province":"Basel-Landschaft",
    "wof:name":"B. C. Sprachdienst Cierpka Barbara Sprachunterricht; \u00dcbersetzungen",
    "wof:placetype":"venue"
},
  "geometry": {"coordinates":[7.7308368683,47.4934005737],"type":"Point"}
}