{
  "type": "Feature",
  "properties": {
    "iso:country":"CH",
    "sg:address":"Chesa Chamuotsch",
    "sg:city":"Celerina",
    "sg:orig_category":"Sportvereine Eissport Curling",
    "sg:postcode":"7505",
    "sg:province":"Graubunden",
    "wof:name":"C.c.celerina-saluver",
    "wof:placetype":"venue"
},
  "geometry": {"coordinates":[9.8600702286,46.5126800537],"type":"Point"}
}