{
  "type": "Feature",
  "properties": {
    "iso:country":"CH",
    "sg:address":"Greyerzstrasse 24",
    "sg:city":"Bern",
    "sg:orig_category":"Architektur U Ingenieurb\u00fcros",
    "sg:postcode":"3013",
    "sg:province":"Bern",
    "wof:name":"Weiss Arthur",
    "wof:placetype":"venue"
},
  "geometry": {"coordinates":[8.858714,47.660702],"type":"Point"}
}