{
  "type": "Feature",
  "properties": {
    "iso:country":"CH",
    "sg:address":"Riehenstrasse 43 4058 Basel. Postfach",
    "sg:city":"Basel",
    "sg:orig_category":"Erschliessung von Grundst\u00fccken",
    "sg:postcode":"4021",
    "wof:name":"Genossenschaft Gl\u00f6cklihof",
    "wof:placetype":"venue"
},
  "geometry": {"coordinates":[7.5990409851,47.561466217],"type":"Point"}
}