{
  "type": "Feature",
  "properties": {
    "iso:country":"CH",
    "sg:address":"Heimst\u00e4ttenweg 8",
    "sg:city":"Neftenbach",
    "sg:orig_category":"Advokaturb\u00fcros",
    "sg:phone":"+41 52 301 03 07",
    "sg:postcode":"8413",
    "sg:province":"Z\u00fcrich",
    "wof:name":"J\u00fcrg B\u00fcgler Advokaturb\u00fcro",
    "wof:placetype":"venue"
},
  "geometry": {"coordinates":[8.660525,47.51836],"type":"Point"}
}