{
  "type": "Feature",
  "properties": {
    "iso:country":"CH",
    "sg:address":"Obere Br\u00fchlstrasse 4 4800 Zofingen. Postfach 123",
    "sg:city":"Zofingen",
    "sg:orig_category":"Pensionskassen",
    "sg:postcode":"4800",
    "sg:province":"Aargau",
    "wof:name":"F\u00fcrsorgefonds Lehmann Ag",
    "wof:placetype":"venue"
},
  "geometry": {"coordinates":[7.944021225,47.284538269],"type":"Point"}
}