{
  "type": "Feature",
  "properties": {
    "iso:country":"CH",
    "sg:address":"Wellhauserweg 31",
    "sg:city":"Frauenfeld",
    "sg:orig_category":"Non-Classified Establishments",
    "sg:postcode":"8500",
    "sg:province":"Thurgau",
    "wof:name":"Deluxe Financial Planing Sousa Und Frei",
    "wof:placetype":"venue"
},
  "geometry": {"coordinates":[8.9148197174,47.5655326843],"type":"Point"}
}