{
  "type": "Feature",
  "properties": {
    "iso:country":"CH",
    "sg:address":"Avenue Louis-ruchonnet 30",
    "sg:city":"Lausanne",
    "sg:orig_category":"Konsulate",
    "sg:phone":"+41 27 480 32 10",
    "sg:postcode":"1003",
    "sg:province":"Vaud",
    "wof:name":"Consulat De Grande-bretagne",
    "wof:placetype":"venue"
},
  "geometry": {"coordinates":[7.5199689865,46.3104286194],"type":"Point"}
}