{
  "type": "Feature",
  "properties": {
    "iso:country":"CH",
    "sg:address":"Riedackerstrasse 19",
    "sg:city":"R\u00fcmlang",
    "sg:orig_category":"Instandhaltung U Reparatur von Automobilen",
    "sg:phone":"+41 18170833",
    "sg:postcode":"8153",
    "sg:province":"Z\u00fcrich",
    "wof:name":"Fritz Walthert Autosattlerei",
    "wof:placetype":"venue"
},
  "geometry": {"coordinates":[8.5227298737,47.4624671936],"type":"Point"}
}