{
  "type": "Feature",
  "properties": {
    "iso:country":"CH",
    "sg:address":"1920",
    "sg:city":"Martigny",
    "sg:orig_category":"Unclassifiable Establishments",
    "sg:phone":"+41 21 344 70 70",
    "sg:postcode":"1920",
    "sg:province":"Valais",
    "wof:name":"Association Des F\u00eates De Vevey.",
    "wof:placetype":"venue"
},
  "geometry": {"coordinates":[5.1808700562,45.8973388672],"type":"Point"}
}