{
  "type": "Feature",
  "properties": {
    "iso:country":"CH",
    "sg:address":"W\u00f6lfflinweg 9",
    "sg:city":"Winterthur",
    "sg:orig_category":"Advokaturb\u00fcros",
    "sg:phone":"+41 52 203 36 66",
    "sg:postcode":"8400",
    "sg:province":"Z\u00fcrich",
    "wof:name":"Dr. Jakob Robert Biedermann Advokaturb\u00fcro",
    "wof:placetype":"venue"
},
  "geometry": {"coordinates":[8.708155,47.497486],"type":"Point"}
}