{
  "type": "Feature",
  "properties": {
    "iso:country":"CH",
    "sg:address":"Kelleramt",
    "sg:city":"Unterlunkhofen",
    "sg:orig_category":"Abwasserreinigung",
    "sg:phone":"+41 56 634 10 80",
    "sg:postcode":"8918",
    "sg:province":"Aargau",
    "wof:name":"Kl\u00e4ranlage",
    "wof:placetype":"venue"
},
  "geometry": {"coordinates":[8.380647,47.32196],"type":"Point"}
}