{
  "type": "Feature",
  "properties": {
    "iso:country":"CH",
    "sg:address":"Place De La Gare 37",
    "sg:city":"Fribourg",
    "sg:orig_category":"Herstellung von sonstiger Bekleidung U Bekleidungszubeh\u00f6r",
    "sg:postcode":"1700",
    "sg:province":"Fribourg",
    "wof:name":"Werro Blanche",
    "wof:placetype":"venue"
},
  "geometry": {"coordinates":[7.1516327858,46.8035583496],"type":"Point"}
}