{
  "type": "Feature",
  "properties": {
    "iso:country":"CH",
    "sg:address":"Aegerten",
    "sg:city":"Kernenried",
    "sg:orig_category":"Grosshandel mit lebenden Tieren",
    "sg:phone":"+41 79 340 92 27",
    "sg:postcode":"3309",
    "sg:province":"Bern",
    "wof:name":"Johann Santschi Viehhandel",
    "wof:placetype":"venue"
},
  "geometry": {"coordinates":[7.3157129288,47.0305671692],"type":"Point"}
}