{
  "type": "Feature",
  "properties": {
    "iso:country":"CH",
    "sg:address":"Hauptstrasse 107",
    "sg:city":"Nidau",
    "sg:orig_category":"Kauf U Verkauf von Immobilien auf eigene Rechnung Vermittlung von Immobilien",
    "sg:phone":"+41 79 251 24 74",
    "sg:postcode":"2560",
    "sg:province":"Bern",
    "wof:name":"Friag",
    "wof:placetype":"venue"
},
  "geometry": {"coordinates":[7.2422690392,47.1227493286],"type":"Point"}
}