{
  "type": "Feature",
  "properties": {
    "iso:country":"CH",
    "sg:address":"Centralstrasse 45 2540 Grenchen. Postfach",
    "sg:city":"Grenchen",
    "sg:orig_category":"Vermietung U Verpachtung von eigenen Immobilien",
    "sg:postcode":"2540",
    "sg:province":"Solothurn",
    "wof:name":"Sunnehuus Immobilien Ag Immobilien Usw",
    "wof:placetype":"venue"
},
  "geometry": {"coordinates":[7.39523983,47.1948623657],"type":"Point"}
}