{
  "type": "Feature",
  "properties": {
    "iso:country":"CH",
    "sg:address":"Rue De Rive 8",
    "sg:city":"Gen\u00e8ve",
    "sg:orig_category":"Detailhandel mit Brillen U anderen Sehhilfen",
    "sg:phone":"+41 22 311 28 14",
    "sg:postcode":"1204",
    "sg:province":"Gen\u00e8ve",
    "wof:name":"Centrale D'appareillage Acoustique Srls",
    "wof:placetype":"venue"
},
  "geometry": {"coordinates":[6.150579,46.202255],"type":"Point"}
}