{
  "type": "Feature",
  "properties": {
    "iso:country":"CH",
    "sg:address":"Place Du Bourg-de-four 22",
    "sg:city":"Gen\u00e8ve",
    "sg:orig_category":"Erbringung von Dienstleistungen f\u00fcr Unternehmen Kunsthandel",
    "sg:phone":"+41 22 312 20 10",
    "sg:postcode":"1204",
    "sg:province":"Gen\u00e8ve",
    "wof:name":"La Pomme D'or Sa",
    "wof:placetype":"venue"
},
  "geometry": {"coordinates":[6.148868084,46.2003631592],"type":"Point"}
}