{
  "type": "Feature",
  "properties": {
    "iso:country":"CH",
    "sg:address":"Malanserstrasse",
    "sg:city":"Jenins",
    "sg:orig_category":"Non-Classified Establishments",
    "sg:phone":"+41 81 833 27 87",
    "sg:postcode":"7307",
    "sg:province":"Graubunden",
    "wof:name":"Atelier You Nails And Beauty Charlotte Robbi",
    "wof:placetype":"venue"
},
  "geometry": {"coordinates":[9.8355789185,46.4889335632],"type":"Point"}
}