{
  "type": "Feature",
  "properties": {
    "iso:country":"CH",
    "sg:address":"Rte De La Corniche",
    "sg:city":"Puidoux",
    "sg:classifiers":[
        {
            "category":"Travel",
            "subcategory":"Hotels & Motels",
            "type":"Entertainment"
        }
    ],
    "sg:postcode":"1070",
    "sg:province":"Vaud",
    "sg:tags":[
        "hotels",
        "mit",
        "restaurant"
    ],
    "wof:name":"H\u00f4tel Bellevue, Panayotis Dit Takis Solomos",
    "wof:placetype":"venue"
},
  "geometry": {"coordinates":[6.7742347717,46.4814109802],"type":"Point"}
}