{
  "type": "Feature",
  "properties": {
    "iso:country":"CH",
    "sg:address":"Gotthardstrasse 20 6300 Zug. Postfach",
    "sg:city":"Baar",
    "sg:orig_category":"Grosshandel mit Erzen U Metallen",
    "sg:postcode":"6340",
    "sg:province":"Zug",
    "wof:name":"Imc Trimet Ag Metalle, Rohstoffe Zur Aluminiumerzeugung; Kauf, Verkauf, Vermittlung",
    "wof:placetype":"venue"
},
  "geometry": {"coordinates":[8.5139894485,47.1727676392],"type":"Point"}
}