{
  "type": "Feature",
  "properties": {
    "iso:country":"CH",
    "sg:address":"6821",
    "sg:city":"Rovio",
    "sg:orig_category":"Vorschulen, Kinderg\u00e4rten",
    "sg:postcode":"6821",
    "sg:province":"Ticino",
    "wof:name":"Scuola Materna",
    "wof:placetype":"venue"
},
  "geometry": {"coordinates":[9.0503702164,45.870098114],"type":"Point"}
}