{
  "type": "Feature",
  "properties": {
    "iso:country":"CH",
    "sg:address":"Champs-montants 10a",
    "sg:city":"Marin-epagnier",
    "sg:orig_category":"Mechanische Werkst\u00e4tten",
    "sg:phone":"+41 32 753 64 50",
    "sg:postcode":"2074",
    "sg:province":"Neuch\u00e2tel",
    "wof:name":"Hugues Buerki Atelier \u00e9lectrom\u00e9canique",
    "wof:placetype":"venue"
},
  "geometry": {"coordinates":[6.99979496,47.0124053955],"type":"Point"}
}