{
  "type": "Feature",
  "properties": {
    "iso:country":"CH",
    "sg:address":"Finstersee",
    "sg:city":"Menzingen",
    "sg:orig_category":"Verwertung von Milch",
    "sg:postcode":"6313",
    "sg:province":"Zug",
    "wof:name":"K\u00e4serei-genossenschaft Fischbach-dorf",
    "wof:placetype":"venue"
},
  "geometry": {"coordinates":[7.9108991623,47.1482391357],"type":"Point"}
}