{
  "type": "Feature",
  "properties": {
    "iso:country":"CH",
    "sg:address":"Rebackerweg 9",
    "sg:city":"Dietlikon",
    "sg:orig_category":"Elektro- and elektronische Maschinen Grosshandel",
    "sg:phone":"+41 18332943",
    "sg:postcode":"8305",
    "sg:province":"Z\u00fcrich",
    "wof:name":"B.c. G\u00fcnther Bcg Consulting Import & Export V.messger\u00e4ten",
    "wof:placetype":"venue"
},
  "geometry": {"coordinates":[8.6190519333,47.4286994934],"type":"Point"}
}