{
  "type": "Feature",
  "properties": {
    "iso:country":"CH",
    "sg:address":"Oberer Lindenrainweg 15",
    "sg:city":"Zurzach",
    "sg:orig_category":"Politische Parteien CVP",
    "sg:phone":"+41 56 249 16 70",
    "sg:postcode":"5330",
    "sg:province":"Aargau",
    "wof:name":"Cvp Ortspartei Zurzach",
    "wof:placetype":"venue"
},
  "geometry": {"coordinates":[8.3019609451,47.5839385986],"type":"Point"}
}