{
  "type": "Feature",
  "properties": {
    "iso:country":"CH",
    "sg:address":"Brunnen",
    "sg:city":"D\u00fcrrenroth",
    "sg:orig_category":"Detailhandel mit Milcherzeugnissen U Eiern Verarbeitung von Milch",
    "sg:phone":"+41 62 964 12 82",
    "sg:postcode":"3465",
    "sg:province":"Bern",
    "wof:name":"Ulrich R\u00f6thlisberger K\u00e4serei",
    "wof:placetype":"venue"
},
  "geometry": {"coordinates":[7.7696948051,47.0665931702],"type":"Point"}
}