{
  "type": "Feature",
  "properties": {
    "iso:country":"CH",
    "sg:address":"Fiechtenstrasse 32",
    "sg:city":"Huttwil",
    "sg:classifiers":[
        {
            "category":"Government",
            "subcategory":"Post Office",
            "type":"Public Place"
        }
    ],
    "sg:phone":"+41 62 959 86 86",
    "sg:postcode":"4950",
    "sg:province":"Bern",
    "sg:tags":[
        "component",
        "assembly"
    ],
    "wof:name":"United Components Afag, Baltec, Mhk",
    "wof:placetype":"venue"
},
  "geometry": {"coordinates":[7.832308,47.114059],"type":"Point"}
}