{
  "type": "Feature",
  "properties": {
    "iso:country":"CH",
    "sg:address":"Bahnhofstrasse 37 6210 Sursee. Postfach",
    "sg:city":"Sursee",
    "sg:orig_category":"Fachdetailhandel in Verkaufsr\u00e4umen",
    "sg:postcode":"6210",
    "sg:province":"Luzern",
    "wof:name":"Wolf Hugo",
    "wof:placetype":"venue"
},
  "geometry": {"coordinates":[8.1001195908,47.1715545654],"type":"Point"}
}