{
  "type": "Feature",
  "properties": {
    "iso:country":"CH",
    "sg:address":"Turnerstrasse 16 8006 Z\u00fcrich. Postfach 245",
    "sg:city":"Z\u00fcrich",
    "sg:orig_category":"Druck ohne Zeitungsdruck",
    "sg:phone":"+41 71 744 45 22",
    "sg:postcode":"8006",
    "sg:province":"Z\u00fcrich",
    "wof:name":"Print-shop Zellweger Ag",
    "wof:placetype":"venue"
},
  "geometry": {"coordinates":[8.5443611145,47.384513855],"type":"Point"}
}