{
  "type": "Feature",
  "properties": {
    "iso:country":"CH",
    "sg:address":"Rosenb\u00fcelstrasse 50 9642 Ebnat. Postfach",
    "sg:city":"Ebnat-kappel",
    "sg:orig_category":"Detailhandel mit Bekleidung",
    "sg:phone":"+41 71 992 60 60",
    "sg:postcode":"9642",
    "sg:province":"St. Gallen",
    "wof:name":"Kauf Ag",
    "wof:placetype":"venue"
},
  "geometry": {"coordinates":[9.128452,47.262356],"type":"Point"}
}