{
  "type": "Feature",
  "properties": {
    "addr:full":"Via Lugano 32 Biasca Ticino 6710",
    "addr:housenumber":"32",
    "addr:postcode":"6710",
    "addr:street":"Via Lugano",
    "iso:country":"CH",
    "sg:address":"Via Lugano 32",
    "sg:city":"Biasca",
    "sg:orig_category":"Bauschreinerei Detailhandel mit Metallwaren, Anstrichmitteln, Glaswaren, Bau U Heimwerkerbedarf",
    "sg:phone":"+41 81 756 12 16",
    "sg:postcode":"6710",
    "sg:province":"Ticino",
    "wof:name":"Schwendener Heinrich's Erben",
    "wof:placetype":"venue"
},
  "geometry": {"coordinates":[9.475375,47.162228],"type":"Point"}
}