{
  "type": "Feature",
  "properties": {
    "iso:country":"CH",
    "sg:address":"8916",
    "sg:city":"Jonen",
    "sg:orig_category":"Schulpflegen",
    "sg:postcode":"8916",
    "sg:province":"Aargau",
    "wof:name":"Schulpflege Der Gemeinde Kaiserstuhl",
    "wof:placetype":"venue"
},
  "geometry": {"coordinates":[8.4187402725,47.5677604675],"type":"Point"}
}