{
  "type": "Feature",
  "properties": {
    "addr:full":"Els\u00e4sserstrasse 41 Basel Basel-Stadt 4056",
    "addr:housenumber":"41",
    "addr:postcode":"4056",
    "addr:street":"Elsaesserstrasse",
    "iso:country":"CH",
    "sg:address":"Els\u00e4sserstrasse 41",
    "sg:city":"Basel",
    "sg:orig_category":"Detailhandel mit Damenbekleidung",
    "sg:phone":"+41 61 382 70 31",
    "sg:postcode":"4056",
    "sg:province":"Basel-Stadt",
    "wof:name":"Sarmis Mode Gmbh Damenmode",
    "wof:placetype":"venue"
},
  "geometry": {"coordinates":[7.579734,47.568588],"type":"Point"}
}