{
  "type": "Feature",
  "properties": {
    "iso:country":"CH",
    "sg:address":"Place Du Port 2 1200 Genf. Postfach",
    "sg:city":"Gen\u00e8ve",
    "sg:orig_category":"Erbringung von Dienstleistungen f\u00fcr Unternehmen",
    "sg:postcode":"1204",
    "sg:province":"Gen\u00e8ve",
    "wof:name":"Giezendanner Paul, Nachfolger Neff Cornel",
    "wof:placetype":"venue"
},
  "geometry": {"coordinates":[9.1993598938,47.2241897583],"type":"Point"}
}