{
  "type": "Feature",
  "properties": {
    "iso:country":"CH",
    "sg:address":"Wallisellenstrasse 34",
    "sg:city":"D\u00fcbendorf",
    "sg:orig_category":"Bauschreinerei Herstellung von Konstruktionsteilen, Fertigbauteilen U Ausbauelementen aus Holz",
    "sg:phone":"+41 79 334 26 36",
    "sg:postcode":"8600",
    "sg:province":"Z\u00fcrich",
    "wof:name":"Zwicky Dieter",
    "wof:placetype":"venue"
},
  "geometry": {"coordinates":[7.595137,47.477783],"type":"Point"}
}