{
  "type": "Feature",
  "properties": {
    "iso:country":"CH",
    "sg:address":"Zugerstrasse 195 6314 Unter\u00e4geri. Postfach",
    "sg:city":"Unter\u00e4geri",
    "sg:orig_category":"Erbringung von Dienstleistungen f\u00fcr Unternehmen",
    "sg:postcode":"6314",
    "sg:province":"Zug",
    "wof:name":"Webcompanion Gmbh Dienstl. Auf Dem Gebiet D. Informationstechnologie Usw",
    "wof:placetype":"venue"
},
  "geometry": {"coordinates":[8.5640697479,47.149181366],"type":"Point"}
}