{
  "type": "Feature",
  "properties": {
    "addr:full":"Ischlagmatt 1 Willisau Luzern 6130",
    "addr:housenumber":"1",
    "addr:postcode":"6130",
    "addr:street":"Ischlagmatt",
    "iso:country":"CH",
    "sg:address":"Ischlagmatt 1",
    "sg:city":"Willisau",
    "sg:orig_category":"Allgemeiner Hoch U Tiefbau Handelsvermittlung U Grosshandel",
    "sg:phone":"+41 41 210 13 56",
    "sg:postcode":"6130",
    "sg:province":"Luzern",
    "wof:name":"Hunziker Ag Festwirtschaften",
    "wof:placetype":"venue"
},
  "geometry": {"coordinates":[8.011263,47.112545],"type":"Point"}
}