{
  "type": "Feature",
  "properties": {
    "iso:country":"CH",
    "sg:address":"1043",
    "sg:city":"Sugnens",
    "sg:orig_category":"Architektur U Ingenieurb\u00fcros Handelsvermittlung U Grosshandel",
    "sg:phone":"+41 21 881 26 29",
    "sg:postcode":"1043",
    "sg:province":"Vaud",
    "wof:name":"Rematec, Ernst Mme H.",
    "wof:placetype":"venue"
},
  "geometry": {"coordinates":[6.67383,46.654869],"type":"Point"}
}