{
  "type": "Feature",
  "properties": {
    "iso:country":"CH",
    "sg:address":"R\u00f6schenzstrasse 90 4242 Laufen. Postfach",
    "sg:city":"Laufen",
    "sg:orig_category":"Sportvereine Wassersport Schwimmen",
    "sg:phone":"+41 61 761 33 46",
    "sg:postcode":"4242",
    "sg:province":"Basel-Landschaft",
    "wof:name":"Schwimmklub Laufen",
    "wof:placetype":"venue"
},
  "geometry": {"coordinates":[7.4895091057,47.4228553772],"type":"Point"}
}