{
  "type": "Feature",
  "properties": {
    "iso:country":"CH",
    "sg:address":"3973",
    "sg:city":"Venth\u00f4ne",
    "sg:orig_category":"Gemeindeverwaltungen",
    "sg:phone":"+41 27 455 55 87",
    "sg:postcode":"3973",
    "sg:province":"Valais",
    "wof:name":"Administration Communale De Venth\u00f4ne",
    "wof:placetype":"venue"
},
  "geometry": {"coordinates":[7.5217700005,46.3066291809],"type":"Point"}
}