{
  "type": "Feature",
  "properties": {
    "iso:country":"CH",
    "sg:address":"Talstrasse 25 8001 Z\u00fcrich. Postfach",
    "sg:city":"Z\u00fcrich",
    "sg:orig_category":"Interessenvertretungen",
    "sg:postcode":"8001",
    "sg:province":"Z\u00fcrich",
    "wof:name":"F\u00fcrsorgefonds Der Z\u00fcrcher Handelskammer",
    "wof:placetype":"venue"
},
  "geometry": {"coordinates":[8.5379705429,47.3688354492],"type":"Point"}
}