{
  "type": "Feature",
  "properties": {
    "iso:country":"CH",
    "sg:address":"Gautier Rue Jean-ant.- 13 1201 Gen\u00e8ve. Postfach",
    "sg:city":"Gen\u00e8ve",
    "sg:orig_category":"Herstellung von sonstigen Metallwaren",
    "sg:phone":"+41 22 738 35 65",
    "sg:postcode":"1201",
    "sg:province":"Gen\u00e8ve",
    "wof:name":"Publicit\u00e9, Sallaberry Bruno",
    "wof:placetype":"venue"
},
  "geometry": {"coordinates":[6.1497831345,46.2136726379],"type":"Point"}
}