{
  "type": "Feature",
  "properties": {
    "iso:country":"CH",
    "sg:address":"9553",
    "sg:city":"Bettwiesen",
    "sg:orig_category":"Primarschulen",
    "sg:phone":"+41 71 655 14 03",
    "sg:postcode":"9553",
    "sg:province":"Thurgau",
    "wof:name":"Primarschule",
    "wof:placetype":"venue"
},
  "geometry": {"coordinates":[9.0172700882,47.4974403381],"type":"Point"}
}