{
  "type": "Feature",
  "properties": {
    "iso:country":"CH",
    "sg:address":"Ober-kuonimattweg 78",
    "sg:city":"Kriens",
    "sg:orig_category":"Sonstiger Grosshandel",
    "sg:postcode":"6010",
    "sg:province":"Luzern",
    "wof:name":"Anba Vertrieb Ulrich Brigitte",
    "wof:placetype":"venue"
},
  "geometry": {"coordinates":[8.3013324738,47.0231361389],"type":"Point"}
}