{
  "type": "Feature",
  "properties": {
    "iso:country":"CH",
    "sg:address":"Wiesentalstrasse 126 7000 Chur. Postfach",
    "sg:city":"Chur",
    "sg:orig_category":"Werbung",
    "sg:phone":"+41 12027766",
    "sg:postcode":"7000",
    "sg:province":"Graubunden",
    "wof:name":"Advertising And Promotion Corp. Ag",
    "wof:placetype":"venue"
},
  "geometry": {"coordinates":[9.5304498672,46.8637886047],"type":"Point"}
}