{
  "type": "Feature",
  "properties": {
    "iso:country":"CH",
    "sg:address":"Bornfeldstrasse 4",
    "sg:city":"Olten",
    "sg:orig_category":"Instandhaltung U Reparatur von Automobilen",
    "sg:phone":"+41 62 212 47 68",
    "sg:postcode":"4600",
    "sg:province":"Solothurn",
    "wof:name":"Ege Garage Maria-theresia Camci",
    "wof:placetype":"venue"
},
  "geometry": {"coordinates":[7.8947219849,47.3425598145],"type":"Point"}
}