{
  "type": "Feature",
  "properties": {
    "iso:country":"CH",
    "sg:address":"Avenue De La Gare 58",
    "sg:city":"Monthey",
    "sg:orig_category":"Kinderkrippen U horte Vorschulen, Kinderg\u00e4rten",
    "sg:phone":"+41 24 475 70 20",
    "sg:postcode":"1870",
    "sg:province":"Valais",
    "wof:name":"Cr\u00e8che & Jardin D'enfants La Tonkinelle",
    "wof:placetype":"venue"
},
  "geometry": {"coordinates":[6.9546170235,46.2552490234],"type":"Point"}
}