{
  "type": "Feature",
  "properties": {
    "iso:country":"CH",
    "sg:address":"Gotthardstrasse 41",
    "sg:city":"Ibach",
    "sg:orig_category":"Grosshandel mit Holz U Baustoffen",
    "sg:phone":"+41 41 813 07 70",
    "sg:postcode":"6438",
    "sg:province":"Schwyz",
    "wof:name":"Hg Commerciale Handelsgen. Des Schweiz. Baumeisterverband",
    "wof:placetype":"venue"
},
  "geometry": {"coordinates":[8.6415691376,47.0108909607],"type":"Point"}
}