{
  "type": "Feature",
  "properties": {
    "iso:country":"CH",
    "sg:address":"Fischingerstrasse 2",
    "sg:city":"Wiezikon",
    "sg:orig_category":"Wooden Window Profiles, Lamellated",
    "sg:phone":"+41 71 977 13 72",
    "sg:postcode":"8372",
    "sg:province":"Thurgau",
    "wof:name":"Br\u00fchwiler Fensterholz Ag",
    "wof:placetype":"venue"
},
  "geometry": {"coordinates":[8.980260849,47.4517784119],"type":"Point"}
}