{
  "type": "Feature",
  "properties": {
    "iso:country":"CH",
    "sg:address":"Z\u00fcrcherstrasse 109 A 5400 Baden. Postfach",
    "sg:city":"Baden",
    "sg:orig_category":"Vermietung U Verpachtung von eigenen Immobilien",
    "sg:phone":"+41 19327240",
    "sg:postcode":"5400",
    "sg:province":"Aargau",
    "wof:name":"Moderbacher Immobilien Ag",
    "wof:placetype":"venue"
},
  "geometry": {"coordinates":[8.7953767776,47.3225784302],"type":"Point"}
}