{
  "type": "Feature",
  "properties": {
    "iso:country":"CH",
    "sg:address":"2072 St-blaise Case Postale 123",
    "sg:city":"St-blaise",
    "sg:orig_category":"Sportvereine Ballsport Fussball",
    "sg:phone":"+41 32 753 30 66",
    "sg:postcode":"2072",
    "sg:province":"Neuch\u00e2tel",
    "wof:name":"Fc St-blaise",
    "wof:placetype":"venue"
},
  "geometry": {"coordinates":[6.9901638031,47.0149078369],"type":"Point"}
}