{
  "type": "Feature",
  "properties": {
    "iso:country":"CH",
    "sg:address":"2733",
    "sg:city":"Pontenet",
    "sg:orig_category":"Sportvereine Sch\u00fctzen",
    "sg:phone":"+41 32 931 64 54",
    "sg:postcode":"2733",
    "sg:province":"Bern",
    "wof:name":"St\u00e9 De Tir Carabiniers Du Stand",
    "wof:placetype":"venue"
},
  "geometry": {"coordinates":[6.748901844,47.0577201843],"type":"Point"}
}