{
  "type": "Feature",
  "properties": {
    "iso:country":"CH",
    "sg:address":"Dorfstrasse 9 8835 Feusisberg. Postfach 33",
    "sg:city":"Feusisberg",
    "sg:classifiers":[
        {
            "category":"Restaurant",
            "type":"Food & Drink"
        }
    ],
    "sg:phone":"+41 17840457",
    "sg:postcode":"8835",
    "sg:province":"Schwyz",
    "wof:name":"Restaurant Sir James",
    "wof:placetype":"venue"
},
  "geometry": {"coordinates":[8.7427568436,47.1848526001],"type":"Point"}
}