{
  "type": "Feature",
  "properties": {
    "iso:country":"CH",
    "sg:address":"Am Oeschbrig 5",
    "sg:city":"Z\u00fcrich",
    "sg:orig_category":"Fernmeldedienste",
    "sg:postcode":"8053",
    "sg:province":"Z\u00fcrich",
    "wof:name":"Pocsi Enterprises",
    "wof:placetype":"venue"
},
  "geometry": {"coordinates":[8.5999011993,47.3570518494],"type":"Point"}
}