{
  "type": "Feature",
  "properties": {
    "iso:country":"CH",
    "sg:address":"Rue De B\u00e9vignoux 7",
    "sg:city":"Martigny",
    "sg:orig_category":"Grosshandel mit sonstigen Maschinen U Ausr\u00fcstungen f\u00fcr Industrie, Handel U Schiffahrt",
    "sg:phone":"+41 27 722 42 12",
    "sg:postcode":"1920",
    "sg:province":"Valais",
    "wof:name":"Toutautomat Sa",
    "wof:placetype":"venue"
},
  "geometry": {"coordinates":[7.0909152031,46.1078224182],"type":"Point"}
}