{
  "type": "Feature",
  "properties": {
    "iso:country":"CH",
    "sg:address":"Alte Frauenfelderstrasse 9 8542 Wiesendangen. Postfach 34",
    "sg:city":"Wiesendangen",
    "sg:orig_category":"Handelsvermittlung U Grosshandel mit Automobilteilen U Zubeh\u00f6r Herstellung von Teilen U Zubeh\u00f6r f\u00fcr ",
    "sg:phone":"+41 52 337 21 21",
    "sg:postcode":"8542",
    "sg:province":"Z\u00fcrich",
    "wof:name":"Erny Willy Ag",
    "wof:placetype":"venue"
},
  "geometry": {"coordinates":[8.7722978592,47.522819519],"type":"Point"}
}