{
  "type": "Feature",
  "properties": {
    "addr:full":"Kaistenbergstrasse 5 Kaisten Aargau 5082",
    "addr:housenumber":"5",
    "addr:postcode":"5082",
    "addr:street":"Kaistenbergstrasse",
    "iso:country":"CH",
    "sg:address":"Kaistenbergstrasse 5",
    "sg:city":"Kaisten",
    "sg:orig_category":"Bauschreinerei Herstellung von Fenstern U T\u00fcren aus Holz",
    "sg:phone":"+41 62 874 14 15",
    "sg:postcode":"5082",
    "sg:province":"Aargau",
    "wof:name":"Max Winter Schreinerei & Fensterbau",
    "wof:placetype":"venue"
},
  "geometry": {"coordinates":[8.04405,47.537483],"type":"Point"}
}