{
  "type": "Feature",
  "properties": {
    "iso:country":"CH",
    "sg:address":"Dorfstrasse 22 3115 Gerzensee. Postfach",
    "sg:city":"Gerzensee",
    "sg:orig_category":"Detailhandel mit Textilien Grosshandel mit Nahrungsmitteln, Getr\u00e4nken U Tabakwaren ohne ausgepr\u00e4gten",
    "sg:postcode":"3115",
    "sg:province":"Bern",
    "wof:name":"Walter Marti",
    "wof:placetype":"venue"
},
  "geometry": {"coordinates":[7.5422558784,46.8370094299],"type":"Point"}
}