{
  "type": "Feature",
  "properties": {
    "iso:country":"CH",
    "sg:address":"In Der Weiermatt 13",
    "sg:city":"Pratteln",
    "sg:orig_category":"P\u00e9dicure",
    "sg:phone":"+41 61 821 03 05",
    "sg:postcode":"4133",
    "sg:province":"Basel-Landschaft",
    "wof:name":"Marlis J\u00f6rin P\u00e9dicure",
    "wof:placetype":"venue"
},
  "geometry": {"coordinates":[7.6961331367,47.5179138184],"type":"Point"}
}