{
  "type": "Feature",
  "properties": {
    "addr:full":"Marktgasse 34 B\u00fclach Z\u00fcrich 8180",
    "addr:housenumber":"34",
    "addr:postcode":"8180",
    "addr:street":"Marktgasse;Zuerich",
    "iso:country":"CH",
    "sg:address":"Marktgasse 34",
    "sg:city":"B\u00fclach",
    "sg:classifiers":[
        {
            "category":"Bars & Pubs",
            "type":"Food & Drink"
        }
    ],
    "sg:phone":"+41 18602312",
    "sg:postcode":"8180",
    "sg:province":"Z\u00fcrich",
    "wof:name":"Differenze Bar",
    "wof:placetype":"venue"
},
  "geometry": {"coordinates":[8.541216,47.516712],"type":"Point"}
}