{
  "type": "Feature",
  "properties": {
    "iso:country":"CH",
    "sg:address":"Hauptstrasse 27",
    "sg:city":"Derendingen",
    "sg:orig_category":"Detailhandel mit B\u00fcchern Detailhandel mit B\u00fcchern, Zeitungen, Schreib U Papeteriewaren",
    "sg:phone":"+41 32 682 36 86",
    "sg:postcode":"4552",
    "sg:province":"Solothurn",
    "wof:name":"Papierhof Ag Papeterie & Buchhandlung",
    "wof:placetype":"venue"
},
  "geometry": {"coordinates":[7.584606,47.197033],"type":"Point"}
}