{
  "type": "Feature",
  "properties": {
    "iso:country":"CH",
    "sg:address":"Rue Saint-germain 7",
    "sg:city":"Bussigny-lausanne",
    "sg:orig_category":"Detailhandel mit Blumen U Pflanzen",
    "sg:phone":"+41 21 701 12 52",
    "sg:postcode":"1030",
    "sg:province":"Vaud",
    "wof:name":"Michel & Annette Annen St-germain Fleurs",
    "wof:placetype":"venue"
},
  "geometry": {"coordinates":[6.550026,46.550274],"type":"Point"}
}