{
  "type": "Feature",
  "properties": {
    "iso:country":"CH",
    "sg:address":"Neudorfstrasse 13a",
    "sg:city":"Steinhausen",
    "sg:orig_category":"Fachdetailhandel in Verkaufsr\u00e4umen Grosshandel mit Foto U Kinoger\u00e4ten, feinmechanischen U optischen ",
    "sg:phone":"+41 41 740 04 30",
    "sg:postcode":"6312",
    "sg:province":"Zug",
    "wof:name":"R.e.s. Optic Gmbh",
    "wof:placetype":"venue"
},
  "geometry": {"coordinates":[8.4822340012,47.1979560852],"type":"Point"}
}