{
  "type": "Feature",
  "properties": {
    "iso:country":"CH",
    "sg:address":"Im Knebel 4",
    "sg:city":"Mannenbach-salenst",
    "sg:orig_category":"Elektroinstallation",
    "sg:phone":"+41 56 282 37 27",
    "sg:postcode":"8268",
    "sg:province":"Thurgau",
    "wof:name":"Feitknecht R. Elektro Ag",
    "wof:placetype":"venue"
},
  "geometry": {"coordinates":[8.2943954468,47.4865951538],"type":"Point"}
}