{
  "type": "Feature",
  "properties": {
    "iso:country":"CH",
    "sg:address":"St.-anna-strasse",
    "sg:city":"Ebikon",
    "sg:orig_category":"Vorschulen, Kinderg\u00e4rten",
    "sg:phone":"+41 41 440 32 53",
    "sg:postcode":"6030",
    "sg:province":"Luzern",
    "wof:name":"Kindergarten St.anna",
    "wof:placetype":"venue"
},
  "geometry": {"coordinates":[8.3425397873,47.0811042786],"type":"Point"}
}