{
  "type": "Feature",
  "properties": {
    "iso:country":"CH",
    "sg:address":"Chemin Grand-pin 61",
    "sg:city":"Corseaux",
    "sg:orig_category":"Blumen U Zierpflanzenbau",
    "sg:phone":"+41 21 923 54 44",
    "sg:postcode":"1802",
    "sg:province":"Vaud",
    "wof:name":"Philippe Pasche Horticulteur",
    "wof:placetype":"venue"
},
  "geometry": {"coordinates":[6.832171,46.473278],"type":"Point"}
}