{
  "type": "Feature",
  "properties": {
    "iso:country":"CH",
    "sg:address":"Bleiche",
    "sg:city":"Niederurnen",
    "sg:orig_category":"Vereine Diverse",
    "sg:phone":"+41 55 610 21 14",
    "sg:postcode":"8867",
    "sg:province":"Glarus",
    "wof:name":"Landwirtschaftlicher Verein",
    "wof:placetype":"venue"
},
  "geometry": {"coordinates":[9.0457801819,47.1247787476],"type":"Point"}
}