{
  "type": "Feature",
  "properties": {
    "iso:country":"CH",
    "sg:address":"Rossmarktplatz 1",
    "sg:city":"Solothurn",
    "sg:orig_category":"Detailhandel mit Ton U Bildtr\u00e4gern Detailhandel mit elektrischen Haushalts-,Radio U Fernsehger\u00e4ten s",
    "sg:phone":"+41 32 623 75 70",
    "sg:postcode":"4500",
    "sg:province":"Solothurn",
    "wof:name":"Musik Melody Br\u00f6nnimann M.",
    "wof:placetype":"venue"
},
  "geometry": {"coordinates":[7.5366988182,47.2046318054],"type":"Point"}
}