{
  "type": "Feature",
  "properties": {
    "iso:country":"CH",
    "sg:address":"Waldegg 3436 Zollbr\u00fcck. Postfach",
    "sg:city":"Zollbr\u00fcck",
    "sg:orig_category":"Handel mit Automobilen",
    "sg:postcode":"3436",
    "sg:province":"Bern",
    "wof:name":"Brechb\u00fchl Auto Gmbh",
    "wof:placetype":"venue"
},
  "geometry": {"coordinates":[7.7407269478,46.9797325134],"type":"Point"}
}