{
  "type": "Feature",
  "properties": {
    "iso:country":"CH",
    "sg:address":"Schwenden Egg",
    "sg:city":"Diemtigen",
    "sg:orig_category":"Instandhaltung U Reparatur von Automobilen",
    "sg:postcode":"3754",
    "sg:province":"Bern",
    "wof:name":"Garage-car-taxi Spring K.",
    "wof:placetype":"venue"
},
  "geometry": {"coordinates":[7.4914069176,46.5693664551],"type":"Point"}
}