{
  "type": "Feature",
  "properties": {
    "iso:country":"CH",
    "sg:address":"Missionsstrasse 33",
    "sg:city":"Basel",
    "sg:orig_category":"Detailhandel mit Bekleidung",
    "sg:phone":"+41 61 381 70 60",
    "sg:postcode":"4055",
    "sg:province":"Basel-Stadt",
    "wof:name":"Gruppo Tuttimodi Sa",
    "wof:placetype":"venue"
},
  "geometry": {"coordinates":[7.577468,47.559792],"type":"Point"}
}