{
  "type": "Feature",
  "properties": {
    "iso:country":"CH",
    "sg:address":"Beauregard Avenue 9",
    "sg:city":"Freiburg",
    "sg:orig_category":"Non-Classified Establishments",
    "sg:postcode":"1700",
    "sg:province":"Fribourg",
    "wof:name":"Kusungana Import Et Export",
    "wof:placetype":"venue"
},
  "geometry": {"coordinates":[7.1470251083,46.8022689819],"type":"Point"}
}