{
  "type": "Feature",
  "properties": {
    "iso:country":"CH",
    "sg:address":"Le Sorgereux",
    "sg:city":"Valangin",
    "sg:orig_category":"Herstellung von sonstigen Holzwaren",
    "sg:phone":"+41 32 857 17 78",
    "sg:postcode":"2042",
    "sg:province":"Neuch\u00e2tel",
    "wof:name":"Tournage Sur Bois, Olivier De Tribolet-hardy",
    "wof:placetype":"venue"
},
  "geometry": {"coordinates":[6.8914017677,47.0176544189],"type":"Point"}
}