{
  "type": "Feature",
  "properties": {
    "iso:country":"CH",
    "sg:address":"Seidengasse 43",
    "sg:city":"Meilen",
    "sg:orig_category":"Gesundheitswesen Physiotherapie",
    "sg:phone":"+41 19237400",
    "sg:postcode":"8706",
    "sg:province":"Z\u00fcrich",
    "wof:name":"Physiotherapie-praxis Meilen, B. Boendermaker + B. Eenhoorn",
    "wof:placetype":"venue"
},
  "geometry": {"coordinates":[8.6552248001,47.2667350769],"type":"Point"}
}