{
  "type": "Feature",
  "properties": {
    "iso:country":"CH",
    "sg:address":"Sch\u00fctzengasse 22",
    "sg:city":"Z\u00fcrich",
    "sg:orig_category":"Reiseb\u00fcros U Reiseveranstalter",
    "sg:phone":"+41 14541133",
    "sg:postcode":"8001",
    "sg:province":"Z\u00fcrich",
    "wof:name":"Plus Reisen Ag",
    "wof:placetype":"venue"
},
  "geometry": {"coordinates":[8.5387582779,47.3767280579],"type":"Point"}
}