{
  "type": "Feature",
  "properties": {
    "iso:country":"CH",
    "sg:address":"Gartenstrasse 11b",
    "sg:city":"Urdorf",
    "sg:orig_category":"Detailhandel mit Musikinstrumenten",
    "sg:phone":"+41 17341666",
    "sg:postcode":"8902",
    "sg:province":"Z\u00fcrich",
    "wof:name":"Eugen Hochstrasser Pianos",
    "wof:placetype":"venue"
},
  "geometry": {"coordinates":[8.4321584702,47.3905448914],"type":"Point"}
}