{
  "type": "Feature",
  "properties": {
    "iso:country":"CH",
    "sg:address":"Wiesenstrasse 17",
    "sg:city":"Z\u00fcrich",
    "sg:orig_category":"Herstellung von Maschinen f\u00fcr das Papiergewerbe",
    "sg:phone":"+41 13838830",
    "sg:postcode":"8008",
    "sg:province":"Z\u00fcrich",
    "wof:name":"Paperboard Ltd",
    "wof:placetype":"venue"
},
  "geometry": {"coordinates":[8.5529594421,47.3625717163],"type":"Point"}
}