{
  "type": "Feature",
  "properties": {
    "iso:country":"CH",
    "sg:address":"Z\u00fcrcherstrasse 4",
    "sg:city":"Altendorf",
    "sg:orig_category":"Vermietung U Verpachtung von eigenen Immobilien",
    "sg:postcode":"8852",
    "sg:province":"Schwyz",
    "wof:name":"Wohag Immobilien Ag",
    "wof:placetype":"venue"
},
  "geometry": {"coordinates":[8.828494072,47.2284736633],"type":"Point"}
}