{
  "type": "Feature",
  "properties": {
    "iso:country":"CH",
    "sg:address":"Rue Des Mara Chers 4 1200 Gen\u00e8ve. Postfach",
    "sg:city":"Gen\u00e8ve",
    "sg:orig_category":"RESTAURANTS: TEA-ROOMS",
    "sg:postcode":"1205",
    "sg:province":"Gen\u00e8ve",
    "wof:name":"Orfei Giovanni",
    "wof:placetype":"venue"
},
  "geometry": {"coordinates":[6.1341910362,46.1996040344],"type":"Point"}
}