{
  "type": "Feature",
  "properties": {
    "addr:full":"Hauptstrasse 57 Rorschach St. Gallen 9400",
    "addr:housenumber":"57",
    "addr:postcode":"9400",
    "addr:street":"Hauptstrasse",
    "iso:country":"CH",
    "sg:address":"Hauptstrasse 57",
    "sg:city":"Rorschach",
    "sg:orig_category":"Detailhandel mit Bekleidung",
    "sg:phone":"+41 71 841 20 44",
    "sg:postcode":"9400",
    "sg:province":"St. Gallen",
    "wof:name":"Monsieur A, Angehrn Herrenmode.",
    "wof:placetype":"venue"
},
  "geometry": {"coordinates":[9.493086,47.478176],"type":"Point"}
}