{
  "type": "Feature",
  "properties": {
    "iso:country":"CH",
    "sg:address":"Palazzo Industria 6814 Cadempino. Postfach Caselle Postale 200",
    "sg:city":"Cadempino",
    "sg:orig_category":"Herstellung von Medikamenten U sonstigen pharmazeutischen Erzeugnissen Herstellung von pharmazeutisc",
    "sg:phone":"+41 91 960 41 11",
    "sg:postcode":"6814",
    "sg:province":"Ticino",
    "wof:name":"Inpharzam Sa",
    "wof:placetype":"venue"
},
  "geometry": {"coordinates":[8.9299869537,46.0297012329],"type":"Point"}
}