{
  "type": "Feature",
  "properties": {
    "iso:country":"CH",
    "sg:address":"Altishoferstrasse 36",
    "sg:city":"Dagmersellen",
    "sg:orig_category":"Fleischverarbeitung",
    "sg:phone":"+41 62 756 11 48",
    "sg:postcode":"6252",
    "sg:province":"Luzern",
    "wof:name":"Bruno H\u00e4ller Schlachthaus",
    "wof:placetype":"venue"
},
  "geometry": {"coordinates":[7.9842000008,47.2099227905],"type":"Point"}
}