{
  "type": "Feature",
  "properties": {
    "iso:country":"CH",
    "sg:address":"Chesa Patria",
    "sg:city":"Maloja",
    "sg:orig_category":"Sportvereine Ballsport Tennis",
    "sg:phone":"+41 34 493 33 02",
    "sg:postcode":"7516",
    "sg:province":"Graubunden",
    "wof:name":"Tc Marbach",
    "wof:placetype":"venue"
},
  "geometry": {"coordinates":[7.896791935,46.8511428833],"type":"Point"}
}