{
  "type": "Feature",
  "properties": {
    "iso:country":"CH",
    "sg:address":"Wilstrasse 11 8610 Uster. Postfach",
    "sg:city":"Uster",
    "sg:orig_category":"Herstellung von k\u00e4lte U lufttechnischen Erzeugnissen f\u00fcr gewerbliche Zwecke",
    "sg:phone":"+41 19435151",
    "sg:postcode":"8610",
    "sg:province":"Z\u00fcrich",
    "wof:name":"Mcleod Russel Filter Ag Luftfilter, Klimabausteine, Komponenten Der Schutztechnik U. Zubeh\u00f6r; Entwicklung, Konstruktion Usw",
    "wof:placetype":"venue"
},
  "geometry": {"coordinates":[8.7086639404,47.3467674255],"type":"Point"}
}