{
  "type": "Feature",
  "properties": {
    "iso:country":"CH",
    "sg:address":"Blumenfeldstrasse 85 8046 Z\u00fcrich. Postfach 356",
    "sg:city":"Z\u00fcrich",
    "sg:orig_category":"Grosshandel mit sonstigen Gebrauchs U Verbrauchsg\u00fctern Siebdruck",
    "sg:phone":"+41 32 913 37 23",
    "sg:postcode":"8046",
    "sg:province":"Z\u00fcrich",
    "wof:name":"Verdon Sa",
    "wof:placetype":"venue"
},
  "geometry": {"coordinates":[6.8165431023,47.0989112854],"type":"Point"}
}