{
  "type": "Feature",
  "properties": {
    "iso:country":"CH",
    "sg:address":"Ruessenstrasse 22",
    "sg:city":"Baar",
    "sg:orig_category":"Autogaragen",
    "sg:phone":"+41 41 760 46 46",
    "sg:postcode":"6340",
    "sg:province":"Zug",
    "wof:name":"Ernst Andermatt Garage",
    "wof:placetype":"venue"
},
  "geometry": {"coordinates":[8.564965,47.212658],"type":"Point"}
}