{
  "type": "Feature",
  "properties": {
    "iso:country":"CH",
    "sg:address":"Geissgasse 29",
    "sg:city":"Rheinfelden",
    "sg:orig_category":"Unclassifiable Establishments",
    "sg:postcode":"4310",
    "sg:province":"Aargau",
    "wof:name":"Agencia Cesar's Ag",
    "wof:placetype":"venue"
},
  "geometry": {"coordinates":[7.7949900627,47.5540885925],"type":"Point"}
}