{
  "type": "Feature",
  "properties": {
    "iso:country":"CH",
    "sg:address":"Weinberglistrasse 4",
    "sg:city":"Luzern",
    "sg:orig_category":"Vermittlung von Immobilien Verwaltung von Immobilien",
    "sg:phone":"+41 41 207 77 77",
    "sg:postcode":"6005",
    "sg:province":"Luzern",
    "wof:name":"Swisscom Immobilien Ag",
    "wof:placetype":"venue"
},
  "geometry": {"coordinates":[8.316857338,47.0419387817],"type":"Point"}
}