{
  "type": "Feature",
  "properties": {
    "iso:country":"CH",
    "sg:address":"Aescherstrasse 5",
    "sg:city":"Fahrwangen",
    "sg:orig_category":"Detailhandel mit Radio U Fernsehger\u00e4ten Detailhandel mit elektrischen Haushalts-,Radio U Fernsehger\u00e4",
    "sg:phone":"+41 56 667 24 79",
    "sg:postcode":"5615",
    "sg:province":"Aargau",
    "wof:name":"Balz Amrein",
    "wof:placetype":"venue"
},
  "geometry": {"coordinates":[8.2408266068,47.2940139771],"type":"Point"}
}