{
  "type": "Feature",
  "properties": {
    "iso:country":"CH",
    "sg:address":"Zentralstrasse 27 8212 Neuhausen. Postfach",
    "sg:city":"Neuhausen",
    "sg:orig_category":"Herstellung von Schmuck, Gold U Silberschmiedwaren",
    "sg:postcode":"8212",
    "sg:province":"Schaffhausen",
    "wof:name":"Goldschmied Fior Goldschmiedatelier. Bijouterieartikel; Handel",
    "wof:placetype":"venue"
},
  "geometry": {"coordinates":[8.6190357208,47.6811828613],"type":"Point"}
}