{
  "type": "Feature",
  "properties": {
    "iso:country":"CH",
    "sg:address":"Chemin Du Verger 3",
    "sg:city":"Ballaigues",
    "sg:orig_category":"Herstellung von sonstigen Maschinen f\u00fcr unspezifische Verwendung",
    "sg:postcode":"1338",
    "sg:province":"Vaud",
    "wof:name":"Mani R.",
    "wof:placetype":"venue"
},
  "geometry": {"coordinates":[7.5289850235,47.1714172363],"type":"Point"}
}