{
  "type": "Feature",
  "properties": {
    "iso:country":"CH",
    "sg:address":"Br\u00fchlmattweg 1 4107 Ettingen. Postfach",
    "sg:city":"Ettingen",
    "sg:orig_category":"Architektur U Ingenieurb\u00fcros",
    "sg:phone":"+41 71 288 27 88",
    "sg:postcode":"4107",
    "sg:province":"Basel-Landschaft",
    "wof:name":"Andres Geotechnik Ag",
    "wof:placetype":"venue"
},
  "geometry": {"coordinates":[9.404032,47.445179],"type":"Point"}
}