{
  "type": "Feature",
  "properties": {
    "iso:country":"CH",
    "sg:address":"Feldbergstrasse 33",
    "sg:city":"Basel",
    "sg:orig_category":"Detailhandel mit B\u00fcchern",
    "sg:phone":"+41 61 691 23 71",
    "sg:postcode":"4057",
    "sg:province":"Basel-Stadt",
    "wof:name":"Oezg\u00fcr Kasetcilik",
    "wof:placetype":"venue"
},
  "geometry": {"coordinates":[7.590009,47.566238],"type":"Point"}
}