{
  "type": "Feature",
  "properties": {
    "iso:country":"CH",
    "sg:address":"Rosenstrasse 27",
    "sg:city":"Dietikon",
    "sg:orig_category":"Kaminfeger",
    "sg:phone":"+41 17414934",
    "sg:postcode":"8953",
    "sg:province":"Z\u00fcrich",
    "wof:name":"Franz Zihlmann Kaminfegergesch\u00e4ft",
    "wof:placetype":"venue"
},
  "geometry": {"coordinates":[8.3997545242,47.3923187256],"type":"Point"}
}