{
  "type": "Feature",
  "properties": {
    "iso:country":"CH",
    "sg:address":"St.galler Strasse 35",
    "sg:city":"T\u00fcbach",
    "sg:orig_category":"Politische Parteien CVP",
    "sg:postcode":"9327",
    "sg:province":"St. Gallen",
    "wof:name":"Cvp Ortspartei T\u00fcbach",
    "wof:placetype":"venue"
},
  "geometry": {"coordinates":[9.4515171051,47.4741783142],"type":"Point"}
}