{
  "type": "Feature",
  "properties": {
    "iso:country":"CH",
    "sg:address":"Ponte Di Valle Strada 34b 6964 Davesco-soragno. Postfach",
    "sg:city":"Davesco-soragno",
    "sg:orig_category":"Maler U Glasergewerbe",
    "sg:postcode":"6964",
    "sg:province":"Ticino",
    "wof:name":"Quinto Colour Sagl Lavori Di Pittura, Intonaco Ecc",
    "wof:placetype":"venue"
},
  "geometry": {"coordinates":[8.9895296097,46.0325584412],"type":"Point"}
}