{
  "type": "Feature",
  "properties": {
    "iso:country":"CH",
    "sg:address":"Chemin Des Faverges 17",
    "sg:city":"Lausanne",
    "sg:orig_category":"Detailhandel mit Tabakwaren",
    "sg:phone":"+41 21 728 70 09",
    "sg:postcode":"1006",
    "sg:province":"Vaud",
    "wof:name":"Anna Depallens Tabacs",
    "wof:placetype":"venue"
},
  "geometry": {"coordinates":[6.6475877762,46.5139808655],"type":"Point"}
}