{
  "type": "Feature",
  "properties": {
    "iso:country":"CH",
    "sg:address":"Village Place Du",
    "sg:city":"Genolier",
    "sg:orig_category":"Fachdetailhandel in Verkaufsr\u00e4umen",
    "sg:postcode":"1272",
    "sg:province":"Vaud",
    "wof:name":"Jakov Gojun",
    "wof:placetype":"venue"
},
  "geometry": {"coordinates":[6.2181859016,46.4349212646],"type":"Point"}
}