{
  "type": "Feature",
  "properties": {
    "iso:country":"CH",
    "sg:address":"Schlifras 4",
    "sg:city":"Ilanz",
    "sg:orig_category":"Sportvereine Sch\u00fctzen",
    "sg:postcode":"7130",
    "sg:province":"Graubunden",
    "wof:name":"Sch\u00fctzenverein",
    "wof:placetype":"venue"
},
  "geometry": {"coordinates":[9.204750061,46.7706604004],"type":"Point"}
}