{
  "type": "Feature",
  "properties": {
    "iso:country":"CH",
    "sg:address":"Place Pestalozzi 12 1400 Yverdon-les-bains Case Postale 396",
    "sg:city":"Yverdon",
    "sg:orig_category":"Detailhandel mit B\u00fcchern Detailhandel mit B\u00fcchern, Zeitungen, Schreib U Papeteriewaren",
    "sg:phone":"+41 24 424 20 02",
    "sg:postcode":"1401",
    "sg:province":"Vaud",
    "wof:name":"Schaer Librairie-papeterie Sa",
    "wof:placetype":"venue"
},
  "geometry": {"coordinates":[6.640347,46.776833],"type":"Point"}
}