{
  "type": "Feature",
  "properties": {
    "iso:country":"CH",
    "sg:address":"3903",
    "sg:city":"Mund",
    "sg:orig_category":"Maurerarbeiten",
    "sg:phone":"+41 27 722 47 45",
    "sg:postcode":"3903",
    "sg:province":"Valais",
    "wof:name":"Robert Di Secli Entreprise De Ma\u00e7onnerie",
    "wof:placetype":"venue"
},
  "geometry": {"coordinates":[7.0662398338,46.0986785889],"type":"Point"}
}