{
  "type": "Feature",
  "properties": {
    "iso:country":"CH",
    "sg:address":"Uetlibergstrasse 345",
    "sg:city":"Z\u00fcrich",
    "sg:orig_category":"Sportvereine Sch\u00fctzen Armbrust",
    "sg:phone":"+41 14634175",
    "sg:postcode":"8045",
    "sg:province":"Z\u00fcrich",
    "wof:name":"Armbrustsch\u00fctzenverein Wiedikon",
    "wof:placetype":"venue"
},
  "geometry": {"coordinates":[8.5074110031,47.3522491455],"type":"Point"}
}