{
  "type": "Feature",
  "properties": {
    "iso:country":"CH",
    "sg:address":"Martastrasse 100",
    "sg:city":"Z\u00fcrich",
    "sg:orig_category":"Unclassifiable Establishments",
    "sg:postcode":"8004",
    "sg:province":"Z\u00fcrich",
    "wof:name":"Edith Engeli Shiatsu",
    "wof:placetype":"venue"
},
  "geometry": {"coordinates":[8.515794754,47.3770599365],"type":"Point"}
}