{
  "type": "Feature",
  "properties": {
    "iso:country":"CH",
    "sg:address":"Route De Billens 7",
    "sg:city":"Romont",
    "sg:classifiers":[
        {
            "category":"Professional",
            "type":"Services"
        }
    ],
    "sg:phone":"+41 26 652 22 08",
    "sg:postcode":"1608",
    "sg:province":"Fribourg",
    "sg:tags":[
        "transport",
        "road"
    ],
    "wof:name":"Michel Et Emmanuel Pittet",
    "wof:placetype":"venue"
},
  "geometry": {"coordinates":[6.91329813,46.6919670105],"type":"Point"}
}