{
  "type": "Feature",
  "properties": {
    "iso:country":"CH",
    "sg:address":"Chemin Du Guignard",
    "sg:city":"Cologny",
    "sg:orig_category":"Primarschulen",
    "sg:phone":"+41 22 736 73 33",
    "sg:postcode":"1223",
    "sg:province":"Gen\u00e8ve",
    "wof:name":"Ecole Primaire Cologny",
    "wof:placetype":"venue"
},
  "geometry": {"coordinates":[6.181374073,46.2144508362],"type":"Point"}
}