{
  "type": "Feature",
  "properties": {
    "iso:country":"CH",
    "sg:address":"Ch\u00e4nnelmattstrasse 13",
    "sg:city":"D\u00fcdingen",
    "sg:orig_category":"Grosshandel mit lebenden Tieren",
    "sg:phone":"+41 26 493 22 00",
    "sg:postcode":"3186",
    "sg:province":"Fribourg",
    "wof:name":"Niklaus Br\u00fclhart Viehhandel",
    "wof:placetype":"venue"
},
  "geometry": {"coordinates":[7.1950850487,46.8456726074],"type":"Point"}
}