{
  "type": "Feature",
  "properties": {
    "iso:country":"CH",
    "sg:address":"Via Massagno 26",
    "sg:city":"Lugano",
    "sg:orig_category":"Handelsvermittlung von Brennstoffen, Erzen, Metallen U Chemikalien Sonstiger Grosshandel",
    "sg:phone":"+41 91 910 18 69",
    "sg:postcode":"6900",
    "sg:province":"Ticino",
    "wof:name":"Selva Sagl",
    "wof:placetype":"venue"
},
  "geometry": {"coordinates":[8.9474172592,46.0102119446],"type":"Point"}
}