{
  "type": "Feature",
  "properties": {
    "iso:country":"CH",
    "sg:address":"Lausanne Route De 9 1096 Cully. Postfach",
    "sg:city":"Cully",
    "sg:orig_category":"Sonstiger Grosshandel",
    "sg:postcode":"1096",
    "sg:province":"Vaud",
    "wof:name":"Zucker Ltd Liab. Co Mat\u00e9riel Et Machines De Construction; Commerce Etc",
    "wof:placetype":"venue"
},
  "geometry": {"coordinates":[6.7286748886,46.4874725342],"type":"Point"}
}