{
  "type": "Feature",
  "properties": {
    "iso:country":"CH",
    "sg:address":"Oberdorf 6",
    "sg:city":"Unterehrendingen",
    "sg:orig_category":"Gemeindeverwaltungen",
    "sg:phone":"+41 56 222 51 66",
    "sg:postcode":"5424",
    "wof:name":"Gemeindeverwaltung Unterehrendingen",
    "wof:placetype":"venue"
},
  "geometry": {"coordinates":[8.3501605988,47.5011863708],"type":"Point"}
}