{
  "type": "Feature",
  "properties": {
    "iso:country":"CH",
    "sg:address":"Neubrunnenstrasse 38 8000 Z\u00fcrich. Postfach",
    "sg:city":"Z\u00fcrich",
    "sg:orig_category":"Unclassifiable Establishments",
    "sg:postcode":"8000",
    "sg:province":"Z\u00fcrich",
    "wof:name":"Osterwalder Hydraulik. Hydraulische Ventile; Beratung, Verkauf U. Service.",
    "wof:placetype":"venue"
},
  "geometry": {"coordinates":[9.347817421,47.4143257141],"type":"Point"}
}