{
  "type": "Feature",
  "properties": {
    "addr:full":"Oltnerstrasse 44 Sch\u00f6nenwerd Solothurn 5012",
    "addr:housenumber":"44",
    "addr:postcode":"5012",
    "addr:street":"Oltnerstrasse;Schoenenwerd Solothurn",
    "iso:country":"CH",
    "sg:address":"Oltnerstrasse 44",
    "sg:city":"Sch\u00f6nenwerd",
    "sg:orig_category":"Detailhandel mit Brillen U anderen Sehhilfen Fachdetailhandel in Verkaufsr\u00e4umen",
    "sg:phone":"+41 56211444",
    "sg:postcode":"5012",
    "sg:province":"Solothurn",
    "wof:name":"Eng Optik Ag",
    "wof:placetype":"venue"
},
  "geometry": {"coordinates":[8.001581,47.370049],"type":"Point"}
}