{
  "type": "Feature",
  "properties": {
    "addr:full":"L\u00e4nggassstrasse 26 Bern Bern 3012",
    "addr:housenumber":"26",
    "addr:postcode":"3012",
    "addr:street":"Laenggassstrasse",
    "iso:country":"CH",
    "sg:address":"L\u00e4nggassstrasse 26",
    "sg:city":"Bern",
    "sg:orig_category":"Arztpraxen",
    "sg:phone":"+41 31 302 51 10",
    "sg:postcode":"3012",
    "sg:province":"Bern",
    "wof:name":"Dr.med.ursula Hiltbrand Spezial\u00e4rztin Fmh",
    "wof:placetype":"venue"
},
  "geometry": {"coordinates":[7.433134,46.952961],"type":"Point"}
}