{
  "type": "Feature",
  "properties": {
    "iso:country":"CH",
    "sg:address":"Gliserallee 135",
    "sg:city":"Glis",
    "sg:orig_category":"Instandhaltung U Reparatur von Automobilen Tankstellen",
    "sg:phone":"+41 41 811 44 88",
    "sg:postcode":"3902",
    "sg:province":"Valais",
    "wof:name":"Zeno Schn\u00fcriger Garage & Tankstelle",
    "wof:placetype":"venue"
},
  "geometry": {"coordinates":[8.6284837723,47.0287055969],"type":"Point"}
}