{
  "type": "Feature",
  "properties": {
    "iso:country":"CH",
    "sg:address":"Rougemont Route De 7",
    "sg:city":"Soral",
    "sg:orig_category":"RESTAURANTS: TEA-ROOMS",
    "sg:phone":"+41 79 219 44 61",
    "sg:postcode":"1286",
    "sg:province":"Gen\u00e8ve",
    "wof:name":"Walle Claude Et Walle Fernande",
    "wof:placetype":"venue"
},
  "geometry": {"coordinates":[6.0443072319,46.144241333],"type":"Point"}
}