{
  "type": "Feature",
  "properties": {
    "iso:country":"CH",
    "sg:address":"Rue Des Grottes 12",
    "sg:city":"Vallorbe",
    "sg:orig_category":"Mechanik Mechanische Werkst\u00e4tten",
    "sg:phone":"+41 26 912 64 29",
    "sg:postcode":"1337",
    "sg:province":"Vaud",
    "wof:name":"Ateliers M\u00e9caniques La Tour Sa",
    "wof:placetype":"venue"
},
  "geometry": {"coordinates":[7.0705189705,46.6082687378],"type":"Point"}
}