{
  "type": "Feature",
  "properties": {
    "iso:country":"CH",
    "sg:address":"M\u00fcnchwilerstrasse 19 T\u00e4gerschen",
    "sg:city":"Tobel",
    "sg:orig_category":"Maschinen-Fabrikation",
    "sg:phone":"+41 71 917 17 45",
    "sg:postcode":"9555",
    "sg:province":"Thurgau",
    "wof:name":"Jetter (schweiz) Ag",
    "wof:placetype":"venue"
},
  "geometry": {"coordinates":[9.0303897858,47.5119667053],"type":"Point"}
}