{
  "type": "Feature",
  "properties": {
    "addr:full":"Querstrasse 10 Z\u00fcrich Z\u00fcrich 8050",
    "addr:housenumber":"10",
    "addr:postcode":"8050",
    "addr:street":"Querstrasse",
    "iso:country":"CH",
    "sg:address":"Querstrasse 10",
    "sg:city":"Z\u00fcrich",
    "sg:orig_category":"Arztpraxen",
    "sg:phone":"+41 13124546",
    "sg:postcode":"8050",
    "sg:province":"Z\u00fcrich",
    "wof:name":"Dr.med.vera Schnyder Spezial\u00e4rztin Fmh",
    "wof:placetype":"venue"
},
  "geometry": {"coordinates":[8.545212,47.410023],"type":"Point"}
}