{
  "type": "Feature",
  "properties": {
    "iso:country":"CH",
    "sg:address":"Avenue Des Grandes-communes 26",
    "sg:city":"Onex",
    "sg:orig_category":"Herstellung von Karosserien U Anh\u00e4ngern",
    "sg:phone":"+41 22 792 87 14",
    "sg:postcode":"1213",
    "sg:province":"Gen\u00e8ve",
    "wof:name":"Carrosserie Leumann Albert",
    "wof:placetype":"venue"
},
  "geometry": {"coordinates":[6.1045279503,46.1926994324],"type":"Point"}
}