{
  "type": "Feature",
  "properties": {
    "iso:country":"CH",
    "sg:address":"Widmerstrasse 100",
    "sg:city":"Z\u00fcrich",
    "sg:orig_category":"Detailhandel mit Fleisch U Fleischwaren",
    "sg:phone":"+41 33 243 12 40",
    "sg:postcode":"8038",
    "sg:province":"Z\u00fcrich",
    "wof:name":"Metzgerei Balmer",
    "wof:placetype":"venue"
},
  "geometry": {"coordinates":[7.6688017845,46.7312202454],"type":"Point"}
}