{
  "type": "Feature",
  "properties": {
    "addr:full":"Rue Cavour 15 Gen\u00e8ve Gen\u00e8ve 1203",
    "addr:housenumber":"15",
    "addr:postcode":"1203",
    "addr:street":"Rue Cavour",
    "iso:country":"CH",
    "sg:address":"Rue Cavour 15",
    "sg:city":"Gen\u00e8ve",
    "sg:orig_category":"Alters U Pflegeheime Wohnheime",
    "sg:phone":"+41 21 653 44 21",
    "sg:postcode":"1203",
    "sg:province":"Gen\u00e8ve",
    "wof:name":"Fondation Plein Soleil",
    "wof:placetype":"venue"
},
  "geometry": {"coordinates":[6.65576,46.5359],"type":"Point"}
}