{
  "type": "Feature",
  "properties": {
    "iso:country":"CH",
    "sg:address":"Wehntalerstrasse 56",
    "sg:city":"H\u00f6ri",
    "sg:classifiers":[
        {
            "category":"Restaurant",
            "type":"Food & Drink"
        }
    ],
    "sg:phone":"+41 18601401",
    "sg:postcode":"8181",
    "sg:province":"Z\u00fcrich",
    "wof:name":"Restaurant Zur Au",
    "wof:placetype":"venue"
},
  "geometry": {"coordinates":[8.5081014633,47.5072174072],"type":"Point"}
}