{
  "type": "Feature",
  "properties": {
    "iso:country":"CH",
    "sg:address":"Dietlikonerstrasse 26",
    "sg:city":"Wallisellen",
    "sg:orig_category":"Kauf U Verkauf von Immobilien auf eigene Rechnung Vermittlung von Immobilien",
    "sg:phone":"+41 18302108",
    "sg:postcode":"8304",
    "sg:province":"Z\u00fcrich",
    "wof:name":"Maienfisch Immobilien-verwaltungen",
    "wof:placetype":"venue"
},
  "geometry": {"coordinates":[8.6036167145,47.4205970764],"type":"Point"}
}