{
  "type": "Feature",
  "properties": {
    "iso:country":"CH",
    "sg:address":"Pr\u00e9-du-march\u00e9 Rue 23",
    "sg:city":"Lausanne",
    "sg:orig_category":"Buchverlag Verlagsgewerbe",
    "sg:phone":"+41 22 309 36 00",
    "sg:postcode":"1000",
    "sg:province":"Vaud",
    "wof:name":"Editions Zo\u00e9 Oeuvres Litt\u00e9raires",
    "wof:placetype":"venue"
},
  "geometry": {"coordinates":[6.143366,46.18301],"type":"Point"}
}