{
  "type": "Feature",
  "properties": {
    "iso:country":"CH",
    "sg:address":"Oberdorfstrasse 56",
    "sg:city":"Glarus",
    "sg:orig_category":"Vereine Milit\u00e4r",
    "sg:phone":"+41 55 640 82 56",
    "sg:postcode":"8750",
    "sg:province":"Glarus",
    "wof:name":"Unteroffiziersverein Glarus",
    "wof:placetype":"venue"
},
  "geometry": {"coordinates":[9.0588283539,47.0394287109],"type":"Point"}
}