{
  "type": "Feature",
  "properties": {
    "iso:country":"CH",
    "sg:address":"Vordere Gasse 13",
    "sg:city":"Kerzers",
    "sg:orig_category":"Detailhandel mit Schreib U Papeteriewaren",
    "sg:phone":"+41 31 755 61 95",
    "sg:postcode":"3210",
    "sg:province":"Fribourg",
    "wof:name":"Barbara Meyer Papeterie",
    "wof:placetype":"venue"
},
  "geometry": {"coordinates":[7.1991090775,46.9747161865],"type":"Point"}
}