{
  "type": "Feature",
  "properties": {
    "iso:country":"CH",
    "sg:address":"Grubenstrasse 3",
    "sg:city":"Urdorf",
    "sg:orig_category":"Herstellung von Metallkonstruktionen Stahl U Leichtmetallbau",
    "sg:phone":"+41 21 960 25 61",
    "sg:postcode":"8902",
    "sg:province":"Z\u00fcrich",
    "wof:name":"Morier Sa Constructions M\u00e9talliques Et V\u00e9hicules",
    "wof:placetype":"venue"
},
  "geometry": {"coordinates":[6.9346351624,46.3913116455],"type":"Point"}
}