{
  "type": "Feature",
  "properties": {
    "iso:country":"CH",
    "sg:address":"Via Maistra 72",
    "sg:city":"Schlarigna",
    "sg:classifiers":[
        {
            "category":"Travel",
            "subcategory":"Hotels & Motels",
            "type":"Entertainment"
        }
    ],
    "sg:phone":"+41 81 833 66 85",
    "sg:postcode":"7505",
    "sg:province":"Graubunden",
    "sg:tags":[
        "hotels",
        "mit",
        "restaurant"
    ],
    "wof:name":"Hotel Arturo",
    "wof:placetype":"venue"
},
  "geometry": {"coordinates":[9.8574171066,46.5113525391],"type":"Point"}
}