{
  "type": "Feature",
  "properties": {
    "iso:country":"CH",
    "sg:address":"Schulstrasse 10",
    "sg:city":"Weinfelden",
    "sg:orig_category":"Sanit\u00e4r, Heizungs U L\u00fcftungsinstallation Sanit\u00e4rinstallation",
    "sg:phone":"+41 71 622 33 18",
    "sg:postcode":"8570",
    "sg:province":"Thurgau",
    "wof:name":"Prandini & Co. Sanit\u00e4ranlagen Und Heizungen.",
    "wof:placetype":"venue"
},
  "geometry": {"coordinates":[9.1068162918,47.5677871704],"type":"Point"}
}