{
  "type": "Feature",
  "properties": {
    "iso:country":"CH",
    "sg:address":"Chriesbaumstrasse 4 8604 Volketswil. Postfach",
    "sg:city":"Volketswil",
    "sg:orig_category":"Farben and Lacke Grosshandel Grosshandel mit sonstigen Gebrauchs U Verbrauchsg\u00fctern",
    "sg:phone":"+41 19083840",
    "sg:postcode":"8604",
    "sg:province":"Z\u00fcrich",
    "wof:name":"Motip Dupli Ag",
    "wof:placetype":"venue"
},
  "geometry": {"coordinates":[8.6803779602,47.3822097778],"type":"Point"}
}