{
  "type": "Feature",
  "properties": {
    "iso:country":"CH",
    "sg:address":"Rue Du Nant 35",
    "sg:city":"Gen\u00e8ve",
    "sg:orig_category":"Primarschulen",
    "sg:phone":"+41 22 736 01 11",
    "sg:postcode":"1207",
    "sg:province":"Gen\u00e8ve",
    "wof:name":"Ecole Primaire Vollandes",
    "wof:placetype":"venue"
},
  "geometry": {"coordinates":[6.1625881195,46.2034759521],"type":"Point"}
}