{
  "type": "Feature",
  "properties": {
    "iso:country":"CH",
    "sg:address":"Amselweg 7 B",
    "sg:city":"Heimberg",
    "sg:orig_category":"Herstellung von medizinischen U chirurgischen Ger\u00e4ten sowie orthop\u00e4dischen Vorrichtungen",
    "sg:phone":"+41 71 929 85 85",
    "sg:postcode":"3627",
    "sg:province":"Bern",
    "wof:name":"Hausmann Spitalbedarf Ag",
    "wof:placetype":"venue"
},
  "geometry": {"coordinates":[9.3765602112,47.4255027771],"type":"Point"}
}