{
  "type": "Feature",
  "properties": {
    "iso:country":"CH",
    "sg:address":"Aarauerstrasse 25",
    "sg:city":"Sins",
    "sg:orig_category":"Bauschreinerei Herstellung von M\u00f6beln verschiedener Art",
    "sg:phone":"+41 41 787 12 25",
    "sg:postcode":"5643",
    "sg:province":"Aargau",
    "wof:name":"Hans M\u00fchlebach Ag",
    "wof:placetype":"venue"
},
  "geometry": {"coordinates":[8.391434,47.192059],"type":"Point"}
}