{
  "type": "Feature",
  "properties": {
    "iso:country":"CH",
    "sg:address":"Gewerbegehaus Moskau",
    "sg:city":"Ramsen",
    "sg:orig_category":"Medien, Sonstige Mediendienstleistungen",
    "sg:phone":"+41 52 743 19 90",
    "sg:postcode":"8262",
    "sg:province":"Schaffhausen",
    "wof:name":"Axing Kommunikationstechnik",
    "wof:placetype":"venue"
},
  "geometry": {"coordinates":[8.81151,47.707146],"type":"Point"}
}