{
  "type": "Feature",
  "properties": {
    "iso:country":"CH",
    "sg:address":"Chemin De Cyrano 1",
    "sg:city":"Pully",
    "sg:orig_category":"Aktivit\u00e4ten der Generalunternehmen im Baugewerbe Architektur U Ingenieurb\u00fcros",
    "sg:phone":"+41 21 711 07 20",
    "sg:postcode":"1009",
    "sg:province":"Vaud",
    "wof:name":"Noverraz, Pham & Associ\u00e9s Sa",
    "wof:placetype":"venue"
},
  "geometry": {"coordinates":[6.642836,46.505718],"type":"Point"}
}