{
  "type": "Feature",
  "properties": {
    "iso:country":"CH",
    "sg:address":"Mittlerestrasse 66 3600 Thun. Postfach",
    "sg:city":"Thun",
    "sg:orig_category":"Detailhandel mit Metallwaren, Anstrichmitteln, Glaswaren, Bau U Heimwerkerbedarf",
    "sg:postcode":"3600",
    "sg:province":"Bern",
    "wof:name":"H.i.t. Hebezeug Industrie Thun Ag",
    "wof:placetype":"venue"
},
  "geometry": {"coordinates":[7.614880085,46.755859375],"type":"Point"}
}