{
  "type": "Feature",
  "properties": {
    "iso:country":"CH",
    "sg:address":"Lavaux Avenue De 78b",
    "sg:city":"Pully",
    "sg:orig_category":"Wirtschaftspr\u00fcfung, Steuerberatung U Treuhand",
    "sg:phone":"+41 21 728 49 75",
    "sg:postcode":"1009",
    "sg:province":"Vaud",
    "wof:name":"Fidom, Evelyne Ducrest",
    "wof:placetype":"venue"
},
  "geometry": {"coordinates":[6.6598000526,46.5102577209],"type":"Point"}
}