{
  "type": "Feature",
  "properties": {
    "iso:country":"CH",
    "sg:address":"Westbahnhofstrasse 1",
    "sg:city":"Solothurn",
    "sg:orig_category":"Detailhandel mit Waren verschiedener Art, Hauptrichtung Nahrungsmittel",
    "sg:phone":"+41 32 622 47 87",
    "sg:postcode":"4500",
    "sg:province":"Solothurn",
    "wof:name":"Denner Top Superdiscount",
    "wof:placetype":"venue"
},
  "geometry": {"coordinates":[7.5323982239,47.2072525024],"type":"Point"}
}