{
  "type": "Feature",
  "properties": {
    "iso:country":"CH",
    "sg:address":"Erlenweg 98",
    "sg:city":"Esslingen",
    "sg:orig_category":"Bauschreinerei",
    "sg:phone":"+41 19842643",
    "sg:postcode":"8133",
    "sg:province":"Z\u00fcrich",
    "wof:name":"Walter Graf Schreinerei",
    "wof:placetype":"venue"
},
  "geometry": {"coordinates":[8.71227,47.285629],"type":"Point"}
}