{
  "type": "Feature",
  "properties": {
    "iso:country":"CH",
    "sg:address":"Fahrhubelweg 5",
    "sg:city":"Belp",
    "sg:orig_category":"Detailhandel mit Geschenkartikeln U Souvenirs",
    "sg:phone":"+41 31 818 38 36",
    "sg:postcode":"3123",
    "sg:province":"Bern",
    "wof:name":"Boutique Smile Gmbh Geschenkartikel",
    "wof:placetype":"venue"
},
  "geometry": {"coordinates":[7.5231370926,46.8892021179],"type":"Point"}
}