{
  "type": "Feature",
  "properties": {
    "addr:full":"Z\u00fcrcherstrasse 212a 8406 Winterthur. Postfach Winterthur Z\u00fcrich 8406",
    "addr:housenumber":"212a",
    "addr:postcode":"8406;8406",
    "addr:street":"Zuercherstrasse;Postfach",
    "iso:country":"CH",
    "sg:address":"Z\u00fcrcherstrasse 212a 8406 Winterthur. Postfach",
    "sg:city":"Winterthur",
    "sg:orig_category":"Autogaragen",
    "sg:phone":"+41 52 203 55 81",
    "sg:postcode":"8406",
    "sg:province":"Z\u00fcrich",
    "wof:name":"Charles Edenhofer West-garage",
    "wof:placetype":"venue"
},
  "geometry": {"coordinates":[8.70775,47.460693],"type":"Point"}
}