{
  "type": "Feature",
  "properties": {
    "iso:country":"CH",
    "sg:address":"Kommetsr\u00fcti 18",
    "sg:city":"Wolhusen",
    "sg:orig_category":"Sonstige mit der Informatik verbundene T\u00e4tigkeiten",
    "sg:phone":"+41 41 490 28 91",
    "sg:postcode":"6110",
    "sg:province":"Luzern",
    "wof:name":"Future Gate Pc D\u00f6tterer",
    "wof:placetype":"venue"
},
  "geometry": {"coordinates":[8.0681276321,47.0560493469],"type":"Point"}
}