{
  "type": "Feature",
  "properties": {
    "iso:country":"CH",
    "sg:address":"Stutzstrasse 50 8834 Schindellegi. Postfach",
    "sg:city":"Schindellegi",
    "sg:orig_category":"Unclassifiable Establishments",
    "sg:postcode":"8834",
    "sg:province":"Schwyz",
    "wof:name":"M\u00fcller Group Sa",
    "wof:placetype":"venue"
},
  "geometry": {"coordinates":[7.2680220604,47.1225967407],"type":"Point"}
}