{
  "type": "Feature",
  "properties": {
    "iso:country":"CH",
    "sg:address":"Riedmattstrasse 22",
    "sg:city":"Wernetshausen",
    "sg:classifiers":[
        {
            "category":"Landmark",
            "subcategory":"Square",
            "type":"Public Place"
        }
    ],
    "sg:phone":"+41 19373297",
    "sg:postcode":"8342",
    "sg:province":"Z\u00fcrich",
    "sg:tags":[
        "fault",
        "location",
        "cable"
    ],
    "wof:name":"Edwin T\u00fcscher Fehlerortungstechnik",
    "wof:placetype":"venue"
},
  "geometry": {"coordinates":[8.862496,47.2994],"type":"Point"}
}