{
  "type": "Feature",
  "properties": {
    "iso:country":"CH",
    "sg:address":"Chisenmattweg 12a",
    "sg:city":"Konolfingen",
    "sg:orig_category":"Organisationen der Wohlfahrtspflege",
    "sg:phone":"+41 71 223 40 11",
    "sg:postcode":"3510",
    "sg:province":"Bern",
    "wof:name":"Pro Senectute",
    "wof:placetype":"venue"
},
  "geometry": {"coordinates":[9.3704376221,47.4208641052],"type":"Point"}
}