{
  "type": "Feature",
  "properties": {
    "iso:country":"CH",
    "sg:address":"Rue Neuve 4",
    "sg:city":"Nyon",
    "sg:orig_category":"Detailhandel mit Sportartikeln Fachdetailhandel in Verkaufsr\u00e4umen",
    "sg:phone":"+41 22 361 38 35",
    "sg:postcode":"1260",
    "sg:province":"Vaud",
    "wof:name":"Ros\u00e9 Jean-luc, Successeur De Ros\u00e9 Raoul",
    "wof:placetype":"venue"
},
  "geometry": {"coordinates":[6.2389240265,46.3832702637],"type":"Point"}
}