{
  "type": "Feature",
  "properties": {
    "iso:country":"CH",
    "sg:address":"Litzistrasse 3",
    "sg:city":"Oberlunkhofen",
    "sg:orig_category":"Sonstige mit der Informatik verbundene T\u00e4tigkeiten",
    "sg:postcode":"8917",
    "sg:province":"Aargau",
    "wof:name":"Kogler Informatik Gmbh",
    "wof:placetype":"venue"
},
  "geometry": {"coordinates":[8.2812671661,47.4539642334],"type":"Point"}
}