{
  "type": "Feature",
  "properties": {
    "iso:country":"CH",
    "sg:address":"Brunnengasse 8",
    "sg:city":"Schaffhausen",
    "sg:orig_category":"Detailhandel mit Schuhen Reparatur von Schuhen U Lederwaren",
    "sg:phone":"+41 79 418 28 62",
    "sg:postcode":"8200",
    "sg:province":"Schaffhausen",
    "wof:name":"Guido Faccani",
    "wof:placetype":"venue"
},
  "geometry": {"coordinates":[8.6374769211,47.696182251],"type":"Point"}
}