{
  "type": "Feature",
  "properties": {
    "iso:country":"CH",
    "sg:address":"Schachenstrasse 6",
    "sg:city":"Lyssach",
    "sg:orig_category":"Elektrizit\u00e4tsversorgung Sanit\u00e4r U Heizungsinstallation",
    "sg:phone":"+41 27 203 44 51",
    "sg:postcode":"3421",
    "sg:province":"Bern",
    "wof:name":"Soval\u00e8re Sa",
    "wof:placetype":"venue"
},
  "geometry": {"coordinates":[7.3588571548,46.2280921936],"type":"Point"}
}