{
  "type": "Feature",
  "properties": {
    "iso:country":"CH",
    "sg:address":"Bahnhofstrasse 44",
    "sg:city":"Wikon",
    "sg:orig_category":"Allgemeiner Hoch U Tiefbau",
    "sg:phone":"+41 62 758 42 25",
    "sg:postcode":"4806",
    "sg:province":"Luzern",
    "wof:name":"Bau Ag Luzern, Mit Baugesch\u00e4ft In Reiden, Filiale Wikon",
    "wof:placetype":"venue"
},
  "geometry": {"coordinates":[7.95612,47.262314],"type":"Point"}
}