{
  "type": "Feature",
  "properties": {
    "iso:country":"CH",
    "sg:address":"Wiedenmoos.",
    "sg:city":"Sennwald",
    "sg:orig_category":"Interessenvertretungen",
    "sg:postcode":"9466",
    "sg:province":"St. Gallen",
    "wof:name":"Stiftung Aebi-gaissmaier Paul.",
    "wof:placetype":"venue"
},
  "geometry": {"coordinates":[9.5058145523,47.2602615356],"type":"Point"}
}