{
  "type": "Feature",
  "properties": {
    "iso:country":"CH",
    "sg:address":"Chemin De L'ep\u00e9nontaz 23",
    "sg:city":"Bernex",
    "sg:orig_category":"Sonstige pers\u00f6nliche Dienstleistungen",
    "sg:phone":"+41 21 691 70 30",
    "sg:postcode":"1233",
    "sg:province":"Gen\u00e8ve",
    "wof:name":"Aqua Mer, D. Weissert",
    "wof:placetype":"venue"
},
  "geometry": {"coordinates":[6.561070919,46.5353317261],"type":"Point"}
}