{
  "type": "Feature",
  "properties": {
    "iso:country":"CH",
    "sg:address":"Langackerstrasse 2",
    "sg:city":"Cham",
    "sg:orig_category":"Handelsvermittlung von Brennstoffen, Erzen, Metallen U Chemikalien",
    "sg:phone":"+41 56 668 14 74",
    "sg:postcode":"6330",
    "sg:province":"Zug",
    "wof:name":"Tracobo Ag",
    "wof:placetype":"venue"
},
  "geometry": {"coordinates":[8.4535274506,47.1973190308],"type":"Point"}
}