{
  "type": "Feature",
  "properties": {
    "iso:country":"CH",
    "sg:address":"Chemin Jean-bapt Vandelle 10 1290 Versoix Case Postale 268",
    "sg:city":"Versoix",
    "sg:orig_category":"Bauspenglerei Dachdeckerei",
    "sg:phone":"+41 22 755 10 45",
    "sg:postcode":"1290",
    "sg:province":"Gen\u00e8ve",
    "wof:name":"Alessi Sanitaires Sa",
    "wof:placetype":"venue"
},
  "geometry": {"coordinates":[6.165509,46.280952],"type":"Point"}
}