{
  "type": "Feature",
  "properties": {
    "iso:country":"CH",
    "sg:address":"Rue Saint-laurent 9",
    "sg:city":"Estavayer-le-lac",
    "sg:orig_category":"Kinderkrippen U horte",
    "sg:phone":"+41 26 663 10 30",
    "sg:postcode":"1470",
    "sg:province":"Fribourg",
    "wof:name":"Cr\u00e8che Catholique",
    "wof:placetype":"venue"
},
  "geometry": {"coordinates":[6.8473591805,46.8503799438],"type":"Point"}
}