{
  "type": "Feature",
  "properties": {
    "iso:country":"CH",
    "sg:address":"Gachnangerstrasse 2",
    "sg:city":"Frauenfeld",
    "sg:orig_category":"G\u00fcterbef\u00f6rderung im Strassenverkehr",
    "sg:phone":"+41 33 822 68 67",
    "sg:postcode":"8500",
    "sg:province":"Thurgau",
    "wof:name":"K\u00fcbli Karl.",
    "wof:placetype":"venue"
},
  "geometry": {"coordinates":[7.866642952,46.6830673218],"type":"Point"}
}