{
  "type": "Feature",
  "properties": {
    "iso:country":"CH",
    "sg:address":"S\u00fcri 80 3204 Rossh\u00e4usern. Postfach",
    "sg:city":"Rossh\u00e4usern",
    "sg:orig_category":"RESTAURANTS: TEA-ROOMS",
    "sg:phone":"+41 31 311 32 05",
    "sg:postcode":"3204",
    "sg:province":"Bern",
    "wof:name":"Restaurant Zum \u00c4usseren Stand Liechti G.",
    "wof:placetype":"venue"
},
  "geometry": {"coordinates":[7.4459280968,46.9488258362],"type":"Point"}
}