{
  "type": "Feature",
  "properties": {
    "iso:country":"CH",
    "sg:address":"Werdenstrasse 90",
    "sg:city":"Grabs",
    "sg:orig_category":"Pensionskassen",
    "sg:phone":"+41 81 750 32 60",
    "sg:postcode":"9472",
    "sg:province":"St. Gallen",
    "wof:name":"Wohlfahrtsfonds Der Vetsch Christian Ag, Hoch- & Tiefbau, Grabs/sg",
    "wof:placetype":"venue"
},
  "geometry": {"coordinates":[9.464384079,47.1822013855],"type":"Point"}
}