{
  "type": "Feature",
  "properties": {
    "iso:country":"CH",
    "sg:address":"Gl\u00e4rnischstrasse 31",
    "sg:city":"Glarus",
    "sg:orig_category":"Allgemeiner Hochbau Zimmerei, Dachdeckerei, Bauspenglerei U Abdichtung",
    "sg:phone":"+41 79 608 39 90",
    "sg:postcode":"8750",
    "sg:province":"Glarus",
    "wof:name":"Kellenberger A., Bedachungen",
    "wof:placetype":"venue"
},
  "geometry": {"coordinates":[9.062392,47.037003],"type":"Point"}
}