{
  "type": "Feature",
  "properties": {
    "iso:country":"CH",
    "sg:address":"Bahnhofstrasse 30",
    "sg:city":"Zug",
    "sg:orig_category":"Herstellung von Duft U K\u00f6rperpflegemitteln",
    "sg:postcode":"6300",
    "sg:province":"Zug",
    "wof:name":"Royal Bijou Gmbh",
    "wof:placetype":"venue"
},
  "geometry": {"coordinates":[8.5160140991,47.1702613831],"type":"Point"}
}