{
  "type": "Feature",
  "properties": {
    "iso:country":"CH",
    "sg:address":"Weiacherstrasse 80",
    "sg:city":"Rorbas",
    "sg:classifiers":[
        {
            "category":"Bars & Pubs",
            "type":"Food & Drink"
        }
    ],
    "sg:phone":"+41 56 441 10 28",
    "sg:postcode":"8427",
    "sg:province":"Z\u00fcrich",
    "wof:name":"Shakespeare-pub",
    "wof:placetype":"venue"
},
  "geometry": {"coordinates":[8.206691,47.485828],"type":"Point"}
}