{
  "type": "Feature",
  "properties": {
    "iso:country":"CH",
    "sg:address":"Hohmattring 20",
    "sg:city":"Turbenthal",
    "sg:orig_category":"Fahrschulen, Flugschulen",
    "sg:phone":"+41 52 385 24 90",
    "sg:postcode":"8488",
    "sg:province":"Z\u00fcrich",
    "wof:name":"Elisabeth Schoch Autofahrschule",
    "wof:placetype":"venue"
},
  "geometry": {"coordinates":[8.841750145,47.4436073303],"type":"Point"}
}