{
  "type": "Feature",
  "properties": {
    "iso:country":"CH",
    "sg:address":"Rietstrasse 2 8108 D\u00e4llikon. Postfach",
    "sg:city":"Z\u00fcrich",
    "sg:orig_category":"Herstellung von sonstigen elektrischen Ausr\u00fcstungen",
    "sg:phone":"+41 13778090",
    "sg:postcode":"8046",
    "sg:province":"Z\u00fcrich",
    "wof:name":"Elnova Ag",
    "wof:placetype":"venue"
},
  "geometry": {"coordinates":[8.4341115952,47.4480857849],"type":"Point"}
}