{
  "type": "Feature",
  "properties": {
    "iso:country":"CH",
    "sg:address":"Finkenweg 15",
    "sg:city":"Gerolfingen",
    "sg:orig_category":"Unclassifiable Establishments",
    "sg:postcode":"2575",
    "sg:province":"Bern",
    "wof:name":"R. Blattmann Consulting",
    "wof:placetype":"venue"
},
  "geometry": {"coordinates":[7.2002248764,47.0695991516],"type":"Point"}
}