{
  "type": "Feature",
  "properties": {
    "iso:country":"CH",
    "sg:address":"Bahnhofstrasse 23 4450 Sissach. Postfach",
    "sg:city":"Sissach",
    "sg:orig_category":"Architektur U Ingenieurb\u00fcros",
    "sg:phone":"+41 61 973 23 33",
    "sg:postcode":"4450",
    "sg:province":"Basel-Landschaft",
    "wof:name":"Dreifels Ag Planung U. Entwicklung Von Methoden U. Ger\u00e4ten Usw",
    "wof:placetype":"venue"
},
  "geometry": {"coordinates":[7.813771,47.462669],"type":"Point"}
}