{
  "type": "Feature",
  "properties": {
    "iso:country":"CH",
    "sg:address":"Tour-haldimand Av. De La 5",
    "sg:city":"Pully",
    "sg:orig_category":"Fernmeldedienste",
    "sg:phone":"+41 21 691 75 09",
    "sg:postcode":"1009",
    "sg:province":"Vaud",
    "wof:name":"Cellsite S\u00e0rl",
    "wof:placetype":"venue"
},
  "geometry": {"coordinates":[6.5580701828,46.5100784302],"type":"Point"}
}