{
  "type": "Feature",
  "properties": {
    "iso:country":"CH",
    "sg:address":"Claramattweg 8",
    "sg:city":"Basel",
    "sg:orig_category":"Interessenvertretungen",
    "sg:phone":"+41 61 690 92 00",
    "sg:postcode":"4057",
    "sg:province":"Basel-Stadt",
    "wof:name":"Schweizer Jugend Forscht",
    "wof:placetype":"venue"
},
  "geometry": {"coordinates":[7.5951662064,47.5626525879],"type":"Point"}
}