{
  "type": "Feature",
  "properties": {
    "iso:country":"CH",
    "sg:address":"Tischlerweg 11",
    "sg:city":"Z\u00fcrich",
    "sg:orig_category":"Geb\u00e4ude, Wohnungsreinigung",
    "sg:phone":"+41 14312236",
    "sg:postcode":"8048",
    "sg:province":"Z\u00fcrich",
    "wof:name":"Heini Gl\u00e4ttli Fensterreinigungsgesch\u00e4ft",
    "wof:placetype":"venue"
},
  "geometry": {"coordinates":[8.4716682434,47.3913116455],"type":"Point"}
}