{
  "type": "Feature",
  "properties": {
    "iso:country":"CH",
    "sg:address":"Via Cantonale 25",
    "sg:city":"Magliaso",
    "sg:orig_category":"Landesverteidigung, Sozialversicherung \u00d6ffentliche Verwaltung",
    "sg:phone":"+41 91 606 14 19",
    "sg:postcode":"6983",
    "sg:province":"Ticino",
    "wof:name":"Centro Di Protezione Civile Di Magliaso",
    "wof:placetype":"venue"
},
  "geometry": {"coordinates":[8.8889141083,45.9838752747],"type":"Point"}
}