{
  "type": "Feature",
  "properties": {
    "iso:country":"CH",
    "sg:address":"Rue Colomb 11 1860 Aigle Case Postale 60",
    "sg:city":"Aigle",
    "sg:orig_category":"Detailhandel mit Beleuchtungs U Haushaltsgegenst\u00e4nden Elektroinstallation",
    "sg:phone":"+41 24 466 31 11",
    "sg:postcode":"1860",
    "sg:province":"Vaud",
    "wof:name":"Soci\u00e9t\u00e9 Romande D'electricit\u00e9",
    "wof:placetype":"venue"
},
  "geometry": {"coordinates":[6.969975,46.318012],"type":"Point"}
}