{
  "type": "Feature",
  "properties": {
    "iso:country":"CH",
    "sg:address":"Hauptstrasse 40",
    "sg:city":"Nidau",
    "sg:orig_category":"Grosshandel mit Nahrungsmitteln, Getr\u00e4nken U Tabakwaren ohne ausgepr\u00e4gten Schwerpunkt",
    "sg:phone":"+41 32 331 62 29",
    "sg:postcode":"2560",
    "sg:province":"Bern",
    "wof:name":"Maruccio Luigi",
    "wof:placetype":"venue"
},
  "geometry": {"coordinates":[7.2404880524,47.1253738403],"type":"Point"}
}