{
  "type": "Feature",
  "properties": {
    "iso:country":"CH",
    "sg:address":"6010",
    "sg:city":"Kriens",
    "sg:orig_category":"Steuer\u00e4mter",
    "sg:phone":"+41 41 329 61 11",
    "sg:postcode":"6010",
    "sg:province":"Luzern",
    "wof:name":"Steueramt",
    "wof:placetype":"venue"
},
  "geometry": {"coordinates":[8.2653503418,47.0156707764],"type":"Point"}
}