{
  "type": "Feature",
  "properties": {
    "iso:country":"CH",
    "sg:address":"Route De Lausanne 23",
    "sg:city":"Yverdon-les-bains",
    "sg:orig_category":"Werbevermittlung",
    "sg:phone":"+41 24 425 85 60",
    "sg:postcode":"1400",
    "sg:province":"Vaud",
    "wof:name":"Sga/apg Soci\u00e9t\u00e9 G\u00e9n\u00e9rale D'affichage",
    "wof:placetype":"venue"
},
  "geometry": {"coordinates":[6.6487011909,46.7632293701],"type":"Point"}
}