{
  "type": "Feature",
  "properties": {
    "iso:country":"CH",
    "sg:address":"Saumstrasse 25",
    "sg:city":"Z\u00fcrich",
    "sg:orig_category":"Vermietung U Verpachtung von eigenen Immobilien",
    "sg:phone":"+41 14621700",
    "sg:postcode":"8055",
    "sg:province":"Z\u00fcrich",
    "wof:name":"Az-immobilien Ag",
    "wof:placetype":"venue"
},
  "geometry": {"coordinates":[8.5126247406,47.3715553284],"type":"Point"}
}