{
  "type": "Feature",
  "properties": {
    "iso:country":"CH",
    "sg:address":"Grand-rue 25",
    "sg:city":"Fribourg",
    "sg:orig_category":"Markt U Meinungsforschung",
    "sg:phone":"+41 26 323 19 93",
    "sg:postcode":"1702",
    "sg:province":"Fribourg",
    "wof:name":"Incognito Sa",
    "wof:placetype":"venue"
},
  "geometry": {"coordinates":[7.1638798714,46.8053665161],"type":"Point"}
}