{
  "type": "Feature",
  "properties": {
    "iso:country":"CH",
    "sg:address":"Rigistr. 2",
    "sg:city":"Merenschwand",
    "sg:orig_category":"Herstellung von Metallerzeugnissen ohne Maschinenbau",
    "sg:phone":"+41 55 442 47 65",
    "sg:postcode":"5634",
    "sg:province":"Aargau",
    "wof:name":"Seminorm Zahner Ag",
    "wof:placetype":"venue"
},
  "geometry": {"coordinates":[8.8522949219,47.1906738281],"type":"Point"}
}