{
  "type": "Feature",
  "properties": {
    "iso:country":"CH",
    "sg:address":"B\u00f6nlerstrasse 54",
    "sg:city":"Ottikon",
    "sg:classifiers":[
        {
            "category":"Home & Garden",
            "subcategory":"Carpets & Floor Coverings",
            "type":"Retail Goods"
        }
    ],
    "sg:phone":"+41 52 385 56 50",
    "sg:postcode":"8626",
    "sg:province":"Z\u00fcrich",
    "wof:name":"Flexi-holzhandels Gmbh",
    "wof:placetype":"venue"
},
  "geometry": {"coordinates":[8.7878313065,47.2966346741],"type":"Point"}
}