{
  "type": "Feature",
  "properties": {
    "iso:country":"CH",
    "sg:address":"St.-jakob-strasse 48",
    "sg:city":"St.gallen",
    "sg:orig_category":"Detailhandel mit Fleisch U Fleischwaren",
    "sg:phone":"+41 71 244 81 32",
    "sg:postcode":"9000",
    "sg:province":"St. Gallen",
    "wof:name":"Metzgerei Schmid Gmbh",
    "wof:placetype":"venue"
},
  "geometry": {"coordinates":[8.4765996933,48.0781707764],"type":"Point"}
}