{
  "type": "Feature",
  "properties": {
    "iso:country":"CH",
    "sg:address":"3975 Bluche-randogne. Postfach",
    "sg:city":"Montana-vermala",
    "sg:orig_category":"Verwertung von Milch",
    "sg:phone":"+41 27 481 22 46",
    "sg:postcode":"3962",
    "wof:name":"Bonvin Pascal, Laiterie Au Petit Chalet.",
    "wof:placetype":"venue"
},
  "geometry": {"coordinates":[7.5151138306,46.2997512817],"type":"Point"}
}