{
  "type": "Feature",
  "properties": {
    "iso:country":"CH",
    "sg:address":"Postackerstrasse 5",
    "sg:city":"Balsthal",
    "sg:orig_category":"Unclassifiable Establishments",
    "sg:postcode":"4710",
    "sg:province":"Solothurn",
    "wof:name":"Ehrsam Gartenbau Ag",
    "wof:placetype":"venue"
},
  "geometry": {"coordinates":[7.6962218285,47.3137893677],"type":"Point"}
}