{
  "type": "Feature",
  "properties": {
    "iso:country":"CH",
    "sg:address":"Rue Du Mont-blanc",
    "sg:city":"Gen\u00e8ve",
    "sg:orig_category":"Unternehmensberatung",
    "sg:phone":"+41 22 900 07 07",
    "sg:postcode":"1201",
    "sg:province":"Gen\u00e8ve",
    "wof:name":"Rolest Management Sa",
    "wof:placetype":"venue"
},
  "geometry": {"coordinates":[6.1437950134,46.2090606689],"type":"Point"}
}