{
  "type": "Feature",
  "properties": {
    "iso:country":"CH",
    "sg:address":"Lindenstrasse 39 8400 Winterthur. Postfach",
    "sg:city":"Winterthur",
    "sg:orig_category":"Pensionskassen",
    "sg:phone":"+41 52 268 04 04",
    "sg:postcode":"8400",
    "sg:province":"Z\u00fcrich",
    "wof:name":"Sozialfonds Des Cmv",
    "wof:placetype":"venue"
},
  "geometry": {"coordinates":[8.7159900665,47.5044517517],"type":"Point"}
}