{
  "type": "Feature",
  "properties": {
    "iso:country":"CH",
    "sg:address":"Limmatquai 120 8001 Z\u00fcrich. Postfach 892",
    "sg:city":"Z\u00fcrich",
    "sg:orig_category":"Interessenvertretungen Verwaltung von Immobilien",
    "sg:phone":"+41 22 344 88 20",
    "sg:postcode":"8025",
    "wof:name":"Cogerim",
    "wof:placetype":"venue"
},
  "geometry": {"coordinates":[6.1277399063,46.2083816528],"type":"Point"}
}