{
  "type": "Feature",
  "properties": {
    "iso:country":"CH",
    "sg:address":"St\u00e4dtle 49",
    "sg:city":"Vaduz",
    "sg:orig_category":"Zivilschutz",
    "sg:postcode":"9490",
    "wof:name":"Amt F\u00fcr Zivilschutz",
    "wof:placetype":"venue"
},
  "geometry": {"coordinates":[9.5226507187,47.1371841431],"type":"Point"}
}