{
  "type": "Feature",
  "properties": {
    "iso:country":"CH",
    "sg:address":"Moosweg 8",
    "sg:city":"Br\u00fcgg",
    "sg:classifiers":[
        {
            "category":"Manufacturing",
            "subcategory":"Metals",
            "type":"Manufacturing & Wholesale Goods"
        }
    ],
    "sg:phone":"+41 32 366 60 90",
    "sg:postcode":"2555",
    "sg:province":"Bern",
    "sg:tags":[
        "alloy",
        "aluminium"
    ],
    "wof:name":"H\u00e4uselmann Metall Ag",
    "wof:placetype":"venue"
},
  "geometry": {"coordinates":[7.266198,47.123066],"type":"Point"}
}