{
  "type": "Feature",
  "properties": {
    "iso:country":"CH",
    "sg:address":"Heckenweg 3",
    "sg:city":"Aarberg",
    "sg:orig_category":"Kaminbau",
    "sg:phone":"+41 32 392 55 88",
    "sg:postcode":"3270",
    "sg:province":"Bern",
    "wof:name":"M\u00fcller Kamine Ag",
    "wof:placetype":"venue"
},
  "geometry": {"coordinates":[7.2833819389,47.0498390198],"type":"Point"}
}