{
  "type": "Feature",
  "properties": {
    "iso:country":"CH",
    "sg:address":"Seewjinenstrasse 2 3930 Visp. Postfach 39",
    "sg:city":"Visp",
    "sg:orig_category":"Unternehmensberatung",
    "sg:phone":"+41 27 946 32 40",
    "sg:postcode":"3930",
    "sg:province":"Valais",
    "wof:name":"A & A Andereggen & Associates Ag",
    "wof:placetype":"venue"
},
  "geometry": {"coordinates":[7.8876409531,46.2923202515],"type":"Point"}
}