{
  "type": "Feature",
  "properties": {
    "iso:country":"CH",
    "sg:address":"7189",
    "sg:city":"Rueras",
    "sg:orig_category":"Primarschulen",
    "sg:phone":"+41 81 949 25 58",
    "sg:postcode":"7189",
    "sg:province":"Graubunden",
    "wof:name":"Primarschule",
    "wof:placetype":"venue"
},
  "geometry": {"coordinates":[8.7533197403,46.6759796143],"type":"Point"}
}