{
  "type": "Feature",
  "properties": {
    "iso:country":"CH",
    "sg:address":"Augsterheglistrasse 30",
    "sg:city":"Pratteln",
    "sg:orig_category":"Handelsvermittlung U Grosshandel",
    "sg:phone":"+41 71 931 52 53",
    "sg:postcode":"4133",
    "sg:province":"Basel-Landschaft",
    "wof:name":"Alldecor Gmbh Handelunternehmen Mit Waren Wie Poster U. Einrahmungen Usw",
    "wof:placetype":"venue"
},
  "geometry": {"coordinates":[9.0411472321,47.4113349915],"type":"Point"}
}