{
  "type": "Feature",
  "properties": {
    "iso:country":"CH",
    "sg:address":"Route Chardonne 1",
    "sg:city":"Puidoux",
    "sg:orig_category":"Hardwareberatung Softwareentwicklung U beratung",
    "sg:phone":"+41 21 946 02 90",
    "sg:postcode":"1070",
    "sg:province":"Vaud",
    "wof:name":"Bison Schweiz Ag",
    "wof:placetype":"venue"
},
  "geometry": {"coordinates":[6.7702088356,46.490852356],"type":"Point"}
}