{
  "type": "Feature",
  "properties": {
    "iso:country":"CH",
    "sg:address":"Dorf 8",
    "sg:city":"Ettiswil",
    "sg:orig_category":"Sonstiger Grosshandel",
    "sg:postcode":"6218",
    "sg:province":"Luzern",
    "wof:name":"Suter The Merry Lord's Productions",
    "wof:placetype":"venue"
},
  "geometry": {"coordinates":[8.0177116394,47.1485862732],"type":"Point"}
}