{
  "type": "Feature",
  "properties": {
    "iso:country":"CH",
    "sg:address":"Unionsgasse 5",
    "sg:city":"Biel/bienne",
    "sg:orig_category":"Architekturb\u00fcros",
    "sg:phone":"+41 32 322 42 74",
    "sg:postcode":"2502",
    "sg:province":"Bern",
    "wof:name":"Walter Rey Architekturb\u00fcro",
    "wof:placetype":"venue"
},
  "geometry": {"coordinates":[7.243767,47.139084],"type":"Point"}
}