{
  "type": "Feature",
  "properties": {
    "iso:country":"CH",
    "sg:address":"Aebnitstrasse 3",
    "sg:city":"Arch",
    "sg:orig_category":"Oberfl\u00e4chenveredlung U W\u00e4rmebehandlung",
    "sg:phone":"+41 19110715",
    "sg:postcode":"3296",
    "sg:province":"Bern",
    "wof:name":"Durrer Systems Oberfl\u00e4chentechnik Gmbh",
    "wof:placetype":"venue"
},
  "geometry": {"coordinates":[8.5816507339,47.3157463074],"type":"Point"}
}