{
  "type": "Feature",
  "properties": {
    "addr:full":"Gr\u00fcningerstrasse Ottikon Z\u00fcrich 8626",
    "addr:postcode":"8626",
    "addr:street":"Grueningerstrasse",
    "iso:country":"CH",
    "sg:address":"Gr\u00fcningerstrasse",
    "sg:city":"Ottikon",
    "sg:orig_category":"Bauschreinerei Innenausbau",
    "sg:phone":"+41 19351214",
    "sg:postcode":"8626",
    "sg:province":"Z\u00fcrich",
    "wof:name":"Sch\u00f6nb\u00e4chler K\u00fcchen Gmbh",
    "wof:placetype":"venue"
},
  "geometry": {"coordinates":[8.782718,47.297855],"type":"Point"}
}