{
  "type": "Feature",
  "properties": {
    "iso:country":"CH",
    "sg:address":"Steinentorstrasse 20",
    "sg:city":"Basel",
    "sg:orig_category":"Museen",
    "sg:postcode":"4051",
    "sg:province":"Basel-Stadt",
    "wof:name":"Db Art Dagmar Bolliger",
    "wof:placetype":"venue"
},
  "geometry": {"coordinates":[8.5813455582,47.3271064758],"type":"Point"}
}