{
  "type": "Feature",
  "properties": {
    "iso:country":"CH",
    "sg:address":"Lauetstrasse 35",
    "sg:city":"Otelfingen",
    "sg:orig_category":"Herstellung von Metallkonstruktionen Stahl U Leichtmetallbau",
    "sg:phone":"+41 18401909",
    "sg:postcode":"8112",
    "sg:province":"Z\u00fcrich",
    "wof:name":"M. Huber Gmbh Alu-& Chromnickelstahl-verarbeitung",
    "wof:placetype":"venue"
},
  "geometry": {"coordinates":[8.4079761505,47.4569473267],"type":"Point"}
}