{
  "type": "Feature",
  "properties": {
    "addr:full":"Rothusweg 12 6300 Zug. Postfach Zug Zug 6300",
    "addr:housenumber":"12",
    "addr:postcode":"6300;postfach;6300",
    "addr:street":"Rothusweg;Zug",
    "iso:country":"CH",
    "sg:address":"Rothusweg 12 6300 Zug. Postfach",
    "sg:city":"Zug",
    "sg:orig_category":"Architektur U Ingenieurb\u00fcros",
    "sg:phone":"+41 41 720 09 99",
    "sg:postcode":"6300",
    "sg:province":"Zug",
    "wof:name":"Zpa Zwimpfer Partner Zug Ag Architektur Und Planungsb\u00fcro",
    "wof:placetype":"venue"
},
  "geometry": {"coordinates":[8.520039,47.170506],"type":"Point"}
}