{
  "type": "Feature",
  "properties": {
    "iso:country":"CH",
    "sg:address":"Landhofstrasse 2",
    "sg:city":"Reichenburg",
    "sg:orig_category":"Grosshandel mit Datenverarbeitungsger\u00e4ten Grosshandel mit Software",
    "sg:phone":"+41 55 444 33 77",
    "sg:postcode":"8864",
    "sg:province":"Schwyz",
    "wof:name":"Computer Rbm Markaj",
    "wof:placetype":"venue"
},
  "geometry": {"coordinates":[8.9813022614,47.1718177795],"type":"Point"}
}