{
  "type": "Feature",
  "properties": {
    "iso:country":"CH",
    "sg:address":"Neuhaus",
    "sg:city":"Alberswil",
    "sg:orig_category":"Mechanik",
    "sg:postcode":"6248",
    "sg:province":"Luzern",
    "wof:name":"Huguet J.p.",
    "wof:placetype":"venue"
},
  "geometry": {"coordinates":[6.5751399994,46.8234176636],"type":"Point"}
}