{
  "type": "Feature",
  "properties": {
    "iso:country":"CH",
    "sg:address":"Les Paccots",
    "sg:city":"Ch\u00e2tel-st-denis",
    "sg:orig_category":"Unternehmensberatung",
    "sg:phone":"+41 21 948 82 02",
    "sg:postcode":"1618",
    "sg:province":"Fribourg",
    "wof:name":"Intermedex Sa",
    "wof:placetype":"venue"
},
  "geometry": {"coordinates":[6.9188947678,46.5245399475],"type":"Point"}
}