{
  "type": "Feature",
  "properties": {
    "iso:country":"CH",
    "sg:address":"K\u00f6chlistrasse 17 8004 Z\u00fcrich. Postfach",
    "sg:city":"Z\u00fcrich",
    "sg:orig_category":"RESTAURANTS: TEA-ROOMS",
    "sg:postcode":"8001",
    "sg:province":"Z\u00fcrich",
    "wof:name":"Malik Gmbh Restaurant",
    "wof:placetype":"venue"
},
  "geometry": {"coordinates":[8.5232467651,47.3732681274],"type":"Point"}
}