{
  "type": "Feature",
  "properties": {
    "iso:country":"CH",
    "sg:address":"Hardstrasse 77",
    "sg:city":"Neuenhof",
    "sg:orig_category":"Malerei",
    "sg:phone":"+41 79 209 64 05",
    "sg:postcode":"5432",
    "sg:province":"Aargau",
    "wof:name":"Alfred Muriset Malergesch\u00e4ft",
    "wof:placetype":"venue"
},
  "geometry": {"coordinates":[8.3291883469,47.4514083862],"type":"Point"}
}