{
  "type": "Feature",
  "properties": {
    "iso:country":"CH",
    "sg:address":"Via Bellinzona 24",
    "sg:city":"Biasca",
    "sg:orig_category":"HOTELS: MIT RESTAURANT Kongress- and Tagungshotels mit Restaurant",
    "sg:phone":"+41 91 862 13 31",
    "sg:postcode":"6710",
    "sg:province":"Ticino",
    "wof:name":"Albergo Nazionale",
    "wof:placetype":"venue"
},
  "geometry": {"coordinates":[8.9737873077,46.3518295288],"type":"Point"}
}