{
  "type": "Feature",
  "properties": {
    "iso:country":"CH",
    "sg:address":"Immenbachstrasse 35",
    "sg:city":"Riehen",
    "sg:orig_category":"Sonstiger Fachdetailhandel mit Nahrungsmitteln, Getr\u00e4nken U Tabak in Verkaufsr\u00e4umen",
    "sg:phone":"+41 56 622 03 13",
    "sg:postcode":"4125",
    "sg:province":"Basel-Stadt",
    "wof:name":"Rolf Beeler, Ma\u00eetre Fromager",
    "wof:placetype":"venue"
},
  "geometry": {"coordinates":[8.2925214767,47.3893241882],"type":"Point"}
}