{
  "type": "Feature",
  "properties": {
    "iso:country":"CH",
    "sg:address":"Avenue Agassiz 2",
    "sg:city":"Lausanne",
    "sg:orig_category":"Wirtschafts- and Arbeitgeberverb\u00e4nde",
    "sg:phone":"+41 21 319 71 11",
    "sg:postcode":"1003",
    "sg:province":"Vaud",
    "wof:name":"Assoc.de L'industrie Vaudoise Des Transports Routiers Aivtr",
    "wof:placetype":"venue"
},
  "geometry": {"coordinates":[6.631734848,46.518119812],"type":"Point"}
}