{
  "type": "Feature",
  "properties": {
    "iso:country":"CH",
    "sg:address":"Neptunstrasse 86",
    "sg:city":"Z\u00fcrich",
    "sg:orig_category":"Malerei",
    "sg:phone":"+41 13831918",
    "sg:postcode":"8032",
    "sg:province":"Z\u00fcrich",
    "wof:name":"Klaus Loth Malergesch\u00e4ft",
    "wof:placetype":"venue"
},
  "geometry": {"coordinates":[8.5580816269,47.3648529053],"type":"Point"}
}