{
  "type": "Feature",
  "properties": {
    "iso:country":"CH",
    "sg:address":"Kapellenweg 5",
    "sg:city":"Buttwil",
    "sg:orig_category":"Grosshandel mit Maschinen U Ausr\u00fcstungen Herstellung von Maschinen f\u00fcr die Nahrungsmittel, Getr\u00e4nkeh",
    "sg:phone":"+41 56 675 50 40",
    "sg:postcode":"5632",
    "sg:province":"Aargau",
    "wof:name":"Krones Ag",
    "wof:placetype":"venue"
},
  "geometry": {"coordinates":[8.313249588,47.2689285278],"type":"Point"}
}