{
  "type": "Feature",
  "properties": {
    "iso:country":"CH",
    "sg:address":"Morgins",
    "sg:city":"Troistorrents",
    "sg:orig_category":"Reiseb\u00fcros U Reiseveranstalter",
    "sg:postcode":"1872",
    "sg:province":"Valais",
    "wof:name":"Morgins-tourisme",
    "wof:placetype":"venue"
},
  "geometry": {"coordinates":[6.9395551682,46.2492294312],"type":"Point"}
}