{
  "type": "Feature",
  "properties": {
    "iso:country":"CH",
    "sg:address":"Churfirstenstrasse 11",
    "sg:city":"Wallisellen",
    "sg:orig_category":"Herstellung von Duft U K\u00f6rperpflegemitteln",
    "sg:phone":"+41 18303172",
    "sg:postcode":"8304",
    "sg:province":"Z\u00fcrich",
    "wof:name":"Aubry Fernand Cosmetics Gmbh",
    "wof:placetype":"venue"
},
  "geometry": {"coordinates":[8.6023426056,47.410774231],"type":"Point"}
}