{
  "type": "Feature",
  "properties": {
    "iso:country":"CH",
    "sg:address":"Laupenstrasse 11",
    "sg:city":"Goldingen",
    "sg:orig_category":"RESTAURANTS: TEA-ROOMS",
    "sg:phone":"+41 55 284 15 69",
    "sg:postcode":"8638",
    "sg:province":"St. Gallen",
    "wof:name":"Restaurant/hotel Freihof, Ch. + B. Nick",
    "wof:placetype":"venue"
},
  "geometry": {"coordinates":[8.9489583969,47.2638816833],"type":"Point"}
}