{
  "type": "Feature",
  "properties": {
    "iso:country":"CH",
    "sg:address":"3001 Bern. Postfach 5032",
    "sg:city":"Bern",
    "sg:orig_category":"Elektrizit\u00e4tsversorgung",
    "sg:phone":"+41 31 320 65 25",
    "sg:postcode":"3001",
    "sg:province":"Bern",
    "wof:name":"Schweizerische Vereinigung F\u00fcr Atomenergie",
    "wof:placetype":"venue"
},
  "geometry": {"coordinates":[7.4482097626,46.9480209351],"type":"Point"}
}