{
  "type": "Feature",
  "properties": {
    "iso:country":"CH",
    "sg:address":"Romanshornerstrasse 14 8580 Amriswil. Postfach 1818",
    "sg:city":"Amriswil",
    "sg:orig_category":"Druck ohne Zeitungsdruck Offsetdruck",
    "sg:phone":"+41 71 411 80 90",
    "sg:postcode":"8580",
    "sg:province":"Thurgau",
    "wof:name":"Andr\u00e9 Diefenbacher Ad-druck",
    "wof:placetype":"venue"
},
  "geometry": {"coordinates":[9.3027162552,47.5465698242],"type":"Point"}
}