{
  "type": "Feature",
  "properties": {
    "iso:country":"CH",
    "sg:address":"Murbacherstrasse 3",
    "sg:city":"Luzern",
    "sg:orig_category":"Advokaturb\u00fcros Notariate",
    "sg:phone":"+41 41 210 62 82",
    "sg:postcode":"6003",
    "sg:province":"Luzern",
    "wof:name":"Dr.rudolf Zihlmann Advokatur-& Notariatsb\u00fcro",
    "wof:placetype":"venue"
},
  "geometry": {"coordinates":[8.309134,47.048443],"type":"Point"}
}