{
  "type": "Feature",
  "properties": {
    "iso:country":"CH",
    "sg:address":"Davoserweg C",
    "sg:city":"Landquart",
    "sg:orig_category":"Stukkateurgewerbe, Gipserei U Verputzerei Verlegen von Fussboden",
    "sg:phone":"+41 81 322 41 08",
    "sg:postcode":"7302",
    "sg:province":"Graubunden",
    "wof:name":"A. Moffa Gipserei & Unterlagsb\u00f6den",
    "wof:placetype":"venue"
},
  "geometry": {"coordinates":[9.5600891113,46.9648895264],"type":"Point"}
}