{
  "type": "Feature",
  "properties": {
    "iso:country":"CH",
    "sg:address":"Von May-strasse 37",
    "sg:city":"Thun",
    "sg:orig_category":"Wohnheime",
    "sg:postcode":"3604",
    "sg:province":"Bern",
    "wof:name":"Neo-geropolis Gmbh",
    "wof:placetype":"venue"
},
  "geometry": {"coordinates":[7.6155729294,46.7324066162],"type":"Point"}
}