{
  "type": "Feature",
  "properties": {
    "iso:country":"CH",
    "sg:address":"Hinterbergstrasse 40",
    "sg:city":"Z\u00fcrich",
    "sg:orig_category":"R\u00f6ntgeninstitute",
    "sg:phone":"+41 12520050",
    "sg:postcode":"8044",
    "sg:province":"Z\u00fcrich",
    "wof:name":"Mri Ag R\u00f6ntgeninstitut",
    "wof:placetype":"venue"
},
  "geometry": {"coordinates":[8.5568447113,47.3811416626],"type":"Point"}
}