{
  "type": "Feature",
  "properties": {
    "iso:country":"CH",
    "sg:address":"Route Du Verdel 8",
    "sg:city":"Bulle",
    "sg:classifiers":[
        {
            "category":"Building & Trades",
            "subcategory":"Construction",
            "type":"Services"
        }
    ],
    "sg:phone":"+41 26 919 67 27",
    "sg:postcode":"1630",
    "sg:province":"Fribourg",
    "sg:tags":[
        "installation",
        "heating"
    ],
    "wof:name":"Riedo Climat S.a. Bulle",
    "wof:placetype":"venue"
},
  "geometry": {"coordinates":[7.0662398338,46.6239776611],"type":"Point"}
}