{
  "type": "Feature",
  "properties": {
    "iso:country":"CH",
    "sg:address":"Oedenhofstrasse 2",
    "sg:city":"Kronb\u00fchl",
    "sg:orig_category":"Grosshandel mit Parf\u00fcmerieartikeln U K\u00f6rperpflegemitteln Grosshandel mit pharmazeutischen Erzeugniss",
    "sg:phone":"+41 22 347 59 37",
    "sg:postcode":"9302",
    "wof:name":"Pharmunion Sa",
    "wof:placetype":"venue"
},
  "geometry": {"coordinates":[6.1536221504,46.195148468],"type":"Point"}
}