{
  "type": "Feature",
  "properties": {
    "iso:country":"CH",
    "sg:address":"Riedernstrasse 30",
    "sg:city":"Grenchen",
    "sg:orig_category":"Handel mit Automobilen",
    "sg:postcode":"2540",
    "sg:province":"Solothurn",
    "wof:name":"Januzaj Muje",
    "wof:placetype":"venue"
},
  "geometry": {"coordinates":[7.4042229652,47.1895446777],"type":"Point"}
}