{
  "type": "Feature",
  "properties": {
    "iso:country":"CH",
    "sg:address":"Buchserstrasse 7",
    "sg:city":"Aarau",
    "sg:orig_category":"Dvd Duplication",
    "sg:phone":"+41 62 836 30 90",
    "sg:postcode":"5000",
    "sg:province":"Aargau",
    "wof:name":"Princo Switzerland Ag",
    "wof:placetype":"venue"
},
  "geometry": {"coordinates":[8.0583763123,47.3916130066],"type":"Point"}
}