{
  "type": "Feature",
  "properties": {
    "iso:country":"CH",
    "sg:address":"Saint-martin Chemin 12",
    "sg:city":"Confignon",
    "sg:orig_category":"Allgemeiner Hoch U Tiefbau",
    "sg:phone":"+41 22 757 38 53",
    "sg:postcode":"1232",
    "sg:province":"Gen\u00e8ve",
    "wof:name":"As B\u00e2timents Sarl",
    "wof:placetype":"venue"
},
  "geometry": {"coordinates":[6.084995,46.173786],"type":"Point"}
}