{
  "type": "Feature",
  "properties": {
    "iso:country":"CH",
    "sg:address":"Soodstrasse 14",
    "sg:city":"Adliswil",
    "sg:classifiers":[
        {
            "category":"Restaurant",
            "type":"Food & Drink"
        }
    ],
    "sg:phone":"+41 17103997",
    "sg:postcode":"8134",
    "sg:province":"Z\u00fcrich",
    "wof:name":"Restaurant Sch\u00f6nau",
    "wof:placetype":"venue"
},
  "geometry": {"coordinates":[8.5255908966,47.3158340454],"type":"Point"}
}