{
  "type": "Feature",
  "properties": {
    "iso:country":"CH",
    "sg:address":"Straja 7430 Thusis. Postfach",
    "sg:city":"Thusis",
    "sg:orig_category":"Mechanik",
    "sg:postcode":"7430",
    "sg:province":"Graubunden",
    "wof:name":"Stoffel Gian Schmiede U. Schlosserei",
    "wof:placetype":"venue"
},
  "geometry": {"coordinates":[9.43612957,46.6940116882],"type":"Point"}
}