{
  "type": "Feature",
  "properties": {
    "iso:country":"CH",
    "sg:address":"1163",
    "sg:city":"Etoy",
    "sg:orig_category":"Herstellung von k\u00e4lte U lufttechnischen Erzeugnissen f\u00fcr gewerbliche Zwecke Mechanische Werkst\u00e4tten",
    "sg:phone":"+41 21 808 75 26",
    "sg:postcode":"1163",
    "sg:province":"Vaud",
    "wof:name":"Grin Fr\u00e8res & Cie",
    "wof:placetype":"venue"
},
  "geometry": {"coordinates":[6.4217200279,46.4850006104],"type":"Point"}
}