{
  "type": "Feature",
  "properties": {
    "iso:country":"CH",
    "sg:address":"Grossm\u00fcnsterplatz 6",
    "sg:city":"Z\u00fcrich",
    "sg:orig_category":"Rechtsberatung",
    "sg:phone":"+41 19325757",
    "sg:postcode":"8001",
    "sg:province":"Z\u00fcrich",
    "wof:name":"Hygolet (schweiz) Ag",
    "wof:placetype":"venue"
},
  "geometry": {"coordinates":[8.7857513428,47.3250007629],"type":"Point"}
}