{
  "type": "Feature",
  "properties": {
    "iso:country":"CH",
    "sg:address":"Felsenstieg 6",
    "sg:city":"Schaffhausen",
    "sg:orig_category":"Sonstige mit Sport verbundene T\u00e4tigkeiten",
    "sg:postcode":"8200",
    "sg:province":"Schaffhausen",
    "wof:name":"Genossenschaft Pferdesporttage Schaffhausen",
    "wof:placetype":"venue"
},
  "geometry": {"coordinates":[8.6282815933,47.708442688],"type":"Point"}
}