{
  "type": "Feature",
  "properties": {
    "iso:country":"CH",
    "sg:address":"6780",
    "sg:city":"Airolo",
    "sg:classifiers":[
        {
            "category":"Government",
            "subcategory":"Post Office",
            "type":"Public Place"
        }
    ],
    "sg:phone":"+41 91 869 22 10",
    "sg:postcode":"6780",
    "sg:province":"Ticino",
    "sg:tags":[
        "caf\u00e9s",
        "tea-rooms"
    ],
    "wof:name":"Caff\u00e8-tea-room Simmen",
    "wof:placetype":"venue"
},
  "geometry": {"coordinates":[8.6094970703,46.5278015137],"type":"Point"}
}