{
  "type": "Feature",
  "properties": {
    "iso:country":"CH",
    "sg:address":"Rebbergstrasse 2",
    "sg:city":"W\u00e4denswil",
    "sg:orig_category":"Mechanik Schlossereien",
    "sg:phone":"+41 17806885",
    "sg:postcode":"8820",
    "sg:province":"Z\u00fcrich",
    "wof:name":"Storz S\u00f6hne K.",
    "wof:placetype":"venue"
},
  "geometry": {"coordinates":[8.6736469269,47.2268104553],"type":"Point"}
}