{
  "type": "Feature",
  "properties": {
    "iso:country":"CH",
    "sg:address":"Winkelgass 17",
    "sg:city":"Schaan",
    "sg:orig_category":"Detailhandel mit Teppichen Verlegen von Fussboden",
    "sg:phone":"+423 232 98 10",
    "sg:postcode":"9494",
    "wof:name":"Peter Beck Ag Teppiche & Bodenbel\u00e4ge",
    "wof:placetype":"venue"
},
  "geometry": {"coordinates":[9.5104446411,47.1626625061],"type":"Point"}
}