{
  "type": "Feature",
  "properties": {
    "iso:country":"CH",
    "sg:address":"Pierre Rue Saint- 18",
    "sg:city":"Fribourg",
    "sg:orig_category":"Grosshandel mit Erzen U Metallen",
    "sg:postcode":"1700",
    "sg:province":"Fribourg",
    "wof:name":"Sadeca Societe Financiere S.a.",
    "wof:placetype":"venue"
},
  "geometry": {"coordinates":[7.1558661461,46.8040313721],"type":"Point"}
}