{
  "type": "Feature",
  "properties": {
    "iso:country":"CH",
    "sg:address":"Eichenweg 5",
    "sg:city":"Gr\u00e4nichen",
    "sg:orig_category":"Architektur U Ingenieurb\u00fcros",
    "sg:phone":"+41 62 842 62 74",
    "sg:postcode":"5722",
    "sg:province":"Aargau",
    "wof:name":"Hermann Schellhorn Technisches B\u00fcro",
    "wof:placetype":"venue"
},
  "geometry": {"coordinates":[8.096953,47.369762],"type":"Point"}
}