{
  "type": "Feature",
  "properties": {
    "iso:country":"CH",
    "sg:address":"Wilerstr. 98",
    "sg:city":"Flawil",
    "sg:classifiers":[
        {
            "category":"Shopping",
            "type":"Retail Goods"
        }
    ],
    "sg:phone":"+41 71 394 13 00",
    "sg:postcode":"9230",
    "sg:province":"St. Gallen",
    "sg:tags":[
        "metallurgy",
        "finished",
        "-",
        "metalworking",
        "metallic"
    ],
    "wof:name":"B\u00dcchler Werkzeugbau Ag",
    "wof:placetype":"venue"
},
  "geometry": {"coordinates":[9.1812791824,47.4156761169],"type":"Point"}
}