{
  "type": "Feature",
  "properties": {
    "iso:country":"CH",
    "sg:address":"Kerenzerstrasse 20 8753 Mollis. Postfach 119",
    "sg:city":"Mollis",
    "sg:orig_category":"Institutionen f\u00fcr Behinderte Sonderschulen",
    "sg:phone":"+41 55 612 12 38",
    "sg:postcode":"8753",
    "sg:province":"Glarus",
    "wof:name":"Sonderschulheim Haltli",
    "wof:placetype":"venue"
},
  "geometry": {"coordinates":[9.0763530731,47.0985984802],"type":"Point"}
}