{
  "type": "Feature",
  "properties": {
    "iso:country":"CH",
    "sg:address":"1081 Montpreveyres. Postfach",
    "sg:city":"Montpreveyres",
    "sg:orig_category":"Fachdetailhandel in Verkaufsr\u00e4umen",
    "sg:phone":"+41 21 903 04 05",
    "sg:postcode":"1081",
    "sg:province":"Vaud",
    "wof:name":"Color Media Sa",
    "wof:placetype":"venue"
},
  "geometry": {"coordinates":[6.7287697792,46.5819511414],"type":"Point"}
}