{
  "type": "Feature",
  "properties": {
    "iso:country":"CH",
    "sg:address":"Dorfplatz.",
    "sg:city":"Breil/brigels",
    "sg:orig_category":"Detailhandel mit Brot, Back U S\u00fcsswaren",
    "sg:postcode":"7165",
    "sg:province":"Graubunden",
    "wof:name":"Gabriel S.",
    "wof:placetype":"venue"
},
  "geometry": {"coordinates":[9.066441,46.781975],"type":"Point"}
}