{
  "type": "Feature",
  "properties": {
    "iso:country":"CH",
    "sg:address":"Lindenstrasse 41",
    "sg:city":"Grenchen",
    "sg:orig_category":"Vereine Lions",
    "sg:phone":"+41 32 654 99 21",
    "sg:postcode":"2540",
    "sg:province":"Solothurn",
    "wof:name":"Lions Club Grenchen Parktheater",
    "wof:placetype":"venue"
},
  "geometry": {"coordinates":[7.3904008865,47.1914176941],"type":"Point"}
}