{
  "type": "Feature",
  "properties": {
    "iso:country":"CH",
    "sg:address":"Elisabethenstrasse 28",
    "sg:city":"Basel",
    "sg:orig_category":"Interessenvertretungen",
    "sg:postcode":"4051",
    "sg:province":"Basel-Stadt",
    "wof:name":"Alfred Oehler-stiftung",
    "wof:placetype":"venue"
},
  "geometry": {"coordinates":[8.1788911819,47.4681015015],"type":"Point"}
}