{
  "type": "Feature",
  "properties": {
    "iso:country":"CH",
    "sg:address":"Freiburgstrasse 111 3174 Th\u00f6rishaus. Postfach",
    "sg:city":"Th\u00f6rishaus",
    "sg:orig_category":"Grosshandel mit Nahrungsmitteln, Getr\u00e4nken U Tabakwaren ohne ausgepr\u00e4gten Schwerpunkt",
    "sg:postcode":"3174",
    "sg:province":"Bern",
    "wof:name":"Primo Lebensmittel, Schertenleib",
    "wof:placetype":"venue"
},
  "geometry": {"coordinates":[7.3501648903,46.8949279785],"type":"Point"}
}