{
  "type": "Feature",
  "properties": {
    "iso:country":"CH",
    "sg:address":"7524",
    "sg:city":"Zuoz",
    "sg:orig_category":"Schlossereien Schmieden",
    "sg:phone":"+41 81 854 12 41",
    "sg:postcode":"7524",
    "sg:province":"Graubunden",
    "wof:name":"Fritz Nyfeler Schmiede & Schlosserei",
    "wof:placetype":"venue"
},
  "geometry": {"coordinates":[9.9598398209,46.6027832031],"type":"Point"}
}