{
  "type": "Feature",
  "properties": {
    "iso:country":"CH",
    "sg:address":"Glockentalstrasse 6 3612 Steffisburg. Postfach 289",
    "sg:city":"Steffisburg",
    "sg:classifiers":[
        {
            "category":"Insurance",
            "subcategory":"Insurance Agent",
            "type":"Services"
        }
    ],
    "sg:phone":"+41 41 930 18 48",
    "sg:postcode":"3612",
    "sg:province":"Bern",
    "sg:tags":[
        "versicherungsagenturen",
        "-broker"
    ],
    "wof:name":"Winterthur Versicherungen Agentur",
    "wof:placetype":"venue"
},
  "geometry": {"coordinates":[8.1516819,47.219707489],"type":"Point"}
}