{
  "type": "Feature",
  "properties": {
    "iso:country":"CH",
    "sg:address":"Rue Du March\u00e9 11",
    "sg:city":"Carouge",
    "sg:classifiers":[
        {
            "category":"Banks & Credit Unions",
            "subcategory":"Bank",
            "type":"Services"
        }
    ],
    "sg:phone":"+41 32 930 78 11",
    "sg:postcode":"1227",
    "sg:province":"Gen\u00e8ve",
    "wof:name":"Swiss Bank Corp.",
    "wof:placetype":"venue"
},
  "geometry": {"coordinates":[6.747104,47.056316],"type":"Point"}
}