{
  "type": "Feature",
  "properties": {
    "iso:country":"CH",
    "sg:address":"Winzerstrasse 11",
    "sg:city":"Z\u00fcrich",
    "sg:orig_category":"Erbringung von Dienstleistungen f\u00fcr Unternehmen",
    "sg:phone":"+41 13422624",
    "sg:postcode":"8006",
    "sg:province":"Z\u00fcrich",
    "wof:name":"Swiss High End Audio Society",
    "wof:placetype":"venue"
},
  "geometry": {"coordinates":[8.4934005737,47.400302887],"type":"Point"}
}