{
  "type": "Feature",
  "properties": {
    "iso:country":"CH",
    "sg:address":"Rue Alexandre Cailler 16",
    "sg:city":"Broc",
    "sg:orig_category":"Polizei",
    "sg:phone":"+41 32 465 32 32",
    "sg:postcode":"1636",
    "sg:province":"Fribourg",
    "wof:name":"Police Cantonale",
    "wof:placetype":"venue"
},
  "geometry": {"coordinates":[7.0772519112,47.4202384949],"type":"Point"}
}