{
  "type": "Feature",
  "properties": {
    "addr:full":"Rue De Vevey 210 Bulle Fribourg 1630",
    "addr:housenumber":"210",
    "addr:postcode":"1630",
    "addr:street":"Rue De Vevey",
    "iso:country":"CH",
    "sg:address":"Rue De Vevey 210",
    "sg:city":"Bulle",
    "sg:classifiers":[
        {
            "category":"Home & Garden",
            "subcategory":"Furniture",
            "type":"Retail Goods"
        }
    ],
    "sg:phone":"+41 26 913 98 77",
    "sg:postcode":"1630",
    "sg:province":"Fribourg",
    "sg:tags":[
        "bathroom"
    ],
    "wof:name":"Cm Habitat Concept S\u00e0rl",
    "wof:placetype":"venue"
},
  "geometry": {"coordinates":[7.04293,46.613552],"type":"Point"}
}