{
  "type": "Feature",
  "properties": {
    "iso:country":"CH",
    "sg:address":"Grossfeldstrasse 79",
    "sg:city":"Sargans",
    "sg:orig_category":"Arztpraxen",
    "sg:phone":"+41 71 911 26 11",
    "sg:postcode":"7320",
    "sg:province":"St. Gallen",
    "wof:name":"Dr.med.juhani Sidler Spezialarzt Fmh",
    "wof:placetype":"venue"
},
  "geometry": {"coordinates":[9.042544,47.463207],"type":"Point"}
}