{
  "type": "Feature",
  "properties": {
    "addr:full":"Allschwilerstrasse 34 Basel Basel-Stadt 4055",
    "addr:housenumber":"34",
    "addr:postcode":"4055",
    "addr:street":"Allschwilerstrasse",
    "iso:country":"CH",
    "sg:address":"Allschwilerstrasse 34",
    "sg:city":"Basel",
    "sg:orig_category":"Bauspenglerei Sanit\u00e4rinstallation",
    "sg:phone":"+41 61 731 11 75",
    "sg:postcode":"4055",
    "sg:province":"Basel-Stadt",
    "wof:name":"Emil Handschin Spenglerei San.installationen",
    "wof:placetype":"venue"
},
  "geometry": {"coordinates":[7.508298,47.479706],"type":"Point"}
}