{
  "type": "Feature",
  "properties": {
    "iso:country":"CH",
    "sg:address":"H\u00fcnzikerstrtasse 15",
    "sg:city":"Schneisingen",
    "sg:orig_category":"Verwertung von Milch",
    "sg:postcode":"5425",
    "sg:province":"Aargau",
    "wof:name":"Milchgenossenschaft Schneit Und Umgebung",
    "wof:placetype":"venue"
},
  "geometry": {"coordinates":[8.889547348,47.520942688],"type":"Point"}
}