{
  "type": "Feature",
  "properties": {
    "iso:country":"CH",
    "sg:address":"Hauptstrasse 18 6260 Reiden. Postfach",
    "sg:city":"Reiden",
    "sg:orig_category":"Grosshandel mit Getr\u00e4nken",
    "sg:phone":"+41 62 758 11 64",
    "sg:postcode":"6260",
    "sg:province":"Luzern",
    "wof:name":"Meyer Eduard & Co Ag",
    "wof:placetype":"venue"
},
  "geometry": {"coordinates":[7.9714188576,47.2430801392],"type":"Point"}
}