{
  "type": "Feature",
  "properties": {
    "addr:full":"Dornacherplatz 7 4500 Solothurn. Postfach Solothurn Solothurn 4501",
    "addr:housenumber":"7",
    "addr:postcode":"4500 solothurn. postfach;4501",
    "addr:street":"Dornacherplatz",
    "iso:country":"CH",
    "sg:address":"Dornacherplatz 7 4500 Solothurn. Postfach",
    "sg:city":"Solothurn",
    "sg:orig_category":"Allgemeiner Hoch U Tiefbau Allgemeiner Hochbau",
    "sg:phone":"+41 62 391 03 45",
    "sg:postcode":"4501",
    "sg:province":"Solothurn",
    "wof:name":"Meier + J\u00e4ggi Ag Solothurn, Zweigniederlassung Balsthal Hoch, Tiefbau Usw",
    "wof:placetype":"venue"
},
  "geometry": {"coordinates":[7.53755,47.204494],"type":"Point"}
}