{
  "type": "Feature",
  "properties": {
    "iso:country":"CH",
    "sg:address":"Zollhausstrasse 57a",
    "sg:city":"Biel/bienne",
    "sg:orig_category":"Sonstige pers\u00f6nliche Dienstleistungen",
    "sg:postcode":"2504",
    "sg:province":"Bern",
    "wof:name":"Schweizerische Stiftung F\u00fcr Parapsychologie Und Wissenschaftliche Ufo-forschung",
    "wof:placetype":"venue"
},
  "geometry": {"coordinates":[7.2672629356,47.1551818848],"type":"Point"}
}