{
  "type": "Feature",
  "properties": {
    "iso:country":"CH",
    "sg:address":"Alpsteinstrasse 56",
    "sg:city":"Herisau",
    "sg:orig_category":"Unclassifiable Establishments",
    "sg:phone":"+41 41 930 00 22",
    "sg:postcode":"9100",
    "sg:province":"Appenzell Ausserrhoden",
    "wof:name":"G\u00e4rtner Pflugshaupt Ag, Zweigniederlassung Rickenbach",
    "wof:placetype":"venue"
},
  "geometry": {"coordinates":[8.1508779526,47.225025177],"type":"Point"}
}