{
  "type": "Feature",
  "properties": {
    "iso:country":"CH",
    "sg:address":"Cordey Rue 8",
    "sg:city":"Yverdon-les-bains",
    "sg:orig_category":"Vermietung U Verpachtung von eigenen Immobilien",
    "sg:postcode":"1400",
    "sg:province":"Vaud",
    "wof:name":"Bobst Patrick R\u00e9gie Immobili\u00e8re Sa",
    "wof:placetype":"venue"
},
  "geometry": {"coordinates":[6.6478180885,46.7769241333],"type":"Point"}
}