{
  "type": "Feature",
  "properties": {
    "iso:country":"CH",
    "sg:address":"Cr\u00eat Sur Le 27a",
    "sg:city":"Corg\u00e9mont",
    "sg:orig_category":"Herstellung von Schrauben, Nieten, Ketten U Federn",
    "sg:phone":"+41 32 489 25 44",
    "sg:postcode":"2606",
    "sg:province":"Bern",
    "wof:name":"D\u00e9colletage - Zehnder Jean-pierre",
    "wof:placetype":"venue"
},
  "geometry": {"coordinates":[7.1346259117,47.1930465698],"type":"Point"}
}