{
  "type": "Feature",
  "properties": {
    "iso:country":"CH",
    "sg:address":"Aeschenvorstadt 71",
    "sg:city":"Basel",
    "sg:orig_category":"Finanzierungsinstitutionen",
    "sg:postcode":"4051",
    "sg:province":"Basel-Stadt",
    "wof:name":"Saxum Ag",
    "wof:placetype":"venue"
},
  "geometry": {"coordinates":[7.5944361687,47.5518875122],"type":"Point"}
}