{
  "type": "Feature",
  "properties": {
    "iso:country":"CH",
    "sg:address":"Riedterstrasse 17 8162 Steinmaur. Postfach 15",
    "sg:city":"Steinmaur",
    "sg:orig_category":"Herstellung von Metallkonstruktionen Stahl U Leichtmetallbau",
    "sg:phone":"+41 18530622",
    "sg:postcode":"8162",
    "sg:province":"Z\u00fcrich",
    "wof:name":"Brander Ag, Metallbau & Normbauteile",
    "wof:placetype":"venue"
},
  "geometry": {"coordinates":[8.4582538605,47.4992828369],"type":"Point"}
}