{
  "type": "Feature",
  "properties": {
    "iso:country":"CH",
    "sg:address":"Mariabergstrasse 15 9400 Rorschach. Postfach 201",
    "sg:city":"Rorschach",
    "sg:orig_category":"Polizei",
    "sg:phone":"+41 71 841 34 34",
    "sg:postcode":"9401",
    "sg:province":"St. Gallen",
    "wof:name":"Kantonale Polizei",
    "wof:placetype":"venue"
},
  "geometry": {"coordinates":[9.4934492111,47.4770050049],"type":"Point"}
}