{
  "type": "Feature",
  "properties": {
    "iso:country":"CH",
    "sg:address":"Eichli 18 6370 Stans. Postfach 1122",
    "sg:city":"Stans",
    "sg:orig_category":"Grosshandel mit elektrischen Haushaltsger\u00e4ten, Radio U Fernsehger\u00e4ten",
    "sg:phone":"+41 41 610 96 01",
    "sg:postcode":"6371",
    "sg:province":"Nidwalden",
    "wof:name":"White House Handels Ag",
    "wof:placetype":"venue"
},
  "geometry": {"coordinates":[8.3644971848,46.9655570984],"type":"Point"}
}