{
  "type": "Feature",
  "properties": {
    "iso:country":"CH",
    "sg:address":"Rothenring 22",
    "sg:city":"Reussb\u00fchl",
    "sg:orig_category":"Industrie, Chemie U Biologie",
    "sg:phone":"+41 41 260 80 55",
    "sg:postcode":"6015",
    "sg:province":"Luzern",
    "wof:name":"Fera Ag",
    "wof:placetype":"venue"
},
  "geometry": {"coordinates":[8.277942,47.067127],"type":"Point"}
}