{
  "type": "Feature",
  "properties": {
    "iso:country":"CH",
    "sg:address":"Route Andr\u00e9 Piller 33b",
    "sg:city":"Givisiez",
    "sg:orig_category":"Grosshandel mit sonstigen Konsumg\u00fctern",
    "sg:phone":"+41 26 466 66 79",
    "sg:postcode":"1762",
    "sg:province":"Fribourg",
    "wof:name":"Jardis Sa Import-export",
    "wof:placetype":"venue"
},
  "geometry": {"coordinates":[7.117128849,46.811794281],"type":"Point"}
}