{
  "type": "Feature",
  "properties": {
    "addr:full":"Rigistrasse 6 Zug Zug 6300",
    "addr:housenumber":"6",
    "addr:postcode":"6300",
    "addr:street":"Rigistrasse;Zug",
    "iso:country":"CH",
    "sg:address":"Rigistrasse 6",
    "sg:city":"Zug",
    "sg:orig_category":"Datenverarbeitungsdienste Softwareentwicklung U beratung",
    "sg:phone":"+41 41 720 33 11",
    "sg:postcode":"6300",
    "sg:province":"Zug",
    "wof:name":"Cis Ag",
    "wof:placetype":"venue"
},
  "geometry": {"coordinates":[8.514707,47.169991],"type":"Point"}
}