{
  "type": "Feature",
  "properties": {
    "iso:country":"CH",
    "sg:address":"Adlerweg 2",
    "sg:city":"Chur",
    "sg:orig_category":"Herstellung von k\u00e4lte U lufttechnischen Erzeugnissen f\u00fcr gewerbliche Zwecke",
    "sg:phone":"+41 81 284 01 01",
    "sg:postcode":"7000",
    "sg:province":"Graubunden",
    "wof:name":"Paganini Plan Ag Integral",
    "wof:placetype":"venue"
},
  "geometry": {"coordinates":[9.5210027695,46.8611717224],"type":"Point"}
}