{
  "type": "Feature",
  "properties": {
    "iso:country":"CH",
    "sg:address":"Bremgartenstr. 20",
    "sg:city":"Niederrohrdorf",
    "sg:classifiers":[
        {
            "category":"Banks & Credit Unions",
            "subcategory":"Bank",
            "type":"Services"
        }
    ],
    "sg:phone":"+41 56 496 15 28",
    "sg:postcode":"5443",
    "sg:province":"Aargau",
    "wof:name":"Raiffeisenbank Rohrdorf",
    "wof:placetype":"venue"
},
  "geometry": {"coordinates":[8.30503,47.421726],"type":"Point"}
}