{
  "type": "Feature",
  "properties": {
    "iso:country":"CH",
    "sg:address":"9475",
    "sg:city":"Sevelen",
    "sg:orig_category":"Landw. Genossenschaften Viehzucht",
    "sg:postcode":"9475",
    "sg:province":"St. Gallen",
    "wof:name":"Viehzuchtgenossenschaft",
    "wof:placetype":"venue"
},
  "geometry": {"coordinates":[9.4878854752,47.1220817566],"type":"Point"}
}