{
  "type": "Feature",
  "properties": {
    "iso:country":"CH",
    "sg:address":"Hauptstrasse 105",
    "sg:city":"Nidau",
    "sg:orig_category":"Detailhandel mit Waren verschiedener Art, Hauptrichtung Nahrungsmittel",
    "sg:phone":"+41 32 331 51 54",
    "sg:postcode":"2560",
    "sg:province":"Bern",
    "wof:name":"Coop Bern/biel",
    "wof:placetype":"venue"
},
  "geometry": {"coordinates":[7.2422151566,47.123046875],"type":"Point"}
}