{
  "type": "Feature",
  "properties": {
    "iso:country":"CH",
    "sg:address":"7504",
    "sg:city":"Pontresina",
    "sg:orig_category":"Bauschreinerei Innenausbau",
    "sg:phone":"+41 81 826 57 48",
    "sg:postcode":"7504",
    "sg:province":"Graubunden",
    "wof:name":"Peter Alder Schreinerei Alder",
    "wof:placetype":"venue"
},
  "geometry": {"coordinates":[9.76417,46.428761],"type":"Point"}
}