{
  "type": "Feature",
  "properties": {
    "iso:country":"CH",
    "sg:address":"6549 Laura. Postfach",
    "sg:city":"Laura",
    "sg:orig_category":"Allgemeiner Hoch U Tiefbau",
    "sg:postcode":"6549",
    "sg:province":"Graubunden",
    "wof:name":"Ceresa, Rinaldo & Figlio.",
    "wof:placetype":"venue"
},
  "geometry": {"coordinates":[9.101622,46.212147],"type":"Point"}
}