{
  "type": "Feature",
  "properties": {
    "iso:country":"CH",
    "sg:address":"Sch\u00fcpbach",
    "sg:city":"Signau",
    "sg:orig_category":"Verwertung von Milch",
    "sg:postcode":"3534",
    "sg:province":"Bern",
    "wof:name":"K\u00e4sereigenossenschaft Sch\u00fcpbach",
    "wof:placetype":"venue"
},
  "geometry": {"coordinates":[7.7339711189,46.9089546204],"type":"Point"}
}