{
  "type": "Feature",
  "properties": {
    "iso:country":"CH",
    "sg:address":"Frutigenstrasse 29",
    "sg:city":"Thun",
    "sg:orig_category":"Sonstige Institutionen des Sozialwesens ohne Beherbergung",
    "sg:phone":"+41 33 222 56 88",
    "sg:postcode":"3600",
    "sg:province":"Bern",
    "wof:name":"Eheberatungsstelle",
    "wof:placetype":"venue"
},
  "geometry": {"coordinates":[7.6270170212,46.7515563965],"type":"Point"}
}