{
  "type": "Feature",
  "properties": {
    "iso:country":"CH",
    "sg:address":"Kirchstrasse 73b 8810 Horgen. Postfach 773",
    "sg:city":"Horgen",
    "sg:orig_category":"Markt U Meinungsforschung Unternehmensberatung",
    "sg:phone":"+41 71 223 78 82",
    "sg:postcode":"8812",
    "sg:province":"Z\u00fcrich",
    "wof:name":"Esb Marketing Consult Ag",
    "wof:placetype":"venue"
},
  "geometry": {"coordinates":[9.3711948395,47.4235572815],"type":"Point"}
}