{
  "type": "Feature",
  "properties": {
    "iso:country":"CH",
    "sg:address":"Hallwylstrasse 40",
    "sg:city":"Z\u00fcrich",
    "sg:orig_category":"Wein Detailhandel",
    "sg:phone":"+41 21 799 16 87",
    "sg:postcode":"8004",
    "sg:province":"Z\u00fcrich",
    "wof:name":"Ernest Parisod Domaine De La Grille",
    "wof:placetype":"venue"
},
  "geometry": {"coordinates":[1.8562330008,50.328994751],"type":"Point"}
}