{
  "type": "Feature",
  "properties": {
    "iso:country":"CH",
    "sg:address":"Rellikonstrasse 2",
    "sg:city":"Maur",
    "sg:orig_category":"Nationale Postdienste",
    "sg:phone":"+41 17811105",
    "sg:postcode":"8124",
    "sg:province":"Z\u00fcrich",
    "wof:name":"Die Schweizerische Post",
    "wof:placetype":"venue"
},
  "geometry": {"coordinates":[8.6444587708,47.2461280823],"type":"Point"}
}