{
  "type": "Feature",
  "properties": {
    "iso:country":"CH",
    "sg:address":"L\u00e4chenstrasse 26",
    "sg:city":"Flurlingen",
    "sg:orig_category":"Non-Classified Establishments",
    "sg:postcode":"8247",
    "sg:province":"Z\u00fcrich",
    "wof:name":"Stc - Schaefer Trading & Consulting Ag",
    "wof:placetype":"venue"
},
  "geometry": {"coordinates":[8.6284723282,47.6804962158],"type":"Point"}
}