{
  "type": "Feature",
  "properties": {
    "iso:country":"CH",
    "sg:address":"Kirchlindachstrasse 25",
    "sg:city":"Zollikofen",
    "sg:orig_category":"Sportvereine Ballsport Volleyball Vereine Damen",
    "sg:phone":"+41 31 911 40 53",
    "sg:postcode":"3052",
    "sg:province":"Bern",
    "wof:name":"Volleyball-club Fr Zollikofen",
    "wof:placetype":"venue"
},
  "geometry": {"coordinates":[7.4577770233,47.0007362366],"type":"Point"}
}