{
  "type": "Feature",
  "properties": {
    "iso:country":"CH",
    "sg:address":"Hubel",
    "sg:city":"B\u00f6singen",
    "sg:orig_category":"Detailhandel mit Fahrr\u00e4dern Handel mit Motorr\u00e4dern, Teilen U Zubeh\u00f6r Instandhaltung U Reparatur von ",
    "sg:phone":"+41 31 747 95 55",
    "sg:postcode":"3178",
    "sg:province":"Fribourg",
    "wof:name":"Yoli's Veloshop Yolande Spicher",
    "wof:placetype":"venue"
},
  "geometry": {"coordinates":[7.2232918739,46.8926391602],"type":"Point"}
}