{
  "type": "Feature",
  "properties": {
    "iso:country":"CH",
    "sg:address":"Zelgstrasse 85",
    "sg:city":"Uetendorf",
    "sg:classifiers":[
        {
            "category":"Building & Trades",
            "subcategory":"Locksmith",
            "type":"Services"
        }
    ],
    "sg:phone":"+41 33 223 37 37",
    "sg:postcode":"3661",
    "sg:province":"Bern",
    "sg:tags":[
        "planting",
        "green",
        "roof"
    ],
    "wof:name":"Hortussa Ag",
    "wof:placetype":"venue"
},
  "geometry": {"coordinates":[7.5890097618,46.7797203064],"type":"Point"}
}