{
  "type": "Feature",
  "properties": {
    "iso:country":"CH",
    "sg:address":"Place Du Tunnel 4",
    "sg:city":"Lausanne",
    "sg:orig_category":"Herstellung von elektrischen Lampen U Leuchten Sonstiger Grosshandel",
    "sg:phone":"+41 32 341 91 01",
    "sg:postcode":"1005",
    "sg:province":"Vaud",
    "wof:name":"Ir Technology Ltd, Londres, Succursale De Bienne",
    "wof:placetype":"venue"
},
  "geometry": {"coordinates":[7.2761301994,47.1589012146],"type":"Point"}
}