{
  "type": "Feature",
  "properties": {
    "iso:country":"CH",
    "sg:address":"Hauptstrasse 6 9214 Kradolf. Postfach 51",
    "sg:city":"Kradolf",
    "sg:orig_category":"Unclassifiable Establishments",
    "sg:phone":"+41 71 642 38 39",
    "sg:postcode":"9214",
    "sg:province":"Thurgau",
    "wof:name":"Sesa Stritmatter Elektro Und Sicherheitsanlagen",
    "wof:placetype":"venue"
},
  "geometry": {"coordinates":[9.200097084,47.5249443054],"type":"Point"}
}