{
  "type": "Feature",
  "properties": {
    "iso:country":"CH",
    "sg:address":"Boulevard De P\u00e9rolles 59",
    "sg:city":"Fribourg",
    "sg:orig_category":"Sonstige mit der Informatik verbundene T\u00e4tigkeiten",
    "sg:postcode":"1700",
    "sg:province":"Fribourg",
    "wof:name":"Gigamips Edv Service, Ingenieurb\u00fcro P. Yuan",
    "wof:placetype":"venue"
},
  "geometry": {"coordinates":[7.1552028656,46.796257019],"type":"Point"}
}