{
  "type": "Feature",
  "properties": {
    "iso:country":"CH",
    "sg:address":"Bahnhofstrasse 15 6430 Schwyz. Postfach 656",
    "sg:city":"Schwyz",
    "sg:orig_category":"Vermessungs\u00e4mter",
    "sg:phone":"+41 41 819 11 24",
    "sg:postcode":"6431",
    "sg:province":"Schwyz",
    "wof:name":"Kantonales Meliorationsamt",
    "wof:placetype":"venue"
},
  "geometry": {"coordinates":[8.6492977142,47.0214271545],"type":"Point"}
}