{
  "type": "Feature",
  "properties": {
    "iso:country":"CH",
    "sg:address":"Grand-rue 21",
    "sg:city":"Rolle",
    "sg:orig_category":"W\u00e4scherei U chemische Reinigung",
    "sg:phone":"+41 22 348 55 22",
    "sg:postcode":"1180",
    "sg:province":"Vaud",
    "wof:name":"Baechler Teinturiers Sa",
    "wof:placetype":"venue"
},
  "geometry": {"coordinates":[6.3390321732,46.4582748413],"type":"Point"}
}