{
  "type": "Feature",
  "properties": {
    "addr:full":"Schlegwegstrasse 7 Linden Bern 3673",
    "addr:housenumber":"7",
    "addr:postcode":"3673",
    "addr:street":"Schlegwegstrasse",
    "iso:country":"CH",
    "sg:address":"Schlegwegstrasse 7",
    "sg:city":"Linden",
    "sg:orig_category":"Allgemeiner Hochbau Strassenbau",
    "sg:phone":"+41 31 882 00 10",
    "sg:postcode":"3673",
    "sg:province":"Bern",
    "wof:name":"Maurer Bau Ag",
    "wof:placetype":"venue"
},
  "geometry": {"coordinates":[7.362327,46.913925],"type":"Point"}
}