{
  "type": "Feature",
  "properties": {
    "iso:country":"CH",
    "sg:address":"Vordere Gasse 49",
    "sg:city":"Felsberg",
    "sg:orig_category":"District Heating Dh Stations, Compact",
    "sg:phone":"+41 81 254 36 50",
    "sg:postcode":"7012",
    "sg:province":"Graubunden",
    "wof:name":"Proenergie W\u00e4rmetechnik Ag",
    "wof:placetype":"venue"
},
  "geometry": {"coordinates":[9.4813241959,46.8468208313],"type":"Point"}
}