{
  "type": "Feature",
  "properties": {
    "iso:country":"CH",
    "sg:address":"Scheuchzerstrasse 64 8006 Z\u00fcrich. Postfach 3076",
    "sg:city":"Z\u00fcrich",
    "sg:orig_category":"Binnenschiffahrt",
    "sg:phone":"+41 13630555",
    "sg:postcode":"8006",
    "sg:province":"Z\u00fcrich",
    "wof:name":"Cargonautic Ag",
    "wof:placetype":"venue"
},
  "geometry": {"coordinates":[8.5456438065,47.3862266541],"type":"Point"}
}