{
  "type": "Feature",
  "properties": {
    "iso:country":"CH",
    "sg:address":"Pavillonweg 12",
    "sg:city":"Bern",
    "sg:orig_category":"Architekturb\u00fcros",
    "sg:phone":"+41 31 302 15 00",
    "sg:postcode":"3012",
    "sg:province":"Bern",
    "wof:name":"Ehrenbold & Schudel Architekturb\u00fcro",
    "wof:placetype":"venue"
},
  "geometry": {"coordinates":[7.433378,46.949501],"type":"Point"}
}