{
  "type": "Feature",
  "properties": {
    "iso:country":"CH",
    "sg:address":"Melchnaustrasse 12",
    "sg:city":"Langenthal",
    "sg:orig_category":"Organisationen des Gesundheitswesen",
    "sg:phone":"+41 62 922 87 79",
    "sg:postcode":"4900",
    "sg:province":"Bern",
    "wof:name":"Beratungsstelle F\u00fcr Kranke",
    "wof:placetype":"venue"
},
  "geometry": {"coordinates":[7.7918410301,47.2109870911],"type":"Point"}
}