{
  "type": "Feature",
  "properties": {
    "iso:country":"CH",
    "sg:address":"Oberdorf 12",
    "sg:city":"Wimmis",
    "sg:orig_category":"Maler U Glasergewerbe",
    "sg:postcode":"3752",
    "sg:province":"Bern",
    "wof:name":"Beat Reist-l\u00fcthi",
    "wof:placetype":"venue"
},
  "geometry": {"coordinates":[7.6366391182,46.6733360291],"type":"Point"}
}