{
  "type": "Feature",
  "properties": {
    "iso:country":"CH",
    "sg:address":"Alte Steinhauserstrasse 2",
    "sg:city":"Cham",
    "sg:orig_category":"Erschliessung von Grundst\u00fccken",
    "sg:postcode":"6330",
    "sg:province":"Zug",
    "wof:name":"Baugenossenschaft Rigiblick",
    "wof:placetype":"venue"
},
  "geometry": {"coordinates":[8.4744949341,47.1861076355],"type":"Point"}
}