{
  "type": "Feature",
  "properties": {
    "addr:full":"Strassburgstrasse 10 Z\u00fcrich Z\u00fcrich 8004",
    "addr:housenumber":"10",
    "addr:postcode":"8004",
    "addr:street":"Strassburgstrasse",
    "iso:country":"CH",
    "sg:address":"Strassburgstrasse 10",
    "sg:city":"Z\u00fcrich",
    "sg:orig_category":"Detailhandel mit B\u00fcchern Detailhandel mit Spielwaren",
    "sg:postcode":"8004",
    "sg:province":"Z\u00fcrich",
    "wof:name":"Marty & Anderegg Ag Spiel- & L\u00e4selade",
    "wof:placetype":"venue"
},
  "geometry": {"coordinates":[8.852955,47.19326],"type":"Point"}
}