{
  "type": "Feature",
  "properties": {
    "iso:country":"CH",
    "sg:address":"Vers-l'eglise",
    "sg:city":"Ormont-dessus",
    "sg:orig_category":"G\u00fcterbef\u00f6rderung im Strassenverkehr",
    "sg:phone":"+41 24 492 33 16",
    "sg:postcode":"1865",
    "sg:province":"Vaud",
    "wof:name":"Genillard Et Fils - Transports Et Excursions.",
    "wof:placetype":"venue"
},
  "geometry": {"coordinates":[7.1587100029,46.3500404358],"type":"Point"}
}