{
  "type": "Feature",
  "properties": {
    "iso:country":"CH",
    "sg:address":"Rue Du Littoral 34a",
    "sg:city":"Chez-le-bart",
    "sg:orig_category":"Grosshandel mit B\u00fcromaschinen Softwareentwicklung U beratung",
    "sg:phone":"+41 79 351 21 53",
    "sg:postcode":"2025",
    "sg:province":"Neuch\u00e2tel",
    "wof:name":"Hg Diffusion Informatique Huguenin C.-p.",
    "wof:placetype":"venue"
},
  "geometry": {"coordinates":[6.7868599892,46.901966095],"type":"Point"}
}