{
  "type": "Feature",
  "properties": {
    "addr:full":"Veia Son Mitgel Savognin Graubunden 7460",
    "addr:housenumber":"7460",
    "addr:street":"Veia",
    "iso:country":"CH",
    "sg:address":"Veia Son Mitgel",
    "sg:city":"Savognin",
    "sg:orig_category":"Bauschreinerei",
    "sg:phone":"+41 81 684 22 28",
    "sg:postcode":"7460",
    "sg:province":"Graubunden",
    "wof:name":"Peder Arpagaus Schreinerei",
    "wof:placetype":"venue"
},
  "geometry": {"coordinates":[9.59905,46.596245],"type":"Point"}
}