{
  "type": "Feature",
  "properties": {
    "iso:country":"CH",
    "sg:address":"Linseb\u00fchlstrasse 89",
    "sg:city":"St.gallen",
    "sg:orig_category":"Wirtschaftspr\u00fcfung, Steuerberatung U Treuhand",
    "sg:phone":"+41 71 311 30 21",
    "sg:postcode":"9000",
    "sg:province":"St. Gallen",
    "wof:name":"Wbt.ch Treuhand Und Revisionsgesellschaft",
    "wof:placetype":"venue"
},
  "geometry": {"coordinates":[9.3844060898,47.4255218506],"type":"Point"}
}