{
  "type": "Feature",
  "properties": {
    "iso:country":"CH",
    "sg:address":"Z\u00fcrcherstrasse 323",
    "sg:city":"Frauenfeld",
    "sg:orig_category":"Verwaltung der Strafvollzuganstalten Wohnheime",
    "sg:phone":"+41 52 728 26 94",
    "sg:postcode":"8500",
    "sg:province":"Thurgau",
    "wof:name":"Kantonalgef\u00e4ngnis",
    "wof:placetype":"venue"
},
  "geometry": {"coordinates":[8.9123830795,47.5659561157],"type":"Point"}
}