{
  "type": "Feature",
  "properties": {
    "iso:country":"CH",
    "sg:address":"Rinaustrasse 4303 Kaiseraugst. Postfach 81",
    "sg:city":"Kaiseraugst",
    "sg:orig_category":"Herstellung von Futtermitteln f\u00fcr Nutztiere Mahl U Sch\u00e4lm\u00fchlen",
    "sg:phone":"+41 61 816 16 16",
    "sg:postcode":"4303",
    "sg:province":"Aargau",
    "wof:name":"Provimi Kliba Sa Alimentation Animale",
    "wof:placetype":"venue"
},
  "geometry": {"coordinates":[7.728496,47.539928],"type":"Point"}
}