{
  "type": "Feature",
  "properties": {
    "iso:country":"CH",
    "sg:address":"Obere Z\u00e4une 12",
    "sg:city":"Z\u00fcrich",
    "sg:orig_category":"Detailhandel mit M\u00f6beln U Haushaltsgegenst\u00e4nden Innenarchitekturb\u00fcros",
    "sg:phone":"+41 12621777",
    "sg:postcode":"8001",
    "sg:province":"Z\u00fcrich",
    "wof:name":"Keeris Raumgestaltung",
    "wof:placetype":"venue"
},
  "geometry": {"coordinates":[8.5457448959,47.3712158203],"type":"Point"}
}