{
  "type": "Feature",
  "properties": {
    "iso:country":"CH",
    "sg:address":"4710 Balsthal. Postfach 11",
    "sg:city":"Balsthal",
    "sg:orig_category":"Interessenvertretungen",
    "sg:postcode":"4710",
    "sg:province":"Solothurn",
    "wof:name":"Von Burg-stiftung Josef",
    "wof:placetype":"venue"
},
  "geometry": {"coordinates":[7.6957850456,47.3158607483],"type":"Point"}
}