{
  "type": "Feature",
  "properties": {
    "iso:country":"CH",
    "sg:address":"Netzelen",
    "sg:city":"Roggliswil",
    "sg:orig_category":"Verarbeitung von Milch Verwertung von Milch",
    "sg:postcode":"6265",
    "sg:province":"Luzern",
    "wof:name":"K\u00e4sereigenossenschaft Roggliswil-oberdorf",
    "wof:placetype":"venue"
},
  "geometry": {"coordinates":[7.8828349113,47.2098731995],"type":"Point"}
}