{
  "type": "Feature",
  "properties": {
    "iso:country":"CH",
    "sg:address":"Laupenstrasse 2 3011 Bern. Postfach",
    "sg:city":"Bern",
    "sg:orig_category":"Detailhandel mit Getr\u00e4nken",
    "sg:phone":"+41 71 288 52 92",
    "sg:postcode":"3001",
    "sg:province":"Bern",
    "wof:name":"Caves M\u00f6venpick Sa",
    "wof:placetype":"venue"
},
  "geometry": {"coordinates":[9.4105577469,47.440071106],"type":"Point"}
}