{
  "type": "Feature",
  "properties": {
    "iso:country":"CH",
    "sg:address":"Bahnhofstrasse 28",
    "sg:city":"Biel/bienne",
    "sg:orig_category":"Detailhandel mit Blumen U Pflanzen",
    "sg:phone":"+41 32 322 20 21",
    "sg:postcode":"2502",
    "sg:province":"Bern",
    "wof:name":"Lerch Ag Blumengesch\u00e4ft",
    "wof:placetype":"venue"
},
  "geometry": {"coordinates":[7.245014,47.135212],"type":"Point"}
}