{
  "type": "Feature",
  "properties": {
    "iso:country":"CH",
    "sg:address":"Chemin Des Granges 28a",
    "sg:city":"Attalens",
    "sg:orig_category":"Bauschreinerei Herstellung von Fenstern U T\u00fcren aus Holz",
    "sg:phone":"+41 21 947 32 88",
    "sg:postcode":"1616",
    "sg:province":"Fribourg",
    "wof:name":"Philippe Saudan S\u00e0rl Menuiserie",
    "wof:placetype":"venue"
},
  "geometry": {"coordinates":[6.86253,46.526131],"type":"Point"}
}