{
  "type": "Feature",
  "properties": {
    "iso:country":"CH",
    "sg:address":"Zeughausstrasse 12",
    "sg:city":"Schwyz",
    "sg:orig_category":"Elektroinstallation Technische B\u00fcros Elektro",
    "sg:phone":"+41 19326016",
    "sg:postcode":"6430",
    "sg:province":"Schwyz",
    "wof:name":"Walder Markus Elektroplanung",
    "wof:placetype":"venue"
},
  "geometry": {"coordinates":[8.7826871872,47.3120307922],"type":"Point"}
}