{
  "type": "Feature",
  "properties": {
    "iso:country":"CH",
    "sg:address":"Roswiesenstrasse 7",
    "sg:city":"N\u00fcrensdorf",
    "sg:orig_category":"Grosshandel mit Getr\u00e4nken",
    "sg:phone":"+41 18367545",
    "sg:postcode":"8309",
    "sg:province":"Z\u00fcrich",
    "wof:name":"Oenothek Capricorn, Lingg Thomas",
    "wof:placetype":"venue"
},
  "geometry": {"coordinates":[8.6360397339,47.4538116455],"type":"Point"}
}