{
  "type": "Feature",
  "properties": {
    "iso:country":"CH",
    "sg:address":"Gottardo Via San 102 6828 Balerna. Postfach",
    "sg:city":"Balerna",
    "sg:orig_category":"RESTAURANTS: TEA-ROOMS",
    "sg:postcode":"6828",
    "sg:province":"Ticino",
    "wof:name":"Sineal Sagl Bar, Ristoranti, Alberghi Ecc",
    "wof:placetype":"venue"
},
  "geometry": {"coordinates":[9.0075235367,45.8501586914],"type":"Point"}
}