{
  "type": "Feature",
  "properties": {
    "iso:country":"CH",
    "sg:address":"D\u00fcnnernstrasse 378",
    "sg:city":"Matzendorf",
    "sg:orig_category":"Herstellung von sonstigen Holzwaren",
    "sg:postcode":"4713",
    "sg:province":"Solothurn",
    "wof:name":"Paul Thomann-fuchs",
    "wof:placetype":"venue"
},
  "geometry": {"coordinates":[8.036860466,46.7545585632],"type":"Point"}
}