{
  "type": "Feature",
  "properties": {
    "iso:country":"CH",
    "sg:address":"2012",
    "sg:city":"Auvernier",
    "sg:orig_category":"Sportvereine Sch\u00fctzen",
    "sg:postcode":"2012",
    "sg:province":"Neuch\u00e2tel",
    "wof:name":"St\u00e9 De Tir Militaire",
    "wof:placetype":"venue"
},
  "geometry": {"coordinates":[6.5584697723,46.9128417969],"type":"Point"}
}