{
  "type": "Feature",
  "properties": {
    "iso:country":"CH",
    "sg:address":"Neugasse 44",
    "sg:city":"Baar",
    "sg:orig_category":"Allgemeiner Hochbau Zimmerei, Dachdeckerei, Bauspenglerei U Abdichtung",
    "sg:phone":"+41 41 761 19 55",
    "sg:postcode":"6340",
    "sg:province":"Zug",
    "wof:name":"Bortis D\u00e4cher & Fassaden",
    "wof:placetype":"venue"
},
  "geometry": {"coordinates":[8.520603,47.199638],"type":"Point"}
}