{
  "type": "Feature",
  "properties": {
    "iso:country":"CH",
    "sg:address":"6685",
    "sg:city":"Bosco/gurin",
    "sg:classifiers":[
        {
            "category":"Travel",
            "subcategory":"Hotels & Motels",
            "type":"Entertainment"
        }
    ],
    "sg:phone":"+41 81 826 52 47",
    "sg:postcode":"6685",
    "sg:province":"Ticino",
    "sg:tags":[
        "hotels",
        "mit",
        "restaurant"
    ],
    "wof:name":"Giovanoli Dumeng",
    "wof:placetype":"venue"
},
  "geometry": {"coordinates":[9.7641716003,46.4287643433],"type":"Point"}
}