{
  "type": "Feature",
  "properties": {
    "iso:country":"CH",
    "sg:address":"Industriestrasse 1a 8157 Dielsdorf. Postfach",
    "sg:city":"Dielsdorf",
    "sg:orig_category":"Softwareentwicklung U beratung",
    "sg:phone":"+41 21 943 73 17",
    "sg:postcode":"8157",
    "sg:province":"Z\u00fcrich",
    "wof:name":"Easyinfo, Grand Laurent",
    "wof:placetype":"venue"
},
  "geometry": {"coordinates":[6.8822221756,46.4711837769],"type":"Point"}
}