{
  "type": "Feature",
  "properties": {
    "addr:full":"Shopping Cent.emmen Emmen Luzern 6020",
    "addr:postcode":"6020",
    "iso:country":"CH",
    "sg:address":"Shopping Cent.emmen",
    "sg:city":"Emmen",
    "sg:classifiers":[
        {
            "category":"Banks & Credit Unions",
            "subcategory":"Bank",
            "type":"Services"
        }
    ],
    "sg:phone":"+41 4141559970",
    "sg:postcode":"6020",
    "sg:province":"Luzern",
    "wof:name":"Luzerner Kantonalbank",
    "wof:placetype":"venue"
},
  "geometry": {"coordinates":[8.275493,47.078087],"type":"Point"}
}