{
  "type": "Feature",
  "properties": {
    "iso:country":"CH",
    "sg:address":"Wiesentalstrasse 30",
    "sg:city":"Aadorf",
    "sg:orig_category":"Rechtsberatung Verwaltung von Immobilien",
    "sg:phone":"+41 52 233 32 88",
    "sg:postcode":"8355",
    "sg:province":"Thurgau",
    "wof:name":"Mapag Maurer & Partner Ag Treuhand & Unternehmensberat.",
    "wof:placetype":"venue"
},
  "geometry": {"coordinates":[8.9005041122,47.4923095703],"type":"Point"}
}