{
  "type": "Feature",
  "properties": {
    "iso:country":"CH",
    "sg:address":"Z\u00fcrcherstrasse 160",
    "sg:city":"Neuenhof",
    "sg:orig_category":"Physiotherapie",
    "sg:phone":"+41 79 349 10 01",
    "sg:postcode":"5432",
    "sg:province":"Aargau",
    "wof:name":"Physio-team Neuenhof",
    "wof:placetype":"venue"
},
  "geometry": {"coordinates":[8.3305263519,47.4468002319],"type":"Point"}
}