{
  "type": "Feature",
  "properties": {
    "iso:country":"CH",
    "sg:address":"Z\u00fcrcher Strasse 14",
    "sg:city":"St.gallen",
    "sg:orig_category":"Sonstiges Versicherungsgewerbe Vermittlung von Immobilien",
    "sg:phone":"+41 71 279 33 44",
    "sg:postcode":"9000",
    "sg:province":"St. Gallen",
    "wof:name":"Poliba Ag",
    "wof:placetype":"venue"
},
  "geometry": {"coordinates":[9.3561229706,47.4205474854],"type":"Point"}
}