{
  "type": "Feature",
  "properties": {
    "iso:country":"CH",
    "sg:address":"Battenhusstrasse 16 9053 Teufen Ar. Postfach",
    "sg:city":"Lustm\u00fchle",
    "sg:orig_category":"Herstellung von Metallerzeugnissen ohne Maschinenbau Maschinenbau",
    "sg:phone":"+41 19500520",
    "sg:postcode":"9062",
    "sg:province":"Appenzell Ausserrhoden",
    "wof:name":"Nuovo Ag",
    "wof:placetype":"venue"
},
  "geometry": {"coordinates":[8.7675390244,47.3718681335],"type":"Point"}
}