{
  "type": "Feature",
  "properties": {
    "iso:country":"CH",
    "sg:address":"B\u00fcrenstr. 1",
    "sg:city":"Leuzigen",
    "sg:orig_category":"Forstwirtschaft ohne Dienstleistungen in der Forstwirtschaft",
    "sg:phone":"+41 26 913 17 11",
    "sg:postcode":"3297",
    "sg:province":"Bern",
    "wof:name":"Travaux Forestiers, Romanens Jean-luc",
    "wof:placetype":"venue"
},
  "geometry": {"coordinates":[7.0576848984,46.5961875916],"type":"Point"}
}