{
  "type": "Feature",
  "properties": {
    "iso:country":"CH",
    "sg:address":"Chemin Du Levant 9",
    "sg:city":"Mont-sur-rolle",
    "sg:orig_category":"Fleischverarbeitung",
    "sg:phone":"+41 21 826 05 09",
    "sg:postcode":"1185",
    "sg:province":"Vaud",
    "wof:name":"Rapelli Sa Industria Salumi",
    "wof:placetype":"venue"
},
  "geometry": {"coordinates":[6.350233078,46.4645423889],"type":"Point"}
}