{
  "type": "Feature",
  "properties": {
    "addr:full":"Stadlerstrasse 11 8400 Winterthur. Postfach Winterthur Z\u00fcrich 8400",
    "addr:housenumber":"11",
    "addr:postcode":"8400;8400",
    "addr:street":"Stadlerstrasse;Postfach",
    "iso:country":"CH",
    "sg:address":"Stadlerstrasse 11 8400 Winterthur. Postfach",
    "sg:city":"Winterthur",
    "sg:orig_category":"Allgemeiner Hoch U Tiefbau",
    "sg:postcode":"8400",
    "sg:province":"Z\u00fcrich",
    "wof:name":"Swisspro Ag Fachbetrieb Der Baubranche. Haustechnik, Bauinstallationen, Projektierung Usw",
    "wof:placetype":"venue"
},
  "geometry": {"coordinates":[8.758147,47.510742],"type":"Point"}
}