{
  "type": "Feature",
  "properties": {
    "iso:country":"CH",
    "sg:address":"Himmelrich 2",
    "sg:city":"Thundorf",
    "sg:orig_category":"Allgemeiner Hoch U Tiefbau Allgemeiner Hochbau",
    "sg:phone":"+41 52 376 33 88",
    "sg:postcode":"8512",
    "sg:province":"Thurgau",
    "wof:name":"Britschgi Bau Ag",
    "wof:placetype":"venue"
},
  "geometry": {"coordinates":[8.964727,47.547436],"type":"Point"}
}