{
  "type": "Feature",
  "properties": {
    "iso:country":"CH",
    "sg:address":"Stengelmattstrasse 14",
    "sg:city":"Dagmersellen",
    "sg:orig_category":"Sonstige Personenbef\u00f6rderung im Landverkehr",
    "sg:postcode":"6252",
    "sg:province":"Luzern",
    "wof:name":"Andric & Co., Reisen",
    "wof:placetype":"venue"
},
  "geometry": {"coordinates":[7.9849338531,47.2129554749],"type":"Point"}
}