{
  "type": "Feature",
  "properties": {
    "iso:country":"CH",
    "sg:address":"Ygrubenstrasse 38 8750 Glarus. Postfach",
    "sg:city":"Glarus",
    "sg:orig_category":"Kauf U Verkauf von Immobilien auf eigene Rechnung",
    "sg:postcode":"8750",
    "sg:province":"Glarus",
    "wof:name":"Ultravision Ag Liegenschaften Usw.",
    "wof:placetype":"venue"
},
  "geometry": {"coordinates":[9.0663757324,47.0473136902],"type":"Point"}
}