{
  "type": "Feature",
  "properties": {
    "iso:country":"CH",
    "sg:address":"Bahnhofstrasse 289 4626 Niederbuchsiten. Postfach",
    "sg:city":"Niederbuchsiten",
    "sg:classifiers":[
        {
            "category":"Professional",
            "subcategory":"Employment Agencies",
            "type":"Services"
        }
    ],
    "sg:postcode":"4626",
    "sg:province":"Solothurn",
    "sg:tags":[
        "personal",
        "u",
        "stellenvermittlung"
    ],
    "wof:name":"Visachic Gr\u00e4ub Franziska Schminkauftr\u00e4ge, Fotoshootings. Schminkprodukte; Vertrieb",
    "wof:placetype":"venue"
},
  "geometry": {"coordinates":[7.7708539963,47.2990188599],"type":"Point"}
}