{
  "type": "Feature",
  "properties": {
    "iso:country":"CH",
    "sg:address":"Seestrasse 17 8702 Zollikon. Postfach",
    "sg:city":"Zollikon",
    "sg:orig_category":"Unternehmensberatung",
    "sg:phone":"+41 13902645",
    "sg:postcode":"8702",
    "sg:province":"Z\u00fcrich",
    "wof:name":"Khmc Management Consulting Hartmann Dr. Karl Unternehmensberatung",
    "wof:placetype":"venue"
},
  "geometry": {"coordinates":[8.5674343109,47.3432540894],"type":"Point"}
}