{
  "type": "Feature",
  "properties": {
    "iso:country":"CH",
    "sg:address":"Feldblumenweg 4",
    "sg:city":"Thalwil",
    "sg:orig_category":"Wirtschaftspr\u00fcfung, Steuerberatung U Treuhand",
    "sg:phone":"+41 17227953",
    "sg:postcode":"8800",
    "sg:province":"Z\u00fcrich",
    "wof:name":"F.o.r. - Service, Wyss M. G.",
    "wof:placetype":"venue"
},
  "geometry": {"coordinates":[8.5620193481,47.2920646667],"type":"Point"}
}