{
  "type": "Feature",
  "properties": {
    "iso:country":"CH",
    "sg:address":"6875",
    "sg:city":"Casima",
    "sg:orig_category":"Allgemeiner Hoch U Tiefbau Hoch U Tiefbau",
    "sg:phone":"+41 91 826 22 32",
    "sg:postcode":"6875",
    "sg:province":"Ticino",
    "wof:name":"Loisi Antonio & Co Sa",
    "wof:placetype":"venue"
},
  "geometry": {"coordinates":[8.995528,46.187714],"type":"Point"}
}