{
  "type": "Feature",
  "properties": {
    "iso:country":"CH",
    "sg:address":"6500 Bellinzona. Postfach Caselle Postale 396",
    "sg:city":"Bellinzona",
    "sg:orig_category":"Vereine Musik/Blasmusik",
    "sg:phone":"+41 91 825 10 47",
    "sg:postcode":"6501",
    "sg:province":"Ticino",
    "wof:name":"Civica Filarmonica",
    "wof:placetype":"venue"
},
  "geometry": {"coordinates":[9.0313901901,46.1970787048],"type":"Point"}
}