{
  "type": "Feature",
  "properties": {
    "iso:country":"CH",
    "sg:address":"Untere Plessurstrasse 54",
    "sg:city":"Chur",
    "sg:orig_category":"Bauschreinerei Herstellung von Konstruktionsteilen, Fertigbauteilen U Ausbauelementen aus Holz",
    "sg:phone":"+41 81 284 49 19",
    "sg:postcode":"7000",
    "sg:province":"Graubunden",
    "wof:name":"Paul Kiebler Schreinerei",
    "wof:placetype":"venue"
},
  "geometry": {"coordinates":[9.519099,46.852951],"type":"Point"}
}