{
  "type": "Feature",
  "properties": {
    "addr:full":"Untere Plessurstrasse 54 Chur Graubunden 7000",
    "addr:housenumber":"54",
    "addr:postcode":"7000",
    "addr:street":"Untere Plessurstrasse",
    "iso:country":"CH",
    "sg:address":"Untere Plessurstrasse 54",
    "sg:city":"Chur",
    "sg:orig_category":"Bauschreinerei Herstellung von Konstruktionsteilen, Fertigbauteilen U Ausbauelementen aus Holz",
    "sg:phone":"+41 81 284 49 19",
    "sg:postcode":"7000",
    "sg:province":"Graubunden",
    "wof:name":"Paul Kiebler Schreinerei",
    "wof:placetype":"venue"
},
  "geometry": {"coordinates":[9.519099,46.852951],"type":"Point"}
}