{
  "type": "Feature",
  "properties": {
    "iso:country":"CH",
    "sg:address":"Lichtstrasse 35",
    "sg:city":"Basel",
    "sg:orig_category":"Forschung U Entwicklung im Bereich der Naturwissenschaften",
    "sg:phone":"+41 61 697 11 11",
    "sg:postcode":"4056",
    "sg:province":"Basel-Stadt",
    "wof:name":"Novartis Forschungsstiftung",
    "wof:placetype":"venue"
},
  "geometry": {"coordinates":[7.5794501305,47.5726928711],"type":"Point"}
}