{
  "type": "Feature",
  "properties": {
    "iso:country":"CH",
    "sg:address":"Badenerstrasse 15",
    "sg:city":"Dietikon",
    "sg:orig_category":"Sonstige Institutionen des Sozialwesens ohne Beherbergung",
    "sg:phone":"+41 55 283 44 06",
    "sg:postcode":"8953",
    "sg:province":"Z\u00fcrich",
    "wof:name":"La Leche Liga Schweiz",
    "wof:placetype":"venue"
},
  "geometry": {"coordinates":[9.0529031754,47.2220687866],"type":"Point"}
}