{
  "type": "Feature",
  "properties": {
    "iso:country":"CH",
    "sg:address":"Ambri",
    "sg:city":"Quinto",
    "sg:orig_category":"Unternehmensberatung",
    "sg:phone":"+41 91 873 66 06",
    "sg:postcode":"6777",
    "sg:province":"Ticino",
    "wof:name":"Secunda Fiduciaria Sa",
    "wof:placetype":"venue"
},
  "geometry": {"coordinates":[8.7026748657,46.5090942383],"type":"Point"}
}