{
  "type": "Feature",
  "properties": {
    "iso:country":"CH",
    "sg:address":"3296",
    "sg:city":"Arch",
    "sg:orig_category":"Sportvereine Hornussen",
    "sg:postcode":"3296",
    "sg:province":"Bern",
    "wof:name":"Hornussergesellschaft",
    "wof:placetype":"venue"
},
  "geometry": {"coordinates":[7.4276208878,47.1672363281],"type":"Point"}
}