{
  "type": "Feature",
  "properties": {
    "iso:country":"CH",
    "sg:address":"Terrassenweg 42",
    "sg:city":"M\u00fcnsingen",
    "sg:orig_category":"Unternehmensberatung",
    "sg:phone":"+41 61 753 05 62",
    "sg:postcode":"3110",
    "sg:province":"Bern",
    "wof:name":"Verena Auer Unternehmensberatung",
    "wof:placetype":"venue"
},
  "geometry": {"coordinates":[7.5979590416,47.4640350342],"type":"Point"}
}