{
  "type": "Feature",
  "properties": {
    "iso:country":"CH",
    "sg:address":"Vorderdorfstrasse 25",
    "sg:city":"Landschlacht",
    "sg:orig_category":"Bauspenglerei Sanit\u00e4rinstallation U Spenglerei",
    "sg:phone":"+41 71 695 15 61",
    "sg:postcode":"8597",
    "sg:province":"Thurgau",
    "wof:name":"Rolf & Ilona Schmid Spenglerei",
    "wof:placetype":"venue"
},
  "geometry": {"coordinates":[9.248984,47.62476],"type":"Point"}
}