{
  "type": "Feature",
  "properties": {
    "addr:full":"6527 Lodrino Ticino 6527",
    "addr:housenumber":"6527",
    "addr:postcode":"6527",
    "addr:street":"Lodrino Ticino",
    "iso:country":"CH",
    "sg:address":"6527",
    "sg:city":"Lodrino",
    "sg:orig_category":"Abbruch U Sprenggewerbe, Erdbewegungsarbeiten",
    "sg:postcode":"6527",
    "sg:province":"Ticino",
    "wof:name":"Scapozza-genzoli-ferrari",
    "wof:placetype":"venue"
},
  "geometry": {"coordinates":[8.981131,46.299667],"type":"Point"}
}