{
  "type": "Feature",
  "properties": {
    "iso:country":"CH",
    "sg:address":"Chemin De La Roche 4 1091 Grandvaux. Postfach",
    "sg:city":"Grandvaux",
    "sg:orig_category":"Benzin, Heiz\u00f6l and Mineral\u00f6lprodukte Grosshandel",
    "sg:phone":"+41 21 799 92 92",
    "sg:postcode":"1091",
    "sg:province":"Vaud",
    "wof:name":"Mazol Sa Combustibles-carburants",
    "wof:placetype":"venue"
},
  "geometry": {"coordinates":[6.718345,46.501495],"type":"Point"}
}