{
  "type": "Feature",
  "properties": {
    "iso:country":"CH",
    "sg:address":"Dorfstrasse 13",
    "sg:city":"Oberengstringen",
    "sg:orig_category":"Sonstige pers\u00f6nliche Dienstleistungen",
    "sg:postcode":"8102",
    "sg:province":"Z\u00fcrich",
    "wof:name":"Kms K\u00e4lin Marketing-services",
    "wof:placetype":"venue"
},
  "geometry": {"coordinates":[8.459405899,47.4066810608],"type":"Point"}
}