{
  "type": "Feature",
  "properties": {
    "iso:country":"CH",
    "sg:address":"Rue Du Rh\u00f4ne 26",
    "sg:city":"Sion",
    "sg:orig_category":"Interessenvertretungen",
    "sg:phone":"+41 27 322 12 02",
    "sg:postcode":"1950",
    "sg:province":"Valais",
    "wof:name":"Sos Futures M\u00e8res Sion-sierre-martigny",
    "wof:placetype":"venue"
},
  "geometry": {"coordinates":[7.3612642288,46.2321815491],"type":"Point"}
}