{
  "type": "Feature",
  "properties": {
    "iso:country":"CH",
    "sg:address":"Hard 628",
    "sg:city":"Erlinsbach",
    "sg:orig_category":"Verarbeitung von Milch Verwertung von Milch",
    "sg:postcode":"5018",
    "sg:province":"Solothurn",
    "wof:name":"Milchverwertungs- Genossenschaft Erlinsbach",
    "wof:placetype":"venue"
},
  "geometry": {"coordinates":[8.0138072968,47.4236221313],"type":"Point"}
}