{
  "type": "Feature",
  "properties": {
    "iso:country":"CH",
    "sg:address":"Eigentalstrasse 11 8309 N\u00fcrensdorf. Postfach",
    "sg:city":"N\u00fcrensdorf",
    "sg:orig_category":"Unclassifiable Establishments",
    "sg:phone":"+41 18653324",
    "sg:postcode":"8309",
    "sg:province":"Z\u00fcrich",
    "wof:name":"Tour De Suisse F\u00e9minin Gmbh Radsportveranstaltungen, Bes. Tour De Suisse F\u00e9minin",
    "wof:placetype":"venue"
},
  "geometry": {"coordinates":[8.6455011368,47.4468383789],"type":"Point"}
}