{
  "type": "Feature",
  "properties": {
    "iso:country":"CH",
    "sg:address":"Schwanengasse 47 2503 Biel/bienne. Postfach",
    "sg:city":"Biel/bienne",
    "sg:orig_category":"Non-Classified Establishments",
    "sg:phone":"+41 56 282 23 86",
    "sg:postcode":"2503",
    "sg:province":"Bern",
    "wof:name":"Honic Izet Transporte Erdbau-transporte",
    "wof:placetype":"venue"
},
  "geometry": {"coordinates":[8.287735939,47.4882011414],"type":"Point"}
}