{
  "type": "Feature",
  "properties": {
    "iso:country":"CH",
    "sg:address":"Oristalstrasse 52",
    "sg:city":"Liestal",
    "sg:orig_category":"Kosmetikinstitute",
    "sg:phone":"+41 61 921 96 04",
    "sg:postcode":"4410",
    "sg:province":"Basel-Landschaft",
    "wof:name":"Karin Garthe Institut De Beaut\u00e9 Vogue",
    "wof:placetype":"venue"
},
  "geometry": {"coordinates":[7.7303709984,47.4801216125],"type":"Point"}
}