{
  "type": "Feature",
  "properties": {
    "iso:country":"CH",
    "sg:address":"Cormondes",
    "sg:city":"Gurmels",
    "sg:orig_category":"Pensionskassen",
    "sg:phone":"+41 32 930 52 00",
    "sg:postcode":"3212",
    "sg:province":"Fribourg",
    "wof:name":"Fondation Huguenin M\u00e9dailleurs Sa.",
    "wof:placetype":"venue"
},
  "geometry": {"coordinates":[6.7440018654,47.0575942993],"type":"Point"}
}