{
  "type": "Feature",
  "properties": {
    "iso:country":"CH",
    "sg:address":"Eisengasse 5a",
    "sg:city":"Brunnen",
    "sg:classifiers":[
        {
            "category":"Home & Garden",
            "subcategory":"Home Furnishings",
            "type":"Retail Goods"
        }
    ],
    "sg:phone":"+41 41 820 03 20",
    "sg:postcode":"6440",
    "sg:province":"Schwyz",
    "sg:tags":[
        "candle",
        "beeswax"
    ],
    "wof:name":"Decofloram Ag",
    "wof:placetype":"venue"
},
  "geometry": {"coordinates":[8.605153,46.994522],"type":"Point"}
}