{
  "type": "Feature",
  "properties": {
    "addr:full":"Bahnstrasse 5 8603 Schwerzenbach. Postfach 403 Schwerzenbach Z\u00fcrich 8603",
    "addr:housenumber":"5;403",
    "addr:postcode":"8603 schwerzenbach.;8603",
    "addr:street":"Bahnstrasse;Postfach",
    "iso:country":"CH",
    "sg:address":"Bahnstrasse 5 8603 Schwerzenbach. Postfach 403",
    "sg:city":"Schwerzenbach",
    "sg:orig_category":"Advokaturb\u00fcros",
    "sg:phone":"+41 18260500",
    "sg:postcode":"8603",
    "sg:province":"Z\u00fcrich",
    "wof:name":"Gamma Hug & Christe Advokaturb\u00fcro",
    "wof:placetype":"venue"
},
  "geometry": {"coordinates":[8.660567,47.383888],"type":"Point"}
}