{
  "type": "Feature",
  "properties": {
    "iso:country":"CH",
    "sg:address":"Dorfstrasse 55 8103 Unterengstringen. Postfach 382",
    "sg:city":"Unterengstringen",
    "sg:orig_category":"Herstellung von nachrichtentechnischen Ger\u00e4ten U Einrichtungen",
    "sg:phone":"+41 17511100",
    "sg:postcode":"8103",
    "sg:province":"Z\u00fcrich",
    "wof:name":"Vimer Communication, Stephan Girsberger",
    "wof:placetype":"venue"
},
  "geometry": {"coordinates":[8.4421844482,47.410736084],"type":"Point"}
}