{
  "type": "Feature",
  "properties": {
    "addr:full":"Winkelriedstrasse 35 St.gallen St. Gallen 9000",
    "addr:housenumber":"35",
    "addr:postcode":"9000",
    "addr:street":"Winkelriedstrasse",
    "iso:country":"CH",
    "sg:address":"Winkelriedstrasse 35",
    "sg:city":"St.gallen",
    "sg:orig_category":"Architektur U Ingenieurb\u00fcros",
    "sg:phone":"+41 71 222 77 80",
    "sg:postcode":"9000",
    "sg:province":"St. Gallen",
    "wof:name":"Interplan St. Gallen Ag",
    "wof:placetype":"venue"
},
  "geometry": {"coordinates":[9.370575,47.426613],"type":"Point"}
}