{
  "type": "Feature",
  "properties": {
    "iso:country":"CH",
    "sg:address":"Rue De Lausanne 11",
    "sg:city":"Renens",
    "sg:classifiers":[
        {
            "category":"Shopping",
            "subcategory":"Baby Store",
            "type":"Retail Goods"
        }
    ],
    "sg:phone":"+41 21 635 64 60",
    "sg:postcode":"1020",
    "sg:province":"Vaud",
    "sg:tags":[
        "children's",
        "belt"
    ],
    "wof:name":"Decotex",
    "wof:placetype":"venue"
},
  "geometry": {"coordinates":[6.580703,46.537056],"type":"Point"}
}