{
  "type": "Feature",
  "properties": {
    "iso:country":"CH",
    "sg:address":"Molino Nuovo Piazza 15 6900 Lugano. Postfach",
    "sg:city":"Calprino",
    "sg:orig_category":"Erbringung von sonstigen Dienstleistungen f\u00fcr Unterhaltung, Erholung U Freizeit",
    "sg:phone":"+41 55 246 41 48",
    "sg:postcode":"6900",
    "sg:province":"Ticino",
    "wof:name":"Agility Max Heiniger - Die Hundeschule",
    "wof:placetype":"venue"
},
  "geometry": {"coordinates":[8.9413003922,47.2884101868],"type":"Point"}
}