{
  "type": "Feature",
  "properties": {
    "addr:full":"J\u00e4gerstrasse 9 Basel Basel-Stadt 4058",
    "addr:housenumber":"9",
    "addr:postcode":"4058",
    "addr:street":"Jaegerstrasse",
    "iso:country":"CH",
    "sg:address":"J\u00e4gerstrasse 9",
    "sg:city":"Basel",
    "sg:orig_category":"Bauschreinerei Herstellung von Konstruktionsteilen, Fertigbauteilen U Ausbauelementen aus Holz",
    "sg:phone":"+41 61 693 01 11",
    "sg:postcode":"4058",
    "sg:province":"Basel-Stadt",
    "wof:name":"Bay + Dold Ag",
    "wof:placetype":"venue"
},
  "geometry": {"coordinates":[7.60229,47.56818],"type":"Point"}
}