{
  "type": "Feature",
  "properties": {
    "addr:full":"En Segrin 1 Cortaillod Neuch\u00e2tel 2016",
    "addr:housenumber":"1",
    "addr:postcode":"2016",
    "addr:street":"En Segrin;Neucha\u0302Tel",
    "iso:country":"CH",
    "sg:address":"En Segrin 1",
    "sg:city":"Cortaillod",
    "sg:orig_category":"Detailhandel mit Beleuchtungs U Haushaltsgegenst\u00e4nden Herstellung von elektrischen Lampen U Leuchten",
    "sg:phone":"+41 32 841 47 01",
    "sg:postcode":"2016",
    "sg:province":"Neuch\u00e2tel",
    "wof:name":"Beauclerc Tulux Sa Luminaires",
    "wof:placetype":"venue"
},
  "geometry": {"coordinates":[6.839588,46.940674],"type":"Point"}
}