{
  "type": "Feature",
  "properties": {
    "addr:full":"Aarberg Rue D' 68 2503 Biel/bienne. Postfach Biel/bienne Bern 2503",
    "addr:housenumber":"68",
    "addr:postcode":"2503;postfach;2503",
    "addr:street":"Rue D '",
    "iso:country":"CH",
    "sg:address":"Aarberg Rue D' 68 2503 Biel/bienne. Postfach",
    "sg:city":"Biel/bienne",
    "sg:orig_category":"Architektur U Ingenieurb\u00fcros",
    "sg:postcode":"2503",
    "sg:province":"Bern",
    "wof:name":"Ajs Ing\u00e9nieurs Civils Sa, Succursale De Bienne",
    "wof:placetype":"venue"
},
  "geometry": {"coordinates":[7.243638,47.134586],"type":"Point"}
}