{
  "type": "Feature",
  "properties": {
    "iso:country":"CH",
    "sg:address":"Hauptstrasse 79",
    "sg:city":"Menziken",
    "sg:orig_category":"Instandhaltung U Reparatur von Automobilen",
    "sg:phone":"+41 62 822 51 51",
    "sg:postcode":"5737",
    "sg:province":"Aargau",
    "wof:name":"Wynenfeld-garage Schweizer Gmbh",
    "wof:placetype":"venue"
},
  "geometry": {"coordinates":[8.0805301666,47.3896789551],"type":"Point"}
}