{
  "type": "Feature",
  "properties": {
    "addr:full":"Spl\u00fcgenstrasse 6 Z\u00fcrich Z\u00fcrich 8002",
    "addr:housenumber":"6",
    "addr:postcode":"8002",
    "addr:street":"Spluegenstrasse",
    "iso:country":"CH",
    "sg:address":"Spl\u00fcgenstrasse 6",
    "sg:city":"Z\u00fcrich",
    "sg:orig_category":"Buchverlag Verlagsgewerbe",
    "sg:phone":"+41 26 670 26 23",
    "sg:postcode":"8002",
    "sg:province":"Z\u00fcrich",
    "wof:name":"Verlag Murtenbieter Ag",
    "wof:placetype":"venue"
},
  "geometry": {"coordinates":[7.108453,46.925232],"type":"Point"}
}