{
  "type": "Feature",
  "properties": {
    "iso:country":"CH",
    "sg:address":"Neudorfstrasse 34",
    "sg:city":"W\u00e4denswil",
    "sg:orig_category":"Detailhandel mit elektrischen Haushalts-,Radio U Fernsehger\u00e4ten sowie Musikinstrumenten",
    "sg:postcode":"8820",
    "sg:province":"Z\u00fcrich",
    "wof:name":"Imperiale, Berni",
    "wof:placetype":"venue"
},
  "geometry": {"coordinates":[8.6629781723,47.2340049744],"type":"Point"}
}