{
  "type": "Feature",
  "properties": {
    "iso:country":"CH",
    "sg:address":"Rudenzweg 42",
    "sg:city":"Z\u00fcrich",
    "sg:orig_category":"Rechtsberatung",
    "sg:phone":"+41 14922584",
    "sg:postcode":"8048",
    "sg:province":"Z\u00fcrich",
    "wof:name":"Erich Stehli Rechtsberatung",
    "wof:placetype":"venue"
},
  "geometry": {"coordinates":[8.4973144531,47.3849372864],"type":"Point"}
}