{
  "type": "Feature",
  "properties": {
    "iso:country":"CH",
    "sg:address":"Avenue Des Alpes 8",
    "sg:city":"Montreux",
    "sg:orig_category":"Herstellung von keramischen Haushaltswaren U Ziergegenst\u00e4nden",
    "sg:phone":"+41 62 893 25 60",
    "sg:postcode":"1820",
    "sg:province":"Vaud",
    "wof:name":"Rita Burger Keramik-atelier",
    "wof:placetype":"venue"
},
  "geometry": {"coordinates":[8.180355072,47.4107284546],"type":"Point"}
}