{
  "type": "Feature",
  "properties": {
    "iso:country":"CH",
    "sg:address":"T\u00f6sstalstrasse 51 B-c",
    "sg:city":"Kollbrunn",
    "sg:orig_category":"Non-Classified Establishments",
    "sg:postcode":"8483",
    "sg:province":"Z\u00fcrich",
    "wof:name":"Begleitet Wohnen Im Felspark, Peter Bez",
    "wof:placetype":"venue"
},
  "geometry": {"coordinates":[8.7850017548,47.456363678],"type":"Point"}
}