{
  "type": "Feature",
  "properties": {
    "iso:country":"CH",
    "sg:address":"Schlachthofstrasse 65 4056 Basel. Postfach",
    "sg:city":"Basel",
    "sg:orig_category":"Berufsorganisationen",
    "sg:phone":"+41 71 385 41 58",
    "sg:postcode":"4051",
    "sg:province":"Basel-Stadt",
    "wof:name":"Nsg Nutz Und Schlachtviehgenossenschaft",
    "wof:placetype":"venue"
},
  "geometry": {"coordinates":[9.224164,47.422565],"type":"Point"}
}