{
  "type": "Feature",
  "properties": {
    "iso:country":"CH",
    "sg:address":"Oberwiler Kirchweg 4c",
    "sg:city":"Zug",
    "sg:orig_category":"Non-Classified Establishments",
    "sg:postcode":"6300",
    "sg:province":"Zug",
    "wof:name":"Casinopartners Ag",
    "wof:placetype":"venue"
},
  "geometry": {"coordinates":[8.517496109,47.1599769592],"type":"Point"}
}