{
  "type": "Feature",
  "properties": {
    "iso:country":"CH",
    "sg:address":"Letzistrasse 27",
    "sg:city":"Zug",
    "sg:orig_category":"Unclassifiable Establishments",
    "sg:postcode":"6300",
    "sg:province":"Zug",
    "wof:name":"H\u00fcrlimann Pars Ag",
    "wof:placetype":"venue"
},
  "geometry": {"coordinates":[8.5021238327,47.1791496277],"type":"Point"}
}