{
  "type": "Feature",
  "properties": {
    "iso:country":"CH",
    "sg:address":"Montchoisi Avenue De 4",
    "sg:city":"Lausanne",
    "sg:orig_category":"Werbung",
    "sg:postcode":"1006",
    "sg:province":"Vaud",
    "wof:name":"Freydoun Alamir",
    "wof:placetype":"venue"
},
  "geometry": {"coordinates":[6.6333022118,46.5133552551],"type":"Point"}
}