{
  "type": "Feature",
  "properties": {
    "iso:country":"CH",
    "sg:address":"Rue De L'industrie 17 1950 Sion Case Postale 1120",
    "sg:city":"Sion",
    "sg:orig_category":"Detailhandel mit Fleisch U Fleischwaren Grosshandel mit Wein U Spirituosen",
    "sg:phone":"+41 27 322 36 01",
    "sg:postcode":"1951",
    "sg:province":"Valais",
    "wof:name":"Pam Produits Alimentaires Sa",
    "wof:placetype":"venue"
},
  "geometry": {"coordinates":[7.3620171547,46.2269706726],"type":"Point"}
}