{
  "type": "Feature",
  "properties": {
    "iso:country":"CH",
    "sg:address":"Im Schossacher 12 8600 D\u00fcbendorf. Postfach",
    "sg:city":"D\u00fcbendorf",
    "sg:orig_category":"Grosshandel mit Radio U Fernsehger\u00e4ten Herstellung von sonstigen elektrischen Ausr\u00fcstungen",
    "sg:phone":"+41 18022880",
    "sg:postcode":"8600",
    "sg:province":"Z\u00fcrich",
    "wof:name":"Omni Ray Ag",
    "wof:placetype":"venue"
},
  "geometry": {"coordinates":[8.640627861,47.3938064575],"type":"Point"}
}