{
  "type": "Feature",
  "properties": {
    "addr:full":"Tour Rue De La 8 Bis Lausanne Vaud 1004",
    "addr:housenumber":"8 bis",
    "addr:postcode":"1004",
    "addr:street":"Rue De La",
    "iso:country":"CH",
    "sg:address":"Tour Rue De La 8 Bis",
    "sg:city":"Lausanne",
    "sg:orig_category":"Berufsbildende weiterf\u00fchrende Schulen",
    "sg:phone":"+41 21 320 56 55",
    "sg:postcode":"1004",
    "sg:province":"Vaud",
    "wof:name":"Ecole Roche Sa",
    "wof:placetype":"venue"
},
  "geometry": {"coordinates":[6.626007,46.507927],"type":"Point"}
}