{
  "type": "Feature",
  "properties": {
    "iso:country":"CH",
    "sg:address":"Rudolfingerstrasse 7 Wildensb",
    "sg:city":"Tr\u00fcllikon",
    "sg:orig_category":"Architektur U Ingenieurb\u00fcros",
    "sg:postcode":"8466",
    "sg:province":"Z\u00fcrich",
    "wof:name":"Konstrukt Gmbh",
    "wof:placetype":"venue"
},
  "geometry": {"coordinates":[8.692568,47.63797],"type":"Point"}
}