{
  "type": "Feature",
  "properties": {
    "iso:country":"CH",
    "sg:address":"Rue Du Nord 22",
    "sg:city":"Rolle",
    "sg:orig_category":"Herstellung von k\u00e4lte U lufttechnischen Erzeugnissen f\u00fcr gewerbliche Zwecke",
    "sg:postcode":"1180",
    "sg:province":"Vaud",
    "wof:name":"Fontannaz Jacques Chauffage Et Ventilation Sa, Succursale De Rolle.",
    "wof:placetype":"venue"
},
  "geometry": {"coordinates":[6.3367238045,46.4573516846],"type":"Point"}
}