{
  "type": "Feature",
  "properties": {
    "iso:country":"CH",
    "sg:address":"Curtibergstrasse 123",
    "sg:city":"Wagen",
    "sg:orig_category":"Dachdeckerei",
    "sg:phone":"+41 55 212 37 05",
    "sg:postcode":"8646",
    "sg:province":"St. Gallen",
    "wof:name":"Ueli Bachmann Dachdeckergesch\u00e4ft",
    "wof:placetype":"venue"
},
  "geometry": {"coordinates":[8.886289,47.232353],"type":"Point"}
}