{
  "type": "Feature",
  "properties": {
    "iso:country":"CH",
    "sg:address":"Sch\u00fcrgistrasse 70 8051 Z\u00fcrich. Postfach",
    "sg:city":"Z\u00fcrich",
    "sg:orig_category":"Reiseb\u00fcros U Reiseveranstalter",
    "sg:phone":"+41 79 440 82 63",
    "sg:postcode":"8051",
    "sg:province":"Z\u00fcrich",
    "wof:name":"Freudiger & Co Travel Reiseb\u00fcro",
    "wof:placetype":"venue"
},
  "geometry": {"coordinates":[8.5781908035,47.4083442688],"type":"Point"}
}