{
  "type": "Feature",
  "properties": {
    "iso:country":"CH",
    "sg:address":"Steinb\u00fchlweg 14 4123 Allschwil. Postfach",
    "sg:city":"Allschwil",
    "sg:orig_category":"Institutionen des Sozialwesens ohne Beherbergung",
    "sg:postcode":"4123",
    "sg:province":"Basel-Landschaft",
    "wof:name":"Dr. Karl Sch\u00f6nfeld-brunner-stiftung",
    "wof:placetype":"venue"
},
  "geometry": {"coordinates":[9.3911724091,47.3914680481],"type":"Point"}
}