{
  "type": "Feature",
  "properties": {
    "iso:country":"CH",
    "sg:address":"Haus Enzian 3993 Grengiols. Postfach",
    "sg:city":"Grengiols",
    "sg:orig_category":"Werbung",
    "sg:phone":"+41 27 927 24 49",
    "sg:postcode":"3993",
    "sg:province":"Valais",
    "wof:name":"Bewa Werbung, Walpen Bernhard Werbungen",
    "wof:placetype":"venue"
},
  "geometry": {"coordinates":[8.0929260254,46.3724136353],"type":"Point"}
}