{
  "type": "Feature",
  "properties": {
    "iso:country":"CH",
    "sg:address":"Untere B\u00f6nigstrasse 46",
    "sg:city":"Interlaken",
    "sg:orig_category":"Non-Classified Establishments",
    "sg:postcode":"3800",
    "sg:province":"Bern",
    "wof:name":"Simon Brawand",
    "wof:placetype":"venue"
},
  "geometry": {"coordinates":[7.8742980957,46.6901054382],"type":"Point"}
}