{
  "type": "Feature",
  "properties": {
    "iso:country":"CH",
    "sg:address":"Bahnweg 4 5504 Othmarsingen. Postfach",
    "sg:city":"Othmarsingen",
    "sg:orig_category":"Handelsvermittlung U Grosshandel Handelsvermittlung U Grosshandel mit Automobilteilen U Zubeh\u00f6r",
    "sg:phone":"+41 62 896 04 40",
    "sg:postcode":"5504",
    "sg:province":"Aargau",
    "wof:name":"Iwis Ag",
    "wof:placetype":"venue"
},
  "geometry": {"coordinates":[8.2069587708,47.399143219],"type":"Point"}
}