{
  "type": "Feature",
  "properties": {
    "iso:country":"CH",
    "sg:address":"Steinlen Chemin Aim\u00e9- 9 1004 Lausanne. Postfach",
    "sg:city":"Lausanne",
    "sg:orig_category":"RESTAURANTS: TEA-ROOMS",
    "sg:postcode":"1003",
    "sg:province":"Vaud",
    "wof:name":"Fomar S\u00e0rl Caf\u00e9s-restaurants, Bars, Discoth\u00e8ques Et Cabarets",
    "wof:placetype":"venue"
},
  "geometry": {"coordinates":[6.6116499901,46.5339317322],"type":"Point"}
}