{
  "type": "Feature",
  "properties": {
    "iso:country":"CH",
    "sg:address":"Les Prays",
    "sg:city":"Gruy\u00e8res",
    "sg:orig_category":"Maurerarbeiten",
    "sg:phone":"+41 26 921 26 84",
    "sg:postcode":"1663",
    "sg:province":"Fribourg",
    "wof:name":"Alfio Pancotti Entreprise De Ma\u00e7onnerie",
    "wof:placetype":"venue"
},
  "geometry": {"coordinates":[7.0817718506,46.5929641724],"type":"Point"}
}