{
  "type": "Feature",
  "properties": {
    "iso:country":"CH",
    "sg:address":"St. Jakobs-strasse 2 4132 Muttenz. Postfach 110",
    "sg:city":"Muttenz",
    "sg:orig_category":"Herstellung von sonstigen Maschinen f\u00fcr unspezifische Verwendung",
    "sg:phone":"+41 61 465 91 11",
    "sg:postcode":"4132",
    "sg:province":"Basel-Landschaft",
    "wof:name":"Imtech Ag",
    "wof:placetype":"venue"
},
  "geometry": {"coordinates":[7.6472978592,47.5281486511],"type":"Point"}
}