{
  "type": "Feature",
  "properties": {
    "iso:country":"CH",
    "sg:address":"Route De Divonne 48",
    "sg:city":"Nyon",
    "sg:orig_category":"Technische B\u00fcros Hoch-& Tiefbau",
    "sg:phone":"+41 71 222 99 03",
    "sg:postcode":"1260",
    "sg:province":"Vaud",
    "wof:name":"Ernst Graf Technisches B\u00fcro",
    "wof:placetype":"venue"
},
  "geometry": {"coordinates":[9.3730106354,47.4298210144],"type":"Point"}
}