{
  "type": "Feature",
  "properties": {
    "iso:country":"CH",
    "sg:address":"Lausanne Rue De 33",
    "sg:city":"Fribourg",
    "sg:orig_category":"Elektrizit\u00e4tsversorgung Ingenieurb\u00fcros Kraftwerkbau",
    "sg:phone":"+41 31 984 17 15",
    "sg:postcode":"1700",
    "sg:province":"Fribourg",
    "wof:name":"Standard Energy Ag",
    "wof:placetype":"venue"
},
  "geometry": {"coordinates":[7.364385128,46.9229469299],"type":"Point"}
}