{
  "type": "Feature",
  "properties": {
    "iso:country":"CH",
    "sg:address":"Les Valettes",
    "sg:city":"Bovernier",
    "sg:orig_category":"Stukkateurgewerbe, Gipserei U Verputzerei",
    "sg:phone":"+41 71 920 10 60",
    "sg:postcode":"1932",
    "sg:province":"Valais",
    "wof:name":"G\u00e4mperle Bau-ac Gmbh",
    "wof:placetype":"venue"
},
  "geometry": {"coordinates":[9.0483894348,47.4553337097],"type":"Point"}
}