{
  "type": "Feature",
  "properties": {
    "addr:full":"Wabernstrasse 41 3007 Bern. Postfach Bern Bern 3001",
    "addr:housenumber":"41",
    "addr:postcode":"3007;postfach;3001",
    "addr:street":"Wabernstrasse",
    "iso:country":"CH",
    "sg:address":"Wabernstrasse 41 3007 Bern. Postfach",
    "sg:city":"Bern",
    "sg:orig_category":"Autogaragen",
    "sg:phone":"+41 31 371 71 91",
    "sg:postcode":"3001",
    "sg:province":"Bern",
    "wof:name":"Th. Willy Ag (ford) Eine Unternehmung Der Willy-gruppe",
    "wof:placetype":"venue"
},
  "geometry": {"coordinates":[7.437647,46.93919],"type":"Point"}
}