{
  "type": "Feature",
  "properties": {
    "iso:country":"CH",
    "sg:address":"St. Gallerstrasse 36a",
    "sg:city":"Rorschach",
    "sg:orig_category":"Grosshandel mit sonstigen Halbwaren Herstellung von Maschinen f\u00fcr die Textil, Bekleidungsherstellung",
    "sg:phone":"+41 71 841 38 88",
    "sg:postcode":"9400",
    "sg:province":"St. Gallen",
    "wof:name":"Bobinerie Weishaupt & Co Garnhandel",
    "wof:placetype":"venue"
},
  "geometry": {"coordinates":[9.4839258194,47.4785881042],"type":"Point"}
}