{
  "type": "Feature",
  "properties": {
    "iso:country":"CH",
    "sg:address":"Riedmattstrasse 6",
    "sg:city":"R\u00fcmlang",
    "sg:orig_category":"Instandhaltung U Reparatur von Automobilen",
    "sg:postcode":"8153",
    "sg:province":"Z\u00fcrich",
    "wof:name":"Walser's Auto Make-up",
    "wof:placetype":"venue"
},
  "geometry": {"coordinates":[8.5257396698,47.4614028931],"type":"Point"}
}