{
  "type": "Feature",
  "properties": {
    "iso:country":"CH",
    "sg:address":"Franscini Viale 1 6900 Lugano. Postfach",
    "sg:city":"Lugano",
    "sg:orig_category":"Non-Classified Establishments",
    "sg:postcode":"6900",
    "sg:province":"Ticino",
    "wof:name":"Twister Establishment, Vaduz, Succursale Di Lugano Partecipazioni E Diritti Ecc",
    "wof:placetype":"venue"
},
  "geometry": {"coordinates":[8.9525566101,46.0080795288],"type":"Point"}
}