{
  "type": "Feature",
  "properties": {
    "iso:country":"CH",
    "sg:address":"Z\u00fcrcherstrasse 29",
    "sg:city":"Tagelswangen",
    "sg:orig_category":"Mechanische Werkst\u00e4tten",
    "sg:phone":"+41 52 343 20 38",
    "sg:postcode":"8317",
    "sg:province":"Z\u00fcrich",
    "wof:name":"Hermann Ribic Mech.werkstatt & Garage",
    "wof:placetype":"venue"
},
  "geometry": {"coordinates":[8.6734266281,47.4308776855],"type":"Point"}
}