{
  "type": "Feature",
  "properties": {
    "iso:country":"CH",
    "sg:address":"Via Rinaldo Simen 96",
    "sg:city":"Minusio",
    "sg:orig_category":"RESTAURANTS: TEA-ROOMS",
    "sg:phone":"+41 91 743 20 20",
    "sg:postcode":"6648",
    "sg:province":"Ticino",
    "wof:name":"Ristorante Carlo Magno Cmg Fin S.a G.l.",
    "wof:placetype":"venue"
},
  "geometry": {"coordinates":[8.826622963,46.177444458],"type":"Point"}
}