{
  "type": "Feature",
  "properties": {
    "iso:country":"CH",
    "sg:address":"Berneckerstrasse 16",
    "sg:city":"Heerbrugg",
    "sg:orig_category":"Detailhandel mit Uhren U Schmuck Fachdetailhandel in Verkaufsr\u00e4umen",
    "sg:postcode":"9435",
    "sg:province":"St. Gallen",
    "wof:name":"Frei, Uhren Und Bijouterie Gmbh",
    "wof:placetype":"venue"
},
  "geometry": {"coordinates":[9.6256523132,47.4116783142],"type":"Point"}
}