{
  "type": "Feature",
  "properties": {
    "iso:country":"CH",
    "sg:address":"Via Cassarinetta 12",
    "sg:city":"Lugano",
    "sg:orig_category":"\u00dcbersetzungsb\u00fcros",
    "sg:phone":"+41 91 994 28 94",
    "sg:postcode":"6900",
    "sg:province":"Ticino",
    "wof:name":"Sabina Protti Traduzioni",
    "wof:placetype":"venue"
},
  "geometry": {"coordinates":[8.94186306,45.9931182861],"type":"Point"}
}