{
  "type": "Feature",
  "properties": {
    "iso:country":"CH",
    "sg:address":"J\u00f6chlerweg 4",
    "sg:city":"Baar",
    "sg:orig_category":"Herstellung von k\u00e4lte U lufttechnischen Erzeugnissen f\u00fcr gewerbliche Zwecke Sanit\u00e4r U Heizungsinstal",
    "sg:phone":"+41 41 260 71 71",
    "sg:postcode":"6340",
    "sg:province":"Zug",
    "wof:name":"Hlk Heizung, L\u00fcftung, Klima Ag",
    "wof:placetype":"venue"
},
  "geometry": {"coordinates":[8.2879123688,47.0684547424],"type":"Point"}
}