{
  "type": "Feature",
  "properties": {
    "iso:country":"CH",
    "sg:address":"Bahnhofstrasse 19",
    "sg:city":"Burgdorf",
    "sg:orig_category":"Detailhandel mit Ton U Bildtr\u00e4gern Detailhandel mit Zeitungen U Zeitschriften Kioske",
    "sg:phone":"+41 34 422 82 00",
    "sg:postcode":"3400",
    "sg:province":"Bern",
    "wof:name":"Cd-kiosk & Multimedia Markt",
    "wof:placetype":"venue"
},
  "geometry": {"coordinates":[7.6231451035,47.0595474243],"type":"Point"}
}