{
  "type": "Feature",
  "properties": {
    "iso:country":"CH",
    "sg:address":"Waffenplatzstrasse 66",
    "sg:city":"Z\u00fcrich",
    "sg:orig_category":"Herstellung von Sport U Freizeitbekleidung Textilgewerbe",
    "sg:phone":"+41 12011788",
    "sg:postcode":"8002",
    "sg:province":"Z\u00fcrich",
    "wof:name":"Marx & Co",
    "wof:placetype":"venue"
},
  "geometry": {"coordinates":[8.526889801,47.3572425842],"type":"Point"}
}