{
  "type": "Feature",
  "properties": {
    "addr:full":"Rue Du Coll\u00e8ge 6 Morges Vaud 1110",
    "addr:housenumber":"6",
    "addr:postcode":"1110",
    "addr:street":"Rue Du Colle\u0300Ge",
    "iso:country":"CH",
    "sg:address":"Rue Du Coll\u00e8ge 6",
    "sg:city":"Morges",
    "sg:orig_category":"Bauschreinerei Herstellung von M\u00f6beln verschiedener Art",
    "sg:phone":"+41 21 801 31 64",
    "sg:postcode":"1110",
    "sg:province":"Vaud",
    "wof:name":"Wood Ch. & J.-m. Lepori Menuiserie & \u00e9b\u00e9nisterie",
    "wof:placetype":"venue"
},
  "geometry": {"coordinates":[6.499273,46.510704],"type":"Point"}
}