{
  "type": "Feature",
  "properties": {
    "iso:country":"CH",
    "sg:address":"B\u00e4renfelserstrasse 6 4057 Basel. Postfach",
    "sg:city":"Basel",
    "sg:orig_category":"Unclassifiable Establishments",
    "sg:postcode":"4051",
    "sg:province":"Basel-Stadt",
    "wof:name":"Feuz Rolf Gartenarbeiten",
    "wof:placetype":"venue"
},
  "geometry": {"coordinates":[7.5881609917,47.566444397],"type":"Point"}
}