{
  "type": "Feature",
  "properties": {
    "iso:country":"CH",
    "sg:address":"Tschalunstrasse 35",
    "sg:city":"Oberiberg",
    "sg:orig_category":"Detailhandel mit Getr\u00e4nken",
    "sg:phone":"+41 55 414 12 71",
    "sg:postcode":"8843",
    "sg:province":"Schwyz",
    "wof:name":"Josef Marty Getr\u00e4nkehandlung",
    "wof:placetype":"venue"
},
  "geometry": {"coordinates":[8.7771720886,47.0369987488],"type":"Point"}
}