{
  "type": "Feature",
  "properties": {
    "iso:country":"CH",
    "sg:address":"Sonnhaldenstrasse 8",
    "sg:city":"Balterswil",
    "sg:orig_category":"Kauf U Verkauf von Immobilien auf eigene Rechnung Vermittlung von Immobilien",
    "sg:phone":"+41 71 970 03 63",
    "sg:postcode":"8362",
    "sg:province":"Thurgau",
    "wof:name":"D\u00fcring Immobilien & Treuhand",
    "wof:placetype":"venue"
},
  "geometry": {"coordinates":[8.9327278137,47.451587677],"type":"Point"}
}