{
  "type": "Feature",
  "properties": {
    "iso:country":"CH",
    "sg:address":"Wagnerweg 7",
    "sg:city":"Oftringen",
    "sg:orig_category":"Hoch U Tiefbau Verlegen von Fliesen U Platten",
    "sg:phone":"+41 62 797 66 06",
    "sg:postcode":"4665",
    "sg:province":"Aargau",
    "wof:name":"Rudolf S\u00e4gesser Umbau Plattenbel\u00e4ge Baugesch.",
    "wof:placetype":"venue"
},
  "geometry": {"coordinates":[7.9319958687,47.3042488098],"type":"Point"}
}