{
  "type": "Feature",
  "properties": {
    "iso:country":"CH",
    "sg:address":"Chemin Des L\u00e9ch\u00e8res 4",
    "sg:city":"Meyrin",
    "sg:classifiers":[
        {
            "category":"Train Station",
            "subcategory":"Light Rail",
            "type":"Transportation"
        }
    ],
    "sg:phone":"+41 22 719 85 80",
    "sg:postcode":"1217",
    "sg:province":"Gen\u00e8ve",
    "sg:tags":[
        "source"
    ],
    "wof:name":"Sylvania Lighting Sa",
    "wof:placetype":"venue"
},
  "geometry": {"coordinates":[6.0678710938,46.2222900391],"type":"Point"}
}