{
  "type": "Feature",
  "properties": {
    "iso:country":"CH",
    "sg:address":"Lindenhof",
    "sg:city":"Sarnen",
    "sg:orig_category":"Fachdetailhandel in Verkaufsr\u00e4umen",
    "sg:phone":"+41 41 660 77 22",
    "sg:postcode":"6060",
    "sg:province":"Obwalden",
    "wof:name":"Ott Urs & Co, Brillen Und Contactlinsen.",
    "wof:placetype":"venue"
},
  "geometry": {"coordinates":[8.2474145889,46.8959159851],"type":"Point"}
}