{
  "type": "Feature",
  "properties": {
    "iso:country":"CH",
    "sg:address":"Chemin Des Carri\u00e8res 21",
    "sg:city":"Monthey",
    "sg:orig_category":"Unclassifiable Establishments",
    "sg:postcode":"1870",
    "sg:province":"Valais",
    "wof:name":"Paillasse Marketing Sa",
    "wof:placetype":"venue"
},
  "geometry": {"coordinates":[7.0927248001,47.0635795593],"type":"Point"}
}