{
  "type": "Feature",
  "properties": {
    "iso:country":"CH",
    "sg:address":"4566",
    "sg:city":"Oekingen",
    "sg:orig_category":"Landw. Genossenschaften Viehzucht",
    "sg:postcode":"4566",
    "sg:province":"Solothurn",
    "wof:name":"Braunviehzuchtgenossenschaft Weiningen & Umgebung",
    "wof:placetype":"venue"
},
  "geometry": {"coordinates":[8.4348802567,47.419719696],"type":"Point"}
}