{
  "type": "Feature",
  "properties": {
    "iso:country":"CH",
    "sg:address":"Hardstrasse 5",
    "sg:city":"Lenzburg",
    "sg:orig_category":"Non-Classified Establishments",
    "sg:postcode":"5600",
    "sg:province":"Aargau",
    "wof:name":"Quadruple Gmbh",
    "wof:placetype":"venue"
},
  "geometry": {"coordinates":[8.857419014,47.1879272461],"type":"Point"}
}