{
  "type": "Feature",
  "properties": {
    "iso:country":"CH",
    "sg:address":"Gen\u00e8ve Rue De 93",
    "sg:city":"Th\u00f4nex",
    "sg:orig_category":"Herstellung von sonstigen elektrischen Ausr\u00fcstungen",
    "sg:postcode":"1226",
    "sg:province":"Gen\u00e8ve",
    "wof:name":"Vensa Sa",
    "wof:placetype":"venue"
},
  "geometry": {"coordinates":[6.552672863,46.5152549744],"type":"Point"}
}