{
  "type": "Feature",
  "properties": {
    "iso:country":"CH",
    "sg:address":"Triststrasse 15 7000 Chur. Postfach",
    "sg:city":"Chur",
    "sg:orig_category":"Fachdetailhandel in Verkaufsr\u00e4umen Kunsthandel",
    "sg:phone":"+41 81 252 07 08",
    "sg:postcode":"7007",
    "sg:province":"Graubunden",
    "wof:name":"Ftc Galerie 85 Kunsthandlung",
    "wof:placetype":"venue"
},
  "geometry": {"coordinates":[9.5073690414,46.8453178406],"type":"Point"}
}