{
  "type": "Feature",
  "properties": {
    "iso:country":"CH",
    "sg:address":"Rabbentalstrasse 83 3013 Bern. Postfach",
    "sg:city":"Bern",
    "sg:orig_category":"Interessenvertretungen",
    "sg:postcode":"3013",
    "sg:province":"Bern",
    "wof:name":"Stiftung F\u00fcr Patientensicherheit In Der An\u00e4sthesie",
    "wof:placetype":"venue"
},
  "geometry": {"coordinates":[7.4472727776,46.9520874023],"type":"Point"}
}