{
  "type": "Feature",
  "properties": {
    "iso:country":"CH",
    "sg:address":"Av. Cardinal-mermillod 42-44",
    "sg:city":"Carouge",
    "sg:classifiers":[
        {
            "category":"Banks & Credit Unions",
            "subcategory":"Bureau De Change",
            "type":"Services"
        }
    ],
    "sg:phone":"+41 21 792 12 83",
    "sg:postcode":"1227",
    "sg:province":"Gen\u00e8ve",
    "sg:tags":[
        "solution",
        "complete",
        "internet"
    ],
    "wof:name":"Quod Sa",
    "wof:placetype":"venue"
},
  "geometry": {"coordinates":[6.7025499344,46.5161094666],"type":"Point"}
}