{
  "type": "Feature",
  "properties": {
    "iso:country":"CH",
    "sg:address":"Via San Gottardo 17",
    "sg:city":"Muralto",
    "sg:orig_category":"Detailhandel mit Fahrr\u00e4dern Handel mit Motorr\u00e4dern, Teilen U Zubeh\u00f6r Instandhaltung U Reparatur von ",
    "sg:phone":"+41 91 743 38 85",
    "sg:postcode":"6600",
    "sg:province":"Ticino",
    "wof:name":"Walter Sutter Casa Due Route Cicli-moto",
    "wof:placetype":"venue"
},
  "geometry": {"coordinates":[8.8038930893,46.1740074158],"type":"Point"}
}