{
  "type": "Feature",
  "properties": {
    "addr:full":"Tegasa Rustico Lantsch Graubunden 7083",
    "addr:postcode":"7083",
    "iso:country":"CH",
    "sg:address":"Tegasa Rustico",
    "sg:city":"Lantsch",
    "sg:classifiers":[
        {
            "category":"Banks & Credit Unions",
            "subcategory":"Bank",
            "type":"Services"
        }
    ],
    "sg:phone":"+41 81 681 16 56",
    "sg:postcode":"7083",
    "sg:province":"Graubunden",
    "wof:name":"Raiffeisenbank, Lenzerheide-valbella-lantsch/lenz",
    "wof:placetype":"venue"
},
  "geometry": {"coordinates":[9.563297,46.685249],"type":"Point"}
}