{
  "type": "Feature",
  "properties": {
    "iso:country":"CH",
    "sg:address":"Feldeggstrasse 53",
    "sg:city":"Z\u00fcrich",
    "sg:orig_category":"Grosshandel mit M\u00f6beln, Wohnbedarf, Teppichen U Bodenbel\u00e4gen Sonstiger Grosshandel",
    "sg:phone":"+41 13825121",
    "sg:postcode":"8008",
    "sg:province":"Z\u00fcrich",
    "wof:name":"Arte Antica Isceri",
    "wof:placetype":"venue"
},
  "geometry": {"coordinates":[8.5525074005,47.3606071472],"type":"Point"}
}