{
  "type": "Feature",
  "properties": {
    "iso:country":"CH",
    "sg:address":"3551",
    "sg:city":"Oberfrittenbach",
    "sg:orig_category":"Primarschulen",
    "sg:phone":"+41 34 402 34 17",
    "sg:postcode":"3551",
    "sg:province":"Bern",
    "wof:name":"Primarschule Frittenbach",
    "wof:placetype":"venue"
},
  "geometry": {"coordinates":[7.7786197662,46.9516487122],"type":"Point"}
}