{
  "type": "Feature",
  "properties": {
    "iso:country":"CH",
    "sg:address":"Poststrasse 1",
    "sg:city":"Oetwil",
    "sg:orig_category":"Detailhandel mit Blumen U Pflanzen Verwaltung von Immobilien",
    "sg:phone":"+41 81 756 15 30",
    "sg:postcode":"8955",
    "sg:province":"Z\u00fcrich",
    "wof:name":"Rt Verwaltungs Ag",
    "wof:placetype":"venue"
},
  "geometry": {"coordinates":[9.47326,47.165936],"type":"Point"}
}