{
  "type": "Feature",
  "properties": {
    "iso:country":"CH",
    "sg:address":"Kapellgasse 4 6004 Luzern. Postfach",
    "sg:city":"Luzern",
    "sg:orig_category":"Warenh\u00e4user",
    "sg:phone":"+41 41 410 48 51",
    "sg:postcode":"6002",
    "sg:province":"Luzern",
    "wof:name":"Abm Au Bon March\u00e9",
    "wof:placetype":"venue"
},
  "geometry": {"coordinates":[8.3073549271,47.0526885986],"type":"Point"}
}