{
  "type": "Feature",
  "properties": {
    "iso:country":"CH",
    "sg:address":"Luzernerstrasse 117",
    "sg:city":"Littau",
    "sg:orig_category":"Elektroinstallation Herstellung von elektronischen Bauelementen",
    "sg:phone":"+41 41 250 26 16",
    "sg:postcode":"6014",
    "sg:province":"Luzern",
    "wof:name":"Martina Ag Elektrounternehmung",
    "wof:placetype":"venue"
},
  "geometry": {"coordinates":[8.2690477371,47.0503120422],"type":"Point"}
}