{
  "type": "Feature",
  "properties": {
    "iso:country":"CH",
    "sg:address":"4852",
    "sg:city":"Rothrist",
    "sg:orig_category":"Elektrizit\u00e4tsversorgung",
    "sg:phone":"+41 71 966 21 40",
    "sg:postcode":"4852",
    "sg:province":"Aargau",
    "wof:name":"Elektrizit\u00e4ts Und Wasserwerk M\u00fcnchwilen (ewm)",
    "wof:placetype":"venue"
},
  "geometry": {"coordinates":[8.9961204529,47.4795417786],"type":"Point"}
}