{
  "type": "Feature",
  "properties": {
    "iso:country":"CH",
    "sg:address":"Ringstrasse 19",
    "sg:city":"Frauenfeld",
    "sg:orig_category":"Advokaturb\u00fcros",
    "sg:phone":"+41 52 721 01 42",
    "sg:postcode":"8500",
    "sg:province":"Thurgau",
    "wof:name":"Dr.brigit H\u00e4nzi Advokaturb\u00fcro",
    "wof:placetype":"venue"
},
  "geometry": {"coordinates":[8.902502,47.556667],"type":"Point"}
}