{
  "type": "Feature",
  "properties": {
    "iso:country":"CH",
    "sg:address":"Rue Du Jura 12",
    "sg:city":"Gland",
    "sg:orig_category":"Physiotherapie",
    "sg:phone":"+41 22 364 41 77",
    "sg:postcode":"1196",
    "sg:province":"Vaud",
    "wof:name":"Muriel Delpiano Physioth\u00e9rapie",
    "wof:placetype":"venue"
},
  "geometry": {"coordinates":[6.2634501457,46.4245452881],"type":"Point"}
}