{
  "type": "Feature",
  "properties": {
    "iso:country":"CH",
    "sg:address":"Rue De L'ecluse 1",
    "sg:city":"Moutier",
    "sg:orig_category":"Detailhandel mit Uhren U Schmuck Reparatur von Uhren U Schmuck",
    "sg:phone":"+41 32 493 59 58",
    "sg:postcode":"2740",
    "sg:province":"Bern",
    "wof:name":"Fran\u00e7ois Pelletier Au Joyau Bijouterie Horlogerie",
    "wof:placetype":"venue"
},
  "geometry": {"coordinates":[7.382581234,47.2798233032],"type":"Point"}
}