{
  "type": "Feature",
  "properties": {
    "iso:country":"CH",
    "sg:address":"Rotfarb",
    "sg:city":"Neftenbach",
    "sg:orig_category":"Maschinen-Fabrikation",
    "sg:phone":"+41 52 304 08 01",
    "sg:postcode":"8413",
    "sg:province":"Z\u00fcrich",
    "wof:name":"Global Tech Ag",
    "wof:placetype":"venue"
},
  "geometry": {"coordinates":[8.6571483612,47.523147583],"type":"Point"}
}