{
  "type": "Feature",
  "properties": {
    "iso:country":"CH",
    "sg:address":"R\u00fcediswilerstrasse 5 6313 Menzingen. Postfach",
    "sg:city":"Ruswil",
    "sg:orig_category":"Unternehmensberatung",
    "sg:phone":"+41 41 755 31 20",
    "sg:postcode":"6017",
    "sg:province":"Luzern",
    "wof:name":"B & E Management Services Gmbh",
    "wof:placetype":"venue"
},
  "geometry": {"coordinates":[8.5906457901,47.1783485413],"type":"Point"}
}