{
  "type": "Feature",
  "properties": {
    "iso:country":"CH",
    "sg:address":"Unterdorfstrasse 3",
    "sg:city":"Udligenswil",
    "sg:orig_category":"Instandhaltung U Reparatur von Automobilen Tankstellen",
    "sg:phone":"+41 41 371 00 68",
    "sg:postcode":"6044",
    "sg:province":"Luzern",
    "wof:name":"Spot-garage Gisler Karl",
    "wof:placetype":"venue"
},
  "geometry": {"coordinates":[8.4007005692,47.089214325],"type":"Point"}
}