{
  "type": "Feature",
  "properties": {
    "iso:country":"CH",
    "sg:address":"Seetalstrasse 5",
    "sg:city":"Boniswil",
    "sg:orig_category":"Instandhaltung U Reparatur von Automobilen Tankstellen",
    "sg:phone":"+41 62 777 13 73",
    "sg:postcode":"5706",
    "sg:province":"Aargau",
    "wof:name":"Auto-urech Ag.",
    "wof:placetype":"venue"
},
  "geometry": {"coordinates":[8.1841602325,47.3173599243],"type":"Point"}
}