{
  "type": "Feature",
  "properties": {
    "iso:country":"CH",
    "sg:address":"Klybeckstrasse 83",
    "sg:city":"Basel",
    "sg:orig_category":"Non-Classified Establishments",
    "sg:postcode":"4057",
    "sg:province":"Basel-Stadt",
    "wof:name":"Vta Versicherungs-treuhand Agentur, K. G\u00fcrbuga",
    "wof:placetype":"venue"
},
  "geometry": {"coordinates":[7.5902872086,47.5684356689],"type":"Point"}
}