{
  "type": "Feature",
  "properties": {
    "iso:country":"CH",
    "sg:address":"Unterstadt 42 8200 Schaffhausen. Postfach",
    "sg:city":"Schaffhausen",
    "sg:orig_category":"Fussboden, Fliesen U Plattenlegerei, Tapeziererei Verlegen von Fliesen U Platten",
    "sg:phone":"+41 52 625 21 10",
    "sg:postcode":"8202",
    "sg:province":"Schaffhausen",
    "wof:name":"Leoni Otto, Inhaber J\u00fcrg Leoni.",
    "wof:placetype":"venue"
},
  "geometry": {"coordinates":[8.6385602951,47.6959228516],"type":"Point"}
}