{
  "type": "Feature",
  "properties": {
    "iso:country":"CH",
    "sg:address":"Hauptstrasse 56",
    "sg:city":"Seltisberg",
    "sg:orig_category":"Herstellung von Schreibwaren U B\u00fcrobedarf aus Papier, Karton U Pappe",
    "sg:postcode":"4411",
    "sg:province":"Basel-Landschaft",
    "wof:name":"Roggwiler, Hans",
    "wof:placetype":"venue"
},
  "geometry": {"coordinates":[8.4597253799,47.2789268494],"type":"Point"}
}