{
  "type": "Feature",
  "properties": {
    "iso:country":"CH",
    "sg:address":"Rosengartenstrasse 5",
    "sg:city":"Z\u00fcrich",
    "sg:orig_category":"Detailhandel mit Teppichen Grosshandel mit Erzen U Metallen",
    "sg:phone":"+41 12714646",
    "sg:postcode":"8037",
    "sg:province":"Z\u00fcrich",
    "wof:name":"Sinacarpets Teppichgesch\u00e4ft Saeed Reza Furutanpey",
    "wof:placetype":"venue"
},
  "geometry": {"coordinates":[8.5246734619,47.3937911987],"type":"Point"}
}