{
  "type": "Feature",
  "properties": {
    "iso:country":"CH",
    "sg:address":"Dullikerstrasse 2",
    "sg:city":"Oberg\u00f6sgen",
    "sg:orig_category":"Finanzierungsinstitutionen",
    "sg:phone":"+41 62 295 40 64",
    "sg:postcode":"4653",
    "sg:province":"Solothurn",
    "wof:name":"Woma Anita Wobmann",
    "wof:placetype":"venue"
},
  "geometry": {"coordinates":[7.9550051689,47.3554344177],"type":"Point"}
}