{
  "type": "Feature",
  "properties": {
    "iso:country":"CH",
    "sg:address":"L\u00f6wenstrasse 17",
    "sg:city":"Dietikon",
    "sg:orig_category":"Arztpraxen",
    "sg:phone":"+41 17453535",
    "sg:postcode":"8953",
    "sg:province":"Z\u00fcrich",
    "wof:name":"Dres Med. D\u00e4twyler & Meister Spezial\u00e4rzte Fmh",
    "wof:placetype":"venue"
},
  "geometry": {"coordinates":[8.402478,47.405472],"type":"Point"}
}