{
  "type": "Feature",
  "properties": {
    "iso:country":"CH",
    "sg:address":"6466",
    "sg:city":"Bauen",
    "sg:classifiers":[
        {
            "category":"Restaurant",
            "type":"Food & Drink"
        }
    ],
    "sg:phone":"+41 41 878 11 30",
    "sg:postcode":"6466",
    "sg:province":"Uri",
    "wof:name":"Gasthaus Sch\u00fctzen",
    "wof:placetype":"venue"
},
  "geometry": {"coordinates":[8.5792150497,46.934551239],"type":"Point"}
}