{
  "type": "Feature",
  "properties": {
    "iso:country":"CH",
    "sg:address":"Talstrasse 72",
    "sg:city":"B\u00e4ttwil-fl\u00fch",
    "sg:orig_category":"M\u00f6belschreinereien",
    "sg:postcode":"4112",
    "sg:province":"Solothurn",
    "wof:name":"Mattinelli E Delmenico",
    "wof:placetype":"venue"
},
  "geometry": {"coordinates":[8.8408298492,46.0080795288],"type":"Point"}
}