{
  "type": "Feature",
  "properties": {
    "iso:country":"CH",
    "sg:address":"Bahnhofstrasse 16",
    "sg:city":"Biel/bienne",
    "sg:orig_category":"Architektur U Ingenieurb\u00fcros",
    "sg:phone":"+41 32 323 69 27",
    "sg:postcode":"2502",
    "sg:province":"Bern",
    "wof:name":"Bonnard & Gardel Ing\u00e9nieurs-conseils Sa",
    "wof:placetype":"venue"
},
  "geometry": {"coordinates":[7.244486,47.134789],"type":"Point"}
}