{
  "type": "Feature",
  "properties": {
    "addr:full":"Alleriedweg 11 Schneisingen Aargau 5425",
    "addr:housenumber":"11",
    "addr:postcode":"5425",
    "addr:street":"Alleriedweg",
    "iso:country":"CH",
    "sg:address":"Alleriedweg 11",
    "sg:city":"Schneisingen",
    "sg:orig_category":"Architektur U Ingenieurb\u00fcros Ingenieurb\u00fcros Maschinenbau",
    "sg:phone":"+41 56 241 22 33",
    "sg:postcode":"5425",
    "sg:province":"Aargau",
    "wof:name":"Techno Ring Ag",
    "wof:placetype":"venue"
},
  "geometry": {"coordinates":[8.35901,47.524158],"type":"Point"}
}