{
  "type": "Feature",
  "properties": {
    "iso:country":"CH",
    "sg:address":"St. Luzistrasse 6",
    "sg:city":"Chur",
    "sg:orig_category":"Interessenvertretungen",
    "sg:phone":"+41 81 255 12 00",
    "sg:postcode":"7000",
    "sg:province":"Graubunden",
    "wof:name":"Rettungsanaesthesie Real\u00fc",
    "wof:placetype":"venue"
},
  "geometry": {"coordinates":[9.5361976624,46.8460540771],"type":"Point"}
}