{
  "type": "Feature",
  "properties": {
    "iso:country":"CH",
    "sg:address":"Weinfelder-strasse 30a",
    "sg:city":"Amriswil",
    "sg:orig_category":"Non-Classified Establishments",
    "sg:postcode":"8580",
    "sg:province":"Thurgau",
    "wof:name":"Optima-computer Gmbh",
    "wof:placetype":"venue"
},
  "geometry": {"coordinates":[9.2937164307,47.5453834534],"type":"Point"}
}