{
  "type": "Feature",
  "properties": {
    "addr:full":"Weidenstrasse 13 M\u00fcnchenstein Basel-Landschaft 4142",
    "addr:housenumber":"13",
    "addr:postcode":"4142",
    "addr:street":"Weidenstrasse",
    "iso:country":"CH",
    "sg:address":"Weidenstrasse 13",
    "sg:city":"M\u00fcnchenstein",
    "sg:orig_category":"Bauingenieurb\u00fcros allgemein",
    "sg:phone":"+41 61 411 96 11",
    "sg:postcode":"4142",
    "sg:province":"Basel-Landschaft",
    "wof:name":"Hans-ulrich Aeschlimann Ingenieurb\u00fcro",
    "wof:placetype":"venue"
},
  "geometry": {"coordinates":[7.617737,47.51572],"type":"Point"}
}