{
  "type": "Feature",
  "properties": {
    "iso:country":"CH",
    "sg:address":"4494",
    "sg:city":"Oltingen",
    "sg:orig_category":"Sportvereine Turnen",
    "sg:postcode":"4494",
    "sg:province":"Basel-Landschaft",
    "wof:name":"Turnverein",
    "wof:placetype":"venue"
},
  "geometry": {"coordinates":[7.929599762,47.4322509766],"type":"Point"}
}