{
  "type": "Feature",
  "properties": {
    "iso:country":"CH",
    "sg:address":"R\u00f6ssliwiese 4 9058 Br\u00fclisau. Postfach",
    "sg:city":"Br\u00fclisau",
    "sg:orig_category":"Sanit\u00e4r, Heizungs U L\u00fcftungsinstallation",
    "sg:postcode":"9058",
    "sg:province":"Appenzell Innerhoden",
    "wof:name":"Hunter H\u00f6gger Peter Heizungsmontagen, Sanierungen U. Neuanlagen Usw",
    "wof:placetype":"venue"
},
  "geometry": {"coordinates":[9.4539012909,47.2974853516],"type":"Point"}
}