{
  "type": "Feature",
  "properties": {
    "iso:country":"CH",
    "sg:address":"Badhusweg 4",
    "sg:city":"Malters",
    "sg:orig_category":"Detailhandel mit Brot, Back U S\u00fcsswaren",
    "sg:phone":"+41 41 497 12 72",
    "sg:postcode":"6102",
    "sg:province":"Luzern",
    "wof:name":"Daniel Iten Konditorei Zum Freihof",
    "wof:placetype":"venue"
},
  "geometry": {"coordinates":[8.18309,47.03804],"type":"Point"}
}