{
  "type": "Feature",
  "properties": {
    "iso:country":"CH",
    "sg:address":"Cornavin Rue De 11 1201 Gen\u00e8ve. Postfach",
    "sg:city":"Gen\u00e8ve",
    "sg:classifiers":[
        {
            "category":"Professional",
            "subcategory":"Employment Agencies",
            "type":"Services"
        }
    ],
    "sg:postcode":"1201",
    "sg:province":"Gen\u00e8ve",
    "sg:tags":[
        "personal",
        "u",
        "stellenvermittlung"
    ],
    "wof:name":"Service Tempostable, Christiane Gavin",
    "wof:placetype":"venue"
},
  "geometry": {"coordinates":[6.1422758102,46.2079963684],"type":"Point"}
}