{
  "type": "Feature",
  "properties": {
    "iso:country":"CH",
    "sg:address":"Chemin De Fontanney 39 1052 Mont-sur-lausanne Case Postale 44",
    "sg:city":"Mont-sur-lausanne",
    "sg:orig_category":"Innenausbau Zimmerei, Dachdeckerei, Bauspenglerei U Abdichtung",
    "sg:phone":"+41 21 653 49 04",
    "sg:postcode":"1052",
    "sg:province":"Vaud",
    "wof:name":"Yvan Graz Charpente & Escaliers",
    "wof:placetype":"venue"
},
  "geometry": {"coordinates":[6.6441979408,46.5660514832],"type":"Point"}
}