{
  "type": "Feature",
  "properties": {
    "iso:country":"CH",
    "sg:address":"Huggenbergerstrasse 9",
    "sg:city":"Gerlikon",
    "sg:orig_category":"Hochschulen U h\u00f6here Ausbildung",
    "sg:postcode":"8500",
    "sg:province":"Thurgau",
    "wof:name":"Bosshard Hansruedi & Partner, Pers\u00f6nlichkeitsbildung Und Verhaltenstraining",
    "wof:placetype":"venue"
},
  "geometry": {"coordinates":[8.8785266876,47.5394668579],"type":"Point"}
}