{
  "type": "Feature",
  "properties": {
    "iso:country":"CH",
    "sg:address":"H\u00fcbelistrasse 18 6020 Emmenbr\u00fccke. Postfach",
    "sg:city":"Luzern",
    "sg:orig_category":"Pensionskassen",
    "sg:phone":"+41 41 210 37 37",
    "sg:postcode":"6003",
    "sg:province":"Luzern",
    "wof:name":"Patronale Personalvorsorgestiftung Der Opes-gruppe",
    "wof:placetype":"venue"
},
  "geometry": {"coordinates":[8.2760801315,47.0858039856],"type":"Point"}
}