{
  "type": "Feature",
  "properties": {
    "iso:country":"CH",
    "sg:address":"Bl\u00e4siring 155 4057 Basel. Postfach",
    "sg:city":"Basel",
    "sg:orig_category":"Handels-H\u00e4user U Gesellschaften",
    "sg:postcode":"4051",
    "sg:province":"Basel-Stadt",
    "wof:name":"Franz Buess, Trading Warenhandel.",
    "wof:placetype":"venue"
},
  "geometry": {"coordinates":[7.5952568054,47.5688591003],"type":"Point"}
}