{
  "type": "Feature",
  "properties": {
    "iso:country":"CH",
    "sg:address":"Bahnhofplatz 11b",
    "sg:city":"Madiswil",
    "sg:orig_category":"Detailhandel mit Zeitungen U Zeitschriften Kioske",
    "sg:phone":"+41 62 965 02 22",
    "sg:postcode":"4934",
    "sg:province":"Bern",
    "wof:name":"Kiosk Beim Bahnhof Esther Sieber",
    "wof:placetype":"venue"
},
  "geometry": {"coordinates":[7.798514843,47.1655158997],"type":"Point"}
}