{
  "type": "Feature",
  "properties": {
    "addr:full":"Krankenhausweg 18a M\u00fcnsingen Bern 3110",
    "addr:housenumber":"18a",
    "addr:postcode":"3110",
    "addr:street":"Krankenhausweg",
    "iso:country":"CH",
    "sg:address":"Krankenhausweg 18a",
    "sg:city":"M\u00fcnsingen",
    "sg:orig_category":"Arztpraxen",
    "sg:phone":"+41 31 720 23 23",
    "sg:postcode":"3110",
    "sg:province":"Bern",
    "wof:name":"Dr.med.markus C. Michel Spezialarzt Fmh",
    "wof:placetype":"venue"
},
  "geometry": {"coordinates":[7.568418,46.87188],"type":"Point"}
}