{
  "type": "Feature",
  "properties": {
    "iso:country":"CH",
    "sg:address":"R\u00fctelti 377",
    "sg:city":"Triesenberg",
    "sg:orig_category":"Elektroinstallation",
    "sg:phone":"+41 62 771 30 53",
    "sg:postcode":"9497",
    "wof:name":"Otto Steiner Ag",
    "wof:placetype":"venue"
},
  "geometry": {"coordinates":[8.2029390335,47.2663993835],"type":"Point"}
}