{
  "type": "Feature",
  "properties": {
    "addr:full":"Bahnhofstrasse 14 Klosters Graubunden 7250",
    "addr:housenumber":"14",
    "addr:postcode":"7250",
    "addr:street":"Bahnhofstrasse",
    "iso:country":"CH",
    "sg:address":"Bahnhofstrasse 14",
    "sg:city":"Klosters",
    "sg:orig_category":"Darlehenskassen U Raiffeisenbanken",
    "sg:phone":"+41 19702120",
    "sg:postcode":"7250",
    "sg:province":"Graubunden",
    "wof:name":"Raiffeisenbank",
    "wof:placetype":"venue"
},
  "geometry": {"coordinates":[8.799845,47.326904],"type":"Point"}
}