{
  "type": "Feature",
  "properties": {
    "iso:country":"CH",
    "sg:address":"Steinackerstrasse 15 4573 Lohn So. Postfach",
    "sg:city":"Ammannsegg",
    "sg:orig_category":"Herstellung von k\u00e4lte U lufttechnischen Erzeugnissen f\u00fcr gewerbliche Zwecke",
    "sg:postcode":"4573",
    "sg:province":"Solothurn",
    "wof:name":"H\u00e4felfinger Gmbh Installations Und Unterhaltsarbeiten In Den Ber. W\u00e4rmer\u00fcckgewinnung, L\u00fcftungstechnik",
    "wof:placetype":"venue"
},
  "geometry": {"coordinates":[7.5289850235,47.1714172363],"type":"Point"}
}