{
  "type": "Feature",
  "properties": {
    "iso:country":"CH",
    "sg:address":"Rue Des Bains 25",
    "sg:city":"Gen\u00e8ve",
    "sg:orig_category":"Elektroinstallation",
    "sg:postcode":"1205",
    "sg:province":"Gen\u00e8ve",
    "wof:name":"Glaettli, Mechanik Und Montagen Mechanische Ger\u00e4te; Herstellung, Reparaturen",
    "wof:placetype":"venue"
},
  "geometry": {"coordinates":[8.897901535,47.1833076477],"type":"Point"}
}