{
  "type": "Feature",
  "properties": {
    "iso:country":"CH",
    "sg:address":"Rue Neuve 41",
    "sg:city":"Villeret",
    "sg:orig_category":"Herstellung von Schrauben, Nieten, Ketten U Federn",
    "sg:phone":"+41 32 941 23 37",
    "sg:postcode":"2613",
    "sg:province":"Bern",
    "wof:name":"Roger Tschumi D\u00e9colletages",
    "wof:placetype":"venue"
},
  "geometry": {"coordinates":[7.0165290833,47.1592788696],"type":"Point"}
}