{
  "type": "Feature",
  "properties": {
    "iso:country":"CH",
    "sg:address":"Sous Moron 5",
    "sg:city":"B\u00e9vilard",
    "sg:orig_category":"Architektur U Ingenieurb\u00fcros",
    "sg:phone":"+41 32 492 22 75",
    "sg:postcode":"2735",
    "sg:province":"Bern",
    "wof:name":"Zenger Patrick, Renobautech",
    "wof:placetype":"venue"
},
  "geometry": {"coordinates":[7.28113,47.24725],"type":"Point"}
}