{
  "type": "Feature",
  "properties": {
    "iso:country":"CH",
    "sg:address":"Rue Du Rh\u00f4ne 19",
    "sg:city":"Aigle",
    "sg:orig_category":"Reparatur von Schuhen U Lederwaren",
    "sg:phone":"+41 24 466 12 24",
    "sg:postcode":"1860",
    "sg:province":"Vaud",
    "wof:name":"Laurence Manigley Cordonnerie La Savatte",
    "wof:placetype":"venue"
},
  "geometry": {"coordinates":[6.9664669037,46.3177986145],"type":"Point"}
}