{
  "type": "Feature",
  "properties": {
    "iso:country":"CH",
    "sg:address":"T\u00f6sstalstrasse 140",
    "sg:city":"Turbenthal",
    "sg:orig_category":"Herstellung von Werkzeugen",
    "sg:phone":"+41 52 762 62 62",
    "sg:postcode":"8488",
    "sg:province":"Z\u00fcrich",
    "wof:name":"Utilis Ag",
    "wof:placetype":"venue"
},
  "geometry": {"coordinates":[9.0056085587,47.6033782959],"type":"Point"}
}