{
  "type": "Feature",
  "properties": {
    "iso:country":"CH",
    "sg:address":"Niesenstrasse 51",
    "sg:city":"Thierachern",
    "sg:orig_category":"Grosshandel mit Datenverarbeitungsger\u00e4ten Softwareentwicklung U beratung",
    "sg:phone":"+41 79 214 52 25",
    "sg:postcode":"3634",
    "sg:province":"Bern",
    "wof:name":"Computer Solution Jaquier S\u00e0rl",
    "wof:placetype":"venue"
},
  "geometry": {"coordinates":[6.9182190895,46.6966667175],"type":"Point"}
}