{
  "type": "Feature",
  "properties": {
    "iso:country":"CH",
    "sg:address":"Poststrasse 18",
    "sg:city":"Richterswil",
    "sg:orig_category":"Reiseb\u00fcros",
    "sg:phone":"+41 17876969",
    "sg:postcode":"8805",
    "sg:province":"Z\u00fcrich",
    "wof:name":"Jo-jo Reisen",
    "wof:placetype":"venue"
},
  "geometry": {"coordinates":[8.7056207657,47.2082328796],"type":"Point"}
}