{
  "type": "Feature",
  "properties": {
    "iso:country":"CH",
    "sg:address":"Lindenstrasse 2a",
    "sg:city":"D\u00e4llikon",
    "sg:classifiers":[
        {
            "category":"Professional",
            "subcategory":"Employment Agencies",
            "type":"Services"
        }
    ],
    "sg:phone":"+41 18725353",
    "sg:postcode":"8108",
    "sg:province":"Z\u00fcrich",
    "sg:tags":[
        "personal",
        "u",
        "stellenvermittlung"
    ],
    "wof:name":"Meister-b\u00f6rse Gmbh",
    "wof:placetype":"venue"
},
  "geometry": {"coordinates":[8.4344377518,47.4464988708],"type":"Point"}
}