{
  "type": "Feature",
  "properties": {
    "addr:full":"Breiti 26 Mellingen Aargau 5507",
    "addr:housenumber":"26",
    "addr:postcode":"5507",
    "addr:street":"Breiti",
    "iso:country":"CH",
    "sg:address":"Breiti 26",
    "sg:city":"Mellingen",
    "sg:orig_category":"Architektur U Ingenieurb\u00fcros Architekturb\u00fcros",
    "sg:phone":"+41 56 491 14 44",
    "sg:postcode":"5507",
    "sg:province":"Aargau",
    "wof:name":"Masarik + Muff Architektur + Planungsb\u00fcro",
    "wof:placetype":"venue"
},
  "geometry": {"coordinates":[8.272705,47.42374],"type":"Point"}
}