{
  "type": "Feature",
  "properties": {
    "iso:country":"CH",
    "sg:address":"Chlupfwisstrasse 34",
    "sg:city":"Oberweningen",
    "sg:orig_category":"Arztpraxen",
    "sg:phone":"+41 18561600",
    "sg:postcode":"8165",
    "sg:province":"Z\u00fcrich",
    "wof:name":"Dres Med. C. & U. K\u00f6ppel Aerzte F\u00fcr Allg.medizin Fmh",
    "wof:placetype":"venue"
},
  "geometry": {"coordinates":[8.410985,47.500172],"type":"Point"}
}