{
  "type": "Feature",
  "properties": {
    "iso:country":"CH",
    "sg:address":"Lindenstrasse 22",
    "sg:city":"Frauenfeld",
    "sg:orig_category":"Grosshandel mit Obst U Gem\u00fcse",
    "sg:phone":"+41 52 720 58 72",
    "sg:postcode":"8500",
    "sg:province":"Thurgau",
    "wof:name":"Gunterswiler Jakob",
    "wof:placetype":"venue"
},
  "geometry": {"coordinates":[8.8973693848,47.5595588684],"type":"Point"}
}