{
  "type": "Feature",
  "properties": {
    "iso:country":"CH",
    "sg:address":"Route De La Gl\u00e2ne 136",
    "sg:city":"Villars-sur-gl\u00e2ne",
    "sg:orig_category":"Giessereiindustrie Herstellung von Metallerzeugnissen ohne Maschinenbau",
    "sg:phone":"+41 26 402 76 03",
    "sg:postcode":"1752",
    "sg:province":"Fribourg",
    "wof:name":"Marius Br\u00fcgger & Fils S\u00e0rl Fonderie De Cloches",
    "wof:placetype":"venue"
},
  "geometry": {"coordinates":[7.1355228424,46.789390564],"type":"Point"}
}