{
  "type": "Feature",
  "properties": {
    "iso:country":"CH",
    "sg:address":"Chamerstrasse 158",
    "sg:city":"Zug",
    "sg:orig_category":"Architektur U Ingenieurb\u00fcros",
    "sg:postcode":"6300",
    "sg:province":"Zug",
    "wof:name":"Hoppe Engineering Ag",
    "wof:placetype":"venue"
},
  "geometry": {"coordinates":[8.485862,47.180737],"type":"Point"}
}