{
  "type": "Feature",
  "properties": {
    "iso:country":"CH",
    "sg:address":"Zeughausstrasse 8887 Mels. Postfach 94",
    "sg:city":"Mels",
    "sg:orig_category":"Maler U Glasergewerbe Stukkateurgewerbe, Gipserei U Verputzerei",
    "sg:phone":"+41 79 438 25 44",
    "sg:postcode":"8887",
    "sg:province":"St. Gallen",
    "wof:name":"Brunner Malerei Ag",
    "wof:placetype":"venue"
},
  "geometry": {"coordinates":[9.4077148438,47.0566482544],"type":"Point"}
}