{
  "type": "Feature",
  "properties": {
    "iso:country":"CH",
    "sg:address":"Weisse Gasse 14",
    "sg:city":"Basel",
    "sg:orig_category":"Kosmetikinstitute",
    "sg:phone":"+41 61 262 00 15",
    "sg:postcode":"4001",
    "sg:province":"Basel-Stadt",
    "wof:name":"C. Hundertmark & C. Verheijen Coiffeur Claus Cosmetic Carla",
    "wof:placetype":"venue"
},
  "geometry": {"coordinates":[7.5894241333,47.5557250977],"type":"Point"}
}