{
  "type": "Feature",
  "properties": {
    "iso:country":"CH",
    "sg:address":"Hinterdorf 1",
    "sg:city":"Jens",
    "sg:orig_category":"Allgemeiner Hochbau",
    "sg:phone":"+41 32 331 29 29",
    "sg:postcode":"2565",
    "sg:province":"Bern",
    "wof:name":"Godi Tr\u00e4chsel Geb\u00e4uderenovationen",
    "wof:placetype":"venue"
},
  "geometry": {"coordinates":[7.262913,47.097969],"type":"Point"}
}