{
  "type": "Feature",
  "properties": {
    "iso:country":"CH",
    "sg:address":"Luisenstrasse 33",
    "sg:city":"Z\u00fcrich",
    "sg:orig_category":"Instandhaltung U Reparatur von Automobilen",
    "sg:phone":"+41 12725545",
    "sg:postcode":"8005",
    "sg:province":"Z\u00fcrich",
    "wof:name":"Ueli Mayer Auto-elektro",
    "wof:placetype":"venue"
},
  "geometry": {"coordinates":[8.5296697617,47.3839797974],"type":"Point"}
}