{
  "type": "Feature",
  "properties": {
    "iso:country":"CH",
    "sg:address":"Widenackerstrasse 15",
    "sg:city":"Wiezikon",
    "sg:classifiers":[
        {
            "category":"Banks & Credit Unions",
            "subcategory":"Investment Brokerage",
            "type":"Services"
        }
    ],
    "sg:phone":"+41 71 960 00 77",
    "sg:postcode":"8372",
    "sg:province":"Thurgau",
    "sg:tags":[
        "electric",
        "drill",
        "hand"
    ],
    "wof:name":"Walter R\u00fcegg Maschinen & Werkzeuge",
    "wof:placetype":"venue"
},
  "geometry": {"coordinates":[8.980260849,47.4517784119],"type":"Point"}
}