{
  "type": "Feature",
  "properties": {
    "iso:country":"CH",
    "sg:address":"Baarerstrasse 8",
    "sg:city":"Zug",
    "sg:orig_category":"Unclassifiable Establishments",
    "sg:postcode":"6300",
    "sg:province":"Zug",
    "wof:name":"Gade-bar Bodmen, Bortis Andrea",
    "wof:placetype":"venue"
},
  "geometry": {"coordinates":[8.2168703079,46.4560203552],"type":"Point"}
}