{
  "type": "Feature",
  "properties": {
    "iso:country":"CH",
    "sg:address":"Dorfstrasse 67",
    "sg:city":"Kleinl\u00fctzel",
    "sg:orig_category":"Erbringung von sonstigen Dienstleistungen f\u00fcr Unterhaltung, Erholung U Freizeit Sonstige Hilfsdienst",
    "sg:phone":"+41 61 771 05 59",
    "sg:postcode":"4245",
    "sg:province":"Solothurn",
    "wof:name":"Dreier Heidi, K\u00fcnstler Und Orchesteragentur.",
    "wof:placetype":"venue"
},
  "geometry": {"coordinates":[7.4179902077,47.4269866943],"type":"Point"}
}