{
  "type": "Feature",
  "properties": {
    "iso:country":"CH",
    "sg:address":"Sch\u00fctzemur 2",
    "sg:city":"Rafz",
    "sg:orig_category":"Sportvereine Ballsport Tennis",
    "sg:phone":"+41 596074",
    "sg:postcode":"8197",
    "sg:province":"Z\u00fcrich",
    "wof:name":"Tc Itschnach",
    "wof:placetype":"venue"
},
  "geometry": {"coordinates":[8.6010103226,47.3284378052],"type":"Point"}
}