{
  "type": "Feature",
  "properties": {
    "iso:country":"CH",
    "sg:address":"M\u00fchlengasse 73",
    "sg:city":"Merishausen",
    "sg:orig_category":"Herstellung von Verbrennungsmotoren U Turbinen ohne Motoren f\u00fcr Luft U Strassenfahrzeuge",
    "sg:phone":"+41 52 653 16 12",
    "sg:postcode":"8232",
    "sg:province":"Schaffhausen",
    "wof:name":"Wirth Silvio Motorger\u00e4te",
    "wof:placetype":"venue"
},
  "geometry": {"coordinates":[8.6092300415,47.7609863281],"type":"Point"}
}