{
  "type": "Feature",
  "properties": {
    "iso:country":"CH",
    "sg:address":"Simmlersteig 6",
    "sg:city":"Z\u00fcrich",
    "sg:orig_category":"Dachdeckerei Zimmerei, Dachdeckerei, Bauspenglerei U Abdichtung",
    "sg:phone":"+41 14816296",
    "sg:postcode":"8038",
    "sg:province":"Z\u00fcrich",
    "wof:name":"R\u00fcedi Bedachungen",
    "wof:placetype":"venue"
},
  "geometry": {"coordinates":[8.531009,47.343864],"type":"Point"}
}