{
  "type": "Feature",
  "properties": {
    "iso:country":"CH",
    "sg:address":"Rue Du Vieux-moulin 17",
    "sg:city":"Court\u00e9telle",
    "sg:orig_category":"Grosshandel mit sonstigen Maschinen U Ausr\u00fcstungen f\u00fcr Industrie, Handel U Schiffahrt Landwirtschaft",
    "sg:phone":"+41 32 422 31 86",
    "sg:postcode":"2852",
    "sg:province":"Jura",
    "wof:name":"Laurent & Christian Comte V\u00e9hicules-machines",
    "wof:placetype":"venue"
},
  "geometry": {"coordinates":[7.3125319481,47.3410301208],"type":"Point"}
}