{
  "type": "Feature",
  "properties": {
    "iso:country":"CH",
    "sg:address":"Friesenbergstrasse 221",
    "sg:city":"Z\u00fcrich",
    "sg:orig_category":"Geb\u00e4ude, Wohnungsreinigung Reinigungsgewerbe",
    "sg:phone":"+41 71 971 23 44",
    "sg:postcode":"8055",
    "sg:province":"Z\u00fcrich",
    "wof:name":"H\u00f6rnli-reinigung Furrer P.",
    "wof:placetype":"venue"
},
  "geometry": {"coordinates":[8.9705295563,47.4648666382],"type":"Point"}
}