{
  "type": "Feature",
  "properties": {
    "iso:country":"CH",
    "sg:address":"Oberhofstrasse 25 6020 Emmenbr\u00fccke. Postfach 3201",
    "sg:city":"Luzern",
    "sg:orig_category":"Unternehmensberatung",
    "sg:phone":"+41 41 282 08 55",
    "sg:postcode":"6002",
    "sg:province":"Luzern",
    "wof:name":"Institut Human Resources Albert Urban Hug + Partner",
    "wof:placetype":"venue"
},
  "geometry": {"coordinates":[8.2844161987,47.0746612549],"type":"Point"}
}