{
  "type": "Feature",
  "properties": {
    "iso:country":"CH",
    "sg:address":"Freihofstrasse 14",
    "sg:city":"Z\u00fcrich",
    "sg:orig_category":"Architektur U Ingenieurb\u00fcros Architekturb\u00fcros",
    "sg:phone":"+41 13621525",
    "sg:postcode":"8048",
    "sg:province":"Z\u00fcrich",
    "wof:name":"Kalfopoulos + Mezzi Architekten",
    "wof:placetype":"venue"
},
  "geometry": {"coordinates":[8.501003,47.385532],"type":"Point"}
}