{
  "type": "Feature",
  "properties": {
    "iso:country":"CH",
    "sg:address":"Altstetterstrasse 331",
    "sg:city":"Z\u00fcrich",
    "sg:orig_category":"Instandhaltung U Reparatur von Automobilen",
    "sg:phone":"+41 79 438 43 56",
    "sg:postcode":"8047",
    "sg:province":"Z\u00fcrich",
    "wof:name":"Garage Wertli",
    "wof:placetype":"venue"
},
  "geometry": {"coordinates":[8.4844245911,47.375793457],"type":"Point"}
}