{
  "type": "Feature",
  "properties": {
    "addr:full":"Kriesbachstrasse 30 D\u00fcbendorf Z\u00fcrich 8600",
    "addr:housenumber":"30",
    "addr:postcode":"8600",
    "addr:street":"Kriesbachstrasse;Zuerich",
    "iso:country":"CH",
    "sg:address":"Kriesbachstrasse 30",
    "sg:city":"D\u00fcbendorf",
    "sg:orig_category":"Datenverarbeitungsdienste Vervielf\u00e4ltigung von bespielten Datentr\u00e4gern",
    "sg:postcode":"8600",
    "sg:province":"Z\u00fcrich",
    "wof:name":"Lsi Media S\u00e0rl",
    "wof:placetype":"venue"
},
  "geometry": {"coordinates":[6.141425,46.183311],"type":"Point"}
}