{
  "type": "Feature",
  "properties": {
    "iso:country":"CH",
    "sg:address":"M\u00fchletalstrasse 88",
    "sg:city":"Zofingen",
    "sg:orig_category":"Blumen U Zierpflanzenbau Detailhandel mit Blumen U Pflanzen",
    "sg:phone":"+41 62 751 12 12",
    "sg:postcode":"4800",
    "sg:province":"Aargau",
    "wof:name":"Peter Br\u00fchlmann Gartenpflege",
    "wof:placetype":"venue"
},
  "geometry": {"coordinates":[7.962918,47.298302],"type":"Point"}
}