{
  "type": "Feature",
  "properties": {
    "iso:country":"CH",
    "sg:address":"Matzingerstrasse 10",
    "sg:city":"Lommis",
    "sg:orig_category":"Sonstiger Fachdetailhandel mit Nahrungsmitteln, Getr\u00e4nken U Tabak in Verkaufsr\u00e4umen Verarbeitung von",
    "sg:postcode":"9506",
    "sg:province":"Thurgau",
    "wof:name":"A.h.s. Kurmann Gmbh",
    "wof:placetype":"venue"
},
  "geometry": {"coordinates":[8.9919557571,47.5184593201],"type":"Point"}
}