{
  "type": "Feature",
  "properties": {
    "iso:country":"CH",
    "sg:address":"Haltingerstrasse 76",
    "sg:city":"Basel",
    "sg:orig_category":"Non-Classified Establishments",
    "sg:postcode":"4057",
    "sg:province":"Basel-Stadt",
    "wof:name":"Ilem Sa",
    "wof:placetype":"venue"
},
  "geometry": {"coordinates":[6.1333489418,46.1848564148],"type":"Point"}
}