{
  "type": "Feature",
  "properties": {
    "iso:country":"CH",
    "sg:address":"Zaunplatz 20",
    "sg:city":"Glarus",
    "sg:orig_category":"Unclassifiable Establishments",
    "sg:postcode":"8750",
    "sg:province":"Glarus",
    "wof:name":"Globec Ag",
    "wof:placetype":"venue"
},
  "geometry": {"coordinates":[9.0675792694,47.0382919312],"type":"Point"}
}