{
  "type": "Feature",
  "properties": {
    "iso:country":"CH",
    "sg:address":"Eglise Catholiquerue De 100",
    "sg:city":"Montreux",
    "sg:orig_category":"Fachdetailhandel in Verkaufsr\u00e4umen",
    "sg:phone":"+41 21 961 10 19",
    "sg:postcode":"1820",
    "sg:province":"Vaud",
    "wof:name":"Development Snowboard Tuning S\u00e0rl",
    "wof:placetype":"venue"
},
  "geometry": {"coordinates":[6.9126029015,46.4309196472],"type":"Point"}
}