{
  "type": "Feature",
  "properties": {
    "addr:full":"Haldenstrasse 22 Niederg\u00f6sgen Solothurn 5013",
    "addr:housenumber":"22",
    "addr:postcode":"5013",
    "addr:street":"Haldenstrasse;Solothurn",
    "iso:country":"CH",
    "sg:address":"Haldenstrasse 22",
    "sg:city":"Niederg\u00f6sgen",
    "sg:orig_category":"Allgemeiner Hoch U Tiefbau Allgemeiner Hochbau",
    "sg:phone":"+41 62 849 16 86",
    "sg:postcode":"5013",
    "sg:province":"Solothurn",
    "wof:name":"Gisi Kurt Ag",
    "wof:placetype":"venue"
},
  "geometry": {"coordinates":[7.977894,47.371006],"type":"Point"}
}