{
  "type": "Feature",
  "properties": {
    "iso:country":"CH",
    "sg:address":"Oltnerstrasse 95 4663 Aarburg. Postfach 110",
    "sg:city":"Olten",
    "sg:orig_category":"Einzelhandel mit Automobilteilen U Zubeh\u00f6r Handel mit Automobilteilen U Zubeh\u00f6r",
    "sg:phone":"+41 31 751 38 39",
    "sg:postcode":"4601",
    "sg:province":"Solothurn",
    "wof:name":"Alpinauto Gmbh",
    "wof:placetype":"venue"
},
  "geometry": {"coordinates":[7.1084527969,46.9252319336],"type":"Point"}
}