{
  "type": "Feature",
  "properties": {
    "iso:country":"CH",
    "sg:address":"Grenzstrasse 22",
    "sg:city":"Winterthur",
    "sg:orig_category":"Sportvereine Ballsport Tennis",
    "sg:phone":"+41 52 202 62 79",
    "sg:postcode":"8406",
    "sg:province":"Z\u00fcrich",
    "wof:name":"Tc Geiselweid",
    "wof:placetype":"venue"
},
  "geometry": {"coordinates":[8.7117996216,47.4914932251],"type":"Point"}
}