{
  "type": "Feature",
  "properties": {
    "iso:country":"CH",
    "sg:address":"Parf\u00e4ra 105",
    "sg:city":"Seewis",
    "sg:classifiers":[
        {
            "category":"Banks & Credit Unions",
            "subcategory":"Bank",
            "type":"Services"
        }
    ],
    "sg:phone":"+41 81 325 11 43",
    "sg:postcode":"7212",
    "sg:province":"Graubunden",
    "wof:name":"Raiffeisenbank Seewis",
    "wof:placetype":"venue"
},
  "geometry": {"coordinates":[9.637289,46.989769],"type":"Point"}
}