{
  "type": "Feature",
  "properties": {
    "iso:country":"CH",
    "sg:address":"Zollikerstrasse 144",
    "sg:city":"Z\u00fcrich",
    "sg:classifiers":[
        {
            "category":"Professional",
            "subcategory":"Employment Agencies",
            "type":"Services"
        }
    ],
    "sg:phone":"+41 13839585",
    "sg:postcode":"8008",
    "sg:province":"Z\u00fcrich",
    "sg:tags":[
        "personal",
        "u",
        "stellenvermittlung"
    ],
    "wof:name":"Human Resources Support Gmbh",
    "wof:placetype":"venue"
},
  "geometry": {"coordinates":[8.5608243942,47.3559379578],"type":"Point"}
}