{
  "type": "Feature",
  "properties": {
    "iso:country":"CH",
    "sg:address":"Winterthurerstrasse 689",
    "sg:city":"Z\u00fcrich",
    "sg:orig_category":"Fachdetailhandel in Verkaufsr\u00e4umen",
    "sg:postcode":"8051",
    "sg:province":"Z\u00fcrich",
    "wof:name":"Blumenatelier Calla, G. Loosli",
    "wof:placetype":"venue"
},
  "geometry": {"coordinates":[8.5830831528,47.406463623],"type":"Point"}
}