{
  "type": "Feature",
  "properties": {
    "iso:country":"CH",
    "sg:address":"Birkenweg 128",
    "sg:city":"Belp",
    "sg:classifiers":[
        {
            "category":"Personal",
            "subcategory":"Piercing",
            "type":"Services"
        }
    ],
    "sg:phone":"+41 31 819 08 34",
    "sg:postcode":"3123",
    "sg:province":"Bern",
    "sg:tags":[
        "tattoo"
    ],
    "wof:name":"Margrit R\u00fctter Bio-tatoo",
    "wof:placetype":"venue"
},
  "geometry": {"coordinates":[7.4973158836,46.8836021423],"type":"Point"}
}