{
  "type": "Feature",
  "properties": {
    "iso:country":"CH",
    "sg:address":"Gotthelfweg 5",
    "sg:city":"Derendingen",
    "sg:orig_category":"Fachdetailhandel in Verkaufsr\u00e4umen",
    "sg:phone":"+41 32 681 00 53",
    "sg:postcode":"4552",
    "sg:province":"Solothurn",
    "wof:name":"Golf Spirit Ag",
    "wof:placetype":"venue"
},
  "geometry": {"coordinates":[7.5854320526,47.1941566467],"type":"Point"}
}