{
  "type": "Feature",
  "properties": {
    "iso:country":"CH",
    "sg:address":"Baarerstrasse 22",
    "sg:city":"Zug",
    "sg:orig_category":"Drogerien Parf\u00fcmerien U sonstiger Detailhandel mit kosmetischen Artikeln U K\u00f6rperpflegemitteln",
    "sg:phone":"+41 41 711 08 63",
    "sg:postcode":"6300",
    "sg:province":"Zug",
    "wof:name":"Hl Drogerie Ag Metalli-parfumerie",
    "wof:placetype":"venue"
},
  "geometry": {"coordinates":[8.516957283,47.1733703613],"type":"Point"}
}