{
  "type": "Feature",
  "properties": {
    "iso:country":"CH",
    "sg:address":"Im D\u00f6rfli 68",
    "sg:city":"Dietikon",
    "sg:orig_category":"Sonstiger Grosshandel",
    "sg:phone":"+41 17413130",
    "sg:postcode":"8953",
    "sg:province":"Z\u00fcrich",
    "wof:name":"Europack Gmbh",
    "wof:placetype":"venue"
},
  "geometry": {"coordinates":[8.4059829712,47.4000587463],"type":"Point"}
}