{
  "type": "Feature",
  "properties": {
    "iso:country":"CH",
    "sg:address":"Strandbadweg 5",
    "sg:city":"Uster",
    "sg:orig_category":"Gartenbau Reinigungsgewerbe",
    "sg:phone":"+41 21 691 30 00",
    "sg:postcode":"8610",
    "sg:province":"Z\u00fcrich",
    "wof:name":"Genevaz S\u00e0rl",
    "wof:placetype":"venue"
},
  "geometry": {"coordinates":[6.5454487801,46.5134506226],"type":"Point"}
}