{
  "type": "Feature",
  "properties": {
    "addr:full":"Alte Zurzacherstrasse 36 Tegerfelden Aargau 5306",
    "addr:housenumber":"36",
    "addr:postcode":"5306",
    "addr:street":"Alte Zurzacherstrasse",
    "iso:country":"CH",
    "sg:address":"Alte Zurzacherstrasse 36",
    "sg:city":"Tegerfelden",
    "sg:orig_category":"Autolackierereien Autospenglereien",
    "sg:phone":"+41 56 245 30 81",
    "sg:postcode":"5306",
    "sg:province":"Aargau",
    "wof:name":"Werner Hauenstein Carrosserie-malerarbeiten",
    "wof:placetype":"venue"
},
  "geometry": {"coordinates":[8.287007,47.565449],"type":"Point"}
}