{
  "type": "Feature",
  "properties": {
    "iso:country":"CH",
    "sg:address":"En D\u00e9zaley",
    "sg:city":"Rivaz",
    "sg:orig_category":"Grosshandel mit Getr\u00e4nken",
    "sg:phone":"+41 62 838 00 30",
    "sg:postcode":"1812",
    "wof:name":"Devini\u00e8re Sa",
    "wof:placetype":"venue"
},
  "geometry": {"coordinates":[6.7786898613,46.4763259888],"type":"Point"}
}