{
  "type": "Feature",
  "properties": {
    "iso:country":"CH",
    "sg:address":"Tr\u00fcllergasse 6",
    "sg:city":"Feuerthalen",
    "sg:orig_category":"Gemeindeverwaltungen",
    "sg:phone":"+41 52 647 47 47",
    "sg:postcode":"8245",
    "sg:province":"Z\u00fcrich",
    "wof:name":"Gemeindeverwaltung Feuerthalen",
    "wof:placetype":"venue"
},
  "geometry": {"coordinates":[8.643696785,47.6934318542],"type":"Point"}
}