{
  "type": "Feature",
  "properties": {
    "iso:country":"CH",
    "sg:address":"General Guisan-strasse 8",
    "sg:city":"Basel",
    "sg:orig_category":"Fachdetailhandel in Verkaufsr\u00e4umen Sportschulen Wassersport",
    "sg:phone":"+41 61 302 21 52",
    "sg:postcode":"4054",
    "sg:province":"Basel-Stadt",
    "wof:name":"Kanuschule Wiemken Michael",
    "wof:placetype":"venue"
},
  "geometry": {"coordinates":[7.570772171,47.5524520874],"type":"Point"}
}