{
  "type": "Feature",
  "properties": {
    "iso:country":"CH",
    "sg:address":"St\u00e4dtchenstrasse 64",
    "sg:city":"Sargans",
    "sg:orig_category":"Arbeitnehmerverb\u00e4nde",
    "sg:phone":"+41 81 723 39 22",
    "sg:postcode":"7320",
    "sg:province":"St. Gallen",
    "wof:name":"Bsgl Pr\u00e4s.frau Heidi Hanselmann",
    "wof:placetype":"venue"
},
  "geometry": {"coordinates":[9.43522,47.050697],"type":"Point"}
}