{
  "type": "Feature",
  "properties": {
    "iso:country":"CH",
    "sg:address":"Hauptstrasse 44",
    "sg:city":"Tann",
    "sg:orig_category":"Unclassifiable Establishments",
    "sg:phone":"+41 1615683",
    "sg:postcode":"8632",
    "sg:province":"Z\u00fcrich",
    "wof:name":"Sport Show Promotion Sonny Sch\u00f6nb\u00e4chler Ag",
    "wof:placetype":"venue"
},
  "geometry": {"coordinates":[8.4389619827,47.2739562988],"type":"Point"}
}