{
  "type": "Feature",
  "properties": {
    "iso:country":"CH",
    "sg:address":"Pr\u00e9alpes Route Des 1",
    "sg:city":"Villars-sur-gl\u00e2ne",
    "sg:orig_category":"RESTAURANTS: TEA-ROOMS",
    "sg:postcode":"1752",
    "sg:province":"Fribourg",
    "wof:name":"Repond Bernard",
    "wof:placetype":"venue"
},
  "geometry": {"coordinates":[7.130428791,46.7955818176],"type":"Point"}
}