{
  "type": "Feature",
  "properties": {
    "iso:country":"CH",
    "sg:address":"Rigistrasse 171b",
    "sg:city":"Baar",
    "sg:orig_category":"Non-Classified Establishments",
    "sg:postcode":"6340",
    "sg:province":"Zug",
    "wof:name":"Ab Treuhand Und Revisions Gmbh",
    "wof:placetype":"venue"
},
  "geometry": {"coordinates":[8.5305099487,47.1919517517],"type":"Point"}
}