{
  "type": "Feature",
  "properties": {
    "iso:country":"CH",
    "sg:address":"Ostb\u00fchlstrasse 15",
    "sg:city":"Z\u00fcrich",
    "sg:orig_category":"Architekturb\u00fcros",
    "sg:phone":"+41 14800585",
    "sg:postcode":"8038",
    "sg:province":"Z\u00fcrich",
    "wof:name":"Ernst Amb\u00fchler Architekturb\u00fcro",
    "wof:placetype":"venue"
},
  "geometry": {"coordinates":[8.535167,47.333057],"type":"Point"}
}