{
  "type": "Feature",
  "properties": {
    "iso:country":"CH",
    "sg:address":"Winterthurerstrasse 83",
    "sg:city":"Z\u00fcrich",
    "sg:orig_category":"Reinigungsgewerbe",
    "sg:phone":"+41 13636296",
    "sg:postcode":"8006",
    "sg:province":"Z\u00fcrich",
    "wof:name":"Kolar Hauswartungen + Reinigung",
    "wof:placetype":"venue"
},
  "geometry": {"coordinates":[8.5451726913,47.3907699585],"type":"Point"}
}