{
  "type": "Feature",
  "properties": {
    "iso:country":"CH",
    "sg:address":"G\u00e9n\u00e9ral-guisan Avenue 34 1180 Rolle Case Postale 99",
    "sg:city":"Rolle",
    "sg:orig_category":"Allgemeiner Hoch U Tiefbau",
    "sg:phone":"+41 21 825 34 34",
    "sg:postcode":"1180",
    "sg:province":"Vaud",
    "wof:name":"K\u00fcnzli Fr\u00e8res Sa Rolle",
    "wof:placetype":"venue"
},
  "geometry": {"coordinates":[6.332338,46.458881],"type":"Point"}
}