{
  "type": "Feature",
  "properties": {
    "iso:country":"CH",
    "sg:address":"Hauptgasse 53",
    "sg:city":"Solothurn",
    "sg:orig_category":"Sonstige Institutionen des Sozialwesens ohne Beherbergung",
    "sg:phone":"+41 32 627 84 00",
    "sg:postcode":"4500",
    "sg:province":"Solothurn",
    "wof:name":"Kinder-& Jugendpsych.dienst Des Kantons Solothurn",
    "wof:placetype":"venue"
},
  "geometry": {"coordinates":[7.5377941132,47.2078514099],"type":"Point"}
}