{
  "type": "Feature",
  "properties": {
    "iso:country":"CH",
    "sg:address":"Hasenm\u00e4tteli",
    "sg:city":"Habschwanden",
    "sg:orig_category":"Organisationen des Gesundheitswesen",
    "sg:phone":"+41 41 480 36 94",
    "sg:postcode":"6166",
    "sg:province":"Luzern",
    "wof:name":"Samariterverein Romoos",
    "wof:placetype":"venue"
},
  "geometry": {"coordinates":[8.049946785,46.9792175293],"type":"Point"}
}