{
  "type": "Feature",
  "properties": {
    "iso:country":"CH",
    "sg:address":"Lindenstrasse 457",
    "sg:city":"Aristau",
    "sg:orig_category":"Elektrizit\u00e4tsversorgung",
    "sg:phone":"+41 61 811 68 54",
    "sg:postcode":"5628",
    "sg:province":"Aargau",
    "wof:name":"Elektra Augst",
    "wof:placetype":"venue"
},
  "geometry": {"coordinates":[7.7212600708,47.5278816223],"type":"Point"}
}