{
  "type": "Feature",
  "properties": {
    "iso:country":"CH",
    "sg:address":"Paradiesweg 6",
    "sg:city":"Niederlenz",
    "sg:orig_category":"Detailhandel mit Blumen U Pflanzen",
    "sg:phone":"+41 62 891 38 87",
    "sg:postcode":"5702",
    "sg:province":"Aargau",
    "wof:name":"Hanspeter Frey Blumengesch\u00e4ft",
    "wof:placetype":"venue"
},
  "geometry": {"coordinates":[8.173373,47.396404],"type":"Point"}
}