{
  "type": "Feature",
  "properties": {
    "addr:full":"Rebstockhalde 56 Luzern Luzern 6006",
    "addr:housenumber":"56",
    "addr:postcode":"6006",
    "addr:street":"Rebstockhalde",
    "iso:country":"CH",
    "sg:address":"Rebstockhalde 56",
    "sg:city":"Luzern",
    "sg:orig_category":"Architekturb\u00fcros",
    "sg:phone":"+41 56 664 21 06",
    "sg:postcode":"6006",
    "sg:province":"Luzern",
    "wof:name":"Peter F. Oswald Architekturb\u00fcro",
    "wof:placetype":"venue"
},
  "geometry": {"coordinates":[8.317482,47.282578],"type":"Point"}
}