{
  "type": "Feature",
  "properties": {
    "iso:country":"CH",
    "sg:address":"Aegetswilerstrasse 2",
    "sg:city":"Wila",
    "sg:orig_category":"Handelsvermittlung U Grosshandel S\u00e4ge, Hobel U Holzimpr\u00e4gnierwerke",
    "sg:phone":"+41 52 385 12 08",
    "sg:postcode":"8492",
    "sg:province":"Z\u00fcrich",
    "wof:name":"Bachmann's A. S\u00f6hne Ag",
    "wof:placetype":"venue"
},
  "geometry": {"coordinates":[8.8525514603,47.4179954529],"type":"Point"}
}