{
  "type": "Feature",
  "properties": {
    "iso:country":"CH",
    "sg:address":"Prada Via 1",
    "sg:city":"Breganzona",
    "sg:orig_category":"Vermietung U Verpachtung von eigenen Immobilien",
    "sg:phone":"+41 91 966 34 58",
    "sg:postcode":"6932",
    "sg:province":"Ticino",
    "wof:name":"Kilma Sa",
    "wof:placetype":"venue"
},
  "geometry": {"coordinates":[8.9339752197,46.0051383972],"type":"Point"}
}