{
  "type": "Feature",
  "properties": {
    "iso:country":"CH",
    "sg:address":"Zentweg 17",
    "sg:city":"Ostermundigen",
    "sg:orig_category":"Herstellung von Akkumulatoren U Batterien",
    "sg:phone":"+41 71 277 17 70",
    "sg:postcode":"3072",
    "sg:province":"Bern",
    "wof:name":"Avb Batterie Ag Vertrieb Autobatterien Filiale St. Gallen",
    "wof:placetype":"venue"
},
  "geometry": {"coordinates":[9.3354253769,47.4110794067],"type":"Point"}
}