{
  "type": "Feature",
  "properties": {
    "iso:country":"CH",
    "sg:address":"Wannengut 6",
    "sg:city":"M\u00fchlethal",
    "sg:orig_category":"Datenbanken Softwareentwicklung U beratung",
    "sg:phone":"+41 62 751 67 10",
    "sg:postcode":"4812",
    "sg:province":"Aargau",
    "wof:name":"Universal Frame Gmbh",
    "wof:placetype":"venue"
},
  "geometry": {"coordinates":[7.970844,47.30262],"type":"Point"}
}