{
  "type": "Feature",
  "properties": {
    "addr:full":"1543 Grandcour Vaud 1543",
    "addr:housenumber":"1543",
    "addr:postcode":"grandcour;1543",
    "iso:country":"CH",
    "sg:address":"1543",
    "sg:city":"Grandcour",
    "sg:classifiers":[
        {
            "category":"Education",
            "subcategory":"Library",
            "type":"Public Place"
        }
    ],
    "sg:postcode":"1543",
    "sg:province":"Vaud",
    "sg:tags":[
        "u",
        "bibliotheken",
        "archive"
    ],
    "wof:name":"Biblioth\u00e8que Populaire",
    "wof:placetype":"venue"
},
  "geometry": {"coordinates":[6.928615,46.871796],"type":"Point"}
}