{
  "type": "Feature",
  "properties": {
    "iso:country":"CH",
    "sg:address":"Ueberlandstrasse 215",
    "sg:city":"Z\u00fcrich",
    "sg:classifiers":[
        {
            "category":"Restaurant",
            "type":"Food & Drink"
        }
    ],
    "sg:phone":"+41 13214477",
    "sg:postcode":"8050",
    "sg:province":"Z\u00fcrich",
    "wof:name":"Restaurant Auhof",
    "wof:placetype":"venue"
},
  "geometry": {"coordinates":[8.5584602356,47.4053115845],"type":"Point"}
}