{
  "type": "Feature",
  "properties": {
    "iso:country":"CH",
    "sg:address":"Vordere Hauptgasse 40",
    "sg:city":"Zofingen",
    "sg:orig_category":"Fachdetailhandel mit pharmazeutischen Produkten",
    "sg:postcode":"4800",
    "sg:province":"Aargau",
    "wof:name":"Unterstadt-apotheke Bucher Matthias H.",
    "wof:placetype":"venue"
},
  "geometry": {"coordinates":[7.9443597794,47.289352417],"type":"Point"}
}