{
  "type": "Feature",
  "properties": {
    "iso:country":"CH",
    "sg:address":"Hauptstrasse 129 8272 Ermatingen. Postfach",
    "sg:city":"Ermatingen",
    "sg:orig_category":"Detailhandel mit Waren verschiedener Art, Hauptrichtung Nahrungsmittel Grosshandel mit Nahrungsmitte",
    "sg:phone":"+41 71 664 30 70",
    "sg:postcode":"8272",
    "sg:province":"Thurgau",
    "wof:name":"Mock Hans",
    "wof:placetype":"venue"
},
  "geometry": {"coordinates":[9.0842790604,47.6690444946],"type":"Point"}
}