{
  "type": "Feature",
  "properties": {
    "iso:country":"CH",
    "sg:address":"Zelgmatt 11",
    "sg:city":"Z\u00fcrich",
    "sg:orig_category":"Sonstige Aktivit\u00e4ten der nicht-\u00e4rztlichen Medizinalberufe",
    "sg:phone":"+41 13716260",
    "sg:postcode":"8046",
    "sg:province":"Z\u00fcrich",
    "wof:name":"Therese F\u00f6rtsch Kinesiologie",
    "wof:placetype":"venue"
},
  "geometry": {"coordinates":[8.5275192261,47.4122962952],"type":"Point"}
}