{
  "type": "Feature",
  "properties": {
    "iso:country":"CH",
    "sg:address":"Rathausstrasse 40/42",
    "sg:city":"Liestal",
    "sg:orig_category":"Non-Classified Establishments",
    "sg:postcode":"4410",
    "sg:province":"Basel-Landschaft",
    "wof:name":"Swissprotect Brighina",
    "wof:placetype":"venue"
},
  "geometry": {"coordinates":[7.3736028671,47.1847572327],"type":"Point"}
}