{
  "type": "Feature",
  "properties": {
    "iso:country":"CH",
    "sg:address":"Weissensteinstrasse 29a",
    "sg:city":"Bern",
    "sg:orig_category":"Detailhandel mit Bekleidung Detailhandel mit Waren verschiedener Art, Hauptrichtung Nahrungsmittel",
    "sg:phone":"+41 34 461 13 13",
    "sg:postcode":"3008",
    "sg:province":"Bern",
    "wof:name":"Christian Brand Lebensmittel & Textilien",
    "wof:placetype":"venue"
},
  "geometry": {"coordinates":[10.169,50.57214],"type":"Point"}
}