{
  "type": "Feature",
  "properties": {
    "iso:country":"CH",
    "sg:address":"Furth 464",
    "sg:city":"Walkringen",
    "sg:orig_category":"Herstellung von Konstruktionsteilen, Fertigbauteilen U Ausbauelementen aus Holz Innenausbau",
    "sg:phone":"+41 31 701 12 65",
    "sg:postcode":"3512",
    "sg:province":"Bern",
    "wof:name":"Aeschlimann Innenausbau Ag Innenausbau, Schreinerei- U. Ladenbauunternehmung Usw.",
    "wof:placetype":"venue"
},
  "geometry": {"coordinates":[7.620718956,46.9572105408],"type":"Point"}
}