{
  "type": "Feature",
  "properties": {
    "iso:country":"CH",
    "sg:address":"5706",
    "sg:city":"Boniswil",
    "sg:orig_category":"Gemeindeverwaltungen",
    "sg:phone":"+41 62 775 01 55",
    "sg:postcode":"5706",
    "sg:province":"Aargau",
    "wof:name":"Gemeindeverwaltung Boniswil",
    "wof:placetype":"venue"
},
  "geometry": {"coordinates":[8.1888504028,47.3125495911],"type":"Point"}
}