{
  "type": "Feature",
  "properties": {
    "iso:country":"CH",
    "sg:address":"Rue De La Cit\u00e9 6bis",
    "sg:city":"Gen\u00e8ve",
    "sg:orig_category":"Detailhandel mit elektrischen Haushaltsger\u00e4ten Grosshandel mit Textilien",
    "sg:phone":"+41 22 312 45 00",
    "sg:postcode":"1204",
    "sg:province":"Gen\u00e8ve",
    "wof:name":"L'aiguille Enchant\u00e9e, Revel Eliane",
    "wof:placetype":"venue"
},
  "geometry": {"coordinates":[6.1435461044,46.2035751343],"type":"Point"}
}