{
  "type": "Feature",
  "properties": {
    "iso:country":"CH",
    "sg:address":"Dorfstrasse",
    "sg:city":"Ausserberg",
    "sg:orig_category":"Sportvereine Alpinismus",
    "sg:phone":"+41 31 839 70 76",
    "sg:postcode":"3938",
    "sg:province":"Valais",
    "wof:name":"Sac Sekt.emmental Grossh\u00f6chs.",
    "wof:placetype":"venue"
},
  "geometry": {"coordinates":[7.5771589279,46.9268188477],"type":"Point"}
}