{
  "type": "Feature",
  "properties": {
    "iso:country":"CH",
    "sg:address":"Voa Principala 38",
    "sg:city":"Lenzerheide/lai",
    "sg:orig_category":"Detailhandel mit Brot, Back U S\u00fcsswaren",
    "sg:phone":"+41 81 384 12 36",
    "sg:postcode":"7078",
    "sg:province":"Graubunden",
    "wof:name":"Walter Hafner B\u00e4ckerei-konditorei",
    "wof:placetype":"venue"
},
  "geometry": {"coordinates":[9.557924,46.72578],"type":"Point"}
}