{
  "type": "Feature",
  "properties": {
    "iso:country":"CH",
    "sg:address":"7000",
    "sg:city":"Chur",
    "sg:orig_category":"Berufliche Weiterbildung, Erwachsenenbildung",
    "sg:phone":"+41 22 320 93 11",
    "sg:postcode":"7000",
    "sg:province":"Graubunden",
    "wof:name":"Institut D'etudes Sociales",
    "wof:placetype":"venue"
},
  "geometry": {"coordinates":[6.144887,46.193283],"type":"Point"}
}