{
  "type": "Feature",
  "properties": {
    "iso:country":"CH",
    "sg:address":"Wartburgstrasse 10",
    "sg:city":"Aarburg",
    "sg:orig_category":"Sportvereine Turnen Vereine Damen",
    "sg:phone":"+41 62 791 15 32",
    "sg:postcode":"4663",
    "sg:province":"Aargau",
    "wof:name":"Damenturnverein Aarburg",
    "wof:placetype":"venue"
},
  "geometry": {"coordinates":[7.9062638283,47.3358459473],"type":"Point"}
}