{
  "type": "Feature",
  "properties": {
    "iso:country":"CH",
    "sg:address":"Von May-strasse 43 3600 Thun. Postfach",
    "sg:city":"Thun",
    "sg:orig_category":"Herstellung von sonstigen Kunststoffwaren",
    "sg:phone":"+41 33 336 27 49",
    "sg:postcode":"3604",
    "sg:province":"Bern",
    "wof:name":"Binggeli Otto",
    "wof:placetype":"venue"
},
  "geometry": {"coordinates":[7.6146922112,46.7323265076],"type":"Point"}
}