{
  "type": "Feature",
  "properties": {
    "iso:country":"CH",
    "sg:address":"Hauptstrasse 76",
    "sg:city":"Guntershausen",
    "sg:orig_category":"Interessenvertretungen U sonstige Vereinigungen",
    "sg:phone":"+41 71 385 49 61",
    "sg:postcode":"8357",
    "sg:province":"Thurgau",
    "wof:name":"Ostschw.kath.turn-& Sportverb.",
    "wof:placetype":"venue"
},
  "geometry": {"coordinates":[8.921998024,47.4725341797],"type":"Point"}
}