{
  "type": "Feature",
  "properties": {
    "iso:country":"CH",
    "sg:address":"Zeughausstrasse",
    "sg:city":"Mels",
    "sg:orig_category":"Herstellung von Baubedarfsartikeln aus Kunststoff Herstellung von Konstruktionsteilen, Fertigbauteil",
    "sg:postcode":"8887",
    "sg:province":"St. Gallen",
    "wof:name":"Sulser David",
    "wof:placetype":"venue"
},
  "geometry": {"coordinates":[9.4077148438,47.0566482544],"type":"Point"}
}