{
  "type": "Feature",
  "properties": {
    "iso:country":"CH",
    "sg:address":"Oberfeld 3",
    "sg:city":"Amlikon",
    "sg:orig_category":"Sanit\u00e4r U Heizungsinstallation Sanit\u00e4r, Heizungs U L\u00fcftungsinstallation",
    "sg:phone":"+41 32 968 83 88",
    "sg:postcode":"8514",
    "sg:province":"Thurgau",
    "wof:name":"Greub Gabriel Sa",
    "wof:placetype":"venue"
},
  "geometry": {"coordinates":[6.8362708092,47.1129798889],"type":"Point"}
}