{
  "type": "Feature",
  "properties": {
    "iso:country":"CH",
    "sg:address":"Moserstrasse 27 8200 Schaffhausen. Postfach 3135",
    "sg:city":"Schaffhausen",
    "sg:orig_category":"Vermietung U Verpachtung von eigenen Immobilien Verwaltung von Immobilien",
    "sg:postcode":"8201",
    "sg:province":"Schaffhausen",
    "wof:name":"Igs Immobilien-treuhand Ag",
    "wof:placetype":"venue"
},
  "geometry": {"coordinates":[8.6385622025,47.6952552795],"type":"Point"}
}