{
  "type": "Feature",
  "properties": {
    "iso:country":"CH",
    "sg:address":"Rue Des Mazots 4 3960 Sierre Case Postale 87",
    "sg:city":"Sierre",
    "sg:orig_category":"Bauspenglerei Dachdeckerei",
    "sg:phone":"+41 79 221 13 57",
    "sg:postcode":"3960",
    "sg:province":"Valais",
    "wof:name":"Charles-albert Vuistiner Ferblanterie & Couverture",
    "wof:placetype":"venue"
},
  "geometry": {"coordinates":[7.524099,46.292755],"type":"Point"}
}