{
  "type": "Feature",
  "properties": {
    "iso:country":"CH",
    "sg:address":"Landvogt Waserstrasse 93",
    "sg:city":"Winterthur",
    "sg:orig_category":"Interessenvertretungen",
    "sg:phone":"+41 52 233 21 67",
    "sg:postcode":"8400",
    "sg:province":"Z\u00fcrich",
    "wof:name":"Stiftung Altersheim St. Urban In Winterthur-seen",
    "wof:placetype":"venue"
},
  "geometry": {"coordinates":[8.7704801559,47.4851837158],"type":"Point"}
}