{
  "type": "Feature",
  "properties": {
    "iso:country":"CH",
    "sg:address":"Curtat Rue Louis- 13 1005 Lausanne. Postfach",
    "sg:city":"Lausanne",
    "sg:orig_category":"Sonstiger Fachdetailhandel mit Nahrungsmitteln, Getr\u00e4nken U Tabak in Verkaufsr\u00e4umen",
    "sg:postcode":"1003",
    "sg:province":"Vaud",
    "wof:name":"Bovay A. Epicerie Et Commerce De Primeurs.",
    "wof:placetype":"venue"
},
  "geometry": {"coordinates":[6.6367788315,46.523601532],"type":"Point"}
}