{
  "type": "Feature",
  "properties": {
    "iso:country":"CH",
    "sg:address":"Dorfstrasse 30",
    "sg:city":"Bettenhausen",
    "sg:orig_category":"Herstellung von Metallkonstruktionen Mechanik",
    "sg:phone":"+41 33 822 67 51",
    "sg:postcode":"3366",
    "sg:province":"Bern",
    "wof:name":"Albert Zwahlen",
    "wof:placetype":"venue"
},
  "geometry": {"coordinates":[7.8638529778,46.6805267334],"type":"Point"}
}