{
  "type": "Feature",
  "properties": {
    "iso:country":"CH",
    "sg:address":"Spalenberg 16",
    "sg:city":"Basel",
    "sg:orig_category":"RESTAURANTS: TEA-ROOMS",
    "sg:phone":"+41 61 261 32 05",
    "sg:postcode":"4051",
    "sg:province":"Basel-Stadt",
    "wof:name":"Caf\u00e9 Spalenberg Waldmeier B. Alkoholfreies Restaurant",
    "wof:placetype":"venue"
},
  "geometry": {"coordinates":[7.5862088203,47.557258606],"type":"Point"}
}