{
  "type": "Feature",
  "properties": {
    "iso:country":"CH",
    "sg:address":"Route De Ch\u00e2tillon 1",
    "sg:city":"Courrendlin",
    "sg:orig_category":"Non-Classified Establishments",
    "sg:postcode":"2830",
    "sg:province":"Jura",
    "wof:name":"Claire-lise Amstutz Coiffure Top",
    "wof:placetype":"venue"
},
  "geometry": {"coordinates":[7.3731307983,47.3387985229],"type":"Point"}
}