{
  "type": "Feature",
  "properties": {
    "iso:country":"CH",
    "sg:address":"Aegeristrasse 9",
    "sg:city":"Zug",
    "sg:orig_category":"Architekturb\u00fcros",
    "sg:phone":"+41 31 331 90 50",
    "sg:postcode":"6300",
    "sg:province":"Zug",
    "wof:name":"Delta Architektur Ag",
    "wof:placetype":"venue"
},
  "geometry": {"coordinates":[7.451685,46.957935],"type":"Point"}
}