{
  "type": "Feature",
  "properties": {
    "iso:country":"CH",
    "sg:address":"Joinville Chemin De 28 1216 Cointrin. Postfach",
    "sg:city":"Cointrin",
    "sg:orig_category":"Unclassifiable Establishments",
    "sg:postcode":"1216",
    "sg:province":"Gen\u00e8ve",
    "wof:name":"Elizabeth Arden (switzerland) Holding S\u00e0rl",
    "wof:placetype":"venue"
},
  "geometry": {"coordinates":[6.1066179276,46.2241020203],"type":"Point"}
}