{
  "type": "Feature",
  "properties": {
    "iso:country":"CH",
    "sg:address":"Hebelstrasse 81 4056 Basel. Postfach",
    "sg:city":"Basel",
    "sg:orig_category":"Herstellung von sonstigen chemischen Erzeugnissen",
    "sg:phone":"+41 61 261 02 00",
    "sg:postcode":"4012",
    "sg:province":"Basel-Stadt",
    "wof:name":"Paroba-chemie Basel, Paul Rohrbach",
    "wof:placetype":"venue"
},
  "geometry": {"coordinates":[7.578413,47.562248],"type":"Point"}
}