{
  "type": "Feature",
  "properties": {
    "iso:country":"CH",
    "sg:address":"Bruelmatt 233",
    "sg:city":"Gurmels",
    "sg:orig_category":"Bauschreinerei Zimmerei, Dachdeckerei, Bauspenglerei U Abdichtung",
    "sg:phone":"+41 41 870 18 04",
    "sg:postcode":"3212",
    "sg:province":"Fribourg",
    "wof:name":"Otto Schuler Holzbau Gmbh",
    "wof:placetype":"venue"
},
  "geometry": {"coordinates":[8.659954,46.874527],"type":"Point"}
}