{
  "type": "Feature",
  "properties": {
    "iso:country":"CH",
    "sg:address":"H\u00f6henweg 8",
    "sg:city":"Riniken",
    "sg:orig_category":"Architekturb\u00fcros",
    "sg:phone":"+41 91 943 39 72",
    "sg:postcode":"5223",
    "sg:province":"Aargau",
    "wof:name":"Emilia & Giuseppe Silvestro Studio D'architettura",
    "wof:placetype":"venue"
},
  "geometry": {"coordinates":[8.98483,46.077789],"type":"Point"}
}