{
  "type": "Feature",
  "properties": {
    "iso:country":"CH",
    "sg:address":"Dangwanger Str. 11",
    "sg:city":"Bonau",
    "sg:classifiers":[
        {
            "category":"Farming",
            "subcategory":"Farm",
            "type":"Manufacturing & Wholesale Goods"
        }
    ],
    "sg:phone":"+41 71 657 13 46",
    "sg:postcode":"8554",
    "sg:province":"Thurgau",
    "sg:tags":[
        "horticulture",
        "agriculture",
        "livestock"
    ],
    "wof:name":"Meisterwerk Ag",
    "wof:placetype":"venue"
},
  "geometry": {"coordinates":[9.0433,47.583374],"type":"Point"}
}