{
  "type": "Feature",
  "properties": {
    "addr:full":"Klosbachstrasse 67 8032 Z\u00fcrich Zust 32",
    "addr:housenumber":"67;32",
    "addr:postcode":"8032",
    "addr:street":"Klosbachstrasse;Zust",
    "iso:country":"CH",
    "sg:address":"Klosbachstrasse 67 8032 Z\u00fcrich",
    "sg:city":"Zust",
    "sg:orig_category":"Pensionskassen",
    "sg:phone":"+41 71 744 11 41",
    "sg:postcode":"32",
    "wof:name":"Personalf\u00fcrsorgestiftung Der Schiess Ag",
    "wof:placetype":"venue"
},
  "geometry": {"coordinates":[9.639805,47.451874],"type":"Point"}
}