{
  "type": "Feature",
  "properties": {
    "iso:country":"CH",
    "sg:address":"Rue Du Temple 20 2024 St-aubin-sauges Case Postale 156",
    "sg:city":"St-aubin-sauges",
    "sg:classifiers":[
        {
            "category":"Restaurant",
            "type":"Food & Drink"
        }
    ],
    "sg:phone":"+41 32 835 15 50",
    "sg:postcode":"2024",
    "sg:province":"Neuch\u00e2tel",
    "wof:name":"Caf\u00e9-restaurant Le Carillon",
    "wof:placetype":"venue"
},
  "geometry": {"coordinates":[6.7735772133,46.8954772949],"type":"Point"}
}