{
  "type": "Feature",
  "properties": {
    "iso:country":"CH",
    "sg:address":"Burgstrasse",
    "sg:city":"Pfaffnau",
    "sg:orig_category":"Haltung von Gefl\u00fcgel",
    "sg:phone":"+41 62 754 13 09",
    "sg:postcode":"6264",
    "sg:province":"Luzern",
    "wof:name":"Peter Blum Gefl\u00fcgelfarm",
    "wof:placetype":"venue"
},
  "geometry": {"coordinates":[7.8968000412,47.2243385315],"type":"Point"}
}