{
  "type": "Feature",
  "properties": {
    "iso:country":"CH",
    "sg:address":"Ruopigenring 77",
    "sg:city":"Reussb\u00fchl",
    "sg:orig_category":"Architekturb\u00fcros Werbeberatung",
    "sg:phone":"+41 41 252 02 20",
    "sg:postcode":"6015",
    "sg:province":"Luzern",
    "wof:name":"Trend Enterprises Gmbh",
    "wof:placetype":"venue"
},
  "geometry": {"coordinates":[8.271826,47.062618],"type":"Point"}
}