{
  "type": "Feature",
  "properties": {
    "iso:country":"CH",
    "sg:address":"Riedhubel 3636 Forst. Postfach",
    "sg:city":"Forst",
    "sg:orig_category":"Unclassifiable Establishments",
    "sg:phone":"+41 71 277 35 01",
    "sg:postcode":"3636",
    "sg:province":"Bern",
    "wof:name":"H\u00e4nni Ernst, Inh. R. H\u00e4nni",
    "wof:placetype":"venue"
},
  "geometry": {"coordinates":[9.3413953781,47.4064750671],"type":"Point"}
}