{
  "type": "Feature",
  "properties": {
    "iso:country":"CH",
    "sg:address":"Birkenweg 61 3013 Bern. Postfach",
    "sg:city":"Bern",
    "sg:orig_category":"Unclassifiable Establishments",
    "sg:phone":"+41 31 332 00 56",
    "sg:postcode":"3005",
    "sg:province":"Bern",
    "wof:name":"Magam Ag Beteiligungen Usw",
    "wof:placetype":"venue"
},
  "geometry": {"coordinates":[7.447010994,46.9592094421],"type":"Point"}
}