{
  "type": "Feature",
  "properties": {
    "iso:country":"CH",
    "sg:address":"Belsitostrasse 17",
    "sg:city":"Z\u00fcrich",
    "sg:orig_category":"Verwaltung von Immobilien",
    "sg:phone":"+41 12524609",
    "sg:postcode":"8044",
    "sg:province":"Z\u00fcrich",
    "wof:name":"Sewe Ag",
    "wof:placetype":"venue"
},
  "geometry": {"coordinates":[8.5630159378,47.3742332458],"type":"Point"}
}