{
  "type": "Feature",
  "properties": {
    "iso:country":"CH",
    "sg:address":"Croix-blanche Rte De La 44",
    "sg:city":"Epalinges",
    "sg:orig_category":"Non-Classified Establishments",
    "sg:postcode":"1066",
    "sg:province":"Vaud",
    "wof:name":"Institut Lydia, D'accault-acco Alla",
    "wof:placetype":"venue"
},
  "geometry": {"coordinates":[5.1808700562,45.8973388672],"type":"Point"}
}