{
  "type": "Feature",
  "properties": {
    "iso:country":"CH",
    "sg:address":"Maupas Rue Du 23",
    "sg:city":"Lausanne",
    "sg:orig_category":"Herstellung von sonstigen Metallwaren",
    "sg:phone":"+41 21 625 84 90",
    "sg:postcode":"1004",
    "sg:province":"Vaud",
    "wof:name":"Artm\u00e9tal, Turina Angelo",
    "wof:placetype":"venue"
},
  "geometry": {"coordinates":[6.625453949,46.5249519348],"type":"Point"}
}