{
  "type": "Feature",
  "properties": {
    "iso:country":"CH",
    "sg:address":"Obere M\u00fchlebodenstrasse 11",
    "sg:city":"Tr\u00fcllikon",
    "sg:orig_category":"Grosshandel mit sonstigen Halbwaren Herstellung von sonstigen Maschinen f\u00fcr unspezifische Verwendung",
    "sg:phone":"+41 52 319 20 81",
    "sg:postcode":"8466",
    "sg:province":"Z\u00fcrich",
    "wof:name":"Prontopack Ag",
    "wof:placetype":"venue"
},
  "geometry": {"coordinates":[8.6867847443,47.6388130188],"type":"Point"}
}