{
  "type": "Feature",
  "properties": {
    "iso:country":"CH",
    "sg:address":"La Rapille",
    "sg:city":"Villars-ste-croix",
    "sg:orig_category":"Detailhandel mit Metallwaren, Anstrichmitteln, Glaswaren, Bau U Heimwerkerbedarf Installation von He",
    "sg:phone":"+41 55 210 62 14",
    "sg:postcode":"1029",
    "sg:province":"Vaud",
    "wof:name":"Eicher Ag Rapperswil",
    "wof:placetype":"venue"
},
  "geometry": {"coordinates":[8.82035923,47.2268562317],"type":"Point"}
}