{
  "type": "Feature",
  "properties": {
    "iso:country":"CH",
    "sg:address":"Hauptstrasse 29",
    "sg:city":"Flaach",
    "sg:classifiers":[
        {
            "category":"Restaurant",
            "type":"Food & Drink"
        }
    ],
    "sg:phone":"+41 52 318 13 13",
    "sg:postcode":"8416",
    "sg:province":"Z\u00fcrich",
    "wof:name":"Restaurant Sternen",
    "wof:placetype":"venue"
},
  "geometry": {"coordinates":[8.602101326,47.5740318298],"type":"Point"}
}