{
  "type": "Feature",
  "properties": {
    "iso:country":"CH",
    "sg:address":"Coll\u00e8gegasse 27",
    "sg:city":"Biel/bienne",
    "sg:orig_category":"Sportvereine Ballsport Tischtennis",
    "sg:phone":"+41 32 322 75 59",
    "sg:postcode":"2502",
    "sg:province":"Bern",
    "wof:name":"Ttc Port",
    "wof:placetype":"venue"
},
  "geometry": {"coordinates":[7.2476830482,47.1399803162],"type":"Point"}
}