{
  "type": "Feature",
  "properties": {
    "iso:country":"CH",
    "sg:address":"Industriestrasse 20",
    "sg:city":"Solothurn",
    "sg:orig_category":"Unclassifiable Establishments",
    "sg:phone":"+41 32 622 16 81",
    "sg:postcode":"4500",
    "sg:province":"Solothurn",
    "wof:name":"S & B Sch\u00e4rer + Bertoli Ladenbau Gmbh Ladenbaueinrichtungen; Planung, Errichtung, Handel Usw",
    "wof:placetype":"venue"
},
  "geometry": {"coordinates":[7.5233340263,47.2135848999],"type":"Point"}
}