{
  "type": "Feature",
  "properties": {
    "addr:full":"H\u00f6rnlistrasse 16 8700 K\u00fcsnacht Zh. Postfach Z\u00fcrich Z\u00fcrich 8001",
    "addr:housenumber":"16",
    "addr:postcode":"8700;8001",
    "addr:street":"Hoernlistrasse",
    "iso:country":"CH",
    "sg:address":"H\u00f6rnlistrasse 16 8700 K\u00fcsnacht Zh. Postfach",
    "sg:city":"Z\u00fcrich",
    "sg:orig_category":"Allgemeiner Hoch U Tiefbau",
    "sg:postcode":"8001",
    "sg:province":"Z\u00fcrich",
    "wof:name":"Renova-bau, D\u00e4twyler R. Ch. Altbausanierungen",
    "wof:placetype":"venue"
},
  "geometry": {"coordinates":[8.58763,47.309963],"type":"Point"}
}