{
  "type": "Feature",
  "properties": {
    "iso:country":"CH",
    "sg:address":"Steinstrasse 33",
    "sg:city":"Z\u00fcrich",
    "sg:orig_category":"Verm\u00f6gensverwaltung",
    "sg:phone":"+41 22 707 43 88",
    "sg:postcode":"8003",
    "sg:province":"Z\u00fcrich",
    "wof:name":"Gedefi Asset Management Sa G\u00e9rance De Fortunes",
    "wof:placetype":"venue"
},
  "geometry": {"coordinates":[6.1607480049,46.2027397156],"type":"Point"}
}