{
  "type": "Feature",
  "properties": {
    "iso:country":"CH",
    "sg:address":"Rasenweg 8. 5737 Menziken. Postfach",
    "sg:city":"Menziken",
    "sg:orig_category":"Unclassifiable Establishments",
    "sg:phone":"+41 62 771 23 65",
    "sg:postcode":"5737",
    "sg:province":"Aargau",
    "wof:name":"Ren\u00e9 Soland",
    "wof:placetype":"venue"
},
  "geometry": {"coordinates":[8.1934890747,47.2479438782],"type":"Point"}
}