{
  "type": "Feature",
  "properties": {
    "iso:country":"CH",
    "sg:address":"Kirchstrasse 58",
    "sg:city":"Grenchen",
    "sg:orig_category":"Autogaragen",
    "sg:phone":"+41 79 333 04 74",
    "sg:postcode":"2540",
    "sg:province":"Solothurn",
    "wof:name":"J.-a. Rochat Garage Central",
    "wof:placetype":"venue"
},
  "geometry": {"coordinates":[6.25995,46.615349],"type":"Point"}
}