{
  "type": "Feature",
  "properties": {
    "iso:country":"CH",
    "sg:address":"Hauptstrasse 10",
    "sg:city":"Arbon",
    "sg:orig_category":"Bauingenieurb\u00fcros allgemein",
    "sg:phone":"+41 22 342 41 13",
    "sg:postcode":"9320",
    "sg:province":"Thurgau",
    "wof:name":"Francis Lachenal Bureau D'ing\u00e9nieur",
    "wof:placetype":"venue"
},
  "geometry": {"coordinates":[6.136112,46.183914],"type":"Point"}
}