{
  "type": "Feature",
  "properties": {
    "iso:country":"CH",
    "sg:address":"Spielh\u00f6lzli 1 3800 Unterseen. Postfach 245",
    "sg:city":"Interlaken",
    "sg:orig_category":"Versicherungen Generalagenturen",
    "sg:phone":"+41 71 228 42 42",
    "sg:postcode":"3800",
    "sg:province":"Bern",
    "wof:name":"Die Mobiliar Versicherungen & Vorsorge",
    "wof:placetype":"venue"
},
  "geometry": {"coordinates":[9.3710641861,47.4227561951],"type":"Point"}
}