{
  "type": "Feature",
  "properties": {
    "iso:country":"CH",
    "sg:address":"Landoltstrasse 28 3007 Bern. Postfach",
    "sg:city":"Bern",
    "sg:orig_category":"Architektur U Ingenieurb\u00fcros",
    "sg:phone":"+41 31 333 20 01",
    "sg:postcode":"3005",
    "sg:province":"Bern",
    "wof:name":"Bittner Hubert, Ing. Htl Bauingenieur- U Architekturarbeiten Usw",
    "wof:placetype":"venue"
},
  "geometry": {"coordinates":[7.439771,46.936249],"type":"Point"}
}