{
  "type": "Feature",
  "properties": {
    "iso:country":"CH",
    "sg:address":"Sonnenweg 16",
    "sg:city":"Rupperswil",
    "sg:orig_category":"Aktivit\u00e4ten der Krankenschwestern U Hebammen, Hauspflege Organisationen des Gesundheitswesen",
    "sg:phone":"+41 62 897 12 21",
    "sg:postcode":"5102",
    "sg:province":"Aargau",
    "wof:name":"Spitex Gesundheits-& Krankenpflege",
    "wof:placetype":"venue"
},
  "geometry": {"coordinates":[8.123242,47.400833],"type":"Point"}
}