{
  "type": "Feature",
  "properties": {
    "iso:country":"CH",
    "sg:address":"Avenue Collonges 2",
    "sg:city":"Lausanne",
    "sg:orig_category":"Informatikschulen",
    "sg:phone":"+41 21 316 55 55",
    "sg:postcode":"1004",
    "sg:province":"Vaud",
    "wof:name":"Ecole Sup\u00e9rieure Vaudoise D'infomatique De Gestion",
    "wof:placetype":"venue"
},
  "geometry": {"coordinates":[6.6219182014,46.5275497437],"type":"Point"}
}