{
  "type": "Feature",
  "properties": {
    "iso:country":"CH",
    "sg:address":"Place De Cornavin 2",
    "sg:city":"Gen\u00e8ve",
    "sg:orig_category":"Arztpraxen",
    "sg:phone":"+41 32 913 97 05",
    "sg:postcode":"1201",
    "sg:province":"Gen\u00e8ve",
    "wof:name":"Dr M\u00e9d. Vincent Froidevaux M\u00e9decin Sp\u00e9cialiste Fmh",
    "wof:placetype":"venue"
},
  "geometry": {"coordinates":[6.82978,47.102913],"type":"Point"}
}