{
  "type": "Feature",
  "properties": {
    "iso:country":"CH",
    "sg:address":"Seestrasse 25",
    "sg:city":"Spiez",
    "sg:orig_category":"Malerei",
    "sg:phone":"+41 33 654 48 65",
    "sg:postcode":"3700",
    "sg:province":"Bern",
    "wof:name":"Gebr.fritz & Ernst Heim Malergesch\u00e4ft",
    "wof:placetype":"venue"
},
  "geometry": {"coordinates":[7.6806550026,46.6898956299],"type":"Point"}
}