{
  "type": "Feature",
  "properties": {
    "iso:country":"CH",
    "sg:address":"Grand-rue 15",
    "sg:city":"Lutry",
    "sg:orig_category":"Detailhandel mit Waren verschiedener Art, Hauptrichtung Nahrungsmittel Grosshandel mit Nahrungsmitte",
    "sg:phone":"+41 21 792 11 30",
    "sg:postcode":"1095",
    "sg:province":"Vaud",
    "wof:name":"Epicerie Au Petit Gourmet, Gerbex Ren\u00e9",
    "wof:placetype":"venue"
},
  "geometry": {"coordinates":[6.6847929955,46.5025177002],"type":"Point"}
}