{
  "type": "Feature",
  "properties": {
    "iso:country":"CH",
    "sg:address":"Haldenstrasse 79",
    "sg:city":"Watt",
    "sg:orig_category":"Gartenbau",
    "sg:phone":"+41 71 277 59 59",
    "sg:postcode":"8105",
    "sg:province":"Z\u00fcrich",
    "wof:name":"Frick Gartenbau & Gartenpflege",
    "wof:placetype":"venue"
},
  "geometry": {"coordinates":[9.3593931198,47.4120178223],"type":"Point"}
}