{
  "type": "Feature",
  "properties": {
    "iso:country":"CH",
    "sg:address":"Via Franco Zorzi 38",
    "sg:city":"Bellinzona",
    "sg:orig_category":"Detailhandel mit Bekleidung Detailhandel mit Damenbekleidung",
    "sg:phone":"+41 81 833 33 15",
    "sg:postcode":"6500",
    "sg:province":"Ticino",
    "wof:name":"Cashmere House Lamm Ag",
    "wof:placetype":"venue"
},
  "geometry": {"coordinates":[9.839244,46.498177],"type":"Point"}
}