{
  "type": "Feature",
  "properties": {
    "iso:country":"CH",
    "sg:address":"Kirchstrasse 6",
    "sg:city":"Horn",
    "sg:orig_category":"Non-Classified Establishments",
    "sg:postcode":"9326",
    "sg:province":"Thurgau",
    "wof:name":"Frey Technology Trade Gmbh",
    "wof:placetype":"venue"
},
  "geometry": {"coordinates":[9.4644460678,47.4936332703],"type":"Point"}
}