{
  "type": "Feature",
  "properties": {
    "iso:country":"CH",
    "sg:address":"Badstrasse 31 5400 Baden. Postfach",
    "sg:city":"Baden",
    "sg:orig_category":"G\u00fcterbef\u00f6rderung im Strassenverkehr",
    "sg:phone":"+41 62 886 37 70",
    "sg:postcode":"5401",
    "sg:province":"Aargau",
    "wof:name":"Eurobus Knecht Ag",
    "wof:placetype":"venue"
},
  "geometry": {"coordinates":[8.1773414612,47.3880844116],"type":"Point"}
}