{
  "type": "Feature",
  "properties": {
    "iso:country":"CH",
    "sg:address":"R\u00e4sch 15",
    "sg:city":"D\u00fcdingen",
    "sg:orig_category":"Sportvereine Sch\u00fctzen Pistolen-& Gewehr",
    "sg:phone":"+41 26 493 33 31",
    "sg:postcode":"3186",
    "sg:province":"Fribourg",
    "wof:name":"Pistolenschiessver.d\u00fcdingen",
    "wof:placetype":"venue"
},
  "geometry": {"coordinates":[7.152985096,46.8367462158],"type":"Point"}
}