{
  "type": "Feature",
  "properties": {
    "iso:country":"CH",
    "sg:address":"Fischrain 64 3063 Ittigen. Postfach",
    "sg:city":"Ittigen",
    "sg:orig_category":"Fotografische Ateliers Sonstige Hilfsdienste des Kultur U Unterhaltungswesens",
    "sg:phone":"+41 31 921 10 21",
    "sg:postcode":"3063",
    "sg:province":"Bern",
    "wof:name":"Erwin H\u00e4sler Artistenagentur & Fotoatelier",
    "wof:placetype":"venue"
},
  "geometry": {"coordinates":[7.4742159843,46.9779853821],"type":"Point"}
}