{
  "type": "Feature",
  "properties": {
    "iso:country":"CH",
    "sg:address":"Hafenstrasse 17",
    "sg:city":"Kreuzlingen",
    "sg:orig_category":"Baugewerbe Dachdeckerei",
    "sg:phone":"+41 71 672 76 12",
    "sg:postcode":"8280",
    "sg:province":"Thurgau",
    "wof:name":"Walker Dach + Wand",
    "wof:placetype":"venue"
},
  "geometry": {"coordinates":[9.180016,47.650131],"type":"Point"}
}