{
  "type": "Feature",
  "properties": {
    "iso:country":"CH",
    "sg:address":"Rotachstrasse 8",
    "sg:city":"St.gallen",
    "sg:orig_category":"Vereine Gesang Vereine Gesang and Jodler",
    "sg:phone":"+41 52 653 15 16",
    "sg:postcode":"9000",
    "sg:province":"St. Gallen",
    "wof:name":"Stadtjodler Schaffhausen",
    "wof:placetype":"venue"
},
  "geometry": {"coordinates":[8.6090106964,47.7934341431],"type":"Point"}
}