{
  "type": "Feature",
  "properties": {
    "iso:country":"CH",
    "sg:address":"Alte Landstrasse 112",
    "sg:city":"Zollikon",
    "sg:orig_category":"Arztpraxen",
    "sg:phone":"+41 12696969",
    "sg:postcode":"8702",
    "sg:province":"Z\u00fcrich",
    "wof:name":"Dr.med.helen Fontana Klaiber Spezial\u00e4rztin Fmh",
    "wof:placetype":"venue"
},
  "geometry": {"coordinates":[8.576728,47.335979],"type":"Point"}
}