{
  "type": "Feature",
  "properties": {
    "addr:full":"Musperfeldstrasse 15 Berikon Aargau 8965",
    "addr:housenumber":"15",
    "addr:postcode":"8965",
    "addr:street":"Musperfeldstrasse",
    "iso:country":"CH",
    "sg:address":"Musperfeldstrasse 15",
    "sg:city":"Berikon",
    "sg:orig_category":"Autospenglereien",
    "sg:phone":"+41 17130611",
    "sg:postcode":"8965",
    "sg:province":"Aargau",
    "wof:name":"Reto Muggler Autospenglerei",
    "wof:placetype":"venue"
},
  "geometry": {"coordinates":[8.544576,47.286961],"type":"Point"}
}