{
  "type": "Feature",
  "properties": {
    "iso:country":"CH",
    "sg:address":"Hauptstrasse 21",
    "sg:city":"Unterseen",
    "sg:classifiers":[
        {
            "category":"Retail",
            "subcategory":"Driving School",
            "type":"Services"
        }
    ],
    "sg:phone":"+41 33 827 55 55",
    "sg:postcode":"3800",
    "sg:province":"Bern",
    "sg:tags":[
        "simulator"
    ],
    "wof:name":"Ruag Electronics",
    "wof:placetype":"venue"
},
  "geometry": {"coordinates":[7.8486690521,46.6856002808],"type":"Point"}
}