{
  "type": "Feature",
  "properties": {
    "addr:full":"Oberlandstrasse 61 Spiez Bern 3700",
    "addr:housenumber":"61",
    "addr:postcode":"3700",
    "addr:street":"Oberlandstrasse",
    "iso:country":"CH",
    "sg:address":"Oberlandstrasse 61",
    "sg:city":"Spiez",
    "sg:orig_category":"Arztpraxen",
    "sg:phone":"+41 33 654 60 66",
    "sg:postcode":"3700",
    "sg:province":"Bern",
    "wof:name":"Dr.med.ruth Barth Spezial\u00e4rztin",
    "wof:placetype":"venue"
},
  "geometry": {"coordinates":[7.68339,46.685493],"type":"Point"}
}