{
  "type": "Feature",
  "properties": {
    "iso:country":"CH",
    "sg:address":"Weiherstrasse 3",
    "sg:city":"Effretikon",
    "sg:orig_category":"Bauspenglerei Sanit\u00e4rinstallation U Spenglerei",
    "sg:phone":"+41 52 343 86 81",
    "sg:postcode":"8307",
    "sg:province":"Z\u00fcrich",
    "wof:name":"Bruno Artho Bauspenglerei",
    "wof:placetype":"venue"
},
  "geometry": {"coordinates":[8.68991,47.434032],"type":"Point"}
}