{
  "type": "Feature",
  "properties": {
    "iso:country":"CH",
    "sg:address":"1663",
    "sg:city":"Gruy\u00e8res",
    "sg:orig_category":"Erdbewegungsarbeiten",
    "sg:phone":"+41 33 951 17 30",
    "sg:postcode":"1663",
    "sg:province":"Fribourg",
    "wof:name":"Christian Abegglen Trax-& Baggerbetrieb",
    "wof:placetype":"venue"
},
  "geometry": {"coordinates":[8.0554924011,46.7590522766],"type":"Point"}
}