{
  "type": "Feature",
  "properties": {
    "iso:country":"CH",
    "sg:address":"Eichenweg 1",
    "sg:city":"Eich",
    "sg:classifiers":[
        {
            "category":"Banks & Credit Unions",
            "subcategory":"Bureau De Change",
            "type":"Services"
        }
    ],
    "sg:phone":"+41 41 460 44 33",
    "sg:postcode":"6205",
    "sg:province":"Luzern",
    "sg:tags":[
        "search",
        "executive"
    ],
    "wof:name":"Marc Daniel",
    "wof:placetype":"venue"
},
  "geometry": {"coordinates":[8.1675710678,47.1600646973],"type":"Point"}
}