{
  "type": "Feature",
  "properties": {
    "iso:country":"CH",
    "sg:address":"Lindenstrasse 52",
    "sg:city":"Widnau",
    "sg:orig_category":"Zahnarztpraxen",
    "sg:phone":"+41 71 722 24 28",
    "sg:postcode":"9443",
    "sg:province":"St. Gallen",
    "wof:name":"Dr. Med. Dent. Beat Wider Zahnarzt",
    "wof:placetype":"venue"
},
  "geometry": {"coordinates":[9.636423111,47.4048461914],"type":"Point"}
}