{
  "type": "Feature",
  "properties": {
    "iso:country":"CH",
    "sg:address":"4702 Oensingen. Postfach",
    "sg:city":"Oensingen",
    "sg:orig_category":"Polizei",
    "sg:phone":"+41 62 388 47 47",
    "sg:postcode":"4702",
    "sg:province":"Solothurn",
    "wof:name":"Autobahnpolizei",
    "wof:placetype":"venue"
},
  "geometry": {"coordinates":[7.7168869972,47.2903594971],"type":"Point"}
}