{
  "type": "Feature",
  "properties": {
    "iso:country":"CH",
    "sg:address":"Stotzhalten 3",
    "sg:city":"Grindelwald",
    "sg:orig_category":"Jugendherbergen U H\u00fctten",
    "sg:phone":"+41 33 853 31 41",
    "sg:postcode":"3818",
    "sg:province":"Bern",
    "wof:name":"Lehmann's Herberge",
    "wof:placetype":"venue"
},
  "geometry": {"coordinates":[8.0380897522,46.6233215332],"type":"Point"}
}