{
  "type": "Feature",
  "properties": {
    "iso:country":"CH",
    "sg:address":"General Wille-strasse 8 8002 Z\u00fcrich. Postfach",
    "sg:city":"Z\u00fcrich",
    "sg:orig_category":"Non-Classified Establishments",
    "sg:postcode":"8002",
    "sg:province":"Z\u00fcrich",
    "wof:name":"Aktiengesellschaft Zum Kleeblatt",
    "wof:placetype":"venue"
},
  "geometry": {"coordinates":[8.2074050903,47.4845466614],"type":"Point"}
}