{
  "type": "Feature",
  "properties": {
    "iso:country":"CH",
    "sg:address":"1938 Champex Case Postale 8",
    "sg:city":"Champex",
    "sg:orig_category":"HOTELS: MIT RESTAURANT Kongress- and Tagungshotels mit Restaurant",
    "sg:phone":"+41 27 783 11 03",
    "sg:postcode":"1938",
    "sg:province":"Valais",
    "wof:name":"H\u00f4tel Gd-combin",
    "wof:placetype":"venue"
},
  "geometry": {"coordinates":[7.1182599068,46.0285491943],"type":"Point"}
}