{
  "type": "Feature",
  "properties": {
    "iso:country":"CH",
    "sg:address":"Lucomagno Via",
    "sg:city":"Biasca",
    "sg:orig_category":"Herstellung von K\u00fcchenm\u00f6beln",
    "sg:phone":"+41 91 862 22 35",
    "sg:postcode":"6710",
    "sg:province":"Ticino",
    "wof:name":"3v Mobili & Cucine Sagl",
    "wof:placetype":"venue"
},
  "geometry": {"coordinates":[8.9673404694,46.3699150085],"type":"Point"}
}