{
  "type": "Feature",
  "properties": {
    "iso:country":"CH",
    "sg:address":"Evole Rue De L' 41",
    "sg:city":"Neuch\u00e2tel",
    "sg:orig_category":"Interessenvertretungen",
    "sg:postcode":"2000",
    "sg:province":"Neuch\u00e2tel",
    "wof:name":"Fondation En Faveur De L'entraide Entre Agriculteurs D'ormont-dessus",
    "wof:placetype":"venue"
},
  "geometry": {"coordinates":[7.1587119102,46.3500404358],"type":"Point"}
}