{
  "type": "Feature",
  "properties": {
    "iso:country":"CH",
    "sg:address":"Industriestrasse 99 3902 Glis. Postfach",
    "sg:city":"Glis",
    "sg:orig_category":"Non-Classified Establishments",
    "sg:phone":"+41 19505612",
    "sg:postcode":"3902",
    "sg:province":"Valais",
    "wof:name":"Tauchsport Jung",
    "wof:placetype":"venue"
},
  "geometry": {"coordinates":[8.7830820084,47.3680534363],"type":"Point"}
}