{
  "type": "Feature",
  "properties": {
    "iso:country":"CH",
    "sg:address":"Z.i.moulin Du Choc",
    "sg:city":"Romanel-sur-morges",
    "sg:classifiers":[
        {
            "category":"Communications",
            "subcategory":"Film & Video Production",
            "type":"Services"
        }
    ],
    "sg:phone":"+41 21 869 90 30",
    "sg:postcode":"1122",
    "sg:province":"Vaud",
    "sg:tags":[
        "videofilmherstellung",
        "u"
    ],
    "wof:name":"Grossenbacher Broadcast Studio Postproduction",
    "wof:placetype":"venue"
},
  "geometry": {"coordinates":[6.5107097626,46.5554008484],"type":"Point"}
}