{
  "type": "Feature",
  "properties": {
    "iso:country":"CH",
    "sg:address":"N\u00fcschelerstr. 24",
    "sg:city":"Z\u00fcrich",
    "sg:classifiers":[
        {
            "category":"Home & Garden",
            "subcategory":"Furniture",
            "type":"Retail Goods"
        }
    ],
    "sg:phone":"+41 4112131363",
    "sg:postcode":"8021",
    "sg:province":"Z\u00fcrich",
    "sg:tags":[
        "household",
        "wood"
    ],
    "wof:name":"Muralto Wohnungseinrichtungen Ag",
    "wof:placetype":"venue"
},
  "geometry": {"coordinates":[8.536450386,47.3721313477],"type":"Point"}
}