{
  "type": "Feature",
  "properties": {
    "addr:full":"Hauptstrasse 66 Murgenthal Aargau 4853",
    "addr:housenumber":"66",
    "addr:postcode":"4853",
    "addr:street":"Hauptstrasse",
    "iso:country":"CH",
    "sg:address":"Hauptstrasse 66",
    "sg:city":"Murgenthal",
    "sg:orig_category":"Chemische Reinigung",
    "sg:phone":"+41 62 926 27 27",
    "sg:postcode":"4853",
    "sg:province":"Aargau",
    "wof:name":"Helene Keller Textilreinig.drynette-center",
    "wof:placetype":"venue"
},
  "geometry": {"coordinates":[7.834604,47.266754],"type":"Point"}
}