{
  "type": "Feature",
  "properties": {
    "iso:country":"CH",
    "sg:address":"Pr\u00e9-loup 1868 Collombey Case Postale 220",
    "sg:city":"Collombey",
    "sg:orig_category":"Herstellung von Metallkonstruktionen Mechanik",
    "sg:phone":"+41 79 439 47 25",
    "sg:postcode":"1868",
    "sg:province":"Valais",
    "wof:name":"Actm Atelier De Construction Et De Traitement De M\u00e9taux Puippe Serge",
    "wof:placetype":"venue"
},
  "geometry": {"coordinates":[6.9587330818,46.2688674927],"type":"Point"}
}