{
  "type": "Feature",
  "properties": {
    "iso:country":"CH",
    "sg:address":"Im Grund 10",
    "sg:city":"D\u00fcbendorf",
    "sg:orig_category":"Non-Classified Establishments",
    "sg:phone":"+41 18203061",
    "sg:postcode":"8600",
    "sg:province":"Z\u00fcrich",
    "wof:name":"Sotelca Ag",
    "wof:placetype":"venue"
},
  "geometry": {"coordinates":[8.6183891296,47.4014053345],"type":"Point"}
}