{
  "type": "Feature",
  "properties": {
    "iso:country":"CH",
    "sg:address":"Auenrainstrasse 44",
    "sg:city":"Winterthur",
    "sg:classifiers":[
        {
            "category":"Home & Garden",
            "subcategory":"Carpets & Floor Coverings",
            "type":"Retail Goods"
        }
    ],
    "sg:phone":"+41 52 202 23 88",
    "sg:postcode":"8406",
    "sg:province":"Z\u00fcrich",
    "sg:tags":[
        "carpeting"
    ],
    "wof:name":"Willi Leutwiler",
    "wof:placetype":"venue"
},
  "geometry": {"coordinates":[8.701445,47.489464],"type":"Point"}
}