{
  "type": "Feature",
  "properties": {
    "iso:country":"CH",
    "sg:address":"P\u00e9quignat Rue Pierre- 17 2900 Porrentruy. Postfach",
    "sg:city":"Pruntrut",
    "sg:orig_category":"Fachdetailhandel in Verkaufsr\u00e4umen",
    "sg:phone":"+41 32 466 81 58",
    "sg:postcode":"2900",
    "sg:province":"Jura",
    "wof:name":"Bike Import Roma Catherine Magasins De Cycles",
    "wof:placetype":"venue"
},
  "geometry": {"coordinates":[7.0734400749,47.4179153442],"type":"Point"}
}