{
  "type": "Feature",
  "properties": {
    "iso:country":"CH",
    "sg:address":"Terrassenstrasse 22",
    "sg:city":"D\u00f6ttingen",
    "sg:orig_category":"Architektur U Ingenieurb\u00fcros",
    "sg:phone":"+41 56 245 41 24",
    "sg:postcode":"5312",
    "sg:province":"Aargau",
    "wof:name":"Paul Bugmann Ingenieurb\u00fcro",
    "wof:placetype":"venue"
},
  "geometry": {"coordinates":[8.261154,47.57563],"type":"Point"}
}