{
  "type": "Feature",
  "properties": {
    "addr:full":"Bachlettenstrasse 62 Basel Basel-Stadt 4054",
    "addr:housenumber":"62",
    "addr:postcode":"4054",
    "addr:street":"Bachlettenstrasse",
    "iso:country":"CH",
    "sg:address":"Bachlettenstrasse 62",
    "sg:city":"Basel",
    "sg:orig_category":"Betrieb von Taxis",
    "sg:phone":"+41 79 413 98 48",
    "sg:postcode":"4054",
    "sg:province":"Basel-Stadt",
    "wof:name":"Carlos Ufenast Taxi",
    "wof:placetype":"venue"
},
  "geometry": {"coordinates":[7.578269,47.548447],"type":"Point"}
}