{
  "type": "Feature",
  "properties": {
    "iso:country":"CH",
    "sg:address":"Unterlowmatt 10",
    "sg:city":"Udligenswil",
    "sg:orig_category":"Saunas, Solarien, Fitnesszentren U \u00e4hnliches",
    "sg:postcode":"6044",
    "sg:province":"Luzern",
    "wof:name":"Sun Business Gmbh",
    "wof:placetype":"venue"
},
  "geometry": {"coordinates":[8.4065942764,47.0906715393],"type":"Point"}
}