{
  "type": "Feature",
  "properties": {
    "iso:country":"CH",
    "sg:address":"B\u00fcndtenweg 6",
    "sg:city":"Nusshof",
    "sg:orig_category":"Unternehmensberatung",
    "sg:phone":"+41 61 971 66 11",
    "sg:postcode":"4453",
    "sg:province":"Basel-Landschaft",
    "wof:name":"Hph Consulting Ag",
    "wof:placetype":"venue"
},
  "geometry": {"coordinates":[7.8070611954,47.4925003052],"type":"Point"}
}