{
  "type": "Feature",
  "properties": {
    "iso:country":"CH",
    "sg:address":"Zone Industriel Le Tr\u00e9si 6c",
    "sg:city":"Pr\u00e9verenges",
    "sg:orig_category":"Leichtmetallgiesserei Pulvermetallurgie Schmieden, Pressen, Stanzen U Profilwalzen von Metallen",
    "sg:phone":"+41 21 811 50 80",
    "sg:postcode":"1028",
    "sg:province":"Vaud",
    "wof:name":"Dana Europe Sa",
    "wof:placetype":"venue"
},
  "geometry": {"coordinates":[6.5308151245,46.5229797363],"type":"Point"}
}