{
  "type": "Feature",
  "properties": {
    "iso:country":"CH",
    "sg:address":"Gotthardstrasse 53",
    "sg:city":"Arth",
    "sg:orig_category":"Sanit\u00e4r, Heizungs U L\u00fcftungsinstallation",
    "sg:postcode":"6415",
    "sg:province":"Schwyz",
    "wof:name":"Sanibad Schmidlin Ag",
    "wof:placetype":"venue"
},
  "geometry": {"coordinates":[8.5260705948,47.0612258911],"type":"Point"}
}