{
  "type": "Feature",
  "properties": {
    "iso:country":"CH",
    "sg:address":"Paoli Via Dei 13 6648 Minusio Casella Postale 1369",
    "sg:city":"Minusio",
    "sg:orig_category":"Zimmerei, Dachdeckerei, Bauspenglerei U Abdichtung",
    "sg:phone":"+41 91 743 24 45",
    "sg:postcode":"6648",
    "sg:province":"Ticino",
    "wof:name":"Gamboni-aschwanden Sa",
    "wof:placetype":"venue"
},
  "geometry": {"coordinates":[8.8130598068,46.1764831543],"type":"Point"}
}