{
  "type": "Feature",
  "properties": {
    "iso:country":"CH",
    "sg:address":"Madrusen",
    "sg:city":"Gams",
    "sg:orig_category":"Herstellung von sonstigen landwirtschaftlichen Maschinen",
    "sg:phone":"+41 81 771 14 18",
    "sg:postcode":"9473",
    "sg:province":"St. Gallen",
    "wof:name":"St\u00f6ckli M. Ag, Landmaschinen",
    "wof:placetype":"venue"
},
  "geometry": {"coordinates":[9.4491996765,47.2038612366],"type":"Point"}
}