{
  "type": "Feature",
  "properties": {
    "iso:country":"CH",
    "sg:address":"Seestrasse 5",
    "sg:city":"Unter\u00e4geri",
    "sg:orig_category":"Grosshandel mit Erzen U Metallen",
    "sg:postcode":"6314",
    "sg:province":"Zug",
    "wof:name":"Iten Josef, Eisenhandlung",
    "wof:placetype":"venue"
},
  "geometry": {"coordinates":[8.5852327347,47.1375427246],"type":"Point"}
}