{
  "type": "Feature",
  "properties": {
    "iso:country":"CH",
    "sg:address":"Hofgraben 11 7000 Chur. Postfach",
    "sg:city":"Chur",
    "sg:orig_category":"Veterin\u00e4r\u00e4mter",
    "sg:phone":"+41 81 257 24 15",
    "sg:postcode":"7001",
    "sg:province":"Graubunden",
    "wof:name":"Kantonales Veterin\u00e4ramt",
    "wof:placetype":"venue"
},
  "geometry": {"coordinates":[9.5348882675,46.8507270813],"type":"Point"}
}