{
  "type": "Feature",
  "properties": {
    "iso:country":"CH",
    "sg:address":"Piazzeta Da La Posta",
    "sg:city":"Morcote",
    "sg:orig_category":"Unclassifiable Establishments",
    "sg:phone":"+41 91 996 11 27",
    "sg:postcode":"6922",
    "sg:province":"Ticino",
    "wof:name":"Albergo Della Posta",
    "wof:placetype":"venue"
},
  "geometry": {"coordinates":[8.9155397415,45.922504425],"type":"Point"}
}