{
  "type": "Feature",
  "properties": {
    "iso:country":"CH",
    "sg:address":"Schwantlernegg 3",
    "sg:city":"Gais",
    "sg:orig_category":"Physiotherapie",
    "sg:phone":"+41 71 793 17 17",
    "sg:postcode":"9056",
    "sg:province":"Appenzell Ausserrhoden",
    "wof:name":"Antonia F\u00e4h Physiotherapie",
    "wof:placetype":"venue"
},
  "geometry": {"coordinates":[9.4596595764,47.3653297424],"type":"Point"}
}