{
  "type": "Feature",
  "properties": {
    "iso:country":"CH",
    "sg:address":"Vogelsangweg 4",
    "sg:city":"Engelberg",
    "sg:orig_category":"Technische, physikalische U chemische Untersuchung",
    "sg:phone":"+41 41 871 14 45",
    "sg:postcode":"6390",
    "sg:province":"Obwalden",
    "wof:name":"Oeko-b Ag, Zweigniederlassung Altdorf",
    "wof:placetype":"venue"
},
  "geometry": {"coordinates":[8.6453943253,46.8810501099],"type":"Point"}
}