{
  "type": "Feature",
  "properties": {
    "iso:country":"CH",
    "sg:address":"Gantrischweg 8",
    "sg:city":"M\u00fchlethurnen",
    "sg:orig_category":"Unternehmensberatung",
    "sg:phone":"+41 31 809 25 05",
    "sg:postcode":"3127",
    "sg:province":"Bern",
    "wof:name":"Rgc Greuter Roland Consulting",
    "wof:placetype":"venue"
},
  "geometry": {"coordinates":[7.5158090591,46.8118553162],"type":"Point"}
}