{
  "type": "Feature",
  "properties": {
    "iso:country":"CH",
    "sg:address":"Route Cantonale 267",
    "sg:city":"V\u00e9troz",
    "sg:orig_category":"Bauingenieurb\u00fcros allgemein",
    "sg:phone":"+41 27 345 39 45",
    "sg:postcode":"1963",
    "sg:province":"Valais",
    "wof:name":"Rebord Sa Bureau D'ing\u00e9nieurs",
    "wof:placetype":"venue"
},
  "geometry": {"coordinates":[7.261756,46.217567],"type":"Point"}
}