{
  "type": "Feature",
  "properties": {
    "iso:country":"CH",
    "sg:address":"Via Cantonale",
    "sg:city":"Vaglio",
    "sg:orig_category":"Physiotherapie",
    "sg:phone":"+41 91 943 62 62",
    "sg:postcode":"6947",
    "sg:province":"Ticino",
    "wof:name":"Paolo Bonacina Fisioterapia",
    "wof:placetype":"venue"
},
  "geometry": {"coordinates":[8.9572849274,46.0606613159],"type":"Point"}
}