{
  "type": "Feature",
  "properties": {
    "iso:country":"CH",
    "sg:address":"Premploz",
    "sg:city":"Erde",
    "sg:orig_category":"Bauschreinerei",
    "sg:phone":"+41 27 346 14 76",
    "sg:postcode":"1976",
    "sg:province":"Valais",
    "wof:name":"Michel Dessimoz Menuiserie",
    "wof:placetype":"venue"
},
  "geometry": {"coordinates":[7.29598,46.24258],"type":"Point"}
}