{
  "type": "Feature",
  "properties": {
    "iso:country":"CH",
    "sg:address":"Doggilochstrasse 55",
    "sg:city":"Klosters",
    "sg:orig_category":"Sportvereine Schwingen",
    "sg:phone":"+41 62 771 58 79",
    "sg:postcode":"7250",
    "sg:province":"Graubunden",
    "wof:name":"Schwingklub Kulm",
    "wof:placetype":"venue"
},
  "geometry": {"coordinates":[8.1906738281,47.253742218],"type":"Point"}
}