{
  "type": "Feature",
  "properties": {
    "iso:country":"CH",
    "sg:address":"Derivaz Quai Isaac",
    "sg:city":"St-gingolph",
    "sg:orig_category":"RESTAURANTS: TEA-ROOMS",
    "sg:phone":"+41 24 481 41 17",
    "sg:postcode":"1898",
    "sg:province":"Valais",
    "wof:name":"Dufresne G\u00e9rald",
    "wof:placetype":"venue"
},
  "geometry": {"coordinates":[6.8057551384,46.3934707642],"type":"Point"}
}