{
  "type": "Feature",
  "properties": {
    "iso:country":"CH",
    "sg:address":"Brunnmattstrasse 5",
    "sg:city":"Basel",
    "sg:orig_category":"Organisationen des Gesundheitswesen",
    "sg:phone":"+41 61 361 93 02",
    "sg:postcode":"4053",
    "sg:province":"Basel-Stadt",
    "wof:name":"Samariterverein Alban-breite",
    "wof:placetype":"venue"
},
  "geometry": {"coordinates":[7.5908021927,47.5405464172],"type":"Point"}
}