{
  "type": "Feature",
  "properties": {
    "iso:country":"CH",
    "sg:address":"Alberich Zwyssig-strasse 32",
    "sg:city":"Wettingen",
    "sg:orig_category":"Vermittlung von Immobilien Verwaltung von Immobilien",
    "sg:postcode":"5430",
    "sg:province":"Aargau",
    "wof:name":"H\u00f6ggerai-kies Ag",
    "wof:placetype":"venue"
},
  "geometry": {"coordinates":[8.321185112,47.4617118835],"type":"Point"}
}