{
  "type": "Feature",
  "properties": {
    "iso:country":"CH",
    "sg:address":"Murbacherstrasse 16",
    "sg:city":"Luzern",
    "sg:orig_category":"Zahnarztpraxen",
    "sg:phone":"+41 41 210 48 88",
    "sg:postcode":"6003",
    "sg:province":"Luzern",
    "wof:name":"Dr.med.dent. Raphael M\u00fchlebach Zahnarzt",
    "wof:placetype":"venue"
},
  "geometry": {"coordinates":[8.3064842224,47.0477218628],"type":"Point"}
}