{
  "type": "Feature",
  "properties": {
    "iso:country":"CH",
    "sg:address":"8057 Z\u00fcrich. Postfach",
    "sg:city":"Z\u00fcrich",
    "sg:orig_category":"Interessenvertretungen Sonstige Institutionen des Sozialwesens ohne Beherbergung",
    "sg:phone":"+41 71 223 48 77",
    "sg:postcode":"8057",
    "sg:province":"Z\u00fcrich",
    "wof:name":"Stiftung F\u00fcr Opfer Strafbarer Handlungen",
    "wof:placetype":"venue"
},
  "geometry": {"coordinates":[9.3745412827,47.4256896973],"type":"Point"}
}