{
  "type": "Feature",
  "properties": {
    "iso:country":"CH",
    "sg:address":"M\u00fcnstergasse 68 3011 Bern. Postfach",
    "sg:city":"Bern",
    "sg:orig_category":"RESTAURANTS: TEA-ROOMS",
    "sg:postcode":"3005",
    "sg:province":"Bern",
    "wof:name":"Wachter-andrini Werner, Caf\u00e9 Altstadt",
    "wof:placetype":"venue"
},
  "geometry": {"coordinates":[7.4486532211,46.9475784302],"type":"Point"}
}