{
  "type": "Feature",
  "properties": {
    "iso:country":"CH",
    "sg:address":"Nordstrasse 9",
    "sg:city":"Heiden",
    "sg:orig_category":"Vermietung U Verpachtung von eigenen Immobilien",
    "sg:postcode":"9410",
    "sg:province":"Appenzell Ausserrhoden",
    "wof:name":"Metu Immobilien Ag",
    "wof:placetype":"venue"
},
  "geometry": {"coordinates":[9.5285282135,47.449180603],"type":"Point"}
}