{
  "type": "Feature",
  "properties": {
    "iso:country":"CH",
    "sg:address":"Freie Strasse 52",
    "sg:city":"Basel",
    "sg:orig_category":"Arztpraxen",
    "sg:phone":"+41 52 232 89 89",
    "sg:postcode":"4001",
    "sg:province":"Basel-Stadt",
    "wof:name":"Dr.med.j\u00fcrg Schlegel Arzt F.allgemeine Medizin Fmh",
    "wof:placetype":"venue"
},
  "geometry": {"coordinates":[8.760722,47.483559],"type":"Point"}
}