{
  "type": "Feature",
  "properties": {
    "iso:country":"CH",
    "sg:address":"Schlossstrasse 8",
    "sg:city":"M\u00fcnsingen",
    "sg:classifiers":[
        {
            "category":"Travel",
            "subcategory":"Hotels & Motels",
            "type":"Entertainment"
        }
    ],
    "sg:phone":"+41 31 721 54 40",
    "sg:postcode":"3110",
    "sg:province":"Bern",
    "sg:tags":[
        "hotels",
        "mit",
        "restaurant"
    ],
    "wof:name":"Zbinden-sch\u00fcrch Fritz Rudolf",
    "wof:placetype":"venue"
},
  "geometry": {"coordinates":[7.5607948303,46.8763313293],"type":"Point"}
}