{
  "type": "Feature",
  "properties": {
    "iso:country":"CH",
    "sg:address":"Rosenweg 14",
    "sg:city":"Jegenstorf",
    "sg:orig_category":"Ingenieurb\u00fcros Datenverarbeitung Softwareentwicklung U beratung",
    "sg:postcode":"3303",
    "sg:province":"Bern",
    "wof:name":"Claude Martin Eisenhut Informatik Softwareanspassung",
    "wof:placetype":"venue"
},
  "geometry": {"coordinates":[7.5120429993,47.0517807007],"type":"Point"}
}