{
  "type": "Feature",
  "properties": {
    "iso:country":"CH",
    "sg:address":"Sonnhalde 7",
    "sg:city":"Oftringen",
    "sg:orig_category":"Handelsvermittlung U Grosshandel mit Automobilteilen U Zubeh\u00f6r",
    "sg:phone":"+41 62 798 03 03",
    "sg:postcode":"4665",
    "sg:province":"Aargau",
    "wof:name":"A. & R. Wullschleger Anh\u00e4ngerkupplungen/autozubeh\u00f6r",
    "wof:placetype":"venue"
},
  "geometry": {"coordinates":[7.9450139999,47.3063926697],"type":"Point"}
}