{
  "type": "Feature",
  "properties": {
    "iso:country":"CH",
    "sg:address":"Dammstrasse 17",
    "sg:city":"Zollikon",
    "sg:orig_category":"Finanzierungsinstitutionen Informatikdienste",
    "sg:phone":"+41 13901536",
    "sg:postcode":"8702",
    "sg:province":"Z\u00fcrich",
    "wof:name":"Koller Consulting Gmbh",
    "wof:placetype":"venue"
},
  "geometry": {"coordinates":[8.5667200089,47.3451461792],"type":"Point"}
}