{
  "type": "Feature",
  "properties": {
    "iso:country":"CH",
    "sg:address":"Luzernerhof",
    "sg:city":"Luzern",
    "sg:orig_category":"Vermietung von Gebrauchsg\u00fctern Vermietung von Wasserfahrzeugen",
    "sg:phone":"+41 41 410 20 55",
    "sg:postcode":"6004",
    "sg:province":"Luzern",
    "wof:name":"Ruedi & Barbara Bucher Bootsvermietung",
    "wof:placetype":"venue"
},
  "geometry": {"coordinates":[8.2956199646,47.0548210144],"type":"Point"}
}