{
  "type": "Feature",
  "properties": {
    "iso:country":"CH",
    "sg:address":"Bruggmattweg 37",
    "sg:city":"Fahrwangen",
    "sg:orig_category":"Grosshandel mit Holz U Baustoffen Herstellung von konfektionierten Textilwaren ohne Bekleidung",
    "sg:phone":"+41 56 667 13 22",
    "sg:postcode":"5615",
    "sg:province":"Aargau",
    "wof:name":"Freivogel Ag",
    "wof:placetype":"venue"
},
  "geometry": {"coordinates":[8.2432518005,47.2908935547],"type":"Point"}
}