{
  "type": "Feature",
  "properties": {
    "iso:country":"CH",
    "sg:address":"Oberdorfweg",
    "sg:city":"Gams",
    "sg:orig_category":"Erbringung von Dienstleistungen f\u00fcr Unternehmen",
    "sg:phone":"+41 81 740 34 51",
    "sg:postcode":"9473",
    "sg:province":"St. Gallen",
    "wof:name":"Langenegger H. Treuhand Inkasso",
    "wof:placetype":"venue"
},
  "geometry": {"coordinates":[9.4427900314,47.2120475769],"type":"Point"}
}