{
  "type": "Feature",
  "properties": {
    "iso:country":"CH",
    "sg:address":"Via San Gottardo 30",
    "sg:city":"Vezia",
    "sg:orig_category":"Chemische Reinigung W\u00e4schereien",
    "sg:phone":"+41 91 966 68 15",
    "sg:postcode":"6943",
    "sg:province":"Ticino",
    "wof:name":"Mcw Modern Chemical Washing Sa",
    "wof:placetype":"venue"
},
  "geometry": {"coordinates":[8.937457,46.024662],"type":"Point"}
}