{
  "type": "Feature",
  "properties": {
    "iso:country":"CH",
    "sg:address":"Platz 12 9100 Herisau. Postfach",
    "sg:city":"Herisau",
    "sg:orig_category":"Gewinnung von Kies U Sand Herstellung von Betonerzeugnissen f\u00fcr den Bau",
    "sg:phone":"+41 71 352 25 30",
    "sg:postcode":"9102",
    "sg:province":"Appenzell Ausserrhoden",
    "wof:name":"Hastag St. Gallen",
    "wof:placetype":"venue"
},
  "geometry": {"coordinates":[9.2789163589,47.3856658936],"type":"Point"}
}