{
  "type": "Feature",
  "properties": {
    "iso:country":"CH",
    "sg:address":"Birmensdorferstrasse 225",
    "sg:city":"Z\u00fcrich",
    "sg:orig_category":"Grosshandel mit pharmazeutischen Erzeugnissen Sonstiger Grosshandel",
    "sg:phone":"+41 14614278",
    "sg:postcode":"8000",
    "sg:province":"Z\u00fcrich",
    "wof:name":"Arvida Handels Und Vertriebs Ag",
    "wof:placetype":"venue"
},
  "geometry": {"coordinates":[8.46479702,47.3689155579],"type":"Point"}
}