{
  "type": "Feature",
  "properties": {
    "iso:country":"CH",
    "sg:address":"Gellertstrasse 5",
    "sg:city":"Basel",
    "sg:orig_category":"Sportvereine Sch\u00fctzen",
    "sg:phone":"+41 61 313 10 25",
    "sg:postcode":"4052",
    "sg:province":"Basel-Stadt",
    "wof:name":"Feldsch\u00fctzenges.basel",
    "wof:placetype":"venue"
},
  "geometry": {"coordinates":[7.60668993,47.5524864197],"type":"Point"}
}