{
  "type": "Feature",
  "properties": {
    "iso:country":"CH",
    "sg:address":"M\u00fclinenstrasse 31",
    "sg:city":"H\u00fcnibach",
    "sg:orig_category":"Vereine Gesang",
    "sg:postcode":"3626",
    "sg:province":"Bern",
    "wof:name":"Ref.kirchenchor Hilterfingen",
    "wof:placetype":"venue"
},
  "geometry": {"coordinates":[7.6457929611,46.7477149963],"type":"Point"}
}