{
  "type": "Feature",
  "properties": {
    "iso:country":"CH",
    "sg:address":"Hartbertstrasse 10",
    "sg:city":"Chur",
    "sg:orig_category":"Non-Classified Establishments",
    "sg:postcode":"7000",
    "sg:province":"Graubunden",
    "wof:name":"Stiftung Mobilita",
    "wof:placetype":"venue"
},
  "geometry": {"coordinates":[9.5325880051,46.8532905579],"type":"Point"}
}