{
  "type": "Feature",
  "properties": {
    "iso:country":"CH",
    "sg:address":"Alexanderstrasse 24 7000 Chur. Postfach",
    "sg:city":"Chur",
    "sg:classifiers":[
        {
            "category":"Government",
            "subcategory":"Post Office",
            "type":"Public Place"
        }
    ],
    "sg:phone":"+41 81 252 36 66",
    "sg:postcode":"7002",
    "sg:province":"Graubunden",
    "sg:tags":[
        "caf\u00e9s",
        "tea-rooms"
    ],
    "wof:name":"Caf\u00e9 Media",
    "wof:placetype":"venue"
},
  "geometry": {"coordinates":[9.5315389633,46.8539237976],"type":"Point"}
}