{
  "type": "Feature",
  "properties": {
    "iso:country":"CH",
    "sg:address":"1262",
    "sg:city":"Eysins",
    "sg:orig_category":"Landesverteidigung, Sozialversicherung \u00d6ffentliche Verwaltung",
    "sg:phone":"+41 22 361 36 78",
    "sg:postcode":"1262",
    "sg:province":"Vaud",
    "wof:name":"Centre De Protection Civile",
    "wof:placetype":"venue"
},
  "geometry": {"coordinates":[6.2055001259,46.3800888062],"type":"Point"}
}