{
  "type": "Feature",
  "properties": {
    "iso:country":"CH",
    "sg:address":"Reusshof",
    "sg:city":"Oberr\u00fcti",
    "sg:orig_category":"Wasserversorgung",
    "sg:postcode":"5647",
    "sg:province":"Aargau",
    "wof:name":"Wasserversorgung Oetwil",
    "wof:placetype":"venue"
},
  "geometry": {"coordinates":[9.0402641296,47.4111328125],"type":"Point"}
}