{
  "type": "Feature",
  "properties": {
    "iso:country":"CH",
    "sg:address":"Gerbeackerstrasse 8",
    "sg:city":"Kerzers",
    "sg:orig_category":"Kauf U Verkauf von Immobilien auf eigene Rechnung",
    "sg:postcode":"3210",
    "sg:province":"Fribourg",
    "wof:name":"Andare Ag",
    "wof:placetype":"venue"
},
  "geometry": {"coordinates":[7.1939249039,46.9721298218],"type":"Point"}
}