{
  "type": "Feature",
  "properties": {
    "iso:country":"CH",
    "sg:address":"Farbikstr. 30 8855 Wangen Sz. Postfach",
    "sg:city":"Siebnen",
    "sg:orig_category":"Maler U Glasergewerbe",
    "sg:postcode":"8854",
    "sg:province":"Schwyz",
    "wof:name":"Maler Und Tapezierarbeiten Ren\u00e9 Vogt",
    "wof:placetype":"venue"
},
  "geometry": {"coordinates":[8.8964147568,47.1912956238],"type":"Point"}
}