{
  "type": "Feature",
  "properties": {
    "iso:country":"CH",
    "sg:address":"Tulpenweg 79",
    "sg:city":"K\u00f6niz",
    "sg:orig_category":"Non-Classified Establishments",
    "sg:postcode":"3098",
    "sg:province":"Bern",
    "wof:name":"Kym's Service Gmbh",
    "wof:placetype":"venue"
},
  "geometry": {"coordinates":[7.4090380669,46.9242248535],"type":"Point"}
}