{
  "type": "Feature",
  "properties": {
    "iso:country":"CH",
    "sg:address":"Dorfrain 2",
    "sg:city":"Safenwil",
    "sg:orig_category":"RESTAURANTS: TEA-ROOMS",
    "sg:phone":"+41 62 797 12 43",
    "sg:postcode":"5745",
    "sg:province":"Aargau",
    "wof:name":"Restaurant Dorfplatz Hugo Zimmerli",
    "wof:placetype":"venue"
},
  "geometry": {"coordinates":[7.984413147,47.3192443848],"type":"Point"}
}