{
  "type": "Feature",
  "properties": {
    "iso:country":"CH",
    "sg:address":"Avenue De Tourbillon 30",
    "sg:city":"Sion",
    "sg:orig_category":"Fahrschulen, Flugschulen",
    "sg:phone":"+41 79 213 30 13",
    "sg:postcode":"1950",
    "sg:province":"Valais",
    "wof:name":"Jean-charles Rey Auto-\u00e9cole",
    "wof:placetype":"venue"
},
  "geometry": {"coordinates":[7.3634109497,46.229019165],"type":"Point"}
}