{
  "type": "Feature",
  "properties": {
    "iso:country":"CH",
    "sg:address":"Rebenweg 33",
    "sg:city":"Uster",
    "sg:orig_category":"Gesundheits U Sozialwesen",
    "sg:phone":"+41 19408844",
    "sg:postcode":"8610",
    "sg:province":"Z\u00fcrich",
    "wof:name":"Wellness-kurier Massage Zu Hause/im B\u00fcro",
    "wof:placetype":"venue"
},
  "geometry": {"coordinates":[8.7112789154,47.36120224],"type":"Point"}
}