{
  "type": "Feature",
  "properties": {
    "iso:country":"CH",
    "sg:address":"Seftigenstrasse 298",
    "sg:city":"Wabern",
    "sg:orig_category":"Detailhandel mit Haustieren U zoologischem Bedarf",
    "sg:phone":"+41 31 961 13 00",
    "sg:postcode":"3084",
    "sg:province":"Bern",
    "wof:name":"Aquarium Herzog",
    "wof:placetype":"venue"
},
  "geometry": {"coordinates":[7.4542160034,46.9273109436],"type":"Point"}
}