{
  "type": "Feature",
  "properties": {
    "iso:country":"CH",
    "sg:address":"Weineggstrasse 63",
    "sg:city":"Z\u00fcrich",
    "sg:orig_category":"Erbringung von Dienstleistungen f\u00fcr Unternehmen Fotografische Ateliers",
    "sg:phone":"+41 13806770",
    "sg:postcode":"8008",
    "sg:province":"Z\u00fcrich",
    "wof:name":"Dmp-network.com De Monaco Production",
    "wof:placetype":"venue"
},
  "geometry": {"coordinates":[8.5674571991,47.3578186035],"type":"Point"}
}