{
  "type": "Feature",
  "properties": {
    "addr:full":"Dorfstrasse 10 8800 Thalwil. Postfach 1531 Thalwil Z\u00fcrich 8801",
    "addr:housenumber":"10",
    "addr:postcode":"8800 thalwil. postfach 1531;8801",
    "addr:street":"Dorfstrasse",
    "iso:country":"CH",
    "sg:address":"Dorfstrasse 10 8800 Thalwil. Postfach 1531",
    "sg:city":"Thalwil",
    "sg:orig_category":"Bau\u00e4mter",
    "sg:phone":"+41 17232323",
    "sg:postcode":"8801",
    "sg:province":"Z\u00fcrich",
    "wof:name":"Bauamt Der Gemeinde Thalwil",
    "wof:placetype":"venue"
},
  "geometry": {"coordinates":[8.568063,47.289768],"type":"Point"}
}