{
  "type": "Feature",
  "properties": {
    "iso:country":"CH",
    "sg:address":"Unterseestrasse 47",
    "sg:city":"Kreuzlingen",
    "sg:classifiers":[
        {
            "category":"Utilities",
            "subcategory":"Electric",
            "type":"Services"
        }
    ],
    "sg:phone":"+41 71 677 45 45",
    "sg:postcode":"8280",
    "sg:province":"Thurgau",
    "sg:tags":[
        "equipment",
        "therapy",
        "electroshock"
    ],
    "wof:name":"Storz Medical Ag",
    "wof:placetype":"venue"
},
  "geometry": {"coordinates":[9.1625299454,47.6480484009],"type":"Point"}
}