{
  "type": "Feature",
  "properties": {
    "iso:country":"CH",
    "sg:address":"Tafelenfeldweg 10 3312 Fraubrunnen. Postfach",
    "sg:city":"Fraubrunnen",
    "sg:orig_category":"Erschliessung von Grundst\u00fccken",
    "sg:postcode":"3312",
    "sg:province":"Bern",
    "wof:name":"Baugenossenschaft Terra Nova Anbieten Von Wohneigentum Zu G\u00fcnstigen Konditionen F\u00fcr Heutige Und Zuk\u00fcnftige Mitglieder Usw",
    "wof:placetype":"venue"
},
  "geometry": {"coordinates":[7.5234131813,47.0888977051],"type":"Point"}
}