{
  "type": "Feature",
  "properties": {
    "iso:country":"CH",
    "sg:address":"Soldini Via 38",
    "sg:city":"Chiasso",
    "sg:orig_category":"Vermietung U Verpachtung von eigenen Immobilien",
    "sg:postcode":"6830",
    "sg:province":"Ticino",
    "wof:name":"Torrequarta Sa",
    "wof:placetype":"venue"
},
  "geometry": {"coordinates":[9.0162334442,45.8353881836],"type":"Point"}
}