{
  "type": "Feature",
  "properties": {
    "iso:country":"CH",
    "sg:address":"Via Dei Pioppi 10",
    "sg:city":"Losone",
    "sg:orig_category":"Datenverarbeitungsdienste",
    "sg:postcode":"6616",
    "sg:province":"Ticino",
    "wof:name":"Ibbs Sa Servizi Internet",
    "wof:placetype":"venue"
},
  "geometry": {"coordinates":[8.770831,46.167324],"type":"Point"}
}