{
  "type": "Feature",
  "properties": {
    "iso:country":"CH",
    "sg:address":"Z\u00fcrichstrasse 61 8840 Einsiedeln. Postfach 61",
    "sg:city":"Einsiedeln",
    "sg:orig_category":"Herstellung von K\u00fcchenm\u00f6beln",
    "sg:phone":"+41 55 418 75 20",
    "sg:postcode":"8840",
    "sg:province":"Schwyz",
    "wof:name":"Astor K\u00fcchen Und M\u00f6belbau Ag",
    "wof:placetype":"venue"
},
  "geometry": {"coordinates":[8.745006,47.135147],"type":"Point"}
}