{
  "type": "Feature",
  "properties": {
    "iso:country":"CH",
    "sg:address":"Feldstrasse 11",
    "sg:city":"Glarus",
    "sg:orig_category":"Herstellung von Schmuck, Gold U Silberschmiedwaren",
    "sg:postcode":"8750",
    "sg:province":"Glarus",
    "wof:name":"Hand-gravuren Walcher",
    "wof:placetype":"venue"
},
  "geometry": {"coordinates":[9.0630283356,47.0386199951],"type":"Point"}
}