{
  "type": "Feature",
  "properties": {
    "iso:country":"CH",
    "sg:address":"Haldenstrasse 18",
    "sg:city":"M\u00fcnsingen",
    "sg:orig_category":"Markt U Meinungsforschung",
    "sg:phone":"+41 31 722 19 45",
    "sg:postcode":"3110",
    "sg:province":"Bern",
    "wof:name":"Zosso & Partner Management Gmbh Dienstleistungen Im Bereich Marketing U. Unternehmensberatung Usw",
    "wof:placetype":"venue"
},
  "geometry": {"coordinates":[7.5692892075,46.8738861084],"type":"Point"}
}