{
  "type": "Feature",
  "properties": {
    "addr:full":"Hauptstrasse 17 Binningen Basel-Landschaft 4102",
    "addr:housenumber":"17",
    "addr:postcode":"4102",
    "addr:street":"Hauptstrasse",
    "iso:country":"CH",
    "sg:address":"Hauptstrasse 17",
    "sg:city":"Binningen",
    "sg:orig_category":"Ackerbau",
    "sg:postcode":"4102",
    "sg:province":"Basel-Landschaft",
    "wof:name":"Premium Afco Ag",
    "wof:placetype":"venue"
},
  "geometry": {"coordinates":[7.575378,47.543072],"type":"Point"}
}