{
  "type": "Feature",
  "properties": {
    "addr:full":"Petit-clos Chemin Du 20 1815 Clarens. Postfach Clarens Vaud 1815",
    "addr:postcode":"1815 clarens. postfach clarens;1815",
    "addr:street":"Chemin Du 20",
    "iso:country":"CH",
    "sg:address":"Petit-clos Chemin Du 20 1815 Clarens. Postfach",
    "sg:city":"Clarens",
    "sg:orig_category":"Allgemeiner Hoch U Tiefbau",
    "sg:postcode":"1815",
    "sg:province":"Vaud",
    "wof:name":"E.g.b. Montreux Sa Entreprise G\u00e9n\u00e9rale Du B\u00e2timent",
    "wof:placetype":"venue"
},
  "geometry": {"coordinates":[6.899134,46.441841],"type":"Point"}
}