{
  "type": "Feature",
  "properties": {
    "iso:country":"CH",
    "sg:address":"Burgdorfstrasse 30",
    "sg:city":"Oberdiessbach",
    "sg:orig_category":"Fotografisches Gewerbe U fotografische Laboratorien",
    "sg:postcode":"3672",
    "sg:province":"Bern",
    "wof:name":"Black & White Fotofachlabor Hoign\u00e9 Christoph",
    "wof:placetype":"venue"
},
  "geometry": {"coordinates":[7.6196808815,46.8439216614],"type":"Point"}
}