{
  "type": "Feature",
  "properties": {
    "iso:country":"CH",
    "sg:address":"Hummelstrasse 8b 8500 Frauenfeld. Postfach",
    "sg:city":"Frauenfeld",
    "sg:orig_category":"Bau von Strassen, Sportanlagen U Bahnverkehrsstrecken Strassenbau",
    "sg:phone":"+41 52 722 32 22",
    "sg:postcode":"8501",
    "sg:province":"Thurgau",
    "wof:name":"H\u00fcppi Ag Bauunternehmung",
    "wof:placetype":"venue"
},
  "geometry": {"coordinates":[8.88382,47.56263],"type":"Point"}
}