{
  "type": "Feature",
  "properties": {
    "iso:country":"CH",
    "sg:address":"Rue Des Grives 35",
    "sg:city":"Givisiez",
    "sg:orig_category":"Geb\u00e4ude, Wohnungsreinigung Reinigungsgewerbe",
    "sg:phone":"+41 79 417 52 35",
    "sg:postcode":"1762",
    "sg:province":"Fribourg",
    "wof:name":"Anna Liaci Tecnica Nettoyage Liaci",
    "wof:placetype":"venue"
},
  "geometry": {"coordinates":[7.1304831505,46.8091545105],"type":"Point"}
}