{
  "type": "Feature",
  "properties": {
    "iso:country":"CH",
    "sg:address":"Bechburgerstrasse 10",
    "sg:city":"Basel",
    "sg:orig_category":"G\u00fcterbef\u00f6rderung im Strassenverkehr",
    "sg:postcode":"4052",
    "sg:province":"Basel-Stadt",
    "wof:name":"Morales Alfonso",
    "wof:placetype":"venue"
},
  "geometry": {"coordinates":[7.6156802177,47.5534057617],"type":"Point"}
}