{
  "type": "Feature",
  "properties": {
    "iso:country":"CH",
    "sg:address":"Rainacherstrasse 9",
    "sg:city":"Obernau",
    "sg:orig_category":"Sanit\u00e4r U Heizungsinstallation",
    "sg:phone":"+41 41 250 52 62",
    "sg:postcode":"6012",
    "sg:province":"Luzern",
    "wof:name":"Centra-therm Ag Feuerungs-& W\u00e4rmetechnik",
    "wof:placetype":"venue"
},
  "geometry": {"coordinates":[8.2534322739,47.0333824158],"type":"Point"}
}