{
  "type": "Feature",
  "properties": {
    "iso:country":"CH",
    "sg:address":"Thannerstrasse 51 4054 Basel. Postfach",
    "sg:city":"Basel",
    "sg:orig_category":"Herstellung von Baubedarfsartikeln aus Kunststoff",
    "sg:phone":"+41 17405375",
    "sg:postcode":"4027",
    "wof:name":"Rollform Ag",
    "wof:placetype":"venue"
},
  "geometry": {"coordinates":[8.3997058868,47.4158401489],"type":"Point"}
}