{
  "type": "Feature",
  "properties": {
    "iso:country":"CH",
    "sg:address":"Trottenstrasse 4 8472 Seuzach. Postfach",
    "sg:city":"Seuzach",
    "sg:orig_category":"Unternehmensberatung",
    "sg:postcode":"8472",
    "sg:province":"Z\u00fcrich",
    "wof:name":"Value Tools Gmbh",
    "wof:placetype":"venue"
},
  "geometry": {"coordinates":[8.7099027634,47.5280532837],"type":"Point"}
}