{
  "type": "Feature",
  "properties": {
    "iso:country":"CH",
    "sg:address":"Rue De L'ale 16",
    "sg:city":"Lausanne",
    "sg:orig_category":"Grosshandel mit sonstigen Nahrungsmitteln Sonstiger Fachdetailhandel mit Nahrungsmitteln, Getr\u00e4nken ",
    "sg:phone":"+41 21 312 30 45",
    "sg:postcode":"1003",
    "sg:province":"Vaud",
    "wof:name":"Rue De L'ale Sant\u00e9 Sa Centre Di\u00e9t\u00e9tique",
    "wof:placetype":"venue"
},
  "geometry": {"coordinates":[6.6304497719,46.5199890137],"type":"Point"}
}