{
  "type": "Feature",
  "properties": {
    "addr:full":"Leimernweg 14 Aarberg Bern 3270",
    "addr:housenumber":"14",
    "addr:postcode":"3270",
    "addr:street":"Leimernweg",
    "iso:country":"CH",
    "sg:address":"Leimernweg 14",
    "sg:city":"Aarberg",
    "sg:orig_category":"Internet, Internetmarketing",
    "sg:phone":"+41 32 393 11 55",
    "sg:postcode":"3270",
    "sg:province":"Bern",
    "wof:name":"Mediatime Gmbh",
    "wof:placetype":"venue"
},
  "geometry": {"coordinates":[7.282053,47.048561],"type":"Point"}
}