{
  "type": "Feature",
  "properties": {
    "iso:country":"CH",
    "sg:address":"Route Du T\u00e9l\u00e9f\u00e9rique",
    "sg:city":"Vercorin",
    "sg:orig_category":"Maurerarbeiten",
    "sg:phone":"+41 79 434 83 50",
    "sg:postcode":"3967",
    "sg:province":"Valais",
    "wof:name":"Fernand Antille Entreprise De Ma\u00e7onnerie",
    "wof:placetype":"venue"
},
  "geometry": {"coordinates":[7.5315108299,46.2563438416],"type":"Point"}
}