{
  "type": "Feature",
  "properties": {
    "iso:country":"CH",
    "sg:address":"6675",
    "sg:city":"Cevio",
    "sg:orig_category":"Fachdetailhandel mit pharmazeutischen Produkten",
    "sg:phone":"+41 91 754 12 13",
    "sg:postcode":"6675",
    "sg:province":"Ticino",
    "wof:name":"Farmacia Della Valle Dott. Marc Tuor",
    "wof:placetype":"venue"
},
  "geometry": {"coordinates":[8.602025032,46.3169059753],"type":"Point"}
}