{
  "type": "Feature",
  "properties": {
    "iso:country":"CH",
    "sg:address":"Riedm\u00fchlestrasse 16",
    "sg:city":"Dietlikon",
    "sg:orig_category":"Herstellung von Betonerzeugnissen f\u00fcr den Bau Herstellung von Fenstern U T\u00fcren aus Holz",
    "sg:phone":"+41 18334318",
    "sg:postcode":"8305",
    "sg:province":"Z\u00fcrich",
    "wof:name":"Piatti Bruno Ag",
    "wof:placetype":"venue"
},
  "geometry": {"coordinates":[8.6224269867,47.4263916016],"type":"Point"}
}