{
  "type": "Feature",
  "properties": {
    "iso:country":"CH",
    "sg:address":"Wyden 23 C",
    "sg:city":"Bowil",
    "sg:orig_category":"Non-Classified Establishments",
    "sg:postcode":"3533",
    "sg:province":"Bern",
    "wof:name":"Meyer G\u00e4rten Ag",
    "wof:placetype":"venue"
},
  "geometry": {"coordinates":[7.6836109161,46.9000053406],"type":"Point"}
}