{
  "type": "Feature",
  "properties": {
    "iso:country":"CH",
    "sg:address":"Rue De L'h\u00f4pital 16",
    "sg:city":"St-aubin-sauges",
    "sg:orig_category":"Primarschulen",
    "sg:phone":"+41 32 835 13 96",
    "sg:postcode":"2024",
    "sg:province":"Neuch\u00e2tel",
    "wof:name":"Ecole Primaire Coll\u00e8ge",
    "wof:placetype":"venue"
},
  "geometry": {"coordinates":[6.7668199539,46.8932914734],"type":"Point"}
}