{
  "type": "Feature",
  "properties": {
    "iso:country":"CH",
    "sg:address":"Weihermattstrasse 57",
    "sg:city":"Urdorf",
    "sg:orig_category":"Vorschulen, Kinderg\u00e4rten",
    "sg:phone":"+41 17343235",
    "sg:postcode":"8902",
    "sg:province":"Z\u00fcrich",
    "wof:name":"Kindergarten",
    "wof:placetype":"venue"
},
  "geometry": {"coordinates":[8.428565979,47.379737854],"type":"Point"}
}