{
  "type": "Feature",
  "properties": {
    "iso:country":"CH",
    "sg:address":"Strehlgasse 7",
    "sg:city":"Seuzach",
    "sg:orig_category":"Sonstiges Gesundheitswesen",
    "sg:phone":"+41 41 460 48 80",
    "sg:postcode":"8472",
    "sg:province":"Z\u00fcrich",
    "wof:name":"Krankenmobilien-depot Alterswohnheim Meierh\u00f6fli",
    "wof:placetype":"venue"
},
  "geometry": {"coordinates":[8.2235832214,47.131149292],"type":"Point"}
}