{
  "type": "Feature",
  "properties": {
    "iso:country":"CH",
    "sg:address":"Chartreusestr. 11",
    "sg:city":"Hilterfingen",
    "sg:orig_category":"Zimmerei, Dachdeckerei, Bauspenglerei U Abdichtung",
    "sg:postcode":"3652",
    "sg:province":"Bern",
    "wof:name":"Zimmerei Wohlwend",
    "wof:placetype":"venue"
},
  "geometry": {"coordinates":[7.6457481384,46.7464866638],"type":"Point"}
}