{
  "type": "Feature",
  "properties": {
    "iso:country":"CH",
    "sg:address":"Wiesenstrasse 30",
    "sg:city":"St.gallen",
    "sg:orig_category":"Sportvereine Alpinismus",
    "sg:phone":"+41 71 223 63 54",
    "sg:postcode":"9000",
    "sg:province":"St. Gallen",
    "wof:name":"Katourg St.gallen",
    "wof:placetype":"venue"
},
  "geometry": {"coordinates":[9.3802719116,47.4178085327],"type":"Point"}
}