{
  "type": "Feature",
  "properties": {
    "iso:country":"CH",
    "sg:address":"Martinsbergstrasse 7",
    "sg:city":"Baden",
    "sg:orig_category":"Malerei",
    "sg:phone":"+41 56 222 22 46",
    "sg:postcode":"5400",
    "sg:province":"Aargau",
    "wof:name":"Hans Aeberhard Malergesch\u00e4ft",
    "wof:placetype":"venue"
},
  "geometry": {"coordinates":[8.3038959503,47.4745635986],"type":"Point"}
}