{
  "type": "Feature",
  "properties": {
    "iso:country":"CH",
    "sg:address":"Nestl\u00e9strasse 3",
    "sg:city":"Cham",
    "sg:orig_category":"Unternehmensberatung",
    "sg:postcode":"6330",
    "sg:province":"Zug",
    "wof:name":"Freezeit Management Ag",
    "wof:placetype":"venue"
},
  "geometry": {"coordinates":[8.462972641,47.180973053],"type":"Point"}
}