{
  "type": "Feature",
  "properties": {
    "iso:country":"CH",
    "sg:address":"Hirschengraben 5 3011 Bern. Postfach",
    "sg:city":"Bern",
    "sg:orig_category":"Detailhandel mit Uhren U Schmuck",
    "sg:phone":"+41 31 312 07 77",
    "sg:postcode":"3001",
    "sg:province":"Bern",
    "wof:name":"Peter Kissling Goldschmiede-atelier",
    "wof:placetype":"venue"
},
  "geometry": {"coordinates":[7.4381861687,46.9466705322],"type":"Point"}
}