{
  "type": "Feature",
  "properties": {
    "iso:country":"CH",
    "sg:address":"Dorfstrasse 2",
    "sg:city":"W\u00fcrenlos",
    "sg:orig_category":"Sanit\u00e4r, Heizungs U L\u00fcftungsinstallation Sanit\u00e4rinstallation",
    "sg:phone":"+41 56 424 14 40",
    "sg:postcode":"5436",
    "sg:province":"Aargau",
    "wof:name":"Brunner Felix.",
    "wof:placetype":"venue"
},
  "geometry": {"coordinates":[8.3617868423,47.4440956116],"type":"Point"}
}