{
  "type": "Feature",
  "properties": {
    "iso:country":"CH",
    "sg:address":"Rue Le-corbusier 22a",
    "sg:city":"Genf",
    "sg:orig_category":"Detailhandel mit Tabakwaren",
    "sg:phone":"+41 22 346 81 10",
    "sg:postcode":"1200",
    "sg:province":"Gen\u00e8ve",
    "wof:name":"La Tabati\u00e8re, Dubois Lucienne",
    "wof:placetype":"venue"
},
  "geometry": {"coordinates":[6.1667118073,46.193359375],"type":"Point"}
}