{
  "type": "Feature",
  "properties": {
    "iso:country":"CH",
    "sg:address":"Reiterstrasse 16 4054 Basel. Postfach",
    "sg:city":"Basel",
    "sg:orig_category":"G\u00fcterbef\u00f6rderung im Strassenverkehr",
    "sg:phone":"+41 61 302 74 74",
    "sg:postcode":"4027",
    "wof:name":"Borer Warentransport",
    "wof:placetype":"venue"
},
  "geometry": {"coordinates":[7.5654277802,47.5491256714],"type":"Point"}
}