{
  "type": "Feature",
  "properties": {
    "addr:full":"Carlo Via San 3 6600 Muralto. Postfach Muralto Ticino 6600",
    "addr:housenumber":"3",
    "addr:postcode":"6600 muralto. postfach;6600",
    "addr:street":"Via San",
    "iso:country":"CH",
    "sg:address":"Carlo Via San 3 6600 Muralto. Postfach",
    "sg:city":"Muralto",
    "sg:orig_category":"Architektur U Ingenieurb\u00fcros",
    "sg:phone":"+41 91 743 30 45",
    "sg:postcode":"6600",
    "sg:province":"Ticino",
    "wof:name":"Studio Arch. Baserga Nicola E Mozzetti Christian Snc Studio D'architettura",
    "wof:placetype":"venue"
},
  "geometry": {"coordinates":[8.800394,46.170574],"type":"Point"}
}