{
  "type": "Feature",
  "properties": {
    "iso:country":"CH",
    "sg:address":"Seestrasse 94 8820 W\u00e4denswil. Postfach",
    "sg:city":"W\u00e4denswil",
    "sg:orig_category":"Detailhandel mit Damenbekleidung Detailhandel mit Herrenbekleidung",
    "sg:phone":"+41 17839596",
    "sg:postcode":"8820",
    "sg:province":"Z\u00fcrich",
    "wof:name":"B\u00e4r Gabriela Sport Und Freizeitartikel Sport, Freizeit, Bes. Box, Kickboxartikel Usw; Vertrieb",
    "wof:placetype":"venue"
},
  "geometry": {"coordinates":[8.6753988266,47.2281417847],"type":"Point"}
}