{
  "type": "Feature",
  "properties": {
    "iso:country":"CH",
    "sg:address":"Avenue De Bel-air 39c",
    "sg:city":"Ch\u00eane-bourg",
    "sg:orig_category":"Herstellung von sonstigen landwirtschaftlichen Maschinen Schlossereien",
    "sg:phone":"+41 22 348 57 93",
    "sg:postcode":"1225",
    "sg:province":"Gen\u00e8ve",
    "wof:name":"Marcel L\u00e9chaire Serrurerie-machines Agricoles",
    "wof:placetype":"venue"
},
  "geometry": {"coordinates":[6.1968688965,46.2007713318],"type":"Point"}
}