{
  "type": "Feature",
  "properties": {
    "iso:country":"CH",
    "sg:address":"Route D'onnens 1",
    "sg:city":"Neyruz",
    "sg:classifiers":[
        {
            "category":"Government",
            "subcategory":"Court House",
            "type":"Public Place"
        }
    ],
    "sg:phone":"+41 26 477 01 23",
    "sg:postcode":"1740",
    "sg:province":"Fribourg",
    "sg:tags":[
        "paint",
        "dispersing",
        "agent"
    ],
    "wof:name":"Alro Information Systems Sa",
    "wof:placetype":"venue"
},
  "geometry": {"coordinates":[7.0673398972,46.76612854],"type":"Point"}
}