{
  "type": "Feature",
  "properties": {
    "iso:country":"CH",
    "sg:address":"Z\u00fcrcherstrasse 48",
    "sg:city":"Feuerthalen",
    "sg:orig_category":"RESTAURANTS: TEA-ROOMS",
    "sg:phone":"+41 52 659 41 21",
    "sg:postcode":"8245",
    "sg:province":"Z\u00fcrich",
    "wof:name":"Sunfun Ag",
    "wof:placetype":"venue"
},
  "geometry": {"coordinates":[8.6417551041,47.6924285889],"type":"Point"}
}