{
  "type": "Feature",
  "properties": {
    "iso:country":"CH",
    "sg:address":"Margritenweg 12",
    "sg:city":"B\u00e4tterkinden",
    "sg:orig_category":"Sportvereine Turnen Vereine Damen",
    "sg:phone":"+41 32 665 37 30",
    "sg:postcode":"3315",
    "sg:province":"Bern",
    "wof:name":"Frauenturnverein B\u00e4tterkinden",
    "wof:placetype":"venue"
},
  "geometry": {"coordinates":[7.5408592224,47.1346321106],"type":"Point"}
}