{
  "type": "Feature",
  "properties": {
    "iso:country":"CH",
    "sg:address":"Franziskanerplatz 11",
    "sg:city":"Luzern",
    "sg:orig_category":"Detailhandel mit Damenbekleidung",
    "sg:phone":"+41 41 210 37 77",
    "sg:postcode":"6003",
    "sg:province":"Luzern",
    "wof:name":"La Donna Boutique",
    "wof:placetype":"venue"
},
  "geometry": {"coordinates":[8.302997,47.049896],"type":"Point"}
}