{
  "type": "Feature",
  "properties": {
    "iso:country":"CH",
    "sg:address":"Bahnhofstrasse 16",
    "sg:city":"N\u00e4fels",
    "sg:orig_category":"Zahnarztpraxen",
    "sg:phone":"+41 71 277 86 68",
    "sg:postcode":"8752",
    "sg:province":"Glarus",
    "wof:name":"Dr. Med. Dent. Walter Maurer Zahnarzt",
    "wof:placetype":"venue"
},
  "geometry": {"coordinates":[9.3692808151,47.4073104858],"type":"Point"}
}