{
  "type": "Feature",
  "properties": {
    "iso:country":"CH",
    "sg:address":"St\u00fcssistrasse 83",
    "sg:city":"Z\u00fcrich",
    "sg:orig_category":"Werbung",
    "sg:postcode":"8057",
    "sg:province":"Z\u00fcrich",
    "wof:name":"Ruchti Info",
    "wof:placetype":"venue"
},
  "geometry": {"coordinates":[8.5410547256,47.3948554993],"type":"Point"}
}