{
  "type": "Feature",
  "properties": {
    "addr:full":"Luzernerstrasse 28 4800 Zofingen. Postfach Zofingen Aargau 4800",
    "addr:housenumber":"28",
    "addr:postcode":"4800 zofingen. postfach;4800",
    "addr:street":"Luzernerstrasse",
    "iso:country":"CH",
    "sg:address":"Luzernerstrasse 28 4800 Zofingen. Postfach",
    "sg:city":"Zofingen",
    "sg:orig_category":"Allgemeiner Hoch U Tiefbau Hoch U Tiefbau",
    "sg:phone":"+41 79 358 43 43",
    "sg:postcode":"4800",
    "sg:province":"Aargau",
    "wof:name":"H.j. Kaspar Ag",
    "wof:placetype":"venue"
},
  "geometry": {"coordinates":[7.948475,47.282654],"type":"Point"}
}