{
  "type": "Feature",
  "properties": {
    "iso:country":"CH",
    "sg:address":"Oberdorfstrasse 10",
    "sg:city":"Giffers",
    "sg:orig_category":"Allgemeiner Hoch U Tiefbau",
    "sg:postcode":"1735",
    "sg:province":"Fribourg",
    "wof:name":"Krattinger & Rogge Gmbh",
    "wof:placetype":"venue"
},
  "geometry": {"coordinates":[7.210452,46.759987],"type":"Point"}
}