{
  "type": "Feature",
  "properties": {
    "iso:country":"CH",
    "sg:address":"Via Ferri 2",
    "sg:city":"Lugano",
    "sg:orig_category":"Kunsthandel Museen",
    "sg:phone":"+41 91 923 40 69",
    "sg:postcode":"6900",
    "sg:province":"Ticino",
    "wof:name":"Fran\u00e7oise Tamo Galleria D'arte L'incontro",
    "wof:placetype":"venue"
},
  "geometry": {"coordinates":[8.9554691315,46.0144348145],"type":"Point"}
}