{
  "type": "Feature",
  "properties": {
    "iso:country":"CH",
    "sg:address":"Altgraben 436",
    "sg:city":"H\u00e4rkingen",
    "sg:orig_category":"Herstellung von Kunststoffwaren Herstellung von Metallerzeugnissen ohne Maschinenbau",
    "sg:phone":"+41 32 653 09 03",
    "sg:postcode":"4624",
    "sg:province":"Solothurn",
    "wof:name":"Rolla Microgear Ag",
    "wof:placetype":"venue"
},
  "geometry": {"coordinates":[7.3883171082,47.2019882202],"type":"Point"}
}