{
  "type": "Feature",
  "properties": {
    "iso:country":"CH",
    "sg:address":"Hauptstrasse 8885 Mols. Postfach",
    "sg:city":"Mols",
    "sg:orig_category":"Grosshandel mit Nahrungsmitteln, Getr\u00e4nken U Tabakwaren ohne ausgepr\u00e4gten Schwerpunkt",
    "sg:phone":"+41 81 710 32 11",
    "sg:postcode":"8885",
    "sg:province":"St. Gallen",
    "wof:name":"Dorfladen-lebensmittel, Isabel Robert",
    "wof:placetype":"venue"
},
  "geometry": {"coordinates":[9.2764253616,47.1129493713],"type":"Point"}
}