{
  "type": "Feature",
  "properties": {
    "iso:country":"CH",
    "sg:address":"Rue Du Bourg 7",
    "sg:city":"Moudon",
    "sg:orig_category":"Herstellung von k\u00e4lte U lufttechnischen Erzeugnissen f\u00fcr gewerbliche Zwecke",
    "sg:phone":"+41 21 905 21 53",
    "sg:postcode":"1510",
    "sg:province":"Vaud",
    "wof:name":"Mathys Arnold",
    "wof:placetype":"venue"
},
  "geometry": {"coordinates":[6.7924451828,46.669002533],"type":"Point"}
}