{
  "type": "Feature",
  "properties": {
    "iso:country":"CH",
    "sg:address":"Stockeri 14",
    "sg:city":"Risch",
    "sg:orig_category":"Grosshandel mit Holz U Baustoffen",
    "sg:phone":"+41 79 435 55 28",
    "sg:postcode":"6343",
    "sg:province":"Zug",
    "wof:name":"Luthiger Edi Gmbh",
    "wof:placetype":"venue"
},
  "geometry": {"coordinates":[8.4540081024,47.1261062622],"type":"Point"}
}