{
  "type": "Feature",
  "properties": {
    "addr:full":"Bahnhofweg 3 Hendschiken Aargau 5604",
    "addr:housenumber":"3",
    "addr:postcode":"5604",
    "addr:street":"Bahnhofweg",
    "iso:country":"CH",
    "sg:address":"Bahnhofweg 3",
    "sg:city":"Hendschiken",
    "sg:classifiers":[
        {
            "category":"Museum",
            "subcategory":"Art Museum",
            "type":"Entertainment"
        }
    ],
    "sg:phone":"+41 62 892 03 70",
    "sg:postcode":"5604",
    "sg:province":"Aargau",
    "sg:tags":[
        "artwork"
    ],
    "wof:name":"Hm-druck",
    "wof:placetype":"venue"
},
  "geometry": {"coordinates":[8.207492,47.38998],"type":"Point"}
}