{
  "type": "Feature",
  "properties": {
    "iso:country":"CH",
    "sg:address":"Immeuble Le Coteau",
    "sg:city":"Vex",
    "sg:orig_category":"Fachdetailhandel mit pharmazeutischen Produkten",
    "sg:phone":"+41 27 207 26 26",
    "sg:postcode":"1981",
    "sg:province":"Valais",
    "wof:name":"Pierre-olivier Grandjean Pharmacie De Vex",
    "wof:placetype":"venue"
},
  "geometry": {"coordinates":[7.3985052109,46.2118530273],"type":"Point"}
}