{
  "type": "Feature",
  "properties": {
    "iso:country":"CH",
    "sg:address":"Zurigo Via 5",
    "sg:city":"Lugano",
    "sg:orig_category":"Werbung",
    "sg:postcode":"6900",
    "sg:province":"Ticino",
    "wof:name":"Correct Connect Suter Werbedienstleistungen",
    "wof:placetype":"venue"
},
  "geometry": {"coordinates":[7.9256281853,47.0269317627],"type":"Point"}
}