{
  "type": "Feature",
  "properties": {
    "iso:country":"CH",
    "sg:address":"Seefeldstrasse 3",
    "sg:city":"Horw",
    "sg:orig_category":"Unclassifiable Establishments",
    "sg:postcode":"6048",
    "sg:province":"Luzern",
    "wof:name":"Piani Umberto",
    "wof:placetype":"venue"
},
  "geometry": {"coordinates":[8.3106794357,47.0129852295],"type":"Point"}
}