{
  "type": "Feature",
  "properties": {
    "iso:country":"CH",
    "sg:address":"Wil 9a",
    "sg:city":"Muotathal",
    "sg:orig_category":"Herstellung von Fenstern U T\u00fcren aus Holz Herstellung von Konstruktionsteilen, Fertigbauteilen U Aus",
    "sg:phone":"+41 41 830 12 80",
    "sg:postcode":"6436",
    "sg:province":"Schwyz",
    "wof:name":"Kopp Hugo Fensterbau Gmbh",
    "wof:placetype":"venue"
},
  "geometry": {"coordinates":[8.7556838989,46.9769172668],"type":"Point"}
}