{
  "type": "Feature",
  "properties": {
    "iso:country":"CH",
    "sg:address":"Hochr\u00fctirain 1",
    "sg:city":"Meggen",
    "sg:orig_category":"Handelsvermittlung U Grosshandel",
    "sg:phone":"+41 41 377 55 22",
    "sg:postcode":"6045",
    "sg:province":"Luzern",
    "wof:name":"K\u00fchnel Agentur Internationale Vertretungen",
    "wof:placetype":"venue"
},
  "geometry": {"coordinates":[8.363319397,47.0505065918],"type":"Point"}
}