{
  "type": "Feature",
  "properties": {
    "iso:country":"CH",
    "sg:address":"Antonio Via Sant 7",
    "sg:city":"Locarno",
    "sg:orig_category":"Erschliessung von Grundst\u00fccken",
    "sg:postcode":"6600",
    "sg:province":"Ticino",
    "wof:name":"Cooperativa Ecohabitat",
    "wof:placetype":"venue"
},
  "geometry": {"coordinates":[8.7912330627,46.1695022583],"type":"Point"}
}