{
  "type": "Feature",
  "properties": {
    "iso:country":"CH",
    "sg:address":"Pont Crittin 12",
    "sg:city":"Chamoson",
    "sg:classifiers":[
        {
            "category":"Restaurant",
            "type":"Food & Drink"
        }
    ],
    "sg:phone":"+41 27 306 22 96",
    "sg:postcode":"1955",
    "sg:province":"Valais",
    "wof:name":"Caf\u00e9 Lion-d'or",
    "wof:placetype":"venue"
},
  "geometry": {"coordinates":[7.2153820992,46.2068634033],"type":"Point"}
}