{
  "type": "Feature",
  "properties": {
    "iso:country":"CH",
    "sg:address":"Im Langen Loh 231",
    "sg:city":"Basel",
    "sg:orig_category":"Non-Classified Establishments",
    "sg:postcode":"4054",
    "sg:province":"Basel-Stadt",
    "wof:name":"Bowi-holding Ag",
    "wof:placetype":"venue"
},
  "geometry": {"coordinates":[7.5603342056,47.5484886169],"type":"Point"}
}