{
  "type": "Feature",
  "properties": {
    "iso:country":"CH",
    "sg:address":"Heusser-staub-strasse 2",
    "sg:city":"Uster",
    "sg:classifiers":[
        {
            "category":"Professional",
            "subcategory":"Employment Agencies",
            "type":"Services"
        }
    ],
    "sg:phone":"+41 55 246 67 77",
    "sg:postcode":"8610",
    "sg:province":"Z\u00fcrich",
    "sg:tags":[
        "personal",
        "u",
        "stellenvermittlung"
    ],
    "wof:name":"United Models Modell-agentur",
    "wof:placetype":"venue"
},
  "geometry": {"coordinates":[8.9318304062,47.2663764954],"type":"Point"}
}