{
  "type": "Feature",
  "properties": {
    "addr:full":"Industriestrasse 27 Kerzers Fribourg 3210",
    "addr:housenumber":"27",
    "addr:postcode":"3210",
    "addr:street":"Industriestrasse",
    "iso:country":"CH",
    "sg:address":"Industriestrasse 27",
    "sg:city":"Kerzers",
    "sg:orig_category":"Cigar Humidors And Humidor Cabinets",
    "sg:phone":"+41 32 925 09 09",
    "sg:postcode":"3210",
    "sg:province":"Fribourg",
    "wof:name":"Setco La Chaux-de-fonds Sa Manufactures",
    "wof:placetype":"venue"
},
  "geometry": {"coordinates":[6.815451,47.096363],"type":"Point"}
}