{
  "type": "Feature",
  "properties": {
    "iso:country":"CH",
    "sg:address":"Schachenstrasse 6 6010 Kriens. Postfach 368",
    "sg:city":"Kriens",
    "sg:orig_category":"Kantonalbanken",
    "sg:phone":"+41 41 206 36 36",
    "sg:postcode":"6011",
    "sg:province":"Luzern",
    "wof:name":"Luzerner Kantonalbank",
    "wof:placetype":"venue"
},
  "geometry": {"coordinates":[8.2793092728,47.0346031189],"type":"Point"}
}