{
  "type": "Feature",
  "properties": {
    "iso:country":"CH",
    "sg:address":"Ziindli",
    "sg:city":"Brienzwiler",
    "sg:orig_category":"Instandhaltung U Reparatur von Automobilen",
    "sg:phone":"+41 33 951 31 44",
    "sg:postcode":"3856",
    "sg:province":"Bern",
    "wof:name":"Br\u00fcnig-garage Ag",
    "wof:placetype":"venue"
},
  "geometry": {"coordinates":[8.0988349915,46.7478599548],"type":"Point"}
}