{
  "type": "Feature",
  "properties": {
    "iso:country":"CH",
    "sg:address":"Brenden",
    "sg:city":"Appenzell",
    "sg:orig_category":"Vermietung U Verpachtung von eigenen Immobilien",
    "sg:postcode":"9050",
    "sg:province":"Appenzell Innerhoden",
    "wof:name":"Bermotop Ag",
    "wof:placetype":"venue"
},
  "geometry": {"coordinates":[9.4282398224,47.3565788269],"type":"Point"}
}