{
  "type": "Feature",
  "properties": {
    "iso:country":"CH",
    "sg:address":"Cardada",
    "sg:city":"Locarno",
    "sg:orig_category":"RESTAURANTS: TEA-ROOMS",
    "sg:postcode":"6600",
    "sg:province":"Ticino",
    "wof:name":"Arranz Maximo",
    "wof:placetype":"venue"
},
  "geometry": {"coordinates":[8.7804613113,46.189414978],"type":"Point"}
}