{
  "type": "Feature",
  "properties": {
    "iso:country":"CH",
    "sg:address":"Oberneuhofstrasse 3",
    "sg:city":"Baar",
    "sg:orig_category":"Vermietung U Verpachtung von eigenen Immobilien",
    "sg:postcode":"6340",
    "sg:province":"Zug",
    "wof:name":"Valanex Ag",
    "wof:placetype":"venue"
},
  "geometry": {"coordinates":[8.5156602859,47.1887626648],"type":"Point"}
}