{
  "type": "Feature",
  "properties": {
    "iso:country":"CH",
    "sg:address":"Marktgasse 16",
    "sg:city":"B\u00fclach",
    "sg:orig_category":"Fachdetailhandel in Verkaufsr\u00e4umen",
    "sg:phone":"+41 18622062",
    "sg:postcode":"8180",
    "sg:province":"Z\u00fcrich",
    "wof:name":"Fleurs Reichenbach & Co",
    "wof:placetype":"venue"
},
  "geometry": {"coordinates":[8.5407848358,47.5182418823],"type":"Point"}
}