{
  "type": "Feature",
  "properties": {
    "iso:country":"CH",
    "sg:address":"Bergstrasse 18",
    "sg:city":"Aarau",
    "sg:orig_category":"Datenverarbeitungsdienste Softwareentwicklung U beratung",
    "sg:phone":"+41 62 825 03 83",
    "sg:postcode":"5000",
    "sg:province":"Aargau",
    "wof:name":"Jan Trnka Software-entwickl.& Beratung",
    "wof:placetype":"venue"
},
  "geometry": {"coordinates":[8.046658,47.382866],"type":"Point"}
}