{
  "type": "Feature",
  "properties": {
    "iso:country":"CH",
    "sg:address":"Rue Arnold Winkelried 6",
    "sg:city":"Gen\u00e8ve",
    "sg:orig_category":"Detailhandel mit Uhren U Schmuck Fachdetailhandel in Verkaufsr\u00e4umen",
    "sg:phone":"+41 22 731 51 30",
    "sg:postcode":"1201",
    "sg:province":"Gen\u00e8ve",
    "wof:name":"Bijouterie-joaillier Racloz Fabian",
    "wof:placetype":"venue"
},
  "geometry": {"coordinates":[6.1462807655,46.2072296143],"type":"Point"}
}