{
  "type": "Feature",
  "properties": {
    "addr:full":"Efringerstrasse 25 Basel Basel-Stadt 4057",
    "addr:housenumber":"25",
    "addr:postcode":"4057",
    "addr:street":"Efringerstrasse",
    "iso:country":"CH",
    "sg:address":"Efringerstrasse 25",
    "sg:city":"Basel",
    "sg:orig_category":"Architektur U Ingenieurb\u00fcros Architekturb\u00fcros",
    "sg:phone":"+41 61 693 46 56",
    "sg:postcode":"4057",
    "sg:province":"Basel-Stadt",
    "wof:name":"Bollinger Architekten Ag",
    "wof:placetype":"venue"
},
  "geometry": {"coordinates":[7.596097,47.568661],"type":"Point"}
}