{
  "type": "Feature",
  "properties": {
    "addr:full":"Avenue Des Sports 42 Yverdon-les-bains Vaud 1400",
    "addr:housenumber":"42",
    "addr:postcode":"1400",
    "addr:street":"Avenue Des Sports",
    "iso:country":"CH",
    "sg:address":"Avenue Des Sports 42",
    "sg:city":"Yverdon-les-bains",
    "sg:classifiers":[
        {
            "category":"Structure",
            "subcategory":"Factory",
            "type":"Public Place"
        }
    ],
    "sg:phone":"+41 24 423 71 11",
    "sg:postcode":"1400",
    "sg:province":"Vaud",
    "sg:tags":[
        "plant",
        "manufacturing",
        "component",
        "cd"
    ],
    "wof:name":"4 M Systems Sa",
    "wof:placetype":"venue"
},
  "geometry": {"coordinates":[6.653197,46.780018],"type":"Point"}
}