{
  "type": "Feature",
  "properties": {
    "iso:country":"CH",
    "sg:address":"B\u00fcfelderstrasse 1",
    "sg:city":"Sirnach",
    "sg:orig_category":"Detailhandel mit Metallwaren, Anstrichmitteln, Glaswaren, Bau U Heimwerkerbedarf",
    "sg:postcode":"8370",
    "sg:province":"Thurgau",
    "wof:name":"Intermech, P. Kellenberger",
    "wof:placetype":"venue"
},
  "geometry": {"coordinates":[8.9874296188,47.4566040039],"type":"Point"}
}