{
  "type": "Feature",
  "properties": {
    "addr:full":"Chemin Du Vigneron 16 Pully Vaud 1009",
    "addr:housenumber":"16",
    "addr:postcode":"1009",
    "addr:street":"Chemin Du Vigneron",
    "iso:country":"CH",
    "sg:address":"Chemin Du Vigneron 16",
    "sg:city":"Pully",
    "sg:orig_category":"Architektur U Ingenieurb\u00fcros",
    "sg:phone":"+41 21 728 59 67",
    "sg:postcode":"1009",
    "sg:province":"Vaud",
    "wof:name":"Bsa Ing\u00e9nieurs Conseils",
    "wof:placetype":"venue"
},
  "geometry": {"coordinates":[6.668978,46.512516],"type":"Point"}
}