{
  "type": "Feature",
  "properties": {
    "iso:country":"CH",
    "sg:address":"Avenue D'echallens 38",
    "sg:city":"Lausanne",
    "sg:orig_category":"Bauspenglerei Sanit\u00e4r, Heizungs U L\u00fcftungsinstallation",
    "sg:phone":"+41 21 624 67 36",
    "sg:postcode":"1004",
    "sg:province":"Vaud",
    "wof:name":"Gremper Roger Sa",
    "wof:placetype":"venue"
},
  "geometry": {"coordinates":[6.61873,46.533489],"type":"Point"}
}