{
  "type": "Feature",
  "properties": {
    "iso:country":"CH",
    "sg:address":"Signalstrasse 15 9400 Rorschach. Postfach 113",
    "sg:city":"Rorschach",
    "sg:orig_category":"Interessenvertretungen U sonstige Vereinigungen Sonstige Institutionen des Sozialwesens ohne Beherbe",
    "sg:phone":"+41 71 222 22 33",
    "sg:postcode":"9401",
    "sg:province":"St. Gallen",
    "wof:name":"Budgetberatungsstelle Der Frauenzentr.des Kts St.gallen",
    "wof:placetype":"venue"
},
  "geometry": {"coordinates":[9.3723211288,47.4216766357],"type":"Point"}
}