{
  "type": "Feature",
  "properties": {
    "iso:country":"CH",
    "sg:address":"Rue Du Grand-pont 9",
    "sg:city":"Orbe",
    "sg:orig_category":"Detailhandel mit Ton U Bildtr\u00e4gern Detailhandel mit elektrischen Haushalts-,Radio U Fernsehger\u00e4ten s",
    "sg:phone":"+41 56 441 21 40",
    "sg:postcode":"1350",
    "sg:province":"Vaud",
    "wof:name":"Ingold Musik Ag",
    "wof:placetype":"venue"
},
  "geometry": {"coordinates":[8.2084093094,47.482334137],"type":"Point"}
}