{
  "type": "Feature",
  "properties": {
    "iso:country":"CH",
    "sg:address":"Steinenweg 36",
    "sg:city":"Zunzgen",
    "sg:orig_category":"Fahrschulen, Flugschulen",
    "sg:phone":"+41 79 408 89 88",
    "sg:postcode":"4455",
    "sg:province":"Basel-Landschaft",
    "wof:name":"Peter Buser Autofahrschule",
    "wof:placetype":"venue"
},
  "geometry": {"coordinates":[7.8040771484,47.454875946],"type":"Point"}
}