{
  "type": "Feature",
  "properties": {
    "iso:country":"CH",
    "sg:address":"Bernstrasse 71",
    "sg:city":"Kehrsatz",
    "sg:orig_category":"Verlagsgewerbe",
    "sg:phone":"+41 31 961 04 08",
    "sg:postcode":"3122",
    "sg:province":"Bern",
    "wof:name":"Samuel Klopfenstein Spenglerei",
    "wof:placetype":"venue"
},
  "geometry": {"coordinates":[7.468378067,46.9133911133],"type":"Point"}
}