{
  "type": "Feature",
  "properties": {
    "iso:country":"CH",
    "sg:address":"6163",
    "sg:city":"Ebnet",
    "sg:orig_category":"S\u00e4gewerke",
    "sg:phone":"+41 41 480 14 49",
    "sg:postcode":"6163",
    "sg:province":"Luzern",
    "wof:name":"Markus Schmid S\u00e4gerei",
    "wof:placetype":"venue"
},
  "geometry": {"coordinates":[8.0784502029,47.0232696533],"type":"Point"}
}