{
  "type": "Feature",
  "properties": {
    "iso:country":"CH",
    "sg:address":"Neugutstrasse 58",
    "sg:city":"D\u00fcbendorf",
    "sg:orig_category":"Pensionskassen",
    "sg:phone":"+41 71 223 15 15",
    "sg:postcode":"8600",
    "sg:province":"Z\u00fcrich",
    "wof:name":"Wohlfahrtsfonds Der Industrie Und Handelskammer St. Gallen-appenzell",
    "wof:placetype":"venue"
},
  "geometry": {"coordinates":[9.3760471344,47.4235725403],"type":"Point"}
}