{
  "type": "Feature",
  "properties": {
    "iso:country":"CH",
    "sg:address":"Baarerstrasse 38",
    "sg:city":"Zug",
    "sg:orig_category":"Unclassifiable Establishments",
    "sg:postcode":"6300",
    "sg:province":"Zug",
    "wof:name":"Crossmedia International Ag",
    "wof:placetype":"venue"
},
  "geometry": {"coordinates":[8.5171451569,47.1743965149],"type":"Point"}
}