{
  "type": "Feature",
  "properties": {
    "iso:country":"CH",
    "sg:address":"Bahnhofstr. 12",
    "sg:city":"Lyss",
    "sg:classifiers":[
        {
            "category":"Banks & Credit Unions",
            "subcategory":"Bank",
            "type":"Services"
        }
    ],
    "sg:phone":"+41 32844181",
    "sg:postcode":"3250",
    "sg:province":"Bern",
    "wof:name":"Schweizerische Volksbank",
    "wof:placetype":"venue"
},
  "geometry": {"coordinates":[7.306301,47.076031],"type":"Point"}
}