{
  "type": "Feature",
  "properties": {
    "iso:country":"CH",
    "sg:address":"Via S.giorgio 29",
    "sg:city":"Castagnola",
    "sg:classifiers":[
        {
            "category":"Social Services",
            "subcategory":"Retirement Home",
            "type":"Services"
        }
    ],
    "sg:phone":"+41 91 971 18 46",
    "sg:postcode":"6976",
    "sg:province":"Ticino",
    "sg:tags":[
        "pflegeheime",
        "u",
        "alters"
    ],
    "wof:name":"Residenza Al Castagneto Casa Per Anziani",
    "wof:placetype":"venue"
},
  "geometry": {"coordinates":[8.976751,46.002464],"type":"Point"}
}