{
  "type": "Feature",
  "properties": {
    "addr:full":"Dorf Wangelen Bern 3615",
    "addr:postcode":"3615",
    "addr:street":"Dorf",
    "iso:country":"CH",
    "sg:address":"Dorf",
    "sg:city":"Wangelen",
    "sg:orig_category":"Detailhandel mit Brot, Back U S\u00fcsswaren Detailhandel mit Waren verschiedener Art, Hauptrichtung Nahr",
    "sg:phone":"+41 33 453 13 25",
    "sg:postcode":"3615",
    "sg:province":"Bern",
    "wof:name":"Alfred Eymann",
    "wof:placetype":"venue"
},
  "geometry": {"coordinates":[7.696945,46.828621],"type":"Point"}
}