{
  "type": "Feature",
  "properties": {
    "iso:country":"CH",
    "sg:address":"R\u00f6merstr. 27",
    "sg:city":"Hallau",
    "sg:orig_category":"Metallurgy and Metalworking Precision Equipment Timekeeping equipement Tools",
    "sg:phone":"+41 22 342 23 55",
    "sg:postcode":"8215",
    "sg:province":"Schaffhausen",
    "wof:name":"Fiedler Sa",
    "wof:placetype":"venue"
},
  "geometry": {"coordinates":[6.137845993,46.1792564392],"type":"Point"}
}