{
  "type": "Feature",
  "properties": {
    "iso:country":"CH",
    "sg:address":"Rue De L'avenir 14",
    "sg:city":"Court\u00e9telle",
    "sg:orig_category":"Grosshandel mit lebenden Tieren",
    "sg:phone":"+41 32 422 28 66",
    "sg:postcode":"2852",
    "sg:province":"Jura",
    "wof:name":"Jean Lauper Commerce De B\u00e9tail",
    "wof:placetype":"venue"
},
  "geometry": {"coordinates":[7.3279891014,47.3484382629],"type":"Point"}
}