{
  "type": "Feature",
  "properties": {
    "iso:country":"CH",
    "sg:address":"Bottigenstrasse 217b",
    "sg:city":"Bern",
    "sg:orig_category":"Bauschreinerei Zimmerei, Ingenieurholzbau",
    "sg:phone":"+41 31 926 20 16",
    "sg:postcode":"3019",
    "sg:province":"Bern",
    "wof:name":"Gerber Holzbau Bern Ag",
    "wof:placetype":"venue"
},
  "geometry": {"coordinates":[7.361123,46.936184],"type":"Point"}
}