{
  "type": "Feature",
  "properties": {
    "iso:country":"CH",
    "sg:address":"Bahnhofstrasse 16 2502 Biel/bienne Case Postale 842",
    "sg:city":"Biel/bienne",
    "sg:orig_category":"Detailhandel mit Herrenbekleidung Herstellung von Oberbekleidung",
    "sg:phone":"+41 32 931 17 20",
    "sg:postcode":"2501",
    "sg:province":"Bern",
    "wof:name":"Frutiger Confection",
    "wof:placetype":"venue"
},
  "geometry": {"coordinates":[6.7502918243,47.0581245422],"type":"Point"}
}