{
  "type": "Feature",
  "properties": {
    "iso:country":"CH",
    "sg:address":"1914",
    "sg:city":"Is\u00e9rables",
    "sg:orig_category":"K\u00fcnstlerische U schriftstellerische T\u00e4tigkeiten U Darbietungen",
    "sg:postcode":"1914",
    "sg:province":"Valais",
    "wof:name":"Soci\u00e9t\u00e9 De Musique L'avenir, Is\u00e9rables",
    "wof:placetype":"venue"
},
  "geometry": {"coordinates":[7.24518013,46.1604385376],"type":"Point"}
}