{
  "type": "Feature",
  "properties": {
    "iso:country":"CH",
    "sg:address":"6997",
    "sg:city":"Sessa",
    "sg:classifiers":[
        {
            "category":"Education",
            "subcategory":"Library",
            "type":"Public Place"
        }
    ],
    "sg:postcode":"6997",
    "sg:province":"Ticino",
    "sg:tags":[
        "u",
        "bibliotheken",
        "archive"
    ],
    "wof:name":"Biblioteca Popolare Parrocchiale",
    "wof:placetype":"venue"
},
  "geometry": {"coordinates":[8.81177,46.002399],"type":"Point"}
}