{
  "type": "Feature",
  "properties": {
    "iso:country":"CH",
    "sg:address":"Milit\u00e4rstrasse 3",
    "sg:city":"Obfelden",
    "sg:orig_category":"Pers\u00f6nliche Dienstleistungen Sonstige mit Sport verbundene T\u00e4tigkeiten",
    "sg:phone":"+41 17600571",
    "sg:postcode":"8912",
    "sg:province":"Z\u00fcrich",
    "wof:name":"Shindo Schule F\u00fcr Tai Ji Und Kampfkunst Jansch",
    "wof:placetype":"venue"
},
  "geometry": {"coordinates":[8.4152879715,47.260925293],"type":"Point"}
}