{
  "type": "Feature",
  "properties": {
    "iso:country":"CH",
    "sg:address":"Champsec",
    "sg:city":"Verseg\u00e8res",
    "sg:orig_category":"Erdbewegungsarbeiten G\u00fcterbef\u00f6rderung im Strassenverkehr",
    "sg:phone":"+41 27 778 15 42",
    "sg:postcode":"1947",
    "sg:province":"Valais",
    "wof:name":"Samuel Rossier Multibennes & Grue",
    "wof:placetype":"venue"
},
  "geometry": {"coordinates":[7.2268300056,46.0673789978],"type":"Point"}
}