{
  "type": "Feature",
  "properties": {
    "iso:country":"CH",
    "sg:address":"Alte Landstrasse 37",
    "sg:city":"Obfelden",
    "sg:orig_category":"Primarschulen",
    "sg:phone":"+41 17611874",
    "sg:postcode":"8912",
    "sg:province":"Z\u00fcrich",
    "wof:name":"Primarschule Schloss\u00e4cher",
    "wof:placetype":"venue"
},
  "geometry": {"coordinates":[8.4291801453,47.2664451599],"type":"Point"}
}