{
  "type": "Feature",
  "properties": {
    "iso:country":"CH",
    "sg:address":"Obergasse 35",
    "sg:city":"Siebnen",
    "sg:orig_category":"Herstellung von Teppichen",
    "sg:phone":"+41 55 440 19 87",
    "sg:postcode":"8854",
    "sg:province":"Schwyz",
    "wof:name":"M\u00e4chler Josef Ag",
    "wof:placetype":"venue"
},
  "geometry": {"coordinates":[8.8752202988,47.1823310852],"type":"Point"}
}