{
  "type": "Feature",
  "properties": {
    "iso:country":"CH",
    "sg:address":"Monbijoustrasse 74",
    "sg:city":"Bern",
    "sg:orig_category":"Datenverarbeitungsdienste",
    "sg:phone":"+41 31 325 90 11",
    "sg:postcode":"3005",
    "sg:province":"Bern",
    "wof:name":"Bundesamt F\u00fcr Informatik & Telekommunikation Bit",
    "wof:placetype":"venue"
},
  "geometry": {"coordinates":[7.44577,46.939957],"type":"Point"}
}