{
  "type": "Feature",
  "properties": {
    "iso:country":"CH",
    "sg:address":"Bahnhofstrasse 131",
    "sg:city":"M\u00f6hlin",
    "sg:orig_category":"Pensionskassen",
    "sg:phone":"+41 61 851 42 42",
    "sg:postcode":"4313",
    "sg:province":"Aargau",
    "wof:name":"Personalf\u00fcrsorgestiftung Der Ernst Weidmann Ag",
    "wof:placetype":"venue"
},
  "geometry": {"coordinates":[7.8520321846,47.5527114868],"type":"Point"}
}