{
  "type": "Feature",
  "properties": {
    "iso:country":"CH",
    "sg:address":"Hauptstrasse",
    "sg:city":"Uerkheim",
    "sg:orig_category":"Gasth\u00f6fe/Gasth\u00e4user mit Restaurant",
    "sg:phone":"+41 62 721 17 66",
    "sg:postcode":"4813",
    "sg:province":"Aargau",
    "wof:name":"Gasthof Sonne",
    "wof:placetype":"venue"
},
  "geometry": {"coordinates":[8.0254392624,47.3068161011],"type":"Point"}
}