{
  "type": "Feature",
  "properties": {
    "iso:country":"CH",
    "sg:address":"Voa Nova 28",
    "sg:city":"Vaz/obervaz",
    "sg:classifiers":[
        {
            "category":"Restaurant",
            "type":"Food & Drink"
        }
    ],
    "sg:phone":"+41 61 751 12 11",
    "sg:postcode":"7082",
    "sg:province":"Graubunden",
    "wof:name":"Restaurant Jura",
    "wof:placetype":"venue"
},
  "geometry": {"coordinates":[7.6002092361,47.4675483704],"type":"Point"}
}