{
  "type": "Feature",
  "properties": {
    "iso:country":"CH",
    "sg:address":"Plazza Cumin 3 7130 Ilanz. Postfach",
    "sg:city":"Ilanz",
    "sg:orig_category":"Detailhandel mit Blumen U Pflanzen Fachdetailhandel in Verkaufsr\u00e4umen",
    "sg:phone":"+41 81 925 44 48",
    "sg:postcode":"7130",
    "sg:province":"Graubunden",
    "wof:name":"Fluras Candinas",
    "wof:placetype":"venue"
},
  "geometry": {"coordinates":[9.204547,46.774448],"type":"Point"}
}