{
  "type": "Feature",
  "properties": {
    "iso:country":"CH",
    "sg:address":"1618",
    "sg:city":"Ch\u00e2tel-st-denis",
    "sg:orig_category":"Landw. Genossenschaften Viehzucht",
    "sg:phone":"+41 56 668 18 07",
    "sg:postcode":"1618",
    "sg:province":"Fribourg",
    "wof:name":"Verband Aargauischer Braunviehzuchtgenossenschaften",
    "wof:placetype":"venue"
},
  "geometry": {"coordinates":[8.3290014267,47.2315940857],"type":"Point"}
}