{
  "type": "Feature",
  "properties": {
    "iso:country":"CH",
    "sg:address":"Avenue Reverdil 6 1260 Nyon Case Postale 36",
    "sg:city":"Nyon",
    "sg:orig_category":"Versicherungen Generalagenturen",
    "sg:phone":"+41 22 311 51 33",
    "sg:postcode":"1260",
    "sg:province":"Vaud",
    "wof:name":"Allianz Suisse Agence G\u00e9n\u00e9rale",
    "wof:placetype":"venue"
},
  "geometry": {"coordinates":[6.1522989273,46.2016220093],"type":"Point"}
}