{
  "type": "Feature",
  "properties": {
    "addr:full":"Rugenaustrasse 1 3800 Interlaken. Postfach 556 Interlaken Bern 3800",
    "addr:housenumber":"1;556",
    "addr:postcode":"3800;3800",
    "addr:street":"Rugenaustrasse;Postfach",
    "iso:country":"CH",
    "sg:address":"Rugenaustrasse 1 3800 Interlaken. Postfach 556",
    "sg:city":"Interlaken",
    "sg:orig_category":"Detailhandel mit Bekleidung Textilveredlung",
    "sg:phone":"+41 56 442 32 87",
    "sg:postcode":"3800",
    "sg:province":"Bern",
    "wof:name":"Josy's T'shirt, Hartmann J.",
    "wof:placetype":"venue"
},
  "geometry": {"coordinates":[8.22698,47.496826],"type":"Point"}
}