{
  "type": "Feature",
  "properties": {
    "iso:country":"CH",
    "sg:address":"Selfrangastrasse 36",
    "sg:city":"Klosters",
    "sg:orig_category":"Korrespondenz U Nachrichtenb\u00fcros Unternehmensberatung",
    "sg:phone":"+41 81 422 55 26",
    "sg:postcode":"7250",
    "sg:province":"Graubunden",
    "wof:name":"Redaktion Heizung Klima",
    "wof:placetype":"venue"
},
  "geometry": {"coordinates":[9.8827190399,46.8626556396],"type":"Point"}
}