{
  "type": "Feature",
  "properties": {
    "iso:country":"CH",
    "sg:address":"Industriestrasse 16",
    "sg:city":"Neuheim",
    "sg:orig_category":"G\u00fcterbef\u00f6rderung im Strassenverkehr",
    "sg:phone":"+41 41 755 22 44",
    "sg:postcode":"6345",
    "sg:province":"Zug",
    "wof:name":"K\u00fcnzle Meinrad Ag",
    "wof:placetype":"venue"
},
  "geometry": {"coordinates":[8.5791292191,47.2030410767],"type":"Point"}
}