{
  "type": "Feature",
  "properties": {
    "iso:country":"CH",
    "sg:address":"Unterneuhaus 461",
    "sg:city":"Wilchingen",
    "sg:orig_category":"Herstellung von sonstigen elektrischen Ausr\u00fcstungen",
    "sg:postcode":"8217",
    "sg:province":"Schaffhausen",
    "wof:name":"Cfr Electronics K\u00fclling",
    "wof:placetype":"venue"
},
  "geometry": {"coordinates":[8.4580850601,47.6777076721],"type":"Point"}
}