{
  "type": "Feature",
  "properties": {
    "iso:country":"CH",
    "sg:address":"Goldgasse 14",
    "sg:city":"Balsthal",
    "sg:orig_category":"Sonstige Finanzierungsinstitutionen Vermietung U Verpachtung von eigenen Immobilien",
    "sg:phone":"+41 62 391 26 71",
    "sg:postcode":"4710",
    "sg:province":"Solothurn",
    "wof:name":"Sipar Immobilien Und Beteiligungen Ag",
    "wof:placetype":"venue"
},
  "geometry": {"coordinates":[7.696313858,47.3170204163],"type":"Point"}
}