{
  "type": "Feature",
  "properties": {
    "iso:country":"CH",
    "sg:address":"Ettenberg 233",
    "sg:city":"Schwellbrunn",
    "sg:orig_category":"G\u00fcterbef\u00f6rderung im Strassenverkehr",
    "sg:postcode":"9103",
    "sg:province":"Appenzell Ausserrhoden",
    "wof:name":"Jakob Alder, Transporte",
    "wof:placetype":"venue"
},
  "geometry": {"coordinates":[9.2559213638,47.3356513977],"type":"Point"}
}