{
  "type": "Feature",
  "properties": {
    "iso:country":"CH",
    "sg:address":"Avenue Ritz 29",
    "sg:city":"Sion",
    "sg:orig_category":"Kosmetikinstitute",
    "sg:phone":"+41 27 323 38 00",
    "sg:postcode":"1950",
    "sg:province":"Valais",
    "wof:name":"Abcasia Institut De Beaut\u00e9",
    "wof:placetype":"venue"
},
  "geometry": {"coordinates":[7.359539032,46.2355918884],"type":"Point"}
}