{
  "type": "Feature",
  "properties": {
    "iso:country":"CH",
    "sg:address":"Haus Guggenbiel 3920 Zermatt. Postfach",
    "sg:city":"Zermatt",
    "sg:orig_category":"Reiseb\u00fcros U Reiseveranstalter",
    "sg:phone":"+41 27 967 53 50",
    "sg:postcode":"3920",
    "sg:province":"Valais",
    "wof:name":"Perrig Amad\u00e9 Dienstleistungen, Bes. Im Bereich Tourismus",
    "wof:placetype":"venue"
},
  "geometry": {"coordinates":[7.7484002113,46.024143219],"type":"Point"}
}