{
  "type": "Feature",
  "properties": {
    "iso:country":"CH",
    "sg:address":"Dorfplatz",
    "sg:city":"Scharans",
    "sg:orig_category":"Herstellung von Konstruktionsteilen, Fertigbauteilen U Ausbauelementen aus Holz",
    "sg:phone":"+41 81 651 29 40",
    "sg:postcode":"7412",
    "sg:province":"Graubunden",
    "wof:name":"Caduff Chr.",
    "wof:placetype":"venue"
},
  "geometry": {"coordinates":[9.4582271576,46.716796875],"type":"Point"}
}