{
  "type": "Feature",
  "properties": {
    "iso:country":"CH",
    "sg:address":"Schaub Rue 1 1202 Gen\u00e8ve. Postfach",
    "sg:city":"Gen\u00e8ve",
    "sg:orig_category":"Herstellung von sonstigen Erzeugnissen",
    "sg:postcode":"1202",
    "sg:province":"Gen\u00e8ve",
    "wof:name":"Socap Besi Vertrieb, Simone Paolo",
    "wof:placetype":"venue"
},
  "geometry": {"coordinates":[8.1829442978,47.2516403198],"type":"Point"}
}