{
  "type": "Feature",
  "properties": {
    "iso:country":"CH",
    "sg:address":"Tiergarten 35",
    "sg:city":"Burgdorf",
    "sg:orig_category":"Bauingenieurb\u00fcros Hochbau Bauingenieurb\u00fcros allgemein",
    "sg:phone":"+41 34 422 31 72",
    "sg:postcode":"3400",
    "sg:province":"Bern",
    "wof:name":"Wenger & Born Ag Ingenieurb\u00fcro",
    "wof:placetype":"venue"
},
  "geometry": {"coordinates":[7.615455,47.061897],"type":"Point"}
}