{
  "type": "Feature",
  "properties": {
    "iso:country":"CH",
    "sg:address":"Staldernstr. 10",
    "sg:city":"Hochfelden",
    "sg:orig_category":"Softwareentwicklung U beratung",
    "sg:phone":"+41 18620619",
    "sg:postcode":"8182",
    "sg:province":"Z\u00fcrich",
    "wof:name":"Sic B\u00fchler",
    "wof:placetype":"venue"
},
  "geometry": {"coordinates":[8.513384819,47.5230484009],"type":"Point"}
}