{
  "type": "Feature",
  "properties": {
    "iso:country":"CH",
    "sg:address":"Hochhausstrasse 4",
    "sg:city":"Sarnen",
    "sg:orig_category":"Unclassifiable Establishments",
    "sg:phone":"+41 17864384",
    "sg:postcode":"6060",
    "sg:province":"Obwalden",
    "wof:name":"Bucher G\u00e4rten",
    "wof:placetype":"venue"
},
  "geometry": {"coordinates":[8.7366437912,47.2040557861],"type":"Point"}
}