{
  "type": "Feature",
  "properties": {
    "iso:country":"CH",
    "sg:address":"Rue Chasse-coq 4-6",
    "sg:city":"Gen\u00e8ve",
    "sg:orig_category":"Detailhandel mit Waren verschiedener Art, Hauptrichtung Nahrungsmittel",
    "sg:phone":"+41 22 311 03 10",
    "sg:postcode":"1204",
    "sg:province":"Gen\u00e8ve",
    "wof:name":"Jaquier Christian",
    "wof:placetype":"venue"
},
  "geometry": {"coordinates":[6.1485881805,46.1994438171],"type":"Point"}
}