{
  "type": "Feature",
  "properties": {
    "iso:country":"CH",
    "sg:address":"R\u00fcdli 248",
    "sg:city":"Wattenwil",
    "sg:orig_category":"Gartenbau Landschaftsplanungsb\u00fcros U Gartenarchitekturb\u00fcros",
    "sg:postcode":"3665",
    "sg:province":"Bern",
    "wof:name":"Boschung Eric",
    "wof:placetype":"venue"
},
  "geometry": {"coordinates":[6.0884099007,46.2410812378],"type":"Point"}
}