{
  "type": "Feature",
  "properties": {
    "iso:country":"CH",
    "sg:address":"Seestrasse 202",
    "sg:city":"Horgen",
    "sg:orig_category":"Grosshandel mit Datenverarbeitungsger\u00e4ten Grosshandel mit Software",
    "sg:phone":"+41 22 309 00 70",
    "sg:postcode":"8810",
    "sg:province":"Z\u00fcrich",
    "wof:name":"Quadrisoft Sa R\u00e9alisations Informatique",
    "wof:placetype":"venue"
},
  "geometry": {"coordinates":[6.1458821297,46.1837043762],"type":"Point"}
}