{
  "type": "Feature",
  "properties": {
    "iso:country":"CH",
    "sg:address":"Baselstrasse 149",
    "sg:city":"Muttenz",
    "sg:orig_category":"Fahrschulen, Flugschulen",
    "sg:phone":"+41 61 461 73 12",
    "sg:postcode":"4132",
    "sg:province":"Basel-Landschaft",
    "wof:name":"Aebin Thomas",
    "wof:placetype":"venue"
},
  "geometry": {"coordinates":[7.6337571144,47.5299491882],"type":"Point"}
}