{
  "type": "Feature",
  "properties": {
    "addr:full":"Hauptstrasse Baltschieder Valais 3937",
    "addr:postcode":"3937",
    "addr:street":"Hauptstrasse",
    "iso:country":"CH",
    "sg:address":"Hauptstrasse",
    "sg:city":"Baltschieder",
    "sg:orig_category":"Darlehenskassen U Raiffeisenbanken",
    "sg:phone":"+41 62 390 15 32",
    "sg:postcode":"3937",
    "sg:province":"Valais",
    "wof:name":"Raiffeisenbank",
    "wof:placetype":"venue"
},
  "geometry": {"coordinates":[7.745925,47.3316],"type":"Point"}
}