{
  "type": "Feature",
  "properties": {
    "iso:country":"CH",
    "sg:address":"Polenstrasse 106",
    "sg:city":"Glis",
    "sg:orig_category":"Allgemeiner Hochbau Strassenbau",
    "sg:phone":"+41 27 923 17 81",
    "sg:postcode":"3902",
    "sg:province":"Valais",
    "wof:name":"Emmanuel Zenklusen & S\u00f6hne Ag Baugesch\u00e4ft",
    "wof:placetype":"venue"
},
  "geometry": {"coordinates":[7.982433,46.304527],"type":"Point"}
}