{
  "type": "Feature",
  "properties": {
    "iso:country":"CH",
    "sg:address":"Via S. Apollonia 35",
    "sg:city":"Coldrerio",
    "sg:orig_category":"Detailhandel mit Antiquit\u00e4ten U Gebrauchtwaren in Verkaufsr\u00e4umen",
    "sg:postcode":"6877",
    "sg:province":"Ticino",
    "wof:name":"Restauro Doc Sagl",
    "wof:placetype":"venue"
},
  "geometry": {"coordinates":[8.981375,45.857243],"type":"Point"}
}