{
  "type": "Feature",
  "properties": {
    "iso:country":"CH",
    "sg:address":"Gotthardstrasse 14 6300 Zug. Postfach",
    "sg:city":"Zug",
    "sg:orig_category":"Eisenbahnverkehr",
    "sg:phone":"+41 41 729 41 61",
    "sg:postcode":"6300",
    "sg:province":"Zug",
    "wof:name":"Transwaggon Ag",
    "wof:placetype":"venue"
},
  "geometry": {"coordinates":[8.5160207748,47.1721229553],"type":"Point"}
}