{
  "type": "Feature",
  "properties": {
    "iso:country":"CH",
    "sg:address":"Chemin De Vuillonnex 32",
    "sg:city":"Confignon",
    "sg:orig_category":"Bauschreinerei Herstellung von Konstruktionsteilen, Fertigbauteilen U Ausbauelementen aus Holz",
    "sg:phone":"+41 22 757 16 84",
    "sg:postcode":"1232",
    "sg:province":"Gen\u00e8ve",
    "wof:name":"Jean-claude Meyer",
    "wof:placetype":"venue"
},
  "geometry": {"coordinates":[6.080044,46.174671],"type":"Point"}
}