{
  "type": "Feature",
  "properties": {
    "iso:country":"CH",
    "sg:address":"Bahnhofstrasse 31",
    "sg:city":"Lenzburg",
    "sg:orig_category":"Unclassifiable Establishments",
    "sg:phone":"+41 62 891 27 47",
    "sg:postcode":"5600",
    "sg:province":"Aargau",
    "wof:name":"Dancing Schl\u00f6ssli + Castle-bar, A. Tschannen",
    "wof:placetype":"venue"
},
  "geometry": {"coordinates":[8.1703176498,47.3905792236],"type":"Point"}
}