{
  "type": "Feature",
  "properties": {
    "iso:country":"CH",
    "sg:address":"Untere Allmendstrasse 11 6312 Steinhausen. Postfach 36",
    "sg:city":"Steinhausen",
    "sg:orig_category":"Grosshandel mit Textilien Grosshandel mit sonstigen Nahrungsmitteln",
    "sg:postcode":"6312",
    "sg:province":"Zug",
    "wof:name":"Impex Afsar & Co",
    "wof:placetype":"venue"
},
  "geometry": {"coordinates":[8.0860996246,47.3878860474],"type":"Point"}
}