{
  "type": "Feature",
  "properties": {
    "iso:country":"CH",
    "sg:address":"Oberdorfstrasse 13",
    "sg:city":"Baar",
    "sg:orig_category":"Non-Classified Establishments",
    "sg:postcode":"6340",
    "sg:province":"Zug",
    "wof:name":"Gratien Lovey Garage Du V\u00e9lan",
    "wof:placetype":"venue"
},
  "geometry": {"coordinates":[7.1862039566,45.9914665222],"type":"Point"}
}