{
  "type": "Feature",
  "properties": {
    "iso:country":"CH",
    "sg:address":"Avenue Plantaud 1",
    "sg:city":"Monthey",
    "sg:orig_category":"Zahnarztpraxen",
    "sg:phone":"+41 24 471 61 62",
    "sg:postcode":"1870",
    "sg:province":"Valais",
    "wof:name":"Dr M\u00e9d.dent.pierre-m. Vuilloud M\u00e9decin-dentiste",
    "wof:placetype":"venue"
},
  "geometry": {"coordinates":[6.9488101006,46.251159668],"type":"Point"}
}