{
  "type": "Feature",
  "properties": {
    "iso:country":"CH",
    "sg:address":"Cornavin Rue De 1",
    "sg:city":"Gen\u00e8ve",
    "sg:orig_category":"Unclassifiable Establishments",
    "sg:postcode":"1201",
    "sg:province":"Gen\u00e8ve",
    "wof:name":"Clerici Fausto",
    "wof:placetype":"venue"
},
  "geometry": {"coordinates":[9.0241451263,45.8446044922],"type":"Point"}
}