{
  "type": "Feature",
  "properties": {
    "iso:country":"CH",
    "sg:address":"Lerchenfeldstrasse 14",
    "sg:city":"Thun",
    "sg:orig_category":"Bauschreinerei Herstellung von Konstruktionsteilen, Fertigbauteilen U Ausbauelementen aus Holz",
    "sg:phone":"+41 33 222 29 42",
    "sg:postcode":"3603",
    "sg:province":"Bern",
    "wof:name":"Ernst Sch\u00fcpbach Ag, Innenausbau & M\u00f6belschreinerei",
    "wof:placetype":"venue"
},
  "geometry": {"coordinates":[7.60411,46.767288],"type":"Point"}
}