{
  "type": "Feature",
  "properties": {
    "iso:country":"CH",
    "sg:address":"Eichenstrasse 32",
    "sg:city":"Glarus",
    "sg:classifiers":[
        {
            "category":"Home & Garden",
            "subcategory":"Kitchen Supply",
            "type":"Retail Goods"
        }
    ],
    "sg:phone":"+41 55 640 80 37",
    "sg:postcode":"8750",
    "sg:province":"Glarus",
    "sg:tags":[
        "plate",
        "ceramic"
    ],
    "wof:name":"Evasioni By Joe Vitale Gmbh",
    "wof:placetype":"venue"
},
  "geometry": {"coordinates":[9.061978,47.040298],"type":"Point"}
}