{
  "type": "Feature",
  "properties": {
    "iso:country":"CH",
    "sg:address":"Industrielle Rue 14",
    "sg:city":"Montagne-moutier",
    "sg:orig_category":"Softwareentwicklung U beratung",
    "sg:phone":"+41 32 494 55 55",
    "sg:postcode":"2740",
    "sg:province":"Bern",
    "wof:name":"Christe St\u00e8ve, Deltasoft",
    "wof:placetype":"venue"
},
  "geometry": {"coordinates":[7.3692951202,47.2775535583],"type":"Point"}
}