{
  "type": "Feature",
  "properties": {
    "iso:country":"CH",
    "sg:address":"Dorfstrasse 12",
    "sg:city":"Thayngen",
    "sg:classifiers":[
        {
            "category":"Restaurant",
            "type":"Food & Drink"
        }
    ],
    "sg:phone":"+41 52 649 33 65",
    "sg:postcode":"8240",
    "sg:province":"Schaffhausen",
    "wof:name":"Restaurant L\u00f6wen",
    "wof:placetype":"venue"
},
  "geometry": {"coordinates":[8.7091760635,47.7476387024],"type":"Point"}
}