{
  "type": "Feature",
  "properties": {
    "iso:country":"CH",
    "sg:address":"Hauptstrasse 2",
    "sg:city":"Laufen",
    "sg:orig_category":"Sonstige Institutionen des Sozialwesens ohne Beherbergung",
    "sg:phone":"+41 61 761 16 65",
    "sg:postcode":"4242",
    "sg:province":"Basel-Landschaft",
    "wof:name":"M\u00fctter-& V\u00e4terberatung Laufenthal",
    "wof:placetype":"venue"
},
  "geometry": {"coordinates":[7.5006670952,47.4210357666],"type":"Point"}
}