{
  "type": "Feature",
  "properties": {
    "iso:country":"CH",
    "sg:address":"Bourgeoisie Rue De La 17",
    "sg:city":"Sion",
    "sg:orig_category":"Instandhaltung U Reparatur von Automobilen",
    "sg:phone":"+41 32 913 43 23",
    "sg:postcode":"1950",
    "sg:province":"Valais",
    "wof:name":"Auto-\u00e9lectricit\u00e9 Winkler Sa",
    "wof:placetype":"venue"
},
  "geometry": {"coordinates":[6.8195199966,47.0994300842],"type":"Point"}
}