{
  "type": "Feature",
  "properties": {
    "iso:country":"CH",
    "sg:address":"Alpenqaui 28",
    "sg:city":"Luzern",
    "sg:classifiers":[
        {
            "category":"Manufacturing",
            "subcategory":"Building Materials",
            "type":"Manufacturing & Wholesale Goods"
        }
    ],
    "sg:phone":"+41 41 360 42 44",
    "sg:postcode":"6002",
    "sg:province":"Luzern",
    "sg:tags":[
        "glass",
        "ceramic"
    ],
    "wof:name":"Buchecker Ag",
    "wof:placetype":"venue"
},
  "geometry": {"coordinates":[8.319169,47.045486],"type":"Point"}
}