{
  "type": "Feature",
  "properties": {
    "addr:full":"S\u00e4ndli Mitl\u00f6di Glarus 8756",
    "addr:postcode":"8756",
    "addr:street":"Mitloedi Glarus",
    "iso:country":"CH",
    "sg:address":"S\u00e4ndli",
    "sg:city":"Mitl\u00f6di",
    "sg:orig_category":"Detailhandel mit Brennstoffen U Heizmaterial G\u00fcterbef\u00f6rderung im Strassenverkehr",
    "sg:phone":"+41 55 644 10 14",
    "sg:postcode":"8756",
    "sg:province":"Glarus",
    "wof:name":"Markus Kundert",
    "wof:placetype":"venue"
},
  "geometry": {"coordinates":[9.080779,47.008842],"type":"Point"}
}