{
  "type": "Feature",
  "properties": {
    "iso:country":"CH",
    "sg:address":"Via San Giorgio 11",
    "sg:city":"Castagnola",
    "sg:orig_category":"Finanzierungsinstitutionen Kauf U Verkauf von Immobilien auf eigene Rechnung",
    "sg:phone":"+41 91 971 05 93",
    "sg:postcode":"6976",
    "sg:province":"Ticino",
    "wof:name":"Builco Sa",
    "wof:placetype":"venue"
},
  "geometry": {"coordinates":[8.9738340378,46.0033836365],"type":"Point"}
}