{
  "type": "Feature",
  "properties": {
    "iso:country":"CH",
    "sg:address":"Rue Verdaine 5",
    "sg:city":"Pully",
    "sg:orig_category":"Detailhandel mit Antiquit\u00e4ten",
    "sg:phone":"+41 21 729 99 60",
    "sg:postcode":"1009",
    "sg:province":"Vaud",
    "wof:name":"Jean-fran\u00e7ois Desmeules Antiquit\u00e9s",
    "wof:placetype":"venue"
},
  "geometry": {"coordinates":[6.660421,46.510403],"type":"Point"}
}