{
  "type": "Feature",
  "properties": {
    "iso:country":"CH",
    "sg:address":"Schauenburgerstrasse 23",
    "sg:city":"Basel",
    "sg:orig_category":"Herstellung von Hebezeugen U F\u00f6rdermitteln",
    "sg:phone":"+41 61 311 22 66",
    "sg:postcode":"4052",
    "sg:province":"Basel-Stadt",
    "wof:name":"Spanlifter Ag",
    "wof:placetype":"venue"
},
  "geometry": {"coordinates":[7.6101589203,47.5550193787],"type":"Point"}
}