{
  "type": "Feature",
  "properties": {
    "iso:country":"CH",
    "sg:address":"Dorfplatz 6",
    "sg:city":"Bettlach",
    "sg:orig_category":"Sportvereine Velo Rad-& Motorfahrer-Bund SRB",
    "sg:postcode":"2544",
    "sg:province":"Solothurn",
    "wof:name":"Veloclub Aeschi",
    "wof:placetype":"venue"
},
  "geometry": {"coordinates":[7.4264760017,47.1983413696],"type":"Point"}
}