{
  "type": "Feature",
  "properties": {
    "iso:country":"CH",
    "sg:address":"Undri Matte 3920 Zermatt. Postfach",
    "sg:city":"Zermatt",
    "sg:orig_category":"RESTAURANTS: TEA-ROOMS",
    "sg:postcode":"3920",
    "sg:province":"Valais",
    "wof:name":"Restaurant Casa Rustica, Russin Harald",
    "wof:placetype":"venue"
},
  "geometry": {"coordinates":[7.7503008842,46.0251541138],"type":"Point"}
}