{
  "type": "Feature",
  "properties": {
    "addr:full":"Untere Plessurstrasse 152 Chur Graubunden 7000",
    "addr:housenumber":"152",
    "addr:postcode":"7000",
    "addr:street":"Untere Plessurstrasse",
    "iso:country":"CH",
    "sg:address":"Untere Plessurstrasse 152",
    "sg:city":"Chur",
    "sg:orig_category":"Campingpl\u00e4tze",
    "sg:phone":"+41 81 284 18 06",
    "sg:postcode":"7000",
    "sg:province":"Graubunden",
    "wof:name":"Christe & Co. Verwaltung",
    "wof:placetype":"venue"
},
  "geometry": {"coordinates":[9.51012,46.860329],"type":"Point"}
}