{
  "type": "Feature",
  "properties": {
    "iso:country":"CH",
    "sg:address":"Beau-s\u00e9jour Rue 14",
    "sg:city":"Lausanne",
    "sg:orig_category":"Herstellung von Oberbekleidung",
    "sg:phone":"+41 22 735 62 35",
    "sg:postcode":"1003",
    "sg:province":"Vaud",
    "wof:name":"Cadaval Sa",
    "wof:placetype":"venue"
},
  "geometry": {"coordinates":[6.6362018585,46.5175933838],"type":"Point"}
}