{
  "type": "Feature",
  "properties": {
    "iso:country":"CH",
    "sg:address":"Anemonenweg 6a",
    "sg:city":"Chur",
    "sg:orig_category":"Grosshandel mit M\u00f6beln, Wohnbedarf, Teppichen U Bodenbel\u00e4gen Herstellung von sonstigen M\u00f6beln",
    "sg:phone":"+41 91 646 76 20",
    "sg:postcode":"7000",
    "sg:province":"Graubunden",
    "wof:name":"Solegarden Di Micheli Angelo",
    "wof:placetype":"venue"
},
  "geometry": {"coordinates":[8.9727640152,45.8888816833],"type":"Point"}
}