{
  "type": "Feature",
  "properties": {
    "addr:full":"Zentralstrasse 60 Neuhausen Schaffhausen 8212",
    "addr:housenumber":"60",
    "addr:postcode":"8212",
    "addr:street":"Zentralstrasse",
    "iso:country":"CH",
    "sg:address":"Zentralstrasse 60",
    "sg:city":"Neuhausen",
    "sg:orig_category":"Detailhandel mit Bekleidung",
    "sg:postcode":"8212",
    "sg:province":"Schaffhausen",
    "wof:name":"Rhyfall Mode Ag",
    "wof:placetype":"venue"
},
  "geometry": {"coordinates":[8.620612,47.682201],"type":"Point"}
}