{
  "type": "Feature",
  "properties": {
    "iso:country":"CH",
    "sg:address":"1784",
    "sg:city":"Courtepin",
    "sg:orig_category":"Tierarztpraxis",
    "sg:phone":"+41 26 684 11 24",
    "sg:postcode":"1784",
    "sg:province":"Fribourg",
    "wof:name":"Dr M\u00e9d. V\u00e9t. J\u00fcrg Immer M\u00e9decin V\u00e9t\u00e9rinaire",
    "wof:placetype":"venue"
},
  "geometry": {"coordinates":[7.1240501404,46.8647003174],"type":"Point"}
}