{
  "type": "Feature",
  "properties": {
    "iso:country":"CH",
    "sg:address":"Genuastrasse 11 4142 M\u00fcnchenstein. Postfach",
    "sg:city":"M\u00fcnchenstein",
    "sg:orig_category":"Vermietung U Verpachtung von eigenen Immobilien",
    "sg:postcode":"4142",
    "sg:province":"Basel-Landschaft",
    "wof:name":"Fiege Goth Immobilien Ag",
    "wof:placetype":"venue"
},
  "geometry": {"coordinates":[7.6100521088,47.5308189392],"type":"Point"}
}