{
  "type": "Feature",
  "properties": {
    "iso:country":"CH",
    "sg:address":"Im Steinen",
    "sg:city":"Luchsingen",
    "sg:orig_category":"Sonstiger Grosshandel",
    "sg:postcode":"8775",
    "sg:province":"Glarus",
    "wof:name":"Stekl Jerry",
    "wof:placetype":"venue"
},
  "geometry": {"coordinates":[8.9471750259,45.9904403687],"type":"Point"}
}