{
  "type": "Feature",
  "properties": {
    "addr:full":"B\u00f6sch 23 H\u00fcnenberg Zug 6331",
    "addr:housenumber":"23",
    "addr:postcode":"6331",
    "addr:street":"Boesch;Huenenberg Zug",
    "iso:country":"CH",
    "sg:address":"B\u00f6sch 23",
    "sg:city":"H\u00fcnenberg",
    "sg:orig_category":"Architektur U Ingenieurb\u00fcros",
    "sg:phone":"+41 19380000",
    "sg:postcode":"6331",
    "sg:province":"Zug",
    "wof:name":"Emutec, Muggli Eddie",
    "wof:placetype":"venue"
},
  "geometry": {"coordinates":[8.84353,47.30233],"type":"Point"}
}