{
  "type": "Feature",
  "properties": {
    "iso:country":"CH",
    "sg:address":"Costa Sot Voa La 23 7077 Valbella. Postfach",
    "sg:city":"Valbella",
    "sg:orig_category":"Finanzierungsinstitutionen",
    "sg:phone":"+41 55 644 27 80",
    "sg:postcode":"7077",
    "sg:province":"Graubunden",
    "wof:name":"Canfina Ag",
    "wof:placetype":"venue"
},
  "geometry": {"coordinates":[9.0670871735,46.9946861267],"type":"Point"}
}