{
  "type": "Feature",
  "properties": {
    "iso:country":"CH",
    "sg:address":"Sonnhalde",
    "sg:city":"Wauwil",
    "sg:orig_category":"Bauschreinerei Innenausbau",
    "sg:phone":"+41 41 980 37 26",
    "sg:postcode":"6242",
    "sg:province":"Luzern",
    "wof:name":"Robert Peter Schreinerei & Innenausbau",
    "wof:placetype":"venue"
},
  "geometry": {"coordinates":[8.029309,47.187927],"type":"Point"}
}