{
  "type": "Feature",
  "properties": {
    "iso:country":"CH",
    "sg:address":"Hintere Bahnhofstrasse 42",
    "sg:city":"Aarau",
    "sg:orig_category":"Detailhandel mit Brot, Back U S\u00fcsswaren",
    "sg:phone":"+41 71 244 56 39",
    "sg:postcode":"5000",
    "sg:province":"Aargau",
    "wof:name":"Konditorei-caf\u00e9 + B\u00e4ckerei Vogel",
    "wof:placetype":"venue"
},
  "geometry": {"coordinates":[9.390486,47.43882],"type":"Point"}
}