{
  "type": "Feature",
  "properties": {
    "iso:country":"CH",
    "sg:address":"Murifeldweg 21",
    "sg:city":"Bern",
    "sg:orig_category":"Markt U Meinungsforschung Werbeberatung",
    "sg:phone":"+41 31 351 81 41",
    "sg:postcode":"3006",
    "sg:province":"Bern",
    "wof:name":"Weiss Marketing Consulting",
    "wof:placetype":"venue"
},
  "geometry": {"coordinates":[7.470990181,46.9402694702],"type":"Point"}
}