{
  "type": "Feature",
  "properties": {
    "iso:country":"CH",
    "sg:address":"Tobeleggweg 19",
    "sg:city":"Z\u00fcrich",
    "sg:orig_category":"Grosshandel mit medizinischen U orthop\u00e4dischen Artikeln",
    "sg:phone":"+41 13415122",
    "sg:postcode":"8049",
    "sg:province":"Z\u00fcrich",
    "wof:name":"Asstech Gmbh",
    "wof:placetype":"venue"
},
  "geometry": {"coordinates":[8.5025568008,47.3977737427],"type":"Point"}
}