{
  "type": "Feature",
  "properties": {
    "iso:country":"CH",
    "sg:address":"Duxgass 6",
    "sg:city":"Schaan",
    "sg:orig_category":"Zahntechnische Laboratorien",
    "sg:postcode":"9494",
    "wof:name":"Andreas Beck Zahntechnisches Labor",
    "wof:placetype":"venue"
},
  "geometry": {"coordinates":[9.5132226944,47.1678161621],"type":"Point"}
}