{
  "type": "Feature",
  "properties": {
    "iso:country":"CH",
    "sg:address":"Schwarzenegg",
    "sg:city":"Unterlangenegg",
    "sg:orig_category":"Haltung von Rindern",
    "sg:postcode":"3614",
    "sg:province":"Bern",
    "wof:name":"Viehzuchtgenossenschaft Schwarzenegg",
    "wof:placetype":"venue"
},
  "geometry": {"coordinates":[7.708509922,46.7959365845],"type":"Point"}
}