{
  "type": "Feature",
  "properties": {
    "iso:country":"CH",
    "sg:address":"Rue Des Parcs 65 2000 Neuenburg. Postfach",
    "sg:city":"Neuenburg",
    "sg:orig_category":"Maler U Glasergewerbe",
    "sg:postcode":"2000",
    "sg:province":"Neuch\u00e2tel",
    "wof:name":"Entreprise-peinture - Lezzi Sandro",
    "wof:placetype":"venue"
},
  "geometry": {"coordinates":[6.9212441444,46.9926834106],"type":"Point"}
}