{
  "type": "Feature",
  "properties": {
    "iso:country":"CH",
    "sg:address":"Terrassenstrasse 5",
    "sg:city":"Sarnen",
    "sg:orig_category":"Architektur U Ingenieurb\u00fcros",
    "sg:phone":"+41 41 660 29 39",
    "sg:postcode":"6060",
    "sg:province":"Obwalden",
    "wof:name":"Peter Zwicky Ingenieurb\u00fcro",
    "wof:placetype":"venue"
},
  "geometry": {"coordinates":[8.245067,46.903595],"type":"Point"}
}