{
  "type": "Feature",
  "properties": {
    "iso:country":"CH",
    "sg:address":"Rue De Gen\u00e8ve 115",
    "sg:city":"Th\u00f4nex",
    "sg:orig_category":"Detailhandel mit Uhren U Schmuck Herstellung von Uhren",
    "sg:phone":"+41 22 348 62 14",
    "sg:postcode":"1226",
    "sg:province":"Gen\u00e8ve",
    "wof:name":"Lemantech Sa",
    "wof:placetype":"venue"
},
  "geometry": {"coordinates":[6.2019629478,46.1932601929],"type":"Point"}
}