{
  "type": "Feature",
  "properties": {
    "iso:country":"CH",
    "sg:address":"Mitteldorfstrasse 494 4703 Kestenholz. Postfach",
    "sg:city":"Kestenholz",
    "sg:orig_category":"Instandhaltung U Reparatur von Automobilen",
    "sg:postcode":"4703",
    "sg:province":"Solothurn",
    "wof:name":"Auto Studer Ag",
    "wof:placetype":"venue"
},
  "geometry": {"coordinates":[7.7575597763,47.2838897705],"type":"Point"}
}