{
  "type": "Feature",
  "properties": {
    "iso:country":"CH",
    "sg:address":"Christoffelgasse 5",
    "sg:city":"Bern",
    "sg:orig_category":"RESTAURANTS: TEA-ROOMS",
    "sg:phone":"+41 31 311 57 01",
    "sg:postcode":"3011",
    "sg:province":"Bern",
    "wof:name":"Caf\u00e9-bar \u00abbelair\u00bb Ruth Farine.",
    "wof:placetype":"venue"
},
  "geometry": {"coordinates":[7.4411001205,46.9467506409],"type":"Point"}
}