{
  "type": "Feature",
  "properties": {
    "iso:country":"CH",
    "sg:address":"Tr\u00e9lex Route De 1266 Duillier. Postfach",
    "sg:city":"Duillier",
    "sg:orig_category":"Herstellung von Metallkonstruktionen",
    "sg:postcode":"1266",
    "sg:province":"Vaud",
    "wof:name":"Solefi, Barioni, Leuenberger, M\u00fcller & Cie",
    "wof:placetype":"venue"
},
  "geometry": {"coordinates":[6.2349047661,46.4098243713],"type":"Point"}
}