{
  "type": "Feature",
  "properties": {
    "iso:country":"CH",
    "sg:address":"Oberdorfstrasse 26 9100 Herisau. Postfach 201",
    "sg:city":"Herisau",
    "sg:orig_category":"Sanit\u00e4r, Heizungs U L\u00fcftungsinstallation",
    "sg:phone":"+41 71 351 52 60",
    "sg:postcode":"9100",
    "sg:province":"Appenzell Ausserrhoden",
    "wof:name":"Alder J\u00f6rg Ag",
    "wof:placetype":"venue"
},
  "geometry": {"coordinates":[9.2804918289,47.3850402832],"type":"Point"}
}