{
  "type": "Feature",
  "properties": {
    "iso:country":"CH",
    "sg:address":"Bernstrasse",
    "sg:city":"Worb",
    "sg:orig_category":"Eisbahnen and Eissportpl\u00e4tze",
    "sg:phone":"+41 31 839 33 38",
    "sg:postcode":"3076",
    "sg:province":"Bern",
    "wof:name":"Kunsteisbahn Hofmatt",
    "wof:placetype":"venue"
},
  "geometry": {"coordinates":[7.5578517914,46.9296188354],"type":"Point"}
}