{
  "type": "Feature",
  "properties": {
    "iso:country":"CH",
    "sg:address":"Effingerstrasse 6 A",
    "sg:city":"Bern",
    "sg:orig_category":"Werbung",
    "sg:postcode":"3011",
    "sg:province":"Bern",
    "wof:name":"B\u00e4renstadt Gmbh",
    "wof:placetype":"venue"
},
  "geometry": {"coordinates":[7.4365501404,46.9459457397],"type":"Point"}
}