{
  "type": "Feature",
  "properties": {
    "iso:country":"CH",
    "sg:address":"Poststrasse 2",
    "sg:city":"Solothurn",
    "sg:orig_category":"Architekturb\u00fcros",
    "sg:phone":"+41 41 870 26 15",
    "sg:postcode":"4500",
    "sg:province":"Solothurn",
    "wof:name":"Max Hofer Architekturb\u00fcro",
    "wof:placetype":"venue"
},
  "geometry": {"coordinates":[8.640781,46.878757],"type":"Point"}
}