{
  "type": "Feature",
  "properties": {
    "iso:country":"CH",
    "sg:address":"Zona Industrie E",
    "sg:city":"Grancia",
    "sg:orig_category":"Grosshandel mit elektrischen Haushaltsger\u00e4ten",
    "sg:phone":"+41 91 994 43 72",
    "sg:postcode":"6916",
    "sg:province":"Ticino",
    "wof:name":"Zanussi Abteilung Der Electrolux Ag Z\u00fcrich",
    "wof:placetype":"venue"
},
  "geometry": {"coordinates":[8.9250659943,45.9669761658],"type":"Point"}
}