{
  "type": "Feature",
  "properties": {
    "iso:country":"CH",
    "sg:address":"Melchr\u00fctistrasse 21",
    "sg:city":"Wallisellen",
    "sg:orig_category":"Unternehmensberatung",
    "sg:phone":"+41 79 401 53 16",
    "sg:postcode":"8304",
    "sg:province":"Z\u00fcrich",
    "wof:name":"Tme Gmbh",
    "wof:placetype":"venue"
},
  "geometry": {"coordinates":[8.5793418884,47.4171104431],"type":"Point"}
}