{
  "type": "Feature",
  "properties": {
    "iso:country":"CH",
    "sg:address":"Hauptstrasse",
    "sg:city":"Pohlern",
    "sg:orig_category":"Detailhandel mit Milcherzeugnissen U Eiern Verarbeitung von Milch",
    "sg:phone":"+41 33 356 12 63",
    "sg:postcode":"3638",
    "sg:province":"Bern",
    "wof:name":"Werner Maurer K\u00e4serei",
    "wof:placetype":"venue"
},
  "geometry": {"coordinates":[7.5350241661,46.7269630432],"type":"Point"}
}