{
  "type": "Feature",
  "properties": {
    "iso:country":"CH",
    "sg:address":"Flughafenstrasse 4a",
    "sg:city":"Altenrhein",
    "sg:orig_category":"Herstellung von elektrischen Lampen U Leuchten",
    "sg:phone":"+41 71 911 52 92",
    "sg:postcode":"9423",
    "sg:province":"St. Gallen",
    "wof:name":"Bolt Tony",
    "wof:placetype":"venue"
},
  "geometry": {"coordinates":[9.5536642075,47.4891853333],"type":"Point"}
}