{
  "type": "Feature",
  "properties": {
    "iso:country":"CH",
    "sg:address":"3434",
    "sg:city":"Obergoldbach",
    "sg:orig_category":"Sportvereine Sch\u00fctzen",
    "sg:phone":"+41 31 701 17 39",
    "sg:postcode":"3434",
    "sg:province":"Bern",
    "wof:name":"Feldsch\u00fctzen Landiswil",
    "wof:placetype":"venue"
},
  "geometry": {"coordinates":[7.6721100807,46.9601593018],"type":"Point"}
}