{
  "type": "Feature",
  "properties": {
    "iso:country":"CH",
    "sg:address":"Zollstrasse 105 8212 Neuhausen. Postfach 17",
    "sg:city":"Neuhausen",
    "sg:orig_category":"Allgemeiner Hoch U Tiefbau Allgemeiner Hochbau",
    "sg:phone":"+41 81 302 79 92",
    "sg:postcode":"8212",
    "sg:province":"Schaffhausen",
    "wof:name":"Aggeler Bau Ag",
    "wof:placetype":"venue"
},
  "geometry": {"coordinates":[9.499752,47.014484],"type":"Point"}
}