{
  "type": "Feature",
  "properties": {
    "iso:country":"CH",
    "sg:address":"Avenue Du Devin-du-village 11",
    "sg:city":"Gen\u00e8ve",
    "sg:orig_category":"Malerei",
    "sg:phone":"+41 22 344 55 82",
    "sg:postcode":"1203",
    "sg:province":"Gen\u00e8ve",
    "wof:name":"Rachid Hasni Peinture En B\u00e2timent",
    "wof:placetype":"venue"
},
  "geometry": {"coordinates":[6.1237339973,46.2035827637],"type":"Point"}
}