{
  "type": "Feature",
  "properties": {
    "iso:country":"CH",
    "sg:address":"Ryblenberg",
    "sg:city":"Zollbr\u00fcck",
    "sg:orig_category":"Grosshandel mit Baumaterialien Sonstiger spezialisierter Hoch U Tiefbau",
    "sg:phone":"+41 34 496 57 40",
    "sg:postcode":"3436",
    "sg:province":"Bern",
    "wof:name":"Building Equipment Fair Trade Ch Gmbh",
    "wof:placetype":"venue"
},
  "geometry": {"coordinates":[7.7408971786,46.9739875793],"type":"Point"}
}