{
  "type": "Feature",
  "properties": {
    "iso:country":"CH",
    "sg:address":"Vordergasse 9",
    "sg:city":"Neunkirch",
    "sg:orig_category":"Detailhandel mit Computern U Software",
    "sg:postcode":"8213",
    "sg:province":"Schaffhausen",
    "wof:name":"Andr\u00e9 Haus Exa-store",
    "wof:placetype":"venue"
},
  "geometry": {"coordinates":[8.200455,47.476048],"type":"Point"}
}