{
  "type": "Feature",
  "properties": {
    "iso:country":"CH",
    "sg:address":"Route De Jura 24",
    "sg:city":"Fribourg",
    "sg:orig_category":"Baugewerbe",
    "sg:phone":"+41 26 466 73 46",
    "sg:postcode":"1700",
    "sg:province":"Fribourg",
    "wof:name":"Giuseppe Russo Dta Services",
    "wof:placetype":"venue"
},
  "geometry": {"coordinates":[7.143252,46.810062],"type":"Point"}
}