{
  "type": "Feature",
  "properties": {
    "iso:country":"CH",
    "sg:address":"Immeuble De La Poste",
    "sg:city":"Vex",
    "sg:orig_category":"Detailhandel mit Zeitungen U Zeitschriften Kioske",
    "sg:phone":"+41 27 207 21 70",
    "sg:postcode":"1981",
    "sg:province":"Valais",
    "wof:name":"B\u00e9atrice Rudaz Kiosque - Boutique",
    "wof:placetype":"venue"
},
  "geometry": {"coordinates":[7.3985052109,46.2118530273],"type":"Point"}
}