{
  "type": "Feature",
  "properties": {
    "iso:country":"CH",
    "sg:address":"Romanshornerstrasse 11",
    "sg:city":"Arbon",
    "sg:orig_category":"Ingenieurb\u00fcros Maschinenbau Maschinen-Fabrikation",
    "sg:phone":"+41 71 446 49 89",
    "sg:postcode":"9320",
    "sg:province":"Thurgau",
    "wof:name":"Aerne Engineering & Project-management Ag",
    "wof:placetype":"venue"
},
  "geometry": {"coordinates":[9.4304456711,47.5170249939],"type":"Point"}
}