{
  "type": "Feature",
  "properties": {
    "iso:country":"CH",
    "sg:address":"Hirsernstrasse 20",
    "sg:city":"Hergiswil",
    "sg:classifiers":[
        {
            "category":"Organizations",
            "subcategory":"Labor Organization",
            "type":"Services"
        }
    ],
    "sg:phone":"+41 41 630 44 77",
    "sg:postcode":"6052",
    "sg:province":"Nidwalden",
    "sg:tags":[
        "consulting",
        "enterprise",
        "certification"
    ],
    "wof:name":"Ddp Concepts Gmbh",
    "wof:placetype":"venue"
},
  "geometry": {"coordinates":[8.309891,46.996838],"type":"Point"}
}