{
  "type": "Feature",
  "properties": {
    "iso:country":"CH",
    "sg:address":"Alte Gasse 6",
    "sg:city":"Brunnen",
    "sg:classifiers":[
        {
            "category":"Restaurant",
            "type":"Food & Drink"
        }
    ],
    "sg:postcode":"6440",
    "sg:province":"Schwyz",
    "wof:name":"Rest. Mostrose, Betschart Anne-marie Restaurant",
    "wof:placetype":"venue"
},
  "geometry": {"coordinates":[8.6071481705,46.9944992065],"type":"Point"}
}