{
  "type": "Feature",
  "properties": {
    "iso:country":"CH",
    "sg:address":"Wiesenstrasse 24",
    "sg:city":"Thalwil",
    "sg:orig_category":"Architektur U Ingenieurb\u00fcros",
    "sg:postcode":"8800",
    "sg:province":"Z\u00fcrich",
    "wof:name":"Von Ballmoos Dieter",
    "wof:placetype":"venue"
},
  "geometry": {"coordinates":[8.566491,47.289471],"type":"Point"}
}