{
  "type": "Feature",
  "properties": {
    "iso:country":"CH",
    "sg:address":"R\u00fcttenenstrasse 68",
    "sg:city":"Langendorf",
    "sg:orig_category":"Fachdetailhandel in Verkaufsr\u00e4umen",
    "sg:phone":"+41 32 623 59 54",
    "sg:postcode":"4513",
    "sg:province":"Solothurn",
    "wof:name":"Fritz Breiter",
    "wof:placetype":"venue"
},
  "geometry": {"coordinates":[7.524450779,47.22423172],"type":"Point"}
}