{
  "type": "Feature",
  "properties": {
    "iso:country":"CH",
    "sg:address":"Avenue Ch\u00e2teau De La Cour 6",
    "sg:city":"Sierre",
    "sg:orig_category":"Bijouterien Reparatur von Uhren U Schmuck",
    "sg:phone":"+41 27 455 82 02",
    "sg:postcode":"3960",
    "sg:province":"Valais",
    "wof:name":"Claude & Maurice Burkardt Horlogerie Bijouterie",
    "wof:placetype":"venue"
},
  "geometry": {"coordinates":[7.533715,46.29401],"type":"Point"}
}