{
  "type": "Feature",
  "properties": {
    "iso:country":"CH",
    "sg:address":"1077 Servion. Postfach",
    "sg:city":"Servion",
    "sg:orig_category":"Instandhaltung U Reparatur von Automobilen",
    "sg:phone":"+41 21 944 03 91",
    "sg:postcode":"1077",
    "sg:province":"Vaud",
    "wof:name":"Pierre Berner Auto-\u00e9lectricit\u00e9",
    "wof:placetype":"venue"
},
  "geometry": {"coordinates":[6.8696961403,46.4601249695],"type":"Point"}
}