{
  "type": "Feature",
  "properties": {
    "iso:country":"CH",
    "sg:address":"Parkterrasse 10",
    "sg:city":"Bern",
    "sg:orig_category":"Bau von Bahnverkehrsstrecken Eisenbahnverkehr",
    "sg:phone":"+41 31 329 09 09",
    "sg:postcode":"3012",
    "sg:province":"Bern",
    "wof:name":"Cisalpino Sa",
    "wof:placetype":"venue"
},
  "geometry": {"coordinates":[7.4385,46.949863],"type":"Point"}
}