{
  "type": "Feature",
  "properties": {
    "iso:country":"CH",
    "sg:address":"Hauptstrasse 19 9556 Affeltrangen. Postfach",
    "sg:city":"Affeltrangen",
    "sg:classifiers":[
        {
            "category":"Restaurant",
            "type":"Food & Drink"
        }
    ],
    "sg:phone":"+41 71 917 12 44",
    "sg:postcode":"9556",
    "sg:province":"Thurgau",
    "wof:name":"Restaurant Frohsinn",
    "wof:placetype":"venue"
},
  "geometry": {"coordinates":[9.0288066864,47.529209137],"type":"Point"}
}