{
  "type": "Feature",
  "properties": {
    "iso:country":"CH",
    "sg:address":"6572",
    "sg:city":"Quartino",
    "sg:orig_category":"Bauschreinerei Zimmerei, Dachdeckerei, Bauspenglerei U Abdichtung",
    "sg:phone":"+41 91 795 15 11",
    "sg:postcode":"6572",
    "sg:province":"Ticino",
    "wof:name":"Legno Pi\u00f9 Sa",
    "wof:placetype":"venue"
},
  "geometry": {"coordinates":[8.89834,46.152069],"type":"Point"}
}