{
  "type": "Feature",
  "properties": {
    "iso:country":"CH",
    "sg:address":"Oberer Graben 2",
    "sg:city":"Winterthur",
    "sg:orig_category":"Detailhandel mit Geschenkartikeln U Souvenirs",
    "sg:phone":"+41 52 213 98 56",
    "sg:postcode":"8400",
    "sg:province":"Z\u00fcrich",
    "wof:name":"Cachet Boutique",
    "wof:placetype":"venue"
},
  "geometry": {"coordinates":[8.731347084,47.4984207153],"type":"Point"}
}