{
  "type": "Feature",
  "properties": {
    "iso:country":"CH",
    "sg:address":"Viale Castagnola 25a",
    "sg:city":"Lugano",
    "sg:orig_category":"Grosshandel mit keramischen Erzeugnissen, Glaswaren U Reinigungsmitteln",
    "sg:phone":"+41 91 683 32 52",
    "sg:postcode":"6900",
    "sg:province":"Ticino",
    "wof:name":"Dirart Sa",
    "wof:placetype":"venue"
},
  "geometry": {"coordinates":[8.9673690796,46.0058517456],"type":"Point"}
}