{
  "type": "Feature",
  "properties": {
    "iso:country":"CH",
    "sg:address":"Industriestrasse 3",
    "sg:city":"Triesen",
    "sg:orig_category":"Detailhandel mit Waren verschiedener Art, Hauptrichtung Nahrungsmittel",
    "sg:phone":"+41 75 390 04 33",
    "sg:postcode":"9495",
    "wof:name":"Alex Burri Denner Satelit",
    "wof:placetype":"venue"
},
  "geometry": {"coordinates":[9.523144722,47.1194915771],"type":"Point"}
}