{
  "type": "Feature",
  "properties": {
    "iso:country":"CH",
    "sg:address":"Toggenburgerstrasse 90",
    "sg:city":"Wil",
    "sg:orig_category":"Glow Lamps, Neon Lamps Illuminants",
    "sg:phone":"+41 71 923 12 23",
    "sg:postcode":"9500",
    "sg:province":"St. Gallen",
    "wof:name":"Brunner Lichtprodukte Ag",
    "wof:placetype":"venue"
},
  "geometry": {"coordinates":[9.0474891663,47.4595375061],"type":"Point"}
}