{
  "type": "Feature",
  "properties": {
    "iso:country":"CH",
    "sg:address":"Jungstrasse 8",
    "sg:city":"Basel",
    "sg:orig_category":"Public-Relations-Agenturen",
    "sg:phone":"+41 61 322 89 90",
    "sg:postcode":"4056",
    "sg:province":"Basel-Stadt",
    "wof:name":"Stefan Bissegger Admi Center Kmu",
    "wof:placetype":"venue"
},
  "geometry": {"coordinates":[7.5798959732,47.5678787231],"type":"Point"}
}