{
  "type": "Feature",
  "properties": {
    "addr:full":"Vers L'eglise Mannens Fribourg 1775",
    "addr:postcode":"mannens;1775",
    "addr:street":"Vers L'Eglise",
    "iso:country":"CH",
    "sg:address":"Vers L'eglise",
    "sg:city":"Mannens",
    "sg:orig_category":"Architektur U Ingenieurb\u00fcros",
    "sg:postcode":"1775",
    "sg:province":"Fribourg",
    "wof:name":"Cad Architecture, Joye Dolor\u00e8s",
    "wof:placetype":"venue"
},
  "geometry": {"coordinates":[4.877982,46.578636],"type":"Point"}
}