{
  "type": "Feature",
  "properties": {
    "iso:country":"CH",
    "sg:address":"Bennauerstrasse 12 8836 Bennau. Postfach",
    "sg:city":"Gross",
    "sg:orig_category":"G\u00fcterbef\u00f6rderung im Strassenverkehr",
    "sg:phone":"+41 55 412 78 31",
    "sg:postcode":"8841",
    "sg:province":"Schwyz",
    "wof:name":"Moser Freddy",
    "wof:placetype":"venue"
},
  "geometry": {"coordinates":[8.7280082703,47.1499862671],"type":"Point"}
}