{
  "type": "Feature",
  "properties": {
    "iso:country":"CH",
    "sg:address":"B\u00f6sch 63",
    "sg:city":"H\u00fcnenberg",
    "sg:orig_category":"Fachdetailhandel mit pharmazeutischen Produkten Grosshandel mit pharmazeutischen Erzeugnissen",
    "sg:phone":"+41 26 919 02 00",
    "sg:postcode":"6331",
    "sg:province":"Zug",
    "wof:name":"Ucb Farchim Sa",
    "wof:placetype":"venue"
},
  "geometry": {"coordinates":[7.0387201309,46.6249504089],"type":"Point"}
}