{
  "type": "Feature",
  "properties": {
    "iso:country":"CH",
    "sg:address":"Alpsteinstrasse 5",
    "sg:city":"Horn",
    "sg:orig_category":"Sonstiger Grosshandel",
    "sg:postcode":"9326",
    "sg:province":"Thurgau",
    "wof:name":"Waeger Bofor",
    "wof:placetype":"venue"
},
  "geometry": {"coordinates":[9.4580726624,47.4902114868],"type":"Point"}
}