{
  "type": "Feature",
  "properties": {
    "iso:country":"CH",
    "sg:address":"Rue Du Cr\u00eat-de-la-fin 1-2 2024 St-aubin-sauges Case Postale 50",
    "sg:city":"St-aubin-sauges",
    "sg:orig_category":"Dauerkulturbau Rebbau",
    "sg:phone":"+41 32 835 11 89",
    "sg:postcode":"2024",
    "sg:province":"Neuch\u00e2tel",
    "wof:name":"Caves De La B\u00e9roche, Association Des Producteurs De Vin",
    "wof:placetype":"venue"
},
  "geometry": {"coordinates":[6.77472,46.895859],"type":"Point"}
}