{
  "type": "Feature",
  "properties": {
    "iso:country":"CH",
    "sg:address":"Place Du March\u00e9 3",
    "sg:city":"Aubonne",
    "sg:orig_category":"Detailhandel mit Blumen U Pflanzen",
    "sg:phone":"+41 21 808 50 79",
    "sg:postcode":"1170",
    "sg:province":"Vaud",
    "wof:name":"Nadine Pache Fleurs",
    "wof:placetype":"venue"
},
  "geometry": {"coordinates":[6.391598,46.495102],"type":"Point"}
}