{
  "type": "Feature",
  "properties": {
    "iso:country":"CH",
    "sg:address":"Bahnhofstrasse 27 6300 Zug. Postfach 1340",
    "sg:city":"Zug",
    "sg:orig_category":"Wirtschaftspr\u00fcfung, Steuerberatung U Treuhand",
    "sg:phone":"+41 41 720 33 90",
    "sg:postcode":"6301",
    "sg:province":"Zug",
    "wof:name":"Vitop Consulting Ag Treuhand & Wirtschaftsberat.",
    "wof:placetype":"venue"
},
  "geometry": {"coordinates":[8.5156202316,47.1702880859],"type":"Point"}
}