{
  "type": "Feature",
  "properties": {
    "iso:country":"CH",
    "sg:address":"Winterthurerstrasse",
    "sg:city":"Flurlingen",
    "sg:orig_category":"Herstellung von Werkzeugen",
    "sg:phone":"+41 52 654 05 55",
    "sg:postcode":"8247",
    "sg:province":"Z\u00fcrich",
    "wof:name":"Sigg Werkzeugtechnik Gmbh",
    "wof:placetype":"venue"
},
  "geometry": {"coordinates":[8.6333255768,47.6791725159],"type":"Point"}
}