{
  "type": "Feature",
  "properties": {
    "iso:country":"CH",
    "sg:address":"Chermignon-dessous",
    "sg:city":"Chermignon",
    "sg:classifiers":[
        {
            "category":"Wholesale",
            "subcategory":"Meat",
            "type":"Manufacturing & Wholesale Goods"
        }
    ],
    "sg:phone":"+41 27 483 33 71",
    "sg:postcode":"3971",
    "sg:province":"Valais",
    "sg:tags":[
        "food",
        "cooked",
        "product",
        "related"
    ],
    "wof:name":"Cher-mignon Sa",
    "wof:placetype":"venue"
},
  "geometry": {"coordinates":[7.4752230644,46.2944602966],"type":"Point"}
}