{
  "type": "Feature",
  "properties": {
    "iso:country":"CH",
    "sg:address":"Seuzachstrasse 2 8413 Neftenbach. Postfach 366",
    "sg:city":"Neftenbach",
    "sg:orig_category":"Patentanwaltsb\u00fcros, Patentverwertung Rechtsberatung",
    "sg:phone":"+41 52 315 47 57",
    "sg:postcode":"8413",
    "sg:province":"Z\u00fcrich",
    "wof:name":"Patentanw\u00e4lte Breiter + Wiedmer Ag",
    "wof:placetype":"venue"
},
  "geometry": {"coordinates":[8.6683959961,47.5285263062],"type":"Point"}
}