{
  "type": "Feature",
  "properties": {
    "iso:country":"CH",
    "sg:address":"Obertorweg 100",
    "sg:city":"Allschwil",
    "sg:orig_category":"Schreibb\u00fcros Unternehmensberatung",
    "sg:postcode":"4123",
    "sg:province":"Basel-Landschaft",
    "wof:name":"Peter W. Sch\u00fcrch Interim Management",
    "wof:placetype":"venue"
},
  "geometry": {"coordinates":[7.5231809616,47.5494842529],"type":"Point"}
}