{
  "type": "Feature",
  "properties": {
    "iso:country":"CH",
    "sg:address":"Luzernerstrasse 92",
    "sg:city":"Cham",
    "sg:orig_category":"Psychotherapie",
    "sg:phone":"+41 41 780 75 06",
    "sg:postcode":"6330",
    "sg:province":"Zug",
    "wof:name":"Marie-theres Annen Psychotherapie",
    "wof:placetype":"venue"
},
  "geometry": {"coordinates":[8.4496021271,47.1744308472],"type":"Point"}
}