{
  "type": "Feature",
  "properties": {
    "iso:country":"CH",
    "sg:address":"Oberfeldhof",
    "sg:city":"Sch\u00fcbelbach",
    "sg:orig_category":"Werbung",
    "sg:postcode":"8862",
    "sg:province":"Schwyz",
    "wof:name":"Suisse-web, Ing. Bachmann Th. Und Herb I. Dienstleistungen Im Bereich Werbung, Bes. Im Internet",
    "wof:placetype":"venue"
},
  "geometry": {"coordinates":[8.9181480408,47.1752815247],"type":"Point"}
}