{
  "type": "Feature",
  "properties": {
    "iso:country":"CH",
    "sg:address":"Z\u00fcrcherstrasse 12",
    "sg:city":"Tuggen",
    "sg:classifiers":[
        {
            "category":"Restaurant",
            "type":"Food & Drink"
        }
    ],
    "sg:phone":"+41 55 445 11 83",
    "sg:postcode":"8856",
    "sg:province":"Schwyz",
    "wof:name":"Restaurant Sch\u00e4fli",
    "wof:placetype":"venue"
},
  "geometry": {"coordinates":[8.9403877258,47.2027130127],"type":"Point"}
}