{
  "type": "Feature",
  "properties": {
    "iso:country":"CH",
    "sg:address":"Rue Du Conseil-g\u00e9n\u00e9ral 20",
    "sg:city":"Gen\u00e8ve",
    "sg:orig_category":"Finanzierungsinstitutionen Handelsvermittlung",
    "sg:phone":"+41 22 708 10 77",
    "sg:postcode":"1205",
    "sg:province":"Gen\u00e8ve",
    "wof:name":"Double A Sa",
    "wof:placetype":"venue"
},
  "geometry": {"coordinates":[6.1428089142,46.1983604431],"type":"Point"}
}