{
  "type": "Feature",
  "properties": {
    "iso:country":"CH",
    "sg:address":"6968",
    "sg:city":"Sonvico",
    "sg:orig_category":"Herstellung von Schrauben, Nieten, Ketten U Federn",
    "sg:phone":"+41 91 945 51 64",
    "sg:postcode":"6968",
    "sg:province":"Ticino",
    "wof:name":"Lemtec Sa",
    "wof:placetype":"venue"
},
  "geometry": {"coordinates":[8.9892520905,46.0570449829],"type":"Point"}
}