{
  "type": "Feature",
  "properties": {
    "iso:country":"CH",
    "sg:address":"Forelstrasse 1 3072 Ostermundigen. Postfach 1039",
    "sg:city":"Ostermundigen",
    "sg:orig_category":"Verwaltung von Immobilien Wirtschaftspr\u00fcfung, Steuerberatung U Treuhand",
    "sg:phone":"+41 31 930 30 30",
    "sg:postcode":"3072",
    "sg:province":"Bern",
    "wof:name":"Bbv Treuhand Ag",
    "wof:placetype":"venue"
},
  "geometry": {"coordinates":[7.4820199013,46.9598808289],"type":"Point"}
}