{
  "type": "Feature",
  "properties": {
    "iso:country":"CH",
    "sg:address":"Bielstrasse 99",
    "sg:city":"Solothurn",
    "sg:orig_category":"Detailhandel mit Fleisch U Fleischwaren",
    "sg:phone":"+41 32 622 28 53",
    "sg:postcode":"4500",
    "sg:province":"Solothurn",
    "wof:name":"Bommer A.",
    "wof:placetype":"venue"
},
  "geometry": {"coordinates":[7.5219740868,47.2120780945],"type":"Point"}
}