{
  "type": "Feature",
  "properties": {
    "iso:country":"CH",
    "sg:address":"Alte Landstrasse 19",
    "sg:city":"Zollikon",
    "sg:orig_category":"Architekturb\u00fcros",
    "sg:phone":"+41 13916927",
    "sg:postcode":"8702",
    "sg:province":"Z\u00fcrich",
    "wof:name":"Archiblumer Architekturb\u00fcro",
    "wof:placetype":"venue"
},
  "geometry": {"coordinates":[8.570831,47.344349],"type":"Point"}
}