{
  "type": "Feature",
  "properties": {
    "iso:country":"CH",
    "sg:address":"Eisenbahnstrasse 27/29",
    "sg:city":"Rorschach",
    "sg:orig_category":"Detailhandel mit Brot, Back U S\u00fcsswaren",
    "sg:phone":"+41 71 841 10 85",
    "sg:postcode":"9400",
    "sg:province":"St. Gallen",
    "wof:name":"Egger Bruno, B\u00e4ckerei-konditorei.",
    "wof:placetype":"venue"
},
  "geometry": {"coordinates":[9.495107,47.476295],"type":"Point"}
}