{
  "type": "Feature",
  "properties": {
    "iso:country":"CH",
    "sg:address":"Ch\u00e2teau Rue Du 2",
    "sg:city":"Fleurier",
    "sg:orig_category":"Schreib U \u00dcbersetzungsb\u00fcros",
    "sg:phone":"+41 21 635 30 29",
    "sg:postcode":"2114",
    "sg:province":"Neuch\u00e2tel",
    "wof:name":"Multioffice, C. M\u00fcller",
    "wof:placetype":"venue"
},
  "geometry": {"coordinates":[6.5970921516,46.541229248],"type":"Point"}
}