{
  "type": "Feature",
  "properties": {
    "iso:country":"CH",
    "sg:address":"Schaffhauserstr. 71.",
    "sg:city":"Neuhausen",
    "sg:orig_category":"RESTAURANTS: TEA-ROOMS",
    "sg:postcode":"8212",
    "sg:province":"Schaffhausen",
    "wof:name":"Zampitelli Pompea.",
    "wof:placetype":"venue"
},
  "geometry": {"coordinates":[8.6223802567,47.6925315857],"type":"Point"}
}