{
  "type": "Feature",
  "properties": {
    "iso:country":"CH",
    "sg:address":"Rosengartenstrasse 1",
    "sg:city":"Weesen",
    "sg:classifiers":[
        {
            "category":"Travel",
            "subcategory":"Hotels & Motels",
            "type":"Entertainment"
        }
    ],
    "sg:phone":"+41 55 616 16 14",
    "sg:postcode":"8872",
    "sg:province":"St. Gallen",
    "sg:tags":[
        "hotels",
        "mit",
        "restaurant"
    ],
    "wof:name":"K\u00f6chli Guido",
    "wof:placetype":"venue"
},
  "geometry": {"coordinates":[9.0935373306,47.1327362061],"type":"Point"}
}