{
  "type": "Feature",
  "properties": {
    "iso:country":"CH",
    "sg:address":"Balainenweg 30",
    "sg:city":"Nidau",
    "sg:orig_category":"Herstellung von keramischen Haushaltswaren U Ziergegenst\u00e4nden",
    "sg:phone":"+41 32 331 60 88",
    "sg:postcode":"2560",
    "sg:province":"Bern",
    "wof:name":"Werner Tschannen T\u00f6pferei",
    "wof:placetype":"venue"
},
  "geometry": {"coordinates":[7.2375249863,47.1235275269],"type":"Point"}
}