{
  "type": "Feature",
  "properties": {
    "iso:country":"CH",
    "sg:address":"Stossstrasse 19",
    "sg:city":"Altst\u00e4tten",
    "sg:classifiers":[
        {
            "category":"Home & Garden",
            "subcategory":"Building Materials",
            "type":"Retail Goods"
        }
    ],
    "sg:phone":"+41 71 755 59 55",
    "sg:postcode":"9450",
    "sg:province":"St. Gallen",
    "sg:tags":[
        "aluminium",
        "gutter"
    ],
    "wof:name":"Gschwend Spenglerei U. Bedachungen Gmbh",
    "wof:placetype":"venue"
},
  "geometry": {"coordinates":[9.531886,47.374802],"type":"Point"}
}