{
  "type": "Feature",
  "properties": {
    "iso:country":"CH",
    "sg:address":"Laufenstrasse 36",
    "sg:city":"Basel",
    "sg:orig_category":"Datenverarbeitungsdienste Sonstige mit der Informatik verbundene T\u00e4tigkeiten",
    "sg:phone":"+41 17370861",
    "sg:postcode":"4053",
    "sg:province":"Basel-Stadt",
    "wof:name":"Roland Steinberger Service-rechenzentrum",
    "wof:placetype":"venue"
},
  "geometry": {"coordinates":[8.436907,47.352844],"type":"Point"}
}