{
  "type": "Feature",
  "properties": {
    "addr:full":"Dahlienweg 2 Zuchwil Solothurn 4528",
    "addr:housenumber":"2",
    "addr:postcode":"4528",
    "addr:street":"Dahlienweg",
    "iso:country":"CH",
    "sg:address":"Dahlienweg 2",
    "sg:city":"Zuchwil",
    "sg:orig_category":"Betrieb von Sportanlagen",
    "sg:postcode":"4528",
    "sg:province":"Solothurn",
    "wof:name":"Herba Rasenbau Ag",
    "wof:placetype":"venue"
},
  "geometry": {"coordinates":[7.560861,47.206642],"type":"Point"}
}