{
  "type": "Feature",
  "properties": {
    "iso:country":"CH",
    "sg:address":"Beckenhofstrasse 16 8006 Z\u00fcrich. Postfach",
    "sg:city":"Z\u00fcrich",
    "sg:orig_category":"Wirtschaftspr\u00fcfung, Steuerberatung U Treuhand",
    "sg:phone":"+41 13610445",
    "sg:postcode":"8001",
    "sg:province":"Z\u00fcrich",
    "wof:name":"Legatax Leysinger Ag Treuhandgesellschaft, Revision, Steuer, Wirtschaftsberatung Usw",
    "wof:placetype":"venue"
},
  "geometry": {"coordinates":[8.5421590805,47.3836135864],"type":"Point"}
}