{
  "type": "Feature",
  "properties": {
    "iso:country":"CH",
    "sg:address":"Kornplatz 2",
    "sg:city":"Chur",
    "sg:orig_category":"Detailhandel mit M\u00f6beln Detailhandel mit M\u00f6beln U Haushaltsgegenst\u00e4nden",
    "sg:phone":"+41 81 252 64 16",
    "sg:postcode":"7000",
    "sg:province":"Graubunden",
    "wof:name":"Einrichtungshaus Sch\u00f6pf Ag",
    "wof:placetype":"venue"
},
  "geometry": {"coordinates":[9.531621933,46.8489685059],"type":"Point"}
}