{
  "type": "Feature",
  "properties": {
    "iso:country":"CH",
    "sg:address":"Passwangstrasse 10",
    "sg:city":"Breitenbach",
    "sg:orig_category":"Non-Classified Establishments",
    "sg:phone":"+41 61 781 40 70",
    "sg:postcode":"4226",
    "sg:province":"Solothurn",
    "wof:name":"Fitness-studio Number 1 Denise Str\u00fcbin",
    "wof:placetype":"venue"
},
  "geometry": {"coordinates":[7.5430240631,47.4069595337],"type":"Point"}
}