{
  "type": "Feature",
  "properties": {
    "iso:country":"CH",
    "sg:address":"4717",
    "sg:city":"M\u00fcmliswil",
    "sg:classifiers":[
        {
            "category":"Restaurant",
            "type":"Food & Drink"
        }
    ],
    "sg:phone":"+41 71 744 32 55",
    "sg:postcode":"4717",
    "sg:province":"Solothurn",
    "wof:name":"Ndp Gastro-management Ag Pizzeriakette Barbarossa",
    "wof:placetype":"venue"
},
  "geometry": {"coordinates":[9.634349823,47.4547958374],"type":"Point"}
}