{
  "type": "Feature",
  "properties": {
    "iso:country":"CH",
    "sg:address":"Urtenenweg 21",
    "sg:city":"M\u00fcnchringen",
    "sg:orig_category":"Sonstiger Grosshandel",
    "sg:postcode":"3303",
    "sg:province":"Bern",
    "wof:name":"Letap Gmbh",
    "wof:placetype":"venue"
},
  "geometry": {"coordinates":[7.5199699402,47.0472412109],"type":"Point"}
}