{
  "type": "Feature",
  "properties": {
    "iso:country":"CH",
    "sg:address":"Bahnweg 1",
    "sg:city":"Gelterkinden",
    "sg:orig_category":"Bauschreinerei",
    "sg:phone":"+41 61 981 44 00",
    "sg:postcode":"4460",
    "sg:province":"Basel-Landschaft",
    "wof:name":"Beat Schmidlin Schreinerei",
    "wof:placetype":"venue"
},
  "geometry": {"coordinates":[7.847575,47.466568],"type":"Point"}
}