{
  "type": "Feature",
  "properties": {
    "iso:country":"CH",
    "sg:address":"Hauptstrasse 198",
    "sg:city":"Uerkheim",
    "sg:orig_category":"Detailhandel mit Waren verschiedener Art, Hauptrichtung Nahrungsmittel",
    "sg:phone":"+41 62 721 00 52",
    "sg:postcode":"4813",
    "sg:province":"Aargau",
    "wof:name":"Elsbeth Byland Lebensmittel",
    "wof:placetype":"venue"
},
  "geometry": {"coordinates":[8.0245847702,47.3047599792],"type":"Point"}
}