{
  "type": "Feature",
  "properties": {
    "iso:country":"CH",
    "sg:address":"Cit\u00e9 Rue De La 1 1204 Gen\u00e8ve. Postfach 399",
    "sg:city":"Gen\u00e8ve",
    "sg:orig_category":"Grosshandel mit festen Brennstoffen U Mineral\u00f6lerzeugnissen",
    "sg:phone":"+41 12421410",
    "sg:postcode":"1204",
    "sg:province":"Gen\u00e8ve",
    "wof:name":"Molyslip Oil Products Sa",
    "wof:placetype":"venue"
},
  "geometry": {"coordinates":[6.1484451294,46.2041435242],"type":"Point"}
}