{
  "type": "Feature",
  "properties": {
    "iso:country":"CH",
    "sg:address":"Unterdorfstrasse 4 3427 Utzenstorf. Postfach",
    "sg:city":"Utzenstorf",
    "sg:orig_category":"Vermittlung von Immobilien Verwaltung von Immobilien",
    "sg:phone":"+41 32 666 40 40",
    "sg:postcode":"3427",
    "sg:province":"Bern",
    "wof:name":"L\u00fcthi & Co Ag Treuhand & Immobilien",
    "wof:placetype":"venue"
},
  "geometry": {"coordinates":[7.5575680733,47.1309547424],"type":"Point"}
}