{
  "type": "Feature",
  "properties": {
    "iso:country":"CH",
    "sg:address":"Hinterburg 118",
    "sg:city":"Merishausen",
    "sg:orig_category":"RESTAURANTS: TEA-ROOMS",
    "sg:postcode":"8232",
    "sg:province":"Schaffhausen",
    "wof:name":"Rheinfall Gastro Ag",
    "wof:placetype":"venue"
},
  "geometry": {"coordinates":[8.6111497879,47.7601318359],"type":"Point"}
}