{
  "type": "Feature",
  "properties": {
    "iso:country":"CH",
    "sg:address":"Ebnetweg 4 5073 Gipf-oberfrick. Postfach",
    "sg:city":"Gipf-oberfrick",
    "sg:orig_category":"Religi\u00f6se Vereinigungen",
    "sg:postcode":"5073",
    "sg:province":"Aargau",
    "wof:name":"Stiftung Des Kultusvereins Gipf-oberfrick",
    "wof:placetype":"venue"
},
  "geometry": {"coordinates":[8.0002765656,47.4952583313],"type":"Point"}
}