{
  "type": "Feature",
  "properties": {
    "iso:country":"CH",
    "sg:address":"Route De Veyrier",
    "sg:city":"Veyrier",
    "sg:orig_category":"Sportvereine Sch\u00fctzen",
    "sg:phone":"+41 22 784 30 05",
    "sg:postcode":"1255",
    "sg:province":"Gen\u00e8ve",
    "wof:name":"St\u00e9 De Tir Militaire",
    "wof:placetype":"venue"
},
  "geometry": {"coordinates":[6.1770157814,46.1758728027],"type":"Point"}
}