{
  "type": "Feature",
  "properties": {
    "iso:country":"CH",
    "sg:address":"Im Grund 12",
    "sg:city":"Embrach",
    "sg:orig_category":"Finanzierungsinstitutionen",
    "sg:phone":"+41 18136101",
    "sg:postcode":"8424",
    "sg:province":"Z\u00fcrich",
    "wof:name":"Inex Consulting Gmbh",
    "wof:placetype":"venue"
},
  "geometry": {"coordinates":[8.5979347229,47.5079536438],"type":"Point"}
}