{
  "type": "Feature",
  "properties": {
    "iso:country":"CH",
    "sg:address":"Place De La Gare 2 1950 Sion Case Postale",
    "sg:city":"Sion",
    "sg:classifiers":[
        {
            "category":"Professional",
            "subcategory":"Employment Agencies",
            "type":"Services"
        }
    ],
    "sg:phone":"+41 27 327 44 66",
    "sg:postcode":"1951",
    "sg:province":"Valais",
    "sg:tags":[
        "personal",
        "u",
        "stellenvermittlung"
    ],
    "wof:name":"F. Deppierraz-glassey Fdg Bureau De Placement",
    "wof:placetype":"venue"
},
  "geometry": {"coordinates":[7.3592648506,46.2277488708],"type":"Point"}
}