{
  "type": "Feature",
  "properties": {
    "iso:country":"CH",
    "sg:address":"Aurigeno 6677 Aurigeno. Postfach",
    "sg:city":"Aurigeno",
    "sg:orig_category":"RESTAURANTS: TEA-ROOMS",
    "sg:postcode":"6677",
    "sg:province":"Ticino",
    "wof:name":"La Pinte Neuch\u00e2teloise, Yuan-ying",
    "wof:placetype":"venue"
},
  "geometry": {"coordinates":[6.831662178,47.1028442383],"type":"Point"}
}