{
  "type": "Feature",
  "properties": {
    "iso:country":"CH",
    "sg:address":"Denkmalstrasse 4",
    "sg:city":"Luzern",
    "sg:orig_category":"Museen",
    "sg:phone":"+41 61 641 10 60",
    "sg:postcode":"6006",
    "sg:province":"Luzern",
    "wof:name":"Gold-eck Beat Schoeneck Einrahmungen",
    "wof:placetype":"venue"
},
  "geometry": {"coordinates":[7.6444439888,47.5793571472],"type":"Point"}
}