{
  "type": "Feature",
  "properties": {
    "iso:country":"CH",
    "sg:address":"Route De Martigny 41",
    "sg:city":"Fully",
    "sg:orig_category":"Autogaragen Einzelhandel mit Automobilen",
    "sg:phone":"+41 27 746 15 23",
    "sg:postcode":"1926",
    "sg:province":"Valais",
    "wof:name":"G\u00e9rard Carron Garage",
    "wof:placetype":"venue"
},
  "geometry": {"coordinates":[7.114966,46.135937],"type":"Point"}
}