{
  "type": "Feature",
  "properties": {
    "iso:country":"CH",
    "sg:address":"Via Principala 19",
    "sg:city":"Sumvitg",
    "sg:orig_category":"Naturheil\u00e4rzte and Heilpraktiker",
    "sg:phone":"+41 81 943 31 91",
    "sg:postcode":"7175",
    "sg:province":"Graubunden",
    "wof:name":"Zentrum Zur Mitte P.leder & B.decurtins",
    "wof:placetype":"venue"
},
  "geometry": {"coordinates":[8.9373149872,46.7275733948],"type":"Point"}
}