{
  "type": "Feature",
  "properties": {
    "iso:country":"CH",
    "sg:address":"Haldenstrasse 8",
    "sg:city":"Zug",
    "sg:orig_category":"Unclassifiable Establishments",
    "sg:phone":"+41 41 710 13 84",
    "sg:postcode":"6300",
    "sg:province":"Zug",
    "wof:name":"Bxmail Ag",
    "wof:placetype":"venue"
},
  "geometry": {"coordinates":[8.5205392838,47.1739006042],"type":"Point"}
}