{
  "type": "Feature",
  "properties": {
    "iso:country":"CH",
    "sg:address":"Spitalgasse 32 3011 Bern. Postfach",
    "sg:city":"Bern",
    "sg:orig_category":"Konsulate",
    "sg:phone":"+41 31 312 38 19",
    "sg:postcode":"3001",
    "sg:province":"Bern",
    "wof:name":"Ambassade De La R\u00e9publique Bosnie-herz\u00e9govine",
    "wof:placetype":"venue"
},
  "geometry": {"coordinates":[7.4419269562,46.9480895996],"type":"Point"}
}