{
  "type": "Feature",
  "properties": {
    "iso:country":"CH",
    "sg:address":"Residenza 51",
    "sg:city":"Camorino",
    "sg:orig_category":"Vermietung U Verpachtung von eigenen Immobilien Vermittlung von Immobilien",
    "sg:phone":"+41 91 857 77 91",
    "sg:postcode":"6528",
    "sg:province":"Ticino",
    "wof:name":"Sofedo Sa",
    "wof:placetype":"venue"
},
  "geometry": {"coordinates":[9.0069608688,46.1635017395],"type":"Point"}
}