{
  "type": "Feature",
  "properties": {
    "iso:country":"CH",
    "sg:address":"Br\u00fcnigstrasse 98",
    "sg:city":"Sarnen",
    "sg:orig_category":"Malerei",
    "sg:phone":"+41 41 660 54 16",
    "sg:postcode":"6060",
    "sg:province":"Obwalden",
    "wof:name":"Burch & Emmenegger Ag Malergesch\u00e4ft",
    "wof:placetype":"venue"
},
  "geometry": {"coordinates":[8.2470521927,46.9015808105],"type":"Point"}
}