{
  "type": "Feature",
  "properties": {
    "iso:country":"CH",
    "sg:address":"Landoltstrasse 87",
    "sg:city":"Bern",
    "sg:orig_category":"Shiatsu-Therapie",
    "sg:phone":"+41 31 372 06 69",
    "sg:postcode":"3007",
    "sg:province":"Bern",
    "wof:name":"Cristina Wong Shiatsu",
    "wof:placetype":"venue"
},
  "geometry": {"coordinates":[7.445734024,46.9318275452],"type":"Point"}
}