{
  "type": "Feature",
  "properties": {
    "iso:country":"CH",
    "sg:address":"Abernstrasse 11",
    "sg:city":"Tann",
    "sg:orig_category":"Grosshandel mit B\u00fcromaschinen Grosshandel mit Datenverarbeitungsger\u00e4ten",
    "sg:phone":"+41 79 354 39 68",
    "sg:postcode":"8632",
    "sg:province":"Z\u00fcrich",
    "wof:name":"Webforce Gmbh Internet Services Provider",
    "wof:placetype":"venue"
},
  "geometry": {"coordinates":[8.7781295776,47.2013702393],"type":"Point"}
}