{
  "type": "Feature",
  "properties": {
    "iso:country":"CH",
    "sg:address":"Sand",
    "sg:city":"Wilderswil",
    "sg:orig_category":"Detailhandel mit Fahrr\u00e4dern Handel mit Motorr\u00e4dern, Teilen U Zubeh\u00f6r Instandhaltung U Reparatur von ",
    "sg:phone":"+41 33 822 20 26",
    "sg:postcode":"3812",
    "sg:province":"Bern",
    "wof:name":"Adrian Sch\u00e4ren Velos-motos",
    "wof:placetype":"venue"
},
  "geometry": {"coordinates":[7.8630990982,46.6605873108],"type":"Point"}
}