{
  "type": "Feature",
  "properties": {
    "iso:country":"CH",
    "sg:address":"En Fl\u00e9ch\u00e8re",
    "sg:city":"Signy",
    "sg:orig_category":"Detailhandel mit Damenbekleidung Detailhandel mit Herrenbekleidung",
    "sg:phone":"+41 22 363 75 75",
    "sg:postcode":"1274",
    "sg:province":"Vaud",
    "wof:name":"Spengler Ag Modehaus",
    "wof:placetype":"venue"
},
  "geometry": {"coordinates":[6.1920938492,46.3949508667],"type":"Point"}
}