{
  "type": "Feature",
  "properties": {
    "iso:country":"CH",
    "sg:address":"Bundesstrasse 7",
    "sg:city":"Zug",
    "sg:orig_category":"Herstellung von sonstigen organischen Grundstoffen U Chemikalien",
    "sg:phone":"+41 41 711 33 88",
    "sg:postcode":"6300",
    "sg:province":"Zug",
    "wof:name":"Sopaco Sa",
    "wof:placetype":"venue"
},
  "geometry": {"coordinates":[8.513379097,47.1713905334],"type":"Point"}
}