{
  "type": "Feature",
  "properties": {
    "iso:country":"CH",
    "sg:address":"St. Johanns-vorstadt 69",
    "sg:city":"Basel",
    "sg:orig_category":"Druckweiterverarbeitung",
    "sg:phone":"+41 61 321 63 00",
    "sg:postcode":"4056",
    "sg:province":"Basel-Stadt",
    "wof:name":"Martin Fischer Buchbinderei",
    "wof:placetype":"venue"
},
  "geometry": {"coordinates":[7.5828108788,47.5652580261],"type":"Point"}
}