{
  "type": "Feature",
  "properties": {
    "iso:country":"CH",
    "sg:address":"1565",
    "sg:city":"Missy",
    "sg:orig_category":"Primarschulen",
    "sg:phone":"+41 32 951 18 35",
    "sg:postcode":"1565",
    "sg:province":"Fribourg",
    "wof:name":"Ecole Primaire",
    "wof:placetype":"venue"
},
  "geometry": {"coordinates":[6.9726400375,46.8835906982],"type":"Point"}
}