{
  "type": "Feature",
  "properties": {
    "iso:country":"CH",
    "sg:address":"Grand-rue 23",
    "sg:city":"Morges",
    "sg:orig_category":"Detailhandel mit Damenbekleidung Kreditinstitute ohne Spezialkreditinstitute",
    "sg:phone":"+41 21 801 30 78",
    "sg:postcode":"1110",
    "sg:province":"Vaud",
    "wof:name":"Colvert Sa",
    "wof:placetype":"venue"
},
  "geometry": {"coordinates":[6.4994258881,46.5100021362],"type":"Point"}
}