{
  "type": "Feature",
  "properties": {
    "iso:country":"CH",
    "sg:address":"Route De Saint-gilles 54",
    "sg:city":"Cornol",
    "sg:orig_category":"Bauschreinerei",
    "sg:phone":"+41 32 462 28 10",
    "sg:postcode":"2952",
    "sg:province":"Jura",
    "wof:name":"Jean-pierre Schneider Menuiserie",
    "wof:placetype":"venue"
},
  "geometry": {"coordinates":[7.16044,47.403881],"type":"Point"}
}