{
  "type": "Feature",
  "properties": {
    "iso:country":"CH",
    "sg:address":"Oberwilerstrasse 16",
    "sg:city":"Therwil",
    "sg:orig_category":"Detailhandel mit B\u00fcromaschinen U einrichtungen",
    "sg:phone":"+41 61 721 15 30",
    "sg:postcode":"4106",
    "sg:province":"Basel-Landschaft",
    "wof:name":"Fringeli",
    "wof:placetype":"venue"
},
  "geometry": {"coordinates":[7.553908,47.500805],"type":"Point"}
}