{
  "type": "Feature",
  "properties": {
    "iso:country":"CH",
    "sg:address":"Untere B\u00fchlstrasse 8",
    "sg:city":"Weinfelden",
    "sg:orig_category":"Architekturb\u00fcros",
    "sg:phone":"+41 56 622 37 55",
    "sg:postcode":"8570",
    "sg:province":"Thurgau",
    "wof:name":"Walter Amrein Architekturb\u00fcro",
    "wof:placetype":"venue"
},
  "geometry": {"coordinates":[8.27879,47.355492],"type":"Point"}
}