{
  "type": "Feature",
  "properties": {
    "iso:country":"CH",
    "sg:address":"Schaalgasse 16 4501 Solothurn. Postfach",
    "sg:city":"Solothurn",
    "sg:orig_category":"Non-Classified Establishments",
    "sg:postcode":"4501",
    "sg:province":"Solothurn",
    "wof:name":"Copera Holding Gmbh",
    "wof:placetype":"venue"
},
  "geometry": {"coordinates":[7.537170887,47.2071685791],"type":"Point"}
}