{
  "type": "Feature",
  "properties": {
    "iso:country":"CH",
    "sg:address":"Hauptstrasse 41 8559 Fruthwilen. Postfach",
    "sg:city":"Fruthwilen",
    "sg:orig_category":"Erschliessung von Grundst\u00fccken",
    "sg:phone":"+41 41 811 46 25",
    "sg:postcode":"8559",
    "wof:name":"Wohnbaugenossenschaft Seewen-schwyz",
    "wof:placetype":"venue"
},
  "geometry": {"coordinates":[8.6334524155,47.0290145874],"type":"Point"}
}