{
  "type": "Feature",
  "properties": {
    "iso:country":"CH",
    "sg:address":"Rue Des Planchettes 47",
    "sg:city":"Porrentruy",
    "sg:orig_category":"Bau von Strassen, Sportanlagen U Bahnverkehrsstrecken",
    "sg:postcode":"2900",
    "sg:province":"Jura",
    "wof:name":"Neue Nickel, Seitz & Kauz Gmbh",
    "wof:placetype":"venue"
},
  "geometry": {"coordinates":[7.500462,46.92469],"type":"Point"}
}