{
  "type": "Feature",
  "properties": {
    "iso:country":"CH",
    "sg:address":"Clendy 6",
    "sg:city":"Yverdon-les-bains",
    "sg:orig_category":"Detailhandel mit Waren verschiedener Art, Hauptrichtung Nahrungsmittel",
    "sg:postcode":"1400",
    "sg:province":"Vaud",
    "wof:name":"Bornand-lassueur Marcel",
    "wof:placetype":"venue"
},
  "geometry": {"coordinates":[6.6544299126,46.7780151367],"type":"Point"}
}