{
  "type": "Feature",
  "properties": {
    "iso:country":"CH",
    "sg:address":"Via Cantonale",
    "sg:city":"Pambio-noranco",
    "sg:classifiers":[
        {
            "category":"Real Estate",
            "subcategory":"Real Estate Services",
            "type":"Services"
        }
    ],
    "sg:phone":"+41 91 994 99 68",
    "sg:postcode":"6915",
    "sg:province":"Ticino",
    "sg:tags":[
        "management",
        "property",
        "software"
    ],
    "wof:name":"Ab Informatica",
    "wof:placetype":"venue"
},
  "geometry": {"coordinates":[8.9336853027,45.9883117676],"type":"Point"}
}