{
  "type": "Feature",
  "properties": {
    "iso:country":"CH",
    "sg:address":"Moron Route De 15",
    "sg:city":"Perrefitte",
    "sg:classifiers":[
        {
            "category":"Travel",
            "subcategory":"Hotels & Motels",
            "type":"Entertainment"
        }
    ],
    "sg:postcode":"2742",
    "sg:province":"Bern",
    "sg:tags":[
        "hotels",
        "mit",
        "restaurant"
    ],
    "wof:name":"Dreamlands Flury & Varin",
    "wof:placetype":"venue"
},
  "geometry": {"coordinates":[7.3420448303,47.2746086121],"type":"Point"}
}