{
  "type": "Feature",
  "properties": {
    "iso:country":"CH",
    "sg:address":"Universit\u00e4tstrasse 65",
    "sg:city":"Z\u00fcrich",
    "sg:orig_category":"Physiotherapie",
    "sg:phone":"+41 13610717",
    "sg:postcode":"8006",
    "sg:province":"Z\u00fcrich",
    "wof:name":"Christine L\u00fcling Physiotherapie",
    "wof:placetype":"venue"
},
  "geometry": {"coordinates":[8.548084259,47.3818435669],"type":"Point"}
}