{
  "type": "Feature",
  "properties": {
    "iso:country":"CH",
    "sg:address":"Eulenweg 25",
    "sg:city":"Z\u00fcrich",
    "sg:orig_category":"Zahntechnische Laboratorien",
    "sg:phone":"+41 14318747",
    "sg:postcode":"8048",
    "sg:province":"Z\u00fcrich",
    "wof:name":"Karl Heinemann Praxis F\u00fcr Zahnprothetik",
    "wof:placetype":"venue"
},
  "geometry": {"coordinates":[8.4815711975,47.3833999634],"type":"Point"}
}