{
  "type": "Feature",
  "properties": {
    "iso:country":"CH",
    "sg:address":"1038",
    "sg:city":"Bercher",
    "sg:orig_category":"Detailhandel mit Waren verschiedener Art, Hauptrichtung Nahrungsmittel",
    "sg:phone":"+41 31 308 91 11",
    "sg:postcode":"1038",
    "sg:province":"Vaud",
    "wof:name":"Fenaco",
    "wof:placetype":"venue"
},
  "geometry": {"coordinates":[6.7114901543,46.6916313171],"type":"Point"}
}