{
  "type": "Feature",
  "properties": {
    "iso:country":"CH",
    "sg:address":"Mont-blanc Avenue Du 38",
    "sg:city":"Gland",
    "sg:orig_category":"Unclassifiable Establishments",
    "sg:postcode":"1196",
    "sg:province":"Vaud",
    "wof:name":"Bowling International Investments Sa",
    "wof:placetype":"venue"
},
  "geometry": {"coordinates":[6.2730379105,46.4142951965],"type":"Point"}
}