{
  "type": "Feature",
  "properties": {
    "iso:country":"CH",
    "sg:address":"Emmenstrasse 9",
    "sg:city":"Hasle-r\u00fcegsau",
    "sg:orig_category":"Sportvereine Turnen",
    "sg:postcode":"3415",
    "sg:province":"Bern",
    "wof:name":"Turnverein Stv Oberburg",
    "wof:placetype":"venue"
},
  "geometry": {"coordinates":[7.6530151367,47.0178489685],"type":"Point"}
}