{
  "type": "Feature",
  "properties": {
    "iso:country":"CH",
    "sg:address":"Justingerweg 4",
    "sg:city":"Bern",
    "sg:orig_category":"Grosshandel mit Getr\u00e4nken Grosshandel mit Wein U Spirituosen",
    "sg:phone":"+41 31 352 92 32",
    "sg:postcode":"3005",
    "sg:province":"Bern",
    "wof:name":"Casa De Vinos Argentinos Zuberb\u00fchler Lidia + Walter Ag Weine, Bes. Aus Argentinien; Einfuhr, Handel",
    "wof:placetype":"venue"
},
  "geometry": {"coordinates":[7.4563250542,46.9416923523],"type":"Point"}
}