{
  "type": "Feature",
  "properties": {
    "iso:country":"CH",
    "sg:address":"Imfeldstrasse 9 8037 Z\u00fcrich. Postfach",
    "sg:city":"Z\u00fcrich",
    "sg:orig_category":"Non-Classified Establishments",
    "sg:postcode":"8037",
    "sg:province":"Z\u00fcrich",
    "wof:name":"Kinowood Gmbh",
    "wof:placetype":"venue"
},
  "geometry": {"coordinates":[8.5351552963,47.3885879517],"type":"Point"}
}