{
  "type": "Feature",
  "properties": {
    "iso:country":"CH",
    "sg:address":"Rue Des Amandiers 5",
    "sg:city":"Sion",
    "sg:orig_category":"Arztpraxen",
    "sg:phone":"+41 27 322 90 80",
    "sg:postcode":"1950",
    "sg:province":"Valais",
    "wof:name":"Pd Dr M\u00e9d. Willy Dettwiler M\u00e9decin Sp\u00e9cialiste Fmh",
    "wof:placetype":"venue"
},
  "geometry": {"coordinates":[7.352508,46.231262],"type":"Point"}
}