{
  "type": "Feature",
  "properties": {
    "iso:country":"CH",
    "sg:address":"Wiesentalstrasse 5",
    "sg:city":"Arbon",
    "sg:orig_category":"Maschinen-Fabrikation",
    "sg:phone":"+41 71 446 64 13",
    "sg:postcode":"9320",
    "sg:province":"Thurgau",
    "wof:name":"Kotzur",
    "wof:placetype":"venue"
},
  "geometry": {"coordinates":[9.4269924164,47.5082244873],"type":"Point"}
}