{
  "type": "Feature",
  "properties": {
    "iso:country":"CH",
    "sg:address":"Vers-chez-les-brandt 57",
    "sg:city":"Brot-plamboz",
    "sg:orig_category":"Torfgewinnung U brikettherstellung",
    "sg:postcode":"2318",
    "sg:province":"Neuch\u00e2tel",
    "wof:name":"Sandoz Jean-louis",
    "wof:placetype":"venue"
},
  "geometry": {"coordinates":[6.7459421158,46.9776153564],"type":"Point"}
}