{
  "type": "Feature",
  "properties": {
    "iso:country":"CH",
    "sg:address":"Baarerstrasse 8",
    "sg:city":"Zug",
    "sg:orig_category":"Wirtschaftspr\u00fcfung, Steuerberatung U Treuhand",
    "sg:postcode":"6300",
    "sg:province":"Zug",
    "wof:name":"Fitreva Beratungs Ag",
    "wof:placetype":"venue"
},
  "geometry": {"coordinates":[8.5163869858,47.1713981628],"type":"Point"}
}