{
  "type": "Feature",
  "properties": {
    "iso:country":"CH",
    "sg:address":"9472",
    "sg:city":"Grabs",
    "sg:classifiers":[
        {
            "category":"Restaurant",
            "type":"Food & Drink"
        }
    ],
    "sg:phone":"+41 81 771 10 65",
    "sg:postcode":"9472",
    "sg:province":"St. Gallen",
    "wof:name":"Gasthaus Traube",
    "wof:placetype":"venue"
},
  "geometry": {"coordinates":[9.4469852448,47.1806488037],"type":"Point"}
}