{
  "type": "Feature",
  "properties": {
    "addr:full":"Gasse 227 Vinelz Bern 3234",
    "addr:housenumber":"227",
    "addr:postcode":"3234",
    "addr:street":"Gasse",
    "iso:country":"CH",
    "sg:address":"Gasse 227",
    "sg:city":"Vinelz",
    "sg:classifiers":[
        {
            "category":"Social Services",
            "subcategory":"Retirement Home",
            "type":"Services"
        }
    ],
    "sg:phone":"+41 32 913 91 95",
    "sg:postcode":"3234",
    "sg:province":"Bern",
    "sg:tags":[
        "pflegeheime",
        "u",
        "alters"
    ],
    "wof:name":"L'escale Home Simple Pr Personnes \u00e2g\u00e9es",
    "wof:placetype":"venue"
},
  "geometry": {"coordinates":[6.818333,47.09827],"type":"Point"}
}