{
  "type": "Feature",
  "properties": {
    "iso:country":"CH",
    "sg:address":"R\u00fctistrasse 1",
    "sg:city":"Amriswil",
    "sg:orig_category":"Detailhandel mit Bekleidung",
    "sg:phone":"+41 71 477 33 40",
    "sg:postcode":"8580",
    "sg:province":"Thurgau",
    "wof:name":"Seba Mode, Haller H. U.",
    "wof:placetype":"venue"
},
  "geometry": {"coordinates":[9.298826,47.545605],"type":"Point"}
}