{
  "type": "Feature",
  "properties": {
    "addr:full":"Alte Buchserstrasse 18 D\u00e4llikon Z\u00fcrich 8108",
    "addr:housenumber":"18",
    "addr:postcode":"8108",
    "addr:street":"Alte Buchserstrasse;Zuerich",
    "iso:country":"CH",
    "sg:address":"Alte Buchserstrasse 18",
    "sg:city":"D\u00e4llikon",
    "sg:orig_category":"Autogaragen",
    "sg:phone":"+41 18440680",
    "sg:postcode":"8108",
    "sg:province":"Z\u00fcrich",
    "wof:name":"Kurt Kolb Autoreparaturwerkstatt",
    "wof:placetype":"venue"
},
  "geometry": {"coordinates":[8.440245,47.443016],"type":"Point"}
}