{
  "type": "Feature",
  "properties": {
    "iso:country":"CH",
    "sg:address":"Bahnhofstrasse 22",
    "sg:city":"Wallisellen",
    "sg:orig_category":"Detailhandel mit Brot, Back U S\u00fcsswaren",
    "sg:phone":"+41 18302213",
    "sg:postcode":"8304",
    "sg:province":"Z\u00fcrich",
    "wof:name":"Berthold Neidhart B\u00e4ckerei-konditorei",
    "wof:placetype":"venue"
},
  "geometry": {"coordinates":[8.590698,47.41412],"type":"Point"}
}