{
  "type": "Feature",
  "properties": {
    "iso:country":"CH",
    "sg:address":"Miesernweg 11 4632 Trimbach. Postfach",
    "sg:city":"Trimbach",
    "sg:orig_category":"Detailhandel mit Schuhen U Lederwaren",
    "sg:postcode":"4632",
    "sg:province":"Solothurn",
    "wof:name":"Sonata Ag Lederwaren, Accessoires; Handel, Vertrieb",
    "wof:placetype":"venue"
},
  "geometry": {"coordinates":[7.8692698479,47.363407135],"type":"Point"}
}