{
  "type": "Feature",
  "properties": {
    "iso:country":"CH",
    "sg:address":"Lyssstrasse 2",
    "sg:city":"Aarberg",
    "sg:classifiers":[
        {
            "category":"Education",
            "subcategory":"Library",
            "type":"Public Place"
        }
    ],
    "sg:phone":"+41 52 672 31 82",
    "sg:postcode":"3270",
    "sg:province":"Bern",
    "sg:tags":[
        "u",
        "bibliotheken",
        "archive"
    ],
    "wof:name":"Gemeindebibliothek",
    "wof:placetype":"venue"
},
  "geometry": {"coordinates":[8.619486,47.68182],"type":"Point"}
}