{
  "type": "Feature",
  "properties": {
    "iso:country":"CH",
    "sg:address":"3464",
    "sg:city":"Schmidigen-m\u00fchlew",
    "sg:classifiers":[
        {
            "category":"Government",
            "subcategory":"Post Office",
            "type":"Public Place"
        }
    ],
    "sg:phone":"+41 34 435 11 97",
    "sg:postcode":"3464",
    "sg:province":"Bern",
    "sg:tags":[
        "die",
        "poststellen"
    ],
    "wof:name":"Die Post",
    "wof:placetype":"venue"
},
  "geometry": {"coordinates":[7.747399807,47.0934715271],"type":"Point"}
}