{
  "type": "Feature",
  "properties": {
    "iso:country":"CH",
    "sg:address":"Wieden 9473 Gams. Postfach",
    "sg:city":"Gams",
    "sg:orig_category":"Interessenvertretungen",
    "sg:postcode":"9473",
    "sg:province":"St. Gallen",
    "wof:name":"Patronale Wohlfahrtsstiftung Der Firma Ortlinghaus Gmbh Gams",
    "wof:placetype":"venue"
},
  "geometry": {"coordinates":[9.4402332306,47.1997871399],"type":"Point"}
}