{
  "type": "Feature",
  "properties": {
    "iso:country":"CH",
    "sg:address":"Eisengrubenweg 24",
    "sg:city":"Zofingen",
    "sg:orig_category":"Betrieb von Sportanlagen",
    "sg:phone":"+41 62 751 21 10",
    "sg:postcode":"4800",
    "sg:province":"Aargau",
    "wof:name":"Tesquash Ag",
    "wof:placetype":"venue"
},
  "geometry": {"coordinates":[7.942617,47.275642],"type":"Point"}
}