{
  "type": "Feature",
  "properties": {
    "iso:country":"CH",
    "sg:address":"Untere Z\u00e4une 7",
    "sg:city":"Z\u00fcrich",
    "sg:orig_category":"Detailhandel mit Uhren U Schmuck",
    "sg:phone":"+41 12624920",
    "sg:postcode":"8001",
    "sg:province":"Z\u00fcrich",
    "wof:name":"Evelyne Oggier Atelier Gold-& Silberschmuck",
    "wof:placetype":"venue"
},
  "geometry": {"coordinates":[8.5464496613,47.3710823059],"type":"Point"}
}