{
  "type": "Feature",
  "properties": {
    "iso:country":"CH",
    "sg:address":"Rugenparkstrasse 55",
    "sg:city":"Interlaken",
    "sg:orig_category":"Architektur U Ingenieurb\u00fcros",
    "sg:phone":"+41 33229205",
    "sg:postcode":"3800",
    "sg:province":"Bern",
    "wof:name":"Suter",
    "wof:placetype":"venue"
},
  "geometry": {"coordinates":[7.851391,46.677593],"type":"Point"}
}