{
  "type": "Feature",
  "properties": {
    "iso:country":"CH",
    "sg:address":"Route De La Veveyse 2",
    "sg:city":"Fribourg",
    "sg:orig_category":"Vermietung U Verpachtung von eigenen Immobilien",
    "sg:phone":"+41 26 424 07 55",
    "sg:postcode":"1700",
    "sg:province":"Fribourg",
    "wof:name":"Richon Christian",
    "wof:placetype":"venue"
},
  "geometry": {"coordinates":[7.1391158104,46.797542572],"type":"Point"}
}