{
  "type": "Feature",
  "properties": {
    "iso:country":"CH",
    "sg:address":"Ernetschwilerstrasse 23",
    "sg:city":"Gommiswald",
    "sg:orig_category":"Pensionskassen",
    "sg:phone":"+41 55 240 16 33",
    "sg:postcode":"8737",
    "sg:province":"St. Gallen",
    "wof:name":"Personalvorsorgestiftung Der Firma Ryf Theodor, Spenglerei & Sanit\u00e4t Ag R\u00fcti",
    "wof:placetype":"venue"
},
  "geometry": {"coordinates":[8.8570737839,47.2595024109],"type":"Point"}
}