{
  "type": "Feature",
  "properties": {
    "iso:country":"CH",
    "sg:address":"Grossmatte 9",
    "sg:city":"Littau",
    "sg:orig_category":"Physiotherapie",
    "sg:phone":"+41 52 233 05 40",
    "sg:postcode":"6014",
    "sg:province":"Luzern",
    "wof:name":"A. & M. K\u00f6nig & S. Schwarz Physiotherapie & Shiatsu",
    "wof:placetype":"venue"
},
  "geometry": {"coordinates":[7.5020627975,47.2292976379],"type":"Point"}
}