{
  "type": "Feature",
  "properties": {
    "iso:country":"CH",
    "sg:address":"Hub",
    "sg:city":"Krauchthal",
    "sg:orig_category":"Abwasserreinigung, Abfallbeseitigung U sonstige Entsorgung R\u00fcckgewinnung U Vorbereitung f\u00fcr die Wied",
    "sg:phone":"+41 31 921 40 66",
    "sg:postcode":"3326",
    "sg:province":"Bern",
    "wof:name":"Kewu Ag",
    "wof:placetype":"venue"
},
  "geometry": {"coordinates":[7.565778,47.00919],"type":"Point"}
}