{
  "type": "Feature",
  "properties": {
    "iso:country":"CH",
    "sg:address":"Pertuis-du-sault Ch. Du 28",
    "sg:city":"Neuch\u00e2tel",
    "sg:orig_category":"Non-Classified Establishments",
    "sg:postcode":"2000",
    "sg:province":"Neuch\u00e2tel",
    "wof:name":"Mycobio Sa",
    "wof:placetype":"venue"
},
  "geometry": {"coordinates":[6.9326190948,46.9992637634],"type":"Point"}
}