{
  "type": "Feature",
  "properties": {
    "iso:country":"CH",
    "sg:address":"Bernstrasse 51",
    "sg:city":"Bern",
    "sg:orig_category":"Detailhandel mit Brot, Back U S\u00fcsswaren",
    "sg:postcode":"3018",
    "sg:province":"Bern",
    "wof:name":"Leonie Seewer-w\u00fcrsten",
    "wof:placetype":"venue"
},
  "geometry": {"coordinates":[7.267317,46.383698],"type":"Point"}
}