{
  "type": "Feature",
  "properties": {
    "iso:country":"CH",
    "sg:address":"Frohe Aussicht 10",
    "sg:city":"Feusisberg",
    "sg:orig_category":"Non-Classified Establishments",
    "sg:postcode":"8835",
    "sg:province":"Schwyz",
    "wof:name":"Fd Consulting, Frank Dargel",
    "wof:placetype":"venue"
},
  "geometry": {"coordinates":[8.7461290359,47.1874771118],"type":"Point"}
}