{
  "type": "Feature",
  "properties": {
    "iso:country":"CH",
    "sg:address":"Grand-rue 25",
    "sg:city":"Ch\u00e2tel-st-denis",
    "sg:classifiers":[
        {
            "category":"Government",
            "subcategory":"Post Office",
            "type":"Public Place"
        }
    ],
    "sg:phone":"+41 21 948 70 35",
    "sg:postcode":"1618",
    "sg:province":"Fribourg",
    "sg:tags":[
        "caf\u00e9s",
        "tea-rooms"
    ],
    "wof:name":"Tea-room Do-r\u00e9-mi",
    "wof:placetype":"venue"
},
  "geometry": {"coordinates":[6.9012150764,46.5274009705],"type":"Point"}
}