{
  "type": "Feature",
  "properties": {
    "iso:country":"CH",
    "sg:address":"Montagne-de-diesse Route 63 2505 Biel/bienne. Postfach",
    "sg:city":"Biel/bienne",
    "sg:orig_category":"Institutionen des Sozialwesens ohne Beherbergung",
    "sg:phone":"+41 27 283 10 07",
    "sg:postcode":"2505",
    "sg:province":"Bern",
    "wof:name":"Fondation Tourbillon Gerber",
    "wof:placetype":"venue"
},
  "geometry": {"coordinates":[7.2190470695,47.1313209534],"type":"Point"}
}