{
  "type": "Feature",
  "properties": {
    "iso:country":"CH",
    "sg:address":"Koppigenstrasse 18b",
    "sg:city":"Utzenstorf",
    "sg:orig_category":"Internet, Internetmarketing",
    "sg:phone":"+41 32 665 26 74",
    "sg:postcode":"3427",
    "sg:province":"Bern",
    "wof:name":"Kostenloses.com",
    "wof:placetype":"venue"
},
  "geometry": {"coordinates":[7.5611,47.12817],"type":"Point"}
}