{
  "type": "Feature",
  "properties": {
    "iso:country":"CH",
    "sg:address":"Malombr\u00e9 Chemin 12 1206 Gen\u00e8ve. Postfach",
    "sg:city":"Gen\u00e8ve",
    "sg:orig_category":"Non-Classified Establishments",
    "sg:postcode":"1206",
    "sg:province":"Gen\u00e8ve",
    "wof:name":"Imc Industrial Mineral & Commercial Trust Ltd",
    "wof:placetype":"venue"
},
  "geometry": {"coordinates":[6.151848793,46.1956596375],"type":"Point"}
}