{
  "type": "Feature",
  "properties": {
    "iso:country":"CH",
    "sg:address":"Via San Gottardo 56a",
    "sg:city":"Balerna",
    "sg:classifiers":[
        {
            "category":"Banks & Credit Unions",
            "subcategory":"Bank",
            "type":"Services"
        }
    ],
    "sg:phone":"+41 4191436894",
    "sg:postcode":"6828",
    "sg:province":"Ticino",
    "wof:name":"Credito Svizzero",
    "wof:placetype":"venue"
},
  "geometry": {"coordinates":[9.010606,45.844482],"type":"Point"}
}