{
  "type": "Feature",
  "properties": {
    "iso:country":"CH",
    "sg:address":"43 Rte Des Jeunes",
    "sg:city":"Gen\u00e8ve",
    "sg:classifiers":[
        {
            "category":"Food Court",
            "type":"Food & Drink"
        }
    ],
    "sg:phone":"+41 32 861 39 61",
    "sg:postcode":"1202",
    "sg:province":"Gen\u00e8ve",
    "sg:tags":[
        "product",
        "related"
    ],
    "wof:name":"Mauler & Cie Sa",
    "wof:placetype":"venue"
},
  "geometry": {"coordinates":[6.6126852036,46.9113502502],"type":"Point"}
}