{
  "type": "Feature",
  "properties": {
    "iso:country":"CH",
    "sg:address":"Kirchplatz 12",
    "sg:city":"Muttenz",
    "sg:orig_category":"Elektroinstallation",
    "sg:phone":"+41 61 461 82 08",
    "sg:postcode":"4132",
    "sg:province":"Basel-Landschaft",
    "wof:name":"Zumirep, Zumsteg Thomi",
    "wof:placetype":"venue"
},
  "geometry": {"coordinates":[7.6456141472,47.5218162537],"type":"Point"}
}