{
  "type": "Feature",
  "properties": {
    "iso:country":"CH",
    "sg:address":"Dassier Rue Jean- 20 1201 Gen\u00e8ve. Postfach",
    "sg:city":"Gen\u00e8ve",
    "sg:orig_category":"Erwachsenenbildung U Unterricht",
    "sg:postcode":"1201",
    "sg:province":"Gen\u00e8ve",
    "wof:name":"Mediane Gestion De Conflit Professionnel, Venchiarutti Gestion De Conflit Interpersonnel Dans Le Cadre Professionnel",
    "wof:placetype":"venue"
},
  "geometry": {"coordinates":[6.1394991875,46.2089538574],"type":"Point"}
}