{
  "type": "Feature",
  "properties": {
    "iso:country":"CH",
    "sg:address":"Dreik\u00f6nigstrasse 21",
    "sg:city":"Z\u00fcrich",
    "sg:orig_category":"Unclassifiable Establishments",
    "sg:postcode":"8002",
    "sg:province":"Z\u00fcrich",
    "wof:name":"Jpmorgan Chase Bank, New York, Zurich Branch",
    "wof:placetype":"venue"
},
  "geometry": {"coordinates":[8.5368719101,47.3670349121],"type":"Point"}
}