{
  "type": "Feature",
  "properties": {
    "iso:country":"CH",
    "sg:address":"Br\u00fclisau 9058 Br\u00fclisau. Postfach",
    "sg:city":"Br\u00fclisau",
    "sg:orig_category":"Sonstiger Grosshandel",
    "sg:postcode":"9058",
    "sg:province":"Appenzell Innerhoden",
    "wof:name":"Lev-life Gmbh",
    "wof:placetype":"venue"
},
  "geometry": {"coordinates":[9.4547977448,47.2967910767],"type":"Point"}
}