{
  "type": "Feature",
  "properties": {
    "iso:country":"CH",
    "sg:address":"Schaffhauserstrasse 432",
    "sg:city":"Z\u00fcrich",
    "sg:orig_category":"Herstellung von medizinischen U chirurgischen Ger\u00e4ten sowie orthop\u00e4dischen Vorrichtungen Zahntechnis",
    "sg:phone":"+41 13011810",
    "sg:postcode":"8050",
    "sg:province":"Z\u00fcrich",
    "wof:name":"Ortho-labor G\u00f6hring R.",
    "wof:placetype":"venue"
},
  "geometry": {"coordinates":[8.5452690125,47.4160728455],"type":"Point"}
}