{
  "type": "Feature",
  "properties": {
    "iso:country":"CH",
    "sg:address":"Avenue Jean-j. Rousseau 20 1815 Clarens Case Postale 129",
    "sg:city":"Clarens",
    "sg:orig_category":"Druck ohne Zeitungsdruck Offsetdruck",
    "sg:phone":"+41 21 964 38 24",
    "sg:postcode":"1815",
    "sg:province":"Vaud",
    "wof:name":"Imprimerie Monney, Aubord Olivier Successeur",
    "wof:placetype":"venue"
},
  "geometry": {"coordinates":[6.8916778564,46.4422912598],"type":"Point"}
}