{
  "type": "Feature",
  "properties": {
    "iso:country":"CH",
    "sg:address":"Rue Du Molage 24",
    "sg:city":"Aigle",
    "sg:orig_category":"Bauschreinerei Herstellung von Konstruktionsteilen, Fertigbauteilen U Ausbauelementen aus Holz",
    "sg:phone":"+41 33 733 35 35",
    "sg:postcode":"1860",
    "sg:province":"Vaud",
    "wof:name":"Saugy Schreinerteam Ag",
    "wof:placetype":"venue"
},
  "geometry": {"coordinates":[7.436736,46.471348],"type":"Point"}
}