{
  "type": "Feature",
  "properties": {
    "iso:country":"CH",
    "sg:address":"Z\u00fcrichstrasse 38a",
    "sg:city":"Br\u00fcttisellen",
    "sg:orig_category":"Grosshandel mit Holz U Baustoffen",
    "sg:phone":"+41 18071717",
    "sg:postcode":"8306",
    "sg:province":"Z\u00fcrich",
    "wof:name":"Ankaba, Ankertechnik + Bauhandel Ag",
    "wof:placetype":"venue"
},
  "geometry": {"coordinates":[8.6285743713,47.42237854],"type":"Point"}
}