{
  "type": "Feature",
  "properties": {
    "iso:country":"CH",
    "sg:address":"Rue Des P\u00e2quis 1",
    "sg:city":"Genf",
    "sg:orig_category":"Unclassifiable Establishments",
    "sg:postcode":"1200",
    "sg:province":"Gen\u00e8ve",
    "wof:name":"Pernot Philippe",
    "wof:placetype":"venue"
},
  "geometry": {"coordinates":[6.1476612091,46.2094802856],"type":"Point"}
}