{
  "type": "Feature",
  "properties": {
    "iso:country":"CH",
    "sg:address":"Nordstrasse 6 8840 Einsiedeln. Postfach",
    "sg:city":"Einsiedeln",
    "sg:orig_category":"Detailhandel mit elektrischen Haushalts-,Radio U Fernsehger\u00e4ten sowie Musikinstrumenten Elektroinsta",
    "sg:phone":"+41 55 412 74 74",
    "sg:postcode":"8840",
    "sg:province":"Schwyz",
    "wof:name":"Expert K\u00e4lin C\u00e4sar Gmbh",
    "wof:placetype":"venue"
},
  "geometry": {"coordinates":[8.747961998,47.1288299561],"type":"Point"}
}