{
  "type": "Feature",
  "properties": {
    "iso:country":"CH",
    "sg:address":"Z\u00fcrcherstrasse",
    "sg:city":"Tuggen",
    "sg:orig_category":"Grosshandel mit Obst U Gem\u00fcse",
    "sg:phone":"+41 79 322 60 44",
    "sg:postcode":"8856",
    "sg:province":"Schwyz",
    "wof:name":"Banado Ag",
    "wof:placetype":"venue"
},
  "geometry": {"coordinates":[7.6046237946,47.4711761475],"type":"Point"}
}