{
  "type": "Feature",
  "properties": {
    "iso:country":"CH",
    "sg:address":"Zentrumsplatz",
    "sg:city":"Sch\u00f6nb\u00fchl-urtenen",
    "sg:orig_category":"Wirtschaftspr\u00fcfung, Steuerberatung U Treuhand",
    "sg:postcode":"3322",
    "sg:province":"Bern",
    "wof:name":"Werner Joege",
    "wof:placetype":"venue"
},
  "geometry": {"coordinates":[7.4981780052,47.0204772949],"type":"Point"}
}