{
  "type": "Feature",
  "properties": {
    "iso:country":"CH",
    "sg:address":"Schafmattstrasse 4",
    "sg:city":"Belp",
    "sg:orig_category":"Sonstiger Grosshandel",
    "sg:phone":"+41 79 651 51 31",
    "sg:postcode":"3123",
    "sg:province":"Bern",
    "wof:name":"Allmasch Gmbh",
    "wof:placetype":"venue"
},
  "geometry": {"coordinates":[7.4966330528,46.8991699219],"type":"Point"}
}