{
  "type": "Feature",
  "properties": {
    "iso:country":"CH",
    "sg:address":"B\u00fcehli",
    "sg:city":"Obstalden",
    "sg:orig_category":"Zimmerei, Dachdeckerei, Bauspenglerei U Abdichtung",
    "sg:phone":"+41 41 310 16 38",
    "sg:postcode":"8758",
    "sg:province":"Glarus",
    "wof:name":"Rohr + Harder Holzbau Gmbh",
    "wof:placetype":"venue"
},
  "geometry": {"coordinates":[9.1615028381,47.1178092957],"type":"Point"}
}