{
  "type": "Feature",
  "properties": {
    "iso:country":"CH",
    "sg:address":"Fr\u00f6licherweg 14",
    "sg:city":"Solothurn",
    "sg:orig_category":"Verlagsgewerbe",
    "sg:phone":"+41 32 622 10 82",
    "sg:postcode":"4500",
    "sg:province":"Solothurn",
    "wof:name":"Bmb Verlag Hugo St\u00fcdeli",
    "wof:placetype":"venue"
},
  "geometry": {"coordinates":[7.5434551239,47.209941864],"type":"Point"}
}