{
  "type": "Feature",
  "properties": {
    "iso:country":"CH",
    "sg:address":"Gartenstadtstrasse 10 3098 K\u00f6niz. Postfach",
    "sg:city":"K\u00f6niz",
    "sg:orig_category":"Non-Classified Establishments",
    "sg:postcode":"3098",
    "sg:province":"Bern",
    "wof:name":"Haage Sagl",
    "wof:placetype":"venue"
},
  "geometry": {"coordinates":[8.8138399124,46.1332893372],"type":"Point"}
}