{
  "type": "Feature",
  "properties": {
    "iso:country":"CH",
    "sg:address":"Ebnetstrasse 1",
    "sg:city":"Herisau",
    "sg:classifiers":[
        {
            "category":"Social Services",
            "subcategory":"Retirement Home",
            "type":"Services"
        }
    ],
    "sg:phone":"+41 18500600",
    "sg:postcode":"9100",
    "sg:province":"Appenzell Ausserrhoden",
    "sg:tags":[
        "pflegeheime",
        "u",
        "alters"
    ],
    "wof:name":"Altersheim Eichi",
    "wof:placetype":"venue"
},
  "geometry": {"coordinates":[8.500973,47.494514],"type":"Point"}
}