{
  "type": "Feature",
  "properties": {
    "iso:country":"CH",
    "sg:address":"R\u00f6schenzstrasse 62 4242 Laufen. Postfach",
    "sg:city":"Laufen",
    "sg:orig_category":"Flachsaufbereitung U spinnerei",
    "sg:postcode":"4242",
    "sg:province":"Basel-Landschaft",
    "wof:name":"Hemp Art, Metzger Michaela",
    "wof:placetype":"venue"
},
  "geometry": {"coordinates":[7.493666172,47.4223213196],"type":"Point"}
}