{
  "type": "Feature",
  "properties": {
    "iso:country":"CH",
    "sg:address":"Industriestrasse 6",
    "sg:city":"Dietlikon",
    "sg:orig_category":"Unclassifiable Establishments",
    "sg:phone":"+41 18059600",
    "sg:postcode":"8305",
    "sg:province":"Z\u00fcrich",
    "wof:name":"Expert Holding Ag",
    "wof:placetype":"venue"
},
  "geometry": {"coordinates":[8.6252803802,47.4160118103],"type":"Point"}
}