{
  "type": "Feature",
  "properties": {
    "iso:country":"CH",
    "sg:address":"Bollwerk 4 3011 Bern. Postfach",
    "sg:city":"Bern",
    "sg:orig_category":"Unclassifiable Establishments",
    "sg:phone":"+41 31 311 21 91",
    "sg:postcode":"3005",
    "sg:province":"Bern",
    "wof:name":"Buffet Suisse Sa Beteiligungen Usw",
    "wof:placetype":"venue"
},
  "geometry": {"coordinates":[7.4403262138,46.9496955872],"type":"Point"}
}