{
  "type": "Feature",
  "properties": {
    "iso:country":"CH",
    "sg:address":"Frauenfelderstrasse 2 8252 Schlatt Tg. Postfach",
    "sg:city":"Mettschlatt",
    "sg:classifiers":[
        {
            "category":"Travel",
            "subcategory":"Hotels & Motels",
            "type":"Entertainment"
        }
    ],
    "sg:postcode":"8252",
    "sg:province":"Thurgau",
    "sg:tags":[
        "hotels",
        "mit",
        "restaurant"
    ],
    "wof:name":"Hotel Restaurant Bahnhof, Milan Acimovic",
    "wof:placetype":"venue"
},
  "geometry": {"coordinates":[8.687669754,47.6789779663],"type":"Point"}
}