{
  "type": "Feature",
  "properties": {
    "iso:country":"CH",
    "sg:address":"Seilerstrasse 12",
    "sg:city":"Arbon",
    "sg:orig_category":"Bauspenglerei Zimmerei, Dachdeckerei, Bauspenglerei U Abdichtung",
    "sg:phone":"+41 71 446 29 72",
    "sg:postcode":"9320",
    "sg:province":"Thurgau",
    "wof:name":"Ott Karl Ag",
    "wof:placetype":"venue"
},
  "geometry": {"coordinates":[9.427228,47.513523],"type":"Point"}
}