{
  "type": "Feature",
  "properties": {
    "iso:country":"CH",
    "sg:address":"Brittnauerstrasse 11",
    "sg:city":"Strengelbach",
    "sg:orig_category":"Museen",
    "sg:phone":"+41 71 222 26 01",
    "sg:postcode":"4802",
    "sg:province":"Aargau",
    "wof:name":"Museum Im Lagerhaus Stiftung F.schweiz.naive Kunst",
    "wof:placetype":"venue"
},
  "geometry": {"coordinates":[9.3670120239,47.419631958],"type":"Point"}
}