{
  "type": "Feature",
  "properties": {
    "iso:country":"CH",
    "sg:address":"Sandsteinstrasse 538",
    "sg:city":"Laupersdorf",
    "sg:orig_category":"Fernmeldedienste",
    "sg:postcode":"4712",
    "sg:province":"Solothurn",
    "wof:name":"Fernsehgenossenschaft Laupersdorf",
    "wof:placetype":"venue"
},
  "geometry": {"coordinates":[7.6508460045,47.3130874634],"type":"Point"}
}