{
  "type": "Feature",
  "properties": {
    "iso:country":"CH",
    "sg:address":"Im Wingert 20 8049 Z\u00fcrich. Postfach",
    "sg:city":"Z\u00fcrich",
    "sg:orig_category":"Wirtschaftspr\u00fcfung, Steuerberatung U Treuhand",
    "sg:postcode":"8049",
    "sg:province":"Z\u00fcrich",
    "wof:name":"Z Bautreuhand H. Spalinger",
    "wof:placetype":"venue"
},
  "geometry": {"coordinates":[8.5091600418,47.4001731873],"type":"Point"}
}