{
  "type": "Feature",
  "properties": {
    "iso:country":"CH",
    "sg:address":"Eichenweg 2",
    "sg:city":"Eich",
    "sg:orig_category":"Hoch U Tiefbau",
    "sg:phone":"+41 41 460 28 52",
    "sg:postcode":"6205",
    "sg:province":"Luzern",
    "wof:name":"Josef B\u00e4ttig Bauunternehmung",
    "wof:placetype":"venue"
},
  "geometry": {"coordinates":[8.1678848267,47.1602363586],"type":"Point"}
}