{
  "type": "Feature",
  "properties": {
    "addr:full":"Route De La Chapelle Estavayer-le-lac Fribourg 1470",
    "addr:postcode":"estavayer-le-lac;1470",
    "addr:street":"Route De La Chapelle",
    "iso:country":"CH",
    "sg:address":"Route De La Chapelle",
    "sg:city":"Estavayer-le-lac",
    "sg:orig_category":"Berufsberatungen Personal U Stellenvermittlung",
    "sg:phone":"+41 21 944 64 43",
    "sg:postcode":"1470",
    "sg:province":"Fribourg",
    "wof:name":"Centre Dupont Orientation Professionnelle",
    "wof:placetype":"venue"
},
  "geometry": {"coordinates":[6.859652,46.451668],"type":"Point"}
}