{
  "type": "Feature",
  "properties": {
    "iso:country":"CH",
    "sg:address":"Luzernstrasse 18",
    "sg:city":"Ballwil",
    "sg:orig_category":"Zahnarztpraxen",
    "sg:phone":"+41 41 448 32 66",
    "sg:postcode":"6275",
    "sg:province":"Luzern",
    "wof:name":"Dr. Med. Dent. Ulrich Gautsch Zahnarzt",
    "wof:placetype":"venue"
},
  "geometry": {"coordinates":[8.3175554276,47.1513519287],"type":"Point"}
}