{
  "type": "Feature",
  "properties": {
    "iso:country":"CH",
    "sg:address":"Hardturmstrasse 319",
    "sg:city":"Z\u00fcrich",
    "sg:orig_category":"Vermietung von Automobilen",
    "sg:phone":"+41 12725050",
    "sg:postcode":"8005",
    "sg:province":"Z\u00fcrich",
    "wof:name":"Hertz Ag",
    "wof:placetype":"venue"
},
  "geometry": {"coordinates":[8.5062227249,47.3937110901],"type":"Point"}
}