{
  "type": "Feature",
  "properties": {
    "iso:country":"CH",
    "sg:address":"1747",
    "sg:city":"Corserey",
    "sg:classifiers":[
        {
            "category":"Restaurant",
            "type":"Food & Drink"
        }
    ],
    "sg:phone":"+41 26 470 14 44",
    "sg:postcode":"1747",
    "sg:province":"Fribourg",
    "wof:name":"Caf\u00e9 Relais Du Vieux Moulin",
    "wof:placetype":"venue"
},
  "geometry": {"coordinates":[6.9889202118,46.7712287903],"type":"Point"}
}