{
  "type": "Feature",
  "properties": {
    "iso:country":"CH",
    "sg:address":"Flor\u00e9al Avenue 3 1006 Lausanne. Postfach",
    "sg:city":"Lausanne",
    "sg:orig_category":"Detailhandel mit Waren verschiedener Art, Hauptrichtung Nahrungsmittel",
    "sg:postcode":"1003",
    "sg:province":"Vaud",
    "wof:name":"Spurio Alberto Denr\u00e9es Alimentaires; Comm, Fabric Et Repr\u00e9sent",
    "wof:placetype":"venue"
},
  "geometry": {"coordinates":[6.6270651817,46.5143737793],"type":"Point"}
}