{
  "type": "Feature",
  "properties": {
    "addr:full":"Werkhofstrasse 23 4500 Solothurn. Postfach Solothurn Solothurn 4502",
    "addr:housenumber":"23",
    "addr:postcode":"4500 solothurn. postfach;4502",
    "addr:street":"Werkhofstrasse",
    "iso:country":"CH",
    "sg:address":"Werkhofstrasse 23 4500 Solothurn. Postfach",
    "sg:city":"Solothurn",
    "sg:orig_category":"Berufliche Weiterbildung, Erwachsenenbildung",
    "sg:phone":"+41 32 622 97 33",
    "sg:postcode":"4502",
    "sg:province":"Solothurn",
    "wof:name":"Volkshochschule Region Solothurn",
    "wof:placetype":"venue"
},
  "geometry": {"coordinates":[7.536433,47.210506],"type":"Point"}
}