{
  "type": "Feature",
  "properties": {
    "iso:country":"CH",
    "sg:address":"Austrasse 3 3176 Neuenegg. Postfach 11",
    "sg:city":"Neuenegg",
    "sg:orig_category":"Elektroinstallation",
    "sg:postcode":"3176",
    "sg:province":"Bern",
    "wof:name":"Spychiger, Kurt.",
    "wof:placetype":"venue"
},
  "geometry": {"coordinates":[7.3044447899,46.8946838379],"type":"Point"}
}