{
  "type": "Feature",
  "properties": {
    "iso:country":"CH",
    "sg:address":"Rue L'industrie 18",
    "sg:city":"Crissier",
    "sg:orig_category":"Elektroinstallation",
    "sg:postcode":"1023",
    "sg:province":"Vaud",
    "wof:name":"Espinosa Antonio \u00e9lectricit\u00e9",
    "wof:placetype":"venue"
},
  "geometry": {"coordinates":[6.5807418823,46.5414352417],"type":"Point"}
}