{
  "type": "Feature",
  "properties": {
    "iso:country":"CH",
    "sg:address":"Spitalstrasse 21",
    "sg:city":"Basel",
    "sg:orig_category":"Pensionskassen",
    "sg:phone":"+41 61 265 72 36",
    "sg:postcode":"4031",
    "sg:province":"Basel-Stadt",
    "wof:name":"International Foundation For Postgraduate Surgery",
    "wof:placetype":"venue"
},
  "geometry": {"coordinates":[7.5832967758,47.5623970032],"type":"Point"}
}