{
  "type": "Feature",
  "properties": {
    "iso:country":"CH",
    "sg:address":"Case Postale",
    "sg:city":"Sembrancher",
    "sg:classifiers":[
        {
            "category":"Manufacturing",
            "subcategory":"Lumber",
            "type":"Manufacturing & Wholesale Goods"
        }
    ],
    "sg:phone":"+41 32 924 50 00",
    "sg:postcode":"1933",
    "sg:province":"Valais",
    "sg:tags":[
        "hardwood",
        "sawmill"
    ],
    "wof:name":"Scierie Des Eplatures S.a.",
    "wof:placetype":"venue"
},
  "geometry": {"coordinates":[6.8108949661,47.0914535522],"type":"Point"}
}