{
  "type": "Feature",
  "properties": {
    "iso:country":"CH",
    "sg:address":"Kreuzstrasse 4",
    "sg:city":"B\u00fclach",
    "sg:orig_category":"Nahrungsmittel-Industrie: Rohstoffe",
    "sg:postcode":"8180",
    "sg:province":"Z\u00fcrich",
    "wof:name":"Lebensmittel Arcobaleno Ferraro A. & Co",
    "wof:placetype":"venue"
},
  "geometry": {"coordinates":[8.5411663055,47.5192108154],"type":"Point"}
}