{
  "type": "Feature",
  "properties": {
    "iso:country":"CH",
    "sg:address":"Etzelstrasse 10",
    "sg:city":"W\u00e4denswil",
    "sg:orig_category":"Unternehmensberatung Wirtschaftspr\u00fcfung, Steuerberatung U Treuhand",
    "sg:phone":"+41 56 460 89 25",
    "sg:postcode":"8820",
    "sg:province":"Z\u00fcrich",
    "wof:name":"Triflex Treuhand Ag",
    "wof:placetype":"venue"
},
  "geometry": {"coordinates":[8.1846828461,47.4679679871],"type":"Point"}
}