{
  "type": "Feature",
  "properties": {
    "iso:country":"CH",
    "sg:address":"Oberer B\u00fchl 26",
    "sg:city":"Oberthal",
    "sg:orig_category":"G\u00fcterbef\u00f6rderung im Strassenverkehr",
    "sg:phone":"+41 41 855 41 12",
    "sg:postcode":"3531",
    "sg:province":"Bern",
    "wof:name":"Translady Gmbh",
    "wof:placetype":"venue"
},
  "geometry": {"coordinates":[7.6738247871,46.9164161682],"type":"Point"}
}