{
  "type": "Feature",
  "properties": {
    "iso:country":"CH",
    "sg:address":"Ueberbach 6",
    "sg:city":"Untervaz",
    "sg:orig_category":"Herstellung von sonstigen Fahrzeugen",
    "sg:phone":"+41 81 322 21 61",
    "sg:postcode":"7204",
    "sg:province":"Graubunden",
    "wof:name":"Benedikt Sch\u00e4dler Wagnerei",
    "wof:placetype":"venue"
},
  "geometry": {"coordinates":[9.5329618454,46.9281654358],"type":"Point"}
}