{
  "type": "Feature",
  "properties": {
    "iso:country":"CH",
    "sg:address":"Obere Wilenhalde 13",
    "sg:city":"Herisau",
    "sg:orig_category":"Unternehmensberatung",
    "sg:postcode":"9100",
    "sg:province":"Appenzell Ausserrhoden",
    "wof:name":"Widmer C. Beratungen",
    "wof:placetype":"venue"
},
  "geometry": {"coordinates":[9.2804527283,47.3777275085],"type":"Point"}
}