{
  "type": "Feature",
  "properties": {
    "iso:country":"CH",
    "sg:address":"Schulhausstrasse 1",
    "sg:city":"Uznach",
    "sg:orig_category":"P\u00e9dicure",
    "sg:phone":"+41 55 280 37 47",
    "sg:postcode":"8730",
    "sg:province":"St. Gallen",
    "wof:name":"Yvonne Kuster Podologie-praxis",
    "wof:placetype":"venue"
},
  "geometry": {"coordinates":[8.9835329056,47.2252807617],"type":"Point"}
}