{
  "type": "Feature",
  "properties": {
    "iso:country":"CH",
    "sg:address":"Seroute 56a",
    "sg:city":"Montsevelier",
    "sg:classifiers":[
        {
            "category":"Shopping",
            "subcategory":"Discount & Variety Stores",
            "type":"Retail Goods"
        }
    ],
    "sg:phone":"+41 79 250 43 15",
    "sg:postcode":"2828",
    "sg:province":"Jura",
    "sg:tags":[
        "shop",
        "locksmith's"
    ],
    "wof:name":"R\u00e9paration Et Soudage Claude Beuchat",
    "wof:placetype":"venue"
},
  "geometry": {"coordinates":[7.5077900887,47.3606987],"type":"Point"}
}