{
  "type": "Feature",
  "properties": {
    "iso:country":"CH",
    "sg:address":"Pfannenstilstrasse 3",
    "sg:city":"W\u00e4denswil",
    "sg:classifiers":[
        {
            "category":"Professional",
            "subcategory":"Computer Services",
            "type":"Services"
        }
    ],
    "sg:phone":"+41 17839661",
    "sg:postcode":"8820",
    "sg:province":"Z\u00fcrich",
    "sg:tags":[
        "administration",
        "software"
    ],
    "wof:name":"Panorgan Ag",
    "wof:placetype":"venue"
},
  "geometry": {"coordinates":[8.654013,47.231403],"type":"Point"}
}