{
  "type": "Feature",
  "properties": {
    "iso:country":"CH",
    "sg:address":"B\u00e2timent Am\u00e9thyste Roches-grises Villars 1867 Ollon Vd. Postfach",
    "sg:city":"Villars-sur-ollon",
    "sg:orig_category":"Allgemeiner Hoch U Tiefbau",
    "sg:phone":"+41 26 652 33 87",
    "sg:postcode":"1884",
    "sg:province":"Vaud",
    "wof:name":"Entreprise Ropraz Sa",
    "wof:placetype":"venue"
},
  "geometry": {"coordinates":[6.95338,46.694305],"type":"Point"}
}