{
  "type": "Feature",
  "properties": {
    "iso:country":"CH",
    "sg:address":"Route Du Centre 27 1723 Marly Case Postale 66",
    "sg:city":"Marly",
    "sg:orig_category":"Grosshandel mit Textilien",
    "sg:phone":"+41 32 322 22 06",
    "sg:postcode":"1723",
    "sg:province":"Fribourg",
    "wof:name":"Fink Import",
    "wof:placetype":"venue"
},
  "geometry": {"coordinates":[7.3792061806,47.1856498718],"type":"Point"}
}