{
  "type": "Feature",
  "properties": {
    "iso:country":"CH",
    "sg:address":"St. Johanns-ring 130",
    "sg:city":"Basel",
    "sg:orig_category":"Bauspenglerei Sanit\u00e4rinstallation",
    "sg:phone":"+41 61 321 92 92",
    "sg:postcode":"4056",
    "sg:province":"Basel-Stadt",
    "wof:name":"Ibach & Co",
    "wof:placetype":"venue"
},
  "geometry": {"coordinates":[7.574352,47.562328],"type":"Point"}
}