{
  "type": "Feature",
  "properties": {
    "iso:country":"CH",
    "sg:address":"Mitteldorfstrasse 1",
    "sg:city":"Ober\u00e4geri",
    "sg:classifiers":[
        {
            "category":"Travel",
            "subcategory":"Hotels & Motels",
            "type":"Entertainment"
        }
    ],
    "sg:phone":"+41 41 750 12 36",
    "sg:postcode":"6315",
    "sg:province":"Zug",
    "sg:tags":[
        "hotels",
        "mit",
        "restaurant"
    ],
    "wof:name":"Gasthaus Zum R\u00f6ssli, Guido Schneider",
    "wof:placetype":"venue"
},
  "geometry": {"coordinates":[8.6127710342,47.1352539062],"type":"Point"}
}