{
  "type": "Feature",
  "properties": {
    "iso:country":"CH",
    "sg:address":"Hurdnerstrasse 117",
    "sg:city":"Hurden",
    "sg:orig_category":"Unclassifiable Establishments",
    "sg:phone":"+41 33 971 33 81",
    "sg:postcode":"8640",
    "sg:province":"Schwyz",
    "wof:name":"Wehren Hans",
    "wof:placetype":"venue"
},
  "geometry": {"coordinates":[8.2025403976,46.7372512817],"type":"Point"}
}