{
  "type": "Feature",
  "properties": {
    "iso:country":"CH",
    "sg:address":"Niederlenzerstrasse 27",
    "sg:city":"Lenzburg",
    "sg:orig_category":"Unclassifiable Establishments",
    "sg:postcode":"5600",
    "sg:province":"Aargau",
    "wof:name":"Are & Dee Holding Ag",
    "wof:placetype":"venue"
},
  "geometry": {"coordinates":[8.1803951263,47.3900337219],"type":"Point"}
}