{
  "type": "Feature",
  "properties": {
    "iso:country":"CH",
    "sg:address":"Gewerbezentrum Wilen",
    "sg:city":"Kaltbrunn",
    "sg:orig_category":"Rechtsberatung",
    "sg:postcode":"8722",
    "sg:province":"St. Gallen",
    "wof:name":"Accelerated Teaching Solutions Ag",
    "wof:placetype":"venue"
},
  "geometry": {"coordinates":[8.7901973724,47.2036628723],"type":"Point"}
}