{
  "type": "Feature",
  "properties": {
    "iso:country":"CH",
    "sg:address":"Klosterplatz 19",
    "sg:city":"Olten",
    "sg:classifiers":[
        {
            "category":"Restaurant",
            "type":"Food & Drink"
        }
    ],
    "sg:phone":"+41 62 212 13 48",
    "sg:postcode":"4600",
    "sg:province":"Solothurn",
    "wof:name":"Restaurant Spaghetteria",
    "wof:placetype":"venue"
},
  "geometry": {"coordinates":[7.9039678574,47.3503417969],"type":"Point"}
}