{
  "type": "Feature",
  "properties": {
    "iso:country":"CH",
    "sg:address":"Am Bach 39",
    "sg:city":"B\u00e4rschwil",
    "sg:orig_category":"Sonstige mit Sport verbundene T\u00e4tigkeiten",
    "sg:postcode":"4252",
    "sg:province":"Solothurn",
    "wof:name":"Haflingerhof Moser E.",
    "wof:placetype":"venue"
},
  "geometry": {"coordinates":[7.4707789421,47.380279541],"type":"Point"}
}