{
  "type": "Feature",
  "properties": {
    "iso:country":"CH",
    "sg:address":"7050",
    "sg:city":"Arosa",
    "sg:orig_category":"Erschliessung von Grundst\u00fccken",
    "sg:postcode":"7050",
    "sg:province":"Graubunden",
    "wof:name":"Eisenbahner-wohnbaugenossenschaft Furka",
    "wof:placetype":"venue"
},
  "geometry": {"coordinates":[9.6765518188,46.7778625488],"type":"Point"}
}