{
  "type": "Feature",
  "properties": {
    "iso:country":"CH",
    "sg:address":"Etzelstrasse 3 8730 Uznach. Postfach 250",
    "sg:city":"Uznach",
    "sg:orig_category":"Detailhandel mit Metallwaren, Anstrichmitteln, Glaswaren, Bau U Heimwerkerbedarf Herstellung von Kun",
    "sg:phone":"+41 55 280 19 94",
    "sg:postcode":"8730",
    "sg:province":"St. Gallen",
    "wof:name":"Hilty Engineering Ag",
    "wof:placetype":"venue"
},
  "geometry": {"coordinates":[8.9684839249,47.2285118103],"type":"Point"}
}