{
  "type": "Feature",
  "properties": {
    "iso:country":"CH",
    "sg:address":"Quartier De La Joux 2 1450 Ste-croix. Postfach",
    "sg:city":"Ste-croix",
    "sg:orig_category":"Herstellung von Uhren",
    "sg:phone":"+41 32 968 08 08",
    "sg:postcode":"1450",
    "sg:province":"Vaud",
    "wof:name":"Jaquet-baume Sa",
    "wof:placetype":"venue"
},
  "geometry": {"coordinates":[6.8304710388,47.1052627563],"type":"Point"}
}