{
  "type": "Feature",
  "properties": {
    "iso:country":"CH",
    "sg:address":"Stationsstrasse 43",
    "sg:city":"Wallenwil",
    "sg:orig_category":"Zimmerei, Dachdeckerei, Bauspenglerei U Abdichtung",
    "sg:phone":"+41 79 697 18 21",
    "sg:postcode":"8360",
    "sg:province":"Thurgau",
    "wof:name":"Raschle Hans",
    "wof:placetype":"venue"
},
  "geometry": {"coordinates":[8.9557685852,47.454826355],"type":"Point"}
}