{
  "type": "Feature",
  "properties": {
    "iso:country":"CH",
    "sg:address":"Lettenstrasse 1 6343 Rotkreuz. Postfach 244",
    "sg:city":"Rotkreuz",
    "sg:orig_category":"Grosshandel mit sonstigen Gebrauchs U Verbrauchsg\u00fctern Herstellung von Papier, Karton U Pappe",
    "sg:phone":"+41 81 756 74 14",
    "sg:postcode":"6343",
    "sg:province":"Zug",
    "wof:name":"Meierhans Papier Ag",
    "wof:placetype":"venue"
},
  "geometry": {"coordinates":[9.4739122391,47.1663551331],"type":"Point"}
}