{
  "type": "Feature",
  "properties": {
    "iso:country":"CH",
    "sg:address":"Rue Jean-grimoux 17 1700 Fribourg Case Postale 904",
    "sg:city":"Fribourg",
    "sg:orig_category":"Betrieb von Taxis",
    "sg:phone":"+41 26 466 10 10",
    "sg:postcode":"1701",
    "sg:province":"Fribourg",
    "wof:name":"Taxis-r\u00e9unis Abc Sa",
    "wof:placetype":"venue"
},
  "geometry": {"coordinates":[7.155357,46.809608],"type":"Point"}
}