{
  "type": "Feature",
  "properties": {
    "iso:country":"CH",
    "sg:address":"Eichstrasse 85",
    "sg:city":"Uerikon",
    "sg:orig_category":"Herstellung von keramischen Wand U Bodenfliesen U platten",
    "sg:postcode":"8713",
    "sg:province":"Z\u00fcrich",
    "wof:name":"Rolf Schmalz Keram. Wand Und Bodenbel\u00e4ge",
    "wof:placetype":"venue"
},
  "geometry": {"coordinates":[8.7498559952,47.2375907898],"type":"Point"}
}