{
  "type": "Feature",
  "properties": {
    "iso:country":"CH",
    "sg:address":"Ergolzstrasse 21",
    "sg:city":"Pratteln",
    "sg:orig_category":"Sportvereine Behindertensport",
    "sg:phone":"+41 61 811 36 11",
    "sg:postcode":"4133",
    "sg:province":"Basel-Landschaft",
    "wof:name":"Svbs Basel Siv",
    "wof:placetype":"venue"
},
  "geometry": {"coordinates":[7.7134418488,47.5305595398],"type":"Point"}
}