{
  "type": "Feature",
  "properties": {
    "iso:country":"CH",
    "sg:address":"Klarastrasse 12",
    "sg:city":"Arbon",
    "sg:orig_category":"Tankstellen",
    "sg:phone":"+41 71 446 90 04",
    "sg:postcode":"9320",
    "sg:province":"Thurgau",
    "wof:name":"Coop Tankstelle",
    "wof:placetype":"venue"
},
  "geometry": {"coordinates":[9.4313268661,47.5106124878],"type":"Point"}
}