{
  "type": "Feature",
  "properties": {
    "iso:country":"CH",
    "sg:address":"M\u00fchlegasse 11 3400 Burgdorf. Postfach",
    "sg:city":"Burgdorf",
    "sg:orig_category":"Verwaltung von Immobilien",
    "sg:phone":"+41 61 756 66 55",
    "sg:postcode":"3401",
    "sg:province":"Bern",
    "wof:name":"Treuhand Thommen Ag",
    "wof:placetype":"venue"
},
  "geometry": {"coordinates":[7.5978589058,47.4669914246],"type":"Point"}
}