{
  "type": "Feature",
  "properties": {
    "iso:country":"CH",
    "sg:address":"Chaulin",
    "sg:city":"Chamby",
    "sg:classifiers":[
        {
            "category":"Restaurant",
            "type":"Food & Drink"
        }
    ],
    "sg:phone":"+41 21 964 46 18",
    "sg:postcode":"1832",
    "sg:province":"Vaud",
    "wof:name":"Restaurant Clos Des Alpes",
    "wof:placetype":"venue"
},
  "geometry": {"coordinates":[6.9136199951,46.4489631653],"type":"Point"}
}