{
  "type": "Feature",
  "properties": {
    "iso:country":"CH",
    "sg:address":"Voltastrasse 69 8044 Z\u00fcrich. Postfach",
    "sg:city":"Z\u00fcrich",
    "sg:orig_category":"Herstellung von sonstigen Maschinen f\u00fcr bestimmte Verwendung",
    "sg:phone":"+41 12515180",
    "sg:postcode":"8044",
    "sg:province":"Z\u00fcrich",
    "wof:name":"Color-print Cp Ag Grafische Erzeugnisse; Herstellung U. Vertrieb Usw.",
    "wof:placetype":"venue"
},
  "geometry": {"coordinates":[8.5547447205,47.380115509],"type":"Point"}
}