{
  "type": "Feature",
  "properties": {
    "iso:country":"CH",
    "sg:address":"Sonnenwiesenstr. 2",
    "sg:city":"Kreuzlingen",
    "sg:classifiers":[
        {
            "category":"Professional",
            "subcategory":"Advertising",
            "type":"Services"
        }
    ],
    "sg:phone":"+41 71 686 54 54",
    "sg:postcode":"8280",
    "sg:province":"Thurgau",
    "sg:tags":[
        "pre",
        "information",
        "medium",
        "equipment",
        "communication",
        "instrument",
        "optical"
    ],
    "wof:name":"Photocolor Kreuzlingen Ag",
    "wof:placetype":"venue"
},
  "geometry": {"coordinates":[9.187803,47.646828],"type":"Point"}
}