{
  "type": "Feature",
  "properties": {
    "iso:country":"CH",
    "sg:address":"Avenue Warnery 8 1110 Morges. Postfach",
    "sg:city":"Morges",
    "sg:classifiers":[
        {
            "category":"Restaurant",
            "type":"Food & Drink"
        }
    ],
    "sg:phone":"+41 21 803 00 63",
    "sg:postcode":"1110",
    "sg:province":"Vaud",
    "sg:tags":[
        "tea-rooms",
        "restaurants"
    ],
    "wof:name":"Caf\u00e9-restaurant Des Eaux-min\u00e9rales, Moser Jean-fran\u00e7ois",
    "wof:placetype":"venue"
},
  "geometry": {"coordinates":[6.4890608788,46.511302948],"type":"Point"}
}