{
  "type": "Feature",
  "properties": {
    "iso:country":"CH",
    "sg:address":"Rebhaldenstrasse 23",
    "sg:city":"Neerach",
    "sg:orig_category":"Grids, Welded",
    "sg:phone":"+41 18583530",
    "sg:postcode":"8173",
    "sg:province":"Z\u00fcrich",
    "wof:name":"Trefil Ag",
    "wof:placetype":"venue"
},
  "geometry": {"coordinates":[8.4707727432,47.5008544922],"type":"Point"}
}