{
  "type": "Feature",
  "properties": {
    "iso:country":"CH",
    "sg:address":"Ferme Des Iles",
    "sg:city":"Martigny",
    "sg:orig_category":"Obstbau",
    "sg:phone":"+41 79 221 02 26",
    "sg:postcode":"1920",
    "sg:province":"Valais",
    "wof:name":"Candide & Hilaire Bonvin Cultures Fruiti\u00e8res",
    "wof:placetype":"venue"
},
  "geometry": {"coordinates":[7.0582389832,46.1257362366],"type":"Point"}
}