{
  "type": "Feature",
  "properties": {
    "iso:country":"CH",
    "sg:address":"Schwerzenbachstrasse 12",
    "sg:city":"F\u00e4llanden",
    "sg:orig_category":"Herstellung von sonstigen Metallwaren Pulvermetallurgie Schmieden, Pressen, Stanzen U Profilwalzen v",
    "sg:phone":"+41 18253134",
    "sg:postcode":"8117",
    "sg:province":"Z\u00fcrich",
    "wof:name":"Wegmann H. J. Metallwaren",
    "wof:placetype":"venue"
},
  "geometry": {"coordinates":[8.6409435272,47.3723182678],"type":"Point"}
}