{
  "type": "Feature",
  "properties": {
    "iso:country":"CH",
    "sg:address":"Gurtengasse 2",
    "sg:city":"Bern",
    "sg:orig_category":"Arztpraxen",
    "sg:phone":"+41 62 771 17 74",
    "sg:postcode":"3011",
    "sg:province":"Bern",
    "wof:name":"Dr.med.walter Peterhans Spezialarzt Fmh",
    "wof:placetype":"venue"
},
  "geometry": {"coordinates":[8.176077,47.251999],"type":"Point"}
}