{
  "type": "Feature",
  "properties": {
    "iso:country":"CH",
    "sg:address":"Baarerstrasse 2 6300 Zug. Postfach 4251",
    "sg:city":"Zug",
    "sg:orig_category":"Unternehmensberatung",
    "sg:phone":"+41 41 711 18 68",
    "sg:postcode":"6304",
    "sg:province":"Zug",
    "wof:name":"Buri Fred W.",
    "wof:placetype":"venue"
},
  "geometry": {"coordinates":[8.5161046982,47.1706962585],"type":"Point"}
}