{
  "type": "Feature",
  "properties": {
    "iso:country":"CH",
    "sg:address":"Wilerstrasse 1 8575 Istighofen. Postfach",
    "sg:city":"Istighofen",
    "sg:orig_category":"Herstellung von Ziegeln U sonstiger Baukeramik",
    "sg:phone":"+41 71 634 88 44",
    "sg:postcode":"8575",
    "sg:province":"Thurgau",
    "wof:name":"Zz Wancor",
    "wof:placetype":"venue"
},
  "geometry": {"coordinates":[9.1491622925,47.5441551208],"type":"Point"}
}