{
  "type": "Feature",
  "properties": {
    "iso:country":"CH",
    "sg:address":"Stockenstrasse 11c",
    "sg:city":"Algetshausen",
    "sg:orig_category":"Instandhaltung U Reparatur von Automobilen",
    "sg:phone":"+41 71 951 70 06",
    "sg:postcode":"9249",
    "sg:province":"St. Gallen",
    "wof:name":"Reto Montibeller Carrosserie",
    "wof:placetype":"venue"
},
  "geometry": {"coordinates":[9.1085805893,47.4464111328],"type":"Point"}
}