{
  "type": "Feature",
  "properties": {
    "iso:country":"CH",
    "sg:address":"St. Alban-vorstadt 5",
    "sg:city":"Basel",
    "sg:classifiers":[
        {
            "category":"Professional",
            "subcategory":"Employment Agencies",
            "type":"Services"
        }
    ],
    "sg:postcode":"4052",
    "sg:province":"Basel-Stadt",
    "sg:tags":[
        "personal",
        "u",
        "stellenvermittlung"
    ],
    "wof:name":"Verein Zur F\u00f6rderung Der Beruflichen Neuorientierung (fbn)",
    "wof:placetype":"venue"
},
  "geometry": {"coordinates":[7.5952701569,47.5547981262],"type":"Point"}
}