{
  "type": "Feature",
  "properties": {
    "iso:country":"CH",
    "sg:address":"Dorf",
    "sg:city":"Trachselwald",
    "sg:classifiers":[
        {
            "category":"Travel",
            "subcategory":"Hotels & Motels",
            "type":"Entertainment"
        }
    ],
    "sg:phone":"+41 34 431 11 45",
    "sg:postcode":"3456",
    "sg:province":"Bern",
    "sg:tags":[
        "hotels",
        "mit",
        "restaurant"
    ],
    "wof:name":"Gasthof Zur Tanne, Daniel Luginb\u00fchl",
    "wof:placetype":"venue"
},
  "geometry": {"coordinates":[7.7379698753,47.0169410706],"type":"Point"}
}