{
  "type": "Feature",
  "properties": {
    "iso:country":"CH",
    "sg:address":"Chemin De La R\u00e9che 49",
    "sg:city":"Bulle",
    "sg:orig_category":"Solarien",
    "sg:phone":"+41 26 912 92 22",
    "sg:postcode":"1630",
    "sg:province":"Fribourg",
    "wof:name":"Fitness-center & Solarium Jack's Sporting Center",
    "wof:placetype":"venue"
},
  "geometry": {"coordinates":[7.0515780449,46.616897583],"type":"Point"}
}