{
  "type": "Feature",
  "properties": {
    "iso:country":"CH",
    "sg:address":"Grieshalde 6",
    "sg:city":"Diessenhofen",
    "sg:orig_category":"Interessenvertretungen",
    "sg:postcode":"8253",
    "sg:province":"Thurgau",
    "wof:name":"A.o. Fundstiftung",
    "wof:placetype":"venue"
},
  "geometry": {"coordinates":[8.7445697784,47.6886444092],"type":"Point"}
}