{
  "type": "Feature",
  "properties": {
    "iso:country":"CH",
    "sg:address":"Route De Bossey 50",
    "sg:city":"Troinex",
    "sg:orig_category":"Gem\u00fcsebau",
    "sg:phone":"+41 22 784 32 08",
    "sg:postcode":"1256",
    "sg:province":"Gen\u00e8ve",
    "wof:name":"Georges H\u00e9ritier Maraicher",
    "wof:placetype":"venue"
},
  "geometry": {"coordinates":[6.1582331657,46.1592025757],"type":"Point"}
}