{
  "type": "Feature",
  "properties": {
    "iso:country":"CH",
    "sg:address":"M\u00e9tiers Rue Des 2 1008 Prilly Case Postale 240",
    "sg:city":"Prilly",
    "sg:orig_category":"Non-Classified Establishments",
    "sg:phone":"+41 21 697 60 60",
    "sg:postcode":"1008",
    "sg:province":"Vaud",
    "wof:name":"Dunes Technologies S.a.",
    "wof:placetype":"venue"
},
  "geometry": {"coordinates":[6.5580701828,46.5100784302],"type":"Point"}
}