{
  "type": "Feature",
  "properties": {
    "iso:country":"CH",
    "sg:address":"Seestrasse 855",
    "sg:city":"Meilen",
    "sg:orig_category":"Wirtschaftspr\u00fcfung, Steuerberatung U Treuhand",
    "sg:phone":"+41 19230881",
    "sg:postcode":"8706",
    "sg:province":"Z\u00fcrich",
    "wof:name":"Bruno Kunz, Buchhaltungsb\u00fcro",
    "wof:placetype":"venue"
},
  "geometry": {"coordinates":[8.6507797241,47.2660903931],"type":"Point"}
}