{
  "type": "Feature",
  "properties": {
    "addr:full":"Letzistr.2 Ganterschwil St. Gallen 9608",
    "addr:housenumber":"9608",
    "addr:street":"Ganterschwil",
    "iso:country":"CH",
    "sg:address":"Letzistr.2",
    "sg:city":"Ganterschwil",
    "sg:orig_category":"Bildung and Forschung, Museen",
    "sg:postcode":"9608",
    "sg:province":"St. Gallen",
    "wof:name":"Internetgemeinde: Ihre T\u00e4gliche Christliche Andacht",
    "wof:placetype":"venue"
},
  "geometry": {"coordinates":[9.089514,47.38134],"type":"Point"}
}