{
  "type": "Feature",
  "properties": {
    "iso:country":"CH",
    "sg:address":"Rue Du Clos 3",
    "sg:city":"Moutier",
    "sg:orig_category":"Sonstige Institutionen des Sozialwesens ohne Beherbergung",
    "sg:phone":"+41 32 493 20 72",
    "sg:postcode":"2740",
    "sg:province":"Bern",
    "wof:name":"Centre De Pu\u00e9riculture",
    "wof:placetype":"venue"
},
  "geometry": {"coordinates":[7.3712439537,47.2772521973],"type":"Point"}
}