{
  "type": "Feature",
  "properties": {
    "iso:country":"CH",
    "sg:address":"Dorfplatz 10",
    "sg:city":"Reigoldswil",
    "sg:classifiers":[
        {
            "category":"Restaurant",
            "type":"Food & Drink"
        }
    ],
    "sg:phone":"+41 61 941 14 15",
    "sg:postcode":"4418",
    "sg:province":"Basel-Landschaft",
    "wof:name":"Restaurant Rebstock",
    "wof:placetype":"venue"
},
  "geometry": {"coordinates":[7.6913938522,47.3969955444],"type":"Point"}
}