{
  "type": "Feature",
  "properties": {
    "iso:country":"CH",
    "sg:address":"Steihaui 4c",
    "sg:city":"Remetschwil",
    "sg:orig_category":"Arztpraxen",
    "sg:phone":"+41 56 496 72 88",
    "sg:postcode":"5453",
    "sg:province":"Aargau",
    "wof:name":"Dr.med.ursula Senn Spezial\u00e4rztin",
    "wof:placetype":"venue"
},
  "geometry": {"coordinates":[8.319303,47.410679],"type":"Point"}
}