{
  "type": "Feature",
  "properties": {
    "iso:country":"CH",
    "sg:address":"Listrigstrasse 8 6020 Emmenbr\u00fccke. Postfach",
    "sg:city":"Emmenbr\u00fccke",
    "sg:orig_category":"Sonstige mit der Informatik verbundene T\u00e4tigkeiten",
    "sg:postcode":"6020",
    "sg:province":"Luzern",
    "wof:name":"Computer And Systems L\u00f6rch",
    "wof:placetype":"venue"
},
  "geometry": {"coordinates":[8.2651147842,47.0813941956],"type":"Point"}
}