{
  "type": "Feature",
  "properties": {
    "iso:country":"CH",
    "sg:address":"1967",
    "sg:city":"Bramois",
    "sg:orig_category":"Erdbewegungsarbeiten G\u00fcterbef\u00f6rderung im Strassenverkehr",
    "sg:phone":"+41 27 203 15 72",
    "sg:postcode":"1967",
    "sg:province":"Valais",
    "wof:name":"Chevrier Nicolas",
    "wof:placetype":"venue"
},
  "geometry": {"coordinates":[7.4026799202,46.2301216125],"type":"Point"}
}