{
  "type": "Feature",
  "properties": {
    "iso:country":"CH",
    "sg:address":"Bahnhofstrasse 30",
    "sg:city":"Schaffhausen",
    "sg:orig_category":"Vermietung U Verpachtung von eigenen Immobilien",
    "sg:postcode":"8200",
    "sg:province":"Schaffhausen",
    "wof:name":"Konforta Immobilien-treuhand Ag",
    "wof:placetype":"venue"
},
  "geometry": {"coordinates":[9.2466087341,47.4197807312],"type":"Point"}
}