{
  "type": "Feature",
  "properties": {
    "iso:country":"CH",
    "sg:address":"Rue De La Malti\u00e8re 33",
    "sg:city":"Porrentruy",
    "sg:orig_category":"Sportvereine Ballsport Tischtennis",
    "sg:phone":"+41 32 466 40 74",
    "sg:postcode":"2900",
    "sg:province":"Jura",
    "wof:name":"Ctt Porrentruy",
    "wof:placetype":"venue"
},
  "geometry": {"coordinates":[7.0858411789,47.4176445007],"type":"Point"}
}