{
  "type": "Feature",
  "properties": {
    "iso:country":"CH",
    "sg:address":"Rosenweg 7",
    "sg:city":"Itingen",
    "sg:orig_category":"Vereine Milit\u00e4r",
    "sg:postcode":"4452",
    "sg:province":"Basel-Landschaft",
    "wof:name":"Unteroffiziersverein Bl",
    "wof:placetype":"venue"
},
  "geometry": {"coordinates":[7.7894020081,47.4684829712],"type":"Point"}
}