{
  "type": "Feature",
  "properties": {
    "iso:country":"CH",
    "sg:address":"Geerenstrasse 6 8157 Dielsdorf. Postfach 266",
    "sg:city":"Dielsdorf",
    "sg:orig_category":"Versicherungen Generalagenturen",
    "sg:phone":"+41 32 322 21 31",
    "sg:postcode":"8157",
    "sg:province":"Z\u00fcrich",
    "wof:name":"Die Mobiliar Versicherungen & Vorsorge",
    "wof:placetype":"venue"
},
  "geometry": {"coordinates":[7.2491521835,47.1404037476],"type":"Point"}
}