{
  "type": "Feature",
  "properties": {
    "iso:country":"CH",
    "sg:address":"Gundeldingerrain 53",
    "sg:city":"Basel",
    "sg:orig_category":"Non-Classified Establishments",
    "sg:postcode":"4059",
    "sg:province":"Basel-Stadt",
    "wof:name":"Galerie24.ch Sunset Trading Ag",
    "wof:placetype":"venue"
},
  "geometry": {"coordinates":[79.1580276489,18.26404953],"type":"Point"}
}