{
  "type": "Feature",
  "properties": {
    "iso:country":"CH",
    "sg:address":"Bahnhofstrasse 20",
    "sg:city":"Dagmersellen",
    "sg:orig_category":"Grosshandel mit Werkzeugmaschinen",
    "sg:phone":"+41 62 756 04 00",
    "sg:postcode":"6252",
    "sg:province":"Luzern",
    "wof:name":"Reconda Ag",
    "wof:placetype":"venue"
},
  "geometry": {"coordinates":[7.9796199799,47.2184791565],"type":"Point"}
}