{
  "type": "Feature",
  "properties": {
    "iso:country":"CH",
    "sg:address":"Aspholzstrasse 29",
    "sg:city":"Z\u00fcrich",
    "sg:classifiers":[
        {
            "category":"Building & Trades",
            "subcategory":"Electrical",
            "type":"Services"
        }
    ],
    "sg:phone":"+41 13719524",
    "sg:postcode":"8046",
    "sg:province":"Z\u00fcrich",
    "sg:tags":[
        "disassembly",
        "assembly",
        "stand",
        "fair"
    ],
    "wof:name":"Pineroli-fink Messebau",
    "wof:placetype":"venue"
},
  "geometry": {"coordinates":[8.498944,47.424183],"type":"Point"}
}