{
  "type": "Feature",
  "properties": {
    "iso:country":"CH",
    "sg:address":"D\u00fcbendorfstrasse 223",
    "sg:city":"Z\u00fcrich",
    "sg:orig_category":"Herstellung von Teppichen",
    "sg:phone":"+41 13211022",
    "sg:postcode":"8037",
    "sg:province":"Z\u00fcrich",
    "wof:name":"Luzi's Heimbodenmarkt Gmbh",
    "wof:placetype":"venue"
},
  "geometry": {"coordinates":[8.5860757828,47.4004249573],"type":"Point"}
}