{
  "type": "Feature",
  "properties": {
    "iso:country":"CH",
    "sg:address":"Davidsbodenstrasse 64",
    "sg:city":"Basel",
    "sg:orig_category":"Ausbaugewerbe Reinigungsgewerbe",
    "sg:phone":"+41 61 321 10 17",
    "sg:postcode":"4056",
    "sg:province":"Basel-Stadt",
    "wof:name":"Top-cleaning Gmbh",
    "wof:placetype":"venue"
},
  "geometry": {"coordinates":[7.575498,47.567039],"type":"Point"}
}