{
  "type": "Feature",
  "properties": {
    "iso:country":"CH",
    "sg:address":"Rue Des Sorbiers 670",
    "sg:city":"Fontenais",
    "sg:orig_category":"Maler U Glasergewerbe",
    "sg:postcode":"2902",
    "sg:province":"Jura",
    "wof:name":"Pedro Sanchez Benitez, Entreprise De Peinture",
    "wof:placetype":"venue"
},
  "geometry": {"coordinates":[7.0805649757,47.3984146118],"type":"Point"}
}