{
  "type": "Feature",
  "properties": {
    "iso:country":"CH",
    "sg:address":"Goldacherstrasse 11",
    "sg:city":"T\u00fcbach",
    "sg:orig_category":"Instandhaltung U Reparatur von Automobilen",
    "sg:phone":"+41 71 841 78 66",
    "sg:postcode":"9327",
    "sg:province":"St. Gallen",
    "wof:name":"Bruno Weiersm\u00fcller Autogarage",
    "wof:placetype":"venue"
},
  "geometry": {"coordinates":[9.4574890137,47.4856681824],"type":"Point"}
}