{
  "type": "Feature",
  "properties": {
    "iso:country":"CH",
    "sg:address":"Oberdorfstrasse 10",
    "sg:city":"Wigoltingen",
    "sg:orig_category":"Handel mit Automobilen",
    "sg:postcode":"8556",
    "sg:province":"Thurgau",
    "wof:name":"Rfh Gmbh",
    "wof:placetype":"venue"
},
  "geometry": {"coordinates":[9.0327615738,47.5955505371],"type":"Point"}
}