{
  "type": "Feature",
  "properties": {
    "iso:country":"CH",
    "sg:address":"Kantonsstrasse 6212 St. Erhard. Postfach",
    "sg:city":"Sursee",
    "sg:orig_category":"Handelsvermittlung U Grosshandel Technische, physikalische U chemische Untersuchung",
    "sg:phone":"+41 41 921 20 68",
    "sg:postcode":"6210",
    "sg:province":"Luzern",
    "wof:name":"Sac-o-mat (schweiz) Ag",
    "wof:placetype":"venue"
},
  "geometry": {"coordinates":[8.0744695663,47.1829185486],"type":"Point"}
}