{
  "type": "Feature",
  "properties": {
    "iso:country":"CH",
    "sg:address":"Werkhofstrasse 52",
    "sg:city":"Solothurn",
    "sg:orig_category":"Bauingenieurb\u00fcros Heizung L\u00fcftung Klima Planer f\u00fcr Alternativenergie and Solararchitektur",
    "sg:phone":"+41 32 621 20 55",
    "sg:postcode":"4500",
    "sg:province":"Solothurn",
    "wof:name":"Enerconom Ag Ingenieurb\u00fcro",
    "wof:placetype":"venue"
},
  "geometry": {"coordinates":[7.540431,47.210258],"type":"Point"}
}