{
  "type": "Feature",
  "properties": {
    "iso:country":"CH",
    "sg:address":"Rue Du Petit-ch\u00eane 18",
    "sg:city":"Lausanne",
    "sg:orig_category":"Gymnastik U Fitnesszentren Saunas, Solarien, Fitnesszentren U \u00e4hnliches",
    "sg:phone":"+41 21 323 20 12",
    "sg:postcode":"1003",
    "sg:province":"Vaud",
    "wof:name":"Institut Richemont, Marcel Baer",
    "wof:placetype":"venue"
},
  "geometry": {"coordinates":[6.6302847862,46.518989563],"type":"Point"}
}