{
  "type": "Feature",
  "properties": {
    "iso:country":"CH",
    "sg:address":"6877",
    "sg:city":"Coldrerio",
    "sg:orig_category":"Detailhandel mit Waren verschiedener Art, Hauptrichtung Nahrungsmittel",
    "sg:phone":"+41 91 746 15 93",
    "sg:postcode":"6877",
    "sg:province":"Ticino",
    "wof:name":"Societ\u00e0 Cooperativa Di Consumo Dell'alta Verzasca",
    "wof:placetype":"venue"
},
  "geometry": {"coordinates":[8.7924995422,46.2998199463],"type":"Point"}
}