{
  "type": "Feature",
  "properties": {
    "iso:country":"CH",
    "sg:address":"Bahnhofstrasse 91",
    "sg:city":"Schwyz",
    "sg:orig_category":"Interessenvertretungen",
    "sg:postcode":"6430",
    "sg:province":"Schwyz",
    "wof:name":"Von Reding Biberegg-stiftung",
    "wof:placetype":"venue"
},
  "geometry": {"coordinates":[8.6390695572,47.0232086182],"type":"Point"}
}