{
  "type": "Feature",
  "properties": {
    "iso:country":"CH",
    "sg:address":"Holeestrasse 3",
    "sg:city":"Basel",
    "sg:orig_category":"Fahrschulen, Flugschulen",
    "sg:phone":"+41 76 348 77 44",
    "sg:postcode":"4054",
    "sg:province":"Basel-Stadt",
    "wof:name":"Verkehrsp\u00e4dagogisches Institut (vpi)",
    "wof:placetype":"venue"
},
  "geometry": {"coordinates":[7.574901104,47.5442237854],"type":"Point"}
}