{
  "type": "Feature",
  "properties": {
    "iso:country":"CH",
    "sg:address":"Via Muraccio 1",
    "sg:city":"Ascona",
    "sg:orig_category":"Detailhandel mit Zeitungen U Zeitschriften Kioske",
    "sg:phone":"+41 91 791 77 17",
    "sg:postcode":"6612",
    "sg:province":"Ticino",
    "wof:name":"Rosa Della-cerra Chiosco Romanello",
    "wof:placetype":"venue"
},
  "geometry": {"coordinates":[8.7733011246,46.1544113159],"type":"Point"}
}