{
  "type": "Feature",
  "properties": {
    "iso:country":"CH",
    "sg:address":"Campagnora 19",
    "sg:city":"Castione",
    "sg:orig_category":"Nationale Postdienste",
    "sg:phone":"+41 91 829 21 91",
    "sg:postcode":"6532",
    "sg:province":"Ticino",
    "wof:name":"La Posta Svizzera",
    "wof:placetype":"venue"
},
  "geometry": {"coordinates":[9.0435819626,46.2270698547],"type":"Point"}
}