{
  "type": "Feature",
  "properties": {
    "iso:country":"CH",
    "sg:address":"Gr\u00fcnring 3",
    "sg:city":"Luzern",
    "sg:orig_category":"Interessenvertretungen",
    "sg:postcode":"6005",
    "sg:province":"Luzern",
    "wof:name":"Hilfs Und Solidarit\u00e4tsfonds F\u00fcr Strafgefangene Und Strafentlassene",
    "wof:placetype":"venue"
},
  "geometry": {"coordinates":[8.3020763397,47.0399703979],"type":"Point"}
}