{
  "type": "Feature",
  "properties": {
    "iso:country":"CH",
    "sg:address":"6999",
    "sg:city":"Astano",
    "sg:classifiers":[
        {
            "category":"Travel",
            "subcategory":"Hotels & Motels",
            "type":"Entertainment"
        }
    ],
    "sg:postcode":"6999",
    "sg:province":"Ticino",
    "sg:tags":[
        "hotels",
        "mit",
        "restaurant"
    ],
    "wof:name":"Matti Hans-peter",
    "wof:placetype":"venue"
},
  "geometry": {"coordinates":[7.1541619301,46.3529930115],"type":"Point"}
}