{
  "type": "Feature",
  "properties": {
    "iso:country":"CH",
    "sg:address":"B\u00e4rengand 8",
    "sg:city":"Schattdorf",
    "sg:orig_category":"G\u00fcterbef\u00f6rderung im Strassenverkehr",
    "sg:phone":"+41 79 439 08 65",
    "sg:postcode":"6467",
    "sg:province":"Uri",
    "wof:name":"Arnold Baumann Transporte",
    "wof:placetype":"venue"
},
  "geometry": {"coordinates":[8.5356836319,47.241985321],"type":"Point"}
}