{
  "type": "Feature",
  "properties": {
    "addr:full":"Rue De La Fontaine 18 2608 Courtelary Case Postale 84 Courtelary Bern 2608",
    "addr:housenumber":"18;84",
    "addr:postcode":"2608;2608",
    "addr:street":"Rue De La Fontaine;Postale",
    "iso:country":"CH",
    "sg:address":"Rue De La Fontaine 18 2608 Courtelary Case Postale 84",
    "sg:city":"Courtelary",
    "sg:orig_category":"Advokaturb\u00fcros",
    "sg:phone":"+41 32 944 15 45",
    "sg:postcode":"2608",
    "sg:province":"Bern",
    "wof:name":"Lanz & Antonioli Etude D'avocat",
    "wof:placetype":"venue"
},
  "geometry": {"coordinates":[7.07446,47.177719],"type":"Point"}
}