{
  "type": "Feature",
  "properties": {
    "iso:country":"CH",
    "sg:address":"Ruederbaum",
    "sg:city":"Altnau",
    "sg:classifiers":[
        {
            "category":"Restaurant",
            "type":"Food & Drink"
        }
    ],
    "sg:phone":"+41 79 335 16 19",
    "sg:postcode":"8595",
    "sg:province":"Thurgau",
    "wof:name":"Restaurant Zum Schiff",
    "wof:placetype":"venue"
},
  "geometry": {"coordinates":[9.2660360336,47.6220016479],"type":"Point"}
}