{
  "type": "Feature",
  "properties": {
    "iso:country":"CH",
    "sg:address":"Im P\u00e4chterried 8",
    "sg:city":"Watt",
    "sg:orig_category":"Softwareentwicklung U beratung",
    "sg:phone":"+41 18702110",
    "sg:postcode":"8105",
    "sg:province":"Z\u00fcrich",
    "wof:name":"Simcom Informatik Kolter Uwe",
    "wof:placetype":"venue"
},
  "geometry": {"coordinates":[8.4730110168,47.4452896118],"type":"Point"}
}