{
  "type": "Feature",
  "properties": {
    "iso:country":"CH",
    "sg:address":"Salmsacherstrasse 9",
    "sg:city":"Romanshorn",
    "sg:orig_category":"D\u00e4mmung gegen K\u00e4lte, W\u00e4rme, Schall U Ersch\u00fctterung",
    "sg:phone":"+41 62 873 32 73",
    "sg:postcode":"8590",
    "sg:province":"Thurgau",
    "wof:name":"Silvio Luder Isolierungen",
    "wof:placetype":"venue"
},
  "geometry": {"coordinates":[7.9573469162,47.5439834595],"type":"Point"}
}