{
  "type": "Feature",
  "properties": {
    "iso:country":"CH",
    "sg:address":"Foresta Viale Villa 29 6850 Mendrisio. Postfach Casa Postale",
    "sg:city":"Mendrisio",
    "sg:orig_category":"Vermietung U Verpachtung von eigenen Immobilien",
    "sg:postcode":"6850",
    "sg:province":"Ticino",
    "wof:name":"Immobiliare Casa Regina Sa Immobili Ecc",
    "wof:placetype":"venue"
},
  "geometry": {"coordinates":[8.9880838394,45.870098114],"type":"Point"}
}