{
  "type": "Feature",
  "properties": {
    "iso:country":"CH",
    "sg:address":"Messmerh\u00f6lzli 5",
    "sg:city":"Mels",
    "sg:orig_category":"Softwareentwicklung U beratung",
    "sg:phone":"+41 81 710 05 95",
    "sg:postcode":"8887",
    "sg:province":"St. Gallen",
    "wof:name":"Audiocom Voice Gmbh",
    "wof:placetype":"venue"
},
  "geometry": {"coordinates":[9.4213819504,47.0389633179],"type":"Point"}
}