{
  "type": "Feature",
  "properties": {
    "iso:country":"CH",
    "sg:address":"Ahornstrasse",
    "sg:city":"Vilters",
    "sg:orig_category":"Architektur U Ingenieurb\u00fcros",
    "sg:postcode":"7324",
    "sg:province":"St. Gallen",
    "wof:name":"Hobi & Schwarzmann Architekten Ag",
    "wof:placetype":"venue"
},
  "geometry": {"coordinates":[9.451669,47.024612],"type":"Point"}
}