{
  "type": "Feature",
  "properties": {
    "iso:country":"CH",
    "sg:address":"Engelg.109",
    "sg:city":"Basel",
    "sg:classifiers":[
        {
            "category":"Building & Trades",
            "subcategory":"Pest Control",
            "type":"Services"
        }
    ],
    "sg:phone":"+41 61 706 48 48",
    "sg:postcode":"4002",
    "sg:province":"Basel-Stadt",
    "sg:tags":[
        "pharmaceutical",
        "-",
        "pharmacy",
        "chemical",
        "engineering",
        "machine",
        "mechanical"
    ],
    "wof:name":"Pentapharm Ag",
    "wof:placetype":"venue"
},
  "geometry": {"coordinates":[7.604989,47.547611],"type":"Point"}
}