{
  "type": "Feature",
  "properties": {
    "iso:country":"CH",
    "sg:address":"Bergstrasse 63",
    "sg:city":"Kriens",
    "sg:orig_category":"Allgemeiner Hoch U Tiefbau Allgemeiner Hochbau",
    "sg:phone":"+41 16875240",
    "sg:postcode":"6010",
    "sg:province":"Luzern",
    "wof:name":"Dangel & Co Ag Hoch Und Tiefbau",
    "wof:placetype":"venue"
},
  "geometry": {"coordinates":[8.728276,47.201622],"type":"Point"}
}