{
  "type": "Feature",
  "properties": {
    "iso:country":"CH",
    "sg:address":"Werdenstrasse 60",
    "sg:city":"Grabs",
    "sg:orig_category":"Herstellung von Metallerzeugnissen ohne Maschinenbau Herstellung von Zahnr\u00e4dern U Antriebselementen",
    "sg:phone":"+41 81 771 38 62",
    "sg:postcode":"9472",
    "sg:province":"St. Gallen",
    "wof:name":"Weg Gelenkwellen Elbe & Co",
    "wof:placetype":"venue"
},
  "geometry": {"coordinates":[9.4538345337,47.1829109192],"type":"Point"}
}