{
  "type": "Feature",
  "properties": {
    "iso:country":"CH",
    "sg:address":"Farbgasse 7",
    "sg:city":"Langenthal",
    "sg:orig_category":"Kauf U Verkauf von Immobilien auf eigene Rechnung Vermittlung von Immobilien",
    "sg:phone":"+41 62 922 14 14",
    "sg:postcode":"4900",
    "sg:province":"Bern",
    "wof:name":"Thulag Immobilien Und Versicherungen, Paul Schneeberger",
    "wof:placetype":"venue"
},
  "geometry": {"coordinates":[7.7892789841,47.2115783691],"type":"Point"}
}