{
  "type": "Feature",
  "properties": {
    "iso:country":"CH",
    "sg:address":"Hermetschloostrasse 70",
    "sg:city":"Z\u00fcrich",
    "sg:orig_category":"Beleuchtungsk\u00f6rper Detailhandel Innendekorationsateliers",
    "sg:phone":"+41 14332222",
    "sg:postcode":"8048",
    "sg:province":"Z\u00fcrich",
    "wof:name":"Ringger & Guazzone Dekoration",
    "wof:placetype":"venue"
},
  "geometry": {"coordinates":[8.473504,47.394047],"type":"Point"}
}