{
  "type": "Feature",
  "properties": {
    "iso:country":"CH",
    "sg:address":"Auf Dem Wolf 30 4052 Basel. Postfach",
    "sg:city":"Basel",
    "sg:orig_category":"Grosshandel mit Spielwaren Grosshandel mit sonstigen Gebrauchs U Verbrauchsg\u00fctern",
    "sg:phone":"+41 31 381 36 38",
    "sg:postcode":"4028",
    "wof:name":"Comus Sa",
    "wof:placetype":"venue"
},
  "geometry": {"coordinates":[7.4164319038,46.949180603],"type":"Point"}
}