{
  "type": "Feature",
  "properties": {
    "iso:country":"CH",
    "sg:address":"Chemin Comble-emine 2053 Cernier. Postfach",
    "sg:city":"Cernier",
    "sg:orig_category":"Handelsvermittlung U Grosshandel Handelsvermittlung U Grosshandel mit Automobilteilen U Zubeh\u00f6r",
    "sg:phone":"+41 32 854 20 10",
    "sg:postcode":"2053",
    "sg:province":"Neuch\u00e2tel",
    "wof:name":"Pierre Hirschi Importation De Filtres",
    "wof:placetype":"venue"
},
  "geometry": {"coordinates":[6.9030399323,47.0572357178],"type":"Point"}
}