{
  "type": "Feature",
  "properties": {
    "iso:country":"CH",
    "sg:address":"Ringstrasse 60",
    "sg:city":"Lyssach",
    "sg:orig_category":"Wirtschaftspr\u00fcfung, Steuerberatung U Treuhand",
    "sg:phone":"+41 34 445 39 00",
    "sg:postcode":"3421",
    "sg:province":"Bern",
    "wof:name":"Lilli Leu Treuhandb\u00fcro",
    "wof:placetype":"venue"
},
  "geometry": {"coordinates":[7.5820331573,47.0777053833],"type":"Point"}
}