{
  "type": "Feature",
  "properties": {
    "addr:full":"Industriestrasse 6 Bronschhofen St. Gallen 9552",
    "addr:housenumber":"6",
    "addr:postcode":"9552",
    "addr:street":"Industriestrasse",
    "iso:country":"CH",
    "sg:address":"Industriestrasse 6",
    "sg:city":"Bronschhofen",
    "sg:classifiers":[
        {
            "category":"Shopping",
            "subcategory":"Clothing, Apparel, & Fashions",
            "type":"Retail Goods"
        }
    ],
    "sg:phone":"+41 71 911 42 32",
    "sg:postcode":"9552",
    "sg:province":"St. Gallen",
    "sg:tags":[
        "clothing",
        "fabric"
    ],
    "wof:name":"Weberei Bronschhofen Ag",
    "wof:placetype":"venue"
},
  "geometry": {"coordinates":[9.0343,47.473324],"type":"Point"}
}