{
  "type": "Feature",
  "properties": {
    "iso:country":"CH",
    "sg:address":"Schulweg 1",
    "sg:city":"Steckborn",
    "sg:orig_category":"Herstellung von Metallkonstruktionen Schlossereien",
    "sg:phone":"+41 52 761 14 71",
    "sg:postcode":"8266",
    "sg:province":"Thurgau",
    "wof:name":"Weiss Metallbau Ag",
    "wof:placetype":"venue"
},
  "geometry": {"coordinates":[8.9841480255,47.6642799377],"type":"Point"}
}