{
  "type": "Feature",
  "properties": {
    "iso:country":"CH",
    "sg:address":"Via Piazzetta San Carlo 6 6512 Giubiasco. Postfach",
    "sg:city":"Giubiasco",
    "sg:orig_category":"Herstellung von sonstigen elektrischen Ausr\u00fcstungen",
    "sg:phone":"+41 79 679 69 06",
    "sg:postcode":"6512",
    "sg:province":"Ticino",
    "wof:name":"Sicurezza 2000 Di Nigro Roberto Apparecchi D'allarme, Elettrici, Telefonici; Vendita, Installazione",
    "wof:placetype":"venue"
},
  "geometry": {"coordinates":[9.0108251572,46.1730804443],"type":"Point"}
}