{
  "type": "Feature",
  "properties": {
    "iso:country":"CH",
    "sg:address":"Wohlerstrasse 5",
    "sg:city":"Fischbach-g\u00f6slikon",
    "sg:orig_category":"Maurerarbeiten Stukkateurgewerbe, Gipserei U Verputzerei",
    "sg:phone":"+41 56 622 14 50",
    "sg:postcode":"5525",
    "sg:province":"Aargau",
    "wof:name":"Keller + Maurer Gmbh Schreinereibetrieb. Warenhandel",
    "wof:placetype":"venue"
},
  "geometry": {"coordinates":[8.3048839569,47.3726577759],"type":"Point"}
}