{
  "type": "Feature",
  "properties": {
    "iso:country":"CH",
    "sg:address":"L\u00f6wenstrasse 42 8001 Z\u00fcrich. Postfach",
    "sg:city":"Z\u00fcrich",
    "sg:orig_category":"Wirtschaftspr\u00fcfung, Steuerberatung U Treuhand",
    "sg:postcode":"8001",
    "sg:province":"Z\u00fcrich",
    "wof:name":"Internationale Vereinigung Von Treuhandgesellschaften",
    "wof:placetype":"venue"
},
  "geometry": {"coordinates":[8.5367546082,47.3751754761],"type":"Point"}
}