{
  "type": "Feature",
  "properties": {
    "iso:country":"CH",
    "sg:address":"Sch\u00f6nenwerderstrasse 35",
    "sg:city":"Aarau",
    "sg:orig_category":"Finanzierungsinstitutionen",
    "sg:phone":"+41 62 824 64 26",
    "sg:postcode":"5000",
    "sg:province":"Aargau",
    "wof:name":"Riwe-finanz Ag",
    "wof:placetype":"venue"
},
  "geometry": {"coordinates":[8.0401411057,47.3873062134],"type":"Point"}
}