{
  "type": "Feature",
  "properties": {
    "iso:country":"CH",
    "sg:address":"Hauptstrasse 13",
    "sg:city":"Ettingen",
    "sg:orig_category":"Kosmetikinstitute",
    "sg:phone":"+41 61 721 00 29",
    "sg:postcode":"4107",
    "sg:province":"Basel-Landschaft",
    "wof:name":"Rebecca Glarner Med.fusspflege & Kosmetik",
    "wof:placetype":"venue"
},
  "geometry": {"coordinates":[7.5459218025,47.4827461243],"type":"Point"}
}