{
  "type": "Feature",
  "properties": {
    "iso:country":"CH",
    "sg:address":"Grabenweg 29 3902 Glis. Postfach",
    "sg:city":"M\u00f6rel",
    "sg:orig_category":"Fachdetailhandel in Verkaufsr\u00e4umen Herstellung von Sportger\u00e4ten",
    "sg:phone":"+41 27 924 58 58",
    "sg:postcode":"3983",
    "sg:province":"Valais",
    "wof:name":"Rtc Ski Ag Sportger\u00e4te Usw.; Entwicklung, Herstellung, Vermarktung, Verkauf",
    "wof:placetype":"venue"
},
  "geometry": {"coordinates":[7.9670300484,46.3100662231],"type":"Point"}
}