{
  "type": "Feature",
  "properties": {
    "iso:country":"CH",
    "sg:address":"Spalenvorstadt 41",
    "sg:city":"Basel",
    "sg:orig_category":"Detailhandel mit Brot, Back U S\u00fcsswaren",
    "sg:phone":"+41 61 261 11 09",
    "sg:postcode":"4051",
    "sg:province":"Basel-Stadt",
    "wof:name":"Fredy Rutschmann B\u00e4ckerei-konditorei",
    "wof:placetype":"venue"
},
  "geometry": {"coordinates":[7.581769,47.557652],"type":"Point"}
}