{
  "type": "Feature",
  "properties": {
    "iso:country":"CH",
    "sg:address":"Schwarzwaldstrasse 14",
    "sg:city":"Urdorf",
    "sg:orig_category":"Sportvereine Behindertensport",
    "sg:phone":"+41 17341161",
    "sg:postcode":"8902",
    "sg:province":"Z\u00fcrich",
    "wof:name":"Svbs Limmattal",
    "wof:placetype":"venue"
},
  "geometry": {"coordinates":[8.4340276718,47.3871765137],"type":"Point"}
}