{
  "type": "Feature",
  "properties": {
    "iso:country":"CH",
    "sg:address":"Kasinostrasse 19",
    "sg:city":"Aarau",
    "sg:classifiers":[
        {
            "category":"Professional",
            "subcategory":"Employment Agencies",
            "type":"Services"
        }
    ],
    "sg:phone":"+41 12136060",
    "sg:postcode":"5000",
    "sg:province":"Aargau",
    "sg:tags":[
        "personal",
        "u",
        "stellenvermittlung"
    ],
    "wof:name":"Joker Personal Ag",
    "wof:placetype":"venue"
},
  "geometry": {"coordinates":[8.0468330383,47.3927230835],"type":"Point"}
}