{
  "type": "Feature",
  "properties": {
    "iso:country":"CH",
    "sg:address":"Weinfelderstrasse 42",
    "sg:city":"Amriswil",
    "sg:orig_category":"Allgemeiner Hoch U Tiefbau",
    "sg:phone":"+41 71 411 81 50",
    "sg:postcode":"8580",
    "sg:province":"Thurgau",
    "wof:name":"St\u00e4heli Max.",
    "wof:placetype":"venue"
},
  "geometry": {"coordinates":[9.291934,47.545097],"type":"Point"}
}