{
  "type": "Feature",
  "properties": {
    "iso:country":"CH",
    "sg:address":"N\u00e4ppisuelistrasse 11",
    "sg:city":"Wattwil",
    "sg:orig_category":"Maturit\u00e4tsschulen, Lehrerseminarien",
    "sg:phone":"+41 71 987 67 27",
    "sg:postcode":"9630",
    "sg:province":"St. Gallen",
    "wof:name":"Kantonsschule Wattwil",
    "wof:placetype":"venue"
},
  "geometry": {"coordinates":[9.0878534317,47.3011550903],"type":"Point"}
}