{
  "type": "Feature",
  "properties": {
    "iso:country":"CH",
    "sg:address":"Reitbahnstrasse 30",
    "sg:city":"Rorschach",
    "sg:orig_category":"Unclassifiable Establishments",
    "sg:postcode":"9400",
    "sg:province":"St. Gallen",
    "wof:name":"L - Trans Gmbh",
    "wof:placetype":"venue"
},
  "geometry": {"coordinates":[9.4872093201,47.4765129089],"type":"Point"}
}