{
  "type": "Feature",
  "properties": {
    "iso:country":"CH",
    "sg:address":"Bagutti Via 9",
    "sg:city":"Lugano",
    "sg:orig_category":"Finanzierungsinstitutionen",
    "sg:phone":"+41 19372078",
    "sg:postcode":"6900",
    "sg:province":"Ticino",
    "wof:name":"Papp Martin, Finanzberatung",
    "wof:placetype":"venue"
},
  "geometry": {"coordinates":[8.860783577,47.2856903076],"type":"Point"}
}