{
  "type": "Feature",
  "properties": {
    "addr:full":"Grand'rue 36 Cormondr\u00e8che Neuch\u00e2tel 2036",
    "addr:housenumber":"36",
    "addr:postcode":"2036",
    "addr:street":"Grand'Rue;Cormondre\u0300Che Neucha\u0302Tel",
    "iso:country":"CH",
    "sg:address":"Grand'rue 36",
    "sg:city":"Cormondr\u00e8che",
    "sg:orig_category":"Detailhandel mit Brot, Back U S\u00fcsswaren",
    "sg:phone":"+41 32 731 98 39",
    "sg:postcode":"2036",
    "sg:province":"Neuch\u00e2tel",
    "wof:name":"Boulangerie P\u00e2tisserie Allemann M.",
    "wof:placetype":"venue"
},
  "geometry": {"coordinates":[6.86853,46.980469],"type":"Point"}
}