{
  "type": "Feature",
  "properties": {
    "iso:country":"CH",
    "sg:address":"Archstrasse 10",
    "sg:city":"Winterthur",
    "sg:orig_category":"Non-Classified Establishments",
    "sg:postcode":"8400",
    "sg:province":"Z\u00fcrich",
    "wof:name":"Trattoria La Torre Gmbh",
    "wof:placetype":"venue"
},
  "geometry": {"coordinates":[8.7235431671,47.4979743958],"type":"Point"}
}