{
  "type": "Feature",
  "properties": {
    "iso:country":"CH",
    "sg:address":"Route De Grandcour",
    "sg:city":"Payerne",
    "sg:orig_category":"Herstellung von Metallerzeugnissen ohne Maschinenbau",
    "sg:phone":"+41 55 251 11 11",
    "sg:postcode":"1530",
    "sg:province":"Vaud",
    "wof:name":"Mantel & Cie Embru-werke",
    "wof:placetype":"venue"
},
  "geometry": {"coordinates":[6.9357538223,46.8316841125],"type":"Point"}
}