{
  "type": "Feature",
  "properties": {
    "iso:country":"CH",
    "sg:address":"Rue Oscar-huguenin 10",
    "sg:city":"Boudry",
    "sg:orig_category":"Detailhandel mit Waren verschiedener Art, Hauptrichtung Nahrungsmittel",
    "sg:phone":"+41 26 652 38 38",
    "sg:postcode":"2017",
    "sg:province":"Neuch\u00e2tel",
    "wof:name":"Migros",
    "wof:placetype":"venue"
},
  "geometry": {"coordinates":[6.9115347862,46.6912689209],"type":"Point"}
}