{
  "type": "Feature",
  "properties": {
    "iso:country":"CH",
    "sg:address":"Alte Landstrasse 30",
    "sg:city":"Oberrieden",
    "sg:orig_category":"Detailhandel mit Waren verschiedener Art, Hauptrichtung Nahrungsmittel",
    "sg:phone":"+41 17211293",
    "sg:postcode":"8942",
    "sg:province":"Z\u00fcrich",
    "wof:name":"Coop Center",
    "wof:placetype":"venue"
},
  "geometry": {"coordinates":[8.5756664276,47.2781486511],"type":"Point"}
}