{
  "type": "Feature",
  "properties": {
    "iso:country":"CH",
    "sg:address":"Rue Cardinal Journet 27",
    "sg:city":"Meyrin",
    "sg:classifiers":[
        {
            "category":"Manufacturing",
            "subcategory":"Aerospace",
            "type":"Manufacturing & Wholesale Goods"
        }
    ],
    "sg:phone":"+41 22 782 29 01",
    "sg:postcode":"1217",
    "sg:province":"Gen\u00e8ve",
    "sg:tags":[
        "equipment",
        "aeronautic",
        "transport",
        "vehicle"
    ],
    "wof:name":"Leman Avionics Sa",
    "wof:placetype":"venue"
},
  "geometry": {"coordinates":[6.082059,46.225075],"type":"Point"}
}