{
  "type": "Feature",
  "properties": {
    "addr:full":"Via Giuseppe Cattori 5 Lugano Ticino 6902",
    "addr:housenumber":"5",
    "addr:postcode":"6902",
    "addr:street":"Via Giuseppe Cattori",
    "iso:country":"CH",
    "sg:address":"Via Giuseppe Cattori 5",
    "sg:city":"Lugano",
    "sg:classifiers":[
        {
            "category":"Banks & Credit Unions",
            "subcategory":"Bank",
            "type":"Services"
        }
    ],
    "sg:phone":"+41 91 993 01 91",
    "sg:postcode":"6902",
    "sg:province":"Ticino",
    "wof:name":"Banque De Commerce, Et De Placements Sa",
    "wof:placetype":"venue"
},
  "geometry": {"coordinates":[8.951305,46.002975],"type":"Point"}
}