{
  "type": "Feature",
  "properties": {
    "iso:country":"CH",
    "sg:address":"Au Moulin",
    "sg:city":"Remaufens",
    "sg:orig_category":"Abwasserreinigung, Abfallbeseitigung U sonstige Entsorgung",
    "sg:postcode":"1617",
    "sg:province":"Fribourg",
    "wof:name":"Cridor Sa, Centre R\u00e9gional D'incin\u00e9ration Des Ordures,coll\u00e8ge",
    "wof:placetype":"venue"
},
  "geometry": {"coordinates":[-75.605957,37.787762],"type":"Point"}
}