{
  "type": "Feature",
  "properties": {
    "addr:full":"Aspermontstrasse 6 Chur Graubunden 7000",
    "addr:housenumber":"6",
    "addr:postcode":"7000",
    "addr:street":"Aspermontstrasse",
    "iso:country":"CH",
    "sg:address":"Aspermontstrasse 6",
    "sg:city":"Chur",
    "sg:orig_category":"Architekturb\u00fcros",
    "sg:phone":"+41 81 356 06 55",
    "sg:postcode":"7000",
    "sg:province":"Graubunden",
    "wof:name":"Martin Ruf Architekturb\u00fcro",
    "wof:placetype":"venue"
},
  "geometry": {"coordinates":[9.529561,46.860401],"type":"Point"}
}