{
  "type": "Feature",
  "properties": {
    "iso:country":"CH",
    "sg:address":"St. Antoniweg 1",
    "sg:city":"Sarnen",
    "sg:orig_category":"Herstellung von Fahrr\u00e4dern",
    "sg:postcode":"6060",
    "sg:province":"Obwalden",
    "wof:name":"Wallimann Thomas, Fafli",
    "wof:placetype":"venue"
},
  "geometry": {"coordinates":[8.2489128113,46.8952484131],"type":"Point"}
}