{
  "type": "Feature",
  "properties": {
    "iso:country":"CH",
    "sg:address":"Perry-center",
    "sg:city":"Oftringen",
    "sg:orig_category":"Detailhandel mit Schreib U Papeteriewaren",
    "sg:phone":"+41 19306606",
    "sg:postcode":"4665",
    "sg:province":"Aargau",
    "wof:name":"Mc Paperland Papeterie- & B\u00fcrobedarf",
    "wof:placetype":"venue"
},
  "geometry": {"coordinates":[8.8001890182,47.3269577026],"type":"Point"}
}