{
  "type": "Feature",
  "properties": {
    "iso:country":"CH",
    "sg:address":"Chi\u00e8tres-sur-bex 1880 Bex. Postfach",
    "sg:city":"Bex",
    "sg:orig_category":"Herstellung von Teppichen",
    "sg:postcode":"1880",
    "sg:province":"Vaud",
    "wof:name":"Pachoud Jean",
    "wof:placetype":"venue"
},
  "geometry": {"coordinates":[7.0076642036,46.2380027771],"type":"Point"}
}