{
  "type": "Feature",
  "properties": {
    "iso:country":"CH",
    "sg:address":"Dammstrasse 15",
    "sg:city":"M\u00e4nnedorf",
    "sg:orig_category":"Sonstige mit der Informatik verbundene T\u00e4tigkeiten Unternehmensberatung",
    "sg:phone":"+41 17901330",
    "sg:postcode":"8708",
    "sg:province":"Z\u00fcrich",
    "wof:name":"Aleco Edv- & Organisationsberatung Gmbh Internet, Edv- & Organisationsberatung",
    "wof:placetype":"venue"
},
  "geometry": {"coordinates":[8.6901483536,47.2555618286],"type":"Point"}
}