{
  "type": "Feature",
  "properties": {
    "iso:country":"CH",
    "sg:address":"Ballonstrasse 20",
    "sg:city":"Schlieren",
    "sg:orig_category":"Instandhaltung U Reparatur von Automobilen",
    "sg:phone":"+41 22 796 76 52",
    "sg:postcode":"8952",
    "sg:province":"Z\u00fcrich",
    "wof:name":"Auto-atelier-a\u00efre-lignon, Rupp J. Et Cesaro S.",
    "wof:placetype":"venue"
},
  "geometry": {"coordinates":[6.0970368385,46.2043876648],"type":"Point"}
}