{
  "type": "Feature",
  "properties": {
    "addr:full":"Dorfstrasse 6 Turtmann Valais 3946",
    "addr:housenumber":"6",
    "addr:postcode":"3946",
    "addr:street":"Dorfstrasse",
    "iso:country":"CH",
    "sg:address":"Dorfstrasse 6",
    "sg:city":"Turtmann",
    "sg:orig_category":"Architektur U Ingenieurb\u00fcros",
    "sg:phone":"+41 27 932 30 01",
    "sg:postcode":"3946",
    "sg:province":"Valais",
    "wof:name":"Kalbermatter & Melly-petrig",
    "wof:placetype":"venue"
},
  "geometry": {"coordinates":[7.703531,46.301476],"type":"Point"}
}