{
  "type": "Feature",
  "properties": {
    "iso:country":"CH",
    "sg:address":"Grand-place Ouest Crans",
    "sg:city":"Lens",
    "sg:orig_category":"Verarbeitung von Tee U Kaffee",
    "sg:phone":"+41 808477",
    "sg:postcode":"1978",
    "sg:province":"Valais",
    "wof:name":"La Maison Du Caf\u00e9, Trottet Sa",
    "wof:placetype":"venue"
},
  "geometry": {"coordinates":[6.07249403,46.2231521606],"type":"Point"}
}