{
  "type": "Feature",
  "properties": {
    "iso:country":"CH",
    "sg:address":"Meiersmattstrasse 34",
    "sg:city":"Adligenswil",
    "sg:orig_category":"Sonstige mit der Informatik verbundene T\u00e4tigkeiten",
    "sg:phone":"+41 56 470 04 81",
    "sg:postcode":"6043",
    "sg:province":"Luzern",
    "wof:name":"Interprisma Gmbh",
    "wof:placetype":"venue"
},
  "geometry": {"coordinates":[8.2884941101,47.4524307251],"type":"Point"}
}