{
  "type": "Feature",
  "properties": {
    "iso:country":"CH",
    "sg:address":"Hondrich 3700 Spiez. Postfach",
    "sg:city":"Hondrich",
    "sg:orig_category":"Haltung von Rindern",
    "sg:postcode":"3702",
    "sg:province":"Bern",
    "wof:name":"Alpfleckviehzuchtgenossenschaft Hondrich",
    "wof:placetype":"venue"
},
  "geometry": {"coordinates":[7.6819648743,46.6810531616],"type":"Point"}
}