{
  "type": "Feature",
  "properties": {
    "iso:country":"CH",
    "sg:address":"Seestrasse 118",
    "sg:city":"Freienbach",
    "sg:orig_category":"Maler U Glasergewerbe",
    "sg:postcode":"8807",
    "sg:province":"Schwyz",
    "wof:name":"Cano Team Gmbh",
    "wof:placetype":"venue"
},
  "geometry": {"coordinates":[8.7427101135,47.2048301697],"type":"Point"}
}