{
  "type": "Feature",
  "properties": {
    "iso:country":"CH",
    "sg:address":"Kronengasse 20",
    "sg:city":"Wolfwil",
    "sg:orig_category":"Sonstiger Detailhandel mit Metallwaren, Anstrichmitteln, Glaswaren, Bau U Heimwerkerbedarf",
    "sg:phone":"+41 62 926 13 17",
    "sg:postcode":"4628",
    "sg:province":"Solothurn",
    "wof:name":"Ruth's Bastel-& Malecke Ruth B\u00fcttiker",
    "wof:placetype":"venue"
},
  "geometry": {"coordinates":[7.8020448685,47.2694206238],"type":"Point"}
}