{
  "type": "Feature",
  "properties": {
    "iso:country":"CH",
    "sg:address":"Stedtligass 16",
    "sg:city":"Gr\u00fcningen",
    "sg:orig_category":"RESTAURANTS: TEA-ROOMS",
    "sg:phone":"+41 19354905",
    "sg:postcode":"8627",
    "sg:province":"Z\u00fcrich",
    "wof:name":"Zurbi Gmbh",
    "wof:placetype":"venue"
},
  "geometry": {"coordinates":[8.7637252808,47.2843933105],"type":"Point"}
}