{
  "type": "Feature",
  "properties": {
    "iso:country":"CH",
    "sg:address":"R\u00fcttistrasse 13",
    "sg:city":"Schattdorf",
    "sg:orig_category":"Herstellung von Metallkonstruktionen",
    "sg:phone":"+41 41 870 80 80",
    "sg:postcode":"6467",
    "sg:province":"Uri",
    "wof:name":"Brand Metallbau Ag",
    "wof:placetype":"venue"
},
  "geometry": {"coordinates":[8.6462717056,46.8638343811],"type":"Point"}
}