{
  "type": "Feature",
  "properties": {
    "iso:country":"CH",
    "sg:address":"Bahnhofstrasse 31 3930 Visp Case Postale 290",
    "sg:city":"Visp",
    "sg:orig_category":"Detailhandel mit Radio U Fernsehger\u00e4ten Detailhandel mit fotografischen Artikeln",
    "sg:phone":"+41 27 946 22 35",
    "sg:postcode":"3930",
    "sg:province":"Valais",
    "wof:name":"Roland Salzgeber",
    "wof:placetype":"venue"
},
  "geometry": {"coordinates":[7.8814578056,46.2910995483],"type":"Point"}
}