{
  "type": "Feature",
  "properties": {
    "iso:country":"CH",
    "sg:address":"Sunneschyn",
    "sg:city":"Kehrsiten",
    "sg:orig_category":"Detailhandel mit Waren verschiedener Art, Hauptrichtung Nahrungsmittel",
    "sg:phone":"+41 41 610 75 36",
    "sg:postcode":"6365",
    "sg:province":"Nidwalden",
    "wof:name":"Walter Mathis Lebensmittel",
    "wof:placetype":"venue"
},
  "geometry": {"coordinates":[8.3650484085,46.9994125366],"type":"Point"}
}