{
  "type": "Feature",
  "properties": {
    "iso:country":"CH",
    "sg:address":"Fabrikstrasse 2",
    "sg:city":"Lyss",
    "sg:orig_category":"Advokaturb\u00fcros Notariate",
    "sg:phone":"+41 32 384 88 78",
    "sg:postcode":"3250",
    "sg:province":"Bern",
    "wof:name":"Marti & Leuenberger Advokatur- & Notariatsb\u00fcro",
    "wof:placetype":"venue"
},
  "geometry": {"coordinates":[7.305064,47.075443],"type":"Point"}
}