{
  "type": "Feature",
  "properties": {
    "iso:country":"CH",
    "sg:address":"Hauptstrasse 143",
    "sg:city":"Reitnau",
    "sg:orig_category":"Non-Classified Establishments",
    "sg:postcode":"5057",
    "sg:province":"Aargau",
    "wof:name":"Felix Wunderland Gmbh",
    "wof:placetype":"venue"
},
  "geometry": {"coordinates":[8.0458221436,47.2512931824],"type":"Point"}
}