{
  "type": "Feature",
  "properties": {
    "iso:country":"CH",
    "sg:address":"B\u00fclachstrasse 5",
    "sg:city":"Z\u00fcrich",
    "sg:classifiers":[
        {
            "category":"Professional",
            "subcategory":"Employment Agencies",
            "type":"Services"
        }
    ],
    "sg:phone":"+41 13118384",
    "sg:postcode":"8057",
    "sg:province":"Z\u00fcrich",
    "sg:tags":[
        "personal",
        "u",
        "stellenvermittlung"
    ],
    "wof:name":"Platec Personal Ag Stellenvermittlungsb\u00fcro",
    "wof:placetype":"venue"
},
  "geometry": {"coordinates":[8.5479726791,47.4012527466],"type":"Point"}
}