{
  "type": "Feature",
  "properties": {
    "iso:country":"CH",
    "sg:address":"Rue Des Paquis 9",
    "sg:city":"Gen\u00e8ve",
    "sg:classifiers":[
        {
            "category":"Bars & Pubs",
            "type":"Food & Drink"
        }
    ],
    "sg:phone":"+41 22 732 78 72",
    "sg:postcode":"1201",
    "sg:province":"Gen\u00e8ve",
    "sg:tags":[
        "restaurant"
    ],
    "wof:name":"Caf\u00e9 & Bar Melody",
    "wof:placetype":"venue"
},
  "geometry": {"coordinates":[6.148261,46.210369],"type":"Point"}
}