{
  "type": "Feature",
  "properties": {
    "iso:country":"CH",
    "sg:address":"Rue Des Oeuches 57",
    "sg:city":"Rossemaison",
    "sg:orig_category":"Primarschulen",
    "sg:phone":"+41 32 422 06 24",
    "sg:postcode":"2842",
    "sg:province":"Jura",
    "wof:name":"Ecole Primaire",
    "wof:placetype":"venue"
},
  "geometry": {"coordinates":[7.3450288773,47.3465766907],"type":"Point"}
}