{
  "type": "Feature",
  "properties": {
    "iso:country":"CH",
    "sg:address":"Viale H.guisan 5",
    "sg:city":"Bellinzona",
    "sg:classifiers":[
        {
            "category":"Banks & Credit Unions",
            "subcategory":"Bank",
            "type":"Services"
        }
    ],
    "sg:phone":"+41 91 803 71 11",
    "sg:postcode":"6501",
    "sg:province":"Ticino",
    "wof:name":"Banca Dello Stato Del, Cantone Ticino",
    "wof:placetype":"venue"
},
  "geometry": {"coordinates":[9.024119,46.194462],"type":"Point"}
}