{
  "type": "Feature",
  "properties": {
    "iso:country":"CH",
    "sg:address":"Riesengasse 72",
    "sg:city":"Krattigen",
    "sg:classifiers":[
        {
            "category":"Travel",
            "subcategory":"Hotels & Motels",
            "type":"Entertainment"
        }
    ],
    "sg:phone":"+41 33 654 29 69",
    "sg:postcode":"3704",
    "sg:province":"Bern",
    "sg:tags":[
        "hotels",
        "mit",
        "restaurant"
    ],
    "wof:name":"Hotel Seeblick",
    "wof:placetype":"venue"
},
  "geometry": {"coordinates":[7.7278847694,46.6610832214],"type":"Point"}
}