{
  "type": "Feature",
  "properties": {
    "iso:country":"CH",
    "sg:address":"Bergstrasse 24",
    "sg:city":"Boppelsen",
    "sg:orig_category":"Unternehmensberatung",
    "sg:phone":"+41 18443041",
    "sg:postcode":"8113",
    "sg:province":"Z\u00fcrich",
    "wof:name":"Asb Ag",
    "wof:placetype":"venue"
},
  "geometry": {"coordinates":[8.3997716904,47.4738502502],"type":"Point"}
}