{
  "type": "Feature",
  "properties": {
    "iso:country":"CH",
    "sg:address":"Neuhaltenring 8",
    "sg:city":"Ebikon",
    "sg:classifiers":[
        {
            "category":"Farming",
            "subcategory":"Fish & Marine Products",
            "type":"Manufacturing & Wholesale Goods"
        }
    ],
    "sg:phone":"+41 41 444 14 41",
    "sg:postcode":"6030",
    "sg:province":"Luzern",
    "sg:tags":[
        "asphalt"
    ],
    "wof:name":"Walo Bertschinger Ag",
    "wof:placetype":"venue"
},
  "geometry": {"coordinates":[8.34437,47.088661],"type":"Point"}
}