{
  "type": "Feature",
  "properties": {
    "iso:country":"CH",
    "sg:address":"Rue De La Prairie 2",
    "sg:city":"Martigny",
    "sg:orig_category":"Forschung U Entwicklung im Bereich der Naturwissenschaften",
    "sg:phone":"+41 27 722 86 73",
    "sg:postcode":"1920",
    "sg:province":"Valais",
    "wof:name":"Rausis Jean-pierre",
    "wof:placetype":"venue"
},
  "geometry": {"coordinates":[7.0767621994,46.1000671387],"type":"Point"}
}