{
  "type": "Feature",
  "properties": {
    "addr:full":"Alte Bernstrasse 123 Steffisburg Bern 3613",
    "addr:housenumber":"123",
    "addr:postcode":"3613",
    "addr:street":"Alte Bernstrasse;Bern",
    "iso:country":"CH",
    "sg:address":"Alte Bernstrasse 123",
    "sg:city":"Steffisburg",
    "sg:orig_category":"Detailhandel mit Brot, Back U S\u00fcsswaren Detailhandel mit Waren verschiedener Art, Hauptrichtung Nahr",
    "sg:phone":"+41 33 437 55 37",
    "sg:postcode":"3613",
    "sg:province":"Bern",
    "wof:name":"Peter L\u00fcthi",
    "wof:placetype":"venue"
},
  "geometry": {"coordinates":[7.616892,46.774422],"type":"Point"}
}