{
  "type": "Feature",
  "properties": {
    "iso:country":"CH",
    "sg:address":"Zeughausgasse 3",
    "sg:city":"Uster",
    "sg:orig_category":"Allgemeiner Hoch U Tiefbau Hoch U Tiefbau",
    "sg:phone":"+41 19541417",
    "sg:postcode":"8610",
    "sg:province":"Z\u00fcrich",
    "wof:name":"Bachmann Ag Gebr., Baugesch\u00e4ft Uster",
    "wof:placetype":"venue"
},
  "geometry": {"coordinates":[8.711994,47.351589],"type":"Point"}
}