{
  "type": "Feature",
  "properties": {
    "iso:country":"CH",
    "sg:address":"Rampe De La Gare 2",
    "sg:city":"Versoix",
    "sg:orig_category":"Detailhandel mit Damenbekleidung",
    "sg:phone":"+41 22 755 11 41",
    "sg:postcode":"1290",
    "sg:province":"Gen\u00e8ve",
    "wof:name":"Ginette Pittet Coiffure & Boutique Ginette",
    "wof:placetype":"venue"
},
  "geometry": {"coordinates":[6.16752,46.279415],"type":"Point"}
}