{
  "type": "Feature",
  "properties": {
    "iso:country":"CH",
    "sg:address":"Grand-rue 63",
    "sg:city":"Bulle",
    "sg:orig_category":"Innendekorationsateliers Maler U Glasergewerbe",
    "sg:phone":"+41 26 912 84 25",
    "sg:postcode":"1630",
    "sg:province":"Fribourg",
    "wof:name":"Chassot-heimoz Dominique",
    "wof:placetype":"venue"
},
  "geometry": {"coordinates":[7.0579180717,46.620880127],"type":"Point"}
}