{
  "type": "Feature",
  "properties": {
    "iso:country":"CH",
    "sg:address":"Weiacherstrasse 14",
    "sg:city":"Rorbas",
    "sg:orig_category":"Sonstige mit der Informatik verbundene T\u00e4tigkeiten",
    "sg:phone":"+41 17603858",
    "sg:postcode":"8427",
    "sg:province":"Z\u00fcrich",
    "wof:name":"Init Ag",
    "wof:placetype":"venue"
},
  "geometry": {"coordinates":[8.5787267685,47.5274963379],"type":"Point"}
}