{
  "type": "Feature",
  "properties": {
    "iso:country":"CH",
    "sg:address":"S\u00e4listrasse 2",
    "sg:city":"Dulliken",
    "sg:orig_category":"Unclassifiable Establishments",
    "sg:postcode":"4657",
    "sg:province":"Solothurn",
    "wof:name":"Physiotherapie & Sportrehabilitation Gossau, Hofland & Jenny & Brussee",
    "wof:placetype":"venue"
},
  "geometry": {"coordinates":[8.7572603226,47.3070106506],"type":"Point"}
}