{
  "type": "Feature",
  "properties": {
    "iso:country":"CH",
    "sg:address":"Augstmattstrasse 3",
    "sg:city":"Pratteln",
    "sg:orig_category":"Verkehrs- and Tourismusb\u00fcros",
    "sg:phone":"+41 61 821 65 76",
    "sg:postcode":"4133",
    "sg:province":"Basel-Landschaft",
    "wof:name":"Verkehrsverein Pratteln Herrn Ren\u00e9 Eichenberger",
    "wof:placetype":"venue"
},
  "geometry": {"coordinates":[7.6924610138,47.5203971863],"type":"Point"}
}