{
  "type": "Feature",
  "properties": {
    "iso:country":"CH",
    "sg:address":"Via Canonica 11",
    "sg:city":"Lugano",
    "sg:orig_category":"Softwareentwicklung U beratung",
    "sg:postcode":"6900",
    "sg:province":"Ticino",
    "wof:name":"Waters & Grove Consulting Services Llc, Cheyenne, Succursale Di Lugano",
    "wof:placetype":"venue"
},
  "geometry": {"coordinates":[8.9586572647,46.0069198608],"type":"Point"}
}