{
  "type": "Feature",
  "properties": {
    "iso:country":"CH",
    "sg:address":"Rue De La Gare 6 1860 Aigle Case Postale 338",
    "sg:city":"Aigle",
    "sg:orig_category":"Zahnarztpraxen",
    "sg:phone":"+41 22 342 62 60",
    "sg:postcode":"1860",
    "sg:province":"Vaud",
    "wof:name":"Dr M\u00e9d. Dent. Jozsef N\u00e9meth M\u00e9decin-dentiste",
    "wof:placetype":"venue"
},
  "geometry": {"coordinates":[6.135931015,46.1879501343],"type":"Point"}
}