{
  "type": "Feature",
  "properties": {
    "iso:country":"CH",
    "sg:address":"Moosackerstrasse 3",
    "sg:city":"Kriegstetten",
    "sg:orig_category":"Politische Parteien CVP",
    "sg:phone":"+41 71 222 33 84",
    "sg:postcode":"4566",
    "sg:province":"Solothurn",
    "wof:name":"Cvp Des Kantons St.gallen",
    "wof:placetype":"venue"
},
  "geometry": {"coordinates":[9.3834171295,47.426990509],"type":"Point"}
}