{
  "type": "Feature",
  "properties": {
    "addr:full":"Tagelswangerstrasse 7 Effretikon Z\u00fcrich 8307",
    "addr:housenumber":"7",
    "addr:postcode":"8307",
    "addr:street":"Tagelswangerstrasse",
    "iso:country":"CH",
    "sg:address":"Tagelswangerstrasse 7",
    "sg:city":"Effretikon",
    "sg:orig_category":"Chemische Reinigung W\u00e4schereien",
    "sg:phone":"+41 21 907 78 52",
    "sg:postcode":"8307",
    "sg:province":"Z\u00fcrich",
    "wof:name":"Jean-marie Jaquet Blanchisserie Ajemari",
    "wof:placetype":"venue"
},
  "geometry": {"coordinates":[6.85426,46.576729],"type":"Point"}
}