{
  "type": "Feature",
  "properties": {
    "iso:country":"CH",
    "sg:address":"Cornavin Rue De 1 1201 Gen\u00e8ve. Postfach",
    "sg:city":"Gen\u00e8ve",
    "sg:orig_category":"Sonstige pers\u00f6nliche Dienstleistungen",
    "sg:postcode":"1201",
    "sg:province":"Gen\u00e8ve",
    "wof:name":"Optimum Developments Limited, Londres, Succursale De Gen\u00e8ve",
    "wof:placetype":"venue"
},
  "geometry": {"coordinates":[6.1419157982,46.2072257996],"type":"Point"}
}