{
  "type": "Feature",
  "properties": {
    "iso:country":"CH",
    "sg:address":"Rue De La Porcelaine 17b",
    "sg:city":"Nyon",
    "sg:orig_category":"Innenarchitekturb\u00fcros",
    "sg:phone":"+41 22 362 63 00",
    "sg:postcode":"1260",
    "sg:province":"Vaud",
    "wof:name":"Atelier El E. Castro & L. Kugler",
    "wof:placetype":"venue"
},
  "geometry": {"coordinates":[6.2413029671,46.3832969666],"type":"Point"}
}