{
  "type": "Feature",
  "properties": {
    "iso:country":"CH",
    "sg:address":"Laubgasse 59a",
    "sg:city":"Frauenfeld",
    "sg:orig_category":"Sportvereine Renn-& Reitsport",
    "sg:postcode":"8500",
    "sg:province":"Thurgau",
    "wof:name":"Reitverein Frauenfeld & Umg.",
    "wof:placetype":"venue"
},
  "geometry": {"coordinates":[8.8896961212,47.5595855713],"type":"Point"}
}