{
  "type": "Feature",
  "properties": {
    "iso:country":"CH",
    "sg:address":"Sattelboden 11",
    "sg:city":"Engelberg",
    "sg:orig_category":"Betrieb von Sportanlagen Herstellung von Sportger\u00e4ten",
    "sg:phone":"+41 41 637 17 37",
    "sg:postcode":"6390",
    "sg:province":"Obwalden",
    "wof:name":"Span Ag",
    "wof:placetype":"venue"
},
  "geometry": {"coordinates":[8.384578,46.824093],"type":"Point"}
}