{
  "type": "Feature",
  "properties": {
    "iso:country":"CH",
    "sg:address":"Industriestrasse 8",
    "sg:city":"Birmensdorf",
    "sg:classifiers":[
        {
            "category":"Utilities",
            "subcategory":"Fuel Oil & Lpg",
            "type":"Services"
        }
    ],
    "sg:phone":"+41 17372520",
    "sg:postcode":"8903",
    "sg:province":"Z\u00fcrich",
    "sg:tags":[
        "services",
        "jig",
        "drilling",
        "boring"
    ],
    "wof:name":"Wettstein Ag",
    "wof:placetype":"venue"
},
  "geometry": {"coordinates":[8.4284582138,47.3662643433],"type":"Point"}
}