{
  "type": "Feature",
  "properties": {
    "iso:country":"CH",
    "sg:address":"Kasimir-pfyffer-strasse 9",
    "sg:city":"Luzern",
    "sg:orig_category":"Detailhandel mit B\u00fcchern",
    "sg:phone":"+41 41 240 13 40",
    "sg:postcode":"6003",
    "sg:province":"Luzern",
    "wof:name":"The English Shop English Children's Books",
    "wof:placetype":"venue"
},
  "geometry": {"coordinates":[8.301277,47.048466],"type":"Point"}
}