{
  "type": "Feature",
  "properties": {
    "iso:country":"CH",
    "sg:address":"Obergrundstrasse 51 6003 Luzern. Postfach",
    "sg:city":"Luzern",
    "sg:orig_category":"RESTAURANTS: TEA-ROOMS",
    "sg:postcode":"6003",
    "sg:province":"Luzern",
    "wof:name":"Restaurant Lindenhof Rupp Ren\u00e9 Und Irene",
    "wof:placetype":"venue"
},
  "geometry": {"coordinates":[8.3041810989,47.0453720093],"type":"Point"}
}