{
  "type": "Feature",
  "properties": {
    "iso:country":"CH",
    "sg:address":"Chilestieg 16 8153 R\u00fcmlang. Postfach",
    "sg:city":"R\u00fcmlang",
    "sg:orig_category":"Sonstiger Grosshandel",
    "sg:postcode":"8153",
    "sg:province":"Z\u00fcrich",
    "wof:name":"T.k. Chikelue Export",
    "wof:placetype":"venue"
},
  "geometry": {"coordinates":[8.5278482437,47.4484863281],"type":"Point"}
}