{
  "type": "Feature",
  "properties": {
    "iso:country":"CH",
    "sg:address":"Via Pedemonte 12",
    "sg:city":"Viganello",
    "sg:orig_category":"Physiotherapie",
    "sg:phone":"+41 91 971 46 77",
    "sg:postcode":"6962",
    "sg:province":"Ticino",
    "wof:name":"Beatrix Vasvary Fisioterapia",
    "wof:placetype":"venue"
},
  "geometry": {"coordinates":[8.9684677124,46.0106773376],"type":"Point"}
}