{
  "type": "Feature",
  "properties": {
    "iso:country":"CH",
    "sg:address":"Chappelistrasse 1",
    "sg:city":"Volketswil",
    "sg:classifiers":[
        {
            "category":"Travel",
            "subcategory":"Hotels & Motels",
            "type":"Entertainment"
        }
    ],
    "sg:postcode":"8604",
    "sg:province":"Z\u00fcrich",
    "sg:tags":[
        "hotels",
        "mit",
        "restaurant"
    ],
    "wof:name":"Ethnotel Betriebs-gmbh",
    "wof:placetype":"venue"
},
  "geometry": {"coordinates":[8.6737508774,47.3893318176],"type":"Point"}
}