{
  "type": "Feature",
  "properties": {
    "iso:country":"CH",
    "sg:address":"Felsenaustrasse 18 7000 Chur. Postfach",
    "sg:city":"Chur",
    "sg:orig_category":"Allgemeiner Hoch U Tiefbau",
    "sg:postcode":"7000",
    "sg:province":"Graubunden",
    "wof:name":"Zschokke Generalunternehmung Ag",
    "wof:placetype":"venue"
},
  "geometry": {"coordinates":[9.409669,47.433258],"type":"Point"}
}