{
  "type": "Feature",
  "properties": {
    "iso:country":"CH",
    "sg:address":"Ruchholzstrasse 11",
    "sg:city":"Bottmingen",
    "sg:orig_category":"Fernmeldedienste",
    "sg:phone":"+41 61 423 00 66",
    "sg:postcode":"4103",
    "sg:province":"Basel-Landschaft",
    "wof:name":"Mad\u00f6rin-engineering Gmbh",
    "wof:placetype":"venue"
},
  "geometry": {"coordinates":[7.5737018585,47.5248527527],"type":"Point"}
}