{
  "type": "Feature",
  "properties": {
    "iso:country":"CH",
    "sg:address":"Luzernerstrasse 3",
    "sg:city":"Grossdietwil",
    "sg:orig_category":"Darlehenskassen U Raiffeisenbanken",
    "sg:phone":"+41 62 927 22 72",
    "sg:postcode":"6146",
    "sg:province":"Luzern",
    "wof:name":"Raiffeisenbank",
    "wof:placetype":"venue"
},
  "geometry": {"coordinates":[7.887298,47.170631],"type":"Point"}
}