{
  "type": "Feature",
  "properties": {
    "iso:country":"CH",
    "sg:address":"Florissant Route De 51 1206 Gen\u00e8ve. Postfach",
    "sg:city":"Gen\u00e8ve",
    "sg:orig_category":"Pensionskassen",
    "sg:postcode":"1206",
    "sg:province":"Gen\u00e8ve",
    "wof:name":"Cunz Dr. Jakob-stiftung",
    "wof:placetype":"venue"
},
  "geometry": {"coordinates":[9.1504201889,47.5487518311],"type":"Point"}
}