{
  "type": "Feature",
  "properties": {
    "iso:country":"CH",
    "sg:address":"Schmittenstrasse 3937 Baltschieder. Postfach",
    "sg:city":"Baltschieder",
    "sg:orig_category":"Sanit\u00e4r U Heizungsinstallation Sanit\u00e4rinstallation",
    "sg:phone":"+41 27 946 36 80",
    "sg:postcode":"3937",
    "sg:province":"Valais",
    "wof:name":"Erwin Hornetz San.installationen Heizungen",
    "wof:placetype":"venue"
},
  "geometry": {"coordinates":[7.8618102074,46.3057250977],"type":"Point"}
}