{
  "type": "Feature",
  "properties": {
    "iso:country":"CH",
    "sg:address":"Alpenstrasse 2",
    "sg:city":"Interlaken",
    "sg:orig_category":"Herstellung von Duft U K\u00f6rperpflegemitteln",
    "sg:phone":"+41 71 877 23 16",
    "sg:postcode":"3800",
    "sg:province":"Bern",
    "wof:name":"Marlin K\u00fcnzler",
    "wof:placetype":"venue"
},
  "geometry": {"coordinates":[9.4836530685,47.4145507812],"type":"Point"}
}