{
  "type": "Feature",
  "properties": {
    "iso:country":"CH",
    "sg:address":"Kantonsstrasse",
    "sg:city":"Altb\u00fcron",
    "sg:orig_category":"Nationale Postdienste",
    "sg:phone":"+41 62 927 20 02",
    "sg:postcode":"6147",
    "sg:province":"Luzern",
    "wof:name":"Die Schweizerische Post",
    "wof:placetype":"venue"
},
  "geometry": {"coordinates":[7.8820648193,47.1776847839],"type":"Point"}
}