{
  "type": "Feature",
  "properties": {
    "iso:country":"CH",
    "sg:address":"Z\u00fcrcherstrasse 334 8500 Frauenfeld. Postfach",
    "sg:city":"Frauenfeld",
    "sg:orig_category":"Instandhaltung U Reparatur von Automobilen",
    "sg:phone":"+41 52 721 18 38",
    "sg:postcode":"8500",
    "sg:province":"Thurgau",
    "wof:name":"Fahrzeug Ag, Frauenfeld",
    "wof:placetype":"venue"
},
  "geometry": {"coordinates":[8.9138813019,47.5665817261],"type":"Point"}
}