{
  "type": "Feature",
  "properties": {
    "iso:country":"CH",
    "sg:address":"Dorfstrasse 1",
    "sg:city":"Wabern",
    "sg:orig_category":"Unternehmensberatung",
    "sg:phone":"+41 31 960 43 10",
    "sg:postcode":"3084",
    "sg:province":"Bern",
    "wof:name":"D'silva Trade Consult",
    "wof:placetype":"venue"
},
  "geometry": {"coordinates":[7.4480371475,46.9300804138],"type":"Point"}
}