{
  "type": "Feature",
  "properties": {
    "iso:country":"CH",
    "sg:address":"Rheintalstrasse 293",
    "sg:city":"Leibstadt",
    "sg:orig_category":"Organisationen des Gesundheitswesen",
    "sg:phone":"+41 56 247 15 45",
    "sg:postcode":"5325",
    "sg:province":"Aargau",
    "wof:name":"Haus-& Krankenpflege",
    "wof:placetype":"venue"
},
  "geometry": {"coordinates":[8.1697587967,47.5894317627],"type":"Point"}
}