{
  "type": "Feature",
  "properties": {
    "iso:country":"CH",
    "sg:address":"Freie Strasse 81 4051 Basel. Postfach",
    "sg:city":"Basel",
    "sg:classifiers":[
        {
            "category":"Communications",
            "subcategory":"Film & Video Production",
            "type":"Services"
        }
    ],
    "sg:phone":"+41 61 272 77 88",
    "sg:postcode":"4001",
    "sg:province":"Basel-Stadt",
    "sg:tags":[
        "videofilmherstellung",
        "u"
    ],
    "wof:name":"Franz Goetschel Audiovisuelle Produktionen",
    "wof:placetype":"venue"
},
  "geometry": {"coordinates":[7.5910711288,47.5552253723],"type":"Point"}
}