{
  "type": "Feature",
  "properties": {
    "iso:country":"CH",
    "sg:address":"Tschachen",
    "sg:city":"N\u00e4fels",
    "sg:classifiers":[
        {
            "category":"Professional",
            "subcategory":"Engineering",
            "type":"Services"
        }
    ],
    "sg:phone":"+41 55 618 61 11",
    "sg:postcode":"8752",
    "sg:province":"Glarus",
    "sg:tags":[
        "machine",
        "-",
        "mechanical"
    ],
    "wof:name":"Netstal-maschinen Ag",
    "wof:placetype":"venue"
},
  "geometry": {"coordinates":[9.0691699982,47.0965003967],"type":"Point"}
}