{
  "type": "Feature",
  "properties": {
    "iso:country":"CH",
    "sg:address":"Freiestrasse 204",
    "sg:city":"Z\u00fcrich",
    "sg:orig_category":"Architektur U Ingenieurb\u00fcros Unternehmensberatung",
    "sg:phone":"+41 31 932 17 91",
    "sg:postcode":"8032",
    "sg:province":"Z\u00fcrich",
    "wof:name":"Us Consulting & Engineering, Stingelin Urs, Ingenieur Htl Ingenierdienstleistungen U. Projektierungen Im Bereich Der Telekommuniktion",
    "wof:placetype":"venue"
},
  "geometry": {"coordinates":[7.515227,46.958321],"type":"Point"}
}