{
  "type": "Feature",
  "properties": {
    "iso:country":"CH",
    "sg:address":"Route Du Village 2",
    "sg:city":"Epalinges",
    "sg:orig_category":"Architekturb\u00fcros",
    "sg:phone":"+41 21 784 06 60",
    "sg:postcode":"1066",
    "sg:province":"Vaud",
    "wof:name":"Pascal Lorini Bureau D'architecture",
    "wof:placetype":"venue"
},
  "geometry": {"coordinates":[6.67417,46.549351],"type":"Point"}
}