{
  "type": "Feature",
  "properties": {
    "iso:country":"CH",
    "sg:address":"Place De La Paix 1",
    "sg:city":"Montreux",
    "sg:orig_category":"Non-Classified Establishments",
    "sg:postcode":"1820",
    "sg:province":"Vaud",
    "wof:name":"Osman Akbal",
    "wof:placetype":"venue"
},
  "geometry": {"coordinates":[6.9110908508,46.4314498901],"type":"Point"}
}