{
  "type": "Feature",
  "properties": {
    "iso:country":"CH",
    "sg:address":"Baarerstr. 25",
    "sg:city":"Zug",
    "sg:classifiers":[
        {
            "category":"Banks & Credit Unions",
            "subcategory":"Bank",
            "type":"Services"
        }
    ],
    "sg:phone":"+41 41 710 32 88",
    "sg:postcode":"6300",
    "sg:province":"Zug",
    "wof:name":"Migrosbank",
    "wof:placetype":"venue"
},
  "geometry": {"coordinates":[8.516214,47.172775],"type":"Point"}
}