{
  "type": "Feature",
  "properties": {
    "iso:country":"CH",
    "sg:address":"Route Du Midi 13",
    "sg:city":"Marly",
    "sg:orig_category":"Fachdetailhandel in Verkaufsr\u00e4umen",
    "sg:postcode":"1723",
    "sg:province":"Fribourg",
    "wof:name":"Snow Zone Biland Marco",
    "wof:placetype":"venue"
},
  "geometry": {"coordinates":[7.1506948471,46.7812042236],"type":"Point"}
}