{
  "type": "Feature",
  "properties": {
    "iso:country":"CH",
    "sg:address":"Chemin De Closel 7",
    "sg:city":"Bevaix",
    "sg:orig_category":"Geb\u00e4ude, Wohnungsreinigung Unterhalt U Reparatur im Hoch U Tiefbau",
    "sg:phone":"+41 32 846 23 36",
    "sg:postcode":"2022",
    "sg:province":"Neuch\u00e2tel",
    "wof:name":"Gilbert Jeanneret James Tous Services",
    "wof:placetype":"venue"
},
  "geometry": {"coordinates":[6.8117399216,46.9277114868],"type":"Point"}
}