{
  "type": "Feature",
  "properties": {
    "iso:country":"CH",
    "sg:address":"Hofstrasse 24 6300 Zug. Postfach 947",
    "sg:city":"Zug",
    "sg:orig_category":"Unclassifiable Establishments",
    "sg:postcode":"6300",
    "sg:province":"Zug",
    "wof:name":"Calltec Ag Dienstleistungen Im Bereich D. Unternehmenskommunikation",
    "wof:placetype":"venue"
},
  "geometry": {"coordinates":[8.5151462555,47.1594581604],"type":"Point"}
}