{
  "type": "Feature",
  "properties": {
    "iso:country":"CH",
    "sg:address":"Unterf\u00fchrungsstrasse 51",
    "sg:city":"Olten",
    "sg:orig_category":"Berufsbildende weiterf\u00fchrende Schulen Coiffeursalons U Kosmetikinstitute",
    "sg:phone":"+41 62 296 27 77",
    "sg:postcode":"4600",
    "sg:province":"Solothurn",
    "wof:name":"R\u00fctimann",
    "wof:placetype":"venue"
},
  "geometry": {"coordinates":[7.910841,47.348938],"type":"Point"}
}