{
  "type": "Feature",
  "properties": {
    "iso:country":"CH",
    "sg:address":"Rothenfluhm\u00e4tteli 13",
    "sg:city":"Wiggen",
    "sg:orig_category":"Grosshandel mit Getreide, Saatgut U Futtermitteln",
    "sg:phone":"+41 41 486 22 77",
    "sg:postcode":"6192",
    "sg:province":"Luzern",
    "wof:name":"Agro-plus Stalder",
    "wof:placetype":"venue"
},
  "geometry": {"coordinates":[7.9097008705,46.8958778381],"type":"Point"}
}