{
  "type": "Feature",
  "properties": {
    "iso:country":"CH",
    "sg:address":"Grabenackerstrasse 5",
    "sg:city":"Oensingen",
    "sg:orig_category":"Grosshandel mit Eisenwaren sowie Installationsbedarf f\u00fcr Gas, Wasser U Heizung Grosshandel mit Erzen",
    "sg:phone":"+41 62 396 24 56",
    "sg:postcode":"4702",
    "sg:province":"Solothurn",
    "wof:name":"W. Roeck Ag Hartmetall & Diamantwerkzeuge",
    "wof:placetype":"venue"
},
  "geometry": {"coordinates":[7.7110128403,47.2850761414],"type":"Point"}
}