{
  "type": "Feature",
  "properties": {
    "iso:country":"CH",
    "sg:address":"La Rochena 2",
    "sg:city":"Enney",
    "sg:orig_category":"Sportvereine Ballsport Badminton",
    "sg:phone":"+41 32 730 65 25",
    "sg:postcode":"1667",
    "sg:province":"Fribourg",
    "wof:name":"Badminton-club Neuch\u00e2tel",
    "wof:placetype":"venue"
},
  "geometry": {"coordinates":[6.941450119,46.9826812744],"type":"Point"}
}