{
  "type": "Feature",
  "properties": {
    "iso:country":"CH",
    "sg:address":"Chemin Du Pr\u00e9-fleuri 27",
    "sg:city":"Plan-les-ouates",
    "sg:orig_category":"Grosshandel mit Fleisch U Fleischwaren Grosshandel mit Wein U Spirituosen",
    "sg:phone":"+41 22 884 34 84",
    "sg:postcode":"1228",
    "sg:province":"Gen\u00e8ve",
    "wof:name":"Covin Ag Spanische Lebensmittel & Biere",
    "wof:placetype":"venue"
},
  "geometry": {"coordinates":[6.10769701,46.1651268005],"type":"Point"}
}