{
  "type": "Feature",
  "properties": {
    "iso:country":"CH",
    "sg:address":"Rheinstrasse 56 7000 Chur. Postfach 30",
    "sg:city":"Chur",
    "sg:orig_category":"Arbeitnehmerverb\u00e4nde",
    "sg:phone":"+41 81 284 81 43",
    "sg:postcode":"7004",
    "sg:province":"Graubunden",
    "wof:name":"Schweiz.verein Technischer Kaufleute",
    "wof:placetype":"venue"
},
  "geometry": {"coordinates":[9.52264,46.854237],"type":"Point"}
}