{
  "type": "Feature",
  "properties": {
    "iso:country":"CH",
    "sg:address":"Langhagweg 47",
    "sg:city":"Laufen",
    "sg:orig_category":"Autospenglereien",
    "sg:phone":"+41 19322628",
    "sg:postcode":"4242",
    "sg:province":"Basel-Landschaft",
    "wof:name":"Andreas Mettler Carrosserie",
    "wof:placetype":"venue"
},
  "geometry": {"coordinates":[8.78526,47.325821],"type":"Point"}
}