{
  "type": "Feature",
  "properties": {
    "iso:country":"CH",
    "sg:address":"Birchli 9",
    "sg:city":"Einsiedeln",
    "sg:orig_category":"Sportvereine Flug Aero-Club",
    "sg:postcode":"8840",
    "sg:province":"Schwyz",
    "wof:name":"Ae.c.s.modellfluggruppe",
    "wof:placetype":"venue"
},
  "geometry": {"coordinates":[8.7675046921,47.1303672791],"type":"Point"}
}