{
  "type": "Feature",
  "properties": {
    "iso:country":"CH",
    "sg:address":"Les Oies 137 D",
    "sg:city":"Nods",
    "sg:orig_category":"Sonstige mit Sport verbundene T\u00e4tigkeiten",
    "sg:phone":"+41 32 751 47 42",
    "sg:postcode":"2518",
    "sg:province":"Bern",
    "wof:name":"Zorro S\u00e0rl",
    "wof:placetype":"venue"
},
  "geometry": {"coordinates":[7.0804219246,47.1172485352],"type":"Point"}
}