{
  "type": "Feature",
  "properties": {
    "iso:country":"CH",
    "sg:address":"Avenue De La Gare 14 1950 Sion Case Postale 727",
    "sg:city":"Sion",
    "sg:orig_category":"K\u00fcnstlerische Schulen",
    "sg:phone":"+41 79 220 71 54",
    "sg:postcode":"1951",
    "sg:province":"Valais",
    "wof:name":"Alfa S\u00e0rl Ecole De Musique C/o Power Sa",
    "wof:placetype":"venue"
},
  "geometry": {"coordinates":[7.3588700294,46.2293243408],"type":"Point"}
}