{
  "type": "Feature",
  "properties": {
    "iso:country":"CH",
    "sg:address":"Dancet Rue 1 1205 Gen\u00e8ve Case Postale",
    "sg:city":"Gen\u00e8ve",
    "sg:orig_category":"Non-Classified Establishments",
    "sg:postcode":"1205",
    "sg:province":"Gen\u00e8ve",
    "wof:name":"Kusar Grafik",
    "wof:placetype":"venue"
},
  "geometry": {"coordinates":[8.2203550339,47.4928741455],"type":"Point"}
}