{
  "type": "Feature",
  "properties": {
    "iso:country":"CH",
    "sg:address":"Chemin Chapons-des-pr\u00e9s 13",
    "sg:city":"Bevaix",
    "sg:orig_category":"Grosshandel mit Foto U Kinoger\u00e4ten, feinmechanischen U optischen Erzeugnissen Herstellung von medizi",
    "sg:phone":"+41 32 720 07 77",
    "sg:postcode":"2022",
    "sg:province":"Neuch\u00e2tel",
    "wof:name":"Bms Sensor Technology Sa",
    "wof:placetype":"venue"
},
  "geometry": {"coordinates":[6.8109521866,46.9246292114],"type":"Point"}
}