{
  "type": "Feature",
  "properties": {
    "iso:country":"CH",
    "sg:address":"Holzmattweg 24",
    "sg:city":"Hermrigen",
    "sg:classifiers":[
        {
            "category":"Banks & Credit Unions",
            "subcategory":"Bank",
            "type":"Services"
        }
    ],
    "sg:phone":"+41 32801331",
    "sg:postcode":"3274",
    "sg:province":"Bern",
    "wof:name":"Schweiz. Mobiliar",
    "wof:placetype":"venue"
},
  "geometry": {"coordinates":[7.243899,47.081314],"type":"Point"}
}