{
  "type": "Feature",
  "properties": {
    "iso:country":"CH",
    "sg:address":"Landstr. 195",
    "sg:city":"Klosters",
    "sg:classifiers":[
        {
            "category":"Autos & Motor Vehicles",
            "subcategory":"Automobile Sales",
            "type":"Retail Goods"
        }
    ],
    "sg:phone":"+41 71 228 64 64",
    "sg:postcode":"7250",
    "sg:province":"Graubunden",
    "sg:tags":[
        "equipment",
        "motor-cars",
        "transport"
    ],
    "wof:name":"Emil Frey Ag Autopark",
    "wof:placetype":"venue"
},
  "geometry": {"coordinates":[9.3879480362,47.4254379272],"type":"Point"}
}