{
  "type": "Feature",
  "properties": {
    "iso:country":"CH",
    "sg:address":"Tachlisbrunnenstrasse 20",
    "sg:city":"Winterthur",
    "sg:orig_category":"Allgemeiner Hoch U Tiefbau Allgemeiner Hochbau",
    "sg:phone":"+41 52 213 26 60",
    "sg:postcode":"8400",
    "sg:province":"Z\u00fcrich",
    "wof:name":"Mimmo Bauunternehmung Ag",
    "wof:placetype":"venue"
},
  "geometry": {"coordinates":[8.729117,47.509964],"type":"Point"}
}