{
  "type": "Feature",
  "properties": {
    "iso:country":"CH",
    "sg:address":"Spisergasse 3",
    "sg:city":"St.gallen",
    "sg:orig_category":"Interessenvertretungen",
    "sg:postcode":"9000",
    "sg:province":"St. Gallen",
    "wof:name":"Stiftung Vetter Claire Und Hans Erben",
    "wof:placetype":"venue"
},
  "geometry": {"coordinates":[9.3768100739,47.4249954224],"type":"Point"}
}