{
  "type": "Feature",
  "properties": {
    "addr:full":"Villars Bramard Villars Bramard 1556",
    "addr:housenumber":"1556",
    "iso:country":"CH",
    "sg:address":"Villars Bramard",
    "sg:city":"Villars Bramard",
    "sg:classifiers":[
        {
            "category":"Banks & Credit Unions",
            "subcategory":"Bank",
            "type":"Services"
        }
    ],
    "sg:phone":"+41 37525455",
    "sg:postcode":"1556",
    "wof:name":"Banque Raiffeisen",
    "wof:placetype":"venue"
},
  "geometry": {"coordinates":[6.898774,46.718956],"type":"Point"}
}