{
  "type": "Feature",
  "properties": {
    "iso:country":"CH",
    "sg:address":"H\u00f6henstrasse 24 9302 Kronb\u00fchl. Postfach",
    "sg:city":"Kronb\u00fchl",
    "sg:orig_category":"Grosshandel mit Textilien",
    "sg:phone":"+41 18292930",
    "sg:postcode":"9302",
    "wof:name":"Temtec Ag",
    "wof:placetype":"venue"
},
  "geometry": {"coordinates":[9.0389566422,47.472202301],"type":"Point"}
}