{
  "type": "Feature",
  "properties": {
    "iso:country":"CH",
    "sg:address":"Z\u00fcrichstrasse 76",
    "sg:city":"Pfaffhausen",
    "sg:orig_category":"Herstellung von Werkzeugen Herstellung von sonstigen Maschinen f\u00fcr bestimmte Verwendung",
    "sg:phone":"+41 18262800",
    "sg:postcode":"8118",
    "sg:province":"Z\u00fcrich",
    "wof:name":"Swisscrimp Gisler Roland & Partner",
    "wof:placetype":"venue"
},
  "geometry": {"coordinates":[8.6205329895,47.3649635315],"type":"Point"}
}