{
  "type": "Feature",
  "properties": {
    "iso:country":"CH",
    "sg:address":"Rebacherring",
    "sg:city":"Pfaffnau",
    "sg:orig_category":"Handelsvermittlung U Grosshandel",
    "sg:phone":"+41 62 754 04 14",
    "sg:postcode":"6264",
    "sg:province":"Luzern",
    "wof:name":"Di Luna's Handel Gmbh",
    "wof:placetype":"venue"
},
  "geometry": {"coordinates":[7.901971817,47.2317390442],"type":"Point"}
}