{
  "type": "Feature",
  "properties": {
    "iso:country":"CH",
    "sg:address":"Wilstrasse 25",
    "sg:city":"Horriwil",
    "sg:orig_category":"Physiotherapie",
    "sg:phone":"+41 32 751 47 69",
    "sg:postcode":"4557",
    "sg:province":"Solothurn",
    "wof:name":"Mariquita Ten Broek Physioth\u00e9rapie",
    "wof:placetype":"venue"
},
  "geometry": {"coordinates":[7.0919408798,47.0653305054],"type":"Point"}
}