{
  "type": "Feature",
  "properties": {
    "iso:country":"CH",
    "sg:address":"Romanshornerstrasse 57",
    "sg:city":"Wittenbach",
    "sg:orig_category":"Grosshandel mit festen Brennstoffen U Mineral\u00f6lerzeugnissen",
    "sg:postcode":"9303",
    "wof:name":"Vulkan Z\u00fcndw\u00fcrfelfabrik, Arnold J.",
    "wof:placetype":"venue"
},
  "geometry": {"coordinates":[9.3827371597,47.4604110718],"type":"Point"}
}