{
  "type": "Feature",
  "properties": {
    "iso:country":"CH",
    "sg:address":"Hotel Wissifluh",
    "sg:city":"Vitznau",
    "sg:orig_category":"Seilbahnen",
    "sg:phone":"+41 41 397 13 27",
    "sg:postcode":"6354",
    "sg:province":"Luzern",
    "wof:name":"Wissifluh-bahn J.trionfini",
    "wof:placetype":"venue"
},
  "geometry": {"coordinates":[8.4949407578,47.002456665],"type":"Point"}
}