{
  "type": "Feature",
  "properties": {
    "iso:country":"CH",
    "sg:address":"Altegghalde 10 6045 Meggen. Postfach",
    "sg:city":"Meggen",
    "sg:orig_category":"Zimmerei, Dachdeckerei, Bauspenglerei U Abdichtung",
    "sg:postcode":"6045",
    "sg:province":"Luzern",
    "wof:name":"Herzog Alois Ag, Spenglerei Und Sanit\u00e4re Anlagen",
    "wof:placetype":"venue"
},
  "geometry": {"coordinates":[8.3668298721,47.0410842896],"type":"Point"}
}