{
  "type": "Feature",
  "properties": {
    "iso:country":"CH",
    "sg:address":"Rue Des Plantys 33",
    "sg:city":"Chamoson",
    "sg:orig_category":"Mechanik Sanit\u00e4rinstallation",
    "sg:phone":"+41 79 220 79 12",
    "sg:postcode":"1955",
    "sg:province":"Valais",
    "wof:name":"Pierre Monnet & Fils Installations Sanitaires",
    "wof:placetype":"venue"
},
  "geometry": {"coordinates":[7.2251372337,46.1985969543],"type":"Point"}
}