{
  "type": "Feature",
  "properties": {
    "iso:country":"CH",
    "sg:address":"B\u00fcelstrasse 16",
    "sg:city":"Baar",
    "sg:orig_category":"Sanit\u00e4r, Heizungs U L\u00fcftungsinstallation",
    "sg:phone":"+41 41 761 43 91",
    "sg:postcode":"6340",
    "sg:province":"Zug",
    "wof:name":"G\u00fcnti B\u00fcttiker",
    "wof:placetype":"venue"
},
  "geometry": {"coordinates":[8.5290727615,47.1980361938],"type":"Point"}
}