{
  "type": "Feature",
  "properties": {
    "iso:country":"CH",
    "sg:address":"Gstaltenrainweg 63 4125 Riehen. Postfach",
    "sg:city":"Riehen",
    "sg:orig_category":"Gesundheitswesen",
    "sg:phone":"+41 61 603 25 35",
    "sg:postcode":"4125",
    "sg:province":"Basel-Stadt",
    "wof:name":"Vitamax Gmbh Ern\u00e4hrungsberatung U. Beratung F\u00fcr Hersteller Von Medizinprodukten Usw",
    "wof:placetype":"venue"
},
  "geometry": {"coordinates":[7.6381659508,47.5743904114],"type":"Point"}
}