{
  "type": "Feature",
  "properties": {
    "iso:country":"CH",
    "sg:address":"Silbernstrasse 18 8953 Dietikon. Postfach",
    "sg:city":"Dietikon",
    "sg:orig_category":"Detailhandel mit elektrischen Haushalts-,Radio U Fernsehger\u00e4ten sowie Musikinstrumenten",
    "sg:postcode":"8953",
    "sg:province":"Z\u00fcrich",
    "wof:name":"Number One Distribution Gmbh",
    "wof:placetype":"venue"
},
  "geometry": {"coordinates":[8.3938560486,47.4180526733],"type":"Point"}
}