{
  "type": "Feature",
  "properties": {
    "iso:country":"CH",
    "sg:address":"Arinstrasse 14 9475 Sevelen. Postfach",
    "sg:city":"Sevelen",
    "sg:orig_category":"Non-Classified Establishments",
    "sg:postcode":"9475",
    "sg:province":"St. Gallen",
    "wof:name":"Pdl Postdienst Gmbh",
    "wof:placetype":"venue"
},
  "geometry": {"coordinates":[9.4885730743,47.1264152527],"type":"Point"}
}