{
  "type": "Feature",
  "properties": {
    "iso:country":"CH",
    "sg:address":"Fasanenstrasse 18",
    "sg:city":"M\u00f6hlin",
    "sg:orig_category":"Kauf U Verkauf von Immobilien auf eigene Rechnung",
    "sg:postcode":"4313",
    "sg:province":"Aargau",
    "wof:name":"Comprima Finanz Ag Hergiswil Liegenschaften, Finanzgesch\u00e4fte Usw",
    "wof:placetype":"venue"
},
  "geometry": {"coordinates":[8.3037157059,46.9888801575],"type":"Point"}
}