{
  "type": "Feature",
  "properties": {
    "iso:country":"CH",
    "sg:address":"Seestrasse 25",
    "sg:city":"Z\u00fcrich",
    "sg:orig_category":"Detailhandel mit fotografischen Artikeln Fotografische Ateliers",
    "sg:phone":"+41 12011483",
    "sg:postcode":"8002",
    "sg:province":"Z\u00fcrich",
    "wof:name":"Foto Star Gmbh",
    "wof:placetype":"venue"
},
  "geometry": {"coordinates":[8.5315589905,47.3637008667],"type":"Point"}
}