{
  "type": "Feature",
  "properties": {
    "iso:country":"CH",
    "sg:address":"9657",
    "sg:city":"Unterwasser",
    "sg:orig_category":"Personenbef\u00f6rderung im Linienverkehr zu Land",
    "sg:phone":"+41 81 927 70 01",
    "sg:postcode":"9657",
    "sg:province":"St. Gallen",
    "wof:name":"Bergbahnen Weisse Arena Ag",
    "wof:placetype":"venue"
},
  "geometry": {"coordinates":[9.2103004456,46.8544311523],"type":"Point"}
}