{
  "type": "Feature",
  "properties": {
    "iso:country":"CH",
    "sg:address":"1587",
    "sg:city":"Montmagny",
    "sg:orig_category":"Detailhandel mit Getr\u00e4nken",
    "sg:phone":"+41 26 677 10 49",
    "sg:postcode":"1587",
    "sg:province":"Vaud",
    "wof:name":"Andr\u00e9 Loup & Fils Commerce De Vins",
    "wof:placetype":"venue"
},
  "geometry": {"coordinates":[7.0109500885,46.9260215759],"type":"Point"}
}