{
  "type": "Feature",
  "properties": {
    "iso:country":"CH",
    "sg:address":"Ebnaterstrasse 23",
    "sg:city":"Wattwil",
    "sg:orig_category":"Herstellung von Konstruktionsteilen, Fertigbauteilen U Ausbauelementen aus Holz",
    "sg:phone":"+41 21 947 45 85",
    "sg:postcode":"9630",
    "sg:province":"St. Gallen",
    "wof:name":"Gabriel Jean-claude",
    "wof:placetype":"venue"
},
  "geometry": {"coordinates":[6.8259902,46.523311615],"type":"Point"}
}