{
  "type": "Feature",
  "properties": {
    "iso:country":"CH",
    "sg:address":"Lausanne Rue De 126 1202 Gen\u00e8ve. Postfach",
    "sg:city":"Gen\u00e8ve",
    "sg:orig_category":"RESTAURANTS: TEA-ROOMS",
    "sg:phone":"+41 19501166",
    "sg:postcode":"1202",
    "sg:province":"Gen\u00e8ve",
    "wof:name":"Hausammann Beatrice, Restaurant Freienstein",
    "wof:placetype":"venue"
},
  "geometry": {"coordinates":[8.7969799042,47.3650588989],"type":"Point"}
}