{
  "type": "Feature",
  "properties": {
    "iso:country":"CH",
    "sg:address":"Baslerstrasse 63",
    "sg:city":"Olten",
    "sg:orig_category":"RESTAURANTS: TEA-ROOMS",
    "sg:phone":"+41 62 212 20 88",
    "sg:postcode":"4600",
    "sg:province":"Solothurn",
    "wof:name":"Verdotti & Partner",
    "wof:placetype":"venue"
},
  "geometry": {"coordinates":[7.902282238,47.3533058167],"type":"Point"}
}