{
  "type": "Feature",
  "properties": {
    "iso:country":"CH",
    "sg:address":"H\u00f6htalstrasse 25",
    "sg:city":"Ennetbaden",
    "sg:orig_category":"Herstellung von Werkzeugen",
    "sg:phone":"+41 56 222 42 01",
    "sg:postcode":"5408",
    "sg:province":"Aargau",
    "wof:name":"Max Horlacher Ag, Werkzeug Und Apparatebau",
    "wof:placetype":"venue"
},
  "geometry": {"coordinates":[8.318523407,47.478805542],"type":"Point"}
}