{
  "type": "Feature",
  "properties": {
    "iso:country":"CH",
    "sg:address":"Erlenstrasse 58",
    "sg:city":"Basel",
    "sg:classifiers":[
        {
            "category":"Restaurant",
            "type":"Food & Drink"
        }
    ],
    "sg:phone":"+41 61 693 18 01",
    "sg:postcode":"4058",
    "sg:province":"Basel-Stadt",
    "wof:name":"Restaurant Flamenco",
    "wof:placetype":"venue"
},
  "geometry": {"coordinates":[7.6017417908,47.5687522888],"type":"Point"}
}