{
  "type": "Feature",
  "properties": {
    "iso:country":"CH",
    "sg:address":"Alte Landstrasse 9",
    "sg:city":"Oberrieden",
    "sg:orig_category":"Herstellung von sonstigen Maschinen f\u00fcr bestimmte Verwendung",
    "sg:phone":"+41 17205553",
    "sg:postcode":"8942",
    "sg:province":"Z\u00fcrich",
    "wof:name":"Ita Gestaltung",
    "wof:placetype":"venue"
},
  "geometry": {"coordinates":[8.5744466782,47.2800064087],"type":"Point"}
}