{
  "type": "Feature",
  "properties": {
    "iso:country":"CH",
    "sg:address":"S. Gallerstrasse 10",
    "sg:city":"Arbon",
    "sg:orig_category":"Druck ohne Zeitungsdruck Schnelldruck U Kopierservice",
    "sg:phone":"+41 71 446 00 07",
    "sg:postcode":"9320",
    "sg:province":"Thurgau",
    "wof:name":"Digisprint Digitaldruck & Kopierservice R.peloli",
    "wof:placetype":"venue"
},
  "geometry": {"coordinates":[9.4317111969,47.5121421814],"type":"Point"}
}