{
  "type": "Feature",
  "properties": {
    "iso:country":"CH",
    "sg:address":"6558",
    "sg:city":"Lostallo",
    "sg:orig_category":"Grosshandel mit Holz U Baustoffen S\u00e4gewerke",
    "sg:phone":"+41 52 649 31 26",
    "sg:postcode":"6558",
    "sg:province":"Graubunden",
    "wof:name":"Steinemann Adolf Ag",
    "wof:placetype":"venue"
},
  "geometry": {"coordinates":[8.676779747,47.782459259],"type":"Point"}
}