{
  "type": "Feature",
  "properties": {
    "iso:country":"CH",
    "sg:address":"Baarerstrasse 12 6300 Zug. Postfach",
    "sg:city":"Zug",
    "sg:orig_category":"Unternehmensberatung",
    "sg:postcode":"6300",
    "sg:province":"Zug",
    "wof:name":"Bcap Schweiz Ag F\u00f6rdert Gr\u00fcndung Und Wachstum Von Unternehmen Usw",
    "wof:placetype":"venue"
},
  "geometry": {"coordinates":[8.5164785385,47.1717300415],"type":"Point"}
}