{
  "type": "Feature",
  "properties": {
    "addr:full":"Westquaistrasse 60 4057 Basel. Postfach Basel Basel-Stadt 4019",
    "addr:housenumber":"60",
    "addr:postcode":"4057;4019",
    "addr:street":"Westquaistrasse;Postfach",
    "iso:country":"CH",
    "sg:address":"Westquaistrasse 60 4057 Basel. Postfach",
    "sg:city":"Basel",
    "sg:orig_category":"Binnenschiffahrt",
    "sg:phone":"+41 61 638 38 38",
    "sg:postcode":"4019",
    "sg:province":"Basel-Stadt",
    "wof:name":"Navis Schiffahrt Ag Transportgesch\u00e4fte Auf Fl\u00fcssen, Kan\u00e4len Usw",
    "wof:placetype":"venue"
},
  "geometry": {"coordinates":[7.589197,47.587105],"type":"Point"}
}