{
  "type": "Feature",
  "properties": {
    "iso:country":"CH",
    "sg:address":"R\u00fctistrasse 3",
    "sg:city":"Hombrechtikon",
    "sg:orig_category":"Erbringung von sonstigen Dienstleistungen f\u00fcr Unternehmen",
    "sg:phone":"+41 55 244 45 31",
    "sg:postcode":"8634",
    "sg:province":"Z\u00fcrich",
    "wof:name":"Claro Weltladen",
    "wof:placetype":"venue"
},
  "geometry": {"coordinates":[8.7667217255,47.2516479492],"type":"Point"}
}