{
  "type": "Feature",
  "properties": {
    "iso:country":"CH",
    "sg:address":"Hauptstrasse 53 5070 Frick. Postfach",
    "sg:city":"Frick",
    "sg:orig_category":"Regionalbanken U Sparkassen",
    "sg:phone":"+41 62 865 15 15",
    "sg:postcode":"5070",
    "sg:province":"Aargau",
    "wof:name":"Neue Aargauer Bank",
    "wof:placetype":"venue"
},
  "geometry": {"coordinates":[8.0212116241,47.5073318481],"type":"Point"}
}