{
  "type": "Feature",
  "properties": {
    "iso:country":"CH",
    "sg:address":"L\u00e4nggasse 25a",
    "sg:city":"Thun",
    "sg:orig_category":"Allgemeiner Hoch U Tiefbau",
    "sg:postcode":"3600",
    "sg:province":"Bern",
    "wof:name":"Germann O.",
    "wof:placetype":"venue"
},
  "geometry": {"coordinates":[7.620802,46.751408],"type":"Point"}
}