{
  "type": "Feature",
  "properties": {
    "iso:country":"CH",
    "sg:address":"Sch\u00f6nenbergstrasse 60",
    "sg:city":"W\u00e4denswil",
    "sg:orig_category":"Mit Sport verbundene T\u00e4tigkeiten",
    "sg:phone":"+41 79 413 17 61",
    "sg:postcode":"8820",
    "sg:province":"Z\u00fcrich",
    "wof:name":"Silvia Bosshard Reitschule Gr\u00fcnfeld",
    "wof:placetype":"venue"
},
  "geometry": {"coordinates":[8.6735219955,47.2230873108],"type":"Point"}
}