{
  "type": "Feature",
  "properties": {
    "iso:country":"CH",
    "sg:address":"4115",
    "sg:city":"Mariastein",
    "sg:orig_category":"Verkehrs- and Tourismusb\u00fcros",
    "sg:phone":"+41 81 404 14 69",
    "sg:postcode":"4115",
    "sg:province":"Solothurn",
    "wof:name":"Kur-& Verkehrsverein",
    "wof:placetype":"venue"
},
  "geometry": {"coordinates":[9.7150802612,46.704498291],"type":"Point"}
}