{
  "type": "Feature",
  "properties": {
    "addr:full":"Schluhmattstrasse 59 Zermatt Valais 3920",
    "addr:housenumber":"59",
    "addr:postcode":"3920",
    "addr:street":"Schluhmattstrasse",
    "iso:country":"CH",
    "sg:address":"Schluhmattstrasse 59",
    "sg:city":"Zermatt",
    "sg:orig_category":"Betrieb von Taxis Detailhandel mit elektrischen Haushalts-,Radio U Fernsehger\u00e4ten sowie Musikinstrum",
    "sg:phone":"+41 27 722 36 10",
    "sg:postcode":"3920",
    "sg:province":"Valais",
    "wof:name":"A \u00ac Aa Piller Michel",
    "wof:placetype":"venue"
},
  "geometry": {"coordinates":[7.06447,46.090988],"type":"Point"}
}