{
  "type": "Feature",
  "properties": {
    "iso:country":"CH",
    "sg:address":"Hofstetterstrasse 7 6010 Kriens. Postfach",
    "sg:city":"Kriens",
    "sg:orig_category":"Instandhaltung U Reparatur von Automobilen",
    "sg:postcode":"6010",
    "sg:province":"Luzern",
    "wof:name":"Swisscars Boustany Iffat",
    "wof:placetype":"venue"
},
  "geometry": {"coordinates":[8.2935085297,47.0362014771],"type":"Point"}
}