{
  "type": "Feature",
  "properties": {
    "iso:country":"CH",
    "sg:address":"Rue Rainer Maria Rilke 4 3960 Sierre. Postfach",
    "sg:city":"Sierre",
    "sg:orig_category":"Arztpraxen",
    "sg:phone":"+41 27 455 16 45",
    "sg:postcode":"3960",
    "sg:province":"Valais",
    "wof:name":"Dr M\u00e9d. Martin Schneller M\u00e9decin Sp\u00e9cialiste Fmh",
    "wof:placetype":"venue"
},
  "geometry": {"coordinates":[7.531141,46.29303],"type":"Point"}
}