{
  "type": "Feature",
  "properties": {
    "iso:country":"CH",
    "sg:address":"Zeughausplatz 26",
    "sg:city":"Liestal",
    "sg:orig_category":"Zahntechnische Laboratorien",
    "sg:phone":"+41 61 923 29 80",
    "sg:postcode":"4410",
    "sg:province":"Basel-Landschaft",
    "wof:name":"Jean-pierre Berlanda Jpb Dental-keramik",
    "wof:placetype":"venue"
},
  "geometry": {"coordinates":[7.735314846,47.4849777222],"type":"Point"}
}