{
  "type": "Feature",
  "properties": {
    "iso:country":"CH",
    "sg:address":"Claridenstrasse 3",
    "sg:city":"Horgen",
    "sg:orig_category":"Interessenvertretungen",
    "sg:postcode":"8812",
    "sg:province":"Z\u00fcrich",
    "wof:name":"Spoerry Kaspar-stiftung",
    "wof:placetype":"venue"
},
  "geometry": {"coordinates":[8.5931472778,47.2550315857],"type":"Point"}
}