{
  "type": "Feature",
  "properties": {
    "addr:full":"Monbijoustrasse 69 Bern Bern 3007",
    "addr:housenumber":"69",
    "addr:postcode":"3007",
    "addr:street":"Monbijoustrasse",
    "iso:country":"CH",
    "sg:address":"Monbijoustrasse 69",
    "sg:city":"Bern",
    "sg:orig_category":"Detailhandel mit Brot, Back U S\u00fcsswaren",
    "sg:phone":"+41 31 371 41 82",
    "sg:postcode":"3007",
    "sg:province":"Bern",
    "wof:name":"Peter Egger B\u00e4ckerei-konditorei",
    "wof:placetype":"venue"
},
  "geometry": {"coordinates":[7.435957,46.940578],"type":"Point"}
}