{
  "type": "Feature",
  "properties": {
    "iso:country":"CH",
    "sg:address":"Industriestr. 9",
    "sg:city":"F\u00e4llanden",
    "sg:classifiers":[
        {
            "category":"Shopping",
            "subcategory":"Computers & Home Electronics",
            "type":"Retail Goods"
        }
    ],
    "sg:phone":"+41 4118062626",
    "sg:postcode":"8117",
    "sg:province":"Z\u00fcrich",
    "sg:tags":[
        "electronic",
        "electrical",
        "equipment"
    ],
    "wof:name":"Meiko Suisse Ag",
    "wof:placetype":"venue"
},
  "geometry": {"coordinates":[8.6421165466,47.3765182495],"type":"Point"}
}