{
  "type": "Feature",
  "properties": {
    "iso:country":"CH",
    "sg:address":"Dallenwilerstr. 20",
    "sg:city":"Stans-oberdorf",
    "sg:classifiers":[
        {
            "category":"Manufacturing",
            "subcategory":"Metals",
            "type":"Manufacturing & Wholesale Goods"
        }
    ],
    "sg:phone":"+41 41 618 61 61",
    "sg:postcode":"6370",
    "sg:province":"Nidwalden",
    "sg:tags":[
        "metallurgy",
        "steel",
        "metalworking"
    ],
    "wof:name":"Bwb-betschart Ag",
    "wof:placetype":"venue"
},
  "geometry": {"coordinates":[8.365904808,46.9572486877],"type":"Point"}
}