{
  "type": "Feature",
  "properties": {
    "iso:country":"CH",
    "sg:address":"Kirchstrasse 19",
    "sg:city":"Glarus",
    "sg:orig_category":"Grosshandel mit Textilien",
    "sg:postcode":"8750",
    "sg:province":"Glarus",
    "wof:name":"Bernet Trend-shop",
    "wof:placetype":"venue"
},
  "geometry": {"coordinates":[9.0671234131,47.0406799316],"type":"Point"}
}