{
  "type": "Feature",
  "properties": {
    "iso:country":"CH",
    "sg:address":"Hinterlohstrasse 5",
    "sg:city":"Alten",
    "sg:orig_category":"Aktivit\u00e4ten der Generalunternehmen im Baugewerbe Allgemeiner Hoch U Tiefbau",
    "sg:phone":"+41 52 317 36 21",
    "sg:postcode":"8453",
    "sg:province":"Z\u00fcrich",
    "wof:name":"Pamo Ag Frauenfeld",
    "wof:placetype":"venue"
},
  "geometry": {"coordinates":[8.644514,47.599117],"type":"Point"}
}