{
  "type": "Feature",
  "properties": {
    "iso:country":"CH",
    "sg:address":"Scheuermattweg 30",
    "sg:city":"R\u00fcnenberg",
    "sg:orig_category":"Sonstige Aktivit\u00e4ten der nicht-\u00e4rztlichen Medizinalberufe",
    "sg:phone":"+41 61 302 21 13",
    "sg:postcode":"4497",
    "sg:province":"Basel-Landschaft",
    "wof:name":"Ursula Bischoff Kinesiologie Fussreflexzonen",
    "wof:placetype":"venue"
},
  "geometry": {"coordinates":[7.8830361366,47.4360389709],"type":"Point"}
}