{
  "type": "Feature",
  "properties": {
    "iso:country":"CH",
    "sg:address":"Weidstrasse 25",
    "sg:city":"Meilen",
    "sg:orig_category":"Markt U Meinungsforschung",
    "sg:phone":"+41 19238024",
    "sg:postcode":"8706",
    "sg:province":"Z\u00fcrich",
    "wof:name":"Nelischer Peter Creative Consulting",
    "wof:placetype":"venue"
},
  "geometry": {"coordinates":[8.6691389084,47.267124176],"type":"Point"}
}