{
  "type": "Feature",
  "properties": {
    "iso:country":"CH",
    "sg:address":"Abl\u00e4schstrasse",
    "sg:city":"Glarus",
    "sg:orig_category":"Zimmerei, Ingenieurholzbau",
    "sg:phone":"+41 55 640 19 48",
    "sg:postcode":"8750",
    "sg:province":"Glarus",
    "wof:name":"Jakob & Martin Grob Holzbau",
    "wof:placetype":"venue"
},
  "geometry": {"coordinates":[9.0700874329,47.0367240906],"type":"Point"}
}