{
  "type": "Feature",
  "properties": {
    "iso:country":"CH",
    "sg:address":"Riehenring 171",
    "sg:city":"Basel",
    "sg:orig_category":"Tierarztpraxis",
    "sg:phone":"+41 56 442 55 42",
    "sg:postcode":"4058",
    "sg:province":"Basel-Stadt",
    "wof:name":"Dr. Med. Vet. Niklaus B\u00e4bler Tierarzt",
    "wof:placetype":"venue"
},
  "geometry": {"coordinates":[8.2065811157,47.4608383179],"type":"Point"}
}