{
  "type": "Feature",
  "properties": {
    "iso:country":"CH",
    "sg:address":"Veysonnaz",
    "sg:city":"Veysonnaz",
    "sg:classifiers":[
        {
            "category":"Banks & Credit Unions",
            "subcategory":"Bank",
            "type":"Services"
        }
    ],
    "sg:phone":"+41 27271730",
    "sg:postcode":"1993",
    "sg:province":"Valais",
    "wof:name":"Banque Raiffeisen De Veysonnaz",
    "wof:placetype":"venue"
},
  "geometry": {"coordinates":[7.338803,46.195984],"type":"Point"}
}