{
  "type": "Feature",
  "properties": {
    "iso:country":"CH",
    "sg:address":"Grand Rue 54",
    "sg:city":"Montreux",
    "sg:orig_category":"Kauf U Verkauf von Immobilien auf eigene Rechnung",
    "sg:phone":"+41 21 963 53 53",
    "sg:postcode":"1820",
    "sg:province":"Vaud",
    "wof:name":"Kramer Immobili\u00e8re Et Participations Sa",
    "wof:placetype":"venue"
},
  "geometry": {"coordinates":[6.9101939201,46.4344825745],"type":"Point"}
}