{
  "type": "Feature",
  "properties": {
    "iso:country":"CH",
    "sg:address":"Hofenstr. 22",
    "sg:city":"Wittenbach",
    "sg:classifiers":[
        {
            "category":"Transit Center",
            "subcategory":"Freight",
            "type":"Transportation"
        }
    ],
    "sg:phone":"+41 62 771 24 66",
    "sg:postcode":"9303",
    "sg:tags":[
        "metallurgy",
        "pipe",
        "metalworking",
        "sheet"
    ],
    "wof:name":"Merz & Cie Drahtwerk Ag",
    "wof:placetype":"venue"
},
  "geometry": {"coordinates":[8.171834,47.270107],"type":"Point"}
}