{
  "type": "Feature",
  "properties": {
    "iso:country":"CH",
    "sg:address":"Z\u00fcrcherstrasse 111",
    "sg:city":"Schlieren",
    "sg:orig_category":"Grosshandel mit elektrischen Haushaltsger\u00e4ten Herstellung von K\u00fcchenm\u00f6beln",
    "sg:phone":"+41 43 433 60 00",
    "sg:postcode":"8952",
    "sg:province":"Z\u00fcrich",
    "wof:name":"Haga Walter Ag",
    "wof:placetype":"venue"
},
  "geometry": {"coordinates":[8.4628248215,47.3972625732],"type":"Point"}
}