{
  "type": "Feature",
  "properties": {
    "iso:country":"CH",
    "sg:address":"1510 Moudon Case Postale 254",
    "sg:city":"Moudon",
    "sg:orig_category":"Verkehrs- and Tourismusb\u00fcros",
    "sg:phone":"+41 21 905 45 45",
    "sg:postcode":"1510",
    "sg:province":"Vaud",
    "wof:name":"St\u00e9 Pour Le D\u00e9veloppement De Moudon",
    "wof:placetype":"venue"
},
  "geometry": {"coordinates":[6.8003668785,46.6674957275],"type":"Point"}
}