{
  "type": "Feature",
  "properties": {
    "iso:country":"CH",
    "sg:address":"Richtstrasse 19 7000 Chur. Postfach",
    "sg:city":"Chur",
    "sg:orig_category":"Detailhandel mit Computern U Software Sonstige mit der Informatik verbundene T\u00e4tigkeiten",
    "sg:phone":"+41 81 253 10 10",
    "sg:postcode":"7000",
    "sg:province":"Graubunden",
    "wof:name":"Pc-help.ch Gmbh Pc, Zubeh\u00f6r; Beratung, Verkauf Usw",
    "wof:placetype":"venue"
},
  "geometry": {"coordinates":[9.511901,46.845852],"type":"Point"}
}