{
  "type": "Feature",
  "properties": {
    "iso:country":"CH",
    "sg:address":"Morgenstrasse 123",
    "sg:city":"Bern",
    "sg:orig_category":"Herstellung von Fenstern U T\u00fcren aus Holz",
    "sg:phone":"+41 31 991 76 66",
    "sg:postcode":"3018",
    "sg:province":"Bern",
    "wof:name":"Schreinerei Bichsel Ag Bern",
    "wof:placetype":"venue"
},
  "geometry": {"coordinates":[7.3902111053,46.9352378845],"type":"Point"}
}