{
  "type": "Feature",
  "properties": {
    "iso:country":"CH",
    "sg:address":"Breistrasse 14",
    "sg:city":"Ried-brig",
    "sg:orig_category":"Sanit\u00e4r U Heizungsinstallation",
    "sg:phone":"+41 79 219 50 07",
    "sg:postcode":"3911",
    "sg:province":"Valais",
    "wof:name":"Leo Eyer Heizungen",
    "wof:placetype":"venue"
},
  "geometry": {"coordinates":[8.0106401443,46.3103256226],"type":"Point"}
}