{
  "type": "Feature",
  "properties": {
    "iso:country":"CH",
    "sg:address":"7516 Maloja. Postfach",
    "sg:city":"Maloja",
    "sg:classifiers":[
        {
            "category":"Travel",
            "subcategory":"Hotels & Motels",
            "type":"Entertainment"
        }
    ],
    "sg:postcode":"7516",
    "sg:province":"Graubunden",
    "sg:tags":[
        "hotels",
        "mit",
        "restaurant"
    ],
    "wof:name":"A. O. Giovanoli & Co.",
    "wof:placetype":"venue"
},
  "geometry": {"coordinates":[9.6952791214,46.401008606],"type":"Point"}
}