{
  "type": "Feature",
  "properties": {
    "iso:country":"CH",
    "sg:address":"Schaffhauserstrasse 431",
    "sg:city":"Z\u00fcrich",
    "sg:orig_category":"Autospenglereien",
    "sg:phone":"+41 13012908",
    "sg:postcode":"8050",
    "sg:province":"Z\u00fcrich",
    "wof:name":"Max Gerteis Carrosserie",
    "wof:placetype":"venue"
},
  "geometry": {"coordinates":[8.544918,47.416176],"type":"Point"}
}