{
  "type": "Feature",
  "properties": {
    "iso:country":"CH",
    "sg:address":"Laveggio Via 2 6850 Mendrisio. Postfach",
    "sg:city":"Mendrisio",
    "sg:orig_category":"Kunststoff-Produkte",
    "sg:postcode":"6850",
    "sg:province":"Ticino",
    "wof:name":"Sonderegger Raymond D",
    "wof:placetype":"venue"
},
  "geometry": {"coordinates":[6.8163371086,47.0993690491],"type":"Point"}
}