{
  "type": "Feature",
  "properties": {
    "iso:country":"CH",
    "sg:address":"Thalwiesenstrasse 1",
    "sg:city":"Kloten",
    "sg:orig_category":"G\u00fcterbef\u00f6rderung im Strassenverkehr",
    "sg:postcode":"8302",
    "sg:province":"Z\u00fcrich",
    "wof:name":"Cargo Roller Ag",
    "wof:placetype":"venue"
},
  "geometry": {"coordinates":[8.5830488205,47.4572677612],"type":"Point"}
}