{
  "type": "Feature",
  "properties": {
    "iso:country":"CH",
    "sg:address":"8712 St\u00e4fa. Postfach 515",
    "sg:city":"St\u00e4fa",
    "sg:orig_category":"Sportvereine Turnen",
    "sg:postcode":"8712",
    "sg:province":"Z\u00fcrich",
    "wof:name":"M\u00e4nnerturnverein St\u00e4fa",
    "wof:placetype":"venue"
},
  "geometry": {"coordinates":[8.7229890823,47.2414932251],"type":"Point"}
}