{
  "type": "Feature",
  "properties": {
    "iso:country":"CH",
    "sg:address":"6945 Origlio. Postfach",
    "sg:city":"Origlio",
    "sg:orig_category":"Herstellung von Konstruktionsteilen, Fertigbauteilen U Ausbauelementen aus Holz",
    "sg:phone":"+41 21 922 17 22",
    "sg:postcode":"6945",
    "sg:province":"Ticino",
    "wof:name":"Michoud Eric",
    "wof:placetype":"venue"
},
  "geometry": {"coordinates":[6.8626499176,46.4653282166],"type":"Point"}
}