{
  "type": "Feature",
  "properties": {
    "iso:country":"CH",
    "sg:address":"Chalais Route De 14",
    "sg:city":"Chippis",
    "sg:orig_category":"Unclassifiable Establishments",
    "sg:postcode":"3965",
    "sg:province":"Valais",
    "wof:name":"Alain Zufferey",
    "wof:placetype":"venue"
},
  "geometry": {"coordinates":[7.5415549278,46.2804908752],"type":"Point"}
}