{
  "type": "Feature",
  "properties": {
    "iso:country":"CH",
    "sg:address":"Hotel Honegg",
    "sg:city":"Ennetb\u00fcrgen",
    "sg:orig_category":"Kauf U Verkauf von Immobilien auf eigene Rechnung",
    "sg:postcode":"6373",
    "sg:province":"Nidwalden",
    "wof:name":"Honegg-mattgrat Ag",
    "wof:placetype":"venue"
},
  "geometry": {"coordinates":[8.4051599503,46.9951133728],"type":"Point"}
}