{
  "type": "Feature",
  "properties": {
    "iso:country":"CH",
    "sg:address":"Lohwisstrasse 21 8123 Ebmatingen. Postfach 210",
    "sg:city":"Ebmatingen",
    "sg:orig_category":"Softwareentwicklung U beratung",
    "sg:postcode":"8123",
    "sg:province":"Z\u00fcrich",
    "wof:name":"Pylon-soft Klaus Philipp",
    "wof:placetype":"venue"
},
  "geometry": {"coordinates":[9.0439462662,47.4655647278],"type":"Point"}
}