{
  "type": "Feature",
  "properties": {
    "iso:country":"CH",
    "sg:address":"Freiburgstrasse 102 3008 Bern. Postfach",
    "sg:city":"Bern",
    "sg:orig_category":"Instandhaltung U Reparatur von Automobilen",
    "sg:phone":"+41 31 381 62 42",
    "sg:postcode":"3005",
    "sg:province":"Bern",
    "wof:name":"Ren\u00e9 Ellenberger Autogarage; Autos U. Zubeh\u00f6r; Handel.",
    "wof:placetype":"venue"
},
  "geometry": {"coordinates":[7.4119057655,46.9450836182],"type":"Point"}
}