{
  "type": "Feature",
  "properties": {
    "iso:country":"CH",
    "sg:address":"Leuholz 4",
    "sg:city":"Wangen",
    "sg:orig_category":"Industrie, Elektronik U Elektrik",
    "sg:phone":"+41 55 440 30 40",
    "sg:postcode":"8855",
    "sg:province":"Schwyz",
    "wof:name":"Transmas Ag",
    "wof:placetype":"venue"
},
  "geometry": {"coordinates":[8.880573,47.193508],"type":"Point"}
}