{
  "type": "Feature",
  "properties": {
    "iso:country":"CH",
    "sg:address":"Harderstrasse 14 3800 Interlaken. Postfach 17",
    "sg:city":"Interlaken",
    "sg:orig_category":"Eisenbahnverkehr Elektrizit\u00e4tsversorgung",
    "sg:phone":"+41 33 828 71 11",
    "sg:postcode":"3800",
    "sg:province":"Bern",
    "wof:name":"Berner Oberland-bahnen Ag",
    "wof:placetype":"venue"
},
  "geometry": {"coordinates":[7.8555231094,46.6864204407],"type":"Point"}
}