{
  "type": "Feature",
  "properties": {
    "iso:country":"CH",
    "sg:address":"Allmendg\u00fctlistrasse 35",
    "sg:city":"Horgen",
    "sg:orig_category":"Allgemeiner Hoch U Tiefbau",
    "sg:postcode":"8810",
    "sg:province":"Z\u00fcrich",
    "wof:name":"A. Fend Bauleitungsb\u00fcro",
    "wof:placetype":"venue"
},
  "geometry": {"coordinates":[8.608606,47.253117],"type":"Point"}
}