{
  "type": "Feature",
  "properties": {
    "iso:country":"CH",
    "sg:address":"4426",
    "sg:city":"Lauwil",
    "sg:orig_category":"Primarschulen",
    "sg:phone":"+41 61 941 11 67",
    "sg:postcode":"4426",
    "sg:province":"Basel-Landschaft",
    "wof:name":"Primarschule",
    "wof:placetype":"venue"
},
  "geometry": {"coordinates":[7.6640000343,47.3875694275],"type":"Point"}
}