{
  "type": "Feature",
  "properties": {
    "iso:country":"CH",
    "sg:address":"Rotackerstrasse 34",
    "sg:city":"Wallisellen",
    "sg:orig_category":"Detailhandel mit Getr\u00e4nken",
    "sg:phone":"+41 18307747",
    "sg:postcode":"8304",
    "sg:province":"Z\u00fcrich",
    "wof:name":"Rio-getr\u00e4nkemarkt Ag",
    "wof:placetype":"venue"
},
  "geometry": {"coordinates":[8.5926065445,47.4142608643],"type":"Point"}
}