{
  "type": "Feature",
  "properties": {
    "iso:country":"CH",
    "sg:address":"Dogana Vecchia Via 2",
    "sg:city":"Lugano",
    "sg:orig_category":"Unclassifiable Establishments",
    "sg:phone":"+41 91 922 70 91",
    "sg:postcode":"6900",
    "sg:province":"Ticino",
    "wof:name":"Gemanco Sa",
    "wof:placetype":"venue"
},
  "geometry": {"coordinates":[8.9501628876,46.0027656555],"type":"Point"}
}