{
  "type": "Feature",
  "properties": {
    "iso:country":"CH",
    "sg:address":"Braschlergasse 10.",
    "sg:city":"Uster",
    "sg:orig_category":"Pensionskassen",
    "sg:phone":"+41 19404352",
    "sg:postcode":"8610",
    "sg:province":"Z\u00fcrich",
    "wof:name":"Personalf\u00fcrsorgestiftung Der Firma Wunderli & Co Ag",
    "wof:placetype":"venue"
},
  "geometry": {"coordinates":[8.72012043,47.3487205505],"type":"Point"}
}