{
  "type": "Feature",
  "properties": {
    "iso:country":"CH",
    "sg:address":"Schwarzseestrasse 18",
    "sg:city":"Tafers",
    "sg:orig_category":"Kauf U Verkauf von Immobilien auf eigene Rechnung",
    "sg:postcode":"1712",
    "sg:province":"Fribourg",
    "wof:name":"Genossenschaft Vorderes Zigerli",
    "wof:placetype":"venue"
},
  "geometry": {"coordinates":[7.2157940865,46.8126335144],"type":"Point"}
}