{
  "type": "Feature",
  "properties": {
    "addr:full":"Route Du Bry 37 Farvagny Fribourg 1726",
    "addr:housenumber":"37",
    "addr:postcode":"1726",
    "addr:street":"Route Du Bry",
    "iso:country":"CH",
    "sg:address":"Route Du Bry 37",
    "sg:city":"Farvagny",
    "sg:orig_category":"Allgemeiner Hoch U Tiefbau Mechanische Werkst\u00e4tten",
    "sg:postcode":"1726",
    "sg:province":"Fribourg",
    "wof:name":"Roubaty S. Sa",
    "wof:placetype":"venue"
},
  "geometry": {"coordinates":[7.070828,46.718792],"type":"Point"}
}