{
  "type": "Feature",
  "properties": {
    "iso:country":"CH",
    "sg:address":"Via Giovan Battist Pioda 9",
    "sg:city":"Lugano",
    "sg:orig_category":"Herstellung von Papier, Karton U Pappe",
    "sg:postcode":"6900",
    "sg:province":"Ticino",
    "wof:name":"Sportkart Sa",
    "wof:placetype":"venue"
},
  "geometry": {"coordinates":[8.9539260864,46.007183075],"type":"Point"}
}