{
  "type": "Feature",
  "properties": {
    "iso:country":"CH",
    "sg:address":"Standstrasse 42 3014 Bern. Postfach",
    "sg:city":"Bern",
    "sg:orig_category":"Grosshandel mit festen Brennstoffen U Mineral\u00f6lerzeugnissen",
    "sg:phone":"+41 12144111",
    "sg:postcode":"3005",
    "sg:province":"Bern",
    "wof:name":"Esso-self-service Wyler T. & Reinhard H.",
    "wof:placetype":"venue"
},
  "geometry": {"coordinates":[7.4524540901,46.9627494812],"type":"Point"}
}