{
  "type": "Feature",
  "properties": {
    "iso:country":"CH",
    "sg:address":"Avenue Mon-repos 24",
    "sg:city":"Lausanne",
    "sg:orig_category":"Arztpraxen",
    "sg:phone":"+41 21 320 05 09",
    "sg:postcode":"1005",
    "sg:province":"Vaud",
    "wof:name":"Dr M\u00e9d. Isabelle Poulenas M\u00e9decin Sp\u00e9cialiste Fmh",
    "wof:placetype":"venue"
},
  "geometry": {"coordinates":[6.641474,46.518482],"type":"Point"}
}