{
  "type": "Feature",
  "properties": {
    "iso:country":"CH",
    "sg:address":"Pont Route Du Petit 1",
    "sg:city":"Conthey",
    "sg:orig_category":"Herstellung von Mess U Kontrollinstrumenten U vorrichtungen",
    "sg:postcode":"1964",
    "sg:province":"Valais",
    "wof:name":"Atelier First S\u00e0rl",
    "wof:placetype":"venue"
},
  "geometry": {"coordinates":[7.2982797623,46.224319458],"type":"Point"}
}