{
  "type": "Feature",
  "properties": {
    "iso:country":"CH",
    "sg:address":"Rue Du Wasen 32 2500 Biel/bienne. Postfach",
    "sg:city":"Biel/bienne",
    "sg:orig_category":"Wirtschaftspr\u00fcfung, Steuerberatung U Treuhand",
    "sg:phone":"+41 21 653 10 11",
    "sg:postcode":"2502",
    "sg:province":"Bern",
    "wof:name":"Fiduciaire Holzmann + Partenaires Sa",
    "wof:placetype":"venue"
},
  "geometry": {"coordinates":[6.6516609192,46.5266799927],"type":"Point"}
}