{
  "type": "Feature",
  "properties": {
    "iso:country":"CH",
    "sg:address":"Zum Ried.",
    "sg:city":"Tamins",
    "sg:orig_category":"Grosshandel mit Holz U Baustoffen",
    "sg:postcode":"7015",
    "sg:province":"Graubunden",
    "wof:name":"Moraschinelli D.",
    "wof:placetype":"venue"
},
  "geometry": {"coordinates":[9.4067792892,46.8335876465],"type":"Point"}
}