{
  "type": "Feature",
  "properties": {
    "iso:country":"CH",
    "sg:address":"Schluhenweg 4",
    "sg:city":"Rothrist",
    "sg:orig_category":"Maler U Glasergewerbe Malerei",
    "sg:phone":"+41 62 794 23 23",
    "sg:postcode":"4852",
    "sg:province":"Aargau",
    "wof:name":"Gyger Malergesch\u00e4ft",
    "wof:placetype":"venue"
},
  "geometry": {"coordinates":[7.8873639107,47.3031616211],"type":"Point"}
}