{
  "type": "Feature",
  "properties": {
    "iso:country":"CH",
    "sg:address":"Sonnenwiesstrasse 6",
    "sg:city":"Goldingen",
    "sg:orig_category":"Maler U Glasergewerbe Malerei",
    "sg:phone":"+41 55 284 13 72",
    "sg:postcode":"8638",
    "sg:province":"St. Gallen",
    "wof:name":"K. & A. G\u00fcbeli Malergesch\u00e4ft",
    "wof:placetype":"venue"
},
  "geometry": {"coordinates":[8.983590126,47.2870483398],"type":"Point"}
}