{
  "type": "Feature",
  "properties": {
    "iso:country":"CH",
    "sg:address":"T\u00e4chmatt 110",
    "sg:city":"Rechthalten",
    "sg:orig_category":"Grosshandel mit lebenden Tieren",
    "sg:phone":"+41 71 455 11 75",
    "sg:postcode":"1718",
    "sg:province":"Fribourg",
    "wof:name":"Bischof Paul",
    "wof:placetype":"venue"
},
  "geometry": {"coordinates":[9.396900177,47.5114784241],"type":"Point"}
}