{
  "type": "Feature",
  "properties": {
    "iso:country":"CH",
    "sg:address":"Zentralstrasse 80",
    "sg:city":"Neuhausen",
    "sg:orig_category":"Sanit\u00e4r, Heizungs U L\u00fcftungsinstallation Sanit\u00e4rinstallation",
    "sg:phone":"+41 71 367 14 34",
    "sg:postcode":"8212",
    "sg:province":"Schaffhausen",
    "wof:name":"Wisag San.installationen & Heizungen",
    "wof:placetype":"venue"
},
  "geometry": {"coordinates":[9.3377304077,47.3631210327],"type":"Point"}
}