{
  "type": "Feature",
  "properties": {
    "iso:country":"CH",
    "sg:address":"M\u00fcsliweg 6",
    "sg:city":"Unterstammheim",
    "sg:orig_category":"Vorschulen, Kinderg\u00e4rten",
    "sg:phone":"+41 62 893 36 61",
    "sg:postcode":"8476",
    "sg:province":"Z\u00fcrich",
    "wof:name":"Kindergarten I & Ii",
    "wof:placetype":"venue"
},
  "geometry": {"coordinates":[8.1786203384,47.4184684753],"type":"Point"}
}