{
  "type": "Feature",
  "properties": {
    "iso:country":"CH",
    "sg:address":"1908",
    "sg:city":"Riddes",
    "sg:orig_category":"Elektrizit\u00e4tsversorgung",
    "sg:phone":"+41 27 306 31 17",
    "sg:postcode":"1908",
    "sg:province":"Valais",
    "wof:name":"Grande Dixence Sa Usine \u00e9lectr.au Bord Du Rh\u00f4ne",
    "wof:placetype":"venue"
},
  "geometry": {"coordinates":[7.2213292122,46.1717376709],"type":"Point"}
}