{
  "type": "Feature",
  "properties": {
    "iso:country":"CH",
    "sg:address":"Erlacker",
    "sg:city":"Wittenbach",
    "sg:orig_category":"RESTAURANTS: TEA-ROOMS",
    "sg:phone":"+41 71 298 35 53",
    "sg:postcode":"9303",
    "wof:name":"Restaurant Zum Erlacker",
    "wof:placetype":"venue"
},
  "geometry": {"coordinates":[9.373052597,47.4547042847],"type":"Point"}
}