{
  "type": "Feature",
  "properties": {
    "iso:country":"CH",
    "sg:address":"L\u00f6wenstrasse 14",
    "sg:city":"Z\u00fcrich",
    "sg:orig_category":"Vermietung U Verpachtung von eigenen Immobilien",
    "sg:phone":"+41 12120700",
    "sg:postcode":"8001",
    "sg:province":"Z\u00fcrich",
    "wof:name":"Bellerive-immobilien Ag",
    "wof:placetype":"venue"
},
  "geometry": {"coordinates":[8.5352210999,47.373626709],"type":"Point"}
}