{
  "type": "Feature",
  "properties": {
    "iso:country":"CH",
    "sg:address":"Holzmattweg 24",
    "sg:city":"Merzligen",
    "sg:classifiers":[
        {
            "category":"Insurance",
            "subcategory":"Insurance Agent",
            "type":"Services"
        }
    ],
    "sg:phone":"+41 32 652 41 49",
    "sg:postcode":"3274",
    "sg:province":"Bern",
    "sg:tags":[
        "versicherungsagenturen",
        "-broker"
    ],
    "wof:name":"Die Mobiliar Versicherungen & Vorsorge",
    "wof:placetype":"venue"
},
  "geometry": {"coordinates":[7.3694162369,47.1859741211],"type":"Point"}
}