{
  "type": "Feature",
  "properties": {
    "iso:country":"CH",
    "sg:address":"Rauracherweg 5",
    "sg:city":"Balsthal",
    "sg:orig_category":"Allgemeiner Hoch U Tiefbau Elektroinstallation",
    "sg:phone":"+41 62 391 40 36",
    "sg:postcode":"4710",
    "sg:province":"Solothurn",
    "wof:name":"Meier Elektromontagen Analog- U. Isdn-telefoninstallationen Usw.",
    "wof:placetype":"venue"
},
  "geometry": {"coordinates":[7.706351,47.320198],"type":"Point"}
}