{
  "type": "Feature",
  "properties": {
    "iso:country":"CH",
    "sg:address":"Avenue De Montchoisi 1",
    "sg:city":"Lausanne",
    "sg:orig_category":"G\u00fcterbef\u00f6rderung im Strassenverkehr",
    "sg:phone":"+41 21 784 11 46",
    "sg:postcode":"1006",
    "sg:province":"Vaud",
    "wof:name":"Pierre Rapaz Transports",
    "wof:placetype":"venue"
},
  "geometry": {"coordinates":[6.6969637871,46.5585212708],"type":"Point"}
}