{
  "type": "Feature",
  "properties": {
    "iso:country":"CH",
    "sg:address":"Aescherstrasse 4",
    "sg:city":"Arni-islisberg",
    "sg:orig_category":"Sportvereine Ballsport Fussball",
    "sg:phone":"+41 56 634 22 07",
    "sg:postcode":"8905",
    "sg:province":"Aargau",
    "wof:name":"Fc Senioren Bremgarten",
    "wof:placetype":"venue"
},
  "geometry": {"coordinates":[8.4219064713,47.3194618225],"type":"Point"}
}