{
  "type": "Feature",
  "properties": {
    "iso:country":"CH",
    "sg:address":"Grundstrasse 37",
    "sg:city":"Winterthur",
    "sg:orig_category":"P\u00e9dicure",
    "sg:phone":"+41 52 232 47 39",
    "sg:postcode":"8405",
    "sg:province":"Z\u00fcrich",
    "wof:name":"Ursula Savary P\u00e9dicure",
    "wof:placetype":"venue"
},
  "geometry": {"coordinates":[8.7648563385,47.4898071289],"type":"Point"}
}