{
  "type": "Feature",
  "properties": {
    "iso:country":"CH",
    "sg:address":"Rue Saint-maurice 21 2852 Court\u00e9telle. Postfach",
    "sg:city":"Court\u00e9telle",
    "sg:orig_category":"Herstellung von Radio U Fernsehger\u00e4ten sowie phono U videotechnischen Ger\u00e4ten",
    "sg:postcode":"2852",
    "sg:province":"Jura",
    "wof:name":"Mc Duny's S\u00e0rl",
    "wof:placetype":"venue"
},
  "geometry": {"coordinates":[7.3172440529,47.345790863],"type":"Point"}
}