{
  "type": "Feature",
  "properties": {
    "iso:country":"CH",
    "sg:address":"Kronenstrasse 7",
    "sg:city":"Rorschach",
    "sg:orig_category":"RESTAURANTS: TEA-ROOMS",
    "sg:phone":"+41 71 841 82 82",
    "sg:postcode":"9400",
    "sg:province":"St. Gallen",
    "wof:name":"G. Herrera Rest Pizzeria Via Veneto",
    "wof:placetype":"venue"
},
  "geometry": {"coordinates":[9.4905042648,47.4785842896],"type":"Point"}
}