{
  "type": "Feature",
  "properties": {
    "iso:country":"CH",
    "sg:address":"8610 Uster. Postfach 310",
    "sg:city":"Uster",
    "sg:orig_category":"Sportvereine Eissport Eishockey",
    "sg:postcode":"8610",
    "sg:province":"Z\u00fcrich",
    "wof:name":"Eishockey-club Uster",
    "wof:placetype":"venue"
},
  "geometry": {"coordinates":[8.719909668,47.3492889404],"type":"Point"}
}