{
  "type": "Feature",
  "properties": {
    "iso:country":"CH",
    "sg:address":"Mittelgasse 4",
    "sg:city":"Frenkendorf",
    "sg:orig_category":"Detailhandel mit elektrischen Haushalts-,Radio U Fernsehger\u00e4ten sowie Musikinstrumenten Elektroinsta",
    "sg:phone":"+41 61 901 18 80",
    "sg:postcode":"4402",
    "sg:province":"Basel-Landschaft",
    "wof:name":"Siegenthaler Radio, Tv Video",
    "wof:placetype":"venue"
},
  "geometry": {"coordinates":[7.7140097618,47.5032997131],"type":"Point"}
}