{
  "type": "Feature",
  "properties": {
    "iso:country":"CH",
    "sg:address":"G\u00e9n\u00e9ral-guisan Avenue 4",
    "sg:city":"Pully",
    "sg:orig_category":"RESTAURANTS: TEA-ROOMS",
    "sg:postcode":"1009",
    "sg:province":"Vaud",
    "wof:name":"Renaud D.",
    "wof:placetype":"venue"
},
  "geometry": {"coordinates":[6.6561689377,46.5066375732],"type":"Point"}
}