{
  "type": "Feature",
  "properties": {
    "iso:country":"CH",
    "sg:address":"Lemggstrasse 26a",
    "sg:city":"Z\u00fcrich",
    "sg:orig_category":"Datenbanken",
    "sg:postcode":"8008",
    "sg:province":"Z\u00fcrich",
    "wof:name":"Sputnik Media Saladin Glauninger Helen",
    "wof:placetype":"venue"
},
  "geometry": {"coordinates":[8.783497,47.717258],"type":"Point"}
}