{
  "type": "Feature",
  "properties": {
    "iso:country":"CH",
    "sg:address":"Oberhelfenschwilerstrasse 6",
    "sg:city":"Dietfurt",
    "sg:orig_category":"Unclassifiable Establishments",
    "sg:postcode":"9615",
    "sg:province":"St. Gallen",
    "wof:name":"Kl\u00e4ger Roland Ag",
    "wof:placetype":"venue"
},
  "geometry": {"coordinates":[9.0802211761,47.3459281921],"type":"Point"}
}