{
  "type": "Feature",
  "properties": {
    "iso:country":"CH",
    "sg:address":"Kraftstrass 37",
    "sg:city":"Z\u00fcrich",
    "sg:orig_category":"Korrespondenz U Nachrichtenb\u00fcros",
    "sg:phone":"+41 22 300 14 20",
    "sg:postcode":"8044",
    "sg:province":"Z\u00fcrich",
    "wof:name":"Ag F\u00fcr Wirtschafts- Publikationen Awp",
    "wof:placetype":"venue"
},
  "geometry": {"coordinates":[6.1324448586,46.2052726746],"type":"Point"}
}