{
  "type": "Feature",
  "properties": {
    "iso:country":"CH",
    "sg:address":"Mattenhofstrasse 15",
    "sg:city":"Bern",
    "sg:orig_category":"Physiotherapie",
    "sg:phone":"+41 31 382 54 00",
    "sg:postcode":"3007",
    "sg:province":"Bern",
    "wof:name":"K\u00f6rpertherapie Praxis-gemeinschaft",
    "wof:placetype":"venue"
},
  "geometry": {"coordinates":[7.4307131767,46.9430046082],"type":"Point"}
}