{
  "type": "Feature",
  "properties": {
    "iso:country":"CH",
    "sg:address":"Riehenring 107 4058 Basel. Postfach",
    "sg:city":"Basel",
    "sg:orig_category":"K\u00fcnstlerische Schulen",
    "sg:phone":"+41 61 692 52 64",
    "sg:postcode":"4021",
    "wof:name":"Musikschule Matschu",
    "wof:placetype":"venue"
},
  "geometry": {"coordinates":[7.5976519585,47.5659103394],"type":"Point"}
}