{
  "type": "Feature",
  "properties": {
    "iso:country":"CH",
    "sg:address":"Konstanzer Strasse 46",
    "sg:city":"Kreuzlingen",
    "sg:orig_category":"Weiterbildungskurse and Seminar Anbieter",
    "sg:postcode":"8280",
    "sg:province":"Thurgau",
    "wof:name":"Gamt Gmbh,ges.f.die Ausbild. In Manueller Therapie",
    "wof:placetype":"venue"
},
  "geometry": {"coordinates":[8.8286447525,47.2318496704],"type":"Point"}
}