{
  "type": "Feature",
  "properties": {
    "iso:country":"CH",
    "sg:address":"Dorfstrasse 31 3472 Wynigen. Postfach",
    "sg:city":"Wynigen",
    "sg:orig_category":"Herstellung von Reiseartikeln, Leder U Sattlerwaren",
    "sg:phone":"+41 62 212 94 32",
    "sg:postcode":"3472",
    "sg:province":"Bern",
    "wof:name":"Fritz & Co Inh.l.kissling Lederwarenfabrik",
    "wof:placetype":"venue"
},
  "geometry": {"coordinates":[7.8756418228,47.3435020447],"type":"Point"}
}