{
  "type": "Feature",
  "properties": {
    "iso:country":"CH",
    "sg:address":"Dorfstrasse 11 8103 Unterengstringen. Postfach 36",
    "sg:city":"Unterengstringen",
    "sg:orig_category":"Architektur U Ingenieurb\u00fcros",
    "sg:phone":"+41 17504144",
    "sg:postcode":"8103",
    "sg:province":"Z\u00fcrich",
    "wof:name":"Howy Ag",
    "wof:placetype":"venue"
},
  "geometry": {"coordinates":[8.447202,47.410995],"type":"Point"}
}