{
  "type": "Feature",
  "properties": {
    "iso:country":"CH",
    "sg:address":"Passage Sant-fran\u00e7ois 4",
    "sg:city":"Gen\u00e8ve",
    "sg:orig_category":"Reiseb\u00fcros U Reiseveranstalter",
    "sg:phone":"+41 21 792 10 18",
    "sg:postcode":"1205",
    "sg:province":"Gen\u00e8ve",
    "wof:name":"Romtour Voyages, Dessaux C.",
    "wof:placetype":"venue"
},
  "geometry": {"coordinates":[6.6792011261,46.514175415],"type":"Point"}
}