{
  "type": "Feature",
  "properties": {
    "iso:country":"CH",
    "sg:address":"Aeulestrasse 22",
    "sg:city":"Vaduz",
    "sg:classifiers":[
        {
            "category":"Restaurant",
            "type":"Food & Drink"
        }
    ],
    "sg:phone":"+423 232 10 65",
    "sg:postcode":"9490",
    "wof:name":"The Old Castle Inn",
    "wof:placetype":"venue"
},
  "geometry": {"coordinates":[9.5213184357,47.1398506165],"type":"Point"}
}