{
  "type": "Feature",
  "properties": {
    "iso:country":"CH",
    "sg:address":"Rothenbadstrasse 2",
    "sg:city":"Reussb\u00fchl",
    "sg:orig_category":"Detailhandel mit B\u00fcromaschinen U einrichtungen Detailhandel mit Computern U Software",
    "sg:phone":"+41 41 269 38 50",
    "sg:postcode":"6015",
    "sg:province":"Luzern",
    "wof:name":"Office World Ag",
    "wof:placetype":"venue"
},
  "geometry": {"coordinates":[8.27817,47.067871],"type":"Point"}
}