{
  "type": "Feature",
  "properties": {
    "iso:country":"CH",
    "sg:address":"Hittnauerstrasse 7",
    "sg:city":"Saland",
    "sg:classifiers":[
        {
            "category":"Restaurant",
            "type":"Food & Drink"
        }
    ],
    "sg:phone":"+41 52 386 18 98",
    "sg:postcode":"8493",
    "sg:province":"Z\u00fcrich",
    "wof:name":"Restaurant & Caf\u00e9 Chelleland",
    "wof:placetype":"venue"
},
  "geometry": {"coordinates":[8.8528985977,47.390537262],"type":"Point"}
}