{
  "type": "Feature",
  "properties": {
    "iso:country":"CH",
    "sg:address":"Waldetenstrasse 17",
    "sg:city":"Rotkreuz",
    "sg:orig_category":"Softwareentwicklung U beratung",
    "sg:phone":"+41 41 790 19 18",
    "sg:postcode":"6343",
    "sg:province":"Zug",
    "wof:name":"Villiger Informatik",
    "wof:placetype":"venue"
},
  "geometry": {"coordinates":[8.4292078018,47.1384239197],"type":"Point"}
}