{
  "type": "Feature",
  "properties": {
    "iso:country":"CH",
    "sg:address":"Kirchb\u00fchlstrasse 10",
    "sg:city":"St\u00e4fa",
    "sg:orig_category":"Architektur U Ingenieurb\u00fcros",
    "sg:postcode":"8712",
    "sg:province":"Z\u00fcrich",
    "wof:name":"Pfiffner K.r., Engineering",
    "wof:placetype":"venue"
},
  "geometry": {"coordinates":[8.576979,47.33115],"type":"Point"}
}