{
  "type": "Feature",
  "properties": {
    "iso:country":"CH",
    "sg:address":"Alpenstrasse 5",
    "sg:city":"Switzerland",
    "sg:classifiers":[
        {
            "category":"Industrial Area",
            "type":"Public Place"
        }
    ],
    "sg:phone":"+41 61 325 30 67",
    "sg:postcode":"6",
    "sg:tags":[
        "large",
        "private"
    ],
    "wof:name":"Farnair Europe Group",
    "wof:placetype":"venue"
},
  "geometry": {"coordinates":[7.5805301666,47.5596618652],"type":"Point"}
}