{
  "type": "Feature",
  "properties": {
    "iso:country":"CH",
    "sg:address":"Route De La Conversion 115",
    "sg:city":"Ch\u00e2telard-lutry",
    "sg:orig_category":"Herstellung von Metallkonstruktionen",
    "sg:phone":"+41 21 791 10 95",
    "sg:postcode":"1095",
    "sg:province":"Vaud",
    "wof:name":"Bridy Chamorel Bolomey Sa Constructions M\u00e9talliques.",
    "wof:placetype":"venue"
},
  "geometry": {"coordinates":[6.6830887794,46.5076217651],"type":"Point"}
}