{
  "type": "Feature",
  "properties": {
    "iso:country":"CH",
    "sg:address":"Buckhauserstrasse 30",
    "sg:city":"Z\u00fcrich",
    "sg:orig_category":"Non-Classified Establishments",
    "sg:postcode":"8048",
    "sg:province":"Z\u00fcrich",
    "wof:name":"Asdim Gmbh",
    "wof:placetype":"venue"
},
  "geometry": {"coordinates":[8.4924058914,47.384059906],"type":"Point"}
}