{
  "type": "Feature",
  "properties": {
    "iso:country":"CH",
    "sg:address":"Z\u00fcrichstrasse 27a 8134 Adliswil. Postfach",
    "sg:city":"Adliswil",
    "sg:classifiers":[
        {
            "category":"Professional",
            "subcategory":"Employment Agencies",
            "type":"Services"
        }
    ],
    "sg:postcode":"8134",
    "sg:province":"Z\u00fcrich",
    "sg:tags":[
        "personal",
        "u",
        "stellenvermittlung"
    ],
    "wof:name":"Thoma & Partner Management Consulting Ag",
    "wof:placetype":"venue"
},
  "geometry": {"coordinates":[8.5283851624,47.3141365051],"type":"Point"}
}