{
  "type": "Feature",
  "properties": {
    "iso:country":"CH",
    "sg:address":"Himmelrichstrasse 3",
    "sg:city":"Horn",
    "sg:orig_category":"Fahrschulen, Flugschulen",
    "sg:phone":"+41 79 218 19 01",
    "sg:postcode":"9326",
    "sg:province":"Thurgau",
    "wof:name":"Ernst Wirth Autofahrschule",
    "wof:placetype":"venue"
},
  "geometry": {"coordinates":[9.4621829987,47.4913291931],"type":"Point"}
}