{
  "type": "Feature",
  "properties": {
    "iso:country":"CH",
    "sg:address":"2887",
    "sg:city":"Soubey",
    "sg:orig_category":"RESTAURANTS: TEA-ROOMS",
    "sg:phone":"+41 32 955 12 44",
    "sg:postcode":"2887",
    "sg:province":"Jura",
    "wof:name":"Boillat-mahon Elianne",
    "wof:placetype":"venue"
},
  "geometry": {"coordinates":[7.0485048294,47.3080940247],"type":"Point"}
}