{
  "type": "Feature",
  "properties": {
    "iso:country":"CH",
    "sg:address":"Hechtstrasse 3",
    "sg:city":"Oberrieden",
    "sg:orig_category":"Vorschulen, Kinderg\u00e4rten",
    "sg:phone":"+41 17209960",
    "sg:postcode":"8942",
    "sg:province":"Z\u00fcrich",
    "wof:name":"Kindergarten Im Boden",
    "wof:placetype":"venue"
},
  "geometry": {"coordinates":[8.5793619156,47.2801742554],"type":"Point"}
}