{
  "type": "Feature",
  "properties": {
    "iso:country":"CH",
    "sg:address":"1524",
    "sg:city":"Marnand",
    "sg:orig_category":"Grosshandel mit landwirtschaftlichen Maschinen U Ger\u00e4ten Herstellung von sonstigen landwirtschaftlic",
    "sg:phone":"+41 26 668 21 25",
    "sg:postcode":"1524",
    "sg:province":"Vaud",
    "wof:name":"Yves Th\u00e9voz Machines Agricoles",
    "wof:placetype":"venue"
},
  "geometry": {"coordinates":[6.9024100304,46.762840271],"type":"Point"}
}