{
  "type": "Feature",
  "properties": {
    "iso:country":"CH",
    "sg:address":"Rue Du Pont 19",
    "sg:city":"Montreux",
    "sg:orig_category":"Herstellung von sonstigen Nahrungsmitteln",
    "sg:postcode":"1820",
    "sg:province":"Vaud",
    "wof:name":"Sauces Artisanales, Robatel Yves",
    "wof:placetype":"venue"
},
  "geometry": {"coordinates":[6.9164857864,46.4337844849],"type":"Point"}
}