{
  "type": "Feature",
  "properties": {
    "iso:country":"CH",
    "sg:address":"Gutenbergstrasse 25",
    "sg:city":"Bern",
    "sg:orig_category":"Sonstige mit der Informatik verbundene T\u00e4tigkeiten",
    "sg:phone":"+41 71 222 80 44",
    "sg:postcode":"3011",
    "sg:province":"Bern",
    "wof:name":"Netcast Ag",
    "wof:placetype":"venue"
},
  "geometry": {"coordinates":[7.4350700378,46.944152832],"type":"Point"}
}