{
  "type": "Feature",
  "properties": {
    "iso:country":"CH",
    "sg:address":"Wampflenstrasse 55",
    "sg:city":"Meilen",
    "sg:orig_category":"Unternehmensberatung",
    "sg:postcode":"8706",
    "sg:province":"Z\u00fcrich",
    "wof:name":"Wegier Unternehmensberatung",
    "wof:placetype":"venue"
},
  "geometry": {"coordinates":[8.6427726746,47.2747077942],"type":"Point"}
}