{
  "type": "Feature",
  "properties": {
    "iso:country":"CH",
    "sg:address":"B\u00fcelisackerstrasse 1",
    "sg:city":"Waltenschwil",
    "sg:orig_category":"Darlehenskassen U Raiffeisenbanken",
    "sg:phone":"+41 81 921 56 56",
    "sg:postcode":"5622",
    "sg:province":"Aargau",
    "wof:name":"Raiffeisenbank",
    "wof:placetype":"venue"
},
  "geometry": {"coordinates":[9.26783,46.815769],"type":"Point"}
}