{
  "type": "Feature",
  "properties": {
    "iso:country":"CH",
    "sg:address":"Route De La Batie 40",
    "sg:city":"Versoix",
    "sg:orig_category":"RESTAURANTS: TEA-ROOMS",
    "sg:phone":"+41 22 755 30 98",
    "sg:postcode":"1290",
    "sg:province":"Gen\u00e8ve",
    "wof:name":"Rendez-vous Des Chasseurs Restaurant Le",
    "wof:placetype":"venue"
},
  "geometry": {"coordinates":[6.1306729317,46.2843971252],"type":"Point"}
}