{
  "type": "Feature",
  "properties": {
    "iso:country":"CH",
    "sg:address":"Artherstrasse 101 6405 Immensee. Postfach 9",
    "sg:city":"Immensee",
    "sg:classifiers":[
        {
            "category":"Travel",
            "subcategory":"Hotels & Motels",
            "type":"Entertainment"
        }
    ],
    "sg:phone":"+41 61 961 03 46",
    "sg:postcode":"6405",
    "sg:province":"Schwyz",
    "sg:tags":[
        "hotels",
        "mit",
        "restaurant"
    ],
    "wof:name":"Hotel Eidgenossen",
    "wof:placetype":"venue"
},
  "geometry": {"coordinates":[7.7487311363,47.3928031921],"type":"Point"}
}