{
  "type": "Feature",
  "properties": {
    "iso:country":"CH",
    "sg:address":"Marktstrasse",
    "sg:city":"Sarnen",
    "sg:orig_category":"Vorschulen, Kinderg\u00e4rten",
    "sg:phone":"+41 41 660 49 77",
    "sg:postcode":"6060",
    "sg:province":"Obwalden",
    "wof:name":"Kindergarten Marktplatz",
    "wof:placetype":"venue"
},
  "geometry": {"coordinates":[8.2486381531,46.896484375],"type":"Point"}
}