{
  "type": "Feature",
  "properties": {
    "iso:country":"CH",
    "sg:address":"Ziegelfeldstrasse 112",
    "sg:city":"Olten",
    "sg:orig_category":"Vereine Heimatschutz",
    "sg:postcode":"4600",
    "sg:province":"Solothurn",
    "wof:name":"Schweizer Heimatschutz Sekt.so",
    "wof:placetype":"venue"
},
  "geometry": {"coordinates":[7.8935871124,47.3513526917],"type":"Point"}
}