{
  "type": "Feature",
  "properties": {
    "iso:country":"CH",
    "sg:address":"Bei Hans Niederhauser",
    "sg:city":"Boltigen",
    "sg:orig_category":"Campingpl\u00e4tze Detailhandel mit Zeitungen U Zeitschriften Kioske",
    "sg:phone":"+41 79 222 74 04",
    "sg:postcode":"3766",
    "sg:province":"Bern",
    "wof:name":"Camping Jaunpass Ag",
    "wof:placetype":"venue"
},
  "geometry": {"coordinates":[7.390518,46.628971],"type":"Point"}
}