{
  "type": "Feature",
  "properties": {
    "iso:country":"CH",
    "sg:address":"H\u00e4gelerstrasse 7",
    "sg:city":"Trimbach",
    "sg:orig_category":"Architektur U Ingenieurb\u00fcros",
    "sg:phone":"+41 62 293 52 32",
    "sg:postcode":"4632",
    "sg:province":"Solothurn",
    "wof:name":"Rapp Ag",
    "wof:placetype":"venue"
},
  "geometry": {"coordinates":[7.903685,47.364746],"type":"Point"}
}