{
  "type": "Feature",
  "properties": {
    "iso:country":"CH",
    "sg:address":"Grenadiers Chemin Des 1",
    "sg:city":"Fribourg",
    "sg:classifiers":[
        {
            "category":"Travel",
            "subcategory":"Hotels & Motels",
            "type":"Entertainment"
        }
    ],
    "sg:phone":"+41 26 322 81 27",
    "sg:postcode":"1702",
    "sg:province":"Fribourg",
    "sg:tags":[
        "hotels",
        "mit",
        "restaurant"
    ],
    "wof:name":"Valentino G. S\u00e0rl",
    "wof:placetype":"venue"
},
  "geometry": {"coordinates":[7.1536831856,46.8037452698],"type":"Point"}
}