{
  "type": "Feature",
  "properties": {
    "iso:country":"CH",
    "sg:address":"Tunnelstr. 20",
    "sg:city":"Brig",
    "sg:orig_category":"RESTAURANTS: TEA-ROOMS",
    "sg:phone":"+41 27 924 40 24",
    "sg:postcode":"3900",
    "sg:province":"Valais",
    "wof:name":"Restaurant Bellevue, Heldner Jakob",
    "wof:placetype":"venue"
},
  "geometry": {"coordinates":[7.9912858009,46.3162345886],"type":"Point"}
}