{
  "type": "Feature",
  "properties": {
    "iso:country":"CH",
    "sg:address":"3826",
    "sg:city":"Gimmelwald",
    "sg:classifiers":[
        {
            "category":"Travel",
            "subcategory":"Hotels & Motels",
            "type":"Entertainment"
        }
    ],
    "sg:phone":"+41 33 855 16 58",
    "sg:postcode":"3826",
    "sg:province":"Bern",
    "sg:tags":[
        "hotels",
        "mit",
        "restaurant"
    ],
    "wof:name":"Hotel Mittaghorn",
    "wof:placetype":"venue"
},
  "geometry": {"coordinates":[7.8921198845,46.5465888977],"type":"Point"}
}