{
  "type": "Feature",
  "properties": {
    "iso:country":"CH",
    "sg:address":"Spielhofweg 6",
    "sg:city":"Selzach",
    "sg:orig_category":"Detailhandel mit Milcherzeugnissen U Eiern Verarbeitung von Milch",
    "sg:phone":"+41 32 641 15 85",
    "sg:postcode":"2545",
    "sg:province":"Solothurn",
    "wof:name":"Hanspeter Kunz K\u00e4serei",
    "wof:placetype":"venue"
},
  "geometry": {"coordinates":[7.453813076,47.2068405151],"type":"Point"}
}