{
  "type": "Feature",
  "properties": {
    "iso:country":"CH",
    "sg:address":"Passage De La Matze 6",
    "sg:city":"Sion",
    "sg:orig_category":"Sonstige mit der Informatik verbundene T\u00e4tigkeiten",
    "sg:phone":"+41 27 323 66 07",
    "sg:postcode":"1950",
    "sg:province":"Valais",
    "wof:name":"Dalla Barba Antonio",
    "wof:placetype":"venue"
},
  "geometry": {"coordinates":[7.3544411659,46.2307510376],"type":"Point"}
}