{
  "type": "Feature",
  "properties": {
    "iso:country":"CH",
    "sg:address":"Hammerweg 24 8404 Oberwinterthur. Postfach",
    "sg:city":"Winterthur",
    "sg:orig_category":"Kauf U Verkauf von Immobilien auf eigene Rechnung",
    "sg:phone":"+41 52 242 47 18",
    "sg:postcode":"8404",
    "sg:province":"Z\u00fcrich",
    "wof:name":"Brack Walter Liegenschaften Ag",
    "wof:placetype":"venue"
},
  "geometry": {"coordinates":[8.7475671768,47.5053215027],"type":"Point"}
}