{
  "type": "Feature",
  "properties": {
    "iso:country":"CH",
    "sg:address":"6515",
    "sg:city":"Gudo",
    "sg:orig_category":"Gem\u00fcsebau Obstbau",
    "sg:phone":"+41 91 858 12 20",
    "sg:postcode":"6515",
    "sg:province":"Ticino",
    "wof:name":"Cooperativa Al Frutteto Orticoltura Biologica",
    "wof:placetype":"venue"
},
  "geometry": {"coordinates":[8.9507379532,46.1750106812],"type":"Point"}
}