{
  "type": "Feature",
  "properties": {
    "iso:country":"CH",
    "sg:address":"Alte Landstrasse 398",
    "sg:city":"M\u00e4nnedorf",
    "sg:orig_category":"Reinigungsgewerbe",
    "sg:phone":"+41 52 385 14 15",
    "sg:postcode":"8708",
    "sg:province":"Z\u00fcrich",
    "wof:name":"Fahrni Gebr. Reinigungen Gmbh",
    "wof:placetype":"venue"
},
  "geometry": {"coordinates":[8.7062168121,47.2474594116],"type":"Point"}
}