{
  "type": "Feature",
  "properties": {
    "iso:country":"CH",
    "sg:address":"Sennweidstrasse 16",
    "sg:city":"Bubikon",
    "sg:orig_category":"Vereine Frauen Vereine Gemeinn\u00fctzige",
    "sg:phone":"+41 55 243 33 02",
    "sg:postcode":"8608",
    "sg:province":"Z\u00fcrich",
    "wof:name":"Gemeinn\u00fctziger Frauenverein",
    "wof:placetype":"venue"
},
  "geometry": {"coordinates":[8.8244743347,47.2734184265],"type":"Point"}
}