{
  "type": "Feature",
  "properties": {
    "iso:country":"CH",
    "sg:address":"Via Schlifras 78",
    "sg:city":"Ilanz",
    "sg:orig_category":"Verlegen von Fliesen U Platten",
    "sg:phone":"+41 81 925 33 80",
    "sg:postcode":"7130",
    "sg:province":"Graubunden",
    "wof:name":"Walter Liechti Bodenbel\u00e4ge",
    "wof:placetype":"venue"
},
  "geometry": {"coordinates":[9.2054185867,46.7684402466],"type":"Point"}
}