{
  "type": "Feature",
  "properties": {
    "iso:country":"CH",
    "sg:address":"6873",
    "sg:city":"Corteglia",
    "sg:orig_category":"D\u00e4mmung gegen K\u00e4lte, W\u00e4rme, Schall U Ersch\u00fctterung",
    "sg:phone":"+41 91 646 77 07",
    "sg:postcode":"6873",
    "sg:province":"Ticino",
    "wof:name":"Coibentazioni Sa",
    "wof:placetype":"venue"
},
  "geometry": {"coordinates":[8.9946899414,45.8618392944],"type":"Point"}
}