{
  "type": "Feature",
  "properties": {
    "addr:full":"Rothenb\u00fchlstrasse 3 5605 Dottikon. Postfach 129 Dottikon Aargau 5605",
    "addr:housenumber":"3;129",
    "addr:postcode":"5605 dottikon.;5605",
    "addr:street":"Rothenbuehlstrasse;Postfach",
    "iso:country":"CH",
    "sg:address":"Rothenb\u00fchlstrasse 3 5605 Dottikon. Postfach 129",
    "sg:city":"Dottikon",
    "sg:orig_category":"Allgemeiner Hoch U Tiefbau",
    "sg:phone":"+41 56 618 70 48",
    "sg:postcode":"5605",
    "sg:province":"Aargau",
    "wof:name":"Meier & Hollenweger Ag",
    "wof:placetype":"venue"
},
  "geometry": {"coordinates":[8.237766,47.386402],"type":"Point"}
}