{
  "type": "Feature",
  "properties": {
    "iso:country":"CH",
    "sg:address":"Waldheimstrasse 17",
    "sg:city":"Thun",
    "sg:orig_category":"Verlag von bespielten Tontr\u00e4gern",
    "sg:phone":"+41 33 335 35 30",
    "sg:postcode":"3604",
    "sg:province":"Bern",
    "wof:name":"B.a.rock Enterprise Musikagentur",
    "wof:placetype":"venue"
},
  "geometry": {"coordinates":[7.6239190102,46.7442245483],"type":"Point"}
}