{
  "type": "Feature",
  "properties": {
    "iso:country":"CH",
    "sg:address":"GetYourGuide AG Technoparkstr. 1",
    "sg:city":"Zurich",
    "sg:classifiers":[
        {
            "category":"Professional",
            "subcategory":"Computer Services",
            "type":"Services"
        }
    ],
    "sg:postcode":"8005",
    "sg:tags":[
        "online-travel",
        "web-2-0",
        "tour-guide",
        "travel",
        "travelers",
        "tours",
        "marketplace",
        "eth-zurich"
    ],
    "sg:website":"http://www.getyourguide.com",
    "wof:name":"GetYourGuide",
    "wof:placetype":"venue"
},
  "geometry": {"coordinates":[8.5082891,47.3912899],"type":"Point"}
}