{
  "type": "Feature",
  "properties": {
    "iso:country":"CH",
    "sg:address":"Rte De La Croix-blanche 28. 1000 Lausanne. Postfach",
    "sg:city":"Epalinges",
    "sg:orig_category":"RESTAURANTS: TEA-ROOMS",
    "sg:postcode":"1066",
    "sg:province":"Vaud",
    "wof:name":"Costantini Leopoldo.",
    "wof:placetype":"venue"
},
  "geometry": {"coordinates":[6.6947751045,46.5545883179],"type":"Point"}
}