{
  "type": "Feature",
  "properties": {
    "iso:country":"CH",
    "sg:address":"Tannacker 113",
    "sg:city":"Aetingen",
    "sg:orig_category":"Politische Parteien FDP",
    "sg:phone":"+41 17610121",
    "sg:postcode":"4587",
    "sg:province":"Solothurn",
    "wof:name":"Fdp Ortspartei Affoltern A/a",
    "wof:placetype":"venue"
},
  "geometry": {"coordinates":[8.4499397278,47.2750091553],"type":"Point"}
}