{
  "type": "Feature",
  "properties": {
    "iso:country":"CH",
    "sg:address":"H\u00f6schgasse 49 8008 Z\u00fcrich. Postfach",
    "sg:city":"Z\u00fcrich",
    "sg:orig_category":"Herstellung von sonstigen Maschinen f\u00fcr unspezifische Verwendung",
    "sg:postcode":"8001",
    "sg:province":"Z\u00fcrich",
    "wof:name":"Hasmo Hasler Service & Montage Verpackungsmaschinen; Service. Div. Baugruppen; Montage. Reparaturen",
    "wof:placetype":"venue"
},
  "geometry": {"coordinates":[8.5535793304,47.3576126099],"type":"Point"}
}