{
  "type": "Feature",
  "properties": {
    "iso:country":"CH",
    "sg:address":"Hulfteggstrasse 32",
    "sg:city":"G\u00e4hwil",
    "sg:orig_category":"Allgemeiner Hochbau Bauschreinerei",
    "sg:phone":"+41 71 931 30 58",
    "sg:postcode":"9534",
    "sg:province":"St. Gallen",
    "wof:name":"Karl L\u00fcthi Schreinerei & Fassadenbau",
    "wof:placetype":"venue"
},
  "geometry": {"coordinates":[8.998398,47.395329],"type":"Point"}
}