{
  "type": "Feature",
  "properties": {
    "iso:country":"CH",
    "sg:address":"Seestrasse 13",
    "sg:city":"Steinach",
    "sg:orig_category":"Forstwirtschaft ohne Dienstleistungen in der Forstwirtschaft",
    "sg:phone":"+41 71 446 07 70",
    "sg:postcode":"9323",
    "sg:province":"St. Gallen",
    "wof:name":"Forst Service Cts-gmbh",
    "wof:placetype":"venue"
},
  "geometry": {"coordinates":[9.4421634674,47.5047531128],"type":"Point"}
}