{
  "type": "Feature",
  "properties": {
    "iso:country":"CH",
    "sg:address":"Kirchrain 20",
    "sg:city":"Hellb\u00fchl",
    "sg:classifiers":[
        {
            "category":"Home & Garden",
            "subcategory":"Furniture",
            "type":"Retail Goods"
        }
    ],
    "sg:phone":"+41 27 721 61 81",
    "sg:postcode":"6016",
    "sg:province":"Luzern",
    "sg:tags":[
        "household",
        "wood"
    ],
    "wof:name":"Daniel Fournier",
    "wof:placetype":"venue"
},
  "geometry": {"coordinates":[7.0851612091,46.1083335876],"type":"Point"}
}