{
  "type": "Feature",
  "properties": {
    "iso:country":"CH",
    "sg:address":"Cur\u00e9-desclouds Chemin Du 11 1226 Th\u00f4nex. Postfach",
    "sg:city":"Th\u00f4nex",
    "sg:orig_category":"Herstellung von Armaturen",
    "sg:phone":"+41 33 334 59 59",
    "sg:postcode":"1226",
    "sg:province":"Gen\u00e8ve",
    "wof:name":"Sanitas Troesch Ag",
    "wof:placetype":"venue"
},
  "geometry": {"coordinates":[7.6175150871,46.7317848206],"type":"Point"}
}