{
  "type": "Feature",
  "properties": {
    "iso:country":"CH",
    "sg:address":"B\u00fcelstrasse 7",
    "sg:city":"Siebnen",
    "sg:orig_category":"Elektroinstallation",
    "sg:phone":"+41 55 440 20 64",
    "sg:postcode":"8854",
    "sg:province":"Schwyz",
    "wof:name":"Wattelec Ag",
    "wof:placetype":"venue"
},
  "geometry": {"coordinates":[8.8949260712,47.1745223999],"type":"Point"}
}