{
  "type": "Feature",
  "properties": {
    "iso:country":"CH",
    "sg:address":"Aeussere Baselstrasse 155",
    "sg:city":"Riehen",
    "sg:orig_category":"Kosmetikinstitute",
    "sg:phone":"+41 18445737",
    "sg:postcode":"4125",
    "sg:province":"Basel-Stadt",
    "wof:name":"Maya Hotz Kosmetikinstitut La Fontaine",
    "wof:placetype":"venue"
},
  "geometry": {"coordinates":[8.4108524323,47.444984436],"type":"Point"}
}