{
  "type": "Feature",
  "properties": {
    "iso:country":"CH",
    "sg:address":"Feldh\u00f6fli 38",
    "sg:city":"Obernau",
    "sg:orig_category":"Malerei Reinigungsgewerbe",
    "sg:phone":"+41 79 434 30 03",
    "sg:postcode":"6012",
    "sg:province":"Luzern",
    "wof:name":"Roth Hubert Ag",
    "wof:placetype":"venue"
},
  "geometry": {"coordinates":[8.2512798309,47.0304031372],"type":"Point"}
}