{
  "type": "Feature",
  "properties": {
    "iso:country":"CH",
    "sg:address":"Bergstrasse 1 8157 Dielsdorf. Postfach 215",
    "sg:city":"Dielsdorf",
    "sg:orig_category":"Allgemeiner Gartenbau",
    "sg:phone":"+41 18531210",
    "sg:postcode":"8157",
    "sg:province":"Z\u00fcrich",
    "wof:name":"Hug J., Baumschulen",
    "wof:placetype":"venue"
},
  "geometry": {"coordinates":[8.449817,47.481445],"type":"Point"}
}