{
  "type": "Feature",
  "properties": {
    "iso:country":"CH",
    "sg:address":"Stelzenweg",
    "sg:city":"Azmoos",
    "sg:orig_category":"Unternehmensberatung",
    "sg:postcode":"9478",
    "sg:province":"St. Gallen",
    "wof:name":"Strobl F. O. Consulting",
    "wof:placetype":"venue"
},
  "geometry": {"coordinates":[9.4792299271,47.0810546875],"type":"Point"}
}