{
  "type": "Feature",
  "properties": {
    "iso:country":"CH",
    "sg:address":"Alte Zurzacherstr. 257.",
    "sg:city":"Tegerfelden",
    "sg:orig_category":"Instandhaltung U Reparatur von Automobilen",
    "sg:postcode":"5306",
    "sg:province":"Aargau",
    "wof:name":"Karosseriewerkstatt Hauenstein",
    "wof:placetype":"venue"
},
  "geometry": {"coordinates":[8.2868204117,47.5659103394],"type":"Point"}
}