{
  "type": "Feature",
  "properties": {
    "iso:country":"CH",
    "sg:address":"Place De La Gare 2 1950 Sion Case Postale 819",
    "sg:city":"Sion",
    "sg:classifiers":[
        {
            "category":"Restaurant",
            "type":"Food & Drink"
        }
    ],
    "sg:phone":"+41 27 323 73 60",
    "sg:postcode":"1951",
    "sg:province":"Valais",
    "wof:name":"Restaurant Pizza Hut",
    "wof:placetype":"venue"
},
  "geometry": {"coordinates":[7.3592648506,46.2277488708],"type":"Point"}
}