{
  "type": "Feature",
  "properties": {
    "addr:full":"Geerenstrasse 44 8604 Volketswil. Postfach Volketswil Z\u00fcrich 8604",
    "addr:housenumber":"44",
    "addr:postcode":"8604;8604",
    "addr:street":"Geerenstrasse;Postfach",
    "iso:country":"CH",
    "sg:address":"Geerenstrasse 44 8604 Volketswil. Postfach",
    "sg:city":"Volketswil",
    "sg:orig_category":"Architektur U Ingenieurb\u00fcros",
    "sg:phone":"+41 19462651",
    "sg:postcode":"8604",
    "sg:province":"Z\u00fcrich",
    "wof:name":"Engeler Martin Baumanagement Architektur, Bauleitungen, Generalunternehmung",
    "wof:placetype":"venue"
},
  "geometry": {"coordinates":[8.686223,47.408508],"type":"Point"}
}