{
  "type": "Feature",
  "properties": {
    "iso:country":"CH",
    "sg:address":"Im Obmann",
    "sg:city":"Thalheim",
    "sg:orig_category":"Mechanische Werkst\u00e4tten",
    "sg:phone":"+41 52 336 10 29",
    "sg:postcode":"8478",
    "sg:province":"Z\u00fcrich",
    "wof:name":"Heinz Herzog Mechanische Werkstatt",
    "wof:placetype":"venue"
},
  "geometry": {"coordinates":[8.7580795288,47.5706443787],"type":"Point"}
}