{
  "type": "Feature",
  "properties": {
    "iso:country":"CH",
    "sg:address":"Altgasse 66",
    "sg:city":"Baar",
    "sg:orig_category":"Instandhaltung U Reparatur von Automobilen",
    "sg:phone":"+41 41 761 77 44",
    "sg:postcode":"6340",
    "sg:province":"Zug",
    "wof:name":"Garage Altgasse, Strickler P.",
    "wof:placetype":"venue"
},
  "geometry": {"coordinates":[8.5155363083,47.1917953491],"type":"Point"}
}