{
  "type": "Feature",
  "properties": {
    "iso:country":"CH",
    "sg:address":"Kantonsstrasse 14 8807 Freienbach. Postfach",
    "sg:city":"Freienbach",
    "sg:orig_category":"Herstellung von Metallerzeugnissen ohne Maschinenbau Herstellung von k\u00e4lte U lufttechnischen Erzeugn",
    "sg:phone":"+41 17733915",
    "sg:postcode":"8807",
    "sg:province":"Schwyz",
    "wof:name":"B\u00f6sch Walter Ag",
    "wof:placetype":"venue"
},
  "geometry": {"coordinates":[8.7455348969,47.2056274414],"type":"Point"}
}