{
  "type": "Feature",
  "properties": {
    "iso:country":"CH",
    "sg:address":"Anton Graff-strasse 44 8400 Winterthur. Postfach 1147",
    "sg:city":"Winterthur",
    "sg:orig_category":"Detailhandel mit elektrischen Haushalts-,Radio U Fernsehger\u00e4ten sowie Musikinstrumenten",
    "sg:phone":"+41 52 202 33 23",
    "sg:postcode":"8401",
    "sg:province":"Z\u00fcrich",
    "wof:name":"Brenner Sounds & Recording Bsr",
    "wof:placetype":"venue"
},
  "geometry": {"coordinates":[8.7135276794,47.4980125427],"type":"Point"}
}