{
  "type": "Feature",
  "properties": {
    "iso:country":"CH",
    "sg:address":"Parkstrasse 16",
    "sg:city":"Sch\u00f6nenwerd",
    "sg:orig_category":"Sample Books",
    "sg:phone":"+41 62 849 96 00",
    "sg:postcode":"5012",
    "sg:province":"Solothurn",
    "wof:name":"Samplex Ag",
    "wof:placetype":"venue"
},
  "geometry": {"coordinates":[7.9979748726,47.3702011108],"type":"Point"}
}