{
  "type": "Feature",
  "properties": {
    "iso:country":"CH",
    "sg:address":"Petit Moniack",
    "sg:city":"Val-d'illiez",
    "sg:orig_category":"Finanzierungsinstitutionen",
    "sg:phone":"+41 24 477 38 70",
    "sg:postcode":"1873",
    "sg:province":"Valais",
    "wof:name":"Alastair Fraser",
    "wof:placetype":"venue"
},
  "geometry": {"coordinates":[-69.44165802000001,11.0685396194],"type":"Point"}
}