{
  "type": "Feature",
  "properties": {
    "iso:country":"CH",
    "sg:address":"En Florettaz",
    "sg:city":"Ch\u00e9serex",
    "sg:orig_category":"Hobel U Holzimpr\u00e4gnierwerke Zimmerei, Dachdeckerei, Bauspenglerei U Abdichtung",
    "sg:phone":"+41 24 436 21 21",
    "sg:postcode":"1275",
    "sg:province":"Vaud",
    "wof:name":"Michon Jacky",
    "wof:placetype":"venue"
},
  "geometry": {"coordinates":[6.6878399849,46.8391799927],"type":"Point"}
}