{
  "type": "Feature",
  "properties": {
    "iso:country":"CH",
    "sg:address":"Banackerweg 385",
    "sg:city":"Neuendorf",
    "sg:orig_category":"Kauf U Verkauf von Immobilien auf eigene Rechnung",
    "sg:phone":"+41 62 398 33 22",
    "sg:postcode":"4623",
    "sg:province":"Solothurn",
    "wof:name":"Smg Sales Ag",
    "wof:placetype":"venue"
},
  "geometry": {"coordinates":[7.7961659431,47.2961463928],"type":"Point"}
}