{
  "type": "Feature",
  "properties": {
    "iso:country":"CH",
    "sg:address":"Sch\u00fctzengasse 21",
    "sg:city":"Z\u00fcrich",
    "sg:orig_category":"Reiseb\u00fcros U Reiseveranstalter",
    "sg:phone":"+41 41 630 34 16",
    "sg:postcode":"8001",
    "sg:province":"Z\u00fcrich",
    "wof:name":"Port-air Ag Reiseb\u00fcro",
    "wof:placetype":"venue"
},
  "geometry": {"coordinates":[8.3119106293,46.9863204956],"type":"Point"}
}