{
  "type": "Feature",
  "properties": {
    "iso:country":"CH",
    "sg:address":"Industriestrasse 20",
    "sg:city":"Aarwangen",
    "sg:orig_category":"Detailhandel mit M\u00f6beln U Haushaltsgegenst\u00e4nden",
    "sg:phone":"+41 61 713 97 97",
    "sg:postcode":"4912",
    "sg:province":"Bern",
    "wof:name":"Nostrac Ag No Stress Accomodation",
    "wof:placetype":"venue"
},
  "geometry": {"coordinates":[7.5757670403,47.4941444397],"type":"Point"}
}