{
  "type": "Feature",
  "properties": {
    "iso:country":"CH",
    "sg:address":"St. Gallerstrasse 2",
    "sg:city":"Flawil",
    "sg:classifiers":[
        {
            "category":"Travel",
            "subcategory":"Hotels & Motels",
            "type":"Entertainment"
        }
    ],
    "sg:postcode":"9230",
    "sg:province":"St. Gallen",
    "sg:tags":[
        "hotels",
        "mit",
        "restaurant"
    ],
    "wof:name":"B\u00fcrki Gastro Ag",
    "wof:placetype":"venue"
},
  "geometry": {"coordinates":[9.1871452332,47.4132270813],"type":"Point"}
}