{
  "type": "Feature",
  "properties": {
    "iso:country":"CH",
    "sg:address":"La Riettaz",
    "sg:city":"Lussy-sur-morges",
    "sg:orig_category":"Softwareentwicklung U beratung",
    "sg:phone":"+41 31 302 80 60",
    "sg:postcode":"1133",
    "wof:name":"Pk Informatik, K\u00fcnzi Peter",
    "wof:placetype":"venue"
},
  "geometry": {"coordinates":[7.4268770218,46.9754943848],"type":"Point"}
}