{
  "type": "Feature",
  "properties": {
    "iso:country":"CH",
    "sg:address":"Ch\u00e4ferweg 2a",
    "sg:city":"Sursee",
    "sg:orig_category":"Vereine Musik/Blasmusik",
    "sg:postcode":"6210",
    "sg:province":"Luzern",
    "wof:name":"Musikverein Schenkon",
    "wof:placetype":"venue"
},
  "geometry": {"coordinates":[8.1066570282,47.1650695801],"type":"Point"}
}