{
  "type": "Feature",
  "properties": {
    "iso:country":"CH",
    "sg:address":"Waldegg 6",
    "sg:city":"Zumikon",
    "sg:orig_category":"Rechtsberatung",
    "sg:postcode":"8126",
    "sg:province":"Z\u00fcrich",
    "wof:name":"Visual Security Ag",
    "wof:placetype":"venue"
},
  "geometry": {"coordinates":[8.6127758026,47.3357048035],"type":"Point"}
}