{
  "type": "Feature",
  "properties": {
    "iso:country":"CH",
    "sg:address":"Steinackerstrasse 8",
    "sg:city":"Sulgen",
    "sg:orig_category":"Artists' Books",
    "sg:phone":"+41 71 644 91 11",
    "sg:postcode":"8583",
    "sg:province":"Thurgau",
    "wof:name":"Verlag Niggli Ag",
    "wof:placetype":"venue"
},
  "geometry": {"coordinates":[9.185453,47.535915],"type":"Point"}
}