{
  "type": "Feature",
  "properties": {
    "addr:full":"Imm. Bouquet Courtepin Fribourg 1784",
    "addr:postcode":"1784",
    "iso:country":"CH",
    "sg:address":"Imm. Bouquet",
    "sg:city":"Courtepin",
    "sg:classifiers":[
        {
            "category":"Banks & Credit Unions",
            "subcategory":"Bank",
            "type":"Services"
        }
    ],
    "sg:phone":"+41 37341677",
    "sg:postcode":"1784",
    "sg:province":"Fribourg",
    "wof:name":"Banque De L'etat De Fribourg",
    "wof:placetype":"venue"
},
  "geometry": {"coordinates":[7.12405,46.8647],"type":"Point"}
}