{
  "type": "Feature",
  "properties": {
    "iso:country":"CH",
    "sg:address":"Avenue De La Plage 73",
    "sg:city":"Pr\u00e9verenges",
    "sg:orig_category":"Herstellung von Metallkonstruktionen",
    "sg:phone":"+41 21 801 16 67",
    "sg:postcode":"1028",
    "sg:province":"Vaud",
    "wof:name":"Br\u00fcgger Gaston.",
    "wof:placetype":"venue"
},
  "geometry": {"coordinates":[6.5377130508,46.5078086853],"type":"Point"}
}