{
  "type": "Feature",
  "properties": {
    "iso:country":"CH",
    "sg:address":"Sierenzerstrasse 76",
    "sg:city":"Basel",
    "sg:orig_category":"Erschliessung von Grundst\u00fccken",
    "sg:postcode":"4055",
    "sg:province":"Basel-Stadt",
    "wof:name":"Wohngenossenschaft B\u00fcndnerstrasse",
    "wof:placetype":"venue"
},
  "geometry": {"coordinates":[7.5679130554,47.5582695007],"type":"Point"}
}