{
  "type": "Feature",
  "properties": {
    "iso:country":"CH",
    "sg:address":"Via Dei Casagrande 27",
    "sg:city":"Breganzona",
    "sg:orig_category":"D\u00e4mmung gegen K\u00e4lte, W\u00e4rme, Schall U Ersch\u00fctterung Reinigungsgewerbe",
    "sg:phone":"+41 91 923 77 81",
    "sg:postcode":"6932",
    "sg:province":"Ticino",
    "wof:name":"Impreso Pulizia Di Weber Walter Pulicasa",
    "wof:placetype":"venue"
},
  "geometry": {"coordinates":[8.9281997681,46.0114021301],"type":"Point"}
}