{
  "type": "Feature",
  "properties": {
    "iso:country":"CH",
    "sg:address":"Kaufhausgasse 7",
    "sg:city":"Basel",
    "sg:orig_category":"Pensionskassen",
    "sg:phone":"+41 61 205 21 00",
    "sg:postcode":"4051",
    "sg:province":"Basel-Stadt",
    "wof:name":"Bvg-stiftung Der E. Gutzwiller & Cie. Banquiers",
    "wof:placetype":"venue"
},
  "geometry": {"coordinates":[7.590526104,47.5548744202],"type":"Point"}
}