{
  "type": "Feature",
  "properties": {
    "iso:country":"CH",
    "sg:address":"Kapfstrasse 29",
    "sg:city":"Emmenbr\u00fccke",
    "sg:orig_category":"Reparatur von Schuhen U Lederwaren",
    "sg:phone":"+41 41 280 50 91",
    "sg:postcode":"6020",
    "sg:province":"Luzern",
    "wof:name":"Adolf Bucheli Schuhmacherei",
    "wof:placetype":"venue"
},
  "geometry": {"coordinates":[8.2757949829,47.091053009],"type":"Point"}
}