{
  "type": "Feature",
  "properties": {
    "iso:country":"CH",
    "sg:address":"3208",
    "sg:city":"Gurbr\u00fc",
    "sg:orig_category":"Autogaragen",
    "sg:phone":"+41 32 392 19 82",
    "sg:postcode":"3208",
    "sg:province":"Bern",
    "wof:name":"Hans H\u00fcgli Autoreparaturen",
    "wof:placetype":"venue"
},
  "geometry": {"coordinates":[7.320185,47.048817],"type":"Point"}
}