{
  "type": "Feature",
  "properties": {
    "iso:country":"CH",
    "sg:address":"Maragn\u00e8ne",
    "sg:city":"Sion",
    "sg:orig_category":"Rebbau",
    "sg:phone":"+41 27 203 11 07",
    "sg:postcode":"1950",
    "sg:province":"Valais",
    "wof:name":"Benjamin Favre Propri\u00e9taire-encaveur",
    "wof:placetype":"venue"
},
  "geometry": {"coordinates":[7.3923549652,46.2251091003],"type":"Point"}
}