{
  "type": "Feature",
  "properties": {
    "iso:country":"CH",
    "sg:address":"Ruggh\u00f6lzi 2/ Busslingen",
    "sg:city":"Remetschwil",
    "sg:classifiers":[
        {
            "category":"Manufacturing",
            "subcategory":"Paper Products",
            "type":"Manufacturing & Wholesale Goods"
        }
    ],
    "sg:phone":"+41 56 485 60 60",
    "sg:postcode":"5453",
    "sg:province":"Aargau",
    "sg:tags":[
        "raw",
        "material",
        "-",
        "cardboard"
    ],
    "wof:name":"Cartonal Ag",
    "wof:placetype":"venue"
},
  "geometry": {"coordinates":[8.3271303177,47.4077911377],"type":"Point"}
}