{
  "type": "Feature",
  "properties": {
    "addr:full":"Rebackost\u00fa 5 D\u00fcbendorf Z\u00fcrich 8600",
    "addr:housenumber":"5",
    "addr:postcode":"8600",
    "addr:street":"Rebackostu\u0301;Zuerich",
    "iso:country":"CH",
    "sg:address":"Rebackost\u00fa 5",
    "sg:city":"D\u00fcbendorf",
    "sg:orig_category":"Architektur U Ingenieurb\u00fcros",
    "sg:phone":"+41 21 944 35 36",
    "sg:postcode":"8600",
    "sg:province":"Z\u00fcrich",
    "wof:name":"Dana Sa",
    "wof:placetype":"venue"
},
  "geometry": {"coordinates":[6.856867,46.453026],"type":"Point"}
}