{
  "type": "Feature",
  "properties": {
    "iso:country":"CH",
    "sg:address":"K\u00fcrzihof 7",
    "sg:city":"Widen",
    "sg:orig_category":"Vereine Fasnacht",
    "sg:phone":"+41 56 633 77 71",
    "sg:postcode":"8967",
    "sg:province":"Aargau",
    "wof:name":"Guggenmusik Gyre-s\u00fcmpfer",
    "wof:placetype":"venue"
},
  "geometry": {"coordinates":[8.3574457169,47.3707084656],"type":"Point"}
}