{
  "type": "Feature",
  "properties": {
    "iso:country":"CH",
    "sg:address":"6675",
    "sg:city":"Cevio",
    "sg:orig_category":"Non-Classified Establishments",
    "sg:phone":"+41 79 754 13 88",
    "sg:postcode":"6675",
    "sg:province":"Ticino",
    "wof:name":"Bettazza Graniti Sa",
    "wof:placetype":"venue"
},
  "geometry": {"coordinates":[8.602025032,46.3169059753],"type":"Point"}
}