{
  "type": "Feature",
  "properties": {
    "iso:country":"CH",
    "sg:address":"9215",
    "sg:city":"Buhwil",
    "sg:orig_category":"Schulpflegen",
    "sg:phone":"+41 33 356 35 20",
    "sg:postcode":"9215",
    "sg:province":"Thurgau",
    "wof:name":"Primarschulkommission Der Gemeinde Burgistein Dorf",
    "wof:placetype":"venue"
},
  "geometry": {"coordinates":[8.6473550797,47.5728683472],"type":"Point"}
}