{
  "type": "Feature",
  "properties": {
    "iso:country":"CH",
    "sg:address":"Industriestrasse 57",
    "sg:city":"R\u00fcmlang",
    "sg:orig_category":"Herstellung von sonstigen chemischen Erzeugnissen",
    "sg:phone":"+41 18101222",
    "sg:postcode":"8153",
    "sg:province":"Z\u00fcrich",
    "wof:name":"Protecsol Ag",
    "wof:placetype":"venue"
},
  "geometry": {"coordinates":[8.5522603989,47.4325942993],"type":"Point"}
}