{
  "type": "Feature",
  "properties": {
    "addr:full":"Kollerweg 9 3006 Bern. Postfach Bern Bern 3006",
    "addr:housenumber":"9",
    "addr:postcode":"3006;postfach;3006",
    "addr:street":"Kollerweg",
    "iso:country":"CH",
    "sg:address":"Kollerweg 9 3006 Bern. Postfach",
    "sg:city":"Bern",
    "sg:orig_category":"Allgemeiner Hoch U Tiefbau",
    "sg:phone":"+41 31 352 63 34",
    "sg:postcode":"3006",
    "sg:province":"Bern",
    "wof:name":"Diggelmann + Partner Ag",
    "wof:placetype":"venue"
},
  "geometry": {"coordinates":[7.456394,46.944981],"type":"Point"}
}