{
  "type": "Feature",
  "properties": {
    "iso:country":"CH",
    "sg:address":"Grubenstrasse 56",
    "sg:city":"Z\u00fcrich",
    "sg:classifiers":[
        {
            "category":"Wholesale",
            "subcategory":"Books, Periodicals, & Newspapers",
            "type":"Manufacturing & Wholesale Goods"
        }
    ],
    "sg:phone":"+41 71 244 25 39",
    "sg:postcode":"8045",
    "sg:province":"Z\u00fcrich",
    "sg:tags":[
        "publisher",
        "journal"
    ],
    "wof:name":"Informationsverlag Gmbh",
    "wof:placetype":"venue"
},
  "geometry": {"coordinates":[9.4037971497,47.433216095],"type":"Point"}
}