{
  "type": "Feature",
  "properties": {
    "iso:country":"CH",
    "sg:address":"Weidstrasse 6b",
    "sg:city":"Steinhausen",
    "sg:orig_category":"Unclassifiable Establishments",
    "sg:postcode":"6312",
    "sg:province":"Zug",
    "wof:name":"Adler Marketing Gmbh",
    "wof:placetype":"venue"
},
  "geometry": {"coordinates":[8.4891462326,47.2008628845],"type":"Point"}
}