{
  "type": "Feature",
  "properties": {
    "addr:full":"Rikonerstrasse 26 Effretikon Z\u00fcrich 8307",
    "addr:housenumber":"26",
    "addr:postcode":"8307",
    "addr:street":"Rikonerstrasse",
    "iso:country":"CH",
    "sg:address":"Rikonerstrasse 26",
    "sg:city":"Effretikon",
    "sg:orig_category":"Autogaragen",
    "sg:phone":"+41 52 343 13 02",
    "sg:postcode":"8307",
    "sg:province":"Z\u00fcrich",
    "wof:name":"Tony Stifter Ford Garage",
    "wof:placetype":"venue"
},
  "geometry": {"coordinates":[8.687541,47.430557],"type":"Point"}
}