{
  "type": "Feature",
  "properties": {
    "iso:country":"CH",
    "sg:address":"Industriestrasse 6215 Berom\u00fcnster. Postfach",
    "sg:city":"Berom\u00fcnster",
    "sg:orig_category":"Instandhaltung U Reparatur von Automobilen",
    "sg:phone":"+41 79 641 15 04",
    "sg:postcode":"6215",
    "sg:province":"Luzern",
    "wof:name":"Moos-garage T. Glanzmann",
    "wof:placetype":"venue"
},
  "geometry": {"coordinates":[8.2038154602,47.2032432556],"type":"Point"}
}