{
  "type": "Feature",
  "properties": {
    "iso:country":"CH",
    "sg:address":"Chemin Des L\u00e9ch\u00e8res 6",
    "sg:city":"Meyrin",
    "sg:orig_category":"Grosshandel mit sonstigen Maschinen U Ausr\u00fcstungen f\u00fcr Industrie, Handel U Schiffahrt",
    "sg:postcode":"1217",
    "sg:province":"Gen\u00e8ve",
    "wof:name":"Comte Francis, Fournitures Industrielles",
    "wof:placetype":"venue"
},
  "geometry": {"coordinates":[6.6845641136,48.3388366699],"type":"Point"}
}