{
  "type": "Feature",
  "properties": {
    "iso:country":"CH",
    "sg:address":"Scheuchenstrasse 45f",
    "sg:city":"Frauenfeld",
    "sg:orig_category":"Sonstige pers\u00f6nliche Dienstleistungen",
    "sg:phone":"+41 52 722 46 70",
    "sg:postcode":"8500",
    "sg:province":"Thurgau",
    "wof:name":"K\u00e4fer Rolf Telematik",
    "wof:placetype":"venue"
},
  "geometry": {"coordinates":[8.8813362122,47.557800293],"type":"Point"}
}