{
  "type": "Feature",
  "properties": {
    "iso:country":"CH",
    "sg:address":"7232",
    "sg:city":"Furna",
    "sg:orig_category":"Bauschreinerei",
    "sg:phone":"+41 81 332 12 85",
    "sg:postcode":"7232",
    "sg:province":"Graubunden",
    "wof:name":"Andreas B\u00e4rtsch Schreinerei",
    "wof:placetype":"venue"
},
  "geometry": {"coordinates":[9.678459,46.936718],"type":"Point"}
}