{
  "type": "Feature",
  "properties": {
    "iso:country":"CH",
    "sg:address":"G\u00fctschstrasse 3",
    "sg:city":"Gersau",
    "sg:orig_category":"Herstellung von Metallkonstruktionen Schlossereien",
    "sg:phone":"+41 41 828 12 80",
    "sg:postcode":"6442",
    "sg:province":"Schwyz",
    "wof:name":"Camenzind Hans, Metallbau, Schlosserei Und Eisenwaren.",
    "wof:placetype":"venue"
},
  "geometry": {"coordinates":[8.5285081863,46.9915237427],"type":"Point"}
}