{
  "type": "Feature",
  "properties": {
    "addr:full":"Boulevard De Grancy 39 Lausanne Vaud 1006",
    "addr:housenumber":"39",
    "addr:postcode":"1006",
    "addr:street":"Boulevard De Grancy",
    "iso:country":"CH",
    "sg:address":"Boulevard De Grancy 39",
    "sg:city":"Lausanne",
    "sg:orig_category":"Arztpraxen",
    "sg:phone":"+41 21 613 32 00",
    "sg:postcode":"1006",
    "sg:province":"Vaud",
    "wof:name":"Dr M\u00e9d. Esther Vonlanthen Roth M\u00e9decin Sp\u00e9cialiste Fmh",
    "wof:placetype":"venue"
},
  "geometry": {"coordinates":[6.626481,46.51606],"type":"Point"}
}