{
  "type": "Feature",
  "properties": {
    "iso:country":"CH",
    "sg:address":"Rue De Lausanne 118",
    "sg:city":"Sitten",
    "sg:orig_category":"Instandhaltung U Reparatur von Automobilen",
    "sg:phone":"+41 27 322 14 91",
    "sg:postcode":"1950",
    "sg:province":"Valais",
    "wof:name":"Frass Antoine",
    "wof:placetype":"venue"
},
  "geometry": {"coordinates":[7.3429789543,46.2282142639],"type":"Point"}
}