{
  "type": "Feature",
  "properties": {
    "iso:country":"CH",
    "sg:address":"Schaffhauserstrasse 5",
    "sg:city":"Z\u00fcrich",
    "sg:orig_category":"Geb\u00e4ude, Wohnungsreinigung Reinigungsgewerbe",
    "sg:phone":"+41 79 232 37 37",
    "sg:postcode":"8006",
    "sg:province":"Z\u00fcrich",
    "wof:name":"Asco-geb\u00e4udereinigung Ag",
    "wof:placetype":"venue"
},
  "geometry": {"coordinates":[8.320649147,47.3587265015],"type":"Point"}
}