{
  "type": "Feature",
  "properties": {
    "iso:country":"CH",
    "sg:address":"Brausmatt",
    "sg:city":"Gondiswil",
    "sg:orig_category":"Haltung von Rindern",
    "sg:postcode":"4955",
    "sg:province":"Bern",
    "wof:name":"Viehzuchtgenossenschaft Gondiswil",
    "wof:placetype":"venue"
},
  "geometry": {"coordinates":[7.8662629128,47.1509933472],"type":"Point"}
}