{
  "type": "Feature",
  "properties": {
    "iso:country":"CH",
    "sg:address":"G\u00e4rtnerstrasse 35",
    "sg:city":"Basel",
    "sg:classifiers":[
        {
            "category":"Restaurant",
            "type":"Food & Drink"
        }
    ],
    "sg:phone":"+41 27 288 21 09",
    "sg:postcode":"4057",
    "sg:province":"Basel-Stadt",
    "wof:name":"Ch\u00e2teau De Brignon Restaurant",
    "wof:placetype":"venue"
},
  "geometry": {"coordinates":[7.3285079002,46.2043037415],"type":"Point"}
}