{
  "type": "Feature",
  "properties": {
    "iso:country":"CH",
    "sg:address":"Wilerstrasse 8",
    "sg:city":"Weinfelden",
    "sg:classifiers":[
        {
            "category":"Restaurant",
            "type":"Food & Drink"
        }
    ],
    "sg:phone":"+41 71 622 12 66",
    "sg:postcode":"8570",
    "sg:province":"Thurgau",
    "wof:name":"Restaurant Pulcinella",
    "wof:placetype":"venue"
},
  "geometry": {"coordinates":[9.1081161499,47.564743042],"type":"Point"}
}