{
  "type": "Feature",
  "properties": {
    "iso:country":"CH",
    "sg:address":"T\u00fcftelstrasse 51",
    "sg:city":"Koblenz",
    "sg:orig_category":"Malerei",
    "sg:postcode":"5322",
    "sg:province":"Aargau",
    "wof:name":"Binkert Gmbh Malergesch\u00e4ft",
    "wof:placetype":"venue"
},
  "geometry": {"coordinates":[8.2495555878,47.6116638184],"type":"Point"}
}