{
  "type": "Feature",
  "properties": {
    "iso:country":"CH",
    "sg:address":"6780",
    "sg:city":"Airolo",
    "sg:classifiers":[
        {
            "category":"Bars & Pubs",
            "type":"Food & Drink"
        }
    ],
    "sg:phone":"+41 91 869 29 30",
    "sg:postcode":"6780",
    "sg:province":"Ticino",
    "wof:name":"Bar Sport",
    "wof:placetype":"venue"
},
  "geometry": {"coordinates":[8.609497,46.527802],"type":"Point"}
}