{
  "type": "Feature",
  "properties": {
    "iso:country":"CH",
    "sg:address":"Chemin Des Croisettes 26-28",
    "sg:city":"Epalinges",
    "sg:orig_category":"Handelsvermittlung U Grosshandel",
    "sg:phone":"+41 21 651 78 11",
    "sg:postcode":"1066",
    "sg:province":"Vaud",
    "wof:name":"Lenark Sa Op\u00e9rations Commerciales",
    "wof:placetype":"venue"
},
  "geometry": {"coordinates":[6.6591029167,46.5440979004],"type":"Point"}
}