{
  "type": "Feature",
  "properties": {
    "iso:country":"CH",
    "sg:address":"B\u00f6sch 69",
    "sg:city":"Zug",
    "sg:classifiers":[
        {
            "category":"Industrial Area",
            "type":"Public Place"
        }
    ],
    "sg:phone":"+41 91 612 91 11",
    "sg:postcode":"6331",
    "sg:province":"Zug",
    "sg:tags":[
        "large",
        "private"
    ],
    "wof:name":"Bally Management Ltd.",
    "wof:placetype":"venue"
},
  "geometry": {"coordinates":[8.8767995834,45.9703636169],"type":"Point"}
}