{
  "type": "Feature",
  "properties": {
    "iso:country":"CH",
    "sg:address":"Zandone",
    "sg:city":"Losone",
    "sg:orig_category":"Non-Classified Establishments",
    "sg:phone":"+41 91 791 63 33",
    "sg:postcode":"6616",
    "sg:province":"Ticino",
    "wof:name":"Pedroli Remo",
    "wof:placetype":"venue"
},
  "geometry": {"coordinates":[8.7371740341,46.1792068481],"type":"Point"}
}