{
  "type": "Feature",
  "properties": {
    "iso:country":"CH",
    "sg:address":"Lerchenbohlstrasse 53 8580 Amriswil. Postfach",
    "sg:city":"Amriswil",
    "sg:orig_category":"Herstellung von sonstigen Maschinen f\u00fcr unspezifische Verwendung",
    "sg:phone":"+41 56 610 42 63",
    "sg:postcode":"8580",
    "sg:province":"Thurgau",
    "wof:name":"Advapack Gmbh Verpackungs, Apparate, Maschinen U. Systeme; Handel, Produktion Usw",
    "wof:placetype":"venue"
},
  "geometry": {"coordinates":[9.2983398438,47.540184021],"type":"Point"}
}