{
  "type": "Feature",
  "properties": {
    "iso:country":"CH",
    "sg:address":"Solothurnerstrasse 48 4053 Basel. Postfach 4273",
    "sg:city":"Basel",
    "sg:orig_category":"Lagerung Sonstige Verkehrsvermittlung",
    "sg:postcode":"4002",
    "sg:province":"Basel-Stadt",
    "wof:name":"Servipack Verpackungs-service Gmbh",
    "wof:placetype":"venue"
},
  "geometry": {"coordinates":[9.5592212677,47.3678779602],"type":"Point"}
}