{
  "type": "Feature",
  "properties": {
    "iso:country":"CH",
    "sg:address":"Via S. Gottardo 154",
    "sg:city":"Savosa",
    "sg:orig_category":"Grossbanken",
    "sg:phone":"+41 62 866 45 45",
    "sg:postcode":"6942",
    "sg:province":"Ticino",
    "wof:name":"Ubs Ag",
    "wof:placetype":"venue"
},
  "geometry": {"coordinates":[7.9498701096,47.5454216003],"type":"Point"}
}