{
  "type": "Feature",
  "properties": {
    "iso:country":"CH",
    "sg:address":"Zollstr. 6 7206 Igis. Postfach",
    "sg:city":"Landquart",
    "sg:orig_category":"Zimmerei, Dachdeckerei, Bauspenglerei U Abdichtung",
    "sg:phone":"+41 31 932 40 32",
    "sg:postcode":"7302",
    "sg:province":"Graubunden",
    "wof:name":"Kr\u00e4uchi + Sohn Ag",
    "wof:placetype":"venue"
},
  "geometry": {"coordinates":[7.5142989159,46.9577255249],"type":"Point"}
}