{
  "type": "Feature",
  "properties": {
    "iso:country":"CH",
    "sg:address":"H\u00f6henweg",
    "sg:city":"Bronschhofen",
    "sg:orig_category":"Politische Parteien CVP",
    "sg:phone":"+41 71 222 33 84",
    "sg:postcode":"9552",
    "sg:province":"St. Gallen",
    "wof:name":"Cvp Ortspartei Buchs",
    "wof:placetype":"venue"
},
  "geometry": {"coordinates":[9.4501104355,47.1685714722],"type":"Point"}
}