{
  "type": "Feature",
  "properties": {
    "iso:country":"CH",
    "sg:address":"Waldenburgerstrasse 1 4410 Liestal. Postfach",
    "sg:city":"Liestal",
    "sg:classifiers":[
        {
            "category":"Travel",
            "subcategory":"Hotels & Motels",
            "type":"Entertainment"
        }
    ],
    "sg:postcode":"4410",
    "sg:province":"Basel-Landschaft",
    "sg:tags":[
        "hotels",
        "mit",
        "restaurant"
    ],
    "wof:name":"Supersaxo Gebr\u00fcder.",
    "wof:placetype":"venue"
},
  "geometry": {"coordinates":[7.933672905,46.1117172241],"type":"Point"}
}