{
  "type": "Feature",
  "properties": {
    "iso:country":"CH",
    "sg:address":"Winznauerstrasse 128 4632 Trimbach. Postfach",
    "sg:city":"Trimbach",
    "sg:orig_category":"Druck ohne Zeitungsdruck Offsetdruck",
    "sg:phone":"+41 62 293 38 13",
    "sg:postcode":"4632",
    "sg:province":"Solothurn",
    "wof:name":"Rankwoog-druck Ag",
    "wof:placetype":"venue"
},
  "geometry": {"coordinates":[7.91127491,47.3675956726],"type":"Point"}
}