{
  "type": "Feature",
  "properties": {
    "iso:country":"CH",
    "sg:address":"Baarerstrasse 8 6300 Zug. Postfach",
    "sg:city":"Zug",
    "sg:orig_category":"Interessenvertretungen",
    "sg:postcode":"6300",
    "sg:province":"Zug",
    "wof:name":"Numerimage",
    "wof:placetype":"venue"
},
  "geometry": {"coordinates":[5.1808700562,45.8973388672],"type":"Point"}
}