{
  "type": "Feature",
  "properties": {
    "iso:country":"CH",
    "sg:address":"Neugasse 20",
    "sg:city":"Rorschach",
    "sg:orig_category":"Detailhandel mit Geschenkartikeln U Souvenirs",
    "sg:phone":"+41 71 841 66 61",
    "sg:postcode":"9400",
    "sg:province":"St. Gallen",
    "wof:name":"Gabriela Ademi Boutique Gabriela",
    "wof:placetype":"venue"
},
  "geometry": {"coordinates":[9.4907913208,47.4787788391],"type":"Point"}
}