{
  "type": "Feature",
  "properties": {
    "iso:country":"CH",
    "sg:address":"3672",
    "sg:city":"Oberdiessbach",
    "sg:orig_category":"Vereine Vogel-& Naturschutz",
    "sg:phone":"+41 31 771 05 02",
    "sg:postcode":"3672",
    "sg:province":"Bern",
    "wof:name":"Ornithologischer Verein",
    "wof:placetype":"venue"
},
  "geometry": {"coordinates":[7.6189479828,46.8401603699],"type":"Point"}
}