{
  "type": "Feature",
  "properties": {
    "iso:country":"CH",
    "sg:address":"Schneidersmatt 20a",
    "sg:city":"W\u00fcnnewil",
    "sg:orig_category":"Herstellung von keramischen Wand U Bodenfliesen U platten Verlegen von Fliesen U Platten",
    "sg:phone":"+41 26 496 23 62",
    "sg:postcode":"3184",
    "sg:province":"Fribourg",
    "wof:name":"Heribert Sch\u00e4fler Keramische Wand-& Bodenbel\u00e4ge",
    "wof:placetype":"venue"
},
  "geometry": {"coordinates":[7.2738919258,46.8672065735],"type":"Point"}
}