{
  "type": "Feature",
  "properties": {
    "iso:country":"CH",
    "sg:address":"6533",
    "sg:city":"Lumino",
    "sg:classifiers":[
        {
            "category":"Travel",
            "subcategory":"Hotels & Motels",
            "type":"Entertainment"
        }
    ],
    "sg:phone":"+41 22 367 26 13",
    "sg:postcode":"6533",
    "sg:province":"Ticino",
    "sg:tags":[
        "hotels",
        "mit",
        "restaurant"
    ],
    "wof:name":"Roelofs Catharina",
    "wof:placetype":"venue"
},
  "geometry": {"coordinates":[6.1641960144,46.3925895691],"type":"Point"}
}