{
  "type": "Feature",
  "properties": {
    "iso:country":"CH",
    "sg:address":"Chemin De La Cure 8 1092 Belmont-lausanne Case Postale 106",
    "sg:city":"Belmont-lausanne",
    "sg:orig_category":"Informatikdienste Softwareentwicklung U beratung",
    "sg:phone":"+41 41 871 24 40",
    "sg:postcode":"1092",
    "sg:province":"Vaud",
    "wof:name":"It Security Management Gmbh",
    "wof:placetype":"venue"
},
  "geometry": {"coordinates":[8.6314439774,46.8786125183],"type":"Point"}
}