{
  "type": "Feature",
  "properties": {
    "iso:country":"CH",
    "sg:address":"Badenerstrasse 745",
    "sg:city":"Z\u00fcrich",
    "sg:orig_category":"Technische, physikalische U chemische Untersuchung",
    "sg:phone":"+41 14326006",
    "sg:postcode":"8048",
    "sg:province":"Z\u00fcrich",
    "wof:name":"Mikrobia Chea Eak Hour Dr.",
    "wof:placetype":"venue"
},
  "geometry": {"coordinates":[8.4794063568,47.3903923035],"type":"Point"}
}