{
  "type": "Feature",
  "properties": {
    "iso:country":"CH",
    "sg:address":"1853",
    "sg:city":"Yvorne",
    "sg:classifiers":[
        {
            "category":"Restaurant",
            "type":"Food & Drink"
        }
    ],
    "sg:phone":"+41 24 466 19 28",
    "sg:postcode":"1853",
    "sg:province":"Vaud",
    "wof:name":"Restaurant Le Torrent",
    "wof:placetype":"venue"
},
  "geometry": {"coordinates":[6.9589409828,46.3313713074],"type":"Point"}
}