{
  "type": "Feature",
  "properties": {
    "iso:country":"CH",
    "sg:address":"Sch\u00f6naustrasse 25",
    "sg:city":"Basel",
    "sg:orig_category":"Unclassifiable Establishments",
    "sg:postcode":"4058",
    "sg:province":"Basel-Stadt",
    "wof:name":"Grosspeter Ag Garage",
    "wof:placetype":"venue"
},
  "geometry": {"coordinates":[7.5987730026,47.5677566528],"type":"Point"}
}