{
  "type": "Feature",
  "properties": {
    "iso:country":"CH",
    "sg:address":"L\u00e4gernstrasse 14",
    "sg:city":"Z\u00fcrich",
    "sg:orig_category":"Geb\u00e4ude, Wohnungsreinigung",
    "sg:phone":"+41 13619585",
    "sg:postcode":"8037",
    "sg:province":"Z\u00fcrich",
    "wof:name":"Georges Geroyannis Gery-reinigung",
    "wof:placetype":"venue"
},
  "geometry": {"coordinates":[8.5313396454,47.3941497803],"type":"Point"}
}