{
  "type": "Feature",
  "properties": {
    "addr:full":"Kasinostrasse 40 Aarau Aargau 5000",
    "addr:housenumber":"40",
    "addr:postcode":"5000",
    "addr:street":"Kasinostrasse",
    "iso:country":"CH",
    "sg:address":"Kasinostrasse 40",
    "sg:city":"Aarau",
    "sg:orig_category":"Detailhandel mit Bekleidung",
    "sg:postcode":"5000",
    "sg:province":"Aargau",
    "wof:name":"Rafael Mode Gmbh",
    "wof:placetype":"venue"
},
  "geometry": {"coordinates":[8.047326,47.391251],"type":"Point"}
}