{
  "type": "Feature",
  "properties": {
    "iso:country":"CH",
    "sg:address":"Erlenstrasse 35",
    "sg:city":"Therwil",
    "sg:orig_category":"Herstellung von M\u00f6beln verschiedener Art Innenausbau",
    "sg:phone":"+41 61 723 07 23",
    "sg:postcode":"4106",
    "sg:province":"Basel-Landschaft",
    "wof:name":"H\u00fcrlimann Peter M\u00f6belschreinerei-innenausbau",
    "wof:placetype":"venue"
},
  "geometry": {"coordinates":[7.5562200546,47.5052757263],"type":"Point"}
}