{
  "type": "Feature",
  "properties": {
    "addr:full":"Heldstrasse 12 Widnau St. Gallen 9443",
    "addr:housenumber":"12;st.",
    "addr:postcode":"9443",
    "addr:street":"Heldstrasse;Widnau",
    "iso:country":"CH",
    "sg:address":"Heldstrasse 12",
    "sg:city":"Widnau",
    "sg:classifiers":[
        {
            "category":"Home & Garden",
            "subcategory":"Building Materials",
            "type":"Retail Goods"
        }
    ],
    "sg:phone":"+41 71 722 59 64",
    "sg:postcode":"9443",
    "sg:province":"St. Gallen",
    "sg:tags":[
        "banister"
    ],
    "wof:name":"Hutter Ag",
    "wof:placetype":"venue"
},
  "geometry": {"coordinates":[9.636984,47.399536],"type":"Point"}
}