{
  "type": "Feature",
  "properties": {
    "iso:country":"CH",
    "sg:address":"Sedelstrasse 1 6020 Emmenbr\u00fccke. Postfach",
    "sg:city":"Emmenbr\u00fccke",
    "sg:orig_category":"Instandhaltung U Reparatur von Automobilen",
    "sg:phone":"+41 41 268 10 25",
    "sg:postcode":"6020",
    "sg:province":"Luzern",
    "wof:name":"Universal Ag",
    "wof:placetype":"venue"
},
  "geometry": {"coordinates":[8.2847099304,47.0695877075],"type":"Point"}
}