{
  "type": "Feature",
  "properties": {
    "iso:country":"CH",
    "sg:address":"Bellerivestrasse 18 8008 Z\u00fcrich. Postfach",
    "sg:city":"Z\u00fcrich",
    "sg:orig_category":"Vermietung U Verpachtung von eigenen Immobilien",
    "sg:postcode":"8001",
    "sg:province":"Z\u00fcrich",
    "wof:name":"Holgan Immobilien Ag Immobilien Usw",
    "wof:placetype":"venue"
},
  "geometry": {"coordinates":[8.5487756729,47.3598022461],"type":"Point"}
}