{
  "type": "Feature",
  "properties": {
    "iso:country":"CH",
    "sg:address":"Cavazz Via Zona Industriale 4",
    "sg:city":"Mezzovico",
    "sg:orig_category":"Allgemeiner Hoch U Tiefbau",
    "sg:postcode":"6805",
    "sg:province":"Ticino",
    "wof:name":"Schafer Manfred Gmbh",
    "wof:placetype":"venue"
},
  "geometry": {"coordinates":[7.260303,46.823997],"type":"Point"}
}