{
  "type": "Feature",
  "properties": {
    "iso:country":"CH",
    "sg:address":"Rheinaustrasse 2",
    "sg:city":"Sargans",
    "sg:orig_category":"Erbringung von Dienstleistungen f\u00fcr Unternehmen Malerei",
    "sg:phone":"+41 81 720 40 70",
    "sg:postcode":"7320",
    "sg:province":"St. Gallen",
    "wof:name":"Kloter Team Ag Dekorations Und Baumalerei",
    "wof:placetype":"venue"
},
  "geometry": {"coordinates":[9.446595192,47.0494689941],"type":"Point"}
}