{
  "type": "Feature",
  "properties": {
    "iso:country":"CH",
    "sg:address":"Vevey Rue De 75",
    "sg:city":"Bulle",
    "sg:orig_category":"G\u00fcterbef\u00f6rderung im Strassenverkehr",
    "sg:phone":"+41 26 913 10 34",
    "sg:postcode":"1630",
    "sg:province":"Fribourg",
    "wof:name":"Antonio Marques Leal",
    "wof:placetype":"venue"
},
  "geometry": {"coordinates":[7.0573811531,46.6186027527],"type":"Point"}
}