{
  "type": "Feature",
  "properties": {
    "iso:country":"CH",
    "sg:address":"Place De La Gare 10 1000 Lausanne. Postfach",
    "sg:city":"Lausanne",
    "sg:orig_category":"Architektur U Ingenieurb\u00fcros",
    "sg:postcode":"1003",
    "sg:province":"Vaud",
    "wof:name":"Emms Engineering And Maintenance Management Services Sa.",
    "wof:placetype":"venue"
},
  "geometry": {"coordinates":[6.628744,46.517551],"type":"Point"}
}