{
  "type": "Feature",
  "properties": {
    "iso:country":"CH",
    "sg:address":"Bohlgutsch 4",
    "sg:city":"Zug",
    "sg:orig_category":"Satzherstellung U Reproduktion",
    "sg:phone":"+41 56 624 24 04",
    "sg:postcode":"6300",
    "sg:province":"Zug",
    "wof:name":"Berger, Viscom, Visuelle Kommunikation",
    "wof:placetype":"venue"
},
  "geometry": {"coordinates":[8.5214958191,47.1652450562],"type":"Point"}
}