{
  "type": "Feature",
  "properties": {
    "iso:country":"CH",
    "sg:address":"Hauptstrasse 36",
    "sg:city":"Muttenz",
    "sg:orig_category":"Architektur U Ingenieurb\u00fcros",
    "sg:postcode":"4132",
    "sg:province":"Basel-Landschaft",
    "wof:name":"Set Projekt Ag",
    "wof:placetype":"venue"
},
  "geometry": {"coordinates":[7.646399,47.524548],"type":"Point"}
}