{
  "type": "Feature",
  "properties": {
    "iso:country":"CH",
    "sg:address":"Innerhofweg 7",
    "sg:city":"Hindelbank",
    "sg:orig_category":"Fotografische Ateliers",
    "sg:phone":"+41 34 411 24 51",
    "sg:postcode":"3324",
    "sg:province":"Bern",
    "wof:name":"Fritz Gerber Fotografisches Atelier",
    "wof:placetype":"venue"
},
  "geometry": {"coordinates":[7.5387539864,47.0402030945],"type":"Point"}
}