{
  "type": "Feature",
  "properties": {
    "addr:full":"Z\u00fcrichstrasse 5 Luzern Luzern 6004",
    "addr:housenumber":"5",
    "addr:postcode":"6004",
    "addr:street":"Zuerichstrasse",
    "iso:country":"CH",
    "sg:address":"Z\u00fcrichstrasse 5",
    "sg:city":"Luzern",
    "sg:orig_category":"Detailhandel mit Damenbekleidung",
    "sg:phone":"+41 41 410 44 01",
    "sg:postcode":"6004",
    "sg:province":"Luzern",
    "wof:name":"Beldona Ag",
    "wof:placetype":"venue"
},
  "geometry": {"coordinates":[8.310325,47.056435],"type":"Point"}
}