{
  "type": "Feature",
  "properties": {
    "iso:country":"CH",
    "sg:address":"Langnaustrasse 72",
    "sg:city":"Zollbr\u00fcck",
    "sg:orig_category":"Sonstiges Gesundheitswesen",
    "sg:phone":"+41 34 496 78 05",
    "sg:postcode":"3436",
    "sg:province":"Bern",
    "wof:name":"Krankenmobilienmagazin Des Samaritervereins A.gerber",
    "wof:placetype":"venue"
},
  "geometry": {"coordinates":[7.751431942,46.9679145813],"type":"Point"}
}