{
  "type": "Feature",
  "properties": {
    "addr:full":"Fichtenweg 7 Zuchwil Solothurn 4528",
    "addr:housenumber":"7",
    "addr:postcode":"4528",
    "addr:street":"Fichtenweg",
    "iso:country":"CH",
    "sg:address":"Fichtenweg 7",
    "sg:city":"Zuchwil",
    "sg:classifiers":[
        {
            "category":"Banks & Credit Unions",
            "subcategory":"Bank",
            "type":"Services"
        }
    ],
    "sg:phone":"+41 4165252531",
    "sg:postcode":"4528",
    "sg:province":"Solothurn",
    "wof:name":"Schweiz. Mobiliar",
    "wof:placetype":"venue"
},
  "geometry": {"coordinates":[7.552306,47.196499],"type":"Point"}
}