{
  "type": "Feature",
  "properties": {
    "iso:country":"CH",
    "sg:address":"L\u00f6tschbergstrasse 6",
    "sg:city":"Frutigen",
    "sg:orig_category":"Instandhaltung U Reparatur von Automobilen",
    "sg:phone":"+41 33 671 14 02",
    "sg:postcode":"3714",
    "sg:province":"Bern",
    "wof:name":"Trachsel Gebr, Garage Tellenburg",
    "wof:placetype":"venue"
},
  "geometry": {"coordinates":[7.6521291733,46.5781364441],"type":"Point"}
}