{
  "type": "Feature",
  "properties": {
    "iso:country":"CH",
    "sg:address":"M\u00fchleweg 8a",
    "sg:city":"Therwil",
    "sg:orig_category":"Bauspenglerei Dachdeckerei",
    "sg:phone":"+41 62 298 30 13",
    "sg:postcode":"4106",
    "sg:province":"Basel-Landschaft",
    "wof:name":"Wyss Bedachungen-bauspenglerei Gmbh",
    "wof:placetype":"venue"
},
  "geometry": {"coordinates":[7.951591,47.410831],"type":"Point"}
}