{
  "type": "Feature",
  "properties": {
    "iso:country":"CH",
    "sg:address":"Moulin Rue Du 1 2738 Court. Postfach",
    "sg:city":"Court",
    "sg:orig_category":"Forstwirtschaft ohne Dienstleistungen in der Forstwirtschaft",
    "sg:phone":"+41 32 497 96 76",
    "sg:postcode":"2738",
    "sg:province":"Bern",
    "wof:name":"Ross\u00e9 Pascal Exploit. Foresti\u00e8re, Fa\u00e7onnage Etc.",
    "wof:placetype":"venue"
},
  "geometry": {"coordinates":[7.33685112,47.2384719849],"type":"Point"}
}