{
  "type": "Feature",
  "properties": {
    "iso:country":"CH",
    "sg:address":"Habsburgerstrasse 22",
    "sg:city":"Luzern",
    "sg:orig_category":"Sonstiger Fachdetailhandel in Verkaufsr\u00e4umen",
    "sg:phone":"+41 41 211 09 33",
    "sg:postcode":"6003",
    "sg:province":"Luzern",
    "wof:name":"Werner Hirsiger Briefmarken & M\u00fcnzenhandel",
    "wof:placetype":"venue"
},
  "geometry": {"coordinates":[8.3071346283,47.0469894409],"type":"Point"}
}