{
  "type": "Feature",
  "properties": {
    "iso:country":"CH",
    "sg:address":"Miesernweg 5",
    "sg:city":"Trimbach",
    "sg:orig_category":"Stukkateurgewerbe, Gipserei U Verputzerei",
    "sg:phone":"+41 62 293 44 55",
    "sg:postcode":"4632",
    "sg:province":"Solothurn",
    "wof:name":"Mini Dario Ag",
    "wof:placetype":"venue"
},
  "geometry": {"coordinates":[7.8692698479,47.363407135],"type":"Point"}
}