{
  "type": "Feature",
  "properties": {
    "addr:full":"B\u00fcren 8558 Raperswilen. Postfach Raperswilen Thurgau 8558",
    "addr:postcode":"8558 raperswilen. postfach;8558",
    "addr:street":"Bueren",
    "iso:country":"CH",
    "sg:address":"B\u00fcren 8558 Raperswilen. Postfach",
    "sg:city":"Raperswilen",
    "sg:orig_category":"Architektur U Ingenieurb\u00fcros",
    "sg:postcode":"8558",
    "sg:province":"Thurgau",
    "wof:name":"Uwe Rogg, Architektur & Generalunternehmen",
    "wof:placetype":"venue"
},
  "geometry": {"coordinates":[9.04495,47.644058],"type":"Point"}
}