{
  "type": "Feature",
  "properties": {
    "iso:country":"CH",
    "sg:address":"Wiesenstrasse 20",
    "sg:city":"Thalwil",
    "sg:orig_category":"Maler U Glasergewerbe Sonstiger Detailhandel mit Metallwaren, Anstrichmitteln, Glaswaren, Bau U Heim",
    "sg:phone":"+41 17200077",
    "sg:postcode":"8800",
    "sg:province":"Z\u00fcrich",
    "wof:name":"Blickenstorfer H. Ag",
    "wof:placetype":"venue"
},
  "geometry": {"coordinates":[8.5662670135,47.2898483276],"type":"Point"}
}