{
  "type": "Feature",
  "properties": {
    "iso:country":"CH",
    "sg:address":"Buchenweg 3",
    "sg:city":"Derendingen",
    "sg:orig_category":"Politische Parteien FDP",
    "sg:phone":"+41 32 682 46 53",
    "sg:postcode":"4552",
    "sg:province":"Solothurn",
    "wof:name":"Fdp Ortspartei Derendingen",
    "wof:placetype":"venue"
},
  "geometry": {"coordinates":[7.5836410522,47.1914024353],"type":"Point"}
}