{
  "type": "Feature",
  "properties": {
    "iso:country":"CH",
    "sg:address":"Grand-rue 36",
    "sg:city":"Ballaigues",
    "sg:orig_category":"W\u00e4schereien",
    "sg:phone":"+41 21 843 30 41",
    "sg:postcode":"1338",
    "sg:province":"Vaud",
    "wof:name":"Jean-pierre Allemann Salon-lavoir",
    "wof:placetype":"venue"
},
  "geometry": {"coordinates":[6.4147820473,46.7293052673],"type":"Point"}
}