{
  "type": "Feature",
  "properties": {
    "iso:country":"CH",
    "sg:address":"Chauderon Place 24",
    "sg:city":"Lausanne",
    "sg:orig_category":"RESTAURANTS: TEA-ROOMS",
    "sg:postcode":"1003",
    "sg:province":"Vaud",
    "wof:name":"Pia Casanova-hodel Und Paul Von Allmen",
    "wof:placetype":"venue"
},
  "geometry": {"coordinates":[9.1225099564,46.7561416626],"type":"Point"}
}