{
  "type": "Feature",
  "properties": {
    "iso:country":"CH",
    "sg:address":"Sumpfstrasse 15 6300 Zug. Postfach 5233",
    "sg:city":"Zug",
    "sg:orig_category":"Sonstige mit der Informatik verbundene T\u00e4tigkeiten",
    "sg:phone":"+41 56 282 28 60",
    "sg:postcode":"6300",
    "sg:province":"Zug",
    "wof:name":"Hsi Informatik Ag",
    "wof:placetype":"venue"
},
  "geometry": {"coordinates":[8.3031110764,47.4840965271],"type":"Point"}
}