{
  "type": "Feature",
  "properties": {
    "iso:country":"CH",
    "sg:address":"Manessestrasse 186",
    "sg:city":"Z\u00fcrich",
    "sg:orig_category":"Detailhandel mit Brot, Back U S\u00fcsswaren",
    "sg:phone":"+41 12013716",
    "sg:postcode":"8045",
    "sg:province":"Z\u00fcrich",
    "wof:name":"B\u00e4ckerei Duria Gold",
    "wof:placetype":"venue"
},
  "geometry": {"coordinates":[8.522346,47.361729],"type":"Point"}
}