{
  "type": "Feature",
  "properties": {
    "addr:full":"Rothenburgstrasse 2 Emmenbr\u00fccke Luzern 6020",
    "addr:housenumber":"2",
    "addr:postcode":"6020",
    "addr:street":"Rothenburgstrasse",
    "iso:country":"CH",
    "sg:address":"Rothenburgstrasse 2",
    "sg:city":"Emmenbr\u00fccke",
    "sg:orig_category":"Chemische Reinigung",
    "sg:phone":"+41 41 260 79 65",
    "sg:postcode":"6020",
    "sg:province":"Luzern",
    "wof:name":"Ghelma Ag Textilreinigung",
    "wof:placetype":"venue"
},
  "geometry": {"coordinates":[8.272173,47.081261],"type":"Point"}
}