{
  "type": "Feature",
  "properties": {
    "iso:country":"CH",
    "sg:address":"1422",
    "sg:city":"Grandson",
    "sg:classifiers":[
        {
            "category":"Restaurant",
            "type":"Food & Drink"
        }
    ],
    "sg:phone":"+41 24 445 09 45",
    "sg:postcode":"1422",
    "sg:province":"Vaud",
    "wof:name":"Restaurant Le Proven\u00e7al",
    "wof:placetype":"venue"
},
  "geometry": {"coordinates":[6.6459851265,46.8093681335],"type":"Point"}
}