{
  "type": "Feature",
  "properties": {
    "iso:country":"CH",
    "sg:address":"Obere Gasse 35",
    "sg:city":"Baden",
    "sg:orig_category":"Detailhandel mit elektrischen Haushalts-,Radio U Fernsehger\u00e4ten sowie Musikinstrumenten",
    "sg:phone":"+41 56 222 40 70",
    "sg:postcode":"5400",
    "sg:province":"Aargau",
    "wof:name":"Paul H\u00fcrlimann",
    "wof:placetype":"venue"
},
  "geometry": {"coordinates":[8.3076295853,47.4727401733],"type":"Point"}
}