{
  "type": "Feature",
  "properties": {
    "iso:country":"CH",
    "sg:address":"8458",
    "sg:city":"Dorf",
    "sg:orig_category":"G\u00fcterbef\u00f6rderung im Strassenverkehr",
    "sg:postcode":"8458",
    "sg:province":"Z\u00fcrich",
    "wof:name":"Schaffner Transport Ag",
    "wof:placetype":"venue"
},
  "geometry": {"coordinates":[8.6481399536,47.5726699829],"type":"Point"}
}