{
  "type": "Feature",
  "properties": {
    "iso:country":"CH",
    "sg:address":"Champ-soleil Chemin De 22 1012 Lausanne. Postfach",
    "sg:city":"Lausanne",
    "sg:orig_category":"D\u00e4mmung gegen K\u00e4lte, W\u00e4rme, Schall U Ersch\u00fctterung",
    "sg:postcode":"1003",
    "sg:province":"Vaud",
    "wof:name":"Schuler Isolations Isolation Thermique D Le Domaine Du Chauffage, Des Sanitaires Etc",
    "wof:placetype":"venue"
},
  "geometry": {"coordinates":[6.6530251503,46.5230293274],"type":"Point"}
}