{
  "type": "Feature",
  "properties": {
    "iso:country":"CH",
    "sg:address":"Chemin De Delay 1",
    "sg:city":"Vernier",
    "sg:orig_category":"Bauspenglerei Schmieden",
    "sg:phone":"+41 22 341 04 88",
    "sg:postcode":"1214",
    "sg:province":"Gen\u00e8ve",
    "wof:name":"Edmond Klauza T\u00f4lerie & Chaudronnerie",
    "wof:placetype":"venue"
},
  "geometry": {"coordinates":[6.078512,46.217094],"type":"Point"}
}