{
  "type": "Feature",
  "properties": {
    "iso:country":"CH",
    "sg:address":"Z\u00fcrichstrasse 1",
    "sg:city":"Uster",
    "sg:orig_category":"Geb\u00e4ude, Wohnungsreinigung Reinigungsgewerbe",
    "sg:phone":"+41 52 317 17 57",
    "sg:postcode":"8610",
    "sg:province":"Z\u00fcrich",
    "wof:name":"Solazzo Wyland-reinigung Ag",
    "wof:placetype":"venue"
},
  "geometry": {"coordinates":[8.7171792984,47.3484840393],"type":"Point"}
}