{
  "type": "Feature",
  "properties": {
    "iso:country":"CH",
    "sg:address":"Bremgartenstrasse 133",
    "sg:city":"Bern",
    "sg:orig_category":"Maturit\u00e4tsschulen, Lehrerseminarien",
    "sg:phone":"+41 31 300 27 32",
    "sg:postcode":"3012",
    "sg:province":"Bern",
    "wof:name":"Berner Maturit\u00e4tsschule F\u00fcr Berufst\u00e4tige Bmb",
    "wof:placetype":"venue"
},
  "geometry": {"coordinates":[7.4283671379,46.959777832],"type":"Point"}
}