{
  "type": "Feature",
  "properties": {
    "iso:country":"CH",
    "sg:address":"Beckenhofstrasse 16",
    "sg:city":"Z\u00fcrich",
    "sg:orig_category":"K\u00fcnstlerische U schriftstellerische T\u00e4tigkeiten U Darbietungen",
    "sg:phone":"+41 13632277",
    "sg:postcode":"8006",
    "sg:province":"Z\u00fcrich",
    "wof:name":"Col Legno Management Ag",
    "wof:placetype":"venue"
},
  "geometry": {"coordinates":[8.5421590805,47.3836135864],"type":"Point"}
}