{
  "type": "Feature",
  "properties": {
    "iso:country":"CH",
    "sg:address":"Hondrichstrasse 27",
    "sg:city":"Spiez",
    "sg:orig_category":"Softwareentwicklung U beratung",
    "sg:postcode":"3700",
    "sg:province":"Bern",
    "wof:name":"Lu-com & Buchvertrieb Luginb\u00fchl R.",
    "wof:placetype":"venue"
},
  "geometry": {"coordinates":[7.6821398735,46.6809921265],"type":"Point"}
}