{
  "type": "Feature",
  "properties": {
    "iso:country":"CH",
    "sg:address":"Chemin De Gotta D'or 5",
    "sg:city":"Ch\u00e2telard-lutry",
    "sg:orig_category":"Unternehmensberatung",
    "sg:phone":"+41 79 204 22 77",
    "sg:postcode":"1095",
    "sg:province":"Vaud",
    "wof:name":"Miles & Cie",
    "wof:placetype":"venue"
},
  "geometry": {"coordinates":[19.0755157471,47.4907684326],"type":"Point"}
}