{
  "type": "Feature",
  "properties": {
    "iso:country":"CH",
    "sg:address":"Rorschacherstrasse 125 9000 St.gallen. Postfach",
    "sg:city":"St.gallen",
    "sg:orig_category":"Lagerh\u00e4user, G\u00fcterumschlag, Verteilzentren",
    "sg:phone":"+41 71 244 20 14",
    "sg:postcode":"9000",
    "sg:province":"St. Gallen",
    "wof:name":"Roland Forrer Ag, Servicelager Sprecher + Schuh",
    "wof:placetype":"venue"
},
  "geometry": {"coordinates":[9.3933982849,47.4309425354],"type":"Point"}
}