{
  "type": "Feature",
  "properties": {
    "iso:country":"CH",
    "sg:address":"Mattenstrasse 8",
    "sg:city":"Feldbrunnen",
    "sg:orig_category":"Grosshandel mit Getr\u00e4nken",
    "sg:phone":"+41 32 622 93 16",
    "sg:postcode":"4532",
    "sg:province":"Solothurn",
    "wof:name":"Weinkeller Delli Liuni Canio",
    "wof:placetype":"venue"
},
  "geometry": {"coordinates":[7.5573120117,47.2188682556],"type":"Point"}
}