{
  "type": "Feature",
  "properties": {
    "iso:country":"CH",
    "sg:address":"Rue Du Pont 18",
    "sg:city":"Montreux",
    "sg:orig_category":"Detailhandel mit Waren verschiedener Art, Hauptrichtung Nahrungsmittel",
    "sg:postcode":"1820",
    "sg:province":"Vaud",
    "wof:name":"Epicerie Du Ch\u00eane, Cherix V\u00e9ronique",
    "wof:placetype":"venue"
},
  "geometry": {"coordinates":[6.916121006,46.4341087341],"type":"Point"}
}