{
  "type": "Feature",
  "properties": {
    "iso:country":"CH",
    "sg:address":"Kirchgasse 4",
    "sg:city":"Igis",
    "sg:orig_category":"Handelsvermittlung U Grosshandel",
    "sg:phone":"+41 81 322 32 30",
    "sg:postcode":"7206",
    "sg:province":"Graubunden",
    "wof:name":"Impex",
    "wof:placetype":"venue"
},
  "geometry": {"coordinates":[9.5710668564,46.945602417],"type":"Point"}
}