{
  "type": "Feature",
  "properties": {
    "iso:country":"CH",
    "sg:address":"Oberg\u00fctschstrasse 9 6003 Luzern. Postfach",
    "sg:city":"Luzern",
    "sg:orig_category":"Sonstige mit der Informatik verbundene T\u00e4tigkeiten",
    "sg:phone":"+41 56 622 65 88",
    "sg:postcode":"6003",
    "sg:province":"Luzern",
    "wof:name":"Hans Furrer, Edv-systemberatung, Datenbanksysteme",
    "wof:placetype":"venue"
},
  "geometry": {"coordinates":[8.2933502197,47.3753089905],"type":"Point"}
}