{
  "type": "Feature",
  "properties": {
    "iso:country":"CH",
    "sg:address":"Bahnhofstr. 17",
    "sg:city":"Z\u00fcrich",
    "sg:classifiers":[
        {
            "category":"Shopping",
            "subcategory":"Luggage & Leather Goods",
            "type":"Retail Goods"
        }
    ],
    "sg:phone":"+41 4117454900",
    "sg:postcode":"8001",
    "sg:province":"Z\u00fcrich",
    "sg:tags":[
        "shoe"
    ],
    "wof:name":"Engros-schuhhaus Ag",
    "wof:placetype":"venue"
},
  "geometry": {"coordinates":[8.4016389847,47.4128990173],"type":"Point"}
}