{
  "type": "Feature",
  "properties": {
    "iso:country":"CH",
    "sg:address":"Schwellistrasse 69",
    "sg:city":"Z\u00fcrich",
    "sg:orig_category":"Detailhandel mit Waren verschiedener Art, Hauptrichtung Nahrungsmittel",
    "sg:phone":"+41 13001580",
    "sg:postcode":"8052",
    "sg:province":"Z\u00fcrich",
    "wof:name":"Coop Laden",
    "wof:placetype":"venue"
},
  "geometry": {"coordinates":[8.5375165939,47.4251823425],"type":"Point"}
}