{
  "type": "Feature",
  "properties": {
    "iso:country":"CH",
    "sg:address":"Birmensdorferstrasse 24 8902 Urdorf. Postfach 35",
    "sg:city":"Urdorf",
    "sg:orig_category":"Satzherstellung U Reproduktion",
    "sg:phone":"+41 17341313",
    "sg:postcode":"8902",
    "sg:province":"Z\u00fcrich",
    "wof:name":"Fotosatz Gut Ag",
    "wof:placetype":"venue"
},
  "geometry": {"coordinates":[8.4175901413,47.3921508789],"type":"Point"}
}