{
  "type": "Feature",
  "properties": {
    "iso:country":"CH",
    "sg:address":"Route De Savoie 86",
    "sg:city":"Pont-de-la-morge",
    "sg:orig_category":"Detailhandel mit Radio U Fernsehger\u00e4ten Detailhandel mit elektrischen Haushalts-,Radio U Fernsehger\u00e4",
    "sg:phone":"+41 27 346 28 28",
    "sg:postcode":"1962",
    "sg:province":"Valais",
    "wof:name":"Antonelli Jean-pierre, Radio-t\u00e9l\u00e9vision.",
    "wof:placetype":"venue"
},
  "geometry": {"coordinates":[7.3176450729,46.2249641418],"type":"Point"}
}