{
  "type": "Feature",
  "properties": {
    "iso:country":"CH",
    "sg:address":"Feldstrasse 7",
    "sg:city":"Vaduz",
    "sg:orig_category":"Organisationen des Gesundheitswesen",
    "sg:postcode":"9490",
    "wof:name":"Gemeindekrankenpflege",
    "wof:placetype":"venue"
},
  "geometry": {"coordinates":[9.5166196823,47.1453895569],"type":"Point"}
}