{
  "type": "Feature",
  "properties": {
    "iso:country":"CH",
    "sg:address":"Freigutstrasse 10 8002 Z\u00fcrich. Postfach",
    "sg:city":"Z\u00fcrich",
    "sg:orig_category":"Wirtschaftspr\u00fcfung, Steuerberatung U Treuhand",
    "sg:phone":"+41 12028478",
    "sg:postcode":"8039",
    "wof:name":"Avere-treuhand",
    "wof:placetype":"venue"
},
  "geometry": {"coordinates":[8.5328578949,47.3669433594],"type":"Point"}
}