{
  "type": "Feature",
  "properties": {
    "iso:country":"CH",
    "sg:address":"Kirchhofplatz 12",
    "sg:city":"Schaffhausen",
    "sg:orig_category":"Organisationen der Wohlfahrtspflege Organisationen des Gesundheitswesen",
    "sg:phone":"+41 52 625 17 33",
    "sg:postcode":"8200",
    "sg:province":"Schaffhausen",
    "wof:name":"Pro Infirmis Beratungst.& Rheumaberatung",
    "wof:placetype":"venue"
},
  "geometry": {"coordinates":[8.635933876,47.6971282959],"type":"Point"}
}