{
  "type": "Feature",
  "properties": {
    "iso:country":"CH",
    "sg:address":"Romanshornerstrasse 27",
    "sg:city":"Arbon",
    "sg:orig_category":"Detailhandel mit elektrischen Haushalts-,Radio U Fernsehger\u00e4ten sowie Musikinstrumenten",
    "sg:phone":"+41 55 440 36 36",
    "sg:postcode":"9320",
    "sg:province":"Thurgau",
    "wof:name":"Schnellmann Hermann, Abural-besteck-einrichtungen",
    "wof:placetype":"venue"
},
  "geometry": {"coordinates":[8.8979320526,47.1887054443],"type":"Point"}
}