{
  "type": "Feature",
  "properties": {
    "addr:full":"Seetalstrasse 9 Muri Aargau 5630",
    "addr:housenumber":"9",
    "addr:postcode":"5630",
    "addr:street":"Seetalstrasse",
    "iso:country":"CH",
    "sg:address":"Seetalstrasse 9",
    "sg:city":"Muri",
    "sg:classifiers":[
        {
            "category":"Banks & Credit Unions",
            "subcategory":"Bank",
            "type":"Services"
        }
    ],
    "sg:phone":"+41 4157451195",
    "sg:postcode":"5630",
    "sg:province":"Aargau",
    "wof:name":"Schweiz. Mobiliar",
    "wof:placetype":"venue"
},
  "geometry": {"coordinates":[8.336914,47.273777],"type":"Point"}
}