{
  "type": "Feature",
  "properties": {
    "iso:country":"CH",
    "sg:address":"H\u00fcningerstrasse 85 4056 Basel. Postfach",
    "sg:city":"Basel",
    "sg:classifiers":[
        {
            "category":"Communications",
            "subcategory":"Film & Video Production",
            "type":"Services"
        }
    ],
    "sg:phone":"+41 21 792 11 46",
    "sg:postcode":"4056",
    "sg:province":"Basel-Stadt",
    "sg:tags":[
        "videofilmherstellung",
        "u"
    ],
    "wof:name":"Fr\u00e9d\u00e9ric Gonseth Fr\u00e9d\u00e9ric Gonseth Productions",
    "wof:placetype":"venue"
},
  "geometry": {"coordinates":[6.7025499344,46.5161094666],"type":"Point"}
}