{
  "type": "Feature",
  "properties": {
    "iso:country":"CH",
    "sg:address":"Adelbodenstrasse 323",
    "sg:city":"Frutigen",
    "sg:orig_category":"Herstellung von Chemiefasern",
    "sg:postcode":"3714",
    "sg:province":"Bern",
    "wof:name":"Kurzen Samuel",
    "wof:placetype":"venue"
},
  "geometry": {"coordinates":[7.5999188423,46.5464820862],"type":"Point"}
}