{
  "type": "Feature",
  "properties": {
    "iso:country":"CH",
    "sg:address":"Haslernstrasse 14",
    "sg:city":"Geroldswil",
    "sg:orig_category":"Architektur U Ingenieurb\u00fcros",
    "sg:phone":"+41 17485256",
    "sg:postcode":"8954",
    "sg:province":"Z\u00fcrich",
    "wof:name":"Dr. Ernest Wallm\u00fcller Qualit\u00e4t & Informatik",
    "wof:placetype":"venue"
},
  "geometry": {"coordinates":[8.418537,47.42091],"type":"Point"}
}