{
  "type": "Feature",
  "properties": {
    "iso:country":"CH",
    "sg:address":"Kantonsstrasse 34",
    "sg:city":"Horw",
    "sg:orig_category":"Non-Classified Establishments",
    "sg:postcode":"6048",
    "sg:province":"Luzern",
    "wof:name":"Schoch Baukeramik Gmbh",
    "wof:placetype":"venue"
},
  "geometry": {"coordinates":[8.3077077866,47.0239524841],"type":"Point"}
}