{
  "type": "Feature",
  "properties": {
    "addr:full":"Grand-rue 69 Rolle Vaud 1180",
    "addr:housenumber":"69",
    "addr:postcode":"1180",
    "addr:street":"Grand-Rue",
    "iso:country":"CH",
    "sg:address":"Grand-rue 69",
    "sg:city":"Rolle",
    "sg:orig_category":"Arztpraxen",
    "sg:phone":"+41 79 203 41 86",
    "sg:postcode":"1180",
    "sg:province":"Vaud",
    "wof:name":"Dr M\u00e9d. Philippe Munier M\u00e9decin G\u00e9n\u00e9raliste",
    "wof:placetype":"venue"
},
  "geometry": {"coordinates":[6.337256,46.456631],"type":"Point"}
}