{
  "type": "Feature",
  "properties": {
    "iso:country":"CH",
    "sg:address":"Notre-dame Place 4 1700 Fribourg Case Postale 22",
    "sg:city":"Freiburg",
    "sg:orig_category":"Interessenvertretungen",
    "sg:postcode":"1700",
    "sg:province":"Fribourg",
    "wof:name":"Fondation \u00e0 La M\u00e9moire De Oskar Kokoschka",
    "wof:placetype":"venue"
},
  "geometry": {"coordinates":[5.1808700562,45.8973388672],"type":"Point"}
}