{
  "type": "Feature",
  "properties": {
    "iso:country":"CH",
    "sg:address":"Spycherhalde 6",
    "sg:city":"Luzern",
    "sg:classifiers":[
        {
            "category":"Education",
            "subcategory":"Vocational School",
            "type":"Public Place"
        }
    ],
    "sg:postcode":"6005",
    "sg:province":"Luzern",
    "sg:tags":[
        "koch-",
        "haushaltschulen"
    ],
    "wof:name":"Haushaltungsschule",
    "wof:placetype":"venue"
},
  "geometry": {"coordinates":[8.3335599899,47.0247917175],"type":"Point"}
}