{
  "type": "Feature",
  "properties": {
    "iso:country":"CH",
    "sg:address":"G\u00e4uggelistrasse 2",
    "sg:city":"Chur",
    "sg:orig_category":"Kauf U Verkauf von Immobilien auf eigene Rechnung",
    "sg:phone":"+41 81 252 26 31",
    "sg:postcode":"7000",
    "sg:province":"Graubunden",
    "wof:name":"Li Lo Forum Ag",
    "wof:placetype":"venue"
},
  "geometry": {"coordinates":[9.5314321518,46.850856781],"type":"Point"}
}