{
  "type": "Feature",
  "properties": {
    "iso:country":"CH",
    "sg:address":"Hauptstrasse 72",
    "sg:city":"Einsiedeln",
    "sg:classifiers":[
        {
            "category":"Travel",
            "subcategory":"Hotels & Motels",
            "type":"Entertainment"
        }
    ],
    "sg:postcode":"8840",
    "sg:province":"Schwyz",
    "sg:tags":[
        "hotels",
        "mit",
        "restaurant"
    ],
    "wof:name":"Ochsner Dominik & Co.",
    "wof:placetype":"venue"
},
  "geometry": {"coordinates":[8.7492551804,47.1268424988],"type":"Point"}
}