{
  "type": "Feature",
  "properties": {
    "iso:country":"CH",
    "sg:address":"Riedstrasse 10",
    "sg:city":"Ermatingen",
    "sg:orig_category":"Architektur U Ingenieurb\u00fcros",
    "sg:phone":"+41 71 660 06 90",
    "sg:postcode":"8272",
    "sg:province":"Thurgau",
    "wof:name":"Singer J\u00f6rg, Dipl. Architekt Eth/sia, Architekturb\u00fcro Gmbh",
    "wof:placetype":"venue"
},
  "geometry": {"coordinates":[9.089306,47.669689],"type":"Point"}
}