{
  "type": "Feature",
  "properties": {
    "iso:country":"CH",
    "sg:address":"R\u00fctlistrasse 51",
    "sg:city":"Basel",
    "sg:orig_category":"Interessenvertretungen",
    "sg:phone":"+41 61 272 83 22",
    "sg:postcode":"4051",
    "sg:province":"Basel-Stadt",
    "wof:name":"Stiftung Basler Ballett-gilde",
    "wof:placetype":"venue"
},
  "geometry": {"coordinates":[7.5769510269,47.5543518066],"type":"Point"}
}