{
  "type": "Feature",
  "properties": {
    "iso:country":"CH",
    "sg:address":"Sonnhof Fenkrieden",
    "sg:city":"Aettenschwil",
    "sg:orig_category":"Verarbeitung von Milch Verwertung von Milch",
    "sg:postcode":"5645",
    "sg:province":"Aargau",
    "wof:name":"K\u00e4sereigenossenschaft Fischbach",
    "wof:placetype":"venue"
},
  "geometry": {"coordinates":[7.9108991623,47.1482391357],"type":"Point"}
}