{
  "type": "Feature",
  "properties": {
    "iso:country":"CH",
    "sg:address":"Stationsweg 15",
    "sg:city":"Tagelswangen",
    "sg:orig_category":"Unternehmensberatung",
    "sg:phone":"+41 52 343 50 65",
    "sg:postcode":"8317",
    "sg:province":"Z\u00fcrich",
    "wof:name":"P & W Consultants, Wegmann & Wegmann",
    "wof:placetype":"venue"
},
  "geometry": {"coordinates":[8.6759977341,47.4278717041],"type":"Point"}
}