{
  "type": "Feature",
  "properties": {
    "iso:country":"CH",
    "sg:address":"3001 Bern. Postfach 5744",
    "sg:city":"Bern",
    "sg:orig_category":"Sportvereine Ballsport Fussball",
    "sg:phone":"+41 79 418 71 06",
    "sg:postcode":"3001",
    "sg:province":"Bern",
    "wof:name":"Calcio Salento Fc",
    "wof:placetype":"venue"
},
  "geometry": {"coordinates":[6.1192398071,46.1778182983],"type":"Point"}
}