{
  "type": "Feature",
  "properties": {
    "iso:country":"CH",
    "sg:address":"Ch\u00e4lenweg",
    "sg:city":"Aathal-seegr\u00e4ben",
    "sg:orig_category":"Landwirtschaft, Jagd U damit verbundene Dienstleistungen",
    "sg:phone":"+41 19321754",
    "sg:postcode":"8607",
    "sg:province":"Z\u00fcrich",
    "wof:name":"Gutsbetrieb Streiff Ruedi Bachofen",
    "wof:placetype":"venue"
},
  "geometry": {"coordinates":[8.7693939209,47.3362312317],"type":"Point"}
}