{
  "type": "Feature",
  "properties": {
    "iso:country":"CH",
    "sg:address":"Untere Landstrasse Ehrikon",
    "sg:city":"Wildberg",
    "sg:orig_category":"Wirtschaftspr\u00fcfung, Steuerberatung U Treuhand",
    "sg:phone":"+41 52 385 41 41",
    "sg:postcode":"8321",
    "wof:name":"Macey Binder Elly, Consulting",
    "wof:placetype":"venue"
},
  "geometry": {"coordinates":[8.8089799881,47.4190406799],"type":"Point"}
}