{
  "type": "Feature",
  "properties": {
    "iso:country":"CH",
    "sg:address":"Avenue Des Vergers 20",
    "sg:city":"V\u00e9troz",
    "sg:classifiers":[
        {
            "category":"Restaurant",
            "type":"Food & Drink"
        }
    ],
    "sg:phone":"+41 27 346 10 11",
    "sg:postcode":"1963",
    "sg:province":"Valais",
    "wof:name":"Restaurant Madeleine",
    "wof:placetype":"venue"
},
  "geometry": {"coordinates":[7.2837791443,46.2240943909],"type":"Point"}
}