{
  "type": "Feature",
  "properties": {
    "iso:country":"CH",
    "sg:address":"Weidenbodenweg 1a",
    "sg:city":"Sissach",
    "sg:orig_category":"Innenausbau",
    "sg:phone":"+41 61 971 35 64",
    "sg:postcode":"4450",
    "sg:province":"Basel-Landschaft",
    "wof:name":"Andreas Sch\u00fcrch Ag Innenausbau",
    "wof:placetype":"venue"
},
  "geometry": {"coordinates":[7.8139681816,47.4639587402],"type":"Point"}
}