{
  "type": "Feature",
  "properties": {
    "iso:country":"CH",
    "sg:address":"Pr\u00e9-bersot 17",
    "sg:city":"Cornaux",
    "sg:classifiers":[
        {
            "category":"Manufacturing",
            "subcategory":"Motor Vehicles & Parts",
            "type":"Manufacturing & Wholesale Goods"
        }
    ],
    "sg:phone":"+41 32 758 75 00",
    "sg:postcode":"2087",
    "sg:province":"Neuch\u00e2tel",
    "sg:tags":[
        "precision",
        "mechanic"
    ],
    "wof:name":"Abrisa S.a.",
    "wof:placetype":"venue"
},
  "geometry": {"coordinates":[7.0246648788,47.0372657776],"type":"Point"}
}