{
  "type": "Feature",
  "properties": {
    "addr:full":"M\u00fcnstergasse 68 Bern Bern 3011",
    "addr:housenumber":"68",
    "addr:postcode":"3011",
    "addr:street":"Muenstergasse",
    "iso:country":"CH",
    "sg:address":"M\u00fcnstergasse 68",
    "sg:city":"Bern",
    "sg:orig_category":"Arztpraxen",
    "sg:phone":"+41 31 312 55 22",
    "sg:postcode":"3011",
    "sg:province":"Bern",
    "wof:name":"Dr.med. Harald F. Haas Spezialarzt Fmh",
    "wof:placetype":"venue"
},
  "geometry": {"coordinates":[7.448653,46.947578],"type":"Point"}
}