{
  "type": "Feature",
  "properties": {
    "iso:country":"CH",
    "sg:address":"Schallerstrasse 23",
    "sg:city":"S\u00f6renberg",
    "sg:orig_category":"Pensionen mit Restaurant",
    "sg:phone":"+41 41 488 16 93",
    "sg:postcode":"6174",
    "sg:province":"Luzern",
    "wof:name":"Pension Wicki",
    "wof:placetype":"venue"
},
  "geometry": {"coordinates":[8.0393743515,46.8214530945],"type":"Point"}
}