{
  "type": "Feature",
  "properties": {
    "iso:country":"CH",
    "sg:address":"Via Giovanni Serodine 3",
    "sg:city":"Lugano",
    "sg:orig_category":"Arztpraxen",
    "sg:phone":"+41 91 921 28 26",
    "sg:postcode":"6900",
    "sg:province":"Ticino",
    "wof:name":"Dott.med.maria-pia Gianinazzi Specialista Fmh",
    "wof:placetype":"venue"
},
  "geometry": {"coordinates":[8.939832,46.008064],"type":"Point"}
}