{
  "type": "Feature",
  "properties": {
    "iso:country":"CH",
    "sg:address":"Unterdorfstrasse 27",
    "sg:city":"Eschenz",
    "sg:orig_category":"Sportvereine Turnen",
    "sg:phone":"+41 52 741 31 05",
    "sg:postcode":"8264",
    "sg:province":"Thurgau",
    "wof:name":"M\u00e4nnerriege Eschenz",
    "wof:placetype":"venue"
},
  "geometry": {"coordinates":[8.8671474457,47.6524009705],"type":"Point"}
}