{
  "type": "Feature",
  "properties": {
    "iso:country":"CH",
    "sg:address":"Schneidergasse 27 4051 Basel. Postfach",
    "sg:city":"Basel",
    "sg:orig_category":"Detailhandel mit Brillen U anderen Sehhilfen",
    "sg:phone":"+41 32 351 17 02",
    "sg:postcode":"4001",
    "sg:province":"Basel-Stadt",
    "wof:name":"Horisberger Optik Ag",
    "wof:placetype":"venue"
},
  "geometry": {"coordinates":[7.372994,47.139843],"type":"Point"}
}