{
  "type": "Feature",
  "properties": {
    "iso:country":"CH",
    "sg:address":"W\u00fclflingerstrasse 59",
    "sg:city":"Winterthur",
    "sg:orig_category":"Datenverarbeitungsdienste Sonstige mit der Informatik verbundene T\u00e4tigkeiten",
    "sg:phone":"+41 52 222 76 66",
    "sg:postcode":"8400",
    "sg:province":"Z\u00fcrich",
    "wof:name":"Ips Ag Informatik Programming Services",
    "wof:placetype":"venue"
},
  "geometry": {"coordinates":[8.713571,47.506474],"type":"Point"}
}