{
  "type": "Feature",
  "properties": {
    "iso:country":"CH",
    "sg:address":"Rue De L'avenir 1",
    "sg:city":"Moutier",
    "sg:orig_category":"Versicherungen Generalagenturen",
    "sg:phone":"+41 32 493 56 06",
    "sg:postcode":"2740",
    "sg:province":"Bern",
    "wof:name":"Coop Assurance",
    "wof:placetype":"venue"
},
  "geometry": {"coordinates":[7.382581234,47.2798233032],"type":"Point"}
}