{
  "type": "Feature",
  "properties": {
    "iso:country":"CH",
    "sg:address":"Piazza Grande 55d",
    "sg:city":"Giubiasco",
    "sg:orig_category":"Gesundheitswesen",
    "sg:phone":"+41 41 630 38 80",
    "sg:postcode":"6512",
    "sg:province":"Ticino",
    "wof:name":"Andris Ruth",
    "wof:placetype":"venue"
},
  "geometry": {"coordinates":[8.3103265762,46.9977645874],"type":"Point"}
}