{
  "type": "Feature",
  "properties": {
    "iso:country":"CH",
    "sg:address":"Kreuzhofstrasse 27 9050 Appenzell. Postfach 159",
    "sg:city":"Appenzell",
    "sg:orig_category":"Grosshandel mit Textilien",
    "sg:phone":"+41 81 750 57 57",
    "sg:postcode":"9050",
    "sg:province":"Appenzell Innerhoden",
    "wof:name":"Helbling.",
    "wof:placetype":"venue"
},
  "geometry": {"coordinates":[9.4746446609,47.1665039062],"type":"Point"}
}