{
  "type": "Feature",
  "properties": {
    "iso:country":"CH",
    "sg:address":"Avenue De Sainte-clotilde 9",
    "sg:city":"Gen\u00e8ve",
    "sg:orig_category":"HOTELS: MIT RESTAURANT Kongress- and Tagungshotels mit Restaurant",
    "sg:phone":"+41 21 925 11 11",
    "sg:postcode":"1205",
    "sg:province":"Gen\u00e8ve",
    "wof:name":"H\u00f4tel Le Mirador",
    "wof:placetype":"venue"
},
  "geometry": {"coordinates":[6.8375020027,46.4779281616],"type":"Point"}
}