{
  "type": "Feature",
  "properties": {
    "iso:country":"CH",
    "sg:address":"Textilstrasse 2",
    "sg:city":"Arbon",
    "sg:orig_category":"Unclassifiable Establishments",
    "sg:phone":"+41 71 447 52 82",
    "sg:postcode":"9320",
    "sg:province":"Thurgau",
    "wof:name":"Aktiengesellschaft Adolph Saurer",
    "wof:placetype":"venue"
},
  "geometry": {"coordinates":[9.4325752258,47.5072555542],"type":"Point"}
}