{
  "type": "Feature",
  "properties": {
    "iso:country":"CH",
    "sg:address":"Via San Gottardo 271",
    "sg:city":"Tenero",
    "sg:orig_category":"Bauingenieurb\u00fcros allgemein",
    "sg:phone":"+41 91 745 41 37",
    "sg:postcode":"6598",
    "sg:province":"Ticino",
    "wof:name":"Peppino Bondietti Studio D'ingegneria",
    "wof:placetype":"venue"
},
  "geometry": {"coordinates":[8.85291,46.182331],"type":"Point"}
}