{
  "type": "Feature",
  "properties": {
    "iso:country":"CH",
    "sg:address":"Rue Des Bouchers 2 1700 Fribourg Case Postale 86",
    "sg:city":"Fribourg",
    "sg:classifiers":[
        {
            "category":"Restaurant",
            "type":"Food & Drink"
        }
    ],
    "sg:phone":"+41 26 322 32 04",
    "sg:postcode":"1702",
    "sg:province":"Fribourg",
    "wof:name":"Restaurant Du Cygne & Schwanen",
    "wof:placetype":"venue"
},
  "geometry": {"coordinates":[7.1643958092,46.8057365417],"type":"Point"}
}