{
  "type": "Feature",
  "properties": {
    "iso:country":"CH",
    "sg:address":"Gr\u00fcndenstrasse 82",
    "sg:city":"Flurlingen",
    "sg:orig_category":"Wirtschaftspr\u00fcfung, Steuerberatung U Treuhand",
    "sg:phone":"+41 52 659 15 95",
    "sg:postcode":"8247",
    "sg:province":"Z\u00fcrich",
    "wof:name":"Risch Versicherungstreuhand",
    "wof:placetype":"venue"
},
  "geometry": {"coordinates":[8.6259412766,47.6893997192],"type":"Point"}
}