{
  "type": "Feature",
  "properties": {
    "iso:country":"CH",
    "sg:address":"4132",
    "sg:city":"Muttenz",
    "sg:orig_category":"Religi\u00f6se Vereinigungen divers",
    "sg:postcode":"4132",
    "sg:province":"Basel-Landschaft",
    "wof:name":"Katholischer Kultusverein",
    "wof:placetype":"venue"
},
  "geometry": {"coordinates":[7.6478300095,47.5212211609],"type":"Point"}
}