{
  "type": "Feature",
  "properties": {
    "iso:country":"CH",
    "sg:address":"Lac Rue Du 1815 Clarens Case Postale 517",
    "sg:city":"Clarens",
    "sg:orig_category":"Elektrizit\u00e4tsversorgung",
    "sg:phone":"+41 21 989 11 11",
    "sg:postcode":"1815",
    "sg:province":"Vaud",
    "wof:name":"Romande Energie Sa",
    "wof:placetype":"venue"
},
  "geometry": {"coordinates":[6.8908047676,46.4409446716],"type":"Point"}
}