{
  "type": "Feature",
  "properties": {
    "addr:full":"Sonnhaldenstrasse 6 Kerzers Fribourg 3210",
    "addr:housenumber":"6",
    "addr:postcode":"3210",
    "addr:street":"Sonnhaldenstrasse",
    "iso:country":"CH",
    "sg:address":"Sonnhaldenstrasse 6",
    "sg:city":"Kerzers",
    "sg:orig_category":"Bauspenglerei Zimmerei, Dachdeckerei, Bauspenglerei U Abdichtung",
    "sg:phone":"+41 31 755 55 58",
    "sg:postcode":"3210",
    "sg:province":"Fribourg",
    "wof:name":"Hans Munz Kerzers Ag",
    "wof:placetype":"venue"
},
  "geometry": {"coordinates":[7.202381,46.974297],"type":"Point"}
}