{
  "type": "Feature",
  "properties": {
    "iso:country":"CH",
    "sg:address":"Place Clapar\u00e8de 3",
    "sg:city":"Gen\u00e8ve",
    "sg:orig_category":"Internationale Organisationen mit Beh\u00f6rdecharakter Organisationen der Wohlfahrtspflege",
    "sg:phone":"+41 22 346 86 87",
    "sg:postcode":"1205",
    "sg:province":"Gen\u00e8ve",
    "wof:name":"Comit\u00e9 International De L'ordre Souverain De Malte",
    "wof:placetype":"venue"
},
  "geometry": {"coordinates":[6.1502170563,46.1959457397],"type":"Point"}
}