{
  "type": "Feature",
  "properties": {
    "iso:country":"CH",
    "sg:address":"Kirchbodenstrasse 64",
    "sg:city":"Thalwil",
    "sg:orig_category":"Architektur U Ingenieurb\u00fcros",
    "sg:postcode":"8800",
    "sg:province":"Z\u00fcrich",
    "wof:name":"Meier-bukowiecki Yvonne",
    "wof:placetype":"venue"
},
  "geometry": {"coordinates":[8.569799,47.291439],"type":"Point"}
}