{
  "type": "Feature",
  "properties": {
    "iso:country":"CH",
    "sg:address":"Rue Pr\u00e9vost-martin 59 1205 Gen\u00e8ve. Postfach",
    "sg:city":"Gen\u00e8ve",
    "sg:orig_category":"Autogaragen Instandhaltung U Reparatur von Automobilen",
    "sg:phone":"+41 32 652 34 77",
    "sg:postcode":"1201",
    "sg:province":"Gen\u00e8ve",
    "wof:name":"Garage Redigolo",
    "wof:placetype":"venue"
},
  "geometry": {"coordinates":[7.368198,47.183887],"type":"Point"}
}