{
  "type": "Feature",
  "properties": {
    "iso:country":"CH",
    "sg:address":"Talackerstrasse 53a",
    "sg:city":"Glattbrugg",
    "sg:orig_category":"Sportvereine Ballsport Tennis",
    "sg:phone":"+41 81 868 54 60",
    "sg:postcode":"8152",
    "sg:province":"Z\u00fcrich",
    "wof:name":"Sport-& Tennisclub",
    "wof:placetype":"venue"
},
  "geometry": {"coordinates":[10.3613004684,46.9444885254],"type":"Point"}
}