{
  "type": "Feature",
  "properties": {
    "iso:country":"CH",
    "sg:address":"Gersauerstrasse 10 Brunnen 6440 Ingenbohl. Postfach",
    "sg:city":"Brunnen",
    "sg:orig_category":"RESTAURANTS: TEA-ROOMS",
    "sg:postcode":"6440",
    "sg:province":"Schwyz",
    "wof:name":"Musik-beiz L\u00f6wen, J. Huber",
    "wof:placetype":"venue"
},
  "geometry": {"coordinates":[8.8261098862,47.5652198792],"type":"Point"}
}