{
  "type": "Feature",
  "properties": {
    "iso:country":"CH",
    "sg:address":"Z\u00fcrcherstrasse 16 8852 Altendorf. Postfach",
    "sg:city":"Altendorf",
    "sg:orig_category":"Finanzierungsinstitutionen",
    "sg:phone":"+41 55 442 69 42",
    "sg:postcode":"8852",
    "sg:province":"Schwyz",
    "wof:name":"Fical-finanzierungs-genossenschaft",
    "wof:placetype":"venue"
},
  "geometry": {"coordinates":[8.8278093338,47.1929321289],"type":"Point"}
}