{
  "type": "Feature",
  "properties": {
    "iso:country":"CH",
    "sg:address":"Hinterdorf",
    "sg:city":"Eriswil",
    "sg:orig_category":"Fahrschulen, Flugschulen",
    "sg:phone":"+41 79 215 52 52",
    "sg:postcode":"4952",
    "sg:province":"Bern",
    "wof:name":"Roland Fiechter",
    "wof:placetype":"venue"
},
  "geometry": {"coordinates":[7.8571438789,47.0698661804],"type":"Point"}
}