{
  "type": "Feature",
  "properties": {
    "iso:country":"CH",
    "sg:address":"Kornfeldstrasse 2 6210 Sursee. Postfach 3089",
    "sg:city":"Sursee",
    "sg:orig_category":"Grosshandel mit Getreide, Saatgut U Futtermitteln",
    "sg:phone":"+41 41 920 21 10",
    "sg:postcode":"6210",
    "sg:province":"Luzern",
    "wof:name":"Landi Nidwalden",
    "wof:placetype":"venue"
},
  "geometry": {"coordinates":[8.1022567749,47.1767654419],"type":"Point"}
}