{
  "type": "Feature",
  "properties": {
    "iso:country":"CH",
    "sg:address":"Faubourg Ph.-suchard 36",
    "sg:city":"Boudry",
    "sg:orig_category":"RESTAURANTS: TEA-ROOMS",
    "sg:postcode":"2017",
    "sg:province":"Neuch\u00e2tel",
    "wof:name":"Grande Lorenzo",
    "wof:placetype":"venue"
},
  "geometry": {"coordinates":[6.8316960335,46.9554023743],"type":"Point"}
}