{
  "type": "Feature",
  "properties": {
    "iso:country":"CH",
    "sg:address":"Ebnaterstrasse 143 9630 Wattwil. Postfach",
    "sg:city":"Ulisbach",
    "sg:orig_category":"Architektur U Ingenieurb\u00fcros",
    "sg:phone":"+41 71 987 60 40",
    "sg:postcode":"9631",
    "sg:province":"St. Gallen",
    "wof:name":"Sch\u00e4llibaum Bau Und Projektmanagement Ag",
    "wof:placetype":"venue"
},
  "geometry": {"coordinates":[9.098878,47.291069],"type":"Point"}
}