{
  "type": "Feature",
  "properties": {
    "addr:full":"Fringeliweg 21 B\u00e4rschwil Solothurn 4252",
    "addr:housenumber":"21",
    "addr:postcode":"4252",
    "addr:street":"Fringeliweg;Solothurn",
    "iso:country":"CH",
    "sg:address":"Fringeliweg 21",
    "sg:city":"B\u00e4rschwil",
    "sg:classifiers":[
        {
            "category":"Banks & Credit Unions",
            "subcategory":"Bank",
            "type":"Services"
        }
    ],
    "sg:phone":"+41 61 761 34 20",
    "sg:postcode":"4252",
    "sg:province":"Solothurn",
    "wof:name":"Raiffeisenbank B\u00e4rschwil",
    "wof:placetype":"venue"
},
  "geometry": {"coordinates":[7.472553,47.381302],"type":"Point"}
}