{
  "type": "Feature",
  "properties": {
    "iso:country":"CH",
    "sg:address":"Chemin Plein-vent 23",
    "sg:city":"Plan-les-ouates",
    "sg:orig_category":"Detailhandel mit Antiquit\u00e4ten",
    "sg:phone":"+41 79 250 60 16",
    "sg:postcode":"1228",
    "sg:province":"Gen\u00e8ve",
    "wof:name":"Genevi\u00e8ve Yersin Domaine De Plein-vent Antiq.",
    "wof:placetype":"venue"
},
  "geometry": {"coordinates":[6.111244,46.159653],"type":"Point"}
}