{
  "type": "Feature",
  "properties": {
    "iso:country":"CH",
    "sg:address":"Lampertji 3945 Gampel. Postfach",
    "sg:city":"Gampel",
    "sg:orig_category":"Herstellung von sonstigen Metallwaren",
    "sg:phone":"+41 27 932 20 72",
    "sg:postcode":"3945",
    "sg:province":"Valais",
    "wof:name":"Zeico Construction Ag Sicherheitstechnik & Metallbau",
    "wof:placetype":"venue"
},
  "geometry": {"coordinates":[7.7442688942,46.3080291748],"type":"Point"}
}