{
  "type": "Feature",
  "properties": {
    "iso:country":"CH",
    "sg:address":"Saleggi Via Ai 34",
    "sg:city":"Locarno",
    "sg:orig_category":"Unclassifiable Establishments",
    "sg:phone":"+41 91 751 41 03",
    "sg:postcode":"6600",
    "sg:province":"Ticino",
    "wof:name":"Terron E Blanco",
    "wof:placetype":"venue"
},
  "geometry": {"coordinates":[8.7944364548,46.1629142761],"type":"Point"}
}