{
  "type": "Feature",
  "properties": {
    "iso:country":"CH",
    "sg:address":"Kirchgasse 11",
    "sg:city":"Oensingen",
    "sg:classifiers":[
        {
            "category":"Building & Trades",
            "subcategory":"Construction",
            "type":"Services"
        }
    ],
    "sg:phone":"+41 62 396 34 00",
    "sg:postcode":"4702",
    "sg:province":"Solothurn",
    "sg:tags":[
        "flat",
        "steep",
        "roof",
        "waterproofing"
    ],
    "wof:name":"K. Schwarzenbach Ag",
    "wof:placetype":"venue"
},
  "geometry": {"coordinates":[7.7250151634,47.2911529541],"type":"Point"}
}