{
  "type": "Feature",
  "properties": {
    "iso:country":"CH",
    "sg:address":"Bahnhofstrasse 2",
    "sg:city":"Lyss",
    "sg:orig_category":"Detailhandel mit Brot, Back U S\u00fcsswaren",
    "sg:phone":"+41 32 384 53 11",
    "sg:postcode":"3250",
    "sg:province":"Bern",
    "wof:name":"Michael Rogen Lyssbach Beck",
    "wof:placetype":"venue"
},
  "geometry": {"coordinates":[7.306569,47.074902],"type":"Point"}
}