{
  "type": "Feature",
  "properties": {
    "iso:country":"CH",
    "sg:address":"Bernstrasse 3 3110 M\u00fcnsingen. Postfach 1060",
    "sg:city":"M\u00fcnsingen",
    "sg:orig_category":"Versicherungen Generalagenturen",
    "sg:phone":"+41 31 721 47 47",
    "sg:postcode":"3110",
    "sg:province":"Bern",
    "wof:name":"Winterthur-versicherungen Generalagentur",
    "wof:placetype":"venue"
},
  "geometry": {"coordinates":[7.562335968,46.8757629395],"type":"Point"}
}