{
  "type": "Feature",
  "properties": {
    "iso:country":"CH",
    "sg:address":"Piazza Muraccio 8 6600 Locarno. Postfach",
    "sg:city":"Locarno",
    "sg:orig_category":"Detailhandel mit B\u00fcchern, Zeitungen, Schreib U Papeteriewaren",
    "sg:postcode":"6600",
    "sg:province":"Ticino",
    "wof:name":"Mazzoni Sa",
    "wof:placetype":"venue"
},
  "geometry": {"coordinates":[8.795708,46.168053],"type":"Point"}
}