{
  "type": "Feature",
  "properties": {
    "iso:country":"CH",
    "sg:address":"Niederhaslistrasse 144 8105 Watt. Postfach",
    "sg:city":"Watt",
    "sg:orig_category":"Grosshandel mit sonstigen Konsumg\u00fctern",
    "sg:phone":"+41 18400327",
    "sg:postcode":"8105",
    "sg:province":"Z\u00fcrich",
    "wof:name":"Milab H.p.bertschi Haushaltartikel Engros",
    "wof:placetype":"venue"
},
  "geometry": {"coordinates":[8.4855461121,47.4487190247],"type":"Point"}
}