{
  "type": "Feature",
  "properties": {
    "iso:country":"CH",
    "sg:address":"Henauerstrasse 11",
    "sg:city":"Niederuzwil",
    "sg:orig_category":"Druck ohne Zeitungsdruck Verlagsgewerbe",
    "sg:phone":"+41 71 951 36 33",
    "sg:postcode":"9244",
    "sg:province":"St. Gallen",
    "wof:name":"Druckerei Raschle",
    "wof:placetype":"venue"
},
  "geometry": {"coordinates":[9.1405353546,47.4452781677],"type":"Point"}
}