{
  "type": "Feature",
  "properties": {
    "iso:country":"CH",
    "sg:address":"Tanneurs Rue Des 5",
    "sg:city":"Pruntrut",
    "sg:orig_category":"Wirtschaftspr\u00fcfung, Steuerberatung U Treuhand",
    "sg:phone":"+41 22 704 15 15",
    "sg:postcode":"2900",
    "sg:province":"Jura",
    "wof:name":"Kpmg Fides",
    "wof:placetype":"venue"
},
  "geometry": {"coordinates":[6.1612529755,46.1893043518],"type":"Point"}
}