{
  "type": "Feature",
  "properties": {
    "iso:country":"CH",
    "sg:address":"Kirchweg 208 4719 Ramiswil. Postfach",
    "sg:city":"Ramiswil",
    "sg:orig_category":"Non-Classified Establishments",
    "sg:postcode":"4719",
    "sg:province":"Solothurn",
    "wof:name":"Elektra Guldenthal",
    "wof:placetype":"venue"
},
  "geometry": {"coordinates":[7.6598720551,47.3456993103],"type":"Point"}
}