{
  "type": "Feature",
  "properties": {
    "iso:country":"CH",
    "sg:address":"Pulverm\u00fchlestrasse 48",
    "sg:city":"Chur",
    "sg:classifiers":[
        {
            "category":"Bars & Pubs",
            "type":"Food & Drink"
        }
    ],
    "sg:postcode":"7000",
    "sg:province":"Graubunden",
    "wof:name":"F1 Gmbh Bar Usw",
    "wof:placetype":"venue"
},
  "geometry": {"coordinates":[9.514448,46.852688],"type":"Point"}
}