{
  "type": "Feature",
  "properties": {
    "iso:country":"CH",
    "sg:address":"Schwarzackerstrasse 8",
    "sg:city":"Wallisellen",
    "sg:orig_category":"Non-Classified Establishments",
    "sg:postcode":"8304",
    "sg:province":"Z\u00fcrich",
    "wof:name":"Globalwealth Consulting Gmbh",
    "wof:placetype":"venue"
},
  "geometry": {"coordinates":[8.5903186798,47.4134025574],"type":"Point"}
}