{
  "type": "Feature",
  "properties": {
    "iso:country":"CH",
    "sg:address":"8228",
    "sg:city":"Beggingen",
    "sg:orig_category":"Primarschulen",
    "sg:phone":"+41 52 680 17 50",
    "sg:postcode":"8228",
    "sg:province":"Schaffhausen",
    "wof:name":"Primarschule",
    "wof:placetype":"venue"
},
  "geometry": {"coordinates":[8.5369205475,47.7667694092],"type":"Point"}
}