{
  "type": "Feature",
  "properties": {
    "addr:full":"Mitteldorfstr. 25 Ossingen Z\u00fcrich 8475",
    "addr:housenumber":"25",
    "addr:postcode":"8475",
    "addr:street":"Mitteldorfstr.",
    "iso:country":"CH",
    "sg:address":"Mitteldorfstr. 25",
    "sg:city":"Ossingen",
    "sg:classifiers":[
        {
            "category":"Banks & Credit Unions",
            "subcategory":"Bank",
            "type":"Services"
        }
    ],
    "sg:phone":"+41 52 317 18 14",
    "sg:postcode":"8475",
    "sg:province":"Z\u00fcrich",
    "wof:name":"Z\u00fcrcher Kantonalbank, Landi",
    "wof:placetype":"venue"
},
  "geometry": {"coordinates":[8.726293,47.61121],"type":"Point"}
}