{
  "type": "Feature",
  "properties": {
    "iso:country":"CH",
    "sg:address":"Bretzwilerstr. 11",
    "sg:city":"Nunningen",
    "sg:orig_category":"Fachdetailhandel in Verkaufsr\u00e4umen",
    "sg:phone":"+41 61 791 06 61",
    "sg:postcode":"4208",
    "sg:province":"Solothurn",
    "wof:name":"Jeger Dora",
    "wof:placetype":"venue"
},
  "geometry": {"coordinates":[7.6209301949,47.3937988281],"type":"Point"}
}