{
  "type": "Feature",
  "properties": {
    "iso:country":"CH",
    "sg:address":"General-guisanstrasse 27a",
    "sg:city":"Interlaken",
    "sg:orig_category":"Fachdetailhandel in Verkaufsr\u00e4umen",
    "sg:phone":"+41 32 841 75 85",
    "sg:postcode":"3800",
    "sg:province":"Bern",
    "wof:name":"Lambelet Diffusion Articles De Sports, De Loisirs; Import., Diffusion, Achat, Vente Etc",
    "wof:placetype":"venue"
},
  "geometry": {"coordinates":[6.8602528572,46.9589805603],"type":"Point"}
}