{
  "type": "Feature",
  "properties": {
    "iso:country":"CH",
    "sg:address":"Morges Route De 23 1162 St-prex. Postfach",
    "sg:city":"St-prex",
    "sg:orig_category":"Vermietung U Verpachtung von eigenen Immobilien",
    "sg:phone":"+41 21 903 28 88",
    "sg:postcode":"1162",
    "sg:province":"Vaud",
    "wof:name":"Aim Sa",
    "wof:placetype":"venue"
},
  "geometry": {"coordinates":[6.7640500069,46.5876998901],"type":"Point"}
}