{
  "type": "Feature",
  "properties": {
    "iso:country":"CH",
    "sg:address":"Chollerstr. 4",
    "sg:city":"Zug",
    "sg:classifiers":[
        {
            "category":"Food Court",
            "type":"Food & Drink"
        }
    ],
    "sg:phone":"+41 41 748 51 51",
    "sg:postcode":"6300",
    "sg:province":"Zug",
    "sg:tags":[
        "product",
        "related"
    ],
    "wof:name":"Etter S\u00d6hne Ag",
    "wof:placetype":"venue"
},
  "geometry": {"coordinates":[8.4850912094,47.1828422546],"type":"Point"}
}