{
  "type": "Feature",
  "properties": {
    "addr:full":"Unterdorf Winikon Luzern 6235",
    "addr:postcode":"6235",
    "addr:street":"Unterdorf",
    "iso:country":"CH",
    "sg:address":"Unterdorf",
    "sg:city":"Winikon",
    "sg:orig_category":"Allgemeiner Hoch U Tiefbau",
    "sg:postcode":"6235",
    "sg:province":"Luzern",
    "wof:name":"M\u00fcller Valentin Bauunternehmung",
    "wof:placetype":"venue"
},
  "geometry": {"coordinates":[8.05367,47.238632],"type":"Point"}
}