{
  "type": "Feature",
  "properties": {
    "iso:country":"CH",
    "sg:address":"Feldstrasse 16",
    "sg:city":"Mellingen",
    "sg:orig_category":"Handelsvermittlung U Grosshandel Sonstiger Grosshandel",
    "sg:phone":"+41 17812260",
    "sg:postcode":"5507",
    "sg:province":"Aargau",
    "wof:name":"Cinatronic Import, Export, Vertrieb, Versand, Service, Litscher T., Au",
    "wof:placetype":"venue"
},
  "geometry": {"coordinates":[8.6308517456,47.2498168945],"type":"Point"}
}