{
  "type": "Feature",
  "properties": {
    "iso:country":"CH",
    "sg:address":"Via Frontini 1",
    "sg:city":"Viganello",
    "sg:orig_category":"Wasserversorgung",
    "sg:postcode":"6962",
    "sg:province":"Ticino",
    "wof:name":"Azienda Acqua Potabile Comune Di Viganello",
    "wof:placetype":"venue"
},
  "geometry": {"coordinates":[8.9673910141,46.0128173828],"type":"Point"}
}