{
  "type": "Feature",
  "properties": {
    "iso:country":"CH",
    "sg:address":"Brunngasse 16",
    "sg:city":"B\u00fclach",
    "sg:orig_category":"Dachdeckerei",
    "sg:phone":"+41 18601116",
    "sg:postcode":"8180",
    "sg:province":"Z\u00fcrich",
    "wof:name":"Emil Bigler Erben Dachdeckergesch\u00e4ft",
    "wof:placetype":"venue"
},
  "geometry": {"coordinates":[8.542475,47.517864],"type":"Point"}
}