{
  "type": "Feature",
  "properties": {
    "iso:country":"CH",
    "sg:address":"8783",
    "sg:city":"Linthal",
    "sg:orig_category":"Vereine Damen Vereine Gesang",
    "sg:postcode":"8783",
    "sg:province":"Glarus",
    "wof:name":"T\u00f6chterchor Lohn",
    "wof:placetype":"venue"
},
  "geometry": {"coordinates":[7.5248098373,47.1698112488],"type":"Point"}
}