{
  "type": "Feature",
  "properties": {
    "iso:country":"CH",
    "sg:address":"Neuweilerstrasse 44 4054 Basel. Postfach",
    "sg:city":"Basel",
    "sg:orig_category":"Herstellung von konfektionierten Textilwaren ohne Bekleidung",
    "sg:phone":"+41 61 302 25 37",
    "sg:postcode":"4051",
    "sg:province":"Basel-Stadt",
    "wof:name":"Atelier Z Dora Zimmermann Schneideratelier",
    "wof:placetype":"venue"
},
  "geometry": {"coordinates":[7.5618457794,47.5465278625],"type":"Point"}
}