{
  "type": "Feature",
  "properties": {
    "iso:country":"CH",
    "sg:address":"Hauptgasse 6",
    "sg:city":"Lichtensteig",
    "sg:orig_category":"Detailhandel mit Bekleidung Detailhandel mit Textilien",
    "sg:phone":"+41 71 988 14 85",
    "sg:postcode":"9620",
    "sg:province":"St. Gallen",
    "wof:name":"Fritz Forrer & Co Mode & Stoffe",
    "wof:placetype":"venue"
},
  "geometry": {"coordinates":[9.087287,47.323799],"type":"Point"}
}