{
  "type": "Feature",
  "properties": {
    "iso:country":"CH",
    "sg:address":"Bahnhofstrasse 1 6300 Zug. Postfach",
    "sg:city":"Zug",
    "sg:orig_category":"Reiseb\u00fcros U Reiseveranstalter",
    "sg:phone":"+41 81 756 71 71",
    "sg:postcode":"6301",
    "sg:province":"Zug",
    "wof:name":"Bta Travel Ag Reiseb\u00fcro",
    "wof:placetype":"venue"
},
  "geometry": {"coordinates":[9.4764175415,47.1665878296],"type":"Point"}
}