{
  "type": "Feature",
  "properties": {
    "iso:country":"CH",
    "sg:address":"Im Grund 38 2500 Biel/bienne. Postfach",
    "sg:city":"Biel/bienne",
    "sg:orig_category":"Fachdetailhandel in Verkaufsr\u00e4umen",
    "sg:postcode":"2502",
    "sg:province":"Bern",
    "wof:name":"Canis Major S\u00e0rl",
    "wof:placetype":"venue"
},
  "geometry": {"coordinates":[7.2635669708,47.1482048035],"type":"Point"}
}