{
  "type": "Feature",
  "properties": {
    "iso:country":"CH",
    "sg:address":"Riedweg 14 8600 D\u00fcbendorf. Postfach",
    "sg:city":"D\u00fcbendorf",
    "sg:orig_category":"Unclassifiable Establishments",
    "sg:postcode":"8600",
    "sg:province":"Z\u00fcrich",
    "wof:name":"X-welt Gmbh, 9000 St. Gallen Internet-anschl\u00fcsse; Installation, Vermietung",
    "wof:placetype":"venue"
},
  "geometry": {"coordinates":[9.3937196732,47.4282455444],"type":"Point"}
}