{
  "type": "Feature",
  "properties": {
    "iso:country":"CH",
    "sg:address":"8926",
    "sg:city":"Uerzlikon",
    "sg:orig_category":"Detailhandel mit Beleuchtungs U Haushaltsgegenst\u00e4nden Detailhandel mit Radio U Fernsehger\u00e4ten",
    "sg:phone":"+41 17641683",
    "sg:postcode":"8926",
    "sg:province":"Z\u00fcrich",
    "wof:name":"Urs Vollenweider Haushaltger\u00e4te",
    "wof:placetype":"venue"
},
  "geometry": {"coordinates":[8.49778,47.222809],"type":"Point"}
}