{
  "type": "Feature",
  "properties": {
    "iso:country":"CH",
    "sg:address":"Waldschluecht",
    "sg:city":"Wengen",
    "sg:orig_category":"Detailhandel mit Blumen U Pflanzen",
    "sg:phone":"+41 31 981 36 74",
    "sg:postcode":"3823",
    "sg:province":"Bern",
    "wof:name":"Hanny Kammermann Blumenboutique",
    "wof:placetype":"venue"
},
  "geometry": {"coordinates":[7.361503,46.917347],"type":"Point"}
}