{
  "type": "Feature",
  "properties": {
    "iso:country":"CH",
    "sg:address":"Lausanne Rue De 70",
    "sg:city":"Fribourg",
    "sg:classifiers":[
        {
            "category":"Communications",
            "subcategory":"Radio Station",
            "type":"Services"
        }
    ],
    "sg:phone":"+41 26 322 07 36",
    "sg:postcode":"1700",
    "sg:province":"Fribourg",
    "sg:tags":[
        "fernsehanstalten",
        "u"
    ],
    "wof:name":"Eclats Multiples S\u00e0rl",
    "wof:placetype":"venue"
},
  "geometry": {"coordinates":[7.1579608917,46.8053779602],"type":"Point"}
}