{
  "type": "Feature",
  "properties": {
    "iso:country":"CH",
    "sg:address":"Chemin Du Paradis 2",
    "sg:city":"Blonay",
    "sg:orig_category":"Landschaftsplanungsb\u00fcros U Gartenarchitekturb\u00fcros",
    "sg:phone":"+41 21 943 16 17",
    "sg:postcode":"1807",
    "sg:province":"Vaud",
    "wof:name":"Yves Maridor Paysagiste & Horticulture",
    "wof:placetype":"venue"
},
  "geometry": {"coordinates":[6.8806118965,46.4625167847],"type":"Point"}
}