{
  "type": "Feature",
  "properties": {
    "iso:country":"CH",
    "sg:address":"Dorfgasse 64",
    "sg:city":"Niederdorf",
    "sg:orig_category":"Herstellung von sonstigen Maschinen f\u00fcr unspezifische Verwendung",
    "sg:phone":"+41 19501168",
    "sg:postcode":"4435",
    "sg:province":"Basel-Landschaft",
    "wof:name":"Flameless Feuerschutz Gmbh",
    "wof:placetype":"venue"
},
  "geometry": {"coordinates":[8.7872781754,47.3635253906],"type":"Point"}
}