{
  "type": "Feature",
  "properties": {
    "iso:country":"CH",
    "sg:address":"Piazza Franscini",
    "sg:city":"Faido",
    "sg:classifiers":[
        {
            "category":"Banks & Credit Unions",
            "subcategory":"Bank",
            "type":"Services"
        }
    ],
    "sg:phone":"+41 91 873 59 11",
    "sg:postcode":"6760",
    "sg:province":"Ticino",
    "wof:name":"Cr\u00e9dit Suisse, Pineza Stefano Fransciai",
    "wof:placetype":"venue"
},
  "geometry": {"coordinates":[8.794981,46.47945],"type":"Point"}
}