{
  "type": "Feature",
  "properties": {
    "iso:country":"CH",
    "sg:address":"Bernex-en-combes 30",
    "sg:city":"Bernex",
    "sg:orig_category":"Herstellung von Hohlglas",
    "sg:phone":"+41 22 777 16 38",
    "sg:postcode":"1233",
    "sg:province":"Gen\u00e8ve",
    "wof:name":"Magma, Rey Jo\u00ebl",
    "wof:placetype":"venue"
},
  "geometry": {"coordinates":[6.080945015,46.1791000366],"type":"Point"}
}