{
  "type": "Feature",
  "properties": {
    "iso:country":"CH",
    "sg:address":"Gubelstrasse 2",
    "sg:city":"Z\u00fcrich",
    "sg:orig_category":"Zahntechnische Laboratorien",
    "sg:phone":"+41 31 351 15 41",
    "sg:postcode":"8050",
    "sg:province":"Z\u00fcrich",
    "wof:name":"Pauli & Co Zahntechnisches-labor",
    "wof:placetype":"venue"
},
  "geometry": {"coordinates":[7.470348835,46.9362335205],"type":"Point"}
}