{
  "type": "Feature",
  "properties": {
    "iso:country":"CH",
    "sg:address":"Zugerstrasse 57",
    "sg:city":"Baar",
    "sg:orig_category":"Non-Classified Establishments",
    "sg:phone":"+41 41 726 85 85",
    "sg:postcode":"6340",
    "sg:province":"Zug",
    "wof:name":"Partners Group Holding Beteiligungen Usw",
    "wof:placetype":"venue"
},
  "geometry": {"coordinates":[8.520731926,47.1853408813],"type":"Point"}
}