{
  "type": "Feature",
  "properties": {
    "iso:country":"CH",
    "sg:address":"4053",
    "sg:city":"Basel",
    "sg:orig_category":"Grosshandel mit elektrischen Haushaltsger\u00e4ten",
    "sg:phone":"+41 61 331 32 40",
    "sg:postcode":"4053",
    "sg:province":"Basel-Stadt",
    "wof:name":"M. Schaerer Ag Kaffeemaschinen",
    "wof:placetype":"venue"
},
  "geometry": {"coordinates":[7.5971298218,47.5378684998],"type":"Point"}
}