{
  "type": "Feature",
  "properties": {
    "iso:country":"CH",
    "sg:address":"Solothurnerstrasse 58a",
    "sg:city":"Luterbach",
    "sg:orig_category":"Sonstige mit der Informatik verbundene T\u00e4tigkeiten",
    "sg:phone":"+41 32 682 32 50",
    "sg:postcode":"4542",
    "sg:province":"Solothurn",
    "wof:name":"Dance Soft Gmbh",
    "wof:placetype":"venue"
},
  "geometry": {"coordinates":[7.5790271759,47.2138633728],"type":"Point"}
}