{
  "type": "Feature",
  "properties": {
    "iso:country":"CH",
    "sg:address":"Gartenhofstrasse 1",
    "sg:city":"Z\u00fcrich",
    "sg:orig_category":"RESTAURANTS: TEA-ROOMS",
    "sg:phone":"+41 12424949",
    "sg:postcode":"8004",
    "sg:province":"Z\u00fcrich",
    "wof:name":"Divine Gmbh",
    "wof:placetype":"venue"
},
  "geometry": {"coordinates":[8.5257854462,47.3718566895],"type":"Point"}
}