{
  "type": "Feature",
  "properties": {
    "iso:country":"CH",
    "sg:address":"Viale Stazione 11",
    "sg:city":"Bellinzona",
    "sg:orig_category":"Telecomshops",
    "sg:phone":"+41 91 807 52 06",
    "sg:postcode":"6500",
    "sg:province":"Ticino",
    "wof:name":"Swisscom-shop",
    "wof:placetype":"venue"
},
  "geometry": {"coordinates":[9.0247650146,46.1928863525],"type":"Point"}
}