{
  "type": "Feature",
  "properties": {
    "iso:country":"CH",
    "sg:address":"Auberge Communale",
    "sg:city":"Pampigny",
    "sg:classifiers":[
        {
            "category":"Restaurant",
            "type":"Food & Drink"
        }
    ],
    "sg:phone":"+41 21 800 35 09",
    "sg:postcode":"1142",
    "sg:province":"Vaud",
    "wof:name":"Auberge Du Ch\u00eane",
    "wof:placetype":"venue"
},
  "geometry": {"coordinates":[6.4278230667,46.5800819397],"type":"Point"}
}