{
  "type": "Feature",
  "properties": {
    "iso:country":"CH",
    "sg:address":"Rebgasse 78 4102 Binningen. Postfach",
    "sg:city":"Binningen",
    "sg:orig_category":"Oberfl\u00e4chenreinigung Sandstrahlen Oberfl\u00e4chenveredlung U W\u00e4rmebehandlung",
    "sg:phone":"+41 33 676 10 88",
    "sg:postcode":"4102",
    "sg:province":"Basel-Landschaft",
    "wof:name":"Sandstrahlerei Kien Gmbh",
    "wof:placetype":"venue"
},
  "geometry": {"coordinates":[7.6810369492,46.6101570129],"type":"Point"}
}