{
  "type": "Feature",
  "properties": {
    "iso:country":"CH",
    "sg:address":"Hohmadstrasse 2a",
    "sg:city":"Thun",
    "sg:classifiers":[
        {
            "category":"Wholesale",
            "subcategory":"Construction Materials",
            "type":"Manufacturing & Wholesale Goods"
        }
    ],
    "sg:phone":"+41 33 223 31 81",
    "sg:postcode":"3600",
    "sg:province":"Bern",
    "sg:tags":[
        "bridge",
        "temporary",
        "materials",
        "crown"
    ],
    "wof:name":"Deckart Ag",
    "wof:placetype":"venue"
},
  "geometry": {"coordinates":[7.62464,46.750031],"type":"Point"}
}