{
  "type": "Feature",
  "properties": {
    "iso:country":"CH",
    "sg:address":"Maihofstrasse 12",
    "sg:city":"Unter\u00e4geri",
    "sg:orig_category":"Erschliessung von Grundst\u00fccken",
    "sg:postcode":"6314",
    "sg:province":"Zug",
    "wof:name":"Baugenossenschaft 91 Fl\u00fchli-s\u00f6renberg",
    "wof:placetype":"venue"
},
  "geometry": {"coordinates":[8.0167274475,46.8771629333],"type":"Point"}
}