{
  "type": "Feature",
  "properties": {
    "iso:country":"CH",
    "sg:address":"Pumpwerkstrasse 40",
    "sg:city":"Regensdorf",
    "sg:orig_category":"Innenausbau Verlegen von Fussboden",
    "sg:phone":"+41 18405052",
    "sg:postcode":"8105",
    "sg:province":"Z\u00fcrich",
    "wof:name":"Sch\u00f6ner Wohnen By Team Gmbh",
    "wof:placetype":"venue"
},
  "geometry": {"coordinates":[8.4608869553,47.4449310303],"type":"Point"}
}