{
  "type": "Feature",
  "properties": {
    "iso:country":"CH",
    "sg:address":"1921",
    "sg:city":"Martigny-croix",
    "sg:orig_category":"Fachdetailhandel in Verkaufsr\u00e4umen",
    "sg:postcode":"1921",
    "sg:province":"Valais",
    "wof:name":"Zo Sport Und Mode Ulrich",
    "wof:placetype":"venue"
},
  "geometry": {"coordinates":[8.8035001755,47.3288803101],"type":"Point"}
}