{
  "type": "Feature",
  "properties": {
    "iso:country":"CH",
    "sg:address":"Leberngasse 9",
    "sg:city":"Olten",
    "sg:orig_category":"Mit dem Versicherungsgewerbe verbundene T\u00e4tigkeiten",
    "sg:postcode":"4600",
    "sg:province":"Solothurn",
    "wof:name":"Renta Verm\u00f6gens Consult Ag",
    "wof:placetype":"venue"
},
  "geometry": {"coordinates":[7.900706768,47.3489761353],"type":"Point"}
}