{
  "type": "Feature",
  "properties": {
    "iso:country":"CH",
    "sg:address":"Fl\u00fcelastrasse 15",
    "sg:city":"Z\u00fcrich",
    "sg:orig_category":"Non-Classified Establishments",
    "sg:phone":"+41 14918359",
    "sg:postcode":"8048",
    "sg:province":"Z\u00fcrich",
    "wof:name":"Body-relax Zuelli",
    "wof:placetype":"venue"
},
  "geometry": {"coordinates":[8.4971752167,47.3837738037],"type":"Point"}
}