{
  "type": "Feature",
  "properties": {
    "iso:country":"CH",
    "sg:address":"Graben\u00e4ckerstrasse 2",
    "sg:city":"Fislisbach",
    "sg:orig_category":"Bauspenglerei Sanit\u00e4rinstallation U Spenglerei",
    "sg:phone":"+41 56 493 11 20",
    "sg:postcode":"5442",
    "sg:province":"Aargau",
    "wof:name":"Willi Gaschen Spenglerei",
    "wof:placetype":"venue"
},
  "geometry": {"coordinates":[8.293518,47.438354],"type":"Point"}
}