{
  "type": "Feature",
  "properties": {
    "iso:country":"CH",
    "sg:address":"3925",
    "sg:city":"Gr\u00e4chen",
    "sg:classifiers":[
        {
            "category":"Restaurant",
            "type":"Food & Drink"
        }
    ],
    "sg:phone":"+41 27 956 15 77",
    "sg:postcode":"3925",
    "sg:province":"Valais",
    "wof:name":"Restaurant B\u00e4rgji-alp",
    "wof:placetype":"venue"
},
  "geometry": {"coordinates":[7.8392400742,46.1961631775],"type":"Point"}
}