{
  "type": "Feature",
  "properties": {
    "iso:country":"CH",
    "sg:address":"Collina Via 24",
    "sg:city":"Bissone",
    "sg:orig_category":"Allgemeiner Hoch U Tiefbau",
    "sg:postcode":"6816",
    "sg:province":"Ticino",
    "wof:name":"David & Pfister Sa",
    "wof:placetype":"venue"
},
  "geometry": {"coordinates":[8.967785,45.950958],"type":"Point"}
}