{
  "type": "Feature",
  "properties": {
    "iso:country":"CH",
    "sg:address":"Cantonale Via",
    "sg:city":"Contone",
    "sg:orig_category":"Vermietung U Verpachtung von eigenen Immobilien",
    "sg:postcode":"6594",
    "sg:province":"Ticino",
    "wof:name":"Immobiliare Zenia Sa",
    "wof:placetype":"venue"
},
  "geometry": {"coordinates":[8.9152402878,46.1521682739],"type":"Point"}
}