{
  "type": "Feature",
  "properties": {
    "iso:country":"CH",
    "sg:address":"Eggerstandenstrasse",
    "sg:city":"Appenzell",
    "sg:orig_category":"Sonstige mit der Informatik verbundene T\u00e4tigkeiten",
    "sg:postcode":"9050",
    "sg:province":"Appenzell Innerhoden",
    "wof:name":"Eisenring Its Informatik Beratung Usw",
    "wof:placetype":"venue"
},
  "geometry": {"coordinates":[8.4522695541,47.2740211487],"type":"Point"}
}