{
  "type": "Feature",
  "properties": {
    "iso:country":"CH",
    "sg:address":"Linthlistrasse 9",
    "sg:city":"Oberurnen",
    "sg:orig_category":"Softwareentwicklung U beratung",
    "sg:phone":"+41 55 617 20 30",
    "sg:postcode":"8868",
    "sg:province":"Glarus",
    "wof:name":"Up-to-date Informatik Ag",
    "wof:placetype":"venue"
},
  "geometry": {"coordinates":[9.063829422,47.1169967651],"type":"Point"}
}