{
  "type": "Feature",
  "properties": {
    "addr:full":"Elisabethenanlage 11 4051 Basel. Postfach Basel Basel-Stadt 4002",
    "addr:housenumber":"11",
    "addr:postcode":"4051;4002",
    "addr:street":"Elisabethenanlage;Postfach",
    "iso:country":"CH",
    "sg:address":"Elisabethenanlage 11 4051 Basel. Postfach",
    "sg:city":"Basel",
    "sg:orig_category":"Advokaturb\u00fcros Notariate",
    "sg:phone":"+41 41 240 56 38",
    "sg:postcode":"4002",
    "sg:province":"Basel-Stadt",
    "wof:name":"Fellmann Von Moos & Wildisen Advokatur- & Notariatsb\u00fcro",
    "wof:placetype":"venue"
},
  "geometry": {"coordinates":[8.300657,47.051365],"type":"Point"}
}