{
  "type": "Feature",
  "properties": {
    "iso:country":"CH",
    "sg:address":"Eichenweg 16",
    "sg:city":"Langenthal",
    "sg:classifiers":[
        {
            "category":"Shopping",
            "subcategory":"Clothing, Apparel, & Fashions",
            "type":"Retail Goods"
        }
    ],
    "sg:phone":"+41 62 922 50 44",
    "sg:postcode":"4900",
    "sg:province":"Bern",
    "sg:tags":[
        "knitted",
        "knitwear",
        "clothes"
    ],
    "wof:name":"Lehsa",
    "wof:placetype":"venue"
},
  "geometry": {"coordinates":[7.7817869186,47.2247543335],"type":"Point"}
}