{
  "type": "Feature",
  "properties": {
    "iso:country":"CH",
    "sg:address":"Strecc Via 6805 Mezzovico. Postfach",
    "sg:city":"Mezzovico",
    "sg:orig_category":"Sonstige mit Sport verbundene T\u00e4tigkeiten",
    "sg:phone":"+41 91 946 38 38",
    "sg:postcode":"6805",
    "sg:province":"Ticino",
    "wof:name":"Igt International Golf Trading Sa Golf; Promozione, Organizzazione Di Manifestazioni Ecc",
    "wof:placetype":"venue"
},
  "geometry": {"coordinates":[8.9202451706,46.0936546326],"type":"Point"}
}