{
  "type": "Feature",
  "properties": {
    "iso:country":"CH",
    "sg:address":"Route De Cossonay 11 1023 Crissier Case Postale 61",
    "sg:city":"Crissier",
    "sg:orig_category":"Wirtschafts- and Arbeitgeberverb\u00e4nde",
    "sg:phone":"+41 21 691 92 74",
    "sg:postcode":"1023",
    "sg:province":"Vaud",
    "wof:name":"Assoc.suisse Des Commer\u00e7ants De Papiers-peints,a.meystre Sa",
    "wof:placetype":"venue"
},
  "geometry": {"coordinates":[6.5741581917,46.5554542542],"type":"Point"}
}