{
  "type": "Feature",
  "properties": {
    "addr:full":"Maderni Contrada 1 6816 Bissone. Postfach Bissone Ticino 6816",
    "addr:housenumber":"1",
    "addr:postcode":"6816 bissone. postfach;6816",
    "addr:street":"Contrada",
    "iso:country":"CH",
    "sg:address":"Maderni Contrada 1 6816 Bissone. Postfach",
    "sg:city":"Bissone",
    "sg:classifiers":[
        {
            "category":"Bars & Pubs",
            "type":"Food & Drink"
        }
    ],
    "sg:postcode":"6816",
    "sg:province":"Ticino",
    "wof:name":"D & D Commerce Sa",
    "wof:placetype":"venue"
},
  "geometry": {"coordinates":[8.96457,45.950375],"type":"Point"}
}