{
  "type": "Feature",
  "properties": {
    "addr:full":"Althardstrasse 195 Regensdorf Z\u00fcrich 8105",
    "addr:housenumber":"195",
    "addr:postcode":"8105",
    "addr:street":"Althardstrasse",
    "iso:country":"CH",
    "sg:address":"Althardstrasse 195",
    "sg:city":"Regensdorf",
    "sg:orig_category":"Architektur U Ingenieurb\u00fcros",
    "sg:phone":"+41 81 330 33 00",
    "sg:postcode":"8105",
    "sg:province":"Z\u00fcrich",
    "wof:name":"Egger Jakob",
    "wof:placetype":"venue"
},
  "geometry": {"coordinates":[9.641161,46.99202],"type":"Point"}
}