{
  "type": "Feature",
  "properties": {
    "iso:country":"CH",
    "sg:address":"Frauenfelderstrasse 17",
    "sg:city":"W\u00e4ngi",
    "sg:orig_category":"Stukkateurgewerbe, Gipserei U Verputzerei",
    "sg:phone":"+41 52 378 27 24",
    "sg:postcode":"9545",
    "sg:province":"Thurgau",
    "wof:name":"Suriano Vito Andrea Gmbh Gipsergesch\u00e4ft",
    "wof:placetype":"venue"
},
  "geometry": {"coordinates":[8.951417923,47.4983444214],"type":"Point"}
}