{
  "type": "Feature",
  "properties": {
    "iso:country":"CH",
    "sg:address":"3962",
    "sg:city":"Montana",
    "sg:orig_category":"Zimmerei, Dachdeckerei, Bauspenglerei U Abdichtung",
    "sg:phone":"+41 21 845 52 43",
    "sg:postcode":"3962",
    "wof:name":"Rochat Florian",
    "wof:placetype":"venue"
},
  "geometry": {"coordinates":[6.2310299873,46.6077919006],"type":"Point"}
}