{
  "type": "Feature",
  "properties": {
    "iso:country":"CH",
    "sg:address":"Walkimatt 4",
    "sg:city":"Willisau",
    "sg:orig_category":"Non-Classified Establishments",
    "sg:phone":"+41 41 970 33 17",
    "sg:postcode":"6130",
    "sg:province":"Luzern",
    "wof:name":"Meier Jules Ingenieurb\u00fcro F\u00fcr Heizung Und Klima",
    "wof:placetype":"venue"
},
  "geometry": {"coordinates":[7.9980740547,47.1151351929],"type":"Point"}
}