{
  "type": "Feature",
  "properties": {
    "iso:country":"CH",
    "sg:address":"Oberneuhofstrasse 3",
    "sg:city":"Baar",
    "sg:orig_category":"Werbung",
    "sg:postcode":"6340",
    "sg:province":"Zug",
    "wof:name":"R + K Laser Show Ag.",
    "wof:placetype":"venue"
},
  "geometry": {"coordinates":[8.5156602859,47.1887626648],"type":"Point"}
}