{
  "type": "Feature",
  "properties": {
    "iso:country":"CH",
    "sg:address":"Racine Rue Edouard 5 1202 Gen\u00e8ve. Postfach",
    "sg:city":"Gen\u00e8ve",
    "sg:orig_category":"Interessenvertretungen",
    "sg:postcode":"1202",
    "sg:province":"Gen\u00e8ve",
    "wof:name":"Organisation Islamique Internationale De Droits De L'homme Des Imamites",
    "wof:placetype":"venue"
},
  "geometry": {"coordinates":[6.1316280365,46.213558197],"type":"Point"}
}