{
  "type": "Feature",
  "properties": {
    "iso:country":"CH",
    "sg:address":"Haldenstrasse 11",
    "sg:city":"Ebnat",
    "sg:orig_category":"Sportvereine Turnen Vereine Damen",
    "sg:phone":"+41 71 993 34 43",
    "sg:postcode":"9642",
    "sg:province":"St. Gallen",
    "wof:name":"Damenturnver.ebnat-kappel",
    "wof:placetype":"venue"
},
  "geometry": {"coordinates":[9.1321735382,47.2606201172],"type":"Point"}
}