{
  "type": "Feature",
  "properties": {
    "iso:country":"CH",
    "sg:address":"Badenerstrasse 329 8003 Z\u00fcrich. Postfach 915",
    "sg:city":"Z\u00fcrich",
    "sg:orig_category":"Wirtschaftspr\u00fcfung, Steuerberatung U Treuhand",
    "sg:phone":"+41 81 833 25 17",
    "sg:postcode":"8040",
    "sg:province":"Z\u00fcrich",
    "wof:name":"Gisafid Sa",
    "wof:placetype":"venue"
},
  "geometry": {"coordinates":[9.8345308304,46.4975814819],"type":"Point"}
}