{
  "type": "Feature",
  "properties": {
    "addr:full":"Hinterofenstrasse 25 Koblenz Aargau 5322",
    "addr:housenumber":"25",
    "addr:postcode":"5322",
    "addr:street":"Hinterofenstrasse",
    "iso:country":"CH",
    "sg:address":"Hinterofenstrasse 25",
    "sg:city":"Koblenz",
    "sg:orig_category":"Herstellung von Kunststoffwaren",
    "sg:phone":"+41 56 246 16 60",
    "sg:postcode":"5322",
    "sg:province":"Aargau",
    "wof:name":"Kunststoffwerk Knecht Inh. D. Schweri",
    "wof:placetype":"venue"
},
  "geometry": {"coordinates":[8.234392,47.606537],"type":"Point"}
}