{
  "type": "Feature",
  "properties": {
    "iso:country":"CH",
    "sg:address":"Schmidenmattweg 3",
    "sg:city":"Langenthal",
    "sg:orig_category":"Vereine Hundedressur",
    "sg:phone":"+41 79 414 09 12",
    "sg:postcode":"4900",
    "sg:province":"Bern",
    "wof:name":"Kynolog.verein M\u00fcnchenbuchsee",
    "wof:placetype":"venue"
},
  "geometry": {"coordinates":[7.7738618851,47.2164840698],"type":"Point"}
}