{
  "type": "Feature",
  "properties": {
    "iso:country":"CH",
    "sg:address":"Langfurren 34",
    "sg:city":"Z\u00fcrich",
    "sg:orig_category":"Sonstige Aktivit\u00e4ten der nicht-\u00e4rztlichen Medizinalberufe",
    "sg:phone":"+41 12913061",
    "sg:postcode":"8057",
    "sg:province":"Z\u00fcrich",
    "wof:name":"Annette Wiesner Atemp\u00e4dagogin Dipl.sbam",
    "wof:placetype":"venue"
},
  "geometry": {"coordinates":[8.5414447784,47.4028396606],"type":"Point"}
}