{
  "type": "Feature",
  "properties": {
    "iso:country":"CH",
    "sg:address":"Hauptstrasse 21",
    "sg:city":"Augst",
    "sg:classifiers":[
        {
            "category":"Autos & Motor Vehicles",
            "subcategory":"Automobile Sales",
            "type":"Retail Goods"
        }
    ],
    "sg:phone":"+41 61 811 55 13",
    "sg:postcode":"4302",
    "sg:province":"Basel-Landschaft",
    "sg:tags":[
        "used",
        "vehicles"
    ],
    "wof:name":"E. + F. Automobile Ag",
    "wof:placetype":"venue"
},
  "geometry": {"coordinates":[7.717414856,47.5355453491],"type":"Point"}
}