{
  "type": "Feature",
  "properties": {
    "iso:country":"CH",
    "sg:address":"Im Steiacher 4",
    "sg:city":"Baden",
    "sg:orig_category":"Unclassifiable Establishments",
    "sg:phone":"+41 56 493 75 75",
    "sg:postcode":"5400",
    "sg:province":"Aargau",
    "wof:name":"Mediclass Gmbh",
    "wof:placetype":"venue"
},
  "geometry": {"coordinates":[8.2754039764,47.4403343201],"type":"Point"}
}