{
  "type": "Feature",
  "properties": {
    "iso:country":"CH",
    "sg:address":"Quellenstrasse 22",
    "sg:city":"Schaffhausen",
    "sg:orig_category":"Malerei",
    "sg:phone":"+41 52 624 25 44",
    "sg:postcode":"8200",
    "sg:province":"Schaffhausen",
    "wof:name":"Hans Haag Malergesch\u00e4ft",
    "wof:placetype":"venue"
},
  "geometry": {"coordinates":[8.6181077957,47.702205658],"type":"Point"}
}