{
  "type": "Feature",
  "properties": {
    "iso:country":"CH",
    "sg:address":"Frowiesstrasse 27",
    "sg:city":"Adetswil",
    "sg:orig_category":"Kaminfeger",
    "sg:phone":"+41 19392545",
    "sg:postcode":"8345",
    "sg:province":"Z\u00fcrich",
    "wof:name":"Peter Gentner Kaminfegermeister",
    "wof:placetype":"venue"
},
  "geometry": {"coordinates":[8.8416032791,47.3385238647],"type":"Point"}
}