{
  "type": "Feature",
  "properties": {
    "addr:full":"Ziegelgut 3f Burgdorf Bern 3400",
    "addr:housenumber":"3f",
    "addr:postcode":"3400",
    "iso:country":"CH",
    "sg:address":"Ziegelgut 3f",
    "sg:city":"Burgdorf",
    "sg:classifiers":[
        {
            "category":"Communications",
            "subcategory":"Television Station",
            "type":"Services"
        }
    ],
    "sg:phone":"+41 34 422 04 54",
    "sg:postcode":"3400",
    "sg:province":"Bern",
    "sg:tags":[
        "carillon",
        "bell"
    ],
    "wof:name":"Emmentaler Glasbl\u00e4serei",
    "wof:placetype":"venue"
},
  "geometry": {"coordinates":[7.635282,47.046448],"type":"Point"}
}