{
  "type": "Feature",
  "properties": {
    "iso:country":"CH",
    "sg:address":"Hauptstrasse 43",
    "sg:city":"Herznach",
    "sg:orig_category":"Grosshandel mit Nahrungsmitteln, Getr\u00e4nken U Tabakwaren",
    "sg:phone":"+41 62 878 11 33",
    "sg:postcode":"5027",
    "sg:province":"Aargau",
    "wof:name":"Markus Kl\u00e4usler Lebensmittel Engros",
    "wof:placetype":"venue"
},
  "geometry": {"coordinates":[8.0512771606,47.4737129211],"type":"Point"}
}