{
  "type": "Feature",
  "properties": {
    "iso:country":"CH",
    "sg:address":"Ch\u00e2tel St-denis Route De 59",
    "sg:city":"Blonay",
    "sg:orig_category":"Softwareentwicklung U beratung",
    "sg:postcode":"1807",
    "sg:province":"Vaud",
    "wof:name":"Icare Engineering S\u00e0rl",
    "wof:placetype":"venue"
},
  "geometry": {"coordinates":[6.893447876,46.4764900208],"type":"Point"}
}