{
  "type": "Feature",
  "properties": {
    "iso:country":"CH",
    "sg:address":"Letz 4",
    "sg:city":"N\u00e4fels",
    "sg:orig_category":"Vermietung U Verpachtung von eigenen Immobilien",
    "sg:postcode":"8752",
    "sg:province":"Glarus",
    "wof:name":"Glarimo Ag",
    "wof:placetype":"venue"
},
  "geometry": {"coordinates":[9.0631799698,47.1017074585],"type":"Point"}
}