{
  "type": "Feature",
  "properties": {
    "iso:country":"CH",
    "sg:address":"Landstrasse 74",
    "sg:city":"Wettingen",
    "sg:orig_category":"Detailhandel mit Schuhen Detailhandel mit Sportartikeln",
    "sg:phone":"+41 56 426 68 66",
    "sg:postcode":"5430",
    "sg:province":"Aargau",
    "wof:name":"Dosenbach Schuhe & Sport",
    "wof:placetype":"venue"
},
  "geometry": {"coordinates":[8.3237409592,47.4670295715],"type":"Point"}
}