{
  "type": "Feature",
  "properties": {
    "iso:country":"CH",
    "sg:address":"R\u00fcmlangstrasse 91a",
    "sg:city":"Z\u00fcrich",
    "sg:orig_category":"Institutionen f\u00fcr Behinderte Tagesheime f\u00fcr Behinderte, gesch\u00fctzte Werkst\u00e4tten",
    "sg:phone":"+41 13020577",
    "sg:postcode":"8052",
    "sg:province":"Z\u00fcrich",
    "wof:name":"Werkstatt F\u00fcr Behinderte Gutweniger Ag",
    "wof:placetype":"venue"
},
  "geometry": {"coordinates":[8.5399503708,47.430847168],"type":"Point"}
}