{
  "type": "Feature",
  "properties": {
    "iso:country":"CH",
    "sg:address":"Hoferbad 12",
    "sg:city":"Appenzell",
    "sg:classifiers":[
        {
            "category":"Manufacturing",
            "subcategory":"Textiles",
            "type":"Manufacturing & Wholesale Goods"
        }
    ],
    "sg:phone":"+41 71 787 14 51",
    "sg:postcode":"9050",
    "sg:province":"Appenzell Innerhoden",
    "sg:tags":[
        "clothing",
        "accessory"
    ],
    "wof:name":"Lehner Ag",
    "wof:placetype":"venue"
},
  "geometry": {"coordinates":[9.410794,47.327244],"type":"Point"}
}