{
  "type": "Feature",
  "properties": {
    "iso:country":"CH",
    "sg:address":"Z\u00fcrcherstrasse 47",
    "sg:city":"Sargans",
    "sg:orig_category":"Wirtschaftspr\u00fcfung, Steuerberatung U Treuhand",
    "sg:postcode":"7320",
    "sg:province":"St. Gallen",
    "wof:name":"Comcontrol Gmbh",
    "wof:placetype":"venue"
},
  "geometry": {"coordinates":[9.4339666367,47.0491333008],"type":"Point"}
}