{
  "type": "Feature",
  "properties": {
    "iso:country":"CH",
    "sg:address":"Alte Gerlafingenstrasse 3",
    "sg:city":"Biberist",
    "sg:orig_category":"Detailhandel mit Radio U Fernsehger\u00e4ten Detailhandel mit elektrischen Haushalts-,Radio U Fernsehger\u00e4",
    "sg:phone":"+41 32 675 35 56",
    "sg:postcode":"4562",
    "sg:province":"Solothurn",
    "wof:name":"Fink Radio-tv-video Ag",
    "wof:placetype":"venue"
},
  "geometry": {"coordinates":[7.5654082298,47.179851532],"type":"Point"}
}