{
  "type": "Feature",
  "properties": {
    "iso:country":"CH",
    "sg:address":"Av. Savoie Immeuble Vouvry-centre",
    "sg:city":"Vouvry",
    "sg:orig_category":"Erschliessung von Grundst\u00fccken",
    "sg:phone":"+41 21 634 20 66",
    "sg:postcode":"1896",
    "sg:province":"Valais",
    "wof:name":"Soci\u00e9t\u00e9 Coop\u00e9rative D'habitation, Renens Et Agglom\u00e9ration",
    "wof:placetype":"venue"
},
  "geometry": {"coordinates":[6.5841188431,46.5446281433],"type":"Point"}
}