{
  "type": "Feature",
  "properties": {
    "iso:country":"CH",
    "sg:address":"Rue Des Graviers 11",
    "sg:city":"Auvernier",
    "sg:orig_category":"Handelsvermittlung U Grosshandel R\u00fcckgewinnung U Vorbereitung f\u00fcr die Wiederverwertung Recycling",
    "sg:phone":"+41 79 213 80 81",
    "sg:postcode":"2012",
    "sg:province":"Neuch\u00e2tel",
    "wof:name":"Auguste Cuany Fers & M\u00e9taux",
    "wof:placetype":"venue"
},
  "geometry": {"coordinates":[6.8744587898,46.9732818604],"type":"Point"}
}