{
  "type": "Feature",
  "properties": {
    "iso:country":"CH",
    "sg:address":"Stein\u00e4cker 3",
    "sg:city":"H\u00fcttlingen",
    "sg:orig_category":"Herstellung von medizinischen U chirurgischen Ger\u00e4ten sowie orthop\u00e4dischen Vorrichtungen Softwareent",
    "sg:phone":"+41 52 765 25 62",
    "sg:postcode":"8553",
    "sg:province":"Thurgau",
    "wof:name":"Mediset Medical-software",
    "wof:placetype":"venue"
},
  "geometry": {"coordinates":[8.9706630707,47.5786972046],"type":"Point"}
}