{
  "type": "Feature",
  "properties": {
    "iso:country":"CH",
    "sg:address":"Bachtobelstrasse 17",
    "sg:city":"Seuzach",
    "sg:orig_category":"Vorschulen, Kinderg\u00e4rten",
    "sg:phone":"+41 18401504",
    "sg:postcode":"8472",
    "sg:province":"Z\u00fcrich",
    "wof:name":"Kindergarten Bachtobel",
    "wof:placetype":"venue"
},
  "geometry": {"coordinates":[8.4656362534,47.4512405396],"type":"Point"}
}