{
  "type": "Feature",
  "properties": {
    "iso:country":"CH",
    "sg:address":"Freiestrasse 43a",
    "sg:city":"Amriswil",
    "sg:orig_category":"Bau U Wohngenossenschaften",
    "sg:phone":"+41 71 411 39 59",
    "sg:postcode":"8580",
    "sg:province":"Thurgau",
    "wof:name":"Wohnbaugenossenschaft R\u00fcti",
    "wof:placetype":"venue"
},
  "geometry": {"coordinates":[9.294769,47.549461],"type":"Point"}
}