{
  "type": "Feature",
  "properties": {
    "addr:full":"Spielhof 14a Glarus Glarus 8750",
    "addr:housenumber":"14a",
    "addr:postcode":"8750",
    "addr:street":"Spielhof",
    "iso:country":"CH",
    "sg:address":"Spielhof 14a",
    "sg:city":"Glarus",
    "sg:orig_category":"Detailhandel mit Beleuchtungs U Haushaltsgegenst\u00e4nden Grosshandel mit Eisenwaren sowie Installations",
    "sg:phone":"+41 55 640 16 19",
    "sg:postcode":"8750",
    "sg:province":"Glarus",
    "wof:name":"E. Dieffenbacher Ag",
    "wof:placetype":"venue"
},
  "geometry": {"coordinates":[9.066008,47.042309],"type":"Point"}
}