{
  "type": "Feature",
  "properties": {
    "iso:country":"CH",
    "sg:address":"Lehmetstrasse 8",
    "sg:city":"Henau",
    "sg:orig_category":"Sportvereine Turnen Vereine Damen",
    "sg:phone":"+41 79 349 13 88",
    "sg:postcode":"9247",
    "sg:province":"St. Gallen",
    "wof:name":"Damenriege Btv St.gallen",
    "wof:placetype":"venue"
},
  "geometry": {"coordinates":[9.2519130707,47.4164657593],"type":"Point"}
}