{
  "type": "Feature",
  "properties": {
    "iso:country":"CH",
    "sg:address":"Hemmikerstr. 7",
    "sg:city":"Buus",
    "sg:classifiers":[
        {
            "category":"Manufacturing",
            "subcategory":"Electronics",
            "type":"Manufacturing & Wholesale Goods"
        }
    ],
    "sg:phone":"+41 61 841 00 10",
    "sg:postcode":"4463",
    "sg:province":"Basel-Landschaft",
    "sg:tags":[
        "amplifier"
    ],
    "wof:name":"M\u00fcller & Koch Holborne Audio Instruments",
    "wof:placetype":"venue"
},
  "geometry": {"coordinates":[7.865462,47.505222],"type":"Point"}
}