{
  "type": "Feature",
  "properties": {
    "iso:country":"CH",
    "sg:address":"Boudines Rue Des 13",
    "sg:city":"Meyrin",
    "sg:orig_category":"Non-Classified Establishments",
    "sg:postcode":"1217",
    "sg:province":"Gen\u00e8ve",
    "wof:name":"Oliveira Carvalheiro Andrade Manuela",
    "wof:placetype":"venue"
},
  "geometry": {"coordinates":[6.0807991028,46.2339096069],"type":"Point"}
}