{
  "type": "Feature",
  "properties": {
    "iso:country":"CH",
    "sg:address":"M\u00fchlebr\u00fccke 2",
    "sg:city":"Biel/bienne",
    "sg:orig_category":"Arztpraxen",
    "sg:phone":"+41 32 322 09 02",
    "sg:postcode":"2502",
    "sg:province":"Bern",
    "wof:name":"Dr.med.hans-martin Keller Spezialarzt Fmh",
    "wof:placetype":"venue"
},
  "geometry": {"coordinates":[7.243871,47.139931],"type":"Point"}
}