{
  "type": "Feature",
  "properties": {
    "iso:country":"CH",
    "sg:address":"Hauptstrasse",
    "sg:city":"Kandersteg",
    "sg:orig_category":"Detailhandel mit Fleisch U Fleischwaren",
    "sg:phone":"+41 33 675 12 09",
    "sg:postcode":"3718",
    "sg:province":"Bern",
    "wof:name":"Hans Sch\u00fcpbach-zmoos",
    "wof:placetype":"venue"
},
  "geometry": {"coordinates":[7.6641669273,46.4781723022],"type":"Point"}
}