{
  "type": "Feature",
  "properties": {
    "iso:country":"CH",
    "sg:address":"Boulevard Georges-favon 15",
    "sg:city":"Gen\u00e8ve",
    "sg:classifiers":[
        {
            "category":"Restaurant",
            "type":"Food & Drink"
        }
    ],
    "sg:phone":"+41 22 310 97 98",
    "sg:postcode":"1204",
    "sg:province":"Gen\u00e8ve",
    "wof:name":"Caf\u00e9-restaurant Le Boulevard",
    "wof:placetype":"venue"
},
  "geometry": {"coordinates":[6.1404027939,46.2021369934],"type":"Point"}
}