{
  "type": "Feature",
  "properties": {
    "addr:full":"Bruderholzstrasse 12 Binningen Basel-Landschaft 4102",
    "addr:housenumber":"12",
    "addr:postcode":"4102",
    "addr:street":"Bruderholzstrasse",
    "iso:country":"CH",
    "sg:address":"Bruderholzstrasse 12",
    "sg:city":"Binningen",
    "sg:orig_category":"Arztpraxen",
    "sg:phone":"+41 61 363 40 15",
    "sg:postcode":"4102",
    "sg:province":"Basel-Landschaft",
    "wof:name":"Dr.med.jadi Fabbri Spezialarzt Fmh",
    "wof:placetype":"venue"
},
  "geometry": {"coordinates":[7.576356,47.537403],"type":"Point"}
}