{
  "type": "Feature",
  "properties": {
    "iso:country":"CH",
    "sg:address":"Poststrasse 112",
    "sg:city":"Arosa",
    "sg:classifiers":[
        {
            "category":"Government",
            "subcategory":"Post Office",
            "type":"Public Place"
        }
    ],
    "sg:phone":"+41 81 377 29 39",
    "sg:postcode":"7050",
    "sg:province":"Graubunden",
    "sg:tags":[
        "caf\u00e9s",
        "tea-rooms"
    ],
    "wof:name":"Caf\u00e9 Weber",
    "wof:placetype":"venue"
},
  "geometry": {"coordinates":[9.6651620865,46.7756080627],"type":"Point"}
}