{
  "type": "Feature",
  "properties": {
    "iso:country":"CH",
    "sg:address":"Boulevard Des Tranch\u00e9es 8",
    "sg:city":"Gen\u00e8ve",
    "sg:classifiers":[
        {
            "category":"Restaurant",
            "type":"Food & Drink"
        }
    ],
    "sg:phone":"+41 22 347 33 47",
    "sg:postcode":"1206",
    "sg:province":"Gen\u00e8ve",
    "wof:name":"Steak-house Red-ox",
    "wof:placetype":"venue"
},
  "geometry": {"coordinates":[6.151570797,46.1960868835],"type":"Point"}
}