{
  "type": "Feature",
  "properties": {
    "iso:country":"CH",
    "sg:address":"Bernstrasse 339 8953 Dietikon. Postfach",
    "sg:city":"Dietikon",
    "sg:orig_category":"Interessenvertretungen",
    "sg:postcode":"8953",
    "sg:province":"Z\u00fcrich",
    "wof:name":"Pili-pili, Verein F\u00fcr Kulturelle Und Wirtschaftliche Zusammenarbeit Schweiz-afrika",
    "wof:placetype":"venue"
},
  "geometry": {"coordinates":[8.4025001526,47.3931083679],"type":"Point"}
}