{
  "type": "Feature",
  "properties": {
    "iso:country":"CH",
    "sg:address":"Avenue Des Gittaz 4",
    "sg:city":"Ste-croix",
    "sg:orig_category":"Architektur U Ingenieurb\u00fcros",
    "sg:phone":"+41 24 454 16 00",
    "sg:postcode":"1450",
    "sg:province":"Vaud",
    "wof:name":"Delacr\u00e9taz Kasimir-dessin Techniques",
    "wof:placetype":"venue"
},
  "geometry": {"coordinates":[6.496833,46.822956],"type":"Point"}
}