{
  "type": "Feature",
  "properties": {
    "iso:country":"CH",
    "sg:address":"Hinterberg Pension Seeblick 6365 Kehrsiten. Postfach",
    "sg:city":"Kehrsiten",
    "sg:orig_category":"Vermietung U Verpachtung von eigenen Immobilien",
    "sg:phone":"+41 41 620 61 32",
    "sg:postcode":"6365",
    "sg:province":"Nidwalden",
    "wof:name":"Jolie Immobilien Ag",
    "wof:placetype":"venue"
},
  "geometry": {"coordinates":[8.3650484085,46.9994125366],"type":"Point"}
}