{
  "type": "Feature",
  "properties": {
    "addr:full":"Oberdorfweg 9 5610 Wohlen Ag. Postfach Zufikon Aargau 5621",
    "addr:housenumber":"9",
    "addr:postcode":"5610;5621",
    "addr:street":"Oberdorfweg",
    "iso:country":"CH",
    "sg:address":"Oberdorfweg 9 5610 Wohlen Ag. Postfach",
    "sg:city":"Zufikon",
    "sg:orig_category":"Architektur U Ingenieurb\u00fcros Herstellung von industriellen Prozesssteuerungsanlagen",
    "sg:phone":"+41 56 649 22 11",
    "sg:postcode":"5621",
    "sg:province":"Aargau",
    "wof:name":"Hauser Steuerungstechnik Ag",
    "wof:placetype":"venue"
},
  "geometry": {"coordinates":[8.282789,47.350079],"type":"Point"}
}