{
  "type": "Feature",
  "properties": {
    "iso:country":"CH",
    "sg:address":"Zw\u00e4ngiweg 11 8038 Z\u00fcrich. Postfach",
    "sg:city":"Z\u00fcrich",
    "sg:orig_category":"Fotografische Ateliers",
    "sg:phone":"+41 14815485",
    "sg:postcode":"8060",
    "sg:province":"Z\u00fcrich",
    "wof:name":"Louis A. Burger Mode-& Werbefotografie",
    "wof:placetype":"venue"
},
  "geometry": {"coordinates":[8.5345315933,47.3304519653],"type":"Point"}
}