{
  "type": "Feature",
  "properties": {
    "iso:country":"CH",
    "sg:address":"Schulstrasse 10",
    "sg:city":"Zufikon",
    "sg:orig_category":"Sonstige Institutionen des Sozialwesens ohne Beherbergung",
    "sg:phone":"+41 56 633 98 33",
    "sg:postcode":"5621",
    "sg:province":"Aargau",
    "wof:name":"Elisabeth L\u00fcscher M\u00fctterberatung Bez. Bremgarten",
    "wof:placetype":"venue"
},
  "geometry": {"coordinates":[8.3581371307,47.347618103],"type":"Point"}
}