{
  "type": "Feature",
  "properties": {
    "addr:full":"Wilerstrasse 3 Oberuzwil St. Gallen 9242",
    "addr:housenumber":"3",
    "addr:postcode":"9242",
    "addr:street":"Wilerstrasse",
    "iso:country":"CH",
    "sg:address":"Wilerstrasse 3",
    "sg:city":"Oberuzwil",
    "sg:orig_category":"Arztpraxen",
    "sg:phone":"+41 71 951 52 52",
    "sg:postcode":"9242",
    "sg:province":"St. Gallen",
    "wof:name":"Dr.med.philippe Steiner Spezialarzt Fmh",
    "wof:placetype":"venue"
},
  "geometry": {"coordinates":[9.122741,47.429897],"type":"Point"}
}