{
  "type": "Feature",
  "properties": {
    "iso:country":"CH",
    "sg:address":"Hauptstrasse 15",
    "sg:city":"Birsfelden",
    "sg:orig_category":"HOTELS: MIT RESTAURANT Kongress- and Tagungshotels mit Restaurant",
    "sg:phone":"+41 61 311 80 15",
    "sg:postcode":"4127",
    "sg:province":"Basel-Landschaft",
    "wof:name":"Hotel Alfa",
    "wof:placetype":"venue"
},
  "geometry": {"coordinates":[7.6192998886,47.5545768738],"type":"Point"}
}