{
  "type": "Feature",
  "properties": {
    "iso:country":"CH",
    "sg:address":"Hauptstrasse 15",
    "sg:city":"Goldach",
    "sg:orig_category":"Physiotherapie",
    "sg:phone":"+41 71 841 89 60",
    "sg:postcode":"9403",
    "sg:province":"St. Gallen",
    "wof:name":"Magdalena Schneider Physiotherapie",
    "wof:placetype":"venue"
},
  "geometry": {"coordinates":[9.4658603668,47.4743041992],"type":"Point"}
}