{
  "type": "Feature",
  "properties": {
    "iso:country":"CH",
    "sg:address":"Limmattalstrasse 37",
    "sg:city":"Z\u00fcrich",
    "sg:orig_category":"Erbringung von Dienstleistungen f\u00fcr Unternehmen",
    "sg:postcode":"8049",
    "sg:province":"Z\u00fcrich",
    "wof:name":"M & M Hans-j\u00f6rg Marbach Design, Edition, Kommunikation; Produkteentwicklung, Dienstleistungen",
    "wof:placetype":"venue"
},
  "geometry": {"coordinates":[8.5092544556,47.396774292],"type":"Point"}
}