{
  "type": "Feature",
  "properties": {
    "iso:country":"CH",
    "sg:address":"Rue Denis-de-rougemont 2",
    "sg:city":"Neuch\u00e2tel",
    "sg:classifiers":[
        {
            "category":"Shopping",
            "subcategory":"Jewelry",
            "type":"Retail Goods"
        }
    ],
    "sg:phone":"+41 32 729 60 20",
    "sg:postcode":"2000",
    "sg:province":"Neuch\u00e2tel",
    "sg:tags":[
        "watch"
    ],
    "wof:name":"Luxury Timepieces Internationale S.a.",
    "wof:placetype":"venue"
},
  "geometry": {"coordinates":[6.9160552025,47.0002479553],"type":"Point"}
}