{
  "type": "Feature",
  "properties": {
    "iso:country":"CH",
    "sg:address":"Hirschmattstrasse 21 6003 Luzern. Postfach",
    "sg:city":"Luzern",
    "sg:orig_category":"Herstellung von konfektionierten Textilwaren ohne Bekleidung",
    "sg:phone":"+41 26 674 32 18",
    "sg:postcode":"6003",
    "sg:province":"Luzern",
    "wof:name":"Kalt Storen",
    "wof:placetype":"venue"
},
  "geometry": {"coordinates":[7.140021801,46.8987121582],"type":"Point"}
}