{
  "type": "Feature",
  "properties": {
    "iso:country":"CH",
    "sg:address":"S\u00fcdstrasse 31 8952 Schlieren. Postfach",
    "sg:city":"Schlieren",
    "sg:orig_category":"Handel mit Automobilen",
    "sg:postcode":"8952",
    "sg:province":"Z\u00fcrich",
    "wof:name":"Carpraxis Gmbh Autogarage, Bes. Handel U. Reparatur Von Automobilen",
    "wof:placetype":"venue"
},
  "geometry": {"coordinates":[8.4608821869,47.4006614685],"type":"Point"}
}