{
  "type": "Feature",
  "properties": {
    "iso:country":"CH",
    "sg:address":"Rue De La Blancherie 23",
    "sg:city":"Sion",
    "sg:orig_category":"Architektur U Ingenieurb\u00fcros",
    "sg:phone":"+41 27 322 01 83",
    "sg:postcode":"1950",
    "sg:province":"Valais",
    "wof:name":"Technoplan 53 Sa",
    "wof:placetype":"venue"
},
  "geometry": {"coordinates":[7.356039,46.226196],"type":"Point"}
}