{
  "type": "Feature",
  "properties": {
    "iso:country":"CH",
    "sg:address":"Fallacher 31",
    "sg:city":"Zumikon",
    "sg:orig_category":"Non-Classified Establishments",
    "sg:postcode":"8126",
    "sg:province":"Z\u00fcrich",
    "wof:name":"Hch Holding Ag",
    "wof:placetype":"venue"
},
  "geometry": {"coordinates":[8.6109809875,47.3298149109],"type":"Point"}
}