{
  "type": "Feature",
  "properties": {
    "iso:country":"CH",
    "sg:address":"Grabenstrasse 6",
    "sg:city":"Schlieren",
    "sg:orig_category":"RESTAURANTS: TEA-ROOMS",
    "sg:phone":"+41 17300242",
    "sg:postcode":"8952",
    "sg:province":"Z\u00fcrich",
    "wof:name":"Restaurant Frohsinn, Kohlbrenner Klaus",
    "wof:placetype":"venue"
},
  "geometry": {"coordinates":[8.4494762421,47.3991661072],"type":"Point"}
}