{
  "type": "Feature",
  "properties": {
    "iso:country":"CH",
    "sg:address":"Rheinstrasse 140",
    "sg:city":"Wallbach",
    "sg:orig_category":"Zimmerei, Dachdeckerei, Bauspenglerei U Abdichtung Zimmerei, Ingenieurholzbau",
    "sg:phone":"+41 79 766 19 18",
    "sg:postcode":"4323",
    "sg:province":"Aargau",
    "wof:name":"Mattle Karl",
    "wof:placetype":"venue"
},
  "geometry": {"coordinates":[9.5446748734,47.2843742371],"type":"Point"}
}