{
  "type": "Feature",
  "properties": {
    "iso:country":"CH",
    "sg:address":"6222",
    "sg:city":"Gunzwil",
    "sg:orig_category":"Detailhandel mit Milcherzeugnissen U Eiern Verarbeitung von Milch",
    "sg:postcode":"6222",
    "sg:province":"Luzern",
    "wof:name":"K\u00e4sereigenossenschaft Walde",
    "wof:placetype":"venue"
},
  "geometry": {"coordinates":[8.1788654327,47.2114143372],"type":"Point"}
}