{
  "type": "Feature",
  "properties": {
    "iso:country":"CH",
    "sg:address":"L\u00f6berenstrasse 47",
    "sg:city":"Zug",
    "sg:orig_category":"Grosshandel mit Datenverarbeitungsger\u00e4ten Softwareentwicklung U beratung",
    "sg:phone":"+41 32 353 14 07",
    "sg:postcode":"6300",
    "sg:province":"Zug",
    "wof:name":"Dll Dienstleistungen Loosli",
    "wof:placetype":"venue"
},
  "geometry": {"coordinates":[7.3587870598,47.1147613525],"type":"Point"}
}