{
  "type": "Feature",
  "properties": {
    "iso:country":"CH",
    "sg:address":"Rue Lect 29",
    "sg:city":"Meyrin",
    "sg:orig_category":"Non-Classified Establishments",
    "sg:postcode":"1217",
    "sg:province":"Gen\u00e8ve",
    "wof:name":"Danirouge Sa",
    "wof:placetype":"venue"
},
  "geometry": {"coordinates":[6.0815730095,46.2250823975],"type":"Point"}
}