{
  "type": "Feature",
  "properties": {
    "iso:country":"CH",
    "sg:address":"Landstrasse 24",
    "sg:city":"Bilten",
    "sg:orig_category":"Reinigungsgewerbe",
    "sg:postcode":"8865",
    "sg:province":"Glarus",
    "wof:name":"Ap Geb\u00e4udeunterhalt Gmbh",
    "wof:placetype":"venue"
},
  "geometry": {"coordinates":[8.5204772949,47.2766304016],"type":"Point"}
}