{
  "type": "Feature",
  "properties": {
    "iso:country":"CH",
    "sg:address":"2715",
    "sg:city":"Monible",
    "sg:orig_category":"Vorschulen, Kinderg\u00e4rten",
    "sg:phone":"+41 32 484 90 45",
    "sg:postcode":"2715",
    "sg:province":"Bern",
    "wof:name":"Ecole Enfantine Petit-val",
    "wof:placetype":"venue"
},
  "geometry": {"coordinates":[7.1950497627,47.2773399353],"type":"Point"}
}