{
  "type": "Feature",
  "properties": {
    "iso:country":"CH",
    "sg:address":"Chemin Du Pontet 18",
    "sg:city":"Collombey",
    "sg:orig_category":"Vereine Gesang",
    "sg:postcode":"1868",
    "sg:province":"Valais",
    "wof:name":"M\u00e4nnerchor Alpina",
    "wof:placetype":"venue"
},
  "geometry": {"coordinates":[9.2852296829,46.8366889954],"type":"Point"}
}