{
  "type": "Feature",
  "properties": {
    "iso:country":"CH",
    "sg:address":"Baselstrasse 16",
    "sg:city":"Feldbrunnen",
    "sg:orig_category":"Herstellung von Hebezeugen U F\u00f6rdermitteln",
    "sg:postcode":"4532",
    "sg:province":"Solothurn",
    "wof:name":"Gru Gmbh",
    "wof:placetype":"venue"
},
  "geometry": {"coordinates":[7.555106163,47.2201652527],"type":"Point"}
}