{
  "type": "Feature",
  "properties": {
    "addr:full":"Sportweg 57 Z\u00fcrich Z\u00fcrich 8048",
    "addr:housenumber":"57",
    "addr:postcode":"8048",
    "addr:street":"Sportweg",
    "iso:country":"CH",
    "sg:address":"Sportweg 57",
    "sg:city":"Z\u00fcrich",
    "sg:orig_category":"Allgemeiner Hoch U Tiefbau",
    "sg:postcode":"8048",
    "sg:province":"Z\u00fcrich",
    "wof:name":"Eltschinger Nicolas Tiefbau",
    "wof:placetype":"venue"
},
  "geometry": {"coordinates":[7.260454,46.862381],"type":"Point"}
}