{
  "type": "Feature",
  "properties": {
    "iso:country":"CH",
    "sg:address":"Riedstrasse 10",
    "sg:city":"Thun",
    "sg:orig_category":"Elektroinstallation",
    "sg:phone":"+41 33 223 44 44",
    "sg:postcode":"3600",
    "sg:province":"Bern",
    "wof:name":"Gerber Ag Elektro-& Telefonanlagen",
    "wof:placetype":"venue"
},
  "geometry": {"coordinates":[7.6393918991,46.7506065369],"type":"Point"}
}