{
  "type": "Feature",
  "properties": {
    "iso:country":"CH",
    "sg:address":"Wibichstrasse 1 8037 Z\u00fcrich. Postfach 424",
    "sg:city":"Z\u00fcrich",
    "sg:orig_category":"Herstellung von Mess U Kontrollinstrumenten U vorrichtungen",
    "sg:phone":"+41 13611025",
    "sg:postcode":"8037",
    "sg:province":"Z\u00fcrich",
    "wof:name":"B\u00fcmaco, B. Marelli",
    "wof:placetype":"venue"
},
  "geometry": {"coordinates":[8.5315322876,47.3958473206],"type":"Point"}
}