{
  "type": "Feature",
  "properties": {
    "iso:country":"CH",
    "sg:address":"Fondlistrasse 5",
    "sg:city":"Dietikon",
    "sg:orig_category":"Allgemeiner Hoch U Tiefbau Zimmerei, Ingenieurholzbau",
    "sg:phone":"+41 17408651",
    "sg:postcode":"8953",
    "sg:province":"Z\u00fcrich",
    "wof:name":"Josef Frauenknecht",
    "wof:placetype":"venue"
},
  "geometry": {"coordinates":[8.388311,47.407825],"type":"Point"}
}