{
  "type": "Feature",
  "properties": {
    "iso:country":"CH",
    "sg:address":"Bodenmattstrasse",
    "sg:city":"Reinach",
    "sg:classifiers":[
        {
            "category":"Home & Garden",
            "subcategory":"Building Materials",
            "type":"Retail Goods"
        }
    ],
    "sg:phone":"+41 61 715 90 90",
    "sg:postcode":"4153",
    "sg:province":"Basel-Landschaft",
    "sg:tags":[
        "window",
        "plastic"
    ],
    "wof:name":"Schneebeli & Co Ag",
    "wof:placetype":"venue"
},
  "geometry": {"coordinates":[7.5948500633,47.4944114685],"type":"Point"}
}