{
  "type": "Feature",
  "properties": {
    "iso:country":"CH",
    "sg:address":"Widumstrasse 1",
    "sg:city":"Stilli",
    "sg:orig_category":"Fussreflexzonenmassage",
    "sg:phone":"+41 56 284 24 45",
    "sg:postcode":"5233",
    "sg:province":"Aargau",
    "wof:name":"Gerda Messikommer Fussreflexzonentherapie",
    "wof:placetype":"venue"
},
  "geometry": {"coordinates":[8.2309026718,47.5186271667],"type":"Point"}
}