{
  "type": "Feature",
  "properties": {
    "iso:country":"CH",
    "sg:address":"Wili",
    "sg:city":"Gunzwil",
    "sg:orig_category":"Allgemeiner Hoch U Tiefbau Hoch U Tiefbau",
    "sg:phone":"+41 41 931 00 75",
    "sg:postcode":"6222",
    "sg:province":"Luzern",
    "wof:name":"Wicky Martin",
    "wof:placetype":"venue"
},
  "geometry": {"coordinates":[8.18674,47.188789],"type":"Point"}
}