{
  "type": "Feature",
  "properties": {
    "iso:country":"CH",
    "sg:address":"In Moosegg",
    "sg:city":"Lauperswil",
    "sg:orig_category":"Elektrizit\u00e4tsversorgung",
    "sg:postcode":"3438",
    "sg:province":"Bern",
    "wof:name":"Elektrizit\u00e4tsgenossenschaft Moosegg",
    "wof:placetype":"venue"
},
  "geometry": {"coordinates":[7.7177100182,46.9421882629],"type":"Point"}
}