{
  "type": "Feature",
  "properties": {
    "iso:country":"CH",
    "sg:address":"Gl\u00e4rnischstrasse 4",
    "sg:city":"Horgen",
    "sg:orig_category":"Herstellung von Radio U Fernsehger\u00e4ten sowie phono U videotechnischen Ger\u00e4ten",
    "sg:postcode":"8810",
    "sg:province":"Z\u00fcrich",
    "wof:name":"Pa Reparaturen, Bachmann G.",
    "wof:placetype":"venue"
},
  "geometry": {"coordinates":[8.601770401,47.2565002441],"type":"Point"}
}