{
  "type": "Feature",
  "properties": {
    "iso:country":"CH",
    "sg:address":"Saint-antoine Prom. De 16 1204 Gen\u00e8ve. Postfach",
    "sg:city":"Gen\u00e8ve",
    "sg:orig_category":"Handels-H\u00e4user U Gesellschaften",
    "sg:phone":"+41 22 311 00 12",
    "sg:postcode":"1204",
    "sg:province":"Gen\u00e8ve",
    "wof:name":"Scholliers Financial Consultancy",
    "wof:placetype":"venue"
},
  "geometry": {"coordinates":[6.149846077,46.1993598938],"type":"Point"}
}