{
  "type": "Feature",
  "properties": {
    "iso:country":"CH",
    "sg:address":"Rue De Carouge 21",
    "sg:city":"Gen\u00e8ve",
    "sg:orig_category":"Malerei Tapeziererei",
    "sg:phone":"+41 22 367 16 58",
    "sg:postcode":"1205",
    "sg:province":"Gen\u00e8ve",
    "wof:name":"Giorgio Acerbis Peinture & Papiers Peints",
    "wof:placetype":"venue"
},
  "geometry": {"coordinates":[6.1518092155,46.3812294006],"type":"Point"}
}