{
  "type": "Feature",
  "properties": {
    "iso:country":"CH",
    "sg:address":"Im Bann 33",
    "sg:city":"Lippoldswilen",
    "sg:orig_category":"Fahrschulen, Flugschulen",
    "sg:phone":"+41 79 436 41 43",
    "sg:postcode":"8566",
    "sg:province":"Thurgau",
    "wof:name":"Fredy Moder Autofahrschule",
    "wof:placetype":"venue"
},
  "geometry": {"coordinates":[9.1096401215,47.6108703613],"type":"Point"}
}