{
  "type": "Feature",
  "properties": {
    "iso:country":"CH",
    "sg:address":"Poststrasse 26",
    "sg:city":"Wattwil",
    "sg:orig_category":"Detailhandel mit Spielwaren Sonstiger Detailhandel mit Metallwaren, Anstrichmitteln, Glaswaren, Bau ",
    "sg:phone":"+41 71 988 27 66",
    "sg:postcode":"9630",
    "sg:province":"St. Gallen",
    "wof:name":"Hobby Keba Spiel & Freizeit",
    "wof:placetype":"venue"
},
  "geometry": {"coordinates":[9.0861988068,47.3026123047],"type":"Point"}
}