{
  "type": "Feature",
  "properties": {
    "iso:country":"CH",
    "sg:address":"Kasernenstrasse 24",
    "sg:city":"B\u00fclach",
    "sg:classifiers":[
        {
            "category":"Bars & Pubs",
            "type":"Food & Drink"
        }
    ],
    "sg:phone":"+41 18610622",
    "sg:postcode":"8180",
    "sg:province":"Z\u00fcrich",
    "wof:name":"Buffalo's Bar",
    "wof:placetype":"venue"
},
  "geometry": {"coordinates":[8.538472,47.518497],"type":"Point"}
}