{
  "type": "Feature",
  "properties": {
    "iso:country":"CH",
    "sg:address":"Suchard Faubourg Ph.- 19",
    "sg:city":"Boudry",
    "sg:orig_category":"Sonstige mit der Informatik verbundene T\u00e4tigkeiten",
    "sg:phone":"+41 32 841 25 20",
    "sg:postcode":"2017",
    "sg:province":"Neuch\u00e2tel",
    "wof:name":"Th. Pittet Pc",
    "wof:placetype":"venue"
},
  "geometry": {"coordinates":[6.838696003,46.9496192932],"type":"Point"}
}