{
  "type": "Feature",
  "properties": {
    "iso:country":"CH",
    "sg:address":"St\u00e4dtchen 22",
    "sg:city":"Uznach",
    "sg:orig_category":"Detailhandel mit Blumen U Pflanzen Fachdetailhandel in Verkaufsr\u00e4umen",
    "sg:phone":"+41 55 280 23 22",
    "sg:postcode":"8730",
    "sg:province":"St. Gallen",
    "wof:name":"Rogger Richard, Bluemel\u00e4deli.",
    "wof:placetype":"venue"
},
  "geometry": {"coordinates":[8.986313,47.225182],"type":"Point"}
}