{
  "type": "Feature",
  "properties": {
    "iso:country":"CH",
    "sg:address":"Hirzengasse 3 6430 Schwyz. Postfach",
    "sg:city":"Schwyz",
    "sg:orig_category":"RESTAURANTS: TEA-ROOMS",
    "sg:postcode":"6431",
    "sg:province":"Schwyz",
    "wof:name":"Fopisa Gmbh",
    "wof:placetype":"venue"
},
  "geometry": {"coordinates":[8.6540613174,47.0212059021],"type":"Point"}
}