{
  "type": "Feature",
  "properties": {
    "iso:country":"CH",
    "sg:address":"Brunnital",
    "sg:city":"Untersch\u00e4chen",
    "sg:orig_category":"Detailhandel mit Waren verschiedener Art, Hauptrichtung Nahrungsmittel",
    "sg:phone":"+41 41 879 18 17",
    "sg:postcode":"6465",
    "sg:province":"Uri",
    "wof:name":"Martin Hauger Lebensmittel",
    "wof:placetype":"venue"
},
  "geometry": {"coordinates":[8.7715864182,46.8570251465],"type":"Point"}
}