{
  "type": "Feature",
  "properties": {
    "iso:country":"CH",
    "sg:address":"Dorfstrasse 45",
    "sg:city":"Kleinl\u00fctzel",
    "sg:orig_category":"Herstellung von Schl\u00f6ssern U Beschl\u00e4gen Stahl U Leichtmetallbau",
    "sg:phone":"+41 61 771 01 80",
    "sg:postcode":"4245",
    "sg:province":"Solothurn",
    "wof:name":"Metallwarenfabrik Dreier Linus Ag",
    "wof:placetype":"venue"
},
  "geometry": {"coordinates":[7.4143409729,47.4272918701],"type":"Point"}
}