{
  "type": "Feature",
  "properties": {
    "iso:country":"CH",
    "sg:address":"D\u00fcnnernstrasse 37",
    "sg:city":"Oensingen",
    "sg:orig_category":"Heat Insulators, Binder-Free",
    "sg:phone":"+41 62 388 40 00",
    "sg:postcode":"4702",
    "sg:province":"Solothurn",
    "wof:name":"Kuratle & Jaecker Ag",
    "wof:placetype":"venue"
},
  "geometry": {"coordinates":[7.7191967964,47.2815666199],"type":"Point"}
}