{
  "type": "Feature",
  "properties": {
    "iso:country":"CH",
    "sg:address":"3766 Boltigen. Postfach",
    "sg:city":"Reidenbach",
    "sg:orig_category":"Sonstiger Fachdetailhandel mit Nahrungsmitteln, Getr\u00e4nken U Tabak in Verkaufsr\u00e4umen",
    "sg:postcode":"3766",
    "sg:province":"Bern",
    "wof:name":"Ida Ueltschi",
    "wof:placetype":"venue"
},
  "geometry": {"coordinates":[7.3905181885,46.6289710999],"type":"Point"}
}