{
  "type": "Feature",
  "properties": {
    "iso:country":"CH",
    "sg:address":"Tramweg 39 6415 Arth. Postfach",
    "sg:city":"Oberarth",
    "sg:orig_category":"G\u00fcterbef\u00f6rderung im Strassenverkehr",
    "sg:postcode":"6414",
    "sg:province":"Schwyz",
    "wof:name":"Riedi Ren\u00e9 Transporte",
    "wof:placetype":"venue"
},
  "geometry": {"coordinates":[8.5263795853,47.0631217957],"type":"Point"}
}