{
  "type": "Feature",
  "properties": {
    "iso:country":"CH",
    "sg:address":"6170 Sch\u00fcpfheim. Postfach",
    "sg:city":"Sch\u00fcpfheim",
    "sg:orig_category":"S\u00e4ge, Hobel U Holzimpr\u00e4gnierwerke",
    "sg:postcode":"6170",
    "sg:province":"Luzern",
    "wof:name":"Sonney A.",
    "wof:placetype":"venue"
},
  "geometry": {"coordinates":[6.9055199623,46.565120697],"type":"Point"}
}