{
  "type": "Feature",
  "properties": {
    "iso:country":"CH",
    "sg:address":"Grossfeldstrasse 16a",
    "sg:city":"Sargans",
    "sg:orig_category":"Non-Classified Establishments",
    "sg:postcode":"7320",
    "sg:province":"St. Gallen",
    "wof:name":"The Oxford School, Susannah Illi",
    "wof:placetype":"venue"
},
  "geometry": {"coordinates":[8.4413146973,47.0852775574],"type":"Point"}
}