{
  "type": "Feature",
  "properties": {
    "iso:country":"CH",
    "sg:address":"6248",
    "sg:city":"Alberswil",
    "sg:orig_category":"Verwaltung von Immobilien",
    "sg:postcode":"6248",
    "sg:province":"Luzern",
    "wof:name":"Genossenschaft Sonne In Alberswil",
    "wof:placetype":"venue"
},
  "geometry": {"coordinates":[7.9967498779,47.1450691223],"type":"Point"}
}