{
  "type": "Feature",
  "properties": {
    "iso:country":"CH",
    "sg:address":"Route De La Bl\u00e9cherette 14",
    "sg:city":"Cheseaux-lausanne",
    "sg:orig_category":"Handelsvermittlung U Grosshandel",
    "sg:phone":"+41 21 731 38 90",
    "sg:postcode":"1033",
    "sg:province":"Vaud",
    "wof:name":"Lamocolor Prod.pour Arts Graphiques",
    "wof:placetype":"venue"
},
  "geometry": {"coordinates":[6.6048598289,46.5855407715],"type":"Point"}
}