{
  "type": "Feature",
  "properties": {
    "iso:country":"CH",
    "sg:address":"Schweighofstrasse 196",
    "sg:city":"Z\u00fcrich",
    "sg:orig_category":"Detailhandel mit Geschenkartikeln U Souvenirs",
    "sg:phone":"+41 14622254",
    "sg:postcode":"8045",
    "sg:province":"Z\u00fcrich",
    "wof:name":"Katharina Wendle Kunstgewerbe",
    "wof:placetype":"venue"
},
  "geometry": {"coordinates":[8.5074224472,47.3598594666],"type":"Point"}
}