{
  "type": "Feature",
  "properties": {
    "iso:country":"CH",
    "sg:address":"Schwandstrasse 18",
    "sg:city":"Ober\u00e4geri",
    "sg:orig_category":"Zimmerei, Dachdeckerei, Bauspenglerei U Abdichtung",
    "sg:postcode":"6315",
    "sg:province":"Zug",
    "wof:name":"Peter Roth Holzbau Gmbh",
    "wof:placetype":"venue"
},
  "geometry": {"coordinates":[8.6351585388,47.1417694092],"type":"Point"}
}