{
  "type": "Feature",
  "properties": {
    "iso:country":"CH",
    "sg:address":"Dorfplatz 6 6060 Sarnen. Postfach",
    "sg:city":"Sarnen",
    "sg:orig_category":"Unternehmensberatung",
    "sg:postcode":"6060",
    "sg:province":"Obwalden",
    "wof:name":"Portmann Heini Management Gmbh",
    "wof:placetype":"venue"
},
  "geometry": {"coordinates":[8.2455263138,46.8959503174],"type":"Point"}
}