{
  "type": "Feature",
  "properties": {
    "iso:country":"CH",
    "sg:address":"Chemin De Montelly 48",
    "sg:city":"Lausanne",
    "sg:orig_category":"Mechanik Schlossereien",
    "sg:phone":"+41 21 634 62 39",
    "sg:postcode":"1007",
    "sg:province":"Vaud",
    "wof:name":"B & B Montage S\u00e0rl",
    "wof:placetype":"venue"
},
  "geometry": {"coordinates":[6.6093111038,46.5216026306],"type":"Point"}
}