{
  "type": "Feature",
  "properties": {
    "iso:country":"CH",
    "sg:address":"Ueberlandstrasse 25 8050 Z\u00fcrich. Postfach 174",
    "sg:city":"Z\u00fcrich",
    "sg:orig_category":"Fachdetailhandel mit pharmazeutischen Produkten",
    "sg:phone":"+41 13113656",
    "sg:postcode":"8062",
    "wof:name":"Ueberland-apotheke Und Drogerie, Saba Dr. Antoine",
    "wof:placetype":"venue"
},
  "geometry": {"coordinates":[8.5574026108,47.4052009583],"type":"Point"}
}