{
  "type": "Feature",
  "properties": {
    "iso:country":"CH",
    "sg:address":"Industriestrasse 4",
    "sg:city":"Lengnau",
    "sg:classifiers":[
        {
            "category":"Manufacturing",
            "subcategory":"Rubber & Plastics",
            "type":"Manufacturing & Wholesale Goods"
        }
    ],
    "sg:phone":"+41 32 652 72 20",
    "sg:postcode":"2543",
    "sg:province":"Bern",
    "sg:tags":[
        "injection",
        "part",
        "moulded"
    ],
    "wof:name":"Plasto Disc Sa",
    "wof:placetype":"venue"
},
  "geometry": {"coordinates":[7.3628668785,47.1772918701],"type":"Point"}
}