{
  "type": "Feature",
  "properties": {
    "iso:country":"CH",
    "sg:address":"Avenue De La Gare 15-17",
    "sg:city":"Sion",
    "sg:orig_category":"Detailhandel mit Brot, Back U S\u00fcsswaren",
    "sg:phone":"+41 27 306 48 08",
    "sg:postcode":"1950",
    "sg:province":"Valais",
    "wof:name":"Michellod Albert.",
    "wof:placetype":"venue"
},
  "geometry": {"coordinates":[7.18193,46.188934],"type":"Point"}
}