{
  "type": "Feature",
  "properties": {
    "iso:country":"CH",
    "sg:address":"Bernstrasse 19 3303 Jegenstorf. Postfach",
    "sg:city":"Mattstetten",
    "sg:orig_category":"Softwareentwicklung U beratung",
    "sg:postcode":"3322",
    "sg:province":"Bern",
    "wof:name":"Core Information Solutions Software; Erstellung U. Vertrieb Usw.",
    "wof:placetype":"venue"
},
  "geometry": {"coordinates":[7.5055689812,47.0473213196],"type":"Point"}
}