{
  "type": "Feature",
  "properties": {
    "addr:full":"Rue Du Midi 6 1000 Lausanne. Postfach Lausanne Vaud 1003",
    "addr:housenumber":"6",
    "addr:postcode":"1000;postfach;1003",
    "addr:street":"Rue Du Midi",
    "iso:country":"CH",
    "sg:address":"Rue Du Midi 6 1000 Lausanne. Postfach",
    "sg:city":"Lausanne",
    "sg:orig_category":"Architektur U Ingenieurb\u00fcros",
    "sg:postcode":"1003",
    "sg:province":"Vaud",
    "wof:name":"Invernizzi Mario Architecte S\u00e0rl",
    "wof:placetype":"venue"
},
  "geometry": {"coordinates":[6.632051,46.518669],"type":"Point"}
}