{
  "type": "Feature",
  "properties": {
    "iso:country":"CH",
    "sg:address":"R\u00f6sslimattweg 8",
    "sg:city":"Luzern",
    "sg:orig_category":"Bauschreinerei Erbringung von sonstigen Dienstleistungen f\u00fcr Unternehmen",
    "sg:phone":"+41 41 361 13 62",
    "sg:postcode":"6005",
    "sg:province":"Luzern",
    "wof:name":"Renato Francesco Fontana Metall-& Stahlbau",
    "wof:placetype":"venue"
},
  "geometry": {"coordinates":[8.3122911453,47.0450172424],"type":"Point"}
}