{
  "type": "Feature",
  "properties": {
    "iso:country":"CH",
    "sg:address":"Rue Kl\u00e9berg 6 1201 Gen\u00e8ve. Postfach",
    "sg:city":"Gen\u00e8ve",
    "sg:orig_category":"Dienstleistungen von Beteiligungsgesellschaften",
    "sg:postcode":"1200",
    "sg:province":"Gen\u00e8ve",
    "wof:name":"Silex Administration Sa Services D'administration, De Comptabilit\u00e9, De Contr\u00f4le Et Gestion Financi\u00e8re",
    "wof:placetype":"venue"
},
  "geometry": {"coordinates":[6.1448221207,46.2065010071],"type":"Point"}
}