{
  "type": "Feature",
  "properties": {
    "iso:country":"CH",
    "sg:address":"Amriswilerstrasse 153",
    "sg:city":"Weinfelden",
    "sg:orig_category":"Einzelhandel mit Automobilteilen U Zubeh\u00f6r",
    "sg:phone":"+41 71 622 22 30",
    "sg:postcode":"8570",
    "sg:province":"Thurgau",
    "wof:name":"Pneu Egger Ag",
    "wof:placetype":"venue"
},
  "geometry": {"coordinates":[9.1279964447,47.561706543],"type":"Point"}
}