{
  "type": "Feature",
  "properties": {
    "iso:country":"CH",
    "sg:address":"Ziegelfeldstrasse 23",
    "sg:city":"Olten",
    "sg:orig_category":"Detailhandel mit fotografischen Artikeln Fachdetailhandel in Verkaufsr\u00e4umen",
    "sg:phone":"+41 62 212 33 56",
    "sg:postcode":"4600",
    "sg:province":"Solothurn",
    "wof:name":"Robert Ringier Fotogesch\u00e4ft",
    "wof:placetype":"venue"
},
  "geometry": {"coordinates":[7.8991999626,47.3518257141],"type":"Point"}
}