{
  "type": "Feature",
  "properties": {
    "iso:country":"CH",
    "sg:address":"Haldenstrasse Gamprin",
    "sg:city":"Gamprin-bendern",
    "sg:orig_category":"Vorschulen, Kinderg\u00e4rten",
    "sg:phone":"+41 75 373 63 40",
    "sg:postcode":"9487",
    "wof:name":"Kindergarten Gamprin",
    "wof:placetype":"venue"
},
  "geometry": {"coordinates":[9.511639595,47.2190589905],"type":"Point"}
}