{
  "type": "Feature",
  "properties": {
    "iso:country":"CH",
    "sg:address":"Fauvettes Chemin Des 3",
    "sg:city":"Avenches",
    "sg:orig_category":"Non-Classified Establishments",
    "sg:phone":"+41 26 675 42 41",
    "sg:postcode":"1580",
    "sg:province":"Vaud",
    "wof:name":"Natascha Vioget",
    "wof:placetype":"venue"
},
  "geometry": {"coordinates":[7.0407848358,46.8800582886],"type":"Point"}
}