{
  "type": "Feature",
  "properties": {
    "iso:country":"CH",
    "sg:address":"Mondmattli 5 6375 Beckenried. Postfach",
    "sg:city":"Beckenried",
    "sg:orig_category":"Gesundheitswesen",
    "sg:postcode":"6375",
    "sg:province":"Nidwalden",
    "wof:name":"Medicons Gmbh Wissenschaftliche Dienst Und Beratungsleistungen Auf Den Gebieten Humanmedizin, Veterin\u00e4rmedizin, Pharmazie",
    "wof:placetype":"venue"
},
  "geometry": {"coordinates":[8.4736452103,46.9674072266],"type":"Point"}
}