{
  "type": "Feature",
  "properties": {
    "iso:country":"CH",
    "sg:address":"Staatsstrasse 985 B 3800 Sundlauenen. Postfach",
    "sg:city":"Kiental",
    "sg:orig_category":"Druck ohne Zeitungsdruck",
    "sg:postcode":"3723",
    "sg:province":"Bern",
    "wof:name":"Schmidli Reto + Co, Identity Publishers",
    "wof:placetype":"venue"
},
  "geometry": {"coordinates":[7.7951002121,46.6874656677],"type":"Point"}
}