{
  "type": "Feature",
  "properties": {
    "iso:country":"CH",
    "sg:address":"H\u00fcsliweg 8 8401 Winterthur. Postfach 1103",
    "sg:city":"Winterthur",
    "sg:orig_category":"Wirtschaftspr\u00fcfung, Steuerberatung U Treuhand",
    "sg:phone":"+41 52 654 17 00",
    "sg:postcode":"8401",
    "sg:province":"Z\u00fcrich",
    "wof:name":"Cti Treuhand & Informatik M\u00fchlethaler Treuhand- U. Informatikdienstleistungen. Hard, Software; Verkauf",
    "wof:placetype":"venue"
},
  "geometry": {"coordinates":[8.7621011734,47.48279953],"type":"Point"}
}