{
  "type": "Feature",
  "properties": {
    "iso:country":"CH",
    "sg:address":"Oberblacki",
    "sg:city":"Unter\u00e4geri",
    "sg:orig_category":"Sonstige mit der Informatik verbundene T\u00e4tigkeiten",
    "sg:postcode":"6314",
    "sg:province":"Zug",
    "wof:name":"Mg Consulting Gmbh",
    "wof:placetype":"venue"
},
  "geometry": {"coordinates":[8.2131624222,47.4590110779],"type":"Point"}
}