{
  "type": "Feature",
  "properties": {
    "iso:country":"CH",
    "sg:address":"Z\u00fcrcherstrasse 25 8102 Oberengstringen. Postfach 68",
    "sg:city":"Oberengstringen",
    "sg:orig_category":"Detailhandel mit Radio U Fernsehger\u00e4ten Herstellung von Radio U Fernsehger\u00e4ten sowie phono U videote",
    "sg:phone":"+41 17756990",
    "sg:postcode":"8102",
    "sg:province":"Z\u00fcrich",
    "wof:name":"Limmatronic Gmbh - Video Hifi Pc",
    "wof:placetype":"venue"
},
  "geometry": {"coordinates":[8.4748868942,47.405330658],"type":"Point"}
}