{
  "type": "Feature",
  "properties": {
    "iso:country":"CH",
    "sg:address":"Gartenstrasse 26",
    "sg:city":"Rehetobel",
    "sg:orig_category":"Architektur U Ingenieurb\u00fcros",
    "sg:phone":"+41 71 877 25 35",
    "sg:postcode":"9038",
    "sg:province":"Appenzell Ausserrhoden",
    "wof:name":"Gc+t Gusset Consulting + Trading Ag",
    "wof:placetype":"venue"
},
  "geometry": {"coordinates":[9.484714,47.424927],"type":"Point"}
}