{
  "type": "Feature",
  "properties": {
    "iso:country":"CH",
    "sg:address":"R\u00fctersp\u00fclstrasse 1",
    "sg:city":"Neerach",
    "sg:orig_category":"Unternehmensberatung",
    "sg:postcode":"8173",
    "sg:province":"Z\u00fcrich",
    "wof:name":"Bepartner Gmbh",
    "wof:placetype":"venue"
},
  "geometry": {"coordinates":[8.4740352631,47.5153617859],"type":"Point"}
}