{
  "type": "Feature",
  "properties": {
    "iso:country":"CH",
    "sg:address":"Rue Du Bourgo 5 1630 Bulle Case Postale 72",
    "sg:city":"Bulle",
    "sg:orig_category":"Herstellung von Reiseartikeln, Leder U Sattlerwaren",
    "sg:phone":"+41 26 912 01 10",
    "sg:postcode":"1630",
    "sg:province":"Fribourg",
    "wof:name":"Sellerie Du Bourgo Sa",
    "wof:placetype":"venue"
},
  "geometry": {"coordinates":[7.0576500893,46.6139564514],"type":"Point"}
}