{
  "type": "Feature",
  "properties": {
    "iso:country":"CH",
    "sg:address":"Vogelsang",
    "sg:city":"Domat/ems",
    "sg:orig_category":"Sportschulen",
    "sg:phone":"+41 81 633 52 50",
    "sg:postcode":"7013",
    "sg:province":"Graubunden",
    "wof:name":"Broersen Peter",
    "wof:placetype":"venue"
},
  "geometry": {"coordinates":[9.4398889542,46.8272399902],"type":"Point"}
}