{
  "type": "Feature",
  "properties": {
    "iso:country":"CH",
    "sg:address":"Friedheimstrasse 15",
    "sg:city":"Thun",
    "sg:orig_category":"Sonstiges Gesundheitswesen",
    "sg:phone":"+41 33 222 10 38",
    "sg:postcode":"3600",
    "sg:province":"Bern",
    "wof:name":"Krankenmobilienmagazin Des Samaritervereins Thun",
    "wof:placetype":"venue"
},
  "geometry": {"coordinates":[7.6174111366,46.7553329468],"type":"Point"}
}