{
  "type": "Feature",
  "properties": {
    "iso:country":"CH",
    "sg:address":"Einkaufszentrum Tivoli",
    "sg:city":"Spreitenbach",
    "sg:orig_category":"Herstellung von Teilen U Zubeh\u00f6r f\u00fcr Automobile",
    "sg:phone":"+41 56 401 38 14",
    "sg:postcode":"8957",
    "sg:province":"Aargau",
    "wof:name":"Sevim",
    "wof:placetype":"venue"
},
  "geometry": {"coordinates":[8.3656835556,47.4180450439],"type":"Point"}
}