{
  "type": "Feature",
  "properties": {
    "addr:full":"Aire-la-ville Route D' 234 1242 Satigny. Postfach Satigny Gen\u00e8ve 1242",
    "addr:housenumber":"aire-la-ville;234",
    "addr:postcode":"1242;postfach;1242",
    "addr:street":"Route D '",
    "iso:country":"CH",
    "sg:address":"Aire-la-ville Route D' 234 1242 Satigny. Postfach",
    "sg:city":"Satigny",
    "sg:orig_category":"Detailhandel mit Brot, Back U S\u00fcsswaren",
    "sg:postcode":"1242",
    "sg:province":"Gen\u00e8ve",
    "wof:name":"Autre Chose Sarl",
    "wof:placetype":"venue"
},
  "geometry": {"coordinates":[6.03302,46.215481],"type":"Point"}
}