{
  "type": "Feature",
  "properties": {
    "iso:country":"CH",
    "sg:address":"Aire-la-ville Route D' 234 1242 Satigny. Postfach",
    "sg:city":"Satigny",
    "sg:orig_category":"Detailhandel mit Brot, Back U S\u00fcsswaren",
    "sg:postcode":"1242",
    "sg:province":"Gen\u00e8ve",
    "wof:name":"Autre Chose Sarl",
    "wof:placetype":"venue"
},
  "geometry": {"coordinates":[6.03302,46.215481],"type":"Point"}
}