{
  "type": "Feature",
  "properties": {
    "iso:country":"CH",
    "sg:address":"Neugrundstrasse 1",
    "sg:city":"Fehraltorf",
    "sg:orig_category":"Maschinen-Fabrikation",
    "sg:phone":"+41 19541885",
    "sg:postcode":"8320",
    "sg:province":"Z\u00fcrich",
    "wof:name":"Schwarz Hans Techn. B\u00fcro + Industriegrafik",
    "wof:placetype":"venue"
},
  "geometry": {"coordinates":[8.7554912567,47.3873214722],"type":"Point"}
}