{
  "type": "Feature",
  "properties": {
    "iso:country":"CH",
    "sg:address":"Dorigny 1022 Chavannes-renens. Postfach",
    "sg:city":"Chavannes-renens",
    "sg:orig_category":"Detailhandel mit Waren verschiedener Art, Hauptrichtung Nahrungsmittel",
    "sg:postcode":"1022",
    "sg:province":"Vaud",
    "wof:name":"M\u00e9diterran\u00e9e Alimentation Traiteur S\u00e0rl",
    "wof:placetype":"venue"
},
  "geometry": {"coordinates":[6.5772900581,46.5327987671],"type":"Point"}
}