{
  "type": "Feature",
  "properties": {
    "iso:country":"CH",
    "sg:address":"Gewerbestrasse 11",
    "sg:city":"Cham",
    "sg:orig_category":"Herstellung von Betonerzeugnissen f\u00fcr den Bau Herstellung von elektronischen Bauelementen",
    "sg:phone":"+41 41 720 23 91",
    "sg:postcode":"6330",
    "sg:province":"Zug",
    "wof:name":"Imes Ag",
    "wof:placetype":"venue"
},
  "geometry": {"coordinates":[8.4720430374,47.1886940002],"type":"Point"}
}