{
  "type": "Feature",
  "properties": {
    "iso:country":"CH",
    "sg:address":"1148",
    "sg:city":"L'isle",
    "sg:orig_category":"Sonstiger Fachdetailhandel mit Nahrungsmitteln, Getr\u00e4nken U Tabak in Verkaufsr\u00e4umen",
    "sg:phone":"+41 21 864 51 18",
    "sg:postcode":"1148",
    "sg:province":"Vaud",
    "wof:name":"Magnin, A.",
    "wof:placetype":"venue"
},
  "geometry": {"coordinates":[-93.47286224370001,46.1380386353],"type":"Point"}
}