{
  "type": "Feature",
  "properties": {
    "addr:full":"Place De La Gare Oron-le-ch\u00e2tel Fribourg 1608",
    "addr:postcode":"1608",
    "addr:street":"Place De La Gare",
    "iso:country":"CH",
    "sg:address":"Place De La Gare",
    "sg:city":"Oron-le-ch\u00e2tel",
    "sg:classifiers":[
        {
            "category":"Bars & Pubs",
            "type":"Food & Drink"
        }
    ],
    "sg:phone":"+41 21 907 72 91",
    "sg:postcode":"1608",
    "sg:province":"Fribourg",
    "wof:name":"Darling Pub",
    "wof:placetype":"venue"
},
  "geometry": {"coordinates":[6.837176,46.572884],"type":"Point"}
}