{
  "type": "Feature",
  "properties": {
    "iso:country":"CH",
    "sg:address":"Brunngasse 4",
    "sg:city":"Herzogenbuchsee",
    "sg:orig_category":"Massagestudios",
    "sg:phone":"+41 62 929 24 46",
    "sg:postcode":"3360",
    "sg:province":"Bern",
    "wof:name":"Robert Merz Massage",
    "wof:placetype":"venue"
},
  "geometry": {"coordinates":[7.8212761879,47.238822937],"type":"Point"}
}