{
  "type": "Feature",
  "properties": {
    "iso:country":"CH",
    "sg:address":"Wieshofstrasse 27",
    "sg:city":"Winterthur",
    "sg:orig_category":"Architekturb\u00fcros",
    "sg:phone":"+41 52 222 31 82",
    "sg:postcode":"8408",
    "sg:province":"Z\u00fcrich",
    "wof:name":"Lothar Moser Atelier F. Architektur&planung",
    "wof:placetype":"venue"
},
  "geometry": {"coordinates":[8.68216,47.50491],"type":"Point"}
}