{
  "type": "Feature",
  "properties": {
    "iso:country":"CH",
    "sg:address":"Schaffhauserstrasse 135 8302 Kloten. Postfach",
    "sg:city":"Kloten",
    "sg:orig_category":"Non-Classified Establishments",
    "sg:postcode":"8302",
    "sg:province":"Z\u00fcrich",
    "wof:name":"Ideen Gmbh",
    "wof:placetype":"venue"
},
  "geometry": {"coordinates":[8.5806035995,47.4518051147],"type":"Point"}
}