{
  "type": "Feature",
  "properties": {
    "iso:country":"CH",
    "sg:address":"Wiesli 6",
    "sg:city":"Glarus",
    "sg:orig_category":"Wirtschaftspr\u00fcfung, Steuerberatung U Treuhand",
    "sg:postcode":"8750",
    "sg:province":"Glarus",
    "wof:name":"Rkt-trust Ag",
    "wof:placetype":"venue"
},
  "geometry": {"coordinates":[9.0680904388,47.0399703979],"type":"Point"}
}