{
  "type": "Feature",
  "properties": {
    "iso:country":"CH",
    "sg:address":"Seestrasse 152 8810 Horgen. Postfach",
    "sg:city":"Horgen",
    "sg:orig_category":"Detailhandel mit Brillen U anderen Sehhilfen Detailhandel mit Uhren U Schmuck",
    "sg:phone":"+41 17258544",
    "sg:postcode":"8810",
    "sg:province":"Z\u00fcrich",
    "wof:name":"Vogt Ag Brillenmode Uhren-schmuck",
    "wof:placetype":"venue"
},
  "geometry": {"coordinates":[8.598167,47.260105],"type":"Point"}
}