{
  "type": "Feature",
  "properties": {
    "iso:country":"CH",
    "sg:address":"Scholtinoss 7",
    "sg:city":"Niederhelfenschwil",
    "sg:orig_category":"Sportvereine Ballsport Handball",
    "sg:phone":"+41 71 947 22 52",
    "sg:postcode":"9527",
    "sg:province":"St. Gallen",
    "wof:name":"Ktv Wil",
    "wof:placetype":"venue"
},
  "geometry": {"coordinates":[9.1853122711,47.4774589539],"type":"Point"}
}