{
  "type": "Feature",
  "properties": {
    "iso:country":"CH",
    "sg:address":"Lettenstrasse 39",
    "sg:city":"M\u00e4genwil",
    "sg:orig_category":"Gartenbau",
    "sg:phone":"+41 62 896 12 49",
    "sg:postcode":"5506",
    "sg:province":"Aargau",
    "wof:name":"Fritz Borner G\u00e4rtnerei",
    "wof:placetype":"venue"
},
  "geometry": {"coordinates":[8.2331256866,47.4111938477],"type":"Point"}
}