{
  "type": "Feature",
  "properties": {
    "iso:country":"CH",
    "sg:address":"Endweg",
    "sg:city":"Grindelwald",
    "sg:orig_category":"Maler U Glasergewerbe",
    "sg:postcode":"3818",
    "sg:province":"Bern",
    "wof:name":"A. Kissling-class",
    "wof:placetype":"venue"
},
  "geometry": {"coordinates":[8.029299736,46.6215133667],"type":"Point"}
}