{
  "type": "Feature",
  "properties": {
    "iso:country":"CH",
    "sg:address":"Hammerstrasse 10 4058 Basel. Postfach",
    "sg:city":"Basel",
    "sg:orig_category":"Verwaltung von Immobilien",
    "sg:phone":"+41 79 652 50 26",
    "sg:postcode":"4012",
    "sg:province":"Basel-Stadt",
    "wof:name":"Guy Blum Immobilien-& Verm\u00f6gensverw.",
    "wof:placetype":"venue"
},
  "geometry": {"coordinates":[7.5984349251,47.5596504211],"type":"Point"}
}