{
  "type": "Feature",
  "properties": {
    "iso:country":"CH",
    "sg:address":"Rothstrasse 3 8057 Z\u00fcrich. Postfach",
    "sg:city":"Z\u00fcrich",
    "sg:orig_category":"Herstellung von medizinischen U chirurgischen Ger\u00e4ten sowie orthop\u00e4dischen Vorrichtungen",
    "sg:phone":"+41 13613302",
    "sg:postcode":"8057",
    "sg:province":"Z\u00fcrich",
    "wof:name":"Ops - Care Gysin Hans-j\u00fcrg Medizinalprodukte; Handel",
    "wof:placetype":"venue"
},
  "geometry": {"coordinates":[8.5345907211,47.3930854797],"type":"Point"}
}