{
  "type": "Feature",
  "properties": {
    "iso:country":"CH",
    "sg:address":"Rue Pierre-aeby 10",
    "sg:city":"Freiburg",
    "sg:orig_category":"Unclassifiable Establishments",
    "sg:postcode":"1700",
    "sg:province":"Fribourg",
    "wof:name":"Fondation Pour Une Terre Humaine",
    "wof:placetype":"venue"
},
  "geometry": {"coordinates":[7.1600670815,46.8076248169],"type":"Point"}
}