{
  "type": "Feature",
  "properties": {
    "iso:country":"CH",
    "sg:address":"Zugerstrasse 76b 6340 Baar. Postfach 448",
    "sg:city":"Baar",
    "sg:orig_category":"Herstellung von Metallerzeugnissen ohne Maschinenbau Herstellung von k\u00e4lte U lufttechnischen Erzeugn",
    "sg:phone":"+41 41 767 28 38",
    "sg:postcode":"6341",
    "sg:province":"Zug",
    "wof:name":"Gwl Ag",
    "wof:placetype":"venue"
},
  "geometry": {"coordinates":[8.519613266,47.1831130981],"type":"Point"}
}