{
  "type": "Feature",
  "properties": {
    "iso:country":"CH",
    "sg:address":"Rue De La Tannerie 2",
    "sg:city":"Bassecourt",
    "sg:classifiers":[
        {
            "category":"Restaurant",
            "type":"Food & Drink"
        }
    ],
    "sg:phone":"+41 32 426 71 25",
    "sg:postcode":"2854",
    "sg:province":"Jura",
    "wof:name":"Caf\u00e9 Suisse",
    "wof:placetype":"venue"
},
  "geometry": {"coordinates":[7.2465090752,47.3390388489],"type":"Point"}
}