{
  "type": "Feature",
  "properties": {
    "iso:country":"CH",
    "sg:address":"Rue De Lorette 63",
    "sg:city":"Porrentruy",
    "sg:orig_category":"Berufliche Weiterbildung, Erwachsenenbildung",
    "sg:phone":"+41 32 466 60 24",
    "sg:postcode":"2900",
    "sg:province":"Jura",
    "wof:name":"Universit\u00e9 Popul.jurasienne Madame Huguette Chapuis",
    "wof:placetype":"venue"
},
  "geometry": {"coordinates":[7.085109,47.424927],"type":"Point"}
}