{
  "type": "Feature",
  "properties": {
    "iso:country":"CH",
    "sg:address":"Wynigenstrasse 4 3400 Burgdorf. Postfach",
    "sg:city":"Burgdorf",
    "sg:orig_category":"Gesundheitswesen Herstellung von nachrichtentechnischen Ger\u00e4ten U Einrichtungen",
    "sg:phone":"+41 19521272",
    "sg:postcode":"3402",
    "sg:province":"Bern",
    "wof:name":"Telemedizin Ag",
    "wof:placetype":"venue"
},
  "geometry": {"coordinates":[8.7838087082,47.3664093018],"type":"Point"}
}