{
  "type": "Feature",
  "properties": {
    "iso:country":"CH",
    "sg:address":"Burgstrasse 20",
    "sg:city":"Thun",
    "sg:classifiers":[
        {
            "category":"Restaurant",
            "type":"Food & Drink"
        }
    ],
    "sg:phone":"+41 33 223 17 07",
    "sg:postcode":"3600",
    "sg:province":"Bern",
    "wof:name":"Pizzeria Castello",
    "wof:placetype":"venue"
},
  "geometry": {"coordinates":[7.6293182373,46.7614021301],"type":"Point"}
}