{
  "type": "Feature",
  "properties": {
    "iso:country":"CH",
    "sg:address":"Chilchackerstrasse 24",
    "sg:city":"Koppigen",
    "sg:orig_category":"Sportvereine Turnen Vereine Damen",
    "sg:phone":"+41 34 413 17 80",
    "sg:postcode":"3425",
    "sg:province":"Bern",
    "wof:name":"Damenturnverein Solothurn",
    "wof:placetype":"venue"
},
  "geometry": {"coordinates":[7.6028208733,47.1359024048],"type":"Point"}
}