{
  "type": "Feature",
  "properties": {
    "iso:country":"CH",
    "sg:address":"Wydenstrasse 15",
    "sg:city":"Niederbipp",
    "sg:orig_category":"Kantonalbanken",
    "sg:phone":"+41 32 633 23 44",
    "sg:postcode":"4704",
    "sg:province":"Bern",
    "wof:name":"Berner Kantonalbank Bekb/bcbe",
    "wof:placetype":"venue"
},
  "geometry": {"coordinates":[7.6919698715,47.2710494995],"type":"Point"}
}