{
  "type": "Feature",
  "properties": {
    "iso:country":"CH",
    "sg:address":"Kirchstrasse 64",
    "sg:city":"Rorschach",
    "sg:classifiers":[
        {
            "category":"Restaurant",
            "type":"Food & Drink"
        }
    ],
    "sg:phone":"+41 71 841 26 53",
    "sg:postcode":"9400",
    "sg:province":"St. Gallen",
    "wof:name":"Restaurant Metropol",
    "wof:placetype":"venue"
},
  "geometry": {"coordinates":[9.4871931076,47.4780273438],"type":"Point"}
}