{
  "type": "Feature",
  "properties": {
    "iso:country":"CH",
    "sg:address":"Geisslooweg 9",
    "sg:city":"Bassersdorf",
    "sg:orig_category":"Sonstige mit der Informatik verbundene T\u00e4tigkeiten",
    "sg:postcode":"8303",
    "sg:province":"Z\u00fcrich",
    "wof:name":"Dahl Consulting",
    "wof:placetype":"venue"
},
  "geometry": {"coordinates":[8.6409139633,47.4388275146],"type":"Point"}
}