{
  "type": "Feature",
  "properties": {
    "iso:country":"CH",
    "sg:address":"Untere B\u00f6nigstrasse 10a",
    "sg:city":"Interlaken",
    "sg:orig_category":"Sonstige mit der Informatik verbundene T\u00e4tigkeiten",
    "sg:postcode":"3800",
    "sg:province":"Bern",
    "wof:name":"Bitsoft 2000 Gmbh Edv, Software; Beratung, Entwicklung",
    "wof:placetype":"venue"
},
  "geometry": {"coordinates":[7.9204740524,47.3210678101],"type":"Point"}
}