{
  "type": "Feature",
  "properties": {
    "addr:full":"Rue Industrielle 30 Montreux Vaud 1820",
    "addr:housenumber":"30",
    "addr:postcode":"1820",
    "addr:street":"Rue Industrielle",
    "iso:country":"CH",
    "sg:address":"Rue Industrielle 30",
    "sg:city":"Montreux",
    "sg:orig_category":"Betrieb von Taxis",
    "sg:postcode":"1820",
    "sg:province":"Vaud",
    "wof:name":"Taxi Thoma, Fernand Et Martina Thoma",
    "wof:placetype":"venue"
},
  "geometry": {"coordinates":[6.913414,46.433182],"type":"Point"}
}