{
  "type": "Feature",
  "properties": {
    "iso:country":"CH",
    "sg:address":"Sihlbruggstrasse 105a",
    "sg:city":"Baar",
    "sg:orig_category":"Sonstiger Fachdetailhandel mit Nahrungsmitteln, Getr\u00e4nken U Tabak in Verkaufsr\u00e4umen",
    "sg:phone":"+41 41 760 63 60",
    "sg:postcode":"6340",
    "sg:province":"Zug",
    "wof:name":"Silat Ag",
    "wof:placetype":"venue"
},
  "geometry": {"coordinates":[8.5390930176,47.1977767944],"type":"Point"}
}