{
  "type": "Feature",
  "properties": {
    "iso:country":"CH",
    "sg:address":"Grand'rue 19",
    "sg:city":"Gland",
    "sg:orig_category":"Non-Classified Establishments",
    "sg:phone":"+41 21 635 35 27",
    "sg:postcode":"1196",
    "sg:province":"Vaud",
    "wof:name":"Michel Gailloud Marbrerie",
    "wof:placetype":"venue"
},
  "geometry": {"coordinates":[6.5822072029,46.5343666077],"type":"Point"}
}