{
  "type": "Feature",
  "properties": {
    "iso:country":"CH",
    "sg:address":"Allmendstrasse 1",
    "sg:city":"Zunzgen",
    "sg:orig_category":"Wirtschaftspr\u00fcfung, Steuerberatung U Treuhand",
    "sg:phone":"+41 21 965 17 65",
    "sg:postcode":"4455",
    "sg:province":"Basel-Landschaft",
    "wof:name":"D. Montessius Sa Fiduciaire",
    "wof:placetype":"venue"
},
  "geometry": {"coordinates":[6.9120240211,46.4321403503],"type":"Point"}
}