{
  "type": "Feature",
  "properties": {
    "iso:country":"CH",
    "sg:address":"Kreuzlingerstrasse 132",
    "sg:city":"Oberaach",
    "sg:orig_category":"Detailhandel mit Waren verschiedener Art in Verkaufsr\u00e4umen Fachdetailhandel mit Nahrungsmitteln, Get",
    "sg:phone":"+41 21 960 27 19",
    "sg:postcode":"8587",
    "sg:province":"Thurgau",
    "wof:name":"Otto's Ag",
    "wof:placetype":"venue"
},
  "geometry": {"coordinates":[6.9333348274,46.3521118164],"type":"Point"}
}