{
  "type": "Feature",
  "properties": {
    "iso:country":"CH",
    "sg:address":"Obstbergweg 2",
    "sg:city":"Bern",
    "sg:orig_category":"Fotografische Ateliers",
    "sg:phone":"+41 31 352 30 55",
    "sg:postcode":"3006",
    "sg:province":"Bern",
    "wof:name":"Matthias Wyssenbach Fotografisches Atelier",
    "wof:placetype":"venue"
},
  "geometry": {"coordinates":[7.4607868195,46.9466972351],"type":"Point"}
}