{
  "type": "Feature",
  "properties": {
    "iso:country":"CH",
    "sg:address":"Roux Rue Dr C\u00e9sar- 13",
    "sg:city":"Lausanne",
    "sg:orig_category":"Elektroinstallation",
    "sg:postcode":"1005",
    "sg:province":"Vaud",
    "wof:name":"Ortiz Roland \u00e9lectricit\u00e9",
    "wof:placetype":"venue"
},
  "geometry": {"coordinates":[6.6381421089,46.5243225098],"type":"Point"}
}