{
  "type": "Feature",
  "properties": {
    "iso:country":"CH",
    "sg:address":"Aar\u00fctistrasse 39",
    "sg:city":"Glattfelden",
    "sg:orig_category":"G\u00fcterbef\u00f6rderung im Strassenverkehr",
    "sg:phone":"+41 79 420 77 34",
    "sg:postcode":"8192",
    "sg:province":"Z\u00fcrich",
    "wof:name":"Kl\u00e4usli Transporte Ag",
    "wof:placetype":"venue"
},
  "geometry": {"coordinates":[8.4883899689,47.5601997375],"type":"Point"}
}