{
  "type": "Feature",
  "properties": {
    "iso:country":"CH",
    "sg:address":"6930",
    "sg:city":"Bedano",
    "sg:orig_category":"G\u00fcterbef\u00f6rderung im Strassenverkehr",
    "sg:phone":"+41 27 283 16 77",
    "sg:postcode":"6930",
    "sg:province":"Ticino",
    "wof:name":"Anz\u00e9vui-rumpf Henri",
    "wof:placetype":"venue"
},
  "geometry": {"coordinates":[7.5053100586,46.0833053589],"type":"Point"}
}