{
  "type": "Feature",
  "properties": {
    "iso:country":"CH",
    "sg:address":"H\u00f6henweg 258",
    "sg:city":"Biberstein",
    "sg:orig_category":"Aktivit\u00e4ten der Generalunternehmen im Baugewerbe",
    "sg:phone":"+41 62 827 27 23",
    "sg:postcode":"5023",
    "sg:province":"Aargau",
    "wof:name":"Gheld Gmbh",
    "wof:placetype":"venue"
},
  "geometry": {"coordinates":[8.080716,47.41489],"type":"Point"}
}