{
  "type": "Feature",
  "properties": {
    "iso:country":"CH",
    "sg:address":"Schulhausstr. 18a. 3063 Ittigen. Postfach",
    "sg:city":"Zollikofen",
    "sg:orig_category":"Mit dem Versicherungsgewerbe verbundene T\u00e4tigkeiten",
    "sg:phone":"+41 21 351 90 90",
    "sg:postcode":"3052",
    "sg:province":"Bern",
    "wof:name":"Michel Perret, Conseiller Toutes Assurances",
    "wof:placetype":"venue"
},
  "geometry": {"coordinates":[6.6774148941,46.5133132935],"type":"Point"}
}