{
  "type": "Feature",
  "properties": {
    "iso:country":"CH",
    "sg:address":"Weinmarkt 11",
    "sg:city":"Luzern",
    "sg:orig_category":"Gesundheitswesen",
    "sg:phone":"+41 41 410 54 61",
    "sg:postcode":"6004",
    "sg:province":"Luzern",
    "wof:name":"Medistat Medical Data Services Ltd",
    "wof:placetype":"venue"
},
  "geometry": {"coordinates":[8.304186821,47.0519752502],"type":"Point"}
}