{
  "type": "Feature",
  "properties": {
    "iso:country":"CH",
    "sg:address":"Rue Des Vollandes 10",
    "sg:city":"Gen\u00e8ve",
    "sg:orig_category":"Massagestudios",
    "sg:phone":"+41 22 786 57 30",
    "sg:postcode":"1207",
    "sg:province":"Gen\u00e8ve",
    "wof:name":"Bermudes Massage De Sant\u00e9",
    "wof:placetype":"venue"
},
  "geometry": {"coordinates":[6.1596231461,46.2055969238],"type":"Point"}
}