{
  "type": "Feature",
  "properties": {
    "iso:country":"CH",
    "sg:address":"Stadtplatz 36",
    "sg:city":"Aarberg",
    "sg:orig_category":"Detailhandel mit Blumen U Pflanzen Fachdetailhandel in Verkaufsr\u00e4umen",
    "sg:phone":"+41 32 392 12 23",
    "sg:postcode":"3270",
    "sg:province":"Bern",
    "wof:name":"Hans Salchli Blumengesch\u00e4ft",
    "wof:placetype":"venue"
},
  "geometry": {"coordinates":[7.275808,47.044529],"type":"Point"}
}