{
  "type": "Feature",
  "properties": {
    "iso:country":"CH",
    "sg:address":"Tscharnerstrasse 39",
    "sg:city":"Bern",
    "sg:orig_category":"Grosshandel mit Maschinen U Ausr\u00fcstungen Herstellung von sonstigen Maschinen f\u00fcr unspezifische Verwe",
    "sg:phone":"+41 31 381 31 10",
    "sg:postcode":"3007",
    "sg:province":"Bern",
    "wof:name":"Rapack Ag",
    "wof:placetype":"venue"
},
  "geometry": {"coordinates":[7.4274401665,46.9425468445],"type":"Point"}
}