{
  "type": "Feature",
  "properties": {
    "iso:country":"CH",
    "sg:address":"Poststrasse 2 3073 G\u00fcmligen. Postfach",
    "sg:city":"G\u00fcmligen",
    "sg:orig_category":"Detailhandel mit Schuhen U Lederwaren",
    "sg:phone":"+41 31 951 00 72",
    "sg:postcode":"3073",
    "sg:province":"Bern",
    "wof:name":"Schuh Mode Dill Ag",
    "wof:placetype":"venue"
},
  "geometry": {"coordinates":[7.507393837,46.9341506958],"type":"Point"}
}