{
  "type": "Feature",
  "properties": {
    "iso:country":"CH",
    "sg:address":"Dorfstrasse 36",
    "sg:city":"Wittenbach",
    "sg:orig_category":"RESTAURANTS: TEA-ROOMS",
    "sg:phone":"+41 71 298 33 83",
    "sg:postcode":"9303",
    "wof:name":"Restaurant Hirschen Trunz Werner",
    "wof:placetype":"venue"
},
  "geometry": {"coordinates":[9.3797130585,47.4635658264],"type":"Point"}
}