{
  "type": "Feature",
  "properties": {
    "iso:country":"CH",
    "sg:address":"Domino 355",
    "sg:city":"Frasnacht",
    "sg:orig_category":"Sonstiger Grosshandel",
    "sg:postcode":"9320",
    "sg:province":"Thurgau",
    "wof:name":"Pasa Lo Nigro",
    "wof:placetype":"venue"
},
  "geometry": {"coordinates":[7.2394890785,46.9021644592],"type":"Point"}
}