{
  "type": "Feature",
  "properties": {
    "iso:country":"CH",
    "sg:address":"Missionsstrasse 16",
    "sg:city":"Basel",
    "sg:orig_category":"Innendekorationsateliers",
    "sg:phone":"+41 61 261 31 91",
    "sg:postcode":"4055",
    "sg:province":"Basel-Stadt",
    "wof:name":"Rosmarie Meyer Innendecor-atelier",
    "wof:placetype":"venue"
},
  "geometry": {"coordinates":[7.5790448189,47.5593261719],"type":"Point"}
}