{
  "type": "Feature",
  "properties": {
    "iso:country":"CH",
    "sg:address":"Rue Du Vieux-moulin 55b",
    "sg:city":"Court\u00e9telle",
    "sg:orig_category":"Autospenglereien Instandhaltung U Reparatur von Automobilen",
    "sg:phone":"+41 32 751 21 18",
    "sg:postcode":"2852",
    "sg:province":"Jura",
    "wof:name":"Carrosserie Du Landeron Rollier Thierry",
    "wof:placetype":"venue"
},
  "geometry": {"coordinates":[7.070836,47.054245],"type":"Point"}
}