{
  "type": "Feature",
  "properties": {
    "iso:country":"CH",
    "sg:address":"Via Maistra",
    "sg:city":"Pontresina",
    "sg:orig_category":"Detailhandel mit Sportartikeln Fachdetailhandel in Verkaufsr\u00e4umen",
    "sg:phone":"+41 81 842 64 37",
    "sg:postcode":"7504",
    "sg:province":"Graubunden",
    "wof:name":"Montanara Sport Ag",
    "wof:placetype":"venue"
},
  "geometry": {"coordinates":[9.9069499969,46.487865448],"type":"Point"}
}