{
  "type": "Feature",
  "properties": {
    "iso:country":"CH",
    "sg:address":"Rue Du Fuet 1",
    "sg:city":"Tavannes",
    "sg:orig_category":"Mechanik Mechanische Werkst\u00e4tten",
    "sg:phone":"+41 32 481 51 39",
    "sg:postcode":"2710",
    "sg:province":"Bern",
    "wof:name":"Alfredo Ripamonti Atelier M\u00e9canique",
    "wof:placetype":"venue"
},
  "geometry": {"coordinates":[7.2023129463,47.2249832153],"type":"Point"}
}