{
  "type": "Feature",
  "properties": {
    "addr:full":"Chemin Des Peupliers 6 Pr\u00e9verenges Vaud 1028",
    "addr:housenumber":"6",
    "addr:postcode":"1028",
    "addr:street":"Chemin Des Peupliers",
    "iso:country":"CH",
    "sg:address":"Chemin Des Peupliers 6",
    "sg:city":"Pr\u00e9verenges",
    "sg:orig_category":"Bauschreinerei Herstellung von Konstruktionsteilen, Fertigbauteilen U Ausbauelementen aus Holz",
    "sg:phone":"+41 21 801 30 30",
    "sg:postcode":"1028",
    "sg:province":"Vaud",
    "wof:name":"Gillard Jean-marc",
    "wof:placetype":"venue"
},
  "geometry": {"coordinates":[6.514514,46.518124],"type":"Point"}
}