{
  "type": "Feature",
  "properties": {
    "iso:country":"CH",
    "sg:address":"Hohlenhausweg 7",
    "sg:city":"Oberdiessbach",
    "sg:orig_category":"Kunsthandel",
    "sg:phone":"+41 31 771 18 89",
    "sg:postcode":"3672",
    "sg:province":"Bern",
    "wof:name":"Galerie M & M St\u00e4hli",
    "wof:placetype":"venue"
},
  "geometry": {"coordinates":[7.6242318153,46.8340034485],"type":"Point"}
}