{
  "type": "Feature",
  "properties": {
    "addr:full":"Sennheimerstrasse 42 Basel Basel-Stadt 4054",
    "addr:housenumber":"42",
    "addr:postcode":"4054",
    "addr:street":"Sennheimerstrasse",
    "iso:country":"CH",
    "sg:address":"Sennheimerstrasse 42",
    "sg:city":"Basel",
    "sg:orig_category":"Bauschreinerei Innenausbau",
    "sg:phone":"+423 373 28 83",
    "sg:postcode":"4054",
    "sg:province":"Basel-Stadt",
    "wof:name":"Salvatore Condito Schreinerei & Innenausbau",
    "wof:placetype":"venue"
},
  "geometry": {"coordinates":[9.536849,47.216705],"type":"Point"}
}