{
  "type": "Feature",
  "properties": {
    "iso:country":"CH",
    "sg:address":"En Margenoz",
    "sg:city":"Montricher",
    "sg:orig_category":"Herstellung von sonstigen landwirtschaftlichen Maschinen Instandhaltung U Reparatur von Automobilen",
    "sg:phone":"+41 21 864 53 01",
    "sg:postcode":"1147",
    "sg:province":"Vaud",
    "wof:name":"Desmeules M.",
    "wof:placetype":"venue"
},
  "geometry": {"coordinates":[6.3768401146,46.6003608704],"type":"Point"}
}