{
  "type": "Feature",
  "properties": {
    "iso:country":"CH",
    "sg:address":"Route De Neuch\u00e2tel 4",
    "sg:city":"Romanel-s-lausanne",
    "sg:orig_category":"Detailhandel mit Brot, Back U S\u00fcsswaren",
    "sg:phone":"+41 21 732 10 11",
    "sg:postcode":"1032",
    "sg:province":"Vaud",
    "wof:name":"Fr\u00e9d\u00e9ric Berset Boulangerie & P\u00e2tisserie",
    "wof:placetype":"venue"
},
  "geometry": {"coordinates":[6.603878,46.563221],"type":"Point"}
}