{
  "type": "Feature",
  "properties": {
    "iso:country":"CH",
    "sg:address":"Via Rompada",
    "sg:city":"Caslano",
    "sg:orig_category":"Herstellung von Holzstoff, Papier, Karton U Pappe Offsetdruck",
    "sg:phone":"+41 91 606 20 15",
    "sg:postcode":"6987",
    "sg:province":"Ticino",
    "wof:name":"Beli-produktions Ag Fabbr.di Album & Stampa Offset",
    "wof:placetype":"venue"
},
  "geometry": {"coordinates":[8.8764753342,45.9763908386],"type":"Point"}
}