{
  "type": "Feature",
  "properties": {
    "addr:full":"Delsbergstrasse 12 Laufen Basel-Landschaft 4242",
    "addr:housenumber":"12",
    "addr:postcode":"4242",
    "addr:street":"Delsbergstrasse",
    "iso:country":"CH",
    "sg:address":"Delsbergstrasse 12",
    "sg:city":"Laufen",
    "sg:classifiers":[
        {
            "category":"Bars & Pubs",
            "type":"Food & Drink"
        }
    ],
    "sg:phone":"+41 61 761 54 84",
    "sg:postcode":"4242",
    "sg:province":"Basel-Landschaft",
    "wof:name":"Piccadilly-pub",
    "wof:placetype":"venue"
},
  "geometry": {"coordinates":[7.50017,47.419884],"type":"Point"}
}