{
  "type": "Feature",
  "properties": {
    "iso:country":"CH",
    "sg:address":"Rue De L'orangerie 3",
    "sg:city":"Neuch\u00e2tel",
    "sg:orig_category":"Kunsthandel",
    "sg:phone":"+41 32724888",
    "sg:postcode":"2000",
    "sg:province":"Neuch\u00e2tel",
    "wof:name":"Jo Jeannet Galerie L'orangerie",
    "wof:placetype":"venue"
},
  "geometry": {"coordinates":[6.9350628853,46.9927787781],"type":"Point"}
}