{
  "type": "Feature",
  "properties": {
    "iso:country":"CH",
    "sg:address":"Grand'rue 58",
    "sg:city":"Payerne",
    "sg:orig_category":"Erbringung von Dienstleistungen f\u00fcr Unternehmen",
    "sg:postcode":"1530",
    "sg:province":"Vaud",
    "wof:name":"Arcasa Diffusion, Jeanette Huguet",
    "wof:placetype":"venue"
},
  "geometry": {"coordinates":[6.9364337921,46.8209266663],"type":"Point"}
}