{
  "type": "Feature",
  "properties": {
    "iso:country":"CH",
    "sg:address":"Rue De La Rochette 9",
    "sg:city":"Estavayer-le-lac",
    "sg:orig_category":"Organisationen des Gesundheitswesen",
    "sg:phone":"+41 81 413 43 03",
    "sg:postcode":"1470",
    "sg:province":"Fribourg",
    "wof:name":"Sozialdienst Das Band F\u00fcr Asthma-& Lungenkranke",
    "wof:placetype":"venue"
},
  "geometry": {"coordinates":[9.8198633194,46.7964019775],"type":"Point"}
}