{
  "type": "Feature",
  "properties": {
    "iso:country":"CH",
    "sg:address":"Hausackerstrasse 16",
    "sg:city":"Wiesendangen",
    "sg:orig_category":"Institutionen f\u00fcr Behinderte Wohnheime",
    "sg:phone":"+41 52 320 90 16",
    "sg:postcode":"8542",
    "sg:province":"Z\u00fcrich",
    "wof:name":"Stiftung Steinegg",
    "wof:placetype":"venue"
},
  "geometry": {"coordinates":[8.7788228989,47.5305938721],"type":"Point"}
}