{
  "type": "Feature",
  "properties": {
    "iso:country":"CH",
    "sg:address":"B\u00f6hlerstrasse 5",
    "sg:city":"Unterkulm",
    "sg:orig_category":"G\u00fcterbef\u00f6rderung im Strassenverkehr",
    "sg:phone":"+41 62 776 19 70",
    "sg:postcode":"5726",
    "sg:province":"Aargau",
    "wof:name":"Bm Transport Ag",
    "wof:placetype":"venue"
},
  "geometry": {"coordinates":[8.1114397049,47.3102340698],"type":"Point"}
}