{
  "type": "Feature",
  "properties": {
    "iso:country":"CH",
    "sg:address":"Oberdorfstrasse 1",
    "sg:city":"Eschenz",
    "sg:orig_category":"S\u00e4ge, Hobel U Holzimpr\u00e4gnierwerke S\u00e4gewerke",
    "sg:phone":"+41 32 484 98 86",
    "sg:postcode":"8264",
    "sg:province":"Thurgau",
    "wof:name":"Ets Gigandet Fr\u00e8res Sa",
    "wof:placetype":"venue"
},
  "geometry": {"coordinates":[7.131289959,47.2574310303],"type":"Point"}
}