{
  "type": "Feature",
  "properties": {
    "iso:country":"CH",
    "sg:address":"Chemin Des Pinsons 3 1000 Lausanne. Postfach",
    "sg:city":"Lausanne",
    "sg:orig_category":"Detailhandel mit Waren verschiedener Art, Hauptrichtung Nahrungsmittel",
    "sg:postcode":"1002",
    "sg:province":"Vaud",
    "wof:name":"United Agro Commodities Trading S\u00e0rl",
    "wof:placetype":"venue"
},
  "geometry": {"coordinates":[6.6578888893,46.5289077759],"type":"Point"}
}