{
  "type": "Feature",
  "properties": {
    "iso:country":"CH",
    "sg:address":"Dorfstrasse 51",
    "sg:city":"Freienstein",
    "sg:orig_category":"Arztpraxen",
    "sg:phone":"+41 18652601",
    "sg:postcode":"8427",
    "sg:province":"Z\u00fcrich",
    "wof:name":"Dr.med.peter Meili Arzt F.allgemeine Medizin Fmh",
    "wof:placetype":"venue"
},
  "geometry": {"coordinates":[8.585172,47.531246],"type":"Point"}
}