{
  "type": "Feature",
  "properties": {
    "iso:country":"CH",
    "sg:address":"Gloriastrasse 66 8044 Z\u00fcrich. Postfach",
    "sg:city":"Z\u00fcrich",
    "sg:orig_category":"Softwareentwicklung U beratung",
    "sg:phone":"+41 12621873",
    "sg:postcode":"8044",
    "sg:province":"Z\u00fcrich",
    "wof:name":"Genericpath Ag Software-komponente; Entwicklung, Produktion, Vertrieb",
    "wof:placetype":"venue"
},
  "geometry": {"coordinates":[8.5562343597,47.3759307861],"type":"Point"}
}