{
  "type": "Feature",
  "properties": {
    "iso:country":"CH",
    "sg:address":"Stationsstrasse 2",
    "sg:city":"Hettlingen",
    "sg:classifiers":[
        {
            "category":"Education",
            "subcategory":"Library",
            "type":"Public Place"
        }
    ],
    "sg:phone":"+41 52 316 19 38",
    "sg:postcode":"8442",
    "sg:province":"Z\u00fcrich",
    "sg:tags":[
        "u",
        "bibliotheken",
        "archive"
    ],
    "wof:name":"Gemeindebibliothek",
    "wof:placetype":"venue"
},
  "geometry": {"coordinates":[8.708358,47.546978],"type":"Point"}
}