{
  "type": "Feature",
  "properties": {
    "addr:full":"Moskau Ramsen Schaffhausen 8262",
    "addr:postcode":"8262",
    "addr:street":"Moskau",
    "iso:country":"CH",
    "sg:address":"Moskau",
    "sg:city":"Ramsen",
    "sg:orig_category":"Autotransporte international Sonstige Verkehrsvermittlung",
    "sg:phone":"+41 52 742 81 00",
    "sg:postcode":"8262",
    "sg:province":"Schaffhausen",
    "wof:name":"Spedition Maier Ag",
    "wof:placetype":"venue"
},
  "geometry": {"coordinates":[8.821025,47.708965],"type":"Point"}
}