{
  "type": "Feature",
  "properties": {
    "iso:country":"CH",
    "sg:address":"Abendstrasse 30/37",
    "sg:city":"Bern",
    "sg:orig_category":"Verlegen von Fliesen U Platten",
    "sg:phone":"+41 61 961 92 85",
    "sg:postcode":"3018",
    "sg:province":"Bern",
    "wof:name":"Alessandro Poggio Chemin\u00e9e-& Ofenbau Platten",
    "wof:placetype":"venue"
},
  "geometry": {"coordinates":[7.74482584,47.3936004639],"type":"Point"}
}