{
  "type": "Feature",
  "properties": {
    "iso:country":"CH",
    "sg:address":"Riehenring 101 4000 Basel. Postfach",
    "sg:city":"Basel",
    "sg:orig_category":"Sanit\u00e4r, Heizungs U L\u00fcftungsinstallation",
    "sg:postcode":"4051",
    "sg:province":"Basel-Stadt",
    "wof:name":"Spesag Ag",
    "wof:placetype":"venue"
},
  "geometry": {"coordinates":[7.5978212357,47.5656166077],"type":"Point"}
}