{
  "type": "Feature",
  "properties": {
    "iso:country":"CH",
    "sg:address":"Landstr. 9",
    "sg:city":"Wettingen",
    "sg:classifiers":[
        {
            "category":"Banks & Credit Unions",
            "subcategory":"Bank",
            "type":"Services"
        }
    ],
    "sg:phone":"+41 4156268096",
    "sg:postcode":"5430",
    "sg:province":"Aargau",
    "wof:name":"Borges Cr\u00e9dito",
    "wof:placetype":"venue"
},
  "geometry": {"coordinates":[8.317924,47.469814],"type":"Point"}
}