{
  "type": "Feature",
  "properties": {
    "iso:country":"CH",
    "sg:address":"Sihltalstrasse 1694 8135 Sihlbrugg Station. Postfach",
    "sg:city":"Z\u00fcrich",
    "sg:orig_category":"Vermietung U Verpachtung von eigenen Immobilien",
    "sg:postcode":"8023",
    "sg:province":"Z\u00fcrich",
    "wof:name":"Tag & Nacht Gastronomie Ag",
    "wof:placetype":"venue"
},
  "geometry": {"coordinates":[8.5765333176,47.2382545471],"type":"Point"}
}