{
  "type": "Feature",
  "properties": {
    "iso:country":"CH",
    "sg:address":"Prinzenhof 10",
    "sg:city":"Beringen",
    "sg:orig_category":"Herstellung von keramischen Wand U Bodenfliesen U platten Verlegen von Fliesen U Platten",
    "sg:phone":"+41 52 643 26 78",
    "sg:postcode":"8222",
    "sg:province":"Schaffhausen",
    "wof:name":"Fink + Weber Ag",
    "wof:placetype":"venue"
},
  "geometry": {"coordinates":[8.5732698441,47.7007408142],"type":"Point"}
}