{
  "type": "Feature",
  "properties": {
    "iso:country":"CH",
    "sg:address":"1544 Gletterens. Postfach",
    "sg:city":"Gletterens",
    "sg:orig_category":"RESTAURANTS: TEA-ROOMS",
    "sg:postcode":"1544",
    "sg:province":"Fribourg",
    "wof:name":"Caf\u00e9-restaurant De La Gare Chez Fran\u00e7oise",
    "wof:placetype":"venue"
},
  "geometry": {"coordinates":[-2.9729800224,48.5345497131],"type":"Point"}
}