{
  "type": "Feature",
  "properties": {
    "iso:country":"CH",
    "sg:address":"Neubadrain 1",
    "sg:city":"Binningen",
    "sg:orig_category":"Dienstleistungen von Beteiligungsgesellschaften Sprachschulen",
    "sg:phone":"+41 61 301 42 38",
    "sg:postcode":"4102",
    "sg:province":"Basel-Landschaft",
    "wof:name":"Language Studio Frau Dr.barbara C.kruschel",
    "wof:placetype":"venue"
},
  "geometry": {"coordinates":[7.5646691322,47.5454864502],"type":"Point"}
}