{
  "type": "Feature",
  "properties": {
    "iso:country":"CH",
    "sg:address":"Neuhus 976",
    "sg:city":"Hinteregg",
    "sg:classifiers":[
        {
            "category":"Autos & Motor Vehicles",
            "subcategory":"Fuel & Gas Station",
            "type":"Retail Goods"
        }
    ],
    "sg:phone":"+41 19862800",
    "sg:postcode":"8132",
    "sg:province":"Z\u00fcrich",
    "sg:tags":[
        "pump",
        "gear"
    ],
    "wof:name":"Viscotherm Ag",
    "wof:placetype":"venue"
},
  "geometry": {"coordinates":[8.6900548935,47.3005561829],"type":"Point"}
}