{
  "type": "Feature",
  "properties": {
    "iso:country":"CH",
    "sg:address":"Route Des Ronquoz",
    "sg:city":"Sion",
    "sg:orig_category":"Bauschreinerei",
    "sg:phone":"+41 27 322 01 02",
    "sg:postcode":"1950",
    "sg:province":"Valais",
    "wof:name":"Charles Rombaldi Menuiserie",
    "wof:placetype":"venue"
},
  "geometry": {"coordinates":[7.344244,46.220947],"type":"Point"}
}