{
  "type": "Feature",
  "properties": {
    "iso:country":"CH",
    "sg:address":"Avenue D'a\u00efre 89bis",
    "sg:city":"Gen\u00e8ve",
    "sg:orig_category":"Grafikateliers, Design Siebdruck",
    "sg:phone":"+41 21 729 48 49",
    "sg:postcode":"1203",
    "sg:province":"Gen\u00e8ve",
    "wof:name":"St\u00e9fano Ducommun",
    "wof:placetype":"venue"
},
  "geometry": {"coordinates":[6.6530017853,46.5167541504],"type":"Point"}
}