{
  "type": "Feature",
  "properties": {
    "iso:country":"CH",
    "sg:address":"Selzacherstrasse 23",
    "sg:city":"Selzach",
    "sg:orig_category":"Herstellung U Zusammensetzung von Uhren",
    "sg:phone":"+41 32 641 16 16",
    "sg:postcode":"2545",
    "sg:province":"Solothurn",
    "wof:name":"Charles Niklaus Terminages",
    "wof:placetype":"venue"
},
  "geometry": {"coordinates":[7.4488101006,47.1923217773],"type":"Point"}
}