{
  "type": "Feature",
  "properties": {
    "iso:country":"CH",
    "sg:address":"Freie Strasse 103 4051 Basel. Postfach",
    "sg:city":"Basel",
    "sg:orig_category":"Grosshandel mit Software Softwareentwicklung U beratung",
    "sg:phone":"+41 61 281 32 01",
    "sg:postcode":"4051",
    "sg:province":"Basel-Stadt",
    "wof:name":"Asp Pharma Ag Dienstleistungen Im Softwarebereich. Software-applikationen; Entwicklung, Verkauf Usw",
    "wof:placetype":"venue"
},
  "geometry": {"coordinates":[7.5917840004,47.5544052124],"type":"Point"}
}