{
  "type": "Feature",
  "properties": {
    "iso:country":"CH",
    "sg:address":"Galserschstrasse 30",
    "sg:city":"Flums",
    "sg:orig_category":"Malerei-Gipserei Stukkateurgewerbe, Gipserei U Verputzerei",
    "sg:phone":"+41 79 430 84 85",
    "sg:postcode":"8890",
    "sg:province":"St. Gallen",
    "wof:name":"Wildhaber Max",
    "wof:placetype":"venue"
},
  "geometry": {"coordinates":[9.3579368591,47.0970573425],"type":"Point"}
}