{
  "type": "Feature",
  "properties": {
    "iso:country":"CH",
    "sg:address":"Riedweg 3 8842 Unteriberg. Postfach 17",
    "sg:city":"Unteriberg",
    "sg:orig_category":"Fussboden, Fliesen U Plattenlegerei, Tapeziererei Verlegen von Fliesen U Platten",
    "sg:phone":"+41 55 414 16 62",
    "sg:postcode":"8842",
    "sg:province":"Schwyz",
    "wof:name":"Jud-fuchs H. R., Plattenbel\u00e4ge",
    "wof:placetype":"venue"
},
  "geometry": {"coordinates":[8.8048601151,47.0557823181],"type":"Point"}
}