{
  "type": "Feature",
  "properties": {
    "iso:country":"CH",
    "sg:address":"Viktoriastrasse 9 3900 Brig. Postfach 222",
    "sg:city":"Brig",
    "sg:orig_category":"Fachdetailhandel in Verkaufsr\u00e4umen Vermietung von Gebrauchsg\u00fctern",
    "sg:phone":"+41 27 924 56 87",
    "sg:postcode":"3900",
    "sg:province":"Valais",
    "wof:name":"Red Shop Ag",
    "wof:placetype":"venue"
},
  "geometry": {"coordinates":[7.9864010811,46.3187179565],"type":"Point"}
}