{
  "type": "Feature",
  "properties": {
    "iso:country":"CH",
    "sg:address":"Grabenstrasse 9",
    "sg:city":"Chur",
    "sg:orig_category":"Non-Classified Establishments",
    "sg:postcode":"7000",
    "sg:province":"Graubunden",
    "wof:name":"Cordasco Gerardo Cosmetics",
    "wof:placetype":"venue"
},
  "geometry": {"coordinates":[9.5328264236,46.8509635925],"type":"Point"}
}