{
  "type": "Feature",
  "properties": {
    "iso:country":"CH",
    "sg:address":"Place Du Manoir 18",
    "sg:city":"Cologny",
    "sg:orig_category":"Erbringung von Dienstleistungen f\u00fcr Unternehmen Innendekorationsateliers",
    "sg:phone":"+41 22 736 39 68",
    "sg:postcode":"1223",
    "sg:province":"Gen\u00e8ve",
    "wof:name":"Le Manoir, Marcelin Et Werner",
    "wof:placetype":"venue"
},
  "geometry": {"coordinates":[6.1826882362,46.2165184021],"type":"Point"}
}