{
  "type": "Feature",
  "properties": {
    "addr:full":"Chemin De La Viane 9 Mont-sur-lausanne Vaud 1052",
    "addr:housenumber":"9",
    "addr:postcode":"1052",
    "addr:street":"Chemin De La Viane",
    "iso:country":"CH",
    "sg:address":"Chemin De La Viane 9",
    "sg:city":"Mont-sur-lausanne",
    "sg:orig_category":"Allgemeiner Hoch U Tiefbau",
    "sg:postcode":"1052",
    "sg:province":"Vaud",
    "wof:name":"May Ren\u00e9 Sa",
    "wof:placetype":"venue"
},
  "geometry": {"coordinates":[6.627101,46.561295],"type":"Point"}
}