{
  "type": "Feature",
  "properties": {
    "iso:country":"CH",
    "sg:address":"Grand-places 1 1700 Fribourg Case Postale",
    "sg:city":"Freiburg",
    "sg:orig_category":"Unclassifiable Establishments",
    "sg:postcode":"1700",
    "sg:province":"Fribourg",
    "wof:name":"Si Placima Sa",
    "wof:placetype":"venue"
},
  "geometry": {"coordinates":[7.1545848846,46.8032188416],"type":"Point"}
}