{
  "type": "Feature",
  "properties": {
    "iso:country":"CH",
    "sg:address":"Brandschenkestrasse 161 8002 Z\u00fcrich. Postfach",
    "sg:city":"Z\u00fcrich",
    "sg:orig_category":"Technische, physikalische U chemische Untersuchung",
    "sg:phone":"+41 12011416",
    "sg:postcode":"8001",
    "sg:province":"Z\u00fcrich",
    "wof:name":"B\u00fcro F\u00fcr Sicherheits Und Umweltfragen Ivic-von Rechenberg Umweltberatung. Risikoanalysen Usw",
    "wof:placetype":"venue"
},
  "geometry": {"coordinates":[8.5264263153,47.3638038635],"type":"Point"}
}