{
  "type": "Feature",
  "properties": {
    "iso:country":"CH",
    "sg:address":"M\u00fchlethalstrasse 14a",
    "sg:city":"Zofingen",
    "sg:orig_category":"Detailhandel mit Gebrauchtwaren in Verkaufsr\u00e4umen",
    "sg:phone":"+41 62 752 10 75",
    "sg:postcode":"4800",
    "sg:province":"Aargau",
    "wof:name":"Hiob Brockenstube",
    "wof:placetype":"venue"
},
  "geometry": {"coordinates":[7.9461688995,47.293712616],"type":"Point"}
}