{
  "type": "Feature",
  "properties": {
    "addr:full":"Sonnenbergstrasse 19 Sarnen Obwalden 6060",
    "addr:housenumber":"19",
    "addr:postcode":"6060",
    "addr:street":"Sonnenbergstrasse",
    "iso:country":"CH",
    "sg:address":"Sonnenbergstrasse 19",
    "sg:city":"Sarnen",
    "sg:orig_category":"Allgemeiner Hoch U Tiefbau Allgemeiner Hochbau",
    "sg:phone":"+41 41 660 44 34",
    "sg:postcode":"6060",
    "sg:province":"Obwalden",
    "wof:name":"Burch Jos. & S\u00f6hne",
    "wof:placetype":"venue"
},
  "geometry": {"coordinates":[8.241158,46.896759],"type":"Point"}
}