{
  "type": "Feature",
  "properties": {
    "addr:full":"Bahnhofstr. 3 Bischofszell Thurgau 9220",
    "addr:housenumber":"3",
    "addr:postcode":"9220",
    "addr:street":"Bahnhofstr.",
    "iso:country":"CH",
    "sg:address":"Bahnhofstr. 3",
    "sg:city":"Bischofszell",
    "sg:classifiers":[
        {
            "category":"Banks & Credit Unions",
            "subcategory":"Bank",
            "type":"Services"
        }
    ],
    "sg:phone":"+41 4171812133",
    "sg:postcode":"9220",
    "sg:province":"Thurgau",
    "wof:name":"Thurgauer Kantonalbank",
    "wof:placetype":"venue"
},
  "geometry": {"coordinates":[9.241107,47.492947],"type":"Point"}
}