{
  "type": "Feature",
  "properties": {
    "iso:country":"CH",
    "sg:address":"Talacker 21",
    "sg:city":"Z\u00fcrich",
    "sg:orig_category":"Detailhandel mit M\u00f6beln U Haushaltsgegenst\u00e4nden Grosshandel mit M\u00f6beln, Wohnbedarf, Teppichen U Bode",
    "sg:phone":"+41 12212162",
    "sg:postcode":"8001",
    "sg:province":"Z\u00fcrich",
    "wof:name":"Ts Teppich Schaich Ag",
    "wof:placetype":"venue"
},
  "geometry": {"coordinates":[8.5368432999,47.370639801],"type":"Point"}
}