{
  "type": "Feature",
  "properties": {
    "iso:country":"CH",
    "sg:address":"Spisergasse 11",
    "sg:city":"St.gallen",
    "sg:orig_category":"Herstellung von Werkzeugen",
    "sg:phone":"+41 71 222 52 72",
    "sg:postcode":"9000",
    "sg:province":"St. Gallen",
    "wof:name":"Baumann Schneidwerkzeug Ag",
    "wof:placetype":"venue"
},
  "geometry": {"coordinates":[9.3774929047,47.4249382019],"type":"Point"}
}