{
  "type": "Feature",
  "properties": {
    "iso:country":"CH",
    "sg:address":"Rue De La Drague 1950 Sion Case Postale 174",
    "sg:city":"Sion",
    "sg:orig_category":"Einzelhandel mit Automobilen",
    "sg:phone":"+41 79 232 54 04",
    "sg:postcode":"1951",
    "sg:province":"Valais",
    "wof:name":"Jean-pierre Jungo Carrosserie",
    "wof:placetype":"venue"
},
  "geometry": {"coordinates":[7.3592448235,46.2222251892],"type":"Point"}
}