{
  "type": "Feature",
  "properties": {
    "iso:country":"CH",
    "sg:address":"Ch. Des Rayes 7",
    "sg:city":"Collonge-bellerive",
    "sg:orig_category":"Detailhandel mit Waren verschiedener Art, Hauptrichtung Nahrungsmittel",
    "sg:postcode":"1245",
    "sg:province":"Gen\u00e8ve",
    "wof:name":"Falquet Et Richardet",
    "wof:placetype":"venue"
},
  "geometry": {"coordinates":[6.2033700943,46.2349433899],"type":"Point"}
}