{
  "type": "Feature",
  "properties": {
    "iso:country":"CH",
    "sg:address":"Hintere Kirchstrasse 1",
    "sg:city":"Diepoldsau",
    "sg:orig_category":"Grosshandel mit Nahrungsmitteln, Getr\u00e4nken U Tabakwaren ohne ausgepr\u00e4gten Schwerpunkt",
    "sg:phone":"+41 79 404 59 26",
    "sg:postcode":"9444",
    "sg:province":"St. Gallen",
    "wof:name":"Alt Hermann",
    "wof:placetype":"venue"
},
  "geometry": {"coordinates":[9.6564950943,47.3857574463],"type":"Point"}
}