{
  "type": "Feature",
  "properties": {
    "iso:country":"CH",
    "sg:address":"Fluhmattstrasse 4",
    "sg:city":"Buchrain",
    "sg:orig_category":"Vereine Musik/Blasmusik",
    "sg:phone":"+41 41 440 09 28",
    "sg:postcode":"6033",
    "sg:province":"Luzern",
    "wof:name":"Feldmusik Ebikon",
    "wof:placetype":"venue"
},
  "geometry": {"coordinates":[8.3501033783,47.0928535461],"type":"Point"}
}