{
  "type": "Feature",
  "properties": {
    "iso:country":"CH",
    "sg:address":"Place Du Temple 10",
    "sg:city":"Allens",
    "sg:classifiers":[
        {
            "category":"Restaurant",
            "type":"Food & Drink"
        }
    ],
    "sg:phone":"+41 21 861 15 12",
    "sg:postcode":"1304",
    "sg:province":"Vaud",
    "wof:name":"Caf\u00e9 Au Vieux-bourg",
    "wof:placetype":"venue"
},
  "geometry": {"coordinates":[6.5077118874,46.613822937],"type":"Point"}
}