{
  "type": "Feature",
  "properties": {
    "iso:country":"CH",
    "sg:address":"Willisauerstrasse 24 6218 Ettiswil. Postfach",
    "sg:city":"Ettiswil",
    "sg:orig_category":"Instandhaltung U Reparatur von Automobilen",
    "sg:phone":"+41 41 980 13 53",
    "sg:postcode":"6218",
    "sg:province":"Luzern",
    "wof:name":"Josef W\u00fcest Autogarage",
    "wof:placetype":"venue"
},
  "geometry": {"coordinates":[8.0149564743,47.1452407837],"type":"Point"}
}