{
  "type": "Feature",
  "properties": {
    "iso:country":"CH",
    "sg:address":"Zugerstrasse 17",
    "sg:city":"Arth",
    "sg:orig_category":"Pensionskassen",
    "sg:phone":"+41 41 855 12 23",
    "sg:postcode":"6415",
    "sg:province":"Schwyz",
    "wof:name":"Personalf\u00fcrsorgestiftung Der Firma Kenel Anita, Rigi-garage, 6415 Arth",
    "wof:placetype":"venue"
},
  "geometry": {"coordinates":[8.5227689743,47.0648574829],"type":"Point"}
}