{
  "type": "Feature",
  "properties": {
    "iso:country":"CH",
    "sg:address":"Beislerstrasse 4",
    "sg:city":"Hombrechtikon",
    "sg:orig_category":"Detailhandel mit Fleisch U Fleischwaren Fleischverarbeitung",
    "sg:phone":"+41 91 825 22 56",
    "sg:postcode":"8634",
    "sg:province":"Z\u00fcrich",
    "wof:name":"Sciaroni Pio",
    "wof:placetype":"venue"
},
  "geometry": {"coordinates":[8.9955282211,46.187713623],"type":"Point"}
}