{
  "type": "Feature",
  "properties": {
    "iso:country":"CH",
    "sg:address":"Feldweg 33",
    "sg:city":"Termen",
    "sg:orig_category":"Grosshandel mit Maschinen U Ausr\u00fcstungen Herstellung von Anstrichmitteln, Druckfarben U Kitten",
    "sg:phone":"+41 27 923 05 55",
    "sg:postcode":"3912",
    "sg:province":"Valais",
    "wof:name":"Ec Color Tech Ag",
    "wof:placetype":"venue"
},
  "geometry": {"coordinates":[8.0220737457,46.3249588013],"type":"Point"}
}