{
  "type": "Feature",
  "properties": {
    "iso:country":"CH",
    "sg:address":"Ginsterstrasse 41",
    "sg:city":"Z\u00fcrich",
    "sg:orig_category":"P\u00e9dicure",
    "sg:phone":"+41 14921026",
    "sg:postcode":"8047",
    "sg:province":"Z\u00fcrich",
    "wof:name":"Heidi Alder P\u00e9dicure",
    "wof:placetype":"venue"
},
  "geometry": {"coordinates":[8.492348671,47.375667572],"type":"Point"}
}