{
  "type": "Feature",
  "properties": {
    "iso:country":"CH",
    "sg:address":"1555",
    "sg:city":"Villarzel",
    "sg:orig_category":"Landesverteidigung, Sozialversicherung \u00d6ffentliche Verwaltung",
    "sg:phone":"+41 26 675 25 55",
    "sg:postcode":"1555",
    "sg:province":"Vaud",
    "wof:name":"Centre De Protection Civile",
    "wof:placetype":"venue"
},
  "geometry": {"coordinates":[6.9903302193,46.8568611145],"type":"Point"}
}