{
  "type": "Feature",
  "properties": {
    "iso:country":"CH",
    "sg:address":"Route De Moudon 10 1040 Echallens. Postfach",
    "sg:city":"Echallens",
    "sg:classifiers":[
        {
            "category":"Travel",
            "subcategory":"Hotels & Motels",
            "type":"Entertainment"
        }
    ],
    "sg:postcode":"1040",
    "sg:province":"Vaud",
    "sg:tags":[
        "hotels",
        "mit",
        "restaurant"
    ],
    "wof:name":"Real Gastro Ag Hotel- U. Restaurationsbetriebe",
    "wof:placetype":"venue"
},
  "geometry": {"coordinates":[9.267829895,46.8157691956],"type":"Point"}
}