{
  "type": "Feature",
  "properties": {
    "iso:country":"CH",
    "sg:address":"G\u00fcnikon",
    "sg:city":"Hohenrain",
    "sg:orig_category":"Landw. Genossenschaften Dresch",
    "sg:phone":"+41 32 389 15 82",
    "sg:postcode":"6276",
    "sg:province":"Luzern",
    "wof:name":"Kurt Bangerter M\u00e4hdrescherei",
    "wof:placetype":"venue"
},
  "geometry": {"coordinates":[7.3951559067,47.0822868347],"type":"Point"}
}