{
  "type": "Feature",
  "properties": {
    "iso:country":"CH",
    "sg:address":"Grundstrasse 12",
    "sg:city":"Rotkreuz",
    "sg:orig_category":"Detailhandel mit Beleuchtungs U Haushaltsgegenst\u00e4nden Herstellung von elektrischen Lampen U Leuchten",
    "sg:phone":"+41 41 790 30 38",
    "sg:postcode":"6343",
    "sg:province":"Zug",
    "wof:name":"Decke & Licht Ag",
    "wof:placetype":"venue"
},
  "geometry": {"coordinates":[8.430276,47.145691],"type":"Point"}
}