{
  "type": "Feature",
  "properties": {
    "iso:country":"CH",
    "sg:address":"Rikonerstrasse 12",
    "sg:city":"Effretikon",
    "sg:orig_category":"Detailhandel mit Blumen U Pflanzen",
    "sg:phone":"+41 52 343 10 64",
    "sg:postcode":"8307",
    "sg:province":"Z\u00fcrich",
    "wof:name":"Annemarie Horisberger Blumengesch\u00e4ft",
    "wof:placetype":"venue"
},
  "geometry": {"coordinates":[8.686702,47.428761],"type":"Point"}
}