{
  "type": "Feature",
  "properties": {
    "iso:country":"CH",
    "sg:address":"Via Balestra 4",
    "sg:city":"Lugano",
    "sg:orig_category":"Detailhandel mit Waren verschiedener Art, Hauptrichtung Nahrungsmittel Geb\u00e4ude, Wohnungsreinigung",
    "sg:phone":"+41 22 788 89 77",
    "sg:postcode":"6900",
    "sg:province":"Ticino",
    "wof:name":"Armesto Sarl",
    "wof:placetype":"venue"
},
  "geometry": {"coordinates":[6.1247959137,46.2388343811],"type":"Point"}
}