{
  "type": "Feature",
  "properties": {
    "iso:country":"CH",
    "sg:address":"Oberdorfstrasse 25",
    "sg:city":"Zufikon",
    "sg:orig_category":"Vereine Fasnacht",
    "sg:postcode":"5621",
    "sg:province":"Aargau",
    "wof:name":"Guggemusig N\u00e4belhacker",
    "wof:placetype":"venue"
},
  "geometry": {"coordinates":[8.3571872711,47.3452987671],"type":"Point"}
}