{
  "type": "Feature",
  "properties": {
    "iso:country":"CH",
    "sg:address":"Luggwegstrasse 28",
    "sg:city":"Z\u00fcrich",
    "sg:orig_category":"Pensionskassen",
    "sg:phone":"+41 14322181",
    "sg:postcode":"8048",
    "sg:province":"Z\u00fcrich",
    "wof:name":"Personalf\u00fcrsorgestiftung Der Firma Beyeler Ag, Z\u00fcrich",
    "wof:placetype":"venue"
},
  "geometry": {"coordinates":[8.4907121658,47.3879852295],"type":"Point"}
}