{
  "type": "Feature",
  "properties": {
    "iso:country":"CH",
    "sg:address":"Via Carlo Frasca 12",
    "sg:city":"Lugano",
    "sg:orig_category":"Physiotherapie",
    "sg:phone":"+41 79 337 10 19",
    "sg:postcode":"6900",
    "sg:province":"Ticino",
    "wof:name":"Eco-bio-tronica Fisioterapia",
    "wof:placetype":"venue"
},
  "geometry": {"coordinates":[8.9541273117,46.0065612793],"type":"Point"}
}