{
  "type": "Feature",
  "properties": {
    "iso:country":"CH",
    "sg:address":"La Levratte 24",
    "sg:city":"Nyon",
    "sg:orig_category":"Zahntechnische Laboratorien",
    "sg:phone":"+41 56 241 22 60",
    "sg:postcode":"1260",
    "sg:province":"Vaud",
    "wof:name":"Egon Alraun Dental-labor",
    "wof:placetype":"venue"
},
  "geometry": {"coordinates":[8.3307752609,47.5235862732],"type":"Point"}
}