{
  "type": "Feature",
  "properties": {
    "iso:country":"CH",
    "sg:address":"Moosfeldstrasse 2",
    "sg:city":"Bottighofen",
    "sg:orig_category":"Organisationen des Gesundheitswesen",
    "sg:phone":"+41 71 488 38 17",
    "sg:postcode":"8598",
    "sg:province":"Thurgau",
    "wof:name":"Samariterverein Kreuzlingen",
    "wof:placetype":"venue"
},
  "geometry": {"coordinates":[9.209900856,47.6368675232],"type":"Point"}
}