{
  "type": "Feature",
  "properties": {
    "iso:country":"CH",
    "sg:address":"Boulevard De Grancy 1",
    "sg:city":"Lausanne",
    "sg:orig_category":"Detailhandel mit Getr\u00e4nken Herstellung von Verpackungsmittelnaus Holz",
    "sg:phone":"+41 21 617 51 01",
    "sg:postcode":"1006",
    "sg:province":"Vaud",
    "wof:name":"Staiger W.",
    "wof:placetype":"venue"
},
  "geometry": {"coordinates":[6.6322541237,46.5148658752],"type":"Point"}
}