{
  "type": "Feature",
  "properties": {
    "iso:country":"CH",
    "sg:address":"Vadianstrasse 40",
    "sg:city":"St.gallen",
    "sg:orig_category":"Unternehmensberatung",
    "sg:postcode":"9000",
    "sg:province":"St. Gallen",
    "wof:name":"Brunner Management Beratung",
    "wof:placetype":"venue"
},
  "geometry": {"coordinates":[9.3697471619,47.4214439392],"type":"Point"}
}