{
  "type": "Feature",
  "properties": {
    "iso:country":"CH",
    "sg:address":"Herrenburg 33",
    "sg:city":"Duggingen",
    "sg:orig_category":"Grosshandel mit medizinischen U orthop\u00e4dischen Artikeln Grosshandel mit pharmazeutischen Erzeugnisse",
    "sg:phone":"+41 61 831 52 50",
    "sg:postcode":"4202",
    "sg:province":"Basel-Landschaft",
    "wof:name":"Kine-rest Gmbh Verm\u00f6gensverwaltung, Beratung Im Steuerrecht Usw",
    "wof:placetype":"venue"
},
  "geometry": {"coordinates":[7.6095108986,47.4525489807],"type":"Point"}
}