{
  "type": "Feature",
  "properties": {
    "iso:country":"CH",
    "sg:address":"Hasenweg 7",
    "sg:city":"Balsthal",
    "sg:orig_category":"Kauf U Verkauf von Immobilien auf eigene Rechnung Vermietung U Verpachtung von eigenen Immobilien",
    "sg:phone":"+41 79 448 17 48",
    "sg:postcode":"4710",
    "sg:province":"Solothurn",
    "wof:name":"Ofm Verkaufs Und Verwaltungs Ag",
    "wof:placetype":"venue"
},
  "geometry": {"coordinates":[7.6933789253,47.3190307617],"type":"Point"}
}