{
  "type": "Feature",
  "properties": {
    "iso:country":"CH",
    "sg:address":"Rue De Clodevis 12",
    "sg:city":"Bramois",
    "sg:orig_category":"G\u00fcterbef\u00f6rderung im Strassenverkehr",
    "sg:phone":"+41 27 205 66 33",
    "sg:postcode":"1967",
    "sg:province":"Valais",
    "wof:name":"Berthod Alcide Transports Sa",
    "wof:placetype":"venue"
},
  "geometry": {"coordinates":[7.3971967697,46.2321434021],"type":"Point"}
}