{
  "type": "Feature",
  "properties": {
    "iso:country":"CH",
    "sg:address":"Winterthurerstrasse 43",
    "sg:city":"B\u00fclach",
    "sg:orig_category":"Verwaltung von Immobilien Wirtschaftspr\u00fcfung, Steuerberatung U Treuhand",
    "sg:phone":"+41 71 929 58 10",
    "sg:postcode":"8180",
    "sg:province":"Z\u00fcrich",
    "wof:name":"Bruno Frey, Treuhandb\u00fcro",
    "wof:placetype":"venue"
},
  "geometry": {"coordinates":[9.0442562103,47.458896637],"type":"Point"}
}