{
  "type": "Feature",
  "properties": {
    "iso:country":"CH",
    "sg:address":"Scheidweg 10",
    "sg:city":"Seuzach",
    "sg:orig_category":"Herstellung von konfektionierten Textilwaren ohne Bekleidung",
    "sg:phone":"+41 52 335 19 53",
    "sg:postcode":"8472",
    "sg:province":"Z\u00fcrich",
    "wof:name":"Studer & Koller Ag",
    "wof:placetype":"venue"
},
  "geometry": {"coordinates":[8.7292509079,47.5312423706],"type":"Point"}
}