{
  "type": "Feature",
  "properties": {
    "iso:country":"CH",
    "sg:address":"Holderstrasse 15 4000 Basel. Postfach",
    "sg:city":"Basel",
    "sg:orig_category":"Reinigungsgewerbe",
    "sg:postcode":"4051",
    "sg:province":"Basel-Stadt",
    "wof:name":"Angelillo & Sohn",
    "wof:placetype":"venue"
},
  "geometry": {"coordinates":[7.5902671814,47.5762748718],"type":"Point"}
}