{
  "type": "Feature",
  "properties": {
    "iso:country":"CH",
    "sg:address":"Burgstrasse 41",
    "sg:city":"Glarus",
    "sg:orig_category":"Detailhandel mit Textilien Herstellung von Sitzm\u00f6beln",
    "sg:phone":"+41 55 640 13 84",
    "sg:postcode":"8750",
    "sg:province":"Glarus",
    "wof:name":"Berlinger August",
    "wof:placetype":"venue"
},
  "geometry": {"coordinates":[9.0680007935,47.0417480469],"type":"Point"}
}