{
  "type": "Feature",
  "properties": {
    "iso:country":"CH",
    "sg:address":"Schulhausstrasse 69",
    "sg:city":"Zollikofen",
    "sg:classifiers":[
        {
            "category":"Education",
            "subcategory":"Library",
            "type":"Public Place"
        }
    ],
    "sg:phone":"+41 31 911 46 29",
    "sg:postcode":"3052",
    "sg:province":"Bern",
    "sg:tags":[
        "u",
        "bibliotheken",
        "archive"
    ],
    "wof:name":"Schulbibliothek T\u00fcrmli",
    "wof:placetype":"venue"
},
  "geometry": {"coordinates":[7.452636,46.998196],"type":"Point"}
}