{
  "type": "Feature",
  "properties": {
    "iso:country":"CH",
    "sg:address":"Rue Ami-lullin 9",
    "sg:city":"Gen\u00e8ve",
    "sg:orig_category":"Offsetdruck",
    "sg:phone":"+41 22 796 29 29",
    "sg:postcode":"1207",
    "sg:province":"Gen\u00e8ve",
    "wof:name":"Imprimerie St\u00e9phane Valente",
    "wof:placetype":"venue"
},
  "geometry": {"coordinates":[6.107793808,46.2214584351],"type":"Point"}
}