{
  "type": "Feature",
  "properties": {
    "iso:country":"CH",
    "sg:address":"Passwangstrasse 19 4226 Breitenbach. Postfach 159",
    "sg:city":"Breitenbach",
    "sg:orig_category":"Elektroinstallation Herstellung von Elektromotoren, Generatoren U Transformatoren",
    "sg:postcode":"4226",
    "sg:province":"Solothurn",
    "wof:name":"Elektro J\u00f6hl Ag.",
    "wof:placetype":"venue"
},
  "geometry": {"coordinates":[8.7852506638,47.3292274475],"type":"Point"}
}