{
  "type": "Feature",
  "properties": {
    "iso:country":"CH",
    "sg:address":"Bahnhofstrasse 14",
    "sg:city":"Mollis",
    "sg:orig_category":"Detailhandel mit Waren verschiedener Art, Hauptrichtung Nahrungsmittel Grosshandel mit Nahrungsmitte",
    "sg:phone":"+41 55 612 43 40",
    "sg:postcode":"8753",
    "sg:province":"Glarus",
    "wof:name":"Ital.spezialit\u00e4ten V.cordella",
    "wof:placetype":"venue"
},
  "geometry": {"coordinates":[9.0727272034,47.0954322815],"type":"Point"}
}