{
  "type": "Feature",
  "properties": {
    "iso:country":"CH",
    "sg:address":"Rheinstrasse 11",
    "sg:city":"Frauenfeld",
    "sg:orig_category":"Detailhandel mit Uhren U Schmuck Reparatur von Uhren U Schmuck",
    "sg:phone":"+41 52 721 34 53",
    "sg:postcode":"8500",
    "sg:province":"Thurgau",
    "wof:name":"Rolf Allemann Uhren Bijouterie",
    "wof:placetype":"venue"
},
  "geometry": {"coordinates":[8.8955364227,47.5561943054],"type":"Point"}
}