{
  "type": "Feature",
  "properties": {
    "iso:country":"CH",
    "sg:address":"Kornweg 7",
    "sg:city":"Unterentfelden",
    "sg:orig_category":"Mechanische Werkst\u00e4tten",
    "sg:phone":"+41 62 723 63 73",
    "sg:postcode":"5035",
    "sg:province":"Aargau",
    "wof:name":"Claude Bossard Mechanische Werkst\u00e4tte",
    "wof:placetype":"venue"
},
  "geometry": {"coordinates":[8.0417098999,47.3691482544],"type":"Point"}
}