{
  "type": "Feature",
  "properties": {
    "iso:country":"CH",
    "sg:address":"Route Cantonale 1",
    "sg:city":"Loveresse",
    "sg:classifiers":[
        {
            "category":"Travel",
            "subcategory":"Hotels & Motels",
            "type":"Entertainment"
        }
    ],
    "sg:phone":"+41 32 481 22 34",
    "sg:postcode":"2732",
    "sg:province":"Bern",
    "sg:tags":[
        "hotels",
        "mit",
        "restaurant"
    ],
    "wof:name":"H\u00f4tel Du Moulin",
    "wof:placetype":"venue"
},
  "geometry": {"coordinates":[7.2412691116,47.2359809875],"type":"Point"}
}