{
  "type": "Feature",
  "properties": {
    "iso:country":"CH",
    "sg:address":"Obermattstrasse 3",
    "sg:city":"T\u00e4uffelen",
    "sg:orig_category":"Unternehmensberatung",
    "sg:postcode":"2575",
    "sg:province":"Bern",
    "wof:name":"D\u00e4llenbach H.",
    "wof:placetype":"venue"
},
  "geometry": {"coordinates":[7.1971869469,47.0705909729],"type":"Point"}
}