{
  "type": "Feature",
  "properties": {
    "iso:country":"CH",
    "sg:address":"Dohlenzelgstrasse 3",
    "sg:city":"Windisch",
    "sg:orig_category":"Detailhandel mit B\u00fcchern, Zeitungen, Schreib U Papeteriewaren Detailhandel mit Schreib U Papeteriewa",
    "sg:phone":"+41 56 441 74 56",
    "sg:postcode":"5210",
    "sg:province":"Aargau",
    "wof:name":"Peter Karpf",
    "wof:placetype":"venue"
},
  "geometry": {"coordinates":[8.217453,47.478363],"type":"Point"}
}