{
  "type": "Feature",
  "properties": {
    "iso:country":"CH",
    "sg:address":"Oschwand 3476 Oschwand. Postfach",
    "sg:city":"Oschwand",
    "sg:orig_category":"Haltung von Rindern",
    "sg:postcode":"3476",
    "sg:province":"Bern",
    "wof:name":"Viehzuchtgenossenschaft Oschwand",
    "wof:placetype":"venue"
},
  "geometry": {"coordinates":[7.7127699852,47.1402359009],"type":"Point"}
}