{
  "type": "Feature",
  "properties": {
    "iso:country":"CH",
    "sg:address":"Chemin Du Guinchet 56a",
    "sg:city":"Collombey",
    "sg:orig_category":"Elektromechanische Werkst\u00e4tten Herstellung von elektronischen Bauelementen",
    "sg:postcode":"1868",
    "sg:province":"Valais",
    "wof:name":"G\u00e9rard Szabo Informatique Et Web",
    "wof:placetype":"venue"
},
  "geometry": {"coordinates":[6.9469099045,46.2746505737],"type":"Point"}
}