{
  "type": "Feature",
  "properties": {
    "iso:country":"CH",
    "sg:address":"Breitistrasse 25",
    "sg:city":"Kloten",
    "sg:orig_category":"Datenverarbeitungsdienste",
    "sg:phone":"+41 18130933",
    "sg:postcode":"8302",
    "sg:province":"Z\u00fcrich",
    "wof:name":"Azbuka Milosavljevic Dejan",
    "wof:placetype":"venue"
},
  "geometry": {"coordinates":[8.583186,47.44746],"type":"Point"}
}