{
  "type": "Feature",
  "properties": {
    "iso:country":"CH",
    "sg:address":"Lagerstrasse 18b",
    "sg:city":"Wanzwil",
    "sg:orig_category":"Herstellung von Elektrizit\u00e4tsverteilungs U schalteinrichtungen",
    "sg:phone":"+41 62 961 47 88",
    "sg:postcode":"3372",
    "sg:province":"Bern",
    "wof:name":"H. Uebersax Ag",
    "wof:placetype":"venue"
},
  "geometry": {"coordinates":[7.6934990883,47.1988716125],"type":"Point"}
}