{
  "type": "Feature",
  "properties": {
    "iso:country":"CH",
    "sg:address":"Avenue Thienne 18",
    "sg:city":"Orbe",
    "sg:orig_category":"Arztpraxen",
    "sg:phone":"+41 24 441 29 44",
    "sg:postcode":"1350",
    "sg:province":"Vaud",
    "wof:name":"Dr M\u00e9d. Fran\u00e7ois Villoz M\u00e9decin Sp\u00e9cialiste Fmh",
    "wof:placetype":"venue"
},
  "geometry": {"coordinates":[6.53239,46.72963],"type":"Point"}
}