{
  "type": "Feature",
  "properties": {
    "iso:country":"CH",
    "sg:address":"Bachstrasse 11 4614 H\u00e4gendorf. Postfach",
    "sg:city":"H\u00e4gendorf",
    "sg:orig_category":"Polizei",
    "sg:phone":"+41 61 706 97 10",
    "sg:postcode":"4614",
    "sg:province":"Solothurn",
    "wof:name":"Polizei Kanton Solothurn",
    "wof:placetype":"venue"
},
  "geometry": {"coordinates":[7.6092557907,47.48777771],"type":"Point"}
}