{
  "type": "Feature",
  "properties": {
    "iso:country":"CH",
    "sg:address":"Faubourg",
    "sg:city":"Sugiez",
    "sg:orig_category":"Grosshandel mit sonstigen Gebrauchs U Verbrauchsg\u00fctern",
    "sg:phone":"+41 26 673 29 10",
    "sg:postcode":"1786",
    "sg:province":"Fribourg",
    "wof:name":"Trotzdem Werbegeschenke, Krebs Suzanne",
    "wof:placetype":"venue"
},
  "geometry": {"coordinates":[7.1125178337,46.9651565552],"type":"Point"}
}