{
  "type": "Feature",
  "properties": {
    "iso:country":"CH",
    "sg:address":"Hofstrasse 71",
    "sg:city":"K\u00f6lliken",
    "sg:orig_category":"Sanit\u00e4r U Heizungsinstallation",
    "sg:phone":"+41 62 723 39 21",
    "sg:postcode":"5742",
    "sg:province":"Aargau",
    "wof:name":"Ulrich K\u00fchni Sos Heizungs-service",
    "wof:placetype":"venue"
},
  "geometry": {"coordinates":[8.0075845718,47.3247756958],"type":"Point"}
}