{
  "type": "Feature",
  "properties": {
    "iso:country":"CH",
    "sg:address":"Chemin Des Aulx 18",
    "sg:city":"Plan-les-ouates",
    "sg:orig_category":"Druck ohne Zeitungsdruck Offsetdruck",
    "sg:phone":"+41 61 751 50 20",
    "sg:postcode":"1228",
    "sg:province":"Gen\u00e8ve",
    "wof:name":"Gysin Ren\u00e9 Druckerei Gmbh",
    "wof:placetype":"venue"
},
  "geometry": {"coordinates":[7.5978732109,47.4671134949],"type":"Point"}
}