{
  "type": "Feature",
  "properties": {
    "iso:country":"CH",
    "sg:address":"Droit Mont 81",
    "sg:city":"Bourrignon",
    "sg:orig_category":"Herstellung von konfektionierten Textilwaren ohne Bekleidung",
    "sg:phone":"+41 32 431 11 53",
    "sg:postcode":"2803",
    "sg:province":"Jura",
    "wof:name":"Tschanz Ag Sonnen-& Wetterschutz",
    "wof:placetype":"venue"
},
  "geometry": {"coordinates":[7.2489509583,47.3924064636],"type":"Point"}
}