{
  "type": "Feature",
  "properties": {
    "iso:country":"CH",
    "sg:address":"Flurstrasse 3",
    "sg:city":"Baar",
    "sg:orig_category":"Maler U Glasergewerbe",
    "sg:postcode":"6340",
    "sg:province":"Zug",
    "wof:name":"Malergesch\u00e4ft Marcello Pellegrino",
    "wof:placetype":"venue"
},
  "geometry": {"coordinates":[8.535197258,47.2011909485],"type":"Point"}
}