{
  "type": "Feature",
  "properties": {
    "iso:country":"CH",
    "sg:address":"Neuch\u00e2tel Rue De 18 1201 Gen\u00e8ve. Postfach",
    "sg:city":"Gen\u00e8ve",
    "sg:orig_category":"RESTAURANTS: TEA-ROOMS",
    "sg:postcode":"1201",
    "sg:province":"Gen\u00e8ve",
    "wof:name":"Singh Arjan",
    "wof:placetype":"venue"
},
  "geometry": {"coordinates":[6.1460170746,46.2109451294],"type":"Point"}
}