{
  "type": "Feature",
  "properties": {
    "iso:country":"CH",
    "sg:address":"Bremgartenstrasse 105",
    "sg:city":"Aristau",
    "sg:orig_category":"Gemeindeverwaltungen",
    "sg:phone":"+41 56 664 18 30",
    "sg:postcode":"5628",
    "sg:province":"Aargau",
    "wof:name":"Gemeindeverwaltung Aristau",
    "wof:placetype":"venue"
},
  "geometry": {"coordinates":[8.3611307144,47.2975578308],"type":"Point"}
}