{
  "type": "Feature",
  "properties": {
    "iso:country":"CH",
    "sg:address":"Route De Ravi\u00e8res 60 D 2856 Bo\u00e9court. Postfach",
    "sg:city":"Bo\u00e9court",
    "sg:orig_category":"Herstellung von Werkzeugmaschinen",
    "sg:phone":"+41 56 484 10 80",
    "sg:postcode":"2856",
    "sg:province":"Jura",
    "wof:name":"B. Schmid Co Ag",
    "wof:placetype":"venue"
},
  "geometry": {"coordinates":[8.2938461304,47.4487304688],"type":"Point"}
}