{
  "type": "Feature",
  "properties": {
    "iso:country":"CH",
    "sg:address":"Sch\u00fctzenhaus",
    "sg:city":"Wileroltigen",
    "sg:orig_category":"Sportvereine Sch\u00fctzen",
    "sg:phone":"+41 31 755 66 26",
    "sg:postcode":"3207",
    "sg:province":"Bern",
    "wof:name":"Feldsch\u00fctzengesellschaft",
    "wof:placetype":"venue"
},
  "geometry": {"coordinates":[7.2387070656,46.9708595276],"type":"Point"}
}