{
  "type": "Feature",
  "properties": {
    "iso:country":"CH",
    "sg:address":"Neuh\u00fcsli",
    "sg:city":"Rain",
    "sg:orig_category":"Erbringung von Dienstleistungen f\u00fcr Unternehmen",
    "sg:postcode":"6026",
    "sg:province":"Luzern",
    "wof:name":"Bachmann Franz",
    "wof:placetype":"venue"
},
  "geometry": {"coordinates":[8.2671337128,47.1271247864],"type":"Point"}
}