{
  "type": "Feature",
  "properties": {
    "iso:country":"CH",
    "sg:address":"Pierre-\u00e0-mazel Rue De La 11",
    "sg:city":"Neuch\u00e2tel",
    "sg:orig_category":"Detailhandel mit elektrischen Haushalts-,Radio U Fernsehger\u00e4ten sowie Musikinstrumenten",
    "sg:postcode":"2000",
    "sg:province":"Neuch\u00e2tel",
    "wof:name":"Banyai A. Trade",
    "wof:placetype":"venue"
},
  "geometry": {"coordinates":[6.9416108131,46.9952049255],"type":"Point"}
}