{
  "type": "Feature",
  "properties": {
    "iso:country":"CH",
    "sg:address":"1588",
    "sg:city":"Cudrefin",
    "sg:orig_category":"Sportvereine Sch\u00fctzen",
    "sg:postcode":"1588",
    "sg:province":"Vaud",
    "wof:name":"St\u00e9 De Tir Armes-r\u00e9unies",
    "wof:placetype":"venue"
},
  "geometry": {"coordinates":[7.0185198784,46.9558601379],"type":"Point"}
}