{
  "type": "Feature",
  "properties": {
    "iso:country":"CH",
    "sg:address":"1932",
    "sg:city":"Bovernier",
    "sg:classifiers":[
        {
            "category":"Bars & Pubs",
            "type":"Food & Drink"
        }
    ],
    "sg:phone":"+41 91 648 13 56",
    "sg:postcode":"1932",
    "sg:province":"Valais",
    "wof:name":"Bar Ticino",
    "wof:placetype":"venue"
},
  "geometry": {"coordinates":[8.97087,45.905128],"type":"Point"}
}