{
  "type": "Feature",
  "properties": {
    "iso:country":"CH",
    "sg:address":"Litzistrasse 229",
    "sg:city":"Jonen",
    "sg:orig_category":"Grosshandel mit Holz U Baustoffen Sanit\u00e4rinstallation",
    "sg:phone":"+41 56 634 12 78",
    "sg:postcode":"8916",
    "sg:province":"Aargau",
    "wof:name":"Gsell-konrad A.",
    "wof:placetype":"venue"
},
  "geometry": {"coordinates":[8.397898674,47.3054275513],"type":"Point"}
}