{
  "type": "Feature",
  "properties": {
    "iso:country":"CH",
    "sg:address":"Hardstrasse 9",
    "sg:city":"Birsfelden",
    "sg:orig_category":"Elektroinstallation Herstellung von Elektromotoren, Generatoren U Transformatoren",
    "sg:phone":"+41 61 603 27 55",
    "sg:postcode":"4127",
    "sg:province":"Basel-Landschaft",
    "wof:name":"Z\u00fcrcher Electric Gmbh",
    "wof:placetype":"venue"
},
  "geometry": {"coordinates":[7.6238079071,47.5526809692],"type":"Point"}
}