{
  "type": "Feature",
  "properties": {
    "iso:country":"CH",
    "sg:address":"Utoquai 39 8008 Z\u00fcrich. Postfach",
    "sg:city":"Z\u00fcrich",
    "sg:classifiers":[
        {
            "category":"Professional",
            "subcategory":"Employment Agencies",
            "type":"Services"
        }
    ],
    "sg:postcode":"8008",
    "sg:province":"Z\u00fcrich",
    "sg:tags":[
        "personal",
        "u",
        "stellenvermittlung"
    ],
    "wof:name":"Yalcin Personalberatung Personalberatung U. -vermittlung",
    "wof:placetype":"venue"
},
  "geometry": {"coordinates":[8.5468835831,47.3635444641],"type":"Point"}
}