{
  "type": "Feature",
  "properties": {
    "iso:country":"CH",
    "sg:address":"Industriestrasse 3",
    "sg:city":"Aadorf",
    "sg:classifiers":[
        {
            "category":"Manufacturing",
            "subcategory":"Textiles",
            "type":"Manufacturing & Wholesale Goods"
        }
    ],
    "sg:phone":"+41 52 365 27 28",
    "sg:postcode":"8355",
    "sg:province":"Thurgau",
    "sg:tags":[
        "linen",
        "clothing",
        "fabric"
    ],
    "wof:name":"Wibutex Ag",
    "wof:placetype":"venue"
},
  "geometry": {"coordinates":[8.9025182724,47.4967422485],"type":"Point"}
}