{
  "type": "Feature",
  "properties": {
    "iso:country":"CH",
    "sg:address":"Scheuchzerstrasse 72",
    "sg:city":"Z\u00fcrich",
    "sg:orig_category":"Kauf U Verkauf von Immobilien auf eigene Rechnung",
    "sg:postcode":"8006",
    "sg:province":"Z\u00fcrich",
    "wof:name":"Tr-verwaltungs Ag",
    "wof:placetype":"venue"
},
  "geometry": {"coordinates":[8.5449838638,47.3869972229],"type":"Point"}
}