{
  "type": "Feature",
  "properties": {
    "iso:country":"CH",
    "sg:address":"Messerliweg 22 3027 Bern. Postfach",
    "sg:city":"Bern",
    "sg:orig_category":"Fachdetailhandel in Verkaufsr\u00e4umen",
    "sg:phone":"+41 31 992 31 65",
    "sg:postcode":"3027",
    "sg:province":"Bern",
    "wof:name":"Kuran Sport Engros Sportartikel, Zubeh\u00f6r; Handel, Vertrieb. Waren; Imp, Exp",
    "wof:placetype":"venue"
},
  "geometry": {"coordinates":[7.3966732025,46.9506034851],"type":"Point"}
}