{
  "type": "Feature",
  "properties": {
    "iso:country":"CH",
    "sg:address":"Bernstrasse 38",
    "sg:city":"Hindelbank",
    "sg:orig_category":"Werbevermittlung",
    "sg:phone":"+41 34 411 23 64",
    "sg:postcode":"3324",
    "sg:province":"Bern",
    "wof:name":"Anzeigerverband Kirchberg, Utzenstorf,koppigen,hindelbank",
    "wof:placetype":"venue"
},
  "geometry": {"coordinates":[7.5376811028,47.037273407],"type":"Point"}
}