{
  "type": "Feature",
  "properties": {
    "iso:country":"CH",
    "sg:address":"Chamerstrasse 117",
    "sg:city":"Zug",
    "sg:classifiers":[
        {
            "category":"Social Services",
            "subcategory":"Job Training",
            "type":"Services"
        }
    ],
    "sg:phone":"+41 71 245 33 33",
    "sg:postcode":"6300",
    "sg:province":"Zug",
    "sg:tags":[
        "machine",
        "industrial",
        "cleaning"
    ],
    "wof:name":"Allrep Gmbh",
    "wof:placetype":"venue"
},
  "geometry": {"coordinates":[9.389596,47.434841],"type":"Point"}
}