{
  "type": "Feature",
  "properties": {
    "iso:country":"CH",
    "sg:address":"Monbijoustr. 33 3000 Bern. Postfach 2712",
    "sg:city":"Bern",
    "sg:orig_category":"Pensionskassen",
    "sg:phone":"+41 31 879 10 16",
    "sg:postcode":"3005",
    "sg:province":"Bern",
    "wof:name":"Angestelltenstiftung Der Ziegelei Rapperswil",
    "wof:placetype":"venue"
},
  "geometry": {"coordinates":[7.4086999893,47.0657196045],"type":"Point"}
}