{
  "type": "Feature",
  "properties": {
    "iso:country":"CH",
    "sg:address":"Biglenstrasse 519",
    "sg:city":"Enggistein",
    "sg:classifiers":[
        {
            "category":"Restaurant",
            "type":"Food & Drink"
        }
    ],
    "sg:phone":"+41 31 839 23 10",
    "sg:postcode":"3077",
    "sg:province":"Bern",
    "wof:name":"Restaurant Z. Bad",
    "wof:placetype":"venue"
},
  "geometry": {"coordinates":[7.5973110199,46.9319915771],"type":"Point"}
}