{
  "type": "Feature",
  "properties": {
    "iso:country":"CH",
    "sg:address":"Schiltstrasse 16",
    "sg:city":"Oberurnen",
    "sg:orig_category":"Politische Parteien CVP",
    "sg:phone":"+41 55 610 22 38",
    "sg:postcode":"8868",
    "sg:province":"Glarus",
    "wof:name":"Cvp Ortspartei",
    "wof:placetype":"venue"
},
  "geometry": {"coordinates":[9.0613594055,47.1164512634],"type":"Point"}
}