{
  "type": "Feature",
  "properties": {
    "iso:country":"CH",
    "sg:address":"Rue De La Blancherie 40",
    "sg:city":"Chavannes-renens",
    "sg:orig_category":"Bauspenglerei Sanit\u00e4rinstallation",
    "sg:phone":"+41 79 413 35 78",
    "sg:postcode":"1022",
    "sg:province":"Vaud",
    "wof:name":"Jean-claude D'albero Installation Sanitaire",
    "wof:placetype":"venue"
},
  "geometry": {"coordinates":[6.57939,46.531921],"type":"Point"}
}