{
  "type": "Feature",
  "properties": {
    "addr:full":"Staffelbacherstrasse 106 Reitnau Aargau 5057",
    "addr:housenumber":"106",
    "addr:postcode":"5057",
    "addr:street":"Staffelbacherstrasse",
    "iso:country":"CH",
    "sg:address":"Staffelbacherstrasse 106",
    "sg:city":"Reitnau",
    "sg:orig_category":"Allgemeiner Hoch U Tiefbau Erschliessung von Grundst\u00fccken",
    "sg:phone":"+41 71 923 30 50",
    "sg:postcode":"5057",
    "sg:province":"Aargau",
    "wof:name":"I+r Schertler Haus Ag",
    "wof:placetype":"venue"
},
  "geometry": {"coordinates":[9.418274,47.44632],"type":"Point"}
}