{
  "type": "Feature",
  "properties": {
    "iso:country":"CH",
    "sg:address":"Kirchgasse 11",
    "sg:city":"Wettswil",
    "sg:orig_category":"Unclassifiable Establishments",
    "sg:postcode":"8907",
    "sg:province":"Z\u00fcrich",
    "wof:name":"Seiler Management",
    "wof:placetype":"venue"
},
  "geometry": {"coordinates":[8.4752941132,47.3377761841],"type":"Point"}
}