{
  "type": "Feature",
  "properties": {
    "iso:country":"CH",
    "sg:address":"Schulhausstrasse 1 6330 Cham. Postfach 181",
    "sg:city":"Cham",
    "sg:orig_category":"F\u00fcrsorge\u00e4mter",
    "sg:phone":"+41 81 756 54 72",
    "sg:postcode":"6330",
    "sg:province":"Zug",
    "wof:name":"Amtsvormundschaft D. Gemeinden Des Bezirks Werdenberg",
    "wof:placetype":"venue"
},
  "geometry": {"coordinates":[9.4501104355,47.1685714722],"type":"Point"}
}