{
  "type": "Feature",
  "properties": {
    "iso:country":"CH",
    "sg:address":"Jura Rue Du 11",
    "sg:city":"Crans-pr\u00e8s-c\u00e9ligny",
    "sg:orig_category":"Berufsbildende weiterf\u00fchrende Schulen",
    "sg:postcode":"1299",
    "sg:province":"Vaud",
    "wof:name":"Shec Swiss Hospitality Engineering Consultants Sa",
    "wof:placetype":"venue"
},
  "geometry": {"coordinates":[6.20611,46.359386],"type":"Point"}
}