{
  "type": "Feature",
  "properties": {
    "iso:country":"CH",
    "sg:address":"Talstrasse 11",
    "sg:city":"Z\u00fcrich",
    "sg:orig_category":"Detailhandel mit B\u00fcromaschinen U einrichtungen Detailhandel mit Radio U Fernsehger\u00e4ten",
    "sg:phone":"+41 33 335 57 00",
    "sg:postcode":"8001",
    "sg:province":"Z\u00fcrich",
    "wof:name":"Rvz H\u00e4nni B\u00fcromaschinen, Telekommunikation Usw.; Reparatur, Verkauf U. Service",
    "wof:placetype":"venue"
},
  "geometry": {"coordinates":[7.618745,46.73233],"type":"Point"}
}