{
  "type": "Feature",
  "properties": {
    "iso:country":"CH",
    "sg:address":"Geissmattstrasse 57 6004 Luzern. Postfach",
    "sg:city":"Luzern",
    "sg:orig_category":"Betrieb von Taxis",
    "sg:phone":"+41 79 444 68 88",
    "sg:postcode":"6002",
    "sg:province":"Luzern",
    "wof:name":"Walter Imfeld Taxi",
    "wof:placetype":"venue"
},
  "geometry": {"coordinates":[8.300598,47.058193],"type":"Point"}
}