{
  "type": "Feature",
  "properties": {
    "iso:country":"CH",
    "sg:address":"Bachlettenstrasse 20 4054 Basel. Postfach 3638",
    "sg:city":"Basel",
    "sg:orig_category":"Grosshandel mit Erzen U Metallen",
    "sg:phone":"+41 61 205 99 55",
    "sg:postcode":"4054",
    "sg:province":"Basel-Stadt",
    "wof:name":"W. Maritz, Metallurgische Produkte",
    "wof:placetype":"venue"
},
  "geometry": {"coordinates":[7.5800638199,47.550075531],"type":"Point"}
}