{
  "type": "Feature",
  "properties": {
    "iso:country":"CH",
    "sg:address":"Neuenschwandstrasse 883c 3536 Aeschau. Postfach",
    "sg:city":"Aeschau",
    "sg:orig_category":"Grosshandel mit Getreide, Saatgut U Futtermitteln",
    "sg:postcode":"3536",
    "sg:province":"Bern",
    "wof:name":"Sun City Optic Gmbh Management Von Verkaufsl\u00e4den F\u00fcr Sonnenbrillen Und Zubeh\u00f6r",
    "wof:placetype":"venue"
},
  "geometry": {"coordinates":[8.7982463837,47.3233222961],"type":"Point"}
}