{
  "type": "Feature",
  "properties": {
    "iso:country":"CH",
    "sg:address":"3429",
    "sg:city":"H\u00f6chstetten",
    "sg:orig_category":"Schulpflegen",
    "sg:postcode":"3429",
    "sg:province":"Bern",
    "wof:name":"Primarschulkommission Der Gemeinde H\u00f6chstetten",
    "wof:placetype":"venue"
},
  "geometry": {"coordinates":[7.6404800415,47.1434707642],"type":"Point"}
}