{
  "type": "Feature",
  "properties": {
    "iso:country":"CH",
    "sg:address":"Route De Ch\u00eane 19",
    "sg:city":"Gen\u00e8ve",
    "sg:orig_category":"Detailhandel mit Tabakwaren Grosshandel mit Tabakwaren",
    "sg:phone":"+41 22 736 14 81",
    "sg:postcode":"1207",
    "sg:province":"Gen\u00e8ve",
    "wof:name":"Mme M. Foudil",
    "wof:placetype":"venue"
},
  "geometry": {"coordinates":[6.1666097641,46.2001991272],"type":"Point"}
}