{
  "type": "Feature",
  "properties": {
    "iso:country":"CH",
    "sg:address":"Gare Avenue De La 8",
    "sg:city":"Monthey",
    "sg:orig_category":"Erschliessung von Grundst\u00fccken",
    "sg:postcode":"1870",
    "sg:province":"Valais",
    "wof:name":"Soci\u00e9t\u00e9 Coop\u00e9rative D'habitation De Monthey",
    "wof:placetype":"venue"
},
  "geometry": {"coordinates":[6.9471468925,46.2516288757],"type":"Point"}
}