{
  "type": "Feature",
  "properties": {
    "iso:country":"CH",
    "sg:address":"Rue De Rive 14",
    "sg:city":"Nyon",
    "sg:orig_category":"Softwareentwicklung U beratung",
    "sg:phone":"+41 22 361 05 60",
    "sg:postcode":"1260",
    "sg:province":"Vaud",
    "wof:name":"Microdyne Systems, Chilon Christine",
    "wof:placetype":"venue"
},
  "geometry": {"coordinates":[6.2449789047,46.3843307495],"type":"Point"}
}