{
  "type": "Feature",
  "properties": {
    "iso:country":"CH",
    "sg:address":"Stalden 39",
    "sg:city":"Solothurn",
    "sg:orig_category":"Detailhandel mit Geschenkartikeln U Souvenirs Grosshandel mit keramischen Erzeugnissen, Glaswaren U ",
    "sg:phone":"+41 32 623 56 80",
    "sg:postcode":"4500",
    "sg:province":"Solothurn",
    "wof:name":"Boutique 19, Ghidini Margrit",
    "wof:placetype":"venue"
},
  "geometry": {"coordinates":[7.5350217819,47.2071762085],"type":"Point"}
}