{
  "type": "Feature",
  "properties": {
    "iso:country":"CH",
    "sg:address":"Via Alberto Franzoni 29",
    "sg:city":"Locarno",
    "sg:orig_category":"Architektur U Ingenieurb\u00fcros",
    "sg:phone":"+41 91 751 48 88",
    "sg:postcode":"6600",
    "sg:province":"Ticino",
    "wof:name":"Scheu Giorgio Ingegneria Ags",
    "wof:placetype":"venue"
},
  "geometry": {"coordinates":[8.78443,46.16856],"type":"Point"}
}