{
  "type": "Feature",
  "properties": {
    "iso:country":"CH",
    "sg:address":"Bundesrat R. Mingerstrasse 5 3054 Sch\u00fcpfen. Postfach",
    "sg:city":"Sch\u00fcpfen",
    "sg:orig_category":"Mechanik",
    "sg:postcode":"3054",
    "sg:province":"Bern",
    "wof:name":"Schlosserei Henzen",
    "wof:placetype":"venue"
},
  "geometry": {"coordinates":[7.7845520973,46.4042396545],"type":"Point"}
}