{
  "type": "Feature",
  "properties": {
    "iso:country":"CH",
    "sg:address":"M\u00fcnsterplatz 1 8200 Schaffhausen. Postfach 91",
    "sg:city":"Schaffhausen",
    "sg:classifiers":[
        {
            "category":"Education",
            "subcategory":"Library",
            "type":"Public Place"
        }
    ],
    "sg:phone":"+41 61 831 24 60",
    "sg:postcode":"8202",
    "sg:province":"Schaffhausen",
    "sg:tags":[
        "u",
        "bibliotheken",
        "archive"
    ],
    "wof:name":"Stadtbibliothek",
    "wof:placetype":"venue"
},
  "geometry": {"coordinates":[7.792601,47.554604],"type":"Point"}
}