{
  "type": "Feature",
  "properties": {
    "iso:country":"CH",
    "sg:address":"Mellinger Str. 10",
    "sg:city":"Niederrohrdorf",
    "sg:classifiers":[
        {
            "category":"Professional",
            "subcategory":"Engineering",
            "type":"Services"
        }
    ],
    "sg:phone":"+41 56 485 95 95",
    "sg:postcode":"5443",
    "sg:province":"Aargau",
    "sg:tags":[
        "machine",
        "-",
        "mechanical"
    ],
    "wof:name":"Egro Ag",
    "wof:placetype":"venue"
},
  "geometry": {"coordinates":[8.3016490936,47.4247932434],"type":"Point"}
}