{
  "type": "Feature",
  "properties": {
    "iso:country":"CH",
    "sg:address":"Dorfackerstrasse 23 4528 Zuchwil. Postfach",
    "sg:city":"Zuchwil",
    "sg:orig_category":"Architektur U Ingenieurb\u00fcros",
    "sg:phone":"+41 61 701 14 46",
    "sg:postcode":"4528",
    "sg:province":"Solothurn",
    "wof:name":"Staub Msre-planung",
    "wof:placetype":"venue"
},
  "geometry": {"coordinates":[7.60426,47.485783],"type":"Point"}
}