{
  "type": "Feature",
  "properties": {
    "iso:country":"CH",
    "sg:address":"Route Fontanivent 70 1817 Brent. Postfach",
    "sg:city":"Brent",
    "sg:orig_category":"Elektro- and elektronische Maschinen Grosshandel",
    "sg:phone":"+41 21 964 80 88",
    "sg:postcode":"1817",
    "sg:province":"Vaud",
    "wof:name":"Phimax Diffusion Snc",
    "wof:placetype":"venue"
},
  "geometry": {"coordinates":[6.9011001587,46.4577255249],"type":"Point"}
}