{
  "type": "Feature",
  "properties": {
    "iso:country":"CH",
    "sg:address":"Via San Vico 5 6952 Canobbio. Postfach",
    "sg:city":"Canobbio",
    "sg:orig_category":"Schallplatten, Videokassetten, MC and CD Grosshandel",
    "sg:postcode":"6952",
    "sg:province":"Ticino",
    "wof:name":"Musicbox",
    "wof:placetype":"venue"
},
  "geometry": {"coordinates":[8.9669380188,46.0280990601],"type":"Point"}
}