{
  "type": "Feature",
  "properties": {
    "iso:country":"CH",
    "sg:address":"Dornacherplatz 21",
    "sg:city":"Solothurn",
    "sg:orig_category":"Solarien",
    "sg:phone":"+41 32 623 95 23",
    "sg:postcode":"4500",
    "sg:province":"Solothurn",
    "wof:name":"Sunpoint Sonnenstudio Ag",
    "wof:placetype":"venue"
},
  "geometry": {"coordinates":[7.5396990776,47.2041664124],"type":"Point"}
}