{
  "type": "Feature",
  "properties": {
    "iso:country":"CH",
    "sg:address":"Industriestrasse 2 6343 Rotkreuz. Postfach 363",
    "sg:city":"Rotkreuz",
    "sg:orig_category":"Herstellung von sonstigen Waren aus Papier, Karton U Pappe Verarbeitung von Tee U Kaffee",
    "sg:phone":"+41 41 798 27 00",
    "sg:postcode":"6343",
    "sg:province":"Zug",
    "wof:name":"Hima Ag",
    "wof:placetype":"venue"
},
  "geometry": {"coordinates":[8.4328117371,47.1507301331],"type":"Point"}
}