{
  "type": "Feature",
  "properties": {
    "iso:country":"CH",
    "sg:address":"Thunstrasse 84",
    "sg:city":"Bern",
    "sg:orig_category":"Innendekorationsateliers",
    "sg:phone":"+41 31 352 34 78",
    "sg:postcode":"3006",
    "sg:province":"Bern",
    "wof:name":"Heinz Gl\u00e4ser Tapezierergesch\u00e4ft",
    "wof:placetype":"venue"
},
  "geometry": {"coordinates":[7.4619750977,46.9408912659],"type":"Point"}
}