{
  "type": "Feature",
  "properties": {
    "iso:country":"CH",
    "sg:address":"Bahnhofstrasse 17",
    "sg:city":"L\u00e4ufelfingen",
    "sg:orig_category":"G\u00fcterbef\u00f6rderung im Strassenverkehr",
    "sg:phone":"+41 61 983 96 90",
    "sg:postcode":"4448",
    "sg:province":"Basel-Landschaft",
    "wof:name":"Cargotrans Mesmer",
    "wof:placetype":"venue"
},
  "geometry": {"coordinates":[7.8542537689,47.3934555054],"type":"Point"}
}