{
  "type": "Feature",
  "properties": {
    "iso:country":"CH",
    "sg:address":"Z\u00e4hrli 9",
    "sg:city":"Galmiz",
    "sg:orig_category":"Fresh Vegetables, Lettuces, And Potatoes",
    "sg:phone":"+41 26 672 34 00",
    "sg:postcode":"3285",
    "sg:province":"Fribourg",
    "wof:name":"Bio-gem\u00fcse-av Ag",
    "wof:placetype":"venue"
},
  "geometry": {"coordinates":[7.1591749191,46.9495201111],"type":"Point"}
}