{
  "type": "Feature",
  "properties": {
    "iso:country":"CH",
    "sg:address":"Vogelsangweg 12",
    "sg:city":"Herzogenbuchsee",
    "sg:orig_category":"Sonstige mit der Informatik verbundene T\u00e4tigkeiten",
    "sg:postcode":"3360",
    "sg:province":"Bern",
    "wof:name":"Q.bex Gmbh",
    "wof:placetype":"venue"
},
  "geometry": {"coordinates":[8.7796049118,47.2022857666],"type":"Point"}
}