{
  "type": "Feature",
  "properties": {
    "iso:country":"CH",
    "sg:address":"Hauptstrasse 28",
    "sg:city":"Wollerau",
    "sg:classifiers":[
        {
            "category":"Education",
            "subcategory":"Library",
            "type":"Public Place"
        }
    ],
    "sg:phone":"+41 17840227",
    "sg:postcode":"8832",
    "sg:province":"Schwyz",
    "sg:tags":[
        "u",
        "bibliotheken",
        "archive"
    ],
    "wof:name":"Katholische Pfarrbibliothek",
    "wof:placetype":"venue"
},
  "geometry": {"coordinates":[8.718933,47.195679],"type":"Point"}
}