{
  "type": "Feature",
  "properties": {
    "iso:country":"CH",
    "sg:address":"Dahlienstrasse 1",
    "sg:city":"Gerlafingen",
    "sg:orig_category":"Detailhandel mit Waren verschiedener Art, Hauptrichtung Nahrungsmittel",
    "sg:phone":"+41 32 675 08 28",
    "sg:postcode":"4563",
    "sg:province":"Solothurn",
    "wof:name":"Quo Vadis Gmbh, Kommunikation Und Vertrieb",
    "wof:placetype":"venue"
},
  "geometry": {"coordinates":[7.573846817,47.1678390503],"type":"Point"}
}