{
  "type": "Feature",
  "properties": {
    "addr:full":"Zeughausgasse 9a Zug Zug 6300",
    "addr:housenumber":"9a",
    "addr:postcode":"6300",
    "addr:street":"Zeughausgasse;Zug",
    "iso:country":"CH",
    "sg:address":"Zeughausgasse 9a",
    "sg:city":"Zug",
    "sg:orig_category":"Binnenschiffahrt",
    "sg:phone":"+41 41 710 93 61",
    "sg:postcode":"6300",
    "sg:province":"Zug",
    "wof:name":"Gotland Shipping Ag",
    "wof:placetype":"venue"
},
  "geometry": {"coordinates":[8.516261,47.166916],"type":"Point"}
}