{
  "type": "Feature",
  "properties": {
    "iso:country":"CH",
    "sg:address":"Rh\u00f4ne Rue Du 84",
    "sg:city":"Gen\u00e8ve",
    "sg:orig_category":"Non-Classified Establishments",
    "sg:postcode":"1204",
    "sg:province":"Gen\u00e8ve",
    "wof:name":"Green-home Gmbh",
    "wof:placetype":"venue"
},
  "geometry": {"coordinates":[8.4409542084,47.4158477783],"type":"Point"}
}