{
  "type": "Feature",
  "properties": {
    "iso:country":"CH",
    "sg:address":"Grand-rue 42",
    "sg:city":"Estavayer-le-lac",
    "sg:orig_category":"Grosshandel mit Textilien",
    "sg:postcode":"1470",
    "sg:province":"Fribourg",
    "wof:name":"Al Mansour Abderrahim, Tex-import",
    "wof:placetype":"venue"
},
  "geometry": {"coordinates":[6.8453879356,46.8497161865],"type":"Point"}
}