{
  "type": "Feature",
  "properties": {
    "iso:country":"CH",
    "sg:address":"8737",
    "sg:city":"Gommiswald",
    "sg:classifiers":[
        {
            "category":"Restaurant",
            "type":"Food & Drink"
        }
    ],
    "sg:phone":"+41 55 280 21 59",
    "sg:postcode":"8737",
    "sg:province":"St. Gallen",
    "wof:name":"Restaurant Adler",
    "wof:placetype":"venue"
},
  "geometry": {"coordinates":[9.0180501938,47.2323799133],"type":"Point"}
}