{
  "type": "Feature",
  "properties": {
    "iso:country":"CH",
    "sg:address":"Hauptstrasse 2",
    "sg:city":"Heldswil",
    "sg:orig_category":"Instandhaltung U Reparatur von Automobilen",
    "sg:phone":"+41 71 642 10 51",
    "sg:postcode":"9216",
    "sg:province":"Thurgau",
    "wof:name":"Dorfgarage Schmidhauser Roland",
    "wof:placetype":"venue"
},
  "geometry": {"coordinates":[9.2196073532,47.5289802551],"type":"Point"}
}