{
  "type": "Feature",
  "properties": {
    "iso:country":"CH",
    "sg:address":"Fridtalweg 12",
    "sg:city":"Turbenthal",
    "sg:orig_category":"Grosshandel mit Datenverarbeitungsger\u00e4ten Grosshandel mit Software",
    "sg:phone":"+41 79 415 51 37",
    "sg:postcode":"8488",
    "sg:province":"Z\u00fcrich",
    "wof:name":"Sos-computerdienst Ruch",
    "wof:placetype":"venue"
},
  "geometry": {"coordinates":[7.9046220779,46.7064666748],"type":"Point"}
}