{
  "type": "Feature",
  "properties": {
    "iso:country":"CH",
    "sg:address":"Allmendstrasse 1",
    "sg:city":"Kiesen",
    "sg:orig_category":"Verarbeitung von Milch Verwertung von Milch",
    "sg:phone":"+41 31 781 01 32",
    "sg:postcode":"3629",
    "sg:province":"Bern",
    "wof:name":"K\u00e4serei Kiesen",
    "wof:placetype":"venue"
},
  "geometry": {"coordinates":[7.582529068,46.8196563721],"type":"Point"}
}