{
  "type": "Feature",
  "properties": {
    "iso:country":"CH",
    "sg:address":"3374",
    "sg:city":"Wangenried",
    "sg:orig_category":"Sportvereine Hornussen",
    "sg:postcode":"3374",
    "sg:province":"Bern",
    "wof:name":"Hornussergesellschaft",
    "wof:placetype":"venue"
},
  "geometry": {"coordinates":[7.658010006,47.2181587219],"type":"Point"}
}