{
  "type": "Feature",
  "properties": {
    "iso:country":"CH",
    "sg:address":"Via Casate 1",
    "sg:city":"Novazzano",
    "sg:classifiers":[
        {
            "category":"Banks & Credit Unions",
            "subcategory":"Bank",
            "type":"Services"
        }
    ],
    "sg:phone":"+41 91 641 64 11",
    "sg:postcode":"6883",
    "sg:province":"Ticino",
    "wof:name":"Raiffeisen",
    "wof:placetype":"venue"
},
  "geometry": {"coordinates":[8.976343,45.841637],"type":"Point"}
}