{
  "type": "Feature",
  "properties": {
    "addr:full":"Reitschulstrasse 5 Biel/bienne Bern 2502",
    "addr:housenumber":"5",
    "addr:postcode":"2502",
    "addr:street":"Reitschulstrasse",
    "iso:country":"CH",
    "sg:address":"Reitschulstrasse 5",
    "sg:city":"Biel/bienne",
    "sg:orig_category":"Arztpraxen",
    "sg:phone":"+41 32 342 31 33",
    "sg:postcode":"2502",
    "sg:province":"Bern",
    "wof:name":"Dr.med.rolf Lehmann Spezialarzt Fmh",
    "wof:placetype":"venue"
},
  "geometry": {"coordinates":[7.248756,47.140713],"type":"Point"}
}