{
  "type": "Feature",
  "properties": {
    "iso:country":"CH",
    "sg:address":"Via Bena 15",
    "sg:city":"Mendrisio",
    "sg:orig_category":"Herstellung von Duft U K\u00f6rperpflegemitteln",
    "sg:postcode":"6850",
    "sg:province":"Ticino",
    "wof:name":"Belcometic Sa",
    "wof:placetype":"venue"
},
  "geometry": {"coordinates":[8.9930057526,45.8688354492],"type":"Point"}
}