{
  "type": "Feature",
  "properties": {
    "iso:country":"CH",
    "sg:address":"Bergmatten 7",
    "sg:city":"Duggingen",
    "sg:orig_category":"K\u00fcnstlerische U schriftstellerische T\u00e4tigkeiten U Darbietungen",
    "sg:phone":"+41 61 741 24 15",
    "sg:postcode":"4202",
    "sg:province":"Basel-Landschaft",
    "wof:name":"Gottwald, Stein Und Bronze",
    "wof:placetype":"venue"
},
  "geometry": {"coordinates":[7.6071090698,47.4446907043],"type":"Point"}
}