{
  "type": "Feature",
  "properties": {
    "iso:country":"CH",
    "sg:address":"Sonnhaldenweg 30",
    "sg:city":"Grossh\u00f6chstetten",
    "sg:orig_category":"Religi\u00f6se Vereinigungen divers Vereine Gemeinn\u00fctzige",
    "sg:phone":"+41 31 711 46 47",
    "sg:postcode":"3506",
    "sg:province":"Bern",
    "wof:name":"Christkath.m\u00e4nnerverein Bern",
    "wof:placetype":"venue"
},
  "geometry": {"coordinates":[7.6430301666,46.9071617126],"type":"Point"}
}