{
  "type": "Feature",
  "properties": {
    "iso:country":"CH",
    "sg:address":"Badenerstrasse 81 8952 Schlieren. Postfach",
    "sg:city":"Schlieren",
    "sg:orig_category":"Grosshandel mit Eisenwaren sowie Installationsbedarf f\u00fcr Gas, Wasser U Heizung Grosshandel mit sonst",
    "sg:phone":"+41 17309929",
    "sg:postcode":"8952",
    "sg:province":"Z\u00fcrich",
    "wof:name":"Robert Wagner Ind'filter & Spezialwerkzeuge",
    "wof:placetype":"venue"
},
  "geometry": {"coordinates":[8.4349946976,47.3967399597],"type":"Point"}
}