{
  "type": "Feature",
  "properties": {
    "iso:country":"CH",
    "sg:address":"Schulhausstrasse 73",
    "sg:city":"Herrliberg",
    "sg:orig_category":"Softwareentwicklung U beratung",
    "sg:postcode":"8704",
    "sg:province":"Z\u00fcrich",
    "wof:name":"Scintec Ag",
    "wof:placetype":"venue"
},
  "geometry": {"coordinates":[8.6093673706,47.2896003723],"type":"Point"}
}