{
  "type": "Feature",
  "properties": {
    "iso:country":"CH",
    "sg:address":"Kirchstrasse 20 8750 Glarus. Postfach",
    "sg:city":"Glarus",
    "sg:orig_category":"Detailhandel mit Metallwaren, Anstrichmitteln, Glaswaren, Bau U Heimwerkerbedarf",
    "sg:postcode":"8750",
    "sg:province":"Glarus",
    "wof:name":"Bastelino - F\u00f6llmi R. & Hofstetter A.",
    "wof:placetype":"venue"
},
  "geometry": {"coordinates":[9.066781044,47.0408554077],"type":"Point"}
}