{
  "type": "Feature",
  "properties": {
    "iso:country":"CH",
    "sg:address":"Via Baragge 11",
    "sg:city":"Giubiasco",
    "sg:orig_category":"G\u00fcterbef\u00f6rderung im Strassenverkehr Herstellung von Tanks U Sammelbeh\u00e4ltern aus Metall",
    "sg:phone":"+41 91 857 27 82",
    "sg:postcode":"6512",
    "sg:province":"Ticino",
    "wof:name":"Congefi Sa",
    "wof:placetype":"venue"
},
  "geometry": {"coordinates":[8.9935274124,46.1713447571],"type":"Point"}
}