{
  "type": "Feature",
  "properties": {
    "iso:country":"CH",
    "sg:address":"Hauptstrasse 62 9323 Steinach. Postfach 30",
    "sg:city":"Steinach",
    "sg:orig_category":"Mechanische Werkst\u00e4tten",
    "sg:phone":"+41 79 340 96 41",
    "sg:postcode":"9323",
    "sg:province":"St. Gallen",
    "wof:name":"Peter Reber Mechanische Werkstatt",
    "wof:placetype":"venue"
},
  "geometry": {"coordinates":[7.3159909248,47.0982971191],"type":"Point"}
}