{
  "type": "Feature",
  "properties": {
    "iso:country":"CH",
    "sg:address":"Chemin Des Hauts 4",
    "sg:city":"Crans-pr\u00e8s-c\u00e9ligny",
    "sg:orig_category":"Unternehmensberatung",
    "sg:phone":"+41 22 362 42 72",
    "sg:postcode":"1299",
    "sg:province":"Vaud",
    "wof:name":"Kleinn Consulting",
    "wof:placetype":"venue"
},
  "geometry": {"coordinates":[6.21043396,46.3680381775],"type":"Point"}
}