{
  "type": "Feature",
  "properties": {
    "iso:country":"CH",
    "sg:address":"Zimmergasse 16",
    "sg:city":"Z\u00fcrich",
    "sg:orig_category":"Museen",
    "sg:postcode":"8008",
    "sg:province":"Z\u00fcrich",
    "wof:name":"Waddington & Bernstein Gallery Ltd",
    "wof:placetype":"venue"
},
  "geometry": {"coordinates":[8.5511760712,47.362285614],"type":"Point"}
}