{
  "type": "Feature",
  "properties": {
    "iso:country":"CH",
    "sg:address":"Unterdorfstrasse 13",
    "sg:city":"Villmergen",
    "sg:orig_category":"RESTAURANTS: TEA-ROOMS",
    "sg:phone":"+41 79 221 22 08",
    "sg:postcode":"5612",
    "sg:province":"Aargau",
    "wof:name":"Restaurant J\u00e4gerst\u00fcbli Horat Markus.",
    "wof:placetype":"venue"
},
  "geometry": {"coordinates":[8.2432632446,47.3489341736],"type":"Point"}
}