{
  "type": "Feature",
  "properties": {
    "iso:country":"CH",
    "sg:address":"Piazza Boffalora 3 6830 Chiasso. Postfach",
    "sg:city":"Chiasso",
    "sg:orig_category":"Detailhandel mit Blumen U Pflanzen Fachdetailhandel in Verkaufsr\u00e4umen",
    "sg:phone":"+41 91 683 82 74",
    "sg:postcode":"6830",
    "sg:province":"Ticino",
    "wof:name":"Selvini Fiori Sagl Negozio Di Fiori, Piante Ecc",
    "wof:placetype":"venue"
},
  "geometry": {"coordinates":[9.021786,45.837723],"type":"Point"}
}