{
  "type": "Feature",
  "properties": {
    "addr:full":"Avenue De La Fusion 16 Martigny Valais 1920",
    "addr:housenumber":"16",
    "addr:postcode":"1920",
    "addr:street":"Avenue De La Fusion",
    "iso:country":"CH",
    "sg:address":"Avenue De La Fusion 16",
    "sg:city":"Martigny",
    "sg:orig_category":"Architekturb\u00fcros",
    "sg:phone":"+41 27 722 26 77",
    "sg:postcode":"1920",
    "sg:province":"Valais",
    "wof:name":"Marius Zryd Bureau D'architecture",
    "wof:placetype":"venue"
},
  "geometry": {"coordinates":[7.069511,46.102757],"type":"Point"}
}