{
  "type": "Feature",
  "properties": {
    "iso:country":"CH",
    "sg:address":"Rue Du Rh\u00f4ne 69 1207 Gen\u00e8ve. Postfach",
    "sg:city":"Gen\u00e8ve",
    "sg:orig_category":"Effektenvermittlung Broker Finanzierungsinstitutionen",
    "sg:phone":"+41 22 707 01 30",
    "sg:postcode":"1204",
    "sg:province":"Gen\u00e8ve",
    "wof:name":"Emf European Merchant Finance Sa Courtage En D\u00e9p\u00f4ts Bancaires Etc",
    "wof:placetype":"venue"
},
  "geometry": {"coordinates":[6.1559062004,46.2025299072],"type":"Point"}
}