{
  "type": "Feature",
  "properties": {
    "iso:country":"CH",
    "sg:address":"Pilatusstrasse 11",
    "sg:city":"Biel/bienne",
    "sg:orig_category":"Kauf U Verkauf von Immobilien auf eigene Rechnung",
    "sg:postcode":"2502",
    "sg:province":"Bern",
    "wof:name":"Bollier Sa",
    "wof:placetype":"venue"
},
  "geometry": {"coordinates":[7.2555880547,47.1483535767],"type":"Point"}
}