{
  "type": "Feature",
  "properties": {
    "iso:country":"CH",
    "sg:address":"Hauptstrasse 17",
    "sg:city":"R\u00fcttenen",
    "sg:orig_category":"G\u00fcterbef\u00f6rderung im Strassenverkehr",
    "sg:phone":"+41 32 622 60 58",
    "sg:postcode":"4522",
    "sg:province":"Solothurn",
    "wof:name":"Von Arx Leo",
    "wof:placetype":"venue"
},
  "geometry": {"coordinates":[7.5277729034,47.2289848328],"type":"Point"}
}