{
  "type": "Feature",
  "properties": {
    "iso:country":"CH",
    "sg:address":"Schaffhauserstrasse 210",
    "sg:city":"Z\u00fcrich",
    "sg:orig_category":"RESTAURANTS: TEA-ROOMS",
    "sg:phone":"+41 13113322",
    "sg:postcode":"8057",
    "sg:province":"Z\u00fcrich",
    "wof:name":"Restaurant Kwang Chow, S. Kwan",
    "wof:placetype":"venue"
},
  "geometry": {"coordinates":[8.5449571609,47.4011268616],"type":"Point"}
}