{
  "type": "Feature",
  "properties": {
    "iso:country":"CH",
    "sg:address":"Aathal",
    "sg:city":"Aathal-seegr\u00e4ben",
    "sg:orig_category":"Interessenvertretungen",
    "sg:phone":"+41 56 664 04 04",
    "sg:postcode":"8607",
    "sg:province":"Z\u00fcrich",
    "wof:name":"Kulturstiftung St. Martin",
    "wof:placetype":"venue"
},
  "geometry": {"coordinates":[8.3174819946,47.2825775146],"type":"Point"}
}