{
  "type": "Feature",
  "properties": {
    "iso:country":"CH",
    "sg:address":"1709 Fribourg Case Postale 62",
    "sg:city":"Fribourg",
    "sg:orig_category":"Sportvereine Ballsport Basketball",
    "sg:postcode":"1709",
    "sg:province":"Fribourg",
    "wof:name":"Bbc Perolles",
    "wof:placetype":"venue"
},
  "geometry": {"coordinates":[7.1512799263,46.8025016785],"type":"Point"}
}