{
  "type": "Feature",
  "properties": {
    "iso:country":"CH",
    "sg:address":"Gartaweg 18",
    "sg:city":"Trimmis",
    "sg:orig_category":"Fachdetailhandel in Verkaufsr\u00e4umen",
    "sg:phone":"+41 79 236 77 24",
    "sg:postcode":"7203",
    "sg:province":"Graubunden",
    "wof:name":"Reich & Partner Gmbh",
    "wof:placetype":"venue"
},
  "geometry": {"coordinates":[9.5591249466,46.9004364014],"type":"Point"}
}