{
  "type": "Feature",
  "properties": {
    "iso:country":"CH",
    "sg:address":"Saum 17",
    "sg:city":"Herisau",
    "sg:orig_category":"Zahnarztpraxen",
    "sg:postcode":"9100",
    "sg:province":"Appenzell Ausserrhoden",
    "wof:name":"Rostetter J. Gmbh",
    "wof:placetype":"venue"
},
  "geometry": {"coordinates":[9.2990598679,47.392326355],"type":"Point"}
}