{
  "type": "Feature",
  "properties": {
    "iso:country":"CH",
    "sg:address":"Bitzigasse 6",
    "sg:city":"Metzerlen",
    "sg:orig_category":"Autospenglereien",
    "sg:phone":"+41 61 731 11 42",
    "sg:postcode":"4116",
    "sg:province":"Solothurn",
    "wof:name":"Armin Siegrist Carrosserie",
    "wof:placetype":"venue"
},
  "geometry": {"coordinates":[7.467622,47.466972],"type":"Point"}
}