{
  "type": "Feature",
  "properties": {
    "iso:country":"CH",
    "sg:address":"Rue Du Panorama 12",
    "sg:city":"Vevey",
    "sg:orig_category":"Kosmetikinstitute",
    "sg:phone":"+41 21 923 57 55",
    "sg:postcode":"1800",
    "sg:province":"Vaud",
    "wof:name":"Fran\u00e7oise Nourrigat Institut De Beaut\u00e9",
    "wof:placetype":"venue"
},
  "geometry": {"coordinates":[6.8471131325,46.4599838257],"type":"Point"}
}