{
  "type": "Feature",
  "properties": {
    "iso:country":"CH",
    "sg:address":"Vordergasse 3 8200 Schaffhausen. Postfach",
    "sg:city":"Schaffhausen",
    "sg:orig_category":"Unclassifiable Establishments",
    "sg:postcode":"8200",
    "sg:province":"Schaffhausen",
    "wof:name":"Royalty Pharma Ag",
    "wof:placetype":"venue"
},
  "geometry": {"coordinates":[8.6378498077,47.6957054138],"type":"Point"}
}