{
  "type": "Feature",
  "properties": {
    "iso:country":"CH",
    "sg:address":"Chemin De Cuard 5",
    "sg:city":"Bevaix",
    "sg:orig_category":"Bauspenglerei Zimmerei, Dachdeckerei, Bauspenglerei U Abdichtung",
    "sg:postcode":"2022",
    "sg:province":"Neuch\u00e2tel",
    "wof:name":"Robert Jean-daniel",
    "wof:placetype":"venue"
},
  "geometry": {"coordinates":[6.812493,46.932156],"type":"Point"}
}