{
  "type": "Feature",
  "properties": {
    "iso:country":"CH",
    "sg:address":"Rossmoos",
    "sg:city":"Menznau",
    "sg:orig_category":"Haltung von Schweinen",
    "sg:phone":"+41 62 797 24 39",
    "sg:postcode":"6122",
    "sg:province":"Luzern",
    "wof:name":"Josef Barmettler Schweinezucht",
    "wof:placetype":"venue"
},
  "geometry": {"coordinates":[7.9831771851,47.3320388794],"type":"Point"}
}