{
  "type": "Feature",
  "properties": {
    "iso:country":"CH",
    "sg:address":"Rotzloch",
    "sg:city":"Stansstad",
    "sg:classifiers":[
        {
            "category":"Restaurant",
            "type":"Food & Drink"
        }
    ],
    "sg:phone":"+41 41 610 22 62",
    "sg:postcode":"6362",
    "sg:province":"Nidwalden",
    "wof:name":"Restaurant Rozloch",
    "wof:placetype":"venue"
},
  "geometry": {"coordinates":[8.3345479965,46.9673080444],"type":"Point"}
}