{
  "type": "Feature",
  "properties": {
    "iso:country":"CH",
    "sg:address":"Champ-jaccoud Chemin De 4a",
    "sg:city":"Blonay",
    "sg:orig_category":"RESTAURANTS: TEA-ROOMS",
    "sg:postcode":"1807",
    "sg:province":"Vaud",
    "wof:name":"Caf\u00e9 Du Raisin Bacchetta G.",
    "wof:placetype":"venue"
},
  "geometry": {"coordinates":[6.8580179214,46.4520492554],"type":"Point"}
}