{
  "type": "Feature",
  "properties": {
    "iso:country":"CH",
    "sg:address":"Eschesbys",
    "sg:city":"Nor\u00e9az",
    "sg:orig_category":"Landwirtschaft, Jagd U damit verbundene Dienstleistungen",
    "sg:phone":"+41 26 470 17 79",
    "sg:postcode":"1757",
    "sg:province":"Fribourg",
    "wof:name":"Marius Corpataux Exploitation Agricole",
    "wof:placetype":"venue"
},
  "geometry": {"coordinates":[7.0165228844,46.8078842163],"type":"Point"}
}