{
  "type": "Feature",
  "properties": {
    "iso:country":"CH",
    "sg:address":"Avenue Max Huber 7 3960 Sierre. Postfach",
    "sg:city":"Sierre",
    "sg:orig_category":"Detailhandel mit Textilien Herstellung von Oberbekleidung",
    "sg:phone":"+41 27 455 10 58",
    "sg:postcode":"3960",
    "sg:province":"Valais",
    "wof:name":"Hertz Jos\u00e9",
    "wof:placetype":"venue"
},
  "geometry": {"coordinates":[7.5345549583,46.2937583923],"type":"Point"}
}