{
  "type": "Feature",
  "properties": {
    "iso:country":"CH",
    "sg:address":"Kirchweg 2",
    "sg:city":"Sirnach",
    "sg:orig_category":"Wohnheime",
    "sg:postcode":"8370",
    "sg:province":"Thurgau",
    "wof:name":"Wohnen Im Alter Sirnach Was",
    "wof:placetype":"venue"
},
  "geometry": {"coordinates":[8.9978532791,47.4605560303],"type":"Point"}
}