{
  "type": "Feature",
  "properties": {
    "iso:country":"CH",
    "sg:address":"Eschenmattstrasse 11b",
    "sg:city":"M\u00f6hlin",
    "sg:orig_category":"D\u00e4mmung gegen K\u00e4lte, W\u00e4rme, Schall U Ersch\u00fctterung",
    "sg:phone":"+41 61 851 55 80",
    "sg:postcode":"4313",
    "sg:province":"Aargau",
    "wof:name":"M\u00fcller Isoliertechnik Ag Isoliertechnik & Deckenbau",
    "wof:placetype":"venue"
},
  "geometry": {"coordinates":[7.8395690918,47.5618743896],"type":"Point"}
}