{
  "type": "Feature",
  "properties": {
    "iso:country":"CH",
    "sg:address":"Chermignon-dessus",
    "sg:city":"Chermignon",
    "sg:orig_category":"Detailhandel mit Waren verschiedener Art, Hauptrichtung Nahrungsmittel",
    "sg:phone":"+41 21 960 47 05",
    "sg:postcode":"3971",
    "sg:province":"Valais",
    "wof:name":"Vis-\u00e0-vis Alimentation Rog\u00e9rio Da Silva",
    "wof:placetype":"venue"
},
  "geometry": {"coordinates":[6.9248428345,46.3969535828],"type":"Point"}
}