{
  "type": "Feature",
  "properties": {
    "iso:country":"CH",
    "sg:address":"Via Gerbione",
    "sg:city":"Tenero",
    "sg:orig_category":"Campingpl\u00e4tze",
    "sg:phone":"+41 91 745 11 42",
    "sg:postcode":"6598",
    "sg:province":"Ticino",
    "wof:name":"Tognetti Filippo & Denise",
    "wof:placetype":"venue"
},
  "geometry": {"coordinates":[8.850845,46.178307],"type":"Point"}
}