{
  "type": "Feature",
  "properties": {
    "iso:country":"CH",
    "sg:address":"Gr\u00fcttstrasse 108",
    "sg:city":"Biberist",
    "sg:orig_category":"Herstellung von Schrauben, Nieten, Ketten U Federn",
    "sg:phone":"+41 32 675 48 38",
    "sg:postcode":"4562",
    "sg:province":"Solothurn",
    "wof:name":"Schraubenfabrik Decovis Ag",
    "wof:placetype":"venue"
},
  "geometry": {"coordinates":[7.5732707977,47.177646637],"type":"Point"}
}