{
  "type": "Feature",
  "properties": {
    "iso:country":"CH",
    "sg:address":"Gurzelngasse 7",
    "sg:city":"Solothurn",
    "sg:orig_category":"Detailhandel mit Brillen U anderen Sehhilfen Fachdetailhandel in Verkaufsr\u00e4umen",
    "sg:phone":"+41 61 621 28 60",
    "sg:postcode":"4500",
    "sg:province":"Solothurn",
    "wof:name":"Fielmann Ag Brillenfachgesch\u00e4ft",
    "wof:placetype":"venue"
},
  "geometry": {"coordinates":[7.536623,47.207775],"type":"Point"}
}