{
  "type": "Feature",
  "properties": {
    "iso:country":"CH",
    "sg:address":"Monthoux Rue De 46 1201 Gen\u00e8ve. Postfach",
    "sg:city":"Gen\u00e8ve",
    "sg:orig_category":"W\u00e4scherei U chemische Reinigung",
    "sg:postcode":"1201",
    "sg:province":"Gen\u00e8ve",
    "wof:name":"Bertsch Ag Sanit\u00e4re Waschanstalt, Chem. Reinigung Und F\u00e4rberei Davos",
    "wof:placetype":"venue"
},
  "geometry": {"coordinates":[9.8209161758,46.7938766479],"type":"Point"}
}