{
  "type": "Feature",
  "properties": {
    "iso:country":"CH",
    "sg:address":"Wolfb\u00fchlstrasse 29 8408 Winterthur. Postfach",
    "sg:city":"Winterthur",
    "sg:orig_category":"Herstellung von Schmuck, Gold U Silberschmiedwaren",
    "sg:phone":"+41 52 222 55 44",
    "sg:postcode":"8408",
    "sg:province":"Z\u00fcrich",
    "wof:name":"Capricho Gmbh",
    "wof:placetype":"venue"
},
  "geometry": {"coordinates":[8.6893453598,47.5049362183],"type":"Point"}
}