{
  "type": "Feature",
  "properties": {
    "iso:country":"CH",
    "sg:address":"Buholzstrasse",
    "sg:city":"Ruswil",
    "sg:orig_category":"Grosshandel mit lebenden Tieren",
    "sg:phone":"+41 79 423 49 56",
    "sg:postcode":"6017",
    "sg:province":"Luzern",
    "wof:name":"Otto Aeberhardt Viehhandel",
    "wof:placetype":"venue"
},
  "geometry": {"coordinates":[7.5960612297,47.0791473389],"type":"Point"}
}