{
  "type": "Feature",
  "properties": {
    "iso:country":"CH",
    "sg:address":"Vazerolgasse 2",
    "sg:city":"Chur",
    "sg:orig_category":"Herstellung von sonstigen Maschinen f\u00fcr unspezifische Verwendung",
    "sg:postcode":"7000",
    "sg:province":"Graubunden",
    "wof:name":"Intertechnochem Ag",
    "wof:placetype":"venue"
},
  "geometry": {"coordinates":[8.4674377441,47.3632888794],"type":"Point"}
}