{
  "type": "Feature",
  "properties": {
    "iso:country":"CH",
    "sg:address":"R\u00e4mistrasse 39",
    "sg:city":"Z\u00fcrich",
    "sg:orig_category":"Zahnarztpraxen",
    "sg:phone":"+41 12522934",
    "sg:postcode":"8001",
    "sg:province":"Z\u00fcrich",
    "wof:name":"Dr.med.dent.willy Baumgartner Zahnarzt",
    "wof:placetype":"venue"
},
  "geometry": {"coordinates":[8.5477056503,47.3691101074],"type":"Point"}
}