{
  "type": "Feature",
  "properties": {
    "iso:country":"CH",
    "sg:address":"Gontenstrasse 17",
    "sg:city":"Appenzell",
    "sg:orig_category":"Sanit\u00e4r, Heizungs U L\u00fcftungsinstallation Sanit\u00e4rinstallation",
    "sg:phone":"+41 71 787 33 37",
    "sg:postcode":"9050",
    "sg:province":"Appenzell Innerhoden",
    "wof:name":"Doplan",
    "wof:placetype":"venue"
},
  "geometry": {"coordinates":[9.3911008835,47.3325920105],"type":"Point"}
}