{
  "type": "Feature",
  "properties": {
    "iso:country":"CH",
    "sg:address":"Landstrasse 29",
    "sg:city":"Oberurnen",
    "sg:orig_category":"Detailhandel mit Metallwaren, Anstrichmitteln, Glaswaren, Bau U Heimwerkerbedarf Mechanische Werkst\u00e4",
    "sg:phone":"+41 32 968 06 56",
    "sg:postcode":"8868",
    "sg:province":"Glarus",
    "wof:name":"Nadem Sa M\u00e9canique Horlog\u00e8re",
    "wof:placetype":"venue"
},
  "geometry": {"coordinates":[6.8358011246,47.1134872437],"type":"Point"}
}