{
  "type": "Feature",
  "properties": {
    "iso:country":"CH",
    "sg:address":"Place Du Centenaire 1",
    "sg:city":"Aigle",
    "sg:orig_category":"Versicherungen Hauptagenturen",
    "sg:phone":"+41 24 466 11 43",
    "sg:postcode":"1860",
    "sg:province":"Vaud",
    "wof:name":"Elvia Assurances Agence R\u00e9gionale",
    "wof:placetype":"venue"
},
  "geometry": {"coordinates":[6.9701910019,46.319065094],"type":"Point"}
}