{
  "type": "Feature",
  "properties": {
    "iso:country":"CH",
    "sg:address":"Hermannstrasse 8",
    "sg:city":"Winterthur",
    "sg:orig_category":"Detailhandel mit Spielwaren",
    "sg:phone":"+41 52 242 81 18",
    "sg:postcode":"8400",
    "sg:province":"Z\u00fcrich",
    "wof:name":"Hope-modellbau Ag",
    "wof:placetype":"venue"
},
  "geometry": {"coordinates":[8.7412967682,47.4983787537],"type":"Point"}
}