{
  "type": "Feature",
  "properties": {
    "iso:country":"CH",
    "sg:address":"Aarbergergasse 36",
    "sg:city":"Bern",
    "sg:orig_category":"Non-Classified Establishments",
    "sg:postcode":"3011",
    "sg:province":"Bern",
    "wof:name":"Bruni X",
    "wof:placetype":"venue"
},
  "geometry": {"coordinates":[7.442553997,46.9497070312],"type":"Point"}
}