{
  "type": "Feature",
  "properties": {
    "iso:country":"CH",
    "sg:address":"H\u00f6henstrasse 36 A",
    "sg:city":"Zollikon",
    "sg:orig_category":"Non-Classified Establishments",
    "sg:postcode":"8702",
    "sg:province":"Z\u00fcrich",
    "wof:name":"Avitas Ag",
    "wof:placetype":"venue"
},
  "geometry": {"coordinates":[7.5570011139,47.5145225525],"type":"Point"}
}