{
  "type": "Feature",
  "properties": {
    "iso:country":"CH",
    "sg:address":"Rue De Vevey 12 1630 Bulle Case Postale 202",
    "sg:city":"Bulle",
    "sg:orig_category":"Fachdetailhandel in Verkaufsr\u00e4umen",
    "sg:phone":"+41 79 230 77 19",
    "sg:postcode":"1630",
    "sg:province":"Fribourg",
    "wof:name":"Photo Overney",
    "wof:placetype":"venue"
},
  "geometry": {"coordinates":[7.055724144,46.61693573],"type":"Point"}
}