{
  "type": "Feature",
  "properties": {
    "iso:country":"CH",
    "sg:address":"Oberhof",
    "sg:city":"Fischenthal",
    "sg:orig_category":"Sportvereine Sch\u00fctzen",
    "sg:phone":"+41 55 245 17 83",
    "sg:postcode":"8497",
    "sg:province":"Z\u00fcrich",
    "wof:name":"Feldsch\u00fctzenverein",
    "wof:placetype":"venue"
},
  "geometry": {"coordinates":[8.9213924408,47.3309745789],"type":"Point"}
}