{
  "type": "Feature",
  "properties": {
    "iso:country":"CH",
    "sg:address":"Engadinstrasse 30 7000 Chur. Postfach",
    "sg:city":"Chur",
    "sg:orig_category":"Verwaltung von Immobilien",
    "sg:phone":"+41 81 252 10 10",
    "sg:postcode":"7001",
    "sg:province":"Graubunden",
    "wof:name":"Zensor Treuhand Chur Ag Treuhand- U. Finanzgesch\u00e4fte",
    "wof:placetype":"venue"
},
  "geometry": {"coordinates":[9.5286598206,46.8506813049],"type":"Point"}
}