{
  "type": "Feature",
  "properties": {
    "iso:country":"CH",
    "sg:address":"Via Del Tiglio 8",
    "sg:city":"Giubiasco",
    "sg:orig_category":"Vorschulen, Kinderg\u00e4rten",
    "sg:phone":"+41 91 857 25 00",
    "sg:postcode":"6512",
    "sg:province":"Ticino",
    "wof:name":"Scuola Materna Sud",
    "wof:placetype":"venue"
},
  "geometry": {"coordinates":[9.0017337799,46.1706199646],"type":"Point"}
}