{
  "type": "Feature",
  "properties": {
    "iso:country":"CH",
    "sg:address":"Bolligenstrasse 18",
    "sg:city":"Bern",
    "sg:orig_category":"Unternehmensberatung",
    "sg:phone":"+41 31 934 42 10",
    "sg:postcode":"3000",
    "sg:province":"Bern",
    "wof:name":"Vega Consulting Gmbh",
    "wof:placetype":"venue"
},
  "geometry": {"coordinates":[7.4658441544,46.9536781311],"type":"Point"}
}