{
  "type": "Feature",
  "properties": {
    "iso:country":"CH",
    "sg:address":"Kronenstrasse 745",
    "sg:city":"Wolfhalden",
    "sg:orig_category":"Gesundheitswesen",
    "sg:postcode":"9427",
    "sg:province":"Appenzell Ausserrhoden",
    "wof:name":"Serafin Naturheilpraxis Ag",
    "wof:placetype":"venue"
},
  "geometry": {"coordinates":[9.5537586212,47.4545593262],"type":"Point"}
}