{
  "type": "Feature",
  "properties": {
    "iso:country":"CH",
    "sg:address":"G\u00fcterstrasse 1a",
    "sg:city":"Safenwil",
    "sg:orig_category":"R\u00fcckgewinnung U Vorbereitung f\u00fcr die Wiederverwertung Recycling von nichtmetallischen Altmaterialien",
    "sg:phone":"+41 62 789 30 00",
    "sg:postcode":"5745",
    "sg:province":"Aargau",
    "wof:name":"Street-tex Gmbh",
    "wof:placetype":"venue"
},
  "geometry": {"coordinates":[7.9846801758,47.3214950562],"type":"Point"}
}