{
  "type": "Feature",
  "properties": {
    "iso:country":"CH",
    "sg:address":"Rue Des Deux-march\u00e9s 3",
    "sg:city":"Vevey",
    "sg:orig_category":"W\u00e4scherei U chemische Reinigung",
    "sg:phone":"+41 21 921 11 26",
    "sg:postcode":"1800",
    "sg:province":"Vaud",
    "wof:name":"Blanchisserie Lave-lux Marie-claire Loup",
    "wof:placetype":"venue"
},
  "geometry": {"coordinates":[6.8445677757,46.4595336914],"type":"Point"}
}