{
  "type": "Feature",
  "properties": {
    "iso:country":"CH",
    "sg:address":"Badenerstrasse 698 8048 Z\u00fcrich. Postfach",
    "sg:city":"Z\u00fcrich",
    "sg:orig_category":"Vermittlung von Immobilien Verwaltung von Immobilien",
    "sg:phone":"+41 31 381 32 62",
    "sg:postcode":"8021",
    "sg:province":"Z\u00fcrich",
    "wof:name":"Mens Treuhand Bern",
    "wof:placetype":"venue"
},
  "geometry": {"coordinates":[7.4293599129,46.9454917908],"type":"Point"}
}