{
  "type": "Feature",
  "properties": {
    "iso:country":"CH",
    "sg:address":"Avenue Beauregard 3",
    "sg:city":"Fribourg",
    "sg:orig_category":"Verlagsgewerbe",
    "sg:phone":"+41 26 424 31 28",
    "sg:postcode":"1700",
    "sg:province":"Fribourg",
    "wof:name":"Imba-verlag",
    "wof:placetype":"venue"
},
  "geometry": {"coordinates":[7.1486549377,46.8023872375],"type":"Point"}
}