{
  "type": "Feature",
  "properties": {
    "iso:country":"CH",
    "sg:address":"Unterdorf 7",
    "sg:city":"Tschugg",
    "sg:orig_category":"Bauschreinerei Herstellung von Konstruktionsteilen, Fertigbauteilen U Ausbauelementen aus Holz",
    "sg:phone":"+41 79 244 77 80",
    "sg:postcode":"3233",
    "sg:province":"Bern",
    "wof:name":"B\u00f6nzli & St\u00f6ckli Ag",
    "wof:placetype":"venue"
},
  "geometry": {"coordinates":[7.077363,47.025558],"type":"Point"}
}