{
  "type": "Feature",
  "properties": {
    "addr:full":"6676 Bignasco Ticino 6676",
    "addr:housenumber":"6676",
    "addr:postcode":"6676",
    "iso:country":"CH",
    "sg:address":"6676",
    "sg:city":"Bignasco",
    "sg:orig_category":"Autogaragen",
    "sg:phone":"+41 91 754 16 36",
    "sg:postcode":"6676",
    "sg:province":"Ticino",
    "wof:name":"Evaristo Inselmini Garage",
    "wof:placetype":"venue"
},
  "geometry": {"coordinates":[8.60713,46.338501],"type":"Point"}
}