{
  "type": "Feature",
  "properties": {
    "iso:country":"CH",
    "sg:address":"Lindenstrasse 33 4123 Allschwil. Postfach",
    "sg:city":"Allschwil",
    "sg:orig_category":"Erbringung von Dienstleistungen f\u00fcr Unternehmen",
    "sg:phone":"+41 61 481 70 22",
    "sg:postcode":"4123",
    "sg:province":"Basel-Landschaft",
    "wof:name":"Sgier Reto 24-h-service Innendekorationen, M\u00f6bel- U. Vorhangmontagen Usw",
    "wof:placetype":"venue"
},
  "geometry": {"coordinates":[7.5612010956,47.5591812134],"type":"Point"}
}