{
  "type": "Feature",
  "properties": {
    "iso:country":"CH",
    "sg:address":"Industriestrasse 19 8112 Otelfingen. Postfach",
    "sg:city":"Otelfingen",
    "sg:orig_category":"Erzeugung U Erstbearbeitung von Aluminium Stahl U Leichtmetallbau",
    "sg:phone":"+41 81 302 16 63",
    "sg:postcode":"8112",
    "sg:province":"Z\u00fcrich",
    "wof:name":"Hubru-produktions Ag",
    "wof:placetype":"venue"
},
  "geometry": {"coordinates":[9.4980945587,47.0134658813],"type":"Point"}
}