{
  "type": "Feature",
  "properties": {
    "iso:country":"CH",
    "sg:address":"Schulstrasse 84 8952 Schlieren. Postfach",
    "sg:city":"Schlieren",
    "sg:orig_category":"Wirtschaftspr\u00fcfung, Steuerberatung U Treuhand",
    "sg:postcode":"8952",
    "sg:province":"Z\u00fcrich",
    "wof:name":"Taormina Maurizio - Steuerberatung Und Buchhaltung",
    "wof:placetype":"venue"
},
  "geometry": {"coordinates":[8.4625959396,47.3959884644],"type":"Point"}
}