{
  "type": "Feature",
  "properties": {
    "iso:country":"CH",
    "sg:address":"Im Sterne 718",
    "sg:city":"Marthalen",
    "sg:orig_category":"Mit dem Versicherungsgewerbe verbundene T\u00e4tigkeiten",
    "sg:phone":"+41 52 319 28 96",
    "sg:postcode":"8460",
    "sg:province":"Z\u00fcrich",
    "wof:name":"Iselin Andreas & Co",
    "wof:placetype":"venue"
},
  "geometry": {"coordinates":[8.6518497467,47.6268882751],"type":"Point"}
}