{
  "type": "Feature",
  "properties": {
    "iso:country":"CH",
    "sg:address":"2922",
    "sg:city":"Courchavon",
    "sg:orig_category":"Detailhandel mit Radio U Fernsehger\u00e4ten",
    "sg:phone":"+41 32 466 18 81",
    "sg:postcode":"2922",
    "sg:province":"Jura",
    "wof:name":"Jean-jacques Lehmann Vid\u00e9o-tv",
    "wof:placetype":"venue"
},
  "geometry": {"coordinates":[7.0565690994,47.4390068054],"type":"Point"}
}