{
  "type": "Feature",
  "properties": {
    "iso:country":"CH",
    "sg:address":"Bahnhofstrasse 35",
    "sg:city":"Z\u00fcrich",
    "sg:orig_category":"Herstellung von medizinischen U chirurgischen Ger\u00e4ten sowie orthop\u00e4dischen Vorrichtungen",
    "sg:phone":"+41 12220565",
    "sg:postcode":"8001",
    "sg:province":"Z\u00fcrich",
    "wof:name":"Pietrobon & Michel Zahntechnisches Labor",
    "wof:placetype":"venue"
},
  "geometry": {"coordinates":[8.5386161804,47.3712043762],"type":"Point"}
}