{
  "type": "Feature",
  "properties": {
    "iso:country":"CH",
    "sg:address":"Route Du Nant-d'avril 51",
    "sg:city":"Vernier",
    "sg:classifiers":[
        {
            "category":"Exhibition Hall",
            "type":"Public Place"
        }
    ],
    "sg:phone":"+41 79 202 07 30",
    "sg:postcode":"1214",
    "sg:province":"Gen\u00e8ve",
    "sg:tags":[
        "equipping",
        "sale",
        "room",
        "show"
    ],
    "wof:name":"Syma System R. Berger Sa",
    "wof:placetype":"venue"
},
  "geometry": {"coordinates":[6.0804700851,46.2123413086],"type":"Point"}
}