{
  "type": "Feature",
  "properties": {
    "iso:country":"CH",
    "sg:address":"Kapuzinerstrasse 53 3902 Glis. Postfach 238",
    "sg:city":"Glis",
    "sg:orig_category":"Bauschreinerei",
    "sg:phone":"+41 27 924 97 27",
    "sg:postcode":"3902",
    "sg:province":"Valais",
    "wof:name":"A. N. Holz-service Gmbh Bauschreinerei",
    "wof:placetype":"venue"
},
  "geometry": {"coordinates":[7.987723,46.314137],"type":"Point"}
}