{
  "type": "Feature",
  "properties": {
    "iso:country":"CH",
    "sg:address":"Grand-rue 26",
    "sg:city":"Fleurier",
    "sg:orig_category":"Detailhandel mit Brot, Back U S\u00fcsswaren",
    "sg:postcode":"2114",
    "sg:province":"Neuch\u00e2tel",
    "wof:name":"Jean-marie Hummel",
    "wof:placetype":"venue"
},
  "geometry": {"coordinates":[6.58005,46.902367],"type":"Point"}
}