{
  "type": "Feature",
  "properties": {
    "iso:country":"CH",
    "sg:address":"Sinserstrasse 47",
    "sg:city":"Cham",
    "sg:orig_category":"Unclassifiable Establishments",
    "sg:phone":"+41 41 785 19 19",
    "sg:postcode":"6330",
    "sg:province":"Zug",
    "wof:name":"M\u00f6venpick Foods International Ltd",
    "wof:placetype":"venue"
},
  "geometry": {"coordinates":[8.4538116455,47.1861457825],"type":"Point"}
}