{
  "type": "Feature",
  "properties": {
    "iso:country":"CH",
    "sg:address":"Gennersbrunnerstr. 2",
    "sg:city":"D\u00f6rflingen",
    "sg:orig_category":"Sonstige mit der Informatik verbundene T\u00e4tigkeiten",
    "sg:phone":"+41 79 353 59 11",
    "sg:postcode":"8239",
    "sg:province":"Schaffhausen",
    "wof:name":"Piccolin Ren\u00e9 Edv Dienst & Leistung",
    "wof:placetype":"venue"
},
  "geometry": {"coordinates":[8.7191038132,47.7082595825],"type":"Point"}
}