{
  "type": "Feature",
  "properties": {
    "iso:country":"CH",
    "sg:address":"Oberdorfstrasse",
    "sg:city":"Glarus",
    "sg:orig_category":"Aktivit\u00e4ten der Generalunternehmen im Baugewerbe Vermittlung von Immobilien",
    "sg:phone":"+41 22 796 87 44",
    "sg:postcode":"8750",
    "sg:province":"Glarus",
    "wof:name":"G\u00f6hner Merkur Sa Entreprise G\u00e9n.& Immeubles",
    "wof:placetype":"venue"
},
  "geometry": {"coordinates":[6.097153,46.202702],"type":"Point"}
}