{
  "type": "Feature",
  "properties": {
    "iso:country":"CH",
    "sg:address":"Riehenstrasse 20",
    "sg:city":"Basel",
    "sg:orig_category":"Arztpraxen",
    "sg:phone":"+41 61 272 58 45",
    "sg:postcode":"4058",
    "sg:province":"Basel-Stadt",
    "wof:name":"Dr.med.silvia Cueni Spezial\u00e4rztin Fmh",
    "wof:placetype":"venue"
},
  "geometry": {"coordinates":[7.598068,47.560543],"type":"Point"}
}