{
  "type": "Feature",
  "properties": {
    "iso:country":"CH",
    "sg:address":"Terbinerstrasse 11 3930 Visp. Postfach",
    "sg:city":"Visp",
    "sg:orig_category":"Herstellung von Metallerzeugnissen ohne Maschinenbau",
    "sg:phone":"+41 27 946 18 35",
    "sg:postcode":"3930",
    "sg:province":"Valais",
    "wof:name":"Vugo Sa",
    "wof:placetype":"venue"
},
  "geometry": {"coordinates":[7.885114193,46.2912597656],"type":"Point"}
}