{
  "type": "Feature",
  "properties": {
    "iso:country":"CH",
    "sg:address":"3236",
    "sg:city":"Gampelen",
    "sg:orig_category":"Verwertung von Milch",
    "sg:phone":"+41 71 385 25 63",
    "sg:postcode":"3236",
    "sg:province":"Bern",
    "wof:name":"Germann Karl",
    "wof:placetype":"venue"
},
  "geometry": {"coordinates":[9.2720041275,47.4358673096],"type":"Point"}
}