{
  "type": "Feature",
  "properties": {
    "iso:country":"CH",
    "sg:address":"M\u00fchlaudamm 10",
    "sg:city":"Aarberg",
    "sg:orig_category":"RESTAURANTS: TEA-ROOMS",
    "sg:phone":"+41 79 334 39 89",
    "sg:postcode":"3270",
    "sg:province":"Bern",
    "wof:name":"Big Bamboo Ag Gastronomiebetriebe",
    "wof:placetype":"venue"
},
  "geometry": {"coordinates":[7.2693529129,47.0406455994],"type":"Point"}
}