{
  "type": "Feature",
  "properties": {
    "iso:country":"CH",
    "sg:address":"Am Galterbach 7",
    "sg:city":"Gansingen",
    "sg:orig_category":"Organisationen des Gesundheitswesen",
    "sg:phone":"+41 62 875 19 28",
    "sg:postcode":"5272",
    "sg:province":"Aargau",
    "wof:name":"Samariterverein Gansingen",
    "wof:placetype":"venue"
},
  "geometry": {"coordinates":[8.1327142715,47.5424613953],"type":"Point"}
}