{
  "type": "Feature",
  "properties": {
    "iso:country":"CH",
    "sg:address":"Amselweg 4",
    "sg:city":"D\u00fcbendorf",
    "sg:orig_category":"Maler U Glasergewerbe Malerei",
    "sg:phone":"+41 18210849",
    "sg:postcode":"8600",
    "sg:province":"Z\u00fcrich",
    "wof:name":"Georg Schelbert, Malergesch\u00e4ft",
    "wof:placetype":"venue"
},
  "geometry": {"coordinates":[8.6104211807,47.3951187134],"type":"Point"}
}