{
  "type": "Feature",
  "properties": {
    "iso:country":"CH",
    "sg:address":"Sidlerstrasse 5",
    "sg:city":"Bern",
    "sg:orig_category":"Forschung U Entwicklung im Bereich der Naturwissenschaften",
    "sg:phone":"+41 31 631 40 52",
    "sg:postcode":"3012",
    "sg:province":"Bern",
    "wof:name":"Hochalpine Forschungsstationen Jungfraujoch Und Gornergrat",
    "wof:placetype":"venue"
},
  "geometry": {"coordinates":[7.4384889603,46.951259613],"type":"Point"}
}