{
  "type": "Feature",
  "properties": {
    "addr:full":"Adolf Frey-strasse 5 Aarau Aargau 5000",
    "addr:housenumber":"5",
    "addr:postcode":"5000",
    "addr:street":"Adolf Frey-Strasse",
    "iso:country":"CH",
    "sg:address":"Adolf Frey-strasse 5",
    "sg:city":"Aarau",
    "sg:orig_category":"Betrieb von Taxis",
    "sg:phone":"+41 79 300 79 79",
    "sg:postcode":"5000",
    "sg:province":"Aargau",
    "wof:name":"Aargauer-taxi Trinkler Bruno + Ogg Carolina",
    "wof:placetype":"venue"
},
  "geometry": {"coordinates":[8.285908,47.450005],"type":"Point"}
}