{
  "type": "Feature",
  "properties": {
    "iso:country":"CH",
    "sg:address":"Birkenmatt 3",
    "sg:city":"Rotkreuz",
    "sg:orig_category":"Detailhandel mit Musikinstrumenten Detailhandel mit elektrischen Haushalts-,Radio U Fernsehger\u00e4ten s",
    "sg:phone":"+41 41 790 09 05",
    "sg:postcode":"6343",
    "sg:province":"Zug",
    "wof:name":"Keller Hans, Harmonika-spezialhaus",
    "wof:placetype":"venue"
},
  "geometry": {"coordinates":[8.4295082092,47.1433982849],"type":"Point"}
}