{
  "type": "Feature",
  "properties": {
    "iso:country":"CH",
    "sg:address":"8165",
    "sg:city":"Oberweningen",
    "sg:orig_category":"Sportvereine Sch\u00fctzen",
    "sg:postcode":"8165",
    "sg:province":"Z\u00fcrich",
    "wof:name":"Schiessverein Oberweningen",
    "wof:placetype":"venue"
},
  "geometry": {"coordinates":[8.4051847458,47.5006599426],"type":"Point"}
}