{
  "type": "Feature",
  "properties": {
    "iso:country":"CH",
    "sg:address":"Dorfplatz 11",
    "sg:city":"Dotzigen",
    "sg:orig_category":"Unternehmensberatung",
    "sg:phone":"+41 32 353 70 04",
    "sg:postcode":"3293",
    "sg:province":"Bern",
    "wof:name":"Bonjour-grand Service Gmbh",
    "wof:placetype":"venue"
},
  "geometry": {"coordinates":[7.3402581215,47.1202011108],"type":"Point"}
}