{
  "type": "Feature",
  "properties": {
    "iso:country":"CH",
    "sg:address":"5040",
    "sg:city":"Sch\u00f6ftland",
    "sg:orig_category":"Gewinnung von Kies U Sand Herstellung von sonstigen Produkten aus nichtmetallischen Mineralien",
    "sg:phone":"+41 31 931 62 51",
    "sg:postcode":"5040",
    "sg:province":"Aargau",
    "wof:name":"Kies-& Transportbetonwerke Bern & Umgebung",
    "wof:placetype":"venue"
},
  "geometry": {"coordinates":[7.4658479691,46.9522171021],"type":"Point"}
}