{
  "type": "Feature",
  "properties": {
    "iso:country":"CH",
    "sg:address":"Bahnhofstrasse 30",
    "sg:city":"Schaffhausen",
    "sg:orig_category":"Darlehenskassen U Raiffeisenbanken",
    "sg:phone":"+41 52 630 04 30",
    "sg:postcode":"8200",
    "sg:province":"Schaffhausen",
    "wof:name":"Raiffeisenbank Schaffhausen",
    "wof:placetype":"venue"
},
  "geometry": {"coordinates":[8.632875,47.697803],"type":"Point"}
}