{
  "type": "Feature",
  "properties": {
    "iso:country":"CH",
    "sg:address":"6595",
    "sg:city":"Riazzino",
    "sg:orig_category":"Einzelhandel mit Automobilen Instandhaltung U Reparatur von Automobilen",
    "sg:phone":"+41 91 859 24 01",
    "sg:postcode":"6595",
    "sg:province":"Ticino",
    "wof:name":"Garage Molea Sagl",
    "wof:placetype":"venue"
},
  "geometry": {"coordinates":[8.897600174,46.1745605469],"type":"Point"}
}