{
  "type": "Feature",
  "properties": {
    "iso:country":"CH",
    "sg:address":"Clarastrasse 56",
    "sg:city":"Basel",
    "sg:orig_category":"Interessenvertretungen",
    "sg:postcode":"4058",
    "sg:province":"Basel-Stadt",
    "wof:name":"Kraemer Gerard-stiftung",
    "wof:placetype":"venue"
},
  "geometry": {"coordinates":[7.5986618996,47.5632247925],"type":"Point"}
}