{
  "type": "Feature",
  "properties": {
    "iso:country":"CH",
    "sg:address":"Hauptstrasse 4",
    "sg:city":"Ober\u00e4geri",
    "sg:orig_category":"Verwaltung von Immobilien",
    "sg:phone":"+41 41 750 80 00",
    "sg:postcode":"6315",
    "sg:province":"Zug",
    "wof:name":"Holiday Home Ag",
    "wof:placetype":"venue"
},
  "geometry": {"coordinates":[8.6137132645,47.1350135803],"type":"Point"}
}