{
  "type": "Feature",
  "properties": {
    "iso:country":"CH",
    "sg:address":"Rue Du Temple 9 1530 Payerne Case Postale 203",
    "sg:city":"Payerne",
    "sg:orig_category":"Geometerb\u00fcros",
    "sg:phone":"+41 26 662 41 11",
    "sg:postcode":"1530",
    "sg:province":"Vaud",
    "wof:name":"Bureau Technique Perrin",
    "wof:placetype":"venue"
},
  "geometry": {"coordinates":[6.9387960434,46.8209533691],"type":"Point"}
}