{
  "type": "Feature",
  "properties": {
    "iso:country":"CH",
    "sg:address":"Haldenstrasse 8 A",
    "sg:city":"Aarwangen",
    "sg:orig_category":"Finanzierungsinstitutionen",
    "sg:postcode":"4912",
    "sg:province":"Bern",
    "wof:name":"Sc Schweizer Consulting",
    "wof:placetype":"venue"
},
  "geometry": {"coordinates":[7.7717719078,47.2352485657],"type":"Point"}
}