{
  "type": "Feature",
  "properties": {
    "iso:country":"CH",
    "sg:address":"Chemin De Cuard 47b",
    "sg:city":"Bevaix",
    "sg:orig_category":"Fahrschulen, Flugschulen",
    "sg:phone":"+41 79 637 45 41",
    "sg:postcode":"2022",
    "sg:province":"Neuch\u00e2tel",
    "wof:name":"Olivier Suzon Auto-\u00e9cole",
    "wof:placetype":"venue"
},
  "geometry": {"coordinates":[6.8130869865,46.9334564209],"type":"Point"}
}