{
  "type": "Feature",
  "properties": {
    "iso:country":"CH",
    "sg:address":"Route De L'aurore 5",
    "sg:city":"Fribourg",
    "sg:orig_category":"Restaurants Schwimmb\u00e4der",
    "sg:phone":"+41 79 401 78 14",
    "sg:postcode":"1700",
    "sg:province":"Fribourg",
    "wof:name":"Piscine Du Levant",
    "wof:placetype":"venue"
},
  "geometry": {"coordinates":[7.151515007,46.8129310608],"type":"Point"}
}