{
  "type": "Feature",
  "properties": {
    "iso:country":"CH",
    "sg:address":"Kurhausstrasse 18 8032 Z\u00fcrich. Postfach 138",
    "sg:city":"Z\u00fcrich",
    "sg:orig_category":"Non-Classified Establishments",
    "sg:phone":"+41 27 957 24 89",
    "sg:postcode":"8030",
    "wof:name":"Hotel Dolomit",
    "wof:placetype":"venue"
},
  "geometry": {"coordinates":[7.9247078896,46.1060218811],"type":"Point"}
}