{
  "type": "Feature",
  "properties": {
    "iso:country":"CH",
    "sg:address":"Hauptstrasse 95",
    "sg:city":"Bettingen",
    "sg:orig_category":"Nationale Postdienste",
    "sg:phone":"+41 62 390 15 44",
    "sg:postcode":"4126",
    "sg:province":"Basel-Stadt",
    "wof:name":"Die Schweizerische Post",
    "wof:placetype":"venue"
},
  "geometry": {"coordinates":[7.7541871071,47.3327217102],"type":"Point"}
}