{
  "type": "Feature",
  "properties": {
    "iso:country":"CH",
    "sg:address":"Route Principale",
    "sg:city":"Fahy",
    "sg:orig_category":"Grosshandel mit festen Brennstoffen U Mineral\u00f6lerzeugnissen Herstellung von Seifen, Wasch U Reinigun",
    "sg:phone":"+41 32 476 60 67",
    "sg:postcode":"2916",
    "sg:province":"Jura",
    "wof:name":"Carlub S\u00e0rl",
    "wof:placetype":"venue"
},
  "geometry": {"coordinates":[6.9486298561,47.4190559387],"type":"Point"}
}