{
  "type": "Feature",
  "properties": {
    "iso:country":"CH",
    "sg:address":"Fuhrstrasse 31",
    "sg:city":"W\u00e4denswil",
    "sg:orig_category":"Sonstige pers\u00f6nliche Dienstleistungen Unternehmensberatung",
    "sg:phone":"+41 17808617",
    "sg:postcode":"8820",
    "sg:province":"Z\u00fcrich",
    "wof:name":"Spirig Innovation & Management Gmbh",
    "wof:placetype":"venue"
},
  "geometry": {"coordinates":[8.6667976379,47.2283477783],"type":"Point"}
}