{
  "type": "Feature",
  "properties": {
    "addr:full":"Im Kleinholz Olten Solothurn 4600",
    "addr:postcode":"4600",
    "addr:street":"Im Kleinholz",
    "iso:country":"CH",
    "sg:address":"Im Kleinholz",
    "sg:city":"Olten",
    "sg:orig_category":"Betrieb von Sportanlagen",
    "sg:phone":"+41 62 212 79 10",
    "sg:postcode":"4600",
    "sg:province":"Solothurn",
    "wof:name":"Kunsteisbahn-genossenschaft Olten",
    "wof:placetype":"venue"
},
  "geometry": {"coordinates":[7.899585,47.344788],"type":"Point"}
}