{
  "type": "Feature",
  "properties": {
    "iso:country":"CH",
    "sg:address":"Hauptstrasse 31 9478 Wartau. Postfach",
    "sg:city":"Tr\u00fcbbach",
    "sg:orig_category":"Detailhandel mit elektrischen Haushalts-,Radio U Fernsehger\u00e4ten sowie Musikinstrumenten",
    "sg:postcode":"9477",
    "sg:province":"St. Gallen",
    "wof:name":"Salis Albert Elektrohaushaltger\u00e4te",
    "wof:placetype":"venue"
},
  "geometry": {"coordinates":[9.4809579849,47.0732345581],"type":"Point"}
}