{
  "type": "Feature",
  "properties": {
    "iso:country":"CH",
    "sg:address":"Elisabethenstrasse 44 4051 Basel. Postfach",
    "sg:city":"Basel",
    "sg:orig_category":"Datenverarbeitungsdienste",
    "sg:postcode":"4051",
    "sg:province":"Basel-Stadt",
    "wof:name":"Safeconsult Ag Beratungs, Schulungsleistungen Im Bereich Sicherheitsmanagement Bes. Logistik Usw",
    "wof:placetype":"venue"
},
  "geometry": {"coordinates":[7.590619,47.550602],"type":"Point"}
}