{
  "type": "Feature",
  "properties": {
    "iso:country":"CH",
    "sg:address":"Rue Galil\u00e9e 15",
    "sg:city":"Yverdon-les-bains",
    "sg:orig_category":"Herstellung von elektrischen Lampen U Leuchten",
    "sg:postcode":"1400",
    "sg:province":"Vaud",
    "wof:name":"Swiss-light Gmbh",
    "wof:placetype":"venue"
},
  "geometry": {"coordinates":[8.6332759857,46.88123703],"type":"Point"}
}