{
  "type": "Feature",
  "properties": {
    "iso:country":"CH",
    "sg:address":"Rue De La Blancherie 29",
    "sg:city":"Sion",
    "sg:orig_category":"Massagestudios",
    "sg:phone":"+41 27 322 70 31",
    "sg:postcode":"1950",
    "sg:province":"Valais",
    "wof:name":"Jean-yves Holzer Centre De Massage",
    "wof:placetype":"venue"
},
  "geometry": {"coordinates":[7.3555631638,46.226184845],"type":"Point"}
}