{
  "type": "Feature",
  "properties": {
    "iso:country":"CH",
    "sg:address":"Hauptstr. 149",
    "sg:city":"Bubendorf",
    "sg:classifiers":[
        {
            "category":"Professional",
            "subcategory":"Engineering",
            "type":"Services"
        }
    ],
    "sg:phone":"+41 61 935 36 36",
    "sg:postcode":"4416",
    "sg:province":"Basel-Landschaft",
    "sg:tags":[
        "machine",
        "-",
        "mechanical"
    ],
    "wof:name":"Lamello Ag",
    "wof:placetype":"venue"
},
  "geometry": {"coordinates":[7.7323770523,47.44272995],"type":"Point"}
}