{
  "type": "Feature",
  "properties": {
    "iso:country":"CH",
    "sg:address":"Sidlerstrasse 4",
    "sg:city":"Bern",
    "sg:orig_category":"Gesundheitswesen",
    "sg:phone":"+41 21 634 70 15",
    "sg:postcode":"3012",
    "sg:province":"Bern",
    "wof:name":"Dream Maker's S\u00e0rl",
    "wof:placetype":"venue"
},
  "geometry": {"coordinates":[6.579390049,46.5390815735],"type":"Point"}
}