{
  "type": "Feature",
  "properties": {
    "iso:country":"CH",
    "sg:address":"Pianscari",
    "sg:city":"Grancia",
    "sg:orig_category":"Grosshandel mit sonstigen Nahrungsmitteln",
    "sg:phone":"+41 91 993 32 42",
    "sg:postcode":"6916",
    "sg:province":"Ticino",
    "wof:name":"Mp Mercato Del Pesce Sa",
    "wof:placetype":"venue"
},
  "geometry": {"coordinates":[8.9250659943,45.9669761658],"type":"Point"}
}