{
  "type": "Feature",
  "properties": {
    "iso:country":"CH",
    "sg:address":"Ohne Domizil",
    "sg:city":"Z\u00fcrich",
    "sg:orig_category":"Vermietung U Verpachtung von eigenen Immobilien",
    "sg:phone":"+41 12689010",
    "sg:postcode":"8000",
    "sg:province":"Z\u00fcrich",
    "wof:name":"Dr. Seiler Immobilien Ag",
    "wof:placetype":"venue"
},
  "geometry": {"coordinates":[8.4809503555,47.3614616394],"type":"Point"}
}