{
  "type": "Feature",
  "properties": {
    "iso:country":"CH",
    "sg:address":"Solothurnstrasse 31 3303 Jegenstorf. Postfach",
    "sg:city":"Jegenstorf",
    "sg:orig_category":"Herstellung von sonstigen elektrischen Ausr\u00fcstungen",
    "sg:phone":"+41 31 762 00 06",
    "sg:postcode":"3303",
    "sg:province":"Bern",
    "wof:name":"Hert Sicherheitsanlagen",
    "wof:placetype":"venue"
},
  "geometry": {"coordinates":[7.5113101006,47.0535697937],"type":"Point"}
}