{
  "type": "Feature",
  "properties": {
    "iso:country":"CH",
    "sg:address":"Chemin De La Porat",
    "sg:city":"Savigny",
    "sg:orig_category":"Herstellung von Konstruktionsteilen, Fertigbauteilen U Ausbauelementen aus Holz",
    "sg:postcode":"1073",
    "sg:province":"Vaud",
    "wof:name":"Bastian Raymond",
    "wof:placetype":"venue"
},
  "geometry": {"coordinates":[6.7278089523,46.5374755859],"type":"Point"}
}