{
  "type": "Feature",
  "properties": {
    "iso:country":"CH",
    "sg:address":"Avenue P.-ceresole 12",
    "sg:city":"Vevey",
    "sg:orig_category":"Zahnarztpraxen",
    "sg:phone":"+41 21 921 74 17",
    "sg:postcode":"1800",
    "sg:province":"Vaud",
    "wof:name":"Dr M\u00e9d. Dent. Michel Sergent M\u00e9decin-dentiste",
    "wof:placetype":"venue"
},
  "geometry": {"coordinates":[6.8421201706,46.4615402222],"type":"Point"}
}