{
  "type": "Feature",
  "properties": {
    "iso:country":"CH",
    "sg:address":"Burggrabenstrasse 23",
    "sg:city":"Kreuzlingen",
    "sg:orig_category":"Detailhandel mit Radio U Fernsehger\u00e4ten",
    "sg:phone":"+41 71 688 45 10",
    "sg:postcode":"8280",
    "sg:province":"Thurgau",
    "wof:name":"Peter Hofstetter Radio-& Tv-service",
    "wof:placetype":"venue"
},
  "geometry": {"coordinates":[9.1868553162,47.6397819519],"type":"Point"}
}