{
  "type": "Feature",
  "properties": {
    "iso:country":"CH",
    "sg:address":"Chemin De Rov\u00e9r\u00e9az 24",
    "sg:city":"Lausanne",
    "sg:orig_category":"Physiotherapie",
    "sg:phone":"+41 21 323 49 21",
    "sg:postcode":"1012",
    "sg:province":"Vaud",
    "wof:name":"Jean-paul Blais Physioth\u00e9rapie",
    "wof:placetype":"venue"
},
  "geometry": {"coordinates":[6.6562991142,46.5294342041],"type":"Point"}
}