{
  "type": "Feature",
  "properties": {
    "iso:country":"CH",
    "sg:address":"G\u00fcrtelstrasse 89",
    "sg:city":"Chur",
    "sg:orig_category":"Institutionen des Sozialwesens ohne Beherbergung",
    "sg:phone":"+41 81 257 26 56",
    "sg:postcode":"7000",
    "sg:province":"Graubunden",
    "wof:name":"Winterhilfe Graub\u00fcnden",
    "wof:placetype":"venue"
},
  "geometry": {"coordinates":[9.5316114426,46.8565826416],"type":"Point"}
}