{
  "type": "Feature",
  "properties": {
    "iso:country":"CH",
    "sg:address":"Dorfstrasse 328",
    "sg:city":"Matzendorf",
    "sg:orig_category":"Elektroinstallation",
    "sg:phone":"+41 62 394 12 74",
    "sg:postcode":"4713",
    "sg:province":"Solothurn",
    "wof:name":"Atel Elektroanlagen Ag",
    "wof:placetype":"venue"
},
  "geometry": {"coordinates":[7.632671833,47.3043556213],"type":"Point"}
}