{
  "type": "Feature",
  "properties": {
    "iso:country":"CH",
    "sg:address":"Oberg\u00e4ssli 3",
    "sg:city":"Biel/bienne",
    "sg:orig_category":"Mit dem Versicherungsgewerbe verbundene T\u00e4tigkeiten",
    "sg:phone":"+41 32 322 20 94",
    "sg:postcode":"2502",
    "sg:province":"Bern",
    "wof:name":"Future Consulting Service S\u00e0rl",
    "wof:placetype":"venue"
},
  "geometry": {"coordinates":[7.2456412315,47.1415710449],"type":"Point"}
}