{
  "type": "Feature",
  "properties": {
    "iso:country":"CH",
    "sg:address":"Rue De La Gare 2 2500 Biel/bienne Case Postale 249",
    "sg:city":"Biel/bienne",
    "sg:orig_category":"Herstellung von Zahnr\u00e4dern U Antriebselementen",
    "sg:phone":"+41 32 322 77 43",
    "sg:postcode":"2500",
    "sg:province":"Bern",
    "wof:name":"Socome Sa, Engrenages, Bienne",
    "wof:placetype":"venue"
},
  "geometry": {"coordinates":[7.2435631752,47.1335487366],"type":"Point"}
}