{
  "type": "Feature",
  "properties": {
    "iso:country":"CH",
    "sg:address":"Obere Hauptgasse 74",
    "sg:city":"Thun",
    "sg:orig_category":"Arztpraxen",
    "sg:phone":"+41 33 222 04 54",
    "sg:postcode":"3600",
    "sg:province":"Bern",
    "wof:name":"Dr.med. Christian Ziegler Spezialarzt Fmh",
    "wof:placetype":"venue"
},
  "geometry": {"coordinates":[7.631492,46.758022],"type":"Point"}
}