{
  "type": "Feature",
  "properties": {
    "iso:country":"CH",
    "sg:address":"Schulhausstrasse 2",
    "sg:city":"Villmergen",
    "sg:classifiers":[
        {
            "category":"Restaurant",
            "type":"Food & Drink"
        }
    ],
    "sg:phone":"+41 56 622 17 38",
    "sg:postcode":"5612",
    "sg:province":"Aargau",
    "wof:name":"Restaurant Ochsen",
    "wof:placetype":"venue"
},
  "geometry": {"coordinates":[8.2445106506,47.3474121094],"type":"Point"}
}