{
  "type": "Feature",
  "properties": {
    "iso:country":"CH",
    "sg:address":"Zelglistrasse 9",
    "sg:city":"Weinfelden",
    "sg:orig_category":"Malerei-Gipserei Stukkateurgewerbe, Gipserei U Verputzerei",
    "sg:phone":"+41 71 622 05 25",
    "sg:postcode":"8570",
    "sg:province":"Thurgau",
    "wof:name":"Esther Bucher Gipsergesch\u00e4ft",
    "wof:placetype":"venue"
},
  "geometry": {"coordinates":[9.0926876068,47.5631523132],"type":"Point"}
}