{
  "type": "Feature",
  "properties": {
    "iso:country":"CH",
    "sg:address":"Geerenstr. 10",
    "sg:city":"Wallisellen",
    "sg:classifiers":[
        {
            "category":"Autos & Motor Vehicles",
            "subcategory":"Automobile Sales",
            "type":"Retail Goods"
        }
    ],
    "sg:phone":"+41 43 233 22 22",
    "sg:postcode":"8304",
    "sg:province":"Z\u00fcrich",
    "sg:tags":[
        "equipment",
        "motor-cars",
        "transport"
    ],
    "wof:name":"Ford Motor Company Sa",
    "wof:placetype":"venue"
},
  "geometry": {"coordinates":[8.6000699997,47.4103775024],"type":"Point"}
}