{
  "type": "Feature",
  "properties": {
    "iso:country":"CH",
    "sg:address":"Warthausen",
    "sg:city":"Sch\u00e4nis",
    "sg:orig_category":"Allgemeiner Hoch U Tiefbau Hoch U Tiefbau",
    "sg:phone":"+41 55 615 10 19",
    "sg:postcode":"8718",
    "sg:province":"St. Gallen",
    "wof:name":"Giba Giger Bau",
    "wof:placetype":"venue"
},
  "geometry": {"coordinates":[9.05419,47.166828],"type":"Point"}
}