{
  "type": "Feature",
  "properties": {
    "iso:country":"CH",
    "sg:address":"Chalet Gentiana",
    "sg:city":"Chesi\u00e8res",
    "sg:orig_category":"Erbringung von Dienstleistungen f\u00fcr Unternehmen Innendekorationsateliers",
    "sg:phone":"+41 24 495 33 77",
    "sg:postcode":"1885",
    "sg:province":"Vaud",
    "wof:name":"Peter Fretz D\u00e9corateur D'int\u00e9rieur",
    "wof:placetype":"venue"
},
  "geometry": {"coordinates":[7.0434799194,46.301109314],"type":"Point"}
}