{
  "type": "Feature",
  "properties": {
    "iso:country":"CH",
    "sg:address":"Jurastrasse 9",
    "sg:city":"Inkwil",
    "sg:orig_category":"G\u00fcterbef\u00f6rderung im Strassenverkehr",
    "sg:phone":"+41 79 332 57 78",
    "sg:postcode":"3375",
    "sg:province":"Bern",
    "wof:name":"Konrad Wyss Transporte",
    "wof:placetype":"venue"
},
  "geometry": {"coordinates":[7.6777191162,47.1990394592],"type":"Point"}
}