{
  "type": "Feature",
  "properties": {
    "iso:country":"CH",
    "sg:address":"Via Torrazza 83",
    "sg:city":"Caslano",
    "sg:classifiers":[
        {
            "category":"Travel",
            "subcategory":"Hotels & Motels",
            "type":"Entertainment"
        }
    ],
    "sg:phone":"+41 91 606 40 66",
    "sg:postcode":"6987",
    "sg:province":"Ticino",
    "sg:tags":[
        "hotels",
        "mit",
        "restaurant"
    ],
    "wof:name":"Albergo Fonte Dei Fiori",
    "wof:placetype":"venue"
},
  "geometry": {"coordinates":[8.8753700256,45.9590797424],"type":"Point"}
}