{
  "type": "Feature",
  "properties": {
    "iso:country":"CH",
    "sg:address":"B\u00fcelweg 3",
    "sg:city":"Dussnang",
    "sg:classifiers":[
        {
            "category":"Education",
            "subcategory":"Library",
            "type":"Public Place"
        }
    ],
    "sg:phone":"+41 19326888",
    "sg:postcode":"8374",
    "sg:province":"Thurgau",
    "sg:tags":[
        "u",
        "bibliotheken",
        "archive"
    ],
    "wof:name":"Gemeindebibliothek Gemeinschafts-zentrum",
    "wof:placetype":"venue"
},
  "geometry": {"coordinates":[8.797373,47.322289],"type":"Point"}
}