{
  "type": "Feature",
  "properties": {
    "iso:country":"CH",
    "sg:address":"Aebnit",
    "sg:city":"Unterlangenegg",
    "sg:orig_category":"Bauspenglerei Sanit\u00e4rinstallation",
    "sg:phone":"+41 33 453 14 23",
    "sg:postcode":"3614",
    "sg:province":"Bern",
    "wof:name":"Stucki Haustechnik Gmbh",
    "wof:placetype":"venue"
},
  "geometry": {"coordinates":[7.69871,46.795425],"type":"Point"}
}