{
  "type": "Feature",
  "properties": {
    "iso:country":"CH",
    "sg:address":"Christoph-schnyder-strasse 1b",
    "sg:city":"Sursee",
    "sg:orig_category":"Detailhandel mit Sportartikeln",
    "sg:phone":"+41 41 920 14 04",
    "sg:postcode":"6210",
    "sg:province":"Luzern",
    "wof:name":"Brigitte Ghisoni Hockey Shop 2000",
    "wof:placetype":"venue"
},
  "geometry": {"coordinates":[8.1021928787,47.1717567444],"type":"Point"}
}