{
  "type": "Feature",
  "properties": {
    "iso:country":"CH",
    "sg:address":"Conterserstrasse 98a",
    "sg:city":"K\u00fcblis",
    "sg:classifiers":[
        {
            "category":"Education",
            "subcategory":"Library",
            "type":"Public Place"
        }
    ],
    "sg:phone":"+41 81 332 39 15",
    "sg:postcode":"7240",
    "sg:province":"Graubunden",
    "sg:tags":[
        "u",
        "bibliotheken",
        "archive"
    ],
    "wof:name":"Kreisbibliothek K\u00fcblis",
    "wof:placetype":"venue"
},
  "geometry": {"coordinates":[9.778604,46.914368],"type":"Point"}
}