{
  "type": "Feature",
  "properties": {
    "iso:country":"CH",
    "sg:address":"M\u00fchlebachstrasse 1",
    "sg:city":"Stans",
    "sg:orig_category":"Grosshandel mit landwirtschaftlichen Maschinen U Ger\u00e4ten Herstellung von Metallkonstruktionen",
    "sg:phone":"+41 41 850 42 37",
    "sg:postcode":"6370",
    "sg:province":"Nidwalden",
    "wof:name":"Zimmermann Bruno",
    "wof:placetype":"venue"
},
  "geometry": {"coordinates":[8.433836937,47.0879058838],"type":"Point"}
}