{
  "type": "Feature",
  "properties": {
    "iso:country":"CH",
    "sg:address":"Gewerbestrasse 2 4528 Zuchwil. Postfach",
    "sg:city":"Zuchwil",
    "sg:orig_category":"D\u00e4mmung gegen K\u00e4lte, W\u00e4rme, Schall U Ersch\u00fctterung Herstellung von sonstigen Produkten aus nichtmeta",
    "sg:phone":"+41 32 685 70 10",
    "sg:postcode":"4528",
    "sg:province":"Solothurn",
    "wof:name":"Agi Ag F\u00fcr Isolierungen, Zweigniederlassung Zuchwil",
    "wof:placetype":"venue"
},
  "geometry": {"coordinates":[7.572412014,47.2007865906],"type":"Point"}
}