{
  "type": "Feature",
  "properties": {
    "iso:country":"CH",
    "sg:address":"Motta Viale Giuseppe 28",
    "sg:city":"Bellinzona",
    "sg:orig_category":"Herstellung von elektrischen Lampen U Leuchten",
    "sg:postcode":"6500",
    "sg:province":"Ticino",
    "wof:name":"Modaluce Sa",
    "wof:placetype":"venue"
},
  "geometry": {"coordinates":[9.0223445892,46.2002716064],"type":"Point"}
}