{
  "type": "Feature",
  "properties": {
    "iso:country":"CH",
    "sg:address":"Steinentorstrasse 23 4051 Basel. Postfach",
    "sg:city":"Basel",
    "sg:orig_category":"Herstellung von Duft U K\u00f6rperpflegemitteln",
    "sg:postcode":"4051",
    "sg:province":"Basel-Stadt",
    "wof:name":"Dionea Holding Ag",
    "wof:placetype":"venue"
},
  "geometry": {"coordinates":[8.828494072,47.2284736633],"type":"Point"}
}