{
  "type": "Feature",
  "properties": {
    "iso:country":"CH",
    "sg:address":"Dornacherstrasse 50",
    "sg:city":"Basel",
    "sg:orig_category":"Finanzierungsinstitutionen",
    "sg:phone":"+41 61 270 96 00",
    "sg:postcode":"4053",
    "sg:province":"Basel-Stadt",
    "wof:name":"Stokar + Partner Ag",
    "wof:placetype":"venue"
},
  "geometry": {"coordinates":[7.585958004,47.5445022583],"type":"Point"}
}