{
  "type": "Feature",
  "properties": {
    "iso:country":"CH",
    "sg:address":"Cordon Route Du 5",
    "sg:city":"Nyon",
    "sg:orig_category":"Grosshandel mit Textilien",
    "sg:phone":"+41 22 361 58 87",
    "sg:postcode":"1260",
    "sg:province":"Vaud",
    "wof:name":"Lw Sa",
    "wof:placetype":"venue"
},
  "geometry": {"coordinates":[6.2390799522,46.3823661804],"type":"Point"}
}