{
  "type": "Feature",
  "properties": {
    "iso:country":"CH",
    "sg:address":"Weingartenstrasse 42",
    "sg:city":"Naters",
    "sg:orig_category":"Kauf U Verkauf von Immobilien auf eigene Rechnung",
    "sg:phone":"+41 27 923 78 85",
    "sg:postcode":"3904",
    "sg:province":"Valais",
    "wof:name":"Reruna, Ruppen Ren\u00e9",
    "wof:placetype":"venue"
},
  "geometry": {"coordinates":[8.0039520264,46.3265647888],"type":"Point"}
}