{
  "type": "Feature",
  "properties": {
    "iso:country":"CH",
    "sg:address":"2053",
    "sg:city":"Cernier",
    "sg:orig_category":"Berufsbildende weiterf\u00fchrende Schulen",
    "sg:postcode":"2053",
    "sg:province":"Neuch\u00e2tel",
    "wof:name":"Ecole M\u00e9nag\u00e8re Centre Pr\u00e9grof",
    "wof:placetype":"venue"
},
  "geometry": {"coordinates":[6.90526,47.057339],"type":"Point"}
}