{
  "type": "Feature",
  "properties": {
    "iso:country":"CH",
    "sg:address":"Schulhausstrasse 8",
    "sg:city":"Br\u00fcttisellen",
    "sg:orig_category":"Primarschulen",
    "sg:phone":"+41 18334033",
    "sg:postcode":"8306",
    "sg:province":"Z\u00fcrich",
    "wof:name":"Primarschule Steiacher",
    "wof:placetype":"venue"
},
  "geometry": {"coordinates":[8.6345567703,47.4244041443],"type":"Point"}
}