{
  "type": "Feature",
  "properties": {
    "iso:country":"CH",
    "sg:address":"K\u00fcferstr. 968",
    "sg:city":"Hallau",
    "sg:orig_category":"Pensionskassen",
    "sg:postcode":"8215",
    "sg:province":"Schaffhausen",
    "wof:name":"Personalf\u00fcrsorgestiftung B\u00fcrger Und Altersheim Ammannsegg",
    "wof:placetype":"venue"
},
  "geometry": {"coordinates":[7.5248098373,47.1698112488],"type":"Point"}
}