{
  "type": "Feature",
  "properties": {
    "iso:country":"CH",
    "sg:address":"Pumpwerkstrasse 29",
    "sg:city":"M\u00fcnchenstein",
    "sg:orig_category":"Bau von Strassen, Sportanlagen U Bahnverkehrsstrecken",
    "sg:phone":"+41 61 411 09 30",
    "sg:postcode":"4142",
    "sg:province":"Basel-Landschaft",
    "wof:name":"Frey Ernst Ag",
    "wof:placetype":"venue"
},
  "geometry": {"coordinates":[7.613047,47.515064],"type":"Point"}
}