{
  "type": "Feature",
  "properties": {
    "addr:full":"Via Pretorio 19 Lugano Ticino 6900",
    "addr:housenumber":"19",
    "addr:postcode":"6900",
    "addr:street":"Via Pretorio",
    "iso:country":"CH",
    "sg:address":"Via Pretorio 19",
    "sg:city":"Lugano",
    "sg:orig_category":"Advokaturb\u00fcros",
    "sg:phone":"+41 91 923 77 47",
    "sg:postcode":"6900",
    "sg:province":"Ticino",
    "wof:name":"Dott.giorgio Bernardoni Studio Legale",
    "wof:placetype":"venue"
},
  "geometry": {"coordinates":[8.952888,46.011875],"type":"Point"}
}