{
  "type": "Feature",
  "properties": {
    "iso:country":"CH",
    "sg:address":"Etzbergstrasse 23 8405 Seen. Postfach 272",
    "sg:city":"Seen",
    "sg:orig_category":"Grosshandel mit festen Brennstoffen U Mineral\u00f6lerzeugnissen",
    "sg:phone":"+41 52 235 12 22",
    "sg:postcode":"8405",
    "sg:province":"Z\u00fcrich",
    "wof:name":"K\u00fcbler Heiz\u00f6l Ag",
    "wof:placetype":"venue"
},
  "geometry": {"coordinates":[8.7649030685,47.4910392761],"type":"Point"}
}