{
  "type": "Feature",
  "properties": {
    "iso:country":"CH",
    "sg:address":"Kastanienweg 2",
    "sg:city":"B\u00e4tterkinden",
    "sg:orig_category":"Detailhandel mit M\u00f6beln Innendekorationsateliers",
    "sg:phone":"+41 32 665 11 40",
    "sg:postcode":"3315",
    "sg:province":"Bern",
    "wof:name":"Ren\u00e9 Christen Wohnatelier",
    "wof:placetype":"venue"
},
  "geometry": {"coordinates":[7.5375299454,47.1304512024],"type":"Point"}
}