{
  "type": "Feature",
  "properties": {
    "iso:country":"CH",
    "sg:address":"Pommernstrasse 8",
    "sg:city":"Bubikon",
    "sg:orig_category":"G\u00fcterbef\u00f6rderung im Strassenverkehr",
    "sg:phone":"+41 27 455 24 60",
    "sg:postcode":"8608",
    "sg:province":"Z\u00fcrich",
    "wof:name":"Mohler Transporte Gmbh",
    "wof:placetype":"venue"
},
  "geometry": {"coordinates":[8.8205814362,47.2711143494],"type":"Point"}
}