{
  "type": "Feature",
  "properties": {
    "iso:country":"CH",
    "sg:address":"Sempacherstrasse 15",
    "sg:city":"Z\u00fcrich",
    "sg:orig_category":"Bau U Wohngenossenschaften",
    "sg:postcode":"8032",
    "sg:province":"Z\u00fcrich",
    "wof:name":"Baugenossenschaft St\u00f6ckli",
    "wof:placetype":"venue"
},
  "geometry": {"coordinates":[7.92698,47.136478],"type":"Point"}
}