{
  "type": "Feature",
  "properties": {
    "iso:country":"CH",
    "sg:address":"Chemin De La Gravi\u00e8re 31",
    "sg:city":"Ch\u00eane-bourg",
    "sg:orig_category":"Unclassifiable Establishments",
    "sg:phone":"+41 22 349 27 42",
    "sg:postcode":"1225",
    "sg:province":"Gen\u00e8ve",
    "wof:name":"Ami, Gander",
    "wof:placetype":"venue"
},
  "geometry": {"coordinates":[6.2017598152,46.1992454529],"type":"Point"}
}