{
  "type": "Feature",
  "properties": {
    "addr:full":"Bahnhofplatz 4 Sarnen Obwalden 6060",
    "addr:housenumber":"4",
    "addr:postcode":"6060",
    "addr:street":"Bahnhofplatz",
    "iso:country":"CH",
    "sg:address":"Bahnhofplatz 4",
    "sg:city":"Sarnen",
    "sg:classifiers":[
        {
            "category":"Manufacturing",
            "subcategory":"Furniture",
            "type":"Manufacturing & Wholesale Goods"
        }
    ],
    "sg:phone":"+41 41 660 64 72",
    "sg:postcode":"6060",
    "sg:province":"Obwalden",
    "sg:tags":[
        "children's"
    ],
    "wof:name":"A. Rosenberg & Co",
    "wof:placetype":"venue"
},
  "geometry": {"coordinates":[8.247139,46.894855],"type":"Point"}
}