{
  "type": "Feature",
  "properties": {
    "iso:country":"CH",
    "sg:address":"Laubigartenweg 23",
    "sg:city":"Hochwald",
    "sg:orig_category":"Detailhandel mit Antiquit\u00e4ten M\u00f6belveredelung U restaurierung",
    "sg:phone":"+41 55 246 34 46",
    "sg:postcode":"4146",
    "sg:province":"Solothurn",
    "wof:name":"Peter Pfister Antiquit\u00e4ten",
    "wof:placetype":"venue"
},
  "geometry": {"coordinates":[8.9413,47.28841],"type":"Point"}
}