{
  "type": "Feature",
  "properties": {
    "iso:country":"CH",
    "sg:address":"Route De Juvigny 9",
    "sg:city":"Jussy",
    "sg:orig_category":"Malerei Tapeziererei",
    "sg:phone":"+41 22 759 06 06",
    "sg:postcode":"1254",
    "sg:province":"Gen\u00e8ve",
    "wof:name":"Gremion & Decouvette Peinture Papiers Peints",
    "wof:placetype":"venue"
},
  "geometry": {"coordinates":[6.2663421631,46.2344055176],"type":"Point"}
}