{
  "type": "Feature",
  "properties": {
    "iso:country":"CH",
    "sg:address":"Neumaadstrasse 3",
    "sg:city":"Diepoldsau",
    "sg:orig_category":"Unternehmensberatung",
    "sg:postcode":"9444",
    "sg:province":"St. Gallen",
    "wof:name":"Schegg Markus E. Management Consulting & Development",
    "wof:placetype":"venue"
},
  "geometry": {"coordinates":[9.6507368088,47.382232666],"type":"Point"}
}