{
  "type": "Feature",
  "properties": {
    "iso:country":"CH",
    "sg:address":"Seestrasse 36",
    "sg:city":"Unterseen",
    "sg:classifiers":[
        {
            "category":"Autos & Motor Vehicles",
            "subcategory":"Auto Supplies",
            "type":"Retail Goods"
        }
    ],
    "sg:phone":"+41 32 822 71 71",
    "sg:postcode":"3800",
    "sg:province":"Bern",
    "sg:tags":[
        "car",
        "brake"
    ],
    "wof:name":"Shaper Wheels Schweiz",
    "wof:placetype":"venue"
},
  "geometry": {"coordinates":[7.844522953,46.6833953857],"type":"Point"}
}