{
  "type": "Feature",
  "properties": {
    "iso:country":"CH",
    "sg:address":"Allmendstrasse 2a",
    "sg:city":"Bellach",
    "sg:orig_category":"G\u00fcterbef\u00f6rderung im Strassenverkehr",
    "sg:phone":"+41 32 623 60 58",
    "sg:postcode":"4512",
    "sg:province":"Solothurn",
    "wof:name":"Ruedi Walker Walker's Team",
    "wof:placetype":"venue"
},
  "geometry": {"coordinates":[7.4988460541,47.2076950073],"type":"Point"}
}