{
  "type": "Feature",
  "properties": {
    "iso:country":"CH",
    "sg:address":"Alte Winterthurerstrasse 37",
    "sg:city":"N\u00fcrensdorf",
    "sg:orig_category":"Softwareentwicklung U beratung Unternehmensberatung",
    "sg:phone":"+41 71 390 02 67",
    "sg:postcode":"8309",
    "sg:province":"Z\u00fcrich",
    "wof:name":"Creditlex Gmbh Wirtschaftsausk\u00fcnfte Usw.; Produktion U. Verkauf",
    "wof:placetype":"venue"
},
  "geometry": {"coordinates":[9.1840600967,47.4143104553],"type":"Point"}
}