{
  "type": "Feature",
  "properties": {
    "iso:country":"CH",
    "sg:address":"Corso San Gottardo 73",
    "sg:city":"Chiasso",
    "sg:orig_category":"Autotransporte international",
    "sg:phone":"+41 91 695 73 73",
    "sg:postcode":"6830",
    "sg:province":"Ticino",
    "wof:name":"Castelletti Sa Spedizioni Internazionali",
    "wof:placetype":"venue"
},
  "geometry": {"coordinates":[9.028121,45.835003],"type":"Point"}
}