{
  "type": "Feature",
  "properties": {
    "addr:full":"Via Trevano 75 Lugano Ticino 6900",
    "addr:housenumber":"75",
    "addr:postcode":"6900",
    "addr:street":"Via Trevano",
    "iso:country":"CH",
    "sg:address":"Via Trevano 75",
    "sg:city":"Lugano",
    "sg:orig_category":"Caterer Detailhandel mit Brot, Back U S\u00fcsswaren",
    "sg:phone":"+41 91 972 11 05",
    "sg:postcode":"6900",
    "sg:province":"Ticino",
    "wof:name":"Pizzamania Sa",
    "wof:placetype":"venue"
},
  "geometry": {"coordinates":[8.957273,46.019459],"type":"Point"}
}