{
  "type": "Feature",
  "properties": {
    "iso:country":"CH",
    "sg:address":"3718",
    "sg:city":"Kandersteg",
    "sg:orig_category":"Allgemeinbildende weiterf\u00fchrende Schulen",
    "sg:postcode":"3718",
    "sg:province":"Bern",
    "wof:name":"Institut Kandersteg, Dr. J. Z\u00fcger",
    "wof:placetype":"venue"
},
  "geometry": {"coordinates":[7.673047,46.494984],"type":"Point"}
}