{
  "type": "Feature",
  "properties": {
    "iso:country":"CH",
    "sg:address":"Ortb\u00fchlweg 105b",
    "sg:city":"Steffisburg",
    "sg:orig_category":"Werbeagenturen",
    "sg:phone":"+41 33 437 77 22",
    "sg:postcode":"3613",
    "sg:province":"Bern",
    "wof:name":"Bruno Mumenthaler Catcom Werbung",
    "wof:placetype":"venue"
},
  "geometry": {"coordinates":[7.6145458221,46.7799186707],"type":"Point"}
}