{
  "type": "Feature",
  "properties": {
    "iso:country":"CH",
    "sg:address":"Avenue Bertrand 4",
    "sg:city":"Gen\u00e8ve",
    "sg:orig_category":"W\u00e4scherei U chemische Reinigung",
    "sg:phone":"+41 22 346 61 50",
    "sg:postcode":"1206",
    "sg:province":"Gen\u00e8ve",
    "wof:name":"Netteco B Champel Sa",
    "wof:placetype":"venue"
},
  "geometry": {"coordinates":[6.1537899971,46.1919746399],"type":"Point"}
}