{
  "type": "Feature",
  "properties": {
    "iso:country":"CH",
    "sg:address":"Via Galli 4",
    "sg:city":"Locarno",
    "sg:orig_category":"Ger\u00fcstbau Sonstiger spezialisierter Hoch U Tiefbau",
    "sg:phone":"+41 31 952 75 15",
    "sg:postcode":"6600",
    "sg:province":"Ticino",
    "wof:name":"Tempo Ger\u00fcst Und Hebetechnik H. Br\u00f6nnimann",
    "wof:placetype":"venue"
},
  "geometry": {"coordinates":[7.5017237663,46.9257011414],"type":"Point"}
}