{
  "type": "Feature",
  "properties": {
    "iso:country":"CH",
    "sg:address":"Rebbergstrasse 20",
    "sg:city":"Wollerau",
    "sg:orig_category":"Grosshandel mit B\u00fcromaschinen Grosshandel mit Datenverarbeitungsger\u00e4ten",
    "sg:phone":"+41 16873303",
    "sg:postcode":"8832",
    "sg:province":"Schwyz",
    "wof:name":"Mit Meyer Information Technology Ag",
    "wof:placetype":"venue"
},
  "geometry": {"coordinates":[8.7213354111,47.1976547241],"type":"Point"}
}