{
  "type": "Feature",
  "properties": {
    "iso:country":"CH",
    "sg:address":"Stradun",
    "sg:city":"Scuol",
    "sg:orig_category":"Detailhandel mit Brot, Back U S\u00fcsswaren",
    "sg:phone":"+41 79 406 73 83",
    "sg:postcode":"7550",
    "sg:province":"Graubunden",
    "wof:name":"Furnaria Pastizaria Benderer Gmbh",
    "wof:placetype":"venue"
},
  "geometry": {"coordinates":[10.293681,46.794941],"type":"Point"}
}