{
  "type": "Feature",
  "properties": {
    "addr:full":"Fl\u00fchg. 80 Z\u00fcrich Z\u00fcrich 8008",
    "addr:housenumber":"80",
    "addr:postcode":"8008",
    "addr:street":"Fluehg.",
    "iso:country":"CH",
    "sg:address":"Fl\u00fchg. 80",
    "sg:city":"Z\u00fcrich",
    "sg:classifiers":[
        {
            "category":"Professional",
            "subcategory":"Business Services",
            "type":"Services"
        }
    ],
    "sg:phone":"+41 4113816065",
    "sg:postcode":"8008",
    "sg:province":"Z\u00fcrich",
    "sg:tags":[
        "body",
        "advice"
    ],
    "wof:name":"Jugendheim Schenkung Dapples",
    "wof:placetype":"venue"
},
  "geometry": {"coordinates":[8.53955,47.37706],"type":"Point"}
}