{
  "type": "Feature",
  "properties": {
    "iso:country":"CH",
    "sg:address":"Goldbrunnenstrasse 151 8055 Z\u00fcrich. Postfach",
    "sg:city":"Z\u00fcrich",
    "sg:orig_category":"Herstellung von sonstigen Metallwaren",
    "sg:phone":"+41 14620455",
    "sg:postcode":"8055",
    "sg:province":"Z\u00fcrich",
    "wof:name":"Ernst Willimann Stempel & Gravuren",
    "wof:placetype":"venue"
},
  "geometry": {"coordinates":[8.5105028152,47.3718910217],"type":"Point"}
}