{
  "type": "Feature",
  "properties": {
    "iso:country":"CH",
    "sg:address":"Vieux-lully 20",
    "sg:city":"Bernex",
    "sg:classifiers":[
        {
            "category":"Restaurant",
            "type":"Food & Drink"
        }
    ],
    "sg:phone":"+41 27 771 25 24",
    "sg:postcode":"1233",
    "sg:province":"Gen\u00e8ve",
    "wof:name":"Restaurant Chez Dany",
    "wof:placetype":"venue"
},
  "geometry": {"coordinates":[7.2332568169,46.0971870422],"type":"Point"}
}