{
  "type": "Feature",
  "properties": {
    "iso:country":"CH",
    "sg:address":"Im Weingarten 10",
    "sg:city":"Kaltenbach",
    "sg:orig_category":"Technische B\u00fcros Apparatebau",
    "sg:phone":"+41 52 741 46 40",
    "sg:postcode":"8259",
    "sg:province":"Thurgau",
    "wof:name":"Kasag Export Ag",
    "wof:placetype":"venue"
},
  "geometry": {"coordinates":[8.8405895233,47.6499214172],"type":"Point"}
}