{
  "type": "Feature",
  "properties": {
    "iso:country":"CH",
    "sg:address":"L\u00f6wenstrasse 28",
    "sg:city":"Dietikon",
    "sg:orig_category":"Detailhandel mit Uhren U Schmuck",
    "sg:phone":"+41 41 410 69 68",
    "sg:postcode":"8953",
    "sg:province":"Z\u00fcrich",
    "wof:name":"Schmuck Zum Hof Dorothe Felder",
    "wof:placetype":"venue"
},
  "geometry": {"coordinates":[8.3129863739,47.0553703308],"type":"Point"}
}