{
  "type": "Feature",
  "properties": {
    "iso:country":"CH",
    "sg:address":"1433",
    "sg:city":"Suchy",
    "sg:orig_category":"Sportvereine Sch\u00fctzen",
    "sg:postcode":"1433",
    "sg:province":"Vaud",
    "wof:name":"St\u00e9 De Tir Armes De Guerre",
    "wof:placetype":"venue"
},
  "geometry": {"coordinates":[6.6006550789,46.7243041992],"type":"Point"}
}