{
  "type": "Feature",
  "properties": {
    "iso:country":"CH",
    "sg:address":"Rue Marc Morand 5",
    "sg:city":"Martigny",
    "sg:classifiers":[
        {
            "category":"Restaurant",
            "type":"Food & Drink"
        }
    ],
    "sg:phone":"+41 27 722 22 95",
    "sg:postcode":"1920",
    "sg:province":"Valais",
    "wof:name":"Restaurant Tamburin",
    "wof:placetype":"venue"
},
  "geometry": {"coordinates":[7.072909832,46.1019973755],"type":"Point"}
}