{
  "type": "Feature",
  "properties": {
    "iso:country":"CH",
    "sg:address":"Poststrasse 13 9410 Heiden. Postfach 36",
    "sg:city":"Heiden",
    "sg:orig_category":"Schl\u00fcsselservice",
    "sg:phone":"+41 61 641 55 55",
    "sg:postcode":"9410",
    "sg:province":"Appenzell Ausserrhoden",
    "wof:name":"Fritz Ackermann Schloss & Schl\u00fcssel",
    "wof:placetype":"venue"
},
  "geometry": {"coordinates":[7.6556611061,47.5844078064],"type":"Point"}
}