{
  "type": "Feature",
  "properties": {
    "iso:country":"CH",
    "sg:address":"Schlossbergstrasse 15",
    "sg:city":"Zollikon",
    "sg:orig_category":"Fachdetailhandel in Verkaufsr\u00e4umen",
    "sg:phone":"+41 13914322",
    "sg:postcode":"8702",
    "sg:province":"Z\u00fcrich",
    "wof:name":"Montres Itraco Cie Sa",
    "wof:placetype":"venue"
},
  "geometry": {"coordinates":[8.5808887482,47.3444900513],"type":"Point"}
}