{
  "type": "Feature",
  "properties": {
    "iso:country":"CH",
    "sg:address":"Rigistrasse 31",
    "sg:city":"Z\u00fcrich",
    "sg:orig_category":"Unclassifiable Establishments",
    "sg:postcode":"8006",
    "sg:province":"Z\u00fcrich",
    "wof:name":"Yourpage! Derrer Michael",
    "wof:placetype":"venue"
},
  "geometry": {"coordinates":[8.5499172211,47.3850631714],"type":"Point"}
}