{
  "type": "Feature",
  "properties": {
    "iso:country":"CH",
    "sg:address":"Avenue Du Midi 8 1950 Sion Case Postale 491",
    "sg:city":"Sion",
    "sg:orig_category":"Reiseb\u00fcros",
    "sg:phone":"+41 27 322 93 27",
    "sg:postcode":"1951",
    "sg:province":"Valais",
    "wof:name":"Hotelplan Internationale Reiseorganisation Ag",
    "wof:placetype":"venue"
},
  "geometry": {"coordinates":[7.3589577675,46.2306518555],"type":"Point"}
}