{
  "type": "Feature",
  "properties": {
    "iso:country":"CH",
    "sg:address":"Via Alle Cantine Di Cima",
    "sg:city":"Melide",
    "sg:orig_category":"Sportschulen Ski-& Snowboardschulen",
    "sg:phone":"+41 91 832 13 44",
    "sg:postcode":"6815",
    "sg:province":"Ticino",
    "wof:name":"Scuola Svizzera Di Sci",
    "wof:placetype":"venue"
},
  "geometry": {"coordinates":[9.1906404495,46.4630584717],"type":"Point"}
}