{
  "type": "Feature",
  "properties": {
    "iso:country":"CH",
    "sg:address":"Eggh\u00f6lzlistrasse 3",
    "sg:city":"Bern",
    "sg:orig_category":"P\u00e9dicure",
    "sg:phone":"+41 55 210 58 16",
    "sg:postcode":"3006",
    "sg:province":"Bern",
    "wof:name":"Ursula Brunner P\u00e9dicure",
    "wof:placetype":"venue"
},
  "geometry": {"coordinates":[8.8284740448,47.2269630432],"type":"Point"}
}