{
  "type": "Feature",
  "properties": {
    "iso:country":"CH",
    "sg:address":"Avenue Des Glaries",
    "sg:city":"Aigle",
    "sg:orig_category":"Campingpl\u00e4tze Detailhandel mit Zeitungen U Zeitschriften Kioske",
    "sg:phone":"+41 24 466 26 60",
    "sg:postcode":"1860",
    "sg:province":"Vaud",
    "wof:name":"Camping Du Tcs",
    "wof:placetype":"venue"
},
  "geometry": {"coordinates":[6.966148,46.321533],"type":"Point"}
}