{
  "type": "Feature",
  "properties": {
    "iso:country":"CH",
    "sg:address":"Rue Marc Morand 9",
    "sg:city":"Martigny",
    "sg:orig_category":"Detailhandel mit Parf\u00fcmerieartikeln U K\u00f6rperpflegemitteln",
    "sg:postcode":"1920",
    "sg:province":"Valais",
    "wof:name":"Nefertoum Parfum Maria Dini Et Jeanine Delasoie",
    "wof:placetype":"venue"
},
  "geometry": {"coordinates":[7.0724830627,46.1027793884],"type":"Point"}
}