{
  "type": "Feature",
  "properties": {
    "iso:country":"CH",
    "sg:address":"Kurparkstrasse 15",
    "sg:city":"Leukerbad",
    "sg:orig_category":"HOTELS: MIT RESTAURANT Kongress- and Tagungshotels mit Restaurant",
    "sg:phone":"+41 81 415 66 50",
    "sg:postcode":"3954",
    "sg:province":"Valais",
    "wof:name":"Hotel Davoserhof",
    "wof:placetype":"venue"
},
  "geometry": {"coordinates":[9.8216171265,46.7931060791],"type":"Point"}
}