{
  "type": "Feature",
  "properties": {
    "iso:country":"CH",
    "sg:address":"Rue Des C\u00e8dres 8",
    "sg:city":"Sion",
    "sg:classifiers":[
        {
            "category":"Banks & Credit Unions",
            "subcategory":"Bank",
            "type":"Services"
        }
    ],
    "sg:phone":"+41 27 324 66 71",
    "sg:postcode":"1950",
    "sg:province":"Valais",
    "wof:name":"Nationale Suisse",
    "wof:placetype":"venue"
},
  "geometry": {"coordinates":[7.360095,46.230114],"type":"Point"}
}