{
  "type": "Feature",
  "properties": {
    "iso:country":"CH",
    "sg:address":"Etzelstrasse 7",
    "sg:city":"Z\u00fcrich",
    "sg:orig_category":"Sonstiger Grosshandel",
    "sg:postcode":"8038",
    "sg:province":"Z\u00fcrich",
    "wof:name":"M. Karim Import - Export",
    "wof:placetype":"venue"
},
  "geometry": {"coordinates":[8.5302791595,47.3445854187],"type":"Point"}
}