{
  "type": "Feature",
  "properties": {
    "iso:country":"CH",
    "sg:address":"Hofackerstrasse 154",
    "sg:city":"Wilchingen",
    "sg:orig_category":"Physiotherapie",
    "sg:phone":"+41 52 681 26 19",
    "sg:postcode":"8217",
    "sg:province":"Schaffhausen",
    "wof:name":"K\u00e4thi Hedinger Physiotherapie",
    "wof:placetype":"venue"
},
  "geometry": {"coordinates":[8.4663734436,47.6682243347],"type":"Point"}
}