{
  "type": "Feature",
  "properties": {
    "iso:country":"CH",
    "sg:address":"Waisenhausplatz 17 3011 Bern. Postfach",
    "sg:city":"Bern",
    "sg:orig_category":"RESTAURANTS: TEA-ROOMS",
    "sg:postcode":"3005",
    "sg:province":"Bern",
    "wof:name":"Wellig & Kaufmann Rest. U. Tea-room Mirabeau",
    "wof:placetype":"venue"
},
  "geometry": {"coordinates":[7.4437098503,46.948638916],"type":"Point"}
}