{
  "type": "Feature",
  "properties": {
    "iso:country":"CH",
    "sg:address":"Mittlere Schwandenstrasse 4",
    "sg:city":"Richterswil",
    "sg:orig_category":"Vereine Harmonika and Akkordeon",
    "sg:phone":"+41 17848736",
    "sg:postcode":"8805",
    "sg:province":"Z\u00fcrich",
    "wof:name":"Harmonie Club",
    "wof:placetype":"venue"
},
  "geometry": {"coordinates":[8.6885900497,47.2033195496],"type":"Point"}
}