{
  "type": "Feature",
  "properties": {
    "iso:country":"CH",
    "sg:address":"Gurnigelstrasse 48 2560 Nidau Case Postale 1131",
    "sg:city":"Biel/bienne",
    "sg:orig_category":"Mechanik Mechanische Werkst\u00e4tten",
    "sg:phone":"+41 32 365 51 31",
    "sg:postcode":"2501",
    "sg:province":"Bern",
    "wof:name":"Aubert Marcel Contr\u00f4le D'installations \u00e9lectriques Int\u00e9rieurs",
    "wof:placetype":"venue"
},
  "geometry": {"coordinates":[7.2458019257,47.1292724609],"type":"Point"}
}