{
  "type": "Feature",
  "properties": {
    "addr:full":"T\u00f6sstalstrasse 70 Turbenthal Z\u00fcrich 8488",
    "addr:housenumber":"70",
    "addr:postcode":"8488",
    "addr:street":"Toesstalstrasse",
    "iso:country":"CH",
    "sg:address":"T\u00f6sstalstrasse 70",
    "sg:city":"Turbenthal",
    "sg:orig_category":"Detailhandel mit B\u00fcchern, Zeitungen, Schreib U Papeteriewaren",
    "sg:phone":"+41 52 394 28 48",
    "sg:postcode":"8488",
    "sg:province":"Z\u00fcrich",
    "wof:name":"Papeterie Schalcher",
    "wof:placetype":"venue"
},
  "geometry": {"coordinates":[8.846439,47.436951],"type":"Point"}
}