{
  "type": "Feature",
  "properties": {
    "iso:country":"CH",
    "sg:address":"Oberalpstrasse 16",
    "sg:city":"Chur",
    "sg:orig_category":"Sonstiges Versicherungsgewerbe",
    "sg:phone":"+41 81 286 77 77",
    "sg:postcode":"7000",
    "sg:province":"Graubunden",
    "wof:name":"Hudson Sky Companie Sa",
    "wof:placetype":"venue"
},
  "geometry": {"coordinates":[9.5251169205,46.8546218872],"type":"Point"}
}