{
  "type": "Feature",
  "properties": {
    "iso:country":"CH",
    "sg:address":"2875",
    "sg:city":"Montfaucon",
    "sg:orig_category":"G\u00fcterbef\u00f6rderung im Strassenverkehr",
    "sg:postcode":"2875",
    "sg:province":"Jura",
    "wof:name":"Jean Transports Sa",
    "wof:placetype":"venue"
},
  "geometry": {"coordinates":[7.4068250656,46.2767829895],"type":"Point"}
}