{
  "type": "Feature",
  "properties": {
    "iso:country":"CH",
    "sg:address":"Br\u00e4chenstrasse 14",
    "sg:city":"Oberiberg",
    "sg:classifiers":[
        {
            "category":"Travel",
            "subcategory":"Hotels & Motels",
            "type":"Entertainment"
        }
    ],
    "sg:postcode":"8843",
    "sg:province":"Schwyz",
    "sg:tags":[
        "hotels",
        "mit",
        "restaurant"
    ],
    "wof:name":"Hogatour Consulting Gmbh",
    "wof:placetype":"venue"
},
  "geometry": {"coordinates":[8.774269104,47.0377426147],"type":"Point"}
}