{
  "type": "Feature",
  "properties": {
    "iso:country":"CH",
    "sg:address":"Ankerstrasse 9",
    "sg:city":"Rorschach",
    "sg:orig_category":"Detailhandel mit Schuhen",
    "sg:phone":"+41 71 841 35 70",
    "sg:postcode":"9400",
    "sg:province":"St. Gallen",
    "wof:name":"Karl V\u00f6gele Ag",
    "wof:placetype":"venue"
},
  "geometry": {"coordinates":[9.4912023544,47.4783668518],"type":"Point"}
}