{
  "type": "Feature",
  "properties": {
    "iso:country":"CH",
    "sg:address":"Laubbach",
    "sg:city":"Waldkirch",
    "sg:orig_category":"Verarbeitung von Milch Verwertung von Milch",
    "sg:phone":"+41 71 433 11 79",
    "sg:postcode":"9205",
    "sg:province":"St. Gallen",
    "wof:name":"Karl Risi K\u00e4serei",
    "wof:placetype":"venue"
},
  "geometry": {"coordinates":[9.2859354019,47.4690666199],"type":"Point"}
}