{
  "type": "Feature",
  "properties": {
    "iso:country":"CH",
    "sg:address":"Schmidgasse 4",
    "sg:city":"Zug",
    "sg:orig_category":"Grosshandel mit pharmazeutischen Erzeugnissen, medizinischen U orthop\u00e4dischen Artikeln",
    "sg:postcode":"6300",
    "sg:province":"Zug",
    "wof:name":"Instruments Dentaires Sa",
    "wof:placetype":"venue"
},
  "geometry": {"coordinates":[6.8299050331,47.102809906],"type":"Point"}
}