{
  "type": "Feature",
  "properties": {
    "addr:full":"Chemin Rieu 10 Gen\u00e8ve Gen\u00e8ve 1208",
    "addr:housenumber":"10",
    "addr:postcode":"1208",
    "addr:street":"Chemin Rieu",
    "iso:country":"CH",
    "sg:address":"Chemin Rieu 10",
    "sg:city":"Gen\u00e8ve",
    "sg:orig_category":"Architekturb\u00fcros",
    "sg:phone":"+41 22 700 10 13",
    "sg:postcode":"1208",
    "sg:province":"Gen\u00e8ve",
    "wof:name":"Thomas Nadas Bureau D'architecture",
    "wof:placetype":"venue"
},
  "geometry": {"coordinates":[6.165257,46.195267],"type":"Point"}
}