{
  "type": "Feature",
  "properties": {
    "iso:country":"CH",
    "sg:address":"Wiesenstrasse 22",
    "sg:city":"Oberuzwil",
    "sg:orig_category":"Non-Classified Establishments",
    "sg:postcode":"9242",
    "sg:province":"St. Gallen",
    "wof:name":"Qualifact Ag",
    "wof:placetype":"venue"
},
  "geometry": {"coordinates":[9.1300821304,47.4321975708],"type":"Point"}
}