{
  "type": "Feature",
  "properties": {
    "iso:country":"CH",
    "sg:address":"Rohrwis 13 8852 Altendorf. Postfach",
    "sg:city":"Altendorf",
    "sg:orig_category":"Kauf U Verkauf von Immobilien auf eigene Rechnung",
    "sg:phone":"+41 79 518 30 22",
    "sg:postcode":"8852",
    "sg:province":"Schwyz",
    "wof:name":"Immopoint Gmbh Liegenschaften; Bau, Erwerb, Verwalten Usw",
    "wof:placetype":"venue"
},
  "geometry": {"coordinates":[8.8471012115,47.1854972839],"type":"Point"}
}