{
  "type": "Feature",
  "properties": {
    "iso:country":"CH",
    "sg:address":"Hirschenweg 6 9434 Au Sg. Postfach",
    "sg:city":"Heerbrugg",
    "sg:orig_category":"Erbringung von Dienstleistungen f\u00fcr Unternehmen",
    "sg:postcode":"9435",
    "sg:province":"St. Gallen",
    "wof:name":"Grafik Frei Bruno",
    "wof:placetype":"venue"
},
  "geometry": {"coordinates":[9.6351919174,47.4310073853],"type":"Point"}
}