{
  "type": "Feature",
  "properties": {
    "iso:country":"CH",
    "sg:address":"Casa Scala",
    "sg:city":"Carona",
    "sg:orig_category":"Unclassifiable Establishments",
    "sg:phone":"+41 31 331 36 75",
    "sg:postcode":"6914",
    "sg:province":"Ticino",
    "wof:name":"Traccia Film Di Lelarge Halperin Christiane",
    "wof:placetype":"venue"
},
  "geometry": {"coordinates":[8.9357252121,45.9573364258],"type":"Point"}
}