{
  "type": "Feature",
  "properties": {
    "iso:country":"CH",
    "sg:address":"Claramattweg 1 4057 Basel. Postfach",
    "sg:city":"Rorschach",
    "sg:orig_category":"Unclassifiable Establishments",
    "sg:postcode":"9400",
    "sg:province":"St. Gallen",
    "wof:name":"Cr\u00e9ole-reisen Ag",
    "wof:placetype":"venue"
},
  "geometry": {"coordinates":[7.5951390266,47.5629920959],"type":"Point"}
}