{
  "type": "Feature",
  "properties": {
    "iso:country":"CH",
    "sg:address":"Hoffeldstrasse 23 9114 Hoffeld. Postfach",
    "sg:city":"Hoffeld",
    "sg:orig_category":"Elektroinstallation",
    "sg:postcode":"9114",
    "sg:province":"St. Gallen",
    "wof:name":"Pfund Sat-electronics",
    "wof:placetype":"venue"
},
  "geometry": {"coordinates":[9.1708498001,47.3631286621],"type":"Point"}
}