{
  "type": "Feature",
  "properties": {
    "iso:country":"CH",
    "sg:address":"Village Rue Du 13 1214 Vernier. Postfach",
    "sg:city":"Vernier",
    "sg:orig_category":"Detailhandel mit Waren verschiedener Art, Hauptrichtung Nahrungsmittel",
    "sg:phone":"+41 22 341 56 02",
    "sg:postcode":"1214",
    "sg:province":"Gen\u00e8ve",
    "wof:name":"Help For Hyperactivity, Dominin Ulisse Produits Alimentaires Par Correspondance; Vente",
    "wof:placetype":"venue"
},
  "geometry": {"coordinates":[6.0838780403,46.2147216797],"type":"Point"}
}