{
  "type": "Feature",
  "properties": {
    "iso:country":"CH",
    "sg:address":"Grossackerstrasse 45",
    "sg:city":"Z\u00fcrich",
    "sg:orig_category":"Grosshandel mit sonstigen Gebrauchs U Verbrauchsg\u00fctern",
    "sg:phone":"+41 18699150",
    "sg:postcode":"8041",
    "sg:province":"Z\u00fcrich",
    "wof:name":"Brangs + Heinrich Ag",
    "wof:placetype":"venue"
},
  "geometry": {"coordinates":[8.5015201569,47.6061706543],"type":"Point"}
}