{
  "type": "Feature",
  "properties": {
    "iso:country":"CH",
    "sg:address":"4316",
    "sg:city":"Hellikon",
    "sg:orig_category":"Landesverteidigung, Sozialversicherung \u00d6ffentliche Verwaltung",
    "sg:phone":"+41 61 871 07 55",
    "sg:postcode":"4316",
    "sg:province":"Aargau",
    "wof:name":"Zivilschutzstelle Hellikon",
    "wof:placetype":"venue"
},
  "geometry": {"coordinates":[7.9253678322,47.5085830688],"type":"Point"}
}