{
  "type": "Feature",
  "properties": {
    "iso:country":"CH",
    "sg:address":"Industriestrasse 5",
    "sg:city":"Egerkingen",
    "sg:orig_category":"G\u00fcterbef\u00f6rderung im Strassenverkehr",
    "sg:phone":"+41 62 398 43 73",
    "sg:postcode":"4622",
    "sg:province":"Solothurn",
    "wof:name":"Gilbert Leclerc Transporte",
    "wof:placetype":"venue"
},
  "geometry": {"coordinates":[7.7948098183,47.3161468506],"type":"Point"}
}