{
  "type": "Feature",
  "properties": {
    "iso:country":"CH",
    "sg:address":"Via Bora Da Besa",
    "sg:city":"Gentilino",
    "sg:classifiers":[
        {
            "category":"Bars & Pubs",
            "type":"Food & Drink"
        }
    ],
    "sg:phone":"+41 91 994 91 89",
    "sg:postcode":"6925",
    "sg:province":"Ticino",
    "sg:tags":[
        "restaurant"
    ],
    "wof:name":"Ristorante-bar Bora Da Besa",
    "wof:placetype":"venue"
},
  "geometry": {"coordinates":[8.930583,45.990791],"type":"Point"}
}