{
  "type": "Feature",
  "properties": {
    "iso:country":"CH",
    "sg:address":"Kempttalstrasse 68",
    "sg:city":"Fehraltorf",
    "sg:orig_category":"Interessenvertretungen",
    "sg:postcode":"8320",
    "sg:province":"Z\u00fcrich",
    "wof:name":"Bachofner Walter-stiftung",
    "wof:placetype":"venue"
},
  "geometry": {"coordinates":[8.7550230026,47.3859138489],"type":"Point"}
}