{
  "type": "Feature",
  "properties": {
    "iso:country":"CH",
    "sg:address":"Kramgasse 19",
    "sg:city":"Bern",
    "sg:orig_category":"Detailhandel mit Uhren U Schmuck Fachdetailhandel in Verkaufsr\u00e4umen",
    "sg:phone":"+41 31 318 01 18",
    "sg:postcode":"3011",
    "sg:province":"Bern",
    "wof:name":"Al-yafei Uhrsachen Gmbh",
    "wof:placetype":"venue"
},
  "geometry": {"coordinates":[7.4513440132,46.9478492737],"type":"Point"}
}