{
  "type": "Feature",
  "properties": {
    "iso:country":"CH",
    "sg:address":"Montchoisy Rue De 2 1207 Gen\u00e8ve. Postfach",
    "sg:city":"Gen\u00e8ve",
    "sg:orig_category":"Fahrschulen, Flugschulen",
    "sg:postcode":"1207",
    "sg:province":"Gen\u00e8ve",
    "wof:name":"Abt Auto-\u00e9cole, B\u00e9at Trinkler",
    "wof:placetype":"venue"
},
  "geometry": {"coordinates":[6.1589131355,46.2024078369],"type":"Point"}
}