{
  "type": "Feature",
  "properties": {
    "iso:country":"CH",
    "sg:address":"Tannerie 1",
    "sg:city":"Yvonand",
    "sg:orig_category":"Elektroinstallation",
    "sg:phone":"+41 24 430 10 89",
    "sg:postcode":"1462",
    "sg:province":"Vaud",
    "wof:name":"Oguey Fran\u00e7ois",
    "wof:placetype":"venue"
},
  "geometry": {"coordinates":[6.7453989983,46.8000679016],"type":"Point"}
}