{
  "type": "Feature",
  "properties": {
    "addr:full":"Sennweidstrasse 1a Bubikon Z\u00fcrich 8608",
    "addr:housenumber":"1a",
    "addr:postcode":"8608",
    "addr:street":"Sennweidstrasse",
    "iso:country":"CH",
    "sg:address":"Sennweidstrasse 1a",
    "sg:city":"Bubikon",
    "sg:orig_category":"Allgemeiner Hoch U Tiefbau Innenarchitekturb\u00fcros",
    "sg:phone":"+41 55 243 43 00",
    "sg:postcode":"8608",
    "sg:province":"Z\u00fcrich",
    "wof:name":"Keller Bachmann & Partner Ag Hoch- U. Innenausbau; Beratung, Planung Usw",
    "wof:placetype":"venue"
},
  "geometry": {"coordinates":[8.82279,47.271988],"type":"Point"}
}