{
  "type": "Feature",
  "properties": {
    "iso:country":"CH",
    "sg:address":"Oberhofen",
    "sg:city":"Turbenthal",
    "sg:orig_category":"Sportvereine Sch\u00fctzen",
    "sg:phone":"+41 52 385 32 63",
    "sg:postcode":"8488",
    "sg:province":"Z\u00fcrich",
    "wof:name":"Sch\u00fctzengesellschaft Neubrunn",
    "wof:placetype":"venue"
},
  "geometry": {"coordinates":[8.8794298172,47.4343910217],"type":"Point"}
}