{
  "type": "Feature",
  "properties": {
    "iso:country":"CH",
    "sg:address":"Hornbachstrasse 64 8008 Z\u00fcrich. Postfach",
    "sg:city":"Z\u00fcrich",
    "sg:orig_category":"Sanit\u00e4rinstallation Zimmerei, Dachdeckerei, Bauspenglerei U Abdichtung",
    "sg:phone":"+41 14224354",
    "sg:postcode":"8008",
    "sg:province":"Z\u00fcrich",
    "wof:name":"Gisiger Spenglerei, Inhaber Gisiger Rudolf Spenglerei, Sanit\u00e4re Installationen",
    "wof:placetype":"venue"
},
  "geometry": {"coordinates":[8.5567007065,47.3562278748],"type":"Point"}
}