{
  "type": "Feature",
  "properties": {
    "iso:country":"CH",
    "sg:address":"Sonnenbergstrasse 10",
    "sg:city":"Vilters",
    "sg:orig_category":"Vorschulen, Kinderg\u00e4rten",
    "sg:phone":"+41 81 723 45 20",
    "sg:postcode":"7324",
    "sg:province":"St. Gallen",
    "wof:name":"Kindergarten Vilters",
    "wof:placetype":"venue"
},
  "geometry": {"coordinates":[9.4485816956,47.0236549377],"type":"Point"}
}