{
  "type": "Feature",
  "properties": {
    "iso:country":"CH",
    "sg:address":"Grubplatz 4",
    "sg:city":"Bischofszell",
    "sg:orig_category":"Detailhandel mit Fleisch U Fleischwaren",
    "sg:phone":"+41 71 422 13 33",
    "sg:postcode":"9220",
    "sg:province":"Thurgau",
    "wof:name":"Erwin Graf Metzgerei",
    "wof:placetype":"venue"
},
  "geometry": {"coordinates":[9.241437912,47.4938354492],"type":"Point"}
}