{
  "type": "Feature",
  "properties": {
    "iso:country":"CH",
    "sg:address":"Burstwiesenstrasse 17",
    "sg:city":"Greifensee",
    "sg:orig_category":"Erschliessung von Grundst\u00fccken",
    "sg:phone":"+41 19409868",
    "sg:postcode":"8606",
    "sg:province":"Z\u00fcrich",
    "wof:name":"Baugenossenschaft Grafenwis",
    "wof:placetype":"venue"
},
  "geometry": {"coordinates":[8.6792545319,47.3692092896],"type":"Point"}
}