{
  "type": "Feature",
  "properties": {
    "addr:full":"Route De Mi\u00e9court 2942 Alle Case Postale 120 Alle Jura 2942",
    "addr:postcode":"2942;2942",
    "addr:street":"Route De Mie\u0301Court;Postale 120;Jura",
    "iso:country":"CH",
    "sg:address":"Route De Mi\u00e9court 2942 Alle Case Postale 120",
    "sg:city":"Alle",
    "sg:orig_category":"Herstellung der Ausstattung von Uhren Herstellung von Uhren",
    "sg:phone":"+41 32 471 01 40",
    "sg:postcode":"2942",
    "sg:province":"Jura",
    "wof:name":"Atokalpa Sa",
    "wof:placetype":"venue"
},
  "geometry": {"coordinates":[7.144873,47.429707],"type":"Point"}
}