{
  "type": "Feature",
  "properties": {
    "iso:country":"CH",
    "sg:address":"Hauptstrasse 31 6280 Hochdorf. Postfach 921",
    "sg:city":"Hochdorf",
    "sg:orig_category":"Detailhandel mit Geschenkartikeln U Souvenirs",
    "sg:phone":"+41 55 282 37 17",
    "sg:postcode":"6281",
    "sg:province":"Luzern",
    "wof:name":"Boutique Joe Erika & Josef Steiner",
    "wof:placetype":"venue"
},
  "geometry": {"coordinates":[8.9224214554,47.2406539917],"type":"Point"}
}