{
  "type": "Feature",
  "properties": {
    "iso:country":"CH",
    "sg:address":"B\u00e4renloch 1 7000 Chur. Postfach",
    "sg:city":"Chur",
    "sg:orig_category":"Non-Classified Establishments",
    "sg:postcode":"7000",
    "sg:province":"Graubunden",
    "wof:name":"Mondia International Sa Partecipazione Ecc",
    "wof:placetype":"venue"
},
  "geometry": {"coordinates":[9.5325145721,46.8478965759],"type":"Point"}
}