{
  "type": "Feature",
  "properties": {
    "iso:country":"CH",
    "sg:address":"Gartenstrasse 24",
    "sg:city":"H\u00fcnenberg",
    "sg:orig_category":"Offsetdruck",
    "sg:phone":"+41 41 761 13 21",
    "sg:postcode":"6331",
    "sg:province":"Zug",
    "wof:name":"Dmg-druck",
    "wof:placetype":"venue"
},
  "geometry": {"coordinates":[8.4312953949,47.1796455383],"type":"Point"}
}