{
  "type": "Feature",
  "properties": {
    "iso:country":"CH",
    "sg:address":"Poststrasse 13",
    "sg:city":"Zug",
    "sg:orig_category":"Werbeagenturen",
    "sg:phone":"+41 41 720 48 48",
    "sg:postcode":"6300",
    "sg:province":"Zug",
    "wof:name":"Martin Stadler Marketing Consulting",
    "wof:placetype":"venue"
},
  "geometry": {"coordinates":[8.5161075592,47.1687202454],"type":"Point"}
}