{
  "type": "Feature",
  "properties": {
    "iso:country":"CH",
    "sg:address":"W\u00e4gitalstrasse 24 8854 Galgenen. Postfach",
    "sg:city":"Siebnen",
    "sg:orig_category":"Herstellung von konfektionierten Textilwaren ohne Bekleidung",
    "sg:postcode":"8854",
    "sg:province":"Schwyz",
    "wof:name":"Bettwarenshop Inh. Hofstetter Andreas",
    "wof:placetype":"venue"
},
  "geometry": {"coordinates":[8.8990001678,47.1705284119],"type":"Point"}
}