{
  "type": "Feature",
  "properties": {
    "iso:country":"CH",
    "sg:address":"Fortenbach 239",
    "sg:city":"Ramsen",
    "sg:classifiers":[
        {
            "category":"Travel",
            "subcategory":"Hotels & Motels",
            "type":"Entertainment"
        }
    ],
    "sg:phone":"+41 33 822 15 45",
    "sg:postcode":"8262",
    "sg:province":"Schaffhausen",
    "sg:tags":[
        "hotels",
        "mit",
        "restaurant"
    ],
    "wof:name":"Hotel Hirschen",
    "wof:placetype":"venue"
},
  "geometry": {"coordinates":[7.8622460365,46.6816444397],"type":"Point"}
}