{
  "type": "Feature",
  "properties": {
    "addr:full":"Schulstrasse 1 Landschlacht Thurgau 8597",
    "addr:housenumber":"1",
    "addr:postcode":"8597",
    "addr:street":"Schulstrasse",
    "iso:country":"CH",
    "sg:address":"Schulstrasse 1",
    "sg:city":"Landschlacht",
    "sg:orig_category":"Darlehenskassen U Raiffeisenbanken",
    "sg:phone":"+41 71 695 23 68",
    "sg:postcode":"8597",
    "sg:province":"Thurgau",
    "wof:name":"Raiffeisenbank Altnau-m\u00fcnsterlingen",
    "wof:placetype":"venue"
},
  "geometry": {"coordinates":[9.245569,47.627579],"type":"Point"}
}