{
  "type": "Feature",
  "properties": {
    "iso:country":"CH",
    "sg:address":"Kleinh\u00fcningerstrasse 97 4000 Basel. Postfach",
    "sg:city":"Basel",
    "sg:orig_category":"RESTAURANTS: TEA-ROOMS",
    "sg:phone":"+41 41 240 86 98",
    "sg:postcode":"4051",
    "sg:province":"Basel-Stadt",
    "wof:name":"Restaurant Iseb\u00e4hnli Ag",
    "wof:placetype":"venue"
},
  "geometry": {"coordinates":[8.296295166,47.0527305603],"type":"Point"}
}