{
  "type": "Feature",
  "properties": {
    "addr:full":"Grossmatte 12 Littau Luzern 6014",
    "addr:housenumber":"12",
    "addr:postcode":"6014",
    "addr:street":"Grossmatte",
    "iso:country":"CH",
    "sg:address":"Grossmatte 12",
    "sg:city":"Littau",
    "sg:classifiers":[
        {
            "category":"Shopping",
            "subcategory":"Clothing, Apparel, & Fashions",
            "type":"Retail Goods"
        }
    ],
    "sg:phone":"+41 71 274 66 90",
    "sg:postcode":"6014",
    "sg:province":"Luzern",
    "sg:tags":[
        "textile",
        "clothing",
        "clothes"
    ],
    "wof:name":"Peter Hahn",
    "wof:placetype":"venue"
},
  "geometry": {"coordinates":[9.376014,47.424767],"type":"Point"}
}