{
  "type": "Feature",
  "properties": {
    "iso:country":"CH",
    "sg:address":"1884",
    "sg:city":"Hu\u00e9moz",
    "sg:classifiers":[
        {
            "category":"Government",
            "subcategory":"Post Office",
            "type":"Public Place"
        }
    ],
    "sg:phone":"+41 24 495 41 95",
    "sg:postcode":"1884",
    "sg:province":"Vaud",
    "sg:tags":[
        "caf\u00e9s",
        "tea-rooms"
    ],
    "wof:name":"Caf\u00e9 Du Raisin",
    "wof:placetype":"venue"
},
  "geometry": {"coordinates":[7.0251288414,46.2912025452],"type":"Point"}
}