{
  "type": "Feature",
  "properties": {
    "iso:country":"CH",
    "sg:address":"Bahnhofstrasse 2",
    "sg:city":"Biel/bienne",
    "sg:orig_category":"Unternehmensberatung",
    "sg:phone":"+41 32 322 77 46",
    "sg:postcode":"2502",
    "sg:province":"Bern",
    "wof:name":"Herbert E. Von Gr\u00fcnigen Unternehmensberatung",
    "wof:placetype":"venue"
},
  "geometry": {"coordinates":[7.2422380447,47.1334648132],"type":"Point"}
}