{
  "type": "Feature",
  "properties": {
    "iso:country":"CH",
    "sg:address":"St. Gallerstrasse 11a",
    "sg:city":"Arbon",
    "sg:orig_category":"Fachdetailhandel in Verkaufsr\u00e4umen",
    "sg:postcode":"9320",
    "sg:province":"Thurgau",
    "wof:name":"Wa Zoohandlung Gmbh",
    "wof:placetype":"venue"
},
  "geometry": {"coordinates":[9.4312982559,47.5117759705],"type":"Point"}
}