{
  "type": "Feature",
  "properties": {
    "iso:country":"CH",
    "sg:address":"Vorderer Steinacker 3-5",
    "sg:city":"Olten",
    "sg:orig_category":"Druck ohne Zeitungsdruck Offsetdruck",
    "sg:phone":"+41 62 212 70 43",
    "sg:postcode":"4600",
    "sg:province":"Solothurn",
    "wof:name":"Amstutz Alexander",
    "wof:placetype":"venue"
},
  "geometry": {"coordinates":[7.9029278755,47.3468475342],"type":"Point"}
}