{
  "type": "Feature",
  "properties": {
    "iso:country":"CH",
    "sg:address":"Sonnenweg 19",
    "sg:city":"Ormalingen",
    "sg:orig_category":"Sonstiger Grosshandel",
    "sg:postcode":"4466",
    "sg:province":"Basel-Landschaft",
    "wof:name":"Allround Handel Hugo V\u00f6llmin",
    "wof:placetype":"venue"
},
  "geometry": {"coordinates":[7.8766989708,47.4710083008],"type":"Point"}
}