{
  "type": "Feature",
  "properties": {
    "iso:country":"CH",
    "sg:address":"Bielstrasse 15",
    "sg:city":"Solothurn",
    "sg:classifiers":[
        {
            "category":"Home & Garden",
            "subcategory":"Carpets & Floor Coverings",
            "type":"Retail Goods"
        }
    ],
    "sg:phone":"+41 32 622 34 24",
    "sg:postcode":"4500",
    "sg:province":"Solothurn",
    "sg:tags":[
        "material",
        "plastic"
    ],
    "wof:name":"Mobilia Solothurn Ag",
    "wof:placetype":"venue"
},
  "geometry": {"coordinates":[7.5322198868,47.2088661194],"type":"Point"}
}