{
  "type": "Feature",
  "properties": {
    "iso:country":"CH",
    "sg:address":"Oberau",
    "sg:city":"Weite",
    "sg:orig_category":"Mit Sport verbundene T\u00e4tigkeiten",
    "sg:phone":"+41 81 783 24 47",
    "sg:postcode":"9476",
    "sg:province":"St. Gallen",
    "wof:name":"Reithalle Reitver.werdenberg Herrn Lic.iur.paul Schlegel",
    "wof:placetype":"venue"
},
  "geometry": {"coordinates":[9.4974250793,47.0933837891],"type":"Point"}
}