{
  "type": "Feature",
  "properties": {
    "iso:country":"CH",
    "sg:address":"Stansstaderstrasse 54",
    "sg:city":"Stans",
    "sg:orig_category":"Unternehmensberatung",
    "sg:phone":"+41 41 610 84 85",
    "sg:postcode":"6370",
    "sg:province":"Nidwalden",
    "wof:name":"Fuhrer Und Partner Audit Ag",
    "wof:placetype":"venue"
},
  "geometry": {"coordinates":[8.3599538803,46.9624671936],"type":"Point"}
}