{
  "type": "Feature",
  "properties": {
    "iso:country":"CH",
    "sg:address":"3001 Bern. Postfach 7910",
    "sg:city":"Bern",
    "sg:orig_category":"Sportvereine Ballsport Fussball",
    "sg:phone":"+41 79 240 79 30",
    "sg:postcode":"3001",
    "sg:province":"Bern",
    "wof:name":"Sc Hota Luzern",
    "wof:placetype":"venue"
},
  "geometry": {"coordinates":[8.3082399368,47.0456581116],"type":"Point"}
}