{
  "type": "Feature",
  "properties": {
    "iso:country":"CH",
    "sg:address":"Le Pontet 14",
    "sg:city":"Belfaux",
    "sg:orig_category":"Verwaltung von Immobilien",
    "sg:postcode":"1782",
    "sg:province":"Fribourg",
    "wof:name":"G. Tornare Sa",
    "wof:placetype":"venue"
},
  "geometry": {"coordinates":[7.0967278481,46.8235244751],"type":"Point"}
}