{
  "type": "Feature",
  "properties": {
    "iso:country":"CH",
    "sg:address":"Wiesenbachstrasse 10",
    "sg:city":"Wiesendangen",
    "sg:orig_category":"Allgemeiner Hoch U Tiefbau Herstellung von Betonerzeugnissen f\u00fcr den Bau",
    "sg:phone":"+41 31 981 02 09",
    "sg:postcode":"8542",
    "sg:province":"Z\u00fcrich",
    "wof:name":"Weibel Hans Ag Bauunternehmung",
    "wof:placetype":"venue"
},
  "geometry": {"coordinates":[7.352617,46.91642],"type":"Point"}
}