{
  "type": "Feature",
  "properties": {
    "iso:country":"CH",
    "sg:address":"Langgasse",
    "sg:city":"Agarn",
    "sg:orig_category":"Hoch U Tiefbau",
    "sg:phone":"+41 79 414 94 40",
    "sg:postcode":"3951",
    "sg:province":"Valais",
    "wof:name":"J.-j. Mathieu & Sohn Gmbh Baugesch\u00e4ft",
    "wof:placetype":"venue"
},
  "geometry": {"coordinates":[7.665872097,46.2934913635],"type":"Point"}
}