{
  "type": "Feature",
  "properties": {
    "iso:country":"CH",
    "sg:address":"Schulstrasse 27",
    "sg:city":"Thun",
    "sg:classifiers":[
        {
            "category":"Professional",
            "subcategory":"Employment Agencies",
            "type":"Services"
        }
    ],
    "sg:phone":"+41 33 336 52 52",
    "sg:postcode":"3604",
    "sg:province":"Bern",
    "sg:tags":[
        "personal",
        "u",
        "stellenvermittlung"
    ],
    "wof:name":"Asb Ag Stellenvermittlung",
    "wof:placetype":"venue"
},
  "geometry": {"coordinates":[7.6227898598,46.7399253845],"type":"Point"}
}