{
  "type": "Feature",
  "properties": {
    "iso:country":"CH",
    "sg:address":"Kirchstrasse 42 8807 Freienbach. Postfach",
    "sg:city":"Freienbach",
    "sg:orig_category":"Erbringung von Dienstleistungen f\u00fcr Unternehmen",
    "sg:postcode":"8807",
    "sg:province":"Schwyz",
    "wof:name":"T-link Fair-management Ag",
    "wof:placetype":"venue"
},
  "geometry": {"coordinates":[8.7593593597,47.2054176331],"type":"Point"}
}