{
  "type": "Feature",
  "properties": {
    "iso:country":"CH",
    "sg:address":"Pavillonweg 3",
    "sg:city":"Biel/bienne",
    "sg:orig_category":"Luft U Raumfahrzeugbau",
    "sg:phone":"+41 32 322 07 15",
    "sg:postcode":"2502",
    "sg:province":"Bern",
    "wof:name":"Loop-air M\u00e4der & Von Bergen",
    "wof:placetype":"venue"
},
  "geometry": {"coordinates":[7.235845089,47.1383285522],"type":"Point"}
}