{
  "type": "Feature",
  "properties": {
    "iso:country":"CH",
    "sg:address":"Friedhofplatz 5 4500 Solothurn. Postfach",
    "sg:city":"Solothurn",
    "sg:orig_category":"Sonstiger Fachdetailhandel mit Nahrungsmitteln, Getr\u00e4nken U Tabak in Verkaufsr\u00e4umen",
    "sg:phone":"+41 32 622 40 69",
    "sg:postcode":"4502",
    "sg:province":"Solothurn",
    "wof:name":"M\u00fcller Reformhaus Ag",
    "wof:placetype":"venue"
},
  "geometry": {"coordinates":[7.5357670784,47.2071685791],"type":"Point"}
}