{
  "type": "Feature",
  "properties": {
    "iso:country":"CH",
    "sg:address":"Salmenweg 5",
    "sg:city":"Basel",
    "sg:orig_category":"Herstellung von Drahtwaren",
    "sg:postcode":"4057",
    "sg:province":"Basel-Stadt",
    "wof:name":"Ukatel Uka B. Handel Und Technologietransfer Von Kabel, Kabelsystemen, Computer-netzwerken Usw",
    "wof:placetype":"venue"
},
  "geometry": {"coordinates":[8.7776355743,47.3748397827],"type":"Point"}
}