{
  "type": "Feature",
  "properties": {
    "iso:country":"CH",
    "sg:address":"Lotzwilstrasse 36",
    "sg:city":"Langenthal",
    "sg:classifiers":[
        {
            "category":"Restaurant",
            "type":"Food & Drink"
        }
    ],
    "sg:phone":"+41 62 922 48 03",
    "sg:postcode":"4900",
    "sg:province":"Bern",
    "wof:name":"Restaurant Neuh\u00fcsli",
    "wof:placetype":"venue"
},
  "geometry": {"coordinates":[7.7837882042,47.2076263428],"type":"Point"}
}