{
  "type": "Feature",
  "properties": {
    "iso:country":"CH",
    "sg:address":"Pradasolweg 1",
    "sg:city":"Flums",
    "sg:orig_category":"S\u00e4gewerke Zimmerei, Dachdeckerei, Bauspenglerei U Abdichtung",
    "sg:phone":"+41 81 733 15 03",
    "sg:postcode":"8890",
    "sg:province":"St. Gallen",
    "wof:name":"Beeler Max",
    "wof:placetype":"venue"
},
  "geometry": {"coordinates":[9.346698761,47.0936164856],"type":"Point"}
}