{
  "type": "Feature",
  "properties": {
    "iso:country":"CH",
    "sg:address":"Promenade Des Artisans 28",
    "sg:city":"Meyrin",
    "sg:orig_category":"Detailhandel mit Tabakwaren",
    "sg:postcode":"1217",
    "sg:province":"Gen\u00e8ve",
    "wof:name":"Beniflah J.",
    "wof:placetype":"venue"
},
  "geometry": {"coordinates":[6.0795822144,46.2376556396],"type":"Point"}
}