{
  "type": "Feature",
  "properties": {
    "iso:country":"CH",
    "sg:address":"Rue De La Samaritaine 24",
    "sg:city":"Fribourg",
    "sg:orig_category":"Maurerarbeiten Sonstiger spezialisierter Hoch U Tiefbau",
    "sg:phone":"+41 32 396 19 19",
    "sg:postcode":"1700",
    "sg:province":"Fribourg",
    "wof:name":"Samuel Schwaar Maurerarbeiten",
    "wof:placetype":"venue"
},
  "geometry": {"coordinates":[7.1876788139,47.0308799744],"type":"Point"}
}