{
  "type": "Feature",
  "properties": {
    "iso:country":"CH",
    "sg:address":"Wallisellerstrasse 8",
    "sg:city":"Glattbrugg",
    "sg:orig_category":"Fachdetailhandel in Verkaufsr\u00e4umen",
    "sg:postcode":"8152",
    "sg:province":"Z\u00fcrich",
    "wof:name":"Minder Hans-j\u00f6rg, Vertretungen Und Verkauf Von Sportartikeln",
    "wof:placetype":"venue"
},
  "geometry": {"coordinates":[8.5678548813,47.4341468811],"type":"Point"}
}