{
  "type": "Feature",
  "properties": {
    "iso:country":"CH",
    "sg:address":"Salmenstrasse 14",
    "sg:city":"Birsfelden",
    "sg:orig_category":"Herstellung von sonstigen elektrischen Ausr\u00fcstungen",
    "sg:postcode":"4127",
    "sg:province":"Basel-Landschaft",
    "wof:name":"Scan Master Electronics Arber R.",
    "wof:placetype":"venue"
},
  "geometry": {"coordinates":[7.6289777756,47.5534973145],"type":"Point"}
}