{
  "type": "Feature",
  "properties": {
    "iso:country":"CH",
    "sg:address":"Chemin Des Croix-rouges 8",
    "sg:city":"Lausanne",
    "sg:orig_category":"Vermietung von Gebrauchsg\u00fctern",
    "sg:phone":"+41 21 311 48 80",
    "sg:postcode":"1007",
    "sg:province":"Vaud",
    "wof:name":"Vid\u00e9o Ho Michel Hallenbarter",
    "wof:placetype":"venue"
},
  "geometry": {"coordinates":[6.621090889,46.5207366943],"type":"Point"}
}