{
  "type": "Feature",
  "properties": {
    "iso:country":"CH",
    "sg:address":"Vordergasse 4",
    "sg:city":"Elgg",
    "sg:orig_category":"Detailhandel mit Waren verschiedener Art, Hauptrichtung Nahrungsmittel",
    "sg:phone":"+41 52 364 16 14",
    "sg:postcode":"8353",
    "sg:province":"Z\u00fcrich",
    "wof:name":"Volg Detailhandels Ag Volg-laden",
    "wof:placetype":"venue"
},
  "geometry": {"coordinates":[8.8666658401,47.4909515381],"type":"Point"}
}