{
  "type": "Feature",
  "properties": {
    "iso:country":"CH",
    "sg:address":"Papierm\u00fchlestrasse 145 3063 Ittigen. Postfach",
    "sg:city":"Ittigen",
    "sg:orig_category":"Softwareentwicklung U beratung",
    "sg:postcode":"3063",
    "sg:province":"Bern",
    "wof:name":"Grapp Ag",
    "wof:placetype":"venue"
},
  "geometry": {"coordinates":[9.3562574387,47.4139823914],"type":"Point"}
}