{
  "type": "Feature",
  "properties": {
    "iso:country":"CH",
    "sg:address":"1733",
    "sg:city":"Treyvaux",
    "sg:orig_category":"Vereine Musik/Blasmusik",
    "sg:postcode":"1733",
    "sg:province":"Fribourg",
    "wof:name":"St\u00e9 De Musique",
    "wof:placetype":"venue"
},
  "geometry": {"coordinates":[6.9309201241,46.9920082092],"type":"Point"}
}