{
  "type": "Feature",
  "properties": {
    "iso:country":"CH",
    "sg:address":"Burstwiesenstrasse 59",
    "sg:city":"Greifensee",
    "sg:orig_category":"Wirtschaftspr\u00fcfung, Steuerberatung U Treuhand",
    "sg:postcode":"8606",
    "sg:province":"Z\u00fcrich",
    "wof:name":"Treucommerz Gmbh",
    "wof:placetype":"venue"
},
  "geometry": {"coordinates":[8.6773681641,47.3738365173],"type":"Point"}
}