{
  "type": "Feature",
  "properties": {
    "addr:full":"Walkeweg 36 4053 Basel. Postfach Basel 4021",
    "addr:housenumber":"36",
    "addr:postcode":"4053;4021",
    "addr:street":"Walkeweg;Postfach",
    "iso:country":"CH",
    "sg:address":"Walkeweg 36 4053 Basel. Postfach",
    "sg:city":"Basel",
    "sg:orig_category":"Detailhandel mit Brot, Back U S\u00fcsswaren RESTAURANTS: TEA-ROOMS",
    "sg:phone":"+41 61 333 21 00",
    "sg:postcode":"4021",
    "wof:name":"Wacker Und Schwob Ag",
    "wof:placetype":"venue"
},
  "geometry": {"coordinates":[7.612432,47.538563],"type":"Point"}
}