{
  "type": "Feature",
  "properties": {
    "iso:country":"CH",
    "sg:address":"Grenzacherstrasse 488",
    "sg:city":"Basel",
    "sg:orig_category":"Detailhandel mit B\u00fcchern, Zeitungen, Schreib U Papeteriewaren Detailhandel mit Zeitungen U Zeitschri",
    "sg:phone":"+41 61 601 77 96",
    "sg:postcode":"4058",
    "sg:province":"Basel-Stadt",
    "wof:name":"Kiosk Grenzacherstrasse 488, Zolin Bruno",
    "wof:placetype":"venue"
},
  "geometry": {"coordinates":[7.626098,47.562225],"type":"Point"}
}