{
  "type": "Feature",
  "properties": {
    "iso:country":"CH",
    "sg:address":"R\u00e4tusstrasse 22",
    "sg:city":"Chur",
    "sg:orig_category":"Fachdetailhandel in Verkaufsr\u00e4umen",
    "sg:postcode":"7000",
    "sg:province":"Graubunden",
    "wof:name":"Pervoi Itfp Ag",
    "wof:placetype":"venue"
},
  "geometry": {"coordinates":[9.523235321,46.8488502502],"type":"Point"}
}