{
  "type": "Feature",
  "properties": {
    "iso:country":"CH",
    "sg:address":"Roschbrunnen 477",
    "sg:city":"Staffelbach",
    "sg:orig_category":"Grosshandel mit Parf\u00fcmerieartikeln U K\u00f6rperpflegemitteln Herstellung von Duft U K\u00f6rperpflegemitteln",
    "sg:phone":"+41 21 636 24 45",
    "sg:postcode":"5053",
    "sg:province":"Aargau",
    "wof:name":"Diamant-cosm\u00e9tiques Sa",
    "wof:placetype":"venue"
},
  "geometry": {"coordinates":[6.5682821274,46.5356864929],"type":"Point"}
}