{
  "type": "Feature",
  "properties": {
    "addr:full":"Avenue De Savoie 31 St-prex Vaud 1162",
    "addr:housenumber":"31",
    "addr:postcode":"1162",
    "addr:street":"Avenue De Savoie",
    "iso:country":"CH",
    "sg:address":"Avenue De Savoie 31",
    "sg:city":"St-prex",
    "sg:orig_category":"Autoelektro and -elektronik Werkst\u00e4tten",
    "sg:postcode":"1162",
    "sg:province":"Vaud",
    "wof:name":"Val\u00e9ry Dubois S\u00e0rl Auto-\u00e9lectricit\u00e9",
    "wof:placetype":"venue"
},
  "geometry": {"coordinates":[6.45767,46.482117],"type":"Point"}
}