{
  "type": "Feature",
  "properties": {
    "iso:country":"CH",
    "sg:address":"Crans-sur-sierre 1978 Lens. Postfach",
    "sg:city":"Crans-sur-sierre",
    "sg:classifiers":[
        {
            "category":"Travel",
            "subcategory":"Hotels & Motels",
            "type":"Entertainment"
        }
    ],
    "sg:postcode":"3963",
    "sg:province":"Valais",
    "sg:tags":[
        "hotels",
        "mit",
        "restaurant"
    ],
    "wof:name":"Bonvin Roger",
    "wof:placetype":"venue"
},
  "geometry": {"coordinates":[7.4460501671,46.2793235779],"type":"Point"}
}