{
  "type": "Feature",
  "properties": {
    "iso:country":"CH",
    "sg:address":"Riehenstrasse 62",
    "sg:city":"Basel",
    "sg:orig_category":"Saunas, Solarien, Fitnesszentren U \u00e4hnliches",
    "sg:phone":"+41 61 681 02 60",
    "sg:postcode":"4058",
    "sg:province":"Basel-Stadt",
    "wof:name":"Solarium Studio Sunline Sofia Erna",
    "wof:placetype":"venue"
},
  "geometry": {"coordinates":[7.6000709534,47.5618743896],"type":"Point"}
}