{
  "type": "Feature",
  "properties": {
    "iso:country":"CH",
    "sg:address":"Sous Le Scex 13 1890 St-maurice. Postfach",
    "sg:city":"Dailly",
    "sg:orig_category":"Architektur U Ingenieurb\u00fcros",
    "sg:phone":"+41 24 485 37 80",
    "sg:postcode":"1890",
    "sg:province":"Valais",
    "wof:name":"Alberio Bt Bureau Technique Dans Le Domaine De La M\u00e9canique Etc",
    "wof:placetype":"venue"
},
  "geometry": {"coordinates":[6.998197,46.21431],"type":"Point"}
}