{
  "type": "Feature",
  "properties": {
    "iso:country":"CH",
    "sg:address":"Avenue Alfred Cortot 7d",
    "sg:city":"Nyon",
    "sg:orig_category":"Softwareentwicklung U beratung Sonstige mit der Informatik verbundene T\u00e4tigkeiten",
    "sg:phone":"+41 22 362 04 60",
    "sg:postcode":"1260",
    "sg:province":"Vaud",
    "wof:name":"Ubik Sa",
    "wof:placetype":"venue"
},
  "geometry": {"coordinates":[6.2316851616,46.3849372864],"type":"Point"}
}