{
  "type": "Feature",
  "properties": {
    "iso:country":"CH",
    "sg:address":"Autostradale Coldrerio-est",
    "sg:city":"Coldrerio",
    "sg:orig_category":"Herstellung von k\u00e4lte U lufttechnischen Erzeugnissen f\u00fcr gewerbliche Zwecke Technische B\u00fcros Heizung",
    "sg:phone":"+41 19951215",
    "sg:postcode":"6877",
    "sg:province":"Ticino",
    "wof:name":"Md-plan D\u00f6rig Martin Haustechnische Anlagen, Heizungen Usw.; Planung",
    "wof:placetype":"venue"
},
  "geometry": {"coordinates":[8.7698993683,47.3693161011],"type":"Point"}
}