{
  "type": "Feature",
  "properties": {
    "addr:full":"Via Vallemaggia 62 Locarno Ticino 6600",
    "addr:housenumber":"62",
    "addr:postcode":"6600",
    "addr:street":"Via Vallemaggia;Ticino",
    "iso:country":"CH",
    "sg:address":"Via Vallemaggia 62",
    "sg:city":"Locarno",
    "sg:orig_category":"Dachdeckerei",
    "sg:phone":"+41 91 751 55 53",
    "sg:postcode":"6600",
    "sg:province":"Ticino",
    "wof:name":"Giovanni Cancelli Copertura Tetti",
    "wof:placetype":"venue"
},
  "geometry": {"coordinates":[8.79054,46.169922],"type":"Point"}
}