{
  "type": "Feature",
  "properties": {
    "iso:country":"CH",
    "sg:address":"R\u00fcttelistrasse 18 4416 Bubendorf. Postfach",
    "sg:city":"Bubendorf",
    "sg:orig_category":"Reiseb\u00fcros U Reiseveranstalter",
    "sg:postcode":"4416",
    "sg:province":"Basel-Landschaft",
    "wof:name":"A+a Travel-business Atbinek Tourismus. Waren; Import, Export",
    "wof:placetype":"venue"
},
  "geometry": {"coordinates":[7.7452411652,47.4520606995],"type":"Point"}
}