{
  "type": "Feature",
  "properties": {
    "iso:country":"CH",
    "sg:address":"Avenue Des Reneveyres 28",
    "sg:city":"Morges",
    "sg:orig_category":"Buchf\u00fchrung Wirtschaftspr\u00fcfung, Steuerberatung U Treuhand",
    "sg:phone":"+41 21 801 40 54",
    "sg:postcode":"1110",
    "sg:province":"Vaud",
    "wof:name":"Fiduciaire Germain-genoux",
    "wof:placetype":"venue"
},
  "geometry": {"coordinates":[6.494306,46.517277],"type":"Point"}
}