{
  "type": "Feature",
  "properties": {
    "iso:country":"CH",
    "sg:address":"Gerichtsgasse 77 5080 Laufenburg. Postfach",
    "sg:city":"Laufenburg",
    "sg:orig_category":"Detailhandel Reparatur von Gebrauchsg\u00fctern Vermietung von Gebrauchsg\u00fctern",
    "sg:phone":"+41 62 874 20 29",
    "sg:postcode":"5080",
    "sg:province":"Aargau",
    "wof:name":"Monika Gartmann Video Treff",
    "wof:placetype":"venue"
},
  "geometry": {"coordinates":[8.0599851608,47.5608520508],"type":"Point"}
}