{
  "type": "Feature",
  "properties": {
    "iso:country":"CH",
    "sg:address":"B\u00fchlfeldstrasse 11 8965 Berikon. Postfach",
    "sg:city":"Berikon",
    "sg:orig_category":"Bau von Strassen, Sportanlagen U Bahnverkehrsstrecken",
    "sg:postcode":"8965",
    "sg:province":"Aargau",
    "wof:name":"Phoenix Ventures Stocker I. Schwimmbad- U. Gartenzubeh\u00f6r Usw.; Im, Export, Handel",
    "wof:placetype":"venue"
},
  "geometry": {"coordinates":[8.365335,47.357452],"type":"Point"}
}