{
  "type": "Feature",
  "properties": {
    "iso:country":"CH",
    "sg:address":"Route De Suisse 57",
    "sg:city":"Versoix",
    "sg:orig_category":"Verwertung von Milch",
    "sg:phone":"+41 22 755 12 15",
    "sg:postcode":"1290",
    "sg:province":"Gen\u00e8ve",
    "wof:name":"Buffat G.",
    "wof:placetype":"venue"
},
  "geometry": {"coordinates":[6.1677889824,46.2789459229],"type":"Point"}
}