{
  "type": "Feature",
  "properties": {
    "iso:country":"CH",
    "sg:address":"R\u00e4mistrasse 2 8001 Z\u00fcrich. Postfach",
    "sg:city":"Z\u00fcrich",
    "sg:orig_category":"Sonstiger Grosshandel",
    "sg:postcode":"8001",
    "sg:province":"Z\u00fcrich",
    "wof:name":"Minident Ag",
    "wof:placetype":"venue"
},
  "geometry": {"coordinates":[8.5455350876,47.3674926758],"type":"Point"}
}