{
  "type": "Feature",
  "properties": {
    "iso:country":"CH",
    "sg:address":"Hauptstrasse 50",
    "sg:city":"Erlen",
    "sg:orig_category":"Handel mit Automobilen",
    "sg:phone":"+41 71 648 14 48",
    "sg:postcode":"8586",
    "sg:province":"Thurgau",
    "wof:name":"Erlengarage Tobler Karl Ag Autohandel Usw",
    "wof:placetype":"venue"
},
  "geometry": {"coordinates":[9.2328739166,47.5481529236],"type":"Point"}
}