{
  "type": "Feature",
  "properties": {
    "iso:country":"CH",
    "sg:address":"St. Jakobs-strasse 59",
    "sg:city":"Muttenz",
    "sg:orig_category":"Vermietung U Verpachtung von eigenen Immobilien",
    "sg:postcode":"4132",
    "sg:province":"Basel-Landschaft",
    "wof:name":"Falkenstein Ag",
    "wof:placetype":"venue"
},
  "geometry": {"coordinates":[9.4746046066,47.1628952026],"type":"Point"}
}