{
  "type": "Feature",
  "properties": {
    "iso:country":"CH",
    "sg:address":"Kirschbl\u00fctenweg 7",
    "sg:city":"Basel",
    "sg:orig_category":"Wohnheime",
    "sg:postcode":"4059",
    "sg:province":"Basel-Stadt",
    "wof:name":"Basler Wirrgarten",
    "wof:placetype":"venue"
},
  "geometry": {"coordinates":[7.5888209343,47.5366783142],"type":"Point"}
}