{
  "type": "Feature",
  "properties": {
    "iso:country":"CH",
    "sg:address":"Bertswilstrasse 28a",
    "sg:city":"Rothenburg",
    "sg:orig_category":"Allgemeiner Hoch U Tiefbau Hoch U Tiefbau",
    "sg:phone":"+41 41 280 12 64",
    "sg:postcode":"6023",
    "sg:province":"Luzern",
    "wof:name":"Sch\u00e4fer Bau Gmbh",
    "wof:placetype":"venue"
},
  "geometry": {"coordinates":[8.270426,47.098232],"type":"Point"}
}