{
  "type": "Feature",
  "properties": {
    "iso:country":"CH",
    "sg:address":"Bahnhofstrasse 9240 Uzwil. Postfach",
    "sg:city":"Uzwil",
    "sg:orig_category":"Pensionskassen",
    "sg:postcode":"9240",
    "sg:province":"St. Gallen",
    "wof:name":"Allgemeine Wohlfahrtsstiftung Der B\u00fchler Ag",
    "wof:placetype":"venue"
},
  "geometry": {"coordinates":[9.1519670486,47.4451370239],"type":"Point"}
}