{
  "type": "Feature",
  "properties": {
    "iso:country":"CH",
    "sg:address":"Im Talacher 26",
    "sg:city":"Br\u00fcttisellen",
    "sg:orig_category":"Sportvereine Eissport Bob, Schlitteln and Skeleton",
    "sg:phone":"+41 81 864 14 21",
    "sg:postcode":"8306",
    "sg:province":"Z\u00fcrich",
    "wof:name":"Skeleton-club Engiadina",
    "wof:placetype":"venue"
},
  "geometry": {"coordinates":[9.8381910324,46.4970664978],"type":"Point"}
}