{
  "type": "Feature",
  "properties": {
    "iso:country":"CH",
    "sg:address":"Bahnhofstrasse 2 8587 Oberaach. Postfach",
    "sg:city":"Oberaach",
    "sg:orig_category":"RESTAURANTS: TEA-ROOMS",
    "sg:postcode":"8587",
    "sg:province":"Thurgau",
    "wof:name":"Faha-gastro Gmbh",
    "wof:placetype":"venue"
},
  "geometry": {"coordinates":[9.2673978806,47.5541572571],"type":"Point"}
}