{
  "type": "Feature",
  "properties": {
    "iso:country":"CH",
    "sg:address":"Riedsortstrasse 5",
    "sg:city":"Weggis",
    "sg:orig_category":"Vermietung U Verpachtung von eigenen Immobilien",
    "sg:phone":"+41 79 340 80 83",
    "sg:postcode":"6353",
    "sg:province":"Luzern",
    "wof:name":"Turel Ag Weggis",
    "wof:placetype":"venue"
},
  "geometry": {"coordinates":[8.4546728134,47.0244140625],"type":"Point"}
}