{
  "type": "Feature",
  "properties": {
    "iso:country":"CH",
    "sg:address":"Birkenweg 1",
    "sg:city":"Safenwil",
    "sg:orig_category":"Malerei",
    "sg:phone":"+41 79 459 03 15",
    "sg:postcode":"5745",
    "sg:province":"Aargau",
    "wof:name":"Dieter Wyss Maler",
    "wof:placetype":"venue"
},
  "geometry": {"coordinates":[7.9827818871,47.3256530762],"type":"Point"}
}