{
  "type": "Feature",
  "properties": {
    "iso:country":"CH",
    "sg:address":"5634",
    "sg:city":"Merenschwand",
    "sg:classifiers":[
        {
            "category":"Restaurant",
            "type":"Food & Drink"
        }
    ],
    "sg:phone":"+41 56 664 12 48",
    "sg:postcode":"5634",
    "sg:province":"Aargau",
    "wof:name":"Restaurant Hirschen",
    "wof:placetype":"venue"
},
  "geometry": {"coordinates":[8.3721055984,47.2608451843],"type":"Point"}
}