{
  "type": "Feature",
  "properties": {
    "iso:country":"CH",
    "sg:address":"Avenue De Lonay 17-19",
    "sg:city":"Morges",
    "sg:orig_category":"Detailhandel mit Fleisch U Fleischwaren",
    "sg:phone":"+41 26 927 13 33",
    "sg:postcode":"1110",
    "sg:province":"Vaud",
    "wof:name":"Grossrieder Fr\u00e9dy",
    "wof:placetype":"venue"
},
  "geometry": {"coordinates":[7.1670150757,46.6194267273],"type":"Point"}
}