{
  "type": "Feature",
  "properties": {
    "iso:country":"CH",
    "sg:address":"Fuchsweg 8",
    "sg:city":"Niederbipp",
    "sg:orig_category":"Sonstige mit der Informatik verbundene T\u00e4tigkeiten",
    "sg:postcode":"4704",
    "sg:province":"Bern",
    "wof:name":"Heer Edv-beratungs-ag",
    "wof:placetype":"venue"
},
  "geometry": {"coordinates":[7.6972818375,47.2699813843],"type":"Point"}
}