{
  "type": "Feature",
  "properties": {
    "iso:country":"CH",
    "sg:address":"Baarerstrasse 18 6300 Zug. Postfach",
    "sg:city":"Zug",
    "sg:orig_category":"Grosshandel mit chemischen Erzeugnissen Sonstiger Grosshandel",
    "sg:phone":"+41 21 847 11 02",
    "sg:postcode":"6304",
    "sg:province":"Zug",
    "wof:name":"Pentamer Sa",
    "wof:placetype":"venue"
},
  "geometry": {"coordinates":[6.6639499664,46.5902061462],"type":"Point"}
}