{
  "type": "Feature",
  "properties": {
    "iso:country":"CH",
    "sg:address":"Via Al Forte 3",
    "sg:city":"Lugano",
    "sg:orig_category":"Erbringung von Dienstleistungen f\u00fcr Unternehmen",
    "sg:phone":"+41 91 924 15 35",
    "sg:postcode":"6900",
    "sg:province":"Ticino",
    "wof:name":"Sbicca & Raach Sagl",
    "wof:placetype":"venue"
},
  "geometry": {"coordinates":[8.9533481598,46.0056495667],"type":"Point"}
}