{
  "type": "Feature",
  "properties": {
    "iso:country":"CH",
    "sg:address":"Rosenbergstrasse 1",
    "sg:city":"W\u00e4denswil",
    "sg:orig_category":"Sonstiger Fachdetailhandel mit Nahrungsmitteln, Getr\u00e4nken U Tabak in Verkaufsr\u00e4umen",
    "sg:phone":"+41 17803522",
    "sg:postcode":"8820",
    "sg:province":"Z\u00fcrich",
    "wof:name":"M\u00fcller Reformhaus Ag",
    "wof:placetype":"venue"
},
  "geometry": {"coordinates":[8.6695985794,47.2294540405],"type":"Point"}
}