{
  "type": "Feature",
  "properties": {
    "iso:country":"CH",
    "sg:address":"M\u00fchlebr\u00fccke 10",
    "sg:city":"Biel/bienne",
    "sg:orig_category":"Non-Classified Establishments",
    "sg:postcode":"2502",
    "sg:province":"Bern",
    "wof:name":"Topbrand Gmbh",
    "wof:placetype":"venue"
},
  "geometry": {"coordinates":[7.2445378304,47.1401824951],"type":"Point"}
}