{
  "type": "Feature",
  "properties": {
    "iso:country":"CH",
    "sg:address":"Dorfstrasse 6 8102 Oberengstringen. Postfach 130",
    "sg:city":"Oberengstringen",
    "sg:orig_category":"Allgemeiner Hoch U Tiefbau",
    "sg:phone":"+41 17503440",
    "sg:postcode":"8102",
    "sg:province":"Z\u00fcrich",
    "wof:name":"Suma Bau Ag",
    "wof:placetype":"venue"
},
  "geometry": {"coordinates":[8.459555,47.406132],"type":"Point"}
}