{
  "type": "Feature",
  "properties": {
    "iso:country":"CH",
    "sg:address":"Fabrikstrasse 11",
    "sg:city":"Herzogenbuchsee",
    "sg:classifiers":[
        {
            "category":"Banks & Credit Unions",
            "subcategory":"Investment Brokerage",
            "type":"Services"
        }
    ],
    "sg:phone":"+41 62 961 16 08",
    "sg:postcode":"3360",
    "sg:province":"Bern",
    "sg:tags":[
        "traditional",
        "brace",
        "costume"
    ],
    "wof:name":"A. Binz Trachtenartikel Ag",
    "wof:placetype":"venue"
},
  "geometry": {"coordinates":[7.70445,47.189224],"type":"Point"}
}