{
  "type": "Feature",
  "properties": {
    "addr:full":"Bahnhofstrasse 15a Lyss Bern 3250",
    "addr:housenumber":"15a",
    "addr:postcode":"3250",
    "addr:street":"Bahnhofstrasse;Bern",
    "iso:country":"CH",
    "sg:address":"Bahnhofstrasse 15a",
    "sg:city":"Lyss",
    "sg:orig_category":"Allgemeiner Hoch U Tiefbau",
    "sg:phone":"+41 79 631 39 09",
    "sg:postcode":"3250",
    "sg:province":"Bern",
    "wof:name":"Weiss + Appetito Ag Lyss",
    "wof:placetype":"venue"
},
  "geometry": {"coordinates":[7.305467,47.076099],"type":"Point"}
}