{
  "type": "Feature",
  "properties": {
    "iso:country":"CH",
    "sg:address":"Chantemerle Route De 1",
    "sg:city":"Granges-paccot",
    "sg:orig_category":"Softwareentwicklung U beratung",
    "sg:phone":"+41 21 651 33 33",
    "sg:postcode":"1763",
    "sg:province":"Fribourg",
    "wof:name":"Logicosoftware Sa",
    "wof:placetype":"venue"
},
  "geometry": {"coordinates":[6.6389751434,46.5118293762],"type":"Point"}
}