{
  "type": "Feature",
  "properties": {
    "iso:country":"CH",
    "sg:address":"Place Du March\u00e9 8",
    "sg:city":"Nyon",
    "sg:orig_category":"Detailhandel mit Brot, Back U S\u00fcsswaren",
    "sg:phone":"+41 22 361 15 36",
    "sg:postcode":"1260",
    "sg:province":"Vaud",
    "wof:name":"Marti Arnold.",
    "wof:placetype":"venue"
},
  "geometry": {"coordinates":[6.238355,46.382],"type":"Point"}
}