{
  "type": "Feature",
  "properties": {
    "iso:country":"CH",
    "sg:address":"Fulachstrasse 46",
    "sg:city":"Schaffhausen",
    "sg:orig_category":"Hardwareberatung",
    "sg:phone":"+41 52 620 26 53",
    "sg:postcode":"8200",
    "sg:province":"Schaffhausen",
    "wof:name":"Bruderer Research Gmbh",
    "wof:placetype":"venue"
},
  "geometry": {"coordinates":[8.6409921646,47.7084236145],"type":"Point"}
}