{
  "type": "Feature",
  "properties": {
    "iso:country":"CH",
    "sg:address":"Wilerstrasse 319a",
    "sg:city":"Ramsen",
    "sg:orig_category":"Handel mit Motorr\u00e4dern, Teilen U Zubeh\u00f6r Instandhaltung U Reparatur von Motorr\u00e4dern",
    "sg:phone":"+41 52 743 16 35",
    "sg:postcode":"8262",
    "sg:province":"Schaffhausen",
    "wof:name":"Atg Gn\u00e4dinger",
    "wof:placetype":"venue"
},
  "geometry": {"coordinates":[8.8134307861,47.7054443359],"type":"Point"}
}