{
  "type": "Feature",
  "properties": {
    "iso:country":"CH",
    "sg:address":"Chemin De Foulon 25",
    "sg:city":"Perly",
    "sg:orig_category":"Installation von Heizungs, L\u00fcftungs U Klimaanlagen Sanit\u00e4r U Heizungsinstallation",
    "sg:phone":"+41 22 771 23 11",
    "sg:postcode":"1258",
    "sg:province":"Gen\u00e8ve",
    "wof:name":"Richard Pillet Chauffages & Ventilation",
    "wof:placetype":"venue"
},
  "geometry": {"coordinates":[6.0810918808,46.157989502],"type":"Point"}
}