{
  "type": "Feature",
  "properties": {
    "addr:full":"Engenb\u00fchl 333 5705 Hallwil. Postfach 45 Hallwil Aargau 5705",
    "addr:housenumber":"333;45",
    "addr:postcode":"5705 hallwil.;5705",
    "addr:street":"Postfach",
    "iso:country":"CH",
    "sg:address":"Engenb\u00fchl 333 5705 Hallwil. Postfach 45",
    "sg:city":"Hallwil",
    "sg:orig_category":"Architektur U Ingenieurb\u00fcros Architekturb\u00fcros",
    "sg:phone":"+41 21 691 50 76",
    "sg:postcode":"5705",
    "sg:province":"Aargau",
    "wof:name":"Arcobat S\u00e0rl",
    "wof:placetype":"venue"
},
  "geometry": {"coordinates":[6.552782,46.513168],"type":"Point"}
}