{
  "type": "Feature",
  "properties": {
    "iso:country":"CH",
    "sg:address":"Schafg\u00e4sslein 6 4058 Basel. Postfach",
    "sg:city":"Basel",
    "sg:orig_category":"Werbeagenturen Werbegrafikateliers",
    "sg:phone":"+41 61 272 20 19",
    "sg:postcode":"4001",
    "sg:province":"Basel-Stadt",
    "wof:name":"Studinger Partner Werbung & Gestaltung",
    "wof:placetype":"venue"
},
  "geometry": {"coordinates":[7.5922989845,47.5603065491],"type":"Point"}
}