{
  "type": "Feature",
  "properties": {
    "iso:country":"CH",
    "sg:address":"Rebstr. 10 8155 Niederhasli. Postfach",
    "sg:city":"Oberhasli",
    "sg:orig_category":"Wirtschaftspr\u00fcfung, Steuerberatung U Treuhand",
    "sg:postcode":"8156",
    "sg:province":"Z\u00fcrich",
    "wof:name":"Erni Treuhand",
    "wof:placetype":"venue"
},
  "geometry": {"coordinates":[8.502158165,47.4693450928],"type":"Point"}
}