{
  "type": "Feature",
  "properties": {
    "iso:country":"CH",
    "sg:address":"K\u00e4nerkinderstrasse 9",
    "sg:city":"Diegten",
    "sg:orig_category":"Datenverarbeitungsdienste Sonstige pers\u00f6nliche Dienstleistungen",
    "sg:phone":"+41 61 973 13 73",
    "sg:postcode":"4457",
    "sg:province":"Basel-Landschaft",
    "wof:name":"Fiedler Consulting Ag",
    "wof:placetype":"venue"
},
  "geometry": {"coordinates":[7.81234,47.413239],"type":"Point"}
}