{
  "type": "Feature",
  "properties": {
    "iso:country":"CH",
    "sg:address":"Gerbergasse 78",
    "sg:city":"Basel",
    "sg:classifiers":[
        {
            "category":"Bars & Pubs",
            "type":"Food & Drink"
        }
    ],
    "sg:phone":"+41 61 261 06 51",
    "sg:postcode":"4001",
    "sg:province":"Basel-Stadt",
    "wof:name":"Piadina Ag Piadina Bar",
    "wof:placetype":"venue"
},
  "geometry": {"coordinates":[7.588702,47.555031],"type":"Point"}
}