{
  "type": "Feature",
  "properties": {
    "iso:country":"CH",
    "sg:address":"Canonica Via 16",
    "sg:city":"Lugano",
    "sg:orig_category":"Sanit\u00e4r U Heizungsinstallation Sanit\u00e4r, Heizungs U L\u00fcftungsinstallation",
    "sg:phone":"+41 19321046",
    "sg:postcode":"6900",
    "sg:province":"Ticino",
    "wof:name":"Caviezel Rolf Ag",
    "wof:placetype":"venue"
},
  "geometry": {"coordinates":[8.7872056961,47.3197402954],"type":"Point"}
}