{
  "type": "Feature",
  "properties": {
    "iso:country":"CH",
    "sg:address":"Kehlstrasse 7 5400 Baden. Postfach",
    "sg:city":"Baden",
    "sg:orig_category":"Architektur U Ingenieurb\u00fcros",
    "sg:postcode":"5400",
    "sg:province":"Aargau",
    "wof:name":"Mogli Solutions Rudow Andreas, 5400 Baden",
    "wof:placetype":"venue"
},
  "geometry": {"coordinates":[8.292529,47.468159],"type":"Point"}
}