{
  "type": "Feature",
  "properties": {
    "iso:country":"CH",
    "sg:address":"Florhofstrasse 13",
    "sg:city":"W\u00e4denswil",
    "sg:orig_category":"HOTELS: MIT RESTAURANT RESTAURANTS: TEA-ROOMS",
    "sg:postcode":"8820",
    "sg:province":"Z\u00fcrich",
    "wof:name":"Restaurant W\u00e4di-brau-huus",
    "wof:placetype":"venue"
},
  "geometry": {"coordinates":[8.6703195572,47.2310829163],"type":"Point"}
}