{
  "type": "Feature",
  "properties": {
    "iso:country":"CH",
    "sg:address":"Via Tratto Di Mezzo",
    "sg:city":"Gordola",
    "sg:orig_category":"Unclassifiable Establishments",
    "sg:phone":"+41 91 745 48 87",
    "sg:postcode":"6596",
    "sg:province":"Ticino",
    "wof:name":"Notatecno Di Notarangelo Nicola Inst. Dipl. Fed.",
    "wof:placetype":"venue"
},
  "geometry": {"coordinates":[8.8649702072,46.1762008667],"type":"Point"}
}