{
  "type": "Feature",
  "properties": {
    "iso:country":"CH",
    "sg:address":"Chemin Des Labours 12",
    "sg:city":"Del\u00e9mont",
    "sg:orig_category":"G\u00fcterbef\u00f6rderung im Strassenverkehr",
    "sg:phone":"+41 32 422 72 73",
    "sg:postcode":"2800",
    "sg:province":"Jura",
    "wof:name":"Andr\u00e9 Fr\u00e9sard Transport De Bois",
    "wof:placetype":"venue"
},
  "geometry": {"coordinates":[7.349339962,47.3732795715],"type":"Point"}
}