{
  "type": "Feature",
  "properties": {
    "iso:country":"CH",
    "sg:address":"Loch 15",
    "sg:city":"Reisiswil",
    "sg:orig_category":"Allgemeiner Hoch U Tiefbau Erdbewegungsarbeiten",
    "sg:phone":"+41 61 401 42 38",
    "sg:postcode":"4919",
    "sg:province":"Bern",
    "wof:name":"Oser Hugo Ag",
    "wof:placetype":"venue"
},
  "geometry": {"coordinates":[7.559837,47.513035],"type":"Point"}
}