{
  "type": "Feature",
  "properties": {
    "iso:country":"CH",
    "sg:address":"Hauptstrasse 560",
    "sg:city":"Nesslau",
    "sg:orig_category":"Drogerien",
    "sg:phone":"+41 19300280",
    "sg:postcode":"9650",
    "sg:province":"St. Gallen",
    "wof:name":"Wiedmer Ag Drogerie Foto",
    "wof:placetype":"venue"
},
  "geometry": {"coordinates":[8.8078584671,47.3315544128],"type":"Point"}
}