{
  "type": "Feature",
  "properties": {
    "iso:country":"CH",
    "sg:address":"Badhaus",
    "sg:city":"Heimenschwand",
    "sg:orig_category":"Unclassifiable Establishments",
    "sg:postcode":"3615",
    "sg:province":"Bern",
    "wof:name":"Knecht Ag Naturnahe G\u00e4rten",
    "wof:placetype":"venue"
},
  "geometry": {"coordinates":[7.6969451904,46.8286209106],"type":"Point"}
}