{
  "type": "Feature",
  "properties": {
    "iso:country":"CH",
    "sg:address":"Place Du Midi 30",
    "sg:city":"Sion",
    "sg:orig_category":"Zahnarztpraxen",
    "sg:phone":"+41 22 347 78 18",
    "sg:postcode":"1950",
    "sg:province":"Valais",
    "wof:name":"Dr M\u00e9d.dent. Claude Antonioli M\u00e9decin-dentiste",
    "wof:placetype":"venue"
},
  "geometry": {"coordinates":[6.154791832,46.1921424866],"type":"Point"}
}