{
  "type": "Feature",
  "properties": {
    "iso:country":"CH",
    "sg:address":"1524",
    "sg:city":"Marnand",
    "sg:orig_category":"Allgemeiner Hoch U Tiefbau Strassenbau",
    "sg:phone":"+41 26 668 11 02",
    "sg:postcode":"1524",
    "sg:province":"Vaud",
    "wof:name":"Cuanoud A. Sa",
    "wof:placetype":"venue"
},
  "geometry": {"coordinates":[6.90241,46.76284],"type":"Point"}
}