{
  "type": "Feature",
  "properties": {
    "iso:country":"CH",
    "sg:address":"Ringstrasse 41",
    "sg:city":"Therwil",
    "sg:orig_category":"Allgemeiner Hoch U Tiefbau Gewinnung von Kies U Sand",
    "sg:phone":"+41 61 301 28 39",
    "sg:postcode":"4106",
    "sg:province":"Basel-Landschaft",
    "wof:name":"Walo Bertschinger Ag",
    "wof:placetype":"venue"
},
  "geometry": {"coordinates":[7.55327,47.504986],"type":"Point"}
}