{
  "type": "Feature",
  "properties": {
    "iso:country":"CH",
    "sg:address":"Paul Brand-strasse 5",
    "sg:city":"Olten",
    "sg:orig_category":"Interessenvertretungen U sonstige Vereinigungen",
    "sg:phone":"+41 62 296 40 80",
    "sg:postcode":"4600",
    "sg:province":"Solothurn",
    "wof:name":"Schweiz.faustballkomm.fako-ch",
    "wof:placetype":"venue"
},
  "geometry": {"coordinates":[7.9110789299,47.3435554504],"type":"Point"}
}