{
  "type": "Feature",
  "properties": {
    "iso:country":"CH",
    "sg:address":"Stradun 330",
    "sg:city":"Scuol",
    "sg:classifiers":[
        {
            "category":"Travel",
            "subcategory":"Hotels & Motels",
            "type":"Entertainment"
        }
    ],
    "sg:phone":"+41 81 833 39 05",
    "sg:postcode":"7550",
    "sg:province":"Graubunden",
    "sg:tags":[
        "hotels",
        "mit",
        "restaurant"
    ],
    "wof:name":"Hotel Belv\u00e9d\u00e8re",
    "wof:placetype":"venue"
},
  "geometry": {"coordinates":[9.8368577957,46.4951477051],"type":"Point"}
}