{
  "type": "Feature",
  "properties": {
    "iso:country":"CH",
    "sg:address":"Grauensteinweg 19",
    "sg:city":"Gelterkinden",
    "sg:orig_category":"Fotografisches Gewerbe U fotografische Laboratorien",
    "sg:phone":"+41 61 983 02 45",
    "sg:postcode":"4460",
    "sg:province":"Basel-Landschaft",
    "wof:name":"Foto-glasur-atelier Rufi",
    "wof:placetype":"venue"
},
  "geometry": {"coordinates":[7.8661780357,47.461025238],"type":"Point"}
}