{
  "type": "Feature",
  "properties": {
    "iso:country":"CH",
    "sg:address":"Anwandstrasse 7 8004 Z\u00fcrich. Postfach",
    "sg:city":"Z\u00fcrich",
    "sg:orig_category":"Pensionskassen",
    "sg:postcode":"8001",
    "sg:province":"Z\u00fcrich",
    "wof:name":"Personalf\u00fcrsorgestiftung Prifa",
    "wof:placetype":"venue"
},
  "geometry": {"coordinates":[8.524769783,47.3759346008],"type":"Point"}
}