{
  "type": "Feature",
  "properties": {
    "iso:country":"CH",
    "sg:address":"3232",
    "sg:city":"Ins",
    "sg:orig_category":"Primarschulen",
    "sg:phone":"+41 32 313 11 78",
    "sg:postcode":"3232",
    "sg:province":"Bern",
    "wof:name":"Primarschule Rebstock",
    "wof:placetype":"venue"
},
  "geometry": {"coordinates":[7.1058449745,47.0058517456],"type":"Point"}
}