{
  "type": "Feature",
  "properties": {
    "iso:country":"CH",
    "sg:address":"Parkterrasse 10",
    "sg:city":"Bern",
    "sg:classifiers":[
        {
            "category":"Travel",
            "subcategory":"Travel Agent",
            "type":"Entertainment"
        }
    ],
    "sg:postcode":"3001",
    "sg:province":"Bern",
    "wof:name":"Dulac Ag Best Western Hotel Flora",
    "wof:placetype":"venue"
},
  "geometry": {"coordinates":[8.3077402115,47.0502471924],"type":"Point"}
}