{
  "type": "Feature",
  "properties": {
    "iso:country":"CH",
    "sg:address":"3707",
    "sg:city":"D\u00e4rligen",
    "sg:orig_category":"Haltung von Rindern",
    "sg:postcode":"3707",
    "sg:province":"Bern",
    "wof:name":"Fleckviehzuchtgenossenschaft D\u00e4rligen",
    "wof:placetype":"venue"
},
  "geometry": {"coordinates":[7.8085451126,46.6625862122],"type":"Point"}
}