{
  "type": "Feature",
  "properties": {
    "iso:country":"CH",
    "sg:address":"Avenue De Marcelin 74",
    "sg:city":"Morges",
    "sg:orig_category":"Rebbau",
    "sg:phone":"+41 21 801 13 82",
    "sg:postcode":"1110",
    "sg:province":"Vaud",
    "wof:name":"Domaine Viticole De Valmont",
    "wof:placetype":"venue"
},
  "geometry": {"coordinates":[6.4912128448,46.5217857361],"type":"Point"}
}