{
  "type": "Feature",
  "properties": {
    "iso:country":"CH",
    "sg:address":"Chemin De Chandieu 29",
    "sg:city":"Lausanne",
    "sg:orig_category":"Sanit\u00e4rinstallation",
    "sg:phone":"+41 21 601 36 13",
    "sg:postcode":"1006",
    "sg:province":"Vaud",
    "wof:name":"Patrick Morier-genoud Installations Sanitaires",
    "wof:placetype":"venue"
},
  "geometry": {"coordinates":[6.6418380737,46.5121269226],"type":"Point"}
}