{
  "type": "Feature",
  "properties": {
    "iso:country":"CH",
    "sg:address":"Avenue Du Lac 3",
    "sg:city":"Versoix",
    "sg:orig_category":"Herstellung von Pumpen U Kompressoren Mechanische Werkst\u00e4tten",
    "sg:phone":"+41 22 755 24 23",
    "sg:postcode":"1290",
    "sg:province":"Gen\u00e8ve",
    "wof:name":"Charles Gabus & Cie Technique Du Vide",
    "wof:placetype":"venue"
},
  "geometry": {"coordinates":[6.1588292122,46.2874183655],"type":"Point"}
}