{
  "type": "Feature",
  "properties": {
    "iso:country":"CH",
    "sg:address":"Chemin Des Petits-bois 67",
    "sg:city":"Plan-les-ouates",
    "sg:orig_category":"Sonstige mit der Informatik verbundene T\u00e4tigkeiten",
    "sg:postcode":"1228",
    "sg:province":"Gen\u00e8ve",
    "wof:name":"Alteris Gmbh",
    "wof:placetype":"venue"
},
  "geometry": {"coordinates":[8.1796979904,47.4190139771],"type":"Point"}
}