{
  "type": "Feature",
  "properties": {
    "addr:full":"Via Del Sole 41 Muralto Ticino 6600",
    "addr:housenumber":"41",
    "addr:postcode":"6600",
    "addr:street":"Via Del Sole",
    "iso:country":"CH",
    "sg:address":"Via Del Sole 41",
    "sg:city":"Muralto",
    "sg:orig_category":"Architekturb\u00fcros",
    "sg:phone":"+41 91 743 35 67",
    "sg:postcode":"6600",
    "sg:province":"Ticino",
    "wof:name":"Fernando Pozzi Studio D'architettura",
    "wof:placetype":"venue"
},
  "geometry": {"coordinates":[8.803095,46.17543],"type":"Point"}
}