{
  "type": "Feature",
  "properties": {
    "iso:country":"CH",
    "sg:address":"Hohle",
    "sg:city":"Gurzelen",
    "sg:orig_category":"Schmieden",
    "sg:phone":"+41 33 442 17 33",
    "sg:postcode":"3663",
    "sg:province":"Bern",
    "wof:name":"Hans Peter D\u00e4hler Mechanische Schmiede",
    "wof:placetype":"venue"
},
  "geometry": {"coordinates":[7.6936078072,46.776260376],"type":"Point"}
}