{
  "type": "Feature",
  "properties": {
    "iso:country":"CH",
    "sg:address":"Weidring 19 6110 Wolhusen. Postfach",
    "sg:city":"Wolhusen",
    "sg:orig_category":"Reiseb\u00fcros U Reiseveranstalter",
    "sg:postcode":"6110",
    "sg:province":"Luzern",
    "wof:name":"Hes Travels Gmbh Reisen, Anl\u00e4sse Usw; Planung, Durchf\u00fchrung",
    "wof:placetype":"venue"
},
  "geometry": {"coordinates":[8.0713653564,47.0657577515],"type":"Point"}
}