{
  "type": "Feature",
  "properties": {
    "iso:country":"CH",
    "sg:address":"Route De L' Estivage 1580 Avenches Case Postale 46",
    "sg:city":"Avenches",
    "sg:orig_category":"Grosshandel mit Holz U Baustoffen Herstellung von Betonerzeugnissen f\u00fcr den Bau",
    "sg:phone":"+41 26 676 72 00",
    "sg:postcode":"1580",
    "sg:province":"Vaud",
    "wof:name":"Prebeton Sa",
    "wof:placetype":"venue"
},
  "geometry": {"coordinates":[7.0449399948,46.8874092102],"type":"Point"}
}