{
  "type": "Feature",
  "properties": {
    "addr:full":"Obernauerstrasse 96 Obernau Luzern 6012",
    "addr:housenumber":"96",
    "addr:postcode":"6012",
    "addr:street":"Obernauerstrasse",
    "iso:country":"CH",
    "sg:address":"Obernauerstrasse 96",
    "sg:city":"Obernau",
    "sg:orig_category":"Dachdeckerei Zimmerei, Dachdeckerei, Bauspenglerei U Abdichtung",
    "sg:phone":"+41 41 320 89 30",
    "sg:postcode":"6012",
    "sg:province":"Luzern",
    "wof:name":"Josef Mattmann Spenglerei & Flachbedachungen",
    "wof:placetype":"venue"
},
  "geometry": {"coordinates":[8.255031,47.033382],"type":"Point"}
}