{
  "type": "Feature",
  "properties": {
    "iso:country":"CH",
    "sg:address":"Dorfmatt 2a 6343 Rotkreuz. Postfach 214",
    "sg:city":"Rotkreuz",
    "sg:orig_category":"Herstellung von sonstigen elektrischen Ausr\u00fcstungen",
    "sg:phone":"+41 41 790 08 28",
    "sg:postcode":"6343",
    "sg:province":"Zug",
    "wof:name":"Reem Ag",
    "wof:placetype":"venue"
},
  "geometry": {"coordinates":[8.4310388565,47.1411933899],"type":"Point"}
}