{
  "type": "Feature",
  "properties": {
    "addr:full":"Rue Du Grand-ch\u00e9zard 4 Ch\u00e9zard-st-martin Neuch\u00e2tel 2054",
    "addr:housenumber":"4",
    "addr:postcode":"2054",
    "addr:street":"Rue Du Grand-Che\u0301Zard;Che\u0301Zard-St-Martin Neucha\u0302Tel",
    "iso:country":"CH",
    "sg:address":"Rue Du Grand-ch\u00e9zard 4",
    "sg:city":"Ch\u00e9zard-st-martin",
    "sg:orig_category":"Autogaragen Autospenglereien",
    "sg:phone":"+41 32 853 38 68",
    "sg:postcode":"2054",
    "sg:province":"Neuch\u00e2tel",
    "wof:name":"Ulrich Sch\u00fcrch Garage & Carrosserie",
    "wof:placetype":"venue"
},
  "geometry": {"coordinates":[6.917394,47.062805],"type":"Point"}
}