{
  "type": "Feature",
  "properties": {
    "iso:country":"CH",
    "sg:address":"Hauptstrasse 17",
    "sg:city":"D\u00fcdingen",
    "sg:orig_category":"Detailhandel mit Schreib U Papeteriewaren",
    "sg:phone":"+41 26 493 33 55",
    "sg:postcode":"3186",
    "sg:province":"Fribourg",
    "wof:name":"Sensler Papeterie+b\u00fcrobedarf B\u00fctikofer Evi Papeterie U. B\u00fcrobedarf; Verkauf",
    "wof:placetype":"venue"
},
  "geometry": {"coordinates":[7.1904258728,46.8477935791],"type":"Point"}
}