{
  "type": "Feature",
  "properties": {
    "iso:country":"CH",
    "sg:address":"Bergstrasse 8",
    "sg:city":"Volketswil",
    "sg:orig_category":"Allgemeiner Hoch U Tiefbau Allgemeiner Hochbau",
    "sg:phone":"+41 19452727",
    "sg:postcode":"8604",
    "sg:province":"Z\u00fcrich",
    "wof:name":"Weber Haus Gmbh & Co Kg, Rheinau-linx, Zweigniederlassung Volketswil",
    "wof:placetype":"venue"
},
  "geometry": {"coordinates":[8.68141,47.403465],"type":"Point"}
}