{
  "type": "Feature",
  "properties": {
    "addr:full":"N1 Bern-z\u00fcrich Z 58 4624 H\u00e4rkingen. Postfach Solothurn Solothurn 4502",
    "addr:housenumber":"58",
    "addr:postcode":"4624;4502",
    "addr:street":"Postfach",
    "iso:country":"CH",
    "sg:address":"N1 Bern-z\u00fcrich Z 58 4624 H\u00e4rkingen. Postfach",
    "sg:city":"Solothurn",
    "sg:orig_category":"Allgemeiner Hoch U Tiefbau ohne ausgepr\u00e4gten Schwerpunkt",
    "sg:phone":"+41 32 627 26 61",
    "sg:postcode":"4502",
    "sg:province":"Solothurn",
    "wof:name":"B\u00fcro F\u00fcr Nationalstrassen",
    "wof:placetype":"venue"
},
  "geometry": {"coordinates":[7.817022,47.309055],"type":"Point"}
}