{
  "type": "Feature",
  "properties": {
    "iso:country":"CH",
    "sg:address":"Frutigenstrasse 50",
    "sg:city":"Thun",
    "sg:orig_category":"Detailhandel mit Haustieren U zoologischem Bedarf",
    "sg:phone":"+41 33 336 34 92",
    "sg:postcode":"3604",
    "sg:province":"Bern",
    "wof:name":"Ruth's Futterl\u00e4deli F\u00fcr Alle Haustiere",
    "wof:placetype":"venue"
},
  "geometry": {"coordinates":[7.6262478828,46.7466964722],"type":"Point"}
}