{
  "type": "Feature",
  "properties": {
    "iso:country":"CH",
    "sg:address":"Lanzenmoosstrasse 8",
    "sg:city":"Schmerikon",
    "sg:orig_category":"Sportvereine Turnen Vereine Damen",
    "sg:phone":"+41 41 811 45 29",
    "sg:postcode":"8716",
    "sg:province":"St. Gallen",
    "wof:name":"Damenturnverein Schwyz",
    "wof:placetype":"venue"
},
  "geometry": {"coordinates":[8.6694259644,47.0137557983],"type":"Point"}
}