{
  "type": "Feature",
  "properties": {
    "iso:country":"CH",
    "sg:address":"Bachlettenstrasse 52",
    "sg:city":"Basel",
    "sg:orig_category":"Architektur U Ingenieurb\u00fcros",
    "sg:phone":"+41 61 281 22 54",
    "sg:postcode":"4054",
    "sg:province":"Basel-Stadt",
    "wof:name":"Schmidt + Partner, Bauingenieure Ag",
    "wof:placetype":"venue"
},
  "geometry": {"coordinates":[7.579093,47.548725],"type":"Point"}
}