{
  "type": "Feature",
  "properties": {
    "addr:full":"Ligornettesi Via Mastri Ligornetto Ticino 6853",
    "addr:postcode":"6853",
    "addr:street":"Via Mastri;Ticino",
    "iso:country":"CH",
    "sg:address":"Ligornettesi Via Mastri",
    "sg:city":"Ligornetto",
    "sg:classifiers":[
        {
            "category":"Bars & Pubs",
            "type":"Food & Drink"
        }
    ],
    "sg:postcode":"6853",
    "sg:province":"Ticino",
    "wof:name":"Energy Sa",
    "wof:placetype":"venue"
},
  "geometry": {"coordinates":[8.950937,45.862564],"type":"Point"}
}