{
  "type": "Feature",
  "properties": {
    "iso:country":"CH",
    "sg:address":"Teufener Strasse 15",
    "sg:city":"St.gallen",
    "sg:orig_category":"Softwareentwicklung U beratung",
    "sg:phone":"+41 71 221 10 71",
    "sg:postcode":"9000",
    "sg:province":"St. Gallen",
    "wof:name":"Csp Ag Competence Solutions Projects",
    "wof:placetype":"venue"
},
  "geometry": {"coordinates":[9.3708963394,47.4200935364],"type":"Point"}
}