{
  "type": "Feature",
  "properties": {
    "iso:country":"CH",
    "sg:address":"Nollenstrasse 25",
    "sg:city":"Appenzell",
    "sg:orig_category":"Grosshandel mit lebenden Tieren",
    "sg:phone":"+41 71 787 11 73",
    "sg:postcode":"9050",
    "sg:province":"Appenzell Innerhoden",
    "wof:name":"Alfred D\u00f6rig Viehhandel",
    "wof:placetype":"venue"
},
  "geometry": {"coordinates":[9.4208631516,47.323425293],"type":"Point"}
}