{
  "type": "Feature",
  "properties": {
    "iso:country":"CH",
    "sg:address":"Geissensteinring 26 6005 Luzern. Postfach",
    "sg:city":"Luzern",
    "sg:orig_category":"Saunas, Solarien, Fitnesszentren U \u00e4hnliches",
    "sg:postcode":"6002",
    "sg:province":"Luzern",
    "wof:name":"Donataccio Fitness",
    "wof:placetype":"venue"
},
  "geometry": {"coordinates":[9.0403766632,47.461391449],"type":"Point"}
}