{
  "type": "Feature",
  "properties": {
    "iso:country":"CH",
    "sg:address":"Steinlerstrasse 17",
    "sg:city":"Br\u00fctten",
    "sg:classifiers":[
        {
            "category":"Professional",
            "subcategory":"Employment Agencies",
            "type":"Services"
        }
    ],
    "sg:phone":"+41 52 345 26 85",
    "sg:postcode":"8311",
    "sg:province":"Z\u00fcrich",
    "sg:tags":[
        "personal",
        "u",
        "stellenvermittlung"
    ],
    "wof:name":"B\u00fcrgin Arthur W.",
    "wof:placetype":"venue"
},
  "geometry": {"coordinates":[8.6818990707,47.4737281799],"type":"Point"}
}