{
  "type": "Feature",
  "properties": {
    "iso:country":"CH",
    "sg:address":"Hauptstrasse 32",
    "sg:city":"H\u00f6lstein",
    "sg:orig_category":"Erzeugung U Erstbearbeitung von Aluminium Herstellung von Metallerzeugnissen ohne Maschinenbau",
    "sg:phone":"+41 41 670 00 24",
    "sg:postcode":"4434",
    "sg:province":"Basel-Landschaft",
    "wof:name":"Metallic Krummenacher Aluminiumtechnik",
    "wof:placetype":"venue"
},
  "geometry": {"coordinates":[8.2766227722,46.9407806396],"type":"Point"}
}