{
  "type": "Feature",
  "properties": {
    "iso:country":"CH",
    "sg:address":"S\u00fcdstrasse 4a",
    "sg:city":"M\u00fcnsingen",
    "sg:orig_category":"Non-Classified Establishments",
    "sg:postcode":"3110",
    "sg:province":"Bern",
    "wof:name":"Willy Korn Ag",
    "wof:placetype":"venue"
},
  "geometry": {"coordinates":[7.5627040863,46.8682289124],"type":"Point"}
}