{
  "type": "Feature",
  "properties": {
    "iso:country":"CH",
    "sg:address":"Mormont",
    "sg:city":"Courchavon",
    "sg:orig_category":"Zimmerei, Dachdeckerei, Bauspenglerei U Abdichtung",
    "sg:phone":"+41 32 466 42 68",
    "sg:postcode":"2922",
    "sg:province":"Jura",
    "wof:name":"Meyer Georges",
    "wof:placetype":"venue"
},
  "geometry": {"coordinates":[7.0386400223,47.439540863],"type":"Point"}
}