{
  "type": "Feature",
  "properties": {
    "iso:country":"CH",
    "sg:address":"Rue Du Cheminet 10",
    "sg:city":"Yverdon-les-bains",
    "sg:orig_category":"D\u00e4mmung gegen K\u00e4lte, W\u00e4rme, Schall U Ersch\u00fctterung",
    "sg:phone":"+41 79 608 33 15",
    "sg:postcode":"1400",
    "sg:province":"Vaud",
    "wof:name":"Mattaflex Bautenschutz Gmbh",
    "wof:placetype":"venue"
},
  "geometry": {"coordinates":[9.4700660706,47.17237854],"type":"Point"}
}