{
  "type": "Feature",
  "properties": {
    "iso:country":"CH",
    "sg:address":"M\u00fcnsterstrasse 2 6210 Sursee. Postfach 316",
    "sg:city":"Sursee",
    "sg:orig_category":"Druck ohne Zeitungsdruck Offsetdruck",
    "sg:phone":"+41 41 921 33 44",
    "sg:postcode":"6210",
    "sg:province":"Luzern",
    "wof:name":"Druckerei Kamm Ag",
    "wof:placetype":"venue"
},
  "geometry": {"coordinates":[8.112238884,47.1715583801],"type":"Point"}
}