{
  "type": "Feature",
  "properties": {
    "iso:country":"CH",
    "sg:address":"Oeligass",
    "sg:city":"W\u00f6lflinswil",
    "sg:orig_category":"Detailhandel mit Waren verschiedener Art, Hauptrichtung Nahrungsmittel",
    "sg:phone":"+41 52 264 26 16",
    "sg:postcode":"5063",
    "sg:province":"Aargau",
    "wof:name":"Volg Detailhandels Ag",
    "wof:placetype":"venue"
},
  "geometry": {"coordinates":[8.0005998611,47.4607391357],"type":"Point"}
}