{
  "type": "Feature",
  "properties": {
    "iso:country":"CH",
    "sg:address":"Route De L'etraz",
    "sg:city":"Vich-coinsins",
    "sg:orig_category":"Grosshandel mit Bekleidung Grosshandel mit Sportartikeln",
    "sg:phone":"+41 22 344 67 38",
    "sg:postcode":"1267",
    "sg:province":"Vaud",
    "wof:name":"Fastyle Sa Import-export Sportswear",
    "wof:placetype":"venue"
},
  "geometry": {"coordinates":[6.1379299164,46.2090492249],"type":"Point"}
}