{
  "type": "Feature",
  "properties": {
    "iso:country":"CH",
    "sg:address":"Tagelswangerstrasse 7",
    "sg:city":"Effretikon",
    "sg:orig_category":"Chemische Reinigung W\u00e4schereien",
    "sg:phone":"+41 52 343 95 91",
    "sg:postcode":"8307",
    "sg:province":"Z\u00fcrich",
    "wof:name":"Jagoda Milicev Chem.reinigung & Waschsalon",
    "wof:placetype":"venue"
},
  "geometry": {"coordinates":[8.684542,47.426292],"type":"Point"}
}