{
  "type": "Feature",
  "properties": {
    "iso:country":"CH",
    "sg:address":"Salita Dei Frati 5",
    "sg:city":"Lugano",
    "sg:classifiers":[
        {
            "category":"Travel",
            "subcategory":"Hotels & Motels",
            "type":"Entertainment"
        }
    ],
    "sg:phone":"+41 91 649 96 22",
    "sg:postcode":"6900",
    "sg:province":"Ticino",
    "sg:tags":[
        "hotels",
        "mit",
        "restaurant"
    ],
    "wof:name":"Rast, Werner E Silvia",
    "wof:placetype":"venue"
},
  "geometry": {"coordinates":[8.9493904114,46.0077285767],"type":"Point"}
}