{
  "type": "Feature",
  "properties": {
    "iso:country":"CH",
    "sg:address":"Marktgasse 3",
    "sg:city":"D\u00fcbendorf",
    "sg:orig_category":"Non-Classified Establishments",
    "sg:postcode":"8600",
    "sg:province":"Z\u00fcrich",
    "wof:name":"Mercatino Italiano Comestibles Lebensmittel",
    "wof:placetype":"venue"
},
  "geometry": {"coordinates":[8.6170148849,47.3977241516],"type":"Point"}
}