{
  "type": "Feature",
  "properties": {
    "iso:country":"CH",
    "sg:address":"Rossmarktplatz 15",
    "sg:city":"Solothurn",
    "sg:orig_category":"Handel mit Motorr\u00e4dern, Teilen U Zubeh\u00f6r Instandhaltung U Reparatur von Motorr\u00e4dern",
    "sg:phone":"+41 32 622 18 55",
    "sg:postcode":"4500",
    "sg:province":"Solothurn",
    "wof:name":"Hauser Ren\u00e9",
    "wof:placetype":"venue"
},
  "geometry": {"coordinates":[7.538105011,47.2046127319],"type":"Point"}
}