{
  "type": "Feature",
  "properties": {
    "iso:country":"CH",
    "sg:address":"Aspermontstrasse 1",
    "sg:city":"Chur",
    "sg:orig_category":"Finanzierungsinstitutionen",
    "sg:postcode":"7000",
    "sg:province":"Graubunden",
    "wof:name":"W\u00fcrth Phoenix International B.v., 's-hertogenbosch, Zweigniederlassung Chur",
    "wof:placetype":"venue"
},
  "geometry": {"coordinates":[9.528719902,46.8606681824],"type":"Point"}
}