{
  "type": "Feature",
  "properties": {
    "iso:country":"CH",
    "sg:address":"Sans Adresse",
    "sg:city":"Misery-courtion",
    "sg:orig_category":"Detailhandel mit Milcherzeugnissen U Eiern Verwertung von Milch",
    "sg:phone":"+41 26 475 50 67",
    "sg:postcode":"1721",
    "sg:province":"Fribourg",
    "wof:name":"Perler Marc",
    "wof:placetype":"venue"
},
  "geometry": {"coordinates":[7.0656499863,46.8526954651],"type":"Point"}
}