{
  "type": "Feature",
  "properties": {
    "iso:country":"CH",
    "sg:address":"Brunnweg 4",
    "sg:city":"Lupfig",
    "sg:orig_category":"Datenverarbeitungsdienste Sonstige mit der Informatik verbundene T\u00e4tigkeiten",
    "sg:phone":"+41 56 444 00 15",
    "sg:postcode":"5242",
    "sg:province":"Aargau",
    "wof:name":"Creativ Informatik Ag",
    "wof:placetype":"venue"
},
  "geometry": {"coordinates":[8.199315,47.442539],"type":"Point"}
}