{
  "type": "Feature",
  "properties": {
    "iso:country":"CH",
    "sg:address":"Rebsteinstr. 400",
    "sg:city":"Egliswil",
    "sg:orig_category":"Unternehmensberatung",
    "sg:postcode":"5704",
    "sg:province":"Aargau",
    "wof:name":"Gk Consult Raudies G.",
    "wof:placetype":"venue"
},
  "geometry": {"coordinates":[8.18638134,47.3523826599],"type":"Point"}
}