{
  "type": "Feature",
  "properties": {
    "iso:country":"CH",
    "sg:address":"Im J\u00f6chler 6340 Baar. Postfach 2841",
    "sg:city":"Baar",
    "sg:orig_category":"Grosshandel mit Blumen U Pflanzen Herstellung von D\u00fcngemitteln U Stickstoffverbindungen",
    "sg:phone":"+41 41 761 35 21",
    "sg:postcode":"6342",
    "sg:province":"Zug",
    "wof:name":"Trachslag Ag",
    "wof:placetype":"venue"
},
  "geometry": {"coordinates":[8.5252799988,47.2036247253],"type":"Point"}
}