{
  "type": "Feature",
  "properties": {
    "iso:country":"CH",
    "sg:address":"D\u00fcbendorfstrasse 22",
    "sg:city":"D\u00fcbendorf",
    "sg:orig_category":"Herstellung von Teppichen",
    "sg:phone":"+41 17372015",
    "sg:postcode":"8600",
    "sg:province":"Z\u00fcrich",
    "wof:name":"Rothlin-bodenbel\u00e4ge",
    "wof:placetype":"venue"
},
  "geometry": {"coordinates":[8.435956955,47.3517189026],"type":"Point"}
}