{
  "type": "Feature",
  "properties": {
    "iso:country":"CH",
    "sg:address":"Coulon Rue 10",
    "sg:city":"Neuch\u00e2tel",
    "sg:orig_category":"Erbringung von sonstigen Dienstleistungen f\u00fcr Unterhaltung, Erholung U Freizeit",
    "sg:phone":"+41 32 725 68 68",
    "sg:postcode":"2000",
    "sg:province":"Neuch\u00e2tel",
    "wof:name":"Bureau Artistique Plateau Libre, Grillon Georges",
    "wof:placetype":"venue"
},
  "geometry": {"coordinates":[6.9381799698,46.9933395386],"type":"Point"}
}