{
  "type": "Feature",
  "properties": {
    "iso:country":"CH",
    "sg:address":"Optingenstrasse 18",
    "sg:city":"Bern",
    "sg:orig_category":"Arztpraxen",
    "sg:phone":"+41 31 331 32 22",
    "sg:postcode":"3013",
    "sg:province":"Bern",
    "wof:name":"Dr.med.rudolf M\u00fcller Spezialarzt Fmh",
    "wof:placetype":"venue"
},
  "geometry": {"coordinates":[7.449901,46.954765],"type":"Point"}
}