{
  "type": "Feature",
  "properties": {
    "iso:country":"CH",
    "sg:address":"Schindellegistrasse 73 Pf\u00e4ffikon Sz",
    "sg:city":"Freienbach",
    "sg:orig_category":"Architektur U Ingenieurb\u00fcros Architekturb\u00fcros",
    "sg:phone":"+41 55 415 30 80",
    "sg:postcode":"8807",
    "sg:province":"Schwyz",
    "wof:name":"Wiserliving Immobilien Treuhand Ag",
    "wof:placetype":"venue"
},
  "geometry": {"coordinates":[8.757775,47.206306],"type":"Point"}
}