{
  "type": "Feature",
  "properties": {
    "iso:country":"CH",
    "sg:address":"Stauffacherstrasse 126p",
    "sg:city":"Bern",
    "sg:orig_category":"Unternehmensberatung",
    "sg:phone":"+41 31 839 71 71",
    "sg:postcode":"3013",
    "sg:province":"Bern",
    "wof:name":"Ec Business Service Ag",
    "wof:placetype":"venue"
},
  "geometry": {"coordinates":[7.4640750885,46.9691352844],"type":"Point"}
}