{
  "type": "Feature",
  "properties": {
    "iso:country":"CH",
    "sg:address":"Hennimoosstrasse 34",
    "sg:city":"Diepoldsau",
    "sg:orig_category":"Maschinenbau Mechanische Werkst\u00e4tten",
    "sg:phone":"+41 17372520",
    "sg:postcode":"9444",
    "sg:province":"St. Gallen",
    "wof:name":"Wettstein Ren\u00e9 Ag",
    "wof:placetype":"venue"
},
  "geometry": {"coordinates":[8.4284582138,47.3662643433],"type":"Point"}
}