{
  "type": "Feature",
  "properties": {
    "addr:full":"Avenue Des Alpes 115 Neuch\u00e2tel Neuch\u00e2tel 2000",
    "addr:housenumber":"115",
    "addr:postcode":"2000",
    "addr:street":"Avenue Des Alpes",
    "iso:country":"CH",
    "sg:address":"Avenue Des Alpes 115",
    "sg:city":"Neuch\u00e2tel",
    "sg:orig_category":"Architektur U Ingenieurb\u00fcros Softwareentwicklung U beratung",
    "sg:phone":"+41 32 724 78 05",
    "sg:postcode":"2000",
    "sg:province":"Neuch\u00e2tel",
    "wof:name":"Decontrade Sa",
    "wof:placetype":"venue"
},
  "geometry": {"coordinates":[6.918768,46.99472],"type":"Point"}
}