{
  "type": "Feature",
  "properties": {
    "iso:country":"CH",
    "sg:address":"Magazzini Generali Via 5",
    "sg:city":"Balerna",
    "sg:orig_category":"Architektur U Ingenieurb\u00fcros",
    "sg:phone":"+41 91 682 99 57",
    "sg:postcode":"6828",
    "sg:province":"Ticino",
    "wof:name":"Ostinelli Diego",
    "wof:placetype":"venue"
},
  "geometry": {"coordinates":[9.01763,45.839661],"type":"Point"}
}