{
  "type": "Feature",
  "properties": {
    "addr:full":"Zentweg 25 Bern Bern 3030",
    "addr:housenumber":"25",
    "addr:postcode":"3030",
    "addr:street":"Zentweg",
    "iso:country":"CH",
    "sg:address":"Zentweg 25",
    "sg:city":"Bern",
    "sg:orig_category":"Internet, Sonstige Internetdienstleistungen",
    "sg:phone":"+41 31 338 72 86",
    "sg:postcode":"3030",
    "sg:province":"Bern",
    "wof:name":"Yellowworld Ag",
    "wof:placetype":"venue"
},
  "geometry": {"coordinates":[7.476165,46.955601],"type":"Point"}
}