{
  "type": "Feature",
  "properties": {
    "iso:country":"CH",
    "sg:address":"Vieux-ch\u00eanes Route Des 2 1700 Fribourg. Postfach",
    "sg:city":"Freiburg",
    "sg:orig_category":"Finanzierungsinstitutionen",
    "sg:postcode":"1700",
    "sg:province":"Fribourg",
    "wof:name":"Ip Invest Prom S\u00e0rl",
    "wof:placetype":"venue"
},
  "geometry": {"coordinates":[4.4258608818,50.9269294739],"type":"Point"}
}