{
  "type": "Feature",
  "properties": {
    "iso:country":"CH",
    "sg:address":"Speerstrasse 1 8865 Bilten. Postfach 52",
    "sg:city":"Bilten",
    "sg:orig_category":"Allgemeiner Hoch U Tiefbau",
    "sg:phone":"+41 55 615 15 55",
    "sg:postcode":"8865",
    "sg:province":"Glarus",
    "wof:name":"Feldmann Ag, Bauunternehmung Bilten",
    "wof:placetype":"venue"
},
  "geometry": {"coordinates":[9.02852,47.152168],"type":"Point"}
}