{
  "type": "Feature",
  "properties": {
    "iso:country":"CH",
    "sg:address":"Marktstrasse 11",
    "sg:city":"Sarnen",
    "sg:orig_category":"Sportvereine Ballsport Tischtennis",
    "sg:phone":"+41 41 660 57 07",
    "sg:postcode":"6060",
    "sg:province":"Obwalden",
    "wof:name":"Ttc Italia Sarnen",
    "wof:placetype":"venue"
},
  "geometry": {"coordinates":[8.2489118576,46.897441864],"type":"Point"}
}