{
  "type": "Feature",
  "properties": {
    "iso:country":"CH",
    "sg:address":"Obere Bahnhofstrasse 17",
    "sg:city":"Mellingen",
    "sg:orig_category":"Feuerwehr",
    "sg:postcode":"5507",
    "sg:province":"Aargau",
    "wof:name":"Sprimo K\u00e4mpf M.",
    "wof:placetype":"venue"
},
  "geometry": {"coordinates":[8.2720108032,47.4296150208],"type":"Point"}
}