{
  "type": "Feature",
  "properties": {
    "iso:country":"CH",
    "sg:address":"Juchstrasse 12",
    "sg:city":"Magden",
    "sg:orig_category":"Religi\u00f6se Vereinigungen divers Vereine Gemeinn\u00fctzige",
    "sg:phone":"+41 61 841 29 94",
    "sg:postcode":"4312",
    "sg:province":"Aargau",
    "wof:name":"Christkath.hilfswerk D.schweiz",
    "wof:placetype":"venue"
},
  "geometry": {"coordinates":[7.8104538918,47.5298805237],"type":"Point"}
}