{
  "type": "Feature",
  "properties": {
    "iso:country":"CH",
    "sg:address":"Route Des Vieux-ch\u00eanes 2 1700 Fribourg Case Postale 32",
    "sg:city":"Fribourg",
    "sg:orig_category":"Elektroinstallation",
    "sg:phone":"+41 26 481 54 54",
    "sg:postcode":"1707",
    "sg:province":"Fribourg",
    "wof:name":"Pro-inel Sa",
    "wof:placetype":"venue"
},
  "geometry": {"coordinates":[7.177382946,46.8107833862],"type":"Point"}
}