{
  "type": "Feature",
  "properties": {
    "iso:country":"CH",
    "sg:address":"Augustinergasse 2 4051 Basel. Postfach",
    "sg:city":"Basel",
    "sg:orig_category":"Museen",
    "sg:phone":"+41 61 266 55 00",
    "sg:postcode":"4001",
    "sg:province":"Basel-Stadt",
    "wof:name":"Museum Der Kulturen Basel",
    "wof:placetype":"venue"
},
  "geometry": {"coordinates":[7.5903081894,47.5577163696],"type":"Point"}
}