{
  "type": "Feature",
  "properties": {
    "iso:country":"CH",
    "sg:address":"Wangenerstrasse 27",
    "sg:city":"Effretikon",
    "sg:orig_category":"Stukkateurgewerbe, Gipserei U Verputzerei",
    "sg:postcode":"8307",
    "sg:province":"Z\u00fcrich",
    "wof:name":"Giustizieri & Partner",
    "wof:placetype":"venue"
},
  "geometry": {"coordinates":[8.3197431564,47.1378860474],"type":"Point"}
}