{
  "type": "Feature",
  "properties": {
    "iso:country":"CH",
    "sg:address":"Bahnhofstrasse 44",
    "sg:city":"Dietlikon",
    "sg:orig_category":"Kauf U Verkauf von Immobilien auf eigene Rechnung",
    "sg:phone":"+41 18333620",
    "sg:postcode":"8305",
    "sg:province":"Z\u00fcrich",
    "wof:name":"Areto Ag",
    "wof:placetype":"venue"
},
  "geometry": {"coordinates":[8.6184310913,47.4233016968],"type":"Point"}
}