{
  "type": "Feature",
  "properties": {
    "iso:country":"CH",
    "sg:address":"Fontannins Chemin Des 19",
    "sg:city":"Epalinges",
    "sg:orig_category":"Grosshandel mit sonstigen Gebrauchs U Verbrauchsg\u00fctern",
    "sg:postcode":"1066",
    "sg:province":"Vaud",
    "wof:name":"Diafin Sa",
    "wof:placetype":"venue"
},
  "geometry": {"coordinates":[6.6612420082,46.5566520691],"type":"Point"}
}