{
  "type": "Feature",
  "properties": {
    "iso:country":"CH",
    "sg:address":"Gabris",
    "sg:city":"Hosenruck",
    "sg:orig_category":"Verkehrs- and Tourismusb\u00fcros",
    "sg:phone":"+41 71 949 09 49",
    "sg:postcode":"9515",
    "sg:province":"Thurgau",
    "wof:name":"Versch\u00f6nerungsverein Am Nollen",
    "wof:placetype":"venue"
},
  "geometry": {"coordinates":[9.122209549,47.4905891418],"type":"Point"}
}