{
  "type": "Feature",
  "properties": {
    "iso:country":"CH",
    "sg:address":"Breitwies 7",
    "sg:city":"Warth",
    "sg:orig_category":"Softwareentwicklung U beratung",
    "sg:phone":"+41 52 747 21 63",
    "sg:postcode":"8532",
    "sg:province":"Thurgau",
    "wof:name":"Idrb Informatikdienste Biedermann R. Gmbh",
    "wof:placetype":"venue"
},
  "geometry": {"coordinates":[8.8764152527,47.583316803],"type":"Point"}
}