{
  "type": "Feature",
  "properties": {
    "iso:country":"CH",
    "sg:address":"Route De La Gare 4",
    "sg:city":"Sugiez",
    "sg:orig_category":"Tin Items, Tinwork, Artisans'",
    "sg:phone":"+41 26 673 15 15",
    "sg:postcode":"1786",
    "sg:province":"Fribourg",
    "wof:name":"Zinn-stube Ag",
    "wof:placetype":"venue"
},
  "geometry": {"coordinates":[7.1186861992,46.9643745422],"type":"Point"}
}