{
  "type": "Feature",
  "properties": {
    "iso:country":"CH",
    "sg:address":"Boulevard Des Philosophes 14",
    "sg:city":"Gen\u00e8ve",
    "sg:orig_category":"Detailhandel mit Sportartikeln Herstellung von Reiseartikeln, Leder U Sattlerwaren",
    "sg:phone":"+41 33 822 22 00",
    "sg:postcode":"1205",
    "sg:province":"Gen\u00e8ve",
    "wof:name":"Rudolf Glaus Sattlerei",
    "wof:placetype":"venue"
},
  "geometry": {"coordinates":[7.8832502365,46.6986885071],"type":"Point"}
}