{
  "type": "Feature",
  "properties": {
    "iso:country":"CH",
    "sg:address":"Chemin De La Belle Luce 4",
    "sg:city":"Bulle",
    "sg:orig_category":"Tierarztpraxis",
    "sg:phone":"+41 26 912 20 22",
    "sg:postcode":"1630",
    "sg:province":"Fribourg",
    "wof:name":"Drs M\u00e9d.v\u00e9t. Deillon & Gremaud M\u00e9decins V\u00e9t\u00e9rinaires",
    "wof:placetype":"venue"
},
  "geometry": {"coordinates":[7.0701260567,46.6224517822],"type":"Point"}
}