{
  "type": "Feature",
  "properties": {
    "iso:country":"CH",
    "sg:address":"Rue De La Navigation 21",
    "sg:city":"Gen\u00e8ve",
    "sg:orig_category":"Elektroinstallation",
    "sg:phone":"+41 22 348 45 86",
    "sg:postcode":"1201",
    "sg:province":"Gen\u00e8ve",
    "wof:name":"Pieraccini J.-f.",
    "wof:placetype":"venue"
},
  "geometry": {"coordinates":[6.1464829445,46.2124404907],"type":"Point"}
}