{
  "type": "Feature",
  "properties": {
    "iso:country":"CH",
    "sg:address":"M\u00fchlegasse 1 8152 Opfikon. Postfach",
    "sg:city":"Glattbrugg",
    "sg:orig_category":"Grosshandel mit Bekleidung Grosshandel mit Textilien",
    "sg:phone":"+41 18103128",
    "sg:postcode":"8152",
    "sg:province":"Z\u00fcrich",
    "wof:name":"Jenny Fashion",
    "wof:placetype":"venue"
},
  "geometry": {"coordinates":[8.5724000931,47.4307746887],"type":"Point"}
}