{
  "type": "Feature",
  "properties": {
    "iso:country":"CH",
    "sg:address":"Rue Du Milieu 5",
    "sg:city":"Yverdon",
    "sg:classifiers":[
        {
            "category":"Banks & Credit Unions",
            "subcategory":"Bank",
            "type":"Services"
        }
    ],
    "sg:phone":"+41 24 424 10 10",
    "sg:postcode":"1400",
    "sg:province":"Vaud",
    "wof:name":"Caisse D'epargne Et De Pr\u00e9voyance D'yverdon",
    "wof:placetype":"venue"
},
  "geometry": {"coordinates":[6.6414,46.77869],"type":"Point"}
}