{
  "type": "Feature",
  "properties": {
    "iso:country":"CH",
    "sg:address":"Pedemonte Via",
    "sg:city":"Bellinzona",
    "sg:orig_category":"Interessenvertretungen",
    "sg:postcode":"6500",
    "sg:province":"Ticino",
    "wof:name":"La Bacchica Bellinzonese",
    "wof:placetype":"venue"
},
  "geometry": {"coordinates":[9.035900116,46.2008399963],"type":"Point"}
}