{
  "type": "Feature",
  "properties": {
    "iso:country":"CH",
    "sg:address":"C.f. Bally-strasse 34",
    "sg:city":"Sch\u00f6nenwerd",
    "sg:orig_category":"Herstellung von Sanit\u00e4rkeramik",
    "sg:phone":"+41 62 849 04 07",
    "sg:postcode":"5012",
    "sg:province":"Solothurn",
    "wof:name":"Buzzi Cerasan Gmbh",
    "wof:placetype":"venue"
},
  "geometry": {"coordinates":[8.0053396225,47.3739776611],"type":"Point"}
}