{
  "type": "Feature",
  "properties": {
    "iso:country":"CH",
    "sg:address":"Gutrainstrasse 7",
    "sg:city":"Bassersdorf",
    "sg:orig_category":"Wirtschaftspr\u00fcfung, Steuerberatung U Treuhand",
    "sg:phone":"+41 55 210 33 12",
    "sg:postcode":"8303",
    "sg:province":"Z\u00fcrich",
    "wof:name":"Siegrist Treuhand Ag",
    "wof:placetype":"venue"
},
  "geometry": {"coordinates":[8.8158483505,47.2262763977],"type":"Point"}
}