{
  "type": "Feature",
  "properties": {
    "iso:country":"CH",
    "sg:address":"W\u00fcrzgrabenstrasse 5",
    "sg:city":"Z\u00fcrich",
    "sg:classifiers":[
        {
            "category":"Shopping",
            "subcategory":"Stationery & Office Supplies",
            "type":"Retail Goods"
        }
    ],
    "sg:phone":"+41 14394949",
    "sg:postcode":"8048",
    "sg:province":"Z\u00fcrich",
    "sg:tags":[
        "furniture"
    ],
    "wof:name":"B\u00fcro-f\u00fcrrer Ag Office Design",
    "wof:placetype":"venue"
},
  "geometry": {"coordinates":[8.494849205,47.3925209045],"type":"Point"}
}