{
  "type": "Feature",
  "properties": {
    "addr:full":"Sonnenstrasse Ramsen Schaffhausen 8262",
    "addr:postcode":"8262",
    "addr:street":"Sonnenstrasse",
    "iso:country":"CH",
    "sg:address":"Sonnenstrasse",
    "sg:city":"Ramsen",
    "sg:orig_category":"Bezirks, Sekundar, Realschulen, Oberstufe der Primarschulen",
    "sg:phone":"+41 81 756 37 75",
    "sg:postcode":"8262",
    "sg:province":"Schaffhausen",
    "wof:name":"Realschule",
    "wof:placetype":"venue"
},
  "geometry": {"coordinates":[9.462694,47.16938],"type":"Point"}
}