{
  "type": "Feature",
  "properties": {
    "iso:country":"CH",
    "sg:address":"Rossmarktplatz 7",
    "sg:city":"Solothurn",
    "sg:orig_category":"RESTAURANTS: TEA-ROOMS",
    "sg:postcode":"4500",
    "sg:province":"Solothurn",
    "wof:name":"Mm Sako Gmbh",
    "wof:placetype":"venue"
},
  "geometry": {"coordinates":[7.5373978615,47.2047042847],"type":"Point"}
}