{
  "type": "Feature",
  "properties": {
    "iso:country":"CH",
    "sg:address":"Hauptstrasse 55",
    "sg:city":"Zurzach",
    "sg:orig_category":"Gesundheitswesen",
    "sg:phone":"+41 56 249 33 10",
    "sg:postcode":"5330",
    "sg:province":"Aargau",
    "wof:name":"Physiotherapie De Caes",
    "wof:placetype":"venue"
},
  "geometry": {"coordinates":[8.293217659,47.5878982544],"type":"Point"}
}