{
  "type": "Feature",
  "properties": {
    "iso:country":"CH",
    "sg:address":"St. Gallerstrasse 20",
    "sg:city":"Rorschach",
    "sg:orig_category":"Detailhandel mit Musikinstrumenten Detailhandel mit elektrischen Haushalts-,Radio U Fernsehger\u00e4ten s",
    "sg:phone":"+41 71 841 21 70",
    "sg:postcode":"9400",
    "sg:province":"St. Gallen",
    "wof:name":"Wachter-rutz & Co",
    "wof:placetype":"venue"
},
  "geometry": {"coordinates":[9.4861774445,47.4787254333],"type":"Point"}
}