{
  "type": "Feature",
  "properties": {
    "iso:country":"CH",
    "sg:address":"Hegibachstrasse 62",
    "sg:city":"Z\u00fcrich",
    "sg:orig_category":"Innenarchitekturb\u00fcros Innendekorationsateliers",
    "sg:phone":"+41 13839901",
    "sg:postcode":"8032",
    "sg:province":"Z\u00fcrich",
    "wof:name":"Walter Eschle Innendekorationen",
    "wof:placetype":"venue"
},
  "geometry": {"coordinates":[8.5649261475,47.3634605408],"type":"Point"}
}