{
  "type": "Feature",
  "properties": {
    "iso:country":"CH",
    "sg:address":"Maderno Via 9",
    "sg:city":"Lugano",
    "sg:orig_category":"Kauf U Verkauf von Immobilien auf eigene Rechnung",
    "sg:postcode":"6900",
    "sg:province":"Ticino",
    "wof:name":"Azimut International Gestioni Immobiliari Sa",
    "wof:placetype":"venue"
},
  "geometry": {"coordinates":[8.9549045563,46.0097045898],"type":"Point"}
}