{
  "type": "Feature",
  "properties": {
    "iso:country":"CH",
    "sg:address":"M\u00fchlematthof 12",
    "sg:city":"Boniswil",
    "sg:orig_category":"Politische Parteien FDP",
    "sg:phone":"+41 62 777 10 51",
    "sg:postcode":"5706",
    "sg:province":"Aargau",
    "wof:name":"Fdp Ortspartei Boniswil",
    "wof:placetype":"venue"
},
  "geometry": {"coordinates":[8.1850299835,47.3172454834],"type":"Point"}
}