{
  "type": "Feature",
  "properties": {
    "iso:country":"CH",
    "sg:address":"Hauptstrasse 59",
    "sg:city":"Eiken",
    "sg:orig_category":"RESTAURANTS: TEA-ROOMS",
    "sg:postcode":"5074",
    "sg:province":"Aargau",
    "wof:name":"Cimesa Handels Ag",
    "wof:placetype":"venue"
},
  "geometry": {"coordinates":[7.9893579483,47.5321464539],"type":"Point"}
}