{
  "type": "Feature",
  "properties": {
    "iso:country":"CH",
    "sg:address":"1489",
    "sg:city":"Murist",
    "sg:orig_category":"Sportvereine Sch\u00fctzen",
    "sg:postcode":"1489",
    "sg:province":"Fribourg",
    "wof:name":"St\u00e9 De Tir Murist-la Molli\u00e8re",
    "wof:placetype":"venue"
},
  "geometry": {"coordinates":[6.8069529533,46.7899894714],"type":"Point"}
}