{
  "type": "Feature",
  "properties": {
    "addr:full":"Viale Giuseppe Motta 36a 6500 Bellinzona. Postfach Bellinzona Ticino 6501",
    "addr:housenumber":"36a",
    "addr:postcode":"6500 bellinzona. postfach;6501",
    "addr:street":"Viale Giuseppe Motta",
    "iso:country":"CH",
    "sg:address":"Viale Giuseppe Motta 36a 6500 Bellinzona. Postfach",
    "sg:city":"Bellinzona",
    "sg:orig_category":"Advokaturb\u00fcros",
    "sg:phone":"+41 55 410 54 24",
    "sg:postcode":"6501",
    "sg:province":"Ticino",
    "wof:name":"Rudolf W. Boxler Advokaturb\u00fcro",
    "wof:placetype":"venue"
},
  "geometry": {"coordinates":[8.777198,47.199459],"type":"Point"}
}