{
  "type": "Feature",
  "properties": {
    "iso:country":"CH",
    "sg:address":"Hartbertstrasse 1",
    "sg:city":"Chur",
    "sg:orig_category":"Sonstige Kultur U Unterhaltungseinrichtungen",
    "sg:postcode":"7000",
    "sg:province":"Graubunden",
    "wof:name":"Casinos International Investment Ag",
    "wof:placetype":"venue"
},
  "geometry": {"coordinates":[8.7796049118,47.2022857666],"type":"Point"}
}