{
  "type": "Feature",
  "properties": {
    "iso:country":"CH",
    "sg:address":"6919",
    "sg:city":"Carabietta",
    "sg:orig_category":"Reparatur von Uhren U Schmuck",
    "sg:phone":"+41 91 995 13 32",
    "sg:postcode":"6919",
    "sg:province":"Ticino",
    "wof:name":"Francesco Bernasconi Orologiaio",
    "wof:placetype":"venue"
},
  "geometry": {"coordinates":[8.9038295746,45.9764595032],"type":"Point"}
}