{
  "type": "Feature",
  "properties": {
    "iso:country":"CH",
    "sg:address":"B\u00fcndnerstrasse 30 4055 Basel. Postfach",
    "sg:city":"Basel",
    "sg:orig_category":"Non-Classified Establishments",
    "sg:phone":"+41 61 302 59 89",
    "sg:postcode":"4051",
    "sg:province":"Basel-Stadt",
    "wof:name":"Max M\u00fcller Holding Ag Beteiligungen Usw",
    "wof:placetype":"venue"
},
  "geometry": {"coordinates":[7.5688052177,47.5586128235],"type":"Point"}
}