{
  "type": "Feature",
  "properties": {
    "addr:full":"B\u00fcndtenweg 5 Aarau Aargau 5000",
    "addr:housenumber":"5",
    "addr:postcode":"5000",
    "addr:street":"Buendtenweg",
    "iso:country":"CH",
    "sg:address":"B\u00fcndtenweg 5",
    "sg:city":"Aarau",
    "sg:orig_category":"Architekturb\u00fcros",
    "sg:phone":"+41 62 824 38 52",
    "sg:postcode":"5000",
    "sg:province":"Aargau",
    "wof:name":"Markus Grob Architekturb\u00fcro",
    "wof:placetype":"venue"
},
  "geometry": {"coordinates":[8.044757,47.397419],"type":"Point"}
}