{
  "type": "Feature",
  "properties": {
    "addr:full":"Rossmarktplatz 12 Solothurn Solothurn 4500",
    "addr:housenumber":"12",
    "addr:postcode":"4500",
    "addr:street":"Rossmarktplatz",
    "iso:country":"CH",
    "sg:address":"Rossmarktplatz 12",
    "sg:city":"Solothurn",
    "sg:orig_category":"Arztpraxen",
    "sg:phone":"+41 32 621 77 11",
    "sg:postcode":"4500",
    "sg:province":"Solothurn",
    "wof:name":"Dr.med. Roger Eltbogen Spezialarzt Fmh",
    "wof:placetype":"venue"
},
  "geometry": {"coordinates":[7.537328,47.204491],"type":"Point"}
}