{
  "type": "Feature",
  "properties": {
    "iso:country":"CH",
    "sg:address":"3949",
    "sg:city":"Hohtenn",
    "sg:orig_category":"Malerei",
    "sg:phone":"+41 32 913 39 71",
    "sg:postcode":"3949",
    "sg:province":"Valais",
    "wof:name":"Alphonse Brossard Entreprise De Peinture",
    "wof:placetype":"venue"
},
  "geometry": {"coordinates":[6.8175392151,47.1023178101],"type":"Point"}
}