{
  "type": "Feature",
  "properties": {
    "iso:country":"CH",
    "sg:address":"Hofwiesenstrasse 376 8000 Z\u00fcrich. Postfach 8050 Z\u00fcrich",
    "sg:city":"Zust",
    "sg:orig_category":"RESTAURANTS: TEA-ROOMS",
    "sg:postcode":"50",
    "wof:name":"Restaurant Fine Choice, Chiu Kai Tong",
    "wof:placetype":"venue"
},
  "geometry": {"coordinates":[8.5451822281,47.4114265442],"type":"Point"}
}