{
  "type": "Feature",
  "properties": {
    "iso:country":"CH",
    "sg:address":"Industriestrasse 472a",
    "sg:city":"Maienfeld",
    "sg:orig_category":"Vermittlung von Immobilien Verwaltung von Immobilien",
    "sg:phone":"+41 81 250 37 03",
    "sg:postcode":"7304",
    "sg:province":"Graubunden",
    "wof:name":"Stocker Immobilientreuhand Und Bauberatung",
    "wof:placetype":"venue"
},
  "geometry": {"coordinates":[9.5235004425,47.0017700195],"type":"Point"}
}