{
  "type": "Feature",
  "properties": {
    "iso:country":"CH",
    "sg:address":"Wettingerstrasse 19a",
    "sg:city":"Baden",
    "sg:orig_category":"Detailhandel mit M\u00f6beln U Haushaltsgegenst\u00e4nden Einbau von Schreinerwaren",
    "sg:phone":"+41 56 221 62 63",
    "sg:postcode":"5400",
    "sg:province":"Aargau",
    "wof:name":"Zeilo Form Ag",
    "wof:placetype":"venue"
},
  "geometry": {"coordinates":[8.3121376038,47.4719963074],"type":"Point"}
}