{
  "type": "Feature",
  "properties": {
    "iso:country":"CH",
    "sg:address":"Alte Strasse 58",
    "sg:city":"Thusis",
    "sg:orig_category":"K\u00fcnstlerische Schulen",
    "sg:phone":"+41 79 463 72 34",
    "sg:postcode":"7430",
    "sg:province":"Graubunden",
    "wof:name":"Gaby's Musikschule",
    "wof:placetype":"venue"
},
  "geometry": {"coordinates":[9.4395198822,46.6993637085],"type":"Point"}
}