{
  "type": "Feature",
  "properties": {
    "addr:full":"Route De Villars-vert 40 Villars-sur-gl\u00e2ne Fribourg 1752",
    "addr:housenumber":"40",
    "addr:postcode":"1752",
    "addr:street":"Route De Villars-Vert",
    "iso:country":"CH",
    "sg:address":"Route De Villars-vert 40",
    "sg:city":"Villars-sur-gl\u00e2ne",
    "sg:orig_category":"Alabaster Gypsum",
    "sg:phone":"+41 76 422 05 40",
    "sg:postcode":"1752",
    "sg:province":"Fribourg",
    "wof:name":"Mt Makshana S.\u00e0.r.l.",
    "wof:placetype":"venue"
},
  "geometry": {"coordinates":[7.130713,46.801334],"type":"Point"}
}