{
  "type": "Feature",
  "properties": {
    "iso:country":"CH",
    "sg:address":"Neumattstrasse 7",
    "sg:city":"Lenzburg",
    "sg:orig_category":"Non-Classified Establishments",
    "sg:postcode":"5600",
    "sg:province":"Aargau",
    "wof:name":"Lichtspieltheater Ag Lenzburg",
    "wof:placetype":"venue"
},
  "geometry": {"coordinates":[8.1727933884,47.3862380981],"type":"Point"}
}