{
  "type": "Feature",
  "properties": {
    "iso:country":"CH",
    "sg:address":"Bahnhofstrasse 15",
    "sg:city":"Rheinfelden",
    "sg:classifiers":[
        {
            "category":"Professional",
            "subcategory":"Employment Agencies",
            "type":"Services"
        }
    ],
    "sg:phone":"+41 41 249 47 47",
    "sg:postcode":"4310",
    "sg:province":"Aargau",
    "sg:tags":[
        "personal",
        "u",
        "stellenvermittlung"
    ],
    "wof:name":"Rav Regionales Arbeitsvermittlungszentrum",
    "wof:placetype":"venue"
},
  "geometry": {"coordinates":[8.2927703857,47.0531768799],"type":"Point"}
}