{
  "type": "Feature",
  "properties": {
    "iso:country":"CH",
    "sg:address":"Grand'rue 75",
    "sg:city":"Rolle",
    "sg:orig_category":"Detailhandel mit Fleisch U Fleischwaren",
    "sg:phone":"+41 21 825 16 09",
    "sg:postcode":"1180",
    "sg:province":"Vaud",
    "wof:name":"Jean Jaggi Boucherie Du Port",
    "wof:placetype":"venue"
},
  "geometry": {"coordinates":[6.3382320404,46.4575157166],"type":"Point"}
}