{
  "type": "Feature",
  "properties": {
    "iso:country":"CH",
    "sg:address":"Rue De L'ile Falcon 3960 Sierre Case Postale 33",
    "sg:city":"Sierre",
    "sg:orig_category":"Herstellung von Elektrizit\u00e4tsverteilungs U schalteinrichtungen Herstellung von sonstigen elektrische",
    "sg:phone":"+41 27 455 64 46",
    "sg:postcode":"3960",
    "sg:province":"Valais",
    "wof:name":"Applica Applications Electro-industrielles Et Informatiques Sa",
    "wof:placetype":"venue"
},
  "geometry": {"coordinates":[7.550339222,46.2863006592],"type":"Point"}
}