{
  "type": "Feature",
  "properties": {
    "addr:full":"Oberdorfstrasse 10 Berlingen Thurgau 8267",
    "addr:housenumber":"10",
    "addr:postcode":"8267",
    "addr:street":"Oberdorfstrasse",
    "iso:country":"CH",
    "sg:address":"Oberdorfstrasse 10",
    "sg:city":"Berlingen",
    "sg:orig_category":"Bauschreinerei Herstellung von Konstruktionsteilen, Fertigbauteilen U Ausbauelementen aus Holz",
    "sg:phone":"+41 52 761 12 08",
    "sg:postcode":"8267",
    "sg:province":"Thurgau",
    "wof:name":"Merkli Andreas, Schreinerei, Zimmerei",
    "wof:placetype":"venue"
},
  "geometry": {"coordinates":[9.019308,47.673546],"type":"Point"}
}