{
  "type": "Feature",
  "properties": {
    "addr:full":"Via Cantonale Prosito Ticino 6526",
    "addr:postcode":"6526",
    "addr:street":"Via Cantonale;Ticino",
    "iso:country":"CH",
    "sg:address":"Via Cantonale",
    "sg:city":"Prosito",
    "sg:orig_category":"Bauschreinerei Herstellung von M\u00f6beln verschiedener Art",
    "sg:phone":"+41 91 863 18 73",
    "sg:postcode":"6526",
    "sg:province":"Ticino",
    "wof:name":"Bruno Pagliuca Falegnameria",
    "wof:placetype":"venue"
},
  "geometry": {"coordinates":[8.986441,46.279083],"type":"Point"}
}