{
  "type": "Feature",
  "properties": {
    "iso:country":"CH",
    "sg:address":"Route De Jussy 312",
    "sg:city":"Jussy",
    "sg:classifiers":[
        {
            "category":"Banks & Credit Unions",
            "subcategory":"Bank",
            "type":"Services"
        }
    ],
    "sg:phone":"+41 27 783 22 88",
    "sg:postcode":"1254",
    "sg:province":"Gen\u00e8ve",
    "wof:name":"Banque Raiffeisen Liddes Et Bourg St-pierre",
    "wof:placetype":"venue"
},
  "geometry": {"coordinates":[7.1862,45.991459],"type":"Point"}
}