{
  "type": "Feature",
  "properties": {
    "iso:country":"CH",
    "sg:address":"Haldenrain 2",
    "sg:city":"Luzern",
    "sg:orig_category":"Detailhandel mit elektrischen Haushalts-,Radio U Fernsehger\u00e4ten sowie Musikinstrumenten",
    "sg:phone":"+41 21 635 24 50",
    "sg:postcode":"6006",
    "sg:province":"Luzern",
    "wof:name":"Royal Ware, Riccio Agostino",
    "wof:placetype":"venue"
},
  "geometry": {"coordinates":[6.5741510391,46.5370445251],"type":"Point"}
}