{
  "type": "Feature",
  "properties": {
    "iso:country":"CH",
    "sg:address":"Ch\u00e4nnelmattstrasse 12",
    "sg:city":"D\u00fcdingen",
    "sg:orig_category":"Handel mit Motorr\u00e4dern, Teilen U Zubeh\u00f6r Instandhaltung U Reparatur von Motorr\u00e4dern",
    "sg:postcode":"3186",
    "sg:province":"Fribourg",
    "wof:name":"Roland L\u00fcthi Ccm Motorcycles",
    "wof:placetype":"venue"
},
  "geometry": {"coordinates":[7.193500042,46.8451919556],"type":"Point"}
}