{
  "type": "Feature",
  "properties": {
    "iso:country":"CH",
    "sg:address":"Kurholzweg 3 3184 W\u00fcnnewil. Postfach",
    "sg:city":"W\u00fcnnewil",
    "sg:orig_category":"Unclassifiable Establishments",
    "sg:postcode":"3184",
    "sg:province":"Fribourg",
    "wof:name":"Garten-design Boschung Marcel",
    "wof:placetype":"venue"
},
  "geometry": {"coordinates":[7.271021843,46.8684616089],"type":"Point"}
}