{
  "type": "Feature",
  "properties": {
    "iso:country":"CH",
    "sg:address":"St. Galler-strasse 142",
    "sg:city":"Winterthur",
    "sg:classifiers":[
        {
            "category":"Restaurant",
            "type":"Food & Drink"
        }
    ],
    "sg:phone":"+41 52 233 14 37",
    "sg:postcode":"8404",
    "sg:province":"Z\u00fcrich",
    "wof:name":"Restaurant Bahnhof Gr\u00fcze",
    "wof:placetype":"venue"
},
  "geometry": {"coordinates":[8.7504682541,47.498210907],"type":"Point"}
}