{
  "type": "Feature",
  "properties": {
    "iso:country":"CH",
    "sg:address":"Plattenstrasse 8627 Gr\u00fcningen. Postfach 135",
    "sg:city":"Gr\u00fcningen",
    "sg:orig_category":"Bauschreinerei Zimmerei, Dachdeckerei, Bauspenglerei U Abdichtung",
    "sg:phone":"+41 71 633 11 49",
    "sg:postcode":"8627",
    "sg:province":"Z\u00fcrich",
    "wof:name":"Huber Kurt",
    "wof:placetype":"venue"
},
  "geometry": {"coordinates":[9.153209,47.554813],"type":"Point"}
}