{
  "type": "Feature",
  "properties": {
    "iso:country":"CH",
    "sg:address":"Route Des Pr\u00e9alpes 20",
    "sg:city":"Villars-sur-gl\u00e2ne",
    "sg:orig_category":"Arztpraxen",
    "sg:phone":"+41 26 401 91 42",
    "sg:postcode":"1752",
    "sg:province":"Fribourg",
    "wof:name":"Dr M\u00e9d. Jacob Hetzel M\u00e9decin G\u00e9n\u00e9raliste",
    "wof:placetype":"venue"
},
  "geometry": {"coordinates":[7.122821,46.792664],"type":"Point"}
}