{
  "type": "Feature",
  "properties": {
    "iso:country":"CH",
    "sg:address":"Erikaweg 1",
    "sg:city":"Langenbruck",
    "sg:orig_category":"Vermietung U Verpachtung von eigenen Immobilien",
    "sg:phone":"+41 61 941 10 13",
    "sg:postcode":"4438",
    "sg:province":"Basel-Landschaft",
    "wof:name":"Lavinar Ag",
    "wof:placetype":"venue"
},
  "geometry": {"coordinates":[7.7661499977,47.3493041992],"type":"Point"}
}