{
  "type": "Feature",
  "properties": {
    "iso:country":"CH",
    "sg:address":"La P\u00e2le 1026 Echandens Case Postale",
    "sg:city":"Echandens-denges",
    "sg:orig_category":"Interessenvertretungen",
    "sg:postcode":"1026",
    "sg:province":"Vaud",
    "wof:name":"Fondation Roth-tr\u00fcb Rodolphe",
    "wof:placetype":"venue"
},
  "geometry": {"coordinates":[6.5408301353,46.534286499],"type":"Point"}
}