{
  "type": "Feature",
  "properties": {
    "iso:country":"CH",
    "sg:address":"Chemin De Plaisance 1926 Fully. Postfach",
    "sg:city":"Fully",
    "sg:orig_category":"Grosshandel mit Getr\u00e4nken Grosshandel mit Wein U Spirituosen",
    "sg:phone":"+41 27 746 38 28",
    "sg:postcode":"1926",
    "sg:province":"Valais",
    "wof:name":"Confr\u00e9rie Vigneronne Fully Cvf Sa",
    "wof:placetype":"venue"
},
  "geometry": {"coordinates":[7.1221199036,46.1374092102],"type":"Point"}
}