{
  "type": "Feature",
  "properties": {
    "iso:country":"CH",
    "sg:address":"Oeuches Rue Des 10",
    "sg:city":"Montagne-moutier",
    "sg:orig_category":"Sonstige pers\u00f6nliche Dienstleistungen",
    "sg:postcode":"2740",
    "sg:province":"Bern",
    "wof:name":"Frebamo, W. Frei",
    "wof:placetype":"venue"
},
  "geometry": {"coordinates":[7.3724632263,47.2787246704],"type":"Point"}
}