{
  "type": "Feature",
  "properties": {
    "iso:country":"CH",
    "sg:address":"Haldenm\u00fchle",
    "sg:city":"Goldach",
    "sg:orig_category":"Allgemeiner Hoch U Tiefbau",
    "sg:phone":"+41 79 438 45 49",
    "sg:postcode":"9403",
    "sg:province":"St. Gallen",
    "wof:name":"Wohnlich Bau",
    "wof:placetype":"venue"
},
  "geometry": {"coordinates":[9.456769,47.471676],"type":"Point"}
}