{
  "type": "Feature",
  "properties": {
    "iso:country":"CH",
    "sg:address":"Dorfstrasse",
    "sg:city":"D\u00e4rligen",
    "sg:orig_category":"Grosshandel mit Nahrungsmitteln, Getr\u00e4nken U Tabakwaren ohne ausgepr\u00e4gten Schwerpunkt KLEINE GESCH\u00c4F",
    "sg:phone":"+41 33 822 83 21",
    "sg:postcode":"3707",
    "sg:province":"Bern",
    "wof:name":"Maria's Dorfl\u00e4deli Gmbh",
    "wof:placetype":"venue"
},
  "geometry": {"coordinates":[7.8128499985,46.660484314],"type":"Point"}
}