{
  "type": "Feature",
  "properties": {
    "iso:country":"CH",
    "sg:address":"Wiggenrainstrasse 15",
    "sg:city":"Rorschacherberg",
    "sg:orig_category":"Kaminfeger",
    "sg:phone":"+41 71 855 14 66",
    "sg:postcode":"9404",
    "sg:province":"St. Gallen",
    "wof:name":"Eugen Eisenreich Kaminfegermeister",
    "wof:placetype":"venue"
},
  "geometry": {"coordinates":[9.5172185898,47.4752845764],"type":"Point"}
}