{
  "type": "Feature",
  "properties": {
    "iso:country":"CH",
    "sg:address":"Rue Du March\u00e9 36 1630 Bulle. Postfach",
    "sg:city":"Bulle",
    "sg:orig_category":"Sanit\u00e4r, Heizungs U L\u00fcftungsinstallation",
    "sg:postcode":"1630",
    "sg:province":"Fribourg",
    "wof:name":"Aqua Tech 3000 S\u00e0rl Entrepr. D'install. De Chauffage, Sanitaire Etc",
    "wof:placetype":"venue"
},
  "geometry": {"coordinates":[7.0593152046,46.6203651428],"type":"Point"}
}