{
  "type": "Feature",
  "properties": {
    "iso:country":"CH",
    "sg:address":"Heiligkreuz 25",
    "sg:city":"Vaduz",
    "sg:orig_category":"Sonstige Institutionen des Sozialwesens ohne Beherbergung",
    "sg:postcode":"9490",
    "wof:name":"M\u00fctterberatung D.liechtenst. Roten Kreuzes",
    "wof:placetype":"venue"
},
  "geometry": {"coordinates":[9.5226249695,47.1341171265],"type":"Point"}
}