{
  "type": "Feature",
  "properties": {
    "addr:full":"Baarerstrasse 12 Zug Zug 6300",
    "addr:housenumber":"12",
    "addr:postcode":"6300",
    "addr:street":"Baarerstrasse;Zug",
    "iso:country":"CH",
    "sg:address":"Baarerstrasse 12",
    "sg:city":"Zug",
    "sg:orig_category":"Architektur U Ingenieurb\u00fcros",
    "sg:phone":"+41 32 672 01 01",
    "sg:postcode":"6300",
    "sg:province":"Zug",
    "wof:name":"Seisma Ag",
    "wof:placetype":"venue"
},
  "geometry": {"coordinates":[8.516479,47.17173],"type":"Point"}
}