{
  "type": "Feature",
  "properties": {
    "iso:country":"CH",
    "sg:address":"Talackerstr. 40 8155 Niederhasli. Postfach",
    "sg:city":"Oberhasli",
    "sg:orig_category":"Detektivb\u00fcros U \u00dcberwachung",
    "sg:postcode":"8156",
    "sg:province":"Z\u00fcrich",
    "wof:name":"Basic Security, Eyer Philippe",
    "wof:placetype":"venue"
},
  "geometry": {"coordinates":[8.5063352585,47.4690284729],"type":"Point"}
}