{
  "type": "Feature",
  "properties": {
    "iso:country":"CH",
    "sg:address":"Ziegelhaustrasse 8",
    "sg:city":"Baden",
    "sg:orig_category":"Gartenbau Landschaftsplanungsb\u00fcros U Gartenarchitekturb\u00fcros",
    "sg:phone":"+41 56 222 16 02",
    "sg:postcode":"5400",
    "sg:province":"Aargau",
    "wof:name":"J\u00f6rg Villiger Gartenarchitekt B.l.a.",
    "wof:placetype":"venue"
},
  "geometry": {"coordinates":[8.2916517258,47.4659347534],"type":"Point"}
}