{
  "type": "Feature",
  "properties": {
    "iso:country":"CH",
    "sg:address":"Tannrietlistrasse 21 8166 Niederweningen. Postfach",
    "sg:city":"Niederweningen",
    "sg:orig_category":"Sonstige mit der Informatik verbundene T\u00e4tigkeiten",
    "sg:postcode":"8166",
    "sg:province":"Z\u00fcrich",
    "wof:name":"Reiss Consulting Gmbh",
    "wof:placetype":"venue"
},
  "geometry": {"coordinates":[8.3743219376,47.5003967285],"type":"Point"}
}