{
  "type": "Feature",
  "properties": {
    "addr:full":"Kirchweg 15 Eichberg St. Gallen 9453",
    "addr:housenumber":"15;st.",
    "addr:postcode":"9453",
    "addr:street":"Kirchweg;Eichberg",
    "iso:country":"CH",
    "sg:address":"Kirchweg 15",
    "sg:city":"Eichberg",
    "sg:orig_category":"Botanische U zoologische G\u00e4rten sowie Naturparks",
    "sg:phone":"+41 71 755 55 70",
    "sg:postcode":"9453",
    "sg:province":"St. Gallen",
    "wof:name":"Zoologischer Garten Erlebniszoo Eichberg",
    "wof:placetype":"venue"
},
  "geometry": {"coordinates":[9.525113,47.346745],"type":"Point"}
}