{
  "type": "Feature",
  "properties": {
    "iso:country":"CH",
    "sg:address":"Rue Du Prince 8",
    "sg:city":"Gen\u00e8ve",
    "sg:orig_category":"Kosmetikinstitute",
    "sg:phone":"+41 22 310 90 17",
    "sg:postcode":"1204",
    "sg:province":"Gen\u00e8ve",
    "wof:name":"Madeleine Th\u00e9venet Institut De Beaut\u00e9 Alexandra",
    "wof:placetype":"venue"
},
  "geometry": {"coordinates":[6.1508522034,46.2027702332],"type":"Point"}
}