{
  "type": "Feature",
  "properties": {
    "iso:country":"CH",
    "sg:address":"Solothurnstrasse 38",
    "sg:city":"Biberist",
    "sg:orig_category":"RESTAURANTS: TEA-ROOMS",
    "sg:postcode":"4562",
    "sg:province":"Solothurn",
    "wof:name":"Bibib Gmbh",
    "wof:placetype":"venue"
},
  "geometry": {"coordinates":[7.556994915,47.1861686707],"type":"Point"}
}