{
  "type": "Feature",
  "properties": {
    "iso:country":"CH",
    "sg:address":"Gutstrasse 222",
    "sg:city":"Z\u00fcrich",
    "sg:orig_category":"Handelsvermittlung U Grosshandel",
    "sg:phone":"+41 14925900",
    "sg:postcode":"8055",
    "sg:province":"Z\u00fcrich",
    "wof:name":"Ic Amexco Ag",
    "wof:placetype":"venue"
},
  "geometry": {"coordinates":[8.5007295609,47.3761558533],"type":"Point"}
}