{
  "type": "Feature",
  "properties": {
    "iso:country":"CH",
    "sg:address":"Veyrot Rue De 27",
    "sg:city":"Meyrin",
    "sg:orig_category":"Herstellung von Tanks U Sammelbeh\u00e4ltern aus Metall",
    "sg:phone":"+41 22 782 82 31",
    "sg:postcode":"1217",
    "sg:province":"Gen\u00e8ve",
    "wof:name":"Depot Box Services Sa",
    "wof:placetype":"venue"
},
  "geometry": {"coordinates":[6.0623149872,46.2276039124],"type":"Point"}
}