{
  "type": "Feature",
  "properties": {
    "addr:full":"Erlosen 762 Hinwil Z\u00fcrich 8340",
    "addr:housenumber":"762",
    "addr:postcode":"8340",
    "iso:country":"CH",
    "sg:address":"Erlosen 762",
    "sg:city":"Hinwil",
    "sg:classifiers":[
        {
            "category":"Food & Beverages",
            "subcategory":"Specialty",
            "type":"Retail Goods"
        }
    ],
    "sg:phone":"+41 19771944",
    "sg:postcode":"8340",
    "sg:province":"Z\u00fcrich",
    "sg:tags":[
        "caterer"
    ],
    "wof:name":"Maximahl Catering",
    "wof:placetype":"venue"
},
  "geometry": {"coordinates":[8.818176,47.317513],"type":"Point"}
}