{
  "type": "Feature",
  "properties": {
    "addr:full":"Rue Des Terrasses 3 Echallens Vaud 1040",
    "addr:housenumber":"3",
    "addr:postcode":"1040",
    "addr:street":"Rue Des Terrasses",
    "iso:country":"CH",
    "sg:address":"Rue Des Terrasses 3",
    "sg:city":"Echallens",
    "sg:orig_category":"Detailhandel mit Antiquit\u00e4ten Innendekorationsateliers",
    "sg:phone":"+41 21 881 15 96",
    "sg:postcode":"1040",
    "sg:province":"Vaud",
    "wof:name":"Fran\u00e7oise Dagon La Mazarine",
    "wof:placetype":"venue"
},
  "geometry": {"coordinates":[6.63382,46.641529],"type":"Point"}
}