{
  "type": "Feature",
  "properties": {
    "iso:country":"CH",
    "sg:address":"Baretta Route De La 21",
    "sg:city":"Belfaux",
    "sg:orig_category":"Herstellung von Konstruktionsteilen, Fertigbauteilen U Ausbauelementen aus Holz",
    "sg:phone":"+41 26 475 57 65",
    "sg:postcode":"1782",
    "sg:province":"Fribourg",
    "wof:name":"Pap Menuiserie S\u00e0rl",
    "wof:placetype":"venue"
},
  "geometry": {"coordinates":[7.1060299873,46.8202896118],"type":"Point"}
}