{
  "type": "Feature",
  "properties": {
    "iso:country":"CH",
    "sg:address":"L\u00fctzelstrasse 1",
    "sg:city":"Basel",
    "sg:orig_category":"Grosshandel mit Holz U Bauelementen aus Holz",
    "sg:phone":"+41 61 321 64 71",
    "sg:postcode":"4055",
    "sg:province":"Basel-Stadt",
    "wof:name":"Justin Meyer Furniere-placages",
    "wof:placetype":"venue"
},
  "geometry": {"coordinates":[7.5689110756,47.5632553101],"type":"Point"}
}