{
  "type": "Feature",
  "properties": {
    "iso:country":"CH",
    "sg:address":"Rue De Lausanne 49",
    "sg:city":"Gen\u00e8ve",
    "sg:orig_category":"Fachdetailhandel mit pharmazeutischen Produkten",
    "sg:phone":"+41 79 413 34 43",
    "sg:postcode":"1201",
    "sg:province":"Gen\u00e8ve",
    "wof:name":"Schopfer Mme H., Pharmacie De S\u00e9cheron Et Laboratoire Sylvia",
    "wof:placetype":"venue"
},
  "geometry": {"coordinates":[6.1456418037,46.2138824463],"type":"Point"}
}