{
  "type": "Feature",
  "properties": {
    "iso:country":"CH",
    "sg:address":"Quellenstrasse 10 4310 Rheinfelden. Postfach",
    "sg:city":"Rheinfelden",
    "sg:orig_category":"Unclassifiable Establishments",
    "sg:phone":"+41 61 831 68 83",
    "sg:postcode":"4310",
    "sg:province":"Aargau",
    "wof:name":"Mobilwerte-verwaltungs Ag",
    "wof:placetype":"venue"
},
  "geometry": {"coordinates":[7.7898387909,47.5511856079],"type":"Point"}
}