{
  "type": "Feature",
  "properties": {
    "iso:country":"CH",
    "sg:address":"Rte De Tavel 2 1700 Fribourg Case Postale",
    "sg:city":"Freiburg",
    "sg:orig_category":"Fachdetailhandel mit pharmazeutischen Produkten",
    "sg:phone":"+41 26 484 88 88",
    "sg:postcode":"1700",
    "sg:province":"Fribourg",
    "wof:name":"M\u00fcller Jean-fran\u00e7ois",
    "wof:placetype":"venue"
},
  "geometry": {"coordinates":[7.1727352142,46.8107185364],"type":"Point"}
}