{
  "type": "Feature",
  "properties": {
    "iso:country":"CH",
    "sg:address":"Rue Neuve 4",
    "sg:city":"Nyon",
    "sg:orig_category":"Reiseb\u00fcros",
    "sg:phone":"+41 22 361 42 35",
    "sg:postcode":"1260",
    "sg:province":"Vaud",
    "wof:name":"Carlson Wagonlit Travel",
    "wof:placetype":"venue"
},
  "geometry": {"coordinates":[6.2389240265,46.3832702637],"type":"Point"}
}