{
  "type": "Feature",
  "properties": {
    "iso:country":"CH",
    "sg:address":"Place De La Gare 24",
    "sg:city":"Del\u00e9mont",
    "sg:orig_category":"Detailhandel mit Fleisch U Fleischwaren",
    "sg:phone":"+41 32 422 26 13",
    "sg:postcode":"2800",
    "sg:province":"Jura",
    "wof:name":"Pierre Von Gr\u00fcnigen Boucherie Chevaline",
    "wof:placetype":"venue"
},
  "geometry": {"coordinates":[7.348982811,47.3647956848],"type":"Point"}
}