{
  "type": "Feature",
  "properties": {
    "iso:country":"CH",
    "sg:address":"Marktplatz 30",
    "sg:city":"Basel",
    "sg:orig_category":"Arztpraxen",
    "sg:phone":"+41 61 261 69 11",
    "sg:postcode":"4001",
    "sg:province":"Basel-Stadt",
    "wof:name":"Dr.med.hans-peter Maier Spezialarzt",
    "wof:placetype":"venue"
},
  "geometry": {"coordinates":[7.587264,47.5583],"type":"Point"}
}