{
  "type": "Feature",
  "properties": {
    "iso:country":"CH",
    "sg:address":"2874",
    "sg:city":"St-brais",
    "sg:orig_category":"Vereine Gesang",
    "sg:postcode":"2874",
    "sg:province":"Jura",
    "wof:name":"St\u00e9 De Chant La Chorale",
    "wof:placetype":"venue"
},
  "geometry": {"coordinates":[6.9261350632,46.39818573],"type":"Point"}
}