{
  "type": "Feature",
  "properties": {
    "addr:full":"Himmeri W\u00e4denswil Z\u00fcrich 8820",
    "addr:postcode":"8820",
    "addr:street":"Zuerich",
    "iso:country":"CH",
    "sg:address":"Himmeri",
    "sg:city":"W\u00e4denswil",
    "sg:orig_category":"Autogaragen Autospenglereien",
    "sg:phone":"+41 17803119",
    "sg:postcode":"8820",
    "sg:province":"Z\u00fcrich",
    "wof:name":"Berg-garage Fritz Sch\u00e4rer Carrosserie & Spritzwerk",
    "wof:placetype":"venue"
},
  "geometry": {"coordinates":[8.664012,47.210991],"type":"Point"}
}