{
  "type": "Feature",
  "properties": {
    "iso:country":"CH",
    "sg:address":"Bahnhofstrasse 24 9424 Rheineck. Postfach",
    "sg:city":"Rheineck",
    "sg:orig_category":"Detailhandel mit Textilien",
    "sg:phone":"+41 27 776 12 64",
    "sg:postcode":"9424",
    "sg:province":"St. Gallen",
    "wof:name":"Valentine Vogel Laines",
    "wof:placetype":"venue"
},
  "geometry": {"coordinates":[7.2124481201,46.0804595947],"type":"Point"}
}