{
  "type": "Feature",
  "properties": {
    "iso:country":"CH",
    "sg:address":"Hofenstrasse 27",
    "sg:city":"Wittenbach",
    "sg:orig_category":"Allgemeiner Hoch U Tiefbau",
    "sg:phone":"+41 81 756 01 29",
    "sg:postcode":"9303",
    "wof:name":"Walo Bertschinger Ag St. Gallen",
    "wof:placetype":"venue"
},
  "geometry": {"coordinates":[9.46943,47.159245],"type":"Point"}
}