{
  "type": "Feature",
  "properties": {
    "iso:country":"CH",
    "sg:address":"Paulihof 2",
    "sg:city":"Vorderthal",
    "sg:orig_category":"G\u00fcterbef\u00f6rderung im Strassenverkehr Reiseb\u00fcros U Reiseveranstalter",
    "sg:phone":"+41 55 446 11 06",
    "sg:postcode":"8857",
    "sg:province":"Schwyz",
    "wof:name":"Hans M\u00e4chler Transport- & Reiseunternehmen",
    "wof:placetype":"venue"
},
  "geometry": {"coordinates":[8.9039907455,47.1209068298],"type":"Point"}
}