{
  "type": "Feature",
  "properties": {
    "iso:country":"CH",
    "sg:address":"Postgasse 26",
    "sg:city":"Pieterlen",
    "sg:orig_category":"Textilveredlung",
    "sg:phone":"+41 55 442 34 86",
    "sg:postcode":"2542",
    "sg:province":"Bern",
    "wof:name":"Cotex Print Schmid & Co Textildruck",
    "wof:placetype":"venue"
},
  "geometry": {"coordinates":[8.8535680771,47.1919708252],"type":"Point"}
}