{
  "type": "Feature",
  "properties": {
    "iso:country":"CH",
    "sg:address":"Flurstrasse 1",
    "sg:city":"Zizers",
    "sg:orig_category":"Mechanik Mechanische Werkst\u00e4tten",
    "sg:phone":"+41 81 322 17 93",
    "sg:postcode":"7205",
    "sg:province":"Graubunden",
    "wof:name":"Wyss Alexander Ag",
    "wof:placetype":"venue"
},
  "geometry": {"coordinates":[9.5572519302,46.9344825745],"type":"Point"}
}