{
  "type": "Feature",
  "properties": {
    "iso:country":"CH",
    "sg:address":"B\u00f6sch 73",
    "sg:city":"H\u00fcnenberg",
    "sg:orig_category":"Sonstige mit der Informatik verbundene T\u00e4tigkeiten",
    "sg:phone":"+41 41 783 14 81",
    "sg:postcode":"6331",
    "sg:province":"Zug",
    "wof:name":"Winformatic Engineering Gmbh",
    "wof:placetype":"venue"
},
  "geometry": {"coordinates":[8.4409618378,47.1616668701],"type":"Point"}
}