{
  "type": "Feature",
  "properties": {
    "iso:country":"CH",
    "sg:address":"Wildsbergstrasse 5",
    "sg:city":"Greifensee",
    "sg:orig_category":"Politische Parteien FDP",
    "sg:phone":"+41 19404595",
    "sg:postcode":"8606",
    "sg:province":"Z\u00fcrich",
    "wof:name":"Fdp Greifensee",
    "wof:placetype":"venue"
},
  "geometry": {"coordinates":[8.6898441315,47.3616981506],"type":"Point"}
}