{
  "type": "Feature",
  "properties": {
    "iso:country":"CH",
    "sg:address":"Untergrundstrasse 10",
    "sg:city":"Olten",
    "sg:orig_category":"Architektur U Ingenieurb\u00fcros",
    "sg:phone":"+41 62 212 12 85",
    "sg:postcode":"4600",
    "sg:province":"Solothurn",
    "wof:name":"J. Mandik, Dipl. Bauing. Eth/sia, Ingenieurb\u00fcro Ag",
    "wof:placetype":"venue"
},
  "geometry": {"coordinates":[7.895642,47.353367],"type":"Point"}
}