{
  "type": "Feature",
  "properties": {
    "iso:country":"CH",
    "sg:address":"Hofmattweg",
    "sg:city":"Gettnau",
    "sg:orig_category":"Allgemeiner Hoch U Tiefbau",
    "sg:phone":"+41 62 771 66 88",
    "sg:postcode":"6142",
    "sg:province":"Luzern",
    "wof:name":"Kurt Weber Ag Bauunternehmung",
    "wof:placetype":"venue"
},
  "geometry": {"coordinates":[8.177224,47.253231],"type":"Point"}
}