{
  "type": "Feature",
  "properties": {
    "iso:country":"CH",
    "sg:address":"Aegetlistrasse 2 9425 Thal. Postfach 156",
    "sg:city":"Thal",
    "sg:orig_category":"Handelsvermittlung U Grosshandel mit Automobilteilen U Zubeh\u00f6r Herstellung von Teilen U Zubeh\u00f6r f\u00fcr ",
    "sg:phone":"+41 71 886 40 30",
    "sg:postcode":"9425",
    "sg:province":"St. Gallen",
    "wof:name":"Kesch Ag",
    "wof:placetype":"venue"
},
  "geometry": {"coordinates":[9.5789337158,47.4777641296],"type":"Point"}
}