{
  "type": "Feature",
  "properties": {
    "iso:country":"CH",
    "sg:address":"Im Br\u00fcnnli 10",
    "sg:city":"Opfikon",
    "sg:orig_category":"Wirtschafts- and Arbeitgeberverb\u00e4nde",
    "sg:phone":"+41 18107810",
    "sg:postcode":"8152",
    "sg:province":"Z\u00fcrich",
    "wof:name":"Arbeiterbildungsverb.mittleres Glattal Herrn Eugen Moor",
    "wof:placetype":"venue"
},
  "geometry": {"coordinates":[8.5740089417,47.4390182495],"type":"Point"}
}