{
  "type": "Feature",
  "properties": {
    "iso:country":"CH",
    "sg:address":"1978",
    "sg:city":"Lens",
    "sg:orig_category":"Detektivb\u00fcros U \u00dcberwachung",
    "sg:postcode":"1978",
    "sg:province":"Valais",
    "wof:name":"Psi, Zogg Michel",
    "wof:placetype":"venue"
},
  "geometry": {"coordinates":[7.4485402107,46.2786102295],"type":"Point"}
}