{
  "type": "Feature",
  "properties": {
    "iso:country":"CH",
    "sg:address":"Kleinalbis 78",
    "sg:city":"Z\u00fcrich",
    "sg:orig_category":"Wirtschafts- and Arbeitgeberverb\u00e4nde",
    "sg:phone":"+41 14633900",
    "sg:postcode":"8045",
    "sg:province":"Z\u00fcrich",
    "wof:name":"Musiklehrerinnen-verband Mlvz",
    "wof:placetype":"venue"
},
  "geometry": {"coordinates":[8.5061359406,47.3582000732],"type":"Point"}
}