{
  "type": "Feature",
  "properties": {
    "iso:country":"CH",
    "sg:address":"Gotthardstrasse 42 - Golda",
    "sg:city":"Arth",
    "sg:orig_category":"Verwertung von Milch",
    "sg:postcode":"6415",
    "sg:province":"Schwyz",
    "wof:name":"Joos J.-m.",
    "wof:placetype":"venue"
},
  "geometry": {"coordinates":[5.1808700562,45.8973388672],"type":"Point"}
}