{
  "type": "Feature",
  "properties": {
    "addr:full":"Aarauerstrasse 101 5015 Niedererlinsbach. Postfach 153 Niedererlinsbach Solothurn 5015",
    "addr:housenumber":"101;153",
    "addr:postcode":"5015;5015",
    "addr:street":"Aarauerstrasse;Postfach;Solothurn",
    "iso:country":"CH",
    "sg:address":"Aarauerstrasse 101 5015 Niedererlinsbach. Postfach 153",
    "sg:city":"Niedererlinsbach",
    "sg:orig_category":"Architekturb\u00fcros",
    "sg:phone":"+41 62 844 34 25",
    "sg:postcode":"5015",
    "sg:province":"Solothurn",
    "wof:name":"Martin Gut Architekturb\u00fcro",
    "wof:placetype":"venue"
},
  "geometry": {"coordinates":[8.008854,47.397125],"type":"Point"}
}