{
  "type": "Feature",
  "properties": {
    "iso:country":"CH",
    "sg:address":"Franches-montagnes",
    "sg:city":"Saignel\u00e9gier",
    "sg:orig_category":"Wasserversorgung",
    "sg:phone":"+41 26 675 15 88",
    "sg:postcode":"2350",
    "sg:province":"Jura",
    "wof:name":"Technimat S\u00e0rl",
    "wof:placetype":"venue"
},
  "geometry": {"coordinates":[7.0989098549,46.9538536072],"type":"Point"}
}