{
  "type": "Feature",
  "properties": {
    "iso:country":"CH",
    "sg:address":"Breitenstrasse 4",
    "sg:city":"D\u00e4llikon",
    "sg:orig_category":"Elektroinstallation",
    "sg:phone":"+41 18441212",
    "sg:postcode":"8108",
    "sg:province":"Z\u00fcrich",
    "wof:name":"Zolliker Elektro Und Telefonanlagen",
    "wof:placetype":"venue"
},
  "geometry": {"coordinates":[8.4480962753,47.4378089905],"type":"Point"}
}