{
  "type": "Feature",
  "properties": {
    "iso:country":"CH",
    "sg:address":"Hinterdorf 28",
    "sg:city":"Wolfhalden",
    "sg:orig_category":"Naturheil\u00e4rzte and Heilpraktiker",
    "sg:phone":"+41 79 319 90 29",
    "sg:postcode":"9427",
    "sg:province":"Appenzell Ausserrhoden",
    "wof:name":"Arianne B\u00e4r Natur\u00e4rztin",
    "wof:placetype":"venue"
},
  "geometry": {"coordinates":[9.5481853485,47.4532089233],"type":"Point"}
}