{
  "type": "Feature",
  "properties": {
    "iso:country":"CH",
    "sg:address":"Altstetterstrasse 188",
    "sg:city":"Z\u00fcrich",
    "sg:orig_category":"Brillen Detailhandel H\u00f6rger\u00e4te Detailhandel",
    "sg:phone":"+41 81 710 41 51",
    "sg:postcode":"8048",
    "sg:province":"Z\u00fcrich",
    "wof:name":"K\u00fchnis Brillen & Optik Ag H\u00f6rger\u00e4te-akustik",
    "wof:placetype":"venue"
},
  "geometry": {"coordinates":[9.25572,47.138939],"type":"Point"}
}