{
  "type": "Feature",
  "properties": {
    "iso:country":"CH",
    "sg:address":"Hochfelderstrasse 5",
    "sg:city":"Neerach",
    "sg:orig_category":"Wirtschaftspr\u00fcfung, Steuerberatung U Treuhand",
    "sg:phone":"+41 18581455",
    "sg:postcode":"8173",
    "sg:province":"Z\u00fcrich",
    "wof:name":"Treuhand Gl\u00fcckler Esther, Eidg. Dipl. Buchhalterin",
    "wof:placetype":"venue"
},
  "geometry": {"coordinates":[8.475230217,47.5139122009],"type":"Point"}
}