{
  "type": "Feature",
  "properties": {
    "iso:country":"CH",
    "sg:address":"Laubgasse 31 8500 Frauenfeld. Postfach",
    "sg:city":"Frauenfeld",
    "sg:orig_category":"Druck ohne Zeitungsdruck Offsetdruck",
    "sg:phone":"+41 31 981 02 02",
    "sg:postcode":"8501",
    "sg:province":"Thurgau",
    "wof:name":"Bawarel Pr\u00e4gedruck Ag",
    "wof:placetype":"venue"
},
  "geometry": {"coordinates":[7.3730568886,46.923324585],"type":"Point"}
}