{
  "type": "Feature",
  "properties": {
    "iso:country":"CH",
    "sg:address":"W\u00fclflingerstrasse 28a 8400 Winterthur. Postfach 119",
    "sg:city":"Winterthur",
    "sg:orig_category":"Grosshandel mit Maschinen U Ausr\u00fcstungen Grosshandel mit sonstigen Maschinen U Ausr\u00fcstungen f\u00fcr Indu",
    "sg:phone":"+41 71 744 15 50",
    "sg:postcode":"8407",
    "wof:name":"Mawera Ag",
    "wof:placetype":"venue"
},
  "geometry": {"coordinates":[9.6523456573,47.4473342896],"type":"Point"}
}