{
  "type": "Feature",
  "properties": {
    "iso:country":"CH",
    "sg:address":"Frauentalweg 4",
    "sg:city":"Z\u00fcrich",
    "sg:orig_category":"Grosshandel mit Textilien Herstellung von gewirktem U gestricktem Stoff",
    "sg:phone":"+41 12427165",
    "sg:postcode":"8045",
    "sg:province":"Z\u00fcrich",
    "wof:name":"Teplitz Ag",
    "wof:placetype":"venue"
},
  "geometry": {"coordinates":[8.5127372742,47.3556671143],"type":"Point"}
}