{
  "type": "Feature",
  "properties": {
    "iso:country":"CH",
    "sg:address":"Tannenmattli",
    "sg:city":"Aeschiried",
    "sg:orig_category":"Unternehmensberatung",
    "sg:postcode":"3703",
    "sg:province":"Bern",
    "wof:name":"Zurbr\u00fcgg Rolf Treuhand",
    "wof:placetype":"venue"
},
  "geometry": {"coordinates":[7.6955251694,46.6565361023],"type":"Point"}
}