{
  "type": "Feature",
  "properties": {
    "iso:country":"CH",
    "sg:address":"Sonnenbergstrasse 42",
    "sg:city":"Schwerzenbach",
    "sg:orig_category":"Hardwareberatung",
    "sg:phone":"+41 18253308",
    "sg:postcode":"8603",
    "sg:province":"Z\u00fcrich",
    "wof:name":"Itcon Gmbh",
    "wof:placetype":"venue"
},
  "geometry": {"coordinates":[8.6523609161,47.3845481873],"type":"Point"}
}