{
  "type": "Feature",
  "properties": {
    "iso:country":"CH",
    "sg:address":"Kolpenweg 7",
    "sg:city":"Muhen",
    "sg:orig_category":"Markt U Meinungsforschung",
    "sg:phone":"+41 62 723 53 08",
    "sg:postcode":"5037",
    "sg:province":"Aargau",
    "wof:name":"Schmid Ernst",
    "wof:placetype":"venue"
},
  "geometry": {"coordinates":[8.0461091995,47.3375205994],"type":"Point"}
}