{
  "type": "Feature",
  "properties": {
    "iso:country":"CH",
    "sg:address":"St. Alban-anlage 57 4052 Basel. Postfach",
    "sg:city":"Basel",
    "sg:orig_category":"Fotografisches Gewerbe U fotografische Laboratorien",
    "sg:postcode":"4051",
    "sg:province":"Basel-Stadt",
    "wof:name":"Fotoatelier-colorlabor Landolt Fotoatelier F\u00fcr Werbung, Mode U. Industrie, Sowie Betrieb Eines Colorlabors",
    "wof:placetype":"venue"
},
  "geometry": {"coordinates":[7.6017661095,47.552986145],"type":"Point"}
}