{
  "type": "Feature",
  "properties": {
    "iso:country":"CH",
    "sg:address":"Place Trois-colombes 2",
    "sg:city":"Collombey",
    "sg:orig_category":"Glaserei",
    "sg:phone":"+41 79 445 06 13",
    "sg:postcode":"1868",
    "sg:province":"Valais",
    "wof:name":"Roger Faes Glaserei",
    "wof:placetype":"venue"
},
  "geometry": {"coordinates":[8.1621904373,47.2592773438],"type":"Point"}
}