{
  "type": "Feature",
  "properties": {
    "iso:country":"CH",
    "sg:address":"Oskar-bider-strasse 1",
    "sg:city":"D\u00fcbendorf",
    "sg:orig_category":"Softwareentwicklung U beratung Sonstige mit der Informatik verbundene T\u00e4tigkeiten",
    "sg:phone":"+41 18821707",
    "sg:postcode":"8600",
    "sg:province":"Z\u00fcrich",
    "wof:name":"E-vision, Inc",
    "wof:placetype":"venue"
},
  "geometry": {"coordinates":[8.626250267,47.3965301514],"type":"Point"}
}