{
  "type": "Feature",
  "properties": {
    "iso:country":"CH",
    "sg:address":"Neustadtstrasse 8",
    "sg:city":"Luzern",
    "sg:orig_category":"Detektivb\u00fcros U \u00dcberwachung",
    "sg:phone":"+41 56 461 77 77",
    "sg:postcode":"6003",
    "sg:province":"Luzern",
    "wof:name":"Daru-wache",
    "wof:placetype":"venue"
},
  "geometry": {"coordinates":[8.2240848541,47.4926605225],"type":"Point"}
}