{
  "type": "Feature",
  "properties": {
    "addr:full":"Rue Pierre-aeby 17 1700 Fribourg. Postfach Fribourg Fribourg 1702",
    "addr:housenumber":"17",
    "addr:postcode":"1700;postfach;1702",
    "addr:street":"Rue Pierre-Aeby",
    "iso:country":"CH",
    "sg:address":"Rue Pierre-aeby 17 1700 Fribourg. Postfach",
    "sg:city":"Fribourg",
    "sg:orig_category":"Architektur U Ingenieurb\u00fcros",
    "sg:phone":"+41 26 322 26 01",
    "sg:postcode":"1702",
    "sg:province":"Fribourg",
    "wof:name":"Urbaplan",
    "wof:placetype":"venue"
},
  "geometry": {"coordinates":[7.158609,46.808502],"type":"Point"}
}