{
  "type": "Feature",
  "properties": {
    "addr:full":"Stiegackerstrasse 6 Balterswil Thurgau 8362",
    "addr:housenumber":"6",
    "addr:postcode":"8362",
    "addr:street":"Stiegackerstrasse",
    "iso:country":"CH",
    "sg:address":"Stiegackerstrasse 6",
    "sg:city":"Balterswil",
    "sg:orig_category":"Baugewerbe",
    "sg:phone":"+41 71 971 36 36",
    "sg:postcode":"8362",
    "sg:province":"Thurgau",
    "wof:name":"Frischknecht Ag Bauunternehmung Zweigniederlassung Balterswil",
    "wof:placetype":"venue"
},
  "geometry": {"coordinates":[8.937837,47.455883],"type":"Point"}
}