{
  "type": "Feature",
  "properties": {
    "iso:country":"CH",
    "sg:address":"Ledi",
    "sg:city":"Feutersoey",
    "sg:orig_category":"Geb\u00e4ude, Wohnungsreinigung",
    "sg:phone":"+41 91 683 83 68",
    "sg:postcode":"3784",
    "sg:province":"Bern",
    "wof:name":"Mario Franchi Impresa Di Pulizia",
    "wof:placetype":"venue"
},
  "geometry": {"coordinates":[9.0155096054,45.8531227112],"type":"Point"}
}