{
  "type": "Feature",
  "properties": {
    "iso:country":"CH",
    "sg:address":"Karl-v\u00f6lker-strasse 2",
    "sg:city":"Heerbrugg",
    "sg:orig_category":"Architektur U Ingenieurb\u00fcros",
    "sg:phone":"+41 71 720 09 09",
    "sg:postcode":"9435",
    "sg:province":"St. Gallen",
    "wof:name":"Pml Ingenieurb\u00fcro Ag",
    "wof:placetype":"venue"
},
  "geometry": {"coordinates":[9.625864,47.41264],"type":"Point"}
}