{
  "type": "Feature",
  "properties": {
    "iso:country":"CH",
    "sg:address":"Stadelmatt",
    "sg:city":"H\u00fcnenberg",
    "sg:orig_category":"Sonstige mit Sport verbundene T\u00e4tigkeiten",
    "sg:postcode":"6331",
    "sg:province":"Zug",
    "wof:name":"Golfclub Reuss H\u00fcnenberg",
    "wof:placetype":"venue"
},
  "geometry": {"coordinates":[8.4124832153,47.2179603577],"type":"Point"}
}