{
  "type": "Feature",
  "properties": {
    "iso:country":"CH",
    "sg:address":"Zugerstrasse 53",
    "sg:city":"Baar",
    "sg:orig_category":"Werbung",
    "sg:phone":"+41 41 761 33 44",
    "sg:postcode":"6340",
    "sg:province":"Zug",
    "wof:name":"Ehrat Annoncen",
    "wof:placetype":"venue"
},
  "geometry": {"coordinates":[8.5208940506,47.1857833862],"type":"Point"}
}