{
  "type": "Feature",
  "properties": {
    "iso:country":"CH",
    "sg:address":"Zurlindenstrasse 51 8003 Z\u00fcrich. Postfach",
    "sg:city":"Z\u00fcrich",
    "sg:orig_category":"Detailhandel mit M\u00f6beln U Haushaltsgegenst\u00e4nden",
    "sg:phone":"+41 14638670",
    "sg:postcode":"8001",
    "sg:province":"Z\u00fcrich",
    "wof:name":"M\u00f6bel-rindlisbacher. M\u00f6beln U. Teppiche; Handel",
    "wof:placetype":"venue"
},
  "geometry": {"coordinates":[8.5209236145,47.3691673279],"type":"Point"}
}