{
  "type": "Feature",
  "properties": {
    "iso:country":"CH",
    "sg:address":"1173",
    "sg:city":"F\u00e9chy",
    "sg:orig_category":"Grosshandel mit Getr\u00e4nken Rebbau",
    "sg:phone":"+41 21 808 51 41",
    "sg:postcode":"1173",
    "sg:province":"Vaud",
    "wof:name":"Pelichet Jacques",
    "wof:placetype":"venue"
},
  "geometry": {"coordinates":[6.3741102219,46.4814109802],"type":"Point"}
}