{
  "type": "Feature",
  "properties": {
    "iso:country":"CH",
    "sg:address":"Rue Abb\u00e9 Bovet 3",
    "sg:city":"Broc",
    "sg:classifiers":[
        {
            "category":"Personal",
            "subcategory":"Shoe Repair & Shine",
            "type":"Services"
        }
    ],
    "sg:phone":"+41 26 921 82 10",
    "sg:postcode":"1636",
    "sg:province":"Fribourg",
    "sg:tags":[
        "injection",
        "moulding",
        "plastic"
    ],
    "wof:name":"Plaspaq S.a.",
    "wof:placetype":"venue"
},
  "geometry": {"coordinates":[7.0979819298,46.6055030823],"type":"Point"}
}