{
  "type": "Feature",
  "properties": {
    "iso:country":"CH",
    "sg:address":"Z\u00fcrcherstrasse 13",
    "sg:city":"Siebnen",
    "sg:orig_category":"Detailhandel mit Waren verschiedener Art, Hauptrichtung Nahrungsmittel Grosshandel mit Nahrungsmitte",
    "sg:phone":"+41 55 440 13 88",
    "sg:postcode":"8854",
    "sg:province":"Schwyz",
    "wof:name":"Keel Ren\u00e9",
    "wof:placetype":"venue"
},
  "geometry": {"coordinates":[8.8950357437,47.175239563],"type":"Point"}
}