{
  "type": "Feature",
  "properties": {
    "iso:country":"CH",
    "sg:address":"Spalenring 17",
    "sg:city":"Basel",
    "sg:orig_category":"Detailhandel mit Waren verschiedener Art, Hauptrichtung Nahrungsmittel",
    "sg:phone":"+41 61 383 86 88",
    "sg:postcode":"4055",
    "sg:province":"Basel-Stadt",
    "wof:name":"Sathiy Stores Gmbh Lebensmittelgesch\u00e4ft",
    "wof:placetype":"venue"
},
  "geometry": {"coordinates":[7.5744071007,47.5608062744],"type":"Point"}
}