{
  "type": "Feature",
  "properties": {
    "iso:country":"CH",
    "sg:address":"Rue Des Anciens-bains 4 1180 Rolle. Postfach",
    "sg:city":"Rolle",
    "sg:orig_category":"Vermietung U Verpachtung von eigenen Immobilien Vermittlung von Immobilien",
    "sg:phone":"+41 61 312 80 20",
    "sg:postcode":"1180",
    "sg:province":"Vaud",
    "wof:name":"Immoteam Ag",
    "wof:placetype":"venue"
},
  "geometry": {"coordinates":[7.5961198807,47.5111083984],"type":"Point"}
}