{
  "type": "Feature",
  "properties": {
    "iso:country":"CH",
    "sg:address":"8594 G\u00fcttingen. Postfach",
    "sg:city":"G\u00fcttingen",
    "sg:orig_category":"Detailhandel mit Waren verschiedener Art, Hauptrichtung Nahrungsmittel",
    "sg:postcode":"8594",
    "sg:province":"Thurgau",
    "wof:name":"Landwirtschaftliche Genossenschaft Hasliberg Und Umgebung",
    "wof:placetype":"venue"
},
  "geometry": {"coordinates":[8.2025403976,46.7372512817],"type":"Point"}
}