{
  "type": "Feature",
  "properties": {
    "iso:country":"CH",
    "sg:address":"La Mauguettaz",
    "sg:city":"Yvonand",
    "sg:orig_category":"Verarbeitung von Milch Verwertung von Milch",
    "sg:postcode":"1462",
    "sg:province":"Vaud",
    "wof:name":"Soci\u00e9t\u00e9 De Laiterie De Lajoux Et Environs",
    "wof:placetype":"venue"
},
  "geometry": {"coordinates":[7.1378297806,47.2788200378],"type":"Point"}
}