{
  "type": "Feature",
  "properties": {
    "iso:country":"CH",
    "sg:address":"Hinterrebenstrasse 5",
    "sg:city":"Gebenstorf",
    "sg:orig_category":"Fachdetailhandel mit pharmazeutischen Produkten",
    "sg:postcode":"5412",
    "sg:province":"Aargau",
    "wof:name":"Suter A., Etablissement Emfa",
    "wof:placetype":"venue"
},
  "geometry": {"coordinates":[7.6656851768,46.7333221436],"type":"Point"}
}