{
  "type": "Feature",
  "properties": {
    "iso:country":"CH",
    "sg:address":"Stockerenweg 16 3000 Bern. Postfach",
    "sg:city":"Bern",
    "sg:orig_category":"Softwareentwicklung U beratung",
    "sg:postcode":"3014",
    "sg:province":"Bern",
    "wof:name":"Hirsbrunner Informatik Gmbh",
    "wof:placetype":"venue"
},
  "geometry": {"coordinates":[7.4529910088,46.9590759277],"type":"Point"}
}