{
  "type": "Feature",
  "properties": {
    "iso:country":"CH",
    "sg:address":"Im Halbiacker 9",
    "sg:city":"Elsau",
    "sg:orig_category":"Dienstleistungen, Versorger",
    "sg:phone":"+41 52 368 72 72",
    "sg:postcode":"8352",
    "sg:province":"Z\u00fcrich",
    "wof:name":"Elektro Gobo Ag",
    "wof:placetype":"venue"
},
  "geometry": {"coordinates":[8.784471,47.501537],"type":"Point"}
}