{
  "type": "Feature",
  "properties": {
    "iso:country":"CH",
    "sg:address":"Dolderstrasse 2",
    "sg:city":"Z\u00fcrich",
    "sg:orig_category":"Detailhandel mit Radio U Fernsehger\u00e4ten Herstellung von Radio U Fernsehger\u00e4ten sowie phono U videote",
    "sg:phone":"+41 12516156",
    "sg:postcode":"8032",
    "sg:province":"Z\u00fcrich",
    "wof:name":"Bertschi's Teleklinik Audio Video Shop",
    "wof:placetype":"venue"
},
  "geometry": {"coordinates":[8.5569982529,47.3700294495],"type":"Point"}
}