{
  "type": "Feature",
  "properties": {
    "iso:country":"CH",
    "sg:address":"Landstrasse 99",
    "sg:city":"Wettingen",
    "sg:orig_category":"Arztpraxen",
    "sg:phone":"+41 56 427 20 60",
    "sg:postcode":"5430",
    "sg:province":"Aargau",
    "wof:name":"Dr.med.bruno W\u00fcthrich Spezialarzt Fmh",
    "wof:placetype":"venue"
},
  "geometry": {"coordinates":[8.327234,47.465748],"type":"Point"}
}