{
  "type": "Feature",
  "properties": {
    "iso:country":"CH",
    "sg:address":"Rue Lamartine 1",
    "sg:city":"Gen\u00e8ve",
    "sg:orig_category":"Arztpraxen",
    "sg:phone":"+41 22 344 38 34",
    "sg:postcode":"1203",
    "sg:province":"Gen\u00e8ve",
    "wof:name":"Dr M\u00e9d. Jean-claude Bonvin M\u00e9decin Sp\u00e9cialiste Fmh",
    "wof:placetype":"venue"
},
  "geometry": {"coordinates":[6.128409,46.208607],"type":"Point"}
}