{
  "type": "Feature",
  "properties": {
    "iso:country":"CH",
    "sg:address":"Dorf 2 9427 Wolfhalden. Postfach",
    "sg:city":"Wolfhalden",
    "sg:orig_category":"Verkehrs- and Tourismusb\u00fcros",
    "sg:phone":"+41 71 891 55 91",
    "sg:postcode":"9427",
    "sg:province":"Appenzell Ausserrhoden",
    "wof:name":"Verkehrsb\u00fcro",
    "wof:placetype":"venue"
},
  "geometry": {"coordinates":[9.5489397049,47.4538002014],"type":"Point"}
}