{
  "type": "Feature",
  "properties": {
    "iso:country":"CH",
    "sg:address":"Talstrasse 83 8001 Z\u00fcrich. Postfach",
    "sg:city":"Z\u00fcrich",
    "sg:orig_category":"Privatbanken",
    "sg:phone":"+41 71 242 64 64",
    "sg:postcode":"8023",
    "sg:province":"Z\u00fcrich",
    "wof:name":"Wegelin & Co Privatbankiers Gesellschafter Bruderer, Hummler, Tolle & Co.",
    "wof:placetype":"venue"
},
  "geometry": {"coordinates":[9.3778295517,47.4264297485],"type":"Point"}
}