{
  "type": "Feature",
  "properties": {
    "iso:country":"CH",
    "sg:address":"Hauptstrasse 73",
    "sg:city":"Einsiedeln",
    "sg:classifiers":[
        {
            "category":"Restaurant",
            "type":"Food & Drink"
        }
    ],
    "sg:phone":"+41 55 412 24 83",
    "sg:postcode":"8840",
    "sg:province":"Schwyz",
    "wof:name":"Restaurant Zur Glocke",
    "wof:placetype":"venue"
},
  "geometry": {"coordinates":[8.749080658,47.1270751953],"type":"Point"}
}