{
  "type": "Feature",
  "properties": {
    "iso:country":"CH",
    "sg:address":"Kapplerstrasse 16",
    "sg:city":"Ebnat-kappel",
    "sg:orig_category":"Detailhandel mit Waren verschiedener Art, Hauptrichtung Nahrungsmittel",
    "sg:phone":"+41 71 993 14 92",
    "sg:postcode":"9642",
    "sg:province":"St. Gallen",
    "wof:name":"Migros-markt",
    "wof:placetype":"venue"
},
  "geometry": {"coordinates":[9.120806694,47.2649230957],"type":"Point"}
}