{
  "type": "Feature",
  "properties": {
    "iso:country":"CH",
    "sg:address":"Walke 9100 Herisau. Postfach",
    "sg:city":"Herisau",
    "sg:orig_category":"Herstellung von Gummi U Kunststoffwaren Herstellung von Werkzeugmaschinen",
    "sg:phone":"+41 71 352 58 88",
    "sg:postcode":"9102",
    "sg:province":"Appenzell Ausserrhoden",
    "wof:name":"Atp Kunststofftechnik Ag",
    "wof:placetype":"venue"
},
  "geometry": {"coordinates":[9.2953453064,47.3919906616],"type":"Point"}
}