{
  "type": "Feature",
  "properties": {
    "addr:full":"Rue Pestalozzi 1 Yverdon-les-bains Vaud 1400",
    "addr:housenumber":"1",
    "addr:postcode":"1400",
    "addr:street":"Rue Pestalozzi",
    "iso:country":"CH",
    "sg:address":"Rue Pestalozzi 1",
    "sg:city":"Yverdon-les-bains",
    "sg:orig_category":"Arztpraxen",
    "sg:phone":"+41 32 967 96 36",
    "sg:postcode":"1400",
    "sg:province":"Vaud",
    "wof:name":"Dr M\u00e9d. Irma Felber M\u00e9decin G\u00e9n\u00e9rale",
    "wof:placetype":"venue"
},
  "geometry": {"coordinates":[6.830084,47.103977],"type":"Point"}
}