{
  "type": "Feature",
  "properties": {
    "iso:country":"CH",
    "sg:address":"Pierre-pertuis Rue De 14",
    "sg:city":"Tavannes",
    "sg:orig_category":"Vermietung U Verpachtung von eigenen Immobilien",
    "sg:postcode":"2710",
    "sg:province":"Bern",
    "wof:name":"Henri Schaller S\u00e0rl",
    "wof:placetype":"venue"
},
  "geometry": {"coordinates":[7.1973881721,47.2195777893],"type":"Point"}
}