{
  "type": "Feature",
  "properties": {
    "iso:country":"CH",
    "sg:address":"Schulgasse 22",
    "sg:city":"L\u00f6hningen",
    "sg:orig_category":"Primarschulen",
    "sg:phone":"+41 52 681 36 87",
    "sg:postcode":"8224",
    "sg:province":"Schaffhausen",
    "wof:name":"Primarschule",
    "wof:placetype":"venue"
},
  "geometry": {"coordinates":[8.5531291962,47.7002639771],"type":"Point"}
}