{
  "type": "Feature",
  "properties": {
    "iso:country":"CH",
    "sg:address":"Baumschulweg 8a",
    "sg:city":"Meggen",
    "sg:orig_category":"Sportschulen Ski-& Snowboardschulen Sportvereine Ski",
    "sg:phone":"+41 41 377 49 31",
    "sg:postcode":"6045",
    "sg:province":"Luzern",
    "wof:name":"Ski-club-skischule Luzern",
    "wof:placetype":"venue"
},
  "geometry": {"coordinates":[8.3849220276,47.0581588745],"type":"Point"}
}