{
  "type": "Feature",
  "properties": {
    "iso:country":"CH",
    "sg:address":"Weidenpark 1",
    "sg:city":"M\u00f6hlin",
    "sg:orig_category":"Gymnastik U Fitnesszentren Saunas, Solarien, Fitnesszentren U \u00e4hnliches",
    "sg:phone":"+41 61 851 56 00",
    "sg:postcode":"4313",
    "sg:province":"Aargau",
    "wof:name":"Olympia Fit-line Gmbh",
    "wof:placetype":"venue"
},
  "geometry": {"coordinates":[7.8402910233,47.5601501465],"type":"Point"}
}