{
  "type": "Feature",
  "properties": {
    "iso:country":"CH",
    "sg:address":"L\u00f6bernweg 1 6330 Cham. Postfach 275",
    "sg:city":"Cham",
    "sg:orig_category":"Herstellung von elektrischen Lampen U Leuchten",
    "sg:postcode":"6330",
    "sg:province":"Zug",
    "wof:name":"Cgs, Collaird",
    "wof:placetype":"venue"
},
  "geometry": {"coordinates":[6.7695250511,46.5411186218],"type":"Point"}
}