{
  "type": "Feature",
  "properties": {
    "iso:country":"CH",
    "sg:address":"Niedermatt 397",
    "sg:city":"Zuzgen",
    "sg:orig_category":"Architektur U Ingenieurb\u00fcros",
    "sg:phone":"+41 61 873 00 48",
    "sg:postcode":"4315",
    "sg:province":"Aargau",
    "wof:name":"Zimmermann & Gerber Gmbh",
    "wof:placetype":"venue"
},
  "geometry": {"coordinates":[7.899109,47.524399],"type":"Point"}
}