{
  "type": "Feature",
  "properties": {
    "iso:country":"CH",
    "sg:address":"Pommier Rue Du 12 2000 Neuenburg Case Postale 406",
    "sg:city":"Neuenburg",
    "sg:orig_category":"Unclassifiable Establishments",
    "sg:postcode":"2000",
    "sg:province":"Neuch\u00e2tel",
    "wof:name":"Fm Und Logistik Gmbh",
    "wof:placetype":"venue"
},
  "geometry": {"coordinates":[8.7943048477,47.3647117615],"type":"Point"}
}