{
  "type": "Feature",
  "properties": {
    "addr:full":"Chemin Des Roseaux 5 Hauterive Neuch\u00e2tel 2068",
    "addr:housenumber":"5",
    "addr:postcode":"2068",
    "addr:street":"Chemin Des Roseaux;Neucha\u0302Tel",
    "iso:country":"CH",
    "sg:address":"Chemin Des Roseaux 5",
    "sg:city":"Hauterive",
    "sg:orig_category":"Autogaragen",
    "sg:postcode":"2068",
    "sg:province":"Neuch\u00e2tel",
    "wof:name":"Gilbert Brauen Garage V\u00e9hitechnique",
    "wof:placetype":"venue"
},
  "geometry": {"coordinates":[6.972457,47.009468],"type":"Point"}
}