{
  "type": "Feature",
  "properties": {
    "iso:country":"CH",
    "sg:address":"Luegisland",
    "sg:city":"Ruswil",
    "sg:classifiers":[
        {
            "category":"Manufacturing",
            "subcategory":"Lumber",
            "type":"Manufacturing & Wholesale Goods"
        }
    ],
    "sg:phone":"+41 41 495 12 27",
    "sg:postcode":"6017",
    "sg:province":"Luzern",
    "sg:tags":[
        "hardwood",
        "sawmill"
    ],
    "wof:name":"Robert H\u00fcsler S\u00e4gewerk, Holzhandel, Holzschindel",
    "wof:placetype":"venue"
},
  "geometry": {"coordinates":[8.1267347336,47.0835609436],"type":"Point"}
}