{
  "type": "Feature",
  "properties": {
    "iso:country":"CH",
    "sg:address":"Rain 7",
    "sg:city":"Ittigen",
    "sg:orig_category":"Polizei",
    "sg:phone":"+41 31 722 88 41",
    "sg:postcode":"3063",
    "sg:province":"Bern",
    "wof:name":"Kantonale Polizei",
    "wof:placetype":"venue"
},
  "geometry": {"coordinates":[7.4783039093,46.9765014648],"type":"Point"}
}