{
  "type": "Feature",
  "properties": {
    "iso:country":"CH",
    "sg:address":"Bahnhofstrasse 38 5000 Aarau. Postfach",
    "sg:city":"Aarau",
    "sg:orig_category":"Sonstiges Versicherungsgewerbe",
    "sg:phone":"+41 62 837 82 00",
    "sg:postcode":"5000",
    "sg:province":"Aargau",
    "wof:name":"Sportversicherungskasse Des Schweizerischen Turnverbandes",
    "wof:placetype":"venue"
},
  "geometry": {"coordinates":[8.0479593277,47.39112854],"type":"Point"}
}