{
  "type": "Feature",
  "properties": {
    "iso:country":"CH",
    "sg:address":"3123",
    "sg:city":"Belp",
    "sg:orig_category":"Sportvereine Sch\u00fctzen Pistolen-& Gewehr",
    "sg:phone":"+41 26 496 24 07",
    "sg:postcode":"3123",
    "sg:province":"Bern",
    "wof:name":"Pistolenklub",
    "wof:placetype":"venue"
},
  "geometry": {"coordinates":[7.2485399246,46.8556518555],"type":"Point"}
}