{
  "type": "Feature",
  "properties": {
    "iso:country":"CH",
    "sg:address":"Thalgarten",
    "sg:city":"Wila",
    "sg:orig_category":"Primarschulen",
    "sg:phone":"+41 52 385 13 52",
    "sg:postcode":"8492",
    "sg:province":"Z\u00fcrich",
    "wof:name":"Primarschule Thalgarten",
    "wof:placetype":"venue"
},
  "geometry": {"coordinates":[8.8682670593,47.4088554382],"type":"Point"}
}