{
  "type": "Feature",
  "properties": {
    "iso:country":"CH",
    "sg:address":"Sch\u00f6nenwerderstrasse 51",
    "sg:city":"Aarau",
    "sg:orig_category":"Werbeagenturen Werbegrafikateliers",
    "sg:phone":"+41 62 824 40 14",
    "sg:postcode":"5000",
    "sg:province":"Aargau",
    "wof:name":"Xaver B\u00fcrgi Grafik & Werbung",
    "wof:placetype":"venue"
},
  "geometry": {"coordinates":[8.038394928,47.386051178],"type":"Point"}
}