{
  "type": "Feature",
  "properties": {
    "iso:country":"CH",
    "sg:address":"Comercialstrasse 19",
    "sg:city":"Chur",
    "sg:orig_category":"Stukkateurgewerbe, Gipserei U Verputzerei",
    "sg:phone":"+41 56 622 08 66",
    "sg:postcode":"7000",
    "sg:province":"Graubunden",
    "wof:name":"Koch Franz Gips Und Verputz Gmbh",
    "wof:placetype":"venue"
},
  "geometry": {"coordinates":[8.2682619095,47.3264045715],"type":"Point"}
}