{
  "type": "Feature",
  "properties": {
    "iso:country":"CH",
    "sg:address":"St.-karli-strasse 54",
    "sg:city":"Luzern",
    "sg:orig_category":"Hom\u00f6opathie",
    "sg:phone":"+41 41 240 86 56",
    "sg:postcode":"6004",
    "sg:province":"Luzern",
    "wof:name":"Andrea Fivian Praxis F\u00fcr Hom\u00f6opathie",
    "wof:placetype":"venue"
},
  "geometry": {"coordinates":[8.2889556885,47.0568504333],"type":"Point"}
}