{
  "type": "Feature",
  "properties": {
    "addr:full":"M\u00fchlezelgstrasse 45 8047 Z\u00fcrich. Postfach Z\u00fcrich Z\u00fcrich 8047",
    "addr:housenumber":"45",
    "addr:postcode":"8047 zuerich. postfach;8047",
    "addr:street":"Muehlezelgstrasse",
    "iso:country":"CH",
    "sg:address":"M\u00fchlezelgstrasse 45 8047 Z\u00fcrich. Postfach",
    "sg:city":"Z\u00fcrich",
    "sg:orig_category":"Allgemeiner Hoch U Tiefbau",
    "sg:phone":"+41 14913433",
    "sg:postcode":"8047",
    "sg:province":"Z\u00fcrich",
    "wof:name":"Gode Contracting And Participations Ag",
    "wof:placetype":"venue"
},
  "geometry": {"coordinates":[8.493138,47.376877],"type":"Point"}
}