{
  "type": "Feature",
  "properties": {
    "iso:country":"CH",
    "sg:address":"Schaffhauserstrasse 227",
    "sg:city":"Beringen",
    "sg:classifiers":[
        {
            "category":"Restaurant",
            "type":"Food & Drink"
        }
    ],
    "sg:phone":"+41 71 393 14 63",
    "sg:postcode":"8222",
    "sg:province":"Schaffhausen",
    "wof:name":"Restaurant Engel",
    "wof:placetype":"venue"
},
  "geometry": {"coordinates":[9.1714801788,47.4311790466],"type":"Point"}
}