{
  "type": "Feature",
  "properties": {
    "iso:country":"CH",
    "sg:address":"Hauptstrasse 81",
    "sg:city":"Degersheim",
    "sg:orig_category":"Detailhandel mit Waren verschiedener Art, Hauptrichtung Nahrungsmittel",
    "sg:phone":"+41 71 371 12 64",
    "sg:postcode":"9113",
    "sg:province":"St. Gallen",
    "wof:name":"Coop Ostschweiz",
    "wof:placetype":"venue"
},
  "geometry": {"coordinates":[9.1964797974,47.372467041],"type":"Point"}
}