{
  "type": "Feature",
  "properties": {
    "iso:country":"CH",
    "sg:address":"Manessestrasse 190",
    "sg:city":"Z\u00fcrich",
    "sg:orig_category":"Tankstellen",
    "sg:phone":"+41 12025205",
    "sg:postcode":"8045",
    "sg:province":"Z\u00fcrich",
    "wof:name":"Agip (suisse) Sa Tankstelle",
    "wof:placetype":"venue"
},
  "geometry": {"coordinates":[8.5224885941,47.3611946106],"type":"Point"}
}