{
  "type": "Feature",
  "properties": {
    "iso:country":"CH",
    "sg:address":"Gunzgen Nord",
    "sg:city":"Gunzgen",
    "sg:orig_category":"Tankstellen",
    "sg:postcode":"4617",
    "sg:province":"Solothurn",
    "wof:name":"Autobahntankstelle Migrol Z'graggen Paul",
    "wof:placetype":"venue"
},
  "geometry": {"coordinates":[7.8253178596,47.3132362366],"type":"Point"}
}