{
  "type": "Feature",
  "properties": {
    "iso:country":"CH",
    "sg:address":"1773",
    "sg:city":"Chandon",
    "sg:orig_category":"Herstellung von sonstigen landwirtschaftlichen Maschinen Mechanische Werkst\u00e4tten",
    "sg:phone":"+41 26 475 11 60",
    "sg:postcode":"1773",
    "sg:province":"Fribourg",
    "wof:name":"J\u00e9r\u00f4me Christian Atelier M\u00e9canique",
    "wof:placetype":"venue"
},
  "geometry": {"coordinates":[7.0473098755,46.8386802673],"type":"Point"}
}