{
  "type": "Feature",
  "properties": {
    "iso:country":"CH",
    "sg:address":"Neugut",
    "sg:city":"Bauma",
    "sg:orig_category":"Vereine Musik/Blasmusik",
    "sg:postcode":"8494",
    "sg:province":"Z\u00fcrich",
    "wof:name":"Musikverein Harmonie",
    "wof:placetype":"venue"
},
  "geometry": {"coordinates":[8.8577442169,47.3746109009],"type":"Point"}
}