{
  "type": "Feature",
  "properties": {
    "iso:country":"CH",
    "sg:address":"M\u00fchlegasse 1",
    "sg:city":"Unter\u00e4geri",
    "sg:orig_category":"Allgemeiner Hoch U Tiefbau",
    "sg:postcode":"6314",
    "sg:province":"Zug",
    "wof:name":"Hulliger Otto Ag",
    "wof:placetype":"venue"
},
  "geometry": {"coordinates":[8.207264,47.482414],"type":"Point"}
}