{
  "type": "Feature",
  "properties": {
    "iso:country":"CH",
    "sg:address":"Cholplatzweg 13 7203 Trimmis. Postfach",
    "sg:city":"Trimmis",
    "sg:orig_category":"Zimmerei, Dachdeckerei, Bauspenglerei U Abdichtung",
    "sg:postcode":"7203",
    "sg:province":"Graubunden",
    "wof:name":"Walli Christof Holzbau Gmbh",
    "wof:placetype":"venue"
},
  "geometry": {"coordinates":[9.5530719757,46.90259552],"type":"Point"}
}