{
  "type": "Feature",
  "properties": {
    "iso:country":"CH",
    "sg:address":"Schloss Mayenfels",
    "sg:city":"Pratteln",
    "sg:orig_category":"Primarschulen Vorschulen, Kinderg\u00e4rten",
    "sg:phone":"+41 61 821 22 66",
    "sg:postcode":"4133",
    "sg:province":"Basel-Landschaft",
    "wof:name":"Rudolf Steiner-schule Mayenfels",
    "wof:placetype":"venue"
},
  "geometry": {"coordinates":[7.6823921204,47.5148277283],"type":"Point"}
}