{
  "type": "Feature",
  "properties": {
    "iso:country":"CH",
    "sg:address":"Alpenstrasse 9 6300 Zug. Postfach",
    "sg:city":"Zug",
    "sg:orig_category":"Wirtschaftspr\u00fcfung, Steuerberatung U Treuhand",
    "sg:postcode":"6300",
    "sg:province":"Zug",
    "wof:name":"Noraton Ag",
    "wof:placetype":"venue"
},
  "geometry": {"coordinates":[8.5144662857,47.1723403931],"type":"Point"}
}