{
  "type": "Feature",
  "properties": {
    "addr:full":"Via Beroldingen 8 Mendrisio Ticino 6850",
    "addr:housenumber":"8",
    "addr:postcode":"6850",
    "addr:street":"Via Beroldingen",
    "iso:country":"CH",
    "sg:address":"Via Beroldingen 8",
    "sg:city":"Mendrisio",
    "sg:orig_category":"Advokaturb\u00fcros Notariate",
    "sg:phone":"+41 33 951 10 10",
    "sg:postcode":"6850",
    "sg:province":"Ticino",
    "wof:name":"Adrian Glatthard Advokatur-& Notariatsb\u00fcro",
    "wof:placetype":"venue"
},
  "geometry": {"coordinates":[8.031138,46.754341],"type":"Point"}
}