{
  "type": "Feature",
  "properties": {
    "iso:country":"CH",
    "sg:address":"Route Principale 21",
    "sg:city":"Orvin",
    "sg:orig_category":"Elektro- and elektronische Maschinen Grosshandel",
    "sg:phone":"+41 77317753",
    "sg:postcode":"2534",
    "sg:province":"Bern",
    "wof:name":"Comelect Electrotechnique",
    "wof:placetype":"venue"
},
  "geometry": {"coordinates":[7.2160391808,47.1611404419],"type":"Point"}
}