{
  "type": "Feature",
  "properties": {
    "iso:country":"CH",
    "sg:address":"Stationsstrasse 8713 Uerikon. Postfach",
    "sg:city":"Uerikon",
    "sg:orig_category":"RESTAURANTS: TEA-ROOMS",
    "sg:postcode":"8713",
    "sg:province":"Z\u00fcrich",
    "wof:name":"Restaurant Bahnhof, Ungricht Iris",
    "wof:placetype":"venue"
},
  "geometry": {"coordinates":[8.7546110153,47.2366638184],"type":"Point"}
}