{
  "type": "Feature",
  "properties": {
    "iso:country":"CH",
    "sg:address":"Bahnhofstr. 41 2540 Grenchen. Postfach 1125",
    "sg:city":"Grenchen",
    "sg:orig_category":"Detailhandel mit medizinischen U orthop\u00e4dischen Artikeln Drogerien",
    "sg:phone":"+41 32 652 52 61",
    "sg:postcode":"2540",
    "sg:province":"Solothurn",
    "wof:name":"Bahnhof-drogerie Otto Saxer",
    "wof:placetype":"venue"
},
  "geometry": {"coordinates":[7.3972477913,47.1895065308],"type":"Point"}
}