{
  "type": "Feature",
  "properties": {
    "iso:country":"CH",
    "sg:address":"Murtenstrasse 13",
    "sg:city":"Biel/bienne",
    "sg:orig_category":"Detailhandel mit elektrischen Haushaltsger\u00e4ten",
    "sg:phone":"+41 56 493 61 41",
    "sg:postcode":"2502",
    "sg:province":"Bern",
    "wof:name":"Hk-dws Gmbh Haushaltger\u00e4te",
    "wof:placetype":"venue"
},
  "geometry": {"coordinates":[8.2858104706,47.454208374],"type":"Point"}
}