{
  "type": "Feature",
  "properties": {
    "iso:country":"CH",
    "sg:address":"Neuhof",
    "sg:city":"Allenwinden",
    "sg:orig_category":"Verarbeitung von Milch Verwertung von Milch",
    "sg:postcode":"6319",
    "sg:province":"Zug",
    "wof:name":"Milchgenossenschaft Allenwinden & Umgebung",
    "wof:placetype":"venue"
},
  "geometry": {"coordinates":[8.556394577,47.164276123],"type":"Point"}
}