{
  "type": "Feature",
  "properties": {
    "iso:country":"CH",
    "sg:address":"Hauptstrasse 149 4416 Bubendorf. Postfach",
    "sg:city":"Bubendorf",
    "sg:orig_category":"Herstellung von Schl\u00f6ssern U Beschl\u00e4gen",
    "sg:phone":"+41 17391111",
    "sg:postcode":"4416",
    "sg:province":"Basel-Landschaft",
    "wof:name":"Iten Franz Ag",
    "wof:placetype":"venue"
},
  "geometry": {"coordinates":[8.4493608475,47.3559455872],"type":"Point"}
}