{
  "type": "Feature",
  "properties": {
    "iso:country":"CH",
    "sg:address":"Schulgasse 5",
    "sg:city":"Lyss",
    "sg:orig_category":"Detailhandel mit Brot, Back U S\u00fcsswaren",
    "sg:phone":"+41 32 384 55 59",
    "sg:postcode":"3250",
    "sg:province":"Bern",
    "wof:name":"Michael Rogen Lyssbach Beck",
    "wof:placetype":"venue"
},
  "geometry": {"coordinates":[7.305718,47.072502],"type":"Point"}
}