{
  "type": "Feature",
  "properties": {
    "iso:country":"CH",
    "sg:address":"Birkenweg 1 9249 Algetshausen. Postfach 50",
    "sg:city":"Uzwil",
    "sg:orig_category":"Grosshandel mit chemischen Erzeugnissen",
    "sg:phone":"+41 71 951 13 51",
    "sg:postcode":"9240",
    "sg:province":"St. Gallen",
    "wof:name":"Swipe Ag",
    "wof:placetype":"venue"
},
  "geometry": {"coordinates":[9.1089305878,47.4453353882],"type":"Point"}
}