{
  "type": "Feature",
  "properties": {
    "iso:country":"CH",
    "sg:address":"Chemin Du Foron 43",
    "sg:city":"Th\u00f4nex",
    "sg:orig_category":"Malerei Tapeziererei",
    "sg:phone":"+41 31 382 44 00",
    "sg:postcode":"1226",
    "sg:province":"Gen\u00e8ve",
    "wof:name":"Bernasconi-tapeten Tapeten-handel; Tapeziererarbeiten.",
    "wof:placetype":"venue"
},
  "geometry": {"coordinates":[7.4115190506,46.9488983154],"type":"Point"}
}