{
  "type": "Feature",
  "properties": {
    "iso:country":"CH",
    "sg:address":"Via Ciseri 2",
    "sg:city":"Lugano",
    "sg:classifiers":[
        {
            "category":"Bars & Pubs",
            "type":"Food & Drink"
        }
    ],
    "sg:phone":"+41 91 923 41 98",
    "sg:postcode":"6900",
    "sg:province":"Ticino",
    "sg:tags":[
        "restaurant"
    ],
    "wof:name":"Caff\u00e8 Flippersbar",
    "wof:placetype":"venue"
},
  "geometry": {"coordinates":[8.953316,46.010151],"type":"Point"}
}