{
  "type": "Feature",
  "properties": {
    "addr:full":"Chalet Aiguille-verte Chesi\u00e8res Vaud 1885",
    "addr:housenumber":"1885",
    "iso:country":"CH",
    "sg:address":"Chalet Aiguille-verte",
    "sg:city":"Chesi\u00e8res",
    "sg:orig_category":"Detailhandel mit Brennstoffen U Heizmaterial",
    "sg:phone":"+41 24 495 72 34",
    "sg:postcode":"1885",
    "sg:province":"Vaud",
    "wof:name":"Jean-michel Moret Combustibles",
    "wof:placetype":"venue"
},
  "geometry": {"coordinates":[7.04348,46.301109],"type":"Point"}
}