{
  "type": "Feature",
  "properties": {
    "iso:country":"CH",
    "sg:address":"8272 Ermatingen. Postfach",
    "sg:city":"Ermatingen",
    "sg:classifiers":[
        {
            "category":"Education",
            "subcategory":"Library",
            "type":"Public Place"
        }
    ],
    "sg:postcode":"8272",
    "sg:province":"Thurgau",
    "sg:tags":[
        "u",
        "bibliotheken",
        "archive"
    ],
    "wof:name":"Reformierte Pfarrbibliothek",
    "wof:placetype":"venue"
},
  "geometry": {"coordinates":[8.91345,47.27433],"type":"Point"}
}