{
  "type": "Feature",
  "properties": {
    "iso:country":"CH",
    "sg:address":"Stanserstrasse 111",
    "sg:city":"Kerns",
    "sg:classifiers":[
        {
            "category":"Manufacturing",
            "subcategory":"Tools & Machinery",
            "type":"Manufacturing & Wholesale Goods"
        }
    ],
    "sg:phone":"+41 41 660 38 38",
    "sg:postcode":"6064",
    "sg:province":"Obwalden",
    "sg:tags":[
        "electric"
    ],
    "wof:name":"Hartwerkzeug Kerns Gmbh",
    "wof:placetype":"venue"
},
  "geometry": {"coordinates":[8.279299736,46.903339386],"type":"Point"}
}