{
  "type": "Feature",
  "properties": {
    "iso:country":"CH",
    "sg:address":"Hardstrasse 37-45",
    "sg:city":"Muttenz",
    "sg:orig_category":"Pensionskassen",
    "sg:postcode":"4132",
    "sg:province":"Basel-Landschaft",
    "wof:name":"D\u00fcrst-haass Stiftung",
    "wof:placetype":"venue"
},
  "geometry": {"coordinates":[7.6539640427,47.5306510925],"type":"Point"}
}