{
  "type": "Feature",
  "properties": {
    "iso:country":"CH",
    "sg:address":"D\u00e4gerlon",
    "sg:city":"Silenen",
    "sg:orig_category":"Grosshandel mit Getr\u00e4nken",
    "sg:phone":"+41 41 880 24 66",
    "sg:postcode":"6473",
    "sg:province":"Uri",
    "wof:name":"Tresch Walter",
    "wof:placetype":"venue"
},
  "geometry": {"coordinates":[8.6690816879,46.7924613953],"type":"Point"}
}