{
  "type": "Feature",
  "properties": {
    "iso:country":"CH",
    "sg:address":"Route Cantonale 283",
    "sg:city":"V\u00e9troz",
    "sg:orig_category":"Herstellung von Teppichen Parkettleger",
    "sg:phone":"+41 27 346 03 10",
    "sg:postcode":"1963",
    "sg:province":"Valais",
    "wof:name":"Blanc & Cie Sa, Succursale De V\u00e9troz (valais)",
    "wof:placetype":"venue"
},
  "geometry": {"coordinates":[7.2598071098,46.2159919739],"type":"Point"}
}