{
  "type": "Feature",
  "properties": {
    "iso:country":"CH",
    "sg:address":"Rehhagstrasse 9",
    "sg:city":"H\u00f6lstein",
    "sg:orig_category":"Grosshandel mit Holz U Baustoffen",
    "sg:postcode":"4434",
    "sg:province":"Basel-Landschaft",
    "wof:name":"Borgeaud-pahud Edouard",
    "wof:placetype":"venue"
},
  "geometry": {"coordinates":[6.6260199547,46.5942802429],"type":"Point"}
}