{
  "type": "Feature",
  "properties": {
    "iso:country":"CH",
    "sg:address":"Chemin Grangettes 11",
    "sg:city":"L'auberson",
    "sg:orig_category":"Tankstellen",
    "sg:phone":"+41 24 454 35 31",
    "sg:postcode":"1454",
    "sg:province":"Vaud",
    "wof:name":"Claude Bornand Station-service Shell",
    "wof:placetype":"venue"
},
  "geometry": {"coordinates":[6.4585638046,46.8174705505],"type":"Point"}
}