{
  "type": "Feature",
  "properties": {
    "iso:country":"CH",
    "sg:address":"1078 Essertes. Postfach",
    "sg:city":"Freiburg",
    "sg:orig_category":"RESTAURANTS: TEA-ROOMS",
    "sg:postcode":"1700",
    "sg:province":"Fribourg",
    "wof:name":"Babou Sa",
    "wof:placetype":"venue"
},
  "geometry": {"coordinates":[6.1420788765,46.185218811],"type":"Point"}
}