{
  "type": "Feature",
  "properties": {
    "iso:country":"CH",
    "sg:address":"G\u00fcggel",
    "sg:city":"Aedermannsdorf",
    "sg:orig_category":"Landw. Genossenschaften Pferdezucht Landw. Genossenschaften Viehzucht",
    "sg:postcode":"4714",
    "sg:province":"Solothurn",
    "wof:name":"Kaltblutpferdezucht- Genossenschaft Falkenstein",
    "wof:placetype":"venue"
},
  "geometry": {"coordinates":[7.5845460892,47.3239250183],"type":"Point"}
}