{
  "type": "Feature",
  "properties": {
    "iso:country":"CH",
    "sg:address":"Freiestrasse 2",
    "sg:city":"Biel/bienne",
    "sg:orig_category":"Detailhandel Reparatur von Gebrauchsg\u00fctern",
    "sg:phone":"+41 32 342 20 13",
    "sg:postcode":"2502",
    "sg:province":"Bern",
    "wof:name":"Sex-shop Euro-tica",
    "wof:placetype":"venue"
},
  "geometry": {"coordinates":[7.2480897903,47.1412315369],"type":"Point"}
}