{
  "type": "Feature",
  "properties": {
    "iso:country":"CH",
    "sg:address":"Neuhausstrasse 3 4057 Basel. Postfach 128",
    "sg:city":"Basel",
    "sg:orig_category":"Druck ohne Zeitungsdruck Offsetdruck",
    "sg:phone":"+41 41 835 15 36",
    "sg:postcode":"4019",
    "sg:province":"Basel-Stadt",
    "wof:name":"Druckerei Scheller J.",
    "wof:placetype":"venue"
},
  "geometry": {"coordinates":[7.5930762291,47.582736969],"type":"Point"}
}