{
  "type": "Feature",
  "properties": {
    "iso:country":"CH",
    "sg:address":"Ruvigliana Via 40",
    "sg:city":"Viganello",
    "sg:orig_category":"Vermietung U Verpachtung von eigenen Immobilien",
    "sg:postcode":"6962",
    "sg:province":"Ticino",
    "wof:name":"Valletorre Sa",
    "wof:placetype":"venue"
},
  "geometry": {"coordinates":[8.9716720581,46.0104446411],"type":"Point"}
}