{
  "type": "Feature",
  "properties": {
    "iso:country":"CH",
    "sg:address":"Rue Du Pont",
    "sg:city":"St-prex",
    "sg:orig_category":"Vorschulen, Kinderg\u00e4rten",
    "sg:postcode":"1162",
    "sg:province":"Vaud",
    "wof:name":"Ecole Enfantine I & Ii Pavillon Scolaire",
    "wof:placetype":"venue"
},
  "geometry": {"coordinates":[6.4598650932,46.480266571],"type":"Point"}
}