{
  "type": "Feature",
  "properties": {
    "iso:country":"CH",
    "sg:address":"Hochfeld",
    "sg:city":"Ganterschwil",
    "sg:orig_category":"Sportvereine Sch\u00fctzen",
    "sg:phone":"+41 71 983 37 63",
    "sg:postcode":"9608",
    "sg:province":"St. Gallen",
    "wof:name":"Milit\u00e4rsch\u00fctzenverein",
    "wof:placetype":"venue"
},
  "geometry": {"coordinates":[9.0838708878,47.3861351013],"type":"Point"}
}