{
  "type": "Feature",
  "properties": {
    "iso:country":"CH",
    "sg:address":"Niederholzstrasse 17 8951 Fahrweid. Postfach 518",
    "sg:city":"Dietikon",
    "sg:orig_category":"Grosshandel mit Eisenwaren sowie Installationsbedarf f\u00fcr Gas, Wasser U Heizung Herstellung von Werkz",
    "sg:phone":"+41 17493939",
    "sg:postcode":"8953",
    "sg:province":"Z\u00fcrich",
    "wof:name":"Leitz Gmbh Holzbearbeitungswerkzeuge",
    "wof:placetype":"venue"
},
  "geometry": {"coordinates":[8.4141273499,47.4078063965],"type":"Point"}
}