{
  "type": "Feature",
  "properties": {
    "iso:country":"CH",
    "sg:address":"Rischli 6173 Fl\u00fchli Lu. Postfach",
    "sg:city":"S\u00f6renberg",
    "sg:orig_category":"Elektroinstallation",
    "sg:phone":"+41 41 488 16 09",
    "sg:postcode":"6174",
    "sg:province":"Luzern",
    "wof:name":"Bucher Erwin.",
    "wof:placetype":"venue"
},
  "geometry": {"coordinates":[8.0188684464,46.8269424438],"type":"Point"}
}