{
  "type": "Feature",
  "properties": {
    "iso:country":"CH",
    "sg:address":"Route Des Barges",
    "sg:city":"Vouvry",
    "sg:orig_category":"Herstellung von Pflanzenschutzmitteln U sonstigen agro- chemikalischen Erzeugnissen",
    "sg:phone":"+41 24 482 52 40",
    "sg:postcode":"1896",
    "sg:province":"Valais",
    "wof:name":"Syngenta Crop Protection Monthey Sa",
    "wof:placetype":"venue"
},
  "geometry": {"coordinates":[6.8988218307,46.3373756409],"type":"Point"}
}