{
  "type": "Feature",
  "properties": {
    "iso:country":"CH",
    "sg:address":"Recordon Avenue 32is 1004 Lausanne. Postfach",
    "sg:city":"Lausanne",
    "sg:orig_category":"Finanzierungsinstitutionen",
    "sg:phone":"+41 21 624 40 45",
    "sg:postcode":"1003",
    "sg:province":"Vaud",
    "wof:name":"Behbehani Lausanne Sa Op\u00e9rat. Financi\u00e8res, Commerce De Produits Et Marchandises Et Administr. Et Gestion De Biens.",
    "wof:placetype":"venue"
},
  "geometry": {"coordinates":[6.6155428886,46.5274887085],"type":"Point"}
}