{
  "type": "Feature",
  "properties": {
    "iso:country":"CH",
    "sg:address":"Wiese",
    "sg:city":"Nesslau",
    "sg:orig_category":"Instandhaltung U Reparatur von Automobilen",
    "sg:phone":"+41 71 994 18 15",
    "sg:postcode":"9650",
    "sg:province":"St. Gallen",
    "wof:name":"Alfred Fr\u00fch Central-garage",
    "wof:placetype":"venue"
},
  "geometry": {"coordinates":[9.2002048492,47.2264556885],"type":"Point"}
}