{
  "type": "Feature",
  "properties": {
    "iso:country":"CH",
    "sg:address":"Riond-bosson 1110 Morges. Postfach",
    "sg:city":"Morges",
    "sg:orig_category":"Sonstiges Versicherungsgewerbe",
    "sg:phone":"+41 21 802 89 89",
    "sg:postcode":"1110",
    "sg:province":"Vaud",
    "wof:name":"Caisse Maladie-accident Philos",
    "wof:placetype":"venue"
},
  "geometry": {"coordinates":[6.4858150482,46.5049514771],"type":"Point"}
}