{
  "type": "Feature",
  "properties": {
    "iso:country":"CH",
    "sg:address":"Grabenstrasse 1",
    "sg:city":"Werdenberg",
    "sg:classifiers":[
        {
            "category":"Restaurant",
            "type":"Food & Drink"
        }
    ],
    "sg:phone":"+41 81 771 46 46",
    "sg:postcode":"9470",
    "sg:province":"St. Gallen",
    "wof:name":"Restaurant Chayio",
    "wof:placetype":"venue"
},
  "geometry": {"coordinates":[9.4621143341,47.1695556641],"type":"Point"}
}