{
  "type": "Feature",
  "properties": {
    "iso:country":"CH",
    "sg:address":"Promenade Des Vignes",
    "sg:city":"Veyras",
    "sg:classifiers":[
        {
            "category":"Insurance",
            "subcategory":"Insurance Agent",
            "type":"Services"
        }
    ],
    "sg:phone":"+41 27 455 53 92",
    "sg:postcode":"3968",
    "sg:province":"Valais",
    "sg:tags":[
        "versicherungsagenturen",
        "-broker"
    ],
    "wof:name":"Assurances Charles Perren",
    "wof:placetype":"venue"
},
  "geometry": {"coordinates":[7.5344772339,46.3042030334],"type":"Point"}
}