{
  "type": "Feature",
  "properties": {
    "iso:country":"CH",
    "sg:address":"Florissant Route De 4 1206 Gen\u00e8ve. Postfach",
    "sg:city":"Gen\u00e8ve",
    "sg:orig_category":"Allgemeiner Hoch U Tiefbau",
    "sg:postcode":"1206",
    "sg:province":"Gen\u00e8ve",
    "wof:name":"Temple Ingenierie Sa",
    "wof:placetype":"venue"
},
  "geometry": {"coordinates":[6.154022,46.196579],"type":"Point"}
}