{
  "type": "Feature",
  "properties": {
    "iso:country":"CH",
    "sg:address":"Gr\u00fcndenstr. 57",
    "sg:city":"Flurlingen",
    "sg:orig_category":"Architektur U Ingenieurb\u00fcros",
    "sg:phone":"+41 52 212 86 42",
    "sg:postcode":"8247",
    "sg:province":"Z\u00fcrich",
    "wof:name":"Ingenieurb\u00fcro B\u00f6ni Ag, Zweigniederlassung Flurlingen",
    "wof:placetype":"venue"
},
  "geometry": {"coordinates":[8.626099,47.687897],"type":"Point"}
}