{
  "type": "Feature",
  "properties": {
    "iso:country":"CH",
    "sg:address":"1772",
    "sg:city":"Grolley",
    "sg:orig_category":"G\u00fcterbef\u00f6rderung im Strassenverkehr",
    "sg:phone":"+41 26 475 31 84",
    "sg:postcode":"1772",
    "sg:province":"Fribourg",
    "wof:name":"Progin-transports Sa",
    "wof:placetype":"venue"
},
  "geometry": {"coordinates":[7.0707321167,46.8333053589],"type":"Point"}
}