{
  "type": "Feature",
  "properties": {
    "iso:country":"CH",
    "sg:address":"3235",
    "sg:city":"Erlach",
    "sg:orig_category":"Polizei",
    "sg:phone":"+41 27 957 22 45",
    "sg:postcode":"3235",
    "sg:province":"Bern",
    "wof:name":"Kantonale Polizei",
    "wof:placetype":"venue"
},
  "geometry": {"coordinates":[7.933672905,46.1117172241],"type":"Point"}
}