{
  "type": "Feature",
  "properties": {
    "iso:country":"CH",
    "sg:address":"Z\u00fcrichstrasse 28 8840 Einsiedeln. Postfach 446",
    "sg:city":"Einsiedeln",
    "sg:orig_category":"Allgemeiner Hochbau Strassenbau",
    "sg:phone":"+41 55 412 71 71",
    "sg:postcode":"8840",
    "sg:province":"Schwyz",
    "wof:name":"Aufdermaur S\u00f6hne Ag",
    "wof:placetype":"venue"
},
  "geometry": {"coordinates":[8.744094,47.130505],"type":"Point"}
}