{
  "type": "Feature",
  "properties": {
    "iso:country":"CH",
    "sg:address":"Sixer 16",
    "sg:city":"Sargans",
    "sg:orig_category":"Gartenbau Landschaftsplanungsb\u00fcros U Gartenarchitekturb\u00fcros",
    "sg:phone":"+41 81 723 36 33",
    "sg:postcode":"7320",
    "sg:province":"St. Gallen",
    "wof:name":"Otto St\u00fcdli Gartenarchitektur",
    "wof:placetype":"venue"
},
  "geometry": {"coordinates":[9.4392547607,47.0527458191],"type":"Point"}
}