{
  "type": "Feature",
  "properties": {
    "iso:country":"CH",
    "sg:address":"Habstettenstrasse 20",
    "sg:city":"Bolligen",
    "sg:orig_category":"Vorschulen, Kinderg\u00e4rten",
    "sg:phone":"+41 31 921 60 47",
    "sg:postcode":"3065",
    "sg:province":"Bern",
    "wof:name":"Kindergarten Bodenacker",
    "wof:placetype":"venue"
},
  "geometry": {"coordinates":[7.4983072281,46.9813804626],"type":"Point"}
}