{
  "type": "Feature",
  "properties": {
    "iso:country":"CH",
    "sg:address":"St. Alban-vorstadt 16 4052 Basel. Postfach",
    "sg:city":"Basel",
    "sg:orig_category":"Fachdetailhandel in Verkaufsr\u00e4umen",
    "sg:postcode":"4051",
    "sg:province":"Basel-Stadt",
    "wof:name":"Belle Cose Pecher Dagmar Warenhandel, Bes. Mit Geschenkartikeln",
    "wof:placetype":"venue"
},
  "geometry": {"coordinates":[7.5953001976,47.554523468],"type":"Point"}
}