{
  "type": "Feature",
  "properties": {
    "iso:country":"CH",
    "sg:address":"Fischermatt 2b",
    "sg:city":"M\u00fchlethurnen",
    "sg:orig_category":"Gartenbau",
    "sg:phone":"+41 31 809 15 80",
    "sg:postcode":"3127",
    "sg:province":"Bern",
    "wof:name":"Dorfg\u00e4rtnerei Ch.schaller",
    "wof:placetype":"venue"
},
  "geometry": {"coordinates":[7.509062767,46.8141326904],"type":"Point"}
}