{
  "type": "Feature",
  "properties": {
    "iso:country":"CH",
    "sg:address":"Unterdorfstrasse 19",
    "sg:city":"Lausen",
    "sg:orig_category":"Fachdetailhandel mit pharmazeutischen Produkten Grosshandel mit pharmazeutischen Erzeugnissen",
    "sg:phone":"+41 61 923 91 03",
    "sg:postcode":"4415",
    "sg:province":"Basel-Landschaft",
    "wof:name":"Ergo-pharm Gmbh",
    "wof:placetype":"venue"
},
  "geometry": {"coordinates":[7.7602472305,47.4726448059],"type":"Point"}
}