{
  "type": "Feature",
  "properties": {
    "iso:country":"CH",
    "sg:address":"Weidstrasse 2",
    "sg:city":"Zwillikon",
    "sg:orig_category":"Fernmeldedienste Sonstiger Grosshandel",
    "sg:phone":"+41 14630921",
    "sg:postcode":"8909",
    "sg:province":"Z\u00fcrich",
    "wof:name":"Wis Worldwide Information System Kobel",
    "wof:placetype":"venue"
},
  "geometry": {"coordinates":[8.4315872192,47.287689209],"type":"Point"}
}