{
  "type": "Feature",
  "properties": {
    "iso:country":"CH",
    "sg:address":"Vergers Chemin Des 4",
    "sg:city":"Yvonand",
    "sg:orig_category":"Fernmeldedienste",
    "sg:phone":"+41 24 430 03 40",
    "sg:postcode":"1462",
    "sg:province":"Vaud",
    "wof:name":"Syn&sys Sa",
    "wof:placetype":"venue"
},
  "geometry": {"coordinates":[6.7450752258,46.7997283936],"type":"Point"}
}