{
  "type": "Feature",
  "properties": {
    "iso:country":"CH",
    "sg:address":"Falkenstrasse 14 8008 Z\u00fcrich. Postfach 4856",
    "sg:city":"Z\u00fcrich",
    "sg:orig_category":"Interessenvertretungen",
    "sg:phone":"+41 41 727 67 80",
    "sg:postcode":"8008",
    "sg:province":"Z\u00fcrich",
    "wof:name":"Vereinigung Der Importeure Pharmazeutischer Spezialit\u00e4ten (vips)",
    "wof:placetype":"venue"
},
  "geometry": {"coordinates":[8.5479202271,47.3649635315],"type":"Point"}
}