{
  "type": "Feature",
  "properties": {
    "iso:country":"CH",
    "sg:address":"Schwarzenburgstrasse 829",
    "sg:city":"Niederscherli",
    "sg:orig_category":"Non-Classified Establishments",
    "sg:postcode":"3145",
    "sg:province":"Bern",
    "wof:name":"Gesundheitsquelle Kn\u00f6pfel-kerbic Eva.",
    "wof:placetype":"venue"
},
  "geometry": {"coordinates":[9.0447912216,47.4644012451],"type":"Point"}
}