{
  "type": "Feature",
  "properties": {
    "iso:country":"CH",
    "sg:address":"Via Motta 57a",
    "sg:city":"Massagno",
    "sg:orig_category":"Sanit\u00e4r, Heizungs U L\u00fcftungsinstallation Sanit\u00e4rinstallation",
    "sg:phone":"+41 79 337 33 54",
    "sg:postcode":"6900",
    "sg:province":"Ticino",
    "wof:name":"Bruno Tresoldi Sa Imp.sanitari & Riscaldamenti",
    "wof:placetype":"venue"
},
  "geometry": {"coordinates":[8.9456539154,46.0120391846],"type":"Point"}
}