{
  "type": "Feature",
  "properties": {
    "iso:country":"CH",
    "sg:address":"Allenberg",
    "sg:city":"B\u00e4retswil",
    "sg:orig_category":"Sportvereine Sch\u00fctzen Pistolen-& Gewehr",
    "sg:phone":"+41 19392425",
    "sg:postcode":"8344",
    "sg:province":"Z\u00fcrich",
    "wof:name":"Pistolensch\u00fctzen Am Bachtel",
    "wof:placetype":"venue"
},
  "geometry": {"coordinates":[8.8783226013,47.335899353],"type":"Point"}
}