{
  "type": "Feature",
  "properties": {
    "iso:country":"CH",
    "sg:address":"Vogelr\u00fcti 114",
    "sg:city":"Niederrohrdorf",
    "sg:orig_category":"Herstellung von Konstruktionsteilen, Fertigbauteilen U Ausbauelementen aus Holz Herstellung von Schr",
    "sg:phone":"+41 56 496 15 59",
    "sg:postcode":"5443",
    "sg:province":"Aargau",
    "wof:name":"Huser Schreinerei-wagnerei",
    "wof:placetype":"venue"
},
  "geometry": {"coordinates":[8.3126897812,47.4152183533],"type":"Point"}
}