{
  "type": "Feature",
  "properties": {
    "addr:full":"Oberzelgli 4 3273 Kappelen. Postfach Kappelen Bern 3273",
    "addr:housenumber":"4",
    "addr:postcode":"3273 kappelen. postfach;3273",
    "addr:street":"Oberzelgli",
    "iso:country":"CH",
    "sg:address":"Oberzelgli 4 3273 Kappelen. Postfach",
    "sg:city":"Kappelen",
    "sg:orig_category":"Abbruch U Sprenggewerbe, Erdbewegungsarbeiten",
    "sg:postcode":"3273",
    "sg:province":"Bern",
    "wof:name":"Hofmann Kappelen",
    "wof:placetype":"venue"
},
  "geometry": {"coordinates":[7.262887,47.056942],"type":"Point"}
}