{
  "type": "Feature",
  "properties": {
    "iso:country":"CH",
    "sg:address":"W\u00fclflingerstrasse 380 8408 Winterthur. Postfach",
    "sg:city":"Winterthur",
    "sg:orig_category":"Wirtschaftspr\u00fcfung, Steuerberatung U Treuhand",
    "sg:phone":"+41 52 222 92 07",
    "sg:postcode":"8408",
    "sg:province":"Z\u00fcrich",
    "wof:name":"Treubau Winterthur Ag",
    "wof:placetype":"venue"
},
  "geometry": {"coordinates":[8.6813306808,47.5158309937],"type":"Point"}
}