{
  "type": "Feature",
  "properties": {
    "iso:country":"CH",
    "sg:address":"Rubigenstrasse 38",
    "sg:city":"Belp",
    "sg:orig_category":"Tierarztpraxis",
    "sg:phone":"+41 31 819 11 77",
    "sg:postcode":"3123",
    "sg:province":"Bern",
    "wof:name":"Dres R. Willener & G. Oppliger Tier\u00e4rzte",
    "wof:placetype":"venue"
},
  "geometry": {"coordinates":[7.501912117,46.8923797607],"type":"Point"}
}