{
  "type": "Feature",
  "properties": {
    "iso:country":"CH",
    "sg:address":"St. Johanns-vorstadt 74",
    "sg:city":"Basel",
    "sg:orig_category":"Detailhandel mit Geschenkartikeln U Souvenirs Kunsthandel",
    "sg:phone":"+41 61 322 10 55",
    "sg:postcode":"4056",
    "sg:province":"Basel-Stadt",
    "wof:name":"Boutique Zem Helgeli Bilder & Geschenke",
    "wof:placetype":"venue"
},
  "geometry": {"coordinates":[7.5833630562,47.5651664734],"type":"Point"}
}