{
  "type": "Feature",
  "properties": {
    "iso:country":"CH",
    "sg:address":"Avenue De Marcelin 2",
    "sg:city":"Morges",
    "sg:orig_category":"Landesverteidigung, Sozialversicherung \u00d6ffentliche Verwaltung",
    "sg:phone":"+41 21 804 97 60",
    "sg:postcode":"1110",
    "sg:province":"Vaud",
    "wof:name":"Protection Civile R\u00e9gion De Morges",
    "wof:placetype":"venue"
},
  "geometry": {"coordinates":[6.4929161072,46.5117263794],"type":"Point"}
}