{
  "type": "Feature",
  "properties": {
    "iso:country":"CH",
    "sg:address":"Chem G\u00e9rard-de-ternier 18",
    "sg:city":"Petit-lancy",
    "sg:classifiers":[
        {
            "category":"Professional",
            "subcategory":"Business Services",
            "type":"Services"
        }
    ],
    "sg:phone":"+41 22 792 25 45",
    "sg:postcode":"1213",
    "sg:province":"Gen\u00e8ve",
    "sg:tags":[
        "training",
        "advice"
    ],
    "wof:name":"Restaurant Cepia Coop-geneve",
    "wof:placetype":"venue"
},
  "geometry": {"coordinates":[6.106874,46.195118],"type":"Point"}
}