{
  "type": "Feature",
  "properties": {
    "iso:country":"CH",
    "sg:address":"Route De Vissigen 18",
    "sg:city":"Sion",
    "sg:orig_category":"Herstellung von Karosserien U Anh\u00e4ngern",
    "sg:phone":"+41 21 634 56 25",
    "sg:postcode":"1950",
    "sg:province":"Valais",
    "wof:name":"Carrosserie Rodel Et Cie",
    "wof:placetype":"venue"
},
  "geometry": {"coordinates":[6.5833220482,46.5328636169],"type":"Point"}
}