{
  "type": "Feature",
  "properties": {
    "iso:country":"CH",
    "sg:address":"Avenue De France 35",
    "sg:city":"Gen\u00e8ve",
    "sg:orig_category":"Detailhandel mit fotografischen Artikeln Grosshandel mit sonstigen Gebrauchs U Verbrauchsg\u00fctern",
    "sg:phone":"+41 22 734 84 84",
    "sg:postcode":"1202",
    "sg:province":"Gen\u00e8ve",
    "wof:name":"Charpilloz Photo & Cie",
    "wof:placetype":"venue"
},
  "geometry": {"coordinates":[6.1421051025,46.2206497192],"type":"Point"}
}