{
  "type": "Feature",
  "properties": {
    "iso:country":"CH",
    "sg:address":"Rue Du Parc 4",
    "sg:city":"Gen\u00e8ve",
    "sg:orig_category":"Handelsvermittlung U Grosshandel Sonstige mit der Informatik verbundene T\u00e4tigkeiten",
    "sg:phone":"+41 91 912 28 80",
    "sg:postcode":"1207",
    "sg:province":"Gen\u00e8ve",
    "wof:name":"It Trading S\u00e0rl Equipements Informatiques Dans Le Monde Entier, En Partic. Sur Les March\u00e9s \u00e9mergents; Commerce, Location Etc",
    "wof:placetype":"venue"
},
  "geometry": {"coordinates":[6.1559967995,46.2014350891],"type":"Point"}
}