{
  "type": "Feature",
  "properties": {
    "iso:country":"CH",
    "sg:address":"Tachlisbrunnenstrasse 23",
    "sg:city":"Winterthur",
    "sg:orig_category":"Arztpraxen",
    "sg:phone":"+41 52 213 23 25",
    "sg:postcode":"8400",
    "sg:province":"Z\u00fcrich",
    "wof:name":"Dres Med.j. Fr\u00f6licher & J.benz Spezial\u00e4rzte Fmh",
    "wof:placetype":"venue"
},
  "geometry": {"coordinates":[8.728632,47.509804],"type":"Point"}
}