{
  "type": "Feature",
  "properties": {
    "iso:country":"CH",
    "sg:address":"4006 Basel. Postfach",
    "sg:city":"Basel",
    "sg:orig_category":"Sportvereine Ballsport Fussball",
    "sg:phone":"+41 31 371 54 35",
    "sg:postcode":"4006",
    "wof:name":"As Tricolore",
    "wof:placetype":"venue"
},
  "geometry": {"coordinates":[7.4001741409,46.9423446655],"type":"Point"}
}