{
  "type": "Feature",
  "properties": {
    "iso:country":"CH",
    "sg:address":"Rue Du Coll\u00e8ge 5 1820 Montreux. Postfach",
    "sg:city":"Clarens",
    "sg:orig_category":"RESTAURANTS: TEA-ROOMS",
    "sg:phone":"+41 41 811 15 48",
    "sg:postcode":"1815",
    "sg:province":"Vaud",
    "wof:name":"B\u00fcrgler Karl, Restaurant Mythenblick",
    "wof:placetype":"venue"
},
  "geometry": {"coordinates":[8.6183691025,46.9815864563],"type":"Point"}
}