{
  "type": "Feature",
  "properties": {
    "iso:country":"CH",
    "sg:address":"Blumenrainstrasse 13 9050 Appenzell. Postfach",
    "sg:city":"Appenzell",
    "sg:orig_category":"Handels-H\u00e4user U Gesellschaften",
    "sg:phone":"+41 71 787 22 52",
    "sg:postcode":"9050",
    "sg:province":"Appenzell Innerhoden",
    "wof:name":"Edelweiss Corporation Ag Waren, Ger\u00e4te U. Produkte; Handel, Import, Export Usw",
    "wof:placetype":"venue"
},
  "geometry": {"coordinates":[9.4151525497,47.3316040039],"type":"Point"}
}