{
  "type": "Feature",
  "properties": {
    "iso:country":"CH",
    "sg:address":"R\u00e4ffelstrasse 20 8045 Z\u00fcrich. Postfach",
    "sg:city":"Z\u00fcrich",
    "sg:orig_category":"G\u00fcterbef\u00f6rderung im Strassenverkehr Lagerung",
    "sg:phone":"+41 18166677",
    "sg:postcode":"8045",
    "sg:province":"Z\u00fcrich",
    "wof:name":"Kuoni Transport Ag",
    "wof:placetype":"venue"
},
  "geometry": {"coordinates":[8.5141983032,47.3634681702],"type":"Point"}
}