{
  "type": "Feature",
  "properties": {
    "iso:country":"CH",
    "sg:address":"Rebbergstrasse 43c",
    "sg:city":"Zofingen",
    "sg:orig_category":"Architektur U Ingenieurb\u00fcros Architekturb\u00fcros",
    "sg:phone":"+41 62 751 84 40",
    "sg:postcode":"4800",
    "sg:province":"Aargau",
    "wof:name":"Werner Schmutz Architektur + Planungs Ag",
    "wof:placetype":"venue"
},
  "geometry": {"coordinates":[7.953105,47.291866],"type":"Point"}
}