{
  "type": "Feature",
  "properties": {
    "iso:country":"CH",
    "sg:address":"Piazza Nosetto 5",
    "sg:city":"Bellinzona",
    "sg:orig_category":"Detailhandel mit Uhren U Schmuck",
    "sg:phone":"+41 91 825 95 65",
    "sg:postcode":"6500",
    "sg:province":"Ticino",
    "wof:name":"Arteor Sa Lavorazione Artigianale Di Gioelleria Ecc.",
    "wof:placetype":"venue"
},
  "geometry": {"coordinates":[9.0224561691,46.1909294128],"type":"Point"}
}