{
  "type": "Feature",
  "properties": {
    "iso:country":"CH",
    "sg:address":"Chemin Du Ch\u00eane 16",
    "sg:city":"Oron-la-ville",
    "sg:orig_category":"Unclassifiable Establishments",
    "sg:postcode":"1610",
    "sg:province":"Vaud",
    "wof:name":"Tonacini S\u00e0rl",
    "wof:placetype":"venue"
},
  "geometry": {"coordinates":[6.8245720863,46.5695152283],"type":"Point"}
}