{
  "type": "Feature",
  "properties": {
    "iso:country":"CH",
    "sg:address":"Ryf 34",
    "sg:city":"Murten",
    "sg:orig_category":"Kunsthandel",
    "sg:phone":"+41 26 670 18 05",
    "sg:postcode":"3280",
    "sg:province":"Fribourg",
    "wof:name":"Peter Hegar Einrahmungen",
    "wof:placetype":"venue"
},
  "geometry": {"coordinates":[7.1163330078,46.9291648865],"type":"Point"}
}