{
  "type": "Feature",
  "properties": {
    "iso:country":"CH",
    "sg:address":"4812",
    "sg:city":"M\u00fchlethal",
    "sg:orig_category":"Primarschulen",
    "sg:phone":"+41 62 751 20 60",
    "sg:postcode":"4812",
    "sg:province":"Aargau",
    "wof:name":"Primarschule",
    "wof:placetype":"venue"
},
  "geometry": {"coordinates":[7.9802799225,47.3040084839],"type":"Point"}
}