{
  "type": "Feature",
  "properties": {
    "iso:country":"CH",
    "sg:address":"Rue St-antoine 1",
    "sg:city":"Avenches",
    "sg:orig_category":"Arztpraxen",
    "sg:phone":"+41 21 635 74 88",
    "sg:postcode":"1580",
    "sg:province":"Vaud",
    "wof:name":"Dr M\u00e9d. Edouard Boulos M\u00e9decin Sp\u00e9cialiste Fmh",
    "wof:placetype":"venue"
},
  "geometry": {"coordinates":[6.582439,46.538795],"type":"Point"}
}