{
  "type": "Feature",
  "properties": {
    "iso:country":"CH",
    "sg:address":"1407",
    "sg:city":"Donneloye",
    "sg:orig_category":"Detailhandel mit Waren verschiedener Art, Hauptrichtung Nichtnahrungsmittel",
    "sg:phone":"+41 24 433 13 49",
    "sg:postcode":"1407",
    "sg:province":"Vaud",
    "wof:name":"Electro Secours, Bohler Pierre",
    "wof:placetype":"venue"
},
  "geometry": {"coordinates":[6.7151279449,46.7428970337],"type":"Point"}
}