{
  "type": "Feature",
  "properties": {
    "iso:country":"CH",
    "sg:address":"1166 Perroy. Postfach",
    "sg:city":"Perroy",
    "sg:orig_category":"Pensionskassen",
    "sg:phone":"+41 21 822 13 13",
    "sg:postcode":"1166",
    "sg:province":"Vaud",
    "wof:name":"Fondation De Pr\u00e9voyance De La Soci\u00e9t\u00e9 Vinicole De Perroy",
    "wof:placetype":"venue"
},
  "geometry": {"coordinates":[6.3654952049,46.467716217],"type":"Point"}
}