{
  "type": "Feature",
  "properties": {
    "addr:full":"Poststrasse 4 8634 Hombrechtikon. Postfach 278 Hombrechtikon Z\u00fcrich 8634",
    "addr:housenumber":"4;278",
    "addr:postcode":"8634;8634",
    "addr:street":"Poststrasse;Postfach",
    "iso:country":"CH",
    "sg:address":"Poststrasse 4 8634 Hombrechtikon. Postfach 278",
    "sg:city":"Hombrechtikon",
    "sg:orig_category":"Grosshandel mit Spielwaren",
    "sg:phone":"+41 55 264 18 00",
    "sg:postcode":"8634",
    "sg:province":"Z\u00fcrich",
    "wof:name":"Robert Kuhn Ag Spielwarengrosshandel",
    "wof:placetype":"venue"
},
  "geometry": {"coordinates":[8.770274,47.251644],"type":"Point"}
}