{
  "type": "Feature",
  "properties": {
    "iso:country":"CH",
    "sg:address":"Eichb\u00fchl",
    "sg:city":"Altishofen",
    "sg:orig_category":"Instandhaltung U Reparatur von Automobilen",
    "sg:phone":"+41 62 756 50 77",
    "sg:postcode":"6246",
    "sg:province":"Luzern",
    "wof:name":"Garage Eichb\u00fchl Erni",
    "wof:placetype":"venue"
},
  "geometry": {"coordinates":[7.9667601585,47.2026443481],"type":"Point"}
}