{
  "type": "Feature",
  "properties": {
    "iso:country":"CH",
    "sg:address":"Hofacherstrasse 6",
    "sg:city":"Winkel",
    "sg:orig_category":"Sanit\u00e4r, Heizungs U L\u00fcftungsinstallation",
    "sg:phone":"+41 34 402 14 52",
    "sg:postcode":"8185",
    "sg:province":"Z\u00fcrich",
    "wof:name":"Hans Fankhauser Ag",
    "wof:placetype":"venue"
},
  "geometry": {"coordinates":[7.757589817,46.9491271973],"type":"Point"}
}