{
  "type": "Feature",
  "properties": {
    "iso:country":"CH",
    "sg:address":"4618",
    "sg:city":"Boningen",
    "sg:orig_category":"Landesverteidigung, Sozialversicherung \u00d6ffentliche Verwaltung",
    "sg:phone":"+41 62 216 41 45",
    "sg:postcode":"4618",
    "sg:province":"Solothurn",
    "wof:name":"Zivilschutzstelle Boningen",
    "wof:placetype":"venue"
},
  "geometry": {"coordinates":[7.8518800735,47.3009414673],"type":"Point"}
}