{
  "type": "Feature",
  "properties": {
    "iso:country":"CH",
    "sg:address":"Zugerstrasse 39",
    "sg:city":"Walchwil",
    "sg:orig_category":"Fernmeldedienste",
    "sg:postcode":"6318",
    "sg:province":"Zug",
    "wof:name":"Fiberwysel Gmbh",
    "wof:placetype":"venue"
},
  "geometry": {"coordinates":[8.5043525696,47.1078186035],"type":"Point"}
}