{
  "type": "Feature",
  "properties": {
    "iso:country":"CH",
    "sg:address":"Fellenbergstrasse 11",
    "sg:city":"M\u00fcnchenbuchsee",
    "sg:orig_category":"Unternehmensberatung",
    "sg:postcode":"3053",
    "sg:province":"Bern",
    "wof:name":"Adrian Muster",
    "wof:placetype":"venue"
},
  "geometry": {"coordinates":[7.4285578728,46.9768333435],"type":"Point"}
}