{
  "type": "Feature",
  "properties": {
    "iso:country":"CH",
    "sg:address":"Waldeggstrasse 45/47 3097 Liebefeld. Postfach",
    "sg:city":"Liebefeld",
    "sg:orig_category":"Fussboden, Fliesen U Plattenlegerei, Tapeziererei",
    "sg:phone":"+41 31 978 22 22",
    "sg:postcode":"3097",
    "sg:province":"Bern",
    "wof:name":"Inter-parkett Ag",
    "wof:placetype":"venue"
},
  "geometry": {"coordinates":[7.4194221497,46.9325866699],"type":"Point"}
}