{
  "type": "Feature",
  "properties": {
    "iso:country":"CH",
    "sg:address":"Kanderstegstrasse 46",
    "sg:city":"Frutigen",
    "sg:orig_category":"Detailhandel mit Radio U Fernsehger\u00e4ten Detailhandel mit elektrischen Haushalts-,Radio U Fernsehger\u00e4",
    "sg:phone":"+41 33 671 32 71",
    "sg:postcode":"3714",
    "sg:province":"Bern",
    "wof:name":"Hilfiker Werner, Radio Tv Hi-fi",
    "wof:placetype":"venue"
},
  "geometry": {"coordinates":[7.6500821114,46.5841331482],"type":"Point"}
}