{
  "type": "Feature",
  "properties": {
    "iso:country":"CH",
    "sg:address":"Grand-rue 10 1260 Nyon. Postfach",
    "sg:city":"Nyon",
    "sg:orig_category":"Elektroinstallation",
    "sg:phone":"+41 22 362 42 28",
    "sg:postcode":"1260",
    "sg:province":"Vaud",
    "wof:name":"Caliri Nunziato Installations \u00e9lectriques, Informatiques Et T\u00e9l\u00e9phoniques",
    "wof:placetype":"venue"
},
  "geometry": {"coordinates":[6.2389941216,46.3820419312],"type":"Point"}
}