{
  "type": "Feature",
  "properties": {
    "iso:country":"CH",
    "sg:address":"Chemin De Grange-collomb 30",
    "sg:city":"Grand-lancy",
    "sg:orig_category":"Autospenglereien",
    "sg:phone":"+41 19504934",
    "sg:postcode":"1212",
    "sg:province":"Gen\u00e8ve",
    "wof:name":"Francesco Patan\u00e9 Carrosserie",
    "wof:placetype":"venue"
},
  "geometry": {"coordinates":[8.769068,47.364792],"type":"Point"}
}