{
  "type": "Feature",
  "properties": {
    "addr:full":"Talacker 16 Z\u00fcrich Z\u00fcrich 8021",
    "addr:housenumber":"16",
    "addr:postcode":"8021",
    "addr:street":"Talacker",
    "iso:country":"CH",
    "sg:address":"Talacker 16",
    "sg:city":"Z\u00fcrich",
    "sg:classifiers":[
        {
            "category":"Banks & Credit Unions",
            "subcategory":"Bank",
            "type":"Services"
        }
    ],
    "sg:phone":"+41 12112830",
    "sg:postcode":"8021",
    "sg:province":"Z\u00fcrich",
    "wof:name":"Finanz Ag Z\u00fcrich",
    "wof:placetype":"venue"
},
  "geometry": {"coordinates":[8.53705,47.370621],"type":"Point"}
}