{
  "type": "Feature",
  "properties": {
    "iso:country":"CH",
    "sg:address":"Gr\u00fcnaustrasse 8",
    "sg:city":"Rebstein",
    "sg:orig_category":"Malerei-Gipserei Stukkateurgewerbe, Gipserei U Verputzerei",
    "sg:phone":"+41 71 777 24 60",
    "sg:postcode":"9445",
    "sg:province":"St. Gallen",
    "wof:name":"Karl Gschwend Gipsergesch\u00e4ft",
    "wof:placetype":"venue"
},
  "geometry": {"coordinates":[9.5883750916,47.3992004395],"type":"Point"}
}