{
  "type": "Feature",
  "properties": {
    "iso:country":"CH",
    "sg:address":"Allmendhof",
    "sg:city":"Sursee",
    "sg:classifiers":[
        {
            "category":"Building & Trades",
            "subcategory":"Construction",
            "type":"Services"
        }
    ],
    "sg:phone":"+41 41 921 21 87",
    "sg:postcode":"6210",
    "sg:province":"Luzern",
    "sg:tags":[
        "crane"
    ],
    "wof:name":"Beck & Co",
    "wof:placetype":"venue"
},
  "geometry": {"coordinates":[8.099743,47.188499],"type":"Point"}
}