{
  "type": "Feature",
  "properties": {
    "iso:country":"CH",
    "sg:address":"Steinbergstrasse 54",
    "sg:city":"Winterthur",
    "sg:orig_category":"Sonstige pers\u00f6nliche Dienstleistungen",
    "sg:phone":"+41 52 303 05 33",
    "sg:postcode":"8400",
    "sg:province":"Z\u00fcrich",
    "wof:name":"Novator Ag",
    "wof:placetype":"venue"
},
  "geometry": {"coordinates":[8.7273893356,47.4983787537],"type":"Point"}
}