{
  "type": "Feature",
  "properties": {
    "iso:country":"CH",
    "sg:address":"Rte De Cartigny 9",
    "sg:city":"Cartigny",
    "sg:orig_category":"Unclassifiable Establishments",
    "sg:postcode":"1236",
    "sg:province":"Gen\u00e8ve",
    "wof:name":"R. Grandvaux Sa",
    "wof:placetype":"venue"
},
  "geometry": {"coordinates":[6.0369768143,46.1710586548],"type":"Point"}
}