{
  "type": "Feature",
  "properties": {
    "iso:country":"CH",
    "sg:address":"Auberge Communale De F\u00e9chy 1173 F\u00e9chy. Postfach",
    "sg:city":"F\u00e9chy",
    "sg:orig_category":"RESTAURANTS: TEA-ROOMS",
    "sg:postcode":"1173",
    "sg:province":"Vaud",
    "wof:name":"Germanier Alain & Najia",
    "wof:placetype":"venue"
},
  "geometry": {"coordinates":[6.3701400757,46.4815368652],"type":"Point"}
}