{
  "type": "Feature",
  "properties": {
    "iso:country":"CH",
    "sg:address":"Hauptstrasse 53",
    "sg:city":"Grindel",
    "sg:classifiers":[
        {
            "category":"Restaurant",
            "type":"Food & Drink"
        }
    ],
    "sg:phone":"+41 61 761 62 36",
    "sg:postcode":"4247",
    "sg:province":"Solothurn",
    "wof:name":"Restaurant Suter",
    "wof:placetype":"venue"
},
  "geometry": {"coordinates":[7.5018157959,47.3819274902],"type":"Point"}
}