{
  "type": "Feature",
  "properties": {
    "iso:country":"CH",
    "sg:address":"Zugerstrasse 66",
    "sg:city":"Arth",
    "sg:orig_category":"Zimmerei, Dachdeckerei, Bauspenglerei U Abdichtung",
    "sg:phone":"+41 41 855 07 07",
    "sg:postcode":"6415",
    "sg:province":"Schwyz",
    "wof:name":"Zihlmann Holzbau Ag",
    "wof:placetype":"venue"
},
  "geometry": {"coordinates":[8.5257101059,47.0676193237],"type":"Point"}
}