{
  "type": "Feature",
  "properties": {
    "iso:country":"CH",
    "sg:address":"Bignasco 6690 Cavergno. Postfach",
    "sg:city":"Bignasco",
    "sg:orig_category":"RESTAURANTS: TEA-ROOMS",
    "sg:phone":"+41 91 754 22 48",
    "sg:postcode":"6676",
    "sg:province":"Ticino",
    "wof:name":"Ristorante La Froda Di Giovanettina-bertoli Martino E Sara",
    "wof:placetype":"venue"
},
  "geometry": {"coordinates":[8.6107549667,46.3444137573],"type":"Point"}
}