{
  "type": "Feature",
  "properties": {
    "iso:country":"CH",
    "sg:address":"Br\u00fcnigstr. 89",
    "sg:city":"Meiringen",
    "sg:orig_category":"Instandhaltung U Reparatur von Automobilen",
    "sg:phone":"+41 33 971 66 36",
    "sg:postcode":"3860",
    "sg:province":"Bern",
    "wof:name":"Kohler Melchior",
    "wof:placetype":"venue"
},
  "geometry": {"coordinates":[8.1766195297,46.7317085266],"type":"Point"}
}