{
  "type": "Feature",
  "properties": {
    "iso:country":"CH",
    "sg:address":"Gustav-kahlenbach-platz",
    "sg:city":"Rheinfelden",
    "sg:orig_category":"Vorschulen, Kinderg\u00e4rten",
    "sg:phone":"+41 61 831 11 41",
    "sg:postcode":"4310",
    "sg:province":"Aargau",
    "wof:name":"Kindergarten",
    "wof:placetype":"venue"
},
  "geometry": {"coordinates":[7.793200016,47.5543861389],"type":"Point"}
}