{
  "type": "Feature",
  "properties": {
    "iso:country":"CH",
    "sg:address":"Staffelackerstrasse 33",
    "sg:city":"Dietikon",
    "sg:orig_category":"Softwareentwicklung U beratung",
    "sg:phone":"+41 19947374",
    "sg:postcode":"8953",
    "sg:province":"Z\u00fcrich",
    "wof:name":"Schl\u00e4pfer-consulting",
    "wof:placetype":"venue"
},
  "geometry": {"coordinates":[8.6900548935,47.3005561829],"type":"Point"}
}