{
  "type": "Feature",
  "properties": {
    "iso:country":"CH",
    "sg:address":"Hagenacherstrasse 21",
    "sg:city":"Effretikon",
    "sg:orig_category":"Sonstige Institutionen des Sozialwesens ohne Beherbergung",
    "sg:phone":"+41 71 223 22 40",
    "sg:postcode":"8307",
    "sg:province":"Z\u00fcrich",
    "wof:name":"Verein F\u00fcr H\u00f6rbehinderte Beratungsst.f\u00fcr Schwerh\u00f6rige",
    "wof:placetype":"venue"
},
  "geometry": {"coordinates":[9.3720808029,47.4237632751],"type":"Point"}
}