{
  "type": "Feature",
  "properties": {
    "iso:country":"CH",
    "sg:address":"Busskirch",
    "sg:city":"Jona",
    "sg:classifiers":[
        {
            "category":"Restaurant",
            "type":"Food & Drink"
        }
    ],
    "sg:phone":"+41 55 210 86 30",
    "sg:postcode":"8645",
    "sg:province":"St. Gallen",
    "wof:name":"Restaurant Seegartenkeller",
    "wof:placetype":"venue"
},
  "geometry": {"coordinates":[8.8330698013,47.2214012146],"type":"Point"}
}