{
  "type": "Feature",
  "properties": {
    "iso:country":"CH",
    "sg:address":"R\u00f6merstrasse 217",
    "sg:city":"Stadel(winterthur)",
    "sg:orig_category":"Instandhaltung U Reparatur von Automobilen",
    "sg:phone":"+41 56 622 10 39",
    "sg:postcode":"8404",
    "sg:province":"Z\u00fcrich",
    "wof:name":"Auto-elektro-service H. R. Kaufmann",
    "wof:placetype":"venue"
},
  "geometry": {"coordinates":[8.2728281021,47.3444671631],"type":"Point"}
}