{
  "type": "Feature",
  "properties": {
    "iso:country":"CH",
    "sg:address":"Baslerstrasse 87",
    "sg:city":"Pratteln",
    "sg:orig_category":"Grosshandel mit Holz U Baustoffen",
    "sg:postcode":"4133",
    "sg:province":"Basel-Landschaft",
    "wof:name":"Rheintalische Kiesversorgungs Ag",
    "wof:placetype":"venue"
},
  "geometry": {"coordinates":[9.5449409485,47.282371521],"type":"Point"}
}