{
  "type": "Feature",
  "properties": {
    "iso:country":"CH",
    "sg:address":"Via Serafino Balestra 27",
    "sg:city":"Lugano",
    "sg:orig_category":"Non-Classified Establishments",
    "sg:postcode":"6900",
    "sg:province":"Ticino",
    "wof:name":"Ceteris Holding B.v.amsterdam",
    "wof:placetype":"venue"
},
  "geometry": {"coordinates":[8.9577894211,46.0079498291],"type":"Point"}
}