{
  "type": "Feature",
  "properties": {
    "iso:country":"CH",
    "sg:address":"Chardonne Route De 37",
    "sg:city":"Chexbres",
    "sg:orig_category":"Sanit\u00e4r, Heizungs U L\u00fcftungsinstallation",
    "sg:postcode":"1071",
    "sg:province":"Vaud",
    "wof:name":"Bocola Chauffage Et Sanitaire S\u00e0rl",
    "wof:placetype":"venue"
},
  "geometry": {"coordinates":[6.7872838974,46.4811058044],"type":"Point"}
}