{
  "type": "Feature",
  "properties": {
    "iso:country":"CH",
    "sg:address":"Murtenstrasse 34",
    "sg:city":"Frauenkappelen",
    "sg:orig_category":"Non-Classified Establishments",
    "sg:postcode":"3202",
    "sg:province":"Bern",
    "wof:name":"Design Discount Llc, Cheyenne, Succursale De Gen\u00e8ve Mobiliers Et Luminaires Etc. Par Internet; Im, Exportation, Vente",
    "wof:placetype":"venue"
},
  "geometry": {"coordinates":[6.1560301781,46.1997451782],"type":"Point"}
}