{
  "type": "Feature",
  "properties": {
    "iso:country":"CH",
    "sg:address":"Stab.ai Cedri",
    "sg:city":"Vezia",
    "sg:orig_category":"Fachdetailhandel mit pharmazeutischen Produkten",
    "sg:phone":"+41 91 967 19 19",
    "sg:postcode":"6943",
    "sg:province":"Ticino",
    "wof:name":"Farmacia San Marco Sa",
    "wof:placetype":"venue"
},
  "geometry": {"coordinates":[8.9374847412,46.0236434937],"type":"Point"}
}