{
  "type": "Feature",
  "properties": {
    "iso:country":"CH",
    "sg:address":"4712",
    "sg:city":"Laupersdorf",
    "sg:orig_category":"Sportvereine Sch\u00fctzen",
    "sg:phone":"+41 62 293 52 29",
    "sg:postcode":"4712",
    "sg:province":"Solothurn",
    "wof:name":"Feldsch\u00fctzengesellschaft",
    "wof:placetype":"venue"
},
  "geometry": {"coordinates":[7.7530999184,47.3325614929],"type":"Point"}
}