{
  "type": "Feature",
  "properties": {
    "iso:country":"CH",
    "sg:address":"Hofackerstrasse 48 4132 Muttenz. Postfach 244",
    "sg:city":"Muttenz",
    "sg:orig_category":"G\u00fcterbef\u00f6rderung im Strassenverkehr Sonstige Kurierdienste",
    "sg:phone":"+41 61 467 78 78",
    "sg:postcode":"4132",
    "sg:province":"Basel-Landschaft",
    "wof:name":"Dhl Sa",
    "wof:placetype":"venue"
},
  "geometry": {"coordinates":[7.6382770538,47.5362548828],"type":"Point"}
}