{
  "type": "Feature",
  "properties": {
    "iso:country":"CH",
    "sg:address":"Route De La Chapelle 29b",
    "sg:city":"Grand-lancy",
    "sg:orig_category":"Gem\u00fcsebau",
    "sg:phone":"+41 79 695 76 37",
    "sg:postcode":"1212",
    "sg:province":"Gen\u00e8ve",
    "wof:name":"Jean Girardoz Fils Maraicher",
    "wof:placetype":"venue"
},
  "geometry": {"coordinates":[6.9258098602,46.3944625854],"type":"Point"}
}