{
  "type": "Feature",
  "properties": {
    "iso:country":"CH",
    "sg:address":"Chemin Des Bancels 6",
    "sg:city":"Lausanne",
    "sg:orig_category":"Sonstige k\u00fcnstlerische U schriftstellerische T\u00e4tigkeiten U Darbietungen",
    "sg:phone":"+41 21 907 85 93",
    "sg:postcode":"1004",
    "sg:province":"Vaud",
    "wof:name":"Eveline Albisser Atelier De M\u00e9lusine",
    "wof:placetype":"venue"
},
  "geometry": {"coordinates":[6.8542599678,46.5767288208],"type":"Point"}
}