{
  "type": "Feature",
  "properties": {
    "iso:country":"CH",
    "sg:address":"Hohlstr. 534",
    "sg:city":"Z\u00fcrich",
    "sg:classifiers":[
        {
            "category":"Professional",
            "subcategory":"Computer Services",
            "type":"Services"
        }
    ],
    "sg:phone":"+41 4118357500",
    "sg:postcode":"8048",
    "sg:province":"Z\u00fcrich",
    "sg:tags":[
        "information",
        "technology",
        "software"
    ],
    "wof:name":"Comicro-netsys Ag",
    "wof:placetype":"venue"
},
  "geometry": {"coordinates":[8.6482591629,47.404510498],"type":"Point"}
}