{
  "type": "Feature",
  "properties": {
    "iso:country":"CH",
    "sg:address":"Industriestr. 25 Pf 260",
    "sg:city":"Buchs",
    "sg:classifiers":[
        {
            "category":"Manufacturing",
            "subcategory":"Chemicals & Compounds",
            "type":"Manufacturing & Wholesale Goods"
        }
    ],
    "sg:phone":"+41 32 913 17 53",
    "sg:postcode":"9471",
    "sg:province":"St. Gallen",
    "sg:tags":[
        "pharmaceutical",
        "chemistry"
    ],
    "wof:name":"He Finishing Sa",
    "wof:placetype":"venue"
},
  "geometry": {"coordinates":[6.816183,47.09948],"type":"Point"}
}