{
  "type": "Feature",
  "properties": {
    "iso:country":"CH",
    "sg:address":"Rue Du Gravier 2",
    "sg:city":"Porrentruy",
    "sg:orig_category":"RESTAURANTS: TEA-ROOMS",
    "sg:phone":"+41 32 466 19 29",
    "sg:postcode":"2900",
    "sg:province":"Jura",
    "wof:name":"Giordano-bloque Josiane.",
    "wof:placetype":"venue"
},
  "geometry": {"coordinates":[7.0736107826,47.4162139893],"type":"Point"}
}