{
  "type": "Feature",
  "properties": {
    "iso:country":"CH",
    "sg:address":"Signalstrasse 28",
    "sg:city":"Rorschach",
    "sg:orig_category":"Detailhandel mit Zeitungen U Zeitschriften Kioske",
    "sg:phone":"+41 71 841 37 75",
    "sg:postcode":"9400",
    "sg:province":"St. Gallen",
    "wof:name":"Harald Widmer B\u00e4umlistorkel-kiosk",
    "wof:placetype":"venue"
},
  "geometry": {"coordinates":[9.4913635254,47.4759902954],"type":"Point"}
}