{
  "type": "Feature",
  "properties": {
    "iso:country":"CH",
    "sg:address":"Grand-rue 25",
    "sg:city":"Bulle",
    "sg:orig_category":"Detailhandel mit Ton U Bildtr\u00e4gern",
    "sg:phone":"+41 90573188",
    "sg:postcode":"1630",
    "sg:province":"Fribourg",
    "wof:name":"Fr\u00e9quence Laser Compact Disc",
    "wof:placetype":"venue"
},
  "geometry": {"coordinates":[7.0572571754,46.618850708],"type":"Point"}
}