{
  "type": "Feature",
  "properties": {
    "iso:country":"CH",
    "sg:address":"3961 Grimentz. Postfach",
    "sg:city":"Grimentz",
    "sg:orig_category":"Herstellung von Konstruktionsteilen, Fertigbauteilen U Ausbauelementen aus Holz",
    "sg:phone":"+41 26 496 44 04",
    "sg:postcode":"3961",
    "sg:province":"Valais",
    "wof:name":"Creaktiv Ag",
    "wof:placetype":"venue"
},
  "geometry": {"coordinates":[7.248415947,46.8632469177],"type":"Point"}
}