{
  "type": "Feature",
  "properties": {
    "iso:country":"CH",
    "sg:address":"Buochserstrasse 32",
    "sg:city":"Ennetb\u00fcrgen",
    "sg:orig_category":"Kauf U Verkauf von Immobilien auf eigene Rechnung",
    "sg:phone":"+41 41 620 39 30",
    "sg:postcode":"6373",
    "sg:province":"Nidwalden",
    "wof:name":"Niedermann Willy Ag, Filiale Ennetb\u00fcrgen",
    "wof:placetype":"venue"
},
  "geometry": {"coordinates":[8.4141788483,46.9813842773],"type":"Point"}
}