{
  "type": "Feature",
  "properties": {
    "iso:country":"CH",
    "sg:address":"N\u00fcnenenstrasse 3 3600 Thun. Postfach",
    "sg:city":"Thun",
    "sg:orig_category":"Detailhandel mit Bekleidung",
    "sg:postcode":"3600",
    "sg:province":"Bern",
    "wof:name":"H.l.k.n. Gmbh",
    "wof:placetype":"venue"
},
  "geometry": {"coordinates":[7.616469,46.754913],"type":"Point"}
}