{
  "type": "Feature",
  "properties": {
    "iso:country":"CH",
    "sg:address":"Z\u00fcrichstrasse 22 4665 Oftringen. Postfach",
    "sg:city":"Oftringen",
    "sg:orig_category":"Herstellung von Elektromotoren, Generatoren U Transformatoren",
    "sg:phone":"+41 71 277 22 44",
    "sg:postcode":"4665",
    "sg:province":"Aargau",
    "wof:name":"Fitze Kurt, Motorenwicklerei, Kaminventilatoren.",
    "wof:placetype":"venue"
},
  "geometry": {"coordinates":[9.3283252716,47.4078140259],"type":"Point"}
}