{
  "type": "Feature",
  "properties": {
    "iso:country":"CH",
    "sg:address":"6043",
    "sg:city":"Adligenswil",
    "sg:orig_category":"Sportvereine Sch\u00fctzen",
    "sg:phone":"+41 62 961 01 03",
    "sg:postcode":"6043",
    "sg:province":"Luzern",
    "wof:name":"Feldsch\u00fctzenges.aeschi",
    "wof:placetype":"venue"
},
  "geometry": {"coordinates":[7.6615200043,47.1808204651],"type":"Point"}
}