{
  "type": "Feature",
  "properties": {
    "iso:country":"CH",
    "sg:address":"Neugutstrasse 17",
    "sg:city":"Andelfingen",
    "sg:orig_category":"Herstellung U Zusammensetzung von Uhren Herstellung von Uhren",
    "sg:phone":"+41 52 317 10 26",
    "sg:postcode":"8450",
    "sg:province":"Z\u00fcrich",
    "wof:name":"Turmuhrenfabrik M\u00e4der Ag",
    "wof:placetype":"venue"
},
  "geometry": {"coordinates":[8.6814069748,47.5966644287],"type":"Point"}
}