{
  "type": "Feature",
  "properties": {
    "iso:country":"CH",
    "sg:address":"Chemin De La Biolleyre 15",
    "sg:city":"Epalinges",
    "sg:orig_category":"Softwareentwicklung U beratung",
    "sg:phone":"+41 21 784 00 88",
    "sg:postcode":"1066",
    "sg:province":"Vaud",
    "wof:name":"Fosfor Sa",
    "wof:placetype":"venue"
},
  "geometry": {"coordinates":[6.6672492027,46.5514526367],"type":"Point"}
}