{
  "type": "Feature",
  "properties": {
    "iso:country":"CH",
    "sg:address":"Dorfplatz 5",
    "sg:city":"Wattwil",
    "sg:orig_category":"Wirtschaftspr\u00fcfung, Steuerberatung U Treuhand",
    "sg:phone":"+41 71 988 25 05",
    "sg:postcode":"9630",
    "sg:province":"St. Gallen",
    "wof:name":"Looser Treuhand & Revisions Ag",
    "wof:placetype":"venue"
},
  "geometry": {"coordinates":[9.0880880356,47.3033981323],"type":"Point"}
}