{
  "type": "Feature",
  "properties": {
    "iso:country":"CH",
    "sg:address":"Metallstrasse 9",
    "sg:city":"Zug",
    "sg:orig_category":"Vermietung U Verpachtung von eigenen Immobilien",
    "sg:phone":"+41 79 206 02 88",
    "sg:postcode":"6300",
    "sg:province":"Zug",
    "wof:name":"Bigler Peter Immobilien",
    "wof:placetype":"venue"
},
  "geometry": {"coordinates":[7.757589817,46.9491271973],"type":"Point"}
}