{
  "type": "Feature",
  "properties": {
    "addr:full":"Promulins Samedan Graubunden 7503",
    "addr:postcode":"7503",
    "addr:street":"Promulins;Graubunden",
    "iso:country":"CH",
    "sg:address":"Promulins",
    "sg:city":"Samedan",
    "sg:orig_category":"Bibliotheken U Archive Wohnheime",
    "sg:phone":"+41 81 852 58 55",
    "sg:postcode":"7503",
    "sg:province":"Graubunden",
    "wof:name":"Genossenschaft Oberengadiner Lehrlingshaus",
    "wof:placetype":"venue"
},
  "geometry": {"coordinates":[9.874291,46.535149],"type":"Point"}
}