{
  "type": "Feature",
  "properties": {
    "iso:country":"CH",
    "sg:address":"Route De Divonne 8",
    "sg:city":"Nyon",
    "sg:orig_category":"Maturit\u00e4tsschulen, Lehrerseminarien",
    "sg:phone":"+41 32 889 69 35",
    "sg:postcode":"1260",
    "sg:province":"Vaud",
    "wof:name":"Gymnase Cantonal",
    "wof:placetype":"venue"
},
  "geometry": {"coordinates":[6.9405741692,46.994228363],"type":"Point"}
}