{
  "type": "Feature",
  "properties": {
    "iso:country":"CH",
    "sg:address":"Klybeckstrasse 1b",
    "sg:city":"Basel",
    "sg:classifiers":[
        {
            "category":"Restaurant",
            "type":"Food & Drink"
        }
    ],
    "sg:phone":"+41 61 681 03 03",
    "sg:postcode":"4057",
    "sg:province":"Basel-Stadt",
    "wof:name":"Restaurant Schlappe",
    "wof:placetype":"venue"
},
  "geometry": {"coordinates":[7.5912570953,47.5644950867],"type":"Point"}
}