{
  "type": "Feature",
  "properties": {
    "iso:country":"CH",
    "sg:address":"Grand Rue 1040 Echallens. Postfach",
    "sg:city":"Echallens",
    "sg:orig_category":"Herstellung von Oberbekleidung",
    "sg:postcode":"1040",
    "sg:province":"Vaud",
    "wof:name":"Gaillard Roger",
    "wof:placetype":"venue"
},
  "geometry": {"coordinates":[6.6341948509,46.6412200928],"type":"Point"}
}