{
  "type": "Feature",
  "properties": {
    "addr:full":"T\u00fcfwisstrasse 7 Winkel Z\u00fcrich 8185",
    "addr:housenumber":"7",
    "addr:postcode":"8185",
    "addr:street":"Tuefwisstrasse",
    "iso:country":"CH",
    "sg:address":"T\u00fcfwisstrasse 7",
    "sg:city":"Winkel",
    "sg:classifiers":[
        {
            "category":"Professional",
            "subcategory":"Advertising",
            "type":"Services"
        }
    ],
    "sg:phone":"+41 18610809",
    "sg:postcode":"8185",
    "sg:province":"Z\u00fcrich",
    "sg:tags":[
        "agency"
    ],
    "wof:name":"Hans Zahnd Werbeagentur",
    "wof:placetype":"venue"
},
  "geometry": {"coordinates":[8.553374,47.491215],"type":"Point"}
}