{
  "type": "Feature",
  "properties": {
    "iso:country":"CH",
    "sg:address":"Dammweg 32",
    "sg:city":"Aarau",
    "sg:orig_category":"Vereine Musik/Blasmusik",
    "sg:phone":"+41 62 822 90 37",
    "sg:postcode":"5000",
    "sg:province":"Aargau",
    "wof:name":"Musikverein Harmonie Aarau",
    "wof:placetype":"venue"
},
  "geometry": {"coordinates":[8.0346746445,47.3867301941],"type":"Point"}
}