{
  "type": "Feature",
  "properties": {
    "iso:country":"CH",
    "sg:address":"Tr\u00e8fle-blanc Chemin De 16 1228 Plan-les-ouates. Postfach",
    "sg:city":"Plan-les-ouates",
    "sg:orig_category":"Wirtschaftspr\u00fcfung, Steuerberatung U Treuhand",
    "sg:postcode":"1228",
    "sg:province":"Gen\u00e8ve",
    "wof:name":"Ficam S\u00e0rl Fiscalit\u00e9, R\u00e9vision-audit Etc",
    "wof:placetype":"venue"
},
  "geometry": {"coordinates":[6.1263170242,46.1717224121],"type":"Point"}
}