{
  "type": "Feature",
  "properties": {
    "iso:country":"CH",
    "sg:address":"Chenalettaz En 8",
    "sg:city":"Gorgier",
    "sg:orig_category":"Allgemeiner Hoch U Tiefbau",
    "sg:phone":"+41 32 842 22 33",
    "sg:postcode":"2023",
    "sg:province":"Neuch\u00e2tel",
    "wof:name":"Pierre Duckert Sa, Succursale Les Verri\u00e8res",
    "wof:placetype":"venue"
},
  "geometry": {"coordinates":[6.481448,46.904552],"type":"Point"}
}