{
  "type": "Feature",
  "properties": {
    "iso:country":"CH",
    "sg:address":"Rue De La Fin 14",
    "sg:city":"Cortaillod",
    "sg:orig_category":"Nationale Postdienste",
    "sg:phone":"+41 32 842 10 96",
    "sg:postcode":"2016",
    "sg:province":"Neuch\u00e2tel",
    "wof:name":"La Poste Suisse",
    "wof:placetype":"venue"
},
  "geometry": {"coordinates":[6.8453159332,46.9441261292],"type":"Point"}
}