{
  "type": "Feature",
  "properties": {
    "iso:country":"CH",
    "sg:address":"Kolinplatz 1",
    "sg:city":"Zug",
    "sg:orig_category":"Grosshandel mit festen Brennstoffen U Mineral\u00f6lerzeugnissen",
    "sg:postcode":"6300",
    "sg:province":"Zug",
    "wof:name":"Zugol Ag Brennstoff-handel",
    "wof:placetype":"venue"
},
  "geometry": {"coordinates":[8.3144922256,46.991733551],"type":"Point"}
}