{
  "type": "Feature",
  "properties": {
    "iso:country":"CH",
    "sg:address":"1453",
    "sg:city":"Bullet",
    "sg:orig_category":"Vereine Gesang",
    "sg:postcode":"1453",
    "sg:province":"Vaud",
    "wof:name":"St\u00e9 De Chant Chorale",
    "wof:placetype":"venue"
},
  "geometry": {"coordinates":[7.0663948059,46.6079711914],"type":"Point"}
}