{
  "type": "Feature",
  "properties": {
    "iso:country":"CH",
    "sg:address":"Hauptstrasse 44 6315 Ober\u00e4geri. Postfach 118",
    "sg:city":"Ober\u00e4geri",
    "sg:orig_category":"Instandhaltung U Reparatur von Automobilen",
    "sg:phone":"+41 41 750 18 35",
    "sg:postcode":"6315",
    "sg:province":"Zug",
    "wof:name":"Rogenmoser Paul, Dorfgarage",
    "wof:placetype":"venue"
},
  "geometry": {"coordinates":[8.6087694168,47.1359863281],"type":"Point"}
}