{
  "type": "Feature",
  "properties": {
    "iso:country":"CH",
    "sg:address":"Camminata Via 3g 6500 Bellinzona. Postfach",
    "sg:city":"Bellinzona",
    "sg:orig_category":"Detailhandel mit Bekleidung",
    "sg:postcode":"6500",
    "sg:province":"Ticino",
    "wof:name":"Eight Eighteen Sagl Capi D'abbigliamento Ed Affini; Comm., Import/export Ecc",
    "wof:placetype":"venue"
},
  "geometry": {"coordinates":[9.022681,46.190693],"type":"Point"}
}