{
  "type": "Feature",
  "properties": {
    "addr:full":"Garstligweg 8 Hombrechtikon Z\u00fcrich 8634",
    "addr:housenumber":"8",
    "addr:postcode":"8634",
    "addr:street":"Garstligweg",
    "iso:country":"CH",
    "sg:address":"Garstligweg 8",
    "sg:city":"Hombrechtikon",
    "sg:classifiers":[
        {
            "category":"Manufacturing",
            "subcategory":"Building Materials",
            "type":"Manufacturing & Wholesale Goods"
        }
    ],
    "sg:phone":"+41 91 690 11 80",
    "sg:postcode":"8634",
    "sg:province":"Z\u00fcrich",
    "sg:tags":[
        "analysis"
    ],
    "wof:name":"C.c.l. Cemcon Laboratoy Sa",
    "wof:placetype":"venue"
},
  "geometry": {"coordinates":[9.01301,45.855247],"type":"Point"}
}