{
  "type": "Feature",
  "properties": {
    "iso:country":"CH",
    "sg:address":"6213",
    "sg:city":"Knutwil",
    "sg:orig_category":"Schulpflegen",
    "sg:phone":"+41 71 461 17 52",
    "sg:postcode":"6213",
    "sg:province":"Luzern",
    "wof:name":"Schulpflege Der Gemeinde St.erhard",
    "wof:placetype":"venue"
},
  "geometry": {"coordinates":[8.0723752975,47.1991119385],"type":"Point"}
}