{
  "type": "Feature",
  "properties": {
    "iso:country":"CH",
    "sg:address":"R\u00e4sch",
    "sg:city":"D\u00fcdingen",
    "sg:orig_category":"Zimmerei, Dachdeckerei, Bauspenglerei U Abdichtung",
    "sg:phone":"+41 26 493 30 78",
    "sg:postcode":"3186",
    "sg:province":"Fribourg",
    "wof:name":"Sch\u00fcpbach Ivar",
    "wof:placetype":"venue"
},
  "geometry": {"coordinates":[7.1577448845,46.8333435059],"type":"Point"}
}