{
  "type": "Feature",
  "properties": {
    "iso:country":"CH",
    "sg:address":"Industriestrasse 49",
    "sg:city":"Zug",
    "sg:orig_category":"Non-Classified Establishments",
    "sg:postcode":"6300",
    "sg:province":"Zug",
    "wof:name":"Salus Alpha Management Ag",
    "wof:placetype":"venue"
},
  "geometry": {"coordinates":[8.5210886002,47.1829452515],"type":"Point"}
}