{
  "type": "Feature",
  "properties": {
    "iso:country":"CH",
    "sg:address":"Vorderi Siten 1",
    "sg:city":"Hirzel",
    "sg:orig_category":"Regionalbanken U Sparkassen",
    "sg:phone":"+41 17299555",
    "sg:postcode":"8816",
    "sg:province":"Z\u00fcrich",
    "wof:name":"Sparkasse Horgen",
    "wof:placetype":"venue"
},
  "geometry": {"coordinates":[8.6105251312,47.2159996033],"type":"Point"}
}