{
  "type": "Feature",
  "properties": {
    "iso:country":"CH",
    "sg:address":"Wyb\u00fcelstrasse 16",
    "sg:city":"Zollikon",
    "sg:orig_category":"Softwareentwicklung U beratung",
    "sg:phone":"+41 71 636 18 15",
    "sg:postcode":"8702",
    "sg:province":"Z\u00fcrich",
    "wof:name":"Wieselweb Ag",
    "wof:placetype":"venue"
},
  "geometry": {"coordinates":[7.568983078,47.0876655579],"type":"Point"}
}