{
  "type": "Feature",
  "properties": {
    "iso:country":"CH",
    "sg:address":"D'ayent",
    "sg:city":"Grimisuat",
    "sg:classifiers":[
        {
            "category":"Restaurant",
            "type":"Food & Drink"
        }
    ],
    "sg:phone":"+41 91 682 21 96",
    "sg:postcode":"1971",
    "sg:province":"Valais",
    "wof:name":"Trattoria Diana",
    "wof:placetype":"venue"
},
  "geometry": {"coordinates":[9.0225248337,45.8414382935],"type":"Point"}
}