{
  "type": "Feature",
  "properties": {
    "iso:country":"CH",
    "sg:address":"Beundenring 9",
    "sg:city":"Nidau",
    "sg:orig_category":"Fernmeldedienste",
    "sg:postcode":"2560",
    "sg:province":"Bern",
    "wof:name":"Creative Web Zapf & Wrobel",
    "wof:placetype":"venue"
},
  "geometry": {"coordinates":[7.2368631363,47.1187133789],"type":"Point"}
}