{
  "type": "Feature",
  "properties": {
    "iso:country":"CH",
    "sg:address":"Schlatterhof 4",
    "sg:city":"Hemmental",
    "sg:orig_category":"Softwareentwicklung U beratung",
    "sg:phone":"+41 52 682 14 00",
    "sg:postcode":"8231",
    "sg:province":"Schaffhausen",
    "wof:name":"Leu-soft Datentechnik Edv-dienstleistungen",
    "wof:placetype":"venue"
},
  "geometry": {"coordinates":[8.5800933838,47.7349128723],"type":"Point"}
}