{
  "type": "Feature",
  "properties": {
    "iso:country":"CH",
    "sg:address":"Neul\u00f6serweg 5",
    "sg:city":"Zizers",
    "sg:orig_category":"Grosshandel mit sonstigen Maschinen U Ausr\u00fcstungen f\u00fcr Industrie, Handel U Schiffahrt",
    "sg:phone":"+41 14923551",
    "sg:postcode":"7205",
    "sg:province":"Graubunden",
    "wof:name":"Gort Maschinen Ag",
    "wof:placetype":"venue"
},
  "geometry": {"coordinates":[9.5578298569,46.9344711304],"type":"Point"}
}