{
  "type": "Feature",
  "properties": {
    "iso:country":"CH",
    "sg:address":"Aefligenstrasse 2",
    "sg:city":"Utzenstorf",
    "sg:orig_category":"Vereine Damen Vereine Gesang",
    "sg:phone":"+41 32 665 22 62",
    "sg:postcode":"3427",
    "sg:province":"Bern",
    "wof:name":"Frauenchor Utzenstorf",
    "wof:placetype":"venue"
},
  "geometry": {"coordinates":[7.560754776,47.1220397949],"type":"Point"}
}