{
  "type": "Feature",
  "properties": {
    "addr:full":"6930 Bedano Ticino 6930",
    "addr:housenumber":"6930;6930",
    "addr:street":"Bedano Ticino",
    "iso:country":"CH",
    "sg:address":"6930",
    "sg:city":"Bedano",
    "sg:orig_category":"Detailhandel mit Brot, Back U S\u00fcsswaren",
    "sg:phone":"+41 21 636 46 89",
    "sg:postcode":"6930",
    "sg:province":"Ticino",
    "wof:name":"Aldo Castelli Boulangerie & P\u00e2tisserie",
    "wof:placetype":"venue"
},
  "geometry": {"coordinates":[6.582439,46.538795],"type":"Point"}
}