{
  "type": "Feature",
  "properties": {
    "iso:country":"CH",
    "sg:address":"Nelkenstrasse 12 6032 Emmen. Postfach",
    "sg:city":"Emmen",
    "sg:orig_category":"Stukkateurgewerbe, Gipserei U Verputzerei",
    "sg:postcode":"6032",
    "sg:province":"Luzern",
    "wof:name":"Gipsergesch\u00e4ft Mushkolaj-l\u00f6tscher Beatrice",
    "wof:placetype":"venue"
},
  "geometry": {"coordinates":[8.2871723175,47.0854225159],"type":"Point"}
}