{
  "type": "Feature",
  "properties": {
    "iso:country":"CH",
    "sg:address":"Z\u00fcrcherstr. 97.",
    "sg:city":"Basel",
    "sg:orig_category":"Fachdetailhandel mit pharmazeutischen Produkten",
    "sg:phone":"+41 61 319 98 98",
    "sg:postcode":"4000",
    "sg:province":"Basel-Stadt",
    "wof:name":"Breite-apotheke, R\u00fcegg Dr. Andreas",
    "wof:placetype":"venue"
},
  "geometry": {"coordinates":[7.6113438606,47.5547561646],"type":"Point"}
}