{
  "type": "Feature",
  "properties": {
    "iso:country":"CH",
    "sg:address":"Bubental 53",
    "sg:city":"Altendorf",
    "sg:orig_category":"Sonstige mit der Informatik verbundene T\u00e4tigkeiten",
    "sg:phone":"+41 55 462 14 81",
    "sg:postcode":"8852",
    "sg:province":"Schwyz",
    "wof:name":"M\u00fcller Andreas, Beratung + Entwicklung",
    "wof:placetype":"venue"
},
  "geometry": {"coordinates":[8.8293542862,47.1863708496],"type":"Point"}
}