{
  "type": "Feature",
  "properties": {
    "iso:country":"CH",
    "sg:address":"1643",
    "sg:city":"Gumefens",
    "sg:orig_category":"Unclassifiable Establishments",
    "sg:postcode":"1643",
    "sg:province":"Fribourg",
    "wof:name":"Rial Et Gaillard S.\u00e0 R.l.",
    "wof:placetype":"venue"
},
  "geometry": {"coordinates":[7.0685901642,46.6771697998],"type":"Point"}
}