{
  "type": "Feature",
  "properties": {
    "iso:country":"CH",
    "sg:address":"Solothurnstrasse 21b",
    "sg:city":"B\u00e4tterkinden",
    "sg:orig_category":"Vorschulen, Kinderg\u00e4rten",
    "sg:phone":"+41 32 665 46 61",
    "sg:postcode":"3315",
    "sg:province":"Bern",
    "wof:name":"Kindergarten Dorfmatt",
    "wof:placetype":"venue"
},
  "geometry": {"coordinates":[7.5376610756,47.1351890564],"type":"Point"}
}