{
  "type": "Feature",
  "properties": {
    "iso:country":"CH",
    "sg:address":"Bienenstrasse 7",
    "sg:city":"Weinfelden",
    "sg:orig_category":"Tierarztpraxis",
    "sg:phone":"+41 32 351 40 33",
    "sg:postcode":"8570",
    "sg:province":"Thurgau",
    "wof:name":"Dr.med.vet.ren\u00e9e Devaux Tier\u00e4rztin",
    "wof:placetype":"venue"
},
  "geometry": {"coordinates":[7.3771018982,47.1400184631],"type":"Point"}
}