{
  "type": "Feature",
  "properties": {
    "iso:country":"CH",
    "sg:address":"Sonnenhalde 25",
    "sg:city":"Bettwiesen",
    "sg:orig_category":"Hoch U Tiefbau",
    "sg:phone":"+41 52 369 45 45",
    "sg:postcode":"9553",
    "sg:province":"Thurgau",
    "wof:name":"Eduard Vetter Ag Bauunternehmung",
    "wof:placetype":"venue"
},
  "geometry": {"coordinates":[9.0232925415,47.500705719],"type":"Point"}
}