{
  "type": "Feature",
  "properties": {
    "iso:country":"CH",
    "sg:address":"Sonnhalde 19",
    "sg:city":"Neuenkirch",
    "sg:orig_category":"G\u00fcterbef\u00f6rderung im Strassenverkehr Rolladen- and Storenmontage",
    "sg:phone":"+41 41 467 23 09",
    "sg:postcode":"6206",
    "sg:province":"Luzern",
    "wof:name":"Fritz Ottiger Transporte & Storenbau",
    "wof:placetype":"venue"
},
  "geometry": {"coordinates":[8.2168292999,47.0974159241],"type":"Point"}
}