{
  "type": "Feature",
  "properties": {
    "iso:country":"CH",
    "sg:address":"Les Champs Du Clos 2 2613 Villeret Case Postale 32",
    "sg:city":"Villeret",
    "sg:orig_category":"Herstellung von medizinischen U chirurgischen Ger\u00e4ten",
    "sg:phone":"+41 22 884 01 11",
    "sg:postcode":"2613",
    "sg:province":"Bern",
    "wof:name":"Stryker Trauma Sa",
    "wof:placetype":"venue"
},
  "geometry": {"coordinates":[6.1079192162,46.168800354],"type":"Point"}
}