{
  "type": "Feature",
  "properties": {
    "iso:country":"CH",
    "sg:address":"Poststrasse 13",
    "sg:city":"Spreitenbach",
    "sg:orig_category":"Landesverteidigung, Sozialversicherung \u00d6ffentliche Verwaltung",
    "sg:phone":"+41 55 284 18 88",
    "sg:postcode":"8957",
    "sg:province":"Aargau",
    "wof:name":"Zivilschutzstelle St. Gallenkappel",
    "wof:placetype":"venue"
},
  "geometry": {"coordinates":[8.967338562,47.2448921204],"type":"Point"}
}