{
  "type": "Feature",
  "properties": {
    "iso:country":"CH",
    "sg:address":"Haubenstrasse 4",
    "sg:city":"Oberdiessbach",
    "sg:orig_category":"Politische Parteien FDP",
    "sg:phone":"+41 33 243 31 61",
    "sg:postcode":"3672",
    "sg:province":"Bern",
    "wof:name":"Fdp Sektion Oberhofen",
    "wof:placetype":"venue"
},
  "geometry": {"coordinates":[9.0390996933,47.2317276001],"type":"Point"}
}