{
  "type": "Feature",
  "properties": {
    "iso:country":"CH",
    "sg:address":"Schwandenholzstrasse 157",
    "sg:city":"Seebach",
    "sg:orig_category":"Verwertung von Milch",
    "sg:postcode":"8052",
    "sg:province":"Z\u00fcrich",
    "wof:name":"Genossenschaft Vereinigter Milchproduzenten Der Sennerei Seebach",
    "wof:placetype":"venue"
},
  "geometry": {"coordinates":[8.5402402878,47.4224815369],"type":"Point"}
}