{
  "type": "Feature",
  "properties": {
    "iso:country":"CH",
    "sg:address":"Grand-rue 12",
    "sg:city":"St-maurice",
    "sg:orig_category":"Herstellung von konfektionierten Textilwaren ohne Bekleidung",
    "sg:postcode":"1890",
    "sg:province":"Valais",
    "wof:name":"Meylan Eric",
    "wof:placetype":"venue"
},
  "geometry": {"coordinates":[7.0047369003,46.217956543],"type":"Point"}
}