{
  "type": "Feature",
  "properties": {
    "iso:country":"CH",
    "sg:address":"Haldenstrasse 44 8173 Neerach. Postfach",
    "sg:city":"Neerach",
    "sg:orig_category":"Unternehmensberatung",
    "sg:postcode":"8173",
    "sg:province":"Z\u00fcrich",
    "wof:name":"Wendling E. & Partner Gmbh, Management Consultants Und Consulting Engineers",
    "wof:placetype":"venue"
},
  "geometry": {"coordinates":[8.4751663208,47.507648468],"type":"Point"}
}