{
  "type": "Feature",
  "properties": {
    "iso:country":"CH",
    "sg:address":"Piolet En 31",
    "sg:city":"Estavayer-le-lac",
    "sg:orig_category":"Mechanik",
    "sg:phone":"+41 79 635 23 93",
    "sg:postcode":"1470",
    "sg:province":"Fribourg",
    "wof:name":"Ts Sa",
    "wof:placetype":"venue"
},
  "geometry": {"coordinates":[6.8504981995,46.8424568176],"type":"Point"}
}