{
  "type": "Feature",
  "properties": {
    "iso:country":"CH",
    "sg:address":"Letziweg 9 4663 Aarburg. Postfach",
    "sg:city":"Aarburg",
    "sg:orig_category":"Non-Classified Establishments",
    "sg:phone":"+41 62 787 20 30",
    "sg:postcode":"4663",
    "sg:province":"Aargau",
    "wof:name":"Sadorex Marketing Ag",
    "wof:placetype":"venue"
},
  "geometry": {"coordinates":[7.8980698586,47.3225021362],"type":"Point"}
}