{
  "type": "Feature",
  "properties": {
    "addr:full":"3975 Bluche-randogne Valais 3975",
    "addr:housenumber":"3975",
    "addr:postcode":"3975",
    "addr:street":"Bluche-Randogne Valais",
    "iso:country":"CH",
    "sg:address":"3975",
    "sg:city":"Bluche-randogne",
    "sg:orig_category":"Bauschreinerei Herstellung von Konstruktionsteilen, Fertigbauteilen U Ausbauelementen aus Holz",
    "sg:phone":"+41 32 866 16 31",
    "sg:postcode":"3975",
    "sg:province":"Valais",
    "wof:name":"Serge Ferrier Menuiserie & \u00e9b\u00e9nisterie",
    "wof:placetype":"venue"
},
  "geometry": {"coordinates":[6.485026,46.905483],"type":"Point"}
}