{
  "type": "Feature",
  "properties": {
    "iso:country":"CH",
    "sg:address":"Vortauenstrasse 13",
    "sg:city":"D\u00e4llikon",
    "sg:orig_category":"Handelsvermittlung von Holz U Baustoffen",
    "sg:phone":"+41 18446042",
    "sg:postcode":"8108",
    "sg:province":"Z\u00fcrich",
    "wof:name":"Interstone Cil Cemal",
    "wof:placetype":"venue"
},
  "geometry": {"coordinates":[8.4373693466,47.4410820007],"type":"Point"}
}