{
  "type": "Feature",
  "properties": {
    "iso:country":"CH",
    "sg:address":"Feldeck",
    "sg:city":"Dietfurt",
    "sg:orig_category":"Institutionen f\u00fcr Finanzierungsleasing",
    "sg:phone":"+41 71 982 88 81",
    "sg:postcode":"9615",
    "sg:province":"St. Gallen",
    "wof:name":"G\u00e4chter Ag Finanz-& Leasing",
    "wof:placetype":"venue"
},
  "geometry": {"coordinates":[9.0788373947,47.347530365],"type":"Point"}
}