{
  "type": "Feature",
  "properties": {
    "iso:country":"CH",
    "sg:address":"Avenue De Ch\u00e2telaine 81bis",
    "sg:city":"Vernier",
    "sg:orig_category":"Architektur U Ingenieurb\u00fcros",
    "sg:phone":"+41 22 796 42 22",
    "sg:postcode":"1214",
    "sg:province":"Gen\u00e8ve",
    "wof:name":"Bg Bonnard & Gardel, Ing\u00e9nieurs-conseils (gen\u00e8ve) Sa",
    "wof:placetype":"venue"
},
  "geometry": {"coordinates":[6.112557,46.210983],"type":"Point"}
}