{
  "type": "Feature",
  "properties": {
    "iso:country":"CH",
    "sg:address":"Eigerstrasse 60 3007 Bern. Postfach",
    "sg:city":"Bern",
    "sg:orig_category":"Verwaltung von Immobilien",
    "sg:postcode":"3005",
    "sg:province":"Bern",
    "wof:name":"Wtf Real Estate (switzerland) Ltd. Hamilton, Bermuda, Bern Branch",
    "wof:placetype":"venue"
},
  "geometry": {"coordinates":[7.4371089935,46.9396514893],"type":"Point"}
}