{
  "type": "Feature",
  "properties": {
    "iso:country":"CH",
    "sg:address":"Rue Des Chavannes 8",
    "sg:city":"Neuenburg",
    "sg:orig_category":"Detailhandel mit Bekleidung",
    "sg:phone":"+41 32 725 16 38",
    "sg:postcode":"2000",
    "sg:province":"Neuch\u00e2tel",
    "wof:name":"Le Tisserin, Trousseaux, Textiles-loisirs, Scheidegger Pierre",
    "wof:placetype":"venue"
},
  "geometry": {"coordinates":[6.931085,46.990334],"type":"Point"}
}