{
  "type": "Feature",
  "properties": {
    "iso:country":"CH",
    "sg:address":"Rue Du Grand-pr\u00e9 26",
    "sg:city":"Crans-pr\u00e8s-c\u00e9ligny",
    "sg:orig_category":"Arztpraxen",
    "sg:phone":"+41 22 776 12 22",
    "sg:postcode":"1299",
    "sg:province":"Vaud",
    "wof:name":"Dr M\u00e9d. Pierre Widmer M\u00e9decine G\u00e9n\u00e9raliste",
    "wof:placetype":"venue"
},
  "geometry": {"coordinates":[6.206279,46.359318],"type":"Point"}
}