{
  "type": "Feature",
  "properties": {
    "iso:country":"CH",
    "sg:address":"Furtstrasse 3",
    "sg:city":"Brunnadern",
    "sg:orig_category":"Grosshandel mit Getreide, Saatgut U Futtermitteln",
    "sg:postcode":"9125",
    "sg:province":"St. Gallen",
    "wof:name":"Asbon Trading Ag",
    "wof:placetype":"venue"
},
  "geometry": {"coordinates":[7.1084527969,46.9252319336],"type":"Point"}
}