{
  "type": "Feature",
  "properties": {
    "iso:country":"CH",
    "sg:address":"Gl\u00e4rnischstrasse 42",
    "sg:city":"Wil",
    "sg:classifiers":[
        {
            "category":"Home & Garden",
            "subcategory":"Carpets & Floor Coverings",
            "type":"Retail Goods"
        }
    ],
    "sg:phone":"+41 71 925 43 25",
    "sg:postcode":"9500",
    "sg:province":"St. Gallen",
    "sg:tags":[
        "ceiling",
        "metal"
    ],
    "wof:name":"Mathys Design Ag",
    "wof:placetype":"venue"
},
  "geometry": {"coordinates":[9.042146,47.45573],"type":"Point"}
}