{
  "type": "Feature",
  "properties": {
    "iso:country":"CH",
    "sg:address":"1958",
    "sg:city":"St-l\u00e9onard",
    "sg:orig_category":"Granit",
    "sg:phone":"+41 55 286 30 00",
    "sg:postcode":"1958",
    "sg:province":"Valais",
    "wof:name":"M\u00fcller Gebr. Steinbruchbetrieb Ag",
    "wof:placetype":"venue"
},
  "geometry": {"coordinates":[8.9213428497,47.2407341003],"type":"Point"}
}