{
  "type": "Feature",
  "properties": {
    "iso:country":"CH",
    "sg:address":"Rue De Neuch\u00e2tel 1 1400 Yverdon-les-bains Case Postale 3167",
    "sg:city":"Yverdon",
    "sg:orig_category":"Notariate",
    "sg:phone":"+41 21 811 55 55",
    "sg:postcode":"1401",
    "sg:province":"Vaud",
    "wof:name":"Jean-jacques De Luze Notariat",
    "wof:placetype":"venue"
},
  "geometry": {"coordinates":[6.4964389801,46.5076713562],"type":"Point"}
}