{
  "type": "Feature",
  "properties": {
    "addr:full":"Kapellgasse 6 Luzern Luzern 6004",
    "addr:housenumber":"6",
    "addr:postcode":"6004",
    "addr:street":"Kapellgasse",
    "iso:country":"CH",
    "sg:address":"Kapellgasse 6",
    "sg:city":"Luzern",
    "sg:orig_category":"Detailhandel mit Brillen U anderen Sehhilfen",
    "sg:phone":"+41 41 410 22 43",
    "sg:postcode":"6004",
    "sg:province":"Luzern",
    "wof:name":"Micro-electric H\u00f6rger\u00e4te Ag H\u00f6rger\u00e4te F. Schwerh\u00f6rige, Ger\u00e4te D. Mediz. Technik Usw.",
    "wof:placetype":"venue"
},
  "geometry": {"coordinates":[8.307197,47.052696],"type":"Point"}
}