{
  "type": "Feature",
  "properties": {
    "iso:country":"CH",
    "sg:address":"Galgenen",
    "sg:city":"Galgenen",
    "sg:classifiers":[
        {
            "category":"Banks & Credit Unions",
            "subcategory":"Bank",
            "type":"Services"
        }
    ],
    "sg:phone":"+41 55643196",
    "sg:postcode":"8854",
    "sg:province":"Schwyz",
    "wof:name":"Kantonalbank Schwyz",
    "wof:placetype":"venue"
},
  "geometry": {"coordinates":[8.87522,47.182331],"type":"Point"}
}