{
  "type": "Feature",
  "properties": {
    "iso:country":"CH",
    "sg:address":"Hafenstrasse 52",
    "sg:city":"Romanshorn",
    "sg:classifiers":[
        {
            "category":"Restaurant",
            "type":"Food & Drink"
        }
    ],
    "sg:phone":"+41 71 463 68 88",
    "sg:postcode":"8590",
    "sg:province":"Thurgau",
    "wof:name":"China Restaurant Wong Seng",
    "wof:placetype":"venue"
},
  "geometry": {"coordinates":[9.3811502457,47.5677566528],"type":"Point"}
}