{
  "type": "Feature",
  "properties": {
    "addr:full":"Winkelriedplatz 1 4053 Basel. Postfach Basel Basel-Stadt 4008",
    "addr:housenumber":"1",
    "addr:postcode":"4053;4008",
    "addr:street":"Winkelriedplatz;Postfach",
    "iso:country":"CH",
    "sg:address":"Winkelriedplatz 1 4053 Basel. Postfach",
    "sg:city":"Basel",
    "sg:orig_category":"Architektur U Ingenieurb\u00fcros",
    "sg:phone":"+41 61 361 44 01",
    "sg:postcode":"4008",
    "sg:province":"Basel-Stadt",
    "wof:name":"Walter Schacher Technisches B\u00fcro",
    "wof:placetype":"venue"
},
  "geometry": {"coordinates":[7.587737,47.543301],"type":"Point"}
}