{
  "type": "Feature",
  "properties": {
    "iso:country":"CH",
    "sg:address":"Bahnhofstrasse 26 6440 Brunnen. Postfach 58",
    "sg:city":"Brunnen",
    "sg:orig_category":"Drogerien",
    "sg:phone":"+41 41 820 17 17",
    "sg:postcode":"6440",
    "sg:province":"Schwyz",
    "wof:name":"Axen-drogerie Ag, Brunnen",
    "wof:placetype":"venue"
},
  "geometry": {"coordinates":[8.6068353653,46.9956741333],"type":"Point"}
}