{
  "type": "Feature",
  "properties": {
    "iso:country":"CH",
    "sg:address":"Maienstrasse 21",
    "sg:city":"Z\u00fcrich",
    "sg:orig_category":"Vorschulen, Kinderg\u00e4rten",
    "sg:postcode":"8050",
    "sg:province":"Z\u00fcrich",
    "wof:name":"St\u00e4dtischer Kindergarten",
    "wof:placetype":"venue"
},
  "geometry": {"coordinates":[8.5293626785,47.4102096558],"type":"Point"}
}