{
  "type": "Feature",
  "properties": {
    "iso:country":"CH",
    "sg:address":"Hauptstrasse 29 9556 Affeltrangen. Postfach",
    "sg:city":"Affeltrangen",
    "sg:orig_category":"Handel mit Automobilen",
    "sg:postcode":"9556",
    "sg:province":"Thurgau",
    "wof:name":"Automarkt Stelz, Stelzstrasse, Alci G\u00fcng\u00f6r",
    "wof:placetype":"venue"
},
  "geometry": {"coordinates":[9.0534296036,47.4628791809],"type":"Point"}
}