{
  "type": "Feature",
  "properties": {
    "iso:country":"CH",
    "sg:address":"Lautengartenstrasse 12",
    "sg:city":"Basel",
    "sg:orig_category":"Sonstige mit der Informatik verbundene T\u00e4tigkeiten",
    "sg:phone":"+41 14000652",
    "sg:postcode":"4052",
    "sg:province":"Basel-Stadt",
    "wof:name":"E3 F\u00fcrling It Consultancy",
    "wof:placetype":"venue"
},
  "geometry": {"coordinates":[8.4562854767,47.3696937561],"type":"Point"}
}