{
  "type": "Feature",
  "properties": {
    "iso:country":"CH",
    "sg:address":"Mantelgasse 12",
    "sg:city":"Z\u00fcrich",
    "sg:orig_category":"Grosshandel mit Bekleidung Handelsvermittlung von Textilien, Bekleidung, Schuhen U Lederwaren",
    "sg:phone":"+41 13825300",
    "sg:postcode":"8008",
    "sg:province":"Z\u00fcrich",
    "wof:name":"Cajacob Evelyne M., Modeagentur",
    "wof:placetype":"venue"
},
  "geometry": {"coordinates":[8.5586595535,47.3566818237],"type":"Point"}
}