{
  "type": "Feature",
  "properties": {
    "iso:country":"CH",
    "sg:address":"Gasstrasse 69",
    "sg:city":"Basel",
    "sg:orig_category":"Sportvereine Velo Rad-& Motorfahrer-Bund SRB",
    "sg:phone":"+41 61 322 85 44",
    "sg:postcode":"4056",
    "sg:province":"Basel-Stadt",
    "wof:name":"Club Cicl.basilea",
    "wof:placetype":"venue"
},
  "geometry": {"coordinates":[7.5743927956,47.5683517456],"type":"Point"}
}