{
  "type": "Feature",
  "properties": {
    "iso:country":"CH",
    "sg:address":"Hauptstrasse 115",
    "sg:city":"Meisterschwanden",
    "sg:classifiers":[
        {
            "category":"Restaurant",
            "type":"Food & Drink"
        }
    ],
    "sg:phone":"+41 56 667 12 92",
    "sg:postcode":"5616",
    "sg:province":"Aargau",
    "wof:name":"Restaurant Traube",
    "wof:placetype":"venue"
},
  "geometry": {"coordinates":[8.2248687744,47.2992553711],"type":"Point"}
}