{
  "type": "Feature",
  "properties": {
    "iso:country":"CH",
    "sg:address":"Talstrasse 3",
    "sg:city":"Klosters",
    "sg:orig_category":"Handel mit Automobilen",
    "sg:postcode":"7250",
    "sg:province":"Graubunden",
    "wof:name":"Neuh\u00e4usler Thomas & Co",
    "wof:placetype":"venue"
},
  "geometry": {"coordinates":[9.8841276169,46.868347168],"type":"Point"}
}