{
  "type": "Feature",
  "properties": {
    "iso:country":"CH",
    "sg:address":"Teufenerstrasse 2",
    "sg:city":"St.gallen",
    "sg:orig_category":"Grosshandel mit sonstigen Halbwaren",
    "sg:postcode":"9000",
    "sg:province":"St. Gallen",
    "wof:name":"Wawi Gesellschaft F\u00fcr Alternative Und Innovative Verpackungsmaterialien Gmbh",
    "wof:placetype":"venue"
},
  "geometry": {"coordinates":[9.3715229034,47.4211921692],"type":"Point"}
}