{
  "type": "Feature",
  "properties": {
    "iso:country":"CH",
    "sg:address":"Stadthausstrasse 119 8400 Winterthur. Postfach 1128",
    "sg:city":"Winterthur",
    "sg:orig_category":"RESTAURANTS: TEA-ROOMS",
    "sg:postcode":"8401",
    "sg:province":"Z\u00fcrich",
    "wof:name":"Restaurant Stadtgarten, Fischer",
    "wof:placetype":"venue"
},
  "geometry": {"coordinates":[7.6550498009,47.2357063293],"type":"Point"}
}