{
  "type": "Feature",
  "properties": {
    "iso:country":"CH",
    "sg:address":"Via Cantonale",
    "sg:city":"Bioggio",
    "sg:orig_category":"Detailhandel mit Bekleidung Detailhandel mit Damenbekleidung",
    "sg:phone":"+41 91 605 34 79",
    "sg:postcode":"6934",
    "sg:province":"Ticino",
    "wof:name":"Pellicceria Maximilian Wankerl Sa",
    "wof:placetype":"venue"
},
  "geometry": {"coordinates":[8.909617,46.015694],"type":"Point"}
}