{
  "type": "Feature",
  "properties": {
    "iso:country":"CH",
    "sg:address":"T\u00f6belistrasse 29",
    "sg:city":"Kollbrunn",
    "sg:orig_category":"Detailhandel mit Getr\u00e4nken",
    "sg:phone":"+41 52 383 19 63",
    "sg:postcode":"8483",
    "sg:province":"Z\u00fcrich",
    "wof:name":"Rosario Carnazza Getr\u00e4nkehandel",
    "wof:placetype":"venue"
},
  "geometry": {"coordinates":[8.7725467682,47.4589996338],"type":"Point"}
}