{
  "type": "Feature",
  "properties": {
    "iso:country":"CH",
    "sg:address":"Sternmattstrasse 30",
    "sg:city":"Luzern",
    "sg:orig_category":"Arbeitnehmerverb\u00e4nde",
    "sg:phone":"+41 41 360 27 03",
    "sg:postcode":"6005",
    "sg:province":"Luzern",
    "wof:name":"Verband Kath.hausangestellten- Vereine D.schweiz Silvia Blum",
    "wof:placetype":"venue"
},
  "geometry": {"coordinates":[8.309993,47.039574],"type":"Point"}
}