{
  "type": "Feature",
  "properties": {
    "iso:country":"CH",
    "sg:address":"Les Grands-champs 162",
    "sg:city":"Rossemaison",
    "sg:orig_category":"Herstellung von k\u00e4lte U lufttechnischen Erzeugnissen f\u00fcr gewerbliche Zwecke Installation von Heizung",
    "sg:phone":"+41 32 423 27 27",
    "sg:postcode":"2842",
    "sg:province":"Jura",
    "wof:name":"Climagel Sa",
    "wof:placetype":"venue"
},
  "geometry": {"coordinates":[7.348567009,47.3451194763],"type":"Point"}
}