{
  "type": "Feature",
  "properties": {
    "iso:country":"CH",
    "sg:address":"Hofstrasse 50",
    "sg:city":"Rheineck",
    "sg:orig_category":"Detailhandel mit M\u00f6beln U Haushaltsgegenst\u00e4nden",
    "sg:postcode":"9424",
    "sg:province":"St. Gallen",
    "wof:name":"Soleil Office Ag",
    "wof:placetype":"venue"
},
  "geometry": {"coordinates":[9.5787277222,47.4626541138],"type":"Point"}
}