{
  "type": "Feature",
  "properties": {
    "iso:country":"CH",
    "sg:address":"Im Gr\u00fct 30",
    "sg:city":"Urdorf",
    "sg:orig_category":"Non-Classified Establishments",
    "sg:phone":"+41 17323131",
    "sg:postcode":"8902",
    "sg:province":"Z\u00fcrich",
    "wof:name":"Brechb\u00fchler Holding Ag",
    "wof:placetype":"venue"
},
  "geometry": {"coordinates":[8.4323654175,47.3876647949],"type":"Point"}
}