{
  "type": "Feature",
  "properties": {
    "iso:country":"CH",
    "sg:address":"Les Vuarines E 2",
    "sg:city":"Belfaux",
    "sg:orig_category":"Handelsvermittlung von Textilien, Bekleidung, Schuhen U Lederwaren",
    "sg:postcode":"1782",
    "sg:province":"Fribourg",
    "wof:name":"Galeuchet Hugues",
    "wof:placetype":"venue"
},
  "geometry": {"coordinates":[7.1063380241,46.8177261353],"type":"Point"}
}