{
  "type": "Feature",
  "properties": {
    "iso:country":"CH",
    "sg:address":"Dorfstrasse 6 9527 Niederhelfenschwil. Postfach",
    "sg:city":"Lenggenwil",
    "sg:orig_category":"Detailhandel mit Waren verschiedener Art, Hauptrichtung Nahrungsmittel",
    "sg:postcode":"9525",
    "sg:province":"St. Gallen",
    "wof:name":"Konsumgenossenschaft Lenggenwil, Kgl",
    "wof:placetype":"venue"
},
  "geometry": {"coordinates":[9.1862916946,47.4752502441],"type":"Point"}
}