{
  "type": "Feature",
  "properties": {
    "iso:country":"CH",
    "sg:address":"Starenstrasse 22",
    "sg:city":"Bottmingen",
    "sg:orig_category":"Gesundheitswesen",
    "sg:postcode":"4103",
    "sg:province":"Basel-Landschaft",
    "wof:name":"Ados Ag",
    "wof:placetype":"venue"
},
  "geometry": {"coordinates":[7.5699820518,47.5187110901],"type":"Point"}
}