{
  "type": "Feature",
  "properties": {
    "iso:country":"CH",
    "sg:address":"Rue De Surfr\u00e8te 3",
    "sg:city":"Martigny",
    "sg:orig_category":"Architekturb\u00fcros",
    "sg:phone":"+41 27 722 14 81",
    "sg:postcode":"1920",
    "sg:province":"Valais",
    "wof:name":"Fr\u00e9d\u00e9ric Fort Bureau D'architecture",
    "wof:placetype":"venue"
},
  "geometry": {"coordinates":[7.069499,46.094402],"type":"Point"}
}