{
  "type": "Feature",
  "properties": {
    "iso:country":"CH",
    "sg:address":"Avenue Louis-aubert 6",
    "sg:city":"Gen\u00e8ve",
    "sg:orig_category":"Detailhandel mit Waren verschiedener Art, Hauptrichtung Nahrungsmittel",
    "sg:phone":"+41 22 347 82 62",
    "sg:postcode":"1206",
    "sg:province":"Gen\u00e8ve",
    "wof:name":"Alimentation Au Bout-de-champel",
    "wof:placetype":"venue"
},
  "geometry": {"coordinates":[6.1589078903,46.1871109009],"type":"Point"}
}