{
  "type": "Feature",
  "properties": {
    "iso:country":"CH",
    "sg:address":"Haselstrasse 16 5400 Baden. Postfach",
    "sg:city":"Baden",
    "sg:orig_category":"Pensionskassen",
    "sg:postcode":"5400",
    "sg:province":"Aargau",
    "wof:name":"Stiftung T\u00f6di",
    "wof:placetype":"venue"
},
  "geometry": {"coordinates":[8.3056564331,47.4780158997],"type":"Point"}
}