{
  "type": "Feature",
  "properties": {
    "iso:country":"CH",
    "sg:address":"Ahornweg 7",
    "sg:city":"Neuenegg",
    "sg:orig_category":"Herstellung von keramischen Wand U Bodenfliesen U platten",
    "sg:phone":"+41 31 741 67 22",
    "sg:postcode":"3176",
    "sg:province":"Bern",
    "wof:name":"Zingg Anton, Keramische Wand Und Bodenbel\u00e4ge",
    "wof:placetype":"venue"
},
  "geometry": {"coordinates":[7.3100771904,46.8951454163],"type":"Point"}
}