{
  "type": "Feature",
  "properties": {
    "iso:country":"CH",
    "sg:address":"Greifenseestrasse 57",
    "sg:city":"Z\u00fcrich",
    "sg:orig_category":"Grosshandel mit chemischen Erzeugnissen Herstellung von Seifen, Wasch U Reinigungsmitteln",
    "sg:phone":"+41 13120880",
    "sg:postcode":"8050",
    "sg:province":"Z\u00fcrich",
    "wof:name":"Aesa A. Santi, Professionelle Reinigungs Und Desinfektionsprodukte,hygieneplanung",
    "wof:placetype":"venue"
},
  "geometry": {"coordinates":[8.5583610535,47.4089813232],"type":"Point"}
}