{
  "type": "Feature",
  "properties": {
    "iso:country":"CH",
    "sg:address":"B\u00f6lchenstrasse 13",
    "sg:city":"H\u00f6lstein",
    "sg:classifiers":[
        {
            "category":"Travel",
            "subcategory":"Hotels & Motels",
            "type":"Entertainment"
        }
    ],
    "sg:postcode":"4434",
    "sg:province":"Basel-Landschaft",
    "sg:tags":[
        "hotels",
        "mit",
        "restaurant"
    ],
    "wof:name":"Simone H\u00e4nle-kieffer",
    "wof:placetype":"venue"
},
  "geometry": {"coordinates":[7.7742371559,47.4213027954],"type":"Point"}
}