{
  "type": "Feature",
  "properties": {
    "iso:country":"CH",
    "sg:address":"Via Della Motta 18",
    "sg:city":"Locarno",
    "sg:orig_category":"Detailhandel mit Lederwaren U Reiseartikeln Detailhandel mit Schuhen U Lederwaren",
    "sg:phone":"+41 91 751 42 86",
    "sg:postcode":"6600",
    "sg:province":"Ticino",
    "wof:name":"Nemeth Stefan",
    "wof:placetype":"venue"
},
  "geometry": {"coordinates":[8.7932310104,46.1691741943],"type":"Point"}
}