{
  "type": "Feature",
  "properties": {
    "iso:country":"CH",
    "sg:address":"Mattackerstrasse 65",
    "sg:city":"Z\u00fcrich",
    "sg:orig_category":"Sanit\u00e4r U Heizungsinstallation Sanit\u00e4rinstallation",
    "sg:phone":"+41 13014639",
    "sg:postcode":"8052",
    "sg:province":"Z\u00fcrich",
    "wof:name":"Bosshard Richhard, Eidg. Dipl. Installateur. Sanit\u00e4r- U. Heizungsinstallationen.",
    "wof:placetype":"venue"
},
  "geometry": {"coordinates":[8.5529947281,47.4262161255],"type":"Point"}
}