{
  "type": "Feature",
  "properties": {
    "iso:country":"CH",
    "sg:address":"Route De Saint-georges 72",
    "sg:city":"Petit-lancy",
    "sg:orig_category":"Fussboden, Fliesen U Plattenlegerei, Tapeziererei Verlegen von Fliesen U Platten",
    "sg:postcode":"1213",
    "sg:province":"Gen\u00e8ve",
    "wof:name":"Erich V\u00f6geli",
    "wof:placetype":"venue"
},
  "geometry": {"coordinates":[7.5242948532,47.0199356079],"type":"Point"}
}