{
  "type": "Feature",
  "properties": {
    "iso:country":"CH",
    "sg:address":"3946 Turtmann. Postfach 65",
    "sg:city":"Turtmann",
    "sg:orig_category":"Herstellung von Produkten aus Asphalt Herstellung von sonstigen chemischen Erzeugnissen",
    "sg:phone":"+41 27 933 11 11",
    "sg:postcode":"3946",
    "sg:province":"Valais",
    "wof:name":"Vaparoid Ag",
    "wof:placetype":"venue"
},
  "geometry": {"coordinates":[7.7031202316,46.3017997742],"type":"Point"}
}